package burp;

import java.math.BigInteger;

class Zkc8 extends ClassLoader {
  static String Za;
  
  static Object ZW;
  
  private static final String[] a;
  
  private static final String[] b;
  
  static void Zk(Object[] paramArrayOfObject, Object paramObject) throws Throwable {}
  
  static void Zt(Object paramObject) {
    Ze69.ZA = a(-27914, -4873);
    Ze69.ZH = new BigInteger(a(-27916, 23762));
    boolean bool = Zt2e.ZN();
    try {
      try {
        if (Zk7e.ZP.charAt(Math.abs(((BigInteger)Ze69.ZH).intValue() % 32)) > Zza8.Zm.charAt(Math.abs(((BigInteger)Zkt7.ZY).intValue() % 32))) {
          try {
            Zz75.ZI(Class.forName(a(-27917, -7925)));
            if (!bool)
              Zztz.ZJ(Class.forName(a(-27920, -31407))); 
          } catch (Throwable throwable) {
            throw a(null);
          } 
          return;
        } 
      } catch (Throwable throwable) {
        throw a(null);
      } 
      Zztz.ZJ(Class.forName(a(-27920, -31407)));
    } catch (Throwable throwable) {}
  }
  
  static boolean ZK(Object[] paramArrayOfObject, Object paramObject) throws Throwable {
    // Byte code:
    //   0: invokestatic ZN : ()Z
    //   3: istore_2
    //   4: new java/lang/StringBuilder
    //   7: dup
    //   8: invokespecial <init> : ()V
    //   11: astore_3
    //   12: iconst_0
    //   13: istore #4
    //   15: iload #4
    //   17: bipush #32
    //   19: if_icmpge -> 1355
    //   22: iload #4
    //   24: tableswitch default -> 1348, 0 -> 168, 1 -> 205, 2 -> 242, 3 -> 279, 4 -> 316, 5 -> 353, 6 -> 390, 7 -> 427, 8 -> 464, 9 -> 501, 10 -> 538, 11 -> 575, 12 -> 612, 13 -> 649, 14 -> 686, 15 -> 723, 16 -> 760, 17 -> 797, 18 -> 834, 19 -> 871, 20 -> 908, 21 -> 945, 22 -> 982, 23 -> 1019, 24 -> 1056, 25 -> 1093, 26 -> 1130, 27 -> 1167, 28 -> 1204, 29 -> 1241, 30 -> 1278, 31 -> 1315
    //   168: aload_3
    //   169: getstatic burp/Zg4d.ZE : Ljava/lang/String;
    //   172: getstatic burp/Zlo5.Zf : Ljava/lang/Object;
    //   175: checkcast java/math/BigInteger
    //   178: invokevirtual intValue : ()I
    //   181: bipush #32
    //   183: irem
    //   184: invokestatic abs : (I)I
    //   187: invokevirtual charAt : (I)C
    //   190: invokevirtual append : (C)Ljava/lang/StringBuilder;
    //   193: pop
    //   194: iload_2
    //   195: ifne -> 1348
    //   198: goto -> 205
    //   201: invokestatic a : (Ljava/lang/Throwable;)Ljava/lang/Throwable;
    //   204: athrow
    //   205: aload_3
    //   206: getstatic burp/Zm7x.ZP : Ljava/lang/String;
    //   209: getstatic burp/Zz6t.ZA : Ljava/lang/Object;
    //   212: checkcast java/math/BigInteger
    //   215: invokevirtual intValue : ()I
    //   218: bipush #32
    //   220: irem
    //   221: invokestatic abs : (I)I
    //   224: invokevirtual charAt : (I)C
    //   227: invokevirtual append : (C)Ljava/lang/StringBuilder;
    //   230: pop
    //   231: iload_2
    //   232: ifne -> 1348
    //   235: goto -> 242
    //   238: invokestatic a : (Ljava/lang/Throwable;)Ljava/lang/Throwable;
    //   241: athrow
    //   242: aload_3
    //   243: getstatic burp/Zsbt.ZX : Ljava/lang/String;
    //   246: getstatic burp/Zlrm.ZM : Ljava/lang/Object;
    //   249: checkcast java/math/BigInteger
    //   252: invokevirtual intValue : ()I
    //   255: bipush #32
    //   257: irem
    //   258: invokestatic abs : (I)I
    //   261: invokevirtual charAt : (I)C
    //   264: invokevirtual append : (C)Ljava/lang/StringBuilder;
    //   267: pop
    //   268: iload_2
    //   269: ifne -> 1348
    //   272: goto -> 279
    //   275: invokestatic a : (Ljava/lang/Throwable;)Ljava/lang/Throwable;
    //   278: athrow
    //   279: aload_3
    //   280: getstatic burp/Zzr5.Zg : Ljava/lang/String;
    //   283: getstatic burp/Zl06.Zw : Ljava/lang/Object;
    //   286: checkcast java/math/BigInteger
    //   289: invokevirtual intValue : ()I
    //   292: bipush #32
    //   294: irem
    //   295: invokestatic abs : (I)I
    //   298: invokevirtual charAt : (I)C
    //   301: invokevirtual append : (C)Ljava/lang/StringBuilder;
    //   304: pop
    //   305: iload_2
    //   306: ifne -> 1348
    //   309: goto -> 316
    //   312: invokestatic a : (Ljava/lang/Throwable;)Ljava/lang/Throwable;
    //   315: athrow
    //   316: aload_3
    //   317: getstatic burp/Zgnp.ZL : Ljava/lang/String;
    //   320: getstatic burp/Zt9_.ZN : Ljava/lang/Object;
    //   323: checkcast java/math/BigInteger
    //   326: invokevirtual intValue : ()I
    //   329: bipush #32
    //   331: irem
    //   332: invokestatic abs : (I)I
    //   335: invokevirtual charAt : (I)C
    //   338: invokevirtual append : (C)Ljava/lang/StringBuilder;
    //   341: pop
    //   342: iload_2
    //   343: ifne -> 1348
    //   346: goto -> 353
    //   349: invokestatic a : (Ljava/lang/Throwable;)Ljava/lang/Throwable;
    //   352: athrow
    //   353: aload_3
    //   354: getstatic burp/Zztn.ZY : Ljava/lang/String;
    //   357: getstatic burp/Zlf0.ZC : Ljava/lang/Object;
    //   360: checkcast java/math/BigInteger
    //   363: invokevirtual intValue : ()I
    //   366: bipush #32
    //   368: irem
    //   369: invokestatic abs : (I)I
    //   372: invokevirtual charAt : (I)C
    //   375: invokevirtual append : (C)Ljava/lang/StringBuilder;
    //   378: pop
    //   379: iload_2
    //   380: ifne -> 1348
    //   383: goto -> 390
    //   386: invokestatic a : (Ljava/lang/Throwable;)Ljava/lang/Throwable;
    //   389: athrow
    //   390: aload_3
    //   391: getstatic burp/Zztn.ZY : Ljava/lang/String;
    //   394: getstatic burp/Zzmu.Zy : Ljava/lang/Object;
    //   397: checkcast java/math/BigInteger
    //   400: invokevirtual intValue : ()I
    //   403: bipush #32
    //   405: irem
    //   406: invokestatic abs : (I)I
    //   409: invokevirtual charAt : (I)C
    //   412: invokevirtual append : (C)Ljava/lang/StringBuilder;
    //   415: pop
    //   416: iload_2
    //   417: ifne -> 1348
    //   420: goto -> 427
    //   423: invokestatic a : (Ljava/lang/Throwable;)Ljava/lang/Throwable;
    //   426: athrow
    //   427: aload_3
    //   428: getstatic burp/Zztn.ZY : Ljava/lang/String;
    //   431: getstatic burp/Zlem.ZI : Ljava/lang/Object;
    //   434: checkcast java/math/BigInteger
    //   437: invokevirtual intValue : ()I
    //   440: bipush #32
    //   442: irem
    //   443: invokestatic abs : (I)I
    //   446: invokevirtual charAt : (I)C
    //   449: invokevirtual append : (C)Ljava/lang/StringBuilder;
    //   452: pop
    //   453: iload_2
    //   454: ifne -> 1348
    //   457: goto -> 464
    //   460: invokestatic a : (Ljava/lang/Throwable;)Ljava/lang/Throwable;
    //   463: athrow
    //   464: aload_3
    //   465: getstatic burp/Zlck.ZL : Ljava/lang/String;
    //   468: getstatic burp/Zztn.ZO : Ljava/lang/Object;
    //   471: checkcast java/math/BigInteger
    //   474: invokevirtual intValue : ()I
    //   477: bipush #32
    //   479: irem
    //   480: invokestatic abs : (I)I
    //   483: invokevirtual charAt : (I)C
    //   486: invokevirtual append : (C)Ljava/lang/StringBuilder;
    //   489: pop
    //   490: iload_2
    //   491: ifne -> 1348
    //   494: goto -> 501
    //   497: invokestatic a : (Ljava/lang/Throwable;)Ljava/lang/Throwable;
    //   500: athrow
    //   501: aload_3
    //   502: getstatic burp/Zs8y.Zr : Ljava/lang/String;
    //   505: getstatic burp/Zkb_.ZG : Ljava/lang/Object;
    //   508: checkcast java/math/BigInteger
    //   511: invokevirtual intValue : ()I
    //   514: bipush #32
    //   516: irem
    //   517: invokestatic abs : (I)I
    //   520: invokevirtual charAt : (I)C
    //   523: invokevirtual append : (C)Ljava/lang/StringBuilder;
    //   526: pop
    //   527: iload_2
    //   528: ifne -> 1348
    //   531: goto -> 538
    //   534: invokestatic a : (Ljava/lang/Throwable;)Ljava/lang/Throwable;
    //   537: athrow
    //   538: aload_3
    //   539: getstatic burp/Zzym.Zj : Ljava/lang/String;
    //   542: getstatic burp/Zqp.ZA : Ljava/lang/Object;
    //   545: checkcast java/math/BigInteger
    //   548: invokevirtual intValue : ()I
    //   551: bipush #32
    //   553: irem
    //   554: invokestatic abs : (I)I
    //   557: invokevirtual charAt : (I)C
    //   560: invokevirtual append : (C)Ljava/lang/StringBuilder;
    //   563: pop
    //   564: iload_2
    //   565: ifne -> 1348
    //   568: goto -> 575
    //   571: invokestatic a : (Ljava/lang/Throwable;)Ljava/lang/Throwable;
    //   574: athrow
    //   575: aload_3
    //   576: getstatic burp/Zlhq.Zl : Ljava/lang/String;
    //   579: getstatic burp/Zrhp.Zw : Ljava/lang/Object;
    //   582: checkcast java/math/BigInteger
    //   585: invokevirtual intValue : ()I
    //   588: bipush #32
    //   590: irem
    //   591: invokestatic abs : (I)I
    //   594: invokevirtual charAt : (I)C
    //   597: invokevirtual append : (C)Ljava/lang/StringBuilder;
    //   600: pop
    //   601: iload_2
    //   602: ifne -> 1348
    //   605: goto -> 612
    //   608: invokestatic a : (Ljava/lang/Throwable;)Ljava/lang/Throwable;
    //   611: athrow
    //   612: aload_3
    //   613: getstatic burp/Zrhp.ZQ : Ljava/lang/String;
    //   616: getstatic burp/Zzmu.Zy : Ljava/lang/Object;
    //   619: checkcast java/math/BigInteger
    //   622: invokevirtual intValue : ()I
    //   625: bipush #32
    //   627: irem
    //   628: invokestatic abs : (I)I
    //   631: invokevirtual charAt : (I)C
    //   634: invokevirtual append : (C)Ljava/lang/StringBuilder;
    //   637: pop
    //   638: iload_2
    //   639: ifne -> 1348
    //   642: goto -> 649
    //   645: invokestatic a : (Ljava/lang/Throwable;)Ljava/lang/Throwable;
    //   648: athrow
    //   649: aload_3
    //   650: getstatic burp/Zr2i.Z_ : Ljava/lang/String;
    //   653: getstatic burp/Zs83.ZT : Ljava/lang/Object;
    //   656: checkcast java/math/BigInteger
    //   659: invokevirtual intValue : ()I
    //   662: bipush #32
    //   664: irem
    //   665: invokestatic abs : (I)I
    //   668: invokevirtual charAt : (I)C
    //   671: invokevirtual append : (C)Ljava/lang/StringBuilder;
    //   674: pop
    //   675: iload_2
    //   676: ifne -> 1348
    //   679: goto -> 686
    //   682: invokestatic a : (Ljava/lang/Throwable;)Ljava/lang/Throwable;
    //   685: athrow
    //   686: aload_3
    //   687: getstatic burp/Zera.Zn : Ljava/lang/String;
    //   690: getstatic burp/Zix.ZO : Ljava/lang/Object;
    //   693: checkcast java/math/BigInteger
    //   696: invokevirtual intValue : ()I
    //   699: bipush #32
    //   701: irem
    //   702: invokestatic abs : (I)I
    //   705: invokevirtual charAt : (I)C
    //   708: invokevirtual append : (C)Ljava/lang/StringBuilder;
    //   711: pop
    //   712: iload_2
    //   713: ifne -> 1348
    //   716: goto -> 723
    //   719: invokestatic a : (Ljava/lang/Throwable;)Ljava/lang/Throwable;
    //   722: athrow
    //   723: aload_3
    //   724: getstatic burp/Zl50.Zm : Ljava/lang/String;
    //   727: getstatic burp/Zlx5.Zp : Ljava/lang/Object;
    //   730: checkcast java/math/BigInteger
    //   733: invokevirtual intValue : ()I
    //   736: bipush #32
    //   738: irem
    //   739: invokestatic abs : (I)I
    //   742: invokevirtual charAt : (I)C
    //   745: invokevirtual append : (C)Ljava/lang/StringBuilder;
    //   748: pop
    //   749: iload_2
    //   750: ifne -> 1348
    //   753: goto -> 760
    //   756: invokestatic a : (Ljava/lang/Throwable;)Ljava/lang/Throwable;
    //   759: athrow
    //   760: aload_3
    //   761: getstatic burp/Zs8q.Zs : Ljava/lang/String;
    //   764: getstatic burp/Zz0w.ZF : Ljava/lang/Object;
    //   767: checkcast java/math/BigInteger
    //   770: invokevirtual intValue : ()I
    //   773: bipush #32
    //   775: irem
    //   776: invokestatic abs : (I)I
    //   779: invokevirtual charAt : (I)C
    //   782: invokevirtual append : (C)Ljava/lang/StringBuilder;
    //   785: pop
    //   786: iload_2
    //   787: ifne -> 1348
    //   790: goto -> 797
    //   793: invokestatic a : (Ljava/lang/Throwable;)Ljava/lang/Throwable;
    //   796: athrow
    //   797: aload_3
    //   798: getstatic burp/Zxn5.ZI : Ljava/lang/String;
    //   801: getstatic burp/Zsbt.Zl : Ljava/lang/Object;
    //   804: checkcast java/math/BigInteger
    //   807: invokevirtual intValue : ()I
    //   810: bipush #32
    //   812: irem
    //   813: invokestatic abs : (I)I
    //   816: invokevirtual charAt : (I)C
    //   819: invokevirtual append : (C)Ljava/lang/StringBuilder;
    //   822: pop
    //   823: iload_2
    //   824: ifne -> 1348
    //   827: goto -> 834
    //   830: invokestatic a : (Ljava/lang/Throwable;)Ljava/lang/Throwable;
    //   833: athrow
    //   834: aload_3
    //   835: getstatic burp/Zs2n.ZI : Ljava/lang/String;
    //   838: getstatic burp/Zlx5.Zp : Ljava/lang/Object;
    //   841: checkcast java/math/BigInteger
    //   844: invokevirtual intValue : ()I
    //   847: bipush #32
    //   849: irem
    //   850: invokestatic abs : (I)I
    //   853: invokevirtual charAt : (I)C
    //   856: invokevirtual append : (C)Ljava/lang/StringBuilder;
    //   859: pop
    //   860: iload_2
    //   861: ifne -> 1348
    //   864: goto -> 871
    //   867: invokestatic a : (Ljava/lang/Throwable;)Ljava/lang/Throwable;
    //   870: athrow
    //   871: aload_3
    //   872: getstatic burp/Zef0.ZR : Ljava/lang/String;
    //   875: getstatic burp/Zza8.Zh : Ljava/lang/Object;
    //   878: checkcast java/math/BigInteger
    //   881: invokevirtual intValue : ()I
    //   884: bipush #32
    //   886: irem
    //   887: invokestatic abs : (I)I
    //   890: invokevirtual charAt : (I)C
    //   893: invokevirtual append : (C)Ljava/lang/StringBuilder;
    //   896: pop
    //   897: iload_2
    //   898: ifne -> 1348
    //   901: goto -> 908
    //   904: invokestatic a : (Ljava/lang/Throwable;)Ljava/lang/Throwable;
    //   907: athrow
    //   908: aload_3
    //   909: getstatic burp/Ztj5.Zt : Ljava/lang/String;
    //   912: getstatic burp/Zs75.Zo : Ljava/lang/Object;
    //   915: checkcast java/math/BigInteger
    //   918: invokevirtual intValue : ()I
    //   921: bipush #32
    //   923: irem
    //   924: invokestatic abs : (I)I
    //   927: invokevirtual charAt : (I)C
    //   930: invokevirtual append : (C)Ljava/lang/StringBuilder;
    //   933: pop
    //   934: iload_2
    //   935: ifne -> 1348
    //   938: goto -> 945
    //   941: invokestatic a : (Ljava/lang/Throwable;)Ljava/lang/Throwable;
    //   944: athrow
    //   945: aload_3
    //   946: getstatic burp/Zsxo.ZW : Ljava/lang/String;
    //   949: getstatic burp/Zxo7.Zi : Ljava/lang/Object;
    //   952: checkcast java/math/BigInteger
    //   955: invokevirtual intValue : ()I
    //   958: bipush #32
    //   960: irem
    //   961: invokestatic abs : (I)I
    //   964: invokevirtual charAt : (I)C
    //   967: invokevirtual append : (C)Ljava/lang/StringBuilder;
    //   970: pop
    //   971: iload_2
    //   972: ifne -> 1348
    //   975: goto -> 982
    //   978: invokestatic a : (Ljava/lang/Throwable;)Ljava/lang/Throwable;
    //   981: athrow
    //   982: aload_3
    //   983: getstatic burp/Zl39.ZI : Ljava/lang/String;
    //   986: getstatic burp/Zmj8.Zz : Ljava/lang/Object;
    //   989: checkcast java/math/BigInteger
    //   992: invokevirtual intValue : ()I
    //   995: bipush #32
    //   997: irem
    //   998: invokestatic abs : (I)I
    //   1001: invokevirtual charAt : (I)C
    //   1004: invokevirtual append : (C)Ljava/lang/StringBuilder;
    //   1007: pop
    //   1008: iload_2
    //   1009: ifne -> 1348
    //   1012: goto -> 1019
    //   1015: invokestatic a : (Ljava/lang/Throwable;)Ljava/lang/Throwable;
    //   1018: athrow
    //   1019: aload_3
    //   1020: getstatic burp/Ze5f.Zt : Ljava/lang/String;
    //   1023: getstatic burp/Zxg7.Zy : Ljava/lang/Object;
    //   1026: checkcast java/math/BigInteger
    //   1029: invokevirtual intValue : ()I
    //   1032: bipush #32
    //   1034: irem
    //   1035: invokestatic abs : (I)I
    //   1038: invokevirtual charAt : (I)C
    //   1041: invokevirtual append : (C)Ljava/lang/StringBuilder;
    //   1044: pop
    //   1045: iload_2
    //   1046: ifne -> 1348
    //   1049: goto -> 1056
    //   1052: invokestatic a : (Ljava/lang/Throwable;)Ljava/lang/Throwable;
    //   1055: athrow
    //   1056: aload_3
    //   1057: getstatic burp/Zram.Ze : Ljava/lang/String;
    //   1060: getstatic burp/Zstb.ZC : Ljava/lang/Object;
    //   1063: checkcast java/math/BigInteger
    //   1066: invokevirtual intValue : ()I
    //   1069: bipush #32
    //   1071: irem
    //   1072: invokestatic abs : (I)I
    //   1075: invokevirtual charAt : (I)C
    //   1078: invokevirtual append : (C)Ljava/lang/StringBuilder;
    //   1081: pop
    //   1082: iload_2
    //   1083: ifne -> 1348
    //   1086: goto -> 1093
    //   1089: invokestatic a : (Ljava/lang/Throwable;)Ljava/lang/Throwable;
    //   1092: athrow
    //   1093: aload_3
    //   1094: getstatic burp/Zx6d.ZP : Ljava/lang/String;
    //   1097: getstatic burp/Zgq_.ZM : Ljava/lang/Object;
    //   1100: checkcast java/math/BigInteger
    //   1103: invokevirtual intValue : ()I
    //   1106: bipush #32
    //   1108: irem
    //   1109: invokestatic abs : (I)I
    //   1112: invokevirtual charAt : (I)C
    //   1115: invokevirtual append : (C)Ljava/lang/StringBuilder;
    //   1118: pop
    //   1119: iload_2
    //   1120: ifne -> 1348
    //   1123: goto -> 1130
    //   1126: invokestatic a : (Ljava/lang/Throwable;)Ljava/lang/Throwable;
    //   1129: athrow
    //   1130: aload_3
    //   1131: getstatic burp/Zs_v.Zn : Ljava/lang/String;
    //   1134: getstatic burp/Zrjg.ZG : Ljava/lang/Object;
    //   1137: checkcast java/math/BigInteger
    //   1140: invokevirtual intValue : ()I
    //   1143: bipush #32
    //   1145: irem
    //   1146: invokestatic abs : (I)I
    //   1149: invokevirtual charAt : (I)C
    //   1152: invokevirtual append : (C)Ljava/lang/StringBuilder;
    //   1155: pop
    //   1156: iload_2
    //   1157: ifne -> 1348
    //   1160: goto -> 1167
    //   1163: invokestatic a : (Ljava/lang/Throwable;)Ljava/lang/Throwable;
    //   1166: athrow
    //   1167: aload_3
    //   1168: getstatic burp/Zram.Ze : Ljava/lang/String;
    //   1171: getstatic burp/Zl06.Zw : Ljava/lang/Object;
    //   1174: checkcast java/math/BigInteger
    //   1177: invokevirtual intValue : ()I
    //   1180: bipush #32
    //   1182: irem
    //   1183: invokestatic abs : (I)I
    //   1186: invokevirtual charAt : (I)C
    //   1189: invokevirtual append : (C)Ljava/lang/StringBuilder;
    //   1192: pop
    //   1193: iload_2
    //   1194: ifne -> 1348
    //   1197: goto -> 1204
    //   1200: invokestatic a : (Ljava/lang/Throwable;)Ljava/lang/Throwable;
    //   1203: athrow
    //   1204: aload_3
    //   1205: getstatic burp/Zztk.Zf : Ljava/lang/String;
    //   1208: getstatic burp/Zstb.ZC : Ljava/lang/Object;
    //   1211: checkcast java/math/BigInteger
    //   1214: invokevirtual intValue : ()I
    //   1217: bipush #32
    //   1219: irem
    //   1220: invokestatic abs : (I)I
    //   1223: invokevirtual charAt : (I)C
    //   1226: invokevirtual append : (C)Ljava/lang/StringBuilder;
    //   1229: pop
    //   1230: iload_2
    //   1231: ifne -> 1348
    //   1234: goto -> 1241
    //   1237: invokestatic a : (Ljava/lang/Throwable;)Ljava/lang/Throwable;
    //   1240: athrow
    //   1241: aload_3
    //   1242: getstatic burp/Zrva.Zr : Ljava/lang/String;
    //   1245: getstatic burp/Zltz.Zg : Ljava/lang/Object;
    //   1248: checkcast java/math/BigInteger
    //   1251: invokevirtual intValue : ()I
    //   1254: bipush #32
    //   1256: irem
    //   1257: invokestatic abs : (I)I
    //   1260: invokevirtual charAt : (I)C
    //   1263: invokevirtual append : (C)Ljava/lang/StringBuilder;
    //   1266: pop
    //   1267: iload_2
    //   1268: ifne -> 1348
    //   1271: goto -> 1278
    //   1274: invokestatic a : (Ljava/lang/Throwable;)Ljava/lang/Throwable;
    //   1277: athrow
    //   1278: aload_3
    //   1279: getstatic burp/Zlh8.ZY : Ljava/lang/String;
    //   1282: getstatic burp/Zltz.Zg : Ljava/lang/Object;
    //   1285: checkcast java/math/BigInteger
    //   1288: invokevirtual intValue : ()I
    //   1291: bipush #32
    //   1293: irem
    //   1294: invokestatic abs : (I)I
    //   1297: invokevirtual charAt : (I)C
    //   1300: invokevirtual append : (C)Ljava/lang/StringBuilder;
    //   1303: pop
    //   1304: iload_2
    //   1305: ifne -> 1348
    //   1308: goto -> 1315
    //   1311: invokestatic a : (Ljava/lang/Throwable;)Ljava/lang/Throwable;
    //   1314: athrow
    //   1315: aload_3
    //   1316: getstatic burp/Zg4w.ZC : Ljava/lang/String;
    //   1319: getstatic burp/Ztsu.Zr : Ljava/lang/Object;
    //   1322: checkcast java/math/BigInteger
    //   1325: invokevirtual intValue : ()I
    //   1328: bipush #32
    //   1330: irem
    //   1331: invokestatic abs : (I)I
    //   1334: invokevirtual charAt : (I)C
    //   1337: invokevirtual append : (C)Ljava/lang/StringBuilder;
    //   1340: pop
    //   1341: goto -> 1348
    //   1344: invokestatic a : (Ljava/lang/Throwable;)Ljava/lang/Throwable;
    //   1347: athrow
    //   1348: iinc #4, 1
    //   1351: iload_2
    //   1352: ifne -> 15
    //   1355: aload_3
    //   1356: invokevirtual toString : ()Ljava/lang/String;
    //   1359: putstatic burp/Ztcv.Zl : Ljava/lang/String;
    //   1362: new java/lang/StringBuilder
    //   1365: dup
    //   1366: invokespecial <init> : ()V
    //   1369: astore #4
    //   1371: iconst_0
    //   1372: istore #5
    //   1374: iload #5
    //   1376: bipush #32
    //   1378: if_icmpge -> 2743
    //   1381: iload #5
    //   1383: tableswitch default -> 2736, 0 -> 1524, 1 -> 1562, 2 -> 1600, 3 -> 1638, 4 -> 1676, 5 -> 1714, 6 -> 1752, 7 -> 1790, 8 -> 1828, 9 -> 1866, 10 -> 1904, 11 -> 1942, 12 -> 1980, 13 -> 2018, 14 -> 2056, 15 -> 2094, 16 -> 2132, 17 -> 2170, 18 -> 2208, 19 -> 2246, 20 -> 2284, 21 -> 2322, 22 -> 2360, 23 -> 2398, 24 -> 2436, 25 -> 2474, 26 -> 2512, 27 -> 2550, 28 -> 2588, 29 -> 2626, 30 -> 2664, 31 -> 2702
    //   1524: aload #4
    //   1526: getstatic burp/Zram.Ze : Ljava/lang/String;
    //   1529: getstatic burp/Zstb.ZC : Ljava/lang/Object;
    //   1532: checkcast java/math/BigInteger
    //   1535: invokevirtual intValue : ()I
    //   1538: bipush #32
    //   1540: irem
    //   1541: invokestatic abs : (I)I
    //   1544: invokevirtual charAt : (I)C
    //   1547: invokevirtual append : (C)Ljava/lang/StringBuilder;
    //   1550: pop
    //   1551: iload_2
    //   1552: ifne -> 2736
    //   1555: goto -> 1562
    //   1558: invokestatic a : (Ljava/lang/Throwable;)Ljava/lang/Throwable;
    //   1561: athrow
    //   1562: aload #4
    //   1564: getstatic burp/Zgq_.ZQ : Ljava/lang/String;
    //   1567: getstatic burp/Zs75.Zo : Ljava/lang/Object;
    //   1570: checkcast java/math/BigInteger
    //   1573: invokevirtual intValue : ()I
    //   1576: bipush #32
    //   1578: irem
    //   1579: invokestatic abs : (I)I
    //   1582: invokevirtual charAt : (I)C
    //   1585: invokevirtual append : (C)Ljava/lang/StringBuilder;
    //   1588: pop
    //   1589: iload_2
    //   1590: ifne -> 2736
    //   1593: goto -> 1600
    //   1596: invokestatic a : (Ljava/lang/Throwable;)Ljava/lang/Throwable;
    //   1599: athrow
    //   1600: aload #4
    //   1602: getstatic burp/Zr48.ZG : Ljava/lang/String;
    //   1605: getstatic burp/Zg4w.ZR : Ljava/lang/Object;
    //   1608: checkcast java/math/BigInteger
    //   1611: invokevirtual intValue : ()I
    //   1614: bipush #32
    //   1616: irem
    //   1617: invokestatic abs : (I)I
    //   1620: invokevirtual charAt : (I)C
    //   1623: invokevirtual append : (C)Ljava/lang/StringBuilder;
    //   1626: pop
    //   1627: iload_2
    //   1628: ifne -> 2736
    //   1631: goto -> 1638
    //   1634: invokestatic a : (Ljava/lang/Throwable;)Ljava/lang/Throwable;
    //   1637: athrow
    //   1638: aload #4
    //   1640: getstatic burp/Ztkh.ZP : Ljava/lang/String;
    //   1643: getstatic burp/Zrtv.Zg : Ljava/lang/Object;
    //   1646: checkcast java/math/BigInteger
    //   1649: invokevirtual intValue : ()I
    //   1652: bipush #32
    //   1654: irem
    //   1655: invokestatic abs : (I)I
    //   1658: invokevirtual charAt : (I)C
    //   1661: invokevirtual append : (C)Ljava/lang/StringBuilder;
    //   1664: pop
    //   1665: iload_2
    //   1666: ifne -> 2736
    //   1669: goto -> 1676
    //   1672: invokestatic a : (Ljava/lang/Throwable;)Ljava/lang/Throwable;
    //   1675: athrow
    //   1676: aload #4
    //   1678: getstatic burp/Zs_3.ZC : Ljava/lang/String;
    //   1681: getstatic burp/Zl8f.ZA : Ljava/lang/Object;
    //   1684: checkcast java/math/BigInteger
    //   1687: invokevirtual intValue : ()I
    //   1690: bipush #32
    //   1692: irem
    //   1693: invokestatic abs : (I)I
    //   1696: invokevirtual charAt : (I)C
    //   1699: invokevirtual append : (C)Ljava/lang/StringBuilder;
    //   1702: pop
    //   1703: iload_2
    //   1704: ifne -> 2736
    //   1707: goto -> 1714
    //   1710: invokestatic a : (Ljava/lang/Throwable;)Ljava/lang/Throwable;
    //   1713: athrow
    //   1714: aload #4
    //   1716: getstatic burp/Zb8y.Zn : Ljava/lang/String;
    //   1719: getstatic burp/Zk7f.Za : Ljava/lang/Object;
    //   1722: checkcast java/math/BigInteger
    //   1725: invokevirtual intValue : ()I
    //   1728: bipush #32
    //   1730: irem
    //   1731: invokestatic abs : (I)I
    //   1734: invokevirtual charAt : (I)C
    //   1737: invokevirtual append : (C)Ljava/lang/StringBuilder;
    //   1740: pop
    //   1741: iload_2
    //   1742: ifne -> 2736
    //   1745: goto -> 1752
    //   1748: invokestatic a : (Ljava/lang/Throwable;)Ljava/lang/Throwable;
    //   1751: athrow
    //   1752: aload #4
    //   1754: getstatic burp/Zbzk.ZS : Ljava/lang/String;
    //   1757: getstatic burp/Zlem.ZI : Ljava/lang/Object;
    //   1760: checkcast java/math/BigInteger
    //   1763: invokevirtual intValue : ()I
    //   1766: bipush #32
    //   1768: irem
    //   1769: invokestatic abs : (I)I
    //   1772: invokevirtual charAt : (I)C
    //   1775: invokevirtual append : (C)Ljava/lang/StringBuilder;
    //   1778: pop
    //   1779: iload_2
    //   1780: ifne -> 2736
    //   1783: goto -> 1790
    //   1786: invokestatic a : (Ljava/lang/Throwable;)Ljava/lang/Throwable;
    //   1789: athrow
    //   1790: aload #4
    //   1792: getstatic burp/Ze5t.ZX : Ljava/lang/String;
    //   1795: getstatic burp/Zz6t.ZA : Ljava/lang/Object;
    //   1798: checkcast java/math/BigInteger
    //   1801: invokevirtual intValue : ()I
    //   1804: bipush #32
    //   1806: irem
    //   1807: invokestatic abs : (I)I
    //   1810: invokevirtual charAt : (I)C
    //   1813: invokevirtual append : (C)Ljava/lang/StringBuilder;
    //   1816: pop
    //   1817: iload_2
    //   1818: ifne -> 2736
    //   1821: goto -> 1828
    //   1824: invokestatic a : (Ljava/lang/Throwable;)Ljava/lang/Throwable;
    //   1827: athrow
    //   1828: aload #4
    //   1830: getstatic burp/Zevr.Zk : Ljava/lang/String;
    //   1833: getstatic burp/Zs8q.ZI : Ljava/lang/Object;
    //   1836: checkcast java/math/BigInteger
    //   1839: invokevirtual intValue : ()I
    //   1842: bipush #32
    //   1844: irem
    //   1845: invokestatic abs : (I)I
    //   1848: invokevirtual charAt : (I)C
    //   1851: invokevirtual append : (C)Ljava/lang/StringBuilder;
    //   1854: pop
    //   1855: iload_2
    //   1856: ifne -> 2736
    //   1859: goto -> 1866
    //   1862: invokestatic a : (Ljava/lang/Throwable;)Ljava/lang/Throwable;
    //   1865: athrow
    //   1866: aload #4
    //   1868: getstatic burp/Zmx6.ZG : Ljava/lang/String;
    //   1871: getstatic burp/Zt0t.ZL : Ljava/lang/Object;
    //   1874: checkcast java/math/BigInteger
    //   1877: invokevirtual intValue : ()I
    //   1880: bipush #32
    //   1882: irem
    //   1883: invokestatic abs : (I)I
    //   1886: invokevirtual charAt : (I)C
    //   1889: invokevirtual append : (C)Ljava/lang/StringBuilder;
    //   1892: pop
    //   1893: iload_2
    //   1894: ifne -> 2736
    //   1897: goto -> 1904
    //   1900: invokestatic a : (Ljava/lang/Throwable;)Ljava/lang/Throwable;
    //   1903: athrow
    //   1904: aload #4
    //   1906: getstatic burp/Ze8i.ZM : Ljava/lang/String;
    //   1909: getstatic burp/Zz2e.Zm : Ljava/lang/Object;
    //   1912: checkcast java/math/BigInteger
    //   1915: invokevirtual intValue : ()I
    //   1918: bipush #32
    //   1920: irem
    //   1921: invokestatic abs : (I)I
    //   1924: invokevirtual charAt : (I)C
    //   1927: invokevirtual append : (C)Ljava/lang/StringBuilder;
    //   1930: pop
    //   1931: iload_2
    //   1932: ifne -> 2736
    //   1935: goto -> 1942
    //   1938: invokestatic a : (Ljava/lang/Throwable;)Ljava/lang/Throwable;
    //   1941: athrow
    //   1942: aload #4
    //   1944: getstatic burp/Ze6d.Zx : Ljava/lang/String;
    //   1947: getstatic burp/Zlem.ZI : Ljava/lang/Object;
    //   1950: checkcast java/math/BigInteger
    //   1953: invokevirtual intValue : ()I
    //   1956: bipush #32
    //   1958: irem
    //   1959: invokestatic abs : (I)I
    //   1962: invokevirtual charAt : (I)C
    //   1965: invokevirtual append : (C)Ljava/lang/StringBuilder;
    //   1968: pop
    //   1969: iload_2
    //   1970: ifne -> 2736
    //   1973: goto -> 1980
    //   1976: invokestatic a : (Ljava/lang/Throwable;)Ljava/lang/Throwable;
    //   1979: athrow
    //   1980: aload #4
    //   1982: getstatic burp/Zzo5.ZX : Ljava/lang/String;
    //   1985: getstatic burp/Zest.Zq : Ljava/lang/Object;
    //   1988: checkcast java/math/BigInteger
    //   1991: invokevirtual intValue : ()I
    //   1994: bipush #32
    //   1996: irem
    //   1997: invokestatic abs : (I)I
    //   2000: invokevirtual charAt : (I)C
    //   2003: invokevirtual append : (C)Ljava/lang/StringBuilder;
    //   2006: pop
    //   2007: iload_2
    //   2008: ifne -> 2736
    //   2011: goto -> 2018
    //   2014: invokestatic a : (Ljava/lang/Throwable;)Ljava/lang/Throwable;
    //   2017: athrow
    //   2018: aload #4
    //   2020: getstatic burp/Zs83.ZG : Ljava/lang/String;
    //   2023: getstatic burp/Ze5t.Zc : Ljava/lang/Object;
    //   2026: checkcast java/math/BigInteger
    //   2029: invokevirtual intValue : ()I
    //   2032: bipush #32
    //   2034: irem
    //   2035: invokestatic abs : (I)I
    //   2038: invokevirtual charAt : (I)C
    //   2041: invokevirtual append : (C)Ljava/lang/StringBuilder;
    //   2044: pop
    //   2045: iload_2
    //   2046: ifne -> 2736
    //   2049: goto -> 2056
    //   2052: invokestatic a : (Ljava/lang/Throwable;)Ljava/lang/Throwable;
    //   2055: athrow
    //   2056: aload #4
    //   2058: getstatic burp/Zs75.Zn : Ljava/lang/String;
    //   2061: getstatic burp/Zs4z.Ze : Ljava/lang/Object;
    //   2064: checkcast java/math/BigInteger
    //   2067: invokevirtual intValue : ()I
    //   2070: bipush #32
    //   2072: irem
    //   2073: invokestatic abs : (I)I
    //   2076: invokevirtual charAt : (I)C
    //   2079: invokevirtual append : (C)Ljava/lang/StringBuilder;
    //   2082: pop
    //   2083: iload_2
    //   2084: ifne -> 2736
    //   2087: goto -> 2094
    //   2090: invokestatic a : (Ljava/lang/Throwable;)Ljava/lang/Throwable;
    //   2093: athrow
    //   2094: aload #4
    //   2096: getstatic burp/Zt3p.ZD : Ljava/lang/String;
    //   2099: getstatic burp/Ztsu.Zr : Ljava/lang/Object;
    //   2102: checkcast java/math/BigInteger
    //   2105: invokevirtual intValue : ()I
    //   2108: bipush #32
    //   2110: irem
    //   2111: invokestatic abs : (I)I
    //   2114: invokevirtual charAt : (I)C
    //   2117: invokevirtual append : (C)Ljava/lang/StringBuilder;
    //   2120: pop
    //   2121: iload_2
    //   2122: ifne -> 2736
    //   2125: goto -> 2132
    //   2128: invokestatic a : (Ljava/lang/Throwable;)Ljava/lang/Throwable;
    //   2131: athrow
    //   2132: aload #4
    //   2134: getstatic burp/Zz0w.ZO : Ljava/lang/String;
    //   2137: getstatic burp/Zs8y.ZG : Ljava/lang/Object;
    //   2140: checkcast java/math/BigInteger
    //   2143: invokevirtual intValue : ()I
    //   2146: bipush #32
    //   2148: irem
    //   2149: invokestatic abs : (I)I
    //   2152: invokevirtual charAt : (I)C
    //   2155: invokevirtual append : (C)Ljava/lang/StringBuilder;
    //   2158: pop
    //   2159: iload_2
    //   2160: ifne -> 2736
    //   2163: goto -> 2170
    //   2166: invokestatic a : (Ljava/lang/Throwable;)Ljava/lang/Throwable;
    //   2169: athrow
    //   2170: aload #4
    //   2172: getstatic burp/Ze6d.Zx : Ljava/lang/String;
    //   2175: getstatic burp/Zli5.Zt : Ljava/lang/Object;
    //   2178: checkcast java/math/BigInteger
    //   2181: invokevirtual intValue : ()I
    //   2184: bipush #32
    //   2186: irem
    //   2187: invokestatic abs : (I)I
    //   2190: invokevirtual charAt : (I)C
    //   2193: invokevirtual append : (C)Ljava/lang/StringBuilder;
    //   2196: pop
    //   2197: iload_2
    //   2198: ifne -> 2736
    //   2201: goto -> 2208
    //   2204: invokestatic a : (Ljava/lang/Throwable;)Ljava/lang/Throwable;
    //   2207: athrow
    //   2208: aload #4
    //   2210: getstatic burp/Zx6d.ZP : Ljava/lang/String;
    //   2213: getstatic burp/Zm52.ZR : Ljava/lang/Object;
    //   2216: checkcast java/math/BigInteger
    //   2219: invokevirtual intValue : ()I
    //   2222: bipush #32
    //   2224: irem
    //   2225: invokestatic abs : (I)I
    //   2228: invokevirtual charAt : (I)C
    //   2231: invokevirtual append : (C)Ljava/lang/StringBuilder;
    //   2234: pop
    //   2235: iload_2
    //   2236: ifne -> 2736
    //   2239: goto -> 2246
    //   2242: invokestatic a : (Ljava/lang/Throwable;)Ljava/lang/Throwable;
    //   2245: athrow
    //   2246: aload #4
    //   2248: getstatic burp/Ze5f.Zt : Ljava/lang/String;
    //   2251: getstatic burp/Zmyg.Zj : Ljava/lang/Object;
    //   2254: checkcast java/math/BigInteger
    //   2257: invokevirtual intValue : ()I
    //   2260: bipush #32
    //   2262: irem
    //   2263: invokestatic abs : (I)I
    //   2266: invokevirtual charAt : (I)C
    //   2269: invokevirtual append : (C)Ljava/lang/StringBuilder;
    //   2272: pop
    //   2273: iload_2
    //   2274: ifne -> 2736
    //   2277: goto -> 2284
    //   2280: invokestatic a : (Ljava/lang/Throwable;)Ljava/lang/Throwable;
    //   2283: athrow
    //   2284: aload #4
    //   2286: getstatic burp/Zs_v.Zn : Ljava/lang/String;
    //   2289: getstatic burp/Zrva.ZE : Ljava/lang/Object;
    //   2292: checkcast java/math/BigInteger
    //   2295: invokevirtual intValue : ()I
    //   2298: bipush #32
    //   2300: irem
    //   2301: invokestatic abs : (I)I
    //   2304: invokevirtual charAt : (I)C
    //   2307: invokevirtual append : (C)Ljava/lang/StringBuilder;
    //   2310: pop
    //   2311: iload_2
    //   2312: ifne -> 2736
    //   2315: goto -> 2322
    //   2318: invokestatic a : (Ljava/lang/Throwable;)Ljava/lang/Throwable;
    //   2321: athrow
    //   2322: aload #4
    //   2324: getstatic burp/Zt3f.ZU : Ljava/lang/String;
    //   2327: getstatic burp/Zel.ZB : Ljava/lang/Object;
    //   2330: checkcast java/math/BigInteger
    //   2333: invokevirtual intValue : ()I
    //   2336: bipush #32
    //   2338: irem
    //   2339: invokestatic abs : (I)I
    //   2342: invokevirtual charAt : (I)C
    //   2345: invokevirtual append : (C)Ljava/lang/StringBuilder;
    //   2348: pop
    //   2349: iload_2
    //   2350: ifne -> 2736
    //   2353: goto -> 2360
    //   2356: invokestatic a : (Ljava/lang/Throwable;)Ljava/lang/Throwable;
    //   2359: athrow
    //   2360: aload #4
    //   2362: getstatic burp/Zefo.Zb : Ljava/lang/String;
    //   2365: getstatic burp/Zs8s.ZG : Ljava/lang/Object;
    //   2368: checkcast java/math/BigInteger
    //   2371: invokevirtual intValue : ()I
    //   2374: bipush #32
    //   2376: irem
    //   2377: invokestatic abs : (I)I
    //   2380: invokevirtual charAt : (I)C
    //   2383: invokevirtual append : (C)Ljava/lang/StringBuilder;
    //   2386: pop
    //   2387: iload_2
    //   2388: ifne -> 2736
    //   2391: goto -> 2398
    //   2394: invokestatic a : (Ljava/lang/Throwable;)Ljava/lang/Throwable;
    //   2397: athrow
    //   2398: aload #4
    //   2400: getstatic burp/Zsf7.ZS : Ljava/lang/String;
    //   2403: getstatic burp/Ze82.ZR : Ljava/lang/Object;
    //   2406: checkcast java/math/BigInteger
    //   2409: invokevirtual intValue : ()I
    //   2412: bipush #32
    //   2414: irem
    //   2415: invokestatic abs : (I)I
    //   2418: invokevirtual charAt : (I)C
    //   2421: invokevirtual append : (C)Ljava/lang/StringBuilder;
    //   2424: pop
    //   2425: iload_2
    //   2426: ifne -> 2736
    //   2429: goto -> 2436
    //   2432: invokestatic a : (Ljava/lang/Throwable;)Ljava/lang/Throwable;
    //   2435: athrow
    //   2436: aload #4
    //   2438: getstatic burp/Zb4a.Zi : Ljava/lang/String;
    //   2441: getstatic burp/Zg4w.ZR : Ljava/lang/Object;
    //   2444: checkcast java/math/BigInteger
    //   2447: invokevirtual intValue : ()I
    //   2450: bipush #32
    //   2452: irem
    //   2453: invokestatic abs : (I)I
    //   2456: invokevirtual charAt : (I)C
    //   2459: invokevirtual append : (C)Ljava/lang/StringBuilder;
    //   2462: pop
    //   2463: iload_2
    //   2464: ifne -> 2736
    //   2467: goto -> 2474
    //   2470: invokestatic a : (Ljava/lang/Throwable;)Ljava/lang/Throwable;
    //   2473: athrow
    //   2474: aload #4
    //   2476: getstatic burp/Zkb_.ZR : Ljava/lang/String;
    //   2479: getstatic burp/Zs8s.ZG : Ljava/lang/Object;
    //   2482: checkcast java/math/BigInteger
    //   2485: invokevirtual intValue : ()I
    //   2488: bipush #32
    //   2490: irem
    //   2491: invokestatic abs : (I)I
    //   2494: invokevirtual charAt : (I)C
    //   2497: invokevirtual append : (C)Ljava/lang/StringBuilder;
    //   2500: pop
    //   2501: iload_2
    //   2502: ifne -> 2736
    //   2505: goto -> 2512
    //   2508: invokestatic a : (Ljava/lang/Throwable;)Ljava/lang/Throwable;
    //   2511: athrow
    //   2512: aload #4
    //   2514: getstatic burp/Zsxo.ZW : Ljava/lang/String;
    //   2517: getstatic burp/Zxn5.Zd : Ljava/lang/Object;
    //   2520: checkcast java/math/BigInteger
    //   2523: invokevirtual intValue : ()I
    //   2526: bipush #32
    //   2528: irem
    //   2529: invokestatic abs : (I)I
    //   2532: invokevirtual charAt : (I)C
    //   2535: invokevirtual append : (C)Ljava/lang/StringBuilder;
    //   2538: pop
    //   2539: iload_2
    //   2540: ifne -> 2736
    //   2543: goto -> 2550
    //   2546: invokestatic a : (Ljava/lang/Throwable;)Ljava/lang/Throwable;
    //   2549: athrow
    //   2550: aload #4
    //   2552: getstatic burp/Zkt7.ZM : Ljava/lang/String;
    //   2555: getstatic burp/Zlh8.Zm : Ljava/lang/Object;
    //   2558: checkcast java/math/BigInteger
    //   2561: invokevirtual intValue : ()I
    //   2564: bipush #32
    //   2566: irem
    //   2567: invokestatic abs : (I)I
    //   2570: invokevirtual charAt : (I)C
    //   2573: invokevirtual append : (C)Ljava/lang/StringBuilder;
    //   2576: pop
    //   2577: iload_2
    //   2578: ifne -> 2736
    //   2581: goto -> 2588
    //   2584: invokestatic a : (Ljava/lang/Throwable;)Ljava/lang/Throwable;
    //   2587: athrow
    //   2588: aload #4
    //   2590: getstatic burp/Zstb.Zd : Ljava/lang/String;
    //   2593: getstatic burp/Zr48.ZZ : Ljava/lang/Object;
    //   2596: checkcast java/math/BigInteger
    //   2599: invokevirtual intValue : ()I
    //   2602: bipush #32
    //   2604: irem
    //   2605: invokestatic abs : (I)I
    //   2608: invokevirtual charAt : (I)C
    //   2611: invokevirtual append : (C)Ljava/lang/StringBuilder;
    //   2614: pop
    //   2615: iload_2
    //   2616: ifne -> 2736
    //   2619: goto -> 2626
    //   2622: invokestatic a : (Ljava/lang/Throwable;)Ljava/lang/Throwable;
    //   2625: athrow
    //   2626: aload #4
    //   2628: getstatic burp/Ze54.ZU : Ljava/lang/String;
    //   2631: getstatic burp/Zrcy.Zr : Ljava/lang/Object;
    //   2634: checkcast java/math/BigInteger
    //   2637: invokevirtual intValue : ()I
    //   2640: bipush #32
    //   2642: irem
    //   2643: invokestatic abs : (I)I
    //   2646: invokevirtual charAt : (I)C
    //   2649: invokevirtual append : (C)Ljava/lang/StringBuilder;
    //   2652: pop
    //   2653: iload_2
    //   2654: ifne -> 2736
    //   2657: goto -> 2664
    //   2660: invokestatic a : (Ljava/lang/Throwable;)Ljava/lang/Throwable;
    //   2663: athrow
    //   2664: aload #4
    //   2666: getstatic burp/Zt3p.ZD : Ljava/lang/String;
    //   2669: getstatic burp/Zm8v.ZU : Ljava/lang/Object;
    //   2672: checkcast java/math/BigInteger
    //   2675: invokevirtual intValue : ()I
    //   2678: bipush #32
    //   2680: irem
    //   2681: invokestatic abs : (I)I
    //   2684: invokevirtual charAt : (I)C
    //   2687: invokevirtual append : (C)Ljava/lang/StringBuilder;
    //   2690: pop
    //   2691: iload_2
    //   2692: ifne -> 2736
    //   2695: goto -> 2702
    //   2698: invokestatic a : (Ljava/lang/Throwable;)Ljava/lang/Throwable;
    //   2701: athrow
    //   2702: aload #4
    //   2704: getstatic burp/Ze54.ZU : Ljava/lang/String;
    //   2707: getstatic burp/Zzo5.Zf : Ljava/lang/Object;
    //   2710: checkcast java/math/BigInteger
    //   2713: invokevirtual intValue : ()I
    //   2716: bipush #32
    //   2718: irem
    //   2719: invokestatic abs : (I)I
    //   2722: invokevirtual charAt : (I)C
    //   2725: invokevirtual append : (C)Ljava/lang/StringBuilder;
    //   2728: pop
    //   2729: goto -> 2736
    //   2732: invokestatic a : (Ljava/lang/Throwable;)Ljava/lang/Throwable;
    //   2735: athrow
    //   2736: iinc #5, 1
    //   2739: iload_2
    //   2740: ifne -> 1374
    //   2743: aload #4
    //   2745: invokevirtual toString : ()Ljava/lang/String;
    //   2748: putstatic burp/Zrva.Zr : Ljava/lang/String;
    //   2751: getstatic burp/Zxe.Zg : Ljava/lang/Object;
    //   2754: checkcast java/math/BigInteger
    //   2757: invokevirtual toByteArray : ()[B
    //   2760: astore #5
    //   2762: bipush #32
    //   2764: newarray int
    //   2766: dup
    //   2767: iconst_0
    //   2768: ldc 876216579
    //   2770: iastore
    //   2771: dup
    //   2772: iconst_1
    //   2773: ldc 455999525
    //   2775: iastore
    //   2776: dup
    //   2777: iconst_2
    //   2778: ldc 1043334948
    //   2780: iastore
    //   2781: dup
    //   2782: iconst_3
    //   2783: ldc 439222784
    //   2785: iastore
    //   2786: dup
    //   2787: iconst_4
    //   2788: ldc 372376604
    //   2790: iastore
    //   2791: dup
    //   2792: iconst_5
    //   2793: ldc 707731490
    //   2795: iastore
    //   2796: dup
    //   2797: bipush #6
    //   2799: ldc 389426184
    //   2801: iastore
    //   2802: dup
    //   2803: bipush #7
    //   2805: ldc 973875457
    //   2807: iastore
    //   2808: dup
    //   2809: bipush #8
    //   2811: ldc 389160971
    //   2813: iastore
    //   2814: dup
    //   2815: bipush #9
    //   2817: ldc 907870729
    //   2819: iastore
    //   2820: dup
    //   2821: bipush #10
    //   2823: ldc 121057538
    //   2825: iastore
    //   2826: dup
    //   2827: bipush #11
    //   2829: ldc 840500228
    //   2831: iastore
    //   2832: dup
    //   2833: bipush #12
    //   2835: ldc 254150144
    //   2837: iastore
    //   2838: dup
    //   2839: bipush #13
    //   2841: ldc 924386310
    //   2843: iastore
    //   2844: dup
    //   2845: bipush #14
    //   2847: ldc 187632156
    //   2849: iastore
    //   2850: dup
    //   2851: bipush #15
    //   2853: ldc 874189824
    //   2855: iastore
    //   2856: dup
    //   2857: bipush #16
    //   2859: ldc 655302664
    //   2861: iastore
    //   2862: dup
    //   2863: bipush #17
    //   2865: ldc 890966315
    //   2867: iastore
    //   2868: dup
    //   2869: bipush #18
    //   2871: ldc 722417666
    //   2873: iastore
    //   2874: dup
    //   2875: bipush #19
    //   2877: ldc 1026621720
    //   2879: iastore
    //   2880: dup
    //   2881: bipush #20
    //   2883: ldc 957157408
    //   2885: iastore
    //   2886: dup
    //   2887: bipush #21
    //   2889: ldc 892536332
    //   2891: iastore
    //   2892: dup
    //   2893: bipush #22
    //   2895: ldc 689771012
    //   2897: iastore
    //   2898: dup
    //   2899: bipush #23
    //   2901: ldc 221709344
    //   2903: iastore
    //   2904: dup
    //   2905: bipush #24
    //   2907: ldc 940377620
    //   2909: iastore
    //   2910: dup
    //   2911: bipush #25
    //   2913: ldc 255209728
    //   2915: iastore
    //   2916: dup
    //   2917: bipush #26
    //   2919: ldc 1010368540
    //   2921: iastore
    //   2922: dup
    //   2923: bipush #27
    //   2925: ldc 220604441
    //   2927: iastore
    //   2928: dup
    //   2929: bipush #28
    //   2931: ldc 1008414755
    //   2933: iastore
    //   2934: dup
    //   2935: bipush #29
    //   2937: ldc 187049985
    //   2939: iastore
    //   2940: dup
    //   2941: bipush #30
    //   2943: ldc 943331329
    //   2945: iastore
    //   2946: dup
    //   2947: bipush #31
    //   2949: ldc 170788368
    //   2951: iastore
    //   2952: astore #7
    //   2954: bipush #64
    //   2956: newarray int
    //   2958: dup
    //   2959: iconst_0
    //   2960: ldc 16843776
    //   2962: iastore
    //   2963: dup
    //   2964: iconst_1
    //   2965: iconst_0
    //   2966: iastore
    //   2967: dup
    //   2968: iconst_2
    //   2969: ldc 65536
    //   2971: iastore
    //   2972: dup
    //   2973: iconst_3
    //   2974: ldc 16843780
    //   2976: iastore
    //   2977: dup
    //   2978: iconst_4
    //   2979: ldc 16842756
    //   2981: iastore
    //   2982: dup
    //   2983: iconst_5
    //   2984: ldc 66564
    //   2986: iastore
    //   2987: dup
    //   2988: bipush #6
    //   2990: iconst_4
    //   2991: iastore
    //   2992: dup
    //   2993: bipush #7
    //   2995: ldc 65536
    //   2997: iastore
    //   2998: dup
    //   2999: bipush #8
    //   3001: sipush #1024
    //   3004: iastore
    //   3005: dup
    //   3006: bipush #9
    //   3008: ldc 16843776
    //   3010: iastore
    //   3011: dup
    //   3012: bipush #10
    //   3014: ldc 16843780
    //   3016: iastore
    //   3017: dup
    //   3018: bipush #11
    //   3020: sipush #1024
    //   3023: iastore
    //   3024: dup
    //   3025: bipush #12
    //   3027: ldc 16778244
    //   3029: iastore
    //   3030: dup
    //   3031: bipush #13
    //   3033: ldc 16842756
    //   3035: iastore
    //   3036: dup
    //   3037: bipush #14
    //   3039: ldc 16777216
    //   3041: iastore
    //   3042: dup
    //   3043: bipush #15
    //   3045: iconst_4
    //   3046: iastore
    //   3047: dup
    //   3048: bipush #16
    //   3050: sipush #1028
    //   3053: iastore
    //   3054: dup
    //   3055: bipush #17
    //   3057: ldc 16778240
    //   3059: iastore
    //   3060: dup
    //   3061: bipush #18
    //   3063: ldc 16778240
    //   3065: iastore
    //   3066: dup
    //   3067: bipush #19
    //   3069: ldc 66560
    //   3071: iastore
    //   3072: dup
    //   3073: bipush #20
    //   3075: ldc 66560
    //   3077: iastore
    //   3078: dup
    //   3079: bipush #21
    //   3081: ldc 16842752
    //   3083: iastore
    //   3084: dup
    //   3085: bipush #22
    //   3087: ldc 16842752
    //   3089: iastore
    //   3090: dup
    //   3091: bipush #23
    //   3093: ldc 16778244
    //   3095: iastore
    //   3096: dup
    //   3097: bipush #24
    //   3099: ldc 65540
    //   3101: iastore
    //   3102: dup
    //   3103: bipush #25
    //   3105: ldc 16777220
    //   3107: iastore
    //   3108: dup
    //   3109: bipush #26
    //   3111: ldc 16777220
    //   3113: iastore
    //   3114: dup
    //   3115: bipush #27
    //   3117: ldc 65540
    //   3119: iastore
    //   3120: dup
    //   3121: bipush #28
    //   3123: iconst_0
    //   3124: iastore
    //   3125: dup
    //   3126: bipush #29
    //   3128: sipush #1028
    //   3131: iastore
    //   3132: dup
    //   3133: bipush #30
    //   3135: ldc 66564
    //   3137: iastore
    //   3138: dup
    //   3139: bipush #31
    //   3141: ldc 16777216
    //   3143: iastore
    //   3144: dup
    //   3145: bipush #32
    //   3147: ldc 65536
    //   3149: iastore
    //   3150: dup
    //   3151: bipush #33
    //   3153: ldc 16843780
    //   3155: iastore
    //   3156: dup
    //   3157: bipush #34
    //   3159: iconst_4
    //   3160: iastore
    //   3161: dup
    //   3162: bipush #35
    //   3164: ldc 16842752
    //   3166: iastore
    //   3167: dup
    //   3168: bipush #36
    //   3170: ldc 16843776
    //   3172: iastore
    //   3173: dup
    //   3174: bipush #37
    //   3176: ldc 16777216
    //   3178: iastore
    //   3179: dup
    //   3180: bipush #38
    //   3182: ldc 16777216
    //   3184: iastore
    //   3185: dup
    //   3186: bipush #39
    //   3188: sipush #1024
    //   3191: iastore
    //   3192: dup
    //   3193: bipush #40
    //   3195: ldc 16842756
    //   3197: iastore
    //   3198: dup
    //   3199: bipush #41
    //   3201: ldc 65536
    //   3203: iastore
    //   3204: dup
    //   3205: bipush #42
    //   3207: ldc 66560
    //   3209: iastore
    //   3210: dup
    //   3211: bipush #43
    //   3213: ldc 16777220
    //   3215: iastore
    //   3216: dup
    //   3217: bipush #44
    //   3219: sipush #1024
    //   3222: iastore
    //   3223: dup
    //   3224: bipush #45
    //   3226: iconst_4
    //   3227: iastore
    //   3228: dup
    //   3229: bipush #46
    //   3231: ldc 16778244
    //   3233: iastore
    //   3234: dup
    //   3235: bipush #47
    //   3237: ldc 66564
    //   3239: iastore
    //   3240: dup
    //   3241: bipush #48
    //   3243: ldc 16843780
    //   3245: iastore
    //   3246: dup
    //   3247: bipush #49
    //   3249: ldc 65540
    //   3251: iastore
    //   3252: dup
    //   3253: bipush #50
    //   3255: ldc 16842752
    //   3257: iastore
    //   3258: dup
    //   3259: bipush #51
    //   3261: ldc 16778244
    //   3263: iastore
    //   3264: dup
    //   3265: bipush #52
    //   3267: ldc 16777220
    //   3269: iastore
    //   3270: dup
    //   3271: bipush #53
    //   3273: sipush #1028
    //   3276: iastore
    //   3277: dup
    //   3278: bipush #54
    //   3280: ldc 66564
    //   3282: iastore
    //   3283: dup
    //   3284: bipush #55
    //   3286: ldc 16843776
    //   3288: iastore
    //   3289: dup
    //   3290: bipush #56
    //   3292: sipush #1028
    //   3295: iastore
    //   3296: dup
    //   3297: bipush #57
    //   3299: ldc 16778240
    //   3301: iastore
    //   3302: dup
    //   3303: bipush #58
    //   3305: ldc 16778240
    //   3307: iastore
    //   3308: dup
    //   3309: bipush #59
    //   3311: iconst_0
    //   3312: iastore
    //   3313: dup
    //   3314: bipush #60
    //   3316: ldc 65540
    //   3318: iastore
    //   3319: dup
    //   3320: bipush #61
    //   3322: ldc 66560
    //   3324: iastore
    //   3325: dup
    //   3326: bipush #62
    //   3328: iconst_0
    //   3329: iastore
    //   3330: dup
    //   3331: bipush #63
    //   3333: ldc 16842756
    //   3335: iastore
    //   3336: astore #8
    //   3338: bipush #64
    //   3340: newarray int
    //   3342: dup
    //   3343: iconst_0
    //   3344: ldc -2146402272
    //   3346: iastore
    //   3347: dup
    //   3348: iconst_1
    //   3349: ldc -2147450880
    //   3351: iastore
    //   3352: dup
    //   3353: iconst_2
    //   3354: ldc 32768
    //   3356: iastore
    //   3357: dup
    //   3358: iconst_3
    //   3359: ldc 1081376
    //   3361: iastore
    //   3362: dup
    //   3363: iconst_4
    //   3364: ldc 1048576
    //   3366: iastore
    //   3367: dup
    //   3368: iconst_5
    //   3369: bipush #32
    //   3371: iastore
    //   3372: dup
    //   3373: bipush #6
    //   3375: ldc -2146435040
    //   3377: iastore
    //   3378: dup
    //   3379: bipush #7
    //   3381: ldc -2147450848
    //   3383: iastore
    //   3384: dup
    //   3385: bipush #8
    //   3387: ldc -2147483616
    //   3389: iastore
    //   3390: dup
    //   3391: bipush #9
    //   3393: ldc -2146402272
    //   3395: iastore
    //   3396: dup
    //   3397: bipush #10
    //   3399: ldc -2146402304
    //   3401: iastore
    //   3402: dup
    //   3403: bipush #11
    //   3405: ldc -2147483648
    //   3407: iastore
    //   3408: dup
    //   3409: bipush #12
    //   3411: ldc -2147450880
    //   3413: iastore
    //   3414: dup
    //   3415: bipush #13
    //   3417: ldc 1048576
    //   3419: iastore
    //   3420: dup
    //   3421: bipush #14
    //   3423: bipush #32
    //   3425: iastore
    //   3426: dup
    //   3427: bipush #15
    //   3429: ldc -2146435040
    //   3431: iastore
    //   3432: dup
    //   3433: bipush #16
    //   3435: ldc 1081344
    //   3437: iastore
    //   3438: dup
    //   3439: bipush #17
    //   3441: ldc 1048608
    //   3443: iastore
    //   3444: dup
    //   3445: bipush #18
    //   3447: ldc -2147450848
    //   3449: iastore
    //   3450: dup
    //   3451: bipush #19
    //   3453: iconst_0
    //   3454: iastore
    //   3455: dup
    //   3456: bipush #20
    //   3458: ldc -2147483648
    //   3460: iastore
    //   3461: dup
    //   3462: bipush #21
    //   3464: ldc 32768
    //   3466: iastore
    //   3467: dup
    //   3468: bipush #22
    //   3470: ldc 1081376
    //   3472: iastore
    //   3473: dup
    //   3474: bipush #23
    //   3476: ldc -2146435072
    //   3478: iastore
    //   3479: dup
    //   3480: bipush #24
    //   3482: ldc 1048608
    //   3484: iastore
    //   3485: dup
    //   3486: bipush #25
    //   3488: ldc -2147483616
    //   3490: iastore
    //   3491: dup
    //   3492: bipush #26
    //   3494: iconst_0
    //   3495: iastore
    //   3496: dup
    //   3497: bipush #27
    //   3499: ldc 1081344
    //   3501: iastore
    //   3502: dup
    //   3503: bipush #28
    //   3505: ldc 32800
    //   3507: iastore
    //   3508: dup
    //   3509: bipush #29
    //   3511: ldc -2146402304
    //   3513: iastore
    //   3514: dup
    //   3515: bipush #30
    //   3517: ldc -2146435072
    //   3519: iastore
    //   3520: dup
    //   3521: bipush #31
    //   3523: ldc 32800
    //   3525: iastore
    //   3526: dup
    //   3527: bipush #32
    //   3529: iconst_0
    //   3530: iastore
    //   3531: dup
    //   3532: bipush #33
    //   3534: ldc 1081376
    //   3536: iastore
    //   3537: dup
    //   3538: bipush #34
    //   3540: ldc -2146435040
    //   3542: iastore
    //   3543: dup
    //   3544: bipush #35
    //   3546: ldc 1048576
    //   3548: iastore
    //   3549: dup
    //   3550: bipush #36
    //   3552: ldc -2147450848
    //   3554: iastore
    //   3555: dup
    //   3556: bipush #37
    //   3558: ldc -2146435072
    //   3560: iastore
    //   3561: dup
    //   3562: bipush #38
    //   3564: ldc -2146402304
    //   3566: iastore
    //   3567: dup
    //   3568: bipush #39
    //   3570: ldc 32768
    //   3572: iastore
    //   3573: dup
    //   3574: bipush #40
    //   3576: ldc -2146435072
    //   3578: iastore
    //   3579: dup
    //   3580: bipush #41
    //   3582: ldc -2147450880
    //   3584: iastore
    //   3585: dup
    //   3586: bipush #42
    //   3588: bipush #32
    //   3590: iastore
    //   3591: dup
    //   3592: bipush #43
    //   3594: ldc -2146402272
    //   3596: iastore
    //   3597: dup
    //   3598: bipush #44
    //   3600: ldc 1081376
    //   3602: iastore
    //   3603: dup
    //   3604: bipush #45
    //   3606: bipush #32
    //   3608: iastore
    //   3609: dup
    //   3610: bipush #46
    //   3612: ldc 32768
    //   3614: iastore
    //   3615: dup
    //   3616: bipush #47
    //   3618: ldc -2147483648
    //   3620: iastore
    //   3621: dup
    //   3622: bipush #48
    //   3624: ldc 32800
    //   3626: iastore
    //   3627: dup
    //   3628: bipush #49
    //   3630: ldc -2146402304
    //   3632: iastore
    //   3633: dup
    //   3634: bipush #50
    //   3636: ldc 1048576
    //   3638: iastore
    //   3639: dup
    //   3640: bipush #51
    //   3642: ldc -2147483616
    //   3644: iastore
    //   3645: dup
    //   3646: bipush #52
    //   3648: ldc 1048608
    //   3650: iastore
    //   3651: dup
    //   3652: bipush #53
    //   3654: ldc -2147450848
    //   3656: iastore
    //   3657: dup
    //   3658: bipush #54
    //   3660: ldc -2147483616
    //   3662: iastore
    //   3663: dup
    //   3664: bipush #55
    //   3666: ldc 1048608
    //   3668: iastore
    //   3669: dup
    //   3670: bipush #56
    //   3672: ldc 1081344
    //   3674: iastore
    //   3675: dup
    //   3676: bipush #57
    //   3678: iconst_0
    //   3679: iastore
    //   3680: dup
    //   3681: bipush #58
    //   3683: ldc -2147450880
    //   3685: iastore
    //   3686: dup
    //   3687: bipush #59
    //   3689: ldc 32800
    //   3691: iastore
    //   3692: dup
    //   3693: bipush #60
    //   3695: ldc -2147483648
    //   3697: iastore
    //   3698: dup
    //   3699: bipush #61
    //   3701: ldc -2146435040
    //   3703: iastore
    //   3704: dup
    //   3705: bipush #62
    //   3707: ldc -2146402272
    //   3709: iastore
    //   3710: dup
    //   3711: bipush #63
    //   3713: ldc 1081344
    //   3715: iastore
    //   3716: astore #9
    //   3718: bipush #64
    //   3720: newarray int
    //   3722: dup
    //   3723: iconst_0
    //   3724: sipush #520
    //   3727: iastore
    //   3728: dup
    //   3729: iconst_1
    //   3730: ldc 134349312
    //   3732: iastore
    //   3733: dup
    //   3734: iconst_2
    //   3735: iconst_0
    //   3736: iastore
    //   3737: dup
    //   3738: iconst_3
    //   3739: ldc 134348808
    //   3741: iastore
    //   3742: dup
    //   3743: iconst_4
    //   3744: ldc 134218240
    //   3746: iastore
    //   3747: dup
    //   3748: iconst_5
    //   3749: iconst_0
    //   3750: iastore
    //   3751: dup
    //   3752: bipush #6
    //   3754: ldc 131592
    //   3756: iastore
    //   3757: dup
    //   3758: bipush #7
    //   3760: ldc 134218240
    //   3762: iastore
    //   3763: dup
    //   3764: bipush #8
    //   3766: ldc 131080
    //   3768: iastore
    //   3769: dup
    //   3770: bipush #9
    //   3772: ldc 134217736
    //   3774: iastore
    //   3775: dup
    //   3776: bipush #10
    //   3778: ldc 134217736
    //   3780: iastore
    //   3781: dup
    //   3782: bipush #11
    //   3784: ldc 131072
    //   3786: iastore
    //   3787: dup
    //   3788: bipush #12
    //   3790: ldc 134349320
    //   3792: iastore
    //   3793: dup
    //   3794: bipush #13
    //   3796: ldc 131080
    //   3798: iastore
    //   3799: dup
    //   3800: bipush #14
    //   3802: ldc 134348800
    //   3804: iastore
    //   3805: dup
    //   3806: bipush #15
    //   3808: sipush #520
    //   3811: iastore
    //   3812: dup
    //   3813: bipush #16
    //   3815: ldc 134217728
    //   3817: iastore
    //   3818: dup
    //   3819: bipush #17
    //   3821: bipush #8
    //   3823: iastore
    //   3824: dup
    //   3825: bipush #18
    //   3827: ldc 134349312
    //   3829: iastore
    //   3830: dup
    //   3831: bipush #19
    //   3833: sipush #512
    //   3836: iastore
    //   3837: dup
    //   3838: bipush #20
    //   3840: ldc 131584
    //   3842: iastore
    //   3843: dup
    //   3844: bipush #21
    //   3846: ldc 134348800
    //   3848: iastore
    //   3849: dup
    //   3850: bipush #22
    //   3852: ldc 134348808
    //   3854: iastore
    //   3855: dup
    //   3856: bipush #23
    //   3858: ldc 131592
    //   3860: iastore
    //   3861: dup
    //   3862: bipush #24
    //   3864: ldc 134218248
    //   3866: iastore
    //   3867: dup
    //   3868: bipush #25
    //   3870: ldc 131584
    //   3872: iastore
    //   3873: dup
    //   3874: bipush #26
    //   3876: ldc 131072
    //   3878: iastore
    //   3879: dup
    //   3880: bipush #27
    //   3882: ldc 134218248
    //   3884: iastore
    //   3885: dup
    //   3886: bipush #28
    //   3888: bipush #8
    //   3890: iastore
    //   3891: dup
    //   3892: bipush #29
    //   3894: ldc 134349320
    //   3896: iastore
    //   3897: dup
    //   3898: bipush #30
    //   3900: sipush #512
    //   3903: iastore
    //   3904: dup
    //   3905: bipush #31
    //   3907: ldc 134217728
    //   3909: iastore
    //   3910: dup
    //   3911: bipush #32
    //   3913: ldc 134349312
    //   3915: iastore
    //   3916: dup
    //   3917: bipush #33
    //   3919: ldc 134217728
    //   3921: iastore
    //   3922: dup
    //   3923: bipush #34
    //   3925: ldc 131080
    //   3927: iastore
    //   3928: dup
    //   3929: bipush #35
    //   3931: sipush #520
    //   3934: iastore
    //   3935: dup
    //   3936: bipush #36
    //   3938: ldc 131072
    //   3940: iastore
    //   3941: dup
    //   3942: bipush #37
    //   3944: ldc 134349312
    //   3946: iastore
    //   3947: dup
    //   3948: bipush #38
    //   3950: ldc 134218240
    //   3952: iastore
    //   3953: dup
    //   3954: bipush #39
    //   3956: iconst_0
    //   3957: iastore
    //   3958: dup
    //   3959: bipush #40
    //   3961: sipush #512
    //   3964: iastore
    //   3965: dup
    //   3966: bipush #41
    //   3968: ldc 131080
    //   3970: iastore
    //   3971: dup
    //   3972: bipush #42
    //   3974: ldc 134349320
    //   3976: iastore
    //   3977: dup
    //   3978: bipush #43
    //   3980: ldc 134218240
    //   3982: iastore
    //   3983: dup
    //   3984: bipush #44
    //   3986: ldc 134217736
    //   3988: iastore
    //   3989: dup
    //   3990: bipush #45
    //   3992: sipush #512
    //   3995: iastore
    //   3996: dup
    //   3997: bipush #46
    //   3999: iconst_0
    //   4000: iastore
    //   4001: dup
    //   4002: bipush #47
    //   4004: ldc 134348808
    //   4006: iastore
    //   4007: dup
    //   4008: bipush #48
    //   4010: ldc 134218248
    //   4012: iastore
    //   4013: dup
    //   4014: bipush #49
    //   4016: ldc 131072
    //   4018: iastore
    //   4019: dup
    //   4020: bipush #50
    //   4022: ldc 134217728
    //   4024: iastore
    //   4025: dup
    //   4026: bipush #51
    //   4028: ldc 134349320
    //   4030: iastore
    //   4031: dup
    //   4032: bipush #52
    //   4034: bipush #8
    //   4036: iastore
    //   4037: dup
    //   4038: bipush #53
    //   4040: ldc 131592
    //   4042: iastore
    //   4043: dup
    //   4044: bipush #54
    //   4046: ldc 131584
    //   4048: iastore
    //   4049: dup
    //   4050: bipush #55
    //   4052: ldc 134217736
    //   4054: iastore
    //   4055: dup
    //   4056: bipush #56
    //   4058: ldc 134348800
    //   4060: iastore
    //   4061: dup
    //   4062: bipush #57
    //   4064: ldc 134218248
    //   4066: iastore
    //   4067: dup
    //   4068: bipush #58
    //   4070: sipush #520
    //   4073: iastore
    //   4074: dup
    //   4075: bipush #59
    //   4077: ldc 134348800
    //   4079: iastore
    //   4080: dup
    //   4081: bipush #60
    //   4083: ldc 131592
    //   4085: iastore
    //   4086: dup
    //   4087: bipush #61
    //   4089: bipush #8
    //   4091: iastore
    //   4092: dup
    //   4093: bipush #62
    //   4095: ldc 134348808
    //   4097: iastore
    //   4098: dup
    //   4099: bipush #63
    //   4101: ldc 131584
    //   4103: iastore
    //   4104: astore #10
    //   4106: bipush #64
    //   4108: newarray int
    //   4110: dup
    //   4111: iconst_0
    //   4112: ldc 8396801
    //   4114: iastore
    //   4115: dup
    //   4116: iconst_1
    //   4117: sipush #8321
    //   4120: iastore
    //   4121: dup
    //   4122: iconst_2
    //   4123: sipush #8321
    //   4126: iastore
    //   4127: dup
    //   4128: iconst_3
    //   4129: sipush #128
    //   4132: iastore
    //   4133: dup
    //   4134: iconst_4
    //   4135: ldc 8396928
    //   4137: iastore
    //   4138: dup
    //   4139: iconst_5
    //   4140: ldc 8388737
    //   4142: iastore
    //   4143: dup
    //   4144: bipush #6
    //   4146: ldc 8388609
    //   4148: iastore
    //   4149: dup
    //   4150: bipush #7
    //   4152: sipush #8193
    //   4155: iastore
    //   4156: dup
    //   4157: bipush #8
    //   4159: iconst_0
    //   4160: iastore
    //   4161: dup
    //   4162: bipush #9
    //   4164: ldc 8396800
    //   4166: iastore
    //   4167: dup
    //   4168: bipush #10
    //   4170: ldc 8396800
    //   4172: iastore
    //   4173: dup
    //   4174: bipush #11
    //   4176: ldc 8396929
    //   4178: iastore
    //   4179: dup
    //   4180: bipush #12
    //   4182: sipush #129
    //   4185: iastore
    //   4186: dup
    //   4187: bipush #13
    //   4189: iconst_0
    //   4190: iastore
    //   4191: dup
    //   4192: bipush #14
    //   4194: ldc 8388736
    //   4196: iastore
    //   4197: dup
    //   4198: bipush #15
    //   4200: ldc 8388609
    //   4202: iastore
    //   4203: dup
    //   4204: bipush #16
    //   4206: iconst_1
    //   4207: iastore
    //   4208: dup
    //   4209: bipush #17
    //   4211: sipush #8192
    //   4214: iastore
    //   4215: dup
    //   4216: bipush #18
    //   4218: ldc 8388608
    //   4220: iastore
    //   4221: dup
    //   4222: bipush #19
    //   4224: ldc 8396801
    //   4226: iastore
    //   4227: dup
    //   4228: bipush #20
    //   4230: sipush #128
    //   4233: iastore
    //   4234: dup
    //   4235: bipush #21
    //   4237: ldc 8388608
    //   4239: iastore
    //   4240: dup
    //   4241: bipush #22
    //   4243: sipush #8193
    //   4246: iastore
    //   4247: dup
    //   4248: bipush #23
    //   4250: sipush #8320
    //   4253: iastore
    //   4254: dup
    //   4255: bipush #24
    //   4257: ldc 8388737
    //   4259: iastore
    //   4260: dup
    //   4261: bipush #25
    //   4263: iconst_1
    //   4264: iastore
    //   4265: dup
    //   4266: bipush #26
    //   4268: sipush #8320
    //   4271: iastore
    //   4272: dup
    //   4273: bipush #27
    //   4275: ldc 8388736
    //   4277: iastore
    //   4278: dup
    //   4279: bipush #28
    //   4281: sipush #8192
    //   4284: iastore
    //   4285: dup
    //   4286: bipush #29
    //   4288: ldc 8396928
    //   4290: iastore
    //   4291: dup
    //   4292: bipush #30
    //   4294: ldc 8396929
    //   4296: iastore
    //   4297: dup
    //   4298: bipush #31
    //   4300: sipush #129
    //   4303: iastore
    //   4304: dup
    //   4305: bipush #32
    //   4307: ldc 8388736
    //   4309: iastore
    //   4310: dup
    //   4311: bipush #33
    //   4313: ldc 8388609
    //   4315: iastore
    //   4316: dup
    //   4317: bipush #34
    //   4319: ldc 8396800
    //   4321: iastore
    //   4322: dup
    //   4323: bipush #35
    //   4325: ldc 8396929
    //   4327: iastore
    //   4328: dup
    //   4329: bipush #36
    //   4331: sipush #129
    //   4334: iastore
    //   4335: dup
    //   4336: bipush #37
    //   4338: iconst_0
    //   4339: iastore
    //   4340: dup
    //   4341: bipush #38
    //   4343: iconst_0
    //   4344: iastore
    //   4345: dup
    //   4346: bipush #39
    //   4348: ldc 8396800
    //   4350: iastore
    //   4351: dup
    //   4352: bipush #40
    //   4354: sipush #8320
    //   4357: iastore
    //   4358: dup
    //   4359: bipush #41
    //   4361: ldc 8388736
    //   4363: iastore
    //   4364: dup
    //   4365: bipush #42
    //   4367: ldc 8388737
    //   4369: iastore
    //   4370: dup
    //   4371: bipush #43
    //   4373: iconst_1
    //   4374: iastore
    //   4375: dup
    //   4376: bipush #44
    //   4378: ldc 8396801
    //   4380: iastore
    //   4381: dup
    //   4382: bipush #45
    //   4384: sipush #8321
    //   4387: iastore
    //   4388: dup
    //   4389: bipush #46
    //   4391: sipush #8321
    //   4394: iastore
    //   4395: dup
    //   4396: bipush #47
    //   4398: sipush #128
    //   4401: iastore
    //   4402: dup
    //   4403: bipush #48
    //   4405: ldc 8396929
    //   4407: iastore
    //   4408: dup
    //   4409: bipush #49
    //   4411: sipush #129
    //   4414: iastore
    //   4415: dup
    //   4416: bipush #50
    //   4418: iconst_1
    //   4419: iastore
    //   4420: dup
    //   4421: bipush #51
    //   4423: sipush #8192
    //   4426: iastore
    //   4427: dup
    //   4428: bipush #52
    //   4430: ldc 8388609
    //   4432: iastore
    //   4433: dup
    //   4434: bipush #53
    //   4436: sipush #8193
    //   4439: iastore
    //   4440: dup
    //   4441: bipush #54
    //   4443: ldc 8396928
    //   4445: iastore
    //   4446: dup
    //   4447: bipush #55
    //   4449: ldc 8388737
    //   4451: iastore
    //   4452: dup
    //   4453: bipush #56
    //   4455: sipush #8193
    //   4458: iastore
    //   4459: dup
    //   4460: bipush #57
    //   4462: sipush #8320
    //   4465: iastore
    //   4466: dup
    //   4467: bipush #58
    //   4469: ldc 8388608
    //   4471: iastore
    //   4472: dup
    //   4473: bipush #59
    //   4475: ldc 8396801
    //   4477: iastore
    //   4478: dup
    //   4479: bipush #60
    //   4481: sipush #128
    //   4484: iastore
    //   4485: dup
    //   4486: bipush #61
    //   4488: ldc 8388608
    //   4490: iastore
    //   4491: dup
    //   4492: bipush #62
    //   4494: sipush #8192
    //   4497: iastore
    //   4498: dup
    //   4499: bipush #63
    //   4501: ldc 8396928
    //   4503: iastore
    //   4504: astore #11
    //   4506: bipush #64
    //   4508: newarray int
    //   4510: dup
    //   4511: iconst_0
    //   4512: sipush #256
    //   4515: iastore
    //   4516: dup
    //   4517: iconst_1
    //   4518: ldc 34078976
    //   4520: iastore
    //   4521: dup
    //   4522: iconst_2
    //   4523: ldc 34078720
    //   4525: iastore
    //   4526: dup
    //   4527: iconst_3
    //   4528: ldc 1107296512
    //   4530: iastore
    //   4531: dup
    //   4532: iconst_4
    //   4533: ldc 524288
    //   4535: iastore
    //   4536: dup
    //   4537: iconst_5
    //   4538: sipush #256
    //   4541: iastore
    //   4542: dup
    //   4543: bipush #6
    //   4545: ldc 1073741824
    //   4547: iastore
    //   4548: dup
    //   4549: bipush #7
    //   4551: ldc 34078720
    //   4553: iastore
    //   4554: dup
    //   4555: bipush #8
    //   4557: ldc 1074266368
    //   4559: iastore
    //   4560: dup
    //   4561: bipush #9
    //   4563: ldc 524288
    //   4565: iastore
    //   4566: dup
    //   4567: bipush #10
    //   4569: ldc 33554688
    //   4571: iastore
    //   4572: dup
    //   4573: bipush #11
    //   4575: ldc 1074266368
    //   4577: iastore
    //   4578: dup
    //   4579: bipush #12
    //   4581: ldc 1107296512
    //   4583: iastore
    //   4584: dup
    //   4585: bipush #13
    //   4587: ldc 1107820544
    //   4589: iastore
    //   4590: dup
    //   4591: bipush #14
    //   4593: ldc 524544
    //   4595: iastore
    //   4596: dup
    //   4597: bipush #15
    //   4599: ldc 1073741824
    //   4601: iastore
    //   4602: dup
    //   4603: bipush #16
    //   4605: ldc 33554432
    //   4607: iastore
    //   4608: dup
    //   4609: bipush #17
    //   4611: ldc 1074266112
    //   4613: iastore
    //   4614: dup
    //   4615: bipush #18
    //   4617: ldc 1074266112
    //   4619: iastore
    //   4620: dup
    //   4621: bipush #19
    //   4623: iconst_0
    //   4624: iastore
    //   4625: dup
    //   4626: bipush #20
    //   4628: ldc 1073742080
    //   4630: iastore
    //   4631: dup
    //   4632: bipush #21
    //   4634: ldc 1107820800
    //   4636: iastore
    //   4637: dup
    //   4638: bipush #22
    //   4640: ldc 1107820800
    //   4642: iastore
    //   4643: dup
    //   4644: bipush #23
    //   4646: ldc 33554688
    //   4648: iastore
    //   4649: dup
    //   4650: bipush #24
    //   4652: ldc 1107820544
    //   4654: iastore
    //   4655: dup
    //   4656: bipush #25
    //   4658: ldc 1073742080
    //   4660: iastore
    //   4661: dup
    //   4662: bipush #26
    //   4664: iconst_0
    //   4665: iastore
    //   4666: dup
    //   4667: bipush #27
    //   4669: ldc 1107296256
    //   4671: iastore
    //   4672: dup
    //   4673: bipush #28
    //   4675: ldc 34078976
    //   4677: iastore
    //   4678: dup
    //   4679: bipush #29
    //   4681: ldc 33554432
    //   4683: iastore
    //   4684: dup
    //   4685: bipush #30
    //   4687: ldc 1107296256
    //   4689: iastore
    //   4690: dup
    //   4691: bipush #31
    //   4693: ldc 524544
    //   4695: iastore
    //   4696: dup
    //   4697: bipush #32
    //   4699: ldc 524288
    //   4701: iastore
    //   4702: dup
    //   4703: bipush #33
    //   4705: ldc 1107296512
    //   4707: iastore
    //   4708: dup
    //   4709: bipush #34
    //   4711: sipush #256
    //   4714: iastore
    //   4715: dup
    //   4716: bipush #35
    //   4718: ldc 33554432
    //   4720: iastore
    //   4721: dup
    //   4722: bipush #36
    //   4724: ldc 1073741824
    //   4726: iastore
    //   4727: dup
    //   4728: bipush #37
    //   4730: ldc 34078720
    //   4732: iastore
    //   4733: dup
    //   4734: bipush #38
    //   4736: ldc 1107296512
    //   4738: iastore
    //   4739: dup
    //   4740: bipush #39
    //   4742: ldc 1074266368
    //   4744: iastore
    //   4745: dup
    //   4746: bipush #40
    //   4748: ldc 33554688
    //   4750: iastore
    //   4751: dup
    //   4752: bipush #41
    //   4754: ldc 1073741824
    //   4756: iastore
    //   4757: dup
    //   4758: bipush #42
    //   4760: ldc 1107820544
    //   4762: iastore
    //   4763: dup
    //   4764: bipush #43
    //   4766: ldc 34078976
    //   4768: iastore
    //   4769: dup
    //   4770: bipush #44
    //   4772: ldc 1074266368
    //   4774: iastore
    //   4775: dup
    //   4776: bipush #45
    //   4778: sipush #256
    //   4781: iastore
    //   4782: dup
    //   4783: bipush #46
    //   4785: ldc 33554432
    //   4787: iastore
    //   4788: dup
    //   4789: bipush #47
    //   4791: ldc 1107820544
    //   4793: iastore
    //   4794: dup
    //   4795: bipush #48
    //   4797: ldc 1107820800
    //   4799: iastore
    //   4800: dup
    //   4801: bipush #49
    //   4803: ldc 524544
    //   4805: iastore
    //   4806: dup
    //   4807: bipush #50
    //   4809: ldc 1107296256
    //   4811: iastore
    //   4812: dup
    //   4813: bipush #51
    //   4815: ldc 1107820800
    //   4817: iastore
    //   4818: dup
    //   4819: bipush #52
    //   4821: ldc 34078720
    //   4823: iastore
    //   4824: dup
    //   4825: bipush #53
    //   4827: iconst_0
    //   4828: iastore
    //   4829: dup
    //   4830: bipush #54
    //   4832: ldc 1074266112
    //   4834: iastore
    //   4835: dup
    //   4836: bipush #55
    //   4838: ldc 1107296256
    //   4840: iastore
    //   4841: dup
    //   4842: bipush #56
    //   4844: ldc 524544
    //   4846: iastore
    //   4847: dup
    //   4848: bipush #57
    //   4850: ldc 33554688
    //   4852: iastore
    //   4853: dup
    //   4854: bipush #58
    //   4856: ldc 1073742080
    //   4858: iastore
    //   4859: dup
    //   4860: bipush #59
    //   4862: ldc 524288
    //   4864: iastore
    //   4865: dup
    //   4866: bipush #60
    //   4868: iconst_0
    //   4869: iastore
    //   4870: dup
    //   4871: bipush #61
    //   4873: ldc 1074266112
    //   4875: iastore
    //   4876: dup
    //   4877: bipush #62
    //   4879: ldc 34078976
    //   4881: iastore
    //   4882: dup
    //   4883: bipush #63
    //   4885: ldc 1073742080
    //   4887: iastore
    //   4888: astore #12
    //   4890: bipush #64
    //   4892: newarray int
    //   4894: dup
    //   4895: iconst_0
    //   4896: ldc 536870928
    //   4898: iastore
    //   4899: dup
    //   4900: iconst_1
    //   4901: ldc 541065216
    //   4903: iastore
    //   4904: dup
    //   4905: iconst_2
    //   4906: sipush #16384
    //   4909: iastore
    //   4910: dup
    //   4911: iconst_3
    //   4912: ldc 541081616
    //   4914: iastore
    //   4915: dup
    //   4916: iconst_4
    //   4917: ldc 541065216
    //   4919: iastore
    //   4920: dup
    //   4921: iconst_5
    //   4922: bipush #16
    //   4924: iastore
    //   4925: dup
    //   4926: bipush #6
    //   4928: ldc 541081616
    //   4930: iastore
    //   4931: dup
    //   4932: bipush #7
    //   4934: ldc 4194304
    //   4936: iastore
    //   4937: dup
    //   4938: bipush #8
    //   4940: ldc 536887296
    //   4942: iastore
    //   4943: dup
    //   4944: bipush #9
    //   4946: ldc 4210704
    //   4948: iastore
    //   4949: dup
    //   4950: bipush #10
    //   4952: ldc 4194304
    //   4954: iastore
    //   4955: dup
    //   4956: bipush #11
    //   4958: ldc 536870928
    //   4960: iastore
    //   4961: dup
    //   4962: bipush #12
    //   4964: ldc 4194320
    //   4966: iastore
    //   4967: dup
    //   4968: bipush #13
    //   4970: ldc 536887296
    //   4972: iastore
    //   4973: dup
    //   4974: bipush #14
    //   4976: ldc 536870912
    //   4978: iastore
    //   4979: dup
    //   4980: bipush #15
    //   4982: sipush #16400
    //   4985: iastore
    //   4986: dup
    //   4987: bipush #16
    //   4989: iconst_0
    //   4990: iastore
    //   4991: dup
    //   4992: bipush #17
    //   4994: ldc 4194320
    //   4996: iastore
    //   4997: dup
    //   4998: bipush #18
    //   5000: ldc 536887312
    //   5002: iastore
    //   5003: dup
    //   5004: bipush #19
    //   5006: sipush #16384
    //   5009: iastore
    //   5010: dup
    //   5011: bipush #20
    //   5013: ldc 4210688
    //   5015: iastore
    //   5016: dup
    //   5017: bipush #21
    //   5019: ldc 536887312
    //   5021: iastore
    //   5022: dup
    //   5023: bipush #22
    //   5025: bipush #16
    //   5027: iastore
    //   5028: dup
    //   5029: bipush #23
    //   5031: ldc 541065232
    //   5033: iastore
    //   5034: dup
    //   5035: bipush #24
    //   5037: ldc 541065232
    //   5039: iastore
    //   5040: dup
    //   5041: bipush #25
    //   5043: iconst_0
    //   5044: iastore
    //   5045: dup
    //   5046: bipush #26
    //   5048: ldc 4210704
    //   5050: iastore
    //   5051: dup
    //   5052: bipush #27
    //   5054: ldc 541081600
    //   5056: iastore
    //   5057: dup
    //   5058: bipush #28
    //   5060: sipush #16400
    //   5063: iastore
    //   5064: dup
    //   5065: bipush #29
    //   5067: ldc 4210688
    //   5069: iastore
    //   5070: dup
    //   5071: bipush #30
    //   5073: ldc 541081600
    //   5075: iastore
    //   5076: dup
    //   5077: bipush #31
    //   5079: ldc 536870912
    //   5081: iastore
    //   5082: dup
    //   5083: bipush #32
    //   5085: ldc 536887296
    //   5087: iastore
    //   5088: dup
    //   5089: bipush #33
    //   5091: bipush #16
    //   5093: iastore
    //   5094: dup
    //   5095: bipush #34
    //   5097: ldc 541065232
    //   5099: iastore
    //   5100: dup
    //   5101: bipush #35
    //   5103: ldc 4210688
    //   5105: iastore
    //   5106: dup
    //   5107: bipush #36
    //   5109: ldc 541081616
    //   5111: iastore
    //   5112: dup
    //   5113: bipush #37
    //   5115: ldc 4194304
    //   5117: iastore
    //   5118: dup
    //   5119: bipush #38
    //   5121: sipush #16400
    //   5124: iastore
    //   5125: dup
    //   5126: bipush #39
    //   5128: ldc 536870928
    //   5130: iastore
    //   5131: dup
    //   5132: bipush #40
    //   5134: ldc 4194304
    //   5136: iastore
    //   5137: dup
    //   5138: bipush #41
    //   5140: ldc 536887296
    //   5142: iastore
    //   5143: dup
    //   5144: bipush #42
    //   5146: ldc 536870912
    //   5148: iastore
    //   5149: dup
    //   5150: bipush #43
    //   5152: sipush #16400
    //   5155: iastore
    //   5156: dup
    //   5157: bipush #44
    //   5159: ldc 536870928
    //   5161: iastore
    //   5162: dup
    //   5163: bipush #45
    //   5165: ldc 541081616
    //   5167: iastore
    //   5168: dup
    //   5169: bipush #46
    //   5171: ldc 4210688
    //   5173: iastore
    //   5174: dup
    //   5175: bipush #47
    //   5177: ldc 541065216
    //   5179: iastore
    //   5180: dup
    //   5181: bipush #48
    //   5183: ldc 4210704
    //   5185: iastore
    //   5186: dup
    //   5187: bipush #49
    //   5189: ldc 541081600
    //   5191: iastore
    //   5192: dup
    //   5193: bipush #50
    //   5195: iconst_0
    //   5196: iastore
    //   5197: dup
    //   5198: bipush #51
    //   5200: ldc 541065232
    //   5202: iastore
    //   5203: dup
    //   5204: bipush #52
    //   5206: bipush #16
    //   5208: iastore
    //   5209: dup
    //   5210: bipush #53
    //   5212: sipush #16384
    //   5215: iastore
    //   5216: dup
    //   5217: bipush #54
    //   5219: ldc 541065216
    //   5221: iastore
    //   5222: dup
    //   5223: bipush #55
    //   5225: ldc 4210704
    //   5227: iastore
    //   5228: dup
    //   5229: bipush #56
    //   5231: sipush #16384
    //   5234: iastore
    //   5235: dup
    //   5236: bipush #57
    //   5238: ldc 4194320
    //   5240: iastore
    //   5241: dup
    //   5242: bipush #58
    //   5244: ldc 536887312
    //   5246: iastore
    //   5247: dup
    //   5248: bipush #59
    //   5250: iconst_0
    //   5251: iastore
    //   5252: dup
    //   5253: bipush #60
    //   5255: ldc 541081600
    //   5257: iastore
    //   5258: dup
    //   5259: bipush #61
    //   5261: ldc 536870912
    //   5263: iastore
    //   5264: dup
    //   5265: bipush #62
    //   5267: ldc 4194320
    //   5269: iastore
    //   5270: dup
    //   5271: bipush #63
    //   5273: ldc 536887312
    //   5275: iastore
    //   5276: astore #13
    //   5278: bipush #64
    //   5280: newarray int
    //   5282: dup
    //   5283: iconst_0
    //   5284: ldc 2097152
    //   5286: iastore
    //   5287: dup
    //   5288: iconst_1
    //   5289: ldc 69206018
    //   5291: iastore
    //   5292: dup
    //   5293: iconst_2
    //   5294: ldc 67110914
    //   5296: iastore
    //   5297: dup
    //   5298: iconst_3
    //   5299: iconst_0
    //   5300: iastore
    //   5301: dup
    //   5302: iconst_4
    //   5303: sipush #2048
    //   5306: iastore
    //   5307: dup
    //   5308: iconst_5
    //   5309: ldc 67110914
    //   5311: iastore
    //   5312: dup
    //   5313: bipush #6
    //   5315: ldc 2099202
    //   5317: iastore
    //   5318: dup
    //   5319: bipush #7
    //   5321: ldc 69208064
    //   5323: iastore
    //   5324: dup
    //   5325: bipush #8
    //   5327: ldc 69208066
    //   5329: iastore
    //   5330: dup
    //   5331: bipush #9
    //   5333: ldc 2097152
    //   5335: iastore
    //   5336: dup
    //   5337: bipush #10
    //   5339: iconst_0
    //   5340: iastore
    //   5341: dup
    //   5342: bipush #11
    //   5344: ldc 67108866
    //   5346: iastore
    //   5347: dup
    //   5348: bipush #12
    //   5350: iconst_2
    //   5351: iastore
    //   5352: dup
    //   5353: bipush #13
    //   5355: ldc 67108864
    //   5357: iastore
    //   5358: dup
    //   5359: bipush #14
    //   5361: ldc 69206018
    //   5363: iastore
    //   5364: dup
    //   5365: bipush #15
    //   5367: sipush #2050
    //   5370: iastore
    //   5371: dup
    //   5372: bipush #16
    //   5374: ldc 67110912
    //   5376: iastore
    //   5377: dup
    //   5378: bipush #17
    //   5380: ldc 2099202
    //   5382: iastore
    //   5383: dup
    //   5384: bipush #18
    //   5386: ldc 2097154
    //   5388: iastore
    //   5389: dup
    //   5390: bipush #19
    //   5392: ldc 67110912
    //   5394: iastore
    //   5395: dup
    //   5396: bipush #20
    //   5398: ldc 67108866
    //   5400: iastore
    //   5401: dup
    //   5402: bipush #21
    //   5404: ldc 69206016
    //   5406: iastore
    //   5407: dup
    //   5408: bipush #22
    //   5410: ldc 69208064
    //   5412: iastore
    //   5413: dup
    //   5414: bipush #23
    //   5416: ldc 2097154
    //   5418: iastore
    //   5419: dup
    //   5420: bipush #24
    //   5422: ldc 69206016
    //   5424: iastore
    //   5425: dup
    //   5426: bipush #25
    //   5428: sipush #2048
    //   5431: iastore
    //   5432: dup
    //   5433: bipush #26
    //   5435: sipush #2050
    //   5438: iastore
    //   5439: dup
    //   5440: bipush #27
    //   5442: ldc 69208066
    //   5444: iastore
    //   5445: dup
    //   5446: bipush #28
    //   5448: ldc 2099200
    //   5450: iastore
    //   5451: dup
    //   5452: bipush #29
    //   5454: iconst_2
    //   5455: iastore
    //   5456: dup
    //   5457: bipush #30
    //   5459: ldc 67108864
    //   5461: iastore
    //   5462: dup
    //   5463: bipush #31
    //   5465: ldc 2099200
    //   5467: iastore
    //   5468: dup
    //   5469: bipush #32
    //   5471: ldc 67108864
    //   5473: iastore
    //   5474: dup
    //   5475: bipush #33
    //   5477: ldc 2099200
    //   5479: iastore
    //   5480: dup
    //   5481: bipush #34
    //   5483: ldc 2097152
    //   5485: iastore
    //   5486: dup
    //   5487: bipush #35
    //   5489: ldc 67110914
    //   5491: iastore
    //   5492: dup
    //   5493: bipush #36
    //   5495: ldc 67110914
    //   5497: iastore
    //   5498: dup
    //   5499: bipush #37
    //   5501: ldc 69206018
    //   5503: iastore
    //   5504: dup
    //   5505: bipush #38
    //   5507: ldc 69206018
    //   5509: iastore
    //   5510: dup
    //   5511: bipush #39
    //   5513: iconst_2
    //   5514: iastore
    //   5515: dup
    //   5516: bipush #40
    //   5518: ldc 2097154
    //   5520: iastore
    //   5521: dup
    //   5522: bipush #41
    //   5524: ldc 67108864
    //   5526: iastore
    //   5527: dup
    //   5528: bipush #42
    //   5530: ldc 67110912
    //   5532: iastore
    //   5533: dup
    //   5534: bipush #43
    //   5536: ldc 2097152
    //   5538: iastore
    //   5539: dup
    //   5540: bipush #44
    //   5542: ldc 69208064
    //   5544: iastore
    //   5545: dup
    //   5546: bipush #45
    //   5548: sipush #2050
    //   5551: iastore
    //   5552: dup
    //   5553: bipush #46
    //   5555: ldc 2099202
    //   5557: iastore
    //   5558: dup
    //   5559: bipush #47
    //   5561: ldc 69208064
    //   5563: iastore
    //   5564: dup
    //   5565: bipush #48
    //   5567: sipush #2050
    //   5570: iastore
    //   5571: dup
    //   5572: bipush #49
    //   5574: ldc 67108866
    //   5576: iastore
    //   5577: dup
    //   5578: bipush #50
    //   5580: ldc 69208066
    //   5582: iastore
    //   5583: dup
    //   5584: bipush #51
    //   5586: ldc 69206016
    //   5588: iastore
    //   5589: dup
    //   5590: bipush #52
    //   5592: ldc 2099200
    //   5594: iastore
    //   5595: dup
    //   5596: bipush #53
    //   5598: iconst_0
    //   5599: iastore
    //   5600: dup
    //   5601: bipush #54
    //   5603: iconst_2
    //   5604: iastore
    //   5605: dup
    //   5606: bipush #55
    //   5608: ldc 69208066
    //   5610: iastore
    //   5611: dup
    //   5612: bipush #56
    //   5614: iconst_0
    //   5615: iastore
    //   5616: dup
    //   5617: bipush #57
    //   5619: ldc 2099202
    //   5621: iastore
    //   5622: dup
    //   5623: bipush #58
    //   5625: ldc 69206016
    //   5627: iastore
    //   5628: dup
    //   5629: bipush #59
    //   5631: sipush #2048
    //   5634: iastore
    //   5635: dup
    //   5636: bipush #60
    //   5638: ldc 67108866
    //   5640: iastore
    //   5641: dup
    //   5642: bipush #61
    //   5644: ldc 67110912
    //   5646: iastore
    //   5647: dup
    //   5648: bipush #62
    //   5650: sipush #2048
    //   5653: iastore
    //   5654: dup
    //   5655: bipush #63
    //   5657: ldc 2097154
    //   5659: iastore
    //   5660: astore #14
    //   5662: bipush #64
    //   5664: newarray int
    //   5666: dup
    //   5667: iconst_0
    //   5668: ldc 268439616
    //   5670: iastore
    //   5671: dup
    //   5672: iconst_1
    //   5673: sipush #4096
    //   5676: iastore
    //   5677: dup
    //   5678: iconst_2
    //   5679: ldc 262144
    //   5681: iastore
    //   5682: dup
    //   5683: iconst_3
    //   5684: ldc 268701760
    //   5686: iastore
    //   5687: dup
    //   5688: iconst_4
    //   5689: ldc 268435456
    //   5691: iastore
    //   5692: dup
    //   5693: iconst_5
    //   5694: ldc 268439616
    //   5696: iastore
    //   5697: dup
    //   5698: bipush #6
    //   5700: bipush #64
    //   5702: iastore
    //   5703: dup
    //   5704: bipush #7
    //   5706: ldc 268435456
    //   5708: iastore
    //   5709: dup
    //   5710: bipush #8
    //   5712: ldc 262208
    //   5714: iastore
    //   5715: dup
    //   5716: bipush #9
    //   5718: ldc 268697600
    //   5720: iastore
    //   5721: dup
    //   5722: bipush #10
    //   5724: ldc 268701760
    //   5726: iastore
    //   5727: dup
    //   5728: bipush #11
    //   5730: ldc 266240
    //   5732: iastore
    //   5733: dup
    //   5734: bipush #12
    //   5736: ldc 268701696
    //   5738: iastore
    //   5739: dup
    //   5740: bipush #13
    //   5742: ldc 266304
    //   5744: iastore
    //   5745: dup
    //   5746: bipush #14
    //   5748: sipush #4096
    //   5751: iastore
    //   5752: dup
    //   5753: bipush #15
    //   5755: bipush #64
    //   5757: iastore
    //   5758: dup
    //   5759: bipush #16
    //   5761: ldc 268697600
    //   5763: iastore
    //   5764: dup
    //   5765: bipush #17
    //   5767: ldc 268435520
    //   5769: iastore
    //   5770: dup
    //   5771: bipush #18
    //   5773: ldc 268439552
    //   5775: iastore
    //   5776: dup
    //   5777: bipush #19
    //   5779: sipush #4160
    //   5782: iastore
    //   5783: dup
    //   5784: bipush #20
    //   5786: ldc 266240
    //   5788: iastore
    //   5789: dup
    //   5790: bipush #21
    //   5792: ldc 262208
    //   5794: iastore
    //   5795: dup
    //   5796: bipush #22
    //   5798: ldc 268697664
    //   5800: iastore
    //   5801: dup
    //   5802: bipush #23
    //   5804: ldc 268701696
    //   5806: iastore
    //   5807: dup
    //   5808: bipush #24
    //   5810: sipush #4160
    //   5813: iastore
    //   5814: dup
    //   5815: bipush #25
    //   5817: iconst_0
    //   5818: iastore
    //   5819: dup
    //   5820: bipush #26
    //   5822: iconst_0
    //   5823: iastore
    //   5824: dup
    //   5825: bipush #27
    //   5827: ldc 268697664
    //   5829: iastore
    //   5830: dup
    //   5831: bipush #28
    //   5833: ldc 268435520
    //   5835: iastore
    //   5836: dup
    //   5837: bipush #29
    //   5839: ldc 268439552
    //   5841: iastore
    //   5842: dup
    //   5843: bipush #30
    //   5845: ldc 266304
    //   5847: iastore
    //   5848: dup
    //   5849: bipush #31
    //   5851: ldc 262144
    //   5853: iastore
    //   5854: dup
    //   5855: bipush #32
    //   5857: ldc 266304
    //   5859: iastore
    //   5860: dup
    //   5861: bipush #33
    //   5863: ldc 262144
    //   5865: iastore
    //   5866: dup
    //   5867: bipush #34
    //   5869: ldc 268701696
    //   5871: iastore
    //   5872: dup
    //   5873: bipush #35
    //   5875: sipush #4096
    //   5878: iastore
    //   5879: dup
    //   5880: bipush #36
    //   5882: bipush #64
    //   5884: iastore
    //   5885: dup
    //   5886: bipush #37
    //   5888: ldc 268697664
    //   5890: iastore
    //   5891: dup
    //   5892: bipush #38
    //   5894: sipush #4096
    //   5897: iastore
    //   5898: dup
    //   5899: bipush #39
    //   5901: ldc 266304
    //   5903: iastore
    //   5904: dup
    //   5905: bipush #40
    //   5907: ldc 268439552
    //   5909: iastore
    //   5910: dup
    //   5911: bipush #41
    //   5913: bipush #64
    //   5915: iastore
    //   5916: dup
    //   5917: bipush #42
    //   5919: ldc 268435520
    //   5921: iastore
    //   5922: dup
    //   5923: bipush #43
    //   5925: ldc 268697600
    //   5927: iastore
    //   5928: dup
    //   5929: bipush #44
    //   5931: ldc 268697664
    //   5933: iastore
    //   5934: dup
    //   5935: bipush #45
    //   5937: ldc 268435456
    //   5939: iastore
    //   5940: dup
    //   5941: bipush #46
    //   5943: ldc 262144
    //   5945: iastore
    //   5946: dup
    //   5947: bipush #47
    //   5949: ldc 268439616
    //   5951: iastore
    //   5952: dup
    //   5953: bipush #48
    //   5955: iconst_0
    //   5956: iastore
    //   5957: dup
    //   5958: bipush #49
    //   5960: ldc 268701760
    //   5962: iastore
    //   5963: dup
    //   5964: bipush #50
    //   5966: ldc 262208
    //   5968: iastore
    //   5969: dup
    //   5970: bipush #51
    //   5972: ldc 268435520
    //   5974: iastore
    //   5975: dup
    //   5976: bipush #52
    //   5978: ldc 268697600
    //   5980: iastore
    //   5981: dup
    //   5982: bipush #53
    //   5984: ldc 268439552
    //   5986: iastore
    //   5987: dup
    //   5988: bipush #54
    //   5990: ldc 268439616
    //   5992: iastore
    //   5993: dup
    //   5994: bipush #55
    //   5996: iconst_0
    //   5997: iastore
    //   5998: dup
    //   5999: bipush #56
    //   6001: ldc 268701760
    //   6003: iastore
    //   6004: dup
    //   6005: bipush #57
    //   6007: ldc 266240
    //   6009: iastore
    //   6010: dup
    //   6011: bipush #58
    //   6013: ldc 266240
    //   6015: iastore
    //   6016: dup
    //   6017: bipush #59
    //   6019: sipush #4160
    //   6022: iastore
    //   6023: dup
    //   6024: bipush #60
    //   6026: sipush #4160
    //   6029: iastore
    //   6030: dup
    //   6031: bipush #61
    //   6033: ldc 262208
    //   6035: iastore
    //   6036: dup
    //   6037: bipush #62
    //   6039: ldc 268435456
    //   6041: iastore
    //   6042: dup
    //   6043: bipush #63
    //   6045: ldc 268701696
    //   6047: iastore
    //   6048: astore #15
    //   6050: aload #5
    //   6052: arraylength
    //   6053: istore #16
    //   6055: iload #16
    //   6057: bipush #8
    //   6059: irem
    //   6060: ifeq -> 6084
    //   6063: new java/lang/Exception
    //   6066: dup
    //   6067: sipush #-27909
    //   6070: sipush #22962
    //   6073: invokestatic a : (II)Ljava/lang/String;
    //   6076: invokespecial <init> : (Ljava/lang/String;)V
    //   6079: athrow
    //   6080: invokestatic a : (Ljava/lang/Throwable;)Ljava/lang/Throwable;
    //   6083: athrow
    //   6084: iconst_2
    //   6085: newarray int
    //   6087: astore #17
    //   6089: iload #16
    //   6091: newarray byte
    //   6093: astore #18
    //   6095: iload #16
    //   6097: bipush #8
    //   6099: idiv
    //   6100: istore #19
    //   6102: iconst_0
    //   6103: istore #20
    //   6105: iload #20
    //   6107: iload #19
    //   6109: if_icmpge -> 7027
    //   6112: iload #20
    //   6114: bipush #8
    //   6116: imul
    //   6117: istore #21
    //   6119: iconst_0
    //   6120: istore #22
    //   6122: iload #22
    //   6124: iconst_2
    //   6125: if_icmpge -> 6214
    //   6128: aload #17
    //   6130: iload #22
    //   6132: aload #5
    //   6134: iload #21
    //   6136: iload #22
    //   6138: iconst_4
    //   6139: imul
    //   6140: iadd
    //   6141: baload
    //   6142: sipush #255
    //   6145: iand
    //   6146: bipush #24
    //   6148: ishl
    //   6149: aload #5
    //   6151: iload #21
    //   6153: iload #22
    //   6155: iconst_4
    //   6156: imul
    //   6157: iadd
    //   6158: iconst_1
    //   6159: iadd
    //   6160: baload
    //   6161: sipush #255
    //   6164: iand
    //   6165: bipush #16
    //   6167: ishl
    //   6168: ior
    //   6169: aload #5
    //   6171: iload #21
    //   6173: iload #22
    //   6175: iconst_4
    //   6176: imul
    //   6177: iadd
    //   6178: iconst_2
    //   6179: iadd
    //   6180: baload
    //   6181: sipush #255
    //   6184: iand
    //   6185: bipush #8
    //   6187: ishl
    //   6188: ior
    //   6189: aload #5
    //   6191: iload #21
    //   6193: iload #22
    //   6195: iconst_4
    //   6196: imul
    //   6197: iadd
    //   6198: iconst_3
    //   6199: iadd
    //   6200: baload
    //   6201: sipush #255
    //   6204: iand
    //   6205: ior
    //   6206: iastore
    //   6207: iinc #22, 1
    //   6210: iload_2
    //   6211: ifne -> 6122
    //   6214: iconst_0
    //   6215: istore #27
    //   6217: aload #17
    //   6219: iconst_0
    //   6220: iaload
    //   6221: istore #25
    //   6223: aload #17
    //   6225: iconst_1
    //   6226: iaload
    //   6227: istore #24
    //   6229: iload #25
    //   6231: iconst_4
    //   6232: iushr
    //   6233: iload #24
    //   6235: ixor
    //   6236: ldc 252645135
    //   6238: iand
    //   6239: istore #23
    //   6241: iload #24
    //   6243: iload #23
    //   6245: ixor
    //   6246: istore #24
    //   6248: iload #25
    //   6250: iload #23
    //   6252: iconst_4
    //   6253: ishl
    //   6254: ixor
    //   6255: istore #25
    //   6257: iload #25
    //   6259: bipush #16
    //   6261: iushr
    //   6262: iload #24
    //   6264: ixor
    //   6265: ldc 65535
    //   6267: iand
    //   6268: istore #23
    //   6270: iload #24
    //   6272: iload #23
    //   6274: ixor
    //   6275: istore #24
    //   6277: iload #25
    //   6279: iload #23
    //   6281: bipush #16
    //   6283: ishl
    //   6284: ixor
    //   6285: istore #25
    //   6287: iload #24
    //   6289: iconst_2
    //   6290: iushr
    //   6291: iload #25
    //   6293: ixor
    //   6294: ldc 858993459
    //   6296: iand
    //   6297: istore #23
    //   6299: iload #25
    //   6301: iload #23
    //   6303: ixor
    //   6304: istore #25
    //   6306: iload #24
    //   6308: iload #23
    //   6310: iconst_2
    //   6311: ishl
    //   6312: ixor
    //   6313: istore #24
    //   6315: iload #24
    //   6317: bipush #8
    //   6319: iushr
    //   6320: iload #25
    //   6322: ixor
    //   6323: ldc 16711935
    //   6325: iand
    //   6326: istore #23
    //   6328: iload #25
    //   6330: iload #23
    //   6332: ixor
    //   6333: istore #25
    //   6335: iload #24
    //   6337: iload #23
    //   6339: bipush #8
    //   6341: ishl
    //   6342: ixor
    //   6343: istore #24
    //   6345: iload #24
    //   6347: iconst_1
    //   6348: ishl
    //   6349: iload #24
    //   6351: bipush #31
    //   6353: iushr
    //   6354: iconst_1
    //   6355: iand
    //   6356: ior
    //   6357: istore #24
    //   6359: iload #25
    //   6361: iload #24
    //   6363: ixor
    //   6364: ldc -1431655766
    //   6366: iand
    //   6367: istore #23
    //   6369: iload #25
    //   6371: iload #23
    //   6373: ixor
    //   6374: istore #25
    //   6376: iload #24
    //   6378: iload #23
    //   6380: ixor
    //   6381: istore #24
    //   6383: iload #25
    //   6385: iconst_1
    //   6386: ishl
    //   6387: iload #25
    //   6389: bipush #31
    //   6391: iushr
    //   6392: iconst_1
    //   6393: iand
    //   6394: ior
    //   6395: istore #25
    //   6397: iconst_0
    //   6398: istore #26
    //   6400: iload #26
    //   6402: bipush #8
    //   6404: if_icmpge -> 6742
    //   6407: iload #24
    //   6409: bipush #28
    //   6411: ishl
    //   6412: iload #24
    //   6414: iconst_4
    //   6415: iushr
    //   6416: ior
    //   6417: istore #23
    //   6419: iload #23
    //   6421: aload #7
    //   6423: iload #27
    //   6425: iinc #27, 1
    //   6428: iaload
    //   6429: ixor
    //   6430: istore #23
    //   6432: aload #14
    //   6434: iload #23
    //   6436: bipush #63
    //   6438: iand
    //   6439: iaload
    //   6440: istore #22
    //   6442: iload #22
    //   6444: aload #12
    //   6446: iload #23
    //   6448: bipush #8
    //   6450: iushr
    //   6451: bipush #63
    //   6453: iand
    //   6454: iaload
    //   6455: ior
    //   6456: istore #22
    //   6458: iload #22
    //   6460: aload #10
    //   6462: iload #23
    //   6464: bipush #16
    //   6466: iushr
    //   6467: bipush #63
    //   6469: iand
    //   6470: iaload
    //   6471: ior
    //   6472: istore #22
    //   6474: iload #22
    //   6476: aload #8
    //   6478: iload #23
    //   6480: bipush #24
    //   6482: iushr
    //   6483: bipush #63
    //   6485: iand
    //   6486: iaload
    //   6487: ior
    //   6488: istore #22
    //   6490: iload #24
    //   6492: aload #7
    //   6494: iload #27
    //   6496: iinc #27, 1
    //   6499: iaload
    //   6500: ixor
    //   6501: istore #23
    //   6503: iload #22
    //   6505: aload #15
    //   6507: iload #23
    //   6509: bipush #63
    //   6511: iand
    //   6512: iaload
    //   6513: ior
    //   6514: istore #22
    //   6516: iload #22
    //   6518: aload #13
    //   6520: iload #23
    //   6522: bipush #8
    //   6524: iushr
    //   6525: bipush #63
    //   6527: iand
    //   6528: iaload
    //   6529: ior
    //   6530: istore #22
    //   6532: iload #22
    //   6534: aload #11
    //   6536: iload #23
    //   6538: bipush #16
    //   6540: iushr
    //   6541: bipush #63
    //   6543: iand
    //   6544: iaload
    //   6545: ior
    //   6546: istore #22
    //   6548: iload #22
    //   6550: aload #9
    //   6552: iload #23
    //   6554: bipush #24
    //   6556: iushr
    //   6557: bipush #63
    //   6559: iand
    //   6560: iaload
    //   6561: ior
    //   6562: istore #22
    //   6564: iload #25
    //   6566: iload #22
    //   6568: ixor
    //   6569: istore #25
    //   6571: iload #25
    //   6573: bipush #28
    //   6575: ishl
    //   6576: iload #25
    //   6578: iconst_4
    //   6579: iushr
    //   6580: ior
    //   6581: istore #23
    //   6583: iload #23
    //   6585: aload #7
    //   6587: iload #27
    //   6589: iinc #27, 1
    //   6592: iaload
    //   6593: ixor
    //   6594: istore #23
    //   6596: aload #14
    //   6598: iload #23
    //   6600: bipush #63
    //   6602: iand
    //   6603: iaload
    //   6604: istore #22
    //   6606: iload #22
    //   6608: aload #12
    //   6610: iload #23
    //   6612: bipush #8
    //   6614: iushr
    //   6615: bipush #63
    //   6617: iand
    //   6618: iaload
    //   6619: ior
    //   6620: istore #22
    //   6622: iload #22
    //   6624: aload #10
    //   6626: iload #23
    //   6628: bipush #16
    //   6630: iushr
    //   6631: bipush #63
    //   6633: iand
    //   6634: iaload
    //   6635: ior
    //   6636: istore #22
    //   6638: iload #22
    //   6640: aload #8
    //   6642: iload #23
    //   6644: bipush #24
    //   6646: iushr
    //   6647: bipush #63
    //   6649: iand
    //   6650: iaload
    //   6651: ior
    //   6652: istore #22
    //   6654: iload #25
    //   6656: aload #7
    //   6658: iload #27
    //   6660: iinc #27, 1
    //   6663: iaload
    //   6664: ixor
    //   6665: istore #23
    //   6667: iload #22
    //   6669: aload #15
    //   6671: iload #23
    //   6673: bipush #63
    //   6675: iand
    //   6676: iaload
    //   6677: ior
    //   6678: istore #22
    //   6680: iload #22
    //   6682: aload #13
    //   6684: iload #23
    //   6686: bipush #8
    //   6688: iushr
    //   6689: bipush #63
    //   6691: iand
    //   6692: iaload
    //   6693: ior
    //   6694: istore #22
    //   6696: iload #22
    //   6698: aload #11
    //   6700: iload #23
    //   6702: bipush #16
    //   6704: iushr
    //   6705: bipush #63
    //   6707: iand
    //   6708: iaload
    //   6709: ior
    //   6710: istore #22
    //   6712: iload #22
    //   6714: aload #9
    //   6716: iload #23
    //   6718: bipush #24
    //   6720: iushr
    //   6721: bipush #63
    //   6723: iand
    //   6724: iaload
    //   6725: ior
    //   6726: istore #22
    //   6728: iload #24
    //   6730: iload #22
    //   6732: ixor
    //   6733: istore #24
    //   6735: iinc #26, 1
    //   6738: iload_2
    //   6739: ifne -> 6400
    //   6742: iload #24
    //   6744: bipush #31
    //   6746: ishl
    //   6747: iload #24
    //   6749: iconst_1
    //   6750: iushr
    //   6751: ior
    //   6752: istore #24
    //   6754: iload #25
    //   6756: iload #24
    //   6758: ixor
    //   6759: ldc -1431655766
    //   6761: iand
    //   6762: istore #23
    //   6764: iload #25
    //   6766: iload #23
    //   6768: ixor
    //   6769: istore #25
    //   6771: iload #24
    //   6773: iload #23
    //   6775: ixor
    //   6776: istore #24
    //   6778: iload #25
    //   6780: bipush #31
    //   6782: ishl
    //   6783: iload #25
    //   6785: iconst_1
    //   6786: iushr
    //   6787: ior
    //   6788: istore #25
    //   6790: iload #25
    //   6792: bipush #8
    //   6794: iushr
    //   6795: iload #24
    //   6797: ixor
    //   6798: ldc 16711935
    //   6800: iand
    //   6801: istore #23
    //   6803: iload #24
    //   6805: iload #23
    //   6807: ixor
    //   6808: istore #24
    //   6810: iload #25
    //   6812: iload #23
    //   6814: bipush #8
    //   6816: ishl
    //   6817: ixor
    //   6818: istore #25
    //   6820: iload #25
    //   6822: iconst_2
    //   6823: iushr
    //   6824: iload #24
    //   6826: ixor
    //   6827: ldc 858993459
    //   6829: iand
    //   6830: istore #23
    //   6832: iload #24
    //   6834: iload #23
    //   6836: ixor
    //   6837: istore #24
    //   6839: iload #25
    //   6841: iload #23
    //   6843: iconst_2
    //   6844: ishl
    //   6845: ixor
    //   6846: istore #25
    //   6848: iload #24
    //   6850: bipush #16
    //   6852: iushr
    //   6853: iload #25
    //   6855: ixor
    //   6856: ldc 65535
    //   6858: iand
    //   6859: istore #23
    //   6861: iload #25
    //   6863: iload #23
    //   6865: ixor
    //   6866: istore #25
    //   6868: iload #24
    //   6870: iload #23
    //   6872: bipush #16
    //   6874: ishl
    //   6875: ixor
    //   6876: istore #24
    //   6878: iload #24
    //   6880: iconst_4
    //   6881: iushr
    //   6882: iload #25
    //   6884: ixor
    //   6885: ldc 252645135
    //   6887: iand
    //   6888: istore #23
    //   6890: iload #25
    //   6892: iload #23
    //   6894: ixor
    //   6895: istore #25
    //   6897: iload #24
    //   6899: iload #23
    //   6901: iconst_4
    //   6902: ishl
    //   6903: ixor
    //   6904: istore #24
    //   6906: aload #17
    //   6908: iconst_0
    //   6909: iload #24
    //   6911: iastore
    //   6912: aload #17
    //   6914: iconst_1
    //   6915: iload #25
    //   6917: iastore
    //   6918: iload #20
    //   6920: bipush #8
    //   6922: imul
    //   6923: istore #28
    //   6925: iconst_0
    //   6926: istore #29
    //   6928: iload #29
    //   6930: iconst_2
    //   6931: if_icmpge -> 7020
    //   6934: aload #18
    //   6936: iload #28
    //   6938: iload #29
    //   6940: iconst_4
    //   6941: imul
    //   6942: iadd
    //   6943: aload #17
    //   6945: iload #29
    //   6947: iaload
    //   6948: bipush #24
    //   6950: iushr
    //   6951: i2b
    //   6952: bastore
    //   6953: aload #18
    //   6955: iload #28
    //   6957: iload #29
    //   6959: iconst_4
    //   6960: imul
    //   6961: iadd
    //   6962: iconst_1
    //   6963: iadd
    //   6964: aload #17
    //   6966: iload #29
    //   6968: iaload
    //   6969: bipush #16
    //   6971: iushr
    //   6972: i2b
    //   6973: bastore
    //   6974: aload #18
    //   6976: iload #28
    //   6978: iload #29
    //   6980: iconst_4
    //   6981: imul
    //   6982: iadd
    //   6983: iconst_2
    //   6984: iadd
    //   6985: aload #17
    //   6987: iload #29
    //   6989: iaload
    //   6990: bipush #8
    //   6992: iushr
    //   6993: i2b
    //   6994: bastore
    //   6995: aload #18
    //   6997: iload #28
    //   6999: iload #29
    //   7001: iconst_4
    //   7002: imul
    //   7003: iadd
    //   7004: iconst_3
    //   7005: iadd
    //   7006: aload #17
    //   7008: iload #29
    //   7010: iaload
    //   7011: i2b
    //   7012: bastore
    //   7013: iinc #29, 1
    //   7016: iload_2
    //   7017: ifne -> 6928
    //   7020: iinc #20, 1
    //   7023: iload_2
    //   7024: ifne -> 6105
    //   7027: aload #18
    //   7029: aload #18
    //   7031: arraylength
    //   7032: iconst_1
    //   7033: isub
    //   7034: baload
    //   7035: istore #20
    //   7037: aload #18
    //   7039: arraylength
    //   7040: iload #20
    //   7042: isub
    //   7043: newarray byte
    //   7045: astore #6
    //   7047: aload #18
    //   7049: arraylength
    //   7050: aload #6
    //   7052: arraylength
    //   7053: if_icmpge -> 7077
    //   7056: new java/lang/Exception
    //   7059: dup
    //   7060: sipush #-27913
    //   7063: sipush #-29304
    //   7066: invokestatic a : (II)Ljava/lang/String;
    //   7069: invokespecial <init> : (Ljava/lang/String;)V
    //   7072: athrow
    //   7073: invokestatic a : (Ljava/lang/Throwable;)Ljava/lang/Throwable;
    //   7076: athrow
    //   7077: iconst_0
    //   7078: istore #21
    //   7080: iload #21
    //   7082: aload #6
    //   7084: arraylength
    //   7085: if_icmpge -> 7105
    //   7088: aload #6
    //   7090: iload #21
    //   7092: aload #18
    //   7094: iload #21
    //   7096: baload
    //   7097: bastore
    //   7098: iinc #21, 1
    //   7101: iload_2
    //   7102: ifne -> 7080
    //   7105: new java/math/BigInteger
    //   7108: dup
    //   7109: aload #6
    //   7111: invokespecial <init> : ([B)V
    //   7114: invokevirtual abs : ()Ljava/math/BigInteger;
    //   7117: putstatic burp/Zl50.ZV : Ljava/lang/Object;
    //   7120: sipush #-27919
    //   7123: sipush #8511
    //   7126: invokestatic a : (II)Ljava/lang/String;
    //   7129: iconst_1
    //   7130: ldc burp/Zszm
    //   7132: invokevirtual getClassLoader : ()Ljava/lang/ClassLoader;
    //   7135: invokestatic forName : (Ljava/lang/String;ZLjava/lang/ClassLoader;)Ljava/lang/Class;
    //   7138: invokevirtual getDeclaredFields : ()[Ljava/lang/reflect/Field;
    //   7141: astore #5
    //   7143: aload #5
    //   7145: arraylength
    //   7146: istore #6
    //   7148: iconst_0
    //   7149: istore #7
    //   7151: iload #7
    //   7153: iload #6
    //   7155: if_icmpge -> 7293
    //   7158: aload #5
    //   7160: iload #7
    //   7162: aaload
    //   7163: astore #8
    //   7165: aload #8
    //   7167: invokevirtual getModifiers : ()I
    //   7170: invokestatic isStatic : (I)Z
    //   7173: ifne -> 7183
    //   7176: goto -> 7286
    //   7179: invokestatic a : (Ljava/lang/Throwable;)Ljava/lang/Throwable;
    //   7182: athrow
    //   7183: aload #8
    //   7185: invokevirtual getType : ()Ljava/lang/Class;
    //   7188: astore #9
    //   7190: aload #9
    //   7192: ifnull -> 7273
    //   7195: aload #9
    //   7197: invokevirtual isPrimitive : ()Z
    //   7200: ifne -> 7273
    //   7203: goto -> 7210
    //   7206: invokestatic a : (Ljava/lang/Throwable;)Ljava/lang/Throwable;
    //   7209: athrow
    //   7210: aload #9
    //   7212: invokevirtual getPackage : ()Ljava/lang/Package;
    //   7215: ifnull -> 7273
    //   7218: goto -> 7225
    //   7221: invokestatic a : (Ljava/lang/Throwable;)Ljava/lang/Throwable;
    //   7224: athrow
    //   7225: aload #9
    //   7227: invokevirtual getPackage : ()Ljava/lang/Package;
    //   7230: invokevirtual getName : ()Ljava/lang/String;
    //   7233: ifnull -> 7273
    //   7236: goto -> 7243
    //   7239: invokestatic a : (Ljava/lang/Throwable;)Ljava/lang/Throwable;
    //   7242: athrow
    //   7243: aload #9
    //   7245: invokevirtual getPackage : ()Ljava/lang/Package;
    //   7248: invokevirtual getName : ()Ljava/lang/String;
    //   7251: sipush #-27918
    //   7254: sipush #-15570
    //   7257: invokestatic a : (II)Ljava/lang/String;
    //   7260: invokevirtual startsWith : (Ljava/lang/String;)Z
    //   7263: ifne -> 7273
    //   7266: goto -> 7273
    //   7269: invokestatic a : (Ljava/lang/Throwable;)Ljava/lang/Throwable;
    //   7272: athrow
    //   7273: aload #8
    //   7275: iconst_1
    //   7276: invokevirtual setAccessible : (Z)V
    //   7279: aload #8
    //   7281: aconst_null
    //   7282: invokevirtual get : (Ljava/lang/Object;)Ljava/lang/Object;
    //   7285: pop
    //   7286: iinc #7, 1
    //   7289: iload_2
    //   7290: ifne -> 7151
    //   7293: sipush #-27910
    //   7296: sipush #-2231
    //   7299: invokestatic a : (II)Ljava/lang/String;
    //   7302: invokestatic forName : (Ljava/lang/String;)Ljava/lang/Class;
    //   7305: invokevirtual getDeclaredMethods : ()[Ljava/lang/reflect/Method;
    //   7308: astore #5
    //   7310: aload #5
    //   7312: arraylength
    //   7313: istore #6
    //   7315: iconst_0
    //   7316: istore #7
    //   7318: iload #7
    //   7320: iload #6
    //   7322: if_icmpge -> 7455
    //   7325: aload #5
    //   7327: iload #7
    //   7329: aaload
    //   7330: astore #8
    //   7332: aload #8
    //   7334: invokevirtual getParameterTypes : ()[Ljava/lang/Class;
    //   7337: pop
    //   7338: aload #8
    //   7340: invokevirtual getModifiers : ()I
    //   7343: invokestatic isStatic : (I)Z
    //   7346: ifeq -> 7441
    //   7349: aload #8
    //   7351: invokevirtual getParameterTypes : ()[Ljava/lang/Class;
    //   7354: arraylength
    //   7355: iconst_2
    //   7356: if_icmpne -> 7441
    //   7359: goto -> 7366
    //   7362: invokestatic a : (Ljava/lang/Throwable;)Ljava/lang/Throwable;
    //   7365: athrow
    //   7366: aload #8
    //   7368: invokevirtual getReturnType : ()Ljava/lang/Class;
    //   7371: getstatic java/lang/Void.TYPE : Ljava/lang/Class;
    //   7374: invokevirtual equals : (Ljava/lang/Object;)Z
    //   7377: ifeq -> 7441
    //   7380: goto -> 7387
    //   7383: invokestatic a : (Ljava/lang/Throwable;)Ljava/lang/Throwable;
    //   7386: athrow
    //   7387: aload #8
    //   7389: iconst_1
    //   7390: invokevirtual setAccessible : (Z)V
    //   7393: aload #8
    //   7395: aconst_null
    //   7396: iconst_2
    //   7397: anewarray java/lang/Object
    //   7400: dup
    //   7401: iconst_0
    //   7402: aload_0
    //   7403: aastore
    //   7404: dup
    //   7405: iconst_1
    //   7406: aload_1
    //   7407: ifnonnull -> 7425
    //   7410: goto -> 7417
    //   7413: invokestatic a : (Ljava/lang/Throwable;)Ljava/lang/Throwable;
    //   7416: athrow
    //   7417: aload_1
    //   7418: goto -> 7432
    //   7421: invokestatic a : (Ljava/lang/Throwable;)Ljava/lang/Throwable;
    //   7424: athrow
    //   7425: aload_1
    //   7426: checkcast [B
    //   7429: invokevirtual clone : ()Ljava/lang/Object;
    //   7432: aastore
    //   7433: invokevirtual invoke : (Ljava/lang/Object;[Ljava/lang/Object;)Ljava/lang/Object;
    //   7436: pop
    //   7437: iload_2
    //   7438: ifne -> 7455
    //   7441: iinc #7, 1
    //   7444: iload_2
    //   7445: ifne -> 7318
    //   7448: goto -> 7455
    //   7451: invokestatic a : (Ljava/lang/Throwable;)Ljava/lang/Throwable;
    //   7454: athrow
    //   7455: getstatic burp/Zeqg.Zh : Ljava/lang/String;
    //   7458: getstatic burp/Zkc8.ZW : Ljava/lang/Object;
    //   7461: checkcast java/math/BigInteger
    //   7464: invokevirtual intValue : ()I
    //   7467: bipush #32
    //   7469: irem
    //   7470: invokestatic abs : (I)I
    //   7473: invokevirtual charAt : (I)C
    //   7476: getstatic burp/Ze54.ZU : Ljava/lang/String;
    //   7479: getstatic burp/Zkb_.ZG : Ljava/lang/Object;
    //   7482: checkcast java/math/BigInteger
    //   7485: invokevirtual intValue : ()I
    //   7488: bipush #32
    //   7490: irem
    //   7491: invokestatic abs : (I)I
    //   7494: invokevirtual charAt : (I)C
    //   7497: if_icmple -> 7604
    //   7500: getstatic burp/Zefo.Zb : Ljava/lang/String;
    //   7503: getstatic burp/Zeoy.Zt : Ljava/lang/Object;
    //   7506: checkcast java/math/BigInteger
    //   7509: invokevirtual intValue : ()I
    //   7512: bipush #32
    //   7514: irem
    //   7515: invokestatic abs : (I)I
    //   7518: invokevirtual charAt : (I)C
    //   7521: getstatic burp/Ze82.Zx : Ljava/lang/String;
    //   7524: getstatic burp/Zk7e.ZW : Ljava/lang/Object;
    //   7527: checkcast java/math/BigInteger
    //   7530: invokevirtual intValue : ()I
    //   7533: bipush #32
    //   7535: irem
    //   7536: invokestatic abs : (I)I
    //   7539: invokevirtual charAt : (I)C
    //   7542: if_icmple -> 7604
    //   7545: goto -> 7552
    //   7548: invokestatic a : (Ljava/lang/Throwable;)Ljava/lang/Throwable;
    //   7551: athrow
    //   7552: getstatic burp/Ztj5.Zt : Ljava/lang/String;
    //   7555: getstatic burp/Zlnm.Zn : Ljava/lang/Object;
    //   7558: checkcast java/math/BigInteger
    //   7561: invokevirtual intValue : ()I
    //   7564: bipush #32
    //   7566: irem
    //   7567: invokestatic abs : (I)I
    //   7570: invokevirtual charAt : (I)C
    //   7573: getstatic burp/Zt98.Zh : Ljava/lang/String;
    //   7576: getstatic burp/Zzoi.ZI : Ljava/lang/Object;
    //   7579: checkcast java/math/BigInteger
    //   7582: invokevirtual intValue : ()I
    //   7585: bipush #32
    //   7587: irem
    //   7588: invokestatic abs : (I)I
    //   7591: invokevirtual charAt : (I)C
    //   7594: if_icmple -> 7612
    //   7597: goto -> 7604
    //   7600: invokestatic a : (Ljava/lang/Throwable;)Ljava/lang/Throwable;
    //   7603: athrow
    //   7604: iconst_1
    //   7605: goto -> 7613
    //   7608: invokestatic a : (Ljava/lang/Throwable;)Ljava/lang/Throwable;
    //   7611: athrow
    //   7612: iconst_0
    //   7613: ireturn
    //   7614: astore_3
    //   7615: new java/lang/Exception
    //   7618: dup
    //   7619: aload_3
    //   7620: invokevirtual getMessage : ()Ljava/lang/String;
    //   7623: invokespecial <init> : (Ljava/lang/String;)V
    //   7626: athrow
    // Exception table:
    //   from	to	target	type
    //   4	7613	7614	java/lang/Throwable
    //   22	198	201	java/lang/Throwable
    //   168	235	238	java/lang/Throwable
    //   205	272	275	java/lang/Throwable
    //   242	309	312	java/lang/Throwable
    //   279	346	349	java/lang/Throwable
    //   316	383	386	java/lang/Throwable
    //   353	420	423	java/lang/Throwable
    //   390	457	460	java/lang/Throwable
    //   427	494	497	java/lang/Throwable
    //   464	531	534	java/lang/Throwable
    //   501	568	571	java/lang/Throwable
    //   538	605	608	java/lang/Throwable
    //   575	642	645	java/lang/Throwable
    //   612	679	682	java/lang/Throwable
    //   649	716	719	java/lang/Throwable
    //   686	753	756	java/lang/Throwable
    //   723	790	793	java/lang/Throwable
    //   760	827	830	java/lang/Throwable
    //   797	864	867	java/lang/Throwable
    //   834	901	904	java/lang/Throwable
    //   871	938	941	java/lang/Throwable
    //   908	975	978	java/lang/Throwable
    //   945	1012	1015	java/lang/Throwable
    //   982	1049	1052	java/lang/Throwable
    //   1019	1086	1089	java/lang/Throwable
    //   1056	1123	1126	java/lang/Throwable
    //   1093	1160	1163	java/lang/Throwable
    //   1130	1197	1200	java/lang/Throwable
    //   1167	1234	1237	java/lang/Throwable
    //   1204	1271	1274	java/lang/Throwable
    //   1241	1308	1311	java/lang/Throwable
    //   1278	1341	1344	java/lang/Throwable
    //   1381	1555	1558	java/lang/Throwable
    //   1524	1593	1596	java/lang/Throwable
    //   1562	1631	1634	java/lang/Throwable
    //   1600	1669	1672	java/lang/Throwable
    //   1638	1707	1710	java/lang/Throwable
    //   1676	1745	1748	java/lang/Throwable
    //   1714	1783	1786	java/lang/Throwable
    //   1752	1821	1824	java/lang/Throwable
    //   1790	1859	1862	java/lang/Throwable
    //   1828	1897	1900	java/lang/Throwable
    //   1866	1935	1938	java/lang/Throwable
    //   1904	1973	1976	java/lang/Throwable
    //   1942	2011	2014	java/lang/Throwable
    //   1980	2049	2052	java/lang/Throwable
    //   2018	2087	2090	java/lang/Throwable
    //   2056	2125	2128	java/lang/Throwable
    //   2094	2163	2166	java/lang/Throwable
    //   2132	2201	2204	java/lang/Throwable
    //   2170	2239	2242	java/lang/Throwable
    //   2208	2277	2280	java/lang/Throwable
    //   2246	2315	2318	java/lang/Throwable
    //   2284	2353	2356	java/lang/Throwable
    //   2322	2391	2394	java/lang/Throwable
    //   2360	2429	2432	java/lang/Throwable
    //   2398	2467	2470	java/lang/Throwable
    //   2436	2505	2508	java/lang/Throwable
    //   2474	2543	2546	java/lang/Throwable
    //   2512	2581	2584	java/lang/Throwable
    //   2550	2619	2622	java/lang/Throwable
    //   2588	2657	2660	java/lang/Throwable
    //   2626	2695	2698	java/lang/Throwable
    //   2664	2729	2732	java/lang/Throwable
    //   6055	6080	6080	java/lang/Throwable
    //   7047	7073	7073	java/lang/Throwable
    //   7165	7179	7179	java/lang/Throwable
    //   7190	7203	7206	java/lang/Throwable
    //   7195	7218	7221	java/lang/Throwable
    //   7210	7236	7239	java/lang/Throwable
    //   7225	7266	7269	java/lang/Throwable
    //   7332	7359	7362	java/lang/Throwable
    //   7349	7380	7383	java/lang/Throwable
    //   7366	7410	7413	java/lang/Throwable
    //   7387	7421	7421	java/lang/Throwable
    //   7432	7448	7451	java/lang/Throwable
    //   7455	7545	7548	java/lang/Throwable
    //   7500	7597	7600	java/lang/Throwable
    //   7552	7608	7608	java/lang/Throwable
  }
  
  static {
    // Byte code:
    //   0: bipush #10
    //   2: anewarray java/lang/String
    //   5: astore #5
    //   7: iconst_0
    //   8: istore_3
    //   9: ldc 'Gb\\t\\f=6&h\\t\\bL EJ\\t%! \\fhj\\t\\tm/6>Pc3#eoxMUw0~Ih/O{\\n\\nv3\\f7yP?RhY"\\r?j( BAzc[|H;FuKn%;;`7PN\\n'
    //   11: dup
    //   12: astore_2
    //   13: invokevirtual length : ()I
    //   16: istore #4
    //   18: iconst_4
    //   19: istore_1
    //   20: iconst_m1
    //   21: istore_0
    //   22: bipush #114
    //   24: iinc #0, 1
    //   27: aload_2
    //   28: iload_0
    //   29: dup
    //   30: iload_1
    //   31: iadd
    //   32: invokevirtual substring : (II)Ljava/lang/String;
    //   35: iconst_m1
    //   36: goto -> 142
    //   39: aload #5
    //   41: swap
    //   42: iload_3
    //   43: iinc #3, 1
    //   46: swap
    //   47: aastore
    //   48: iload_0
    //   49: iload_1
    //   50: iadd
    //   51: dup
    //   52: istore_0
    //   53: iload #4
    //   55: if_icmpge -> 67
    //   58: aload_2
    //   59: iload_0
    //   60: invokevirtual charAt : (I)C
    //   63: istore_1
    //   64: goto -> 22
    //   67: ldc '4j6op'
    //   69: dup
    //   70: astore_2
    //   71: invokevirtual length : ()I
    //   74: istore #4
    //   76: bipush #9
    //   78: istore_1
    //   79: iconst_m1
    //   80: istore_0
    //   81: bipush #115
    //   83: iinc #0, 1
    //   86: aload_2
    //   87: iload_0
    //   88: dup
    //   89: iload_1
    //   90: iadd
    //   91: invokevirtual substring : (II)Ljava/lang/String;
    //   94: iconst_0
    //   95: goto -> 142
    //   98: aload #5
    //   100: swap
    //   101: iload_3
    //   102: iinc #3, 1
    //   105: swap
    //   106: aastore
    //   107: iload_0
    //   108: iload_1
    //   109: iadd
    //   110: dup
    //   111: istore_0
    //   112: iload #4
    //   114: if_icmpge -> 126
    //   117: aload_2
    //   118: iload_0
    //   119: invokevirtual charAt : (I)C
    //   122: istore_1
    //   123: goto -> 81
    //   126: aload #5
    //   128: putstatic burp/Zkc8.a : [Ljava/lang/String;
    //   131: bipush #10
    //   133: anewarray java/lang/String
    //   136: putstatic burp/Zkc8.b : [Ljava/lang/String;
    //   139: goto -> 300
    //   142: dup_x2
    //   143: pop
    //   144: invokevirtual toCharArray : ()[C
    //   147: dup_x1
    //   148: arraylength
    //   149: dup_x2
    //   150: pop
    //   151: iconst_0
    //   152: istore #6
    //   154: dup2_x1
    //   155: pop2
    //   156: dup_x2
    //   157: iconst_1
    //   158: if_icmpgt -> 260
    //   161: dup2
    //   162: swap
    //   163: iload #6
    //   165: dup2_x1
    //   166: caload
    //   167: swap
    //   168: iload #6
    //   170: bipush #7
    //   172: irem
    //   173: tableswitch default -> 242, 0 -> 212, 1 -> 217, 2 -> 222, 3 -> 227, 4 -> 232, 5 -> 237
    //   212: bipush #61
    //   214: goto -> 244
    //   217: bipush #53
    //   219: goto -> 244
    //   222: bipush #28
    //   224: goto -> 244
    //   227: bipush #12
    //   229: goto -> 244
    //   232: bipush #118
    //   234: goto -> 244
    //   237: bipush #37
    //   239: goto -> 244
    //   242: bipush #39
    //   244: ixor
    //   245: ixor
    //   246: i2c
    //   247: castore
    //   248: iinc #6, 1
    //   251: dup
    //   252: ifne -> 260
    //   255: dup2
    //   256: dup_x1
    //   257: goto -> 165
    //   260: dup2_x1
    //   261: pop2
    //   262: dup_x2
    //   263: iload #6
    //   265: if_icmpgt -> 161
    //   268: pop
    //   269: new java/lang/String
    //   272: dup_x1
    //   273: swap
    //   274: invokespecial <init> : ([C)V
    //   277: invokevirtual intern : ()Ljava/lang/String;
    //   280: swap
    //   281: pop
    //   282: swap
    //   283: tableswitch default -> 39, 0 -> 98
    //   300: sipush #-27915
    //   303: sipush #-21632
    //   306: invokestatic a : (II)Ljava/lang/String;
    //   309: putstatic burp/Zkc8.Za : Ljava/lang/String;
    //   312: new java/math/BigInteger
    //   315: dup
    //   316: bipush #32
    //   318: newarray byte
    //   320: dup
    //   321: iconst_0
    //   322: bipush #45
    //   324: bastore
    //   325: dup
    //   326: iconst_1
    //   327: bipush #22
    //   329: bastore
    //   330: dup
    //   331: iconst_2
    //   332: iconst_m1
    //   333: bastore
    //   334: dup
    //   335: iconst_3
    //   336: bipush #-84
    //   338: bastore
    //   339: dup
    //   340: iconst_4
    //   341: iconst_m1
    //   342: bastore
    //   343: dup
    //   344: iconst_5
    //   345: bipush #-96
    //   347: bastore
    //   348: dup
    //   349: bipush #6
    //   351: bipush #40
    //   353: bastore
    //   354: dup
    //   355: bipush #7
    //   357: bipush #-59
    //   359: bastore
    //   360: dup
    //   361: bipush #8
    //   363: bipush #-109
    //   365: bastore
    //   366: dup
    //   367: bipush #9
    //   369: bipush #102
    //   371: bastore
    //   372: dup
    //   373: bipush #10
    //   375: bipush #-58
    //   377: bastore
    //   378: dup
    //   379: bipush #11
    //   381: bipush #-16
    //   383: bastore
    //   384: dup
    //   385: bipush #12
    //   387: bipush #37
    //   389: bastore
    //   390: dup
    //   391: bipush #13
    //   393: bipush #99
    //   395: bastore
    //   396: dup
    //   397: bipush #14
    //   399: bipush #-6
    //   401: bastore
    //   402: dup
    //   403: bipush #15
    //   405: bipush #-60
    //   407: bastore
    //   408: dup
    //   409: bipush #16
    //   411: iconst_4
    //   412: bastore
    //   413: dup
    //   414: bipush #17
    //   416: iconst_1
    //   417: bastore
    //   418: dup
    //   419: bipush #18
    //   421: bipush #35
    //   423: bastore
    //   424: dup
    //   425: bipush #19
    //   427: bipush #84
    //   429: bastore
    //   430: dup
    //   431: bipush #20
    //   433: bipush #-84
    //   435: bastore
    //   436: dup
    //   437: bipush #21
    //   439: bipush #19
    //   441: bastore
    //   442: dup
    //   443: bipush #22
    //   445: bipush #107
    //   447: bastore
    //   448: dup
    //   449: bipush #23
    //   451: bipush #-69
    //   453: bastore
    //   454: dup
    //   455: bipush #24
    //   457: bipush #-101
    //   459: bastore
    //   460: dup
    //   461: bipush #25
    //   463: iconst_2
    //   464: bastore
    //   465: dup
    //   466: bipush #26
    //   468: iconst_1
    //   469: bastore
    //   470: dup
    //   471: bipush #27
    //   473: bipush #6
    //   475: bastore
    //   476: dup
    //   477: bipush #28
    //   479: bipush #14
    //   481: bastore
    //   482: dup
    //   483: bipush #29
    //   485: bipush #-42
    //   487: bastore
    //   488: dup
    //   489: bipush #30
    //   491: bipush #92
    //   493: bastore
    //   494: dup
    //   495: bipush #31
    //   497: bipush #70
    //   499: bastore
    //   500: invokespecial <init> : ([B)V
    //   503: putstatic burp/Zkc8.ZW : Ljava/lang/Object;
    //   506: return
  }
  
  private static Throwable a(Throwable paramThrowable) {
    return paramThrowable;
  }
  
  private static String a(int paramInt1, int paramInt2) {
    int i = (paramInt1 ^ 0xFFFF92F2) & 0xFFFF;
    if (b[i] == null) {
      char[] arrayOfChar = a[i].toCharArray();
      switch (arrayOfChar[0] & 0xFF) {
        case 0:
        
        case 1:
        
        case 2:
        
        case 3:
        
        case 4:
        
        case 5:
        
        case 6:
        
        case 7:
        
        case 8:
        
        case 9:
        
        case 10:
        
        case 11:
        
        case 12:
        
        case 13:
        
        case 14:
        
        case 15:
        
        case 16:
        
        case 17:
        
        case 18:
        
        case 19:
        
        case 20:
        
        case 21:
        
        case 22:
        
        case 23:
        
        case 24:
        
        case 25:
        
        case 26:
        
        case 27:
        
        case 28:
        
        case 29:
        
        case 30:
        
        case 31:
        
        case 32:
        
        case 33:
        
        case 34:
        
        case 35:
        
        case 36:
        
        case 37:
        
        case 38:
        
        case 39:
        
        case 40:
        
        case 41:
        
        case 42:
        
        case 43:
        
        case 44:
        
        case 45:
        
        case 46:
        
        case 47:
        
        case 48:
        
        case 49:
        
        case 50:
        
        case 51:
        
        case 52:
        
        case 53:
        
        case 54:
        
        case 55:
        
        case 56:
        
        case 57:
        
        case 58:
        
        case 59:
        
        case 60:
        
        case 61:
        
        case 62:
        
        case 63:
        
        case 64:
        
        case 65:
        
        case 66:
        
        case 67:
        
        case 68:
        
        case 69:
        
        case 70:
        
        case 71:
        
        case 72:
        
        case 73:
        
        case 74:
        
        case 75:
        
        case 76:
        
        case 77:
        
        case 78:
        
        case 79:
        
        case 80:
        
        case 81:
        
        case 82:
        
        case 83:
        
        case 84:
        
        case 85:
        
        case 86:
        
        case 87:
        
        case 88:
        
        case 89:
        
        case 90:
        
        case 91:
        
        case 92:
        
        case 93:
        
        case 94:
        
        case 95:
        
        case 96:
        
        case 97:
        
        case 98:
        
        case 99:
        
        case 100:
        
        case 101:
        
        case 102:
        
        case 103:
        
        case 104:
        
        case 105:
        
        case 106:
        
        case 107:
        
        case 108:
        
        case 109:
        
        case 110:
        
        case 111:
        
        case 112:
        
        case 113:
        
        case 114:
        
        case 115:
        
        case 116:
        
        case 117:
        
        case 118:
        
        case 119:
        
        case 120:
        
        case 121:
        
        case 122:
        
        case 123:
        
        case 124:
        
        case 125:
        
        case 126:
        
        case 127:
        
        case 128:
        
        case 129:
        
        case 130:
        
        case 131:
        
        case 132:
        
        case 133:
        
        case 134:
        
        case 135:
        
        case 136:
        
        case 137:
        
        case 138:
        
        case 139:
        
        case 140:
        
        case 141:
        
        case 142:
        
        case 143:
        
        case 144:
        
        case 145:
        
        case 146:
        
        case 147:
        
        case 148:
        
        case 149:
        
        case 150:
        
        case 151:
        
        case 152:
        
        case 153:
        
        case 154:
        
        case 155:
        
        case 156:
        
        case 157:
        
        case 158:
        
        case 159:
        
        case 160:
        
        case 161:
        
        case 162:
        
        case 163:
        
        case 164:
        
        case 165:
        
        case 166:
        
        case 167:
        
        case 168:
        
        case 169:
        
        case 170:
        
        case 171:
        
        case 172:
        
        case 173:
        
        case 174:
        
        case 175:
        
        case 176:
        
        case 177:
        
        case 178:
        
        case 179:
        
        case 180:
        
        case 181:
        
        case 182:
        
        case 183:
        
        case 184:
        
        case 185:
        
        case 186:
        
        case 187:
        
        case 188:
        
        case 189:
        
        case 190:
        
        case 191:
        
        case 192:
        
        case 193:
        
        case 194:
        
        case 195:
        
        case 196:
        
        case 197:
        
        case 198:
        
        case 199:
        
        case 200:
        
        case 201:
        
        case 202:
        
        case 203:
        
        case 204:
        
        case 205:
        
        case 206:
        
        case 207:
        
        case 208:
        
        case 209:
        
        case 210:
        
        case 211:
        
        case 212:
        
        case 213:
        
        case 214:
        
        case 215:
        
        case 216:
        
        case 217:
        
        case 218:
        
        case 219:
        
        case 220:
        
        case 221:
        
        case 222:
        
        case 223:
        
        case 224:
        
        case 225:
        
        case 226:
        
        case 227:
        
        case 228:
        
        case 229:
        
        case 230:
        
        case 231:
        
        case 232:
        
        case 233:
        
        case 234:
        
        case 235:
        
        case 236:
        
        case 237:
        
        case 238:
        
        case 239:
        
        case 240:
        
        case 241:
        
        case 242:
        
        case 243:
        
        case 244:
        
        case 245:
        
        case 246:
        
        case 247:
        
        case 248:
        
        case 249:
        
        case 250:
        
        case 251:
        
        case 252:
        
        case 253:
        
        case 254:
        
        default:
          break;
      } 
      char c = '';
      int j = (paramInt2 & 0xFF) - c;
      if (j < 0)
        j += 256; 
      int k = ((paramInt2 & 0xFFFF) >>> 8) - c;
      if (k < 0)
        k += 256; 
      for (byte b = 0; b < arrayOfChar.length; b++) {
        int m = b % 2;
        if (m == 0) {
          arrayOfChar[b] = (char)(arrayOfChar[b] ^ j);
          j = ((j >>> 3 | j << 5) ^ arrayOfChar[b]) & 0xFF;
        } else {
          arrayOfChar[b] = (char)(arrayOfChar[b] ^ k);
          k = ((k >>> 3 | k << 5) ^ arrayOfChar[b]) & 0xFF;
        } 
      } 
      b[i] = (new String(arrayOfChar)).intern();
    } 
    return b[i];
  }
}


/* Location:              C:\Program Files\BurpSuitePro\burpsuite_pro.jar!\burp\Zkc8.class
 * Java compiler version: 21 (65.0)
 * JD-Core Version:       1.1.3
 */