package burp;

import java.math.BigInteger;

class Zkco extends ClassLoader {
  static Object Zg;
  
  static String Zz;
  
  private static final String[] a;
  
  private static final String[] b;
  
  static boolean ZX(Object[] paramArrayOfObject, Object paramObject) throws Throwable {
    // Byte code:
    //   0: invokestatic ZK : ()Z
    //   3: istore_2
    //   4: getstatic burp/Zlhm.ZT : Ljava/lang/Object;
    //   7: checkcast java/math/BigInteger
    //   10: getstatic burp/Zxtc.ZF : Ljava/lang/Object;
    //   13: checkcast java/math/BigInteger
    //   16: invokevirtual add : (Ljava/math/BigInteger;)Ljava/math/BigInteger;
    //   19: putstatic burp/Zrc0.Zz : Ljava/lang/Object;
    //   22: new java/lang/StringBuilder
    //   25: dup
    //   26: invokespecial <init> : ()V
    //   29: astore_3
    //   30: iconst_0
    //   31: istore #4
    //   33: iload #4
    //   35: bipush #32
    //   37: if_icmpge -> 1371
    //   40: iload #4
    //   42: tableswitch default -> 1364, 0 -> 184, 1 -> 221, 2 -> 258, 3 -> 295, 4 -> 332, 5 -> 369, 6 -> 406, 7 -> 443, 8 -> 480, 9 -> 517, 10 -> 554, 11 -> 591, 12 -> 628, 13 -> 665, 14 -> 702, 15 -> 739, 16 -> 776, 17 -> 813, 18 -> 850, 19 -> 887, 20 -> 924, 21 -> 961, 22 -> 998, 23 -> 1035, 24 -> 1072, 25 -> 1109, 26 -> 1146, 27 -> 1183, 28 -> 1220, 29 -> 1257, 30 -> 1294, 31 -> 1331
    //   184: aload_3
    //   185: getstatic burp/Zevc.ZF : Ljava/lang/String;
    //   188: getstatic burp/Zg8v.ZB : Ljava/lang/Object;
    //   191: checkcast java/math/BigInteger
    //   194: invokevirtual intValue : ()I
    //   197: bipush #32
    //   199: irem
    //   200: invokestatic abs : (I)I
    //   203: invokevirtual charAt : (I)C
    //   206: invokevirtual append : (C)Ljava/lang/StringBuilder;
    //   209: pop
    //   210: iload_2
    //   211: ifeq -> 1364
    //   214: goto -> 221
    //   217: invokestatic a : (Ljava/lang/Throwable;)Ljava/lang/Throwable;
    //   220: athrow
    //   221: aload_3
    //   222: getstatic burp/Zrly.ZS : Ljava/lang/String;
    //   225: getstatic burp/Ze_e.Za : Ljava/lang/Object;
    //   228: checkcast java/math/BigInteger
    //   231: invokevirtual intValue : ()I
    //   234: bipush #32
    //   236: irem
    //   237: invokestatic abs : (I)I
    //   240: invokevirtual charAt : (I)C
    //   243: invokevirtual append : (C)Ljava/lang/StringBuilder;
    //   246: pop
    //   247: iload_2
    //   248: ifeq -> 1364
    //   251: goto -> 258
    //   254: invokestatic a : (Ljava/lang/Throwable;)Ljava/lang/Throwable;
    //   257: athrow
    //   258: aload_3
    //   259: getstatic burp/Zmha.Zo : Ljava/lang/String;
    //   262: getstatic burp/Zrhu.Zs : Ljava/lang/Object;
    //   265: checkcast java/math/BigInteger
    //   268: invokevirtual intValue : ()I
    //   271: bipush #32
    //   273: irem
    //   274: invokestatic abs : (I)I
    //   277: invokevirtual charAt : (I)C
    //   280: invokevirtual append : (C)Ljava/lang/StringBuilder;
    //   283: pop
    //   284: iload_2
    //   285: ifeq -> 1364
    //   288: goto -> 295
    //   291: invokestatic a : (Ljava/lang/Throwable;)Ljava/lang/Throwable;
    //   294: athrow
    //   295: aload_3
    //   296: getstatic burp/Zkmx.Zg : Ljava/lang/String;
    //   299: getstatic burp/Zllw.ZW : Ljava/lang/Object;
    //   302: checkcast java/math/BigInteger
    //   305: invokevirtual intValue : ()I
    //   308: bipush #32
    //   310: irem
    //   311: invokestatic abs : (I)I
    //   314: invokevirtual charAt : (I)C
    //   317: invokevirtual append : (C)Ljava/lang/StringBuilder;
    //   320: pop
    //   321: iload_2
    //   322: ifeq -> 1364
    //   325: goto -> 332
    //   328: invokestatic a : (Ljava/lang/Throwable;)Ljava/lang/Throwable;
    //   331: athrow
    //   332: aload_3
    //   333: getstatic burp/Zxzj.ZZ : Ljava/lang/String;
    //   336: getstatic burp/Zzk9.ZK : Ljava/lang/Object;
    //   339: checkcast java/math/BigInteger
    //   342: invokevirtual intValue : ()I
    //   345: bipush #32
    //   347: irem
    //   348: invokestatic abs : (I)I
    //   351: invokevirtual charAt : (I)C
    //   354: invokevirtual append : (C)Ljava/lang/StringBuilder;
    //   357: pop
    //   358: iload_2
    //   359: ifeq -> 1364
    //   362: goto -> 369
    //   365: invokestatic a : (Ljava/lang/Throwable;)Ljava/lang/Throwable;
    //   368: athrow
    //   369: aload_3
    //   370: getstatic burp/Zr4k.Zy : Ljava/lang/String;
    //   373: getstatic burp/Zsf3.ZH : Ljava/lang/Object;
    //   376: checkcast java/math/BigInteger
    //   379: invokevirtual intValue : ()I
    //   382: bipush #32
    //   384: irem
    //   385: invokestatic abs : (I)I
    //   388: invokevirtual charAt : (I)C
    //   391: invokevirtual append : (C)Ljava/lang/StringBuilder;
    //   394: pop
    //   395: iload_2
    //   396: ifeq -> 1364
    //   399: goto -> 406
    //   402: invokestatic a : (Ljava/lang/Throwable;)Ljava/lang/Throwable;
    //   405: athrow
    //   406: aload_3
    //   407: getstatic burp/Ze6k.ZM : Ljava/lang/String;
    //   410: getstatic burp/Zlna.ZG : Ljava/lang/Object;
    //   413: checkcast java/math/BigInteger
    //   416: invokevirtual intValue : ()I
    //   419: bipush #32
    //   421: irem
    //   422: invokestatic abs : (I)I
    //   425: invokevirtual charAt : (I)C
    //   428: invokevirtual append : (C)Ljava/lang/StringBuilder;
    //   431: pop
    //   432: iload_2
    //   433: ifeq -> 1364
    //   436: goto -> 443
    //   439: invokestatic a : (Ljava/lang/Throwable;)Ljava/lang/Throwable;
    //   442: athrow
    //   443: aload_3
    //   444: getstatic burp/Zmv9.Zm : Ljava/lang/String;
    //   447: getstatic burp/Zzok.ZY : Ljava/lang/Object;
    //   450: checkcast java/math/BigInteger
    //   453: invokevirtual intValue : ()I
    //   456: bipush #32
    //   458: irem
    //   459: invokestatic abs : (I)I
    //   462: invokevirtual charAt : (I)C
    //   465: invokevirtual append : (C)Ljava/lang/StringBuilder;
    //   468: pop
    //   469: iload_2
    //   470: ifeq -> 1364
    //   473: goto -> 480
    //   476: invokestatic a : (Ljava/lang/Throwable;)Ljava/lang/Throwable;
    //   479: athrow
    //   480: aload_3
    //   481: getstatic burp/Zzym.Zj : Ljava/lang/String;
    //   484: getstatic burp/Ze0z.ZQ : Ljava/lang/Object;
    //   487: checkcast java/math/BigInteger
    //   490: invokevirtual intValue : ()I
    //   493: bipush #32
    //   495: irem
    //   496: invokestatic abs : (I)I
    //   499: invokevirtual charAt : (I)C
    //   502: invokevirtual append : (C)Ljava/lang/StringBuilder;
    //   505: pop
    //   506: iload_2
    //   507: ifeq -> 1364
    //   510: goto -> 517
    //   513: invokestatic a : (Ljava/lang/Throwable;)Ljava/lang/Throwable;
    //   516: athrow
    //   517: aload_3
    //   518: getstatic burp/Zxtc.Zo : Ljava/lang/String;
    //   521: getstatic burp/Zxzv.Zg : Ljava/lang/Object;
    //   524: checkcast java/math/BigInteger
    //   527: invokevirtual intValue : ()I
    //   530: bipush #32
    //   532: irem
    //   533: invokestatic abs : (I)I
    //   536: invokevirtual charAt : (I)C
    //   539: invokevirtual append : (C)Ljava/lang/StringBuilder;
    //   542: pop
    //   543: iload_2
    //   544: ifeq -> 1364
    //   547: goto -> 554
    //   550: invokestatic a : (Ljava/lang/Throwable;)Ljava/lang/Throwable;
    //   553: athrow
    //   554: aload_3
    //   555: getstatic burp/Zszm.Zf : Ljava/lang/String;
    //   558: getstatic burp/Ze08.ZJ : Ljava/lang/Object;
    //   561: checkcast java/math/BigInteger
    //   564: invokevirtual intValue : ()I
    //   567: bipush #32
    //   569: irem
    //   570: invokestatic abs : (I)I
    //   573: invokevirtual charAt : (I)C
    //   576: invokevirtual append : (C)Ljava/lang/StringBuilder;
    //   579: pop
    //   580: iload_2
    //   581: ifeq -> 1364
    //   584: goto -> 591
    //   587: invokestatic a : (Ljava/lang/Throwable;)Ljava/lang/Throwable;
    //   590: athrow
    //   591: aload_3
    //   592: getstatic burp/Zrod.ZQ : Ljava/lang/String;
    //   595: getstatic burp/Zt0t.ZL : Ljava/lang/Object;
    //   598: checkcast java/math/BigInteger
    //   601: invokevirtual intValue : ()I
    //   604: bipush #32
    //   606: irem
    //   607: invokestatic abs : (I)I
    //   610: invokevirtual charAt : (I)C
    //   613: invokevirtual append : (C)Ljava/lang/StringBuilder;
    //   616: pop
    //   617: iload_2
    //   618: ifeq -> 1364
    //   621: goto -> 628
    //   624: invokestatic a : (Ljava/lang/Throwable;)Ljava/lang/Throwable;
    //   627: athrow
    //   628: aload_3
    //   629: getstatic burp/Zr04.ZA : Ljava/lang/String;
    //   632: getstatic burp/Zzxs.Zg : Ljava/lang/Object;
    //   635: checkcast java/math/BigInteger
    //   638: invokevirtual intValue : ()I
    //   641: bipush #32
    //   643: irem
    //   644: invokestatic abs : (I)I
    //   647: invokevirtual charAt : (I)C
    //   650: invokevirtual append : (C)Ljava/lang/StringBuilder;
    //   653: pop
    //   654: iload_2
    //   655: ifeq -> 1364
    //   658: goto -> 665
    //   661: invokestatic a : (Ljava/lang/Throwable;)Ljava/lang/Throwable;
    //   664: athrow
    //   665: aload_3
    //   666: getstatic burp/Zr3x.ZM : Ljava/lang/String;
    //   669: getstatic burp/Zeno.Zo : Ljava/lang/Object;
    //   672: checkcast java/math/BigInteger
    //   675: invokevirtual intValue : ()I
    //   678: bipush #32
    //   680: irem
    //   681: invokestatic abs : (I)I
    //   684: invokevirtual charAt : (I)C
    //   687: invokevirtual append : (C)Ljava/lang/StringBuilder;
    //   690: pop
    //   691: iload_2
    //   692: ifeq -> 1364
    //   695: goto -> 702
    //   698: invokestatic a : (Ljava/lang/Throwable;)Ljava/lang/Throwable;
    //   701: athrow
    //   702: aload_3
    //   703: getstatic burp/Zb3r.Zo : Ljava/lang/String;
    //   706: getstatic burp/Zry0.Zr : Ljava/lang/Object;
    //   709: checkcast java/math/BigInteger
    //   712: invokevirtual intValue : ()I
    //   715: bipush #32
    //   717: irem
    //   718: invokestatic abs : (I)I
    //   721: invokevirtual charAt : (I)C
    //   724: invokevirtual append : (C)Ljava/lang/StringBuilder;
    //   727: pop
    //   728: iload_2
    //   729: ifeq -> 1364
    //   732: goto -> 739
    //   735: invokestatic a : (Ljava/lang/Throwable;)Ljava/lang/Throwable;
    //   738: athrow
    //   739: aload_3
    //   740: getstatic burp/Zea9.Zd : Ljava/lang/String;
    //   743: getstatic burp/Zg2.ZE : Ljava/lang/Object;
    //   746: checkcast java/math/BigInteger
    //   749: invokevirtual intValue : ()I
    //   752: bipush #32
    //   754: irem
    //   755: invokestatic abs : (I)I
    //   758: invokevirtual charAt : (I)C
    //   761: invokevirtual append : (C)Ljava/lang/StringBuilder;
    //   764: pop
    //   765: iload_2
    //   766: ifeq -> 1364
    //   769: goto -> 776
    //   772: invokestatic a : (Ljava/lang/Throwable;)Ljava/lang/Throwable;
    //   775: athrow
    //   776: aload_3
    //   777: getstatic burp/Zevc.ZF : Ljava/lang/String;
    //   780: getstatic burp/Zrcu.Zs : Ljava/lang/Object;
    //   783: checkcast java/math/BigInteger
    //   786: invokevirtual intValue : ()I
    //   789: bipush #32
    //   791: irem
    //   792: invokestatic abs : (I)I
    //   795: invokevirtual charAt : (I)C
    //   798: invokevirtual append : (C)Ljava/lang/StringBuilder;
    //   801: pop
    //   802: iload_2
    //   803: ifeq -> 1364
    //   806: goto -> 813
    //   809: invokestatic a : (Ljava/lang/Throwable;)Ljava/lang/Throwable;
    //   812: athrow
    //   813: aload_3
    //   814: getstatic burp/Zez0.Zp : Ljava/lang/String;
    //   817: getstatic burp/Zmt6.ZK : Ljava/lang/Object;
    //   820: checkcast java/math/BigInteger
    //   823: invokevirtual intValue : ()I
    //   826: bipush #32
    //   828: irem
    //   829: invokestatic abs : (I)I
    //   832: invokevirtual charAt : (I)C
    //   835: invokevirtual append : (C)Ljava/lang/StringBuilder;
    //   838: pop
    //   839: iload_2
    //   840: ifeq -> 1364
    //   843: goto -> 850
    //   846: invokestatic a : (Ljava/lang/Throwable;)Ljava/lang/Throwable;
    //   849: athrow
    //   850: aload_3
    //   851: getstatic burp/Zzo5.ZX : Ljava/lang/String;
    //   854: getstatic burp/Zshq.ZK : Ljava/lang/Object;
    //   857: checkcast java/math/BigInteger
    //   860: invokevirtual intValue : ()I
    //   863: bipush #32
    //   865: irem
    //   866: invokestatic abs : (I)I
    //   869: invokevirtual charAt : (I)C
    //   872: invokevirtual append : (C)Ljava/lang/StringBuilder;
    //   875: pop
    //   876: iload_2
    //   877: ifeq -> 1364
    //   880: goto -> 887
    //   883: invokestatic a : (Ljava/lang/Throwable;)Ljava/lang/Throwable;
    //   886: athrow
    //   887: aload_3
    //   888: getstatic burp/Zg0j.Ze : Ljava/lang/String;
    //   891: getstatic burp/Zl2g.ZG : Ljava/lang/Object;
    //   894: checkcast java/math/BigInteger
    //   897: invokevirtual intValue : ()I
    //   900: bipush #32
    //   902: irem
    //   903: invokestatic abs : (I)I
    //   906: invokevirtual charAt : (I)C
    //   909: invokevirtual append : (C)Ljava/lang/StringBuilder;
    //   912: pop
    //   913: iload_2
    //   914: ifeq -> 1364
    //   917: goto -> 924
    //   920: invokestatic a : (Ljava/lang/Throwable;)Ljava/lang/Throwable;
    //   923: athrow
    //   924: aload_3
    //   925: getstatic burp/Ze_l.ZY : Ljava/lang/String;
    //   928: getstatic burp/Zmt_.Zl : Ljava/lang/Object;
    //   931: checkcast java/math/BigInteger
    //   934: invokevirtual intValue : ()I
    //   937: bipush #32
    //   939: irem
    //   940: invokestatic abs : (I)I
    //   943: invokevirtual charAt : (I)C
    //   946: invokevirtual append : (C)Ljava/lang/StringBuilder;
    //   949: pop
    //   950: iload_2
    //   951: ifeq -> 1364
    //   954: goto -> 961
    //   957: invokestatic a : (Ljava/lang/Throwable;)Ljava/lang/Throwable;
    //   960: athrow
    //   961: aload_3
    //   962: getstatic burp/Zbow.Zr : Ljava/lang/String;
    //   965: getstatic burp/Zr8s.Zt : Ljava/lang/Object;
    //   968: checkcast java/math/BigInteger
    //   971: invokevirtual intValue : ()I
    //   974: bipush #32
    //   976: irem
    //   977: invokestatic abs : (I)I
    //   980: invokevirtual charAt : (I)C
    //   983: invokevirtual append : (C)Ljava/lang/StringBuilder;
    //   986: pop
    //   987: iload_2
    //   988: ifeq -> 1364
    //   991: goto -> 998
    //   994: invokestatic a : (Ljava/lang/Throwable;)Ljava/lang/Throwable;
    //   997: athrow
    //   998: aload_3
    //   999: getstatic burp/Zxjm.ZG : Ljava/lang/String;
    //   1002: getstatic burp/Zxd0.Za : Ljava/lang/Object;
    //   1005: checkcast java/math/BigInteger
    //   1008: invokevirtual intValue : ()I
    //   1011: bipush #32
    //   1013: irem
    //   1014: invokestatic abs : (I)I
    //   1017: invokevirtual charAt : (I)C
    //   1020: invokevirtual append : (C)Ljava/lang/StringBuilder;
    //   1023: pop
    //   1024: iload_2
    //   1025: ifeq -> 1364
    //   1028: goto -> 1035
    //   1031: invokestatic a : (Ljava/lang/Throwable;)Ljava/lang/Throwable;
    //   1034: athrow
    //   1035: aload_3
    //   1036: getstatic burp/Zgb9.Zk : Ljava/lang/String;
    //   1039: getstatic burp/Zrx5.ZE : Ljava/lang/Object;
    //   1042: checkcast java/math/BigInteger
    //   1045: invokevirtual intValue : ()I
    //   1048: bipush #32
    //   1050: irem
    //   1051: invokestatic abs : (I)I
    //   1054: invokevirtual charAt : (I)C
    //   1057: invokevirtual append : (C)Ljava/lang/StringBuilder;
    //   1060: pop
    //   1061: iload_2
    //   1062: ifeq -> 1364
    //   1065: goto -> 1072
    //   1068: invokestatic a : (Ljava/lang/Throwable;)Ljava/lang/Throwable;
    //   1071: athrow
    //   1072: aload_3
    //   1073: getstatic burp/Zzou.ZN : Ljava/lang/String;
    //   1076: getstatic burp/Zl2q.Zg : Ljava/lang/Object;
    //   1079: checkcast java/math/BigInteger
    //   1082: invokevirtual intValue : ()I
    //   1085: bipush #32
    //   1087: irem
    //   1088: invokestatic abs : (I)I
    //   1091: invokevirtual charAt : (I)C
    //   1094: invokevirtual append : (C)Ljava/lang/StringBuilder;
    //   1097: pop
    //   1098: iload_2
    //   1099: ifeq -> 1364
    //   1102: goto -> 1109
    //   1105: invokestatic a : (Ljava/lang/Throwable;)Ljava/lang/Throwable;
    //   1108: athrow
    //   1109: aload_3
    //   1110: getstatic burp/Zrp3.Zf : Ljava/lang/String;
    //   1113: getstatic burp/Zgds.Z_ : Ljava/lang/Object;
    //   1116: checkcast java/math/BigInteger
    //   1119: invokevirtual intValue : ()I
    //   1122: bipush #32
    //   1124: irem
    //   1125: invokestatic abs : (I)I
    //   1128: invokevirtual charAt : (I)C
    //   1131: invokevirtual append : (C)Ljava/lang/StringBuilder;
    //   1134: pop
    //   1135: iload_2
    //   1136: ifeq -> 1364
    //   1139: goto -> 1146
    //   1142: invokestatic a : (Ljava/lang/Throwable;)Ljava/lang/Throwable;
    //   1145: athrow
    //   1146: aload_3
    //   1147: getstatic burp/Zz80.Ze : Ljava/lang/String;
    //   1150: getstatic burp/Zxoa.Zr : Ljava/lang/Object;
    //   1153: checkcast java/math/BigInteger
    //   1156: invokevirtual intValue : ()I
    //   1159: bipush #32
    //   1161: irem
    //   1162: invokestatic abs : (I)I
    //   1165: invokevirtual charAt : (I)C
    //   1168: invokevirtual append : (C)Ljava/lang/StringBuilder;
    //   1171: pop
    //   1172: iload_2
    //   1173: ifeq -> 1364
    //   1176: goto -> 1183
    //   1179: invokestatic a : (Ljava/lang/Throwable;)Ljava/lang/Throwable;
    //   1182: athrow
    //   1183: aload_3
    //   1184: getstatic burp/Zejj.ZQ : Ljava/lang/String;
    //   1187: getstatic burp/Zod.ZP : Ljava/lang/Object;
    //   1190: checkcast java/math/BigInteger
    //   1193: invokevirtual intValue : ()I
    //   1196: bipush #32
    //   1198: irem
    //   1199: invokestatic abs : (I)I
    //   1202: invokevirtual charAt : (I)C
    //   1205: invokevirtual append : (C)Ljava/lang/StringBuilder;
    //   1208: pop
    //   1209: iload_2
    //   1210: ifeq -> 1364
    //   1213: goto -> 1220
    //   1216: invokestatic a : (Ljava/lang/Throwable;)Ljava/lang/Throwable;
    //   1219: athrow
    //   1220: aload_3
    //   1221: getstatic burp/Zsx6.ZJ : Ljava/lang/String;
    //   1224: getstatic burp/Zeyt.ZR : Ljava/lang/Object;
    //   1227: checkcast java/math/BigInteger
    //   1230: invokevirtual intValue : ()I
    //   1233: bipush #32
    //   1235: irem
    //   1236: invokestatic abs : (I)I
    //   1239: invokevirtual charAt : (I)C
    //   1242: invokevirtual append : (C)Ljava/lang/StringBuilder;
    //   1245: pop
    //   1246: iload_2
    //   1247: ifeq -> 1364
    //   1250: goto -> 1257
    //   1253: invokestatic a : (Ljava/lang/Throwable;)Ljava/lang/Throwable;
    //   1256: athrow
    //   1257: aload_3
    //   1258: getstatic burp/Zmou.ZP : Ljava/lang/String;
    //   1261: getstatic burp/Zegk.ZR : Ljava/lang/Object;
    //   1264: checkcast java/math/BigInteger
    //   1267: invokevirtual intValue : ()I
    //   1270: bipush #32
    //   1272: irem
    //   1273: invokestatic abs : (I)I
    //   1276: invokevirtual charAt : (I)C
    //   1279: invokevirtual append : (C)Ljava/lang/StringBuilder;
    //   1282: pop
    //   1283: iload_2
    //   1284: ifeq -> 1364
    //   1287: goto -> 1294
    //   1290: invokestatic a : (Ljava/lang/Throwable;)Ljava/lang/Throwable;
    //   1293: athrow
    //   1294: aload_3
    //   1295: getstatic burp/Zefm.ZK : Ljava/lang/String;
    //   1298: getstatic burp/Zss6.ZG : Ljava/lang/Object;
    //   1301: checkcast java/math/BigInteger
    //   1304: invokevirtual intValue : ()I
    //   1307: bipush #32
    //   1309: irem
    //   1310: invokestatic abs : (I)I
    //   1313: invokevirtual charAt : (I)C
    //   1316: invokevirtual append : (C)Ljava/lang/StringBuilder;
    //   1319: pop
    //   1320: iload_2
    //   1321: ifeq -> 1364
    //   1324: goto -> 1331
    //   1327: invokestatic a : (Ljava/lang/Throwable;)Ljava/lang/Throwable;
    //   1330: athrow
    //   1331: aload_3
    //   1332: getstatic burp/Zec_.Zv : Ljava/lang/String;
    //   1335: getstatic burp/Ze69.ZH : Ljava/lang/Object;
    //   1338: checkcast java/math/BigInteger
    //   1341: invokevirtual intValue : ()I
    //   1344: bipush #32
    //   1346: irem
    //   1347: invokestatic abs : (I)I
    //   1350: invokevirtual charAt : (I)C
    //   1353: invokevirtual append : (C)Ljava/lang/StringBuilder;
    //   1356: pop
    //   1357: goto -> 1364
    //   1360: invokestatic a : (Ljava/lang/Throwable;)Ljava/lang/Throwable;
    //   1363: athrow
    //   1364: iinc #4, 1
    //   1367: iload_2
    //   1368: ifeq -> 33
    //   1371: aload_3
    //   1372: invokevirtual toString : ()Ljava/lang/String;
    //   1375: putstatic burp/Zsxo.ZW : Ljava/lang/String;
    //   1378: sipush #-1348
    //   1381: getstatic burp/Zg1k.ZG : Ljava/lang/Object;
    //   1384: checkcast java/math/BigInteger
    //   1387: getstatic burp/Zmt_.Zl : Ljava/lang/Object;
    //   1390: checkcast java/math/BigInteger
    //   1393: invokevirtual add : (Ljava/math/BigInteger;)Ljava/math/BigInteger;
    //   1396: putstatic burp/Zgii.ZD : Ljava/lang/Object;
    //   1399: sipush #5889
    //   1402: invokestatic a : (II)Ljava/lang/String;
    //   1405: iconst_1
    //   1406: ldc burp/Zsby
    //   1408: invokevirtual getClassLoader : ()Ljava/lang/ClassLoader;
    //   1411: invokestatic forName : (Ljava/lang/String;ZLjava/lang/ClassLoader;)Ljava/lang/Class;
    //   1414: invokevirtual getDeclaredFields : ()[Ljava/lang/reflect/Field;
    //   1417: astore #4
    //   1419: aload #4
    //   1421: arraylength
    //   1422: istore #5
    //   1424: iconst_0
    //   1425: istore #6
    //   1427: iload #6
    //   1429: iload #5
    //   1431: if_icmpge -> 1569
    //   1434: aload #4
    //   1436: iload #6
    //   1438: aaload
    //   1439: astore #7
    //   1441: aload #7
    //   1443: invokevirtual getModifiers : ()I
    //   1446: invokestatic isStatic : (I)Z
    //   1449: ifne -> 1459
    //   1452: goto -> 1562
    //   1455: invokestatic a : (Ljava/lang/Throwable;)Ljava/lang/Throwable;
    //   1458: athrow
    //   1459: aload #7
    //   1461: invokevirtual getType : ()Ljava/lang/Class;
    //   1464: astore #8
    //   1466: aload #8
    //   1468: ifnull -> 1549
    //   1471: aload #8
    //   1473: invokevirtual isPrimitive : ()Z
    //   1476: ifne -> 1549
    //   1479: goto -> 1486
    //   1482: invokestatic a : (Ljava/lang/Throwable;)Ljava/lang/Throwable;
    //   1485: athrow
    //   1486: aload #8
    //   1488: invokevirtual getPackage : ()Ljava/lang/Package;
    //   1491: ifnull -> 1549
    //   1494: goto -> 1501
    //   1497: invokestatic a : (Ljava/lang/Throwable;)Ljava/lang/Throwable;
    //   1500: athrow
    //   1501: aload #8
    //   1503: invokevirtual getPackage : ()Ljava/lang/Package;
    //   1506: invokevirtual getName : ()Ljava/lang/String;
    //   1509: ifnull -> 1549
    //   1512: goto -> 1519
    //   1515: invokestatic a : (Ljava/lang/Throwable;)Ljava/lang/Throwable;
    //   1518: athrow
    //   1519: aload #8
    //   1521: invokevirtual getPackage : ()Ljava/lang/Package;
    //   1524: invokevirtual getName : ()Ljava/lang/String;
    //   1527: sipush #-1360
    //   1530: sipush #-14674
    //   1533: invokestatic a : (II)Ljava/lang/String;
    //   1536: invokevirtual startsWith : (Ljava/lang/String;)Z
    //   1539: ifne -> 1549
    //   1542: goto -> 1549
    //   1545: invokestatic a : (Ljava/lang/Throwable;)Ljava/lang/Throwable;
    //   1548: athrow
    //   1549: aload #7
    //   1551: iconst_1
    //   1552: invokevirtual setAccessible : (Z)V
    //   1555: aload #7
    //   1557: aconst_null
    //   1558: invokevirtual get : (Ljava/lang/Object;)Ljava/lang/Object;
    //   1561: pop
    //   1562: iinc #6, 1
    //   1565: iload_2
    //   1566: ifeq -> 1427
    //   1569: sipush #-1347
    //   1572: sipush #27831
    //   1575: invokestatic a : (II)Ljava/lang/String;
    //   1578: invokestatic forName : (Ljava/lang/String;)Ljava/lang/Class;
    //   1581: invokevirtual getDeclaredMethods : ()[Ljava/lang/reflect/Method;
    //   1584: astore #4
    //   1586: aload #4
    //   1588: arraylength
    //   1589: istore #5
    //   1591: iconst_0
    //   1592: istore #6
    //   1594: iload #6
    //   1596: iload #5
    //   1598: if_icmpge -> 1710
    //   1601: aload #4
    //   1603: iload #6
    //   1605: aaload
    //   1606: astore #7
    //   1608: aload #7
    //   1610: invokevirtual getParameterTypes : ()[Ljava/lang/Class;
    //   1613: pop
    //   1614: aload #7
    //   1616: invokevirtual getModifiers : ()I
    //   1619: invokestatic isStatic : (I)Z
    //   1622: ifeq -> 1696
    //   1625: aload #7
    //   1627: invokevirtual getParameterTypes : ()[Ljava/lang/Class;
    //   1630: arraylength
    //   1631: iconst_2
    //   1632: if_icmpne -> 1696
    //   1635: goto -> 1642
    //   1638: invokestatic a : (Ljava/lang/Throwable;)Ljava/lang/Throwable;
    //   1641: athrow
    //   1642: aload #7
    //   1644: invokevirtual getReturnType : ()Ljava/lang/Class;
    //   1647: getstatic java/lang/Boolean.TYPE : Ljava/lang/Class;
    //   1650: if_acmpne -> 1696
    //   1653: goto -> 1660
    //   1656: invokestatic a : (Ljava/lang/Throwable;)Ljava/lang/Throwable;
    //   1659: athrow
    //   1660: aload #7
    //   1662: iconst_1
    //   1663: invokevirtual setAccessible : (Z)V
    //   1666: aload #7
    //   1668: aconst_null
    //   1669: iconst_2
    //   1670: anewarray java/lang/Object
    //   1673: dup
    //   1674: iconst_0
    //   1675: aload_0
    //   1676: aastore
    //   1677: dup
    //   1678: iconst_1
    //   1679: aload_1
    //   1680: aastore
    //   1681: invokevirtual invoke : (Ljava/lang/Object;[Ljava/lang/Object;)Ljava/lang/Object;
    //   1684: pop
    //   1685: iload_2
    //   1686: ifeq -> 1710
    //   1689: goto -> 1696
    //   1692: invokestatic a : (Ljava/lang/Throwable;)Ljava/lang/Throwable;
    //   1695: athrow
    //   1696: iinc #6, 1
    //   1699: iload_2
    //   1700: ifeq -> 1594
    //   1703: goto -> 1710
    //   1706: invokestatic a : (Ljava/lang/Throwable;)Ljava/lang/Throwable;
    //   1709: athrow
    //   1710: sipush #-1359
    //   1713: sipush #-28746
    //   1716: invokestatic a : (II)Ljava/lang/String;
    //   1719: iconst_1
    //   1720: ldc burp/Zl22
    //   1722: invokevirtual getClassLoader : ()Ljava/lang/ClassLoader;
    //   1725: invokestatic forName : (Ljava/lang/String;ZLjava/lang/ClassLoader;)Ljava/lang/Class;
    //   1728: invokevirtual getDeclaredFields : ()[Ljava/lang/reflect/Field;
    //   1731: astore #4
    //   1733: aload #4
    //   1735: arraylength
    //   1736: istore #5
    //   1738: iconst_0
    //   1739: istore #6
    //   1741: iload #6
    //   1743: iload #5
    //   1745: if_icmpge -> 1883
    //   1748: aload #4
    //   1750: iload #6
    //   1752: aaload
    //   1753: astore #7
    //   1755: aload #7
    //   1757: invokevirtual getModifiers : ()I
    //   1760: invokestatic isStatic : (I)Z
    //   1763: ifne -> 1773
    //   1766: goto -> 1876
    //   1769: invokestatic a : (Ljava/lang/Throwable;)Ljava/lang/Throwable;
    //   1772: athrow
    //   1773: aload #7
    //   1775: invokevirtual getType : ()Ljava/lang/Class;
    //   1778: astore #8
    //   1780: aload #8
    //   1782: ifnull -> 1863
    //   1785: aload #8
    //   1787: invokevirtual isPrimitive : ()Z
    //   1790: ifne -> 1863
    //   1793: goto -> 1800
    //   1796: invokestatic a : (Ljava/lang/Throwable;)Ljava/lang/Throwable;
    //   1799: athrow
    //   1800: aload #8
    //   1802: invokevirtual getPackage : ()Ljava/lang/Package;
    //   1805: ifnull -> 1863
    //   1808: goto -> 1815
    //   1811: invokestatic a : (Ljava/lang/Throwable;)Ljava/lang/Throwable;
    //   1814: athrow
    //   1815: aload #8
    //   1817: invokevirtual getPackage : ()Ljava/lang/Package;
    //   1820: invokevirtual getName : ()Ljava/lang/String;
    //   1823: ifnull -> 1863
    //   1826: goto -> 1833
    //   1829: invokestatic a : (Ljava/lang/Throwable;)Ljava/lang/Throwable;
    //   1832: athrow
    //   1833: aload #8
    //   1835: invokevirtual getPackage : ()Ljava/lang/Package;
    //   1838: invokevirtual getName : ()Ljava/lang/String;
    //   1841: sipush #-1357
    //   1844: sipush #-3347
    //   1847: invokestatic a : (II)Ljava/lang/String;
    //   1850: invokevirtual startsWith : (Ljava/lang/String;)Z
    //   1853: ifne -> 1863
    //   1856: goto -> 1863
    //   1859: invokestatic a : (Ljava/lang/Throwable;)Ljava/lang/Throwable;
    //   1862: athrow
    //   1863: aload #7
    //   1865: iconst_1
    //   1866: invokevirtual setAccessible : (Z)V
    //   1869: aload #7
    //   1871: aconst_null
    //   1872: invokevirtual get : (Ljava/lang/Object;)Ljava/lang/Object;
    //   1875: pop
    //   1876: iinc #6, 1
    //   1879: iload_2
    //   1880: ifeq -> 1741
    //   1883: sipush #-1346
    //   1886: sipush #23247
    //   1889: invokestatic a : (II)Ljava/lang/String;
    //   1892: invokestatic forName : (Ljava/lang/String;)Ljava/lang/Class;
    //   1895: invokevirtual getDeclaredMethods : ()[Ljava/lang/reflect/Method;
    //   1898: astore #4
    //   1900: aload #4
    //   1902: arraylength
    //   1903: istore #5
    //   1905: iconst_0
    //   1906: istore #6
    //   1908: iload #6
    //   1910: iload #5
    //   1912: if_icmpge -> 2045
    //   1915: aload #4
    //   1917: iload #6
    //   1919: aaload
    //   1920: astore #7
    //   1922: aload #7
    //   1924: invokevirtual getParameterTypes : ()[Ljava/lang/Class;
    //   1927: pop
    //   1928: aload #7
    //   1930: invokevirtual getModifiers : ()I
    //   1933: invokestatic isStatic : (I)Z
    //   1936: ifeq -> 2031
    //   1939: aload #7
    //   1941: invokevirtual getParameterTypes : ()[Ljava/lang/Class;
    //   1944: arraylength
    //   1945: iconst_2
    //   1946: if_icmpne -> 2031
    //   1949: goto -> 1956
    //   1952: invokestatic a : (Ljava/lang/Throwable;)Ljava/lang/Throwable;
    //   1955: athrow
    //   1956: aload #7
    //   1958: invokevirtual getReturnType : ()Ljava/lang/Class;
    //   1961: getstatic java/lang/Void.TYPE : Ljava/lang/Class;
    //   1964: invokevirtual equals : (Ljava/lang/Object;)Z
    //   1967: ifeq -> 2031
    //   1970: goto -> 1977
    //   1973: invokestatic a : (Ljava/lang/Throwable;)Ljava/lang/Throwable;
    //   1976: athrow
    //   1977: aload #7
    //   1979: iconst_1
    //   1980: invokevirtual setAccessible : (Z)V
    //   1983: aload #7
    //   1985: aconst_null
    //   1986: iconst_2
    //   1987: anewarray java/lang/Object
    //   1990: dup
    //   1991: iconst_0
    //   1992: aload_0
    //   1993: aastore
    //   1994: dup
    //   1995: iconst_1
    //   1996: aload_1
    //   1997: ifnonnull -> 2015
    //   2000: goto -> 2007
    //   2003: invokestatic a : (Ljava/lang/Throwable;)Ljava/lang/Throwable;
    //   2006: athrow
    //   2007: aload_1
    //   2008: goto -> 2022
    //   2011: invokestatic a : (Ljava/lang/Throwable;)Ljava/lang/Throwable;
    //   2014: athrow
    //   2015: aload_1
    //   2016: checkcast [B
    //   2019: invokevirtual clone : ()Ljava/lang/Object;
    //   2022: aastore
    //   2023: invokevirtual invoke : (Ljava/lang/Object;[Ljava/lang/Object;)Ljava/lang/Object;
    //   2026: pop
    //   2027: iload_2
    //   2028: ifeq -> 2045
    //   2031: iinc #6, 1
    //   2034: iload_2
    //   2035: ifeq -> 1908
    //   2038: goto -> 2045
    //   2041: invokestatic a : (Ljava/lang/Throwable;)Ljava/lang/Throwable;
    //   2044: athrow
    //   2045: iconst_0
    //   2046: istore #4
    //   2048: sipush #-1351
    //   2051: sipush #30619
    //   2054: invokestatic a : (II)Ljava/lang/String;
    //   2057: iconst_1
    //   2058: ldc burp/Zlsw
    //   2060: invokevirtual getClassLoader : ()Ljava/lang/ClassLoader;
    //   2063: invokestatic forName : (Ljava/lang/String;ZLjava/lang/ClassLoader;)Ljava/lang/Class;
    //   2066: invokevirtual getDeclaredFields : ()[Ljava/lang/reflect/Field;
    //   2069: astore #5
    //   2071: aload #5
    //   2073: arraylength
    //   2074: istore #6
    //   2076: iconst_0
    //   2077: istore #7
    //   2079: iload #7
    //   2081: iload #6
    //   2083: if_icmpge -> 2221
    //   2086: aload #5
    //   2088: iload #7
    //   2090: aaload
    //   2091: astore #8
    //   2093: aload #8
    //   2095: invokevirtual getModifiers : ()I
    //   2098: invokestatic isStatic : (I)Z
    //   2101: ifne -> 2111
    //   2104: goto -> 2214
    //   2107: invokestatic a : (Ljava/lang/Throwable;)Ljava/lang/Throwable;
    //   2110: athrow
    //   2111: aload #8
    //   2113: invokevirtual getType : ()Ljava/lang/Class;
    //   2116: astore #9
    //   2118: aload #9
    //   2120: ifnull -> 2201
    //   2123: aload #9
    //   2125: invokevirtual isPrimitive : ()Z
    //   2128: ifne -> 2201
    //   2131: goto -> 2138
    //   2134: invokestatic a : (Ljava/lang/Throwable;)Ljava/lang/Throwable;
    //   2137: athrow
    //   2138: aload #9
    //   2140: invokevirtual getPackage : ()Ljava/lang/Package;
    //   2143: ifnull -> 2201
    //   2146: goto -> 2153
    //   2149: invokestatic a : (Ljava/lang/Throwable;)Ljava/lang/Throwable;
    //   2152: athrow
    //   2153: aload #9
    //   2155: invokevirtual getPackage : ()Ljava/lang/Package;
    //   2158: invokevirtual getName : ()Ljava/lang/String;
    //   2161: ifnull -> 2201
    //   2164: goto -> 2171
    //   2167: invokestatic a : (Ljava/lang/Throwable;)Ljava/lang/Throwable;
    //   2170: athrow
    //   2171: aload #9
    //   2173: invokevirtual getPackage : ()Ljava/lang/Package;
    //   2176: invokevirtual getName : ()Ljava/lang/String;
    //   2179: sipush #-1357
    //   2182: sipush #-3347
    //   2185: invokestatic a : (II)Ljava/lang/String;
    //   2188: invokevirtual startsWith : (Ljava/lang/String;)Z
    //   2191: ifne -> 2201
    //   2194: goto -> 2201
    //   2197: invokestatic a : (Ljava/lang/Throwable;)Ljava/lang/Throwable;
    //   2200: athrow
    //   2201: aload #8
    //   2203: iconst_1
    //   2204: invokevirtual setAccessible : (Z)V
    //   2207: aload #8
    //   2209: aconst_null
    //   2210: invokevirtual get : (Ljava/lang/Object;)Ljava/lang/Object;
    //   2213: pop
    //   2214: iinc #7, 1
    //   2217: iload_2
    //   2218: ifeq -> 2079
    //   2221: sipush #-1356
    //   2224: sipush #29130
    //   2227: invokestatic a : (II)Ljava/lang/String;
    //   2230: invokestatic forName : (Ljava/lang/String;)Ljava/lang/Class;
    //   2233: invokevirtual getDeclaredMethods : ()[Ljava/lang/reflect/Method;
    //   2236: astore #5
    //   2238: aload #5
    //   2240: arraylength
    //   2241: istore #6
    //   2243: iconst_0
    //   2244: istore #7
    //   2246: iload #7
    //   2248: iload #6
    //   2250: if_icmpge -> 2387
    //   2253: aload #5
    //   2255: iload #7
    //   2257: aaload
    //   2258: astore #8
    //   2260: aload #8
    //   2262: invokevirtual getParameterTypes : ()[Ljava/lang/Class;
    //   2265: pop
    //   2266: aload #8
    //   2268: invokevirtual getModifiers : ()I
    //   2271: invokestatic isStatic : (I)Z
    //   2274: ifeq -> 2373
    //   2277: aload #8
    //   2279: invokevirtual getParameterTypes : ()[Ljava/lang/Class;
    //   2282: arraylength
    //   2283: iconst_2
    //   2284: if_icmpne -> 2373
    //   2287: goto -> 2294
    //   2290: invokestatic a : (Ljava/lang/Throwable;)Ljava/lang/Throwable;
    //   2293: athrow
    //   2294: aload #8
    //   2296: invokevirtual getReturnType : ()Ljava/lang/Class;
    //   2299: getstatic java/lang/Boolean.TYPE : Ljava/lang/Class;
    //   2302: if_acmpne -> 2373
    //   2305: goto -> 2312
    //   2308: invokestatic a : (Ljava/lang/Throwable;)Ljava/lang/Throwable;
    //   2311: athrow
    //   2312: aload #8
    //   2314: iconst_1
    //   2315: invokevirtual setAccessible : (Z)V
    //   2318: aload #8
    //   2320: aconst_null
    //   2321: iconst_2
    //   2322: anewarray java/lang/Object
    //   2325: dup
    //   2326: iconst_0
    //   2327: aload_0
    //   2328: aastore
    //   2329: dup
    //   2330: iconst_1
    //   2331: aload_1
    //   2332: ifnonnull -> 2350
    //   2335: goto -> 2342
    //   2338: invokestatic a : (Ljava/lang/Throwable;)Ljava/lang/Throwable;
    //   2341: athrow
    //   2342: aload_1
    //   2343: goto -> 2357
    //   2346: invokestatic a : (Ljava/lang/Throwable;)Ljava/lang/Throwable;
    //   2349: athrow
    //   2350: aload_1
    //   2351: checkcast [B
    //   2354: invokevirtual clone : ()Ljava/lang/Object;
    //   2357: aastore
    //   2358: invokevirtual invoke : (Ljava/lang/Object;[Ljava/lang/Object;)Ljava/lang/Object;
    //   2361: checkcast java/lang/Boolean
    //   2364: invokevirtual booleanValue : ()Z
    //   2367: istore #4
    //   2369: iload_2
    //   2370: ifeq -> 2387
    //   2373: iinc #7, 1
    //   2376: iload_2
    //   2377: ifeq -> 2246
    //   2380: goto -> 2387
    //   2383: invokestatic a : (Ljava/lang/Throwable;)Ljava/lang/Throwable;
    //   2386: athrow
    //   2387: iload #4
    //   2389: ireturn
    //   2390: astore_3
    //   2391: new java/lang/Exception
    //   2394: dup
    //   2395: aload_3
    //   2396: invokevirtual getMessage : ()Ljava/lang/String;
    //   2399: invokespecial <init> : (Ljava/lang/String;)V
    //   2402: athrow
    // Exception table:
    //   from	to	target	type
    //   4	2389	2390	java/lang/Throwable
    //   40	214	217	java/lang/Throwable
    //   184	251	254	java/lang/Throwable
    //   221	288	291	java/lang/Throwable
    //   258	325	328	java/lang/Throwable
    //   295	362	365	java/lang/Throwable
    //   332	399	402	java/lang/Throwable
    //   369	436	439	java/lang/Throwable
    //   406	473	476	java/lang/Throwable
    //   443	510	513	java/lang/Throwable
    //   480	547	550	java/lang/Throwable
    //   517	584	587	java/lang/Throwable
    //   554	621	624	java/lang/Throwable
    //   591	658	661	java/lang/Throwable
    //   628	695	698	java/lang/Throwable
    //   665	732	735	java/lang/Throwable
    //   702	769	772	java/lang/Throwable
    //   739	806	809	java/lang/Throwable
    //   776	843	846	java/lang/Throwable
    //   813	880	883	java/lang/Throwable
    //   850	917	920	java/lang/Throwable
    //   887	954	957	java/lang/Throwable
    //   924	991	994	java/lang/Throwable
    //   961	1028	1031	java/lang/Throwable
    //   998	1065	1068	java/lang/Throwable
    //   1035	1102	1105	java/lang/Throwable
    //   1072	1139	1142	java/lang/Throwable
    //   1109	1176	1179	java/lang/Throwable
    //   1146	1213	1216	java/lang/Throwable
    //   1183	1250	1253	java/lang/Throwable
    //   1220	1287	1290	java/lang/Throwable
    //   1257	1324	1327	java/lang/Throwable
    //   1294	1357	1360	java/lang/Throwable
    //   1441	1455	1455	java/lang/Throwable
    //   1466	1479	1482	java/lang/Throwable
    //   1471	1494	1497	java/lang/Throwable
    //   1486	1512	1515	java/lang/Throwable
    //   1501	1542	1545	java/lang/Throwable
    //   1608	1635	1638	java/lang/Throwable
    //   1625	1653	1656	java/lang/Throwable
    //   1642	1689	1692	java/lang/Throwable
    //   1660	1703	1706	java/lang/Throwable
    //   1755	1769	1769	java/lang/Throwable
    //   1780	1793	1796	java/lang/Throwable
    //   1785	1808	1811	java/lang/Throwable
    //   1800	1826	1829	java/lang/Throwable
    //   1815	1856	1859	java/lang/Throwable
    //   1922	1949	1952	java/lang/Throwable
    //   1939	1970	1973	java/lang/Throwable
    //   1956	2000	2003	java/lang/Throwable
    //   1977	2011	2011	java/lang/Throwable
    //   2022	2038	2041	java/lang/Throwable
    //   2093	2107	2107	java/lang/Throwable
    //   2118	2131	2134	java/lang/Throwable
    //   2123	2146	2149	java/lang/Throwable
    //   2138	2164	2167	java/lang/Throwable
    //   2153	2194	2197	java/lang/Throwable
    //   2260	2287	2290	java/lang/Throwable
    //   2277	2305	2308	java/lang/Throwable
    //   2294	2335	2338	java/lang/Throwable
    //   2312	2346	2346	java/lang/Throwable
    //   2369	2380	2383	java/lang/Throwable
  }
  
  static void ZE(Object[] paramArrayOfObject, Object paramObject) throws Throwable {}
  
  static void Zq(Object paramObject) {
    Zzok.ZC = a(-1355, 13292);
    Zzok.ZY = new BigInteger(a(-1345, -32137));
    boolean bool = Zt2e.ZN();
    try {
      try {
        if (Zmji.Zs.charAt(Math.abs(((BigInteger)Zme.Zd).intValue() % 32)) > Zb9h.Zf.charAt(Math.abs(((BigInteger)Zkf9.ZX).intValue() % 32))) {
          try {
            Zxtc.ZD(Class.forName(a(-1358, 25681)));
            if (!bool)
              Ztte.ZN(Class.forName(a(-1354, -25043))); 
          } catch (Throwable throwable) {
            throw a(null);
          } 
          return;
        } 
      } catch (Throwable throwable) {
        throw a(null);
      } 
      Ztte.ZN(Class.forName(a(-1354, -25043)));
    } catch (Throwable throwable) {}
  }
  
  static {
    // Byte code:
    //   0: bipush #13
    //   2: anewarray java/lang/String
    //   5: astore #5
    //   7: iconst_0
    //   8: istore_3
    //   9: ldc 'yÂ¡Â°V2aÂÂŸx8Â°z\Â¦Â(Â(Â™Â³Ã¶Ã½Ã·ÃÂ·ÃµÂ‘XP\\t+Ã‘Ã“Â±Jp4Ã¥0 Â–Â°Â’Ã°[Âº%\\n7Â‹ÃÂ¶}Ã¤4Ã¸kcÃŸÂ–Ã†Ã†Ã‡Ã›gÃ³Ã£\\bÃ¶4UÂ¶Ã¬Â¼}\\tf\z FÂ„)Â¿PÃ«Â¼Ã¶Â¾Ã¨aÂ–\\t|89ÂŒÃ—Â˜B\\bÃ¢Ã¼ÃªmÃ„Ã†x\\bÃ–Â“lÃ¹Â½yÃœÃMÂ«Ã8~mÃ¨Ã‘Ã†Ã°Â˜ÃÃ•_Ã…ÂŸÃµÃ¬Ã›5Ã«Ã·Â¢~7Â“?Â“ÃšÂƒÂ·Ã‰Â£Â•xÃ.zÂ¼:Ã½jÃ™iÃ™Ã¶ÂU1Â€Â¥\\nH*Â8Â¡Â“Ã¨|Â¼Â“(Â‚ÃŸÂ–ÂŸÂµÂ—|'
    //   11: dup
    //   12: astore_2
    //   13: invokevirtual length : ()I
    //   16: istore #4
    //   18: bipush #32
    //   20: istore_1
    //   21: iconst_m1
    //   22: istore_0
    //   23: bipush #41
    //   25: iinc #0, 1
    //   28: aload_2
    //   29: iload_0
    //   30: dup
    //   31: iload_1
    //   32: iadd
    //   33: invokevirtual substring : (II)Ljava/lang/String;
    //   36: iconst_m1
    //   37: goto -> 143
    //   40: aload #5
    //   42: swap
    //   43: iload_3
    //   44: iinc #3, 1
    //   47: swap
    //   48: aastore
    //   49: iload_0
    //   50: iload_1
    //   51: iadd
    //   52: dup
    //   53: istore_0
    //   54: iload #4
    //   56: if_icmpge -> 68
    //   59: aload_2
    //   60: iload_0
    //   61: invokevirtual charAt : (I)C
    //   64: istore_1
    //   65: goto -> 23
    //   68: ldc 'Â¶~D`ÂœnÃÂƒ\\t?Â°uÂ¹ÂºU`'
    //   70: dup
    //   71: astore_2
    //   72: invokevirtual length : ()I
    //   75: istore #4
    //   77: bipush #9
    //   79: istore_1
    //   80: iconst_m1
    //   81: istore_0
    //   82: bipush #9
    //   84: iinc #0, 1
    //   87: aload_2
    //   88: iload_0
    //   89: dup
    //   90: iload_1
    //   91: iadd
    //   92: invokevirtual substring : (II)Ljava/lang/String;
    //   95: iconst_0
    //   96: goto -> 143
    //   99: aload #5
    //   101: swap
    //   102: iload_3
    //   103: iinc #3, 1
    //   106: swap
    //   107: aastore
    //   108: iload_0
    //   109: iload_1
    //   110: iadd
    //   111: dup
    //   112: istore_0
    //   113: iload #4
    //   115: if_icmpge -> 127
    //   118: aload_2
    //   119: iload_0
    //   120: invokevirtual charAt : (I)C
    //   123: istore_1
    //   124: goto -> 82
    //   127: aload #5
    //   129: putstatic burp/Zkco.a : [Ljava/lang/String;
    //   132: bipush #13
    //   134: anewarray java/lang/String
    //   137: putstatic burp/Zkco.b : [Ljava/lang/String;
    //   140: goto -> 300
    //   143: dup_x2
    //   144: pop
    //   145: invokevirtual toCharArray : ()[C
    //   148: dup_x1
    //   149: arraylength
    //   150: dup_x2
    //   151: pop
    //   152: iconst_0
    //   153: istore #6
    //   155: dup2_x1
    //   156: pop2
    //   157: dup_x2
    //   158: iconst_1
    //   159: if_icmpgt -> 260
    //   162: dup2
    //   163: swap
    //   164: iload #6
    //   166: dup2_x1
    //   167: caload
    //   168: swap
    //   169: iload #6
    //   171: bipush #7
    //   173: irem
    //   174: tableswitch default -> 242, 0 -> 212, 1 -> 217, 2 -> 222, 3 -> 227, 4 -> 232, 5 -> 237
    //   212: bipush #117
    //   214: goto -> 244
    //   217: bipush #49
    //   219: goto -> 244
    //   222: bipush #72
    //   224: goto -> 244
    //   227: bipush #10
    //   229: goto -> 244
    //   232: bipush #39
    //   234: goto -> 244
    //   237: bipush #47
    //   239: goto -> 244
    //   242: bipush #13
    //   244: ixor
    //   245: ixor
    //   246: i2c
    //   247: castore
    //   248: iinc #6, 1
    //   251: dup
    //   252: ifne -> 260
    //   255: dup2
    //   256: dup_x1
    //   257: goto -> 166
    //   260: dup2_x1
    //   261: pop2
    //   262: dup_x2
    //   263: iload #6
    //   265: if_icmpgt -> 162
    //   268: pop
    //   269: new java/lang/String
    //   272: dup_x1
    //   273: swap
    //   274: invokespecial <init> : ([C)V
    //   277: invokevirtual intern : ()Ljava/lang/String;
    //   280: swap
    //   281: pop
    //   282: swap
    //   283: tableswitch default -> 40, 0 -> 99
    //   300: new java/math/BigInteger
    //   303: dup
    //   304: bipush #32
    //   306: newarray byte
    //   308: dup
    //   309: iconst_0
    //   310: bipush #42
    //   312: bastore
    //   313: dup
    //   314: iconst_1
    //   315: bipush #-6
    //   317: bastore
    //   318: dup
    //   319: iconst_2
    //   320: bipush #-97
    //   322: bastore
    //   323: dup
    //   324: iconst_3
    //   325: bipush #84
    //   327: bastore
    //   328: dup
    //   329: iconst_4
    //   330: bipush #-22
    //   332: bastore
    //   333: dup
    //   334: iconst_5
    //   335: bipush #-43
    //   337: bastore
    //   338: dup
    //   339: bipush #6
    //   341: bipush #107
    //   343: bastore
    //   344: dup
    //   345: bipush #7
    //   347: bipush #-46
    //   349: bastore
    //   350: dup
    //   351: bipush #8
    //   353: bipush #127
    //   355: bastore
    //   356: dup
    //   357: bipush #9
    //   359: bipush #71
    //   361: bastore
    //   362: dup
    //   363: bipush #10
    //   365: bipush #64
    //   367: bastore
    //   368: dup
    //   369: bipush #11
    //   371: bipush #61
    //   373: bastore
    //   374: dup
    //   375: bipush #12
    //   377: bipush #13
    //   379: bastore
    //   380: dup
    //   381: bipush #13
    //   383: bipush #54
    //   385: bastore
    //   386: dup
    //   387: bipush #14
    //   389: bipush #-93
    //   391: bastore
    //   392: dup
    //   393: bipush #15
    //   395: bipush #-28
    //   397: bastore
    //   398: dup
    //   399: bipush #16
    //   401: bipush #92
    //   403: bastore
    //   404: dup
    //   405: bipush #17
    //   407: bipush #98
    //   409: bastore
    //   410: dup
    //   411: bipush #18
    //   413: bipush #-77
    //   415: bastore
    //   416: dup
    //   417: bipush #19
    //   419: bipush #25
    //   421: bastore
    //   422: dup
    //   423: bipush #20
    //   425: bipush #34
    //   427: bastore
    //   428: dup
    //   429: bipush #21
    //   431: bipush #63
    //   433: bastore
    //   434: dup
    //   435: bipush #22
    //   437: iconst_3
    //   438: bastore
    //   439: dup
    //   440: bipush #23
    //   442: bipush #52
    //   444: bastore
    //   445: dup
    //   446: bipush #24
    //   448: bipush #-45
    //   450: bastore
    //   451: dup
    //   452: bipush #25
    //   454: bipush #-96
    //   456: bastore
    //   457: dup
    //   458: bipush #26
    //   460: bipush #39
    //   462: bastore
    //   463: dup
    //   464: bipush #27
    //   466: iconst_0
    //   467: bastore
    //   468: dup
    //   469: bipush #28
    //   471: bipush #-69
    //   473: bastore
    //   474: dup
    //   475: bipush #29
    //   477: bipush #33
    //   479: bastore
    //   480: dup
    //   481: bipush #30
    //   483: bipush #-122
    //   485: bastore
    //   486: dup
    //   487: bipush #31
    //   489: bipush #12
    //   491: bastore
    //   492: invokespecial <init> : ([B)V
    //   495: putstatic burp/Zkco.Zg : Ljava/lang/Object;
    //   498: sipush #-1353
    //   501: sipush #-15066
    //   504: invokestatic a : (II)Ljava/lang/String;
    //   507: putstatic burp/Zkco.Zz : Ljava/lang/String;
    //   510: return
  }
  
  private static Throwable a(Throwable paramThrowable) {
    return paramThrowable;
  }
  
  private static String a(int paramInt1, int paramInt2) {
    int i = (paramInt1 ^ 0xFFFFFAB5) & 0xFFFF;
    if (b[i] == null) {
      char[] arrayOfChar = a[i].toCharArray();
      switch (arrayOfChar[0] & 0xFF) {
        case 0:
        
        case 1:
        
        case 2:
        
        case 3:
        
        case 4:
        
        case 5:
        
        case 6:
        
        case 7:
        
        case 8:
        
        case 9:
        
        case 10:
        
        case 11:
        
        case 12:
        
        case 13:
        
        case 14:
        
        case 15:
        
        case 16:
        
        case 17:
        
        case 18:
        
        case 19:
        
        case 20:
        
        case 21:
        
        case 22:
        
        case 23:
        
        case 24:
        
        case 25:
        
        case 26:
        
        case 27:
        
        case 28:
        
        case 29:
        
        case 30:
        
        case 31:
        
        case 32:
        
        case 33:
        
        case 34:
        
        case 35:
        
        case 36:
        
        case 37:
        
        case 38:
        
        case 39:
        
        case 40:
        
        case 41:
        
        case 42:
        
        case 43:
        
        case 44:
        
        case 45:
        
        case 46:
        
        case 47:
        
        case 48:
        
        case 49:
        
        case 50:
        
        case 51:
        
        case 52:
        
        case 53:
        
        case 54:
        
        case 55:
        
        case 56:
        
        case 57:
        
        case 58:
        
        case 59:
        
        case 60:
        
        case 61:
        
        case 62:
        
        case 63:
        
        case 64:
        
        case 65:
        
        case 66:
        
        case 67:
        
        case 68:
        
        case 69:
        
        case 70:
        
        case 71:
        
        case 72:
        
        case 73:
        
        case 74:
        
        case 75:
        
        case 76:
        
        case 77:
        
        case 78:
        
        case 79:
        
        case 80:
        
        case 81:
        
        case 82:
        
        case 83:
        
        case 84:
        
        case 85:
        
        case 86:
        
        case 87:
        
        case 88:
        
        case 89:
        
        case 90:
        
        case 91:
        
        case 92:
        
        case 93:
        
        case 94:
        
        case 95:
        
        case 96:
        
        case 97:
        
        case 98:
        
        case 99:
        
        case 100:
        
        case 101:
        
        case 102:
        
        case 103:
        
        case 104:
        
        case 105:
        
        case 106:
        
        case 107:
        
        case 108:
        
        case 109:
        
        case 110:
        
        case 111:
        
        case 112:
        
        case 113:
        
        case 114:
        
        case 115:
        
        case 116:
        
        case 117:
        
        case 118:
        
        case 119:
        
        case 120:
        
        case 121:
        
        case 122:
        
        case 123:
        
        case 124:
        
        case 125:
        
        case 126:
        
        case 127:
        
        case 128:
        
        case 129:
        
        case 130:
        
        case 131:
        
        case 132:
        
        case 133:
        
        case 134:
        
        case 135:
        
        case 136:
        
        case 137:
        
        case 138:
        
        case 139:
        
        case 140:
        
        case 141:
        
        case 142:
        
        case 143:
        
        case 144:
        
        case 145:
        
        case 146:
        
        case 147:
        
        case 148:
        
        case 149:
        
        case 150:
        
        case 151:
        
        case 152:
        
        case 153:
        
        case 154:
        
        case 155:
        
        case 156:
        
        case 157:
        
        case 158:
        
        case 159:
        
        case 160:
        
        case 161:
        
        case 162:
        
        case 163:
        
        case 164:
        
        case 165:
        
        case 166:
        
        case 167:
        
        case 168:
        
        case 169:
        
        case 170:
        
        case 171:
        
        case 172:
        
        case 173:
        
        case 174:
        
        case 175:
        
        case 176:
        
        case 177:
        
        case 178:
        
        case 179:
        
        case 180:
        
        case 181:
        
        case 182:
        
        case 183:
        
        case 184:
        
        case 185:
        
        case 186:
        
        case 187:
        
        case 188:
        
        case 189:
        
        case 190:
        
        case 191:
        
        case 192:
        
        case 193:
        
        case 194:
        
        case 195:
        
        case 196:
        
        case 197:
        
        case 198:
        
        case 199:
        
        case 200:
        
        case 201:
        
        case 202:
        
        case 203:
        
        case 204:
        
        case 205:
        
        case 206:
        
        case 207:
        
        case 208:
        
        case 209:
        
        case 210:
        
        case 211:
        
        case 212:
        
        case 213:
        
        case 214:
        
        case 215:
        
        case 216:
        
        case 217:
        
        case 218:
        
        case 219:
        
        case 220:
        
        case 221:
        
        case 222:
        
        case 223:
        
        case 224:
        
        case 225:
        
        case 226:
        
        case 227:
        
        case 228:
        
        case 229:
        
        case 230:
        
        case 231:
        
        case 232:
        
        case 233:
        
        case 234:
        
        case 235:
        
        case 236:
        
        case 237:
        
        case 238:
        
        case 239:
        
        case 240:
        
        case 241:
        
        case 242:
        
        case 243:
        
        case 244:
        
        case 245:
        
        case 246:
        
        case 247:
        
        case 248:
        
        case 249:
        
        case 250:
        
        case 251:
        
        case 252:
        
        case 253:
        
        case 254:
        
        default:
          break;
      } 
      byte b1 = 57;
      int j = (paramInt2 & 0xFF) - b1;
      if (j < 0)
        j += 256; 
      int k = ((paramInt2 & 0xFFFF) >>> 8) - b1;
      if (k < 0)
        k += 256; 
      for (byte b2 = 0; b2 < arrayOfChar.length; b2++) {
        int m = b2 % 2;
        if (m == 0) {
          arrayOfChar[b2] = (char)(arrayOfChar[b2] ^ j);
          j = ((j >>> 3 | j << 5) ^ arrayOfChar[b2]) & 0xFF;
        } else {
          arrayOfChar[b2] = (char)(arrayOfChar[b2] ^ k);
          k = ((k >>> 3 | k << 5) ^ arrayOfChar[b2]) & 0xFF;
        } 
      } 
      b[i] = (new String(arrayOfChar)).intern();
    } 
    return b[i];
  }
}


/* Location:              C:\Program Files\BurpSuitePro\burpsuite_pro.jar!\burp\Zkco.class
 * Java compiler version: 21 (65.0)
 * JD-Core Version:       1.1.3
 */