package burp;

import java.math.BigInteger;

class Zkdc extends ClassLoader {
  static String Zc;
  
  static Object Zv;
  
  private static final String[] a;
  
  private static final String[] b;
  
  static void ZD(Object[] paramArrayOfObject, Object paramObject) throws Throwable {}
  
  static void ZA(Object paramObject) {
    Zl22.ZL = a(29216, -18384);
    Zl22.ZJ = new BigInteger(a(29229, -23387));
    boolean bool = Zt2e.ZK();
    try {
      try {
        if (Zr9p.Za.charAt(Math.abs(((BigInteger)Zr9p.ZC).intValue() % 32)) <= Zlhz.Zo.charAt(Math.abs(((BigInteger)Zle4.Zh).intValue() % 32))) {
          try {
            Ztod.ZK(Class.forName(a(29224, 31926)));
            if (bool)
              Ztcv.ZI(Class.forName(a(29217, 181))); 
          } catch (Throwable throwable) {
            throw a(null);
          } 
          return;
        } 
      } catch (Throwable throwable) {
        throw a(null);
      } 
      Ztcv.ZI(Class.forName(a(29217, 181)));
    } catch (Throwable throwable) {}
  }
  
  static boolean Zi(Object[] paramArrayOfObject, Object paramObject) throws Throwable {
    // Byte code:
    //   0: invokestatic ZK : ()Z
    //   3: istore_2
    //   4: getstatic burp/Zetv.ZI : Ljava/lang/Object;
    //   7: checkcast java/math/BigInteger
    //   10: invokevirtual toByteArray : ()[B
    //   13: astore_3
    //   14: new java/lang/StringBuilder
    //   17: dup
    //   18: invokespecial <init> : ()V
    //   21: astore #5
    //   23: aload #5
    //   25: sipush #29218
    //   28: sipush #12396
    //   31: invokestatic a : (II)Ljava/lang/String;
    //   34: invokevirtual append : (Ljava/lang/String;)Ljava/lang/StringBuilder;
    //   37: pop
    //   38: aload_3
    //   39: astore #6
    //   41: aload #6
    //   43: arraylength
    //   44: istore #7
    //   46: iconst_0
    //   47: istore #8
    //   49: iload #8
    //   51: iload #7
    //   53: if_icmpge -> 79
    //   56: aload #6
    //   58: iload #8
    //   60: baload
    //   61: istore #9
    //   63: aload #5
    //   65: iload #9
    //   67: i2c
    //   68: invokevirtual append : (C)Ljava/lang/StringBuilder;
    //   71: pop
    //   72: iinc #8, 1
    //   75: iload_2
    //   76: ifeq -> 49
    //   79: aload #5
    //   81: sipush #29230
    //   84: sipush #-28755
    //   87: invokestatic a : (II)Ljava/lang/String;
    //   90: ldc ''
    //   92: invokestatic getProperty : (Ljava/lang/String;Ljava/lang/String;)Ljava/lang/String;
    //   95: invokevirtual toLowerCase : ()Ljava/lang/String;
    //   98: invokevirtual append : (Ljava/lang/String;)Ljava/lang/StringBuilder;
    //   101: pop
    //   102: aload #5
    //   104: sipush #29226
    //   107: sipush #-24971
    //   110: invokestatic a : (II)Ljava/lang/String;
    //   113: ldc ''
    //   115: invokestatic getProperty : (Ljava/lang/String;Ljava/lang/String;)Ljava/lang/String;
    //   118: invokevirtual toLowerCase : ()Ljava/lang/String;
    //   121: invokevirtual append : (Ljava/lang/String;)Ljava/lang/StringBuilder;
    //   124: pop
    //   125: aload #5
    //   127: invokevirtual toString : ()Ljava/lang/String;
    //   130: invokevirtual getBytes : ()[B
    //   133: astore #4
    //   135: aload #4
    //   137: astore_3
    //   138: aload_3
    //   139: arraylength
    //   140: bipush #8
    //   142: iadd
    //   143: bipush #6
    //   145: ishr
    //   146: iconst_1
    //   147: iadd
    //   148: bipush #16
    //   150: imul
    //   151: newarray int
    //   153: astore #5
    //   155: iconst_0
    //   156: istore #6
    //   158: iload #6
    //   160: aload_3
    //   161: arraylength
    //   162: if_icmpge -> 205
    //   165: aload_3
    //   166: iload #6
    //   168: baload
    //   169: sipush #255
    //   172: iand
    //   173: istore #7
    //   175: aload #5
    //   177: iload #6
    //   179: iconst_2
    //   180: ishr
    //   181: dup2
    //   182: iaload
    //   183: iload #7
    //   185: bipush #24
    //   187: iload #6
    //   189: iconst_4
    //   190: irem
    //   191: bipush #8
    //   193: imul
    //   194: isub
    //   195: ishl
    //   196: ior
    //   197: iastore
    //   198: iinc #6, 1
    //   201: iload_2
    //   202: ifeq -> 158
    //   205: aload #5
    //   207: iload #6
    //   209: iconst_2
    //   210: ishr
    //   211: dup2
    //   212: iaload
    //   213: sipush #128
    //   216: bipush #24
    //   218: iload #6
    //   220: iconst_4
    //   221: irem
    //   222: bipush #8
    //   224: imul
    //   225: isub
    //   226: ishl
    //   227: ior
    //   228: iastore
    //   229: aload #5
    //   231: aload #5
    //   233: arraylength
    //   234: iconst_1
    //   235: isub
    //   236: aload_3
    //   237: arraylength
    //   238: bipush #8
    //   240: imul
    //   241: iastore
    //   242: bipush #80
    //   244: newarray int
    //   246: astore #7
    //   248: ldc 1732584193
    //   250: istore #8
    //   252: ldc -271733879
    //   254: istore #9
    //   256: ldc -1732584194
    //   258: istore #10
    //   260: ldc 271733878
    //   262: istore #11
    //   264: ldc -1009589776
    //   266: istore #12
    //   268: iconst_0
    //   269: istore #6
    //   271: iload #6
    //   273: aload #5
    //   275: arraylength
    //   276: if_icmpge -> 598
    //   279: iload #8
    //   281: istore #13
    //   283: iload #9
    //   285: istore #14
    //   287: iload #10
    //   289: istore #15
    //   291: iload #11
    //   293: istore #16
    //   295: iload #12
    //   297: istore #17
    //   299: iconst_0
    //   300: istore #18
    //   302: iload #18
    //   304: bipush #80
    //   306: if_icmpge -> 556
    //   309: iload #18
    //   311: bipush #16
    //   313: if_icmpge -> 340
    //   316: aload #7
    //   318: iload #18
    //   320: aload #5
    //   322: iload #6
    //   324: iload #18
    //   326: iadd
    //   327: iaload
    //   328: iastore
    //   329: iload_2
    //   330: ifeq -> 395
    //   333: goto -> 340
    //   336: invokestatic a : (Ljava/lang/Throwable;)Ljava/lang/Throwable;
    //   339: athrow
    //   340: aload #7
    //   342: iload #18
    //   344: iconst_3
    //   345: isub
    //   346: iaload
    //   347: aload #7
    //   349: iload #18
    //   351: bipush #8
    //   353: isub
    //   354: iaload
    //   355: ixor
    //   356: aload #7
    //   358: iload #18
    //   360: bipush #14
    //   362: isub
    //   363: iaload
    //   364: ixor
    //   365: aload #7
    //   367: iload #18
    //   369: bipush #16
    //   371: isub
    //   372: iaload
    //   373: ixor
    //   374: istore #19
    //   376: iload #19
    //   378: iconst_1
    //   379: ishl
    //   380: iload #19
    //   382: bipush #31
    //   384: iushr
    //   385: ior
    //   386: istore #20
    //   388: aload #7
    //   390: iload #18
    //   392: iload #20
    //   394: iastore
    //   395: iload #8
    //   397: iconst_5
    //   398: ishl
    //   399: iload #8
    //   401: bipush #27
    //   403: iushr
    //   404: ior
    //   405: istore #19
    //   407: iload #19
    //   409: iload #12
    //   411: iadd
    //   412: aload #7
    //   414: iload #18
    //   416: iaload
    //   417: iadd
    //   418: iload #18
    //   420: bipush #20
    //   422: if_icmpge -> 448
    //   425: ldc 1518500249
    //   427: iload #9
    //   429: iload #10
    //   431: iand
    //   432: iload #9
    //   434: iconst_m1
    //   435: ixor
    //   436: iload #11
    //   438: iand
    //   439: ior
    //   440: iadd
    //   441: goto -> 518
    //   444: invokestatic a : (Ljava/lang/Throwable;)Ljava/lang/Throwable;
    //   447: athrow
    //   448: iload #18
    //   450: bipush #40
    //   452: if_icmpge -> 473
    //   455: ldc 1859775393
    //   457: iload #9
    //   459: iload #10
    //   461: ixor
    //   462: iload #11
    //   464: ixor
    //   465: iadd
    //   466: goto -> 518
    //   469: invokestatic a : (Ljava/lang/Throwable;)Ljava/lang/Throwable;
    //   472: athrow
    //   473: iload #18
    //   475: bipush #60
    //   477: if_icmpge -> 507
    //   480: ldc -1894007588
    //   482: iload #9
    //   484: iload #10
    //   486: iand
    //   487: iload #9
    //   489: iload #11
    //   491: iand
    //   492: ior
    //   493: iload #10
    //   495: iload #11
    //   497: iand
    //   498: ior
    //   499: iadd
    //   500: goto -> 518
    //   503: invokestatic a : (Ljava/lang/Throwable;)Ljava/lang/Throwable;
    //   506: athrow
    //   507: ldc -899497514
    //   509: iload #9
    //   511: iload #10
    //   513: ixor
    //   514: iload #11
    //   516: ixor
    //   517: iadd
    //   518: iadd
    //   519: istore #20
    //   521: iload #11
    //   523: istore #12
    //   525: iload #10
    //   527: istore #11
    //   529: iload #9
    //   531: bipush #30
    //   533: ishl
    //   534: iload #9
    //   536: iconst_2
    //   537: iushr
    //   538: ior
    //   539: istore #10
    //   541: iload #8
    //   543: istore #9
    //   545: iload #20
    //   547: istore #8
    //   549: iinc #18, 1
    //   552: iload_2
    //   553: ifeq -> 302
    //   556: iload #8
    //   558: iload #13
    //   560: iadd
    //   561: istore #8
    //   563: iload #9
    //   565: iload #14
    //   567: iadd
    //   568: istore #9
    //   570: iload #10
    //   572: iload #15
    //   574: iadd
    //   575: istore #10
    //   577: iload #11
    //   579: iload #16
    //   581: iadd
    //   582: istore #11
    //   584: iload #12
    //   586: iload #17
    //   588: iadd
    //   589: istore #12
    //   591: iinc #6, 16
    //   594: iload_2
    //   595: ifeq -> 271
    //   598: iconst_5
    //   599: newarray int
    //   601: dup
    //   602: iconst_0
    //   603: iload #8
    //   605: iastore
    //   606: dup
    //   607: iconst_1
    //   608: iload #9
    //   610: iastore
    //   611: dup
    //   612: iconst_2
    //   613: iload #10
    //   615: iastore
    //   616: dup
    //   617: iconst_3
    //   618: iload #11
    //   620: iastore
    //   621: dup
    //   622: iconst_4
    //   623: iload #12
    //   625: iastore
    //   626: astore #13
    //   628: bipush #20
    //   630: newarray byte
    //   632: astore #14
    //   634: iconst_0
    //   635: istore #15
    //   637: iload #15
    //   639: bipush #20
    //   641: if_icmpge -> 682
    //   644: aload #13
    //   646: iload #15
    //   648: iconst_4
    //   649: idiv
    //   650: iaload
    //   651: istore #16
    //   653: iconst_3
    //   654: iload #15
    //   656: iconst_4
    //   657: irem
    //   658: isub
    //   659: bipush #8
    //   661: imul
    //   662: istore #17
    //   664: aload #14
    //   666: iload #15
    //   668: iload #16
    //   670: iload #17
    //   672: iushr
    //   673: i2b
    //   674: bastore
    //   675: iinc #15, 1
    //   678: iload_2
    //   679: ifeq -> 637
    //   682: aload #14
    //   684: astore #4
    //   686: new java/lang/StringBuilder
    //   689: dup
    //   690: invokespecial <init> : ()V
    //   693: astore_3
    //   694: iconst_0
    //   695: istore #4
    //   697: iload #4
    //   699: bipush #32
    //   701: if_icmpge -> 2035
    //   704: iload #4
    //   706: tableswitch default -> 2028, 0 -> 848, 1 -> 885, 2 -> 922, 3 -> 959, 4 -> 996, 5 -> 1033, 6 -> 1070, 7 -> 1107, 8 -> 1144, 9 -> 1181, 10 -> 1218, 11 -> 1255, 12 -> 1292, 13 -> 1329, 14 -> 1366, 15 -> 1403, 16 -> 1440, 17 -> 1477, 18 -> 1514, 19 -> 1551, 20 -> 1588, 21 -> 1625, 22 -> 1662, 23 -> 1699, 24 -> 1736, 25 -> 1773, 26 -> 1810, 27 -> 1847, 28 -> 1884, 29 -> 1921, 30 -> 1958, 31 -> 1995
    //   848: aload_3
    //   849: getstatic burp/Zr_y.Zb : Ljava/lang/String;
    //   852: getstatic burp/Zgvl.ZK : Ljava/lang/Object;
    //   855: checkcast java/math/BigInteger
    //   858: invokevirtual intValue : ()I
    //   861: bipush #32
    //   863: irem
    //   864: invokestatic abs : (I)I
    //   867: invokevirtual charAt : (I)C
    //   870: invokevirtual append : (C)Ljava/lang/StringBuilder;
    //   873: pop
    //   874: iload_2
    //   875: ifeq -> 2028
    //   878: goto -> 885
    //   881: invokestatic a : (Ljava/lang/Throwable;)Ljava/lang/Throwable;
    //   884: athrow
    //   885: aload_3
    //   886: getstatic burp/Ze0w.ZT : Ljava/lang/String;
    //   889: getstatic burp/Zero.ZE : Ljava/lang/Object;
    //   892: checkcast java/math/BigInteger
    //   895: invokevirtual intValue : ()I
    //   898: bipush #32
    //   900: irem
    //   901: invokestatic abs : (I)I
    //   904: invokevirtual charAt : (I)C
    //   907: invokevirtual append : (C)Ljava/lang/StringBuilder;
    //   910: pop
    //   911: iload_2
    //   912: ifeq -> 2028
    //   915: goto -> 922
    //   918: invokestatic a : (Ljava/lang/Throwable;)Ljava/lang/Throwable;
    //   921: athrow
    //   922: aload_3
    //   923: getstatic burp/Zl22.ZL : Ljava/lang/String;
    //   926: getstatic burp/Zrxm.ZL : Ljava/lang/Object;
    //   929: checkcast java/math/BigInteger
    //   932: invokevirtual intValue : ()I
    //   935: bipush #32
    //   937: irem
    //   938: invokestatic abs : (I)I
    //   941: invokevirtual charAt : (I)C
    //   944: invokevirtual append : (C)Ljava/lang/StringBuilder;
    //   947: pop
    //   948: iload_2
    //   949: ifeq -> 2028
    //   952: goto -> 959
    //   955: invokestatic a : (Ljava/lang/Throwable;)Ljava/lang/Throwable;
    //   958: athrow
    //   959: aload_3
    //   960: getstatic burp/Zgj5.ZH : Ljava/lang/String;
    //   963: getstatic burp/Ze_b.Zp : Ljava/lang/Object;
    //   966: checkcast java/math/BigInteger
    //   969: invokevirtual intValue : ()I
    //   972: bipush #32
    //   974: irem
    //   975: invokestatic abs : (I)I
    //   978: invokevirtual charAt : (I)C
    //   981: invokevirtual append : (C)Ljava/lang/StringBuilder;
    //   984: pop
    //   985: iload_2
    //   986: ifeq -> 2028
    //   989: goto -> 996
    //   992: invokestatic a : (Ljava/lang/Throwable;)Ljava/lang/Throwable;
    //   995: athrow
    //   996: aload_3
    //   997: getstatic burp/Zb_c.ZS : Ljava/lang/String;
    //   1000: getstatic burp/Zxdh.ZD : Ljava/lang/Object;
    //   1003: checkcast java/math/BigInteger
    //   1006: invokevirtual intValue : ()I
    //   1009: bipush #32
    //   1011: irem
    //   1012: invokestatic abs : (I)I
    //   1015: invokevirtual charAt : (I)C
    //   1018: invokevirtual append : (C)Ljava/lang/StringBuilder;
    //   1021: pop
    //   1022: iload_2
    //   1023: ifeq -> 2028
    //   1026: goto -> 1033
    //   1029: invokestatic a : (Ljava/lang/Throwable;)Ljava/lang/Throwable;
    //   1032: athrow
    //   1033: aload_3
    //   1034: getstatic burp/Zeud.Za : Ljava/lang/String;
    //   1037: getstatic burp/Zr4k.Zf : Ljava/lang/Object;
    //   1040: checkcast java/math/BigInteger
    //   1043: invokevirtual intValue : ()I
    //   1046: bipush #32
    //   1048: irem
    //   1049: invokestatic abs : (I)I
    //   1052: invokevirtual charAt : (I)C
    //   1055: invokevirtual append : (C)Ljava/lang/StringBuilder;
    //   1058: pop
    //   1059: iload_2
    //   1060: ifeq -> 2028
    //   1063: goto -> 1070
    //   1066: invokestatic a : (Ljava/lang/Throwable;)Ljava/lang/Throwable;
    //   1069: athrow
    //   1070: aload_3
    //   1071: getstatic burp/Zth7.Zf : Ljava/lang/String;
    //   1074: getstatic burp/Zero.ZE : Ljava/lang/Object;
    //   1077: checkcast java/math/BigInteger
    //   1080: invokevirtual intValue : ()I
    //   1083: bipush #32
    //   1085: irem
    //   1086: invokestatic abs : (I)I
    //   1089: invokevirtual charAt : (I)C
    //   1092: invokevirtual append : (C)Ljava/lang/StringBuilder;
    //   1095: pop
    //   1096: iload_2
    //   1097: ifeq -> 2028
    //   1100: goto -> 1107
    //   1103: invokestatic a : (Ljava/lang/Throwable;)Ljava/lang/Throwable;
    //   1106: athrow
    //   1107: aload_3
    //   1108: getstatic burp/Zth7.Zf : Ljava/lang/String;
    //   1111: getstatic burp/Zeno.Zo : Ljava/lang/Object;
    //   1114: checkcast java/math/BigInteger
    //   1117: invokevirtual intValue : ()I
    //   1120: bipush #32
    //   1122: irem
    //   1123: invokestatic abs : (I)I
    //   1126: invokevirtual charAt : (I)C
    //   1129: invokevirtual append : (C)Ljava/lang/StringBuilder;
    //   1132: pop
    //   1133: iload_2
    //   1134: ifeq -> 2028
    //   1137: goto -> 1144
    //   1140: invokestatic a : (Ljava/lang/Throwable;)Ljava/lang/Throwable;
    //   1143: athrow
    //   1144: aload_3
    //   1145: getstatic burp/Zlpl.ZO : Ljava/lang/String;
    //   1148: getstatic burp/Zexu.ZI : Ljava/lang/Object;
    //   1151: checkcast java/math/BigInteger
    //   1154: invokevirtual intValue : ()I
    //   1157: bipush #32
    //   1159: irem
    //   1160: invokestatic abs : (I)I
    //   1163: invokevirtual charAt : (I)C
    //   1166: invokevirtual append : (C)Ljava/lang/StringBuilder;
    //   1169: pop
    //   1170: iload_2
    //   1171: ifeq -> 2028
    //   1174: goto -> 1181
    //   1177: invokestatic a : (Ljava/lang/Throwable;)Ljava/lang/Throwable;
    //   1180: athrow
    //   1181: aload_3
    //   1182: getstatic burp/Zexu.Zp : Ljava/lang/String;
    //   1185: getstatic burp/Zrd0.Zs : Ljava/lang/Object;
    //   1188: checkcast java/math/BigInteger
    //   1191: invokevirtual intValue : ()I
    //   1194: bipush #32
    //   1196: irem
    //   1197: invokestatic abs : (I)I
    //   1200: invokevirtual charAt : (I)C
    //   1203: invokevirtual append : (C)Ljava/lang/StringBuilder;
    //   1206: pop
    //   1207: iload_2
    //   1208: ifeq -> 2028
    //   1211: goto -> 1218
    //   1214: invokestatic a : (Ljava/lang/Throwable;)Ljava/lang/Throwable;
    //   1217: athrow
    //   1218: aload_3
    //   1219: getstatic burp/Zdm.ZJ : Ljava/lang/String;
    //   1222: getstatic burp/Zlxm.Zc : Ljava/lang/Object;
    //   1225: checkcast java/math/BigInteger
    //   1228: invokevirtual intValue : ()I
    //   1231: bipush #32
    //   1233: irem
    //   1234: invokestatic abs : (I)I
    //   1237: invokevirtual charAt : (I)C
    //   1240: invokevirtual append : (C)Ljava/lang/StringBuilder;
    //   1243: pop
    //   1244: iload_2
    //   1245: ifeq -> 2028
    //   1248: goto -> 1255
    //   1251: invokestatic a : (Ljava/lang/Throwable;)Ljava/lang/Throwable;
    //   1254: athrow
    //   1255: aload_3
    //   1256: getstatic burp/Zkaw.ZI : Ljava/lang/String;
    //   1259: getstatic burp/Zkaw.ZB : Ljava/lang/Object;
    //   1262: checkcast java/math/BigInteger
    //   1265: invokevirtual intValue : ()I
    //   1268: bipush #32
    //   1270: irem
    //   1271: invokestatic abs : (I)I
    //   1274: invokevirtual charAt : (I)C
    //   1277: invokevirtual append : (C)Ljava/lang/StringBuilder;
    //   1280: pop
    //   1281: iload_2
    //   1282: ifeq -> 2028
    //   1285: goto -> 1292
    //   1288: invokestatic a : (Ljava/lang/Throwable;)Ljava/lang/Throwable;
    //   1291: athrow
    //   1292: aload_3
    //   1293: getstatic burp/Ztod.Zj : Ljava/lang/String;
    //   1296: getstatic burp/Zb6b.ZU : Ljava/lang/Object;
    //   1299: checkcast java/math/BigInteger
    //   1302: invokevirtual intValue : ()I
    //   1305: bipush #32
    //   1307: irem
    //   1308: invokestatic abs : (I)I
    //   1311: invokevirtual charAt : (I)C
    //   1314: invokevirtual append : (C)Ljava/lang/StringBuilder;
    //   1317: pop
    //   1318: iload_2
    //   1319: ifeq -> 2028
    //   1322: goto -> 1329
    //   1325: invokestatic a : (Ljava/lang/Throwable;)Ljava/lang/Throwable;
    //   1328: athrow
    //   1329: aload_3
    //   1330: getstatic burp/Zkhy.Zu : Ljava/lang/String;
    //   1333: getstatic burp/Ztdt.ZN : Ljava/lang/Object;
    //   1336: checkcast java/math/BigInteger
    //   1339: invokevirtual intValue : ()I
    //   1342: bipush #32
    //   1344: irem
    //   1345: invokestatic abs : (I)I
    //   1348: invokevirtual charAt : (I)C
    //   1351: invokevirtual append : (C)Ljava/lang/StringBuilder;
    //   1354: pop
    //   1355: iload_2
    //   1356: ifeq -> 2028
    //   1359: goto -> 1366
    //   1362: invokestatic a : (Ljava/lang/Throwable;)Ljava/lang/Throwable;
    //   1365: athrow
    //   1366: aload_3
    //   1367: getstatic burp/Zz5s.ZL : Ljava/lang/String;
    //   1370: getstatic burp/Zkk6.Zb : Ljava/lang/Object;
    //   1373: checkcast java/math/BigInteger
    //   1376: invokevirtual intValue : ()I
    //   1379: bipush #32
    //   1381: irem
    //   1382: invokestatic abs : (I)I
    //   1385: invokevirtual charAt : (I)C
    //   1388: invokevirtual append : (C)Ljava/lang/StringBuilder;
    //   1391: pop
    //   1392: iload_2
    //   1393: ifeq -> 2028
    //   1396: goto -> 1403
    //   1399: invokestatic a : (Ljava/lang/Throwable;)Ljava/lang/Throwable;
    //   1402: athrow
    //   1403: aload_3
    //   1404: getstatic burp/Zgvf.ZM : Ljava/lang/String;
    //   1407: getstatic burp/Zlpl.Ze : Ljava/lang/Object;
    //   1410: checkcast java/math/BigInteger
    //   1413: invokevirtual intValue : ()I
    //   1416: bipush #32
    //   1418: irem
    //   1419: invokestatic abs : (I)I
    //   1422: invokevirtual charAt : (I)C
    //   1425: invokevirtual append : (C)Ljava/lang/StringBuilder;
    //   1428: pop
    //   1429: iload_2
    //   1430: ifeq -> 2028
    //   1433: goto -> 1440
    //   1436: invokestatic a : (Ljava/lang/Throwable;)Ljava/lang/Throwable;
    //   1439: athrow
    //   1440: aload_3
    //   1441: getstatic burp/Ztev.Zp : Ljava/lang/String;
    //   1444: getstatic burp/Zlhz.Zy : Ljava/lang/Object;
    //   1447: checkcast java/math/BigInteger
    //   1450: invokevirtual intValue : ()I
    //   1453: bipush #32
    //   1455: irem
    //   1456: invokestatic abs : (I)I
    //   1459: invokevirtual charAt : (I)C
    //   1462: invokevirtual append : (C)Ljava/lang/StringBuilder;
    //   1465: pop
    //   1466: iload_2
    //   1467: ifeq -> 2028
    //   1470: goto -> 1477
    //   1473: invokestatic a : (Ljava/lang/Throwable;)Ljava/lang/Throwable;
    //   1476: athrow
    //   1477: aload_3
    //   1478: getstatic burp/Zlxm.Zv : Ljava/lang/String;
    //   1481: getstatic burp/Zttq.Zh : Ljava/lang/Object;
    //   1484: checkcast java/math/BigInteger
    //   1487: invokevirtual intValue : ()I
    //   1490: bipush #32
    //   1492: irem
    //   1493: invokestatic abs : (I)I
    //   1496: invokevirtual charAt : (I)C
    //   1499: invokevirtual append : (C)Ljava/lang/StringBuilder;
    //   1502: pop
    //   1503: iload_2
    //   1504: ifeq -> 2028
    //   1507: goto -> 1514
    //   1510: invokestatic a : (Ljava/lang/Throwable;)Ljava/lang/Throwable;
    //   1513: athrow
    //   1514: aload_3
    //   1515: getstatic burp/Zkk6.ZP : Ljava/lang/String;
    //   1518: getstatic burp/Zxjw.ZU : Ljava/lang/Object;
    //   1521: checkcast java/math/BigInteger
    //   1524: invokevirtual intValue : ()I
    //   1527: bipush #32
    //   1529: irem
    //   1530: invokestatic abs : (I)I
    //   1533: invokevirtual charAt : (I)C
    //   1536: invokevirtual append : (C)Ljava/lang/StringBuilder;
    //   1539: pop
    //   1540: iload_2
    //   1541: ifeq -> 2028
    //   1544: goto -> 1551
    //   1547: invokestatic a : (Ljava/lang/Throwable;)Ljava/lang/Throwable;
    //   1550: athrow
    //   1551: aload_3
    //   1552: getstatic burp/Zb6b.Zn : Ljava/lang/String;
    //   1555: getstatic burp/Zrkc.ZI : Ljava/lang/Object;
    //   1558: checkcast java/math/BigInteger
    //   1561: invokevirtual intValue : ()I
    //   1564: bipush #32
    //   1566: irem
    //   1567: invokestatic abs : (I)I
    //   1570: invokevirtual charAt : (I)C
    //   1573: invokevirtual append : (C)Ljava/lang/StringBuilder;
    //   1576: pop
    //   1577: iload_2
    //   1578: ifeq -> 2028
    //   1581: goto -> 1588
    //   1584: invokestatic a : (Ljava/lang/Throwable;)Ljava/lang/Throwable;
    //   1587: athrow
    //   1588: aload_3
    //   1589: getstatic burp/Zkdc.Zc : Ljava/lang/String;
    //   1592: getstatic burp/Zl5b.ZI : Ljava/lang/Object;
    //   1595: checkcast java/math/BigInteger
    //   1598: invokevirtual intValue : ()I
    //   1601: bipush #32
    //   1603: irem
    //   1604: invokestatic abs : (I)I
    //   1607: invokevirtual charAt : (I)C
    //   1610: invokevirtual append : (C)Ljava/lang/StringBuilder;
    //   1613: pop
    //   1614: iload_2
    //   1615: ifeq -> 2028
    //   1618: goto -> 1625
    //   1621: invokestatic a : (Ljava/lang/Throwable;)Ljava/lang/Throwable;
    //   1624: athrow
    //   1625: aload_3
    //   1626: getstatic burp/Zeno.ZL : Ljava/lang/String;
    //   1629: getstatic burp/Zkk6.Zb : Ljava/lang/Object;
    //   1632: checkcast java/math/BigInteger
    //   1635: invokevirtual intValue : ()I
    //   1638: bipush #32
    //   1640: irem
    //   1641: invokestatic abs : (I)I
    //   1644: invokevirtual charAt : (I)C
    //   1647: invokevirtual append : (C)Ljava/lang/StringBuilder;
    //   1650: pop
    //   1651: iload_2
    //   1652: ifeq -> 2028
    //   1655: goto -> 1662
    //   1658: invokestatic a : (Ljava/lang/Throwable;)Ljava/lang/Throwable;
    //   1661: athrow
    //   1662: aload_3
    //   1663: getstatic burp/Zeud.Za : Ljava/lang/String;
    //   1666: getstatic burp/Zr9p.ZC : Ljava/lang/Object;
    //   1669: checkcast java/math/BigInteger
    //   1672: invokevirtual intValue : ()I
    //   1675: bipush #32
    //   1677: irem
    //   1678: invokestatic abs : (I)I
    //   1681: invokevirtual charAt : (I)C
    //   1684: invokevirtual append : (C)Ljava/lang/StringBuilder;
    //   1687: pop
    //   1688: iload_2
    //   1689: ifeq -> 2028
    //   1692: goto -> 1699
    //   1695: invokestatic a : (Ljava/lang/Throwable;)Ljava/lang/Throwable;
    //   1698: athrow
    //   1699: aload_3
    //   1700: getstatic burp/Zmh5.Zh : Ljava/lang/String;
    //   1703: getstatic burp/Zlp7.ZM : Ljava/lang/Object;
    //   1706: checkcast java/math/BigInteger
    //   1709: invokevirtual intValue : ()I
    //   1712: bipush #32
    //   1714: irem
    //   1715: invokestatic abs : (I)I
    //   1718: invokevirtual charAt : (I)C
    //   1721: invokevirtual append : (C)Ljava/lang/StringBuilder;
    //   1724: pop
    //   1725: iload_2
    //   1726: ifeq -> 2028
    //   1729: goto -> 1736
    //   1732: invokestatic a : (Ljava/lang/Throwable;)Ljava/lang/Throwable;
    //   1735: athrow
    //   1736: aload_3
    //   1737: getstatic burp/Zry7.Z_ : Ljava/lang/String;
    //   1740: getstatic burp/Ze_b.Zp : Ljava/lang/Object;
    //   1743: checkcast java/math/BigInteger
    //   1746: invokevirtual intValue : ()I
    //   1749: bipush #32
    //   1751: irem
    //   1752: invokestatic abs : (I)I
    //   1755: invokevirtual charAt : (I)C
    //   1758: invokevirtual append : (C)Ljava/lang/StringBuilder;
    //   1761: pop
    //   1762: iload_2
    //   1763: ifeq -> 2028
    //   1766: goto -> 1773
    //   1769: invokestatic a : (Ljava/lang/Throwable;)Ljava/lang/Throwable;
    //   1772: athrow
    //   1773: aload_3
    //   1774: getstatic burp/Zlp7.ZO : Ljava/lang/String;
    //   1777: getstatic burp/Zz5s.Zg : Ljava/lang/Object;
    //   1780: checkcast java/math/BigInteger
    //   1783: invokevirtual intValue : ()I
    //   1786: bipush #32
    //   1788: irem
    //   1789: invokestatic abs : (I)I
    //   1792: invokevirtual charAt : (I)C
    //   1795: invokevirtual append : (C)Ljava/lang/StringBuilder;
    //   1798: pop
    //   1799: iload_2
    //   1800: ifeq -> 2028
    //   1803: goto -> 1810
    //   1806: invokestatic a : (Ljava/lang/Throwable;)Ljava/lang/Throwable;
    //   1809: athrow
    //   1810: aload_3
    //   1811: getstatic burp/Zkhy.Zu : Ljava/lang/String;
    //   1814: getstatic burp/Zete.Zm : Ljava/lang/Object;
    //   1817: checkcast java/math/BigInteger
    //   1820: invokevirtual intValue : ()I
    //   1823: bipush #32
    //   1825: irem
    //   1826: invokestatic abs : (I)I
    //   1829: invokevirtual charAt : (I)C
    //   1832: invokevirtual append : (C)Ljava/lang/StringBuilder;
    //   1835: pop
    //   1836: iload_2
    //   1837: ifeq -> 2028
    //   1840: goto -> 1847
    //   1843: invokestatic a : (Ljava/lang/Throwable;)Ljava/lang/Throwable;
    //   1846: athrow
    //   1847: aload_3
    //   1848: getstatic burp/Zero.ZL : Ljava/lang/String;
    //   1851: getstatic burp/Zz3k.Zz : Ljava/lang/Object;
    //   1854: checkcast java/math/BigInteger
    //   1857: invokevirtual intValue : ()I
    //   1860: bipush #32
    //   1862: irem
    //   1863: invokestatic abs : (I)I
    //   1866: invokevirtual charAt : (I)C
    //   1869: invokevirtual append : (C)Ljava/lang/StringBuilder;
    //   1872: pop
    //   1873: iload_2
    //   1874: ifeq -> 2028
    //   1877: goto -> 1884
    //   1880: invokestatic a : (Ljava/lang/Throwable;)Ljava/lang/Throwable;
    //   1883: athrow
    //   1884: aload_3
    //   1885: getstatic burp/Zxdh.Zj : Ljava/lang/String;
    //   1888: getstatic burp/Zzr.ZZ : Ljava/lang/Object;
    //   1891: checkcast java/math/BigInteger
    //   1894: invokevirtual intValue : ()I
    //   1897: bipush #32
    //   1899: irem
    //   1900: invokestatic abs : (I)I
    //   1903: invokevirtual charAt : (I)C
    //   1906: invokevirtual append : (C)Ljava/lang/StringBuilder;
    //   1909: pop
    //   1910: iload_2
    //   1911: ifeq -> 2028
    //   1914: goto -> 1921
    //   1917: invokestatic a : (Ljava/lang/Throwable;)Ljava/lang/Throwable;
    //   1920: athrow
    //   1921: aload_3
    //   1922: getstatic burp/Zepm.Zl : Ljava/lang/String;
    //   1925: getstatic burp/Zepm.Zp : Ljava/lang/Object;
    //   1928: checkcast java/math/BigInteger
    //   1931: invokevirtual intValue : ()I
    //   1934: bipush #32
    //   1936: irem
    //   1937: invokestatic abs : (I)I
    //   1940: invokevirtual charAt : (I)C
    //   1943: invokevirtual append : (C)Ljava/lang/StringBuilder;
    //   1946: pop
    //   1947: iload_2
    //   1948: ifeq -> 2028
    //   1951: goto -> 1958
    //   1954: invokestatic a : (Ljava/lang/Throwable;)Ljava/lang/Throwable;
    //   1957: athrow
    //   1958: aload_3
    //   1959: getstatic burp/Ze_b.ZX : Ljava/lang/String;
    //   1962: getstatic burp/Zsun.ZP : Ljava/lang/Object;
    //   1965: checkcast java/math/BigInteger
    //   1968: invokevirtual intValue : ()I
    //   1971: bipush #32
    //   1973: irem
    //   1974: invokestatic abs : (I)I
    //   1977: invokevirtual charAt : (I)C
    //   1980: invokevirtual append : (C)Ljava/lang/StringBuilder;
    //   1983: pop
    //   1984: iload_2
    //   1985: ifeq -> 2028
    //   1988: goto -> 1995
    //   1991: invokestatic a : (Ljava/lang/Throwable;)Ljava/lang/Throwable;
    //   1994: athrow
    //   1995: aload_3
    //   1996: getstatic burp/Ztap.Zk : Ljava/lang/String;
    //   1999: getstatic burp/Zgvf.Zd : Ljava/lang/Object;
    //   2002: checkcast java/math/BigInteger
    //   2005: invokevirtual intValue : ()I
    //   2008: bipush #32
    //   2010: irem
    //   2011: invokestatic abs : (I)I
    //   2014: invokevirtual charAt : (I)C
    //   2017: invokevirtual append : (C)Ljava/lang/StringBuilder;
    //   2020: pop
    //   2021: goto -> 2028
    //   2024: invokestatic a : (Ljava/lang/Throwable;)Ljava/lang/Throwable;
    //   2027: athrow
    //   2028: iinc #4, 1
    //   2031: iload_2
    //   2032: ifeq -> 697
    //   2035: aload_3
    //   2036: invokevirtual toString : ()Ljava/lang/String;
    //   2039: putstatic burp/Zbnb.Zd : Ljava/lang/String;
    //   2042: sipush #29223
    //   2045: sipush #-4332
    //   2048: invokestatic a : (II)Ljava/lang/String;
    //   2051: iconst_1
    //   2052: ldc burp/Zlav
    //   2054: invokevirtual getClassLoader : ()Ljava/lang/ClassLoader;
    //   2057: invokestatic forName : (Ljava/lang/String;ZLjava/lang/ClassLoader;)Ljava/lang/Class;
    //   2060: invokevirtual getDeclaredFields : ()[Ljava/lang/reflect/Field;
    //   2063: astore #4
    //   2065: aload #4
    //   2067: arraylength
    //   2068: istore #5
    //   2070: iconst_0
    //   2071: istore #6
    //   2073: iload #6
    //   2075: iload #5
    //   2077: if_icmpge -> 2215
    //   2080: aload #4
    //   2082: iload #6
    //   2084: aaload
    //   2085: astore #7
    //   2087: aload #7
    //   2089: invokevirtual getModifiers : ()I
    //   2092: invokestatic isStatic : (I)Z
    //   2095: ifne -> 2105
    //   2098: goto -> 2208
    //   2101: invokestatic a : (Ljava/lang/Throwable;)Ljava/lang/Throwable;
    //   2104: athrow
    //   2105: aload #7
    //   2107: invokevirtual getType : ()Ljava/lang/Class;
    //   2110: astore #8
    //   2112: aload #8
    //   2114: ifnull -> 2195
    //   2117: aload #8
    //   2119: invokevirtual isPrimitive : ()Z
    //   2122: ifne -> 2195
    //   2125: goto -> 2132
    //   2128: invokestatic a : (Ljava/lang/Throwable;)Ljava/lang/Throwable;
    //   2131: athrow
    //   2132: aload #8
    //   2134: invokevirtual getPackage : ()Ljava/lang/Package;
    //   2137: ifnull -> 2195
    //   2140: goto -> 2147
    //   2143: invokestatic a : (Ljava/lang/Throwable;)Ljava/lang/Throwable;
    //   2146: athrow
    //   2147: aload #8
    //   2149: invokevirtual getPackage : ()Ljava/lang/Package;
    //   2152: invokevirtual getName : ()Ljava/lang/String;
    //   2155: ifnull -> 2195
    //   2158: goto -> 2165
    //   2161: invokestatic a : (Ljava/lang/Throwable;)Ljava/lang/Throwable;
    //   2164: athrow
    //   2165: aload #8
    //   2167: invokevirtual getPackage : ()Ljava/lang/Package;
    //   2170: invokevirtual getName : ()Ljava/lang/String;
    //   2173: sipush #29227
    //   2176: sipush #18854
    //   2179: invokestatic a : (II)Ljava/lang/String;
    //   2182: invokevirtual startsWith : (Ljava/lang/String;)Z
    //   2185: ifne -> 2195
    //   2188: goto -> 2195
    //   2191: invokestatic a : (Ljava/lang/Throwable;)Ljava/lang/Throwable;
    //   2194: athrow
    //   2195: aload #7
    //   2197: iconst_1
    //   2198: invokevirtual setAccessible : (Z)V
    //   2201: aload #7
    //   2203: aconst_null
    //   2204: invokevirtual get : (Ljava/lang/Object;)Ljava/lang/Object;
    //   2207: pop
    //   2208: iinc #6, 1
    //   2211: iload_2
    //   2212: ifeq -> 2073
    //   2215: sipush #29225
    //   2218: sipush #6475
    //   2221: invokestatic a : (II)Ljava/lang/String;
    //   2224: invokestatic forName : (Ljava/lang/String;)Ljava/lang/Class;
    //   2227: invokevirtual getDeclaredMethods : ()[Ljava/lang/reflect/Method;
    //   2230: astore #4
    //   2232: aload #4
    //   2234: arraylength
    //   2235: istore #5
    //   2237: iconst_0
    //   2238: istore #6
    //   2240: iload #6
    //   2242: iload #5
    //   2244: if_icmpge -> 2377
    //   2247: aload #4
    //   2249: iload #6
    //   2251: aaload
    //   2252: astore #7
    //   2254: aload #7
    //   2256: invokevirtual getParameterTypes : ()[Ljava/lang/Class;
    //   2259: pop
    //   2260: aload #7
    //   2262: invokevirtual getModifiers : ()I
    //   2265: invokestatic isStatic : (I)Z
    //   2268: ifeq -> 2363
    //   2271: aload #7
    //   2273: invokevirtual getParameterTypes : ()[Ljava/lang/Class;
    //   2276: arraylength
    //   2277: iconst_2
    //   2278: if_icmpne -> 2363
    //   2281: goto -> 2288
    //   2284: invokestatic a : (Ljava/lang/Throwable;)Ljava/lang/Throwable;
    //   2287: athrow
    //   2288: aload #7
    //   2290: invokevirtual getReturnType : ()Ljava/lang/Class;
    //   2293: getstatic java/lang/Void.TYPE : Ljava/lang/Class;
    //   2296: invokevirtual equals : (Ljava/lang/Object;)Z
    //   2299: ifeq -> 2363
    //   2302: goto -> 2309
    //   2305: invokestatic a : (Ljava/lang/Throwable;)Ljava/lang/Throwable;
    //   2308: athrow
    //   2309: aload #7
    //   2311: iconst_1
    //   2312: invokevirtual setAccessible : (Z)V
    //   2315: aload #7
    //   2317: aconst_null
    //   2318: iconst_2
    //   2319: anewarray java/lang/Object
    //   2322: dup
    //   2323: iconst_0
    //   2324: aload_0
    //   2325: aastore
    //   2326: dup
    //   2327: iconst_1
    //   2328: aload_1
    //   2329: ifnonnull -> 2347
    //   2332: goto -> 2339
    //   2335: invokestatic a : (Ljava/lang/Throwable;)Ljava/lang/Throwable;
    //   2338: athrow
    //   2339: aload_1
    //   2340: goto -> 2354
    //   2343: invokestatic a : (Ljava/lang/Throwable;)Ljava/lang/Throwable;
    //   2346: athrow
    //   2347: aload_1
    //   2348: checkcast [B
    //   2351: invokevirtual clone : ()Ljava/lang/Object;
    //   2354: aastore
    //   2355: invokevirtual invoke : (Ljava/lang/Object;[Ljava/lang/Object;)Ljava/lang/Object;
    //   2358: pop
    //   2359: iload_2
    //   2360: ifeq -> 2377
    //   2363: iinc #6, 1
    //   2366: iload_2
    //   2367: ifeq -> 2240
    //   2370: goto -> 2377
    //   2373: invokestatic a : (Ljava/lang/Throwable;)Ljava/lang/Throwable;
    //   2376: athrow
    //   2377: getstatic burp/Zct.ZW : Ljava/lang/Object;
    //   2380: checkcast java/math/BigInteger
    //   2383: invokevirtual intValue : ()I
    //   2386: i2l
    //   2387: invokestatic currentTimeMillis : ()J
    //   2390: ladd
    //   2391: getstatic burp/Zkaw.ZB : Ljava/lang/Object;
    //   2394: checkcast java/math/BigInteger
    //   2397: invokevirtual intValue : ()I
    //   2400: i2l
    //   2401: lcmp
    //   2402: ifge -> 2740
    //   2405: sipush #29222
    //   2408: sipush #-22684
    //   2411: invokestatic a : (II)Ljava/lang/String;
    //   2414: iconst_1
    //   2415: ldc burp/Zlqm
    //   2417: invokevirtual getClassLoader : ()Ljava/lang/ClassLoader;
    //   2420: invokestatic forName : (Ljava/lang/String;ZLjava/lang/ClassLoader;)Ljava/lang/Class;
    //   2423: invokevirtual getDeclaredFields : ()[Ljava/lang/reflect/Field;
    //   2426: astore #4
    //   2428: aload #4
    //   2430: arraylength
    //   2431: istore #5
    //   2433: iconst_0
    //   2434: istore #6
    //   2436: iload #6
    //   2438: iload #5
    //   2440: if_icmpge -> 2578
    //   2443: aload #4
    //   2445: iload #6
    //   2447: aaload
    //   2448: astore #7
    //   2450: aload #7
    //   2452: invokevirtual getModifiers : ()I
    //   2455: invokestatic isStatic : (I)Z
    //   2458: ifne -> 2468
    //   2461: goto -> 2571
    //   2464: invokestatic a : (Ljava/lang/Throwable;)Ljava/lang/Throwable;
    //   2467: athrow
    //   2468: aload #7
    //   2470: invokevirtual getType : ()Ljava/lang/Class;
    //   2473: astore #8
    //   2475: aload #8
    //   2477: ifnull -> 2558
    //   2480: aload #8
    //   2482: invokevirtual isPrimitive : ()Z
    //   2485: ifne -> 2558
    //   2488: goto -> 2495
    //   2491: invokestatic a : (Ljava/lang/Throwable;)Ljava/lang/Throwable;
    //   2494: athrow
    //   2495: aload #8
    //   2497: invokevirtual getPackage : ()Ljava/lang/Package;
    //   2500: ifnull -> 2558
    //   2503: goto -> 2510
    //   2506: invokestatic a : (Ljava/lang/Throwable;)Ljava/lang/Throwable;
    //   2509: athrow
    //   2510: aload #8
    //   2512: invokevirtual getPackage : ()Ljava/lang/Package;
    //   2515: invokevirtual getName : ()Ljava/lang/String;
    //   2518: ifnull -> 2558
    //   2521: goto -> 2528
    //   2524: invokestatic a : (Ljava/lang/Throwable;)Ljava/lang/Throwable;
    //   2527: athrow
    //   2528: aload #8
    //   2530: invokevirtual getPackage : ()Ljava/lang/Package;
    //   2533: invokevirtual getName : ()Ljava/lang/String;
    //   2536: sipush #29219
    //   2539: sipush #22924
    //   2542: invokestatic a : (II)Ljava/lang/String;
    //   2545: invokevirtual startsWith : (Ljava/lang/String;)Z
    //   2548: ifne -> 2558
    //   2551: goto -> 2558
    //   2554: invokestatic a : (Ljava/lang/Throwable;)Ljava/lang/Throwable;
    //   2557: athrow
    //   2558: aload #7
    //   2560: iconst_1
    //   2561: invokevirtual setAccessible : (Z)V
    //   2564: aload #7
    //   2566: aconst_null
    //   2567: invokevirtual get : (Ljava/lang/Object;)Ljava/lang/Object;
    //   2570: pop
    //   2571: iinc #6, 1
    //   2574: iload_2
    //   2575: ifeq -> 2436
    //   2578: sipush #29228
    //   2581: sipush #-4168
    //   2584: invokestatic a : (II)Ljava/lang/String;
    //   2587: invokestatic forName : (Ljava/lang/String;)Ljava/lang/Class;
    //   2590: invokevirtual getDeclaredMethods : ()[Ljava/lang/reflect/Method;
    //   2593: astore #4
    //   2595: aload #4
    //   2597: arraylength
    //   2598: istore #5
    //   2600: iconst_0
    //   2601: istore #6
    //   2603: iload #6
    //   2605: iload #5
    //   2607: if_icmpge -> 2740
    //   2610: aload #4
    //   2612: iload #6
    //   2614: aaload
    //   2615: astore #7
    //   2617: aload #7
    //   2619: invokevirtual getParameterTypes : ()[Ljava/lang/Class;
    //   2622: pop
    //   2623: aload #7
    //   2625: invokevirtual getModifiers : ()I
    //   2628: invokestatic isStatic : (I)Z
    //   2631: ifeq -> 2726
    //   2634: aload #7
    //   2636: invokevirtual getParameterTypes : ()[Ljava/lang/Class;
    //   2639: arraylength
    //   2640: iconst_2
    //   2641: if_icmpne -> 2726
    //   2644: goto -> 2651
    //   2647: invokestatic a : (Ljava/lang/Throwable;)Ljava/lang/Throwable;
    //   2650: athrow
    //   2651: aload #7
    //   2653: invokevirtual getReturnType : ()Ljava/lang/Class;
    //   2656: getstatic java/lang/Void.TYPE : Ljava/lang/Class;
    //   2659: invokevirtual equals : (Ljava/lang/Object;)Z
    //   2662: ifeq -> 2726
    //   2665: goto -> 2672
    //   2668: invokestatic a : (Ljava/lang/Throwable;)Ljava/lang/Throwable;
    //   2671: athrow
    //   2672: aload #7
    //   2674: iconst_1
    //   2675: invokevirtual setAccessible : (Z)V
    //   2678: aload #7
    //   2680: aconst_null
    //   2681: iconst_2
    //   2682: anewarray java/lang/Object
    //   2685: dup
    //   2686: iconst_0
    //   2687: aload_0
    //   2688: aastore
    //   2689: dup
    //   2690: iconst_1
    //   2691: aload_1
    //   2692: ifnonnull -> 2710
    //   2695: goto -> 2702
    //   2698: invokestatic a : (Ljava/lang/Throwable;)Ljava/lang/Throwable;
    //   2701: athrow
    //   2702: aload_1
    //   2703: goto -> 2717
    //   2706: invokestatic a : (Ljava/lang/Throwable;)Ljava/lang/Throwable;
    //   2709: athrow
    //   2710: aload_1
    //   2711: checkcast [B
    //   2714: invokevirtual clone : ()Ljava/lang/Object;
    //   2717: aastore
    //   2718: invokevirtual invoke : (Ljava/lang/Object;[Ljava/lang/Object;)Ljava/lang/Object;
    //   2721: pop
    //   2722: iload_2
    //   2723: ifeq -> 2740
    //   2726: iinc #6, 1
    //   2729: iload_2
    //   2730: ifeq -> 2603
    //   2733: goto -> 2740
    //   2736: invokestatic a : (Ljava/lang/Throwable;)Ljava/lang/Throwable;
    //   2739: athrow
    //   2740: getstatic burp/Ztmy.ZF : Ljava/lang/String;
    //   2743: getstatic burp/Zrkc.ZI : Ljava/lang/Object;
    //   2746: checkcast java/math/BigInteger
    //   2749: invokevirtual intValue : ()I
    //   2752: bipush #32
    //   2754: irem
    //   2755: invokestatic abs : (I)I
    //   2758: invokevirtual charAt : (I)C
    //   2761: getstatic burp/Zgw7.ZN : Ljava/lang/String;
    //   2764: getstatic burp/Zlpl.Ze : Ljava/lang/Object;
    //   2767: checkcast java/math/BigInteger
    //   2770: invokevirtual intValue : ()I
    //   2773: bipush #32
    //   2775: irem
    //   2776: invokestatic abs : (I)I
    //   2779: invokevirtual charAt : (I)C
    //   2782: if_icmpgt -> 2889
    //   2785: getstatic burp/Ztdt.Zk : Ljava/lang/String;
    //   2788: getstatic burp/Zezq.Zu : Ljava/lang/Object;
    //   2791: checkcast java/math/BigInteger
    //   2794: invokevirtual intValue : ()I
    //   2797: bipush #32
    //   2799: irem
    //   2800: invokestatic abs : (I)I
    //   2803: invokevirtual charAt : (I)C
    //   2806: getstatic burp/Zsq5.ZA : Ljava/lang/String;
    //   2809: getstatic burp/Zblj.Zl : Ljava/lang/Object;
    //   2812: checkcast java/math/BigInteger
    //   2815: invokevirtual intValue : ()I
    //   2818: bipush #32
    //   2820: irem
    //   2821: invokestatic abs : (I)I
    //   2824: invokevirtual charAt : (I)C
    //   2827: if_icmple -> 2889
    //   2830: goto -> 2837
    //   2833: invokestatic a : (Ljava/lang/Throwable;)Ljava/lang/Throwable;
    //   2836: athrow
    //   2837: getstatic burp/Zmh5.Zh : Ljava/lang/String;
    //   2840: getstatic burp/Zxdh.ZD : Ljava/lang/Object;
    //   2843: checkcast java/math/BigInteger
    //   2846: invokevirtual intValue : ()I
    //   2849: bipush #32
    //   2851: irem
    //   2852: invokestatic abs : (I)I
    //   2855: invokevirtual charAt : (I)C
    //   2858: getstatic burp/Zgw7.ZN : Ljava/lang/String;
    //   2861: getstatic burp/Zle4.Zh : Ljava/lang/Object;
    //   2864: checkcast java/math/BigInteger
    //   2867: invokevirtual intValue : ()I
    //   2870: bipush #32
    //   2872: irem
    //   2873: invokestatic abs : (I)I
    //   2876: invokevirtual charAt : (I)C
    //   2879: if_icmple -> 2897
    //   2882: goto -> 2889
    //   2885: invokestatic a : (Ljava/lang/Throwable;)Ljava/lang/Throwable;
    //   2888: athrow
    //   2889: iconst_1
    //   2890: goto -> 2898
    //   2893: invokestatic a : (Ljava/lang/Throwable;)Ljava/lang/Throwable;
    //   2896: athrow
    //   2897: iconst_0
    //   2898: ireturn
    //   2899: astore_3
    //   2900: new java/lang/Exception
    //   2903: dup
    //   2904: aload_3
    //   2905: invokevirtual getMessage : ()Ljava/lang/String;
    //   2908: invokespecial <init> : (Ljava/lang/String;)V
    //   2911: athrow
    // Exception table:
    //   from	to	target	type
    //   4	2898	2899	java/lang/Throwable
    //   309	333	336	java/lang/Throwable
    //   407	444	444	java/lang/Throwable
    //   448	469	469	java/lang/Throwable
    //   473	503	503	java/lang/Throwable
    //   704	878	881	java/lang/Throwable
    //   848	915	918	java/lang/Throwable
    //   885	952	955	java/lang/Throwable
    //   922	989	992	java/lang/Throwable
    //   959	1026	1029	java/lang/Throwable
    //   996	1063	1066	java/lang/Throwable
    //   1033	1100	1103	java/lang/Throwable
    //   1070	1137	1140	java/lang/Throwable
    //   1107	1174	1177	java/lang/Throwable
    //   1144	1211	1214	java/lang/Throwable
    //   1181	1248	1251	java/lang/Throwable
    //   1218	1285	1288	java/lang/Throwable
    //   1255	1322	1325	java/lang/Throwable
    //   1292	1359	1362	java/lang/Throwable
    //   1329	1396	1399	java/lang/Throwable
    //   1366	1433	1436	java/lang/Throwable
    //   1403	1470	1473	java/lang/Throwable
    //   1440	1507	1510	java/lang/Throwable
    //   1477	1544	1547	java/lang/Throwable
    //   1514	1581	1584	java/lang/Throwable
    //   1551	1618	1621	java/lang/Throwable
    //   1588	1655	1658	java/lang/Throwable
    //   1625	1692	1695	java/lang/Throwable
    //   1662	1729	1732	java/lang/Throwable
    //   1699	1766	1769	java/lang/Throwable
    //   1736	1803	1806	java/lang/Throwable
    //   1773	1840	1843	java/lang/Throwable
    //   1810	1877	1880	java/lang/Throwable
    //   1847	1914	1917	java/lang/Throwable
    //   1884	1951	1954	java/lang/Throwable
    //   1921	1988	1991	java/lang/Throwable
    //   1958	2021	2024	java/lang/Throwable
    //   2087	2101	2101	java/lang/Throwable
    //   2112	2125	2128	java/lang/Throwable
    //   2117	2140	2143	java/lang/Throwable
    //   2132	2158	2161	java/lang/Throwable
    //   2147	2188	2191	java/lang/Throwable
    //   2254	2281	2284	java/lang/Throwable
    //   2271	2302	2305	java/lang/Throwable
    //   2288	2332	2335	java/lang/Throwable
    //   2309	2343	2343	java/lang/Throwable
    //   2354	2370	2373	java/lang/Throwable
    //   2450	2464	2464	java/lang/Throwable
    //   2475	2488	2491	java/lang/Throwable
    //   2480	2503	2506	java/lang/Throwable
    //   2495	2521	2524	java/lang/Throwable
    //   2510	2551	2554	java/lang/Throwable
    //   2617	2644	2647	java/lang/Throwable
    //   2634	2665	2668	java/lang/Throwable
    //   2651	2695	2698	java/lang/Throwable
    //   2672	2706	2706	java/lang/Throwable
    //   2717	2733	2736	java/lang/Throwable
    //   2740	2830	2833	java/lang/Throwable
    //   2785	2882	2885	java/lang/Throwable
    //   2837	2893	2893	java/lang/Throwable
  }
  
  static {
    // Byte code:
    //   0: bipush #14
    //   2: anewarray java/lang/String
    //   5: astore #5
    //   7: iconst_0
    //   8: istore_3
    //   9: ldc 'f\\t[}t\\bO\\r%\\tLo (Lj|\\rcf\\r+]}(S M?\^*[E;GRjnH|[\je\\t]&)(MIz7L}P_4SJaHwNx_/\\t\\rH,x  +!RM0Y0in `c4{Z\\t!D| \\t@mil/M\\ba3s*'
    //   11: dup
    //   12: astore_2
    //   13: invokevirtual length : ()I
    //   16: istore #4
    //   18: iconst_4
    //   19: istore_1
    //   20: iconst_m1
    //   21: istore_0
    //   22: bipush #11
    //   24: iinc #0, 1
    //   27: aload_2
    //   28: iload_0
    //   29: dup
    //   30: iload_1
    //   31: iadd
    //   32: invokevirtual substring : (II)Ljava/lang/String;
    //   35: iconst_m1
    //   36: goto -> 142
    //   39: aload #5
    //   41: swap
    //   42: iload_3
    //   43: iinc #3, 1
    //   46: swap
    //   47: aastore
    //   48: iload_0
    //   49: iload_1
    //   50: iadd
    //   51: dup
    //   52: istore_0
    //   53: iload #4
    //   55: if_icmpge -> 67
    //   58: aload_2
    //   59: iload_0
    //   60: invokevirtual charAt : (I)C
    //   63: istore_1
    //   64: goto -> 22
    //   67: ldc '\\t0eI}'
    //   69: dup
    //   70: astore_2
    //   71: invokevirtual length : ()I
    //   74: istore #4
    //   76: bipush #8
    //   78: istore_1
    //   79: iconst_m1
    //   80: istore_0
    //   81: bipush #109
    //   83: iinc #0, 1
    //   86: aload_2
    //   87: iload_0
    //   88: dup
    //   89: iload_1
    //   90: iadd
    //   91: invokevirtual substring : (II)Ljava/lang/String;
    //   94: iconst_0
    //   95: goto -> 142
    //   98: aload #5
    //   100: swap
    //   101: iload_3
    //   102: iinc #3, 1
    //   105: swap
    //   106: aastore
    //   107: iload_0
    //   108: iload_1
    //   109: iadd
    //   110: dup
    //   111: istore_0
    //   112: iload #4
    //   114: if_icmpge -> 126
    //   117: aload_2
    //   118: iload_0
    //   119: invokevirtual charAt : (I)C
    //   122: istore_1
    //   123: goto -> 81
    //   126: aload #5
    //   128: putstatic burp/Zkdc.a : [Ljava/lang/String;
    //   131: bipush #14
    //   133: anewarray java/lang/String
    //   136: putstatic burp/Zkdc.b : [Ljava/lang/String;
    //   139: goto -> 300
    //   142: dup_x2
    //   143: pop
    //   144: invokevirtual toCharArray : ()[C
    //   147: dup_x1
    //   148: arraylength
    //   149: dup_x2
    //   150: pop
    //   151: iconst_0
    //   152: istore #6
    //   154: dup2_x1
    //   155: pop2
    //   156: dup_x2
    //   157: iconst_1
    //   158: if_icmpgt -> 260
    //   161: dup2
    //   162: swap
    //   163: iload #6
    //   165: dup2_x1
    //   166: caload
    //   167: swap
    //   168: iload #6
    //   170: bipush #7
    //   172: irem
    //   173: tableswitch default -> 242, 0 -> 212, 1 -> 217, 2 -> 222, 3 -> 227, 4 -> 232, 5 -> 237
    //   212: bipush #25
    //   214: goto -> 244
    //   217: bipush #126
    //   219: goto -> 244
    //   222: bipush #122
    //   224: goto -> 244
    //   227: bipush #33
    //   229: goto -> 244
    //   232: bipush #120
    //   234: goto -> 244
    //   237: bipush #21
    //   239: goto -> 244
    //   242: bipush #18
    //   244: ixor
    //   245: ixor
    //   246: i2c
    //   247: castore
    //   248: iinc #6, 1
    //   251: dup
    //   252: ifne -> 260
    //   255: dup2
    //   256: dup_x1
    //   257: goto -> 165
    //   260: dup2_x1
    //   261: pop2
    //   262: dup_x2
    //   263: iload #6
    //   265: if_icmpgt -> 161
    //   268: pop
    //   269: new java/lang/String
    //   272: dup_x1
    //   273: swap
    //   274: invokespecial <init> : ([C)V
    //   277: invokevirtual intern : ()Ljava/lang/String;
    //   280: swap
    //   281: pop
    //   282: swap
    //   283: tableswitch default -> 39, 0 -> 98
    //   300: sipush #29231
    //   303: sipush #16180
    //   306: invokestatic a : (II)Ljava/lang/String;
    //   309: putstatic burp/Zkdc.Zc : Ljava/lang/String;
    //   312: new java/math/BigInteger
    //   315: dup
    //   316: bipush #32
    //   318: newarray byte
    //   320: dup
    //   321: iconst_0
    //   322: bipush #126
    //   324: bastore
    //   325: dup
    //   326: iconst_1
    //   327: bipush #110
    //   329: bastore
    //   330: dup
    //   331: iconst_2
    //   332: bipush #112
    //   334: bastore
    //   335: dup
    //   336: iconst_3
    //   337: bipush #68
    //   339: bastore
    //   340: dup
    //   341: iconst_4
    //   342: bipush #-102
    //   344: bastore
    //   345: dup
    //   346: iconst_5
    //   347: bipush #96
    //   349: bastore
    //   350: dup
    //   351: bipush #6
    //   353: iconst_0
    //   354: bastore
    //   355: dup
    //   356: bipush #7
    //   358: bipush #98
    //   360: bastore
    //   361: dup
    //   362: bipush #8
    //   364: bipush #-15
    //   366: bastore
    //   367: dup
    //   368: bipush #9
    //   370: bipush #8
    //   372: bastore
    //   373: dup
    //   374: bipush #10
    //   376: bipush #116
    //   378: bastore
    //   379: dup
    //   380: bipush #11
    //   382: bipush #18
    //   384: bastore
    //   385: dup
    //   386: bipush #12
    //   388: bipush #11
    //   390: bastore
    //   391: dup
    //   392: bipush #13
    //   394: bipush #111
    //   396: bastore
    //   397: dup
    //   398: bipush #14
    //   400: bipush #-58
    //   402: bastore
    //   403: dup
    //   404: bipush #15
    //   406: bipush #127
    //   408: bastore
    //   409: dup
    //   410: bipush #16
    //   412: bipush #102
    //   414: bastore
    //   415: dup
    //   416: bipush #17
    //   418: bipush #-83
    //   420: bastore
    //   421: dup
    //   422: bipush #18
    //   424: bipush #-12
    //   426: bastore
    //   427: dup
    //   428: bipush #19
    //   430: bipush #-111
    //   432: bastore
    //   433: dup
    //   434: bipush #20
    //   436: bipush #100
    //   438: bastore
    //   439: dup
    //   440: bipush #21
    //   442: bipush #54
    //   444: bastore
    //   445: dup
    //   446: bipush #22
    //   448: bipush #47
    //   450: bastore
    //   451: dup
    //   452: bipush #23
    //   454: bipush #67
    //   456: bastore
    //   457: dup
    //   458: bipush #24
    //   460: bipush #52
    //   462: bastore
    //   463: dup
    //   464: bipush #25
    //   466: iconst_2
    //   467: bastore
    //   468: dup
    //   469: bipush #26
    //   471: bipush #93
    //   473: bastore
    //   474: dup
    //   475: bipush #27
    //   477: bipush #100
    //   479: bastore
    //   480: dup
    //   481: bipush #28
    //   483: bipush #-32
    //   485: bastore
    //   486: dup
    //   487: bipush #29
    //   489: bipush #-127
    //   491: bastore
    //   492: dup
    //   493: bipush #30
    //   495: bipush #87
    //   497: bastore
    //   498: dup
    //   499: bipush #31
    //   501: bipush #106
    //   503: bastore
    //   504: invokespecial <init> : ([B)V
    //   507: putstatic burp/Zkdc.Zv : Ljava/lang/Object;
    //   510: return
  }
  
  private static Throwable a(Throwable paramThrowable) {
    return paramThrowable;
  }
  
  private static String a(int paramInt1, int paramInt2) {
    int i = (paramInt1 ^ 0x722B) & 0xFFFF;
    if (b[i] == null) {
      char[] arrayOfChar = a[i].toCharArray();
      switch (arrayOfChar[0] & 0xFF) {
        case 0:
        
        case 1:
        
        case 2:
        
        case 3:
        
        case 4:
        
        case 5:
        
        case 6:
        
        case 7:
        
        case 8:
        
        case 9:
        
        case 10:
        
        case 11:
        
        case 12:
        
        case 13:
        
        case 14:
        
        case 15:
        
        case 16:
        
        case 17:
        
        case 18:
        
        case 19:
        
        case 20:
        
        case 21:
        
        case 22:
        
        case 23:
        
        case 24:
        
        case 25:
        
        case 26:
        
        case 27:
        
        case 28:
        
        case 29:
        
        case 30:
        
        case 31:
        
        case 32:
        
        case 33:
        
        case 34:
        
        case 35:
        
        case 36:
        
        case 37:
        
        case 38:
        
        case 39:
        
        case 40:
        
        case 41:
        
        case 42:
        
        case 43:
        
        case 44:
        
        case 45:
        
        case 46:
        
        case 47:
        
        case 48:
        
        case 49:
        
        case 50:
        
        case 51:
        
        case 52:
        
        case 53:
        
        case 54:
        
        case 55:
        
        case 56:
        
        case 57:
        
        case 58:
        
        case 59:
        
        case 60:
        
        case 61:
        
        case 62:
        
        case 63:
        
        case 64:
        
        case 65:
        
        case 66:
        
        case 67:
        
        case 68:
        
        case 69:
        
        case 70:
        
        case 71:
        
        case 72:
        
        case 73:
        
        case 74:
        
        case 75:
        
        case 76:
        
        case 77:
        
        case 78:
        
        case 79:
        
        case 80:
        
        case 81:
        
        case 82:
        
        case 83:
        
        case 84:
        
        case 85:
        
        case 86:
        
        case 87:
        
        case 88:
        
        case 89:
        
        case 90:
        
        case 91:
        
        case 92:
        
        case 93:
        
        case 94:
        
        case 95:
        
        case 96:
        
        case 97:
        
        case 98:
        
        case 99:
        
        case 100:
        
        case 101:
        
        case 102:
        
        case 103:
        
        case 104:
        
        case 105:
        
        case 106:
        
        case 107:
        
        case 108:
        
        case 109:
        
        case 110:
        
        case 111:
        
        case 112:
        
        case 113:
        
        case 114:
        
        case 115:
        
        case 116:
        
        case 117:
        
        case 118:
        
        case 119:
        
        case 120:
        
        case 121:
        
        case 122:
        
        case 123:
        
        case 124:
        
        case 125:
        
        case 126:
        
        case 127:
        
        case 128:
        
        case 129:
        
        case 130:
        
        case 131:
        
        case 132:
        
        case 133:
        
        case 134:
        
        case 135:
        
        case 136:
        
        case 137:
        
        case 138:
        
        case 139:
        
        case 140:
        
        case 141:
        
        case 142:
        
        case 143:
        
        case 144:
        
        case 145:
        
        case 146:
        
        case 147:
        
        case 148:
        
        case 149:
        
        case 150:
        
        case 151:
        
        case 152:
        
        case 153:
        
        case 154:
        
        case 155:
        
        case 156:
        
        case 157:
        
        case 158:
        
        case 159:
        
        case 160:
        
        case 161:
        
        case 162:
        
        case 163:
        
        case 164:
        
        case 165:
        
        case 166:
        
        case 167:
        
        case 168:
        
        case 169:
        
        case 170:
        
        case 171:
        
        case 172:
        
        case 173:
        
        case 174:
        
        case 175:
        
        case 176:
        
        case 177:
        
        case 178:
        
        case 179:
        
        case 180:
        
        case 181:
        
        case 182:
        
        case 183:
        
        case 184:
        
        case 185:
        
        case 186:
        
        case 187:
        
        case 188:
        
        case 189:
        
        case 190:
        
        case 191:
        
        case 192:
        
        case 193:
        
        case 194:
        
        case 195:
        
        case 196:
        
        case 197:
        
        case 198:
        
        case 199:
        
        case 200:
        
        case 201:
        
        case 202:
        
        case 203:
        
        case 204:
        
        case 205:
        
        case 206:
        
        case 207:
        
        case 208:
        
        case 209:
        
        case 210:
        
        case 211:
        
        case 212:
        
        case 213:
        
        case 214:
        
        case 215:
        
        case 216:
        
        case 217:
        
        case 218:
        
        case 219:
        
        case 220:
        
        case 221:
        
        case 222:
        
        case 223:
        
        case 224:
        
        case 225:
        
        case 226:
        
        case 227:
        
        case 228:
        
        case 229:
        
        case 230:
        
        case 231:
        
        case 232:
        
        case 233:
        
        case 234:
        
        case 235:
        
        case 236:
        
        case 237:
        
        case 238:
        
        case 239:
        
        case 240:
        
        case 241:
        
        case 242:
        
        case 243:
        
        case 244:
        
        case 245:
        
        case 246:
        
        case 247:
        
        case 248:
        
        case 249:
        
        case 250:
        
        case 251:
        
        case 252:
        
        case 253:
        
        case 254:
        
        default:
          break;
      } 
      byte b1 = 61;
      int j = (paramInt2 & 0xFF) - b1;
      if (j < 0)
        j += 256; 
      int k = ((paramInt2 & 0xFFFF) >>> 8) - b1;
      if (k < 0)
        k += 256; 
      for (byte b2 = 0; b2 < arrayOfChar.length; b2++) {
        int m = b2 % 2;
        if (m == 0) {
          arrayOfChar[b2] = (char)(arrayOfChar[b2] ^ j);
          j = ((j >>> 3 | j << 5) ^ arrayOfChar[b2]) & 0xFF;
        } else {
          arrayOfChar[b2] = (char)(arrayOfChar[b2] ^ k);
          k = ((k >>> 3 | k << 5) ^ arrayOfChar[b2]) & 0xFF;
        } 
      } 
      b[i] = (new String(arrayOfChar)).intern();
    } 
    return b[i];
  }
}


/* Location:              C:\Program Files\BurpSuitePro\burpsuite_pro.jar!\burp\Zkdc.class
 * Java compiler version: 21 (65.0)
 * JD-Core Version:       1.1.3
 */