package burp;

import java.math.BigInteger;

class Zkf6 extends ClassLoader {
  static Object ZS;
  
  static String ZO;
  
  private static final String[] a;
  
  private static final String[] b;
  
  static boolean ZU(Object[] paramArrayOfObject, Object paramObject) throws Throwable {
    // Byte code:
    //   0: invokestatic ZN : ()Z
    //   3: istore_2
    //   4: getstatic burp/Zg61.Zp : Ljava/lang/Object;
    //   7: checkcast java/math/BigInteger
    //   10: getstatic burp/Zk1.Z_ : Ljava/lang/Object;
    //   13: checkcast java/math/BigInteger
    //   16: invokevirtual add : (Ljava/math/BigInteger;)Ljava/math/BigInteger;
    //   19: putstatic burp/Zeub.ZD : Ljava/lang/Object;
    //   22: sipush #-10793
    //   25: sipush #-23620
    //   28: invokestatic a : (II)Ljava/lang/String;
    //   31: iconst_1
    //   32: ldc burp/Zlav
    //   34: invokevirtual getClassLoader : ()Ljava/lang/ClassLoader;
    //   37: invokestatic forName : (Ljava/lang/String;ZLjava/lang/ClassLoader;)Ljava/lang/Class;
    //   40: invokevirtual getDeclaredFields : ()[Ljava/lang/reflect/Field;
    //   43: astore_3
    //   44: aload_3
    //   45: arraylength
    //   46: istore #4
    //   48: iconst_0
    //   49: istore #5
    //   51: iload #5
    //   53: iload #4
    //   55: if_icmpge -> 192
    //   58: aload_3
    //   59: iload #5
    //   61: aaload
    //   62: astore #6
    //   64: aload #6
    //   66: invokevirtual getModifiers : ()I
    //   69: invokestatic isStatic : (I)Z
    //   72: ifne -> 82
    //   75: goto -> 185
    //   78: invokestatic a : (Ljava/lang/Throwable;)Ljava/lang/Throwable;
    //   81: athrow
    //   82: aload #6
    //   84: invokevirtual getType : ()Ljava/lang/Class;
    //   87: astore #7
    //   89: aload #7
    //   91: ifnull -> 172
    //   94: aload #7
    //   96: invokevirtual isPrimitive : ()Z
    //   99: ifne -> 172
    //   102: goto -> 109
    //   105: invokestatic a : (Ljava/lang/Throwable;)Ljava/lang/Throwable;
    //   108: athrow
    //   109: aload #7
    //   111: invokevirtual getPackage : ()Ljava/lang/Package;
    //   114: ifnull -> 172
    //   117: goto -> 124
    //   120: invokestatic a : (Ljava/lang/Throwable;)Ljava/lang/Throwable;
    //   123: athrow
    //   124: aload #7
    //   126: invokevirtual getPackage : ()Ljava/lang/Package;
    //   129: invokevirtual getName : ()Ljava/lang/String;
    //   132: ifnull -> 172
    //   135: goto -> 142
    //   138: invokestatic a : (Ljava/lang/Throwable;)Ljava/lang/Throwable;
    //   141: athrow
    //   142: aload #7
    //   144: invokevirtual getPackage : ()Ljava/lang/Package;
    //   147: invokevirtual getName : ()Ljava/lang/String;
    //   150: sipush #-10800
    //   153: sipush #10638
    //   156: invokestatic a : (II)Ljava/lang/String;
    //   159: invokevirtual startsWith : (Ljava/lang/String;)Z
    //   162: ifne -> 172
    //   165: goto -> 172
    //   168: invokestatic a : (Ljava/lang/Throwable;)Ljava/lang/Throwable;
    //   171: athrow
    //   172: aload #6
    //   174: iconst_1
    //   175: invokevirtual setAccessible : (Z)V
    //   178: aload #6
    //   180: aconst_null
    //   181: invokevirtual get : (Ljava/lang/Object;)Ljava/lang/Object;
    //   184: pop
    //   185: iinc #5, 1
    //   188: iload_2
    //   189: ifne -> 51
    //   192: sipush #-10797
    //   195: sipush #-6446
    //   198: invokestatic a : (II)Ljava/lang/String;
    //   201: invokestatic forName : (Ljava/lang/String;)Ljava/lang/Class;
    //   204: invokevirtual getDeclaredMethods : ()[Ljava/lang/reflect/Method;
    //   207: astore_3
    //   208: aload_3
    //   209: arraylength
    //   210: istore #4
    //   212: iconst_0
    //   213: istore #5
    //   215: iload #5
    //   217: iload #4
    //   219: if_icmpge -> 351
    //   222: aload_3
    //   223: iload #5
    //   225: aaload
    //   226: astore #6
    //   228: aload #6
    //   230: invokevirtual getParameterTypes : ()[Ljava/lang/Class;
    //   233: pop
    //   234: aload #6
    //   236: invokevirtual getModifiers : ()I
    //   239: invokestatic isStatic : (I)Z
    //   242: ifeq -> 337
    //   245: aload #6
    //   247: invokevirtual getParameterTypes : ()[Ljava/lang/Class;
    //   250: arraylength
    //   251: iconst_2
    //   252: if_icmpne -> 337
    //   255: goto -> 262
    //   258: invokestatic a : (Ljava/lang/Throwable;)Ljava/lang/Throwable;
    //   261: athrow
    //   262: aload #6
    //   264: invokevirtual getReturnType : ()Ljava/lang/Class;
    //   267: getstatic java/lang/Void.TYPE : Ljava/lang/Class;
    //   270: invokevirtual equals : (Ljava/lang/Object;)Z
    //   273: ifeq -> 337
    //   276: goto -> 283
    //   279: invokestatic a : (Ljava/lang/Throwable;)Ljava/lang/Throwable;
    //   282: athrow
    //   283: aload #6
    //   285: iconst_1
    //   286: invokevirtual setAccessible : (Z)V
    //   289: aload #6
    //   291: aconst_null
    //   292: iconst_2
    //   293: anewarray java/lang/Object
    //   296: dup
    //   297: iconst_0
    //   298: aload_0
    //   299: aastore
    //   300: dup
    //   301: iconst_1
    //   302: aload_1
    //   303: ifnonnull -> 321
    //   306: goto -> 313
    //   309: invokestatic a : (Ljava/lang/Throwable;)Ljava/lang/Throwable;
    //   312: athrow
    //   313: aload_1
    //   314: goto -> 328
    //   317: invokestatic a : (Ljava/lang/Throwable;)Ljava/lang/Throwable;
    //   320: athrow
    //   321: aload_1
    //   322: checkcast [B
    //   325: invokevirtual clone : ()Ljava/lang/Object;
    //   328: aastore
    //   329: invokevirtual invoke : (Ljava/lang/Object;[Ljava/lang/Object;)Ljava/lang/Object;
    //   332: pop
    //   333: iload_2
    //   334: ifne -> 351
    //   337: iinc #5, 1
    //   340: iload_2
    //   341: ifne -> 215
    //   344: goto -> 351
    //   347: invokestatic a : (Ljava/lang/Throwable;)Ljava/lang/Throwable;
    //   350: athrow
    //   351: getstatic burp/Zgsy.ZC : Ljava/lang/Object;
    //   354: checkcast java/math/BigInteger
    //   357: invokevirtual toByteArray : ()[B
    //   360: astore_3
    //   361: new java/lang/StringBuilder
    //   364: dup
    //   365: invokespecial <init> : ()V
    //   368: astore #5
    //   370: aload #5
    //   372: sipush #-10799
    //   375: sipush #-4764
    //   378: invokestatic a : (II)Ljava/lang/String;
    //   381: invokevirtual append : (Ljava/lang/String;)Ljava/lang/StringBuilder;
    //   384: pop
    //   385: aload_3
    //   386: astore #6
    //   388: aload #6
    //   390: arraylength
    //   391: istore #7
    //   393: iconst_0
    //   394: istore #8
    //   396: iload #8
    //   398: iload #7
    //   400: if_icmpge -> 426
    //   403: aload #6
    //   405: iload #8
    //   407: baload
    //   408: istore #9
    //   410: aload #5
    //   412: iload #9
    //   414: i2c
    //   415: invokevirtual append : (C)Ljava/lang/StringBuilder;
    //   418: pop
    //   419: iinc #8, 1
    //   422: iload_2
    //   423: ifne -> 396
    //   426: aload #5
    //   428: sipush #-10789
    //   431: sipush #14661
    //   434: invokestatic a : (II)Ljava/lang/String;
    //   437: ldc ''
    //   439: invokestatic getProperty : (Ljava/lang/String;Ljava/lang/String;)Ljava/lang/String;
    //   442: invokevirtual toLowerCase : ()Ljava/lang/String;
    //   445: invokevirtual append : (Ljava/lang/String;)Ljava/lang/StringBuilder;
    //   448: pop
    //   449: aload #5
    //   451: sipush #-10791
    //   454: sipush #-18714
    //   457: invokestatic a : (II)Ljava/lang/String;
    //   460: ldc ''
    //   462: invokestatic getProperty : (Ljava/lang/String;Ljava/lang/String;)Ljava/lang/String;
    //   465: invokevirtual toLowerCase : ()Ljava/lang/String;
    //   468: invokevirtual append : (Ljava/lang/String;)Ljava/lang/StringBuilder;
    //   471: pop
    //   472: aload #5
    //   474: invokevirtual toString : ()Ljava/lang/String;
    //   477: invokevirtual getBytes : ()[B
    //   480: astore #4
    //   482: aload #4
    //   484: astore_3
    //   485: aload_3
    //   486: arraylength
    //   487: bipush #8
    //   489: iadd
    //   490: bipush #6
    //   492: ishr
    //   493: iconst_1
    //   494: iadd
    //   495: bipush #16
    //   497: imul
    //   498: newarray int
    //   500: astore #5
    //   502: iconst_0
    //   503: istore #6
    //   505: iload #6
    //   507: aload_3
    //   508: arraylength
    //   509: if_icmpge -> 552
    //   512: aload_3
    //   513: iload #6
    //   515: baload
    //   516: sipush #255
    //   519: iand
    //   520: istore #7
    //   522: aload #5
    //   524: iload #6
    //   526: iconst_2
    //   527: ishr
    //   528: dup2
    //   529: iaload
    //   530: iload #7
    //   532: bipush #24
    //   534: iload #6
    //   536: iconst_4
    //   537: irem
    //   538: bipush #8
    //   540: imul
    //   541: isub
    //   542: ishl
    //   543: ior
    //   544: iastore
    //   545: iinc #6, 1
    //   548: iload_2
    //   549: ifne -> 505
    //   552: aload #5
    //   554: iload #6
    //   556: iconst_2
    //   557: ishr
    //   558: dup2
    //   559: iaload
    //   560: sipush #128
    //   563: bipush #24
    //   565: iload #6
    //   567: iconst_4
    //   568: irem
    //   569: bipush #8
    //   571: imul
    //   572: isub
    //   573: ishl
    //   574: ior
    //   575: iastore
    //   576: aload #5
    //   578: aload #5
    //   580: arraylength
    //   581: iconst_1
    //   582: isub
    //   583: aload_3
    //   584: arraylength
    //   585: bipush #8
    //   587: imul
    //   588: iastore
    //   589: bipush #80
    //   591: newarray int
    //   593: astore #7
    //   595: ldc 1732584193
    //   597: istore #8
    //   599: ldc -271733879
    //   601: istore #9
    //   603: ldc -1732584194
    //   605: istore #10
    //   607: ldc 271733878
    //   609: istore #11
    //   611: ldc -1009589776
    //   613: istore #12
    //   615: iconst_0
    //   616: istore #6
    //   618: iload #6
    //   620: aload #5
    //   622: arraylength
    //   623: if_icmpge -> 945
    //   626: iload #8
    //   628: istore #13
    //   630: iload #9
    //   632: istore #14
    //   634: iload #10
    //   636: istore #15
    //   638: iload #11
    //   640: istore #16
    //   642: iload #12
    //   644: istore #17
    //   646: iconst_0
    //   647: istore #18
    //   649: iload #18
    //   651: bipush #80
    //   653: if_icmpge -> 903
    //   656: iload #18
    //   658: bipush #16
    //   660: if_icmpge -> 687
    //   663: aload #7
    //   665: iload #18
    //   667: aload #5
    //   669: iload #6
    //   671: iload #18
    //   673: iadd
    //   674: iaload
    //   675: iastore
    //   676: iload_2
    //   677: ifne -> 742
    //   680: goto -> 687
    //   683: invokestatic a : (Ljava/lang/Throwable;)Ljava/lang/Throwable;
    //   686: athrow
    //   687: aload #7
    //   689: iload #18
    //   691: iconst_3
    //   692: isub
    //   693: iaload
    //   694: aload #7
    //   696: iload #18
    //   698: bipush #8
    //   700: isub
    //   701: iaload
    //   702: ixor
    //   703: aload #7
    //   705: iload #18
    //   707: bipush #14
    //   709: isub
    //   710: iaload
    //   711: ixor
    //   712: aload #7
    //   714: iload #18
    //   716: bipush #16
    //   718: isub
    //   719: iaload
    //   720: ixor
    //   721: istore #19
    //   723: iload #19
    //   725: iconst_1
    //   726: ishl
    //   727: iload #19
    //   729: bipush #31
    //   731: iushr
    //   732: ior
    //   733: istore #20
    //   735: aload #7
    //   737: iload #18
    //   739: iload #20
    //   741: iastore
    //   742: iload #8
    //   744: iconst_5
    //   745: ishl
    //   746: iload #8
    //   748: bipush #27
    //   750: iushr
    //   751: ior
    //   752: istore #19
    //   754: iload #19
    //   756: iload #12
    //   758: iadd
    //   759: aload #7
    //   761: iload #18
    //   763: iaload
    //   764: iadd
    //   765: iload #18
    //   767: bipush #20
    //   769: if_icmpge -> 795
    //   772: ldc 1518500249
    //   774: iload #9
    //   776: iload #10
    //   778: iand
    //   779: iload #9
    //   781: iconst_m1
    //   782: ixor
    //   783: iload #11
    //   785: iand
    //   786: ior
    //   787: iadd
    //   788: goto -> 865
    //   791: invokestatic a : (Ljava/lang/Throwable;)Ljava/lang/Throwable;
    //   794: athrow
    //   795: iload #18
    //   797: bipush #40
    //   799: if_icmpge -> 820
    //   802: ldc 1859775393
    //   804: iload #9
    //   806: iload #10
    //   808: ixor
    //   809: iload #11
    //   811: ixor
    //   812: iadd
    //   813: goto -> 865
    //   816: invokestatic a : (Ljava/lang/Throwable;)Ljava/lang/Throwable;
    //   819: athrow
    //   820: iload #18
    //   822: bipush #60
    //   824: if_icmpge -> 854
    //   827: ldc -1894007588
    //   829: iload #9
    //   831: iload #10
    //   833: iand
    //   834: iload #9
    //   836: iload #11
    //   838: iand
    //   839: ior
    //   840: iload #10
    //   842: iload #11
    //   844: iand
    //   845: ior
    //   846: iadd
    //   847: goto -> 865
    //   850: invokestatic a : (Ljava/lang/Throwable;)Ljava/lang/Throwable;
    //   853: athrow
    //   854: ldc -899497514
    //   856: iload #9
    //   858: iload #10
    //   860: ixor
    //   861: iload #11
    //   863: ixor
    //   864: iadd
    //   865: iadd
    //   866: istore #20
    //   868: iload #11
    //   870: istore #12
    //   872: iload #10
    //   874: istore #11
    //   876: iload #9
    //   878: bipush #30
    //   880: ishl
    //   881: iload #9
    //   883: iconst_2
    //   884: iushr
    //   885: ior
    //   886: istore #10
    //   888: iload #8
    //   890: istore #9
    //   892: iload #20
    //   894: istore #8
    //   896: iinc #18, 1
    //   899: iload_2
    //   900: ifne -> 649
    //   903: iload #8
    //   905: iload #13
    //   907: iadd
    //   908: istore #8
    //   910: iload #9
    //   912: iload #14
    //   914: iadd
    //   915: istore #9
    //   917: iload #10
    //   919: iload #15
    //   921: iadd
    //   922: istore #10
    //   924: iload #11
    //   926: iload #16
    //   928: iadd
    //   929: istore #11
    //   931: iload #12
    //   933: iload #17
    //   935: iadd
    //   936: istore #12
    //   938: iinc #6, 16
    //   941: iload_2
    //   942: ifne -> 618
    //   945: iconst_5
    //   946: newarray int
    //   948: dup
    //   949: iconst_0
    //   950: iload #8
    //   952: iastore
    //   953: dup
    //   954: iconst_1
    //   955: iload #9
    //   957: iastore
    //   958: dup
    //   959: iconst_2
    //   960: iload #10
    //   962: iastore
    //   963: dup
    //   964: iconst_3
    //   965: iload #11
    //   967: iastore
    //   968: dup
    //   969: iconst_4
    //   970: iload #12
    //   972: iastore
    //   973: astore #13
    //   975: bipush #20
    //   977: newarray byte
    //   979: astore #14
    //   981: iconst_0
    //   982: istore #15
    //   984: iload #15
    //   986: bipush #20
    //   988: if_icmpge -> 1029
    //   991: aload #13
    //   993: iload #15
    //   995: iconst_4
    //   996: idiv
    //   997: iaload
    //   998: istore #16
    //   1000: iconst_3
    //   1001: iload #15
    //   1003: iconst_4
    //   1004: irem
    //   1005: isub
    //   1006: bipush #8
    //   1008: imul
    //   1009: istore #17
    //   1011: aload #14
    //   1013: iload #15
    //   1015: iload #16
    //   1017: iload #17
    //   1019: iushr
    //   1020: i2b
    //   1021: bastore
    //   1022: iinc #15, 1
    //   1025: iload_2
    //   1026: ifne -> 984
    //   1029: aload #14
    //   1031: astore #4
    //   1033: getstatic burp/Zsfg.Zh : Ljava/lang/String;
    //   1036: getstatic burp/Zsko.ZD : Ljava/lang/Object;
    //   1039: checkcast java/math/BigInteger
    //   1042: invokevirtual intValue : ()I
    //   1045: bipush #32
    //   1047: irem
    //   1048: invokestatic abs : (I)I
    //   1051: invokevirtual charAt : (I)C
    //   1054: getstatic burp/Zsp9.ZA : Ljava/lang/String;
    //   1057: getstatic burp/Zm0d.Zz : Ljava/lang/Object;
    //   1060: checkcast java/math/BigInteger
    //   1063: invokevirtual intValue : ()I
    //   1066: bipush #32
    //   1068: irem
    //   1069: invokestatic abs : (I)I
    //   1072: invokevirtual charAt : (I)C
    //   1075: if_icmple -> 1190
    //   1078: getstatic burp/Zsfj.Zg : Ljava/lang/String;
    //   1081: getstatic burp/Zg4l.ZI : Ljava/lang/Object;
    //   1084: checkcast java/math/BigInteger
    //   1087: invokevirtual intValue : ()I
    //   1090: bipush #32
    //   1092: irem
    //   1093: invokestatic abs : (I)I
    //   1096: invokevirtual charAt : (I)C
    //   1099: getstatic burp/Zej8.ZP : Ljava/lang/String;
    //   1102: getstatic burp/Zml9.ZH : Ljava/lang/Object;
    //   1105: checkcast java/math/BigInteger
    //   1108: invokevirtual intValue : ()I
    //   1111: bipush #32
    //   1113: irem
    //   1114: invokestatic abs : (I)I
    //   1117: invokevirtual charAt : (I)C
    //   1120: if_icmpgt -> 1190
    //   1123: goto -> 1130
    //   1126: invokestatic a : (Ljava/lang/Throwable;)Ljava/lang/Throwable;
    //   1129: athrow
    //   1130: getstatic burp/Zlwc.ZM : Ljava/lang/String;
    //   1133: getstatic burp/Zrkw.ZV : Ljava/lang/Object;
    //   1136: checkcast java/math/BigInteger
    //   1139: invokevirtual intValue : ()I
    //   1142: bipush #32
    //   1144: irem
    //   1145: invokestatic abs : (I)I
    //   1148: invokevirtual charAt : (I)C
    //   1151: getstatic burp/Zr9u.Zc : Ljava/lang/String;
    //   1154: getstatic burp/Ztnn.ZA : Ljava/lang/Object;
    //   1157: checkcast java/math/BigInteger
    //   1160: invokevirtual intValue : ()I
    //   1163: bipush #32
    //   1165: irem
    //   1166: invokestatic abs : (I)I
    //   1169: invokevirtual charAt : (I)C
    //   1172: if_icmpgt -> 1190
    //   1175: goto -> 1182
    //   1178: invokestatic a : (Ljava/lang/Throwable;)Ljava/lang/Throwable;
    //   1181: athrow
    //   1182: iconst_1
    //   1183: goto -> 1191
    //   1186: invokestatic a : (Ljava/lang/Throwable;)Ljava/lang/Throwable;
    //   1189: athrow
    //   1190: iconst_0
    //   1191: ireturn
    //   1192: astore_3
    //   1193: new java/lang/Exception
    //   1196: dup
    //   1197: aload_3
    //   1198: invokevirtual getMessage : ()Ljava/lang/String;
    //   1201: invokespecial <init> : (Ljava/lang/String;)V
    //   1204: athrow
    // Exception table:
    //   from	to	target	type
    //   4	1191	1192	java/lang/Throwable
    //   64	78	78	java/lang/Throwable
    //   89	102	105	java/lang/Throwable
    //   94	117	120	java/lang/Throwable
    //   109	135	138	java/lang/Throwable
    //   124	165	168	java/lang/Throwable
    //   228	255	258	java/lang/Throwable
    //   245	276	279	java/lang/Throwable
    //   262	306	309	java/lang/Throwable
    //   283	317	317	java/lang/Throwable
    //   328	344	347	java/lang/Throwable
    //   656	680	683	java/lang/Throwable
    //   754	791	791	java/lang/Throwable
    //   795	816	816	java/lang/Throwable
    //   820	850	850	java/lang/Throwable
    //   1033	1123	1126	java/lang/Throwable
    //   1078	1175	1178	java/lang/Throwable
    //   1130	1186	1186	java/lang/Throwable
  }
  
  static void ZA(Object paramObject) {
    Zxwf.ZX = a(-10790, 28679);
    Zxwf.Zi = new BigInteger(a(-10794, -26990));
    boolean bool = Zt2e.ZN();
    try {
      try {
        if (Zepy.Zg.charAt(Math.abs(((BigInteger)Zrp2.Zw).intValue() % 32)) <= Zrjq.Zx.charAt(Math.abs(((BigInteger)Zrjq.ZU).intValue() % 32))) {
          try {
            Zb2n.Zt(Class.forName(a(-10796, 10315)));
            if (!bool)
              Zzgh.ZA(Class.forName(a(-10798, -14759))); 
          } catch (Throwable throwable) {
            throw a(null);
          } 
          return;
        } 
      } catch (Throwable throwable) {
        throw a(null);
      } 
      Zzgh.ZA(Class.forName(a(-10798, -14759)));
    } catch (Throwable throwable) {}
  }
  
  static void ZD(Object[] paramArrayOfObject, Object paramObject) throws Throwable {}
  
  static {
    // Byte code:
    //   0: bipush #12
    //   2: anewarray java/lang/String
    //   5: astore #5
    //   7: iconst_0
    //   8: istore_3
    //   9: ldc '\\fÃ²Ã‹o]ÃµÂ³Âµ\\t6CÂŒYÂµ3\\b9\\bÂžRÂ™{ 1Ã†ÃÂ°Ã…Â˜Ã»Km`Â¯u=R.aÃ­ Âˆ;Ã­Ã„ÂƒMÃ¾Ã˜Ã¤Â—\ÃºÂ±Â¦M*Â¯q[?Ã™Ã™ÃŽÃ¾Â‰Ã±Ã¡'ÃÃ¸rÂÃ¬Ã†Â§ÃŒÂ®Ã‹Ãª\\rÂ‡rLÃ¬Â²3Â£Ã¼aÃ§qÃ²Ã¶'~Â¼!fÃ³>lcÃµn?Ã˜G'Ã³Â¬x\\tL<ÃƒÂ¶\ÃŽ5Â†Â¯\\t0LÃ±Â­&Ã. AÃžywyÃ¼Â­Ã¦>}ÂŠPÂ‘Ã¡$ÂœBÂ•.ÃœjÂ…KÃ¤Â¢Â± Â w [Â–Y&Â‘ÃrÃ¸> Â·Â‚ Â°Ã°P#Ã¯Ã‰YÂªCÂ·Â§Ã¡~Â¸&Â«6|'
    //   11: dup
    //   12: astore_2
    //   13: invokevirtual length : ()I
    //   16: istore #4
    //   18: bipush #9
    //   20: istore_1
    //   21: iconst_m1
    //   22: istore_0
    //   23: bipush #117
    //   25: iinc #0, 1
    //   28: aload_2
    //   29: iload_0
    //   30: dup
    //   31: iload_1
    //   32: iadd
    //   33: invokevirtual substring : (II)Ljava/lang/String;
    //   36: iconst_m1
    //   37: goto -> 143
    //   40: aload #5
    //   42: swap
    //   43: iload_3
    //   44: iinc #3, 1
    //   47: swap
    //   48: aastore
    //   49: iload_0
    //   50: iload_1
    //   51: iadd
    //   52: dup
    //   53: istore_0
    //   54: iload #4
    //   56: if_icmpge -> 68
    //   59: aload_2
    //   60: iload_0
    //   61: invokevirtual charAt : (I)C
    //   64: istore_1
    //   65: goto -> 23
    //   68: ldc 'zÂ•Ã›Ã©Ã…Ã¶Ã–Ã¹ÃaÂ¤EmMÃ°ÃœÂ£Ã±Â¥Â¿HÃ¹Â“Ã³lÂ'Ã“2Ã¹Â¶ThÂ™Â²Â©Ã½"ÃÃ¼ÂˆÃ¤Â„pGÃŠÂ\\nÂ¯Â°'Ã¡Â´Â«Ã…ÂˆÃ«ÃŸÃ¡Âˆ\\nÃ‰Ã¢Â«ÂˆHÂƒ`\\tÂŠ"VÂ´Â’Y\'
    //   70: dup
    //   71: astore_2
    //   72: invokevirtual length : ()I
    //   75: istore #4
    //   77: bipush #77
    //   79: istore_1
    //   80: iconst_m1
    //   81: istore_0
    //   82: bipush #50
    //   84: iinc #0, 1
    //   87: aload_2
    //   88: iload_0
    //   89: dup
    //   90: iload_1
    //   91: iadd
    //   92: invokevirtual substring : (II)Ljava/lang/String;
    //   95: iconst_0
    //   96: goto -> 143
    //   99: aload #5
    //   101: swap
    //   102: iload_3
    //   103: iinc #3, 1
    //   106: swap
    //   107: aastore
    //   108: iload_0
    //   109: iload_1
    //   110: iadd
    //   111: dup
    //   112: istore_0
    //   113: iload #4
    //   115: if_icmpge -> 127
    //   118: aload_2
    //   119: iload_0
    //   120: invokevirtual charAt : (I)C
    //   123: istore_1
    //   124: goto -> 82
    //   127: aload #5
    //   129: putstatic burp/Zkf6.a : [Ljava/lang/String;
    //   132: bipush #12
    //   134: anewarray java/lang/String
    //   137: putstatic burp/Zkf6.b : [Ljava/lang/String;
    //   140: goto -> 300
    //   143: dup_x2
    //   144: pop
    //   145: invokevirtual toCharArray : ()[C
    //   148: dup_x1
    //   149: arraylength
    //   150: dup_x2
    //   151: pop
    //   152: iconst_0
    //   153: istore #6
    //   155: dup2_x1
    //   156: pop2
    //   157: dup_x2
    //   158: iconst_1
    //   159: if_icmpgt -> 259
    //   162: dup2
    //   163: swap
    //   164: iload #6
    //   166: dup2_x1
    //   167: caload
    //   168: swap
    //   169: iload #6
    //   171: bipush #7
    //   173: irem
    //   174: tableswitch default -> 241, 0 -> 212, 1 -> 217, 2 -> 222, 3 -> 226, 4 -> 231, 5 -> 236
    //   212: bipush #70
    //   214: goto -> 243
    //   217: bipush #56
    //   219: goto -> 243
    //   222: iconst_5
    //   223: goto -> 243
    //   226: bipush #70
    //   228: goto -> 243
    //   231: bipush #77
    //   233: goto -> 243
    //   236: bipush #47
    //   238: goto -> 243
    //   241: bipush #83
    //   243: ixor
    //   244: ixor
    //   245: i2c
    //   246: castore
    //   247: iinc #6, 1
    //   250: dup
    //   251: ifne -> 259
    //   254: dup2
    //   255: dup_x1
    //   256: goto -> 166
    //   259: dup2_x1
    //   260: pop2
    //   261: dup_x2
    //   262: iload #6
    //   264: if_icmpgt -> 162
    //   267: pop
    //   268: new java/lang/String
    //   271: dup_x1
    //   272: swap
    //   273: invokespecial <init> : ([C)V
    //   276: invokevirtual intern : ()Ljava/lang/String;
    //   279: swap
    //   280: pop
    //   281: swap
    //   282: tableswitch default -> 40, 0 -> 99
    //   300: new java/math/BigInteger
    //   303: dup
    //   304: sipush #-10792
    //   307: sipush #6168
    //   310: invokestatic a : (II)Ljava/lang/String;
    //   313: invokespecial <init> : (Ljava/lang/String;)V
    //   316: putstatic burp/Zkf6.ZS : Ljava/lang/Object;
    //   319: sipush #-10795
    //   322: sipush #-12256
    //   325: invokestatic a : (II)Ljava/lang/String;
    //   328: putstatic burp/Zkf6.ZO : Ljava/lang/String;
    //   331: return
  }
  
  private static Throwable a(Throwable paramThrowable) {
    return paramThrowable;
  }
  
  private static String a(int paramInt1, int paramInt2) {
    int i = (paramInt1 ^ 0xFFFFD5D2) & 0xFFFF;
    if (b[i] == null) {
      char[] arrayOfChar = a[i].toCharArray();
      switch (arrayOfChar[0] & 0xFF) {
        case 0:
        
        case 1:
        
        case 2:
        
        case 3:
        
        case 4:
        
        case 5:
        
        case 6:
        
        case 7:
        
        case 8:
        
        case 9:
        
        case 10:
        
        case 11:
        
        case 12:
        
        case 13:
        
        case 14:
        
        case 15:
        
        case 16:
        
        case 17:
        
        case 18:
        
        case 19:
        
        case 20:
        
        case 21:
        
        case 22:
        
        case 23:
        
        case 24:
        
        case 25:
        
        case 26:
        
        case 27:
        
        case 28:
        
        case 29:
        
        case 30:
        
        case 31:
        
        case 32:
        
        case 33:
        
        case 34:
        
        case 35:
        
        case 36:
        
        case 37:
        
        case 38:
        
        case 39:
        
        case 40:
        
        case 41:
        
        case 42:
        
        case 43:
        
        case 44:
        
        case 45:
        
        case 46:
        
        case 47:
        
        case 48:
        
        case 49:
        
        case 50:
        
        case 51:
        
        case 52:
        
        case 53:
        
        case 54:
        
        case 55:
        
        case 56:
        
        case 57:
        
        case 58:
        
        case 59:
        
        case 60:
        
        case 61:
        
        case 62:
        
        case 63:
        
        case 64:
        
        case 65:
        
        case 66:
        
        case 67:
        
        case 68:
        
        case 69:
        
        case 70:
        
        case 71:
        
        case 72:
        
        case 73:
        
        case 74:
        
        case 75:
        
        case 76:
        
        case 77:
        
        case 78:
        
        case 79:
        
        case 80:
        
        case 81:
        
        case 82:
        
        case 83:
        
        case 84:
        
        case 85:
        
        case 86:
        
        case 87:
        
        case 88:
        
        case 89:
        
        case 90:
        
        case 91:
        
        case 92:
        
        case 93:
        
        case 94:
        
        case 95:
        
        case 96:
        
        case 97:
        
        case 98:
        
        case 99:
        
        case 100:
        
        case 101:
        
        case 102:
        
        case 103:
        
        case 104:
        
        case 105:
        
        case 106:
        
        case 107:
        
        case 108:
        
        case 109:
        
        case 110:
        
        case 111:
        
        case 112:
        
        case 113:
        
        case 114:
        
        case 115:
        
        case 116:
        
        case 117:
        
        case 118:
        
        case 119:
        
        case 120:
        
        case 121:
        
        case 122:
        
        case 123:
        
        case 124:
        
        case 125:
        
        case 126:
        
        case 127:
        
        case 128:
        
        case 129:
        
        case 130:
        
        case 131:
        
        case 132:
        
        case 133:
        
        case 134:
        
        case 135:
        
        case 136:
        
        case 137:
        
        case 138:
        
        case 139:
        
        case 140:
        
        case 141:
        
        case 142:
        
        case 143:
        
        case 144:
        
        case 145:
        
        case 146:
        
        case 147:
        
        case 148:
        
        case 149:
        
        case 150:
        
        case 151:
        
        case 152:
        
        case 153:
        
        case 154:
        
        case 155:
        
        case 156:
        
        case 157:
        
        case 158:
        
        case 159:
        
        case 160:
        
        case 161:
        
        case 162:
        
        case 163:
        
        case 164:
        
        case 165:
        
        case 166:
        
        case 167:
        
        case 168:
        
        case 169:
        
        case 170:
        
        case 171:
        
        case 172:
        
        case 173:
        
        case 174:
        
        case 175:
        
        case 176:
        
        case 177:
        
        case 178:
        
        case 179:
        
        case 180:
        
        case 181:
        
        case 182:
        
        case 183:
        
        case 184:
        
        case 185:
        
        case 186:
        
        case 187:
        
        case 188:
        
        case 189:
        
        case 190:
        
        case 191:
        
        case 192:
        
        case 193:
        
        case 194:
        
        case 195:
        
        case 196:
        
        case 197:
        
        case 198:
        
        case 199:
        
        case 200:
        
        case 201:
        
        case 202:
        
        case 203:
        
        case 204:
        
        case 205:
        
        case 206:
        
        case 207:
        
        case 208:
        
        case 209:
        
        case 210:
        
        case 211:
        
        case 212:
        
        case 213:
        
        case 214:
        
        case 215:
        
        case 216:
        
        case 217:
        
        case 218:
        
        case 219:
        
        case 220:
        
        case 221:
        
        case 222:
        
        case 223:
        
        case 224:
        
        case 225:
        
        case 226:
        
        case 227:
        
        case 228:
        
        case 229:
        
        case 230:
        
        case 231:
        
        case 232:
        
        case 233:
        
        case 234:
        
        case 235:
        
        case 236:
        
        case 237:
        
        case 238:
        
        case 239:
        
        case 240:
        
        case 241:
        
        case 242:
        
        case 243:
        
        case 244:
        
        case 245:
        
        case 246:
        
        case 247:
        
        case 248:
        
        case 249:
        
        case 250:
        
        case 251:
        
        case 252:
        
        case 253:
        
        case 254:
        
        default:
          break;
      } 
      byte b1 = 25;
      int j = (paramInt2 & 0xFF) - b1;
      if (j < 0)
        j += 256; 
      int k = ((paramInt2 & 0xFFFF) >>> 8) - b1;
      if (k < 0)
        k += 256; 
      for (byte b2 = 0; b2 < arrayOfChar.length; b2++) {
        int m = b2 % 2;
        if (m == 0) {
          arrayOfChar[b2] = (char)(arrayOfChar[b2] ^ j);
          j = ((j >>> 3 | j << 5) ^ arrayOfChar[b2]) & 0xFF;
        } else {
          arrayOfChar[b2] = (char)(arrayOfChar[b2] ^ k);
          k = ((k >>> 3 | k << 5) ^ arrayOfChar[b2]) & 0xFF;
        } 
      } 
      b[i] = (new String(arrayOfChar)).intern();
    } 
    return b[i];
  }
}


/* Location:              C:\Program Files\BurpSuitePro\burpsuite_pro.jar!\burp\Zkf6.class
 * Java compiler version: 21 (65.0)
 * JD-Core Version:       1.1.3
 */