package burp;

import java.math.BigInteger;

class Zkf9 extends ClassLoader {
  static Object ZX;
  
  static String ZS;
  
  private static final String[] a;
  
  private static final String[] b;
  
  static boolean Zy(Object[] paramArrayOfObject, Object paramObject) throws Throwable {
    // Byte code:
    //   0: invokestatic ZN : ()Z
    //   3: istore_2
    //   4: getstatic burp/Ztfh.Zo : Ljava/lang/Object;
    //   7: checkcast java/math/BigInteger
    //   10: getstatic burp/Zgjs.Za : Ljava/lang/Object;
    //   13: checkcast java/math/BigInteger
    //   16: invokevirtual add : (Ljava/math/BigInteger;)Ljava/math/BigInteger;
    //   19: putstatic burp/Zsun.ZP : Ljava/lang/Object;
    //   22: new java/lang/StringBuilder
    //   25: dup
    //   26: invokespecial <init> : ()V
    //   29: astore_3
    //   30: iconst_0
    //   31: istore #4
    //   33: iload #4
    //   35: bipush #32
    //   37: if_icmpge -> 1371
    //   40: iload #4
    //   42: tableswitch default -> 1364, 0 -> 184, 1 -> 221, 2 -> 258, 3 -> 295, 4 -> 332, 5 -> 369, 6 -> 406, 7 -> 443, 8 -> 480, 9 -> 517, 10 -> 554, 11 -> 591, 12 -> 628, 13 -> 665, 14 -> 702, 15 -> 739, 16 -> 776, 17 -> 813, 18 -> 850, 19 -> 887, 20 -> 924, 21 -> 961, 22 -> 998, 23 -> 1035, 24 -> 1072, 25 -> 1109, 26 -> 1146, 27 -> 1183, 28 -> 1220, 29 -> 1257, 30 -> 1294, 31 -> 1331
    //   184: aload_3
    //   185: getstatic burp/Zz75.ZT : Ljava/lang/String;
    //   188: getstatic burp/Zr04.ZB : Ljava/lang/Object;
    //   191: checkcast java/math/BigInteger
    //   194: invokevirtual intValue : ()I
    //   197: bipush #32
    //   199: irem
    //   200: invokestatic abs : (I)I
    //   203: invokevirtual charAt : (I)C
    //   206: invokevirtual append : (C)Ljava/lang/StringBuilder;
    //   209: pop
    //   210: iload_2
    //   211: ifne -> 1364
    //   214: goto -> 221
    //   217: invokestatic a : (Ljava/lang/Throwable;)Ljava/lang/Throwable;
    //   220: athrow
    //   221: aload_3
    //   222: getstatic burp/Ztq2.Zt : Ljava/lang/String;
    //   225: getstatic burp/Zg2.ZE : Ljava/lang/Object;
    //   228: checkcast java/math/BigInteger
    //   231: invokevirtual intValue : ()I
    //   234: bipush #32
    //   236: irem
    //   237: invokestatic abs : (I)I
    //   240: invokevirtual charAt : (I)C
    //   243: invokevirtual append : (C)Ljava/lang/StringBuilder;
    //   246: pop
    //   247: iload_2
    //   248: ifne -> 1364
    //   251: goto -> 258
    //   254: invokestatic a : (Ljava/lang/Throwable;)Ljava/lang/Throwable;
    //   257: athrow
    //   258: aload_3
    //   259: getstatic burp/Zt3l.Zi : Ljava/lang/String;
    //   262: getstatic burp/Zk7o.ZO : Ljava/lang/Object;
    //   265: checkcast java/math/BigInteger
    //   268: invokevirtual intValue : ()I
    //   271: bipush #32
    //   273: irem
    //   274: invokestatic abs : (I)I
    //   277: invokevirtual charAt : (I)C
    //   280: invokevirtual append : (C)Ljava/lang/StringBuilder;
    //   283: pop
    //   284: iload_2
    //   285: ifne -> 1364
    //   288: goto -> 295
    //   291: invokestatic a : (Ljava/lang/Throwable;)Ljava/lang/Throwable;
    //   294: athrow
    //   295: aload_3
    //   296: getstatic burp/Zro5.ZY : Ljava/lang/String;
    //   299: getstatic burp/Zg0j.ZV : Ljava/lang/Object;
    //   302: checkcast java/math/BigInteger
    //   305: invokevirtual intValue : ()I
    //   308: bipush #32
    //   310: irem
    //   311: invokestatic abs : (I)I
    //   314: invokevirtual charAt : (I)C
    //   317: invokevirtual append : (C)Ljava/lang/StringBuilder;
    //   320: pop
    //   321: iload_2
    //   322: ifne -> 1364
    //   325: goto -> 332
    //   328: invokestatic a : (Ljava/lang/Throwable;)Ljava/lang/Throwable;
    //   331: athrow
    //   332: aload_3
    //   333: getstatic burp/Zszm.Zf : Ljava/lang/String;
    //   336: getstatic burp/Zg_i.ZQ : Ljava/lang/Object;
    //   339: checkcast java/math/BigInteger
    //   342: invokevirtual intValue : ()I
    //   345: bipush #32
    //   347: irem
    //   348: invokestatic abs : (I)I
    //   351: invokevirtual charAt : (I)C
    //   354: invokevirtual append : (C)Ljava/lang/StringBuilder;
    //   357: pop
    //   358: iload_2
    //   359: ifne -> 1364
    //   362: goto -> 369
    //   365: invokestatic a : (Ljava/lang/Throwable;)Ljava/lang/Throwable;
    //   368: athrow
    //   369: aload_3
    //   370: getstatic burp/Zg2z.ZE : Ljava/lang/String;
    //   373: getstatic burp/Zsxm.Zv : Ljava/lang/Object;
    //   376: checkcast java/math/BigInteger
    //   379: invokevirtual intValue : ()I
    //   382: bipush #32
    //   384: irem
    //   385: invokestatic abs : (I)I
    //   388: invokevirtual charAt : (I)C
    //   391: invokevirtual append : (C)Ljava/lang/StringBuilder;
    //   394: pop
    //   395: iload_2
    //   396: ifne -> 1364
    //   399: goto -> 406
    //   402: invokestatic a : (Ljava/lang/Throwable;)Ljava/lang/Throwable;
    //   405: athrow
    //   406: aload_3
    //   407: getstatic burp/Ze54.ZU : Ljava/lang/String;
    //   410: getstatic burp/Zl2g.ZG : Ljava/lang/Object;
    //   413: checkcast java/math/BigInteger
    //   416: invokevirtual intValue : ()I
    //   419: bipush #32
    //   421: irem
    //   422: invokestatic abs : (I)I
    //   425: invokevirtual charAt : (I)C
    //   428: invokevirtual append : (C)Ljava/lang/StringBuilder;
    //   431: pop
    //   432: iload_2
    //   433: ifne -> 1364
    //   436: goto -> 443
    //   439: invokestatic a : (Ljava/lang/Throwable;)Ljava/lang/Throwable;
    //   442: athrow
    //   443: aload_3
    //   444: getstatic burp/Zl1u.ZO : Ljava/lang/String;
    //   447: getstatic burp/Zoa.ZI : Ljava/lang/Object;
    //   450: checkcast java/math/BigInteger
    //   453: invokevirtual intValue : ()I
    //   456: bipush #32
    //   458: irem
    //   459: invokestatic abs : (I)I
    //   462: invokevirtual charAt : (I)C
    //   465: invokevirtual append : (C)Ljava/lang/StringBuilder;
    //   468: pop
    //   469: iload_2
    //   470: ifne -> 1364
    //   473: goto -> 480
    //   476: invokestatic a : (Ljava/lang/Throwable;)Ljava/lang/Throwable;
    //   479: athrow
    //   480: aload_3
    //   481: getstatic burp/Zgs6.ZD : Ljava/lang/String;
    //   484: getstatic burp/Zeno.Zo : Ljava/lang/Object;
    //   487: checkcast java/math/BigInteger
    //   490: invokevirtual intValue : ()I
    //   493: bipush #32
    //   495: irem
    //   496: invokestatic abs : (I)I
    //   499: invokevirtual charAt : (I)C
    //   502: invokevirtual append : (C)Ljava/lang/StringBuilder;
    //   505: pop
    //   506: iload_2
    //   507: ifne -> 1364
    //   510: goto -> 517
    //   513: invokestatic a : (Ljava/lang/Throwable;)Ljava/lang/Throwable;
    //   516: athrow
    //   517: aload_3
    //   518: getstatic burp/Ze_e.ZH : Ljava/lang/String;
    //   521: getstatic burp/Zz1k.ZP : Ljava/lang/Object;
    //   524: checkcast java/math/BigInteger
    //   527: invokevirtual intValue : ()I
    //   530: bipush #32
    //   532: irem
    //   533: invokestatic abs : (I)I
    //   536: invokevirtual charAt : (I)C
    //   539: invokevirtual append : (C)Ljava/lang/StringBuilder;
    //   542: pop
    //   543: iload_2
    //   544: ifne -> 1364
    //   547: goto -> 554
    //   550: invokestatic a : (Ljava/lang/Throwable;)Ljava/lang/Throwable;
    //   553: athrow
    //   554: aload_3
    //   555: getstatic burp/Zlbr.Zr : Ljava/lang/String;
    //   558: getstatic burp/Ztq2.Zj : Ljava/lang/Object;
    //   561: checkcast java/math/BigInteger
    //   564: invokevirtual intValue : ()I
    //   567: bipush #32
    //   569: irem
    //   570: invokestatic abs : (I)I
    //   573: invokevirtual charAt : (I)C
    //   576: invokevirtual append : (C)Ljava/lang/StringBuilder;
    //   579: pop
    //   580: iload_2
    //   581: ifne -> 1364
    //   584: goto -> 591
    //   587: invokestatic a : (Ljava/lang/Throwable;)Ljava/lang/Throwable;
    //   590: athrow
    //   591: aload_3
    //   592: getstatic burp/Zsyu.ZJ : Ljava/lang/String;
    //   595: getstatic burp/Zexn.Zl : Ljava/lang/Object;
    //   598: checkcast java/math/BigInteger
    //   601: invokevirtual intValue : ()I
    //   604: bipush #32
    //   606: irem
    //   607: invokestatic abs : (I)I
    //   610: invokevirtual charAt : (I)C
    //   613: invokevirtual append : (C)Ljava/lang/StringBuilder;
    //   616: pop
    //   617: iload_2
    //   618: ifne -> 1364
    //   621: goto -> 628
    //   624: invokestatic a : (Ljava/lang/Throwable;)Ljava/lang/Throwable;
    //   627: athrow
    //   628: aload_3
    //   629: getstatic burp/Ztd6.Zu : Ljava/lang/String;
    //   632: getstatic burp/Zk9s.ZY : Ljava/lang/Object;
    //   635: checkcast java/math/BigInteger
    //   638: invokevirtual intValue : ()I
    //   641: bipush #32
    //   643: irem
    //   644: invokestatic abs : (I)I
    //   647: invokevirtual charAt : (I)C
    //   650: invokevirtual append : (C)Ljava/lang/StringBuilder;
    //   653: pop
    //   654: iload_2
    //   655: ifne -> 1364
    //   658: goto -> 665
    //   661: invokestatic a : (Ljava/lang/Throwable;)Ljava/lang/Throwable;
    //   664: athrow
    //   665: aload_3
    //   666: getstatic burp/Zgil.ZK : Ljava/lang/String;
    //   669: getstatic burp/Zb29.ZM : Ljava/lang/Object;
    //   672: checkcast java/math/BigInteger
    //   675: invokevirtual intValue : ()I
    //   678: bipush #32
    //   680: irem
    //   681: invokestatic abs : (I)I
    //   684: invokevirtual charAt : (I)C
    //   687: invokevirtual append : (C)Ljava/lang/StringBuilder;
    //   690: pop
    //   691: iload_2
    //   692: ifne -> 1364
    //   695: goto -> 702
    //   698: invokestatic a : (Ljava/lang/Throwable;)Ljava/lang/Throwable;
    //   701: athrow
    //   702: aload_3
    //   703: getstatic burp/Zlxh.ZG : Ljava/lang/String;
    //   706: getstatic burp/Zmou.ZT : Ljava/lang/Object;
    //   709: checkcast java/math/BigInteger
    //   712: invokevirtual intValue : ()I
    //   715: bipush #32
    //   717: irem
    //   718: invokestatic abs : (I)I
    //   721: invokevirtual charAt : (I)C
    //   724: invokevirtual append : (C)Ljava/lang/StringBuilder;
    //   727: pop
    //   728: iload_2
    //   729: ifne -> 1364
    //   732: goto -> 739
    //   735: invokestatic a : (Ljava/lang/Throwable;)Ljava/lang/Throwable;
    //   738: athrow
    //   739: aload_3
    //   740: getstatic burp/Zg2.ZN : Ljava/lang/String;
    //   743: getstatic burp/Zs00.ZF : Ljava/lang/Object;
    //   746: checkcast java/math/BigInteger
    //   749: invokevirtual intValue : ()I
    //   752: bipush #32
    //   754: irem
    //   755: invokestatic abs : (I)I
    //   758: invokevirtual charAt : (I)C
    //   761: invokevirtual append : (C)Ljava/lang/StringBuilder;
    //   764: pop
    //   765: iload_2
    //   766: ifne -> 1364
    //   769: goto -> 776
    //   772: invokestatic a : (Ljava/lang/Throwable;)Ljava/lang/Throwable;
    //   775: athrow
    //   776: aload_3
    //   777: getstatic burp/Zxzv.ZI : Ljava/lang/String;
    //   780: getstatic burp/Zter.Zc : Ljava/lang/Object;
    //   783: checkcast java/math/BigInteger
    //   786: invokevirtual intValue : ()I
    //   789: bipush #32
    //   791: irem
    //   792: invokestatic abs : (I)I
    //   795: invokevirtual charAt : (I)C
    //   798: invokevirtual append : (C)Ljava/lang/StringBuilder;
    //   801: pop
    //   802: iload_2
    //   803: ifne -> 1364
    //   806: goto -> 813
    //   809: invokestatic a : (Ljava/lang/Throwable;)Ljava/lang/Throwable;
    //   812: athrow
    //   813: aload_3
    //   814: getstatic burp/Zxso.ZH : Ljava/lang/String;
    //   817: getstatic burp/Zrqd.Zi : Ljava/lang/Object;
    //   820: checkcast java/math/BigInteger
    //   823: invokevirtual intValue : ()I
    //   826: bipush #32
    //   828: irem
    //   829: invokestatic abs : (I)I
    //   832: invokevirtual charAt : (I)C
    //   835: invokevirtual append : (C)Ljava/lang/StringBuilder;
    //   838: pop
    //   839: iload_2
    //   840: ifne -> 1364
    //   843: goto -> 850
    //   846: invokestatic a : (Ljava/lang/Throwable;)Ljava/lang/Throwable;
    //   849: athrow
    //   850: aload_3
    //   851: getstatic burp/Zg_6.Zc : Ljava/lang/String;
    //   854: getstatic burp/Zg4d.Zm : Ljava/lang/Object;
    //   857: checkcast java/math/BigInteger
    //   860: invokevirtual intValue : ()I
    //   863: bipush #32
    //   865: irem
    //   866: invokestatic abs : (I)I
    //   869: invokevirtual charAt : (I)C
    //   872: invokevirtual append : (C)Ljava/lang/StringBuilder;
    //   875: pop
    //   876: iload_2
    //   877: ifne -> 1364
    //   880: goto -> 887
    //   883: invokestatic a : (Ljava/lang/Throwable;)Ljava/lang/Throwable;
    //   886: athrow
    //   887: aload_3
    //   888: getstatic burp/Zg1l.Zl : Ljava/lang/String;
    //   891: getstatic burp/Ze82.ZR : Ljava/lang/Object;
    //   894: checkcast java/math/BigInteger
    //   897: invokevirtual intValue : ()I
    //   900: bipush #32
    //   902: irem
    //   903: invokestatic abs : (I)I
    //   906: invokevirtual charAt : (I)C
    //   909: invokevirtual append : (C)Ljava/lang/StringBuilder;
    //   912: pop
    //   913: iload_2
    //   914: ifne -> 1364
    //   917: goto -> 924
    //   920: invokestatic a : (Ljava/lang/Throwable;)Ljava/lang/Throwable;
    //   923: athrow
    //   924: aload_3
    //   925: getstatic burp/Zz5d.Zb : Ljava/lang/String;
    //   928: getstatic burp/Zxsb.ZN : Ljava/lang/Object;
    //   931: checkcast java/math/BigInteger
    //   934: invokevirtual intValue : ()I
    //   937: bipush #32
    //   939: irem
    //   940: invokestatic abs : (I)I
    //   943: invokevirtual charAt : (I)C
    //   946: invokevirtual append : (C)Ljava/lang/StringBuilder;
    //   949: pop
    //   950: iload_2
    //   951: ifne -> 1364
    //   954: goto -> 961
    //   957: invokestatic a : (Ljava/lang/Throwable;)Ljava/lang/Throwable;
    //   960: athrow
    //   961: aload_3
    //   962: getstatic burp/Zxyq.Zr : Ljava/lang/String;
    //   965: getstatic burp/Zzoi.ZI : Ljava/lang/Object;
    //   968: checkcast java/math/BigInteger
    //   971: invokevirtual intValue : ()I
    //   974: bipush #32
    //   976: irem
    //   977: invokestatic abs : (I)I
    //   980: invokevirtual charAt : (I)C
    //   983: invokevirtual append : (C)Ljava/lang/StringBuilder;
    //   986: pop
    //   987: iload_2
    //   988: ifne -> 1364
    //   991: goto -> 998
    //   994: invokestatic a : (Ljava/lang/Throwable;)Ljava/lang/Throwable;
    //   997: athrow
    //   998: aload_3
    //   999: getstatic burp/Zrt9.Zc : Ljava/lang/String;
    //   1002: getstatic burp/Zzmo.ZI : Ljava/lang/Object;
    //   1005: checkcast java/math/BigInteger
    //   1008: invokevirtual intValue : ()I
    //   1011: bipush #32
    //   1013: irem
    //   1014: invokestatic abs : (I)I
    //   1017: invokevirtual charAt : (I)C
    //   1020: invokevirtual append : (C)Ljava/lang/StringBuilder;
    //   1023: pop
    //   1024: iload_2
    //   1025: ifne -> 1364
    //   1028: goto -> 1035
    //   1031: invokestatic a : (Ljava/lang/Throwable;)Ljava/lang/Throwable;
    //   1034: athrow
    //   1035: aload_3
    //   1036: getstatic burp/Zsby.Zx : Ljava/lang/String;
    //   1039: getstatic burp/Zx_x.Zi : Ljava/lang/Object;
    //   1042: checkcast java/math/BigInteger
    //   1045: invokevirtual intValue : ()I
    //   1048: bipush #32
    //   1050: irem
    //   1051: invokestatic abs : (I)I
    //   1054: invokevirtual charAt : (I)C
    //   1057: invokevirtual append : (C)Ljava/lang/StringBuilder;
    //   1060: pop
    //   1061: iload_2
    //   1062: ifne -> 1364
    //   1065: goto -> 1072
    //   1068: invokestatic a : (Ljava/lang/Throwable;)Ljava/lang/Throwable;
    //   1071: athrow
    //   1072: aload_3
    //   1073: getstatic burp/Zezn.Ze : Ljava/lang/String;
    //   1076: getstatic burp/Zxxf.ZZ : Ljava/lang/Object;
    //   1079: checkcast java/math/BigInteger
    //   1082: invokevirtual intValue : ()I
    //   1085: bipush #32
    //   1087: irem
    //   1088: invokestatic abs : (I)I
    //   1091: invokevirtual charAt : (I)C
    //   1094: invokevirtual append : (C)Ljava/lang/StringBuilder;
    //   1097: pop
    //   1098: iload_2
    //   1099: ifne -> 1364
    //   1102: goto -> 1109
    //   1105: invokestatic a : (Ljava/lang/Throwable;)Ljava/lang/Throwable;
    //   1108: athrow
    //   1109: aload_3
    //   1110: getstatic burp/Zlhm.Zx : Ljava/lang/String;
    //   1113: getstatic burp/Ztpa.Zv : Ljava/lang/Object;
    //   1116: checkcast java/math/BigInteger
    //   1119: invokevirtual intValue : ()I
    //   1122: bipush #32
    //   1124: irem
    //   1125: invokestatic abs : (I)I
    //   1128: invokevirtual charAt : (I)C
    //   1131: invokevirtual append : (C)Ljava/lang/StringBuilder;
    //   1134: pop
    //   1135: iload_2
    //   1136: ifne -> 1364
    //   1139: goto -> 1146
    //   1142: invokestatic a : (Ljava/lang/Throwable;)Ljava/lang/Throwable;
    //   1145: athrow
    //   1146: aload_3
    //   1147: getstatic burp/Zlyf.ZU : Ljava/lang/String;
    //   1150: getstatic burp/Ztmy.ZH : Ljava/lang/Object;
    //   1153: checkcast java/math/BigInteger
    //   1156: invokevirtual intValue : ()I
    //   1159: bipush #32
    //   1161: irem
    //   1162: invokestatic abs : (I)I
    //   1165: invokevirtual charAt : (I)C
    //   1168: invokevirtual append : (C)Ljava/lang/StringBuilder;
    //   1171: pop
    //   1172: iload_2
    //   1173: ifne -> 1364
    //   1176: goto -> 1183
    //   1179: invokestatic a : (Ljava/lang/Throwable;)Ljava/lang/Throwable;
    //   1182: athrow
    //   1183: aload_3
    //   1184: getstatic burp/Zlno.ZM : Ljava/lang/String;
    //   1187: getstatic burp/Zk5y.ZL : Ljava/lang/Object;
    //   1190: checkcast java/math/BigInteger
    //   1193: invokevirtual intValue : ()I
    //   1196: bipush #32
    //   1198: irem
    //   1199: invokestatic abs : (I)I
    //   1202: invokevirtual charAt : (I)C
    //   1205: invokevirtual append : (C)Ljava/lang/StringBuilder;
    //   1208: pop
    //   1209: iload_2
    //   1210: ifne -> 1364
    //   1213: goto -> 1220
    //   1216: invokestatic a : (Ljava/lang/Throwable;)Ljava/lang/Throwable;
    //   1219: athrow
    //   1220: aload_3
    //   1221: getstatic burp/Zb29.Zf : Ljava/lang/String;
    //   1224: getstatic burp/Zegw.ZW : Ljava/lang/Object;
    //   1227: checkcast java/math/BigInteger
    //   1230: invokevirtual intValue : ()I
    //   1233: bipush #32
    //   1235: irem
    //   1236: invokestatic abs : (I)I
    //   1239: invokevirtual charAt : (I)C
    //   1242: invokevirtual append : (C)Ljava/lang/StringBuilder;
    //   1245: pop
    //   1246: iload_2
    //   1247: ifne -> 1364
    //   1250: goto -> 1257
    //   1253: invokestatic a : (Ljava/lang/Throwable;)Ljava/lang/Throwable;
    //   1256: athrow
    //   1257: aload_3
    //   1258: getstatic burp/Zb3l.Zz : Ljava/lang/String;
    //   1261: getstatic burp/Zzh9.Zv : Ljava/lang/Object;
    //   1264: checkcast java/math/BigInteger
    //   1267: invokevirtual intValue : ()I
    //   1270: bipush #32
    //   1272: irem
    //   1273: invokestatic abs : (I)I
    //   1276: invokevirtual charAt : (I)C
    //   1279: invokevirtual append : (C)Ljava/lang/StringBuilder;
    //   1282: pop
    //   1283: iload_2
    //   1284: ifne -> 1364
    //   1287: goto -> 1294
    //   1290: invokestatic a : (Ljava/lang/Throwable;)Ljava/lang/Throwable;
    //   1293: athrow
    //   1294: aload_3
    //   1295: getstatic burp/Zstq.ZL : Ljava/lang/String;
    //   1298: getstatic burp/Zm_w.ZW : Ljava/lang/Object;
    //   1301: checkcast java/math/BigInteger
    //   1304: invokevirtual intValue : ()I
    //   1307: bipush #32
    //   1309: irem
    //   1310: invokestatic abs : (I)I
    //   1313: invokevirtual charAt : (I)C
    //   1316: invokevirtual append : (C)Ljava/lang/StringBuilder;
    //   1319: pop
    //   1320: iload_2
    //   1321: ifne -> 1364
    //   1324: goto -> 1331
    //   1327: invokestatic a : (Ljava/lang/Throwable;)Ljava/lang/Throwable;
    //   1330: athrow
    //   1331: aload_3
    //   1332: getstatic burp/Zmwx.ZB : Ljava/lang/String;
    //   1335: getstatic burp/Zm4k.Zm : Ljava/lang/Object;
    //   1338: checkcast java/math/BigInteger
    //   1341: invokevirtual intValue : ()I
    //   1344: bipush #32
    //   1346: irem
    //   1347: invokestatic abs : (I)I
    //   1350: invokevirtual charAt : (I)C
    //   1353: invokevirtual append : (C)Ljava/lang/StringBuilder;
    //   1356: pop
    //   1357: goto -> 1364
    //   1360: invokestatic a : (Ljava/lang/Throwable;)Ljava/lang/Throwable;
    //   1363: athrow
    //   1364: iinc #4, 1
    //   1367: iload_2
    //   1368: ifne -> 33
    //   1371: aload_3
    //   1372: invokevirtual toString : ()Ljava/lang/String;
    //   1375: putstatic burp/Zbxa.ZY : Ljava/lang/String;
    //   1378: sipush #-27868
    //   1381: sipush #-19983
    //   1384: invokestatic a : (II)Ljava/lang/String;
    //   1387: iconst_1
    //   1388: ldc burp/Zvh
    //   1390: invokevirtual getClassLoader : ()Ljava/lang/ClassLoader;
    //   1393: invokestatic forName : (Ljava/lang/String;ZLjava/lang/ClassLoader;)Ljava/lang/Class;
    //   1396: invokevirtual getDeclaredFields : ()[Ljava/lang/reflect/Field;
    //   1399: astore #4
    //   1401: aload #4
    //   1403: arraylength
    //   1404: istore #5
    //   1406: iconst_0
    //   1407: istore #6
    //   1409: iload #6
    //   1411: iload #5
    //   1413: if_icmpge -> 1551
    //   1416: aload #4
    //   1418: iload #6
    //   1420: aaload
    //   1421: astore #7
    //   1423: aload #7
    //   1425: invokevirtual getModifiers : ()I
    //   1428: invokestatic isStatic : (I)Z
    //   1431: ifne -> 1441
    //   1434: goto -> 1544
    //   1437: invokestatic a : (Ljava/lang/Throwable;)Ljava/lang/Throwable;
    //   1440: athrow
    //   1441: aload #7
    //   1443: invokevirtual getType : ()Ljava/lang/Class;
    //   1446: astore #8
    //   1448: aload #8
    //   1450: ifnull -> 1531
    //   1453: aload #8
    //   1455: invokevirtual isPrimitive : ()Z
    //   1458: ifne -> 1531
    //   1461: goto -> 1468
    //   1464: invokestatic a : (Ljava/lang/Throwable;)Ljava/lang/Throwable;
    //   1467: athrow
    //   1468: aload #8
    //   1470: invokevirtual getPackage : ()Ljava/lang/Package;
    //   1473: ifnull -> 1531
    //   1476: goto -> 1483
    //   1479: invokestatic a : (Ljava/lang/Throwable;)Ljava/lang/Throwable;
    //   1482: athrow
    //   1483: aload #8
    //   1485: invokevirtual getPackage : ()Ljava/lang/Package;
    //   1488: invokevirtual getName : ()Ljava/lang/String;
    //   1491: ifnull -> 1531
    //   1494: goto -> 1501
    //   1497: invokestatic a : (Ljava/lang/Throwable;)Ljava/lang/Throwable;
    //   1500: athrow
    //   1501: aload #8
    //   1503: invokevirtual getPackage : ()Ljava/lang/Package;
    //   1506: invokevirtual getName : ()Ljava/lang/String;
    //   1509: sipush #-27862
    //   1512: sipush #23465
    //   1515: invokestatic a : (II)Ljava/lang/String;
    //   1518: invokevirtual startsWith : (Ljava/lang/String;)Z
    //   1521: ifne -> 1531
    //   1524: goto -> 1531
    //   1527: invokestatic a : (Ljava/lang/Throwable;)Ljava/lang/Throwable;
    //   1530: athrow
    //   1531: aload #7
    //   1533: iconst_1
    //   1534: invokevirtual setAccessible : (Z)V
    //   1537: aload #7
    //   1539: aconst_null
    //   1540: invokevirtual get : (Ljava/lang/Object;)Ljava/lang/Object;
    //   1543: pop
    //   1544: iinc #6, 1
    //   1547: iload_2
    //   1548: ifne -> 1409
    //   1551: sipush #-27871
    //   1554: sipush #-30654
    //   1557: invokestatic a : (II)Ljava/lang/String;
    //   1560: invokestatic forName : (Ljava/lang/String;)Ljava/lang/Class;
    //   1563: invokevirtual getDeclaredMethods : ()[Ljava/lang/reflect/Method;
    //   1566: astore #4
    //   1568: aload #4
    //   1570: arraylength
    //   1571: istore #5
    //   1573: iconst_0
    //   1574: istore #6
    //   1576: iload #6
    //   1578: iload #5
    //   1580: if_icmpge -> 1710
    //   1583: aload #4
    //   1585: iload #6
    //   1587: aaload
    //   1588: astore #7
    //   1590: aload #7
    //   1592: invokevirtual getParameterTypes : ()[Ljava/lang/Class;
    //   1595: pop
    //   1596: aload #7
    //   1598: invokevirtual getModifiers : ()I
    //   1601: invokestatic isStatic : (I)Z
    //   1604: ifeq -> 1696
    //   1607: aload #7
    //   1609: invokevirtual getParameterTypes : ()[Ljava/lang/Class;
    //   1612: arraylength
    //   1613: iconst_2
    //   1614: if_icmpne -> 1696
    //   1617: goto -> 1624
    //   1620: invokestatic a : (Ljava/lang/Throwable;)Ljava/lang/Throwable;
    //   1623: athrow
    //   1624: aload #7
    //   1626: invokevirtual getReturnType : ()Ljava/lang/Class;
    //   1629: getstatic java/lang/Boolean.TYPE : Ljava/lang/Class;
    //   1632: if_acmpne -> 1696
    //   1635: goto -> 1642
    //   1638: invokestatic a : (Ljava/lang/Throwable;)Ljava/lang/Throwable;
    //   1641: athrow
    //   1642: aload #7
    //   1644: iconst_1
    //   1645: invokevirtual setAccessible : (Z)V
    //   1648: aload #7
    //   1650: aconst_null
    //   1651: iconst_2
    //   1652: anewarray java/lang/Object
    //   1655: dup
    //   1656: iconst_0
    //   1657: aload_0
    //   1658: aastore
    //   1659: dup
    //   1660: iconst_1
    //   1661: aload_1
    //   1662: ifnonnull -> 1680
    //   1665: goto -> 1672
    //   1668: invokestatic a : (Ljava/lang/Throwable;)Ljava/lang/Throwable;
    //   1671: athrow
    //   1672: aload_1
    //   1673: goto -> 1687
    //   1676: invokestatic a : (Ljava/lang/Throwable;)Ljava/lang/Throwable;
    //   1679: athrow
    //   1680: aload_1
    //   1681: checkcast [B
    //   1684: invokevirtual clone : ()Ljava/lang/Object;
    //   1687: aastore
    //   1688: invokevirtual invoke : (Ljava/lang/Object;[Ljava/lang/Object;)Ljava/lang/Object;
    //   1691: pop
    //   1692: iload_2
    //   1693: ifne -> 1710
    //   1696: iinc #6, 1
    //   1699: iload_2
    //   1700: ifne -> 1576
    //   1703: goto -> 1710
    //   1706: invokestatic a : (Ljava/lang/Throwable;)Ljava/lang/Throwable;
    //   1709: athrow
    //   1710: sipush #-27863
    //   1713: sipush #-3520
    //   1716: invokestatic a : (II)Ljava/lang/String;
    //   1719: iconst_1
    //   1720: ldc burp/Zgdj
    //   1722: invokevirtual getClassLoader : ()Ljava/lang/ClassLoader;
    //   1725: invokestatic forName : (Ljava/lang/String;ZLjava/lang/ClassLoader;)Ljava/lang/Class;
    //   1728: invokevirtual getDeclaredFields : ()[Ljava/lang/reflect/Field;
    //   1731: astore #4
    //   1733: aload #4
    //   1735: arraylength
    //   1736: istore #5
    //   1738: iconst_0
    //   1739: istore #6
    //   1741: iload #6
    //   1743: iload #5
    //   1745: if_icmpge -> 1883
    //   1748: aload #4
    //   1750: iload #6
    //   1752: aaload
    //   1753: astore #7
    //   1755: aload #7
    //   1757: invokevirtual getModifiers : ()I
    //   1760: invokestatic isStatic : (I)Z
    //   1763: ifne -> 1773
    //   1766: goto -> 1876
    //   1769: invokestatic a : (Ljava/lang/Throwable;)Ljava/lang/Throwable;
    //   1772: athrow
    //   1773: aload #7
    //   1775: invokevirtual getType : ()Ljava/lang/Class;
    //   1778: astore #8
    //   1780: aload #8
    //   1782: ifnull -> 1863
    //   1785: aload #8
    //   1787: invokevirtual isPrimitive : ()Z
    //   1790: ifne -> 1863
    //   1793: goto -> 1800
    //   1796: invokestatic a : (Ljava/lang/Throwable;)Ljava/lang/Throwable;
    //   1799: athrow
    //   1800: aload #8
    //   1802: invokevirtual getPackage : ()Ljava/lang/Package;
    //   1805: ifnull -> 1863
    //   1808: goto -> 1815
    //   1811: invokestatic a : (Ljava/lang/Throwable;)Ljava/lang/Throwable;
    //   1814: athrow
    //   1815: aload #8
    //   1817: invokevirtual getPackage : ()Ljava/lang/Package;
    //   1820: invokevirtual getName : ()Ljava/lang/String;
    //   1823: ifnull -> 1863
    //   1826: goto -> 1833
    //   1829: invokestatic a : (Ljava/lang/Throwable;)Ljava/lang/Throwable;
    //   1832: athrow
    //   1833: aload #8
    //   1835: invokevirtual getPackage : ()Ljava/lang/Package;
    //   1838: invokevirtual getName : ()Ljava/lang/String;
    //   1841: sipush #-27869
    //   1844: sipush #18432
    //   1847: invokestatic a : (II)Ljava/lang/String;
    //   1850: invokevirtual startsWith : (Ljava/lang/String;)Z
    //   1853: ifne -> 1863
    //   1856: goto -> 1863
    //   1859: invokestatic a : (Ljava/lang/Throwable;)Ljava/lang/Throwable;
    //   1862: athrow
    //   1863: aload #7
    //   1865: iconst_1
    //   1866: invokevirtual setAccessible : (Z)V
    //   1869: aload #7
    //   1871: aconst_null
    //   1872: invokevirtual get : (Ljava/lang/Object;)Ljava/lang/Object;
    //   1875: pop
    //   1876: iinc #6, 1
    //   1879: iload_2
    //   1880: ifne -> 1741
    //   1883: sipush #-27870
    //   1886: sipush #-21449
    //   1889: invokestatic a : (II)Ljava/lang/String;
    //   1892: invokestatic forName : (Ljava/lang/String;)Ljava/lang/Class;
    //   1895: invokevirtual getDeclaredMethods : ()[Ljava/lang/reflect/Method;
    //   1898: astore #4
    //   1900: aload #4
    //   1902: arraylength
    //   1903: istore #5
    //   1905: iconst_0
    //   1906: istore #6
    //   1908: iload #6
    //   1910: iload #5
    //   1912: if_icmpge -> 2045
    //   1915: aload #4
    //   1917: iload #6
    //   1919: aaload
    //   1920: astore #7
    //   1922: aload #7
    //   1924: invokevirtual getParameterTypes : ()[Ljava/lang/Class;
    //   1927: pop
    //   1928: aload #7
    //   1930: invokevirtual getModifiers : ()I
    //   1933: invokestatic isStatic : (I)Z
    //   1936: ifeq -> 2031
    //   1939: aload #7
    //   1941: invokevirtual getParameterTypes : ()[Ljava/lang/Class;
    //   1944: arraylength
    //   1945: iconst_2
    //   1946: if_icmpne -> 2031
    //   1949: goto -> 1956
    //   1952: invokestatic a : (Ljava/lang/Throwable;)Ljava/lang/Throwable;
    //   1955: athrow
    //   1956: aload #7
    //   1958: invokevirtual getReturnType : ()Ljava/lang/Class;
    //   1961: getstatic java/lang/Void.TYPE : Ljava/lang/Class;
    //   1964: invokevirtual equals : (Ljava/lang/Object;)Z
    //   1967: ifeq -> 2031
    //   1970: goto -> 1977
    //   1973: invokestatic a : (Ljava/lang/Throwable;)Ljava/lang/Throwable;
    //   1976: athrow
    //   1977: aload #7
    //   1979: iconst_1
    //   1980: invokevirtual setAccessible : (Z)V
    //   1983: aload #7
    //   1985: aconst_null
    //   1986: iconst_2
    //   1987: anewarray java/lang/Object
    //   1990: dup
    //   1991: iconst_0
    //   1992: aload_0
    //   1993: aastore
    //   1994: dup
    //   1995: iconst_1
    //   1996: aload_1
    //   1997: ifnonnull -> 2015
    //   2000: goto -> 2007
    //   2003: invokestatic a : (Ljava/lang/Throwable;)Ljava/lang/Throwable;
    //   2006: athrow
    //   2007: aload_1
    //   2008: goto -> 2022
    //   2011: invokestatic a : (Ljava/lang/Throwable;)Ljava/lang/Throwable;
    //   2014: athrow
    //   2015: aload_1
    //   2016: checkcast [B
    //   2019: invokevirtual clone : ()Ljava/lang/Object;
    //   2022: aastore
    //   2023: invokevirtual invoke : (Ljava/lang/Object;[Ljava/lang/Object;)Ljava/lang/Object;
    //   2026: pop
    //   2027: iload_2
    //   2028: ifne -> 2045
    //   2031: iinc #6, 1
    //   2034: iload_2
    //   2035: ifne -> 1908
    //   2038: goto -> 2045
    //   2041: invokestatic a : (Ljava/lang/Throwable;)Ljava/lang/Throwable;
    //   2044: athrow
    //   2045: getstatic burp/Zep8.ZC : Ljava/lang/String;
    //   2048: getstatic burp/Zm6h.ZB : Ljava/lang/Object;
    //   2051: checkcast java/math/BigInteger
    //   2054: invokevirtual intValue : ()I
    //   2057: bipush #32
    //   2059: irem
    //   2060: invokestatic abs : (I)I
    //   2063: invokevirtual charAt : (I)C
    //   2066: getstatic burp/Zg4d.ZE : Ljava/lang/String;
    //   2069: getstatic burp/Zsmn.Zq : Ljava/lang/Object;
    //   2072: checkcast java/math/BigInteger
    //   2075: invokevirtual intValue : ()I
    //   2078: bipush #32
    //   2080: irem
    //   2081: invokestatic abs : (I)I
    //   2084: invokevirtual charAt : (I)C
    //   2087: if_icmpgt -> 2202
    //   2090: getstatic burp/Zgrf.ZE : Ljava/lang/String;
    //   2093: getstatic burp/Zlhu.ZJ : Ljava/lang/Object;
    //   2096: checkcast java/math/BigInteger
    //   2099: invokevirtual intValue : ()I
    //   2102: bipush #32
    //   2104: irem
    //   2105: invokestatic abs : (I)I
    //   2108: invokevirtual charAt : (I)C
    //   2111: getstatic burp/Zxk9.Zx : Ljava/lang/String;
    //   2114: getstatic burp/Zx_x.Zi : Ljava/lang/Object;
    //   2117: checkcast java/math/BigInteger
    //   2120: invokevirtual intValue : ()I
    //   2123: bipush #32
    //   2125: irem
    //   2126: invokestatic abs : (I)I
    //   2129: invokevirtual charAt : (I)C
    //   2132: if_icmple -> 2202
    //   2135: goto -> 2142
    //   2138: invokestatic a : (Ljava/lang/Throwable;)Ljava/lang/Throwable;
    //   2141: athrow
    //   2142: getstatic burp/Zkc5.ZH : Ljava/lang/String;
    //   2145: getstatic burp/Zb20.Zq : Ljava/lang/Object;
    //   2148: checkcast java/math/BigInteger
    //   2151: invokevirtual intValue : ()I
    //   2154: bipush #32
    //   2156: irem
    //   2157: invokestatic abs : (I)I
    //   2160: invokevirtual charAt : (I)C
    //   2163: getstatic burp/Zedz.Zh : Ljava/lang/String;
    //   2166: getstatic burp/Zrj3.ZA : Ljava/lang/Object;
    //   2169: checkcast java/math/BigInteger
    //   2172: invokevirtual intValue : ()I
    //   2175: bipush #32
    //   2177: irem
    //   2178: invokestatic abs : (I)I
    //   2181: invokevirtual charAt : (I)C
    //   2184: if_icmple -> 2202
    //   2187: goto -> 2194
    //   2190: invokestatic a : (Ljava/lang/Throwable;)Ljava/lang/Throwable;
    //   2193: athrow
    //   2194: iconst_1
    //   2195: goto -> 2203
    //   2198: invokestatic a : (Ljava/lang/Throwable;)Ljava/lang/Throwable;
    //   2201: athrow
    //   2202: iconst_0
    //   2203: ireturn
    //   2204: astore_3
    //   2205: new java/lang/Exception
    //   2208: dup
    //   2209: aload_3
    //   2210: invokevirtual getMessage : ()Ljava/lang/String;
    //   2213: invokespecial <init> : (Ljava/lang/String;)V
    //   2216: athrow
    // Exception table:
    //   from	to	target	type
    //   4	2203	2204	java/lang/Throwable
    //   40	214	217	java/lang/Throwable
    //   184	251	254	java/lang/Throwable
    //   221	288	291	java/lang/Throwable
    //   258	325	328	java/lang/Throwable
    //   295	362	365	java/lang/Throwable
    //   332	399	402	java/lang/Throwable
    //   369	436	439	java/lang/Throwable
    //   406	473	476	java/lang/Throwable
    //   443	510	513	java/lang/Throwable
    //   480	547	550	java/lang/Throwable
    //   517	584	587	java/lang/Throwable
    //   554	621	624	java/lang/Throwable
    //   591	658	661	java/lang/Throwable
    //   628	695	698	java/lang/Throwable
    //   665	732	735	java/lang/Throwable
    //   702	769	772	java/lang/Throwable
    //   739	806	809	java/lang/Throwable
    //   776	843	846	java/lang/Throwable
    //   813	880	883	java/lang/Throwable
    //   850	917	920	java/lang/Throwable
    //   887	954	957	java/lang/Throwable
    //   924	991	994	java/lang/Throwable
    //   961	1028	1031	java/lang/Throwable
    //   998	1065	1068	java/lang/Throwable
    //   1035	1102	1105	java/lang/Throwable
    //   1072	1139	1142	java/lang/Throwable
    //   1109	1176	1179	java/lang/Throwable
    //   1146	1213	1216	java/lang/Throwable
    //   1183	1250	1253	java/lang/Throwable
    //   1220	1287	1290	java/lang/Throwable
    //   1257	1324	1327	java/lang/Throwable
    //   1294	1357	1360	java/lang/Throwable
    //   1423	1437	1437	java/lang/Throwable
    //   1448	1461	1464	java/lang/Throwable
    //   1453	1476	1479	java/lang/Throwable
    //   1468	1494	1497	java/lang/Throwable
    //   1483	1524	1527	java/lang/Throwable
    //   1590	1617	1620	java/lang/Throwable
    //   1607	1635	1638	java/lang/Throwable
    //   1624	1665	1668	java/lang/Throwable
    //   1642	1676	1676	java/lang/Throwable
    //   1687	1703	1706	java/lang/Throwable
    //   1755	1769	1769	java/lang/Throwable
    //   1780	1793	1796	java/lang/Throwable
    //   1785	1808	1811	java/lang/Throwable
    //   1800	1826	1829	java/lang/Throwable
    //   1815	1856	1859	java/lang/Throwable
    //   1922	1949	1952	java/lang/Throwable
    //   1939	1970	1973	java/lang/Throwable
    //   1956	2000	2003	java/lang/Throwable
    //   1977	2011	2011	java/lang/Throwable
    //   2022	2038	2041	java/lang/Throwable
    //   2045	2135	2138	java/lang/Throwable
    //   2090	2187	2190	java/lang/Throwable
    //   2142	2198	2198	java/lang/Throwable
  }
  
  static void Zh(Object[] paramArrayOfObject, Object paramObject) throws Throwable {}
  
  static void ZF(Object paramObject) {
    Ztd3.ZC = a(-27865, -2843);
    Ztd3.ZX = new BigInteger(a(-27864, -23962));
    boolean bool = Zt2e.ZK();
    try {
      try {
        if (Zlr2.ZV.charAt(Math.abs(((BigInteger)Ztys.Zs).intValue() % 32)) > Zb14.Ze.charAt(Math.abs(((BigInteger)Zlo2.ZM).intValue() % 32))) {
          try {
            Zzou.ZG(Class.forName(a(-27872, 2834)));
            if (bool)
              Zzxa.Zq(Class.forName(a(-27867, -19933))); 
          } catch (Throwable throwable) {
            throw a(null);
          } 
          return;
        } 
      } catch (Throwable throwable) {
        throw a(null);
      } 
      Zzxa.Zq(Class.forName(a(-27867, -19933)));
    } catch (Throwable throwable) {}
  }
  
  static {
    // Byte code:
    //   0: bipush #11
    //   2: anewarray java/lang/String
    //   5: astore #5
    //   7: iconst_0
    //   8: istore_3
    //   9: ldc 'm\\fÃ©ÂŒÂŽÂ˜0Âº\\tÂµÂ“Ã²Ã­Ã«Ã°t\\tzÂ™>Ã’)\\fÃ¨ÂŠÂ™Â©w8\\tÃŽÃ¦ÂÃ‘ Ã”SÂž\\tQÂ¶nÃ›~Â•Â™fd Ã˜MÂŸMÃ‡Â¥ÂÂÃ‚ÂŸrÂ³ÂˆÃŒÂ¿Ã¥SlqÃ‹Ã±WÂ¾ÂŸ1LÂœ8Ã“Â  ÂÂ’Ã¤ xÂžÂ³:ÃˆMÂÂ¿Â†ÂV!Â°0ÃŸaÃ³!QÂ£nÃºÃ´Ã´DM%ÂžÃ°8Â·Ã£ÃŽÃ„_ÂeVÂ®]mhÂ›MÃµÂ‡CÃ£Â¨Â¢24Ã¯~Â‰ÂŽl~\\tÃ…Â¹\\f-eqÃ¤Â’Ã˜Ã´ÂµJ!ÂÃ¸:=Ã¯[Â®Â§OvNgÂ™FLGmÃ‚VÃ‰Ã¦ Â½GÂœS'
    //   11: dup
    //   12: astore_2
    //   13: invokevirtual length : ()I
    //   16: istore #4
    //   18: bipush #9
    //   20: istore_1
    //   21: iconst_m1
    //   22: istore_0
    //   23: bipush #119
    //   25: iinc #0, 1
    //   28: aload_2
    //   29: iload_0
    //   30: dup
    //   31: iload_1
    //   32: iadd
    //   33: invokevirtual substring : (II)Ljava/lang/String;
    //   36: iconst_m1
    //   37: goto -> 143
    //   40: aload #5
    //   42: swap
    //   43: iload_3
    //   44: iinc #3, 1
    //   47: swap
    //   48: aastore
    //   49: iload_0
    //   50: iload_1
    //   51: iadd
    //   52: dup
    //   53: istore_0
    //   54: iload #4
    //   56: if_icmpge -> 68
    //   59: aload_2
    //   60: iload_0
    //   61: invokevirtual charAt : (I)C
    //   64: istore_1
    //   65: goto -> 23
    //   68: ldc 'Ã¨^ÃºeOÃ¡H5OÃµ'
    //   70: dup
    //   71: astore_2
    //   72: invokevirtual length : ()I
    //   75: istore #4
    //   77: bipush #9
    //   79: istore_1
    //   80: iconst_m1
    //   81: istore_0
    //   82: bipush #25
    //   84: iinc #0, 1
    //   87: aload_2
    //   88: iload_0
    //   89: dup
    //   90: iload_1
    //   91: iadd
    //   92: invokevirtual substring : (II)Ljava/lang/String;
    //   95: iconst_0
    //   96: goto -> 143
    //   99: aload #5
    //   101: swap
    //   102: iload_3
    //   103: iinc #3, 1
    //   106: swap
    //   107: aastore
    //   108: iload_0
    //   109: iload_1
    //   110: iadd
    //   111: dup
    //   112: istore_0
    //   113: iload #4
    //   115: if_icmpge -> 127
    //   118: aload_2
    //   119: iload_0
    //   120: invokevirtual charAt : (I)C
    //   123: istore_1
    //   124: goto -> 82
    //   127: aload #5
    //   129: putstatic burp/Zkf9.a : [Ljava/lang/String;
    //   132: bipush #11
    //   134: anewarray java/lang/String
    //   137: putstatic burp/Zkf9.b : [Ljava/lang/String;
    //   140: goto -> 300
    //   143: dup_x2
    //   144: pop
    //   145: invokevirtual toCharArray : ()[C
    //   148: dup_x1
    //   149: arraylength
    //   150: dup_x2
    //   151: pop
    //   152: iconst_0
    //   153: istore #6
    //   155: dup2_x1
    //   156: pop2
    //   157: dup_x2
    //   158: iconst_1
    //   159: if_icmpgt -> 258
    //   162: dup2
    //   163: swap
    //   164: iload #6
    //   166: dup2_x1
    //   167: caload
    //   168: swap
    //   169: iload #6
    //   171: bipush #7
    //   173: irem
    //   174: tableswitch default -> 240, 0 -> 212, 1 -> 216, 2 -> 221, 3 -> 225, 4 -> 230, 5 -> 235
    //   212: iconst_4
    //   213: goto -> 242
    //   216: bipush #123
    //   218: goto -> 242
    //   221: iconst_1
    //   222: goto -> 242
    //   225: bipush #80
    //   227: goto -> 242
    //   230: bipush #24
    //   232: goto -> 242
    //   235: bipush #89
    //   237: goto -> 242
    //   240: bipush #64
    //   242: ixor
    //   243: ixor
    //   244: i2c
    //   245: castore
    //   246: iinc #6, 1
    //   249: dup
    //   250: ifne -> 258
    //   253: dup2
    //   254: dup_x1
    //   255: goto -> 166
    //   258: dup2_x1
    //   259: pop2
    //   260: dup_x2
    //   261: iload #6
    //   263: if_icmpgt -> 162
    //   266: pop
    //   267: new java/lang/String
    //   270: dup_x1
    //   271: swap
    //   272: invokespecial <init> : ([C)V
    //   275: invokevirtual intern : ()Ljava/lang/String;
    //   278: swap
    //   279: pop
    //   280: swap
    //   281: tableswitch default -> 40, 0 -> 99
    //   300: new java/math/BigInteger
    //   303: dup
    //   304: iconst_1
    //   305: bipush #32
    //   307: newarray byte
    //   309: dup
    //   310: iconst_0
    //   311: bipush #34
    //   313: bastore
    //   314: dup
    //   315: iconst_1
    //   316: bipush #-126
    //   318: bastore
    //   319: dup
    //   320: iconst_2
    //   321: bipush #116
    //   323: bastore
    //   324: dup
    //   325: iconst_3
    //   326: bipush #57
    //   328: bastore
    //   329: dup
    //   330: iconst_4
    //   331: bipush #53
    //   333: bastore
    //   334: dup
    //   335: iconst_5
    //   336: bipush #25
    //   338: bastore
    //   339: dup
    //   340: bipush #6
    //   342: bipush #118
    //   344: bastore
    //   345: dup
    //   346: bipush #7
    //   348: bipush #25
    //   350: bastore
    //   351: dup
    //   352: bipush #8
    //   354: bipush #116
    //   356: bastore
    //   357: dup
    //   358: bipush #9
    //   360: bipush #53
    //   362: bastore
    //   363: dup
    //   364: bipush #10
    //   366: bipush #-28
    //   368: bastore
    //   369: dup
    //   370: bipush #11
    //   372: bipush #27
    //   374: bastore
    //   375: dup
    //   376: bipush #12
    //   378: bipush #-56
    //   380: bastore
    //   381: dup
    //   382: bipush #13
    //   384: bipush #43
    //   386: bastore
    //   387: dup
    //   388: bipush #14
    //   390: bipush #118
    //   392: bastore
    //   393: dup
    //   394: bipush #15
    //   396: bipush #-19
    //   398: bastore
    //   399: dup
    //   400: bipush #16
    //   402: bipush #-127
    //   404: bastore
    //   405: dup
    //   406: bipush #17
    //   408: bipush #48
    //   410: bastore
    //   411: dup
    //   412: bipush #18
    //   414: bipush #-119
    //   416: bastore
    //   417: dup
    //   418: bipush #19
    //   420: bipush #112
    //   422: bastore
    //   423: dup
    //   424: bipush #20
    //   426: bipush #86
    //   428: bastore
    //   429: dup
    //   430: bipush #21
    //   432: bipush #91
    //   434: bastore
    //   435: dup
    //   436: bipush #22
    //   438: bipush #36
    //   440: bastore
    //   441: dup
    //   442: bipush #23
    //   444: bipush #109
    //   446: bastore
    //   447: dup
    //   448: bipush #24
    //   450: bipush #87
    //   452: bastore
    //   453: dup
    //   454: bipush #25
    //   456: bipush #78
    //   458: bastore
    //   459: dup
    //   460: bipush #26
    //   462: bipush #-31
    //   464: bastore
    //   465: dup
    //   466: bipush #27
    //   468: bipush #72
    //   470: bastore
    //   471: dup
    //   472: bipush #28
    //   474: bipush #92
    //   476: bastore
    //   477: dup
    //   478: bipush #29
    //   480: bipush #-110
    //   482: bastore
    //   483: dup
    //   484: bipush #30
    //   486: bipush #-46
    //   488: bastore
    //   489: dup
    //   490: bipush #31
    //   492: bipush #-124
    //   494: bastore
    //   495: invokespecial <init> : (I[B)V
    //   498: putstatic burp/Zkf9.ZX : Ljava/lang/Object;
    //   501: sipush #-27866
    //   504: sipush #27075
    //   507: invokestatic a : (II)Ljava/lang/String;
    //   510: putstatic burp/Zkf9.ZS : Ljava/lang/String;
    //   513: return
  }
  
  private static Throwable a(Throwable paramThrowable) {
    return paramThrowable;
  }
  
  private static String a(int paramInt1, int paramInt2) {
    int i = (paramInt1 ^ 0xFFFF9320) & 0xFFFF;
    if (b[i] == null) {
      char[] arrayOfChar = a[i].toCharArray();
      switch (arrayOfChar[0] & 0xFF) {
        case 0:
        
        case 1:
        
        case 2:
        
        case 3:
        
        case 4:
        
        case 5:
        
        case 6:
        
        case 7:
        
        case 8:
        
        case 9:
        
        case 10:
        
        case 11:
        
        case 12:
        
        case 13:
        
        case 14:
        
        case 15:
        
        case 16:
        
        case 17:
        
        case 18:
        
        case 19:
        
        case 20:
        
        case 21:
        
        case 22:
        
        case 23:
        
        case 24:
        
        case 25:
        
        case 26:
        
        case 27:
        
        case 28:
        
        case 29:
        
        case 30:
        
        case 31:
        
        case 32:
        
        case 33:
        
        case 34:
        
        case 35:
        
        case 36:
        
        case 37:
        
        case 38:
        
        case 39:
        
        case 40:
        
        case 41:
        
        case 42:
        
        case 43:
        
        case 44:
        
        case 45:
        
        case 46:
        
        case 47:
        
        case 48:
        
        case 49:
        
        case 50:
        
        case 51:
        
        case 52:
        
        case 53:
        
        case 54:
        
        case 55:
        
        case 56:
        
        case 57:
        
        case 58:
        
        case 59:
        
        case 60:
        
        case 61:
        
        case 62:
        
        case 63:
        
        case 64:
        
        case 65:
        
        case 66:
        
        case 67:
        
        case 68:
        
        case 69:
        
        case 70:
        
        case 71:
        
        case 72:
        
        case 73:
        
        case 74:
        
        case 75:
        
        case 76:
        
        case 77:
        
        case 78:
        
        case 79:
        
        case 80:
        
        case 81:
        
        case 82:
        
        case 83:
        
        case 84:
        
        case 85:
        
        case 86:
        
        case 87:
        
        case 88:
        
        case 89:
        
        case 90:
        
        case 91:
        
        case 92:
        
        case 93:
        
        case 94:
        
        case 95:
        
        case 96:
        
        case 97:
        
        case 98:
        
        case 99:
        
        case 100:
        
        case 101:
        
        case 102:
        
        case 103:
        
        case 104:
        
        case 105:
        
        case 106:
        
        case 107:
        
        case 108:
        
        case 109:
        
        case 110:
        
        case 111:
        
        case 112:
        
        case 113:
        
        case 114:
        
        case 115:
        
        case 116:
        
        case 117:
        
        case 118:
        
        case 119:
        
        case 120:
        
        case 121:
        
        case 122:
        
        case 123:
        
        case 124:
        
        case 125:
        
        case 126:
        
        case 127:
        
        case 128:
        
        case 129:
        
        case 130:
        
        case 131:
        
        case 132:
        
        case 133:
        
        case 134:
        
        case 135:
        
        case 136:
        
        case 137:
        
        case 138:
        
        case 139:
        
        case 140:
        
        case 141:
        
        case 142:
        
        case 143:
        
        case 144:
        
        case 145:
        
        case 146:
        
        case 147:
        
        case 148:
        
        case 149:
        
        case 150:
        
        case 151:
        
        case 152:
        
        case 153:
        
        case 154:
        
        case 155:
        
        case 156:
        
        case 157:
        
        case 158:
        
        case 159:
        
        case 160:
        
        case 161:
        
        case 162:
        
        case 163:
        
        case 164:
        
        case 165:
        
        case 166:
        
        case 167:
        
        case 168:
        
        case 169:
        
        case 170:
        
        case 171:
        
        case 172:
        
        case 173:
        
        case 174:
        
        case 175:
        
        case 176:
        
        case 177:
        
        case 178:
        
        case 179:
        
        case 180:
        
        case 181:
        
        case 182:
        
        case 183:
        
        case 184:
        
        case 185:
        
        case 186:
        
        case 187:
        
        case 188:
        
        case 189:
        
        case 190:
        
        case 191:
        
        case 192:
        
        case 193:
        
        case 194:
        
        case 195:
        
        case 196:
        
        case 197:
        
        case 198:
        
        case 199:
        
        case 200:
        
        case 201:
        
        case 202:
        
        case 203:
        
        case 204:
        
        case 205:
        
        case 206:
        
        case 207:
        
        case 208:
        
        case 209:
        
        case 210:
        
        case 211:
        
        case 212:
        
        case 213:
        
        case 214:
        
        case 215:
        
        case 216:
        
        case 217:
        
        case 218:
        
        case 219:
        
        case 220:
        
        case 221:
        
        case 222:
        
        case 223:
        
        case 224:
        
        case 225:
        
        case 226:
        
        case 227:
        
        case 228:
        
        case 229:
        
        case 230:
        
        case 231:
        
        case 232:
        
        case 233:
        
        case 234:
        
        case 235:
        
        case 236:
        
        case 237:
        
        case 238:
        
        case 239:
        
        case 240:
        
        case 241:
        
        case 242:
        
        case 243:
        
        case 244:
        
        case 245:
        
        case 246:
        
        case 247:
        
        case 248:
        
        case 249:
        
        case 250:
        
        case 251:
        
        case 252:
        
        case 253:
        
        case 254:
        
        default:
          break;
      } 
      char c = 'Â°';
      int j = (paramInt2 & 0xFF) - c;
      if (j < 0)
        j += 256; 
      int k = ((paramInt2 & 0xFFFF) >>> 8) - c;
      if (k < 0)
        k += 256; 
      for (byte b = 0; b < arrayOfChar.length; b++) {
        int m = b % 2;
        if (m == 0) {
          arrayOfChar[b] = (char)(arrayOfChar[b] ^ j);
          j = ((j >>> 3 | j << 5) ^ arrayOfChar[b]) & 0xFF;
        } else {
          arrayOfChar[b] = (char)(arrayOfChar[b] ^ k);
          k = ((k >>> 3 | k << 5) ^ arrayOfChar[b]) & 0xFF;
        } 
      } 
      b[i] = (new String(arrayOfChar)).intern();
    } 
    return b[i];
  }
}


/* Location:              C:\Program Files\BurpSuitePro\burpsuite_pro.jar!\burp\Zkf9.class
 * Java compiler version: 21 (65.0)
 * JD-Core Version:       1.1.3
 */