package burp;

import java.math.BigInteger;

class Zkfb extends ClassLoader {
  static String ZV;
  
  static Object ZN;
  
  private static final String[] a;
  
  private static final String[] b;
  
  static boolean ZU(Object[] paramArrayOfObject, Object paramObject) throws Throwable {
    // Byte code:
    //   0: invokestatic ZK : ()Z
    //   3: istore_2
    //   4: getstatic burp/Zzpj.ZI : Ljava/lang/Object;
    //   7: checkcast java/math/BigInteger
    //   10: getstatic burp/Zmfw.ZS : Ljava/lang/Object;
    //   13: checkcast java/math/BigInteger
    //   16: invokevirtual add : (Ljava/math/BigInteger;)Ljava/math/BigInteger;
    //   19: putstatic burp/Zszm.ZI : Ljava/lang/Object;
    //   22: new java/lang/StringBuilder
    //   25: dup
    //   26: invokespecial <init> : ()V
    //   29: astore_3
    //   30: iconst_0
    //   31: istore #4
    //   33: iload #4
    //   35: bipush #32
    //   37: if_icmpge -> 1371
    //   40: iload #4
    //   42: tableswitch default -> 1364, 0 -> 184, 1 -> 221, 2 -> 258, 3 -> 295, 4 -> 332, 5 -> 369, 6 -> 406, 7 -> 443, 8 -> 480, 9 -> 517, 10 -> 554, 11 -> 591, 12 -> 628, 13 -> 665, 14 -> 702, 15 -> 739, 16 -> 776, 17 -> 813, 18 -> 850, 19 -> 887, 20 -> 924, 21 -> 961, 22 -> 998, 23 -> 1035, 24 -> 1072, 25 -> 1109, 26 -> 1146, 27 -> 1183, 28 -> 1220, 29 -> 1257, 30 -> 1294, 31 -> 1331
    //   184: aload_3
    //   185: getstatic burp/Zbzj.Zw : Ljava/lang/String;
    //   188: getstatic burp/Zbzj.Zz : Ljava/lang/Object;
    //   191: checkcast java/math/BigInteger
    //   194: invokevirtual intValue : ()I
    //   197: bipush #32
    //   199: irem
    //   200: invokestatic abs : (I)I
    //   203: invokevirtual charAt : (I)C
    //   206: invokevirtual append : (C)Ljava/lang/StringBuilder;
    //   209: pop
    //   210: iload_2
    //   211: ifeq -> 1364
    //   214: goto -> 221
    //   217: invokestatic a : (Ljava/lang/Throwable;)Ljava/lang/Throwable;
    //   220: athrow
    //   221: aload_3
    //   222: getstatic burp/Zzb2.ZJ : Ljava/lang/String;
    //   225: getstatic burp/Zm5s.ZB : Ljava/lang/Object;
    //   228: checkcast java/math/BigInteger
    //   231: invokevirtual intValue : ()I
    //   234: bipush #32
    //   236: irem
    //   237: invokestatic abs : (I)I
    //   240: invokevirtual charAt : (I)C
    //   243: invokevirtual append : (C)Ljava/lang/StringBuilder;
    //   246: pop
    //   247: iload_2
    //   248: ifeq -> 1364
    //   251: goto -> 258
    //   254: invokestatic a : (Ljava/lang/Throwable;)Ljava/lang/Throwable;
    //   257: athrow
    //   258: aload_3
    //   259: getstatic burp/Zzb2.ZJ : Ljava/lang/String;
    //   262: getstatic burp/Ztw4.ZF : Ljava/lang/Object;
    //   265: checkcast java/math/BigInteger
    //   268: invokevirtual intValue : ()I
    //   271: bipush #32
    //   273: irem
    //   274: invokestatic abs : (I)I
    //   277: invokevirtual charAt : (I)C
    //   280: invokevirtual append : (C)Ljava/lang/StringBuilder;
    //   283: pop
    //   284: iload_2
    //   285: ifeq -> 1364
    //   288: goto -> 295
    //   291: invokestatic a : (Ljava/lang/Throwable;)Ljava/lang/Throwable;
    //   294: athrow
    //   295: aload_3
    //   296: getstatic burp/Zktq.Zc : Ljava/lang/String;
    //   299: getstatic burp/Zrfh.ZJ : Ljava/lang/Object;
    //   302: checkcast java/math/BigInteger
    //   305: invokevirtual intValue : ()I
    //   308: bipush #32
    //   310: irem
    //   311: invokestatic abs : (I)I
    //   314: invokevirtual charAt : (I)C
    //   317: invokevirtual append : (C)Ljava/lang/StringBuilder;
    //   320: pop
    //   321: iload_2
    //   322: ifeq -> 1364
    //   325: goto -> 332
    //   328: invokestatic a : (Ljava/lang/Throwable;)Ljava/lang/Throwable;
    //   331: athrow
    //   332: aload_3
    //   333: getstatic burp/Zmdm.Za : Ljava/lang/String;
    //   336: getstatic burp/Zsot.ZJ : Ljava/lang/Object;
    //   339: checkcast java/math/BigInteger
    //   342: invokevirtual intValue : ()I
    //   345: bipush #32
    //   347: irem
    //   348: invokestatic abs : (I)I
    //   351: invokevirtual charAt : (I)C
    //   354: invokevirtual append : (C)Ljava/lang/StringBuilder;
    //   357: pop
    //   358: iload_2
    //   359: ifeq -> 1364
    //   362: goto -> 369
    //   365: invokestatic a : (Ljava/lang/Throwable;)Ljava/lang/Throwable;
    //   368: athrow
    //   369: aload_3
    //   370: getstatic burp/Zefn.Ze : Ljava/lang/String;
    //   373: getstatic burp/Zro_.ZP : Ljava/lang/Object;
    //   376: checkcast java/math/BigInteger
    //   379: invokevirtual intValue : ()I
    //   382: bipush #32
    //   384: irem
    //   385: invokestatic abs : (I)I
    //   388: invokevirtual charAt : (I)C
    //   391: invokevirtual append : (C)Ljava/lang/StringBuilder;
    //   394: pop
    //   395: iload_2
    //   396: ifeq -> 1364
    //   399: goto -> 406
    //   402: invokestatic a : (Ljava/lang/Throwable;)Ljava/lang/Throwable;
    //   405: athrow
    //   406: aload_3
    //   407: getstatic burp/Ze9.Zh : Ljava/lang/String;
    //   410: getstatic burp/Zth8.Zk : Ljava/lang/Object;
    //   413: checkcast java/math/BigInteger
    //   416: invokevirtual intValue : ()I
    //   419: bipush #32
    //   421: irem
    //   422: invokestatic abs : (I)I
    //   425: invokevirtual charAt : (I)C
    //   428: invokevirtual append : (C)Ljava/lang/StringBuilder;
    //   431: pop
    //   432: iload_2
    //   433: ifeq -> 1364
    //   436: goto -> 443
    //   439: invokestatic a : (Ljava/lang/Throwable;)Ljava/lang/Throwable;
    //   442: athrow
    //   443: aload_3
    //   444: getstatic burp/Zefn.Ze : Ljava/lang/String;
    //   447: getstatic burp/Zbzj.Zz : Ljava/lang/Object;
    //   450: checkcast java/math/BigInteger
    //   453: invokevirtual intValue : ()I
    //   456: bipush #32
    //   458: irem
    //   459: invokestatic abs : (I)I
    //   462: invokevirtual charAt : (I)C
    //   465: invokevirtual append : (C)Ljava/lang/StringBuilder;
    //   468: pop
    //   469: iload_2
    //   470: ifeq -> 1364
    //   473: goto -> 480
    //   476: invokestatic a : (Ljava/lang/Throwable;)Ljava/lang/Throwable;
    //   479: athrow
    //   480: aload_3
    //   481: getstatic burp/Zl1z.Zh : Ljava/lang/String;
    //   484: getstatic burp/Zkfb.ZN : Ljava/lang/Object;
    //   487: checkcast java/math/BigInteger
    //   490: invokevirtual intValue : ()I
    //   493: bipush #32
    //   495: irem
    //   496: invokestatic abs : (I)I
    //   499: invokevirtual charAt : (I)C
    //   502: invokevirtual append : (C)Ljava/lang/StringBuilder;
    //   505: pop
    //   506: iload_2
    //   507: ifeq -> 1364
    //   510: goto -> 517
    //   513: invokestatic a : (Ljava/lang/Throwable;)Ljava/lang/Throwable;
    //   516: athrow
    //   517: aload_3
    //   518: getstatic burp/Zs5k.ZI : Ljava/lang/String;
    //   521: getstatic burp/Zrnw.ZN : Ljava/lang/Object;
    //   524: checkcast java/math/BigInteger
    //   527: invokevirtual intValue : ()I
    //   530: bipush #32
    //   532: irem
    //   533: invokestatic abs : (I)I
    //   536: invokevirtual charAt : (I)C
    //   539: invokevirtual append : (C)Ljava/lang/StringBuilder;
    //   542: pop
    //   543: iload_2
    //   544: ifeq -> 1364
    //   547: goto -> 554
    //   550: invokestatic a : (Ljava/lang/Throwable;)Ljava/lang/Throwable;
    //   553: athrow
    //   554: aload_3
    //   555: getstatic burp/Zz8o.Zo : Ljava/lang/String;
    //   558: getstatic burp/Ztg3.Zg : Ljava/lang/Object;
    //   561: checkcast java/math/BigInteger
    //   564: invokevirtual intValue : ()I
    //   567: bipush #32
    //   569: irem
    //   570: invokestatic abs : (I)I
    //   573: invokevirtual charAt : (I)C
    //   576: invokevirtual append : (C)Ljava/lang/StringBuilder;
    //   579: pop
    //   580: iload_2
    //   581: ifeq -> 1364
    //   584: goto -> 591
    //   587: invokestatic a : (Ljava/lang/Throwable;)Ljava/lang/Throwable;
    //   590: athrow
    //   591: aload_3
    //   592: getstatic burp/Zrt9.Zc : Ljava/lang/String;
    //   595: getstatic burp/Zmec.ZY : Ljava/lang/Object;
    //   598: checkcast java/math/BigInteger
    //   601: invokevirtual intValue : ()I
    //   604: bipush #32
    //   606: irem
    //   607: invokestatic abs : (I)I
    //   610: invokevirtual charAt : (I)C
    //   613: invokevirtual append : (C)Ljava/lang/StringBuilder;
    //   616: pop
    //   617: iload_2
    //   618: ifeq -> 1364
    //   621: goto -> 628
    //   624: invokestatic a : (Ljava/lang/Throwable;)Ljava/lang/Throwable;
    //   627: athrow
    //   628: aload_3
    //   629: getstatic burp/Zmh0.Zs : Ljava/lang/String;
    //   632: getstatic burp/Zlvx.ZM : Ljava/lang/Object;
    //   635: checkcast java/math/BigInteger
    //   638: invokevirtual intValue : ()I
    //   641: bipush #32
    //   643: irem
    //   644: invokestatic abs : (I)I
    //   647: invokevirtual charAt : (I)C
    //   650: invokevirtual append : (C)Ljava/lang/StringBuilder;
    //   653: pop
    //   654: iload_2
    //   655: ifeq -> 1364
    //   658: goto -> 665
    //   661: invokestatic a : (Ljava/lang/Throwable;)Ljava/lang/Throwable;
    //   664: athrow
    //   665: aload_3
    //   666: getstatic burp/Zbxa.ZY : Ljava/lang/String;
    //   669: getstatic burp/Zm14.ZZ : Ljava/lang/Object;
    //   672: checkcast java/math/BigInteger
    //   675: invokevirtual intValue : ()I
    //   678: bipush #32
    //   680: irem
    //   681: invokestatic abs : (I)I
    //   684: invokevirtual charAt : (I)C
    //   687: invokevirtual append : (C)Ljava/lang/StringBuilder;
    //   690: pop
    //   691: iload_2
    //   692: ifeq -> 1364
    //   695: goto -> 702
    //   698: invokestatic a : (Ljava/lang/Throwable;)Ljava/lang/Throwable;
    //   701: athrow
    //   702: aload_3
    //   703: getstatic burp/Zlwi.ZN : Ljava/lang/String;
    //   706: getstatic burp/Zr8r.ZR : Ljava/lang/Object;
    //   709: checkcast java/math/BigInteger
    //   712: invokevirtual intValue : ()I
    //   715: bipush #32
    //   717: irem
    //   718: invokestatic abs : (I)I
    //   721: invokevirtual charAt : (I)C
    //   724: invokevirtual append : (C)Ljava/lang/StringBuilder;
    //   727: pop
    //   728: iload_2
    //   729: ifeq -> 1364
    //   732: goto -> 739
    //   735: invokestatic a : (Ljava/lang/Throwable;)Ljava/lang/Throwable;
    //   738: athrow
    //   739: aload_3
    //   740: getstatic burp/Zrx5.ZD : Ljava/lang/String;
    //   743: getstatic burp/Zmh0.Zt : Ljava/lang/Object;
    //   746: checkcast java/math/BigInteger
    //   749: invokevirtual intValue : ()I
    //   752: bipush #32
    //   754: irem
    //   755: invokestatic abs : (I)I
    //   758: invokevirtual charAt : (I)C
    //   761: invokevirtual append : (C)Ljava/lang/StringBuilder;
    //   764: pop
    //   765: iload_2
    //   766: ifeq -> 1364
    //   769: goto -> 776
    //   772: invokestatic a : (Ljava/lang/Throwable;)Ljava/lang/Throwable;
    //   775: athrow
    //   776: aload_3
    //   777: getstatic burp/Zzoc.Zg : Ljava/lang/String;
    //   780: getstatic burp/Zzpj.ZI : Ljava/lang/Object;
    //   783: checkcast java/math/BigInteger
    //   786: invokevirtual intValue : ()I
    //   789: bipush #32
    //   791: irem
    //   792: invokestatic abs : (I)I
    //   795: invokevirtual charAt : (I)C
    //   798: invokevirtual append : (C)Ljava/lang/StringBuilder;
    //   801: pop
    //   802: iload_2
    //   803: ifeq -> 1364
    //   806: goto -> 813
    //   809: invokestatic a : (Ljava/lang/Throwable;)Ljava/lang/Throwable;
    //   812: athrow
    //   813: aload_3
    //   814: getstatic burp/Ztg3.ZM : Ljava/lang/String;
    //   817: getstatic burp/Zt5a.Zs : Ljava/lang/Object;
    //   820: checkcast java/math/BigInteger
    //   823: invokevirtual intValue : ()I
    //   826: bipush #32
    //   828: irem
    //   829: invokestatic abs : (I)I
    //   832: invokevirtual charAt : (I)C
    //   835: invokevirtual append : (C)Ljava/lang/StringBuilder;
    //   838: pop
    //   839: iload_2
    //   840: ifeq -> 1364
    //   843: goto -> 850
    //   846: invokestatic a : (Ljava/lang/Throwable;)Ljava/lang/Throwable;
    //   849: athrow
    //   850: aload_3
    //   851: getstatic burp/Zth8.ZN : Ljava/lang/String;
    //   854: getstatic burp/Zlzs.ZL : Ljava/lang/Object;
    //   857: checkcast java/math/BigInteger
    //   860: invokevirtual intValue : ()I
    //   863: bipush #32
    //   865: irem
    //   866: invokestatic abs : (I)I
    //   869: invokevirtual charAt : (I)C
    //   872: invokevirtual append : (C)Ljava/lang/StringBuilder;
    //   875: pop
    //   876: iload_2
    //   877: ifeq -> 1364
    //   880: goto -> 887
    //   883: invokestatic a : (Ljava/lang/Throwable;)Ljava/lang/Throwable;
    //   886: athrow
    //   887: aload_3
    //   888: getstatic burp/Zg1k.Ze : Ljava/lang/String;
    //   891: getstatic burp/Zz5l.Zb : Ljava/lang/Object;
    //   894: checkcast java/math/BigInteger
    //   897: invokevirtual intValue : ()I
    //   900: bipush #32
    //   902: irem
    //   903: invokestatic abs : (I)I
    //   906: invokevirtual charAt : (I)C
    //   909: invokevirtual append : (C)Ljava/lang/StringBuilder;
    //   912: pop
    //   913: iload_2
    //   914: ifeq -> 1364
    //   917: goto -> 924
    //   920: invokestatic a : (Ljava/lang/Throwable;)Ljava/lang/Throwable;
    //   923: athrow
    //   924: aload_3
    //   925: getstatic burp/Ztpg.Zr : Ljava/lang/String;
    //   928: getstatic burp/Zz0.ZJ : Ljava/lang/Object;
    //   931: checkcast java/math/BigInteger
    //   934: invokevirtual intValue : ()I
    //   937: bipush #32
    //   939: irem
    //   940: invokestatic abs : (I)I
    //   943: invokevirtual charAt : (I)C
    //   946: invokevirtual append : (C)Ljava/lang/StringBuilder;
    //   949: pop
    //   950: iload_2
    //   951: ifeq -> 1364
    //   954: goto -> 961
    //   957: invokestatic a : (Ljava/lang/Throwable;)Ljava/lang/Throwable;
    //   960: athrow
    //   961: aload_3
    //   962: getstatic burp/Zrfh.ZH : Ljava/lang/String;
    //   965: getstatic burp/Zt7k.Zc : Ljava/lang/Object;
    //   968: checkcast java/math/BigInteger
    //   971: invokevirtual intValue : ()I
    //   974: bipush #32
    //   976: irem
    //   977: invokestatic abs : (I)I
    //   980: invokevirtual charAt : (I)C
    //   983: invokevirtual append : (C)Ljava/lang/StringBuilder;
    //   986: pop
    //   987: iload_2
    //   988: ifeq -> 1364
    //   991: goto -> 998
    //   994: invokestatic a : (Ljava/lang/Throwable;)Ljava/lang/Throwable;
    //   997: athrow
    //   998: aload_3
    //   999: getstatic burp/Zm5s.Z_ : Ljava/lang/String;
    //   1002: getstatic burp/Zktq.Zn : Ljava/lang/Object;
    //   1005: checkcast java/math/BigInteger
    //   1008: invokevirtual intValue : ()I
    //   1011: bipush #32
    //   1013: irem
    //   1014: invokestatic abs : (I)I
    //   1017: invokevirtual charAt : (I)C
    //   1020: invokevirtual append : (C)Ljava/lang/StringBuilder;
    //   1023: pop
    //   1024: iload_2
    //   1025: ifeq -> 1364
    //   1028: goto -> 1035
    //   1031: invokestatic a : (Ljava/lang/Throwable;)Ljava/lang/Throwable;
    //   1034: athrow
    //   1035: aload_3
    //   1036: getstatic burp/Zrfh.ZH : Ljava/lang/String;
    //   1039: getstatic burp/Ztc2.ZM : Ljava/lang/Object;
    //   1042: checkcast java/math/BigInteger
    //   1045: invokevirtual intValue : ()I
    //   1048: bipush #32
    //   1050: irem
    //   1051: invokestatic abs : (I)I
    //   1054: invokevirtual charAt : (I)C
    //   1057: invokevirtual append : (C)Ljava/lang/StringBuilder;
    //   1060: pop
    //   1061: iload_2
    //   1062: ifeq -> 1364
    //   1065: goto -> 1072
    //   1068: invokestatic a : (Ljava/lang/Throwable;)Ljava/lang/Throwable;
    //   1071: athrow
    //   1072: aload_3
    //   1073: getstatic burp/Zr4z.Zw : Ljava/lang/String;
    //   1076: getstatic burp/Zmfw.ZS : Ljava/lang/Object;
    //   1079: checkcast java/math/BigInteger
    //   1082: invokevirtual intValue : ()I
    //   1085: bipush #32
    //   1087: irem
    //   1088: invokestatic abs : (I)I
    //   1091: invokevirtual charAt : (I)C
    //   1094: invokevirtual append : (C)Ljava/lang/StringBuilder;
    //   1097: pop
    //   1098: iload_2
    //   1099: ifeq -> 1364
    //   1102: goto -> 1109
    //   1105: invokestatic a : (Ljava/lang/Throwable;)Ljava/lang/Throwable;
    //   1108: athrow
    //   1109: aload_3
    //   1110: getstatic burp/Zg_6.Zc : Ljava/lang/String;
    //   1113: getstatic burp/Zzh9.Zv : Ljava/lang/Object;
    //   1116: checkcast java/math/BigInteger
    //   1119: invokevirtual intValue : ()I
    //   1122: bipush #32
    //   1124: irem
    //   1125: invokestatic abs : (I)I
    //   1128: invokevirtual charAt : (I)C
    //   1131: invokevirtual append : (C)Ljava/lang/StringBuilder;
    //   1134: pop
    //   1135: iload_2
    //   1136: ifeq -> 1364
    //   1139: goto -> 1146
    //   1142: invokestatic a : (Ljava/lang/Throwable;)Ljava/lang/Throwable;
    //   1145: athrow
    //   1146: aload_3
    //   1147: getstatic burp/Zg1k.Ze : Ljava/lang/String;
    //   1150: getstatic burp/Zrnw.ZN : Ljava/lang/Object;
    //   1153: checkcast java/math/BigInteger
    //   1156: invokevirtual intValue : ()I
    //   1159: bipush #32
    //   1161: irem
    //   1162: invokestatic abs : (I)I
    //   1165: invokevirtual charAt : (I)C
    //   1168: invokevirtual append : (C)Ljava/lang/StringBuilder;
    //   1171: pop
    //   1172: iload_2
    //   1173: ifeq -> 1364
    //   1176: goto -> 1183
    //   1179: invokestatic a : (Ljava/lang/Throwable;)Ljava/lang/Throwable;
    //   1182: athrow
    //   1183: aload_3
    //   1184: getstatic burp/Zenq.ZG : Ljava/lang/String;
    //   1187: getstatic burp/Zr4z.ZH : Ljava/lang/Object;
    //   1190: checkcast java/math/BigInteger
    //   1193: invokevirtual intValue : ()I
    //   1196: bipush #32
    //   1198: irem
    //   1199: invokestatic abs : (I)I
    //   1202: invokevirtual charAt : (I)C
    //   1205: invokevirtual append : (C)Ljava/lang/StringBuilder;
    //   1208: pop
    //   1209: iload_2
    //   1210: ifeq -> 1364
    //   1213: goto -> 1220
    //   1216: invokestatic a : (Ljava/lang/Throwable;)Ljava/lang/Throwable;
    //   1219: athrow
    //   1220: aload_3
    //   1221: getstatic burp/Zmh0.Zs : Ljava/lang/String;
    //   1224: getstatic burp/Zmfw.ZS : Ljava/lang/Object;
    //   1227: checkcast java/math/BigInteger
    //   1230: invokevirtual intValue : ()I
    //   1233: bipush #32
    //   1235: irem
    //   1236: invokestatic abs : (I)I
    //   1239: invokevirtual charAt : (I)C
    //   1242: invokevirtual append : (C)Ljava/lang/StringBuilder;
    //   1245: pop
    //   1246: iload_2
    //   1247: ifeq -> 1364
    //   1250: goto -> 1257
    //   1253: invokestatic a : (Ljava/lang/Throwable;)Ljava/lang/Throwable;
    //   1256: athrow
    //   1257: aload_3
    //   1258: getstatic burp/Zzh9.ZF : Ljava/lang/String;
    //   1261: getstatic burp/Ztc2.ZM : Ljava/lang/Object;
    //   1264: checkcast java/math/BigInteger
    //   1267: invokevirtual intValue : ()I
    //   1270: bipush #32
    //   1272: irem
    //   1273: invokestatic abs : (I)I
    //   1276: invokevirtual charAt : (I)C
    //   1279: invokevirtual append : (C)Ljava/lang/StringBuilder;
    //   1282: pop
    //   1283: iload_2
    //   1284: ifeq -> 1364
    //   1287: goto -> 1294
    //   1290: invokestatic a : (Ljava/lang/Throwable;)Ljava/lang/Throwable;
    //   1293: athrow
    //   1294: aload_3
    //   1295: getstatic burp/Zbxa.ZY : Ljava/lang/String;
    //   1298: getstatic burp/Zm14.ZZ : Ljava/lang/Object;
    //   1301: checkcast java/math/BigInteger
    //   1304: invokevirtual intValue : ()I
    //   1307: bipush #32
    //   1309: irem
    //   1310: invokestatic abs : (I)I
    //   1313: invokevirtual charAt : (I)C
    //   1316: invokevirtual append : (C)Ljava/lang/StringBuilder;
    //   1319: pop
    //   1320: iload_2
    //   1321: ifeq -> 1364
    //   1324: goto -> 1331
    //   1327: invokestatic a : (Ljava/lang/Throwable;)Ljava/lang/Throwable;
    //   1330: athrow
    //   1331: aload_3
    //   1332: getstatic burp/Zb8_.ZP : Ljava/lang/String;
    //   1335: getstatic burp/Zzhu.ZW : Ljava/lang/Object;
    //   1338: checkcast java/math/BigInteger
    //   1341: invokevirtual intValue : ()I
    //   1344: bipush #32
    //   1346: irem
    //   1347: invokestatic abs : (I)I
    //   1350: invokevirtual charAt : (I)C
    //   1353: invokevirtual append : (C)Ljava/lang/StringBuilder;
    //   1356: pop
    //   1357: goto -> 1364
    //   1360: invokestatic a : (Ljava/lang/Throwable;)Ljava/lang/Throwable;
    //   1363: athrow
    //   1364: iinc #4, 1
    //   1367: iload_2
    //   1368: ifeq -> 33
    //   1371: aload_3
    //   1372: invokevirtual toString : ()Ljava/lang/String;
    //   1375: putstatic burp/Zro_.Zz : Ljava/lang/String;
    //   1378: getstatic burp/Zktq.Zn : Ljava/lang/Object;
    //   1381: checkcast java/math/BigInteger
    //   1384: invokevirtual toByteArray : ()[B
    //   1387: astore #4
    //   1389: bipush #32
    //   1391: newarray int
    //   1393: dup
    //   1394: iconst_0
    //   1395: ldc 876216579
    //   1397: iastore
    //   1398: dup
    //   1399: iconst_1
    //   1400: ldc 455999525
    //   1402: iastore
    //   1403: dup
    //   1404: iconst_2
    //   1405: ldc 1043334948
    //   1407: iastore
    //   1408: dup
    //   1409: iconst_3
    //   1410: ldc 439222784
    //   1412: iastore
    //   1413: dup
    //   1414: iconst_4
    //   1415: ldc 372376604
    //   1417: iastore
    //   1418: dup
    //   1419: iconst_5
    //   1420: ldc 707731490
    //   1422: iastore
    //   1423: dup
    //   1424: bipush #6
    //   1426: ldc 389426184
    //   1428: iastore
    //   1429: dup
    //   1430: bipush #7
    //   1432: ldc 973875457
    //   1434: iastore
    //   1435: dup
    //   1436: bipush #8
    //   1438: ldc 389160971
    //   1440: iastore
    //   1441: dup
    //   1442: bipush #9
    //   1444: ldc 907870729
    //   1446: iastore
    //   1447: dup
    //   1448: bipush #10
    //   1450: ldc 121057538
    //   1452: iastore
    //   1453: dup
    //   1454: bipush #11
    //   1456: ldc 840500228
    //   1458: iastore
    //   1459: dup
    //   1460: bipush #12
    //   1462: ldc 254150144
    //   1464: iastore
    //   1465: dup
    //   1466: bipush #13
    //   1468: ldc 924386310
    //   1470: iastore
    //   1471: dup
    //   1472: bipush #14
    //   1474: ldc 187632156
    //   1476: iastore
    //   1477: dup
    //   1478: bipush #15
    //   1480: ldc 874189824
    //   1482: iastore
    //   1483: dup
    //   1484: bipush #16
    //   1486: ldc 655302664
    //   1488: iastore
    //   1489: dup
    //   1490: bipush #17
    //   1492: ldc 890966315
    //   1494: iastore
    //   1495: dup
    //   1496: bipush #18
    //   1498: ldc 722417666
    //   1500: iastore
    //   1501: dup
    //   1502: bipush #19
    //   1504: ldc 1026621720
    //   1506: iastore
    //   1507: dup
    //   1508: bipush #20
    //   1510: ldc 957157408
    //   1512: iastore
    //   1513: dup
    //   1514: bipush #21
    //   1516: ldc 892536332
    //   1518: iastore
    //   1519: dup
    //   1520: bipush #22
    //   1522: ldc 689771012
    //   1524: iastore
    //   1525: dup
    //   1526: bipush #23
    //   1528: ldc 221709344
    //   1530: iastore
    //   1531: dup
    //   1532: bipush #24
    //   1534: ldc 940377620
    //   1536: iastore
    //   1537: dup
    //   1538: bipush #25
    //   1540: ldc 255209728
    //   1542: iastore
    //   1543: dup
    //   1544: bipush #26
    //   1546: ldc 1010368540
    //   1548: iastore
    //   1549: dup
    //   1550: bipush #27
    //   1552: ldc 220604441
    //   1554: iastore
    //   1555: dup
    //   1556: bipush #28
    //   1558: ldc 1008414755
    //   1560: iastore
    //   1561: dup
    //   1562: bipush #29
    //   1564: ldc 187049985
    //   1566: iastore
    //   1567: dup
    //   1568: bipush #30
    //   1570: ldc 943331329
    //   1572: iastore
    //   1573: dup
    //   1574: bipush #31
    //   1576: ldc 170788368
    //   1578: iastore
    //   1579: astore #6
    //   1581: bipush #64
    //   1583: newarray int
    //   1585: dup
    //   1586: iconst_0
    //   1587: ldc 16843776
    //   1589: iastore
    //   1590: dup
    //   1591: iconst_1
    //   1592: iconst_0
    //   1593: iastore
    //   1594: dup
    //   1595: iconst_2
    //   1596: ldc 65536
    //   1598: iastore
    //   1599: dup
    //   1600: iconst_3
    //   1601: ldc 16843780
    //   1603: iastore
    //   1604: dup
    //   1605: iconst_4
    //   1606: ldc 16842756
    //   1608: iastore
    //   1609: dup
    //   1610: iconst_5
    //   1611: ldc 66564
    //   1613: iastore
    //   1614: dup
    //   1615: bipush #6
    //   1617: iconst_4
    //   1618: iastore
    //   1619: dup
    //   1620: bipush #7
    //   1622: ldc 65536
    //   1624: iastore
    //   1625: dup
    //   1626: bipush #8
    //   1628: sipush #1024
    //   1631: iastore
    //   1632: dup
    //   1633: bipush #9
    //   1635: ldc 16843776
    //   1637: iastore
    //   1638: dup
    //   1639: bipush #10
    //   1641: ldc 16843780
    //   1643: iastore
    //   1644: dup
    //   1645: bipush #11
    //   1647: sipush #1024
    //   1650: iastore
    //   1651: dup
    //   1652: bipush #12
    //   1654: ldc 16778244
    //   1656: iastore
    //   1657: dup
    //   1658: bipush #13
    //   1660: ldc 16842756
    //   1662: iastore
    //   1663: dup
    //   1664: bipush #14
    //   1666: ldc 16777216
    //   1668: iastore
    //   1669: dup
    //   1670: bipush #15
    //   1672: iconst_4
    //   1673: iastore
    //   1674: dup
    //   1675: bipush #16
    //   1677: sipush #1028
    //   1680: iastore
    //   1681: dup
    //   1682: bipush #17
    //   1684: ldc 16778240
    //   1686: iastore
    //   1687: dup
    //   1688: bipush #18
    //   1690: ldc 16778240
    //   1692: iastore
    //   1693: dup
    //   1694: bipush #19
    //   1696: ldc 66560
    //   1698: iastore
    //   1699: dup
    //   1700: bipush #20
    //   1702: ldc 66560
    //   1704: iastore
    //   1705: dup
    //   1706: bipush #21
    //   1708: ldc 16842752
    //   1710: iastore
    //   1711: dup
    //   1712: bipush #22
    //   1714: ldc 16842752
    //   1716: iastore
    //   1717: dup
    //   1718: bipush #23
    //   1720: ldc 16778244
    //   1722: iastore
    //   1723: dup
    //   1724: bipush #24
    //   1726: ldc 65540
    //   1728: iastore
    //   1729: dup
    //   1730: bipush #25
    //   1732: ldc 16777220
    //   1734: iastore
    //   1735: dup
    //   1736: bipush #26
    //   1738: ldc 16777220
    //   1740: iastore
    //   1741: dup
    //   1742: bipush #27
    //   1744: ldc 65540
    //   1746: iastore
    //   1747: dup
    //   1748: bipush #28
    //   1750: iconst_0
    //   1751: iastore
    //   1752: dup
    //   1753: bipush #29
    //   1755: sipush #1028
    //   1758: iastore
    //   1759: dup
    //   1760: bipush #30
    //   1762: ldc 66564
    //   1764: iastore
    //   1765: dup
    //   1766: bipush #31
    //   1768: ldc 16777216
    //   1770: iastore
    //   1771: dup
    //   1772: bipush #32
    //   1774: ldc 65536
    //   1776: iastore
    //   1777: dup
    //   1778: bipush #33
    //   1780: ldc 16843780
    //   1782: iastore
    //   1783: dup
    //   1784: bipush #34
    //   1786: iconst_4
    //   1787: iastore
    //   1788: dup
    //   1789: bipush #35
    //   1791: ldc 16842752
    //   1793: iastore
    //   1794: dup
    //   1795: bipush #36
    //   1797: ldc 16843776
    //   1799: iastore
    //   1800: dup
    //   1801: bipush #37
    //   1803: ldc 16777216
    //   1805: iastore
    //   1806: dup
    //   1807: bipush #38
    //   1809: ldc 16777216
    //   1811: iastore
    //   1812: dup
    //   1813: bipush #39
    //   1815: sipush #1024
    //   1818: iastore
    //   1819: dup
    //   1820: bipush #40
    //   1822: ldc 16842756
    //   1824: iastore
    //   1825: dup
    //   1826: bipush #41
    //   1828: ldc 65536
    //   1830: iastore
    //   1831: dup
    //   1832: bipush #42
    //   1834: ldc 66560
    //   1836: iastore
    //   1837: dup
    //   1838: bipush #43
    //   1840: ldc 16777220
    //   1842: iastore
    //   1843: dup
    //   1844: bipush #44
    //   1846: sipush #1024
    //   1849: iastore
    //   1850: dup
    //   1851: bipush #45
    //   1853: iconst_4
    //   1854: iastore
    //   1855: dup
    //   1856: bipush #46
    //   1858: ldc 16778244
    //   1860: iastore
    //   1861: dup
    //   1862: bipush #47
    //   1864: ldc 66564
    //   1866: iastore
    //   1867: dup
    //   1868: bipush #48
    //   1870: ldc 16843780
    //   1872: iastore
    //   1873: dup
    //   1874: bipush #49
    //   1876: ldc 65540
    //   1878: iastore
    //   1879: dup
    //   1880: bipush #50
    //   1882: ldc 16842752
    //   1884: iastore
    //   1885: dup
    //   1886: bipush #51
    //   1888: ldc 16778244
    //   1890: iastore
    //   1891: dup
    //   1892: bipush #52
    //   1894: ldc 16777220
    //   1896: iastore
    //   1897: dup
    //   1898: bipush #53
    //   1900: sipush #1028
    //   1903: iastore
    //   1904: dup
    //   1905: bipush #54
    //   1907: ldc 66564
    //   1909: iastore
    //   1910: dup
    //   1911: bipush #55
    //   1913: ldc 16843776
    //   1915: iastore
    //   1916: dup
    //   1917: bipush #56
    //   1919: sipush #1028
    //   1922: iastore
    //   1923: dup
    //   1924: bipush #57
    //   1926: ldc 16778240
    //   1928: iastore
    //   1929: dup
    //   1930: bipush #58
    //   1932: ldc 16778240
    //   1934: iastore
    //   1935: dup
    //   1936: bipush #59
    //   1938: iconst_0
    //   1939: iastore
    //   1940: dup
    //   1941: bipush #60
    //   1943: ldc 65540
    //   1945: iastore
    //   1946: dup
    //   1947: bipush #61
    //   1949: ldc 66560
    //   1951: iastore
    //   1952: dup
    //   1953: bipush #62
    //   1955: iconst_0
    //   1956: iastore
    //   1957: dup
    //   1958: bipush #63
    //   1960: ldc 16842756
    //   1962: iastore
    //   1963: astore #7
    //   1965: bipush #64
    //   1967: newarray int
    //   1969: dup
    //   1970: iconst_0
    //   1971: ldc -2146402272
    //   1973: iastore
    //   1974: dup
    //   1975: iconst_1
    //   1976: ldc -2147450880
    //   1978: iastore
    //   1979: dup
    //   1980: iconst_2
    //   1981: ldc 32768
    //   1983: iastore
    //   1984: dup
    //   1985: iconst_3
    //   1986: ldc 1081376
    //   1988: iastore
    //   1989: dup
    //   1990: iconst_4
    //   1991: ldc 1048576
    //   1993: iastore
    //   1994: dup
    //   1995: iconst_5
    //   1996: bipush #32
    //   1998: iastore
    //   1999: dup
    //   2000: bipush #6
    //   2002: ldc -2146435040
    //   2004: iastore
    //   2005: dup
    //   2006: bipush #7
    //   2008: ldc -2147450848
    //   2010: iastore
    //   2011: dup
    //   2012: bipush #8
    //   2014: ldc -2147483616
    //   2016: iastore
    //   2017: dup
    //   2018: bipush #9
    //   2020: ldc -2146402272
    //   2022: iastore
    //   2023: dup
    //   2024: bipush #10
    //   2026: ldc -2146402304
    //   2028: iastore
    //   2029: dup
    //   2030: bipush #11
    //   2032: ldc -2147483648
    //   2034: iastore
    //   2035: dup
    //   2036: bipush #12
    //   2038: ldc -2147450880
    //   2040: iastore
    //   2041: dup
    //   2042: bipush #13
    //   2044: ldc 1048576
    //   2046: iastore
    //   2047: dup
    //   2048: bipush #14
    //   2050: bipush #32
    //   2052: iastore
    //   2053: dup
    //   2054: bipush #15
    //   2056: ldc -2146435040
    //   2058: iastore
    //   2059: dup
    //   2060: bipush #16
    //   2062: ldc 1081344
    //   2064: iastore
    //   2065: dup
    //   2066: bipush #17
    //   2068: ldc 1048608
    //   2070: iastore
    //   2071: dup
    //   2072: bipush #18
    //   2074: ldc -2147450848
    //   2076: iastore
    //   2077: dup
    //   2078: bipush #19
    //   2080: iconst_0
    //   2081: iastore
    //   2082: dup
    //   2083: bipush #20
    //   2085: ldc -2147483648
    //   2087: iastore
    //   2088: dup
    //   2089: bipush #21
    //   2091: ldc 32768
    //   2093: iastore
    //   2094: dup
    //   2095: bipush #22
    //   2097: ldc 1081376
    //   2099: iastore
    //   2100: dup
    //   2101: bipush #23
    //   2103: ldc -2146435072
    //   2105: iastore
    //   2106: dup
    //   2107: bipush #24
    //   2109: ldc 1048608
    //   2111: iastore
    //   2112: dup
    //   2113: bipush #25
    //   2115: ldc -2147483616
    //   2117: iastore
    //   2118: dup
    //   2119: bipush #26
    //   2121: iconst_0
    //   2122: iastore
    //   2123: dup
    //   2124: bipush #27
    //   2126: ldc 1081344
    //   2128: iastore
    //   2129: dup
    //   2130: bipush #28
    //   2132: ldc 32800
    //   2134: iastore
    //   2135: dup
    //   2136: bipush #29
    //   2138: ldc -2146402304
    //   2140: iastore
    //   2141: dup
    //   2142: bipush #30
    //   2144: ldc -2146435072
    //   2146: iastore
    //   2147: dup
    //   2148: bipush #31
    //   2150: ldc 32800
    //   2152: iastore
    //   2153: dup
    //   2154: bipush #32
    //   2156: iconst_0
    //   2157: iastore
    //   2158: dup
    //   2159: bipush #33
    //   2161: ldc 1081376
    //   2163: iastore
    //   2164: dup
    //   2165: bipush #34
    //   2167: ldc -2146435040
    //   2169: iastore
    //   2170: dup
    //   2171: bipush #35
    //   2173: ldc 1048576
    //   2175: iastore
    //   2176: dup
    //   2177: bipush #36
    //   2179: ldc -2147450848
    //   2181: iastore
    //   2182: dup
    //   2183: bipush #37
    //   2185: ldc -2146435072
    //   2187: iastore
    //   2188: dup
    //   2189: bipush #38
    //   2191: ldc -2146402304
    //   2193: iastore
    //   2194: dup
    //   2195: bipush #39
    //   2197: ldc 32768
    //   2199: iastore
    //   2200: dup
    //   2201: bipush #40
    //   2203: ldc -2146435072
    //   2205: iastore
    //   2206: dup
    //   2207: bipush #41
    //   2209: ldc -2147450880
    //   2211: iastore
    //   2212: dup
    //   2213: bipush #42
    //   2215: bipush #32
    //   2217: iastore
    //   2218: dup
    //   2219: bipush #43
    //   2221: ldc -2146402272
    //   2223: iastore
    //   2224: dup
    //   2225: bipush #44
    //   2227: ldc 1081376
    //   2229: iastore
    //   2230: dup
    //   2231: bipush #45
    //   2233: bipush #32
    //   2235: iastore
    //   2236: dup
    //   2237: bipush #46
    //   2239: ldc 32768
    //   2241: iastore
    //   2242: dup
    //   2243: bipush #47
    //   2245: ldc -2147483648
    //   2247: iastore
    //   2248: dup
    //   2249: bipush #48
    //   2251: ldc 32800
    //   2253: iastore
    //   2254: dup
    //   2255: bipush #49
    //   2257: ldc -2146402304
    //   2259: iastore
    //   2260: dup
    //   2261: bipush #50
    //   2263: ldc 1048576
    //   2265: iastore
    //   2266: dup
    //   2267: bipush #51
    //   2269: ldc -2147483616
    //   2271: iastore
    //   2272: dup
    //   2273: bipush #52
    //   2275: ldc 1048608
    //   2277: iastore
    //   2278: dup
    //   2279: bipush #53
    //   2281: ldc -2147450848
    //   2283: iastore
    //   2284: dup
    //   2285: bipush #54
    //   2287: ldc -2147483616
    //   2289: iastore
    //   2290: dup
    //   2291: bipush #55
    //   2293: ldc 1048608
    //   2295: iastore
    //   2296: dup
    //   2297: bipush #56
    //   2299: ldc 1081344
    //   2301: iastore
    //   2302: dup
    //   2303: bipush #57
    //   2305: iconst_0
    //   2306: iastore
    //   2307: dup
    //   2308: bipush #58
    //   2310: ldc -2147450880
    //   2312: iastore
    //   2313: dup
    //   2314: bipush #59
    //   2316: ldc 32800
    //   2318: iastore
    //   2319: dup
    //   2320: bipush #60
    //   2322: ldc -2147483648
    //   2324: iastore
    //   2325: dup
    //   2326: bipush #61
    //   2328: ldc -2146435040
    //   2330: iastore
    //   2331: dup
    //   2332: bipush #62
    //   2334: ldc -2146402272
    //   2336: iastore
    //   2337: dup
    //   2338: bipush #63
    //   2340: ldc 1081344
    //   2342: iastore
    //   2343: astore #8
    //   2345: bipush #64
    //   2347: newarray int
    //   2349: dup
    //   2350: iconst_0
    //   2351: sipush #520
    //   2354: iastore
    //   2355: dup
    //   2356: iconst_1
    //   2357: ldc 134349312
    //   2359: iastore
    //   2360: dup
    //   2361: iconst_2
    //   2362: iconst_0
    //   2363: iastore
    //   2364: dup
    //   2365: iconst_3
    //   2366: ldc 134348808
    //   2368: iastore
    //   2369: dup
    //   2370: iconst_4
    //   2371: ldc 134218240
    //   2373: iastore
    //   2374: dup
    //   2375: iconst_5
    //   2376: iconst_0
    //   2377: iastore
    //   2378: dup
    //   2379: bipush #6
    //   2381: ldc 131592
    //   2383: iastore
    //   2384: dup
    //   2385: bipush #7
    //   2387: ldc 134218240
    //   2389: iastore
    //   2390: dup
    //   2391: bipush #8
    //   2393: ldc 131080
    //   2395: iastore
    //   2396: dup
    //   2397: bipush #9
    //   2399: ldc 134217736
    //   2401: iastore
    //   2402: dup
    //   2403: bipush #10
    //   2405: ldc 134217736
    //   2407: iastore
    //   2408: dup
    //   2409: bipush #11
    //   2411: ldc 131072
    //   2413: iastore
    //   2414: dup
    //   2415: bipush #12
    //   2417: ldc 134349320
    //   2419: iastore
    //   2420: dup
    //   2421: bipush #13
    //   2423: ldc 131080
    //   2425: iastore
    //   2426: dup
    //   2427: bipush #14
    //   2429: ldc 134348800
    //   2431: iastore
    //   2432: dup
    //   2433: bipush #15
    //   2435: sipush #520
    //   2438: iastore
    //   2439: dup
    //   2440: bipush #16
    //   2442: ldc 134217728
    //   2444: iastore
    //   2445: dup
    //   2446: bipush #17
    //   2448: bipush #8
    //   2450: iastore
    //   2451: dup
    //   2452: bipush #18
    //   2454: ldc 134349312
    //   2456: iastore
    //   2457: dup
    //   2458: bipush #19
    //   2460: sipush #512
    //   2463: iastore
    //   2464: dup
    //   2465: bipush #20
    //   2467: ldc 131584
    //   2469: iastore
    //   2470: dup
    //   2471: bipush #21
    //   2473: ldc 134348800
    //   2475: iastore
    //   2476: dup
    //   2477: bipush #22
    //   2479: ldc 134348808
    //   2481: iastore
    //   2482: dup
    //   2483: bipush #23
    //   2485: ldc 131592
    //   2487: iastore
    //   2488: dup
    //   2489: bipush #24
    //   2491: ldc 134218248
    //   2493: iastore
    //   2494: dup
    //   2495: bipush #25
    //   2497: ldc 131584
    //   2499: iastore
    //   2500: dup
    //   2501: bipush #26
    //   2503: ldc 131072
    //   2505: iastore
    //   2506: dup
    //   2507: bipush #27
    //   2509: ldc 134218248
    //   2511: iastore
    //   2512: dup
    //   2513: bipush #28
    //   2515: bipush #8
    //   2517: iastore
    //   2518: dup
    //   2519: bipush #29
    //   2521: ldc 134349320
    //   2523: iastore
    //   2524: dup
    //   2525: bipush #30
    //   2527: sipush #512
    //   2530: iastore
    //   2531: dup
    //   2532: bipush #31
    //   2534: ldc 134217728
    //   2536: iastore
    //   2537: dup
    //   2538: bipush #32
    //   2540: ldc 134349312
    //   2542: iastore
    //   2543: dup
    //   2544: bipush #33
    //   2546: ldc 134217728
    //   2548: iastore
    //   2549: dup
    //   2550: bipush #34
    //   2552: ldc 131080
    //   2554: iastore
    //   2555: dup
    //   2556: bipush #35
    //   2558: sipush #520
    //   2561: iastore
    //   2562: dup
    //   2563: bipush #36
    //   2565: ldc 131072
    //   2567: iastore
    //   2568: dup
    //   2569: bipush #37
    //   2571: ldc 134349312
    //   2573: iastore
    //   2574: dup
    //   2575: bipush #38
    //   2577: ldc 134218240
    //   2579: iastore
    //   2580: dup
    //   2581: bipush #39
    //   2583: iconst_0
    //   2584: iastore
    //   2585: dup
    //   2586: bipush #40
    //   2588: sipush #512
    //   2591: iastore
    //   2592: dup
    //   2593: bipush #41
    //   2595: ldc 131080
    //   2597: iastore
    //   2598: dup
    //   2599: bipush #42
    //   2601: ldc 134349320
    //   2603: iastore
    //   2604: dup
    //   2605: bipush #43
    //   2607: ldc 134218240
    //   2609: iastore
    //   2610: dup
    //   2611: bipush #44
    //   2613: ldc 134217736
    //   2615: iastore
    //   2616: dup
    //   2617: bipush #45
    //   2619: sipush #512
    //   2622: iastore
    //   2623: dup
    //   2624: bipush #46
    //   2626: iconst_0
    //   2627: iastore
    //   2628: dup
    //   2629: bipush #47
    //   2631: ldc 134348808
    //   2633: iastore
    //   2634: dup
    //   2635: bipush #48
    //   2637: ldc 134218248
    //   2639: iastore
    //   2640: dup
    //   2641: bipush #49
    //   2643: ldc 131072
    //   2645: iastore
    //   2646: dup
    //   2647: bipush #50
    //   2649: ldc 134217728
    //   2651: iastore
    //   2652: dup
    //   2653: bipush #51
    //   2655: ldc 134349320
    //   2657: iastore
    //   2658: dup
    //   2659: bipush #52
    //   2661: bipush #8
    //   2663: iastore
    //   2664: dup
    //   2665: bipush #53
    //   2667: ldc 131592
    //   2669: iastore
    //   2670: dup
    //   2671: bipush #54
    //   2673: ldc 131584
    //   2675: iastore
    //   2676: dup
    //   2677: bipush #55
    //   2679: ldc 134217736
    //   2681: iastore
    //   2682: dup
    //   2683: bipush #56
    //   2685: ldc 134348800
    //   2687: iastore
    //   2688: dup
    //   2689: bipush #57
    //   2691: ldc 134218248
    //   2693: iastore
    //   2694: dup
    //   2695: bipush #58
    //   2697: sipush #520
    //   2700: iastore
    //   2701: dup
    //   2702: bipush #59
    //   2704: ldc 134348800
    //   2706: iastore
    //   2707: dup
    //   2708: bipush #60
    //   2710: ldc 131592
    //   2712: iastore
    //   2713: dup
    //   2714: bipush #61
    //   2716: bipush #8
    //   2718: iastore
    //   2719: dup
    //   2720: bipush #62
    //   2722: ldc 134348808
    //   2724: iastore
    //   2725: dup
    //   2726: bipush #63
    //   2728: ldc 131584
    //   2730: iastore
    //   2731: astore #9
    //   2733: bipush #64
    //   2735: newarray int
    //   2737: dup
    //   2738: iconst_0
    //   2739: ldc 8396801
    //   2741: iastore
    //   2742: dup
    //   2743: iconst_1
    //   2744: sipush #8321
    //   2747: iastore
    //   2748: dup
    //   2749: iconst_2
    //   2750: sipush #8321
    //   2753: iastore
    //   2754: dup
    //   2755: iconst_3
    //   2756: sipush #128
    //   2759: iastore
    //   2760: dup
    //   2761: iconst_4
    //   2762: ldc 8396928
    //   2764: iastore
    //   2765: dup
    //   2766: iconst_5
    //   2767: ldc 8388737
    //   2769: iastore
    //   2770: dup
    //   2771: bipush #6
    //   2773: ldc 8388609
    //   2775: iastore
    //   2776: dup
    //   2777: bipush #7
    //   2779: sipush #8193
    //   2782: iastore
    //   2783: dup
    //   2784: bipush #8
    //   2786: iconst_0
    //   2787: iastore
    //   2788: dup
    //   2789: bipush #9
    //   2791: ldc 8396800
    //   2793: iastore
    //   2794: dup
    //   2795: bipush #10
    //   2797: ldc 8396800
    //   2799: iastore
    //   2800: dup
    //   2801: bipush #11
    //   2803: ldc 8396929
    //   2805: iastore
    //   2806: dup
    //   2807: bipush #12
    //   2809: sipush #129
    //   2812: iastore
    //   2813: dup
    //   2814: bipush #13
    //   2816: iconst_0
    //   2817: iastore
    //   2818: dup
    //   2819: bipush #14
    //   2821: ldc 8388736
    //   2823: iastore
    //   2824: dup
    //   2825: bipush #15
    //   2827: ldc 8388609
    //   2829: iastore
    //   2830: dup
    //   2831: bipush #16
    //   2833: iconst_1
    //   2834: iastore
    //   2835: dup
    //   2836: bipush #17
    //   2838: sipush #8192
    //   2841: iastore
    //   2842: dup
    //   2843: bipush #18
    //   2845: ldc 8388608
    //   2847: iastore
    //   2848: dup
    //   2849: bipush #19
    //   2851: ldc 8396801
    //   2853: iastore
    //   2854: dup
    //   2855: bipush #20
    //   2857: sipush #128
    //   2860: iastore
    //   2861: dup
    //   2862: bipush #21
    //   2864: ldc 8388608
    //   2866: iastore
    //   2867: dup
    //   2868: bipush #22
    //   2870: sipush #8193
    //   2873: iastore
    //   2874: dup
    //   2875: bipush #23
    //   2877: sipush #8320
    //   2880: iastore
    //   2881: dup
    //   2882: bipush #24
    //   2884: ldc 8388737
    //   2886: iastore
    //   2887: dup
    //   2888: bipush #25
    //   2890: iconst_1
    //   2891: iastore
    //   2892: dup
    //   2893: bipush #26
    //   2895: sipush #8320
    //   2898: iastore
    //   2899: dup
    //   2900: bipush #27
    //   2902: ldc 8388736
    //   2904: iastore
    //   2905: dup
    //   2906: bipush #28
    //   2908: sipush #8192
    //   2911: iastore
    //   2912: dup
    //   2913: bipush #29
    //   2915: ldc 8396928
    //   2917: iastore
    //   2918: dup
    //   2919: bipush #30
    //   2921: ldc 8396929
    //   2923: iastore
    //   2924: dup
    //   2925: bipush #31
    //   2927: sipush #129
    //   2930: iastore
    //   2931: dup
    //   2932: bipush #32
    //   2934: ldc 8388736
    //   2936: iastore
    //   2937: dup
    //   2938: bipush #33
    //   2940: ldc 8388609
    //   2942: iastore
    //   2943: dup
    //   2944: bipush #34
    //   2946: ldc 8396800
    //   2948: iastore
    //   2949: dup
    //   2950: bipush #35
    //   2952: ldc 8396929
    //   2954: iastore
    //   2955: dup
    //   2956: bipush #36
    //   2958: sipush #129
    //   2961: iastore
    //   2962: dup
    //   2963: bipush #37
    //   2965: iconst_0
    //   2966: iastore
    //   2967: dup
    //   2968: bipush #38
    //   2970: iconst_0
    //   2971: iastore
    //   2972: dup
    //   2973: bipush #39
    //   2975: ldc 8396800
    //   2977: iastore
    //   2978: dup
    //   2979: bipush #40
    //   2981: sipush #8320
    //   2984: iastore
    //   2985: dup
    //   2986: bipush #41
    //   2988: ldc 8388736
    //   2990: iastore
    //   2991: dup
    //   2992: bipush #42
    //   2994: ldc 8388737
    //   2996: iastore
    //   2997: dup
    //   2998: bipush #43
    //   3000: iconst_1
    //   3001: iastore
    //   3002: dup
    //   3003: bipush #44
    //   3005: ldc 8396801
    //   3007: iastore
    //   3008: dup
    //   3009: bipush #45
    //   3011: sipush #8321
    //   3014: iastore
    //   3015: dup
    //   3016: bipush #46
    //   3018: sipush #8321
    //   3021: iastore
    //   3022: dup
    //   3023: bipush #47
    //   3025: sipush #128
    //   3028: iastore
    //   3029: dup
    //   3030: bipush #48
    //   3032: ldc 8396929
    //   3034: iastore
    //   3035: dup
    //   3036: bipush #49
    //   3038: sipush #129
    //   3041: iastore
    //   3042: dup
    //   3043: bipush #50
    //   3045: iconst_1
    //   3046: iastore
    //   3047: dup
    //   3048: bipush #51
    //   3050: sipush #8192
    //   3053: iastore
    //   3054: dup
    //   3055: bipush #52
    //   3057: ldc 8388609
    //   3059: iastore
    //   3060: dup
    //   3061: bipush #53
    //   3063: sipush #8193
    //   3066: iastore
    //   3067: dup
    //   3068: bipush #54
    //   3070: ldc 8396928
    //   3072: iastore
    //   3073: dup
    //   3074: bipush #55
    //   3076: ldc 8388737
    //   3078: iastore
    //   3079: dup
    //   3080: bipush #56
    //   3082: sipush #8193
    //   3085: iastore
    //   3086: dup
    //   3087: bipush #57
    //   3089: sipush #8320
    //   3092: iastore
    //   3093: dup
    //   3094: bipush #58
    //   3096: ldc 8388608
    //   3098: iastore
    //   3099: dup
    //   3100: bipush #59
    //   3102: ldc 8396801
    //   3104: iastore
    //   3105: dup
    //   3106: bipush #60
    //   3108: sipush #128
    //   3111: iastore
    //   3112: dup
    //   3113: bipush #61
    //   3115: ldc 8388608
    //   3117: iastore
    //   3118: dup
    //   3119: bipush #62
    //   3121: sipush #8192
    //   3124: iastore
    //   3125: dup
    //   3126: bipush #63
    //   3128: ldc 8396928
    //   3130: iastore
    //   3131: astore #10
    //   3133: bipush #64
    //   3135: newarray int
    //   3137: dup
    //   3138: iconst_0
    //   3139: sipush #256
    //   3142: iastore
    //   3143: dup
    //   3144: iconst_1
    //   3145: ldc 34078976
    //   3147: iastore
    //   3148: dup
    //   3149: iconst_2
    //   3150: ldc 34078720
    //   3152: iastore
    //   3153: dup
    //   3154: iconst_3
    //   3155: ldc 1107296512
    //   3157: iastore
    //   3158: dup
    //   3159: iconst_4
    //   3160: ldc 524288
    //   3162: iastore
    //   3163: dup
    //   3164: iconst_5
    //   3165: sipush #256
    //   3168: iastore
    //   3169: dup
    //   3170: bipush #6
    //   3172: ldc 1073741824
    //   3174: iastore
    //   3175: dup
    //   3176: bipush #7
    //   3178: ldc 34078720
    //   3180: iastore
    //   3181: dup
    //   3182: bipush #8
    //   3184: ldc 1074266368
    //   3186: iastore
    //   3187: dup
    //   3188: bipush #9
    //   3190: ldc 524288
    //   3192: iastore
    //   3193: dup
    //   3194: bipush #10
    //   3196: ldc 33554688
    //   3198: iastore
    //   3199: dup
    //   3200: bipush #11
    //   3202: ldc 1074266368
    //   3204: iastore
    //   3205: dup
    //   3206: bipush #12
    //   3208: ldc 1107296512
    //   3210: iastore
    //   3211: dup
    //   3212: bipush #13
    //   3214: ldc 1107820544
    //   3216: iastore
    //   3217: dup
    //   3218: bipush #14
    //   3220: ldc 524544
    //   3222: iastore
    //   3223: dup
    //   3224: bipush #15
    //   3226: ldc 1073741824
    //   3228: iastore
    //   3229: dup
    //   3230: bipush #16
    //   3232: ldc 33554432
    //   3234: iastore
    //   3235: dup
    //   3236: bipush #17
    //   3238: ldc 1074266112
    //   3240: iastore
    //   3241: dup
    //   3242: bipush #18
    //   3244: ldc 1074266112
    //   3246: iastore
    //   3247: dup
    //   3248: bipush #19
    //   3250: iconst_0
    //   3251: iastore
    //   3252: dup
    //   3253: bipush #20
    //   3255: ldc 1073742080
    //   3257: iastore
    //   3258: dup
    //   3259: bipush #21
    //   3261: ldc 1107820800
    //   3263: iastore
    //   3264: dup
    //   3265: bipush #22
    //   3267: ldc 1107820800
    //   3269: iastore
    //   3270: dup
    //   3271: bipush #23
    //   3273: ldc 33554688
    //   3275: iastore
    //   3276: dup
    //   3277: bipush #24
    //   3279: ldc 1107820544
    //   3281: iastore
    //   3282: dup
    //   3283: bipush #25
    //   3285: ldc 1073742080
    //   3287: iastore
    //   3288: dup
    //   3289: bipush #26
    //   3291: iconst_0
    //   3292: iastore
    //   3293: dup
    //   3294: bipush #27
    //   3296: ldc 1107296256
    //   3298: iastore
    //   3299: dup
    //   3300: bipush #28
    //   3302: ldc 34078976
    //   3304: iastore
    //   3305: dup
    //   3306: bipush #29
    //   3308: ldc 33554432
    //   3310: iastore
    //   3311: dup
    //   3312: bipush #30
    //   3314: ldc 1107296256
    //   3316: iastore
    //   3317: dup
    //   3318: bipush #31
    //   3320: ldc 524544
    //   3322: iastore
    //   3323: dup
    //   3324: bipush #32
    //   3326: ldc 524288
    //   3328: iastore
    //   3329: dup
    //   3330: bipush #33
    //   3332: ldc 1107296512
    //   3334: iastore
    //   3335: dup
    //   3336: bipush #34
    //   3338: sipush #256
    //   3341: iastore
    //   3342: dup
    //   3343: bipush #35
    //   3345: ldc 33554432
    //   3347: iastore
    //   3348: dup
    //   3349: bipush #36
    //   3351: ldc 1073741824
    //   3353: iastore
    //   3354: dup
    //   3355: bipush #37
    //   3357: ldc 34078720
    //   3359: iastore
    //   3360: dup
    //   3361: bipush #38
    //   3363: ldc 1107296512
    //   3365: iastore
    //   3366: dup
    //   3367: bipush #39
    //   3369: ldc 1074266368
    //   3371: iastore
    //   3372: dup
    //   3373: bipush #40
    //   3375: ldc 33554688
    //   3377: iastore
    //   3378: dup
    //   3379: bipush #41
    //   3381: ldc 1073741824
    //   3383: iastore
    //   3384: dup
    //   3385: bipush #42
    //   3387: ldc 1107820544
    //   3389: iastore
    //   3390: dup
    //   3391: bipush #43
    //   3393: ldc 34078976
    //   3395: iastore
    //   3396: dup
    //   3397: bipush #44
    //   3399: ldc 1074266368
    //   3401: iastore
    //   3402: dup
    //   3403: bipush #45
    //   3405: sipush #256
    //   3408: iastore
    //   3409: dup
    //   3410: bipush #46
    //   3412: ldc 33554432
    //   3414: iastore
    //   3415: dup
    //   3416: bipush #47
    //   3418: ldc 1107820544
    //   3420: iastore
    //   3421: dup
    //   3422: bipush #48
    //   3424: ldc 1107820800
    //   3426: iastore
    //   3427: dup
    //   3428: bipush #49
    //   3430: ldc 524544
    //   3432: iastore
    //   3433: dup
    //   3434: bipush #50
    //   3436: ldc 1107296256
    //   3438: iastore
    //   3439: dup
    //   3440: bipush #51
    //   3442: ldc 1107820800
    //   3444: iastore
    //   3445: dup
    //   3446: bipush #52
    //   3448: ldc 34078720
    //   3450: iastore
    //   3451: dup
    //   3452: bipush #53
    //   3454: iconst_0
    //   3455: iastore
    //   3456: dup
    //   3457: bipush #54
    //   3459: ldc 1074266112
    //   3461: iastore
    //   3462: dup
    //   3463: bipush #55
    //   3465: ldc 1107296256
    //   3467: iastore
    //   3468: dup
    //   3469: bipush #56
    //   3471: ldc 524544
    //   3473: iastore
    //   3474: dup
    //   3475: bipush #57
    //   3477: ldc 33554688
    //   3479: iastore
    //   3480: dup
    //   3481: bipush #58
    //   3483: ldc 1073742080
    //   3485: iastore
    //   3486: dup
    //   3487: bipush #59
    //   3489: ldc 524288
    //   3491: iastore
    //   3492: dup
    //   3493: bipush #60
    //   3495: iconst_0
    //   3496: iastore
    //   3497: dup
    //   3498: bipush #61
    //   3500: ldc 1074266112
    //   3502: iastore
    //   3503: dup
    //   3504: bipush #62
    //   3506: ldc 34078976
    //   3508: iastore
    //   3509: dup
    //   3510: bipush #63
    //   3512: ldc 1073742080
    //   3514: iastore
    //   3515: astore #11
    //   3517: bipush #64
    //   3519: newarray int
    //   3521: dup
    //   3522: iconst_0
    //   3523: ldc 536870928
    //   3525: iastore
    //   3526: dup
    //   3527: iconst_1
    //   3528: ldc 541065216
    //   3530: iastore
    //   3531: dup
    //   3532: iconst_2
    //   3533: sipush #16384
    //   3536: iastore
    //   3537: dup
    //   3538: iconst_3
    //   3539: ldc 541081616
    //   3541: iastore
    //   3542: dup
    //   3543: iconst_4
    //   3544: ldc 541065216
    //   3546: iastore
    //   3547: dup
    //   3548: iconst_5
    //   3549: bipush #16
    //   3551: iastore
    //   3552: dup
    //   3553: bipush #6
    //   3555: ldc 541081616
    //   3557: iastore
    //   3558: dup
    //   3559: bipush #7
    //   3561: ldc 4194304
    //   3563: iastore
    //   3564: dup
    //   3565: bipush #8
    //   3567: ldc 536887296
    //   3569: iastore
    //   3570: dup
    //   3571: bipush #9
    //   3573: ldc 4210704
    //   3575: iastore
    //   3576: dup
    //   3577: bipush #10
    //   3579: ldc 4194304
    //   3581: iastore
    //   3582: dup
    //   3583: bipush #11
    //   3585: ldc 536870928
    //   3587: iastore
    //   3588: dup
    //   3589: bipush #12
    //   3591: ldc 4194320
    //   3593: iastore
    //   3594: dup
    //   3595: bipush #13
    //   3597: ldc 536887296
    //   3599: iastore
    //   3600: dup
    //   3601: bipush #14
    //   3603: ldc 536870912
    //   3605: iastore
    //   3606: dup
    //   3607: bipush #15
    //   3609: sipush #16400
    //   3612: iastore
    //   3613: dup
    //   3614: bipush #16
    //   3616: iconst_0
    //   3617: iastore
    //   3618: dup
    //   3619: bipush #17
    //   3621: ldc 4194320
    //   3623: iastore
    //   3624: dup
    //   3625: bipush #18
    //   3627: ldc 536887312
    //   3629: iastore
    //   3630: dup
    //   3631: bipush #19
    //   3633: sipush #16384
    //   3636: iastore
    //   3637: dup
    //   3638: bipush #20
    //   3640: ldc 4210688
    //   3642: iastore
    //   3643: dup
    //   3644: bipush #21
    //   3646: ldc 536887312
    //   3648: iastore
    //   3649: dup
    //   3650: bipush #22
    //   3652: bipush #16
    //   3654: iastore
    //   3655: dup
    //   3656: bipush #23
    //   3658: ldc 541065232
    //   3660: iastore
    //   3661: dup
    //   3662: bipush #24
    //   3664: ldc 541065232
    //   3666: iastore
    //   3667: dup
    //   3668: bipush #25
    //   3670: iconst_0
    //   3671: iastore
    //   3672: dup
    //   3673: bipush #26
    //   3675: ldc 4210704
    //   3677: iastore
    //   3678: dup
    //   3679: bipush #27
    //   3681: ldc 541081600
    //   3683: iastore
    //   3684: dup
    //   3685: bipush #28
    //   3687: sipush #16400
    //   3690: iastore
    //   3691: dup
    //   3692: bipush #29
    //   3694: ldc 4210688
    //   3696: iastore
    //   3697: dup
    //   3698: bipush #30
    //   3700: ldc 541081600
    //   3702: iastore
    //   3703: dup
    //   3704: bipush #31
    //   3706: ldc 536870912
    //   3708: iastore
    //   3709: dup
    //   3710: bipush #32
    //   3712: ldc 536887296
    //   3714: iastore
    //   3715: dup
    //   3716: bipush #33
    //   3718: bipush #16
    //   3720: iastore
    //   3721: dup
    //   3722: bipush #34
    //   3724: ldc 541065232
    //   3726: iastore
    //   3727: dup
    //   3728: bipush #35
    //   3730: ldc 4210688
    //   3732: iastore
    //   3733: dup
    //   3734: bipush #36
    //   3736: ldc 541081616
    //   3738: iastore
    //   3739: dup
    //   3740: bipush #37
    //   3742: ldc 4194304
    //   3744: iastore
    //   3745: dup
    //   3746: bipush #38
    //   3748: sipush #16400
    //   3751: iastore
    //   3752: dup
    //   3753: bipush #39
    //   3755: ldc 536870928
    //   3757: iastore
    //   3758: dup
    //   3759: bipush #40
    //   3761: ldc 4194304
    //   3763: iastore
    //   3764: dup
    //   3765: bipush #41
    //   3767: ldc 536887296
    //   3769: iastore
    //   3770: dup
    //   3771: bipush #42
    //   3773: ldc 536870912
    //   3775: iastore
    //   3776: dup
    //   3777: bipush #43
    //   3779: sipush #16400
    //   3782: iastore
    //   3783: dup
    //   3784: bipush #44
    //   3786: ldc 536870928
    //   3788: iastore
    //   3789: dup
    //   3790: bipush #45
    //   3792: ldc 541081616
    //   3794: iastore
    //   3795: dup
    //   3796: bipush #46
    //   3798: ldc 4210688
    //   3800: iastore
    //   3801: dup
    //   3802: bipush #47
    //   3804: ldc 541065216
    //   3806: iastore
    //   3807: dup
    //   3808: bipush #48
    //   3810: ldc 4210704
    //   3812: iastore
    //   3813: dup
    //   3814: bipush #49
    //   3816: ldc 541081600
    //   3818: iastore
    //   3819: dup
    //   3820: bipush #50
    //   3822: iconst_0
    //   3823: iastore
    //   3824: dup
    //   3825: bipush #51
    //   3827: ldc 541065232
    //   3829: iastore
    //   3830: dup
    //   3831: bipush #52
    //   3833: bipush #16
    //   3835: iastore
    //   3836: dup
    //   3837: bipush #53
    //   3839: sipush #16384
    //   3842: iastore
    //   3843: dup
    //   3844: bipush #54
    //   3846: ldc 541065216
    //   3848: iastore
    //   3849: dup
    //   3850: bipush #55
    //   3852: ldc 4210704
    //   3854: iastore
    //   3855: dup
    //   3856: bipush #56
    //   3858: sipush #16384
    //   3861: iastore
    //   3862: dup
    //   3863: bipush #57
    //   3865: ldc 4194320
    //   3867: iastore
    //   3868: dup
    //   3869: bipush #58
    //   3871: ldc 536887312
    //   3873: iastore
    //   3874: dup
    //   3875: bipush #59
    //   3877: iconst_0
    //   3878: iastore
    //   3879: dup
    //   3880: bipush #60
    //   3882: ldc 541081600
    //   3884: iastore
    //   3885: dup
    //   3886: bipush #61
    //   3888: ldc 536870912
    //   3890: iastore
    //   3891: dup
    //   3892: bipush #62
    //   3894: ldc 4194320
    //   3896: iastore
    //   3897: dup
    //   3898: bipush #63
    //   3900: ldc 536887312
    //   3902: iastore
    //   3903: astore #12
    //   3905: bipush #64
    //   3907: newarray int
    //   3909: dup
    //   3910: iconst_0
    //   3911: ldc 2097152
    //   3913: iastore
    //   3914: dup
    //   3915: iconst_1
    //   3916: ldc 69206018
    //   3918: iastore
    //   3919: dup
    //   3920: iconst_2
    //   3921: ldc 67110914
    //   3923: iastore
    //   3924: dup
    //   3925: iconst_3
    //   3926: iconst_0
    //   3927: iastore
    //   3928: dup
    //   3929: iconst_4
    //   3930: sipush #2048
    //   3933: iastore
    //   3934: dup
    //   3935: iconst_5
    //   3936: ldc 67110914
    //   3938: iastore
    //   3939: dup
    //   3940: bipush #6
    //   3942: ldc 2099202
    //   3944: iastore
    //   3945: dup
    //   3946: bipush #7
    //   3948: ldc 69208064
    //   3950: iastore
    //   3951: dup
    //   3952: bipush #8
    //   3954: ldc 69208066
    //   3956: iastore
    //   3957: dup
    //   3958: bipush #9
    //   3960: ldc 2097152
    //   3962: iastore
    //   3963: dup
    //   3964: bipush #10
    //   3966: iconst_0
    //   3967: iastore
    //   3968: dup
    //   3969: bipush #11
    //   3971: ldc 67108866
    //   3973: iastore
    //   3974: dup
    //   3975: bipush #12
    //   3977: iconst_2
    //   3978: iastore
    //   3979: dup
    //   3980: bipush #13
    //   3982: ldc 67108864
    //   3984: iastore
    //   3985: dup
    //   3986: bipush #14
    //   3988: ldc 69206018
    //   3990: iastore
    //   3991: dup
    //   3992: bipush #15
    //   3994: sipush #2050
    //   3997: iastore
    //   3998: dup
    //   3999: bipush #16
    //   4001: ldc 67110912
    //   4003: iastore
    //   4004: dup
    //   4005: bipush #17
    //   4007: ldc 2099202
    //   4009: iastore
    //   4010: dup
    //   4011: bipush #18
    //   4013: ldc 2097154
    //   4015: iastore
    //   4016: dup
    //   4017: bipush #19
    //   4019: ldc 67110912
    //   4021: iastore
    //   4022: dup
    //   4023: bipush #20
    //   4025: ldc 67108866
    //   4027: iastore
    //   4028: dup
    //   4029: bipush #21
    //   4031: ldc 69206016
    //   4033: iastore
    //   4034: dup
    //   4035: bipush #22
    //   4037: ldc 69208064
    //   4039: iastore
    //   4040: dup
    //   4041: bipush #23
    //   4043: ldc 2097154
    //   4045: iastore
    //   4046: dup
    //   4047: bipush #24
    //   4049: ldc 69206016
    //   4051: iastore
    //   4052: dup
    //   4053: bipush #25
    //   4055: sipush #2048
    //   4058: iastore
    //   4059: dup
    //   4060: bipush #26
    //   4062: sipush #2050
    //   4065: iastore
    //   4066: dup
    //   4067: bipush #27
    //   4069: ldc 69208066
    //   4071: iastore
    //   4072: dup
    //   4073: bipush #28
    //   4075: ldc 2099200
    //   4077: iastore
    //   4078: dup
    //   4079: bipush #29
    //   4081: iconst_2
    //   4082: iastore
    //   4083: dup
    //   4084: bipush #30
    //   4086: ldc 67108864
    //   4088: iastore
    //   4089: dup
    //   4090: bipush #31
    //   4092: ldc 2099200
    //   4094: iastore
    //   4095: dup
    //   4096: bipush #32
    //   4098: ldc 67108864
    //   4100: iastore
    //   4101: dup
    //   4102: bipush #33
    //   4104: ldc 2099200
    //   4106: iastore
    //   4107: dup
    //   4108: bipush #34
    //   4110: ldc 2097152
    //   4112: iastore
    //   4113: dup
    //   4114: bipush #35
    //   4116: ldc 67110914
    //   4118: iastore
    //   4119: dup
    //   4120: bipush #36
    //   4122: ldc 67110914
    //   4124: iastore
    //   4125: dup
    //   4126: bipush #37
    //   4128: ldc 69206018
    //   4130: iastore
    //   4131: dup
    //   4132: bipush #38
    //   4134: ldc 69206018
    //   4136: iastore
    //   4137: dup
    //   4138: bipush #39
    //   4140: iconst_2
    //   4141: iastore
    //   4142: dup
    //   4143: bipush #40
    //   4145: ldc 2097154
    //   4147: iastore
    //   4148: dup
    //   4149: bipush #41
    //   4151: ldc 67108864
    //   4153: iastore
    //   4154: dup
    //   4155: bipush #42
    //   4157: ldc 67110912
    //   4159: iastore
    //   4160: dup
    //   4161: bipush #43
    //   4163: ldc 2097152
    //   4165: iastore
    //   4166: dup
    //   4167: bipush #44
    //   4169: ldc 69208064
    //   4171: iastore
    //   4172: dup
    //   4173: bipush #45
    //   4175: sipush #2050
    //   4178: iastore
    //   4179: dup
    //   4180: bipush #46
    //   4182: ldc 2099202
    //   4184: iastore
    //   4185: dup
    //   4186: bipush #47
    //   4188: ldc 69208064
    //   4190: iastore
    //   4191: dup
    //   4192: bipush #48
    //   4194: sipush #2050
    //   4197: iastore
    //   4198: dup
    //   4199: bipush #49
    //   4201: ldc 67108866
    //   4203: iastore
    //   4204: dup
    //   4205: bipush #50
    //   4207: ldc 69208066
    //   4209: iastore
    //   4210: dup
    //   4211: bipush #51
    //   4213: ldc 69206016
    //   4215: iastore
    //   4216: dup
    //   4217: bipush #52
    //   4219: ldc 2099200
    //   4221: iastore
    //   4222: dup
    //   4223: bipush #53
    //   4225: iconst_0
    //   4226: iastore
    //   4227: dup
    //   4228: bipush #54
    //   4230: iconst_2
    //   4231: iastore
    //   4232: dup
    //   4233: bipush #55
    //   4235: ldc 69208066
    //   4237: iastore
    //   4238: dup
    //   4239: bipush #56
    //   4241: iconst_0
    //   4242: iastore
    //   4243: dup
    //   4244: bipush #57
    //   4246: ldc 2099202
    //   4248: iastore
    //   4249: dup
    //   4250: bipush #58
    //   4252: ldc 69206016
    //   4254: iastore
    //   4255: dup
    //   4256: bipush #59
    //   4258: sipush #2048
    //   4261: iastore
    //   4262: dup
    //   4263: bipush #60
    //   4265: ldc 67108866
    //   4267: iastore
    //   4268: dup
    //   4269: bipush #61
    //   4271: ldc 67110912
    //   4273: iastore
    //   4274: dup
    //   4275: bipush #62
    //   4277: sipush #2048
    //   4280: iastore
    //   4281: dup
    //   4282: bipush #63
    //   4284: ldc 2097154
    //   4286: iastore
    //   4287: astore #13
    //   4289: bipush #64
    //   4291: newarray int
    //   4293: dup
    //   4294: iconst_0
    //   4295: ldc 268439616
    //   4297: iastore
    //   4298: dup
    //   4299: iconst_1
    //   4300: sipush #4096
    //   4303: iastore
    //   4304: dup
    //   4305: iconst_2
    //   4306: ldc 262144
    //   4308: iastore
    //   4309: dup
    //   4310: iconst_3
    //   4311: ldc 268701760
    //   4313: iastore
    //   4314: dup
    //   4315: iconst_4
    //   4316: ldc 268435456
    //   4318: iastore
    //   4319: dup
    //   4320: iconst_5
    //   4321: ldc 268439616
    //   4323: iastore
    //   4324: dup
    //   4325: bipush #6
    //   4327: bipush #64
    //   4329: iastore
    //   4330: dup
    //   4331: bipush #7
    //   4333: ldc 268435456
    //   4335: iastore
    //   4336: dup
    //   4337: bipush #8
    //   4339: ldc 262208
    //   4341: iastore
    //   4342: dup
    //   4343: bipush #9
    //   4345: ldc 268697600
    //   4347: iastore
    //   4348: dup
    //   4349: bipush #10
    //   4351: ldc 268701760
    //   4353: iastore
    //   4354: dup
    //   4355: bipush #11
    //   4357: ldc 266240
    //   4359: iastore
    //   4360: dup
    //   4361: bipush #12
    //   4363: ldc 268701696
    //   4365: iastore
    //   4366: dup
    //   4367: bipush #13
    //   4369: ldc 266304
    //   4371: iastore
    //   4372: dup
    //   4373: bipush #14
    //   4375: sipush #4096
    //   4378: iastore
    //   4379: dup
    //   4380: bipush #15
    //   4382: bipush #64
    //   4384: iastore
    //   4385: dup
    //   4386: bipush #16
    //   4388: ldc 268697600
    //   4390: iastore
    //   4391: dup
    //   4392: bipush #17
    //   4394: ldc 268435520
    //   4396: iastore
    //   4397: dup
    //   4398: bipush #18
    //   4400: ldc 268439552
    //   4402: iastore
    //   4403: dup
    //   4404: bipush #19
    //   4406: sipush #4160
    //   4409: iastore
    //   4410: dup
    //   4411: bipush #20
    //   4413: ldc 266240
    //   4415: iastore
    //   4416: dup
    //   4417: bipush #21
    //   4419: ldc 262208
    //   4421: iastore
    //   4422: dup
    //   4423: bipush #22
    //   4425: ldc 268697664
    //   4427: iastore
    //   4428: dup
    //   4429: bipush #23
    //   4431: ldc 268701696
    //   4433: iastore
    //   4434: dup
    //   4435: bipush #24
    //   4437: sipush #4160
    //   4440: iastore
    //   4441: dup
    //   4442: bipush #25
    //   4444: iconst_0
    //   4445: iastore
    //   4446: dup
    //   4447: bipush #26
    //   4449: iconst_0
    //   4450: iastore
    //   4451: dup
    //   4452: bipush #27
    //   4454: ldc 268697664
    //   4456: iastore
    //   4457: dup
    //   4458: bipush #28
    //   4460: ldc 268435520
    //   4462: iastore
    //   4463: dup
    //   4464: bipush #29
    //   4466: ldc 268439552
    //   4468: iastore
    //   4469: dup
    //   4470: bipush #30
    //   4472: ldc 266304
    //   4474: iastore
    //   4475: dup
    //   4476: bipush #31
    //   4478: ldc 262144
    //   4480: iastore
    //   4481: dup
    //   4482: bipush #32
    //   4484: ldc 266304
    //   4486: iastore
    //   4487: dup
    //   4488: bipush #33
    //   4490: ldc 262144
    //   4492: iastore
    //   4493: dup
    //   4494: bipush #34
    //   4496: ldc 268701696
    //   4498: iastore
    //   4499: dup
    //   4500: bipush #35
    //   4502: sipush #4096
    //   4505: iastore
    //   4506: dup
    //   4507: bipush #36
    //   4509: bipush #64
    //   4511: iastore
    //   4512: dup
    //   4513: bipush #37
    //   4515: ldc 268697664
    //   4517: iastore
    //   4518: dup
    //   4519: bipush #38
    //   4521: sipush #4096
    //   4524: iastore
    //   4525: dup
    //   4526: bipush #39
    //   4528: ldc 266304
    //   4530: iastore
    //   4531: dup
    //   4532: bipush #40
    //   4534: ldc 268439552
    //   4536: iastore
    //   4537: dup
    //   4538: bipush #41
    //   4540: bipush #64
    //   4542: iastore
    //   4543: dup
    //   4544: bipush #42
    //   4546: ldc 268435520
    //   4548: iastore
    //   4549: dup
    //   4550: bipush #43
    //   4552: ldc 268697600
    //   4554: iastore
    //   4555: dup
    //   4556: bipush #44
    //   4558: ldc 268697664
    //   4560: iastore
    //   4561: dup
    //   4562: bipush #45
    //   4564: ldc 268435456
    //   4566: iastore
    //   4567: dup
    //   4568: bipush #46
    //   4570: ldc 262144
    //   4572: iastore
    //   4573: dup
    //   4574: bipush #47
    //   4576: ldc 268439616
    //   4578: iastore
    //   4579: dup
    //   4580: bipush #48
    //   4582: iconst_0
    //   4583: iastore
    //   4584: dup
    //   4585: bipush #49
    //   4587: ldc 268701760
    //   4589: iastore
    //   4590: dup
    //   4591: bipush #50
    //   4593: ldc 262208
    //   4595: iastore
    //   4596: dup
    //   4597: bipush #51
    //   4599: ldc 268435520
    //   4601: iastore
    //   4602: dup
    //   4603: bipush #52
    //   4605: ldc 268697600
    //   4607: iastore
    //   4608: dup
    //   4609: bipush #53
    //   4611: ldc 268439552
    //   4613: iastore
    //   4614: dup
    //   4615: bipush #54
    //   4617: ldc 268439616
    //   4619: iastore
    //   4620: dup
    //   4621: bipush #55
    //   4623: iconst_0
    //   4624: iastore
    //   4625: dup
    //   4626: bipush #56
    //   4628: ldc 268701760
    //   4630: iastore
    //   4631: dup
    //   4632: bipush #57
    //   4634: ldc 266240
    //   4636: iastore
    //   4637: dup
    //   4638: bipush #58
    //   4640: ldc 266240
    //   4642: iastore
    //   4643: dup
    //   4644: bipush #59
    //   4646: sipush #4160
    //   4649: iastore
    //   4650: dup
    //   4651: bipush #60
    //   4653: sipush #4160
    //   4656: iastore
    //   4657: dup
    //   4658: bipush #61
    //   4660: ldc 262208
    //   4662: iastore
    //   4663: dup
    //   4664: bipush #62
    //   4666: ldc 268435456
    //   4668: iastore
    //   4669: dup
    //   4670: bipush #63
    //   4672: ldc 268701696
    //   4674: iastore
    //   4675: astore #14
    //   4677: aload #4
    //   4679: arraylength
    //   4680: istore #15
    //   4682: iload #15
    //   4684: bipush #8
    //   4686: irem
    //   4687: ifeq -> 4711
    //   4690: new java/lang/Exception
    //   4693: dup
    //   4694: sipush #-15827
    //   4697: sipush #30094
    //   4700: invokestatic a : (II)Ljava/lang/String;
    //   4703: invokespecial <init> : (Ljava/lang/String;)V
    //   4706: athrow
    //   4707: invokestatic a : (Ljava/lang/Throwable;)Ljava/lang/Throwable;
    //   4710: athrow
    //   4711: iconst_2
    //   4712: newarray int
    //   4714: astore #16
    //   4716: iload #15
    //   4718: newarray byte
    //   4720: astore #17
    //   4722: iload #15
    //   4724: bipush #8
    //   4726: idiv
    //   4727: istore #18
    //   4729: iconst_0
    //   4730: istore #19
    //   4732: iload #19
    //   4734: iload #18
    //   4736: if_icmpge -> 5654
    //   4739: iload #19
    //   4741: bipush #8
    //   4743: imul
    //   4744: istore #20
    //   4746: iconst_0
    //   4747: istore #21
    //   4749: iload #21
    //   4751: iconst_2
    //   4752: if_icmpge -> 4841
    //   4755: aload #16
    //   4757: iload #21
    //   4759: aload #4
    //   4761: iload #20
    //   4763: iload #21
    //   4765: iconst_4
    //   4766: imul
    //   4767: iadd
    //   4768: baload
    //   4769: sipush #255
    //   4772: iand
    //   4773: bipush #24
    //   4775: ishl
    //   4776: aload #4
    //   4778: iload #20
    //   4780: iload #21
    //   4782: iconst_4
    //   4783: imul
    //   4784: iadd
    //   4785: iconst_1
    //   4786: iadd
    //   4787: baload
    //   4788: sipush #255
    //   4791: iand
    //   4792: bipush #16
    //   4794: ishl
    //   4795: ior
    //   4796: aload #4
    //   4798: iload #20
    //   4800: iload #21
    //   4802: iconst_4
    //   4803: imul
    //   4804: iadd
    //   4805: iconst_2
    //   4806: iadd
    //   4807: baload
    //   4808: sipush #255
    //   4811: iand
    //   4812: bipush #8
    //   4814: ishl
    //   4815: ior
    //   4816: aload #4
    //   4818: iload #20
    //   4820: iload #21
    //   4822: iconst_4
    //   4823: imul
    //   4824: iadd
    //   4825: iconst_3
    //   4826: iadd
    //   4827: baload
    //   4828: sipush #255
    //   4831: iand
    //   4832: ior
    //   4833: iastore
    //   4834: iinc #21, 1
    //   4837: iload_2
    //   4838: ifeq -> 4749
    //   4841: iconst_0
    //   4842: istore #26
    //   4844: aload #16
    //   4846: iconst_0
    //   4847: iaload
    //   4848: istore #24
    //   4850: aload #16
    //   4852: iconst_1
    //   4853: iaload
    //   4854: istore #23
    //   4856: iload #24
    //   4858: iconst_4
    //   4859: iushr
    //   4860: iload #23
    //   4862: ixor
    //   4863: ldc 252645135
    //   4865: iand
    //   4866: istore #22
    //   4868: iload #23
    //   4870: iload #22
    //   4872: ixor
    //   4873: istore #23
    //   4875: iload #24
    //   4877: iload #22
    //   4879: iconst_4
    //   4880: ishl
    //   4881: ixor
    //   4882: istore #24
    //   4884: iload #24
    //   4886: bipush #16
    //   4888: iushr
    //   4889: iload #23
    //   4891: ixor
    //   4892: ldc 65535
    //   4894: iand
    //   4895: istore #22
    //   4897: iload #23
    //   4899: iload #22
    //   4901: ixor
    //   4902: istore #23
    //   4904: iload #24
    //   4906: iload #22
    //   4908: bipush #16
    //   4910: ishl
    //   4911: ixor
    //   4912: istore #24
    //   4914: iload #23
    //   4916: iconst_2
    //   4917: iushr
    //   4918: iload #24
    //   4920: ixor
    //   4921: ldc 858993459
    //   4923: iand
    //   4924: istore #22
    //   4926: iload #24
    //   4928: iload #22
    //   4930: ixor
    //   4931: istore #24
    //   4933: iload #23
    //   4935: iload #22
    //   4937: iconst_2
    //   4938: ishl
    //   4939: ixor
    //   4940: istore #23
    //   4942: iload #23
    //   4944: bipush #8
    //   4946: iushr
    //   4947: iload #24
    //   4949: ixor
    //   4950: ldc 16711935
    //   4952: iand
    //   4953: istore #22
    //   4955: iload #24
    //   4957: iload #22
    //   4959: ixor
    //   4960: istore #24
    //   4962: iload #23
    //   4964: iload #22
    //   4966: bipush #8
    //   4968: ishl
    //   4969: ixor
    //   4970: istore #23
    //   4972: iload #23
    //   4974: iconst_1
    //   4975: ishl
    //   4976: iload #23
    //   4978: bipush #31
    //   4980: iushr
    //   4981: iconst_1
    //   4982: iand
    //   4983: ior
    //   4984: istore #23
    //   4986: iload #24
    //   4988: iload #23
    //   4990: ixor
    //   4991: ldc -1431655766
    //   4993: iand
    //   4994: istore #22
    //   4996: iload #24
    //   4998: iload #22
    //   5000: ixor
    //   5001: istore #24
    //   5003: iload #23
    //   5005: iload #22
    //   5007: ixor
    //   5008: istore #23
    //   5010: iload #24
    //   5012: iconst_1
    //   5013: ishl
    //   5014: iload #24
    //   5016: bipush #31
    //   5018: iushr
    //   5019: iconst_1
    //   5020: iand
    //   5021: ior
    //   5022: istore #24
    //   5024: iconst_0
    //   5025: istore #25
    //   5027: iload #25
    //   5029: bipush #8
    //   5031: if_icmpge -> 5369
    //   5034: iload #23
    //   5036: bipush #28
    //   5038: ishl
    //   5039: iload #23
    //   5041: iconst_4
    //   5042: iushr
    //   5043: ior
    //   5044: istore #22
    //   5046: iload #22
    //   5048: aload #6
    //   5050: iload #26
    //   5052: iinc #26, 1
    //   5055: iaload
    //   5056: ixor
    //   5057: istore #22
    //   5059: aload #13
    //   5061: iload #22
    //   5063: bipush #63
    //   5065: iand
    //   5066: iaload
    //   5067: istore #21
    //   5069: iload #21
    //   5071: aload #11
    //   5073: iload #22
    //   5075: bipush #8
    //   5077: iushr
    //   5078: bipush #63
    //   5080: iand
    //   5081: iaload
    //   5082: ior
    //   5083: istore #21
    //   5085: iload #21
    //   5087: aload #9
    //   5089: iload #22
    //   5091: bipush #16
    //   5093: iushr
    //   5094: bipush #63
    //   5096: iand
    //   5097: iaload
    //   5098: ior
    //   5099: istore #21
    //   5101: iload #21
    //   5103: aload #7
    //   5105: iload #22
    //   5107: bipush #24
    //   5109: iushr
    //   5110: bipush #63
    //   5112: iand
    //   5113: iaload
    //   5114: ior
    //   5115: istore #21
    //   5117: iload #23
    //   5119: aload #6
    //   5121: iload #26
    //   5123: iinc #26, 1
    //   5126: iaload
    //   5127: ixor
    //   5128: istore #22
    //   5130: iload #21
    //   5132: aload #14
    //   5134: iload #22
    //   5136: bipush #63
    //   5138: iand
    //   5139: iaload
    //   5140: ior
    //   5141: istore #21
    //   5143: iload #21
    //   5145: aload #12
    //   5147: iload #22
    //   5149: bipush #8
    //   5151: iushr
    //   5152: bipush #63
    //   5154: iand
    //   5155: iaload
    //   5156: ior
    //   5157: istore #21
    //   5159: iload #21
    //   5161: aload #10
    //   5163: iload #22
    //   5165: bipush #16
    //   5167: iushr
    //   5168: bipush #63
    //   5170: iand
    //   5171: iaload
    //   5172: ior
    //   5173: istore #21
    //   5175: iload #21
    //   5177: aload #8
    //   5179: iload #22
    //   5181: bipush #24
    //   5183: iushr
    //   5184: bipush #63
    //   5186: iand
    //   5187: iaload
    //   5188: ior
    //   5189: istore #21
    //   5191: iload #24
    //   5193: iload #21
    //   5195: ixor
    //   5196: istore #24
    //   5198: iload #24
    //   5200: bipush #28
    //   5202: ishl
    //   5203: iload #24
    //   5205: iconst_4
    //   5206: iushr
    //   5207: ior
    //   5208: istore #22
    //   5210: iload #22
    //   5212: aload #6
    //   5214: iload #26
    //   5216: iinc #26, 1
    //   5219: iaload
    //   5220: ixor
    //   5221: istore #22
    //   5223: aload #13
    //   5225: iload #22
    //   5227: bipush #63
    //   5229: iand
    //   5230: iaload
    //   5231: istore #21
    //   5233: iload #21
    //   5235: aload #11
    //   5237: iload #22
    //   5239: bipush #8
    //   5241: iushr
    //   5242: bipush #63
    //   5244: iand
    //   5245: iaload
    //   5246: ior
    //   5247: istore #21
    //   5249: iload #21
    //   5251: aload #9
    //   5253: iload #22
    //   5255: bipush #16
    //   5257: iushr
    //   5258: bipush #63
    //   5260: iand
    //   5261: iaload
    //   5262: ior
    //   5263: istore #21
    //   5265: iload #21
    //   5267: aload #7
    //   5269: iload #22
    //   5271: bipush #24
    //   5273: iushr
    //   5274: bipush #63
    //   5276: iand
    //   5277: iaload
    //   5278: ior
    //   5279: istore #21
    //   5281: iload #24
    //   5283: aload #6
    //   5285: iload #26
    //   5287: iinc #26, 1
    //   5290: iaload
    //   5291: ixor
    //   5292: istore #22
    //   5294: iload #21
    //   5296: aload #14
    //   5298: iload #22
    //   5300: bipush #63
    //   5302: iand
    //   5303: iaload
    //   5304: ior
    //   5305: istore #21
    //   5307: iload #21
    //   5309: aload #12
    //   5311: iload #22
    //   5313: bipush #8
    //   5315: iushr
    //   5316: bipush #63
    //   5318: iand
    //   5319: iaload
    //   5320: ior
    //   5321: istore #21
    //   5323: iload #21
    //   5325: aload #10
    //   5327: iload #22
    //   5329: bipush #16
    //   5331: iushr
    //   5332: bipush #63
    //   5334: iand
    //   5335: iaload
    //   5336: ior
    //   5337: istore #21
    //   5339: iload #21
    //   5341: aload #8
    //   5343: iload #22
    //   5345: bipush #24
    //   5347: iushr
    //   5348: bipush #63
    //   5350: iand
    //   5351: iaload
    //   5352: ior
    //   5353: istore #21
    //   5355: iload #23
    //   5357: iload #21
    //   5359: ixor
    //   5360: istore #23
    //   5362: iinc #25, 1
    //   5365: iload_2
    //   5366: ifeq -> 5027
    //   5369: iload #23
    //   5371: bipush #31
    //   5373: ishl
    //   5374: iload #23
    //   5376: iconst_1
    //   5377: iushr
    //   5378: ior
    //   5379: istore #23
    //   5381: iload #24
    //   5383: iload #23
    //   5385: ixor
    //   5386: ldc -1431655766
    //   5388: iand
    //   5389: istore #22
    //   5391: iload #24
    //   5393: iload #22
    //   5395: ixor
    //   5396: istore #24
    //   5398: iload #23
    //   5400: iload #22
    //   5402: ixor
    //   5403: istore #23
    //   5405: iload #24
    //   5407: bipush #31
    //   5409: ishl
    //   5410: iload #24
    //   5412: iconst_1
    //   5413: iushr
    //   5414: ior
    //   5415: istore #24
    //   5417: iload #24
    //   5419: bipush #8
    //   5421: iushr
    //   5422: iload #23
    //   5424: ixor
    //   5425: ldc 16711935
    //   5427: iand
    //   5428: istore #22
    //   5430: iload #23
    //   5432: iload #22
    //   5434: ixor
    //   5435: istore #23
    //   5437: iload #24
    //   5439: iload #22
    //   5441: bipush #8
    //   5443: ishl
    //   5444: ixor
    //   5445: istore #24
    //   5447: iload #24
    //   5449: iconst_2
    //   5450: iushr
    //   5451: iload #23
    //   5453: ixor
    //   5454: ldc 858993459
    //   5456: iand
    //   5457: istore #22
    //   5459: iload #23
    //   5461: iload #22
    //   5463: ixor
    //   5464: istore #23
    //   5466: iload #24
    //   5468: iload #22
    //   5470: iconst_2
    //   5471: ishl
    //   5472: ixor
    //   5473: istore #24
    //   5475: iload #23
    //   5477: bipush #16
    //   5479: iushr
    //   5480: iload #24
    //   5482: ixor
    //   5483: ldc 65535
    //   5485: iand
    //   5486: istore #22
    //   5488: iload #24
    //   5490: iload #22
    //   5492: ixor
    //   5493: istore #24
    //   5495: iload #23
    //   5497: iload #22
    //   5499: bipush #16
    //   5501: ishl
    //   5502: ixor
    //   5503: istore #23
    //   5505: iload #23
    //   5507: iconst_4
    //   5508: iushr
    //   5509: iload #24
    //   5511: ixor
    //   5512: ldc 252645135
    //   5514: iand
    //   5515: istore #22
    //   5517: iload #24
    //   5519: iload #22
    //   5521: ixor
    //   5522: istore #24
    //   5524: iload #23
    //   5526: iload #22
    //   5528: iconst_4
    //   5529: ishl
    //   5530: ixor
    //   5531: istore #23
    //   5533: aload #16
    //   5535: iconst_0
    //   5536: iload #23
    //   5538: iastore
    //   5539: aload #16
    //   5541: iconst_1
    //   5542: iload #24
    //   5544: iastore
    //   5545: iload #19
    //   5547: bipush #8
    //   5549: imul
    //   5550: istore #27
    //   5552: iconst_0
    //   5553: istore #28
    //   5555: iload #28
    //   5557: iconst_2
    //   5558: if_icmpge -> 5647
    //   5561: aload #17
    //   5563: iload #27
    //   5565: iload #28
    //   5567: iconst_4
    //   5568: imul
    //   5569: iadd
    //   5570: aload #16
    //   5572: iload #28
    //   5574: iaload
    //   5575: bipush #24
    //   5577: iushr
    //   5578: i2b
    //   5579: bastore
    //   5580: aload #17
    //   5582: iload #27
    //   5584: iload #28
    //   5586: iconst_4
    //   5587: imul
    //   5588: iadd
    //   5589: iconst_1
    //   5590: iadd
    //   5591: aload #16
    //   5593: iload #28
    //   5595: iaload
    //   5596: bipush #16
    //   5598: iushr
    //   5599: i2b
    //   5600: bastore
    //   5601: aload #17
    //   5603: iload #27
    //   5605: iload #28
    //   5607: iconst_4
    //   5608: imul
    //   5609: iadd
    //   5610: iconst_2
    //   5611: iadd
    //   5612: aload #16
    //   5614: iload #28
    //   5616: iaload
    //   5617: bipush #8
    //   5619: iushr
    //   5620: i2b
    //   5621: bastore
    //   5622: aload #17
    //   5624: iload #27
    //   5626: iload #28
    //   5628: iconst_4
    //   5629: imul
    //   5630: iadd
    //   5631: iconst_3
    //   5632: iadd
    //   5633: aload #16
    //   5635: iload #28
    //   5637: iaload
    //   5638: i2b
    //   5639: bastore
    //   5640: iinc #28, 1
    //   5643: iload_2
    //   5644: ifeq -> 5555
    //   5647: iinc #19, 1
    //   5650: iload_2
    //   5651: ifeq -> 4732
    //   5654: aload #17
    //   5656: aload #17
    //   5658: arraylength
    //   5659: iconst_1
    //   5660: isub
    //   5661: baload
    //   5662: istore #19
    //   5664: aload #17
    //   5666: arraylength
    //   5667: iload #19
    //   5669: isub
    //   5670: newarray byte
    //   5672: astore #5
    //   5674: aload #17
    //   5676: arraylength
    //   5677: aload #5
    //   5679: arraylength
    //   5680: if_icmpge -> 5704
    //   5683: new java/lang/Exception
    //   5686: dup
    //   5687: sipush #-15823
    //   5690: sipush #-28386
    //   5693: invokestatic a : (II)Ljava/lang/String;
    //   5696: invokespecial <init> : (Ljava/lang/String;)V
    //   5699: athrow
    //   5700: invokestatic a : (Ljava/lang/Throwable;)Ljava/lang/Throwable;
    //   5703: athrow
    //   5704: iconst_0
    //   5705: istore #20
    //   5707: iload #20
    //   5709: aload #5
    //   5711: arraylength
    //   5712: if_icmpge -> 5732
    //   5715: aload #5
    //   5717: iload #20
    //   5719: aload #17
    //   5721: iload #20
    //   5723: baload
    //   5724: bastore
    //   5725: iinc #20, 1
    //   5728: iload_2
    //   5729: ifeq -> 5707
    //   5732: new java/math/BigInteger
    //   5735: dup
    //   5736: aload #5
    //   5738: invokespecial <init> : ([B)V
    //   5741: invokevirtual abs : ()Ljava/math/BigInteger;
    //   5744: putstatic burp/Ze9.Zu : Ljava/lang/Object;
    //   5747: sipush #-15829
    //   5750: sipush #25643
    //   5753: invokestatic a : (II)Ljava/lang/String;
    //   5756: iconst_1
    //   5757: ldc burp/Zssb
    //   5759: invokevirtual getClassLoader : ()Ljava/lang/ClassLoader;
    //   5762: invokestatic forName : (Ljava/lang/String;ZLjava/lang/ClassLoader;)Ljava/lang/Class;
    //   5765: invokevirtual getDeclaredFields : ()[Ljava/lang/reflect/Field;
    //   5768: astore #4
    //   5770: aload #4
    //   5772: arraylength
    //   5773: istore #5
    //   5775: iconst_0
    //   5776: istore #6
    //   5778: iload #6
    //   5780: iload #5
    //   5782: if_icmpge -> 5920
    //   5785: aload #4
    //   5787: iload #6
    //   5789: aaload
    //   5790: astore #7
    //   5792: aload #7
    //   5794: invokevirtual getModifiers : ()I
    //   5797: invokestatic isStatic : (I)Z
    //   5800: ifne -> 5810
    //   5803: goto -> 5913
    //   5806: invokestatic a : (Ljava/lang/Throwable;)Ljava/lang/Throwable;
    //   5809: athrow
    //   5810: aload #7
    //   5812: invokevirtual getType : ()Ljava/lang/Class;
    //   5815: astore #8
    //   5817: aload #8
    //   5819: ifnull -> 5900
    //   5822: aload #8
    //   5824: invokevirtual isPrimitive : ()Z
    //   5827: ifne -> 5900
    //   5830: goto -> 5837
    //   5833: invokestatic a : (Ljava/lang/Throwable;)Ljava/lang/Throwable;
    //   5836: athrow
    //   5837: aload #8
    //   5839: invokevirtual getPackage : ()Ljava/lang/Package;
    //   5842: ifnull -> 5900
    //   5845: goto -> 5852
    //   5848: invokestatic a : (Ljava/lang/Throwable;)Ljava/lang/Throwable;
    //   5851: athrow
    //   5852: aload #8
    //   5854: invokevirtual getPackage : ()Ljava/lang/Package;
    //   5857: invokevirtual getName : ()Ljava/lang/String;
    //   5860: ifnull -> 5900
    //   5863: goto -> 5870
    //   5866: invokestatic a : (Ljava/lang/Throwable;)Ljava/lang/Throwable;
    //   5869: athrow
    //   5870: aload #8
    //   5872: invokevirtual getPackage : ()Ljava/lang/Package;
    //   5875: invokevirtual getName : ()Ljava/lang/String;
    //   5878: sipush #-15810
    //   5881: sipush #17238
    //   5884: invokestatic a : (II)Ljava/lang/String;
    //   5887: invokevirtual startsWith : (Ljava/lang/String;)Z
    //   5890: ifne -> 5900
    //   5893: goto -> 5900
    //   5896: invokestatic a : (Ljava/lang/Throwable;)Ljava/lang/Throwable;
    //   5899: athrow
    //   5900: aload #7
    //   5902: iconst_1
    //   5903: invokevirtual setAccessible : (Z)V
    //   5906: aload #7
    //   5908: aconst_null
    //   5909: invokevirtual get : (Ljava/lang/Object;)Ljava/lang/Object;
    //   5912: pop
    //   5913: iinc #6, 1
    //   5916: iload_2
    //   5917: ifeq -> 5778
    //   5920: sipush #-15826
    //   5923: sipush #30748
    //   5926: invokestatic a : (II)Ljava/lang/String;
    //   5929: invokestatic forName : (Ljava/lang/String;)Ljava/lang/Class;
    //   5932: invokevirtual getDeclaredMethods : ()[Ljava/lang/reflect/Method;
    //   5935: astore #4
    //   5937: aload #4
    //   5939: arraylength
    //   5940: istore #5
    //   5942: iconst_0
    //   5943: istore #6
    //   5945: iload #6
    //   5947: iload #5
    //   5949: if_icmpge -> 6082
    //   5952: aload #4
    //   5954: iload #6
    //   5956: aaload
    //   5957: astore #7
    //   5959: aload #7
    //   5961: invokevirtual getParameterTypes : ()[Ljava/lang/Class;
    //   5964: pop
    //   5965: aload #7
    //   5967: invokevirtual getModifiers : ()I
    //   5970: invokestatic isStatic : (I)Z
    //   5973: ifeq -> 6068
    //   5976: aload #7
    //   5978: invokevirtual getParameterTypes : ()[Ljava/lang/Class;
    //   5981: arraylength
    //   5982: iconst_2
    //   5983: if_icmpne -> 6068
    //   5986: goto -> 5993
    //   5989: invokestatic a : (Ljava/lang/Throwable;)Ljava/lang/Throwable;
    //   5992: athrow
    //   5993: aload #7
    //   5995: invokevirtual getReturnType : ()Ljava/lang/Class;
    //   5998: getstatic java/lang/Void.TYPE : Ljava/lang/Class;
    //   6001: invokevirtual equals : (Ljava/lang/Object;)Z
    //   6004: ifeq -> 6068
    //   6007: goto -> 6014
    //   6010: invokestatic a : (Ljava/lang/Throwable;)Ljava/lang/Throwable;
    //   6013: athrow
    //   6014: aload #7
    //   6016: iconst_1
    //   6017: invokevirtual setAccessible : (Z)V
    //   6020: aload #7
    //   6022: aconst_null
    //   6023: iconst_2
    //   6024: anewarray java/lang/Object
    //   6027: dup
    //   6028: iconst_0
    //   6029: aload_0
    //   6030: aastore
    //   6031: dup
    //   6032: iconst_1
    //   6033: aload_1
    //   6034: ifnonnull -> 6052
    //   6037: goto -> 6044
    //   6040: invokestatic a : (Ljava/lang/Throwable;)Ljava/lang/Throwable;
    //   6043: athrow
    //   6044: aload_1
    //   6045: goto -> 6059
    //   6048: invokestatic a : (Ljava/lang/Throwable;)Ljava/lang/Throwable;
    //   6051: athrow
    //   6052: aload_1
    //   6053: checkcast [B
    //   6056: invokevirtual clone : ()Ljava/lang/Object;
    //   6059: aastore
    //   6060: invokevirtual invoke : (Ljava/lang/Object;[Ljava/lang/Object;)Ljava/lang/Object;
    //   6063: pop
    //   6064: iload_2
    //   6065: ifeq -> 6082
    //   6068: iinc #6, 1
    //   6071: iload_2
    //   6072: ifeq -> 5945
    //   6075: goto -> 6082
    //   6078: invokestatic a : (Ljava/lang/Throwable;)Ljava/lang/Throwable;
    //   6081: athrow
    //   6082: getstatic burp/Zrct.ZV : Ljava/lang/Object;
    //   6085: checkcast java/math/BigInteger
    //   6088: invokevirtual toByteArray : ()[B
    //   6091: astore #4
    //   6093: bipush #64
    //   6095: newarray byte
    //   6097: dup
    //   6098: iconst_0
    //   6099: bipush #-128
    //   6101: bastore
    //   6102: dup
    //   6103: iconst_1
    //   6104: iconst_0
    //   6105: bastore
    //   6106: dup
    //   6107: iconst_2
    //   6108: iconst_0
    //   6109: bastore
    //   6110: dup
    //   6111: iconst_3
    //   6112: iconst_0
    //   6113: bastore
    //   6114: dup
    //   6115: iconst_4
    //   6116: iconst_0
    //   6117: bastore
    //   6118: dup
    //   6119: iconst_5
    //   6120: iconst_0
    //   6121: bastore
    //   6122: dup
    //   6123: bipush #6
    //   6125: iconst_0
    //   6126: bastore
    //   6127: dup
    //   6128: bipush #7
    //   6130: iconst_0
    //   6131: bastore
    //   6132: dup
    //   6133: bipush #8
    //   6135: iconst_0
    //   6136: bastore
    //   6137: dup
    //   6138: bipush #9
    //   6140: iconst_0
    //   6141: bastore
    //   6142: dup
    //   6143: bipush #10
    //   6145: iconst_0
    //   6146: bastore
    //   6147: dup
    //   6148: bipush #11
    //   6150: iconst_0
    //   6151: bastore
    //   6152: dup
    //   6153: bipush #12
    //   6155: iconst_0
    //   6156: bastore
    //   6157: dup
    //   6158: bipush #13
    //   6160: iconst_0
    //   6161: bastore
    //   6162: dup
    //   6163: bipush #14
    //   6165: iconst_0
    //   6166: bastore
    //   6167: dup
    //   6168: bipush #15
    //   6170: iconst_0
    //   6171: bastore
    //   6172: dup
    //   6173: bipush #16
    //   6175: iconst_0
    //   6176: bastore
    //   6177: dup
    //   6178: bipush #17
    //   6180: iconst_0
    //   6181: bastore
    //   6182: dup
    //   6183: bipush #18
    //   6185: iconst_0
    //   6186: bastore
    //   6187: dup
    //   6188: bipush #19
    //   6190: iconst_0
    //   6191: bastore
    //   6192: dup
    //   6193: bipush #20
    //   6195: iconst_0
    //   6196: bastore
    //   6197: dup
    //   6198: bipush #21
    //   6200: iconst_0
    //   6201: bastore
    //   6202: dup
    //   6203: bipush #22
    //   6205: iconst_0
    //   6206: bastore
    //   6207: dup
    //   6208: bipush #23
    //   6210: iconst_0
    //   6211: bastore
    //   6212: dup
    //   6213: bipush #24
    //   6215: iconst_0
    //   6216: bastore
    //   6217: dup
    //   6218: bipush #25
    //   6220: iconst_0
    //   6221: bastore
    //   6222: dup
    //   6223: bipush #26
    //   6225: iconst_0
    //   6226: bastore
    //   6227: dup
    //   6228: bipush #27
    //   6230: iconst_0
    //   6231: bastore
    //   6232: dup
    //   6233: bipush #28
    //   6235: iconst_0
    //   6236: bastore
    //   6237: dup
    //   6238: bipush #29
    //   6240: iconst_0
    //   6241: bastore
    //   6242: dup
    //   6243: bipush #30
    //   6245: iconst_0
    //   6246: bastore
    //   6247: dup
    //   6248: bipush #31
    //   6250: iconst_0
    //   6251: bastore
    //   6252: dup
    //   6253: bipush #32
    //   6255: iconst_0
    //   6256: bastore
    //   6257: dup
    //   6258: bipush #33
    //   6260: iconst_0
    //   6261: bastore
    //   6262: dup
    //   6263: bipush #34
    //   6265: iconst_0
    //   6266: bastore
    //   6267: dup
    //   6268: bipush #35
    //   6270: iconst_0
    //   6271: bastore
    //   6272: dup
    //   6273: bipush #36
    //   6275: iconst_0
    //   6276: bastore
    //   6277: dup
    //   6278: bipush #37
    //   6280: iconst_0
    //   6281: bastore
    //   6282: dup
    //   6283: bipush #38
    //   6285: iconst_0
    //   6286: bastore
    //   6287: dup
    //   6288: bipush #39
    //   6290: iconst_0
    //   6291: bastore
    //   6292: dup
    //   6293: bipush #40
    //   6295: iconst_0
    //   6296: bastore
    //   6297: dup
    //   6298: bipush #41
    //   6300: iconst_0
    //   6301: bastore
    //   6302: dup
    //   6303: bipush #42
    //   6305: iconst_0
    //   6306: bastore
    //   6307: dup
    //   6308: bipush #43
    //   6310: iconst_0
    //   6311: bastore
    //   6312: dup
    //   6313: bipush #44
    //   6315: iconst_0
    //   6316: bastore
    //   6317: dup
    //   6318: bipush #45
    //   6320: iconst_0
    //   6321: bastore
    //   6322: dup
    //   6323: bipush #46
    //   6325: iconst_0
    //   6326: bastore
    //   6327: dup
    //   6328: bipush #47
    //   6330: iconst_0
    //   6331: bastore
    //   6332: dup
    //   6333: bipush #48
    //   6335: iconst_0
    //   6336: bastore
    //   6337: dup
    //   6338: bipush #49
    //   6340: iconst_0
    //   6341: bastore
    //   6342: dup
    //   6343: bipush #50
    //   6345: iconst_0
    //   6346: bastore
    //   6347: dup
    //   6348: bipush #51
    //   6350: iconst_0
    //   6351: bastore
    //   6352: dup
    //   6353: bipush #52
    //   6355: iconst_0
    //   6356: bastore
    //   6357: dup
    //   6358: bipush #53
    //   6360: iconst_0
    //   6361: bastore
    //   6362: dup
    //   6363: bipush #54
    //   6365: iconst_0
    //   6366: bastore
    //   6367: dup
    //   6368: bipush #55
    //   6370: iconst_0
    //   6371: bastore
    //   6372: dup
    //   6373: bipush #56
    //   6375: iconst_0
    //   6376: bastore
    //   6377: dup
    //   6378: bipush #57
    //   6380: iconst_0
    //   6381: bastore
    //   6382: dup
    //   6383: bipush #58
    //   6385: iconst_0
    //   6386: bastore
    //   6387: dup
    //   6388: bipush #59
    //   6390: iconst_0
    //   6391: bastore
    //   6392: dup
    //   6393: bipush #60
    //   6395: iconst_0
    //   6396: bastore
    //   6397: dup
    //   6398: bipush #61
    //   6400: iconst_0
    //   6401: bastore
    //   6402: dup
    //   6403: bipush #62
    //   6405: iconst_0
    //   6406: bastore
    //   6407: dup
    //   6408: bipush #63
    //   6410: iconst_0
    //   6411: bastore
    //   6412: astore #6
    //   6414: bipush #64
    //   6416: newarray int
    //   6418: dup
    //   6419: iconst_0
    //   6420: ldc 1116352408
    //   6422: iastore
    //   6423: dup
    //   6424: iconst_1
    //   6425: ldc 1899447441
    //   6427: iastore
    //   6428: dup
    //   6429: iconst_2
    //   6430: ldc -1245643825
    //   6432: iastore
    //   6433: dup
    //   6434: iconst_3
    //   6435: ldc -373957723
    //   6437: iastore
    //   6438: dup
    //   6439: iconst_4
    //   6440: ldc 961987163
    //   6442: iastore
    //   6443: dup
    //   6444: iconst_5
    //   6445: ldc 1508970993
    //   6447: iastore
    //   6448: dup
    //   6449: bipush #6
    //   6451: ldc -1841331548
    //   6453: iastore
    //   6454: dup
    //   6455: bipush #7
    //   6457: ldc -1424204075
    //   6459: iastore
    //   6460: dup
    //   6461: bipush #8
    //   6463: ldc -670586216
    //   6465: iastore
    //   6466: dup
    //   6467: bipush #9
    //   6469: ldc 310598401
    //   6471: iastore
    //   6472: dup
    //   6473: bipush #10
    //   6475: ldc 607225278
    //   6477: iastore
    //   6478: dup
    //   6479: bipush #11
    //   6481: ldc 1426881987
    //   6483: iastore
    //   6484: dup
    //   6485: bipush #12
    //   6487: ldc 1925078388
    //   6489: iastore
    //   6490: dup
    //   6491: bipush #13
    //   6493: ldc -2132889090
    //   6495: iastore
    //   6496: dup
    //   6497: bipush #14
    //   6499: ldc -1680079193
    //   6501: iastore
    //   6502: dup
    //   6503: bipush #15
    //   6505: ldc -1046744716
    //   6507: iastore
    //   6508: dup
    //   6509: bipush #16
    //   6511: ldc -459576895
    //   6513: iastore
    //   6514: dup
    //   6515: bipush #17
    //   6517: ldc -272742522
    //   6519: iastore
    //   6520: dup
    //   6521: bipush #18
    //   6523: ldc 264347078
    //   6525: iastore
    //   6526: dup
    //   6527: bipush #19
    //   6529: ldc 604807628
    //   6531: iastore
    //   6532: dup
    //   6533: bipush #20
    //   6535: ldc 770255983
    //   6537: iastore
    //   6538: dup
    //   6539: bipush #21
    //   6541: ldc 1249150122
    //   6543: iastore
    //   6544: dup
    //   6545: bipush #22
    //   6547: ldc 1555081692
    //   6549: iastore
    //   6550: dup
    //   6551: bipush #23
    //   6553: ldc 1996064986
    //   6555: iastore
    //   6556: dup
    //   6557: bipush #24
    //   6559: ldc -1740746414
    //   6561: iastore
    //   6562: dup
    //   6563: bipush #25
    //   6565: ldc -1473132947
    //   6567: iastore
    //   6568: dup
    //   6569: bipush #26
    //   6571: ldc -1341970488
    //   6573: iastore
    //   6574: dup
    //   6575: bipush #27
    //   6577: ldc -1084653625
    //   6579: iastore
    //   6580: dup
    //   6581: bipush #28
    //   6583: ldc -958395405
    //   6585: iastore
    //   6586: dup
    //   6587: bipush #29
    //   6589: ldc -710438585
    //   6591: iastore
    //   6592: dup
    //   6593: bipush #30
    //   6595: ldc 113926993
    //   6597: iastore
    //   6598: dup
    //   6599: bipush #31
    //   6601: ldc 338241895
    //   6603: iastore
    //   6604: dup
    //   6605: bipush #32
    //   6607: ldc 666307205
    //   6609: iastore
    //   6610: dup
    //   6611: bipush #33
    //   6613: ldc 773529912
    //   6615: iastore
    //   6616: dup
    //   6617: bipush #34
    //   6619: ldc 1294757372
    //   6621: iastore
    //   6622: dup
    //   6623: bipush #35
    //   6625: ldc 1396182291
    //   6627: iastore
    //   6628: dup
    //   6629: bipush #36
    //   6631: ldc 1695183700
    //   6633: iastore
    //   6634: dup
    //   6635: bipush #37
    //   6637: ldc 1986661051
    //   6639: iastore
    //   6640: dup
    //   6641: bipush #38
    //   6643: ldc -2117940946
    //   6645: iastore
    //   6646: dup
    //   6647: bipush #39
    //   6649: ldc -1838011259
    //   6651: iastore
    //   6652: dup
    //   6653: bipush #40
    //   6655: ldc -1564481375
    //   6657: iastore
    //   6658: dup
    //   6659: bipush #41
    //   6661: ldc -1474664885
    //   6663: iastore
    //   6664: dup
    //   6665: bipush #42
    //   6667: ldc -1035236496
    //   6669: iastore
    //   6670: dup
    //   6671: bipush #43
    //   6673: ldc -949202525
    //   6675: iastore
    //   6676: dup
    //   6677: bipush #44
    //   6679: ldc -778901479
    //   6681: iastore
    //   6682: dup
    //   6683: bipush #45
    //   6685: ldc -694614492
    //   6687: iastore
    //   6688: dup
    //   6689: bipush #46
    //   6691: ldc -200395387
    //   6693: iastore
    //   6694: dup
    //   6695: bipush #47
    //   6697: ldc 275423344
    //   6699: iastore
    //   6700: dup
    //   6701: bipush #48
    //   6703: ldc 430227734
    //   6705: iastore
    //   6706: dup
    //   6707: bipush #49
    //   6709: ldc 506948616
    //   6711: iastore
    //   6712: dup
    //   6713: bipush #50
    //   6715: ldc 659060556
    //   6717: iastore
    //   6718: dup
    //   6719: bipush #51
    //   6721: ldc 883997877
    //   6723: iastore
    //   6724: dup
    //   6725: bipush #52
    //   6727: ldc 958139571
    //   6729: iastore
    //   6730: dup
    //   6731: bipush #53
    //   6733: ldc 1322822218
    //   6735: iastore
    //   6736: dup
    //   6737: bipush #54
    //   6739: ldc 1537002063
    //   6741: iastore
    //   6742: dup
    //   6743: bipush #55
    //   6745: ldc 1747873779
    //   6747: iastore
    //   6748: dup
    //   6749: bipush #56
    //   6751: ldc 1955562222
    //   6753: iastore
    //   6754: dup
    //   6755: bipush #57
    //   6757: ldc 2024104815
    //   6759: iastore
    //   6760: dup
    //   6761: bipush #58
    //   6763: ldc -2067236844
    //   6765: iastore
    //   6766: dup
    //   6767: bipush #59
    //   6769: ldc -1933114872
    //   6771: iastore
    //   6772: dup
    //   6773: bipush #60
    //   6775: ldc -1866530822
    //   6777: iastore
    //   6778: dup
    //   6779: bipush #61
    //   6781: ldc -1538233109
    //   6783: iastore
    //   6784: dup
    //   6785: bipush #62
    //   6787: ldc -1090935817
    //   6789: iastore
    //   6790: dup
    //   6791: bipush #63
    //   6793: ldc -965641998
    //   6795: iastore
    //   6796: astore #7
    //   6798: iconst_2
    //   6799: newarray int
    //   6801: dup
    //   6802: iconst_0
    //   6803: iconst_0
    //   6804: iastore
    //   6805: dup
    //   6806: iconst_1
    //   6807: iconst_0
    //   6808: iastore
    //   6809: astore #8
    //   6811: bipush #8
    //   6813: newarray int
    //   6815: dup
    //   6816: iconst_0
    //   6817: ldc 1779033703
    //   6819: iastore
    //   6820: dup
    //   6821: iconst_1
    //   6822: ldc -1150833019
    //   6824: iastore
    //   6825: dup
    //   6826: iconst_2
    //   6827: ldc 1013904242
    //   6829: iastore
    //   6830: dup
    //   6831: iconst_3
    //   6832: ldc -1521486534
    //   6834: iastore
    //   6835: dup
    //   6836: iconst_4
    //   6837: ldc 1359893119
    //   6839: iastore
    //   6840: dup
    //   6841: iconst_5
    //   6842: ldc -1694144372
    //   6844: iastore
    //   6845: dup
    //   6846: bipush #6
    //   6848: ldc 528734635
    //   6850: iastore
    //   6851: dup
    //   6852: bipush #7
    //   6854: ldc 1541459225
    //   6856: iastore
    //   6857: astore #9
    //   6859: bipush #64
    //   6861: newarray byte
    //   6863: astore #10
    //   6865: bipush #64
    //   6867: newarray byte
    //   6869: astore #11
    //   6871: aload #4
    //   6873: arraylength
    //   6874: istore #12
    //   6876: aload #8
    //   6878: iconst_0
    //   6879: iaload
    //   6880: bipush #63
    //   6882: iand
    //   6883: istore #13
    //   6885: aload #8
    //   6887: iconst_0
    //   6888: dup2
    //   6889: iaload
    //   6890: iload #12
    //   6892: iadd
    //   6893: iastore
    //   6894: aload #8
    //   6896: iconst_0
    //   6897: dup2
    //   6898: iaload
    //   6899: iconst_m1
    //   6900: iand
    //   6901: iastore
    //   6902: aload #8
    //   6904: iconst_0
    //   6905: iaload
    //   6906: iload #12
    //   6908: if_icmpge -> 6926
    //   6911: aload #8
    //   6913: iconst_1
    //   6914: dup2
    //   6915: iaload
    //   6916: iconst_1
    //   6917: iadd
    //   6918: iastore
    //   6919: goto -> 6926
    //   6922: invokestatic a : (Ljava/lang/Throwable;)Ljava/lang/Throwable;
    //   6925: athrow
    //   6926: iconst_0
    //   6927: istore #14
    //   6929: iload #12
    //   6931: bipush #64
    //   6933: if_icmplt -> 7543
    //   6936: iconst_0
    //   6937: istore #15
    //   6939: iload #15
    //   6941: bipush #64
    //   6943: if_icmpge -> 6966
    //   6946: aload #11
    //   6948: iload #15
    //   6950: aload #4
    //   6952: iload #14
    //   6954: iload #15
    //   6956: iadd
    //   6957: baload
    //   6958: bastore
    //   6959: iinc #15, 1
    //   6962: iload_2
    //   6963: ifeq -> 6939
    //   6966: bipush #64
    //   6968: newarray int
    //   6970: astore #15
    //   6972: bipush #8
    //   6974: newarray int
    //   6976: astore #16
    //   6978: iconst_0
    //   6979: istore #17
    //   6981: iload #17
    //   6983: bipush #8
    //   6985: if_icmpge -> 7005
    //   6988: aload #16
    //   6990: iload #17
    //   6992: aload #9
    //   6994: iload #17
    //   6996: iaload
    //   6997: iastore
    //   6998: iinc #17, 1
    //   7001: iload_2
    //   7002: ifeq -> 6981
    //   7005: iconst_0
    //   7006: istore #17
    //   7008: iload #17
    //   7010: bipush #64
    //   7012: if_icmpge -> 7503
    //   7015: iload #17
    //   7017: bipush #16
    //   7019: if_icmpge -> 7100
    //   7022: aload #15
    //   7024: iload #17
    //   7026: aload #11
    //   7028: iconst_4
    //   7029: iload #17
    //   7031: imul
    //   7032: baload
    //   7033: sipush #255
    //   7036: iand
    //   7037: bipush #24
    //   7039: ishl
    //   7040: aload #11
    //   7042: iconst_4
    //   7043: iload #17
    //   7045: imul
    //   7046: iconst_1
    //   7047: iadd
    //   7048: baload
    //   7049: sipush #255
    //   7052: iand
    //   7053: bipush #16
    //   7055: ishl
    //   7056: ior
    //   7057: aload #11
    //   7059: iconst_4
    //   7060: iload #17
    //   7062: imul
    //   7063: iconst_2
    //   7064: iadd
    //   7065: baload
    //   7066: sipush #255
    //   7069: iand
    //   7070: bipush #8
    //   7072: ishl
    //   7073: ior
    //   7074: aload #11
    //   7076: iconst_4
    //   7077: iload #17
    //   7079: imul
    //   7080: iconst_3
    //   7081: iadd
    //   7082: baload
    //   7083: sipush #255
    //   7086: iand
    //   7087: ior
    //   7088: iastore
    //   7089: iload_2
    //   7090: ifeq -> 7243
    //   7093: goto -> 7100
    //   7096: invokestatic a : (Ljava/lang/Throwable;)Ljava/lang/Throwable;
    //   7099: athrow
    //   7100: aload #15
    //   7102: iload #17
    //   7104: aload #15
    //   7106: iload #17
    //   7108: iconst_2
    //   7109: isub
    //   7110: iaload
    //   7111: bipush #17
    //   7113: iushr
    //   7114: aload #15
    //   7116: iload #17
    //   7118: iconst_2
    //   7119: isub
    //   7120: iaload
    //   7121: bipush #15
    //   7123: ishl
    //   7124: ior
    //   7125: aload #15
    //   7127: iload #17
    //   7129: iconst_2
    //   7130: isub
    //   7131: iaload
    //   7132: bipush #19
    //   7134: iushr
    //   7135: aload #15
    //   7137: iload #17
    //   7139: iconst_2
    //   7140: isub
    //   7141: iaload
    //   7142: bipush #13
    //   7144: ishl
    //   7145: ior
    //   7146: ixor
    //   7147: aload #15
    //   7149: iload #17
    //   7151: iconst_2
    //   7152: isub
    //   7153: iaload
    //   7154: bipush #10
    //   7156: iushr
    //   7157: ixor
    //   7158: aload #15
    //   7160: iload #17
    //   7162: bipush #7
    //   7164: isub
    //   7165: iaload
    //   7166: iadd
    //   7167: aload #15
    //   7169: iload #17
    //   7171: bipush #15
    //   7173: isub
    //   7174: iaload
    //   7175: bipush #7
    //   7177: iushr
    //   7178: aload #15
    //   7180: iload #17
    //   7182: bipush #15
    //   7184: isub
    //   7185: iaload
    //   7186: bipush #25
    //   7188: ishl
    //   7189: ior
    //   7190: aload #15
    //   7192: iload #17
    //   7194: bipush #15
    //   7196: isub
    //   7197: iaload
    //   7198: bipush #18
    //   7200: iushr
    //   7201: aload #15
    //   7203: iload #17
    //   7205: bipush #15
    //   7207: isub
    //   7208: iaload
    //   7209: bipush #14
    //   7211: ishl
    //   7212: ior
    //   7213: ixor
    //   7214: aload #15
    //   7216: iload #17
    //   7218: bipush #15
    //   7220: isub
    //   7221: iaload
    //   7222: iconst_3
    //   7223: iushr
    //   7224: ixor
    //   7225: iadd
    //   7226: aload #15
    //   7228: iload #17
    //   7230: bipush #16
    //   7232: isub
    //   7233: iaload
    //   7234: iadd
    //   7235: iastore
    //   7236: goto -> 7243
    //   7239: invokestatic a : (Ljava/lang/Throwable;)Ljava/lang/Throwable;
    //   7242: athrow
    //   7243: aload #16
    //   7245: bipush #7
    //   7247: iaload
    //   7248: aload #16
    //   7250: iconst_4
    //   7251: iaload
    //   7252: bipush #6
    //   7254: iushr
    //   7255: aload #16
    //   7257: iconst_4
    //   7258: iaload
    //   7259: bipush #26
    //   7261: ishl
    //   7262: ior
    //   7263: aload #16
    //   7265: iconst_4
    //   7266: iaload
    //   7267: bipush #11
    //   7269: iushr
    //   7270: aload #16
    //   7272: iconst_4
    //   7273: iaload
    //   7274: bipush #21
    //   7276: ishl
    //   7277: ior
    //   7278: ixor
    //   7279: aload #16
    //   7281: iconst_4
    //   7282: iaload
    //   7283: bipush #25
    //   7285: iushr
    //   7286: aload #16
    //   7288: iconst_4
    //   7289: iaload
    //   7290: bipush #7
    //   7292: ishl
    //   7293: ior
    //   7294: ixor
    //   7295: iadd
    //   7296: aload #16
    //   7298: bipush #6
    //   7300: iaload
    //   7301: aload #16
    //   7303: iconst_4
    //   7304: iaload
    //   7305: aload #16
    //   7307: iconst_5
    //   7308: iaload
    //   7309: aload #16
    //   7311: bipush #6
    //   7313: iaload
    //   7314: ixor
    //   7315: iand
    //   7316: ixor
    //   7317: iadd
    //   7318: aload #7
    //   7320: iload #17
    //   7322: iaload
    //   7323: iadd
    //   7324: aload #15
    //   7326: iload #17
    //   7328: iaload
    //   7329: iadd
    //   7330: istore #18
    //   7332: aload #16
    //   7334: iconst_0
    //   7335: iaload
    //   7336: iconst_2
    //   7337: iushr
    //   7338: aload #16
    //   7340: iconst_0
    //   7341: iaload
    //   7342: bipush #30
    //   7344: ishl
    //   7345: ior
    //   7346: aload #16
    //   7348: iconst_0
    //   7349: iaload
    //   7350: bipush #13
    //   7352: iushr
    //   7353: aload #16
    //   7355: iconst_0
    //   7356: iaload
    //   7357: bipush #19
    //   7359: ishl
    //   7360: ior
    //   7361: ixor
    //   7362: aload #16
    //   7364: iconst_0
    //   7365: iaload
    //   7366: bipush #22
    //   7368: iushr
    //   7369: aload #16
    //   7371: iconst_0
    //   7372: iaload
    //   7373: bipush #10
    //   7375: ishl
    //   7376: ior
    //   7377: ixor
    //   7378: aload #16
    //   7380: iconst_0
    //   7381: iaload
    //   7382: aload #16
    //   7384: iconst_1
    //   7385: iaload
    //   7386: iand
    //   7387: aload #16
    //   7389: iconst_2
    //   7390: iaload
    //   7391: aload #16
    //   7393: iconst_0
    //   7394: iaload
    //   7395: aload #16
    //   7397: iconst_1
    //   7398: iaload
    //   7399: ior
    //   7400: iand
    //   7401: ior
    //   7402: iadd
    //   7403: istore #19
    //   7405: aload #16
    //   7407: iconst_3
    //   7408: dup2
    //   7409: iaload
    //   7410: iload #18
    //   7412: iadd
    //   7413: iastore
    //   7414: aload #16
    //   7416: bipush #7
    //   7418: iload #18
    //   7420: iload #19
    //   7422: iadd
    //   7423: iastore
    //   7424: aload #16
    //   7426: bipush #7
    //   7428: iaload
    //   7429: istore #18
    //   7431: aload #16
    //   7433: bipush #7
    //   7435: aload #16
    //   7437: bipush #6
    //   7439: iaload
    //   7440: iastore
    //   7441: aload #16
    //   7443: bipush #6
    //   7445: aload #16
    //   7447: iconst_5
    //   7448: iaload
    //   7449: iastore
    //   7450: aload #16
    //   7452: iconst_5
    //   7453: aload #16
    //   7455: iconst_4
    //   7456: iaload
    //   7457: iastore
    //   7458: aload #16
    //   7460: iconst_4
    //   7461: aload #16
    //   7463: iconst_3
    //   7464: iaload
    //   7465: iastore
    //   7466: aload #16
    //   7468: iconst_3
    //   7469: aload #16
    //   7471: iconst_2
    //   7472: iaload
    //   7473: iastore
    //   7474: aload #16
    //   7476: iconst_2
    //   7477: aload #16
    //   7479: iconst_1
    //   7480: iaload
    //   7481: iastore
    //   7482: aload #16
    //   7484: iconst_1
    //   7485: aload #16
    //   7487: iconst_0
    //   7488: iaload
    //   7489: iastore
    //   7490: aload #16
    //   7492: iconst_0
    //   7493: iload #18
    //   7495: iastore
    //   7496: iinc #17, 1
    //   7499: iload_2
    //   7500: ifeq -> 7008
    //   7503: iconst_0
    //   7504: istore #17
    //   7506: iload #17
    //   7508: bipush #8
    //   7510: if_icmpge -> 7533
    //   7513: aload #9
    //   7515: iload #17
    //   7517: dup2
    //   7518: iaload
    //   7519: aload #16
    //   7521: iload #17
    //   7523: iaload
    //   7524: iadd
    //   7525: iastore
    //   7526: iinc #17, 1
    //   7529: iload_2
    //   7530: ifeq -> 7506
    //   7533: iinc #14, 64
    //   7536: iinc #12, -64
    //   7539: iload_2
    //   7540: ifeq -> 6929
    //   7543: iload #12
    //   7545: ifle -> 7581
    //   7548: iconst_0
    //   7549: istore #15
    //   7551: iload #15
    //   7553: iload #12
    //   7555: if_icmpge -> 7581
    //   7558: aload #10
    //   7560: iload #13
    //   7562: iload #15
    //   7564: iadd
    //   7565: aload #4
    //   7567: iload #14
    //   7569: iload #15
    //   7571: iadd
    //   7572: baload
    //   7573: bastore
    //   7574: iinc #15, 1
    //   7577: iload_2
    //   7578: ifeq -> 7551
    //   7581: aload #8
    //   7583: iconst_0
    //   7584: iaload
    //   7585: bipush #29
    //   7587: iushr
    //   7588: aload #8
    //   7590: iconst_1
    //   7591: iaload
    //   7592: iconst_3
    //   7593: ishl
    //   7594: ior
    //   7595: istore #15
    //   7597: aload #8
    //   7599: iconst_0
    //   7600: iaload
    //   7601: iconst_3
    //   7602: ishl
    //   7603: istore #16
    //   7605: aload #8
    //   7607: iconst_0
    //   7608: iaload
    //   7609: bipush #63
    //   7611: iand
    //   7612: istore #17
    //   7614: iload #17
    //   7616: bipush #56
    //   7618: if_icmpge -> 7633
    //   7621: bipush #56
    //   7623: iload #17
    //   7625: isub
    //   7626: goto -> 7638
    //   7629: invokestatic a : (Ljava/lang/Throwable;)Ljava/lang/Throwable;
    //   7632: athrow
    //   7633: bipush #120
    //   7635: iload #17
    //   7637: isub
    //   7638: istore #18
    //   7640: aload #8
    //   7642: iconst_0
    //   7643: iaload
    //   7644: bipush #63
    //   7646: iand
    //   7647: istore #13
    //   7649: bipush #64
    //   7651: iload #13
    //   7653: isub
    //   7654: istore #19
    //   7656: aload #8
    //   7658: iconst_0
    //   7659: dup2
    //   7660: iaload
    //   7661: iload #18
    //   7663: iadd
    //   7664: iastore
    //   7665: aload #8
    //   7667: iconst_0
    //   7668: dup2
    //   7669: iaload
    //   7670: iconst_m1
    //   7671: iand
    //   7672: iastore
    //   7673: aload #8
    //   7675: iconst_0
    //   7676: iaload
    //   7677: iload #18
    //   7679: if_icmpge -> 7697
    //   7682: aload #8
    //   7684: iconst_1
    //   7685: dup2
    //   7686: iaload
    //   7687: iconst_1
    //   7688: iadd
    //   7689: iastore
    //   7690: goto -> 7697
    //   7693: invokestatic a : (Ljava/lang/Throwable;)Ljava/lang/Throwable;
    //   7696: athrow
    //   7697: iconst_0
    //   7698: istore #14
    //   7700: iload #13
    //   7702: ifle -> 8333
    //   7705: iload #18
    //   7707: iload #19
    //   7709: if_icmplt -> 8333
    //   7712: goto -> 7719
    //   7715: invokestatic a : (Ljava/lang/Throwable;)Ljava/lang/Throwable;
    //   7718: athrow
    //   7719: iconst_0
    //   7720: istore #20
    //   7722: iload #20
    //   7724: iload #19
    //   7726: if_icmpge -> 7749
    //   7729: aload #10
    //   7731: iload #13
    //   7733: iload #20
    //   7735: iadd
    //   7736: aload #6
    //   7738: iload #20
    //   7740: baload
    //   7741: bastore
    //   7742: iinc #20, 1
    //   7745: iload_2
    //   7746: ifeq -> 7722
    //   7749: bipush #64
    //   7751: newarray int
    //   7753: astore #20
    //   7755: bipush #8
    //   7757: newarray int
    //   7759: astore #21
    //   7761: iconst_0
    //   7762: istore #22
    //   7764: iload #22
    //   7766: bipush #8
    //   7768: if_icmpge -> 7788
    //   7771: aload #21
    //   7773: iload #22
    //   7775: aload #9
    //   7777: iload #22
    //   7779: iaload
    //   7780: iastore
    //   7781: iinc #22, 1
    //   7784: iload_2
    //   7785: ifeq -> 7764
    //   7788: iconst_0
    //   7789: istore #22
    //   7791: iload #22
    //   7793: bipush #64
    //   7795: if_icmpge -> 8286
    //   7798: iload #22
    //   7800: bipush #16
    //   7802: if_icmpge -> 7883
    //   7805: aload #20
    //   7807: iload #22
    //   7809: aload #10
    //   7811: iconst_4
    //   7812: iload #22
    //   7814: imul
    //   7815: baload
    //   7816: sipush #255
    //   7819: iand
    //   7820: bipush #24
    //   7822: ishl
    //   7823: aload #10
    //   7825: iconst_4
    //   7826: iload #22
    //   7828: imul
    //   7829: iconst_1
    //   7830: iadd
    //   7831: baload
    //   7832: sipush #255
    //   7835: iand
    //   7836: bipush #16
    //   7838: ishl
    //   7839: ior
    //   7840: aload #10
    //   7842: iconst_4
    //   7843: iload #22
    //   7845: imul
    //   7846: iconst_2
    //   7847: iadd
    //   7848: baload
    //   7849: sipush #255
    //   7852: iand
    //   7853: bipush #8
    //   7855: ishl
    //   7856: ior
    //   7857: aload #10
    //   7859: iconst_4
    //   7860: iload #22
    //   7862: imul
    //   7863: iconst_3
    //   7864: iadd
    //   7865: baload
    //   7866: sipush #255
    //   7869: iand
    //   7870: ior
    //   7871: iastore
    //   7872: iload_2
    //   7873: ifeq -> 8026
    //   7876: goto -> 7883
    //   7879: invokestatic a : (Ljava/lang/Throwable;)Ljava/lang/Throwable;
    //   7882: athrow
    //   7883: aload #20
    //   7885: iload #22
    //   7887: aload #20
    //   7889: iload #22
    //   7891: iconst_2
    //   7892: isub
    //   7893: iaload
    //   7894: bipush #17
    //   7896: iushr
    //   7897: aload #20
    //   7899: iload #22
    //   7901: iconst_2
    //   7902: isub
    //   7903: iaload
    //   7904: bipush #15
    //   7906: ishl
    //   7907: ior
    //   7908: aload #20
    //   7910: iload #22
    //   7912: iconst_2
    //   7913: isub
    //   7914: iaload
    //   7915: bipush #19
    //   7917: iushr
    //   7918: aload #20
    //   7920: iload #22
    //   7922: iconst_2
    //   7923: isub
    //   7924: iaload
    //   7925: bipush #13
    //   7927: ishl
    //   7928: ior
    //   7929: ixor
    //   7930: aload #20
    //   7932: iload #22
    //   7934: iconst_2
    //   7935: isub
    //   7936: iaload
    //   7937: bipush #10
    //   7939: iushr
    //   7940: ixor
    //   7941: aload #20
    //   7943: iload #22
    //   7945: bipush #7
    //   7947: isub
    //   7948: iaload
    //   7949: iadd
    //   7950: aload #20
    //   7952: iload #22
    //   7954: bipush #15
    //   7956: isub
    //   7957: iaload
    //   7958: bipush #7
    //   7960: iushr
    //   7961: aload #20
    //   7963: iload #22
    //   7965: bipush #15
    //   7967: isub
    //   7968: iaload
    //   7969: bipush #25
    //   7971: ishl
    //   7972: ior
    //   7973: aload #20
    //   7975: iload #22
    //   7977: bipush #15
    //   7979: isub
    //   7980: iaload
    //   7981: bipush #18
    //   7983: iushr
    //   7984: aload #20
    //   7986: iload #22
    //   7988: bipush #15
    //   7990: isub
    //   7991: iaload
    //   7992: bipush #14
    //   7994: ishl
    //   7995: ior
    //   7996: ixor
    //   7997: aload #20
    //   7999: iload #22
    //   8001: bipush #15
    //   8003: isub
    //   8004: iaload
    //   8005: iconst_3
    //   8006: iushr
    //   8007: ixor
    //   8008: iadd
    //   8009: aload #20
    //   8011: iload #22
    //   8013: bipush #16
    //   8015: isub
    //   8016: iaload
    //   8017: iadd
    //   8018: iastore
    //   8019: goto -> 8026
    //   8022: invokestatic a : (Ljava/lang/Throwable;)Ljava/lang/Throwable;
    //   8025: athrow
    //   8026: aload #21
    //   8028: bipush #7
    //   8030: iaload
    //   8031: aload #21
    //   8033: iconst_4
    //   8034: iaload
    //   8035: bipush #6
    //   8037: iushr
    //   8038: aload #21
    //   8040: iconst_4
    //   8041: iaload
    //   8042: bipush #26
    //   8044: ishl
    //   8045: ior
    //   8046: aload #21
    //   8048: iconst_4
    //   8049: iaload
    //   8050: bipush #11
    //   8052: iushr
    //   8053: aload #21
    //   8055: iconst_4
    //   8056: iaload
    //   8057: bipush #21
    //   8059: ishl
    //   8060: ior
    //   8061: ixor
    //   8062: aload #21
    //   8064: iconst_4
    //   8065: iaload
    //   8066: bipush #25
    //   8068: iushr
    //   8069: aload #21
    //   8071: iconst_4
    //   8072: iaload
    //   8073: bipush #7
    //   8075: ishl
    //   8076: ior
    //   8077: ixor
    //   8078: iadd
    //   8079: aload #21
    //   8081: bipush #6
    //   8083: iaload
    //   8084: aload #21
    //   8086: iconst_4
    //   8087: iaload
    //   8088: aload #21
    //   8090: iconst_5
    //   8091: iaload
    //   8092: aload #21
    //   8094: bipush #6
    //   8096: iaload
    //   8097: ixor
    //   8098: iand
    //   8099: ixor
    //   8100: iadd
    //   8101: aload #7
    //   8103: iload #22
    //   8105: iaload
    //   8106: iadd
    //   8107: aload #20
    //   8109: iload #22
    //   8111: iaload
    //   8112: iadd
    //   8113: istore #23
    //   8115: aload #21
    //   8117: iconst_0
    //   8118: iaload
    //   8119: iconst_2
    //   8120: iushr
    //   8121: aload #21
    //   8123: iconst_0
    //   8124: iaload
    //   8125: bipush #30
    //   8127: ishl
    //   8128: ior
    //   8129: aload #21
    //   8131: iconst_0
    //   8132: iaload
    //   8133: bipush #13
    //   8135: iushr
    //   8136: aload #21
    //   8138: iconst_0
    //   8139: iaload
    //   8140: bipush #19
    //   8142: ishl
    //   8143: ior
    //   8144: ixor
    //   8145: aload #21
    //   8147: iconst_0
    //   8148: iaload
    //   8149: bipush #22
    //   8151: iushr
    //   8152: aload #21
    //   8154: iconst_0
    //   8155: iaload
    //   8156: bipush #10
    //   8158: ishl
    //   8159: ior
    //   8160: ixor
    //   8161: aload #21
    //   8163: iconst_0
    //   8164: iaload
    //   8165: aload #21
    //   8167: iconst_1
    //   8168: iaload
    //   8169: iand
    //   8170: aload #21
    //   8172: iconst_2
    //   8173: iaload
    //   8174: aload #21
    //   8176: iconst_0
    //   8177: iaload
    //   8178: aload #21
    //   8180: iconst_1
    //   8181: iaload
    //   8182: ior
    //   8183: iand
    //   8184: ior
    //   8185: iadd
    //   8186: istore #24
    //   8188: aload #21
    //   8190: iconst_3
    //   8191: dup2
    //   8192: iaload
    //   8193: iload #23
    //   8195: iadd
    //   8196: iastore
    //   8197: aload #21
    //   8199: bipush #7
    //   8201: iload #23
    //   8203: iload #24
    //   8205: iadd
    //   8206: iastore
    //   8207: aload #21
    //   8209: bipush #7
    //   8211: iaload
    //   8212: istore #23
    //   8214: aload #21
    //   8216: bipush #7
    //   8218: aload #21
    //   8220: bipush #6
    //   8222: iaload
    //   8223: iastore
    //   8224: aload #21
    //   8226: bipush #6
    //   8228: aload #21
    //   8230: iconst_5
    //   8231: iaload
    //   8232: iastore
    //   8233: aload #21
    //   8235: iconst_5
    //   8236: aload #21
    //   8238: iconst_4
    //   8239: iaload
    //   8240: iastore
    //   8241: aload #21
    //   8243: iconst_4
    //   8244: aload #21
    //   8246: iconst_3
    //   8247: iaload
    //   8248: iastore
    //   8249: aload #21
    //   8251: iconst_3
    //   8252: aload #21
    //   8254: iconst_2
    //   8255: iaload
    //   8256: iastore
    //   8257: aload #21
    //   8259: iconst_2
    //   8260: aload #21
    //   8262: iconst_1
    //   8263: iaload
    //   8264: iastore
    //   8265: aload #21
    //   8267: iconst_1
    //   8268: aload #21
    //   8270: iconst_0
    //   8271: iaload
    //   8272: iastore
    //   8273: aload #21
    //   8275: iconst_0
    //   8276: iload #23
    //   8278: iastore
    //   8279: iinc #22, 1
    //   8282: iload_2
    //   8283: ifeq -> 7791
    //   8286: iconst_0
    //   8287: istore #22
    //   8289: iload #22
    //   8291: bipush #8
    //   8293: if_icmpge -> 8316
    //   8296: aload #9
    //   8298: iload #22
    //   8300: dup2
    //   8301: iaload
    //   8302: aload #21
    //   8304: iload #22
    //   8306: iaload
    //   8307: iadd
    //   8308: iastore
    //   8309: iinc #22, 1
    //   8312: iload_2
    //   8313: ifeq -> 8289
    //   8316: iload #14
    //   8318: iload #19
    //   8320: iadd
    //   8321: istore #14
    //   8323: iload #18
    //   8325: iload #19
    //   8327: isub
    //   8328: istore #18
    //   8330: iconst_0
    //   8331: istore #13
    //   8333: iload #18
    //   8335: bipush #64
    //   8337: if_icmplt -> 8947
    //   8340: iconst_0
    //   8341: istore #20
    //   8343: iload #20
    //   8345: bipush #64
    //   8347: if_icmpge -> 8370
    //   8350: aload #11
    //   8352: iload #20
    //   8354: aload #6
    //   8356: iload #14
    //   8358: iload #20
    //   8360: iadd
    //   8361: baload
    //   8362: bastore
    //   8363: iinc #20, 1
    //   8366: iload_2
    //   8367: ifeq -> 8343
    //   8370: bipush #64
    //   8372: newarray int
    //   8374: astore #20
    //   8376: bipush #8
    //   8378: newarray int
    //   8380: astore #21
    //   8382: iconst_0
    //   8383: istore #22
    //   8385: iload #22
    //   8387: bipush #8
    //   8389: if_icmpge -> 8409
    //   8392: aload #21
    //   8394: iload #22
    //   8396: aload #9
    //   8398: iload #22
    //   8400: iaload
    //   8401: iastore
    //   8402: iinc #22, 1
    //   8405: iload_2
    //   8406: ifeq -> 8385
    //   8409: iconst_0
    //   8410: istore #22
    //   8412: iload #22
    //   8414: bipush #64
    //   8416: if_icmpge -> 8907
    //   8419: iload #22
    //   8421: bipush #16
    //   8423: if_icmpge -> 8504
    //   8426: aload #20
    //   8428: iload #22
    //   8430: aload #11
    //   8432: iconst_4
    //   8433: iload #22
    //   8435: imul
    //   8436: baload
    //   8437: sipush #255
    //   8440: iand
    //   8441: bipush #24
    //   8443: ishl
    //   8444: aload #11
    //   8446: iconst_4
    //   8447: iload #22
    //   8449: imul
    //   8450: iconst_1
    //   8451: iadd
    //   8452: baload
    //   8453: sipush #255
    //   8456: iand
    //   8457: bipush #16
    //   8459: ishl
    //   8460: ior
    //   8461: aload #11
    //   8463: iconst_4
    //   8464: iload #22
    //   8466: imul
    //   8467: iconst_2
    //   8468: iadd
    //   8469: baload
    //   8470: sipush #255
    //   8473: iand
    //   8474: bipush #8
    //   8476: ishl
    //   8477: ior
    //   8478: aload #11
    //   8480: iconst_4
    //   8481: iload #22
    //   8483: imul
    //   8484: iconst_3
    //   8485: iadd
    //   8486: baload
    //   8487: sipush #255
    //   8490: iand
    //   8491: ior
    //   8492: iastore
    //   8493: iload_2
    //   8494: ifeq -> 8647
    //   8497: goto -> 8504
    //   8500: invokestatic a : (Ljava/lang/Throwable;)Ljava/lang/Throwable;
    //   8503: athrow
    //   8504: aload #20
    //   8506: iload #22
    //   8508: aload #20
    //   8510: iload #22
    //   8512: iconst_2
    //   8513: isub
    //   8514: iaload
    //   8515: bipush #17
    //   8517: iushr
    //   8518: aload #20
    //   8520: iload #22
    //   8522: iconst_2
    //   8523: isub
    //   8524: iaload
    //   8525: bipush #15
    //   8527: ishl
    //   8528: ior
    //   8529: aload #20
    //   8531: iload #22
    //   8533: iconst_2
    //   8534: isub
    //   8535: iaload
    //   8536: bipush #19
    //   8538: iushr
    //   8539: aload #20
    //   8541: iload #22
    //   8543: iconst_2
    //   8544: isub
    //   8545: iaload
    //   8546: bipush #13
    //   8548: ishl
    //   8549: ior
    //   8550: ixor
    //   8551: aload #20
    //   8553: iload #22
    //   8555: iconst_2
    //   8556: isub
    //   8557: iaload
    //   8558: bipush #10
    //   8560: iushr
    //   8561: ixor
    //   8562: aload #20
    //   8564: iload #22
    //   8566: bipush #7
    //   8568: isub
    //   8569: iaload
    //   8570: iadd
    //   8571: aload #20
    //   8573: iload #22
    //   8575: bipush #15
    //   8577: isub
    //   8578: iaload
    //   8579: bipush #7
    //   8581: iushr
    //   8582: aload #20
    //   8584: iload #22
    //   8586: bipush #15
    //   8588: isub
    //   8589: iaload
    //   8590: bipush #25
    //   8592: ishl
    //   8593: ior
    //   8594: aload #20
    //   8596: iload #22
    //   8598: bipush #15
    //   8600: isub
    //   8601: iaload
    //   8602: bipush #18
    //   8604: iushr
    //   8605: aload #20
    //   8607: iload #22
    //   8609: bipush #15
    //   8611: isub
    //   8612: iaload
    //   8613: bipush #14
    //   8615: ishl
    //   8616: ior
    //   8617: ixor
    //   8618: aload #20
    //   8620: iload #22
    //   8622: bipush #15
    //   8624: isub
    //   8625: iaload
    //   8626: iconst_3
    //   8627: iushr
    //   8628: ixor
    //   8629: iadd
    //   8630: aload #20
    //   8632: iload #22
    //   8634: bipush #16
    //   8636: isub
    //   8637: iaload
    //   8638: iadd
    //   8639: iastore
    //   8640: goto -> 8647
    //   8643: invokestatic a : (Ljava/lang/Throwable;)Ljava/lang/Throwable;
    //   8646: athrow
    //   8647: aload #21
    //   8649: bipush #7
    //   8651: iaload
    //   8652: aload #21
    //   8654: iconst_4
    //   8655: iaload
    //   8656: bipush #6
    //   8658: iushr
    //   8659: aload #21
    //   8661: iconst_4
    //   8662: iaload
    //   8663: bipush #26
    //   8665: ishl
    //   8666: ior
    //   8667: aload #21
    //   8669: iconst_4
    //   8670: iaload
    //   8671: bipush #11
    //   8673: iushr
    //   8674: aload #21
    //   8676: iconst_4
    //   8677: iaload
    //   8678: bipush #21
    //   8680: ishl
    //   8681: ior
    //   8682: ixor
    //   8683: aload #21
    //   8685: iconst_4
    //   8686: iaload
    //   8687: bipush #25
    //   8689: iushr
    //   8690: aload #21
    //   8692: iconst_4
    //   8693: iaload
    //   8694: bipush #7
    //   8696: ishl
    //   8697: ior
    //   8698: ixor
    //   8699: iadd
    //   8700: aload #21
    //   8702: bipush #6
    //   8704: iaload
    //   8705: aload #21
    //   8707: iconst_4
    //   8708: iaload
    //   8709: aload #21
    //   8711: iconst_5
    //   8712: iaload
    //   8713: aload #21
    //   8715: bipush #6
    //   8717: iaload
    //   8718: ixor
    //   8719: iand
    //   8720: ixor
    //   8721: iadd
    //   8722: aload #7
    //   8724: iload #22
    //   8726: iaload
    //   8727: iadd
    //   8728: aload #20
    //   8730: iload #22
    //   8732: iaload
    //   8733: iadd
    //   8734: istore #23
    //   8736: aload #21
    //   8738: iconst_0
    //   8739: iaload
    //   8740: iconst_2
    //   8741: iushr
    //   8742: aload #21
    //   8744: iconst_0
    //   8745: iaload
    //   8746: bipush #30
    //   8748: ishl
    //   8749: ior
    //   8750: aload #21
    //   8752: iconst_0
    //   8753: iaload
    //   8754: bipush #13
    //   8756: iushr
    //   8757: aload #21
    //   8759: iconst_0
    //   8760: iaload
    //   8761: bipush #19
    //   8763: ishl
    //   8764: ior
    //   8765: ixor
    //   8766: aload #21
    //   8768: iconst_0
    //   8769: iaload
    //   8770: bipush #22
    //   8772: iushr
    //   8773: aload #21
    //   8775: iconst_0
    //   8776: iaload
    //   8777: bipush #10
    //   8779: ishl
    //   8780: ior
    //   8781: ixor
    //   8782: aload #21
    //   8784: iconst_0
    //   8785: iaload
    //   8786: aload #21
    //   8788: iconst_1
    //   8789: iaload
    //   8790: iand
    //   8791: aload #21
    //   8793: iconst_2
    //   8794: iaload
    //   8795: aload #21
    //   8797: iconst_0
    //   8798: iaload
    //   8799: aload #21
    //   8801: iconst_1
    //   8802: iaload
    //   8803: ior
    //   8804: iand
    //   8805: ior
    //   8806: iadd
    //   8807: istore #24
    //   8809: aload #21
    //   8811: iconst_3
    //   8812: dup2
    //   8813: iaload
    //   8814: iload #23
    //   8816: iadd
    //   8817: iastore
    //   8818: aload #21
    //   8820: bipush #7
    //   8822: iload #23
    //   8824: iload #24
    //   8826: iadd
    //   8827: iastore
    //   8828: aload #21
    //   8830: bipush #7
    //   8832: iaload
    //   8833: istore #23
    //   8835: aload #21
    //   8837: bipush #7
    //   8839: aload #21
    //   8841: bipush #6
    //   8843: iaload
    //   8844: iastore
    //   8845: aload #21
    //   8847: bipush #6
    //   8849: aload #21
    //   8851: iconst_5
    //   8852: iaload
    //   8853: iastore
    //   8854: aload #21
    //   8856: iconst_5
    //   8857: aload #21
    //   8859: iconst_4
    //   8860: iaload
    //   8861: iastore
    //   8862: aload #21
    //   8864: iconst_4
    //   8865: aload #21
    //   8867: iconst_3
    //   8868: iaload
    //   8869: iastore
    //   8870: aload #21
    //   8872: iconst_3
    //   8873: aload #21
    //   8875: iconst_2
    //   8876: iaload
    //   8877: iastore
    //   8878: aload #21
    //   8880: iconst_2
    //   8881: aload #21
    //   8883: iconst_1
    //   8884: iaload
    //   8885: iastore
    //   8886: aload #21
    //   8888: iconst_1
    //   8889: aload #21
    //   8891: iconst_0
    //   8892: iaload
    //   8893: iastore
    //   8894: aload #21
    //   8896: iconst_0
    //   8897: iload #23
    //   8899: iastore
    //   8900: iinc #22, 1
    //   8903: iload_2
    //   8904: ifeq -> 8412
    //   8907: iconst_0
    //   8908: istore #22
    //   8910: iload #22
    //   8912: bipush #8
    //   8914: if_icmpge -> 8937
    //   8917: aload #9
    //   8919: iload #22
    //   8921: dup2
    //   8922: iaload
    //   8923: aload #21
    //   8925: iload #22
    //   8927: iaload
    //   8928: iadd
    //   8929: iastore
    //   8930: iinc #22, 1
    //   8933: iload_2
    //   8934: ifeq -> 8910
    //   8937: iinc #14, 64
    //   8940: iinc #18, -64
    //   8943: iload_2
    //   8944: ifeq -> 8333
    //   8947: iload #18
    //   8949: ifle -> 8985
    //   8952: iconst_0
    //   8953: istore #20
    //   8955: iload #20
    //   8957: iload #18
    //   8959: if_icmpge -> 8985
    //   8962: aload #10
    //   8964: iload #13
    //   8966: iload #20
    //   8968: iadd
    //   8969: aload #6
    //   8971: iload #14
    //   8973: iload #20
    //   8975: iadd
    //   8976: baload
    //   8977: bastore
    //   8978: iinc #20, 1
    //   8981: iload_2
    //   8982: ifeq -> 8955
    //   8985: bipush #8
    //   8987: newarray byte
    //   8989: astore #20
    //   8991: aload #20
    //   8993: iconst_0
    //   8994: iload #15
    //   8996: bipush #24
    //   8998: iushr
    //   8999: i2b
    //   9000: bastore
    //   9001: aload #20
    //   9003: iconst_1
    //   9004: iload #15
    //   9006: bipush #16
    //   9008: iushr
    //   9009: i2b
    //   9010: bastore
    //   9011: aload #20
    //   9013: iconst_2
    //   9014: iload #15
    //   9016: bipush #8
    //   9018: iushr
    //   9019: i2b
    //   9020: bastore
    //   9021: aload #20
    //   9023: iconst_3
    //   9024: iload #15
    //   9026: i2b
    //   9027: bastore
    //   9028: aload #20
    //   9030: iconst_4
    //   9031: iload #16
    //   9033: bipush #24
    //   9035: iushr
    //   9036: i2b
    //   9037: bastore
    //   9038: aload #20
    //   9040: iconst_5
    //   9041: iload #16
    //   9043: bipush #16
    //   9045: iushr
    //   9046: i2b
    //   9047: bastore
    //   9048: aload #20
    //   9050: bipush #6
    //   9052: iload #16
    //   9054: bipush #8
    //   9056: iushr
    //   9057: i2b
    //   9058: bastore
    //   9059: aload #20
    //   9061: bipush #7
    //   9063: iload #16
    //   9065: i2b
    //   9066: bastore
    //   9067: bipush #8
    //   9069: istore #12
    //   9071: aload #8
    //   9073: iconst_0
    //   9074: iaload
    //   9075: bipush #63
    //   9077: iand
    //   9078: istore #13
    //   9080: bipush #64
    //   9082: iload #13
    //   9084: isub
    //   9085: istore #19
    //   9087: aload #8
    //   9089: iconst_0
    //   9090: dup2
    //   9091: iaload
    //   9092: iload #12
    //   9094: iadd
    //   9095: iastore
    //   9096: aload #8
    //   9098: iconst_0
    //   9099: dup2
    //   9100: iaload
    //   9101: iconst_m1
    //   9102: iand
    //   9103: iastore
    //   9104: aload #8
    //   9106: iconst_0
    //   9107: iaload
    //   9108: iload #12
    //   9110: if_icmpge -> 9128
    //   9113: aload #8
    //   9115: iconst_1
    //   9116: dup2
    //   9117: iaload
    //   9118: iconst_1
    //   9119: iadd
    //   9120: iastore
    //   9121: goto -> 9128
    //   9124: invokestatic a : (Ljava/lang/Throwable;)Ljava/lang/Throwable;
    //   9127: athrow
    //   9128: iload #13
    //   9130: ifle -> 9744
    //   9133: iload #12
    //   9135: iload #19
    //   9137: if_icmplt -> 9744
    //   9140: goto -> 9147
    //   9143: invokestatic a : (Ljava/lang/Throwable;)Ljava/lang/Throwable;
    //   9146: athrow
    //   9147: iconst_0
    //   9148: istore #21
    //   9150: iload #21
    //   9152: iload #19
    //   9154: if_icmpge -> 9177
    //   9157: aload #10
    //   9159: iload #13
    //   9161: iload #21
    //   9163: iadd
    //   9164: aload #20
    //   9166: iload #21
    //   9168: baload
    //   9169: bastore
    //   9170: iinc #21, 1
    //   9173: iload_2
    //   9174: ifeq -> 9150
    //   9177: bipush #64
    //   9179: newarray int
    //   9181: astore #21
    //   9183: bipush #8
    //   9185: newarray int
    //   9187: astore #22
    //   9189: iconst_0
    //   9190: istore #23
    //   9192: iload #23
    //   9194: bipush #8
    //   9196: if_icmpge -> 9216
    //   9199: aload #22
    //   9201: iload #23
    //   9203: aload #9
    //   9205: iload #23
    //   9207: iaload
    //   9208: iastore
    //   9209: iinc #23, 1
    //   9212: iload_2
    //   9213: ifeq -> 9192
    //   9216: iconst_0
    //   9217: istore #23
    //   9219: iload #23
    //   9221: bipush #64
    //   9223: if_icmpge -> 9714
    //   9226: iload #23
    //   9228: bipush #16
    //   9230: if_icmpge -> 9311
    //   9233: aload #21
    //   9235: iload #23
    //   9237: aload #10
    //   9239: iconst_4
    //   9240: iload #23
    //   9242: imul
    //   9243: baload
    //   9244: sipush #255
    //   9247: iand
    //   9248: bipush #24
    //   9250: ishl
    //   9251: aload #10
    //   9253: iconst_4
    //   9254: iload #23
    //   9256: imul
    //   9257: iconst_1
    //   9258: iadd
    //   9259: baload
    //   9260: sipush #255
    //   9263: iand
    //   9264: bipush #16
    //   9266: ishl
    //   9267: ior
    //   9268: aload #10
    //   9270: iconst_4
    //   9271: iload #23
    //   9273: imul
    //   9274: iconst_2
    //   9275: iadd
    //   9276: baload
    //   9277: sipush #255
    //   9280: iand
    //   9281: bipush #8
    //   9283: ishl
    //   9284: ior
    //   9285: aload #10
    //   9287: iconst_4
    //   9288: iload #23
    //   9290: imul
    //   9291: iconst_3
    //   9292: iadd
    //   9293: baload
    //   9294: sipush #255
    //   9297: iand
    //   9298: ior
    //   9299: iastore
    //   9300: iload_2
    //   9301: ifeq -> 9454
    //   9304: goto -> 9311
    //   9307: invokestatic a : (Ljava/lang/Throwable;)Ljava/lang/Throwable;
    //   9310: athrow
    //   9311: aload #21
    //   9313: iload #23
    //   9315: aload #21
    //   9317: iload #23
    //   9319: iconst_2
    //   9320: isub
    //   9321: iaload
    //   9322: bipush #17
    //   9324: iushr
    //   9325: aload #21
    //   9327: iload #23
    //   9329: iconst_2
    //   9330: isub
    //   9331: iaload
    //   9332: bipush #15
    //   9334: ishl
    //   9335: ior
    //   9336: aload #21
    //   9338: iload #23
    //   9340: iconst_2
    //   9341: isub
    //   9342: iaload
    //   9343: bipush #19
    //   9345: iushr
    //   9346: aload #21
    //   9348: iload #23
    //   9350: iconst_2
    //   9351: isub
    //   9352: iaload
    //   9353: bipush #13
    //   9355: ishl
    //   9356: ior
    //   9357: ixor
    //   9358: aload #21
    //   9360: iload #23
    //   9362: iconst_2
    //   9363: isub
    //   9364: iaload
    //   9365: bipush #10
    //   9367: iushr
    //   9368: ixor
    //   9369: aload #21
    //   9371: iload #23
    //   9373: bipush #7
    //   9375: isub
    //   9376: iaload
    //   9377: iadd
    //   9378: aload #21
    //   9380: iload #23
    //   9382: bipush #15
    //   9384: isub
    //   9385: iaload
    //   9386: bipush #7
    //   9388: iushr
    //   9389: aload #21
    //   9391: iload #23
    //   9393: bipush #15
    //   9395: isub
    //   9396: iaload
    //   9397: bipush #25
    //   9399: ishl
    //   9400: ior
    //   9401: aload #21
    //   9403: iload #23
    //   9405: bipush #15
    //   9407: isub
    //   9408: iaload
    //   9409: bipush #18
    //   9411: iushr
    //   9412: aload #21
    //   9414: iload #23
    //   9416: bipush #15
    //   9418: isub
    //   9419: iaload
    //   9420: bipush #14
    //   9422: ishl
    //   9423: ior
    //   9424: ixor
    //   9425: aload #21
    //   9427: iload #23
    //   9429: bipush #15
    //   9431: isub
    //   9432: iaload
    //   9433: iconst_3
    //   9434: iushr
    //   9435: ixor
    //   9436: iadd
    //   9437: aload #21
    //   9439: iload #23
    //   9441: bipush #16
    //   9443: isub
    //   9444: iaload
    //   9445: iadd
    //   9446: iastore
    //   9447: goto -> 9454
    //   9450: invokestatic a : (Ljava/lang/Throwable;)Ljava/lang/Throwable;
    //   9453: athrow
    //   9454: aload #22
    //   9456: bipush #7
    //   9458: iaload
    //   9459: aload #22
    //   9461: iconst_4
    //   9462: iaload
    //   9463: bipush #6
    //   9465: iushr
    //   9466: aload #22
    //   9468: iconst_4
    //   9469: iaload
    //   9470: bipush #26
    //   9472: ishl
    //   9473: ior
    //   9474: aload #22
    //   9476: iconst_4
    //   9477: iaload
    //   9478: bipush #11
    //   9480: iushr
    //   9481: aload #22
    //   9483: iconst_4
    //   9484: iaload
    //   9485: bipush #21
    //   9487: ishl
    //   9488: ior
    //   9489: ixor
    //   9490: aload #22
    //   9492: iconst_4
    //   9493: iaload
    //   9494: bipush #25
    //   9496: iushr
    //   9497: aload #22
    //   9499: iconst_4
    //   9500: iaload
    //   9501: bipush #7
    //   9503: ishl
    //   9504: ior
    //   9505: ixor
    //   9506: iadd
    //   9507: aload #22
    //   9509: bipush #6
    //   9511: iaload
    //   9512: aload #22
    //   9514: iconst_4
    //   9515: iaload
    //   9516: aload #22
    //   9518: iconst_5
    //   9519: iaload
    //   9520: aload #22
    //   9522: bipush #6
    //   9524: iaload
    //   9525: ixor
    //   9526: iand
    //   9527: ixor
    //   9528: iadd
    //   9529: aload #7
    //   9531: iload #23
    //   9533: iaload
    //   9534: iadd
    //   9535: aload #21
    //   9537: iload #23
    //   9539: iaload
    //   9540: iadd
    //   9541: istore #24
    //   9543: aload #22
    //   9545: iconst_0
    //   9546: iaload
    //   9547: iconst_2
    //   9548: iushr
    //   9549: aload #22
    //   9551: iconst_0
    //   9552: iaload
    //   9553: bipush #30
    //   9555: ishl
    //   9556: ior
    //   9557: aload #22
    //   9559: iconst_0
    //   9560: iaload
    //   9561: bipush #13
    //   9563: iushr
    //   9564: aload #22
    //   9566: iconst_0
    //   9567: iaload
    //   9568: bipush #19
    //   9570: ishl
    //   9571: ior
    //   9572: ixor
    //   9573: aload #22
    //   9575: iconst_0
    //   9576: iaload
    //   9577: bipush #22
    //   9579: iushr
    //   9580: aload #22
    //   9582: iconst_0
    //   9583: iaload
    //   9584: bipush #10
    //   9586: ishl
    //   9587: ior
    //   9588: ixor
    //   9589: aload #22
    //   9591: iconst_0
    //   9592: iaload
    //   9593: aload #22
    //   9595: iconst_1
    //   9596: iaload
    //   9597: iand
    //   9598: aload #22
    //   9600: iconst_2
    //   9601: iaload
    //   9602: aload #22
    //   9604: iconst_0
    //   9605: iaload
    //   9606: aload #22
    //   9608: iconst_1
    //   9609: iaload
    //   9610: ior
    //   9611: iand
    //   9612: ior
    //   9613: iadd
    //   9614: istore #25
    //   9616: aload #22
    //   9618: iconst_3
    //   9619: dup2
    //   9620: iaload
    //   9621: iload #24
    //   9623: iadd
    //   9624: iastore
    //   9625: aload #22
    //   9627: bipush #7
    //   9629: iload #24
    //   9631: iload #25
    //   9633: iadd
    //   9634: iastore
    //   9635: aload #22
    //   9637: bipush #7
    //   9639: iaload
    //   9640: istore #24
    //   9642: aload #22
    //   9644: bipush #7
    //   9646: aload #22
    //   9648: bipush #6
    //   9650: iaload
    //   9651: iastore
    //   9652: aload #22
    //   9654: bipush #6
    //   9656: aload #22
    //   9658: iconst_5
    //   9659: iaload
    //   9660: iastore
    //   9661: aload #22
    //   9663: iconst_5
    //   9664: aload #22
    //   9666: iconst_4
    //   9667: iaload
    //   9668: iastore
    //   9669: aload #22
    //   9671: iconst_4
    //   9672: aload #22
    //   9674: iconst_3
    //   9675: iaload
    //   9676: iastore
    //   9677: aload #22
    //   9679: iconst_3
    //   9680: aload #22
    //   9682: iconst_2
    //   9683: iaload
    //   9684: iastore
    //   9685: aload #22
    //   9687: iconst_2
    //   9688: aload #22
    //   9690: iconst_1
    //   9691: iaload
    //   9692: iastore
    //   9693: aload #22
    //   9695: iconst_1
    //   9696: aload #22
    //   9698: iconst_0
    //   9699: iaload
    //   9700: iastore
    //   9701: aload #22
    //   9703: iconst_0
    //   9704: iload #24
    //   9706: iastore
    //   9707: iinc #23, 1
    //   9710: iload_2
    //   9711: ifeq -> 9219
    //   9714: iconst_0
    //   9715: istore #23
    //   9717: iload #23
    //   9719: bipush #8
    //   9721: if_icmpge -> 9744
    //   9724: aload #9
    //   9726: iload #23
    //   9728: dup2
    //   9729: iaload
    //   9730: aload #22
    //   9732: iload #23
    //   9734: iaload
    //   9735: iadd
    //   9736: iastore
    //   9737: iinc #23, 1
    //   9740: iload_2
    //   9741: ifeq -> 9717
    //   9744: bipush #32
    //   9746: newarray byte
    //   9748: astore #5
    //   9750: aload #5
    //   9752: iconst_0
    //   9753: aload #9
    //   9755: iconst_0
    //   9756: iaload
    //   9757: bipush #24
    //   9759: iushr
    //   9760: i2b
    //   9761: bastore
    //   9762: aload #5
    //   9764: iconst_1
    //   9765: aload #9
    //   9767: iconst_0
    //   9768: iaload
    //   9769: bipush #16
    //   9771: iushr
    //   9772: i2b
    //   9773: bastore
    //   9774: aload #5
    //   9776: iconst_2
    //   9777: aload #9
    //   9779: iconst_0
    //   9780: iaload
    //   9781: bipush #8
    //   9783: iushr
    //   9784: i2b
    //   9785: bastore
    //   9786: aload #5
    //   9788: iconst_3
    //   9789: aload #9
    //   9791: iconst_0
    //   9792: iaload
    //   9793: i2b
    //   9794: bastore
    //   9795: aload #5
    //   9797: iconst_4
    //   9798: aload #9
    //   9800: iconst_1
    //   9801: iaload
    //   9802: bipush #24
    //   9804: iushr
    //   9805: i2b
    //   9806: bastore
    //   9807: aload #5
    //   9809: iconst_5
    //   9810: aload #9
    //   9812: iconst_1
    //   9813: iaload
    //   9814: bipush #16
    //   9816: iushr
    //   9817: i2b
    //   9818: bastore
    //   9819: aload #5
    //   9821: bipush #6
    //   9823: aload #9
    //   9825: iconst_1
    //   9826: iaload
    //   9827: bipush #8
    //   9829: iushr
    //   9830: i2b
    //   9831: bastore
    //   9832: aload #5
    //   9834: bipush #7
    //   9836: aload #9
    //   9838: iconst_1
    //   9839: iaload
    //   9840: i2b
    //   9841: bastore
    //   9842: aload #5
    //   9844: bipush #8
    //   9846: aload #9
    //   9848: iconst_2
    //   9849: iaload
    //   9850: bipush #24
    //   9852: iushr
    //   9853: i2b
    //   9854: bastore
    //   9855: aload #5
    //   9857: bipush #9
    //   9859: aload #9
    //   9861: iconst_2
    //   9862: iaload
    //   9863: bipush #16
    //   9865: iushr
    //   9866: i2b
    //   9867: bastore
    //   9868: aload #5
    //   9870: bipush #10
    //   9872: aload #9
    //   9874: iconst_2
    //   9875: iaload
    //   9876: bipush #8
    //   9878: iushr
    //   9879: i2b
    //   9880: bastore
    //   9881: aload #5
    //   9883: bipush #11
    //   9885: aload #9
    //   9887: iconst_2
    //   9888: iaload
    //   9889: i2b
    //   9890: bastore
    //   9891: aload #5
    //   9893: bipush #12
    //   9895: aload #9
    //   9897: iconst_3
    //   9898: iaload
    //   9899: bipush #24
    //   9901: iushr
    //   9902: i2b
    //   9903: bastore
    //   9904: aload #5
    //   9906: bipush #13
    //   9908: aload #9
    //   9910: iconst_3
    //   9911: iaload
    //   9912: bipush #16
    //   9914: iushr
    //   9915: i2b
    //   9916: bastore
    //   9917: aload #5
    //   9919: bipush #14
    //   9921: aload #9
    //   9923: iconst_3
    //   9924: iaload
    //   9925: bipush #8
    //   9927: iushr
    //   9928: i2b
    //   9929: bastore
    //   9930: aload #5
    //   9932: bipush #15
    //   9934: aload #9
    //   9936: iconst_3
    //   9937: iaload
    //   9938: i2b
    //   9939: bastore
    //   9940: aload #5
    //   9942: bipush #16
    //   9944: aload #9
    //   9946: iconst_4
    //   9947: iaload
    //   9948: bipush #24
    //   9950: iushr
    //   9951: i2b
    //   9952: bastore
    //   9953: aload #5
    //   9955: bipush #17
    //   9957: aload #9
    //   9959: iconst_4
    //   9960: iaload
    //   9961: bipush #16
    //   9963: iushr
    //   9964: i2b
    //   9965: bastore
    //   9966: aload #5
    //   9968: bipush #18
    //   9970: aload #9
    //   9972: iconst_4
    //   9973: iaload
    //   9974: bipush #8
    //   9976: iushr
    //   9977: i2b
    //   9978: bastore
    //   9979: aload #5
    //   9981: bipush #19
    //   9983: aload #9
    //   9985: iconst_4
    //   9986: iaload
    //   9987: i2b
    //   9988: bastore
    //   9989: aload #5
    //   9991: bipush #20
    //   9993: aload #9
    //   9995: iconst_5
    //   9996: iaload
    //   9997: bipush #24
    //   9999: iushr
    //   10000: i2b
    //   10001: bastore
    //   10002: aload #5
    //   10004: bipush #21
    //   10006: aload #9
    //   10008: iconst_5
    //   10009: iaload
    //   10010: bipush #16
    //   10012: iushr
    //   10013: i2b
    //   10014: bastore
    //   10015: aload #5
    //   10017: bipush #22
    //   10019: aload #9
    //   10021: iconst_5
    //   10022: iaload
    //   10023: bipush #8
    //   10025: iushr
    //   10026: i2b
    //   10027: bastore
    //   10028: aload #5
    //   10030: bipush #23
    //   10032: aload #9
    //   10034: iconst_5
    //   10035: iaload
    //   10036: i2b
    //   10037: bastore
    //   10038: aload #5
    //   10040: bipush #24
    //   10042: aload #9
    //   10044: bipush #6
    //   10046: iaload
    //   10047: bipush #24
    //   10049: iushr
    //   10050: i2b
    //   10051: bastore
    //   10052: aload #5
    //   10054: bipush #25
    //   10056: aload #9
    //   10058: bipush #6
    //   10060: iaload
    //   10061: bipush #16
    //   10063: iushr
    //   10064: i2b
    //   10065: bastore
    //   10066: aload #5
    //   10068: bipush #26
    //   10070: aload #9
    //   10072: bipush #6
    //   10074: iaload
    //   10075: bipush #8
    //   10077: iushr
    //   10078: i2b
    //   10079: bastore
    //   10080: aload #5
    //   10082: bipush #27
    //   10084: aload #9
    //   10086: bipush #6
    //   10088: iaload
    //   10089: i2b
    //   10090: bastore
    //   10091: aload #5
    //   10093: bipush #28
    //   10095: aload #9
    //   10097: bipush #7
    //   10099: iaload
    //   10100: bipush #24
    //   10102: iushr
    //   10103: i2b
    //   10104: bastore
    //   10105: aload #5
    //   10107: bipush #29
    //   10109: aload #9
    //   10111: bipush #7
    //   10113: iaload
    //   10114: bipush #16
    //   10116: iushr
    //   10117: i2b
    //   10118: bastore
    //   10119: aload #5
    //   10121: bipush #30
    //   10123: aload #9
    //   10125: bipush #7
    //   10127: iaload
    //   10128: bipush #8
    //   10130: iushr
    //   10131: i2b
    //   10132: bastore
    //   10133: aload #5
    //   10135: bipush #31
    //   10137: aload #9
    //   10139: bipush #7
    //   10141: iaload
    //   10142: i2b
    //   10143: bastore
    //   10144: iconst_0
    //   10145: istore #4
    //   10147: getstatic burp/Zrfh.ZH : Ljava/lang/String;
    //   10150: getstatic burp/Zkfb.ZN : Ljava/lang/Object;
    //   10153: checkcast java/math/BigInteger
    //   10156: invokevirtual intValue : ()I
    //   10159: bipush #32
    //   10161: irem
    //   10162: invokestatic abs : (I)I
    //   10165: invokevirtual charAt : (I)C
    //   10168: getstatic burp/Zre4.Zh : Ljava/lang/String;
    //   10171: getstatic burp/Ztsc.Zr : Ljava/lang/Object;
    //   10174: checkcast java/math/BigInteger
    //   10177: invokevirtual intValue : ()I
    //   10180: bipush #32
    //   10182: irem
    //   10183: invokestatic abs : (I)I
    //   10186: invokevirtual charAt : (I)C
    //   10189: if_icmpgt -> 10534
    //   10192: sipush #-15832
    //   10195: sipush #-9892
    //   10198: invokestatic a : (II)Ljava/lang/String;
    //   10201: iconst_1
    //   10202: ldc burp/Zb1
    //   10204: invokevirtual getClassLoader : ()Ljava/lang/ClassLoader;
    //   10207: invokestatic forName : (Ljava/lang/String;ZLjava/lang/ClassLoader;)Ljava/lang/Class;
    //   10210: invokevirtual getDeclaredFields : ()[Ljava/lang/reflect/Field;
    //   10213: astore #5
    //   10215: aload #5
    //   10217: arraylength
    //   10218: istore #6
    //   10220: iconst_0
    //   10221: istore #7
    //   10223: iload #7
    //   10225: iload #6
    //   10227: if_icmpge -> 10365
    //   10230: aload #5
    //   10232: iload #7
    //   10234: aaload
    //   10235: astore #8
    //   10237: aload #8
    //   10239: invokevirtual getModifiers : ()I
    //   10242: invokestatic isStatic : (I)Z
    //   10245: ifne -> 10255
    //   10248: goto -> 10358
    //   10251: invokestatic a : (Ljava/lang/Throwable;)Ljava/lang/Throwable;
    //   10254: athrow
    //   10255: aload #8
    //   10257: invokevirtual getType : ()Ljava/lang/Class;
    //   10260: astore #9
    //   10262: aload #9
    //   10264: ifnull -> 10345
    //   10267: aload #9
    //   10269: invokevirtual isPrimitive : ()Z
    //   10272: ifne -> 10345
    //   10275: goto -> 10282
    //   10278: invokestatic a : (Ljava/lang/Throwable;)Ljava/lang/Throwable;
    //   10281: athrow
    //   10282: aload #9
    //   10284: invokevirtual getPackage : ()Ljava/lang/Package;
    //   10287: ifnull -> 10345
    //   10290: goto -> 10297
    //   10293: invokestatic a : (Ljava/lang/Throwable;)Ljava/lang/Throwable;
    //   10296: athrow
    //   10297: aload #9
    //   10299: invokevirtual getPackage : ()Ljava/lang/Package;
    //   10302: invokevirtual getName : ()Ljava/lang/String;
    //   10305: ifnull -> 10345
    //   10308: goto -> 10315
    //   10311: invokestatic a : (Ljava/lang/Throwable;)Ljava/lang/Throwable;
    //   10314: athrow
    //   10315: aload #9
    //   10317: invokevirtual getPackage : ()Ljava/lang/Package;
    //   10320: invokevirtual getName : ()Ljava/lang/String;
    //   10323: sipush #-15813
    //   10326: sipush #-1561
    //   10329: invokestatic a : (II)Ljava/lang/String;
    //   10332: invokevirtual startsWith : (Ljava/lang/String;)Z
    //   10335: ifne -> 10345
    //   10338: goto -> 10345
    //   10341: invokestatic a : (Ljava/lang/Throwable;)Ljava/lang/Throwable;
    //   10344: athrow
    //   10345: aload #8
    //   10347: iconst_1
    //   10348: invokevirtual setAccessible : (Z)V
    //   10351: aload #8
    //   10353: aconst_null
    //   10354: invokevirtual get : (Ljava/lang/Object;)Ljava/lang/Object;
    //   10357: pop
    //   10358: iinc #7, 1
    //   10361: iload_2
    //   10362: ifeq -> 10223
    //   10365: sipush #-15830
    //   10368: sipush #23795
    //   10371: invokestatic a : (II)Ljava/lang/String;
    //   10374: invokestatic forName : (Ljava/lang/String;)Ljava/lang/Class;
    //   10377: invokevirtual getDeclaredMethods : ()[Ljava/lang/reflect/Method;
    //   10380: astore #5
    //   10382: aload #5
    //   10384: arraylength
    //   10385: istore #6
    //   10387: iconst_0
    //   10388: istore #7
    //   10390: iload #7
    //   10392: iload #6
    //   10394: if_icmpge -> 10531
    //   10397: aload #5
    //   10399: iload #7
    //   10401: aaload
    //   10402: astore #8
    //   10404: aload #8
    //   10406: invokevirtual getParameterTypes : ()[Ljava/lang/Class;
    //   10409: pop
    //   10410: aload #8
    //   10412: invokevirtual getModifiers : ()I
    //   10415: invokestatic isStatic : (I)Z
    //   10418: ifeq -> 10517
    //   10421: aload #8
    //   10423: invokevirtual getParameterTypes : ()[Ljava/lang/Class;
    //   10426: arraylength
    //   10427: iconst_2
    //   10428: if_icmpne -> 10517
    //   10431: goto -> 10438
    //   10434: invokestatic a : (Ljava/lang/Throwable;)Ljava/lang/Throwable;
    //   10437: athrow
    //   10438: aload #8
    //   10440: invokevirtual getReturnType : ()Ljava/lang/Class;
    //   10443: getstatic java/lang/Boolean.TYPE : Ljava/lang/Class;
    //   10446: if_acmpne -> 10517
    //   10449: goto -> 10456
    //   10452: invokestatic a : (Ljava/lang/Throwable;)Ljava/lang/Throwable;
    //   10455: athrow
    //   10456: aload #8
    //   10458: iconst_1
    //   10459: invokevirtual setAccessible : (Z)V
    //   10462: aload #8
    //   10464: aconst_null
    //   10465: iconst_2
    //   10466: anewarray java/lang/Object
    //   10469: dup
    //   10470: iconst_0
    //   10471: aload_0
    //   10472: aastore
    //   10473: dup
    //   10474: iconst_1
    //   10475: aload_1
    //   10476: ifnonnull -> 10494
    //   10479: goto -> 10486
    //   10482: invokestatic a : (Ljava/lang/Throwable;)Ljava/lang/Throwable;
    //   10485: athrow
    //   10486: aload_1
    //   10487: goto -> 10501
    //   10490: invokestatic a : (Ljava/lang/Throwable;)Ljava/lang/Throwable;
    //   10493: athrow
    //   10494: aload_1
    //   10495: checkcast [B
    //   10498: invokevirtual clone : ()Ljava/lang/Object;
    //   10501: aastore
    //   10502: invokevirtual invoke : (Ljava/lang/Object;[Ljava/lang/Object;)Ljava/lang/Object;
    //   10505: checkcast java/lang/Boolean
    //   10508: invokevirtual booleanValue : ()Z
    //   10511: istore #4
    //   10513: iload_2
    //   10514: ifeq -> 10531
    //   10517: iinc #7, 1
    //   10520: iload_2
    //   10521: ifeq -> 10390
    //   10524: goto -> 10531
    //   10527: invokestatic a : (Ljava/lang/Throwable;)Ljava/lang/Throwable;
    //   10530: athrow
    //   10531: goto -> 10873
    //   10534: sipush #-15816
    //   10537: sipush #-20452
    //   10540: invokestatic a : (II)Ljava/lang/String;
    //   10543: iconst_1
    //   10544: ldc burp/Zl39
    //   10546: invokevirtual getClassLoader : ()Ljava/lang/ClassLoader;
    //   10549: invokestatic forName : (Ljava/lang/String;ZLjava/lang/ClassLoader;)Ljava/lang/Class;
    //   10552: invokevirtual getDeclaredFields : ()[Ljava/lang/reflect/Field;
    //   10555: astore #5
    //   10557: aload #5
    //   10559: arraylength
    //   10560: istore #6
    //   10562: iconst_0
    //   10563: istore #7
    //   10565: iload #7
    //   10567: iload #6
    //   10569: if_icmpge -> 10707
    //   10572: aload #5
    //   10574: iload #7
    //   10576: aaload
    //   10577: astore #8
    //   10579: aload #8
    //   10581: invokevirtual getModifiers : ()I
    //   10584: invokestatic isStatic : (I)Z
    //   10587: ifne -> 10597
    //   10590: goto -> 10700
    //   10593: invokestatic a : (Ljava/lang/Throwable;)Ljava/lang/Throwable;
    //   10596: athrow
    //   10597: aload #8
    //   10599: invokevirtual getType : ()Ljava/lang/Class;
    //   10602: astore #9
    //   10604: aload #9
    //   10606: ifnull -> 10687
    //   10609: aload #9
    //   10611: invokevirtual isPrimitive : ()Z
    //   10614: ifne -> 10687
    //   10617: goto -> 10624
    //   10620: invokestatic a : (Ljava/lang/Throwable;)Ljava/lang/Throwable;
    //   10623: athrow
    //   10624: aload #9
    //   10626: invokevirtual getPackage : ()Ljava/lang/Package;
    //   10629: ifnull -> 10687
    //   10632: goto -> 10639
    //   10635: invokestatic a : (Ljava/lang/Throwable;)Ljava/lang/Throwable;
    //   10638: athrow
    //   10639: aload #9
    //   10641: invokevirtual getPackage : ()Ljava/lang/Package;
    //   10644: invokevirtual getName : ()Ljava/lang/String;
    //   10647: ifnull -> 10687
    //   10650: goto -> 10657
    //   10653: invokestatic a : (Ljava/lang/Throwable;)Ljava/lang/Throwable;
    //   10656: athrow
    //   10657: aload #9
    //   10659: invokevirtual getPackage : ()Ljava/lang/Package;
    //   10662: invokevirtual getName : ()Ljava/lang/String;
    //   10665: sipush #-15813
    //   10668: sipush #-1561
    //   10671: invokestatic a : (II)Ljava/lang/String;
    //   10674: invokevirtual startsWith : (Ljava/lang/String;)Z
    //   10677: ifne -> 10687
    //   10680: goto -> 10687
    //   10683: invokestatic a : (Ljava/lang/Throwable;)Ljava/lang/Throwable;
    //   10686: athrow
    //   10687: aload #8
    //   10689: iconst_1
    //   10690: invokevirtual setAccessible : (Z)V
    //   10693: aload #8
    //   10695: aconst_null
    //   10696: invokevirtual get : (Ljava/lang/Object;)Ljava/lang/Object;
    //   10699: pop
    //   10700: iinc #7, 1
    //   10703: iload_2
    //   10704: ifeq -> 10565
    //   10707: sipush #-15833
    //   10710: sipush #5128
    //   10713: invokestatic a : (II)Ljava/lang/String;
    //   10716: invokestatic forName : (Ljava/lang/String;)Ljava/lang/Class;
    //   10719: invokevirtual getDeclaredMethods : ()[Ljava/lang/reflect/Method;
    //   10722: astore #5
    //   10724: aload #5
    //   10726: arraylength
    //   10727: istore #6
    //   10729: iconst_0
    //   10730: istore #7
    //   10732: iload #7
    //   10734: iload #6
    //   10736: if_icmpge -> 10873
    //   10739: aload #5
    //   10741: iload #7
    //   10743: aaload
    //   10744: astore #8
    //   10746: aload #8
    //   10748: invokevirtual getParameterTypes : ()[Ljava/lang/Class;
    //   10751: pop
    //   10752: aload #8
    //   10754: invokevirtual getModifiers : ()I
    //   10757: invokestatic isStatic : (I)Z
    //   10760: ifeq -> 10859
    //   10763: aload #8
    //   10765: invokevirtual getParameterTypes : ()[Ljava/lang/Class;
    //   10768: arraylength
    //   10769: iconst_2
    //   10770: if_icmpne -> 10859
    //   10773: goto -> 10780
    //   10776: invokestatic a : (Ljava/lang/Throwable;)Ljava/lang/Throwable;
    //   10779: athrow
    //   10780: aload #8
    //   10782: invokevirtual getReturnType : ()Ljava/lang/Class;
    //   10785: getstatic java/lang/Boolean.TYPE : Ljava/lang/Class;
    //   10788: if_acmpne -> 10859
    //   10791: goto -> 10798
    //   10794: invokestatic a : (Ljava/lang/Throwable;)Ljava/lang/Throwable;
    //   10797: athrow
    //   10798: aload #8
    //   10800: iconst_1
    //   10801: invokevirtual setAccessible : (Z)V
    //   10804: aload #8
    //   10806: aconst_null
    //   10807: iconst_2
    //   10808: anewarray java/lang/Object
    //   10811: dup
    //   10812: iconst_0
    //   10813: aload_0
    //   10814: aastore
    //   10815: dup
    //   10816: iconst_1
    //   10817: aload_1
    //   10818: ifnonnull -> 10836
    //   10821: goto -> 10828
    //   10824: invokestatic a : (Ljava/lang/Throwable;)Ljava/lang/Throwable;
    //   10827: athrow
    //   10828: aload_1
    //   10829: goto -> 10843
    //   10832: invokestatic a : (Ljava/lang/Throwable;)Ljava/lang/Throwable;
    //   10835: athrow
    //   10836: aload_1
    //   10837: checkcast [B
    //   10840: invokevirtual clone : ()Ljava/lang/Object;
    //   10843: aastore
    //   10844: invokevirtual invoke : (Ljava/lang/Object;[Ljava/lang/Object;)Ljava/lang/Object;
    //   10847: checkcast java/lang/Boolean
    //   10850: invokevirtual booleanValue : ()Z
    //   10853: istore #4
    //   10855: iload_2
    //   10856: ifeq -> 10873
    //   10859: iinc #7, 1
    //   10862: iload_2
    //   10863: ifeq -> 10732
    //   10866: goto -> 10873
    //   10869: invokestatic a : (Ljava/lang/Throwable;)Ljava/lang/Throwable;
    //   10872: athrow
    //   10873: iload #4
    //   10875: ifeq -> 10881
    //   10878: iload #4
    //   10880: ireturn
    //   10881: getstatic burp/Zefn.Ze : Ljava/lang/String;
    //   10884: getstatic burp/Zktq.Zn : Ljava/lang/Object;
    //   10887: checkcast java/math/BigInteger
    //   10890: invokevirtual intValue : ()I
    //   10893: bipush #32
    //   10895: irem
    //   10896: invokestatic abs : (I)I
    //   10899: invokevirtual charAt : (I)C
    //   10902: getstatic burp/Ze_e.ZH : Ljava/lang/String;
    //   10905: getstatic burp/Zeqw.ZV : Ljava/lang/Object;
    //   10908: checkcast java/math/BigInteger
    //   10911: invokevirtual intValue : ()I
    //   10914: bipush #32
    //   10916: irem
    //   10917: invokestatic abs : (I)I
    //   10920: invokevirtual charAt : (I)C
    //   10923: if_icmpgt -> 11269
    //   10926: sipush #-15819
    //   10929: sipush #-3603
    //   10932: invokestatic a : (II)Ljava/lang/String;
    //   10935: iconst_1
    //   10936: ldc burp/Zzbr
    //   10938: invokevirtual getClassLoader : ()Ljava/lang/ClassLoader;
    //   10941: invokestatic forName : (Ljava/lang/String;ZLjava/lang/ClassLoader;)Ljava/lang/Class;
    //   10944: invokevirtual getDeclaredFields : ()[Ljava/lang/reflect/Field;
    //   10947: astore #5
    //   10949: aload #5
    //   10951: arraylength
    //   10952: istore #6
    //   10954: iconst_0
    //   10955: istore #7
    //   10957: iload #7
    //   10959: iload #6
    //   10961: if_icmpge -> 11099
    //   10964: aload #5
    //   10966: iload #7
    //   10968: aaload
    //   10969: astore #8
    //   10971: aload #8
    //   10973: invokevirtual getModifiers : ()I
    //   10976: invokestatic isStatic : (I)Z
    //   10979: ifne -> 10989
    //   10982: goto -> 11092
    //   10985: invokestatic a : (Ljava/lang/Throwable;)Ljava/lang/Throwable;
    //   10988: athrow
    //   10989: aload #8
    //   10991: invokevirtual getType : ()Ljava/lang/Class;
    //   10994: astore #9
    //   10996: aload #9
    //   10998: ifnull -> 11079
    //   11001: aload #9
    //   11003: invokevirtual isPrimitive : ()Z
    //   11006: ifne -> 11079
    //   11009: goto -> 11016
    //   11012: invokestatic a : (Ljava/lang/Throwable;)Ljava/lang/Throwable;
    //   11015: athrow
    //   11016: aload #9
    //   11018: invokevirtual getPackage : ()Ljava/lang/Package;
    //   11021: ifnull -> 11079
    //   11024: goto -> 11031
    //   11027: invokestatic a : (Ljava/lang/Throwable;)Ljava/lang/Throwable;
    //   11030: athrow
    //   11031: aload #9
    //   11033: invokevirtual getPackage : ()Ljava/lang/Package;
    //   11036: invokevirtual getName : ()Ljava/lang/String;
    //   11039: ifnull -> 11079
    //   11042: goto -> 11049
    //   11045: invokestatic a : (Ljava/lang/Throwable;)Ljava/lang/Throwable;
    //   11048: athrow
    //   11049: aload #9
    //   11051: invokevirtual getPackage : ()Ljava/lang/Package;
    //   11054: invokevirtual getName : ()Ljava/lang/String;
    //   11057: sipush #-15813
    //   11060: sipush #-1561
    //   11063: invokestatic a : (II)Ljava/lang/String;
    //   11066: invokevirtual startsWith : (Ljava/lang/String;)Z
    //   11069: ifne -> 11079
    //   11072: goto -> 11079
    //   11075: invokestatic a : (Ljava/lang/Throwable;)Ljava/lang/Throwable;
    //   11078: athrow
    //   11079: aload #8
    //   11081: iconst_1
    //   11082: invokevirtual setAccessible : (Z)V
    //   11085: aload #8
    //   11087: aconst_null
    //   11088: invokevirtual get : (Ljava/lang/Object;)Ljava/lang/Object;
    //   11091: pop
    //   11092: iinc #7, 1
    //   11095: iload_2
    //   11096: ifeq -> 10957
    //   11099: sipush #-15824
    //   11102: sipush #16281
    //   11105: invokestatic a : (II)Ljava/lang/String;
    //   11108: invokestatic forName : (Ljava/lang/String;)Ljava/lang/Class;
    //   11111: invokevirtual getDeclaredMethods : ()[Ljava/lang/reflect/Method;
    //   11114: astore #5
    //   11116: aload #5
    //   11118: arraylength
    //   11119: istore #6
    //   11121: iconst_0
    //   11122: istore #7
    //   11124: iload #7
    //   11126: iload #6
    //   11128: if_icmpge -> 11265
    //   11131: aload #5
    //   11133: iload #7
    //   11135: aaload
    //   11136: astore #8
    //   11138: aload #8
    //   11140: invokevirtual getParameterTypes : ()[Ljava/lang/Class;
    //   11143: pop
    //   11144: aload #8
    //   11146: invokevirtual getModifiers : ()I
    //   11149: invokestatic isStatic : (I)Z
    //   11152: ifeq -> 11251
    //   11155: aload #8
    //   11157: invokevirtual getParameterTypes : ()[Ljava/lang/Class;
    //   11160: arraylength
    //   11161: iconst_2
    //   11162: if_icmpne -> 11251
    //   11165: goto -> 11172
    //   11168: invokestatic a : (Ljava/lang/Throwable;)Ljava/lang/Throwable;
    //   11171: athrow
    //   11172: aload #8
    //   11174: invokevirtual getReturnType : ()Ljava/lang/Class;
    //   11177: getstatic java/lang/Boolean.TYPE : Ljava/lang/Class;
    //   11180: if_acmpne -> 11251
    //   11183: goto -> 11190
    //   11186: invokestatic a : (Ljava/lang/Throwable;)Ljava/lang/Throwable;
    //   11189: athrow
    //   11190: aload #8
    //   11192: iconst_1
    //   11193: invokevirtual setAccessible : (Z)V
    //   11196: aload #8
    //   11198: aconst_null
    //   11199: iconst_2
    //   11200: anewarray java/lang/Object
    //   11203: dup
    //   11204: iconst_0
    //   11205: aload_0
    //   11206: aastore
    //   11207: dup
    //   11208: iconst_1
    //   11209: aload_1
    //   11210: ifnonnull -> 11228
    //   11213: goto -> 11220
    //   11216: invokestatic a : (Ljava/lang/Throwable;)Ljava/lang/Throwable;
    //   11219: athrow
    //   11220: aload_1
    //   11221: goto -> 11235
    //   11224: invokestatic a : (Ljava/lang/Throwable;)Ljava/lang/Throwable;
    //   11227: athrow
    //   11228: aload_1
    //   11229: checkcast [B
    //   11232: invokevirtual clone : ()Ljava/lang/Object;
    //   11235: aastore
    //   11236: invokevirtual invoke : (Ljava/lang/Object;[Ljava/lang/Object;)Ljava/lang/Object;
    //   11239: checkcast java/lang/Boolean
    //   11242: invokevirtual booleanValue : ()Z
    //   11245: istore #4
    //   11247: iload_2
    //   11248: ifeq -> 11265
    //   11251: iinc #7, 1
    //   11254: iload_2
    //   11255: ifeq -> 11124
    //   11258: goto -> 11265
    //   11261: invokestatic a : (Ljava/lang/Throwable;)Ljava/lang/Throwable;
    //   11264: athrow
    //   11265: iload_2
    //   11266: ifeq -> 11608
    //   11269: sipush #-15825
    //   11272: sipush #-9788
    //   11275: invokestatic a : (II)Ljava/lang/String;
    //   11278: iconst_1
    //   11279: ldc burp/Zb9q
    //   11281: invokevirtual getClassLoader : ()Ljava/lang/ClassLoader;
    //   11284: invokestatic forName : (Ljava/lang/String;ZLjava/lang/ClassLoader;)Ljava/lang/Class;
    //   11287: invokevirtual getDeclaredFields : ()[Ljava/lang/reflect/Field;
    //   11290: astore #5
    //   11292: aload #5
    //   11294: arraylength
    //   11295: istore #6
    //   11297: iconst_0
    //   11298: istore #7
    //   11300: iload #7
    //   11302: iload #6
    //   11304: if_icmpge -> 11442
    //   11307: aload #5
    //   11309: iload #7
    //   11311: aaload
    //   11312: astore #8
    //   11314: aload #8
    //   11316: invokevirtual getModifiers : ()I
    //   11319: invokestatic isStatic : (I)Z
    //   11322: ifne -> 11332
    //   11325: goto -> 11435
    //   11328: invokestatic a : (Ljava/lang/Throwable;)Ljava/lang/Throwable;
    //   11331: athrow
    //   11332: aload #8
    //   11334: invokevirtual getType : ()Ljava/lang/Class;
    //   11337: astore #9
    //   11339: aload #9
    //   11341: ifnull -> 11422
    //   11344: aload #9
    //   11346: invokevirtual isPrimitive : ()Z
    //   11349: ifne -> 11422
    //   11352: goto -> 11359
    //   11355: invokestatic a : (Ljava/lang/Throwable;)Ljava/lang/Throwable;
    //   11358: athrow
    //   11359: aload #9
    //   11361: invokevirtual getPackage : ()Ljava/lang/Package;
    //   11364: ifnull -> 11422
    //   11367: goto -> 11374
    //   11370: invokestatic a : (Ljava/lang/Throwable;)Ljava/lang/Throwable;
    //   11373: athrow
    //   11374: aload #9
    //   11376: invokevirtual getPackage : ()Ljava/lang/Package;
    //   11379: invokevirtual getName : ()Ljava/lang/String;
    //   11382: ifnull -> 11422
    //   11385: goto -> 11392
    //   11388: invokestatic a : (Ljava/lang/Throwable;)Ljava/lang/Throwable;
    //   11391: athrow
    //   11392: aload #9
    //   11394: invokevirtual getPackage : ()Ljava/lang/Package;
    //   11397: invokevirtual getName : ()Ljava/lang/String;
    //   11400: sipush #-15813
    //   11403: sipush #-1561
    //   11406: invokestatic a : (II)Ljava/lang/String;
    //   11409: invokevirtual startsWith : (Ljava/lang/String;)Z
    //   11412: ifne -> 11422
    //   11415: goto -> 11422
    //   11418: invokestatic a : (Ljava/lang/Throwable;)Ljava/lang/Throwable;
    //   11421: athrow
    //   11422: aload #8
    //   11424: iconst_1
    //   11425: invokevirtual setAccessible : (Z)V
    //   11428: aload #8
    //   11430: aconst_null
    //   11431: invokevirtual get : (Ljava/lang/Object;)Ljava/lang/Object;
    //   11434: pop
    //   11435: iinc #7, 1
    //   11438: iload_2
    //   11439: ifeq -> 11300
    //   11442: sipush #-15814
    //   11445: sipush #29225
    //   11448: invokestatic a : (II)Ljava/lang/String;
    //   11451: invokestatic forName : (Ljava/lang/String;)Ljava/lang/Class;
    //   11454: invokevirtual getDeclaredMethods : ()[Ljava/lang/reflect/Method;
    //   11457: astore #5
    //   11459: aload #5
    //   11461: arraylength
    //   11462: istore #6
    //   11464: iconst_0
    //   11465: istore #7
    //   11467: iload #7
    //   11469: iload #6
    //   11471: if_icmpge -> 11608
    //   11474: aload #5
    //   11476: iload #7
    //   11478: aaload
    //   11479: astore #8
    //   11481: aload #8
    //   11483: invokevirtual getParameterTypes : ()[Ljava/lang/Class;
    //   11486: pop
    //   11487: aload #8
    //   11489: invokevirtual getModifiers : ()I
    //   11492: invokestatic isStatic : (I)Z
    //   11495: ifeq -> 11594
    //   11498: aload #8
    //   11500: invokevirtual getParameterTypes : ()[Ljava/lang/Class;
    //   11503: arraylength
    //   11504: iconst_2
    //   11505: if_icmpne -> 11594
    //   11508: goto -> 11515
    //   11511: invokestatic a : (Ljava/lang/Throwable;)Ljava/lang/Throwable;
    //   11514: athrow
    //   11515: aload #8
    //   11517: invokevirtual getReturnType : ()Ljava/lang/Class;
    //   11520: getstatic java/lang/Boolean.TYPE : Ljava/lang/Class;
    //   11523: if_acmpne -> 11594
    //   11526: goto -> 11533
    //   11529: invokestatic a : (Ljava/lang/Throwable;)Ljava/lang/Throwable;
    //   11532: athrow
    //   11533: aload #8
    //   11535: iconst_1
    //   11536: invokevirtual setAccessible : (Z)V
    //   11539: aload #8
    //   11541: aconst_null
    //   11542: iconst_2
    //   11543: anewarray java/lang/Object
    //   11546: dup
    //   11547: iconst_0
    //   11548: aload_0
    //   11549: aastore
    //   11550: dup
    //   11551: iconst_1
    //   11552: aload_1
    //   11553: ifnonnull -> 11571
    //   11556: goto -> 11563
    //   11559: invokestatic a : (Ljava/lang/Throwable;)Ljava/lang/Throwable;
    //   11562: athrow
    //   11563: aload_1
    //   11564: goto -> 11578
    //   11567: invokestatic a : (Ljava/lang/Throwable;)Ljava/lang/Throwable;
    //   11570: athrow
    //   11571: aload_1
    //   11572: checkcast [B
    //   11575: invokevirtual clone : ()Ljava/lang/Object;
    //   11578: aastore
    //   11579: invokevirtual invoke : (Ljava/lang/Object;[Ljava/lang/Object;)Ljava/lang/Object;
    //   11582: checkcast java/lang/Boolean
    //   11585: invokevirtual booleanValue : ()Z
    //   11588: istore #4
    //   11590: iload_2
    //   11591: ifeq -> 11608
    //   11594: iinc #7, 1
    //   11597: iload_2
    //   11598: ifeq -> 11467
    //   11601: goto -> 11608
    //   11604: invokestatic a : (Ljava/lang/Throwable;)Ljava/lang/Throwable;
    //   11607: athrow
    //   11608: iload #4
    //   11610: ifeq -> 11616
    //   11613: iload #4
    //   11615: ireturn
    //   11616: getstatic burp/Zenq.ZG : Ljava/lang/String;
    //   11619: getstatic burp/Zeai.ZI : Ljava/lang/Object;
    //   11622: checkcast java/math/BigInteger
    //   11625: invokevirtual intValue : ()I
    //   11628: bipush #32
    //   11630: irem
    //   11631: invokestatic abs : (I)I
    //   11634: invokevirtual charAt : (I)C
    //   11637: getstatic burp/Zefn.Ze : Ljava/lang/String;
    //   11640: getstatic burp/Zspk.ZF : Ljava/lang/Object;
    //   11643: checkcast java/math/BigInteger
    //   11646: invokevirtual intValue : ()I
    //   11649: bipush #32
    //   11651: irem
    //   11652: invokestatic abs : (I)I
    //   11655: invokevirtual charAt : (I)C
    //   11658: if_icmpgt -> 12004
    //   11661: sipush #-15820
    //   11664: sipush #29341
    //   11667: invokestatic a : (II)Ljava/lang/String;
    //   11670: iconst_1
    //   11671: ldc burp/Zgsy
    //   11673: invokevirtual getClassLoader : ()Ljava/lang/ClassLoader;
    //   11676: invokestatic forName : (Ljava/lang/String;ZLjava/lang/ClassLoader;)Ljava/lang/Class;
    //   11679: invokevirtual getDeclaredFields : ()[Ljava/lang/reflect/Field;
    //   11682: astore #5
    //   11684: aload #5
    //   11686: arraylength
    //   11687: istore #6
    //   11689: iconst_0
    //   11690: istore #7
    //   11692: iload #7
    //   11694: iload #6
    //   11696: if_icmpge -> 11834
    //   11699: aload #5
    //   11701: iload #7
    //   11703: aaload
    //   11704: astore #8
    //   11706: aload #8
    //   11708: invokevirtual getModifiers : ()I
    //   11711: invokestatic isStatic : (I)Z
    //   11714: ifne -> 11724
    //   11717: goto -> 11827
    //   11720: invokestatic a : (Ljava/lang/Throwable;)Ljava/lang/Throwable;
    //   11723: athrow
    //   11724: aload #8
    //   11726: invokevirtual getType : ()Ljava/lang/Class;
    //   11729: astore #9
    //   11731: aload #9
    //   11733: ifnull -> 11814
    //   11736: aload #9
    //   11738: invokevirtual isPrimitive : ()Z
    //   11741: ifne -> 11814
    //   11744: goto -> 11751
    //   11747: invokestatic a : (Ljava/lang/Throwable;)Ljava/lang/Throwable;
    //   11750: athrow
    //   11751: aload #9
    //   11753: invokevirtual getPackage : ()Ljava/lang/Package;
    //   11756: ifnull -> 11814
    //   11759: goto -> 11766
    //   11762: invokestatic a : (Ljava/lang/Throwable;)Ljava/lang/Throwable;
    //   11765: athrow
    //   11766: aload #9
    //   11768: invokevirtual getPackage : ()Ljava/lang/Package;
    //   11771: invokevirtual getName : ()Ljava/lang/String;
    //   11774: ifnull -> 11814
    //   11777: goto -> 11784
    //   11780: invokestatic a : (Ljava/lang/Throwable;)Ljava/lang/Throwable;
    //   11783: athrow
    //   11784: aload #9
    //   11786: invokevirtual getPackage : ()Ljava/lang/Package;
    //   11789: invokevirtual getName : ()Ljava/lang/String;
    //   11792: sipush #-15813
    //   11795: sipush #-1561
    //   11798: invokestatic a : (II)Ljava/lang/String;
    //   11801: invokevirtual startsWith : (Ljava/lang/String;)Z
    //   11804: ifne -> 11814
    //   11807: goto -> 11814
    //   11810: invokestatic a : (Ljava/lang/Throwable;)Ljava/lang/Throwable;
    //   11813: athrow
    //   11814: aload #8
    //   11816: iconst_1
    //   11817: invokevirtual setAccessible : (Z)V
    //   11820: aload #8
    //   11822: aconst_null
    //   11823: invokevirtual get : (Ljava/lang/Object;)Ljava/lang/Object;
    //   11826: pop
    //   11827: iinc #7, 1
    //   11830: iload_2
    //   11831: ifeq -> 11692
    //   11834: sipush #-15818
    //   11837: sipush #15212
    //   11840: invokestatic a : (II)Ljava/lang/String;
    //   11843: invokestatic forName : (Ljava/lang/String;)Ljava/lang/Class;
    //   11846: invokevirtual getDeclaredMethods : ()[Ljava/lang/reflect/Method;
    //   11849: astore #5
    //   11851: aload #5
    //   11853: arraylength
    //   11854: istore #6
    //   11856: iconst_0
    //   11857: istore #7
    //   11859: iload #7
    //   11861: iload #6
    //   11863: if_icmpge -> 12000
    //   11866: aload #5
    //   11868: iload #7
    //   11870: aaload
    //   11871: astore #8
    //   11873: aload #8
    //   11875: invokevirtual getParameterTypes : ()[Ljava/lang/Class;
    //   11878: pop
    //   11879: aload #8
    //   11881: invokevirtual getModifiers : ()I
    //   11884: invokestatic isStatic : (I)Z
    //   11887: ifeq -> 11986
    //   11890: aload #8
    //   11892: invokevirtual getParameterTypes : ()[Ljava/lang/Class;
    //   11895: arraylength
    //   11896: iconst_2
    //   11897: if_icmpne -> 11986
    //   11900: goto -> 11907
    //   11903: invokestatic a : (Ljava/lang/Throwable;)Ljava/lang/Throwable;
    //   11906: athrow
    //   11907: aload #8
    //   11909: invokevirtual getReturnType : ()Ljava/lang/Class;
    //   11912: getstatic java/lang/Boolean.TYPE : Ljava/lang/Class;
    //   11915: if_acmpne -> 11986
    //   11918: goto -> 11925
    //   11921: invokestatic a : (Ljava/lang/Throwable;)Ljava/lang/Throwable;
    //   11924: athrow
    //   11925: aload #8
    //   11927: iconst_1
    //   11928: invokevirtual setAccessible : (Z)V
    //   11931: aload #8
    //   11933: aconst_null
    //   11934: iconst_2
    //   11935: anewarray java/lang/Object
    //   11938: dup
    //   11939: iconst_0
    //   11940: aload_0
    //   11941: aastore
    //   11942: dup
    //   11943: iconst_1
    //   11944: aload_1
    //   11945: ifnonnull -> 11963
    //   11948: goto -> 11955
    //   11951: invokestatic a : (Ljava/lang/Throwable;)Ljava/lang/Throwable;
    //   11954: athrow
    //   11955: aload_1
    //   11956: goto -> 11970
    //   11959: invokestatic a : (Ljava/lang/Throwable;)Ljava/lang/Throwable;
    //   11962: athrow
    //   11963: aload_1
    //   11964: checkcast [B
    //   11967: invokevirtual clone : ()Ljava/lang/Object;
    //   11970: aastore
    //   11971: invokevirtual invoke : (Ljava/lang/Object;[Ljava/lang/Object;)Ljava/lang/Object;
    //   11974: checkcast java/lang/Boolean
    //   11977: invokevirtual booleanValue : ()Z
    //   11980: istore #4
    //   11982: iload_2
    //   11983: ifeq -> 12000
    //   11986: iinc #7, 1
    //   11989: iload_2
    //   11990: ifeq -> 11859
    //   11993: goto -> 12000
    //   11996: invokestatic a : (Ljava/lang/Throwable;)Ljava/lang/Throwable;
    //   11999: athrow
    //   12000: iload_2
    //   12001: ifeq -> 12343
    //   12004: sipush #-15812
    //   12007: sipush #-14225
    //   12010: invokestatic a : (II)Ljava/lang/String;
    //   12013: iconst_1
    //   12014: ldc burp/Zge1
    //   12016: invokevirtual getClassLoader : ()Ljava/lang/ClassLoader;
    //   12019: invokestatic forName : (Ljava/lang/String;ZLjava/lang/ClassLoader;)Ljava/lang/Class;
    //   12022: invokevirtual getDeclaredFields : ()[Ljava/lang/reflect/Field;
    //   12025: astore #5
    //   12027: aload #5
    //   12029: arraylength
    //   12030: istore #6
    //   12032: iconst_0
    //   12033: istore #7
    //   12035: iload #7
    //   12037: iload #6
    //   12039: if_icmpge -> 12177
    //   12042: aload #5
    //   12044: iload #7
    //   12046: aaload
    //   12047: astore #8
    //   12049: aload #8
    //   12051: invokevirtual getModifiers : ()I
    //   12054: invokestatic isStatic : (I)Z
    //   12057: ifne -> 12067
    //   12060: goto -> 12170
    //   12063: invokestatic a : (Ljava/lang/Throwable;)Ljava/lang/Throwable;
    //   12066: athrow
    //   12067: aload #8
    //   12069: invokevirtual getType : ()Ljava/lang/Class;
    //   12072: astore #9
    //   12074: aload #9
    //   12076: ifnull -> 12157
    //   12079: aload #9
    //   12081: invokevirtual isPrimitive : ()Z
    //   12084: ifne -> 12157
    //   12087: goto -> 12094
    //   12090: invokestatic a : (Ljava/lang/Throwable;)Ljava/lang/Throwable;
    //   12093: athrow
    //   12094: aload #9
    //   12096: invokevirtual getPackage : ()Ljava/lang/Package;
    //   12099: ifnull -> 12157
    //   12102: goto -> 12109
    //   12105: invokestatic a : (Ljava/lang/Throwable;)Ljava/lang/Throwable;
    //   12108: athrow
    //   12109: aload #9
    //   12111: invokevirtual getPackage : ()Ljava/lang/Package;
    //   12114: invokevirtual getName : ()Ljava/lang/String;
    //   12117: ifnull -> 12157
    //   12120: goto -> 12127
    //   12123: invokestatic a : (Ljava/lang/Throwable;)Ljava/lang/Throwable;
    //   12126: athrow
    //   12127: aload #9
    //   12129: invokevirtual getPackage : ()Ljava/lang/Package;
    //   12132: invokevirtual getName : ()Ljava/lang/String;
    //   12135: sipush #-15813
    //   12138: sipush #-1561
    //   12141: invokestatic a : (II)Ljava/lang/String;
    //   12144: invokevirtual startsWith : (Ljava/lang/String;)Z
    //   12147: ifne -> 12157
    //   12150: goto -> 12157
    //   12153: invokestatic a : (Ljava/lang/Throwable;)Ljava/lang/Throwable;
    //   12156: athrow
    //   12157: aload #8
    //   12159: iconst_1
    //   12160: invokevirtual setAccessible : (Z)V
    //   12163: aload #8
    //   12165: aconst_null
    //   12166: invokevirtual get : (Ljava/lang/Object;)Ljava/lang/Object;
    //   12169: pop
    //   12170: iinc #7, 1
    //   12173: iload_2
    //   12174: ifeq -> 12035
    //   12177: sipush #-15817
    //   12180: sipush #11665
    //   12183: invokestatic a : (II)Ljava/lang/String;
    //   12186: invokestatic forName : (Ljava/lang/String;)Ljava/lang/Class;
    //   12189: invokevirtual getDeclaredMethods : ()[Ljava/lang/reflect/Method;
    //   12192: astore #5
    //   12194: aload #5
    //   12196: arraylength
    //   12197: istore #6
    //   12199: iconst_0
    //   12200: istore #7
    //   12202: iload #7
    //   12204: iload #6
    //   12206: if_icmpge -> 12343
    //   12209: aload #5
    //   12211: iload #7
    //   12213: aaload
    //   12214: astore #8
    //   12216: aload #8
    //   12218: invokevirtual getParameterTypes : ()[Ljava/lang/Class;
    //   12221: pop
    //   12222: aload #8
    //   12224: invokevirtual getModifiers : ()I
    //   12227: invokestatic isStatic : (I)Z
    //   12230: ifeq -> 12329
    //   12233: aload #8
    //   12235: invokevirtual getParameterTypes : ()[Ljava/lang/Class;
    //   12238: arraylength
    //   12239: iconst_2
    //   12240: if_icmpne -> 12329
    //   12243: goto -> 12250
    //   12246: invokestatic a : (Ljava/lang/Throwable;)Ljava/lang/Throwable;
    //   12249: athrow
    //   12250: aload #8
    //   12252: invokevirtual getReturnType : ()Ljava/lang/Class;
    //   12255: getstatic java/lang/Boolean.TYPE : Ljava/lang/Class;
    //   12258: if_acmpne -> 12329
    //   12261: goto -> 12268
    //   12264: invokestatic a : (Ljava/lang/Throwable;)Ljava/lang/Throwable;
    //   12267: athrow
    //   12268: aload #8
    //   12270: iconst_1
    //   12271: invokevirtual setAccessible : (Z)V
    //   12274: aload #8
    //   12276: aconst_null
    //   12277: iconst_2
    //   12278: anewarray java/lang/Object
    //   12281: dup
    //   12282: iconst_0
    //   12283: aload_0
    //   12284: aastore
    //   12285: dup
    //   12286: iconst_1
    //   12287: aload_1
    //   12288: ifnonnull -> 12306
    //   12291: goto -> 12298
    //   12294: invokestatic a : (Ljava/lang/Throwable;)Ljava/lang/Throwable;
    //   12297: athrow
    //   12298: aload_1
    //   12299: goto -> 12313
    //   12302: invokestatic a : (Ljava/lang/Throwable;)Ljava/lang/Throwable;
    //   12305: athrow
    //   12306: aload_1
    //   12307: checkcast [B
    //   12310: invokevirtual clone : ()Ljava/lang/Object;
    //   12313: aastore
    //   12314: invokevirtual invoke : (Ljava/lang/Object;[Ljava/lang/Object;)Ljava/lang/Object;
    //   12317: checkcast java/lang/Boolean
    //   12320: invokevirtual booleanValue : ()Z
    //   12323: istore #4
    //   12325: iload_2
    //   12326: ifeq -> 12343
    //   12329: iinc #7, 1
    //   12332: iload_2
    //   12333: ifeq -> 12202
    //   12336: goto -> 12343
    //   12339: invokestatic a : (Ljava/lang/Throwable;)Ljava/lang/Throwable;
    //   12342: athrow
    //   12343: iload #4
    //   12345: ifeq -> 12351
    //   12348: iload #4
    //   12350: ireturn
    //   12351: getstatic burp/Zso7.Zr : Ljava/lang/String;
    //   12354: getstatic burp/Ztpg.Z_ : Ljava/lang/Object;
    //   12357: checkcast java/math/BigInteger
    //   12360: invokevirtual intValue : ()I
    //   12363: bipush #32
    //   12365: irem
    //   12366: invokestatic abs : (I)I
    //   12369: invokevirtual charAt : (I)C
    //   12372: getstatic burp/Zl8s.Zn : Ljava/lang/String;
    //   12375: getstatic burp/Zzoc.Zx : Ljava/lang/Object;
    //   12378: checkcast java/math/BigInteger
    //   12381: invokevirtual intValue : ()I
    //   12384: bipush #32
    //   12386: irem
    //   12387: invokestatic abs : (I)I
    //   12390: invokevirtual charAt : (I)C
    //   12393: if_icmpgt -> 12739
    //   12396: sipush #-15835
    //   12399: sipush #2946
    //   12402: invokestatic a : (II)Ljava/lang/String;
    //   12405: iconst_1
    //   12406: ldc burp/Zlum
    //   12408: invokevirtual getClassLoader : ()Ljava/lang/ClassLoader;
    //   12411: invokestatic forName : (Ljava/lang/String;ZLjava/lang/ClassLoader;)Ljava/lang/Class;
    //   12414: invokevirtual getDeclaredFields : ()[Ljava/lang/reflect/Field;
    //   12417: astore #5
    //   12419: aload #5
    //   12421: arraylength
    //   12422: istore #6
    //   12424: iconst_0
    //   12425: istore #7
    //   12427: iload #7
    //   12429: iload #6
    //   12431: if_icmpge -> 12569
    //   12434: aload #5
    //   12436: iload #7
    //   12438: aaload
    //   12439: astore #8
    //   12441: aload #8
    //   12443: invokevirtual getModifiers : ()I
    //   12446: invokestatic isStatic : (I)Z
    //   12449: ifne -> 12459
    //   12452: goto -> 12562
    //   12455: invokestatic a : (Ljava/lang/Throwable;)Ljava/lang/Throwable;
    //   12458: athrow
    //   12459: aload #8
    //   12461: invokevirtual getType : ()Ljava/lang/Class;
    //   12464: astore #9
    //   12466: aload #9
    //   12468: ifnull -> 12549
    //   12471: aload #9
    //   12473: invokevirtual isPrimitive : ()Z
    //   12476: ifne -> 12549
    //   12479: goto -> 12486
    //   12482: invokestatic a : (Ljava/lang/Throwable;)Ljava/lang/Throwable;
    //   12485: athrow
    //   12486: aload #9
    //   12488: invokevirtual getPackage : ()Ljava/lang/Package;
    //   12491: ifnull -> 12549
    //   12494: goto -> 12501
    //   12497: invokestatic a : (Ljava/lang/Throwable;)Ljava/lang/Throwable;
    //   12500: athrow
    //   12501: aload #9
    //   12503: invokevirtual getPackage : ()Ljava/lang/Package;
    //   12506: invokevirtual getName : ()Ljava/lang/String;
    //   12509: ifnull -> 12549
    //   12512: goto -> 12519
    //   12515: invokestatic a : (Ljava/lang/Throwable;)Ljava/lang/Throwable;
    //   12518: athrow
    //   12519: aload #9
    //   12521: invokevirtual getPackage : ()Ljava/lang/Package;
    //   12524: invokevirtual getName : ()Ljava/lang/String;
    //   12527: sipush #-15813
    //   12530: sipush #-1561
    //   12533: invokestatic a : (II)Ljava/lang/String;
    //   12536: invokevirtual startsWith : (Ljava/lang/String;)Z
    //   12539: ifne -> 12549
    //   12542: goto -> 12549
    //   12545: invokestatic a : (Ljava/lang/Throwable;)Ljava/lang/Throwable;
    //   12548: athrow
    //   12549: aload #8
    //   12551: iconst_1
    //   12552: invokevirtual setAccessible : (Z)V
    //   12555: aload #8
    //   12557: aconst_null
    //   12558: invokevirtual get : (Ljava/lang/Object;)Ljava/lang/Object;
    //   12561: pop
    //   12562: iinc #7, 1
    //   12565: iload_2
    //   12566: ifeq -> 12427
    //   12569: sipush #-15834
    //   12572: sipush #-31691
    //   12575: invokestatic a : (II)Ljava/lang/String;
    //   12578: invokestatic forName : (Ljava/lang/String;)Ljava/lang/Class;
    //   12581: invokevirtual getDeclaredMethods : ()[Ljava/lang/reflect/Method;
    //   12584: astore #5
    //   12586: aload #5
    //   12588: arraylength
    //   12589: istore #6
    //   12591: iconst_0
    //   12592: istore #7
    //   12594: iload #7
    //   12596: iload #6
    //   12598: if_icmpge -> 12735
    //   12601: aload #5
    //   12603: iload #7
    //   12605: aaload
    //   12606: astore #8
    //   12608: aload #8
    //   12610: invokevirtual getParameterTypes : ()[Ljava/lang/Class;
    //   12613: pop
    //   12614: aload #8
    //   12616: invokevirtual getModifiers : ()I
    //   12619: invokestatic isStatic : (I)Z
    //   12622: ifeq -> 12721
    //   12625: aload #8
    //   12627: invokevirtual getParameterTypes : ()[Ljava/lang/Class;
    //   12630: arraylength
    //   12631: iconst_2
    //   12632: if_icmpne -> 12721
    //   12635: goto -> 12642
    //   12638: invokestatic a : (Ljava/lang/Throwable;)Ljava/lang/Throwable;
    //   12641: athrow
    //   12642: aload #8
    //   12644: invokevirtual getReturnType : ()Ljava/lang/Class;
    //   12647: getstatic java/lang/Boolean.TYPE : Ljava/lang/Class;
    //   12650: if_acmpne -> 12721
    //   12653: goto -> 12660
    //   12656: invokestatic a : (Ljava/lang/Throwable;)Ljava/lang/Throwable;
    //   12659: athrow
    //   12660: aload #8
    //   12662: iconst_1
    //   12663: invokevirtual setAccessible : (Z)V
    //   12666: aload #8
    //   12668: aconst_null
    //   12669: iconst_2
    //   12670: anewarray java/lang/Object
    //   12673: dup
    //   12674: iconst_0
    //   12675: aload_0
    //   12676: aastore
    //   12677: dup
    //   12678: iconst_1
    //   12679: aload_1
    //   12680: ifnonnull -> 12698
    //   12683: goto -> 12690
    //   12686: invokestatic a : (Ljava/lang/Throwable;)Ljava/lang/Throwable;
    //   12689: athrow
    //   12690: aload_1
    //   12691: goto -> 12705
    //   12694: invokestatic a : (Ljava/lang/Throwable;)Ljava/lang/Throwable;
    //   12697: athrow
    //   12698: aload_1
    //   12699: checkcast [B
    //   12702: invokevirtual clone : ()Ljava/lang/Object;
    //   12705: aastore
    //   12706: invokevirtual invoke : (Ljava/lang/Object;[Ljava/lang/Object;)Ljava/lang/Object;
    //   12709: checkcast java/lang/Boolean
    //   12712: invokevirtual booleanValue : ()Z
    //   12715: istore #4
    //   12717: iload_2
    //   12718: ifeq -> 12735
    //   12721: iinc #7, 1
    //   12724: iload_2
    //   12725: ifeq -> 12594
    //   12728: goto -> 12735
    //   12731: invokestatic a : (Ljava/lang/Throwable;)Ljava/lang/Throwable;
    //   12734: athrow
    //   12735: iload_2
    //   12736: ifeq -> 13078
    //   12739: sipush #-15828
    //   12742: sipush #19740
    //   12745: invokestatic a : (II)Ljava/lang/String;
    //   12748: iconst_1
    //   12749: ldc burp/Zxx4
    //   12751: invokevirtual getClassLoader : ()Ljava/lang/ClassLoader;
    //   12754: invokestatic forName : (Ljava/lang/String;ZLjava/lang/ClassLoader;)Ljava/lang/Class;
    //   12757: invokevirtual getDeclaredFields : ()[Ljava/lang/reflect/Field;
    //   12760: astore #5
    //   12762: aload #5
    //   12764: arraylength
    //   12765: istore #6
    //   12767: iconst_0
    //   12768: istore #7
    //   12770: iload #7
    //   12772: iload #6
    //   12774: if_icmpge -> 12912
    //   12777: aload #5
    //   12779: iload #7
    //   12781: aaload
    //   12782: astore #8
    //   12784: aload #8
    //   12786: invokevirtual getModifiers : ()I
    //   12789: invokestatic isStatic : (I)Z
    //   12792: ifne -> 12802
    //   12795: goto -> 12905
    //   12798: invokestatic a : (Ljava/lang/Throwable;)Ljava/lang/Throwable;
    //   12801: athrow
    //   12802: aload #8
    //   12804: invokevirtual getType : ()Ljava/lang/Class;
    //   12807: astore #9
    //   12809: aload #9
    //   12811: ifnull -> 12892
    //   12814: aload #9
    //   12816: invokevirtual isPrimitive : ()Z
    //   12819: ifne -> 12892
    //   12822: goto -> 12829
    //   12825: invokestatic a : (Ljava/lang/Throwable;)Ljava/lang/Throwable;
    //   12828: athrow
    //   12829: aload #9
    //   12831: invokevirtual getPackage : ()Ljava/lang/Package;
    //   12834: ifnull -> 12892
    //   12837: goto -> 12844
    //   12840: invokestatic a : (Ljava/lang/Throwable;)Ljava/lang/Throwable;
    //   12843: athrow
    //   12844: aload #9
    //   12846: invokevirtual getPackage : ()Ljava/lang/Package;
    //   12849: invokevirtual getName : ()Ljava/lang/String;
    //   12852: ifnull -> 12892
    //   12855: goto -> 12862
    //   12858: invokestatic a : (Ljava/lang/Throwable;)Ljava/lang/Throwable;
    //   12861: athrow
    //   12862: aload #9
    //   12864: invokevirtual getPackage : ()Ljava/lang/Package;
    //   12867: invokevirtual getName : ()Ljava/lang/String;
    //   12870: sipush #-15813
    //   12873: sipush #-1561
    //   12876: invokestatic a : (II)Ljava/lang/String;
    //   12879: invokevirtual startsWith : (Ljava/lang/String;)Z
    //   12882: ifne -> 12892
    //   12885: goto -> 12892
    //   12888: invokestatic a : (Ljava/lang/Throwable;)Ljava/lang/Throwable;
    //   12891: athrow
    //   12892: aload #8
    //   12894: iconst_1
    //   12895: invokevirtual setAccessible : (Z)V
    //   12898: aload #8
    //   12900: aconst_null
    //   12901: invokevirtual get : (Ljava/lang/Object;)Ljava/lang/Object;
    //   12904: pop
    //   12905: iinc #7, 1
    //   12908: iload_2
    //   12909: ifeq -> 12770
    //   12912: sipush #-15809
    //   12915: sipush #-13310
    //   12918: invokestatic a : (II)Ljava/lang/String;
    //   12921: invokestatic forName : (Ljava/lang/String;)Ljava/lang/Class;
    //   12924: invokevirtual getDeclaredMethods : ()[Ljava/lang/reflect/Method;
    //   12927: astore #5
    //   12929: aload #5
    //   12931: arraylength
    //   12932: istore #6
    //   12934: iconst_0
    //   12935: istore #7
    //   12937: iload #7
    //   12939: iload #6
    //   12941: if_icmpge -> 13078
    //   12944: aload #5
    //   12946: iload #7
    //   12948: aaload
    //   12949: astore #8
    //   12951: aload #8
    //   12953: invokevirtual getParameterTypes : ()[Ljava/lang/Class;
    //   12956: pop
    //   12957: aload #8
    //   12959: invokevirtual getModifiers : ()I
    //   12962: invokestatic isStatic : (I)Z
    //   12965: ifeq -> 13064
    //   12968: aload #8
    //   12970: invokevirtual getParameterTypes : ()[Ljava/lang/Class;
    //   12973: arraylength
    //   12974: iconst_2
    //   12975: if_icmpne -> 13064
    //   12978: goto -> 12985
    //   12981: invokestatic a : (Ljava/lang/Throwable;)Ljava/lang/Throwable;
    //   12984: athrow
    //   12985: aload #8
    //   12987: invokevirtual getReturnType : ()Ljava/lang/Class;
    //   12990: getstatic java/lang/Boolean.TYPE : Ljava/lang/Class;
    //   12993: if_acmpne -> 13064
    //   12996: goto -> 13003
    //   12999: invokestatic a : (Ljava/lang/Throwable;)Ljava/lang/Throwable;
    //   13002: athrow
    //   13003: aload #8
    //   13005: iconst_1
    //   13006: invokevirtual setAccessible : (Z)V
    //   13009: aload #8
    //   13011: aconst_null
    //   13012: iconst_2
    //   13013: anewarray java/lang/Object
    //   13016: dup
    //   13017: iconst_0
    //   13018: aload_0
    //   13019: aastore
    //   13020: dup
    //   13021: iconst_1
    //   13022: aload_1
    //   13023: ifnonnull -> 13041
    //   13026: goto -> 13033
    //   13029: invokestatic a : (Ljava/lang/Throwable;)Ljava/lang/Throwable;
    //   13032: athrow
    //   13033: aload_1
    //   13034: goto -> 13048
    //   13037: invokestatic a : (Ljava/lang/Throwable;)Ljava/lang/Throwable;
    //   13040: athrow
    //   13041: aload_1
    //   13042: checkcast [B
    //   13045: invokevirtual clone : ()Ljava/lang/Object;
    //   13048: aastore
    //   13049: invokevirtual invoke : (Ljava/lang/Object;[Ljava/lang/Object;)Ljava/lang/Object;
    //   13052: checkcast java/lang/Boolean
    //   13055: invokevirtual booleanValue : ()Z
    //   13058: istore #4
    //   13060: iload_2
    //   13061: ifeq -> 13078
    //   13064: iinc #7, 1
    //   13067: iload_2
    //   13068: ifeq -> 12937
    //   13071: goto -> 13078
    //   13074: invokestatic a : (Ljava/lang/Throwable;)Ljava/lang/Throwable;
    //   13077: athrow
    //   13078: iload #4
    //   13080: ireturn
    //   13081: astore_3
    //   13082: new java/lang/Exception
    //   13085: dup
    //   13086: aload_3
    //   13087: invokevirtual getMessage : ()Ljava/lang/String;
    //   13090: invokespecial <init> : (Ljava/lang/String;)V
    //   13093: athrow
    // Exception table:
    //   from	to	target	type
    //   4	10880	13081	java/lang/Throwable
    //   40	214	217	java/lang/Throwable
    //   184	251	254	java/lang/Throwable
    //   221	288	291	java/lang/Throwable
    //   258	325	328	java/lang/Throwable
    //   295	362	365	java/lang/Throwable
    //   332	399	402	java/lang/Throwable
    //   369	436	439	java/lang/Throwable
    //   406	473	476	java/lang/Throwable
    //   443	510	513	java/lang/Throwable
    //   480	547	550	java/lang/Throwable
    //   517	584	587	java/lang/Throwable
    //   554	621	624	java/lang/Throwable
    //   591	658	661	java/lang/Throwable
    //   628	695	698	java/lang/Throwable
    //   665	732	735	java/lang/Throwable
    //   702	769	772	java/lang/Throwable
    //   739	806	809	java/lang/Throwable
    //   776	843	846	java/lang/Throwable
    //   813	880	883	java/lang/Throwable
    //   850	917	920	java/lang/Throwable
    //   887	954	957	java/lang/Throwable
    //   924	991	994	java/lang/Throwable
    //   961	1028	1031	java/lang/Throwable
    //   998	1065	1068	java/lang/Throwable
    //   1035	1102	1105	java/lang/Throwable
    //   1072	1139	1142	java/lang/Throwable
    //   1109	1176	1179	java/lang/Throwable
    //   1146	1213	1216	java/lang/Throwable
    //   1183	1250	1253	java/lang/Throwable
    //   1220	1287	1290	java/lang/Throwable
    //   1257	1324	1327	java/lang/Throwable
    //   1294	1357	1360	java/lang/Throwable
    //   4682	4707	4707	java/lang/Throwable
    //   5674	5700	5700	java/lang/Throwable
    //   5792	5806	5806	java/lang/Throwable
    //   5817	5830	5833	java/lang/Throwable
    //   5822	5845	5848	java/lang/Throwable
    //   5837	5863	5866	java/lang/Throwable
    //   5852	5893	5896	java/lang/Throwable
    //   5959	5986	5989	java/lang/Throwable
    //   5976	6007	6010	java/lang/Throwable
    //   5993	6037	6040	java/lang/Throwable
    //   6014	6048	6048	java/lang/Throwable
    //   6059	6075	6078	java/lang/Throwable
    //   6885	6919	6922	java/lang/Throwable
    //   7015	7093	7096	java/lang/Throwable
    //   7022	7236	7239	java/lang/Throwable
    //   7614	7629	7629	java/lang/Throwable
    //   7656	7690	7693	java/lang/Throwable
    //   7700	7712	7715	java/lang/Throwable
    //   7798	7876	7879	java/lang/Throwable
    //   7805	8019	8022	java/lang/Throwable
    //   8419	8497	8500	java/lang/Throwable
    //   8426	8640	8643	java/lang/Throwable
    //   9087	9121	9124	java/lang/Throwable
    //   9128	9140	9143	java/lang/Throwable
    //   9226	9304	9307	java/lang/Throwable
    //   9233	9447	9450	java/lang/Throwable
    //   10237	10251	10251	java/lang/Throwable
    //   10262	10275	10278	java/lang/Throwable
    //   10267	10290	10293	java/lang/Throwable
    //   10282	10308	10311	java/lang/Throwable
    //   10297	10338	10341	java/lang/Throwable
    //   10404	10431	10434	java/lang/Throwable
    //   10421	10449	10452	java/lang/Throwable
    //   10438	10479	10482	java/lang/Throwable
    //   10456	10490	10490	java/lang/Throwable
    //   10513	10524	10527	java/lang/Throwable
    //   10579	10593	10593	java/lang/Throwable
    //   10604	10617	10620	java/lang/Throwable
    //   10609	10632	10635	java/lang/Throwable
    //   10624	10650	10653	java/lang/Throwable
    //   10639	10680	10683	java/lang/Throwable
    //   10746	10773	10776	java/lang/Throwable
    //   10763	10791	10794	java/lang/Throwable
    //   10780	10821	10824	java/lang/Throwable
    //   10798	10832	10832	java/lang/Throwable
    //   10855	10866	10869	java/lang/Throwable
    //   10881	11615	13081	java/lang/Throwable
    //   10971	10985	10985	java/lang/Throwable
    //   10996	11009	11012	java/lang/Throwable
    //   11001	11024	11027	java/lang/Throwable
    //   11016	11042	11045	java/lang/Throwable
    //   11031	11072	11075	java/lang/Throwable
    //   11138	11165	11168	java/lang/Throwable
    //   11155	11183	11186	java/lang/Throwable
    //   11172	11213	11216	java/lang/Throwable
    //   11190	11224	11224	java/lang/Throwable
    //   11247	11258	11261	java/lang/Throwable
    //   11314	11328	11328	java/lang/Throwable
    //   11339	11352	11355	java/lang/Throwable
    //   11344	11367	11370	java/lang/Throwable
    //   11359	11385	11388	java/lang/Throwable
    //   11374	11415	11418	java/lang/Throwable
    //   11481	11508	11511	java/lang/Throwable
    //   11498	11526	11529	java/lang/Throwable
    //   11515	11556	11559	java/lang/Throwable
    //   11533	11567	11567	java/lang/Throwable
    //   11590	11601	11604	java/lang/Throwable
    //   11616	12350	13081	java/lang/Throwable
    //   11706	11720	11720	java/lang/Throwable
    //   11731	11744	11747	java/lang/Throwable
    //   11736	11759	11762	java/lang/Throwable
    //   11751	11777	11780	java/lang/Throwable
    //   11766	11807	11810	java/lang/Throwable
    //   11873	11900	11903	java/lang/Throwable
    //   11890	11918	11921	java/lang/Throwable
    //   11907	11948	11951	java/lang/Throwable
    //   11925	11959	11959	java/lang/Throwable
    //   11982	11993	11996	java/lang/Throwable
    //   12049	12063	12063	java/lang/Throwable
    //   12074	12087	12090	java/lang/Throwable
    //   12079	12102	12105	java/lang/Throwable
    //   12094	12120	12123	java/lang/Throwable
    //   12109	12150	12153	java/lang/Throwable
    //   12216	12243	12246	java/lang/Throwable
    //   12233	12261	12264	java/lang/Throwable
    //   12250	12291	12294	java/lang/Throwable
    //   12268	12302	12302	java/lang/Throwable
    //   12325	12336	12339	java/lang/Throwable
    //   12351	13080	13081	java/lang/Throwable
    //   12441	12455	12455	java/lang/Throwable
    //   12466	12479	12482	java/lang/Throwable
    //   12471	12494	12497	java/lang/Throwable
    //   12486	12512	12515	java/lang/Throwable
    //   12501	12542	12545	java/lang/Throwable
    //   12608	12635	12638	java/lang/Throwable
    //   12625	12653	12656	java/lang/Throwable
    //   12642	12683	12686	java/lang/Throwable
    //   12660	12694	12694	java/lang/Throwable
    //   12717	12728	12731	java/lang/Throwable
    //   12784	12798	12798	java/lang/Throwable
    //   12809	12822	12825	java/lang/Throwable
    //   12814	12837	12840	java/lang/Throwable
    //   12829	12855	12858	java/lang/Throwable
    //   12844	12885	12888	java/lang/Throwable
    //   12951	12978	12981	java/lang/Throwable
    //   12968	12996	12999	java/lang/Throwable
    //   12985	13026	13029	java/lang/Throwable
    //   13003	13037	13037	java/lang/Throwable
    //   13060	13071	13074	java/lang/Throwable
  }
  
  static void Zt(Object[] paramArrayOfObject, Object paramObject) throws Throwable {}
  
  static void Zr(Object paramObject) {
    Zefn.Ze = a(-15831, -19463);
    Zefn.ZJ = new BigInteger(a(-15822, 18069));
    boolean bool = Zt2e.ZN();
    try {
      try {
        if (Zewq.ZV.charAt(Math.abs(((BigInteger)Zewq.ZO).intValue() % 32)) <= Zzoc.Zg.charAt(Math.abs(((BigInteger)Zzoc.Zx).intValue() % 32))) {
          try {
            Zrfh.ZP(Class.forName(a(-15815, 7801)));
            if (!bool)
              Zkv2.Zc(Class.forName(a(-15811, -28936))); 
          } catch (Throwable throwable) {
            throw a(null);
          } 
          return;
        } 
      } catch (Throwable throwable) {
        throw a(null);
      } 
      Zkv2.Zc(Class.forName(a(-15811, -28936)));
    } catch (Throwable throwable) {}
  }
  
  static {
    // Byte code:
    //   0: bipush #27
    //   2: anewarray java/lang/String
    //   5: astore #5
    //   7: iconst_0
    //   8: istore_3
    //   9: ldc 'JaB_2\\tg57,uE\\t[\\fM><^\\tFvYWn\\t-BGV\\t,Pg\\tV(#\\tH/[t4\\t,Ye\\tj! \\b4\\f'#d3/|r<VyMr:Q_FE#3JpAC1DP@n%!seG$<EFn"B+jD4\\tS7m}\\n%\\t|pF\\t,g?&Fz^NE\\n\\t,gg}\\tQ9\\t^/)<} 9xIR2B!78M*m\\tf35\\tuqLol'
    //   11: dup
    //   12: astore_2
    //   13: invokevirtual length : ()I
    //   16: istore #4
    //   18: bipush #9
    //   20: istore_1
    //   21: iconst_m1
    //   22: istore_0
    //   23: bipush #42
    //   25: iinc #0, 1
    //   28: aload_2
    //   29: iload_0
    //   30: dup
    //   31: iload_1
    //   32: iadd
    //   33: invokevirtual substring : (II)Ljava/lang/String;
    //   36: iconst_m1
    //   37: goto -> 143
    //   40: aload #5
    //   42: swap
    //   43: iload_3
    //   44: iinc #3, 1
    //   47: swap
    //   48: aastore
    //   49: iload_0
    //   50: iload_1
    //   51: iadd
    //   52: dup
    //   53: istore_0
    //   54: iload #4
    //   56: if_icmpge -> 68
    //   59: aload_2
    //   60: iload_0
    //   61: invokevirtual charAt : (I)C
    //   64: istore_1
    //   65: goto -> 23
    //   68: ldc '^[k\\tQZ\\b@'
    //   70: dup
    //   71: astore_2
    //   72: invokevirtual length : ()I
    //   75: istore #4
    //   77: bipush #9
    //   79: istore_1
    //   80: iconst_m1
    //   81: istore_0
    //   82: bipush #87
    //   84: iinc #0, 1
    //   87: aload_2
    //   88: iload_0
    //   89: dup
    //   90: iload_1
    //   91: iadd
    //   92: invokevirtual substring : (II)Ljava/lang/String;
    //   95: iconst_0
    //   96: goto -> 143
    //   99: aload #5
    //   101: swap
    //   102: iload_3
    //   103: iinc #3, 1
    //   106: swap
    //   107: aastore
    //   108: iload_0
    //   109: iload_1
    //   110: iadd
    //   111: dup
    //   112: istore_0
    //   113: iload #4
    //   115: if_icmpge -> 127
    //   118: aload_2
    //   119: iload_0
    //   120: invokevirtual charAt : (I)C
    //   123: istore_1
    //   124: goto -> 82
    //   127: aload #5
    //   129: putstatic burp/Zkfb.a : [Ljava/lang/String;
    //   132: bipush #27
    //   134: anewarray java/lang/String
    //   137: putstatic burp/Zkfb.b : [Ljava/lang/String;
    //   140: goto -> 300
    //   143: dup_x2
    //   144: pop
    //   145: invokevirtual toCharArray : ()[C
    //   148: dup_x1
    //   149: arraylength
    //   150: dup_x2
    //   151: pop
    //   152: iconst_0
    //   153: istore #6
    //   155: dup2_x1
    //   156: pop2
    //   157: dup_x2
    //   158: iconst_1
    //   159: if_icmpgt -> 259
    //   162: dup2
    //   163: swap
    //   164: iload #6
    //   166: dup2_x1
    //   167: caload
    //   168: swap
    //   169: iload #6
    //   171: bipush #7
    //   173: irem
    //   174: tableswitch default -> 241, 0 -> 212, 1 -> 217, 2 -> 221, 3 -> 226, 4 -> 231, 5 -> 236
    //   212: bipush #28
    //   214: goto -> 243
    //   217: iconst_3
    //   218: goto -> 243
    //   221: bipush #82
    //   223: goto -> 243
    //   226: bipush #125
    //   228: goto -> 243
    //   231: bipush #17
    //   233: goto -> 243
    //   236: bipush #117
    //   238: goto -> 243
    //   241: bipush #69
    //   243: ixor
    //   244: ixor
    //   245: i2c
    //   246: castore
    //   247: iinc #6, 1
    //   250: dup
    //   251: ifne -> 259
    //   254: dup2
    //   255: dup_x1
    //   256: goto -> 166
    //   259: dup2_x1
    //   260: pop2
    //   261: dup_x2
    //   262: iload #6
    //   264: if_icmpgt -> 162
    //   267: pop
    //   268: new java/lang/String
    //   271: dup_x1
    //   272: swap
    //   273: invokespecial <init> : ([C)V
    //   276: invokevirtual intern : ()Ljava/lang/String;
    //   279: swap
    //   280: pop
    //   281: swap
    //   282: tableswitch default -> 40, 0 -> 99
    //   300: sipush #-15821
    //   303: sipush #19708
    //   306: invokestatic a : (II)Ljava/lang/String;
    //   309: putstatic burp/Zkfb.ZV : Ljava/lang/String;
    //   312: new java/math/BigInteger
    //   315: dup
    //   316: bipush #32
    //   318: newarray byte
    //   320: dup
    //   321: iconst_0
    //   322: bipush #14
    //   324: bastore
    //   325: dup
    //   326: iconst_1
    //   327: bipush #-84
    //   329: bastore
    //   330: dup
    //   331: iconst_2
    //   332: bipush #-41
    //   334: bastore
    //   335: dup
    //   336: iconst_3
    //   337: bipush #-67
    //   339: bastore
    //   340: dup
    //   341: iconst_4
    //   342: bipush #-42
    //   344: bastore
    //   345: dup
    //   346: iconst_5
    //   347: bipush #56
    //   349: bastore
    //   350: dup
    //   351: bipush #6
    //   353: bipush #-26
    //   355: bastore
    //   356: dup
    //   357: bipush #7
    //   359: bipush #-26
    //   361: bastore
    //   362: dup
    //   363: bipush #8
    //   365: bipush #-100
    //   367: bastore
    //   368: dup
    //   369: bipush #9
    //   371: bipush #-109
    //   373: bastore
    //   374: dup
    //   375: bipush #10
    //   377: bipush #-96
    //   379: bastore
    //   380: dup
    //   381: bipush #11
    //   383: bipush #-95
    //   385: bastore
    //   386: dup
    //   387: bipush #12
    //   389: bipush #-81
    //   391: bastore
    //   392: dup
    //   393: bipush #13
    //   395: bipush #62
    //   397: bastore
    //   398: dup
    //   399: bipush #14
    //   401: bipush #120
    //   403: bastore
    //   404: dup
    //   405: bipush #15
    //   407: bipush #-92
    //   409: bastore
    //   410: dup
    //   411: bipush #16
    //   413: bipush #-99
    //   415: bastore
    //   416: dup
    //   417: bipush #17
    //   419: bipush #-100
    //   421: bastore
    //   422: dup
    //   423: bipush #18
    //   425: bipush #-84
    //   427: bastore
    //   428: dup
    //   429: bipush #19
    //   431: bipush #-81
    //   433: bastore
    //   434: dup
    //   435: bipush #20
    //   437: bipush #40
    //   439: bastore
    //   440: dup
    //   441: bipush #21
    //   443: bipush #-103
    //   445: bastore
    //   446: dup
    //   447: bipush #22
    //   449: bipush #17
    //   451: bastore
    //   452: dup
    //   453: bipush #23
    //   455: bipush #19
    //   457: bastore
    //   458: dup
    //   459: bipush #24
    //   461: bipush #47
    //   463: bastore
    //   464: dup
    //   465: bipush #25
    //   467: bipush #-113
    //   469: bastore
    //   470: dup
    //   471: bipush #26
    //   473: bipush #125
    //   475: bastore
    //   476: dup
    //   477: bipush #27
    //   479: bipush #112
    //   481: bastore
    //   482: dup
    //   483: bipush #28
    //   485: bipush #76
    //   487: bastore
    //   488: dup
    //   489: bipush #29
    //   491: bipush #21
    //   493: bastore
    //   494: dup
    //   495: bipush #30
    //   497: bipush #-72
    //   499: bastore
    //   500: dup
    //   501: bipush #31
    //   503: bipush #-42
    //   505: bastore
    //   506: invokespecial <init> : ([B)V
    //   509: putstatic burp/Zkfb.ZN : Ljava/lang/Object;
    //   512: return
  }
  
  private static Throwable a(Throwable paramThrowable) {
    return paramThrowable;
  }
  
  private static String a(int paramInt1, int paramInt2) {
    int i = (paramInt1 ^ 0xFFFFC23F) & 0xFFFF;
    if (b[i] == null) {
      char[] arrayOfChar = a[i].toCharArray();
      switch (arrayOfChar[0] & 0xFF) {
        case 0:
        
        case 1:
        
        case 2:
        
        case 3:
        
        case 4:
        
        case 5:
        
        case 6:
        
        case 7:
        
        case 8:
        
        case 9:
        
        case 10:
        
        case 11:
        
        case 12:
        
        case 13:
        
        case 14:
        
        case 15:
        
        case 16:
        
        case 17:
        
        case 18:
        
        case 19:
        
        case 20:
        
        case 21:
        
        case 22:
        
        case 23:
        
        case 24:
        
        case 25:
        
        case 26:
        
        case 27:
        
        case 28:
        
        case 29:
        
        case 30:
        
        case 31:
        
        case 32:
        
        case 33:
        
        case 34:
        
        case 35:
        
        case 36:
        
        case 37:
        
        case 38:
        
        case 39:
        
        case 40:
        
        case 41:
        
        case 42:
        
        case 43:
        
        case 44:
        
        case 45:
        
        case 46:
        
        case 47:
        
        case 48:
        
        case 49:
        
        case 50:
        
        case 51:
        
        case 52:
        
        case 53:
        
        case 54:
        
        case 55:
        
        case 56:
        
        case 57:
        
        case 58:
        
        case 59:
        
        case 60:
        
        case 61:
        
        case 62:
        
        case 63:
        
        case 64:
        
        case 65:
        
        case 66:
        
        case 67:
        
        case 68:
        
        case 69:
        
        case 70:
        
        case 71:
        
        case 72:
        
        case 73:
        
        case 74:
        
        case 75:
        
        case 76:
        
        case 77:
        
        case 78:
        
        case 79:
        
        case 80:
        
        case 81:
        
        case 82:
        
        case 83:
        
        case 84:
        
        case 85:
        
        case 86:
        
        case 87:
        
        case 88:
        
        case 89:
        
        case 90:
        
        case 91:
        
        case 92:
        
        case 93:
        
        case 94:
        
        case 95:
        
        case 96:
        
        case 97:
        
        case 98:
        
        case 99:
        
        case 100:
        
        case 101:
        
        case 102:
        
        case 103:
        
        case 104:
        
        case 105:
        
        case 106:
        
        case 107:
        
        case 108:
        
        case 109:
        
        case 110:
        
        case 111:
        
        case 112:
        
        case 113:
        
        case 114:
        
        case 115:
        
        case 116:
        
        case 117:
        
        case 118:
        
        case 119:
        
        case 120:
        
        case 121:
        
        case 122:
        
        case 123:
        
        case 124:
        
        case 125:
        
        case 126:
        
        case 127:
        
        case 128:
        
        case 129:
        
        case 130:
        
        case 131:
        
        case 132:
        
        case 133:
        
        case 134:
        
        case 135:
        
        case 136:
        
        case 137:
        
        case 138:
        
        case 139:
        
        case 140:
        
        case 141:
        
        case 142:
        
        case 143:
        
        case 144:
        
        case 145:
        
        case 146:
        
        case 147:
        
        case 148:
        
        case 149:
        
        case 150:
        
        case 151:
        
        case 152:
        
        case 153:
        
        case 154:
        
        case 155:
        
        case 156:
        
        case 157:
        
        case 158:
        
        case 159:
        
        case 160:
        
        case 161:
        
        case 162:
        
        case 163:
        
        case 164:
        
        case 165:
        
        case 166:
        
        case 167:
        
        case 168:
        
        case 169:
        
        case 170:
        
        case 171:
        
        case 172:
        
        case 173:
        
        case 174:
        
        case 175:
        
        case 176:
        
        case 177:
        
        case 178:
        
        case 179:
        
        case 180:
        
        case 181:
        
        case 182:
        
        case 183:
        
        case 184:
        
        case 185:
        
        case 186:
        
        case 187:
        
        case 188:
        
        case 189:
        
        case 190:
        
        case 191:
        
        case 192:
        
        case 193:
        
        case 194:
        
        case 195:
        
        case 196:
        
        case 197:
        
        case 198:
        
        case 199:
        
        case 200:
        
        case 201:
        
        case 202:
        
        case 203:
        
        case 204:
        
        case 205:
        
        case 206:
        
        case 207:
        
        case 208:
        
        case 209:
        
        case 210:
        
        case 211:
        
        case 212:
        
        case 213:
        
        case 214:
        
        case 215:
        
        case 216:
        
        case 217:
        
        case 218:
        
        case 219:
        
        case 220:
        
        case 221:
        
        case 222:
        
        case 223:
        
        case 224:
        
        case 225:
        
        case 226:
        
        case 227:
        
        case 228:
        
        case 229:
        
        case 230:
        
        case 231:
        
        case 232:
        
        case 233:
        
        case 234:
        
        case 235:
        
        case 236:
        
        case 237:
        
        case 238:
        
        case 239:
        
        case 240:
        
        case 241:
        
        case 242:
        
        case 243:
        
        case 244:
        
        case 245:
        
        case 246:
        
        case 247:
        
        case 248:
        
        case 249:
        
        case 250:
        
        case 251:
        
        case 252:
        
        case 253:
        
        case 254:
        
        default:
          break;
      } 
      byte b1 = 61;
      int j = (paramInt2 & 0xFF) - b1;
      if (j < 0)
        j += 256; 
      int k = ((paramInt2 & 0xFFFF) >>> 8) - b1;
      if (k < 0)
        k += 256; 
      for (byte b2 = 0; b2 < arrayOfChar.length; b2++) {
        int m = b2 % 2;
        if (m == 0) {
          arrayOfChar[b2] = (char)(arrayOfChar[b2] ^ j);
          j = ((j >>> 3 | j << 5) ^ arrayOfChar[b2]) & 0xFF;
        } else {
          arrayOfChar[b2] = (char)(arrayOfChar[b2] ^ k);
          k = ((k >>> 3 | k << 5) ^ arrayOfChar[b2]) & 0xFF;
        } 
      } 
      b[i] = (new String(arrayOfChar)).intern();
    } 
    return b[i];
  }
}


/* Location:              C:\Program Files\BurpSuitePro\burpsuite_pro.jar!\burp\Zkfb.class
 * Java compiler version: 21 (65.0)
 * JD-Core Version:       1.1.3
 */