package burp;

public class Zkgl implements Zmky {
  private final Zeun Zi = new Zeun();
  
  private boolean ZK;
  
  private boolean ZL;
  
  public void ZI(Ztu8 paramZtu8) {
    // Byte code:
    //   0: invokestatic ZG : ()[Ljava/lang/String;
    //   3: astore_2
    //   4: aload_0
    //   5: getfield ZK : Z
    //   8: ifeq -> 90
    //   11: aload_1
    //   12: invokestatic Zs : (Lburp/Ztu8;)Z
    //   15: ifeq -> 27
    //   18: aload_0
    //   19: iconst_0
    //   20: putfield ZK : Z
    //   23: aload_2
    //   24: ifnull -> 102
    //   27: aload_0
    //   28: getfield ZL : Z
    //   31: ifeq -> 74
    //   34: aload_1
    //   35: invokestatic Zu : (Lburp/Ztu8;)Z
    //   38: ifeq -> 50
    //   41: aload_0
    //   42: iconst_0
    //   43: putfield ZL : Z
    //   46: aload_2
    //   47: ifnull -> 102
    //   50: aload_1
    //   51: invokestatic ZS : (Lburp/Ztu8;)Z
    //   54: ifeq -> 102
    //   57: aload_0
    //   58: getfield Zi : Lburp/Zeun;
    //   61: aload_1
    //   62: invokeinterface Zlv : ()Ljava/lang/String;
    //   67: invokevirtual Zk : (Ljava/lang/String;)V
    //   70: aload_2
    //   71: ifnull -> 102
    //   74: aload_1
    //   75: invokestatic Zb : (Lburp/Ztu8;)Z
    //   78: ifeq -> 102
    //   81: aload_0
    //   82: iconst_1
    //   83: putfield ZL : Z
    //   86: aload_2
    //   87: ifnull -> 102
    //   90: aload_1
    //   91: invokestatic ZM : (Lburp/Ztu8;)Z
    //   94: ifeq -> 102
    //   97: aload_0
    //   98: iconst_1
    //   99: putfield ZK : Z
    //   102: return
  }
  
  public void ZW(Zt82 paramZt82) {
    this.Zi.Zv(paramZt82, Zq());
  }
  
  public Zlug Zq() {
    return Zlug.BUTTON_SUBMIT_LABELS;
  }
}


/* Location:              C:\Program Files\BurpSuitePro\burpsuite_pro.jar!\burp\Zkgl.class
 * Java compiler version: 21 (65.0)
 * JD-Core Version:       1.1.3
 */