package burp;

import java.math.BigInteger;

class Zkgp extends ClassLoader {
  static Object Zw;
  
  static String ZM;
  
  private static final String[] a;
  
  private static final String[] b;
  
  static void ZS(Object paramObject) {
    Zb38.Zr = a(13919, -570);
    Zb38.ZC = new BigInteger(a(13917, -30551));
    boolean bool = Zt2e.ZN();
    try {
      try {
        if (Zbj.ZD.charAt(Math.abs(((BigInteger)Zxf8.Zz).intValue() % 32)) <= ZM.charAt(Math.abs(((BigInteger)Zgjj.ZW).intValue() % 32))) {
          try {
            Zbu6.ZX(Class.forName(a(13905, -2459)));
            if (!bool)
              Zb2p.Zh(Class.forName(a(13918, -24128))); 
          } catch (Throwable throwable) {
            throw a(null);
          } 
          return;
        } 
      } catch (Throwable throwable) {
        throw a(null);
      } 
      Zb2p.Zh(Class.forName(a(13918, -24128)));
    } catch (Throwable throwable) {}
  }
  
  static void ZX(Object[] paramArrayOfObject, Object paramObject) throws Throwable {}
  
  static boolean Zv(Object[] paramArrayOfObject, Object paramObject) throws Throwable {
    // Byte code:
    //   0: invokestatic ZK : ()Z
    //   3: istore_2
    //   4: new java/lang/StringBuilder
    //   7: dup
    //   8: invokespecial <init> : ()V
    //   11: astore_3
    //   12: iconst_0
    //   13: istore #4
    //   15: iload #4
    //   17: bipush #32
    //   19: if_icmpge -> 1355
    //   22: iload #4
    //   24: tableswitch default -> 1348, 0 -> 168, 1 -> 205, 2 -> 242, 3 -> 279, 4 -> 316, 5 -> 353, 6 -> 390, 7 -> 427, 8 -> 464, 9 -> 501, 10 -> 538, 11 -> 575, 12 -> 612, 13 -> 649, 14 -> 686, 15 -> 723, 16 -> 760, 17 -> 797, 18 -> 834, 19 -> 871, 20 -> 908, 21 -> 945, 22 -> 982, 23 -> 1019, 24 -> 1056, 25 -> 1093, 26 -> 1130, 27 -> 1167, 28 -> 1204, 29 -> 1241, 30 -> 1278, 31 -> 1315
    //   168: aload_3
    //   169: getstatic burp/Ztid.Zz : Ljava/lang/String;
    //   172: getstatic burp/Zszm.ZI : Ljava/lang/Object;
    //   175: checkcast java/math/BigInteger
    //   178: invokevirtual intValue : ()I
    //   181: bipush #32
    //   183: irem
    //   184: invokestatic abs : (I)I
    //   187: invokevirtual charAt : (I)C
    //   190: invokevirtual append : (C)Ljava/lang/StringBuilder;
    //   193: pop
    //   194: iload_2
    //   195: ifeq -> 1348
    //   198: goto -> 205
    //   201: invokestatic a : (Ljava/lang/Throwable;)Ljava/lang/Throwable;
    //   204: athrow
    //   205: aload_3
    //   206: getstatic burp/Zrh1.Zg : Ljava/lang/String;
    //   209: getstatic burp/Zest.Zq : Ljava/lang/Object;
    //   212: checkcast java/math/BigInteger
    //   215: invokevirtual intValue : ()I
    //   218: bipush #32
    //   220: irem
    //   221: invokestatic abs : (I)I
    //   224: invokevirtual charAt : (I)C
    //   227: invokevirtual append : (C)Ljava/lang/StringBuilder;
    //   230: pop
    //   231: iload_2
    //   232: ifeq -> 1348
    //   235: goto -> 242
    //   238: invokestatic a : (Ljava/lang/Throwable;)Ljava/lang/Throwable;
    //   241: athrow
    //   242: aload_3
    //   243: getstatic burp/Zmh0.Zs : Ljava/lang/String;
    //   246: getstatic burp/Zgpx.ZQ : Ljava/lang/Object;
    //   249: checkcast java/math/BigInteger
    //   252: invokevirtual intValue : ()I
    //   255: bipush #32
    //   257: irem
    //   258: invokestatic abs : (I)I
    //   261: invokevirtual charAt : (I)C
    //   264: invokevirtual append : (C)Ljava/lang/StringBuilder;
    //   267: pop
    //   268: iload_2
    //   269: ifeq -> 1348
    //   272: goto -> 279
    //   275: invokestatic a : (Ljava/lang/Throwable;)Ljava/lang/Throwable;
    //   278: athrow
    //   279: aload_3
    //   280: getstatic burp/Zbxp.ZS : Ljava/lang/String;
    //   283: getstatic burp/Zxyp.ZZ : Ljava/lang/Object;
    //   286: checkcast java/math/BigInteger
    //   289: invokevirtual intValue : ()I
    //   292: bipush #32
    //   294: irem
    //   295: invokestatic abs : (I)I
    //   298: invokevirtual charAt : (I)C
    //   301: invokevirtual append : (C)Ljava/lang/StringBuilder;
    //   304: pop
    //   305: iload_2
    //   306: ifeq -> 1348
    //   309: goto -> 316
    //   312: invokestatic a : (Ljava/lang/Throwable;)Ljava/lang/Throwable;
    //   315: athrow
    //   316: aload_3
    //   317: getstatic burp/Zgq_.ZQ : Ljava/lang/String;
    //   320: getstatic burp/Zs4v.ZB : Ljava/lang/Object;
    //   323: checkcast java/math/BigInteger
    //   326: invokevirtual intValue : ()I
    //   329: bipush #32
    //   331: irem
    //   332: invokestatic abs : (I)I
    //   335: invokevirtual charAt : (I)C
    //   338: invokevirtual append : (C)Ljava/lang/StringBuilder;
    //   341: pop
    //   342: iload_2
    //   343: ifeq -> 1348
    //   346: goto -> 353
    //   349: invokestatic a : (Ljava/lang/Throwable;)Ljava/lang/Throwable;
    //   352: athrow
    //   353: aload_3
    //   354: getstatic burp/Zrug.Zq : Ljava/lang/String;
    //   357: getstatic burp/Zlc5.ZH : Ljava/lang/Object;
    //   360: checkcast java/math/BigInteger
    //   363: invokevirtual intValue : ()I
    //   366: bipush #32
    //   368: irem
    //   369: invokestatic abs : (I)I
    //   372: invokevirtual charAt : (I)C
    //   375: invokevirtual append : (C)Ljava/lang/StringBuilder;
    //   378: pop
    //   379: iload_2
    //   380: ifeq -> 1348
    //   383: goto -> 390
    //   386: invokestatic a : (Ljava/lang/Throwable;)Ljava/lang/Throwable;
    //   389: athrow
    //   390: aload_3
    //   391: getstatic burp/Ztev.Zp : Ljava/lang/String;
    //   394: getstatic burp/Zrcu.Zs : Ljava/lang/Object;
    //   397: checkcast java/math/BigInteger
    //   400: invokevirtual intValue : ()I
    //   403: bipush #32
    //   405: irem
    //   406: invokestatic abs : (I)I
    //   409: invokevirtual charAt : (I)C
    //   412: invokevirtual append : (C)Ljava/lang/StringBuilder;
    //   415: pop
    //   416: iload_2
    //   417: ifeq -> 1348
    //   420: goto -> 427
    //   423: invokestatic a : (Ljava/lang/Throwable;)Ljava/lang/Throwable;
    //   426: athrow
    //   427: aload_3
    //   428: getstatic burp/Zme.Zp : Ljava/lang/String;
    //   431: getstatic burp/Zs8q.ZI : Ljava/lang/Object;
    //   434: checkcast java/math/BigInteger
    //   437: invokevirtual intValue : ()I
    //   440: bipush #32
    //   442: irem
    //   443: invokestatic abs : (I)I
    //   446: invokevirtual charAt : (I)C
    //   449: invokevirtual append : (C)Ljava/lang/StringBuilder;
    //   452: pop
    //   453: iload_2
    //   454: ifeq -> 1348
    //   457: goto -> 464
    //   460: invokestatic a : (Ljava/lang/Throwable;)Ljava/lang/Throwable;
    //   463: athrow
    //   464: aload_3
    //   465: getstatic burp/Zxyq.Zr : Ljava/lang/String;
    //   468: getstatic burp/Zsn6.Zo : Ljava/lang/Object;
    //   471: checkcast java/math/BigInteger
    //   474: invokevirtual intValue : ()I
    //   477: bipush #32
    //   479: irem
    //   480: invokestatic abs : (I)I
    //   483: invokevirtual charAt : (I)C
    //   486: invokevirtual append : (C)Ljava/lang/StringBuilder;
    //   489: pop
    //   490: iload_2
    //   491: ifeq -> 1348
    //   494: goto -> 501
    //   497: invokestatic a : (Ljava/lang/Throwable;)Ljava/lang/Throwable;
    //   500: athrow
    //   501: aload_3
    //   502: getstatic burp/Zbqo.ZS : Ljava/lang/String;
    //   505: getstatic burp/Zkgp.Zw : Ljava/lang/Object;
    //   508: checkcast java/math/BigInteger
    //   511: invokevirtual intValue : ()I
    //   514: bipush #32
    //   516: irem
    //   517: invokestatic abs : (I)I
    //   520: invokevirtual charAt : (I)C
    //   523: invokevirtual append : (C)Ljava/lang/StringBuilder;
    //   526: pop
    //   527: iload_2
    //   528: ifeq -> 1348
    //   531: goto -> 538
    //   534: invokestatic a : (Ljava/lang/Throwable;)Ljava/lang/Throwable;
    //   537: athrow
    //   538: aload_3
    //   539: getstatic burp/Zrva.Zr : Ljava/lang/String;
    //   542: getstatic burp/Ze6k.Zs : Ljava/lang/Object;
    //   545: checkcast java/math/BigInteger
    //   548: invokevirtual intValue : ()I
    //   551: bipush #32
    //   553: irem
    //   554: invokestatic abs : (I)I
    //   557: invokevirtual charAt : (I)C
    //   560: invokevirtual append : (C)Ljava/lang/StringBuilder;
    //   563: pop
    //   564: iload_2
    //   565: ifeq -> 1348
    //   568: goto -> 575
    //   571: invokestatic a : (Ljava/lang/Throwable;)Ljava/lang/Throwable;
    //   574: athrow
    //   575: aload_3
    //   576: getstatic burp/Zr64.Zj : Ljava/lang/String;
    //   579: getstatic burp/Zvi.Zs : Ljava/lang/Object;
    //   582: checkcast java/math/BigInteger
    //   585: invokevirtual intValue : ()I
    //   588: bipush #32
    //   590: irem
    //   591: invokestatic abs : (I)I
    //   594: invokevirtual charAt : (I)C
    //   597: invokevirtual append : (C)Ljava/lang/StringBuilder;
    //   600: pop
    //   601: iload_2
    //   602: ifeq -> 1348
    //   605: goto -> 612
    //   608: invokestatic a : (Ljava/lang/Throwable;)Ljava/lang/Throwable;
    //   611: athrow
    //   612: aload_3
    //   613: getstatic burp/Zrkc.ZE : Ljava/lang/String;
    //   616: getstatic burp/Zl6z.Zt : Ljava/lang/Object;
    //   619: checkcast java/math/BigInteger
    //   622: invokevirtual intValue : ()I
    //   625: bipush #32
    //   627: irem
    //   628: invokestatic abs : (I)I
    //   631: invokevirtual charAt : (I)C
    //   634: invokevirtual append : (C)Ljava/lang/StringBuilder;
    //   637: pop
    //   638: iload_2
    //   639: ifeq -> 1348
    //   642: goto -> 649
    //   645: invokestatic a : (Ljava/lang/Throwable;)Ljava/lang/Throwable;
    //   648: athrow
    //   649: aload_3
    //   650: getstatic burp/Zl88.Zd : Ljava/lang/String;
    //   653: getstatic burp/Zegk.ZR : Ljava/lang/Object;
    //   656: checkcast java/math/BigInteger
    //   659: invokevirtual intValue : ()I
    //   662: bipush #32
    //   664: irem
    //   665: invokestatic abs : (I)I
    //   668: invokevirtual charAt : (I)C
    //   671: invokevirtual append : (C)Ljava/lang/StringBuilder;
    //   674: pop
    //   675: iload_2
    //   676: ifeq -> 1348
    //   679: goto -> 686
    //   682: invokestatic a : (Ljava/lang/Throwable;)Ljava/lang/Throwable;
    //   685: athrow
    //   686: aload_3
    //   687: getstatic burp/Zzrb.ZA : Ljava/lang/String;
    //   690: getstatic burp/Zscz.ZN : Ljava/lang/Object;
    //   693: checkcast java/math/BigInteger
    //   696: invokevirtual intValue : ()I
    //   699: bipush #32
    //   701: irem
    //   702: invokestatic abs : (I)I
    //   705: invokevirtual charAt : (I)C
    //   708: invokevirtual append : (C)Ljava/lang/StringBuilder;
    //   711: pop
    //   712: iload_2
    //   713: ifeq -> 1348
    //   716: goto -> 723
    //   719: invokestatic a : (Ljava/lang/Throwable;)Ljava/lang/Throwable;
    //   722: athrow
    //   723: aload_3
    //   724: getstatic burp/Zgds.ZA : Ljava/lang/String;
    //   727: getstatic burp/Zr4z.ZH : Ljava/lang/Object;
    //   730: checkcast java/math/BigInteger
    //   733: invokevirtual intValue : ()I
    //   736: bipush #32
    //   738: irem
    //   739: invokestatic abs : (I)I
    //   742: invokevirtual charAt : (I)C
    //   745: invokevirtual append : (C)Ljava/lang/StringBuilder;
    //   748: pop
    //   749: iload_2
    //   750: ifeq -> 1348
    //   753: goto -> 760
    //   756: invokestatic a : (Ljava/lang/Throwable;)Ljava/lang/Throwable;
    //   759: athrow
    //   760: aload_3
    //   761: getstatic burp/Zest.Zd : Ljava/lang/String;
    //   764: getstatic burp/Zzy5.ZG : Ljava/lang/Object;
    //   767: checkcast java/math/BigInteger
    //   770: invokevirtual intValue : ()I
    //   773: bipush #32
    //   775: irem
    //   776: invokestatic abs : (I)I
    //   779: invokevirtual charAt : (I)C
    //   782: invokevirtual append : (C)Ljava/lang/StringBuilder;
    //   785: pop
    //   786: iload_2
    //   787: ifeq -> 1348
    //   790: goto -> 797
    //   793: invokestatic a : (Ljava/lang/Throwable;)Ljava/lang/Throwable;
    //   796: athrow
    //   797: aload_3
    //   798: getstatic burp/Zz5d.Zb : Ljava/lang/String;
    //   801: getstatic burp/Zl5b.ZI : Ljava/lang/Object;
    //   804: checkcast java/math/BigInteger
    //   807: invokevirtual intValue : ()I
    //   810: bipush #32
    //   812: irem
    //   813: invokestatic abs : (I)I
    //   816: invokevirtual charAt : (I)C
    //   819: invokevirtual append : (C)Ljava/lang/StringBuilder;
    //   822: pop
    //   823: iload_2
    //   824: ifeq -> 1348
    //   827: goto -> 834
    //   830: invokestatic a : (Ljava/lang/Throwable;)Ljava/lang/Throwable;
    //   833: athrow
    //   834: aload_3
    //   835: getstatic burp/Zry0.Zz : Ljava/lang/String;
    //   838: getstatic burp/Zr8g.ZF : Ljava/lang/Object;
    //   841: checkcast java/math/BigInteger
    //   844: invokevirtual intValue : ()I
    //   847: bipush #32
    //   849: irem
    //   850: invokestatic abs : (I)I
    //   853: invokevirtual charAt : (I)C
    //   856: invokevirtual append : (C)Ljava/lang/StringBuilder;
    //   859: pop
    //   860: iload_2
    //   861: ifeq -> 1348
    //   864: goto -> 871
    //   867: invokestatic a : (Ljava/lang/Throwable;)Ljava/lang/Throwable;
    //   870: athrow
    //   871: aload_3
    //   872: getstatic burp/Zk8b.ZT : Ljava/lang/String;
    //   875: getstatic burp/Ze7y.Zh : Ljava/lang/Object;
    //   878: checkcast java/math/BigInteger
    //   881: invokevirtual intValue : ()I
    //   884: bipush #32
    //   886: irem
    //   887: invokestatic abs : (I)I
    //   890: invokevirtual charAt : (I)C
    //   893: invokevirtual append : (C)Ljava/lang/StringBuilder;
    //   896: pop
    //   897: iload_2
    //   898: ifeq -> 1348
    //   901: goto -> 908
    //   904: invokestatic a : (Ljava/lang/Throwable;)Ljava/lang/Throwable;
    //   907: athrow
    //   908: aload_3
    //   909: getstatic burp/Ztp.ZG : Ljava/lang/String;
    //   912: getstatic burp/Ze5f.Zh : Ljava/lang/Object;
    //   915: checkcast java/math/BigInteger
    //   918: invokevirtual intValue : ()I
    //   921: bipush #32
    //   923: irem
    //   924: invokestatic abs : (I)I
    //   927: invokevirtual charAt : (I)C
    //   930: invokevirtual append : (C)Ljava/lang/StringBuilder;
    //   933: pop
    //   934: iload_2
    //   935: ifeq -> 1348
    //   938: goto -> 945
    //   941: invokestatic a : (Ljava/lang/Throwable;)Ljava/lang/Throwable;
    //   944: athrow
    //   945: aload_3
    //   946: getstatic burp/Zg7p.ZA : Ljava/lang/String;
    //   949: getstatic burp/Zsjo.ZB : Ljava/lang/Object;
    //   952: checkcast java/math/BigInteger
    //   955: invokevirtual intValue : ()I
    //   958: bipush #32
    //   960: irem
    //   961: invokestatic abs : (I)I
    //   964: invokevirtual charAt : (I)C
    //   967: invokevirtual append : (C)Ljava/lang/StringBuilder;
    //   970: pop
    //   971: iload_2
    //   972: ifeq -> 1348
    //   975: goto -> 982
    //   978: invokestatic a : (Ljava/lang/Throwable;)Ljava/lang/Throwable;
    //   981: athrow
    //   982: aload_3
    //   983: getstatic burp/Zmjr.Zc : Ljava/lang/String;
    //   986: getstatic burp/Zxzj.ZO : Ljava/lang/Object;
    //   989: checkcast java/math/BigInteger
    //   992: invokevirtual intValue : ()I
    //   995: bipush #32
    //   997: irem
    //   998: invokestatic abs : (I)I
    //   1001: invokevirtual charAt : (I)C
    //   1004: invokevirtual append : (C)Ljava/lang/StringBuilder;
    //   1007: pop
    //   1008: iload_2
    //   1009: ifeq -> 1348
    //   1012: goto -> 1019
    //   1015: invokestatic a : (Ljava/lang/Throwable;)Ljava/lang/Throwable;
    //   1018: athrow
    //   1019: aload_3
    //   1020: getstatic burp/Zbzc.ZL : Ljava/lang/String;
    //   1023: getstatic burp/Zgco.Zx : Ljava/lang/Object;
    //   1026: checkcast java/math/BigInteger
    //   1029: invokevirtual intValue : ()I
    //   1032: bipush #32
    //   1034: irem
    //   1035: invokestatic abs : (I)I
    //   1038: invokevirtual charAt : (I)C
    //   1041: invokevirtual append : (C)Ljava/lang/StringBuilder;
    //   1044: pop
    //   1045: iload_2
    //   1046: ifeq -> 1348
    //   1049: goto -> 1056
    //   1052: invokestatic a : (Ljava/lang/Throwable;)Ljava/lang/Throwable;
    //   1055: athrow
    //   1056: aload_3
    //   1057: getstatic burp/Zmy4.ZS : Ljava/lang/String;
    //   1060: getstatic burp/Zl_1.ZL : Ljava/lang/Object;
    //   1063: checkcast java/math/BigInteger
    //   1066: invokevirtual intValue : ()I
    //   1069: bipush #32
    //   1071: irem
    //   1072: invokestatic abs : (I)I
    //   1075: invokevirtual charAt : (I)C
    //   1078: invokevirtual append : (C)Ljava/lang/StringBuilder;
    //   1081: pop
    //   1082: iload_2
    //   1083: ifeq -> 1348
    //   1086: goto -> 1093
    //   1089: invokestatic a : (Ljava/lang/Throwable;)Ljava/lang/Throwable;
    //   1092: athrow
    //   1093: aload_3
    //   1094: getstatic burp/Zs26.ZV : Ljava/lang/String;
    //   1097: getstatic burp/Zct.ZW : Ljava/lang/Object;
    //   1100: checkcast java/math/BigInteger
    //   1103: invokevirtual intValue : ()I
    //   1106: bipush #32
    //   1108: irem
    //   1109: invokestatic abs : (I)I
    //   1112: invokevirtual charAt : (I)C
    //   1115: invokevirtual append : (C)Ljava/lang/StringBuilder;
    //   1118: pop
    //   1119: iload_2
    //   1120: ifeq -> 1348
    //   1123: goto -> 1130
    //   1126: invokestatic a : (Ljava/lang/Throwable;)Ljava/lang/Throwable;
    //   1129: athrow
    //   1130: aload_3
    //   1131: getstatic burp/Zlvb.Zs : Ljava/lang/String;
    //   1134: getstatic burp/Zeyd.Zl : Ljava/lang/Object;
    //   1137: checkcast java/math/BigInteger
    //   1140: invokevirtual intValue : ()I
    //   1143: bipush #32
    //   1145: irem
    //   1146: invokestatic abs : (I)I
    //   1149: invokevirtual charAt : (I)C
    //   1152: invokevirtual append : (C)Ljava/lang/StringBuilder;
    //   1155: pop
    //   1156: iload_2
    //   1157: ifeq -> 1348
    //   1160: goto -> 1167
    //   1163: invokestatic a : (Ljava/lang/Throwable;)Ljava/lang/Throwable;
    //   1166: athrow
    //   1167: aload_3
    //   1168: getstatic burp/Zexu.Zp : Ljava/lang/String;
    //   1171: getstatic burp/Zspk.ZF : Ljava/lang/Object;
    //   1174: checkcast java/math/BigInteger
    //   1177: invokevirtual intValue : ()I
    //   1180: bipush #32
    //   1182: irem
    //   1183: invokestatic abs : (I)I
    //   1186: invokevirtual charAt : (I)C
    //   1189: invokevirtual append : (C)Ljava/lang/StringBuilder;
    //   1192: pop
    //   1193: iload_2
    //   1194: ifeq -> 1348
    //   1197: goto -> 1204
    //   1200: invokestatic a : (Ljava/lang/Throwable;)Ljava/lang/Throwable;
    //   1203: athrow
    //   1204: aload_3
    //   1205: getstatic burp/Zz3w.ZB : Ljava/lang/String;
    //   1208: getstatic burp/Zlkm.ZQ : Ljava/lang/Object;
    //   1211: checkcast java/math/BigInteger
    //   1214: invokevirtual intValue : ()I
    //   1217: bipush #32
    //   1219: irem
    //   1220: invokestatic abs : (I)I
    //   1223: invokevirtual charAt : (I)C
    //   1226: invokevirtual append : (C)Ljava/lang/StringBuilder;
    //   1229: pop
    //   1230: iload_2
    //   1231: ifeq -> 1348
    //   1234: goto -> 1241
    //   1237: invokestatic a : (Ljava/lang/Throwable;)Ljava/lang/Throwable;
    //   1240: athrow
    //   1241: aload_3
    //   1242: getstatic burp/Ztuj.Zk : Ljava/lang/String;
    //   1245: getstatic burp/Zxso.ZF : Ljava/lang/Object;
    //   1248: checkcast java/math/BigInteger
    //   1251: invokevirtual intValue : ()I
    //   1254: bipush #32
    //   1256: irem
    //   1257: invokestatic abs : (I)I
    //   1260: invokevirtual charAt : (I)C
    //   1263: invokevirtual append : (C)Ljava/lang/StringBuilder;
    //   1266: pop
    //   1267: iload_2
    //   1268: ifeq -> 1348
    //   1271: goto -> 1278
    //   1274: invokestatic a : (Ljava/lang/Throwable;)Ljava/lang/Throwable;
    //   1277: athrow
    //   1278: aload_3
    //   1279: getstatic burp/Ze_e.ZH : Ljava/lang/String;
    //   1282: getstatic burp/Zezq.Zu : Ljava/lang/Object;
    //   1285: checkcast java/math/BigInteger
    //   1288: invokevirtual intValue : ()I
    //   1291: bipush #32
    //   1293: irem
    //   1294: invokestatic abs : (I)I
    //   1297: invokevirtual charAt : (I)C
    //   1300: invokevirtual append : (C)Ljava/lang/StringBuilder;
    //   1303: pop
    //   1304: iload_2
    //   1305: ifeq -> 1348
    //   1308: goto -> 1315
    //   1311: invokestatic a : (Ljava/lang/Throwable;)Ljava/lang/Throwable;
    //   1314: athrow
    //   1315: aload_3
    //   1316: getstatic burp/Zgrf.ZE : Ljava/lang/String;
    //   1319: getstatic burp/Zg6f.Zl : Ljava/lang/Object;
    //   1322: checkcast java/math/BigInteger
    //   1325: invokevirtual intValue : ()I
    //   1328: bipush #32
    //   1330: irem
    //   1331: invokestatic abs : (I)I
    //   1334: invokevirtual charAt : (I)C
    //   1337: invokevirtual append : (C)Ljava/lang/StringBuilder;
    //   1340: pop
    //   1341: goto -> 1348
    //   1344: invokestatic a : (Ljava/lang/Throwable;)Ljava/lang/Throwable;
    //   1347: athrow
    //   1348: iinc #4, 1
    //   1351: iload_2
    //   1352: ifeq -> 15
    //   1355: aload_3
    //   1356: invokevirtual toString : ()Ljava/lang/String;
    //   1359: putstatic burp/Zr8h.Zk : Ljava/lang/String;
    //   1362: getstatic burp/Zmy4.ZB : Ljava/lang/Object;
    //   1365: checkcast java/math/BigInteger
    //   1368: invokevirtual toByteArray : ()[B
    //   1371: astore #4
    //   1373: bipush #64
    //   1375: newarray byte
    //   1377: dup
    //   1378: iconst_0
    //   1379: bipush #-128
    //   1381: bastore
    //   1382: dup
    //   1383: iconst_1
    //   1384: iconst_0
    //   1385: bastore
    //   1386: dup
    //   1387: iconst_2
    //   1388: iconst_0
    //   1389: bastore
    //   1390: dup
    //   1391: iconst_3
    //   1392: iconst_0
    //   1393: bastore
    //   1394: dup
    //   1395: iconst_4
    //   1396: iconst_0
    //   1397: bastore
    //   1398: dup
    //   1399: iconst_5
    //   1400: iconst_0
    //   1401: bastore
    //   1402: dup
    //   1403: bipush #6
    //   1405: iconst_0
    //   1406: bastore
    //   1407: dup
    //   1408: bipush #7
    //   1410: iconst_0
    //   1411: bastore
    //   1412: dup
    //   1413: bipush #8
    //   1415: iconst_0
    //   1416: bastore
    //   1417: dup
    //   1418: bipush #9
    //   1420: iconst_0
    //   1421: bastore
    //   1422: dup
    //   1423: bipush #10
    //   1425: iconst_0
    //   1426: bastore
    //   1427: dup
    //   1428: bipush #11
    //   1430: iconst_0
    //   1431: bastore
    //   1432: dup
    //   1433: bipush #12
    //   1435: iconst_0
    //   1436: bastore
    //   1437: dup
    //   1438: bipush #13
    //   1440: iconst_0
    //   1441: bastore
    //   1442: dup
    //   1443: bipush #14
    //   1445: iconst_0
    //   1446: bastore
    //   1447: dup
    //   1448: bipush #15
    //   1450: iconst_0
    //   1451: bastore
    //   1452: dup
    //   1453: bipush #16
    //   1455: iconst_0
    //   1456: bastore
    //   1457: dup
    //   1458: bipush #17
    //   1460: iconst_0
    //   1461: bastore
    //   1462: dup
    //   1463: bipush #18
    //   1465: iconst_0
    //   1466: bastore
    //   1467: dup
    //   1468: bipush #19
    //   1470: iconst_0
    //   1471: bastore
    //   1472: dup
    //   1473: bipush #20
    //   1475: iconst_0
    //   1476: bastore
    //   1477: dup
    //   1478: bipush #21
    //   1480: iconst_0
    //   1481: bastore
    //   1482: dup
    //   1483: bipush #22
    //   1485: iconst_0
    //   1486: bastore
    //   1487: dup
    //   1488: bipush #23
    //   1490: iconst_0
    //   1491: bastore
    //   1492: dup
    //   1493: bipush #24
    //   1495: iconst_0
    //   1496: bastore
    //   1497: dup
    //   1498: bipush #25
    //   1500: iconst_0
    //   1501: bastore
    //   1502: dup
    //   1503: bipush #26
    //   1505: iconst_0
    //   1506: bastore
    //   1507: dup
    //   1508: bipush #27
    //   1510: iconst_0
    //   1511: bastore
    //   1512: dup
    //   1513: bipush #28
    //   1515: iconst_0
    //   1516: bastore
    //   1517: dup
    //   1518: bipush #29
    //   1520: iconst_0
    //   1521: bastore
    //   1522: dup
    //   1523: bipush #30
    //   1525: iconst_0
    //   1526: bastore
    //   1527: dup
    //   1528: bipush #31
    //   1530: iconst_0
    //   1531: bastore
    //   1532: dup
    //   1533: bipush #32
    //   1535: iconst_0
    //   1536: bastore
    //   1537: dup
    //   1538: bipush #33
    //   1540: iconst_0
    //   1541: bastore
    //   1542: dup
    //   1543: bipush #34
    //   1545: iconst_0
    //   1546: bastore
    //   1547: dup
    //   1548: bipush #35
    //   1550: iconst_0
    //   1551: bastore
    //   1552: dup
    //   1553: bipush #36
    //   1555: iconst_0
    //   1556: bastore
    //   1557: dup
    //   1558: bipush #37
    //   1560: iconst_0
    //   1561: bastore
    //   1562: dup
    //   1563: bipush #38
    //   1565: iconst_0
    //   1566: bastore
    //   1567: dup
    //   1568: bipush #39
    //   1570: iconst_0
    //   1571: bastore
    //   1572: dup
    //   1573: bipush #40
    //   1575: iconst_0
    //   1576: bastore
    //   1577: dup
    //   1578: bipush #41
    //   1580: iconst_0
    //   1581: bastore
    //   1582: dup
    //   1583: bipush #42
    //   1585: iconst_0
    //   1586: bastore
    //   1587: dup
    //   1588: bipush #43
    //   1590: iconst_0
    //   1591: bastore
    //   1592: dup
    //   1593: bipush #44
    //   1595: iconst_0
    //   1596: bastore
    //   1597: dup
    //   1598: bipush #45
    //   1600: iconst_0
    //   1601: bastore
    //   1602: dup
    //   1603: bipush #46
    //   1605: iconst_0
    //   1606: bastore
    //   1607: dup
    //   1608: bipush #47
    //   1610: iconst_0
    //   1611: bastore
    //   1612: dup
    //   1613: bipush #48
    //   1615: iconst_0
    //   1616: bastore
    //   1617: dup
    //   1618: bipush #49
    //   1620: iconst_0
    //   1621: bastore
    //   1622: dup
    //   1623: bipush #50
    //   1625: iconst_0
    //   1626: bastore
    //   1627: dup
    //   1628: bipush #51
    //   1630: iconst_0
    //   1631: bastore
    //   1632: dup
    //   1633: bipush #52
    //   1635: iconst_0
    //   1636: bastore
    //   1637: dup
    //   1638: bipush #53
    //   1640: iconst_0
    //   1641: bastore
    //   1642: dup
    //   1643: bipush #54
    //   1645: iconst_0
    //   1646: bastore
    //   1647: dup
    //   1648: bipush #55
    //   1650: iconst_0
    //   1651: bastore
    //   1652: dup
    //   1653: bipush #56
    //   1655: iconst_0
    //   1656: bastore
    //   1657: dup
    //   1658: bipush #57
    //   1660: iconst_0
    //   1661: bastore
    //   1662: dup
    //   1663: bipush #58
    //   1665: iconst_0
    //   1666: bastore
    //   1667: dup
    //   1668: bipush #59
    //   1670: iconst_0
    //   1671: bastore
    //   1672: dup
    //   1673: bipush #60
    //   1675: iconst_0
    //   1676: bastore
    //   1677: dup
    //   1678: bipush #61
    //   1680: iconst_0
    //   1681: bastore
    //   1682: dup
    //   1683: bipush #62
    //   1685: iconst_0
    //   1686: bastore
    //   1687: dup
    //   1688: bipush #63
    //   1690: iconst_0
    //   1691: bastore
    //   1692: astore #6
    //   1694: bipush #64
    //   1696: newarray int
    //   1698: dup
    //   1699: iconst_0
    //   1700: ldc 1116352408
    //   1702: iastore
    //   1703: dup
    //   1704: iconst_1
    //   1705: ldc 1899447441
    //   1707: iastore
    //   1708: dup
    //   1709: iconst_2
    //   1710: ldc -1245643825
    //   1712: iastore
    //   1713: dup
    //   1714: iconst_3
    //   1715: ldc -373957723
    //   1717: iastore
    //   1718: dup
    //   1719: iconst_4
    //   1720: ldc 961987163
    //   1722: iastore
    //   1723: dup
    //   1724: iconst_5
    //   1725: ldc 1508970993
    //   1727: iastore
    //   1728: dup
    //   1729: bipush #6
    //   1731: ldc -1841331548
    //   1733: iastore
    //   1734: dup
    //   1735: bipush #7
    //   1737: ldc -1424204075
    //   1739: iastore
    //   1740: dup
    //   1741: bipush #8
    //   1743: ldc -670586216
    //   1745: iastore
    //   1746: dup
    //   1747: bipush #9
    //   1749: ldc 310598401
    //   1751: iastore
    //   1752: dup
    //   1753: bipush #10
    //   1755: ldc 607225278
    //   1757: iastore
    //   1758: dup
    //   1759: bipush #11
    //   1761: ldc 1426881987
    //   1763: iastore
    //   1764: dup
    //   1765: bipush #12
    //   1767: ldc 1925078388
    //   1769: iastore
    //   1770: dup
    //   1771: bipush #13
    //   1773: ldc -2132889090
    //   1775: iastore
    //   1776: dup
    //   1777: bipush #14
    //   1779: ldc -1680079193
    //   1781: iastore
    //   1782: dup
    //   1783: bipush #15
    //   1785: ldc -1046744716
    //   1787: iastore
    //   1788: dup
    //   1789: bipush #16
    //   1791: ldc -459576895
    //   1793: iastore
    //   1794: dup
    //   1795: bipush #17
    //   1797: ldc -272742522
    //   1799: iastore
    //   1800: dup
    //   1801: bipush #18
    //   1803: ldc 264347078
    //   1805: iastore
    //   1806: dup
    //   1807: bipush #19
    //   1809: ldc 604807628
    //   1811: iastore
    //   1812: dup
    //   1813: bipush #20
    //   1815: ldc 770255983
    //   1817: iastore
    //   1818: dup
    //   1819: bipush #21
    //   1821: ldc 1249150122
    //   1823: iastore
    //   1824: dup
    //   1825: bipush #22
    //   1827: ldc 1555081692
    //   1829: iastore
    //   1830: dup
    //   1831: bipush #23
    //   1833: ldc 1996064986
    //   1835: iastore
    //   1836: dup
    //   1837: bipush #24
    //   1839: ldc -1740746414
    //   1841: iastore
    //   1842: dup
    //   1843: bipush #25
    //   1845: ldc -1473132947
    //   1847: iastore
    //   1848: dup
    //   1849: bipush #26
    //   1851: ldc -1341970488
    //   1853: iastore
    //   1854: dup
    //   1855: bipush #27
    //   1857: ldc -1084653625
    //   1859: iastore
    //   1860: dup
    //   1861: bipush #28
    //   1863: ldc -958395405
    //   1865: iastore
    //   1866: dup
    //   1867: bipush #29
    //   1869: ldc -710438585
    //   1871: iastore
    //   1872: dup
    //   1873: bipush #30
    //   1875: ldc 113926993
    //   1877: iastore
    //   1878: dup
    //   1879: bipush #31
    //   1881: ldc 338241895
    //   1883: iastore
    //   1884: dup
    //   1885: bipush #32
    //   1887: ldc 666307205
    //   1889: iastore
    //   1890: dup
    //   1891: bipush #33
    //   1893: ldc 773529912
    //   1895: iastore
    //   1896: dup
    //   1897: bipush #34
    //   1899: ldc 1294757372
    //   1901: iastore
    //   1902: dup
    //   1903: bipush #35
    //   1905: ldc 1396182291
    //   1907: iastore
    //   1908: dup
    //   1909: bipush #36
    //   1911: ldc 1695183700
    //   1913: iastore
    //   1914: dup
    //   1915: bipush #37
    //   1917: ldc 1986661051
    //   1919: iastore
    //   1920: dup
    //   1921: bipush #38
    //   1923: ldc -2117940946
    //   1925: iastore
    //   1926: dup
    //   1927: bipush #39
    //   1929: ldc -1838011259
    //   1931: iastore
    //   1932: dup
    //   1933: bipush #40
    //   1935: ldc -1564481375
    //   1937: iastore
    //   1938: dup
    //   1939: bipush #41
    //   1941: ldc -1474664885
    //   1943: iastore
    //   1944: dup
    //   1945: bipush #42
    //   1947: ldc -1035236496
    //   1949: iastore
    //   1950: dup
    //   1951: bipush #43
    //   1953: ldc -949202525
    //   1955: iastore
    //   1956: dup
    //   1957: bipush #44
    //   1959: ldc -778901479
    //   1961: iastore
    //   1962: dup
    //   1963: bipush #45
    //   1965: ldc -694614492
    //   1967: iastore
    //   1968: dup
    //   1969: bipush #46
    //   1971: ldc -200395387
    //   1973: iastore
    //   1974: dup
    //   1975: bipush #47
    //   1977: ldc 275423344
    //   1979: iastore
    //   1980: dup
    //   1981: bipush #48
    //   1983: ldc 430227734
    //   1985: iastore
    //   1986: dup
    //   1987: bipush #49
    //   1989: ldc 506948616
    //   1991: iastore
    //   1992: dup
    //   1993: bipush #50
    //   1995: ldc 659060556
    //   1997: iastore
    //   1998: dup
    //   1999: bipush #51
    //   2001: ldc 883997877
    //   2003: iastore
    //   2004: dup
    //   2005: bipush #52
    //   2007: ldc 958139571
    //   2009: iastore
    //   2010: dup
    //   2011: bipush #53
    //   2013: ldc 1322822218
    //   2015: iastore
    //   2016: dup
    //   2017: bipush #54
    //   2019: ldc 1537002063
    //   2021: iastore
    //   2022: dup
    //   2023: bipush #55
    //   2025: ldc 1747873779
    //   2027: iastore
    //   2028: dup
    //   2029: bipush #56
    //   2031: ldc 1955562222
    //   2033: iastore
    //   2034: dup
    //   2035: bipush #57
    //   2037: ldc 2024104815
    //   2039: iastore
    //   2040: dup
    //   2041: bipush #58
    //   2043: ldc -2067236844
    //   2045: iastore
    //   2046: dup
    //   2047: bipush #59
    //   2049: ldc -1933114872
    //   2051: iastore
    //   2052: dup
    //   2053: bipush #60
    //   2055: ldc -1866530822
    //   2057: iastore
    //   2058: dup
    //   2059: bipush #61
    //   2061: ldc -1538233109
    //   2063: iastore
    //   2064: dup
    //   2065: bipush #62
    //   2067: ldc -1090935817
    //   2069: iastore
    //   2070: dup
    //   2071: bipush #63
    //   2073: ldc -965641998
    //   2075: iastore
    //   2076: astore #7
    //   2078: iconst_2
    //   2079: newarray int
    //   2081: dup
    //   2082: iconst_0
    //   2083: iconst_0
    //   2084: iastore
    //   2085: dup
    //   2086: iconst_1
    //   2087: iconst_0
    //   2088: iastore
    //   2089: astore #8
    //   2091: bipush #8
    //   2093: newarray int
    //   2095: dup
    //   2096: iconst_0
    //   2097: ldc 1779033703
    //   2099: iastore
    //   2100: dup
    //   2101: iconst_1
    //   2102: ldc -1150833019
    //   2104: iastore
    //   2105: dup
    //   2106: iconst_2
    //   2107: ldc 1013904242
    //   2109: iastore
    //   2110: dup
    //   2111: iconst_3
    //   2112: ldc -1521486534
    //   2114: iastore
    //   2115: dup
    //   2116: iconst_4
    //   2117: ldc 1359893119
    //   2119: iastore
    //   2120: dup
    //   2121: iconst_5
    //   2122: ldc -1694144372
    //   2124: iastore
    //   2125: dup
    //   2126: bipush #6
    //   2128: ldc 528734635
    //   2130: iastore
    //   2131: dup
    //   2132: bipush #7
    //   2134: ldc 1541459225
    //   2136: iastore
    //   2137: astore #9
    //   2139: bipush #64
    //   2141: newarray byte
    //   2143: astore #10
    //   2145: bipush #64
    //   2147: newarray byte
    //   2149: astore #11
    //   2151: aload #4
    //   2153: arraylength
    //   2154: istore #12
    //   2156: aload #8
    //   2158: iconst_0
    //   2159: iaload
    //   2160: bipush #63
    //   2162: iand
    //   2163: istore #13
    //   2165: aload #8
    //   2167: iconst_0
    //   2168: dup2
    //   2169: iaload
    //   2170: iload #12
    //   2172: iadd
    //   2173: iastore
    //   2174: aload #8
    //   2176: iconst_0
    //   2177: dup2
    //   2178: iaload
    //   2179: iconst_m1
    //   2180: iand
    //   2181: iastore
    //   2182: aload #8
    //   2184: iconst_0
    //   2185: iaload
    //   2186: iload #12
    //   2188: if_icmpge -> 2206
    //   2191: aload #8
    //   2193: iconst_1
    //   2194: dup2
    //   2195: iaload
    //   2196: iconst_1
    //   2197: iadd
    //   2198: iastore
    //   2199: goto -> 2206
    //   2202: invokestatic a : (Ljava/lang/Throwable;)Ljava/lang/Throwable;
    //   2205: athrow
    //   2206: iconst_0
    //   2207: istore #14
    //   2209: iload #12
    //   2211: bipush #64
    //   2213: if_icmplt -> 2823
    //   2216: iconst_0
    //   2217: istore #15
    //   2219: iload #15
    //   2221: bipush #64
    //   2223: if_icmpge -> 2246
    //   2226: aload #11
    //   2228: iload #15
    //   2230: aload #4
    //   2232: iload #14
    //   2234: iload #15
    //   2236: iadd
    //   2237: baload
    //   2238: bastore
    //   2239: iinc #15, 1
    //   2242: iload_2
    //   2243: ifeq -> 2219
    //   2246: bipush #64
    //   2248: newarray int
    //   2250: astore #15
    //   2252: bipush #8
    //   2254: newarray int
    //   2256: astore #16
    //   2258: iconst_0
    //   2259: istore #17
    //   2261: iload #17
    //   2263: bipush #8
    //   2265: if_icmpge -> 2285
    //   2268: aload #16
    //   2270: iload #17
    //   2272: aload #9
    //   2274: iload #17
    //   2276: iaload
    //   2277: iastore
    //   2278: iinc #17, 1
    //   2281: iload_2
    //   2282: ifeq -> 2261
    //   2285: iconst_0
    //   2286: istore #17
    //   2288: iload #17
    //   2290: bipush #64
    //   2292: if_icmpge -> 2783
    //   2295: iload #17
    //   2297: bipush #16
    //   2299: if_icmpge -> 2380
    //   2302: aload #15
    //   2304: iload #17
    //   2306: aload #11
    //   2308: iconst_4
    //   2309: iload #17
    //   2311: imul
    //   2312: baload
    //   2313: sipush #255
    //   2316: iand
    //   2317: bipush #24
    //   2319: ishl
    //   2320: aload #11
    //   2322: iconst_4
    //   2323: iload #17
    //   2325: imul
    //   2326: iconst_1
    //   2327: iadd
    //   2328: baload
    //   2329: sipush #255
    //   2332: iand
    //   2333: bipush #16
    //   2335: ishl
    //   2336: ior
    //   2337: aload #11
    //   2339: iconst_4
    //   2340: iload #17
    //   2342: imul
    //   2343: iconst_2
    //   2344: iadd
    //   2345: baload
    //   2346: sipush #255
    //   2349: iand
    //   2350: bipush #8
    //   2352: ishl
    //   2353: ior
    //   2354: aload #11
    //   2356: iconst_4
    //   2357: iload #17
    //   2359: imul
    //   2360: iconst_3
    //   2361: iadd
    //   2362: baload
    //   2363: sipush #255
    //   2366: iand
    //   2367: ior
    //   2368: iastore
    //   2369: iload_2
    //   2370: ifeq -> 2523
    //   2373: goto -> 2380
    //   2376: invokestatic a : (Ljava/lang/Throwable;)Ljava/lang/Throwable;
    //   2379: athrow
    //   2380: aload #15
    //   2382: iload #17
    //   2384: aload #15
    //   2386: iload #17
    //   2388: iconst_2
    //   2389: isub
    //   2390: iaload
    //   2391: bipush #17
    //   2393: iushr
    //   2394: aload #15
    //   2396: iload #17
    //   2398: iconst_2
    //   2399: isub
    //   2400: iaload
    //   2401: bipush #15
    //   2403: ishl
    //   2404: ior
    //   2405: aload #15
    //   2407: iload #17
    //   2409: iconst_2
    //   2410: isub
    //   2411: iaload
    //   2412: bipush #19
    //   2414: iushr
    //   2415: aload #15
    //   2417: iload #17
    //   2419: iconst_2
    //   2420: isub
    //   2421: iaload
    //   2422: bipush #13
    //   2424: ishl
    //   2425: ior
    //   2426: ixor
    //   2427: aload #15
    //   2429: iload #17
    //   2431: iconst_2
    //   2432: isub
    //   2433: iaload
    //   2434: bipush #10
    //   2436: iushr
    //   2437: ixor
    //   2438: aload #15
    //   2440: iload #17
    //   2442: bipush #7
    //   2444: isub
    //   2445: iaload
    //   2446: iadd
    //   2447: aload #15
    //   2449: iload #17
    //   2451: bipush #15
    //   2453: isub
    //   2454: iaload
    //   2455: bipush #7
    //   2457: iushr
    //   2458: aload #15
    //   2460: iload #17
    //   2462: bipush #15
    //   2464: isub
    //   2465: iaload
    //   2466: bipush #25
    //   2468: ishl
    //   2469: ior
    //   2470: aload #15
    //   2472: iload #17
    //   2474: bipush #15
    //   2476: isub
    //   2477: iaload
    //   2478: bipush #18
    //   2480: iushr
    //   2481: aload #15
    //   2483: iload #17
    //   2485: bipush #15
    //   2487: isub
    //   2488: iaload
    //   2489: bipush #14
    //   2491: ishl
    //   2492: ior
    //   2493: ixor
    //   2494: aload #15
    //   2496: iload #17
    //   2498: bipush #15
    //   2500: isub
    //   2501: iaload
    //   2502: iconst_3
    //   2503: iushr
    //   2504: ixor
    //   2505: iadd
    //   2506: aload #15
    //   2508: iload #17
    //   2510: bipush #16
    //   2512: isub
    //   2513: iaload
    //   2514: iadd
    //   2515: iastore
    //   2516: goto -> 2523
    //   2519: invokestatic a : (Ljava/lang/Throwable;)Ljava/lang/Throwable;
    //   2522: athrow
    //   2523: aload #16
    //   2525: bipush #7
    //   2527: iaload
    //   2528: aload #16
    //   2530: iconst_4
    //   2531: iaload
    //   2532: bipush #6
    //   2534: iushr
    //   2535: aload #16
    //   2537: iconst_4
    //   2538: iaload
    //   2539: bipush #26
    //   2541: ishl
    //   2542: ior
    //   2543: aload #16
    //   2545: iconst_4
    //   2546: iaload
    //   2547: bipush #11
    //   2549: iushr
    //   2550: aload #16
    //   2552: iconst_4
    //   2553: iaload
    //   2554: bipush #21
    //   2556: ishl
    //   2557: ior
    //   2558: ixor
    //   2559: aload #16
    //   2561: iconst_4
    //   2562: iaload
    //   2563: bipush #25
    //   2565: iushr
    //   2566: aload #16
    //   2568: iconst_4
    //   2569: iaload
    //   2570: bipush #7
    //   2572: ishl
    //   2573: ior
    //   2574: ixor
    //   2575: iadd
    //   2576: aload #16
    //   2578: bipush #6
    //   2580: iaload
    //   2581: aload #16
    //   2583: iconst_4
    //   2584: iaload
    //   2585: aload #16
    //   2587: iconst_5
    //   2588: iaload
    //   2589: aload #16
    //   2591: bipush #6
    //   2593: iaload
    //   2594: ixor
    //   2595: iand
    //   2596: ixor
    //   2597: iadd
    //   2598: aload #7
    //   2600: iload #17
    //   2602: iaload
    //   2603: iadd
    //   2604: aload #15
    //   2606: iload #17
    //   2608: iaload
    //   2609: iadd
    //   2610: istore #18
    //   2612: aload #16
    //   2614: iconst_0
    //   2615: iaload
    //   2616: iconst_2
    //   2617: iushr
    //   2618: aload #16
    //   2620: iconst_0
    //   2621: iaload
    //   2622: bipush #30
    //   2624: ishl
    //   2625: ior
    //   2626: aload #16
    //   2628: iconst_0
    //   2629: iaload
    //   2630: bipush #13
    //   2632: iushr
    //   2633: aload #16
    //   2635: iconst_0
    //   2636: iaload
    //   2637: bipush #19
    //   2639: ishl
    //   2640: ior
    //   2641: ixor
    //   2642: aload #16
    //   2644: iconst_0
    //   2645: iaload
    //   2646: bipush #22
    //   2648: iushr
    //   2649: aload #16
    //   2651: iconst_0
    //   2652: iaload
    //   2653: bipush #10
    //   2655: ishl
    //   2656: ior
    //   2657: ixor
    //   2658: aload #16
    //   2660: iconst_0
    //   2661: iaload
    //   2662: aload #16
    //   2664: iconst_1
    //   2665: iaload
    //   2666: iand
    //   2667: aload #16
    //   2669: iconst_2
    //   2670: iaload
    //   2671: aload #16
    //   2673: iconst_0
    //   2674: iaload
    //   2675: aload #16
    //   2677: iconst_1
    //   2678: iaload
    //   2679: ior
    //   2680: iand
    //   2681: ior
    //   2682: iadd
    //   2683: istore #19
    //   2685: aload #16
    //   2687: iconst_3
    //   2688: dup2
    //   2689: iaload
    //   2690: iload #18
    //   2692: iadd
    //   2693: iastore
    //   2694: aload #16
    //   2696: bipush #7
    //   2698: iload #18
    //   2700: iload #19
    //   2702: iadd
    //   2703: iastore
    //   2704: aload #16
    //   2706: bipush #7
    //   2708: iaload
    //   2709: istore #18
    //   2711: aload #16
    //   2713: bipush #7
    //   2715: aload #16
    //   2717: bipush #6
    //   2719: iaload
    //   2720: iastore
    //   2721: aload #16
    //   2723: bipush #6
    //   2725: aload #16
    //   2727: iconst_5
    //   2728: iaload
    //   2729: iastore
    //   2730: aload #16
    //   2732: iconst_5
    //   2733: aload #16
    //   2735: iconst_4
    //   2736: iaload
    //   2737: iastore
    //   2738: aload #16
    //   2740: iconst_4
    //   2741: aload #16
    //   2743: iconst_3
    //   2744: iaload
    //   2745: iastore
    //   2746: aload #16
    //   2748: iconst_3
    //   2749: aload #16
    //   2751: iconst_2
    //   2752: iaload
    //   2753: iastore
    //   2754: aload #16
    //   2756: iconst_2
    //   2757: aload #16
    //   2759: iconst_1
    //   2760: iaload
    //   2761: iastore
    //   2762: aload #16
    //   2764: iconst_1
    //   2765: aload #16
    //   2767: iconst_0
    //   2768: iaload
    //   2769: iastore
    //   2770: aload #16
    //   2772: iconst_0
    //   2773: iload #18
    //   2775: iastore
    //   2776: iinc #17, 1
    //   2779: iload_2
    //   2780: ifeq -> 2288
    //   2783: iconst_0
    //   2784: istore #17
    //   2786: iload #17
    //   2788: bipush #8
    //   2790: if_icmpge -> 2813
    //   2793: aload #9
    //   2795: iload #17
    //   2797: dup2
    //   2798: iaload
    //   2799: aload #16
    //   2801: iload #17
    //   2803: iaload
    //   2804: iadd
    //   2805: iastore
    //   2806: iinc #17, 1
    //   2809: iload_2
    //   2810: ifeq -> 2786
    //   2813: iinc #14, 64
    //   2816: iinc #12, -64
    //   2819: iload_2
    //   2820: ifeq -> 2209
    //   2823: iload #12
    //   2825: ifle -> 2861
    //   2828: iconst_0
    //   2829: istore #15
    //   2831: iload #15
    //   2833: iload #12
    //   2835: if_icmpge -> 2861
    //   2838: aload #10
    //   2840: iload #13
    //   2842: iload #15
    //   2844: iadd
    //   2845: aload #4
    //   2847: iload #14
    //   2849: iload #15
    //   2851: iadd
    //   2852: baload
    //   2853: bastore
    //   2854: iinc #15, 1
    //   2857: iload_2
    //   2858: ifeq -> 2831
    //   2861: aload #8
    //   2863: iconst_0
    //   2864: iaload
    //   2865: bipush #29
    //   2867: iushr
    //   2868: aload #8
    //   2870: iconst_1
    //   2871: iaload
    //   2872: iconst_3
    //   2873: ishl
    //   2874: ior
    //   2875: istore #15
    //   2877: aload #8
    //   2879: iconst_0
    //   2880: iaload
    //   2881: iconst_3
    //   2882: ishl
    //   2883: istore #16
    //   2885: aload #8
    //   2887: iconst_0
    //   2888: iaload
    //   2889: bipush #63
    //   2891: iand
    //   2892: istore #17
    //   2894: iload #17
    //   2896: bipush #56
    //   2898: if_icmpge -> 2913
    //   2901: bipush #56
    //   2903: iload #17
    //   2905: isub
    //   2906: goto -> 2918
    //   2909: invokestatic a : (Ljava/lang/Throwable;)Ljava/lang/Throwable;
    //   2912: athrow
    //   2913: bipush #120
    //   2915: iload #17
    //   2917: isub
    //   2918: istore #18
    //   2920: aload #8
    //   2922: iconst_0
    //   2923: iaload
    //   2924: bipush #63
    //   2926: iand
    //   2927: istore #13
    //   2929: bipush #64
    //   2931: iload #13
    //   2933: isub
    //   2934: istore #19
    //   2936: aload #8
    //   2938: iconst_0
    //   2939: dup2
    //   2940: iaload
    //   2941: iload #18
    //   2943: iadd
    //   2944: iastore
    //   2945: aload #8
    //   2947: iconst_0
    //   2948: dup2
    //   2949: iaload
    //   2950: iconst_m1
    //   2951: iand
    //   2952: iastore
    //   2953: aload #8
    //   2955: iconst_0
    //   2956: iaload
    //   2957: iload #18
    //   2959: if_icmpge -> 2977
    //   2962: aload #8
    //   2964: iconst_1
    //   2965: dup2
    //   2966: iaload
    //   2967: iconst_1
    //   2968: iadd
    //   2969: iastore
    //   2970: goto -> 2977
    //   2973: invokestatic a : (Ljava/lang/Throwable;)Ljava/lang/Throwable;
    //   2976: athrow
    //   2977: iconst_0
    //   2978: istore #14
    //   2980: iload #13
    //   2982: ifle -> 3613
    //   2985: iload #18
    //   2987: iload #19
    //   2989: if_icmplt -> 3613
    //   2992: goto -> 2999
    //   2995: invokestatic a : (Ljava/lang/Throwable;)Ljava/lang/Throwable;
    //   2998: athrow
    //   2999: iconst_0
    //   3000: istore #20
    //   3002: iload #20
    //   3004: iload #19
    //   3006: if_icmpge -> 3029
    //   3009: aload #10
    //   3011: iload #13
    //   3013: iload #20
    //   3015: iadd
    //   3016: aload #6
    //   3018: iload #20
    //   3020: baload
    //   3021: bastore
    //   3022: iinc #20, 1
    //   3025: iload_2
    //   3026: ifeq -> 3002
    //   3029: bipush #64
    //   3031: newarray int
    //   3033: astore #20
    //   3035: bipush #8
    //   3037: newarray int
    //   3039: astore #21
    //   3041: iconst_0
    //   3042: istore #22
    //   3044: iload #22
    //   3046: bipush #8
    //   3048: if_icmpge -> 3068
    //   3051: aload #21
    //   3053: iload #22
    //   3055: aload #9
    //   3057: iload #22
    //   3059: iaload
    //   3060: iastore
    //   3061: iinc #22, 1
    //   3064: iload_2
    //   3065: ifeq -> 3044
    //   3068: iconst_0
    //   3069: istore #22
    //   3071: iload #22
    //   3073: bipush #64
    //   3075: if_icmpge -> 3566
    //   3078: iload #22
    //   3080: bipush #16
    //   3082: if_icmpge -> 3163
    //   3085: aload #20
    //   3087: iload #22
    //   3089: aload #10
    //   3091: iconst_4
    //   3092: iload #22
    //   3094: imul
    //   3095: baload
    //   3096: sipush #255
    //   3099: iand
    //   3100: bipush #24
    //   3102: ishl
    //   3103: aload #10
    //   3105: iconst_4
    //   3106: iload #22
    //   3108: imul
    //   3109: iconst_1
    //   3110: iadd
    //   3111: baload
    //   3112: sipush #255
    //   3115: iand
    //   3116: bipush #16
    //   3118: ishl
    //   3119: ior
    //   3120: aload #10
    //   3122: iconst_4
    //   3123: iload #22
    //   3125: imul
    //   3126: iconst_2
    //   3127: iadd
    //   3128: baload
    //   3129: sipush #255
    //   3132: iand
    //   3133: bipush #8
    //   3135: ishl
    //   3136: ior
    //   3137: aload #10
    //   3139: iconst_4
    //   3140: iload #22
    //   3142: imul
    //   3143: iconst_3
    //   3144: iadd
    //   3145: baload
    //   3146: sipush #255
    //   3149: iand
    //   3150: ior
    //   3151: iastore
    //   3152: iload_2
    //   3153: ifeq -> 3306
    //   3156: goto -> 3163
    //   3159: invokestatic a : (Ljava/lang/Throwable;)Ljava/lang/Throwable;
    //   3162: athrow
    //   3163: aload #20
    //   3165: iload #22
    //   3167: aload #20
    //   3169: iload #22
    //   3171: iconst_2
    //   3172: isub
    //   3173: iaload
    //   3174: bipush #17
    //   3176: iushr
    //   3177: aload #20
    //   3179: iload #22
    //   3181: iconst_2
    //   3182: isub
    //   3183: iaload
    //   3184: bipush #15
    //   3186: ishl
    //   3187: ior
    //   3188: aload #20
    //   3190: iload #22
    //   3192: iconst_2
    //   3193: isub
    //   3194: iaload
    //   3195: bipush #19
    //   3197: iushr
    //   3198: aload #20
    //   3200: iload #22
    //   3202: iconst_2
    //   3203: isub
    //   3204: iaload
    //   3205: bipush #13
    //   3207: ishl
    //   3208: ior
    //   3209: ixor
    //   3210: aload #20
    //   3212: iload #22
    //   3214: iconst_2
    //   3215: isub
    //   3216: iaload
    //   3217: bipush #10
    //   3219: iushr
    //   3220: ixor
    //   3221: aload #20
    //   3223: iload #22
    //   3225: bipush #7
    //   3227: isub
    //   3228: iaload
    //   3229: iadd
    //   3230: aload #20
    //   3232: iload #22
    //   3234: bipush #15
    //   3236: isub
    //   3237: iaload
    //   3238: bipush #7
    //   3240: iushr
    //   3241: aload #20
    //   3243: iload #22
    //   3245: bipush #15
    //   3247: isub
    //   3248: iaload
    //   3249: bipush #25
    //   3251: ishl
    //   3252: ior
    //   3253: aload #20
    //   3255: iload #22
    //   3257: bipush #15
    //   3259: isub
    //   3260: iaload
    //   3261: bipush #18
    //   3263: iushr
    //   3264: aload #20
    //   3266: iload #22
    //   3268: bipush #15
    //   3270: isub
    //   3271: iaload
    //   3272: bipush #14
    //   3274: ishl
    //   3275: ior
    //   3276: ixor
    //   3277: aload #20
    //   3279: iload #22
    //   3281: bipush #15
    //   3283: isub
    //   3284: iaload
    //   3285: iconst_3
    //   3286: iushr
    //   3287: ixor
    //   3288: iadd
    //   3289: aload #20
    //   3291: iload #22
    //   3293: bipush #16
    //   3295: isub
    //   3296: iaload
    //   3297: iadd
    //   3298: iastore
    //   3299: goto -> 3306
    //   3302: invokestatic a : (Ljava/lang/Throwable;)Ljava/lang/Throwable;
    //   3305: athrow
    //   3306: aload #21
    //   3308: bipush #7
    //   3310: iaload
    //   3311: aload #21
    //   3313: iconst_4
    //   3314: iaload
    //   3315: bipush #6
    //   3317: iushr
    //   3318: aload #21
    //   3320: iconst_4
    //   3321: iaload
    //   3322: bipush #26
    //   3324: ishl
    //   3325: ior
    //   3326: aload #21
    //   3328: iconst_4
    //   3329: iaload
    //   3330: bipush #11
    //   3332: iushr
    //   3333: aload #21
    //   3335: iconst_4
    //   3336: iaload
    //   3337: bipush #21
    //   3339: ishl
    //   3340: ior
    //   3341: ixor
    //   3342: aload #21
    //   3344: iconst_4
    //   3345: iaload
    //   3346: bipush #25
    //   3348: iushr
    //   3349: aload #21
    //   3351: iconst_4
    //   3352: iaload
    //   3353: bipush #7
    //   3355: ishl
    //   3356: ior
    //   3357: ixor
    //   3358: iadd
    //   3359: aload #21
    //   3361: bipush #6
    //   3363: iaload
    //   3364: aload #21
    //   3366: iconst_4
    //   3367: iaload
    //   3368: aload #21
    //   3370: iconst_5
    //   3371: iaload
    //   3372: aload #21
    //   3374: bipush #6
    //   3376: iaload
    //   3377: ixor
    //   3378: iand
    //   3379: ixor
    //   3380: iadd
    //   3381: aload #7
    //   3383: iload #22
    //   3385: iaload
    //   3386: iadd
    //   3387: aload #20
    //   3389: iload #22
    //   3391: iaload
    //   3392: iadd
    //   3393: istore #23
    //   3395: aload #21
    //   3397: iconst_0
    //   3398: iaload
    //   3399: iconst_2
    //   3400: iushr
    //   3401: aload #21
    //   3403: iconst_0
    //   3404: iaload
    //   3405: bipush #30
    //   3407: ishl
    //   3408: ior
    //   3409: aload #21
    //   3411: iconst_0
    //   3412: iaload
    //   3413: bipush #13
    //   3415: iushr
    //   3416: aload #21
    //   3418: iconst_0
    //   3419: iaload
    //   3420: bipush #19
    //   3422: ishl
    //   3423: ior
    //   3424: ixor
    //   3425: aload #21
    //   3427: iconst_0
    //   3428: iaload
    //   3429: bipush #22
    //   3431: iushr
    //   3432: aload #21
    //   3434: iconst_0
    //   3435: iaload
    //   3436: bipush #10
    //   3438: ishl
    //   3439: ior
    //   3440: ixor
    //   3441: aload #21
    //   3443: iconst_0
    //   3444: iaload
    //   3445: aload #21
    //   3447: iconst_1
    //   3448: iaload
    //   3449: iand
    //   3450: aload #21
    //   3452: iconst_2
    //   3453: iaload
    //   3454: aload #21
    //   3456: iconst_0
    //   3457: iaload
    //   3458: aload #21
    //   3460: iconst_1
    //   3461: iaload
    //   3462: ior
    //   3463: iand
    //   3464: ior
    //   3465: iadd
    //   3466: istore #24
    //   3468: aload #21
    //   3470: iconst_3
    //   3471: dup2
    //   3472: iaload
    //   3473: iload #23
    //   3475: iadd
    //   3476: iastore
    //   3477: aload #21
    //   3479: bipush #7
    //   3481: iload #23
    //   3483: iload #24
    //   3485: iadd
    //   3486: iastore
    //   3487: aload #21
    //   3489: bipush #7
    //   3491: iaload
    //   3492: istore #23
    //   3494: aload #21
    //   3496: bipush #7
    //   3498: aload #21
    //   3500: bipush #6
    //   3502: iaload
    //   3503: iastore
    //   3504: aload #21
    //   3506: bipush #6
    //   3508: aload #21
    //   3510: iconst_5
    //   3511: iaload
    //   3512: iastore
    //   3513: aload #21
    //   3515: iconst_5
    //   3516: aload #21
    //   3518: iconst_4
    //   3519: iaload
    //   3520: iastore
    //   3521: aload #21
    //   3523: iconst_4
    //   3524: aload #21
    //   3526: iconst_3
    //   3527: iaload
    //   3528: iastore
    //   3529: aload #21
    //   3531: iconst_3
    //   3532: aload #21
    //   3534: iconst_2
    //   3535: iaload
    //   3536: iastore
    //   3537: aload #21
    //   3539: iconst_2
    //   3540: aload #21
    //   3542: iconst_1
    //   3543: iaload
    //   3544: iastore
    //   3545: aload #21
    //   3547: iconst_1
    //   3548: aload #21
    //   3550: iconst_0
    //   3551: iaload
    //   3552: iastore
    //   3553: aload #21
    //   3555: iconst_0
    //   3556: iload #23
    //   3558: iastore
    //   3559: iinc #22, 1
    //   3562: iload_2
    //   3563: ifeq -> 3071
    //   3566: iconst_0
    //   3567: istore #22
    //   3569: iload #22
    //   3571: bipush #8
    //   3573: if_icmpge -> 3596
    //   3576: aload #9
    //   3578: iload #22
    //   3580: dup2
    //   3581: iaload
    //   3582: aload #21
    //   3584: iload #22
    //   3586: iaload
    //   3587: iadd
    //   3588: iastore
    //   3589: iinc #22, 1
    //   3592: iload_2
    //   3593: ifeq -> 3569
    //   3596: iload #14
    //   3598: iload #19
    //   3600: iadd
    //   3601: istore #14
    //   3603: iload #18
    //   3605: iload #19
    //   3607: isub
    //   3608: istore #18
    //   3610: iconst_0
    //   3611: istore #13
    //   3613: iload #18
    //   3615: bipush #64
    //   3617: if_icmplt -> 4227
    //   3620: iconst_0
    //   3621: istore #20
    //   3623: iload #20
    //   3625: bipush #64
    //   3627: if_icmpge -> 3650
    //   3630: aload #11
    //   3632: iload #20
    //   3634: aload #6
    //   3636: iload #14
    //   3638: iload #20
    //   3640: iadd
    //   3641: baload
    //   3642: bastore
    //   3643: iinc #20, 1
    //   3646: iload_2
    //   3647: ifeq -> 3623
    //   3650: bipush #64
    //   3652: newarray int
    //   3654: astore #20
    //   3656: bipush #8
    //   3658: newarray int
    //   3660: astore #21
    //   3662: iconst_0
    //   3663: istore #22
    //   3665: iload #22
    //   3667: bipush #8
    //   3669: if_icmpge -> 3689
    //   3672: aload #21
    //   3674: iload #22
    //   3676: aload #9
    //   3678: iload #22
    //   3680: iaload
    //   3681: iastore
    //   3682: iinc #22, 1
    //   3685: iload_2
    //   3686: ifeq -> 3665
    //   3689: iconst_0
    //   3690: istore #22
    //   3692: iload #22
    //   3694: bipush #64
    //   3696: if_icmpge -> 4187
    //   3699: iload #22
    //   3701: bipush #16
    //   3703: if_icmpge -> 3784
    //   3706: aload #20
    //   3708: iload #22
    //   3710: aload #11
    //   3712: iconst_4
    //   3713: iload #22
    //   3715: imul
    //   3716: baload
    //   3717: sipush #255
    //   3720: iand
    //   3721: bipush #24
    //   3723: ishl
    //   3724: aload #11
    //   3726: iconst_4
    //   3727: iload #22
    //   3729: imul
    //   3730: iconst_1
    //   3731: iadd
    //   3732: baload
    //   3733: sipush #255
    //   3736: iand
    //   3737: bipush #16
    //   3739: ishl
    //   3740: ior
    //   3741: aload #11
    //   3743: iconst_4
    //   3744: iload #22
    //   3746: imul
    //   3747: iconst_2
    //   3748: iadd
    //   3749: baload
    //   3750: sipush #255
    //   3753: iand
    //   3754: bipush #8
    //   3756: ishl
    //   3757: ior
    //   3758: aload #11
    //   3760: iconst_4
    //   3761: iload #22
    //   3763: imul
    //   3764: iconst_3
    //   3765: iadd
    //   3766: baload
    //   3767: sipush #255
    //   3770: iand
    //   3771: ior
    //   3772: iastore
    //   3773: iload_2
    //   3774: ifeq -> 3927
    //   3777: goto -> 3784
    //   3780: invokestatic a : (Ljava/lang/Throwable;)Ljava/lang/Throwable;
    //   3783: athrow
    //   3784: aload #20
    //   3786: iload #22
    //   3788: aload #20
    //   3790: iload #22
    //   3792: iconst_2
    //   3793: isub
    //   3794: iaload
    //   3795: bipush #17
    //   3797: iushr
    //   3798: aload #20
    //   3800: iload #22
    //   3802: iconst_2
    //   3803: isub
    //   3804: iaload
    //   3805: bipush #15
    //   3807: ishl
    //   3808: ior
    //   3809: aload #20
    //   3811: iload #22
    //   3813: iconst_2
    //   3814: isub
    //   3815: iaload
    //   3816: bipush #19
    //   3818: iushr
    //   3819: aload #20
    //   3821: iload #22
    //   3823: iconst_2
    //   3824: isub
    //   3825: iaload
    //   3826: bipush #13
    //   3828: ishl
    //   3829: ior
    //   3830: ixor
    //   3831: aload #20
    //   3833: iload #22
    //   3835: iconst_2
    //   3836: isub
    //   3837: iaload
    //   3838: bipush #10
    //   3840: iushr
    //   3841: ixor
    //   3842: aload #20
    //   3844: iload #22
    //   3846: bipush #7
    //   3848: isub
    //   3849: iaload
    //   3850: iadd
    //   3851: aload #20
    //   3853: iload #22
    //   3855: bipush #15
    //   3857: isub
    //   3858: iaload
    //   3859: bipush #7
    //   3861: iushr
    //   3862: aload #20
    //   3864: iload #22
    //   3866: bipush #15
    //   3868: isub
    //   3869: iaload
    //   3870: bipush #25
    //   3872: ishl
    //   3873: ior
    //   3874: aload #20
    //   3876: iload #22
    //   3878: bipush #15
    //   3880: isub
    //   3881: iaload
    //   3882: bipush #18
    //   3884: iushr
    //   3885: aload #20
    //   3887: iload #22
    //   3889: bipush #15
    //   3891: isub
    //   3892: iaload
    //   3893: bipush #14
    //   3895: ishl
    //   3896: ior
    //   3897: ixor
    //   3898: aload #20
    //   3900: iload #22
    //   3902: bipush #15
    //   3904: isub
    //   3905: iaload
    //   3906: iconst_3
    //   3907: iushr
    //   3908: ixor
    //   3909: iadd
    //   3910: aload #20
    //   3912: iload #22
    //   3914: bipush #16
    //   3916: isub
    //   3917: iaload
    //   3918: iadd
    //   3919: iastore
    //   3920: goto -> 3927
    //   3923: invokestatic a : (Ljava/lang/Throwable;)Ljava/lang/Throwable;
    //   3926: athrow
    //   3927: aload #21
    //   3929: bipush #7
    //   3931: iaload
    //   3932: aload #21
    //   3934: iconst_4
    //   3935: iaload
    //   3936: bipush #6
    //   3938: iushr
    //   3939: aload #21
    //   3941: iconst_4
    //   3942: iaload
    //   3943: bipush #26
    //   3945: ishl
    //   3946: ior
    //   3947: aload #21
    //   3949: iconst_4
    //   3950: iaload
    //   3951: bipush #11
    //   3953: iushr
    //   3954: aload #21
    //   3956: iconst_4
    //   3957: iaload
    //   3958: bipush #21
    //   3960: ishl
    //   3961: ior
    //   3962: ixor
    //   3963: aload #21
    //   3965: iconst_4
    //   3966: iaload
    //   3967: bipush #25
    //   3969: iushr
    //   3970: aload #21
    //   3972: iconst_4
    //   3973: iaload
    //   3974: bipush #7
    //   3976: ishl
    //   3977: ior
    //   3978: ixor
    //   3979: iadd
    //   3980: aload #21
    //   3982: bipush #6
    //   3984: iaload
    //   3985: aload #21
    //   3987: iconst_4
    //   3988: iaload
    //   3989: aload #21
    //   3991: iconst_5
    //   3992: iaload
    //   3993: aload #21
    //   3995: bipush #6
    //   3997: iaload
    //   3998: ixor
    //   3999: iand
    //   4000: ixor
    //   4001: iadd
    //   4002: aload #7
    //   4004: iload #22
    //   4006: iaload
    //   4007: iadd
    //   4008: aload #20
    //   4010: iload #22
    //   4012: iaload
    //   4013: iadd
    //   4014: istore #23
    //   4016: aload #21
    //   4018: iconst_0
    //   4019: iaload
    //   4020: iconst_2
    //   4021: iushr
    //   4022: aload #21
    //   4024: iconst_0
    //   4025: iaload
    //   4026: bipush #30
    //   4028: ishl
    //   4029: ior
    //   4030: aload #21
    //   4032: iconst_0
    //   4033: iaload
    //   4034: bipush #13
    //   4036: iushr
    //   4037: aload #21
    //   4039: iconst_0
    //   4040: iaload
    //   4041: bipush #19
    //   4043: ishl
    //   4044: ior
    //   4045: ixor
    //   4046: aload #21
    //   4048: iconst_0
    //   4049: iaload
    //   4050: bipush #22
    //   4052: iushr
    //   4053: aload #21
    //   4055: iconst_0
    //   4056: iaload
    //   4057: bipush #10
    //   4059: ishl
    //   4060: ior
    //   4061: ixor
    //   4062: aload #21
    //   4064: iconst_0
    //   4065: iaload
    //   4066: aload #21
    //   4068: iconst_1
    //   4069: iaload
    //   4070: iand
    //   4071: aload #21
    //   4073: iconst_2
    //   4074: iaload
    //   4075: aload #21
    //   4077: iconst_0
    //   4078: iaload
    //   4079: aload #21
    //   4081: iconst_1
    //   4082: iaload
    //   4083: ior
    //   4084: iand
    //   4085: ior
    //   4086: iadd
    //   4087: istore #24
    //   4089: aload #21
    //   4091: iconst_3
    //   4092: dup2
    //   4093: iaload
    //   4094: iload #23
    //   4096: iadd
    //   4097: iastore
    //   4098: aload #21
    //   4100: bipush #7
    //   4102: iload #23
    //   4104: iload #24
    //   4106: iadd
    //   4107: iastore
    //   4108: aload #21
    //   4110: bipush #7
    //   4112: iaload
    //   4113: istore #23
    //   4115: aload #21
    //   4117: bipush #7
    //   4119: aload #21
    //   4121: bipush #6
    //   4123: iaload
    //   4124: iastore
    //   4125: aload #21
    //   4127: bipush #6
    //   4129: aload #21
    //   4131: iconst_5
    //   4132: iaload
    //   4133: iastore
    //   4134: aload #21
    //   4136: iconst_5
    //   4137: aload #21
    //   4139: iconst_4
    //   4140: iaload
    //   4141: iastore
    //   4142: aload #21
    //   4144: iconst_4
    //   4145: aload #21
    //   4147: iconst_3
    //   4148: iaload
    //   4149: iastore
    //   4150: aload #21
    //   4152: iconst_3
    //   4153: aload #21
    //   4155: iconst_2
    //   4156: iaload
    //   4157: iastore
    //   4158: aload #21
    //   4160: iconst_2
    //   4161: aload #21
    //   4163: iconst_1
    //   4164: iaload
    //   4165: iastore
    //   4166: aload #21
    //   4168: iconst_1
    //   4169: aload #21
    //   4171: iconst_0
    //   4172: iaload
    //   4173: iastore
    //   4174: aload #21
    //   4176: iconst_0
    //   4177: iload #23
    //   4179: iastore
    //   4180: iinc #22, 1
    //   4183: iload_2
    //   4184: ifeq -> 3692
    //   4187: iconst_0
    //   4188: istore #22
    //   4190: iload #22
    //   4192: bipush #8
    //   4194: if_icmpge -> 4217
    //   4197: aload #9
    //   4199: iload #22
    //   4201: dup2
    //   4202: iaload
    //   4203: aload #21
    //   4205: iload #22
    //   4207: iaload
    //   4208: iadd
    //   4209: iastore
    //   4210: iinc #22, 1
    //   4213: iload_2
    //   4214: ifeq -> 4190
    //   4217: iinc #14, 64
    //   4220: iinc #18, -64
    //   4223: iload_2
    //   4224: ifeq -> 3613
    //   4227: iload #18
    //   4229: ifle -> 4265
    //   4232: iconst_0
    //   4233: istore #20
    //   4235: iload #20
    //   4237: iload #18
    //   4239: if_icmpge -> 4265
    //   4242: aload #10
    //   4244: iload #13
    //   4246: iload #20
    //   4248: iadd
    //   4249: aload #6
    //   4251: iload #14
    //   4253: iload #20
    //   4255: iadd
    //   4256: baload
    //   4257: bastore
    //   4258: iinc #20, 1
    //   4261: iload_2
    //   4262: ifeq -> 4235
    //   4265: bipush #8
    //   4267: newarray byte
    //   4269: astore #20
    //   4271: aload #20
    //   4273: iconst_0
    //   4274: iload #15
    //   4276: bipush #24
    //   4278: iushr
    //   4279: i2b
    //   4280: bastore
    //   4281: aload #20
    //   4283: iconst_1
    //   4284: iload #15
    //   4286: bipush #16
    //   4288: iushr
    //   4289: i2b
    //   4290: bastore
    //   4291: aload #20
    //   4293: iconst_2
    //   4294: iload #15
    //   4296: bipush #8
    //   4298: iushr
    //   4299: i2b
    //   4300: bastore
    //   4301: aload #20
    //   4303: iconst_3
    //   4304: iload #15
    //   4306: i2b
    //   4307: bastore
    //   4308: aload #20
    //   4310: iconst_4
    //   4311: iload #16
    //   4313: bipush #24
    //   4315: iushr
    //   4316: i2b
    //   4317: bastore
    //   4318: aload #20
    //   4320: iconst_5
    //   4321: iload #16
    //   4323: bipush #16
    //   4325: iushr
    //   4326: i2b
    //   4327: bastore
    //   4328: aload #20
    //   4330: bipush #6
    //   4332: iload #16
    //   4334: bipush #8
    //   4336: iushr
    //   4337: i2b
    //   4338: bastore
    //   4339: aload #20
    //   4341: bipush #7
    //   4343: iload #16
    //   4345: i2b
    //   4346: bastore
    //   4347: bipush #8
    //   4349: istore #12
    //   4351: aload #8
    //   4353: iconst_0
    //   4354: iaload
    //   4355: bipush #63
    //   4357: iand
    //   4358: istore #13
    //   4360: bipush #64
    //   4362: iload #13
    //   4364: isub
    //   4365: istore #19
    //   4367: aload #8
    //   4369: iconst_0
    //   4370: dup2
    //   4371: iaload
    //   4372: iload #12
    //   4374: iadd
    //   4375: iastore
    //   4376: aload #8
    //   4378: iconst_0
    //   4379: dup2
    //   4380: iaload
    //   4381: iconst_m1
    //   4382: iand
    //   4383: iastore
    //   4384: aload #8
    //   4386: iconst_0
    //   4387: iaload
    //   4388: iload #12
    //   4390: if_icmpge -> 4408
    //   4393: aload #8
    //   4395: iconst_1
    //   4396: dup2
    //   4397: iaload
    //   4398: iconst_1
    //   4399: iadd
    //   4400: iastore
    //   4401: goto -> 4408
    //   4404: invokestatic a : (Ljava/lang/Throwable;)Ljava/lang/Throwable;
    //   4407: athrow
    //   4408: iload #13
    //   4410: ifle -> 5024
    //   4413: iload #12
    //   4415: iload #19
    //   4417: if_icmplt -> 5024
    //   4420: goto -> 4427
    //   4423: invokestatic a : (Ljava/lang/Throwable;)Ljava/lang/Throwable;
    //   4426: athrow
    //   4427: iconst_0
    //   4428: istore #21
    //   4430: iload #21
    //   4432: iload #19
    //   4434: if_icmpge -> 4457
    //   4437: aload #10
    //   4439: iload #13
    //   4441: iload #21
    //   4443: iadd
    //   4444: aload #20
    //   4446: iload #21
    //   4448: baload
    //   4449: bastore
    //   4450: iinc #21, 1
    //   4453: iload_2
    //   4454: ifeq -> 4430
    //   4457: bipush #64
    //   4459: newarray int
    //   4461: astore #21
    //   4463: bipush #8
    //   4465: newarray int
    //   4467: astore #22
    //   4469: iconst_0
    //   4470: istore #23
    //   4472: iload #23
    //   4474: bipush #8
    //   4476: if_icmpge -> 4496
    //   4479: aload #22
    //   4481: iload #23
    //   4483: aload #9
    //   4485: iload #23
    //   4487: iaload
    //   4488: iastore
    //   4489: iinc #23, 1
    //   4492: iload_2
    //   4493: ifeq -> 4472
    //   4496: iconst_0
    //   4497: istore #23
    //   4499: iload #23
    //   4501: bipush #64
    //   4503: if_icmpge -> 4994
    //   4506: iload #23
    //   4508: bipush #16
    //   4510: if_icmpge -> 4591
    //   4513: aload #21
    //   4515: iload #23
    //   4517: aload #10
    //   4519: iconst_4
    //   4520: iload #23
    //   4522: imul
    //   4523: baload
    //   4524: sipush #255
    //   4527: iand
    //   4528: bipush #24
    //   4530: ishl
    //   4531: aload #10
    //   4533: iconst_4
    //   4534: iload #23
    //   4536: imul
    //   4537: iconst_1
    //   4538: iadd
    //   4539: baload
    //   4540: sipush #255
    //   4543: iand
    //   4544: bipush #16
    //   4546: ishl
    //   4547: ior
    //   4548: aload #10
    //   4550: iconst_4
    //   4551: iload #23
    //   4553: imul
    //   4554: iconst_2
    //   4555: iadd
    //   4556: baload
    //   4557: sipush #255
    //   4560: iand
    //   4561: bipush #8
    //   4563: ishl
    //   4564: ior
    //   4565: aload #10
    //   4567: iconst_4
    //   4568: iload #23
    //   4570: imul
    //   4571: iconst_3
    //   4572: iadd
    //   4573: baload
    //   4574: sipush #255
    //   4577: iand
    //   4578: ior
    //   4579: iastore
    //   4580: iload_2
    //   4581: ifeq -> 4734
    //   4584: goto -> 4591
    //   4587: invokestatic a : (Ljava/lang/Throwable;)Ljava/lang/Throwable;
    //   4590: athrow
    //   4591: aload #21
    //   4593: iload #23
    //   4595: aload #21
    //   4597: iload #23
    //   4599: iconst_2
    //   4600: isub
    //   4601: iaload
    //   4602: bipush #17
    //   4604: iushr
    //   4605: aload #21
    //   4607: iload #23
    //   4609: iconst_2
    //   4610: isub
    //   4611: iaload
    //   4612: bipush #15
    //   4614: ishl
    //   4615: ior
    //   4616: aload #21
    //   4618: iload #23
    //   4620: iconst_2
    //   4621: isub
    //   4622: iaload
    //   4623: bipush #19
    //   4625: iushr
    //   4626: aload #21
    //   4628: iload #23
    //   4630: iconst_2
    //   4631: isub
    //   4632: iaload
    //   4633: bipush #13
    //   4635: ishl
    //   4636: ior
    //   4637: ixor
    //   4638: aload #21
    //   4640: iload #23
    //   4642: iconst_2
    //   4643: isub
    //   4644: iaload
    //   4645: bipush #10
    //   4647: iushr
    //   4648: ixor
    //   4649: aload #21
    //   4651: iload #23
    //   4653: bipush #7
    //   4655: isub
    //   4656: iaload
    //   4657: iadd
    //   4658: aload #21
    //   4660: iload #23
    //   4662: bipush #15
    //   4664: isub
    //   4665: iaload
    //   4666: bipush #7
    //   4668: iushr
    //   4669: aload #21
    //   4671: iload #23
    //   4673: bipush #15
    //   4675: isub
    //   4676: iaload
    //   4677: bipush #25
    //   4679: ishl
    //   4680: ior
    //   4681: aload #21
    //   4683: iload #23
    //   4685: bipush #15
    //   4687: isub
    //   4688: iaload
    //   4689: bipush #18
    //   4691: iushr
    //   4692: aload #21
    //   4694: iload #23
    //   4696: bipush #15
    //   4698: isub
    //   4699: iaload
    //   4700: bipush #14
    //   4702: ishl
    //   4703: ior
    //   4704: ixor
    //   4705: aload #21
    //   4707: iload #23
    //   4709: bipush #15
    //   4711: isub
    //   4712: iaload
    //   4713: iconst_3
    //   4714: iushr
    //   4715: ixor
    //   4716: iadd
    //   4717: aload #21
    //   4719: iload #23
    //   4721: bipush #16
    //   4723: isub
    //   4724: iaload
    //   4725: iadd
    //   4726: iastore
    //   4727: goto -> 4734
    //   4730: invokestatic a : (Ljava/lang/Throwable;)Ljava/lang/Throwable;
    //   4733: athrow
    //   4734: aload #22
    //   4736: bipush #7
    //   4738: iaload
    //   4739: aload #22
    //   4741: iconst_4
    //   4742: iaload
    //   4743: bipush #6
    //   4745: iushr
    //   4746: aload #22
    //   4748: iconst_4
    //   4749: iaload
    //   4750: bipush #26
    //   4752: ishl
    //   4753: ior
    //   4754: aload #22
    //   4756: iconst_4
    //   4757: iaload
    //   4758: bipush #11
    //   4760: iushr
    //   4761: aload #22
    //   4763: iconst_4
    //   4764: iaload
    //   4765: bipush #21
    //   4767: ishl
    //   4768: ior
    //   4769: ixor
    //   4770: aload #22
    //   4772: iconst_4
    //   4773: iaload
    //   4774: bipush #25
    //   4776: iushr
    //   4777: aload #22
    //   4779: iconst_4
    //   4780: iaload
    //   4781: bipush #7
    //   4783: ishl
    //   4784: ior
    //   4785: ixor
    //   4786: iadd
    //   4787: aload #22
    //   4789: bipush #6
    //   4791: iaload
    //   4792: aload #22
    //   4794: iconst_4
    //   4795: iaload
    //   4796: aload #22
    //   4798: iconst_5
    //   4799: iaload
    //   4800: aload #22
    //   4802: bipush #6
    //   4804: iaload
    //   4805: ixor
    //   4806: iand
    //   4807: ixor
    //   4808: iadd
    //   4809: aload #7
    //   4811: iload #23
    //   4813: iaload
    //   4814: iadd
    //   4815: aload #21
    //   4817: iload #23
    //   4819: iaload
    //   4820: iadd
    //   4821: istore #24
    //   4823: aload #22
    //   4825: iconst_0
    //   4826: iaload
    //   4827: iconst_2
    //   4828: iushr
    //   4829: aload #22
    //   4831: iconst_0
    //   4832: iaload
    //   4833: bipush #30
    //   4835: ishl
    //   4836: ior
    //   4837: aload #22
    //   4839: iconst_0
    //   4840: iaload
    //   4841: bipush #13
    //   4843: iushr
    //   4844: aload #22
    //   4846: iconst_0
    //   4847: iaload
    //   4848: bipush #19
    //   4850: ishl
    //   4851: ior
    //   4852: ixor
    //   4853: aload #22
    //   4855: iconst_0
    //   4856: iaload
    //   4857: bipush #22
    //   4859: iushr
    //   4860: aload #22
    //   4862: iconst_0
    //   4863: iaload
    //   4864: bipush #10
    //   4866: ishl
    //   4867: ior
    //   4868: ixor
    //   4869: aload #22
    //   4871: iconst_0
    //   4872: iaload
    //   4873: aload #22
    //   4875: iconst_1
    //   4876: iaload
    //   4877: iand
    //   4878: aload #22
    //   4880: iconst_2
    //   4881: iaload
    //   4882: aload #22
    //   4884: iconst_0
    //   4885: iaload
    //   4886: aload #22
    //   4888: iconst_1
    //   4889: iaload
    //   4890: ior
    //   4891: iand
    //   4892: ior
    //   4893: iadd
    //   4894: istore #25
    //   4896: aload #22
    //   4898: iconst_3
    //   4899: dup2
    //   4900: iaload
    //   4901: iload #24
    //   4903: iadd
    //   4904: iastore
    //   4905: aload #22
    //   4907: bipush #7
    //   4909: iload #24
    //   4911: iload #25
    //   4913: iadd
    //   4914: iastore
    //   4915: aload #22
    //   4917: bipush #7
    //   4919: iaload
    //   4920: istore #24
    //   4922: aload #22
    //   4924: bipush #7
    //   4926: aload #22
    //   4928: bipush #6
    //   4930: iaload
    //   4931: iastore
    //   4932: aload #22
    //   4934: bipush #6
    //   4936: aload #22
    //   4938: iconst_5
    //   4939: iaload
    //   4940: iastore
    //   4941: aload #22
    //   4943: iconst_5
    //   4944: aload #22
    //   4946: iconst_4
    //   4947: iaload
    //   4948: iastore
    //   4949: aload #22
    //   4951: iconst_4
    //   4952: aload #22
    //   4954: iconst_3
    //   4955: iaload
    //   4956: iastore
    //   4957: aload #22
    //   4959: iconst_3
    //   4960: aload #22
    //   4962: iconst_2
    //   4963: iaload
    //   4964: iastore
    //   4965: aload #22
    //   4967: iconst_2
    //   4968: aload #22
    //   4970: iconst_1
    //   4971: iaload
    //   4972: iastore
    //   4973: aload #22
    //   4975: iconst_1
    //   4976: aload #22
    //   4978: iconst_0
    //   4979: iaload
    //   4980: iastore
    //   4981: aload #22
    //   4983: iconst_0
    //   4984: iload #24
    //   4986: iastore
    //   4987: iinc #23, 1
    //   4990: iload_2
    //   4991: ifeq -> 4499
    //   4994: iconst_0
    //   4995: istore #23
    //   4997: iload #23
    //   4999: bipush #8
    //   5001: if_icmpge -> 5024
    //   5004: aload #9
    //   5006: iload #23
    //   5008: dup2
    //   5009: iaload
    //   5010: aload #22
    //   5012: iload #23
    //   5014: iaload
    //   5015: iadd
    //   5016: iastore
    //   5017: iinc #23, 1
    //   5020: iload_2
    //   5021: ifeq -> 4997
    //   5024: bipush #32
    //   5026: newarray byte
    //   5028: astore #5
    //   5030: aload #5
    //   5032: iconst_0
    //   5033: aload #9
    //   5035: iconst_0
    //   5036: iaload
    //   5037: bipush #24
    //   5039: iushr
    //   5040: i2b
    //   5041: bastore
    //   5042: aload #5
    //   5044: iconst_1
    //   5045: aload #9
    //   5047: iconst_0
    //   5048: iaload
    //   5049: bipush #16
    //   5051: iushr
    //   5052: i2b
    //   5053: bastore
    //   5054: aload #5
    //   5056: iconst_2
    //   5057: aload #9
    //   5059: iconst_0
    //   5060: iaload
    //   5061: bipush #8
    //   5063: iushr
    //   5064: i2b
    //   5065: bastore
    //   5066: aload #5
    //   5068: iconst_3
    //   5069: aload #9
    //   5071: iconst_0
    //   5072: iaload
    //   5073: i2b
    //   5074: bastore
    //   5075: aload #5
    //   5077: iconst_4
    //   5078: aload #9
    //   5080: iconst_1
    //   5081: iaload
    //   5082: bipush #24
    //   5084: iushr
    //   5085: i2b
    //   5086: bastore
    //   5087: aload #5
    //   5089: iconst_5
    //   5090: aload #9
    //   5092: iconst_1
    //   5093: iaload
    //   5094: bipush #16
    //   5096: iushr
    //   5097: i2b
    //   5098: bastore
    //   5099: aload #5
    //   5101: bipush #6
    //   5103: aload #9
    //   5105: iconst_1
    //   5106: iaload
    //   5107: bipush #8
    //   5109: iushr
    //   5110: i2b
    //   5111: bastore
    //   5112: aload #5
    //   5114: bipush #7
    //   5116: aload #9
    //   5118: iconst_1
    //   5119: iaload
    //   5120: i2b
    //   5121: bastore
    //   5122: aload #5
    //   5124: bipush #8
    //   5126: aload #9
    //   5128: iconst_2
    //   5129: iaload
    //   5130: bipush #24
    //   5132: iushr
    //   5133: i2b
    //   5134: bastore
    //   5135: aload #5
    //   5137: bipush #9
    //   5139: aload #9
    //   5141: iconst_2
    //   5142: iaload
    //   5143: bipush #16
    //   5145: iushr
    //   5146: i2b
    //   5147: bastore
    //   5148: aload #5
    //   5150: bipush #10
    //   5152: aload #9
    //   5154: iconst_2
    //   5155: iaload
    //   5156: bipush #8
    //   5158: iushr
    //   5159: i2b
    //   5160: bastore
    //   5161: aload #5
    //   5163: bipush #11
    //   5165: aload #9
    //   5167: iconst_2
    //   5168: iaload
    //   5169: i2b
    //   5170: bastore
    //   5171: aload #5
    //   5173: bipush #12
    //   5175: aload #9
    //   5177: iconst_3
    //   5178: iaload
    //   5179: bipush #24
    //   5181: iushr
    //   5182: i2b
    //   5183: bastore
    //   5184: aload #5
    //   5186: bipush #13
    //   5188: aload #9
    //   5190: iconst_3
    //   5191: iaload
    //   5192: bipush #16
    //   5194: iushr
    //   5195: i2b
    //   5196: bastore
    //   5197: aload #5
    //   5199: bipush #14
    //   5201: aload #9
    //   5203: iconst_3
    //   5204: iaload
    //   5205: bipush #8
    //   5207: iushr
    //   5208: i2b
    //   5209: bastore
    //   5210: aload #5
    //   5212: bipush #15
    //   5214: aload #9
    //   5216: iconst_3
    //   5217: iaload
    //   5218: i2b
    //   5219: bastore
    //   5220: aload #5
    //   5222: bipush #16
    //   5224: aload #9
    //   5226: iconst_4
    //   5227: iaload
    //   5228: bipush #24
    //   5230: iushr
    //   5231: i2b
    //   5232: bastore
    //   5233: aload #5
    //   5235: bipush #17
    //   5237: aload #9
    //   5239: iconst_4
    //   5240: iaload
    //   5241: bipush #16
    //   5243: iushr
    //   5244: i2b
    //   5245: bastore
    //   5246: aload #5
    //   5248: bipush #18
    //   5250: aload #9
    //   5252: iconst_4
    //   5253: iaload
    //   5254: bipush #8
    //   5256: iushr
    //   5257: i2b
    //   5258: bastore
    //   5259: aload #5
    //   5261: bipush #19
    //   5263: aload #9
    //   5265: iconst_4
    //   5266: iaload
    //   5267: i2b
    //   5268: bastore
    //   5269: aload #5
    //   5271: bipush #20
    //   5273: aload #9
    //   5275: iconst_5
    //   5276: iaload
    //   5277: bipush #24
    //   5279: iushr
    //   5280: i2b
    //   5281: bastore
    //   5282: aload #5
    //   5284: bipush #21
    //   5286: aload #9
    //   5288: iconst_5
    //   5289: iaload
    //   5290: bipush #16
    //   5292: iushr
    //   5293: i2b
    //   5294: bastore
    //   5295: aload #5
    //   5297: bipush #22
    //   5299: aload #9
    //   5301: iconst_5
    //   5302: iaload
    //   5303: bipush #8
    //   5305: iushr
    //   5306: i2b
    //   5307: bastore
    //   5308: aload #5
    //   5310: bipush #23
    //   5312: aload #9
    //   5314: iconst_5
    //   5315: iaload
    //   5316: i2b
    //   5317: bastore
    //   5318: aload #5
    //   5320: bipush #24
    //   5322: aload #9
    //   5324: bipush #6
    //   5326: iaload
    //   5327: bipush #24
    //   5329: iushr
    //   5330: i2b
    //   5331: bastore
    //   5332: aload #5
    //   5334: bipush #25
    //   5336: aload #9
    //   5338: bipush #6
    //   5340: iaload
    //   5341: bipush #16
    //   5343: iushr
    //   5344: i2b
    //   5345: bastore
    //   5346: aload #5
    //   5348: bipush #26
    //   5350: aload #9
    //   5352: bipush #6
    //   5354: iaload
    //   5355: bipush #8
    //   5357: iushr
    //   5358: i2b
    //   5359: bastore
    //   5360: aload #5
    //   5362: bipush #27
    //   5364: aload #9
    //   5366: bipush #6
    //   5368: iaload
    //   5369: i2b
    //   5370: bastore
    //   5371: aload #5
    //   5373: bipush #28
    //   5375: aload #9
    //   5377: bipush #7
    //   5379: iaload
    //   5380: bipush #24
    //   5382: iushr
    //   5383: i2b
    //   5384: bastore
    //   5385: aload #5
    //   5387: bipush #29
    //   5389: aload #9
    //   5391: bipush #7
    //   5393: iaload
    //   5394: bipush #16
    //   5396: iushr
    //   5397: i2b
    //   5398: bastore
    //   5399: aload #5
    //   5401: bipush #30
    //   5403: aload #9
    //   5405: bipush #7
    //   5407: iaload
    //   5408: bipush #8
    //   5410: iushr
    //   5411: i2b
    //   5412: bastore
    //   5413: aload #5
    //   5415: bipush #31
    //   5417: aload #9
    //   5419: bipush #7
    //   5421: iaload
    //   5422: i2b
    //   5423: bastore
    //   5424: new java/math/BigInteger
    //   5427: dup
    //   5428: aload #5
    //   5430: invokespecial <init> : ([B)V
    //   5433: invokevirtual abs : ()Ljava/math/BigInteger;
    //   5436: putstatic burp/Zb6a.Zz : Ljava/lang/Object;
    //   5439: new java/lang/StringBuilder
    //   5442: dup
    //   5443: invokespecial <init> : ()V
    //   5446: astore #4
    //   5448: iconst_0
    //   5449: istore #5
    //   5451: iload #5
    //   5453: bipush #32
    //   5455: if_icmpge -> 6823
    //   5458: iload #5
    //   5460: tableswitch default -> 6816, 0 -> 5604, 1 -> 5642, 2 -> 5680, 3 -> 5718, 4 -> 5756, 5 -> 5794, 6 -> 5832, 7 -> 5870, 8 -> 5908, 9 -> 5946, 10 -> 5984, 11 -> 6022, 12 -> 6060, 13 -> 6098, 14 -> 6136, 15 -> 6174, 16 -> 6212, 17 -> 6250, 18 -> 6288, 19 -> 6326, 20 -> 6364, 21 -> 6402, 22 -> 6440, 23 -> 6478, 24 -> 6516, 25 -> 6554, 26 -> 6592, 27 -> 6630, 28 -> 6668, 29 -> 6706, 30 -> 6744, 31 -> 6782
    //   5604: aload #4
    //   5606: getstatic burp/Zko9.Zf : Ljava/lang/String;
    //   5609: getstatic burp/Zlfi.ZV : Ljava/lang/Object;
    //   5612: checkcast java/math/BigInteger
    //   5615: invokevirtual intValue : ()I
    //   5618: bipush #32
    //   5620: irem
    //   5621: invokestatic abs : (I)I
    //   5624: invokevirtual charAt : (I)C
    //   5627: invokevirtual append : (C)Ljava/lang/StringBuilder;
    //   5630: pop
    //   5631: iload_2
    //   5632: ifeq -> 6816
    //   5635: goto -> 5642
    //   5638: invokestatic a : (Ljava/lang/Throwable;)Ljava/lang/Throwable;
    //   5641: athrow
    //   5642: aload #4
    //   5644: getstatic burp/Zd0.Zi : Ljava/lang/String;
    //   5647: getstatic burp/Zg99.ZZ : Ljava/lang/Object;
    //   5650: checkcast java/math/BigInteger
    //   5653: invokevirtual intValue : ()I
    //   5656: bipush #32
    //   5658: irem
    //   5659: invokestatic abs : (I)I
    //   5662: invokevirtual charAt : (I)C
    //   5665: invokevirtual append : (C)Ljava/lang/StringBuilder;
    //   5668: pop
    //   5669: iload_2
    //   5670: ifeq -> 6816
    //   5673: goto -> 5680
    //   5676: invokestatic a : (Ljava/lang/Throwable;)Ljava/lang/Throwable;
    //   5679: athrow
    //   5680: aload #4
    //   5682: getstatic burp/Zms1.ZZ : Ljava/lang/String;
    //   5685: getstatic burp/Ze_e.Za : Ljava/lang/Object;
    //   5688: checkcast java/math/BigInteger
    //   5691: invokevirtual intValue : ()I
    //   5694: bipush #32
    //   5696: irem
    //   5697: invokestatic abs : (I)I
    //   5700: invokevirtual charAt : (I)C
    //   5703: invokevirtual append : (C)Ljava/lang/StringBuilder;
    //   5706: pop
    //   5707: iload_2
    //   5708: ifeq -> 6816
    //   5711: goto -> 5718
    //   5714: invokestatic a : (Ljava/lang/Throwable;)Ljava/lang/Throwable;
    //   5717: athrow
    //   5718: aload #4
    //   5720: getstatic burp/Zgia.Zh : Ljava/lang/String;
    //   5723: getstatic burp/Zlp8.Zu : Ljava/lang/Object;
    //   5726: checkcast java/math/BigInteger
    //   5729: invokevirtual intValue : ()I
    //   5732: bipush #32
    //   5734: irem
    //   5735: invokestatic abs : (I)I
    //   5738: invokevirtual charAt : (I)C
    //   5741: invokevirtual append : (C)Ljava/lang/StringBuilder;
    //   5744: pop
    //   5745: iload_2
    //   5746: ifeq -> 6816
    //   5749: goto -> 5756
    //   5752: invokestatic a : (Ljava/lang/Throwable;)Ljava/lang/Throwable;
    //   5755: athrow
    //   5756: aload #4
    //   5758: getstatic burp/Zkmx.Zg : Ljava/lang/String;
    //   5761: getstatic burp/Zgsy.ZC : Ljava/lang/Object;
    //   5764: checkcast java/math/BigInteger
    //   5767: invokevirtual intValue : ()I
    //   5770: bipush #32
    //   5772: irem
    //   5773: invokestatic abs : (I)I
    //   5776: invokevirtual charAt : (I)C
    //   5779: invokevirtual append : (C)Ljava/lang/StringBuilder;
    //   5782: pop
    //   5783: iload_2
    //   5784: ifeq -> 6816
    //   5787: goto -> 5794
    //   5790: invokestatic a : (Ljava/lang/Throwable;)Ljava/lang/Throwable;
    //   5793: athrow
    //   5794: aload #4
    //   5796: getstatic burp/Zkku.Zq : Ljava/lang/String;
    //   5799: getstatic burp/Zbu.ZW : Ljava/lang/Object;
    //   5802: checkcast java/math/BigInteger
    //   5805: invokevirtual intValue : ()I
    //   5808: bipush #32
    //   5810: irem
    //   5811: invokestatic abs : (I)I
    //   5814: invokevirtual charAt : (I)C
    //   5817: invokevirtual append : (C)Ljava/lang/StringBuilder;
    //   5820: pop
    //   5821: iload_2
    //   5822: ifeq -> 6816
    //   5825: goto -> 5832
    //   5828: invokestatic a : (Ljava/lang/Throwable;)Ljava/lang/Throwable;
    //   5831: athrow
    //   5832: aload #4
    //   5834: getstatic burp/Zl1q.ZY : Ljava/lang/String;
    //   5837: getstatic burp/Zbo7.Zl : Ljava/lang/Object;
    //   5840: checkcast java/math/BigInteger
    //   5843: invokevirtual intValue : ()I
    //   5846: bipush #32
    //   5848: irem
    //   5849: invokestatic abs : (I)I
    //   5852: invokevirtual charAt : (I)C
    //   5855: invokevirtual append : (C)Ljava/lang/StringBuilder;
    //   5858: pop
    //   5859: iload_2
    //   5860: ifeq -> 6816
    //   5863: goto -> 5870
    //   5866: invokestatic a : (Ljava/lang/Throwable;)Ljava/lang/Throwable;
    //   5869: athrow
    //   5870: aload #4
    //   5872: getstatic burp/Zlsg.Zs : Ljava/lang/String;
    //   5875: getstatic burp/Zm3x.ZM : Ljava/lang/Object;
    //   5878: checkcast java/math/BigInteger
    //   5881: invokevirtual intValue : ()I
    //   5884: bipush #32
    //   5886: irem
    //   5887: invokestatic abs : (I)I
    //   5890: invokevirtual charAt : (I)C
    //   5893: invokevirtual append : (C)Ljava/lang/StringBuilder;
    //   5896: pop
    //   5897: iload_2
    //   5898: ifeq -> 6816
    //   5901: goto -> 5908
    //   5904: invokestatic a : (Ljava/lang/Throwable;)Ljava/lang/Throwable;
    //   5907: athrow
    //   5908: aload #4
    //   5910: getstatic burp/Zm6g.ZG : Ljava/lang/String;
    //   5913: getstatic burp/Zebu.Zu : Ljava/lang/Object;
    //   5916: checkcast java/math/BigInteger
    //   5919: invokevirtual intValue : ()I
    //   5922: bipush #32
    //   5924: irem
    //   5925: invokestatic abs : (I)I
    //   5928: invokevirtual charAt : (I)C
    //   5931: invokevirtual append : (C)Ljava/lang/StringBuilder;
    //   5934: pop
    //   5935: iload_2
    //   5936: ifeq -> 6816
    //   5939: goto -> 5946
    //   5942: invokestatic a : (Ljava/lang/Throwable;)Ljava/lang/Throwable;
    //   5945: athrow
    //   5946: aload #4
    //   5948: getstatic burp/Zmvk.Z_ : Ljava/lang/String;
    //   5951: getstatic burp/Zry0.Zr : Ljava/lang/Object;
    //   5954: checkcast java/math/BigInteger
    //   5957: invokevirtual intValue : ()I
    //   5960: bipush #32
    //   5962: irem
    //   5963: invokestatic abs : (I)I
    //   5966: invokevirtual charAt : (I)C
    //   5969: invokevirtual append : (C)Ljava/lang/StringBuilder;
    //   5972: pop
    //   5973: iload_2
    //   5974: ifeq -> 6816
    //   5977: goto -> 5984
    //   5980: invokestatic a : (Ljava/lang/Throwable;)Ljava/lang/Throwable;
    //   5983: athrow
    //   5984: aload #4
    //   5986: getstatic burp/Zkhy.Zu : Ljava/lang/String;
    //   5989: getstatic burp/Zgco.Zx : Ljava/lang/Object;
    //   5992: checkcast java/math/BigInteger
    //   5995: invokevirtual intValue : ()I
    //   5998: bipush #32
    //   6000: irem
    //   6001: invokestatic abs : (I)I
    //   6004: invokevirtual charAt : (I)C
    //   6007: invokevirtual append : (C)Ljava/lang/StringBuilder;
    //   6010: pop
    //   6011: iload_2
    //   6012: ifeq -> 6816
    //   6015: goto -> 6022
    //   6018: invokestatic a : (Ljava/lang/Throwable;)Ljava/lang/Throwable;
    //   6021: athrow
    //   6022: aload #4
    //   6024: getstatic burp/Zenr.Z_ : Ljava/lang/String;
    //   6027: getstatic burp/Zs8q.ZI : Ljava/lang/Object;
    //   6030: checkcast java/math/BigInteger
    //   6033: invokevirtual intValue : ()I
    //   6036: bipush #32
    //   6038: irem
    //   6039: invokestatic abs : (I)I
    //   6042: invokevirtual charAt : (I)C
    //   6045: invokevirtual append : (C)Ljava/lang/StringBuilder;
    //   6048: pop
    //   6049: iload_2
    //   6050: ifeq -> 6816
    //   6053: goto -> 6060
    //   6056: invokestatic a : (Ljava/lang/Throwable;)Ljava/lang/Throwable;
    //   6059: athrow
    //   6060: aload #4
    //   6062: getstatic burp/Zvi.ZR : Ljava/lang/String;
    //   6065: getstatic burp/Ztd3.ZX : Ljava/lang/Object;
    //   6068: checkcast java/math/BigInteger
    //   6071: invokevirtual intValue : ()I
    //   6074: bipush #32
    //   6076: irem
    //   6077: invokestatic abs : (I)I
    //   6080: invokevirtual charAt : (I)C
    //   6083: invokevirtual append : (C)Ljava/lang/StringBuilder;
    //   6086: pop
    //   6087: iload_2
    //   6088: ifeq -> 6816
    //   6091: goto -> 6098
    //   6094: invokestatic a : (Ljava/lang/Throwable;)Ljava/lang/Throwable;
    //   6097: athrow
    //   6098: aload #4
    //   6100: getstatic burp/Zmrc.Zx : Ljava/lang/String;
    //   6103: getstatic burp/Zl1e.Zp : Ljava/lang/Object;
    //   6106: checkcast java/math/BigInteger
    //   6109: invokevirtual intValue : ()I
    //   6112: bipush #32
    //   6114: irem
    //   6115: invokestatic abs : (I)I
    //   6118: invokevirtual charAt : (I)C
    //   6121: invokevirtual append : (C)Ljava/lang/StringBuilder;
    //   6124: pop
    //   6125: iload_2
    //   6126: ifeq -> 6816
    //   6129: goto -> 6136
    //   6132: invokestatic a : (Ljava/lang/Throwable;)Ljava/lang/Throwable;
    //   6135: athrow
    //   6136: aload #4
    //   6138: getstatic burp/Zb29.Zf : Ljava/lang/String;
    //   6141: getstatic burp/Zelc.ZR : Ljava/lang/Object;
    //   6144: checkcast java/math/BigInteger
    //   6147: invokevirtual intValue : ()I
    //   6150: bipush #32
    //   6152: irem
    //   6153: invokestatic abs : (I)I
    //   6156: invokevirtual charAt : (I)C
    //   6159: invokevirtual append : (C)Ljava/lang/StringBuilder;
    //   6162: pop
    //   6163: iload_2
    //   6164: ifeq -> 6816
    //   6167: goto -> 6174
    //   6170: invokestatic a : (Ljava/lang/Throwable;)Ljava/lang/Throwable;
    //   6173: athrow
    //   6174: aload #4
    //   6176: getstatic burp/Zx4k.ZC : Ljava/lang/String;
    //   6179: getstatic burp/Ztzh.ZT : Ljava/lang/Object;
    //   6182: checkcast java/math/BigInteger
    //   6185: invokevirtual intValue : ()I
    //   6188: bipush #32
    //   6190: irem
    //   6191: invokestatic abs : (I)I
    //   6194: invokevirtual charAt : (I)C
    //   6197: invokevirtual append : (C)Ljava/lang/StringBuilder;
    //   6200: pop
    //   6201: iload_2
    //   6202: ifeq -> 6816
    //   6205: goto -> 6212
    //   6208: invokestatic a : (Ljava/lang/Throwable;)Ljava/lang/Throwable;
    //   6211: athrow
    //   6212: aload #4
    //   6214: getstatic burp/Zl_1.ZH : Ljava/lang/String;
    //   6217: getstatic burp/Zgre.ZD : Ljava/lang/Object;
    //   6220: checkcast java/math/BigInteger
    //   6223: invokevirtual intValue : ()I
    //   6226: bipush #32
    //   6228: irem
    //   6229: invokestatic abs : (I)I
    //   6232: invokevirtual charAt : (I)C
    //   6235: invokevirtual append : (C)Ljava/lang/StringBuilder;
    //   6238: pop
    //   6239: iload_2
    //   6240: ifeq -> 6816
    //   6243: goto -> 6250
    //   6246: invokestatic a : (Ljava/lang/Throwable;)Ljava/lang/Throwable;
    //   6249: athrow
    //   6250: aload #4
    //   6252: getstatic burp/Zrye.Za : Ljava/lang/String;
    //   6255: getstatic burp/Zxdy.ZZ : Ljava/lang/Object;
    //   6258: checkcast java/math/BigInteger
    //   6261: invokevirtual intValue : ()I
    //   6264: bipush #32
    //   6266: irem
    //   6267: invokestatic abs : (I)I
    //   6270: invokevirtual charAt : (I)C
    //   6273: invokevirtual append : (C)Ljava/lang/StringBuilder;
    //   6276: pop
    //   6277: iload_2
    //   6278: ifeq -> 6816
    //   6281: goto -> 6288
    //   6284: invokestatic a : (Ljava/lang/Throwable;)Ljava/lang/Throwable;
    //   6287: athrow
    //   6288: aload #4
    //   6290: getstatic burp/Zsn6.Zs : Ljava/lang/String;
    //   6293: getstatic burp/Zg_y.ZR : Ljava/lang/Object;
    //   6296: checkcast java/math/BigInteger
    //   6299: invokevirtual intValue : ()I
    //   6302: bipush #32
    //   6304: irem
    //   6305: invokestatic abs : (I)I
    //   6308: invokevirtual charAt : (I)C
    //   6311: invokevirtual append : (C)Ljava/lang/StringBuilder;
    //   6314: pop
    //   6315: iload_2
    //   6316: ifeq -> 6816
    //   6319: goto -> 6326
    //   6322: invokestatic a : (Ljava/lang/Throwable;)Ljava/lang/Throwable;
    //   6325: athrow
    //   6326: aload #4
    //   6328: getstatic burp/Zec_.Zv : Ljava/lang/String;
    //   6331: getstatic burp/Zrnw.ZN : Ljava/lang/Object;
    //   6334: checkcast java/math/BigInteger
    //   6337: invokevirtual intValue : ()I
    //   6340: bipush #32
    //   6342: irem
    //   6343: invokestatic abs : (I)I
    //   6346: invokevirtual charAt : (I)C
    //   6349: invokevirtual append : (C)Ljava/lang/StringBuilder;
    //   6352: pop
    //   6353: iload_2
    //   6354: ifeq -> 6816
    //   6357: goto -> 6364
    //   6360: invokestatic a : (Ljava/lang/Throwable;)Ljava/lang/Throwable;
    //   6363: athrow
    //   6364: aload #4
    //   6366: getstatic burp/Ze0w.ZT : Ljava/lang/String;
    //   6369: getstatic burp/Zgr4.ZL : Ljava/lang/Object;
    //   6372: checkcast java/math/BigInteger
    //   6375: invokevirtual intValue : ()I
    //   6378: bipush #32
    //   6380: irem
    //   6381: invokestatic abs : (I)I
    //   6384: invokevirtual charAt : (I)C
    //   6387: invokevirtual append : (C)Ljava/lang/StringBuilder;
    //   6390: pop
    //   6391: iload_2
    //   6392: ifeq -> 6816
    //   6395: goto -> 6402
    //   6398: invokestatic a : (Ljava/lang/Throwable;)Ljava/lang/Throwable;
    //   6401: athrow
    //   6402: aload #4
    //   6404: getstatic burp/Zsgl.ZG : Ljava/lang/String;
    //   6407: getstatic burp/Zlbr.Zp : Ljava/lang/Object;
    //   6410: checkcast java/math/BigInteger
    //   6413: invokevirtual intValue : ()I
    //   6416: bipush #32
    //   6418: irem
    //   6419: invokestatic abs : (I)I
    //   6422: invokevirtual charAt : (I)C
    //   6425: invokevirtual append : (C)Ljava/lang/StringBuilder;
    //   6428: pop
    //   6429: iload_2
    //   6430: ifeq -> 6816
    //   6433: goto -> 6440
    //   6436: invokestatic a : (Ljava/lang/Throwable;)Ljava/lang/Throwable;
    //   6439: athrow
    //   6440: aload #4
    //   6442: getstatic burp/Zgpx.Z_ : Ljava/lang/String;
    //   6445: getstatic burp/Zss6.ZG : Ljava/lang/Object;
    //   6448: checkcast java/math/BigInteger
    //   6451: invokevirtual intValue : ()I
    //   6454: bipush #32
    //   6456: irem
    //   6457: invokestatic abs : (I)I
    //   6460: invokevirtual charAt : (I)C
    //   6463: invokevirtual append : (C)Ljava/lang/StringBuilder;
    //   6466: pop
    //   6467: iload_2
    //   6468: ifeq -> 6816
    //   6471: goto -> 6478
    //   6474: invokestatic a : (Ljava/lang/Throwable;)Ljava/lang/Throwable;
    //   6477: athrow
    //   6478: aload #4
    //   6480: getstatic burp/Zg97.ZX : Ljava/lang/String;
    //   6483: getstatic burp/Zt5b.Zc : Ljava/lang/Object;
    //   6486: checkcast java/math/BigInteger
    //   6489: invokevirtual intValue : ()I
    //   6492: bipush #32
    //   6494: irem
    //   6495: invokestatic abs : (I)I
    //   6498: invokevirtual charAt : (I)C
    //   6501: invokevirtual append : (C)Ljava/lang/StringBuilder;
    //   6504: pop
    //   6505: iload_2
    //   6506: ifeq -> 6816
    //   6509: goto -> 6516
    //   6512: invokestatic a : (Ljava/lang/Throwable;)Ljava/lang/Throwable;
    //   6515: athrow
    //   6516: aload #4
    //   6518: getstatic burp/Zgde.Zr : Ljava/lang/String;
    //   6521: getstatic burp/Zmzj.Zm : Ljava/lang/Object;
    //   6524: checkcast java/math/BigInteger
    //   6527: invokevirtual intValue : ()I
    //   6530: bipush #32
    //   6532: irem
    //   6533: invokestatic abs : (I)I
    //   6536: invokevirtual charAt : (I)C
    //   6539: invokevirtual append : (C)Ljava/lang/StringBuilder;
    //   6542: pop
    //   6543: iload_2
    //   6544: ifeq -> 6816
    //   6547: goto -> 6554
    //   6550: invokestatic a : (Ljava/lang/Throwable;)Ljava/lang/Throwable;
    //   6553: athrow
    //   6554: aload #4
    //   6556: getstatic burp/Zb38.Zr : Ljava/lang/String;
    //   6559: getstatic burp/Zry9.Zw : Ljava/lang/Object;
    //   6562: checkcast java/math/BigInteger
    //   6565: invokevirtual intValue : ()I
    //   6568: bipush #32
    //   6570: irem
    //   6571: invokestatic abs : (I)I
    //   6574: invokevirtual charAt : (I)C
    //   6577: invokevirtual append : (C)Ljava/lang/StringBuilder;
    //   6580: pop
    //   6581: iload_2
    //   6582: ifeq -> 6816
    //   6585: goto -> 6592
    //   6588: invokestatic a : (Ljava/lang/Throwable;)Ljava/lang/Throwable;
    //   6591: athrow
    //   6592: aload #4
    //   6594: getstatic burp/Zx4u.ZL : Ljava/lang/String;
    //   6597: getstatic burp/Zelz.Z_ : Ljava/lang/Object;
    //   6600: checkcast java/math/BigInteger
    //   6603: invokevirtual intValue : ()I
    //   6606: bipush #32
    //   6608: irem
    //   6609: invokestatic abs : (I)I
    //   6612: invokevirtual charAt : (I)C
    //   6615: invokevirtual append : (C)Ljava/lang/StringBuilder;
    //   6618: pop
    //   6619: iload_2
    //   6620: ifeq -> 6816
    //   6623: goto -> 6630
    //   6626: invokestatic a : (Ljava/lang/Throwable;)Ljava/lang/Throwable;
    //   6629: athrow
    //   6630: aload #4
    //   6632: getstatic burp/Zlw8.Zs : Ljava/lang/String;
    //   6635: getstatic burp/Zzqj.Zq : Ljava/lang/Object;
    //   6638: checkcast java/math/BigInteger
    //   6641: invokevirtual intValue : ()I
    //   6644: bipush #32
    //   6646: irem
    //   6647: invokestatic abs : (I)I
    //   6650: invokevirtual charAt : (I)C
    //   6653: invokevirtual append : (C)Ljava/lang/StringBuilder;
    //   6656: pop
    //   6657: iload_2
    //   6658: ifeq -> 6816
    //   6661: goto -> 6668
    //   6664: invokestatic a : (Ljava/lang/Throwable;)Ljava/lang/Throwable;
    //   6667: athrow
    //   6668: aload #4
    //   6670: getstatic burp/Zb14.Ze : Ljava/lang/String;
    //   6673: getstatic burp/Zbzk.ZI : Ljava/lang/Object;
    //   6676: checkcast java/math/BigInteger
    //   6679: invokevirtual intValue : ()I
    //   6682: bipush #32
    //   6684: irem
    //   6685: invokestatic abs : (I)I
    //   6688: invokevirtual charAt : (I)C
    //   6691: invokevirtual append : (C)Ljava/lang/StringBuilder;
    //   6694: pop
    //   6695: iload_2
    //   6696: ifeq -> 6816
    //   6699: goto -> 6706
    //   6702: invokestatic a : (Ljava/lang/Throwable;)Ljava/lang/Throwable;
    //   6705: athrow
    //   6706: aload #4
    //   6708: getstatic burp/Ze_e.ZH : Ljava/lang/String;
    //   6711: getstatic burp/Ztv8.ZS : Ljava/lang/Object;
    //   6714: checkcast java/math/BigInteger
    //   6717: invokevirtual intValue : ()I
    //   6720: bipush #32
    //   6722: irem
    //   6723: invokestatic abs : (I)I
    //   6726: invokevirtual charAt : (I)C
    //   6729: invokevirtual append : (C)Ljava/lang/StringBuilder;
    //   6732: pop
    //   6733: iload_2
    //   6734: ifeq -> 6816
    //   6737: goto -> 6744
    //   6740: invokestatic a : (Ljava/lang/Throwable;)Ljava/lang/Throwable;
    //   6743: athrow
    //   6744: aload #4
    //   6746: getstatic burp/Zmhx.ZD : Ljava/lang/String;
    //   6749: getstatic burp/Zzh0.Z_ : Ljava/lang/Object;
    //   6752: checkcast java/math/BigInteger
    //   6755: invokevirtual intValue : ()I
    //   6758: bipush #32
    //   6760: irem
    //   6761: invokestatic abs : (I)I
    //   6764: invokevirtual charAt : (I)C
    //   6767: invokevirtual append : (C)Ljava/lang/StringBuilder;
    //   6770: pop
    //   6771: iload_2
    //   6772: ifeq -> 6816
    //   6775: goto -> 6782
    //   6778: invokestatic a : (Ljava/lang/Throwable;)Ljava/lang/Throwable;
    //   6781: athrow
    //   6782: aload #4
    //   6784: getstatic burp/Zb8_.ZP : Ljava/lang/String;
    //   6787: getstatic burp/Zr9j.Zw : Ljava/lang/Object;
    //   6790: checkcast java/math/BigInteger
    //   6793: invokevirtual intValue : ()I
    //   6796: bipush #32
    //   6798: irem
    //   6799: invokestatic abs : (I)I
    //   6802: invokevirtual charAt : (I)C
    //   6805: invokevirtual append : (C)Ljava/lang/StringBuilder;
    //   6808: pop
    //   6809: goto -> 6816
    //   6812: invokestatic a : (Ljava/lang/Throwable;)Ljava/lang/Throwable;
    //   6815: athrow
    //   6816: iinc #5, 1
    //   6819: iload_2
    //   6820: ifeq -> 5451
    //   6823: aload #4
    //   6825: invokevirtual toString : ()Ljava/lang/String;
    //   6828: putstatic burp/Ztzj.ZB : Ljava/lang/String;
    //   6831: sipush #13913
    //   6834: sipush #22667
    //   6837: invokestatic a : (II)Ljava/lang/String;
    //   6840: iconst_1
    //   6841: ldc burp/Zlx5
    //   6843: invokevirtual getClassLoader : ()Ljava/lang/ClassLoader;
    //   6846: invokestatic forName : (Ljava/lang/String;ZLjava/lang/ClassLoader;)Ljava/lang/Class;
    //   6849: invokevirtual getDeclaredFields : ()[Ljava/lang/reflect/Field;
    //   6852: astore #5
    //   6854: aload #5
    //   6856: arraylength
    //   6857: istore #6
    //   6859: iconst_0
    //   6860: istore #7
    //   6862: iload #7
    //   6864: iload #6
    //   6866: if_icmpge -> 7004
    //   6869: aload #5
    //   6871: iload #7
    //   6873: aaload
    //   6874: astore #8
    //   6876: aload #8
    //   6878: invokevirtual getModifiers : ()I
    //   6881: invokestatic isStatic : (I)Z
    //   6884: ifne -> 6894
    //   6887: goto -> 6997
    //   6890: invokestatic a : (Ljava/lang/Throwable;)Ljava/lang/Throwable;
    //   6893: athrow
    //   6894: aload #8
    //   6896: invokevirtual getType : ()Ljava/lang/Class;
    //   6899: astore #9
    //   6901: aload #9
    //   6903: ifnull -> 6984
    //   6906: aload #9
    //   6908: invokevirtual isPrimitive : ()Z
    //   6911: ifne -> 6984
    //   6914: goto -> 6921
    //   6917: invokestatic a : (Ljava/lang/Throwable;)Ljava/lang/Throwable;
    //   6920: athrow
    //   6921: aload #9
    //   6923: invokevirtual getPackage : ()Ljava/lang/Package;
    //   6926: ifnull -> 6984
    //   6929: goto -> 6936
    //   6932: invokestatic a : (Ljava/lang/Throwable;)Ljava/lang/Throwable;
    //   6935: athrow
    //   6936: aload #9
    //   6938: invokevirtual getPackage : ()Ljava/lang/Package;
    //   6941: invokevirtual getName : ()Ljava/lang/String;
    //   6944: ifnull -> 6984
    //   6947: goto -> 6954
    //   6950: invokestatic a : (Ljava/lang/Throwable;)Ljava/lang/Throwable;
    //   6953: athrow
    //   6954: aload #9
    //   6956: invokevirtual getPackage : ()Ljava/lang/Package;
    //   6959: invokevirtual getName : ()Ljava/lang/String;
    //   6962: sipush #13907
    //   6965: sipush #-17031
    //   6968: invokestatic a : (II)Ljava/lang/String;
    //   6971: invokevirtual startsWith : (Ljava/lang/String;)Z
    //   6974: ifne -> 6984
    //   6977: goto -> 6984
    //   6980: invokestatic a : (Ljava/lang/Throwable;)Ljava/lang/Throwable;
    //   6983: athrow
    //   6984: aload #8
    //   6986: iconst_1
    //   6987: invokevirtual setAccessible : (Z)V
    //   6990: aload #8
    //   6992: aconst_null
    //   6993: invokevirtual get : (Ljava/lang/Object;)Ljava/lang/Object;
    //   6996: pop
    //   6997: iinc #7, 1
    //   7000: iload_2
    //   7001: ifeq -> 6862
    //   7004: sipush #13908
    //   7007: sipush #-21805
    //   7010: invokestatic a : (II)Ljava/lang/String;
    //   7013: invokestatic forName : (Ljava/lang/String;)Ljava/lang/Class;
    //   7016: invokevirtual getDeclaredMethods : ()[Ljava/lang/reflect/Method;
    //   7019: astore #5
    //   7021: aload #5
    //   7023: arraylength
    //   7024: istore #6
    //   7026: iconst_0
    //   7027: istore #7
    //   7029: iload #7
    //   7031: iload #6
    //   7033: if_icmpge -> 7145
    //   7036: aload #5
    //   7038: iload #7
    //   7040: aaload
    //   7041: astore #8
    //   7043: aload #8
    //   7045: invokevirtual getParameterTypes : ()[Ljava/lang/Class;
    //   7048: pop
    //   7049: aload #8
    //   7051: invokevirtual getModifiers : ()I
    //   7054: invokestatic isStatic : (I)Z
    //   7057: ifeq -> 7131
    //   7060: aload #8
    //   7062: invokevirtual getParameterTypes : ()[Ljava/lang/Class;
    //   7065: arraylength
    //   7066: iconst_2
    //   7067: if_icmpne -> 7131
    //   7070: goto -> 7077
    //   7073: invokestatic a : (Ljava/lang/Throwable;)Ljava/lang/Throwable;
    //   7076: athrow
    //   7077: aload #8
    //   7079: invokevirtual getReturnType : ()Ljava/lang/Class;
    //   7082: getstatic java/lang/Boolean.TYPE : Ljava/lang/Class;
    //   7085: if_acmpne -> 7131
    //   7088: goto -> 7095
    //   7091: invokestatic a : (Ljava/lang/Throwable;)Ljava/lang/Throwable;
    //   7094: athrow
    //   7095: aload #8
    //   7097: iconst_1
    //   7098: invokevirtual setAccessible : (Z)V
    //   7101: aload #8
    //   7103: aconst_null
    //   7104: iconst_2
    //   7105: anewarray java/lang/Object
    //   7108: dup
    //   7109: iconst_0
    //   7110: aload_0
    //   7111: aastore
    //   7112: dup
    //   7113: iconst_1
    //   7114: aload_1
    //   7115: aastore
    //   7116: invokevirtual invoke : (Ljava/lang/Object;[Ljava/lang/Object;)Ljava/lang/Object;
    //   7119: pop
    //   7120: iload_2
    //   7121: ifeq -> 7145
    //   7124: goto -> 7131
    //   7127: invokestatic a : (Ljava/lang/Throwable;)Ljava/lang/Throwable;
    //   7130: athrow
    //   7131: iinc #7, 1
    //   7134: iload_2
    //   7135: ifeq -> 7029
    //   7138: goto -> 7145
    //   7141: invokestatic a : (Ljava/lang/Throwable;)Ljava/lang/Throwable;
    //   7144: athrow
    //   7145: sipush #13904
    //   7148: sipush #2964
    //   7151: invokestatic a : (II)Ljava/lang/String;
    //   7154: iconst_1
    //   7155: ldc burp/Zz3w
    //   7157: invokevirtual getClassLoader : ()Ljava/lang/ClassLoader;
    //   7160: invokestatic forName : (Ljava/lang/String;ZLjava/lang/ClassLoader;)Ljava/lang/Class;
    //   7163: invokevirtual getDeclaredFields : ()[Ljava/lang/reflect/Field;
    //   7166: astore #5
    //   7168: aload #5
    //   7170: arraylength
    //   7171: istore #6
    //   7173: iconst_0
    //   7174: istore #7
    //   7176: iload #7
    //   7178: iload #6
    //   7180: if_icmpge -> 7318
    //   7183: aload #5
    //   7185: iload #7
    //   7187: aaload
    //   7188: astore #8
    //   7190: aload #8
    //   7192: invokevirtual getModifiers : ()I
    //   7195: invokestatic isStatic : (I)Z
    //   7198: ifne -> 7208
    //   7201: goto -> 7311
    //   7204: invokestatic a : (Ljava/lang/Throwable;)Ljava/lang/Throwable;
    //   7207: athrow
    //   7208: aload #8
    //   7210: invokevirtual getType : ()Ljava/lang/Class;
    //   7213: astore #9
    //   7215: aload #9
    //   7217: ifnull -> 7298
    //   7220: aload #9
    //   7222: invokevirtual isPrimitive : ()Z
    //   7225: ifne -> 7298
    //   7228: goto -> 7235
    //   7231: invokestatic a : (Ljava/lang/Throwable;)Ljava/lang/Throwable;
    //   7234: athrow
    //   7235: aload #9
    //   7237: invokevirtual getPackage : ()Ljava/lang/Package;
    //   7240: ifnull -> 7298
    //   7243: goto -> 7250
    //   7246: invokestatic a : (Ljava/lang/Throwable;)Ljava/lang/Throwable;
    //   7249: athrow
    //   7250: aload #9
    //   7252: invokevirtual getPackage : ()Ljava/lang/Package;
    //   7255: invokevirtual getName : ()Ljava/lang/String;
    //   7258: ifnull -> 7298
    //   7261: goto -> 7268
    //   7264: invokestatic a : (Ljava/lang/Throwable;)Ljava/lang/Throwable;
    //   7267: athrow
    //   7268: aload #9
    //   7270: invokevirtual getPackage : ()Ljava/lang/Package;
    //   7273: invokevirtual getName : ()Ljava/lang/String;
    //   7276: sipush #13914
    //   7279: sipush #-11576
    //   7282: invokestatic a : (II)Ljava/lang/String;
    //   7285: invokevirtual startsWith : (Ljava/lang/String;)Z
    //   7288: ifne -> 7298
    //   7291: goto -> 7298
    //   7294: invokestatic a : (Ljava/lang/Throwable;)Ljava/lang/Throwable;
    //   7297: athrow
    //   7298: aload #8
    //   7300: iconst_1
    //   7301: invokevirtual setAccessible : (Z)V
    //   7304: aload #8
    //   7306: aconst_null
    //   7307: invokevirtual get : (Ljava/lang/Object;)Ljava/lang/Object;
    //   7310: pop
    //   7311: iinc #7, 1
    //   7314: iload_2
    //   7315: ifeq -> 7176
    //   7318: sipush #13906
    //   7321: sipush #15059
    //   7324: invokestatic a : (II)Ljava/lang/String;
    //   7327: invokestatic forName : (Ljava/lang/String;)Ljava/lang/Class;
    //   7330: invokevirtual getDeclaredMethods : ()[Ljava/lang/reflect/Method;
    //   7333: astore #5
    //   7335: aload #5
    //   7337: arraylength
    //   7338: istore #6
    //   7340: iconst_0
    //   7341: istore #7
    //   7343: iload #7
    //   7345: iload #6
    //   7347: if_icmpge -> 7480
    //   7350: aload #5
    //   7352: iload #7
    //   7354: aaload
    //   7355: astore #8
    //   7357: aload #8
    //   7359: invokevirtual getParameterTypes : ()[Ljava/lang/Class;
    //   7362: pop
    //   7363: aload #8
    //   7365: invokevirtual getModifiers : ()I
    //   7368: invokestatic isStatic : (I)Z
    //   7371: ifeq -> 7466
    //   7374: aload #8
    //   7376: invokevirtual getParameterTypes : ()[Ljava/lang/Class;
    //   7379: arraylength
    //   7380: iconst_2
    //   7381: if_icmpne -> 7466
    //   7384: goto -> 7391
    //   7387: invokestatic a : (Ljava/lang/Throwable;)Ljava/lang/Throwable;
    //   7390: athrow
    //   7391: aload #8
    //   7393: invokevirtual getReturnType : ()Ljava/lang/Class;
    //   7396: getstatic java/lang/Void.TYPE : Ljava/lang/Class;
    //   7399: invokevirtual equals : (Ljava/lang/Object;)Z
    //   7402: ifeq -> 7466
    //   7405: goto -> 7412
    //   7408: invokestatic a : (Ljava/lang/Throwable;)Ljava/lang/Throwable;
    //   7411: athrow
    //   7412: aload #8
    //   7414: iconst_1
    //   7415: invokevirtual setAccessible : (Z)V
    //   7418: aload #8
    //   7420: aconst_null
    //   7421: iconst_2
    //   7422: anewarray java/lang/Object
    //   7425: dup
    //   7426: iconst_0
    //   7427: aload_0
    //   7428: aastore
    //   7429: dup
    //   7430: iconst_1
    //   7431: aload_1
    //   7432: ifnonnull -> 7450
    //   7435: goto -> 7442
    //   7438: invokestatic a : (Ljava/lang/Throwable;)Ljava/lang/Throwable;
    //   7441: athrow
    //   7442: aload_1
    //   7443: goto -> 7457
    //   7446: invokestatic a : (Ljava/lang/Throwable;)Ljava/lang/Throwable;
    //   7449: athrow
    //   7450: aload_1
    //   7451: checkcast [B
    //   7454: invokevirtual clone : ()Ljava/lang/Object;
    //   7457: aastore
    //   7458: invokevirtual invoke : (Ljava/lang/Object;[Ljava/lang/Object;)Ljava/lang/Object;
    //   7461: pop
    //   7462: iload_2
    //   7463: ifeq -> 7480
    //   7466: iinc #7, 1
    //   7469: iload_2
    //   7470: ifeq -> 7343
    //   7473: goto -> 7480
    //   7476: invokestatic a : (Ljava/lang/Throwable;)Ljava/lang/Throwable;
    //   7479: athrow
    //   7480: iconst_0
    //   7481: istore #5
    //   7483: sipush #13909
    //   7486: sipush #5159
    //   7489: invokestatic a : (II)Ljava/lang/String;
    //   7492: iconst_1
    //   7493: ldc burp/Zgmo
    //   7495: invokevirtual getClassLoader : ()Ljava/lang/ClassLoader;
    //   7498: invokestatic forName : (Ljava/lang/String;ZLjava/lang/ClassLoader;)Ljava/lang/Class;
    //   7501: invokevirtual getDeclaredFields : ()[Ljava/lang/reflect/Field;
    //   7504: astore #6
    //   7506: aload #6
    //   7508: arraylength
    //   7509: istore #7
    //   7511: iconst_0
    //   7512: istore #8
    //   7514: iload #8
    //   7516: iload #7
    //   7518: if_icmpge -> 7656
    //   7521: aload #6
    //   7523: iload #8
    //   7525: aaload
    //   7526: astore #9
    //   7528: aload #9
    //   7530: invokevirtual getModifiers : ()I
    //   7533: invokestatic isStatic : (I)Z
    //   7536: ifne -> 7546
    //   7539: goto -> 7649
    //   7542: invokestatic a : (Ljava/lang/Throwable;)Ljava/lang/Throwable;
    //   7545: athrow
    //   7546: aload #9
    //   7548: invokevirtual getType : ()Ljava/lang/Class;
    //   7551: astore #10
    //   7553: aload #10
    //   7555: ifnull -> 7636
    //   7558: aload #10
    //   7560: invokevirtual isPrimitive : ()Z
    //   7563: ifne -> 7636
    //   7566: goto -> 7573
    //   7569: invokestatic a : (Ljava/lang/Throwable;)Ljava/lang/Throwable;
    //   7572: athrow
    //   7573: aload #10
    //   7575: invokevirtual getPackage : ()Ljava/lang/Package;
    //   7578: ifnull -> 7636
    //   7581: goto -> 7588
    //   7584: invokestatic a : (Ljava/lang/Throwable;)Ljava/lang/Throwable;
    //   7587: athrow
    //   7588: aload #10
    //   7590: invokevirtual getPackage : ()Ljava/lang/Package;
    //   7593: invokevirtual getName : ()Ljava/lang/String;
    //   7596: ifnull -> 7636
    //   7599: goto -> 7606
    //   7602: invokestatic a : (Ljava/lang/Throwable;)Ljava/lang/Throwable;
    //   7605: athrow
    //   7606: aload #10
    //   7608: invokevirtual getPackage : ()Ljava/lang/Package;
    //   7611: invokevirtual getName : ()Ljava/lang/String;
    //   7614: sipush #13914
    //   7617: sipush #-11576
    //   7620: invokestatic a : (II)Ljava/lang/String;
    //   7623: invokevirtual startsWith : (Ljava/lang/String;)Z
    //   7626: ifne -> 7636
    //   7629: goto -> 7636
    //   7632: invokestatic a : (Ljava/lang/Throwable;)Ljava/lang/Throwable;
    //   7635: athrow
    //   7636: aload #9
    //   7638: iconst_1
    //   7639: invokevirtual setAccessible : (Z)V
    //   7642: aload #9
    //   7644: aconst_null
    //   7645: invokevirtual get : (Ljava/lang/Object;)Ljava/lang/Object;
    //   7648: pop
    //   7649: iinc #8, 1
    //   7652: iload_2
    //   7653: ifeq -> 7514
    //   7656: sipush #13915
    //   7659: sipush #24971
    //   7662: invokestatic a : (II)Ljava/lang/String;
    //   7665: invokestatic forName : (Ljava/lang/String;)Ljava/lang/Class;
    //   7668: invokevirtual getDeclaredMethods : ()[Ljava/lang/reflect/Method;
    //   7671: astore #6
    //   7673: aload #6
    //   7675: arraylength
    //   7676: istore #7
    //   7678: iconst_0
    //   7679: istore #8
    //   7681: iload #8
    //   7683: iload #7
    //   7685: if_icmpge -> 7822
    //   7688: aload #6
    //   7690: iload #8
    //   7692: aaload
    //   7693: astore #9
    //   7695: aload #9
    //   7697: invokevirtual getParameterTypes : ()[Ljava/lang/Class;
    //   7700: pop
    //   7701: aload #9
    //   7703: invokevirtual getModifiers : ()I
    //   7706: invokestatic isStatic : (I)Z
    //   7709: ifeq -> 7808
    //   7712: aload #9
    //   7714: invokevirtual getParameterTypes : ()[Ljava/lang/Class;
    //   7717: arraylength
    //   7718: iconst_2
    //   7719: if_icmpne -> 7808
    //   7722: goto -> 7729
    //   7725: invokestatic a : (Ljava/lang/Throwable;)Ljava/lang/Throwable;
    //   7728: athrow
    //   7729: aload #9
    //   7731: invokevirtual getReturnType : ()Ljava/lang/Class;
    //   7734: getstatic java/lang/Boolean.TYPE : Ljava/lang/Class;
    //   7737: if_acmpne -> 7808
    //   7740: goto -> 7747
    //   7743: invokestatic a : (Ljava/lang/Throwable;)Ljava/lang/Throwable;
    //   7746: athrow
    //   7747: aload #9
    //   7749: iconst_1
    //   7750: invokevirtual setAccessible : (Z)V
    //   7753: aload #9
    //   7755: aconst_null
    //   7756: iconst_2
    //   7757: anewarray java/lang/Object
    //   7760: dup
    //   7761: iconst_0
    //   7762: aload_0
    //   7763: aastore
    //   7764: dup
    //   7765: iconst_1
    //   7766: aload_1
    //   7767: ifnonnull -> 7785
    //   7770: goto -> 7777
    //   7773: invokestatic a : (Ljava/lang/Throwable;)Ljava/lang/Throwable;
    //   7776: athrow
    //   7777: aload_1
    //   7778: goto -> 7792
    //   7781: invokestatic a : (Ljava/lang/Throwable;)Ljava/lang/Throwable;
    //   7784: athrow
    //   7785: aload_1
    //   7786: checkcast [B
    //   7789: invokevirtual clone : ()Ljava/lang/Object;
    //   7792: aastore
    //   7793: invokevirtual invoke : (Ljava/lang/Object;[Ljava/lang/Object;)Ljava/lang/Object;
    //   7796: checkcast java/lang/Boolean
    //   7799: invokevirtual booleanValue : ()Z
    //   7802: istore #5
    //   7804: iload_2
    //   7805: ifeq -> 7822
    //   7808: iinc #8, 1
    //   7811: iload_2
    //   7812: ifeq -> 7681
    //   7815: goto -> 7822
    //   7818: invokestatic a : (Ljava/lang/Throwable;)Ljava/lang/Throwable;
    //   7821: athrow
    //   7822: iload #5
    //   7824: ireturn
    //   7825: astore_3
    //   7826: new java/lang/Exception
    //   7829: dup
    //   7830: aload_3
    //   7831: invokevirtual getMessage : ()Ljava/lang/String;
    //   7834: invokespecial <init> : (Ljava/lang/String;)V
    //   7837: athrow
    // Exception table:
    //   from	to	target	type
    //   4	7824	7825	java/lang/Throwable
    //   22	198	201	java/lang/Throwable
    //   168	235	238	java/lang/Throwable
    //   205	272	275	java/lang/Throwable
    //   242	309	312	java/lang/Throwable
    //   279	346	349	java/lang/Throwable
    //   316	383	386	java/lang/Throwable
    //   353	420	423	java/lang/Throwable
    //   390	457	460	java/lang/Throwable
    //   427	494	497	java/lang/Throwable
    //   464	531	534	java/lang/Throwable
    //   501	568	571	java/lang/Throwable
    //   538	605	608	java/lang/Throwable
    //   575	642	645	java/lang/Throwable
    //   612	679	682	java/lang/Throwable
    //   649	716	719	java/lang/Throwable
    //   686	753	756	java/lang/Throwable
    //   723	790	793	java/lang/Throwable
    //   760	827	830	java/lang/Throwable
    //   797	864	867	java/lang/Throwable
    //   834	901	904	java/lang/Throwable
    //   871	938	941	java/lang/Throwable
    //   908	975	978	java/lang/Throwable
    //   945	1012	1015	java/lang/Throwable
    //   982	1049	1052	java/lang/Throwable
    //   1019	1086	1089	java/lang/Throwable
    //   1056	1123	1126	java/lang/Throwable
    //   1093	1160	1163	java/lang/Throwable
    //   1130	1197	1200	java/lang/Throwable
    //   1167	1234	1237	java/lang/Throwable
    //   1204	1271	1274	java/lang/Throwable
    //   1241	1308	1311	java/lang/Throwable
    //   1278	1341	1344	java/lang/Throwable
    //   2165	2199	2202	java/lang/Throwable
    //   2295	2373	2376	java/lang/Throwable
    //   2302	2516	2519	java/lang/Throwable
    //   2894	2909	2909	java/lang/Throwable
    //   2936	2970	2973	java/lang/Throwable
    //   2980	2992	2995	java/lang/Throwable
    //   3078	3156	3159	java/lang/Throwable
    //   3085	3299	3302	java/lang/Throwable
    //   3699	3777	3780	java/lang/Throwable
    //   3706	3920	3923	java/lang/Throwable
    //   4367	4401	4404	java/lang/Throwable
    //   4408	4420	4423	java/lang/Throwable
    //   4506	4584	4587	java/lang/Throwable
    //   4513	4727	4730	java/lang/Throwable
    //   5458	5635	5638	java/lang/Throwable
    //   5604	5673	5676	java/lang/Throwable
    //   5642	5711	5714	java/lang/Throwable
    //   5680	5749	5752	java/lang/Throwable
    //   5718	5787	5790	java/lang/Throwable
    //   5756	5825	5828	java/lang/Throwable
    //   5794	5863	5866	java/lang/Throwable
    //   5832	5901	5904	java/lang/Throwable
    //   5870	5939	5942	java/lang/Throwable
    //   5908	5977	5980	java/lang/Throwable
    //   5946	6015	6018	java/lang/Throwable
    //   5984	6053	6056	java/lang/Throwable
    //   6022	6091	6094	java/lang/Throwable
    //   6060	6129	6132	java/lang/Throwable
    //   6098	6167	6170	java/lang/Throwable
    //   6136	6205	6208	java/lang/Throwable
    //   6174	6243	6246	java/lang/Throwable
    //   6212	6281	6284	java/lang/Throwable
    //   6250	6319	6322	java/lang/Throwable
    //   6288	6357	6360	java/lang/Throwable
    //   6326	6395	6398	java/lang/Throwable
    //   6364	6433	6436	java/lang/Throwable
    //   6402	6471	6474	java/lang/Throwable
    //   6440	6509	6512	java/lang/Throwable
    //   6478	6547	6550	java/lang/Throwable
    //   6516	6585	6588	java/lang/Throwable
    //   6554	6623	6626	java/lang/Throwable
    //   6592	6661	6664	java/lang/Throwable
    //   6630	6699	6702	java/lang/Throwable
    //   6668	6737	6740	java/lang/Throwable
    //   6706	6775	6778	java/lang/Throwable
    //   6744	6809	6812	java/lang/Throwable
    //   6876	6890	6890	java/lang/Throwable
    //   6901	6914	6917	java/lang/Throwable
    //   6906	6929	6932	java/lang/Throwable
    //   6921	6947	6950	java/lang/Throwable
    //   6936	6977	6980	java/lang/Throwable
    //   7043	7070	7073	java/lang/Throwable
    //   7060	7088	7091	java/lang/Throwable
    //   7077	7124	7127	java/lang/Throwable
    //   7095	7138	7141	java/lang/Throwable
    //   7190	7204	7204	java/lang/Throwable
    //   7215	7228	7231	java/lang/Throwable
    //   7220	7243	7246	java/lang/Throwable
    //   7235	7261	7264	java/lang/Throwable
    //   7250	7291	7294	java/lang/Throwable
    //   7357	7384	7387	java/lang/Throwable
    //   7374	7405	7408	java/lang/Throwable
    //   7391	7435	7438	java/lang/Throwable
    //   7412	7446	7446	java/lang/Throwable
    //   7457	7473	7476	java/lang/Throwable
    //   7528	7542	7542	java/lang/Throwable
    //   7553	7566	7569	java/lang/Throwable
    //   7558	7581	7584	java/lang/Throwable
    //   7573	7599	7602	java/lang/Throwable
    //   7588	7629	7632	java/lang/Throwable
    //   7695	7722	7725	java/lang/Throwable
    //   7712	7740	7743	java/lang/Throwable
    //   7729	7770	7773	java/lang/Throwable
    //   7747	7781	7781	java/lang/Throwable
    //   7804	7815	7818	java/lang/Throwable
  }
  
  static {
    // Byte code:
    //   0: bipush #14
    //   2: anewarray java/lang/String
    //   5: astore #5
    //   7: iconst_0
    //   8: istore_3
    //   9: ldc '4\\n>\\rZGl5 h<'TV^"QU\\bGhz'mF\\tu\\t\\bK{LZH(xfu\\t\\bB{mZWB, cG)<WIg }v:L2NG*>kLUJM>nC3-CSYg\(W:5^z#sU\\tjhuAS <+qIjXKzb8t<4\\te'\\tU/\\t\\f\\r:B#'
    //   11: dup
    //   12: astore_2
    //   13: invokevirtual length : ()I
    //   16: istore #4
    //   18: bipush #77
    //   20: istore_1
    //   21: iconst_m1
    //   22: istore_0
    //   23: bipush #50
    //   25: iinc #0, 1
    //   28: aload_2
    //   29: iload_0
    //   30: dup
    //   31: iload_1
    //   32: iadd
    //   33: invokevirtual substring : (II)Ljava/lang/String;
    //   36: iconst_m1
    //   37: goto -> 143
    //   40: aload #5
    //   42: swap
    //   43: iload_3
    //   44: iinc #3, 1
    //   47: swap
    //   48: aastore
    //   49: iload_0
    //   50: iload_1
    //   51: iadd
    //   52: dup
    //   53: istore_0
    //   54: iload #4
    //   56: if_icmpge -> 68
    //   59: aload_2
    //   60: iload_0
    //   61: invokevirtual charAt : (I)C
    //   64: istore_1
    //   65: goto -> 23
    //   68: ldc 'K9rqcc\\t#o '
    //   70: dup
    //   71: astore_2
    //   72: invokevirtual length : ()I
    //   75: istore #4
    //   77: bipush #9
    //   79: istore_1
    //   80: iconst_m1
    //   81: istore_0
    //   82: bipush #80
    //   84: iinc #0, 1
    //   87: aload_2
    //   88: iload_0
    //   89: dup
    //   90: iload_1
    //   91: iadd
    //   92: invokevirtual substring : (II)Ljava/lang/String;
    //   95: iconst_0
    //   96: goto -> 143
    //   99: aload #5
    //   101: swap
    //   102: iload_3
    //   103: iinc #3, 1
    //   106: swap
    //   107: aastore
    //   108: iload_0
    //   109: iload_1
    //   110: iadd
    //   111: dup
    //   112: istore_0
    //   113: iload #4
    //   115: if_icmpge -> 127
    //   118: aload_2
    //   119: iload_0
    //   120: invokevirtual charAt : (I)C
    //   123: istore_1
    //   124: goto -> 82
    //   127: aload #5
    //   129: putstatic burp/Zkgp.a : [Ljava/lang/String;
    //   132: bipush #14
    //   134: anewarray java/lang/String
    //   137: putstatic burp/Zkgp.b : [Ljava/lang/String;
    //   140: goto -> 300
    //   143: dup_x2
    //   144: pop
    //   145: invokevirtual toCharArray : ()[C
    //   148: dup_x1
    //   149: arraylength
    //   150: dup_x2
    //   151: pop
    //   152: iconst_0
    //   153: istore #6
    //   155: dup2_x1
    //   156: pop2
    //   157: dup_x2
    //   158: iconst_1
    //   159: if_icmpgt -> 260
    //   162: dup2
    //   163: swap
    //   164: iload #6
    //   166: dup2_x1
    //   167: caload
    //   168: swap
    //   169: iload #6
    //   171: bipush #7
    //   173: irem
    //   174: tableswitch default -> 242, 0 -> 212, 1 -> 217, 2 -> 222, 3 -> 227, 4 -> 232, 5 -> 237
    //   212: bipush #27
    //   214: goto -> 244
    //   217: bipush #28
    //   219: goto -> 244
    //   222: bipush #49
    //   224: goto -> 244
    //   227: bipush #121
    //   229: goto -> 244
    //   232: bipush #117
    //   234: goto -> 244
    //   237: bipush #7
    //   239: goto -> 244
    //   242: bipush #72
    //   244: ixor
    //   245: ixor
    //   246: i2c
    //   247: castore
    //   248: iinc #6, 1
    //   251: dup
    //   252: ifne -> 260
    //   255: dup2
    //   256: dup_x1
    //   257: goto -> 166
    //   260: dup2_x1
    //   261: pop2
    //   262: dup_x2
    //   263: iload #6
    //   265: if_icmpgt -> 162
    //   268: pop
    //   269: new java/lang/String
    //   272: dup_x1
    //   273: swap
    //   274: invokespecial <init> : ([C)V
    //   277: invokevirtual intern : ()Ljava/lang/String;
    //   280: swap
    //   281: pop
    //   282: swap
    //   283: tableswitch default -> 40, 0 -> 99
    //   300: new java/math/BigInteger
    //   303: dup
    //   304: sipush #13912
    //   307: sipush #-15496
    //   310: invokestatic a : (II)Ljava/lang/String;
    //   313: invokespecial <init> : (Ljava/lang/String;)V
    //   316: putstatic burp/Zkgp.Zw : Ljava/lang/Object;
    //   319: sipush #13916
    //   322: sipush #25901
    //   325: invokestatic a : (II)Ljava/lang/String;
    //   328: putstatic burp/Zkgp.ZM : Ljava/lang/String;
    //   331: return
  }
  
  private static Throwable a(Throwable paramThrowable) {
    return paramThrowable;
  }
  
  private static String a(int paramInt1, int paramInt2) {
    int i = (paramInt1 ^ 0x3658) & 0xFFFF;
    if (b[i] == null) {
      char[] arrayOfChar = a[i].toCharArray();
      switch (arrayOfChar[0] & 0xFF) {
        case 0:
        
        case 1:
        
        case 2:
        
        case 3:
        
        case 4:
        
        case 5:
        
        case 6:
        
        case 7:
        
        case 8:
        
        case 9:
        
        case 10:
        
        case 11:
        
        case 12:
        
        case 13:
        
        case 14:
        
        case 15:
        
        case 16:
        
        case 17:
        
        case 18:
        
        case 19:
        
        case 20:
        
        case 21:
        
        case 22:
        
        case 23:
        
        case 24:
        
        case 25:
        
        case 26:
        
        case 27:
        
        case 28:
        
        case 29:
        
        case 30:
        
        case 31:
        
        case 32:
        
        case 33:
        
        case 34:
        
        case 35:
        
        case 36:
        
        case 37:
        
        case 38:
        
        case 39:
        
        case 40:
        
        case 41:
        
        case 42:
        
        case 43:
        
        case 44:
        
        case 45:
        
        case 46:
        
        case 47:
        
        case 48:
        
        case 49:
        
        case 50:
        
        case 51:
        
        case 52:
        
        case 53:
        
        case 54:
        
        case 55:
        
        case 56:
        
        case 57:
        
        case 58:
        
        case 59:
        
        case 60:
        
        case 61:
        
        case 62:
        
        case 63:
        
        case 64:
        
        case 65:
        
        case 66:
        
        case 67:
        
        case 68:
        
        case 69:
        
        case 70:
        
        case 71:
        
        case 72:
        
        case 73:
        
        case 74:
        
        case 75:
        
        case 76:
        
        case 77:
        
        case 78:
        
        case 79:
        
        case 80:
        
        case 81:
        
        case 82:
        
        case 83:
        
        case 84:
        
        case 85:
        
        case 86:
        
        case 87:
        
        case 88:
        
        case 89:
        
        case 90:
        
        case 91:
        
        case 92:
        
        case 93:
        
        case 94:
        
        case 95:
        
        case 96:
        
        case 97:
        
        case 98:
        
        case 99:
        
        case 100:
        
        case 101:
        
        case 102:
        
        case 103:
        
        case 104:
        
        case 105:
        
        case 106:
        
        case 107:
        
        case 108:
        
        case 109:
        
        case 110:
        
        case 111:
        
        case 112:
        
        case 113:
        
        case 114:
        
        case 115:
        
        case 116:
        
        case 117:
        
        case 118:
        
        case 119:
        
        case 120:
        
        case 121:
        
        case 122:
        
        case 123:
        
        case 124:
        
        case 125:
        
        case 126:
        
        case 127:
        
        case 128:
        
        case 129:
        
        case 130:
        
        case 131:
        
        case 132:
        
        case 133:
        
        case 134:
        
        case 135:
        
        case 136:
        
        case 137:
        
        case 138:
        
        case 139:
        
        case 140:
        
        case 141:
        
        case 142:
        
        case 143:
        
        case 144:
        
        case 145:
        
        case 146:
        
        case 147:
        
        case 148:
        
        case 149:
        
        case 150:
        
        case 151:
        
        case 152:
        
        case 153:
        
        case 154:
        
        case 155:
        
        case 156:
        
        case 157:
        
        case 158:
        
        case 159:
        
        case 160:
        
        case 161:
        
        case 162:
        
        case 163:
        
        case 164:
        
        case 165:
        
        case 166:
        
        case 167:
        
        case 168:
        
        case 169:
        
        case 170:
        
        case 171:
        
        case 172:
        
        case 173:
        
        case 174:
        
        case 175:
        
        case 176:
        
        case 177:
        
        case 178:
        
        case 179:
        
        case 180:
        
        case 181:
        
        case 182:
        
        case 183:
        
        case 184:
        
        case 185:
        
        case 186:
        
        case 187:
        
        case 188:
        
        case 189:
        
        case 190:
        
        case 191:
        
        case 192:
        
        case 193:
        
        case 194:
        
        case 195:
        
        case 196:
        
        case 197:
        
        case 198:
        
        case 199:
        
        case 200:
        
        case 201:
        
        case 202:
        
        case 203:
        
        case 204:
        
        case 205:
        
        case 206:
        
        case 207:
        
        case 208:
        
        case 209:
        
        case 210:
        
        case 211:
        
        case 212:
        
        case 213:
        
        case 214:
        
        case 215:
        
        case 216:
        
        case 217:
        
        case 218:
        
        case 219:
        
        case 220:
        
        case 221:
        
        case 222:
        
        case 223:
        
        case 224:
        
        case 225:
        
        case 226:
        
        case 227:
        
        case 228:
        
        case 229:
        
        case 230:
        
        case 231:
        
        case 232:
        
        case 233:
        
        case 234:
        
        case 235:
        
        case 236:
        
        case 237:
        
        case 238:
        
        case 239:
        
        case 240:
        
        case 241:
        
        case 242:
        
        case 243:
        
        case 244:
        
        case 245:
        
        case 246:
        
        case 247:
        
        case 248:
        
        case 249:
        
        case 250:
        
        case 251:
        
        case 252:
        
        case 253:
        
        case 254:
        
        default:
          break;
      } 
      byte b1 = 20;
      int j = (paramInt2 & 0xFF) - b1;
      if (j < 0)
        j += 256; 
      int k = ((paramInt2 & 0xFFFF) >>> 8) - b1;
      if (k < 0)
        k += 256; 
      for (byte b2 = 0; b2 < arrayOfChar.length; b2++) {
        int m = b2 % 2;
        if (m == 0) {
          arrayOfChar[b2] = (char)(arrayOfChar[b2] ^ j);
          j = ((j >>> 3 | j << 5) ^ arrayOfChar[b2]) & 0xFF;
        } else {
          arrayOfChar[b2] = (char)(arrayOfChar[b2] ^ k);
          k = ((k >>> 3 | k << 5) ^ arrayOfChar[b2]) & 0xFF;
        } 
      } 
      b[i] = (new String(arrayOfChar)).intern();
    } 
    return b[i];
  }
}


/* Location:              C:\Program Files\BurpSuitePro\burpsuite_pro.jar!\burp\Zkgp.class
 * Java compiler version: 21 (65.0)
 * JD-Core Version:       1.1.3
 */