package burp;

import java.math.BigInteger;

class Zkku extends ClassLoader {
  static String Zq;
  
  static Object Zz;
  
  private static final String[] a;
  
  private static final String[] b;
  
  static void ZC(Object[] paramArrayOfObject, Object paramObject) throws Throwable {}
  
  static void Zv(Object paramObject) {
    Zejg.ZP = a(-1554, -13770);
    Zejg.ZR = new BigInteger(a(-1568, 22756));
    boolean bool = Zt2e.ZK();
    try {
      try {
        if (Zejg.ZP.charAt(Math.abs(((BigInteger)Zzv.Zu).intValue() % 32)) <= Zmt6.Zx.charAt(Math.abs(((BigInteger)Zejg.ZR).intValue() % 32))) {
          try {
            Zgny.Zz(Class.forName(a(-1556, -2736)));
            if (bool)
              Zenq.ZR(Class.forName(a(-1563, -28968))); 
          } catch (Throwable throwable) {
            throw a(null);
          } 
          return;
        } 
      } catch (Throwable throwable) {
        throw a(null);
      } 
      Zenq.ZR(Class.forName(a(-1563, -28968)));
    } catch (Throwable throwable) {}
  }
  
  static boolean Zy(Object[] paramArrayOfObject, Object paramObject) throws Throwable {
    // Byte code:
    //   0: invokestatic ZN : ()Z
    //   3: istore_2
    //   4: new java/lang/StringBuilder
    //   7: dup
    //   8: invokespecial <init> : ()V
    //   11: astore_3
    //   12: iconst_0
    //   13: istore #4
    //   15: iload #4
    //   17: bipush #32
    //   19: if_icmpge -> 1355
    //   22: iload #4
    //   24: tableswitch default -> 1348, 0 -> 168, 1 -> 205, 2 -> 242, 3 -> 279, 4 -> 316, 5 -> 353, 6 -> 390, 7 -> 427, 8 -> 464, 9 -> 501, 10 -> 538, 11 -> 575, 12 -> 612, 13 -> 649, 14 -> 686, 15 -> 723, 16 -> 760, 17 -> 797, 18 -> 834, 19 -> 871, 20 -> 908, 21 -> 945, 22 -> 982, 23 -> 1019, 24 -> 1056, 25 -> 1093, 26 -> 1130, 27 -> 1167, 28 -> 1204, 29 -> 1241, 30 -> 1278, 31 -> 1315
    //   168: aload_3
    //   169: getstatic burp/Zsin.ZC : Ljava/lang/String;
    //   172: getstatic burp/Zkku.Zz : Ljava/lang/Object;
    //   175: checkcast java/math/BigInteger
    //   178: invokevirtual intValue : ()I
    //   181: bipush #32
    //   183: irem
    //   184: invokestatic abs : (I)I
    //   187: invokevirtual charAt : (I)C
    //   190: invokevirtual append : (C)Ljava/lang/StringBuilder;
    //   193: pop
    //   194: iload_2
    //   195: ifne -> 1348
    //   198: goto -> 205
    //   201: invokestatic a : (Ljava/lang/Throwable;)Ljava/lang/Throwable;
    //   204: athrow
    //   205: aload_3
    //   206: getstatic burp/Zmhx.ZD : Ljava/lang/String;
    //   209: getstatic burp/Zkv2.ZC : Ljava/lang/Object;
    //   212: checkcast java/math/BigInteger
    //   215: invokevirtual intValue : ()I
    //   218: bipush #32
    //   220: irem
    //   221: invokestatic abs : (I)I
    //   224: invokevirtual charAt : (I)C
    //   227: invokevirtual append : (C)Ljava/lang/StringBuilder;
    //   230: pop
    //   231: iload_2
    //   232: ifne -> 1348
    //   235: goto -> 242
    //   238: invokestatic a : (Ljava/lang/Throwable;)Ljava/lang/Throwable;
    //   241: athrow
    //   242: aload_3
    //   243: getstatic burp/Zezz.Zi : Ljava/lang/String;
    //   246: getstatic burp/Zs0b.ZI : Ljava/lang/Object;
    //   249: checkcast java/math/BigInteger
    //   252: invokevirtual intValue : ()I
    //   255: bipush #32
    //   257: irem
    //   258: invokestatic abs : (I)I
    //   261: invokevirtual charAt : (I)C
    //   264: invokevirtual append : (C)Ljava/lang/StringBuilder;
    //   267: pop
    //   268: iload_2
    //   269: ifne -> 1348
    //   272: goto -> 279
    //   275: invokestatic a : (Ljava/lang/Throwable;)Ljava/lang/Throwable;
    //   278: athrow
    //   279: aload_3
    //   280: getstatic burp/Zz0j.Zf : Ljava/lang/String;
    //   283: getstatic burp/Zghe.ZJ : Ljava/lang/Object;
    //   286: checkcast java/math/BigInteger
    //   289: invokevirtual intValue : ()I
    //   292: bipush #32
    //   294: irem
    //   295: invokestatic abs : (I)I
    //   298: invokevirtual charAt : (I)C
    //   301: invokevirtual append : (C)Ljava/lang/StringBuilder;
    //   304: pop
    //   305: iload_2
    //   306: ifne -> 1348
    //   309: goto -> 316
    //   312: invokestatic a : (Ljava/lang/Throwable;)Ljava/lang/Throwable;
    //   315: athrow
    //   316: aload_3
    //   317: getstatic burp/Zm06.Zg : Ljava/lang/String;
    //   320: getstatic burp/Zs33.ZT : Ljava/lang/Object;
    //   323: checkcast java/math/BigInteger
    //   326: invokevirtual intValue : ()I
    //   329: bipush #32
    //   331: irem
    //   332: invokestatic abs : (I)I
    //   335: invokevirtual charAt : (I)C
    //   338: invokevirtual append : (C)Ljava/lang/StringBuilder;
    //   341: pop
    //   342: iload_2
    //   343: ifne -> 1348
    //   346: goto -> 353
    //   349: invokestatic a : (Ljava/lang/Throwable;)Ljava/lang/Throwable;
    //   352: athrow
    //   353: aload_3
    //   354: getstatic burp/Zko9.Zf : Ljava/lang/String;
    //   357: getstatic burp/Zl1u.Zq : Ljava/lang/Object;
    //   360: checkcast java/math/BigInteger
    //   363: invokevirtual intValue : ()I
    //   366: bipush #32
    //   368: irem
    //   369: invokestatic abs : (I)I
    //   372: invokevirtual charAt : (I)C
    //   375: invokevirtual append : (C)Ljava/lang/StringBuilder;
    //   378: pop
    //   379: iload_2
    //   380: ifne -> 1348
    //   383: goto -> 390
    //   386: invokestatic a : (Ljava/lang/Throwable;)Ljava/lang/Throwable;
    //   389: athrow
    //   390: aload_3
    //   391: getstatic burp/Ztte.ZD : Ljava/lang/String;
    //   394: getstatic burp/Zgdt.Zb : Ljava/lang/Object;
    //   397: checkcast java/math/BigInteger
    //   400: invokevirtual intValue : ()I
    //   403: bipush #32
    //   405: irem
    //   406: invokestatic abs : (I)I
    //   409: invokevirtual charAt : (I)C
    //   412: invokevirtual append : (C)Ljava/lang/StringBuilder;
    //   415: pop
    //   416: iload_2
    //   417: ifne -> 1348
    //   420: goto -> 427
    //   423: invokestatic a : (Ljava/lang/Throwable;)Ljava/lang/Throwable;
    //   426: athrow
    //   427: aload_3
    //   428: getstatic burp/Zzy5.ZD : Ljava/lang/String;
    //   431: getstatic burp/Zz9p.Zw : Ljava/lang/Object;
    //   434: checkcast java/math/BigInteger
    //   437: invokevirtual intValue : ()I
    //   440: bipush #32
    //   442: irem
    //   443: invokestatic abs : (I)I
    //   446: invokevirtual charAt : (I)C
    //   449: invokevirtual append : (C)Ljava/lang/StringBuilder;
    //   452: pop
    //   453: iload_2
    //   454: ifne -> 1348
    //   457: goto -> 464
    //   460: invokestatic a : (Ljava/lang/Throwable;)Ljava/lang/Throwable;
    //   463: athrow
    //   464: aload_3
    //   465: getstatic burp/Zb9k.Za : Ljava/lang/String;
    //   468: getstatic burp/Zzvr.Z_ : Ljava/lang/Object;
    //   471: checkcast java/math/BigInteger
    //   474: invokevirtual intValue : ()I
    //   477: bipush #32
    //   479: irem
    //   480: invokestatic abs : (I)I
    //   483: invokevirtual charAt : (I)C
    //   486: invokevirtual append : (C)Ljava/lang/StringBuilder;
    //   489: pop
    //   490: iload_2
    //   491: ifne -> 1348
    //   494: goto -> 501
    //   497: invokestatic a : (Ljava/lang/Throwable;)Ljava/lang/Throwable;
    //   500: athrow
    //   501: aload_3
    //   502: getstatic burp/Zxsb.Zh : Ljava/lang/String;
    //   505: getstatic burp/Zebj.Zf : Ljava/lang/Object;
    //   508: checkcast java/math/BigInteger
    //   511: invokevirtual intValue : ()I
    //   514: bipush #32
    //   516: irem
    //   517: invokestatic abs : (I)I
    //   520: invokevirtual charAt : (I)C
    //   523: invokevirtual append : (C)Ljava/lang/StringBuilder;
    //   526: pop
    //   527: iload_2
    //   528: ifne -> 1348
    //   531: goto -> 538
    //   534: invokestatic a : (Ljava/lang/Throwable;)Ljava/lang/Throwable;
    //   537: athrow
    //   538: aload_3
    //   539: getstatic burp/Ztid.Zz : Ljava/lang/String;
    //   542: getstatic burp/Zb3p.Zx : Ljava/lang/Object;
    //   545: checkcast java/math/BigInteger
    //   548: invokevirtual intValue : ()I
    //   551: bipush #32
    //   553: irem
    //   554: invokestatic abs : (I)I
    //   557: invokevirtual charAt : (I)C
    //   560: invokevirtual append : (C)Ljava/lang/StringBuilder;
    //   563: pop
    //   564: iload_2
    //   565: ifne -> 1348
    //   568: goto -> 575
    //   571: invokestatic a : (Ljava/lang/Throwable;)Ljava/lang/Throwable;
    //   574: athrow
    //   575: aload_3
    //   576: getstatic burp/Ztpa.ZZ : Ljava/lang/String;
    //   579: getstatic burp/Zxd0.Za : Ljava/lang/Object;
    //   582: checkcast java/math/BigInteger
    //   585: invokevirtual intValue : ()I
    //   588: bipush #32
    //   590: irem
    //   591: invokestatic abs : (I)I
    //   594: invokevirtual charAt : (I)C
    //   597: invokevirtual append : (C)Ljava/lang/StringBuilder;
    //   600: pop
    //   601: iload_2
    //   602: ifne -> 1348
    //   605: goto -> 612
    //   608: invokestatic a : (Ljava/lang/Throwable;)Ljava/lang/Throwable;
    //   611: athrow
    //   612: aload_3
    //   613: getstatic burp/Zkv2.Z_ : Ljava/lang/String;
    //   616: getstatic burp/Zs9u.Zd : Ljava/lang/Object;
    //   619: checkcast java/math/BigInteger
    //   622: invokevirtual intValue : ()I
    //   625: bipush #32
    //   627: irem
    //   628: invokestatic abs : (I)I
    //   631: invokevirtual charAt : (I)C
    //   634: invokevirtual append : (C)Ljava/lang/StringBuilder;
    //   637: pop
    //   638: iload_2
    //   639: ifne -> 1348
    //   642: goto -> 649
    //   645: invokestatic a : (Ljava/lang/Throwable;)Ljava/lang/Throwable;
    //   648: athrow
    //   649: aload_3
    //   650: getstatic burp/Zr3x.ZM : Ljava/lang/String;
    //   653: getstatic burp/Zzwl.Z_ : Ljava/lang/Object;
    //   656: checkcast java/math/BigInteger
    //   659: invokevirtual intValue : ()I
    //   662: bipush #32
    //   664: irem
    //   665: invokestatic abs : (I)I
    //   668: invokevirtual charAt : (I)C
    //   671: invokevirtual append : (C)Ljava/lang/StringBuilder;
    //   674: pop
    //   675: iload_2
    //   676: ifne -> 1348
    //   679: goto -> 686
    //   682: invokestatic a : (Ljava/lang/Throwable;)Ljava/lang/Throwable;
    //   685: athrow
    //   686: aload_3
    //   687: getstatic burp/Zxsb.Zh : Ljava/lang/String;
    //   690: getstatic burp/Zrvb.ZD : Ljava/lang/Object;
    //   693: checkcast java/math/BigInteger
    //   696: invokevirtual intValue : ()I
    //   699: bipush #32
    //   701: irem
    //   702: invokestatic abs : (I)I
    //   705: invokevirtual charAt : (I)C
    //   708: invokevirtual append : (C)Ljava/lang/StringBuilder;
    //   711: pop
    //   712: iload_2
    //   713: ifne -> 1348
    //   716: goto -> 723
    //   719: invokestatic a : (Ljava/lang/Throwable;)Ljava/lang/Throwable;
    //   722: athrow
    //   723: aload_3
    //   724: getstatic burp/Zsgj.ZN : Ljava/lang/String;
    //   727: getstatic burp/Zgwq.Ze : Ljava/lang/Object;
    //   730: checkcast java/math/BigInteger
    //   733: invokevirtual intValue : ()I
    //   736: bipush #32
    //   738: irem
    //   739: invokestatic abs : (I)I
    //   742: invokevirtual charAt : (I)C
    //   745: invokevirtual append : (C)Ljava/lang/StringBuilder;
    //   748: pop
    //   749: iload_2
    //   750: ifne -> 1348
    //   753: goto -> 760
    //   756: invokestatic a : (Ljava/lang/Throwable;)Ljava/lang/Throwable;
    //   759: athrow
    //   760: aload_3
    //   761: getstatic burp/Zgny.Zf : Ljava/lang/String;
    //   764: getstatic burp/Zzy5.ZG : Ljava/lang/Object;
    //   767: checkcast java/math/BigInteger
    //   770: invokevirtual intValue : ()I
    //   773: bipush #32
    //   775: irem
    //   776: invokestatic abs : (I)I
    //   779: invokevirtual charAt : (I)C
    //   782: invokevirtual append : (C)Ljava/lang/StringBuilder;
    //   785: pop
    //   786: iload_2
    //   787: ifne -> 1348
    //   790: goto -> 797
    //   793: invokestatic a : (Ljava/lang/Throwable;)Ljava/lang/Throwable;
    //   796: athrow
    //   797: aload_3
    //   798: getstatic burp/Zebj.ZF : Ljava/lang/String;
    //   801: getstatic burp/Zxd0.Za : Ljava/lang/Object;
    //   804: checkcast java/math/BigInteger
    //   807: invokevirtual intValue : ()I
    //   810: bipush #32
    //   812: irem
    //   813: invokestatic abs : (I)I
    //   816: invokevirtual charAt : (I)C
    //   819: invokevirtual append : (C)Ljava/lang/StringBuilder;
    //   822: pop
    //   823: iload_2
    //   824: ifne -> 1348
    //   827: goto -> 834
    //   830: invokestatic a : (Ljava/lang/Throwable;)Ljava/lang/Throwable;
    //   833: athrow
    //   834: aload_3
    //   835: getstatic burp/Zxd0.Zc : Ljava/lang/String;
    //   838: getstatic burp/Zs_.Zs : Ljava/lang/Object;
    //   841: checkcast java/math/BigInteger
    //   844: invokevirtual intValue : ()I
    //   847: bipush #32
    //   849: irem
    //   850: invokestatic abs : (I)I
    //   853: invokevirtual charAt : (I)C
    //   856: invokevirtual append : (C)Ljava/lang/StringBuilder;
    //   859: pop
    //   860: iload_2
    //   861: ifne -> 1348
    //   864: goto -> 871
    //   867: invokestatic a : (Ljava/lang/Throwable;)Ljava/lang/Throwable;
    //   870: athrow
    //   871: aload_3
    //   872: getstatic burp/Zgwq.ZV : Ljava/lang/String;
    //   875: getstatic burp/Zmjr.ZU : Ljava/lang/Object;
    //   878: checkcast java/math/BigInteger
    //   881: invokevirtual intValue : ()I
    //   884: bipush #32
    //   886: irem
    //   887: invokestatic abs : (I)I
    //   890: invokevirtual charAt : (I)C
    //   893: invokevirtual append : (C)Ljava/lang/StringBuilder;
    //   896: pop
    //   897: iload_2
    //   898: ifne -> 1348
    //   901: goto -> 908
    //   904: invokestatic a : (Ljava/lang/Throwable;)Ljava/lang/Throwable;
    //   907: athrow
    //   908: aload_3
    //   909: getstatic burp/Zttj.ZN : Ljava/lang/String;
    //   912: getstatic burp/Zg97.Zc : Ljava/lang/Object;
    //   915: checkcast java/math/BigInteger
    //   918: invokevirtual intValue : ()I
    //   921: bipush #32
    //   923: irem
    //   924: invokestatic abs : (I)I
    //   927: invokevirtual charAt : (I)C
    //   930: invokevirtual append : (C)Ljava/lang/StringBuilder;
    //   933: pop
    //   934: iload_2
    //   935: ifne -> 1348
    //   938: goto -> 945
    //   941: invokestatic a : (Ljava/lang/Throwable;)Ljava/lang/Throwable;
    //   944: athrow
    //   945: aload_3
    //   946: getstatic burp/Zzv.Zy : Ljava/lang/String;
    //   949: getstatic burp/Zxsb.ZN : Ljava/lang/Object;
    //   952: checkcast java/math/BigInteger
    //   955: invokevirtual intValue : ()I
    //   958: bipush #32
    //   960: irem
    //   961: invokestatic abs : (I)I
    //   964: invokevirtual charAt : (I)C
    //   967: invokevirtual append : (C)Ljava/lang/StringBuilder;
    //   970: pop
    //   971: iload_2
    //   972: ifne -> 1348
    //   975: goto -> 982
    //   978: invokestatic a : (Ljava/lang/Throwable;)Ljava/lang/Throwable;
    //   981: athrow
    //   982: aload_3
    //   983: getstatic burp/Zxrd.ZF : Ljava/lang/String;
    //   986: getstatic burp/Zxyq.ZQ : Ljava/lang/Object;
    //   989: checkcast java/math/BigInteger
    //   992: invokevirtual intValue : ()I
    //   995: bipush #32
    //   997: irem
    //   998: invokestatic abs : (I)I
    //   1001: invokevirtual charAt : (I)C
    //   1004: invokevirtual append : (C)Ljava/lang/StringBuilder;
    //   1007: pop
    //   1008: iload_2
    //   1009: ifne -> 1348
    //   1012: goto -> 1019
    //   1015: invokestatic a : (Ljava/lang/Throwable;)Ljava/lang/Throwable;
    //   1018: athrow
    //   1019: aload_3
    //   1020: getstatic burp/Zxrd.ZF : Ljava/lang/String;
    //   1023: getstatic burp/Zs36.Zs : Ljava/lang/Object;
    //   1026: checkcast java/math/BigInteger
    //   1029: invokevirtual intValue : ()I
    //   1032: bipush #32
    //   1034: irem
    //   1035: invokestatic abs : (I)I
    //   1038: invokevirtual charAt : (I)C
    //   1041: invokevirtual append : (C)Ljava/lang/StringBuilder;
    //   1044: pop
    //   1045: iload_2
    //   1046: ifne -> 1348
    //   1049: goto -> 1056
    //   1052: invokestatic a : (Ljava/lang/Throwable;)Ljava/lang/Throwable;
    //   1055: athrow
    //   1056: aload_3
    //   1057: getstatic burp/Ztes.Zo : Ljava/lang/String;
    //   1060: getstatic burp/Zb9k.Zi : Ljava/lang/Object;
    //   1063: checkcast java/math/BigInteger
    //   1066: invokevirtual intValue : ()I
    //   1069: bipush #32
    //   1071: irem
    //   1072: invokestatic abs : (I)I
    //   1075: invokevirtual charAt : (I)C
    //   1078: invokevirtual append : (C)Ljava/lang/StringBuilder;
    //   1081: pop
    //   1082: iload_2
    //   1083: ifne -> 1348
    //   1086: goto -> 1093
    //   1089: invokestatic a : (Ljava/lang/Throwable;)Ljava/lang/Throwable;
    //   1092: athrow
    //   1093: aload_3
    //   1094: getstatic burp/Zb_u.ZK : Ljava/lang/String;
    //   1097: getstatic burp/Zl1u.Zq : Ljava/lang/Object;
    //   1100: checkcast java/math/BigInteger
    //   1103: invokevirtual intValue : ()I
    //   1106: bipush #32
    //   1108: irem
    //   1109: invokestatic abs : (I)I
    //   1112: invokevirtual charAt : (I)C
    //   1115: invokevirtual append : (C)Ljava/lang/StringBuilder;
    //   1118: pop
    //   1119: iload_2
    //   1120: ifne -> 1348
    //   1123: goto -> 1130
    //   1126: invokestatic a : (Ljava/lang/Throwable;)Ljava/lang/Throwable;
    //   1129: athrow
    //   1130: aload_3
    //   1131: getstatic burp/Zg97.ZX : Ljava/lang/String;
    //   1134: getstatic burp/Zzwl.Z_ : Ljava/lang/Object;
    //   1137: checkcast java/math/BigInteger
    //   1140: invokevirtual intValue : ()I
    //   1143: bipush #32
    //   1145: irem
    //   1146: invokestatic abs : (I)I
    //   1149: invokevirtual charAt : (I)C
    //   1152: invokevirtual append : (C)Ljava/lang/StringBuilder;
    //   1155: pop
    //   1156: iload_2
    //   1157: ifne -> 1348
    //   1160: goto -> 1167
    //   1163: invokestatic a : (Ljava/lang/Throwable;)Ljava/lang/Throwable;
    //   1166: athrow
    //   1167: aload_3
    //   1168: getstatic burp/Zzv.Zy : Ljava/lang/String;
    //   1171: getstatic burp/Zmjr.ZU : Ljava/lang/Object;
    //   1174: checkcast java/math/BigInteger
    //   1177: invokevirtual intValue : ()I
    //   1180: bipush #32
    //   1182: irem
    //   1183: invokestatic abs : (I)I
    //   1186: invokevirtual charAt : (I)C
    //   1189: invokevirtual append : (C)Ljava/lang/StringBuilder;
    //   1192: pop
    //   1193: iload_2
    //   1194: ifne -> 1348
    //   1197: goto -> 1204
    //   1200: invokestatic a : (Ljava/lang/Throwable;)Ljava/lang/Throwable;
    //   1203: athrow
    //   1204: aload_3
    //   1205: getstatic burp/Zkv2.Z_ : Ljava/lang/String;
    //   1208: getstatic burp/Zzvr.Z_ : Ljava/lang/Object;
    //   1211: checkcast java/math/BigInteger
    //   1214: invokevirtual intValue : ()I
    //   1217: bipush #32
    //   1219: irem
    //   1220: invokestatic abs : (I)I
    //   1223: invokevirtual charAt : (I)C
    //   1226: invokevirtual append : (C)Ljava/lang/StringBuilder;
    //   1229: pop
    //   1230: iload_2
    //   1231: ifne -> 1348
    //   1234: goto -> 1241
    //   1237: invokestatic a : (Ljava/lang/Throwable;)Ljava/lang/Throwable;
    //   1240: athrow
    //   1241: aload_3
    //   1242: getstatic burp/Zs36.Zr : Ljava/lang/String;
    //   1245: getstatic burp/Zzwl.Z_ : Ljava/lang/Object;
    //   1248: checkcast java/math/BigInteger
    //   1251: invokevirtual intValue : ()I
    //   1254: bipush #32
    //   1256: irem
    //   1257: invokestatic abs : (I)I
    //   1260: invokevirtual charAt : (I)C
    //   1263: invokevirtual append : (C)Ljava/lang/StringBuilder;
    //   1266: pop
    //   1267: iload_2
    //   1268: ifne -> 1348
    //   1271: goto -> 1278
    //   1274: invokestatic a : (Ljava/lang/Throwable;)Ljava/lang/Throwable;
    //   1277: athrow
    //   1278: aload_3
    //   1279: getstatic burp/Ztes.Zo : Ljava/lang/String;
    //   1282: getstatic burp/Zs33.ZT : Ljava/lang/Object;
    //   1285: checkcast java/math/BigInteger
    //   1288: invokevirtual intValue : ()I
    //   1291: bipush #32
    //   1293: irem
    //   1294: invokestatic abs : (I)I
    //   1297: invokevirtual charAt : (I)C
    //   1300: invokevirtual append : (C)Ljava/lang/StringBuilder;
    //   1303: pop
    //   1304: iload_2
    //   1305: ifne -> 1348
    //   1308: goto -> 1315
    //   1311: invokestatic a : (Ljava/lang/Throwable;)Ljava/lang/Throwable;
    //   1314: athrow
    //   1315: aload_3
    //   1316: getstatic burp/Zsej.Zd : Ljava/lang/String;
    //   1319: getstatic burp/Zgny.ZR : Ljava/lang/Object;
    //   1322: checkcast java/math/BigInteger
    //   1325: invokevirtual intValue : ()I
    //   1328: bipush #32
    //   1330: irem
    //   1331: invokestatic abs : (I)I
    //   1334: invokevirtual charAt : (I)C
    //   1337: invokevirtual append : (C)Ljava/lang/StringBuilder;
    //   1340: pop
    //   1341: goto -> 1348
    //   1344: invokestatic a : (Ljava/lang/Throwable;)Ljava/lang/Throwable;
    //   1347: athrow
    //   1348: iinc #4, 1
    //   1351: iload_2
    //   1352: ifne -> 15
    //   1355: aload_3
    //   1356: invokevirtual toString : ()Ljava/lang/String;
    //   1359: putstatic burp/Zxtn.Zu : Ljava/lang/String;
    //   1362: new java/lang/StringBuilder
    //   1365: dup
    //   1366: invokespecial <init> : ()V
    //   1369: astore #4
    //   1371: iconst_0
    //   1372: istore #5
    //   1374: iload #5
    //   1376: bipush #32
    //   1378: if_icmpge -> 2743
    //   1381: iload #5
    //   1383: tableswitch default -> 2736, 0 -> 1524, 1 -> 1562, 2 -> 1600, 3 -> 1638, 4 -> 1676, 5 -> 1714, 6 -> 1752, 7 -> 1790, 8 -> 1828, 9 -> 1866, 10 -> 1904, 11 -> 1942, 12 -> 1980, 13 -> 2018, 14 -> 2056, 15 -> 2094, 16 -> 2132, 17 -> 2170, 18 -> 2208, 19 -> 2246, 20 -> 2284, 21 -> 2322, 22 -> 2360, 23 -> 2398, 24 -> 2436, 25 -> 2474, 26 -> 2512, 27 -> 2550, 28 -> 2588, 29 -> 2626, 30 -> 2664, 31 -> 2702
    //   1524: aload #4
    //   1526: getstatic burp/Zgdt.Zd : Ljava/lang/String;
    //   1529: getstatic burp/Zead.ZI : Ljava/lang/Object;
    //   1532: checkcast java/math/BigInteger
    //   1535: invokevirtual intValue : ()I
    //   1538: bipush #32
    //   1540: irem
    //   1541: invokestatic abs : (I)I
    //   1544: invokevirtual charAt : (I)C
    //   1547: invokevirtual append : (C)Ljava/lang/StringBuilder;
    //   1550: pop
    //   1551: iload_2
    //   1552: ifne -> 2736
    //   1555: goto -> 1562
    //   1558: invokestatic a : (Ljava/lang/Throwable;)Ljava/lang/Throwable;
    //   1561: athrow
    //   1562: aload #4
    //   1564: getstatic burp/Zxd0.Zc : Ljava/lang/String;
    //   1567: getstatic burp/Zzc7.ZG : Ljava/lang/Object;
    //   1570: checkcast java/math/BigInteger
    //   1573: invokevirtual intValue : ()I
    //   1576: bipush #32
    //   1578: irem
    //   1579: invokestatic abs : (I)I
    //   1582: invokevirtual charAt : (I)C
    //   1585: invokevirtual append : (C)Ljava/lang/StringBuilder;
    //   1588: pop
    //   1589: iload_2
    //   1590: ifne -> 2736
    //   1593: goto -> 1600
    //   1596: invokestatic a : (Ljava/lang/Throwable;)Ljava/lang/Throwable;
    //   1599: athrow
    //   1600: aload #4
    //   1602: getstatic burp/Zebj.ZF : Ljava/lang/String;
    //   1605: getstatic burp/Ztes.ZX : Ljava/lang/Object;
    //   1608: checkcast java/math/BigInteger
    //   1611: invokevirtual intValue : ()I
    //   1614: bipush #32
    //   1616: irem
    //   1617: invokestatic abs : (I)I
    //   1620: invokevirtual charAt : (I)C
    //   1623: invokevirtual append : (C)Ljava/lang/StringBuilder;
    //   1626: pop
    //   1627: iload_2
    //   1628: ifne -> 2736
    //   1631: goto -> 1638
    //   1634: invokestatic a : (Ljava/lang/Throwable;)Ljava/lang/Throwable;
    //   1637: athrow
    //   1638: aload #4
    //   1640: getstatic burp/Zbxp.ZS : Ljava/lang/String;
    //   1643: getstatic burp/Zgkl.ZK : Ljava/lang/Object;
    //   1646: checkcast java/math/BigInteger
    //   1649: invokevirtual intValue : ()I
    //   1652: bipush #32
    //   1654: irem
    //   1655: invokestatic abs : (I)I
    //   1658: invokevirtual charAt : (I)C
    //   1661: invokevirtual append : (C)Ljava/lang/StringBuilder;
    //   1664: pop
    //   1665: iload_2
    //   1666: ifne -> 2736
    //   1669: goto -> 1676
    //   1672: invokestatic a : (Ljava/lang/Throwable;)Ljava/lang/Throwable;
    //   1675: athrow
    //   1676: aload #4
    //   1678: getstatic burp/Zs0b.ZT : Ljava/lang/String;
    //   1681: getstatic burp/Zs0b.ZI : Ljava/lang/Object;
    //   1684: checkcast java/math/BigInteger
    //   1687: invokevirtual intValue : ()I
    //   1690: bipush #32
    //   1692: irem
    //   1693: invokestatic abs : (I)I
    //   1696: invokevirtual charAt : (I)C
    //   1699: invokevirtual append : (C)Ljava/lang/StringBuilder;
    //   1702: pop
    //   1703: iload_2
    //   1704: ifne -> 2736
    //   1707: goto -> 1714
    //   1710: invokestatic a : (Ljava/lang/Throwable;)Ljava/lang/Throwable;
    //   1713: athrow
    //   1714: aload #4
    //   1716: getstatic burp/Zl1u.ZO : Ljava/lang/String;
    //   1719: getstatic burp/Ztid.ZL : Ljava/lang/Object;
    //   1722: checkcast java/math/BigInteger
    //   1725: invokevirtual intValue : ()I
    //   1728: bipush #32
    //   1730: irem
    //   1731: invokestatic abs : (I)I
    //   1734: invokevirtual charAt : (I)C
    //   1737: invokevirtual append : (C)Ljava/lang/StringBuilder;
    //   1740: pop
    //   1741: iload_2
    //   1742: ifne -> 2736
    //   1745: goto -> 1752
    //   1748: invokestatic a : (Ljava/lang/Throwable;)Ljava/lang/Throwable;
    //   1751: athrow
    //   1752: aload #4
    //   1754: getstatic burp/Zgdt.Zd : Ljava/lang/String;
    //   1757: getstatic burp/Zgny.ZR : Ljava/lang/Object;
    //   1760: checkcast java/math/BigInteger
    //   1763: invokevirtual intValue : ()I
    //   1766: bipush #32
    //   1768: irem
    //   1769: invokestatic abs : (I)I
    //   1772: invokevirtual charAt : (I)C
    //   1775: invokevirtual append : (C)Ljava/lang/StringBuilder;
    //   1778: pop
    //   1779: iload_2
    //   1780: ifne -> 2736
    //   1783: goto -> 1790
    //   1786: invokestatic a : (Ljava/lang/Throwable;)Ljava/lang/Throwable;
    //   1789: athrow
    //   1790: aload #4
    //   1792: getstatic burp/Ze3t.ZG : Ljava/lang/String;
    //   1795: getstatic burp/Zb9k.Zi : Ljava/lang/Object;
    //   1798: checkcast java/math/BigInteger
    //   1801: invokevirtual intValue : ()I
    //   1804: bipush #32
    //   1806: irem
    //   1807: invokestatic abs : (I)I
    //   1810: invokevirtual charAt : (I)C
    //   1813: invokevirtual append : (C)Ljava/lang/StringBuilder;
    //   1816: pop
    //   1817: iload_2
    //   1818: ifne -> 2736
    //   1821: goto -> 1828
    //   1824: invokestatic a : (Ljava/lang/Throwable;)Ljava/lang/Throwable;
    //   1827: athrow
    //   1828: aload #4
    //   1830: getstatic burp/Ztpa.ZZ : Ljava/lang/String;
    //   1833: getstatic burp/Zlc5.ZH : Ljava/lang/Object;
    //   1836: checkcast java/math/BigInteger
    //   1839: invokevirtual intValue : ()I
    //   1842: bipush #32
    //   1844: irem
    //   1845: invokestatic abs : (I)I
    //   1848: invokevirtual charAt : (I)C
    //   1851: invokevirtual append : (C)Ljava/lang/StringBuilder;
    //   1854: pop
    //   1855: iload_2
    //   1856: ifne -> 2736
    //   1859: goto -> 1866
    //   1862: invokestatic a : (Ljava/lang/Throwable;)Ljava/lang/Throwable;
    //   1865: athrow
    //   1866: aload #4
    //   1868: getstatic burp/Ztid.Zz : Ljava/lang/String;
    //   1871: getstatic burp/Ztd6.ZI : Ljava/lang/Object;
    //   1874: checkcast java/math/BigInteger
    //   1877: invokevirtual intValue : ()I
    //   1880: bipush #32
    //   1882: irem
    //   1883: invokestatic abs : (I)I
    //   1886: invokevirtual charAt : (I)C
    //   1889: invokevirtual append : (C)Ljava/lang/StringBuilder;
    //   1892: pop
    //   1893: iload_2
    //   1894: ifne -> 2736
    //   1897: goto -> 1904
    //   1900: invokestatic a : (Ljava/lang/Throwable;)Ljava/lang/Throwable;
    //   1903: athrow
    //   1904: aload #4
    //   1906: getstatic burp/Zzvr.Zc : Ljava/lang/String;
    //   1909: getstatic burp/Zm06.ZU : Ljava/lang/Object;
    //   1912: checkcast java/math/BigInteger
    //   1915: invokevirtual intValue : ()I
    //   1918: bipush #32
    //   1920: irem
    //   1921: invokestatic abs : (I)I
    //   1924: invokevirtual charAt : (I)C
    //   1927: invokevirtual append : (C)Ljava/lang/StringBuilder;
    //   1930: pop
    //   1931: iload_2
    //   1932: ifne -> 2736
    //   1935: goto -> 1942
    //   1938: invokestatic a : (Ljava/lang/Throwable;)Ljava/lang/Throwable;
    //   1941: athrow
    //   1942: aload #4
    //   1944: getstatic burp/Zty5.Za : Ljava/lang/String;
    //   1947: getstatic burp/Zei_.Za : Ljava/lang/Object;
    //   1950: checkcast java/math/BigInteger
    //   1953: invokevirtual intValue : ()I
    //   1956: bipush #32
    //   1958: irem
    //   1959: invokestatic abs : (I)I
    //   1962: invokevirtual charAt : (I)C
    //   1965: invokevirtual append : (C)Ljava/lang/StringBuilder;
    //   1968: pop
    //   1969: iload_2
    //   1970: ifne -> 2736
    //   1973: goto -> 1980
    //   1976: invokestatic a : (Ljava/lang/Throwable;)Ljava/lang/Throwable;
    //   1979: athrow
    //   1980: aload #4
    //   1982: getstatic burp/Zsgj.ZN : Ljava/lang/String;
    //   1985: getstatic burp/Zgwq.Ze : Ljava/lang/Object;
    //   1988: checkcast java/math/BigInteger
    //   1991: invokevirtual intValue : ()I
    //   1994: bipush #32
    //   1996: irem
    //   1997: invokestatic abs : (I)I
    //   2000: invokevirtual charAt : (I)C
    //   2003: invokevirtual append : (C)Ljava/lang/StringBuilder;
    //   2006: pop
    //   2007: iload_2
    //   2008: ifne -> 2736
    //   2011: goto -> 2018
    //   2014: invokestatic a : (Ljava/lang/Throwable;)Ljava/lang/Throwable;
    //   2017: athrow
    //   2018: aload #4
    //   2020: getstatic burp/Zg97.ZX : Ljava/lang/String;
    //   2023: getstatic burp/Zezz.Zu : Ljava/lang/Object;
    //   2026: checkcast java/math/BigInteger
    //   2029: invokevirtual intValue : ()I
    //   2032: bipush #32
    //   2034: irem
    //   2035: invokestatic abs : (I)I
    //   2038: invokevirtual charAt : (I)C
    //   2041: invokevirtual append : (C)Ljava/lang/StringBuilder;
    //   2044: pop
    //   2045: iload_2
    //   2046: ifne -> 2736
    //   2049: goto -> 2056
    //   2052: invokestatic a : (Ljava/lang/Throwable;)Ljava/lang/Throwable;
    //   2055: athrow
    //   2056: aload #4
    //   2058: getstatic burp/Zxnm.Zw : Ljava/lang/String;
    //   2061: getstatic burp/Zxyq.ZQ : Ljava/lang/Object;
    //   2064: checkcast java/math/BigInteger
    //   2067: invokevirtual intValue : ()I
    //   2070: bipush #32
    //   2072: irem
    //   2073: invokestatic abs : (I)I
    //   2076: invokevirtual charAt : (I)C
    //   2079: invokevirtual append : (C)Ljava/lang/StringBuilder;
    //   2082: pop
    //   2083: iload_2
    //   2084: ifne -> 2736
    //   2087: goto -> 2094
    //   2090: invokestatic a : (Ljava/lang/Throwable;)Ljava/lang/Throwable;
    //   2093: athrow
    //   2094: aload #4
    //   2096: getstatic burp/Ztte.ZD : Ljava/lang/String;
    //   2099: getstatic burp/Zxnm.ZW : Ljava/lang/Object;
    //   2102: checkcast java/math/BigInteger
    //   2105: invokevirtual intValue : ()I
    //   2108: bipush #32
    //   2110: irem
    //   2111: invokestatic abs : (I)I
    //   2114: invokevirtual charAt : (I)C
    //   2117: invokevirtual append : (C)Ljava/lang/StringBuilder;
    //   2120: pop
    //   2121: iload_2
    //   2122: ifne -> 2736
    //   2125: goto -> 2132
    //   2128: invokestatic a : (Ljava/lang/Throwable;)Ljava/lang/Throwable;
    //   2131: athrow
    //   2132: aload #4
    //   2134: getstatic burp/Zzy5.ZD : Ljava/lang/String;
    //   2137: getstatic burp/Zl_9.ZM : Ljava/lang/Object;
    //   2140: checkcast java/math/BigInteger
    //   2143: invokevirtual intValue : ()I
    //   2146: bipush #32
    //   2148: irem
    //   2149: invokestatic abs : (I)I
    //   2152: invokevirtual charAt : (I)C
    //   2155: invokevirtual append : (C)Ljava/lang/StringBuilder;
    //   2158: pop
    //   2159: iload_2
    //   2160: ifne -> 2736
    //   2163: goto -> 2170
    //   2166: invokestatic a : (Ljava/lang/Throwable;)Ljava/lang/Throwable;
    //   2169: athrow
    //   2170: aload #4
    //   2172: getstatic burp/Ztd6.Zu : Ljava/lang/String;
    //   2175: getstatic burp/Zkvr.Zb : Ljava/lang/Object;
    //   2178: checkcast java/math/BigInteger
    //   2181: invokevirtual intValue : ()I
    //   2184: bipush #32
    //   2186: irem
    //   2187: invokestatic abs : (I)I
    //   2190: invokevirtual charAt : (I)C
    //   2193: invokevirtual append : (C)Ljava/lang/StringBuilder;
    //   2196: pop
    //   2197: iload_2
    //   2198: ifne -> 2736
    //   2201: goto -> 2208
    //   2204: invokestatic a : (Ljava/lang/Throwable;)Ljava/lang/Throwable;
    //   2207: athrow
    //   2208: aload #4
    //   2210: getstatic burp/Zzv.Zy : Ljava/lang/String;
    //   2213: getstatic burp/Zmhx.ZQ : Ljava/lang/Object;
    //   2216: checkcast java/math/BigInteger
    //   2219: invokevirtual intValue : ()I
    //   2222: bipush #32
    //   2224: irem
    //   2225: invokestatic abs : (I)I
    //   2228: invokevirtual charAt : (I)C
    //   2231: invokevirtual append : (C)Ljava/lang/StringBuilder;
    //   2234: pop
    //   2235: iload_2
    //   2236: ifne -> 2736
    //   2239: goto -> 2246
    //   2242: invokestatic a : (Ljava/lang/Throwable;)Ljava/lang/Throwable;
    //   2245: athrow
    //   2246: aload #4
    //   2248: getstatic burp/Zr3x.ZM : Ljava/lang/String;
    //   2251: getstatic burp/Zzwl.Z_ : Ljava/lang/Object;
    //   2254: checkcast java/math/BigInteger
    //   2257: invokevirtual intValue : ()I
    //   2260: bipush #32
    //   2262: irem
    //   2263: invokestatic abs : (I)I
    //   2266: invokevirtual charAt : (I)C
    //   2269: invokevirtual append : (C)Ljava/lang/StringBuilder;
    //   2272: pop
    //   2273: iload_2
    //   2274: ifne -> 2736
    //   2277: goto -> 2284
    //   2280: invokestatic a : (Ljava/lang/Throwable;)Ljava/lang/Throwable;
    //   2283: athrow
    //   2284: aload #4
    //   2286: getstatic burp/Zr3x.ZM : Ljava/lang/String;
    //   2289: getstatic burp/Zejg.ZR : Ljava/lang/Object;
    //   2292: checkcast java/math/BigInteger
    //   2295: invokevirtual intValue : ()I
    //   2298: bipush #32
    //   2300: irem
    //   2301: invokestatic abs : (I)I
    //   2304: invokevirtual charAt : (I)C
    //   2307: invokevirtual append : (C)Ljava/lang/StringBuilder;
    //   2310: pop
    //   2311: iload_2
    //   2312: ifne -> 2736
    //   2315: goto -> 2322
    //   2318: invokestatic a : (Ljava/lang/Throwable;)Ljava/lang/Throwable;
    //   2321: athrow
    //   2322: aload #4
    //   2324: getstatic burp/Zsej.Zd : Ljava/lang/String;
    //   2327: getstatic burp/Zkku.Zz : Ljava/lang/Object;
    //   2330: checkcast java/math/BigInteger
    //   2333: invokevirtual intValue : ()I
    //   2336: bipush #32
    //   2338: irem
    //   2339: invokestatic abs : (I)I
    //   2342: invokevirtual charAt : (I)C
    //   2345: invokevirtual append : (C)Ljava/lang/StringBuilder;
    //   2348: pop
    //   2349: iload_2
    //   2350: ifne -> 2736
    //   2353: goto -> 2360
    //   2356: invokestatic a : (Ljava/lang/Throwable;)Ljava/lang/Throwable;
    //   2359: athrow
    //   2360: aload #4
    //   2362: getstatic burp/Zls_.Zn : Ljava/lang/String;
    //   2365: getstatic burp/Zz0j.Zn : Ljava/lang/Object;
    //   2368: checkcast java/math/BigInteger
    //   2371: invokevirtual intValue : ()I
    //   2374: bipush #32
    //   2376: irem
    //   2377: invokestatic abs : (I)I
    //   2380: invokevirtual charAt : (I)C
    //   2383: invokevirtual append : (C)Ljava/lang/StringBuilder;
    //   2386: pop
    //   2387: iload_2
    //   2388: ifne -> 2736
    //   2391: goto -> 2398
    //   2394: invokestatic a : (Ljava/lang/Throwable;)Ljava/lang/Throwable;
    //   2397: athrow
    //   2398: aload #4
    //   2400: getstatic burp/Zttj.ZN : Ljava/lang/String;
    //   2403: getstatic burp/Zl1u.Zq : Ljava/lang/Object;
    //   2406: checkcast java/math/BigInteger
    //   2409: invokevirtual intValue : ()I
    //   2412: bipush #32
    //   2414: irem
    //   2415: invokestatic abs : (I)I
    //   2418: invokevirtual charAt : (I)C
    //   2421: invokevirtual append : (C)Ljava/lang/StringBuilder;
    //   2424: pop
    //   2425: iload_2
    //   2426: ifne -> 2736
    //   2429: goto -> 2436
    //   2432: invokestatic a : (Ljava/lang/Throwable;)Ljava/lang/Throwable;
    //   2435: athrow
    //   2436: aload #4
    //   2438: getstatic burp/Zr8g.ZH : Ljava/lang/String;
    //   2441: getstatic burp/Zzy5.ZG : Ljava/lang/Object;
    //   2444: checkcast java/math/BigInteger
    //   2447: invokevirtual intValue : ()I
    //   2450: bipush #32
    //   2452: irem
    //   2453: invokestatic abs : (I)I
    //   2456: invokevirtual charAt : (I)C
    //   2459: invokevirtual append : (C)Ljava/lang/StringBuilder;
    //   2462: pop
    //   2463: iload_2
    //   2464: ifne -> 2736
    //   2467: goto -> 2474
    //   2470: invokestatic a : (Ljava/lang/Throwable;)Ljava/lang/Throwable;
    //   2473: athrow
    //   2474: aload #4
    //   2476: getstatic burp/Zkul.ZJ : Ljava/lang/String;
    //   2479: getstatic burp/Zz9p.Zw : Ljava/lang/Object;
    //   2482: checkcast java/math/BigInteger
    //   2485: invokevirtual intValue : ()I
    //   2488: bipush #32
    //   2490: irem
    //   2491: invokestatic abs : (I)I
    //   2494: invokevirtual charAt : (I)C
    //   2497: invokevirtual append : (C)Ljava/lang/StringBuilder;
    //   2500: pop
    //   2501: iload_2
    //   2502: ifne -> 2736
    //   2505: goto -> 2512
    //   2508: invokestatic a : (Ljava/lang/Throwable;)Ljava/lang/Throwable;
    //   2511: athrow
    //   2512: aload #4
    //   2514: getstatic burp/Zl_9.ZP : Ljava/lang/String;
    //   2517: getstatic burp/Zewo.ZZ : Ljava/lang/Object;
    //   2520: checkcast java/math/BigInteger
    //   2523: invokevirtual intValue : ()I
    //   2526: bipush #32
    //   2528: irem
    //   2529: invokestatic abs : (I)I
    //   2532: invokevirtual charAt : (I)C
    //   2535: invokevirtual append : (C)Ljava/lang/StringBuilder;
    //   2538: pop
    //   2539: iload_2
    //   2540: ifne -> 2736
    //   2543: goto -> 2550
    //   2546: invokestatic a : (Ljava/lang/Throwable;)Ljava/lang/Throwable;
    //   2549: athrow
    //   2550: aload #4
    //   2552: getstatic burp/Zs6g.ZU : Ljava/lang/String;
    //   2555: getstatic burp/Zxn7.ZU : Ljava/lang/Object;
    //   2558: checkcast java/math/BigInteger
    //   2561: invokevirtual intValue : ()I
    //   2564: bipush #32
    //   2566: irem
    //   2567: invokestatic abs : (I)I
    //   2570: invokevirtual charAt : (I)C
    //   2573: invokevirtual append : (C)Ljava/lang/StringBuilder;
    //   2576: pop
    //   2577: iload_2
    //   2578: ifne -> 2736
    //   2581: goto -> 2588
    //   2584: invokestatic a : (Ljava/lang/Throwable;)Ljava/lang/Throwable;
    //   2587: athrow
    //   2588: aload #4
    //   2590: getstatic burp/Zkku.Zq : Ljava/lang/String;
    //   2593: getstatic burp/Zebj.Zf : Ljava/lang/Object;
    //   2596: checkcast java/math/BigInteger
    //   2599: invokevirtual intValue : ()I
    //   2602: bipush #32
    //   2604: irem
    //   2605: invokestatic abs : (I)I
    //   2608: invokevirtual charAt : (I)C
    //   2611: invokevirtual append : (C)Ljava/lang/StringBuilder;
    //   2614: pop
    //   2615: iload_2
    //   2616: ifne -> 2736
    //   2619: goto -> 2626
    //   2622: invokestatic a : (Ljava/lang/Throwable;)Ljava/lang/Throwable;
    //   2625: athrow
    //   2626: aload #4
    //   2628: getstatic burp/Zejg.ZP : Ljava/lang/String;
    //   2631: getstatic burp/Zs9u.Zd : Ljava/lang/Object;
    //   2634: checkcast java/math/BigInteger
    //   2637: invokevirtual intValue : ()I
    //   2640: bipush #32
    //   2642: irem
    //   2643: invokestatic abs : (I)I
    //   2646: invokevirtual charAt : (I)C
    //   2649: invokevirtual append : (C)Ljava/lang/StringBuilder;
    //   2652: pop
    //   2653: iload_2
    //   2654: ifne -> 2736
    //   2657: goto -> 2664
    //   2660: invokestatic a : (Ljava/lang/Throwable;)Ljava/lang/Throwable;
    //   2663: athrow
    //   2664: aload #4
    //   2666: getstatic burp/Zxyq.Zr : Ljava/lang/String;
    //   2669: getstatic burp/Zghe.ZJ : Ljava/lang/Object;
    //   2672: checkcast java/math/BigInteger
    //   2675: invokevirtual intValue : ()I
    //   2678: bipush #32
    //   2680: irem
    //   2681: invokestatic abs : (I)I
    //   2684: invokevirtual charAt : (I)C
    //   2687: invokevirtual append : (C)Ljava/lang/StringBuilder;
    //   2690: pop
    //   2691: iload_2
    //   2692: ifne -> 2736
    //   2695: goto -> 2702
    //   2698: invokestatic a : (Ljava/lang/Throwable;)Ljava/lang/Throwable;
    //   2701: athrow
    //   2702: aload #4
    //   2704: getstatic burp/Zblv.ZF : Ljava/lang/String;
    //   2707: getstatic burp/Ztid.ZL : Ljava/lang/Object;
    //   2710: checkcast java/math/BigInteger
    //   2713: invokevirtual intValue : ()I
    //   2716: bipush #32
    //   2718: irem
    //   2719: invokestatic abs : (I)I
    //   2722: invokevirtual charAt : (I)C
    //   2725: invokevirtual append : (C)Ljava/lang/StringBuilder;
    //   2728: pop
    //   2729: goto -> 2736
    //   2732: invokestatic a : (Ljava/lang/Throwable;)Ljava/lang/Throwable;
    //   2735: athrow
    //   2736: iinc #5, 1
    //   2739: iload_2
    //   2740: ifne -> 1374
    //   2743: aload #4
    //   2745: invokevirtual toString : ()Ljava/lang/String;
    //   2748: putstatic burp/Ztid.Zz : Ljava/lang/String;
    //   2751: new java/io/ByteArrayOutputStream
    //   2754: dup
    //   2755: invokespecial <init> : ()V
    //   2758: astore #5
    //   2760: getstatic burp/Zs33.ZX : Ljava/lang/String;
    //   2763: astore #6
    //   2765: iconst_0
    //   2766: istore #7
    //   2768: iload #7
    //   2770: aload #6
    //   2772: invokevirtual length : ()I
    //   2775: if_icmpge -> 2806
    //   2778: aload #5
    //   2780: aload #6
    //   2782: iload #7
    //   2784: iload #7
    //   2786: iconst_2
    //   2787: iadd
    //   2788: invokevirtual substring : (II)Ljava/lang/String;
    //   2791: bipush #16
    //   2793: invokestatic parseInt : (Ljava/lang/String;I)I
    //   2796: invokevirtual write : (I)V
    //   2799: iinc #7, 2
    //   2802: iload_2
    //   2803: ifne -> 2768
    //   2806: aload #5
    //   2808: invokevirtual toByteArray : ()[B
    //   2811: astore #7
    //   2813: getstatic burp/Zxrd.ZL : Ljava/lang/Object;
    //   2816: checkcast java/math/BigInteger
    //   2819: invokevirtual toByteArray : ()[B
    //   2822: astore #8
    //   2824: sipush #256
    //   2827: newarray byte
    //   2829: astore #10
    //   2831: sipush #256
    //   2834: newarray int
    //   2836: astore #11
    //   2838: sipush #256
    //   2841: newarray int
    //   2843: astore #12
    //   2845: sipush #256
    //   2848: newarray int
    //   2850: astore #13
    //   2852: sipush #256
    //   2855: newarray int
    //   2857: astore #14
    //   2859: bipush #10
    //   2861: newarray int
    //   2863: astore #15
    //   2865: sipush #283
    //   2868: istore #16
    //   2870: iconst_0
    //   2871: istore #18
    //   2873: iload #18
    //   2875: sipush #256
    //   2878: if_icmpge -> 3112
    //   2881: sipush #-1564
    //   2884: sipush #-3990
    //   2887: invokestatic a : (II)Ljava/lang/String;
    //   2890: iload #18
    //   2892: iconst_1
    //   2893: iushr
    //   2894: invokevirtual charAt : (I)C
    //   2897: istore #27
    //   2899: iload #18
    //   2901: iconst_1
    //   2902: iand
    //   2903: ifne -> 2918
    //   2906: iload #27
    //   2908: bipush #8
    //   2910: iushr
    //   2911: goto -> 2920
    //   2914: invokestatic a : (Ljava/lang/Throwable;)Ljava/lang/Throwable;
    //   2917: athrow
    //   2918: iload #27
    //   2920: i2b
    //   2921: sipush #255
    //   2924: iand
    //   2925: istore #17
    //   2927: iload #18
    //   2929: iconst_1
    //   2930: ishl
    //   2931: istore #19
    //   2933: iload #19
    //   2935: sipush #256
    //   2938: if_icmplt -> 2948
    //   2941: iload #19
    //   2943: iload #16
    //   2945: ixor
    //   2946: istore #19
    //   2948: iload #19
    //   2950: iconst_1
    //   2951: ishl
    //   2952: istore #20
    //   2954: iload #20
    //   2956: sipush #256
    //   2959: if_icmplt -> 2969
    //   2962: iload #20
    //   2964: iload #16
    //   2966: ixor
    //   2967: istore #20
    //   2969: iload #20
    //   2971: iconst_1
    //   2972: ishl
    //   2973: istore #21
    //   2975: iload #21
    //   2977: sipush #256
    //   2980: if_icmplt -> 2990
    //   2983: iload #21
    //   2985: iload #16
    //   2987: ixor
    //   2988: istore #21
    //   2990: iload #21
    //   2992: iload #18
    //   2994: ixor
    //   2995: istore #22
    //   2997: iload #22
    //   2999: iload #19
    //   3001: ixor
    //   3002: istore #23
    //   3004: iload #22
    //   3006: iload #20
    //   3008: ixor
    //   3009: istore #24
    //   3011: iload #21
    //   3013: iload #20
    //   3015: ixor
    //   3016: iload #19
    //   3018: ixor
    //   3019: istore #25
    //   3021: aload #10
    //   3023: iload #18
    //   3025: iload #17
    //   3027: i2b
    //   3028: bastore
    //   3029: aload #11
    //   3031: iload #17
    //   3033: iload #25
    //   3035: bipush #24
    //   3037: ishl
    //   3038: iload #22
    //   3040: bipush #16
    //   3042: ishl
    //   3043: ior
    //   3044: iload #24
    //   3046: bipush #8
    //   3048: ishl
    //   3049: ior
    //   3050: iload #23
    //   3052: ior
    //   3053: dup
    //   3054: istore #26
    //   3056: iastore
    //   3057: aload #12
    //   3059: iload #17
    //   3061: iload #26
    //   3063: bipush #8
    //   3065: iushr
    //   3066: iload #26
    //   3068: bipush #24
    //   3070: ishl
    //   3071: ior
    //   3072: iastore
    //   3073: aload #13
    //   3075: iload #17
    //   3077: iload #26
    //   3079: bipush #16
    //   3081: iushr
    //   3082: iload #26
    //   3084: bipush #16
    //   3086: ishl
    //   3087: ior
    //   3088: iastore
    //   3089: aload #14
    //   3091: iload #17
    //   3093: iload #26
    //   3095: bipush #24
    //   3097: iushr
    //   3098: iload #26
    //   3100: bipush #8
    //   3102: ishl
    //   3103: ior
    //   3104: iastore
    //   3105: iinc #18, 1
    //   3108: iload_2
    //   3109: ifne -> 2873
    //   3112: iconst_1
    //   3113: istore #27
    //   3115: aload #15
    //   3117: iconst_0
    //   3118: iload #27
    //   3120: bipush #24
    //   3122: ishl
    //   3123: iastore
    //   3124: iconst_1
    //   3125: istore #28
    //   3127: iload #28
    //   3129: bipush #10
    //   3131: if_icmpge -> 3172
    //   3134: iload #27
    //   3136: iconst_1
    //   3137: ishl
    //   3138: istore #27
    //   3140: iload #27
    //   3142: sipush #256
    //   3145: if_icmplt -> 3155
    //   3148: iload #27
    //   3150: iload #16
    //   3152: ixor
    //   3153: istore #27
    //   3155: aload #15
    //   3157: iload #28
    //   3159: iload #27
    //   3161: bipush #24
    //   3163: ishl
    //   3164: iastore
    //   3165: iinc #28, 1
    //   3168: iload_2
    //   3169: ifne -> 3127
    //   3172: iconst_4
    //   3173: istore #28
    //   3175: iload #28
    //   3177: bipush #6
    //   3179: iadd
    //   3180: istore #29
    //   3182: iconst_4
    //   3183: iload #29
    //   3185: iconst_1
    //   3186: iadd
    //   3187: imul
    //   3188: istore #30
    //   3190: iload #30
    //   3192: newarray int
    //   3194: astore #31
    //   3196: iload #30
    //   3198: newarray int
    //   3200: astore #32
    //   3202: iconst_0
    //   3203: istore #27
    //   3205: iconst_0
    //   3206: istore #34
    //   3208: iconst_0
    //   3209: istore #35
    //   3211: iload #34
    //   3213: iload #28
    //   3215: if_icmpge -> 3283
    //   3218: aload #31
    //   3220: iload #34
    //   3222: aload #7
    //   3224: iload #35
    //   3226: baload
    //   3227: bipush #24
    //   3229: ishl
    //   3230: aload #7
    //   3232: iload #35
    //   3234: iconst_1
    //   3235: iadd
    //   3236: baload
    //   3237: sipush #255
    //   3240: iand
    //   3241: bipush #16
    //   3243: ishl
    //   3244: ior
    //   3245: aload #7
    //   3247: iload #35
    //   3249: iconst_2
    //   3250: iadd
    //   3251: baload
    //   3252: sipush #255
    //   3255: iand
    //   3256: bipush #8
    //   3258: ishl
    //   3259: ior
    //   3260: aload #7
    //   3262: iload #35
    //   3264: iconst_3
    //   3265: iadd
    //   3266: baload
    //   3267: sipush #255
    //   3270: iand
    //   3271: ior
    //   3272: iastore
    //   3273: iinc #34, 1
    //   3276: iinc #35, 4
    //   3279: iload_2
    //   3280: ifne -> 3211
    //   3283: iload #28
    //   3285: istore #34
    //   3287: iconst_0
    //   3288: istore #35
    //   3290: iload #34
    //   3292: iload #30
    //   3294: if_icmpge -> 3421
    //   3297: aload #31
    //   3299: iload #34
    //   3301: iconst_1
    //   3302: isub
    //   3303: iaload
    //   3304: istore #33
    //   3306: iload #35
    //   3308: ifne -> 3395
    //   3311: iload #28
    //   3313: istore #35
    //   3315: aload #10
    //   3317: iload #33
    //   3319: bipush #16
    //   3321: iushr
    //   3322: sipush #255
    //   3325: iand
    //   3326: baload
    //   3327: bipush #24
    //   3329: ishl
    //   3330: aload #10
    //   3332: iload #33
    //   3334: bipush #8
    //   3336: iushr
    //   3337: sipush #255
    //   3340: iand
    //   3341: baload
    //   3342: sipush #255
    //   3345: iand
    //   3346: bipush #16
    //   3348: ishl
    //   3349: ior
    //   3350: aload #10
    //   3352: iload #33
    //   3354: sipush #255
    //   3357: iand
    //   3358: baload
    //   3359: sipush #255
    //   3362: iand
    //   3363: bipush #8
    //   3365: ishl
    //   3366: ior
    //   3367: aload #10
    //   3369: iload #33
    //   3371: bipush #24
    //   3373: iushr
    //   3374: baload
    //   3375: sipush #255
    //   3378: iand
    //   3379: ior
    //   3380: istore #33
    //   3382: iload #33
    //   3384: aload #15
    //   3386: iload #27
    //   3388: iinc #27, 1
    //   3391: iaload
    //   3392: ixor
    //   3393: istore #33
    //   3395: aload #31
    //   3397: iload #34
    //   3399: aload #31
    //   3401: iload #34
    //   3403: iload #28
    //   3405: isub
    //   3406: iaload
    //   3407: iload #33
    //   3409: ixor
    //   3410: iastore
    //   3411: iinc #34, 1
    //   3414: iinc #35, -1
    //   3417: iload_2
    //   3418: ifne -> 3290
    //   3421: iconst_0
    //   3422: istore #34
    //   3424: iconst_4
    //   3425: iload #29
    //   3427: imul
    //   3428: istore #35
    //   3430: aload #32
    //   3432: iload #34
    //   3434: aload #31
    //   3436: iload #35
    //   3438: iaload
    //   3439: iastore
    //   3440: aload #32
    //   3442: iload #34
    //   3444: iconst_1
    //   3445: iadd
    //   3446: aload #31
    //   3448: iload #35
    //   3450: iconst_1
    //   3451: iadd
    //   3452: iaload
    //   3453: iastore
    //   3454: aload #32
    //   3456: iload #34
    //   3458: iconst_2
    //   3459: iadd
    //   3460: aload #31
    //   3462: iload #35
    //   3464: iconst_2
    //   3465: iadd
    //   3466: iaload
    //   3467: iastore
    //   3468: aload #32
    //   3470: iload #34
    //   3472: iconst_3
    //   3473: iadd
    //   3474: aload #31
    //   3476: iload #35
    //   3478: iconst_3
    //   3479: iadd
    //   3480: iaload
    //   3481: iastore
    //   3482: iinc #34, 4
    //   3485: iinc #35, -4
    //   3488: iconst_1
    //   3489: istore #37
    //   3491: iload #37
    //   3493: iload #29
    //   3495: if_icmpge -> 3859
    //   3498: aload #31
    //   3500: iload #35
    //   3502: iaload
    //   3503: istore #36
    //   3505: aload #32
    //   3507: iload #34
    //   3509: aload #11
    //   3511: aload #10
    //   3513: iload #36
    //   3515: bipush #24
    //   3517: iushr
    //   3518: baload
    //   3519: sipush #255
    //   3522: iand
    //   3523: iaload
    //   3524: aload #12
    //   3526: aload #10
    //   3528: iload #36
    //   3530: bipush #16
    //   3532: iushr
    //   3533: sipush #255
    //   3536: iand
    //   3537: baload
    //   3538: sipush #255
    //   3541: iand
    //   3542: iaload
    //   3543: ixor
    //   3544: aload #13
    //   3546: aload #10
    //   3548: iload #36
    //   3550: bipush #8
    //   3552: iushr
    //   3553: sipush #255
    //   3556: iand
    //   3557: baload
    //   3558: sipush #255
    //   3561: iand
    //   3562: iaload
    //   3563: ixor
    //   3564: aload #14
    //   3566: aload #10
    //   3568: iload #36
    //   3570: sipush #255
    //   3573: iand
    //   3574: baload
    //   3575: sipush #255
    //   3578: iand
    //   3579: iaload
    //   3580: ixor
    //   3581: iastore
    //   3582: aload #31
    //   3584: iload #35
    //   3586: iconst_1
    //   3587: iadd
    //   3588: iaload
    //   3589: istore #36
    //   3591: aload #32
    //   3593: iload #34
    //   3595: iconst_1
    //   3596: iadd
    //   3597: aload #11
    //   3599: aload #10
    //   3601: iload #36
    //   3603: bipush #24
    //   3605: iushr
    //   3606: baload
    //   3607: sipush #255
    //   3610: iand
    //   3611: iaload
    //   3612: aload #12
    //   3614: aload #10
    //   3616: iload #36
    //   3618: bipush #16
    //   3620: iushr
    //   3621: sipush #255
    //   3624: iand
    //   3625: baload
    //   3626: sipush #255
    //   3629: iand
    //   3630: iaload
    //   3631: ixor
    //   3632: aload #13
    //   3634: aload #10
    //   3636: iload #36
    //   3638: bipush #8
    //   3640: iushr
    //   3641: sipush #255
    //   3644: iand
    //   3645: baload
    //   3646: sipush #255
    //   3649: iand
    //   3650: iaload
    //   3651: ixor
    //   3652: aload #14
    //   3654: aload #10
    //   3656: iload #36
    //   3658: sipush #255
    //   3661: iand
    //   3662: baload
    //   3663: sipush #255
    //   3666: iand
    //   3667: iaload
    //   3668: ixor
    //   3669: iastore
    //   3670: aload #31
    //   3672: iload #35
    //   3674: iconst_2
    //   3675: iadd
    //   3676: iaload
    //   3677: istore #36
    //   3679: aload #32
    //   3681: iload #34
    //   3683: iconst_2
    //   3684: iadd
    //   3685: aload #11
    //   3687: aload #10
    //   3689: iload #36
    //   3691: bipush #24
    //   3693: iushr
    //   3694: baload
    //   3695: sipush #255
    //   3698: iand
    //   3699: iaload
    //   3700: aload #12
    //   3702: aload #10
    //   3704: iload #36
    //   3706: bipush #16
    //   3708: iushr
    //   3709: sipush #255
    //   3712: iand
    //   3713: baload
    //   3714: sipush #255
    //   3717: iand
    //   3718: iaload
    //   3719: ixor
    //   3720: aload #13
    //   3722: aload #10
    //   3724: iload #36
    //   3726: bipush #8
    //   3728: iushr
    //   3729: sipush #255
    //   3732: iand
    //   3733: baload
    //   3734: sipush #255
    //   3737: iand
    //   3738: iaload
    //   3739: ixor
    //   3740: aload #14
    //   3742: aload #10
    //   3744: iload #36
    //   3746: sipush #255
    //   3749: iand
    //   3750: baload
    //   3751: sipush #255
    //   3754: iand
    //   3755: iaload
    //   3756: ixor
    //   3757: iastore
    //   3758: aload #31
    //   3760: iload #35
    //   3762: iconst_3
    //   3763: iadd
    //   3764: iaload
    //   3765: istore #36
    //   3767: aload #32
    //   3769: iload #34
    //   3771: iconst_3
    //   3772: iadd
    //   3773: aload #11
    //   3775: aload #10
    //   3777: iload #36
    //   3779: bipush #24
    //   3781: iushr
    //   3782: baload
    //   3783: sipush #255
    //   3786: iand
    //   3787: iaload
    //   3788: aload #12
    //   3790: aload #10
    //   3792: iload #36
    //   3794: bipush #16
    //   3796: iushr
    //   3797: sipush #255
    //   3800: iand
    //   3801: baload
    //   3802: sipush #255
    //   3805: iand
    //   3806: iaload
    //   3807: ixor
    //   3808: aload #13
    //   3810: aload #10
    //   3812: iload #36
    //   3814: bipush #8
    //   3816: iushr
    //   3817: sipush #255
    //   3820: iand
    //   3821: baload
    //   3822: sipush #255
    //   3825: iand
    //   3826: iaload
    //   3827: ixor
    //   3828: aload #14
    //   3830: aload #10
    //   3832: iload #36
    //   3834: sipush #255
    //   3837: iand
    //   3838: baload
    //   3839: sipush #255
    //   3842: iand
    //   3843: iaload
    //   3844: ixor
    //   3845: iastore
    //   3846: iinc #34, 4
    //   3849: iinc #35, -4
    //   3852: iinc #37, 1
    //   3855: iload_2
    //   3856: ifne -> 3491
    //   3859: aload #32
    //   3861: iload #34
    //   3863: aload #31
    //   3865: iload #35
    //   3867: iaload
    //   3868: iastore
    //   3869: aload #32
    //   3871: iload #34
    //   3873: iconst_1
    //   3874: iadd
    //   3875: aload #31
    //   3877: iload #35
    //   3879: iconst_1
    //   3880: iadd
    //   3881: iaload
    //   3882: iastore
    //   3883: aload #32
    //   3885: iload #34
    //   3887: iconst_2
    //   3888: iadd
    //   3889: aload #31
    //   3891: iload #35
    //   3893: iconst_2
    //   3894: iadd
    //   3895: iaload
    //   3896: iastore
    //   3897: aload #32
    //   3899: iload #34
    //   3901: iconst_3
    //   3902: iadd
    //   3903: aload #31
    //   3905: iload #35
    //   3907: iconst_3
    //   3908: iadd
    //   3909: iaload
    //   3910: iastore
    //   3911: iconst_0
    //   3912: newarray byte
    //   3914: astore #37
    //   3916: aload #8
    //   3918: arraylength
    //   3919: bipush #16
    //   3921: irem
    //   3922: ifeq -> 3946
    //   3925: new java/lang/Exception
    //   3928: dup
    //   3929: sipush #-1562
    //   3932: sipush #15144
    //   3935: invokestatic a : (II)Ljava/lang/String;
    //   3938: invokespecial <init> : (Ljava/lang/String;)V
    //   3941: athrow
    //   3942: invokestatic a : (Ljava/lang/Throwable;)Ljava/lang/Throwable;
    //   3945: athrow
    //   3946: bipush #10
    //   3948: istore #38
    //   3950: sipush #-1566
    //   3953: sipush #256
    //   3956: newarray byte
    //   3958: astore #39
    //   3960: sipush #19606
    //   3963: sipush #256
    //   3966: newarray int
    //   3968: astore #40
    //   3970: sipush #256
    //   3973: newarray int
    //   3975: astore #41
    //   3977: sipush #256
    //   3980: newarray int
    //   3982: astore #42
    //   3984: sipush #256
    //   3987: newarray int
    //   3989: astore #43
    //   3991: sipush #283
    //   3994: istore #16
    //   3996: invokestatic a : (II)Ljava/lang/String;
    //   3999: astore #44
    //   4001: iconst_0
    //   4002: istore #18
    //   4004: iload #18
    //   4006: sipush #256
    //   4009: if_icmpge -> 4236
    //   4012: aload #44
    //   4014: iload #18
    //   4016: iconst_1
    //   4017: iushr
    //   4018: invokevirtual charAt : (I)C
    //   4021: istore #45
    //   4023: iload #18
    //   4025: iconst_1
    //   4026: iand
    //   4027: ifne -> 4042
    //   4030: iload #45
    //   4032: bipush #8
    //   4034: iushr
    //   4035: goto -> 4044
    //   4038: invokestatic a : (Ljava/lang/Throwable;)Ljava/lang/Throwable;
    //   4041: athrow
    //   4042: iload #45
    //   4044: i2b
    //   4045: sipush #255
    //   4048: iand
    //   4049: istore #17
    //   4051: iload #18
    //   4053: iconst_1
    //   4054: ishl
    //   4055: istore #19
    //   4057: iload #19
    //   4059: sipush #256
    //   4062: if_icmplt -> 4072
    //   4065: iload #19
    //   4067: iload #16
    //   4069: ixor
    //   4070: istore #19
    //   4072: iload #19
    //   4074: iconst_1
    //   4075: ishl
    //   4076: istore #20
    //   4078: iload #20
    //   4080: sipush #256
    //   4083: if_icmplt -> 4093
    //   4086: iload #20
    //   4088: iload #16
    //   4090: ixor
    //   4091: istore #20
    //   4093: iload #20
    //   4095: iconst_1
    //   4096: ishl
    //   4097: istore #21
    //   4099: iload #21
    //   4101: sipush #256
    //   4104: if_icmplt -> 4114
    //   4107: iload #21
    //   4109: iload #16
    //   4111: ixor
    //   4112: istore #21
    //   4114: iload #21
    //   4116: iload #18
    //   4118: ixor
    //   4119: istore #22
    //   4121: iload #22
    //   4123: iload #19
    //   4125: ixor
    //   4126: istore #23
    //   4128: iload #22
    //   4130: iload #20
    //   4132: ixor
    //   4133: istore #24
    //   4135: iload #21
    //   4137: iload #20
    //   4139: ixor
    //   4140: iload #19
    //   4142: ixor
    //   4143: istore #25
    //   4145: aload #39
    //   4147: iload #17
    //   4149: iload #18
    //   4151: i2b
    //   4152: bastore
    //   4153: aload #40
    //   4155: iload #17
    //   4157: iload #25
    //   4159: bipush #24
    //   4161: ishl
    //   4162: iload #22
    //   4164: bipush #16
    //   4166: ishl
    //   4167: ior
    //   4168: iload #24
    //   4170: bipush #8
    //   4172: ishl
    //   4173: ior
    //   4174: iload #23
    //   4176: ior
    //   4177: dup
    //   4178: istore #26
    //   4180: iastore
    //   4181: aload #41
    //   4183: iload #17
    //   4185: iload #26
    //   4187: bipush #8
    //   4189: iushr
    //   4190: iload #26
    //   4192: bipush #24
    //   4194: ishl
    //   4195: ior
    //   4196: iastore
    //   4197: aload #42
    //   4199: iload #17
    //   4201: iload #26
    //   4203: bipush #16
    //   4205: iushr
    //   4206: iload #26
    //   4208: bipush #16
    //   4210: ishl
    //   4211: ior
    //   4212: iastore
    //   4213: aload #43
    //   4215: iload #17
    //   4217: iload #26
    //   4219: bipush #24
    //   4221: iushr
    //   4222: iload #26
    //   4224: bipush #8
    //   4226: ishl
    //   4227: ior
    //   4228: iastore
    //   4229: iinc #18, 1
    //   4232: iload_2
    //   4233: ifne -> 4004
    //   4236: aload #8
    //   4238: arraylength
    //   4239: newarray byte
    //   4241: astore #45
    //   4243: iconst_0
    //   4244: istore #46
    //   4246: iload #46
    //   4248: aload #8
    //   4250: arraylength
    //   4251: bipush #16
    //   4253: idiv
    //   4254: if_icmpge -> 5168
    //   4257: bipush #16
    //   4259: newarray byte
    //   4261: astore #47
    //   4263: bipush #16
    //   4265: newarray byte
    //   4267: astore #48
    //   4269: iconst_0
    //   4270: istore #49
    //   4272: iload #49
    //   4274: bipush #16
    //   4276: if_icmpge -> 4302
    //   4279: aload #47
    //   4281: iload #49
    //   4283: aload #8
    //   4285: iload #49
    //   4287: iload #46
    //   4289: bipush #16
    //   4291: imul
    //   4292: iadd
    //   4293: baload
    //   4294: bastore
    //   4295: iinc #49, 1
    //   4298: iload_2
    //   4299: ifne -> 4272
    //   4302: iconst_0
    //   4303: istore #49
    //   4305: aload #47
    //   4307: iconst_0
    //   4308: baload
    //   4309: bipush #24
    //   4311: ishl
    //   4312: aload #47
    //   4314: iconst_1
    //   4315: baload
    //   4316: sipush #255
    //   4319: iand
    //   4320: bipush #16
    //   4322: ishl
    //   4323: ior
    //   4324: aload #47
    //   4326: iconst_2
    //   4327: baload
    //   4328: sipush #255
    //   4331: iand
    //   4332: bipush #8
    //   4334: ishl
    //   4335: ior
    //   4336: aload #47
    //   4338: iconst_3
    //   4339: baload
    //   4340: sipush #255
    //   4343: iand
    //   4344: ior
    //   4345: aload #32
    //   4347: iconst_0
    //   4348: iaload
    //   4349: ixor
    //   4350: istore #51
    //   4352: aload #47
    //   4354: iconst_4
    //   4355: baload
    //   4356: bipush #24
    //   4358: ishl
    //   4359: aload #47
    //   4361: iconst_5
    //   4362: baload
    //   4363: sipush #255
    //   4366: iand
    //   4367: bipush #16
    //   4369: ishl
    //   4370: ior
    //   4371: aload #47
    //   4373: bipush #6
    //   4375: baload
    //   4376: sipush #255
    //   4379: iand
    //   4380: bipush #8
    //   4382: ishl
    //   4383: ior
    //   4384: aload #47
    //   4386: bipush #7
    //   4388: baload
    //   4389: sipush #255
    //   4392: iand
    //   4393: ior
    //   4394: aload #32
    //   4396: iconst_1
    //   4397: iaload
    //   4398: ixor
    //   4399: istore #52
    //   4401: aload #47
    //   4403: bipush #8
    //   4405: baload
    //   4406: bipush #24
    //   4408: ishl
    //   4409: aload #47
    //   4411: bipush #9
    //   4413: baload
    //   4414: sipush #255
    //   4417: iand
    //   4418: bipush #16
    //   4420: ishl
    //   4421: ior
    //   4422: aload #47
    //   4424: bipush #10
    //   4426: baload
    //   4427: sipush #255
    //   4430: iand
    //   4431: bipush #8
    //   4433: ishl
    //   4434: ior
    //   4435: aload #47
    //   4437: bipush #11
    //   4439: baload
    //   4440: sipush #255
    //   4443: iand
    //   4444: ior
    //   4445: aload #32
    //   4447: iconst_2
    //   4448: iaload
    //   4449: ixor
    //   4450: istore #53
    //   4452: aload #47
    //   4454: bipush #12
    //   4456: baload
    //   4457: bipush #24
    //   4459: ishl
    //   4460: aload #47
    //   4462: bipush #13
    //   4464: baload
    //   4465: sipush #255
    //   4468: iand
    //   4469: bipush #16
    //   4471: ishl
    //   4472: ior
    //   4473: aload #47
    //   4475: bipush #14
    //   4477: baload
    //   4478: sipush #255
    //   4481: iand
    //   4482: bipush #8
    //   4484: ishl
    //   4485: ior
    //   4486: aload #47
    //   4488: bipush #15
    //   4490: baload
    //   4491: sipush #255
    //   4494: iand
    //   4495: ior
    //   4496: aload #32
    //   4498: iconst_3
    //   4499: iaload
    //   4500: ixor
    //   4501: istore #54
    //   4503: iconst_1
    //   4504: istore #55
    //   4506: iload #55
    //   4508: iload #38
    //   4510: if_icmpge -> 4753
    //   4513: iinc #49, 4
    //   4516: aload #40
    //   4518: iload #51
    //   4520: bipush #24
    //   4522: iushr
    //   4523: iaload
    //   4524: aload #41
    //   4526: iload #54
    //   4528: bipush #16
    //   4530: iushr
    //   4531: sipush #255
    //   4534: iand
    //   4535: iaload
    //   4536: ixor
    //   4537: aload #42
    //   4539: iload #53
    //   4541: bipush #8
    //   4543: iushr
    //   4544: sipush #255
    //   4547: iand
    //   4548: iaload
    //   4549: ixor
    //   4550: aload #43
    //   4552: iload #52
    //   4554: sipush #255
    //   4557: iand
    //   4558: iaload
    //   4559: ixor
    //   4560: aload #32
    //   4562: iload #49
    //   4564: iaload
    //   4565: ixor
    //   4566: istore #56
    //   4568: aload #40
    //   4570: iload #52
    //   4572: bipush #24
    //   4574: iushr
    //   4575: iaload
    //   4576: aload #41
    //   4578: iload #51
    //   4580: bipush #16
    //   4582: iushr
    //   4583: sipush #255
    //   4586: iand
    //   4587: iaload
    //   4588: ixor
    //   4589: aload #42
    //   4591: iload #54
    //   4593: bipush #8
    //   4595: iushr
    //   4596: sipush #255
    //   4599: iand
    //   4600: iaload
    //   4601: ixor
    //   4602: aload #43
    //   4604: iload #53
    //   4606: sipush #255
    //   4609: iand
    //   4610: iaload
    //   4611: ixor
    //   4612: aload #32
    //   4614: iload #49
    //   4616: iconst_1
    //   4617: iadd
    //   4618: iaload
    //   4619: ixor
    //   4620: istore #57
    //   4622: aload #40
    //   4624: iload #53
    //   4626: bipush #24
    //   4628: iushr
    //   4629: iaload
    //   4630: aload #41
    //   4632: iload #52
    //   4634: bipush #16
    //   4636: iushr
    //   4637: sipush #255
    //   4640: iand
    //   4641: iaload
    //   4642: ixor
    //   4643: aload #42
    //   4645: iload #51
    //   4647: bipush #8
    //   4649: iushr
    //   4650: sipush #255
    //   4653: iand
    //   4654: iaload
    //   4655: ixor
    //   4656: aload #43
    //   4658: iload #54
    //   4660: sipush #255
    //   4663: iand
    //   4664: iaload
    //   4665: ixor
    //   4666: aload #32
    //   4668: iload #49
    //   4670: iconst_2
    //   4671: iadd
    //   4672: iaload
    //   4673: ixor
    //   4674: istore #58
    //   4676: aload #40
    //   4678: iload #54
    //   4680: bipush #24
    //   4682: iushr
    //   4683: iaload
    //   4684: aload #41
    //   4686: iload #53
    //   4688: bipush #16
    //   4690: iushr
    //   4691: sipush #255
    //   4694: iand
    //   4695: iaload
    //   4696: ixor
    //   4697: aload #42
    //   4699: iload #52
    //   4701: bipush #8
    //   4703: iushr
    //   4704: sipush #255
    //   4707: iand
    //   4708: iaload
    //   4709: ixor
    //   4710: aload #43
    //   4712: iload #51
    //   4714: sipush #255
    //   4717: iand
    //   4718: iaload
    //   4719: ixor
    //   4720: aload #32
    //   4722: iload #49
    //   4724: iconst_3
    //   4725: iadd
    //   4726: iaload
    //   4727: ixor
    //   4728: istore #59
    //   4730: iload #56
    //   4732: istore #51
    //   4734: iload #57
    //   4736: istore #52
    //   4738: iload #58
    //   4740: istore #53
    //   4742: iload #59
    //   4744: istore #54
    //   4746: iinc #55, 1
    //   4749: iload_2
    //   4750: ifne -> 4506
    //   4753: iinc #49, 4
    //   4756: aload #32
    //   4758: iload #49
    //   4760: iaload
    //   4761: istore #50
    //   4763: aload #48
    //   4765: iconst_0
    //   4766: aload #39
    //   4768: iload #51
    //   4770: bipush #24
    //   4772: iushr
    //   4773: baload
    //   4774: iload #50
    //   4776: bipush #24
    //   4778: iushr
    //   4779: ixor
    //   4780: i2b
    //   4781: bastore
    //   4782: aload #48
    //   4784: iconst_1
    //   4785: aload #39
    //   4787: iload #54
    //   4789: bipush #16
    //   4791: iushr
    //   4792: sipush #255
    //   4795: iand
    //   4796: baload
    //   4797: iload #50
    //   4799: bipush #16
    //   4801: iushr
    //   4802: ixor
    //   4803: i2b
    //   4804: bastore
    //   4805: aload #48
    //   4807: iconst_2
    //   4808: aload #39
    //   4810: iload #53
    //   4812: bipush #8
    //   4814: iushr
    //   4815: sipush #255
    //   4818: iand
    //   4819: baload
    //   4820: iload #50
    //   4822: bipush #8
    //   4824: iushr
    //   4825: ixor
    //   4826: i2b
    //   4827: bastore
    //   4828: aload #48
    //   4830: iconst_3
    //   4831: aload #39
    //   4833: iload #52
    //   4835: sipush #255
    //   4838: iand
    //   4839: baload
    //   4840: iload #50
    //   4842: ixor
    //   4843: i2b
    //   4844: bastore
    //   4845: aload #32
    //   4847: iload #49
    //   4849: iconst_1
    //   4850: iadd
    //   4851: iaload
    //   4852: istore #50
    //   4854: aload #48
    //   4856: iconst_4
    //   4857: aload #39
    //   4859: iload #52
    //   4861: bipush #24
    //   4863: iushr
    //   4864: baload
    //   4865: iload #50
    //   4867: bipush #24
    //   4869: iushr
    //   4870: ixor
    //   4871: i2b
    //   4872: bastore
    //   4873: aload #48
    //   4875: iconst_5
    //   4876: aload #39
    //   4878: iload #51
    //   4880: bipush #16
    //   4882: iushr
    //   4883: sipush #255
    //   4886: iand
    //   4887: baload
    //   4888: iload #50
    //   4890: bipush #16
    //   4892: iushr
    //   4893: ixor
    //   4894: i2b
    //   4895: bastore
    //   4896: aload #48
    //   4898: bipush #6
    //   4900: aload #39
    //   4902: iload #54
    //   4904: bipush #8
    //   4906: iushr
    //   4907: sipush #255
    //   4910: iand
    //   4911: baload
    //   4912: iload #50
    //   4914: bipush #8
    //   4916: iushr
    //   4917: ixor
    //   4918: i2b
    //   4919: bastore
    //   4920: aload #48
    //   4922: bipush #7
    //   4924: aload #39
    //   4926: iload #53
    //   4928: sipush #255
    //   4931: iand
    //   4932: baload
    //   4933: iload #50
    //   4935: ixor
    //   4936: i2b
    //   4937: bastore
    //   4938: aload #32
    //   4940: iload #49
    //   4942: iconst_2
    //   4943: iadd
    //   4944: iaload
    //   4945: istore #50
    //   4947: aload #48
    //   4949: bipush #8
    //   4951: aload #39
    //   4953: iload #53
    //   4955: bipush #24
    //   4957: iushr
    //   4958: baload
    //   4959: iload #50
    //   4961: bipush #24
    //   4963: iushr
    //   4964: ixor
    //   4965: i2b
    //   4966: bastore
    //   4967: aload #48
    //   4969: bipush #9
    //   4971: aload #39
    //   4973: iload #52
    //   4975: bipush #16
    //   4977: iushr
    //   4978: sipush #255
    //   4981: iand
    //   4982: baload
    //   4983: iload #50
    //   4985: bipush #16
    //   4987: iushr
    //   4988: ixor
    //   4989: i2b
    //   4990: bastore
    //   4991: aload #48
    //   4993: bipush #10
    //   4995: aload #39
    //   4997: iload #51
    //   4999: bipush #8
    //   5001: iushr
    //   5002: sipush #255
    //   5005: iand
    //   5006: baload
    //   5007: iload #50
    //   5009: bipush #8
    //   5011: iushr
    //   5012: ixor
    //   5013: i2b
    //   5014: bastore
    //   5015: aload #48
    //   5017: bipush #11
    //   5019: aload #39
    //   5021: iload #54
    //   5023: sipush #255
    //   5026: iand
    //   5027: baload
    //   5028: iload #50
    //   5030: ixor
    //   5031: i2b
    //   5032: bastore
    //   5033: aload #32
    //   5035: iload #49
    //   5037: iconst_3
    //   5038: iadd
    //   5039: iaload
    //   5040: istore #50
    //   5042: aload #48
    //   5044: bipush #12
    //   5046: aload #39
    //   5048: iload #54
    //   5050: bipush #24
    //   5052: iushr
    //   5053: baload
    //   5054: iload #50
    //   5056: bipush #24
    //   5058: iushr
    //   5059: ixor
    //   5060: i2b
    //   5061: bastore
    //   5062: aload #48
    //   5064: bipush #13
    //   5066: aload #39
    //   5068: iload #53
    //   5070: bipush #16
    //   5072: iushr
    //   5073: sipush #255
    //   5076: iand
    //   5077: baload
    //   5078: iload #50
    //   5080: bipush #16
    //   5082: iushr
    //   5083: ixor
    //   5084: i2b
    //   5085: bastore
    //   5086: aload #48
    //   5088: bipush #14
    //   5090: aload #39
    //   5092: iload #52
    //   5094: bipush #8
    //   5096: iushr
    //   5097: sipush #255
    //   5100: iand
    //   5101: baload
    //   5102: iload #50
    //   5104: bipush #8
    //   5106: iushr
    //   5107: ixor
    //   5108: i2b
    //   5109: bastore
    //   5110: aload #48
    //   5112: bipush #15
    //   5114: aload #39
    //   5116: iload #51
    //   5118: sipush #255
    //   5121: iand
    //   5122: baload
    //   5123: iload #50
    //   5125: ixor
    //   5126: i2b
    //   5127: bastore
    //   5128: iconst_0
    //   5129: istore #55
    //   5131: iload #55
    //   5133: bipush #16
    //   5135: if_icmpge -> 5161
    //   5138: aload #45
    //   5140: iload #55
    //   5142: iload #46
    //   5144: bipush #16
    //   5146: imul
    //   5147: iadd
    //   5148: aload #48
    //   5150: iload #55
    //   5152: baload
    //   5153: bastore
    //   5154: iinc #55, 1
    //   5157: iload_2
    //   5158: ifne -> 5131
    //   5161: iinc #46, 1
    //   5164: iload_2
    //   5165: ifne -> 4246
    //   5168: aload #45
    //   5170: arraylength
    //   5171: ifle -> 5252
    //   5174: aload #45
    //   5176: aload #45
    //   5178: arraylength
    //   5179: iconst_1
    //   5180: isub
    //   5181: baload
    //   5182: istore #46
    //   5184: iload #46
    //   5186: bipush #16
    //   5188: if_icmple -> 5199
    //   5191: aload #45
    //   5193: astore #37
    //   5195: iload_2
    //   5196: ifne -> 5252
    //   5199: aload #45
    //   5201: arraylength
    //   5202: iload #46
    //   5204: isub
    //   5205: newarray byte
    //   5207: astore #37
    //   5209: iconst_0
    //   5210: istore #47
    //   5212: iload #47
    //   5214: aload #37
    //   5216: arraylength
    //   5217: if_icmpge -> 5252
    //   5220: iload #47
    //   5222: aload #45
    //   5224: arraylength
    //   5225: if_icmpge -> 5252
    //   5228: aload #37
    //   5230: iload #47
    //   5232: aload #45
    //   5234: iload #47
    //   5236: baload
    //   5237: bastore
    //   5238: iinc #47, 1
    //   5241: iload_2
    //   5242: ifne -> 5212
    //   5245: goto -> 5252
    //   5248: invokestatic a : (Ljava/lang/Throwable;)Ljava/lang/Throwable;
    //   5251: athrow
    //   5252: aload #37
    //   5254: astore #9
    //   5256: sipush #-1553
    //   5259: new java/math/BigInteger
    //   5262: dup
    //   5263: aload #9
    //   5265: invokespecial <init> : ([B)V
    //   5268: invokevirtual abs : ()Ljava/math/BigInteger;
    //   5271: putstatic burp/Zko9.ZC : Ljava/lang/Object;
    //   5274: sipush #-3286
    //   5277: invokestatic a : (II)Ljava/lang/String;
    //   5280: iconst_1
    //   5281: ldc burp/Zrva
    //   5283: invokevirtual getClassLoader : ()Ljava/lang/ClassLoader;
    //   5286: invokestatic forName : (Ljava/lang/String;ZLjava/lang/ClassLoader;)Ljava/lang/Class;
    //   5289: invokevirtual getDeclaredFields : ()[Ljava/lang/reflect/Field;
    //   5292: astore #5
    //   5294: aload #5
    //   5296: arraylength
    //   5297: istore #6
    //   5299: iconst_0
    //   5300: istore #7
    //   5302: iload #7
    //   5304: iload #6
    //   5306: if_icmpge -> 5444
    //   5309: aload #5
    //   5311: iload #7
    //   5313: aaload
    //   5314: astore #8
    //   5316: aload #8
    //   5318: invokevirtual getModifiers : ()I
    //   5321: invokestatic isStatic : (I)Z
    //   5324: ifne -> 5334
    //   5327: goto -> 5437
    //   5330: invokestatic a : (Ljava/lang/Throwable;)Ljava/lang/Throwable;
    //   5333: athrow
    //   5334: aload #8
    //   5336: invokevirtual getType : ()Ljava/lang/Class;
    //   5339: astore #9
    //   5341: aload #9
    //   5343: ifnull -> 5424
    //   5346: aload #9
    //   5348: invokevirtual isPrimitive : ()Z
    //   5351: ifne -> 5424
    //   5354: goto -> 5361
    //   5357: invokestatic a : (Ljava/lang/Throwable;)Ljava/lang/Throwable;
    //   5360: athrow
    //   5361: aload #9
    //   5363: invokevirtual getPackage : ()Ljava/lang/Package;
    //   5366: ifnull -> 5424
    //   5369: goto -> 5376
    //   5372: invokestatic a : (Ljava/lang/Throwable;)Ljava/lang/Throwable;
    //   5375: athrow
    //   5376: aload #9
    //   5378: invokevirtual getPackage : ()Ljava/lang/Package;
    //   5381: invokevirtual getName : ()Ljava/lang/String;
    //   5384: ifnull -> 5424
    //   5387: goto -> 5394
    //   5390: invokestatic a : (Ljava/lang/Throwable;)Ljava/lang/Throwable;
    //   5393: athrow
    //   5394: aload #9
    //   5396: invokevirtual getPackage : ()Ljava/lang/Package;
    //   5399: invokevirtual getName : ()Ljava/lang/String;
    //   5402: sipush #-1567
    //   5405: sipush #-19694
    //   5408: invokestatic a : (II)Ljava/lang/String;
    //   5411: invokevirtual startsWith : (Ljava/lang/String;)Z
    //   5414: ifne -> 5424
    //   5417: goto -> 5424
    //   5420: invokestatic a : (Ljava/lang/Throwable;)Ljava/lang/Throwable;
    //   5423: athrow
    //   5424: aload #8
    //   5426: iconst_1
    //   5427: invokevirtual setAccessible : (Z)V
    //   5430: aload #8
    //   5432: aconst_null
    //   5433: invokevirtual get : (Ljava/lang/Object;)Ljava/lang/Object;
    //   5436: pop
    //   5437: iinc #7, 1
    //   5440: iload_2
    //   5441: ifne -> 5302
    //   5444: sipush #-1561
    //   5447: sipush #-24758
    //   5450: invokestatic a : (II)Ljava/lang/String;
    //   5453: invokestatic forName : (Ljava/lang/String;)Ljava/lang/Class;
    //   5456: invokevirtual getDeclaredMethods : ()[Ljava/lang/reflect/Method;
    //   5459: astore #5
    //   5461: aload #5
    //   5463: arraylength
    //   5464: istore #6
    //   5466: iconst_0
    //   5467: istore #7
    //   5469: iload #7
    //   5471: iload #6
    //   5473: if_icmpge -> 5606
    //   5476: aload #5
    //   5478: iload #7
    //   5480: aaload
    //   5481: astore #8
    //   5483: aload #8
    //   5485: invokevirtual getParameterTypes : ()[Ljava/lang/Class;
    //   5488: pop
    //   5489: aload #8
    //   5491: invokevirtual getModifiers : ()I
    //   5494: invokestatic isStatic : (I)Z
    //   5497: ifeq -> 5592
    //   5500: aload #8
    //   5502: invokevirtual getParameterTypes : ()[Ljava/lang/Class;
    //   5505: arraylength
    //   5506: iconst_2
    //   5507: if_icmpne -> 5592
    //   5510: goto -> 5517
    //   5513: invokestatic a : (Ljava/lang/Throwable;)Ljava/lang/Throwable;
    //   5516: athrow
    //   5517: aload #8
    //   5519: invokevirtual getReturnType : ()Ljava/lang/Class;
    //   5522: getstatic java/lang/Void.TYPE : Ljava/lang/Class;
    //   5525: invokevirtual equals : (Ljava/lang/Object;)Z
    //   5528: ifeq -> 5592
    //   5531: goto -> 5538
    //   5534: invokestatic a : (Ljava/lang/Throwable;)Ljava/lang/Throwable;
    //   5537: athrow
    //   5538: aload #8
    //   5540: iconst_1
    //   5541: invokevirtual setAccessible : (Z)V
    //   5544: aload #8
    //   5546: aconst_null
    //   5547: iconst_2
    //   5548: anewarray java/lang/Object
    //   5551: dup
    //   5552: iconst_0
    //   5553: aload_0
    //   5554: aastore
    //   5555: dup
    //   5556: iconst_1
    //   5557: aload_1
    //   5558: ifnonnull -> 5576
    //   5561: goto -> 5568
    //   5564: invokestatic a : (Ljava/lang/Throwable;)Ljava/lang/Throwable;
    //   5567: athrow
    //   5568: aload_1
    //   5569: goto -> 5583
    //   5572: invokestatic a : (Ljava/lang/Throwable;)Ljava/lang/Throwable;
    //   5575: athrow
    //   5576: aload_1
    //   5577: checkcast [B
    //   5580: invokevirtual clone : ()Ljava/lang/Object;
    //   5583: aastore
    //   5584: invokevirtual invoke : (Ljava/lang/Object;[Ljava/lang/Object;)Ljava/lang/Object;
    //   5587: pop
    //   5588: iload_2
    //   5589: ifne -> 5606
    //   5592: iinc #7, 1
    //   5595: iload_2
    //   5596: ifne -> 5469
    //   5599: goto -> 5606
    //   5602: invokestatic a : (Ljava/lang/Throwable;)Ljava/lang/Throwable;
    //   5605: athrow
    //   5606: getstatic burp/Zblv.ZF : Ljava/lang/String;
    //   5609: getstatic burp/Ztte.ZR : Ljava/lang/Object;
    //   5612: checkcast java/math/BigInteger
    //   5615: invokevirtual intValue : ()I
    //   5618: bipush #32
    //   5620: irem
    //   5621: invokestatic abs : (I)I
    //   5624: invokevirtual charAt : (I)C
    //   5627: getstatic burp/Zg97.ZX : Ljava/lang/String;
    //   5630: getstatic burp/Zltb.ZL : Ljava/lang/Object;
    //   5633: checkcast java/math/BigInteger
    //   5636: invokevirtual intValue : ()I
    //   5639: bipush #32
    //   5641: irem
    //   5642: invokestatic abs : (I)I
    //   5645: invokevirtual charAt : (I)C
    //   5648: if_icmple -> 5763
    //   5651: getstatic burp/Zlc5.Z_ : Ljava/lang/String;
    //   5654: getstatic burp/Zlc5.ZH : Ljava/lang/Object;
    //   5657: checkcast java/math/BigInteger
    //   5660: invokevirtual intValue : ()I
    //   5663: bipush #32
    //   5665: irem
    //   5666: invokestatic abs : (I)I
    //   5669: invokevirtual charAt : (I)C
    //   5672: getstatic burp/Zzv.Zy : Ljava/lang/String;
    //   5675: getstatic burp/Ztes.ZX : Ljava/lang/Object;
    //   5678: checkcast java/math/BigInteger
    //   5681: invokevirtual intValue : ()I
    //   5684: bipush #32
    //   5686: irem
    //   5687: invokestatic abs : (I)I
    //   5690: invokevirtual charAt : (I)C
    //   5693: if_icmple -> 5763
    //   5696: goto -> 5703
    //   5699: invokestatic a : (Ljava/lang/Throwable;)Ljava/lang/Throwable;
    //   5702: athrow
    //   5703: getstatic burp/Zb9k.Za : Ljava/lang/String;
    //   5706: getstatic burp/Zz67.ZE : Ljava/lang/Object;
    //   5709: checkcast java/math/BigInteger
    //   5712: invokevirtual intValue : ()I
    //   5715: bipush #32
    //   5717: irem
    //   5718: invokestatic abs : (I)I
    //   5721: invokevirtual charAt : (I)C
    //   5724: getstatic burp/Zxn7.ZG : Ljava/lang/String;
    //   5727: getstatic burp/Zr3x.Zb : Ljava/lang/Object;
    //   5730: checkcast java/math/BigInteger
    //   5733: invokevirtual intValue : ()I
    //   5736: bipush #32
    //   5738: irem
    //   5739: invokestatic abs : (I)I
    //   5742: invokevirtual charAt : (I)C
    //   5745: if_icmple -> 5763
    //   5748: goto -> 5755
    //   5751: invokestatic a : (Ljava/lang/Throwable;)Ljava/lang/Throwable;
    //   5754: athrow
    //   5755: iconst_1
    //   5756: goto -> 5764
    //   5759: invokestatic a : (Ljava/lang/Throwable;)Ljava/lang/Throwable;
    //   5762: athrow
    //   5763: iconst_0
    //   5764: ireturn
    //   5765: astore_3
    //   5766: new java/lang/Exception
    //   5769: dup
    //   5770: aload_3
    //   5771: invokevirtual getMessage : ()Ljava/lang/String;
    //   5774: invokespecial <init> : (Ljava/lang/String;)V
    //   5777: athrow
    // Exception table:
    //   from	to	target	type
    //   4	5764	5765	java/lang/Throwable
    //   22	198	201	java/lang/Throwable
    //   168	235	238	java/lang/Throwable
    //   205	272	275	java/lang/Throwable
    //   242	309	312	java/lang/Throwable
    //   279	346	349	java/lang/Throwable
    //   316	383	386	java/lang/Throwable
    //   353	420	423	java/lang/Throwable
    //   390	457	460	java/lang/Throwable
    //   427	494	497	java/lang/Throwable
    //   464	531	534	java/lang/Throwable
    //   501	568	571	java/lang/Throwable
    //   538	605	608	java/lang/Throwable
    //   575	642	645	java/lang/Throwable
    //   612	679	682	java/lang/Throwable
    //   649	716	719	java/lang/Throwable
    //   686	753	756	java/lang/Throwable
    //   723	790	793	java/lang/Throwable
    //   760	827	830	java/lang/Throwable
    //   797	864	867	java/lang/Throwable
    //   834	901	904	java/lang/Throwable
    //   871	938	941	java/lang/Throwable
    //   908	975	978	java/lang/Throwable
    //   945	1012	1015	java/lang/Throwable
    //   982	1049	1052	java/lang/Throwable
    //   1019	1086	1089	java/lang/Throwable
    //   1056	1123	1126	java/lang/Throwable
    //   1093	1160	1163	java/lang/Throwable
    //   1130	1197	1200	java/lang/Throwable
    //   1167	1234	1237	java/lang/Throwable
    //   1204	1271	1274	java/lang/Throwable
    //   1241	1308	1311	java/lang/Throwable
    //   1278	1341	1344	java/lang/Throwable
    //   1381	1555	1558	java/lang/Throwable
    //   1524	1593	1596	java/lang/Throwable
    //   1562	1631	1634	java/lang/Throwable
    //   1600	1669	1672	java/lang/Throwable
    //   1638	1707	1710	java/lang/Throwable
    //   1676	1745	1748	java/lang/Throwable
    //   1714	1783	1786	java/lang/Throwable
    //   1752	1821	1824	java/lang/Throwable
    //   1790	1859	1862	java/lang/Throwable
    //   1828	1897	1900	java/lang/Throwable
    //   1866	1935	1938	java/lang/Throwable
    //   1904	1973	1976	java/lang/Throwable
    //   1942	2011	2014	java/lang/Throwable
    //   1980	2049	2052	java/lang/Throwable
    //   2018	2087	2090	java/lang/Throwable
    //   2056	2125	2128	java/lang/Throwable
    //   2094	2163	2166	java/lang/Throwable
    //   2132	2201	2204	java/lang/Throwable
    //   2170	2239	2242	java/lang/Throwable
    //   2208	2277	2280	java/lang/Throwable
    //   2246	2315	2318	java/lang/Throwable
    //   2284	2353	2356	java/lang/Throwable
    //   2322	2391	2394	java/lang/Throwable
    //   2360	2429	2432	java/lang/Throwable
    //   2398	2467	2470	java/lang/Throwable
    //   2436	2505	2508	java/lang/Throwable
    //   2474	2543	2546	java/lang/Throwable
    //   2512	2581	2584	java/lang/Throwable
    //   2550	2619	2622	java/lang/Throwable
    //   2588	2657	2660	java/lang/Throwable
    //   2626	2695	2698	java/lang/Throwable
    //   2664	2729	2732	java/lang/Throwable
    //   2899	2914	2914	java/lang/Throwable
    //   3916	3942	3942	java/lang/Throwable
    //   4023	4038	4038	java/lang/Throwable
    //   5220	5245	5248	java/lang/Throwable
    //   5316	5330	5330	java/lang/Throwable
    //   5341	5354	5357	java/lang/Throwable
    //   5346	5369	5372	java/lang/Throwable
    //   5361	5387	5390	java/lang/Throwable
    //   5376	5417	5420	java/lang/Throwable
    //   5483	5510	5513	java/lang/Throwable
    //   5500	5531	5534	java/lang/Throwable
    //   5517	5561	5564	java/lang/Throwable
    //   5538	5572	5572	java/lang/Throwable
    //   5583	5599	5602	java/lang/Throwable
    //   5606	5696	5699	java/lang/Throwable
    //   5651	5748	5751	java/lang/Throwable
    //   5703	5759	5759	java/lang/Throwable
  }
  
  static {
    // Byte code:
    //   0: bipush #12
    //   2: anewarray java/lang/String
    //   5: astore #5
    //   7: iconst_0
    //   8: istore_3
    //   9: ldc 'N\\feFL:cb`0V\\tV1??M|\\b;i"\\t\\tU3z\\n8|\\f{<|bpY(HiV\ \\b" <SMui??[Mk(\\bFav\:O 0l2#.4*{_n$-Na\\tB^t= \\fxU\\f3\\tZ}7'
    //   11: dup
    //   12: astore_2
    //   13: invokevirtual length : ()I
    //   16: istore #4
    //   18: bipush #9
    //   20: istore_1
    //   21: iconst_m1
    //   22: istore_0
    //   23: bipush #116
    //   25: iinc #0, 1
    //   28: aload_2
    //   29: iload_0
    //   30: dup
    //   31: iload_1
    //   32: iadd
    //   33: invokevirtual substring : (II)Ljava/lang/String;
    //   36: iconst_m1
    //   37: goto -> 143
    //   40: aload #5
    //   42: swap
    //   43: iload_3
    //   44: iinc #3, 1
    //   47: swap
    //   48: aastore
    //   49: iload_0
    //   50: iload_1
    //   51: iadd
    //   52: dup
    //   53: istore_0
    //   54: iload #4
    //   56: if_icmpge -> 68
    //   59: aload_2
    //   60: iload_0
    //   61: invokevirtual charAt : (I)C
    //   64: istore_1
    //   65: goto -> 23
    //   68: ldc 'Tn|\\f]:p@[a\\tj'
    //   70: dup
    //   71: astore_2
    //   72: invokevirtual length : ()I
    //   75: istore #4
    //   77: bipush #32
    //   79: istore_1
    //   80: iconst_m1
    //   81: istore_0
    //   82: bipush #42
    //   84: iinc #0, 1
    //   87: aload_2
    //   88: iload_0
    //   89: dup
    //   90: iload_1
    //   91: iadd
    //   92: invokevirtual substring : (II)Ljava/lang/String;
    //   95: iconst_0
    //   96: goto -> 143
    //   99: aload #5
    //   101: swap
    //   102: iload_3
    //   103: iinc #3, 1
    //   106: swap
    //   107: aastore
    //   108: iload_0
    //   109: iload_1
    //   110: iadd
    //   111: dup
    //   112: istore_0
    //   113: iload #4
    //   115: if_icmpge -> 127
    //   118: aload_2
    //   119: iload_0
    //   120: invokevirtual charAt : (I)C
    //   123: istore_1
    //   124: goto -> 82
    //   127: aload #5
    //   129: putstatic burp/Zkku.a : [Ljava/lang/String;
    //   132: bipush #12
    //   134: anewarray java/lang/String
    //   137: putstatic burp/Zkku.b : [Ljava/lang/String;
    //   140: goto -> 300
    //   143: dup_x2
    //   144: pop
    //   145: invokevirtual toCharArray : ()[C
    //   148: dup_x1
    //   149: arraylength
    //   150: dup_x2
    //   151: pop
    //   152: iconst_0
    //   153: istore #6
    //   155: dup2_x1
    //   156: pop2
    //   157: dup_x2
    //   158: iconst_1
    //   159: if_icmpgt -> 260
    //   162: dup2
    //   163: swap
    //   164: iload #6
    //   166: dup2_x1
    //   167: caload
    //   168: swap
    //   169: iload #6
    //   171: bipush #7
    //   173: irem
    //   174: tableswitch default -> 242, 0 -> 212, 1 -> 217, 2 -> 222, 3 -> 227, 4 -> 232, 5 -> 237
    //   212: bipush #124
    //   214: goto -> 244
    //   217: bipush #116
    //   219: goto -> 244
    //   222: bipush #63
    //   224: goto -> 244
    //   227: bipush #59
    //   229: goto -> 244
    //   232: bipush #15
    //   234: goto -> 244
    //   237: bipush #10
    //   239: goto -> 244
    //   242: bipush #89
    //   244: ixor
    //   245: ixor
    //   246: i2c
    //   247: castore
    //   248: iinc #6, 1
    //   251: dup
    //   252: ifne -> 260
    //   255: dup2
    //   256: dup_x1
    //   257: goto -> 166
    //   260: dup2_x1
    //   261: pop2
    //   262: dup_x2
    //   263: iload #6
    //   265: if_icmpgt -> 162
    //   268: pop
    //   269: new java/lang/String
    //   272: dup_x1
    //   273: swap
    //   274: invokespecial <init> : ([C)V
    //   277: invokevirtual intern : ()Ljava/lang/String;
    //   280: swap
    //   281: pop
    //   282: swap
    //   283: tableswitch default -> 40, 0 -> 99
    //   300: sipush #-1555
    //   303: sipush #-22399
    //   306: invokestatic a : (II)Ljava/lang/String;
    //   309: putstatic burp/Zkku.Zq : Ljava/lang/String;
    //   312: new java/math/BigInteger
    //   315: dup
    //   316: sipush #-1565
    //   319: sipush #-16571
    //   322: invokestatic a : (II)Ljava/lang/String;
    //   325: invokespecial <init> : (Ljava/lang/String;)V
    //   328: putstatic burp/Zkku.Zz : Ljava/lang/Object;
    //   331: return
  }
  
  private static Throwable a(Throwable paramThrowable) {
    return paramThrowable;
  }
  
  private static String a(int paramInt1, int paramInt2) {
    int i = (paramInt1 ^ 0xFFFFF9E7) & 0xFFFF;
    if (b[i] == null) {
      char[] arrayOfChar = a[i].toCharArray();
      switch (arrayOfChar[0] & 0xFF) {
        case 0:
        
        case 1:
        
        case 2:
        
        case 3:
        
        case 4:
        
        case 5:
        
        case 6:
        
        case 7:
        
        case 8:
        
        case 9:
        
        case 10:
        
        case 11:
        
        case 12:
        
        case 13:
        
        case 14:
        
        case 15:
        
        case 16:
        
        case 17:
        
        case 18:
        
        case 19:
        
        case 20:
        
        case 21:
        
        case 22:
        
        case 23:
        
        case 24:
        
        case 25:
        
        case 26:
        
        case 27:
        
        case 28:
        
        case 29:
        
        case 30:
        
        case 31:
        
        case 32:
        
        case 33:
        
        case 34:
        
        case 35:
        
        case 36:
        
        case 37:
        
        case 38:
        
        case 39:
        
        case 40:
        
        case 41:
        
        case 42:
        
        case 43:
        
        case 44:
        
        case 45:
        
        case 46:
        
        case 47:
        
        case 48:
        
        case 49:
        
        case 50:
        
        case 51:
        
        case 52:
        
        case 53:
        
        case 54:
        
        case 55:
        
        case 56:
        
        case 57:
        
        case 58:
        
        case 59:
        
        case 60:
        
        case 61:
        
        case 62:
        
        case 63:
        
        case 64:
        
        case 65:
        
        case 66:
        
        case 67:
        
        case 68:
        
        case 69:
        
        case 70:
        
        case 71:
        
        case 72:
        
        case 73:
        
        case 74:
        
        case 75:
        
        case 76:
        
        case 77:
        
        case 78:
        
        case 79:
        
        case 80:
        
        case 81:
        
        case 82:
        
        case 83:
        
        case 84:
        
        case 85:
        
        case 86:
        
        case 87:
        
        case 88:
        
        case 89:
        
        case 90:
        
        case 91:
        
        case 92:
        
        case 93:
        
        case 94:
        
        case 95:
        
        case 96:
        
        case 97:
        
        case 98:
        
        case 99:
        
        case 100:
        
        case 101:
        
        case 102:
        
        case 103:
        
        case 104:
        
        case 105:
        
        case 106:
        
        case 107:
        
        case 108:
        
        case 109:
        
        case 110:
        
        case 111:
        
        case 112:
        
        case 113:
        
        case 114:
        
        case 115:
        
        case 116:
        
        case 117:
        
        case 118:
        
        case 119:
        
        case 120:
        
        case 121:
        
        case 122:
        
        case 123:
        
        case 124:
        
        case 125:
        
        case 126:
        
        case 127:
        
        case 128:
        
        case 129:
        
        case 130:
        
        case 131:
        
        case 132:
        
        case 133:
        
        case 134:
        
        case 135:
        
        case 136:
        
        case 137:
        
        case 138:
        
        case 139:
        
        case 140:
        
        case 141:
        
        case 142:
        
        case 143:
        
        case 144:
        
        case 145:
        
        case 146:
        
        case 147:
        
        case 148:
        
        case 149:
        
        case 150:
        
        case 151:
        
        case 152:
        
        case 153:
        
        case 154:
        
        case 155:
        
        case 156:
        
        case 157:
        
        case 158:
        
        case 159:
        
        case 160:
        
        case 161:
        
        case 162:
        
        case 163:
        
        case 164:
        
        case 165:
        
        case 166:
        
        case 167:
        
        case 168:
        
        case 169:
        
        case 170:
        
        case 171:
        
        case 172:
        
        case 173:
        
        case 174:
        
        case 175:
        
        case 176:
        
        case 177:
        
        case 178:
        
        case 179:
        
        case 180:
        
        case 181:
        
        case 182:
        
        case 183:
        
        case 184:
        
        case 185:
        
        case 186:
        
        case 187:
        
        case 188:
        
        case 189:
        
        case 190:
        
        case 191:
        
        case 192:
        
        case 193:
        
        case 194:
        
        case 195:
        
        case 196:
        
        case 197:
        
        case 198:
        
        case 199:
        
        case 200:
        
        case 201:
        
        case 202:
        
        case 203:
        
        case 204:
        
        case 205:
        
        case 206:
        
        case 207:
        
        case 208:
        
        case 209:
        
        case 210:
        
        case 211:
        
        case 212:
        
        case 213:
        
        case 214:
        
        case 215:
        
        case 216:
        
        case 217:
        
        case 218:
        
        case 219:
        
        case 220:
        
        case 221:
        
        case 222:
        
        case 223:
        
        case 224:
        
        case 225:
        
        case 226:
        
        case 227:
        
        case 228:
        
        case 229:
        
        case 230:
        
        case 231:
        
        case 232:
        
        case 233:
        
        case 234:
        
        case 235:
        
        case 236:
        
        case 237:
        
        case 238:
        
        case 239:
        
        case 240:
        
        case 241:
        
        case 242:
        
        case 243:
        
        case 244:
        
        case 245:
        
        case 246:
        
        case 247:
        
        case 248:
        
        case 249:
        
        case 250:
        
        case 251:
        
        case 252:
        
        case 253:
        
        case 254:
        
        default:
          break;
      } 
      char c = '';
      int j = (paramInt2 & 0xFF) - c;
      if (j < 0)
        j += 256; 
      int k = ((paramInt2 & 0xFFFF) >>> 8) - c;
      if (k < 0)
        k += 256; 
      for (byte b = 0; b < arrayOfChar.length; b++) {
        int m = b % 2;
        if (m == 0) {
          arrayOfChar[b] = (char)(arrayOfChar[b] ^ j);
          j = ((j >>> 3 | j << 5) ^ arrayOfChar[b]) & 0xFF;
        } else {
          arrayOfChar[b] = (char)(arrayOfChar[b] ^ k);
          k = ((k >>> 3 | k << 5) ^ arrayOfChar[b]) & 0xFF;
        } 
      } 
      b[i] = (new String(arrayOfChar)).intern();
    } 
    return b[i];
  }
}


/* Location:              C:\Program Files\BurpSuitePro\burpsuite_pro.jar!\burp\Zkku.class
 * Java compiler version: 21 (65.0)
 * JD-Core Version:       1.1.3
 */