package burp;

import java.math.BigInteger;

class Zkm0 extends ClassLoader {
  static Object ZI;
  
  static String ZL;
  
  private static final String[] a;
  
  private static final String[] b;
  
  static boolean Zs(Object[] paramArrayOfObject, Object paramObject) throws Throwable {
    // Byte code:
    //   0: invokestatic ZN : ()Z
    //   3: istore_2
    //   4: getstatic burp/Zm3p.Zz : Ljava/lang/Object;
    //   7: checkcast java/math/BigInteger
    //   10: getstatic burp/Ze8m.Zm : Ljava/lang/Object;
    //   13: checkcast java/math/BigInteger
    //   16: invokevirtual subtract : (Ljava/math/BigInteger;)Ljava/math/BigInteger;
    //   19: putstatic burp/Zz2e.Zm : Ljava/lang/Object;
    //   22: new java/lang/StringBuilder
    //   25: dup
    //   26: invokespecial <init> : ()V
    //   29: astore_3
    //   30: iconst_0
    //   31: istore #4
    //   33: iload #4
    //   35: bipush #32
    //   37: if_icmpge -> 1371
    //   40: iload #4
    //   42: tableswitch default -> 1364, 0 -> 184, 1 -> 221, 2 -> 258, 3 -> 295, 4 -> 332, 5 -> 369, 6 -> 406, 7 -> 443, 8 -> 480, 9 -> 517, 10 -> 554, 11 -> 591, 12 -> 628, 13 -> 665, 14 -> 702, 15 -> 739, 16 -> 776, 17 -> 813, 18 -> 850, 19 -> 887, 20 -> 924, 21 -> 961, 22 -> 998, 23 -> 1035, 24 -> 1072, 25 -> 1109, 26 -> 1146, 27 -> 1183, 28 -> 1220, 29 -> 1257, 30 -> 1294, 31 -> 1331
    //   184: aload_3
    //   185: getstatic burp/Zr2i.Z_ : Ljava/lang/String;
    //   188: getstatic burp/Ze6d.Zw : Ljava/lang/Object;
    //   191: checkcast java/math/BigInteger
    //   194: invokevirtual intValue : ()I
    //   197: bipush #32
    //   199: irem
    //   200: invokestatic abs : (I)I
    //   203: invokevirtual charAt : (I)C
    //   206: invokevirtual append : (C)Ljava/lang/StringBuilder;
    //   209: pop
    //   210: iload_2
    //   211: ifne -> 1364
    //   214: goto -> 221
    //   217: invokestatic a : (Ljava/lang/Throwable;)Ljava/lang/Throwable;
    //   220: athrow
    //   221: aload_3
    //   222: getstatic burp/Zs0_.ZH : Ljava/lang/String;
    //   225: getstatic burp/Zk7f.Za : Ljava/lang/Object;
    //   228: checkcast java/math/BigInteger
    //   231: invokevirtual intValue : ()I
    //   234: bipush #32
    //   236: irem
    //   237: invokestatic abs : (I)I
    //   240: invokevirtual charAt : (I)C
    //   243: invokevirtual append : (C)Ljava/lang/StringBuilder;
    //   246: pop
    //   247: iload_2
    //   248: ifne -> 1364
    //   251: goto -> 258
    //   254: invokestatic a : (Ljava/lang/Throwable;)Ljava/lang/Throwable;
    //   257: athrow
    //   258: aload_3
    //   259: getstatic burp/Zsbt.ZX : Ljava/lang/String;
    //   262: getstatic burp/Zsbt.Zl : Ljava/lang/Object;
    //   265: checkcast java/math/BigInteger
    //   268: invokevirtual intValue : ()I
    //   271: bipush #32
    //   273: irem
    //   274: invokestatic abs : (I)I
    //   277: invokevirtual charAt : (I)C
    //   280: invokevirtual append : (C)Ljava/lang/StringBuilder;
    //   283: pop
    //   284: iload_2
    //   285: ifne -> 1364
    //   288: goto -> 295
    //   291: invokestatic a : (Ljava/lang/Throwable;)Ljava/lang/Throwable;
    //   294: athrow
    //   295: aload_3
    //   296: getstatic burp/Zztn.ZY : Ljava/lang/String;
    //   299: getstatic burp/Zs0_.Zu : Ljava/lang/Object;
    //   302: checkcast java/math/BigInteger
    //   305: invokevirtual intValue : ()I
    //   308: bipush #32
    //   310: irem
    //   311: invokestatic abs : (I)I
    //   314: invokevirtual charAt : (I)C
    //   317: invokevirtual append : (C)Ljava/lang/StringBuilder;
    //   320: pop
    //   321: iload_2
    //   322: ifne -> 1364
    //   325: goto -> 332
    //   328: invokestatic a : (Ljava/lang/Throwable;)Ljava/lang/Throwable;
    //   331: athrow
    //   332: aload_3
    //   333: getstatic burp/Zsqy.Zo : Ljava/lang/String;
    //   336: getstatic burp/Zt3f.Zp : Ljava/lang/Object;
    //   339: checkcast java/math/BigInteger
    //   342: invokevirtual intValue : ()I
    //   345: bipush #32
    //   347: irem
    //   348: invokestatic abs : (I)I
    //   351: invokevirtual charAt : (I)C
    //   354: invokevirtual append : (C)Ljava/lang/StringBuilder;
    //   357: pop
    //   358: iload_2
    //   359: ifne -> 1364
    //   362: goto -> 369
    //   365: invokestatic a : (Ljava/lang/Throwable;)Ljava/lang/Throwable;
    //   368: athrow
    //   369: aload_3
    //   370: getstatic burp/Ztye.ZR : Ljava/lang/String;
    //   373: getstatic burp/Zex.ZO : Ljava/lang/Object;
    //   376: checkcast java/math/BigInteger
    //   379: invokevirtual intValue : ()I
    //   382: bipush #32
    //   384: irem
    //   385: invokestatic abs : (I)I
    //   388: invokevirtual charAt : (I)C
    //   391: invokevirtual append : (C)Ljava/lang/StringBuilder;
    //   394: pop
    //   395: iload_2
    //   396: ifne -> 1364
    //   399: goto -> 406
    //   402: invokestatic a : (Ljava/lang/Throwable;)Ljava/lang/Throwable;
    //   405: athrow
    //   406: aload_3
    //   407: getstatic burp/Zlx5.ZP : Ljava/lang/String;
    //   410: getstatic burp/Zram.ZF : Ljava/lang/Object;
    //   413: checkcast java/math/BigInteger
    //   416: invokevirtual intValue : ()I
    //   419: bipush #32
    //   421: irem
    //   422: invokestatic abs : (I)I
    //   425: invokevirtual charAt : (I)C
    //   428: invokevirtual append : (C)Ljava/lang/StringBuilder;
    //   431: pop
    //   432: iload_2
    //   433: ifne -> 1364
    //   436: goto -> 443
    //   439: invokestatic a : (Ljava/lang/Throwable;)Ljava/lang/Throwable;
    //   442: athrow
    //   443: aload_3
    //   444: getstatic burp/Zkc8.Za : Ljava/lang/String;
    //   447: getstatic burp/Zg4d.Zm : Ljava/lang/Object;
    //   450: checkcast java/math/BigInteger
    //   453: invokevirtual intValue : ()I
    //   456: bipush #32
    //   458: irem
    //   459: invokestatic abs : (I)I
    //   462: invokevirtual charAt : (I)C
    //   465: invokevirtual append : (C)Ljava/lang/StringBuilder;
    //   468: pop
    //   469: iload_2
    //   470: ifne -> 1364
    //   473: goto -> 480
    //   476: invokestatic a : (Ljava/lang/Throwable;)Ljava/lang/Throwable;
    //   479: athrow
    //   480: aload_3
    //   481: getstatic burp/Zlf0.ZS : Ljava/lang/String;
    //   484: getstatic burp/Zrhp.Zw : Ljava/lang/Object;
    //   487: checkcast java/math/BigInteger
    //   490: invokevirtual intValue : ()I
    //   493: bipush #32
    //   495: irem
    //   496: invokestatic abs : (I)I
    //   499: invokevirtual charAt : (I)C
    //   502: invokevirtual append : (C)Ljava/lang/StringBuilder;
    //   505: pop
    //   506: iload_2
    //   507: ifne -> 1364
    //   510: goto -> 517
    //   513: invokestatic a : (Ljava/lang/Throwable;)Ljava/lang/Throwable;
    //   516: athrow
    //   517: aload_3
    //   518: getstatic burp/Zs0_.ZH : Ljava/lang/String;
    //   521: getstatic burp/Zxn5.Zd : Ljava/lang/Object;
    //   524: checkcast java/math/BigInteger
    //   527: invokevirtual intValue : ()I
    //   530: bipush #32
    //   532: irem
    //   533: invokestatic abs : (I)I
    //   536: invokevirtual charAt : (I)C
    //   539: invokevirtual append : (C)Ljava/lang/StringBuilder;
    //   542: pop
    //   543: iload_2
    //   544: ifne -> 1364
    //   547: goto -> 554
    //   550: invokestatic a : (Ljava/lang/Throwable;)Ljava/lang/Throwable;
    //   553: athrow
    //   554: aload_3
    //   555: getstatic burp/Zb8y.Zn : Ljava/lang/String;
    //   558: getstatic burp/Zz6t.ZA : Ljava/lang/Object;
    //   561: checkcast java/math/BigInteger
    //   564: invokevirtual intValue : ()I
    //   567: bipush #32
    //   569: irem
    //   570: invokestatic abs : (I)I
    //   573: invokevirtual charAt : (I)C
    //   576: invokevirtual append : (C)Ljava/lang/StringBuilder;
    //   579: pop
    //   580: iload_2
    //   581: ifne -> 1364
    //   584: goto -> 591
    //   587: invokestatic a : (Ljava/lang/Throwable;)Ljava/lang/Throwable;
    //   590: athrow
    //   591: aload_3
    //   592: getstatic burp/Zg_5.ZG : Ljava/lang/String;
    //   595: getstatic burp/Zxn5.Zd : Ljava/lang/Object;
    //   598: checkcast java/math/BigInteger
    //   601: invokevirtual intValue : ()I
    //   604: bipush #32
    //   606: irem
    //   607: invokestatic abs : (I)I
    //   610: invokevirtual charAt : (I)C
    //   613: invokevirtual append : (C)Ljava/lang/StringBuilder;
    //   616: pop
    //   617: iload_2
    //   618: ifne -> 1364
    //   621: goto -> 628
    //   624: invokestatic a : (Ljava/lang/Throwable;)Ljava/lang/Throwable;
    //   627: athrow
    //   628: aload_3
    //   629: getstatic burp/Zram.Ze : Ljava/lang/String;
    //   632: getstatic burp/Zg6f.Zl : Ljava/lang/Object;
    //   635: checkcast java/math/BigInteger
    //   638: invokevirtual intValue : ()I
    //   641: bipush #32
    //   643: irem
    //   644: invokestatic abs : (I)I
    //   647: invokevirtual charAt : (I)C
    //   650: invokevirtual append : (C)Ljava/lang/StringBuilder;
    //   653: pop
    //   654: iload_2
    //   655: ifne -> 1364
    //   658: goto -> 665
    //   661: invokestatic a : (Ljava/lang/Throwable;)Ljava/lang/Throwable;
    //   664: athrow
    //   665: aload_3
    //   666: getstatic burp/Ztj5.Zt : Ljava/lang/String;
    //   669: getstatic burp/Zm6h.ZB : Ljava/lang/Object;
    //   672: checkcast java/math/BigInteger
    //   675: invokevirtual intValue : ()I
    //   678: bipush #32
    //   680: irem
    //   681: invokestatic abs : (I)I
    //   684: invokevirtual charAt : (I)C
    //   687: invokevirtual append : (C)Ljava/lang/StringBuilder;
    //   690: pop
    //   691: iload_2
    //   692: ifne -> 1364
    //   695: goto -> 702
    //   698: invokestatic a : (Ljava/lang/Throwable;)Ljava/lang/Throwable;
    //   701: athrow
    //   702: aload_3
    //   703: getstatic burp/Zk12.Zu : Ljava/lang/String;
    //   706: getstatic burp/Zli5.Zt : Ljava/lang/Object;
    //   709: checkcast java/math/BigInteger
    //   712: invokevirtual intValue : ()I
    //   715: bipush #32
    //   717: irem
    //   718: invokestatic abs : (I)I
    //   721: invokevirtual charAt : (I)C
    //   724: invokevirtual append : (C)Ljava/lang/StringBuilder;
    //   727: pop
    //   728: iload_2
    //   729: ifne -> 1364
    //   732: goto -> 739
    //   735: invokestatic a : (Ljava/lang/Throwable;)Ljava/lang/Throwable;
    //   738: athrow
    //   739: aload_3
    //   740: getstatic burp/Zzo5.ZX : Ljava/lang/String;
    //   743: getstatic burp/Ze64.ZW : Ljava/lang/Object;
    //   746: checkcast java/math/BigInteger
    //   749: invokevirtual intValue : ()I
    //   752: bipush #32
    //   754: irem
    //   755: invokestatic abs : (I)I
    //   758: invokevirtual charAt : (I)C
    //   761: invokevirtual append : (C)Ljava/lang/StringBuilder;
    //   764: pop
    //   765: iload_2
    //   766: ifne -> 1364
    //   769: goto -> 776
    //   772: invokestatic a : (Ljava/lang/Throwable;)Ljava/lang/Throwable;
    //   775: athrow
    //   776: aload_3
    //   777: getstatic burp/Ze_t.ZZ : Ljava/lang/String;
    //   780: getstatic burp/Zs_v.Zs : Ljava/lang/Object;
    //   783: checkcast java/math/BigInteger
    //   786: invokevirtual intValue : ()I
    //   789: bipush #32
    //   791: irem
    //   792: invokestatic abs : (I)I
    //   795: invokevirtual charAt : (I)C
    //   798: invokevirtual append : (C)Ljava/lang/StringBuilder;
    //   801: pop
    //   802: iload_2
    //   803: ifne -> 1364
    //   806: goto -> 813
    //   809: invokestatic a : (Ljava/lang/Throwable;)Ljava/lang/Throwable;
    //   812: athrow
    //   813: aload_3
    //   814: getstatic burp/Ztsu.ZE : Ljava/lang/String;
    //   817: getstatic burp/Zs2n.ZK : Ljava/lang/Object;
    //   820: checkcast java/math/BigInteger
    //   823: invokevirtual intValue : ()I
    //   826: bipush #32
    //   828: irem
    //   829: invokestatic abs : (I)I
    //   832: invokevirtual charAt : (I)C
    //   835: invokevirtual append : (C)Ljava/lang/StringBuilder;
    //   838: pop
    //   839: iload_2
    //   840: ifne -> 1364
    //   843: goto -> 850
    //   846: invokestatic a : (Ljava/lang/Throwable;)Ljava/lang/Throwable;
    //   849: athrow
    //   850: aload_3
    //   851: getstatic burp/Zess.Zc : Ljava/lang/String;
    //   854: getstatic burp/Zs83.ZT : Ljava/lang/Object;
    //   857: checkcast java/math/BigInteger
    //   860: invokevirtual intValue : ()I
    //   863: bipush #32
    //   865: irem
    //   866: invokestatic abs : (I)I
    //   869: invokevirtual charAt : (I)C
    //   872: invokevirtual append : (C)Ljava/lang/StringBuilder;
    //   875: pop
    //   876: iload_2
    //   877: ifne -> 1364
    //   880: goto -> 887
    //   883: invokestatic a : (Ljava/lang/Throwable;)Ljava/lang/Throwable;
    //   886: athrow
    //   887: aload_3
    //   888: getstatic burp/Zef0.ZR : Ljava/lang/String;
    //   891: getstatic burp/Zxg7.Zy : Ljava/lang/Object;
    //   894: checkcast java/math/BigInteger
    //   897: invokevirtual intValue : ()I
    //   900: bipush #32
    //   902: irem
    //   903: invokestatic abs : (I)I
    //   906: invokevirtual charAt : (I)C
    //   909: invokevirtual append : (C)Ljava/lang/StringBuilder;
    //   912: pop
    //   913: iload_2
    //   914: ifne -> 1364
    //   917: goto -> 924
    //   920: invokestatic a : (Ljava/lang/Throwable;)Ljava/lang/Throwable;
    //   923: athrow
    //   924: aload_3
    //   925: getstatic burp/Zgva.ZV : Ljava/lang/String;
    //   928: getstatic burp/Zel.ZB : Ljava/lang/Object;
    //   931: checkcast java/math/BigInteger
    //   934: invokevirtual intValue : ()I
    //   937: bipush #32
    //   939: irem
    //   940: invokestatic abs : (I)I
    //   943: invokevirtual charAt : (I)C
    //   946: invokevirtual append : (C)Ljava/lang/StringBuilder;
    //   949: pop
    //   950: iload_2
    //   951: ifne -> 1364
    //   954: goto -> 961
    //   957: invokestatic a : (Ljava/lang/Throwable;)Ljava/lang/Throwable;
    //   960: athrow
    //   961: aload_3
    //   962: getstatic burp/Zkll.ZX : Ljava/lang/String;
    //   965: getstatic burp/Zmyg.Zj : Ljava/lang/Object;
    //   968: checkcast java/math/BigInteger
    //   971: invokevirtual intValue : ()I
    //   974: bipush #32
    //   976: irem
    //   977: invokestatic abs : (I)I
    //   980: invokevirtual charAt : (I)C
    //   983: invokevirtual append : (C)Ljava/lang/StringBuilder;
    //   986: pop
    //   987: iload_2
    //   988: ifne -> 1364
    //   991: goto -> 998
    //   994: invokestatic a : (Ljava/lang/Throwable;)Ljava/lang/Throwable;
    //   997: athrow
    //   998: aload_3
    //   999: getstatic burp/Zb8y.Zn : Ljava/lang/String;
    //   1002: getstatic burp/Zxzz.ZM : Ljava/lang/Object;
    //   1005: checkcast java/math/BigInteger
    //   1008: invokevirtual intValue : ()I
    //   1011: bipush #32
    //   1013: irem
    //   1014: invokestatic abs : (I)I
    //   1017: invokevirtual charAt : (I)C
    //   1020: invokevirtual append : (C)Ljava/lang/StringBuilder;
    //   1023: pop
    //   1024: iload_2
    //   1025: ifne -> 1364
    //   1028: goto -> 1035
    //   1031: invokestatic a : (Ljava/lang/Throwable;)Ljava/lang/Throwable;
    //   1034: athrow
    //   1035: aload_3
    //   1036: getstatic burp/Ze5t.ZX : Ljava/lang/String;
    //   1039: getstatic burp/Ze_t.Za : Ljava/lang/Object;
    //   1042: checkcast java/math/BigInteger
    //   1045: invokevirtual intValue : ()I
    //   1048: bipush #32
    //   1050: irem
    //   1051: invokestatic abs : (I)I
    //   1054: invokevirtual charAt : (I)C
    //   1057: invokevirtual append : (C)Ljava/lang/StringBuilder;
    //   1060: pop
    //   1061: iload_2
    //   1062: ifne -> 1364
    //   1065: goto -> 1072
    //   1068: invokestatic a : (Ljava/lang/Throwable;)Ljava/lang/Throwable;
    //   1071: athrow
    //   1072: aload_3
    //   1073: getstatic burp/Ze64.ZM : Ljava/lang/String;
    //   1076: getstatic burp/Zm7x.Zv : Ljava/lang/Object;
    //   1079: checkcast java/math/BigInteger
    //   1082: invokevirtual intValue : ()I
    //   1085: bipush #32
    //   1087: irem
    //   1088: invokestatic abs : (I)I
    //   1091: invokevirtual charAt : (I)C
    //   1094: invokevirtual append : (C)Ljava/lang/StringBuilder;
    //   1097: pop
    //   1098: iload_2
    //   1099: ifne -> 1364
    //   1102: goto -> 1109
    //   1105: invokestatic a : (Ljava/lang/Throwable;)Ljava/lang/Throwable;
    //   1108: athrow
    //   1109: aload_3
    //   1110: getstatic burp/Zgq_.ZQ : Ljava/lang/String;
    //   1113: getstatic burp/Zt0t.ZL : Ljava/lang/Object;
    //   1116: checkcast java/math/BigInteger
    //   1119: invokevirtual intValue : ()I
    //   1122: bipush #32
    //   1124: irem
    //   1125: invokestatic abs : (I)I
    //   1128: invokevirtual charAt : (I)C
    //   1131: invokevirtual append : (C)Ljava/lang/StringBuilder;
    //   1134: pop
    //   1135: iload_2
    //   1136: ifne -> 1364
    //   1139: goto -> 1146
    //   1142: invokestatic a : (Ljava/lang/Throwable;)Ljava/lang/Throwable;
    //   1145: athrow
    //   1146: aload_3
    //   1147: getstatic burp/Zb8y.Zn : Ljava/lang/String;
    //   1150: getstatic burp/Zztn.ZO : Ljava/lang/Object;
    //   1153: checkcast java/math/BigInteger
    //   1156: invokevirtual intValue : ()I
    //   1159: bipush #32
    //   1161: irem
    //   1162: invokestatic abs : (I)I
    //   1165: invokevirtual charAt : (I)C
    //   1168: invokevirtual append : (C)Ljava/lang/StringBuilder;
    //   1171: pop
    //   1172: iload_2
    //   1173: ifne -> 1364
    //   1176: goto -> 1183
    //   1179: invokestatic a : (Ljava/lang/Throwable;)Ljava/lang/Throwable;
    //   1182: athrow
    //   1183: aload_3
    //   1184: getstatic burp/Zram.Ze : Ljava/lang/String;
    //   1187: getstatic burp/Zzmu.Zy : Ljava/lang/Object;
    //   1190: checkcast java/math/BigInteger
    //   1193: invokevirtual intValue : ()I
    //   1196: bipush #32
    //   1198: irem
    //   1199: invokestatic abs : (I)I
    //   1202: invokevirtual charAt : (I)C
    //   1205: invokevirtual append : (C)Ljava/lang/StringBuilder;
    //   1208: pop
    //   1209: iload_2
    //   1210: ifne -> 1364
    //   1213: goto -> 1220
    //   1216: invokestatic a : (Ljava/lang/Throwable;)Ljava/lang/Throwable;
    //   1219: athrow
    //   1220: aload_3
    //   1221: getstatic burp/Zgqi.Zv : Ljava/lang/String;
    //   1224: getstatic burp/Zix.ZO : Ljava/lang/Object;
    //   1227: checkcast java/math/BigInteger
    //   1230: invokevirtual intValue : ()I
    //   1233: bipush #32
    //   1235: irem
    //   1236: invokestatic abs : (I)I
    //   1239: invokevirtual charAt : (I)C
    //   1242: invokevirtual append : (C)Ljava/lang/StringBuilder;
    //   1245: pop
    //   1246: iload_2
    //   1247: ifne -> 1364
    //   1250: goto -> 1257
    //   1253: invokestatic a : (Ljava/lang/Throwable;)Ljava/lang/Throwable;
    //   1256: athrow
    //   1257: aload_3
    //   1258: getstatic burp/Zlem.Zl : Ljava/lang/String;
    //   1261: getstatic burp/Zlem.ZI : Ljava/lang/Object;
    //   1264: checkcast java/math/BigInteger
    //   1267: invokevirtual intValue : ()I
    //   1270: bipush #32
    //   1272: irem
    //   1273: invokestatic abs : (I)I
    //   1276: invokevirtual charAt : (I)C
    //   1279: invokevirtual append : (C)Ljava/lang/StringBuilder;
    //   1282: pop
    //   1283: iload_2
    //   1284: ifne -> 1364
    //   1287: goto -> 1294
    //   1290: invokestatic a : (Ljava/lang/Throwable;)Ljava/lang/Throwable;
    //   1293: athrow
    //   1294: aload_3
    //   1295: getstatic burp/Ztj5.Zt : Ljava/lang/String;
    //   1298: getstatic burp/Zx6d.ZU : Ljava/lang/Object;
    //   1301: checkcast java/math/BigInteger
    //   1304: invokevirtual intValue : ()I
    //   1307: bipush #32
    //   1309: irem
    //   1310: invokestatic abs : (I)I
    //   1313: invokevirtual charAt : (I)C
    //   1316: invokevirtual append : (C)Ljava/lang/StringBuilder;
    //   1319: pop
    //   1320: iload_2
    //   1321: ifne -> 1364
    //   1324: goto -> 1331
    //   1327: invokestatic a : (Ljava/lang/Throwable;)Ljava/lang/Throwable;
    //   1330: athrow
    //   1331: aload_3
    //   1332: getstatic burp/Zsbt.ZX : Ljava/lang/String;
    //   1335: getstatic burp/Zbzk.ZI : Ljava/lang/Object;
    //   1338: checkcast java/math/BigInteger
    //   1341: invokevirtual intValue : ()I
    //   1344: bipush #32
    //   1346: irem
    //   1347: invokestatic abs : (I)I
    //   1350: invokevirtual charAt : (I)C
    //   1353: invokevirtual append : (C)Ljava/lang/StringBuilder;
    //   1356: pop
    //   1357: goto -> 1364
    //   1360: invokestatic a : (Ljava/lang/Throwable;)Ljava/lang/Throwable;
    //   1363: athrow
    //   1364: iinc #4, 1
    //   1367: iload_2
    //   1368: ifne -> 33
    //   1371: aload_3
    //   1372: invokevirtual toString : ()Ljava/lang/String;
    //   1375: putstatic burp/Zlx5.ZP : Ljava/lang/String;
    //   1378: getstatic burp/Zlf0.ZC : Ljava/lang/Object;
    //   1381: checkcast java/math/BigInteger
    //   1384: invokevirtual toByteArray : ()[B
    //   1387: astore #4
    //   1389: iconst_0
    //   1390: istore #6
    //   1392: iconst_0
    //   1393: istore #7
    //   1395: iload #7
    //   1397: aload #4
    //   1399: arraylength
    //   1400: if_icmpge -> 1546
    //   1403: aload #4
    //   1405: iload #7
    //   1407: baload
    //   1408: istore #8
    //   1410: iload #8
    //   1412: bipush #48
    //   1414: if_icmplt -> 1431
    //   1417: iload #8
    //   1419: bipush #57
    //   1421: if_icmple -> 1529
    //   1424: goto -> 1431
    //   1427: invokestatic a : (Ljava/lang/Throwable;)Ljava/lang/Throwable;
    //   1430: athrow
    //   1431: iload #8
    //   1433: bipush #65
    //   1435: if_icmplt -> 1459
    //   1438: goto -> 1445
    //   1441: invokestatic a : (Ljava/lang/Throwable;)Ljava/lang/Throwable;
    //   1444: athrow
    //   1445: iload #8
    //   1447: bipush #90
    //   1449: if_icmple -> 1529
    //   1452: goto -> 1459
    //   1455: invokestatic a : (Ljava/lang/Throwable;)Ljava/lang/Throwable;
    //   1458: athrow
    //   1459: iload #8
    //   1461: bipush #97
    //   1463: if_icmplt -> 1487
    //   1466: goto -> 1473
    //   1469: invokestatic a : (Ljava/lang/Throwable;)Ljava/lang/Throwable;
    //   1472: athrow
    //   1473: iload #8
    //   1475: bipush #122
    //   1477: if_icmple -> 1529
    //   1480: goto -> 1487
    //   1483: invokestatic a : (Ljava/lang/Throwable;)Ljava/lang/Throwable;
    //   1486: athrow
    //   1487: iload #8
    //   1489: bipush #43
    //   1491: if_icmpeq -> 1529
    //   1494: goto -> 1501
    //   1497: invokestatic a : (Ljava/lang/Throwable;)Ljava/lang/Throwable;
    //   1500: athrow
    //   1501: iload #8
    //   1503: bipush #47
    //   1505: if_icmpeq -> 1529
    //   1508: goto -> 1515
    //   1511: invokestatic a : (Ljava/lang/Throwable;)Ljava/lang/Throwable;
    //   1514: athrow
    //   1515: iload #8
    //   1517: bipush #61
    //   1519: if_icmpne -> 1539
    //   1522: goto -> 1529
    //   1525: invokestatic a : (Ljava/lang/Throwable;)Ljava/lang/Throwable;
    //   1528: athrow
    //   1529: iinc #6, 1
    //   1532: goto -> 1539
    //   1535: invokestatic a : (Ljava/lang/Throwable;)Ljava/lang/Throwable;
    //   1538: athrow
    //   1539: iinc #7, 1
    //   1542: iload_2
    //   1543: ifne -> 1395
    //   1546: iload #6
    //   1548: newarray byte
    //   1550: astore #7
    //   1552: iconst_0
    //   1553: istore #8
    //   1555: iconst_0
    //   1556: istore #9
    //   1558: iload #9
    //   1560: aload #4
    //   1562: arraylength
    //   1563: if_icmpge -> 1716
    //   1566: aload #4
    //   1568: iload #9
    //   1570: baload
    //   1571: istore #10
    //   1573: iload #10
    //   1575: bipush #48
    //   1577: if_icmplt -> 1594
    //   1580: iload #10
    //   1582: bipush #57
    //   1584: if_icmple -> 1692
    //   1587: goto -> 1594
    //   1590: invokestatic a : (Ljava/lang/Throwable;)Ljava/lang/Throwable;
    //   1593: athrow
    //   1594: iload #10
    //   1596: bipush #65
    //   1598: if_icmplt -> 1622
    //   1601: goto -> 1608
    //   1604: invokestatic a : (Ljava/lang/Throwable;)Ljava/lang/Throwable;
    //   1607: athrow
    //   1608: iload #10
    //   1610: bipush #90
    //   1612: if_icmple -> 1692
    //   1615: goto -> 1622
    //   1618: invokestatic a : (Ljava/lang/Throwable;)Ljava/lang/Throwable;
    //   1621: athrow
    //   1622: iload #10
    //   1624: bipush #97
    //   1626: if_icmplt -> 1650
    //   1629: goto -> 1636
    //   1632: invokestatic a : (Ljava/lang/Throwable;)Ljava/lang/Throwable;
    //   1635: athrow
    //   1636: iload #10
    //   1638: bipush #122
    //   1640: if_icmple -> 1692
    //   1643: goto -> 1650
    //   1646: invokestatic a : (Ljava/lang/Throwable;)Ljava/lang/Throwable;
    //   1649: athrow
    //   1650: iload #10
    //   1652: bipush #43
    //   1654: if_icmpeq -> 1692
    //   1657: goto -> 1664
    //   1660: invokestatic a : (Ljava/lang/Throwable;)Ljava/lang/Throwable;
    //   1663: athrow
    //   1664: iload #10
    //   1666: bipush #47
    //   1668: if_icmpeq -> 1692
    //   1671: goto -> 1678
    //   1674: invokestatic a : (Ljava/lang/Throwable;)Ljava/lang/Throwable;
    //   1677: athrow
    //   1678: iload #10
    //   1680: bipush #61
    //   1682: if_icmpne -> 1709
    //   1685: goto -> 1692
    //   1688: invokestatic a : (Ljava/lang/Throwable;)Ljava/lang/Throwable;
    //   1691: athrow
    //   1692: aload #7
    //   1694: iload #8
    //   1696: iload #10
    //   1698: bastore
    //   1699: iinc #8, 1
    //   1702: goto -> 1709
    //   1705: invokestatic a : (Ljava/lang/Throwable;)Ljava/lang/Throwable;
    //   1708: athrow
    //   1709: iinc #9, 1
    //   1712: iload_2
    //   1713: ifne -> 1558
    //   1716: aload #7
    //   1718: astore #5
    //   1720: aload #5
    //   1722: astore #4
    //   1724: aload #4
    //   1726: arraylength
    //   1727: istore #6
    //   1729: aload #4
    //   1731: iload #6
    //   1733: iconst_1
    //   1734: isub
    //   1735: baload
    //   1736: bipush #61
    //   1738: if_icmpne -> 1748
    //   1741: iinc #6, -1
    //   1744: iload_2
    //   1745: ifne -> 1729
    //   1748: iload #6
    //   1750: aload #4
    //   1752: arraylength
    //   1753: iconst_4
    //   1754: idiv
    //   1755: isub
    //   1756: newarray byte
    //   1758: astore #7
    //   1760: iconst_0
    //   1761: istore #8
    //   1763: iload #8
    //   1765: aload #4
    //   1767: arraylength
    //   1768: if_icmpge -> 2048
    //   1771: aload #4
    //   1773: iload #8
    //   1775: baload
    //   1776: bipush #61
    //   1778: if_icmpne -> 1798
    //   1781: aload #4
    //   1783: iload #8
    //   1785: iconst_0
    //   1786: bastore
    //   1787: iload_2
    //   1788: ifne -> 2041
    //   1791: goto -> 1798
    //   1794: invokestatic a : (Ljava/lang/Throwable;)Ljava/lang/Throwable;
    //   1797: athrow
    //   1798: aload #4
    //   1800: iload #8
    //   1802: baload
    //   1803: bipush #47
    //   1805: if_icmpne -> 1833
    //   1808: goto -> 1815
    //   1811: invokestatic a : (Ljava/lang/Throwable;)Ljava/lang/Throwable;
    //   1814: athrow
    //   1815: aload #4
    //   1817: iload #8
    //   1819: bipush #63
    //   1821: bastore
    //   1822: iload_2
    //   1823: ifne -> 2041
    //   1826: goto -> 1833
    //   1829: invokestatic a : (Ljava/lang/Throwable;)Ljava/lang/Throwable;
    //   1832: athrow
    //   1833: aload #4
    //   1835: iload #8
    //   1837: baload
    //   1838: bipush #43
    //   1840: if_icmpne -> 1868
    //   1843: goto -> 1850
    //   1846: invokestatic a : (Ljava/lang/Throwable;)Ljava/lang/Throwable;
    //   1849: athrow
    //   1850: aload #4
    //   1852: iload #8
    //   1854: bipush #62
    //   1856: bastore
    //   1857: iload_2
    //   1858: ifne -> 2041
    //   1861: goto -> 1868
    //   1864: invokestatic a : (Ljava/lang/Throwable;)Ljava/lang/Throwable;
    //   1867: athrow
    //   1868: aload #4
    //   1870: iload #8
    //   1872: baload
    //   1873: bipush #48
    //   1875: if_icmplt -> 1927
    //   1878: goto -> 1885
    //   1881: invokestatic a : (Ljava/lang/Throwable;)Ljava/lang/Throwable;
    //   1884: athrow
    //   1885: aload #4
    //   1887: iload #8
    //   1889: baload
    //   1890: bipush #57
    //   1892: if_icmpgt -> 1927
    //   1895: goto -> 1902
    //   1898: invokestatic a : (Ljava/lang/Throwable;)Ljava/lang/Throwable;
    //   1901: athrow
    //   1902: aload #4
    //   1904: iload #8
    //   1906: aload #4
    //   1908: iload #8
    //   1910: baload
    //   1911: bipush #-4
    //   1913: isub
    //   1914: i2b
    //   1915: bastore
    //   1916: iload_2
    //   1917: ifne -> 2041
    //   1920: goto -> 1927
    //   1923: invokestatic a : (Ljava/lang/Throwable;)Ljava/lang/Throwable;
    //   1926: athrow
    //   1927: aload #4
    //   1929: iload #8
    //   1931: baload
    //   1932: bipush #97
    //   1934: if_icmplt -> 1986
    //   1937: goto -> 1944
    //   1940: invokestatic a : (Ljava/lang/Throwable;)Ljava/lang/Throwable;
    //   1943: athrow
    //   1944: aload #4
    //   1946: iload #8
    //   1948: baload
    //   1949: bipush #122
    //   1951: if_icmpgt -> 1986
    //   1954: goto -> 1961
    //   1957: invokestatic a : (Ljava/lang/Throwable;)Ljava/lang/Throwable;
    //   1960: athrow
    //   1961: aload #4
    //   1963: iload #8
    //   1965: aload #4
    //   1967: iload #8
    //   1969: baload
    //   1970: bipush #71
    //   1972: isub
    //   1973: i2b
    //   1974: bastore
    //   1975: iload_2
    //   1976: ifne -> 2041
    //   1979: goto -> 1986
    //   1982: invokestatic a : (Ljava/lang/Throwable;)Ljava/lang/Throwable;
    //   1985: athrow
    //   1986: aload #4
    //   1988: iload #8
    //   1990: baload
    //   1991: bipush #65
    //   1993: if_icmplt -> 2041
    //   1996: goto -> 2003
    //   1999: invokestatic a : (Ljava/lang/Throwable;)Ljava/lang/Throwable;
    //   2002: athrow
    //   2003: aload #4
    //   2005: iload #8
    //   2007: baload
    //   2008: bipush #90
    //   2010: if_icmpgt -> 2041
    //   2013: goto -> 2020
    //   2016: invokestatic a : (Ljava/lang/Throwable;)Ljava/lang/Throwable;
    //   2019: athrow
    //   2020: aload #4
    //   2022: iload #8
    //   2024: aload #4
    //   2026: iload #8
    //   2028: baload
    //   2029: bipush #65
    //   2031: isub
    //   2032: i2b
    //   2033: bastore
    //   2034: goto -> 2041
    //   2037: invokestatic a : (Ljava/lang/Throwable;)Ljava/lang/Throwable;
    //   2040: athrow
    //   2041: iinc #8, 1
    //   2044: iload_2
    //   2045: ifne -> 1763
    //   2048: iconst_0
    //   2049: istore #8
    //   2051: iconst_0
    //   2052: istore #9
    //   2054: iload #9
    //   2056: aload #7
    //   2058: arraylength
    //   2059: iconst_2
    //   2060: isub
    //   2061: if_icmpge -> 2170
    //   2064: aload #7
    //   2066: iload #9
    //   2068: aload #4
    //   2070: iload #8
    //   2072: baload
    //   2073: iconst_2
    //   2074: ishl
    //   2075: sipush #255
    //   2078: iand
    //   2079: aload #4
    //   2081: iload #8
    //   2083: iconst_1
    //   2084: iadd
    //   2085: baload
    //   2086: iconst_4
    //   2087: iushr
    //   2088: iconst_3
    //   2089: iand
    //   2090: ior
    //   2091: i2b
    //   2092: bastore
    //   2093: aload #7
    //   2095: iload #9
    //   2097: iconst_1
    //   2098: iadd
    //   2099: aload #4
    //   2101: iload #8
    //   2103: iconst_1
    //   2104: iadd
    //   2105: baload
    //   2106: iconst_4
    //   2107: ishl
    //   2108: sipush #255
    //   2111: iand
    //   2112: aload #4
    //   2114: iload #8
    //   2116: iconst_2
    //   2117: iadd
    //   2118: baload
    //   2119: iconst_2
    //   2120: iushr
    //   2121: bipush #15
    //   2123: iand
    //   2124: ior
    //   2125: i2b
    //   2126: bastore
    //   2127: aload #7
    //   2129: iload #9
    //   2131: iconst_2
    //   2132: iadd
    //   2133: aload #4
    //   2135: iload #8
    //   2137: iconst_2
    //   2138: iadd
    //   2139: baload
    //   2140: bipush #6
    //   2142: ishl
    //   2143: sipush #255
    //   2146: iand
    //   2147: aload #4
    //   2149: iload #8
    //   2151: iconst_3
    //   2152: iadd
    //   2153: baload
    //   2154: bipush #63
    //   2156: iand
    //   2157: ior
    //   2158: i2b
    //   2159: bastore
    //   2160: iinc #8, 4
    //   2163: iinc #9, 3
    //   2166: iload_2
    //   2167: ifne -> 2054
    //   2170: iload #9
    //   2172: aload #7
    //   2174: arraylength
    //   2175: if_icmpge -> 2214
    //   2178: aload #7
    //   2180: iload #9
    //   2182: aload #4
    //   2184: iload #8
    //   2186: baload
    //   2187: iconst_2
    //   2188: ishl
    //   2189: sipush #255
    //   2192: iand
    //   2193: aload #4
    //   2195: iload #8
    //   2197: iconst_1
    //   2198: iadd
    //   2199: baload
    //   2200: iconst_4
    //   2201: iushr
    //   2202: iconst_3
    //   2203: iand
    //   2204: ior
    //   2205: i2b
    //   2206: bastore
    //   2207: goto -> 2214
    //   2210: invokestatic a : (Ljava/lang/Throwable;)Ljava/lang/Throwable;
    //   2213: athrow
    //   2214: iinc #9, 1
    //   2217: iload #9
    //   2219: aload #7
    //   2221: arraylength
    //   2222: if_icmpge -> 2264
    //   2225: aload #7
    //   2227: iload #9
    //   2229: aload #4
    //   2231: iload #8
    //   2233: iconst_1
    //   2234: iadd
    //   2235: baload
    //   2236: iconst_4
    //   2237: ishl
    //   2238: sipush #255
    //   2241: iand
    //   2242: aload #4
    //   2244: iload #8
    //   2246: iconst_2
    //   2247: iadd
    //   2248: baload
    //   2249: iconst_2
    //   2250: iushr
    //   2251: bipush #15
    //   2253: iand
    //   2254: ior
    //   2255: i2b
    //   2256: bastore
    //   2257: goto -> 2264
    //   2260: invokestatic a : (Ljava/lang/Throwable;)Ljava/lang/Throwable;
    //   2263: athrow
    //   2264: aload #7
    //   2266: astore #5
    //   2268: sipush #-16701
    //   2271: new java/math/BigInteger
    //   2274: dup
    //   2275: aload #5
    //   2277: invokespecial <init> : ([B)V
    //   2280: invokevirtual abs : ()Ljava/math/BigInteger;
    //   2283: putstatic burp/Zzoi.ZI : Ljava/lang/Object;
    //   2286: sipush #-8673
    //   2289: invokestatic a : (II)Ljava/lang/String;
    //   2292: iconst_1
    //   2293: ldc burp/Zmz
    //   2295: invokevirtual getClassLoader : ()Ljava/lang/ClassLoader;
    //   2298: invokestatic forName : (Ljava/lang/String;ZLjava/lang/ClassLoader;)Ljava/lang/Class;
    //   2301: invokevirtual getDeclaredFields : ()[Ljava/lang/reflect/Field;
    //   2304: astore #4
    //   2306: aload #4
    //   2308: arraylength
    //   2309: istore #5
    //   2311: iconst_0
    //   2312: istore #6
    //   2314: iload #6
    //   2316: iload #5
    //   2318: if_icmpge -> 2456
    //   2321: aload #4
    //   2323: iload #6
    //   2325: aaload
    //   2326: astore #7
    //   2328: aload #7
    //   2330: invokevirtual getModifiers : ()I
    //   2333: invokestatic isStatic : (I)Z
    //   2336: ifne -> 2346
    //   2339: goto -> 2449
    //   2342: invokestatic a : (Ljava/lang/Throwable;)Ljava/lang/Throwable;
    //   2345: athrow
    //   2346: aload #7
    //   2348: invokevirtual getType : ()Ljava/lang/Class;
    //   2351: astore #8
    //   2353: aload #8
    //   2355: ifnull -> 2436
    //   2358: aload #8
    //   2360: invokevirtual isPrimitive : ()Z
    //   2363: ifne -> 2436
    //   2366: goto -> 2373
    //   2369: invokestatic a : (Ljava/lang/Throwable;)Ljava/lang/Throwable;
    //   2372: athrow
    //   2373: aload #8
    //   2375: invokevirtual getPackage : ()Ljava/lang/Package;
    //   2378: ifnull -> 2436
    //   2381: goto -> 2388
    //   2384: invokestatic a : (Ljava/lang/Throwable;)Ljava/lang/Throwable;
    //   2387: athrow
    //   2388: aload #8
    //   2390: invokevirtual getPackage : ()Ljava/lang/Package;
    //   2393: invokevirtual getName : ()Ljava/lang/String;
    //   2396: ifnull -> 2436
    //   2399: goto -> 2406
    //   2402: invokestatic a : (Ljava/lang/Throwable;)Ljava/lang/Throwable;
    //   2405: athrow
    //   2406: aload #8
    //   2408: invokevirtual getPackage : ()Ljava/lang/Package;
    //   2411: invokevirtual getName : ()Ljava/lang/String;
    //   2414: sipush #-16703
    //   2417: sipush #1063
    //   2420: invokestatic a : (II)Ljava/lang/String;
    //   2423: invokevirtual startsWith : (Ljava/lang/String;)Z
    //   2426: ifne -> 2436
    //   2429: goto -> 2436
    //   2432: invokestatic a : (Ljava/lang/Throwable;)Ljava/lang/Throwable;
    //   2435: athrow
    //   2436: aload #7
    //   2438: iconst_1
    //   2439: invokevirtual setAccessible : (Z)V
    //   2442: aload #7
    //   2444: aconst_null
    //   2445: invokevirtual get : (Ljava/lang/Object;)Ljava/lang/Object;
    //   2448: pop
    //   2449: iinc #6, 1
    //   2452: iload_2
    //   2453: ifne -> 2314
    //   2456: sipush #-16697
    //   2459: sipush #-9356
    //   2462: invokestatic a : (II)Ljava/lang/String;
    //   2465: invokestatic forName : (Ljava/lang/String;)Ljava/lang/Class;
    //   2468: invokevirtual getDeclaredMethods : ()[Ljava/lang/reflect/Method;
    //   2471: astore #4
    //   2473: aload #4
    //   2475: arraylength
    //   2476: istore #5
    //   2478: iconst_0
    //   2479: istore #6
    //   2481: iload #6
    //   2483: iload #5
    //   2485: if_icmpge -> 2618
    //   2488: aload #4
    //   2490: iload #6
    //   2492: aaload
    //   2493: astore #7
    //   2495: aload #7
    //   2497: invokevirtual getParameterTypes : ()[Ljava/lang/Class;
    //   2500: pop
    //   2501: aload #7
    //   2503: invokevirtual getModifiers : ()I
    //   2506: invokestatic isStatic : (I)Z
    //   2509: ifeq -> 2604
    //   2512: aload #7
    //   2514: invokevirtual getParameterTypes : ()[Ljava/lang/Class;
    //   2517: arraylength
    //   2518: iconst_2
    //   2519: if_icmpne -> 2604
    //   2522: goto -> 2529
    //   2525: invokestatic a : (Ljava/lang/Throwable;)Ljava/lang/Throwable;
    //   2528: athrow
    //   2529: aload #7
    //   2531: invokevirtual getReturnType : ()Ljava/lang/Class;
    //   2534: getstatic java/lang/Void.TYPE : Ljava/lang/Class;
    //   2537: invokevirtual equals : (Ljava/lang/Object;)Z
    //   2540: ifeq -> 2604
    //   2543: goto -> 2550
    //   2546: invokestatic a : (Ljava/lang/Throwable;)Ljava/lang/Throwable;
    //   2549: athrow
    //   2550: aload #7
    //   2552: iconst_1
    //   2553: invokevirtual setAccessible : (Z)V
    //   2556: aload #7
    //   2558: aconst_null
    //   2559: iconst_2
    //   2560: anewarray java/lang/Object
    //   2563: dup
    //   2564: iconst_0
    //   2565: aload_0
    //   2566: aastore
    //   2567: dup
    //   2568: iconst_1
    //   2569: aload_1
    //   2570: ifnonnull -> 2588
    //   2573: goto -> 2580
    //   2576: invokestatic a : (Ljava/lang/Throwable;)Ljava/lang/Throwable;
    //   2579: athrow
    //   2580: aload_1
    //   2581: goto -> 2595
    //   2584: invokestatic a : (Ljava/lang/Throwable;)Ljava/lang/Throwable;
    //   2587: athrow
    //   2588: aload_1
    //   2589: checkcast [B
    //   2592: invokevirtual clone : ()Ljava/lang/Object;
    //   2595: aastore
    //   2596: invokevirtual invoke : (Ljava/lang/Object;[Ljava/lang/Object;)Ljava/lang/Object;
    //   2599: pop
    //   2600: iload_2
    //   2601: ifne -> 2618
    //   2604: iinc #6, 1
    //   2607: iload_2
    //   2608: ifne -> 2481
    //   2611: goto -> 2618
    //   2614: invokestatic a : (Ljava/lang/Throwable;)Ljava/lang/Throwable;
    //   2617: athrow
    //   2618: getstatic burp/Zr2i.Z_ : Ljava/lang/String;
    //   2621: getstatic burp/Zm3p.Zz : Ljava/lang/Object;
    //   2624: checkcast java/math/BigInteger
    //   2627: invokevirtual intValue : ()I
    //   2630: bipush #32
    //   2632: irem
    //   2633: invokestatic abs : (I)I
    //   2636: invokevirtual charAt : (I)C
    //   2639: getstatic burp/Zl06.ZL : Ljava/lang/String;
    //   2642: getstatic burp/Zrtc.Zr : Ljava/lang/Object;
    //   2645: checkcast java/math/BigInteger
    //   2648: invokevirtual intValue : ()I
    //   2651: bipush #32
    //   2653: irem
    //   2654: invokestatic abs : (I)I
    //   2657: invokevirtual charAt : (I)C
    //   2660: if_icmpgt -> 2767
    //   2663: getstatic burp/Zm8w.ZL : Ljava/lang/String;
    //   2666: getstatic burp/Zlck.Zr : Ljava/lang/Object;
    //   2669: checkcast java/math/BigInteger
    //   2672: invokevirtual intValue : ()I
    //   2675: bipush #32
    //   2677: irem
    //   2678: invokestatic abs : (I)I
    //   2681: invokevirtual charAt : (I)C
    //   2684: getstatic burp/Zs4z.Zs : Ljava/lang/String;
    //   2687: getstatic burp/Ze8m.Zm : Ljava/lang/Object;
    //   2690: checkcast java/math/BigInteger
    //   2693: invokevirtual intValue : ()I
    //   2696: bipush #32
    //   2698: irem
    //   2699: invokestatic abs : (I)I
    //   2702: invokevirtual charAt : (I)C
    //   2705: if_icmpgt -> 2767
    //   2708: goto -> 2715
    //   2711: invokestatic a : (Ljava/lang/Throwable;)Ljava/lang/Throwable;
    //   2714: athrow
    //   2715: getstatic burp/Zk7e.ZP : Ljava/lang/String;
    //   2718: getstatic burp/Zs8q.ZI : Ljava/lang/Object;
    //   2721: checkcast java/math/BigInteger
    //   2724: invokevirtual intValue : ()I
    //   2727: bipush #32
    //   2729: irem
    //   2730: invokestatic abs : (I)I
    //   2733: invokevirtual charAt : (I)C
    //   2736: getstatic burp/Zt9_.Zf : Ljava/lang/String;
    //   2739: getstatic burp/Zb4a.ZJ : Ljava/lang/Object;
    //   2742: checkcast java/math/BigInteger
    //   2745: invokevirtual intValue : ()I
    //   2748: bipush #32
    //   2750: irem
    //   2751: invokestatic abs : (I)I
    //   2754: invokevirtual charAt : (I)C
    //   2757: if_icmpgt -> 2775
    //   2760: goto -> 2767
    //   2763: invokestatic a : (Ljava/lang/Throwable;)Ljava/lang/Throwable;
    //   2766: athrow
    //   2767: iconst_1
    //   2768: goto -> 2776
    //   2771: invokestatic a : (Ljava/lang/Throwable;)Ljava/lang/Throwable;
    //   2774: athrow
    //   2775: iconst_0
    //   2776: ireturn
    //   2777: astore_3
    //   2778: new java/lang/Exception
    //   2781: dup
    //   2782: aload_3
    //   2783: invokevirtual getMessage : ()Ljava/lang/String;
    //   2786: invokespecial <init> : (Ljava/lang/String;)V
    //   2789: athrow
    // Exception table:
    //   from	to	target	type
    //   4	2776	2777	java/lang/Throwable
    //   40	214	217	java/lang/Throwable
    //   184	251	254	java/lang/Throwable
    //   221	288	291	java/lang/Throwable
    //   258	325	328	java/lang/Throwable
    //   295	362	365	java/lang/Throwable
    //   332	399	402	java/lang/Throwable
    //   369	436	439	java/lang/Throwable
    //   406	473	476	java/lang/Throwable
    //   443	510	513	java/lang/Throwable
    //   480	547	550	java/lang/Throwable
    //   517	584	587	java/lang/Throwable
    //   554	621	624	java/lang/Throwable
    //   591	658	661	java/lang/Throwable
    //   628	695	698	java/lang/Throwable
    //   665	732	735	java/lang/Throwable
    //   702	769	772	java/lang/Throwable
    //   739	806	809	java/lang/Throwable
    //   776	843	846	java/lang/Throwable
    //   813	880	883	java/lang/Throwable
    //   850	917	920	java/lang/Throwable
    //   887	954	957	java/lang/Throwable
    //   924	991	994	java/lang/Throwable
    //   961	1028	1031	java/lang/Throwable
    //   998	1065	1068	java/lang/Throwable
    //   1035	1102	1105	java/lang/Throwable
    //   1072	1139	1142	java/lang/Throwable
    //   1109	1176	1179	java/lang/Throwable
    //   1146	1213	1216	java/lang/Throwable
    //   1183	1250	1253	java/lang/Throwable
    //   1220	1287	1290	java/lang/Throwable
    //   1257	1324	1327	java/lang/Throwable
    //   1294	1357	1360	java/lang/Throwable
    //   1410	1424	1427	java/lang/Throwable
    //   1417	1438	1441	java/lang/Throwable
    //   1431	1452	1455	java/lang/Throwable
    //   1445	1466	1469	java/lang/Throwable
    //   1459	1480	1483	java/lang/Throwable
    //   1473	1494	1497	java/lang/Throwable
    //   1487	1508	1511	java/lang/Throwable
    //   1501	1522	1525	java/lang/Throwable
    //   1515	1532	1535	java/lang/Throwable
    //   1573	1587	1590	java/lang/Throwable
    //   1580	1601	1604	java/lang/Throwable
    //   1594	1615	1618	java/lang/Throwable
    //   1608	1629	1632	java/lang/Throwable
    //   1622	1643	1646	java/lang/Throwable
    //   1636	1657	1660	java/lang/Throwable
    //   1650	1671	1674	java/lang/Throwable
    //   1664	1685	1688	java/lang/Throwable
    //   1678	1702	1705	java/lang/Throwable
    //   1771	1791	1794	java/lang/Throwable
    //   1781	1808	1811	java/lang/Throwable
    //   1798	1826	1829	java/lang/Throwable
    //   1815	1843	1846	java/lang/Throwable
    //   1833	1861	1864	java/lang/Throwable
    //   1850	1878	1881	java/lang/Throwable
    //   1868	1895	1898	java/lang/Throwable
    //   1885	1920	1923	java/lang/Throwable
    //   1902	1937	1940	java/lang/Throwable
    //   1927	1954	1957	java/lang/Throwable
    //   1944	1979	1982	java/lang/Throwable
    //   1961	1996	1999	java/lang/Throwable
    //   1986	2013	2016	java/lang/Throwable
    //   2003	2034	2037	java/lang/Throwable
    //   2170	2207	2210	java/lang/Throwable
    //   2214	2257	2260	java/lang/Throwable
    //   2328	2342	2342	java/lang/Throwable
    //   2353	2366	2369	java/lang/Throwable
    //   2358	2381	2384	java/lang/Throwable
    //   2373	2399	2402	java/lang/Throwable
    //   2388	2429	2432	java/lang/Throwable
    //   2495	2522	2525	java/lang/Throwable
    //   2512	2543	2546	java/lang/Throwable
    //   2529	2573	2576	java/lang/Throwable
    //   2550	2584	2584	java/lang/Throwable
    //   2595	2611	2614	java/lang/Throwable
    //   2618	2708	2711	java/lang/Throwable
    //   2663	2760	2763	java/lang/Throwable
    //   2715	2771	2771	java/lang/Throwable
  }
  
  static void ZO(Object[] paramArrayOfObject, Object paramObject) throws Throwable {}
  
  static void ZQ(Object paramObject) {
    Zl8f.ZK = a(-16704, 1212);
    Zl8f.ZA = new BigInteger(a(-16699, -20552));
    boolean bool = Zt2e.ZN();
    try {
      try {
        if (Zlo5.ZJ.charAt(Math.abs(((BigInteger)Zs83.ZT).intValue() % 32)) > Ze_t.ZZ.charAt(Math.abs(((BigInteger)Zlo5.Zf).intValue() % 32))) {
          try {
            Zlid.Zq(Class.forName(a(-16702, -7335)));
            if (!bool)
              Zera.ZU(Class.forName(a(-16698, -31617))); 
          } catch (Throwable throwable) {
            throw a(null);
          } 
          return;
        } 
      } catch (Throwable throwable) {
        throw a(null);
      } 
      Zera.ZU(Class.forName(a(-16698, -31617)));
    } catch (Throwable throwable) {}
  }
  
  static {
    // Byte code:
    //   0: bipush #9
    //   2: anewarray java/lang/String
    //   5: astore #5
    //   7: iconst_0
    //   8: istore_3
    //   9: ldc 'åáìÿ p lÓáoç6xZHÍ&-ª¼,u=ç¨%Ø-Ô\\tlHÝÊê?p\\t\\fýÑ|DÝþwMÚÂY"ÂÕS±åà)D(@LÙVíí±KoéÂYt¦9Ò¬¹óÒ'³oTBÑÇ­PwG+9ìRó!>`½%aÍé¶gûZ?B÷W ä"yÑw/-Ö2cè±sÝºxæK[w1©\\tÒøøÕr'
    //   11: dup
    //   12: astore_2
    //   13: invokevirtual length : ()I
    //   16: istore #4
    //   18: iconst_4
    //   19: istore_1
    //   20: iconst_m1
    //   21: istore_0
    //   22: bipush #62
    //   24: iinc #0, 1
    //   27: aload_2
    //   28: iload_0
    //   29: dup
    //   30: iload_1
    //   31: iadd
    //   32: invokevirtual substring : (II)Ljava/lang/String;
    //   35: iconst_m1
    //   36: goto -> 142
    //   39: aload #5
    //   41: swap
    //   42: iload_3
    //   43: iinc #3, 1
    //   46: swap
    //   47: aastore
    //   48: iload_0
    //   49: iload_1
    //   50: iadd
    //   51: dup
    //   52: istore_0
    //   53: iload #4
    //   55: if_icmpge -> 67
    //   58: aload_2
    //   59: iload_0
    //   60: invokevirtual charAt : (I)C
    //   63: istore_1
    //   64: goto -> 22
    //   67: ldc 't´*FähÝM«T|®tµäù:Zó1ðãôdbò¡ß 4\\tÞ/"­gx­\Ê"²"aÎ.'r4ÉÔrð°¦=HÑW¶vòÿî'
    //   69: dup
    //   70: astore_2
    //   71: invokevirtual length : ()I
    //   74: istore #4
    //   76: bipush #9
    //   78: istore_1
    //   79: iconst_m1
    //   80: istore_0
    //   81: bipush #53
    //   83: iinc #0, 1
    //   86: aload_2
    //   87: iload_0
    //   88: dup
    //   89: iload_1
    //   90: iadd
    //   91: invokevirtual substring : (II)Ljava/lang/String;
    //   94: iconst_0
    //   95: goto -> 142
    //   98: aload #5
    //   100: swap
    //   101: iload_3
    //   102: iinc #3, 1
    //   105: swap
    //   106: aastore
    //   107: iload_0
    //   108: iload_1
    //   109: iadd
    //   110: dup
    //   111: istore_0
    //   112: iload #4
    //   114: if_icmpge -> 126
    //   117: aload_2
    //   118: iload_0
    //   119: invokevirtual charAt : (I)C
    //   122: istore_1
    //   123: goto -> 81
    //   126: aload #5
    //   128: putstatic burp/Zkm0.a : [Ljava/lang/String;
    //   131: bipush #9
    //   133: anewarray java/lang/String
    //   136: putstatic burp/Zkm0.b : [Ljava/lang/String;
    //   139: goto -> 300
    //   142: dup_x2
    //   143: pop
    //   144: invokevirtual toCharArray : ()[C
    //   147: dup_x1
    //   148: arraylength
    //   149: dup_x2
    //   150: pop
    //   151: iconst_0
    //   152: istore #6
    //   154: dup2_x1
    //   155: pop2
    //   156: dup_x2
    //   157: iconst_1
    //   158: if_icmpgt -> 260
    //   161: dup2
    //   162: swap
    //   163: iload #6
    //   165: dup2_x1
    //   166: caload
    //   167: swap
    //   168: iload #6
    //   170: bipush #7
    //   172: irem
    //   173: tableswitch default -> 242, 0 -> 212, 1 -> 217, 2 -> 222, 3 -> 227, 4 -> 232, 5 -> 237
    //   212: bipush #118
    //   214: goto -> 244
    //   217: bipush #6
    //   219: goto -> 244
    //   222: bipush #59
    //   224: goto -> 244
    //   227: bipush #81
    //   229: goto -> 244
    //   232: bipush #54
    //   234: goto -> 244
    //   237: bipush #60
    //   239: goto -> 244
    //   242: bipush #109
    //   244: ixor
    //   245: ixor
    //   246: i2c
    //   247: castore
    //   248: iinc #6, 1
    //   251: dup
    //   252: ifne -> 260
    //   255: dup2
    //   256: dup_x1
    //   257: goto -> 165
    //   260: dup2_x1
    //   261: pop2
    //   262: dup_x2
    //   263: iload #6
    //   265: if_icmpgt -> 161
    //   268: pop
    //   269: new java/lang/String
    //   272: dup_x1
    //   273: swap
    //   274: invokespecial <init> : ([C)V
    //   277: invokevirtual intern : ()Ljava/lang/String;
    //   280: swap
    //   281: pop
    //   282: swap
    //   283: tableswitch default -> 39, 0 -> 98
    //   300: new java/math/BigInteger
    //   303: dup
    //   304: sipush #-16695
    //   307: sipush #16530
    //   310: invokestatic a : (II)Ljava/lang/String;
    //   313: invokespecial <init> : (Ljava/lang/String;)V
    //   316: putstatic burp/Zkm0.ZI : Ljava/lang/Object;
    //   319: sipush #-16700
    //   322: sipush #-6913
    //   325: invokestatic a : (II)Ljava/lang/String;
    //   328: putstatic burp/Zkm0.ZL : Ljava/lang/String;
    //   331: return
  }
  
  private static Throwable a(Throwable paramThrowable) {
    return paramThrowable;
  }
  
  private static String a(int paramInt1, int paramInt2) {
    int i = (paramInt1 ^ 0xFFFFBEC1) & 0xFFFF;
    if (b[i] == null) {
      char[] arrayOfChar = a[i].toCharArray();
      switch (arrayOfChar[0] & 0xFF) {
        case 0:
        
        case 1:
        
        case 2:
        
        case 3:
        
        case 4:
        
        case 5:
        
        case 6:
        
        case 7:
        
        case 8:
        
        case 9:
        
        case 10:
        
        case 11:
        
        case 12:
        
        case 13:
        
        case 14:
        
        case 15:
        
        case 16:
        
        case 17:
        
        case 18:
        
        case 19:
        
        case 20:
        
        case 21:
        
        case 22:
        
        case 23:
        
        case 24:
        
        case 25:
        
        case 26:
        
        case 27:
        
        case 28:
        
        case 29:
        
        case 30:
        
        case 31:
        
        case 32:
        
        case 33:
        
        case 34:
        
        case 35:
        
        case 36:
        
        case 37:
        
        case 38:
        
        case 39:
        
        case 40:
        
        case 41:
        
        case 42:
        
        case 43:
        
        case 44:
        
        case 45:
        
        case 46:
        
        case 47:
        
        case 48:
        
        case 49:
        
        case 50:
        
        case 51:
        
        case 52:
        
        case 53:
        
        case 54:
        
        case 55:
        
        case 56:
        
        case 57:
        
        case 58:
        
        case 59:
        
        case 60:
        
        case 61:
        
        case 62:
        
        case 63:
        
        case 64:
        
        case 65:
        
        case 66:
        
        case 67:
        
        case 68:
        
        case 69:
        
        case 70:
        
        case 71:
        
        case 72:
        
        case 73:
        
        case 74:
        
        case 75:
        
        case 76:
        
        case 77:
        
        case 78:
        
        case 79:
        
        case 80:
        
        case 81:
        
        case 82:
        
        case 83:
        
        case 84:
        
        case 85:
        
        case 86:
        
        case 87:
        
        case 88:
        
        case 89:
        
        case 90:
        
        case 91:
        
        case 92:
        
        case 93:
        
        case 94:
        
        case 95:
        
        case 96:
        
        case 97:
        
        case 98:
        
        case 99:
        
        case 100:
        
        case 101:
        
        case 102:
        
        case 103:
        
        case 104:
        
        case 105:
        
        case 106:
        
        case 107:
        
        case 108:
        
        case 109:
        
        case 110:
        
        case 111:
        
        case 112:
        
        case 113:
        
        case 114:
        
        case 115:
        
        case 116:
        
        case 117:
        
        case 118:
        
        case 119:
        
        case 120:
        
        case 121:
        
        case 122:
        
        case 123:
        
        case 124:
        
        case 125:
        
        case 126:
        
        case 127:
        
        case 128:
        
        case 129:
        
        case 130:
        
        case 131:
        
        case 132:
        
        case 133:
        
        case 134:
        
        case 135:
        
        case 136:
        
        case 137:
        
        case 138:
        
        case 139:
        
        case 140:
        
        case 141:
        
        case 142:
        
        case 143:
        
        case 144:
        
        case 145:
        
        case 146:
        
        case 147:
        
        case 148:
        
        case 149:
        
        case 150:
        
        case 151:
        
        case 152:
        
        case 153:
        
        case 154:
        
        case 155:
        
        case 156:
        
        case 157:
        
        case 158:
        
        case 159:
        
        case 160:
        
        case 161:
        
        case 162:
        
        case 163:
        
        case 164:
        
        case 165:
        
        case 166:
        
        case 167:
        
        case 168:
        
        case 169:
        
        case 170:
        
        case 171:
        
        case 172:
        
        case 173:
        
        case 174:
        
        case 175:
        
        case 176:
        
        case 177:
        
        case 178:
        
        case 179:
        
        case 180:
        
        case 181:
        
        case 182:
        
        case 183:
        
        case 184:
        
        case 185:
        
        case 186:
        
        case 187:
        
        case 188:
        
        case 189:
        
        case 190:
        
        case 191:
        
        case 192:
        
        case 193:
        
        case 194:
        
        case 195:
        
        case 196:
        
        case 197:
        
        case 198:
        
        case 199:
        
        case 200:
        
        case 201:
        
        case 202:
        
        case 203:
        
        case 204:
        
        case 205:
        
        case 206:
        
        case 207:
        
        case 208:
        
        case 209:
        
        case 210:
        
        case 211:
        
        case 212:
        
        case 213:
        
        case 214:
        
        case 215:
        
        case 216:
        
        case 217:
        
        case 218:
        
        case 219:
        
        case 220:
        
        case 221:
        
        case 222:
        
        case 223:
        
        case 224:
        
        case 225:
        
        case 226:
        
        case 227:
        
        case 228:
        
        case 229:
        
        case 230:
        
        case 231:
        
        case 232:
        
        case 233:
        
        case 234:
        
        case 235:
        
        case 236:
        
        case 237:
        
        case 238:
        
        case 239:
        
        case 240:
        
        case 241:
        
        case 242:
        
        case 243:
        
        case 244:
        
        case 245:
        
        case 246:
        
        case 247:
        
        case 248:
        
        case 249:
        
        case 250:
        
        case 251:
        
        case 252:
        
        case 253:
        
        case 254:
        
        default:
          break;
      } 
      char c = '';
      int j = (paramInt2 & 0xFF) - c;
      if (j < 0)
        j += 256; 
      int k = ((paramInt2 & 0xFFFF) >>> 8) - c;
      if (k < 0)
        k += 256; 
      for (byte b = 0; b < arrayOfChar.length; b++) {
        int m = b % 2;
        if (m == 0) {
          arrayOfChar[b] = (char)(arrayOfChar[b] ^ j);
          j = ((j >>> 3 | j << 5) ^ arrayOfChar[b]) & 0xFF;
        } else {
          arrayOfChar[b] = (char)(arrayOfChar[b] ^ k);
          k = ((k >>> 3 | k << 5) ^ arrayOfChar[b]) & 0xFF;
        } 
      } 
      b[i] = (new String(arrayOfChar)).intern();
    } 
    return b[i];
  }
}


/* Location:              C:\Program Files\BurpSuitePro\burpsuite_pro.jar!\burp\Zkm0.class
 * Java compiler version: 21 (65.0)
 * JD-Core Version:       1.1.3
 */