package burp;

import java.math.BigInteger;

class Zko9 extends ClassLoader {
  static String Zf;
  
  static Object ZC;
  
  private static final String[] a;
  
  private static final String[] b;
  
  static boolean ZE(Object[] paramArrayOfObject, Object paramObject) throws Throwable {
    // Byte code:
    //   0: invokestatic ZK : ()Z
    //   3: istore_2
    //   4: getstatic burp/Zkv2.ZC : Ljava/lang/Object;
    //   7: checkcast java/math/BigInteger
    //   10: invokevirtual toByteArray : ()[B
    //   13: astore_3
    //   14: new java/lang/StringBuilder
    //   17: dup
    //   18: invokespecial <init> : ()V
    //   21: astore #5
    //   23: aload #5
    //   25: sipush #6488
    //   28: sipush #19452
    //   31: invokestatic a : (II)Ljava/lang/String;
    //   34: invokevirtual append : (Ljava/lang/String;)Ljava/lang/StringBuilder;
    //   37: pop
    //   38: aload_3
    //   39: astore #6
    //   41: aload #6
    //   43: arraylength
    //   44: istore #7
    //   46: iconst_0
    //   47: istore #8
    //   49: iload #8
    //   51: iload #7
    //   53: if_icmpge -> 79
    //   56: aload #6
    //   58: iload #8
    //   60: baload
    //   61: istore #9
    //   63: aload #5
    //   65: iload #9
    //   67: i2c
    //   68: invokevirtual append : (C)Ljava/lang/StringBuilder;
    //   71: pop
    //   72: iinc #8, 1
    //   75: iload_2
    //   76: ifeq -> 49
    //   79: aload #5
    //   81: sipush #6494
    //   84: sipush #-16467
    //   87: invokestatic a : (II)Ljava/lang/String;
    //   90: ldc ''
    //   92: invokestatic getProperty : (Ljava/lang/String;Ljava/lang/String;)Ljava/lang/String;
    //   95: invokevirtual toLowerCase : ()Ljava/lang/String;
    //   98: invokevirtual append : (Ljava/lang/String;)Ljava/lang/StringBuilder;
    //   101: pop
    //   102: aload #5
    //   104: sipush #6491
    //   107: sipush #24631
    //   110: invokestatic a : (II)Ljava/lang/String;
    //   113: ldc ''
    //   115: invokestatic getProperty : (Ljava/lang/String;Ljava/lang/String;)Ljava/lang/String;
    //   118: invokevirtual toLowerCase : ()Ljava/lang/String;
    //   121: invokevirtual append : (Ljava/lang/String;)Ljava/lang/StringBuilder;
    //   124: pop
    //   125: aload #5
    //   127: invokevirtual toString : ()Ljava/lang/String;
    //   130: invokevirtual getBytes : ()[B
    //   133: astore #4
    //   135: aload #4
    //   137: astore_3
    //   138: aload_3
    //   139: arraylength
    //   140: bipush #8
    //   142: iadd
    //   143: bipush #6
    //   145: ishr
    //   146: iconst_1
    //   147: iadd
    //   148: bipush #16
    //   150: imul
    //   151: newarray int
    //   153: astore #5
    //   155: iconst_0
    //   156: istore #6
    //   158: iload #6
    //   160: aload_3
    //   161: arraylength
    //   162: if_icmpge -> 205
    //   165: aload_3
    //   166: iload #6
    //   168: baload
    //   169: sipush #255
    //   172: iand
    //   173: istore #7
    //   175: aload #5
    //   177: iload #6
    //   179: iconst_2
    //   180: ishr
    //   181: dup2
    //   182: iaload
    //   183: iload #7
    //   185: bipush #24
    //   187: iload #6
    //   189: iconst_4
    //   190: irem
    //   191: bipush #8
    //   193: imul
    //   194: isub
    //   195: ishl
    //   196: ior
    //   197: iastore
    //   198: iinc #6, 1
    //   201: iload_2
    //   202: ifeq -> 158
    //   205: aload #5
    //   207: iload #6
    //   209: iconst_2
    //   210: ishr
    //   211: dup2
    //   212: iaload
    //   213: sipush #128
    //   216: bipush #24
    //   218: iload #6
    //   220: iconst_4
    //   221: irem
    //   222: bipush #8
    //   224: imul
    //   225: isub
    //   226: ishl
    //   227: ior
    //   228: iastore
    //   229: aload #5
    //   231: aload #5
    //   233: arraylength
    //   234: iconst_1
    //   235: isub
    //   236: aload_3
    //   237: arraylength
    //   238: bipush #8
    //   240: imul
    //   241: iastore
    //   242: bipush #80
    //   244: newarray int
    //   246: astore #7
    //   248: ldc 1732584193
    //   250: istore #8
    //   252: ldc -271733879
    //   254: istore #9
    //   256: ldc -1732584194
    //   258: istore #10
    //   260: ldc 271733878
    //   262: istore #11
    //   264: ldc -1009589776
    //   266: istore #12
    //   268: iconst_0
    //   269: istore #6
    //   271: iload #6
    //   273: aload #5
    //   275: arraylength
    //   276: if_icmpge -> 598
    //   279: iload #8
    //   281: istore #13
    //   283: iload #9
    //   285: istore #14
    //   287: iload #10
    //   289: istore #15
    //   291: iload #11
    //   293: istore #16
    //   295: iload #12
    //   297: istore #17
    //   299: iconst_0
    //   300: istore #18
    //   302: iload #18
    //   304: bipush #80
    //   306: if_icmpge -> 556
    //   309: iload #18
    //   311: bipush #16
    //   313: if_icmpge -> 340
    //   316: aload #7
    //   318: iload #18
    //   320: aload #5
    //   322: iload #6
    //   324: iload #18
    //   326: iadd
    //   327: iaload
    //   328: iastore
    //   329: iload_2
    //   330: ifeq -> 395
    //   333: goto -> 340
    //   336: invokestatic a : (Ljava/lang/Throwable;)Ljava/lang/Throwable;
    //   339: athrow
    //   340: aload #7
    //   342: iload #18
    //   344: iconst_3
    //   345: isub
    //   346: iaload
    //   347: aload #7
    //   349: iload #18
    //   351: bipush #8
    //   353: isub
    //   354: iaload
    //   355: ixor
    //   356: aload #7
    //   358: iload #18
    //   360: bipush #14
    //   362: isub
    //   363: iaload
    //   364: ixor
    //   365: aload #7
    //   367: iload #18
    //   369: bipush #16
    //   371: isub
    //   372: iaload
    //   373: ixor
    //   374: istore #19
    //   376: iload #19
    //   378: iconst_1
    //   379: ishl
    //   380: iload #19
    //   382: bipush #31
    //   384: iushr
    //   385: ior
    //   386: istore #20
    //   388: aload #7
    //   390: iload #18
    //   392: iload #20
    //   394: iastore
    //   395: iload #8
    //   397: iconst_5
    //   398: ishl
    //   399: iload #8
    //   401: bipush #27
    //   403: iushr
    //   404: ior
    //   405: istore #19
    //   407: iload #19
    //   409: iload #12
    //   411: iadd
    //   412: aload #7
    //   414: iload #18
    //   416: iaload
    //   417: iadd
    //   418: iload #18
    //   420: bipush #20
    //   422: if_icmpge -> 448
    //   425: ldc 1518500249
    //   427: iload #9
    //   429: iload #10
    //   431: iand
    //   432: iload #9
    //   434: iconst_m1
    //   435: ixor
    //   436: iload #11
    //   438: iand
    //   439: ior
    //   440: iadd
    //   441: goto -> 518
    //   444: invokestatic a : (Ljava/lang/Throwable;)Ljava/lang/Throwable;
    //   447: athrow
    //   448: iload #18
    //   450: bipush #40
    //   452: if_icmpge -> 473
    //   455: ldc 1859775393
    //   457: iload #9
    //   459: iload #10
    //   461: ixor
    //   462: iload #11
    //   464: ixor
    //   465: iadd
    //   466: goto -> 518
    //   469: invokestatic a : (Ljava/lang/Throwable;)Ljava/lang/Throwable;
    //   472: athrow
    //   473: iload #18
    //   475: bipush #60
    //   477: if_icmpge -> 507
    //   480: ldc -1894007588
    //   482: iload #9
    //   484: iload #10
    //   486: iand
    //   487: iload #9
    //   489: iload #11
    //   491: iand
    //   492: ior
    //   493: iload #10
    //   495: iload #11
    //   497: iand
    //   498: ior
    //   499: iadd
    //   500: goto -> 518
    //   503: invokestatic a : (Ljava/lang/Throwable;)Ljava/lang/Throwable;
    //   506: athrow
    //   507: ldc -899497514
    //   509: iload #9
    //   511: iload #10
    //   513: ixor
    //   514: iload #11
    //   516: ixor
    //   517: iadd
    //   518: iadd
    //   519: istore #20
    //   521: iload #11
    //   523: istore #12
    //   525: iload #10
    //   527: istore #11
    //   529: iload #9
    //   531: bipush #30
    //   533: ishl
    //   534: iload #9
    //   536: iconst_2
    //   537: iushr
    //   538: ior
    //   539: istore #10
    //   541: iload #8
    //   543: istore #9
    //   545: iload #20
    //   547: istore #8
    //   549: iinc #18, 1
    //   552: iload_2
    //   553: ifeq -> 302
    //   556: iload #8
    //   558: iload #13
    //   560: iadd
    //   561: istore #8
    //   563: iload #9
    //   565: iload #14
    //   567: iadd
    //   568: istore #9
    //   570: iload #10
    //   572: iload #15
    //   574: iadd
    //   575: istore #10
    //   577: iload #11
    //   579: iload #16
    //   581: iadd
    //   582: istore #11
    //   584: iload #12
    //   586: iload #17
    //   588: iadd
    //   589: istore #12
    //   591: iinc #6, 16
    //   594: iload_2
    //   595: ifeq -> 271
    //   598: iconst_5
    //   599: newarray int
    //   601: dup
    //   602: iconst_0
    //   603: iload #8
    //   605: iastore
    //   606: dup
    //   607: iconst_1
    //   608: iload #9
    //   610: iastore
    //   611: dup
    //   612: iconst_2
    //   613: iload #10
    //   615: iastore
    //   616: dup
    //   617: iconst_3
    //   618: iload #11
    //   620: iastore
    //   621: dup
    //   622: iconst_4
    //   623: iload #12
    //   625: iastore
    //   626: astore #13
    //   628: bipush #20
    //   630: newarray byte
    //   632: astore #14
    //   634: iconst_0
    //   635: istore #15
    //   637: iload #15
    //   639: bipush #20
    //   641: if_icmpge -> 682
    //   644: aload #13
    //   646: iload #15
    //   648: iconst_4
    //   649: idiv
    //   650: iaload
    //   651: istore #16
    //   653: iconst_3
    //   654: iload #15
    //   656: iconst_4
    //   657: irem
    //   658: isub
    //   659: bipush #8
    //   661: imul
    //   662: istore #17
    //   664: aload #14
    //   666: iload #15
    //   668: iload #16
    //   670: iload #17
    //   672: iushr
    //   673: i2b
    //   674: bastore
    //   675: iinc #15, 1
    //   678: iload_2
    //   679: ifeq -> 637
    //   682: aload #14
    //   684: astore #4
    //   686: new java/lang/StringBuilder
    //   689: dup
    //   690: invokespecial <init> : ()V
    //   693: astore_3
    //   694: iconst_0
    //   695: istore #4
    //   697: iload #4
    //   699: bipush #32
    //   701: if_icmpge -> 2035
    //   704: iload #4
    //   706: tableswitch default -> 2028, 0 -> 848, 1 -> 885, 2 -> 922, 3 -> 959, 4 -> 996, 5 -> 1033, 6 -> 1070, 7 -> 1107, 8 -> 1144, 9 -> 1181, 10 -> 1218, 11 -> 1255, 12 -> 1292, 13 -> 1329, 14 -> 1366, 15 -> 1403, 16 -> 1440, 17 -> 1477, 18 -> 1514, 19 -> 1551, 20 -> 1588, 21 -> 1625, 22 -> 1662, 23 -> 1699, 24 -> 1736, 25 -> 1773, 26 -> 1810, 27 -> 1847, 28 -> 1884, 29 -> 1921, 30 -> 1958, 31 -> 1995
    //   848: aload_3
    //   849: getstatic burp/Zep1.ZQ : Ljava/lang/String;
    //   852: getstatic burp/Zxn7.ZU : Ljava/lang/Object;
    //   855: checkcast java/math/BigInteger
    //   858: invokevirtual intValue : ()I
    //   861: bipush #32
    //   863: irem
    //   864: invokestatic abs : (I)I
    //   867: invokevirtual charAt : (I)C
    //   870: invokevirtual append : (C)Ljava/lang/StringBuilder;
    //   873: pop
    //   874: iload_2
    //   875: ifeq -> 2028
    //   878: goto -> 885
    //   881: invokestatic a : (Ljava/lang/Throwable;)Ljava/lang/Throwable;
    //   884: athrow
    //   885: aload_3
    //   886: getstatic burp/Zl3l.Z_ : Ljava/lang/String;
    //   889: getstatic burp/Zkff.Zr : Ljava/lang/Object;
    //   892: checkcast java/math/BigInteger
    //   895: invokevirtual intValue : ()I
    //   898: bipush #32
    //   900: irem
    //   901: invokestatic abs : (I)I
    //   904: invokevirtual charAt : (I)C
    //   907: invokevirtual append : (C)Ljava/lang/StringBuilder;
    //   910: pop
    //   911: iload_2
    //   912: ifeq -> 2028
    //   915: goto -> 922
    //   918: invokestatic a : (Ljava/lang/Throwable;)Ljava/lang/Throwable;
    //   921: athrow
    //   922: aload_3
    //   923: getstatic burp/Zsq6.Zm : Ljava/lang/String;
    //   926: getstatic burp/Zzvr.Z_ : Ljava/lang/Object;
    //   929: checkcast java/math/BigInteger
    //   932: invokevirtual intValue : ()I
    //   935: bipush #32
    //   937: irem
    //   938: invokestatic abs : (I)I
    //   941: invokevirtual charAt : (I)C
    //   944: invokevirtual append : (C)Ljava/lang/StringBuilder;
    //   947: pop
    //   948: iload_2
    //   949: ifeq -> 2028
    //   952: goto -> 959
    //   955: invokestatic a : (Ljava/lang/Throwable;)Ljava/lang/Throwable;
    //   958: athrow
    //   959: aload_3
    //   960: getstatic burp/Zb0s.Zi : Ljava/lang/String;
    //   963: getstatic burp/Zszz.ZG : Ljava/lang/Object;
    //   966: checkcast java/math/BigInteger
    //   969: invokevirtual intValue : ()I
    //   972: bipush #32
    //   974: irem
    //   975: invokestatic abs : (I)I
    //   978: invokevirtual charAt : (I)C
    //   981: invokevirtual append : (C)Ljava/lang/StringBuilder;
    //   984: pop
    //   985: iload_2
    //   986: ifeq -> 2028
    //   989: goto -> 996
    //   992: invokestatic a : (Ljava/lang/Throwable;)Ljava/lang/Throwable;
    //   995: athrow
    //   996: aload_3
    //   997: getstatic burp/Zxl5.Zq : Ljava/lang/String;
    //   1000: getstatic burp/Zmpc.Zc : Ljava/lang/Object;
    //   1003: checkcast java/math/BigInteger
    //   1006: invokevirtual intValue : ()I
    //   1009: bipush #32
    //   1011: irem
    //   1012: invokestatic abs : (I)I
    //   1015: invokevirtual charAt : (I)C
    //   1018: invokevirtual append : (C)Ljava/lang/StringBuilder;
    //   1021: pop
    //   1022: iload_2
    //   1023: ifeq -> 2028
    //   1026: goto -> 1033
    //   1029: invokestatic a : (Ljava/lang/Throwable;)Ljava/lang/Throwable;
    //   1032: athrow
    //   1033: aload_3
    //   1034: getstatic burp/Zshq.Zi : Ljava/lang/String;
    //   1037: getstatic burp/Zkjr.Zw : Ljava/lang/Object;
    //   1040: checkcast java/math/BigInteger
    //   1043: invokevirtual intValue : ()I
    //   1046: bipush #32
    //   1048: irem
    //   1049: invokestatic abs : (I)I
    //   1052: invokevirtual charAt : (I)C
    //   1055: invokevirtual append : (C)Ljava/lang/StringBuilder;
    //   1058: pop
    //   1059: iload_2
    //   1060: ifeq -> 2028
    //   1063: goto -> 1070
    //   1066: invokestatic a : (Ljava/lang/Throwable;)Ljava/lang/Throwable;
    //   1069: athrow
    //   1070: aload_3
    //   1071: getstatic burp/Zx4l.Zy : Ljava/lang/String;
    //   1074: getstatic burp/Zrvb.ZD : Ljava/lang/Object;
    //   1077: checkcast java/math/BigInteger
    //   1080: invokevirtual intValue : ()I
    //   1083: bipush #32
    //   1085: irem
    //   1086: invokestatic abs : (I)I
    //   1089: invokevirtual charAt : (I)C
    //   1092: invokevirtual append : (C)Ljava/lang/StringBuilder;
    //   1095: pop
    //   1096: iload_2
    //   1097: ifeq -> 2028
    //   1100: goto -> 1107
    //   1103: invokestatic a : (Ljava/lang/Throwable;)Ljava/lang/Throwable;
    //   1106: athrow
    //   1107: aload_3
    //   1108: getstatic burp/Zelz.ZK : Ljava/lang/String;
    //   1111: getstatic burp/Zenq.Zd : Ljava/lang/Object;
    //   1114: checkcast java/math/BigInteger
    //   1117: invokevirtual intValue : ()I
    //   1120: bipush #32
    //   1122: irem
    //   1123: invokestatic abs : (I)I
    //   1126: invokevirtual charAt : (I)C
    //   1129: invokevirtual append : (C)Ljava/lang/StringBuilder;
    //   1132: pop
    //   1133: iload_2
    //   1134: ifeq -> 2028
    //   1137: goto -> 1144
    //   1140: invokestatic a : (Ljava/lang/Throwable;)Ljava/lang/Throwable;
    //   1143: athrow
    //   1144: aload_3
    //   1145: getstatic burp/Zva.Zi : Ljava/lang/String;
    //   1148: getstatic burp/Zgsy.ZC : Ljava/lang/Object;
    //   1151: checkcast java/math/BigInteger
    //   1154: invokevirtual intValue : ()I
    //   1157: bipush #32
    //   1159: irem
    //   1160: invokestatic abs : (I)I
    //   1163: invokevirtual charAt : (I)C
    //   1166: invokevirtual append : (C)Ljava/lang/StringBuilder;
    //   1169: pop
    //   1170: iload_2
    //   1171: ifeq -> 2028
    //   1174: goto -> 1181
    //   1177: invokestatic a : (Ljava/lang/Throwable;)Ljava/lang/Throwable;
    //   1180: athrow
    //   1181: aload_3
    //   1182: getstatic burp/Zem6.Zp : Ljava/lang/String;
    //   1185: getstatic burp/Zkgp.Zw : Ljava/lang/Object;
    //   1188: checkcast java/math/BigInteger
    //   1191: invokevirtual intValue : ()I
    //   1194: bipush #32
    //   1196: irem
    //   1197: invokestatic abs : (I)I
    //   1200: invokevirtual charAt : (I)C
    //   1203: invokevirtual append : (C)Ljava/lang/StringBuilder;
    //   1206: pop
    //   1207: iload_2
    //   1208: ifeq -> 2028
    //   1211: goto -> 1218
    //   1214: invokestatic a : (Ljava/lang/Throwable;)Ljava/lang/Throwable;
    //   1217: athrow
    //   1218: aload_3
    //   1219: getstatic burp/Zz7j.ZP : Ljava/lang/String;
    //   1222: getstatic burp/Zr8s.Zt : Ljava/lang/Object;
    //   1225: checkcast java/math/BigInteger
    //   1228: invokevirtual intValue : ()I
    //   1231: bipush #32
    //   1233: irem
    //   1234: invokestatic abs : (I)I
    //   1237: invokevirtual charAt : (I)C
    //   1240: invokevirtual append : (C)Ljava/lang/StringBuilder;
    //   1243: pop
    //   1244: iload_2
    //   1245: ifeq -> 2028
    //   1248: goto -> 1255
    //   1251: invokestatic a : (Ljava/lang/Throwable;)Ljava/lang/Throwable;
    //   1254: athrow
    //   1255: aload_3
    //   1256: getstatic burp/Zmcb.Zl : Ljava/lang/String;
    //   1259: getstatic burp/Zxn9.ZN : Ljava/lang/Object;
    //   1262: checkcast java/math/BigInteger
    //   1265: invokevirtual intValue : ()I
    //   1268: bipush #32
    //   1270: irem
    //   1271: invokestatic abs : (I)I
    //   1274: invokevirtual charAt : (I)C
    //   1277: invokevirtual append : (C)Ljava/lang/StringBuilder;
    //   1280: pop
    //   1281: iload_2
    //   1282: ifeq -> 2028
    //   1285: goto -> 1292
    //   1288: invokestatic a : (Ljava/lang/Throwable;)Ljava/lang/Throwable;
    //   1291: athrow
    //   1292: aload_3
    //   1293: getstatic burp/Zxnm.Zw : Ljava/lang/String;
    //   1296: getstatic burp/Zr8s.Zt : Ljava/lang/Object;
    //   1299: checkcast java/math/BigInteger
    //   1302: invokevirtual intValue : ()I
    //   1305: bipush #32
    //   1307: irem
    //   1308: invokestatic abs : (I)I
    //   1311: invokevirtual charAt : (I)C
    //   1314: invokevirtual append : (C)Ljava/lang/StringBuilder;
    //   1317: pop
    //   1318: iload_2
    //   1319: ifeq -> 2028
    //   1322: goto -> 1329
    //   1325: invokestatic a : (Ljava/lang/Throwable;)Ljava/lang/Throwable;
    //   1328: athrow
    //   1329: aload_3
    //   1330: getstatic burp/Zlid.ZU : Ljava/lang/String;
    //   1333: getstatic burp/Zszm.ZI : Ljava/lang/Object;
    //   1336: checkcast java/math/BigInteger
    //   1339: invokevirtual intValue : ()I
    //   1342: bipush #32
    //   1344: irem
    //   1345: invokestatic abs : (I)I
    //   1348: invokevirtual charAt : (I)C
    //   1351: invokevirtual append : (C)Ljava/lang/StringBuilder;
    //   1354: pop
    //   1355: iload_2
    //   1356: ifeq -> 2028
    //   1359: goto -> 1366
    //   1362: invokestatic a : (Ljava/lang/Throwable;)Ljava/lang/Throwable;
    //   1365: athrow
    //   1366: aload_3
    //   1367: getstatic burp/Zegw.Zn : Ljava/lang/String;
    //   1370: getstatic burp/Zeb3.Zb : Ljava/lang/Object;
    //   1373: checkcast java/math/BigInteger
    //   1376: invokevirtual intValue : ()I
    //   1379: bipush #32
    //   1381: irem
    //   1382: invokestatic abs : (I)I
    //   1385: invokevirtual charAt : (I)C
    //   1388: invokevirtual append : (C)Ljava/lang/StringBuilder;
    //   1391: pop
    //   1392: iload_2
    //   1393: ifeq -> 2028
    //   1396: goto -> 1403
    //   1399: invokestatic a : (Ljava/lang/Throwable;)Ljava/lang/Throwable;
    //   1402: athrow
    //   1403: aload_3
    //   1404: getstatic burp/Zl4v.ZD : Ljava/lang/String;
    //   1407: getstatic burp/Zlpj.Zc : Ljava/lang/Object;
    //   1410: checkcast java/math/BigInteger
    //   1413: invokevirtual intValue : ()I
    //   1416: bipush #32
    //   1418: irem
    //   1419: invokestatic abs : (I)I
    //   1422: invokevirtual charAt : (I)C
    //   1425: invokevirtual append : (C)Ljava/lang/StringBuilder;
    //   1428: pop
    //   1429: iload_2
    //   1430: ifeq -> 2028
    //   1433: goto -> 1440
    //   1436: invokestatic a : (Ljava/lang/Throwable;)Ljava/lang/Throwable;
    //   1439: athrow
    //   1440: aload_3
    //   1441: getstatic burp/Zxzd.ZM : Ljava/lang/String;
    //   1444: getstatic burp/Zlno.ZU : Ljava/lang/Object;
    //   1447: checkcast java/math/BigInteger
    //   1450: invokevirtual intValue : ()I
    //   1453: bipush #32
    //   1455: irem
    //   1456: invokestatic abs : (I)I
    //   1459: invokevirtual charAt : (I)C
    //   1462: invokevirtual append : (C)Ljava/lang/StringBuilder;
    //   1465: pop
    //   1466: iload_2
    //   1467: ifeq -> 2028
    //   1470: goto -> 1477
    //   1473: invokestatic a : (Ljava/lang/Throwable;)Ljava/lang/Throwable;
    //   1476: athrow
    //   1477: aload_3
    //   1478: getstatic burp/Zr3x.ZM : Ljava/lang/String;
    //   1481: getstatic burp/Zm6h.ZB : Ljava/lang/Object;
    //   1484: checkcast java/math/BigInteger
    //   1487: invokevirtual intValue : ()I
    //   1490: bipush #32
    //   1492: irem
    //   1493: invokestatic abs : (I)I
    //   1496: invokevirtual charAt : (I)C
    //   1499: invokevirtual append : (C)Ljava/lang/StringBuilder;
    //   1502: pop
    //   1503: iload_2
    //   1504: ifeq -> 2028
    //   1507: goto -> 1514
    //   1510: invokestatic a : (Ljava/lang/Throwable;)Ljava/lang/Throwable;
    //   1513: athrow
    //   1514: aload_3
    //   1515: getstatic burp/Zrfl.Zy : Ljava/lang/String;
    //   1518: getstatic burp/Zs8q.ZI : Ljava/lang/Object;
    //   1521: checkcast java/math/BigInteger
    //   1524: invokevirtual intValue : ()I
    //   1527: bipush #32
    //   1529: irem
    //   1530: invokestatic abs : (I)I
    //   1533: invokevirtual charAt : (I)C
    //   1536: invokevirtual append : (C)Ljava/lang/StringBuilder;
    //   1539: pop
    //   1540: iload_2
    //   1541: ifeq -> 2028
    //   1544: goto -> 1551
    //   1547: invokestatic a : (Ljava/lang/Throwable;)Ljava/lang/Throwable;
    //   1550: athrow
    //   1551: aload_3
    //   1552: getstatic burp/Zsk2.ZE : Ljava/lang/String;
    //   1555: getstatic burp/Zex.ZO : Ljava/lang/Object;
    //   1558: checkcast java/math/BigInteger
    //   1561: invokevirtual intValue : ()I
    //   1564: bipush #32
    //   1566: irem
    //   1567: invokestatic abs : (I)I
    //   1570: invokevirtual charAt : (I)C
    //   1573: invokevirtual append : (C)Ljava/lang/StringBuilder;
    //   1576: pop
    //   1577: iload_2
    //   1578: ifeq -> 2028
    //   1581: goto -> 1588
    //   1584: invokestatic a : (Ljava/lang/Throwable;)Ljava/lang/Throwable;
    //   1587: athrow
    //   1588: aload_3
    //   1589: getstatic burp/Zl15.ZI : Ljava/lang/String;
    //   1592: getstatic burp/Zs5k.Zg : Ljava/lang/Object;
    //   1595: checkcast java/math/BigInteger
    //   1598: invokevirtual intValue : ()I
    //   1601: bipush #32
    //   1603: irem
    //   1604: invokestatic abs : (I)I
    //   1607: invokevirtual charAt : (I)C
    //   1610: invokevirtual append : (C)Ljava/lang/StringBuilder;
    //   1613: pop
    //   1614: iload_2
    //   1615: ifeq -> 2028
    //   1618: goto -> 1625
    //   1621: invokestatic a : (Ljava/lang/Throwable;)Ljava/lang/Throwable;
    //   1624: athrow
    //   1625: aload_3
    //   1626: getstatic burp/Zty5.Za : Ljava/lang/String;
    //   1629: getstatic burp/Zzxa.ZI : Ljava/lang/Object;
    //   1632: checkcast java/math/BigInteger
    //   1635: invokevirtual intValue : ()I
    //   1638: bipush #32
    //   1640: irem
    //   1641: invokestatic abs : (I)I
    //   1644: invokevirtual charAt : (I)C
    //   1647: invokevirtual append : (C)Ljava/lang/StringBuilder;
    //   1650: pop
    //   1651: iload_2
    //   1652: ifeq -> 2028
    //   1655: goto -> 1662
    //   1658: invokestatic a : (Ljava/lang/Throwable;)Ljava/lang/Throwable;
    //   1661: athrow
    //   1662: aload_3
    //   1663: getstatic burp/Zrdo.Zj : Ljava/lang/String;
    //   1666: getstatic burp/Zre4.Zx : Ljava/lang/Object;
    //   1669: checkcast java/math/BigInteger
    //   1672: invokevirtual intValue : ()I
    //   1675: bipush #32
    //   1677: irem
    //   1678: invokestatic abs : (I)I
    //   1681: invokevirtual charAt : (I)C
    //   1684: invokevirtual append : (C)Ljava/lang/StringBuilder;
    //   1687: pop
    //   1688: iload_2
    //   1689: ifeq -> 2028
    //   1692: goto -> 1699
    //   1695: invokestatic a : (Ljava/lang/Throwable;)Ljava/lang/Throwable;
    //   1698: athrow
    //   1699: aload_3
    //   1700: getstatic burp/Zzr5.Zg : Ljava/lang/String;
    //   1703: getstatic burp/Zex.ZO : Ljava/lang/Object;
    //   1706: checkcast java/math/BigInteger
    //   1709: invokevirtual intValue : ()I
    //   1712: bipush #32
    //   1714: irem
    //   1715: invokestatic abs : (I)I
    //   1718: invokevirtual charAt : (I)C
    //   1721: invokevirtual append : (C)Ljava/lang/StringBuilder;
    //   1724: pop
    //   1725: iload_2
    //   1726: ifeq -> 2028
    //   1729: goto -> 1736
    //   1732: invokestatic a : (Ljava/lang/Throwable;)Ljava/lang/Throwable;
    //   1735: athrow
    //   1736: aload_3
    //   1737: getstatic burp/Zl88.Zd : Ljava/lang/String;
    //   1740: getstatic burp/Zs56.ZC : Ljava/lang/Object;
    //   1743: checkcast java/math/BigInteger
    //   1746: invokevirtual intValue : ()I
    //   1749: bipush #32
    //   1751: irem
    //   1752: invokestatic abs : (I)I
    //   1755: invokevirtual charAt : (I)C
    //   1758: invokevirtual append : (C)Ljava/lang/StringBuilder;
    //   1761: pop
    //   1762: iload_2
    //   1763: ifeq -> 2028
    //   1766: goto -> 1773
    //   1769: invokestatic a : (Ljava/lang/Throwable;)Ljava/lang/Throwable;
    //   1772: athrow
    //   1773: aload_3
    //   1774: getstatic burp/Zkul.ZJ : Ljava/lang/String;
    //   1777: getstatic burp/Zbu6.ZJ : Ljava/lang/Object;
    //   1780: checkcast java/math/BigInteger
    //   1783: invokevirtual intValue : ()I
    //   1786: bipush #32
    //   1788: irem
    //   1789: invokestatic abs : (I)I
    //   1792: invokevirtual charAt : (I)C
    //   1795: invokevirtual append : (C)Ljava/lang/StringBuilder;
    //   1798: pop
    //   1799: iload_2
    //   1800: ifeq -> 2028
    //   1803: goto -> 1810
    //   1806: invokestatic a : (Ljava/lang/Throwable;)Ljava/lang/Throwable;
    //   1809: athrow
    //   1810: aload_3
    //   1811: getstatic burp/Zep1.ZQ : Ljava/lang/String;
    //   1814: getstatic burp/Zkjr.Zw : Ljava/lang/Object;
    //   1817: checkcast java/math/BigInteger
    //   1820: invokevirtual intValue : ()I
    //   1823: bipush #32
    //   1825: irem
    //   1826: invokestatic abs : (I)I
    //   1829: invokevirtual charAt : (I)C
    //   1832: invokevirtual append : (C)Ljava/lang/StringBuilder;
    //   1835: pop
    //   1836: iload_2
    //   1837: ifeq -> 2028
    //   1840: goto -> 1847
    //   1843: invokestatic a : (Ljava/lang/Throwable;)Ljava/lang/Throwable;
    //   1846: athrow
    //   1847: aload_3
    //   1848: getstatic burp/Zljx.ZD : Ljava/lang/String;
    //   1851: getstatic burp/Zebu.Zu : Ljava/lang/Object;
    //   1854: checkcast java/math/BigInteger
    //   1857: invokevirtual intValue : ()I
    //   1860: bipush #32
    //   1862: irem
    //   1863: invokestatic abs : (I)I
    //   1866: invokevirtual charAt : (I)C
    //   1869: invokevirtual append : (C)Ljava/lang/StringBuilder;
    //   1872: pop
    //   1873: iload_2
    //   1874: ifeq -> 2028
    //   1877: goto -> 1884
    //   1880: invokestatic a : (Ljava/lang/Throwable;)Ljava/lang/Throwable;
    //   1883: athrow
    //   1884: aload_3
    //   1885: getstatic burp/Ztv8.ZJ : Ljava/lang/String;
    //   1888: getstatic burp/Zm0s.Zl : Ljava/lang/Object;
    //   1891: checkcast java/math/BigInteger
    //   1894: invokevirtual intValue : ()I
    //   1897: bipush #32
    //   1899: irem
    //   1900: invokestatic abs : (I)I
    //   1903: invokevirtual charAt : (I)C
    //   1906: invokevirtual append : (C)Ljava/lang/StringBuilder;
    //   1909: pop
    //   1910: iload_2
    //   1911: ifeq -> 2028
    //   1914: goto -> 1921
    //   1917: invokestatic a : (Ljava/lang/Throwable;)Ljava/lang/Throwable;
    //   1920: athrow
    //   1921: aload_3
    //   1922: getstatic burp/Zek5.ZE : Ljava/lang/String;
    //   1925: getstatic burp/Zgrf.ZN : Ljava/lang/Object;
    //   1928: checkcast java/math/BigInteger
    //   1931: invokevirtual intValue : ()I
    //   1934: bipush #32
    //   1936: irem
    //   1937: invokestatic abs : (I)I
    //   1940: invokevirtual charAt : (I)C
    //   1943: invokevirtual append : (C)Ljava/lang/StringBuilder;
    //   1946: pop
    //   1947: iload_2
    //   1948: ifeq -> 2028
    //   1951: goto -> 1958
    //   1954: invokestatic a : (Ljava/lang/Throwable;)Ljava/lang/Throwable;
    //   1957: athrow
    //   1958: aload_3
    //   1959: getstatic burp/Zlot.ZD : Ljava/lang/String;
    //   1962: getstatic burp/Zkco.Zg : Ljava/lang/Object;
    //   1965: checkcast java/math/BigInteger
    //   1968: invokevirtual intValue : ()I
    //   1971: bipush #32
    //   1973: irem
    //   1974: invokestatic abs : (I)I
    //   1977: invokevirtual charAt : (I)C
    //   1980: invokevirtual append : (C)Ljava/lang/StringBuilder;
    //   1983: pop
    //   1984: iload_2
    //   1985: ifeq -> 2028
    //   1988: goto -> 1995
    //   1991: invokestatic a : (Ljava/lang/Throwable;)Ljava/lang/Throwable;
    //   1994: athrow
    //   1995: aload_3
    //   1996: getstatic burp/Zl8y.ZY : Ljava/lang/String;
    //   1999: getstatic burp/Zlpn.ZU : Ljava/lang/Object;
    //   2002: checkcast java/math/BigInteger
    //   2005: invokevirtual intValue : ()I
    //   2008: bipush #32
    //   2010: irem
    //   2011: invokestatic abs : (I)I
    //   2014: invokevirtual charAt : (I)C
    //   2017: invokevirtual append : (C)Ljava/lang/StringBuilder;
    //   2020: pop
    //   2021: goto -> 2028
    //   2024: invokestatic a : (Ljava/lang/Throwable;)Ljava/lang/Throwable;
    //   2027: athrow
    //   2028: iinc #4, 1
    //   2031: iload_2
    //   2032: ifeq -> 697
    //   2035: aload_3
    //   2036: invokevirtual toString : ()Ljava/lang/String;
    //   2039: putstatic burp/Zg3m.Za : Ljava/lang/String;
    //   2042: getstatic burp/Zltb.ZL : Ljava/lang/Object;
    //   2045: checkcast java/math/BigInteger
    //   2048: invokevirtual toByteArray : ()[B
    //   2051: astore #4
    //   2053: bipush #32
    //   2055: newarray int
    //   2057: dup
    //   2058: iconst_0
    //   2059: ldc 943331329
    //   2061: iastore
    //   2062: dup
    //   2063: iconst_1
    //   2064: ldc 170788368
    //   2066: iastore
    //   2067: dup
    //   2068: iconst_2
    //   2069: ldc 1008414755
    //   2071: iastore
    //   2072: dup
    //   2073: iconst_3
    //   2074: ldc 187049985
    //   2076: iastore
    //   2077: dup
    //   2078: iconst_4
    //   2079: ldc 1010368540
    //   2081: iastore
    //   2082: dup
    //   2083: iconst_5
    //   2084: ldc 220604441
    //   2086: iastore
    //   2087: dup
    //   2088: bipush #6
    //   2090: ldc 940377620
    //   2092: iastore
    //   2093: dup
    //   2094: bipush #7
    //   2096: ldc 255209728
    //   2098: iastore
    //   2099: dup
    //   2100: bipush #8
    //   2102: ldc 689771012
    //   2104: iastore
    //   2105: dup
    //   2106: bipush #9
    //   2108: ldc 221709344
    //   2110: iastore
    //   2111: dup
    //   2112: bipush #10
    //   2114: ldc 957157408
    //   2116: iastore
    //   2117: dup
    //   2118: bipush #11
    //   2120: ldc 892536332
    //   2122: iastore
    //   2123: dup
    //   2124: bipush #12
    //   2126: ldc 722417666
    //   2128: iastore
    //   2129: dup
    //   2130: bipush #13
    //   2132: ldc 1026621720
    //   2134: iastore
    //   2135: dup
    //   2136: bipush #14
    //   2138: ldc 655302664
    //   2140: iastore
    //   2141: dup
    //   2142: bipush #15
    //   2144: ldc 890966315
    //   2146: iastore
    //   2147: dup
    //   2148: bipush #16
    //   2150: ldc 187632156
    //   2152: iastore
    //   2153: dup
    //   2154: bipush #17
    //   2156: ldc 874189824
    //   2158: iastore
    //   2159: dup
    //   2160: bipush #18
    //   2162: ldc 254150144
    //   2164: iastore
    //   2165: dup
    //   2166: bipush #19
    //   2168: ldc 924386310
    //   2170: iastore
    //   2171: dup
    //   2172: bipush #20
    //   2174: ldc 121057538
    //   2176: iastore
    //   2177: dup
    //   2178: bipush #21
    //   2180: ldc 840500228
    //   2182: iastore
    //   2183: dup
    //   2184: bipush #22
    //   2186: ldc 389160971
    //   2188: iastore
    //   2189: dup
    //   2190: bipush #23
    //   2192: ldc 907870729
    //   2194: iastore
    //   2195: dup
    //   2196: bipush #24
    //   2198: ldc 389426184
    //   2200: iastore
    //   2201: dup
    //   2202: bipush #25
    //   2204: ldc 973875457
    //   2206: iastore
    //   2207: dup
    //   2208: bipush #26
    //   2210: ldc 372376604
    //   2212: iastore
    //   2213: dup
    //   2214: bipush #27
    //   2216: ldc 707731490
    //   2218: iastore
    //   2219: dup
    //   2220: bipush #28
    //   2222: ldc 1043334948
    //   2224: iastore
    //   2225: dup
    //   2226: bipush #29
    //   2228: ldc 439222784
    //   2230: iastore
    //   2231: dup
    //   2232: bipush #30
    //   2234: ldc 876216579
    //   2236: iastore
    //   2237: dup
    //   2238: bipush #31
    //   2240: ldc 455999525
    //   2242: iastore
    //   2243: astore #6
    //   2245: bipush #8
    //   2247: aload #4
    //   2249: arraylength
    //   2250: bipush #8
    //   2252: irem
    //   2253: isub
    //   2254: istore #7
    //   2256: aload #4
    //   2258: arraylength
    //   2259: iload #7
    //   2261: iadd
    //   2262: newarray byte
    //   2264: astore #8
    //   2266: iconst_0
    //   2267: istore #9
    //   2269: iload #9
    //   2271: aload #4
    //   2273: arraylength
    //   2274: if_icmpge -> 2294
    //   2277: aload #8
    //   2279: iload #9
    //   2281: aload #4
    //   2283: iload #9
    //   2285: baload
    //   2286: bastore
    //   2287: iinc #9, 1
    //   2290: iload_2
    //   2291: ifeq -> 2269
    //   2294: aload #4
    //   2296: arraylength
    //   2297: istore #9
    //   2299: iload #9
    //   2301: aload #8
    //   2303: arraylength
    //   2304: if_icmpge -> 2322
    //   2307: aload #8
    //   2309: iload #9
    //   2311: iload #7
    //   2313: i2b
    //   2314: bastore
    //   2315: iinc #9, 1
    //   2318: iload_2
    //   2319: ifeq -> 2299
    //   2322: aload #8
    //   2324: astore #4
    //   2326: bipush #64
    //   2328: newarray int
    //   2330: dup
    //   2331: iconst_0
    //   2332: ldc 16843776
    //   2334: iastore
    //   2335: dup
    //   2336: iconst_1
    //   2337: iconst_0
    //   2338: iastore
    //   2339: dup
    //   2340: iconst_2
    //   2341: ldc 65536
    //   2343: iastore
    //   2344: dup
    //   2345: iconst_3
    //   2346: ldc 16843780
    //   2348: iastore
    //   2349: dup
    //   2350: iconst_4
    //   2351: ldc 16842756
    //   2353: iastore
    //   2354: dup
    //   2355: iconst_5
    //   2356: ldc 66564
    //   2358: iastore
    //   2359: dup
    //   2360: bipush #6
    //   2362: iconst_4
    //   2363: iastore
    //   2364: dup
    //   2365: bipush #7
    //   2367: ldc 65536
    //   2369: iastore
    //   2370: dup
    //   2371: bipush #8
    //   2373: sipush #1024
    //   2376: iastore
    //   2377: dup
    //   2378: bipush #9
    //   2380: ldc 16843776
    //   2382: iastore
    //   2383: dup
    //   2384: bipush #10
    //   2386: ldc 16843780
    //   2388: iastore
    //   2389: dup
    //   2390: bipush #11
    //   2392: sipush #1024
    //   2395: iastore
    //   2396: dup
    //   2397: bipush #12
    //   2399: ldc 16778244
    //   2401: iastore
    //   2402: dup
    //   2403: bipush #13
    //   2405: ldc 16842756
    //   2407: iastore
    //   2408: dup
    //   2409: bipush #14
    //   2411: ldc 16777216
    //   2413: iastore
    //   2414: dup
    //   2415: bipush #15
    //   2417: iconst_4
    //   2418: iastore
    //   2419: dup
    //   2420: bipush #16
    //   2422: sipush #1028
    //   2425: iastore
    //   2426: dup
    //   2427: bipush #17
    //   2429: ldc 16778240
    //   2431: iastore
    //   2432: dup
    //   2433: bipush #18
    //   2435: ldc 16778240
    //   2437: iastore
    //   2438: dup
    //   2439: bipush #19
    //   2441: ldc 66560
    //   2443: iastore
    //   2444: dup
    //   2445: bipush #20
    //   2447: ldc 66560
    //   2449: iastore
    //   2450: dup
    //   2451: bipush #21
    //   2453: ldc 16842752
    //   2455: iastore
    //   2456: dup
    //   2457: bipush #22
    //   2459: ldc 16842752
    //   2461: iastore
    //   2462: dup
    //   2463: bipush #23
    //   2465: ldc 16778244
    //   2467: iastore
    //   2468: dup
    //   2469: bipush #24
    //   2471: ldc 65540
    //   2473: iastore
    //   2474: dup
    //   2475: bipush #25
    //   2477: ldc 16777220
    //   2479: iastore
    //   2480: dup
    //   2481: bipush #26
    //   2483: ldc 16777220
    //   2485: iastore
    //   2486: dup
    //   2487: bipush #27
    //   2489: ldc 65540
    //   2491: iastore
    //   2492: dup
    //   2493: bipush #28
    //   2495: iconst_0
    //   2496: iastore
    //   2497: dup
    //   2498: bipush #29
    //   2500: sipush #1028
    //   2503: iastore
    //   2504: dup
    //   2505: bipush #30
    //   2507: ldc 66564
    //   2509: iastore
    //   2510: dup
    //   2511: bipush #31
    //   2513: ldc 16777216
    //   2515: iastore
    //   2516: dup
    //   2517: bipush #32
    //   2519: ldc 65536
    //   2521: iastore
    //   2522: dup
    //   2523: bipush #33
    //   2525: ldc 16843780
    //   2527: iastore
    //   2528: dup
    //   2529: bipush #34
    //   2531: iconst_4
    //   2532: iastore
    //   2533: dup
    //   2534: bipush #35
    //   2536: ldc 16842752
    //   2538: iastore
    //   2539: dup
    //   2540: bipush #36
    //   2542: ldc 16843776
    //   2544: iastore
    //   2545: dup
    //   2546: bipush #37
    //   2548: ldc 16777216
    //   2550: iastore
    //   2551: dup
    //   2552: bipush #38
    //   2554: ldc 16777216
    //   2556: iastore
    //   2557: dup
    //   2558: bipush #39
    //   2560: sipush #1024
    //   2563: iastore
    //   2564: dup
    //   2565: bipush #40
    //   2567: ldc 16842756
    //   2569: iastore
    //   2570: dup
    //   2571: bipush #41
    //   2573: ldc 65536
    //   2575: iastore
    //   2576: dup
    //   2577: bipush #42
    //   2579: ldc 66560
    //   2581: iastore
    //   2582: dup
    //   2583: bipush #43
    //   2585: ldc 16777220
    //   2587: iastore
    //   2588: dup
    //   2589: bipush #44
    //   2591: sipush #1024
    //   2594: iastore
    //   2595: dup
    //   2596: bipush #45
    //   2598: iconst_4
    //   2599: iastore
    //   2600: dup
    //   2601: bipush #46
    //   2603: ldc 16778244
    //   2605: iastore
    //   2606: dup
    //   2607: bipush #47
    //   2609: ldc 66564
    //   2611: iastore
    //   2612: dup
    //   2613: bipush #48
    //   2615: ldc 16843780
    //   2617: iastore
    //   2618: dup
    //   2619: bipush #49
    //   2621: ldc 65540
    //   2623: iastore
    //   2624: dup
    //   2625: bipush #50
    //   2627: ldc 16842752
    //   2629: iastore
    //   2630: dup
    //   2631: bipush #51
    //   2633: ldc 16778244
    //   2635: iastore
    //   2636: dup
    //   2637: bipush #52
    //   2639: ldc 16777220
    //   2641: iastore
    //   2642: dup
    //   2643: bipush #53
    //   2645: sipush #1028
    //   2648: iastore
    //   2649: dup
    //   2650: bipush #54
    //   2652: ldc 66564
    //   2654: iastore
    //   2655: dup
    //   2656: bipush #55
    //   2658: ldc 16843776
    //   2660: iastore
    //   2661: dup
    //   2662: bipush #56
    //   2664: sipush #1028
    //   2667: iastore
    //   2668: dup
    //   2669: bipush #57
    //   2671: ldc 16778240
    //   2673: iastore
    //   2674: dup
    //   2675: bipush #58
    //   2677: ldc 16778240
    //   2679: iastore
    //   2680: dup
    //   2681: bipush #59
    //   2683: iconst_0
    //   2684: iastore
    //   2685: dup
    //   2686: bipush #60
    //   2688: ldc 65540
    //   2690: iastore
    //   2691: dup
    //   2692: bipush #61
    //   2694: ldc 66560
    //   2696: iastore
    //   2697: dup
    //   2698: bipush #62
    //   2700: iconst_0
    //   2701: iastore
    //   2702: dup
    //   2703: bipush #63
    //   2705: ldc 16842756
    //   2707: iastore
    //   2708: astore #9
    //   2710: bipush #64
    //   2712: newarray int
    //   2714: dup
    //   2715: iconst_0
    //   2716: ldc -2146402272
    //   2718: iastore
    //   2719: dup
    //   2720: iconst_1
    //   2721: ldc -2147450880
    //   2723: iastore
    //   2724: dup
    //   2725: iconst_2
    //   2726: ldc 32768
    //   2728: iastore
    //   2729: dup
    //   2730: iconst_3
    //   2731: ldc 1081376
    //   2733: iastore
    //   2734: dup
    //   2735: iconst_4
    //   2736: ldc 1048576
    //   2738: iastore
    //   2739: dup
    //   2740: iconst_5
    //   2741: bipush #32
    //   2743: iastore
    //   2744: dup
    //   2745: bipush #6
    //   2747: ldc -2146435040
    //   2749: iastore
    //   2750: dup
    //   2751: bipush #7
    //   2753: ldc -2147450848
    //   2755: iastore
    //   2756: dup
    //   2757: bipush #8
    //   2759: ldc -2147483616
    //   2761: iastore
    //   2762: dup
    //   2763: bipush #9
    //   2765: ldc -2146402272
    //   2767: iastore
    //   2768: dup
    //   2769: bipush #10
    //   2771: ldc -2146402304
    //   2773: iastore
    //   2774: dup
    //   2775: bipush #11
    //   2777: ldc -2147483648
    //   2779: iastore
    //   2780: dup
    //   2781: bipush #12
    //   2783: ldc -2147450880
    //   2785: iastore
    //   2786: dup
    //   2787: bipush #13
    //   2789: ldc 1048576
    //   2791: iastore
    //   2792: dup
    //   2793: bipush #14
    //   2795: bipush #32
    //   2797: iastore
    //   2798: dup
    //   2799: bipush #15
    //   2801: ldc -2146435040
    //   2803: iastore
    //   2804: dup
    //   2805: bipush #16
    //   2807: ldc 1081344
    //   2809: iastore
    //   2810: dup
    //   2811: bipush #17
    //   2813: ldc 1048608
    //   2815: iastore
    //   2816: dup
    //   2817: bipush #18
    //   2819: ldc -2147450848
    //   2821: iastore
    //   2822: dup
    //   2823: bipush #19
    //   2825: iconst_0
    //   2826: iastore
    //   2827: dup
    //   2828: bipush #20
    //   2830: ldc -2147483648
    //   2832: iastore
    //   2833: dup
    //   2834: bipush #21
    //   2836: ldc 32768
    //   2838: iastore
    //   2839: dup
    //   2840: bipush #22
    //   2842: ldc 1081376
    //   2844: iastore
    //   2845: dup
    //   2846: bipush #23
    //   2848: ldc -2146435072
    //   2850: iastore
    //   2851: dup
    //   2852: bipush #24
    //   2854: ldc 1048608
    //   2856: iastore
    //   2857: dup
    //   2858: bipush #25
    //   2860: ldc -2147483616
    //   2862: iastore
    //   2863: dup
    //   2864: bipush #26
    //   2866: iconst_0
    //   2867: iastore
    //   2868: dup
    //   2869: bipush #27
    //   2871: ldc 1081344
    //   2873: iastore
    //   2874: dup
    //   2875: bipush #28
    //   2877: ldc 32800
    //   2879: iastore
    //   2880: dup
    //   2881: bipush #29
    //   2883: ldc -2146402304
    //   2885: iastore
    //   2886: dup
    //   2887: bipush #30
    //   2889: ldc -2146435072
    //   2891: iastore
    //   2892: dup
    //   2893: bipush #31
    //   2895: ldc 32800
    //   2897: iastore
    //   2898: dup
    //   2899: bipush #32
    //   2901: iconst_0
    //   2902: iastore
    //   2903: dup
    //   2904: bipush #33
    //   2906: ldc 1081376
    //   2908: iastore
    //   2909: dup
    //   2910: bipush #34
    //   2912: ldc -2146435040
    //   2914: iastore
    //   2915: dup
    //   2916: bipush #35
    //   2918: ldc 1048576
    //   2920: iastore
    //   2921: dup
    //   2922: bipush #36
    //   2924: ldc -2147450848
    //   2926: iastore
    //   2927: dup
    //   2928: bipush #37
    //   2930: ldc -2146435072
    //   2932: iastore
    //   2933: dup
    //   2934: bipush #38
    //   2936: ldc -2146402304
    //   2938: iastore
    //   2939: dup
    //   2940: bipush #39
    //   2942: ldc 32768
    //   2944: iastore
    //   2945: dup
    //   2946: bipush #40
    //   2948: ldc -2146435072
    //   2950: iastore
    //   2951: dup
    //   2952: bipush #41
    //   2954: ldc -2147450880
    //   2956: iastore
    //   2957: dup
    //   2958: bipush #42
    //   2960: bipush #32
    //   2962: iastore
    //   2963: dup
    //   2964: bipush #43
    //   2966: ldc -2146402272
    //   2968: iastore
    //   2969: dup
    //   2970: bipush #44
    //   2972: ldc 1081376
    //   2974: iastore
    //   2975: dup
    //   2976: bipush #45
    //   2978: bipush #32
    //   2980: iastore
    //   2981: dup
    //   2982: bipush #46
    //   2984: ldc 32768
    //   2986: iastore
    //   2987: dup
    //   2988: bipush #47
    //   2990: ldc -2147483648
    //   2992: iastore
    //   2993: dup
    //   2994: bipush #48
    //   2996: ldc 32800
    //   2998: iastore
    //   2999: dup
    //   3000: bipush #49
    //   3002: ldc -2146402304
    //   3004: iastore
    //   3005: dup
    //   3006: bipush #50
    //   3008: ldc 1048576
    //   3010: iastore
    //   3011: dup
    //   3012: bipush #51
    //   3014: ldc -2147483616
    //   3016: iastore
    //   3017: dup
    //   3018: bipush #52
    //   3020: ldc 1048608
    //   3022: iastore
    //   3023: dup
    //   3024: bipush #53
    //   3026: ldc -2147450848
    //   3028: iastore
    //   3029: dup
    //   3030: bipush #54
    //   3032: ldc -2147483616
    //   3034: iastore
    //   3035: dup
    //   3036: bipush #55
    //   3038: ldc 1048608
    //   3040: iastore
    //   3041: dup
    //   3042: bipush #56
    //   3044: ldc 1081344
    //   3046: iastore
    //   3047: dup
    //   3048: bipush #57
    //   3050: iconst_0
    //   3051: iastore
    //   3052: dup
    //   3053: bipush #58
    //   3055: ldc -2147450880
    //   3057: iastore
    //   3058: dup
    //   3059: bipush #59
    //   3061: ldc 32800
    //   3063: iastore
    //   3064: dup
    //   3065: bipush #60
    //   3067: ldc -2147483648
    //   3069: iastore
    //   3070: dup
    //   3071: bipush #61
    //   3073: ldc -2146435040
    //   3075: iastore
    //   3076: dup
    //   3077: bipush #62
    //   3079: ldc -2146402272
    //   3081: iastore
    //   3082: dup
    //   3083: bipush #63
    //   3085: ldc 1081344
    //   3087: iastore
    //   3088: astore #10
    //   3090: bipush #64
    //   3092: newarray int
    //   3094: dup
    //   3095: iconst_0
    //   3096: sipush #520
    //   3099: iastore
    //   3100: dup
    //   3101: iconst_1
    //   3102: ldc 134349312
    //   3104: iastore
    //   3105: dup
    //   3106: iconst_2
    //   3107: iconst_0
    //   3108: iastore
    //   3109: dup
    //   3110: iconst_3
    //   3111: ldc 134348808
    //   3113: iastore
    //   3114: dup
    //   3115: iconst_4
    //   3116: ldc 134218240
    //   3118: iastore
    //   3119: dup
    //   3120: iconst_5
    //   3121: iconst_0
    //   3122: iastore
    //   3123: dup
    //   3124: bipush #6
    //   3126: ldc 131592
    //   3128: iastore
    //   3129: dup
    //   3130: bipush #7
    //   3132: ldc 134218240
    //   3134: iastore
    //   3135: dup
    //   3136: bipush #8
    //   3138: ldc 131080
    //   3140: iastore
    //   3141: dup
    //   3142: bipush #9
    //   3144: ldc 134217736
    //   3146: iastore
    //   3147: dup
    //   3148: bipush #10
    //   3150: ldc 134217736
    //   3152: iastore
    //   3153: dup
    //   3154: bipush #11
    //   3156: ldc 131072
    //   3158: iastore
    //   3159: dup
    //   3160: bipush #12
    //   3162: ldc 134349320
    //   3164: iastore
    //   3165: dup
    //   3166: bipush #13
    //   3168: ldc 131080
    //   3170: iastore
    //   3171: dup
    //   3172: bipush #14
    //   3174: ldc 134348800
    //   3176: iastore
    //   3177: dup
    //   3178: bipush #15
    //   3180: sipush #520
    //   3183: iastore
    //   3184: dup
    //   3185: bipush #16
    //   3187: ldc 134217728
    //   3189: iastore
    //   3190: dup
    //   3191: bipush #17
    //   3193: bipush #8
    //   3195: iastore
    //   3196: dup
    //   3197: bipush #18
    //   3199: ldc 134349312
    //   3201: iastore
    //   3202: dup
    //   3203: bipush #19
    //   3205: sipush #512
    //   3208: iastore
    //   3209: dup
    //   3210: bipush #20
    //   3212: ldc 131584
    //   3214: iastore
    //   3215: dup
    //   3216: bipush #21
    //   3218: ldc 134348800
    //   3220: iastore
    //   3221: dup
    //   3222: bipush #22
    //   3224: ldc 134348808
    //   3226: iastore
    //   3227: dup
    //   3228: bipush #23
    //   3230: ldc 131592
    //   3232: iastore
    //   3233: dup
    //   3234: bipush #24
    //   3236: ldc 134218248
    //   3238: iastore
    //   3239: dup
    //   3240: bipush #25
    //   3242: ldc 131584
    //   3244: iastore
    //   3245: dup
    //   3246: bipush #26
    //   3248: ldc 131072
    //   3250: iastore
    //   3251: dup
    //   3252: bipush #27
    //   3254: ldc 134218248
    //   3256: iastore
    //   3257: dup
    //   3258: bipush #28
    //   3260: bipush #8
    //   3262: iastore
    //   3263: dup
    //   3264: bipush #29
    //   3266: ldc 134349320
    //   3268: iastore
    //   3269: dup
    //   3270: bipush #30
    //   3272: sipush #512
    //   3275: iastore
    //   3276: dup
    //   3277: bipush #31
    //   3279: ldc 134217728
    //   3281: iastore
    //   3282: dup
    //   3283: bipush #32
    //   3285: ldc 134349312
    //   3287: iastore
    //   3288: dup
    //   3289: bipush #33
    //   3291: ldc 134217728
    //   3293: iastore
    //   3294: dup
    //   3295: bipush #34
    //   3297: ldc 131080
    //   3299: iastore
    //   3300: dup
    //   3301: bipush #35
    //   3303: sipush #520
    //   3306: iastore
    //   3307: dup
    //   3308: bipush #36
    //   3310: ldc 131072
    //   3312: iastore
    //   3313: dup
    //   3314: bipush #37
    //   3316: ldc 134349312
    //   3318: iastore
    //   3319: dup
    //   3320: bipush #38
    //   3322: ldc 134218240
    //   3324: iastore
    //   3325: dup
    //   3326: bipush #39
    //   3328: iconst_0
    //   3329: iastore
    //   3330: dup
    //   3331: bipush #40
    //   3333: sipush #512
    //   3336: iastore
    //   3337: dup
    //   3338: bipush #41
    //   3340: ldc 131080
    //   3342: iastore
    //   3343: dup
    //   3344: bipush #42
    //   3346: ldc 134349320
    //   3348: iastore
    //   3349: dup
    //   3350: bipush #43
    //   3352: ldc 134218240
    //   3354: iastore
    //   3355: dup
    //   3356: bipush #44
    //   3358: ldc 134217736
    //   3360: iastore
    //   3361: dup
    //   3362: bipush #45
    //   3364: sipush #512
    //   3367: iastore
    //   3368: dup
    //   3369: bipush #46
    //   3371: iconst_0
    //   3372: iastore
    //   3373: dup
    //   3374: bipush #47
    //   3376: ldc 134348808
    //   3378: iastore
    //   3379: dup
    //   3380: bipush #48
    //   3382: ldc 134218248
    //   3384: iastore
    //   3385: dup
    //   3386: bipush #49
    //   3388: ldc 131072
    //   3390: iastore
    //   3391: dup
    //   3392: bipush #50
    //   3394: ldc 134217728
    //   3396: iastore
    //   3397: dup
    //   3398: bipush #51
    //   3400: ldc 134349320
    //   3402: iastore
    //   3403: dup
    //   3404: bipush #52
    //   3406: bipush #8
    //   3408: iastore
    //   3409: dup
    //   3410: bipush #53
    //   3412: ldc 131592
    //   3414: iastore
    //   3415: dup
    //   3416: bipush #54
    //   3418: ldc 131584
    //   3420: iastore
    //   3421: dup
    //   3422: bipush #55
    //   3424: ldc 134217736
    //   3426: iastore
    //   3427: dup
    //   3428: bipush #56
    //   3430: ldc 134348800
    //   3432: iastore
    //   3433: dup
    //   3434: bipush #57
    //   3436: ldc 134218248
    //   3438: iastore
    //   3439: dup
    //   3440: bipush #58
    //   3442: sipush #520
    //   3445: iastore
    //   3446: dup
    //   3447: bipush #59
    //   3449: ldc 134348800
    //   3451: iastore
    //   3452: dup
    //   3453: bipush #60
    //   3455: ldc 131592
    //   3457: iastore
    //   3458: dup
    //   3459: bipush #61
    //   3461: bipush #8
    //   3463: iastore
    //   3464: dup
    //   3465: bipush #62
    //   3467: ldc 134348808
    //   3469: iastore
    //   3470: dup
    //   3471: bipush #63
    //   3473: ldc 131584
    //   3475: iastore
    //   3476: astore #11
    //   3478: bipush #64
    //   3480: newarray int
    //   3482: dup
    //   3483: iconst_0
    //   3484: ldc 8396801
    //   3486: iastore
    //   3487: dup
    //   3488: iconst_1
    //   3489: sipush #8321
    //   3492: iastore
    //   3493: dup
    //   3494: iconst_2
    //   3495: sipush #8321
    //   3498: iastore
    //   3499: dup
    //   3500: iconst_3
    //   3501: sipush #128
    //   3504: iastore
    //   3505: dup
    //   3506: iconst_4
    //   3507: ldc 8396928
    //   3509: iastore
    //   3510: dup
    //   3511: iconst_5
    //   3512: ldc 8388737
    //   3514: iastore
    //   3515: dup
    //   3516: bipush #6
    //   3518: ldc 8388609
    //   3520: iastore
    //   3521: dup
    //   3522: bipush #7
    //   3524: sipush #8193
    //   3527: iastore
    //   3528: dup
    //   3529: bipush #8
    //   3531: iconst_0
    //   3532: iastore
    //   3533: dup
    //   3534: bipush #9
    //   3536: ldc 8396800
    //   3538: iastore
    //   3539: dup
    //   3540: bipush #10
    //   3542: ldc 8396800
    //   3544: iastore
    //   3545: dup
    //   3546: bipush #11
    //   3548: ldc 8396929
    //   3550: iastore
    //   3551: dup
    //   3552: bipush #12
    //   3554: sipush #129
    //   3557: iastore
    //   3558: dup
    //   3559: bipush #13
    //   3561: iconst_0
    //   3562: iastore
    //   3563: dup
    //   3564: bipush #14
    //   3566: ldc 8388736
    //   3568: iastore
    //   3569: dup
    //   3570: bipush #15
    //   3572: ldc 8388609
    //   3574: iastore
    //   3575: dup
    //   3576: bipush #16
    //   3578: iconst_1
    //   3579: iastore
    //   3580: dup
    //   3581: bipush #17
    //   3583: sipush #8192
    //   3586: iastore
    //   3587: dup
    //   3588: bipush #18
    //   3590: ldc 8388608
    //   3592: iastore
    //   3593: dup
    //   3594: bipush #19
    //   3596: ldc 8396801
    //   3598: iastore
    //   3599: dup
    //   3600: bipush #20
    //   3602: sipush #128
    //   3605: iastore
    //   3606: dup
    //   3607: bipush #21
    //   3609: ldc 8388608
    //   3611: iastore
    //   3612: dup
    //   3613: bipush #22
    //   3615: sipush #8193
    //   3618: iastore
    //   3619: dup
    //   3620: bipush #23
    //   3622: sipush #8320
    //   3625: iastore
    //   3626: dup
    //   3627: bipush #24
    //   3629: ldc 8388737
    //   3631: iastore
    //   3632: dup
    //   3633: bipush #25
    //   3635: iconst_1
    //   3636: iastore
    //   3637: dup
    //   3638: bipush #26
    //   3640: sipush #8320
    //   3643: iastore
    //   3644: dup
    //   3645: bipush #27
    //   3647: ldc 8388736
    //   3649: iastore
    //   3650: dup
    //   3651: bipush #28
    //   3653: sipush #8192
    //   3656: iastore
    //   3657: dup
    //   3658: bipush #29
    //   3660: ldc 8396928
    //   3662: iastore
    //   3663: dup
    //   3664: bipush #30
    //   3666: ldc 8396929
    //   3668: iastore
    //   3669: dup
    //   3670: bipush #31
    //   3672: sipush #129
    //   3675: iastore
    //   3676: dup
    //   3677: bipush #32
    //   3679: ldc 8388736
    //   3681: iastore
    //   3682: dup
    //   3683: bipush #33
    //   3685: ldc 8388609
    //   3687: iastore
    //   3688: dup
    //   3689: bipush #34
    //   3691: ldc 8396800
    //   3693: iastore
    //   3694: dup
    //   3695: bipush #35
    //   3697: ldc 8396929
    //   3699: iastore
    //   3700: dup
    //   3701: bipush #36
    //   3703: sipush #129
    //   3706: iastore
    //   3707: dup
    //   3708: bipush #37
    //   3710: iconst_0
    //   3711: iastore
    //   3712: dup
    //   3713: bipush #38
    //   3715: iconst_0
    //   3716: iastore
    //   3717: dup
    //   3718: bipush #39
    //   3720: ldc 8396800
    //   3722: iastore
    //   3723: dup
    //   3724: bipush #40
    //   3726: sipush #8320
    //   3729: iastore
    //   3730: dup
    //   3731: bipush #41
    //   3733: ldc 8388736
    //   3735: iastore
    //   3736: dup
    //   3737: bipush #42
    //   3739: ldc 8388737
    //   3741: iastore
    //   3742: dup
    //   3743: bipush #43
    //   3745: iconst_1
    //   3746: iastore
    //   3747: dup
    //   3748: bipush #44
    //   3750: ldc 8396801
    //   3752: iastore
    //   3753: dup
    //   3754: bipush #45
    //   3756: sipush #8321
    //   3759: iastore
    //   3760: dup
    //   3761: bipush #46
    //   3763: sipush #8321
    //   3766: iastore
    //   3767: dup
    //   3768: bipush #47
    //   3770: sipush #128
    //   3773: iastore
    //   3774: dup
    //   3775: bipush #48
    //   3777: ldc 8396929
    //   3779: iastore
    //   3780: dup
    //   3781: bipush #49
    //   3783: sipush #129
    //   3786: iastore
    //   3787: dup
    //   3788: bipush #50
    //   3790: iconst_1
    //   3791: iastore
    //   3792: dup
    //   3793: bipush #51
    //   3795: sipush #8192
    //   3798: iastore
    //   3799: dup
    //   3800: bipush #52
    //   3802: ldc 8388609
    //   3804: iastore
    //   3805: dup
    //   3806: bipush #53
    //   3808: sipush #8193
    //   3811: iastore
    //   3812: dup
    //   3813: bipush #54
    //   3815: ldc 8396928
    //   3817: iastore
    //   3818: dup
    //   3819: bipush #55
    //   3821: ldc 8388737
    //   3823: iastore
    //   3824: dup
    //   3825: bipush #56
    //   3827: sipush #8193
    //   3830: iastore
    //   3831: dup
    //   3832: bipush #57
    //   3834: sipush #8320
    //   3837: iastore
    //   3838: dup
    //   3839: bipush #58
    //   3841: ldc 8388608
    //   3843: iastore
    //   3844: dup
    //   3845: bipush #59
    //   3847: ldc 8396801
    //   3849: iastore
    //   3850: dup
    //   3851: bipush #60
    //   3853: sipush #128
    //   3856: iastore
    //   3857: dup
    //   3858: bipush #61
    //   3860: ldc 8388608
    //   3862: iastore
    //   3863: dup
    //   3864: bipush #62
    //   3866: sipush #8192
    //   3869: iastore
    //   3870: dup
    //   3871: bipush #63
    //   3873: ldc 8396928
    //   3875: iastore
    //   3876: astore #12
    //   3878: bipush #64
    //   3880: newarray int
    //   3882: dup
    //   3883: iconst_0
    //   3884: sipush #256
    //   3887: iastore
    //   3888: dup
    //   3889: iconst_1
    //   3890: ldc 34078976
    //   3892: iastore
    //   3893: dup
    //   3894: iconst_2
    //   3895: ldc 34078720
    //   3897: iastore
    //   3898: dup
    //   3899: iconst_3
    //   3900: ldc 1107296512
    //   3902: iastore
    //   3903: dup
    //   3904: iconst_4
    //   3905: ldc 524288
    //   3907: iastore
    //   3908: dup
    //   3909: iconst_5
    //   3910: sipush #256
    //   3913: iastore
    //   3914: dup
    //   3915: bipush #6
    //   3917: ldc 1073741824
    //   3919: iastore
    //   3920: dup
    //   3921: bipush #7
    //   3923: ldc 34078720
    //   3925: iastore
    //   3926: dup
    //   3927: bipush #8
    //   3929: ldc 1074266368
    //   3931: iastore
    //   3932: dup
    //   3933: bipush #9
    //   3935: ldc 524288
    //   3937: iastore
    //   3938: dup
    //   3939: bipush #10
    //   3941: ldc 33554688
    //   3943: iastore
    //   3944: dup
    //   3945: bipush #11
    //   3947: ldc 1074266368
    //   3949: iastore
    //   3950: dup
    //   3951: bipush #12
    //   3953: ldc 1107296512
    //   3955: iastore
    //   3956: dup
    //   3957: bipush #13
    //   3959: ldc 1107820544
    //   3961: iastore
    //   3962: dup
    //   3963: bipush #14
    //   3965: ldc 524544
    //   3967: iastore
    //   3968: dup
    //   3969: bipush #15
    //   3971: ldc 1073741824
    //   3973: iastore
    //   3974: dup
    //   3975: bipush #16
    //   3977: ldc 33554432
    //   3979: iastore
    //   3980: dup
    //   3981: bipush #17
    //   3983: ldc 1074266112
    //   3985: iastore
    //   3986: dup
    //   3987: bipush #18
    //   3989: ldc 1074266112
    //   3991: iastore
    //   3992: dup
    //   3993: bipush #19
    //   3995: iconst_0
    //   3996: iastore
    //   3997: dup
    //   3998: bipush #20
    //   4000: ldc 1073742080
    //   4002: iastore
    //   4003: dup
    //   4004: bipush #21
    //   4006: ldc 1107820800
    //   4008: iastore
    //   4009: dup
    //   4010: bipush #22
    //   4012: ldc 1107820800
    //   4014: iastore
    //   4015: dup
    //   4016: bipush #23
    //   4018: ldc 33554688
    //   4020: iastore
    //   4021: dup
    //   4022: bipush #24
    //   4024: ldc 1107820544
    //   4026: iastore
    //   4027: dup
    //   4028: bipush #25
    //   4030: ldc 1073742080
    //   4032: iastore
    //   4033: dup
    //   4034: bipush #26
    //   4036: iconst_0
    //   4037: iastore
    //   4038: dup
    //   4039: bipush #27
    //   4041: ldc 1107296256
    //   4043: iastore
    //   4044: dup
    //   4045: bipush #28
    //   4047: ldc 34078976
    //   4049: iastore
    //   4050: dup
    //   4051: bipush #29
    //   4053: ldc 33554432
    //   4055: iastore
    //   4056: dup
    //   4057: bipush #30
    //   4059: ldc 1107296256
    //   4061: iastore
    //   4062: dup
    //   4063: bipush #31
    //   4065: ldc 524544
    //   4067: iastore
    //   4068: dup
    //   4069: bipush #32
    //   4071: ldc 524288
    //   4073: iastore
    //   4074: dup
    //   4075: bipush #33
    //   4077: ldc 1107296512
    //   4079: iastore
    //   4080: dup
    //   4081: bipush #34
    //   4083: sipush #256
    //   4086: iastore
    //   4087: dup
    //   4088: bipush #35
    //   4090: ldc 33554432
    //   4092: iastore
    //   4093: dup
    //   4094: bipush #36
    //   4096: ldc 1073741824
    //   4098: iastore
    //   4099: dup
    //   4100: bipush #37
    //   4102: ldc 34078720
    //   4104: iastore
    //   4105: dup
    //   4106: bipush #38
    //   4108: ldc 1107296512
    //   4110: iastore
    //   4111: dup
    //   4112: bipush #39
    //   4114: ldc 1074266368
    //   4116: iastore
    //   4117: dup
    //   4118: bipush #40
    //   4120: ldc 33554688
    //   4122: iastore
    //   4123: dup
    //   4124: bipush #41
    //   4126: ldc 1073741824
    //   4128: iastore
    //   4129: dup
    //   4130: bipush #42
    //   4132: ldc 1107820544
    //   4134: iastore
    //   4135: dup
    //   4136: bipush #43
    //   4138: ldc 34078976
    //   4140: iastore
    //   4141: dup
    //   4142: bipush #44
    //   4144: ldc 1074266368
    //   4146: iastore
    //   4147: dup
    //   4148: bipush #45
    //   4150: sipush #256
    //   4153: iastore
    //   4154: dup
    //   4155: bipush #46
    //   4157: ldc 33554432
    //   4159: iastore
    //   4160: dup
    //   4161: bipush #47
    //   4163: ldc 1107820544
    //   4165: iastore
    //   4166: dup
    //   4167: bipush #48
    //   4169: ldc 1107820800
    //   4171: iastore
    //   4172: dup
    //   4173: bipush #49
    //   4175: ldc 524544
    //   4177: iastore
    //   4178: dup
    //   4179: bipush #50
    //   4181: ldc 1107296256
    //   4183: iastore
    //   4184: dup
    //   4185: bipush #51
    //   4187: ldc 1107820800
    //   4189: iastore
    //   4190: dup
    //   4191: bipush #52
    //   4193: ldc 34078720
    //   4195: iastore
    //   4196: dup
    //   4197: bipush #53
    //   4199: iconst_0
    //   4200: iastore
    //   4201: dup
    //   4202: bipush #54
    //   4204: ldc 1074266112
    //   4206: iastore
    //   4207: dup
    //   4208: bipush #55
    //   4210: ldc 1107296256
    //   4212: iastore
    //   4213: dup
    //   4214: bipush #56
    //   4216: ldc 524544
    //   4218: iastore
    //   4219: dup
    //   4220: bipush #57
    //   4222: ldc 33554688
    //   4224: iastore
    //   4225: dup
    //   4226: bipush #58
    //   4228: ldc 1073742080
    //   4230: iastore
    //   4231: dup
    //   4232: bipush #59
    //   4234: ldc 524288
    //   4236: iastore
    //   4237: dup
    //   4238: bipush #60
    //   4240: iconst_0
    //   4241: iastore
    //   4242: dup
    //   4243: bipush #61
    //   4245: ldc 1074266112
    //   4247: iastore
    //   4248: dup
    //   4249: bipush #62
    //   4251: ldc 34078976
    //   4253: iastore
    //   4254: dup
    //   4255: bipush #63
    //   4257: ldc 1073742080
    //   4259: iastore
    //   4260: astore #13
    //   4262: bipush #64
    //   4264: newarray int
    //   4266: dup
    //   4267: iconst_0
    //   4268: ldc 536870928
    //   4270: iastore
    //   4271: dup
    //   4272: iconst_1
    //   4273: ldc 541065216
    //   4275: iastore
    //   4276: dup
    //   4277: iconst_2
    //   4278: sipush #16384
    //   4281: iastore
    //   4282: dup
    //   4283: iconst_3
    //   4284: ldc 541081616
    //   4286: iastore
    //   4287: dup
    //   4288: iconst_4
    //   4289: ldc 541065216
    //   4291: iastore
    //   4292: dup
    //   4293: iconst_5
    //   4294: bipush #16
    //   4296: iastore
    //   4297: dup
    //   4298: bipush #6
    //   4300: ldc 541081616
    //   4302: iastore
    //   4303: dup
    //   4304: bipush #7
    //   4306: ldc 4194304
    //   4308: iastore
    //   4309: dup
    //   4310: bipush #8
    //   4312: ldc 536887296
    //   4314: iastore
    //   4315: dup
    //   4316: bipush #9
    //   4318: ldc 4210704
    //   4320: iastore
    //   4321: dup
    //   4322: bipush #10
    //   4324: ldc 4194304
    //   4326: iastore
    //   4327: dup
    //   4328: bipush #11
    //   4330: ldc 536870928
    //   4332: iastore
    //   4333: dup
    //   4334: bipush #12
    //   4336: ldc 4194320
    //   4338: iastore
    //   4339: dup
    //   4340: bipush #13
    //   4342: ldc 536887296
    //   4344: iastore
    //   4345: dup
    //   4346: bipush #14
    //   4348: ldc 536870912
    //   4350: iastore
    //   4351: dup
    //   4352: bipush #15
    //   4354: sipush #16400
    //   4357: iastore
    //   4358: dup
    //   4359: bipush #16
    //   4361: iconst_0
    //   4362: iastore
    //   4363: dup
    //   4364: bipush #17
    //   4366: ldc 4194320
    //   4368: iastore
    //   4369: dup
    //   4370: bipush #18
    //   4372: ldc 536887312
    //   4374: iastore
    //   4375: dup
    //   4376: bipush #19
    //   4378: sipush #16384
    //   4381: iastore
    //   4382: dup
    //   4383: bipush #20
    //   4385: ldc 4210688
    //   4387: iastore
    //   4388: dup
    //   4389: bipush #21
    //   4391: ldc 536887312
    //   4393: iastore
    //   4394: dup
    //   4395: bipush #22
    //   4397: bipush #16
    //   4399: iastore
    //   4400: dup
    //   4401: bipush #23
    //   4403: ldc 541065232
    //   4405: iastore
    //   4406: dup
    //   4407: bipush #24
    //   4409: ldc 541065232
    //   4411: iastore
    //   4412: dup
    //   4413: bipush #25
    //   4415: iconst_0
    //   4416: iastore
    //   4417: dup
    //   4418: bipush #26
    //   4420: ldc 4210704
    //   4422: iastore
    //   4423: dup
    //   4424: bipush #27
    //   4426: ldc 541081600
    //   4428: iastore
    //   4429: dup
    //   4430: bipush #28
    //   4432: sipush #16400
    //   4435: iastore
    //   4436: dup
    //   4437: bipush #29
    //   4439: ldc 4210688
    //   4441: iastore
    //   4442: dup
    //   4443: bipush #30
    //   4445: ldc 541081600
    //   4447: iastore
    //   4448: dup
    //   4449: bipush #31
    //   4451: ldc 536870912
    //   4453: iastore
    //   4454: dup
    //   4455: bipush #32
    //   4457: ldc 536887296
    //   4459: iastore
    //   4460: dup
    //   4461: bipush #33
    //   4463: bipush #16
    //   4465: iastore
    //   4466: dup
    //   4467: bipush #34
    //   4469: ldc 541065232
    //   4471: iastore
    //   4472: dup
    //   4473: bipush #35
    //   4475: ldc 4210688
    //   4477: iastore
    //   4478: dup
    //   4479: bipush #36
    //   4481: ldc 541081616
    //   4483: iastore
    //   4484: dup
    //   4485: bipush #37
    //   4487: ldc 4194304
    //   4489: iastore
    //   4490: dup
    //   4491: bipush #38
    //   4493: sipush #16400
    //   4496: iastore
    //   4497: dup
    //   4498: bipush #39
    //   4500: ldc 536870928
    //   4502: iastore
    //   4503: dup
    //   4504: bipush #40
    //   4506: ldc 4194304
    //   4508: iastore
    //   4509: dup
    //   4510: bipush #41
    //   4512: ldc 536887296
    //   4514: iastore
    //   4515: dup
    //   4516: bipush #42
    //   4518: ldc 536870912
    //   4520: iastore
    //   4521: dup
    //   4522: bipush #43
    //   4524: sipush #16400
    //   4527: iastore
    //   4528: dup
    //   4529: bipush #44
    //   4531: ldc 536870928
    //   4533: iastore
    //   4534: dup
    //   4535: bipush #45
    //   4537: ldc 541081616
    //   4539: iastore
    //   4540: dup
    //   4541: bipush #46
    //   4543: ldc 4210688
    //   4545: iastore
    //   4546: dup
    //   4547: bipush #47
    //   4549: ldc 541065216
    //   4551: iastore
    //   4552: dup
    //   4553: bipush #48
    //   4555: ldc 4210704
    //   4557: iastore
    //   4558: dup
    //   4559: bipush #49
    //   4561: ldc 541081600
    //   4563: iastore
    //   4564: dup
    //   4565: bipush #50
    //   4567: iconst_0
    //   4568: iastore
    //   4569: dup
    //   4570: bipush #51
    //   4572: ldc 541065232
    //   4574: iastore
    //   4575: dup
    //   4576: bipush #52
    //   4578: bipush #16
    //   4580: iastore
    //   4581: dup
    //   4582: bipush #53
    //   4584: sipush #16384
    //   4587: iastore
    //   4588: dup
    //   4589: bipush #54
    //   4591: ldc 541065216
    //   4593: iastore
    //   4594: dup
    //   4595: bipush #55
    //   4597: ldc 4210704
    //   4599: iastore
    //   4600: dup
    //   4601: bipush #56
    //   4603: sipush #16384
    //   4606: iastore
    //   4607: dup
    //   4608: bipush #57
    //   4610: ldc 4194320
    //   4612: iastore
    //   4613: dup
    //   4614: bipush #58
    //   4616: ldc 536887312
    //   4618: iastore
    //   4619: dup
    //   4620: bipush #59
    //   4622: iconst_0
    //   4623: iastore
    //   4624: dup
    //   4625: bipush #60
    //   4627: ldc 541081600
    //   4629: iastore
    //   4630: dup
    //   4631: bipush #61
    //   4633: ldc 536870912
    //   4635: iastore
    //   4636: dup
    //   4637: bipush #62
    //   4639: ldc 4194320
    //   4641: iastore
    //   4642: dup
    //   4643: bipush #63
    //   4645: ldc 536887312
    //   4647: iastore
    //   4648: astore #14
    //   4650: bipush #64
    //   4652: newarray int
    //   4654: dup
    //   4655: iconst_0
    //   4656: ldc 2097152
    //   4658: iastore
    //   4659: dup
    //   4660: iconst_1
    //   4661: ldc 69206018
    //   4663: iastore
    //   4664: dup
    //   4665: iconst_2
    //   4666: ldc 67110914
    //   4668: iastore
    //   4669: dup
    //   4670: iconst_3
    //   4671: iconst_0
    //   4672: iastore
    //   4673: dup
    //   4674: iconst_4
    //   4675: sipush #2048
    //   4678: iastore
    //   4679: dup
    //   4680: iconst_5
    //   4681: ldc 67110914
    //   4683: iastore
    //   4684: dup
    //   4685: bipush #6
    //   4687: ldc 2099202
    //   4689: iastore
    //   4690: dup
    //   4691: bipush #7
    //   4693: ldc 69208064
    //   4695: iastore
    //   4696: dup
    //   4697: bipush #8
    //   4699: ldc 69208066
    //   4701: iastore
    //   4702: dup
    //   4703: bipush #9
    //   4705: ldc 2097152
    //   4707: iastore
    //   4708: dup
    //   4709: bipush #10
    //   4711: iconst_0
    //   4712: iastore
    //   4713: dup
    //   4714: bipush #11
    //   4716: ldc 67108866
    //   4718: iastore
    //   4719: dup
    //   4720: bipush #12
    //   4722: iconst_2
    //   4723: iastore
    //   4724: dup
    //   4725: bipush #13
    //   4727: ldc 67108864
    //   4729: iastore
    //   4730: dup
    //   4731: bipush #14
    //   4733: ldc 69206018
    //   4735: iastore
    //   4736: dup
    //   4737: bipush #15
    //   4739: sipush #2050
    //   4742: iastore
    //   4743: dup
    //   4744: bipush #16
    //   4746: ldc 67110912
    //   4748: iastore
    //   4749: dup
    //   4750: bipush #17
    //   4752: ldc 2099202
    //   4754: iastore
    //   4755: dup
    //   4756: bipush #18
    //   4758: ldc 2097154
    //   4760: iastore
    //   4761: dup
    //   4762: bipush #19
    //   4764: ldc 67110912
    //   4766: iastore
    //   4767: dup
    //   4768: bipush #20
    //   4770: ldc 67108866
    //   4772: iastore
    //   4773: dup
    //   4774: bipush #21
    //   4776: ldc 69206016
    //   4778: iastore
    //   4779: dup
    //   4780: bipush #22
    //   4782: ldc 69208064
    //   4784: iastore
    //   4785: dup
    //   4786: bipush #23
    //   4788: ldc 2097154
    //   4790: iastore
    //   4791: dup
    //   4792: bipush #24
    //   4794: ldc 69206016
    //   4796: iastore
    //   4797: dup
    //   4798: bipush #25
    //   4800: sipush #2048
    //   4803: iastore
    //   4804: dup
    //   4805: bipush #26
    //   4807: sipush #2050
    //   4810: iastore
    //   4811: dup
    //   4812: bipush #27
    //   4814: ldc 69208066
    //   4816: iastore
    //   4817: dup
    //   4818: bipush #28
    //   4820: ldc 2099200
    //   4822: iastore
    //   4823: dup
    //   4824: bipush #29
    //   4826: iconst_2
    //   4827: iastore
    //   4828: dup
    //   4829: bipush #30
    //   4831: ldc 67108864
    //   4833: iastore
    //   4834: dup
    //   4835: bipush #31
    //   4837: ldc 2099200
    //   4839: iastore
    //   4840: dup
    //   4841: bipush #32
    //   4843: ldc 67108864
    //   4845: iastore
    //   4846: dup
    //   4847: bipush #33
    //   4849: ldc 2099200
    //   4851: iastore
    //   4852: dup
    //   4853: bipush #34
    //   4855: ldc 2097152
    //   4857: iastore
    //   4858: dup
    //   4859: bipush #35
    //   4861: ldc 67110914
    //   4863: iastore
    //   4864: dup
    //   4865: bipush #36
    //   4867: ldc 67110914
    //   4869: iastore
    //   4870: dup
    //   4871: bipush #37
    //   4873: ldc 69206018
    //   4875: iastore
    //   4876: dup
    //   4877: bipush #38
    //   4879: ldc 69206018
    //   4881: iastore
    //   4882: dup
    //   4883: bipush #39
    //   4885: iconst_2
    //   4886: iastore
    //   4887: dup
    //   4888: bipush #40
    //   4890: ldc 2097154
    //   4892: iastore
    //   4893: dup
    //   4894: bipush #41
    //   4896: ldc 67108864
    //   4898: iastore
    //   4899: dup
    //   4900: bipush #42
    //   4902: ldc 67110912
    //   4904: iastore
    //   4905: dup
    //   4906: bipush #43
    //   4908: ldc 2097152
    //   4910: iastore
    //   4911: dup
    //   4912: bipush #44
    //   4914: ldc 69208064
    //   4916: iastore
    //   4917: dup
    //   4918: bipush #45
    //   4920: sipush #2050
    //   4923: iastore
    //   4924: dup
    //   4925: bipush #46
    //   4927: ldc 2099202
    //   4929: iastore
    //   4930: dup
    //   4931: bipush #47
    //   4933: ldc 69208064
    //   4935: iastore
    //   4936: dup
    //   4937: bipush #48
    //   4939: sipush #2050
    //   4942: iastore
    //   4943: dup
    //   4944: bipush #49
    //   4946: ldc 67108866
    //   4948: iastore
    //   4949: dup
    //   4950: bipush #50
    //   4952: ldc 69208066
    //   4954: iastore
    //   4955: dup
    //   4956: bipush #51
    //   4958: ldc 69206016
    //   4960: iastore
    //   4961: dup
    //   4962: bipush #52
    //   4964: ldc 2099200
    //   4966: iastore
    //   4967: dup
    //   4968: bipush #53
    //   4970: iconst_0
    //   4971: iastore
    //   4972: dup
    //   4973: bipush #54
    //   4975: iconst_2
    //   4976: iastore
    //   4977: dup
    //   4978: bipush #55
    //   4980: ldc 69208066
    //   4982: iastore
    //   4983: dup
    //   4984: bipush #56
    //   4986: iconst_0
    //   4987: iastore
    //   4988: dup
    //   4989: bipush #57
    //   4991: ldc 2099202
    //   4993: iastore
    //   4994: dup
    //   4995: bipush #58
    //   4997: ldc 69206016
    //   4999: iastore
    //   5000: dup
    //   5001: bipush #59
    //   5003: sipush #2048
    //   5006: iastore
    //   5007: dup
    //   5008: bipush #60
    //   5010: ldc 67108866
    //   5012: iastore
    //   5013: dup
    //   5014: bipush #61
    //   5016: ldc 67110912
    //   5018: iastore
    //   5019: dup
    //   5020: bipush #62
    //   5022: sipush #2048
    //   5025: iastore
    //   5026: dup
    //   5027: bipush #63
    //   5029: ldc 2097154
    //   5031: iastore
    //   5032: astore #15
    //   5034: bipush #64
    //   5036: newarray int
    //   5038: dup
    //   5039: iconst_0
    //   5040: ldc 268439616
    //   5042: iastore
    //   5043: dup
    //   5044: iconst_1
    //   5045: sipush #4096
    //   5048: iastore
    //   5049: dup
    //   5050: iconst_2
    //   5051: ldc 262144
    //   5053: iastore
    //   5054: dup
    //   5055: iconst_3
    //   5056: ldc 268701760
    //   5058: iastore
    //   5059: dup
    //   5060: iconst_4
    //   5061: ldc 268435456
    //   5063: iastore
    //   5064: dup
    //   5065: iconst_5
    //   5066: ldc 268439616
    //   5068: iastore
    //   5069: dup
    //   5070: bipush #6
    //   5072: bipush #64
    //   5074: iastore
    //   5075: dup
    //   5076: bipush #7
    //   5078: ldc 268435456
    //   5080: iastore
    //   5081: dup
    //   5082: bipush #8
    //   5084: ldc 262208
    //   5086: iastore
    //   5087: dup
    //   5088: bipush #9
    //   5090: ldc 268697600
    //   5092: iastore
    //   5093: dup
    //   5094: bipush #10
    //   5096: ldc 268701760
    //   5098: iastore
    //   5099: dup
    //   5100: bipush #11
    //   5102: ldc 266240
    //   5104: iastore
    //   5105: dup
    //   5106: bipush #12
    //   5108: ldc 268701696
    //   5110: iastore
    //   5111: dup
    //   5112: bipush #13
    //   5114: ldc 266304
    //   5116: iastore
    //   5117: dup
    //   5118: bipush #14
    //   5120: sipush #4096
    //   5123: iastore
    //   5124: dup
    //   5125: bipush #15
    //   5127: bipush #64
    //   5129: iastore
    //   5130: dup
    //   5131: bipush #16
    //   5133: ldc 268697600
    //   5135: iastore
    //   5136: dup
    //   5137: bipush #17
    //   5139: ldc 268435520
    //   5141: iastore
    //   5142: dup
    //   5143: bipush #18
    //   5145: ldc 268439552
    //   5147: iastore
    //   5148: dup
    //   5149: bipush #19
    //   5151: sipush #4160
    //   5154: iastore
    //   5155: dup
    //   5156: bipush #20
    //   5158: ldc 266240
    //   5160: iastore
    //   5161: dup
    //   5162: bipush #21
    //   5164: ldc 262208
    //   5166: iastore
    //   5167: dup
    //   5168: bipush #22
    //   5170: ldc 268697664
    //   5172: iastore
    //   5173: dup
    //   5174: bipush #23
    //   5176: ldc 268701696
    //   5178: iastore
    //   5179: dup
    //   5180: bipush #24
    //   5182: sipush #4160
    //   5185: iastore
    //   5186: dup
    //   5187: bipush #25
    //   5189: iconst_0
    //   5190: iastore
    //   5191: dup
    //   5192: bipush #26
    //   5194: iconst_0
    //   5195: iastore
    //   5196: dup
    //   5197: bipush #27
    //   5199: ldc 268697664
    //   5201: iastore
    //   5202: dup
    //   5203: bipush #28
    //   5205: ldc 268435520
    //   5207: iastore
    //   5208: dup
    //   5209: bipush #29
    //   5211: ldc 268439552
    //   5213: iastore
    //   5214: dup
    //   5215: bipush #30
    //   5217: ldc 266304
    //   5219: iastore
    //   5220: dup
    //   5221: bipush #31
    //   5223: ldc 262144
    //   5225: iastore
    //   5226: dup
    //   5227: bipush #32
    //   5229: ldc 266304
    //   5231: iastore
    //   5232: dup
    //   5233: bipush #33
    //   5235: ldc 262144
    //   5237: iastore
    //   5238: dup
    //   5239: bipush #34
    //   5241: ldc 268701696
    //   5243: iastore
    //   5244: dup
    //   5245: bipush #35
    //   5247: sipush #4096
    //   5250: iastore
    //   5251: dup
    //   5252: bipush #36
    //   5254: bipush #64
    //   5256: iastore
    //   5257: dup
    //   5258: bipush #37
    //   5260: ldc 268697664
    //   5262: iastore
    //   5263: dup
    //   5264: bipush #38
    //   5266: sipush #4096
    //   5269: iastore
    //   5270: dup
    //   5271: bipush #39
    //   5273: ldc 266304
    //   5275: iastore
    //   5276: dup
    //   5277: bipush #40
    //   5279: ldc 268439552
    //   5281: iastore
    //   5282: dup
    //   5283: bipush #41
    //   5285: bipush #64
    //   5287: iastore
    //   5288: dup
    //   5289: bipush #42
    //   5291: ldc 268435520
    //   5293: iastore
    //   5294: dup
    //   5295: bipush #43
    //   5297: ldc 268697600
    //   5299: iastore
    //   5300: dup
    //   5301: bipush #44
    //   5303: ldc 268697664
    //   5305: iastore
    //   5306: dup
    //   5307: bipush #45
    //   5309: ldc 268435456
    //   5311: iastore
    //   5312: dup
    //   5313: bipush #46
    //   5315: ldc 262144
    //   5317: iastore
    //   5318: dup
    //   5319: bipush #47
    //   5321: ldc 268439616
    //   5323: iastore
    //   5324: dup
    //   5325: bipush #48
    //   5327: iconst_0
    //   5328: iastore
    //   5329: dup
    //   5330: bipush #49
    //   5332: ldc 268701760
    //   5334: iastore
    //   5335: dup
    //   5336: bipush #50
    //   5338: ldc 262208
    //   5340: iastore
    //   5341: dup
    //   5342: bipush #51
    //   5344: ldc 268435520
    //   5346: iastore
    //   5347: dup
    //   5348: bipush #52
    //   5350: ldc 268697600
    //   5352: iastore
    //   5353: dup
    //   5354: bipush #53
    //   5356: ldc 268439552
    //   5358: iastore
    //   5359: dup
    //   5360: bipush #54
    //   5362: ldc 268439616
    //   5364: iastore
    //   5365: dup
    //   5366: bipush #55
    //   5368: iconst_0
    //   5369: iastore
    //   5370: dup
    //   5371: bipush #56
    //   5373: ldc 268701760
    //   5375: iastore
    //   5376: dup
    //   5377: bipush #57
    //   5379: ldc 266240
    //   5381: iastore
    //   5382: dup
    //   5383: bipush #58
    //   5385: ldc 266240
    //   5387: iastore
    //   5388: dup
    //   5389: bipush #59
    //   5391: sipush #4160
    //   5394: iastore
    //   5395: dup
    //   5396: bipush #60
    //   5398: sipush #4160
    //   5401: iastore
    //   5402: dup
    //   5403: bipush #61
    //   5405: ldc 262208
    //   5407: iastore
    //   5408: dup
    //   5409: bipush #62
    //   5411: ldc 268435456
    //   5413: iastore
    //   5414: dup
    //   5415: bipush #63
    //   5417: ldc 268701696
    //   5419: iastore
    //   5420: astore #16
    //   5422: aload #4
    //   5424: arraylength
    //   5425: istore #17
    //   5427: iconst_2
    //   5428: newarray int
    //   5430: astore #18
    //   5432: iload #17
    //   5434: newarray byte
    //   5436: astore #5
    //   5438: iload #17
    //   5440: bipush #8
    //   5442: idiv
    //   5443: istore #19
    //   5445: iconst_0
    //   5446: istore #20
    //   5448: iload #20
    //   5450: iload #19
    //   5452: if_icmpge -> 6370
    //   5455: iload #20
    //   5457: bipush #8
    //   5459: imul
    //   5460: istore #21
    //   5462: iconst_0
    //   5463: istore #22
    //   5465: iload #22
    //   5467: iconst_2
    //   5468: if_icmpge -> 5557
    //   5471: aload #18
    //   5473: iload #22
    //   5475: aload #4
    //   5477: iload #21
    //   5479: iload #22
    //   5481: iconst_4
    //   5482: imul
    //   5483: iadd
    //   5484: baload
    //   5485: sipush #255
    //   5488: iand
    //   5489: bipush #24
    //   5491: ishl
    //   5492: aload #4
    //   5494: iload #21
    //   5496: iload #22
    //   5498: iconst_4
    //   5499: imul
    //   5500: iadd
    //   5501: iconst_1
    //   5502: iadd
    //   5503: baload
    //   5504: sipush #255
    //   5507: iand
    //   5508: bipush #16
    //   5510: ishl
    //   5511: ior
    //   5512: aload #4
    //   5514: iload #21
    //   5516: iload #22
    //   5518: iconst_4
    //   5519: imul
    //   5520: iadd
    //   5521: iconst_2
    //   5522: iadd
    //   5523: baload
    //   5524: sipush #255
    //   5527: iand
    //   5528: bipush #8
    //   5530: ishl
    //   5531: ior
    //   5532: aload #4
    //   5534: iload #21
    //   5536: iload #22
    //   5538: iconst_4
    //   5539: imul
    //   5540: iadd
    //   5541: iconst_3
    //   5542: iadd
    //   5543: baload
    //   5544: sipush #255
    //   5547: iand
    //   5548: ior
    //   5549: iastore
    //   5550: iinc #22, 1
    //   5553: iload_2
    //   5554: ifeq -> 5465
    //   5557: iconst_0
    //   5558: istore #27
    //   5560: aload #18
    //   5562: iconst_0
    //   5563: iaload
    //   5564: istore #25
    //   5566: aload #18
    //   5568: iconst_1
    //   5569: iaload
    //   5570: istore #24
    //   5572: iload #25
    //   5574: iconst_4
    //   5575: iushr
    //   5576: iload #24
    //   5578: ixor
    //   5579: ldc 252645135
    //   5581: iand
    //   5582: istore #23
    //   5584: iload #24
    //   5586: iload #23
    //   5588: ixor
    //   5589: istore #24
    //   5591: iload #25
    //   5593: iload #23
    //   5595: iconst_4
    //   5596: ishl
    //   5597: ixor
    //   5598: istore #25
    //   5600: iload #25
    //   5602: bipush #16
    //   5604: iushr
    //   5605: iload #24
    //   5607: ixor
    //   5608: ldc 65535
    //   5610: iand
    //   5611: istore #23
    //   5613: iload #24
    //   5615: iload #23
    //   5617: ixor
    //   5618: istore #24
    //   5620: iload #25
    //   5622: iload #23
    //   5624: bipush #16
    //   5626: ishl
    //   5627: ixor
    //   5628: istore #25
    //   5630: iload #24
    //   5632: iconst_2
    //   5633: iushr
    //   5634: iload #25
    //   5636: ixor
    //   5637: ldc 858993459
    //   5639: iand
    //   5640: istore #23
    //   5642: iload #25
    //   5644: iload #23
    //   5646: ixor
    //   5647: istore #25
    //   5649: iload #24
    //   5651: iload #23
    //   5653: iconst_2
    //   5654: ishl
    //   5655: ixor
    //   5656: istore #24
    //   5658: iload #24
    //   5660: bipush #8
    //   5662: iushr
    //   5663: iload #25
    //   5665: ixor
    //   5666: ldc 16711935
    //   5668: iand
    //   5669: istore #23
    //   5671: iload #25
    //   5673: iload #23
    //   5675: ixor
    //   5676: istore #25
    //   5678: iload #24
    //   5680: iload #23
    //   5682: bipush #8
    //   5684: ishl
    //   5685: ixor
    //   5686: istore #24
    //   5688: iload #24
    //   5690: iconst_1
    //   5691: ishl
    //   5692: iload #24
    //   5694: bipush #31
    //   5696: iushr
    //   5697: iconst_1
    //   5698: iand
    //   5699: ior
    //   5700: istore #24
    //   5702: iload #25
    //   5704: iload #24
    //   5706: ixor
    //   5707: ldc -1431655766
    //   5709: iand
    //   5710: istore #23
    //   5712: iload #25
    //   5714: iload #23
    //   5716: ixor
    //   5717: istore #25
    //   5719: iload #24
    //   5721: iload #23
    //   5723: ixor
    //   5724: istore #24
    //   5726: iload #25
    //   5728: iconst_1
    //   5729: ishl
    //   5730: iload #25
    //   5732: bipush #31
    //   5734: iushr
    //   5735: iconst_1
    //   5736: iand
    //   5737: ior
    //   5738: istore #25
    //   5740: iconst_0
    //   5741: istore #26
    //   5743: iload #26
    //   5745: bipush #8
    //   5747: if_icmpge -> 6085
    //   5750: iload #24
    //   5752: bipush #28
    //   5754: ishl
    //   5755: iload #24
    //   5757: iconst_4
    //   5758: iushr
    //   5759: ior
    //   5760: istore #23
    //   5762: iload #23
    //   5764: aload #6
    //   5766: iload #27
    //   5768: iinc #27, 1
    //   5771: iaload
    //   5772: ixor
    //   5773: istore #23
    //   5775: aload #15
    //   5777: iload #23
    //   5779: bipush #63
    //   5781: iand
    //   5782: iaload
    //   5783: istore #22
    //   5785: iload #22
    //   5787: aload #13
    //   5789: iload #23
    //   5791: bipush #8
    //   5793: iushr
    //   5794: bipush #63
    //   5796: iand
    //   5797: iaload
    //   5798: ior
    //   5799: istore #22
    //   5801: iload #22
    //   5803: aload #11
    //   5805: iload #23
    //   5807: bipush #16
    //   5809: iushr
    //   5810: bipush #63
    //   5812: iand
    //   5813: iaload
    //   5814: ior
    //   5815: istore #22
    //   5817: iload #22
    //   5819: aload #9
    //   5821: iload #23
    //   5823: bipush #24
    //   5825: iushr
    //   5826: bipush #63
    //   5828: iand
    //   5829: iaload
    //   5830: ior
    //   5831: istore #22
    //   5833: iload #24
    //   5835: aload #6
    //   5837: iload #27
    //   5839: iinc #27, 1
    //   5842: iaload
    //   5843: ixor
    //   5844: istore #23
    //   5846: iload #22
    //   5848: aload #16
    //   5850: iload #23
    //   5852: bipush #63
    //   5854: iand
    //   5855: iaload
    //   5856: ior
    //   5857: istore #22
    //   5859: iload #22
    //   5861: aload #14
    //   5863: iload #23
    //   5865: bipush #8
    //   5867: iushr
    //   5868: bipush #63
    //   5870: iand
    //   5871: iaload
    //   5872: ior
    //   5873: istore #22
    //   5875: iload #22
    //   5877: aload #12
    //   5879: iload #23
    //   5881: bipush #16
    //   5883: iushr
    //   5884: bipush #63
    //   5886: iand
    //   5887: iaload
    //   5888: ior
    //   5889: istore #22
    //   5891: iload #22
    //   5893: aload #10
    //   5895: iload #23
    //   5897: bipush #24
    //   5899: iushr
    //   5900: bipush #63
    //   5902: iand
    //   5903: iaload
    //   5904: ior
    //   5905: istore #22
    //   5907: iload #25
    //   5909: iload #22
    //   5911: ixor
    //   5912: istore #25
    //   5914: iload #25
    //   5916: bipush #28
    //   5918: ishl
    //   5919: iload #25
    //   5921: iconst_4
    //   5922: iushr
    //   5923: ior
    //   5924: istore #23
    //   5926: iload #23
    //   5928: aload #6
    //   5930: iload #27
    //   5932: iinc #27, 1
    //   5935: iaload
    //   5936: ixor
    //   5937: istore #23
    //   5939: aload #15
    //   5941: iload #23
    //   5943: bipush #63
    //   5945: iand
    //   5946: iaload
    //   5947: istore #22
    //   5949: iload #22
    //   5951: aload #13
    //   5953: iload #23
    //   5955: bipush #8
    //   5957: iushr
    //   5958: bipush #63
    //   5960: iand
    //   5961: iaload
    //   5962: ior
    //   5963: istore #22
    //   5965: iload #22
    //   5967: aload #11
    //   5969: iload #23
    //   5971: bipush #16
    //   5973: iushr
    //   5974: bipush #63
    //   5976: iand
    //   5977: iaload
    //   5978: ior
    //   5979: istore #22
    //   5981: iload #22
    //   5983: aload #9
    //   5985: iload #23
    //   5987: bipush #24
    //   5989: iushr
    //   5990: bipush #63
    //   5992: iand
    //   5993: iaload
    //   5994: ior
    //   5995: istore #22
    //   5997: iload #25
    //   5999: aload #6
    //   6001: iload #27
    //   6003: iinc #27, 1
    //   6006: iaload
    //   6007: ixor
    //   6008: istore #23
    //   6010: iload #22
    //   6012: aload #16
    //   6014: iload #23
    //   6016: bipush #63
    //   6018: iand
    //   6019: iaload
    //   6020: ior
    //   6021: istore #22
    //   6023: iload #22
    //   6025: aload #14
    //   6027: iload #23
    //   6029: bipush #8
    //   6031: iushr
    //   6032: bipush #63
    //   6034: iand
    //   6035: iaload
    //   6036: ior
    //   6037: istore #22
    //   6039: iload #22
    //   6041: aload #12
    //   6043: iload #23
    //   6045: bipush #16
    //   6047: iushr
    //   6048: bipush #63
    //   6050: iand
    //   6051: iaload
    //   6052: ior
    //   6053: istore #22
    //   6055: iload #22
    //   6057: aload #10
    //   6059: iload #23
    //   6061: bipush #24
    //   6063: iushr
    //   6064: bipush #63
    //   6066: iand
    //   6067: iaload
    //   6068: ior
    //   6069: istore #22
    //   6071: iload #24
    //   6073: iload #22
    //   6075: ixor
    //   6076: istore #24
    //   6078: iinc #26, 1
    //   6081: iload_2
    //   6082: ifeq -> 5743
    //   6085: iload #24
    //   6087: bipush #31
    //   6089: ishl
    //   6090: iload #24
    //   6092: iconst_1
    //   6093: iushr
    //   6094: ior
    //   6095: istore #24
    //   6097: iload #25
    //   6099: iload #24
    //   6101: ixor
    //   6102: ldc -1431655766
    //   6104: iand
    //   6105: istore #23
    //   6107: iload #25
    //   6109: iload #23
    //   6111: ixor
    //   6112: istore #25
    //   6114: iload #24
    //   6116: iload #23
    //   6118: ixor
    //   6119: istore #24
    //   6121: iload #25
    //   6123: bipush #31
    //   6125: ishl
    //   6126: iload #25
    //   6128: iconst_1
    //   6129: iushr
    //   6130: ior
    //   6131: istore #25
    //   6133: iload #25
    //   6135: bipush #8
    //   6137: iushr
    //   6138: iload #24
    //   6140: ixor
    //   6141: ldc 16711935
    //   6143: iand
    //   6144: istore #23
    //   6146: iload #24
    //   6148: iload #23
    //   6150: ixor
    //   6151: istore #24
    //   6153: iload #25
    //   6155: iload #23
    //   6157: bipush #8
    //   6159: ishl
    //   6160: ixor
    //   6161: istore #25
    //   6163: iload #25
    //   6165: iconst_2
    //   6166: iushr
    //   6167: iload #24
    //   6169: ixor
    //   6170: ldc 858993459
    //   6172: iand
    //   6173: istore #23
    //   6175: iload #24
    //   6177: iload #23
    //   6179: ixor
    //   6180: istore #24
    //   6182: iload #25
    //   6184: iload #23
    //   6186: iconst_2
    //   6187: ishl
    //   6188: ixor
    //   6189: istore #25
    //   6191: iload #24
    //   6193: bipush #16
    //   6195: iushr
    //   6196: iload #25
    //   6198: ixor
    //   6199: ldc 65535
    //   6201: iand
    //   6202: istore #23
    //   6204: iload #25
    //   6206: iload #23
    //   6208: ixor
    //   6209: istore #25
    //   6211: iload #24
    //   6213: iload #23
    //   6215: bipush #16
    //   6217: ishl
    //   6218: ixor
    //   6219: istore #24
    //   6221: iload #24
    //   6223: iconst_4
    //   6224: iushr
    //   6225: iload #25
    //   6227: ixor
    //   6228: ldc 252645135
    //   6230: iand
    //   6231: istore #23
    //   6233: iload #25
    //   6235: iload #23
    //   6237: ixor
    //   6238: istore #25
    //   6240: iload #24
    //   6242: iload #23
    //   6244: iconst_4
    //   6245: ishl
    //   6246: ixor
    //   6247: istore #24
    //   6249: aload #18
    //   6251: iconst_0
    //   6252: iload #24
    //   6254: iastore
    //   6255: aload #18
    //   6257: iconst_1
    //   6258: iload #25
    //   6260: iastore
    //   6261: iload #20
    //   6263: bipush #8
    //   6265: imul
    //   6266: istore #28
    //   6268: iconst_0
    //   6269: istore #29
    //   6271: iload #29
    //   6273: iconst_2
    //   6274: if_icmpge -> 6363
    //   6277: aload #5
    //   6279: iload #28
    //   6281: iload #29
    //   6283: iconst_4
    //   6284: imul
    //   6285: iadd
    //   6286: aload #18
    //   6288: iload #29
    //   6290: iaload
    //   6291: bipush #24
    //   6293: iushr
    //   6294: i2b
    //   6295: bastore
    //   6296: aload #5
    //   6298: iload #28
    //   6300: iload #29
    //   6302: iconst_4
    //   6303: imul
    //   6304: iadd
    //   6305: iconst_1
    //   6306: iadd
    //   6307: aload #18
    //   6309: iload #29
    //   6311: iaload
    //   6312: bipush #16
    //   6314: iushr
    //   6315: i2b
    //   6316: bastore
    //   6317: aload #5
    //   6319: iload #28
    //   6321: iload #29
    //   6323: iconst_4
    //   6324: imul
    //   6325: iadd
    //   6326: iconst_2
    //   6327: iadd
    //   6328: aload #18
    //   6330: iload #29
    //   6332: iaload
    //   6333: bipush #8
    //   6335: iushr
    //   6336: i2b
    //   6337: bastore
    //   6338: aload #5
    //   6340: iload #28
    //   6342: iload #29
    //   6344: iconst_4
    //   6345: imul
    //   6346: iadd
    //   6347: iconst_3
    //   6348: iadd
    //   6349: aload #18
    //   6351: iload #29
    //   6353: iaload
    //   6354: i2b
    //   6355: bastore
    //   6356: iinc #29, 1
    //   6359: iload_2
    //   6360: ifeq -> 6271
    //   6363: iinc #20, 1
    //   6366: iload_2
    //   6367: ifeq -> 5448
    //   6370: new java/math/BigInteger
    //   6373: dup
    //   6374: aload #5
    //   6376: invokespecial <init> : ([B)V
    //   6379: invokevirtual abs : ()Ljava/math/BigInteger;
    //   6382: putstatic burp/Zead.ZI : Ljava/lang/Object;
    //   6385: sipush #6482
    //   6388: sipush #-3051
    //   6391: invokestatic a : (II)Ljava/lang/String;
    //   6394: iconst_1
    //   6395: ldc burp/Zlnq
    //   6397: invokevirtual getClassLoader : ()Ljava/lang/ClassLoader;
    //   6400: invokestatic forName : (Ljava/lang/String;ZLjava/lang/ClassLoader;)Ljava/lang/Class;
    //   6403: invokevirtual getDeclaredFields : ()[Ljava/lang/reflect/Field;
    //   6406: astore #4
    //   6408: aload #4
    //   6410: arraylength
    //   6411: istore #5
    //   6413: iconst_0
    //   6414: istore #6
    //   6416: iload #6
    //   6418: iload #5
    //   6420: if_icmpge -> 6558
    //   6423: aload #4
    //   6425: iload #6
    //   6427: aaload
    //   6428: astore #7
    //   6430: aload #7
    //   6432: invokevirtual getModifiers : ()I
    //   6435: invokestatic isStatic : (I)Z
    //   6438: ifne -> 6448
    //   6441: goto -> 6551
    //   6444: invokestatic a : (Ljava/lang/Throwable;)Ljava/lang/Throwable;
    //   6447: athrow
    //   6448: aload #7
    //   6450: invokevirtual getType : ()Ljava/lang/Class;
    //   6453: astore #8
    //   6455: aload #8
    //   6457: ifnull -> 6538
    //   6460: aload #8
    //   6462: invokevirtual isPrimitive : ()Z
    //   6465: ifne -> 6538
    //   6468: goto -> 6475
    //   6471: invokestatic a : (Ljava/lang/Throwable;)Ljava/lang/Throwable;
    //   6474: athrow
    //   6475: aload #8
    //   6477: invokevirtual getPackage : ()Ljava/lang/Package;
    //   6480: ifnull -> 6538
    //   6483: goto -> 6490
    //   6486: invokestatic a : (Ljava/lang/Throwable;)Ljava/lang/Throwable;
    //   6489: athrow
    //   6490: aload #8
    //   6492: invokevirtual getPackage : ()Ljava/lang/Package;
    //   6495: invokevirtual getName : ()Ljava/lang/String;
    //   6498: ifnull -> 6538
    //   6501: goto -> 6508
    //   6504: invokestatic a : (Ljava/lang/Throwable;)Ljava/lang/Throwable;
    //   6507: athrow
    //   6508: aload #8
    //   6510: invokevirtual getPackage : ()Ljava/lang/Package;
    //   6513: invokevirtual getName : ()Ljava/lang/String;
    //   6516: sipush #6492
    //   6519: sipush #-31242
    //   6522: invokestatic a : (II)Ljava/lang/String;
    //   6525: invokevirtual startsWith : (Ljava/lang/String;)Z
    //   6528: ifne -> 6538
    //   6531: goto -> 6538
    //   6534: invokestatic a : (Ljava/lang/Throwable;)Ljava/lang/Throwable;
    //   6537: athrow
    //   6538: aload #7
    //   6540: iconst_1
    //   6541: invokevirtual setAccessible : (Z)V
    //   6544: aload #7
    //   6546: aconst_null
    //   6547: invokevirtual get : (Ljava/lang/Object;)Ljava/lang/Object;
    //   6550: pop
    //   6551: iinc #6, 1
    //   6554: iload_2
    //   6555: ifeq -> 6416
    //   6558: sipush #6489
    //   6561: sipush #16289
    //   6564: invokestatic a : (II)Ljava/lang/String;
    //   6567: invokestatic forName : (Ljava/lang/String;)Ljava/lang/Class;
    //   6570: invokevirtual getDeclaredMethods : ()[Ljava/lang/reflect/Method;
    //   6573: astore #4
    //   6575: aload #4
    //   6577: arraylength
    //   6578: istore #5
    //   6580: iconst_0
    //   6581: istore #6
    //   6583: iload #6
    //   6585: iload #5
    //   6587: if_icmpge -> 6720
    //   6590: aload #4
    //   6592: iload #6
    //   6594: aaload
    //   6595: astore #7
    //   6597: aload #7
    //   6599: invokevirtual getParameterTypes : ()[Ljava/lang/Class;
    //   6602: pop
    //   6603: aload #7
    //   6605: invokevirtual getModifiers : ()I
    //   6608: invokestatic isStatic : (I)Z
    //   6611: ifeq -> 6706
    //   6614: aload #7
    //   6616: invokevirtual getParameterTypes : ()[Ljava/lang/Class;
    //   6619: arraylength
    //   6620: iconst_2
    //   6621: if_icmpne -> 6706
    //   6624: goto -> 6631
    //   6627: invokestatic a : (Ljava/lang/Throwable;)Ljava/lang/Throwable;
    //   6630: athrow
    //   6631: aload #7
    //   6633: invokevirtual getReturnType : ()Ljava/lang/Class;
    //   6636: getstatic java/lang/Void.TYPE : Ljava/lang/Class;
    //   6639: invokevirtual equals : (Ljava/lang/Object;)Z
    //   6642: ifeq -> 6706
    //   6645: goto -> 6652
    //   6648: invokestatic a : (Ljava/lang/Throwable;)Ljava/lang/Throwable;
    //   6651: athrow
    //   6652: aload #7
    //   6654: iconst_1
    //   6655: invokevirtual setAccessible : (Z)V
    //   6658: aload #7
    //   6660: aconst_null
    //   6661: iconst_2
    //   6662: anewarray java/lang/Object
    //   6665: dup
    //   6666: iconst_0
    //   6667: aload_0
    //   6668: aastore
    //   6669: dup
    //   6670: iconst_1
    //   6671: aload_1
    //   6672: ifnonnull -> 6690
    //   6675: goto -> 6682
    //   6678: invokestatic a : (Ljava/lang/Throwable;)Ljava/lang/Throwable;
    //   6681: athrow
    //   6682: aload_1
    //   6683: goto -> 6697
    //   6686: invokestatic a : (Ljava/lang/Throwable;)Ljava/lang/Throwable;
    //   6689: athrow
    //   6690: aload_1
    //   6691: checkcast [B
    //   6694: invokevirtual clone : ()Ljava/lang/Object;
    //   6697: aastore
    //   6698: invokevirtual invoke : (Ljava/lang/Object;[Ljava/lang/Object;)Ljava/lang/Object;
    //   6701: pop
    //   6702: iload_2
    //   6703: ifeq -> 6720
    //   6706: iinc #6, 1
    //   6709: iload_2
    //   6710: ifeq -> 6583
    //   6713: goto -> 6720
    //   6716: invokestatic a : (Ljava/lang/Throwable;)Ljava/lang/Throwable;
    //   6719: athrow
    //   6720: getstatic burp/Zebj.ZF : Ljava/lang/String;
    //   6723: getstatic burp/Zgk1.ZD : Ljava/lang/Object;
    //   6726: checkcast java/math/BigInteger
    //   6729: invokevirtual intValue : ()I
    //   6732: bipush #32
    //   6734: irem
    //   6735: invokestatic abs : (I)I
    //   6738: invokevirtual charAt : (I)C
    //   6741: getstatic burp/Zxxd.Za : Ljava/lang/String;
    //   6744: getstatic burp/Zzip.ZW : Ljava/lang/Object;
    //   6747: checkcast java/math/BigInteger
    //   6750: invokevirtual intValue : ()I
    //   6753: bipush #32
    //   6755: irem
    //   6756: invokestatic abs : (I)I
    //   6759: invokevirtual charAt : (I)C
    //   6762: if_icmpgt -> 6869
    //   6765: getstatic burp/Zx4u.ZL : Ljava/lang/String;
    //   6768: getstatic burp/Zlw8.ZA : Ljava/lang/Object;
    //   6771: checkcast java/math/BigInteger
    //   6774: invokevirtual intValue : ()I
    //   6777: bipush #32
    //   6779: irem
    //   6780: invokestatic abs : (I)I
    //   6783: invokevirtual charAt : (I)C
    //   6786: getstatic burp/Zxn9.ZU : Ljava/lang/String;
    //   6789: getstatic burp/Zedz.Za : Ljava/lang/Object;
    //   6792: checkcast java/math/BigInteger
    //   6795: invokevirtual intValue : ()I
    //   6798: bipush #32
    //   6800: irem
    //   6801: invokestatic abs : (I)I
    //   6804: invokevirtual charAt : (I)C
    //   6807: if_icmple -> 6869
    //   6810: goto -> 6817
    //   6813: invokestatic a : (Ljava/lang/Throwable;)Ljava/lang/Throwable;
    //   6816: athrow
    //   6817: getstatic burp/Zlo4.Zn : Ljava/lang/String;
    //   6820: getstatic burp/Zeud.Zs : Ljava/lang/Object;
    //   6823: checkcast java/math/BigInteger
    //   6826: invokevirtual intValue : ()I
    //   6829: bipush #32
    //   6831: irem
    //   6832: invokestatic abs : (I)I
    //   6835: invokevirtual charAt : (I)C
    //   6838: getstatic burp/Zlo2.ZJ : Ljava/lang/String;
    //   6841: getstatic burp/Ze0z.ZQ : Ljava/lang/Object;
    //   6844: checkcast java/math/BigInteger
    //   6847: invokevirtual intValue : ()I
    //   6850: bipush #32
    //   6852: irem
    //   6853: invokestatic abs : (I)I
    //   6856: invokevirtual charAt : (I)C
    //   6859: if_icmple -> 6877
    //   6862: goto -> 6869
    //   6865: invokestatic a : (Ljava/lang/Throwable;)Ljava/lang/Throwable;
    //   6868: athrow
    //   6869: iconst_1
    //   6870: goto -> 6878
    //   6873: invokestatic a : (Ljava/lang/Throwable;)Ljava/lang/Throwable;
    //   6876: athrow
    //   6877: iconst_0
    //   6878: ireturn
    //   6879: astore_3
    //   6880: new java/lang/Exception
    //   6883: dup
    //   6884: aload_3
    //   6885: invokevirtual getMessage : ()Ljava/lang/String;
    //   6888: invokespecial <init> : (Ljava/lang/String;)V
    //   6891: athrow
    // Exception table:
    //   from	to	target	type
    //   4	6878	6879	java/lang/Throwable
    //   309	333	336	java/lang/Throwable
    //   407	444	444	java/lang/Throwable
    //   448	469	469	java/lang/Throwable
    //   473	503	503	java/lang/Throwable
    //   704	878	881	java/lang/Throwable
    //   848	915	918	java/lang/Throwable
    //   885	952	955	java/lang/Throwable
    //   922	989	992	java/lang/Throwable
    //   959	1026	1029	java/lang/Throwable
    //   996	1063	1066	java/lang/Throwable
    //   1033	1100	1103	java/lang/Throwable
    //   1070	1137	1140	java/lang/Throwable
    //   1107	1174	1177	java/lang/Throwable
    //   1144	1211	1214	java/lang/Throwable
    //   1181	1248	1251	java/lang/Throwable
    //   1218	1285	1288	java/lang/Throwable
    //   1255	1322	1325	java/lang/Throwable
    //   1292	1359	1362	java/lang/Throwable
    //   1329	1396	1399	java/lang/Throwable
    //   1366	1433	1436	java/lang/Throwable
    //   1403	1470	1473	java/lang/Throwable
    //   1440	1507	1510	java/lang/Throwable
    //   1477	1544	1547	java/lang/Throwable
    //   1514	1581	1584	java/lang/Throwable
    //   1551	1618	1621	java/lang/Throwable
    //   1588	1655	1658	java/lang/Throwable
    //   1625	1692	1695	java/lang/Throwable
    //   1662	1729	1732	java/lang/Throwable
    //   1699	1766	1769	java/lang/Throwable
    //   1736	1803	1806	java/lang/Throwable
    //   1773	1840	1843	java/lang/Throwable
    //   1810	1877	1880	java/lang/Throwable
    //   1847	1914	1917	java/lang/Throwable
    //   1884	1951	1954	java/lang/Throwable
    //   1921	1988	1991	java/lang/Throwable
    //   1958	2021	2024	java/lang/Throwable
    //   6430	6444	6444	java/lang/Throwable
    //   6455	6468	6471	java/lang/Throwable
    //   6460	6483	6486	java/lang/Throwable
    //   6475	6501	6504	java/lang/Throwable
    //   6490	6531	6534	java/lang/Throwable
    //   6597	6624	6627	java/lang/Throwable
    //   6614	6645	6648	java/lang/Throwable
    //   6631	6675	6678	java/lang/Throwable
    //   6652	6686	6686	java/lang/Throwable
    //   6697	6713	6716	java/lang/Throwable
    //   6720	6810	6813	java/lang/Throwable
    //   6765	6862	6865	java/lang/Throwable
    //   6817	6873	6873	java/lang/Throwable
  }
  
  static void ZJ(Object[] paramArrayOfObject, Object paramObject) throws Throwable {}
  
  static void ZX(Object paramObject) {
    Zz58.ZT = a(6493, 3644);
    Zz58.ZD = new BigInteger(a(6495, 28999));
    boolean bool = Zt2e.ZN();
    try {
      try {
        if (Zzv.Zy.charAt(Math.abs(((BigInteger)Zk7w.ZF).intValue() % 32)) <= Zljx.ZD.charAt(Math.abs(((BigInteger)Zz58.ZD).intValue() % 32))) {
          try {
            Zxyu.Zh(Class.forName(a(6480, -2922)));
            if (!bool)
              Zb9k.ZA(Class.forName(a(6481, 5015))); 
          } catch (Throwable throwable) {
            throw a(null);
          } 
          return;
        } 
      } catch (Throwable throwable) {
        throw a(null);
      } 
      Zb9k.ZA(Class.forName(a(6481, 5015)));
    } catch (Throwable throwable) {}
  }
  
  static {
    // Byte code:
    //   0: bipush #11
    //   2: anewarray java/lang/String
    //   5: astore #5
    //   7: iconst_0
    //   8: istore_3
    //   9: ldc 'U\P3>Z8yhN\\t>V&\\rw !Fdip7aBb,l\\tgc7XMD } R77%*C|fi LgM-B.1"`1xPK.Cj|_16-|X\\r>6p\\nc\\toRog'
    //   11: dup
    //   12: astore_2
    //   13: invokevirtual length : ()I
    //   16: istore #4
    //   18: bipush #32
    //   20: istore_1
    //   21: iconst_m1
    //   22: istore_0
    //   23: bipush #12
    //   25: iinc #0, 1
    //   28: aload_2
    //   29: iload_0
    //   30: dup
    //   31: iload_1
    //   32: iadd
    //   33: invokevirtual substring : (II)Ljava/lang/String;
    //   36: iconst_m1
    //   37: goto -> 143
    //   40: aload #5
    //   42: swap
    //   43: iload_3
    //   44: iinc #3, 1
    //   47: swap
    //   48: aastore
    //   49: iload_0
    //   50: iload_1
    //   51: iadd
    //   52: dup
    //   53: istore_0
    //   54: iload #4
    //   56: if_icmpge -> 68
    //   59: aload_2
    //   60: iload_0
    //   61: invokevirtual charAt : (I)C
    //   64: istore_1
    //   65: goto -> 23
    //   68: ldc 'nF`\\t]2'
    //   70: dup
    //   71: astore_2
    //   72: invokevirtual length : ()I
    //   75: istore #4
    //   77: bipush #9
    //   79: istore_1
    //   80: iconst_m1
    //   81: istore_0
    //   82: bipush #112
    //   84: iinc #0, 1
    //   87: aload_2
    //   88: iload_0
    //   89: dup
    //   90: iload_1
    //   91: iadd
    //   92: invokevirtual substring : (II)Ljava/lang/String;
    //   95: iconst_0
    //   96: goto -> 143
    //   99: aload #5
    //   101: swap
    //   102: iload_3
    //   103: iinc #3, 1
    //   106: swap
    //   107: aastore
    //   108: iload_0
    //   109: iload_1
    //   110: iadd
    //   111: dup
    //   112: istore_0
    //   113: iload #4
    //   115: if_icmpge -> 127
    //   118: aload_2
    //   119: iload_0
    //   120: invokevirtual charAt : (I)C
    //   123: istore_1
    //   124: goto -> 82
    //   127: aload #5
    //   129: putstatic burp/Zko9.a : [Ljava/lang/String;
    //   132: bipush #11
    //   134: anewarray java/lang/String
    //   137: putstatic burp/Zko9.b : [Ljava/lang/String;
    //   140: goto -> 300
    //   143: dup_x2
    //   144: pop
    //   145: invokevirtual toCharArray : ()[C
    //   148: dup_x1
    //   149: arraylength
    //   150: dup_x2
    //   151: pop
    //   152: iconst_0
    //   153: istore #6
    //   155: dup2_x1
    //   156: pop2
    //   157: dup_x2
    //   158: iconst_1
    //   159: if_icmpgt -> 260
    //   162: dup2
    //   163: swap
    //   164: iload #6
    //   166: dup2_x1
    //   167: caload
    //   168: swap
    //   169: iload #6
    //   171: bipush #7
    //   173: irem
    //   174: tableswitch default -> 242, 0 -> 212, 1 -> 217, 2 -> 222, 3 -> 227, 4 -> 232, 5 -> 237
    //   212: bipush #82
    //   214: goto -> 244
    //   217: bipush #21
    //   219: goto -> 244
    //   222: bipush #10
    //   224: goto -> 244
    //   227: bipush #59
    //   229: goto -> 244
    //   232: bipush #25
    //   234: goto -> 244
    //   237: bipush #125
    //   239: goto -> 244
    //   242: bipush #67
    //   244: ixor
    //   245: ixor
    //   246: i2c
    //   247: castore
    //   248: iinc #6, 1
    //   251: dup
    //   252: ifne -> 260
    //   255: dup2
    //   256: dup_x1
    //   257: goto -> 166
    //   260: dup2_x1
    //   261: pop2
    //   262: dup_x2
    //   263: iload #6
    //   265: if_icmpgt -> 162
    //   268: pop
    //   269: new java/lang/String
    //   272: dup_x1
    //   273: swap
    //   274: invokespecial <init> : ([C)V
    //   277: invokevirtual intern : ()Ljava/lang/String;
    //   280: swap
    //   281: pop
    //   282: swap
    //   283: tableswitch default -> 40, 0 -> 99
    //   300: sipush #6490
    //   303: sipush #29790
    //   306: invokestatic a : (II)Ljava/lang/String;
    //   309: putstatic burp/Zko9.Zf : Ljava/lang/String;
    //   312: new java/math/BigInteger
    //   315: dup
    //   316: bipush #32
    //   318: newarray byte
    //   320: dup
    //   321: iconst_0
    //   322: bipush #121
    //   324: bastore
    //   325: dup
    //   326: iconst_1
    //   327: bipush #34
    //   329: bastore
    //   330: dup
    //   331: iconst_2
    //   332: bipush #-79
    //   334: bastore
    //   335: dup
    //   336: iconst_3
    //   337: bipush #89
    //   339: bastore
    //   340: dup
    //   341: iconst_4
    //   342: bipush #-73
    //   344: bastore
    //   345: dup
    //   346: iconst_5
    //   347: bipush #-10
    //   349: bastore
    //   350: dup
    //   351: bipush #6
    //   353: bipush #110
    //   355: bastore
    //   356: dup
    //   357: bipush #7
    //   359: bipush #-95
    //   361: bastore
    //   362: dup
    //   363: bipush #8
    //   365: bipush #127
    //   367: bastore
    //   368: dup
    //   369: bipush #9
    //   371: bipush #-30
    //   373: bastore
    //   374: dup
    //   375: bipush #10
    //   377: bipush #105
    //   379: bastore
    //   380: dup
    //   381: bipush #11
    //   383: bipush #-2
    //   385: bastore
    //   386: dup
    //   387: bipush #12
    //   389: bipush #56
    //   391: bastore
    //   392: dup
    //   393: bipush #13
    //   395: bipush #-85
    //   397: bastore
    //   398: dup
    //   399: bipush #14
    //   401: iconst_4
    //   402: bastore
    //   403: dup
    //   404: bipush #15
    //   406: bipush #25
    //   408: bastore
    //   409: dup
    //   410: bipush #16
    //   412: bipush #-68
    //   414: bastore
    //   415: dup
    //   416: bipush #17
    //   418: bipush #-9
    //   420: bastore
    //   421: dup
    //   422: bipush #18
    //   424: bipush #75
    //   426: bastore
    //   427: dup
    //   428: bipush #19
    //   430: bipush #-55
    //   432: bastore
    //   433: dup
    //   434: bipush #20
    //   436: bipush #33
    //   438: bastore
    //   439: dup
    //   440: bipush #21
    //   442: bipush #-23
    //   444: bastore
    //   445: dup
    //   446: bipush #22
    //   448: bipush #-62
    //   450: bastore
    //   451: dup
    //   452: bipush #23
    //   454: bipush #95
    //   456: bastore
    //   457: dup
    //   458: bipush #24
    //   460: bipush #-127
    //   462: bastore
    //   463: dup
    //   464: bipush #25
    //   466: bipush #73
    //   468: bastore
    //   469: dup
    //   470: bipush #26
    //   472: bipush #19
    //   474: bastore
    //   475: dup
    //   476: bipush #27
    //   478: bipush #-94
    //   480: bastore
    //   481: dup
    //   482: bipush #28
    //   484: bipush #95
    //   486: bastore
    //   487: dup
    //   488: bipush #29
    //   490: bipush #87
    //   492: bastore
    //   493: dup
    //   494: bipush #30
    //   496: bipush #-113
    //   498: bastore
    //   499: dup
    //   500: bipush #31
    //   502: bipush #-102
    //   504: bastore
    //   505: invokespecial <init> : ([B)V
    //   508: putstatic burp/Zko9.ZC : Ljava/lang/Object;
    //   511: return
  }
  
  private static Throwable a(Throwable paramThrowable) {
    return paramThrowable;
  }
  
  private static String a(int paramInt1, int paramInt2) {
    int i = (paramInt1 ^ 0x1958) & 0xFFFF;
    if (b[i] == null) {
      char[] arrayOfChar = a[i].toCharArray();
      switch (arrayOfChar[0] & 0xFF) {
        case 0:
        
        case 1:
        
        case 2:
        
        case 3:
        
        case 4:
        
        case 5:
        
        case 6:
        
        case 7:
        
        case 8:
        
        case 9:
        
        case 10:
        
        case 11:
        
        case 12:
        
        case 13:
        
        case 14:
        
        case 15:
        
        case 16:
        
        case 17:
        
        case 18:
        
        case 19:
        
        case 20:
        
        case 21:
        
        case 22:
        
        case 23:
        
        case 24:
        
        case 25:
        
        case 26:
        
        case 27:
        
        case 28:
        
        case 29:
        
        case 30:
        
        case 31:
        
        case 32:
        
        case 33:
        
        case 34:
        
        case 35:
        
        case 36:
        
        case 37:
        
        case 38:
        
        case 39:
        
        case 40:
        
        case 41:
        
        case 42:
        
        case 43:
        
        case 44:
        
        case 45:
        
        case 46:
        
        case 47:
        
        case 48:
        
        case 49:
        
        case 50:
        
        case 51:
        
        case 52:
        
        case 53:
        
        case 54:
        
        case 55:
        
        case 56:
        
        case 57:
        
        case 58:
        
        case 59:
        
        case 60:
        
        case 61:
        
        case 62:
        
        case 63:
        
        case 64:
        
        case 65:
        
        case 66:
        
        case 67:
        
        case 68:
        
        case 69:
        
        case 70:
        
        case 71:
        
        case 72:
        
        case 73:
        
        case 74:
        
        case 75:
        
        case 76:
        
        case 77:
        
        case 78:
        
        case 79:
        
        case 80:
        
        case 81:
        
        case 82:
        
        case 83:
        
        case 84:
        
        case 85:
        
        case 86:
        
        case 87:
        
        case 88:
        
        case 89:
        
        case 90:
        
        case 91:
        
        case 92:
        
        case 93:
        
        case 94:
        
        case 95:
        
        case 96:
        
        case 97:
        
        case 98:
        
        case 99:
        
        case 100:
        
        case 101:
        
        case 102:
        
        case 103:
        
        case 104:
        
        case 105:
        
        case 106:
        
        case 107:
        
        case 108:
        
        case 109:
        
        case 110:
        
        case 111:
        
        case 112:
        
        case 113:
        
        case 114:
        
        case 115:
        
        case 116:
        
        case 117:
        
        case 118:
        
        case 119:
        
        case 120:
        
        case 121:
        
        case 122:
        
        case 123:
        
        case 124:
        
        case 125:
        
        case 126:
        
        case 127:
        
        case 128:
        
        case 129:
        
        case 130:
        
        case 131:
        
        case 132:
        
        case 133:
        
        case 134:
        
        case 135:
        
        case 136:
        
        case 137:
        
        case 138:
        
        case 139:
        
        case 140:
        
        case 141:
        
        case 142:
        
        case 143:
        
        case 144:
        
        case 145:
        
        case 146:
        
        case 147:
        
        case 148:
        
        case 149:
        
        case 150:
        
        case 151:
        
        case 152:
        
        case 153:
        
        case 154:
        
        case 155:
        
        case 156:
        
        case 157:
        
        case 158:
        
        case 159:
        
        case 160:
        
        case 161:
        
        case 162:
        
        case 163:
        
        case 164:
        
        case 165:
        
        case 166:
        
        case 167:
        
        case 168:
        
        case 169:
        
        case 170:
        
        case 171:
        
        case 172:
        
        case 173:
        
        case 174:
        
        case 175:
        
        case 176:
        
        case 177:
        
        case 178:
        
        case 179:
        
        case 180:
        
        case 181:
        
        case 182:
        
        case 183:
        
        case 184:
        
        case 185:
        
        case 186:
        
        case 187:
        
        case 188:
        
        case 189:
        
        case 190:
        
        case 191:
        
        case 192:
        
        case 193:
        
        case 194:
        
        case 195:
        
        case 196:
        
        case 197:
        
        case 198:
        
        case 199:
        
        case 200:
        
        case 201:
        
        case 202:
        
        case 203:
        
        case 204:
        
        case 205:
        
        case 206:
        
        case 207:
        
        case 208:
        
        case 209:
        
        case 210:
        
        case 211:
        
        case 212:
        
        case 213:
        
        case 214:
        
        case 215:
        
        case 216:
        
        case 217:
        
        case 218:
        
        case 219:
        
        case 220:
        
        case 221:
        
        case 222:
        
        case 223:
        
        case 224:
        
        case 225:
        
        case 226:
        
        case 227:
        
        case 228:
        
        case 229:
        
        case 230:
        
        case 231:
        
        case 232:
        
        case 233:
        
        case 234:
        
        case 235:
        
        case 236:
        
        case 237:
        
        case 238:
        
        case 239:
        
        case 240:
        
        case 241:
        
        case 242:
        
        case 243:
        
        case 244:
        
        case 245:
        
        case 246:
        
        case 247:
        
        case 248:
        
        case 249:
        
        case 250:
        
        case 251:
        
        case 252:
        
        case 253:
        
        case 254:
        
        default:
          break;
      } 
      char c = '';
      int j = (paramInt2 & 0xFF) - c;
      if (j < 0)
        j += 256; 
      int k = ((paramInt2 & 0xFFFF) >>> 8) - c;
      if (k < 0)
        k += 256; 
      for (byte b = 0; b < arrayOfChar.length; b++) {
        int m = b % 2;
        if (m == 0) {
          arrayOfChar[b] = (char)(arrayOfChar[b] ^ j);
          j = ((j >>> 3 | j << 5) ^ arrayOfChar[b]) & 0xFF;
        } else {
          arrayOfChar[b] = (char)(arrayOfChar[b] ^ k);
          k = ((k >>> 3 | k << 5) ^ arrayOfChar[b]) & 0xFF;
        } 
      } 
      b[i] = (new String(arrayOfChar)).intern();
    } 
    return b[i];
  }
}


/* Location:              C:\Program Files\BurpSuitePro\burpsuite_pro.jar!\burp\Zko9.class
 * Java compiler version: 21 (65.0)
 * JD-Core Version:       1.1.3
 */