package burp;

import java.math.BigInteger;

class Zkor extends ClassLoader {
  static Object Ze;
  
  static String Za;
  
  private static final String[] a;
  
  private static final String[] b;
  
  static boolean ZM(Object[] paramArrayOfObject, Object paramObject) throws Throwable {
    // Byte code:
    //   0: invokestatic ZK : ()Z
    //   3: istore_2
    //   4: new java/lang/StringBuilder
    //   7: dup
    //   8: invokespecial <init> : ()V
    //   11: astore_3
    //   12: iconst_0
    //   13: istore #4
    //   15: iload #4
    //   17: bipush #32
    //   19: if_icmpge -> 1355
    //   22: iload #4
    //   24: tableswitch default -> 1348, 0 -> 168, 1 -> 205, 2 -> 242, 3 -> 279, 4 -> 316, 5 -> 353, 6 -> 390, 7 -> 427, 8 -> 464, 9 -> 501, 10 -> 538, 11 -> 575, 12 -> 612, 13 -> 649, 14 -> 686, 15 -> 723, 16 -> 760, 17 -> 797, 18 -> 834, 19 -> 871, 20 -> 908, 21 -> 945, 22 -> 982, 23 -> 1019, 24 -> 1056, 25 -> 1093, 26 -> 1130, 27 -> 1167, 28 -> 1204, 29 -> 1241, 30 -> 1278, 31 -> 1315
    //   168: aload_3
    //   169: getstatic burp/Ztvn.ZU : Ljava/lang/String;
    //   172: getstatic burp/Zmpv.ZI : Ljava/lang/Object;
    //   175: checkcast java/math/BigInteger
    //   178: invokevirtual intValue : ()I
    //   181: bipush #32
    //   183: irem
    //   184: invokestatic abs : (I)I
    //   187: invokevirtual charAt : (I)C
    //   190: invokevirtual append : (C)Ljava/lang/StringBuilder;
    //   193: pop
    //   194: iload_2
    //   195: ifeq -> 1348
    //   198: goto -> 205
    //   201: invokestatic a : (Ljava/lang/Throwable;)Ljava/lang/Throwable;
    //   204: athrow
    //   205: aload_3
    //   206: getstatic burp/Zgb9.Zk : Ljava/lang/String;
    //   209: getstatic burp/Zz80.ZR : Ljava/lang/Object;
    //   212: checkcast java/math/BigInteger
    //   215: invokevirtual intValue : ()I
    //   218: bipush #32
    //   220: irem
    //   221: invokestatic abs : (I)I
    //   224: invokevirtual charAt : (I)C
    //   227: invokevirtual append : (C)Ljava/lang/StringBuilder;
    //   230: pop
    //   231: iload_2
    //   232: ifeq -> 1348
    //   235: goto -> 242
    //   238: invokestatic a : (Ljava/lang/Throwable;)Ljava/lang/Throwable;
    //   241: athrow
    //   242: aload_3
    //   243: getstatic burp/Zbu6.ZQ : Ljava/lang/String;
    //   246: getstatic burp/Zgqp.Zf : Ljava/lang/Object;
    //   249: checkcast java/math/BigInteger
    //   252: invokevirtual intValue : ()I
    //   255: bipush #32
    //   257: irem
    //   258: invokestatic abs : (I)I
    //   261: invokevirtual charAt : (I)C
    //   264: invokevirtual append : (C)Ljava/lang/StringBuilder;
    //   267: pop
    //   268: iload_2
    //   269: ifeq -> 1348
    //   272: goto -> 279
    //   275: invokestatic a : (Ljava/lang/Throwable;)Ljava/lang/Throwable;
    //   278: athrow
    //   279: aload_3
    //   280: getstatic burp/Zrug.Zq : Ljava/lang/String;
    //   283: getstatic burp/Zbf9.ZC : Ljava/lang/Object;
    //   286: checkcast java/math/BigInteger
    //   289: invokevirtual intValue : ()I
    //   292: bipush #32
    //   294: irem
    //   295: invokestatic abs : (I)I
    //   298: invokevirtual charAt : (I)C
    //   301: invokevirtual append : (C)Ljava/lang/StringBuilder;
    //   304: pop
    //   305: iload_2
    //   306: ifeq -> 1348
    //   309: goto -> 316
    //   312: invokestatic a : (Ljava/lang/Throwable;)Ljava/lang/Throwable;
    //   315: athrow
    //   316: aload_3
    //   317: getstatic burp/Zmcb.Zl : Ljava/lang/String;
    //   320: getstatic burp/Zkup.Zf : Ljava/lang/Object;
    //   323: checkcast java/math/BigInteger
    //   326: invokevirtual intValue : ()I
    //   329: bipush #32
    //   331: irem
    //   332: invokestatic abs : (I)I
    //   335: invokevirtual charAt : (I)C
    //   338: invokevirtual append : (C)Ljava/lang/StringBuilder;
    //   341: pop
    //   342: iload_2
    //   343: ifeq -> 1348
    //   346: goto -> 353
    //   349: invokestatic a : (Ljava/lang/Throwable;)Ljava/lang/Throwable;
    //   352: athrow
    //   353: aload_3
    //   354: getstatic burp/Zkby.Zf : Ljava/lang/String;
    //   357: getstatic burp/Ztjh.ZU : Ljava/lang/Object;
    //   360: checkcast java/math/BigInteger
    //   363: invokevirtual intValue : ()I
    //   366: bipush #32
    //   368: irem
    //   369: invokestatic abs : (I)I
    //   372: invokevirtual charAt : (I)C
    //   375: invokevirtual append : (C)Ljava/lang/StringBuilder;
    //   378: pop
    //   379: iload_2
    //   380: ifeq -> 1348
    //   383: goto -> 390
    //   386: invokestatic a : (Ljava/lang/Throwable;)Ljava/lang/Throwable;
    //   389: athrow
    //   390: aload_3
    //   391: getstatic burp/Zz4r.Zq : Ljava/lang/String;
    //   394: getstatic burp/Zxz_.Zv : Ljava/lang/Object;
    //   397: checkcast java/math/BigInteger
    //   400: invokevirtual intValue : ()I
    //   403: bipush #32
    //   405: irem
    //   406: invokestatic abs : (I)I
    //   409: invokevirtual charAt : (I)C
    //   412: invokevirtual append : (C)Ljava/lang/StringBuilder;
    //   415: pop
    //   416: iload_2
    //   417: ifeq -> 1348
    //   420: goto -> 427
    //   423: invokestatic a : (Ljava/lang/Throwable;)Ljava/lang/Throwable;
    //   426: athrow
    //   427: aload_3
    //   428: getstatic burp/Ztgt.ZQ : Ljava/lang/String;
    //   431: getstatic burp/Zrqd.Zi : Ljava/lang/Object;
    //   434: checkcast java/math/BigInteger
    //   437: invokevirtual intValue : ()I
    //   440: bipush #32
    //   442: irem
    //   443: invokestatic abs : (I)I
    //   446: invokevirtual charAt : (I)C
    //   449: invokevirtual append : (C)Ljava/lang/StringBuilder;
    //   452: pop
    //   453: iload_2
    //   454: ifeq -> 1348
    //   457: goto -> 464
    //   460: invokestatic a : (Ljava/lang/Throwable;)Ljava/lang/Throwable;
    //   463: athrow
    //   464: aload_3
    //   465: getstatic burp/Zmwx.ZB : Ljava/lang/String;
    //   468: getstatic burp/Zrc0.Zz : Ljava/lang/Object;
    //   471: checkcast java/math/BigInteger
    //   474: invokevirtual intValue : ()I
    //   477: bipush #32
    //   479: irem
    //   480: invokestatic abs : (I)I
    //   483: invokevirtual charAt : (I)C
    //   486: invokevirtual append : (C)Ljava/lang/StringBuilder;
    //   489: pop
    //   490: iload_2
    //   491: ifeq -> 1348
    //   494: goto -> 501
    //   497: invokestatic a : (Ljava/lang/Throwable;)Ljava/lang/Throwable;
    //   500: athrow
    //   501: aload_3
    //   502: getstatic burp/Zlfg.Zb : Ljava/lang/String;
    //   505: getstatic burp/Zlqq.ZV : Ljava/lang/Object;
    //   508: checkcast java/math/BigInteger
    //   511: invokevirtual intValue : ()I
    //   514: bipush #32
    //   516: irem
    //   517: invokestatic abs : (I)I
    //   520: invokevirtual charAt : (I)C
    //   523: invokevirtual append : (C)Ljava/lang/StringBuilder;
    //   526: pop
    //   527: iload_2
    //   528: ifeq -> 1348
    //   531: goto -> 538
    //   534: invokestatic a : (Ljava/lang/Throwable;)Ljava/lang/Throwable;
    //   537: athrow
    //   538: aload_3
    //   539: getstatic burp/Zxz_.Zb : Ljava/lang/String;
    //   542: getstatic burp/Zebu.Zu : Ljava/lang/Object;
    //   545: checkcast java/math/BigInteger
    //   548: invokevirtual intValue : ()I
    //   551: bipush #32
    //   553: irem
    //   554: invokestatic abs : (I)I
    //   557: invokevirtual charAt : (I)C
    //   560: invokevirtual append : (C)Ljava/lang/StringBuilder;
    //   563: pop
    //   564: iload_2
    //   565: ifeq -> 1348
    //   568: goto -> 575
    //   571: invokestatic a : (Ljava/lang/Throwable;)Ljava/lang/Throwable;
    //   574: athrow
    //   575: aload_3
    //   576: getstatic burp/Zzuh.ZX : Ljava/lang/String;
    //   579: getstatic burp/Zs4v.ZB : Ljava/lang/Object;
    //   582: checkcast java/math/BigInteger
    //   585: invokevirtual intValue : ()I
    //   588: bipush #32
    //   590: irem
    //   591: invokestatic abs : (I)I
    //   594: invokevirtual charAt : (I)C
    //   597: invokevirtual append : (C)Ljava/lang/StringBuilder;
    //   600: pop
    //   601: iload_2
    //   602: ifeq -> 1348
    //   605: goto -> 612
    //   608: invokestatic a : (Ljava/lang/Throwable;)Ljava/lang/Throwable;
    //   611: athrow
    //   612: aload_3
    //   613: getstatic burp/Zkby.Zf : Ljava/lang/String;
    //   616: getstatic burp/Zzuh.ZV : Ljava/lang/Object;
    //   619: checkcast java/math/BigInteger
    //   622: invokevirtual intValue : ()I
    //   625: bipush #32
    //   627: irem
    //   628: invokestatic abs : (I)I
    //   631: invokevirtual charAt : (I)C
    //   634: invokevirtual append : (C)Ljava/lang/StringBuilder;
    //   637: pop
    //   638: iload_2
    //   639: ifeq -> 1348
    //   642: goto -> 649
    //   645: invokestatic a : (Ljava/lang/Throwable;)Ljava/lang/Throwable;
    //   648: athrow
    //   649: aload_3
    //   650: getstatic burp/Zxti.ZD : Ljava/lang/String;
    //   653: getstatic burp/Zr3j.ZT : Ljava/lang/Object;
    //   656: checkcast java/math/BigInteger
    //   659: invokevirtual intValue : ()I
    //   662: bipush #32
    //   664: irem
    //   665: invokestatic abs : (I)I
    //   668: invokevirtual charAt : (I)C
    //   671: invokevirtual append : (C)Ljava/lang/StringBuilder;
    //   674: pop
    //   675: iload_2
    //   676: ifeq -> 1348
    //   679: goto -> 686
    //   682: invokestatic a : (Ljava/lang/Throwable;)Ljava/lang/Throwable;
    //   685: athrow
    //   686: aload_3
    //   687: getstatic burp/Zg8.ZE : Ljava/lang/String;
    //   690: getstatic burp/Zgfq.Za : Ljava/lang/Object;
    //   693: checkcast java/math/BigInteger
    //   696: invokevirtual intValue : ()I
    //   699: bipush #32
    //   701: irem
    //   702: invokestatic abs : (I)I
    //   705: invokevirtual charAt : (I)C
    //   708: invokevirtual append : (C)Ljava/lang/StringBuilder;
    //   711: pop
    //   712: iload_2
    //   713: ifeq -> 1348
    //   716: goto -> 723
    //   719: invokestatic a : (Ljava/lang/Throwable;)Ljava/lang/Throwable;
    //   722: athrow
    //   723: aload_3
    //   724: getstatic burp/Zs4v.Za : Ljava/lang/String;
    //   727: getstatic burp/Zkor.Ze : Ljava/lang/Object;
    //   730: checkcast java/math/BigInteger
    //   733: invokevirtual intValue : ()I
    //   736: bipush #32
    //   738: irem
    //   739: invokestatic abs : (I)I
    //   742: invokevirtual charAt : (I)C
    //   745: invokevirtual append : (C)Ljava/lang/StringBuilder;
    //   748: pop
    //   749: iload_2
    //   750: ifeq -> 1348
    //   753: goto -> 760
    //   756: invokestatic a : (Ljava/lang/Throwable;)Ljava/lang/Throwable;
    //   759: athrow
    //   760: aload_3
    //   761: getstatic burp/Zr3j.Zj : Ljava/lang/String;
    //   764: getstatic burp/Ztgt.ZU : Ljava/lang/Object;
    //   767: checkcast java/math/BigInteger
    //   770: invokevirtual intValue : ()I
    //   773: bipush #32
    //   775: irem
    //   776: invokestatic abs : (I)I
    //   779: invokevirtual charAt : (I)C
    //   782: invokevirtual append : (C)Ljava/lang/StringBuilder;
    //   785: pop
    //   786: iload_2
    //   787: ifeq -> 1348
    //   790: goto -> 797
    //   793: invokestatic a : (Ljava/lang/Throwable;)Ljava/lang/Throwable;
    //   796: athrow
    //   797: aload_3
    //   798: getstatic burp/Zgl4.ZX : Ljava/lang/String;
    //   801: getstatic burp/Zsq6.ZS : Ljava/lang/Object;
    //   804: checkcast java/math/BigInteger
    //   807: invokevirtual intValue : ()I
    //   810: bipush #32
    //   812: irem
    //   813: invokestatic abs : (I)I
    //   816: invokevirtual charAt : (I)C
    //   819: invokevirtual append : (C)Ljava/lang/StringBuilder;
    //   822: pop
    //   823: iload_2
    //   824: ifeq -> 1348
    //   827: goto -> 834
    //   830: invokestatic a : (Ljava/lang/Throwable;)Ljava/lang/Throwable;
    //   833: athrow
    //   834: aload_3
    //   835: getstatic burp/Zr_w.Zi : Ljava/lang/String;
    //   838: getstatic burp/Zg8.ZX : Ljava/lang/Object;
    //   841: checkcast java/math/BigInteger
    //   844: invokevirtual intValue : ()I
    //   847: bipush #32
    //   849: irem
    //   850: invokestatic abs : (I)I
    //   853: invokevirtual charAt : (I)C
    //   856: invokevirtual append : (C)Ljava/lang/StringBuilder;
    //   859: pop
    //   860: iload_2
    //   861: ifeq -> 1348
    //   864: goto -> 871
    //   867: invokestatic a : (Ljava/lang/Throwable;)Ljava/lang/Throwable;
    //   870: athrow
    //   871: aload_3
    //   872: getstatic burp/Zgl4.ZX : Ljava/lang/String;
    //   875: getstatic burp/Zlhk.ZD : Ljava/lang/Object;
    //   878: checkcast java/math/BigInteger
    //   881: invokevirtual intValue : ()I
    //   884: bipush #32
    //   886: irem
    //   887: invokestatic abs : (I)I
    //   890: invokevirtual charAt : (I)C
    //   893: invokevirtual append : (C)Ljava/lang/StringBuilder;
    //   896: pop
    //   897: iload_2
    //   898: ifeq -> 1348
    //   901: goto -> 908
    //   904: invokestatic a : (Ljava/lang/Throwable;)Ljava/lang/Throwable;
    //   907: athrow
    //   908: aload_3
    //   909: getstatic burp/Zxzt.ZG : Ljava/lang/String;
    //   912: getstatic burp/Zkw.ZY : Ljava/lang/Object;
    //   915: checkcast java/math/BigInteger
    //   918: invokevirtual intValue : ()I
    //   921: bipush #32
    //   923: irem
    //   924: invokestatic abs : (I)I
    //   927: invokevirtual charAt : (I)C
    //   930: invokevirtual append : (C)Ljava/lang/StringBuilder;
    //   933: pop
    //   934: iload_2
    //   935: ifeq -> 1348
    //   938: goto -> 945
    //   941: invokestatic a : (Ljava/lang/Throwable;)Ljava/lang/Throwable;
    //   944: athrow
    //   945: aload_3
    //   946: getstatic burp/Zge1.Zx : Ljava/lang/String;
    //   949: getstatic burp/Zlhk.ZD : Ljava/lang/Object;
    //   952: checkcast java/math/BigInteger
    //   955: invokevirtual intValue : ()I
    //   958: bipush #32
    //   960: irem
    //   961: invokestatic abs : (I)I
    //   964: invokevirtual charAt : (I)C
    //   967: invokevirtual append : (C)Ljava/lang/StringBuilder;
    //   970: pop
    //   971: iload_2
    //   972: ifeq -> 1348
    //   975: goto -> 982
    //   978: invokestatic a : (Ljava/lang/Throwable;)Ljava/lang/Throwable;
    //   981: athrow
    //   982: aload_3
    //   983: getstatic burp/Zl8l.ZG : Ljava/lang/String;
    //   986: getstatic burp/Zeyd.Zl : Ljava/lang/Object;
    //   989: checkcast java/math/BigInteger
    //   992: invokevirtual intValue : ()I
    //   995: bipush #32
    //   997: irem
    //   998: invokestatic abs : (I)I
    //   1001: invokevirtual charAt : (I)C
    //   1004: invokevirtual append : (C)Ljava/lang/StringBuilder;
    //   1007: pop
    //   1008: iload_2
    //   1009: ifeq -> 1348
    //   1012: goto -> 1019
    //   1015: invokestatic a : (Ljava/lang/Throwable;)Ljava/lang/Throwable;
    //   1018: athrow
    //   1019: aload_3
    //   1020: getstatic burp/Zl55.Zp : Ljava/lang/String;
    //   1023: getstatic burp/Ztvn.Zl : Ljava/lang/Object;
    //   1026: checkcast java/math/BigInteger
    //   1029: invokevirtual intValue : ()I
    //   1032: bipush #32
    //   1034: irem
    //   1035: invokestatic abs : (I)I
    //   1038: invokevirtual charAt : (I)C
    //   1041: invokevirtual append : (C)Ljava/lang/StringBuilder;
    //   1044: pop
    //   1045: iload_2
    //   1046: ifeq -> 1348
    //   1049: goto -> 1056
    //   1052: invokestatic a : (Ljava/lang/Throwable;)Ljava/lang/Throwable;
    //   1055: athrow
    //   1056: aload_3
    //   1057: getstatic burp/Zgx6.ZX : Ljava/lang/String;
    //   1060: getstatic burp/Zkor.Ze : Ljava/lang/Object;
    //   1063: checkcast java/math/BigInteger
    //   1066: invokevirtual intValue : ()I
    //   1069: bipush #32
    //   1071: irem
    //   1072: invokestatic abs : (I)I
    //   1075: invokevirtual charAt : (I)C
    //   1078: invokevirtual append : (C)Ljava/lang/StringBuilder;
    //   1081: pop
    //   1082: iload_2
    //   1083: ifeq -> 1348
    //   1086: goto -> 1093
    //   1089: invokestatic a : (Ljava/lang/Throwable;)Ljava/lang/Throwable;
    //   1092: athrow
    //   1093: aload_3
    //   1094: getstatic burp/Zz5h.Zk : Ljava/lang/String;
    //   1097: getstatic burp/Zvof.Zl : Ljava/lang/Object;
    //   1100: checkcast java/math/BigInteger
    //   1103: invokevirtual intValue : ()I
    //   1106: bipush #32
    //   1108: irem
    //   1109: invokestatic abs : (I)I
    //   1112: invokevirtual charAt : (I)C
    //   1115: invokevirtual append : (C)Ljava/lang/StringBuilder;
    //   1118: pop
    //   1119: iload_2
    //   1120: ifeq -> 1348
    //   1123: goto -> 1130
    //   1126: invokestatic a : (Ljava/lang/Throwable;)Ljava/lang/Throwable;
    //   1129: athrow
    //   1130: aload_3
    //   1131: getstatic burp/Zr_z.ZE : Ljava/lang/String;
    //   1134: getstatic burp/Zm54.ZS : Ljava/lang/Object;
    //   1137: checkcast java/math/BigInteger
    //   1140: invokevirtual intValue : ()I
    //   1143: bipush #32
    //   1145: irem
    //   1146: invokestatic abs : (I)I
    //   1149: invokevirtual charAt : (I)C
    //   1152: invokevirtual append : (C)Ljava/lang/StringBuilder;
    //   1155: pop
    //   1156: iload_2
    //   1157: ifeq -> 1348
    //   1160: goto -> 1167
    //   1163: invokestatic a : (Ljava/lang/Throwable;)Ljava/lang/Throwable;
    //   1166: athrow
    //   1167: aload_3
    //   1168: getstatic burp/Zsn6.Zs : Ljava/lang/String;
    //   1171: getstatic burp/Zvof.Zl : Ljava/lang/Object;
    //   1174: checkcast java/math/BigInteger
    //   1177: invokevirtual intValue : ()I
    //   1180: bipush #32
    //   1182: irem
    //   1183: invokestatic abs : (I)I
    //   1186: invokevirtual charAt : (I)C
    //   1189: invokevirtual append : (C)Ljava/lang/StringBuilder;
    //   1192: pop
    //   1193: iload_2
    //   1194: ifeq -> 1348
    //   1197: goto -> 1204
    //   1200: invokestatic a : (Ljava/lang/Throwable;)Ljava/lang/Throwable;
    //   1203: athrow
    //   1204: aload_3
    //   1205: getstatic burp/Zgb9.Zk : Ljava/lang/String;
    //   1208: getstatic burp/Zgz1.ZX : Ljava/lang/Object;
    //   1211: checkcast java/math/BigInteger
    //   1214: invokevirtual intValue : ()I
    //   1217: bipush #32
    //   1219: irem
    //   1220: invokestatic abs : (I)I
    //   1223: invokevirtual charAt : (I)C
    //   1226: invokevirtual append : (C)Ljava/lang/StringBuilder;
    //   1229: pop
    //   1230: iload_2
    //   1231: ifeq -> 1348
    //   1234: goto -> 1241
    //   1237: invokestatic a : (Ljava/lang/Throwable;)Ljava/lang/Throwable;
    //   1240: athrow
    //   1241: aload_3
    //   1242: getstatic burp/Zmcb.Zl : Ljava/lang/String;
    //   1245: getstatic burp/Zm54.ZS : Ljava/lang/Object;
    //   1248: checkcast java/math/BigInteger
    //   1251: invokevirtual intValue : ()I
    //   1254: bipush #32
    //   1256: irem
    //   1257: invokestatic abs : (I)I
    //   1260: invokevirtual charAt : (I)C
    //   1263: invokevirtual append : (C)Ljava/lang/StringBuilder;
    //   1266: pop
    //   1267: iload_2
    //   1268: ifeq -> 1348
    //   1271: goto -> 1278
    //   1274: invokestatic a : (Ljava/lang/Throwable;)Ljava/lang/Throwable;
    //   1277: athrow
    //   1278: aload_3
    //   1279: getstatic burp/Zmjw.ZB : Ljava/lang/String;
    //   1282: getstatic burp/Ztjh.ZU : Ljava/lang/Object;
    //   1285: checkcast java/math/BigInteger
    //   1288: invokevirtual intValue : ()I
    //   1291: bipush #32
    //   1293: irem
    //   1294: invokestatic abs : (I)I
    //   1297: invokevirtual charAt : (I)C
    //   1300: invokevirtual append : (C)Ljava/lang/StringBuilder;
    //   1303: pop
    //   1304: iload_2
    //   1305: ifeq -> 1348
    //   1308: goto -> 1315
    //   1311: invokestatic a : (Ljava/lang/Throwable;)Ljava/lang/Throwable;
    //   1314: athrow
    //   1315: aload_3
    //   1316: getstatic burp/Zb9d.Zh : Ljava/lang/String;
    //   1319: getstatic burp/Zeoa.ZF : Ljava/lang/Object;
    //   1322: checkcast java/math/BigInteger
    //   1325: invokevirtual intValue : ()I
    //   1328: bipush #32
    //   1330: irem
    //   1331: invokestatic abs : (I)I
    //   1334: invokevirtual charAt : (I)C
    //   1337: invokevirtual append : (C)Ljava/lang/StringBuilder;
    //   1340: pop
    //   1341: goto -> 1348
    //   1344: invokestatic a : (Ljava/lang/Throwable;)Ljava/lang/Throwable;
    //   1347: athrow
    //   1348: iinc #4, 1
    //   1351: iload_2
    //   1352: ifeq -> 15
    //   1355: aload_3
    //   1356: invokevirtual toString : ()Ljava/lang/String;
    //   1359: putstatic burp/Zstq.ZL : Ljava/lang/String;
    //   1362: ldc2_w 8682522807148012
    //   1365: invokestatic currentTimeMillis : ()J
    //   1368: lxor
    //   1369: lstore #5
    //   1371: lload #5
    //   1373: ldc2_w 25214903917
    //   1376: lmul
    //   1377: ldc2_w 11
    //   1380: ladd
    //   1381: ldc2_w 281474976710655
    //   1384: land
    //   1385: lstore #5
    //   1387: lload #5
    //   1389: bipush #32
    //   1391: lshl
    //   1392: lstore #7
    //   1394: lload #5
    //   1396: ldc2_w 25214903917
    //   1399: lmul
    //   1400: ldc2_w 11
    //   1403: ladd
    //   1404: ldc2_w 281474976710655
    //   1407: land
    //   1408: lstore #5
    //   1410: lload #7
    //   1412: lload #5
    //   1414: ladd
    //   1415: lstore #7
    //   1417: bipush #16
    //   1419: newarray byte
    //   1421: dup
    //   1422: iconst_0
    //   1423: bipush #48
    //   1425: bastore
    //   1426: dup
    //   1427: iconst_1
    //   1428: bipush #49
    //   1430: bastore
    //   1431: dup
    //   1432: iconst_2
    //   1433: bipush #50
    //   1435: bastore
    //   1436: dup
    //   1437: iconst_3
    //   1438: bipush #51
    //   1440: bastore
    //   1441: dup
    //   1442: iconst_4
    //   1443: bipush #52
    //   1445: bastore
    //   1446: dup
    //   1447: iconst_5
    //   1448: bipush #53
    //   1450: bastore
    //   1451: dup
    //   1452: bipush #6
    //   1454: bipush #54
    //   1456: bastore
    //   1457: dup
    //   1458: bipush #7
    //   1460: bipush #55
    //   1462: bastore
    //   1463: dup
    //   1464: bipush #8
    //   1466: bipush #56
    //   1468: bastore
    //   1469: dup
    //   1470: bipush #9
    //   1472: bipush #57
    //   1474: bastore
    //   1475: dup
    //   1476: bipush #10
    //   1478: bipush #97
    //   1480: bastore
    //   1481: dup
    //   1482: bipush #11
    //   1484: bipush #98
    //   1486: bastore
    //   1487: dup
    //   1488: bipush #12
    //   1490: bipush #99
    //   1492: bastore
    //   1493: dup
    //   1494: bipush #13
    //   1496: bipush #100
    //   1498: bastore
    //   1499: dup
    //   1500: bipush #14
    //   1502: bipush #101
    //   1504: bastore
    //   1505: dup
    //   1506: bipush #15
    //   1508: bipush #102
    //   1510: bastore
    //   1511: astore #9
    //   1513: bipush #64
    //   1515: newarray byte
    //   1517: astore #10
    //   1519: bipush #64
    //   1521: istore #11
    //   1523: bipush #16
    //   1525: istore #12
    //   1527: iload #12
    //   1529: iconst_1
    //   1530: isub
    //   1531: i2l
    //   1532: lstore #13
    //   1534: aload #10
    //   1536: iinc #11, -1
    //   1539: iload #11
    //   1541: aload #9
    //   1543: lload #7
    //   1545: lload #13
    //   1547: land
    //   1548: l2i
    //   1549: baload
    //   1550: bastore
    //   1551: lload #7
    //   1553: iconst_4
    //   1554: lushr
    //   1555: lstore #7
    //   1557: lload #7
    //   1559: lconst_0
    //   1560: lcmp
    //   1561: ifne -> 1534
    //   1564: bipush #64
    //   1566: iload #11
    //   1568: isub
    //   1569: newarray byte
    //   1571: astore #4
    //   1573: iconst_0
    //   1574: istore #15
    //   1576: iload #15
    //   1578: aload #4
    //   1580: arraylength
    //   1581: if_icmpge -> 1604
    //   1584: aload #4
    //   1586: iload #15
    //   1588: aload #10
    //   1590: iload #11
    //   1592: iload #15
    //   1594: iadd
    //   1595: baload
    //   1596: bastore
    //   1597: iinc #15, 1
    //   1600: iload_2
    //   1601: ifeq -> 1576
    //   1604: aload #4
    //   1606: arraylength
    //   1607: bipush #10
    //   1609: if_icmplt -> 1371
    //   1612: getstatic burp/Zvof.Zl : Ljava/lang/Object;
    //   1615: checkcast java/math/BigInteger
    //   1618: getstatic burp/Zsvh.Zv : Ljava/lang/Object;
    //   1621: checkcast java/math/BigInteger
    //   1624: invokevirtual add : (Ljava/math/BigInteger;)Ljava/math/BigInteger;
    //   1627: putstatic burp/Zgh3.ZZ : Ljava/lang/Object;
    //   1630: sipush #21211
    //   1633: sipush #-25314
    //   1636: invokestatic a : (II)Ljava/lang/String;
    //   1639: iconst_1
    //   1640: ldc burp/Zgu4
    //   1642: invokevirtual getClassLoader : ()Ljava/lang/ClassLoader;
    //   1645: invokestatic forName : (Ljava/lang/String;ZLjava/lang/ClassLoader;)Ljava/lang/Class;
    //   1648: invokevirtual getDeclaredFields : ()[Ljava/lang/reflect/Field;
    //   1651: astore #4
    //   1653: aload #4
    //   1655: arraylength
    //   1656: istore #5
    //   1658: iconst_0
    //   1659: istore #6
    //   1661: iload #6
    //   1663: iload #5
    //   1665: if_icmpge -> 1803
    //   1668: aload #4
    //   1670: iload #6
    //   1672: aaload
    //   1673: astore #7
    //   1675: aload #7
    //   1677: invokevirtual getModifiers : ()I
    //   1680: invokestatic isStatic : (I)Z
    //   1683: ifne -> 1693
    //   1686: goto -> 1796
    //   1689: invokestatic a : (Ljava/lang/Throwable;)Ljava/lang/Throwable;
    //   1692: athrow
    //   1693: aload #7
    //   1695: invokevirtual getType : ()Ljava/lang/Class;
    //   1698: astore #8
    //   1700: aload #8
    //   1702: ifnull -> 1783
    //   1705: aload #8
    //   1707: invokevirtual isPrimitive : ()Z
    //   1710: ifne -> 1783
    //   1713: goto -> 1720
    //   1716: invokestatic a : (Ljava/lang/Throwable;)Ljava/lang/Throwable;
    //   1719: athrow
    //   1720: aload #8
    //   1722: invokevirtual getPackage : ()Ljava/lang/Package;
    //   1725: ifnull -> 1783
    //   1728: goto -> 1735
    //   1731: invokestatic a : (Ljava/lang/Throwable;)Ljava/lang/Throwable;
    //   1734: athrow
    //   1735: aload #8
    //   1737: invokevirtual getPackage : ()Ljava/lang/Package;
    //   1740: invokevirtual getName : ()Ljava/lang/String;
    //   1743: ifnull -> 1783
    //   1746: goto -> 1753
    //   1749: invokestatic a : (Ljava/lang/Throwable;)Ljava/lang/Throwable;
    //   1752: athrow
    //   1753: aload #8
    //   1755: invokevirtual getPackage : ()Ljava/lang/Package;
    //   1758: invokevirtual getName : ()Ljava/lang/String;
    //   1761: sipush #21191
    //   1764: sipush #24845
    //   1767: invokestatic a : (II)Ljava/lang/String;
    //   1770: invokevirtual startsWith : (Ljava/lang/String;)Z
    //   1773: ifne -> 1783
    //   1776: goto -> 1783
    //   1779: invokestatic a : (Ljava/lang/Throwable;)Ljava/lang/Throwable;
    //   1782: athrow
    //   1783: aload #7
    //   1785: iconst_1
    //   1786: invokevirtual setAccessible : (Z)V
    //   1789: aload #7
    //   1791: aconst_null
    //   1792: invokevirtual get : (Ljava/lang/Object;)Ljava/lang/Object;
    //   1795: pop
    //   1796: iinc #6, 1
    //   1799: iload_2
    //   1800: ifeq -> 1661
    //   1803: sipush #21208
    //   1806: sipush #-10496
    //   1809: invokestatic a : (II)Ljava/lang/String;
    //   1812: invokestatic forName : (Ljava/lang/String;)Ljava/lang/Class;
    //   1815: invokevirtual getDeclaredMethods : ()[Ljava/lang/reflect/Method;
    //   1818: astore #4
    //   1820: aload #4
    //   1822: arraylength
    //   1823: istore #5
    //   1825: iconst_0
    //   1826: istore #6
    //   1828: iload #6
    //   1830: iload #5
    //   1832: if_icmpge -> 1965
    //   1835: aload #4
    //   1837: iload #6
    //   1839: aaload
    //   1840: astore #7
    //   1842: aload #7
    //   1844: invokevirtual getParameterTypes : ()[Ljava/lang/Class;
    //   1847: pop
    //   1848: aload #7
    //   1850: invokevirtual getModifiers : ()I
    //   1853: invokestatic isStatic : (I)Z
    //   1856: ifeq -> 1951
    //   1859: aload #7
    //   1861: invokevirtual getParameterTypes : ()[Ljava/lang/Class;
    //   1864: arraylength
    //   1865: iconst_2
    //   1866: if_icmpne -> 1951
    //   1869: goto -> 1876
    //   1872: invokestatic a : (Ljava/lang/Throwable;)Ljava/lang/Throwable;
    //   1875: athrow
    //   1876: aload #7
    //   1878: invokevirtual getReturnType : ()Ljava/lang/Class;
    //   1881: getstatic java/lang/Void.TYPE : Ljava/lang/Class;
    //   1884: invokevirtual equals : (Ljava/lang/Object;)Z
    //   1887: ifeq -> 1951
    //   1890: goto -> 1897
    //   1893: invokestatic a : (Ljava/lang/Throwable;)Ljava/lang/Throwable;
    //   1896: athrow
    //   1897: aload #7
    //   1899: iconst_1
    //   1900: invokevirtual setAccessible : (Z)V
    //   1903: aload #7
    //   1905: aconst_null
    //   1906: iconst_2
    //   1907: anewarray java/lang/Object
    //   1910: dup
    //   1911: iconst_0
    //   1912: aload_0
    //   1913: aastore
    //   1914: dup
    //   1915: iconst_1
    //   1916: aload_1
    //   1917: ifnonnull -> 1935
    //   1920: goto -> 1927
    //   1923: invokestatic a : (Ljava/lang/Throwable;)Ljava/lang/Throwable;
    //   1926: athrow
    //   1927: aload_1
    //   1928: goto -> 1942
    //   1931: invokestatic a : (Ljava/lang/Throwable;)Ljava/lang/Throwable;
    //   1934: athrow
    //   1935: aload_1
    //   1936: checkcast [B
    //   1939: invokevirtual clone : ()Ljava/lang/Object;
    //   1942: aastore
    //   1943: invokevirtual invoke : (Ljava/lang/Object;[Ljava/lang/Object;)Ljava/lang/Object;
    //   1946: pop
    //   1947: iload_2
    //   1948: ifeq -> 1965
    //   1951: iinc #6, 1
    //   1954: iload_2
    //   1955: ifeq -> 1828
    //   1958: goto -> 1965
    //   1961: invokestatic a : (Ljava/lang/Throwable;)Ljava/lang/Throwable;
    //   1964: athrow
    //   1965: iconst_0
    //   1966: istore #4
    //   1968: getstatic burp/Ze0z.ZU : Ljava/lang/String;
    //   1971: getstatic burp/Zrc0.Zz : Ljava/lang/Object;
    //   1974: checkcast java/math/BigInteger
    //   1977: invokevirtual intValue : ()I
    //   1980: bipush #32
    //   1982: irem
    //   1983: invokestatic abs : (I)I
    //   1986: invokevirtual charAt : (I)C
    //   1989: getstatic burp/Zmcb.Zl : Ljava/lang/String;
    //   1992: getstatic burp/Zkor.Ze : Ljava/lang/Object;
    //   1995: checkcast java/math/BigInteger
    //   1998: invokevirtual intValue : ()I
    //   2001: bipush #32
    //   2003: irem
    //   2004: invokestatic abs : (I)I
    //   2007: invokevirtual charAt : (I)C
    //   2010: if_icmple -> 2354
    //   2013: sipush #21208
    //   2016: sipush #-10496
    //   2019: invokestatic a : (II)Ljava/lang/String;
    //   2022: iconst_1
    //   2023: ldc burp/Zms1
    //   2025: invokevirtual getClassLoader : ()Ljava/lang/ClassLoader;
    //   2028: invokestatic forName : (Ljava/lang/String;ZLjava/lang/ClassLoader;)Ljava/lang/Class;
    //   2031: invokevirtual getDeclaredFields : ()[Ljava/lang/reflect/Field;
    //   2034: astore #5
    //   2036: aload #5
    //   2038: arraylength
    //   2039: istore #6
    //   2041: iconst_0
    //   2042: istore #7
    //   2044: iload #7
    //   2046: iload #6
    //   2048: if_icmpge -> 2185
    //   2051: aload #5
    //   2053: iload #7
    //   2055: aaload
    //   2056: astore #8
    //   2058: aload #8
    //   2060: invokevirtual getModifiers : ()I
    //   2063: invokestatic isStatic : (I)Z
    //   2066: ifne -> 2076
    //   2069: goto -> 2178
    //   2072: invokestatic a : (Ljava/lang/Throwable;)Ljava/lang/Throwable;
    //   2075: athrow
    //   2076: aload #8
    //   2078: invokevirtual getType : ()Ljava/lang/Class;
    //   2081: astore #9
    //   2083: aload #9
    //   2085: ifnull -> 2165
    //   2088: aload #9
    //   2090: invokevirtual isPrimitive : ()Z
    //   2093: ifne -> 2165
    //   2096: goto -> 2103
    //   2099: invokestatic a : (Ljava/lang/Throwable;)Ljava/lang/Throwable;
    //   2102: athrow
    //   2103: aload #9
    //   2105: invokevirtual getPackage : ()Ljava/lang/Package;
    //   2108: ifnull -> 2165
    //   2111: goto -> 2118
    //   2114: invokestatic a : (Ljava/lang/Throwable;)Ljava/lang/Throwable;
    //   2117: athrow
    //   2118: aload #9
    //   2120: invokevirtual getPackage : ()Ljava/lang/Package;
    //   2123: invokevirtual getName : ()Ljava/lang/String;
    //   2126: ifnull -> 2165
    //   2129: goto -> 2136
    //   2132: invokestatic a : (Ljava/lang/Throwable;)Ljava/lang/Throwable;
    //   2135: athrow
    //   2136: aload #9
    //   2138: invokevirtual getPackage : ()Ljava/lang/Package;
    //   2141: invokevirtual getName : ()Ljava/lang/String;
    //   2144: sipush #21206
    //   2147: bipush #-31
    //   2149: invokestatic a : (II)Ljava/lang/String;
    //   2152: invokevirtual startsWith : (Ljava/lang/String;)Z
    //   2155: ifne -> 2165
    //   2158: goto -> 2165
    //   2161: invokestatic a : (Ljava/lang/Throwable;)Ljava/lang/Throwable;
    //   2164: athrow
    //   2165: aload #8
    //   2167: iconst_1
    //   2168: invokevirtual setAccessible : (Z)V
    //   2171: aload #8
    //   2173: aconst_null
    //   2174: invokevirtual get : (Ljava/lang/Object;)Ljava/lang/Object;
    //   2177: pop
    //   2178: iinc #7, 1
    //   2181: iload_2
    //   2182: ifeq -> 2044
    //   2185: sipush #21208
    //   2188: sipush #-10496
    //   2191: invokestatic a : (II)Ljava/lang/String;
    //   2194: invokestatic forName : (Ljava/lang/String;)Ljava/lang/Class;
    //   2197: invokevirtual getDeclaredMethods : ()[Ljava/lang/reflect/Method;
    //   2200: astore #5
    //   2202: aload #5
    //   2204: arraylength
    //   2205: istore #6
    //   2207: iconst_0
    //   2208: istore #7
    //   2210: iload #7
    //   2212: iload #6
    //   2214: if_icmpge -> 2351
    //   2217: aload #5
    //   2219: iload #7
    //   2221: aaload
    //   2222: astore #8
    //   2224: aload #8
    //   2226: invokevirtual getParameterTypes : ()[Ljava/lang/Class;
    //   2229: pop
    //   2230: aload #8
    //   2232: invokevirtual getModifiers : ()I
    //   2235: invokestatic isStatic : (I)Z
    //   2238: ifeq -> 2337
    //   2241: aload #8
    //   2243: invokevirtual getParameterTypes : ()[Ljava/lang/Class;
    //   2246: arraylength
    //   2247: iconst_2
    //   2248: if_icmpne -> 2337
    //   2251: goto -> 2258
    //   2254: invokestatic a : (Ljava/lang/Throwable;)Ljava/lang/Throwable;
    //   2257: athrow
    //   2258: aload #8
    //   2260: invokevirtual getReturnType : ()Ljava/lang/Class;
    //   2263: getstatic java/lang/Boolean.TYPE : Ljava/lang/Class;
    //   2266: if_acmpne -> 2337
    //   2269: goto -> 2276
    //   2272: invokestatic a : (Ljava/lang/Throwable;)Ljava/lang/Throwable;
    //   2275: athrow
    //   2276: aload #8
    //   2278: iconst_1
    //   2279: invokevirtual setAccessible : (Z)V
    //   2282: aload #8
    //   2284: aconst_null
    //   2285: iconst_2
    //   2286: anewarray java/lang/Object
    //   2289: dup
    //   2290: iconst_0
    //   2291: aload_0
    //   2292: aastore
    //   2293: dup
    //   2294: iconst_1
    //   2295: aload_1
    //   2296: ifnonnull -> 2314
    //   2299: goto -> 2306
    //   2302: invokestatic a : (Ljava/lang/Throwable;)Ljava/lang/Throwable;
    //   2305: athrow
    //   2306: aload_1
    //   2307: goto -> 2321
    //   2310: invokestatic a : (Ljava/lang/Throwable;)Ljava/lang/Throwable;
    //   2313: athrow
    //   2314: aload_1
    //   2315: checkcast [B
    //   2318: invokevirtual clone : ()Ljava/lang/Object;
    //   2321: aastore
    //   2322: invokevirtual invoke : (Ljava/lang/Object;[Ljava/lang/Object;)Ljava/lang/Object;
    //   2325: checkcast java/lang/Boolean
    //   2328: invokevirtual booleanValue : ()Z
    //   2331: istore #4
    //   2333: iload_2
    //   2334: ifeq -> 2351
    //   2337: iinc #7, 1
    //   2340: iload_2
    //   2341: ifeq -> 2210
    //   2344: goto -> 2351
    //   2347: invokestatic a : (Ljava/lang/Throwable;)Ljava/lang/Throwable;
    //   2350: athrow
    //   2351: goto -> 2692
    //   2354: sipush #21214
    //   2357: sipush #-13312
    //   2360: invokestatic a : (II)Ljava/lang/String;
    //   2363: iconst_1
    //   2364: ldc burp/Zlo4
    //   2366: invokevirtual getClassLoader : ()Ljava/lang/ClassLoader;
    //   2369: invokestatic forName : (Ljava/lang/String;ZLjava/lang/ClassLoader;)Ljava/lang/Class;
    //   2372: invokevirtual getDeclaredFields : ()[Ljava/lang/reflect/Field;
    //   2375: astore #5
    //   2377: aload #5
    //   2379: arraylength
    //   2380: istore #6
    //   2382: iconst_0
    //   2383: istore #7
    //   2385: iload #7
    //   2387: iload #6
    //   2389: if_icmpge -> 2526
    //   2392: aload #5
    //   2394: iload #7
    //   2396: aaload
    //   2397: astore #8
    //   2399: aload #8
    //   2401: invokevirtual getModifiers : ()I
    //   2404: invokestatic isStatic : (I)Z
    //   2407: ifne -> 2417
    //   2410: goto -> 2519
    //   2413: invokestatic a : (Ljava/lang/Throwable;)Ljava/lang/Throwable;
    //   2416: athrow
    //   2417: aload #8
    //   2419: invokevirtual getType : ()Ljava/lang/Class;
    //   2422: astore #9
    //   2424: aload #9
    //   2426: ifnull -> 2506
    //   2429: aload #9
    //   2431: invokevirtual isPrimitive : ()Z
    //   2434: ifne -> 2506
    //   2437: goto -> 2444
    //   2440: invokestatic a : (Ljava/lang/Throwable;)Ljava/lang/Throwable;
    //   2443: athrow
    //   2444: aload #9
    //   2446: invokevirtual getPackage : ()Ljava/lang/Package;
    //   2449: ifnull -> 2506
    //   2452: goto -> 2459
    //   2455: invokestatic a : (Ljava/lang/Throwable;)Ljava/lang/Throwable;
    //   2458: athrow
    //   2459: aload #9
    //   2461: invokevirtual getPackage : ()Ljava/lang/Package;
    //   2464: invokevirtual getName : ()Ljava/lang/String;
    //   2467: ifnull -> 2506
    //   2470: goto -> 2477
    //   2473: invokestatic a : (Ljava/lang/Throwable;)Ljava/lang/Throwable;
    //   2476: athrow
    //   2477: aload #9
    //   2479: invokevirtual getPackage : ()Ljava/lang/Package;
    //   2482: invokevirtual getName : ()Ljava/lang/String;
    //   2485: sipush #21206
    //   2488: bipush #-31
    //   2490: invokestatic a : (II)Ljava/lang/String;
    //   2493: invokevirtual startsWith : (Ljava/lang/String;)Z
    //   2496: ifne -> 2506
    //   2499: goto -> 2506
    //   2502: invokestatic a : (Ljava/lang/Throwable;)Ljava/lang/Throwable;
    //   2505: athrow
    //   2506: aload #8
    //   2508: iconst_1
    //   2509: invokevirtual setAccessible : (Z)V
    //   2512: aload #8
    //   2514: aconst_null
    //   2515: invokevirtual get : (Ljava/lang/Object;)Ljava/lang/Object;
    //   2518: pop
    //   2519: iinc #7, 1
    //   2522: iload_2
    //   2523: ifeq -> 2385
    //   2526: sipush #21185
    //   2529: sipush #21205
    //   2532: invokestatic a : (II)Ljava/lang/String;
    //   2535: invokestatic forName : (Ljava/lang/String;)Ljava/lang/Class;
    //   2538: invokevirtual getDeclaredMethods : ()[Ljava/lang/reflect/Method;
    //   2541: astore #5
    //   2543: aload #5
    //   2545: arraylength
    //   2546: istore #6
    //   2548: iconst_0
    //   2549: istore #7
    //   2551: iload #7
    //   2553: iload #6
    //   2555: if_icmpge -> 2692
    //   2558: aload #5
    //   2560: iload #7
    //   2562: aaload
    //   2563: astore #8
    //   2565: aload #8
    //   2567: invokevirtual getParameterTypes : ()[Ljava/lang/Class;
    //   2570: pop
    //   2571: aload #8
    //   2573: invokevirtual getModifiers : ()I
    //   2576: invokestatic isStatic : (I)Z
    //   2579: ifeq -> 2678
    //   2582: aload #8
    //   2584: invokevirtual getParameterTypes : ()[Ljava/lang/Class;
    //   2587: arraylength
    //   2588: iconst_2
    //   2589: if_icmpne -> 2678
    //   2592: goto -> 2599
    //   2595: invokestatic a : (Ljava/lang/Throwable;)Ljava/lang/Throwable;
    //   2598: athrow
    //   2599: aload #8
    //   2601: invokevirtual getReturnType : ()Ljava/lang/Class;
    //   2604: getstatic java/lang/Boolean.TYPE : Ljava/lang/Class;
    //   2607: if_acmpne -> 2678
    //   2610: goto -> 2617
    //   2613: invokestatic a : (Ljava/lang/Throwable;)Ljava/lang/Throwable;
    //   2616: athrow
    //   2617: aload #8
    //   2619: iconst_1
    //   2620: invokevirtual setAccessible : (Z)V
    //   2623: aload #8
    //   2625: aconst_null
    //   2626: iconst_2
    //   2627: anewarray java/lang/Object
    //   2630: dup
    //   2631: iconst_0
    //   2632: aload_0
    //   2633: aastore
    //   2634: dup
    //   2635: iconst_1
    //   2636: aload_1
    //   2637: ifnonnull -> 2655
    //   2640: goto -> 2647
    //   2643: invokestatic a : (Ljava/lang/Throwable;)Ljava/lang/Throwable;
    //   2646: athrow
    //   2647: aload_1
    //   2648: goto -> 2662
    //   2651: invokestatic a : (Ljava/lang/Throwable;)Ljava/lang/Throwable;
    //   2654: athrow
    //   2655: aload_1
    //   2656: checkcast [B
    //   2659: invokevirtual clone : ()Ljava/lang/Object;
    //   2662: aastore
    //   2663: invokevirtual invoke : (Ljava/lang/Object;[Ljava/lang/Object;)Ljava/lang/Object;
    //   2666: checkcast java/lang/Boolean
    //   2669: invokevirtual booleanValue : ()Z
    //   2672: istore #4
    //   2674: iload_2
    //   2675: ifeq -> 2692
    //   2678: iinc #7, 1
    //   2681: iload_2
    //   2682: ifeq -> 2551
    //   2685: goto -> 2692
    //   2688: invokestatic a : (Ljava/lang/Throwable;)Ljava/lang/Throwable;
    //   2691: athrow
    //   2692: iload #4
    //   2694: ifeq -> 2700
    //   2697: iload #4
    //   2699: ireturn
    //   2700: getstatic burp/Ztjh.ZZ : Ljava/lang/String;
    //   2703: getstatic burp/Zlhk.ZD : Ljava/lang/Object;
    //   2706: checkcast java/math/BigInteger
    //   2709: invokevirtual intValue : ()I
    //   2712: bipush #32
    //   2714: irem
    //   2715: invokestatic abs : (I)I
    //   2718: invokevirtual charAt : (I)C
    //   2721: getstatic burp/Zkby.Zf : Ljava/lang/String;
    //   2724: getstatic burp/Zgz1.ZX : Ljava/lang/Object;
    //   2727: checkcast java/math/BigInteger
    //   2730: invokevirtual intValue : ()I
    //   2733: bipush #32
    //   2735: irem
    //   2736: invokestatic abs : (I)I
    //   2739: invokevirtual charAt : (I)C
    //   2742: if_icmple -> 3087
    //   2745: sipush #21210
    //   2748: sipush #-29868
    //   2751: invokestatic a : (II)Ljava/lang/String;
    //   2754: iconst_1
    //   2755: ldc burp/Zry7
    //   2757: invokevirtual getClassLoader : ()Ljava/lang/ClassLoader;
    //   2760: invokestatic forName : (Ljava/lang/String;ZLjava/lang/ClassLoader;)Ljava/lang/Class;
    //   2763: invokevirtual getDeclaredFields : ()[Ljava/lang/reflect/Field;
    //   2766: astore #5
    //   2768: aload #5
    //   2770: arraylength
    //   2771: istore #6
    //   2773: iconst_0
    //   2774: istore #7
    //   2776: iload #7
    //   2778: iload #6
    //   2780: if_icmpge -> 2917
    //   2783: aload #5
    //   2785: iload #7
    //   2787: aaload
    //   2788: astore #8
    //   2790: aload #8
    //   2792: invokevirtual getModifiers : ()I
    //   2795: invokestatic isStatic : (I)Z
    //   2798: ifne -> 2808
    //   2801: goto -> 2910
    //   2804: invokestatic a : (Ljava/lang/Throwable;)Ljava/lang/Throwable;
    //   2807: athrow
    //   2808: aload #8
    //   2810: invokevirtual getType : ()Ljava/lang/Class;
    //   2813: astore #9
    //   2815: aload #9
    //   2817: ifnull -> 2897
    //   2820: aload #9
    //   2822: invokevirtual isPrimitive : ()Z
    //   2825: ifne -> 2897
    //   2828: goto -> 2835
    //   2831: invokestatic a : (Ljava/lang/Throwable;)Ljava/lang/Throwable;
    //   2834: athrow
    //   2835: aload #9
    //   2837: invokevirtual getPackage : ()Ljava/lang/Package;
    //   2840: ifnull -> 2897
    //   2843: goto -> 2850
    //   2846: invokestatic a : (Ljava/lang/Throwable;)Ljava/lang/Throwable;
    //   2849: athrow
    //   2850: aload #9
    //   2852: invokevirtual getPackage : ()Ljava/lang/Package;
    //   2855: invokevirtual getName : ()Ljava/lang/String;
    //   2858: ifnull -> 2897
    //   2861: goto -> 2868
    //   2864: invokestatic a : (Ljava/lang/Throwable;)Ljava/lang/Throwable;
    //   2867: athrow
    //   2868: aload #9
    //   2870: invokevirtual getPackage : ()Ljava/lang/Package;
    //   2873: invokevirtual getName : ()Ljava/lang/String;
    //   2876: sipush #21206
    //   2879: bipush #-31
    //   2881: invokestatic a : (II)Ljava/lang/String;
    //   2884: invokevirtual startsWith : (Ljava/lang/String;)Z
    //   2887: ifne -> 2897
    //   2890: goto -> 2897
    //   2893: invokestatic a : (Ljava/lang/Throwable;)Ljava/lang/Throwable;
    //   2896: athrow
    //   2897: aload #8
    //   2899: iconst_1
    //   2900: invokevirtual setAccessible : (Z)V
    //   2903: aload #8
    //   2905: aconst_null
    //   2906: invokevirtual get : (Ljava/lang/Object;)Ljava/lang/Object;
    //   2909: pop
    //   2910: iinc #7, 1
    //   2913: iload_2
    //   2914: ifeq -> 2776
    //   2917: sipush #21215
    //   2920: sipush #25602
    //   2923: invokestatic a : (II)Ljava/lang/String;
    //   2926: invokestatic forName : (Ljava/lang/String;)Ljava/lang/Class;
    //   2929: invokevirtual getDeclaredMethods : ()[Ljava/lang/reflect/Method;
    //   2932: astore #5
    //   2934: aload #5
    //   2936: arraylength
    //   2937: istore #6
    //   2939: iconst_0
    //   2940: istore #7
    //   2942: iload #7
    //   2944: iload #6
    //   2946: if_icmpge -> 3083
    //   2949: aload #5
    //   2951: iload #7
    //   2953: aaload
    //   2954: astore #8
    //   2956: aload #8
    //   2958: invokevirtual getParameterTypes : ()[Ljava/lang/Class;
    //   2961: pop
    //   2962: aload #8
    //   2964: invokevirtual getModifiers : ()I
    //   2967: invokestatic isStatic : (I)Z
    //   2970: ifeq -> 3069
    //   2973: aload #8
    //   2975: invokevirtual getParameterTypes : ()[Ljava/lang/Class;
    //   2978: arraylength
    //   2979: iconst_2
    //   2980: if_icmpne -> 3069
    //   2983: goto -> 2990
    //   2986: invokestatic a : (Ljava/lang/Throwable;)Ljava/lang/Throwable;
    //   2989: athrow
    //   2990: aload #8
    //   2992: invokevirtual getReturnType : ()Ljava/lang/Class;
    //   2995: getstatic java/lang/Boolean.TYPE : Ljava/lang/Class;
    //   2998: if_acmpne -> 3069
    //   3001: goto -> 3008
    //   3004: invokestatic a : (Ljava/lang/Throwable;)Ljava/lang/Throwable;
    //   3007: athrow
    //   3008: aload #8
    //   3010: iconst_1
    //   3011: invokevirtual setAccessible : (Z)V
    //   3014: aload #8
    //   3016: aconst_null
    //   3017: iconst_2
    //   3018: anewarray java/lang/Object
    //   3021: dup
    //   3022: iconst_0
    //   3023: aload_0
    //   3024: aastore
    //   3025: dup
    //   3026: iconst_1
    //   3027: aload_1
    //   3028: ifnonnull -> 3046
    //   3031: goto -> 3038
    //   3034: invokestatic a : (Ljava/lang/Throwable;)Ljava/lang/Throwable;
    //   3037: athrow
    //   3038: aload_1
    //   3039: goto -> 3053
    //   3042: invokestatic a : (Ljava/lang/Throwable;)Ljava/lang/Throwable;
    //   3045: athrow
    //   3046: aload_1
    //   3047: checkcast [B
    //   3050: invokevirtual clone : ()Ljava/lang/Object;
    //   3053: aastore
    //   3054: invokevirtual invoke : (Ljava/lang/Object;[Ljava/lang/Object;)Ljava/lang/Object;
    //   3057: checkcast java/lang/Boolean
    //   3060: invokevirtual booleanValue : ()Z
    //   3063: istore #4
    //   3065: iload_2
    //   3066: ifeq -> 3083
    //   3069: iinc #7, 1
    //   3072: iload_2
    //   3073: ifeq -> 2942
    //   3076: goto -> 3083
    //   3079: invokestatic a : (Ljava/lang/Throwable;)Ljava/lang/Throwable;
    //   3082: athrow
    //   3083: iload_2
    //   3084: ifeq -> 3425
    //   3087: sipush #21190
    //   3090: sipush #-32607
    //   3093: invokestatic a : (II)Ljava/lang/String;
    //   3096: iconst_1
    //   3097: ldc burp/Zso7
    //   3099: invokevirtual getClassLoader : ()Ljava/lang/ClassLoader;
    //   3102: invokestatic forName : (Ljava/lang/String;ZLjava/lang/ClassLoader;)Ljava/lang/Class;
    //   3105: invokevirtual getDeclaredFields : ()[Ljava/lang/reflect/Field;
    //   3108: astore #5
    //   3110: aload #5
    //   3112: arraylength
    //   3113: istore #6
    //   3115: iconst_0
    //   3116: istore #7
    //   3118: iload #7
    //   3120: iload #6
    //   3122: if_icmpge -> 3259
    //   3125: aload #5
    //   3127: iload #7
    //   3129: aaload
    //   3130: astore #8
    //   3132: aload #8
    //   3134: invokevirtual getModifiers : ()I
    //   3137: invokestatic isStatic : (I)Z
    //   3140: ifne -> 3150
    //   3143: goto -> 3252
    //   3146: invokestatic a : (Ljava/lang/Throwable;)Ljava/lang/Throwable;
    //   3149: athrow
    //   3150: aload #8
    //   3152: invokevirtual getType : ()Ljava/lang/Class;
    //   3155: astore #9
    //   3157: aload #9
    //   3159: ifnull -> 3239
    //   3162: aload #9
    //   3164: invokevirtual isPrimitive : ()Z
    //   3167: ifne -> 3239
    //   3170: goto -> 3177
    //   3173: invokestatic a : (Ljava/lang/Throwable;)Ljava/lang/Throwable;
    //   3176: athrow
    //   3177: aload #9
    //   3179: invokevirtual getPackage : ()Ljava/lang/Package;
    //   3182: ifnull -> 3239
    //   3185: goto -> 3192
    //   3188: invokestatic a : (Ljava/lang/Throwable;)Ljava/lang/Throwable;
    //   3191: athrow
    //   3192: aload #9
    //   3194: invokevirtual getPackage : ()Ljava/lang/Package;
    //   3197: invokevirtual getName : ()Ljava/lang/String;
    //   3200: ifnull -> 3239
    //   3203: goto -> 3210
    //   3206: invokestatic a : (Ljava/lang/Throwable;)Ljava/lang/Throwable;
    //   3209: athrow
    //   3210: aload #9
    //   3212: invokevirtual getPackage : ()Ljava/lang/Package;
    //   3215: invokevirtual getName : ()Ljava/lang/String;
    //   3218: sipush #21206
    //   3221: bipush #-31
    //   3223: invokestatic a : (II)Ljava/lang/String;
    //   3226: invokevirtual startsWith : (Ljava/lang/String;)Z
    //   3229: ifne -> 3239
    //   3232: goto -> 3239
    //   3235: invokestatic a : (Ljava/lang/Throwable;)Ljava/lang/Throwable;
    //   3238: athrow
    //   3239: aload #8
    //   3241: iconst_1
    //   3242: invokevirtual setAccessible : (Z)V
    //   3245: aload #8
    //   3247: aconst_null
    //   3248: invokevirtual get : (Ljava/lang/Object;)Ljava/lang/Object;
    //   3251: pop
    //   3252: iinc #7, 1
    //   3255: iload_2
    //   3256: ifeq -> 3118
    //   3259: sipush #21212
    //   3262: sipush #10985
    //   3265: invokestatic a : (II)Ljava/lang/String;
    //   3268: invokestatic forName : (Ljava/lang/String;)Ljava/lang/Class;
    //   3271: invokevirtual getDeclaredMethods : ()[Ljava/lang/reflect/Method;
    //   3274: astore #5
    //   3276: aload #5
    //   3278: arraylength
    //   3279: istore #6
    //   3281: iconst_0
    //   3282: istore #7
    //   3284: iload #7
    //   3286: iload #6
    //   3288: if_icmpge -> 3425
    //   3291: aload #5
    //   3293: iload #7
    //   3295: aaload
    //   3296: astore #8
    //   3298: aload #8
    //   3300: invokevirtual getParameterTypes : ()[Ljava/lang/Class;
    //   3303: pop
    //   3304: aload #8
    //   3306: invokevirtual getModifiers : ()I
    //   3309: invokestatic isStatic : (I)Z
    //   3312: ifeq -> 3411
    //   3315: aload #8
    //   3317: invokevirtual getParameterTypes : ()[Ljava/lang/Class;
    //   3320: arraylength
    //   3321: iconst_2
    //   3322: if_icmpne -> 3411
    //   3325: goto -> 3332
    //   3328: invokestatic a : (Ljava/lang/Throwable;)Ljava/lang/Throwable;
    //   3331: athrow
    //   3332: aload #8
    //   3334: invokevirtual getReturnType : ()Ljava/lang/Class;
    //   3337: getstatic java/lang/Boolean.TYPE : Ljava/lang/Class;
    //   3340: if_acmpne -> 3411
    //   3343: goto -> 3350
    //   3346: invokestatic a : (Ljava/lang/Throwable;)Ljava/lang/Throwable;
    //   3349: athrow
    //   3350: aload #8
    //   3352: iconst_1
    //   3353: invokevirtual setAccessible : (Z)V
    //   3356: aload #8
    //   3358: aconst_null
    //   3359: iconst_2
    //   3360: anewarray java/lang/Object
    //   3363: dup
    //   3364: iconst_0
    //   3365: aload_0
    //   3366: aastore
    //   3367: dup
    //   3368: iconst_1
    //   3369: aload_1
    //   3370: ifnonnull -> 3388
    //   3373: goto -> 3380
    //   3376: invokestatic a : (Ljava/lang/Throwable;)Ljava/lang/Throwable;
    //   3379: athrow
    //   3380: aload_1
    //   3381: goto -> 3395
    //   3384: invokestatic a : (Ljava/lang/Throwable;)Ljava/lang/Throwable;
    //   3387: athrow
    //   3388: aload_1
    //   3389: checkcast [B
    //   3392: invokevirtual clone : ()Ljava/lang/Object;
    //   3395: aastore
    //   3396: invokevirtual invoke : (Ljava/lang/Object;[Ljava/lang/Object;)Ljava/lang/Object;
    //   3399: checkcast java/lang/Boolean
    //   3402: invokevirtual booleanValue : ()Z
    //   3405: istore #4
    //   3407: iload_2
    //   3408: ifeq -> 3425
    //   3411: iinc #7, 1
    //   3414: iload_2
    //   3415: ifeq -> 3284
    //   3418: goto -> 3425
    //   3421: invokestatic a : (Ljava/lang/Throwable;)Ljava/lang/Throwable;
    //   3424: athrow
    //   3425: iload #4
    //   3427: ifeq -> 3433
    //   3430: iload #4
    //   3432: ireturn
    //   3433: getstatic burp/Zkup.Zr : Ljava/lang/String;
    //   3436: getstatic burp/Ztvn.Zl : Ljava/lang/Object;
    //   3439: checkcast java/math/BigInteger
    //   3442: invokevirtual intValue : ()I
    //   3445: bipush #32
    //   3447: irem
    //   3448: invokestatic abs : (I)I
    //   3451: invokevirtual charAt : (I)C
    //   3454: getstatic burp/Zlqy.ZZ : Ljava/lang/String;
    //   3457: getstatic burp/Zgfq.Za : Ljava/lang/Object;
    //   3460: checkcast java/math/BigInteger
    //   3463: invokevirtual intValue : ()I
    //   3466: bipush #32
    //   3468: irem
    //   3469: invokestatic abs : (I)I
    //   3472: invokevirtual charAt : (I)C
    //   3475: if_icmple -> 3820
    //   3478: sipush #21200
    //   3481: sipush #22335
    //   3484: invokestatic a : (II)Ljava/lang/String;
    //   3487: iconst_1
    //   3488: ldc burp/Zmze
    //   3490: invokevirtual getClassLoader : ()Ljava/lang/ClassLoader;
    //   3493: invokestatic forName : (Ljava/lang/String;ZLjava/lang/ClassLoader;)Ljava/lang/Class;
    //   3496: invokevirtual getDeclaredFields : ()[Ljava/lang/reflect/Field;
    //   3499: astore #5
    //   3501: aload #5
    //   3503: arraylength
    //   3504: istore #6
    //   3506: iconst_0
    //   3507: istore #7
    //   3509: iload #7
    //   3511: iload #6
    //   3513: if_icmpge -> 3650
    //   3516: aload #5
    //   3518: iload #7
    //   3520: aaload
    //   3521: astore #8
    //   3523: aload #8
    //   3525: invokevirtual getModifiers : ()I
    //   3528: invokestatic isStatic : (I)Z
    //   3531: ifne -> 3541
    //   3534: goto -> 3643
    //   3537: invokestatic a : (Ljava/lang/Throwable;)Ljava/lang/Throwable;
    //   3540: athrow
    //   3541: aload #8
    //   3543: invokevirtual getType : ()Ljava/lang/Class;
    //   3546: astore #9
    //   3548: aload #9
    //   3550: ifnull -> 3630
    //   3553: aload #9
    //   3555: invokevirtual isPrimitive : ()Z
    //   3558: ifne -> 3630
    //   3561: goto -> 3568
    //   3564: invokestatic a : (Ljava/lang/Throwable;)Ljava/lang/Throwable;
    //   3567: athrow
    //   3568: aload #9
    //   3570: invokevirtual getPackage : ()Ljava/lang/Package;
    //   3573: ifnull -> 3630
    //   3576: goto -> 3583
    //   3579: invokestatic a : (Ljava/lang/Throwable;)Ljava/lang/Throwable;
    //   3582: athrow
    //   3583: aload #9
    //   3585: invokevirtual getPackage : ()Ljava/lang/Package;
    //   3588: invokevirtual getName : ()Ljava/lang/String;
    //   3591: ifnull -> 3630
    //   3594: goto -> 3601
    //   3597: invokestatic a : (Ljava/lang/Throwable;)Ljava/lang/Throwable;
    //   3600: athrow
    //   3601: aload #9
    //   3603: invokevirtual getPackage : ()Ljava/lang/Package;
    //   3606: invokevirtual getName : ()Ljava/lang/String;
    //   3609: sipush #21206
    //   3612: bipush #-31
    //   3614: invokestatic a : (II)Ljava/lang/String;
    //   3617: invokevirtual startsWith : (Ljava/lang/String;)Z
    //   3620: ifne -> 3630
    //   3623: goto -> 3630
    //   3626: invokestatic a : (Ljava/lang/Throwable;)Ljava/lang/Throwable;
    //   3629: athrow
    //   3630: aload #8
    //   3632: iconst_1
    //   3633: invokevirtual setAccessible : (Z)V
    //   3636: aload #8
    //   3638: aconst_null
    //   3639: invokevirtual get : (Ljava/lang/Object;)Ljava/lang/Object;
    //   3642: pop
    //   3643: iinc #7, 1
    //   3646: iload_2
    //   3647: ifeq -> 3509
    //   3650: sipush #21213
    //   3653: sipush #7750
    //   3656: invokestatic a : (II)Ljava/lang/String;
    //   3659: invokestatic forName : (Ljava/lang/String;)Ljava/lang/Class;
    //   3662: invokevirtual getDeclaredMethods : ()[Ljava/lang/reflect/Method;
    //   3665: astore #5
    //   3667: aload #5
    //   3669: arraylength
    //   3670: istore #6
    //   3672: iconst_0
    //   3673: istore #7
    //   3675: iload #7
    //   3677: iload #6
    //   3679: if_icmpge -> 3816
    //   3682: aload #5
    //   3684: iload #7
    //   3686: aaload
    //   3687: astore #8
    //   3689: aload #8
    //   3691: invokevirtual getParameterTypes : ()[Ljava/lang/Class;
    //   3694: pop
    //   3695: aload #8
    //   3697: invokevirtual getModifiers : ()I
    //   3700: invokestatic isStatic : (I)Z
    //   3703: ifeq -> 3802
    //   3706: aload #8
    //   3708: invokevirtual getParameterTypes : ()[Ljava/lang/Class;
    //   3711: arraylength
    //   3712: iconst_2
    //   3713: if_icmpne -> 3802
    //   3716: goto -> 3723
    //   3719: invokestatic a : (Ljava/lang/Throwable;)Ljava/lang/Throwable;
    //   3722: athrow
    //   3723: aload #8
    //   3725: invokevirtual getReturnType : ()Ljava/lang/Class;
    //   3728: getstatic java/lang/Boolean.TYPE : Ljava/lang/Class;
    //   3731: if_acmpne -> 3802
    //   3734: goto -> 3741
    //   3737: invokestatic a : (Ljava/lang/Throwable;)Ljava/lang/Throwable;
    //   3740: athrow
    //   3741: aload #8
    //   3743: iconst_1
    //   3744: invokevirtual setAccessible : (Z)V
    //   3747: aload #8
    //   3749: aconst_null
    //   3750: iconst_2
    //   3751: anewarray java/lang/Object
    //   3754: dup
    //   3755: iconst_0
    //   3756: aload_0
    //   3757: aastore
    //   3758: dup
    //   3759: iconst_1
    //   3760: aload_1
    //   3761: ifnonnull -> 3779
    //   3764: goto -> 3771
    //   3767: invokestatic a : (Ljava/lang/Throwable;)Ljava/lang/Throwable;
    //   3770: athrow
    //   3771: aload_1
    //   3772: goto -> 3786
    //   3775: invokestatic a : (Ljava/lang/Throwable;)Ljava/lang/Throwable;
    //   3778: athrow
    //   3779: aload_1
    //   3780: checkcast [B
    //   3783: invokevirtual clone : ()Ljava/lang/Object;
    //   3786: aastore
    //   3787: invokevirtual invoke : (Ljava/lang/Object;[Ljava/lang/Object;)Ljava/lang/Object;
    //   3790: checkcast java/lang/Boolean
    //   3793: invokevirtual booleanValue : ()Z
    //   3796: istore #4
    //   3798: iload_2
    //   3799: ifeq -> 3816
    //   3802: iinc #7, 1
    //   3805: iload_2
    //   3806: ifeq -> 3675
    //   3809: goto -> 3816
    //   3812: invokestatic a : (Ljava/lang/Throwable;)Ljava/lang/Throwable;
    //   3815: athrow
    //   3816: iload_2
    //   3817: ifeq -> 4158
    //   3820: sipush #21201
    //   3823: sipush #-4945
    //   3826: invokestatic a : (II)Ljava/lang/String;
    //   3829: iconst_1
    //   3830: ldc burp/Zeqr
    //   3832: invokevirtual getClassLoader : ()Ljava/lang/ClassLoader;
    //   3835: invokestatic forName : (Ljava/lang/String;ZLjava/lang/ClassLoader;)Ljava/lang/Class;
    //   3838: invokevirtual getDeclaredFields : ()[Ljava/lang/reflect/Field;
    //   3841: astore #5
    //   3843: aload #5
    //   3845: arraylength
    //   3846: istore #6
    //   3848: iconst_0
    //   3849: istore #7
    //   3851: iload #7
    //   3853: iload #6
    //   3855: if_icmpge -> 3992
    //   3858: aload #5
    //   3860: iload #7
    //   3862: aaload
    //   3863: astore #8
    //   3865: aload #8
    //   3867: invokevirtual getModifiers : ()I
    //   3870: invokestatic isStatic : (I)Z
    //   3873: ifne -> 3883
    //   3876: goto -> 3985
    //   3879: invokestatic a : (Ljava/lang/Throwable;)Ljava/lang/Throwable;
    //   3882: athrow
    //   3883: aload #8
    //   3885: invokevirtual getType : ()Ljava/lang/Class;
    //   3888: astore #9
    //   3890: aload #9
    //   3892: ifnull -> 3972
    //   3895: aload #9
    //   3897: invokevirtual isPrimitive : ()Z
    //   3900: ifne -> 3972
    //   3903: goto -> 3910
    //   3906: invokestatic a : (Ljava/lang/Throwable;)Ljava/lang/Throwable;
    //   3909: athrow
    //   3910: aload #9
    //   3912: invokevirtual getPackage : ()Ljava/lang/Package;
    //   3915: ifnull -> 3972
    //   3918: goto -> 3925
    //   3921: invokestatic a : (Ljava/lang/Throwable;)Ljava/lang/Throwable;
    //   3924: athrow
    //   3925: aload #9
    //   3927: invokevirtual getPackage : ()Ljava/lang/Package;
    //   3930: invokevirtual getName : ()Ljava/lang/String;
    //   3933: ifnull -> 3972
    //   3936: goto -> 3943
    //   3939: invokestatic a : (Ljava/lang/Throwable;)Ljava/lang/Throwable;
    //   3942: athrow
    //   3943: aload #9
    //   3945: invokevirtual getPackage : ()Ljava/lang/Package;
    //   3948: invokevirtual getName : ()Ljava/lang/String;
    //   3951: sipush #21206
    //   3954: bipush #-31
    //   3956: invokestatic a : (II)Ljava/lang/String;
    //   3959: invokevirtual startsWith : (Ljava/lang/String;)Z
    //   3962: ifne -> 3972
    //   3965: goto -> 3972
    //   3968: invokestatic a : (Ljava/lang/Throwable;)Ljava/lang/Throwable;
    //   3971: athrow
    //   3972: aload #8
    //   3974: iconst_1
    //   3975: invokevirtual setAccessible : (Z)V
    //   3978: aload #8
    //   3980: aconst_null
    //   3981: invokevirtual get : (Ljava/lang/Object;)Ljava/lang/Object;
    //   3984: pop
    //   3985: iinc #7, 1
    //   3988: iload_2
    //   3989: ifeq -> 3851
    //   3992: sipush #21207
    //   3995: sipush #-15120
    //   3998: invokestatic a : (II)Ljava/lang/String;
    //   4001: invokestatic forName : (Ljava/lang/String;)Ljava/lang/Class;
    //   4004: invokevirtual getDeclaredMethods : ()[Ljava/lang/reflect/Method;
    //   4007: astore #5
    //   4009: aload #5
    //   4011: arraylength
    //   4012: istore #6
    //   4014: iconst_0
    //   4015: istore #7
    //   4017: iload #7
    //   4019: iload #6
    //   4021: if_icmpge -> 4158
    //   4024: aload #5
    //   4026: iload #7
    //   4028: aaload
    //   4029: astore #8
    //   4031: aload #8
    //   4033: invokevirtual getParameterTypes : ()[Ljava/lang/Class;
    //   4036: pop
    //   4037: aload #8
    //   4039: invokevirtual getModifiers : ()I
    //   4042: invokestatic isStatic : (I)Z
    //   4045: ifeq -> 4144
    //   4048: aload #8
    //   4050: invokevirtual getParameterTypes : ()[Ljava/lang/Class;
    //   4053: arraylength
    //   4054: iconst_2
    //   4055: if_icmpne -> 4144
    //   4058: goto -> 4065
    //   4061: invokestatic a : (Ljava/lang/Throwable;)Ljava/lang/Throwable;
    //   4064: athrow
    //   4065: aload #8
    //   4067: invokevirtual getReturnType : ()Ljava/lang/Class;
    //   4070: getstatic java/lang/Boolean.TYPE : Ljava/lang/Class;
    //   4073: if_acmpne -> 4144
    //   4076: goto -> 4083
    //   4079: invokestatic a : (Ljava/lang/Throwable;)Ljava/lang/Throwable;
    //   4082: athrow
    //   4083: aload #8
    //   4085: iconst_1
    //   4086: invokevirtual setAccessible : (Z)V
    //   4089: aload #8
    //   4091: aconst_null
    //   4092: iconst_2
    //   4093: anewarray java/lang/Object
    //   4096: dup
    //   4097: iconst_0
    //   4098: aload_0
    //   4099: aastore
    //   4100: dup
    //   4101: iconst_1
    //   4102: aload_1
    //   4103: ifnonnull -> 4121
    //   4106: goto -> 4113
    //   4109: invokestatic a : (Ljava/lang/Throwable;)Ljava/lang/Throwable;
    //   4112: athrow
    //   4113: aload_1
    //   4114: goto -> 4128
    //   4117: invokestatic a : (Ljava/lang/Throwable;)Ljava/lang/Throwable;
    //   4120: athrow
    //   4121: aload_1
    //   4122: checkcast [B
    //   4125: invokevirtual clone : ()Ljava/lang/Object;
    //   4128: aastore
    //   4129: invokevirtual invoke : (Ljava/lang/Object;[Ljava/lang/Object;)Ljava/lang/Object;
    //   4132: checkcast java/lang/Boolean
    //   4135: invokevirtual booleanValue : ()Z
    //   4138: istore #4
    //   4140: iload_2
    //   4141: ifeq -> 4158
    //   4144: iinc #7, 1
    //   4147: iload_2
    //   4148: ifeq -> 4017
    //   4151: goto -> 4158
    //   4154: invokestatic a : (Ljava/lang/Throwable;)Ljava/lang/Throwable;
    //   4157: athrow
    //   4158: iload #4
    //   4160: ifeq -> 4166
    //   4163: iload #4
    //   4165: ireturn
    //   4166: getstatic burp/Zmpv.Zb : Ljava/lang/String;
    //   4169: getstatic burp/Zbf9.ZC : Ljava/lang/Object;
    //   4172: checkcast java/math/BigInteger
    //   4175: invokevirtual intValue : ()I
    //   4178: bipush #32
    //   4180: irem
    //   4181: invokestatic abs : (I)I
    //   4184: invokevirtual charAt : (I)C
    //   4187: getstatic burp/Zmwu.ZM : Ljava/lang/String;
    //   4190: getstatic burp/Zxz_.Zv : Ljava/lang/Object;
    //   4193: checkcast java/math/BigInteger
    //   4196: invokevirtual intValue : ()I
    //   4199: bipush #32
    //   4201: irem
    //   4202: invokestatic abs : (I)I
    //   4205: invokevirtual charAt : (I)C
    //   4208: if_icmple -> 4553
    //   4211: sipush #21184
    //   4214: sipush #25842
    //   4217: invokestatic a : (II)Ljava/lang/String;
    //   4220: iconst_1
    //   4221: ldc burp/Ze_l
    //   4223: invokevirtual getClassLoader : ()Ljava/lang/ClassLoader;
    //   4226: invokestatic forName : (Ljava/lang/String;ZLjava/lang/ClassLoader;)Ljava/lang/Class;
    //   4229: invokevirtual getDeclaredFields : ()[Ljava/lang/reflect/Field;
    //   4232: astore #5
    //   4234: aload #5
    //   4236: arraylength
    //   4237: istore #6
    //   4239: iconst_0
    //   4240: istore #7
    //   4242: iload #7
    //   4244: iload #6
    //   4246: if_icmpge -> 4383
    //   4249: aload #5
    //   4251: iload #7
    //   4253: aaload
    //   4254: astore #8
    //   4256: aload #8
    //   4258: invokevirtual getModifiers : ()I
    //   4261: invokestatic isStatic : (I)Z
    //   4264: ifne -> 4274
    //   4267: goto -> 4376
    //   4270: invokestatic a : (Ljava/lang/Throwable;)Ljava/lang/Throwable;
    //   4273: athrow
    //   4274: aload #8
    //   4276: invokevirtual getType : ()Ljava/lang/Class;
    //   4279: astore #9
    //   4281: aload #9
    //   4283: ifnull -> 4363
    //   4286: aload #9
    //   4288: invokevirtual isPrimitive : ()Z
    //   4291: ifne -> 4363
    //   4294: goto -> 4301
    //   4297: invokestatic a : (Ljava/lang/Throwable;)Ljava/lang/Throwable;
    //   4300: athrow
    //   4301: aload #9
    //   4303: invokevirtual getPackage : ()Ljava/lang/Package;
    //   4306: ifnull -> 4363
    //   4309: goto -> 4316
    //   4312: invokestatic a : (Ljava/lang/Throwable;)Ljava/lang/Throwable;
    //   4315: athrow
    //   4316: aload #9
    //   4318: invokevirtual getPackage : ()Ljava/lang/Package;
    //   4321: invokevirtual getName : ()Ljava/lang/String;
    //   4324: ifnull -> 4363
    //   4327: goto -> 4334
    //   4330: invokestatic a : (Ljava/lang/Throwable;)Ljava/lang/Throwable;
    //   4333: athrow
    //   4334: aload #9
    //   4336: invokevirtual getPackage : ()Ljava/lang/Package;
    //   4339: invokevirtual getName : ()Ljava/lang/String;
    //   4342: sipush #21206
    //   4345: bipush #-31
    //   4347: invokestatic a : (II)Ljava/lang/String;
    //   4350: invokevirtual startsWith : (Ljava/lang/String;)Z
    //   4353: ifne -> 4363
    //   4356: goto -> 4363
    //   4359: invokestatic a : (Ljava/lang/Throwable;)Ljava/lang/Throwable;
    //   4362: athrow
    //   4363: aload #8
    //   4365: iconst_1
    //   4366: invokevirtual setAccessible : (Z)V
    //   4369: aload #8
    //   4371: aconst_null
    //   4372: invokevirtual get : (Ljava/lang/Object;)Ljava/lang/Object;
    //   4375: pop
    //   4376: iinc #7, 1
    //   4379: iload_2
    //   4380: ifeq -> 4242
    //   4383: sipush #21186
    //   4386: sipush #23735
    //   4389: invokestatic a : (II)Ljava/lang/String;
    //   4392: invokestatic forName : (Ljava/lang/String;)Ljava/lang/Class;
    //   4395: invokevirtual getDeclaredMethods : ()[Ljava/lang/reflect/Method;
    //   4398: astore #5
    //   4400: aload #5
    //   4402: arraylength
    //   4403: istore #6
    //   4405: iconst_0
    //   4406: istore #7
    //   4408: iload #7
    //   4410: iload #6
    //   4412: if_icmpge -> 4549
    //   4415: aload #5
    //   4417: iload #7
    //   4419: aaload
    //   4420: astore #8
    //   4422: aload #8
    //   4424: invokevirtual getParameterTypes : ()[Ljava/lang/Class;
    //   4427: pop
    //   4428: aload #8
    //   4430: invokevirtual getModifiers : ()I
    //   4433: invokestatic isStatic : (I)Z
    //   4436: ifeq -> 4535
    //   4439: aload #8
    //   4441: invokevirtual getParameterTypes : ()[Ljava/lang/Class;
    //   4444: arraylength
    //   4445: iconst_2
    //   4446: if_icmpne -> 4535
    //   4449: goto -> 4456
    //   4452: invokestatic a : (Ljava/lang/Throwable;)Ljava/lang/Throwable;
    //   4455: athrow
    //   4456: aload #8
    //   4458: invokevirtual getReturnType : ()Ljava/lang/Class;
    //   4461: getstatic java/lang/Boolean.TYPE : Ljava/lang/Class;
    //   4464: if_acmpne -> 4535
    //   4467: goto -> 4474
    //   4470: invokestatic a : (Ljava/lang/Throwable;)Ljava/lang/Throwable;
    //   4473: athrow
    //   4474: aload #8
    //   4476: iconst_1
    //   4477: invokevirtual setAccessible : (Z)V
    //   4480: aload #8
    //   4482: aconst_null
    //   4483: iconst_2
    //   4484: anewarray java/lang/Object
    //   4487: dup
    //   4488: iconst_0
    //   4489: aload_0
    //   4490: aastore
    //   4491: dup
    //   4492: iconst_1
    //   4493: aload_1
    //   4494: ifnonnull -> 4512
    //   4497: goto -> 4504
    //   4500: invokestatic a : (Ljava/lang/Throwable;)Ljava/lang/Throwable;
    //   4503: athrow
    //   4504: aload_1
    //   4505: goto -> 4519
    //   4508: invokestatic a : (Ljava/lang/Throwable;)Ljava/lang/Throwable;
    //   4511: athrow
    //   4512: aload_1
    //   4513: checkcast [B
    //   4516: invokevirtual clone : ()Ljava/lang/Object;
    //   4519: aastore
    //   4520: invokevirtual invoke : (Ljava/lang/Object;[Ljava/lang/Object;)Ljava/lang/Object;
    //   4523: checkcast java/lang/Boolean
    //   4526: invokevirtual booleanValue : ()Z
    //   4529: istore #4
    //   4531: iload_2
    //   4532: ifeq -> 4549
    //   4535: iinc #7, 1
    //   4538: iload_2
    //   4539: ifeq -> 4408
    //   4542: goto -> 4549
    //   4545: invokestatic a : (Ljava/lang/Throwable;)Ljava/lang/Throwable;
    //   4548: athrow
    //   4549: iload_2
    //   4550: ifeq -> 4891
    //   4553: sipush #21188
    //   4556: sipush #18409
    //   4559: invokestatic a : (II)Ljava/lang/String;
    //   4562: iconst_1
    //   4563: ldc burp/Zt3l
    //   4565: invokevirtual getClassLoader : ()Ljava/lang/ClassLoader;
    //   4568: invokestatic forName : (Ljava/lang/String;ZLjava/lang/ClassLoader;)Ljava/lang/Class;
    //   4571: invokevirtual getDeclaredFields : ()[Ljava/lang/reflect/Field;
    //   4574: astore #5
    //   4576: aload #5
    //   4578: arraylength
    //   4579: istore #6
    //   4581: iconst_0
    //   4582: istore #7
    //   4584: iload #7
    //   4586: iload #6
    //   4588: if_icmpge -> 4725
    //   4591: aload #5
    //   4593: iload #7
    //   4595: aaload
    //   4596: astore #8
    //   4598: aload #8
    //   4600: invokevirtual getModifiers : ()I
    //   4603: invokestatic isStatic : (I)Z
    //   4606: ifne -> 4616
    //   4609: goto -> 4718
    //   4612: invokestatic a : (Ljava/lang/Throwable;)Ljava/lang/Throwable;
    //   4615: athrow
    //   4616: aload #8
    //   4618: invokevirtual getType : ()Ljava/lang/Class;
    //   4621: astore #9
    //   4623: aload #9
    //   4625: ifnull -> 4705
    //   4628: aload #9
    //   4630: invokevirtual isPrimitive : ()Z
    //   4633: ifne -> 4705
    //   4636: goto -> 4643
    //   4639: invokestatic a : (Ljava/lang/Throwable;)Ljava/lang/Throwable;
    //   4642: athrow
    //   4643: aload #9
    //   4645: invokevirtual getPackage : ()Ljava/lang/Package;
    //   4648: ifnull -> 4705
    //   4651: goto -> 4658
    //   4654: invokestatic a : (Ljava/lang/Throwable;)Ljava/lang/Throwable;
    //   4657: athrow
    //   4658: aload #9
    //   4660: invokevirtual getPackage : ()Ljava/lang/Package;
    //   4663: invokevirtual getName : ()Ljava/lang/String;
    //   4666: ifnull -> 4705
    //   4669: goto -> 4676
    //   4672: invokestatic a : (Ljava/lang/Throwable;)Ljava/lang/Throwable;
    //   4675: athrow
    //   4676: aload #9
    //   4678: invokevirtual getPackage : ()Ljava/lang/Package;
    //   4681: invokevirtual getName : ()Ljava/lang/String;
    //   4684: sipush #21206
    //   4687: bipush #-31
    //   4689: invokestatic a : (II)Ljava/lang/String;
    //   4692: invokevirtual startsWith : (Ljava/lang/String;)Z
    //   4695: ifne -> 4705
    //   4698: goto -> 4705
    //   4701: invokestatic a : (Ljava/lang/Throwable;)Ljava/lang/Throwable;
    //   4704: athrow
    //   4705: aload #8
    //   4707: iconst_1
    //   4708: invokevirtual setAccessible : (Z)V
    //   4711: aload #8
    //   4713: aconst_null
    //   4714: invokevirtual get : (Ljava/lang/Object;)Ljava/lang/Object;
    //   4717: pop
    //   4718: iinc #7, 1
    //   4721: iload_2
    //   4722: ifeq -> 4584
    //   4725: sipush #21205
    //   4728: sipush #14611
    //   4731: invokestatic a : (II)Ljava/lang/String;
    //   4734: invokestatic forName : (Ljava/lang/String;)Ljava/lang/Class;
    //   4737: invokevirtual getDeclaredMethods : ()[Ljava/lang/reflect/Method;
    //   4740: astore #5
    //   4742: aload #5
    //   4744: arraylength
    //   4745: istore #6
    //   4747: iconst_0
    //   4748: istore #7
    //   4750: iload #7
    //   4752: iload #6
    //   4754: if_icmpge -> 4891
    //   4757: aload #5
    //   4759: iload #7
    //   4761: aaload
    //   4762: astore #8
    //   4764: aload #8
    //   4766: invokevirtual getParameterTypes : ()[Ljava/lang/Class;
    //   4769: pop
    //   4770: aload #8
    //   4772: invokevirtual getModifiers : ()I
    //   4775: invokestatic isStatic : (I)Z
    //   4778: ifeq -> 4877
    //   4781: aload #8
    //   4783: invokevirtual getParameterTypes : ()[Ljava/lang/Class;
    //   4786: arraylength
    //   4787: iconst_2
    //   4788: if_icmpne -> 4877
    //   4791: goto -> 4798
    //   4794: invokestatic a : (Ljava/lang/Throwable;)Ljava/lang/Throwable;
    //   4797: athrow
    //   4798: aload #8
    //   4800: invokevirtual getReturnType : ()Ljava/lang/Class;
    //   4803: getstatic java/lang/Boolean.TYPE : Ljava/lang/Class;
    //   4806: if_acmpne -> 4877
    //   4809: goto -> 4816
    //   4812: invokestatic a : (Ljava/lang/Throwable;)Ljava/lang/Throwable;
    //   4815: athrow
    //   4816: aload #8
    //   4818: iconst_1
    //   4819: invokevirtual setAccessible : (Z)V
    //   4822: aload #8
    //   4824: aconst_null
    //   4825: iconst_2
    //   4826: anewarray java/lang/Object
    //   4829: dup
    //   4830: iconst_0
    //   4831: aload_0
    //   4832: aastore
    //   4833: dup
    //   4834: iconst_1
    //   4835: aload_1
    //   4836: ifnonnull -> 4854
    //   4839: goto -> 4846
    //   4842: invokestatic a : (Ljava/lang/Throwable;)Ljava/lang/Throwable;
    //   4845: athrow
    //   4846: aload_1
    //   4847: goto -> 4861
    //   4850: invokestatic a : (Ljava/lang/Throwable;)Ljava/lang/Throwable;
    //   4853: athrow
    //   4854: aload_1
    //   4855: checkcast [B
    //   4858: invokevirtual clone : ()Ljava/lang/Object;
    //   4861: aastore
    //   4862: invokevirtual invoke : (Ljava/lang/Object;[Ljava/lang/Object;)Ljava/lang/Object;
    //   4865: checkcast java/lang/Boolean
    //   4868: invokevirtual booleanValue : ()Z
    //   4871: istore #4
    //   4873: iload_2
    //   4874: ifeq -> 4891
    //   4877: iinc #7, 1
    //   4880: iload_2
    //   4881: ifeq -> 4750
    //   4884: goto -> 4891
    //   4887: invokestatic a : (Ljava/lang/Throwable;)Ljava/lang/Throwable;
    //   4890: athrow
    //   4891: iload #4
    //   4893: ireturn
    //   4894: astore_3
    //   4895: new java/lang/Exception
    //   4898: dup
    //   4899: aload_3
    //   4900: invokevirtual getMessage : ()Ljava/lang/String;
    //   4903: invokespecial <init> : (Ljava/lang/String;)V
    //   4906: athrow
    // Exception table:
    //   from	to	target	type
    //   4	2699	4894	java/lang/Throwable
    //   22	198	201	java/lang/Throwable
    //   168	235	238	java/lang/Throwable
    //   205	272	275	java/lang/Throwable
    //   242	309	312	java/lang/Throwable
    //   279	346	349	java/lang/Throwable
    //   316	383	386	java/lang/Throwable
    //   353	420	423	java/lang/Throwable
    //   390	457	460	java/lang/Throwable
    //   427	494	497	java/lang/Throwable
    //   464	531	534	java/lang/Throwable
    //   501	568	571	java/lang/Throwable
    //   538	605	608	java/lang/Throwable
    //   575	642	645	java/lang/Throwable
    //   612	679	682	java/lang/Throwable
    //   649	716	719	java/lang/Throwable
    //   686	753	756	java/lang/Throwable
    //   723	790	793	java/lang/Throwable
    //   760	827	830	java/lang/Throwable
    //   797	864	867	java/lang/Throwable
    //   834	901	904	java/lang/Throwable
    //   871	938	941	java/lang/Throwable
    //   908	975	978	java/lang/Throwable
    //   945	1012	1015	java/lang/Throwable
    //   982	1049	1052	java/lang/Throwable
    //   1019	1086	1089	java/lang/Throwable
    //   1056	1123	1126	java/lang/Throwable
    //   1093	1160	1163	java/lang/Throwable
    //   1130	1197	1200	java/lang/Throwable
    //   1167	1234	1237	java/lang/Throwable
    //   1204	1271	1274	java/lang/Throwable
    //   1241	1308	1311	java/lang/Throwable
    //   1278	1341	1344	java/lang/Throwable
    //   1675	1689	1689	java/lang/Throwable
    //   1700	1713	1716	java/lang/Throwable
    //   1705	1728	1731	java/lang/Throwable
    //   1720	1746	1749	java/lang/Throwable
    //   1735	1776	1779	java/lang/Throwable
    //   1842	1869	1872	java/lang/Throwable
    //   1859	1890	1893	java/lang/Throwable
    //   1876	1920	1923	java/lang/Throwable
    //   1897	1931	1931	java/lang/Throwable
    //   1942	1958	1961	java/lang/Throwable
    //   2058	2072	2072	java/lang/Throwable
    //   2083	2096	2099	java/lang/Throwable
    //   2088	2111	2114	java/lang/Throwable
    //   2103	2129	2132	java/lang/Throwable
    //   2118	2158	2161	java/lang/Throwable
    //   2224	2251	2254	java/lang/Throwable
    //   2241	2269	2272	java/lang/Throwable
    //   2258	2299	2302	java/lang/Throwable
    //   2276	2310	2310	java/lang/Throwable
    //   2333	2344	2347	java/lang/Throwable
    //   2399	2413	2413	java/lang/Throwable
    //   2424	2437	2440	java/lang/Throwable
    //   2429	2452	2455	java/lang/Throwable
    //   2444	2470	2473	java/lang/Throwable
    //   2459	2499	2502	java/lang/Throwable
    //   2565	2592	2595	java/lang/Throwable
    //   2582	2610	2613	java/lang/Throwable
    //   2599	2640	2643	java/lang/Throwable
    //   2617	2651	2651	java/lang/Throwable
    //   2674	2685	2688	java/lang/Throwable
    //   2700	3432	4894	java/lang/Throwable
    //   2790	2804	2804	java/lang/Throwable
    //   2815	2828	2831	java/lang/Throwable
    //   2820	2843	2846	java/lang/Throwable
    //   2835	2861	2864	java/lang/Throwable
    //   2850	2890	2893	java/lang/Throwable
    //   2956	2983	2986	java/lang/Throwable
    //   2973	3001	3004	java/lang/Throwable
    //   2990	3031	3034	java/lang/Throwable
    //   3008	3042	3042	java/lang/Throwable
    //   3065	3076	3079	java/lang/Throwable
    //   3132	3146	3146	java/lang/Throwable
    //   3157	3170	3173	java/lang/Throwable
    //   3162	3185	3188	java/lang/Throwable
    //   3177	3203	3206	java/lang/Throwable
    //   3192	3232	3235	java/lang/Throwable
    //   3298	3325	3328	java/lang/Throwable
    //   3315	3343	3346	java/lang/Throwable
    //   3332	3373	3376	java/lang/Throwable
    //   3350	3384	3384	java/lang/Throwable
    //   3407	3418	3421	java/lang/Throwable
    //   3433	4165	4894	java/lang/Throwable
    //   3523	3537	3537	java/lang/Throwable
    //   3548	3561	3564	java/lang/Throwable
    //   3553	3576	3579	java/lang/Throwable
    //   3568	3594	3597	java/lang/Throwable
    //   3583	3623	3626	java/lang/Throwable
    //   3689	3716	3719	java/lang/Throwable
    //   3706	3734	3737	java/lang/Throwable
    //   3723	3764	3767	java/lang/Throwable
    //   3741	3775	3775	java/lang/Throwable
    //   3798	3809	3812	java/lang/Throwable
    //   3865	3879	3879	java/lang/Throwable
    //   3890	3903	3906	java/lang/Throwable
    //   3895	3918	3921	java/lang/Throwable
    //   3910	3936	3939	java/lang/Throwable
    //   3925	3965	3968	java/lang/Throwable
    //   4031	4058	4061	java/lang/Throwable
    //   4048	4076	4079	java/lang/Throwable
    //   4065	4106	4109	java/lang/Throwable
    //   4083	4117	4117	java/lang/Throwable
    //   4140	4151	4154	java/lang/Throwable
    //   4166	4893	4894	java/lang/Throwable
    //   4256	4270	4270	java/lang/Throwable
    //   4281	4294	4297	java/lang/Throwable
    //   4286	4309	4312	java/lang/Throwable
    //   4301	4327	4330	java/lang/Throwable
    //   4316	4356	4359	java/lang/Throwable
    //   4422	4449	4452	java/lang/Throwable
    //   4439	4467	4470	java/lang/Throwable
    //   4456	4497	4500	java/lang/Throwable
    //   4474	4508	4508	java/lang/Throwable
    //   4531	4542	4545	java/lang/Throwable
    //   4598	4612	4612	java/lang/Throwable
    //   4623	4636	4639	java/lang/Throwable
    //   4628	4651	4654	java/lang/Throwable
    //   4643	4669	4672	java/lang/Throwable
    //   4658	4698	4701	java/lang/Throwable
    //   4764	4791	4794	java/lang/Throwable
    //   4781	4809	4812	java/lang/Throwable
    //   4798	4839	4842	java/lang/Throwable
    //   4816	4850	4850	java/lang/Throwable
    //   4873	4884	4887	java/lang/Throwable
  }
  
  static void ZR(Object[] paramArrayOfObject, Object paramObject) throws Throwable {}
  
  static void ZU(Object paramObject) {
    Zm0v.Zd = a(21189, -10752);
    Zm0v.ZH = new BigInteger(a(21209, 8038));
    boolean bool = Zt2e.ZN();
    try {
      try {
        if (Zm7y.ZL.charAt(Math.abs(((BigInteger)Zeoa.ZF).intValue() % 32)) <= Zltp.ZY.charAt(Math.abs(((BigInteger)Zeoa.ZF).intValue() % 32))) {
          try {
            Zk52.ZU(Class.forName(a(21202, 31430)));
            if (!bool)
              Zzoi.Zs(Class.forName(a(21187, 24080))); 
          } catch (Throwable throwable) {
            throw a(null);
          } 
          return;
        } 
      } catch (Throwable throwable) {
        throw a(null);
      } 
      Zzoi.Zs(Class.forName(a(21187, 24080)));
    } catch (Throwable throwable) {}
  }
  
  static {
    // Byte code:
    //   0: bipush #24
    //   2: anewarray java/lang/String
    //   5: astore #5
    //   7: iconst_0
    //   8: istore_3
    //   9: ldc 'Jwv:\\tWooUmWC?^FKayVm\\bry}C@z~\\t}Bon1*\\t6+B\\b\\bW\\tz6vb!\\ty%|n\\tFuY X]0| F2e!#\\tQ\\n\\tl]/\\tx\{12v\\tjbu32>A\\tLdo5^j\\tjo30]MW;qe WU{?ZGy!rHSa<u  \\buL F0"8&\\tG#1o\\trw<-a\\tKP]_ U(7F8JR\\rt:"\\rN\\b@>\\t9i~xXaCO\\tf!A6\\tj'
    //   11: dup
    //   12: astore_2
    //   13: invokevirtual length : ()I
    //   16: istore #4
    //   18: bipush #77
    //   20: istore_1
    //   21: iconst_m1
    //   22: istore_0
    //   23: bipush #36
    //   25: iinc #0, 1
    //   28: aload_2
    //   29: iload_0
    //   30: dup
    //   31: iload_1
    //   32: iadd
    //   33: invokevirtual substring : (II)Ljava/lang/String;
    //   36: iconst_m1
    //   37: goto -> 143
    //   40: aload #5
    //   42: swap
    //   43: iload_3
    //   44: iinc #3, 1
    //   47: swap
    //   48: aastore
    //   49: iload_0
    //   50: iload_1
    //   51: iadd
    //   52: dup
    //   53: istore_0
    //   54: iload #4
    //   56: if_icmpge -> 68
    //   59: aload_2
    //   60: iload_0
    //   61: invokevirtual charAt : (I)C
    //   64: istore_1
    //   65: goto -> 23
    //   68: ldc '0\\tz'
    //   70: dup
    //   71: astore_2
    //   72: invokevirtual length : ()I
    //   75: istore #4
    //   77: bipush #9
    //   79: istore_1
    //   80: iconst_m1
    //   81: istore_0
    //   82: bipush #113
    //   84: iinc #0, 1
    //   87: aload_2
    //   88: iload_0
    //   89: dup
    //   90: iload_1
    //   91: iadd
    //   92: invokevirtual substring : (II)Ljava/lang/String;
    //   95: iconst_0
    //   96: goto -> 143
    //   99: aload #5
    //   101: swap
    //   102: iload_3
    //   103: iinc #3, 1
    //   106: swap
    //   107: aastore
    //   108: iload_0
    //   109: iload_1
    //   110: iadd
    //   111: dup
    //   112: istore_0
    //   113: iload #4
    //   115: if_icmpge -> 127
    //   118: aload_2
    //   119: iload_0
    //   120: invokevirtual charAt : (I)C
    //   123: istore_1
    //   124: goto -> 82
    //   127: aload #5
    //   129: putstatic burp/Zkor.a : [Ljava/lang/String;
    //   132: bipush #24
    //   134: anewarray java/lang/String
    //   137: putstatic burp/Zkor.b : [Ljava/lang/String;
    //   140: goto -> 300
    //   143: dup_x2
    //   144: pop
    //   145: invokevirtual toCharArray : ()[C
    //   148: dup_x1
    //   149: arraylength
    //   150: dup_x2
    //   151: pop
    //   152: iconst_0
    //   153: istore #6
    //   155: dup2_x1
    //   156: pop2
    //   157: dup_x2
    //   158: iconst_1
    //   159: if_icmpgt -> 260
    //   162: dup2
    //   163: swap
    //   164: iload #6
    //   166: dup2_x1
    //   167: caload
    //   168: swap
    //   169: iload #6
    //   171: bipush #7
    //   173: irem
    //   174: tableswitch default -> 242, 0 -> 212, 1 -> 217, 2 -> 222, 3 -> 227, 4 -> 232, 5 -> 237
    //   212: bipush #107
    //   214: goto -> 244
    //   217: bipush #32
    //   219: goto -> 244
    //   222: bipush #124
    //   224: goto -> 244
    //   227: bipush #54
    //   229: goto -> 244
    //   232: bipush #26
    //   234: goto -> 244
    //   237: bipush #23
    //   239: goto -> 244
    //   242: bipush #59
    //   244: ixor
    //   245: ixor
    //   246: i2c
    //   247: castore
    //   248: iinc #6, 1
    //   251: dup
    //   252: ifne -> 260
    //   255: dup2
    //   256: dup_x1
    //   257: goto -> 166
    //   260: dup2_x1
    //   261: pop2
    //   262: dup_x2
    //   263: iload #6
    //   265: if_icmpgt -> 162
    //   268: pop
    //   269: new java/lang/String
    //   272: dup_x1
    //   273: swap
    //   274: invokespecial <init> : ([C)V
    //   277: invokevirtual intern : ()Ljava/lang/String;
    //   280: swap
    //   281: pop
    //   282: swap
    //   283: tableswitch default -> 40, 0 -> 99
    //   300: new java/math/BigInteger
    //   303: dup
    //   304: sipush #21204
    //   307: sipush #15028
    //   310: invokestatic a : (II)Ljava/lang/String;
    //   313: invokespecial <init> : (Ljava/lang/String;)V
    //   316: putstatic burp/Zkor.Ze : Ljava/lang/Object;
    //   319: sipush #21203
    //   322: sipush #28197
    //   325: invokestatic a : (II)Ljava/lang/String;
    //   328: putstatic burp/Zkor.Za : Ljava/lang/String;
    //   331: return
  }
  
  private static Throwable a(Throwable paramThrowable) {
    return paramThrowable;
  }
  
  private static String a(int paramInt1, int paramInt2) {
    int i = (paramInt1 ^ 0x52D4) & 0xFFFF;
    if (b[i] == null) {
      char[] arrayOfChar = a[i].toCharArray();
      switch (arrayOfChar[0] & 0xFF) {
        case 0:
        
        case 1:
        
        case 2:
        
        case 3:
        
        case 4:
        
        case 5:
        
        case 6:
        
        case 7:
        
        case 8:
        
        case 9:
        
        case 10:
        
        case 11:
        
        case 12:
        
        case 13:
        
        case 14:
        
        case 15:
        
        case 16:
        
        case 17:
        
        case 18:
        
        case 19:
        
        case 20:
        
        case 21:
        
        case 22:
        
        case 23:
        
        case 24:
        
        case 25:
        
        case 26:
        
        case 27:
        
        case 28:
        
        case 29:
        
        case 30:
        
        case 31:
        
        case 32:
        
        case 33:
        
        case 34:
        
        case 35:
        
        case 36:
        
        case 37:
        
        case 38:
        
        case 39:
        
        case 40:
        
        case 41:
        
        case 42:
        
        case 43:
        
        case 44:
        
        case 45:
        
        case 46:
        
        case 47:
        
        case 48:
        
        case 49:
        
        case 50:
        
        case 51:
        
        case 52:
        
        case 53:
        
        case 54:
        
        case 55:
        
        case 56:
        
        case 57:
        
        case 58:
        
        case 59:
        
        case 60:
        
        case 61:
        
        case 62:
        
        case 63:
        
        case 64:
        
        case 65:
        
        case 66:
        
        case 67:
        
        case 68:
        
        case 69:
        
        case 70:
        
        case 71:
        
        case 72:
        
        case 73:
        
        case 74:
        
        case 75:
        
        case 76:
        
        case 77:
        
        case 78:
        
        case 79:
        
        case 80:
        
        case 81:
        
        case 82:
        
        case 83:
        
        case 84:
        
        case 85:
        
        case 86:
        
        case 87:
        
        case 88:
        
        case 89:
        
        case 90:
        
        case 91:
        
        case 92:
        
        case 93:
        
        case 94:
        
        case 95:
        
        case 96:
        
        case 97:
        
        case 98:
        
        case 99:
        
        case 100:
        
        case 101:
        
        case 102:
        
        case 103:
        
        case 104:
        
        case 105:
        
        case 106:
        
        case 107:
        
        case 108:
        
        case 109:
        
        case 110:
        
        case 111:
        
        case 112:
        
        case 113:
        
        case 114:
        
        case 115:
        
        case 116:
        
        case 117:
        
        case 118:
        
        case 119:
        
        case 120:
        
        case 121:
        
        case 122:
        
        case 123:
        
        case 124:
        
        case 125:
        
        case 126:
        
        case 127:
        
        case 128:
        
        case 129:
        
        case 130:
        
        case 131:
        
        case 132:
        
        case 133:
        
        case 134:
        
        case 135:
        
        case 136:
        
        case 137:
        
        case 138:
        
        case 139:
        
        case 140:
        
        case 141:
        
        case 142:
        
        case 143:
        
        case 144:
        
        case 145:
        
        case 146:
        
        case 147:
        
        case 148:
        
        case 149:
        
        case 150:
        
        case 151:
        
        case 152:
        
        case 153:
        
        case 154:
        
        case 155:
        
        case 156:
        
        case 157:
        
        case 158:
        
        case 159:
        
        case 160:
        
        case 161:
        
        case 162:
        
        case 163:
        
        case 164:
        
        case 165:
        
        case 166:
        
        case 167:
        
        case 168:
        
        case 169:
        
        case 170:
        
        case 171:
        
        case 172:
        
        case 173:
        
        case 174:
        
        case 175:
        
        case 176:
        
        case 177:
        
        case 178:
        
        case 179:
        
        case 180:
        
        case 181:
        
        case 182:
        
        case 183:
        
        case 184:
        
        case 185:
        
        case 186:
        
        case 187:
        
        case 188:
        
        case 189:
        
        case 190:
        
        case 191:
        
        case 192:
        
        case 193:
        
        case 194:
        
        case 195:
        
        case 196:
        
        case 197:
        
        case 198:
        
        case 199:
        
        case 200:
        
        case 201:
        
        case 202:
        
        case 203:
        
        case 204:
        
        case 205:
        
        case 206:
        
        case 207:
        
        case 208:
        
        case 209:
        
        case 210:
        
        case 211:
        
        case 212:
        
        case 213:
        
        case 214:
        
        case 215:
        
        case 216:
        
        case 217:
        
        case 218:
        
        case 219:
        
        case 220:
        
        case 221:
        
        case 222:
        
        case 223:
        
        case 224:
        
        case 225:
        
        case 226:
        
        case 227:
        
        case 228:
        
        case 229:
        
        case 230:
        
        case 231:
        
        case 232:
        
        case 233:
        
        case 234:
        
        case 235:
        
        case 236:
        
        case 237:
        
        case 238:
        
        case 239:
        
        case 240:
        
        case 241:
        
        case 242:
        
        case 243:
        
        case 244:
        
        case 245:
        
        case 246:
        
        case 247:
        
        case 248:
        
        case 249:
        
        case 250:
        
        case 251:
        
        case 252:
        
        case 253:
        
        case 254:
        
        default:
          break;
      } 
      char c = '';
      int j = (paramInt2 & 0xFF) - c;
      if (j < 0)
        j += 256; 
      int k = ((paramInt2 & 0xFFFF) >>> 8) - c;
      if (k < 0)
        k += 256; 
      for (byte b = 0; b < arrayOfChar.length; b++) {
        int m = b % 2;
        if (m == 0) {
          arrayOfChar[b] = (char)(arrayOfChar[b] ^ j);
          j = ((j >>> 3 | j << 5) ^ arrayOfChar[b]) & 0xFF;
        } else {
          arrayOfChar[b] = (char)(arrayOfChar[b] ^ k);
          k = ((k >>> 3 | k << 5) ^ arrayOfChar[b]) & 0xFF;
        } 
      } 
      b[i] = (new String(arrayOfChar)).intern();
    } 
    return b[i];
  }
}


/* Location:              C:\Program Files\BurpSuitePro\burpsuite_pro.jar!\burp\Zkor.class
 * Java compiler version: 21 (65.0)
 * JD-Core Version:       1.1.3
 */