package burp;

import java.math.BigInteger;

class Zkqx extends ClassLoader {
  static String Ze;
  
  static Object ZW;
  
  private static final String[] a;
  
  private static final String[] b;
  
  static boolean Zn(Object[] paramArrayOfObject, Object paramObject) throws Throwable {
    // Byte code:
    //   0: invokestatic ZK : ()Z
    //   3: istore_2
    //   4: new java/lang/StringBuilder
    //   7: dup
    //   8: invokespecial <init> : ()V
    //   11: astore_3
    //   12: iconst_0
    //   13: istore #4
    //   15: iload #4
    //   17: bipush #32
    //   19: if_icmpge -> 1355
    //   22: iload #4
    //   24: tableswitch default -> 1348, 0 -> 168, 1 -> 205, 2 -> 242, 3 -> 279, 4 -> 316, 5 -> 353, 6 -> 390, 7 -> 427, 8 -> 464, 9 -> 501, 10 -> 538, 11 -> 575, 12 -> 612, 13 -> 649, 14 -> 686, 15 -> 723, 16 -> 760, 17 -> 797, 18 -> 834, 19 -> 871, 20 -> 908, 21 -> 945, 22 -> 982, 23 -> 1019, 24 -> 1056, 25 -> 1093, 26 -> 1130, 27 -> 1167, 28 -> 1204, 29 -> 1241, 30 -> 1278, 31 -> 1315
    //   168: aload_3
    //   169: getstatic burp/Zkbf.Zv : Ljava/lang/String;
    //   172: getstatic burp/Zzhu.ZW : Ljava/lang/Object;
    //   175: checkcast java/math/BigInteger
    //   178: invokevirtual intValue : ()I
    //   181: bipush #32
    //   183: irem
    //   184: invokestatic abs : (I)I
    //   187: invokevirtual charAt : (I)C
    //   190: invokevirtual append : (C)Ljava/lang/StringBuilder;
    //   193: pop
    //   194: iload_2
    //   195: ifeq -> 1348
    //   198: goto -> 205
    //   201: invokestatic a : (Ljava/lang/Throwable;)Ljava/lang/Throwable;
    //   204: athrow
    //   205: aload_3
    //   206: getstatic burp/Ztw4.Zb : Ljava/lang/String;
    //   209: getstatic burp/Zmou.ZT : Ljava/lang/Object;
    //   212: checkcast java/math/BigInteger
    //   215: invokevirtual intValue : ()I
    //   218: bipush #32
    //   220: irem
    //   221: invokestatic abs : (I)I
    //   224: invokevirtual charAt : (I)C
    //   227: invokevirtual append : (C)Ljava/lang/StringBuilder;
    //   230: pop
    //   231: iload_2
    //   232: ifeq -> 1348
    //   235: goto -> 242
    //   238: invokestatic a : (Ljava/lang/Throwable;)Ljava/lang/Throwable;
    //   241: athrow
    //   242: aload_3
    //   243: getstatic burp/Zxfu.Zo : Ljava/lang/String;
    //   246: getstatic burp/Zkm0.ZI : Ljava/lang/Object;
    //   249: checkcast java/math/BigInteger
    //   252: invokevirtual intValue : ()I
    //   255: bipush #32
    //   257: irem
    //   258: invokestatic abs : (I)I
    //   261: invokevirtual charAt : (I)C
    //   264: invokevirtual append : (C)Ljava/lang/StringBuilder;
    //   267: pop
    //   268: iload_2
    //   269: ifeq -> 1348
    //   272: goto -> 279
    //   275: invokestatic a : (Ljava/lang/Throwable;)Ljava/lang/Throwable;
    //   278: athrow
    //   279: aload_3
    //   280: getstatic burp/Ztd6.Zu : Ljava/lang/String;
    //   283: getstatic burp/Zegk.ZR : Ljava/lang/Object;
    //   286: checkcast java/math/BigInteger
    //   289: invokevirtual intValue : ()I
    //   292: bipush #32
    //   294: irem
    //   295: invokestatic abs : (I)I
    //   298: invokevirtual charAt : (I)C
    //   301: invokevirtual append : (C)Ljava/lang/StringBuilder;
    //   304: pop
    //   305: iload_2
    //   306: ifeq -> 1348
    //   309: goto -> 316
    //   312: invokestatic a : (Ljava/lang/Throwable;)Ljava/lang/Throwable;
    //   315: athrow
    //   316: aload_3
    //   317: getstatic burp/Zt5t.ZK : Ljava/lang/String;
    //   320: getstatic burp/Zkig.ZK : Ljava/lang/Object;
    //   323: checkcast java/math/BigInteger
    //   326: invokevirtual intValue : ()I
    //   329: bipush #32
    //   331: irem
    //   332: invokestatic abs : (I)I
    //   335: invokevirtual charAt : (I)C
    //   338: invokevirtual append : (C)Ljava/lang/StringBuilder;
    //   341: pop
    //   342: iload_2
    //   343: ifeq -> 1348
    //   346: goto -> 353
    //   349: invokestatic a : (Ljava/lang/Throwable;)Ljava/lang/Throwable;
    //   352: athrow
    //   353: aload_3
    //   354: getstatic burp/Zk52.ZL : Ljava/lang/String;
    //   357: getstatic burp/Zg7j.Zr : Ljava/lang/Object;
    //   360: checkcast java/math/BigInteger
    //   363: invokevirtual intValue : ()I
    //   366: bipush #32
    //   368: irem
    //   369: invokestatic abs : (I)I
    //   372: invokevirtual charAt : (I)C
    //   375: invokevirtual append : (C)Ljava/lang/StringBuilder;
    //   378: pop
    //   379: iload_2
    //   380: ifeq -> 1348
    //   383: goto -> 390
    //   386: invokestatic a : (Ljava/lang/Throwable;)Ljava/lang/Throwable;
    //   389: athrow
    //   390: aload_3
    //   391: getstatic burp/Zg7z.Zf : Ljava/lang/String;
    //   394: getstatic burp/Zrh1.ZF : Ljava/lang/Object;
    //   397: checkcast java/math/BigInteger
    //   400: invokevirtual intValue : ()I
    //   403: bipush #32
    //   405: irem
    //   406: invokestatic abs : (I)I
    //   409: invokevirtual charAt : (I)C
    //   412: invokevirtual append : (C)Ljava/lang/StringBuilder;
    //   415: pop
    //   416: iload_2
    //   417: ifeq -> 1348
    //   420: goto -> 427
    //   423: invokestatic a : (Ljava/lang/Throwable;)Ljava/lang/Throwable;
    //   426: athrow
    //   427: aload_3
    //   428: getstatic burp/Zr9j.Zc : Ljava/lang/String;
    //   431: getstatic burp/Zs5k.Zg : Ljava/lang/Object;
    //   434: checkcast java/math/BigInteger
    //   437: invokevirtual intValue : ()I
    //   440: bipush #32
    //   442: irem
    //   443: invokestatic abs : (I)I
    //   446: invokevirtual charAt : (I)C
    //   449: invokevirtual append : (C)Ljava/lang/StringBuilder;
    //   452: pop
    //   453: iload_2
    //   454: ifeq -> 1348
    //   457: goto -> 464
    //   460: invokestatic a : (Ljava/lang/Throwable;)Ljava/lang/Throwable;
    //   463: athrow
    //   464: aload_3
    //   465: getstatic burp/Zlbr.Zr : Ljava/lang/String;
    //   468: getstatic burp/Zx_u.Zy : Ljava/lang/Object;
    //   471: checkcast java/math/BigInteger
    //   474: invokevirtual intValue : ()I
    //   477: bipush #32
    //   479: irem
    //   480: invokestatic abs : (I)I
    //   483: invokevirtual charAt : (I)C
    //   486: invokevirtual append : (C)Ljava/lang/StringBuilder;
    //   489: pop
    //   490: iload_2
    //   491: ifeq -> 1348
    //   494: goto -> 501
    //   497: invokestatic a : (Ljava/lang/Throwable;)Ljava/lang/Throwable;
    //   500: athrow
    //   501: aload_3
    //   502: getstatic burp/Zz8o.Zo : Ljava/lang/String;
    //   505: getstatic burp/Zva.Zu : Ljava/lang/Object;
    //   508: checkcast java/math/BigInteger
    //   511: invokevirtual intValue : ()I
    //   514: bipush #32
    //   516: irem
    //   517: invokestatic abs : (I)I
    //   520: invokevirtual charAt : (I)C
    //   523: invokevirtual append : (C)Ljava/lang/StringBuilder;
    //   526: pop
    //   527: iload_2
    //   528: ifeq -> 1348
    //   531: goto -> 538
    //   534: invokestatic a : (Ljava/lang/Throwable;)Ljava/lang/Throwable;
    //   537: athrow
    //   538: aload_3
    //   539: getstatic burp/Zxjw.Zv : Ljava/lang/String;
    //   542: getstatic burp/Zllw.ZW : Ljava/lang/Object;
    //   545: checkcast java/math/BigInteger
    //   548: invokevirtual intValue : ()I
    //   551: bipush #32
    //   553: irem
    //   554: invokestatic abs : (I)I
    //   557: invokevirtual charAt : (I)C
    //   560: invokevirtual append : (C)Ljava/lang/StringBuilder;
    //   563: pop
    //   564: iload_2
    //   565: ifeq -> 1348
    //   568: goto -> 575
    //   571: invokestatic a : (Ljava/lang/Throwable;)Ljava/lang/Throwable;
    //   574: athrow
    //   575: aload_3
    //   576: getstatic burp/Zgil.ZK : Ljava/lang/String;
    //   579: getstatic burp/Zxe.Zg : Ljava/lang/Object;
    //   582: checkcast java/math/BigInteger
    //   585: invokevirtual intValue : ()I
    //   588: bipush #32
    //   590: irem
    //   591: invokestatic abs : (I)I
    //   594: invokevirtual charAt : (I)C
    //   597: invokevirtual append : (C)Ljava/lang/StringBuilder;
    //   600: pop
    //   601: iload_2
    //   602: ifeq -> 1348
    //   605: goto -> 612
    //   608: invokestatic a : (Ljava/lang/Throwable;)Ljava/lang/Throwable;
    //   611: athrow
    //   612: aload_3
    //   613: getstatic burp/Zl4v.ZD : Ljava/lang/String;
    //   616: getstatic burp/Zb4m.Zp : Ljava/lang/Object;
    //   619: checkcast java/math/BigInteger
    //   622: invokevirtual intValue : ()I
    //   625: bipush #32
    //   627: irem
    //   628: invokestatic abs : (I)I
    //   631: invokevirtual charAt : (I)C
    //   634: invokevirtual append : (C)Ljava/lang/StringBuilder;
    //   637: pop
    //   638: iload_2
    //   639: ifeq -> 1348
    //   642: goto -> 649
    //   645: invokestatic a : (Ljava/lang/Throwable;)Ljava/lang/Throwable;
    //   648: athrow
    //   649: aload_3
    //   650: getstatic burp/Zep8.ZC : Ljava/lang/String;
    //   653: getstatic burp/Zkaw.ZB : Ljava/lang/Object;
    //   656: checkcast java/math/BigInteger
    //   659: invokevirtual intValue : ()I
    //   662: bipush #32
    //   664: irem
    //   665: invokestatic abs : (I)I
    //   668: invokevirtual charAt : (I)C
    //   671: invokevirtual append : (C)Ljava/lang/StringBuilder;
    //   674: pop
    //   675: iload_2
    //   676: ifeq -> 1348
    //   679: goto -> 686
    //   682: invokestatic a : (Ljava/lang/Throwable;)Ljava/lang/Throwable;
    //   685: athrow
    //   686: aload_3
    //   687: getstatic burp/Zltb.ZO : Ljava/lang/String;
    //   690: getstatic burp/Zlxm.Zc : Ljava/lang/Object;
    //   693: checkcast java/math/BigInteger
    //   696: invokevirtual intValue : ()I
    //   699: bipush #32
    //   701: irem
    //   702: invokestatic abs : (I)I
    //   705: invokevirtual charAt : (I)C
    //   708: invokevirtual append : (C)Ljava/lang/StringBuilder;
    //   711: pop
    //   712: iload_2
    //   713: ifeq -> 1348
    //   716: goto -> 723
    //   719: invokestatic a : (Ljava/lang/Throwable;)Ljava/lang/Throwable;
    //   722: athrow
    //   723: aload_3
    //   724: getstatic burp/Zblj.Za : Ljava/lang/String;
    //   727: getstatic burp/Zzoc.Zx : Ljava/lang/Object;
    //   730: checkcast java/math/BigInteger
    //   733: invokevirtual intValue : ()I
    //   736: bipush #32
    //   738: irem
    //   739: invokestatic abs : (I)I
    //   742: invokevirtual charAt : (I)C
    //   745: invokevirtual append : (C)Ljava/lang/StringBuilder;
    //   748: pop
    //   749: iload_2
    //   750: ifeq -> 1348
    //   753: goto -> 760
    //   756: invokestatic a : (Ljava/lang/Throwable;)Ljava/lang/Throwable;
    //   759: athrow
    //   760: aload_3
    //   761: getstatic burp/Zg_5.ZG : Ljava/lang/String;
    //   764: getstatic burp/Zera.Zy : Ljava/lang/Object;
    //   767: checkcast java/math/BigInteger
    //   770: invokevirtual intValue : ()I
    //   773: bipush #32
    //   775: irem
    //   776: invokestatic abs : (I)I
    //   779: invokevirtual charAt : (I)C
    //   782: invokevirtual append : (C)Ljava/lang/StringBuilder;
    //   785: pop
    //   786: iload_2
    //   787: ifeq -> 1348
    //   790: goto -> 797
    //   793: invokestatic a : (Ljava/lang/Throwable;)Ljava/lang/Throwable;
    //   796: athrow
    //   797: aload_3
    //   798: getstatic burp/Zlqm.ZQ : Ljava/lang/String;
    //   801: getstatic burp/Zk12.Zh : Ljava/lang/Object;
    //   804: checkcast java/math/BigInteger
    //   807: invokevirtual intValue : ()I
    //   810: bipush #32
    //   812: irem
    //   813: invokestatic abs : (I)I
    //   816: invokevirtual charAt : (I)C
    //   819: invokevirtual append : (C)Ljava/lang/StringBuilder;
    //   822: pop
    //   823: iload_2
    //   824: ifeq -> 1348
    //   827: goto -> 834
    //   830: invokestatic a : (Ljava/lang/Throwable;)Ljava/lang/Throwable;
    //   833: athrow
    //   834: aload_3
    //   835: getstatic burp/Zlpu.ZA : Ljava/lang/String;
    //   838: getstatic burp/Zxti.ZJ : Ljava/lang/Object;
    //   841: checkcast java/math/BigInteger
    //   844: invokevirtual intValue : ()I
    //   847: bipush #32
    //   849: irem
    //   850: invokestatic abs : (I)I
    //   853: invokevirtual charAt : (I)C
    //   856: invokevirtual append : (C)Ljava/lang/StringBuilder;
    //   859: pop
    //   860: iload_2
    //   861: ifeq -> 1348
    //   864: goto -> 871
    //   867: invokestatic a : (Ljava/lang/Throwable;)Ljava/lang/Throwable;
    //   870: athrow
    //   871: aload_3
    //   872: getstatic burp/Zmzh.Zm : Ljava/lang/String;
    //   875: getstatic burp/Zbnb.ZZ : Ljava/lang/Object;
    //   878: checkcast java/math/BigInteger
    //   881: invokevirtual intValue : ()I
    //   884: bipush #32
    //   886: irem
    //   887: invokestatic abs : (I)I
    //   890: invokevirtual charAt : (I)C
    //   893: invokevirtual append : (C)Ljava/lang/StringBuilder;
    //   896: pop
    //   897: iload_2
    //   898: ifeq -> 1348
    //   901: goto -> 908
    //   904: invokestatic a : (Ljava/lang/Throwable;)Ljava/lang/Throwable;
    //   907: athrow
    //   908: aload_3
    //   909: getstatic burp/Zsfj.Zg : Ljava/lang/String;
    //   912: getstatic burp/Zz80.ZR : Ljava/lang/Object;
    //   915: checkcast java/math/BigInteger
    //   918: invokevirtual intValue : ()I
    //   921: bipush #32
    //   923: irem
    //   924: invokestatic abs : (I)I
    //   927: invokevirtual charAt : (I)C
    //   930: invokevirtual append : (C)Ljava/lang/StringBuilder;
    //   933: pop
    //   934: iload_2
    //   935: ifeq -> 1348
    //   938: goto -> 945
    //   941: invokestatic a : (Ljava/lang/Throwable;)Ljava/lang/Throwable;
    //   944: athrow
    //   945: aload_3
    //   946: getstatic burp/Zrd3.Z_ : Ljava/lang/String;
    //   949: getstatic burp/Zex.ZO : Ljava/lang/Object;
    //   952: checkcast java/math/BigInteger
    //   955: invokevirtual intValue : ()I
    //   958: bipush #32
    //   960: irem
    //   961: invokestatic abs : (I)I
    //   964: invokevirtual charAt : (I)C
    //   967: invokevirtual append : (C)Ljava/lang/StringBuilder;
    //   970: pop
    //   971: iload_2
    //   972: ifeq -> 1348
    //   975: goto -> 982
    //   978: invokestatic a : (Ljava/lang/Throwable;)Ljava/lang/Throwable;
    //   981: athrow
    //   982: aload_3
    //   983: getstatic burp/Zgly.Zb : Ljava/lang/String;
    //   986: getstatic burp/Zsq5.ZF : Ljava/lang/Object;
    //   989: checkcast java/math/BigInteger
    //   992: invokevirtual intValue : ()I
    //   995: bipush #32
    //   997: irem
    //   998: invokestatic abs : (I)I
    //   1001: invokevirtual charAt : (I)C
    //   1004: invokevirtual append : (C)Ljava/lang/StringBuilder;
    //   1007: pop
    //   1008: iload_2
    //   1009: ifeq -> 1348
    //   1012: goto -> 1019
    //   1015: invokestatic a : (Ljava/lang/Throwable;)Ljava/lang/Throwable;
    //   1018: athrow
    //   1019: aload_3
    //   1020: getstatic burp/Zmjr.Zc : Ljava/lang/String;
    //   1023: getstatic burp/Zsx6.ZN : Ljava/lang/Object;
    //   1026: checkcast java/math/BigInteger
    //   1029: invokevirtual intValue : ()I
    //   1032: bipush #32
    //   1034: irem
    //   1035: invokestatic abs : (I)I
    //   1038: invokevirtual charAt : (I)C
    //   1041: invokevirtual append : (C)Ljava/lang/StringBuilder;
    //   1044: pop
    //   1045: iload_2
    //   1046: ifeq -> 1348
    //   1049: goto -> 1056
    //   1052: invokestatic a : (Ljava/lang/Throwable;)Ljava/lang/Throwable;
    //   1055: athrow
    //   1056: aload_3
    //   1057: getstatic burp/Zmu6.Zl : Ljava/lang/String;
    //   1060: getstatic burp/Zgj5.ZO : Ljava/lang/Object;
    //   1063: checkcast java/math/BigInteger
    //   1066: invokevirtual intValue : ()I
    //   1069: bipush #32
    //   1071: irem
    //   1072: invokestatic abs : (I)I
    //   1075: invokevirtual charAt : (I)C
    //   1078: invokevirtual append : (C)Ljava/lang/StringBuilder;
    //   1081: pop
    //   1082: iload_2
    //   1083: ifeq -> 1348
    //   1086: goto -> 1093
    //   1089: invokestatic a : (Ljava/lang/Throwable;)Ljava/lang/Throwable;
    //   1092: athrow
    //   1093: aload_3
    //   1094: getstatic burp/Ztys.Zn : Ljava/lang/String;
    //   1097: getstatic burp/Zg6f.Zl : Ljava/lang/Object;
    //   1100: checkcast java/math/BigInteger
    //   1103: invokevirtual intValue : ()I
    //   1106: bipush #32
    //   1108: irem
    //   1109: invokestatic abs : (I)I
    //   1112: invokevirtual charAt : (I)C
    //   1115: invokevirtual append : (C)Ljava/lang/StringBuilder;
    //   1118: pop
    //   1119: iload_2
    //   1120: ifeq -> 1348
    //   1123: goto -> 1130
    //   1126: invokestatic a : (Ljava/lang/Throwable;)Ljava/lang/Throwable;
    //   1129: athrow
    //   1130: aload_3
    //   1131: getstatic burp/Zsn4.ZZ : Ljava/lang/String;
    //   1134: getstatic burp/Zrpm.ZR : Ljava/lang/Object;
    //   1137: checkcast java/math/BigInteger
    //   1140: invokevirtual intValue : ()I
    //   1143: bipush #32
    //   1145: irem
    //   1146: invokestatic abs : (I)I
    //   1149: invokevirtual charAt : (I)C
    //   1152: invokevirtual append : (C)Ljava/lang/StringBuilder;
    //   1155: pop
    //   1156: iload_2
    //   1157: ifeq -> 1348
    //   1160: goto -> 1167
    //   1163: invokestatic a : (Ljava/lang/Throwable;)Ljava/lang/Throwable;
    //   1166: athrow
    //   1167: aload_3
    //   1168: getstatic burp/Zl8l.ZG : Ljava/lang/String;
    //   1171: getstatic burp/Zbqk.ZT : Ljava/lang/Object;
    //   1174: checkcast java/math/BigInteger
    //   1177: invokevirtual intValue : ()I
    //   1180: bipush #32
    //   1182: irem
    //   1183: invokestatic abs : (I)I
    //   1186: invokevirtual charAt : (I)C
    //   1189: invokevirtual append : (C)Ljava/lang/StringBuilder;
    //   1192: pop
    //   1193: iload_2
    //   1194: ifeq -> 1348
    //   1197: goto -> 1204
    //   1200: invokestatic a : (Ljava/lang/Throwable;)Ljava/lang/Throwable;
    //   1203: athrow
    //   1204: aload_3
    //   1205: getstatic burp/Zr8s.ZA : Ljava/lang/String;
    //   1208: getstatic burp/Zeqo.ZZ : Ljava/lang/Object;
    //   1211: checkcast java/math/BigInteger
    //   1214: invokevirtual intValue : ()I
    //   1217: bipush #32
    //   1219: irem
    //   1220: invokestatic abs : (I)I
    //   1223: invokevirtual charAt : (I)C
    //   1226: invokevirtual append : (C)Ljava/lang/StringBuilder;
    //   1229: pop
    //   1230: iload_2
    //   1231: ifeq -> 1348
    //   1234: goto -> 1241
    //   1237: invokestatic a : (Ljava/lang/Throwable;)Ljava/lang/Throwable;
    //   1240: athrow
    //   1241: aload_3
    //   1242: getstatic burp/Zrpu.Zy : Ljava/lang/String;
    //   1245: getstatic burp/Zsin.Za : Ljava/lang/Object;
    //   1248: checkcast java/math/BigInteger
    //   1251: invokevirtual intValue : ()I
    //   1254: bipush #32
    //   1256: irem
    //   1257: invokestatic abs : (I)I
    //   1260: invokevirtual charAt : (I)C
    //   1263: invokevirtual append : (C)Ljava/lang/StringBuilder;
    //   1266: pop
    //   1267: iload_2
    //   1268: ifeq -> 1348
    //   1271: goto -> 1278
    //   1274: invokestatic a : (Ljava/lang/Throwable;)Ljava/lang/Throwable;
    //   1277: athrow
    //   1278: aload_3
    //   1279: getstatic burp/Zl8i.Zb : Ljava/lang/String;
    //   1282: getstatic burp/Zxso.ZF : Ljava/lang/Object;
    //   1285: checkcast java/math/BigInteger
    //   1288: invokevirtual intValue : ()I
    //   1291: bipush #32
    //   1293: irem
    //   1294: invokestatic abs : (I)I
    //   1297: invokevirtual charAt : (I)C
    //   1300: invokevirtual append : (C)Ljava/lang/StringBuilder;
    //   1303: pop
    //   1304: iload_2
    //   1305: ifeq -> 1348
    //   1308: goto -> 1315
    //   1311: invokestatic a : (Ljava/lang/Throwable;)Ljava/lang/Throwable;
    //   1314: athrow
    //   1315: aload_3
    //   1316: getstatic burp/Zmd.Zf : Ljava/lang/String;
    //   1319: getstatic burp/Zrd0.Zs : Ljava/lang/Object;
    //   1322: checkcast java/math/BigInteger
    //   1325: invokevirtual intValue : ()I
    //   1328: bipush #32
    //   1330: irem
    //   1331: invokestatic abs : (I)I
    //   1334: invokevirtual charAt : (I)C
    //   1337: invokevirtual append : (C)Ljava/lang/StringBuilder;
    //   1340: pop
    //   1341: goto -> 1348
    //   1344: invokestatic a : (Ljava/lang/Throwable;)Ljava/lang/Throwable;
    //   1347: athrow
    //   1348: iinc #4, 1
    //   1351: iload_2
    //   1352: ifeq -> 15
    //   1355: aload_3
    //   1356: invokevirtual toString : ()Ljava/lang/String;
    //   1359: putstatic burp/Ztgv.ZC : Ljava/lang/String;
    //   1362: getstatic burp/Zgia.Zx : Ljava/lang/Object;
    //   1365: checkcast java/math/BigInteger
    //   1368: invokevirtual toByteArray : ()[B
    //   1371: astore #4
    //   1373: bipush #64
    //   1375: newarray byte
    //   1377: dup
    //   1378: iconst_0
    //   1379: bipush #-128
    //   1381: bastore
    //   1382: dup
    //   1383: iconst_1
    //   1384: iconst_0
    //   1385: bastore
    //   1386: dup
    //   1387: iconst_2
    //   1388: iconst_0
    //   1389: bastore
    //   1390: dup
    //   1391: iconst_3
    //   1392: iconst_0
    //   1393: bastore
    //   1394: dup
    //   1395: iconst_4
    //   1396: iconst_0
    //   1397: bastore
    //   1398: dup
    //   1399: iconst_5
    //   1400: iconst_0
    //   1401: bastore
    //   1402: dup
    //   1403: bipush #6
    //   1405: iconst_0
    //   1406: bastore
    //   1407: dup
    //   1408: bipush #7
    //   1410: iconst_0
    //   1411: bastore
    //   1412: dup
    //   1413: bipush #8
    //   1415: iconst_0
    //   1416: bastore
    //   1417: dup
    //   1418: bipush #9
    //   1420: iconst_0
    //   1421: bastore
    //   1422: dup
    //   1423: bipush #10
    //   1425: iconst_0
    //   1426: bastore
    //   1427: dup
    //   1428: bipush #11
    //   1430: iconst_0
    //   1431: bastore
    //   1432: dup
    //   1433: bipush #12
    //   1435: iconst_0
    //   1436: bastore
    //   1437: dup
    //   1438: bipush #13
    //   1440: iconst_0
    //   1441: bastore
    //   1442: dup
    //   1443: bipush #14
    //   1445: iconst_0
    //   1446: bastore
    //   1447: dup
    //   1448: bipush #15
    //   1450: iconst_0
    //   1451: bastore
    //   1452: dup
    //   1453: bipush #16
    //   1455: iconst_0
    //   1456: bastore
    //   1457: dup
    //   1458: bipush #17
    //   1460: iconst_0
    //   1461: bastore
    //   1462: dup
    //   1463: bipush #18
    //   1465: iconst_0
    //   1466: bastore
    //   1467: dup
    //   1468: bipush #19
    //   1470: iconst_0
    //   1471: bastore
    //   1472: dup
    //   1473: bipush #20
    //   1475: iconst_0
    //   1476: bastore
    //   1477: dup
    //   1478: bipush #21
    //   1480: iconst_0
    //   1481: bastore
    //   1482: dup
    //   1483: bipush #22
    //   1485: iconst_0
    //   1486: bastore
    //   1487: dup
    //   1488: bipush #23
    //   1490: iconst_0
    //   1491: bastore
    //   1492: dup
    //   1493: bipush #24
    //   1495: iconst_0
    //   1496: bastore
    //   1497: dup
    //   1498: bipush #25
    //   1500: iconst_0
    //   1501: bastore
    //   1502: dup
    //   1503: bipush #26
    //   1505: iconst_0
    //   1506: bastore
    //   1507: dup
    //   1508: bipush #27
    //   1510: iconst_0
    //   1511: bastore
    //   1512: dup
    //   1513: bipush #28
    //   1515: iconst_0
    //   1516: bastore
    //   1517: dup
    //   1518: bipush #29
    //   1520: iconst_0
    //   1521: bastore
    //   1522: dup
    //   1523: bipush #30
    //   1525: iconst_0
    //   1526: bastore
    //   1527: dup
    //   1528: bipush #31
    //   1530: iconst_0
    //   1531: bastore
    //   1532: dup
    //   1533: bipush #32
    //   1535: iconst_0
    //   1536: bastore
    //   1537: dup
    //   1538: bipush #33
    //   1540: iconst_0
    //   1541: bastore
    //   1542: dup
    //   1543: bipush #34
    //   1545: iconst_0
    //   1546: bastore
    //   1547: dup
    //   1548: bipush #35
    //   1550: iconst_0
    //   1551: bastore
    //   1552: dup
    //   1553: bipush #36
    //   1555: iconst_0
    //   1556: bastore
    //   1557: dup
    //   1558: bipush #37
    //   1560: iconst_0
    //   1561: bastore
    //   1562: dup
    //   1563: bipush #38
    //   1565: iconst_0
    //   1566: bastore
    //   1567: dup
    //   1568: bipush #39
    //   1570: iconst_0
    //   1571: bastore
    //   1572: dup
    //   1573: bipush #40
    //   1575: iconst_0
    //   1576: bastore
    //   1577: dup
    //   1578: bipush #41
    //   1580: iconst_0
    //   1581: bastore
    //   1582: dup
    //   1583: bipush #42
    //   1585: iconst_0
    //   1586: bastore
    //   1587: dup
    //   1588: bipush #43
    //   1590: iconst_0
    //   1591: bastore
    //   1592: dup
    //   1593: bipush #44
    //   1595: iconst_0
    //   1596: bastore
    //   1597: dup
    //   1598: bipush #45
    //   1600: iconst_0
    //   1601: bastore
    //   1602: dup
    //   1603: bipush #46
    //   1605: iconst_0
    //   1606: bastore
    //   1607: dup
    //   1608: bipush #47
    //   1610: iconst_0
    //   1611: bastore
    //   1612: dup
    //   1613: bipush #48
    //   1615: iconst_0
    //   1616: bastore
    //   1617: dup
    //   1618: bipush #49
    //   1620: iconst_0
    //   1621: bastore
    //   1622: dup
    //   1623: bipush #50
    //   1625: iconst_0
    //   1626: bastore
    //   1627: dup
    //   1628: bipush #51
    //   1630: iconst_0
    //   1631: bastore
    //   1632: dup
    //   1633: bipush #52
    //   1635: iconst_0
    //   1636: bastore
    //   1637: dup
    //   1638: bipush #53
    //   1640: iconst_0
    //   1641: bastore
    //   1642: dup
    //   1643: bipush #54
    //   1645: iconst_0
    //   1646: bastore
    //   1647: dup
    //   1648: bipush #55
    //   1650: iconst_0
    //   1651: bastore
    //   1652: dup
    //   1653: bipush #56
    //   1655: iconst_0
    //   1656: bastore
    //   1657: dup
    //   1658: bipush #57
    //   1660: iconst_0
    //   1661: bastore
    //   1662: dup
    //   1663: bipush #58
    //   1665: iconst_0
    //   1666: bastore
    //   1667: dup
    //   1668: bipush #59
    //   1670: iconst_0
    //   1671: bastore
    //   1672: dup
    //   1673: bipush #60
    //   1675: iconst_0
    //   1676: bastore
    //   1677: dup
    //   1678: bipush #61
    //   1680: iconst_0
    //   1681: bastore
    //   1682: dup
    //   1683: bipush #62
    //   1685: iconst_0
    //   1686: bastore
    //   1687: dup
    //   1688: bipush #63
    //   1690: iconst_0
    //   1691: bastore
    //   1692: astore #6
    //   1694: bipush #64
    //   1696: newarray int
    //   1698: dup
    //   1699: iconst_0
    //   1700: ldc 1116352408
    //   1702: iastore
    //   1703: dup
    //   1704: iconst_1
    //   1705: ldc 1899447441
    //   1707: iastore
    //   1708: dup
    //   1709: iconst_2
    //   1710: ldc -1245643825
    //   1712: iastore
    //   1713: dup
    //   1714: iconst_3
    //   1715: ldc -373957723
    //   1717: iastore
    //   1718: dup
    //   1719: iconst_4
    //   1720: ldc 961987163
    //   1722: iastore
    //   1723: dup
    //   1724: iconst_5
    //   1725: ldc 1508970993
    //   1727: iastore
    //   1728: dup
    //   1729: bipush #6
    //   1731: ldc -1841331548
    //   1733: iastore
    //   1734: dup
    //   1735: bipush #7
    //   1737: ldc -1424204075
    //   1739: iastore
    //   1740: dup
    //   1741: bipush #8
    //   1743: ldc -670586216
    //   1745: iastore
    //   1746: dup
    //   1747: bipush #9
    //   1749: ldc 310598401
    //   1751: iastore
    //   1752: dup
    //   1753: bipush #10
    //   1755: ldc 607225278
    //   1757: iastore
    //   1758: dup
    //   1759: bipush #11
    //   1761: ldc 1426881987
    //   1763: iastore
    //   1764: dup
    //   1765: bipush #12
    //   1767: ldc 1925078388
    //   1769: iastore
    //   1770: dup
    //   1771: bipush #13
    //   1773: ldc -2132889090
    //   1775: iastore
    //   1776: dup
    //   1777: bipush #14
    //   1779: ldc -1680079193
    //   1781: iastore
    //   1782: dup
    //   1783: bipush #15
    //   1785: ldc -1046744716
    //   1787: iastore
    //   1788: dup
    //   1789: bipush #16
    //   1791: ldc -459576895
    //   1793: iastore
    //   1794: dup
    //   1795: bipush #17
    //   1797: ldc -272742522
    //   1799: iastore
    //   1800: dup
    //   1801: bipush #18
    //   1803: ldc 264347078
    //   1805: iastore
    //   1806: dup
    //   1807: bipush #19
    //   1809: ldc 604807628
    //   1811: iastore
    //   1812: dup
    //   1813: bipush #20
    //   1815: ldc 770255983
    //   1817: iastore
    //   1818: dup
    //   1819: bipush #21
    //   1821: ldc 1249150122
    //   1823: iastore
    //   1824: dup
    //   1825: bipush #22
    //   1827: ldc 1555081692
    //   1829: iastore
    //   1830: dup
    //   1831: bipush #23
    //   1833: ldc 1996064986
    //   1835: iastore
    //   1836: dup
    //   1837: bipush #24
    //   1839: ldc -1740746414
    //   1841: iastore
    //   1842: dup
    //   1843: bipush #25
    //   1845: ldc -1473132947
    //   1847: iastore
    //   1848: dup
    //   1849: bipush #26
    //   1851: ldc -1341970488
    //   1853: iastore
    //   1854: dup
    //   1855: bipush #27
    //   1857: ldc -1084653625
    //   1859: iastore
    //   1860: dup
    //   1861: bipush #28
    //   1863: ldc -958395405
    //   1865: iastore
    //   1866: dup
    //   1867: bipush #29
    //   1869: ldc -710438585
    //   1871: iastore
    //   1872: dup
    //   1873: bipush #30
    //   1875: ldc 113926993
    //   1877: iastore
    //   1878: dup
    //   1879: bipush #31
    //   1881: ldc 338241895
    //   1883: iastore
    //   1884: dup
    //   1885: bipush #32
    //   1887: ldc 666307205
    //   1889: iastore
    //   1890: dup
    //   1891: bipush #33
    //   1893: ldc 773529912
    //   1895: iastore
    //   1896: dup
    //   1897: bipush #34
    //   1899: ldc 1294757372
    //   1901: iastore
    //   1902: dup
    //   1903: bipush #35
    //   1905: ldc 1396182291
    //   1907: iastore
    //   1908: dup
    //   1909: bipush #36
    //   1911: ldc 1695183700
    //   1913: iastore
    //   1914: dup
    //   1915: bipush #37
    //   1917: ldc 1986661051
    //   1919: iastore
    //   1920: dup
    //   1921: bipush #38
    //   1923: ldc -2117940946
    //   1925: iastore
    //   1926: dup
    //   1927: bipush #39
    //   1929: ldc -1838011259
    //   1931: iastore
    //   1932: dup
    //   1933: bipush #40
    //   1935: ldc -1564481375
    //   1937: iastore
    //   1938: dup
    //   1939: bipush #41
    //   1941: ldc -1474664885
    //   1943: iastore
    //   1944: dup
    //   1945: bipush #42
    //   1947: ldc -1035236496
    //   1949: iastore
    //   1950: dup
    //   1951: bipush #43
    //   1953: ldc -949202525
    //   1955: iastore
    //   1956: dup
    //   1957: bipush #44
    //   1959: ldc -778901479
    //   1961: iastore
    //   1962: dup
    //   1963: bipush #45
    //   1965: ldc -694614492
    //   1967: iastore
    //   1968: dup
    //   1969: bipush #46
    //   1971: ldc -200395387
    //   1973: iastore
    //   1974: dup
    //   1975: bipush #47
    //   1977: ldc 275423344
    //   1979: iastore
    //   1980: dup
    //   1981: bipush #48
    //   1983: ldc 430227734
    //   1985: iastore
    //   1986: dup
    //   1987: bipush #49
    //   1989: ldc 506948616
    //   1991: iastore
    //   1992: dup
    //   1993: bipush #50
    //   1995: ldc 659060556
    //   1997: iastore
    //   1998: dup
    //   1999: bipush #51
    //   2001: ldc 883997877
    //   2003: iastore
    //   2004: dup
    //   2005: bipush #52
    //   2007: ldc 958139571
    //   2009: iastore
    //   2010: dup
    //   2011: bipush #53
    //   2013: ldc 1322822218
    //   2015: iastore
    //   2016: dup
    //   2017: bipush #54
    //   2019: ldc 1537002063
    //   2021: iastore
    //   2022: dup
    //   2023: bipush #55
    //   2025: ldc 1747873779
    //   2027: iastore
    //   2028: dup
    //   2029: bipush #56
    //   2031: ldc 1955562222
    //   2033: iastore
    //   2034: dup
    //   2035: bipush #57
    //   2037: ldc 2024104815
    //   2039: iastore
    //   2040: dup
    //   2041: bipush #58
    //   2043: ldc -2067236844
    //   2045: iastore
    //   2046: dup
    //   2047: bipush #59
    //   2049: ldc -1933114872
    //   2051: iastore
    //   2052: dup
    //   2053: bipush #60
    //   2055: ldc -1866530822
    //   2057: iastore
    //   2058: dup
    //   2059: bipush #61
    //   2061: ldc -1538233109
    //   2063: iastore
    //   2064: dup
    //   2065: bipush #62
    //   2067: ldc -1090935817
    //   2069: iastore
    //   2070: dup
    //   2071: bipush #63
    //   2073: ldc -965641998
    //   2075: iastore
    //   2076: astore #7
    //   2078: iconst_2
    //   2079: newarray int
    //   2081: dup
    //   2082: iconst_0
    //   2083: iconst_0
    //   2084: iastore
    //   2085: dup
    //   2086: iconst_1
    //   2087: iconst_0
    //   2088: iastore
    //   2089: astore #8
    //   2091: bipush #8
    //   2093: newarray int
    //   2095: dup
    //   2096: iconst_0
    //   2097: ldc 1779033703
    //   2099: iastore
    //   2100: dup
    //   2101: iconst_1
    //   2102: ldc -1150833019
    //   2104: iastore
    //   2105: dup
    //   2106: iconst_2
    //   2107: ldc 1013904242
    //   2109: iastore
    //   2110: dup
    //   2111: iconst_3
    //   2112: ldc -1521486534
    //   2114: iastore
    //   2115: dup
    //   2116: iconst_4
    //   2117: ldc 1359893119
    //   2119: iastore
    //   2120: dup
    //   2121: iconst_5
    //   2122: ldc -1694144372
    //   2124: iastore
    //   2125: dup
    //   2126: bipush #6
    //   2128: ldc 528734635
    //   2130: iastore
    //   2131: dup
    //   2132: bipush #7
    //   2134: ldc 1541459225
    //   2136: iastore
    //   2137: astore #9
    //   2139: bipush #64
    //   2141: newarray byte
    //   2143: astore #10
    //   2145: bipush #64
    //   2147: newarray byte
    //   2149: astore #11
    //   2151: aload #4
    //   2153: arraylength
    //   2154: istore #12
    //   2156: aload #8
    //   2158: iconst_0
    //   2159: iaload
    //   2160: bipush #63
    //   2162: iand
    //   2163: istore #13
    //   2165: aload #8
    //   2167: iconst_0
    //   2168: dup2
    //   2169: iaload
    //   2170: iload #12
    //   2172: iadd
    //   2173: iastore
    //   2174: aload #8
    //   2176: iconst_0
    //   2177: dup2
    //   2178: iaload
    //   2179: iconst_m1
    //   2180: iand
    //   2181: iastore
    //   2182: aload #8
    //   2184: iconst_0
    //   2185: iaload
    //   2186: iload #12
    //   2188: if_icmpge -> 2206
    //   2191: aload #8
    //   2193: iconst_1
    //   2194: dup2
    //   2195: iaload
    //   2196: iconst_1
    //   2197: iadd
    //   2198: iastore
    //   2199: goto -> 2206
    //   2202: invokestatic a : (Ljava/lang/Throwable;)Ljava/lang/Throwable;
    //   2205: athrow
    //   2206: iconst_0
    //   2207: istore #14
    //   2209: iload #12
    //   2211: bipush #64
    //   2213: if_icmplt -> 2823
    //   2216: iconst_0
    //   2217: istore #15
    //   2219: iload #15
    //   2221: bipush #64
    //   2223: if_icmpge -> 2246
    //   2226: aload #11
    //   2228: iload #15
    //   2230: aload #4
    //   2232: iload #14
    //   2234: iload #15
    //   2236: iadd
    //   2237: baload
    //   2238: bastore
    //   2239: iinc #15, 1
    //   2242: iload_2
    //   2243: ifeq -> 2219
    //   2246: bipush #64
    //   2248: newarray int
    //   2250: astore #15
    //   2252: bipush #8
    //   2254: newarray int
    //   2256: astore #16
    //   2258: iconst_0
    //   2259: istore #17
    //   2261: iload #17
    //   2263: bipush #8
    //   2265: if_icmpge -> 2285
    //   2268: aload #16
    //   2270: iload #17
    //   2272: aload #9
    //   2274: iload #17
    //   2276: iaload
    //   2277: iastore
    //   2278: iinc #17, 1
    //   2281: iload_2
    //   2282: ifeq -> 2261
    //   2285: iconst_0
    //   2286: istore #17
    //   2288: iload #17
    //   2290: bipush #64
    //   2292: if_icmpge -> 2783
    //   2295: iload #17
    //   2297: bipush #16
    //   2299: if_icmpge -> 2380
    //   2302: aload #15
    //   2304: iload #17
    //   2306: aload #11
    //   2308: iconst_4
    //   2309: iload #17
    //   2311: imul
    //   2312: baload
    //   2313: sipush #255
    //   2316: iand
    //   2317: bipush #24
    //   2319: ishl
    //   2320: aload #11
    //   2322: iconst_4
    //   2323: iload #17
    //   2325: imul
    //   2326: iconst_1
    //   2327: iadd
    //   2328: baload
    //   2329: sipush #255
    //   2332: iand
    //   2333: bipush #16
    //   2335: ishl
    //   2336: ior
    //   2337: aload #11
    //   2339: iconst_4
    //   2340: iload #17
    //   2342: imul
    //   2343: iconst_2
    //   2344: iadd
    //   2345: baload
    //   2346: sipush #255
    //   2349: iand
    //   2350: bipush #8
    //   2352: ishl
    //   2353: ior
    //   2354: aload #11
    //   2356: iconst_4
    //   2357: iload #17
    //   2359: imul
    //   2360: iconst_3
    //   2361: iadd
    //   2362: baload
    //   2363: sipush #255
    //   2366: iand
    //   2367: ior
    //   2368: iastore
    //   2369: iload_2
    //   2370: ifeq -> 2523
    //   2373: goto -> 2380
    //   2376: invokestatic a : (Ljava/lang/Throwable;)Ljava/lang/Throwable;
    //   2379: athrow
    //   2380: aload #15
    //   2382: iload #17
    //   2384: aload #15
    //   2386: iload #17
    //   2388: iconst_2
    //   2389: isub
    //   2390: iaload
    //   2391: bipush #17
    //   2393: iushr
    //   2394: aload #15
    //   2396: iload #17
    //   2398: iconst_2
    //   2399: isub
    //   2400: iaload
    //   2401: bipush #15
    //   2403: ishl
    //   2404: ior
    //   2405: aload #15
    //   2407: iload #17
    //   2409: iconst_2
    //   2410: isub
    //   2411: iaload
    //   2412: bipush #19
    //   2414: iushr
    //   2415: aload #15
    //   2417: iload #17
    //   2419: iconst_2
    //   2420: isub
    //   2421: iaload
    //   2422: bipush #13
    //   2424: ishl
    //   2425: ior
    //   2426: ixor
    //   2427: aload #15
    //   2429: iload #17
    //   2431: iconst_2
    //   2432: isub
    //   2433: iaload
    //   2434: bipush #10
    //   2436: iushr
    //   2437: ixor
    //   2438: aload #15
    //   2440: iload #17
    //   2442: bipush #7
    //   2444: isub
    //   2445: iaload
    //   2446: iadd
    //   2447: aload #15
    //   2449: iload #17
    //   2451: bipush #15
    //   2453: isub
    //   2454: iaload
    //   2455: bipush #7
    //   2457: iushr
    //   2458: aload #15
    //   2460: iload #17
    //   2462: bipush #15
    //   2464: isub
    //   2465: iaload
    //   2466: bipush #25
    //   2468: ishl
    //   2469: ior
    //   2470: aload #15
    //   2472: iload #17
    //   2474: bipush #15
    //   2476: isub
    //   2477: iaload
    //   2478: bipush #18
    //   2480: iushr
    //   2481: aload #15
    //   2483: iload #17
    //   2485: bipush #15
    //   2487: isub
    //   2488: iaload
    //   2489: bipush #14
    //   2491: ishl
    //   2492: ior
    //   2493: ixor
    //   2494: aload #15
    //   2496: iload #17
    //   2498: bipush #15
    //   2500: isub
    //   2501: iaload
    //   2502: iconst_3
    //   2503: iushr
    //   2504: ixor
    //   2505: iadd
    //   2506: aload #15
    //   2508: iload #17
    //   2510: bipush #16
    //   2512: isub
    //   2513: iaload
    //   2514: iadd
    //   2515: iastore
    //   2516: goto -> 2523
    //   2519: invokestatic a : (Ljava/lang/Throwable;)Ljava/lang/Throwable;
    //   2522: athrow
    //   2523: aload #16
    //   2525: bipush #7
    //   2527: iaload
    //   2528: aload #16
    //   2530: iconst_4
    //   2531: iaload
    //   2532: bipush #6
    //   2534: iushr
    //   2535: aload #16
    //   2537: iconst_4
    //   2538: iaload
    //   2539: bipush #26
    //   2541: ishl
    //   2542: ior
    //   2543: aload #16
    //   2545: iconst_4
    //   2546: iaload
    //   2547: bipush #11
    //   2549: iushr
    //   2550: aload #16
    //   2552: iconst_4
    //   2553: iaload
    //   2554: bipush #21
    //   2556: ishl
    //   2557: ior
    //   2558: ixor
    //   2559: aload #16
    //   2561: iconst_4
    //   2562: iaload
    //   2563: bipush #25
    //   2565: iushr
    //   2566: aload #16
    //   2568: iconst_4
    //   2569: iaload
    //   2570: bipush #7
    //   2572: ishl
    //   2573: ior
    //   2574: ixor
    //   2575: iadd
    //   2576: aload #16
    //   2578: bipush #6
    //   2580: iaload
    //   2581: aload #16
    //   2583: iconst_4
    //   2584: iaload
    //   2585: aload #16
    //   2587: iconst_5
    //   2588: iaload
    //   2589: aload #16
    //   2591: bipush #6
    //   2593: iaload
    //   2594: ixor
    //   2595: iand
    //   2596: ixor
    //   2597: iadd
    //   2598: aload #7
    //   2600: iload #17
    //   2602: iaload
    //   2603: iadd
    //   2604: aload #15
    //   2606: iload #17
    //   2608: iaload
    //   2609: iadd
    //   2610: istore #18
    //   2612: aload #16
    //   2614: iconst_0
    //   2615: iaload
    //   2616: iconst_2
    //   2617: iushr
    //   2618: aload #16
    //   2620: iconst_0
    //   2621: iaload
    //   2622: bipush #30
    //   2624: ishl
    //   2625: ior
    //   2626: aload #16
    //   2628: iconst_0
    //   2629: iaload
    //   2630: bipush #13
    //   2632: iushr
    //   2633: aload #16
    //   2635: iconst_0
    //   2636: iaload
    //   2637: bipush #19
    //   2639: ishl
    //   2640: ior
    //   2641: ixor
    //   2642: aload #16
    //   2644: iconst_0
    //   2645: iaload
    //   2646: bipush #22
    //   2648: iushr
    //   2649: aload #16
    //   2651: iconst_0
    //   2652: iaload
    //   2653: bipush #10
    //   2655: ishl
    //   2656: ior
    //   2657: ixor
    //   2658: aload #16
    //   2660: iconst_0
    //   2661: iaload
    //   2662: aload #16
    //   2664: iconst_1
    //   2665: iaload
    //   2666: iand
    //   2667: aload #16
    //   2669: iconst_2
    //   2670: iaload
    //   2671: aload #16
    //   2673: iconst_0
    //   2674: iaload
    //   2675: aload #16
    //   2677: iconst_1
    //   2678: iaload
    //   2679: ior
    //   2680: iand
    //   2681: ior
    //   2682: iadd
    //   2683: istore #19
    //   2685: aload #16
    //   2687: iconst_3
    //   2688: dup2
    //   2689: iaload
    //   2690: iload #18
    //   2692: iadd
    //   2693: iastore
    //   2694: aload #16
    //   2696: bipush #7
    //   2698: iload #18
    //   2700: iload #19
    //   2702: iadd
    //   2703: iastore
    //   2704: aload #16
    //   2706: bipush #7
    //   2708: iaload
    //   2709: istore #18
    //   2711: aload #16
    //   2713: bipush #7
    //   2715: aload #16
    //   2717: bipush #6
    //   2719: iaload
    //   2720: iastore
    //   2721: aload #16
    //   2723: bipush #6
    //   2725: aload #16
    //   2727: iconst_5
    //   2728: iaload
    //   2729: iastore
    //   2730: aload #16
    //   2732: iconst_5
    //   2733: aload #16
    //   2735: iconst_4
    //   2736: iaload
    //   2737: iastore
    //   2738: aload #16
    //   2740: iconst_4
    //   2741: aload #16
    //   2743: iconst_3
    //   2744: iaload
    //   2745: iastore
    //   2746: aload #16
    //   2748: iconst_3
    //   2749: aload #16
    //   2751: iconst_2
    //   2752: iaload
    //   2753: iastore
    //   2754: aload #16
    //   2756: iconst_2
    //   2757: aload #16
    //   2759: iconst_1
    //   2760: iaload
    //   2761: iastore
    //   2762: aload #16
    //   2764: iconst_1
    //   2765: aload #16
    //   2767: iconst_0
    //   2768: iaload
    //   2769: iastore
    //   2770: aload #16
    //   2772: iconst_0
    //   2773: iload #18
    //   2775: iastore
    //   2776: iinc #17, 1
    //   2779: iload_2
    //   2780: ifeq -> 2288
    //   2783: iconst_0
    //   2784: istore #17
    //   2786: iload #17
    //   2788: bipush #8
    //   2790: if_icmpge -> 2813
    //   2793: aload #9
    //   2795: iload #17
    //   2797: dup2
    //   2798: iaload
    //   2799: aload #16
    //   2801: iload #17
    //   2803: iaload
    //   2804: iadd
    //   2805: iastore
    //   2806: iinc #17, 1
    //   2809: iload_2
    //   2810: ifeq -> 2786
    //   2813: iinc #14, 64
    //   2816: iinc #12, -64
    //   2819: iload_2
    //   2820: ifeq -> 2209
    //   2823: iload #12
    //   2825: ifle -> 2861
    //   2828: iconst_0
    //   2829: istore #15
    //   2831: iload #15
    //   2833: iload #12
    //   2835: if_icmpge -> 2861
    //   2838: aload #10
    //   2840: iload #13
    //   2842: iload #15
    //   2844: iadd
    //   2845: aload #4
    //   2847: iload #14
    //   2849: iload #15
    //   2851: iadd
    //   2852: baload
    //   2853: bastore
    //   2854: iinc #15, 1
    //   2857: iload_2
    //   2858: ifeq -> 2831
    //   2861: aload #8
    //   2863: iconst_0
    //   2864: iaload
    //   2865: bipush #29
    //   2867: iushr
    //   2868: aload #8
    //   2870: iconst_1
    //   2871: iaload
    //   2872: iconst_3
    //   2873: ishl
    //   2874: ior
    //   2875: istore #15
    //   2877: aload #8
    //   2879: iconst_0
    //   2880: iaload
    //   2881: iconst_3
    //   2882: ishl
    //   2883: istore #16
    //   2885: aload #8
    //   2887: iconst_0
    //   2888: iaload
    //   2889: bipush #63
    //   2891: iand
    //   2892: istore #17
    //   2894: iload #17
    //   2896: bipush #56
    //   2898: if_icmpge -> 2913
    //   2901: bipush #56
    //   2903: iload #17
    //   2905: isub
    //   2906: goto -> 2918
    //   2909: invokestatic a : (Ljava/lang/Throwable;)Ljava/lang/Throwable;
    //   2912: athrow
    //   2913: bipush #120
    //   2915: iload #17
    //   2917: isub
    //   2918: istore #18
    //   2920: aload #8
    //   2922: iconst_0
    //   2923: iaload
    //   2924: bipush #63
    //   2926: iand
    //   2927: istore #13
    //   2929: bipush #64
    //   2931: iload #13
    //   2933: isub
    //   2934: istore #19
    //   2936: aload #8
    //   2938: iconst_0
    //   2939: dup2
    //   2940: iaload
    //   2941: iload #18
    //   2943: iadd
    //   2944: iastore
    //   2945: aload #8
    //   2947: iconst_0
    //   2948: dup2
    //   2949: iaload
    //   2950: iconst_m1
    //   2951: iand
    //   2952: iastore
    //   2953: aload #8
    //   2955: iconst_0
    //   2956: iaload
    //   2957: iload #18
    //   2959: if_icmpge -> 2977
    //   2962: aload #8
    //   2964: iconst_1
    //   2965: dup2
    //   2966: iaload
    //   2967: iconst_1
    //   2968: iadd
    //   2969: iastore
    //   2970: goto -> 2977
    //   2973: invokestatic a : (Ljava/lang/Throwable;)Ljava/lang/Throwable;
    //   2976: athrow
    //   2977: iconst_0
    //   2978: istore #14
    //   2980: iload #13
    //   2982: ifle -> 3613
    //   2985: iload #18
    //   2987: iload #19
    //   2989: if_icmplt -> 3613
    //   2992: goto -> 2999
    //   2995: invokestatic a : (Ljava/lang/Throwable;)Ljava/lang/Throwable;
    //   2998: athrow
    //   2999: iconst_0
    //   3000: istore #20
    //   3002: iload #20
    //   3004: iload #19
    //   3006: if_icmpge -> 3029
    //   3009: aload #10
    //   3011: iload #13
    //   3013: iload #20
    //   3015: iadd
    //   3016: aload #6
    //   3018: iload #20
    //   3020: baload
    //   3021: bastore
    //   3022: iinc #20, 1
    //   3025: iload_2
    //   3026: ifeq -> 3002
    //   3029: bipush #64
    //   3031: newarray int
    //   3033: astore #20
    //   3035: bipush #8
    //   3037: newarray int
    //   3039: astore #21
    //   3041: iconst_0
    //   3042: istore #22
    //   3044: iload #22
    //   3046: bipush #8
    //   3048: if_icmpge -> 3068
    //   3051: aload #21
    //   3053: iload #22
    //   3055: aload #9
    //   3057: iload #22
    //   3059: iaload
    //   3060: iastore
    //   3061: iinc #22, 1
    //   3064: iload_2
    //   3065: ifeq -> 3044
    //   3068: iconst_0
    //   3069: istore #22
    //   3071: iload #22
    //   3073: bipush #64
    //   3075: if_icmpge -> 3566
    //   3078: iload #22
    //   3080: bipush #16
    //   3082: if_icmpge -> 3163
    //   3085: aload #20
    //   3087: iload #22
    //   3089: aload #10
    //   3091: iconst_4
    //   3092: iload #22
    //   3094: imul
    //   3095: baload
    //   3096: sipush #255
    //   3099: iand
    //   3100: bipush #24
    //   3102: ishl
    //   3103: aload #10
    //   3105: iconst_4
    //   3106: iload #22
    //   3108: imul
    //   3109: iconst_1
    //   3110: iadd
    //   3111: baload
    //   3112: sipush #255
    //   3115: iand
    //   3116: bipush #16
    //   3118: ishl
    //   3119: ior
    //   3120: aload #10
    //   3122: iconst_4
    //   3123: iload #22
    //   3125: imul
    //   3126: iconst_2
    //   3127: iadd
    //   3128: baload
    //   3129: sipush #255
    //   3132: iand
    //   3133: bipush #8
    //   3135: ishl
    //   3136: ior
    //   3137: aload #10
    //   3139: iconst_4
    //   3140: iload #22
    //   3142: imul
    //   3143: iconst_3
    //   3144: iadd
    //   3145: baload
    //   3146: sipush #255
    //   3149: iand
    //   3150: ior
    //   3151: iastore
    //   3152: iload_2
    //   3153: ifeq -> 3306
    //   3156: goto -> 3163
    //   3159: invokestatic a : (Ljava/lang/Throwable;)Ljava/lang/Throwable;
    //   3162: athrow
    //   3163: aload #20
    //   3165: iload #22
    //   3167: aload #20
    //   3169: iload #22
    //   3171: iconst_2
    //   3172: isub
    //   3173: iaload
    //   3174: bipush #17
    //   3176: iushr
    //   3177: aload #20
    //   3179: iload #22
    //   3181: iconst_2
    //   3182: isub
    //   3183: iaload
    //   3184: bipush #15
    //   3186: ishl
    //   3187: ior
    //   3188: aload #20
    //   3190: iload #22
    //   3192: iconst_2
    //   3193: isub
    //   3194: iaload
    //   3195: bipush #19
    //   3197: iushr
    //   3198: aload #20
    //   3200: iload #22
    //   3202: iconst_2
    //   3203: isub
    //   3204: iaload
    //   3205: bipush #13
    //   3207: ishl
    //   3208: ior
    //   3209: ixor
    //   3210: aload #20
    //   3212: iload #22
    //   3214: iconst_2
    //   3215: isub
    //   3216: iaload
    //   3217: bipush #10
    //   3219: iushr
    //   3220: ixor
    //   3221: aload #20
    //   3223: iload #22
    //   3225: bipush #7
    //   3227: isub
    //   3228: iaload
    //   3229: iadd
    //   3230: aload #20
    //   3232: iload #22
    //   3234: bipush #15
    //   3236: isub
    //   3237: iaload
    //   3238: bipush #7
    //   3240: iushr
    //   3241: aload #20
    //   3243: iload #22
    //   3245: bipush #15
    //   3247: isub
    //   3248: iaload
    //   3249: bipush #25
    //   3251: ishl
    //   3252: ior
    //   3253: aload #20
    //   3255: iload #22
    //   3257: bipush #15
    //   3259: isub
    //   3260: iaload
    //   3261: bipush #18
    //   3263: iushr
    //   3264: aload #20
    //   3266: iload #22
    //   3268: bipush #15
    //   3270: isub
    //   3271: iaload
    //   3272: bipush #14
    //   3274: ishl
    //   3275: ior
    //   3276: ixor
    //   3277: aload #20
    //   3279: iload #22
    //   3281: bipush #15
    //   3283: isub
    //   3284: iaload
    //   3285: iconst_3
    //   3286: iushr
    //   3287: ixor
    //   3288: iadd
    //   3289: aload #20
    //   3291: iload #22
    //   3293: bipush #16
    //   3295: isub
    //   3296: iaload
    //   3297: iadd
    //   3298: iastore
    //   3299: goto -> 3306
    //   3302: invokestatic a : (Ljava/lang/Throwable;)Ljava/lang/Throwable;
    //   3305: athrow
    //   3306: aload #21
    //   3308: bipush #7
    //   3310: iaload
    //   3311: aload #21
    //   3313: iconst_4
    //   3314: iaload
    //   3315: bipush #6
    //   3317: iushr
    //   3318: aload #21
    //   3320: iconst_4
    //   3321: iaload
    //   3322: bipush #26
    //   3324: ishl
    //   3325: ior
    //   3326: aload #21
    //   3328: iconst_4
    //   3329: iaload
    //   3330: bipush #11
    //   3332: iushr
    //   3333: aload #21
    //   3335: iconst_4
    //   3336: iaload
    //   3337: bipush #21
    //   3339: ishl
    //   3340: ior
    //   3341: ixor
    //   3342: aload #21
    //   3344: iconst_4
    //   3345: iaload
    //   3346: bipush #25
    //   3348: iushr
    //   3349: aload #21
    //   3351: iconst_4
    //   3352: iaload
    //   3353: bipush #7
    //   3355: ishl
    //   3356: ior
    //   3357: ixor
    //   3358: iadd
    //   3359: aload #21
    //   3361: bipush #6
    //   3363: iaload
    //   3364: aload #21
    //   3366: iconst_4
    //   3367: iaload
    //   3368: aload #21
    //   3370: iconst_5
    //   3371: iaload
    //   3372: aload #21
    //   3374: bipush #6
    //   3376: iaload
    //   3377: ixor
    //   3378: iand
    //   3379: ixor
    //   3380: iadd
    //   3381: aload #7
    //   3383: iload #22
    //   3385: iaload
    //   3386: iadd
    //   3387: aload #20
    //   3389: iload #22
    //   3391: iaload
    //   3392: iadd
    //   3393: istore #23
    //   3395: aload #21
    //   3397: iconst_0
    //   3398: iaload
    //   3399: iconst_2
    //   3400: iushr
    //   3401: aload #21
    //   3403: iconst_0
    //   3404: iaload
    //   3405: bipush #30
    //   3407: ishl
    //   3408: ior
    //   3409: aload #21
    //   3411: iconst_0
    //   3412: iaload
    //   3413: bipush #13
    //   3415: iushr
    //   3416: aload #21
    //   3418: iconst_0
    //   3419: iaload
    //   3420: bipush #19
    //   3422: ishl
    //   3423: ior
    //   3424: ixor
    //   3425: aload #21
    //   3427: iconst_0
    //   3428: iaload
    //   3429: bipush #22
    //   3431: iushr
    //   3432: aload #21
    //   3434: iconst_0
    //   3435: iaload
    //   3436: bipush #10
    //   3438: ishl
    //   3439: ior
    //   3440: ixor
    //   3441: aload #21
    //   3443: iconst_0
    //   3444: iaload
    //   3445: aload #21
    //   3447: iconst_1
    //   3448: iaload
    //   3449: iand
    //   3450: aload #21
    //   3452: iconst_2
    //   3453: iaload
    //   3454: aload #21
    //   3456: iconst_0
    //   3457: iaload
    //   3458: aload #21
    //   3460: iconst_1
    //   3461: iaload
    //   3462: ior
    //   3463: iand
    //   3464: ior
    //   3465: iadd
    //   3466: istore #24
    //   3468: aload #21
    //   3470: iconst_3
    //   3471: dup2
    //   3472: iaload
    //   3473: iload #23
    //   3475: iadd
    //   3476: iastore
    //   3477: aload #21
    //   3479: bipush #7
    //   3481: iload #23
    //   3483: iload #24
    //   3485: iadd
    //   3486: iastore
    //   3487: aload #21
    //   3489: bipush #7
    //   3491: iaload
    //   3492: istore #23
    //   3494: aload #21
    //   3496: bipush #7
    //   3498: aload #21
    //   3500: bipush #6
    //   3502: iaload
    //   3503: iastore
    //   3504: aload #21
    //   3506: bipush #6
    //   3508: aload #21
    //   3510: iconst_5
    //   3511: iaload
    //   3512: iastore
    //   3513: aload #21
    //   3515: iconst_5
    //   3516: aload #21
    //   3518: iconst_4
    //   3519: iaload
    //   3520: iastore
    //   3521: aload #21
    //   3523: iconst_4
    //   3524: aload #21
    //   3526: iconst_3
    //   3527: iaload
    //   3528: iastore
    //   3529: aload #21
    //   3531: iconst_3
    //   3532: aload #21
    //   3534: iconst_2
    //   3535: iaload
    //   3536: iastore
    //   3537: aload #21
    //   3539: iconst_2
    //   3540: aload #21
    //   3542: iconst_1
    //   3543: iaload
    //   3544: iastore
    //   3545: aload #21
    //   3547: iconst_1
    //   3548: aload #21
    //   3550: iconst_0
    //   3551: iaload
    //   3552: iastore
    //   3553: aload #21
    //   3555: iconst_0
    //   3556: iload #23
    //   3558: iastore
    //   3559: iinc #22, 1
    //   3562: iload_2
    //   3563: ifeq -> 3071
    //   3566: iconst_0
    //   3567: istore #22
    //   3569: iload #22
    //   3571: bipush #8
    //   3573: if_icmpge -> 3596
    //   3576: aload #9
    //   3578: iload #22
    //   3580: dup2
    //   3581: iaload
    //   3582: aload #21
    //   3584: iload #22
    //   3586: iaload
    //   3587: iadd
    //   3588: iastore
    //   3589: iinc #22, 1
    //   3592: iload_2
    //   3593: ifeq -> 3569
    //   3596: iload #14
    //   3598: iload #19
    //   3600: iadd
    //   3601: istore #14
    //   3603: iload #18
    //   3605: iload #19
    //   3607: isub
    //   3608: istore #18
    //   3610: iconst_0
    //   3611: istore #13
    //   3613: iload #18
    //   3615: bipush #64
    //   3617: if_icmplt -> 4227
    //   3620: iconst_0
    //   3621: istore #20
    //   3623: iload #20
    //   3625: bipush #64
    //   3627: if_icmpge -> 3650
    //   3630: aload #11
    //   3632: iload #20
    //   3634: aload #6
    //   3636: iload #14
    //   3638: iload #20
    //   3640: iadd
    //   3641: baload
    //   3642: bastore
    //   3643: iinc #20, 1
    //   3646: iload_2
    //   3647: ifeq -> 3623
    //   3650: bipush #64
    //   3652: newarray int
    //   3654: astore #20
    //   3656: bipush #8
    //   3658: newarray int
    //   3660: astore #21
    //   3662: iconst_0
    //   3663: istore #22
    //   3665: iload #22
    //   3667: bipush #8
    //   3669: if_icmpge -> 3689
    //   3672: aload #21
    //   3674: iload #22
    //   3676: aload #9
    //   3678: iload #22
    //   3680: iaload
    //   3681: iastore
    //   3682: iinc #22, 1
    //   3685: iload_2
    //   3686: ifeq -> 3665
    //   3689: iconst_0
    //   3690: istore #22
    //   3692: iload #22
    //   3694: bipush #64
    //   3696: if_icmpge -> 4187
    //   3699: iload #22
    //   3701: bipush #16
    //   3703: if_icmpge -> 3784
    //   3706: aload #20
    //   3708: iload #22
    //   3710: aload #11
    //   3712: iconst_4
    //   3713: iload #22
    //   3715: imul
    //   3716: baload
    //   3717: sipush #255
    //   3720: iand
    //   3721: bipush #24
    //   3723: ishl
    //   3724: aload #11
    //   3726: iconst_4
    //   3727: iload #22
    //   3729: imul
    //   3730: iconst_1
    //   3731: iadd
    //   3732: baload
    //   3733: sipush #255
    //   3736: iand
    //   3737: bipush #16
    //   3739: ishl
    //   3740: ior
    //   3741: aload #11
    //   3743: iconst_4
    //   3744: iload #22
    //   3746: imul
    //   3747: iconst_2
    //   3748: iadd
    //   3749: baload
    //   3750: sipush #255
    //   3753: iand
    //   3754: bipush #8
    //   3756: ishl
    //   3757: ior
    //   3758: aload #11
    //   3760: iconst_4
    //   3761: iload #22
    //   3763: imul
    //   3764: iconst_3
    //   3765: iadd
    //   3766: baload
    //   3767: sipush #255
    //   3770: iand
    //   3771: ior
    //   3772: iastore
    //   3773: iload_2
    //   3774: ifeq -> 3927
    //   3777: goto -> 3784
    //   3780: invokestatic a : (Ljava/lang/Throwable;)Ljava/lang/Throwable;
    //   3783: athrow
    //   3784: aload #20
    //   3786: iload #22
    //   3788: aload #20
    //   3790: iload #22
    //   3792: iconst_2
    //   3793: isub
    //   3794: iaload
    //   3795: bipush #17
    //   3797: iushr
    //   3798: aload #20
    //   3800: iload #22
    //   3802: iconst_2
    //   3803: isub
    //   3804: iaload
    //   3805: bipush #15
    //   3807: ishl
    //   3808: ior
    //   3809: aload #20
    //   3811: iload #22
    //   3813: iconst_2
    //   3814: isub
    //   3815: iaload
    //   3816: bipush #19
    //   3818: iushr
    //   3819: aload #20
    //   3821: iload #22
    //   3823: iconst_2
    //   3824: isub
    //   3825: iaload
    //   3826: bipush #13
    //   3828: ishl
    //   3829: ior
    //   3830: ixor
    //   3831: aload #20
    //   3833: iload #22
    //   3835: iconst_2
    //   3836: isub
    //   3837: iaload
    //   3838: bipush #10
    //   3840: iushr
    //   3841: ixor
    //   3842: aload #20
    //   3844: iload #22
    //   3846: bipush #7
    //   3848: isub
    //   3849: iaload
    //   3850: iadd
    //   3851: aload #20
    //   3853: iload #22
    //   3855: bipush #15
    //   3857: isub
    //   3858: iaload
    //   3859: bipush #7
    //   3861: iushr
    //   3862: aload #20
    //   3864: iload #22
    //   3866: bipush #15
    //   3868: isub
    //   3869: iaload
    //   3870: bipush #25
    //   3872: ishl
    //   3873: ior
    //   3874: aload #20
    //   3876: iload #22
    //   3878: bipush #15
    //   3880: isub
    //   3881: iaload
    //   3882: bipush #18
    //   3884: iushr
    //   3885: aload #20
    //   3887: iload #22
    //   3889: bipush #15
    //   3891: isub
    //   3892: iaload
    //   3893: bipush #14
    //   3895: ishl
    //   3896: ior
    //   3897: ixor
    //   3898: aload #20
    //   3900: iload #22
    //   3902: bipush #15
    //   3904: isub
    //   3905: iaload
    //   3906: iconst_3
    //   3907: iushr
    //   3908: ixor
    //   3909: iadd
    //   3910: aload #20
    //   3912: iload #22
    //   3914: bipush #16
    //   3916: isub
    //   3917: iaload
    //   3918: iadd
    //   3919: iastore
    //   3920: goto -> 3927
    //   3923: invokestatic a : (Ljava/lang/Throwable;)Ljava/lang/Throwable;
    //   3926: athrow
    //   3927: aload #21
    //   3929: bipush #7
    //   3931: iaload
    //   3932: aload #21
    //   3934: iconst_4
    //   3935: iaload
    //   3936: bipush #6
    //   3938: iushr
    //   3939: aload #21
    //   3941: iconst_4
    //   3942: iaload
    //   3943: bipush #26
    //   3945: ishl
    //   3946: ior
    //   3947: aload #21
    //   3949: iconst_4
    //   3950: iaload
    //   3951: bipush #11
    //   3953: iushr
    //   3954: aload #21
    //   3956: iconst_4
    //   3957: iaload
    //   3958: bipush #21
    //   3960: ishl
    //   3961: ior
    //   3962: ixor
    //   3963: aload #21
    //   3965: iconst_4
    //   3966: iaload
    //   3967: bipush #25
    //   3969: iushr
    //   3970: aload #21
    //   3972: iconst_4
    //   3973: iaload
    //   3974: bipush #7
    //   3976: ishl
    //   3977: ior
    //   3978: ixor
    //   3979: iadd
    //   3980: aload #21
    //   3982: bipush #6
    //   3984: iaload
    //   3985: aload #21
    //   3987: iconst_4
    //   3988: iaload
    //   3989: aload #21
    //   3991: iconst_5
    //   3992: iaload
    //   3993: aload #21
    //   3995: bipush #6
    //   3997: iaload
    //   3998: ixor
    //   3999: iand
    //   4000: ixor
    //   4001: iadd
    //   4002: aload #7
    //   4004: iload #22
    //   4006: iaload
    //   4007: iadd
    //   4008: aload #20
    //   4010: iload #22
    //   4012: iaload
    //   4013: iadd
    //   4014: istore #23
    //   4016: aload #21
    //   4018: iconst_0
    //   4019: iaload
    //   4020: iconst_2
    //   4021: iushr
    //   4022: aload #21
    //   4024: iconst_0
    //   4025: iaload
    //   4026: bipush #30
    //   4028: ishl
    //   4029: ior
    //   4030: aload #21
    //   4032: iconst_0
    //   4033: iaload
    //   4034: bipush #13
    //   4036: iushr
    //   4037: aload #21
    //   4039: iconst_0
    //   4040: iaload
    //   4041: bipush #19
    //   4043: ishl
    //   4044: ior
    //   4045: ixor
    //   4046: aload #21
    //   4048: iconst_0
    //   4049: iaload
    //   4050: bipush #22
    //   4052: iushr
    //   4053: aload #21
    //   4055: iconst_0
    //   4056: iaload
    //   4057: bipush #10
    //   4059: ishl
    //   4060: ior
    //   4061: ixor
    //   4062: aload #21
    //   4064: iconst_0
    //   4065: iaload
    //   4066: aload #21
    //   4068: iconst_1
    //   4069: iaload
    //   4070: iand
    //   4071: aload #21
    //   4073: iconst_2
    //   4074: iaload
    //   4075: aload #21
    //   4077: iconst_0
    //   4078: iaload
    //   4079: aload #21
    //   4081: iconst_1
    //   4082: iaload
    //   4083: ior
    //   4084: iand
    //   4085: ior
    //   4086: iadd
    //   4087: istore #24
    //   4089: aload #21
    //   4091: iconst_3
    //   4092: dup2
    //   4093: iaload
    //   4094: iload #23
    //   4096: iadd
    //   4097: iastore
    //   4098: aload #21
    //   4100: bipush #7
    //   4102: iload #23
    //   4104: iload #24
    //   4106: iadd
    //   4107: iastore
    //   4108: aload #21
    //   4110: bipush #7
    //   4112: iaload
    //   4113: istore #23
    //   4115: aload #21
    //   4117: bipush #7
    //   4119: aload #21
    //   4121: bipush #6
    //   4123: iaload
    //   4124: iastore
    //   4125: aload #21
    //   4127: bipush #6
    //   4129: aload #21
    //   4131: iconst_5
    //   4132: iaload
    //   4133: iastore
    //   4134: aload #21
    //   4136: iconst_5
    //   4137: aload #21
    //   4139: iconst_4
    //   4140: iaload
    //   4141: iastore
    //   4142: aload #21
    //   4144: iconst_4
    //   4145: aload #21
    //   4147: iconst_3
    //   4148: iaload
    //   4149: iastore
    //   4150: aload #21
    //   4152: iconst_3
    //   4153: aload #21
    //   4155: iconst_2
    //   4156: iaload
    //   4157: iastore
    //   4158: aload #21
    //   4160: iconst_2
    //   4161: aload #21
    //   4163: iconst_1
    //   4164: iaload
    //   4165: iastore
    //   4166: aload #21
    //   4168: iconst_1
    //   4169: aload #21
    //   4171: iconst_0
    //   4172: iaload
    //   4173: iastore
    //   4174: aload #21
    //   4176: iconst_0
    //   4177: iload #23
    //   4179: iastore
    //   4180: iinc #22, 1
    //   4183: iload_2
    //   4184: ifeq -> 3692
    //   4187: iconst_0
    //   4188: istore #22
    //   4190: iload #22
    //   4192: bipush #8
    //   4194: if_icmpge -> 4217
    //   4197: aload #9
    //   4199: iload #22
    //   4201: dup2
    //   4202: iaload
    //   4203: aload #21
    //   4205: iload #22
    //   4207: iaload
    //   4208: iadd
    //   4209: iastore
    //   4210: iinc #22, 1
    //   4213: iload_2
    //   4214: ifeq -> 4190
    //   4217: iinc #14, 64
    //   4220: iinc #18, -64
    //   4223: iload_2
    //   4224: ifeq -> 3613
    //   4227: iload #18
    //   4229: ifle -> 4265
    //   4232: iconst_0
    //   4233: istore #20
    //   4235: iload #20
    //   4237: iload #18
    //   4239: if_icmpge -> 4265
    //   4242: aload #10
    //   4244: iload #13
    //   4246: iload #20
    //   4248: iadd
    //   4249: aload #6
    //   4251: iload #14
    //   4253: iload #20
    //   4255: iadd
    //   4256: baload
    //   4257: bastore
    //   4258: iinc #20, 1
    //   4261: iload_2
    //   4262: ifeq -> 4235
    //   4265: bipush #8
    //   4267: newarray byte
    //   4269: astore #20
    //   4271: aload #20
    //   4273: iconst_0
    //   4274: iload #15
    //   4276: bipush #24
    //   4278: iushr
    //   4279: i2b
    //   4280: bastore
    //   4281: aload #20
    //   4283: iconst_1
    //   4284: iload #15
    //   4286: bipush #16
    //   4288: iushr
    //   4289: i2b
    //   4290: bastore
    //   4291: aload #20
    //   4293: iconst_2
    //   4294: iload #15
    //   4296: bipush #8
    //   4298: iushr
    //   4299: i2b
    //   4300: bastore
    //   4301: aload #20
    //   4303: iconst_3
    //   4304: iload #15
    //   4306: i2b
    //   4307: bastore
    //   4308: aload #20
    //   4310: iconst_4
    //   4311: iload #16
    //   4313: bipush #24
    //   4315: iushr
    //   4316: i2b
    //   4317: bastore
    //   4318: aload #20
    //   4320: iconst_5
    //   4321: iload #16
    //   4323: bipush #16
    //   4325: iushr
    //   4326: i2b
    //   4327: bastore
    //   4328: aload #20
    //   4330: bipush #6
    //   4332: iload #16
    //   4334: bipush #8
    //   4336: iushr
    //   4337: i2b
    //   4338: bastore
    //   4339: aload #20
    //   4341: bipush #7
    //   4343: iload #16
    //   4345: i2b
    //   4346: bastore
    //   4347: bipush #8
    //   4349: istore #12
    //   4351: aload #8
    //   4353: iconst_0
    //   4354: iaload
    //   4355: bipush #63
    //   4357: iand
    //   4358: istore #13
    //   4360: bipush #64
    //   4362: iload #13
    //   4364: isub
    //   4365: istore #19
    //   4367: aload #8
    //   4369: iconst_0
    //   4370: dup2
    //   4371: iaload
    //   4372: iload #12
    //   4374: iadd
    //   4375: iastore
    //   4376: aload #8
    //   4378: iconst_0
    //   4379: dup2
    //   4380: iaload
    //   4381: iconst_m1
    //   4382: iand
    //   4383: iastore
    //   4384: aload #8
    //   4386: iconst_0
    //   4387: iaload
    //   4388: iload #12
    //   4390: if_icmpge -> 4408
    //   4393: aload #8
    //   4395: iconst_1
    //   4396: dup2
    //   4397: iaload
    //   4398: iconst_1
    //   4399: iadd
    //   4400: iastore
    //   4401: goto -> 4408
    //   4404: invokestatic a : (Ljava/lang/Throwable;)Ljava/lang/Throwable;
    //   4407: athrow
    //   4408: iload #13
    //   4410: ifle -> 5024
    //   4413: iload #12
    //   4415: iload #19
    //   4417: if_icmplt -> 5024
    //   4420: goto -> 4427
    //   4423: invokestatic a : (Ljava/lang/Throwable;)Ljava/lang/Throwable;
    //   4426: athrow
    //   4427: iconst_0
    //   4428: istore #21
    //   4430: iload #21
    //   4432: iload #19
    //   4434: if_icmpge -> 4457
    //   4437: aload #10
    //   4439: iload #13
    //   4441: iload #21
    //   4443: iadd
    //   4444: aload #20
    //   4446: iload #21
    //   4448: baload
    //   4449: bastore
    //   4450: iinc #21, 1
    //   4453: iload_2
    //   4454: ifeq -> 4430
    //   4457: bipush #64
    //   4459: newarray int
    //   4461: astore #21
    //   4463: bipush #8
    //   4465: newarray int
    //   4467: astore #22
    //   4469: iconst_0
    //   4470: istore #23
    //   4472: iload #23
    //   4474: bipush #8
    //   4476: if_icmpge -> 4496
    //   4479: aload #22
    //   4481: iload #23
    //   4483: aload #9
    //   4485: iload #23
    //   4487: iaload
    //   4488: iastore
    //   4489: iinc #23, 1
    //   4492: iload_2
    //   4493: ifeq -> 4472
    //   4496: iconst_0
    //   4497: istore #23
    //   4499: iload #23
    //   4501: bipush #64
    //   4503: if_icmpge -> 4994
    //   4506: iload #23
    //   4508: bipush #16
    //   4510: if_icmpge -> 4591
    //   4513: aload #21
    //   4515: iload #23
    //   4517: aload #10
    //   4519: iconst_4
    //   4520: iload #23
    //   4522: imul
    //   4523: baload
    //   4524: sipush #255
    //   4527: iand
    //   4528: bipush #24
    //   4530: ishl
    //   4531: aload #10
    //   4533: iconst_4
    //   4534: iload #23
    //   4536: imul
    //   4537: iconst_1
    //   4538: iadd
    //   4539: baload
    //   4540: sipush #255
    //   4543: iand
    //   4544: bipush #16
    //   4546: ishl
    //   4547: ior
    //   4548: aload #10
    //   4550: iconst_4
    //   4551: iload #23
    //   4553: imul
    //   4554: iconst_2
    //   4555: iadd
    //   4556: baload
    //   4557: sipush #255
    //   4560: iand
    //   4561: bipush #8
    //   4563: ishl
    //   4564: ior
    //   4565: aload #10
    //   4567: iconst_4
    //   4568: iload #23
    //   4570: imul
    //   4571: iconst_3
    //   4572: iadd
    //   4573: baload
    //   4574: sipush #255
    //   4577: iand
    //   4578: ior
    //   4579: iastore
    //   4580: iload_2
    //   4581: ifeq -> 4734
    //   4584: goto -> 4591
    //   4587: invokestatic a : (Ljava/lang/Throwable;)Ljava/lang/Throwable;
    //   4590: athrow
    //   4591: aload #21
    //   4593: iload #23
    //   4595: aload #21
    //   4597: iload #23
    //   4599: iconst_2
    //   4600: isub
    //   4601: iaload
    //   4602: bipush #17
    //   4604: iushr
    //   4605: aload #21
    //   4607: iload #23
    //   4609: iconst_2
    //   4610: isub
    //   4611: iaload
    //   4612: bipush #15
    //   4614: ishl
    //   4615: ior
    //   4616: aload #21
    //   4618: iload #23
    //   4620: iconst_2
    //   4621: isub
    //   4622: iaload
    //   4623: bipush #19
    //   4625: iushr
    //   4626: aload #21
    //   4628: iload #23
    //   4630: iconst_2
    //   4631: isub
    //   4632: iaload
    //   4633: bipush #13
    //   4635: ishl
    //   4636: ior
    //   4637: ixor
    //   4638: aload #21
    //   4640: iload #23
    //   4642: iconst_2
    //   4643: isub
    //   4644: iaload
    //   4645: bipush #10
    //   4647: iushr
    //   4648: ixor
    //   4649: aload #21
    //   4651: iload #23
    //   4653: bipush #7
    //   4655: isub
    //   4656: iaload
    //   4657: iadd
    //   4658: aload #21
    //   4660: iload #23
    //   4662: bipush #15
    //   4664: isub
    //   4665: iaload
    //   4666: bipush #7
    //   4668: iushr
    //   4669: aload #21
    //   4671: iload #23
    //   4673: bipush #15
    //   4675: isub
    //   4676: iaload
    //   4677: bipush #25
    //   4679: ishl
    //   4680: ior
    //   4681: aload #21
    //   4683: iload #23
    //   4685: bipush #15
    //   4687: isub
    //   4688: iaload
    //   4689: bipush #18
    //   4691: iushr
    //   4692: aload #21
    //   4694: iload #23
    //   4696: bipush #15
    //   4698: isub
    //   4699: iaload
    //   4700: bipush #14
    //   4702: ishl
    //   4703: ior
    //   4704: ixor
    //   4705: aload #21
    //   4707: iload #23
    //   4709: bipush #15
    //   4711: isub
    //   4712: iaload
    //   4713: iconst_3
    //   4714: iushr
    //   4715: ixor
    //   4716: iadd
    //   4717: aload #21
    //   4719: iload #23
    //   4721: bipush #16
    //   4723: isub
    //   4724: iaload
    //   4725: iadd
    //   4726: iastore
    //   4727: goto -> 4734
    //   4730: invokestatic a : (Ljava/lang/Throwable;)Ljava/lang/Throwable;
    //   4733: athrow
    //   4734: aload #22
    //   4736: bipush #7
    //   4738: iaload
    //   4739: aload #22
    //   4741: iconst_4
    //   4742: iaload
    //   4743: bipush #6
    //   4745: iushr
    //   4746: aload #22
    //   4748: iconst_4
    //   4749: iaload
    //   4750: bipush #26
    //   4752: ishl
    //   4753: ior
    //   4754: aload #22
    //   4756: iconst_4
    //   4757: iaload
    //   4758: bipush #11
    //   4760: iushr
    //   4761: aload #22
    //   4763: iconst_4
    //   4764: iaload
    //   4765: bipush #21
    //   4767: ishl
    //   4768: ior
    //   4769: ixor
    //   4770: aload #22
    //   4772: iconst_4
    //   4773: iaload
    //   4774: bipush #25
    //   4776: iushr
    //   4777: aload #22
    //   4779: iconst_4
    //   4780: iaload
    //   4781: bipush #7
    //   4783: ishl
    //   4784: ior
    //   4785: ixor
    //   4786: iadd
    //   4787: aload #22
    //   4789: bipush #6
    //   4791: iaload
    //   4792: aload #22
    //   4794: iconst_4
    //   4795: iaload
    //   4796: aload #22
    //   4798: iconst_5
    //   4799: iaload
    //   4800: aload #22
    //   4802: bipush #6
    //   4804: iaload
    //   4805: ixor
    //   4806: iand
    //   4807: ixor
    //   4808: iadd
    //   4809: aload #7
    //   4811: iload #23
    //   4813: iaload
    //   4814: iadd
    //   4815: aload #21
    //   4817: iload #23
    //   4819: iaload
    //   4820: iadd
    //   4821: istore #24
    //   4823: aload #22
    //   4825: iconst_0
    //   4826: iaload
    //   4827: iconst_2
    //   4828: iushr
    //   4829: aload #22
    //   4831: iconst_0
    //   4832: iaload
    //   4833: bipush #30
    //   4835: ishl
    //   4836: ior
    //   4837: aload #22
    //   4839: iconst_0
    //   4840: iaload
    //   4841: bipush #13
    //   4843: iushr
    //   4844: aload #22
    //   4846: iconst_0
    //   4847: iaload
    //   4848: bipush #19
    //   4850: ishl
    //   4851: ior
    //   4852: ixor
    //   4853: aload #22
    //   4855: iconst_0
    //   4856: iaload
    //   4857: bipush #22
    //   4859: iushr
    //   4860: aload #22
    //   4862: iconst_0
    //   4863: iaload
    //   4864: bipush #10
    //   4866: ishl
    //   4867: ior
    //   4868: ixor
    //   4869: aload #22
    //   4871: iconst_0
    //   4872: iaload
    //   4873: aload #22
    //   4875: iconst_1
    //   4876: iaload
    //   4877: iand
    //   4878: aload #22
    //   4880: iconst_2
    //   4881: iaload
    //   4882: aload #22
    //   4884: iconst_0
    //   4885: iaload
    //   4886: aload #22
    //   4888: iconst_1
    //   4889: iaload
    //   4890: ior
    //   4891: iand
    //   4892: ior
    //   4893: iadd
    //   4894: istore #25
    //   4896: aload #22
    //   4898: iconst_3
    //   4899: dup2
    //   4900: iaload
    //   4901: iload #24
    //   4903: iadd
    //   4904: iastore
    //   4905: aload #22
    //   4907: bipush #7
    //   4909: iload #24
    //   4911: iload #25
    //   4913: iadd
    //   4914: iastore
    //   4915: aload #22
    //   4917: bipush #7
    //   4919: iaload
    //   4920: istore #24
    //   4922: aload #22
    //   4924: bipush #7
    //   4926: aload #22
    //   4928: bipush #6
    //   4930: iaload
    //   4931: iastore
    //   4932: aload #22
    //   4934: bipush #6
    //   4936: aload #22
    //   4938: iconst_5
    //   4939: iaload
    //   4940: iastore
    //   4941: aload #22
    //   4943: iconst_5
    //   4944: aload #22
    //   4946: iconst_4
    //   4947: iaload
    //   4948: iastore
    //   4949: aload #22
    //   4951: iconst_4
    //   4952: aload #22
    //   4954: iconst_3
    //   4955: iaload
    //   4956: iastore
    //   4957: aload #22
    //   4959: iconst_3
    //   4960: aload #22
    //   4962: iconst_2
    //   4963: iaload
    //   4964: iastore
    //   4965: aload #22
    //   4967: iconst_2
    //   4968: aload #22
    //   4970: iconst_1
    //   4971: iaload
    //   4972: iastore
    //   4973: aload #22
    //   4975: iconst_1
    //   4976: aload #22
    //   4978: iconst_0
    //   4979: iaload
    //   4980: iastore
    //   4981: aload #22
    //   4983: iconst_0
    //   4984: iload #24
    //   4986: iastore
    //   4987: iinc #23, 1
    //   4990: iload_2
    //   4991: ifeq -> 4499
    //   4994: iconst_0
    //   4995: istore #23
    //   4997: iload #23
    //   4999: bipush #8
    //   5001: if_icmpge -> 5024
    //   5004: aload #9
    //   5006: iload #23
    //   5008: dup2
    //   5009: iaload
    //   5010: aload #22
    //   5012: iload #23
    //   5014: iaload
    //   5015: iadd
    //   5016: iastore
    //   5017: iinc #23, 1
    //   5020: iload_2
    //   5021: ifeq -> 4997
    //   5024: bipush #32
    //   5026: newarray byte
    //   5028: astore #5
    //   5030: sipush #-25585
    //   5033: aload #5
    //   5035: iconst_0
    //   5036: aload #9
    //   5038: iconst_0
    //   5039: iaload
    //   5040: bipush #24
    //   5042: iushr
    //   5043: i2b
    //   5044: bastore
    //   5045: sipush #23180
    //   5048: aload #5
    //   5050: iconst_1
    //   5051: aload #9
    //   5053: iconst_0
    //   5054: iaload
    //   5055: bipush #16
    //   5057: iushr
    //   5058: i2b
    //   5059: bastore
    //   5060: aload #5
    //   5062: iconst_2
    //   5063: aload #9
    //   5065: iconst_0
    //   5066: iaload
    //   5067: bipush #8
    //   5069: iushr
    //   5070: i2b
    //   5071: bastore
    //   5072: aload #5
    //   5074: iconst_3
    //   5075: aload #9
    //   5077: iconst_0
    //   5078: iaload
    //   5079: i2b
    //   5080: bastore
    //   5081: aload #5
    //   5083: iconst_4
    //   5084: aload #9
    //   5086: iconst_1
    //   5087: iaload
    //   5088: bipush #24
    //   5090: iushr
    //   5091: i2b
    //   5092: bastore
    //   5093: aload #5
    //   5095: iconst_5
    //   5096: aload #9
    //   5098: iconst_1
    //   5099: iaload
    //   5100: bipush #16
    //   5102: iushr
    //   5103: i2b
    //   5104: bastore
    //   5105: aload #5
    //   5107: bipush #6
    //   5109: aload #9
    //   5111: iconst_1
    //   5112: iaload
    //   5113: bipush #8
    //   5115: iushr
    //   5116: i2b
    //   5117: bastore
    //   5118: aload #5
    //   5120: bipush #7
    //   5122: aload #9
    //   5124: iconst_1
    //   5125: iaload
    //   5126: i2b
    //   5127: bastore
    //   5128: aload #5
    //   5130: bipush #8
    //   5132: aload #9
    //   5134: iconst_2
    //   5135: iaload
    //   5136: bipush #24
    //   5138: iushr
    //   5139: i2b
    //   5140: bastore
    //   5141: aload #5
    //   5143: bipush #9
    //   5145: aload #9
    //   5147: iconst_2
    //   5148: iaload
    //   5149: bipush #16
    //   5151: iushr
    //   5152: i2b
    //   5153: bastore
    //   5154: aload #5
    //   5156: bipush #10
    //   5158: aload #9
    //   5160: iconst_2
    //   5161: iaload
    //   5162: bipush #8
    //   5164: iushr
    //   5165: i2b
    //   5166: bastore
    //   5167: aload #5
    //   5169: bipush #11
    //   5171: aload #9
    //   5173: iconst_2
    //   5174: iaload
    //   5175: i2b
    //   5176: bastore
    //   5177: aload #5
    //   5179: bipush #12
    //   5181: aload #9
    //   5183: iconst_3
    //   5184: iaload
    //   5185: bipush #24
    //   5187: iushr
    //   5188: i2b
    //   5189: bastore
    //   5190: aload #5
    //   5192: bipush #13
    //   5194: aload #9
    //   5196: iconst_3
    //   5197: iaload
    //   5198: bipush #16
    //   5200: iushr
    //   5201: i2b
    //   5202: bastore
    //   5203: aload #5
    //   5205: bipush #14
    //   5207: aload #9
    //   5209: iconst_3
    //   5210: iaload
    //   5211: bipush #8
    //   5213: iushr
    //   5214: i2b
    //   5215: bastore
    //   5216: aload #5
    //   5218: bipush #15
    //   5220: aload #9
    //   5222: iconst_3
    //   5223: iaload
    //   5224: i2b
    //   5225: bastore
    //   5226: aload #5
    //   5228: bipush #16
    //   5230: aload #9
    //   5232: iconst_4
    //   5233: iaload
    //   5234: bipush #24
    //   5236: iushr
    //   5237: i2b
    //   5238: bastore
    //   5239: aload #5
    //   5241: bipush #17
    //   5243: aload #9
    //   5245: iconst_4
    //   5246: iaload
    //   5247: bipush #16
    //   5249: iushr
    //   5250: i2b
    //   5251: bastore
    //   5252: aload #5
    //   5254: bipush #18
    //   5256: aload #9
    //   5258: iconst_4
    //   5259: iaload
    //   5260: bipush #8
    //   5262: iushr
    //   5263: i2b
    //   5264: bastore
    //   5265: aload #5
    //   5267: bipush #19
    //   5269: aload #9
    //   5271: iconst_4
    //   5272: iaload
    //   5273: i2b
    //   5274: bastore
    //   5275: aload #5
    //   5277: bipush #20
    //   5279: aload #9
    //   5281: iconst_5
    //   5282: iaload
    //   5283: bipush #24
    //   5285: iushr
    //   5286: i2b
    //   5287: bastore
    //   5288: aload #5
    //   5290: bipush #21
    //   5292: aload #9
    //   5294: iconst_5
    //   5295: iaload
    //   5296: bipush #16
    //   5298: iushr
    //   5299: i2b
    //   5300: bastore
    //   5301: aload #5
    //   5303: bipush #22
    //   5305: aload #9
    //   5307: iconst_5
    //   5308: iaload
    //   5309: bipush #8
    //   5311: iushr
    //   5312: i2b
    //   5313: bastore
    //   5314: aload #5
    //   5316: bipush #23
    //   5318: aload #9
    //   5320: iconst_5
    //   5321: iaload
    //   5322: i2b
    //   5323: bastore
    //   5324: aload #5
    //   5326: bipush #24
    //   5328: aload #9
    //   5330: bipush #6
    //   5332: iaload
    //   5333: bipush #24
    //   5335: iushr
    //   5336: i2b
    //   5337: bastore
    //   5338: aload #5
    //   5340: bipush #25
    //   5342: aload #9
    //   5344: bipush #6
    //   5346: iaload
    //   5347: bipush #16
    //   5349: iushr
    //   5350: i2b
    //   5351: bastore
    //   5352: aload #5
    //   5354: bipush #26
    //   5356: aload #9
    //   5358: bipush #6
    //   5360: iaload
    //   5361: bipush #8
    //   5363: iushr
    //   5364: i2b
    //   5365: bastore
    //   5366: aload #5
    //   5368: bipush #27
    //   5370: aload #9
    //   5372: bipush #6
    //   5374: iaload
    //   5375: i2b
    //   5376: bastore
    //   5377: aload #5
    //   5379: bipush #28
    //   5381: aload #9
    //   5383: bipush #7
    //   5385: iaload
    //   5386: bipush #24
    //   5388: iushr
    //   5389: i2b
    //   5390: bastore
    //   5391: aload #5
    //   5393: bipush #29
    //   5395: aload #9
    //   5397: bipush #7
    //   5399: iaload
    //   5400: bipush #16
    //   5402: iushr
    //   5403: i2b
    //   5404: bastore
    //   5405: aload #5
    //   5407: bipush #30
    //   5409: aload #9
    //   5411: bipush #7
    //   5413: iaload
    //   5414: bipush #8
    //   5416: iushr
    //   5417: i2b
    //   5418: bastore
    //   5419: aload #5
    //   5421: bipush #31
    //   5423: aload #9
    //   5425: bipush #7
    //   5427: iaload
    //   5428: i2b
    //   5429: bastore
    //   5430: new java/math/BigInteger
    //   5433: dup
    //   5434: aload #5
    //   5436: invokespecial <init> : ([B)V
    //   5439: invokevirtual abs : ()Ljava/math/BigInteger;
    //   5442: putstatic burp/Zro2.Zu : Ljava/lang/Object;
    //   5445: invokestatic a : (II)Ljava/lang/String;
    //   5448: iconst_1
    //   5449: ldc burp/Zter
    //   5451: invokevirtual getClassLoader : ()Ljava/lang/ClassLoader;
    //   5454: invokestatic forName : (Ljava/lang/String;ZLjava/lang/ClassLoader;)Ljava/lang/Class;
    //   5457: invokevirtual getDeclaredFields : ()[Ljava/lang/reflect/Field;
    //   5460: astore #4
    //   5462: aload #4
    //   5464: arraylength
    //   5465: istore #5
    //   5467: iconst_0
    //   5468: istore #6
    //   5470: iload #6
    //   5472: iload #5
    //   5474: if_icmpge -> 5612
    //   5477: aload #4
    //   5479: iload #6
    //   5481: aaload
    //   5482: astore #7
    //   5484: aload #7
    //   5486: invokevirtual getModifiers : ()I
    //   5489: invokestatic isStatic : (I)Z
    //   5492: ifne -> 5502
    //   5495: goto -> 5605
    //   5498: invokestatic a : (Ljava/lang/Throwable;)Ljava/lang/Throwable;
    //   5501: athrow
    //   5502: aload #7
    //   5504: invokevirtual getType : ()Ljava/lang/Class;
    //   5507: astore #8
    //   5509: aload #8
    //   5511: ifnull -> 5592
    //   5514: aload #8
    //   5516: invokevirtual isPrimitive : ()Z
    //   5519: ifne -> 5592
    //   5522: goto -> 5529
    //   5525: invokestatic a : (Ljava/lang/Throwable;)Ljava/lang/Throwable;
    //   5528: athrow
    //   5529: aload #8
    //   5531: invokevirtual getPackage : ()Ljava/lang/Package;
    //   5534: ifnull -> 5592
    //   5537: goto -> 5544
    //   5540: invokestatic a : (Ljava/lang/Throwable;)Ljava/lang/Throwable;
    //   5543: athrow
    //   5544: aload #8
    //   5546: invokevirtual getPackage : ()Ljava/lang/Package;
    //   5549: invokevirtual getName : ()Ljava/lang/String;
    //   5552: ifnull -> 5592
    //   5555: goto -> 5562
    //   5558: invokestatic a : (Ljava/lang/Throwable;)Ljava/lang/Throwable;
    //   5561: athrow
    //   5562: aload #8
    //   5564: invokevirtual getPackage : ()Ljava/lang/Package;
    //   5567: invokevirtual getName : ()Ljava/lang/String;
    //   5570: sipush #-25592
    //   5573: sipush #-13726
    //   5576: invokestatic a : (II)Ljava/lang/String;
    //   5579: invokevirtual startsWith : (Ljava/lang/String;)Z
    //   5582: ifne -> 5592
    //   5585: goto -> 5592
    //   5588: invokestatic a : (Ljava/lang/Throwable;)Ljava/lang/Throwable;
    //   5591: athrow
    //   5592: aload #7
    //   5594: iconst_1
    //   5595: invokevirtual setAccessible : (Z)V
    //   5598: aload #7
    //   5600: aconst_null
    //   5601: invokevirtual get : (Ljava/lang/Object;)Ljava/lang/Object;
    //   5604: pop
    //   5605: iinc #6, 1
    //   5608: iload_2
    //   5609: ifeq -> 5470
    //   5612: sipush #-25599
    //   5615: sipush #-32722
    //   5618: invokestatic a : (II)Ljava/lang/String;
    //   5621: invokestatic forName : (Ljava/lang/String;)Ljava/lang/Class;
    //   5624: invokevirtual getDeclaredMethods : ()[Ljava/lang/reflect/Method;
    //   5627: astore #4
    //   5629: aload #4
    //   5631: arraylength
    //   5632: istore #5
    //   5634: iconst_0
    //   5635: istore #6
    //   5637: iload #6
    //   5639: iload #5
    //   5641: if_icmpge -> 5774
    //   5644: aload #4
    //   5646: iload #6
    //   5648: aaload
    //   5649: astore #7
    //   5651: aload #7
    //   5653: invokevirtual getParameterTypes : ()[Ljava/lang/Class;
    //   5656: pop
    //   5657: aload #7
    //   5659: invokevirtual getModifiers : ()I
    //   5662: invokestatic isStatic : (I)Z
    //   5665: ifeq -> 5760
    //   5668: aload #7
    //   5670: invokevirtual getParameterTypes : ()[Ljava/lang/Class;
    //   5673: arraylength
    //   5674: iconst_2
    //   5675: if_icmpne -> 5760
    //   5678: goto -> 5685
    //   5681: invokestatic a : (Ljava/lang/Throwable;)Ljava/lang/Throwable;
    //   5684: athrow
    //   5685: aload #7
    //   5687: invokevirtual getReturnType : ()Ljava/lang/Class;
    //   5690: getstatic java/lang/Void.TYPE : Ljava/lang/Class;
    //   5693: invokevirtual equals : (Ljava/lang/Object;)Z
    //   5696: ifeq -> 5760
    //   5699: goto -> 5706
    //   5702: invokestatic a : (Ljava/lang/Throwable;)Ljava/lang/Throwable;
    //   5705: athrow
    //   5706: aload #7
    //   5708: iconst_1
    //   5709: invokevirtual setAccessible : (Z)V
    //   5712: aload #7
    //   5714: aconst_null
    //   5715: iconst_2
    //   5716: anewarray java/lang/Object
    //   5719: dup
    //   5720: iconst_0
    //   5721: aload_0
    //   5722: aastore
    //   5723: dup
    //   5724: iconst_1
    //   5725: aload_1
    //   5726: ifnonnull -> 5744
    //   5729: goto -> 5736
    //   5732: invokestatic a : (Ljava/lang/Throwable;)Ljava/lang/Throwable;
    //   5735: athrow
    //   5736: aload_1
    //   5737: goto -> 5751
    //   5740: invokestatic a : (Ljava/lang/Throwable;)Ljava/lang/Throwable;
    //   5743: athrow
    //   5744: aload_1
    //   5745: checkcast [B
    //   5748: invokevirtual clone : ()Ljava/lang/Object;
    //   5751: aastore
    //   5752: invokevirtual invoke : (Ljava/lang/Object;[Ljava/lang/Object;)Ljava/lang/Object;
    //   5755: pop
    //   5756: iload_2
    //   5757: ifeq -> 5774
    //   5760: iinc #6, 1
    //   5763: iload_2
    //   5764: ifeq -> 5637
    //   5767: goto -> 5774
    //   5770: invokestatic a : (Ljava/lang/Throwable;)Ljava/lang/Throwable;
    //   5773: athrow
    //   5774: getstatic burp/Zzh1.Zf : Ljava/lang/Object;
    //   5777: checkcast java/math/BigInteger
    //   5780: invokevirtual toByteArray : ()[B
    //   5783: astore #4
    //   5785: new java/lang/StringBuilder
    //   5788: dup
    //   5789: invokespecial <init> : ()V
    //   5792: astore #6
    //   5794: aload #6
    //   5796: sipush #-25600
    //   5799: sipush #23530
    //   5802: invokestatic a : (II)Ljava/lang/String;
    //   5805: invokevirtual append : (Ljava/lang/String;)Ljava/lang/StringBuilder;
    //   5808: pop
    //   5809: aload #4
    //   5811: astore #7
    //   5813: aload #7
    //   5815: arraylength
    //   5816: istore #8
    //   5818: iconst_0
    //   5819: istore #9
    //   5821: iload #9
    //   5823: iload #8
    //   5825: if_icmpge -> 5851
    //   5828: aload #7
    //   5830: iload #9
    //   5832: baload
    //   5833: istore #10
    //   5835: aload #6
    //   5837: iload #10
    //   5839: i2c
    //   5840: invokevirtual append : (C)Ljava/lang/StringBuilder;
    //   5843: pop
    //   5844: iinc #9, 1
    //   5847: iload_2
    //   5848: ifeq -> 5821
    //   5851: aload #6
    //   5853: sipush #-25597
    //   5856: sipush #-2233
    //   5859: invokestatic a : (II)Ljava/lang/String;
    //   5862: ldc ''
    //   5864: invokestatic getProperty : (Ljava/lang/String;Ljava/lang/String;)Ljava/lang/String;
    //   5867: invokevirtual toLowerCase : ()Ljava/lang/String;
    //   5870: invokevirtual append : (Ljava/lang/String;)Ljava/lang/StringBuilder;
    //   5873: pop
    //   5874: aload #6
    //   5876: sipush #-25591
    //   5879: sipush #-30319
    //   5882: invokestatic a : (II)Ljava/lang/String;
    //   5885: ldc ''
    //   5887: invokestatic getProperty : (Ljava/lang/String;Ljava/lang/String;)Ljava/lang/String;
    //   5890: invokevirtual toLowerCase : ()Ljava/lang/String;
    //   5893: invokevirtual append : (Ljava/lang/String;)Ljava/lang/StringBuilder;
    //   5896: pop
    //   5897: aload #6
    //   5899: invokevirtual toString : ()Ljava/lang/String;
    //   5902: invokevirtual getBytes : ()[B
    //   5905: astore #5
    //   5907: aload #5
    //   5909: astore #4
    //   5911: aload #4
    //   5913: arraylength
    //   5914: bipush #8
    //   5916: iadd
    //   5917: bipush #6
    //   5919: ishr
    //   5920: iconst_1
    //   5921: iadd
    //   5922: bipush #16
    //   5924: imul
    //   5925: newarray int
    //   5927: astore #6
    //   5929: iconst_0
    //   5930: istore #7
    //   5932: iload #7
    //   5934: aload #4
    //   5936: arraylength
    //   5937: if_icmpge -> 5981
    //   5940: aload #4
    //   5942: iload #7
    //   5944: baload
    //   5945: sipush #255
    //   5948: iand
    //   5949: istore #8
    //   5951: aload #6
    //   5953: iload #7
    //   5955: iconst_2
    //   5956: ishr
    //   5957: dup2
    //   5958: iaload
    //   5959: iload #8
    //   5961: bipush #24
    //   5963: iload #7
    //   5965: iconst_4
    //   5966: irem
    //   5967: bipush #8
    //   5969: imul
    //   5970: isub
    //   5971: ishl
    //   5972: ior
    //   5973: iastore
    //   5974: iinc #7, 1
    //   5977: iload_2
    //   5978: ifeq -> 5932
    //   5981: aload #6
    //   5983: iload #7
    //   5985: iconst_2
    //   5986: ishr
    //   5987: dup2
    //   5988: iaload
    //   5989: sipush #128
    //   5992: bipush #24
    //   5994: iload #7
    //   5996: iconst_4
    //   5997: irem
    //   5998: bipush #8
    //   6000: imul
    //   6001: isub
    //   6002: ishl
    //   6003: ior
    //   6004: iastore
    //   6005: aload #6
    //   6007: aload #6
    //   6009: arraylength
    //   6010: iconst_1
    //   6011: isub
    //   6012: aload #4
    //   6014: arraylength
    //   6015: bipush #8
    //   6017: imul
    //   6018: iastore
    //   6019: bipush #80
    //   6021: newarray int
    //   6023: astore #8
    //   6025: ldc 1732584193
    //   6027: istore #9
    //   6029: ldc -271733879
    //   6031: istore #10
    //   6033: ldc -1732584194
    //   6035: istore #11
    //   6037: ldc 271733878
    //   6039: istore #12
    //   6041: ldc -1009589776
    //   6043: istore #13
    //   6045: iconst_0
    //   6046: istore #7
    //   6048: iload #7
    //   6050: aload #6
    //   6052: arraylength
    //   6053: if_icmpge -> 6375
    //   6056: iload #9
    //   6058: istore #14
    //   6060: iload #10
    //   6062: istore #15
    //   6064: iload #11
    //   6066: istore #16
    //   6068: iload #12
    //   6070: istore #17
    //   6072: iload #13
    //   6074: istore #18
    //   6076: iconst_0
    //   6077: istore #19
    //   6079: iload #19
    //   6081: bipush #80
    //   6083: if_icmpge -> 6333
    //   6086: iload #19
    //   6088: bipush #16
    //   6090: if_icmpge -> 6117
    //   6093: aload #8
    //   6095: iload #19
    //   6097: aload #6
    //   6099: iload #7
    //   6101: iload #19
    //   6103: iadd
    //   6104: iaload
    //   6105: iastore
    //   6106: iload_2
    //   6107: ifeq -> 6172
    //   6110: goto -> 6117
    //   6113: invokestatic a : (Ljava/lang/Throwable;)Ljava/lang/Throwable;
    //   6116: athrow
    //   6117: aload #8
    //   6119: iload #19
    //   6121: iconst_3
    //   6122: isub
    //   6123: iaload
    //   6124: aload #8
    //   6126: iload #19
    //   6128: bipush #8
    //   6130: isub
    //   6131: iaload
    //   6132: ixor
    //   6133: aload #8
    //   6135: iload #19
    //   6137: bipush #14
    //   6139: isub
    //   6140: iaload
    //   6141: ixor
    //   6142: aload #8
    //   6144: iload #19
    //   6146: bipush #16
    //   6148: isub
    //   6149: iaload
    //   6150: ixor
    //   6151: istore #20
    //   6153: iload #20
    //   6155: iconst_1
    //   6156: ishl
    //   6157: iload #20
    //   6159: bipush #31
    //   6161: iushr
    //   6162: ior
    //   6163: istore #21
    //   6165: aload #8
    //   6167: iload #19
    //   6169: iload #21
    //   6171: iastore
    //   6172: iload #9
    //   6174: iconst_5
    //   6175: ishl
    //   6176: iload #9
    //   6178: bipush #27
    //   6180: iushr
    //   6181: ior
    //   6182: istore #20
    //   6184: iload #20
    //   6186: iload #13
    //   6188: iadd
    //   6189: aload #8
    //   6191: iload #19
    //   6193: iaload
    //   6194: iadd
    //   6195: iload #19
    //   6197: bipush #20
    //   6199: if_icmpge -> 6225
    //   6202: ldc 1518500249
    //   6204: iload #10
    //   6206: iload #11
    //   6208: iand
    //   6209: iload #10
    //   6211: iconst_m1
    //   6212: ixor
    //   6213: iload #12
    //   6215: iand
    //   6216: ior
    //   6217: iadd
    //   6218: goto -> 6295
    //   6221: invokestatic a : (Ljava/lang/Throwable;)Ljava/lang/Throwable;
    //   6224: athrow
    //   6225: iload #19
    //   6227: bipush #40
    //   6229: if_icmpge -> 6250
    //   6232: ldc 1859775393
    //   6234: iload #10
    //   6236: iload #11
    //   6238: ixor
    //   6239: iload #12
    //   6241: ixor
    //   6242: iadd
    //   6243: goto -> 6295
    //   6246: invokestatic a : (Ljava/lang/Throwable;)Ljava/lang/Throwable;
    //   6249: athrow
    //   6250: iload #19
    //   6252: bipush #60
    //   6254: if_icmpge -> 6284
    //   6257: ldc -1894007588
    //   6259: iload #10
    //   6261: iload #11
    //   6263: iand
    //   6264: iload #10
    //   6266: iload #12
    //   6268: iand
    //   6269: ior
    //   6270: iload #11
    //   6272: iload #12
    //   6274: iand
    //   6275: ior
    //   6276: iadd
    //   6277: goto -> 6295
    //   6280: invokestatic a : (Ljava/lang/Throwable;)Ljava/lang/Throwable;
    //   6283: athrow
    //   6284: ldc -899497514
    //   6286: iload #10
    //   6288: iload #11
    //   6290: ixor
    //   6291: iload #12
    //   6293: ixor
    //   6294: iadd
    //   6295: iadd
    //   6296: istore #21
    //   6298: iload #12
    //   6300: istore #13
    //   6302: iload #11
    //   6304: istore #12
    //   6306: iload #10
    //   6308: bipush #30
    //   6310: ishl
    //   6311: iload #10
    //   6313: iconst_2
    //   6314: iushr
    //   6315: ior
    //   6316: istore #11
    //   6318: iload #9
    //   6320: istore #10
    //   6322: iload #21
    //   6324: istore #9
    //   6326: iinc #19, 1
    //   6329: iload_2
    //   6330: ifeq -> 6079
    //   6333: iload #9
    //   6335: iload #14
    //   6337: iadd
    //   6338: istore #9
    //   6340: iload #10
    //   6342: iload #15
    //   6344: iadd
    //   6345: istore #10
    //   6347: iload #11
    //   6349: iload #16
    //   6351: iadd
    //   6352: istore #11
    //   6354: iload #12
    //   6356: iload #17
    //   6358: iadd
    //   6359: istore #12
    //   6361: iload #13
    //   6363: iload #18
    //   6365: iadd
    //   6366: istore #13
    //   6368: iinc #7, 16
    //   6371: iload_2
    //   6372: ifeq -> 6048
    //   6375: iconst_5
    //   6376: newarray int
    //   6378: dup
    //   6379: iconst_0
    //   6380: iload #9
    //   6382: iastore
    //   6383: dup
    //   6384: iconst_1
    //   6385: iload #10
    //   6387: iastore
    //   6388: dup
    //   6389: iconst_2
    //   6390: iload #11
    //   6392: iastore
    //   6393: dup
    //   6394: iconst_3
    //   6395: iload #12
    //   6397: iastore
    //   6398: dup
    //   6399: iconst_4
    //   6400: iload #13
    //   6402: iastore
    //   6403: astore #14
    //   6405: bipush #20
    //   6407: newarray byte
    //   6409: astore #15
    //   6411: iconst_0
    //   6412: istore #16
    //   6414: iload #16
    //   6416: bipush #20
    //   6418: if_icmpge -> 6459
    //   6421: aload #14
    //   6423: iload #16
    //   6425: iconst_4
    //   6426: idiv
    //   6427: iaload
    //   6428: istore #17
    //   6430: iconst_3
    //   6431: iload #16
    //   6433: iconst_4
    //   6434: irem
    //   6435: isub
    //   6436: bipush #8
    //   6438: imul
    //   6439: istore #18
    //   6441: aload #15
    //   6443: iload #16
    //   6445: iload #17
    //   6447: iload #18
    //   6449: iushr
    //   6450: i2b
    //   6451: bastore
    //   6452: iinc #16, 1
    //   6455: iload_2
    //   6456: ifeq -> 6414
    //   6459: aload #15
    //   6461: astore #5
    //   6463: sipush #-25590
    //   6466: iconst_0
    //   6467: istore #4
    //   6469: sipush #6939
    //   6472: invokestatic a : (II)Ljava/lang/String;
    //   6475: iconst_1
    //   6476: ldc burp/Zrvb
    //   6478: invokevirtual getClassLoader : ()Ljava/lang/ClassLoader;
    //   6481: invokestatic forName : (Ljava/lang/String;ZLjava/lang/ClassLoader;)Ljava/lang/Class;
    //   6484: invokevirtual getDeclaredFields : ()[Ljava/lang/reflect/Field;
    //   6487: astore #5
    //   6489: aload #5
    //   6491: arraylength
    //   6492: istore #6
    //   6494: iconst_0
    //   6495: istore #7
    //   6497: iload #7
    //   6499: iload #6
    //   6501: if_icmpge -> 6639
    //   6504: aload #5
    //   6506: iload #7
    //   6508: aaload
    //   6509: astore #8
    //   6511: aload #8
    //   6513: invokevirtual getModifiers : ()I
    //   6516: invokestatic isStatic : (I)Z
    //   6519: ifne -> 6529
    //   6522: goto -> 6632
    //   6525: invokestatic a : (Ljava/lang/Throwable;)Ljava/lang/Throwable;
    //   6528: athrow
    //   6529: aload #8
    //   6531: invokevirtual getType : ()Ljava/lang/Class;
    //   6534: astore #9
    //   6536: aload #9
    //   6538: ifnull -> 6619
    //   6541: aload #9
    //   6543: invokevirtual isPrimitive : ()Z
    //   6546: ifne -> 6619
    //   6549: goto -> 6556
    //   6552: invokestatic a : (Ljava/lang/Throwable;)Ljava/lang/Throwable;
    //   6555: athrow
    //   6556: aload #9
    //   6558: invokevirtual getPackage : ()Ljava/lang/Package;
    //   6561: ifnull -> 6619
    //   6564: goto -> 6571
    //   6567: invokestatic a : (Ljava/lang/Throwable;)Ljava/lang/Throwable;
    //   6570: athrow
    //   6571: aload #9
    //   6573: invokevirtual getPackage : ()Ljava/lang/Package;
    //   6576: invokevirtual getName : ()Ljava/lang/String;
    //   6579: ifnull -> 6619
    //   6582: goto -> 6589
    //   6585: invokestatic a : (Ljava/lang/Throwable;)Ljava/lang/Throwable;
    //   6588: athrow
    //   6589: aload #9
    //   6591: invokevirtual getPackage : ()Ljava/lang/Package;
    //   6594: invokevirtual getName : ()Ljava/lang/String;
    //   6597: sipush #-25586
    //   6600: sipush #9031
    //   6603: invokestatic a : (II)Ljava/lang/String;
    //   6606: invokevirtual startsWith : (Ljava/lang/String;)Z
    //   6609: ifne -> 6619
    //   6612: goto -> 6619
    //   6615: invokestatic a : (Ljava/lang/Throwable;)Ljava/lang/Throwable;
    //   6618: athrow
    //   6619: aload #8
    //   6621: iconst_1
    //   6622: invokevirtual setAccessible : (Z)V
    //   6625: aload #8
    //   6627: aconst_null
    //   6628: invokevirtual get : (Ljava/lang/Object;)Ljava/lang/Object;
    //   6631: pop
    //   6632: iinc #7, 1
    //   6635: iload_2
    //   6636: ifeq -> 6497
    //   6639: sipush #-25596
    //   6642: sipush #-8816
    //   6645: invokestatic a : (II)Ljava/lang/String;
    //   6648: invokestatic forName : (Ljava/lang/String;)Ljava/lang/Class;
    //   6651: invokevirtual getDeclaredMethods : ()[Ljava/lang/reflect/Method;
    //   6654: astore #5
    //   6656: aload #5
    //   6658: arraylength
    //   6659: istore #6
    //   6661: iconst_0
    //   6662: istore #7
    //   6664: iload #7
    //   6666: iload #6
    //   6668: if_icmpge -> 6805
    //   6671: aload #5
    //   6673: iload #7
    //   6675: aaload
    //   6676: astore #8
    //   6678: aload #8
    //   6680: invokevirtual getParameterTypes : ()[Ljava/lang/Class;
    //   6683: pop
    //   6684: aload #8
    //   6686: invokevirtual getModifiers : ()I
    //   6689: invokestatic isStatic : (I)Z
    //   6692: ifeq -> 6791
    //   6695: aload #8
    //   6697: invokevirtual getParameterTypes : ()[Ljava/lang/Class;
    //   6700: arraylength
    //   6701: iconst_2
    //   6702: if_icmpne -> 6791
    //   6705: goto -> 6712
    //   6708: invokestatic a : (Ljava/lang/Throwable;)Ljava/lang/Throwable;
    //   6711: athrow
    //   6712: aload #8
    //   6714: invokevirtual getReturnType : ()Ljava/lang/Class;
    //   6717: getstatic java/lang/Boolean.TYPE : Ljava/lang/Class;
    //   6720: if_acmpne -> 6791
    //   6723: goto -> 6730
    //   6726: invokestatic a : (Ljava/lang/Throwable;)Ljava/lang/Throwable;
    //   6729: athrow
    //   6730: aload #8
    //   6732: iconst_1
    //   6733: invokevirtual setAccessible : (Z)V
    //   6736: aload #8
    //   6738: aconst_null
    //   6739: iconst_2
    //   6740: anewarray java/lang/Object
    //   6743: dup
    //   6744: iconst_0
    //   6745: aload_0
    //   6746: aastore
    //   6747: dup
    //   6748: iconst_1
    //   6749: aload_1
    //   6750: ifnonnull -> 6768
    //   6753: goto -> 6760
    //   6756: invokestatic a : (Ljava/lang/Throwable;)Ljava/lang/Throwable;
    //   6759: athrow
    //   6760: aload_1
    //   6761: goto -> 6775
    //   6764: invokestatic a : (Ljava/lang/Throwable;)Ljava/lang/Throwable;
    //   6767: athrow
    //   6768: aload_1
    //   6769: checkcast [B
    //   6772: invokevirtual clone : ()Ljava/lang/Object;
    //   6775: aastore
    //   6776: invokevirtual invoke : (Ljava/lang/Object;[Ljava/lang/Object;)Ljava/lang/Object;
    //   6779: checkcast java/lang/Boolean
    //   6782: invokevirtual booleanValue : ()Z
    //   6785: istore #4
    //   6787: iload_2
    //   6788: ifeq -> 6805
    //   6791: iinc #7, 1
    //   6794: iload_2
    //   6795: ifeq -> 6664
    //   6798: goto -> 6805
    //   6801: invokestatic a : (Ljava/lang/Throwable;)Ljava/lang/Throwable;
    //   6804: athrow
    //   6805: iload #4
    //   6807: ireturn
    //   6808: astore_3
    //   6809: new java/lang/Exception
    //   6812: dup
    //   6813: aload_3
    //   6814: invokevirtual getMessage : ()Ljava/lang/String;
    //   6817: invokespecial <init> : (Ljava/lang/String;)V
    //   6820: athrow
    // Exception table:
    //   from	to	target	type
    //   4	6807	6808	java/lang/Throwable
    //   22	198	201	java/lang/Throwable
    //   168	235	238	java/lang/Throwable
    //   205	272	275	java/lang/Throwable
    //   242	309	312	java/lang/Throwable
    //   279	346	349	java/lang/Throwable
    //   316	383	386	java/lang/Throwable
    //   353	420	423	java/lang/Throwable
    //   390	457	460	java/lang/Throwable
    //   427	494	497	java/lang/Throwable
    //   464	531	534	java/lang/Throwable
    //   501	568	571	java/lang/Throwable
    //   538	605	608	java/lang/Throwable
    //   575	642	645	java/lang/Throwable
    //   612	679	682	java/lang/Throwable
    //   649	716	719	java/lang/Throwable
    //   686	753	756	java/lang/Throwable
    //   723	790	793	java/lang/Throwable
    //   760	827	830	java/lang/Throwable
    //   797	864	867	java/lang/Throwable
    //   834	901	904	java/lang/Throwable
    //   871	938	941	java/lang/Throwable
    //   908	975	978	java/lang/Throwable
    //   945	1012	1015	java/lang/Throwable
    //   982	1049	1052	java/lang/Throwable
    //   1019	1086	1089	java/lang/Throwable
    //   1056	1123	1126	java/lang/Throwable
    //   1093	1160	1163	java/lang/Throwable
    //   1130	1197	1200	java/lang/Throwable
    //   1167	1234	1237	java/lang/Throwable
    //   1204	1271	1274	java/lang/Throwable
    //   1241	1308	1311	java/lang/Throwable
    //   1278	1341	1344	java/lang/Throwable
    //   2165	2199	2202	java/lang/Throwable
    //   2295	2373	2376	java/lang/Throwable
    //   2302	2516	2519	java/lang/Throwable
    //   2894	2909	2909	java/lang/Throwable
    //   2936	2970	2973	java/lang/Throwable
    //   2980	2992	2995	java/lang/Throwable
    //   3078	3156	3159	java/lang/Throwable
    //   3085	3299	3302	java/lang/Throwable
    //   3699	3777	3780	java/lang/Throwable
    //   3706	3920	3923	java/lang/Throwable
    //   4367	4401	4404	java/lang/Throwable
    //   4408	4420	4423	java/lang/Throwable
    //   4506	4584	4587	java/lang/Throwable
    //   4513	4727	4730	java/lang/Throwable
    //   5484	5498	5498	java/lang/Throwable
    //   5509	5522	5525	java/lang/Throwable
    //   5514	5537	5540	java/lang/Throwable
    //   5529	5555	5558	java/lang/Throwable
    //   5544	5585	5588	java/lang/Throwable
    //   5651	5678	5681	java/lang/Throwable
    //   5668	5699	5702	java/lang/Throwable
    //   5685	5729	5732	java/lang/Throwable
    //   5706	5740	5740	java/lang/Throwable
    //   5751	5767	5770	java/lang/Throwable
    //   6086	6110	6113	java/lang/Throwable
    //   6184	6221	6221	java/lang/Throwable
    //   6225	6246	6246	java/lang/Throwable
    //   6250	6280	6280	java/lang/Throwable
    //   6511	6525	6525	java/lang/Throwable
    //   6536	6549	6552	java/lang/Throwable
    //   6541	6564	6567	java/lang/Throwable
    //   6556	6582	6585	java/lang/Throwable
    //   6571	6612	6615	java/lang/Throwable
    //   6678	6705	6708	java/lang/Throwable
    //   6695	6723	6726	java/lang/Throwable
    //   6712	6753	6756	java/lang/Throwable
    //   6730	6764	6764	java/lang/Throwable
    //   6787	6798	6801	java/lang/Throwable
  }
  
  static void ZL(Object[] paramArrayOfObject, Object paramObject) throws Throwable {}
  
  static void Zt(Object paramObject) {
    Zs26.ZV = a(-25594, -5661);
    Zs26.Z_ = new BigInteger(a(-25589, -26090));
    boolean bool = Zt2e.ZK();
    try {
      try {
        if (Zmgl.Zh.charAt(Math.abs(((BigInteger)Zlot.ZJ).intValue() % 32)) <= Zbj.ZD.charAt(Math.abs(((BigInteger)Zkgp.Zw).intValue() % 32))) {
          try {
            Zmf6.ZJ(Class.forName(a(-25598, -30624)));
            if (bool)
              Zsow.Zm(Class.forName(a(-25588, -9185))); 
          } catch (Throwable throwable) {
            throw a(null);
          } 
          return;
        } 
      } catch (Throwable throwable) {
        throw a(null);
      } 
      Zsow.Zm(Class.forName(a(-25588, -9185)));
    } catch (Throwable throwable) {}
  }
  
  static {
    // Byte code:
    //   0: bipush #15
    //   2: anewarray java/lang/String
    //   5: astore #5
    //   7: iconst_0
    //   8: istore_3
    //   9: ldc '\\rP\\tBAeO\\t#';fuMG99\\t3~A9ocT`8\\nWWM]+4/<+jR\\t"h=MV_ U|+r$q,0I6uN/MKC2y381@8.8<d;"pTC\\tGt\\rQN!; .1 K\\fT{vSx\\n\\tA~I?^\\tjcC:Mx8F\\t~Q'
    //   11: dup
    //   12: astore_2
    //   13: invokevirtual length : ()I
    //   16: istore #4
    //   18: iconst_4
    //   19: istore_1
    //   20: iconst_m1
    //   21: istore_0
    //   22: bipush #8
    //   24: iinc #0, 1
    //   27: aload_2
    //   28: iload_0
    //   29: dup
    //   30: iload_1
    //   31: iadd
    //   32: invokevirtual substring : (II)Ljava/lang/String;
    //   35: iconst_m1
    //   36: goto -> 142
    //   39: aload #5
    //   41: swap
    //   42: iload_3
    //   43: iinc #3, 1
    //   46: swap
    //   47: aastore
    //   48: iload_0
    //   49: iload_1
    //   50: iadd
    //   51: dup
    //   52: istore_0
    //   53: iload #4
    //   55: if_icmpge -> 67
    //   58: aload_2
    //   59: iload_0
    //   60: invokevirtual charAt : (I)C
    //   63: istore_1
    //   64: goto -> 22
    //   67: ldc 'KF[fEW\\\nm6i|3$ G#T`mF8Uo[@q2<Q'
    //   69: dup
    //   70: astore_2
    //   71: invokevirtual length : ()I
    //   74: istore #4
    //   76: bipush #32
    //   78: istore_1
    //   79: iconst_m1
    //   80: istore_0
    //   81: bipush #99
    //   83: iinc #0, 1
    //   86: aload_2
    //   87: iload_0
    //   88: dup
    //   89: iload_1
    //   90: iadd
    //   91: invokevirtual substring : (II)Ljava/lang/String;
    //   94: iconst_0
    //   95: goto -> 142
    //   98: aload #5
    //   100: swap
    //   101: iload_3
    //   102: iinc #3, 1
    //   105: swap
    //   106: aastore
    //   107: iload_0
    //   108: iload_1
    //   109: iadd
    //   110: dup
    //   111: istore_0
    //   112: iload #4
    //   114: if_icmpge -> 126
    //   117: aload_2
    //   118: iload_0
    //   119: invokevirtual charAt : (I)C
    //   122: istore_1
    //   123: goto -> 81
    //   126: aload #5
    //   128: putstatic burp/Zkqx.a : [Ljava/lang/String;
    //   131: bipush #15
    //   133: anewarray java/lang/String
    //   136: putstatic burp/Zkqx.b : [Ljava/lang/String;
    //   139: goto -> 300
    //   142: dup_x2
    //   143: pop
    //   144: invokevirtual toCharArray : ()[C
    //   147: dup_x1
    //   148: arraylength
    //   149: dup_x2
    //   150: pop
    //   151: iconst_0
    //   152: istore #6
    //   154: dup2_x1
    //   155: pop2
    //   156: dup_x2
    //   157: iconst_1
    //   158: if_icmpgt -> 259
    //   161: dup2
    //   162: swap
    //   163: iload #6
    //   165: dup2_x1
    //   166: caload
    //   167: swap
    //   168: iload #6
    //   170: bipush #7
    //   172: irem
    //   173: tableswitch default -> 241, 0 -> 212, 1 -> 217, 2 -> 222, 3 -> 226, 4 -> 231, 5 -> 236
    //   212: bipush #107
    //   214: goto -> 243
    //   217: bipush #89
    //   219: goto -> 243
    //   222: iconst_4
    //   223: goto -> 243
    //   226: bipush #21
    //   228: goto -> 243
    //   231: bipush #67
    //   233: goto -> 243
    //   236: bipush #80
    //   238: goto -> 243
    //   241: bipush #8
    //   243: ixor
    //   244: ixor
    //   245: i2c
    //   246: castore
    //   247: iinc #6, 1
    //   250: dup
    //   251: ifne -> 259
    //   254: dup2
    //   255: dup_x1
    //   256: goto -> 165
    //   259: dup2_x1
    //   260: pop2
    //   261: dup_x2
    //   262: iload #6
    //   264: if_icmpgt -> 161
    //   267: pop
    //   268: new java/lang/String
    //   271: dup_x1
    //   272: swap
    //   273: invokespecial <init> : ([C)V
    //   276: invokevirtual intern : ()Ljava/lang/String;
    //   279: swap
    //   280: pop
    //   281: swap
    //   282: tableswitch default -> 39, 0 -> 98
    //   300: sipush #-25595
    //   303: sipush #20197
    //   306: invokestatic a : (II)Ljava/lang/String;
    //   309: putstatic burp/Zkqx.Ze : Ljava/lang/String;
    //   312: new java/math/BigInteger
    //   315: dup
    //   316: sipush #-25587
    //   319: sipush #-23961
    //   322: invokestatic a : (II)Ljava/lang/String;
    //   325: invokespecial <init> : (Ljava/lang/String;)V
    //   328: putstatic burp/Zkqx.ZW : Ljava/lang/Object;
    //   331: return
  }
  
  private static Throwable a(Throwable paramThrowable) {
    return paramThrowable;
  }
  
  private static String a(int paramInt1, int paramInt2) {
    int i = (paramInt1 ^ 0xFFFF9C08) & 0xFFFF;
    if (b[i] == null) {
      char[] arrayOfChar = a[i].toCharArray();
      switch (arrayOfChar[0] & 0xFF) {
        case 0:
        
        case 1:
        
        case 2:
        
        case 3:
        
        case 4:
        
        case 5:
        
        case 6:
        
        case 7:
        
        case 8:
        
        case 9:
        
        case 10:
        
        case 11:
        
        case 12:
        
        case 13:
        
        case 14:
        
        case 15:
        
        case 16:
        
        case 17:
        
        case 18:
        
        case 19:
        
        case 20:
        
        case 21:
        
        case 22:
        
        case 23:
        
        case 24:
        
        case 25:
        
        case 26:
        
        case 27:
        
        case 28:
        
        case 29:
        
        case 30:
        
        case 31:
        
        case 32:
        
        case 33:
        
        case 34:
        
        case 35:
        
        case 36:
        
        case 37:
        
        case 38:
        
        case 39:
        
        case 40:
        
        case 41:
        
        case 42:
        
        case 43:
        
        case 44:
        
        case 45:
        
        case 46:
        
        case 47:
        
        case 48:
        
        case 49:
        
        case 50:
        
        case 51:
        
        case 52:
        
        case 53:
        
        case 54:
        
        case 55:
        
        case 56:
        
        case 57:
        
        case 58:
        
        case 59:
        
        case 60:
        
        case 61:
        
        case 62:
        
        case 63:
        
        case 64:
        
        case 65:
        
        case 66:
        
        case 67:
        
        case 68:
        
        case 69:
        
        case 70:
        
        case 71:
        
        case 72:
        
        case 73:
        
        case 74:
        
        case 75:
        
        case 76:
        
        case 77:
        
        case 78:
        
        case 79:
        
        case 80:
        
        case 81:
        
        case 82:
        
        case 83:
        
        case 84:
        
        case 85:
        
        case 86:
        
        case 87:
        
        case 88:
        
        case 89:
        
        case 90:
        
        case 91:
        
        case 92:
        
        case 93:
        
        case 94:
        
        case 95:
        
        case 96:
        
        case 97:
        
        case 98:
        
        case 99:
        
        case 100:
        
        case 101:
        
        case 102:
        
        case 103:
        
        case 104:
        
        case 105:
        
        case 106:
        
        case 107:
        
        case 108:
        
        case 109:
        
        case 110:
        
        case 111:
        
        case 112:
        
        case 113:
        
        case 114:
        
        case 115:
        
        case 116:
        
        case 117:
        
        case 118:
        
        case 119:
        
        case 120:
        
        case 121:
        
        case 122:
        
        case 123:
        
        case 124:
        
        case 125:
        
        case 126:
        
        case 127:
        
        case 128:
        
        case 129:
        
        case 130:
        
        case 131:
        
        case 132:
        
        case 133:
        
        case 134:
        
        case 135:
        
        case 136:
        
        case 137:
        
        case 138:
        
        case 139:
        
        case 140:
        
        case 141:
        
        case 142:
        
        case 143:
        
        case 144:
        
        case 145:
        
        case 146:
        
        case 147:
        
        case 148:
        
        case 149:
        
        case 150:
        
        case 151:
        
        case 152:
        
        case 153:
        
        case 154:
        
        case 155:
        
        case 156:
        
        case 157:
        
        case 158:
        
        case 159:
        
        case 160:
        
        case 161:
        
        case 162:
        
        case 163:
        
        case 164:
        
        case 165:
        
        case 166:
        
        case 167:
        
        case 168:
        
        case 169:
        
        case 170:
        
        case 171:
        
        case 172:
        
        case 173:
        
        case 174:
        
        case 175:
        
        case 176:
        
        case 177:
        
        case 178:
        
        case 179:
        
        case 180:
        
        case 181:
        
        case 182:
        
        case 183:
        
        case 184:
        
        case 185:
        
        case 186:
        
        case 187:
        
        case 188:
        
        case 189:
        
        case 190:
        
        case 191:
        
        case 192:
        
        case 193:
        
        case 194:
        
        case 195:
        
        case 196:
        
        case 197:
        
        case 198:
        
        case 199:
        
        case 200:
        
        case 201:
        
        case 202:
        
        case 203:
        
        case 204:
        
        case 205:
        
        case 206:
        
        case 207:
        
        case 208:
        
        case 209:
        
        case 210:
        
        case 211:
        
        case 212:
        
        case 213:
        
        case 214:
        
        case 215:
        
        case 216:
        
        case 217:
        
        case 218:
        
        case 219:
        
        case 220:
        
        case 221:
        
        case 222:
        
        case 223:
        
        case 224:
        
        case 225:
        
        case 226:
        
        case 227:
        
        case 228:
        
        case 229:
        
        case 230:
        
        case 231:
        
        case 232:
        
        case 233:
        
        case 234:
        
        case 235:
        
        case 236:
        
        case 237:
        
        case 238:
        
        case 239:
        
        case 240:
        
        case 241:
        
        case 242:
        
        case 243:
        
        case 244:
        
        case 245:
        
        case 246:
        
        case 247:
        
        case 248:
        
        case 249:
        
        case 250:
        
        case 251:
        
        case 252:
        
        case 253:
        
        case 254:
        
        default:
          break;
      } 
      char c = '';
      int j = (paramInt2 & 0xFF) - c;
      if (j < 0)
        j += 256; 
      int k = ((paramInt2 & 0xFFFF) >>> 8) - c;
      if (k < 0)
        k += 256; 
      for (byte b = 0; b < arrayOfChar.length; b++) {
        int m = b % 2;
        if (m == 0) {
          arrayOfChar[b] = (char)(arrayOfChar[b] ^ j);
          j = ((j >>> 3 | j << 5) ^ arrayOfChar[b]) & 0xFF;
        } else {
          arrayOfChar[b] = (char)(arrayOfChar[b] ^ k);
          k = ((k >>> 3 | k << 5) ^ arrayOfChar[b]) & 0xFF;
        } 
      } 
      b[i] = (new String(arrayOfChar)).intern();
    } 
    return b[i];
  }
}


/* Location:              C:\Program Files\BurpSuitePro\burpsuite_pro.jar!\burp\Zkqx.class
 * Java compiler version: 21 (65.0)
 * JD-Core Version:       1.1.3
 */