package burp;

public class Zkr5 {
  private static Zbqc[] ZL;
  
  private static final String[] a;
  
  private static final String[] b;
  
  static void Zy(Zx6t paramZx6t, Zl7h paramZl7h, Zz1i paramZz1i, Zriy paramZriy) {
    paramZx6t.ZP(a(15582, -31919), Integer.valueOf(paramZl7h.ZVI()));
    paramZx6t.ZP(a(15581, 13274), Integer.valueOf(paramZl7h.ZVp()));
    paramZx6t.ZP(a(15573, -6289), Integer.valueOf(paramZl7h.ZVJ()));
    paramZx6t.ZP(a(15574, -2956), Integer.valueOf(paramZl7h.ZVP().ZXY()));
    paramZx6t.ZQ(a(15571, 22821), Integer.valueOf(paramZl7h.ZVv().ZZo()));
    Zbqc[] arrayOfZbqc = ZP();
    ZY(paramZx6t, paramZz1i, paramZriy);
    if (Zbqc.Zwu() == null)
      ZQ(new Zbqc[2]); 
  }
  
  public static void ZY(Zx6t paramZx6t, Zz1i paramZz1i, Zriy paramZriy) {
    // Byte code:
    //   0: aload_1
    //   1: invokeinterface ZHU : ()Lburp/Zefg;
    //   6: invokeinterface size : ()I
    //   11: istore_3
    //   12: aload_0
    //   13: sipush #15569
    //   16: sipush #-5439
    //   19: invokestatic a : (II)Ljava/lang/String;
    //   22: aload_1
    //   23: invokeinterface ZHW : ()I
    //   28: invokestatic valueOf : (I)Ljava/lang/Integer;
    //   31: invokevirtual ZP : (Ljava/lang/String;Ljava/lang/Number;)V
    //   34: aload_0
    //   35: sipush #15576
    //   38: sipush #24804
    //   41: invokestatic a : (II)Ljava/lang/String;
    //   44: aload_1
    //   45: invokeinterface ZHg : ()I
    //   50: invokestatic valueOf : (I)Ljava/lang/Integer;
    //   53: invokevirtual ZP : (Ljava/lang/String;Ljava/lang/Number;)V
    //   56: aload_0
    //   57: sipush #15572
    //   60: sipush #18987
    //   63: invokestatic a : (II)Ljava/lang/String;
    //   66: iload_3
    //   67: invokestatic valueOf : (I)Ljava/lang/Integer;
    //   70: invokevirtual ZP : (Ljava/lang/String;Ljava/lang/Number;)V
    //   73: aload_0
    //   74: sipush #15570
    //   77: sipush #27377
    //   80: invokestatic a : (II)Ljava/lang/String;
    //   83: aload_1
    //   84: invokeinterface ZHo : ()J
    //   89: invokestatic valueOf : (J)Ljava/lang/Long;
    //   92: invokevirtual ZP : (Ljava/lang/String;Ljava/lang/Number;)V
    //   95: iload_3
    //   96: ifle -> 113
    //   99: aload_2
    //   100: invokevirtual Zj : ()Lburp/Zt5o;
    //   103: aload_0
    //   104: iload_3
    //   105: <illegal opcode> accept : (Lburp/Zx6t;I)Ljava/util/function/Consumer;
    //   110: invokevirtual Zk : (Ljava/util/function/Consumer;)V
    //   113: return
  }
  
  private static void lambda$addAuditMetricsTo$0(Zx6t paramZx6t, int paramInt, Zl3i paramZl3i) {
    paramZx6t.ZQ(a(15580, 27740) + a(15580, 27740) + String.valueOf(paramZl3i.Zc), Integer.valueOf(Math.max(paramZl3i.Zk, 0)));
    paramZx6t.ZQ(a(15568, 22786) + a(15568, 22786) + String.valueOf(paramZl3i.Zc), Integer.valueOf(paramInt - Math.max(paramZl3i.Zy, 0)));
  }
  
  public static void ZQ(Zbqc[] paramArrayOfZbqc) {
    ZL = paramArrayOfZbqc;
  }
  
  public static Zbqc[] ZP() {
    return ZL;
  }
  
  static {
    // Byte code:
    //   0: bipush #13
    //   2: anewarray java/lang/String
    //   5: astore #5
    //   7: iconst_0
    //   8: istore_3
    //   9: ldc 'LÂ²T\\fÃ‘\\\tWÃ—Â  Ã‹Ã—Ã—BÃ¥Â•Ã¦Ã©\\tÃ»Ã½Ã¿B$Â€Â„Ãº@ÃŸÃ•Â¡Ã¡Ã«\\bÃ¦Ã\FQ\\fÂ‹Â›,Ã…Ã¤Â¢BÃ±%Â¿Ã©MÃ•&Â´mÂ“Ã”Âœ[Ã¯Â¶Â§Â)Â‚Ã¹uÂŽÂ˜ÃœÃŽÃÂ‚Ã¥c`I1\\tÃ§Ã¯CÂ´Ã…ÂŸ>Ã”ÃžNÂ“Â›Â¯@)-Â…Ã€zÃ§Â„GÂ¬5ÃÃ½&Â‹_Â­kHÂµÃ‡TÂ Ã—3Ã¢Ã“Â¬SÃ§\\rÂ¨Ã‡Â¼Ã™Â¾Â‘\\nhÃpÃ†+Ã¥EÂ›-Â®Ã¿ÂŽ Ã¥ÂŸ`sÃ±Â£Ã§=Z~Ã´9C}3pRÂ•Â–2/Âœ+,,(ÂŒÂƒÂ¶'
    //   11: dup
    //   12: astore_2
    //   13: invokevirtual length : ()I
    //   16: istore #4
    //   18: bipush #16
    //   20: istore_1
    //   21: iconst_3
    //   22: anewarray burp/Zbqc
    //   25: iconst_m1
    //   26: istore_0
    //   27: invokestatic ZQ : ([Lburp/Zbqc;)V
    //   30: bipush #90
    //   32: iinc #0, 1
    //   35: aload_2
    //   36: iload_0
    //   37: dup
    //   38: iload_1
    //   39: iadd
    //   40: invokevirtual substring : (II)Ljava/lang/String;
    //   43: iconst_m1
    //   44: goto -> 150
    //   47: aload #5
    //   49: swap
    //   50: iload_3
    //   51: iinc #3, 1
    //   54: swap
    //   55: aastore
    //   56: iload_0
    //   57: iload_1
    //   58: iadd
    //   59: dup
    //   60: istore_0
    //   61: iload #4
    //   63: if_icmpge -> 75
    //   66: aload_2
    //   67: iload_0
    //   68: invokevirtual charAt : (I)C
    //   71: istore_1
    //   72: goto -> 30
    //   75: ldc 'Â«wÃ±Ã¹ÂžWNÂ©}Â¦)HÃ±Â‚Ã»!9Ã¾bÃ§i/Ã±Â©ÂÃ©Ã¦'
    //   77: dup
    //   78: astore_2
    //   79: invokevirtual length : ()I
    //   82: istore #4
    //   84: bipush #14
    //   86: istore_1
    //   87: iconst_m1
    //   88: istore_0
    //   89: bipush #123
    //   91: iinc #0, 1
    //   94: aload_2
    //   95: iload_0
    //   96: dup
    //   97: iload_1
    //   98: iadd
    //   99: invokevirtual substring : (II)Ljava/lang/String;
    //   102: iconst_0
    //   103: goto -> 150
    //   106: aload #5
    //   108: swap
    //   109: iload_3
    //   110: iinc #3, 1
    //   113: swap
    //   114: aastore
    //   115: iload_0
    //   116: iload_1
    //   117: iadd
    //   118: dup
    //   119: istore_0
    //   120: iload #4
    //   122: if_icmpge -> 134
    //   125: aload_2
    //   126: iload_0
    //   127: invokevirtual charAt : (I)C
    //   130: istore_1
    //   131: goto -> 89
    //   134: aload #5
    //   136: putstatic burp/Zkr5.a : [Ljava/lang/String;
    //   139: bipush #13
    //   141: anewarray java/lang/String
    //   144: putstatic burp/Zkr5.b : [Ljava/lang/String;
    //   147: goto -> 308
    //   150: dup_x2
    //   151: pop
    //   152: invokevirtual toCharArray : ()[C
    //   155: dup_x1
    //   156: arraylength
    //   157: dup_x2
    //   158: pop
    //   159: iconst_0
    //   160: istore #6
    //   162: dup2_x1
    //   163: pop2
    //   164: dup_x2
    //   165: iconst_1
    //   166: if_icmpgt -> 267
    //   169: dup2
    //   170: swap
    //   171: iload #6
    //   173: dup2_x1
    //   174: caload
    //   175: swap
    //   176: iload #6
    //   178: bipush #7
    //   180: irem
    //   181: tableswitch default -> 249, 0 -> 220, 1 -> 225, 2 -> 229, 3 -> 234, 4 -> 239, 5 -> 244
    //   220: bipush #12
    //   222: goto -> 251
    //   225: iconst_3
    //   226: goto -> 251
    //   229: bipush #49
    //   231: goto -> 251
    //   234: bipush #74
    //   236: goto -> 251
    //   239: bipush #126
    //   241: goto -> 251
    //   244: bipush #71
    //   246: goto -> 251
    //   249: bipush #44
    //   251: ixor
    //   252: ixor
    //   253: i2c
    //   254: castore
    //   255: iinc #6, 1
    //   258: dup
    //   259: ifne -> 267
    //   262: dup2
    //   263: dup_x1
    //   264: goto -> 173
    //   267: dup2_x1
    //   268: pop2
    //   269: dup_x2
    //   270: iload #6
    //   272: if_icmpgt -> 169
    //   275: pop
    //   276: new java/lang/String
    //   279: dup_x1
    //   280: swap
    //   281: invokespecial <init> : ([C)V
    //   284: invokevirtual intern : ()Ljava/lang/String;
    //   287: swap
    //   288: pop
    //   289: swap
    //   290: tableswitch default -> 47, 0 -> 106
    //   308: return
  }
  
  private static String a(int paramInt1, int paramInt2) {
    int i = (paramInt1 ^ 0x3CD4) & 0xFFFF;
    if (b[i] == null) {
      char[] arrayOfChar = a[i].toCharArray();
      switch (arrayOfChar[0] & 0xFF) {
        case 0:
        
        case 1:
        
        case 2:
        
        case 3:
        
        case 4:
        
        case 5:
        
        case 6:
        
        case 7:
        
        case 8:
        
        case 9:
        
        case 10:
        
        case 11:
        
        case 12:
        
        case 13:
        
        case 14:
        
        case 15:
        
        case 16:
        
        case 17:
        
        case 18:
        
        case 19:
        
        case 20:
        
        case 21:
        
        case 22:
        
        case 23:
        
        case 24:
        
        case 25:
        
        case 26:
        
        case 27:
        
        case 28:
        
        case 29:
        
        case 30:
        
        case 31:
        
        case 32:
        
        case 33:
        
        case 34:
        
        case 35:
        
        case 36:
        
        case 37:
        
        case 38:
        
        case 39:
        
        case 40:
        
        case 41:
        
        case 42:
        
        case 43:
        
        case 44:
        
        case 45:
        
        case 46:
        
        case 47:
        
        case 48:
        
        case 49:
        
        case 50:
        
        case 51:
        
        case 52:
        
        case 53:
        
        case 54:
        
        case 55:
        
        case 56:
        
        case 57:
        
        case 58:
        
        case 59:
        
        case 60:
        
        case 61:
        
        case 62:
        
        case 63:
        
        case 64:
        
        case 65:
        
        case 66:
        
        case 67:
        
        case 68:
        
        case 69:
        
        case 70:
        
        case 71:
        
        case 72:
        
        case 73:
        
        case 74:
        
        case 75:
        
        case 76:
        
        case 77:
        
        case 78:
        
        case 79:
        
        case 80:
        
        case 81:
        
        case 82:
        
        case 83:
        
        case 84:
        
        case 85:
        
        case 86:
        
        case 87:
        
        case 88:
        
        case 89:
        
        case 90:
        
        case 91:
        
        case 92:
        
        case 93:
        
        case 94:
        
        case 95:
        
        case 96:
        
        case 97:
        
        case 98:
        
        case 99:
        
        case 100:
        
        case 101:
        
        case 102:
        
        case 103:
        
        case 104:
        
        case 105:
        
        case 106:
        
        case 107:
        
        case 108:
        
        case 109:
        
        case 110:
        
        case 111:
        
        case 112:
        
        case 113:
        
        case 114:
        
        case 115:
        
        case 116:
        
        case 117:
        
        case 118:
        
        case 119:
        
        case 120:
        
        case 121:
        
        case 122:
        
        case 123:
        
        case 124:
        
        case 125:
        
        case 126:
        
        case 127:
        
        case 128:
        
        case 129:
        
        case 130:
        
        case 131:
        
        case 132:
        
        case 133:
        
        case 134:
        
        case 135:
        
        case 136:
        
        case 137:
        
        case 138:
        
        case 139:
        
        case 140:
        
        case 141:
        
        case 142:
        
        case 143:
        
        case 144:
        
        case 145:
        
        case 146:
        
        case 147:
        
        case 148:
        
        case 149:
        
        case 150:
        
        case 151:
        
        case 152:
        
        case 153:
        
        case 154:
        
        case 155:
        
        case 156:
        
        case 157:
        
        case 158:
        
        case 159:
        
        case 160:
        
        case 161:
        
        case 162:
        
        case 163:
        
        case 164:
        
        case 165:
        
        case 166:
        
        case 167:
        
        case 168:
        
        case 169:
        
        case 170:
        
        case 171:
        
        case 172:
        
        case 173:
        
        case 174:
        
        case 175:
        
        case 176:
        
        case 177:
        
        case 178:
        
        case 179:
        
        case 180:
        
        case 181:
        
        case 182:
        
        case 183:
        
        case 184:
        
        case 185:
        
        case 186:
        
        case 187:
        
        case 188:
        
        case 189:
        
        case 190:
        
        case 191:
        
        case 192:
        
        case 193:
        
        case 194:
        
        case 195:
        
        case 196:
        
        case 197:
        
        case 198:
        
        case 199:
        
        case 200:
        
        case 201:
        
        case 202:
        
        case 203:
        
        case 204:
        
        case 205:
        
        case 206:
        
        case 207:
        
        case 208:
        
        case 209:
        
        case 210:
        
        case 211:
        
        case 212:
        
        case 213:
        
        case 214:
        
        case 215:
        
        case 216:
        
        case 217:
        
        case 218:
        
        case 219:
        
        case 220:
        
        case 221:
        
        case 222:
        
        case 223:
        
        case 224:
        
        case 225:
        
        case 226:
        
        case 227:
        
        case 228:
        
        case 229:
        
        case 230:
        
        case 231:
        
        case 232:
        
        case 233:
        
        case 234:
        
        case 235:
        
        case 236:
        
        case 237:
        
        case 238:
        
        case 239:
        
        case 240:
        
        case 241:
        
        case 242:
        
        case 243:
        
        case 244:
        
        case 245:
        
        case 246:
        
        case 247:
        
        case 248:
        
        case 249:
        
        case 250:
        
        case 251:
        
        case 252:
        
        case 253:
        
        case 254:
        
        default:
          break;
      } 
      byte b1 = 31;
      int j = (paramInt2 & 0xFF) - b1;
      if (j < 0)
        j += 256; 
      int k = ((paramInt2 & 0xFFFF) >>> 8) - b1;
      if (k < 0)
        k += 256; 
      for (byte b2 = 0; b2 < arrayOfChar.length; b2++) {
        int m = b2 % 2;
        if (m == 0) {
          arrayOfChar[b2] = (char)(arrayOfChar[b2] ^ j);
          j = ((j >>> 3 | j << 5) ^ arrayOfChar[b2]) & 0xFF;
        } else {
          arrayOfChar[b2] = (char)(arrayOfChar[b2] ^ k);
          k = ((k >>> 3 | k << 5) ^ arrayOfChar[b2]) & 0xFF;
        } 
      } 
      b[i] = (new String(arrayOfChar)).intern();
    } 
    return b[i];
  }
}


/* Location:              C:\Program Files\BurpSuitePro\burpsuite_pro.jar!\burp\Zkr5.class
 * Java compiler version: 21 (65.0)
 * JD-Core Version:       1.1.3
 */