package burp;

import java.math.BigInteger;

class Zktq extends ClassLoader {
  static String Zc;
  
  static Object Zn;
  
  private static final String[] a;
  
  private static final String[] b;
  
  static boolean ZR(Object[] paramArrayOfObject, Object paramObject) throws Throwable {
    // Byte code:
    //   0: invokestatic ZK : ()Z
    //   3: istore_2
    //   4: sipush #-1065
    //   7: sipush #-18793
    //   10: invokestatic a : (II)Ljava/lang/String;
    //   13: invokestatic forName : (Ljava/lang/String;)Ljava/lang/Class;
    //   16: invokestatic Zq : (Ljava/lang/Object;)V
    //   19: getstatic burp/Zlvx.ZM : Ljava/lang/Object;
    //   22: checkcast java/math/BigInteger
    //   25: invokevirtual toByteArray : ()[B
    //   28: astore_3
    //   29: bipush #32
    //   31: newarray int
    //   33: dup
    //   34: iconst_0
    //   35: ldc 876216579
    //   37: iastore
    //   38: dup
    //   39: iconst_1
    //   40: ldc 455999525
    //   42: iastore
    //   43: dup
    //   44: iconst_2
    //   45: ldc 1043334948
    //   47: iastore
    //   48: dup
    //   49: iconst_3
    //   50: ldc 439222784
    //   52: iastore
    //   53: dup
    //   54: iconst_4
    //   55: ldc 372376604
    //   57: iastore
    //   58: dup
    //   59: iconst_5
    //   60: ldc 707731490
    //   62: iastore
    //   63: dup
    //   64: bipush #6
    //   66: ldc 389426184
    //   68: iastore
    //   69: dup
    //   70: bipush #7
    //   72: ldc 973875457
    //   74: iastore
    //   75: dup
    //   76: bipush #8
    //   78: ldc 389160971
    //   80: iastore
    //   81: dup
    //   82: bipush #9
    //   84: ldc 907870729
    //   86: iastore
    //   87: dup
    //   88: bipush #10
    //   90: ldc 121057538
    //   92: iastore
    //   93: dup
    //   94: bipush #11
    //   96: ldc 840500228
    //   98: iastore
    //   99: dup
    //   100: bipush #12
    //   102: ldc 254150144
    //   104: iastore
    //   105: dup
    //   106: bipush #13
    //   108: ldc 924386310
    //   110: iastore
    //   111: dup
    //   112: bipush #14
    //   114: ldc 187632156
    //   116: iastore
    //   117: dup
    //   118: bipush #15
    //   120: ldc 874189824
    //   122: iastore
    //   123: dup
    //   124: bipush #16
    //   126: ldc 655302664
    //   128: iastore
    //   129: dup
    //   130: bipush #17
    //   132: ldc 890966315
    //   134: iastore
    //   135: dup
    //   136: bipush #18
    //   138: ldc 722417666
    //   140: iastore
    //   141: dup
    //   142: bipush #19
    //   144: ldc 1026621720
    //   146: iastore
    //   147: dup
    //   148: bipush #20
    //   150: ldc 957157408
    //   152: iastore
    //   153: dup
    //   154: bipush #21
    //   156: ldc 892536332
    //   158: iastore
    //   159: dup
    //   160: bipush #22
    //   162: ldc 689771012
    //   164: iastore
    //   165: dup
    //   166: bipush #23
    //   168: ldc 221709344
    //   170: iastore
    //   171: dup
    //   172: bipush #24
    //   174: ldc 940377620
    //   176: iastore
    //   177: dup
    //   178: bipush #25
    //   180: ldc 255209728
    //   182: iastore
    //   183: dup
    //   184: bipush #26
    //   186: ldc 1010368540
    //   188: iastore
    //   189: dup
    //   190: bipush #27
    //   192: ldc 220604441
    //   194: iastore
    //   195: dup
    //   196: bipush #28
    //   198: ldc 1008414755
    //   200: iastore
    //   201: dup
    //   202: bipush #29
    //   204: ldc 187049985
    //   206: iastore
    //   207: dup
    //   208: bipush #30
    //   210: ldc 943331329
    //   212: iastore
    //   213: dup
    //   214: bipush #31
    //   216: ldc 170788368
    //   218: iastore
    //   219: astore #5
    //   221: bipush #64
    //   223: newarray int
    //   225: dup
    //   226: iconst_0
    //   227: ldc 16843776
    //   229: iastore
    //   230: dup
    //   231: iconst_1
    //   232: iconst_0
    //   233: iastore
    //   234: dup
    //   235: iconst_2
    //   236: ldc 65536
    //   238: iastore
    //   239: dup
    //   240: iconst_3
    //   241: ldc 16843780
    //   243: iastore
    //   244: dup
    //   245: iconst_4
    //   246: ldc 16842756
    //   248: iastore
    //   249: dup
    //   250: iconst_5
    //   251: ldc 66564
    //   253: iastore
    //   254: dup
    //   255: bipush #6
    //   257: iconst_4
    //   258: iastore
    //   259: dup
    //   260: bipush #7
    //   262: ldc 65536
    //   264: iastore
    //   265: dup
    //   266: bipush #8
    //   268: sipush #1024
    //   271: iastore
    //   272: dup
    //   273: bipush #9
    //   275: ldc 16843776
    //   277: iastore
    //   278: dup
    //   279: bipush #10
    //   281: ldc 16843780
    //   283: iastore
    //   284: dup
    //   285: bipush #11
    //   287: sipush #1024
    //   290: iastore
    //   291: dup
    //   292: bipush #12
    //   294: ldc 16778244
    //   296: iastore
    //   297: dup
    //   298: bipush #13
    //   300: ldc 16842756
    //   302: iastore
    //   303: dup
    //   304: bipush #14
    //   306: ldc 16777216
    //   308: iastore
    //   309: dup
    //   310: bipush #15
    //   312: iconst_4
    //   313: iastore
    //   314: dup
    //   315: bipush #16
    //   317: sipush #1028
    //   320: iastore
    //   321: dup
    //   322: bipush #17
    //   324: ldc 16778240
    //   326: iastore
    //   327: dup
    //   328: bipush #18
    //   330: ldc 16778240
    //   332: iastore
    //   333: dup
    //   334: bipush #19
    //   336: ldc 66560
    //   338: iastore
    //   339: dup
    //   340: bipush #20
    //   342: ldc 66560
    //   344: iastore
    //   345: dup
    //   346: bipush #21
    //   348: ldc 16842752
    //   350: iastore
    //   351: dup
    //   352: bipush #22
    //   354: ldc 16842752
    //   356: iastore
    //   357: dup
    //   358: bipush #23
    //   360: ldc 16778244
    //   362: iastore
    //   363: dup
    //   364: bipush #24
    //   366: ldc 65540
    //   368: iastore
    //   369: dup
    //   370: bipush #25
    //   372: ldc 16777220
    //   374: iastore
    //   375: dup
    //   376: bipush #26
    //   378: ldc 16777220
    //   380: iastore
    //   381: dup
    //   382: bipush #27
    //   384: ldc 65540
    //   386: iastore
    //   387: dup
    //   388: bipush #28
    //   390: iconst_0
    //   391: iastore
    //   392: dup
    //   393: bipush #29
    //   395: sipush #1028
    //   398: iastore
    //   399: dup
    //   400: bipush #30
    //   402: ldc 66564
    //   404: iastore
    //   405: dup
    //   406: bipush #31
    //   408: ldc 16777216
    //   410: iastore
    //   411: dup
    //   412: bipush #32
    //   414: ldc 65536
    //   416: iastore
    //   417: dup
    //   418: bipush #33
    //   420: ldc 16843780
    //   422: iastore
    //   423: dup
    //   424: bipush #34
    //   426: iconst_4
    //   427: iastore
    //   428: dup
    //   429: bipush #35
    //   431: ldc 16842752
    //   433: iastore
    //   434: dup
    //   435: bipush #36
    //   437: ldc 16843776
    //   439: iastore
    //   440: dup
    //   441: bipush #37
    //   443: ldc 16777216
    //   445: iastore
    //   446: dup
    //   447: bipush #38
    //   449: ldc 16777216
    //   451: iastore
    //   452: dup
    //   453: bipush #39
    //   455: sipush #1024
    //   458: iastore
    //   459: dup
    //   460: bipush #40
    //   462: ldc 16842756
    //   464: iastore
    //   465: dup
    //   466: bipush #41
    //   468: ldc 65536
    //   470: iastore
    //   471: dup
    //   472: bipush #42
    //   474: ldc 66560
    //   476: iastore
    //   477: dup
    //   478: bipush #43
    //   480: ldc 16777220
    //   482: iastore
    //   483: dup
    //   484: bipush #44
    //   486: sipush #1024
    //   489: iastore
    //   490: dup
    //   491: bipush #45
    //   493: iconst_4
    //   494: iastore
    //   495: dup
    //   496: bipush #46
    //   498: ldc 16778244
    //   500: iastore
    //   501: dup
    //   502: bipush #47
    //   504: ldc 66564
    //   506: iastore
    //   507: dup
    //   508: bipush #48
    //   510: ldc 16843780
    //   512: iastore
    //   513: dup
    //   514: bipush #49
    //   516: ldc 65540
    //   518: iastore
    //   519: dup
    //   520: bipush #50
    //   522: ldc 16842752
    //   524: iastore
    //   525: dup
    //   526: bipush #51
    //   528: ldc 16778244
    //   530: iastore
    //   531: dup
    //   532: bipush #52
    //   534: ldc 16777220
    //   536: iastore
    //   537: dup
    //   538: bipush #53
    //   540: sipush #1028
    //   543: iastore
    //   544: dup
    //   545: bipush #54
    //   547: ldc 66564
    //   549: iastore
    //   550: dup
    //   551: bipush #55
    //   553: ldc 16843776
    //   555: iastore
    //   556: dup
    //   557: bipush #56
    //   559: sipush #1028
    //   562: iastore
    //   563: dup
    //   564: bipush #57
    //   566: ldc 16778240
    //   568: iastore
    //   569: dup
    //   570: bipush #58
    //   572: ldc 16778240
    //   574: iastore
    //   575: dup
    //   576: bipush #59
    //   578: iconst_0
    //   579: iastore
    //   580: dup
    //   581: bipush #60
    //   583: ldc 65540
    //   585: iastore
    //   586: dup
    //   587: bipush #61
    //   589: ldc 66560
    //   591: iastore
    //   592: dup
    //   593: bipush #62
    //   595: iconst_0
    //   596: iastore
    //   597: dup
    //   598: bipush #63
    //   600: ldc 16842756
    //   602: iastore
    //   603: astore #6
    //   605: bipush #64
    //   607: newarray int
    //   609: dup
    //   610: iconst_0
    //   611: ldc -2146402272
    //   613: iastore
    //   614: dup
    //   615: iconst_1
    //   616: ldc -2147450880
    //   618: iastore
    //   619: dup
    //   620: iconst_2
    //   621: ldc 32768
    //   623: iastore
    //   624: dup
    //   625: iconst_3
    //   626: ldc 1081376
    //   628: iastore
    //   629: dup
    //   630: iconst_4
    //   631: ldc 1048576
    //   633: iastore
    //   634: dup
    //   635: iconst_5
    //   636: bipush #32
    //   638: iastore
    //   639: dup
    //   640: bipush #6
    //   642: ldc -2146435040
    //   644: iastore
    //   645: dup
    //   646: bipush #7
    //   648: ldc -2147450848
    //   650: iastore
    //   651: dup
    //   652: bipush #8
    //   654: ldc -2147483616
    //   656: iastore
    //   657: dup
    //   658: bipush #9
    //   660: ldc -2146402272
    //   662: iastore
    //   663: dup
    //   664: bipush #10
    //   666: ldc -2146402304
    //   668: iastore
    //   669: dup
    //   670: bipush #11
    //   672: ldc -2147483648
    //   674: iastore
    //   675: dup
    //   676: bipush #12
    //   678: ldc -2147450880
    //   680: iastore
    //   681: dup
    //   682: bipush #13
    //   684: ldc 1048576
    //   686: iastore
    //   687: dup
    //   688: bipush #14
    //   690: bipush #32
    //   692: iastore
    //   693: dup
    //   694: bipush #15
    //   696: ldc -2146435040
    //   698: iastore
    //   699: dup
    //   700: bipush #16
    //   702: ldc 1081344
    //   704: iastore
    //   705: dup
    //   706: bipush #17
    //   708: ldc 1048608
    //   710: iastore
    //   711: dup
    //   712: bipush #18
    //   714: ldc -2147450848
    //   716: iastore
    //   717: dup
    //   718: bipush #19
    //   720: iconst_0
    //   721: iastore
    //   722: dup
    //   723: bipush #20
    //   725: ldc -2147483648
    //   727: iastore
    //   728: dup
    //   729: bipush #21
    //   731: ldc 32768
    //   733: iastore
    //   734: dup
    //   735: bipush #22
    //   737: ldc 1081376
    //   739: iastore
    //   740: dup
    //   741: bipush #23
    //   743: ldc -2146435072
    //   745: iastore
    //   746: dup
    //   747: bipush #24
    //   749: ldc 1048608
    //   751: iastore
    //   752: dup
    //   753: bipush #25
    //   755: ldc -2147483616
    //   757: iastore
    //   758: dup
    //   759: bipush #26
    //   761: iconst_0
    //   762: iastore
    //   763: dup
    //   764: bipush #27
    //   766: ldc 1081344
    //   768: iastore
    //   769: dup
    //   770: bipush #28
    //   772: ldc 32800
    //   774: iastore
    //   775: dup
    //   776: bipush #29
    //   778: ldc -2146402304
    //   780: iastore
    //   781: dup
    //   782: bipush #30
    //   784: ldc -2146435072
    //   786: iastore
    //   787: dup
    //   788: bipush #31
    //   790: ldc 32800
    //   792: iastore
    //   793: dup
    //   794: bipush #32
    //   796: iconst_0
    //   797: iastore
    //   798: dup
    //   799: bipush #33
    //   801: ldc 1081376
    //   803: iastore
    //   804: dup
    //   805: bipush #34
    //   807: ldc -2146435040
    //   809: iastore
    //   810: dup
    //   811: bipush #35
    //   813: ldc 1048576
    //   815: iastore
    //   816: dup
    //   817: bipush #36
    //   819: ldc -2147450848
    //   821: iastore
    //   822: dup
    //   823: bipush #37
    //   825: ldc -2146435072
    //   827: iastore
    //   828: dup
    //   829: bipush #38
    //   831: ldc -2146402304
    //   833: iastore
    //   834: dup
    //   835: bipush #39
    //   837: ldc 32768
    //   839: iastore
    //   840: dup
    //   841: bipush #40
    //   843: ldc -2146435072
    //   845: iastore
    //   846: dup
    //   847: bipush #41
    //   849: ldc -2147450880
    //   851: iastore
    //   852: dup
    //   853: bipush #42
    //   855: bipush #32
    //   857: iastore
    //   858: dup
    //   859: bipush #43
    //   861: ldc -2146402272
    //   863: iastore
    //   864: dup
    //   865: bipush #44
    //   867: ldc 1081376
    //   869: iastore
    //   870: dup
    //   871: bipush #45
    //   873: bipush #32
    //   875: iastore
    //   876: dup
    //   877: bipush #46
    //   879: ldc 32768
    //   881: iastore
    //   882: dup
    //   883: bipush #47
    //   885: ldc -2147483648
    //   887: iastore
    //   888: dup
    //   889: bipush #48
    //   891: ldc 32800
    //   893: iastore
    //   894: dup
    //   895: bipush #49
    //   897: ldc -2146402304
    //   899: iastore
    //   900: dup
    //   901: bipush #50
    //   903: ldc 1048576
    //   905: iastore
    //   906: dup
    //   907: bipush #51
    //   909: ldc -2147483616
    //   911: iastore
    //   912: dup
    //   913: bipush #52
    //   915: ldc 1048608
    //   917: iastore
    //   918: dup
    //   919: bipush #53
    //   921: ldc -2147450848
    //   923: iastore
    //   924: dup
    //   925: bipush #54
    //   927: ldc -2147483616
    //   929: iastore
    //   930: dup
    //   931: bipush #55
    //   933: ldc 1048608
    //   935: iastore
    //   936: dup
    //   937: bipush #56
    //   939: ldc 1081344
    //   941: iastore
    //   942: dup
    //   943: bipush #57
    //   945: iconst_0
    //   946: iastore
    //   947: dup
    //   948: bipush #58
    //   950: ldc -2147450880
    //   952: iastore
    //   953: dup
    //   954: bipush #59
    //   956: ldc 32800
    //   958: iastore
    //   959: dup
    //   960: bipush #60
    //   962: ldc -2147483648
    //   964: iastore
    //   965: dup
    //   966: bipush #61
    //   968: ldc -2146435040
    //   970: iastore
    //   971: dup
    //   972: bipush #62
    //   974: ldc -2146402272
    //   976: iastore
    //   977: dup
    //   978: bipush #63
    //   980: ldc 1081344
    //   982: iastore
    //   983: astore #7
    //   985: bipush #64
    //   987: newarray int
    //   989: dup
    //   990: iconst_0
    //   991: sipush #520
    //   994: iastore
    //   995: dup
    //   996: iconst_1
    //   997: ldc 134349312
    //   999: iastore
    //   1000: dup
    //   1001: iconst_2
    //   1002: iconst_0
    //   1003: iastore
    //   1004: dup
    //   1005: iconst_3
    //   1006: ldc 134348808
    //   1008: iastore
    //   1009: dup
    //   1010: iconst_4
    //   1011: ldc 134218240
    //   1013: iastore
    //   1014: dup
    //   1015: iconst_5
    //   1016: iconst_0
    //   1017: iastore
    //   1018: dup
    //   1019: bipush #6
    //   1021: ldc 131592
    //   1023: iastore
    //   1024: dup
    //   1025: bipush #7
    //   1027: ldc 134218240
    //   1029: iastore
    //   1030: dup
    //   1031: bipush #8
    //   1033: ldc 131080
    //   1035: iastore
    //   1036: dup
    //   1037: bipush #9
    //   1039: ldc 134217736
    //   1041: iastore
    //   1042: dup
    //   1043: bipush #10
    //   1045: ldc 134217736
    //   1047: iastore
    //   1048: dup
    //   1049: bipush #11
    //   1051: ldc 131072
    //   1053: iastore
    //   1054: dup
    //   1055: bipush #12
    //   1057: ldc 134349320
    //   1059: iastore
    //   1060: dup
    //   1061: bipush #13
    //   1063: ldc 131080
    //   1065: iastore
    //   1066: dup
    //   1067: bipush #14
    //   1069: ldc 134348800
    //   1071: iastore
    //   1072: dup
    //   1073: bipush #15
    //   1075: sipush #520
    //   1078: iastore
    //   1079: dup
    //   1080: bipush #16
    //   1082: ldc 134217728
    //   1084: iastore
    //   1085: dup
    //   1086: bipush #17
    //   1088: bipush #8
    //   1090: iastore
    //   1091: dup
    //   1092: bipush #18
    //   1094: ldc 134349312
    //   1096: iastore
    //   1097: dup
    //   1098: bipush #19
    //   1100: sipush #512
    //   1103: iastore
    //   1104: dup
    //   1105: bipush #20
    //   1107: ldc 131584
    //   1109: iastore
    //   1110: dup
    //   1111: bipush #21
    //   1113: ldc 134348800
    //   1115: iastore
    //   1116: dup
    //   1117: bipush #22
    //   1119: ldc 134348808
    //   1121: iastore
    //   1122: dup
    //   1123: bipush #23
    //   1125: ldc 131592
    //   1127: iastore
    //   1128: dup
    //   1129: bipush #24
    //   1131: ldc 134218248
    //   1133: iastore
    //   1134: dup
    //   1135: bipush #25
    //   1137: ldc 131584
    //   1139: iastore
    //   1140: dup
    //   1141: bipush #26
    //   1143: ldc 131072
    //   1145: iastore
    //   1146: dup
    //   1147: bipush #27
    //   1149: ldc 134218248
    //   1151: iastore
    //   1152: dup
    //   1153: bipush #28
    //   1155: bipush #8
    //   1157: iastore
    //   1158: dup
    //   1159: bipush #29
    //   1161: ldc 134349320
    //   1163: iastore
    //   1164: dup
    //   1165: bipush #30
    //   1167: sipush #512
    //   1170: iastore
    //   1171: dup
    //   1172: bipush #31
    //   1174: ldc 134217728
    //   1176: iastore
    //   1177: dup
    //   1178: bipush #32
    //   1180: ldc 134349312
    //   1182: iastore
    //   1183: dup
    //   1184: bipush #33
    //   1186: ldc 134217728
    //   1188: iastore
    //   1189: dup
    //   1190: bipush #34
    //   1192: ldc 131080
    //   1194: iastore
    //   1195: dup
    //   1196: bipush #35
    //   1198: sipush #520
    //   1201: iastore
    //   1202: dup
    //   1203: bipush #36
    //   1205: ldc 131072
    //   1207: iastore
    //   1208: dup
    //   1209: bipush #37
    //   1211: ldc 134349312
    //   1213: iastore
    //   1214: dup
    //   1215: bipush #38
    //   1217: ldc 134218240
    //   1219: iastore
    //   1220: dup
    //   1221: bipush #39
    //   1223: iconst_0
    //   1224: iastore
    //   1225: dup
    //   1226: bipush #40
    //   1228: sipush #512
    //   1231: iastore
    //   1232: dup
    //   1233: bipush #41
    //   1235: ldc 131080
    //   1237: iastore
    //   1238: dup
    //   1239: bipush #42
    //   1241: ldc 134349320
    //   1243: iastore
    //   1244: dup
    //   1245: bipush #43
    //   1247: ldc 134218240
    //   1249: iastore
    //   1250: dup
    //   1251: bipush #44
    //   1253: ldc 134217736
    //   1255: iastore
    //   1256: dup
    //   1257: bipush #45
    //   1259: sipush #512
    //   1262: iastore
    //   1263: dup
    //   1264: bipush #46
    //   1266: iconst_0
    //   1267: iastore
    //   1268: dup
    //   1269: bipush #47
    //   1271: ldc 134348808
    //   1273: iastore
    //   1274: dup
    //   1275: bipush #48
    //   1277: ldc 134218248
    //   1279: iastore
    //   1280: dup
    //   1281: bipush #49
    //   1283: ldc 131072
    //   1285: iastore
    //   1286: dup
    //   1287: bipush #50
    //   1289: ldc 134217728
    //   1291: iastore
    //   1292: dup
    //   1293: bipush #51
    //   1295: ldc 134349320
    //   1297: iastore
    //   1298: dup
    //   1299: bipush #52
    //   1301: bipush #8
    //   1303: iastore
    //   1304: dup
    //   1305: bipush #53
    //   1307: ldc 131592
    //   1309: iastore
    //   1310: dup
    //   1311: bipush #54
    //   1313: ldc 131584
    //   1315: iastore
    //   1316: dup
    //   1317: bipush #55
    //   1319: ldc 134217736
    //   1321: iastore
    //   1322: dup
    //   1323: bipush #56
    //   1325: ldc 134348800
    //   1327: iastore
    //   1328: dup
    //   1329: bipush #57
    //   1331: ldc 134218248
    //   1333: iastore
    //   1334: dup
    //   1335: bipush #58
    //   1337: sipush #520
    //   1340: iastore
    //   1341: dup
    //   1342: bipush #59
    //   1344: ldc 134348800
    //   1346: iastore
    //   1347: dup
    //   1348: bipush #60
    //   1350: ldc 131592
    //   1352: iastore
    //   1353: dup
    //   1354: bipush #61
    //   1356: bipush #8
    //   1358: iastore
    //   1359: dup
    //   1360: bipush #62
    //   1362: ldc 134348808
    //   1364: iastore
    //   1365: dup
    //   1366: bipush #63
    //   1368: ldc 131584
    //   1370: iastore
    //   1371: astore #8
    //   1373: bipush #64
    //   1375: newarray int
    //   1377: dup
    //   1378: iconst_0
    //   1379: ldc 8396801
    //   1381: iastore
    //   1382: dup
    //   1383: iconst_1
    //   1384: sipush #8321
    //   1387: iastore
    //   1388: dup
    //   1389: iconst_2
    //   1390: sipush #8321
    //   1393: iastore
    //   1394: dup
    //   1395: iconst_3
    //   1396: sipush #128
    //   1399: iastore
    //   1400: dup
    //   1401: iconst_4
    //   1402: ldc 8396928
    //   1404: iastore
    //   1405: dup
    //   1406: iconst_5
    //   1407: ldc 8388737
    //   1409: iastore
    //   1410: dup
    //   1411: bipush #6
    //   1413: ldc 8388609
    //   1415: iastore
    //   1416: dup
    //   1417: bipush #7
    //   1419: sipush #8193
    //   1422: iastore
    //   1423: dup
    //   1424: bipush #8
    //   1426: iconst_0
    //   1427: iastore
    //   1428: dup
    //   1429: bipush #9
    //   1431: ldc 8396800
    //   1433: iastore
    //   1434: dup
    //   1435: bipush #10
    //   1437: ldc 8396800
    //   1439: iastore
    //   1440: dup
    //   1441: bipush #11
    //   1443: ldc 8396929
    //   1445: iastore
    //   1446: dup
    //   1447: bipush #12
    //   1449: sipush #129
    //   1452: iastore
    //   1453: dup
    //   1454: bipush #13
    //   1456: iconst_0
    //   1457: iastore
    //   1458: dup
    //   1459: bipush #14
    //   1461: ldc 8388736
    //   1463: iastore
    //   1464: dup
    //   1465: bipush #15
    //   1467: ldc 8388609
    //   1469: iastore
    //   1470: dup
    //   1471: bipush #16
    //   1473: iconst_1
    //   1474: iastore
    //   1475: dup
    //   1476: bipush #17
    //   1478: sipush #8192
    //   1481: iastore
    //   1482: dup
    //   1483: bipush #18
    //   1485: ldc 8388608
    //   1487: iastore
    //   1488: dup
    //   1489: bipush #19
    //   1491: ldc 8396801
    //   1493: iastore
    //   1494: dup
    //   1495: bipush #20
    //   1497: sipush #128
    //   1500: iastore
    //   1501: dup
    //   1502: bipush #21
    //   1504: ldc 8388608
    //   1506: iastore
    //   1507: dup
    //   1508: bipush #22
    //   1510: sipush #8193
    //   1513: iastore
    //   1514: dup
    //   1515: bipush #23
    //   1517: sipush #8320
    //   1520: iastore
    //   1521: dup
    //   1522: bipush #24
    //   1524: ldc 8388737
    //   1526: iastore
    //   1527: dup
    //   1528: bipush #25
    //   1530: iconst_1
    //   1531: iastore
    //   1532: dup
    //   1533: bipush #26
    //   1535: sipush #8320
    //   1538: iastore
    //   1539: dup
    //   1540: bipush #27
    //   1542: ldc 8388736
    //   1544: iastore
    //   1545: dup
    //   1546: bipush #28
    //   1548: sipush #8192
    //   1551: iastore
    //   1552: dup
    //   1553: bipush #29
    //   1555: ldc 8396928
    //   1557: iastore
    //   1558: dup
    //   1559: bipush #30
    //   1561: ldc 8396929
    //   1563: iastore
    //   1564: dup
    //   1565: bipush #31
    //   1567: sipush #129
    //   1570: iastore
    //   1571: dup
    //   1572: bipush #32
    //   1574: ldc 8388736
    //   1576: iastore
    //   1577: dup
    //   1578: bipush #33
    //   1580: ldc 8388609
    //   1582: iastore
    //   1583: dup
    //   1584: bipush #34
    //   1586: ldc 8396800
    //   1588: iastore
    //   1589: dup
    //   1590: bipush #35
    //   1592: ldc 8396929
    //   1594: iastore
    //   1595: dup
    //   1596: bipush #36
    //   1598: sipush #129
    //   1601: iastore
    //   1602: dup
    //   1603: bipush #37
    //   1605: iconst_0
    //   1606: iastore
    //   1607: dup
    //   1608: bipush #38
    //   1610: iconst_0
    //   1611: iastore
    //   1612: dup
    //   1613: bipush #39
    //   1615: ldc 8396800
    //   1617: iastore
    //   1618: dup
    //   1619: bipush #40
    //   1621: sipush #8320
    //   1624: iastore
    //   1625: dup
    //   1626: bipush #41
    //   1628: ldc 8388736
    //   1630: iastore
    //   1631: dup
    //   1632: bipush #42
    //   1634: ldc 8388737
    //   1636: iastore
    //   1637: dup
    //   1638: bipush #43
    //   1640: iconst_1
    //   1641: iastore
    //   1642: dup
    //   1643: bipush #44
    //   1645: ldc 8396801
    //   1647: iastore
    //   1648: dup
    //   1649: bipush #45
    //   1651: sipush #8321
    //   1654: iastore
    //   1655: dup
    //   1656: bipush #46
    //   1658: sipush #8321
    //   1661: iastore
    //   1662: dup
    //   1663: bipush #47
    //   1665: sipush #128
    //   1668: iastore
    //   1669: dup
    //   1670: bipush #48
    //   1672: ldc 8396929
    //   1674: iastore
    //   1675: dup
    //   1676: bipush #49
    //   1678: sipush #129
    //   1681: iastore
    //   1682: dup
    //   1683: bipush #50
    //   1685: iconst_1
    //   1686: iastore
    //   1687: dup
    //   1688: bipush #51
    //   1690: sipush #8192
    //   1693: iastore
    //   1694: dup
    //   1695: bipush #52
    //   1697: ldc 8388609
    //   1699: iastore
    //   1700: dup
    //   1701: bipush #53
    //   1703: sipush #8193
    //   1706: iastore
    //   1707: dup
    //   1708: bipush #54
    //   1710: ldc 8396928
    //   1712: iastore
    //   1713: dup
    //   1714: bipush #55
    //   1716: ldc 8388737
    //   1718: iastore
    //   1719: dup
    //   1720: bipush #56
    //   1722: sipush #8193
    //   1725: iastore
    //   1726: dup
    //   1727: bipush #57
    //   1729: sipush #8320
    //   1732: iastore
    //   1733: dup
    //   1734: bipush #58
    //   1736: ldc 8388608
    //   1738: iastore
    //   1739: dup
    //   1740: bipush #59
    //   1742: ldc 8396801
    //   1744: iastore
    //   1745: dup
    //   1746: bipush #60
    //   1748: sipush #128
    //   1751: iastore
    //   1752: dup
    //   1753: bipush #61
    //   1755: ldc 8388608
    //   1757: iastore
    //   1758: dup
    //   1759: bipush #62
    //   1761: sipush #8192
    //   1764: iastore
    //   1765: dup
    //   1766: bipush #63
    //   1768: ldc 8396928
    //   1770: iastore
    //   1771: astore #9
    //   1773: bipush #64
    //   1775: newarray int
    //   1777: dup
    //   1778: iconst_0
    //   1779: sipush #256
    //   1782: iastore
    //   1783: dup
    //   1784: iconst_1
    //   1785: ldc 34078976
    //   1787: iastore
    //   1788: dup
    //   1789: iconst_2
    //   1790: ldc 34078720
    //   1792: iastore
    //   1793: dup
    //   1794: iconst_3
    //   1795: ldc 1107296512
    //   1797: iastore
    //   1798: dup
    //   1799: iconst_4
    //   1800: ldc 524288
    //   1802: iastore
    //   1803: dup
    //   1804: iconst_5
    //   1805: sipush #256
    //   1808: iastore
    //   1809: dup
    //   1810: bipush #6
    //   1812: ldc 1073741824
    //   1814: iastore
    //   1815: dup
    //   1816: bipush #7
    //   1818: ldc 34078720
    //   1820: iastore
    //   1821: dup
    //   1822: bipush #8
    //   1824: ldc 1074266368
    //   1826: iastore
    //   1827: dup
    //   1828: bipush #9
    //   1830: ldc 524288
    //   1832: iastore
    //   1833: dup
    //   1834: bipush #10
    //   1836: ldc 33554688
    //   1838: iastore
    //   1839: dup
    //   1840: bipush #11
    //   1842: ldc 1074266368
    //   1844: iastore
    //   1845: dup
    //   1846: bipush #12
    //   1848: ldc 1107296512
    //   1850: iastore
    //   1851: dup
    //   1852: bipush #13
    //   1854: ldc 1107820544
    //   1856: iastore
    //   1857: dup
    //   1858: bipush #14
    //   1860: ldc 524544
    //   1862: iastore
    //   1863: dup
    //   1864: bipush #15
    //   1866: ldc 1073741824
    //   1868: iastore
    //   1869: dup
    //   1870: bipush #16
    //   1872: ldc 33554432
    //   1874: iastore
    //   1875: dup
    //   1876: bipush #17
    //   1878: ldc 1074266112
    //   1880: iastore
    //   1881: dup
    //   1882: bipush #18
    //   1884: ldc 1074266112
    //   1886: iastore
    //   1887: dup
    //   1888: bipush #19
    //   1890: iconst_0
    //   1891: iastore
    //   1892: dup
    //   1893: bipush #20
    //   1895: ldc 1073742080
    //   1897: iastore
    //   1898: dup
    //   1899: bipush #21
    //   1901: ldc 1107820800
    //   1903: iastore
    //   1904: dup
    //   1905: bipush #22
    //   1907: ldc 1107820800
    //   1909: iastore
    //   1910: dup
    //   1911: bipush #23
    //   1913: ldc 33554688
    //   1915: iastore
    //   1916: dup
    //   1917: bipush #24
    //   1919: ldc 1107820544
    //   1921: iastore
    //   1922: dup
    //   1923: bipush #25
    //   1925: ldc 1073742080
    //   1927: iastore
    //   1928: dup
    //   1929: bipush #26
    //   1931: iconst_0
    //   1932: iastore
    //   1933: dup
    //   1934: bipush #27
    //   1936: ldc 1107296256
    //   1938: iastore
    //   1939: dup
    //   1940: bipush #28
    //   1942: ldc 34078976
    //   1944: iastore
    //   1945: dup
    //   1946: bipush #29
    //   1948: ldc 33554432
    //   1950: iastore
    //   1951: dup
    //   1952: bipush #30
    //   1954: ldc 1107296256
    //   1956: iastore
    //   1957: dup
    //   1958: bipush #31
    //   1960: ldc 524544
    //   1962: iastore
    //   1963: dup
    //   1964: bipush #32
    //   1966: ldc 524288
    //   1968: iastore
    //   1969: dup
    //   1970: bipush #33
    //   1972: ldc 1107296512
    //   1974: iastore
    //   1975: dup
    //   1976: bipush #34
    //   1978: sipush #256
    //   1981: iastore
    //   1982: dup
    //   1983: bipush #35
    //   1985: ldc 33554432
    //   1987: iastore
    //   1988: dup
    //   1989: bipush #36
    //   1991: ldc 1073741824
    //   1993: iastore
    //   1994: dup
    //   1995: bipush #37
    //   1997: ldc 34078720
    //   1999: iastore
    //   2000: dup
    //   2001: bipush #38
    //   2003: ldc 1107296512
    //   2005: iastore
    //   2006: dup
    //   2007: bipush #39
    //   2009: ldc 1074266368
    //   2011: iastore
    //   2012: dup
    //   2013: bipush #40
    //   2015: ldc 33554688
    //   2017: iastore
    //   2018: dup
    //   2019: bipush #41
    //   2021: ldc 1073741824
    //   2023: iastore
    //   2024: dup
    //   2025: bipush #42
    //   2027: ldc 1107820544
    //   2029: iastore
    //   2030: dup
    //   2031: bipush #43
    //   2033: ldc 34078976
    //   2035: iastore
    //   2036: dup
    //   2037: bipush #44
    //   2039: ldc 1074266368
    //   2041: iastore
    //   2042: dup
    //   2043: bipush #45
    //   2045: sipush #256
    //   2048: iastore
    //   2049: dup
    //   2050: bipush #46
    //   2052: ldc 33554432
    //   2054: iastore
    //   2055: dup
    //   2056: bipush #47
    //   2058: ldc 1107820544
    //   2060: iastore
    //   2061: dup
    //   2062: bipush #48
    //   2064: ldc 1107820800
    //   2066: iastore
    //   2067: dup
    //   2068: bipush #49
    //   2070: ldc 524544
    //   2072: iastore
    //   2073: dup
    //   2074: bipush #50
    //   2076: ldc 1107296256
    //   2078: iastore
    //   2079: dup
    //   2080: bipush #51
    //   2082: ldc 1107820800
    //   2084: iastore
    //   2085: dup
    //   2086: bipush #52
    //   2088: ldc 34078720
    //   2090: iastore
    //   2091: dup
    //   2092: bipush #53
    //   2094: iconst_0
    //   2095: iastore
    //   2096: dup
    //   2097: bipush #54
    //   2099: ldc 1074266112
    //   2101: iastore
    //   2102: dup
    //   2103: bipush #55
    //   2105: ldc 1107296256
    //   2107: iastore
    //   2108: dup
    //   2109: bipush #56
    //   2111: ldc 524544
    //   2113: iastore
    //   2114: dup
    //   2115: bipush #57
    //   2117: ldc 33554688
    //   2119: iastore
    //   2120: dup
    //   2121: bipush #58
    //   2123: ldc 1073742080
    //   2125: iastore
    //   2126: dup
    //   2127: bipush #59
    //   2129: ldc 524288
    //   2131: iastore
    //   2132: dup
    //   2133: bipush #60
    //   2135: iconst_0
    //   2136: iastore
    //   2137: dup
    //   2138: bipush #61
    //   2140: ldc 1074266112
    //   2142: iastore
    //   2143: dup
    //   2144: bipush #62
    //   2146: ldc 34078976
    //   2148: iastore
    //   2149: dup
    //   2150: bipush #63
    //   2152: ldc 1073742080
    //   2154: iastore
    //   2155: astore #10
    //   2157: bipush #64
    //   2159: newarray int
    //   2161: dup
    //   2162: iconst_0
    //   2163: ldc 536870928
    //   2165: iastore
    //   2166: dup
    //   2167: iconst_1
    //   2168: ldc 541065216
    //   2170: iastore
    //   2171: dup
    //   2172: iconst_2
    //   2173: sipush #16384
    //   2176: iastore
    //   2177: dup
    //   2178: iconst_3
    //   2179: ldc 541081616
    //   2181: iastore
    //   2182: dup
    //   2183: iconst_4
    //   2184: ldc 541065216
    //   2186: iastore
    //   2187: dup
    //   2188: iconst_5
    //   2189: bipush #16
    //   2191: iastore
    //   2192: dup
    //   2193: bipush #6
    //   2195: ldc 541081616
    //   2197: iastore
    //   2198: dup
    //   2199: bipush #7
    //   2201: ldc 4194304
    //   2203: iastore
    //   2204: dup
    //   2205: bipush #8
    //   2207: ldc 536887296
    //   2209: iastore
    //   2210: dup
    //   2211: bipush #9
    //   2213: ldc 4210704
    //   2215: iastore
    //   2216: dup
    //   2217: bipush #10
    //   2219: ldc 4194304
    //   2221: iastore
    //   2222: dup
    //   2223: bipush #11
    //   2225: ldc 536870928
    //   2227: iastore
    //   2228: dup
    //   2229: bipush #12
    //   2231: ldc 4194320
    //   2233: iastore
    //   2234: dup
    //   2235: bipush #13
    //   2237: ldc 536887296
    //   2239: iastore
    //   2240: dup
    //   2241: bipush #14
    //   2243: ldc 536870912
    //   2245: iastore
    //   2246: dup
    //   2247: bipush #15
    //   2249: sipush #16400
    //   2252: iastore
    //   2253: dup
    //   2254: bipush #16
    //   2256: iconst_0
    //   2257: iastore
    //   2258: dup
    //   2259: bipush #17
    //   2261: ldc 4194320
    //   2263: iastore
    //   2264: dup
    //   2265: bipush #18
    //   2267: ldc 536887312
    //   2269: iastore
    //   2270: dup
    //   2271: bipush #19
    //   2273: sipush #16384
    //   2276: iastore
    //   2277: dup
    //   2278: bipush #20
    //   2280: ldc 4210688
    //   2282: iastore
    //   2283: dup
    //   2284: bipush #21
    //   2286: ldc 536887312
    //   2288: iastore
    //   2289: dup
    //   2290: bipush #22
    //   2292: bipush #16
    //   2294: iastore
    //   2295: dup
    //   2296: bipush #23
    //   2298: ldc 541065232
    //   2300: iastore
    //   2301: dup
    //   2302: bipush #24
    //   2304: ldc 541065232
    //   2306: iastore
    //   2307: dup
    //   2308: bipush #25
    //   2310: iconst_0
    //   2311: iastore
    //   2312: dup
    //   2313: bipush #26
    //   2315: ldc 4210704
    //   2317: iastore
    //   2318: dup
    //   2319: bipush #27
    //   2321: ldc 541081600
    //   2323: iastore
    //   2324: dup
    //   2325: bipush #28
    //   2327: sipush #16400
    //   2330: iastore
    //   2331: dup
    //   2332: bipush #29
    //   2334: ldc 4210688
    //   2336: iastore
    //   2337: dup
    //   2338: bipush #30
    //   2340: ldc 541081600
    //   2342: iastore
    //   2343: dup
    //   2344: bipush #31
    //   2346: ldc 536870912
    //   2348: iastore
    //   2349: dup
    //   2350: bipush #32
    //   2352: ldc 536887296
    //   2354: iastore
    //   2355: dup
    //   2356: bipush #33
    //   2358: bipush #16
    //   2360: iastore
    //   2361: dup
    //   2362: bipush #34
    //   2364: ldc 541065232
    //   2366: iastore
    //   2367: dup
    //   2368: bipush #35
    //   2370: ldc 4210688
    //   2372: iastore
    //   2373: dup
    //   2374: bipush #36
    //   2376: ldc 541081616
    //   2378: iastore
    //   2379: dup
    //   2380: bipush #37
    //   2382: ldc 4194304
    //   2384: iastore
    //   2385: dup
    //   2386: bipush #38
    //   2388: sipush #16400
    //   2391: iastore
    //   2392: dup
    //   2393: bipush #39
    //   2395: ldc 536870928
    //   2397: iastore
    //   2398: dup
    //   2399: bipush #40
    //   2401: ldc 4194304
    //   2403: iastore
    //   2404: dup
    //   2405: bipush #41
    //   2407: ldc 536887296
    //   2409: iastore
    //   2410: dup
    //   2411: bipush #42
    //   2413: ldc 536870912
    //   2415: iastore
    //   2416: dup
    //   2417: bipush #43
    //   2419: sipush #16400
    //   2422: iastore
    //   2423: dup
    //   2424: bipush #44
    //   2426: ldc 536870928
    //   2428: iastore
    //   2429: dup
    //   2430: bipush #45
    //   2432: ldc 541081616
    //   2434: iastore
    //   2435: dup
    //   2436: bipush #46
    //   2438: ldc 4210688
    //   2440: iastore
    //   2441: dup
    //   2442: bipush #47
    //   2444: ldc 541065216
    //   2446: iastore
    //   2447: dup
    //   2448: bipush #48
    //   2450: ldc 4210704
    //   2452: iastore
    //   2453: dup
    //   2454: bipush #49
    //   2456: ldc 541081600
    //   2458: iastore
    //   2459: dup
    //   2460: bipush #50
    //   2462: iconst_0
    //   2463: iastore
    //   2464: dup
    //   2465: bipush #51
    //   2467: ldc 541065232
    //   2469: iastore
    //   2470: dup
    //   2471: bipush #52
    //   2473: bipush #16
    //   2475: iastore
    //   2476: dup
    //   2477: bipush #53
    //   2479: sipush #16384
    //   2482: iastore
    //   2483: dup
    //   2484: bipush #54
    //   2486: ldc 541065216
    //   2488: iastore
    //   2489: dup
    //   2490: bipush #55
    //   2492: ldc 4210704
    //   2494: iastore
    //   2495: dup
    //   2496: bipush #56
    //   2498: sipush #16384
    //   2501: iastore
    //   2502: dup
    //   2503: bipush #57
    //   2505: ldc 4194320
    //   2507: iastore
    //   2508: dup
    //   2509: bipush #58
    //   2511: ldc 536887312
    //   2513: iastore
    //   2514: dup
    //   2515: bipush #59
    //   2517: iconst_0
    //   2518: iastore
    //   2519: dup
    //   2520: bipush #60
    //   2522: ldc 541081600
    //   2524: iastore
    //   2525: dup
    //   2526: bipush #61
    //   2528: ldc 536870912
    //   2530: iastore
    //   2531: dup
    //   2532: bipush #62
    //   2534: ldc 4194320
    //   2536: iastore
    //   2537: dup
    //   2538: bipush #63
    //   2540: ldc 536887312
    //   2542: iastore
    //   2543: astore #11
    //   2545: bipush #64
    //   2547: newarray int
    //   2549: dup
    //   2550: iconst_0
    //   2551: ldc 2097152
    //   2553: iastore
    //   2554: dup
    //   2555: iconst_1
    //   2556: ldc 69206018
    //   2558: iastore
    //   2559: dup
    //   2560: iconst_2
    //   2561: ldc 67110914
    //   2563: iastore
    //   2564: dup
    //   2565: iconst_3
    //   2566: iconst_0
    //   2567: iastore
    //   2568: dup
    //   2569: iconst_4
    //   2570: sipush #2048
    //   2573: iastore
    //   2574: dup
    //   2575: iconst_5
    //   2576: ldc 67110914
    //   2578: iastore
    //   2579: dup
    //   2580: bipush #6
    //   2582: ldc 2099202
    //   2584: iastore
    //   2585: dup
    //   2586: bipush #7
    //   2588: ldc 69208064
    //   2590: iastore
    //   2591: dup
    //   2592: bipush #8
    //   2594: ldc 69208066
    //   2596: iastore
    //   2597: dup
    //   2598: bipush #9
    //   2600: ldc 2097152
    //   2602: iastore
    //   2603: dup
    //   2604: bipush #10
    //   2606: iconst_0
    //   2607: iastore
    //   2608: dup
    //   2609: bipush #11
    //   2611: ldc 67108866
    //   2613: iastore
    //   2614: dup
    //   2615: bipush #12
    //   2617: iconst_2
    //   2618: iastore
    //   2619: dup
    //   2620: bipush #13
    //   2622: ldc 67108864
    //   2624: iastore
    //   2625: dup
    //   2626: bipush #14
    //   2628: ldc 69206018
    //   2630: iastore
    //   2631: dup
    //   2632: bipush #15
    //   2634: sipush #2050
    //   2637: iastore
    //   2638: dup
    //   2639: bipush #16
    //   2641: ldc 67110912
    //   2643: iastore
    //   2644: dup
    //   2645: bipush #17
    //   2647: ldc 2099202
    //   2649: iastore
    //   2650: dup
    //   2651: bipush #18
    //   2653: ldc 2097154
    //   2655: iastore
    //   2656: dup
    //   2657: bipush #19
    //   2659: ldc 67110912
    //   2661: iastore
    //   2662: dup
    //   2663: bipush #20
    //   2665: ldc 67108866
    //   2667: iastore
    //   2668: dup
    //   2669: bipush #21
    //   2671: ldc 69206016
    //   2673: iastore
    //   2674: dup
    //   2675: bipush #22
    //   2677: ldc 69208064
    //   2679: iastore
    //   2680: dup
    //   2681: bipush #23
    //   2683: ldc 2097154
    //   2685: iastore
    //   2686: dup
    //   2687: bipush #24
    //   2689: ldc 69206016
    //   2691: iastore
    //   2692: dup
    //   2693: bipush #25
    //   2695: sipush #2048
    //   2698: iastore
    //   2699: dup
    //   2700: bipush #26
    //   2702: sipush #2050
    //   2705: iastore
    //   2706: dup
    //   2707: bipush #27
    //   2709: ldc 69208066
    //   2711: iastore
    //   2712: dup
    //   2713: bipush #28
    //   2715: ldc 2099200
    //   2717: iastore
    //   2718: dup
    //   2719: bipush #29
    //   2721: iconst_2
    //   2722: iastore
    //   2723: dup
    //   2724: bipush #30
    //   2726: ldc 67108864
    //   2728: iastore
    //   2729: dup
    //   2730: bipush #31
    //   2732: ldc 2099200
    //   2734: iastore
    //   2735: dup
    //   2736: bipush #32
    //   2738: ldc 67108864
    //   2740: iastore
    //   2741: dup
    //   2742: bipush #33
    //   2744: ldc 2099200
    //   2746: iastore
    //   2747: dup
    //   2748: bipush #34
    //   2750: ldc 2097152
    //   2752: iastore
    //   2753: dup
    //   2754: bipush #35
    //   2756: ldc 67110914
    //   2758: iastore
    //   2759: dup
    //   2760: bipush #36
    //   2762: ldc 67110914
    //   2764: iastore
    //   2765: dup
    //   2766: bipush #37
    //   2768: ldc 69206018
    //   2770: iastore
    //   2771: dup
    //   2772: bipush #38
    //   2774: ldc 69206018
    //   2776: iastore
    //   2777: dup
    //   2778: bipush #39
    //   2780: iconst_2
    //   2781: iastore
    //   2782: dup
    //   2783: bipush #40
    //   2785: ldc 2097154
    //   2787: iastore
    //   2788: dup
    //   2789: bipush #41
    //   2791: ldc 67108864
    //   2793: iastore
    //   2794: dup
    //   2795: bipush #42
    //   2797: ldc 67110912
    //   2799: iastore
    //   2800: dup
    //   2801: bipush #43
    //   2803: ldc 2097152
    //   2805: iastore
    //   2806: dup
    //   2807: bipush #44
    //   2809: ldc 69208064
    //   2811: iastore
    //   2812: dup
    //   2813: bipush #45
    //   2815: sipush #2050
    //   2818: iastore
    //   2819: dup
    //   2820: bipush #46
    //   2822: ldc 2099202
    //   2824: iastore
    //   2825: dup
    //   2826: bipush #47
    //   2828: ldc 69208064
    //   2830: iastore
    //   2831: dup
    //   2832: bipush #48
    //   2834: sipush #2050
    //   2837: iastore
    //   2838: dup
    //   2839: bipush #49
    //   2841: ldc 67108866
    //   2843: iastore
    //   2844: dup
    //   2845: bipush #50
    //   2847: ldc 69208066
    //   2849: iastore
    //   2850: dup
    //   2851: bipush #51
    //   2853: ldc 69206016
    //   2855: iastore
    //   2856: dup
    //   2857: bipush #52
    //   2859: ldc 2099200
    //   2861: iastore
    //   2862: dup
    //   2863: bipush #53
    //   2865: iconst_0
    //   2866: iastore
    //   2867: dup
    //   2868: bipush #54
    //   2870: iconst_2
    //   2871: iastore
    //   2872: dup
    //   2873: bipush #55
    //   2875: ldc 69208066
    //   2877: iastore
    //   2878: dup
    //   2879: bipush #56
    //   2881: iconst_0
    //   2882: iastore
    //   2883: dup
    //   2884: bipush #57
    //   2886: ldc 2099202
    //   2888: iastore
    //   2889: dup
    //   2890: bipush #58
    //   2892: ldc 69206016
    //   2894: iastore
    //   2895: dup
    //   2896: bipush #59
    //   2898: sipush #2048
    //   2901: iastore
    //   2902: dup
    //   2903: bipush #60
    //   2905: ldc 67108866
    //   2907: iastore
    //   2908: dup
    //   2909: bipush #61
    //   2911: ldc 67110912
    //   2913: iastore
    //   2914: dup
    //   2915: bipush #62
    //   2917: sipush #2048
    //   2920: iastore
    //   2921: dup
    //   2922: bipush #63
    //   2924: ldc 2097154
    //   2926: iastore
    //   2927: astore #12
    //   2929: bipush #64
    //   2931: newarray int
    //   2933: dup
    //   2934: iconst_0
    //   2935: ldc 268439616
    //   2937: iastore
    //   2938: dup
    //   2939: iconst_1
    //   2940: sipush #4096
    //   2943: iastore
    //   2944: dup
    //   2945: iconst_2
    //   2946: ldc 262144
    //   2948: iastore
    //   2949: dup
    //   2950: iconst_3
    //   2951: ldc 268701760
    //   2953: iastore
    //   2954: dup
    //   2955: iconst_4
    //   2956: ldc 268435456
    //   2958: iastore
    //   2959: dup
    //   2960: iconst_5
    //   2961: ldc 268439616
    //   2963: iastore
    //   2964: dup
    //   2965: bipush #6
    //   2967: bipush #64
    //   2969: iastore
    //   2970: dup
    //   2971: bipush #7
    //   2973: ldc 268435456
    //   2975: iastore
    //   2976: dup
    //   2977: bipush #8
    //   2979: ldc 262208
    //   2981: iastore
    //   2982: dup
    //   2983: bipush #9
    //   2985: ldc 268697600
    //   2987: iastore
    //   2988: dup
    //   2989: bipush #10
    //   2991: ldc 268701760
    //   2993: iastore
    //   2994: dup
    //   2995: bipush #11
    //   2997: ldc 266240
    //   2999: iastore
    //   3000: dup
    //   3001: bipush #12
    //   3003: ldc 268701696
    //   3005: iastore
    //   3006: dup
    //   3007: bipush #13
    //   3009: ldc 266304
    //   3011: iastore
    //   3012: dup
    //   3013: bipush #14
    //   3015: sipush #4096
    //   3018: iastore
    //   3019: dup
    //   3020: bipush #15
    //   3022: bipush #64
    //   3024: iastore
    //   3025: dup
    //   3026: bipush #16
    //   3028: ldc 268697600
    //   3030: iastore
    //   3031: dup
    //   3032: bipush #17
    //   3034: ldc 268435520
    //   3036: iastore
    //   3037: dup
    //   3038: bipush #18
    //   3040: ldc 268439552
    //   3042: iastore
    //   3043: dup
    //   3044: bipush #19
    //   3046: sipush #4160
    //   3049: iastore
    //   3050: dup
    //   3051: bipush #20
    //   3053: ldc 266240
    //   3055: iastore
    //   3056: dup
    //   3057: bipush #21
    //   3059: ldc 262208
    //   3061: iastore
    //   3062: dup
    //   3063: bipush #22
    //   3065: ldc 268697664
    //   3067: iastore
    //   3068: dup
    //   3069: bipush #23
    //   3071: ldc 268701696
    //   3073: iastore
    //   3074: dup
    //   3075: bipush #24
    //   3077: sipush #4160
    //   3080: iastore
    //   3081: dup
    //   3082: bipush #25
    //   3084: iconst_0
    //   3085: iastore
    //   3086: dup
    //   3087: bipush #26
    //   3089: iconst_0
    //   3090: iastore
    //   3091: dup
    //   3092: bipush #27
    //   3094: ldc 268697664
    //   3096: iastore
    //   3097: dup
    //   3098: bipush #28
    //   3100: ldc 268435520
    //   3102: iastore
    //   3103: dup
    //   3104: bipush #29
    //   3106: ldc 268439552
    //   3108: iastore
    //   3109: dup
    //   3110: bipush #30
    //   3112: ldc 266304
    //   3114: iastore
    //   3115: dup
    //   3116: bipush #31
    //   3118: ldc 262144
    //   3120: iastore
    //   3121: dup
    //   3122: bipush #32
    //   3124: ldc 266304
    //   3126: iastore
    //   3127: dup
    //   3128: bipush #33
    //   3130: ldc 262144
    //   3132: iastore
    //   3133: dup
    //   3134: bipush #34
    //   3136: ldc 268701696
    //   3138: iastore
    //   3139: dup
    //   3140: bipush #35
    //   3142: sipush #4096
    //   3145: iastore
    //   3146: dup
    //   3147: bipush #36
    //   3149: bipush #64
    //   3151: iastore
    //   3152: dup
    //   3153: bipush #37
    //   3155: ldc 268697664
    //   3157: iastore
    //   3158: dup
    //   3159: bipush #38
    //   3161: sipush #4096
    //   3164: iastore
    //   3165: dup
    //   3166: bipush #39
    //   3168: ldc 266304
    //   3170: iastore
    //   3171: dup
    //   3172: bipush #40
    //   3174: ldc 268439552
    //   3176: iastore
    //   3177: dup
    //   3178: bipush #41
    //   3180: bipush #64
    //   3182: iastore
    //   3183: dup
    //   3184: bipush #42
    //   3186: ldc 268435520
    //   3188: iastore
    //   3189: dup
    //   3190: bipush #43
    //   3192: ldc 268697600
    //   3194: iastore
    //   3195: dup
    //   3196: bipush #44
    //   3198: ldc 268697664
    //   3200: iastore
    //   3201: dup
    //   3202: bipush #45
    //   3204: ldc 268435456
    //   3206: iastore
    //   3207: dup
    //   3208: bipush #46
    //   3210: ldc 262144
    //   3212: iastore
    //   3213: dup
    //   3214: bipush #47
    //   3216: ldc 268439616
    //   3218: iastore
    //   3219: dup
    //   3220: bipush #48
    //   3222: iconst_0
    //   3223: iastore
    //   3224: dup
    //   3225: bipush #49
    //   3227: ldc 268701760
    //   3229: iastore
    //   3230: dup
    //   3231: bipush #50
    //   3233: ldc 262208
    //   3235: iastore
    //   3236: dup
    //   3237: bipush #51
    //   3239: ldc 268435520
    //   3241: iastore
    //   3242: dup
    //   3243: bipush #52
    //   3245: ldc 268697600
    //   3247: iastore
    //   3248: dup
    //   3249: bipush #53
    //   3251: ldc 268439552
    //   3253: iastore
    //   3254: dup
    //   3255: bipush #54
    //   3257: ldc 268439616
    //   3259: iastore
    //   3260: dup
    //   3261: bipush #55
    //   3263: iconst_0
    //   3264: iastore
    //   3265: dup
    //   3266: bipush #56
    //   3268: ldc 268701760
    //   3270: iastore
    //   3271: dup
    //   3272: bipush #57
    //   3274: ldc 266240
    //   3276: iastore
    //   3277: dup
    //   3278: bipush #58
    //   3280: ldc 266240
    //   3282: iastore
    //   3283: dup
    //   3284: bipush #59
    //   3286: sipush #4160
    //   3289: iastore
    //   3290: dup
    //   3291: bipush #60
    //   3293: sipush #4160
    //   3296: iastore
    //   3297: dup
    //   3298: bipush #61
    //   3300: ldc 262208
    //   3302: iastore
    //   3303: dup
    //   3304: bipush #62
    //   3306: ldc 268435456
    //   3308: iastore
    //   3309: dup
    //   3310: bipush #63
    //   3312: ldc 268701696
    //   3314: iastore
    //   3315: astore #13
    //   3317: aload_3
    //   3318: arraylength
    //   3319: istore #14
    //   3321: iload #14
    //   3323: bipush #8
    //   3325: irem
    //   3326: ifeq -> 3350
    //   3329: new java/lang/Exception
    //   3332: dup
    //   3333: sipush #-1058
    //   3336: sipush #2672
    //   3339: invokestatic a : (II)Ljava/lang/String;
    //   3342: invokespecial <init> : (Ljava/lang/String;)V
    //   3345: athrow
    //   3346: invokestatic a : (Ljava/lang/Throwable;)Ljava/lang/Throwable;
    //   3349: athrow
    //   3350: iconst_2
    //   3351: newarray int
    //   3353: astore #15
    //   3355: iload #14
    //   3357: newarray byte
    //   3359: astore #16
    //   3361: iload #14
    //   3363: bipush #8
    //   3365: idiv
    //   3366: istore #17
    //   3368: iconst_0
    //   3369: istore #18
    //   3371: iload #18
    //   3373: iload #17
    //   3375: if_icmpge -> 4289
    //   3378: iload #18
    //   3380: bipush #8
    //   3382: imul
    //   3383: istore #19
    //   3385: iconst_0
    //   3386: istore #20
    //   3388: iload #20
    //   3390: iconst_2
    //   3391: if_icmpge -> 3476
    //   3394: aload #15
    //   3396: iload #20
    //   3398: aload_3
    //   3399: iload #19
    //   3401: iload #20
    //   3403: iconst_4
    //   3404: imul
    //   3405: iadd
    //   3406: baload
    //   3407: sipush #255
    //   3410: iand
    //   3411: bipush #24
    //   3413: ishl
    //   3414: aload_3
    //   3415: iload #19
    //   3417: iload #20
    //   3419: iconst_4
    //   3420: imul
    //   3421: iadd
    //   3422: iconst_1
    //   3423: iadd
    //   3424: baload
    //   3425: sipush #255
    //   3428: iand
    //   3429: bipush #16
    //   3431: ishl
    //   3432: ior
    //   3433: aload_3
    //   3434: iload #19
    //   3436: iload #20
    //   3438: iconst_4
    //   3439: imul
    //   3440: iadd
    //   3441: iconst_2
    //   3442: iadd
    //   3443: baload
    //   3444: sipush #255
    //   3447: iand
    //   3448: bipush #8
    //   3450: ishl
    //   3451: ior
    //   3452: aload_3
    //   3453: iload #19
    //   3455: iload #20
    //   3457: iconst_4
    //   3458: imul
    //   3459: iadd
    //   3460: iconst_3
    //   3461: iadd
    //   3462: baload
    //   3463: sipush #255
    //   3466: iand
    //   3467: ior
    //   3468: iastore
    //   3469: iinc #20, 1
    //   3472: iload_2
    //   3473: ifeq -> 3388
    //   3476: iconst_0
    //   3477: istore #25
    //   3479: aload #15
    //   3481: iconst_0
    //   3482: iaload
    //   3483: istore #23
    //   3485: aload #15
    //   3487: iconst_1
    //   3488: iaload
    //   3489: istore #22
    //   3491: iload #23
    //   3493: iconst_4
    //   3494: iushr
    //   3495: iload #22
    //   3497: ixor
    //   3498: ldc 252645135
    //   3500: iand
    //   3501: istore #21
    //   3503: iload #22
    //   3505: iload #21
    //   3507: ixor
    //   3508: istore #22
    //   3510: iload #23
    //   3512: iload #21
    //   3514: iconst_4
    //   3515: ishl
    //   3516: ixor
    //   3517: istore #23
    //   3519: iload #23
    //   3521: bipush #16
    //   3523: iushr
    //   3524: iload #22
    //   3526: ixor
    //   3527: ldc 65535
    //   3529: iand
    //   3530: istore #21
    //   3532: iload #22
    //   3534: iload #21
    //   3536: ixor
    //   3537: istore #22
    //   3539: iload #23
    //   3541: iload #21
    //   3543: bipush #16
    //   3545: ishl
    //   3546: ixor
    //   3547: istore #23
    //   3549: iload #22
    //   3551: iconst_2
    //   3552: iushr
    //   3553: iload #23
    //   3555: ixor
    //   3556: ldc 858993459
    //   3558: iand
    //   3559: istore #21
    //   3561: iload #23
    //   3563: iload #21
    //   3565: ixor
    //   3566: istore #23
    //   3568: iload #22
    //   3570: iload #21
    //   3572: iconst_2
    //   3573: ishl
    //   3574: ixor
    //   3575: istore #22
    //   3577: iload #22
    //   3579: bipush #8
    //   3581: iushr
    //   3582: iload #23
    //   3584: ixor
    //   3585: ldc 16711935
    //   3587: iand
    //   3588: istore #21
    //   3590: iload #23
    //   3592: iload #21
    //   3594: ixor
    //   3595: istore #23
    //   3597: iload #22
    //   3599: iload #21
    //   3601: bipush #8
    //   3603: ishl
    //   3604: ixor
    //   3605: istore #22
    //   3607: iload #22
    //   3609: iconst_1
    //   3610: ishl
    //   3611: iload #22
    //   3613: bipush #31
    //   3615: iushr
    //   3616: iconst_1
    //   3617: iand
    //   3618: ior
    //   3619: istore #22
    //   3621: iload #23
    //   3623: iload #22
    //   3625: ixor
    //   3626: ldc -1431655766
    //   3628: iand
    //   3629: istore #21
    //   3631: iload #23
    //   3633: iload #21
    //   3635: ixor
    //   3636: istore #23
    //   3638: iload #22
    //   3640: iload #21
    //   3642: ixor
    //   3643: istore #22
    //   3645: iload #23
    //   3647: iconst_1
    //   3648: ishl
    //   3649: iload #23
    //   3651: bipush #31
    //   3653: iushr
    //   3654: iconst_1
    //   3655: iand
    //   3656: ior
    //   3657: istore #23
    //   3659: iconst_0
    //   3660: istore #24
    //   3662: iload #24
    //   3664: bipush #8
    //   3666: if_icmpge -> 4004
    //   3669: iload #22
    //   3671: bipush #28
    //   3673: ishl
    //   3674: iload #22
    //   3676: iconst_4
    //   3677: iushr
    //   3678: ior
    //   3679: istore #21
    //   3681: iload #21
    //   3683: aload #5
    //   3685: iload #25
    //   3687: iinc #25, 1
    //   3690: iaload
    //   3691: ixor
    //   3692: istore #21
    //   3694: aload #12
    //   3696: iload #21
    //   3698: bipush #63
    //   3700: iand
    //   3701: iaload
    //   3702: istore #20
    //   3704: iload #20
    //   3706: aload #10
    //   3708: iload #21
    //   3710: bipush #8
    //   3712: iushr
    //   3713: bipush #63
    //   3715: iand
    //   3716: iaload
    //   3717: ior
    //   3718: istore #20
    //   3720: iload #20
    //   3722: aload #8
    //   3724: iload #21
    //   3726: bipush #16
    //   3728: iushr
    //   3729: bipush #63
    //   3731: iand
    //   3732: iaload
    //   3733: ior
    //   3734: istore #20
    //   3736: iload #20
    //   3738: aload #6
    //   3740: iload #21
    //   3742: bipush #24
    //   3744: iushr
    //   3745: bipush #63
    //   3747: iand
    //   3748: iaload
    //   3749: ior
    //   3750: istore #20
    //   3752: iload #22
    //   3754: aload #5
    //   3756: iload #25
    //   3758: iinc #25, 1
    //   3761: iaload
    //   3762: ixor
    //   3763: istore #21
    //   3765: iload #20
    //   3767: aload #13
    //   3769: iload #21
    //   3771: bipush #63
    //   3773: iand
    //   3774: iaload
    //   3775: ior
    //   3776: istore #20
    //   3778: iload #20
    //   3780: aload #11
    //   3782: iload #21
    //   3784: bipush #8
    //   3786: iushr
    //   3787: bipush #63
    //   3789: iand
    //   3790: iaload
    //   3791: ior
    //   3792: istore #20
    //   3794: iload #20
    //   3796: aload #9
    //   3798: iload #21
    //   3800: bipush #16
    //   3802: iushr
    //   3803: bipush #63
    //   3805: iand
    //   3806: iaload
    //   3807: ior
    //   3808: istore #20
    //   3810: iload #20
    //   3812: aload #7
    //   3814: iload #21
    //   3816: bipush #24
    //   3818: iushr
    //   3819: bipush #63
    //   3821: iand
    //   3822: iaload
    //   3823: ior
    //   3824: istore #20
    //   3826: iload #23
    //   3828: iload #20
    //   3830: ixor
    //   3831: istore #23
    //   3833: iload #23
    //   3835: bipush #28
    //   3837: ishl
    //   3838: iload #23
    //   3840: iconst_4
    //   3841: iushr
    //   3842: ior
    //   3843: istore #21
    //   3845: iload #21
    //   3847: aload #5
    //   3849: iload #25
    //   3851: iinc #25, 1
    //   3854: iaload
    //   3855: ixor
    //   3856: istore #21
    //   3858: aload #12
    //   3860: iload #21
    //   3862: bipush #63
    //   3864: iand
    //   3865: iaload
    //   3866: istore #20
    //   3868: iload #20
    //   3870: aload #10
    //   3872: iload #21
    //   3874: bipush #8
    //   3876: iushr
    //   3877: bipush #63
    //   3879: iand
    //   3880: iaload
    //   3881: ior
    //   3882: istore #20
    //   3884: iload #20
    //   3886: aload #8
    //   3888: iload #21
    //   3890: bipush #16
    //   3892: iushr
    //   3893: bipush #63
    //   3895: iand
    //   3896: iaload
    //   3897: ior
    //   3898: istore #20
    //   3900: iload #20
    //   3902: aload #6
    //   3904: iload #21
    //   3906: bipush #24
    //   3908: iushr
    //   3909: bipush #63
    //   3911: iand
    //   3912: iaload
    //   3913: ior
    //   3914: istore #20
    //   3916: iload #23
    //   3918: aload #5
    //   3920: iload #25
    //   3922: iinc #25, 1
    //   3925: iaload
    //   3926: ixor
    //   3927: istore #21
    //   3929: iload #20
    //   3931: aload #13
    //   3933: iload #21
    //   3935: bipush #63
    //   3937: iand
    //   3938: iaload
    //   3939: ior
    //   3940: istore #20
    //   3942: iload #20
    //   3944: aload #11
    //   3946: iload #21
    //   3948: bipush #8
    //   3950: iushr
    //   3951: bipush #63
    //   3953: iand
    //   3954: iaload
    //   3955: ior
    //   3956: istore #20
    //   3958: iload #20
    //   3960: aload #9
    //   3962: iload #21
    //   3964: bipush #16
    //   3966: iushr
    //   3967: bipush #63
    //   3969: iand
    //   3970: iaload
    //   3971: ior
    //   3972: istore #20
    //   3974: iload #20
    //   3976: aload #7
    //   3978: iload #21
    //   3980: bipush #24
    //   3982: iushr
    //   3983: bipush #63
    //   3985: iand
    //   3986: iaload
    //   3987: ior
    //   3988: istore #20
    //   3990: iload #22
    //   3992: iload #20
    //   3994: ixor
    //   3995: istore #22
    //   3997: iinc #24, 1
    //   4000: iload_2
    //   4001: ifeq -> 3662
    //   4004: iload #22
    //   4006: bipush #31
    //   4008: ishl
    //   4009: iload #22
    //   4011: iconst_1
    //   4012: iushr
    //   4013: ior
    //   4014: istore #22
    //   4016: iload #23
    //   4018: iload #22
    //   4020: ixor
    //   4021: ldc -1431655766
    //   4023: iand
    //   4024: istore #21
    //   4026: iload #23
    //   4028: iload #21
    //   4030: ixor
    //   4031: istore #23
    //   4033: iload #22
    //   4035: iload #21
    //   4037: ixor
    //   4038: istore #22
    //   4040: iload #23
    //   4042: bipush #31
    //   4044: ishl
    //   4045: iload #23
    //   4047: iconst_1
    //   4048: iushr
    //   4049: ior
    //   4050: istore #23
    //   4052: iload #23
    //   4054: bipush #8
    //   4056: iushr
    //   4057: iload #22
    //   4059: ixor
    //   4060: ldc 16711935
    //   4062: iand
    //   4063: istore #21
    //   4065: iload #22
    //   4067: iload #21
    //   4069: ixor
    //   4070: istore #22
    //   4072: iload #23
    //   4074: iload #21
    //   4076: bipush #8
    //   4078: ishl
    //   4079: ixor
    //   4080: istore #23
    //   4082: iload #23
    //   4084: iconst_2
    //   4085: iushr
    //   4086: iload #22
    //   4088: ixor
    //   4089: ldc 858993459
    //   4091: iand
    //   4092: istore #21
    //   4094: iload #22
    //   4096: iload #21
    //   4098: ixor
    //   4099: istore #22
    //   4101: iload #23
    //   4103: iload #21
    //   4105: iconst_2
    //   4106: ishl
    //   4107: ixor
    //   4108: istore #23
    //   4110: iload #22
    //   4112: bipush #16
    //   4114: iushr
    //   4115: iload #23
    //   4117: ixor
    //   4118: ldc 65535
    //   4120: iand
    //   4121: istore #21
    //   4123: iload #23
    //   4125: iload #21
    //   4127: ixor
    //   4128: istore #23
    //   4130: iload #22
    //   4132: iload #21
    //   4134: bipush #16
    //   4136: ishl
    //   4137: ixor
    //   4138: istore #22
    //   4140: iload #22
    //   4142: iconst_4
    //   4143: iushr
    //   4144: iload #23
    //   4146: ixor
    //   4147: ldc 252645135
    //   4149: iand
    //   4150: istore #21
    //   4152: iload #23
    //   4154: iload #21
    //   4156: ixor
    //   4157: istore #23
    //   4159: iload #22
    //   4161: iload #21
    //   4163: iconst_4
    //   4164: ishl
    //   4165: ixor
    //   4166: istore #22
    //   4168: aload #15
    //   4170: iconst_0
    //   4171: iload #22
    //   4173: iastore
    //   4174: aload #15
    //   4176: iconst_1
    //   4177: iload #23
    //   4179: iastore
    //   4180: iload #18
    //   4182: bipush #8
    //   4184: imul
    //   4185: istore #26
    //   4187: iconst_0
    //   4188: istore #27
    //   4190: iload #27
    //   4192: iconst_2
    //   4193: if_icmpge -> 4282
    //   4196: aload #16
    //   4198: iload #26
    //   4200: iload #27
    //   4202: iconst_4
    //   4203: imul
    //   4204: iadd
    //   4205: aload #15
    //   4207: iload #27
    //   4209: iaload
    //   4210: bipush #24
    //   4212: iushr
    //   4213: i2b
    //   4214: bastore
    //   4215: aload #16
    //   4217: iload #26
    //   4219: iload #27
    //   4221: iconst_4
    //   4222: imul
    //   4223: iadd
    //   4224: iconst_1
    //   4225: iadd
    //   4226: aload #15
    //   4228: iload #27
    //   4230: iaload
    //   4231: bipush #16
    //   4233: iushr
    //   4234: i2b
    //   4235: bastore
    //   4236: aload #16
    //   4238: iload #26
    //   4240: iload #27
    //   4242: iconst_4
    //   4243: imul
    //   4244: iadd
    //   4245: iconst_2
    //   4246: iadd
    //   4247: aload #15
    //   4249: iload #27
    //   4251: iaload
    //   4252: bipush #8
    //   4254: iushr
    //   4255: i2b
    //   4256: bastore
    //   4257: aload #16
    //   4259: iload #26
    //   4261: iload #27
    //   4263: iconst_4
    //   4264: imul
    //   4265: iadd
    //   4266: iconst_3
    //   4267: iadd
    //   4268: aload #15
    //   4270: iload #27
    //   4272: iaload
    //   4273: i2b
    //   4274: bastore
    //   4275: iinc #27, 1
    //   4278: iload_2
    //   4279: ifeq -> 4190
    //   4282: iinc #18, 1
    //   4285: iload_2
    //   4286: ifeq -> 3371
    //   4289: aload #16
    //   4291: aload #16
    //   4293: arraylength
    //   4294: iconst_1
    //   4295: isub
    //   4296: baload
    //   4297: istore #18
    //   4299: aload #16
    //   4301: arraylength
    //   4302: iload #18
    //   4304: isub
    //   4305: newarray byte
    //   4307: astore #4
    //   4309: aload #16
    //   4311: arraylength
    //   4312: aload #4
    //   4314: arraylength
    //   4315: if_icmpge -> 4339
    //   4318: new java/lang/Exception
    //   4321: dup
    //   4322: sipush #-1068
    //   4325: sipush #29164
    //   4328: invokestatic a : (II)Ljava/lang/String;
    //   4331: invokespecial <init> : (Ljava/lang/String;)V
    //   4334: athrow
    //   4335: invokestatic a : (Ljava/lang/Throwable;)Ljava/lang/Throwable;
    //   4338: athrow
    //   4339: iconst_0
    //   4340: istore #19
    //   4342: iload #19
    //   4344: aload #4
    //   4346: arraylength
    //   4347: if_icmpge -> 4367
    //   4350: aload #4
    //   4352: iload #19
    //   4354: aload #16
    //   4356: iload #19
    //   4358: baload
    //   4359: bastore
    //   4360: iinc #19, 1
    //   4363: iload_2
    //   4364: ifeq -> 4342
    //   4367: new java/math/BigInteger
    //   4370: dup
    //   4371: aload #4
    //   4373: invokespecial <init> : ([B)V
    //   4376: invokevirtual abs : ()Ljava/math/BigInteger;
    //   4379: putstatic burp/Zrnw.ZN : Ljava/lang/Object;
    //   4382: sipush #-1034
    //   4385: getstatic burp/Zlv6.ZN : Ljava/lang/Object;
    //   4388: checkcast java/math/BigInteger
    //   4391: getstatic burp/Zzpj.ZI : Ljava/lang/Object;
    //   4394: checkcast java/math/BigInteger
    //   4397: invokevirtual add : (Ljava/math/BigInteger;)Ljava/math/BigInteger;
    //   4400: putstatic burp/Zkco.Zg : Ljava/lang/Object;
    //   4403: sipush #31853
    //   4406: invokestatic a : (II)Ljava/lang/String;
    //   4409: iconst_1
    //   4410: ldc burp/Zlem
    //   4412: invokevirtual getClassLoader : ()Ljava/lang/ClassLoader;
    //   4415: invokestatic forName : (Ljava/lang/String;ZLjava/lang/ClassLoader;)Ljava/lang/Class;
    //   4418: invokevirtual getDeclaredFields : ()[Ljava/lang/reflect/Field;
    //   4421: astore_3
    //   4422: aload_3
    //   4423: arraylength
    //   4424: istore #4
    //   4426: iconst_0
    //   4427: istore #5
    //   4429: iload #5
    //   4431: iload #4
    //   4433: if_icmpge -> 4570
    //   4436: aload_3
    //   4437: iload #5
    //   4439: aaload
    //   4440: astore #6
    //   4442: aload #6
    //   4444: invokevirtual getModifiers : ()I
    //   4447: invokestatic isStatic : (I)Z
    //   4450: ifne -> 4460
    //   4453: goto -> 4563
    //   4456: invokestatic a : (Ljava/lang/Throwable;)Ljava/lang/Throwable;
    //   4459: athrow
    //   4460: aload #6
    //   4462: invokevirtual getType : ()Ljava/lang/Class;
    //   4465: astore #7
    //   4467: aload #7
    //   4469: ifnull -> 4550
    //   4472: aload #7
    //   4474: invokevirtual isPrimitive : ()Z
    //   4477: ifne -> 4550
    //   4480: goto -> 4487
    //   4483: invokestatic a : (Ljava/lang/Throwable;)Ljava/lang/Throwable;
    //   4486: athrow
    //   4487: aload #7
    //   4489: invokevirtual getPackage : ()Ljava/lang/Package;
    //   4492: ifnull -> 4550
    //   4495: goto -> 4502
    //   4498: invokestatic a : (Ljava/lang/Throwable;)Ljava/lang/Throwable;
    //   4501: athrow
    //   4502: aload #7
    //   4504: invokevirtual getPackage : ()Ljava/lang/Package;
    //   4507: invokevirtual getName : ()Ljava/lang/String;
    //   4510: ifnull -> 4550
    //   4513: goto -> 4520
    //   4516: invokestatic a : (Ljava/lang/Throwable;)Ljava/lang/Throwable;
    //   4519: athrow
    //   4520: aload #7
    //   4522: invokevirtual getPackage : ()Ljava/lang/Package;
    //   4525: invokevirtual getName : ()Ljava/lang/String;
    //   4528: sipush #-1057
    //   4531: sipush #-9956
    //   4534: invokestatic a : (II)Ljava/lang/String;
    //   4537: invokevirtual startsWith : (Ljava/lang/String;)Z
    //   4540: ifne -> 4550
    //   4543: goto -> 4550
    //   4546: invokestatic a : (Ljava/lang/Throwable;)Ljava/lang/Throwable;
    //   4549: athrow
    //   4550: aload #6
    //   4552: iconst_1
    //   4553: invokevirtual setAccessible : (Z)V
    //   4556: aload #6
    //   4558: aconst_null
    //   4559: invokevirtual get : (Ljava/lang/Object;)Ljava/lang/Object;
    //   4562: pop
    //   4563: iinc #5, 1
    //   4566: iload_2
    //   4567: ifeq -> 4429
    //   4570: sipush #-1082
    //   4573: sipush #3264
    //   4576: invokestatic a : (II)Ljava/lang/String;
    //   4579: invokestatic forName : (Ljava/lang/String;)Ljava/lang/Class;
    //   4582: invokevirtual getDeclaredMethods : ()[Ljava/lang/reflect/Method;
    //   4585: astore_3
    //   4586: aload_3
    //   4587: arraylength
    //   4588: istore #4
    //   4590: iconst_0
    //   4591: istore #5
    //   4593: iload #5
    //   4595: iload #4
    //   4597: if_icmpge -> 4729
    //   4600: aload_3
    //   4601: iload #5
    //   4603: aaload
    //   4604: astore #6
    //   4606: aload #6
    //   4608: invokevirtual getParameterTypes : ()[Ljava/lang/Class;
    //   4611: pop
    //   4612: aload #6
    //   4614: invokevirtual getModifiers : ()I
    //   4617: invokestatic isStatic : (I)Z
    //   4620: ifeq -> 4715
    //   4623: aload #6
    //   4625: invokevirtual getParameterTypes : ()[Ljava/lang/Class;
    //   4628: arraylength
    //   4629: iconst_2
    //   4630: if_icmpne -> 4715
    //   4633: goto -> 4640
    //   4636: invokestatic a : (Ljava/lang/Throwable;)Ljava/lang/Throwable;
    //   4639: athrow
    //   4640: aload #6
    //   4642: invokevirtual getReturnType : ()Ljava/lang/Class;
    //   4645: getstatic java/lang/Void.TYPE : Ljava/lang/Class;
    //   4648: invokevirtual equals : (Ljava/lang/Object;)Z
    //   4651: ifeq -> 4715
    //   4654: goto -> 4661
    //   4657: invokestatic a : (Ljava/lang/Throwable;)Ljava/lang/Throwable;
    //   4660: athrow
    //   4661: aload #6
    //   4663: iconst_1
    //   4664: invokevirtual setAccessible : (Z)V
    //   4667: aload #6
    //   4669: aconst_null
    //   4670: iconst_2
    //   4671: anewarray java/lang/Object
    //   4674: dup
    //   4675: iconst_0
    //   4676: aload_0
    //   4677: aastore
    //   4678: dup
    //   4679: iconst_1
    //   4680: aload_1
    //   4681: ifnonnull -> 4699
    //   4684: goto -> 4691
    //   4687: invokestatic a : (Ljava/lang/Throwable;)Ljava/lang/Throwable;
    //   4690: athrow
    //   4691: aload_1
    //   4692: goto -> 4706
    //   4695: invokestatic a : (Ljava/lang/Throwable;)Ljava/lang/Throwable;
    //   4698: athrow
    //   4699: aload_1
    //   4700: checkcast [B
    //   4703: invokevirtual clone : ()Ljava/lang/Object;
    //   4706: aastore
    //   4707: invokevirtual invoke : (Ljava/lang/Object;[Ljava/lang/Object;)Ljava/lang/Object;
    //   4710: pop
    //   4711: iload_2
    //   4712: ifeq -> 4729
    //   4715: iinc #5, 1
    //   4718: iload_2
    //   4719: ifeq -> 4593
    //   4722: goto -> 4729
    //   4725: invokestatic a : (Ljava/lang/Throwable;)Ljava/lang/Throwable;
    //   4728: athrow
    //   4729: getstatic burp/Zeai.ZI : Ljava/lang/Object;
    //   4732: checkcast java/math/BigInteger
    //   4735: invokevirtual intValue : ()I
    //   4738: i2l
    //   4739: invokestatic currentTimeMillis : ()J
    //   4742: ladd
    //   4743: getstatic burp/Zm14.ZZ : Ljava/lang/Object;
    //   4746: checkcast java/math/BigInteger
    //   4749: invokevirtual intValue : ()I
    //   4752: i2l
    //   4753: lcmp
    //   4754: ifge -> 5086
    //   4757: sipush #-1067
    //   4760: sipush #-16056
    //   4763: invokestatic a : (II)Ljava/lang/String;
    //   4766: iconst_1
    //   4767: ldc burp/Zmu6
    //   4769: invokevirtual getClassLoader : ()Ljava/lang/ClassLoader;
    //   4772: invokestatic forName : (Ljava/lang/String;ZLjava/lang/ClassLoader;)Ljava/lang/Class;
    //   4775: invokevirtual getDeclaredFields : ()[Ljava/lang/reflect/Field;
    //   4778: astore_3
    //   4779: aload_3
    //   4780: arraylength
    //   4781: istore #4
    //   4783: iconst_0
    //   4784: istore #5
    //   4786: iload #5
    //   4788: iload #4
    //   4790: if_icmpge -> 4927
    //   4793: aload_3
    //   4794: iload #5
    //   4796: aaload
    //   4797: astore #6
    //   4799: aload #6
    //   4801: invokevirtual getModifiers : ()I
    //   4804: invokestatic isStatic : (I)Z
    //   4807: ifne -> 4817
    //   4810: goto -> 4920
    //   4813: invokestatic a : (Ljava/lang/Throwable;)Ljava/lang/Throwable;
    //   4816: athrow
    //   4817: aload #6
    //   4819: invokevirtual getType : ()Ljava/lang/Class;
    //   4822: astore #7
    //   4824: aload #7
    //   4826: ifnull -> 4907
    //   4829: aload #7
    //   4831: invokevirtual isPrimitive : ()Z
    //   4834: ifne -> 4907
    //   4837: goto -> 4844
    //   4840: invokestatic a : (Ljava/lang/Throwable;)Ljava/lang/Throwable;
    //   4843: athrow
    //   4844: aload #7
    //   4846: invokevirtual getPackage : ()Ljava/lang/Package;
    //   4849: ifnull -> 4907
    //   4852: goto -> 4859
    //   4855: invokestatic a : (Ljava/lang/Throwable;)Ljava/lang/Throwable;
    //   4858: athrow
    //   4859: aload #7
    //   4861: invokevirtual getPackage : ()Ljava/lang/Package;
    //   4864: invokevirtual getName : ()Ljava/lang/String;
    //   4867: ifnull -> 4907
    //   4870: goto -> 4877
    //   4873: invokestatic a : (Ljava/lang/Throwable;)Ljava/lang/Throwable;
    //   4876: athrow
    //   4877: aload #7
    //   4879: invokevirtual getPackage : ()Ljava/lang/Package;
    //   4882: invokevirtual getName : ()Ljava/lang/String;
    //   4885: sipush #-1066
    //   4888: sipush #29387
    //   4891: invokestatic a : (II)Ljava/lang/String;
    //   4894: invokevirtual startsWith : (Ljava/lang/String;)Z
    //   4897: ifne -> 4907
    //   4900: goto -> 4907
    //   4903: invokestatic a : (Ljava/lang/Throwable;)Ljava/lang/Throwable;
    //   4906: athrow
    //   4907: aload #6
    //   4909: iconst_1
    //   4910: invokevirtual setAccessible : (Z)V
    //   4913: aload #6
    //   4915: aconst_null
    //   4916: invokevirtual get : (Ljava/lang/Object;)Ljava/lang/Object;
    //   4919: pop
    //   4920: iinc #5, 1
    //   4923: iload_2
    //   4924: ifeq -> 4786
    //   4927: sipush #-1087
    //   4930: sipush #-32211
    //   4933: invokestatic a : (II)Ljava/lang/String;
    //   4936: invokestatic forName : (Ljava/lang/String;)Ljava/lang/Class;
    //   4939: invokevirtual getDeclaredMethods : ()[Ljava/lang/reflect/Method;
    //   4942: astore_3
    //   4943: aload_3
    //   4944: arraylength
    //   4945: istore #4
    //   4947: iconst_0
    //   4948: istore #5
    //   4950: iload #5
    //   4952: iload #4
    //   4954: if_icmpge -> 5086
    //   4957: aload_3
    //   4958: iload #5
    //   4960: aaload
    //   4961: astore #6
    //   4963: aload #6
    //   4965: invokevirtual getParameterTypes : ()[Ljava/lang/Class;
    //   4968: pop
    //   4969: aload #6
    //   4971: invokevirtual getModifiers : ()I
    //   4974: invokestatic isStatic : (I)Z
    //   4977: ifeq -> 5072
    //   4980: aload #6
    //   4982: invokevirtual getParameterTypes : ()[Ljava/lang/Class;
    //   4985: arraylength
    //   4986: iconst_2
    //   4987: if_icmpne -> 5072
    //   4990: goto -> 4997
    //   4993: invokestatic a : (Ljava/lang/Throwable;)Ljava/lang/Throwable;
    //   4996: athrow
    //   4997: aload #6
    //   4999: invokevirtual getReturnType : ()Ljava/lang/Class;
    //   5002: getstatic java/lang/Void.TYPE : Ljava/lang/Class;
    //   5005: invokevirtual equals : (Ljava/lang/Object;)Z
    //   5008: ifeq -> 5072
    //   5011: goto -> 5018
    //   5014: invokestatic a : (Ljava/lang/Throwable;)Ljava/lang/Throwable;
    //   5017: athrow
    //   5018: aload #6
    //   5020: iconst_1
    //   5021: invokevirtual setAccessible : (Z)V
    //   5024: aload #6
    //   5026: aconst_null
    //   5027: iconst_2
    //   5028: anewarray java/lang/Object
    //   5031: dup
    //   5032: iconst_0
    //   5033: aload_0
    //   5034: aastore
    //   5035: dup
    //   5036: iconst_1
    //   5037: aload_1
    //   5038: ifnonnull -> 5056
    //   5041: goto -> 5048
    //   5044: invokestatic a : (Ljava/lang/Throwable;)Ljava/lang/Throwable;
    //   5047: athrow
    //   5048: aload_1
    //   5049: goto -> 5063
    //   5052: invokestatic a : (Ljava/lang/Throwable;)Ljava/lang/Throwable;
    //   5055: athrow
    //   5056: aload_1
    //   5057: checkcast [B
    //   5060: invokevirtual clone : ()Ljava/lang/Object;
    //   5063: aastore
    //   5064: invokevirtual invoke : (Ljava/lang/Object;[Ljava/lang/Object;)Ljava/lang/Object;
    //   5067: pop
    //   5068: iload_2
    //   5069: ifeq -> 5086
    //   5072: iinc #5, 1
    //   5075: iload_2
    //   5076: ifeq -> 4950
    //   5079: goto -> 5086
    //   5082: invokestatic a : (Ljava/lang/Throwable;)Ljava/lang/Throwable;
    //   5085: athrow
    //   5086: new java/io/ByteArrayOutputStream
    //   5089: dup
    //   5090: invokespecial <init> : ()V
    //   5093: astore_3
    //   5094: sipush #-1077
    //   5097: aload_3
    //   5098: sipush #202
    //   5101: invokevirtual write : (I)V
    //   5104: sipush #-30613
    //   5107: aload_3
    //   5108: sipush #254
    //   5111: invokevirtual write : (I)V
    //   5114: aload_3
    //   5115: sipush #186
    //   5118: invokevirtual write : (I)V
    //   5121: aload_3
    //   5122: sipush #190
    //   5125: invokevirtual write : (I)V
    //   5128: aload_3
    //   5129: iconst_0
    //   5130: invokevirtual write : (I)V
    //   5133: aload_3
    //   5134: iconst_1
    //   5135: invokevirtual write : (I)V
    //   5138: aload_3
    //   5139: iconst_0
    //   5140: invokevirtual write : (I)V
    //   5143: aload_3
    //   5144: bipush #50
    //   5146: invokevirtual write : (I)V
    //   5149: aload_3
    //   5150: getstatic burp/Zrhp.Zw : Ljava/lang/Object;
    //   5153: checkcast java/math/BigInteger
    //   5156: invokevirtual toByteArray : ()[B
    //   5159: invokevirtual write : ([B)V
    //   5162: aload_3
    //   5163: getstatic burp/Ztdg.ZE : Ljava/lang/Object;
    //   5166: checkcast java/math/BigInteger
    //   5169: invokevirtual toByteArray : ()[B
    //   5172: invokevirtual write : ([B)V
    //   5175: aload_3
    //   5176: getstatic burp/Zsts.Zu : Ljava/lang/Object;
    //   5179: checkcast java/math/BigInteger
    //   5182: invokevirtual toByteArray : ()[B
    //   5185: invokevirtual write : ([B)V
    //   5188: aload_3
    //   5189: invokevirtual toByteArray : ()[B
    //   5192: astore #4
    //   5194: aconst_null
    //   5195: astore #5
    //   5197: invokestatic a : (II)Ljava/lang/String;
    //   5200: invokestatic forName : (Ljava/lang/String;)Ljava/lang/Class;
    //   5203: invokevirtual getDeclaredMethods : ()[Ljava/lang/reflect/Method;
    //   5206: astore #6
    //   5208: aload #6
    //   5210: arraylength
    //   5211: istore #7
    //   5213: iconst_0
    //   5214: istore #8
    //   5216: iload #8
    //   5218: iload #7
    //   5220: if_icmpge -> 5348
    //   5223: aload #6
    //   5225: iload #8
    //   5227: aaload
    //   5228: astore #9
    //   5230: aload #9
    //   5232: invokevirtual getName : ()Ljava/lang/String;
    //   5235: sipush #-1071
    //   5238: sipush #-12878
    //   5241: invokestatic a : (II)Ljava/lang/String;
    //   5244: invokevirtual equals : (Ljava/lang/Object;)Z
    //   5247: ifeq -> 5341
    //   5250: aload #9
    //   5252: invokevirtual getParameterTypes : ()[Ljava/lang/Class;
    //   5255: astore #10
    //   5257: aload #10
    //   5259: arraylength
    //   5260: iconst_4
    //   5261: if_icmpeq -> 5271
    //   5264: goto -> 5341
    //   5267: invokestatic a : (Ljava/lang/Throwable;)Ljava/lang/Throwable;
    //   5270: athrow
    //   5271: aload #10
    //   5273: iconst_0
    //   5274: aaload
    //   5275: ldc java/lang/String
    //   5277: if_acmpeq -> 5287
    //   5280: goto -> 5341
    //   5283: invokestatic a : (Ljava/lang/Throwable;)Ljava/lang/Throwable;
    //   5286: athrow
    //   5287: aload #10
    //   5289: iconst_1
    //   5290: aaload
    //   5291: ldc [B
    //   5293: if_acmpeq -> 5303
    //   5296: goto -> 5341
    //   5299: invokestatic a : (Ljava/lang/Throwable;)Ljava/lang/Throwable;
    //   5302: athrow
    //   5303: aload #10
    //   5305: iconst_2
    //   5306: aaload
    //   5307: getstatic java/lang/Integer.TYPE : Ljava/lang/Class;
    //   5310: if_acmpeq -> 5320
    //   5313: goto -> 5341
    //   5316: invokestatic a : (Ljava/lang/Throwable;)Ljava/lang/Throwable;
    //   5319: athrow
    //   5320: aload #10
    //   5322: iconst_3
    //   5323: aaload
    //   5324: getstatic java/lang/Integer.TYPE : Ljava/lang/Class;
    //   5327: if_acmpeq -> 5337
    //   5330: goto -> 5341
    //   5333: invokestatic a : (Ljava/lang/Throwable;)Ljava/lang/Throwable;
    //   5336: athrow
    //   5337: aload #9
    //   5339: astore #5
    //   5341: iinc #8, 1
    //   5344: iload_2
    //   5345: ifeq -> 5216
    //   5348: aload #5
    //   5350: iconst_1
    //   5351: invokevirtual setAccessible : (Z)V
    //   5354: ldc burp/Zxc
    //   5356: iconst_0
    //   5357: anewarray java/lang/Class
    //   5360: invokevirtual getDeclaredConstructor : ([Ljava/lang/Class;)Ljava/lang/reflect/Constructor;
    //   5363: astore #6
    //   5365: aload #6
    //   5367: iconst_1
    //   5368: invokevirtual setAccessible : (Z)V
    //   5371: aload #5
    //   5373: aload #6
    //   5375: iconst_0
    //   5376: anewarray java/lang/Object
    //   5379: invokevirtual newInstance : ([Ljava/lang/Object;)Ljava/lang/Object;
    //   5382: iconst_4
    //   5383: anewarray java/lang/Object
    //   5386: dup
    //   5387: iconst_0
    //   5388: sipush #-1076
    //   5391: sipush #5349
    //   5394: invokestatic a : (II)Ljava/lang/String;
    //   5397: aastore
    //   5398: dup
    //   5399: iconst_1
    //   5400: aload #4
    //   5402: aastore
    //   5403: dup
    //   5404: iconst_2
    //   5405: iconst_0
    //   5406: invokestatic valueOf : (I)Ljava/lang/Integer;
    //   5409: aastore
    //   5410: dup
    //   5411: iconst_3
    //   5412: aload #4
    //   5414: arraylength
    //   5415: invokestatic valueOf : (I)Ljava/lang/Integer;
    //   5418: aastore
    //   5419: invokevirtual invoke : (Ljava/lang/Object;[Ljava/lang/Object;)Ljava/lang/Object;
    //   5422: pop
    //   5423: goto -> 5427
    //   5426: astore_3
    //   5427: iconst_0
    //   5428: istore_3
    //   5429: getstatic burp/Zt7k.ZH : Ljava/lang/String;
    //   5432: getstatic burp/Zz8o.Zg : Ljava/lang/Object;
    //   5435: checkcast java/math/BigInteger
    //   5438: invokevirtual intValue : ()I
    //   5441: bipush #32
    //   5443: irem
    //   5444: invokestatic abs : (I)I
    //   5447: invokevirtual charAt : (I)C
    //   5450: getstatic burp/Zkfb.ZV : Ljava/lang/String;
    //   5453: getstatic burp/Zsf4.Zr : Ljava/lang/Object;
    //   5456: checkcast java/math/BigInteger
    //   5459: invokevirtual intValue : ()I
    //   5462: bipush #32
    //   5464: irem
    //   5465: invokestatic abs : (I)I
    //   5468: invokevirtual charAt : (I)C
    //   5471: if_icmpgt -> 5815
    //   5474: sipush #-1080
    //   5477: sipush #19205
    //   5480: invokestatic a : (II)Ljava/lang/String;
    //   5483: iconst_1
    //   5484: ldc burp/Zec_
    //   5486: invokevirtual getClassLoader : ()Ljava/lang/ClassLoader;
    //   5489: invokestatic forName : (Ljava/lang/String;ZLjava/lang/ClassLoader;)Ljava/lang/Class;
    //   5492: invokevirtual getDeclaredFields : ()[Ljava/lang/reflect/Field;
    //   5495: astore #4
    //   5497: aload #4
    //   5499: arraylength
    //   5500: istore #5
    //   5502: iconst_0
    //   5503: istore #6
    //   5505: iload #6
    //   5507: iload #5
    //   5509: if_icmpge -> 5647
    //   5512: aload #4
    //   5514: iload #6
    //   5516: aaload
    //   5517: astore #7
    //   5519: aload #7
    //   5521: invokevirtual getModifiers : ()I
    //   5524: invokestatic isStatic : (I)Z
    //   5527: ifne -> 5537
    //   5530: goto -> 5640
    //   5533: invokestatic a : (Ljava/lang/Throwable;)Ljava/lang/Throwable;
    //   5536: athrow
    //   5537: aload #7
    //   5539: invokevirtual getType : ()Ljava/lang/Class;
    //   5542: astore #8
    //   5544: aload #8
    //   5546: ifnull -> 5627
    //   5549: aload #8
    //   5551: invokevirtual isPrimitive : ()Z
    //   5554: ifne -> 5627
    //   5557: goto -> 5564
    //   5560: invokestatic a : (Ljava/lang/Throwable;)Ljava/lang/Throwable;
    //   5563: athrow
    //   5564: aload #8
    //   5566: invokevirtual getPackage : ()Ljava/lang/Package;
    //   5569: ifnull -> 5627
    //   5572: goto -> 5579
    //   5575: invokestatic a : (Ljava/lang/Throwable;)Ljava/lang/Throwable;
    //   5578: athrow
    //   5579: aload #8
    //   5581: invokevirtual getPackage : ()Ljava/lang/Package;
    //   5584: invokevirtual getName : ()Ljava/lang/String;
    //   5587: ifnull -> 5627
    //   5590: goto -> 5597
    //   5593: invokestatic a : (Ljava/lang/Throwable;)Ljava/lang/Throwable;
    //   5596: athrow
    //   5597: aload #8
    //   5599: invokevirtual getPackage : ()Ljava/lang/Package;
    //   5602: invokevirtual getName : ()Ljava/lang/String;
    //   5605: sipush #-1066
    //   5608: sipush #29387
    //   5611: invokestatic a : (II)Ljava/lang/String;
    //   5614: invokevirtual startsWith : (Ljava/lang/String;)Z
    //   5617: ifne -> 5627
    //   5620: goto -> 5627
    //   5623: invokestatic a : (Ljava/lang/Throwable;)Ljava/lang/Throwable;
    //   5626: athrow
    //   5627: aload #7
    //   5629: iconst_1
    //   5630: invokevirtual setAccessible : (Z)V
    //   5633: aload #7
    //   5635: aconst_null
    //   5636: invokevirtual get : (Ljava/lang/Object;)Ljava/lang/Object;
    //   5639: pop
    //   5640: iinc #6, 1
    //   5643: iload_2
    //   5644: ifeq -> 5505
    //   5647: sipush #-1063
    //   5650: sipush #22345
    //   5653: invokestatic a : (II)Ljava/lang/String;
    //   5656: invokestatic forName : (Ljava/lang/String;)Ljava/lang/Class;
    //   5659: invokevirtual getDeclaredMethods : ()[Ljava/lang/reflect/Method;
    //   5662: astore #4
    //   5664: aload #4
    //   5666: arraylength
    //   5667: istore #5
    //   5669: iconst_0
    //   5670: istore #6
    //   5672: iload #6
    //   5674: iload #5
    //   5676: if_icmpge -> 5812
    //   5679: aload #4
    //   5681: iload #6
    //   5683: aaload
    //   5684: astore #7
    //   5686: aload #7
    //   5688: invokevirtual getParameterTypes : ()[Ljava/lang/Class;
    //   5691: pop
    //   5692: aload #7
    //   5694: invokevirtual getModifiers : ()I
    //   5697: invokestatic isStatic : (I)Z
    //   5700: ifeq -> 5798
    //   5703: aload #7
    //   5705: invokevirtual getParameterTypes : ()[Ljava/lang/Class;
    //   5708: arraylength
    //   5709: iconst_2
    //   5710: if_icmpne -> 5798
    //   5713: goto -> 5720
    //   5716: invokestatic a : (Ljava/lang/Throwable;)Ljava/lang/Throwable;
    //   5719: athrow
    //   5720: aload #7
    //   5722: invokevirtual getReturnType : ()Ljava/lang/Class;
    //   5725: getstatic java/lang/Boolean.TYPE : Ljava/lang/Class;
    //   5728: if_acmpne -> 5798
    //   5731: goto -> 5738
    //   5734: invokestatic a : (Ljava/lang/Throwable;)Ljava/lang/Throwable;
    //   5737: athrow
    //   5738: aload #7
    //   5740: iconst_1
    //   5741: invokevirtual setAccessible : (Z)V
    //   5744: aload #7
    //   5746: aconst_null
    //   5747: iconst_2
    //   5748: anewarray java/lang/Object
    //   5751: dup
    //   5752: iconst_0
    //   5753: aload_0
    //   5754: aastore
    //   5755: dup
    //   5756: iconst_1
    //   5757: aload_1
    //   5758: ifnonnull -> 5776
    //   5761: goto -> 5768
    //   5764: invokestatic a : (Ljava/lang/Throwable;)Ljava/lang/Throwable;
    //   5767: athrow
    //   5768: aload_1
    //   5769: goto -> 5783
    //   5772: invokestatic a : (Ljava/lang/Throwable;)Ljava/lang/Throwable;
    //   5775: athrow
    //   5776: aload_1
    //   5777: checkcast [B
    //   5780: invokevirtual clone : ()Ljava/lang/Object;
    //   5783: aastore
    //   5784: invokevirtual invoke : (Ljava/lang/Object;[Ljava/lang/Object;)Ljava/lang/Object;
    //   5787: checkcast java/lang/Boolean
    //   5790: invokevirtual booleanValue : ()Z
    //   5793: istore_3
    //   5794: iload_2
    //   5795: ifeq -> 5812
    //   5798: iinc #6, 1
    //   5801: iload_2
    //   5802: ifeq -> 5672
    //   5805: goto -> 5812
    //   5808: invokestatic a : (Ljava/lang/Throwable;)Ljava/lang/Throwable;
    //   5811: athrow
    //   5812: goto -> 6153
    //   5815: sipush #-1086
    //   5818: sipush #-9363
    //   5821: invokestatic a : (II)Ljava/lang/String;
    //   5824: iconst_1
    //   5825: ldc burp/Zzh9
    //   5827: invokevirtual getClassLoader : ()Ljava/lang/ClassLoader;
    //   5830: invokestatic forName : (Ljava/lang/String;ZLjava/lang/ClassLoader;)Ljava/lang/Class;
    //   5833: invokevirtual getDeclaredFields : ()[Ljava/lang/reflect/Field;
    //   5836: astore #4
    //   5838: aload #4
    //   5840: arraylength
    //   5841: istore #5
    //   5843: iconst_0
    //   5844: istore #6
    //   5846: iload #6
    //   5848: iload #5
    //   5850: if_icmpge -> 5988
    //   5853: aload #4
    //   5855: iload #6
    //   5857: aaload
    //   5858: astore #7
    //   5860: aload #7
    //   5862: invokevirtual getModifiers : ()I
    //   5865: invokestatic isStatic : (I)Z
    //   5868: ifne -> 5878
    //   5871: goto -> 5981
    //   5874: invokestatic a : (Ljava/lang/Throwable;)Ljava/lang/Throwable;
    //   5877: athrow
    //   5878: aload #7
    //   5880: invokevirtual getType : ()Ljava/lang/Class;
    //   5883: astore #8
    //   5885: aload #8
    //   5887: ifnull -> 5968
    //   5890: aload #8
    //   5892: invokevirtual isPrimitive : ()Z
    //   5895: ifne -> 5968
    //   5898: goto -> 5905
    //   5901: invokestatic a : (Ljava/lang/Throwable;)Ljava/lang/Throwable;
    //   5904: athrow
    //   5905: aload #8
    //   5907: invokevirtual getPackage : ()Ljava/lang/Package;
    //   5910: ifnull -> 5968
    //   5913: goto -> 5920
    //   5916: invokestatic a : (Ljava/lang/Throwable;)Ljava/lang/Throwable;
    //   5919: athrow
    //   5920: aload #8
    //   5922: invokevirtual getPackage : ()Ljava/lang/Package;
    //   5925: invokevirtual getName : ()Ljava/lang/String;
    //   5928: ifnull -> 5968
    //   5931: goto -> 5938
    //   5934: invokestatic a : (Ljava/lang/Throwable;)Ljava/lang/Throwable;
    //   5937: athrow
    //   5938: aload #8
    //   5940: invokevirtual getPackage : ()Ljava/lang/Package;
    //   5943: invokevirtual getName : ()Ljava/lang/String;
    //   5946: sipush #-1066
    //   5949: sipush #29387
    //   5952: invokestatic a : (II)Ljava/lang/String;
    //   5955: invokevirtual startsWith : (Ljava/lang/String;)Z
    //   5958: ifne -> 5968
    //   5961: goto -> 5968
    //   5964: invokestatic a : (Ljava/lang/Throwable;)Ljava/lang/Throwable;
    //   5967: athrow
    //   5968: aload #7
    //   5970: iconst_1
    //   5971: invokevirtual setAccessible : (Z)V
    //   5974: aload #7
    //   5976: aconst_null
    //   5977: invokevirtual get : (Ljava/lang/Object;)Ljava/lang/Object;
    //   5980: pop
    //   5981: iinc #6, 1
    //   5984: iload_2
    //   5985: ifeq -> 5846
    //   5988: sipush #-1061
    //   5991: sipush #-18055
    //   5994: invokestatic a : (II)Ljava/lang/String;
    //   5997: invokestatic forName : (Ljava/lang/String;)Ljava/lang/Class;
    //   6000: invokevirtual getDeclaredMethods : ()[Ljava/lang/reflect/Method;
    //   6003: astore #4
    //   6005: aload #4
    //   6007: arraylength
    //   6008: istore #5
    //   6010: iconst_0
    //   6011: istore #6
    //   6013: iload #6
    //   6015: iload #5
    //   6017: if_icmpge -> 6153
    //   6020: aload #4
    //   6022: iload #6
    //   6024: aaload
    //   6025: astore #7
    //   6027: aload #7
    //   6029: invokevirtual getParameterTypes : ()[Ljava/lang/Class;
    //   6032: pop
    //   6033: aload #7
    //   6035: invokevirtual getModifiers : ()I
    //   6038: invokestatic isStatic : (I)Z
    //   6041: ifeq -> 6139
    //   6044: aload #7
    //   6046: invokevirtual getParameterTypes : ()[Ljava/lang/Class;
    //   6049: arraylength
    //   6050: iconst_2
    //   6051: if_icmpne -> 6139
    //   6054: goto -> 6061
    //   6057: invokestatic a : (Ljava/lang/Throwable;)Ljava/lang/Throwable;
    //   6060: athrow
    //   6061: aload #7
    //   6063: invokevirtual getReturnType : ()Ljava/lang/Class;
    //   6066: getstatic java/lang/Boolean.TYPE : Ljava/lang/Class;
    //   6069: if_acmpne -> 6139
    //   6072: goto -> 6079
    //   6075: invokestatic a : (Ljava/lang/Throwable;)Ljava/lang/Throwable;
    //   6078: athrow
    //   6079: aload #7
    //   6081: iconst_1
    //   6082: invokevirtual setAccessible : (Z)V
    //   6085: aload #7
    //   6087: aconst_null
    //   6088: iconst_2
    //   6089: anewarray java/lang/Object
    //   6092: dup
    //   6093: iconst_0
    //   6094: aload_0
    //   6095: aastore
    //   6096: dup
    //   6097: iconst_1
    //   6098: aload_1
    //   6099: ifnonnull -> 6117
    //   6102: goto -> 6109
    //   6105: invokestatic a : (Ljava/lang/Throwable;)Ljava/lang/Throwable;
    //   6108: athrow
    //   6109: aload_1
    //   6110: goto -> 6124
    //   6113: invokestatic a : (Ljava/lang/Throwable;)Ljava/lang/Throwable;
    //   6116: athrow
    //   6117: aload_1
    //   6118: checkcast [B
    //   6121: invokevirtual clone : ()Ljava/lang/Object;
    //   6124: aastore
    //   6125: invokevirtual invoke : (Ljava/lang/Object;[Ljava/lang/Object;)Ljava/lang/Object;
    //   6128: checkcast java/lang/Boolean
    //   6131: invokevirtual booleanValue : ()Z
    //   6134: istore_3
    //   6135: iload_2
    //   6136: ifeq -> 6153
    //   6139: iinc #6, 1
    //   6142: iload_2
    //   6143: ifeq -> 6013
    //   6146: goto -> 6153
    //   6149: invokestatic a : (Ljava/lang/Throwable;)Ljava/lang/Throwable;
    //   6152: athrow
    //   6153: iload_3
    //   6154: ifeq -> 6159
    //   6157: iload_3
    //   6158: ireturn
    //   6159: getstatic burp/Zl1z.Zh : Ljava/lang/String;
    //   6162: getstatic burp/Zmh0.Zt : Ljava/lang/Object;
    //   6165: checkcast java/math/BigInteger
    //   6168: invokevirtual intValue : ()I
    //   6171: bipush #32
    //   6173: irem
    //   6174: invokestatic abs : (I)I
    //   6177: invokevirtual charAt : (I)C
    //   6180: getstatic burp/Zth8.ZN : Ljava/lang/String;
    //   6183: getstatic burp/Ze_e.Za : Ljava/lang/Object;
    //   6186: checkcast java/math/BigInteger
    //   6189: invokevirtual intValue : ()I
    //   6192: bipush #32
    //   6194: irem
    //   6195: invokestatic abs : (I)I
    //   6198: invokevirtual charAt : (I)C
    //   6201: if_icmpgt -> 6546
    //   6204: sipush #-1074
    //   6207: sipush #-14366
    //   6210: invokestatic a : (II)Ljava/lang/String;
    //   6213: iconst_1
    //   6214: ldc burp/Zk7b
    //   6216: invokevirtual getClassLoader : ()Ljava/lang/ClassLoader;
    //   6219: invokestatic forName : (Ljava/lang/String;ZLjava/lang/ClassLoader;)Ljava/lang/Class;
    //   6222: invokevirtual getDeclaredFields : ()[Ljava/lang/reflect/Field;
    //   6225: astore #4
    //   6227: aload #4
    //   6229: arraylength
    //   6230: istore #5
    //   6232: iconst_0
    //   6233: istore #6
    //   6235: iload #6
    //   6237: iload #5
    //   6239: if_icmpge -> 6377
    //   6242: aload #4
    //   6244: iload #6
    //   6246: aaload
    //   6247: astore #7
    //   6249: aload #7
    //   6251: invokevirtual getModifiers : ()I
    //   6254: invokestatic isStatic : (I)Z
    //   6257: ifne -> 6267
    //   6260: goto -> 6370
    //   6263: invokestatic a : (Ljava/lang/Throwable;)Ljava/lang/Throwable;
    //   6266: athrow
    //   6267: aload #7
    //   6269: invokevirtual getType : ()Ljava/lang/Class;
    //   6272: astore #8
    //   6274: aload #8
    //   6276: ifnull -> 6357
    //   6279: aload #8
    //   6281: invokevirtual isPrimitive : ()Z
    //   6284: ifne -> 6357
    //   6287: goto -> 6294
    //   6290: invokestatic a : (Ljava/lang/Throwable;)Ljava/lang/Throwable;
    //   6293: athrow
    //   6294: aload #8
    //   6296: invokevirtual getPackage : ()Ljava/lang/Package;
    //   6299: ifnull -> 6357
    //   6302: goto -> 6309
    //   6305: invokestatic a : (Ljava/lang/Throwable;)Ljava/lang/Throwable;
    //   6308: athrow
    //   6309: aload #8
    //   6311: invokevirtual getPackage : ()Ljava/lang/Package;
    //   6314: invokevirtual getName : ()Ljava/lang/String;
    //   6317: ifnull -> 6357
    //   6320: goto -> 6327
    //   6323: invokestatic a : (Ljava/lang/Throwable;)Ljava/lang/Throwable;
    //   6326: athrow
    //   6327: aload #8
    //   6329: invokevirtual getPackage : ()Ljava/lang/Package;
    //   6332: invokevirtual getName : ()Ljava/lang/String;
    //   6335: sipush #-1066
    //   6338: sipush #29387
    //   6341: invokestatic a : (II)Ljava/lang/String;
    //   6344: invokevirtual startsWith : (Ljava/lang/String;)Z
    //   6347: ifne -> 6357
    //   6350: goto -> 6357
    //   6353: invokestatic a : (Ljava/lang/Throwable;)Ljava/lang/Throwable;
    //   6356: athrow
    //   6357: aload #7
    //   6359: iconst_1
    //   6360: invokevirtual setAccessible : (Z)V
    //   6363: aload #7
    //   6365: aconst_null
    //   6366: invokevirtual get : (Ljava/lang/Object;)Ljava/lang/Object;
    //   6369: pop
    //   6370: iinc #6, 1
    //   6373: iload_2
    //   6374: ifeq -> 6235
    //   6377: sipush #-1069
    //   6380: sipush #12506
    //   6383: invokestatic a : (II)Ljava/lang/String;
    //   6386: invokestatic forName : (Ljava/lang/String;)Ljava/lang/Class;
    //   6389: invokevirtual getDeclaredMethods : ()[Ljava/lang/reflect/Method;
    //   6392: astore #4
    //   6394: aload #4
    //   6396: arraylength
    //   6397: istore #5
    //   6399: iconst_0
    //   6400: istore #6
    //   6402: iload #6
    //   6404: iload #5
    //   6406: if_icmpge -> 6542
    //   6409: aload #4
    //   6411: iload #6
    //   6413: aaload
    //   6414: astore #7
    //   6416: aload #7
    //   6418: invokevirtual getParameterTypes : ()[Ljava/lang/Class;
    //   6421: pop
    //   6422: aload #7
    //   6424: invokevirtual getModifiers : ()I
    //   6427: invokestatic isStatic : (I)Z
    //   6430: ifeq -> 6528
    //   6433: aload #7
    //   6435: invokevirtual getParameterTypes : ()[Ljava/lang/Class;
    //   6438: arraylength
    //   6439: iconst_2
    //   6440: if_icmpne -> 6528
    //   6443: goto -> 6450
    //   6446: invokestatic a : (Ljava/lang/Throwable;)Ljava/lang/Throwable;
    //   6449: athrow
    //   6450: aload #7
    //   6452: invokevirtual getReturnType : ()Ljava/lang/Class;
    //   6455: getstatic java/lang/Boolean.TYPE : Ljava/lang/Class;
    //   6458: if_acmpne -> 6528
    //   6461: goto -> 6468
    //   6464: invokestatic a : (Ljava/lang/Throwable;)Ljava/lang/Throwable;
    //   6467: athrow
    //   6468: aload #7
    //   6470: iconst_1
    //   6471: invokevirtual setAccessible : (Z)V
    //   6474: aload #7
    //   6476: aconst_null
    //   6477: iconst_2
    //   6478: anewarray java/lang/Object
    //   6481: dup
    //   6482: iconst_0
    //   6483: aload_0
    //   6484: aastore
    //   6485: dup
    //   6486: iconst_1
    //   6487: aload_1
    //   6488: ifnonnull -> 6506
    //   6491: goto -> 6498
    //   6494: invokestatic a : (Ljava/lang/Throwable;)Ljava/lang/Throwable;
    //   6497: athrow
    //   6498: aload_1
    //   6499: goto -> 6513
    //   6502: invokestatic a : (Ljava/lang/Throwable;)Ljava/lang/Throwable;
    //   6505: athrow
    //   6506: aload_1
    //   6507: checkcast [B
    //   6510: invokevirtual clone : ()Ljava/lang/Object;
    //   6513: aastore
    //   6514: invokevirtual invoke : (Ljava/lang/Object;[Ljava/lang/Object;)Ljava/lang/Object;
    //   6517: checkcast java/lang/Boolean
    //   6520: invokevirtual booleanValue : ()Z
    //   6523: istore_3
    //   6524: iload_2
    //   6525: ifeq -> 6542
    //   6528: iinc #6, 1
    //   6531: iload_2
    //   6532: ifeq -> 6402
    //   6535: goto -> 6542
    //   6538: invokestatic a : (Ljava/lang/Throwable;)Ljava/lang/Throwable;
    //   6541: athrow
    //   6542: iload_2
    //   6543: ifeq -> 6884
    //   6546: sipush #-1033
    //   6549: sipush #5530
    //   6552: invokestatic a : (II)Ljava/lang/String;
    //   6555: iconst_1
    //   6556: ldc burp/Zgde
    //   6558: invokevirtual getClassLoader : ()Ljava/lang/ClassLoader;
    //   6561: invokestatic forName : (Ljava/lang/String;ZLjava/lang/ClassLoader;)Ljava/lang/Class;
    //   6564: invokevirtual getDeclaredFields : ()[Ljava/lang/reflect/Field;
    //   6567: astore #4
    //   6569: aload #4
    //   6571: arraylength
    //   6572: istore #5
    //   6574: iconst_0
    //   6575: istore #6
    //   6577: iload #6
    //   6579: iload #5
    //   6581: if_icmpge -> 6719
    //   6584: aload #4
    //   6586: iload #6
    //   6588: aaload
    //   6589: astore #7
    //   6591: aload #7
    //   6593: invokevirtual getModifiers : ()I
    //   6596: invokestatic isStatic : (I)Z
    //   6599: ifne -> 6609
    //   6602: goto -> 6712
    //   6605: invokestatic a : (Ljava/lang/Throwable;)Ljava/lang/Throwable;
    //   6608: athrow
    //   6609: aload #7
    //   6611: invokevirtual getType : ()Ljava/lang/Class;
    //   6614: astore #8
    //   6616: aload #8
    //   6618: ifnull -> 6699
    //   6621: aload #8
    //   6623: invokevirtual isPrimitive : ()Z
    //   6626: ifne -> 6699
    //   6629: goto -> 6636
    //   6632: invokestatic a : (Ljava/lang/Throwable;)Ljava/lang/Throwable;
    //   6635: athrow
    //   6636: aload #8
    //   6638: invokevirtual getPackage : ()Ljava/lang/Package;
    //   6641: ifnull -> 6699
    //   6644: goto -> 6651
    //   6647: invokestatic a : (Ljava/lang/Throwable;)Ljava/lang/Throwable;
    //   6650: athrow
    //   6651: aload #8
    //   6653: invokevirtual getPackage : ()Ljava/lang/Package;
    //   6656: invokevirtual getName : ()Ljava/lang/String;
    //   6659: ifnull -> 6699
    //   6662: goto -> 6669
    //   6665: invokestatic a : (Ljava/lang/Throwable;)Ljava/lang/Throwable;
    //   6668: athrow
    //   6669: aload #8
    //   6671: invokevirtual getPackage : ()Ljava/lang/Package;
    //   6674: invokevirtual getName : ()Ljava/lang/String;
    //   6677: sipush #-1066
    //   6680: sipush #29387
    //   6683: invokestatic a : (II)Ljava/lang/String;
    //   6686: invokevirtual startsWith : (Ljava/lang/String;)Z
    //   6689: ifne -> 6699
    //   6692: goto -> 6699
    //   6695: invokestatic a : (Ljava/lang/Throwable;)Ljava/lang/Throwable;
    //   6698: athrow
    //   6699: aload #7
    //   6701: iconst_1
    //   6702: invokevirtual setAccessible : (Z)V
    //   6705: aload #7
    //   6707: aconst_null
    //   6708: invokevirtual get : (Ljava/lang/Object;)Ljava/lang/Object;
    //   6711: pop
    //   6712: iinc #6, 1
    //   6715: iload_2
    //   6716: ifeq -> 6577
    //   6719: sipush #-1084
    //   6722: sipush #-23149
    //   6725: invokestatic a : (II)Ljava/lang/String;
    //   6728: invokestatic forName : (Ljava/lang/String;)Ljava/lang/Class;
    //   6731: invokevirtual getDeclaredMethods : ()[Ljava/lang/reflect/Method;
    //   6734: astore #4
    //   6736: aload #4
    //   6738: arraylength
    //   6739: istore #5
    //   6741: iconst_0
    //   6742: istore #6
    //   6744: iload #6
    //   6746: iload #5
    //   6748: if_icmpge -> 6884
    //   6751: aload #4
    //   6753: iload #6
    //   6755: aaload
    //   6756: astore #7
    //   6758: aload #7
    //   6760: invokevirtual getParameterTypes : ()[Ljava/lang/Class;
    //   6763: pop
    //   6764: aload #7
    //   6766: invokevirtual getModifiers : ()I
    //   6769: invokestatic isStatic : (I)Z
    //   6772: ifeq -> 6870
    //   6775: aload #7
    //   6777: invokevirtual getParameterTypes : ()[Ljava/lang/Class;
    //   6780: arraylength
    //   6781: iconst_2
    //   6782: if_icmpne -> 6870
    //   6785: goto -> 6792
    //   6788: invokestatic a : (Ljava/lang/Throwable;)Ljava/lang/Throwable;
    //   6791: athrow
    //   6792: aload #7
    //   6794: invokevirtual getReturnType : ()Ljava/lang/Class;
    //   6797: getstatic java/lang/Boolean.TYPE : Ljava/lang/Class;
    //   6800: if_acmpne -> 6870
    //   6803: goto -> 6810
    //   6806: invokestatic a : (Ljava/lang/Throwable;)Ljava/lang/Throwable;
    //   6809: athrow
    //   6810: aload #7
    //   6812: iconst_1
    //   6813: invokevirtual setAccessible : (Z)V
    //   6816: aload #7
    //   6818: aconst_null
    //   6819: iconst_2
    //   6820: anewarray java/lang/Object
    //   6823: dup
    //   6824: iconst_0
    //   6825: aload_0
    //   6826: aastore
    //   6827: dup
    //   6828: iconst_1
    //   6829: aload_1
    //   6830: ifnonnull -> 6848
    //   6833: goto -> 6840
    //   6836: invokestatic a : (Ljava/lang/Throwable;)Ljava/lang/Throwable;
    //   6839: athrow
    //   6840: aload_1
    //   6841: goto -> 6855
    //   6844: invokestatic a : (Ljava/lang/Throwable;)Ljava/lang/Throwable;
    //   6847: athrow
    //   6848: aload_1
    //   6849: checkcast [B
    //   6852: invokevirtual clone : ()Ljava/lang/Object;
    //   6855: aastore
    //   6856: invokevirtual invoke : (Ljava/lang/Object;[Ljava/lang/Object;)Ljava/lang/Object;
    //   6859: checkcast java/lang/Boolean
    //   6862: invokevirtual booleanValue : ()Z
    //   6865: istore_3
    //   6866: iload_2
    //   6867: ifeq -> 6884
    //   6870: iinc #6, 1
    //   6873: iload_2
    //   6874: ifeq -> 6744
    //   6877: goto -> 6884
    //   6880: invokestatic a : (Ljava/lang/Throwable;)Ljava/lang/Throwable;
    //   6883: athrow
    //   6884: iload_3
    //   6885: ifeq -> 6890
    //   6888: iload_3
    //   6889: ireturn
    //   6890: getstatic burp/Zs5i.ZJ : Ljava/lang/String;
    //   6893: getstatic burp/Zxee.Zj : Ljava/lang/Object;
    //   6896: checkcast java/math/BigInteger
    //   6899: invokevirtual intValue : ()I
    //   6902: bipush #32
    //   6904: irem
    //   6905: invokestatic abs : (I)I
    //   6908: invokevirtual charAt : (I)C
    //   6911: getstatic burp/Zeqw.Zw : Ljava/lang/String;
    //   6914: getstatic burp/Zrh1.ZF : Ljava/lang/Object;
    //   6917: checkcast java/math/BigInteger
    //   6920: invokevirtual intValue : ()I
    //   6923: bipush #32
    //   6925: irem
    //   6926: invokestatic abs : (I)I
    //   6929: invokevirtual charAt : (I)C
    //   6932: if_icmple -> 7277
    //   6935: sipush #-1083
    //   6938: sipush #31817
    //   6941: invokestatic a : (II)Ljava/lang/String;
    //   6944: iconst_1
    //   6945: ldc burp/Zro_
    //   6947: invokevirtual getClassLoader : ()Ljava/lang/ClassLoader;
    //   6950: invokestatic forName : (Ljava/lang/String;ZLjava/lang/ClassLoader;)Ljava/lang/Class;
    //   6953: invokevirtual getDeclaredFields : ()[Ljava/lang/reflect/Field;
    //   6956: astore #4
    //   6958: aload #4
    //   6960: arraylength
    //   6961: istore #5
    //   6963: iconst_0
    //   6964: istore #6
    //   6966: iload #6
    //   6968: iload #5
    //   6970: if_icmpge -> 7108
    //   6973: aload #4
    //   6975: iload #6
    //   6977: aaload
    //   6978: astore #7
    //   6980: aload #7
    //   6982: invokevirtual getModifiers : ()I
    //   6985: invokestatic isStatic : (I)Z
    //   6988: ifne -> 6998
    //   6991: goto -> 7101
    //   6994: invokestatic a : (Ljava/lang/Throwable;)Ljava/lang/Throwable;
    //   6997: athrow
    //   6998: aload #7
    //   7000: invokevirtual getType : ()Ljava/lang/Class;
    //   7003: astore #8
    //   7005: aload #8
    //   7007: ifnull -> 7088
    //   7010: aload #8
    //   7012: invokevirtual isPrimitive : ()Z
    //   7015: ifne -> 7088
    //   7018: goto -> 7025
    //   7021: invokestatic a : (Ljava/lang/Throwable;)Ljava/lang/Throwable;
    //   7024: athrow
    //   7025: aload #8
    //   7027: invokevirtual getPackage : ()Ljava/lang/Package;
    //   7030: ifnull -> 7088
    //   7033: goto -> 7040
    //   7036: invokestatic a : (Ljava/lang/Throwable;)Ljava/lang/Throwable;
    //   7039: athrow
    //   7040: aload #8
    //   7042: invokevirtual getPackage : ()Ljava/lang/Package;
    //   7045: invokevirtual getName : ()Ljava/lang/String;
    //   7048: ifnull -> 7088
    //   7051: goto -> 7058
    //   7054: invokestatic a : (Ljava/lang/Throwable;)Ljava/lang/Throwable;
    //   7057: athrow
    //   7058: aload #8
    //   7060: invokevirtual getPackage : ()Ljava/lang/Package;
    //   7063: invokevirtual getName : ()Ljava/lang/String;
    //   7066: sipush #-1066
    //   7069: sipush #29387
    //   7072: invokestatic a : (II)Ljava/lang/String;
    //   7075: invokevirtual startsWith : (Ljava/lang/String;)Z
    //   7078: ifne -> 7088
    //   7081: goto -> 7088
    //   7084: invokestatic a : (Ljava/lang/Throwable;)Ljava/lang/Throwable;
    //   7087: athrow
    //   7088: aload #7
    //   7090: iconst_1
    //   7091: invokevirtual setAccessible : (Z)V
    //   7094: aload #7
    //   7096: aconst_null
    //   7097: invokevirtual get : (Ljava/lang/Object;)Ljava/lang/Object;
    //   7100: pop
    //   7101: iinc #6, 1
    //   7104: iload_2
    //   7105: ifeq -> 6966
    //   7108: sipush #-1060
    //   7111: sipush #9372
    //   7114: invokestatic a : (II)Ljava/lang/String;
    //   7117: invokestatic forName : (Ljava/lang/String;)Ljava/lang/Class;
    //   7120: invokevirtual getDeclaredMethods : ()[Ljava/lang/reflect/Method;
    //   7123: astore #4
    //   7125: aload #4
    //   7127: arraylength
    //   7128: istore #5
    //   7130: iconst_0
    //   7131: istore #6
    //   7133: iload #6
    //   7135: iload #5
    //   7137: if_icmpge -> 7273
    //   7140: aload #4
    //   7142: iload #6
    //   7144: aaload
    //   7145: astore #7
    //   7147: aload #7
    //   7149: invokevirtual getParameterTypes : ()[Ljava/lang/Class;
    //   7152: pop
    //   7153: aload #7
    //   7155: invokevirtual getModifiers : ()I
    //   7158: invokestatic isStatic : (I)Z
    //   7161: ifeq -> 7259
    //   7164: aload #7
    //   7166: invokevirtual getParameterTypes : ()[Ljava/lang/Class;
    //   7169: arraylength
    //   7170: iconst_2
    //   7171: if_icmpne -> 7259
    //   7174: goto -> 7181
    //   7177: invokestatic a : (Ljava/lang/Throwable;)Ljava/lang/Throwable;
    //   7180: athrow
    //   7181: aload #7
    //   7183: invokevirtual getReturnType : ()Ljava/lang/Class;
    //   7186: getstatic java/lang/Boolean.TYPE : Ljava/lang/Class;
    //   7189: if_acmpne -> 7259
    //   7192: goto -> 7199
    //   7195: invokestatic a : (Ljava/lang/Throwable;)Ljava/lang/Throwable;
    //   7198: athrow
    //   7199: aload #7
    //   7201: iconst_1
    //   7202: invokevirtual setAccessible : (Z)V
    //   7205: aload #7
    //   7207: aconst_null
    //   7208: iconst_2
    //   7209: anewarray java/lang/Object
    //   7212: dup
    //   7213: iconst_0
    //   7214: aload_0
    //   7215: aastore
    //   7216: dup
    //   7217: iconst_1
    //   7218: aload_1
    //   7219: ifnonnull -> 7237
    //   7222: goto -> 7229
    //   7225: invokestatic a : (Ljava/lang/Throwable;)Ljava/lang/Throwable;
    //   7228: athrow
    //   7229: aload_1
    //   7230: goto -> 7244
    //   7233: invokestatic a : (Ljava/lang/Throwable;)Ljava/lang/Throwable;
    //   7236: athrow
    //   7237: aload_1
    //   7238: checkcast [B
    //   7241: invokevirtual clone : ()Ljava/lang/Object;
    //   7244: aastore
    //   7245: invokevirtual invoke : (Ljava/lang/Object;[Ljava/lang/Object;)Ljava/lang/Object;
    //   7248: checkcast java/lang/Boolean
    //   7251: invokevirtual booleanValue : ()Z
    //   7254: istore_3
    //   7255: iload_2
    //   7256: ifeq -> 7273
    //   7259: iinc #6, 1
    //   7262: iload_2
    //   7263: ifeq -> 7133
    //   7266: goto -> 7273
    //   7269: invokestatic a : (Ljava/lang/Throwable;)Ljava/lang/Throwable;
    //   7272: athrow
    //   7273: iload_2
    //   7274: ifeq -> 7615
    //   7277: sipush #-1062
    //   7280: sipush #-24109
    //   7283: invokestatic a : (II)Ljava/lang/String;
    //   7286: iconst_1
    //   7287: ldc burp/Zzah
    //   7289: invokevirtual getClassLoader : ()Ljava/lang/ClassLoader;
    //   7292: invokestatic forName : (Ljava/lang/String;ZLjava/lang/ClassLoader;)Ljava/lang/Class;
    //   7295: invokevirtual getDeclaredFields : ()[Ljava/lang/reflect/Field;
    //   7298: astore #4
    //   7300: aload #4
    //   7302: arraylength
    //   7303: istore #5
    //   7305: iconst_0
    //   7306: istore #6
    //   7308: iload #6
    //   7310: iload #5
    //   7312: if_icmpge -> 7450
    //   7315: aload #4
    //   7317: iload #6
    //   7319: aaload
    //   7320: astore #7
    //   7322: aload #7
    //   7324: invokevirtual getModifiers : ()I
    //   7327: invokestatic isStatic : (I)Z
    //   7330: ifne -> 7340
    //   7333: goto -> 7443
    //   7336: invokestatic a : (Ljava/lang/Throwable;)Ljava/lang/Throwable;
    //   7339: athrow
    //   7340: aload #7
    //   7342: invokevirtual getType : ()Ljava/lang/Class;
    //   7345: astore #8
    //   7347: aload #8
    //   7349: ifnull -> 7430
    //   7352: aload #8
    //   7354: invokevirtual isPrimitive : ()Z
    //   7357: ifne -> 7430
    //   7360: goto -> 7367
    //   7363: invokestatic a : (Ljava/lang/Throwable;)Ljava/lang/Throwable;
    //   7366: athrow
    //   7367: aload #8
    //   7369: invokevirtual getPackage : ()Ljava/lang/Package;
    //   7372: ifnull -> 7430
    //   7375: goto -> 7382
    //   7378: invokestatic a : (Ljava/lang/Throwable;)Ljava/lang/Throwable;
    //   7381: athrow
    //   7382: aload #8
    //   7384: invokevirtual getPackage : ()Ljava/lang/Package;
    //   7387: invokevirtual getName : ()Ljava/lang/String;
    //   7390: ifnull -> 7430
    //   7393: goto -> 7400
    //   7396: invokestatic a : (Ljava/lang/Throwable;)Ljava/lang/Throwable;
    //   7399: athrow
    //   7400: aload #8
    //   7402: invokevirtual getPackage : ()Ljava/lang/Package;
    //   7405: invokevirtual getName : ()Ljava/lang/String;
    //   7408: sipush #-1066
    //   7411: sipush #29387
    //   7414: invokestatic a : (II)Ljava/lang/String;
    //   7417: invokevirtual startsWith : (Ljava/lang/String;)Z
    //   7420: ifne -> 7430
    //   7423: goto -> 7430
    //   7426: invokestatic a : (Ljava/lang/Throwable;)Ljava/lang/Throwable;
    //   7429: athrow
    //   7430: aload #7
    //   7432: iconst_1
    //   7433: invokevirtual setAccessible : (Z)V
    //   7436: aload #7
    //   7438: aconst_null
    //   7439: invokevirtual get : (Ljava/lang/Object;)Ljava/lang/Object;
    //   7442: pop
    //   7443: iinc #6, 1
    //   7446: iload_2
    //   7447: ifeq -> 7308
    //   7450: sipush #-1079
    //   7453: sipush #-30180
    //   7456: invokestatic a : (II)Ljava/lang/String;
    //   7459: invokestatic forName : (Ljava/lang/String;)Ljava/lang/Class;
    //   7462: invokevirtual getDeclaredMethods : ()[Ljava/lang/reflect/Method;
    //   7465: astore #4
    //   7467: aload #4
    //   7469: arraylength
    //   7470: istore #5
    //   7472: iconst_0
    //   7473: istore #6
    //   7475: iload #6
    //   7477: iload #5
    //   7479: if_icmpge -> 7615
    //   7482: aload #4
    //   7484: iload #6
    //   7486: aaload
    //   7487: astore #7
    //   7489: aload #7
    //   7491: invokevirtual getParameterTypes : ()[Ljava/lang/Class;
    //   7494: pop
    //   7495: aload #7
    //   7497: invokevirtual getModifiers : ()I
    //   7500: invokestatic isStatic : (I)Z
    //   7503: ifeq -> 7601
    //   7506: aload #7
    //   7508: invokevirtual getParameterTypes : ()[Ljava/lang/Class;
    //   7511: arraylength
    //   7512: iconst_2
    //   7513: if_icmpne -> 7601
    //   7516: goto -> 7523
    //   7519: invokestatic a : (Ljava/lang/Throwable;)Ljava/lang/Throwable;
    //   7522: athrow
    //   7523: aload #7
    //   7525: invokevirtual getReturnType : ()Ljava/lang/Class;
    //   7528: getstatic java/lang/Boolean.TYPE : Ljava/lang/Class;
    //   7531: if_acmpne -> 7601
    //   7534: goto -> 7541
    //   7537: invokestatic a : (Ljava/lang/Throwable;)Ljava/lang/Throwable;
    //   7540: athrow
    //   7541: aload #7
    //   7543: iconst_1
    //   7544: invokevirtual setAccessible : (Z)V
    //   7547: aload #7
    //   7549: aconst_null
    //   7550: iconst_2
    //   7551: anewarray java/lang/Object
    //   7554: dup
    //   7555: iconst_0
    //   7556: aload_0
    //   7557: aastore
    //   7558: dup
    //   7559: iconst_1
    //   7560: aload_1
    //   7561: ifnonnull -> 7579
    //   7564: goto -> 7571
    //   7567: invokestatic a : (Ljava/lang/Throwable;)Ljava/lang/Throwable;
    //   7570: athrow
    //   7571: aload_1
    //   7572: goto -> 7586
    //   7575: invokestatic a : (Ljava/lang/Throwable;)Ljava/lang/Throwable;
    //   7578: athrow
    //   7579: aload_1
    //   7580: checkcast [B
    //   7583: invokevirtual clone : ()Ljava/lang/Object;
    //   7586: aastore
    //   7587: invokevirtual invoke : (Ljava/lang/Object;[Ljava/lang/Object;)Ljava/lang/Object;
    //   7590: checkcast java/lang/Boolean
    //   7593: invokevirtual booleanValue : ()Z
    //   7596: istore_3
    //   7597: iload_2
    //   7598: ifeq -> 7615
    //   7601: iinc #6, 1
    //   7604: iload_2
    //   7605: ifeq -> 7475
    //   7608: goto -> 7615
    //   7611: invokestatic a : (Ljava/lang/Throwable;)Ljava/lang/Throwable;
    //   7614: athrow
    //   7615: iload_3
    //   7616: ifeq -> 7621
    //   7619: iload_3
    //   7620: ireturn
    //   7621: getstatic burp/Zszm.Zf : Ljava/lang/String;
    //   7624: getstatic burp/Zs5i.ZD : Ljava/lang/Object;
    //   7627: checkcast java/math/BigInteger
    //   7630: invokevirtual intValue : ()I
    //   7633: bipush #32
    //   7635: irem
    //   7636: invokestatic abs : (I)I
    //   7639: invokevirtual charAt : (I)C
    //   7642: getstatic burp/Zxee.Zd : Ljava/lang/String;
    //   7645: getstatic burp/Zs5k.Zg : Ljava/lang/Object;
    //   7648: checkcast java/math/BigInteger
    //   7651: invokevirtual intValue : ()I
    //   7654: bipush #32
    //   7656: irem
    //   7657: invokestatic abs : (I)I
    //   7660: invokevirtual charAt : (I)C
    //   7663: if_icmpgt -> 8008
    //   7666: sipush #-1073
    //   7669: sipush #-15235
    //   7672: invokestatic a : (II)Ljava/lang/String;
    //   7675: iconst_1
    //   7676: ldc burp/Zl8l
    //   7678: invokevirtual getClassLoader : ()Ljava/lang/ClassLoader;
    //   7681: invokestatic forName : (Ljava/lang/String;ZLjava/lang/ClassLoader;)Ljava/lang/Class;
    //   7684: invokevirtual getDeclaredFields : ()[Ljava/lang/reflect/Field;
    //   7687: astore #4
    //   7689: aload #4
    //   7691: arraylength
    //   7692: istore #5
    //   7694: iconst_0
    //   7695: istore #6
    //   7697: iload #6
    //   7699: iload #5
    //   7701: if_icmpge -> 7839
    //   7704: aload #4
    //   7706: iload #6
    //   7708: aaload
    //   7709: astore #7
    //   7711: aload #7
    //   7713: invokevirtual getModifiers : ()I
    //   7716: invokestatic isStatic : (I)Z
    //   7719: ifne -> 7729
    //   7722: goto -> 7832
    //   7725: invokestatic a : (Ljava/lang/Throwable;)Ljava/lang/Throwable;
    //   7728: athrow
    //   7729: aload #7
    //   7731: invokevirtual getType : ()Ljava/lang/Class;
    //   7734: astore #8
    //   7736: aload #8
    //   7738: ifnull -> 7819
    //   7741: aload #8
    //   7743: invokevirtual isPrimitive : ()Z
    //   7746: ifne -> 7819
    //   7749: goto -> 7756
    //   7752: invokestatic a : (Ljava/lang/Throwable;)Ljava/lang/Throwable;
    //   7755: athrow
    //   7756: aload #8
    //   7758: invokevirtual getPackage : ()Ljava/lang/Package;
    //   7761: ifnull -> 7819
    //   7764: goto -> 7771
    //   7767: invokestatic a : (Ljava/lang/Throwable;)Ljava/lang/Throwable;
    //   7770: athrow
    //   7771: aload #8
    //   7773: invokevirtual getPackage : ()Ljava/lang/Package;
    //   7776: invokevirtual getName : ()Ljava/lang/String;
    //   7779: ifnull -> 7819
    //   7782: goto -> 7789
    //   7785: invokestatic a : (Ljava/lang/Throwable;)Ljava/lang/Throwable;
    //   7788: athrow
    //   7789: aload #8
    //   7791: invokevirtual getPackage : ()Ljava/lang/Package;
    //   7794: invokevirtual getName : ()Ljava/lang/String;
    //   7797: sipush #-1066
    //   7800: sipush #29387
    //   7803: invokestatic a : (II)Ljava/lang/String;
    //   7806: invokevirtual startsWith : (Ljava/lang/String;)Z
    //   7809: ifne -> 7819
    //   7812: goto -> 7819
    //   7815: invokestatic a : (Ljava/lang/Throwable;)Ljava/lang/Throwable;
    //   7818: athrow
    //   7819: aload #7
    //   7821: iconst_1
    //   7822: invokevirtual setAccessible : (Z)V
    //   7825: aload #7
    //   7827: aconst_null
    //   7828: invokevirtual get : (Ljava/lang/Object;)Ljava/lang/Object;
    //   7831: pop
    //   7832: iinc #6, 1
    //   7835: iload_2
    //   7836: ifeq -> 7697
    //   7839: sipush #-1085
    //   7842: sipush #-30846
    //   7845: invokestatic a : (II)Ljava/lang/String;
    //   7848: invokestatic forName : (Ljava/lang/String;)Ljava/lang/Class;
    //   7851: invokevirtual getDeclaredMethods : ()[Ljava/lang/reflect/Method;
    //   7854: astore #4
    //   7856: aload #4
    //   7858: arraylength
    //   7859: istore #5
    //   7861: iconst_0
    //   7862: istore #6
    //   7864: iload #6
    //   7866: iload #5
    //   7868: if_icmpge -> 8004
    //   7871: aload #4
    //   7873: iload #6
    //   7875: aaload
    //   7876: astore #7
    //   7878: aload #7
    //   7880: invokevirtual getParameterTypes : ()[Ljava/lang/Class;
    //   7883: pop
    //   7884: aload #7
    //   7886: invokevirtual getModifiers : ()I
    //   7889: invokestatic isStatic : (I)Z
    //   7892: ifeq -> 7990
    //   7895: aload #7
    //   7897: invokevirtual getParameterTypes : ()[Ljava/lang/Class;
    //   7900: arraylength
    //   7901: iconst_2
    //   7902: if_icmpne -> 7990
    //   7905: goto -> 7912
    //   7908: invokestatic a : (Ljava/lang/Throwable;)Ljava/lang/Throwable;
    //   7911: athrow
    //   7912: aload #7
    //   7914: invokevirtual getReturnType : ()Ljava/lang/Class;
    //   7917: getstatic java/lang/Boolean.TYPE : Ljava/lang/Class;
    //   7920: if_acmpne -> 7990
    //   7923: goto -> 7930
    //   7926: invokestatic a : (Ljava/lang/Throwable;)Ljava/lang/Throwable;
    //   7929: athrow
    //   7930: aload #7
    //   7932: iconst_1
    //   7933: invokevirtual setAccessible : (Z)V
    //   7936: aload #7
    //   7938: aconst_null
    //   7939: iconst_2
    //   7940: anewarray java/lang/Object
    //   7943: dup
    //   7944: iconst_0
    //   7945: aload_0
    //   7946: aastore
    //   7947: dup
    //   7948: iconst_1
    //   7949: aload_1
    //   7950: ifnonnull -> 7968
    //   7953: goto -> 7960
    //   7956: invokestatic a : (Ljava/lang/Throwable;)Ljava/lang/Throwable;
    //   7959: athrow
    //   7960: aload_1
    //   7961: goto -> 7975
    //   7964: invokestatic a : (Ljava/lang/Throwable;)Ljava/lang/Throwable;
    //   7967: athrow
    //   7968: aload_1
    //   7969: checkcast [B
    //   7972: invokevirtual clone : ()Ljava/lang/Object;
    //   7975: aastore
    //   7976: invokevirtual invoke : (Ljava/lang/Object;[Ljava/lang/Object;)Ljava/lang/Object;
    //   7979: checkcast java/lang/Boolean
    //   7982: invokevirtual booleanValue : ()Z
    //   7985: istore_3
    //   7986: iload_2
    //   7987: ifeq -> 8004
    //   7990: iinc #6, 1
    //   7993: iload_2
    //   7994: ifeq -> 7864
    //   7997: goto -> 8004
    //   8000: invokestatic a : (Ljava/lang/Throwable;)Ljava/lang/Throwable;
    //   8003: athrow
    //   8004: iload_2
    //   8005: ifeq -> 8346
    //   8008: sipush #-1088
    //   8011: sipush #30229
    //   8014: invokestatic a : (II)Ljava/lang/String;
    //   8017: iconst_1
    //   8018: ldc burp/Zgb9
    //   8020: invokevirtual getClassLoader : ()Ljava/lang/ClassLoader;
    //   8023: invokestatic forName : (Ljava/lang/String;ZLjava/lang/ClassLoader;)Ljava/lang/Class;
    //   8026: invokevirtual getDeclaredFields : ()[Ljava/lang/reflect/Field;
    //   8029: astore #4
    //   8031: aload #4
    //   8033: arraylength
    //   8034: istore #5
    //   8036: iconst_0
    //   8037: istore #6
    //   8039: iload #6
    //   8041: iload #5
    //   8043: if_icmpge -> 8181
    //   8046: aload #4
    //   8048: iload #6
    //   8050: aaload
    //   8051: astore #7
    //   8053: aload #7
    //   8055: invokevirtual getModifiers : ()I
    //   8058: invokestatic isStatic : (I)Z
    //   8061: ifne -> 8071
    //   8064: goto -> 8174
    //   8067: invokestatic a : (Ljava/lang/Throwable;)Ljava/lang/Throwable;
    //   8070: athrow
    //   8071: aload #7
    //   8073: invokevirtual getType : ()Ljava/lang/Class;
    //   8076: astore #8
    //   8078: aload #8
    //   8080: ifnull -> 8161
    //   8083: aload #8
    //   8085: invokevirtual isPrimitive : ()Z
    //   8088: ifne -> 8161
    //   8091: goto -> 8098
    //   8094: invokestatic a : (Ljava/lang/Throwable;)Ljava/lang/Throwable;
    //   8097: athrow
    //   8098: aload #8
    //   8100: invokevirtual getPackage : ()Ljava/lang/Package;
    //   8103: ifnull -> 8161
    //   8106: goto -> 8113
    //   8109: invokestatic a : (Ljava/lang/Throwable;)Ljava/lang/Throwable;
    //   8112: athrow
    //   8113: aload #8
    //   8115: invokevirtual getPackage : ()Ljava/lang/Package;
    //   8118: invokevirtual getName : ()Ljava/lang/String;
    //   8121: ifnull -> 8161
    //   8124: goto -> 8131
    //   8127: invokestatic a : (Ljava/lang/Throwable;)Ljava/lang/Throwable;
    //   8130: athrow
    //   8131: aload #8
    //   8133: invokevirtual getPackage : ()Ljava/lang/Package;
    //   8136: invokevirtual getName : ()Ljava/lang/String;
    //   8139: sipush #-1066
    //   8142: sipush #29387
    //   8145: invokestatic a : (II)Ljava/lang/String;
    //   8148: invokevirtual startsWith : (Ljava/lang/String;)Z
    //   8151: ifne -> 8161
    //   8154: goto -> 8161
    //   8157: invokestatic a : (Ljava/lang/Throwable;)Ljava/lang/Throwable;
    //   8160: athrow
    //   8161: aload #7
    //   8163: iconst_1
    //   8164: invokevirtual setAccessible : (Z)V
    //   8167: aload #7
    //   8169: aconst_null
    //   8170: invokevirtual get : (Ljava/lang/Object;)Ljava/lang/Object;
    //   8173: pop
    //   8174: iinc #6, 1
    //   8177: iload_2
    //   8178: ifeq -> 8039
    //   8181: sipush #-1072
    //   8184: sipush #16852
    //   8187: invokestatic a : (II)Ljava/lang/String;
    //   8190: invokestatic forName : (Ljava/lang/String;)Ljava/lang/Class;
    //   8193: invokevirtual getDeclaredMethods : ()[Ljava/lang/reflect/Method;
    //   8196: astore #4
    //   8198: aload #4
    //   8200: arraylength
    //   8201: istore #5
    //   8203: iconst_0
    //   8204: istore #6
    //   8206: iload #6
    //   8208: iload #5
    //   8210: if_icmpge -> 8346
    //   8213: aload #4
    //   8215: iload #6
    //   8217: aaload
    //   8218: astore #7
    //   8220: aload #7
    //   8222: invokevirtual getParameterTypes : ()[Ljava/lang/Class;
    //   8225: pop
    //   8226: aload #7
    //   8228: invokevirtual getModifiers : ()I
    //   8231: invokestatic isStatic : (I)Z
    //   8234: ifeq -> 8332
    //   8237: aload #7
    //   8239: invokevirtual getParameterTypes : ()[Ljava/lang/Class;
    //   8242: arraylength
    //   8243: iconst_2
    //   8244: if_icmpne -> 8332
    //   8247: goto -> 8254
    //   8250: invokestatic a : (Ljava/lang/Throwable;)Ljava/lang/Throwable;
    //   8253: athrow
    //   8254: aload #7
    //   8256: invokevirtual getReturnType : ()Ljava/lang/Class;
    //   8259: getstatic java/lang/Boolean.TYPE : Ljava/lang/Class;
    //   8262: if_acmpne -> 8332
    //   8265: goto -> 8272
    //   8268: invokestatic a : (Ljava/lang/Throwable;)Ljava/lang/Throwable;
    //   8271: athrow
    //   8272: aload #7
    //   8274: iconst_1
    //   8275: invokevirtual setAccessible : (Z)V
    //   8278: aload #7
    //   8280: aconst_null
    //   8281: iconst_2
    //   8282: anewarray java/lang/Object
    //   8285: dup
    //   8286: iconst_0
    //   8287: aload_0
    //   8288: aastore
    //   8289: dup
    //   8290: iconst_1
    //   8291: aload_1
    //   8292: ifnonnull -> 8310
    //   8295: goto -> 8302
    //   8298: invokestatic a : (Ljava/lang/Throwable;)Ljava/lang/Throwable;
    //   8301: athrow
    //   8302: aload_1
    //   8303: goto -> 8317
    //   8306: invokestatic a : (Ljava/lang/Throwable;)Ljava/lang/Throwable;
    //   8309: athrow
    //   8310: aload_1
    //   8311: checkcast [B
    //   8314: invokevirtual clone : ()Ljava/lang/Object;
    //   8317: aastore
    //   8318: invokevirtual invoke : (Ljava/lang/Object;[Ljava/lang/Object;)Ljava/lang/Object;
    //   8321: checkcast java/lang/Boolean
    //   8324: invokevirtual booleanValue : ()Z
    //   8327: istore_3
    //   8328: iload_2
    //   8329: ifeq -> 8346
    //   8332: iinc #6, 1
    //   8335: iload_2
    //   8336: ifeq -> 8206
    //   8339: goto -> 8346
    //   8342: invokestatic a : (Ljava/lang/Throwable;)Ljava/lang/Throwable;
    //   8345: athrow
    //   8346: iload_3
    //   8347: ireturn
    //   8348: astore_3
    //   8349: new java/lang/Exception
    //   8352: dup
    //   8353: aload_3
    //   8354: invokevirtual getMessage : ()Ljava/lang/String;
    //   8357: invokespecial <init> : (Ljava/lang/String;)V
    //   8360: athrow
    // Exception table:
    //   from	to	target	type
    //   4	6158	8348	java/lang/Throwable
    //   3321	3346	3346	java/lang/Throwable
    //   4309	4335	4335	java/lang/Throwable
    //   4442	4456	4456	java/lang/Throwable
    //   4467	4480	4483	java/lang/Throwable
    //   4472	4495	4498	java/lang/Throwable
    //   4487	4513	4516	java/lang/Throwable
    //   4502	4543	4546	java/lang/Throwable
    //   4606	4633	4636	java/lang/Throwable
    //   4623	4654	4657	java/lang/Throwable
    //   4640	4684	4687	java/lang/Throwable
    //   4661	4695	4695	java/lang/Throwable
    //   4706	4722	4725	java/lang/Throwable
    //   4799	4813	4813	java/lang/Throwable
    //   4824	4837	4840	java/lang/Throwable
    //   4829	4852	4855	java/lang/Throwable
    //   4844	4870	4873	java/lang/Throwable
    //   4859	4900	4903	java/lang/Throwable
    //   4963	4990	4993	java/lang/Throwable
    //   4980	5011	5014	java/lang/Throwable
    //   4997	5041	5044	java/lang/Throwable
    //   5018	5052	5052	java/lang/Throwable
    //   5063	5079	5082	java/lang/Throwable
    //   5086	5423	5426	java/lang/Throwable
    //   5257	5267	5267	java/lang/Throwable
    //   5271	5283	5283	java/lang/Throwable
    //   5287	5299	5299	java/lang/Throwable
    //   5303	5316	5316	java/lang/Throwable
    //   5320	5333	5333	java/lang/Throwable
    //   5519	5533	5533	java/lang/Throwable
    //   5544	5557	5560	java/lang/Throwable
    //   5549	5572	5575	java/lang/Throwable
    //   5564	5590	5593	java/lang/Throwable
    //   5579	5620	5623	java/lang/Throwable
    //   5686	5713	5716	java/lang/Throwable
    //   5703	5731	5734	java/lang/Throwable
    //   5720	5761	5764	java/lang/Throwable
    //   5738	5772	5772	java/lang/Throwable
    //   5794	5805	5808	java/lang/Throwable
    //   5860	5874	5874	java/lang/Throwable
    //   5885	5898	5901	java/lang/Throwable
    //   5890	5913	5916	java/lang/Throwable
    //   5905	5931	5934	java/lang/Throwable
    //   5920	5961	5964	java/lang/Throwable
    //   6027	6054	6057	java/lang/Throwable
    //   6044	6072	6075	java/lang/Throwable
    //   6061	6102	6105	java/lang/Throwable
    //   6079	6113	6113	java/lang/Throwable
    //   6135	6146	6149	java/lang/Throwable
    //   6159	6889	8348	java/lang/Throwable
    //   6249	6263	6263	java/lang/Throwable
    //   6274	6287	6290	java/lang/Throwable
    //   6279	6302	6305	java/lang/Throwable
    //   6294	6320	6323	java/lang/Throwable
    //   6309	6350	6353	java/lang/Throwable
    //   6416	6443	6446	java/lang/Throwable
    //   6433	6461	6464	java/lang/Throwable
    //   6450	6491	6494	java/lang/Throwable
    //   6468	6502	6502	java/lang/Throwable
    //   6524	6535	6538	java/lang/Throwable
    //   6591	6605	6605	java/lang/Throwable
    //   6616	6629	6632	java/lang/Throwable
    //   6621	6644	6647	java/lang/Throwable
    //   6636	6662	6665	java/lang/Throwable
    //   6651	6692	6695	java/lang/Throwable
    //   6758	6785	6788	java/lang/Throwable
    //   6775	6803	6806	java/lang/Throwable
    //   6792	6833	6836	java/lang/Throwable
    //   6810	6844	6844	java/lang/Throwable
    //   6866	6877	6880	java/lang/Throwable
    //   6890	7620	8348	java/lang/Throwable
    //   6980	6994	6994	java/lang/Throwable
    //   7005	7018	7021	java/lang/Throwable
    //   7010	7033	7036	java/lang/Throwable
    //   7025	7051	7054	java/lang/Throwable
    //   7040	7081	7084	java/lang/Throwable
    //   7147	7174	7177	java/lang/Throwable
    //   7164	7192	7195	java/lang/Throwable
    //   7181	7222	7225	java/lang/Throwable
    //   7199	7233	7233	java/lang/Throwable
    //   7255	7266	7269	java/lang/Throwable
    //   7322	7336	7336	java/lang/Throwable
    //   7347	7360	7363	java/lang/Throwable
    //   7352	7375	7378	java/lang/Throwable
    //   7367	7393	7396	java/lang/Throwable
    //   7382	7423	7426	java/lang/Throwable
    //   7489	7516	7519	java/lang/Throwable
    //   7506	7534	7537	java/lang/Throwable
    //   7523	7564	7567	java/lang/Throwable
    //   7541	7575	7575	java/lang/Throwable
    //   7597	7608	7611	java/lang/Throwable
    //   7621	8347	8348	java/lang/Throwable
    //   7711	7725	7725	java/lang/Throwable
    //   7736	7749	7752	java/lang/Throwable
    //   7741	7764	7767	java/lang/Throwable
    //   7756	7782	7785	java/lang/Throwable
    //   7771	7812	7815	java/lang/Throwable
    //   7878	7905	7908	java/lang/Throwable
    //   7895	7923	7926	java/lang/Throwable
    //   7912	7953	7956	java/lang/Throwable
    //   7930	7964	7964	java/lang/Throwable
    //   7986	7997	8000	java/lang/Throwable
    //   8053	8067	8067	java/lang/Throwable
    //   8078	8091	8094	java/lang/Throwable
    //   8083	8106	8109	java/lang/Throwable
    //   8098	8124	8127	java/lang/Throwable
    //   8113	8154	8157	java/lang/Throwable
    //   8220	8247	8250	java/lang/Throwable
    //   8237	8265	8268	java/lang/Throwable
    //   8254	8295	8298	java/lang/Throwable
    //   8272	8306	8306	java/lang/Throwable
    //   8328	8339	8342	java/lang/Throwable
  }
  
  static void Zd(Object[] paramArrayOfObject, Object paramObject) throws Throwable {}
  
  static void ZS(Object paramObject) {
    Zro_.Zz = a(-1081, 8689);
    Zro_.ZP = new BigInteger(a(-1064, -25771));
    boolean bool = Zt2e.ZK();
    try {
      try {
        if (Zza3.ZU.charAt(Math.abs(((BigInteger)Ztw4.ZF).intValue() % 32)) <= Zza3.ZU.charAt(Math.abs(((BigInteger)Ztsc.Zr).intValue() % 32))) {
          try {
            Zm5s.ZC(Class.forName(a(-1075, 30834)));
            if (bool)
              Zmwx.Zr(Class.forName(a(-1070, 13306))); 
          } catch (Throwable throwable) {
            throw a(null);
          } 
          return;
        } 
      } catch (Throwable throwable) {
        throw a(null);
      } 
      Zmwx.Zr(Class.forName(a(-1070, 13306)));
    } catch (Throwable throwable) {}
  }
  
  static {
    // Byte code:
    //   0: bipush #34
    //   2: anewarray java/lang/String
    //   5: astore #5
    //   7: iconst_0
    //   8: istore_3
    //   9: ldc 'o \\tIz]JES"mg6ybd%"\\t\\rTY\\bW\\tH\\fc=\\r\\t?VY]\\t2C?j^U{#',U%\\tW7M 4k//EI;ZB\\f \\f7=!c-xQy6'5}o`6Je;\\tN( Y/\\tj9RP:Mn;(tq#J_\\b3(CA8]\\bPCRm5o@,:qD#=5U?\\t#hYD\\t6rKs, %\\f\\r$ > \\t:83Z]\\t|1</\\tKMlG\\teqB4]\\t\\bC\\f\\tagZ\\t AI\\tAE/\\bU\\tbPPr h5vT H\\f\\tkwZ/ffc4[":<u#~\\tM\\t%JM '
    //   11: dup
    //   12: astore_2
    //   13: invokevirtual length : ()I
    //   16: istore #4
    //   18: iconst_4
    //   19: istore_1
    //   20: iconst_m1
    //   21: istore_0
    //   22: bipush #90
    //   24: iinc #0, 1
    //   27: aload_2
    //   28: iload_0
    //   29: dup
    //   30: iload_1
    //   31: iadd
    //   32: invokevirtual substring : (II)Ljava/lang/String;
    //   35: iconst_m1
    //   36: goto -> 142
    //   39: aload #5
    //   41: swap
    //   42: iload_3
    //   43: iinc #3, 1
    //   46: swap
    //   47: aastore
    //   48: iload_0
    //   49: iload_1
    //   50: iadd
    //   51: dup
    //   52: istore_0
    //   53: iload #4
    //   55: if_icmpge -> 67
    //   58: aload_2
    //   59: iload_0
    //   60: invokevirtual charAt : (I)C
    //   63: istore_1
    //   64: goto -> 22
    //   67: ldc 'B`\\tOgCD'
    //   69: dup
    //   70: astore_2
    //   71: invokevirtual length : ()I
    //   74: istore #4
    //   76: bipush #9
    //   78: istore_1
    //   79: iconst_m1
    //   80: istore_0
    //   81: bipush #9
    //   83: iinc #0, 1
    //   86: aload_2
    //   87: iload_0
    //   88: dup
    //   89: iload_1
    //   90: iadd
    //   91: invokevirtual substring : (II)Ljava/lang/String;
    //   94: iconst_0
    //   95: goto -> 142
    //   98: aload #5
    //   100: swap
    //   101: iload_3
    //   102: iinc #3, 1
    //   105: swap
    //   106: aastore
    //   107: iload_0
    //   108: iload_1
    //   109: iadd
    //   110: dup
    //   111: istore_0
    //   112: iload #4
    //   114: if_icmpge -> 126
    //   117: aload_2
    //   118: iload_0
    //   119: invokevirtual charAt : (I)C
    //   122: istore_1
    //   123: goto -> 81
    //   126: aload #5
    //   128: putstatic burp/Zktq.a : [Ljava/lang/String;
    //   131: bipush #34
    //   133: anewarray java/lang/String
    //   136: putstatic burp/Zktq.b : [Ljava/lang/String;
    //   139: goto -> 300
    //   142: dup_x2
    //   143: pop
    //   144: invokevirtual toCharArray : ()[C
    //   147: dup_x1
    //   148: arraylength
    //   149: dup_x2
    //   150: pop
    //   151: iconst_0
    //   152: istore #6
    //   154: dup2_x1
    //   155: pop2
    //   156: dup_x2
    //   157: iconst_1
    //   158: if_icmpgt -> 260
    //   161: dup2
    //   162: swap
    //   163: iload #6
    //   165: dup2_x1
    //   166: caload
    //   167: swap
    //   168: iload #6
    //   170: bipush #7
    //   172: irem
    //   173: tableswitch default -> 242, 0 -> 212, 1 -> 217, 2 -> 222, 3 -> 227, 4 -> 232, 5 -> 237
    //   212: bipush #43
    //   214: goto -> 244
    //   217: bipush #44
    //   219: goto -> 244
    //   222: bipush #92
    //   224: goto -> 244
    //   227: bipush #58
    //   229: goto -> 244
    //   232: bipush #102
    //   234: goto -> 244
    //   237: bipush #104
    //   239: goto -> 244
    //   242: bipush #70
    //   244: ixor
    //   245: ixor
    //   246: i2c
    //   247: castore
    //   248: iinc #6, 1
    //   251: dup
    //   252: ifne -> 260
    //   255: dup2
    //   256: dup_x1
    //   257: goto -> 165
    //   260: dup2_x1
    //   261: pop2
    //   262: dup_x2
    //   263: iload #6
    //   265: if_icmpgt -> 161
    //   268: pop
    //   269: new java/lang/String
    //   272: dup_x1
    //   273: swap
    //   274: invokespecial <init> : ([C)V
    //   277: invokevirtual intern : ()Ljava/lang/String;
    //   280: swap
    //   281: pop
    //   282: swap
    //   283: tableswitch default -> 39, 0 -> 98
    //   300: sipush #-1078
    //   303: sipush #8599
    //   306: invokestatic a : (II)Ljava/lang/String;
    //   309: putstatic burp/Zktq.Zc : Ljava/lang/String;
    //   312: new java/math/BigInteger
    //   315: dup
    //   316: sipush #-1059
    //   319: sipush #12056
    //   322: invokestatic a : (II)Ljava/lang/String;
    //   325: invokespecial <init> : (Ljava/lang/String;)V
    //   328: putstatic burp/Zktq.Zn : Ljava/lang/Object;
    //   331: return
  }
  
  private static Throwable a(Throwable paramThrowable) {
    return paramThrowable;
  }
  
  private static String a(int paramInt1, int paramInt2) {
    int i = (paramInt1 ^ 0xFFFFFBD6) & 0xFFFF;
    if (b[i] == null) {
      char[] arrayOfChar = a[i].toCharArray();
      switch (arrayOfChar[0] & 0xFF) {
        case 0:
        
        case 1:
        
        case 2:
        
        case 3:
        
        case 4:
        
        case 5:
        
        case 6:
        
        case 7:
        
        case 8:
        
        case 9:
        
        case 10:
        
        case 11:
        
        case 12:
        
        case 13:
        
        case 14:
        
        case 15:
        
        case 16:
        
        case 17:
        
        case 18:
        
        case 19:
        
        case 20:
        
        case 21:
        
        case 22:
        
        case 23:
        
        case 24:
        
        case 25:
        
        case 26:
        
        case 27:
        
        case 28:
        
        case 29:
        
        case 30:
        
        case 31:
        
        case 32:
        
        case 33:
        
        case 34:
        
        case 35:
        
        case 36:
        
        case 37:
        
        case 38:
        
        case 39:
        
        case 40:
        
        case 41:
        
        case 42:
        
        case 43:
        
        case 44:
        
        case 45:
        
        case 46:
        
        case 47:
        
        case 48:
        
        case 49:
        
        case 50:
        
        case 51:
        
        case 52:
        
        case 53:
        
        case 54:
        
        case 55:
        
        case 56:
        
        case 57:
        
        case 58:
        
        case 59:
        
        case 60:
        
        case 61:
        
        case 62:
        
        case 63:
        
        case 64:
        
        case 65:
        
        case 66:
        
        case 67:
        
        case 68:
        
        case 69:
        
        case 70:
        
        case 71:
        
        case 72:
        
        case 73:
        
        case 74:
        
        case 75:
        
        case 76:
        
        case 77:
        
        case 78:
        
        case 79:
        
        case 80:
        
        case 81:
        
        case 82:
        
        case 83:
        
        case 84:
        
        case 85:
        
        case 86:
        
        case 87:
        
        case 88:
        
        case 89:
        
        case 90:
        
        case 91:
        
        case 92:
        
        case 93:
        
        case 94:
        
        case 95:
        
        case 96:
        
        case 97:
        
        case 98:
        
        case 99:
        
        case 100:
        
        case 101:
        
        case 102:
        
        case 103:
        
        case 104:
        
        case 105:
        
        case 106:
        
        case 107:
        
        case 108:
        
        case 109:
        
        case 110:
        
        case 111:
        
        case 112:
        
        case 113:
        
        case 114:
        
        case 115:
        
        case 116:
        
        case 117:
        
        case 118:
        
        case 119:
        
        case 120:
        
        case 121:
        
        case 122:
        
        case 123:
        
        case 124:
        
        case 125:
        
        case 126:
        
        case 127:
        
        case 128:
        
        case 129:
        
        case 130:
        
        case 131:
        
        case 132:
        
        case 133:
        
        case 134:
        
        case 135:
        
        case 136:
        
        case 137:
        
        case 138:
        
        case 139:
        
        case 140:
        
        case 141:
        
        case 142:
        
        case 143:
        
        case 144:
        
        case 145:
        
        case 146:
        
        case 147:
        
        case 148:
        
        case 149:
        
        case 150:
        
        case 151:
        
        case 152:
        
        case 153:
        
        case 154:
        
        case 155:
        
        case 156:
        
        case 157:
        
        case 158:
        
        case 159:
        
        case 160:
        
        case 161:
        
        case 162:
        
        case 163:
        
        case 164:
        
        case 165:
        
        case 166:
        
        case 167:
        
        case 168:
        
        case 169:
        
        case 170:
        
        case 171:
        
        case 172:
        
        case 173:
        
        case 174:
        
        case 175:
        
        case 176:
        
        case 177:
        
        case 178:
        
        case 179:
        
        case 180:
        
        case 181:
        
        case 182:
        
        case 183:
        
        case 184:
        
        case 185:
        
        case 186:
        
        case 187:
        
        case 188:
        
        case 189:
        
        case 190:
        
        case 191:
        
        case 192:
        
        case 193:
        
        case 194:
        
        case 195:
        
        case 196:
        
        case 197:
        
        case 198:
        
        case 199:
        
        case 200:
        
        case 201:
        
        case 202:
        
        case 203:
        
        case 204:
        
        case 205:
        
        case 206:
        
        case 207:
        
        case 208:
        
        case 209:
        
        case 210:
        
        case 211:
        
        case 212:
        
        case 213:
        
        case 214:
        
        case 215:
        
        case 216:
        
        case 217:
        
        case 218:
        
        case 219:
        
        case 220:
        
        case 221:
        
        case 222:
        
        case 223:
        
        case 224:
        
        case 225:
        
        case 226:
        
        case 227:
        
        case 228:
        
        case 229:
        
        case 230:
        
        case 231:
        
        case 232:
        
        case 233:
        
        case 234:
        
        case 235:
        
        case 236:
        
        case 237:
        
        case 238:
        
        case 239:
        
        case 240:
        
        case 241:
        
        case 242:
        
        case 243:
        
        case 244:
        
        case 245:
        
        case 246:
        
        case 247:
        
        case 248:
        
        case 249:
        
        case 250:
        
        case 251:
        
        case 252:
        
        case 253:
        
        case 254:
        
        default:
          break;
      } 
      char c = '';
      int j = (paramInt2 & 0xFF) - c;
      if (j < 0)
        j += 256; 
      int k = ((paramInt2 & 0xFFFF) >>> 8) - c;
      if (k < 0)
        k += 256; 
      for (byte b = 0; b < arrayOfChar.length; b++) {
        int m = b % 2;
        if (m == 0) {
          arrayOfChar[b] = (char)(arrayOfChar[b] ^ j);
          j = ((j >>> 3 | j << 5) ^ arrayOfChar[b]) & 0xFF;
        } else {
          arrayOfChar[b] = (char)(arrayOfChar[b] ^ k);
          k = ((k >>> 3 | k << 5) ^ arrayOfChar[b]) & 0xFF;
        } 
      } 
      b[i] = (new String(arrayOfChar)).intern();
    } 
    return b[i];
  }
}


/* Location:              C:\Program Files\BurpSuitePro\burpsuite_pro.jar!\burp\Zktq.class
 * Java compiler version: 21 (65.0)
 * JD-Core Version:       1.1.3
 */