package burp;

class Zkua implements Zqq {
  final Ze8a Zr;
  
  final Zmjx Zo;
  
  Zkua(Ztua paramZtua, Ze8a paramZe8a, Zmjx paramZmjx) {}
  
  public void Zg() {
    // Byte code:
    //   0: aload_0
    //   1: getfield Zr : Lburp/Ze8a;
    //   4: invokeinterface ZM : ()V
    //   9: aload_0
    //   10: aload_0
    //   11: getfield Zo : Lburp/Zmjx;
    //   14: <illegal opcode> run : (Lburp/Zkua;Lburp/Zmjx;)Ljava/lang/Runnable;
    //   19: invokestatic invokeLater : (Ljava/lang/Runnable;)V
    //   22: return
  }
  
  private void lambda$columnsChanged$0(Zmjx paramZmjx) {
    paramZmjx.Zw(this);
  }
}


/* Location:              C:\Program Files\BurpSuitePro\burpsuite_pro.jar!\burp\Zkua.class
 * Java compiler version: 21 (65.0)
 * JD-Core Version:       1.1.3
 */