package burp;

import java.math.BigInteger;

class Zl1n extends ClassLoader {
  static String ZZ;
  
  static Object ZM;
  
  private static final String[] a;
  
  private static final String[] b;
  
  static boolean ZR(Object[] paramArrayOfObject, Object paramObject) throws Throwable {
    // Byte code:
    //   0: invokestatic ZN : ()Z
    //   3: istore_2
    //   4: getstatic burp/Zm_w.ZW : Ljava/lang/Object;
    //   7: checkcast java/math/BigInteger
    //   10: invokevirtual toByteArray : ()[B
    //   13: astore_3
    //   14: iconst_0
    //   15: istore #5
    //   17: iconst_0
    //   18: istore #6
    //   20: iload #6
    //   22: aload_3
    //   23: arraylength
    //   24: if_icmpge -> 169
    //   27: aload_3
    //   28: iload #6
    //   30: baload
    //   31: istore #7
    //   33: iload #7
    //   35: bipush #48
    //   37: if_icmplt -> 54
    //   40: iload #7
    //   42: bipush #57
    //   44: if_icmple -> 152
    //   47: goto -> 54
    //   50: invokestatic a : (Ljava/lang/Throwable;)Ljava/lang/Throwable;
    //   53: athrow
    //   54: iload #7
    //   56: bipush #65
    //   58: if_icmplt -> 82
    //   61: goto -> 68
    //   64: invokestatic a : (Ljava/lang/Throwable;)Ljava/lang/Throwable;
    //   67: athrow
    //   68: iload #7
    //   70: bipush #90
    //   72: if_icmple -> 152
    //   75: goto -> 82
    //   78: invokestatic a : (Ljava/lang/Throwable;)Ljava/lang/Throwable;
    //   81: athrow
    //   82: iload #7
    //   84: bipush #97
    //   86: if_icmplt -> 110
    //   89: goto -> 96
    //   92: invokestatic a : (Ljava/lang/Throwable;)Ljava/lang/Throwable;
    //   95: athrow
    //   96: iload #7
    //   98: bipush #122
    //   100: if_icmple -> 152
    //   103: goto -> 110
    //   106: invokestatic a : (Ljava/lang/Throwable;)Ljava/lang/Throwable;
    //   109: athrow
    //   110: iload #7
    //   112: bipush #43
    //   114: if_icmpeq -> 152
    //   117: goto -> 124
    //   120: invokestatic a : (Ljava/lang/Throwable;)Ljava/lang/Throwable;
    //   123: athrow
    //   124: iload #7
    //   126: bipush #47
    //   128: if_icmpeq -> 152
    //   131: goto -> 138
    //   134: invokestatic a : (Ljava/lang/Throwable;)Ljava/lang/Throwable;
    //   137: athrow
    //   138: iload #7
    //   140: bipush #61
    //   142: if_icmpne -> 162
    //   145: goto -> 152
    //   148: invokestatic a : (Ljava/lang/Throwable;)Ljava/lang/Throwable;
    //   151: athrow
    //   152: iinc #5, 1
    //   155: goto -> 162
    //   158: invokestatic a : (Ljava/lang/Throwable;)Ljava/lang/Throwable;
    //   161: athrow
    //   162: iinc #6, 1
    //   165: iload_2
    //   166: ifne -> 20
    //   169: iload #5
    //   171: newarray byte
    //   173: astore #6
    //   175: iconst_0
    //   176: istore #7
    //   178: iconst_0
    //   179: istore #8
    //   181: iload #8
    //   183: aload_3
    //   184: arraylength
    //   185: if_icmpge -> 337
    //   188: aload_3
    //   189: iload #8
    //   191: baload
    //   192: istore #9
    //   194: iload #9
    //   196: bipush #48
    //   198: if_icmplt -> 215
    //   201: iload #9
    //   203: bipush #57
    //   205: if_icmple -> 313
    //   208: goto -> 215
    //   211: invokestatic a : (Ljava/lang/Throwable;)Ljava/lang/Throwable;
    //   214: athrow
    //   215: iload #9
    //   217: bipush #65
    //   219: if_icmplt -> 243
    //   222: goto -> 229
    //   225: invokestatic a : (Ljava/lang/Throwable;)Ljava/lang/Throwable;
    //   228: athrow
    //   229: iload #9
    //   231: bipush #90
    //   233: if_icmple -> 313
    //   236: goto -> 243
    //   239: invokestatic a : (Ljava/lang/Throwable;)Ljava/lang/Throwable;
    //   242: athrow
    //   243: iload #9
    //   245: bipush #97
    //   247: if_icmplt -> 271
    //   250: goto -> 257
    //   253: invokestatic a : (Ljava/lang/Throwable;)Ljava/lang/Throwable;
    //   256: athrow
    //   257: iload #9
    //   259: bipush #122
    //   261: if_icmple -> 313
    //   264: goto -> 271
    //   267: invokestatic a : (Ljava/lang/Throwable;)Ljava/lang/Throwable;
    //   270: athrow
    //   271: iload #9
    //   273: bipush #43
    //   275: if_icmpeq -> 313
    //   278: goto -> 285
    //   281: invokestatic a : (Ljava/lang/Throwable;)Ljava/lang/Throwable;
    //   284: athrow
    //   285: iload #9
    //   287: bipush #47
    //   289: if_icmpeq -> 313
    //   292: goto -> 299
    //   295: invokestatic a : (Ljava/lang/Throwable;)Ljava/lang/Throwable;
    //   298: athrow
    //   299: iload #9
    //   301: bipush #61
    //   303: if_icmpne -> 330
    //   306: goto -> 313
    //   309: invokestatic a : (Ljava/lang/Throwable;)Ljava/lang/Throwable;
    //   312: athrow
    //   313: aload #6
    //   315: iload #7
    //   317: iload #9
    //   319: bastore
    //   320: iinc #7, 1
    //   323: goto -> 330
    //   326: invokestatic a : (Ljava/lang/Throwable;)Ljava/lang/Throwable;
    //   329: athrow
    //   330: iinc #8, 1
    //   333: iload_2
    //   334: ifne -> 181
    //   337: aload #6
    //   339: astore #4
    //   341: aload #4
    //   343: astore_3
    //   344: aload_3
    //   345: arraylength
    //   346: istore #5
    //   348: aload_3
    //   349: iload #5
    //   351: iconst_1
    //   352: isub
    //   353: baload
    //   354: bipush #61
    //   356: if_icmpne -> 366
    //   359: iinc #5, -1
    //   362: iload_2
    //   363: ifne -> 348
    //   366: iload #5
    //   368: aload_3
    //   369: arraylength
    //   370: iconst_4
    //   371: idiv
    //   372: isub
    //   373: newarray byte
    //   375: astore #6
    //   377: iconst_0
    //   378: istore #7
    //   380: iload #7
    //   382: aload_3
    //   383: arraylength
    //   384: if_icmpge -> 646
    //   387: aload_3
    //   388: iload #7
    //   390: baload
    //   391: bipush #61
    //   393: if_icmpne -> 412
    //   396: aload_3
    //   397: iload #7
    //   399: iconst_0
    //   400: bastore
    //   401: iload_2
    //   402: ifne -> 639
    //   405: goto -> 412
    //   408: invokestatic a : (Ljava/lang/Throwable;)Ljava/lang/Throwable;
    //   411: athrow
    //   412: aload_3
    //   413: iload #7
    //   415: baload
    //   416: bipush #47
    //   418: if_icmpne -> 445
    //   421: goto -> 428
    //   424: invokestatic a : (Ljava/lang/Throwable;)Ljava/lang/Throwable;
    //   427: athrow
    //   428: aload_3
    //   429: iload #7
    //   431: bipush #63
    //   433: bastore
    //   434: iload_2
    //   435: ifne -> 639
    //   438: goto -> 445
    //   441: invokestatic a : (Ljava/lang/Throwable;)Ljava/lang/Throwable;
    //   444: athrow
    //   445: aload_3
    //   446: iload #7
    //   448: baload
    //   449: bipush #43
    //   451: if_icmpne -> 478
    //   454: goto -> 461
    //   457: invokestatic a : (Ljava/lang/Throwable;)Ljava/lang/Throwable;
    //   460: athrow
    //   461: aload_3
    //   462: iload #7
    //   464: bipush #62
    //   466: bastore
    //   467: iload_2
    //   468: ifne -> 639
    //   471: goto -> 478
    //   474: invokestatic a : (Ljava/lang/Throwable;)Ljava/lang/Throwable;
    //   477: athrow
    //   478: aload_3
    //   479: iload #7
    //   481: baload
    //   482: bipush #48
    //   484: if_icmplt -> 533
    //   487: goto -> 494
    //   490: invokestatic a : (Ljava/lang/Throwable;)Ljava/lang/Throwable;
    //   493: athrow
    //   494: aload_3
    //   495: iload #7
    //   497: baload
    //   498: bipush #57
    //   500: if_icmpgt -> 533
    //   503: goto -> 510
    //   506: invokestatic a : (Ljava/lang/Throwable;)Ljava/lang/Throwable;
    //   509: athrow
    //   510: aload_3
    //   511: iload #7
    //   513: aload_3
    //   514: iload #7
    //   516: baload
    //   517: bipush #-4
    //   519: isub
    //   520: i2b
    //   521: bastore
    //   522: iload_2
    //   523: ifne -> 639
    //   526: goto -> 533
    //   529: invokestatic a : (Ljava/lang/Throwable;)Ljava/lang/Throwable;
    //   532: athrow
    //   533: aload_3
    //   534: iload #7
    //   536: baload
    //   537: bipush #97
    //   539: if_icmplt -> 588
    //   542: goto -> 549
    //   545: invokestatic a : (Ljava/lang/Throwable;)Ljava/lang/Throwable;
    //   548: athrow
    //   549: aload_3
    //   550: iload #7
    //   552: baload
    //   553: bipush #122
    //   555: if_icmpgt -> 588
    //   558: goto -> 565
    //   561: invokestatic a : (Ljava/lang/Throwable;)Ljava/lang/Throwable;
    //   564: athrow
    //   565: aload_3
    //   566: iload #7
    //   568: aload_3
    //   569: iload #7
    //   571: baload
    //   572: bipush #71
    //   574: isub
    //   575: i2b
    //   576: bastore
    //   577: iload_2
    //   578: ifne -> 639
    //   581: goto -> 588
    //   584: invokestatic a : (Ljava/lang/Throwable;)Ljava/lang/Throwable;
    //   587: athrow
    //   588: aload_3
    //   589: iload #7
    //   591: baload
    //   592: bipush #65
    //   594: if_icmplt -> 639
    //   597: goto -> 604
    //   600: invokestatic a : (Ljava/lang/Throwable;)Ljava/lang/Throwable;
    //   603: athrow
    //   604: aload_3
    //   605: iload #7
    //   607: baload
    //   608: bipush #90
    //   610: if_icmpgt -> 639
    //   613: goto -> 620
    //   616: invokestatic a : (Ljava/lang/Throwable;)Ljava/lang/Throwable;
    //   619: athrow
    //   620: aload_3
    //   621: iload #7
    //   623: aload_3
    //   624: iload #7
    //   626: baload
    //   627: bipush #65
    //   629: isub
    //   630: i2b
    //   631: bastore
    //   632: goto -> 639
    //   635: invokestatic a : (Ljava/lang/Throwable;)Ljava/lang/Throwable;
    //   638: athrow
    //   639: iinc #7, 1
    //   642: iload_2
    //   643: ifne -> 380
    //   646: iconst_0
    //   647: istore #7
    //   649: iconst_0
    //   650: istore #8
    //   652: iload #8
    //   654: aload #6
    //   656: arraylength
    //   657: iconst_2
    //   658: isub
    //   659: if_icmpge -> 762
    //   662: aload #6
    //   664: iload #8
    //   666: aload_3
    //   667: iload #7
    //   669: baload
    //   670: iconst_2
    //   671: ishl
    //   672: sipush #255
    //   675: iand
    //   676: aload_3
    //   677: iload #7
    //   679: iconst_1
    //   680: iadd
    //   681: baload
    //   682: iconst_4
    //   683: iushr
    //   684: iconst_3
    //   685: iand
    //   686: ior
    //   687: i2b
    //   688: bastore
    //   689: aload #6
    //   691: iload #8
    //   693: iconst_1
    //   694: iadd
    //   695: aload_3
    //   696: iload #7
    //   698: iconst_1
    //   699: iadd
    //   700: baload
    //   701: iconst_4
    //   702: ishl
    //   703: sipush #255
    //   706: iand
    //   707: aload_3
    //   708: iload #7
    //   710: iconst_2
    //   711: iadd
    //   712: baload
    //   713: iconst_2
    //   714: iushr
    //   715: bipush #15
    //   717: iand
    //   718: ior
    //   719: i2b
    //   720: bastore
    //   721: aload #6
    //   723: iload #8
    //   725: iconst_2
    //   726: iadd
    //   727: aload_3
    //   728: iload #7
    //   730: iconst_2
    //   731: iadd
    //   732: baload
    //   733: bipush #6
    //   735: ishl
    //   736: sipush #255
    //   739: iand
    //   740: aload_3
    //   741: iload #7
    //   743: iconst_3
    //   744: iadd
    //   745: baload
    //   746: bipush #63
    //   748: iand
    //   749: ior
    //   750: i2b
    //   751: bastore
    //   752: iinc #7, 4
    //   755: iinc #8, 3
    //   758: iload_2
    //   759: ifne -> 652
    //   762: iload #8
    //   764: aload #6
    //   766: arraylength
    //   767: if_icmpge -> 804
    //   770: aload #6
    //   772: iload #8
    //   774: aload_3
    //   775: iload #7
    //   777: baload
    //   778: iconst_2
    //   779: ishl
    //   780: sipush #255
    //   783: iand
    //   784: aload_3
    //   785: iload #7
    //   787: iconst_1
    //   788: iadd
    //   789: baload
    //   790: iconst_4
    //   791: iushr
    //   792: iconst_3
    //   793: iand
    //   794: ior
    //   795: i2b
    //   796: bastore
    //   797: goto -> 804
    //   800: invokestatic a : (Ljava/lang/Throwable;)Ljava/lang/Throwable;
    //   803: athrow
    //   804: iinc #8, 1
    //   807: iload #8
    //   809: aload #6
    //   811: arraylength
    //   812: if_icmpge -> 852
    //   815: aload #6
    //   817: iload #8
    //   819: aload_3
    //   820: iload #7
    //   822: iconst_1
    //   823: iadd
    //   824: baload
    //   825: iconst_4
    //   826: ishl
    //   827: sipush #255
    //   830: iand
    //   831: aload_3
    //   832: iload #7
    //   834: iconst_2
    //   835: iadd
    //   836: baload
    //   837: iconst_2
    //   838: iushr
    //   839: bipush #15
    //   841: iand
    //   842: ior
    //   843: i2b
    //   844: bastore
    //   845: goto -> 852
    //   848: invokestatic a : (Ljava/lang/Throwable;)Ljava/lang/Throwable;
    //   851: athrow
    //   852: aload #6
    //   854: astore #4
    //   856: new java/math/BigInteger
    //   859: dup
    //   860: aload #4
    //   862: invokespecial <init> : ([B)V
    //   865: invokevirtual abs : ()Ljava/math/BigInteger;
    //   868: putstatic burp/Ze6k.Zs : Ljava/lang/Object;
    //   871: new java/io/ByteArrayOutputStream
    //   874: dup
    //   875: invokespecial <init> : ()V
    //   878: astore_3
    //   879: getstatic burp/Zxjm.ZG : Ljava/lang/String;
    //   882: astore #4
    //   884: iconst_0
    //   885: istore #5
    //   887: iload #5
    //   889: aload #4
    //   891: invokevirtual length : ()I
    //   894: if_icmpge -> 924
    //   897: aload_3
    //   898: aload #4
    //   900: iload #5
    //   902: iload #5
    //   904: iconst_2
    //   905: iadd
    //   906: invokevirtual substring : (II)Ljava/lang/String;
    //   909: bipush #16
    //   911: invokestatic parseInt : (Ljava/lang/String;I)I
    //   914: invokevirtual write : (I)V
    //   917: iinc #5, 2
    //   920: iload_2
    //   921: ifne -> 887
    //   924: aload_3
    //   925: invokevirtual toByteArray : ()[B
    //   928: astore #5
    //   930: getstatic burp/Ztfr.Zr : Ljava/lang/Object;
    //   933: checkcast java/math/BigInteger
    //   936: invokevirtual toByteArray : ()[B
    //   939: astore #6
    //   941: sipush #256
    //   944: newarray byte
    //   946: astore #8
    //   948: sipush #256
    //   951: newarray int
    //   953: astore #9
    //   955: sipush #256
    //   958: newarray int
    //   960: astore #10
    //   962: sipush #256
    //   965: newarray int
    //   967: astore #11
    //   969: sipush #256
    //   972: newarray int
    //   974: astore #12
    //   976: bipush #10
    //   978: newarray int
    //   980: astore #13
    //   982: sipush #283
    //   985: istore #14
    //   987: iconst_0
    //   988: istore #16
    //   990: iload #16
    //   992: sipush #256
    //   995: if_icmpge -> 1229
    //   998: sipush #18650
    //   1001: sipush #25230
    //   1004: invokestatic a : (II)Ljava/lang/String;
    //   1007: iload #16
    //   1009: iconst_1
    //   1010: iushr
    //   1011: invokevirtual charAt : (I)C
    //   1014: istore #25
    //   1016: iload #16
    //   1018: iconst_1
    //   1019: iand
    //   1020: ifne -> 1035
    //   1023: iload #25
    //   1025: bipush #8
    //   1027: iushr
    //   1028: goto -> 1037
    //   1031: invokestatic a : (Ljava/lang/Throwable;)Ljava/lang/Throwable;
    //   1034: athrow
    //   1035: iload #25
    //   1037: i2b
    //   1038: sipush #255
    //   1041: iand
    //   1042: istore #15
    //   1044: iload #16
    //   1046: iconst_1
    //   1047: ishl
    //   1048: istore #17
    //   1050: iload #17
    //   1052: sipush #256
    //   1055: if_icmplt -> 1065
    //   1058: iload #17
    //   1060: iload #14
    //   1062: ixor
    //   1063: istore #17
    //   1065: iload #17
    //   1067: iconst_1
    //   1068: ishl
    //   1069: istore #18
    //   1071: iload #18
    //   1073: sipush #256
    //   1076: if_icmplt -> 1086
    //   1079: iload #18
    //   1081: iload #14
    //   1083: ixor
    //   1084: istore #18
    //   1086: iload #18
    //   1088: iconst_1
    //   1089: ishl
    //   1090: istore #19
    //   1092: iload #19
    //   1094: sipush #256
    //   1097: if_icmplt -> 1107
    //   1100: iload #19
    //   1102: iload #14
    //   1104: ixor
    //   1105: istore #19
    //   1107: iload #19
    //   1109: iload #16
    //   1111: ixor
    //   1112: istore #20
    //   1114: iload #20
    //   1116: iload #17
    //   1118: ixor
    //   1119: istore #21
    //   1121: iload #20
    //   1123: iload #18
    //   1125: ixor
    //   1126: istore #22
    //   1128: iload #19
    //   1130: iload #18
    //   1132: ixor
    //   1133: iload #17
    //   1135: ixor
    //   1136: istore #23
    //   1138: aload #8
    //   1140: iload #16
    //   1142: iload #15
    //   1144: i2b
    //   1145: bastore
    //   1146: aload #9
    //   1148: iload #15
    //   1150: iload #23
    //   1152: bipush #24
    //   1154: ishl
    //   1155: iload #20
    //   1157: bipush #16
    //   1159: ishl
    //   1160: ior
    //   1161: iload #22
    //   1163: bipush #8
    //   1165: ishl
    //   1166: ior
    //   1167: iload #21
    //   1169: ior
    //   1170: dup
    //   1171: istore #24
    //   1173: iastore
    //   1174: aload #10
    //   1176: iload #15
    //   1178: iload #24
    //   1180: bipush #8
    //   1182: iushr
    //   1183: iload #24
    //   1185: bipush #24
    //   1187: ishl
    //   1188: ior
    //   1189: iastore
    //   1190: aload #11
    //   1192: iload #15
    //   1194: iload #24
    //   1196: bipush #16
    //   1198: iushr
    //   1199: iload #24
    //   1201: bipush #16
    //   1203: ishl
    //   1204: ior
    //   1205: iastore
    //   1206: aload #12
    //   1208: iload #15
    //   1210: iload #24
    //   1212: bipush #24
    //   1214: iushr
    //   1215: iload #24
    //   1217: bipush #8
    //   1219: ishl
    //   1220: ior
    //   1221: iastore
    //   1222: iinc #16, 1
    //   1225: iload_2
    //   1226: ifne -> 990
    //   1229: iconst_1
    //   1230: istore #25
    //   1232: aload #13
    //   1234: iconst_0
    //   1235: iload #25
    //   1237: bipush #24
    //   1239: ishl
    //   1240: iastore
    //   1241: iconst_1
    //   1242: istore #26
    //   1244: iload #26
    //   1246: bipush #10
    //   1248: if_icmpge -> 1289
    //   1251: iload #25
    //   1253: iconst_1
    //   1254: ishl
    //   1255: istore #25
    //   1257: iload #25
    //   1259: sipush #256
    //   1262: if_icmplt -> 1272
    //   1265: iload #25
    //   1267: iload #14
    //   1269: ixor
    //   1270: istore #25
    //   1272: aload #13
    //   1274: iload #26
    //   1276: iload #25
    //   1278: bipush #24
    //   1280: ishl
    //   1281: iastore
    //   1282: iinc #26, 1
    //   1285: iload_2
    //   1286: ifne -> 1244
    //   1289: iconst_4
    //   1290: istore #26
    //   1292: iload #26
    //   1294: bipush #6
    //   1296: iadd
    //   1297: istore #27
    //   1299: iconst_4
    //   1300: iload #27
    //   1302: iconst_1
    //   1303: iadd
    //   1304: imul
    //   1305: istore #28
    //   1307: iload #28
    //   1309: newarray int
    //   1311: astore #29
    //   1313: iload #28
    //   1315: newarray int
    //   1317: astore #30
    //   1319: iconst_0
    //   1320: istore #25
    //   1322: iconst_0
    //   1323: istore #32
    //   1325: iconst_0
    //   1326: istore #33
    //   1328: iload #32
    //   1330: iload #26
    //   1332: if_icmpge -> 1400
    //   1335: aload #29
    //   1337: iload #32
    //   1339: aload #5
    //   1341: iload #33
    //   1343: baload
    //   1344: bipush #24
    //   1346: ishl
    //   1347: aload #5
    //   1349: iload #33
    //   1351: iconst_1
    //   1352: iadd
    //   1353: baload
    //   1354: sipush #255
    //   1357: iand
    //   1358: bipush #16
    //   1360: ishl
    //   1361: ior
    //   1362: aload #5
    //   1364: iload #33
    //   1366: iconst_2
    //   1367: iadd
    //   1368: baload
    //   1369: sipush #255
    //   1372: iand
    //   1373: bipush #8
    //   1375: ishl
    //   1376: ior
    //   1377: aload #5
    //   1379: iload #33
    //   1381: iconst_3
    //   1382: iadd
    //   1383: baload
    //   1384: sipush #255
    //   1387: iand
    //   1388: ior
    //   1389: iastore
    //   1390: iinc #32, 1
    //   1393: iinc #33, 4
    //   1396: iload_2
    //   1397: ifne -> 1328
    //   1400: iload #26
    //   1402: istore #32
    //   1404: iconst_0
    //   1405: istore #33
    //   1407: iload #32
    //   1409: iload #28
    //   1411: if_icmpge -> 1538
    //   1414: aload #29
    //   1416: iload #32
    //   1418: iconst_1
    //   1419: isub
    //   1420: iaload
    //   1421: istore #31
    //   1423: iload #33
    //   1425: ifne -> 1512
    //   1428: iload #26
    //   1430: istore #33
    //   1432: aload #8
    //   1434: iload #31
    //   1436: bipush #16
    //   1438: iushr
    //   1439: sipush #255
    //   1442: iand
    //   1443: baload
    //   1444: bipush #24
    //   1446: ishl
    //   1447: aload #8
    //   1449: iload #31
    //   1451: bipush #8
    //   1453: iushr
    //   1454: sipush #255
    //   1457: iand
    //   1458: baload
    //   1459: sipush #255
    //   1462: iand
    //   1463: bipush #16
    //   1465: ishl
    //   1466: ior
    //   1467: aload #8
    //   1469: iload #31
    //   1471: sipush #255
    //   1474: iand
    //   1475: baload
    //   1476: sipush #255
    //   1479: iand
    //   1480: bipush #8
    //   1482: ishl
    //   1483: ior
    //   1484: aload #8
    //   1486: iload #31
    //   1488: bipush #24
    //   1490: iushr
    //   1491: baload
    //   1492: sipush #255
    //   1495: iand
    //   1496: ior
    //   1497: istore #31
    //   1499: iload #31
    //   1501: aload #13
    //   1503: iload #25
    //   1505: iinc #25, 1
    //   1508: iaload
    //   1509: ixor
    //   1510: istore #31
    //   1512: aload #29
    //   1514: iload #32
    //   1516: aload #29
    //   1518: iload #32
    //   1520: iload #26
    //   1522: isub
    //   1523: iaload
    //   1524: iload #31
    //   1526: ixor
    //   1527: iastore
    //   1528: iinc #32, 1
    //   1531: iinc #33, -1
    //   1534: iload_2
    //   1535: ifne -> 1407
    //   1538: iconst_0
    //   1539: istore #32
    //   1541: iconst_4
    //   1542: iload #27
    //   1544: imul
    //   1545: istore #33
    //   1547: aload #30
    //   1549: iload #32
    //   1551: aload #29
    //   1553: iload #33
    //   1555: iaload
    //   1556: iastore
    //   1557: aload #30
    //   1559: iload #32
    //   1561: iconst_1
    //   1562: iadd
    //   1563: aload #29
    //   1565: iload #33
    //   1567: iconst_1
    //   1568: iadd
    //   1569: iaload
    //   1570: iastore
    //   1571: aload #30
    //   1573: iload #32
    //   1575: iconst_2
    //   1576: iadd
    //   1577: aload #29
    //   1579: iload #33
    //   1581: iconst_2
    //   1582: iadd
    //   1583: iaload
    //   1584: iastore
    //   1585: aload #30
    //   1587: iload #32
    //   1589: iconst_3
    //   1590: iadd
    //   1591: aload #29
    //   1593: iload #33
    //   1595: iconst_3
    //   1596: iadd
    //   1597: iaload
    //   1598: iastore
    //   1599: iinc #32, 4
    //   1602: iinc #33, -4
    //   1605: iconst_1
    //   1606: istore #35
    //   1608: iload #35
    //   1610: iload #27
    //   1612: if_icmpge -> 1976
    //   1615: aload #29
    //   1617: iload #33
    //   1619: iaload
    //   1620: istore #34
    //   1622: aload #30
    //   1624: iload #32
    //   1626: aload #9
    //   1628: aload #8
    //   1630: iload #34
    //   1632: bipush #24
    //   1634: iushr
    //   1635: baload
    //   1636: sipush #255
    //   1639: iand
    //   1640: iaload
    //   1641: aload #10
    //   1643: aload #8
    //   1645: iload #34
    //   1647: bipush #16
    //   1649: iushr
    //   1650: sipush #255
    //   1653: iand
    //   1654: baload
    //   1655: sipush #255
    //   1658: iand
    //   1659: iaload
    //   1660: ixor
    //   1661: aload #11
    //   1663: aload #8
    //   1665: iload #34
    //   1667: bipush #8
    //   1669: iushr
    //   1670: sipush #255
    //   1673: iand
    //   1674: baload
    //   1675: sipush #255
    //   1678: iand
    //   1679: iaload
    //   1680: ixor
    //   1681: aload #12
    //   1683: aload #8
    //   1685: iload #34
    //   1687: sipush #255
    //   1690: iand
    //   1691: baload
    //   1692: sipush #255
    //   1695: iand
    //   1696: iaload
    //   1697: ixor
    //   1698: iastore
    //   1699: aload #29
    //   1701: iload #33
    //   1703: iconst_1
    //   1704: iadd
    //   1705: iaload
    //   1706: istore #34
    //   1708: aload #30
    //   1710: iload #32
    //   1712: iconst_1
    //   1713: iadd
    //   1714: aload #9
    //   1716: aload #8
    //   1718: iload #34
    //   1720: bipush #24
    //   1722: iushr
    //   1723: baload
    //   1724: sipush #255
    //   1727: iand
    //   1728: iaload
    //   1729: aload #10
    //   1731: aload #8
    //   1733: iload #34
    //   1735: bipush #16
    //   1737: iushr
    //   1738: sipush #255
    //   1741: iand
    //   1742: baload
    //   1743: sipush #255
    //   1746: iand
    //   1747: iaload
    //   1748: ixor
    //   1749: aload #11
    //   1751: aload #8
    //   1753: iload #34
    //   1755: bipush #8
    //   1757: iushr
    //   1758: sipush #255
    //   1761: iand
    //   1762: baload
    //   1763: sipush #255
    //   1766: iand
    //   1767: iaload
    //   1768: ixor
    //   1769: aload #12
    //   1771: aload #8
    //   1773: iload #34
    //   1775: sipush #255
    //   1778: iand
    //   1779: baload
    //   1780: sipush #255
    //   1783: iand
    //   1784: iaload
    //   1785: ixor
    //   1786: iastore
    //   1787: aload #29
    //   1789: iload #33
    //   1791: iconst_2
    //   1792: iadd
    //   1793: iaload
    //   1794: istore #34
    //   1796: aload #30
    //   1798: iload #32
    //   1800: iconst_2
    //   1801: iadd
    //   1802: aload #9
    //   1804: aload #8
    //   1806: iload #34
    //   1808: bipush #24
    //   1810: iushr
    //   1811: baload
    //   1812: sipush #255
    //   1815: iand
    //   1816: iaload
    //   1817: aload #10
    //   1819: aload #8
    //   1821: iload #34
    //   1823: bipush #16
    //   1825: iushr
    //   1826: sipush #255
    //   1829: iand
    //   1830: baload
    //   1831: sipush #255
    //   1834: iand
    //   1835: iaload
    //   1836: ixor
    //   1837: aload #11
    //   1839: aload #8
    //   1841: iload #34
    //   1843: bipush #8
    //   1845: iushr
    //   1846: sipush #255
    //   1849: iand
    //   1850: baload
    //   1851: sipush #255
    //   1854: iand
    //   1855: iaload
    //   1856: ixor
    //   1857: aload #12
    //   1859: aload #8
    //   1861: iload #34
    //   1863: sipush #255
    //   1866: iand
    //   1867: baload
    //   1868: sipush #255
    //   1871: iand
    //   1872: iaload
    //   1873: ixor
    //   1874: iastore
    //   1875: aload #29
    //   1877: iload #33
    //   1879: iconst_3
    //   1880: iadd
    //   1881: iaload
    //   1882: istore #34
    //   1884: aload #30
    //   1886: iload #32
    //   1888: iconst_3
    //   1889: iadd
    //   1890: aload #9
    //   1892: aload #8
    //   1894: iload #34
    //   1896: bipush #24
    //   1898: iushr
    //   1899: baload
    //   1900: sipush #255
    //   1903: iand
    //   1904: iaload
    //   1905: aload #10
    //   1907: aload #8
    //   1909: iload #34
    //   1911: bipush #16
    //   1913: iushr
    //   1914: sipush #255
    //   1917: iand
    //   1918: baload
    //   1919: sipush #255
    //   1922: iand
    //   1923: iaload
    //   1924: ixor
    //   1925: aload #11
    //   1927: aload #8
    //   1929: iload #34
    //   1931: bipush #8
    //   1933: iushr
    //   1934: sipush #255
    //   1937: iand
    //   1938: baload
    //   1939: sipush #255
    //   1942: iand
    //   1943: iaload
    //   1944: ixor
    //   1945: aload #12
    //   1947: aload #8
    //   1949: iload #34
    //   1951: sipush #255
    //   1954: iand
    //   1955: baload
    //   1956: sipush #255
    //   1959: iand
    //   1960: iaload
    //   1961: ixor
    //   1962: iastore
    //   1963: iinc #32, 4
    //   1966: iinc #33, -4
    //   1969: iinc #35, 1
    //   1972: iload_2
    //   1973: ifne -> 1608
    //   1976: aload #30
    //   1978: iload #32
    //   1980: aload #29
    //   1982: iload #33
    //   1984: iaload
    //   1985: iastore
    //   1986: aload #30
    //   1988: iload #32
    //   1990: iconst_1
    //   1991: iadd
    //   1992: aload #29
    //   1994: iload #33
    //   1996: iconst_1
    //   1997: iadd
    //   1998: iaload
    //   1999: iastore
    //   2000: aload #30
    //   2002: iload #32
    //   2004: iconst_2
    //   2005: iadd
    //   2006: aload #29
    //   2008: iload #33
    //   2010: iconst_2
    //   2011: iadd
    //   2012: iaload
    //   2013: iastore
    //   2014: aload #30
    //   2016: iload #32
    //   2018: iconst_3
    //   2019: iadd
    //   2020: aload #29
    //   2022: iload #33
    //   2024: iconst_3
    //   2025: iadd
    //   2026: iaload
    //   2027: iastore
    //   2028: iconst_0
    //   2029: newarray byte
    //   2031: astore #35
    //   2033: aload #6
    //   2035: arraylength
    //   2036: bipush #16
    //   2038: irem
    //   2039: ifeq -> 2063
    //   2042: new java/lang/Exception
    //   2045: dup
    //   2046: sipush #18628
    //   2049: sipush #-16259
    //   2052: invokestatic a : (II)Ljava/lang/String;
    //   2055: invokespecial <init> : (Ljava/lang/String;)V
    //   2058: athrow
    //   2059: invokestatic a : (Ljava/lang/Throwable;)Ljava/lang/Throwable;
    //   2062: athrow
    //   2063: bipush #10
    //   2065: istore #36
    //   2067: sipush #18624
    //   2070: sipush #256
    //   2073: newarray byte
    //   2075: astore #37
    //   2077: sipush #-20362
    //   2080: sipush #256
    //   2083: newarray int
    //   2085: astore #38
    //   2087: sipush #256
    //   2090: newarray int
    //   2092: astore #39
    //   2094: sipush #256
    //   2097: newarray int
    //   2099: astore #40
    //   2101: sipush #256
    //   2104: newarray int
    //   2106: astore #41
    //   2108: sipush #283
    //   2111: istore #14
    //   2113: invokestatic a : (II)Ljava/lang/String;
    //   2116: astore #42
    //   2118: iconst_0
    //   2119: istore #16
    //   2121: iload #16
    //   2123: sipush #256
    //   2126: if_icmpge -> 2353
    //   2129: aload #42
    //   2131: iload #16
    //   2133: iconst_1
    //   2134: iushr
    //   2135: invokevirtual charAt : (I)C
    //   2138: istore #43
    //   2140: iload #16
    //   2142: iconst_1
    //   2143: iand
    //   2144: ifne -> 2159
    //   2147: iload #43
    //   2149: bipush #8
    //   2151: iushr
    //   2152: goto -> 2161
    //   2155: invokestatic a : (Ljava/lang/Throwable;)Ljava/lang/Throwable;
    //   2158: athrow
    //   2159: iload #43
    //   2161: i2b
    //   2162: sipush #255
    //   2165: iand
    //   2166: istore #15
    //   2168: iload #16
    //   2170: iconst_1
    //   2171: ishl
    //   2172: istore #17
    //   2174: iload #17
    //   2176: sipush #256
    //   2179: if_icmplt -> 2189
    //   2182: iload #17
    //   2184: iload #14
    //   2186: ixor
    //   2187: istore #17
    //   2189: iload #17
    //   2191: iconst_1
    //   2192: ishl
    //   2193: istore #18
    //   2195: iload #18
    //   2197: sipush #256
    //   2200: if_icmplt -> 2210
    //   2203: iload #18
    //   2205: iload #14
    //   2207: ixor
    //   2208: istore #18
    //   2210: iload #18
    //   2212: iconst_1
    //   2213: ishl
    //   2214: istore #19
    //   2216: iload #19
    //   2218: sipush #256
    //   2221: if_icmplt -> 2231
    //   2224: iload #19
    //   2226: iload #14
    //   2228: ixor
    //   2229: istore #19
    //   2231: iload #19
    //   2233: iload #16
    //   2235: ixor
    //   2236: istore #20
    //   2238: iload #20
    //   2240: iload #17
    //   2242: ixor
    //   2243: istore #21
    //   2245: iload #20
    //   2247: iload #18
    //   2249: ixor
    //   2250: istore #22
    //   2252: iload #19
    //   2254: iload #18
    //   2256: ixor
    //   2257: iload #17
    //   2259: ixor
    //   2260: istore #23
    //   2262: aload #37
    //   2264: iload #15
    //   2266: iload #16
    //   2268: i2b
    //   2269: bastore
    //   2270: aload #38
    //   2272: iload #15
    //   2274: iload #23
    //   2276: bipush #24
    //   2278: ishl
    //   2279: iload #20
    //   2281: bipush #16
    //   2283: ishl
    //   2284: ior
    //   2285: iload #22
    //   2287: bipush #8
    //   2289: ishl
    //   2290: ior
    //   2291: iload #21
    //   2293: ior
    //   2294: dup
    //   2295: istore #24
    //   2297: iastore
    //   2298: aload #39
    //   2300: iload #15
    //   2302: iload #24
    //   2304: bipush #8
    //   2306: iushr
    //   2307: iload #24
    //   2309: bipush #24
    //   2311: ishl
    //   2312: ior
    //   2313: iastore
    //   2314: aload #40
    //   2316: iload #15
    //   2318: iload #24
    //   2320: bipush #16
    //   2322: iushr
    //   2323: iload #24
    //   2325: bipush #16
    //   2327: ishl
    //   2328: ior
    //   2329: iastore
    //   2330: aload #41
    //   2332: iload #15
    //   2334: iload #24
    //   2336: bipush #24
    //   2338: iushr
    //   2339: iload #24
    //   2341: bipush #8
    //   2343: ishl
    //   2344: ior
    //   2345: iastore
    //   2346: iinc #16, 1
    //   2349: iload_2
    //   2350: ifne -> 2121
    //   2353: aload #6
    //   2355: arraylength
    //   2356: newarray byte
    //   2358: astore #43
    //   2360: iconst_0
    //   2361: istore #44
    //   2363: iload #44
    //   2365: aload #6
    //   2367: arraylength
    //   2368: bipush #16
    //   2370: idiv
    //   2371: if_icmpge -> 3285
    //   2374: bipush #16
    //   2376: newarray byte
    //   2378: astore #45
    //   2380: bipush #16
    //   2382: newarray byte
    //   2384: astore #46
    //   2386: iconst_0
    //   2387: istore #47
    //   2389: iload #47
    //   2391: bipush #16
    //   2393: if_icmpge -> 2419
    //   2396: aload #45
    //   2398: iload #47
    //   2400: aload #6
    //   2402: iload #47
    //   2404: iload #44
    //   2406: bipush #16
    //   2408: imul
    //   2409: iadd
    //   2410: baload
    //   2411: bastore
    //   2412: iinc #47, 1
    //   2415: iload_2
    //   2416: ifne -> 2389
    //   2419: iconst_0
    //   2420: istore #47
    //   2422: aload #45
    //   2424: iconst_0
    //   2425: baload
    //   2426: bipush #24
    //   2428: ishl
    //   2429: aload #45
    //   2431: iconst_1
    //   2432: baload
    //   2433: sipush #255
    //   2436: iand
    //   2437: bipush #16
    //   2439: ishl
    //   2440: ior
    //   2441: aload #45
    //   2443: iconst_2
    //   2444: baload
    //   2445: sipush #255
    //   2448: iand
    //   2449: bipush #8
    //   2451: ishl
    //   2452: ior
    //   2453: aload #45
    //   2455: iconst_3
    //   2456: baload
    //   2457: sipush #255
    //   2460: iand
    //   2461: ior
    //   2462: aload #30
    //   2464: iconst_0
    //   2465: iaload
    //   2466: ixor
    //   2467: istore #49
    //   2469: aload #45
    //   2471: iconst_4
    //   2472: baload
    //   2473: bipush #24
    //   2475: ishl
    //   2476: aload #45
    //   2478: iconst_5
    //   2479: baload
    //   2480: sipush #255
    //   2483: iand
    //   2484: bipush #16
    //   2486: ishl
    //   2487: ior
    //   2488: aload #45
    //   2490: bipush #6
    //   2492: baload
    //   2493: sipush #255
    //   2496: iand
    //   2497: bipush #8
    //   2499: ishl
    //   2500: ior
    //   2501: aload #45
    //   2503: bipush #7
    //   2505: baload
    //   2506: sipush #255
    //   2509: iand
    //   2510: ior
    //   2511: aload #30
    //   2513: iconst_1
    //   2514: iaload
    //   2515: ixor
    //   2516: istore #50
    //   2518: aload #45
    //   2520: bipush #8
    //   2522: baload
    //   2523: bipush #24
    //   2525: ishl
    //   2526: aload #45
    //   2528: bipush #9
    //   2530: baload
    //   2531: sipush #255
    //   2534: iand
    //   2535: bipush #16
    //   2537: ishl
    //   2538: ior
    //   2539: aload #45
    //   2541: bipush #10
    //   2543: baload
    //   2544: sipush #255
    //   2547: iand
    //   2548: bipush #8
    //   2550: ishl
    //   2551: ior
    //   2552: aload #45
    //   2554: bipush #11
    //   2556: baload
    //   2557: sipush #255
    //   2560: iand
    //   2561: ior
    //   2562: aload #30
    //   2564: iconst_2
    //   2565: iaload
    //   2566: ixor
    //   2567: istore #51
    //   2569: aload #45
    //   2571: bipush #12
    //   2573: baload
    //   2574: bipush #24
    //   2576: ishl
    //   2577: aload #45
    //   2579: bipush #13
    //   2581: baload
    //   2582: sipush #255
    //   2585: iand
    //   2586: bipush #16
    //   2588: ishl
    //   2589: ior
    //   2590: aload #45
    //   2592: bipush #14
    //   2594: baload
    //   2595: sipush #255
    //   2598: iand
    //   2599: bipush #8
    //   2601: ishl
    //   2602: ior
    //   2603: aload #45
    //   2605: bipush #15
    //   2607: baload
    //   2608: sipush #255
    //   2611: iand
    //   2612: ior
    //   2613: aload #30
    //   2615: iconst_3
    //   2616: iaload
    //   2617: ixor
    //   2618: istore #52
    //   2620: iconst_1
    //   2621: istore #53
    //   2623: iload #53
    //   2625: iload #36
    //   2627: if_icmpge -> 2870
    //   2630: iinc #47, 4
    //   2633: aload #38
    //   2635: iload #49
    //   2637: bipush #24
    //   2639: iushr
    //   2640: iaload
    //   2641: aload #39
    //   2643: iload #52
    //   2645: bipush #16
    //   2647: iushr
    //   2648: sipush #255
    //   2651: iand
    //   2652: iaload
    //   2653: ixor
    //   2654: aload #40
    //   2656: iload #51
    //   2658: bipush #8
    //   2660: iushr
    //   2661: sipush #255
    //   2664: iand
    //   2665: iaload
    //   2666: ixor
    //   2667: aload #41
    //   2669: iload #50
    //   2671: sipush #255
    //   2674: iand
    //   2675: iaload
    //   2676: ixor
    //   2677: aload #30
    //   2679: iload #47
    //   2681: iaload
    //   2682: ixor
    //   2683: istore #54
    //   2685: aload #38
    //   2687: iload #50
    //   2689: bipush #24
    //   2691: iushr
    //   2692: iaload
    //   2693: aload #39
    //   2695: iload #49
    //   2697: bipush #16
    //   2699: iushr
    //   2700: sipush #255
    //   2703: iand
    //   2704: iaload
    //   2705: ixor
    //   2706: aload #40
    //   2708: iload #52
    //   2710: bipush #8
    //   2712: iushr
    //   2713: sipush #255
    //   2716: iand
    //   2717: iaload
    //   2718: ixor
    //   2719: aload #41
    //   2721: iload #51
    //   2723: sipush #255
    //   2726: iand
    //   2727: iaload
    //   2728: ixor
    //   2729: aload #30
    //   2731: iload #47
    //   2733: iconst_1
    //   2734: iadd
    //   2735: iaload
    //   2736: ixor
    //   2737: istore #55
    //   2739: aload #38
    //   2741: iload #51
    //   2743: bipush #24
    //   2745: iushr
    //   2746: iaload
    //   2747: aload #39
    //   2749: iload #50
    //   2751: bipush #16
    //   2753: iushr
    //   2754: sipush #255
    //   2757: iand
    //   2758: iaload
    //   2759: ixor
    //   2760: aload #40
    //   2762: iload #49
    //   2764: bipush #8
    //   2766: iushr
    //   2767: sipush #255
    //   2770: iand
    //   2771: iaload
    //   2772: ixor
    //   2773: aload #41
    //   2775: iload #52
    //   2777: sipush #255
    //   2780: iand
    //   2781: iaload
    //   2782: ixor
    //   2783: aload #30
    //   2785: iload #47
    //   2787: iconst_2
    //   2788: iadd
    //   2789: iaload
    //   2790: ixor
    //   2791: istore #56
    //   2793: aload #38
    //   2795: iload #52
    //   2797: bipush #24
    //   2799: iushr
    //   2800: iaload
    //   2801: aload #39
    //   2803: iload #51
    //   2805: bipush #16
    //   2807: iushr
    //   2808: sipush #255
    //   2811: iand
    //   2812: iaload
    //   2813: ixor
    //   2814: aload #40
    //   2816: iload #50
    //   2818: bipush #8
    //   2820: iushr
    //   2821: sipush #255
    //   2824: iand
    //   2825: iaload
    //   2826: ixor
    //   2827: aload #41
    //   2829: iload #49
    //   2831: sipush #255
    //   2834: iand
    //   2835: iaload
    //   2836: ixor
    //   2837: aload #30
    //   2839: iload #47
    //   2841: iconst_3
    //   2842: iadd
    //   2843: iaload
    //   2844: ixor
    //   2845: istore #57
    //   2847: iload #54
    //   2849: istore #49
    //   2851: iload #55
    //   2853: istore #50
    //   2855: iload #56
    //   2857: istore #51
    //   2859: iload #57
    //   2861: istore #52
    //   2863: iinc #53, 1
    //   2866: iload_2
    //   2867: ifne -> 2623
    //   2870: iinc #47, 4
    //   2873: aload #30
    //   2875: iload #47
    //   2877: iaload
    //   2878: istore #48
    //   2880: aload #46
    //   2882: iconst_0
    //   2883: aload #37
    //   2885: iload #49
    //   2887: bipush #24
    //   2889: iushr
    //   2890: baload
    //   2891: iload #48
    //   2893: bipush #24
    //   2895: iushr
    //   2896: ixor
    //   2897: i2b
    //   2898: bastore
    //   2899: aload #46
    //   2901: iconst_1
    //   2902: aload #37
    //   2904: iload #52
    //   2906: bipush #16
    //   2908: iushr
    //   2909: sipush #255
    //   2912: iand
    //   2913: baload
    //   2914: iload #48
    //   2916: bipush #16
    //   2918: iushr
    //   2919: ixor
    //   2920: i2b
    //   2921: bastore
    //   2922: aload #46
    //   2924: iconst_2
    //   2925: aload #37
    //   2927: iload #51
    //   2929: bipush #8
    //   2931: iushr
    //   2932: sipush #255
    //   2935: iand
    //   2936: baload
    //   2937: iload #48
    //   2939: bipush #8
    //   2941: iushr
    //   2942: ixor
    //   2943: i2b
    //   2944: bastore
    //   2945: aload #46
    //   2947: iconst_3
    //   2948: aload #37
    //   2950: iload #50
    //   2952: sipush #255
    //   2955: iand
    //   2956: baload
    //   2957: iload #48
    //   2959: ixor
    //   2960: i2b
    //   2961: bastore
    //   2962: aload #30
    //   2964: iload #47
    //   2966: iconst_1
    //   2967: iadd
    //   2968: iaload
    //   2969: istore #48
    //   2971: aload #46
    //   2973: iconst_4
    //   2974: aload #37
    //   2976: iload #50
    //   2978: bipush #24
    //   2980: iushr
    //   2981: baload
    //   2982: iload #48
    //   2984: bipush #24
    //   2986: iushr
    //   2987: ixor
    //   2988: i2b
    //   2989: bastore
    //   2990: aload #46
    //   2992: iconst_5
    //   2993: aload #37
    //   2995: iload #49
    //   2997: bipush #16
    //   2999: iushr
    //   3000: sipush #255
    //   3003: iand
    //   3004: baload
    //   3005: iload #48
    //   3007: bipush #16
    //   3009: iushr
    //   3010: ixor
    //   3011: i2b
    //   3012: bastore
    //   3013: aload #46
    //   3015: bipush #6
    //   3017: aload #37
    //   3019: iload #52
    //   3021: bipush #8
    //   3023: iushr
    //   3024: sipush #255
    //   3027: iand
    //   3028: baload
    //   3029: iload #48
    //   3031: bipush #8
    //   3033: iushr
    //   3034: ixor
    //   3035: i2b
    //   3036: bastore
    //   3037: aload #46
    //   3039: bipush #7
    //   3041: aload #37
    //   3043: iload #51
    //   3045: sipush #255
    //   3048: iand
    //   3049: baload
    //   3050: iload #48
    //   3052: ixor
    //   3053: i2b
    //   3054: bastore
    //   3055: aload #30
    //   3057: iload #47
    //   3059: iconst_2
    //   3060: iadd
    //   3061: iaload
    //   3062: istore #48
    //   3064: aload #46
    //   3066: bipush #8
    //   3068: aload #37
    //   3070: iload #51
    //   3072: bipush #24
    //   3074: iushr
    //   3075: baload
    //   3076: iload #48
    //   3078: bipush #24
    //   3080: iushr
    //   3081: ixor
    //   3082: i2b
    //   3083: bastore
    //   3084: aload #46
    //   3086: bipush #9
    //   3088: aload #37
    //   3090: iload #50
    //   3092: bipush #16
    //   3094: iushr
    //   3095: sipush #255
    //   3098: iand
    //   3099: baload
    //   3100: iload #48
    //   3102: bipush #16
    //   3104: iushr
    //   3105: ixor
    //   3106: i2b
    //   3107: bastore
    //   3108: aload #46
    //   3110: bipush #10
    //   3112: aload #37
    //   3114: iload #49
    //   3116: bipush #8
    //   3118: iushr
    //   3119: sipush #255
    //   3122: iand
    //   3123: baload
    //   3124: iload #48
    //   3126: bipush #8
    //   3128: iushr
    //   3129: ixor
    //   3130: i2b
    //   3131: bastore
    //   3132: aload #46
    //   3134: bipush #11
    //   3136: aload #37
    //   3138: iload #52
    //   3140: sipush #255
    //   3143: iand
    //   3144: baload
    //   3145: iload #48
    //   3147: ixor
    //   3148: i2b
    //   3149: bastore
    //   3150: aload #30
    //   3152: iload #47
    //   3154: iconst_3
    //   3155: iadd
    //   3156: iaload
    //   3157: istore #48
    //   3159: aload #46
    //   3161: bipush #12
    //   3163: aload #37
    //   3165: iload #52
    //   3167: bipush #24
    //   3169: iushr
    //   3170: baload
    //   3171: iload #48
    //   3173: bipush #24
    //   3175: iushr
    //   3176: ixor
    //   3177: i2b
    //   3178: bastore
    //   3179: aload #46
    //   3181: bipush #13
    //   3183: aload #37
    //   3185: iload #51
    //   3187: bipush #16
    //   3189: iushr
    //   3190: sipush #255
    //   3193: iand
    //   3194: baload
    //   3195: iload #48
    //   3197: bipush #16
    //   3199: iushr
    //   3200: ixor
    //   3201: i2b
    //   3202: bastore
    //   3203: aload #46
    //   3205: bipush #14
    //   3207: aload #37
    //   3209: iload #50
    //   3211: bipush #8
    //   3213: iushr
    //   3214: sipush #255
    //   3217: iand
    //   3218: baload
    //   3219: iload #48
    //   3221: bipush #8
    //   3223: iushr
    //   3224: ixor
    //   3225: i2b
    //   3226: bastore
    //   3227: aload #46
    //   3229: bipush #15
    //   3231: aload #37
    //   3233: iload #49
    //   3235: sipush #255
    //   3238: iand
    //   3239: baload
    //   3240: iload #48
    //   3242: ixor
    //   3243: i2b
    //   3244: bastore
    //   3245: iconst_0
    //   3246: istore #53
    //   3248: iload #53
    //   3250: bipush #16
    //   3252: if_icmpge -> 3278
    //   3255: aload #43
    //   3257: iload #53
    //   3259: iload #44
    //   3261: bipush #16
    //   3263: imul
    //   3264: iadd
    //   3265: aload #46
    //   3267: iload #53
    //   3269: baload
    //   3270: bastore
    //   3271: iinc #53, 1
    //   3274: iload_2
    //   3275: ifne -> 3248
    //   3278: iinc #44, 1
    //   3281: iload_2
    //   3282: ifne -> 2363
    //   3285: aload #43
    //   3287: arraylength
    //   3288: ifle -> 3369
    //   3291: aload #43
    //   3293: aload #43
    //   3295: arraylength
    //   3296: iconst_1
    //   3297: isub
    //   3298: baload
    //   3299: istore #44
    //   3301: iload #44
    //   3303: bipush #16
    //   3305: if_icmple -> 3316
    //   3308: aload #43
    //   3310: astore #35
    //   3312: iload_2
    //   3313: ifne -> 3369
    //   3316: aload #43
    //   3318: arraylength
    //   3319: iload #44
    //   3321: isub
    //   3322: newarray byte
    //   3324: astore #35
    //   3326: iconst_0
    //   3327: istore #45
    //   3329: iload #45
    //   3331: aload #35
    //   3333: arraylength
    //   3334: if_icmpge -> 3369
    //   3337: iload #45
    //   3339: aload #43
    //   3341: arraylength
    //   3342: if_icmpge -> 3369
    //   3345: aload #35
    //   3347: iload #45
    //   3349: aload #43
    //   3351: iload #45
    //   3353: baload
    //   3354: bastore
    //   3355: iinc #45, 1
    //   3358: iload_2
    //   3359: ifne -> 3329
    //   3362: goto -> 3369
    //   3365: invokestatic a : (Ljava/lang/Throwable;)Ljava/lang/Throwable;
    //   3368: athrow
    //   3369: aload #35
    //   3371: astore #7
    //   3373: new java/math/BigInteger
    //   3376: dup
    //   3377: aload #7
    //   3379: invokespecial <init> : ([B)V
    //   3382: invokevirtual abs : ()Ljava/math/BigInteger;
    //   3385: putstatic burp/Zxyu.Zp : Ljava/lang/Object;
    //   3388: new java/lang/StringBuilder
    //   3391: dup
    //   3392: invokespecial <init> : ()V
    //   3395: astore_3
    //   3396: iconst_0
    //   3397: istore #4
    //   3399: iload #4
    //   3401: bipush #32
    //   3403: if_icmpge -> 4739
    //   3406: iload #4
    //   3408: tableswitch default -> 4732, 0 -> 3552, 1 -> 3589, 2 -> 3626, 3 -> 3663, 4 -> 3700, 5 -> 3737, 6 -> 3774, 7 -> 3811, 8 -> 3848, 9 -> 3885, 10 -> 3922, 11 -> 3959, 12 -> 3996, 13 -> 4033, 14 -> 4070, 15 -> 4107, 16 -> 4144, 17 -> 4181, 18 -> 4218, 19 -> 4255, 20 -> 4292, 21 -> 4329, 22 -> 4366, 23 -> 4403, 24 -> 4440, 25 -> 4477, 26 -> 4514, 27 -> 4551, 28 -> 4588, 29 -> 4625, 30 -> 4662, 31 -> 4699
    //   3552: aload_3
    //   3553: getstatic burp/Zmpc.ZT : Ljava/lang/String;
    //   3556: getstatic burp/Zec0.Zg : Ljava/lang/Object;
    //   3559: checkcast java/math/BigInteger
    //   3562: invokevirtual intValue : ()I
    //   3565: bipush #32
    //   3567: irem
    //   3568: invokestatic abs : (I)I
    //   3571: invokevirtual charAt : (I)C
    //   3574: invokevirtual append : (C)Ljava/lang/StringBuilder;
    //   3577: pop
    //   3578: iload_2
    //   3579: ifne -> 4732
    //   3582: goto -> 3589
    //   3585: invokestatic a : (Ljava/lang/Throwable;)Ljava/lang/Throwable;
    //   3588: athrow
    //   3589: aload_3
    //   3590: getstatic burp/Zmsl.ZP : Ljava/lang/String;
    //   3593: getstatic burp/Zl6e.Zo : Ljava/lang/Object;
    //   3596: checkcast java/math/BigInteger
    //   3599: invokevirtual intValue : ()I
    //   3602: bipush #32
    //   3604: irem
    //   3605: invokestatic abs : (I)I
    //   3608: invokevirtual charAt : (I)C
    //   3611: invokevirtual append : (C)Ljava/lang/StringBuilder;
    //   3614: pop
    //   3615: iload_2
    //   3616: ifne -> 4732
    //   3619: goto -> 3626
    //   3622: invokestatic a : (Ljava/lang/Throwable;)Ljava/lang/Throwable;
    //   3625: athrow
    //   3626: aload_3
    //   3627: getstatic burp/Zs9x.ZY : Ljava/lang/String;
    //   3630: getstatic burp/Ze08.ZJ : Ljava/lang/Object;
    //   3633: checkcast java/math/BigInteger
    //   3636: invokevirtual intValue : ()I
    //   3639: bipush #32
    //   3641: irem
    //   3642: invokestatic abs : (I)I
    //   3645: invokevirtual charAt : (I)C
    //   3648: invokevirtual append : (C)Ljava/lang/StringBuilder;
    //   3651: pop
    //   3652: iload_2
    //   3653: ifne -> 4732
    //   3656: goto -> 3663
    //   3659: invokestatic a : (Ljava/lang/Throwable;)Ljava/lang/Throwable;
    //   3662: athrow
    //   3663: aload_3
    //   3664: getstatic burp/Ze3z.Zv : Ljava/lang/String;
    //   3667: getstatic burp/Zg7j.Zr : Ljava/lang/Object;
    //   3670: checkcast java/math/BigInteger
    //   3673: invokevirtual intValue : ()I
    //   3676: bipush #32
    //   3678: irem
    //   3679: invokestatic abs : (I)I
    //   3682: invokevirtual charAt : (I)C
    //   3685: invokevirtual append : (C)Ljava/lang/StringBuilder;
    //   3688: pop
    //   3689: iload_2
    //   3690: ifne -> 4732
    //   3693: goto -> 3700
    //   3696: invokestatic a : (Ljava/lang/Throwable;)Ljava/lang/Throwable;
    //   3699: athrow
    //   3700: aload_3
    //   3701: getstatic burp/Ze6k.ZM : Ljava/lang/String;
    //   3704: getstatic burp/Zd8.Zs : Ljava/lang/Object;
    //   3707: checkcast java/math/BigInteger
    //   3710: invokevirtual intValue : ()I
    //   3713: bipush #32
    //   3715: irem
    //   3716: invokestatic abs : (I)I
    //   3719: invokevirtual charAt : (I)C
    //   3722: invokevirtual append : (C)Ljava/lang/StringBuilder;
    //   3725: pop
    //   3726: iload_2
    //   3727: ifne -> 4732
    //   3730: goto -> 3737
    //   3733: invokestatic a : (Ljava/lang/Throwable;)Ljava/lang/Throwable;
    //   3736: athrow
    //   3737: aload_3
    //   3738: getstatic burp/Ze08.Zh : Ljava/lang/String;
    //   3741: getstatic burp/Zec_.ZN : Ljava/lang/Object;
    //   3744: checkcast java/math/BigInteger
    //   3747: invokevirtual intValue : ()I
    //   3750: bipush #32
    //   3752: irem
    //   3753: invokestatic abs : (I)I
    //   3756: invokevirtual charAt : (I)C
    //   3759: invokevirtual append : (C)Ljava/lang/StringBuilder;
    //   3762: pop
    //   3763: iload_2
    //   3764: ifne -> 4732
    //   3767: goto -> 3774
    //   3770: invokestatic a : (Ljava/lang/Throwable;)Ljava/lang/Throwable;
    //   3773: athrow
    //   3774: aload_3
    //   3775: getstatic burp/Ztfr.Zo : Ljava/lang/String;
    //   3778: getstatic burp/Zem6.Zm : Ljava/lang/Object;
    //   3781: checkcast java/math/BigInteger
    //   3784: invokevirtual intValue : ()I
    //   3787: bipush #32
    //   3789: irem
    //   3790: invokestatic abs : (I)I
    //   3793: invokevirtual charAt : (I)C
    //   3796: invokevirtual append : (C)Ljava/lang/StringBuilder;
    //   3799: pop
    //   3800: iload_2
    //   3801: ifne -> 4732
    //   3804: goto -> 3811
    //   3807: invokestatic a : (Ljava/lang/Throwable;)Ljava/lang/Throwable;
    //   3810: athrow
    //   3811: aload_3
    //   3812: getstatic burp/Zb9m.Zc : Ljava/lang/String;
    //   3815: getstatic burp/Zs15.Zk : Ljava/lang/Object;
    //   3818: checkcast java/math/BigInteger
    //   3821: invokevirtual intValue : ()I
    //   3824: bipush #32
    //   3826: irem
    //   3827: invokestatic abs : (I)I
    //   3830: invokevirtual charAt : (I)C
    //   3833: invokevirtual append : (C)Ljava/lang/StringBuilder;
    //   3836: pop
    //   3837: iload_2
    //   3838: ifne -> 4732
    //   3841: goto -> 3848
    //   3844: invokestatic a : (Ljava/lang/Throwable;)Ljava/lang/Throwable;
    //   3847: athrow
    //   3848: aload_3
    //   3849: getstatic burp/Zl1n.ZZ : Ljava/lang/String;
    //   3852: getstatic burp/Zrcx.Za : Ljava/lang/Object;
    //   3855: checkcast java/math/BigInteger
    //   3858: invokevirtual intValue : ()I
    //   3861: bipush #32
    //   3863: irem
    //   3864: invokestatic abs : (I)I
    //   3867: invokevirtual charAt : (I)C
    //   3870: invokevirtual append : (C)Ljava/lang/StringBuilder;
    //   3873: pop
    //   3874: iload_2
    //   3875: ifne -> 4732
    //   3878: goto -> 3885
    //   3881: invokestatic a : (Ljava/lang/Throwable;)Ljava/lang/Throwable;
    //   3884: athrow
    //   3885: aload_3
    //   3886: getstatic burp/Zsk4.ZH : Ljava/lang/String;
    //   3889: getstatic burp/Zm_w.ZW : Ljava/lang/Object;
    //   3892: checkcast java/math/BigInteger
    //   3895: invokevirtual intValue : ()I
    //   3898: bipush #32
    //   3900: irem
    //   3901: invokestatic abs : (I)I
    //   3904: invokevirtual charAt : (I)C
    //   3907: invokevirtual append : (C)Ljava/lang/StringBuilder;
    //   3910: pop
    //   3911: iload_2
    //   3912: ifne -> 4732
    //   3915: goto -> 3922
    //   3918: invokestatic a : (Ljava/lang/Throwable;)Ljava/lang/Throwable;
    //   3921: athrow
    //   3922: aload_3
    //   3923: getstatic burp/Zb6e.ZR : Ljava/lang/String;
    //   3926: getstatic burp/Zlh2.Zc : Ljava/lang/Object;
    //   3929: checkcast java/math/BigInteger
    //   3932: invokevirtual intValue : ()I
    //   3935: bipush #32
    //   3937: irem
    //   3938: invokestatic abs : (I)I
    //   3941: invokevirtual charAt : (I)C
    //   3944: invokevirtual append : (C)Ljava/lang/StringBuilder;
    //   3947: pop
    //   3948: iload_2
    //   3949: ifne -> 4732
    //   3952: goto -> 3959
    //   3955: invokestatic a : (Ljava/lang/Throwable;)Ljava/lang/Throwable;
    //   3958: athrow
    //   3959: aload_3
    //   3960: getstatic burp/Ze7y.Zm : Ljava/lang/String;
    //   3963: getstatic burp/Ze6k.Zs : Ljava/lang/Object;
    //   3966: checkcast java/math/BigInteger
    //   3969: invokevirtual intValue : ()I
    //   3972: bipush #32
    //   3974: irem
    //   3975: invokestatic abs : (I)I
    //   3978: invokevirtual charAt : (I)C
    //   3981: invokevirtual append : (C)Ljava/lang/StringBuilder;
    //   3984: pop
    //   3985: iload_2
    //   3986: ifne -> 4732
    //   3989: goto -> 3996
    //   3992: invokestatic a : (Ljava/lang/Throwable;)Ljava/lang/Throwable;
    //   3995: athrow
    //   3996: aload_3
    //   3997: getstatic burp/Zd0.Zi : Ljava/lang/String;
    //   4000: getstatic burp/Zec_.ZN : Ljava/lang/Object;
    //   4003: checkcast java/math/BigInteger
    //   4006: invokevirtual intValue : ()I
    //   4009: bipush #32
    //   4011: irem
    //   4012: invokestatic abs : (I)I
    //   4015: invokevirtual charAt : (I)C
    //   4018: invokevirtual append : (C)Ljava/lang/StringBuilder;
    //   4021: pop
    //   4022: iload_2
    //   4023: ifne -> 4732
    //   4026: goto -> 4033
    //   4029: invokestatic a : (Ljava/lang/Throwable;)Ljava/lang/Throwable;
    //   4032: athrow
    //   4033: aload_3
    //   4034: getstatic burp/Zex5.Zh : Ljava/lang/String;
    //   4037: getstatic burp/Zbu.ZW : Ljava/lang/Object;
    //   4040: checkcast java/math/BigInteger
    //   4043: invokevirtual intValue : ()I
    //   4046: bipush #32
    //   4048: irem
    //   4049: invokestatic abs : (I)I
    //   4052: invokevirtual charAt : (I)C
    //   4055: invokevirtual append : (C)Ljava/lang/StringBuilder;
    //   4058: pop
    //   4059: iload_2
    //   4060: ifne -> 4732
    //   4063: goto -> 4070
    //   4066: invokestatic a : (Ljava/lang/Throwable;)Ljava/lang/Throwable;
    //   4069: athrow
    //   4070: aload_3
    //   4071: getstatic burp/Zxyu.ZM : Ljava/lang/String;
    //   4074: getstatic burp/Zxxd.Zn : Ljava/lang/Object;
    //   4077: checkcast java/math/BigInteger
    //   4080: invokevirtual intValue : ()I
    //   4083: bipush #32
    //   4085: irem
    //   4086: invokestatic abs : (I)I
    //   4089: invokevirtual charAt : (I)C
    //   4092: invokevirtual append : (C)Ljava/lang/StringBuilder;
    //   4095: pop
    //   4096: iload_2
    //   4097: ifne -> 4732
    //   4100: goto -> 4107
    //   4103: invokestatic a : (Ljava/lang/Throwable;)Ljava/lang/Throwable;
    //   4106: athrow
    //   4107: aload_3
    //   4108: getstatic burp/Zb9m.Zc : Ljava/lang/String;
    //   4111: getstatic burp/Zm1l.Za : Ljava/lang/Object;
    //   4114: checkcast java/math/BigInteger
    //   4117: invokevirtual intValue : ()I
    //   4120: bipush #32
    //   4122: irem
    //   4123: invokestatic abs : (I)I
    //   4126: invokevirtual charAt : (I)C
    //   4129: invokevirtual append : (C)Ljava/lang/StringBuilder;
    //   4132: pop
    //   4133: iload_2
    //   4134: ifne -> 4732
    //   4137: goto -> 4144
    //   4140: invokestatic a : (Ljava/lang/Throwable;)Ljava/lang/Throwable;
    //   4143: athrow
    //   4144: aload_3
    //   4145: getstatic burp/Zkff.Zs : Ljava/lang/String;
    //   4148: getstatic burp/Zsk4.Ze : Ljava/lang/Object;
    //   4151: checkcast java/math/BigInteger
    //   4154: invokevirtual intValue : ()I
    //   4157: bipush #32
    //   4159: irem
    //   4160: invokestatic abs : (I)I
    //   4163: invokevirtual charAt : (I)C
    //   4166: invokevirtual append : (C)Ljava/lang/StringBuilder;
    //   4169: pop
    //   4170: iload_2
    //   4171: ifne -> 4732
    //   4174: goto -> 4181
    //   4177: invokestatic a : (Ljava/lang/Throwable;)Ljava/lang/Throwable;
    //   4180: athrow
    //   4181: aload_3
    //   4182: getstatic burp/Zl4v.ZD : Ljava/lang/String;
    //   4185: getstatic burp/Zmir.ZF : Ljava/lang/Object;
    //   4188: checkcast java/math/BigInteger
    //   4191: invokevirtual intValue : ()I
    //   4194: bipush #32
    //   4196: irem
    //   4197: invokestatic abs : (I)I
    //   4200: invokevirtual charAt : (I)C
    //   4203: invokevirtual append : (C)Ljava/lang/StringBuilder;
    //   4206: pop
    //   4207: iload_2
    //   4208: ifne -> 4732
    //   4211: goto -> 4218
    //   4214: invokestatic a : (Ljava/lang/Throwable;)Ljava/lang/Throwable;
    //   4217: athrow
    //   4218: aload_3
    //   4219: getstatic burp/Zlpu.ZA : Ljava/lang/String;
    //   4222: getstatic burp/Zem6.Zm : Ljava/lang/Object;
    //   4225: checkcast java/math/BigInteger
    //   4228: invokevirtual intValue : ()I
    //   4231: bipush #32
    //   4233: irem
    //   4234: invokestatic abs : (I)I
    //   4237: invokevirtual charAt : (I)C
    //   4240: invokevirtual append : (C)Ljava/lang/StringBuilder;
    //   4243: pop
    //   4244: iload_2
    //   4245: ifne -> 4732
    //   4248: goto -> 4255
    //   4251: invokestatic a : (Ljava/lang/Throwable;)Ljava/lang/Throwable;
    //   4254: athrow
    //   4255: aload_3
    //   4256: getstatic burp/Zgco.Zh : Ljava/lang/String;
    //   4259: getstatic burp/Zegk.ZR : Ljava/lang/Object;
    //   4262: checkcast java/math/BigInteger
    //   4265: invokevirtual intValue : ()I
    //   4268: bipush #32
    //   4270: irem
    //   4271: invokestatic abs : (I)I
    //   4274: invokevirtual charAt : (I)C
    //   4277: invokevirtual append : (C)Ljava/lang/StringBuilder;
    //   4280: pop
    //   4281: iload_2
    //   4282: ifne -> 4732
    //   4285: goto -> 4292
    //   4288: invokestatic a : (Ljava/lang/Throwable;)Ljava/lang/Throwable;
    //   4291: athrow
    //   4292: aload_3
    //   4293: getstatic burp/Zkde.Zb : Ljava/lang/String;
    //   4296: getstatic burp/Ztvp.Zy : Ljava/lang/Object;
    //   4299: checkcast java/math/BigInteger
    //   4302: invokevirtual intValue : ()I
    //   4305: bipush #32
    //   4307: irem
    //   4308: invokestatic abs : (I)I
    //   4311: invokevirtual charAt : (I)C
    //   4314: invokevirtual append : (C)Ljava/lang/StringBuilder;
    //   4317: pop
    //   4318: iload_2
    //   4319: ifne -> 4732
    //   4322: goto -> 4329
    //   4325: invokestatic a : (Ljava/lang/Throwable;)Ljava/lang/Throwable;
    //   4328: athrow
    //   4329: aload_3
    //   4330: getstatic burp/Zb9m.Zc : Ljava/lang/String;
    //   4333: getstatic burp/Zxof.Zi : Ljava/lang/Object;
    //   4336: checkcast java/math/BigInteger
    //   4339: invokevirtual intValue : ()I
    //   4342: bipush #32
    //   4344: irem
    //   4345: invokestatic abs : (I)I
    //   4348: invokevirtual charAt : (I)C
    //   4351: invokevirtual append : (C)Ljava/lang/StringBuilder;
    //   4354: pop
    //   4355: iload_2
    //   4356: ifne -> 4732
    //   4359: goto -> 4366
    //   4362: invokestatic a : (Ljava/lang/Throwable;)Ljava/lang/Throwable;
    //   4365: athrow
    //   4366: aload_3
    //   4367: getstatic burp/Zkff.Zs : Ljava/lang/String;
    //   4370: getstatic burp/Zlbr.Zp : Ljava/lang/Object;
    //   4373: checkcast java/math/BigInteger
    //   4376: invokevirtual intValue : ()I
    //   4379: bipush #32
    //   4381: irem
    //   4382: invokestatic abs : (I)I
    //   4385: invokevirtual charAt : (I)C
    //   4388: invokevirtual append : (C)Ljava/lang/StringBuilder;
    //   4391: pop
    //   4392: iload_2
    //   4393: ifne -> 4732
    //   4396: goto -> 4403
    //   4399: invokestatic a : (Ljava/lang/Throwable;)Ljava/lang/Throwable;
    //   4402: athrow
    //   4403: aload_3
    //   4404: getstatic burp/Zl6e.ZC : Ljava/lang/String;
    //   4407: getstatic burp/Zrcu.Zs : Ljava/lang/Object;
    //   4410: checkcast java/math/BigInteger
    //   4413: invokevirtual intValue : ()I
    //   4416: bipush #32
    //   4418: irem
    //   4419: invokestatic abs : (I)I
    //   4422: invokevirtual charAt : (I)C
    //   4425: invokevirtual append : (C)Ljava/lang/StringBuilder;
    //   4428: pop
    //   4429: iload_2
    //   4430: ifne -> 4732
    //   4433: goto -> 4440
    //   4436: invokestatic a : (Ljava/lang/Throwable;)Ljava/lang/Throwable;
    //   4439: athrow
    //   4440: aload_3
    //   4441: getstatic burp/Zry9.ZW : Ljava/lang/String;
    //   4444: getstatic burp/Zlh2.Zc : Ljava/lang/Object;
    //   4447: checkcast java/math/BigInteger
    //   4450: invokevirtual intValue : ()I
    //   4453: bipush #32
    //   4455: irem
    //   4456: invokestatic abs : (I)I
    //   4459: invokevirtual charAt : (I)C
    //   4462: invokevirtual append : (C)Ljava/lang/StringBuilder;
    //   4465: pop
    //   4466: iload_2
    //   4467: ifne -> 4732
    //   4470: goto -> 4477
    //   4473: invokestatic a : (Ljava/lang/Throwable;)Ljava/lang/Throwable;
    //   4476: athrow
    //   4477: aload_3
    //   4478: getstatic burp/Zm1l.Zp : Ljava/lang/String;
    //   4481: getstatic burp/Ztzw.Zk : Ljava/lang/Object;
    //   4484: checkcast java/math/BigInteger
    //   4487: invokevirtual intValue : ()I
    //   4490: bipush #32
    //   4492: irem
    //   4493: invokestatic abs : (I)I
    //   4496: invokevirtual charAt : (I)C
    //   4499: invokevirtual append : (C)Ljava/lang/StringBuilder;
    //   4502: pop
    //   4503: iload_2
    //   4504: ifne -> 4732
    //   4507: goto -> 4514
    //   4510: invokestatic a : (Ljava/lang/Throwable;)Ljava/lang/Throwable;
    //   4513: athrow
    //   4514: aload_3
    //   4515: getstatic burp/Zsuw.ZK : Ljava/lang/String;
    //   4518: getstatic burp/Zm1l.Za : Ljava/lang/Object;
    //   4521: checkcast java/math/BigInteger
    //   4524: invokevirtual intValue : ()I
    //   4527: bipush #32
    //   4529: irem
    //   4530: invokestatic abs : (I)I
    //   4533: invokevirtual charAt : (I)C
    //   4536: invokevirtual append : (C)Ljava/lang/StringBuilder;
    //   4539: pop
    //   4540: iload_2
    //   4541: ifne -> 4732
    //   4544: goto -> 4551
    //   4547: invokestatic a : (Ljava/lang/Throwable;)Ljava/lang/Throwable;
    //   4550: athrow
    //   4551: aload_3
    //   4552: getstatic burp/Zsyu.ZJ : Ljava/lang/String;
    //   4555: getstatic burp/Zlpu.ZE : Ljava/lang/Object;
    //   4558: checkcast java/math/BigInteger
    //   4561: invokevirtual intValue : ()I
    //   4564: bipush #32
    //   4566: irem
    //   4567: invokestatic abs : (I)I
    //   4570: invokevirtual charAt : (I)C
    //   4573: invokevirtual append : (C)Ljava/lang/StringBuilder;
    //   4576: pop
    //   4577: iload_2
    //   4578: ifne -> 4732
    //   4581: goto -> 4588
    //   4584: invokestatic a : (Ljava/lang/Throwable;)Ljava/lang/Throwable;
    //   4587: athrow
    //   4588: aload_3
    //   4589: getstatic burp/Ztfr.Zo : Ljava/lang/String;
    //   4592: getstatic burp/Zsmn.Zq : Ljava/lang/Object;
    //   4595: checkcast java/math/BigInteger
    //   4598: invokevirtual intValue : ()I
    //   4601: bipush #32
    //   4603: irem
    //   4604: invokestatic abs : (I)I
    //   4607: invokevirtual charAt : (I)C
    //   4610: invokevirtual append : (C)Ljava/lang/StringBuilder;
    //   4613: pop
    //   4614: iload_2
    //   4615: ifne -> 4732
    //   4618: goto -> 4625
    //   4621: invokestatic a : (Ljava/lang/Throwable;)Ljava/lang/Throwable;
    //   4624: athrow
    //   4625: aload_3
    //   4626: getstatic burp/Zg27.ZP : Ljava/lang/String;
    //   4629: getstatic burp/Zeoi.ZE : Ljava/lang/Object;
    //   4632: checkcast java/math/BigInteger
    //   4635: invokevirtual intValue : ()I
    //   4638: bipush #32
    //   4640: irem
    //   4641: invokestatic abs : (I)I
    //   4644: invokevirtual charAt : (I)C
    //   4647: invokevirtual append : (C)Ljava/lang/StringBuilder;
    //   4650: pop
    //   4651: iload_2
    //   4652: ifne -> 4732
    //   4655: goto -> 4662
    //   4658: invokestatic a : (Ljava/lang/Throwable;)Ljava/lang/Throwable;
    //   4661: athrow
    //   4662: aload_3
    //   4663: getstatic burp/Zl1n.ZZ : Ljava/lang/String;
    //   4666: getstatic burp/Zkde.Zk : Ljava/lang/Object;
    //   4669: checkcast java/math/BigInteger
    //   4672: invokevirtual intValue : ()I
    //   4675: bipush #32
    //   4677: irem
    //   4678: invokestatic abs : (I)I
    //   4681: invokevirtual charAt : (I)C
    //   4684: invokevirtual append : (C)Ljava/lang/StringBuilder;
    //   4687: pop
    //   4688: iload_2
    //   4689: ifne -> 4732
    //   4692: goto -> 4699
    //   4695: invokestatic a : (Ljava/lang/Throwable;)Ljava/lang/Throwable;
    //   4698: athrow
    //   4699: aload_3
    //   4700: getstatic burp/Zelz.ZK : Ljava/lang/String;
    //   4703: getstatic burp/Zboa.Zh : Ljava/lang/Object;
    //   4706: checkcast java/math/BigInteger
    //   4709: invokevirtual intValue : ()I
    //   4712: bipush #32
    //   4714: irem
    //   4715: invokestatic abs : (I)I
    //   4718: invokevirtual charAt : (I)C
    //   4721: invokevirtual append : (C)Ljava/lang/StringBuilder;
    //   4724: pop
    //   4725: goto -> 4732
    //   4728: invokestatic a : (Ljava/lang/Throwable;)Ljava/lang/Throwable;
    //   4731: athrow
    //   4732: iinc #4, 1
    //   4735: iload_2
    //   4736: ifne -> 3399
    //   4739: aload_3
    //   4740: invokevirtual toString : ()Ljava/lang/String;
    //   4743: putstatic burp/Ze08.Zh : Ljava/lang/String;
    //   4746: sipush #18641
    //   4749: sipush #3876
    //   4752: invokestatic a : (II)Ljava/lang/String;
    //   4755: iconst_1
    //   4756: ldc burp/Zrly
    //   4758: invokevirtual getClassLoader : ()Ljava/lang/ClassLoader;
    //   4761: invokestatic forName : (Ljava/lang/String;ZLjava/lang/ClassLoader;)Ljava/lang/Class;
    //   4764: invokevirtual getDeclaredFields : ()[Ljava/lang/reflect/Field;
    //   4767: astore #4
    //   4769: aload #4
    //   4771: arraylength
    //   4772: istore #5
    //   4774: iconst_0
    //   4775: istore #6
    //   4777: iload #6
    //   4779: iload #5
    //   4781: if_icmpge -> 4919
    //   4784: aload #4
    //   4786: iload #6
    //   4788: aaload
    //   4789: astore #7
    //   4791: aload #7
    //   4793: invokevirtual getModifiers : ()I
    //   4796: invokestatic isStatic : (I)Z
    //   4799: ifne -> 4809
    //   4802: goto -> 4912
    //   4805: invokestatic a : (Ljava/lang/Throwable;)Ljava/lang/Throwable;
    //   4808: athrow
    //   4809: aload #7
    //   4811: invokevirtual getType : ()Ljava/lang/Class;
    //   4814: astore #8
    //   4816: aload #8
    //   4818: ifnull -> 4899
    //   4821: aload #8
    //   4823: invokevirtual isPrimitive : ()Z
    //   4826: ifne -> 4899
    //   4829: goto -> 4836
    //   4832: invokestatic a : (Ljava/lang/Throwable;)Ljava/lang/Throwable;
    //   4835: athrow
    //   4836: aload #8
    //   4838: invokevirtual getPackage : ()Ljava/lang/Package;
    //   4841: ifnull -> 4899
    //   4844: goto -> 4851
    //   4847: invokestatic a : (Ljava/lang/Throwable;)Ljava/lang/Throwable;
    //   4850: athrow
    //   4851: aload #8
    //   4853: invokevirtual getPackage : ()Ljava/lang/Package;
    //   4856: invokevirtual getName : ()Ljava/lang/String;
    //   4859: ifnull -> 4899
    //   4862: goto -> 4869
    //   4865: invokestatic a : (Ljava/lang/Throwable;)Ljava/lang/Throwable;
    //   4868: athrow
    //   4869: aload #8
    //   4871: invokevirtual getPackage : ()Ljava/lang/Package;
    //   4874: invokevirtual getName : ()Ljava/lang/String;
    //   4877: sipush #18626
    //   4880: sipush #-2385
    //   4883: invokestatic a : (II)Ljava/lang/String;
    //   4886: invokevirtual startsWith : (Ljava/lang/String;)Z
    //   4889: ifne -> 4899
    //   4892: goto -> 4899
    //   4895: invokestatic a : (Ljava/lang/Throwable;)Ljava/lang/Throwable;
    //   4898: athrow
    //   4899: aload #7
    //   4901: iconst_1
    //   4902: invokevirtual setAccessible : (Z)V
    //   4905: aload #7
    //   4907: aconst_null
    //   4908: invokevirtual get : (Ljava/lang/Object;)Ljava/lang/Object;
    //   4911: pop
    //   4912: iinc #6, 1
    //   4915: iload_2
    //   4916: ifne -> 4777
    //   4919: sipush #18649
    //   4922: sipush #-2915
    //   4925: invokestatic a : (II)Ljava/lang/String;
    //   4928: invokestatic forName : (Ljava/lang/String;)Ljava/lang/Class;
    //   4931: invokevirtual getDeclaredMethods : ()[Ljava/lang/reflect/Method;
    //   4934: astore #4
    //   4936: aload #4
    //   4938: arraylength
    //   4939: istore #5
    //   4941: iconst_0
    //   4942: istore #6
    //   4944: iload #6
    //   4946: iload #5
    //   4948: if_icmpge -> 5081
    //   4951: aload #4
    //   4953: iload #6
    //   4955: aaload
    //   4956: astore #7
    //   4958: aload #7
    //   4960: invokevirtual getParameterTypes : ()[Ljava/lang/Class;
    //   4963: pop
    //   4964: aload #7
    //   4966: invokevirtual getModifiers : ()I
    //   4969: invokestatic isStatic : (I)Z
    //   4972: ifeq -> 5067
    //   4975: aload #7
    //   4977: invokevirtual getParameterTypes : ()[Ljava/lang/Class;
    //   4980: arraylength
    //   4981: iconst_2
    //   4982: if_icmpne -> 5067
    //   4985: goto -> 4992
    //   4988: invokestatic a : (Ljava/lang/Throwable;)Ljava/lang/Throwable;
    //   4991: athrow
    //   4992: aload #7
    //   4994: invokevirtual getReturnType : ()Ljava/lang/Class;
    //   4997: getstatic java/lang/Void.TYPE : Ljava/lang/Class;
    //   5000: invokevirtual equals : (Ljava/lang/Object;)Z
    //   5003: ifeq -> 5067
    //   5006: goto -> 5013
    //   5009: invokestatic a : (Ljava/lang/Throwable;)Ljava/lang/Throwable;
    //   5012: athrow
    //   5013: aload #7
    //   5015: iconst_1
    //   5016: invokevirtual setAccessible : (Z)V
    //   5019: aload #7
    //   5021: aconst_null
    //   5022: iconst_2
    //   5023: anewarray java/lang/Object
    //   5026: dup
    //   5027: iconst_0
    //   5028: aload_0
    //   5029: aastore
    //   5030: dup
    //   5031: iconst_1
    //   5032: aload_1
    //   5033: ifnonnull -> 5051
    //   5036: goto -> 5043
    //   5039: invokestatic a : (Ljava/lang/Throwable;)Ljava/lang/Throwable;
    //   5042: athrow
    //   5043: aload_1
    //   5044: goto -> 5058
    //   5047: invokestatic a : (Ljava/lang/Throwable;)Ljava/lang/Throwable;
    //   5050: athrow
    //   5051: aload_1
    //   5052: checkcast [B
    //   5055: invokevirtual clone : ()Ljava/lang/Object;
    //   5058: aastore
    //   5059: invokevirtual invoke : (Ljava/lang/Object;[Ljava/lang/Object;)Ljava/lang/Object;
    //   5062: pop
    //   5063: iload_2
    //   5064: ifne -> 5081
    //   5067: iinc #6, 1
    //   5070: iload_2
    //   5071: ifne -> 4944
    //   5074: goto -> 5081
    //   5077: invokestatic a : (Ljava/lang/Throwable;)Ljava/lang/Throwable;
    //   5080: athrow
    //   5081: iconst_0
    //   5082: istore #4
    //   5084: getstatic burp/Zrcu.Zb : Ljava/lang/String;
    //   5087: getstatic burp/Zxyu.Zp : Ljava/lang/Object;
    //   5090: checkcast java/math/BigInteger
    //   5093: invokevirtual intValue : ()I
    //   5096: bipush #32
    //   5098: irem
    //   5099: invokestatic abs : (I)I
    //   5102: invokevirtual charAt : (I)C
    //   5105: getstatic burp/Ze7y.Zm : Ljava/lang/String;
    //   5108: getstatic burp/Zxof.Zi : Ljava/lang/Object;
    //   5111: checkcast java/math/BigInteger
    //   5114: invokevirtual intValue : ()I
    //   5117: bipush #32
    //   5119: irem
    //   5120: invokestatic abs : (I)I
    //   5123: invokevirtual charAt : (I)C
    //   5126: if_icmple -> 5471
    //   5129: sipush #18634
    //   5132: sipush #-17838
    //   5135: invokestatic a : (II)Ljava/lang/String;
    //   5138: iconst_1
    //   5139: ldc burp/Zs8q
    //   5141: invokevirtual getClassLoader : ()Ljava/lang/ClassLoader;
    //   5144: invokestatic forName : (Ljava/lang/String;ZLjava/lang/ClassLoader;)Ljava/lang/Class;
    //   5147: invokevirtual getDeclaredFields : ()[Ljava/lang/reflect/Field;
    //   5150: astore #5
    //   5152: aload #5
    //   5154: arraylength
    //   5155: istore #6
    //   5157: iconst_0
    //   5158: istore #7
    //   5160: iload #7
    //   5162: iload #6
    //   5164: if_icmpge -> 5302
    //   5167: aload #5
    //   5169: iload #7
    //   5171: aaload
    //   5172: astore #8
    //   5174: aload #8
    //   5176: invokevirtual getModifiers : ()I
    //   5179: invokestatic isStatic : (I)Z
    //   5182: ifne -> 5192
    //   5185: goto -> 5295
    //   5188: invokestatic a : (Ljava/lang/Throwable;)Ljava/lang/Throwable;
    //   5191: athrow
    //   5192: aload #8
    //   5194: invokevirtual getType : ()Ljava/lang/Class;
    //   5197: astore #9
    //   5199: aload #9
    //   5201: ifnull -> 5282
    //   5204: aload #9
    //   5206: invokevirtual isPrimitive : ()Z
    //   5209: ifne -> 5282
    //   5212: goto -> 5219
    //   5215: invokestatic a : (Ljava/lang/Throwable;)Ljava/lang/Throwable;
    //   5218: athrow
    //   5219: aload #9
    //   5221: invokevirtual getPackage : ()Ljava/lang/Package;
    //   5224: ifnull -> 5282
    //   5227: goto -> 5234
    //   5230: invokestatic a : (Ljava/lang/Throwable;)Ljava/lang/Throwable;
    //   5233: athrow
    //   5234: aload #9
    //   5236: invokevirtual getPackage : ()Ljava/lang/Package;
    //   5239: invokevirtual getName : ()Ljava/lang/String;
    //   5242: ifnull -> 5282
    //   5245: goto -> 5252
    //   5248: invokestatic a : (Ljava/lang/Throwable;)Ljava/lang/Throwable;
    //   5251: athrow
    //   5252: aload #9
    //   5254: invokevirtual getPackage : ()Ljava/lang/Package;
    //   5257: invokevirtual getName : ()Ljava/lang/String;
    //   5260: sipush #18638
    //   5263: sipush #-1648
    //   5266: invokestatic a : (II)Ljava/lang/String;
    //   5269: invokevirtual startsWith : (Ljava/lang/String;)Z
    //   5272: ifne -> 5282
    //   5275: goto -> 5282
    //   5278: invokestatic a : (Ljava/lang/Throwable;)Ljava/lang/Throwable;
    //   5281: athrow
    //   5282: aload #8
    //   5284: iconst_1
    //   5285: invokevirtual setAccessible : (Z)V
    //   5288: aload #8
    //   5290: aconst_null
    //   5291: invokevirtual get : (Ljava/lang/Object;)Ljava/lang/Object;
    //   5294: pop
    //   5295: iinc #7, 1
    //   5298: iload_2
    //   5299: ifne -> 5160
    //   5302: sipush #18640
    //   5305: sipush #-1488
    //   5308: invokestatic a : (II)Ljava/lang/String;
    //   5311: invokestatic forName : (Ljava/lang/String;)Ljava/lang/Class;
    //   5314: invokevirtual getDeclaredMethods : ()[Ljava/lang/reflect/Method;
    //   5317: astore #5
    //   5319: aload #5
    //   5321: arraylength
    //   5322: istore #6
    //   5324: iconst_0
    //   5325: istore #7
    //   5327: iload #7
    //   5329: iload #6
    //   5331: if_icmpge -> 5468
    //   5334: aload #5
    //   5336: iload #7
    //   5338: aaload
    //   5339: astore #8
    //   5341: aload #8
    //   5343: invokevirtual getParameterTypes : ()[Ljava/lang/Class;
    //   5346: pop
    //   5347: aload #8
    //   5349: invokevirtual getModifiers : ()I
    //   5352: invokestatic isStatic : (I)Z
    //   5355: ifeq -> 5454
    //   5358: aload #8
    //   5360: invokevirtual getParameterTypes : ()[Ljava/lang/Class;
    //   5363: arraylength
    //   5364: iconst_2
    //   5365: if_icmpne -> 5454
    //   5368: goto -> 5375
    //   5371: invokestatic a : (Ljava/lang/Throwable;)Ljava/lang/Throwable;
    //   5374: athrow
    //   5375: aload #8
    //   5377: invokevirtual getReturnType : ()Ljava/lang/Class;
    //   5380: getstatic java/lang/Boolean.TYPE : Ljava/lang/Class;
    //   5383: if_acmpne -> 5454
    //   5386: goto -> 5393
    //   5389: invokestatic a : (Ljava/lang/Throwable;)Ljava/lang/Throwable;
    //   5392: athrow
    //   5393: aload #8
    //   5395: iconst_1
    //   5396: invokevirtual setAccessible : (Z)V
    //   5399: aload #8
    //   5401: aconst_null
    //   5402: iconst_2
    //   5403: anewarray java/lang/Object
    //   5406: dup
    //   5407: iconst_0
    //   5408: aload_0
    //   5409: aastore
    //   5410: dup
    //   5411: iconst_1
    //   5412: aload_1
    //   5413: ifnonnull -> 5431
    //   5416: goto -> 5423
    //   5419: invokestatic a : (Ljava/lang/Throwable;)Ljava/lang/Throwable;
    //   5422: athrow
    //   5423: aload_1
    //   5424: goto -> 5438
    //   5427: invokestatic a : (Ljava/lang/Throwable;)Ljava/lang/Throwable;
    //   5430: athrow
    //   5431: aload_1
    //   5432: checkcast [B
    //   5435: invokevirtual clone : ()Ljava/lang/Object;
    //   5438: aastore
    //   5439: invokevirtual invoke : (Ljava/lang/Object;[Ljava/lang/Object;)Ljava/lang/Object;
    //   5442: checkcast java/lang/Boolean
    //   5445: invokevirtual booleanValue : ()Z
    //   5448: istore #4
    //   5450: iload_2
    //   5451: ifne -> 5468
    //   5454: iinc #7, 1
    //   5457: iload_2
    //   5458: ifne -> 5327
    //   5461: goto -> 5468
    //   5464: invokestatic a : (Ljava/lang/Throwable;)Ljava/lang/Throwable;
    //   5467: athrow
    //   5468: goto -> 5810
    //   5471: sipush #18636
    //   5474: sipush #-24278
    //   5477: invokestatic a : (II)Ljava/lang/String;
    //   5480: iconst_1
    //   5481: ldc burp/Zm52
    //   5483: invokevirtual getClassLoader : ()Ljava/lang/ClassLoader;
    //   5486: invokestatic forName : (Ljava/lang/String;ZLjava/lang/ClassLoader;)Ljava/lang/Class;
    //   5489: invokevirtual getDeclaredFields : ()[Ljava/lang/reflect/Field;
    //   5492: astore #5
    //   5494: aload #5
    //   5496: arraylength
    //   5497: istore #6
    //   5499: iconst_0
    //   5500: istore #7
    //   5502: iload #7
    //   5504: iload #6
    //   5506: if_icmpge -> 5644
    //   5509: aload #5
    //   5511: iload #7
    //   5513: aaload
    //   5514: astore #8
    //   5516: aload #8
    //   5518: invokevirtual getModifiers : ()I
    //   5521: invokestatic isStatic : (I)Z
    //   5524: ifne -> 5534
    //   5527: goto -> 5637
    //   5530: invokestatic a : (Ljava/lang/Throwable;)Ljava/lang/Throwable;
    //   5533: athrow
    //   5534: aload #8
    //   5536: invokevirtual getType : ()Ljava/lang/Class;
    //   5539: astore #9
    //   5541: aload #9
    //   5543: ifnull -> 5624
    //   5546: aload #9
    //   5548: invokevirtual isPrimitive : ()Z
    //   5551: ifne -> 5624
    //   5554: goto -> 5561
    //   5557: invokestatic a : (Ljava/lang/Throwable;)Ljava/lang/Throwable;
    //   5560: athrow
    //   5561: aload #9
    //   5563: invokevirtual getPackage : ()Ljava/lang/Package;
    //   5566: ifnull -> 5624
    //   5569: goto -> 5576
    //   5572: invokestatic a : (Ljava/lang/Throwable;)Ljava/lang/Throwable;
    //   5575: athrow
    //   5576: aload #9
    //   5578: invokevirtual getPackage : ()Ljava/lang/Package;
    //   5581: invokevirtual getName : ()Ljava/lang/String;
    //   5584: ifnull -> 5624
    //   5587: goto -> 5594
    //   5590: invokestatic a : (Ljava/lang/Throwable;)Ljava/lang/Throwable;
    //   5593: athrow
    //   5594: aload #9
    //   5596: invokevirtual getPackage : ()Ljava/lang/Package;
    //   5599: invokevirtual getName : ()Ljava/lang/String;
    //   5602: sipush #18638
    //   5605: sipush #-1648
    //   5608: invokestatic a : (II)Ljava/lang/String;
    //   5611: invokevirtual startsWith : (Ljava/lang/String;)Z
    //   5614: ifne -> 5624
    //   5617: goto -> 5624
    //   5620: invokestatic a : (Ljava/lang/Throwable;)Ljava/lang/Throwable;
    //   5623: athrow
    //   5624: aload #8
    //   5626: iconst_1
    //   5627: invokevirtual setAccessible : (Z)V
    //   5630: aload #8
    //   5632: aconst_null
    //   5633: invokevirtual get : (Ljava/lang/Object;)Ljava/lang/Object;
    //   5636: pop
    //   5637: iinc #7, 1
    //   5640: iload_2
    //   5641: ifne -> 5502
    //   5644: sipush #18629
    //   5647: sipush #-28225
    //   5650: invokestatic a : (II)Ljava/lang/String;
    //   5653: invokestatic forName : (Ljava/lang/String;)Ljava/lang/Class;
    //   5656: invokevirtual getDeclaredMethods : ()[Ljava/lang/reflect/Method;
    //   5659: astore #5
    //   5661: aload #5
    //   5663: arraylength
    //   5664: istore #6
    //   5666: iconst_0
    //   5667: istore #7
    //   5669: iload #7
    //   5671: iload #6
    //   5673: if_icmpge -> 5810
    //   5676: aload #5
    //   5678: iload #7
    //   5680: aaload
    //   5681: astore #8
    //   5683: aload #8
    //   5685: invokevirtual getParameterTypes : ()[Ljava/lang/Class;
    //   5688: pop
    //   5689: aload #8
    //   5691: invokevirtual getModifiers : ()I
    //   5694: invokestatic isStatic : (I)Z
    //   5697: ifeq -> 5796
    //   5700: aload #8
    //   5702: invokevirtual getParameterTypes : ()[Ljava/lang/Class;
    //   5705: arraylength
    //   5706: iconst_2
    //   5707: if_icmpne -> 5796
    //   5710: goto -> 5717
    //   5713: invokestatic a : (Ljava/lang/Throwable;)Ljava/lang/Throwable;
    //   5716: athrow
    //   5717: aload #8
    //   5719: invokevirtual getReturnType : ()Ljava/lang/Class;
    //   5722: getstatic java/lang/Boolean.TYPE : Ljava/lang/Class;
    //   5725: if_acmpne -> 5796
    //   5728: goto -> 5735
    //   5731: invokestatic a : (Ljava/lang/Throwable;)Ljava/lang/Throwable;
    //   5734: athrow
    //   5735: aload #8
    //   5737: iconst_1
    //   5738: invokevirtual setAccessible : (Z)V
    //   5741: aload #8
    //   5743: aconst_null
    //   5744: iconst_2
    //   5745: anewarray java/lang/Object
    //   5748: dup
    //   5749: iconst_0
    //   5750: aload_0
    //   5751: aastore
    //   5752: dup
    //   5753: iconst_1
    //   5754: aload_1
    //   5755: ifnonnull -> 5773
    //   5758: goto -> 5765
    //   5761: invokestatic a : (Ljava/lang/Throwable;)Ljava/lang/Throwable;
    //   5764: athrow
    //   5765: aload_1
    //   5766: goto -> 5780
    //   5769: invokestatic a : (Ljava/lang/Throwable;)Ljava/lang/Throwable;
    //   5772: athrow
    //   5773: aload_1
    //   5774: checkcast [B
    //   5777: invokevirtual clone : ()Ljava/lang/Object;
    //   5780: aastore
    //   5781: invokevirtual invoke : (Ljava/lang/Object;[Ljava/lang/Object;)Ljava/lang/Object;
    //   5784: checkcast java/lang/Boolean
    //   5787: invokevirtual booleanValue : ()Z
    //   5790: istore #4
    //   5792: iload_2
    //   5793: ifne -> 5810
    //   5796: iinc #7, 1
    //   5799: iload_2
    //   5800: ifne -> 5669
    //   5803: goto -> 5810
    //   5806: invokestatic a : (Ljava/lang/Throwable;)Ljava/lang/Throwable;
    //   5809: athrow
    //   5810: iload #4
    //   5812: ifeq -> 5818
    //   5815: iload #4
    //   5817: ireturn
    //   5818: getstatic burp/Zry9.ZW : Ljava/lang/String;
    //   5821: getstatic burp/Zl4v.ZT : Ljava/lang/Object;
    //   5824: checkcast java/math/BigInteger
    //   5827: invokevirtual intValue : ()I
    //   5830: bipush #32
    //   5832: irem
    //   5833: invokestatic abs : (I)I
    //   5836: invokevirtual charAt : (I)C
    //   5839: getstatic burp/Zty4.Zu : Ljava/lang/String;
    //   5842: getstatic burp/Zsk4.Ze : Ljava/lang/Object;
    //   5845: checkcast java/math/BigInteger
    //   5848: invokevirtual intValue : ()I
    //   5851: bipush #32
    //   5853: irem
    //   5854: invokestatic abs : (I)I
    //   5857: invokevirtual charAt : (I)C
    //   5860: if_icmpgt -> 6206
    //   5863: sipush #18639
    //   5866: sipush #26014
    //   5869: invokestatic a : (II)Ljava/lang/String;
    //   5872: iconst_1
    //   5873: ldc burp/Zera
    //   5875: invokevirtual getClassLoader : ()Ljava/lang/ClassLoader;
    //   5878: invokestatic forName : (Ljava/lang/String;ZLjava/lang/ClassLoader;)Ljava/lang/Class;
    //   5881: invokevirtual getDeclaredFields : ()[Ljava/lang/reflect/Field;
    //   5884: astore #5
    //   5886: aload #5
    //   5888: arraylength
    //   5889: istore #6
    //   5891: iconst_0
    //   5892: istore #7
    //   5894: iload #7
    //   5896: iload #6
    //   5898: if_icmpge -> 6036
    //   5901: aload #5
    //   5903: iload #7
    //   5905: aaload
    //   5906: astore #8
    //   5908: aload #8
    //   5910: invokevirtual getModifiers : ()I
    //   5913: invokestatic isStatic : (I)Z
    //   5916: ifne -> 5926
    //   5919: goto -> 6029
    //   5922: invokestatic a : (Ljava/lang/Throwable;)Ljava/lang/Throwable;
    //   5925: athrow
    //   5926: aload #8
    //   5928: invokevirtual getType : ()Ljava/lang/Class;
    //   5931: astore #9
    //   5933: aload #9
    //   5935: ifnull -> 6016
    //   5938: aload #9
    //   5940: invokevirtual isPrimitive : ()Z
    //   5943: ifne -> 6016
    //   5946: goto -> 5953
    //   5949: invokestatic a : (Ljava/lang/Throwable;)Ljava/lang/Throwable;
    //   5952: athrow
    //   5953: aload #9
    //   5955: invokevirtual getPackage : ()Ljava/lang/Package;
    //   5958: ifnull -> 6016
    //   5961: goto -> 5968
    //   5964: invokestatic a : (Ljava/lang/Throwable;)Ljava/lang/Throwable;
    //   5967: athrow
    //   5968: aload #9
    //   5970: invokevirtual getPackage : ()Ljava/lang/Package;
    //   5973: invokevirtual getName : ()Ljava/lang/String;
    //   5976: ifnull -> 6016
    //   5979: goto -> 5986
    //   5982: invokestatic a : (Ljava/lang/Throwable;)Ljava/lang/Throwable;
    //   5985: athrow
    //   5986: aload #9
    //   5988: invokevirtual getPackage : ()Ljava/lang/Package;
    //   5991: invokevirtual getName : ()Ljava/lang/String;
    //   5994: sipush #18638
    //   5997: sipush #-1648
    //   6000: invokestatic a : (II)Ljava/lang/String;
    //   6003: invokevirtual startsWith : (Ljava/lang/String;)Z
    //   6006: ifne -> 6016
    //   6009: goto -> 6016
    //   6012: invokestatic a : (Ljava/lang/Throwable;)Ljava/lang/Throwable;
    //   6015: athrow
    //   6016: aload #8
    //   6018: iconst_1
    //   6019: invokevirtual setAccessible : (Z)V
    //   6022: aload #8
    //   6024: aconst_null
    //   6025: invokevirtual get : (Ljava/lang/Object;)Ljava/lang/Object;
    //   6028: pop
    //   6029: iinc #7, 1
    //   6032: iload_2
    //   6033: ifne -> 5894
    //   6036: sipush #18646
    //   6039: sipush #14110
    //   6042: invokestatic a : (II)Ljava/lang/String;
    //   6045: invokestatic forName : (Ljava/lang/String;)Ljava/lang/Class;
    //   6048: invokevirtual getDeclaredMethods : ()[Ljava/lang/reflect/Method;
    //   6051: astore #5
    //   6053: aload #5
    //   6055: arraylength
    //   6056: istore #6
    //   6058: iconst_0
    //   6059: istore #7
    //   6061: iload #7
    //   6063: iload #6
    //   6065: if_icmpge -> 6202
    //   6068: aload #5
    //   6070: iload #7
    //   6072: aaload
    //   6073: astore #8
    //   6075: aload #8
    //   6077: invokevirtual getParameterTypes : ()[Ljava/lang/Class;
    //   6080: pop
    //   6081: aload #8
    //   6083: invokevirtual getModifiers : ()I
    //   6086: invokestatic isStatic : (I)Z
    //   6089: ifeq -> 6188
    //   6092: aload #8
    //   6094: invokevirtual getParameterTypes : ()[Ljava/lang/Class;
    //   6097: arraylength
    //   6098: iconst_2
    //   6099: if_icmpne -> 6188
    //   6102: goto -> 6109
    //   6105: invokestatic a : (Ljava/lang/Throwable;)Ljava/lang/Throwable;
    //   6108: athrow
    //   6109: aload #8
    //   6111: invokevirtual getReturnType : ()Ljava/lang/Class;
    //   6114: getstatic java/lang/Boolean.TYPE : Ljava/lang/Class;
    //   6117: if_acmpne -> 6188
    //   6120: goto -> 6127
    //   6123: invokestatic a : (Ljava/lang/Throwable;)Ljava/lang/Throwable;
    //   6126: athrow
    //   6127: aload #8
    //   6129: iconst_1
    //   6130: invokevirtual setAccessible : (Z)V
    //   6133: aload #8
    //   6135: aconst_null
    //   6136: iconst_2
    //   6137: anewarray java/lang/Object
    //   6140: dup
    //   6141: iconst_0
    //   6142: aload_0
    //   6143: aastore
    //   6144: dup
    //   6145: iconst_1
    //   6146: aload_1
    //   6147: ifnonnull -> 6165
    //   6150: goto -> 6157
    //   6153: invokestatic a : (Ljava/lang/Throwable;)Ljava/lang/Throwable;
    //   6156: athrow
    //   6157: aload_1
    //   6158: goto -> 6172
    //   6161: invokestatic a : (Ljava/lang/Throwable;)Ljava/lang/Throwable;
    //   6164: athrow
    //   6165: aload_1
    //   6166: checkcast [B
    //   6169: invokevirtual clone : ()Ljava/lang/Object;
    //   6172: aastore
    //   6173: invokevirtual invoke : (Ljava/lang/Object;[Ljava/lang/Object;)Ljava/lang/Object;
    //   6176: checkcast java/lang/Boolean
    //   6179: invokevirtual booleanValue : ()Z
    //   6182: istore #4
    //   6184: iload_2
    //   6185: ifne -> 6202
    //   6188: iinc #7, 1
    //   6191: iload_2
    //   6192: ifne -> 6061
    //   6195: goto -> 6202
    //   6198: invokestatic a : (Ljava/lang/Throwable;)Ljava/lang/Throwable;
    //   6201: athrow
    //   6202: iload_2
    //   6203: ifne -> 6545
    //   6206: sipush #18631
    //   6209: sipush #13666
    //   6212: invokestatic a : (II)Ljava/lang/String;
    //   6215: iconst_1
    //   6216: ldc burp/Zkor
    //   6218: invokevirtual getClassLoader : ()Ljava/lang/ClassLoader;
    //   6221: invokestatic forName : (Ljava/lang/String;ZLjava/lang/ClassLoader;)Ljava/lang/Class;
    //   6224: invokevirtual getDeclaredFields : ()[Ljava/lang/reflect/Field;
    //   6227: astore #5
    //   6229: aload #5
    //   6231: arraylength
    //   6232: istore #6
    //   6234: iconst_0
    //   6235: istore #7
    //   6237: iload #7
    //   6239: iload #6
    //   6241: if_icmpge -> 6379
    //   6244: aload #5
    //   6246: iload #7
    //   6248: aaload
    //   6249: astore #8
    //   6251: aload #8
    //   6253: invokevirtual getModifiers : ()I
    //   6256: invokestatic isStatic : (I)Z
    //   6259: ifne -> 6269
    //   6262: goto -> 6372
    //   6265: invokestatic a : (Ljava/lang/Throwable;)Ljava/lang/Throwable;
    //   6268: athrow
    //   6269: aload #8
    //   6271: invokevirtual getType : ()Ljava/lang/Class;
    //   6274: astore #9
    //   6276: aload #9
    //   6278: ifnull -> 6359
    //   6281: aload #9
    //   6283: invokevirtual isPrimitive : ()Z
    //   6286: ifne -> 6359
    //   6289: goto -> 6296
    //   6292: invokestatic a : (Ljava/lang/Throwable;)Ljava/lang/Throwable;
    //   6295: athrow
    //   6296: aload #9
    //   6298: invokevirtual getPackage : ()Ljava/lang/Package;
    //   6301: ifnull -> 6359
    //   6304: goto -> 6311
    //   6307: invokestatic a : (Ljava/lang/Throwable;)Ljava/lang/Throwable;
    //   6310: athrow
    //   6311: aload #9
    //   6313: invokevirtual getPackage : ()Ljava/lang/Package;
    //   6316: invokevirtual getName : ()Ljava/lang/String;
    //   6319: ifnull -> 6359
    //   6322: goto -> 6329
    //   6325: invokestatic a : (Ljava/lang/Throwable;)Ljava/lang/Throwable;
    //   6328: athrow
    //   6329: aload #9
    //   6331: invokevirtual getPackage : ()Ljava/lang/Package;
    //   6334: invokevirtual getName : ()Ljava/lang/String;
    //   6337: sipush #18638
    //   6340: sipush #-1648
    //   6343: invokestatic a : (II)Ljava/lang/String;
    //   6346: invokevirtual startsWith : (Ljava/lang/String;)Z
    //   6349: ifne -> 6359
    //   6352: goto -> 6359
    //   6355: invokestatic a : (Ljava/lang/Throwable;)Ljava/lang/Throwable;
    //   6358: athrow
    //   6359: aload #8
    //   6361: iconst_1
    //   6362: invokevirtual setAccessible : (Z)V
    //   6365: aload #8
    //   6367: aconst_null
    //   6368: invokevirtual get : (Ljava/lang/Object;)Ljava/lang/Object;
    //   6371: pop
    //   6372: iinc #7, 1
    //   6375: iload_2
    //   6376: ifne -> 6237
    //   6379: sipush #18637
    //   6382: sipush #27817
    //   6385: invokestatic a : (II)Ljava/lang/String;
    //   6388: invokestatic forName : (Ljava/lang/String;)Ljava/lang/Class;
    //   6391: invokevirtual getDeclaredMethods : ()[Ljava/lang/reflect/Method;
    //   6394: astore #5
    //   6396: aload #5
    //   6398: arraylength
    //   6399: istore #6
    //   6401: iconst_0
    //   6402: istore #7
    //   6404: iload #7
    //   6406: iload #6
    //   6408: if_icmpge -> 6545
    //   6411: aload #5
    //   6413: iload #7
    //   6415: aaload
    //   6416: astore #8
    //   6418: aload #8
    //   6420: invokevirtual getParameterTypes : ()[Ljava/lang/Class;
    //   6423: pop
    //   6424: aload #8
    //   6426: invokevirtual getModifiers : ()I
    //   6429: invokestatic isStatic : (I)Z
    //   6432: ifeq -> 6531
    //   6435: aload #8
    //   6437: invokevirtual getParameterTypes : ()[Ljava/lang/Class;
    //   6440: arraylength
    //   6441: iconst_2
    //   6442: if_icmpne -> 6531
    //   6445: goto -> 6452
    //   6448: invokestatic a : (Ljava/lang/Throwable;)Ljava/lang/Throwable;
    //   6451: athrow
    //   6452: aload #8
    //   6454: invokevirtual getReturnType : ()Ljava/lang/Class;
    //   6457: getstatic java/lang/Boolean.TYPE : Ljava/lang/Class;
    //   6460: if_acmpne -> 6531
    //   6463: goto -> 6470
    //   6466: invokestatic a : (Ljava/lang/Throwable;)Ljava/lang/Throwable;
    //   6469: athrow
    //   6470: aload #8
    //   6472: iconst_1
    //   6473: invokevirtual setAccessible : (Z)V
    //   6476: aload #8
    //   6478: aconst_null
    //   6479: iconst_2
    //   6480: anewarray java/lang/Object
    //   6483: dup
    //   6484: iconst_0
    //   6485: aload_0
    //   6486: aastore
    //   6487: dup
    //   6488: iconst_1
    //   6489: aload_1
    //   6490: ifnonnull -> 6508
    //   6493: goto -> 6500
    //   6496: invokestatic a : (Ljava/lang/Throwable;)Ljava/lang/Throwable;
    //   6499: athrow
    //   6500: aload_1
    //   6501: goto -> 6515
    //   6504: invokestatic a : (Ljava/lang/Throwable;)Ljava/lang/Throwable;
    //   6507: athrow
    //   6508: aload_1
    //   6509: checkcast [B
    //   6512: invokevirtual clone : ()Ljava/lang/Object;
    //   6515: aastore
    //   6516: invokevirtual invoke : (Ljava/lang/Object;[Ljava/lang/Object;)Ljava/lang/Object;
    //   6519: checkcast java/lang/Boolean
    //   6522: invokevirtual booleanValue : ()Z
    //   6525: istore #4
    //   6527: iload_2
    //   6528: ifne -> 6545
    //   6531: iinc #7, 1
    //   6534: iload_2
    //   6535: ifne -> 6404
    //   6538: goto -> 6545
    //   6541: invokestatic a : (Ljava/lang/Throwable;)Ljava/lang/Throwable;
    //   6544: athrow
    //   6545: iload #4
    //   6547: ifeq -> 6553
    //   6550: iload #4
    //   6552: ireturn
    //   6553: getstatic burp/Zszz.Zg : Ljava/lang/String;
    //   6556: getstatic burp/Ztvp.Zy : Ljava/lang/Object;
    //   6559: checkcast java/math/BigInteger
    //   6562: invokevirtual intValue : ()I
    //   6565: bipush #32
    //   6567: irem
    //   6568: invokestatic abs : (I)I
    //   6571: invokevirtual charAt : (I)C
    //   6574: getstatic burp/Zsmn.Zo : Ljava/lang/String;
    //   6577: getstatic burp/Ze08.ZJ : Ljava/lang/Object;
    //   6580: checkcast java/math/BigInteger
    //   6583: invokevirtual intValue : ()I
    //   6586: bipush #32
    //   6588: irem
    //   6589: invokestatic abs : (I)I
    //   6592: invokevirtual charAt : (I)C
    //   6595: if_icmpgt -> 6941
    //   6598: sipush #18642
    //   6601: sipush #15649
    //   6604: invokestatic a : (II)Ljava/lang/String;
    //   6607: iconst_1
    //   6608: ldc burp/Zm06
    //   6610: invokevirtual getClassLoader : ()Ljava/lang/ClassLoader;
    //   6613: invokestatic forName : (Ljava/lang/String;ZLjava/lang/ClassLoader;)Ljava/lang/Class;
    //   6616: invokevirtual getDeclaredFields : ()[Ljava/lang/reflect/Field;
    //   6619: astore #5
    //   6621: aload #5
    //   6623: arraylength
    //   6624: istore #6
    //   6626: iconst_0
    //   6627: istore #7
    //   6629: iload #7
    //   6631: iload #6
    //   6633: if_icmpge -> 6771
    //   6636: aload #5
    //   6638: iload #7
    //   6640: aaload
    //   6641: astore #8
    //   6643: aload #8
    //   6645: invokevirtual getModifiers : ()I
    //   6648: invokestatic isStatic : (I)Z
    //   6651: ifne -> 6661
    //   6654: goto -> 6764
    //   6657: invokestatic a : (Ljava/lang/Throwable;)Ljava/lang/Throwable;
    //   6660: athrow
    //   6661: aload #8
    //   6663: invokevirtual getType : ()Ljava/lang/Class;
    //   6666: astore #9
    //   6668: aload #9
    //   6670: ifnull -> 6751
    //   6673: aload #9
    //   6675: invokevirtual isPrimitive : ()Z
    //   6678: ifne -> 6751
    //   6681: goto -> 6688
    //   6684: invokestatic a : (Ljava/lang/Throwable;)Ljava/lang/Throwable;
    //   6687: athrow
    //   6688: aload #9
    //   6690: invokevirtual getPackage : ()Ljava/lang/Package;
    //   6693: ifnull -> 6751
    //   6696: goto -> 6703
    //   6699: invokestatic a : (Ljava/lang/Throwable;)Ljava/lang/Throwable;
    //   6702: athrow
    //   6703: aload #9
    //   6705: invokevirtual getPackage : ()Ljava/lang/Package;
    //   6708: invokevirtual getName : ()Ljava/lang/String;
    //   6711: ifnull -> 6751
    //   6714: goto -> 6721
    //   6717: invokestatic a : (Ljava/lang/Throwable;)Ljava/lang/Throwable;
    //   6720: athrow
    //   6721: aload #9
    //   6723: invokevirtual getPackage : ()Ljava/lang/Package;
    //   6726: invokevirtual getName : ()Ljava/lang/String;
    //   6729: sipush #18638
    //   6732: sipush #-1648
    //   6735: invokestatic a : (II)Ljava/lang/String;
    //   6738: invokevirtual startsWith : (Ljava/lang/String;)Z
    //   6741: ifne -> 6751
    //   6744: goto -> 6751
    //   6747: invokestatic a : (Ljava/lang/Throwable;)Ljava/lang/Throwable;
    //   6750: athrow
    //   6751: aload #8
    //   6753: iconst_1
    //   6754: invokevirtual setAccessible : (Z)V
    //   6757: aload #8
    //   6759: aconst_null
    //   6760: invokevirtual get : (Ljava/lang/Object;)Ljava/lang/Object;
    //   6763: pop
    //   6764: iinc #7, 1
    //   6767: iload_2
    //   6768: ifne -> 6629
    //   6771: sipush #18627
    //   6774: sipush #28347
    //   6777: invokestatic a : (II)Ljava/lang/String;
    //   6780: invokestatic forName : (Ljava/lang/String;)Ljava/lang/Class;
    //   6783: invokevirtual getDeclaredMethods : ()[Ljava/lang/reflect/Method;
    //   6786: astore #5
    //   6788: aload #5
    //   6790: arraylength
    //   6791: istore #6
    //   6793: iconst_0
    //   6794: istore #7
    //   6796: iload #7
    //   6798: iload #6
    //   6800: if_icmpge -> 6937
    //   6803: aload #5
    //   6805: iload #7
    //   6807: aaload
    //   6808: astore #8
    //   6810: aload #8
    //   6812: invokevirtual getParameterTypes : ()[Ljava/lang/Class;
    //   6815: pop
    //   6816: aload #8
    //   6818: invokevirtual getModifiers : ()I
    //   6821: invokestatic isStatic : (I)Z
    //   6824: ifeq -> 6923
    //   6827: aload #8
    //   6829: invokevirtual getParameterTypes : ()[Ljava/lang/Class;
    //   6832: arraylength
    //   6833: iconst_2
    //   6834: if_icmpne -> 6923
    //   6837: goto -> 6844
    //   6840: invokestatic a : (Ljava/lang/Throwable;)Ljava/lang/Throwable;
    //   6843: athrow
    //   6844: aload #8
    //   6846: invokevirtual getReturnType : ()Ljava/lang/Class;
    //   6849: getstatic java/lang/Boolean.TYPE : Ljava/lang/Class;
    //   6852: if_acmpne -> 6923
    //   6855: goto -> 6862
    //   6858: invokestatic a : (Ljava/lang/Throwable;)Ljava/lang/Throwable;
    //   6861: athrow
    //   6862: aload #8
    //   6864: iconst_1
    //   6865: invokevirtual setAccessible : (Z)V
    //   6868: aload #8
    //   6870: aconst_null
    //   6871: iconst_2
    //   6872: anewarray java/lang/Object
    //   6875: dup
    //   6876: iconst_0
    //   6877: aload_0
    //   6878: aastore
    //   6879: dup
    //   6880: iconst_1
    //   6881: aload_1
    //   6882: ifnonnull -> 6900
    //   6885: goto -> 6892
    //   6888: invokestatic a : (Ljava/lang/Throwable;)Ljava/lang/Throwable;
    //   6891: athrow
    //   6892: aload_1
    //   6893: goto -> 6907
    //   6896: invokestatic a : (Ljava/lang/Throwable;)Ljava/lang/Throwable;
    //   6899: athrow
    //   6900: aload_1
    //   6901: checkcast [B
    //   6904: invokevirtual clone : ()Ljava/lang/Object;
    //   6907: aastore
    //   6908: invokevirtual invoke : (Ljava/lang/Object;[Ljava/lang/Object;)Ljava/lang/Object;
    //   6911: checkcast java/lang/Boolean
    //   6914: invokevirtual booleanValue : ()Z
    //   6917: istore #4
    //   6919: iload_2
    //   6920: ifne -> 6937
    //   6923: iinc #7, 1
    //   6926: iload_2
    //   6927: ifne -> 6796
    //   6930: goto -> 6937
    //   6933: invokestatic a : (Ljava/lang/Throwable;)Ljava/lang/Throwable;
    //   6936: athrow
    //   6937: iload_2
    //   6938: ifne -> 7280
    //   6941: sipush #18635
    //   6944: sipush #-11635
    //   6947: invokestatic a : (II)Ljava/lang/String;
    //   6950: iconst_1
    //   6951: ldc burp/Zzyr
    //   6953: invokevirtual getClassLoader : ()Ljava/lang/ClassLoader;
    //   6956: invokestatic forName : (Ljava/lang/String;ZLjava/lang/ClassLoader;)Ljava/lang/Class;
    //   6959: invokevirtual getDeclaredFields : ()[Ljava/lang/reflect/Field;
    //   6962: astore #5
    //   6964: aload #5
    //   6966: arraylength
    //   6967: istore #6
    //   6969: iconst_0
    //   6970: istore #7
    //   6972: iload #7
    //   6974: iload #6
    //   6976: if_icmpge -> 7114
    //   6979: aload #5
    //   6981: iload #7
    //   6983: aaload
    //   6984: astore #8
    //   6986: aload #8
    //   6988: invokevirtual getModifiers : ()I
    //   6991: invokestatic isStatic : (I)Z
    //   6994: ifne -> 7004
    //   6997: goto -> 7107
    //   7000: invokestatic a : (Ljava/lang/Throwable;)Ljava/lang/Throwable;
    //   7003: athrow
    //   7004: aload #8
    //   7006: invokevirtual getType : ()Ljava/lang/Class;
    //   7009: astore #9
    //   7011: aload #9
    //   7013: ifnull -> 7094
    //   7016: aload #9
    //   7018: invokevirtual isPrimitive : ()Z
    //   7021: ifne -> 7094
    //   7024: goto -> 7031
    //   7027: invokestatic a : (Ljava/lang/Throwable;)Ljava/lang/Throwable;
    //   7030: athrow
    //   7031: aload #9
    //   7033: invokevirtual getPackage : ()Ljava/lang/Package;
    //   7036: ifnull -> 7094
    //   7039: goto -> 7046
    //   7042: invokestatic a : (Ljava/lang/Throwable;)Ljava/lang/Throwable;
    //   7045: athrow
    //   7046: aload #9
    //   7048: invokevirtual getPackage : ()Ljava/lang/Package;
    //   7051: invokevirtual getName : ()Ljava/lang/String;
    //   7054: ifnull -> 7094
    //   7057: goto -> 7064
    //   7060: invokestatic a : (Ljava/lang/Throwable;)Ljava/lang/Throwable;
    //   7063: athrow
    //   7064: aload #9
    //   7066: invokevirtual getPackage : ()Ljava/lang/Package;
    //   7069: invokevirtual getName : ()Ljava/lang/String;
    //   7072: sipush #18638
    //   7075: sipush #-1648
    //   7078: invokestatic a : (II)Ljava/lang/String;
    //   7081: invokevirtual startsWith : (Ljava/lang/String;)Z
    //   7084: ifne -> 7094
    //   7087: goto -> 7094
    //   7090: invokestatic a : (Ljava/lang/Throwable;)Ljava/lang/Throwable;
    //   7093: athrow
    //   7094: aload #8
    //   7096: iconst_1
    //   7097: invokevirtual setAccessible : (Z)V
    //   7100: aload #8
    //   7102: aconst_null
    //   7103: invokevirtual get : (Ljava/lang/Object;)Ljava/lang/Object;
    //   7106: pop
    //   7107: iinc #7, 1
    //   7110: iload_2
    //   7111: ifne -> 6972
    //   7114: sipush #18644
    //   7117: sipush #-30112
    //   7120: invokestatic a : (II)Ljava/lang/String;
    //   7123: invokestatic forName : (Ljava/lang/String;)Ljava/lang/Class;
    //   7126: invokevirtual getDeclaredMethods : ()[Ljava/lang/reflect/Method;
    //   7129: astore #5
    //   7131: aload #5
    //   7133: arraylength
    //   7134: istore #6
    //   7136: iconst_0
    //   7137: istore #7
    //   7139: iload #7
    //   7141: iload #6
    //   7143: if_icmpge -> 7280
    //   7146: aload #5
    //   7148: iload #7
    //   7150: aaload
    //   7151: astore #8
    //   7153: aload #8
    //   7155: invokevirtual getParameterTypes : ()[Ljava/lang/Class;
    //   7158: pop
    //   7159: aload #8
    //   7161: invokevirtual getModifiers : ()I
    //   7164: invokestatic isStatic : (I)Z
    //   7167: ifeq -> 7266
    //   7170: aload #8
    //   7172: invokevirtual getParameterTypes : ()[Ljava/lang/Class;
    //   7175: arraylength
    //   7176: iconst_2
    //   7177: if_icmpne -> 7266
    //   7180: goto -> 7187
    //   7183: invokestatic a : (Ljava/lang/Throwable;)Ljava/lang/Throwable;
    //   7186: athrow
    //   7187: aload #8
    //   7189: invokevirtual getReturnType : ()Ljava/lang/Class;
    //   7192: getstatic java/lang/Boolean.TYPE : Ljava/lang/Class;
    //   7195: if_acmpne -> 7266
    //   7198: goto -> 7205
    //   7201: invokestatic a : (Ljava/lang/Throwable;)Ljava/lang/Throwable;
    //   7204: athrow
    //   7205: aload #8
    //   7207: iconst_1
    //   7208: invokevirtual setAccessible : (Z)V
    //   7211: aload #8
    //   7213: aconst_null
    //   7214: iconst_2
    //   7215: anewarray java/lang/Object
    //   7218: dup
    //   7219: iconst_0
    //   7220: aload_0
    //   7221: aastore
    //   7222: dup
    //   7223: iconst_1
    //   7224: aload_1
    //   7225: ifnonnull -> 7243
    //   7228: goto -> 7235
    //   7231: invokestatic a : (Ljava/lang/Throwable;)Ljava/lang/Throwable;
    //   7234: athrow
    //   7235: aload_1
    //   7236: goto -> 7250
    //   7239: invokestatic a : (Ljava/lang/Throwable;)Ljava/lang/Throwable;
    //   7242: athrow
    //   7243: aload_1
    //   7244: checkcast [B
    //   7247: invokevirtual clone : ()Ljava/lang/Object;
    //   7250: aastore
    //   7251: invokevirtual invoke : (Ljava/lang/Object;[Ljava/lang/Object;)Ljava/lang/Object;
    //   7254: checkcast java/lang/Boolean
    //   7257: invokevirtual booleanValue : ()Z
    //   7260: istore #4
    //   7262: iload_2
    //   7263: ifne -> 7280
    //   7266: iinc #7, 1
    //   7269: iload_2
    //   7270: ifne -> 7139
    //   7273: goto -> 7280
    //   7276: invokestatic a : (Ljava/lang/Throwable;)Ljava/lang/Throwable;
    //   7279: athrow
    //   7280: iload #4
    //   7282: ifeq -> 7288
    //   7285: iload #4
    //   7287: ireturn
    //   7288: getstatic burp/Zeoi.Zh : Ljava/lang/String;
    //   7291: getstatic burp/Zxjm.Zn : Ljava/lang/Object;
    //   7294: checkcast java/math/BigInteger
    //   7297: invokevirtual intValue : ()I
    //   7300: bipush #32
    //   7302: irem
    //   7303: invokestatic abs : (I)I
    //   7306: invokevirtual charAt : (I)C
    //   7309: getstatic burp/Zkff.Zs : Ljava/lang/String;
    //   7312: getstatic burp/Zboa.Zh : Ljava/lang/Object;
    //   7315: checkcast java/math/BigInteger
    //   7318: invokevirtual intValue : ()I
    //   7321: bipush #32
    //   7323: irem
    //   7324: invokestatic abs : (I)I
    //   7327: invokevirtual charAt : (I)C
    //   7330: if_icmpgt -> 7676
    //   7333: sipush #18648
    //   7336: sipush #-20680
    //   7339: invokestatic a : (II)Ljava/lang/String;
    //   7342: iconst_1
    //   7343: ldc burp/Zs0h
    //   7345: invokevirtual getClassLoader : ()Ljava/lang/ClassLoader;
    //   7348: invokestatic forName : (Ljava/lang/String;ZLjava/lang/ClassLoader;)Ljava/lang/Class;
    //   7351: invokevirtual getDeclaredFields : ()[Ljava/lang/reflect/Field;
    //   7354: astore #5
    //   7356: aload #5
    //   7358: arraylength
    //   7359: istore #6
    //   7361: iconst_0
    //   7362: istore #7
    //   7364: iload #7
    //   7366: iload #6
    //   7368: if_icmpge -> 7506
    //   7371: aload #5
    //   7373: iload #7
    //   7375: aaload
    //   7376: astore #8
    //   7378: aload #8
    //   7380: invokevirtual getModifiers : ()I
    //   7383: invokestatic isStatic : (I)Z
    //   7386: ifne -> 7396
    //   7389: goto -> 7499
    //   7392: invokestatic a : (Ljava/lang/Throwable;)Ljava/lang/Throwable;
    //   7395: athrow
    //   7396: aload #8
    //   7398: invokevirtual getType : ()Ljava/lang/Class;
    //   7401: astore #9
    //   7403: aload #9
    //   7405: ifnull -> 7486
    //   7408: aload #9
    //   7410: invokevirtual isPrimitive : ()Z
    //   7413: ifne -> 7486
    //   7416: goto -> 7423
    //   7419: invokestatic a : (Ljava/lang/Throwable;)Ljava/lang/Throwable;
    //   7422: athrow
    //   7423: aload #9
    //   7425: invokevirtual getPackage : ()Ljava/lang/Package;
    //   7428: ifnull -> 7486
    //   7431: goto -> 7438
    //   7434: invokestatic a : (Ljava/lang/Throwable;)Ljava/lang/Throwable;
    //   7437: athrow
    //   7438: aload #9
    //   7440: invokevirtual getPackage : ()Ljava/lang/Package;
    //   7443: invokevirtual getName : ()Ljava/lang/String;
    //   7446: ifnull -> 7486
    //   7449: goto -> 7456
    //   7452: invokestatic a : (Ljava/lang/Throwable;)Ljava/lang/Throwable;
    //   7455: athrow
    //   7456: aload #9
    //   7458: invokevirtual getPackage : ()Ljava/lang/Package;
    //   7461: invokevirtual getName : ()Ljava/lang/String;
    //   7464: sipush #18638
    //   7467: sipush #-1648
    //   7470: invokestatic a : (II)Ljava/lang/String;
    //   7473: invokevirtual startsWith : (Ljava/lang/String;)Z
    //   7476: ifne -> 7486
    //   7479: goto -> 7486
    //   7482: invokestatic a : (Ljava/lang/Throwable;)Ljava/lang/Throwable;
    //   7485: athrow
    //   7486: aload #8
    //   7488: iconst_1
    //   7489: invokevirtual setAccessible : (Z)V
    //   7492: aload #8
    //   7494: aconst_null
    //   7495: invokevirtual get : (Ljava/lang/Object;)Ljava/lang/Object;
    //   7498: pop
    //   7499: iinc #7, 1
    //   7502: iload_2
    //   7503: ifne -> 7364
    //   7506: sipush #18647
    //   7509: sipush #4912
    //   7512: invokestatic a : (II)Ljava/lang/String;
    //   7515: invokestatic forName : (Ljava/lang/String;)Ljava/lang/Class;
    //   7518: invokevirtual getDeclaredMethods : ()[Ljava/lang/reflect/Method;
    //   7521: astore #5
    //   7523: aload #5
    //   7525: arraylength
    //   7526: istore #6
    //   7528: iconst_0
    //   7529: istore #7
    //   7531: iload #7
    //   7533: iload #6
    //   7535: if_icmpge -> 7672
    //   7538: aload #5
    //   7540: iload #7
    //   7542: aaload
    //   7543: astore #8
    //   7545: aload #8
    //   7547: invokevirtual getParameterTypes : ()[Ljava/lang/Class;
    //   7550: pop
    //   7551: aload #8
    //   7553: invokevirtual getModifiers : ()I
    //   7556: invokestatic isStatic : (I)Z
    //   7559: ifeq -> 7658
    //   7562: aload #8
    //   7564: invokevirtual getParameterTypes : ()[Ljava/lang/Class;
    //   7567: arraylength
    //   7568: iconst_2
    //   7569: if_icmpne -> 7658
    //   7572: goto -> 7579
    //   7575: invokestatic a : (Ljava/lang/Throwable;)Ljava/lang/Throwable;
    //   7578: athrow
    //   7579: aload #8
    //   7581: invokevirtual getReturnType : ()Ljava/lang/Class;
    //   7584: getstatic java/lang/Boolean.TYPE : Ljava/lang/Class;
    //   7587: if_acmpne -> 7658
    //   7590: goto -> 7597
    //   7593: invokestatic a : (Ljava/lang/Throwable;)Ljava/lang/Throwable;
    //   7596: athrow
    //   7597: aload #8
    //   7599: iconst_1
    //   7600: invokevirtual setAccessible : (Z)V
    //   7603: aload #8
    //   7605: aconst_null
    //   7606: iconst_2
    //   7607: anewarray java/lang/Object
    //   7610: dup
    //   7611: iconst_0
    //   7612: aload_0
    //   7613: aastore
    //   7614: dup
    //   7615: iconst_1
    //   7616: aload_1
    //   7617: ifnonnull -> 7635
    //   7620: goto -> 7627
    //   7623: invokestatic a : (Ljava/lang/Throwable;)Ljava/lang/Throwable;
    //   7626: athrow
    //   7627: aload_1
    //   7628: goto -> 7642
    //   7631: invokestatic a : (Ljava/lang/Throwable;)Ljava/lang/Throwable;
    //   7634: athrow
    //   7635: aload_1
    //   7636: checkcast [B
    //   7639: invokevirtual clone : ()Ljava/lang/Object;
    //   7642: aastore
    //   7643: invokevirtual invoke : (Ljava/lang/Object;[Ljava/lang/Object;)Ljava/lang/Object;
    //   7646: checkcast java/lang/Boolean
    //   7649: invokevirtual booleanValue : ()Z
    //   7652: istore #4
    //   7654: iload_2
    //   7655: ifne -> 7672
    //   7658: iinc #7, 1
    //   7661: iload_2
    //   7662: ifne -> 7531
    //   7665: goto -> 7672
    //   7668: invokestatic a : (Ljava/lang/Throwable;)Ljava/lang/Throwable;
    //   7671: athrow
    //   7672: iload_2
    //   7673: ifne -> 8015
    //   7676: sipush #18633
    //   7679: sipush #32458
    //   7682: invokestatic a : (II)Ljava/lang/String;
    //   7685: iconst_1
    //   7686: ldc burp/Zktq
    //   7688: invokevirtual getClassLoader : ()Ljava/lang/ClassLoader;
    //   7691: invokestatic forName : (Ljava/lang/String;ZLjava/lang/ClassLoader;)Ljava/lang/Class;
    //   7694: invokevirtual getDeclaredFields : ()[Ljava/lang/reflect/Field;
    //   7697: astore #5
    //   7699: aload #5
    //   7701: arraylength
    //   7702: istore #6
    //   7704: iconst_0
    //   7705: istore #7
    //   7707: iload #7
    //   7709: iload #6
    //   7711: if_icmpge -> 7849
    //   7714: aload #5
    //   7716: iload #7
    //   7718: aaload
    //   7719: astore #8
    //   7721: aload #8
    //   7723: invokevirtual getModifiers : ()I
    //   7726: invokestatic isStatic : (I)Z
    //   7729: ifne -> 7739
    //   7732: goto -> 7842
    //   7735: invokestatic a : (Ljava/lang/Throwable;)Ljava/lang/Throwable;
    //   7738: athrow
    //   7739: aload #8
    //   7741: invokevirtual getType : ()Ljava/lang/Class;
    //   7744: astore #9
    //   7746: aload #9
    //   7748: ifnull -> 7829
    //   7751: aload #9
    //   7753: invokevirtual isPrimitive : ()Z
    //   7756: ifne -> 7829
    //   7759: goto -> 7766
    //   7762: invokestatic a : (Ljava/lang/Throwable;)Ljava/lang/Throwable;
    //   7765: athrow
    //   7766: aload #9
    //   7768: invokevirtual getPackage : ()Ljava/lang/Package;
    //   7771: ifnull -> 7829
    //   7774: goto -> 7781
    //   7777: invokestatic a : (Ljava/lang/Throwable;)Ljava/lang/Throwable;
    //   7780: athrow
    //   7781: aload #9
    //   7783: invokevirtual getPackage : ()Ljava/lang/Package;
    //   7786: invokevirtual getName : ()Ljava/lang/String;
    //   7789: ifnull -> 7829
    //   7792: goto -> 7799
    //   7795: invokestatic a : (Ljava/lang/Throwable;)Ljava/lang/Throwable;
    //   7798: athrow
    //   7799: aload #9
    //   7801: invokevirtual getPackage : ()Ljava/lang/Package;
    //   7804: invokevirtual getName : ()Ljava/lang/String;
    //   7807: sipush #18638
    //   7810: sipush #-1648
    //   7813: invokestatic a : (II)Ljava/lang/String;
    //   7816: invokevirtual startsWith : (Ljava/lang/String;)Z
    //   7819: ifne -> 7829
    //   7822: goto -> 7829
    //   7825: invokestatic a : (Ljava/lang/Throwable;)Ljava/lang/Throwable;
    //   7828: athrow
    //   7829: aload #8
    //   7831: iconst_1
    //   7832: invokevirtual setAccessible : (Z)V
    //   7835: aload #8
    //   7837: aconst_null
    //   7838: invokevirtual get : (Ljava/lang/Object;)Ljava/lang/Object;
    //   7841: pop
    //   7842: iinc #7, 1
    //   7845: iload_2
    //   7846: ifne -> 7707
    //   7849: sipush #18643
    //   7852: sipush #21841
    //   7855: invokestatic a : (II)Ljava/lang/String;
    //   7858: invokestatic forName : (Ljava/lang/String;)Ljava/lang/Class;
    //   7861: invokevirtual getDeclaredMethods : ()[Ljava/lang/reflect/Method;
    //   7864: astore #5
    //   7866: aload #5
    //   7868: arraylength
    //   7869: istore #6
    //   7871: iconst_0
    //   7872: istore #7
    //   7874: iload #7
    //   7876: iload #6
    //   7878: if_icmpge -> 8015
    //   7881: aload #5
    //   7883: iload #7
    //   7885: aaload
    //   7886: astore #8
    //   7888: aload #8
    //   7890: invokevirtual getParameterTypes : ()[Ljava/lang/Class;
    //   7893: pop
    //   7894: aload #8
    //   7896: invokevirtual getModifiers : ()I
    //   7899: invokestatic isStatic : (I)Z
    //   7902: ifeq -> 8001
    //   7905: aload #8
    //   7907: invokevirtual getParameterTypes : ()[Ljava/lang/Class;
    //   7910: arraylength
    //   7911: iconst_2
    //   7912: if_icmpne -> 8001
    //   7915: goto -> 7922
    //   7918: invokestatic a : (Ljava/lang/Throwable;)Ljava/lang/Throwable;
    //   7921: athrow
    //   7922: aload #8
    //   7924: invokevirtual getReturnType : ()Ljava/lang/Class;
    //   7927: getstatic java/lang/Boolean.TYPE : Ljava/lang/Class;
    //   7930: if_acmpne -> 8001
    //   7933: goto -> 7940
    //   7936: invokestatic a : (Ljava/lang/Throwable;)Ljava/lang/Throwable;
    //   7939: athrow
    //   7940: aload #8
    //   7942: iconst_1
    //   7943: invokevirtual setAccessible : (Z)V
    //   7946: aload #8
    //   7948: aconst_null
    //   7949: iconst_2
    //   7950: anewarray java/lang/Object
    //   7953: dup
    //   7954: iconst_0
    //   7955: aload_0
    //   7956: aastore
    //   7957: dup
    //   7958: iconst_1
    //   7959: aload_1
    //   7960: ifnonnull -> 7978
    //   7963: goto -> 7970
    //   7966: invokestatic a : (Ljava/lang/Throwable;)Ljava/lang/Throwable;
    //   7969: athrow
    //   7970: aload_1
    //   7971: goto -> 7985
    //   7974: invokestatic a : (Ljava/lang/Throwable;)Ljava/lang/Throwable;
    //   7977: athrow
    //   7978: aload_1
    //   7979: checkcast [B
    //   7982: invokevirtual clone : ()Ljava/lang/Object;
    //   7985: aastore
    //   7986: invokevirtual invoke : (Ljava/lang/Object;[Ljava/lang/Object;)Ljava/lang/Object;
    //   7989: checkcast java/lang/Boolean
    //   7992: invokevirtual booleanValue : ()Z
    //   7995: istore #4
    //   7997: iload_2
    //   7998: ifne -> 8015
    //   8001: iinc #7, 1
    //   8004: iload_2
    //   8005: ifne -> 7874
    //   8008: goto -> 8015
    //   8011: invokestatic a : (Ljava/lang/Throwable;)Ljava/lang/Throwable;
    //   8014: athrow
    //   8015: iload #4
    //   8017: ireturn
    //   8018: astore_3
    //   8019: new java/lang/Exception
    //   8022: dup
    //   8023: aload_3
    //   8024: invokevirtual getMessage : ()Ljava/lang/String;
    //   8027: invokespecial <init> : (Ljava/lang/String;)V
    //   8030: athrow
    // Exception table:
    //   from	to	target	type
    //   4	5817	8018	java/lang/Throwable
    //   33	47	50	java/lang/Throwable
    //   40	61	64	java/lang/Throwable
    //   54	75	78	java/lang/Throwable
    //   68	89	92	java/lang/Throwable
    //   82	103	106	java/lang/Throwable
    //   96	117	120	java/lang/Throwable
    //   110	131	134	java/lang/Throwable
    //   124	145	148	java/lang/Throwable
    //   138	155	158	java/lang/Throwable
    //   194	208	211	java/lang/Throwable
    //   201	222	225	java/lang/Throwable
    //   215	236	239	java/lang/Throwable
    //   229	250	253	java/lang/Throwable
    //   243	264	267	java/lang/Throwable
    //   257	278	281	java/lang/Throwable
    //   271	292	295	java/lang/Throwable
    //   285	306	309	java/lang/Throwable
    //   299	323	326	java/lang/Throwable
    //   387	405	408	java/lang/Throwable
    //   396	421	424	java/lang/Throwable
    //   412	438	441	java/lang/Throwable
    //   428	454	457	java/lang/Throwable
    //   445	471	474	java/lang/Throwable
    //   461	487	490	java/lang/Throwable
    //   478	503	506	java/lang/Throwable
    //   494	526	529	java/lang/Throwable
    //   510	542	545	java/lang/Throwable
    //   533	558	561	java/lang/Throwable
    //   549	581	584	java/lang/Throwable
    //   565	597	600	java/lang/Throwable
    //   588	613	616	java/lang/Throwable
    //   604	632	635	java/lang/Throwable
    //   762	797	800	java/lang/Throwable
    //   804	845	848	java/lang/Throwable
    //   1016	1031	1031	java/lang/Throwable
    //   2033	2059	2059	java/lang/Throwable
    //   2140	2155	2155	java/lang/Throwable
    //   3337	3362	3365	java/lang/Throwable
    //   3406	3582	3585	java/lang/Throwable
    //   3552	3619	3622	java/lang/Throwable
    //   3589	3656	3659	java/lang/Throwable
    //   3626	3693	3696	java/lang/Throwable
    //   3663	3730	3733	java/lang/Throwable
    //   3700	3767	3770	java/lang/Throwable
    //   3737	3804	3807	java/lang/Throwable
    //   3774	3841	3844	java/lang/Throwable
    //   3811	3878	3881	java/lang/Throwable
    //   3848	3915	3918	java/lang/Throwable
    //   3885	3952	3955	java/lang/Throwable
    //   3922	3989	3992	java/lang/Throwable
    //   3959	4026	4029	java/lang/Throwable
    //   3996	4063	4066	java/lang/Throwable
    //   4033	4100	4103	java/lang/Throwable
    //   4070	4137	4140	java/lang/Throwable
    //   4107	4174	4177	java/lang/Throwable
    //   4144	4211	4214	java/lang/Throwable
    //   4181	4248	4251	java/lang/Throwable
    //   4218	4285	4288	java/lang/Throwable
    //   4255	4322	4325	java/lang/Throwable
    //   4292	4359	4362	java/lang/Throwable
    //   4329	4396	4399	java/lang/Throwable
    //   4366	4433	4436	java/lang/Throwable
    //   4403	4470	4473	java/lang/Throwable
    //   4440	4507	4510	java/lang/Throwable
    //   4477	4544	4547	java/lang/Throwable
    //   4514	4581	4584	java/lang/Throwable
    //   4551	4618	4621	java/lang/Throwable
    //   4588	4655	4658	java/lang/Throwable
    //   4625	4692	4695	java/lang/Throwable
    //   4662	4725	4728	java/lang/Throwable
    //   4791	4805	4805	java/lang/Throwable
    //   4816	4829	4832	java/lang/Throwable
    //   4821	4844	4847	java/lang/Throwable
    //   4836	4862	4865	java/lang/Throwable
    //   4851	4892	4895	java/lang/Throwable
    //   4958	4985	4988	java/lang/Throwable
    //   4975	5006	5009	java/lang/Throwable
    //   4992	5036	5039	java/lang/Throwable
    //   5013	5047	5047	java/lang/Throwable
    //   5058	5074	5077	java/lang/Throwable
    //   5174	5188	5188	java/lang/Throwable
    //   5199	5212	5215	java/lang/Throwable
    //   5204	5227	5230	java/lang/Throwable
    //   5219	5245	5248	java/lang/Throwable
    //   5234	5275	5278	java/lang/Throwable
    //   5341	5368	5371	java/lang/Throwable
    //   5358	5386	5389	java/lang/Throwable
    //   5375	5416	5419	java/lang/Throwable
    //   5393	5427	5427	java/lang/Throwable
    //   5450	5461	5464	java/lang/Throwable
    //   5516	5530	5530	java/lang/Throwable
    //   5541	5554	5557	java/lang/Throwable
    //   5546	5569	5572	java/lang/Throwable
    //   5561	5587	5590	java/lang/Throwable
    //   5576	5617	5620	java/lang/Throwable
    //   5683	5710	5713	java/lang/Throwable
    //   5700	5728	5731	java/lang/Throwable
    //   5717	5758	5761	java/lang/Throwable
    //   5735	5769	5769	java/lang/Throwable
    //   5792	5803	5806	java/lang/Throwable
    //   5818	6552	8018	java/lang/Throwable
    //   5908	5922	5922	java/lang/Throwable
    //   5933	5946	5949	java/lang/Throwable
    //   5938	5961	5964	java/lang/Throwable
    //   5953	5979	5982	java/lang/Throwable
    //   5968	6009	6012	java/lang/Throwable
    //   6075	6102	6105	java/lang/Throwable
    //   6092	6120	6123	java/lang/Throwable
    //   6109	6150	6153	java/lang/Throwable
    //   6127	6161	6161	java/lang/Throwable
    //   6184	6195	6198	java/lang/Throwable
    //   6251	6265	6265	java/lang/Throwable
    //   6276	6289	6292	java/lang/Throwable
    //   6281	6304	6307	java/lang/Throwable
    //   6296	6322	6325	java/lang/Throwable
    //   6311	6352	6355	java/lang/Throwable
    //   6418	6445	6448	java/lang/Throwable
    //   6435	6463	6466	java/lang/Throwable
    //   6452	6493	6496	java/lang/Throwable
    //   6470	6504	6504	java/lang/Throwable
    //   6527	6538	6541	java/lang/Throwable
    //   6553	7287	8018	java/lang/Throwable
    //   6643	6657	6657	java/lang/Throwable
    //   6668	6681	6684	java/lang/Throwable
    //   6673	6696	6699	java/lang/Throwable
    //   6688	6714	6717	java/lang/Throwable
    //   6703	6744	6747	java/lang/Throwable
    //   6810	6837	6840	java/lang/Throwable
    //   6827	6855	6858	java/lang/Throwable
    //   6844	6885	6888	java/lang/Throwable
    //   6862	6896	6896	java/lang/Throwable
    //   6919	6930	6933	java/lang/Throwable
    //   6986	7000	7000	java/lang/Throwable
    //   7011	7024	7027	java/lang/Throwable
    //   7016	7039	7042	java/lang/Throwable
    //   7031	7057	7060	java/lang/Throwable
    //   7046	7087	7090	java/lang/Throwable
    //   7153	7180	7183	java/lang/Throwable
    //   7170	7198	7201	java/lang/Throwable
    //   7187	7228	7231	java/lang/Throwable
    //   7205	7239	7239	java/lang/Throwable
    //   7262	7273	7276	java/lang/Throwable
    //   7288	8017	8018	java/lang/Throwable
    //   7378	7392	7392	java/lang/Throwable
    //   7403	7416	7419	java/lang/Throwable
    //   7408	7431	7434	java/lang/Throwable
    //   7423	7449	7452	java/lang/Throwable
    //   7438	7479	7482	java/lang/Throwable
    //   7545	7572	7575	java/lang/Throwable
    //   7562	7590	7593	java/lang/Throwable
    //   7579	7620	7623	java/lang/Throwable
    //   7597	7631	7631	java/lang/Throwable
    //   7654	7665	7668	java/lang/Throwable
    //   7721	7735	7735	java/lang/Throwable
    //   7746	7759	7762	java/lang/Throwable
    //   7751	7774	7777	java/lang/Throwable
    //   7766	7792	7795	java/lang/Throwable
    //   7781	7822	7825	java/lang/Throwable
    //   7888	7915	7918	java/lang/Throwable
    //   7905	7933	7936	java/lang/Throwable
    //   7922	7963	7966	java/lang/Throwable
    //   7940	7974	7974	java/lang/Throwable
    //   7997	8008	8011	java/lang/Throwable
  }
  
  static void Zc(Object[] paramArrayOfObject, Object paramObject) throws Throwable {}
  
  static void Zz(Object paramObject) {
    Zsx6.ZJ = a(18625, 17092);
    Zsx6.ZN = new BigInteger(a(18632, -2811));
    boolean bool = Zt2e.ZN();
    try {
      try {
        if (Zgr4.Zi.charAt(Math.abs(((BigInteger)Zl4v.ZT).intValue() % 32)) > Zly7.ZC.charAt(Math.abs(((BigInteger)Zsmn.Zq).intValue() % 32))) {
          try {
            Zx_u.ZC(Class.forName(a(18645, -5550)));
            if (!bool)
              Zs5y.ZX(Class.forName(a(18651, 5838))); 
          } catch (Throwable throwable) {
            throw a(null);
          } 
          return;
        } 
      } catch (Throwable throwable) {
        throw a(null);
      } 
      Zs5y.ZX(Class.forName(a(18651, 5838)));
    } catch (Throwable throwable) {}
  }
  
  static {
    // Byte code:
    //   0: bipush #28
    //   2: anewarray java/lang/String
    //   5: astore #5
    //   7: iconst_0
    //   8: istore_3
    //   9: ldc 's\\th<~?? nb7\\t"*j\J0OM9 uP~[\\n\\fh:R(F[\\t/j3<HxW;sI\\t$XW b\\t7Z\\tJMiQO#3ACV!\\n{>{Z:&y ZZE3?HU)RY4tv#\\t't_VmfcC\\t[8\\t9T\\tE\\tOydr\\tV:ZX?\\t3iQ\y\\b{p~\\tI:x\\tMz?\\t8\\n}\\tSCswmX??\\tn]$'
    //   11: dup
    //   12: astore_2
    //   13: invokevirtual length : ()I
    //   16: istore #4
    //   18: iconst_4
    //   19: istore_1
    //   20: iconst_m1
    //   21: istore_0
    //   22: bipush #24
    //   24: iinc #0, 1
    //   27: aload_2
    //   28: iload_0
    //   29: dup
    //   30: iload_1
    //   31: iadd
    //   32: invokevirtual substring : (II)Ljava/lang/String;
    //   35: iconst_m1
    //   36: goto -> 142
    //   39: aload #5
    //   41: swap
    //   42: iload_3
    //   43: iinc #3, 1
    //   46: swap
    //   47: aastore
    //   48: iload_0
    //   49: iload_1
    //   50: iadd
    //   51: dup
    //   52: istore_0
    //   53: iload #4
    //   55: if_icmpge -> 67
    //   58: aload_2
    //   59: iload_0
    //   60: invokevirtual charAt : (I)C
    //   63: istore_1
    //   64: goto -> 22
    //   67: ldc '>aO\\bvd'
    //   69: dup
    //   70: astore_2
    //   71: invokevirtual length : ()I
    //   74: istore #4
    //   76: bipush #9
    //   78: istore_1
    //   79: iconst_m1
    //   80: istore_0
    //   81: bipush #90
    //   83: iinc #0, 1
    //   86: aload_2
    //   87: iload_0
    //   88: dup
    //   89: iload_1
    //   90: iadd
    //   91: invokevirtual substring : (II)Ljava/lang/String;
    //   94: iconst_0
    //   95: goto -> 142
    //   98: aload #5
    //   100: swap
    //   101: iload_3
    //   102: iinc #3, 1
    //   105: swap
    //   106: aastore
    //   107: iload_0
    //   108: iload_1
    //   109: iadd
    //   110: dup
    //   111: istore_0
    //   112: iload #4
    //   114: if_icmpge -> 126
    //   117: aload_2
    //   118: iload_0
    //   119: invokevirtual charAt : (I)C
    //   122: istore_1
    //   123: goto -> 81
    //   126: aload #5
    //   128: putstatic burp/Zl1n.a : [Ljava/lang/String;
    //   131: bipush #28
    //   133: anewarray java/lang/String
    //   136: putstatic burp/Zl1n.b : [Ljava/lang/String;
    //   139: goto -> 300
    //   142: dup_x2
    //   143: pop
    //   144: invokevirtual toCharArray : ()[C
    //   147: dup_x1
    //   148: arraylength
    //   149: dup_x2
    //   150: pop
    //   151: iconst_0
    //   152: istore #6
    //   154: dup2_x1
    //   155: pop2
    //   156: dup_x2
    //   157: iconst_1
    //   158: if_icmpgt -> 259
    //   161: dup2
    //   162: swap
    //   163: iload #6
    //   165: dup2_x1
    //   166: caload
    //   167: swap
    //   168: iload #6
    //   170: bipush #7
    //   172: irem
    //   173: tableswitch default -> 241, 0 -> 212, 1 -> 217, 2 -> 222, 3 -> 227, 4 -> 232, 5 -> 236
    //   212: bipush #94
    //   214: goto -> 243
    //   217: bipush #33
    //   219: goto -> 243
    //   222: bipush #28
    //   224: goto -> 243
    //   227: bipush #72
    //   229: goto -> 243
    //   232: iconst_5
    //   233: goto -> 243
    //   236: bipush #29
    //   238: goto -> 243
    //   241: bipush #77
    //   243: ixor
    //   244: ixor
    //   245: i2c
    //   246: castore
    //   247: iinc #6, 1
    //   250: dup
    //   251: ifne -> 259
    //   254: dup2
    //   255: dup_x1
    //   256: goto -> 165
    //   259: dup2_x1
    //   260: pop2
    //   261: dup_x2
    //   262: iload #6
    //   264: if_icmpgt -> 161
    //   267: pop
    //   268: new java/lang/String
    //   271: dup_x1
    //   272: swap
    //   273: invokespecial <init> : ([C)V
    //   276: invokevirtual intern : ()Ljava/lang/String;
    //   279: swap
    //   280: pop
    //   281: swap
    //   282: tableswitch default -> 39, 0 -> 98
    //   300: sipush #18630
    //   303: sipush #11933
    //   306: invokestatic a : (II)Ljava/lang/String;
    //   309: putstatic burp/Zl1n.ZZ : Ljava/lang/String;
    //   312: new java/math/BigInteger
    //   315: dup
    //   316: bipush #32
    //   318: newarray byte
    //   320: dup
    //   321: iconst_0
    //   322: bipush #58
    //   324: bastore
    //   325: dup
    //   326: iconst_1
    //   327: bipush #45
    //   329: bastore
    //   330: dup
    //   331: iconst_2
    //   332: bipush #9
    //   334: bastore
    //   335: dup
    //   336: iconst_3
    //   337: bipush #57
    //   339: bastore
    //   340: dup
    //   341: iconst_4
    //   342: bipush #-52
    //   344: bastore
    //   345: dup
    //   346: iconst_5
    //   347: bipush #54
    //   349: bastore
    //   350: dup
    //   351: bipush #6
    //   353: bipush #-99
    //   355: bastore
    //   356: dup
    //   357: bipush #7
    //   359: bipush #66
    //   361: bastore
    //   362: dup
    //   363: bipush #8
    //   365: bipush #-38
    //   367: bastore
    //   368: dup
    //   369: bipush #9
    //   371: bipush #32
    //   373: bastore
    //   374: dup
    //   375: bipush #10
    //   377: bipush #25
    //   379: bastore
    //   380: dup
    //   381: bipush #11
    //   383: bipush #-15
    //   385: bastore
    //   386: dup
    //   387: bipush #12
    //   389: bipush #-104
    //   391: bastore
    //   392: dup
    //   393: bipush #13
    //   395: bipush #110
    //   397: bastore
    //   398: dup
    //   399: bipush #14
    //   401: bipush #122
    //   403: bastore
    //   404: dup
    //   405: bipush #15
    //   407: bipush #75
    //   409: bastore
    //   410: dup
    //   411: bipush #16
    //   413: bipush #9
    //   415: bastore
    //   416: dup
    //   417: bipush #17
    //   419: bipush #-101
    //   421: bastore
    //   422: dup
    //   423: bipush #18
    //   425: bipush #45
    //   427: bastore
    //   428: dup
    //   429: bipush #19
    //   431: bipush #-24
    //   433: bastore
    //   434: dup
    //   435: bipush #20
    //   437: bipush #6
    //   439: bastore
    //   440: dup
    //   441: bipush #21
    //   443: bipush #96
    //   445: bastore
    //   446: dup
    //   447: bipush #22
    //   449: bipush #-116
    //   451: bastore
    //   452: dup
    //   453: bipush #23
    //   455: bipush #107
    //   457: bastore
    //   458: dup
    //   459: bipush #24
    //   461: bipush #73
    //   463: bastore
    //   464: dup
    //   465: bipush #25
    //   467: iconst_1
    //   468: bastore
    //   469: dup
    //   470: bipush #26
    //   472: bipush #-92
    //   474: bastore
    //   475: dup
    //   476: bipush #27
    //   478: bipush #-83
    //   480: bastore
    //   481: dup
    //   482: bipush #28
    //   484: bipush #-40
    //   486: bastore
    //   487: dup
    //   488: bipush #29
    //   490: bipush #79
    //   492: bastore
    //   493: dup
    //   494: bipush #30
    //   496: bipush #35
    //   498: bastore
    //   499: dup
    //   500: bipush #31
    //   502: bipush #-93
    //   504: bastore
    //   505: invokespecial <init> : ([B)V
    //   508: putstatic burp/Zl1n.ZM : Ljava/lang/Object;
    //   511: return
  }
  
  private static Throwable a(Throwable paramThrowable) {
    return paramThrowable;
  }
  
  private static String a(int paramInt1, int paramInt2) {
    int i = (paramInt1 ^ 0x48C2) & 0xFFFF;
    if (b[i] == null) {
      char[] arrayOfChar = a[i].toCharArray();
      switch (arrayOfChar[0] & 0xFF) {
        case 0:
        
        case 1:
        
        case 2:
        
        case 3:
        
        case 4:
        
        case 5:
        
        case 6:
        
        case 7:
        
        case 8:
        
        case 9:
        
        case 10:
        
        case 11:
        
        case 12:
        
        case 13:
        
        case 14:
        
        case 15:
        
        case 16:
        
        case 17:
        
        case 18:
        
        case 19:
        
        case 20:
        
        case 21:
        
        case 22:
        
        case 23:
        
        case 24:
        
        case 25:
        
        case 26:
        
        case 27:
        
        case 28:
        
        case 29:
        
        case 30:
        
        case 31:
        
        case 32:
        
        case 33:
        
        case 34:
        
        case 35:
        
        case 36:
        
        case 37:
        
        case 38:
        
        case 39:
        
        case 40:
        
        case 41:
        
        case 42:
        
        case 43:
        
        case 44:
        
        case 45:
        
        case 46:
        
        case 47:
        
        case 48:
        
        case 49:
        
        case 50:
        
        case 51:
        
        case 52:
        
        case 53:
        
        case 54:
        
        case 55:
        
        case 56:
        
        case 57:
        
        case 58:
        
        case 59:
        
        case 60:
        
        case 61:
        
        case 62:
        
        case 63:
        
        case 64:
        
        case 65:
        
        case 66:
        
        case 67:
        
        case 68:
        
        case 69:
        
        case 70:
        
        case 71:
        
        case 72:
        
        case 73:
        
        case 74:
        
        case 75:
        
        case 76:
        
        case 77:
        
        case 78:
        
        case 79:
        
        case 80:
        
        case 81:
        
        case 82:
        
        case 83:
        
        case 84:
        
        case 85:
        
        case 86:
        
        case 87:
        
        case 88:
        
        case 89:
        
        case 90:
        
        case 91:
        
        case 92:
        
        case 93:
        
        case 94:
        
        case 95:
        
        case 96:
        
        case 97:
        
        case 98:
        
        case 99:
        
        case 100:
        
        case 101:
        
        case 102:
        
        case 103:
        
        case 104:
        
        case 105:
        
        case 106:
        
        case 107:
        
        case 108:
        
        case 109:
        
        case 110:
        
        case 111:
        
        case 112:
        
        case 113:
        
        case 114:
        
        case 115:
        
        case 116:
        
        case 117:
        
        case 118:
        
        case 119:
        
        case 120:
        
        case 121:
        
        case 122:
        
        case 123:
        
        case 124:
        
        case 125:
        
        case 126:
        
        case 127:
        
        case 128:
        
        case 129:
        
        case 130:
        
        case 131:
        
        case 132:
        
        case 133:
        
        case 134:
        
        case 135:
        
        case 136:
        
        case 137:
        
        case 138:
        
        case 139:
        
        case 140:
        
        case 141:
        
        case 142:
        
        case 143:
        
        case 144:
        
        case 145:
        
        case 146:
        
        case 147:
        
        case 148:
        
        case 149:
        
        case 150:
        
        case 151:
        
        case 152:
        
        case 153:
        
        case 154:
        
        case 155:
        
        case 156:
        
        case 157:
        
        case 158:
        
        case 159:
        
        case 160:
        
        case 161:
        
        case 162:
        
        case 163:
        
        case 164:
        
        case 165:
        
        case 166:
        
        case 167:
        
        case 168:
        
        case 169:
        
        case 170:
        
        case 171:
        
        case 172:
        
        case 173:
        
        case 174:
        
        case 175:
        
        case 176:
        
        case 177:
        
        case 178:
        
        case 179:
        
        case 180:
        
        case 181:
        
        case 182:
        
        case 183:
        
        case 184:
        
        case 185:
        
        case 186:
        
        case 187:
        
        case 188:
        
        case 189:
        
        case 190:
        
        case 191:
        
        case 192:
        
        case 193:
        
        case 194:
        
        case 195:
        
        case 196:
        
        case 197:
        
        case 198:
        
        case 199:
        
        case 200:
        
        case 201:
        
        case 202:
        
        case 203:
        
        case 204:
        
        case 205:
        
        case 206:
        
        case 207:
        
        case 208:
        
        case 209:
        
        case 210:
        
        case 211:
        
        case 212:
        
        case 213:
        
        case 214:
        
        case 215:
        
        case 216:
        
        case 217:
        
        case 218:
        
        case 219:
        
        case 220:
        
        case 221:
        
        case 222:
        
        case 223:
        
        case 224:
        
        case 225:
        
        case 226:
        
        case 227:
        
        case 228:
        
        case 229:
        
        case 230:
        
        case 231:
        
        case 232:
        
        case 233:
        
        case 234:
        
        case 235:
        
        case 236:
        
        case 237:
        
        case 238:
        
        case 239:
        
        case 240:
        
        case 241:
        
        case 242:
        
        case 243:
        
        case 244:
        
        case 245:
        
        case 246:
        
        case 247:
        
        case 248:
        
        case 249:
        
        case 250:
        
        case 251:
        
        case 252:
        
        case 253:
        
        case 254:
        
        default:
          break;
      } 
      char c = '';
      int j = (paramInt2 & 0xFF) - c;
      if (j < 0)
        j += 256; 
      int k = ((paramInt2 & 0xFFFF) >>> 8) - c;
      if (k < 0)
        k += 256; 
      for (byte b = 0; b < arrayOfChar.length; b++) {
        int m = b % 2;
        if (m == 0) {
          arrayOfChar[b] = (char)(arrayOfChar[b] ^ j);
          j = ((j >>> 3 | j << 5) ^ arrayOfChar[b]) & 0xFF;
        } else {
          arrayOfChar[b] = (char)(arrayOfChar[b] ^ k);
          k = ((k >>> 3 | k << 5) ^ arrayOfChar[b]) & 0xFF;
        } 
      } 
      b[i] = (new String(arrayOfChar)).intern();
    } 
    return b[i];
  }
}


/* Location:              C:\Program Files\BurpSuitePro\burpsuite_pro.jar!\burp\Zl1n.class
 * Java compiler version: 21 (65.0)
 * JD-Core Version:       1.1.3
 */