package burp;

import java.math.BigInteger;

class Zl39 extends ClassLoader {
  static String ZI;
  
  static Object ZA;
  
  private static final String[] a;
  
  private static final String[] b;
  
  static boolean ZC(Object[] paramArrayOfObject, Object paramObject) throws Throwable {
    // Byte code:
    //   0: invokestatic ZK : ()Z
    //   3: istore_2
    //   4: new java/lang/StringBuilder
    //   7: dup
    //   8: invokespecial <init> : ()V
    //   11: astore_3
    //   12: iconst_0
    //   13: istore #4
    //   15: iload #4
    //   17: bipush #32
    //   19: if_icmpge -> 1355
    //   22: iload #4
    //   24: tableswitch default -> 1348, 0 -> 168, 1 -> 205, 2 -> 242, 3 -> 279, 4 -> 316, 5 -> 353, 6 -> 390, 7 -> 427, 8 -> 464, 9 -> 501, 10 -> 538, 11 -> 575, 12 -> 612, 13 -> 649, 14 -> 686, 15 -> 723, 16 -> 760, 17 -> 797, 18 -> 834, 19 -> 871, 20 -> 908, 21 -> 945, 22 -> 982, 23 -> 1019, 24 -> 1056, 25 -> 1093, 26 -> 1130, 27 -> 1167, 28 -> 1204, 29 -> 1241, 30 -> 1278, 31 -> 1315
    //   168: aload_3
    //   169: getstatic burp/Ztye.ZR : Ljava/lang/String;
    //   172: getstatic burp/Zram.ZF : Ljava/lang/Object;
    //   175: checkcast java/math/BigInteger
    //   178: invokevirtual intValue : ()I
    //   181: bipush #32
    //   183: irem
    //   184: invokestatic abs : (I)I
    //   187: invokevirtual charAt : (I)C
    //   190: invokevirtual append : (C)Ljava/lang/StringBuilder;
    //   193: pop
    //   194: iload_2
    //   195: ifeq -> 1348
    //   198: goto -> 205
    //   201: invokestatic a : (Ljava/lang/Throwable;)Ljava/lang/Throwable;
    //   204: athrow
    //   205: aload_3
    //   206: getstatic burp/Zlpj.Zj : Ljava/lang/String;
    //   209: getstatic burp/Zzo5.Zf : Ljava/lang/Object;
    //   212: checkcast java/math/BigInteger
    //   215: invokevirtual intValue : ()I
    //   218: bipush #32
    //   220: irem
    //   221: invokestatic abs : (I)I
    //   224: invokevirtual charAt : (I)C
    //   227: invokevirtual append : (C)Ljava/lang/StringBuilder;
    //   230: pop
    //   231: iload_2
    //   232: ifeq -> 1348
    //   235: goto -> 242
    //   238: invokestatic a : (Ljava/lang/Throwable;)Ljava/lang/Throwable;
    //   241: athrow
    //   242: aload_3
    //   243: getstatic burp/Zrcy.Zq : Ljava/lang/String;
    //   246: getstatic burp/Zl06.Zw : Ljava/lang/Object;
    //   249: checkcast java/math/BigInteger
    //   252: invokevirtual intValue : ()I
    //   255: bipush #32
    //   257: irem
    //   258: invokestatic abs : (I)I
    //   261: invokevirtual charAt : (I)C
    //   264: invokevirtual append : (C)Ljava/lang/StringBuilder;
    //   267: pop
    //   268: iload_2
    //   269: ifeq -> 1348
    //   272: goto -> 279
    //   275: invokestatic a : (Ljava/lang/Throwable;)Ljava/lang/Throwable;
    //   278: athrow
    //   279: aload_3
    //   280: getstatic burp/Zzr5.Zg : Ljava/lang/String;
    //   283: getstatic burp/Zrjg.ZG : Ljava/lang/Object;
    //   286: checkcast java/math/BigInteger
    //   289: invokevirtual intValue : ()I
    //   292: bipush #32
    //   294: irem
    //   295: invokestatic abs : (I)I
    //   298: invokevirtual charAt : (I)C
    //   301: invokevirtual append : (C)Ljava/lang/StringBuilder;
    //   304: pop
    //   305: iload_2
    //   306: ifeq -> 1348
    //   309: goto -> 316
    //   312: invokestatic a : (Ljava/lang/Throwable;)Ljava/lang/Throwable;
    //   315: athrow
    //   316: aload_3
    //   317: getstatic burp/Zl39.ZI : Ljava/lang/String;
    //   320: getstatic burp/Zrcy.Zr : Ljava/lang/Object;
    //   323: checkcast java/math/BigInteger
    //   326: invokevirtual intValue : ()I
    //   329: bipush #32
    //   331: irem
    //   332: invokestatic abs : (I)I
    //   335: invokevirtual charAt : (I)C
    //   338: invokevirtual append : (C)Ljava/lang/StringBuilder;
    //   341: pop
    //   342: iload_2
    //   343: ifeq -> 1348
    //   346: goto -> 353
    //   349: invokestatic a : (Ljava/lang/Throwable;)Ljava/lang/Throwable;
    //   352: athrow
    //   353: aload_3
    //   354: getstatic burp/Zg4d.ZE : Ljava/lang/String;
    //   357: getstatic burp/Ztye.ZK : Ljava/lang/Object;
    //   360: checkcast java/math/BigInteger
    //   363: invokevirtual intValue : ()I
    //   366: bipush #32
    //   368: irem
    //   369: invokestatic abs : (I)I
    //   372: invokevirtual charAt : (I)C
    //   375: invokevirtual append : (C)Ljava/lang/StringBuilder;
    //   378: pop
    //   379: iload_2
    //   380: ifeq -> 1348
    //   383: goto -> 390
    //   386: invokestatic a : (Ljava/lang/Throwable;)Ljava/lang/Throwable;
    //   389: athrow
    //   390: aload_3
    //   391: getstatic burp/Zs0_.ZH : Ljava/lang/String;
    //   394: getstatic burp/Zqp.ZA : Ljava/lang/Object;
    //   397: checkcast java/math/BigInteger
    //   400: invokevirtual intValue : ()I
    //   403: bipush #32
    //   405: irem
    //   406: invokestatic abs : (I)I
    //   409: invokevirtual charAt : (I)C
    //   412: invokevirtual append : (C)Ljava/lang/StringBuilder;
    //   415: pop
    //   416: iload_2
    //   417: ifeq -> 1348
    //   420: goto -> 427
    //   423: invokestatic a : (Ljava/lang/Throwable;)Ljava/lang/Throwable;
    //   426: athrow
    //   427: aload_3
    //   428: getstatic burp/Ztdd.ZA : Ljava/lang/String;
    //   431: getstatic burp/Zsf7.Zg : Ljava/lang/Object;
    //   434: checkcast java/math/BigInteger
    //   437: invokevirtual intValue : ()I
    //   440: bipush #32
    //   442: irem
    //   443: invokestatic abs : (I)I
    //   446: invokevirtual charAt : (I)C
    //   449: invokevirtual append : (C)Ljava/lang/StringBuilder;
    //   452: pop
    //   453: iload_2
    //   454: ifeq -> 1348
    //   457: goto -> 464
    //   460: invokestatic a : (Ljava/lang/Throwable;)Ljava/lang/Throwable;
    //   463: athrow
    //   464: aload_3
    //   465: getstatic burp/Zsbt.ZX : Ljava/lang/String;
    //   468: getstatic burp/Zxjv.ZY : Ljava/lang/Object;
    //   471: checkcast java/math/BigInteger
    //   474: invokevirtual intValue : ()I
    //   477: bipush #32
    //   479: irem
    //   480: invokestatic abs : (I)I
    //   483: invokevirtual charAt : (I)C
    //   486: invokevirtual append : (C)Ljava/lang/StringBuilder;
    //   489: pop
    //   490: iload_2
    //   491: ifeq -> 1348
    //   494: goto -> 501
    //   497: invokestatic a : (Ljava/lang/Throwable;)Ljava/lang/Throwable;
    //   500: athrow
    //   501: aload_3
    //   502: getstatic burp/Zmyg.ZE : Ljava/lang/String;
    //   505: getstatic burp/Zeb7.ZJ : Ljava/lang/Object;
    //   508: checkcast java/math/BigInteger
    //   511: invokevirtual intValue : ()I
    //   514: bipush #32
    //   516: irem
    //   517: invokestatic abs : (I)I
    //   520: invokevirtual charAt : (I)C
    //   523: invokevirtual append : (C)Ljava/lang/StringBuilder;
    //   526: pop
    //   527: iload_2
    //   528: ifeq -> 1348
    //   531: goto -> 538
    //   534: invokestatic a : (Ljava/lang/Throwable;)Ljava/lang/Throwable;
    //   537: athrow
    //   538: aload_3
    //   539: getstatic burp/Zzc_.Zg : Ljava/lang/String;
    //   542: getstatic burp/Zxzz.ZM : Ljava/lang/Object;
    //   545: checkcast java/math/BigInteger
    //   548: invokevirtual intValue : ()I
    //   551: bipush #32
    //   553: irem
    //   554: invokestatic abs : (I)I
    //   557: invokevirtual charAt : (I)C
    //   560: invokevirtual append : (C)Ljava/lang/StringBuilder;
    //   563: pop
    //   564: iload_2
    //   565: ifeq -> 1348
    //   568: goto -> 575
    //   571: invokestatic a : (Ljava/lang/Throwable;)Ljava/lang/Throwable;
    //   574: athrow
    //   575: aload_3
    //   576: getstatic burp/Zkll.ZX : Ljava/lang/String;
    //   579: getstatic burp/Zsbt.Zl : Ljava/lang/Object;
    //   582: checkcast java/math/BigInteger
    //   585: invokevirtual intValue : ()I
    //   588: bipush #32
    //   590: irem
    //   591: invokestatic abs : (I)I
    //   594: invokevirtual charAt : (I)C
    //   597: invokevirtual append : (C)Ljava/lang/StringBuilder;
    //   600: pop
    //   601: iload_2
    //   602: ifeq -> 1348
    //   605: goto -> 612
    //   608: invokestatic a : (Ljava/lang/Throwable;)Ljava/lang/Throwable;
    //   611: athrow
    //   612: aload_3
    //   613: getstatic burp/Zxe.ZD : Ljava/lang/String;
    //   616: getstatic burp/Ztcv.ZY : Ljava/lang/Object;
    //   619: checkcast java/math/BigInteger
    //   622: invokevirtual intValue : ()I
    //   625: bipush #32
    //   627: irem
    //   628: invokestatic abs : (I)I
    //   631: invokevirtual charAt : (I)C
    //   634: invokevirtual append : (C)Ljava/lang/StringBuilder;
    //   637: pop
    //   638: iload_2
    //   639: ifeq -> 1348
    //   642: goto -> 649
    //   645: invokestatic a : (Ljava/lang/Throwable;)Ljava/lang/Throwable;
    //   648: athrow
    //   649: aload_3
    //   650: getstatic burp/Zzym.Zj : Ljava/lang/String;
    //   653: getstatic burp/Zeb7.ZJ : Ljava/lang/Object;
    //   656: checkcast java/math/BigInteger
    //   659: invokevirtual intValue : ()I
    //   662: bipush #32
    //   664: irem
    //   665: invokestatic abs : (I)I
    //   668: invokevirtual charAt : (I)C
    //   671: invokevirtual append : (C)Ljava/lang/StringBuilder;
    //   674: pop
    //   675: iload_2
    //   676: ifeq -> 1348
    //   679: goto -> 686
    //   682: invokestatic a : (Ljava/lang/Throwable;)Ljava/lang/Throwable;
    //   685: athrow
    //   686: aload_3
    //   687: getstatic burp/Zgva.ZV : Ljava/lang/String;
    //   690: getstatic burp/Zgqi.Zp : Ljava/lang/Object;
    //   693: checkcast java/math/BigInteger
    //   696: invokevirtual intValue : ()I
    //   699: bipush #32
    //   701: irem
    //   702: invokestatic abs : (I)I
    //   705: invokevirtual charAt : (I)C
    //   708: invokevirtual append : (C)Ljava/lang/StringBuilder;
    //   711: pop
    //   712: iload_2
    //   713: ifeq -> 1348
    //   716: goto -> 723
    //   719: invokestatic a : (Ljava/lang/Throwable;)Ljava/lang/Throwable;
    //   722: athrow
    //   723: aload_3
    //   724: getstatic burp/Zsj5.Zn : Ljava/lang/String;
    //   727: getstatic burp/Zxzz.ZM : Ljava/lang/Object;
    //   730: checkcast java/math/BigInteger
    //   733: invokevirtual intValue : ()I
    //   736: bipush #32
    //   738: irem
    //   739: invokestatic abs : (I)I
    //   742: invokevirtual charAt : (I)C
    //   745: invokevirtual append : (C)Ljava/lang/StringBuilder;
    //   748: pop
    //   749: iload_2
    //   750: ifeq -> 1348
    //   753: goto -> 760
    //   756: invokestatic a : (Ljava/lang/Throwable;)Ljava/lang/Throwable;
    //   759: athrow
    //   760: aload_3
    //   761: getstatic burp/Ze_t.ZZ : Ljava/lang/String;
    //   764: getstatic burp/Zmr7.ZO : Ljava/lang/Object;
    //   767: checkcast java/math/BigInteger
    //   770: invokevirtual intValue : ()I
    //   773: bipush #32
    //   775: irem
    //   776: invokestatic abs : (I)I
    //   779: invokevirtual charAt : (I)C
    //   782: invokevirtual append : (C)Ljava/lang/StringBuilder;
    //   785: pop
    //   786: iload_2
    //   787: ifeq -> 1348
    //   790: goto -> 797
    //   793: invokestatic a : (Ljava/lang/Throwable;)Ljava/lang/Throwable;
    //   796: athrow
    //   797: aload_3
    //   798: getstatic burp/Zg4w.ZC : Ljava/lang/String;
    //   801: getstatic burp/Zgqi.Zp : Ljava/lang/Object;
    //   804: checkcast java/math/BigInteger
    //   807: invokevirtual intValue : ()I
    //   810: bipush #32
    //   812: irem
    //   813: invokestatic abs : (I)I
    //   816: invokevirtual charAt : (I)C
    //   819: invokevirtual append : (C)Ljava/lang/StringBuilder;
    //   822: pop
    //   823: iload_2
    //   824: ifeq -> 1348
    //   827: goto -> 834
    //   830: invokestatic a : (Ljava/lang/Throwable;)Ljava/lang/Throwable;
    //   833: athrow
    //   834: aload_3
    //   835: getstatic burp/Zl06.ZL : Ljava/lang/String;
    //   838: getstatic burp/Zm4i.Zr : Ljava/lang/Object;
    //   841: checkcast java/math/BigInteger
    //   844: invokevirtual intValue : ()I
    //   847: bipush #32
    //   849: irem
    //   850: invokestatic abs : (I)I
    //   853: invokevirtual charAt : (I)C
    //   856: invokevirtual append : (C)Ljava/lang/StringBuilder;
    //   859: pop
    //   860: iload_2
    //   861: ifeq -> 1348
    //   864: goto -> 871
    //   867: invokestatic a : (Ljava/lang/Throwable;)Ljava/lang/Throwable;
    //   870: athrow
    //   871: aload_3
    //   872: getstatic burp/Ztdd.ZA : Ljava/lang/String;
    //   875: getstatic burp/Zsf7.Zg : Ljava/lang/Object;
    //   878: checkcast java/math/BigInteger
    //   881: invokevirtual intValue : ()I
    //   884: bipush #32
    //   886: irem
    //   887: invokestatic abs : (I)I
    //   890: invokevirtual charAt : (I)C
    //   893: invokevirtual append : (C)Ljava/lang/StringBuilder;
    //   896: pop
    //   897: iload_2
    //   898: ifeq -> 1348
    //   901: goto -> 908
    //   904: invokestatic a : (Ljava/lang/Throwable;)Ljava/lang/Throwable;
    //   907: athrow
    //   908: aload_3
    //   909: getstatic burp/Zstb.Zd : Ljava/lang/String;
    //   912: getstatic burp/Zzmu.Zy : Ljava/lang/Object;
    //   915: checkcast java/math/BigInteger
    //   918: invokevirtual intValue : ()I
    //   921: bipush #32
    //   923: irem
    //   924: invokestatic abs : (I)I
    //   927: invokevirtual charAt : (I)C
    //   930: invokevirtual append : (C)Ljava/lang/StringBuilder;
    //   933: pop
    //   934: iload_2
    //   935: ifeq -> 1348
    //   938: goto -> 945
    //   941: invokestatic a : (Ljava/lang/Throwable;)Ljava/lang/Throwable;
    //   944: athrow
    //   945: aload_3
    //   946: getstatic burp/Zrva.Zr : Ljava/lang/String;
    //   949: getstatic burp/Ze8i.Zq : Ljava/lang/Object;
    //   952: checkcast java/math/BigInteger
    //   955: invokevirtual intValue : ()I
    //   958: bipush #32
    //   960: irem
    //   961: invokestatic abs : (I)I
    //   964: invokevirtual charAt : (I)C
    //   967: invokevirtual append : (C)Ljava/lang/StringBuilder;
    //   970: pop
    //   971: iload_2
    //   972: ifeq -> 1348
    //   975: goto -> 982
    //   978: invokestatic a : (Ljava/lang/Throwable;)Ljava/lang/Throwable;
    //   981: athrow
    //   982: aload_3
    //   983: getstatic burp/Zlr.ZO : Ljava/lang/String;
    //   986: getstatic burp/Zstb.ZC : Ljava/lang/Object;
    //   989: checkcast java/math/BigInteger
    //   992: invokevirtual intValue : ()I
    //   995: bipush #32
    //   997: irem
    //   998: invokestatic abs : (I)I
    //   1001: invokevirtual charAt : (I)C
    //   1004: invokevirtual append : (C)Ljava/lang/StringBuilder;
    //   1007: pop
    //   1008: iload_2
    //   1009: ifeq -> 1348
    //   1012: goto -> 1019
    //   1015: invokestatic a : (Ljava/lang/Throwable;)Ljava/lang/Throwable;
    //   1018: athrow
    //   1019: aload_3
    //   1020: getstatic burp/Ze8i.ZM : Ljava/lang/String;
    //   1023: getstatic burp/Zg_5.ZA : Ljava/lang/Object;
    //   1026: checkcast java/math/BigInteger
    //   1029: invokevirtual intValue : ()I
    //   1032: bipush #32
    //   1034: irem
    //   1035: invokestatic abs : (I)I
    //   1038: invokevirtual charAt : (I)C
    //   1041: invokevirtual append : (C)Ljava/lang/StringBuilder;
    //   1044: pop
    //   1045: iload_2
    //   1046: ifeq -> 1348
    //   1049: goto -> 1056
    //   1052: invokestatic a : (Ljava/lang/Throwable;)Ljava/lang/Throwable;
    //   1055: athrow
    //   1056: aload_3
    //   1057: getstatic burp/Zz0w.ZO : Ljava/lang/String;
    //   1060: getstatic burp/Zzyr.Za : Ljava/lang/Object;
    //   1063: checkcast java/math/BigInteger
    //   1066: invokevirtual intValue : ()I
    //   1069: bipush #32
    //   1071: irem
    //   1072: invokestatic abs : (I)I
    //   1075: invokevirtual charAt : (I)C
    //   1078: invokevirtual append : (C)Ljava/lang/StringBuilder;
    //   1081: pop
    //   1082: iload_2
    //   1083: ifeq -> 1348
    //   1086: goto -> 1093
    //   1089: invokestatic a : (Ljava/lang/Throwable;)Ljava/lang/Throwable;
    //   1092: athrow
    //   1093: aload_3
    //   1094: getstatic burp/Zs34.Zq : Ljava/lang/String;
    //   1097: getstatic burp/Zzmw.ZS : Ljava/lang/Object;
    //   1100: checkcast java/math/BigInteger
    //   1103: invokevirtual intValue : ()I
    //   1106: bipush #32
    //   1108: irem
    //   1109: invokestatic abs : (I)I
    //   1112: invokevirtual charAt : (I)C
    //   1115: invokevirtual append : (C)Ljava/lang/StringBuilder;
    //   1118: pop
    //   1119: iload_2
    //   1120: ifeq -> 1348
    //   1123: goto -> 1130
    //   1126: invokestatic a : (Ljava/lang/Throwable;)Ljava/lang/Throwable;
    //   1129: athrow
    //   1130: aload_3
    //   1131: getstatic burp/Zxzz.ZT : Ljava/lang/String;
    //   1134: getstatic burp/Zeoy.Zt : Ljava/lang/Object;
    //   1137: checkcast java/math/BigInteger
    //   1140: invokevirtual intValue : ()I
    //   1143: bipush #32
    //   1145: irem
    //   1146: invokestatic abs : (I)I
    //   1149: invokevirtual charAt : (I)C
    //   1152: invokevirtual append : (C)Ljava/lang/StringBuilder;
    //   1155: pop
    //   1156: iload_2
    //   1157: ifeq -> 1348
    //   1160: goto -> 1167
    //   1163: invokestatic a : (Ljava/lang/Throwable;)Ljava/lang/Throwable;
    //   1166: athrow
    //   1167: aload_3
    //   1168: getstatic burp/Zli5.Zq : Ljava/lang/String;
    //   1171: getstatic burp/Zeuc.Zd : Ljava/lang/Object;
    //   1174: checkcast java/math/BigInteger
    //   1177: invokevirtual intValue : ()I
    //   1180: bipush #32
    //   1182: irem
    //   1183: invokestatic abs : (I)I
    //   1186: invokevirtual charAt : (I)C
    //   1189: invokevirtual append : (C)Ljava/lang/StringBuilder;
    //   1192: pop
    //   1193: iload_2
    //   1194: ifeq -> 1348
    //   1197: goto -> 1204
    //   1200: invokestatic a : (Ljava/lang/Throwable;)Ljava/lang/Throwable;
    //   1203: athrow
    //   1204: aload_3
    //   1205: getstatic burp/Zl8f.ZK : Ljava/lang/String;
    //   1208: getstatic burp/Zqp.ZA : Ljava/lang/Object;
    //   1211: checkcast java/math/BigInteger
    //   1214: invokevirtual intValue : ()I
    //   1217: bipush #32
    //   1219: irem
    //   1220: invokestatic abs : (I)I
    //   1223: invokevirtual charAt : (I)C
    //   1226: invokevirtual append : (C)Ljava/lang/StringBuilder;
    //   1229: pop
    //   1230: iload_2
    //   1231: ifeq -> 1348
    //   1234: goto -> 1241
    //   1237: invokestatic a : (Ljava/lang/Throwable;)Ljava/lang/Throwable;
    //   1240: athrow
    //   1241: aload_3
    //   1242: getstatic burp/Zs00.Zv : Ljava/lang/String;
    //   1245: getstatic burp/Ztye.ZK : Ljava/lang/Object;
    //   1248: checkcast java/math/BigInteger
    //   1251: invokevirtual intValue : ()I
    //   1254: bipush #32
    //   1256: irem
    //   1257: invokestatic abs : (I)I
    //   1260: invokevirtual charAt : (I)C
    //   1263: invokevirtual append : (C)Ljava/lang/StringBuilder;
    //   1266: pop
    //   1267: iload_2
    //   1268: ifeq -> 1348
    //   1271: goto -> 1278
    //   1274: invokestatic a : (Ljava/lang/Throwable;)Ljava/lang/Throwable;
    //   1277: athrow
    //   1278: aload_3
    //   1279: getstatic burp/Zza8.Zm : Ljava/lang/String;
    //   1282: getstatic burp/Zmhi.ZZ : Ljava/lang/Object;
    //   1285: checkcast java/math/BigInteger
    //   1288: invokevirtual intValue : ()I
    //   1291: bipush #32
    //   1293: irem
    //   1294: invokestatic abs : (I)I
    //   1297: invokevirtual charAt : (I)C
    //   1300: invokevirtual append : (C)Ljava/lang/StringBuilder;
    //   1303: pop
    //   1304: iload_2
    //   1305: ifeq -> 1348
    //   1308: goto -> 1315
    //   1311: invokestatic a : (Ljava/lang/Throwable;)Ljava/lang/Throwable;
    //   1314: athrow
    //   1315: aload_3
    //   1316: getstatic burp/Zx6d.ZP : Ljava/lang/String;
    //   1319: getstatic burp/Zs_v.Zs : Ljava/lang/Object;
    //   1322: checkcast java/math/BigInteger
    //   1325: invokevirtual intValue : ()I
    //   1328: bipush #32
    //   1330: irem
    //   1331: invokestatic abs : (I)I
    //   1334: invokevirtual charAt : (I)C
    //   1337: invokevirtual append : (C)Ljava/lang/StringBuilder;
    //   1340: pop
    //   1341: goto -> 1348
    //   1344: invokestatic a : (Ljava/lang/Throwable;)Ljava/lang/Throwable;
    //   1347: athrow
    //   1348: iinc #4, 1
    //   1351: iload_2
    //   1352: ifeq -> 15
    //   1355: aload_3
    //   1356: invokevirtual toString : ()Ljava/lang/String;
    //   1359: putstatic burp/Zl39.ZI : Ljava/lang/String;
    //   1362: getstatic burp/Zzr5.Za : Ljava/lang/Object;
    //   1365: checkcast java/math/BigInteger
    //   1368: getstatic burp/Zxzz.ZM : Ljava/lang/Object;
    //   1371: checkcast java/math/BigInteger
    //   1374: invokevirtual subtract : (Ljava/math/BigInteger;)Ljava/math/BigInteger;
    //   1377: putstatic burp/Zxn5.Zd : Ljava/lang/Object;
    //   1380: getstatic burp/Zz0w.ZF : Ljava/lang/Object;
    //   1383: checkcast java/math/BigInteger
    //   1386: invokevirtual toByteArray : ()[B
    //   1389: astore #4
    //   1391: bipush #32
    //   1393: newarray int
    //   1395: dup
    //   1396: iconst_0
    //   1397: ldc 943331329
    //   1399: iastore
    //   1400: dup
    //   1401: iconst_1
    //   1402: ldc 170788368
    //   1404: iastore
    //   1405: dup
    //   1406: iconst_2
    //   1407: ldc 1008414755
    //   1409: iastore
    //   1410: dup
    //   1411: iconst_3
    //   1412: ldc 187049985
    //   1414: iastore
    //   1415: dup
    //   1416: iconst_4
    //   1417: ldc 1010368540
    //   1419: iastore
    //   1420: dup
    //   1421: iconst_5
    //   1422: ldc 220604441
    //   1424: iastore
    //   1425: dup
    //   1426: bipush #6
    //   1428: ldc 940377620
    //   1430: iastore
    //   1431: dup
    //   1432: bipush #7
    //   1434: ldc 255209728
    //   1436: iastore
    //   1437: dup
    //   1438: bipush #8
    //   1440: ldc 689771012
    //   1442: iastore
    //   1443: dup
    //   1444: bipush #9
    //   1446: ldc 221709344
    //   1448: iastore
    //   1449: dup
    //   1450: bipush #10
    //   1452: ldc 957157408
    //   1454: iastore
    //   1455: dup
    //   1456: bipush #11
    //   1458: ldc 892536332
    //   1460: iastore
    //   1461: dup
    //   1462: bipush #12
    //   1464: ldc 722417666
    //   1466: iastore
    //   1467: dup
    //   1468: bipush #13
    //   1470: ldc 1026621720
    //   1472: iastore
    //   1473: dup
    //   1474: bipush #14
    //   1476: ldc 655302664
    //   1478: iastore
    //   1479: dup
    //   1480: bipush #15
    //   1482: ldc 890966315
    //   1484: iastore
    //   1485: dup
    //   1486: bipush #16
    //   1488: ldc 187632156
    //   1490: iastore
    //   1491: dup
    //   1492: bipush #17
    //   1494: ldc 874189824
    //   1496: iastore
    //   1497: dup
    //   1498: bipush #18
    //   1500: ldc 254150144
    //   1502: iastore
    //   1503: dup
    //   1504: bipush #19
    //   1506: ldc 924386310
    //   1508: iastore
    //   1509: dup
    //   1510: bipush #20
    //   1512: ldc 121057538
    //   1514: iastore
    //   1515: dup
    //   1516: bipush #21
    //   1518: ldc 840500228
    //   1520: iastore
    //   1521: dup
    //   1522: bipush #22
    //   1524: ldc 389160971
    //   1526: iastore
    //   1527: dup
    //   1528: bipush #23
    //   1530: ldc 907870729
    //   1532: iastore
    //   1533: dup
    //   1534: bipush #24
    //   1536: ldc 389426184
    //   1538: iastore
    //   1539: dup
    //   1540: bipush #25
    //   1542: ldc 973875457
    //   1544: iastore
    //   1545: dup
    //   1546: bipush #26
    //   1548: ldc 372376604
    //   1550: iastore
    //   1551: dup
    //   1552: bipush #27
    //   1554: ldc 707731490
    //   1556: iastore
    //   1557: dup
    //   1558: bipush #28
    //   1560: ldc 1043334948
    //   1562: iastore
    //   1563: dup
    //   1564: bipush #29
    //   1566: ldc 439222784
    //   1568: iastore
    //   1569: dup
    //   1570: bipush #30
    //   1572: ldc 876216579
    //   1574: iastore
    //   1575: dup
    //   1576: bipush #31
    //   1578: ldc 455999525
    //   1580: iastore
    //   1581: astore #6
    //   1583: bipush #8
    //   1585: aload #4
    //   1587: arraylength
    //   1588: bipush #8
    //   1590: irem
    //   1591: isub
    //   1592: istore #7
    //   1594: aload #4
    //   1596: arraylength
    //   1597: iload #7
    //   1599: iadd
    //   1600: newarray byte
    //   1602: astore #8
    //   1604: iconst_0
    //   1605: istore #9
    //   1607: iload #9
    //   1609: aload #4
    //   1611: arraylength
    //   1612: if_icmpge -> 1632
    //   1615: aload #8
    //   1617: iload #9
    //   1619: aload #4
    //   1621: iload #9
    //   1623: baload
    //   1624: bastore
    //   1625: iinc #9, 1
    //   1628: iload_2
    //   1629: ifeq -> 1607
    //   1632: aload #4
    //   1634: arraylength
    //   1635: istore #9
    //   1637: iload #9
    //   1639: aload #8
    //   1641: arraylength
    //   1642: if_icmpge -> 1660
    //   1645: aload #8
    //   1647: iload #9
    //   1649: iload #7
    //   1651: i2b
    //   1652: bastore
    //   1653: iinc #9, 1
    //   1656: iload_2
    //   1657: ifeq -> 1637
    //   1660: aload #8
    //   1662: astore #4
    //   1664: bipush #64
    //   1666: newarray int
    //   1668: dup
    //   1669: iconst_0
    //   1670: ldc 16843776
    //   1672: iastore
    //   1673: dup
    //   1674: iconst_1
    //   1675: iconst_0
    //   1676: iastore
    //   1677: dup
    //   1678: iconst_2
    //   1679: ldc 65536
    //   1681: iastore
    //   1682: dup
    //   1683: iconst_3
    //   1684: ldc 16843780
    //   1686: iastore
    //   1687: dup
    //   1688: iconst_4
    //   1689: ldc 16842756
    //   1691: iastore
    //   1692: dup
    //   1693: iconst_5
    //   1694: ldc 66564
    //   1696: iastore
    //   1697: dup
    //   1698: bipush #6
    //   1700: iconst_4
    //   1701: iastore
    //   1702: dup
    //   1703: bipush #7
    //   1705: ldc 65536
    //   1707: iastore
    //   1708: dup
    //   1709: bipush #8
    //   1711: sipush #1024
    //   1714: iastore
    //   1715: dup
    //   1716: bipush #9
    //   1718: ldc 16843776
    //   1720: iastore
    //   1721: dup
    //   1722: bipush #10
    //   1724: ldc 16843780
    //   1726: iastore
    //   1727: dup
    //   1728: bipush #11
    //   1730: sipush #1024
    //   1733: iastore
    //   1734: dup
    //   1735: bipush #12
    //   1737: ldc 16778244
    //   1739: iastore
    //   1740: dup
    //   1741: bipush #13
    //   1743: ldc 16842756
    //   1745: iastore
    //   1746: dup
    //   1747: bipush #14
    //   1749: ldc 16777216
    //   1751: iastore
    //   1752: dup
    //   1753: bipush #15
    //   1755: iconst_4
    //   1756: iastore
    //   1757: dup
    //   1758: bipush #16
    //   1760: sipush #1028
    //   1763: iastore
    //   1764: dup
    //   1765: bipush #17
    //   1767: ldc 16778240
    //   1769: iastore
    //   1770: dup
    //   1771: bipush #18
    //   1773: ldc 16778240
    //   1775: iastore
    //   1776: dup
    //   1777: bipush #19
    //   1779: ldc 66560
    //   1781: iastore
    //   1782: dup
    //   1783: bipush #20
    //   1785: ldc 66560
    //   1787: iastore
    //   1788: dup
    //   1789: bipush #21
    //   1791: ldc 16842752
    //   1793: iastore
    //   1794: dup
    //   1795: bipush #22
    //   1797: ldc 16842752
    //   1799: iastore
    //   1800: dup
    //   1801: bipush #23
    //   1803: ldc 16778244
    //   1805: iastore
    //   1806: dup
    //   1807: bipush #24
    //   1809: ldc 65540
    //   1811: iastore
    //   1812: dup
    //   1813: bipush #25
    //   1815: ldc 16777220
    //   1817: iastore
    //   1818: dup
    //   1819: bipush #26
    //   1821: ldc 16777220
    //   1823: iastore
    //   1824: dup
    //   1825: bipush #27
    //   1827: ldc 65540
    //   1829: iastore
    //   1830: dup
    //   1831: bipush #28
    //   1833: iconst_0
    //   1834: iastore
    //   1835: dup
    //   1836: bipush #29
    //   1838: sipush #1028
    //   1841: iastore
    //   1842: dup
    //   1843: bipush #30
    //   1845: ldc 66564
    //   1847: iastore
    //   1848: dup
    //   1849: bipush #31
    //   1851: ldc 16777216
    //   1853: iastore
    //   1854: dup
    //   1855: bipush #32
    //   1857: ldc 65536
    //   1859: iastore
    //   1860: dup
    //   1861: bipush #33
    //   1863: ldc 16843780
    //   1865: iastore
    //   1866: dup
    //   1867: bipush #34
    //   1869: iconst_4
    //   1870: iastore
    //   1871: dup
    //   1872: bipush #35
    //   1874: ldc 16842752
    //   1876: iastore
    //   1877: dup
    //   1878: bipush #36
    //   1880: ldc 16843776
    //   1882: iastore
    //   1883: dup
    //   1884: bipush #37
    //   1886: ldc 16777216
    //   1888: iastore
    //   1889: dup
    //   1890: bipush #38
    //   1892: ldc 16777216
    //   1894: iastore
    //   1895: dup
    //   1896: bipush #39
    //   1898: sipush #1024
    //   1901: iastore
    //   1902: dup
    //   1903: bipush #40
    //   1905: ldc 16842756
    //   1907: iastore
    //   1908: dup
    //   1909: bipush #41
    //   1911: ldc 65536
    //   1913: iastore
    //   1914: dup
    //   1915: bipush #42
    //   1917: ldc 66560
    //   1919: iastore
    //   1920: dup
    //   1921: bipush #43
    //   1923: ldc 16777220
    //   1925: iastore
    //   1926: dup
    //   1927: bipush #44
    //   1929: sipush #1024
    //   1932: iastore
    //   1933: dup
    //   1934: bipush #45
    //   1936: iconst_4
    //   1937: iastore
    //   1938: dup
    //   1939: bipush #46
    //   1941: ldc 16778244
    //   1943: iastore
    //   1944: dup
    //   1945: bipush #47
    //   1947: ldc 66564
    //   1949: iastore
    //   1950: dup
    //   1951: bipush #48
    //   1953: ldc 16843780
    //   1955: iastore
    //   1956: dup
    //   1957: bipush #49
    //   1959: ldc 65540
    //   1961: iastore
    //   1962: dup
    //   1963: bipush #50
    //   1965: ldc 16842752
    //   1967: iastore
    //   1968: dup
    //   1969: bipush #51
    //   1971: ldc 16778244
    //   1973: iastore
    //   1974: dup
    //   1975: bipush #52
    //   1977: ldc 16777220
    //   1979: iastore
    //   1980: dup
    //   1981: bipush #53
    //   1983: sipush #1028
    //   1986: iastore
    //   1987: dup
    //   1988: bipush #54
    //   1990: ldc 66564
    //   1992: iastore
    //   1993: dup
    //   1994: bipush #55
    //   1996: ldc 16843776
    //   1998: iastore
    //   1999: dup
    //   2000: bipush #56
    //   2002: sipush #1028
    //   2005: iastore
    //   2006: dup
    //   2007: bipush #57
    //   2009: ldc 16778240
    //   2011: iastore
    //   2012: dup
    //   2013: bipush #58
    //   2015: ldc 16778240
    //   2017: iastore
    //   2018: dup
    //   2019: bipush #59
    //   2021: iconst_0
    //   2022: iastore
    //   2023: dup
    //   2024: bipush #60
    //   2026: ldc 65540
    //   2028: iastore
    //   2029: dup
    //   2030: bipush #61
    //   2032: ldc 66560
    //   2034: iastore
    //   2035: dup
    //   2036: bipush #62
    //   2038: iconst_0
    //   2039: iastore
    //   2040: dup
    //   2041: bipush #63
    //   2043: ldc 16842756
    //   2045: iastore
    //   2046: astore #9
    //   2048: bipush #64
    //   2050: newarray int
    //   2052: dup
    //   2053: iconst_0
    //   2054: ldc -2146402272
    //   2056: iastore
    //   2057: dup
    //   2058: iconst_1
    //   2059: ldc -2147450880
    //   2061: iastore
    //   2062: dup
    //   2063: iconst_2
    //   2064: ldc 32768
    //   2066: iastore
    //   2067: dup
    //   2068: iconst_3
    //   2069: ldc 1081376
    //   2071: iastore
    //   2072: dup
    //   2073: iconst_4
    //   2074: ldc 1048576
    //   2076: iastore
    //   2077: dup
    //   2078: iconst_5
    //   2079: bipush #32
    //   2081: iastore
    //   2082: dup
    //   2083: bipush #6
    //   2085: ldc -2146435040
    //   2087: iastore
    //   2088: dup
    //   2089: bipush #7
    //   2091: ldc -2147450848
    //   2093: iastore
    //   2094: dup
    //   2095: bipush #8
    //   2097: ldc -2147483616
    //   2099: iastore
    //   2100: dup
    //   2101: bipush #9
    //   2103: ldc -2146402272
    //   2105: iastore
    //   2106: dup
    //   2107: bipush #10
    //   2109: ldc -2146402304
    //   2111: iastore
    //   2112: dup
    //   2113: bipush #11
    //   2115: ldc -2147483648
    //   2117: iastore
    //   2118: dup
    //   2119: bipush #12
    //   2121: ldc -2147450880
    //   2123: iastore
    //   2124: dup
    //   2125: bipush #13
    //   2127: ldc 1048576
    //   2129: iastore
    //   2130: dup
    //   2131: bipush #14
    //   2133: bipush #32
    //   2135: iastore
    //   2136: dup
    //   2137: bipush #15
    //   2139: ldc -2146435040
    //   2141: iastore
    //   2142: dup
    //   2143: bipush #16
    //   2145: ldc 1081344
    //   2147: iastore
    //   2148: dup
    //   2149: bipush #17
    //   2151: ldc 1048608
    //   2153: iastore
    //   2154: dup
    //   2155: bipush #18
    //   2157: ldc -2147450848
    //   2159: iastore
    //   2160: dup
    //   2161: bipush #19
    //   2163: iconst_0
    //   2164: iastore
    //   2165: dup
    //   2166: bipush #20
    //   2168: ldc -2147483648
    //   2170: iastore
    //   2171: dup
    //   2172: bipush #21
    //   2174: ldc 32768
    //   2176: iastore
    //   2177: dup
    //   2178: bipush #22
    //   2180: ldc 1081376
    //   2182: iastore
    //   2183: dup
    //   2184: bipush #23
    //   2186: ldc -2146435072
    //   2188: iastore
    //   2189: dup
    //   2190: bipush #24
    //   2192: ldc 1048608
    //   2194: iastore
    //   2195: dup
    //   2196: bipush #25
    //   2198: ldc -2147483616
    //   2200: iastore
    //   2201: dup
    //   2202: bipush #26
    //   2204: iconst_0
    //   2205: iastore
    //   2206: dup
    //   2207: bipush #27
    //   2209: ldc 1081344
    //   2211: iastore
    //   2212: dup
    //   2213: bipush #28
    //   2215: ldc 32800
    //   2217: iastore
    //   2218: dup
    //   2219: bipush #29
    //   2221: ldc -2146402304
    //   2223: iastore
    //   2224: dup
    //   2225: bipush #30
    //   2227: ldc -2146435072
    //   2229: iastore
    //   2230: dup
    //   2231: bipush #31
    //   2233: ldc 32800
    //   2235: iastore
    //   2236: dup
    //   2237: bipush #32
    //   2239: iconst_0
    //   2240: iastore
    //   2241: dup
    //   2242: bipush #33
    //   2244: ldc 1081376
    //   2246: iastore
    //   2247: dup
    //   2248: bipush #34
    //   2250: ldc -2146435040
    //   2252: iastore
    //   2253: dup
    //   2254: bipush #35
    //   2256: ldc 1048576
    //   2258: iastore
    //   2259: dup
    //   2260: bipush #36
    //   2262: ldc -2147450848
    //   2264: iastore
    //   2265: dup
    //   2266: bipush #37
    //   2268: ldc -2146435072
    //   2270: iastore
    //   2271: dup
    //   2272: bipush #38
    //   2274: ldc -2146402304
    //   2276: iastore
    //   2277: dup
    //   2278: bipush #39
    //   2280: ldc 32768
    //   2282: iastore
    //   2283: dup
    //   2284: bipush #40
    //   2286: ldc -2146435072
    //   2288: iastore
    //   2289: dup
    //   2290: bipush #41
    //   2292: ldc -2147450880
    //   2294: iastore
    //   2295: dup
    //   2296: bipush #42
    //   2298: bipush #32
    //   2300: iastore
    //   2301: dup
    //   2302: bipush #43
    //   2304: ldc -2146402272
    //   2306: iastore
    //   2307: dup
    //   2308: bipush #44
    //   2310: ldc 1081376
    //   2312: iastore
    //   2313: dup
    //   2314: bipush #45
    //   2316: bipush #32
    //   2318: iastore
    //   2319: dup
    //   2320: bipush #46
    //   2322: ldc 32768
    //   2324: iastore
    //   2325: dup
    //   2326: bipush #47
    //   2328: ldc -2147483648
    //   2330: iastore
    //   2331: dup
    //   2332: bipush #48
    //   2334: ldc 32800
    //   2336: iastore
    //   2337: dup
    //   2338: bipush #49
    //   2340: ldc -2146402304
    //   2342: iastore
    //   2343: dup
    //   2344: bipush #50
    //   2346: ldc 1048576
    //   2348: iastore
    //   2349: dup
    //   2350: bipush #51
    //   2352: ldc -2147483616
    //   2354: iastore
    //   2355: dup
    //   2356: bipush #52
    //   2358: ldc 1048608
    //   2360: iastore
    //   2361: dup
    //   2362: bipush #53
    //   2364: ldc -2147450848
    //   2366: iastore
    //   2367: dup
    //   2368: bipush #54
    //   2370: ldc -2147483616
    //   2372: iastore
    //   2373: dup
    //   2374: bipush #55
    //   2376: ldc 1048608
    //   2378: iastore
    //   2379: dup
    //   2380: bipush #56
    //   2382: ldc 1081344
    //   2384: iastore
    //   2385: dup
    //   2386: bipush #57
    //   2388: iconst_0
    //   2389: iastore
    //   2390: dup
    //   2391: bipush #58
    //   2393: ldc -2147450880
    //   2395: iastore
    //   2396: dup
    //   2397: bipush #59
    //   2399: ldc 32800
    //   2401: iastore
    //   2402: dup
    //   2403: bipush #60
    //   2405: ldc -2147483648
    //   2407: iastore
    //   2408: dup
    //   2409: bipush #61
    //   2411: ldc -2146435040
    //   2413: iastore
    //   2414: dup
    //   2415: bipush #62
    //   2417: ldc -2146402272
    //   2419: iastore
    //   2420: dup
    //   2421: bipush #63
    //   2423: ldc 1081344
    //   2425: iastore
    //   2426: astore #10
    //   2428: bipush #64
    //   2430: newarray int
    //   2432: dup
    //   2433: iconst_0
    //   2434: sipush #520
    //   2437: iastore
    //   2438: dup
    //   2439: iconst_1
    //   2440: ldc 134349312
    //   2442: iastore
    //   2443: dup
    //   2444: iconst_2
    //   2445: iconst_0
    //   2446: iastore
    //   2447: dup
    //   2448: iconst_3
    //   2449: ldc 134348808
    //   2451: iastore
    //   2452: dup
    //   2453: iconst_4
    //   2454: ldc 134218240
    //   2456: iastore
    //   2457: dup
    //   2458: iconst_5
    //   2459: iconst_0
    //   2460: iastore
    //   2461: dup
    //   2462: bipush #6
    //   2464: ldc 131592
    //   2466: iastore
    //   2467: dup
    //   2468: bipush #7
    //   2470: ldc 134218240
    //   2472: iastore
    //   2473: dup
    //   2474: bipush #8
    //   2476: ldc 131080
    //   2478: iastore
    //   2479: dup
    //   2480: bipush #9
    //   2482: ldc 134217736
    //   2484: iastore
    //   2485: dup
    //   2486: bipush #10
    //   2488: ldc 134217736
    //   2490: iastore
    //   2491: dup
    //   2492: bipush #11
    //   2494: ldc 131072
    //   2496: iastore
    //   2497: dup
    //   2498: bipush #12
    //   2500: ldc 134349320
    //   2502: iastore
    //   2503: dup
    //   2504: bipush #13
    //   2506: ldc 131080
    //   2508: iastore
    //   2509: dup
    //   2510: bipush #14
    //   2512: ldc 134348800
    //   2514: iastore
    //   2515: dup
    //   2516: bipush #15
    //   2518: sipush #520
    //   2521: iastore
    //   2522: dup
    //   2523: bipush #16
    //   2525: ldc 134217728
    //   2527: iastore
    //   2528: dup
    //   2529: bipush #17
    //   2531: bipush #8
    //   2533: iastore
    //   2534: dup
    //   2535: bipush #18
    //   2537: ldc 134349312
    //   2539: iastore
    //   2540: dup
    //   2541: bipush #19
    //   2543: sipush #512
    //   2546: iastore
    //   2547: dup
    //   2548: bipush #20
    //   2550: ldc 131584
    //   2552: iastore
    //   2553: dup
    //   2554: bipush #21
    //   2556: ldc 134348800
    //   2558: iastore
    //   2559: dup
    //   2560: bipush #22
    //   2562: ldc 134348808
    //   2564: iastore
    //   2565: dup
    //   2566: bipush #23
    //   2568: ldc 131592
    //   2570: iastore
    //   2571: dup
    //   2572: bipush #24
    //   2574: ldc 134218248
    //   2576: iastore
    //   2577: dup
    //   2578: bipush #25
    //   2580: ldc 131584
    //   2582: iastore
    //   2583: dup
    //   2584: bipush #26
    //   2586: ldc 131072
    //   2588: iastore
    //   2589: dup
    //   2590: bipush #27
    //   2592: ldc 134218248
    //   2594: iastore
    //   2595: dup
    //   2596: bipush #28
    //   2598: bipush #8
    //   2600: iastore
    //   2601: dup
    //   2602: bipush #29
    //   2604: ldc 134349320
    //   2606: iastore
    //   2607: dup
    //   2608: bipush #30
    //   2610: sipush #512
    //   2613: iastore
    //   2614: dup
    //   2615: bipush #31
    //   2617: ldc 134217728
    //   2619: iastore
    //   2620: dup
    //   2621: bipush #32
    //   2623: ldc 134349312
    //   2625: iastore
    //   2626: dup
    //   2627: bipush #33
    //   2629: ldc 134217728
    //   2631: iastore
    //   2632: dup
    //   2633: bipush #34
    //   2635: ldc 131080
    //   2637: iastore
    //   2638: dup
    //   2639: bipush #35
    //   2641: sipush #520
    //   2644: iastore
    //   2645: dup
    //   2646: bipush #36
    //   2648: ldc 131072
    //   2650: iastore
    //   2651: dup
    //   2652: bipush #37
    //   2654: ldc 134349312
    //   2656: iastore
    //   2657: dup
    //   2658: bipush #38
    //   2660: ldc 134218240
    //   2662: iastore
    //   2663: dup
    //   2664: bipush #39
    //   2666: iconst_0
    //   2667: iastore
    //   2668: dup
    //   2669: bipush #40
    //   2671: sipush #512
    //   2674: iastore
    //   2675: dup
    //   2676: bipush #41
    //   2678: ldc 131080
    //   2680: iastore
    //   2681: dup
    //   2682: bipush #42
    //   2684: ldc 134349320
    //   2686: iastore
    //   2687: dup
    //   2688: bipush #43
    //   2690: ldc 134218240
    //   2692: iastore
    //   2693: dup
    //   2694: bipush #44
    //   2696: ldc 134217736
    //   2698: iastore
    //   2699: dup
    //   2700: bipush #45
    //   2702: sipush #512
    //   2705: iastore
    //   2706: dup
    //   2707: bipush #46
    //   2709: iconst_0
    //   2710: iastore
    //   2711: dup
    //   2712: bipush #47
    //   2714: ldc 134348808
    //   2716: iastore
    //   2717: dup
    //   2718: bipush #48
    //   2720: ldc 134218248
    //   2722: iastore
    //   2723: dup
    //   2724: bipush #49
    //   2726: ldc 131072
    //   2728: iastore
    //   2729: dup
    //   2730: bipush #50
    //   2732: ldc 134217728
    //   2734: iastore
    //   2735: dup
    //   2736: bipush #51
    //   2738: ldc 134349320
    //   2740: iastore
    //   2741: dup
    //   2742: bipush #52
    //   2744: bipush #8
    //   2746: iastore
    //   2747: dup
    //   2748: bipush #53
    //   2750: ldc 131592
    //   2752: iastore
    //   2753: dup
    //   2754: bipush #54
    //   2756: ldc 131584
    //   2758: iastore
    //   2759: dup
    //   2760: bipush #55
    //   2762: ldc 134217736
    //   2764: iastore
    //   2765: dup
    //   2766: bipush #56
    //   2768: ldc 134348800
    //   2770: iastore
    //   2771: dup
    //   2772: bipush #57
    //   2774: ldc 134218248
    //   2776: iastore
    //   2777: dup
    //   2778: bipush #58
    //   2780: sipush #520
    //   2783: iastore
    //   2784: dup
    //   2785: bipush #59
    //   2787: ldc 134348800
    //   2789: iastore
    //   2790: dup
    //   2791: bipush #60
    //   2793: ldc 131592
    //   2795: iastore
    //   2796: dup
    //   2797: bipush #61
    //   2799: bipush #8
    //   2801: iastore
    //   2802: dup
    //   2803: bipush #62
    //   2805: ldc 134348808
    //   2807: iastore
    //   2808: dup
    //   2809: bipush #63
    //   2811: ldc 131584
    //   2813: iastore
    //   2814: astore #11
    //   2816: bipush #64
    //   2818: newarray int
    //   2820: dup
    //   2821: iconst_0
    //   2822: ldc 8396801
    //   2824: iastore
    //   2825: dup
    //   2826: iconst_1
    //   2827: sipush #8321
    //   2830: iastore
    //   2831: dup
    //   2832: iconst_2
    //   2833: sipush #8321
    //   2836: iastore
    //   2837: dup
    //   2838: iconst_3
    //   2839: sipush #128
    //   2842: iastore
    //   2843: dup
    //   2844: iconst_4
    //   2845: ldc 8396928
    //   2847: iastore
    //   2848: dup
    //   2849: iconst_5
    //   2850: ldc 8388737
    //   2852: iastore
    //   2853: dup
    //   2854: bipush #6
    //   2856: ldc 8388609
    //   2858: iastore
    //   2859: dup
    //   2860: bipush #7
    //   2862: sipush #8193
    //   2865: iastore
    //   2866: dup
    //   2867: bipush #8
    //   2869: iconst_0
    //   2870: iastore
    //   2871: dup
    //   2872: bipush #9
    //   2874: ldc 8396800
    //   2876: iastore
    //   2877: dup
    //   2878: bipush #10
    //   2880: ldc 8396800
    //   2882: iastore
    //   2883: dup
    //   2884: bipush #11
    //   2886: ldc 8396929
    //   2888: iastore
    //   2889: dup
    //   2890: bipush #12
    //   2892: sipush #129
    //   2895: iastore
    //   2896: dup
    //   2897: bipush #13
    //   2899: iconst_0
    //   2900: iastore
    //   2901: dup
    //   2902: bipush #14
    //   2904: ldc 8388736
    //   2906: iastore
    //   2907: dup
    //   2908: bipush #15
    //   2910: ldc 8388609
    //   2912: iastore
    //   2913: dup
    //   2914: bipush #16
    //   2916: iconst_1
    //   2917: iastore
    //   2918: dup
    //   2919: bipush #17
    //   2921: sipush #8192
    //   2924: iastore
    //   2925: dup
    //   2926: bipush #18
    //   2928: ldc 8388608
    //   2930: iastore
    //   2931: dup
    //   2932: bipush #19
    //   2934: ldc 8396801
    //   2936: iastore
    //   2937: dup
    //   2938: bipush #20
    //   2940: sipush #128
    //   2943: iastore
    //   2944: dup
    //   2945: bipush #21
    //   2947: ldc 8388608
    //   2949: iastore
    //   2950: dup
    //   2951: bipush #22
    //   2953: sipush #8193
    //   2956: iastore
    //   2957: dup
    //   2958: bipush #23
    //   2960: sipush #8320
    //   2963: iastore
    //   2964: dup
    //   2965: bipush #24
    //   2967: ldc 8388737
    //   2969: iastore
    //   2970: dup
    //   2971: bipush #25
    //   2973: iconst_1
    //   2974: iastore
    //   2975: dup
    //   2976: bipush #26
    //   2978: sipush #8320
    //   2981: iastore
    //   2982: dup
    //   2983: bipush #27
    //   2985: ldc 8388736
    //   2987: iastore
    //   2988: dup
    //   2989: bipush #28
    //   2991: sipush #8192
    //   2994: iastore
    //   2995: dup
    //   2996: bipush #29
    //   2998: ldc 8396928
    //   3000: iastore
    //   3001: dup
    //   3002: bipush #30
    //   3004: ldc 8396929
    //   3006: iastore
    //   3007: dup
    //   3008: bipush #31
    //   3010: sipush #129
    //   3013: iastore
    //   3014: dup
    //   3015: bipush #32
    //   3017: ldc 8388736
    //   3019: iastore
    //   3020: dup
    //   3021: bipush #33
    //   3023: ldc 8388609
    //   3025: iastore
    //   3026: dup
    //   3027: bipush #34
    //   3029: ldc 8396800
    //   3031: iastore
    //   3032: dup
    //   3033: bipush #35
    //   3035: ldc 8396929
    //   3037: iastore
    //   3038: dup
    //   3039: bipush #36
    //   3041: sipush #129
    //   3044: iastore
    //   3045: dup
    //   3046: bipush #37
    //   3048: iconst_0
    //   3049: iastore
    //   3050: dup
    //   3051: bipush #38
    //   3053: iconst_0
    //   3054: iastore
    //   3055: dup
    //   3056: bipush #39
    //   3058: ldc 8396800
    //   3060: iastore
    //   3061: dup
    //   3062: bipush #40
    //   3064: sipush #8320
    //   3067: iastore
    //   3068: dup
    //   3069: bipush #41
    //   3071: ldc 8388736
    //   3073: iastore
    //   3074: dup
    //   3075: bipush #42
    //   3077: ldc 8388737
    //   3079: iastore
    //   3080: dup
    //   3081: bipush #43
    //   3083: iconst_1
    //   3084: iastore
    //   3085: dup
    //   3086: bipush #44
    //   3088: ldc 8396801
    //   3090: iastore
    //   3091: dup
    //   3092: bipush #45
    //   3094: sipush #8321
    //   3097: iastore
    //   3098: dup
    //   3099: bipush #46
    //   3101: sipush #8321
    //   3104: iastore
    //   3105: dup
    //   3106: bipush #47
    //   3108: sipush #128
    //   3111: iastore
    //   3112: dup
    //   3113: bipush #48
    //   3115: ldc 8396929
    //   3117: iastore
    //   3118: dup
    //   3119: bipush #49
    //   3121: sipush #129
    //   3124: iastore
    //   3125: dup
    //   3126: bipush #50
    //   3128: iconst_1
    //   3129: iastore
    //   3130: dup
    //   3131: bipush #51
    //   3133: sipush #8192
    //   3136: iastore
    //   3137: dup
    //   3138: bipush #52
    //   3140: ldc 8388609
    //   3142: iastore
    //   3143: dup
    //   3144: bipush #53
    //   3146: sipush #8193
    //   3149: iastore
    //   3150: dup
    //   3151: bipush #54
    //   3153: ldc 8396928
    //   3155: iastore
    //   3156: dup
    //   3157: bipush #55
    //   3159: ldc 8388737
    //   3161: iastore
    //   3162: dup
    //   3163: bipush #56
    //   3165: sipush #8193
    //   3168: iastore
    //   3169: dup
    //   3170: bipush #57
    //   3172: sipush #8320
    //   3175: iastore
    //   3176: dup
    //   3177: bipush #58
    //   3179: ldc 8388608
    //   3181: iastore
    //   3182: dup
    //   3183: bipush #59
    //   3185: ldc 8396801
    //   3187: iastore
    //   3188: dup
    //   3189: bipush #60
    //   3191: sipush #128
    //   3194: iastore
    //   3195: dup
    //   3196: bipush #61
    //   3198: ldc 8388608
    //   3200: iastore
    //   3201: dup
    //   3202: bipush #62
    //   3204: sipush #8192
    //   3207: iastore
    //   3208: dup
    //   3209: bipush #63
    //   3211: ldc 8396928
    //   3213: iastore
    //   3214: astore #12
    //   3216: bipush #64
    //   3218: newarray int
    //   3220: dup
    //   3221: iconst_0
    //   3222: sipush #256
    //   3225: iastore
    //   3226: dup
    //   3227: iconst_1
    //   3228: ldc 34078976
    //   3230: iastore
    //   3231: dup
    //   3232: iconst_2
    //   3233: ldc 34078720
    //   3235: iastore
    //   3236: dup
    //   3237: iconst_3
    //   3238: ldc 1107296512
    //   3240: iastore
    //   3241: dup
    //   3242: iconst_4
    //   3243: ldc 524288
    //   3245: iastore
    //   3246: dup
    //   3247: iconst_5
    //   3248: sipush #256
    //   3251: iastore
    //   3252: dup
    //   3253: bipush #6
    //   3255: ldc 1073741824
    //   3257: iastore
    //   3258: dup
    //   3259: bipush #7
    //   3261: ldc 34078720
    //   3263: iastore
    //   3264: dup
    //   3265: bipush #8
    //   3267: ldc 1074266368
    //   3269: iastore
    //   3270: dup
    //   3271: bipush #9
    //   3273: ldc 524288
    //   3275: iastore
    //   3276: dup
    //   3277: bipush #10
    //   3279: ldc 33554688
    //   3281: iastore
    //   3282: dup
    //   3283: bipush #11
    //   3285: ldc 1074266368
    //   3287: iastore
    //   3288: dup
    //   3289: bipush #12
    //   3291: ldc 1107296512
    //   3293: iastore
    //   3294: dup
    //   3295: bipush #13
    //   3297: ldc 1107820544
    //   3299: iastore
    //   3300: dup
    //   3301: bipush #14
    //   3303: ldc 524544
    //   3305: iastore
    //   3306: dup
    //   3307: bipush #15
    //   3309: ldc 1073741824
    //   3311: iastore
    //   3312: dup
    //   3313: bipush #16
    //   3315: ldc 33554432
    //   3317: iastore
    //   3318: dup
    //   3319: bipush #17
    //   3321: ldc 1074266112
    //   3323: iastore
    //   3324: dup
    //   3325: bipush #18
    //   3327: ldc 1074266112
    //   3329: iastore
    //   3330: dup
    //   3331: bipush #19
    //   3333: iconst_0
    //   3334: iastore
    //   3335: dup
    //   3336: bipush #20
    //   3338: ldc 1073742080
    //   3340: iastore
    //   3341: dup
    //   3342: bipush #21
    //   3344: ldc 1107820800
    //   3346: iastore
    //   3347: dup
    //   3348: bipush #22
    //   3350: ldc 1107820800
    //   3352: iastore
    //   3353: dup
    //   3354: bipush #23
    //   3356: ldc 33554688
    //   3358: iastore
    //   3359: dup
    //   3360: bipush #24
    //   3362: ldc 1107820544
    //   3364: iastore
    //   3365: dup
    //   3366: bipush #25
    //   3368: ldc 1073742080
    //   3370: iastore
    //   3371: dup
    //   3372: bipush #26
    //   3374: iconst_0
    //   3375: iastore
    //   3376: dup
    //   3377: bipush #27
    //   3379: ldc 1107296256
    //   3381: iastore
    //   3382: dup
    //   3383: bipush #28
    //   3385: ldc 34078976
    //   3387: iastore
    //   3388: dup
    //   3389: bipush #29
    //   3391: ldc 33554432
    //   3393: iastore
    //   3394: dup
    //   3395: bipush #30
    //   3397: ldc 1107296256
    //   3399: iastore
    //   3400: dup
    //   3401: bipush #31
    //   3403: ldc 524544
    //   3405: iastore
    //   3406: dup
    //   3407: bipush #32
    //   3409: ldc 524288
    //   3411: iastore
    //   3412: dup
    //   3413: bipush #33
    //   3415: ldc 1107296512
    //   3417: iastore
    //   3418: dup
    //   3419: bipush #34
    //   3421: sipush #256
    //   3424: iastore
    //   3425: dup
    //   3426: bipush #35
    //   3428: ldc 33554432
    //   3430: iastore
    //   3431: dup
    //   3432: bipush #36
    //   3434: ldc 1073741824
    //   3436: iastore
    //   3437: dup
    //   3438: bipush #37
    //   3440: ldc 34078720
    //   3442: iastore
    //   3443: dup
    //   3444: bipush #38
    //   3446: ldc 1107296512
    //   3448: iastore
    //   3449: dup
    //   3450: bipush #39
    //   3452: ldc 1074266368
    //   3454: iastore
    //   3455: dup
    //   3456: bipush #40
    //   3458: ldc 33554688
    //   3460: iastore
    //   3461: dup
    //   3462: bipush #41
    //   3464: ldc 1073741824
    //   3466: iastore
    //   3467: dup
    //   3468: bipush #42
    //   3470: ldc 1107820544
    //   3472: iastore
    //   3473: dup
    //   3474: bipush #43
    //   3476: ldc 34078976
    //   3478: iastore
    //   3479: dup
    //   3480: bipush #44
    //   3482: ldc 1074266368
    //   3484: iastore
    //   3485: dup
    //   3486: bipush #45
    //   3488: sipush #256
    //   3491: iastore
    //   3492: dup
    //   3493: bipush #46
    //   3495: ldc 33554432
    //   3497: iastore
    //   3498: dup
    //   3499: bipush #47
    //   3501: ldc 1107820544
    //   3503: iastore
    //   3504: dup
    //   3505: bipush #48
    //   3507: ldc 1107820800
    //   3509: iastore
    //   3510: dup
    //   3511: bipush #49
    //   3513: ldc 524544
    //   3515: iastore
    //   3516: dup
    //   3517: bipush #50
    //   3519: ldc 1107296256
    //   3521: iastore
    //   3522: dup
    //   3523: bipush #51
    //   3525: ldc 1107820800
    //   3527: iastore
    //   3528: dup
    //   3529: bipush #52
    //   3531: ldc 34078720
    //   3533: iastore
    //   3534: dup
    //   3535: bipush #53
    //   3537: iconst_0
    //   3538: iastore
    //   3539: dup
    //   3540: bipush #54
    //   3542: ldc 1074266112
    //   3544: iastore
    //   3545: dup
    //   3546: bipush #55
    //   3548: ldc 1107296256
    //   3550: iastore
    //   3551: dup
    //   3552: bipush #56
    //   3554: ldc 524544
    //   3556: iastore
    //   3557: dup
    //   3558: bipush #57
    //   3560: ldc 33554688
    //   3562: iastore
    //   3563: dup
    //   3564: bipush #58
    //   3566: ldc 1073742080
    //   3568: iastore
    //   3569: dup
    //   3570: bipush #59
    //   3572: ldc 524288
    //   3574: iastore
    //   3575: dup
    //   3576: bipush #60
    //   3578: iconst_0
    //   3579: iastore
    //   3580: dup
    //   3581: bipush #61
    //   3583: ldc 1074266112
    //   3585: iastore
    //   3586: dup
    //   3587: bipush #62
    //   3589: ldc 34078976
    //   3591: iastore
    //   3592: dup
    //   3593: bipush #63
    //   3595: ldc 1073742080
    //   3597: iastore
    //   3598: astore #13
    //   3600: bipush #64
    //   3602: newarray int
    //   3604: dup
    //   3605: iconst_0
    //   3606: ldc 536870928
    //   3608: iastore
    //   3609: dup
    //   3610: iconst_1
    //   3611: ldc 541065216
    //   3613: iastore
    //   3614: dup
    //   3615: iconst_2
    //   3616: sipush #16384
    //   3619: iastore
    //   3620: dup
    //   3621: iconst_3
    //   3622: ldc 541081616
    //   3624: iastore
    //   3625: dup
    //   3626: iconst_4
    //   3627: ldc 541065216
    //   3629: iastore
    //   3630: dup
    //   3631: iconst_5
    //   3632: bipush #16
    //   3634: iastore
    //   3635: dup
    //   3636: bipush #6
    //   3638: ldc 541081616
    //   3640: iastore
    //   3641: dup
    //   3642: bipush #7
    //   3644: ldc 4194304
    //   3646: iastore
    //   3647: dup
    //   3648: bipush #8
    //   3650: ldc 536887296
    //   3652: iastore
    //   3653: dup
    //   3654: bipush #9
    //   3656: ldc 4210704
    //   3658: iastore
    //   3659: dup
    //   3660: bipush #10
    //   3662: ldc 4194304
    //   3664: iastore
    //   3665: dup
    //   3666: bipush #11
    //   3668: ldc 536870928
    //   3670: iastore
    //   3671: dup
    //   3672: bipush #12
    //   3674: ldc 4194320
    //   3676: iastore
    //   3677: dup
    //   3678: bipush #13
    //   3680: ldc 536887296
    //   3682: iastore
    //   3683: dup
    //   3684: bipush #14
    //   3686: ldc 536870912
    //   3688: iastore
    //   3689: dup
    //   3690: bipush #15
    //   3692: sipush #16400
    //   3695: iastore
    //   3696: dup
    //   3697: bipush #16
    //   3699: iconst_0
    //   3700: iastore
    //   3701: dup
    //   3702: bipush #17
    //   3704: ldc 4194320
    //   3706: iastore
    //   3707: dup
    //   3708: bipush #18
    //   3710: ldc 536887312
    //   3712: iastore
    //   3713: dup
    //   3714: bipush #19
    //   3716: sipush #16384
    //   3719: iastore
    //   3720: dup
    //   3721: bipush #20
    //   3723: ldc 4210688
    //   3725: iastore
    //   3726: dup
    //   3727: bipush #21
    //   3729: ldc 536887312
    //   3731: iastore
    //   3732: dup
    //   3733: bipush #22
    //   3735: bipush #16
    //   3737: iastore
    //   3738: dup
    //   3739: bipush #23
    //   3741: ldc 541065232
    //   3743: iastore
    //   3744: dup
    //   3745: bipush #24
    //   3747: ldc 541065232
    //   3749: iastore
    //   3750: dup
    //   3751: bipush #25
    //   3753: iconst_0
    //   3754: iastore
    //   3755: dup
    //   3756: bipush #26
    //   3758: ldc 4210704
    //   3760: iastore
    //   3761: dup
    //   3762: bipush #27
    //   3764: ldc 541081600
    //   3766: iastore
    //   3767: dup
    //   3768: bipush #28
    //   3770: sipush #16400
    //   3773: iastore
    //   3774: dup
    //   3775: bipush #29
    //   3777: ldc 4210688
    //   3779: iastore
    //   3780: dup
    //   3781: bipush #30
    //   3783: ldc 541081600
    //   3785: iastore
    //   3786: dup
    //   3787: bipush #31
    //   3789: ldc 536870912
    //   3791: iastore
    //   3792: dup
    //   3793: bipush #32
    //   3795: ldc 536887296
    //   3797: iastore
    //   3798: dup
    //   3799: bipush #33
    //   3801: bipush #16
    //   3803: iastore
    //   3804: dup
    //   3805: bipush #34
    //   3807: ldc 541065232
    //   3809: iastore
    //   3810: dup
    //   3811: bipush #35
    //   3813: ldc 4210688
    //   3815: iastore
    //   3816: dup
    //   3817: bipush #36
    //   3819: ldc 541081616
    //   3821: iastore
    //   3822: dup
    //   3823: bipush #37
    //   3825: ldc 4194304
    //   3827: iastore
    //   3828: dup
    //   3829: bipush #38
    //   3831: sipush #16400
    //   3834: iastore
    //   3835: dup
    //   3836: bipush #39
    //   3838: ldc 536870928
    //   3840: iastore
    //   3841: dup
    //   3842: bipush #40
    //   3844: ldc 4194304
    //   3846: iastore
    //   3847: dup
    //   3848: bipush #41
    //   3850: ldc 536887296
    //   3852: iastore
    //   3853: dup
    //   3854: bipush #42
    //   3856: ldc 536870912
    //   3858: iastore
    //   3859: dup
    //   3860: bipush #43
    //   3862: sipush #16400
    //   3865: iastore
    //   3866: dup
    //   3867: bipush #44
    //   3869: ldc 536870928
    //   3871: iastore
    //   3872: dup
    //   3873: bipush #45
    //   3875: ldc 541081616
    //   3877: iastore
    //   3878: dup
    //   3879: bipush #46
    //   3881: ldc 4210688
    //   3883: iastore
    //   3884: dup
    //   3885: bipush #47
    //   3887: ldc 541065216
    //   3889: iastore
    //   3890: dup
    //   3891: bipush #48
    //   3893: ldc 4210704
    //   3895: iastore
    //   3896: dup
    //   3897: bipush #49
    //   3899: ldc 541081600
    //   3901: iastore
    //   3902: dup
    //   3903: bipush #50
    //   3905: iconst_0
    //   3906: iastore
    //   3907: dup
    //   3908: bipush #51
    //   3910: ldc 541065232
    //   3912: iastore
    //   3913: dup
    //   3914: bipush #52
    //   3916: bipush #16
    //   3918: iastore
    //   3919: dup
    //   3920: bipush #53
    //   3922: sipush #16384
    //   3925: iastore
    //   3926: dup
    //   3927: bipush #54
    //   3929: ldc 541065216
    //   3931: iastore
    //   3932: dup
    //   3933: bipush #55
    //   3935: ldc 4210704
    //   3937: iastore
    //   3938: dup
    //   3939: bipush #56
    //   3941: sipush #16384
    //   3944: iastore
    //   3945: dup
    //   3946: bipush #57
    //   3948: ldc 4194320
    //   3950: iastore
    //   3951: dup
    //   3952: bipush #58
    //   3954: ldc 536887312
    //   3956: iastore
    //   3957: dup
    //   3958: bipush #59
    //   3960: iconst_0
    //   3961: iastore
    //   3962: dup
    //   3963: bipush #60
    //   3965: ldc 541081600
    //   3967: iastore
    //   3968: dup
    //   3969: bipush #61
    //   3971: ldc 536870912
    //   3973: iastore
    //   3974: dup
    //   3975: bipush #62
    //   3977: ldc 4194320
    //   3979: iastore
    //   3980: dup
    //   3981: bipush #63
    //   3983: ldc 536887312
    //   3985: iastore
    //   3986: astore #14
    //   3988: bipush #64
    //   3990: newarray int
    //   3992: dup
    //   3993: iconst_0
    //   3994: ldc 2097152
    //   3996: iastore
    //   3997: dup
    //   3998: iconst_1
    //   3999: ldc 69206018
    //   4001: iastore
    //   4002: dup
    //   4003: iconst_2
    //   4004: ldc 67110914
    //   4006: iastore
    //   4007: dup
    //   4008: iconst_3
    //   4009: iconst_0
    //   4010: iastore
    //   4011: dup
    //   4012: iconst_4
    //   4013: sipush #2048
    //   4016: iastore
    //   4017: dup
    //   4018: iconst_5
    //   4019: ldc 67110914
    //   4021: iastore
    //   4022: dup
    //   4023: bipush #6
    //   4025: ldc 2099202
    //   4027: iastore
    //   4028: dup
    //   4029: bipush #7
    //   4031: ldc 69208064
    //   4033: iastore
    //   4034: dup
    //   4035: bipush #8
    //   4037: ldc 69208066
    //   4039: iastore
    //   4040: dup
    //   4041: bipush #9
    //   4043: ldc 2097152
    //   4045: iastore
    //   4046: dup
    //   4047: bipush #10
    //   4049: iconst_0
    //   4050: iastore
    //   4051: dup
    //   4052: bipush #11
    //   4054: ldc 67108866
    //   4056: iastore
    //   4057: dup
    //   4058: bipush #12
    //   4060: iconst_2
    //   4061: iastore
    //   4062: dup
    //   4063: bipush #13
    //   4065: ldc 67108864
    //   4067: iastore
    //   4068: dup
    //   4069: bipush #14
    //   4071: ldc 69206018
    //   4073: iastore
    //   4074: dup
    //   4075: bipush #15
    //   4077: sipush #2050
    //   4080: iastore
    //   4081: dup
    //   4082: bipush #16
    //   4084: ldc 67110912
    //   4086: iastore
    //   4087: dup
    //   4088: bipush #17
    //   4090: ldc 2099202
    //   4092: iastore
    //   4093: dup
    //   4094: bipush #18
    //   4096: ldc 2097154
    //   4098: iastore
    //   4099: dup
    //   4100: bipush #19
    //   4102: ldc 67110912
    //   4104: iastore
    //   4105: dup
    //   4106: bipush #20
    //   4108: ldc 67108866
    //   4110: iastore
    //   4111: dup
    //   4112: bipush #21
    //   4114: ldc 69206016
    //   4116: iastore
    //   4117: dup
    //   4118: bipush #22
    //   4120: ldc 69208064
    //   4122: iastore
    //   4123: dup
    //   4124: bipush #23
    //   4126: ldc 2097154
    //   4128: iastore
    //   4129: dup
    //   4130: bipush #24
    //   4132: ldc 69206016
    //   4134: iastore
    //   4135: dup
    //   4136: bipush #25
    //   4138: sipush #2048
    //   4141: iastore
    //   4142: dup
    //   4143: bipush #26
    //   4145: sipush #2050
    //   4148: iastore
    //   4149: dup
    //   4150: bipush #27
    //   4152: ldc 69208066
    //   4154: iastore
    //   4155: dup
    //   4156: bipush #28
    //   4158: ldc 2099200
    //   4160: iastore
    //   4161: dup
    //   4162: bipush #29
    //   4164: iconst_2
    //   4165: iastore
    //   4166: dup
    //   4167: bipush #30
    //   4169: ldc 67108864
    //   4171: iastore
    //   4172: dup
    //   4173: bipush #31
    //   4175: ldc 2099200
    //   4177: iastore
    //   4178: dup
    //   4179: bipush #32
    //   4181: ldc 67108864
    //   4183: iastore
    //   4184: dup
    //   4185: bipush #33
    //   4187: ldc 2099200
    //   4189: iastore
    //   4190: dup
    //   4191: bipush #34
    //   4193: ldc 2097152
    //   4195: iastore
    //   4196: dup
    //   4197: bipush #35
    //   4199: ldc 67110914
    //   4201: iastore
    //   4202: dup
    //   4203: bipush #36
    //   4205: ldc 67110914
    //   4207: iastore
    //   4208: dup
    //   4209: bipush #37
    //   4211: ldc 69206018
    //   4213: iastore
    //   4214: dup
    //   4215: bipush #38
    //   4217: ldc 69206018
    //   4219: iastore
    //   4220: dup
    //   4221: bipush #39
    //   4223: iconst_2
    //   4224: iastore
    //   4225: dup
    //   4226: bipush #40
    //   4228: ldc 2097154
    //   4230: iastore
    //   4231: dup
    //   4232: bipush #41
    //   4234: ldc 67108864
    //   4236: iastore
    //   4237: dup
    //   4238: bipush #42
    //   4240: ldc 67110912
    //   4242: iastore
    //   4243: dup
    //   4244: bipush #43
    //   4246: ldc 2097152
    //   4248: iastore
    //   4249: dup
    //   4250: bipush #44
    //   4252: ldc 69208064
    //   4254: iastore
    //   4255: dup
    //   4256: bipush #45
    //   4258: sipush #2050
    //   4261: iastore
    //   4262: dup
    //   4263: bipush #46
    //   4265: ldc 2099202
    //   4267: iastore
    //   4268: dup
    //   4269: bipush #47
    //   4271: ldc 69208064
    //   4273: iastore
    //   4274: dup
    //   4275: bipush #48
    //   4277: sipush #2050
    //   4280: iastore
    //   4281: dup
    //   4282: bipush #49
    //   4284: ldc 67108866
    //   4286: iastore
    //   4287: dup
    //   4288: bipush #50
    //   4290: ldc 69208066
    //   4292: iastore
    //   4293: dup
    //   4294: bipush #51
    //   4296: ldc 69206016
    //   4298: iastore
    //   4299: dup
    //   4300: bipush #52
    //   4302: ldc 2099200
    //   4304: iastore
    //   4305: dup
    //   4306: bipush #53
    //   4308: iconst_0
    //   4309: iastore
    //   4310: dup
    //   4311: bipush #54
    //   4313: iconst_2
    //   4314: iastore
    //   4315: dup
    //   4316: bipush #55
    //   4318: ldc 69208066
    //   4320: iastore
    //   4321: dup
    //   4322: bipush #56
    //   4324: iconst_0
    //   4325: iastore
    //   4326: dup
    //   4327: bipush #57
    //   4329: ldc 2099202
    //   4331: iastore
    //   4332: dup
    //   4333: bipush #58
    //   4335: ldc 69206016
    //   4337: iastore
    //   4338: dup
    //   4339: bipush #59
    //   4341: sipush #2048
    //   4344: iastore
    //   4345: dup
    //   4346: bipush #60
    //   4348: ldc 67108866
    //   4350: iastore
    //   4351: dup
    //   4352: bipush #61
    //   4354: ldc 67110912
    //   4356: iastore
    //   4357: dup
    //   4358: bipush #62
    //   4360: sipush #2048
    //   4363: iastore
    //   4364: dup
    //   4365: bipush #63
    //   4367: ldc 2097154
    //   4369: iastore
    //   4370: astore #15
    //   4372: bipush #64
    //   4374: newarray int
    //   4376: dup
    //   4377: iconst_0
    //   4378: ldc 268439616
    //   4380: iastore
    //   4381: dup
    //   4382: iconst_1
    //   4383: sipush #4096
    //   4386: iastore
    //   4387: dup
    //   4388: iconst_2
    //   4389: ldc 262144
    //   4391: iastore
    //   4392: dup
    //   4393: iconst_3
    //   4394: ldc 268701760
    //   4396: iastore
    //   4397: dup
    //   4398: iconst_4
    //   4399: ldc 268435456
    //   4401: iastore
    //   4402: dup
    //   4403: iconst_5
    //   4404: ldc 268439616
    //   4406: iastore
    //   4407: dup
    //   4408: bipush #6
    //   4410: bipush #64
    //   4412: iastore
    //   4413: dup
    //   4414: bipush #7
    //   4416: ldc 268435456
    //   4418: iastore
    //   4419: dup
    //   4420: bipush #8
    //   4422: ldc 262208
    //   4424: iastore
    //   4425: dup
    //   4426: bipush #9
    //   4428: ldc 268697600
    //   4430: iastore
    //   4431: dup
    //   4432: bipush #10
    //   4434: ldc 268701760
    //   4436: iastore
    //   4437: dup
    //   4438: bipush #11
    //   4440: ldc 266240
    //   4442: iastore
    //   4443: dup
    //   4444: bipush #12
    //   4446: ldc 268701696
    //   4448: iastore
    //   4449: dup
    //   4450: bipush #13
    //   4452: ldc 266304
    //   4454: iastore
    //   4455: dup
    //   4456: bipush #14
    //   4458: sipush #4096
    //   4461: iastore
    //   4462: dup
    //   4463: bipush #15
    //   4465: bipush #64
    //   4467: iastore
    //   4468: dup
    //   4469: bipush #16
    //   4471: ldc 268697600
    //   4473: iastore
    //   4474: dup
    //   4475: bipush #17
    //   4477: ldc 268435520
    //   4479: iastore
    //   4480: dup
    //   4481: bipush #18
    //   4483: ldc 268439552
    //   4485: iastore
    //   4486: dup
    //   4487: bipush #19
    //   4489: sipush #4160
    //   4492: iastore
    //   4493: dup
    //   4494: bipush #20
    //   4496: ldc 266240
    //   4498: iastore
    //   4499: dup
    //   4500: bipush #21
    //   4502: ldc 262208
    //   4504: iastore
    //   4505: dup
    //   4506: bipush #22
    //   4508: ldc 268697664
    //   4510: iastore
    //   4511: dup
    //   4512: bipush #23
    //   4514: ldc 268701696
    //   4516: iastore
    //   4517: dup
    //   4518: bipush #24
    //   4520: sipush #4160
    //   4523: iastore
    //   4524: dup
    //   4525: bipush #25
    //   4527: iconst_0
    //   4528: iastore
    //   4529: dup
    //   4530: bipush #26
    //   4532: iconst_0
    //   4533: iastore
    //   4534: dup
    //   4535: bipush #27
    //   4537: ldc 268697664
    //   4539: iastore
    //   4540: dup
    //   4541: bipush #28
    //   4543: ldc 268435520
    //   4545: iastore
    //   4546: dup
    //   4547: bipush #29
    //   4549: ldc 268439552
    //   4551: iastore
    //   4552: dup
    //   4553: bipush #30
    //   4555: ldc 266304
    //   4557: iastore
    //   4558: dup
    //   4559: bipush #31
    //   4561: ldc 262144
    //   4563: iastore
    //   4564: dup
    //   4565: bipush #32
    //   4567: ldc 266304
    //   4569: iastore
    //   4570: dup
    //   4571: bipush #33
    //   4573: ldc 262144
    //   4575: iastore
    //   4576: dup
    //   4577: bipush #34
    //   4579: ldc 268701696
    //   4581: iastore
    //   4582: dup
    //   4583: bipush #35
    //   4585: sipush #4096
    //   4588: iastore
    //   4589: dup
    //   4590: bipush #36
    //   4592: bipush #64
    //   4594: iastore
    //   4595: dup
    //   4596: bipush #37
    //   4598: ldc 268697664
    //   4600: iastore
    //   4601: dup
    //   4602: bipush #38
    //   4604: sipush #4096
    //   4607: iastore
    //   4608: dup
    //   4609: bipush #39
    //   4611: ldc 266304
    //   4613: iastore
    //   4614: dup
    //   4615: bipush #40
    //   4617: ldc 268439552
    //   4619: iastore
    //   4620: dup
    //   4621: bipush #41
    //   4623: bipush #64
    //   4625: iastore
    //   4626: dup
    //   4627: bipush #42
    //   4629: ldc 268435520
    //   4631: iastore
    //   4632: dup
    //   4633: bipush #43
    //   4635: ldc 268697600
    //   4637: iastore
    //   4638: dup
    //   4639: bipush #44
    //   4641: ldc 268697664
    //   4643: iastore
    //   4644: dup
    //   4645: bipush #45
    //   4647: ldc 268435456
    //   4649: iastore
    //   4650: dup
    //   4651: bipush #46
    //   4653: ldc 262144
    //   4655: iastore
    //   4656: dup
    //   4657: bipush #47
    //   4659: ldc 268439616
    //   4661: iastore
    //   4662: dup
    //   4663: bipush #48
    //   4665: iconst_0
    //   4666: iastore
    //   4667: dup
    //   4668: bipush #49
    //   4670: ldc 268701760
    //   4672: iastore
    //   4673: dup
    //   4674: bipush #50
    //   4676: ldc 262208
    //   4678: iastore
    //   4679: dup
    //   4680: bipush #51
    //   4682: ldc 268435520
    //   4684: iastore
    //   4685: dup
    //   4686: bipush #52
    //   4688: ldc 268697600
    //   4690: iastore
    //   4691: dup
    //   4692: bipush #53
    //   4694: ldc 268439552
    //   4696: iastore
    //   4697: dup
    //   4698: bipush #54
    //   4700: ldc 268439616
    //   4702: iastore
    //   4703: dup
    //   4704: bipush #55
    //   4706: iconst_0
    //   4707: iastore
    //   4708: dup
    //   4709: bipush #56
    //   4711: ldc 268701760
    //   4713: iastore
    //   4714: dup
    //   4715: bipush #57
    //   4717: ldc 266240
    //   4719: iastore
    //   4720: dup
    //   4721: bipush #58
    //   4723: ldc 266240
    //   4725: iastore
    //   4726: dup
    //   4727: bipush #59
    //   4729: sipush #4160
    //   4732: iastore
    //   4733: dup
    //   4734: bipush #60
    //   4736: sipush #4160
    //   4739: iastore
    //   4740: dup
    //   4741: bipush #61
    //   4743: ldc 262208
    //   4745: iastore
    //   4746: dup
    //   4747: bipush #62
    //   4749: ldc 268435456
    //   4751: iastore
    //   4752: dup
    //   4753: bipush #63
    //   4755: ldc 268701696
    //   4757: iastore
    //   4758: astore #16
    //   4760: aload #4
    //   4762: arraylength
    //   4763: istore #17
    //   4765: iconst_2
    //   4766: newarray int
    //   4768: astore #18
    //   4770: iload #17
    //   4772: newarray byte
    //   4774: astore #5
    //   4776: iload #17
    //   4778: bipush #8
    //   4780: idiv
    //   4781: istore #19
    //   4783: iconst_0
    //   4784: istore #20
    //   4786: iload #20
    //   4788: iload #19
    //   4790: if_icmpge -> 5708
    //   4793: iload #20
    //   4795: bipush #8
    //   4797: imul
    //   4798: istore #21
    //   4800: iconst_0
    //   4801: istore #22
    //   4803: iload #22
    //   4805: iconst_2
    //   4806: if_icmpge -> 4895
    //   4809: aload #18
    //   4811: iload #22
    //   4813: aload #4
    //   4815: iload #21
    //   4817: iload #22
    //   4819: iconst_4
    //   4820: imul
    //   4821: iadd
    //   4822: baload
    //   4823: sipush #255
    //   4826: iand
    //   4827: bipush #24
    //   4829: ishl
    //   4830: aload #4
    //   4832: iload #21
    //   4834: iload #22
    //   4836: iconst_4
    //   4837: imul
    //   4838: iadd
    //   4839: iconst_1
    //   4840: iadd
    //   4841: baload
    //   4842: sipush #255
    //   4845: iand
    //   4846: bipush #16
    //   4848: ishl
    //   4849: ior
    //   4850: aload #4
    //   4852: iload #21
    //   4854: iload #22
    //   4856: iconst_4
    //   4857: imul
    //   4858: iadd
    //   4859: iconst_2
    //   4860: iadd
    //   4861: baload
    //   4862: sipush #255
    //   4865: iand
    //   4866: bipush #8
    //   4868: ishl
    //   4869: ior
    //   4870: aload #4
    //   4872: iload #21
    //   4874: iload #22
    //   4876: iconst_4
    //   4877: imul
    //   4878: iadd
    //   4879: iconst_3
    //   4880: iadd
    //   4881: baload
    //   4882: sipush #255
    //   4885: iand
    //   4886: ior
    //   4887: iastore
    //   4888: iinc #22, 1
    //   4891: iload_2
    //   4892: ifeq -> 4803
    //   4895: iconst_0
    //   4896: istore #27
    //   4898: aload #18
    //   4900: iconst_0
    //   4901: iaload
    //   4902: istore #25
    //   4904: aload #18
    //   4906: iconst_1
    //   4907: iaload
    //   4908: istore #24
    //   4910: iload #25
    //   4912: iconst_4
    //   4913: iushr
    //   4914: iload #24
    //   4916: ixor
    //   4917: ldc 252645135
    //   4919: iand
    //   4920: istore #23
    //   4922: iload #24
    //   4924: iload #23
    //   4926: ixor
    //   4927: istore #24
    //   4929: iload #25
    //   4931: iload #23
    //   4933: iconst_4
    //   4934: ishl
    //   4935: ixor
    //   4936: istore #25
    //   4938: iload #25
    //   4940: bipush #16
    //   4942: iushr
    //   4943: iload #24
    //   4945: ixor
    //   4946: ldc 65535
    //   4948: iand
    //   4949: istore #23
    //   4951: iload #24
    //   4953: iload #23
    //   4955: ixor
    //   4956: istore #24
    //   4958: iload #25
    //   4960: iload #23
    //   4962: bipush #16
    //   4964: ishl
    //   4965: ixor
    //   4966: istore #25
    //   4968: iload #24
    //   4970: iconst_2
    //   4971: iushr
    //   4972: iload #25
    //   4974: ixor
    //   4975: ldc 858993459
    //   4977: iand
    //   4978: istore #23
    //   4980: iload #25
    //   4982: iload #23
    //   4984: ixor
    //   4985: istore #25
    //   4987: iload #24
    //   4989: iload #23
    //   4991: iconst_2
    //   4992: ishl
    //   4993: ixor
    //   4994: istore #24
    //   4996: iload #24
    //   4998: bipush #8
    //   5000: iushr
    //   5001: iload #25
    //   5003: ixor
    //   5004: ldc 16711935
    //   5006: iand
    //   5007: istore #23
    //   5009: iload #25
    //   5011: iload #23
    //   5013: ixor
    //   5014: istore #25
    //   5016: iload #24
    //   5018: iload #23
    //   5020: bipush #8
    //   5022: ishl
    //   5023: ixor
    //   5024: istore #24
    //   5026: iload #24
    //   5028: iconst_1
    //   5029: ishl
    //   5030: iload #24
    //   5032: bipush #31
    //   5034: iushr
    //   5035: iconst_1
    //   5036: iand
    //   5037: ior
    //   5038: istore #24
    //   5040: iload #25
    //   5042: iload #24
    //   5044: ixor
    //   5045: ldc -1431655766
    //   5047: iand
    //   5048: istore #23
    //   5050: iload #25
    //   5052: iload #23
    //   5054: ixor
    //   5055: istore #25
    //   5057: iload #24
    //   5059: iload #23
    //   5061: ixor
    //   5062: istore #24
    //   5064: iload #25
    //   5066: iconst_1
    //   5067: ishl
    //   5068: iload #25
    //   5070: bipush #31
    //   5072: iushr
    //   5073: iconst_1
    //   5074: iand
    //   5075: ior
    //   5076: istore #25
    //   5078: iconst_0
    //   5079: istore #26
    //   5081: iload #26
    //   5083: bipush #8
    //   5085: if_icmpge -> 5423
    //   5088: iload #24
    //   5090: bipush #28
    //   5092: ishl
    //   5093: iload #24
    //   5095: iconst_4
    //   5096: iushr
    //   5097: ior
    //   5098: istore #23
    //   5100: iload #23
    //   5102: aload #6
    //   5104: iload #27
    //   5106: iinc #27, 1
    //   5109: iaload
    //   5110: ixor
    //   5111: istore #23
    //   5113: aload #15
    //   5115: iload #23
    //   5117: bipush #63
    //   5119: iand
    //   5120: iaload
    //   5121: istore #22
    //   5123: iload #22
    //   5125: aload #13
    //   5127: iload #23
    //   5129: bipush #8
    //   5131: iushr
    //   5132: bipush #63
    //   5134: iand
    //   5135: iaload
    //   5136: ior
    //   5137: istore #22
    //   5139: iload #22
    //   5141: aload #11
    //   5143: iload #23
    //   5145: bipush #16
    //   5147: iushr
    //   5148: bipush #63
    //   5150: iand
    //   5151: iaload
    //   5152: ior
    //   5153: istore #22
    //   5155: iload #22
    //   5157: aload #9
    //   5159: iload #23
    //   5161: bipush #24
    //   5163: iushr
    //   5164: bipush #63
    //   5166: iand
    //   5167: iaload
    //   5168: ior
    //   5169: istore #22
    //   5171: iload #24
    //   5173: aload #6
    //   5175: iload #27
    //   5177: iinc #27, 1
    //   5180: iaload
    //   5181: ixor
    //   5182: istore #23
    //   5184: iload #22
    //   5186: aload #16
    //   5188: iload #23
    //   5190: bipush #63
    //   5192: iand
    //   5193: iaload
    //   5194: ior
    //   5195: istore #22
    //   5197: iload #22
    //   5199: aload #14
    //   5201: iload #23
    //   5203: bipush #8
    //   5205: iushr
    //   5206: bipush #63
    //   5208: iand
    //   5209: iaload
    //   5210: ior
    //   5211: istore #22
    //   5213: iload #22
    //   5215: aload #12
    //   5217: iload #23
    //   5219: bipush #16
    //   5221: iushr
    //   5222: bipush #63
    //   5224: iand
    //   5225: iaload
    //   5226: ior
    //   5227: istore #22
    //   5229: iload #22
    //   5231: aload #10
    //   5233: iload #23
    //   5235: bipush #24
    //   5237: iushr
    //   5238: bipush #63
    //   5240: iand
    //   5241: iaload
    //   5242: ior
    //   5243: istore #22
    //   5245: iload #25
    //   5247: iload #22
    //   5249: ixor
    //   5250: istore #25
    //   5252: iload #25
    //   5254: bipush #28
    //   5256: ishl
    //   5257: iload #25
    //   5259: iconst_4
    //   5260: iushr
    //   5261: ior
    //   5262: istore #23
    //   5264: iload #23
    //   5266: aload #6
    //   5268: iload #27
    //   5270: iinc #27, 1
    //   5273: iaload
    //   5274: ixor
    //   5275: istore #23
    //   5277: aload #15
    //   5279: iload #23
    //   5281: bipush #63
    //   5283: iand
    //   5284: iaload
    //   5285: istore #22
    //   5287: iload #22
    //   5289: aload #13
    //   5291: iload #23
    //   5293: bipush #8
    //   5295: iushr
    //   5296: bipush #63
    //   5298: iand
    //   5299: iaload
    //   5300: ior
    //   5301: istore #22
    //   5303: iload #22
    //   5305: aload #11
    //   5307: iload #23
    //   5309: bipush #16
    //   5311: iushr
    //   5312: bipush #63
    //   5314: iand
    //   5315: iaload
    //   5316: ior
    //   5317: istore #22
    //   5319: iload #22
    //   5321: aload #9
    //   5323: iload #23
    //   5325: bipush #24
    //   5327: iushr
    //   5328: bipush #63
    //   5330: iand
    //   5331: iaload
    //   5332: ior
    //   5333: istore #22
    //   5335: iload #25
    //   5337: aload #6
    //   5339: iload #27
    //   5341: iinc #27, 1
    //   5344: iaload
    //   5345: ixor
    //   5346: istore #23
    //   5348: iload #22
    //   5350: aload #16
    //   5352: iload #23
    //   5354: bipush #63
    //   5356: iand
    //   5357: iaload
    //   5358: ior
    //   5359: istore #22
    //   5361: iload #22
    //   5363: aload #14
    //   5365: iload #23
    //   5367: bipush #8
    //   5369: iushr
    //   5370: bipush #63
    //   5372: iand
    //   5373: iaload
    //   5374: ior
    //   5375: istore #22
    //   5377: iload #22
    //   5379: aload #12
    //   5381: iload #23
    //   5383: bipush #16
    //   5385: iushr
    //   5386: bipush #63
    //   5388: iand
    //   5389: iaload
    //   5390: ior
    //   5391: istore #22
    //   5393: iload #22
    //   5395: aload #10
    //   5397: iload #23
    //   5399: bipush #24
    //   5401: iushr
    //   5402: bipush #63
    //   5404: iand
    //   5405: iaload
    //   5406: ior
    //   5407: istore #22
    //   5409: iload #24
    //   5411: iload #22
    //   5413: ixor
    //   5414: istore #24
    //   5416: iinc #26, 1
    //   5419: iload_2
    //   5420: ifeq -> 5081
    //   5423: iload #24
    //   5425: bipush #31
    //   5427: ishl
    //   5428: iload #24
    //   5430: iconst_1
    //   5431: iushr
    //   5432: ior
    //   5433: istore #24
    //   5435: iload #25
    //   5437: iload #24
    //   5439: ixor
    //   5440: ldc -1431655766
    //   5442: iand
    //   5443: istore #23
    //   5445: iload #25
    //   5447: iload #23
    //   5449: ixor
    //   5450: istore #25
    //   5452: iload #24
    //   5454: iload #23
    //   5456: ixor
    //   5457: istore #24
    //   5459: iload #25
    //   5461: bipush #31
    //   5463: ishl
    //   5464: iload #25
    //   5466: iconst_1
    //   5467: iushr
    //   5468: ior
    //   5469: istore #25
    //   5471: iload #25
    //   5473: bipush #8
    //   5475: iushr
    //   5476: iload #24
    //   5478: ixor
    //   5479: ldc 16711935
    //   5481: iand
    //   5482: istore #23
    //   5484: iload #24
    //   5486: iload #23
    //   5488: ixor
    //   5489: istore #24
    //   5491: iload #25
    //   5493: iload #23
    //   5495: bipush #8
    //   5497: ishl
    //   5498: ixor
    //   5499: istore #25
    //   5501: iload #25
    //   5503: iconst_2
    //   5504: iushr
    //   5505: iload #24
    //   5507: ixor
    //   5508: ldc 858993459
    //   5510: iand
    //   5511: istore #23
    //   5513: iload #24
    //   5515: iload #23
    //   5517: ixor
    //   5518: istore #24
    //   5520: iload #25
    //   5522: iload #23
    //   5524: iconst_2
    //   5525: ishl
    //   5526: ixor
    //   5527: istore #25
    //   5529: iload #24
    //   5531: bipush #16
    //   5533: iushr
    //   5534: iload #25
    //   5536: ixor
    //   5537: ldc 65535
    //   5539: iand
    //   5540: istore #23
    //   5542: iload #25
    //   5544: iload #23
    //   5546: ixor
    //   5547: istore #25
    //   5549: iload #24
    //   5551: iload #23
    //   5553: bipush #16
    //   5555: ishl
    //   5556: ixor
    //   5557: istore #24
    //   5559: iload #24
    //   5561: iconst_4
    //   5562: iushr
    //   5563: iload #25
    //   5565: ixor
    //   5566: ldc 252645135
    //   5568: iand
    //   5569: istore #23
    //   5571: iload #25
    //   5573: iload #23
    //   5575: ixor
    //   5576: istore #25
    //   5578: iload #24
    //   5580: iload #23
    //   5582: iconst_4
    //   5583: ishl
    //   5584: ixor
    //   5585: istore #24
    //   5587: aload #18
    //   5589: iconst_0
    //   5590: iload #24
    //   5592: iastore
    //   5593: aload #18
    //   5595: iconst_1
    //   5596: iload #25
    //   5598: iastore
    //   5599: iload #20
    //   5601: bipush #8
    //   5603: imul
    //   5604: istore #28
    //   5606: iconst_0
    //   5607: istore #29
    //   5609: iload #29
    //   5611: iconst_2
    //   5612: if_icmpge -> 5701
    //   5615: aload #5
    //   5617: iload #28
    //   5619: iload #29
    //   5621: iconst_4
    //   5622: imul
    //   5623: iadd
    //   5624: aload #18
    //   5626: iload #29
    //   5628: iaload
    //   5629: bipush #24
    //   5631: iushr
    //   5632: i2b
    //   5633: bastore
    //   5634: aload #5
    //   5636: iload #28
    //   5638: iload #29
    //   5640: iconst_4
    //   5641: imul
    //   5642: iadd
    //   5643: iconst_1
    //   5644: iadd
    //   5645: aload #18
    //   5647: iload #29
    //   5649: iaload
    //   5650: bipush #16
    //   5652: iushr
    //   5653: i2b
    //   5654: bastore
    //   5655: aload #5
    //   5657: iload #28
    //   5659: iload #29
    //   5661: iconst_4
    //   5662: imul
    //   5663: iadd
    //   5664: iconst_2
    //   5665: iadd
    //   5666: aload #18
    //   5668: iload #29
    //   5670: iaload
    //   5671: bipush #8
    //   5673: iushr
    //   5674: i2b
    //   5675: bastore
    //   5676: aload #5
    //   5678: iload #28
    //   5680: iload #29
    //   5682: iconst_4
    //   5683: imul
    //   5684: iadd
    //   5685: iconst_3
    //   5686: iadd
    //   5687: aload #18
    //   5689: iload #29
    //   5691: iaload
    //   5692: i2b
    //   5693: bastore
    //   5694: iinc #29, 1
    //   5697: iload_2
    //   5698: ifeq -> 5609
    //   5701: iinc #20, 1
    //   5704: iload_2
    //   5705: ifeq -> 4786
    //   5708: new java/math/BigInteger
    //   5711: dup
    //   5712: aload #5
    //   5714: invokespecial <init> : ([B)V
    //   5717: invokevirtual abs : ()Ljava/math/BigInteger;
    //   5720: putstatic burp/Zg_5.ZA : Ljava/lang/Object;
    //   5723: sipush #-32699
    //   5726: sipush #-25377
    //   5729: invokestatic a : (II)Ljava/lang/String;
    //   5732: iconst_1
    //   5733: ldc burp/Zgr1
    //   5735: invokevirtual getClassLoader : ()Ljava/lang/ClassLoader;
    //   5738: invokestatic forName : (Ljava/lang/String;ZLjava/lang/ClassLoader;)Ljava/lang/Class;
    //   5741: invokevirtual getDeclaredFields : ()[Ljava/lang/reflect/Field;
    //   5744: astore #4
    //   5746: aload #4
    //   5748: arraylength
    //   5749: istore #5
    //   5751: iconst_0
    //   5752: istore #6
    //   5754: iload #6
    //   5756: iload #5
    //   5758: if_icmpge -> 5896
    //   5761: aload #4
    //   5763: iload #6
    //   5765: aaload
    //   5766: astore #7
    //   5768: aload #7
    //   5770: invokevirtual getModifiers : ()I
    //   5773: invokestatic isStatic : (I)Z
    //   5776: ifne -> 5786
    //   5779: goto -> 5889
    //   5782: invokestatic a : (Ljava/lang/Throwable;)Ljava/lang/Throwable;
    //   5785: athrow
    //   5786: aload #7
    //   5788: invokevirtual getType : ()Ljava/lang/Class;
    //   5791: astore #8
    //   5793: aload #8
    //   5795: ifnull -> 5876
    //   5798: aload #8
    //   5800: invokevirtual isPrimitive : ()Z
    //   5803: ifne -> 5876
    //   5806: goto -> 5813
    //   5809: invokestatic a : (Ljava/lang/Throwable;)Ljava/lang/Throwable;
    //   5812: athrow
    //   5813: aload #8
    //   5815: invokevirtual getPackage : ()Ljava/lang/Package;
    //   5818: ifnull -> 5876
    //   5821: goto -> 5828
    //   5824: invokestatic a : (Ljava/lang/Throwable;)Ljava/lang/Throwable;
    //   5827: athrow
    //   5828: aload #8
    //   5830: invokevirtual getPackage : ()Ljava/lang/Package;
    //   5833: invokevirtual getName : ()Ljava/lang/String;
    //   5836: ifnull -> 5876
    //   5839: goto -> 5846
    //   5842: invokestatic a : (Ljava/lang/Throwable;)Ljava/lang/Throwable;
    //   5845: athrow
    //   5846: aload #8
    //   5848: invokevirtual getPackage : ()Ljava/lang/Package;
    //   5851: invokevirtual getName : ()Ljava/lang/String;
    //   5854: sipush #-32700
    //   5857: sipush #12393
    //   5860: invokestatic a : (II)Ljava/lang/String;
    //   5863: invokevirtual startsWith : (Ljava/lang/String;)Z
    //   5866: ifne -> 5876
    //   5869: goto -> 5876
    //   5872: invokestatic a : (Ljava/lang/Throwable;)Ljava/lang/Throwable;
    //   5875: athrow
    //   5876: aload #7
    //   5878: iconst_1
    //   5879: invokevirtual setAccessible : (Z)V
    //   5882: aload #7
    //   5884: aconst_null
    //   5885: invokevirtual get : (Ljava/lang/Object;)Ljava/lang/Object;
    //   5888: pop
    //   5889: iinc #6, 1
    //   5892: iload_2
    //   5893: ifeq -> 5754
    //   5896: sipush #-32701
    //   5899: sipush #23584
    //   5902: invokestatic a : (II)Ljava/lang/String;
    //   5905: invokestatic forName : (Ljava/lang/String;)Ljava/lang/Class;
    //   5908: invokevirtual getDeclaredMethods : ()[Ljava/lang/reflect/Method;
    //   5911: astore #4
    //   5913: aload #4
    //   5915: arraylength
    //   5916: istore #5
    //   5918: iconst_0
    //   5919: istore #6
    //   5921: iload #6
    //   5923: iload #5
    //   5925: if_icmpge -> 6058
    //   5928: aload #4
    //   5930: iload #6
    //   5932: aaload
    //   5933: astore #7
    //   5935: aload #7
    //   5937: invokevirtual getParameterTypes : ()[Ljava/lang/Class;
    //   5940: pop
    //   5941: aload #7
    //   5943: invokevirtual getModifiers : ()I
    //   5946: invokestatic isStatic : (I)Z
    //   5949: ifeq -> 6044
    //   5952: aload #7
    //   5954: invokevirtual getParameterTypes : ()[Ljava/lang/Class;
    //   5957: arraylength
    //   5958: iconst_2
    //   5959: if_icmpne -> 6044
    //   5962: goto -> 5969
    //   5965: invokestatic a : (Ljava/lang/Throwable;)Ljava/lang/Throwable;
    //   5968: athrow
    //   5969: aload #7
    //   5971: invokevirtual getReturnType : ()Ljava/lang/Class;
    //   5974: getstatic java/lang/Void.TYPE : Ljava/lang/Class;
    //   5977: invokevirtual equals : (Ljava/lang/Object;)Z
    //   5980: ifeq -> 6044
    //   5983: goto -> 5990
    //   5986: invokestatic a : (Ljava/lang/Throwable;)Ljava/lang/Throwable;
    //   5989: athrow
    //   5990: aload #7
    //   5992: iconst_1
    //   5993: invokevirtual setAccessible : (Z)V
    //   5996: aload #7
    //   5998: aconst_null
    //   5999: iconst_2
    //   6000: anewarray java/lang/Object
    //   6003: dup
    //   6004: iconst_0
    //   6005: aload_0
    //   6006: aastore
    //   6007: dup
    //   6008: iconst_1
    //   6009: aload_1
    //   6010: ifnonnull -> 6028
    //   6013: goto -> 6020
    //   6016: invokestatic a : (Ljava/lang/Throwable;)Ljava/lang/Throwable;
    //   6019: athrow
    //   6020: aload_1
    //   6021: goto -> 6035
    //   6024: invokestatic a : (Ljava/lang/Throwable;)Ljava/lang/Throwable;
    //   6027: athrow
    //   6028: aload_1
    //   6029: checkcast [B
    //   6032: invokevirtual clone : ()Ljava/lang/Object;
    //   6035: aastore
    //   6036: invokevirtual invoke : (Ljava/lang/Object;[Ljava/lang/Object;)Ljava/lang/Object;
    //   6039: pop
    //   6040: iload_2
    //   6041: ifeq -> 6058
    //   6044: iinc #6, 1
    //   6047: iload_2
    //   6048: ifeq -> 5921
    //   6051: goto -> 6058
    //   6054: invokestatic a : (Ljava/lang/Throwable;)Ljava/lang/Throwable;
    //   6057: athrow
    //   6058: getstatic burp/Zqp.ZX : Ljava/lang/String;
    //   6061: getstatic burp/Zrof.ZB : Ljava/lang/Object;
    //   6064: checkcast java/math/BigInteger
    //   6067: invokevirtual intValue : ()I
    //   6070: bipush #32
    //   6072: irem
    //   6073: invokestatic abs : (I)I
    //   6076: invokevirtual charAt : (I)C
    //   6079: getstatic burp/Zest.Zd : Ljava/lang/String;
    //   6082: getstatic burp/Zztk.Za : Ljava/lang/Object;
    //   6085: checkcast java/math/BigInteger
    //   6088: invokevirtual intValue : ()I
    //   6091: bipush #32
    //   6093: irem
    //   6094: invokestatic abs : (I)I
    //   6097: invokevirtual charAt : (I)C
    //   6100: if_icmpgt -> 6207
    //   6103: getstatic burp/Zmx6.ZG : Ljava/lang/String;
    //   6106: getstatic burp/Zlx5.Zp : Ljava/lang/Object;
    //   6109: checkcast java/math/BigInteger
    //   6112: invokevirtual intValue : ()I
    //   6115: bipush #32
    //   6117: irem
    //   6118: invokestatic abs : (I)I
    //   6121: invokevirtual charAt : (I)C
    //   6124: getstatic burp/Zera.Zn : Ljava/lang/String;
    //   6127: getstatic burp/Zvo3.Ze : Ljava/lang/Object;
    //   6130: checkcast java/math/BigInteger
    //   6133: invokevirtual intValue : ()I
    //   6136: bipush #32
    //   6138: irem
    //   6139: invokestatic abs : (I)I
    //   6142: invokevirtual charAt : (I)C
    //   6145: if_icmpgt -> 6207
    //   6148: goto -> 6155
    //   6151: invokestatic a : (Ljava/lang/Throwable;)Ljava/lang/Throwable;
    //   6154: athrow
    //   6155: getstatic burp/Zztn.ZY : Ljava/lang/String;
    //   6158: getstatic burp/Zram.ZF : Ljava/lang/Object;
    //   6161: checkcast java/math/BigInteger
    //   6164: invokevirtual intValue : ()I
    //   6167: bipush #32
    //   6169: irem
    //   6170: invokestatic abs : (I)I
    //   6173: invokevirtual charAt : (I)C
    //   6176: getstatic burp/Zeoy.ZS : Ljava/lang/String;
    //   6179: getstatic burp/Zgva.Zr : Ljava/lang/Object;
    //   6182: checkcast java/math/BigInteger
    //   6185: invokevirtual intValue : ()I
    //   6188: bipush #32
    //   6190: irem
    //   6191: invokestatic abs : (I)I
    //   6194: invokevirtual charAt : (I)C
    //   6197: if_icmpgt -> 6215
    //   6200: goto -> 6207
    //   6203: invokestatic a : (Ljava/lang/Throwable;)Ljava/lang/Throwable;
    //   6206: athrow
    //   6207: iconst_1
    //   6208: goto -> 6216
    //   6211: invokestatic a : (Ljava/lang/Throwable;)Ljava/lang/Throwable;
    //   6214: athrow
    //   6215: iconst_0
    //   6216: ireturn
    //   6217: astore_3
    //   6218: new java/lang/Exception
    //   6221: dup
    //   6222: aload_3
    //   6223: invokevirtual getMessage : ()Ljava/lang/String;
    //   6226: invokespecial <init> : (Ljava/lang/String;)V
    //   6229: athrow
    // Exception table:
    //   from	to	target	type
    //   4	6216	6217	java/lang/Throwable
    //   22	198	201	java/lang/Throwable
    //   168	235	238	java/lang/Throwable
    //   205	272	275	java/lang/Throwable
    //   242	309	312	java/lang/Throwable
    //   279	346	349	java/lang/Throwable
    //   316	383	386	java/lang/Throwable
    //   353	420	423	java/lang/Throwable
    //   390	457	460	java/lang/Throwable
    //   427	494	497	java/lang/Throwable
    //   464	531	534	java/lang/Throwable
    //   501	568	571	java/lang/Throwable
    //   538	605	608	java/lang/Throwable
    //   575	642	645	java/lang/Throwable
    //   612	679	682	java/lang/Throwable
    //   649	716	719	java/lang/Throwable
    //   686	753	756	java/lang/Throwable
    //   723	790	793	java/lang/Throwable
    //   760	827	830	java/lang/Throwable
    //   797	864	867	java/lang/Throwable
    //   834	901	904	java/lang/Throwable
    //   871	938	941	java/lang/Throwable
    //   908	975	978	java/lang/Throwable
    //   945	1012	1015	java/lang/Throwable
    //   982	1049	1052	java/lang/Throwable
    //   1019	1086	1089	java/lang/Throwable
    //   1056	1123	1126	java/lang/Throwable
    //   1093	1160	1163	java/lang/Throwable
    //   1130	1197	1200	java/lang/Throwable
    //   1167	1234	1237	java/lang/Throwable
    //   1204	1271	1274	java/lang/Throwable
    //   1241	1308	1311	java/lang/Throwable
    //   1278	1341	1344	java/lang/Throwable
    //   5768	5782	5782	java/lang/Throwable
    //   5793	5806	5809	java/lang/Throwable
    //   5798	5821	5824	java/lang/Throwable
    //   5813	5839	5842	java/lang/Throwable
    //   5828	5869	5872	java/lang/Throwable
    //   5935	5962	5965	java/lang/Throwable
    //   5952	5983	5986	java/lang/Throwable
    //   5969	6013	6016	java/lang/Throwable
    //   5990	6024	6024	java/lang/Throwable
    //   6035	6051	6054	java/lang/Throwable
    //   6058	6148	6151	java/lang/Throwable
    //   6103	6200	6203	java/lang/Throwable
    //   6155	6211	6211	java/lang/Throwable
  }
  
  static void Zt(Object[] paramArrayOfObject, Object paramObject) throws Throwable {}
  
  static void Zn(Object paramObject) {
    Zkm0.ZL = a(-32697, 5947);
    Zkm0.ZI = new BigInteger(a(-32702, -21739));
    boolean bool = Zt2e.ZN();
    try {
      try {
        if (Zlhq.Zl.charAt(Math.abs(((BigInteger)Zr48.ZZ).intValue() % 32)) <= Ze69.ZA.charAt(Math.abs(((BigInteger)Zsf7.Zg).intValue() % 32))) {
          try {
            Zz0w.ZG(Class.forName(a(-32703, -11812)));
            if (!bool)
              Zshq.Zf(Class.forName(a(-32704, -30040))); 
          } catch (Throwable throwable) {
            throw a(null);
          } 
          return;
        } 
      } catch (Throwable throwable) {
        throw a(null);
      } 
      Zshq.Zf(Class.forName(a(-32704, -30040)));
    } catch (Throwable throwable) {}
  }
  
  static {
    // Byte code:
    //   0: bipush #8
    //   2: anewarray java/lang/String
    //   5: astore #5
    //   7: iconst_0
    //   8: istore_3
    //   9: ldc '\\t|v I4  [W:`08 _!Vc{\GSn Md\\t}5lo\\tr'
    //   11: dup
    //   12: astore_2
    //   13: invokevirtual length : ()I
    //   16: istore #4
    //   18: iconst_4
    //   19: istore_1
    //   20: iconst_m1
    //   21: istore_0
    //   22: bipush #60
    //   24: iinc #0, 1
    //   27: aload_2
    //   28: iload_0
    //   29: dup
    //   30: iload_1
    //   31: iadd
    //   32: invokevirtual substring : (II)Ljava/lang/String;
    //   35: iconst_m1
    //   36: goto -> 142
    //   39: aload #5
    //   41: swap
    //   42: iload_3
    //   43: iinc #3, 1
    //   46: swap
    //   47: aastore
    //   48: iload_0
    //   49: iload_1
    //   50: iadd
    //   51: dup
    //   52: istore_0
    //   53: iload #4
    //   55: if_icmpge -> 67
    //   58: aload_2
    //   59: iload_0
    //   60: invokevirtual charAt : (I)C
    //   63: istore_1
    //   64: goto -> 22
    //   67: ldc 'sa70bL81i\\r5*6?BTe=#}#V:xH=o9V5AU!x\\tMl]g'
    //   69: dup
    //   70: astore_2
    //   71: invokevirtual length : ()I
    //   74: istore #4
    //   76: bipush #77
    //   78: istore_1
    //   79: iconst_m1
    //   80: istore_0
    //   81: bipush #21
    //   83: iinc #0, 1
    //   86: aload_2
    //   87: iload_0
    //   88: dup
    //   89: iload_1
    //   90: iadd
    //   91: invokevirtual substring : (II)Ljava/lang/String;
    //   94: iconst_0
    //   95: goto -> 142
    //   98: aload #5
    //   100: swap
    //   101: iload_3
    //   102: iinc #3, 1
    //   105: swap
    //   106: aastore
    //   107: iload_0
    //   108: iload_1
    //   109: iadd
    //   110: dup
    //   111: istore_0
    //   112: iload #4
    //   114: if_icmpge -> 126
    //   117: aload_2
    //   118: iload_0
    //   119: invokevirtual charAt : (I)C
    //   122: istore_1
    //   123: goto -> 81
    //   126: aload #5
    //   128: putstatic burp/Zl39.a : [Ljava/lang/String;
    //   131: bipush #8
    //   133: anewarray java/lang/String
    //   136: putstatic burp/Zl39.b : [Ljava/lang/String;
    //   139: goto -> 300
    //   142: dup_x2
    //   143: pop
    //   144: invokevirtual toCharArray : ()[C
    //   147: dup_x1
    //   148: arraylength
    //   149: dup_x2
    //   150: pop
    //   151: iconst_0
    //   152: istore #6
    //   154: dup2_x1
    //   155: pop2
    //   156: dup_x2
    //   157: iconst_1
    //   158: if_icmpgt -> 260
    //   161: dup2
    //   162: swap
    //   163: iload #6
    //   165: dup2_x1
    //   166: caload
    //   167: swap
    //   168: iload #6
    //   170: bipush #7
    //   172: irem
    //   173: tableswitch default -> 242, 0 -> 212, 1 -> 217, 2 -> 222, 3 -> 227, 4 -> 232, 5 -> 237
    //   212: bipush #75
    //   214: goto -> 244
    //   217: bipush #54
    //   219: goto -> 244
    //   222: bipush #77
    //   224: goto -> 244
    //   227: bipush #31
    //   229: goto -> 244
    //   232: bipush #39
    //   234: goto -> 244
    //   237: bipush #88
    //   239: goto -> 244
    //   242: bipush #125
    //   244: ixor
    //   245: ixor
    //   246: i2c
    //   247: castore
    //   248: iinc #6, 1
    //   251: dup
    //   252: ifne -> 260
    //   255: dup2
    //   256: dup_x1
    //   257: goto -> 165
    //   260: dup2_x1
    //   261: pop2
    //   262: dup_x2
    //   263: iload #6
    //   265: if_icmpgt -> 161
    //   268: pop
    //   269: new java/lang/String
    //   272: dup_x1
    //   273: swap
    //   274: invokespecial <init> : ([C)V
    //   277: invokevirtual intern : ()Ljava/lang/String;
    //   280: swap
    //   281: pop
    //   282: swap
    //   283: tableswitch default -> 39, 0 -> 98
    //   300: sipush #-32698
    //   303: sipush #22926
    //   306: invokestatic a : (II)Ljava/lang/String;
    //   309: putstatic burp/Zl39.ZI : Ljava/lang/String;
    //   312: new java/math/BigInteger
    //   315: dup
    //   316: bipush #32
    //   318: newarray byte
    //   320: dup
    //   321: iconst_0
    //   322: bipush #124
    //   324: bastore
    //   325: dup
    //   326: iconst_1
    //   327: bipush #-50
    //   329: bastore
    //   330: dup
    //   331: iconst_2
    //   332: bipush #93
    //   334: bastore
    //   335: dup
    //   336: iconst_3
    //   337: bipush #-27
    //   339: bastore
    //   340: dup
    //   341: iconst_4
    //   342: bipush #-24
    //   344: bastore
    //   345: dup
    //   346: iconst_5
    //   347: bipush #46
    //   349: bastore
    //   350: dup
    //   351: bipush #6
    //   353: bipush #-87
    //   355: bastore
    //   356: dup
    //   357: bipush #7
    //   359: bipush #-110
    //   361: bastore
    //   362: dup
    //   363: bipush #8
    //   365: bipush #94
    //   367: bastore
    //   368: dup
    //   369: bipush #9
    //   371: bipush #71
    //   373: bastore
    //   374: dup
    //   375: bipush #10
    //   377: bipush #-37
    //   379: bastore
    //   380: dup
    //   381: bipush #11
    //   383: bipush #77
    //   385: bastore
    //   386: dup
    //   387: bipush #12
    //   389: bipush #-79
    //   391: bastore
    //   392: dup
    //   393: bipush #13
    //   395: bipush #120
    //   397: bastore
    //   398: dup
    //   399: bipush #14
    //   401: bipush #-47
    //   403: bastore
    //   404: dup
    //   405: bipush #15
    //   407: bipush #-76
    //   409: bastore
    //   410: dup
    //   411: bipush #16
    //   413: bipush #18
    //   415: bastore
    //   416: dup
    //   417: bipush #17
    //   419: bipush #-80
    //   421: bastore
    //   422: dup
    //   423: bipush #18
    //   425: bipush #-45
    //   427: bastore
    //   428: dup
    //   429: bipush #19
    //   431: bipush #-37
    //   433: bastore
    //   434: dup
    //   435: bipush #20
    //   437: bipush #-124
    //   439: bastore
    //   440: dup
    //   441: bipush #21
    //   443: bipush #26
    //   445: bastore
    //   446: dup
    //   447: bipush #22
    //   449: bipush #-27
    //   451: bastore
    //   452: dup
    //   453: bipush #23
    //   455: bipush #-46
    //   457: bastore
    //   458: dup
    //   459: bipush #24
    //   461: bipush #-122
    //   463: bastore
    //   464: dup
    //   465: bipush #25
    //   467: bipush #-115
    //   469: bastore
    //   470: dup
    //   471: bipush #26
    //   473: bipush #58
    //   475: bastore
    //   476: dup
    //   477: bipush #27
    //   479: bipush #-102
    //   481: bastore
    //   482: dup
    //   483: bipush #28
    //   485: bipush #96
    //   487: bastore
    //   488: dup
    //   489: bipush #29
    //   491: bipush #103
    //   493: bastore
    //   494: dup
    //   495: bipush #30
    //   497: bipush #-44
    //   499: bastore
    //   500: dup
    //   501: bipush #31
    //   503: bipush #-80
    //   505: bastore
    //   506: invokespecial <init> : ([B)V
    //   509: putstatic burp/Zl39.ZA : Ljava/lang/Object;
    //   512: return
  }
  
  private static Throwable a(Throwable paramThrowable) {
    return paramThrowable;
  }
  
  private static String a(int paramInt1, int paramInt2) {
    int i = (paramInt1 ^ 0xFFFF8044) & 0xFFFF;
    if (b[i] == null) {
      char[] arrayOfChar = a[i].toCharArray();
      switch (arrayOfChar[0] & 0xFF) {
        case 0:
        
        case 1:
        
        case 2:
        
        case 3:
        
        case 4:
        
        case 5:
        
        case 6:
        
        case 7:
        
        case 8:
        
        case 9:
        
        case 10:
        
        case 11:
        
        case 12:
        
        case 13:
        
        case 14:
        
        case 15:
        
        case 16:
        
        case 17:
        
        case 18:
        
        case 19:
        
        case 20:
        
        case 21:
        
        case 22:
        
        case 23:
        
        case 24:
        
        case 25:
        
        case 26:
        
        case 27:
        
        case 28:
        
        case 29:
        
        case 30:
        
        case 31:
        
        case 32:
        
        case 33:
        
        case 34:
        
        case 35:
        
        case 36:
        
        case 37:
        
        case 38:
        
        case 39:
        
        case 40:
        
        case 41:
        
        case 42:
        
        case 43:
        
        case 44:
        
        case 45:
        
        case 46:
        
        case 47:
        
        case 48:
        
        case 49:
        
        case 50:
        
        case 51:
        
        case 52:
        
        case 53:
        
        case 54:
        
        case 55:
        
        case 56:
        
        case 57:
        
        case 58:
        
        case 59:
        
        case 60:
        
        case 61:
        
        case 62:
        
        case 63:
        
        case 64:
        
        case 65:
        
        case 66:
        
        case 67:
        
        case 68:
        
        case 69:
        
        case 70:
        
        case 71:
        
        case 72:
        
        case 73:
        
        case 74:
        
        case 75:
        
        case 76:
        
        case 77:
        
        case 78:
        
        case 79:
        
        case 80:
        
        case 81:
        
        case 82:
        
        case 83:
        
        case 84:
        
        case 85:
        
        case 86:
        
        case 87:
        
        case 88:
        
        case 89:
        
        case 90:
        
        case 91:
        
        case 92:
        
        case 93:
        
        case 94:
        
        case 95:
        
        case 96:
        
        case 97:
        
        case 98:
        
        case 99:
        
        case 100:
        
        case 101:
        
        case 102:
        
        case 103:
        
        case 104:
        
        case 105:
        
        case 106:
        
        case 107:
        
        case 108:
        
        case 109:
        
        case 110:
        
        case 111:
        
        case 112:
        
        case 113:
        
        case 114:
        
        case 115:
        
        case 116:
        
        case 117:
        
        case 118:
        
        case 119:
        
        case 120:
        
        case 121:
        
        case 122:
        
        case 123:
        
        case 124:
        
        case 125:
        
        case 126:
        
        case 127:
        
        case 128:
        
        case 129:
        
        case 130:
        
        case 131:
        
        case 132:
        
        case 133:
        
        case 134:
        
        case 135:
        
        case 136:
        
        case 137:
        
        case 138:
        
        case 139:
        
        case 140:
        
        case 141:
        
        case 142:
        
        case 143:
        
        case 144:
        
        case 145:
        
        case 146:
        
        case 147:
        
        case 148:
        
        case 149:
        
        case 150:
        
        case 151:
        
        case 152:
        
        case 153:
        
        case 154:
        
        case 155:
        
        case 156:
        
        case 157:
        
        case 158:
        
        case 159:
        
        case 160:
        
        case 161:
        
        case 162:
        
        case 163:
        
        case 164:
        
        case 165:
        
        case 166:
        
        case 167:
        
        case 168:
        
        case 169:
        
        case 170:
        
        case 171:
        
        case 172:
        
        case 173:
        
        case 174:
        
        case 175:
        
        case 176:
        
        case 177:
        
        case 178:
        
        case 179:
        
        case 180:
        
        case 181:
        
        case 182:
        
        case 183:
        
        case 184:
        
        case 185:
        
        case 186:
        
        case 187:
        
        case 188:
        
        case 189:
        
        case 190:
        
        case 191:
        
        case 192:
        
        case 193:
        
        case 194:
        
        case 195:
        
        case 196:
        
        case 197:
        
        case 198:
        
        case 199:
        
        case 200:
        
        case 201:
        
        case 202:
        
        case 203:
        
        case 204:
        
        case 205:
        
        case 206:
        
        case 207:
        
        case 208:
        
        case 209:
        
        case 210:
        
        case 211:
        
        case 212:
        
        case 213:
        
        case 214:
        
        case 215:
        
        case 216:
        
        case 217:
        
        case 218:
        
        case 219:
        
        case 220:
        
        case 221:
        
        case 222:
        
        case 223:
        
        case 224:
        
        case 225:
        
        case 226:
        
        case 227:
        
        case 228:
        
        case 229:
        
        case 230:
        
        case 231:
        
        case 232:
        
        case 233:
        
        case 234:
        
        case 235:
        
        case 236:
        
        case 237:
        
        case 238:
        
        case 239:
        
        case 240:
        
        case 241:
        
        case 242:
        
        case 243:
        
        case 244:
        
        case 245:
        
        case 246:
        
        case 247:
        
        case 248:
        
        case 249:
        
        case 250:
        
        case 251:
        
        case 252:
        
        case 253:
        
        case 254:
        
        default:
          break;
      } 
      char c = '';
      int j = (paramInt2 & 0xFF) - c;
      if (j < 0)
        j += 256; 
      int k = ((paramInt2 & 0xFFFF) >>> 8) - c;
      if (k < 0)
        k += 256; 
      for (byte b = 0; b < arrayOfChar.length; b++) {
        int m = b % 2;
        if (m == 0) {
          arrayOfChar[b] = (char)(arrayOfChar[b] ^ j);
          j = ((j >>> 3 | j << 5) ^ arrayOfChar[b]) & 0xFF;
        } else {
          arrayOfChar[b] = (char)(arrayOfChar[b] ^ k);
          k = ((k >>> 3 | k << 5) ^ arrayOfChar[b]) & 0xFF;
        } 
      } 
      b[i] = (new String(arrayOfChar)).intern();
    } 
    return b[i];
  }
}


/* Location:              C:\Program Files\BurpSuitePro\burpsuite_pro.jar!\burp\Zl39.class
 * Java compiler version: 21 (65.0)
 * JD-Core Version:       1.1.3
 */