package burp;

import java.math.BigInteger;

class Zl3j extends ClassLoader {
  static String Zr;
  
  static Object ZY;
  
  private static final String[] a;
  
  private static final String[] b;
  
  static boolean Zc(Object[] paramArrayOfObject, Object paramObject) throws Throwable {
    // Byte code:
    //   0: invokestatic ZN : ()Z
    //   3: istore_2
    //   4: new java/lang/StringBuilder
    //   7: dup
    //   8: invokespecial <init> : ()V
    //   11: astore_3
    //   12: iconst_0
    //   13: istore #4
    //   15: iload #4
    //   17: bipush #32
    //   19: if_icmpge -> 1355
    //   22: iload #4
    //   24: tableswitch default -> 1348, 0 -> 168, 1 -> 205, 2 -> 242, 3 -> 279, 4 -> 316, 5 -> 353, 6 -> 390, 7 -> 427, 8 -> 464, 9 -> 501, 10 -> 538, 11 -> 575, 12 -> 612, 13 -> 649, 14 -> 686, 15 -> 723, 16 -> 760, 17 -> 797, 18 -> 834, 19 -> 871, 20 -> 908, 21 -> 945, 22 -> 982, 23 -> 1019, 24 -> 1056, 25 -> 1093, 26 -> 1130, 27 -> 1167, 28 -> 1204, 29 -> 1241, 30 -> 1278, 31 -> 1315
    //   168: aload_3
    //   169: getstatic burp/Zttd.Ze : Ljava/lang/String;
    //   172: getstatic burp/Zdv.Zw : Ljava/lang/Object;
    //   175: checkcast java/math/BigInteger
    //   178: invokevirtual intValue : ()I
    //   181: bipush #32
    //   183: irem
    //   184: invokestatic abs : (I)I
    //   187: invokevirtual charAt : (I)C
    //   190: invokevirtual append : (C)Ljava/lang/StringBuilder;
    //   193: pop
    //   194: iload_2
    //   195: ifne -> 1348
    //   198: goto -> 205
    //   201: invokestatic a : (Ljava/lang/Throwable;)Ljava/lang/Throwable;
    //   204: athrow
    //   205: aload_3
    //   206: getstatic burp/Zr14.ZL : Ljava/lang/String;
    //   209: getstatic burp/Zld5.ZX : Ljava/lang/Object;
    //   212: checkcast java/math/BigInteger
    //   215: invokevirtual intValue : ()I
    //   218: bipush #32
    //   220: irem
    //   221: invokestatic abs : (I)I
    //   224: invokevirtual charAt : (I)C
    //   227: invokevirtual append : (C)Ljava/lang/StringBuilder;
    //   230: pop
    //   231: iload_2
    //   232: ifne -> 1348
    //   235: goto -> 242
    //   238: invokestatic a : (Ljava/lang/Throwable;)Ljava/lang/Throwable;
    //   241: athrow
    //   242: aload_3
    //   243: getstatic burp/Zt0m.ZH : Ljava/lang/String;
    //   246: getstatic burp/Zlo0.Zu : Ljava/lang/Object;
    //   249: checkcast java/math/BigInteger
    //   252: invokevirtual intValue : ()I
    //   255: bipush #32
    //   257: irem
    //   258: invokestatic abs : (I)I
    //   261: invokevirtual charAt : (I)C
    //   264: invokevirtual append : (C)Ljava/lang/StringBuilder;
    //   267: pop
    //   268: iload_2
    //   269: ifne -> 1348
    //   272: goto -> 279
    //   275: invokestatic a : (Ljava/lang/Throwable;)Ljava/lang/Throwable;
    //   278: athrow
    //   279: aload_3
    //   280: getstatic burp/Zrwp.ZS : Ljava/lang/String;
    //   283: getstatic burp/Zm1d.ZS : Ljava/lang/Object;
    //   286: checkcast java/math/BigInteger
    //   289: invokevirtual intValue : ()I
    //   292: bipush #32
    //   294: irem
    //   295: invokestatic abs : (I)I
    //   298: invokevirtual charAt : (I)C
    //   301: invokevirtual append : (C)Ljava/lang/StringBuilder;
    //   304: pop
    //   305: iload_2
    //   306: ifne -> 1348
    //   309: goto -> 316
    //   312: invokestatic a : (Ljava/lang/Throwable;)Ljava/lang/Throwable;
    //   315: athrow
    //   316: aload_3
    //   317: getstatic burp/Zgu4.Za : Ljava/lang/String;
    //   320: getstatic burp/Zxc0.Zl : Ljava/lang/Object;
    //   323: checkcast java/math/BigInteger
    //   326: invokevirtual intValue : ()I
    //   329: bipush #32
    //   331: irem
    //   332: invokestatic abs : (I)I
    //   335: invokevirtual charAt : (I)C
    //   338: invokevirtual append : (C)Ljava/lang/StringBuilder;
    //   341: pop
    //   342: iload_2
    //   343: ifne -> 1348
    //   346: goto -> 353
    //   349: invokestatic a : (Ljava/lang/Throwable;)Ljava/lang/Throwable;
    //   352: athrow
    //   353: aload_3
    //   354: getstatic burp/Zxd1.ZQ : Ljava/lang/String;
    //   357: getstatic burp/Zmc_.Zj : Ljava/lang/Object;
    //   360: checkcast java/math/BigInteger
    //   363: invokevirtual intValue : ()I
    //   366: bipush #32
    //   368: irem
    //   369: invokestatic abs : (I)I
    //   372: invokevirtual charAt : (I)C
    //   375: invokevirtual append : (C)Ljava/lang/StringBuilder;
    //   378: pop
    //   379: iload_2
    //   380: ifne -> 1348
    //   383: goto -> 390
    //   386: invokestatic a : (Ljava/lang/Throwable;)Ljava/lang/Throwable;
    //   389: athrow
    //   390: aload_3
    //   391: getstatic burp/Zeqx.Zu : Ljava/lang/String;
    //   394: getstatic burp/Zxwf.Zi : Ljava/lang/Object;
    //   397: checkcast java/math/BigInteger
    //   400: invokevirtual intValue : ()I
    //   403: bipush #32
    //   405: irem
    //   406: invokestatic abs : (I)I
    //   409: invokevirtual charAt : (I)C
    //   412: invokevirtual append : (C)Ljava/lang/StringBuilder;
    //   415: pop
    //   416: iload_2
    //   417: ifne -> 1348
    //   420: goto -> 427
    //   423: invokestatic a : (Ljava/lang/Throwable;)Ljava/lang/Throwable;
    //   426: athrow
    //   427: aload_3
    //   428: getstatic burp/Zxxf.Zw : Ljava/lang/String;
    //   431: getstatic burp/Zt81.ZY : Ljava/lang/Object;
    //   434: checkcast java/math/BigInteger
    //   437: invokevirtual intValue : ()I
    //   440: bipush #32
    //   442: irem
    //   443: invokestatic abs : (I)I
    //   446: invokevirtual charAt : (I)C
    //   449: invokevirtual append : (C)Ljava/lang/StringBuilder;
    //   452: pop
    //   453: iload_2
    //   454: ifne -> 1348
    //   457: goto -> 464
    //   460: invokestatic a : (Ljava/lang/Throwable;)Ljava/lang/Throwable;
    //   463: athrow
    //   464: aload_3
    //   465: getstatic burp/Ze84.Zv : Ljava/lang/String;
    //   468: getstatic burp/Zegj.ZT : Ljava/lang/Object;
    //   471: checkcast java/math/BigInteger
    //   474: invokevirtual intValue : ()I
    //   477: bipush #32
    //   479: irem
    //   480: invokestatic abs : (I)I
    //   483: invokevirtual charAt : (I)C
    //   486: invokevirtual append : (C)Ljava/lang/StringBuilder;
    //   489: pop
    //   490: iload_2
    //   491: ifne -> 1348
    //   494: goto -> 501
    //   497: invokestatic a : (Ljava/lang/Throwable;)Ljava/lang/Throwable;
    //   500: athrow
    //   501: aload_3
    //   502: getstatic burp/Zrm6.ZV : Ljava/lang/String;
    //   505: getstatic burp/Zsp9.ZV : Ljava/lang/Object;
    //   508: checkcast java/math/BigInteger
    //   511: invokevirtual intValue : ()I
    //   514: bipush #32
    //   516: irem
    //   517: invokestatic abs : (I)I
    //   520: invokevirtual charAt : (I)C
    //   523: invokevirtual append : (C)Ljava/lang/StringBuilder;
    //   526: pop
    //   527: iload_2
    //   528: ifne -> 1348
    //   531: goto -> 538
    //   534: invokestatic a : (Ljava/lang/Throwable;)Ljava/lang/Throwable;
    //   537: athrow
    //   538: aload_3
    //   539: getstatic burp/Zrww.ZV : Ljava/lang/String;
    //   542: getstatic burp/Zl_a.ZP : Ljava/lang/Object;
    //   545: checkcast java/math/BigInteger
    //   548: invokevirtual intValue : ()I
    //   551: bipush #32
    //   553: irem
    //   554: invokestatic abs : (I)I
    //   557: invokevirtual charAt : (I)C
    //   560: invokevirtual append : (C)Ljava/lang/StringBuilder;
    //   563: pop
    //   564: iload_2
    //   565: ifne -> 1348
    //   568: goto -> 575
    //   571: invokestatic a : (Ljava/lang/Throwable;)Ljava/lang/Throwable;
    //   574: athrow
    //   575: aload_3
    //   576: getstatic burp/Zgrz.Zu : Ljava/lang/String;
    //   579: getstatic burp/Zz0f.ZL : Ljava/lang/Object;
    //   582: checkcast java/math/BigInteger
    //   585: invokevirtual intValue : ()I
    //   588: bipush #32
    //   590: irem
    //   591: invokestatic abs : (I)I
    //   594: invokevirtual charAt : (I)C
    //   597: invokevirtual append : (C)Ljava/lang/StringBuilder;
    //   600: pop
    //   601: iload_2
    //   602: ifne -> 1348
    //   605: goto -> 612
    //   608: invokestatic a : (Ljava/lang/Throwable;)Ljava/lang/Throwable;
    //   611: athrow
    //   612: aload_3
    //   613: getstatic burp/Ze7e.Zc : Ljava/lang/String;
    //   616: getstatic burp/Zs_m.Z_ : Ljava/lang/Object;
    //   619: checkcast java/math/BigInteger
    //   622: invokevirtual intValue : ()I
    //   625: bipush #32
    //   627: irem
    //   628: invokestatic abs : (I)I
    //   631: invokevirtual charAt : (I)C
    //   634: invokevirtual append : (C)Ljava/lang/StringBuilder;
    //   637: pop
    //   638: iload_2
    //   639: ifne -> 1348
    //   642: goto -> 649
    //   645: invokestatic a : (Ljava/lang/Throwable;)Ljava/lang/Throwable;
    //   648: athrow
    //   649: aload_3
    //   650: getstatic burp/Zka9.ZM : Ljava/lang/String;
    //   653: getstatic burp/Zmzj.Zm : Ljava/lang/Object;
    //   656: checkcast java/math/BigInteger
    //   659: invokevirtual intValue : ()I
    //   662: bipush #32
    //   664: irem
    //   665: invokestatic abs : (I)I
    //   668: invokevirtual charAt : (I)C
    //   671: invokevirtual append : (C)Ljava/lang/StringBuilder;
    //   674: pop
    //   675: iload_2
    //   676: ifne -> 1348
    //   679: goto -> 686
    //   682: invokestatic a : (Ljava/lang/Throwable;)Ljava/lang/Throwable;
    //   685: athrow
    //   686: aload_3
    //   687: getstatic burp/Ztzj.ZB : Ljava/lang/String;
    //   690: getstatic burp/Zlwj.ZE : Ljava/lang/Object;
    //   693: checkcast java/math/BigInteger
    //   696: invokevirtual intValue : ()I
    //   699: bipush #32
    //   701: irem
    //   702: invokestatic abs : (I)I
    //   705: invokevirtual charAt : (I)C
    //   708: invokevirtual append : (C)Ljava/lang/StringBuilder;
    //   711: pop
    //   712: iload_2
    //   713: ifne -> 1348
    //   716: goto -> 723
    //   719: invokestatic a : (Ljava/lang/Throwable;)Ljava/lang/Throwable;
    //   722: athrow
    //   723: aload_3
    //   724: getstatic burp/Zld5.ZO : Ljava/lang/String;
    //   727: getstatic burp/Zmzj.Zm : Ljava/lang/Object;
    //   730: checkcast java/math/BigInteger
    //   733: invokevirtual intValue : ()I
    //   736: bipush #32
    //   738: irem
    //   739: invokestatic abs : (I)I
    //   742: invokevirtual charAt : (I)C
    //   745: invokevirtual append : (C)Ljava/lang/StringBuilder;
    //   748: pop
    //   749: iload_2
    //   750: ifne -> 1348
    //   753: goto -> 760
    //   756: invokestatic a : (Ljava/lang/Throwable;)Ljava/lang/Throwable;
    //   759: athrow
    //   760: aload_3
    //   761: getstatic burp/Zspg.ZG : Ljava/lang/String;
    //   764: getstatic burp/Zt8m.Zf : Ljava/lang/Object;
    //   767: checkcast java/math/BigInteger
    //   770: invokevirtual intValue : ()I
    //   773: bipush #32
    //   775: irem
    //   776: invokestatic abs : (I)I
    //   779: invokevirtual charAt : (I)C
    //   782: invokevirtual append : (C)Ljava/lang/StringBuilder;
    //   785: pop
    //   786: iload_2
    //   787: ifne -> 1348
    //   790: goto -> 797
    //   793: invokestatic a : (Ljava/lang/Throwable;)Ljava/lang/Throwable;
    //   796: athrow
    //   797: aload_3
    //   798: getstatic burp/Zgei.Zl : Ljava/lang/String;
    //   801: getstatic burp/Zk92.Zn : Ljava/lang/Object;
    //   804: checkcast java/math/BigInteger
    //   807: invokevirtual intValue : ()I
    //   810: bipush #32
    //   812: irem
    //   813: invokestatic abs : (I)I
    //   816: invokevirtual charAt : (I)C
    //   819: invokevirtual append : (C)Ljava/lang/StringBuilder;
    //   822: pop
    //   823: iload_2
    //   824: ifne -> 1348
    //   827: goto -> 834
    //   830: invokestatic a : (Ljava/lang/Throwable;)Ljava/lang/Throwable;
    //   833: athrow
    //   834: aload_3
    //   835: getstatic burp/Zti4.ZI : Ljava/lang/String;
    //   838: getstatic burp/Zle9.ZI : Ljava/lang/Object;
    //   841: checkcast java/math/BigInteger
    //   844: invokevirtual intValue : ()I
    //   847: bipush #32
    //   849: irem
    //   850: invokestatic abs : (I)I
    //   853: invokevirtual charAt : (I)C
    //   856: invokevirtual append : (C)Ljava/lang/StringBuilder;
    //   859: pop
    //   860: iload_2
    //   861: ifne -> 1348
    //   864: goto -> 871
    //   867: invokestatic a : (Ljava/lang/Throwable;)Ljava/lang/Throwable;
    //   870: athrow
    //   871: aload_3
    //   872: getstatic burp/Zrkd.ZL : Ljava/lang/String;
    //   875: getstatic burp/Zxxo.ZJ : Ljava/lang/Object;
    //   878: checkcast java/math/BigInteger
    //   881: invokevirtual intValue : ()I
    //   884: bipush #32
    //   886: irem
    //   887: invokestatic abs : (I)I
    //   890: invokevirtual charAt : (I)C
    //   893: invokevirtual append : (C)Ljava/lang/StringBuilder;
    //   896: pop
    //   897: iload_2
    //   898: ifne -> 1348
    //   901: goto -> 908
    //   904: invokestatic a : (Ljava/lang/Throwable;)Ljava/lang/Throwable;
    //   907: athrow
    //   908: aload_3
    //   909: getstatic burp/Zb3r.Zo : Ljava/lang/String;
    //   912: getstatic burp/Zb9q.ZI : Ljava/lang/Object;
    //   915: checkcast java/math/BigInteger
    //   918: invokevirtual intValue : ()I
    //   921: bipush #32
    //   923: irem
    //   924: invokestatic abs : (I)I
    //   927: invokevirtual charAt : (I)C
    //   930: invokevirtual append : (C)Ljava/lang/StringBuilder;
    //   933: pop
    //   934: iload_2
    //   935: ifne -> 1348
    //   938: goto -> 945
    //   941: invokestatic a : (Ljava/lang/Throwable;)Ljava/lang/Throwable;
    //   944: athrow
    //   945: aload_3
    //   946: getstatic burp/Zt8m.ZT : Ljava/lang/String;
    //   949: getstatic burp/Zgsb.Zl : Ljava/lang/Object;
    //   952: checkcast java/math/BigInteger
    //   955: invokevirtual intValue : ()I
    //   958: bipush #32
    //   960: irem
    //   961: invokestatic abs : (I)I
    //   964: invokevirtual charAt : (I)C
    //   967: invokevirtual append : (C)Ljava/lang/StringBuilder;
    //   970: pop
    //   971: iload_2
    //   972: ifne -> 1348
    //   975: goto -> 982
    //   978: invokestatic a : (Ljava/lang/Throwable;)Ljava/lang/Throwable;
    //   981: athrow
    //   982: aload_3
    //   983: getstatic burp/Zzr8.ZY : Ljava/lang/String;
    //   986: getstatic burp/Zmlr.Zh : Ljava/lang/Object;
    //   989: checkcast java/math/BigInteger
    //   992: invokevirtual intValue : ()I
    //   995: bipush #32
    //   997: irem
    //   998: invokestatic abs : (I)I
    //   1001: invokevirtual charAt : (I)C
    //   1004: invokevirtual append : (C)Ljava/lang/StringBuilder;
    //   1007: pop
    //   1008: iload_2
    //   1009: ifne -> 1348
    //   1012: goto -> 1019
    //   1015: invokestatic a : (Ljava/lang/Throwable;)Ljava/lang/Throwable;
    //   1018: athrow
    //   1019: aload_3
    //   1020: getstatic burp/Ze6w.ZY : Ljava/lang/String;
    //   1023: getstatic burp/Zl3j.ZY : Ljava/lang/Object;
    //   1026: checkcast java/math/BigInteger
    //   1029: invokevirtual intValue : ()I
    //   1032: bipush #32
    //   1034: irem
    //   1035: invokestatic abs : (I)I
    //   1038: invokevirtual charAt : (I)C
    //   1041: invokevirtual append : (C)Ljava/lang/StringBuilder;
    //   1044: pop
    //   1045: iload_2
    //   1046: ifne -> 1348
    //   1049: goto -> 1056
    //   1052: invokestatic a : (Ljava/lang/Throwable;)Ljava/lang/Throwable;
    //   1055: athrow
    //   1056: aload_3
    //   1057: getstatic burp/Zlc2.Zz : Ljava/lang/String;
    //   1060: getstatic burp/Zrfs.ZV : Ljava/lang/Object;
    //   1063: checkcast java/math/BigInteger
    //   1066: invokevirtual intValue : ()I
    //   1069: bipush #32
    //   1071: irem
    //   1072: invokestatic abs : (I)I
    //   1075: invokevirtual charAt : (I)C
    //   1078: invokevirtual append : (C)Ljava/lang/StringBuilder;
    //   1081: pop
    //   1082: iload_2
    //   1083: ifne -> 1348
    //   1086: goto -> 1093
    //   1089: invokestatic a : (Ljava/lang/Throwable;)Ljava/lang/Throwable;
    //   1092: athrow
    //   1093: aload_3
    //   1094: getstatic burp/Zrd3.Z_ : Ljava/lang/String;
    //   1097: getstatic burp/Zs0h.ZU : Ljava/lang/Object;
    //   1100: checkcast java/math/BigInteger
    //   1103: invokevirtual intValue : ()I
    //   1106: bipush #32
    //   1108: irem
    //   1109: invokestatic abs : (I)I
    //   1112: invokevirtual charAt : (I)C
    //   1115: invokevirtual append : (C)Ljava/lang/StringBuilder;
    //   1118: pop
    //   1119: iload_2
    //   1120: ifne -> 1348
    //   1123: goto -> 1130
    //   1126: invokestatic a : (Ljava/lang/Throwable;)Ljava/lang/Throwable;
    //   1129: athrow
    //   1130: aload_3
    //   1131: getstatic burp/Zebe.ZW : Ljava/lang/String;
    //   1134: getstatic burp/Zegv.ZL : Ljava/lang/Object;
    //   1137: checkcast java/math/BigInteger
    //   1140: invokevirtual intValue : ()I
    //   1143: bipush #32
    //   1145: irem
    //   1146: invokestatic abs : (I)I
    //   1149: invokevirtual charAt : (I)C
    //   1152: invokevirtual append : (C)Ljava/lang/StringBuilder;
    //   1155: pop
    //   1156: iload_2
    //   1157: ifne -> 1348
    //   1160: goto -> 1167
    //   1163: invokestatic a : (Ljava/lang/Throwable;)Ljava/lang/Throwable;
    //   1166: athrow
    //   1167: aload_3
    //   1168: getstatic burp/Zlc2.Zz : Ljava/lang/String;
    //   1171: getstatic burp/Zkeb.ZH : Ljava/lang/Object;
    //   1174: checkcast java/math/BigInteger
    //   1177: invokevirtual intValue : ()I
    //   1180: bipush #32
    //   1182: irem
    //   1183: invokestatic abs : (I)I
    //   1186: invokevirtual charAt : (I)C
    //   1189: invokevirtual append : (C)Ljava/lang/StringBuilder;
    //   1192: pop
    //   1193: iload_2
    //   1194: ifne -> 1348
    //   1197: goto -> 1204
    //   1200: invokestatic a : (Ljava/lang/Throwable;)Ljava/lang/Throwable;
    //   1203: athrow
    //   1204: aload_3
    //   1205: getstatic burp/Zrn4.ZY : Ljava/lang/String;
    //   1208: getstatic burp/Zt6z.Zl : Ljava/lang/Object;
    //   1211: checkcast java/math/BigInteger
    //   1214: invokevirtual intValue : ()I
    //   1217: bipush #32
    //   1219: irem
    //   1220: invokestatic abs : (I)I
    //   1223: invokevirtual charAt : (I)C
    //   1226: invokevirtual append : (C)Ljava/lang/StringBuilder;
    //   1229: pop
    //   1230: iload_2
    //   1231: ifne -> 1348
    //   1234: goto -> 1241
    //   1237: invokestatic a : (Ljava/lang/Throwable;)Ljava/lang/Throwable;
    //   1240: athrow
    //   1241: aload_3
    //   1242: getstatic burp/Zspg.ZG : Ljava/lang/String;
    //   1245: getstatic burp/Zewr.Zw : Ljava/lang/Object;
    //   1248: checkcast java/math/BigInteger
    //   1251: invokevirtual intValue : ()I
    //   1254: bipush #32
    //   1256: irem
    //   1257: invokestatic abs : (I)I
    //   1260: invokevirtual charAt : (I)C
    //   1263: invokevirtual append : (C)Ljava/lang/StringBuilder;
    //   1266: pop
    //   1267: iload_2
    //   1268: ifne -> 1348
    //   1271: goto -> 1278
    //   1274: invokestatic a : (Ljava/lang/Throwable;)Ljava/lang/Throwable;
    //   1277: athrow
    //   1278: aload_3
    //   1279: getstatic burp/Zlo0.ZD : Ljava/lang/String;
    //   1282: getstatic burp/Zepy.Ze : Ljava/lang/Object;
    //   1285: checkcast java/math/BigInteger
    //   1288: invokevirtual intValue : ()I
    //   1291: bipush #32
    //   1293: irem
    //   1294: invokestatic abs : (I)I
    //   1297: invokevirtual charAt : (I)C
    //   1300: invokevirtual append : (C)Ljava/lang/StringBuilder;
    //   1303: pop
    //   1304: iload_2
    //   1305: ifne -> 1348
    //   1308: goto -> 1315
    //   1311: invokestatic a : (Ljava/lang/Throwable;)Ljava/lang/Throwable;
    //   1314: athrow
    //   1315: aload_3
    //   1316: getstatic burp/Ze2w.Za : Ljava/lang/String;
    //   1319: getstatic burp/Zrb6.ZQ : Ljava/lang/Object;
    //   1322: checkcast java/math/BigInteger
    //   1325: invokevirtual intValue : ()I
    //   1328: bipush #32
    //   1330: irem
    //   1331: invokestatic abs : (I)I
    //   1334: invokevirtual charAt : (I)C
    //   1337: invokevirtual append : (C)Ljava/lang/StringBuilder;
    //   1340: pop
    //   1341: goto -> 1348
    //   1344: invokestatic a : (Ljava/lang/Throwable;)Ljava/lang/Throwable;
    //   1347: athrow
    //   1348: iinc #4, 1
    //   1351: iload_2
    //   1352: ifne -> 15
    //   1355: aload_3
    //   1356: invokevirtual toString : ()Ljava/lang/String;
    //   1359: putstatic burp/Zr17.Zu : Ljava/lang/String;
    //   1362: getstatic burp/Zti7.Zw : Ljava/lang/Object;
    //   1365: checkcast java/math/BigInteger
    //   1368: invokevirtual toByteArray : ()[B
    //   1371: astore #4
    //   1373: aload #4
    //   1375: arraylength
    //   1376: bipush #8
    //   1378: iadd
    //   1379: bipush #6
    //   1381: ishr
    //   1382: iconst_1
    //   1383: iadd
    //   1384: bipush #16
    //   1386: imul
    //   1387: newarray int
    //   1389: astore #6
    //   1391: iconst_0
    //   1392: istore #7
    //   1394: iload #7
    //   1396: aload #4
    //   1398: arraylength
    //   1399: if_icmpge -> 1443
    //   1402: aload #4
    //   1404: iload #7
    //   1406: baload
    //   1407: sipush #255
    //   1410: iand
    //   1411: istore #8
    //   1413: aload #6
    //   1415: iload #7
    //   1417: iconst_2
    //   1418: ishr
    //   1419: dup2
    //   1420: iaload
    //   1421: iload #8
    //   1423: bipush #24
    //   1425: iload #7
    //   1427: iconst_4
    //   1428: irem
    //   1429: bipush #8
    //   1431: imul
    //   1432: isub
    //   1433: ishl
    //   1434: ior
    //   1435: iastore
    //   1436: iinc #7, 1
    //   1439: iload_2
    //   1440: ifne -> 1394
    //   1443: aload #6
    //   1445: iload #7
    //   1447: iconst_2
    //   1448: ishr
    //   1449: dup2
    //   1450: iaload
    //   1451: sipush #128
    //   1454: bipush #24
    //   1456: iload #7
    //   1458: iconst_4
    //   1459: irem
    //   1460: bipush #8
    //   1462: imul
    //   1463: isub
    //   1464: ishl
    //   1465: ior
    //   1466: iastore
    //   1467: aload #6
    //   1469: aload #6
    //   1471: arraylength
    //   1472: iconst_1
    //   1473: isub
    //   1474: aload #4
    //   1476: arraylength
    //   1477: bipush #8
    //   1479: imul
    //   1480: iastore
    //   1481: bipush #80
    //   1483: newarray int
    //   1485: astore #8
    //   1487: ldc 1732584193
    //   1489: istore #9
    //   1491: ldc -271733879
    //   1493: istore #10
    //   1495: ldc -1732584194
    //   1497: istore #11
    //   1499: ldc 271733878
    //   1501: istore #12
    //   1503: ldc -1009589776
    //   1505: istore #13
    //   1507: iconst_0
    //   1508: istore #7
    //   1510: iload #7
    //   1512: aload #6
    //   1514: arraylength
    //   1515: if_icmpge -> 1837
    //   1518: iload #9
    //   1520: istore #14
    //   1522: iload #10
    //   1524: istore #15
    //   1526: iload #11
    //   1528: istore #16
    //   1530: iload #12
    //   1532: istore #17
    //   1534: iload #13
    //   1536: istore #18
    //   1538: iconst_0
    //   1539: istore #19
    //   1541: iload #19
    //   1543: bipush #80
    //   1545: if_icmpge -> 1795
    //   1548: iload #19
    //   1550: bipush #16
    //   1552: if_icmpge -> 1579
    //   1555: aload #8
    //   1557: iload #19
    //   1559: aload #6
    //   1561: iload #7
    //   1563: iload #19
    //   1565: iadd
    //   1566: iaload
    //   1567: iastore
    //   1568: iload_2
    //   1569: ifne -> 1634
    //   1572: goto -> 1579
    //   1575: invokestatic a : (Ljava/lang/Throwable;)Ljava/lang/Throwable;
    //   1578: athrow
    //   1579: aload #8
    //   1581: iload #19
    //   1583: iconst_3
    //   1584: isub
    //   1585: iaload
    //   1586: aload #8
    //   1588: iload #19
    //   1590: bipush #8
    //   1592: isub
    //   1593: iaload
    //   1594: ixor
    //   1595: aload #8
    //   1597: iload #19
    //   1599: bipush #14
    //   1601: isub
    //   1602: iaload
    //   1603: ixor
    //   1604: aload #8
    //   1606: iload #19
    //   1608: bipush #16
    //   1610: isub
    //   1611: iaload
    //   1612: ixor
    //   1613: istore #20
    //   1615: iload #20
    //   1617: iconst_1
    //   1618: ishl
    //   1619: iload #20
    //   1621: bipush #31
    //   1623: iushr
    //   1624: ior
    //   1625: istore #21
    //   1627: aload #8
    //   1629: iload #19
    //   1631: iload #21
    //   1633: iastore
    //   1634: iload #9
    //   1636: iconst_5
    //   1637: ishl
    //   1638: iload #9
    //   1640: bipush #27
    //   1642: iushr
    //   1643: ior
    //   1644: istore #20
    //   1646: iload #20
    //   1648: iload #13
    //   1650: iadd
    //   1651: aload #8
    //   1653: iload #19
    //   1655: iaload
    //   1656: iadd
    //   1657: iload #19
    //   1659: bipush #20
    //   1661: if_icmpge -> 1687
    //   1664: ldc 1518500249
    //   1666: iload #10
    //   1668: iload #11
    //   1670: iand
    //   1671: iload #10
    //   1673: iconst_m1
    //   1674: ixor
    //   1675: iload #12
    //   1677: iand
    //   1678: ior
    //   1679: iadd
    //   1680: goto -> 1757
    //   1683: invokestatic a : (Ljava/lang/Throwable;)Ljava/lang/Throwable;
    //   1686: athrow
    //   1687: iload #19
    //   1689: bipush #40
    //   1691: if_icmpge -> 1712
    //   1694: ldc 1859775393
    //   1696: iload #10
    //   1698: iload #11
    //   1700: ixor
    //   1701: iload #12
    //   1703: ixor
    //   1704: iadd
    //   1705: goto -> 1757
    //   1708: invokestatic a : (Ljava/lang/Throwable;)Ljava/lang/Throwable;
    //   1711: athrow
    //   1712: iload #19
    //   1714: bipush #60
    //   1716: if_icmpge -> 1746
    //   1719: ldc -1894007588
    //   1721: iload #10
    //   1723: iload #11
    //   1725: iand
    //   1726: iload #10
    //   1728: iload #12
    //   1730: iand
    //   1731: ior
    //   1732: iload #11
    //   1734: iload #12
    //   1736: iand
    //   1737: ior
    //   1738: iadd
    //   1739: goto -> 1757
    //   1742: invokestatic a : (Ljava/lang/Throwable;)Ljava/lang/Throwable;
    //   1745: athrow
    //   1746: ldc -899497514
    //   1748: iload #10
    //   1750: iload #11
    //   1752: ixor
    //   1753: iload #12
    //   1755: ixor
    //   1756: iadd
    //   1757: iadd
    //   1758: istore #21
    //   1760: iload #12
    //   1762: istore #13
    //   1764: iload #11
    //   1766: istore #12
    //   1768: iload #10
    //   1770: bipush #30
    //   1772: ishl
    //   1773: iload #10
    //   1775: iconst_2
    //   1776: iushr
    //   1777: ior
    //   1778: istore #11
    //   1780: iload #9
    //   1782: istore #10
    //   1784: iload #21
    //   1786: istore #9
    //   1788: iinc #19, 1
    //   1791: iload_2
    //   1792: ifne -> 1541
    //   1795: iload #9
    //   1797: iload #14
    //   1799: iadd
    //   1800: istore #9
    //   1802: iload #10
    //   1804: iload #15
    //   1806: iadd
    //   1807: istore #10
    //   1809: iload #11
    //   1811: iload #16
    //   1813: iadd
    //   1814: istore #11
    //   1816: iload #12
    //   1818: iload #17
    //   1820: iadd
    //   1821: istore #12
    //   1823: iload #13
    //   1825: iload #18
    //   1827: iadd
    //   1828: istore #13
    //   1830: iinc #7, 16
    //   1833: iload_2
    //   1834: ifne -> 1510
    //   1837: iconst_5
    //   1838: newarray int
    //   1840: dup
    //   1841: iconst_0
    //   1842: iload #9
    //   1844: iastore
    //   1845: dup
    //   1846: iconst_1
    //   1847: iload #10
    //   1849: iastore
    //   1850: dup
    //   1851: iconst_2
    //   1852: iload #11
    //   1854: iastore
    //   1855: dup
    //   1856: iconst_3
    //   1857: iload #12
    //   1859: iastore
    //   1860: dup
    //   1861: iconst_4
    //   1862: iload #13
    //   1864: iastore
    //   1865: astore #14
    //   1867: bipush #20
    //   1869: newarray byte
    //   1871: astore #15
    //   1873: iconst_0
    //   1874: istore #16
    //   1876: iload #16
    //   1878: bipush #20
    //   1880: if_icmpge -> 1921
    //   1883: aload #14
    //   1885: iload #16
    //   1887: iconst_4
    //   1888: idiv
    //   1889: iaload
    //   1890: istore #17
    //   1892: iconst_3
    //   1893: iload #16
    //   1895: iconst_4
    //   1896: irem
    //   1897: isub
    //   1898: bipush #8
    //   1900: imul
    //   1901: istore #18
    //   1903: aload #15
    //   1905: iload #16
    //   1907: iload #17
    //   1909: iload #18
    //   1911: iushr
    //   1912: i2b
    //   1913: bastore
    //   1914: iinc #16, 1
    //   1917: iload_2
    //   1918: ifne -> 1876
    //   1921: aload #15
    //   1923: astore #5
    //   1925: sipush #-10233
    //   1928: new java/math/BigInteger
    //   1931: dup
    //   1932: aload #5
    //   1934: invokespecial <init> : ([B)V
    //   1937: invokevirtual abs : ()Ljava/math/BigInteger;
    //   1940: putstatic burp/Zrom.ZF : Ljava/lang/Object;
    //   1943: sipush #-18714
    //   1946: getstatic burp/Zk5k.Zr : Ljava/lang/Object;
    //   1949: checkcast java/math/BigInteger
    //   1952: getstatic burp/Zxln.ZJ : Ljava/lang/Object;
    //   1955: checkcast java/math/BigInteger
    //   1958: invokevirtual subtract : (Ljava/math/BigInteger;)Ljava/math/BigInteger;
    //   1961: putstatic burp/Zzhx.ZB : Ljava/lang/Object;
    //   1964: invokestatic a : (II)Ljava/lang/String;
    //   1967: iconst_1
    //   1968: ldc burp/Zz9p
    //   1970: invokevirtual getClassLoader : ()Ljava/lang/ClassLoader;
    //   1973: invokestatic forName : (Ljava/lang/String;ZLjava/lang/ClassLoader;)Ljava/lang/Class;
    //   1976: invokevirtual getDeclaredFields : ()[Ljava/lang/reflect/Field;
    //   1979: astore #4
    //   1981: aload #4
    //   1983: arraylength
    //   1984: istore #5
    //   1986: iconst_0
    //   1987: istore #6
    //   1989: iload #6
    //   1991: iload #5
    //   1993: if_icmpge -> 2131
    //   1996: aload #4
    //   1998: iload #6
    //   2000: aaload
    //   2001: astore #7
    //   2003: aload #7
    //   2005: invokevirtual getModifiers : ()I
    //   2008: invokestatic isStatic : (I)Z
    //   2011: ifne -> 2021
    //   2014: goto -> 2124
    //   2017: invokestatic a : (Ljava/lang/Throwable;)Ljava/lang/Throwable;
    //   2020: athrow
    //   2021: aload #7
    //   2023: invokevirtual getType : ()Ljava/lang/Class;
    //   2026: astore #8
    //   2028: aload #8
    //   2030: ifnull -> 2111
    //   2033: aload #8
    //   2035: invokevirtual isPrimitive : ()Z
    //   2038: ifne -> 2111
    //   2041: goto -> 2048
    //   2044: invokestatic a : (Ljava/lang/Throwable;)Ljava/lang/Throwable;
    //   2047: athrow
    //   2048: aload #8
    //   2050: invokevirtual getPackage : ()Ljava/lang/Package;
    //   2053: ifnull -> 2111
    //   2056: goto -> 2063
    //   2059: invokestatic a : (Ljava/lang/Throwable;)Ljava/lang/Throwable;
    //   2062: athrow
    //   2063: aload #8
    //   2065: invokevirtual getPackage : ()Ljava/lang/Package;
    //   2068: invokevirtual getName : ()Ljava/lang/String;
    //   2071: ifnull -> 2111
    //   2074: goto -> 2081
    //   2077: invokestatic a : (Ljava/lang/Throwable;)Ljava/lang/Throwable;
    //   2080: athrow
    //   2081: aload #8
    //   2083: invokevirtual getPackage : ()Ljava/lang/Package;
    //   2086: invokevirtual getName : ()Ljava/lang/String;
    //   2089: sipush #-10240
    //   2092: sipush #15061
    //   2095: invokestatic a : (II)Ljava/lang/String;
    //   2098: invokevirtual startsWith : (Ljava/lang/String;)Z
    //   2101: ifne -> 2111
    //   2104: goto -> 2111
    //   2107: invokestatic a : (Ljava/lang/Throwable;)Ljava/lang/Throwable;
    //   2110: athrow
    //   2111: aload #7
    //   2113: iconst_1
    //   2114: invokevirtual setAccessible : (Z)V
    //   2117: aload #7
    //   2119: aconst_null
    //   2120: invokevirtual get : (Ljava/lang/Object;)Ljava/lang/Object;
    //   2123: pop
    //   2124: iinc #6, 1
    //   2127: iload_2
    //   2128: ifne -> 1989
    //   2131: sipush #-10229
    //   2134: sipush #21655
    //   2137: invokestatic a : (II)Ljava/lang/String;
    //   2140: invokestatic forName : (Ljava/lang/String;)Ljava/lang/Class;
    //   2143: invokevirtual getDeclaredMethods : ()[Ljava/lang/reflect/Method;
    //   2146: astore #4
    //   2148: aload #4
    //   2150: arraylength
    //   2151: istore #5
    //   2153: iconst_0
    //   2154: istore #6
    //   2156: iload #6
    //   2158: iload #5
    //   2160: if_icmpge -> 2293
    //   2163: aload #4
    //   2165: iload #6
    //   2167: aaload
    //   2168: astore #7
    //   2170: aload #7
    //   2172: invokevirtual getParameterTypes : ()[Ljava/lang/Class;
    //   2175: pop
    //   2176: aload #7
    //   2178: invokevirtual getModifiers : ()I
    //   2181: invokestatic isStatic : (I)Z
    //   2184: ifeq -> 2279
    //   2187: aload #7
    //   2189: invokevirtual getParameterTypes : ()[Ljava/lang/Class;
    //   2192: arraylength
    //   2193: iconst_2
    //   2194: if_icmpne -> 2279
    //   2197: goto -> 2204
    //   2200: invokestatic a : (Ljava/lang/Throwable;)Ljava/lang/Throwable;
    //   2203: athrow
    //   2204: aload #7
    //   2206: invokevirtual getReturnType : ()Ljava/lang/Class;
    //   2209: getstatic java/lang/Void.TYPE : Ljava/lang/Class;
    //   2212: invokevirtual equals : (Ljava/lang/Object;)Z
    //   2215: ifeq -> 2279
    //   2218: goto -> 2225
    //   2221: invokestatic a : (Ljava/lang/Throwable;)Ljava/lang/Throwable;
    //   2224: athrow
    //   2225: aload #7
    //   2227: iconst_1
    //   2228: invokevirtual setAccessible : (Z)V
    //   2231: aload #7
    //   2233: aconst_null
    //   2234: iconst_2
    //   2235: anewarray java/lang/Object
    //   2238: dup
    //   2239: iconst_0
    //   2240: aload_0
    //   2241: aastore
    //   2242: dup
    //   2243: iconst_1
    //   2244: aload_1
    //   2245: ifnonnull -> 2263
    //   2248: goto -> 2255
    //   2251: invokestatic a : (Ljava/lang/Throwable;)Ljava/lang/Throwable;
    //   2254: athrow
    //   2255: aload_1
    //   2256: goto -> 2270
    //   2259: invokestatic a : (Ljava/lang/Throwable;)Ljava/lang/Throwable;
    //   2262: athrow
    //   2263: aload_1
    //   2264: checkcast [B
    //   2267: invokevirtual clone : ()Ljava/lang/Object;
    //   2270: aastore
    //   2271: invokevirtual invoke : (Ljava/lang/Object;[Ljava/lang/Object;)Ljava/lang/Object;
    //   2274: pop
    //   2275: iload_2
    //   2276: ifne -> 2293
    //   2279: iinc #6, 1
    //   2282: iload_2
    //   2283: ifne -> 2156
    //   2286: goto -> 2293
    //   2289: invokestatic a : (Ljava/lang/Throwable;)Ljava/lang/Throwable;
    //   2292: athrow
    //   2293: getstatic burp/Zg6z.ZS : Ljava/lang/Object;
    //   2296: checkcast java/math/BigInteger
    //   2299: invokevirtual intValue : ()I
    //   2302: i2l
    //   2303: invokestatic currentTimeMillis : ()J
    //   2306: ladd
    //   2307: getstatic burp/Zthx.ZH : Ljava/lang/Object;
    //   2310: checkcast java/math/BigInteger
    //   2313: invokevirtual intValue : ()I
    //   2316: i2l
    //   2317: lcmp
    //   2318: ifge -> 2656
    //   2321: sipush #-10239
    //   2324: sipush #-6887
    //   2327: invokestatic a : (II)Ljava/lang/String;
    //   2330: iconst_1
    //   2331: ldc burp/Zkq9
    //   2333: invokevirtual getClassLoader : ()Ljava/lang/ClassLoader;
    //   2336: invokestatic forName : (Ljava/lang/String;ZLjava/lang/ClassLoader;)Ljava/lang/Class;
    //   2339: invokevirtual getDeclaredFields : ()[Ljava/lang/reflect/Field;
    //   2342: astore #4
    //   2344: aload #4
    //   2346: arraylength
    //   2347: istore #5
    //   2349: iconst_0
    //   2350: istore #6
    //   2352: iload #6
    //   2354: iload #5
    //   2356: if_icmpge -> 2494
    //   2359: aload #4
    //   2361: iload #6
    //   2363: aaload
    //   2364: astore #7
    //   2366: aload #7
    //   2368: invokevirtual getModifiers : ()I
    //   2371: invokestatic isStatic : (I)Z
    //   2374: ifne -> 2384
    //   2377: goto -> 2487
    //   2380: invokestatic a : (Ljava/lang/Throwable;)Ljava/lang/Throwable;
    //   2383: athrow
    //   2384: aload #7
    //   2386: invokevirtual getType : ()Ljava/lang/Class;
    //   2389: astore #8
    //   2391: aload #8
    //   2393: ifnull -> 2474
    //   2396: aload #8
    //   2398: invokevirtual isPrimitive : ()Z
    //   2401: ifne -> 2474
    //   2404: goto -> 2411
    //   2407: invokestatic a : (Ljava/lang/Throwable;)Ljava/lang/Throwable;
    //   2410: athrow
    //   2411: aload #8
    //   2413: invokevirtual getPackage : ()Ljava/lang/Package;
    //   2416: ifnull -> 2474
    //   2419: goto -> 2426
    //   2422: invokestatic a : (Ljava/lang/Throwable;)Ljava/lang/Throwable;
    //   2425: athrow
    //   2426: aload #8
    //   2428: invokevirtual getPackage : ()Ljava/lang/Package;
    //   2431: invokevirtual getName : ()Ljava/lang/String;
    //   2434: ifnull -> 2474
    //   2437: goto -> 2444
    //   2440: invokestatic a : (Ljava/lang/Throwable;)Ljava/lang/Throwable;
    //   2443: athrow
    //   2444: aload #8
    //   2446: invokevirtual getPackage : ()Ljava/lang/Package;
    //   2449: invokevirtual getName : ()Ljava/lang/String;
    //   2452: sipush #-10238
    //   2455: sipush #-28606
    //   2458: invokestatic a : (II)Ljava/lang/String;
    //   2461: invokevirtual startsWith : (Ljava/lang/String;)Z
    //   2464: ifne -> 2474
    //   2467: goto -> 2474
    //   2470: invokestatic a : (Ljava/lang/Throwable;)Ljava/lang/Throwable;
    //   2473: athrow
    //   2474: aload #7
    //   2476: iconst_1
    //   2477: invokevirtual setAccessible : (Z)V
    //   2480: aload #7
    //   2482: aconst_null
    //   2483: invokevirtual get : (Ljava/lang/Object;)Ljava/lang/Object;
    //   2486: pop
    //   2487: iinc #6, 1
    //   2490: iload_2
    //   2491: ifne -> 2352
    //   2494: sipush #-10234
    //   2497: sipush #1401
    //   2500: invokestatic a : (II)Ljava/lang/String;
    //   2503: invokestatic forName : (Ljava/lang/String;)Ljava/lang/Class;
    //   2506: invokevirtual getDeclaredMethods : ()[Ljava/lang/reflect/Method;
    //   2509: astore #4
    //   2511: aload #4
    //   2513: arraylength
    //   2514: istore #5
    //   2516: iconst_0
    //   2517: istore #6
    //   2519: iload #6
    //   2521: iload #5
    //   2523: if_icmpge -> 2656
    //   2526: aload #4
    //   2528: iload #6
    //   2530: aaload
    //   2531: astore #7
    //   2533: aload #7
    //   2535: invokevirtual getParameterTypes : ()[Ljava/lang/Class;
    //   2538: pop
    //   2539: aload #7
    //   2541: invokevirtual getModifiers : ()I
    //   2544: invokestatic isStatic : (I)Z
    //   2547: ifeq -> 2642
    //   2550: aload #7
    //   2552: invokevirtual getParameterTypes : ()[Ljava/lang/Class;
    //   2555: arraylength
    //   2556: iconst_2
    //   2557: if_icmpne -> 2642
    //   2560: goto -> 2567
    //   2563: invokestatic a : (Ljava/lang/Throwable;)Ljava/lang/Throwable;
    //   2566: athrow
    //   2567: aload #7
    //   2569: invokevirtual getReturnType : ()Ljava/lang/Class;
    //   2572: getstatic java/lang/Void.TYPE : Ljava/lang/Class;
    //   2575: invokevirtual equals : (Ljava/lang/Object;)Z
    //   2578: ifeq -> 2642
    //   2581: goto -> 2588
    //   2584: invokestatic a : (Ljava/lang/Throwable;)Ljava/lang/Throwable;
    //   2587: athrow
    //   2588: aload #7
    //   2590: iconst_1
    //   2591: invokevirtual setAccessible : (Z)V
    //   2594: aload #7
    //   2596: aconst_null
    //   2597: iconst_2
    //   2598: anewarray java/lang/Object
    //   2601: dup
    //   2602: iconst_0
    //   2603: aload_0
    //   2604: aastore
    //   2605: dup
    //   2606: iconst_1
    //   2607: aload_1
    //   2608: ifnonnull -> 2626
    //   2611: goto -> 2618
    //   2614: invokestatic a : (Ljava/lang/Throwable;)Ljava/lang/Throwable;
    //   2617: athrow
    //   2618: aload_1
    //   2619: goto -> 2633
    //   2622: invokestatic a : (Ljava/lang/Throwable;)Ljava/lang/Throwable;
    //   2625: athrow
    //   2626: aload_1
    //   2627: checkcast [B
    //   2630: invokevirtual clone : ()Ljava/lang/Object;
    //   2633: aastore
    //   2634: invokevirtual invoke : (Ljava/lang/Object;[Ljava/lang/Object;)Ljava/lang/Object;
    //   2637: pop
    //   2638: iload_2
    //   2639: ifne -> 2656
    //   2642: iinc #6, 1
    //   2645: iload_2
    //   2646: ifne -> 2519
    //   2649: goto -> 2656
    //   2652: invokestatic a : (Ljava/lang/Throwable;)Ljava/lang/Throwable;
    //   2655: athrow
    //   2656: getstatic burp/Zlg2.ZL : Ljava/lang/String;
    //   2659: getstatic burp/Ztwp.Ze : Ljava/lang/Object;
    //   2662: checkcast java/math/BigInteger
    //   2665: invokevirtual intValue : ()I
    //   2668: bipush #32
    //   2670: irem
    //   2671: invokestatic abs : (I)I
    //   2674: invokevirtual charAt : (I)C
    //   2677: getstatic burp/Zr14.ZL : Ljava/lang/String;
    //   2680: getstatic burp/Zz4m.Zo : Ljava/lang/Object;
    //   2683: checkcast java/math/BigInteger
    //   2686: invokevirtual intValue : ()I
    //   2689: bipush #32
    //   2691: irem
    //   2692: invokestatic abs : (I)I
    //   2695: invokevirtual charAt : (I)C
    //   2698: if_icmple -> 2805
    //   2701: getstatic burp/Zg61.ZX : Ljava/lang/String;
    //   2704: getstatic burp/Zz5e.Zl : Ljava/lang/Object;
    //   2707: checkcast java/math/BigInteger
    //   2710: invokevirtual intValue : ()I
    //   2713: bipush #32
    //   2715: irem
    //   2716: invokestatic abs : (I)I
    //   2719: invokevirtual charAt : (I)C
    //   2722: getstatic burp/Zbze.ZK : Ljava/lang/String;
    //   2725: getstatic burp/Zs1k.Ze : Ljava/lang/Object;
    //   2728: checkcast java/math/BigInteger
    //   2731: invokevirtual intValue : ()I
    //   2734: bipush #32
    //   2736: irem
    //   2737: invokestatic abs : (I)I
    //   2740: invokevirtual charAt : (I)C
    //   2743: if_icmple -> 2805
    //   2746: goto -> 2753
    //   2749: invokestatic a : (Ljava/lang/Throwable;)Ljava/lang/Throwable;
    //   2752: athrow
    //   2753: getstatic burp/Zbw5.ZC : Ljava/lang/String;
    //   2756: getstatic burp/Zbwj.ZW : Ljava/lang/Object;
    //   2759: checkcast java/math/BigInteger
    //   2762: invokevirtual intValue : ()I
    //   2765: bipush #32
    //   2767: irem
    //   2768: invokestatic abs : (I)I
    //   2771: invokevirtual charAt : (I)C
    //   2774: getstatic burp/Zst7.Zi : Ljava/lang/String;
    //   2777: getstatic burp/Zr9u.ZX : Ljava/lang/Object;
    //   2780: checkcast java/math/BigInteger
    //   2783: invokevirtual intValue : ()I
    //   2786: bipush #32
    //   2788: irem
    //   2789: invokestatic abs : (I)I
    //   2792: invokevirtual charAt : (I)C
    //   2795: if_icmpgt -> 2813
    //   2798: goto -> 2805
    //   2801: invokestatic a : (Ljava/lang/Throwable;)Ljava/lang/Throwable;
    //   2804: athrow
    //   2805: iconst_1
    //   2806: goto -> 2814
    //   2809: invokestatic a : (Ljava/lang/Throwable;)Ljava/lang/Throwable;
    //   2812: athrow
    //   2813: iconst_0
    //   2814: ireturn
    //   2815: astore_3
    //   2816: new java/lang/Exception
    //   2819: dup
    //   2820: aload_3
    //   2821: invokevirtual getMessage : ()Ljava/lang/String;
    //   2824: invokespecial <init> : (Ljava/lang/String;)V
    //   2827: athrow
    // Exception table:
    //   from	to	target	type
    //   4	2814	2815	java/lang/Throwable
    //   22	198	201	java/lang/Throwable
    //   168	235	238	java/lang/Throwable
    //   205	272	275	java/lang/Throwable
    //   242	309	312	java/lang/Throwable
    //   279	346	349	java/lang/Throwable
    //   316	383	386	java/lang/Throwable
    //   353	420	423	java/lang/Throwable
    //   390	457	460	java/lang/Throwable
    //   427	494	497	java/lang/Throwable
    //   464	531	534	java/lang/Throwable
    //   501	568	571	java/lang/Throwable
    //   538	605	608	java/lang/Throwable
    //   575	642	645	java/lang/Throwable
    //   612	679	682	java/lang/Throwable
    //   649	716	719	java/lang/Throwable
    //   686	753	756	java/lang/Throwable
    //   723	790	793	java/lang/Throwable
    //   760	827	830	java/lang/Throwable
    //   797	864	867	java/lang/Throwable
    //   834	901	904	java/lang/Throwable
    //   871	938	941	java/lang/Throwable
    //   908	975	978	java/lang/Throwable
    //   945	1012	1015	java/lang/Throwable
    //   982	1049	1052	java/lang/Throwable
    //   1019	1086	1089	java/lang/Throwable
    //   1056	1123	1126	java/lang/Throwable
    //   1093	1160	1163	java/lang/Throwable
    //   1130	1197	1200	java/lang/Throwable
    //   1167	1234	1237	java/lang/Throwable
    //   1204	1271	1274	java/lang/Throwable
    //   1241	1308	1311	java/lang/Throwable
    //   1278	1341	1344	java/lang/Throwable
    //   1548	1572	1575	java/lang/Throwable
    //   1646	1683	1683	java/lang/Throwable
    //   1687	1708	1708	java/lang/Throwable
    //   1712	1742	1742	java/lang/Throwable
    //   2003	2017	2017	java/lang/Throwable
    //   2028	2041	2044	java/lang/Throwable
    //   2033	2056	2059	java/lang/Throwable
    //   2048	2074	2077	java/lang/Throwable
    //   2063	2104	2107	java/lang/Throwable
    //   2170	2197	2200	java/lang/Throwable
    //   2187	2218	2221	java/lang/Throwable
    //   2204	2248	2251	java/lang/Throwable
    //   2225	2259	2259	java/lang/Throwable
    //   2270	2286	2289	java/lang/Throwable
    //   2366	2380	2380	java/lang/Throwable
    //   2391	2404	2407	java/lang/Throwable
    //   2396	2419	2422	java/lang/Throwable
    //   2411	2437	2440	java/lang/Throwable
    //   2426	2467	2470	java/lang/Throwable
    //   2533	2560	2563	java/lang/Throwable
    //   2550	2581	2584	java/lang/Throwable
    //   2567	2611	2614	java/lang/Throwable
    //   2588	2622	2622	java/lang/Throwable
    //   2633	2649	2652	java/lang/Throwable
    //   2656	2746	2749	java/lang/Throwable
    //   2701	2798	2801	java/lang/Throwable
    //   2753	2809	2809	java/lang/Throwable
  }
  
  static void ZG(Object[] paramArrayOfObject, Object paramObject) throws Throwable {}
  
  static void Zl(Object paramObject) {
    Zeig.Zg = a(-10230, 17201);
    Zeig.ZA = new BigInteger(a(-10236, -22645));
    boolean bool = Zt2e.ZN();
    try {
      try {
        if (Ztwp.ZK.charAt(Math.abs(((BigInteger)Zzk_.Zx).intValue() % 32)) <= Ztq4.Zb.charAt(Math.abs(((BigInteger)Ze4w.Zd).intValue() % 32))) {
          try {
            Zscz.Zk(Class.forName(a(-10232, 26511)));
            if (!bool)
              Zezz.ZO(Class.forName(a(-10237, -32341))); 
          } catch (Throwable throwable) {
            throw a(null);
          } 
          return;
        } 
      } catch (Throwable throwable) {
        throw a(null);
      } 
      Zezz.ZO(Class.forName(a(-10237, -32341)));
    } catch (Throwable throwable) {}
  }
  
  static {
    // Byte code:
    //   0: bipush #11
    //   2: anewarray java/lang/String
    //   5: astore #5
    //   7: iconst_0
    //   8: istore_3
    //   9: ldc '4Ã¢Ã¥\\bÃŠ8Ã‰Â¾Â£`ÃšÃ•Â Ã²Â­\\tÃ”Ã€\\nÂ¡Ã›ÂƒÃŸÃºÂ…\\tÂ…1 ÂŸÂžDwÂ\\bTL0Ã™Â±Â‹Ã¤MÂ¶Â¢wÃ‚o\\bÃŠ7Ã”ÂÂ´Â¡4ÃªÃ²VPÂ•Â¨Â¦UEÂ‰ÂŽ qÃˆÃ°Â›QVÂšHÃ¤Âƒ]Ã„`Ã©ÂŠiXhZÃ‹wZRoÃ‡Ã·ÂšFÃ™4Ã¸Â½Â“Ã…SÂˆÃ›Â¼Ã¯Ã¾ ÃƒÂ½{eH;Ã®ÃžÃ <Â€Â—Â›Ã˜Ã¯MÂ’ÂˆÃ«Â‚Â•ÂžRÂˆÂ¤A7\\rt ÂµÃŽTÂ¥*SÂ¤Ã«-ÃÂlÃÃ²Ã‚Âž2ÃÂ¼w)Ã§LÃ Â§Â—z'
    //   11: dup
    //   12: astore_2
    //   13: invokevirtual length : ()I
    //   16: istore #4
    //   18: iconst_4
    //   19: istore_1
    //   20: iconst_m1
    //   21: istore_0
    //   22: bipush #97
    //   24: iinc #0, 1
    //   27: aload_2
    //   28: iload_0
    //   29: dup
    //   30: iload_1
    //   31: iadd
    //   32: invokevirtual substring : (II)Ljava/lang/String;
    //   35: iconst_m1
    //   36: goto -> 142
    //   39: aload #5
    //   41: swap
    //   42: iload_3
    //   43: iinc #3, 1
    //   46: swap
    //   47: aastore
    //   48: iload_0
    //   49: iload_1
    //   50: iadd
    //   51: dup
    //   52: istore_0
    //   53: iload #4
    //   55: if_icmpge -> 67
    //   58: aload_2
    //   59: iload_0
    //   60: invokevirtual charAt : (I)C
    //   63: istore_1
    //   64: goto -> 22
    //   67: ldc '-Ã‚ÃÂ™.yÃ­\\bÃ›Â«6BÂ‹L'
    //   69: dup
    //   70: astore_2
    //   71: invokevirtual length : ()I
    //   74: istore #4
    //   76: bipush #8
    //   78: istore_1
    //   79: iconst_m1
    //   80: istore_0
    //   81: bipush #21
    //   83: iinc #0, 1
    //   86: aload_2
    //   87: iload_0
    //   88: dup
    //   89: iload_1
    //   90: iadd
    //   91: invokevirtual substring : (II)Ljava/lang/String;
    //   94: iconst_0
    //   95: goto -> 142
    //   98: aload #5
    //   100: swap
    //   101: iload_3
    //   102: iinc #3, 1
    //   105: swap
    //   106: aastore
    //   107: iload_0
    //   108: iload_1
    //   109: iadd
    //   110: dup
    //   111: istore_0
    //   112: iload #4
    //   114: if_icmpge -> 126
    //   117: aload_2
    //   118: iload_0
    //   119: invokevirtual charAt : (I)C
    //   122: istore_1
    //   123: goto -> 81
    //   126: aload #5
    //   128: putstatic burp/Zl3j.a : [Ljava/lang/String;
    //   131: bipush #11
    //   133: anewarray java/lang/String
    //   136: putstatic burp/Zl3j.b : [Ljava/lang/String;
    //   139: goto -> 300
    //   142: dup_x2
    //   143: pop
    //   144: invokevirtual toCharArray : ()[C
    //   147: dup_x1
    //   148: arraylength
    //   149: dup_x2
    //   150: pop
    //   151: iconst_0
    //   152: istore #6
    //   154: dup2_x1
    //   155: pop2
    //   156: dup_x2
    //   157: iconst_1
    //   158: if_icmpgt -> 260
    //   161: dup2
    //   162: swap
    //   163: iload #6
    //   165: dup2_x1
    //   166: caload
    //   167: swap
    //   168: iload #6
    //   170: bipush #7
    //   172: irem
    //   173: tableswitch default -> 242, 0 -> 212, 1 -> 217, 2 -> 222, 3 -> 227, 4 -> 232, 5 -> 237
    //   212: bipush #111
    //   214: goto -> 244
    //   217: bipush #80
    //   219: goto -> 244
    //   222: bipush #108
    //   224: goto -> 244
    //   227: bipush #85
    //   229: goto -> 244
    //   232: bipush #72
    //   234: goto -> 244
    //   237: bipush #116
    //   239: goto -> 244
    //   242: bipush #108
    //   244: ixor
    //   245: ixor
    //   246: i2c
    //   247: castore
    //   248: iinc #6, 1
    //   251: dup
    //   252: ifne -> 260
    //   255: dup2
    //   256: dup_x1
    //   257: goto -> 165
    //   260: dup2_x1
    //   261: pop2
    //   262: dup_x2
    //   263: iload #6
    //   265: if_icmpgt -> 161
    //   268: pop
    //   269: new java/lang/String
    //   272: dup_x1
    //   273: swap
    //   274: invokespecial <init> : ([C)V
    //   277: invokevirtual intern : ()Ljava/lang/String;
    //   280: swap
    //   281: pop
    //   282: swap
    //   283: tableswitch default -> 39, 0 -> 98
    //   300: sipush #-10235
    //   303: sipush #-15693
    //   306: invokestatic a : (II)Ljava/lang/String;
    //   309: putstatic burp/Zl3j.Zr : Ljava/lang/String;
    //   312: new java/math/BigInteger
    //   315: dup
    //   316: bipush #32
    //   318: newarray byte
    //   320: dup
    //   321: iconst_0
    //   322: bipush #46
    //   324: bastore
    //   325: dup
    //   326: iconst_1
    //   327: bipush #79
    //   329: bastore
    //   330: dup
    //   331: iconst_2
    //   332: bipush #-98
    //   334: bastore
    //   335: dup
    //   336: iconst_3
    //   337: bipush #-93
    //   339: bastore
    //   340: dup
    //   341: iconst_4
    //   342: bipush #87
    //   344: bastore
    //   345: dup
    //   346: iconst_5
    //   347: bipush #93
    //   349: bastore
    //   350: dup
    //   351: bipush #6
    //   353: bipush #94
    //   355: bastore
    //   356: dup
    //   357: bipush #7
    //   359: bipush #-115
    //   361: bastore
    //   362: dup
    //   363: bipush #8
    //   365: bipush #57
    //   367: bastore
    //   368: dup
    //   369: bipush #9
    //   371: bipush #-65
    //   373: bastore
    //   374: dup
    //   375: bipush #10
    //   377: bipush #-42
    //   379: bastore
    //   380: dup
    //   381: bipush #11
    //   383: bipush #-17
    //   385: bastore
    //   386: dup
    //   387: bipush #12
    //   389: bipush #-72
    //   391: bastore
    //   392: dup
    //   393: bipush #13
    //   395: bipush #-82
    //   397: bastore
    //   398: dup
    //   399: bipush #14
    //   401: bipush #102
    //   403: bastore
    //   404: dup
    //   405: bipush #15
    //   407: bipush #-105
    //   409: bastore
    //   410: dup
    //   411: bipush #16
    //   413: bipush #-83
    //   415: bastore
    //   416: dup
    //   417: bipush #17
    //   419: bipush #64
    //   421: bastore
    //   422: dup
    //   423: bipush #18
    //   425: bipush #-9
    //   427: bastore
    //   428: dup
    //   429: bipush #19
    //   431: bipush #-99
    //   433: bastore
    //   434: dup
    //   435: bipush #20
    //   437: bipush #-19
    //   439: bastore
    //   440: dup
    //   441: bipush #21
    //   443: bipush #81
    //   445: bastore
    //   446: dup
    //   447: bipush #22
    //   449: bipush #-114
    //   451: bastore
    //   452: dup
    //   453: bipush #23
    //   455: bipush #-115
    //   457: bastore
    //   458: dup
    //   459: bipush #24
    //   461: bipush #30
    //   463: bastore
    //   464: dup
    //   465: bipush #25
    //   467: bipush #48
    //   469: bastore
    //   470: dup
    //   471: bipush #26
    //   473: bipush #-125
    //   475: bastore
    //   476: dup
    //   477: bipush #27
    //   479: bipush #53
    //   481: bastore
    //   482: dup
    //   483: bipush #28
    //   485: bipush #-88
    //   487: bastore
    //   488: dup
    //   489: bipush #29
    //   491: bipush #32
    //   493: bastore
    //   494: dup
    //   495: bipush #30
    //   497: bipush #-117
    //   499: bastore
    //   500: dup
    //   501: bipush #31
    //   503: bipush #-75
    //   505: bastore
    //   506: invokespecial <init> : ([B)V
    //   509: putstatic burp/Zl3j.ZY : Ljava/lang/Object;
    //   512: return
  }
  
  private static Throwable a(Throwable paramThrowable) {
    return paramThrowable;
  }
  
  private static String a(int paramInt1, int paramInt2) {
    int i = (paramInt1 ^ 0xFFFFD802) & 0xFFFF;
    if (b[i] == null) {
      char[] arrayOfChar = a[i].toCharArray();
      switch (arrayOfChar[0] & 0xFF) {
        case 0:
        
        case 1:
        
        case 2:
        
        case 3:
        
        case 4:
        
        case 5:
        
        case 6:
        
        case 7:
        
        case 8:
        
        case 9:
        
        case 10:
        
        case 11:
        
        case 12:
        
        case 13:
        
        case 14:
        
        case 15:
        
        case 16:
        
        case 17:
        
        case 18:
        
        case 19:
        
        case 20:
        
        case 21:
        
        case 22:
        
        case 23:
        
        case 24:
        
        case 25:
        
        case 26:
        
        case 27:
        
        case 28:
        
        case 29:
        
        case 30:
        
        case 31:
        
        case 32:
        
        case 33:
        
        case 34:
        
        case 35:
        
        case 36:
        
        case 37:
        
        case 38:
        
        case 39:
        
        case 40:
        
        case 41:
        
        case 42:
        
        case 43:
        
        case 44:
        
        case 45:
        
        case 46:
        
        case 47:
        
        case 48:
        
        case 49:
        
        case 50:
        
        case 51:
        
        case 52:
        
        case 53:
        
        case 54:
        
        case 55:
        
        case 56:
        
        case 57:
        
        case 58:
        
        case 59:
        
        case 60:
        
        case 61:
        
        case 62:
        
        case 63:
        
        case 64:
        
        case 65:
        
        case 66:
        
        case 67:
        
        case 68:
        
        case 69:
        
        case 70:
        
        case 71:
        
        case 72:
        
        case 73:
        
        case 74:
        
        case 75:
        
        case 76:
        
        case 77:
        
        case 78:
        
        case 79:
        
        case 80:
        
        case 81:
        
        case 82:
        
        case 83:
        
        case 84:
        
        case 85:
        
        case 86:
        
        case 87:
        
        case 88:
        
        case 89:
        
        case 90:
        
        case 91:
        
        case 92:
        
        case 93:
        
        case 94:
        
        case 95:
        
        case 96:
        
        case 97:
        
        case 98:
        
        case 99:
        
        case 100:
        
        case 101:
        
        case 102:
        
        case 103:
        
        case 104:
        
        case 105:
        
        case 106:
        
        case 107:
        
        case 108:
        
        case 109:
        
        case 110:
        
        case 111:
        
        case 112:
        
        case 113:
        
        case 114:
        
        case 115:
        
        case 116:
        
        case 117:
        
        case 118:
        
        case 119:
        
        case 120:
        
        case 121:
        
        case 122:
        
        case 123:
        
        case 124:
        
        case 125:
        
        case 126:
        
        case 127:
        
        case 128:
        
        case 129:
        
        case 130:
        
        case 131:
        
        case 132:
        
        case 133:
        
        case 134:
        
        case 135:
        
        case 136:
        
        case 137:
        
        case 138:
        
        case 139:
        
        case 140:
        
        case 141:
        
        case 142:
        
        case 143:
        
        case 144:
        
        case 145:
        
        case 146:
        
        case 147:
        
        case 148:
        
        case 149:
        
        case 150:
        
        case 151:
        
        case 152:
        
        case 153:
        
        case 154:
        
        case 155:
        
        case 156:
        
        case 157:
        
        case 158:
        
        case 159:
        
        case 160:
        
        case 161:
        
        case 162:
        
        case 163:
        
        case 164:
        
        case 165:
        
        case 166:
        
        case 167:
        
        case 168:
        
        case 169:
        
        case 170:
        
        case 171:
        
        case 172:
        
        case 173:
        
        case 174:
        
        case 175:
        
        case 176:
        
        case 177:
        
        case 178:
        
        case 179:
        
        case 180:
        
        case 181:
        
        case 182:
        
        case 183:
        
        case 184:
        
        case 185:
        
        case 186:
        
        case 187:
        
        case 188:
        
        case 189:
        
        case 190:
        
        case 191:
        
        case 192:
        
        case 193:
        
        case 194:
        
        case 195:
        
        case 196:
        
        case 197:
        
        case 198:
        
        case 199:
        
        case 200:
        
        case 201:
        
        case 202:
        
        case 203:
        
        case 204:
        
        case 205:
        
        case 206:
        
        case 207:
        
        case 208:
        
        case 209:
        
        case 210:
        
        case 211:
        
        case 212:
        
        case 213:
        
        case 214:
        
        case 215:
        
        case 216:
        
        case 217:
        
        case 218:
        
        case 219:
        
        case 220:
        
        case 221:
        
        case 222:
        
        case 223:
        
        case 224:
        
        case 225:
        
        case 226:
        
        case 227:
        
        case 228:
        
        case 229:
        
        case 230:
        
        case 231:
        
        case 232:
        
        case 233:
        
        case 234:
        
        case 235:
        
        case 236:
        
        case 237:
        
        case 238:
        
        case 239:
        
        case 240:
        
        case 241:
        
        case 242:
        
        case 243:
        
        case 244:
        
        case 245:
        
        case 246:
        
        case 247:
        
        case 248:
        
        case 249:
        
        case 250:
        
        case 251:
        
        case 252:
        
        case 253:
        
        case 254:
        
        default:
          break;
      } 
      char c = 'ÃŸ';
      int j = (paramInt2 & 0xFF) - c;
      if (j < 0)
        j += 256; 
      int k = ((paramInt2 & 0xFFFF) >>> 8) - c;
      if (k < 0)
        k += 256; 
      for (byte b = 0; b < arrayOfChar.length; b++) {
        int m = b % 2;
        if (m == 0) {
          arrayOfChar[b] = (char)(arrayOfChar[b] ^ j);
          j = ((j >>> 3 | j << 5) ^ arrayOfChar[b]) & 0xFF;
        } else {
          arrayOfChar[b] = (char)(arrayOfChar[b] ^ k);
          k = ((k >>> 3 | k << 5) ^ arrayOfChar[b]) & 0xFF;
        } 
      } 
      b[i] = (new String(arrayOfChar)).intern();
    } 
    return b[i];
  }
}


/* Location:              C:\Program Files\BurpSuitePro\burpsuite_pro.jar!\burp\Zl3j.class
 * Java compiler version: 21 (65.0)
 * JD-Core Version:       1.1.3
 */