package burp;

import java.math.BigInteger;

class Zl3l extends ClassLoader {
  static Object Zv;
  
  static String Z_;
  
  private static final String[] a;
  
  private static final String[] b;
  
  static void ZM(Object[] paramArrayOfObject, Object paramObject) throws Throwable {}
  
  static boolean Zh(Object[] paramArrayOfObject, Object paramObject) throws Throwable {
    // Byte code:
    //   0: invokestatic ZN : ()Z
    //   3: istore_2
    //   4: sipush #-12266
    //   7: sipush #-19035
    //   10: invokestatic a : (II)Ljava/lang/String;
    //   13: invokestatic forName : (Ljava/lang/String;)Ljava/lang/Class;
    //   16: invokestatic ZZ : (Ljava/lang/Object;)V
    //   19: getstatic burp/Zezn.Zh : Ljava/lang/Object;
    //   22: checkcast java/math/BigInteger
    //   25: invokevirtual toByteArray : ()[B
    //   28: astore_3
    //   29: bipush #32
    //   31: newarray int
    //   33: dup
    //   34: iconst_0
    //   35: ldc 943331329
    //   37: iastore
    //   38: dup
    //   39: iconst_1
    //   40: ldc 170788368
    //   42: iastore
    //   43: dup
    //   44: iconst_2
    //   45: ldc 1008414755
    //   47: iastore
    //   48: dup
    //   49: iconst_3
    //   50: ldc 187049985
    //   52: iastore
    //   53: dup
    //   54: iconst_4
    //   55: ldc 1010368540
    //   57: iastore
    //   58: dup
    //   59: iconst_5
    //   60: ldc 220604441
    //   62: iastore
    //   63: dup
    //   64: bipush #6
    //   66: ldc 940377620
    //   68: iastore
    //   69: dup
    //   70: bipush #7
    //   72: ldc 255209728
    //   74: iastore
    //   75: dup
    //   76: bipush #8
    //   78: ldc 689771012
    //   80: iastore
    //   81: dup
    //   82: bipush #9
    //   84: ldc 221709344
    //   86: iastore
    //   87: dup
    //   88: bipush #10
    //   90: ldc 957157408
    //   92: iastore
    //   93: dup
    //   94: bipush #11
    //   96: ldc 892536332
    //   98: iastore
    //   99: dup
    //   100: bipush #12
    //   102: ldc 722417666
    //   104: iastore
    //   105: dup
    //   106: bipush #13
    //   108: ldc 1026621720
    //   110: iastore
    //   111: dup
    //   112: bipush #14
    //   114: ldc 655302664
    //   116: iastore
    //   117: dup
    //   118: bipush #15
    //   120: ldc 890966315
    //   122: iastore
    //   123: dup
    //   124: bipush #16
    //   126: ldc 187632156
    //   128: iastore
    //   129: dup
    //   130: bipush #17
    //   132: ldc 874189824
    //   134: iastore
    //   135: dup
    //   136: bipush #18
    //   138: ldc 254150144
    //   140: iastore
    //   141: dup
    //   142: bipush #19
    //   144: ldc 924386310
    //   146: iastore
    //   147: dup
    //   148: bipush #20
    //   150: ldc 121057538
    //   152: iastore
    //   153: dup
    //   154: bipush #21
    //   156: ldc 840500228
    //   158: iastore
    //   159: dup
    //   160: bipush #22
    //   162: ldc 389160971
    //   164: iastore
    //   165: dup
    //   166: bipush #23
    //   168: ldc 907870729
    //   170: iastore
    //   171: dup
    //   172: bipush #24
    //   174: ldc 389426184
    //   176: iastore
    //   177: dup
    //   178: bipush #25
    //   180: ldc 973875457
    //   182: iastore
    //   183: dup
    //   184: bipush #26
    //   186: ldc 372376604
    //   188: iastore
    //   189: dup
    //   190: bipush #27
    //   192: ldc 707731490
    //   194: iastore
    //   195: dup
    //   196: bipush #28
    //   198: ldc 1043334948
    //   200: iastore
    //   201: dup
    //   202: bipush #29
    //   204: ldc 439222784
    //   206: iastore
    //   207: dup
    //   208: bipush #30
    //   210: ldc 876216579
    //   212: iastore
    //   213: dup
    //   214: bipush #31
    //   216: ldc 455999525
    //   218: iastore
    //   219: astore #5
    //   221: bipush #8
    //   223: aload_3
    //   224: arraylength
    //   225: bipush #8
    //   227: irem
    //   228: isub
    //   229: istore #6
    //   231: aload_3
    //   232: arraylength
    //   233: iload #6
    //   235: iadd
    //   236: newarray byte
    //   238: astore #7
    //   240: iconst_0
    //   241: istore #8
    //   243: iload #8
    //   245: aload_3
    //   246: arraylength
    //   247: if_icmpge -> 266
    //   250: aload #7
    //   252: iload #8
    //   254: aload_3
    //   255: iload #8
    //   257: baload
    //   258: bastore
    //   259: iinc #8, 1
    //   262: iload_2
    //   263: ifne -> 243
    //   266: aload_3
    //   267: arraylength
    //   268: istore #8
    //   270: iload #8
    //   272: aload #7
    //   274: arraylength
    //   275: if_icmpge -> 293
    //   278: aload #7
    //   280: iload #8
    //   282: iload #6
    //   284: i2b
    //   285: bastore
    //   286: iinc #8, 1
    //   289: iload_2
    //   290: ifne -> 270
    //   293: aload #7
    //   295: astore_3
    //   296: bipush #64
    //   298: newarray int
    //   300: dup
    //   301: iconst_0
    //   302: ldc 16843776
    //   304: iastore
    //   305: dup
    //   306: iconst_1
    //   307: iconst_0
    //   308: iastore
    //   309: dup
    //   310: iconst_2
    //   311: ldc 65536
    //   313: iastore
    //   314: dup
    //   315: iconst_3
    //   316: ldc 16843780
    //   318: iastore
    //   319: dup
    //   320: iconst_4
    //   321: ldc 16842756
    //   323: iastore
    //   324: dup
    //   325: iconst_5
    //   326: ldc 66564
    //   328: iastore
    //   329: dup
    //   330: bipush #6
    //   332: iconst_4
    //   333: iastore
    //   334: dup
    //   335: bipush #7
    //   337: ldc 65536
    //   339: iastore
    //   340: dup
    //   341: bipush #8
    //   343: sipush #1024
    //   346: iastore
    //   347: dup
    //   348: bipush #9
    //   350: ldc 16843776
    //   352: iastore
    //   353: dup
    //   354: bipush #10
    //   356: ldc 16843780
    //   358: iastore
    //   359: dup
    //   360: bipush #11
    //   362: sipush #1024
    //   365: iastore
    //   366: dup
    //   367: bipush #12
    //   369: ldc 16778244
    //   371: iastore
    //   372: dup
    //   373: bipush #13
    //   375: ldc 16842756
    //   377: iastore
    //   378: dup
    //   379: bipush #14
    //   381: ldc 16777216
    //   383: iastore
    //   384: dup
    //   385: bipush #15
    //   387: iconst_4
    //   388: iastore
    //   389: dup
    //   390: bipush #16
    //   392: sipush #1028
    //   395: iastore
    //   396: dup
    //   397: bipush #17
    //   399: ldc 16778240
    //   401: iastore
    //   402: dup
    //   403: bipush #18
    //   405: ldc 16778240
    //   407: iastore
    //   408: dup
    //   409: bipush #19
    //   411: ldc 66560
    //   413: iastore
    //   414: dup
    //   415: bipush #20
    //   417: ldc 66560
    //   419: iastore
    //   420: dup
    //   421: bipush #21
    //   423: ldc 16842752
    //   425: iastore
    //   426: dup
    //   427: bipush #22
    //   429: ldc 16842752
    //   431: iastore
    //   432: dup
    //   433: bipush #23
    //   435: ldc 16778244
    //   437: iastore
    //   438: dup
    //   439: bipush #24
    //   441: ldc 65540
    //   443: iastore
    //   444: dup
    //   445: bipush #25
    //   447: ldc 16777220
    //   449: iastore
    //   450: dup
    //   451: bipush #26
    //   453: ldc 16777220
    //   455: iastore
    //   456: dup
    //   457: bipush #27
    //   459: ldc 65540
    //   461: iastore
    //   462: dup
    //   463: bipush #28
    //   465: iconst_0
    //   466: iastore
    //   467: dup
    //   468: bipush #29
    //   470: sipush #1028
    //   473: iastore
    //   474: dup
    //   475: bipush #30
    //   477: ldc 66564
    //   479: iastore
    //   480: dup
    //   481: bipush #31
    //   483: ldc 16777216
    //   485: iastore
    //   486: dup
    //   487: bipush #32
    //   489: ldc 65536
    //   491: iastore
    //   492: dup
    //   493: bipush #33
    //   495: ldc 16843780
    //   497: iastore
    //   498: dup
    //   499: bipush #34
    //   501: iconst_4
    //   502: iastore
    //   503: dup
    //   504: bipush #35
    //   506: ldc 16842752
    //   508: iastore
    //   509: dup
    //   510: bipush #36
    //   512: ldc 16843776
    //   514: iastore
    //   515: dup
    //   516: bipush #37
    //   518: ldc 16777216
    //   520: iastore
    //   521: dup
    //   522: bipush #38
    //   524: ldc 16777216
    //   526: iastore
    //   527: dup
    //   528: bipush #39
    //   530: sipush #1024
    //   533: iastore
    //   534: dup
    //   535: bipush #40
    //   537: ldc 16842756
    //   539: iastore
    //   540: dup
    //   541: bipush #41
    //   543: ldc 65536
    //   545: iastore
    //   546: dup
    //   547: bipush #42
    //   549: ldc 66560
    //   551: iastore
    //   552: dup
    //   553: bipush #43
    //   555: ldc 16777220
    //   557: iastore
    //   558: dup
    //   559: bipush #44
    //   561: sipush #1024
    //   564: iastore
    //   565: dup
    //   566: bipush #45
    //   568: iconst_4
    //   569: iastore
    //   570: dup
    //   571: bipush #46
    //   573: ldc 16778244
    //   575: iastore
    //   576: dup
    //   577: bipush #47
    //   579: ldc 66564
    //   581: iastore
    //   582: dup
    //   583: bipush #48
    //   585: ldc 16843780
    //   587: iastore
    //   588: dup
    //   589: bipush #49
    //   591: ldc 65540
    //   593: iastore
    //   594: dup
    //   595: bipush #50
    //   597: ldc 16842752
    //   599: iastore
    //   600: dup
    //   601: bipush #51
    //   603: ldc 16778244
    //   605: iastore
    //   606: dup
    //   607: bipush #52
    //   609: ldc 16777220
    //   611: iastore
    //   612: dup
    //   613: bipush #53
    //   615: sipush #1028
    //   618: iastore
    //   619: dup
    //   620: bipush #54
    //   622: ldc 66564
    //   624: iastore
    //   625: dup
    //   626: bipush #55
    //   628: ldc 16843776
    //   630: iastore
    //   631: dup
    //   632: bipush #56
    //   634: sipush #1028
    //   637: iastore
    //   638: dup
    //   639: bipush #57
    //   641: ldc 16778240
    //   643: iastore
    //   644: dup
    //   645: bipush #58
    //   647: ldc 16778240
    //   649: iastore
    //   650: dup
    //   651: bipush #59
    //   653: iconst_0
    //   654: iastore
    //   655: dup
    //   656: bipush #60
    //   658: ldc 65540
    //   660: iastore
    //   661: dup
    //   662: bipush #61
    //   664: ldc 66560
    //   666: iastore
    //   667: dup
    //   668: bipush #62
    //   670: iconst_0
    //   671: iastore
    //   672: dup
    //   673: bipush #63
    //   675: ldc 16842756
    //   677: iastore
    //   678: astore #8
    //   680: bipush #64
    //   682: newarray int
    //   684: dup
    //   685: iconst_0
    //   686: ldc -2146402272
    //   688: iastore
    //   689: dup
    //   690: iconst_1
    //   691: ldc -2147450880
    //   693: iastore
    //   694: dup
    //   695: iconst_2
    //   696: ldc 32768
    //   698: iastore
    //   699: dup
    //   700: iconst_3
    //   701: ldc 1081376
    //   703: iastore
    //   704: dup
    //   705: iconst_4
    //   706: ldc 1048576
    //   708: iastore
    //   709: dup
    //   710: iconst_5
    //   711: bipush #32
    //   713: iastore
    //   714: dup
    //   715: bipush #6
    //   717: ldc -2146435040
    //   719: iastore
    //   720: dup
    //   721: bipush #7
    //   723: ldc -2147450848
    //   725: iastore
    //   726: dup
    //   727: bipush #8
    //   729: ldc -2147483616
    //   731: iastore
    //   732: dup
    //   733: bipush #9
    //   735: ldc -2146402272
    //   737: iastore
    //   738: dup
    //   739: bipush #10
    //   741: ldc -2146402304
    //   743: iastore
    //   744: dup
    //   745: bipush #11
    //   747: ldc -2147483648
    //   749: iastore
    //   750: dup
    //   751: bipush #12
    //   753: ldc -2147450880
    //   755: iastore
    //   756: dup
    //   757: bipush #13
    //   759: ldc 1048576
    //   761: iastore
    //   762: dup
    //   763: bipush #14
    //   765: bipush #32
    //   767: iastore
    //   768: dup
    //   769: bipush #15
    //   771: ldc -2146435040
    //   773: iastore
    //   774: dup
    //   775: bipush #16
    //   777: ldc 1081344
    //   779: iastore
    //   780: dup
    //   781: bipush #17
    //   783: ldc 1048608
    //   785: iastore
    //   786: dup
    //   787: bipush #18
    //   789: ldc -2147450848
    //   791: iastore
    //   792: dup
    //   793: bipush #19
    //   795: iconst_0
    //   796: iastore
    //   797: dup
    //   798: bipush #20
    //   800: ldc -2147483648
    //   802: iastore
    //   803: dup
    //   804: bipush #21
    //   806: ldc 32768
    //   808: iastore
    //   809: dup
    //   810: bipush #22
    //   812: ldc 1081376
    //   814: iastore
    //   815: dup
    //   816: bipush #23
    //   818: ldc -2146435072
    //   820: iastore
    //   821: dup
    //   822: bipush #24
    //   824: ldc 1048608
    //   826: iastore
    //   827: dup
    //   828: bipush #25
    //   830: ldc -2147483616
    //   832: iastore
    //   833: dup
    //   834: bipush #26
    //   836: iconst_0
    //   837: iastore
    //   838: dup
    //   839: bipush #27
    //   841: ldc 1081344
    //   843: iastore
    //   844: dup
    //   845: bipush #28
    //   847: ldc 32800
    //   849: iastore
    //   850: dup
    //   851: bipush #29
    //   853: ldc -2146402304
    //   855: iastore
    //   856: dup
    //   857: bipush #30
    //   859: ldc -2146435072
    //   861: iastore
    //   862: dup
    //   863: bipush #31
    //   865: ldc 32800
    //   867: iastore
    //   868: dup
    //   869: bipush #32
    //   871: iconst_0
    //   872: iastore
    //   873: dup
    //   874: bipush #33
    //   876: ldc 1081376
    //   878: iastore
    //   879: dup
    //   880: bipush #34
    //   882: ldc -2146435040
    //   884: iastore
    //   885: dup
    //   886: bipush #35
    //   888: ldc 1048576
    //   890: iastore
    //   891: dup
    //   892: bipush #36
    //   894: ldc -2147450848
    //   896: iastore
    //   897: dup
    //   898: bipush #37
    //   900: ldc -2146435072
    //   902: iastore
    //   903: dup
    //   904: bipush #38
    //   906: ldc -2146402304
    //   908: iastore
    //   909: dup
    //   910: bipush #39
    //   912: ldc 32768
    //   914: iastore
    //   915: dup
    //   916: bipush #40
    //   918: ldc -2146435072
    //   920: iastore
    //   921: dup
    //   922: bipush #41
    //   924: ldc -2147450880
    //   926: iastore
    //   927: dup
    //   928: bipush #42
    //   930: bipush #32
    //   932: iastore
    //   933: dup
    //   934: bipush #43
    //   936: ldc -2146402272
    //   938: iastore
    //   939: dup
    //   940: bipush #44
    //   942: ldc 1081376
    //   944: iastore
    //   945: dup
    //   946: bipush #45
    //   948: bipush #32
    //   950: iastore
    //   951: dup
    //   952: bipush #46
    //   954: ldc 32768
    //   956: iastore
    //   957: dup
    //   958: bipush #47
    //   960: ldc -2147483648
    //   962: iastore
    //   963: dup
    //   964: bipush #48
    //   966: ldc 32800
    //   968: iastore
    //   969: dup
    //   970: bipush #49
    //   972: ldc -2146402304
    //   974: iastore
    //   975: dup
    //   976: bipush #50
    //   978: ldc 1048576
    //   980: iastore
    //   981: dup
    //   982: bipush #51
    //   984: ldc -2147483616
    //   986: iastore
    //   987: dup
    //   988: bipush #52
    //   990: ldc 1048608
    //   992: iastore
    //   993: dup
    //   994: bipush #53
    //   996: ldc -2147450848
    //   998: iastore
    //   999: dup
    //   1000: bipush #54
    //   1002: ldc -2147483616
    //   1004: iastore
    //   1005: dup
    //   1006: bipush #55
    //   1008: ldc 1048608
    //   1010: iastore
    //   1011: dup
    //   1012: bipush #56
    //   1014: ldc 1081344
    //   1016: iastore
    //   1017: dup
    //   1018: bipush #57
    //   1020: iconst_0
    //   1021: iastore
    //   1022: dup
    //   1023: bipush #58
    //   1025: ldc -2147450880
    //   1027: iastore
    //   1028: dup
    //   1029: bipush #59
    //   1031: ldc 32800
    //   1033: iastore
    //   1034: dup
    //   1035: bipush #60
    //   1037: ldc -2147483648
    //   1039: iastore
    //   1040: dup
    //   1041: bipush #61
    //   1043: ldc -2146435040
    //   1045: iastore
    //   1046: dup
    //   1047: bipush #62
    //   1049: ldc -2146402272
    //   1051: iastore
    //   1052: dup
    //   1053: bipush #63
    //   1055: ldc 1081344
    //   1057: iastore
    //   1058: astore #9
    //   1060: bipush #64
    //   1062: newarray int
    //   1064: dup
    //   1065: iconst_0
    //   1066: sipush #520
    //   1069: iastore
    //   1070: dup
    //   1071: iconst_1
    //   1072: ldc 134349312
    //   1074: iastore
    //   1075: dup
    //   1076: iconst_2
    //   1077: iconst_0
    //   1078: iastore
    //   1079: dup
    //   1080: iconst_3
    //   1081: ldc 134348808
    //   1083: iastore
    //   1084: dup
    //   1085: iconst_4
    //   1086: ldc 134218240
    //   1088: iastore
    //   1089: dup
    //   1090: iconst_5
    //   1091: iconst_0
    //   1092: iastore
    //   1093: dup
    //   1094: bipush #6
    //   1096: ldc 131592
    //   1098: iastore
    //   1099: dup
    //   1100: bipush #7
    //   1102: ldc 134218240
    //   1104: iastore
    //   1105: dup
    //   1106: bipush #8
    //   1108: ldc 131080
    //   1110: iastore
    //   1111: dup
    //   1112: bipush #9
    //   1114: ldc 134217736
    //   1116: iastore
    //   1117: dup
    //   1118: bipush #10
    //   1120: ldc 134217736
    //   1122: iastore
    //   1123: dup
    //   1124: bipush #11
    //   1126: ldc 131072
    //   1128: iastore
    //   1129: dup
    //   1130: bipush #12
    //   1132: ldc 134349320
    //   1134: iastore
    //   1135: dup
    //   1136: bipush #13
    //   1138: ldc 131080
    //   1140: iastore
    //   1141: dup
    //   1142: bipush #14
    //   1144: ldc 134348800
    //   1146: iastore
    //   1147: dup
    //   1148: bipush #15
    //   1150: sipush #520
    //   1153: iastore
    //   1154: dup
    //   1155: bipush #16
    //   1157: ldc 134217728
    //   1159: iastore
    //   1160: dup
    //   1161: bipush #17
    //   1163: bipush #8
    //   1165: iastore
    //   1166: dup
    //   1167: bipush #18
    //   1169: ldc 134349312
    //   1171: iastore
    //   1172: dup
    //   1173: bipush #19
    //   1175: sipush #512
    //   1178: iastore
    //   1179: dup
    //   1180: bipush #20
    //   1182: ldc 131584
    //   1184: iastore
    //   1185: dup
    //   1186: bipush #21
    //   1188: ldc 134348800
    //   1190: iastore
    //   1191: dup
    //   1192: bipush #22
    //   1194: ldc 134348808
    //   1196: iastore
    //   1197: dup
    //   1198: bipush #23
    //   1200: ldc 131592
    //   1202: iastore
    //   1203: dup
    //   1204: bipush #24
    //   1206: ldc 134218248
    //   1208: iastore
    //   1209: dup
    //   1210: bipush #25
    //   1212: ldc 131584
    //   1214: iastore
    //   1215: dup
    //   1216: bipush #26
    //   1218: ldc 131072
    //   1220: iastore
    //   1221: dup
    //   1222: bipush #27
    //   1224: ldc 134218248
    //   1226: iastore
    //   1227: dup
    //   1228: bipush #28
    //   1230: bipush #8
    //   1232: iastore
    //   1233: dup
    //   1234: bipush #29
    //   1236: ldc 134349320
    //   1238: iastore
    //   1239: dup
    //   1240: bipush #30
    //   1242: sipush #512
    //   1245: iastore
    //   1246: dup
    //   1247: bipush #31
    //   1249: ldc 134217728
    //   1251: iastore
    //   1252: dup
    //   1253: bipush #32
    //   1255: ldc 134349312
    //   1257: iastore
    //   1258: dup
    //   1259: bipush #33
    //   1261: ldc 134217728
    //   1263: iastore
    //   1264: dup
    //   1265: bipush #34
    //   1267: ldc 131080
    //   1269: iastore
    //   1270: dup
    //   1271: bipush #35
    //   1273: sipush #520
    //   1276: iastore
    //   1277: dup
    //   1278: bipush #36
    //   1280: ldc 131072
    //   1282: iastore
    //   1283: dup
    //   1284: bipush #37
    //   1286: ldc 134349312
    //   1288: iastore
    //   1289: dup
    //   1290: bipush #38
    //   1292: ldc 134218240
    //   1294: iastore
    //   1295: dup
    //   1296: bipush #39
    //   1298: iconst_0
    //   1299: iastore
    //   1300: dup
    //   1301: bipush #40
    //   1303: sipush #512
    //   1306: iastore
    //   1307: dup
    //   1308: bipush #41
    //   1310: ldc 131080
    //   1312: iastore
    //   1313: dup
    //   1314: bipush #42
    //   1316: ldc 134349320
    //   1318: iastore
    //   1319: dup
    //   1320: bipush #43
    //   1322: ldc 134218240
    //   1324: iastore
    //   1325: dup
    //   1326: bipush #44
    //   1328: ldc 134217736
    //   1330: iastore
    //   1331: dup
    //   1332: bipush #45
    //   1334: sipush #512
    //   1337: iastore
    //   1338: dup
    //   1339: bipush #46
    //   1341: iconst_0
    //   1342: iastore
    //   1343: dup
    //   1344: bipush #47
    //   1346: ldc 134348808
    //   1348: iastore
    //   1349: dup
    //   1350: bipush #48
    //   1352: ldc 134218248
    //   1354: iastore
    //   1355: dup
    //   1356: bipush #49
    //   1358: ldc 131072
    //   1360: iastore
    //   1361: dup
    //   1362: bipush #50
    //   1364: ldc 134217728
    //   1366: iastore
    //   1367: dup
    //   1368: bipush #51
    //   1370: ldc 134349320
    //   1372: iastore
    //   1373: dup
    //   1374: bipush #52
    //   1376: bipush #8
    //   1378: iastore
    //   1379: dup
    //   1380: bipush #53
    //   1382: ldc 131592
    //   1384: iastore
    //   1385: dup
    //   1386: bipush #54
    //   1388: ldc 131584
    //   1390: iastore
    //   1391: dup
    //   1392: bipush #55
    //   1394: ldc 134217736
    //   1396: iastore
    //   1397: dup
    //   1398: bipush #56
    //   1400: ldc 134348800
    //   1402: iastore
    //   1403: dup
    //   1404: bipush #57
    //   1406: ldc 134218248
    //   1408: iastore
    //   1409: dup
    //   1410: bipush #58
    //   1412: sipush #520
    //   1415: iastore
    //   1416: dup
    //   1417: bipush #59
    //   1419: ldc 134348800
    //   1421: iastore
    //   1422: dup
    //   1423: bipush #60
    //   1425: ldc 131592
    //   1427: iastore
    //   1428: dup
    //   1429: bipush #61
    //   1431: bipush #8
    //   1433: iastore
    //   1434: dup
    //   1435: bipush #62
    //   1437: ldc 134348808
    //   1439: iastore
    //   1440: dup
    //   1441: bipush #63
    //   1443: ldc 131584
    //   1445: iastore
    //   1446: astore #10
    //   1448: bipush #64
    //   1450: newarray int
    //   1452: dup
    //   1453: iconst_0
    //   1454: ldc 8396801
    //   1456: iastore
    //   1457: dup
    //   1458: iconst_1
    //   1459: sipush #8321
    //   1462: iastore
    //   1463: dup
    //   1464: iconst_2
    //   1465: sipush #8321
    //   1468: iastore
    //   1469: dup
    //   1470: iconst_3
    //   1471: sipush #128
    //   1474: iastore
    //   1475: dup
    //   1476: iconst_4
    //   1477: ldc 8396928
    //   1479: iastore
    //   1480: dup
    //   1481: iconst_5
    //   1482: ldc 8388737
    //   1484: iastore
    //   1485: dup
    //   1486: bipush #6
    //   1488: ldc 8388609
    //   1490: iastore
    //   1491: dup
    //   1492: bipush #7
    //   1494: sipush #8193
    //   1497: iastore
    //   1498: dup
    //   1499: bipush #8
    //   1501: iconst_0
    //   1502: iastore
    //   1503: dup
    //   1504: bipush #9
    //   1506: ldc 8396800
    //   1508: iastore
    //   1509: dup
    //   1510: bipush #10
    //   1512: ldc 8396800
    //   1514: iastore
    //   1515: dup
    //   1516: bipush #11
    //   1518: ldc 8396929
    //   1520: iastore
    //   1521: dup
    //   1522: bipush #12
    //   1524: sipush #129
    //   1527: iastore
    //   1528: dup
    //   1529: bipush #13
    //   1531: iconst_0
    //   1532: iastore
    //   1533: dup
    //   1534: bipush #14
    //   1536: ldc 8388736
    //   1538: iastore
    //   1539: dup
    //   1540: bipush #15
    //   1542: ldc 8388609
    //   1544: iastore
    //   1545: dup
    //   1546: bipush #16
    //   1548: iconst_1
    //   1549: iastore
    //   1550: dup
    //   1551: bipush #17
    //   1553: sipush #8192
    //   1556: iastore
    //   1557: dup
    //   1558: bipush #18
    //   1560: ldc 8388608
    //   1562: iastore
    //   1563: dup
    //   1564: bipush #19
    //   1566: ldc 8396801
    //   1568: iastore
    //   1569: dup
    //   1570: bipush #20
    //   1572: sipush #128
    //   1575: iastore
    //   1576: dup
    //   1577: bipush #21
    //   1579: ldc 8388608
    //   1581: iastore
    //   1582: dup
    //   1583: bipush #22
    //   1585: sipush #8193
    //   1588: iastore
    //   1589: dup
    //   1590: bipush #23
    //   1592: sipush #8320
    //   1595: iastore
    //   1596: dup
    //   1597: bipush #24
    //   1599: ldc 8388737
    //   1601: iastore
    //   1602: dup
    //   1603: bipush #25
    //   1605: iconst_1
    //   1606: iastore
    //   1607: dup
    //   1608: bipush #26
    //   1610: sipush #8320
    //   1613: iastore
    //   1614: dup
    //   1615: bipush #27
    //   1617: ldc 8388736
    //   1619: iastore
    //   1620: dup
    //   1621: bipush #28
    //   1623: sipush #8192
    //   1626: iastore
    //   1627: dup
    //   1628: bipush #29
    //   1630: ldc 8396928
    //   1632: iastore
    //   1633: dup
    //   1634: bipush #30
    //   1636: ldc 8396929
    //   1638: iastore
    //   1639: dup
    //   1640: bipush #31
    //   1642: sipush #129
    //   1645: iastore
    //   1646: dup
    //   1647: bipush #32
    //   1649: ldc 8388736
    //   1651: iastore
    //   1652: dup
    //   1653: bipush #33
    //   1655: ldc 8388609
    //   1657: iastore
    //   1658: dup
    //   1659: bipush #34
    //   1661: ldc 8396800
    //   1663: iastore
    //   1664: dup
    //   1665: bipush #35
    //   1667: ldc 8396929
    //   1669: iastore
    //   1670: dup
    //   1671: bipush #36
    //   1673: sipush #129
    //   1676: iastore
    //   1677: dup
    //   1678: bipush #37
    //   1680: iconst_0
    //   1681: iastore
    //   1682: dup
    //   1683: bipush #38
    //   1685: iconst_0
    //   1686: iastore
    //   1687: dup
    //   1688: bipush #39
    //   1690: ldc 8396800
    //   1692: iastore
    //   1693: dup
    //   1694: bipush #40
    //   1696: sipush #8320
    //   1699: iastore
    //   1700: dup
    //   1701: bipush #41
    //   1703: ldc 8388736
    //   1705: iastore
    //   1706: dup
    //   1707: bipush #42
    //   1709: ldc 8388737
    //   1711: iastore
    //   1712: dup
    //   1713: bipush #43
    //   1715: iconst_1
    //   1716: iastore
    //   1717: dup
    //   1718: bipush #44
    //   1720: ldc 8396801
    //   1722: iastore
    //   1723: dup
    //   1724: bipush #45
    //   1726: sipush #8321
    //   1729: iastore
    //   1730: dup
    //   1731: bipush #46
    //   1733: sipush #8321
    //   1736: iastore
    //   1737: dup
    //   1738: bipush #47
    //   1740: sipush #128
    //   1743: iastore
    //   1744: dup
    //   1745: bipush #48
    //   1747: ldc 8396929
    //   1749: iastore
    //   1750: dup
    //   1751: bipush #49
    //   1753: sipush #129
    //   1756: iastore
    //   1757: dup
    //   1758: bipush #50
    //   1760: iconst_1
    //   1761: iastore
    //   1762: dup
    //   1763: bipush #51
    //   1765: sipush #8192
    //   1768: iastore
    //   1769: dup
    //   1770: bipush #52
    //   1772: ldc 8388609
    //   1774: iastore
    //   1775: dup
    //   1776: bipush #53
    //   1778: sipush #8193
    //   1781: iastore
    //   1782: dup
    //   1783: bipush #54
    //   1785: ldc 8396928
    //   1787: iastore
    //   1788: dup
    //   1789: bipush #55
    //   1791: ldc 8388737
    //   1793: iastore
    //   1794: dup
    //   1795: bipush #56
    //   1797: sipush #8193
    //   1800: iastore
    //   1801: dup
    //   1802: bipush #57
    //   1804: sipush #8320
    //   1807: iastore
    //   1808: dup
    //   1809: bipush #58
    //   1811: ldc 8388608
    //   1813: iastore
    //   1814: dup
    //   1815: bipush #59
    //   1817: ldc 8396801
    //   1819: iastore
    //   1820: dup
    //   1821: bipush #60
    //   1823: sipush #128
    //   1826: iastore
    //   1827: dup
    //   1828: bipush #61
    //   1830: ldc 8388608
    //   1832: iastore
    //   1833: dup
    //   1834: bipush #62
    //   1836: sipush #8192
    //   1839: iastore
    //   1840: dup
    //   1841: bipush #63
    //   1843: ldc 8396928
    //   1845: iastore
    //   1846: astore #11
    //   1848: bipush #64
    //   1850: newarray int
    //   1852: dup
    //   1853: iconst_0
    //   1854: sipush #256
    //   1857: iastore
    //   1858: dup
    //   1859: iconst_1
    //   1860: ldc 34078976
    //   1862: iastore
    //   1863: dup
    //   1864: iconst_2
    //   1865: ldc 34078720
    //   1867: iastore
    //   1868: dup
    //   1869: iconst_3
    //   1870: ldc 1107296512
    //   1872: iastore
    //   1873: dup
    //   1874: iconst_4
    //   1875: ldc 524288
    //   1877: iastore
    //   1878: dup
    //   1879: iconst_5
    //   1880: sipush #256
    //   1883: iastore
    //   1884: dup
    //   1885: bipush #6
    //   1887: ldc 1073741824
    //   1889: iastore
    //   1890: dup
    //   1891: bipush #7
    //   1893: ldc 34078720
    //   1895: iastore
    //   1896: dup
    //   1897: bipush #8
    //   1899: ldc 1074266368
    //   1901: iastore
    //   1902: dup
    //   1903: bipush #9
    //   1905: ldc 524288
    //   1907: iastore
    //   1908: dup
    //   1909: bipush #10
    //   1911: ldc 33554688
    //   1913: iastore
    //   1914: dup
    //   1915: bipush #11
    //   1917: ldc 1074266368
    //   1919: iastore
    //   1920: dup
    //   1921: bipush #12
    //   1923: ldc 1107296512
    //   1925: iastore
    //   1926: dup
    //   1927: bipush #13
    //   1929: ldc 1107820544
    //   1931: iastore
    //   1932: dup
    //   1933: bipush #14
    //   1935: ldc 524544
    //   1937: iastore
    //   1938: dup
    //   1939: bipush #15
    //   1941: ldc 1073741824
    //   1943: iastore
    //   1944: dup
    //   1945: bipush #16
    //   1947: ldc 33554432
    //   1949: iastore
    //   1950: dup
    //   1951: bipush #17
    //   1953: ldc 1074266112
    //   1955: iastore
    //   1956: dup
    //   1957: bipush #18
    //   1959: ldc 1074266112
    //   1961: iastore
    //   1962: dup
    //   1963: bipush #19
    //   1965: iconst_0
    //   1966: iastore
    //   1967: dup
    //   1968: bipush #20
    //   1970: ldc 1073742080
    //   1972: iastore
    //   1973: dup
    //   1974: bipush #21
    //   1976: ldc 1107820800
    //   1978: iastore
    //   1979: dup
    //   1980: bipush #22
    //   1982: ldc 1107820800
    //   1984: iastore
    //   1985: dup
    //   1986: bipush #23
    //   1988: ldc 33554688
    //   1990: iastore
    //   1991: dup
    //   1992: bipush #24
    //   1994: ldc 1107820544
    //   1996: iastore
    //   1997: dup
    //   1998: bipush #25
    //   2000: ldc 1073742080
    //   2002: iastore
    //   2003: dup
    //   2004: bipush #26
    //   2006: iconst_0
    //   2007: iastore
    //   2008: dup
    //   2009: bipush #27
    //   2011: ldc 1107296256
    //   2013: iastore
    //   2014: dup
    //   2015: bipush #28
    //   2017: ldc 34078976
    //   2019: iastore
    //   2020: dup
    //   2021: bipush #29
    //   2023: ldc 33554432
    //   2025: iastore
    //   2026: dup
    //   2027: bipush #30
    //   2029: ldc 1107296256
    //   2031: iastore
    //   2032: dup
    //   2033: bipush #31
    //   2035: ldc 524544
    //   2037: iastore
    //   2038: dup
    //   2039: bipush #32
    //   2041: ldc 524288
    //   2043: iastore
    //   2044: dup
    //   2045: bipush #33
    //   2047: ldc 1107296512
    //   2049: iastore
    //   2050: dup
    //   2051: bipush #34
    //   2053: sipush #256
    //   2056: iastore
    //   2057: dup
    //   2058: bipush #35
    //   2060: ldc 33554432
    //   2062: iastore
    //   2063: dup
    //   2064: bipush #36
    //   2066: ldc 1073741824
    //   2068: iastore
    //   2069: dup
    //   2070: bipush #37
    //   2072: ldc 34078720
    //   2074: iastore
    //   2075: dup
    //   2076: bipush #38
    //   2078: ldc 1107296512
    //   2080: iastore
    //   2081: dup
    //   2082: bipush #39
    //   2084: ldc 1074266368
    //   2086: iastore
    //   2087: dup
    //   2088: bipush #40
    //   2090: ldc 33554688
    //   2092: iastore
    //   2093: dup
    //   2094: bipush #41
    //   2096: ldc 1073741824
    //   2098: iastore
    //   2099: dup
    //   2100: bipush #42
    //   2102: ldc 1107820544
    //   2104: iastore
    //   2105: dup
    //   2106: bipush #43
    //   2108: ldc 34078976
    //   2110: iastore
    //   2111: dup
    //   2112: bipush #44
    //   2114: ldc 1074266368
    //   2116: iastore
    //   2117: dup
    //   2118: bipush #45
    //   2120: sipush #256
    //   2123: iastore
    //   2124: dup
    //   2125: bipush #46
    //   2127: ldc 33554432
    //   2129: iastore
    //   2130: dup
    //   2131: bipush #47
    //   2133: ldc 1107820544
    //   2135: iastore
    //   2136: dup
    //   2137: bipush #48
    //   2139: ldc 1107820800
    //   2141: iastore
    //   2142: dup
    //   2143: bipush #49
    //   2145: ldc 524544
    //   2147: iastore
    //   2148: dup
    //   2149: bipush #50
    //   2151: ldc 1107296256
    //   2153: iastore
    //   2154: dup
    //   2155: bipush #51
    //   2157: ldc 1107820800
    //   2159: iastore
    //   2160: dup
    //   2161: bipush #52
    //   2163: ldc 34078720
    //   2165: iastore
    //   2166: dup
    //   2167: bipush #53
    //   2169: iconst_0
    //   2170: iastore
    //   2171: dup
    //   2172: bipush #54
    //   2174: ldc 1074266112
    //   2176: iastore
    //   2177: dup
    //   2178: bipush #55
    //   2180: ldc 1107296256
    //   2182: iastore
    //   2183: dup
    //   2184: bipush #56
    //   2186: ldc 524544
    //   2188: iastore
    //   2189: dup
    //   2190: bipush #57
    //   2192: ldc 33554688
    //   2194: iastore
    //   2195: dup
    //   2196: bipush #58
    //   2198: ldc 1073742080
    //   2200: iastore
    //   2201: dup
    //   2202: bipush #59
    //   2204: ldc 524288
    //   2206: iastore
    //   2207: dup
    //   2208: bipush #60
    //   2210: iconst_0
    //   2211: iastore
    //   2212: dup
    //   2213: bipush #61
    //   2215: ldc 1074266112
    //   2217: iastore
    //   2218: dup
    //   2219: bipush #62
    //   2221: ldc 34078976
    //   2223: iastore
    //   2224: dup
    //   2225: bipush #63
    //   2227: ldc 1073742080
    //   2229: iastore
    //   2230: astore #12
    //   2232: bipush #64
    //   2234: newarray int
    //   2236: dup
    //   2237: iconst_0
    //   2238: ldc 536870928
    //   2240: iastore
    //   2241: dup
    //   2242: iconst_1
    //   2243: ldc 541065216
    //   2245: iastore
    //   2246: dup
    //   2247: iconst_2
    //   2248: sipush #16384
    //   2251: iastore
    //   2252: dup
    //   2253: iconst_3
    //   2254: ldc 541081616
    //   2256: iastore
    //   2257: dup
    //   2258: iconst_4
    //   2259: ldc 541065216
    //   2261: iastore
    //   2262: dup
    //   2263: iconst_5
    //   2264: bipush #16
    //   2266: iastore
    //   2267: dup
    //   2268: bipush #6
    //   2270: ldc 541081616
    //   2272: iastore
    //   2273: dup
    //   2274: bipush #7
    //   2276: ldc 4194304
    //   2278: iastore
    //   2279: dup
    //   2280: bipush #8
    //   2282: ldc 536887296
    //   2284: iastore
    //   2285: dup
    //   2286: bipush #9
    //   2288: ldc 4210704
    //   2290: iastore
    //   2291: dup
    //   2292: bipush #10
    //   2294: ldc 4194304
    //   2296: iastore
    //   2297: dup
    //   2298: bipush #11
    //   2300: ldc 536870928
    //   2302: iastore
    //   2303: dup
    //   2304: bipush #12
    //   2306: ldc 4194320
    //   2308: iastore
    //   2309: dup
    //   2310: bipush #13
    //   2312: ldc 536887296
    //   2314: iastore
    //   2315: dup
    //   2316: bipush #14
    //   2318: ldc 536870912
    //   2320: iastore
    //   2321: dup
    //   2322: bipush #15
    //   2324: sipush #16400
    //   2327: iastore
    //   2328: dup
    //   2329: bipush #16
    //   2331: iconst_0
    //   2332: iastore
    //   2333: dup
    //   2334: bipush #17
    //   2336: ldc 4194320
    //   2338: iastore
    //   2339: dup
    //   2340: bipush #18
    //   2342: ldc 536887312
    //   2344: iastore
    //   2345: dup
    //   2346: bipush #19
    //   2348: sipush #16384
    //   2351: iastore
    //   2352: dup
    //   2353: bipush #20
    //   2355: ldc 4210688
    //   2357: iastore
    //   2358: dup
    //   2359: bipush #21
    //   2361: ldc 536887312
    //   2363: iastore
    //   2364: dup
    //   2365: bipush #22
    //   2367: bipush #16
    //   2369: iastore
    //   2370: dup
    //   2371: bipush #23
    //   2373: ldc 541065232
    //   2375: iastore
    //   2376: dup
    //   2377: bipush #24
    //   2379: ldc 541065232
    //   2381: iastore
    //   2382: dup
    //   2383: bipush #25
    //   2385: iconst_0
    //   2386: iastore
    //   2387: dup
    //   2388: bipush #26
    //   2390: ldc 4210704
    //   2392: iastore
    //   2393: dup
    //   2394: bipush #27
    //   2396: ldc 541081600
    //   2398: iastore
    //   2399: dup
    //   2400: bipush #28
    //   2402: sipush #16400
    //   2405: iastore
    //   2406: dup
    //   2407: bipush #29
    //   2409: ldc 4210688
    //   2411: iastore
    //   2412: dup
    //   2413: bipush #30
    //   2415: ldc 541081600
    //   2417: iastore
    //   2418: dup
    //   2419: bipush #31
    //   2421: ldc 536870912
    //   2423: iastore
    //   2424: dup
    //   2425: bipush #32
    //   2427: ldc 536887296
    //   2429: iastore
    //   2430: dup
    //   2431: bipush #33
    //   2433: bipush #16
    //   2435: iastore
    //   2436: dup
    //   2437: bipush #34
    //   2439: ldc 541065232
    //   2441: iastore
    //   2442: dup
    //   2443: bipush #35
    //   2445: ldc 4210688
    //   2447: iastore
    //   2448: dup
    //   2449: bipush #36
    //   2451: ldc 541081616
    //   2453: iastore
    //   2454: dup
    //   2455: bipush #37
    //   2457: ldc 4194304
    //   2459: iastore
    //   2460: dup
    //   2461: bipush #38
    //   2463: sipush #16400
    //   2466: iastore
    //   2467: dup
    //   2468: bipush #39
    //   2470: ldc 536870928
    //   2472: iastore
    //   2473: dup
    //   2474: bipush #40
    //   2476: ldc 4194304
    //   2478: iastore
    //   2479: dup
    //   2480: bipush #41
    //   2482: ldc 536887296
    //   2484: iastore
    //   2485: dup
    //   2486: bipush #42
    //   2488: ldc 536870912
    //   2490: iastore
    //   2491: dup
    //   2492: bipush #43
    //   2494: sipush #16400
    //   2497: iastore
    //   2498: dup
    //   2499: bipush #44
    //   2501: ldc 536870928
    //   2503: iastore
    //   2504: dup
    //   2505: bipush #45
    //   2507: ldc 541081616
    //   2509: iastore
    //   2510: dup
    //   2511: bipush #46
    //   2513: ldc 4210688
    //   2515: iastore
    //   2516: dup
    //   2517: bipush #47
    //   2519: ldc 541065216
    //   2521: iastore
    //   2522: dup
    //   2523: bipush #48
    //   2525: ldc 4210704
    //   2527: iastore
    //   2528: dup
    //   2529: bipush #49
    //   2531: ldc 541081600
    //   2533: iastore
    //   2534: dup
    //   2535: bipush #50
    //   2537: iconst_0
    //   2538: iastore
    //   2539: dup
    //   2540: bipush #51
    //   2542: ldc 541065232
    //   2544: iastore
    //   2545: dup
    //   2546: bipush #52
    //   2548: bipush #16
    //   2550: iastore
    //   2551: dup
    //   2552: bipush #53
    //   2554: sipush #16384
    //   2557: iastore
    //   2558: dup
    //   2559: bipush #54
    //   2561: ldc 541065216
    //   2563: iastore
    //   2564: dup
    //   2565: bipush #55
    //   2567: ldc 4210704
    //   2569: iastore
    //   2570: dup
    //   2571: bipush #56
    //   2573: sipush #16384
    //   2576: iastore
    //   2577: dup
    //   2578: bipush #57
    //   2580: ldc 4194320
    //   2582: iastore
    //   2583: dup
    //   2584: bipush #58
    //   2586: ldc 536887312
    //   2588: iastore
    //   2589: dup
    //   2590: bipush #59
    //   2592: iconst_0
    //   2593: iastore
    //   2594: dup
    //   2595: bipush #60
    //   2597: ldc 541081600
    //   2599: iastore
    //   2600: dup
    //   2601: bipush #61
    //   2603: ldc 536870912
    //   2605: iastore
    //   2606: dup
    //   2607: bipush #62
    //   2609: ldc 4194320
    //   2611: iastore
    //   2612: dup
    //   2613: bipush #63
    //   2615: ldc 536887312
    //   2617: iastore
    //   2618: astore #13
    //   2620: bipush #64
    //   2622: newarray int
    //   2624: dup
    //   2625: iconst_0
    //   2626: ldc 2097152
    //   2628: iastore
    //   2629: dup
    //   2630: iconst_1
    //   2631: ldc 69206018
    //   2633: iastore
    //   2634: dup
    //   2635: iconst_2
    //   2636: ldc 67110914
    //   2638: iastore
    //   2639: dup
    //   2640: iconst_3
    //   2641: iconst_0
    //   2642: iastore
    //   2643: dup
    //   2644: iconst_4
    //   2645: sipush #2048
    //   2648: iastore
    //   2649: dup
    //   2650: iconst_5
    //   2651: ldc 67110914
    //   2653: iastore
    //   2654: dup
    //   2655: bipush #6
    //   2657: ldc 2099202
    //   2659: iastore
    //   2660: dup
    //   2661: bipush #7
    //   2663: ldc 69208064
    //   2665: iastore
    //   2666: dup
    //   2667: bipush #8
    //   2669: ldc 69208066
    //   2671: iastore
    //   2672: dup
    //   2673: bipush #9
    //   2675: ldc 2097152
    //   2677: iastore
    //   2678: dup
    //   2679: bipush #10
    //   2681: iconst_0
    //   2682: iastore
    //   2683: dup
    //   2684: bipush #11
    //   2686: ldc 67108866
    //   2688: iastore
    //   2689: dup
    //   2690: bipush #12
    //   2692: iconst_2
    //   2693: iastore
    //   2694: dup
    //   2695: bipush #13
    //   2697: ldc 67108864
    //   2699: iastore
    //   2700: dup
    //   2701: bipush #14
    //   2703: ldc 69206018
    //   2705: iastore
    //   2706: dup
    //   2707: bipush #15
    //   2709: sipush #2050
    //   2712: iastore
    //   2713: dup
    //   2714: bipush #16
    //   2716: ldc 67110912
    //   2718: iastore
    //   2719: dup
    //   2720: bipush #17
    //   2722: ldc 2099202
    //   2724: iastore
    //   2725: dup
    //   2726: bipush #18
    //   2728: ldc 2097154
    //   2730: iastore
    //   2731: dup
    //   2732: bipush #19
    //   2734: ldc 67110912
    //   2736: iastore
    //   2737: dup
    //   2738: bipush #20
    //   2740: ldc 67108866
    //   2742: iastore
    //   2743: dup
    //   2744: bipush #21
    //   2746: ldc 69206016
    //   2748: iastore
    //   2749: dup
    //   2750: bipush #22
    //   2752: ldc 69208064
    //   2754: iastore
    //   2755: dup
    //   2756: bipush #23
    //   2758: ldc 2097154
    //   2760: iastore
    //   2761: dup
    //   2762: bipush #24
    //   2764: ldc 69206016
    //   2766: iastore
    //   2767: dup
    //   2768: bipush #25
    //   2770: sipush #2048
    //   2773: iastore
    //   2774: dup
    //   2775: bipush #26
    //   2777: sipush #2050
    //   2780: iastore
    //   2781: dup
    //   2782: bipush #27
    //   2784: ldc 69208066
    //   2786: iastore
    //   2787: dup
    //   2788: bipush #28
    //   2790: ldc 2099200
    //   2792: iastore
    //   2793: dup
    //   2794: bipush #29
    //   2796: iconst_2
    //   2797: iastore
    //   2798: dup
    //   2799: bipush #30
    //   2801: ldc 67108864
    //   2803: iastore
    //   2804: dup
    //   2805: bipush #31
    //   2807: ldc 2099200
    //   2809: iastore
    //   2810: dup
    //   2811: bipush #32
    //   2813: ldc 67108864
    //   2815: iastore
    //   2816: dup
    //   2817: bipush #33
    //   2819: ldc 2099200
    //   2821: iastore
    //   2822: dup
    //   2823: bipush #34
    //   2825: ldc 2097152
    //   2827: iastore
    //   2828: dup
    //   2829: bipush #35
    //   2831: ldc 67110914
    //   2833: iastore
    //   2834: dup
    //   2835: bipush #36
    //   2837: ldc 67110914
    //   2839: iastore
    //   2840: dup
    //   2841: bipush #37
    //   2843: ldc 69206018
    //   2845: iastore
    //   2846: dup
    //   2847: bipush #38
    //   2849: ldc 69206018
    //   2851: iastore
    //   2852: dup
    //   2853: bipush #39
    //   2855: iconst_2
    //   2856: iastore
    //   2857: dup
    //   2858: bipush #40
    //   2860: ldc 2097154
    //   2862: iastore
    //   2863: dup
    //   2864: bipush #41
    //   2866: ldc 67108864
    //   2868: iastore
    //   2869: dup
    //   2870: bipush #42
    //   2872: ldc 67110912
    //   2874: iastore
    //   2875: dup
    //   2876: bipush #43
    //   2878: ldc 2097152
    //   2880: iastore
    //   2881: dup
    //   2882: bipush #44
    //   2884: ldc 69208064
    //   2886: iastore
    //   2887: dup
    //   2888: bipush #45
    //   2890: sipush #2050
    //   2893: iastore
    //   2894: dup
    //   2895: bipush #46
    //   2897: ldc 2099202
    //   2899: iastore
    //   2900: dup
    //   2901: bipush #47
    //   2903: ldc 69208064
    //   2905: iastore
    //   2906: dup
    //   2907: bipush #48
    //   2909: sipush #2050
    //   2912: iastore
    //   2913: dup
    //   2914: bipush #49
    //   2916: ldc 67108866
    //   2918: iastore
    //   2919: dup
    //   2920: bipush #50
    //   2922: ldc 69208066
    //   2924: iastore
    //   2925: dup
    //   2926: bipush #51
    //   2928: ldc 69206016
    //   2930: iastore
    //   2931: dup
    //   2932: bipush #52
    //   2934: ldc 2099200
    //   2936: iastore
    //   2937: dup
    //   2938: bipush #53
    //   2940: iconst_0
    //   2941: iastore
    //   2942: dup
    //   2943: bipush #54
    //   2945: iconst_2
    //   2946: iastore
    //   2947: dup
    //   2948: bipush #55
    //   2950: ldc 69208066
    //   2952: iastore
    //   2953: dup
    //   2954: bipush #56
    //   2956: iconst_0
    //   2957: iastore
    //   2958: dup
    //   2959: bipush #57
    //   2961: ldc 2099202
    //   2963: iastore
    //   2964: dup
    //   2965: bipush #58
    //   2967: ldc 69206016
    //   2969: iastore
    //   2970: dup
    //   2971: bipush #59
    //   2973: sipush #2048
    //   2976: iastore
    //   2977: dup
    //   2978: bipush #60
    //   2980: ldc 67108866
    //   2982: iastore
    //   2983: dup
    //   2984: bipush #61
    //   2986: ldc 67110912
    //   2988: iastore
    //   2989: dup
    //   2990: bipush #62
    //   2992: sipush #2048
    //   2995: iastore
    //   2996: dup
    //   2997: bipush #63
    //   2999: ldc 2097154
    //   3001: iastore
    //   3002: astore #14
    //   3004: bipush #64
    //   3006: newarray int
    //   3008: dup
    //   3009: iconst_0
    //   3010: ldc 268439616
    //   3012: iastore
    //   3013: dup
    //   3014: iconst_1
    //   3015: sipush #4096
    //   3018: iastore
    //   3019: dup
    //   3020: iconst_2
    //   3021: ldc 262144
    //   3023: iastore
    //   3024: dup
    //   3025: iconst_3
    //   3026: ldc 268701760
    //   3028: iastore
    //   3029: dup
    //   3030: iconst_4
    //   3031: ldc 268435456
    //   3033: iastore
    //   3034: dup
    //   3035: iconst_5
    //   3036: ldc 268439616
    //   3038: iastore
    //   3039: dup
    //   3040: bipush #6
    //   3042: bipush #64
    //   3044: iastore
    //   3045: dup
    //   3046: bipush #7
    //   3048: ldc 268435456
    //   3050: iastore
    //   3051: dup
    //   3052: bipush #8
    //   3054: ldc 262208
    //   3056: iastore
    //   3057: dup
    //   3058: bipush #9
    //   3060: ldc 268697600
    //   3062: iastore
    //   3063: dup
    //   3064: bipush #10
    //   3066: ldc 268701760
    //   3068: iastore
    //   3069: dup
    //   3070: bipush #11
    //   3072: ldc 266240
    //   3074: iastore
    //   3075: dup
    //   3076: bipush #12
    //   3078: ldc 268701696
    //   3080: iastore
    //   3081: dup
    //   3082: bipush #13
    //   3084: ldc 266304
    //   3086: iastore
    //   3087: dup
    //   3088: bipush #14
    //   3090: sipush #4096
    //   3093: iastore
    //   3094: dup
    //   3095: bipush #15
    //   3097: bipush #64
    //   3099: iastore
    //   3100: dup
    //   3101: bipush #16
    //   3103: ldc 268697600
    //   3105: iastore
    //   3106: dup
    //   3107: bipush #17
    //   3109: ldc 268435520
    //   3111: iastore
    //   3112: dup
    //   3113: bipush #18
    //   3115: ldc 268439552
    //   3117: iastore
    //   3118: dup
    //   3119: bipush #19
    //   3121: sipush #4160
    //   3124: iastore
    //   3125: dup
    //   3126: bipush #20
    //   3128: ldc 266240
    //   3130: iastore
    //   3131: dup
    //   3132: bipush #21
    //   3134: ldc 262208
    //   3136: iastore
    //   3137: dup
    //   3138: bipush #22
    //   3140: ldc 268697664
    //   3142: iastore
    //   3143: dup
    //   3144: bipush #23
    //   3146: ldc 268701696
    //   3148: iastore
    //   3149: dup
    //   3150: bipush #24
    //   3152: sipush #4160
    //   3155: iastore
    //   3156: dup
    //   3157: bipush #25
    //   3159: iconst_0
    //   3160: iastore
    //   3161: dup
    //   3162: bipush #26
    //   3164: iconst_0
    //   3165: iastore
    //   3166: dup
    //   3167: bipush #27
    //   3169: ldc 268697664
    //   3171: iastore
    //   3172: dup
    //   3173: bipush #28
    //   3175: ldc 268435520
    //   3177: iastore
    //   3178: dup
    //   3179: bipush #29
    //   3181: ldc 268439552
    //   3183: iastore
    //   3184: dup
    //   3185: bipush #30
    //   3187: ldc 266304
    //   3189: iastore
    //   3190: dup
    //   3191: bipush #31
    //   3193: ldc 262144
    //   3195: iastore
    //   3196: dup
    //   3197: bipush #32
    //   3199: ldc 266304
    //   3201: iastore
    //   3202: dup
    //   3203: bipush #33
    //   3205: ldc 262144
    //   3207: iastore
    //   3208: dup
    //   3209: bipush #34
    //   3211: ldc 268701696
    //   3213: iastore
    //   3214: dup
    //   3215: bipush #35
    //   3217: sipush #4096
    //   3220: iastore
    //   3221: dup
    //   3222: bipush #36
    //   3224: bipush #64
    //   3226: iastore
    //   3227: dup
    //   3228: bipush #37
    //   3230: ldc 268697664
    //   3232: iastore
    //   3233: dup
    //   3234: bipush #38
    //   3236: sipush #4096
    //   3239: iastore
    //   3240: dup
    //   3241: bipush #39
    //   3243: ldc 266304
    //   3245: iastore
    //   3246: dup
    //   3247: bipush #40
    //   3249: ldc 268439552
    //   3251: iastore
    //   3252: dup
    //   3253: bipush #41
    //   3255: bipush #64
    //   3257: iastore
    //   3258: dup
    //   3259: bipush #42
    //   3261: ldc 268435520
    //   3263: iastore
    //   3264: dup
    //   3265: bipush #43
    //   3267: ldc 268697600
    //   3269: iastore
    //   3270: dup
    //   3271: bipush #44
    //   3273: ldc 268697664
    //   3275: iastore
    //   3276: dup
    //   3277: bipush #45
    //   3279: ldc 268435456
    //   3281: iastore
    //   3282: dup
    //   3283: bipush #46
    //   3285: ldc 262144
    //   3287: iastore
    //   3288: dup
    //   3289: bipush #47
    //   3291: ldc 268439616
    //   3293: iastore
    //   3294: dup
    //   3295: bipush #48
    //   3297: iconst_0
    //   3298: iastore
    //   3299: dup
    //   3300: bipush #49
    //   3302: ldc 268701760
    //   3304: iastore
    //   3305: dup
    //   3306: bipush #50
    //   3308: ldc 262208
    //   3310: iastore
    //   3311: dup
    //   3312: bipush #51
    //   3314: ldc 268435520
    //   3316: iastore
    //   3317: dup
    //   3318: bipush #52
    //   3320: ldc 268697600
    //   3322: iastore
    //   3323: dup
    //   3324: bipush #53
    //   3326: ldc 268439552
    //   3328: iastore
    //   3329: dup
    //   3330: bipush #54
    //   3332: ldc 268439616
    //   3334: iastore
    //   3335: dup
    //   3336: bipush #55
    //   3338: iconst_0
    //   3339: iastore
    //   3340: dup
    //   3341: bipush #56
    //   3343: ldc 268701760
    //   3345: iastore
    //   3346: dup
    //   3347: bipush #57
    //   3349: ldc 266240
    //   3351: iastore
    //   3352: dup
    //   3353: bipush #58
    //   3355: ldc 266240
    //   3357: iastore
    //   3358: dup
    //   3359: bipush #59
    //   3361: sipush #4160
    //   3364: iastore
    //   3365: dup
    //   3366: bipush #60
    //   3368: sipush #4160
    //   3371: iastore
    //   3372: dup
    //   3373: bipush #61
    //   3375: ldc 262208
    //   3377: iastore
    //   3378: dup
    //   3379: bipush #62
    //   3381: ldc 268435456
    //   3383: iastore
    //   3384: dup
    //   3385: bipush #63
    //   3387: ldc 268701696
    //   3389: iastore
    //   3390: astore #15
    //   3392: aload_3
    //   3393: arraylength
    //   3394: istore #16
    //   3396: iconst_2
    //   3397: newarray int
    //   3399: astore #17
    //   3401: iload #16
    //   3403: newarray byte
    //   3405: astore #4
    //   3407: iload #16
    //   3409: bipush #8
    //   3411: idiv
    //   3412: istore #18
    //   3414: iconst_0
    //   3415: istore #19
    //   3417: iload #19
    //   3419: iload #18
    //   3421: if_icmpge -> 4335
    //   3424: iload #19
    //   3426: bipush #8
    //   3428: imul
    //   3429: istore #20
    //   3431: iconst_0
    //   3432: istore #21
    //   3434: iload #21
    //   3436: iconst_2
    //   3437: if_icmpge -> 3522
    //   3440: aload #17
    //   3442: iload #21
    //   3444: aload_3
    //   3445: iload #20
    //   3447: iload #21
    //   3449: iconst_4
    //   3450: imul
    //   3451: iadd
    //   3452: baload
    //   3453: sipush #255
    //   3456: iand
    //   3457: bipush #24
    //   3459: ishl
    //   3460: aload_3
    //   3461: iload #20
    //   3463: iload #21
    //   3465: iconst_4
    //   3466: imul
    //   3467: iadd
    //   3468: iconst_1
    //   3469: iadd
    //   3470: baload
    //   3471: sipush #255
    //   3474: iand
    //   3475: bipush #16
    //   3477: ishl
    //   3478: ior
    //   3479: aload_3
    //   3480: iload #20
    //   3482: iload #21
    //   3484: iconst_4
    //   3485: imul
    //   3486: iadd
    //   3487: iconst_2
    //   3488: iadd
    //   3489: baload
    //   3490: sipush #255
    //   3493: iand
    //   3494: bipush #8
    //   3496: ishl
    //   3497: ior
    //   3498: aload_3
    //   3499: iload #20
    //   3501: iload #21
    //   3503: iconst_4
    //   3504: imul
    //   3505: iadd
    //   3506: iconst_3
    //   3507: iadd
    //   3508: baload
    //   3509: sipush #255
    //   3512: iand
    //   3513: ior
    //   3514: iastore
    //   3515: iinc #21, 1
    //   3518: iload_2
    //   3519: ifne -> 3434
    //   3522: iconst_0
    //   3523: istore #26
    //   3525: aload #17
    //   3527: iconst_0
    //   3528: iaload
    //   3529: istore #24
    //   3531: aload #17
    //   3533: iconst_1
    //   3534: iaload
    //   3535: istore #23
    //   3537: iload #24
    //   3539: iconst_4
    //   3540: iushr
    //   3541: iload #23
    //   3543: ixor
    //   3544: ldc 252645135
    //   3546: iand
    //   3547: istore #22
    //   3549: iload #23
    //   3551: iload #22
    //   3553: ixor
    //   3554: istore #23
    //   3556: iload #24
    //   3558: iload #22
    //   3560: iconst_4
    //   3561: ishl
    //   3562: ixor
    //   3563: istore #24
    //   3565: iload #24
    //   3567: bipush #16
    //   3569: iushr
    //   3570: iload #23
    //   3572: ixor
    //   3573: ldc 65535
    //   3575: iand
    //   3576: istore #22
    //   3578: iload #23
    //   3580: iload #22
    //   3582: ixor
    //   3583: istore #23
    //   3585: iload #24
    //   3587: iload #22
    //   3589: bipush #16
    //   3591: ishl
    //   3592: ixor
    //   3593: istore #24
    //   3595: iload #23
    //   3597: iconst_2
    //   3598: iushr
    //   3599: iload #24
    //   3601: ixor
    //   3602: ldc 858993459
    //   3604: iand
    //   3605: istore #22
    //   3607: iload #24
    //   3609: iload #22
    //   3611: ixor
    //   3612: istore #24
    //   3614: iload #23
    //   3616: iload #22
    //   3618: iconst_2
    //   3619: ishl
    //   3620: ixor
    //   3621: istore #23
    //   3623: iload #23
    //   3625: bipush #8
    //   3627: iushr
    //   3628: iload #24
    //   3630: ixor
    //   3631: ldc 16711935
    //   3633: iand
    //   3634: istore #22
    //   3636: iload #24
    //   3638: iload #22
    //   3640: ixor
    //   3641: istore #24
    //   3643: iload #23
    //   3645: iload #22
    //   3647: bipush #8
    //   3649: ishl
    //   3650: ixor
    //   3651: istore #23
    //   3653: iload #23
    //   3655: iconst_1
    //   3656: ishl
    //   3657: iload #23
    //   3659: bipush #31
    //   3661: iushr
    //   3662: iconst_1
    //   3663: iand
    //   3664: ior
    //   3665: istore #23
    //   3667: iload #24
    //   3669: iload #23
    //   3671: ixor
    //   3672: ldc -1431655766
    //   3674: iand
    //   3675: istore #22
    //   3677: iload #24
    //   3679: iload #22
    //   3681: ixor
    //   3682: istore #24
    //   3684: iload #23
    //   3686: iload #22
    //   3688: ixor
    //   3689: istore #23
    //   3691: iload #24
    //   3693: iconst_1
    //   3694: ishl
    //   3695: iload #24
    //   3697: bipush #31
    //   3699: iushr
    //   3700: iconst_1
    //   3701: iand
    //   3702: ior
    //   3703: istore #24
    //   3705: iconst_0
    //   3706: istore #25
    //   3708: iload #25
    //   3710: bipush #8
    //   3712: if_icmpge -> 4050
    //   3715: iload #23
    //   3717: bipush #28
    //   3719: ishl
    //   3720: iload #23
    //   3722: iconst_4
    //   3723: iushr
    //   3724: ior
    //   3725: istore #22
    //   3727: iload #22
    //   3729: aload #5
    //   3731: iload #26
    //   3733: iinc #26, 1
    //   3736: iaload
    //   3737: ixor
    //   3738: istore #22
    //   3740: aload #14
    //   3742: iload #22
    //   3744: bipush #63
    //   3746: iand
    //   3747: iaload
    //   3748: istore #21
    //   3750: iload #21
    //   3752: aload #12
    //   3754: iload #22
    //   3756: bipush #8
    //   3758: iushr
    //   3759: bipush #63
    //   3761: iand
    //   3762: iaload
    //   3763: ior
    //   3764: istore #21
    //   3766: iload #21
    //   3768: aload #10
    //   3770: iload #22
    //   3772: bipush #16
    //   3774: iushr
    //   3775: bipush #63
    //   3777: iand
    //   3778: iaload
    //   3779: ior
    //   3780: istore #21
    //   3782: iload #21
    //   3784: aload #8
    //   3786: iload #22
    //   3788: bipush #24
    //   3790: iushr
    //   3791: bipush #63
    //   3793: iand
    //   3794: iaload
    //   3795: ior
    //   3796: istore #21
    //   3798: iload #23
    //   3800: aload #5
    //   3802: iload #26
    //   3804: iinc #26, 1
    //   3807: iaload
    //   3808: ixor
    //   3809: istore #22
    //   3811: iload #21
    //   3813: aload #15
    //   3815: iload #22
    //   3817: bipush #63
    //   3819: iand
    //   3820: iaload
    //   3821: ior
    //   3822: istore #21
    //   3824: iload #21
    //   3826: aload #13
    //   3828: iload #22
    //   3830: bipush #8
    //   3832: iushr
    //   3833: bipush #63
    //   3835: iand
    //   3836: iaload
    //   3837: ior
    //   3838: istore #21
    //   3840: iload #21
    //   3842: aload #11
    //   3844: iload #22
    //   3846: bipush #16
    //   3848: iushr
    //   3849: bipush #63
    //   3851: iand
    //   3852: iaload
    //   3853: ior
    //   3854: istore #21
    //   3856: iload #21
    //   3858: aload #9
    //   3860: iload #22
    //   3862: bipush #24
    //   3864: iushr
    //   3865: bipush #63
    //   3867: iand
    //   3868: iaload
    //   3869: ior
    //   3870: istore #21
    //   3872: iload #24
    //   3874: iload #21
    //   3876: ixor
    //   3877: istore #24
    //   3879: iload #24
    //   3881: bipush #28
    //   3883: ishl
    //   3884: iload #24
    //   3886: iconst_4
    //   3887: iushr
    //   3888: ior
    //   3889: istore #22
    //   3891: iload #22
    //   3893: aload #5
    //   3895: iload #26
    //   3897: iinc #26, 1
    //   3900: iaload
    //   3901: ixor
    //   3902: istore #22
    //   3904: aload #14
    //   3906: iload #22
    //   3908: bipush #63
    //   3910: iand
    //   3911: iaload
    //   3912: istore #21
    //   3914: iload #21
    //   3916: aload #12
    //   3918: iload #22
    //   3920: bipush #8
    //   3922: iushr
    //   3923: bipush #63
    //   3925: iand
    //   3926: iaload
    //   3927: ior
    //   3928: istore #21
    //   3930: iload #21
    //   3932: aload #10
    //   3934: iload #22
    //   3936: bipush #16
    //   3938: iushr
    //   3939: bipush #63
    //   3941: iand
    //   3942: iaload
    //   3943: ior
    //   3944: istore #21
    //   3946: iload #21
    //   3948: aload #8
    //   3950: iload #22
    //   3952: bipush #24
    //   3954: iushr
    //   3955: bipush #63
    //   3957: iand
    //   3958: iaload
    //   3959: ior
    //   3960: istore #21
    //   3962: iload #24
    //   3964: aload #5
    //   3966: iload #26
    //   3968: iinc #26, 1
    //   3971: iaload
    //   3972: ixor
    //   3973: istore #22
    //   3975: iload #21
    //   3977: aload #15
    //   3979: iload #22
    //   3981: bipush #63
    //   3983: iand
    //   3984: iaload
    //   3985: ior
    //   3986: istore #21
    //   3988: iload #21
    //   3990: aload #13
    //   3992: iload #22
    //   3994: bipush #8
    //   3996: iushr
    //   3997: bipush #63
    //   3999: iand
    //   4000: iaload
    //   4001: ior
    //   4002: istore #21
    //   4004: iload #21
    //   4006: aload #11
    //   4008: iload #22
    //   4010: bipush #16
    //   4012: iushr
    //   4013: bipush #63
    //   4015: iand
    //   4016: iaload
    //   4017: ior
    //   4018: istore #21
    //   4020: iload #21
    //   4022: aload #9
    //   4024: iload #22
    //   4026: bipush #24
    //   4028: iushr
    //   4029: bipush #63
    //   4031: iand
    //   4032: iaload
    //   4033: ior
    //   4034: istore #21
    //   4036: iload #23
    //   4038: iload #21
    //   4040: ixor
    //   4041: istore #23
    //   4043: iinc #25, 1
    //   4046: iload_2
    //   4047: ifne -> 3708
    //   4050: iload #23
    //   4052: bipush #31
    //   4054: ishl
    //   4055: iload #23
    //   4057: iconst_1
    //   4058: iushr
    //   4059: ior
    //   4060: istore #23
    //   4062: iload #24
    //   4064: iload #23
    //   4066: ixor
    //   4067: ldc -1431655766
    //   4069: iand
    //   4070: istore #22
    //   4072: iload #24
    //   4074: iload #22
    //   4076: ixor
    //   4077: istore #24
    //   4079: iload #23
    //   4081: iload #22
    //   4083: ixor
    //   4084: istore #23
    //   4086: iload #24
    //   4088: bipush #31
    //   4090: ishl
    //   4091: iload #24
    //   4093: iconst_1
    //   4094: iushr
    //   4095: ior
    //   4096: istore #24
    //   4098: iload #24
    //   4100: bipush #8
    //   4102: iushr
    //   4103: iload #23
    //   4105: ixor
    //   4106: ldc 16711935
    //   4108: iand
    //   4109: istore #22
    //   4111: iload #23
    //   4113: iload #22
    //   4115: ixor
    //   4116: istore #23
    //   4118: iload #24
    //   4120: iload #22
    //   4122: bipush #8
    //   4124: ishl
    //   4125: ixor
    //   4126: istore #24
    //   4128: iload #24
    //   4130: iconst_2
    //   4131: iushr
    //   4132: iload #23
    //   4134: ixor
    //   4135: ldc 858993459
    //   4137: iand
    //   4138: istore #22
    //   4140: iload #23
    //   4142: iload #22
    //   4144: ixor
    //   4145: istore #23
    //   4147: iload #24
    //   4149: iload #22
    //   4151: iconst_2
    //   4152: ishl
    //   4153: ixor
    //   4154: istore #24
    //   4156: iload #23
    //   4158: bipush #16
    //   4160: iushr
    //   4161: iload #24
    //   4163: ixor
    //   4164: ldc 65535
    //   4166: iand
    //   4167: istore #22
    //   4169: iload #24
    //   4171: iload #22
    //   4173: ixor
    //   4174: istore #24
    //   4176: iload #23
    //   4178: iload #22
    //   4180: bipush #16
    //   4182: ishl
    //   4183: ixor
    //   4184: istore #23
    //   4186: iload #23
    //   4188: iconst_4
    //   4189: iushr
    //   4190: iload #24
    //   4192: ixor
    //   4193: ldc 252645135
    //   4195: iand
    //   4196: istore #22
    //   4198: iload #24
    //   4200: iload #22
    //   4202: ixor
    //   4203: istore #24
    //   4205: iload #23
    //   4207: iload #22
    //   4209: iconst_4
    //   4210: ishl
    //   4211: ixor
    //   4212: istore #23
    //   4214: aload #17
    //   4216: iconst_0
    //   4217: iload #23
    //   4219: iastore
    //   4220: aload #17
    //   4222: iconst_1
    //   4223: iload #24
    //   4225: iastore
    //   4226: iload #19
    //   4228: bipush #8
    //   4230: imul
    //   4231: istore #27
    //   4233: iconst_0
    //   4234: istore #28
    //   4236: iload #28
    //   4238: iconst_2
    //   4239: if_icmpge -> 4328
    //   4242: aload #4
    //   4244: iload #27
    //   4246: iload #28
    //   4248: iconst_4
    //   4249: imul
    //   4250: iadd
    //   4251: aload #17
    //   4253: iload #28
    //   4255: iaload
    //   4256: bipush #24
    //   4258: iushr
    //   4259: i2b
    //   4260: bastore
    //   4261: aload #4
    //   4263: iload #27
    //   4265: iload #28
    //   4267: iconst_4
    //   4268: imul
    //   4269: iadd
    //   4270: iconst_1
    //   4271: iadd
    //   4272: aload #17
    //   4274: iload #28
    //   4276: iaload
    //   4277: bipush #16
    //   4279: iushr
    //   4280: i2b
    //   4281: bastore
    //   4282: aload #4
    //   4284: iload #27
    //   4286: iload #28
    //   4288: iconst_4
    //   4289: imul
    //   4290: iadd
    //   4291: iconst_2
    //   4292: iadd
    //   4293: aload #17
    //   4295: iload #28
    //   4297: iaload
    //   4298: bipush #8
    //   4300: iushr
    //   4301: i2b
    //   4302: bastore
    //   4303: aload #4
    //   4305: iload #27
    //   4307: iload #28
    //   4309: iconst_4
    //   4310: imul
    //   4311: iadd
    //   4312: iconst_3
    //   4313: iadd
    //   4314: aload #17
    //   4316: iload #28
    //   4318: iaload
    //   4319: i2b
    //   4320: bastore
    //   4321: iinc #28, 1
    //   4324: iload_2
    //   4325: ifne -> 4236
    //   4328: iinc #19, 1
    //   4331: iload_2
    //   4332: ifne -> 3417
    //   4335: new java/math/BigInteger
    //   4338: dup
    //   4339: aload #4
    //   4341: invokespecial <init> : ([B)V
    //   4344: invokevirtual abs : ()Ljava/math/BigInteger;
    //   4347: putstatic burp/Zmh5.ZN : Ljava/lang/Object;
    //   4350: sipush #-12261
    //   4353: sipush #-24465
    //   4356: invokestatic a : (II)Ljava/lang/String;
    //   4359: iconst_1
    //   4360: ldc burp/Zzlg
    //   4362: invokevirtual getClassLoader : ()Ljava/lang/ClassLoader;
    //   4365: invokestatic forName : (Ljava/lang/String;ZLjava/lang/ClassLoader;)Ljava/lang/Class;
    //   4368: invokevirtual getDeclaredFields : ()[Ljava/lang/reflect/Field;
    //   4371: astore_3
    //   4372: aload_3
    //   4373: arraylength
    //   4374: istore #4
    //   4376: iconst_0
    //   4377: istore #5
    //   4379: iload #5
    //   4381: iload #4
    //   4383: if_icmpge -> 4520
    //   4386: aload_3
    //   4387: iload #5
    //   4389: aaload
    //   4390: astore #6
    //   4392: aload #6
    //   4394: invokevirtual getModifiers : ()I
    //   4397: invokestatic isStatic : (I)Z
    //   4400: ifne -> 4410
    //   4403: goto -> 4513
    //   4406: invokestatic a : (Ljava/lang/Throwable;)Ljava/lang/Throwable;
    //   4409: athrow
    //   4410: aload #6
    //   4412: invokevirtual getType : ()Ljava/lang/Class;
    //   4415: astore #7
    //   4417: aload #7
    //   4419: ifnull -> 4500
    //   4422: aload #7
    //   4424: invokevirtual isPrimitive : ()Z
    //   4427: ifne -> 4500
    //   4430: goto -> 4437
    //   4433: invokestatic a : (Ljava/lang/Throwable;)Ljava/lang/Throwable;
    //   4436: athrow
    //   4437: aload #7
    //   4439: invokevirtual getPackage : ()Ljava/lang/Package;
    //   4442: ifnull -> 4500
    //   4445: goto -> 4452
    //   4448: invokestatic a : (Ljava/lang/Throwable;)Ljava/lang/Throwable;
    //   4451: athrow
    //   4452: aload #7
    //   4454: invokevirtual getPackage : ()Ljava/lang/Package;
    //   4457: invokevirtual getName : ()Ljava/lang/String;
    //   4460: ifnull -> 4500
    //   4463: goto -> 4470
    //   4466: invokestatic a : (Ljava/lang/Throwable;)Ljava/lang/Throwable;
    //   4469: athrow
    //   4470: aload #7
    //   4472: invokevirtual getPackage : ()Ljava/lang/Package;
    //   4475: invokevirtual getName : ()Ljava/lang/String;
    //   4478: sipush #-12257
    //   4481: sipush #4254
    //   4484: invokestatic a : (II)Ljava/lang/String;
    //   4487: invokevirtual startsWith : (Ljava/lang/String;)Z
    //   4490: ifne -> 4500
    //   4493: goto -> 4500
    //   4496: invokestatic a : (Ljava/lang/Throwable;)Ljava/lang/Throwable;
    //   4499: athrow
    //   4500: aload #6
    //   4502: iconst_1
    //   4503: invokevirtual setAccessible : (Z)V
    //   4506: aload #6
    //   4508: aconst_null
    //   4509: invokevirtual get : (Ljava/lang/Object;)Ljava/lang/Object;
    //   4512: pop
    //   4513: iinc #5, 1
    //   4516: iload_2
    //   4517: ifne -> 4379
    //   4520: sipush #-12259
    //   4523: sipush #20126
    //   4526: invokestatic a : (II)Ljava/lang/String;
    //   4529: invokestatic forName : (Ljava/lang/String;)Ljava/lang/Class;
    //   4532: invokevirtual getDeclaredMethods : ()[Ljava/lang/reflect/Method;
    //   4535: astore_3
    //   4536: aload_3
    //   4537: arraylength
    //   4538: istore #4
    //   4540: iconst_0
    //   4541: istore #5
    //   4543: iload #5
    //   4545: iload #4
    //   4547: if_icmpge -> 4679
    //   4550: aload_3
    //   4551: iload #5
    //   4553: aaload
    //   4554: astore #6
    //   4556: aload #6
    //   4558: invokevirtual getParameterTypes : ()[Ljava/lang/Class;
    //   4561: pop
    //   4562: aload #6
    //   4564: invokevirtual getModifiers : ()I
    //   4567: invokestatic isStatic : (I)Z
    //   4570: ifeq -> 4665
    //   4573: aload #6
    //   4575: invokevirtual getParameterTypes : ()[Ljava/lang/Class;
    //   4578: arraylength
    //   4579: iconst_2
    //   4580: if_icmpne -> 4665
    //   4583: goto -> 4590
    //   4586: invokestatic a : (Ljava/lang/Throwable;)Ljava/lang/Throwable;
    //   4589: athrow
    //   4590: aload #6
    //   4592: invokevirtual getReturnType : ()Ljava/lang/Class;
    //   4595: getstatic java/lang/Void.TYPE : Ljava/lang/Class;
    //   4598: invokevirtual equals : (Ljava/lang/Object;)Z
    //   4601: ifeq -> 4665
    //   4604: goto -> 4611
    //   4607: invokestatic a : (Ljava/lang/Throwable;)Ljava/lang/Throwable;
    //   4610: athrow
    //   4611: aload #6
    //   4613: iconst_1
    //   4614: invokevirtual setAccessible : (Z)V
    //   4617: aload #6
    //   4619: aconst_null
    //   4620: iconst_2
    //   4621: anewarray java/lang/Object
    //   4624: dup
    //   4625: iconst_0
    //   4626: aload_0
    //   4627: aastore
    //   4628: dup
    //   4629: iconst_1
    //   4630: aload_1
    //   4631: ifnonnull -> 4649
    //   4634: goto -> 4641
    //   4637: invokestatic a : (Ljava/lang/Throwable;)Ljava/lang/Throwable;
    //   4640: athrow
    //   4641: aload_1
    //   4642: goto -> 4656
    //   4645: invokestatic a : (Ljava/lang/Throwable;)Ljava/lang/Throwable;
    //   4648: athrow
    //   4649: aload_1
    //   4650: checkcast [B
    //   4653: invokevirtual clone : ()Ljava/lang/Object;
    //   4656: aastore
    //   4657: invokevirtual invoke : (Ljava/lang/Object;[Ljava/lang/Object;)Ljava/lang/Object;
    //   4660: pop
    //   4661: iload_2
    //   4662: ifne -> 4679
    //   4665: iinc #5, 1
    //   4668: iload_2
    //   4669: ifne -> 4543
    //   4672: goto -> 4679
    //   4675: invokestatic a : (Ljava/lang/Throwable;)Ljava/lang/Throwable;
    //   4678: athrow
    //   4679: getstatic burp/Zgvf.ZM : Ljava/lang/String;
    //   4682: getstatic burp/Zvof.Zl : Ljava/lang/Object;
    //   4685: checkcast java/math/BigInteger
    //   4688: invokevirtual intValue : ()I
    //   4691: bipush #32
    //   4693: irem
    //   4694: invokestatic abs : (I)I
    //   4697: invokevirtual charAt : (I)C
    //   4700: getstatic burp/Zryq.Zb : Ljava/lang/String;
    //   4703: getstatic burp/Ze54.Zx : Ljava/lang/Object;
    //   4706: checkcast java/math/BigInteger
    //   4709: invokevirtual intValue : ()I
    //   4712: bipush #32
    //   4714: irem
    //   4715: invokestatic abs : (I)I
    //   4718: invokevirtual charAt : (I)C
    //   4721: if_icmple -> 4828
    //   4724: getstatic burp/Zeju.ZR : Ljava/lang/String;
    //   4727: getstatic burp/Zegv.ZL : Ljava/lang/Object;
    //   4730: checkcast java/math/BigInteger
    //   4733: invokevirtual intValue : ()I
    //   4736: bipush #32
    //   4738: irem
    //   4739: invokestatic abs : (I)I
    //   4742: invokevirtual charAt : (I)C
    //   4745: getstatic burp/Zemp.Zs : Ljava/lang/String;
    //   4748: getstatic burp/Zrxm.ZL : Ljava/lang/Object;
    //   4751: checkcast java/math/BigInteger
    //   4754: invokevirtual intValue : ()I
    //   4757: bipush #32
    //   4759: irem
    //   4760: invokestatic abs : (I)I
    //   4763: invokevirtual charAt : (I)C
    //   4766: if_icmple -> 4828
    //   4769: goto -> 4776
    //   4772: invokestatic a : (Ljava/lang/Throwable;)Ljava/lang/Throwable;
    //   4775: athrow
    //   4776: getstatic burp/Zs6g.ZU : Ljava/lang/String;
    //   4779: getstatic burp/Zss8.ZO : Ljava/lang/Object;
    //   4782: checkcast java/math/BigInteger
    //   4785: invokevirtual intValue : ()I
    //   4788: bipush #32
    //   4790: irem
    //   4791: invokestatic abs : (I)I
    //   4794: invokevirtual charAt : (I)C
    //   4797: getstatic burp/Zb0z.ZM : Ljava/lang/String;
    //   4800: getstatic burp/Zb20.Zq : Ljava/lang/Object;
    //   4803: checkcast java/math/BigInteger
    //   4806: invokevirtual intValue : ()I
    //   4809: bipush #32
    //   4811: irem
    //   4812: invokestatic abs : (I)I
    //   4815: invokevirtual charAt : (I)C
    //   4818: if_icmpgt -> 4836
    //   4821: goto -> 4828
    //   4824: invokestatic a : (Ljava/lang/Throwable;)Ljava/lang/Throwable;
    //   4827: athrow
    //   4828: iconst_1
    //   4829: goto -> 4837
    //   4832: invokestatic a : (Ljava/lang/Throwable;)Ljava/lang/Throwable;
    //   4835: athrow
    //   4836: iconst_0
    //   4837: ireturn
    //   4838: astore_3
    //   4839: new java/lang/Exception
    //   4842: dup
    //   4843: aload_3
    //   4844: invokevirtual getMessage : ()Ljava/lang/String;
    //   4847: invokespecial <init> : (Ljava/lang/String;)V
    //   4850: athrow
    // Exception table:
    //   from	to	target	type
    //   4	4837	4838	java/lang/Throwable
    //   4392	4406	4406	java/lang/Throwable
    //   4417	4430	4433	java/lang/Throwable
    //   4422	4445	4448	java/lang/Throwable
    //   4437	4463	4466	java/lang/Throwable
    //   4452	4493	4496	java/lang/Throwable
    //   4556	4583	4586	java/lang/Throwable
    //   4573	4604	4607	java/lang/Throwable
    //   4590	4634	4637	java/lang/Throwable
    //   4611	4645	4645	java/lang/Throwable
    //   4656	4672	4675	java/lang/Throwable
    //   4679	4769	4772	java/lang/Throwable
    //   4724	4821	4824	java/lang/Throwable
    //   4776	4832	4832	java/lang/Throwable
  }
  
  static void ZH(Object paramObject) {
    Zz5s.ZL = a(-12262, 14327);
    Zz5s.Zg = new BigInteger(a(-12264, -32360));
    boolean bool = Zt2e.ZN();
    try {
      try {
        if (Zr_y.Zb.charAt(Math.abs(((BigInteger)Zdm.ZA).intValue() % 32)) <= Zr9p.Za.charAt(Math.abs(((BigInteger)Zezq.Zu).intValue() % 32))) {
          try {
            Zbqo.ZX(Class.forName(a(-12258, 995)));
            if (!bool)
              Ztkh.Zh(Class.forName(a(-12263, 6212))); 
          } catch (Throwable throwable) {
            throw a(null);
          } 
          return;
        } 
      } catch (Throwable throwable) {
        throw a(null);
      } 
      Ztkh.Zh(Class.forName(a(-12263, 6212)));
    } catch (Throwable throwable) {}
  }
  
  static {
    // Byte code:
    //   0: bipush #9
    //   2: anewarray java/lang/String
    //   5: astore #5
    //   7: iconst_0
    //   8: istore_3
    //   9: ldc 'P^/-G +\yp}xr!jU^a\\tGM r"~INX'$s!49lt(t\\ttOlS2MV<MP}\\nuu'c`e}-\\n,[8?#iM\\rAB'
    //   11: dup
    //   12: astore_2
    //   13: invokevirtual length : ()I
    //   16: istore #4
    //   18: bipush #9
    //   20: istore_1
    //   21: iconst_m1
    //   22: istore_0
    //   23: bipush #82
    //   25: iinc #0, 1
    //   28: aload_2
    //   29: iload_0
    //   30: dup
    //   31: iload_1
    //   32: iadd
    //   33: invokevirtual substring : (II)Ljava/lang/String;
    //   36: iconst_m1
    //   37: goto -> 143
    //   40: aload #5
    //   42: swap
    //   43: iload_3
    //   44: iinc #3, 1
    //   47: swap
    //   48: aastore
    //   49: iload_0
    //   50: iload_1
    //   51: iadd
    //   52: dup
    //   53: istore_0
    //   54: iload #4
    //   56: if_icmpge -> 68
    //   59: aload_2
    //   60: iload_0
    //   61: invokevirtual charAt : (I)C
    //   64: istore_1
    //   65: goto -> 23
    //   68: ldc '\\t)\\t^A4'
    //   70: dup
    //   71: astore_2
    //   72: invokevirtual length : ()I
    //   75: istore #4
    //   77: bipush #9
    //   79: istore_1
    //   80: iconst_m1
    //   81: istore_0
    //   82: bipush #10
    //   84: iinc #0, 1
    //   87: aload_2
    //   88: iload_0
    //   89: dup
    //   90: iload_1
    //   91: iadd
    //   92: invokevirtual substring : (II)Ljava/lang/String;
    //   95: iconst_0
    //   96: goto -> 143
    //   99: aload #5
    //   101: swap
    //   102: iload_3
    //   103: iinc #3, 1
    //   106: swap
    //   107: aastore
    //   108: iload_0
    //   109: iload_1
    //   110: iadd
    //   111: dup
    //   112: istore_0
    //   113: iload #4
    //   115: if_icmpge -> 127
    //   118: aload_2
    //   119: iload_0
    //   120: invokevirtual charAt : (I)C
    //   123: istore_1
    //   124: goto -> 82
    //   127: aload #5
    //   129: putstatic burp/Zl3l.a : [Ljava/lang/String;
    //   132: bipush #9
    //   134: anewarray java/lang/String
    //   137: putstatic burp/Zl3l.b : [Ljava/lang/String;
    //   140: goto -> 300
    //   143: dup_x2
    //   144: pop
    //   145: invokevirtual toCharArray : ()[C
    //   148: dup_x1
    //   149: arraylength
    //   150: dup_x2
    //   151: pop
    //   152: iconst_0
    //   153: istore #6
    //   155: dup2_x1
    //   156: pop2
    //   157: dup_x2
    //   158: iconst_1
    //   159: if_icmpgt -> 260
    //   162: dup2
    //   163: swap
    //   164: iload #6
    //   166: dup2_x1
    //   167: caload
    //   168: swap
    //   169: iload #6
    //   171: bipush #7
    //   173: irem
    //   174: tableswitch default -> 242, 0 -> 212, 1 -> 217, 2 -> 222, 3 -> 227, 4 -> 232, 5 -> 237
    //   212: bipush #19
    //   214: goto -> 244
    //   217: bipush #43
    //   219: goto -> 244
    //   222: bipush #15
    //   224: goto -> 244
    //   227: bipush #52
    //   229: goto -> 244
    //   232: bipush #19
    //   234: goto -> 244
    //   237: bipush #88
    //   239: goto -> 244
    //   242: bipush #73
    //   244: ixor
    //   245: ixor
    //   246: i2c
    //   247: castore
    //   248: iinc #6, 1
    //   251: dup
    //   252: ifne -> 260
    //   255: dup2
    //   256: dup_x1
    //   257: goto -> 166
    //   260: dup2_x1
    //   261: pop2
    //   262: dup_x2
    //   263: iload #6
    //   265: if_icmpgt -> 162
    //   268: pop
    //   269: new java/lang/String
    //   272: dup_x1
    //   273: swap
    //   274: invokespecial <init> : ([C)V
    //   277: invokevirtual intern : ()Ljava/lang/String;
    //   280: swap
    //   281: pop
    //   282: swap
    //   283: tableswitch default -> 40, 0 -> 99
    //   300: new java/math/BigInteger
    //   303: dup
    //   304: iconst_1
    //   305: bipush #32
    //   307: newarray byte
    //   309: dup
    //   310: iconst_0
    //   311: bipush #121
    //   313: bastore
    //   314: dup
    //   315: iconst_1
    //   316: bipush #-94
    //   318: bastore
    //   319: dup
    //   320: iconst_2
    //   321: bipush #-114
    //   323: bastore
    //   324: dup
    //   325: iconst_3
    //   326: bipush #84
    //   328: bastore
    //   329: dup
    //   330: iconst_4
    //   331: bipush #99
    //   333: bastore
    //   334: dup
    //   335: iconst_5
    //   336: bipush #62
    //   338: bastore
    //   339: dup
    //   340: bipush #6
    //   342: bipush #7
    //   344: bastore
    //   345: dup
    //   346: bipush #7
    //   348: bipush #-109
    //   350: bastore
    //   351: dup
    //   352: bipush #8
    //   354: bipush #114
    //   356: bastore
    //   357: dup
    //   358: bipush #9
    //   360: bipush #77
    //   362: bastore
    //   363: dup
    //   364: bipush #10
    //   366: bipush #92
    //   368: bastore
    //   369: dup
    //   370: bipush #11
    //   372: bipush #-88
    //   374: bastore
    //   375: dup
    //   376: bipush #12
    //   378: bipush #-128
    //   380: bastore
    //   381: dup
    //   382: bipush #13
    //   384: bipush #-90
    //   386: bastore
    //   387: dup
    //   388: bipush #14
    //   390: iconst_4
    //   391: bastore
    //   392: dup
    //   393: bipush #15
    //   395: bipush #-21
    //   397: bastore
    //   398: dup
    //   399: bipush #16
    //   401: bipush #-14
    //   403: bastore
    //   404: dup
    //   405: bipush #17
    //   407: bipush #-73
    //   409: bastore
    //   410: dup
    //   411: bipush #18
    //   413: bipush #104
    //   415: bastore
    //   416: dup
    //   417: bipush #19
    //   419: bipush #-46
    //   421: bastore
    //   422: dup
    //   423: bipush #20
    //   425: bipush #-80
    //   427: bastore
    //   428: dup
    //   429: bipush #21
    //   431: bipush #-105
    //   433: bastore
    //   434: dup
    //   435: bipush #22
    //   437: bipush #-66
    //   439: bastore
    //   440: dup
    //   441: bipush #23
    //   443: bipush #55
    //   445: bastore
    //   446: dup
    //   447: bipush #24
    //   449: bipush #-97
    //   451: bastore
    //   452: dup
    //   453: bipush #25
    //   455: iconst_2
    //   456: bastore
    //   457: dup
    //   458: bipush #26
    //   460: bipush #46
    //   462: bastore
    //   463: dup
    //   464: bipush #27
    //   466: bipush #57
    //   468: bastore
    //   469: dup
    //   470: bipush #28
    //   472: bipush #73
    //   474: bastore
    //   475: dup
    //   476: bipush #29
    //   478: bipush #110
    //   480: bastore
    //   481: dup
    //   482: bipush #30
    //   484: bipush #69
    //   486: bastore
    //   487: dup
    //   488: bipush #31
    //   490: bipush #15
    //   492: bastore
    //   493: invokespecial <init> : (I[B)V
    //   496: putstatic burp/Zl3l.Zv : Ljava/lang/Object;
    //   499: sipush #-12260
    //   502: sipush #28046
    //   505: invokestatic a : (II)Ljava/lang/String;
    //   508: putstatic burp/Zl3l.Z_ : Ljava/lang/String;
    //   511: return
  }
  
  private static Throwable a(Throwable paramThrowable) {
    return paramThrowable;
  }
  
  private static String a(int paramInt1, int paramInt2) {
    int i = (paramInt1 ^ 0xFFFFD01E) & 0xFFFF;
    if (b[i] == null) {
      char[] arrayOfChar = a[i].toCharArray();
      switch (arrayOfChar[0] & 0xFF) {
        case 0:
        
        case 1:
        
        case 2:
        
        case 3:
        
        case 4:
        
        case 5:
        
        case 6:
        
        case 7:
        
        case 8:
        
        case 9:
        
        case 10:
        
        case 11:
        
        case 12:
        
        case 13:
        
        case 14:
        
        case 15:
        
        case 16:
        
        case 17:
        
        case 18:
        
        case 19:
        
        case 20:
        
        case 21:
        
        case 22:
        
        case 23:
        
        case 24:
        
        case 25:
        
        case 26:
        
        case 27:
        
        case 28:
        
        case 29:
        
        case 30:
        
        case 31:
        
        case 32:
        
        case 33:
        
        case 34:
        
        case 35:
        
        case 36:
        
        case 37:
        
        case 38:
        
        case 39:
        
        case 40:
        
        case 41:
        
        case 42:
        
        case 43:
        
        case 44:
        
        case 45:
        
        case 46:
        
        case 47:
        
        case 48:
        
        case 49:
        
        case 50:
        
        case 51:
        
        case 52:
        
        case 53:
        
        case 54:
        
        case 55:
        
        case 56:
        
        case 57:
        
        case 58:
        
        case 59:
        
        case 60:
        
        case 61:
        
        case 62:
        
        case 63:
        
        case 64:
        
        case 65:
        
        case 66:
        
        case 67:
        
        case 68:
        
        case 69:
        
        case 70:
        
        case 71:
        
        case 72:
        
        case 73:
        
        case 74:
        
        case 75:
        
        case 76:
        
        case 77:
        
        case 78:
        
        case 79:
        
        case 80:
        
        case 81:
        
        case 82:
        
        case 83:
        
        case 84:
        
        case 85:
        
        case 86:
        
        case 87:
        
        case 88:
        
        case 89:
        
        case 90:
        
        case 91:
        
        case 92:
        
        case 93:
        
        case 94:
        
        case 95:
        
        case 96:
        
        case 97:
        
        case 98:
        
        case 99:
        
        case 100:
        
        case 101:
        
        case 102:
        
        case 103:
        
        case 104:
        
        case 105:
        
        case 106:
        
        case 107:
        
        case 108:
        
        case 109:
        
        case 110:
        
        case 111:
        
        case 112:
        
        case 113:
        
        case 114:
        
        case 115:
        
        case 116:
        
        case 117:
        
        case 118:
        
        case 119:
        
        case 120:
        
        case 121:
        
        case 122:
        
        case 123:
        
        case 124:
        
        case 125:
        
        case 126:
        
        case 127:
        
        case 128:
        
        case 129:
        
        case 130:
        
        case 131:
        
        case 132:
        
        case 133:
        
        case 134:
        
        case 135:
        
        case 136:
        
        case 137:
        
        case 138:
        
        case 139:
        
        case 140:
        
        case 141:
        
        case 142:
        
        case 143:
        
        case 144:
        
        case 145:
        
        case 146:
        
        case 147:
        
        case 148:
        
        case 149:
        
        case 150:
        
        case 151:
        
        case 152:
        
        case 153:
        
        case 154:
        
        case 155:
        
        case 156:
        
        case 157:
        
        case 158:
        
        case 159:
        
        case 160:
        
        case 161:
        
        case 162:
        
        case 163:
        
        case 164:
        
        case 165:
        
        case 166:
        
        case 167:
        
        case 168:
        
        case 169:
        
        case 170:
        
        case 171:
        
        case 172:
        
        case 173:
        
        case 174:
        
        case 175:
        
        case 176:
        
        case 177:
        
        case 178:
        
        case 179:
        
        case 180:
        
        case 181:
        
        case 182:
        
        case 183:
        
        case 184:
        
        case 185:
        
        case 186:
        
        case 187:
        
        case 188:
        
        case 189:
        
        case 190:
        
        case 191:
        
        case 192:
        
        case 193:
        
        case 194:
        
        case 195:
        
        case 196:
        
        case 197:
        
        case 198:
        
        case 199:
        
        case 200:
        
        case 201:
        
        case 202:
        
        case 203:
        
        case 204:
        
        case 205:
        
        case 206:
        
        case 207:
        
        case 208:
        
        case 209:
        
        case 210:
        
        case 211:
        
        case 212:
        
        case 213:
        
        case 214:
        
        case 215:
        
        case 216:
        
        case 217:
        
        case 218:
        
        case 219:
        
        case 220:
        
        case 221:
        
        case 222:
        
        case 223:
        
        case 224:
        
        case 225:
        
        case 226:
        
        case 227:
        
        case 228:
        
        case 229:
        
        case 230:
        
        case 231:
        
        case 232:
        
        case 233:
        
        case 234:
        
        case 235:
        
        case 236:
        
        case 237:
        
        case 238:
        
        case 239:
        
        case 240:
        
        case 241:
        
        case 242:
        
        case 243:
        
        case 244:
        
        case 245:
        
        case 246:
        
        case 247:
        
        case 248:
        
        case 249:
        
        case 250:
        
        case 251:
        
        case 252:
        
        case 253:
        
        case 254:
        
        default:
          break;
      } 
      char c = '';
      int j = (paramInt2 & 0xFF) - c;
      if (j < 0)
        j += 256; 
      int k = ((paramInt2 & 0xFFFF) >>> 8) - c;
      if (k < 0)
        k += 256; 
      for (byte b = 0; b < arrayOfChar.length; b++) {
        int m = b % 2;
        if (m == 0) {
          arrayOfChar[b] = (char)(arrayOfChar[b] ^ j);
          j = ((j >>> 3 | j << 5) ^ arrayOfChar[b]) & 0xFF;
        } else {
          arrayOfChar[b] = (char)(arrayOfChar[b] ^ k);
          k = ((k >>> 3 | k << 5) ^ arrayOfChar[b]) & 0xFF;
        } 
      } 
      b[i] = (new String(arrayOfChar)).intern();
    } 
    return b[i];
  }
}


/* Location:              C:\Program Files\BurpSuitePro\burpsuite_pro.jar!\burp\Zl3l.class
 * Java compiler version: 21 (65.0)
 * JD-Core Version:       1.1.3
 */