package burp;

import java.math.BigInteger;

class Zl4v extends ClassLoader {
  static Object ZT;
  
  static String ZD;
  
  private static final String[] a;
  
  private static final String[] b;
  
  static void Zg(Object[] paramArrayOfObject, Object paramObject) throws Throwable {}
  
  static boolean ZY(Object[] paramArrayOfObject, Object paramObject) throws Throwable {
    // Byte code:
    //   0: invokestatic ZK : ()Z
    //   3: istore_2
    //   4: sipush #-2840
    //   7: sipush #-11250
    //   10: invokestatic a : (II)Ljava/lang/String;
    //   13: invokestatic forName : (Ljava/lang/String;)Ljava/lang/Class;
    //   16: invokestatic Z_ : (Ljava/lang/Object;)V
    //   19: new java/io/ByteArrayOutputStream
    //   22: dup
    //   23: invokespecial <init> : ()V
    //   26: astore_3
    //   27: getstatic burp/Zty4.Zu : Ljava/lang/String;
    //   30: astore #4
    //   32: iconst_0
    //   33: istore #5
    //   35: iload #5
    //   37: aload #4
    //   39: invokevirtual length : ()I
    //   42: if_icmpge -> 72
    //   45: aload_3
    //   46: aload #4
    //   48: iload #5
    //   50: iload #5
    //   52: iconst_2
    //   53: iadd
    //   54: invokevirtual substring : (II)Ljava/lang/String;
    //   57: bipush #16
    //   59: invokestatic parseInt : (Ljava/lang/String;I)I
    //   62: invokevirtual write : (I)V
    //   65: iinc #5, 2
    //   68: iload_2
    //   69: ifeq -> 35
    //   72: aload_3
    //   73: invokevirtual toByteArray : ()[B
    //   76: astore #5
    //   78: getstatic burp/Zvi.Zs : Ljava/lang/Object;
    //   81: checkcast java/math/BigInteger
    //   84: invokevirtual toByteArray : ()[B
    //   87: astore #6
    //   89: sipush #256
    //   92: newarray byte
    //   94: astore #8
    //   96: sipush #256
    //   99: newarray int
    //   101: astore #9
    //   103: sipush #256
    //   106: newarray int
    //   108: astore #10
    //   110: sipush #256
    //   113: newarray int
    //   115: astore #11
    //   117: sipush #256
    //   120: newarray int
    //   122: astore #12
    //   124: bipush #10
    //   126: newarray int
    //   128: astore #13
    //   130: sipush #283
    //   133: istore #14
    //   135: iconst_0
    //   136: istore #16
    //   138: iload #16
    //   140: sipush #256
    //   143: if_icmpge -> 377
    //   146: sipush #-2835
    //   149: sipush #-22605
    //   152: invokestatic a : (II)Ljava/lang/String;
    //   155: iload #16
    //   157: iconst_1
    //   158: iushr
    //   159: invokevirtual charAt : (I)C
    //   162: istore #25
    //   164: iload #16
    //   166: iconst_1
    //   167: iand
    //   168: ifne -> 183
    //   171: iload #25
    //   173: bipush #8
    //   175: iushr
    //   176: goto -> 185
    //   179: invokestatic a : (Ljava/lang/Throwable;)Ljava/lang/Throwable;
    //   182: athrow
    //   183: iload #25
    //   185: i2b
    //   186: sipush #255
    //   189: iand
    //   190: istore #15
    //   192: iload #16
    //   194: iconst_1
    //   195: ishl
    //   196: istore #17
    //   198: iload #17
    //   200: sipush #256
    //   203: if_icmplt -> 213
    //   206: iload #17
    //   208: iload #14
    //   210: ixor
    //   211: istore #17
    //   213: iload #17
    //   215: iconst_1
    //   216: ishl
    //   217: istore #18
    //   219: iload #18
    //   221: sipush #256
    //   224: if_icmplt -> 234
    //   227: iload #18
    //   229: iload #14
    //   231: ixor
    //   232: istore #18
    //   234: iload #18
    //   236: iconst_1
    //   237: ishl
    //   238: istore #19
    //   240: iload #19
    //   242: sipush #256
    //   245: if_icmplt -> 255
    //   248: iload #19
    //   250: iload #14
    //   252: ixor
    //   253: istore #19
    //   255: iload #19
    //   257: iload #16
    //   259: ixor
    //   260: istore #20
    //   262: iload #20
    //   264: iload #17
    //   266: ixor
    //   267: istore #21
    //   269: iload #20
    //   271: iload #18
    //   273: ixor
    //   274: istore #22
    //   276: iload #19
    //   278: iload #18
    //   280: ixor
    //   281: iload #17
    //   283: ixor
    //   284: istore #23
    //   286: aload #8
    //   288: iload #16
    //   290: iload #15
    //   292: i2b
    //   293: bastore
    //   294: aload #9
    //   296: iload #15
    //   298: iload #23
    //   300: bipush #24
    //   302: ishl
    //   303: iload #20
    //   305: bipush #16
    //   307: ishl
    //   308: ior
    //   309: iload #22
    //   311: bipush #8
    //   313: ishl
    //   314: ior
    //   315: iload #21
    //   317: ior
    //   318: dup
    //   319: istore #24
    //   321: iastore
    //   322: aload #10
    //   324: iload #15
    //   326: iload #24
    //   328: bipush #8
    //   330: iushr
    //   331: iload #24
    //   333: bipush #24
    //   335: ishl
    //   336: ior
    //   337: iastore
    //   338: aload #11
    //   340: iload #15
    //   342: iload #24
    //   344: bipush #16
    //   346: iushr
    //   347: iload #24
    //   349: bipush #16
    //   351: ishl
    //   352: ior
    //   353: iastore
    //   354: aload #12
    //   356: iload #15
    //   358: iload #24
    //   360: bipush #24
    //   362: iushr
    //   363: iload #24
    //   365: bipush #8
    //   367: ishl
    //   368: ior
    //   369: iastore
    //   370: iinc #16, 1
    //   373: iload_2
    //   374: ifeq -> 138
    //   377: iconst_1
    //   378: istore #25
    //   380: aload #13
    //   382: iconst_0
    //   383: iload #25
    //   385: bipush #24
    //   387: ishl
    //   388: iastore
    //   389: iconst_1
    //   390: istore #26
    //   392: iload #26
    //   394: bipush #10
    //   396: if_icmpge -> 437
    //   399: iload #25
    //   401: iconst_1
    //   402: ishl
    //   403: istore #25
    //   405: iload #25
    //   407: sipush #256
    //   410: if_icmplt -> 420
    //   413: iload #25
    //   415: iload #14
    //   417: ixor
    //   418: istore #25
    //   420: aload #13
    //   422: iload #26
    //   424: iload #25
    //   426: bipush #24
    //   428: ishl
    //   429: iastore
    //   430: iinc #26, 1
    //   433: iload_2
    //   434: ifeq -> 392
    //   437: iconst_4
    //   438: istore #26
    //   440: iload #26
    //   442: bipush #6
    //   444: iadd
    //   445: istore #27
    //   447: iconst_4
    //   448: iload #27
    //   450: iconst_1
    //   451: iadd
    //   452: imul
    //   453: istore #28
    //   455: iload #28
    //   457: newarray int
    //   459: astore #29
    //   461: iload #28
    //   463: newarray int
    //   465: astore #30
    //   467: iconst_0
    //   468: istore #25
    //   470: iconst_0
    //   471: istore #32
    //   473: iconst_0
    //   474: istore #33
    //   476: iload #32
    //   478: iload #26
    //   480: if_icmpge -> 548
    //   483: aload #29
    //   485: iload #32
    //   487: aload #5
    //   489: iload #33
    //   491: baload
    //   492: bipush #24
    //   494: ishl
    //   495: aload #5
    //   497: iload #33
    //   499: iconst_1
    //   500: iadd
    //   501: baload
    //   502: sipush #255
    //   505: iand
    //   506: bipush #16
    //   508: ishl
    //   509: ior
    //   510: aload #5
    //   512: iload #33
    //   514: iconst_2
    //   515: iadd
    //   516: baload
    //   517: sipush #255
    //   520: iand
    //   521: bipush #8
    //   523: ishl
    //   524: ior
    //   525: aload #5
    //   527: iload #33
    //   529: iconst_3
    //   530: iadd
    //   531: baload
    //   532: sipush #255
    //   535: iand
    //   536: ior
    //   537: iastore
    //   538: iinc #32, 1
    //   541: iinc #33, 4
    //   544: iload_2
    //   545: ifeq -> 476
    //   548: iload #26
    //   550: istore #32
    //   552: iconst_0
    //   553: istore #33
    //   555: iload #32
    //   557: iload #28
    //   559: if_icmpge -> 686
    //   562: aload #29
    //   564: iload #32
    //   566: iconst_1
    //   567: isub
    //   568: iaload
    //   569: istore #31
    //   571: iload #33
    //   573: ifne -> 660
    //   576: iload #26
    //   578: istore #33
    //   580: aload #8
    //   582: iload #31
    //   584: bipush #16
    //   586: iushr
    //   587: sipush #255
    //   590: iand
    //   591: baload
    //   592: bipush #24
    //   594: ishl
    //   595: aload #8
    //   597: iload #31
    //   599: bipush #8
    //   601: iushr
    //   602: sipush #255
    //   605: iand
    //   606: baload
    //   607: sipush #255
    //   610: iand
    //   611: bipush #16
    //   613: ishl
    //   614: ior
    //   615: aload #8
    //   617: iload #31
    //   619: sipush #255
    //   622: iand
    //   623: baload
    //   624: sipush #255
    //   627: iand
    //   628: bipush #8
    //   630: ishl
    //   631: ior
    //   632: aload #8
    //   634: iload #31
    //   636: bipush #24
    //   638: iushr
    //   639: baload
    //   640: sipush #255
    //   643: iand
    //   644: ior
    //   645: istore #31
    //   647: iload #31
    //   649: aload #13
    //   651: iload #25
    //   653: iinc #25, 1
    //   656: iaload
    //   657: ixor
    //   658: istore #31
    //   660: aload #29
    //   662: iload #32
    //   664: aload #29
    //   666: iload #32
    //   668: iload #26
    //   670: isub
    //   671: iaload
    //   672: iload #31
    //   674: ixor
    //   675: iastore
    //   676: iinc #32, 1
    //   679: iinc #33, -1
    //   682: iload_2
    //   683: ifeq -> 555
    //   686: iconst_0
    //   687: istore #32
    //   689: iconst_4
    //   690: iload #27
    //   692: imul
    //   693: istore #33
    //   695: aload #30
    //   697: iload #32
    //   699: aload #29
    //   701: iload #33
    //   703: iaload
    //   704: iastore
    //   705: aload #30
    //   707: iload #32
    //   709: iconst_1
    //   710: iadd
    //   711: aload #29
    //   713: iload #33
    //   715: iconst_1
    //   716: iadd
    //   717: iaload
    //   718: iastore
    //   719: aload #30
    //   721: iload #32
    //   723: iconst_2
    //   724: iadd
    //   725: aload #29
    //   727: iload #33
    //   729: iconst_2
    //   730: iadd
    //   731: iaload
    //   732: iastore
    //   733: aload #30
    //   735: iload #32
    //   737: iconst_3
    //   738: iadd
    //   739: aload #29
    //   741: iload #33
    //   743: iconst_3
    //   744: iadd
    //   745: iaload
    //   746: iastore
    //   747: iinc #32, 4
    //   750: iinc #33, -4
    //   753: iconst_1
    //   754: istore #35
    //   756: iload #35
    //   758: iload #27
    //   760: if_icmpge -> 1124
    //   763: aload #29
    //   765: iload #33
    //   767: iaload
    //   768: istore #34
    //   770: aload #30
    //   772: iload #32
    //   774: aload #9
    //   776: aload #8
    //   778: iload #34
    //   780: bipush #24
    //   782: iushr
    //   783: baload
    //   784: sipush #255
    //   787: iand
    //   788: iaload
    //   789: aload #10
    //   791: aload #8
    //   793: iload #34
    //   795: bipush #16
    //   797: iushr
    //   798: sipush #255
    //   801: iand
    //   802: baload
    //   803: sipush #255
    //   806: iand
    //   807: iaload
    //   808: ixor
    //   809: aload #11
    //   811: aload #8
    //   813: iload #34
    //   815: bipush #8
    //   817: iushr
    //   818: sipush #255
    //   821: iand
    //   822: baload
    //   823: sipush #255
    //   826: iand
    //   827: iaload
    //   828: ixor
    //   829: aload #12
    //   831: aload #8
    //   833: iload #34
    //   835: sipush #255
    //   838: iand
    //   839: baload
    //   840: sipush #255
    //   843: iand
    //   844: iaload
    //   845: ixor
    //   846: iastore
    //   847: aload #29
    //   849: iload #33
    //   851: iconst_1
    //   852: iadd
    //   853: iaload
    //   854: istore #34
    //   856: aload #30
    //   858: iload #32
    //   860: iconst_1
    //   861: iadd
    //   862: aload #9
    //   864: aload #8
    //   866: iload #34
    //   868: bipush #24
    //   870: iushr
    //   871: baload
    //   872: sipush #255
    //   875: iand
    //   876: iaload
    //   877: aload #10
    //   879: aload #8
    //   881: iload #34
    //   883: bipush #16
    //   885: iushr
    //   886: sipush #255
    //   889: iand
    //   890: baload
    //   891: sipush #255
    //   894: iand
    //   895: iaload
    //   896: ixor
    //   897: aload #11
    //   899: aload #8
    //   901: iload #34
    //   903: bipush #8
    //   905: iushr
    //   906: sipush #255
    //   909: iand
    //   910: baload
    //   911: sipush #255
    //   914: iand
    //   915: iaload
    //   916: ixor
    //   917: aload #12
    //   919: aload #8
    //   921: iload #34
    //   923: sipush #255
    //   926: iand
    //   927: baload
    //   928: sipush #255
    //   931: iand
    //   932: iaload
    //   933: ixor
    //   934: iastore
    //   935: aload #29
    //   937: iload #33
    //   939: iconst_2
    //   940: iadd
    //   941: iaload
    //   942: istore #34
    //   944: aload #30
    //   946: iload #32
    //   948: iconst_2
    //   949: iadd
    //   950: aload #9
    //   952: aload #8
    //   954: iload #34
    //   956: bipush #24
    //   958: iushr
    //   959: baload
    //   960: sipush #255
    //   963: iand
    //   964: iaload
    //   965: aload #10
    //   967: aload #8
    //   969: iload #34
    //   971: bipush #16
    //   973: iushr
    //   974: sipush #255
    //   977: iand
    //   978: baload
    //   979: sipush #255
    //   982: iand
    //   983: iaload
    //   984: ixor
    //   985: aload #11
    //   987: aload #8
    //   989: iload #34
    //   991: bipush #8
    //   993: iushr
    //   994: sipush #255
    //   997: iand
    //   998: baload
    //   999: sipush #255
    //   1002: iand
    //   1003: iaload
    //   1004: ixor
    //   1005: aload #12
    //   1007: aload #8
    //   1009: iload #34
    //   1011: sipush #255
    //   1014: iand
    //   1015: baload
    //   1016: sipush #255
    //   1019: iand
    //   1020: iaload
    //   1021: ixor
    //   1022: iastore
    //   1023: aload #29
    //   1025: iload #33
    //   1027: iconst_3
    //   1028: iadd
    //   1029: iaload
    //   1030: istore #34
    //   1032: aload #30
    //   1034: iload #32
    //   1036: iconst_3
    //   1037: iadd
    //   1038: aload #9
    //   1040: aload #8
    //   1042: iload #34
    //   1044: bipush #24
    //   1046: iushr
    //   1047: baload
    //   1048: sipush #255
    //   1051: iand
    //   1052: iaload
    //   1053: aload #10
    //   1055: aload #8
    //   1057: iload #34
    //   1059: bipush #16
    //   1061: iushr
    //   1062: sipush #255
    //   1065: iand
    //   1066: baload
    //   1067: sipush #255
    //   1070: iand
    //   1071: iaload
    //   1072: ixor
    //   1073: aload #11
    //   1075: aload #8
    //   1077: iload #34
    //   1079: bipush #8
    //   1081: iushr
    //   1082: sipush #255
    //   1085: iand
    //   1086: baload
    //   1087: sipush #255
    //   1090: iand
    //   1091: iaload
    //   1092: ixor
    //   1093: aload #12
    //   1095: aload #8
    //   1097: iload #34
    //   1099: sipush #255
    //   1102: iand
    //   1103: baload
    //   1104: sipush #255
    //   1107: iand
    //   1108: iaload
    //   1109: ixor
    //   1110: iastore
    //   1111: iinc #32, 4
    //   1114: iinc #33, -4
    //   1117: iinc #35, 1
    //   1120: iload_2
    //   1121: ifeq -> 756
    //   1124: aload #30
    //   1126: iload #32
    //   1128: aload #29
    //   1130: iload #33
    //   1132: iaload
    //   1133: iastore
    //   1134: aload #30
    //   1136: iload #32
    //   1138: iconst_1
    //   1139: iadd
    //   1140: aload #29
    //   1142: iload #33
    //   1144: iconst_1
    //   1145: iadd
    //   1146: iaload
    //   1147: iastore
    //   1148: aload #30
    //   1150: iload #32
    //   1152: iconst_2
    //   1153: iadd
    //   1154: aload #29
    //   1156: iload #33
    //   1158: iconst_2
    //   1159: iadd
    //   1160: iaload
    //   1161: iastore
    //   1162: aload #30
    //   1164: iload #32
    //   1166: iconst_3
    //   1167: iadd
    //   1168: aload #29
    //   1170: iload #33
    //   1172: iconst_3
    //   1173: iadd
    //   1174: iaload
    //   1175: iastore
    //   1176: iconst_0
    //   1177: newarray byte
    //   1179: astore #35
    //   1181: aload #6
    //   1183: arraylength
    //   1184: bipush #16
    //   1186: irem
    //   1187: ifeq -> 1211
    //   1190: new java/lang/Exception
    //   1193: dup
    //   1194: sipush #-2838
    //   1197: sipush #18384
    //   1200: invokestatic a : (II)Ljava/lang/String;
    //   1203: invokespecial <init> : (Ljava/lang/String;)V
    //   1206: athrow
    //   1207: invokestatic a : (Ljava/lang/Throwable;)Ljava/lang/Throwable;
    //   1210: athrow
    //   1211: bipush #10
    //   1213: istore #36
    //   1215: sipush #-2848
    //   1218: sipush #256
    //   1221: newarray byte
    //   1223: astore #37
    //   1225: sipush #24966
    //   1228: sipush #256
    //   1231: newarray int
    //   1233: astore #38
    //   1235: sipush #256
    //   1238: newarray int
    //   1240: astore #39
    //   1242: sipush #256
    //   1245: newarray int
    //   1247: astore #40
    //   1249: sipush #256
    //   1252: newarray int
    //   1254: astore #41
    //   1256: sipush #283
    //   1259: istore #14
    //   1261: invokestatic a : (II)Ljava/lang/String;
    //   1264: astore #42
    //   1266: iconst_0
    //   1267: istore #16
    //   1269: iload #16
    //   1271: sipush #256
    //   1274: if_icmpge -> 1501
    //   1277: aload #42
    //   1279: iload #16
    //   1281: iconst_1
    //   1282: iushr
    //   1283: invokevirtual charAt : (I)C
    //   1286: istore #43
    //   1288: iload #16
    //   1290: iconst_1
    //   1291: iand
    //   1292: ifne -> 1307
    //   1295: iload #43
    //   1297: bipush #8
    //   1299: iushr
    //   1300: goto -> 1309
    //   1303: invokestatic a : (Ljava/lang/Throwable;)Ljava/lang/Throwable;
    //   1306: athrow
    //   1307: iload #43
    //   1309: i2b
    //   1310: sipush #255
    //   1313: iand
    //   1314: istore #15
    //   1316: iload #16
    //   1318: iconst_1
    //   1319: ishl
    //   1320: istore #17
    //   1322: iload #17
    //   1324: sipush #256
    //   1327: if_icmplt -> 1337
    //   1330: iload #17
    //   1332: iload #14
    //   1334: ixor
    //   1335: istore #17
    //   1337: iload #17
    //   1339: iconst_1
    //   1340: ishl
    //   1341: istore #18
    //   1343: iload #18
    //   1345: sipush #256
    //   1348: if_icmplt -> 1358
    //   1351: iload #18
    //   1353: iload #14
    //   1355: ixor
    //   1356: istore #18
    //   1358: iload #18
    //   1360: iconst_1
    //   1361: ishl
    //   1362: istore #19
    //   1364: iload #19
    //   1366: sipush #256
    //   1369: if_icmplt -> 1379
    //   1372: iload #19
    //   1374: iload #14
    //   1376: ixor
    //   1377: istore #19
    //   1379: iload #19
    //   1381: iload #16
    //   1383: ixor
    //   1384: istore #20
    //   1386: iload #20
    //   1388: iload #17
    //   1390: ixor
    //   1391: istore #21
    //   1393: iload #20
    //   1395: iload #18
    //   1397: ixor
    //   1398: istore #22
    //   1400: iload #19
    //   1402: iload #18
    //   1404: ixor
    //   1405: iload #17
    //   1407: ixor
    //   1408: istore #23
    //   1410: aload #37
    //   1412: iload #15
    //   1414: iload #16
    //   1416: i2b
    //   1417: bastore
    //   1418: aload #38
    //   1420: iload #15
    //   1422: iload #23
    //   1424: bipush #24
    //   1426: ishl
    //   1427: iload #20
    //   1429: bipush #16
    //   1431: ishl
    //   1432: ior
    //   1433: iload #22
    //   1435: bipush #8
    //   1437: ishl
    //   1438: ior
    //   1439: iload #21
    //   1441: ior
    //   1442: dup
    //   1443: istore #24
    //   1445: iastore
    //   1446: aload #39
    //   1448: iload #15
    //   1450: iload #24
    //   1452: bipush #8
    //   1454: iushr
    //   1455: iload #24
    //   1457: bipush #24
    //   1459: ishl
    //   1460: ior
    //   1461: iastore
    //   1462: aload #40
    //   1464: iload #15
    //   1466: iload #24
    //   1468: bipush #16
    //   1470: iushr
    //   1471: iload #24
    //   1473: bipush #16
    //   1475: ishl
    //   1476: ior
    //   1477: iastore
    //   1478: aload #41
    //   1480: iload #15
    //   1482: iload #24
    //   1484: bipush #24
    //   1486: iushr
    //   1487: iload #24
    //   1489: bipush #8
    //   1491: ishl
    //   1492: ior
    //   1493: iastore
    //   1494: iinc #16, 1
    //   1497: iload_2
    //   1498: ifeq -> 1269
    //   1501: aload #6
    //   1503: arraylength
    //   1504: newarray byte
    //   1506: astore #43
    //   1508: iconst_0
    //   1509: istore #44
    //   1511: iload #44
    //   1513: aload #6
    //   1515: arraylength
    //   1516: bipush #16
    //   1518: idiv
    //   1519: if_icmpge -> 2433
    //   1522: bipush #16
    //   1524: newarray byte
    //   1526: astore #45
    //   1528: bipush #16
    //   1530: newarray byte
    //   1532: astore #46
    //   1534: iconst_0
    //   1535: istore #47
    //   1537: iload #47
    //   1539: bipush #16
    //   1541: if_icmpge -> 1567
    //   1544: aload #45
    //   1546: iload #47
    //   1548: aload #6
    //   1550: iload #47
    //   1552: iload #44
    //   1554: bipush #16
    //   1556: imul
    //   1557: iadd
    //   1558: baload
    //   1559: bastore
    //   1560: iinc #47, 1
    //   1563: iload_2
    //   1564: ifeq -> 1537
    //   1567: iconst_0
    //   1568: istore #47
    //   1570: aload #45
    //   1572: iconst_0
    //   1573: baload
    //   1574: bipush #24
    //   1576: ishl
    //   1577: aload #45
    //   1579: iconst_1
    //   1580: baload
    //   1581: sipush #255
    //   1584: iand
    //   1585: bipush #16
    //   1587: ishl
    //   1588: ior
    //   1589: aload #45
    //   1591: iconst_2
    //   1592: baload
    //   1593: sipush #255
    //   1596: iand
    //   1597: bipush #8
    //   1599: ishl
    //   1600: ior
    //   1601: aload #45
    //   1603: iconst_3
    //   1604: baload
    //   1605: sipush #255
    //   1608: iand
    //   1609: ior
    //   1610: aload #30
    //   1612: iconst_0
    //   1613: iaload
    //   1614: ixor
    //   1615: istore #49
    //   1617: aload #45
    //   1619: iconst_4
    //   1620: baload
    //   1621: bipush #24
    //   1623: ishl
    //   1624: aload #45
    //   1626: iconst_5
    //   1627: baload
    //   1628: sipush #255
    //   1631: iand
    //   1632: bipush #16
    //   1634: ishl
    //   1635: ior
    //   1636: aload #45
    //   1638: bipush #6
    //   1640: baload
    //   1641: sipush #255
    //   1644: iand
    //   1645: bipush #8
    //   1647: ishl
    //   1648: ior
    //   1649: aload #45
    //   1651: bipush #7
    //   1653: baload
    //   1654: sipush #255
    //   1657: iand
    //   1658: ior
    //   1659: aload #30
    //   1661: iconst_1
    //   1662: iaload
    //   1663: ixor
    //   1664: istore #50
    //   1666: aload #45
    //   1668: bipush #8
    //   1670: baload
    //   1671: bipush #24
    //   1673: ishl
    //   1674: aload #45
    //   1676: bipush #9
    //   1678: baload
    //   1679: sipush #255
    //   1682: iand
    //   1683: bipush #16
    //   1685: ishl
    //   1686: ior
    //   1687: aload #45
    //   1689: bipush #10
    //   1691: baload
    //   1692: sipush #255
    //   1695: iand
    //   1696: bipush #8
    //   1698: ishl
    //   1699: ior
    //   1700: aload #45
    //   1702: bipush #11
    //   1704: baload
    //   1705: sipush #255
    //   1708: iand
    //   1709: ior
    //   1710: aload #30
    //   1712: iconst_2
    //   1713: iaload
    //   1714: ixor
    //   1715: istore #51
    //   1717: aload #45
    //   1719: bipush #12
    //   1721: baload
    //   1722: bipush #24
    //   1724: ishl
    //   1725: aload #45
    //   1727: bipush #13
    //   1729: baload
    //   1730: sipush #255
    //   1733: iand
    //   1734: bipush #16
    //   1736: ishl
    //   1737: ior
    //   1738: aload #45
    //   1740: bipush #14
    //   1742: baload
    //   1743: sipush #255
    //   1746: iand
    //   1747: bipush #8
    //   1749: ishl
    //   1750: ior
    //   1751: aload #45
    //   1753: bipush #15
    //   1755: baload
    //   1756: sipush #255
    //   1759: iand
    //   1760: ior
    //   1761: aload #30
    //   1763: iconst_3
    //   1764: iaload
    //   1765: ixor
    //   1766: istore #52
    //   1768: iconst_1
    //   1769: istore #53
    //   1771: iload #53
    //   1773: iload #36
    //   1775: if_icmpge -> 2018
    //   1778: iinc #47, 4
    //   1781: aload #38
    //   1783: iload #49
    //   1785: bipush #24
    //   1787: iushr
    //   1788: iaload
    //   1789: aload #39
    //   1791: iload #52
    //   1793: bipush #16
    //   1795: iushr
    //   1796: sipush #255
    //   1799: iand
    //   1800: iaload
    //   1801: ixor
    //   1802: aload #40
    //   1804: iload #51
    //   1806: bipush #8
    //   1808: iushr
    //   1809: sipush #255
    //   1812: iand
    //   1813: iaload
    //   1814: ixor
    //   1815: aload #41
    //   1817: iload #50
    //   1819: sipush #255
    //   1822: iand
    //   1823: iaload
    //   1824: ixor
    //   1825: aload #30
    //   1827: iload #47
    //   1829: iaload
    //   1830: ixor
    //   1831: istore #54
    //   1833: aload #38
    //   1835: iload #50
    //   1837: bipush #24
    //   1839: iushr
    //   1840: iaload
    //   1841: aload #39
    //   1843: iload #49
    //   1845: bipush #16
    //   1847: iushr
    //   1848: sipush #255
    //   1851: iand
    //   1852: iaload
    //   1853: ixor
    //   1854: aload #40
    //   1856: iload #52
    //   1858: bipush #8
    //   1860: iushr
    //   1861: sipush #255
    //   1864: iand
    //   1865: iaload
    //   1866: ixor
    //   1867: aload #41
    //   1869: iload #51
    //   1871: sipush #255
    //   1874: iand
    //   1875: iaload
    //   1876: ixor
    //   1877: aload #30
    //   1879: iload #47
    //   1881: iconst_1
    //   1882: iadd
    //   1883: iaload
    //   1884: ixor
    //   1885: istore #55
    //   1887: aload #38
    //   1889: iload #51
    //   1891: bipush #24
    //   1893: iushr
    //   1894: iaload
    //   1895: aload #39
    //   1897: iload #50
    //   1899: bipush #16
    //   1901: iushr
    //   1902: sipush #255
    //   1905: iand
    //   1906: iaload
    //   1907: ixor
    //   1908: aload #40
    //   1910: iload #49
    //   1912: bipush #8
    //   1914: iushr
    //   1915: sipush #255
    //   1918: iand
    //   1919: iaload
    //   1920: ixor
    //   1921: aload #41
    //   1923: iload #52
    //   1925: sipush #255
    //   1928: iand
    //   1929: iaload
    //   1930: ixor
    //   1931: aload #30
    //   1933: iload #47
    //   1935: iconst_2
    //   1936: iadd
    //   1937: iaload
    //   1938: ixor
    //   1939: istore #56
    //   1941: aload #38
    //   1943: iload #52
    //   1945: bipush #24
    //   1947: iushr
    //   1948: iaload
    //   1949: aload #39
    //   1951: iload #51
    //   1953: bipush #16
    //   1955: iushr
    //   1956: sipush #255
    //   1959: iand
    //   1960: iaload
    //   1961: ixor
    //   1962: aload #40
    //   1964: iload #50
    //   1966: bipush #8
    //   1968: iushr
    //   1969: sipush #255
    //   1972: iand
    //   1973: iaload
    //   1974: ixor
    //   1975: aload #41
    //   1977: iload #49
    //   1979: sipush #255
    //   1982: iand
    //   1983: iaload
    //   1984: ixor
    //   1985: aload #30
    //   1987: iload #47
    //   1989: iconst_3
    //   1990: iadd
    //   1991: iaload
    //   1992: ixor
    //   1993: istore #57
    //   1995: iload #54
    //   1997: istore #49
    //   1999: iload #55
    //   2001: istore #50
    //   2003: iload #56
    //   2005: istore #51
    //   2007: iload #57
    //   2009: istore #52
    //   2011: iinc #53, 1
    //   2014: iload_2
    //   2015: ifeq -> 1771
    //   2018: iinc #47, 4
    //   2021: aload #30
    //   2023: iload #47
    //   2025: iaload
    //   2026: istore #48
    //   2028: aload #46
    //   2030: iconst_0
    //   2031: aload #37
    //   2033: iload #49
    //   2035: bipush #24
    //   2037: iushr
    //   2038: baload
    //   2039: iload #48
    //   2041: bipush #24
    //   2043: iushr
    //   2044: ixor
    //   2045: i2b
    //   2046: bastore
    //   2047: aload #46
    //   2049: iconst_1
    //   2050: aload #37
    //   2052: iload #52
    //   2054: bipush #16
    //   2056: iushr
    //   2057: sipush #255
    //   2060: iand
    //   2061: baload
    //   2062: iload #48
    //   2064: bipush #16
    //   2066: iushr
    //   2067: ixor
    //   2068: i2b
    //   2069: bastore
    //   2070: aload #46
    //   2072: iconst_2
    //   2073: aload #37
    //   2075: iload #51
    //   2077: bipush #8
    //   2079: iushr
    //   2080: sipush #255
    //   2083: iand
    //   2084: baload
    //   2085: iload #48
    //   2087: bipush #8
    //   2089: iushr
    //   2090: ixor
    //   2091: i2b
    //   2092: bastore
    //   2093: aload #46
    //   2095: iconst_3
    //   2096: aload #37
    //   2098: iload #50
    //   2100: sipush #255
    //   2103: iand
    //   2104: baload
    //   2105: iload #48
    //   2107: ixor
    //   2108: i2b
    //   2109: bastore
    //   2110: aload #30
    //   2112: iload #47
    //   2114: iconst_1
    //   2115: iadd
    //   2116: iaload
    //   2117: istore #48
    //   2119: aload #46
    //   2121: iconst_4
    //   2122: aload #37
    //   2124: iload #50
    //   2126: bipush #24
    //   2128: iushr
    //   2129: baload
    //   2130: iload #48
    //   2132: bipush #24
    //   2134: iushr
    //   2135: ixor
    //   2136: i2b
    //   2137: bastore
    //   2138: aload #46
    //   2140: iconst_5
    //   2141: aload #37
    //   2143: iload #49
    //   2145: bipush #16
    //   2147: iushr
    //   2148: sipush #255
    //   2151: iand
    //   2152: baload
    //   2153: iload #48
    //   2155: bipush #16
    //   2157: iushr
    //   2158: ixor
    //   2159: i2b
    //   2160: bastore
    //   2161: aload #46
    //   2163: bipush #6
    //   2165: aload #37
    //   2167: iload #52
    //   2169: bipush #8
    //   2171: iushr
    //   2172: sipush #255
    //   2175: iand
    //   2176: baload
    //   2177: iload #48
    //   2179: bipush #8
    //   2181: iushr
    //   2182: ixor
    //   2183: i2b
    //   2184: bastore
    //   2185: aload #46
    //   2187: bipush #7
    //   2189: aload #37
    //   2191: iload #51
    //   2193: sipush #255
    //   2196: iand
    //   2197: baload
    //   2198: iload #48
    //   2200: ixor
    //   2201: i2b
    //   2202: bastore
    //   2203: aload #30
    //   2205: iload #47
    //   2207: iconst_2
    //   2208: iadd
    //   2209: iaload
    //   2210: istore #48
    //   2212: aload #46
    //   2214: bipush #8
    //   2216: aload #37
    //   2218: iload #51
    //   2220: bipush #24
    //   2222: iushr
    //   2223: baload
    //   2224: iload #48
    //   2226: bipush #24
    //   2228: iushr
    //   2229: ixor
    //   2230: i2b
    //   2231: bastore
    //   2232: aload #46
    //   2234: bipush #9
    //   2236: aload #37
    //   2238: iload #50
    //   2240: bipush #16
    //   2242: iushr
    //   2243: sipush #255
    //   2246: iand
    //   2247: baload
    //   2248: iload #48
    //   2250: bipush #16
    //   2252: iushr
    //   2253: ixor
    //   2254: i2b
    //   2255: bastore
    //   2256: aload #46
    //   2258: bipush #10
    //   2260: aload #37
    //   2262: iload #49
    //   2264: bipush #8
    //   2266: iushr
    //   2267: sipush #255
    //   2270: iand
    //   2271: baload
    //   2272: iload #48
    //   2274: bipush #8
    //   2276: iushr
    //   2277: ixor
    //   2278: i2b
    //   2279: bastore
    //   2280: aload #46
    //   2282: bipush #11
    //   2284: aload #37
    //   2286: iload #52
    //   2288: sipush #255
    //   2291: iand
    //   2292: baload
    //   2293: iload #48
    //   2295: ixor
    //   2296: i2b
    //   2297: bastore
    //   2298: aload #30
    //   2300: iload #47
    //   2302: iconst_3
    //   2303: iadd
    //   2304: iaload
    //   2305: istore #48
    //   2307: aload #46
    //   2309: bipush #12
    //   2311: aload #37
    //   2313: iload #52
    //   2315: bipush #24
    //   2317: iushr
    //   2318: baload
    //   2319: iload #48
    //   2321: bipush #24
    //   2323: iushr
    //   2324: ixor
    //   2325: i2b
    //   2326: bastore
    //   2327: aload #46
    //   2329: bipush #13
    //   2331: aload #37
    //   2333: iload #51
    //   2335: bipush #16
    //   2337: iushr
    //   2338: sipush #255
    //   2341: iand
    //   2342: baload
    //   2343: iload #48
    //   2345: bipush #16
    //   2347: iushr
    //   2348: ixor
    //   2349: i2b
    //   2350: bastore
    //   2351: aload #46
    //   2353: bipush #14
    //   2355: aload #37
    //   2357: iload #50
    //   2359: bipush #8
    //   2361: iushr
    //   2362: sipush #255
    //   2365: iand
    //   2366: baload
    //   2367: iload #48
    //   2369: bipush #8
    //   2371: iushr
    //   2372: ixor
    //   2373: i2b
    //   2374: bastore
    //   2375: aload #46
    //   2377: bipush #15
    //   2379: aload #37
    //   2381: iload #49
    //   2383: sipush #255
    //   2386: iand
    //   2387: baload
    //   2388: iload #48
    //   2390: ixor
    //   2391: i2b
    //   2392: bastore
    //   2393: iconst_0
    //   2394: istore #53
    //   2396: iload #53
    //   2398: bipush #16
    //   2400: if_icmpge -> 2426
    //   2403: aload #43
    //   2405: iload #53
    //   2407: iload #44
    //   2409: bipush #16
    //   2411: imul
    //   2412: iadd
    //   2413: aload #46
    //   2415: iload #53
    //   2417: baload
    //   2418: bastore
    //   2419: iinc #53, 1
    //   2422: iload_2
    //   2423: ifeq -> 2396
    //   2426: iinc #44, 1
    //   2429: iload_2
    //   2430: ifeq -> 1511
    //   2433: aload #43
    //   2435: arraylength
    //   2436: ifle -> 2517
    //   2439: aload #43
    //   2441: aload #43
    //   2443: arraylength
    //   2444: iconst_1
    //   2445: isub
    //   2446: baload
    //   2447: istore #44
    //   2449: iload #44
    //   2451: bipush #16
    //   2453: if_icmple -> 2464
    //   2456: aload #43
    //   2458: astore #35
    //   2460: iload_2
    //   2461: ifeq -> 2517
    //   2464: aload #43
    //   2466: arraylength
    //   2467: iload #44
    //   2469: isub
    //   2470: newarray byte
    //   2472: astore #35
    //   2474: iconst_0
    //   2475: istore #45
    //   2477: iload #45
    //   2479: aload #35
    //   2481: arraylength
    //   2482: if_icmpge -> 2517
    //   2485: iload #45
    //   2487: aload #43
    //   2489: arraylength
    //   2490: if_icmpge -> 2517
    //   2493: aload #35
    //   2495: iload #45
    //   2497: aload #43
    //   2499: iload #45
    //   2501: baload
    //   2502: bastore
    //   2503: iinc #45, 1
    //   2506: iload_2
    //   2507: ifeq -> 2477
    //   2510: goto -> 2517
    //   2513: invokestatic a : (Ljava/lang/Throwable;)Ljava/lang/Throwable;
    //   2516: athrow
    //   2517: aload #35
    //   2519: astore #7
    //   2521: new java/math/BigInteger
    //   2524: dup
    //   2525: aload #7
    //   2527: invokespecial <init> : ([B)V
    //   2530: invokevirtual abs : ()Ljava/math/BigInteger;
    //   2533: putstatic burp/Ze40.ZO : Ljava/lang/Object;
    //   2536: getstatic burp/Zx_u.Zy : Ljava/lang/Object;
    //   2539: checkcast java/math/BigInteger
    //   2542: invokevirtual toByteArray : ()[B
    //   2545: astore_3
    //   2546: bipush #32
    //   2548: newarray int
    //   2550: dup
    //   2551: iconst_0
    //   2552: ldc 876216579
    //   2554: iastore
    //   2555: dup
    //   2556: iconst_1
    //   2557: ldc 455999525
    //   2559: iastore
    //   2560: dup
    //   2561: iconst_2
    //   2562: ldc 1043334948
    //   2564: iastore
    //   2565: dup
    //   2566: iconst_3
    //   2567: ldc 439222784
    //   2569: iastore
    //   2570: dup
    //   2571: iconst_4
    //   2572: ldc 372376604
    //   2574: iastore
    //   2575: dup
    //   2576: iconst_5
    //   2577: ldc 707731490
    //   2579: iastore
    //   2580: dup
    //   2581: bipush #6
    //   2583: ldc 389426184
    //   2585: iastore
    //   2586: dup
    //   2587: bipush #7
    //   2589: ldc 973875457
    //   2591: iastore
    //   2592: dup
    //   2593: bipush #8
    //   2595: ldc 389160971
    //   2597: iastore
    //   2598: dup
    //   2599: bipush #9
    //   2601: ldc 907870729
    //   2603: iastore
    //   2604: dup
    //   2605: bipush #10
    //   2607: ldc 121057538
    //   2609: iastore
    //   2610: dup
    //   2611: bipush #11
    //   2613: ldc 840500228
    //   2615: iastore
    //   2616: dup
    //   2617: bipush #12
    //   2619: ldc 254150144
    //   2621: iastore
    //   2622: dup
    //   2623: bipush #13
    //   2625: ldc 924386310
    //   2627: iastore
    //   2628: dup
    //   2629: bipush #14
    //   2631: ldc 187632156
    //   2633: iastore
    //   2634: dup
    //   2635: bipush #15
    //   2637: ldc 874189824
    //   2639: iastore
    //   2640: dup
    //   2641: bipush #16
    //   2643: ldc 655302664
    //   2645: iastore
    //   2646: dup
    //   2647: bipush #17
    //   2649: ldc 890966315
    //   2651: iastore
    //   2652: dup
    //   2653: bipush #18
    //   2655: ldc 722417666
    //   2657: iastore
    //   2658: dup
    //   2659: bipush #19
    //   2661: ldc 1026621720
    //   2663: iastore
    //   2664: dup
    //   2665: bipush #20
    //   2667: ldc 957157408
    //   2669: iastore
    //   2670: dup
    //   2671: bipush #21
    //   2673: ldc 892536332
    //   2675: iastore
    //   2676: dup
    //   2677: bipush #22
    //   2679: ldc 689771012
    //   2681: iastore
    //   2682: dup
    //   2683: bipush #23
    //   2685: ldc 221709344
    //   2687: iastore
    //   2688: dup
    //   2689: bipush #24
    //   2691: ldc 940377620
    //   2693: iastore
    //   2694: dup
    //   2695: bipush #25
    //   2697: ldc 255209728
    //   2699: iastore
    //   2700: dup
    //   2701: bipush #26
    //   2703: ldc 1010368540
    //   2705: iastore
    //   2706: dup
    //   2707: bipush #27
    //   2709: ldc 220604441
    //   2711: iastore
    //   2712: dup
    //   2713: bipush #28
    //   2715: ldc 1008414755
    //   2717: iastore
    //   2718: dup
    //   2719: bipush #29
    //   2721: ldc 187049985
    //   2723: iastore
    //   2724: dup
    //   2725: bipush #30
    //   2727: ldc 943331329
    //   2729: iastore
    //   2730: dup
    //   2731: bipush #31
    //   2733: ldc 170788368
    //   2735: iastore
    //   2736: astore #5
    //   2738: bipush #64
    //   2740: newarray int
    //   2742: dup
    //   2743: iconst_0
    //   2744: ldc 16843776
    //   2746: iastore
    //   2747: dup
    //   2748: iconst_1
    //   2749: iconst_0
    //   2750: iastore
    //   2751: dup
    //   2752: iconst_2
    //   2753: ldc 65536
    //   2755: iastore
    //   2756: dup
    //   2757: iconst_3
    //   2758: ldc 16843780
    //   2760: iastore
    //   2761: dup
    //   2762: iconst_4
    //   2763: ldc 16842756
    //   2765: iastore
    //   2766: dup
    //   2767: iconst_5
    //   2768: ldc 66564
    //   2770: iastore
    //   2771: dup
    //   2772: bipush #6
    //   2774: iconst_4
    //   2775: iastore
    //   2776: dup
    //   2777: bipush #7
    //   2779: ldc 65536
    //   2781: iastore
    //   2782: dup
    //   2783: bipush #8
    //   2785: sipush #1024
    //   2788: iastore
    //   2789: dup
    //   2790: bipush #9
    //   2792: ldc 16843776
    //   2794: iastore
    //   2795: dup
    //   2796: bipush #10
    //   2798: ldc 16843780
    //   2800: iastore
    //   2801: dup
    //   2802: bipush #11
    //   2804: sipush #1024
    //   2807: iastore
    //   2808: dup
    //   2809: bipush #12
    //   2811: ldc 16778244
    //   2813: iastore
    //   2814: dup
    //   2815: bipush #13
    //   2817: ldc 16842756
    //   2819: iastore
    //   2820: dup
    //   2821: bipush #14
    //   2823: ldc 16777216
    //   2825: iastore
    //   2826: dup
    //   2827: bipush #15
    //   2829: iconst_4
    //   2830: iastore
    //   2831: dup
    //   2832: bipush #16
    //   2834: sipush #1028
    //   2837: iastore
    //   2838: dup
    //   2839: bipush #17
    //   2841: ldc 16778240
    //   2843: iastore
    //   2844: dup
    //   2845: bipush #18
    //   2847: ldc 16778240
    //   2849: iastore
    //   2850: dup
    //   2851: bipush #19
    //   2853: ldc 66560
    //   2855: iastore
    //   2856: dup
    //   2857: bipush #20
    //   2859: ldc 66560
    //   2861: iastore
    //   2862: dup
    //   2863: bipush #21
    //   2865: ldc 16842752
    //   2867: iastore
    //   2868: dup
    //   2869: bipush #22
    //   2871: ldc 16842752
    //   2873: iastore
    //   2874: dup
    //   2875: bipush #23
    //   2877: ldc 16778244
    //   2879: iastore
    //   2880: dup
    //   2881: bipush #24
    //   2883: ldc 65540
    //   2885: iastore
    //   2886: dup
    //   2887: bipush #25
    //   2889: ldc 16777220
    //   2891: iastore
    //   2892: dup
    //   2893: bipush #26
    //   2895: ldc 16777220
    //   2897: iastore
    //   2898: dup
    //   2899: bipush #27
    //   2901: ldc 65540
    //   2903: iastore
    //   2904: dup
    //   2905: bipush #28
    //   2907: iconst_0
    //   2908: iastore
    //   2909: dup
    //   2910: bipush #29
    //   2912: sipush #1028
    //   2915: iastore
    //   2916: dup
    //   2917: bipush #30
    //   2919: ldc 66564
    //   2921: iastore
    //   2922: dup
    //   2923: bipush #31
    //   2925: ldc 16777216
    //   2927: iastore
    //   2928: dup
    //   2929: bipush #32
    //   2931: ldc 65536
    //   2933: iastore
    //   2934: dup
    //   2935: bipush #33
    //   2937: ldc 16843780
    //   2939: iastore
    //   2940: dup
    //   2941: bipush #34
    //   2943: iconst_4
    //   2944: iastore
    //   2945: dup
    //   2946: bipush #35
    //   2948: ldc 16842752
    //   2950: iastore
    //   2951: dup
    //   2952: bipush #36
    //   2954: ldc 16843776
    //   2956: iastore
    //   2957: dup
    //   2958: bipush #37
    //   2960: ldc 16777216
    //   2962: iastore
    //   2963: dup
    //   2964: bipush #38
    //   2966: ldc 16777216
    //   2968: iastore
    //   2969: dup
    //   2970: bipush #39
    //   2972: sipush #1024
    //   2975: iastore
    //   2976: dup
    //   2977: bipush #40
    //   2979: ldc 16842756
    //   2981: iastore
    //   2982: dup
    //   2983: bipush #41
    //   2985: ldc 65536
    //   2987: iastore
    //   2988: dup
    //   2989: bipush #42
    //   2991: ldc 66560
    //   2993: iastore
    //   2994: dup
    //   2995: bipush #43
    //   2997: ldc 16777220
    //   2999: iastore
    //   3000: dup
    //   3001: bipush #44
    //   3003: sipush #1024
    //   3006: iastore
    //   3007: dup
    //   3008: bipush #45
    //   3010: iconst_4
    //   3011: iastore
    //   3012: dup
    //   3013: bipush #46
    //   3015: ldc 16778244
    //   3017: iastore
    //   3018: dup
    //   3019: bipush #47
    //   3021: ldc 66564
    //   3023: iastore
    //   3024: dup
    //   3025: bipush #48
    //   3027: ldc 16843780
    //   3029: iastore
    //   3030: dup
    //   3031: bipush #49
    //   3033: ldc 65540
    //   3035: iastore
    //   3036: dup
    //   3037: bipush #50
    //   3039: ldc 16842752
    //   3041: iastore
    //   3042: dup
    //   3043: bipush #51
    //   3045: ldc 16778244
    //   3047: iastore
    //   3048: dup
    //   3049: bipush #52
    //   3051: ldc 16777220
    //   3053: iastore
    //   3054: dup
    //   3055: bipush #53
    //   3057: sipush #1028
    //   3060: iastore
    //   3061: dup
    //   3062: bipush #54
    //   3064: ldc 66564
    //   3066: iastore
    //   3067: dup
    //   3068: bipush #55
    //   3070: ldc 16843776
    //   3072: iastore
    //   3073: dup
    //   3074: bipush #56
    //   3076: sipush #1028
    //   3079: iastore
    //   3080: dup
    //   3081: bipush #57
    //   3083: ldc 16778240
    //   3085: iastore
    //   3086: dup
    //   3087: bipush #58
    //   3089: ldc 16778240
    //   3091: iastore
    //   3092: dup
    //   3093: bipush #59
    //   3095: iconst_0
    //   3096: iastore
    //   3097: dup
    //   3098: bipush #60
    //   3100: ldc 65540
    //   3102: iastore
    //   3103: dup
    //   3104: bipush #61
    //   3106: ldc 66560
    //   3108: iastore
    //   3109: dup
    //   3110: bipush #62
    //   3112: iconst_0
    //   3113: iastore
    //   3114: dup
    //   3115: bipush #63
    //   3117: ldc 16842756
    //   3119: iastore
    //   3120: astore #6
    //   3122: bipush #64
    //   3124: newarray int
    //   3126: dup
    //   3127: iconst_0
    //   3128: ldc -2146402272
    //   3130: iastore
    //   3131: dup
    //   3132: iconst_1
    //   3133: ldc -2147450880
    //   3135: iastore
    //   3136: dup
    //   3137: iconst_2
    //   3138: ldc 32768
    //   3140: iastore
    //   3141: dup
    //   3142: iconst_3
    //   3143: ldc 1081376
    //   3145: iastore
    //   3146: dup
    //   3147: iconst_4
    //   3148: ldc 1048576
    //   3150: iastore
    //   3151: dup
    //   3152: iconst_5
    //   3153: bipush #32
    //   3155: iastore
    //   3156: dup
    //   3157: bipush #6
    //   3159: ldc -2146435040
    //   3161: iastore
    //   3162: dup
    //   3163: bipush #7
    //   3165: ldc -2147450848
    //   3167: iastore
    //   3168: dup
    //   3169: bipush #8
    //   3171: ldc -2147483616
    //   3173: iastore
    //   3174: dup
    //   3175: bipush #9
    //   3177: ldc -2146402272
    //   3179: iastore
    //   3180: dup
    //   3181: bipush #10
    //   3183: ldc -2146402304
    //   3185: iastore
    //   3186: dup
    //   3187: bipush #11
    //   3189: ldc -2147483648
    //   3191: iastore
    //   3192: dup
    //   3193: bipush #12
    //   3195: ldc -2147450880
    //   3197: iastore
    //   3198: dup
    //   3199: bipush #13
    //   3201: ldc 1048576
    //   3203: iastore
    //   3204: dup
    //   3205: bipush #14
    //   3207: bipush #32
    //   3209: iastore
    //   3210: dup
    //   3211: bipush #15
    //   3213: ldc -2146435040
    //   3215: iastore
    //   3216: dup
    //   3217: bipush #16
    //   3219: ldc 1081344
    //   3221: iastore
    //   3222: dup
    //   3223: bipush #17
    //   3225: ldc 1048608
    //   3227: iastore
    //   3228: dup
    //   3229: bipush #18
    //   3231: ldc -2147450848
    //   3233: iastore
    //   3234: dup
    //   3235: bipush #19
    //   3237: iconst_0
    //   3238: iastore
    //   3239: dup
    //   3240: bipush #20
    //   3242: ldc -2147483648
    //   3244: iastore
    //   3245: dup
    //   3246: bipush #21
    //   3248: ldc 32768
    //   3250: iastore
    //   3251: dup
    //   3252: bipush #22
    //   3254: ldc 1081376
    //   3256: iastore
    //   3257: dup
    //   3258: bipush #23
    //   3260: ldc -2146435072
    //   3262: iastore
    //   3263: dup
    //   3264: bipush #24
    //   3266: ldc 1048608
    //   3268: iastore
    //   3269: dup
    //   3270: bipush #25
    //   3272: ldc -2147483616
    //   3274: iastore
    //   3275: dup
    //   3276: bipush #26
    //   3278: iconst_0
    //   3279: iastore
    //   3280: dup
    //   3281: bipush #27
    //   3283: ldc 1081344
    //   3285: iastore
    //   3286: dup
    //   3287: bipush #28
    //   3289: ldc 32800
    //   3291: iastore
    //   3292: dup
    //   3293: bipush #29
    //   3295: ldc -2146402304
    //   3297: iastore
    //   3298: dup
    //   3299: bipush #30
    //   3301: ldc -2146435072
    //   3303: iastore
    //   3304: dup
    //   3305: bipush #31
    //   3307: ldc 32800
    //   3309: iastore
    //   3310: dup
    //   3311: bipush #32
    //   3313: iconst_0
    //   3314: iastore
    //   3315: dup
    //   3316: bipush #33
    //   3318: ldc 1081376
    //   3320: iastore
    //   3321: dup
    //   3322: bipush #34
    //   3324: ldc -2146435040
    //   3326: iastore
    //   3327: dup
    //   3328: bipush #35
    //   3330: ldc 1048576
    //   3332: iastore
    //   3333: dup
    //   3334: bipush #36
    //   3336: ldc -2147450848
    //   3338: iastore
    //   3339: dup
    //   3340: bipush #37
    //   3342: ldc -2146435072
    //   3344: iastore
    //   3345: dup
    //   3346: bipush #38
    //   3348: ldc -2146402304
    //   3350: iastore
    //   3351: dup
    //   3352: bipush #39
    //   3354: ldc 32768
    //   3356: iastore
    //   3357: dup
    //   3358: bipush #40
    //   3360: ldc -2146435072
    //   3362: iastore
    //   3363: dup
    //   3364: bipush #41
    //   3366: ldc -2147450880
    //   3368: iastore
    //   3369: dup
    //   3370: bipush #42
    //   3372: bipush #32
    //   3374: iastore
    //   3375: dup
    //   3376: bipush #43
    //   3378: ldc -2146402272
    //   3380: iastore
    //   3381: dup
    //   3382: bipush #44
    //   3384: ldc 1081376
    //   3386: iastore
    //   3387: dup
    //   3388: bipush #45
    //   3390: bipush #32
    //   3392: iastore
    //   3393: dup
    //   3394: bipush #46
    //   3396: ldc 32768
    //   3398: iastore
    //   3399: dup
    //   3400: bipush #47
    //   3402: ldc -2147483648
    //   3404: iastore
    //   3405: dup
    //   3406: bipush #48
    //   3408: ldc 32800
    //   3410: iastore
    //   3411: dup
    //   3412: bipush #49
    //   3414: ldc -2146402304
    //   3416: iastore
    //   3417: dup
    //   3418: bipush #50
    //   3420: ldc 1048576
    //   3422: iastore
    //   3423: dup
    //   3424: bipush #51
    //   3426: ldc -2147483616
    //   3428: iastore
    //   3429: dup
    //   3430: bipush #52
    //   3432: ldc 1048608
    //   3434: iastore
    //   3435: dup
    //   3436: bipush #53
    //   3438: ldc -2147450848
    //   3440: iastore
    //   3441: dup
    //   3442: bipush #54
    //   3444: ldc -2147483616
    //   3446: iastore
    //   3447: dup
    //   3448: bipush #55
    //   3450: ldc 1048608
    //   3452: iastore
    //   3453: dup
    //   3454: bipush #56
    //   3456: ldc 1081344
    //   3458: iastore
    //   3459: dup
    //   3460: bipush #57
    //   3462: iconst_0
    //   3463: iastore
    //   3464: dup
    //   3465: bipush #58
    //   3467: ldc -2147450880
    //   3469: iastore
    //   3470: dup
    //   3471: bipush #59
    //   3473: ldc 32800
    //   3475: iastore
    //   3476: dup
    //   3477: bipush #60
    //   3479: ldc -2147483648
    //   3481: iastore
    //   3482: dup
    //   3483: bipush #61
    //   3485: ldc -2146435040
    //   3487: iastore
    //   3488: dup
    //   3489: bipush #62
    //   3491: ldc -2146402272
    //   3493: iastore
    //   3494: dup
    //   3495: bipush #63
    //   3497: ldc 1081344
    //   3499: iastore
    //   3500: astore #7
    //   3502: bipush #64
    //   3504: newarray int
    //   3506: dup
    //   3507: iconst_0
    //   3508: sipush #520
    //   3511: iastore
    //   3512: dup
    //   3513: iconst_1
    //   3514: ldc 134349312
    //   3516: iastore
    //   3517: dup
    //   3518: iconst_2
    //   3519: iconst_0
    //   3520: iastore
    //   3521: dup
    //   3522: iconst_3
    //   3523: ldc 134348808
    //   3525: iastore
    //   3526: dup
    //   3527: iconst_4
    //   3528: ldc 134218240
    //   3530: iastore
    //   3531: dup
    //   3532: iconst_5
    //   3533: iconst_0
    //   3534: iastore
    //   3535: dup
    //   3536: bipush #6
    //   3538: ldc 131592
    //   3540: iastore
    //   3541: dup
    //   3542: bipush #7
    //   3544: ldc 134218240
    //   3546: iastore
    //   3547: dup
    //   3548: bipush #8
    //   3550: ldc 131080
    //   3552: iastore
    //   3553: dup
    //   3554: bipush #9
    //   3556: ldc 134217736
    //   3558: iastore
    //   3559: dup
    //   3560: bipush #10
    //   3562: ldc 134217736
    //   3564: iastore
    //   3565: dup
    //   3566: bipush #11
    //   3568: ldc 131072
    //   3570: iastore
    //   3571: dup
    //   3572: bipush #12
    //   3574: ldc 134349320
    //   3576: iastore
    //   3577: dup
    //   3578: bipush #13
    //   3580: ldc 131080
    //   3582: iastore
    //   3583: dup
    //   3584: bipush #14
    //   3586: ldc 134348800
    //   3588: iastore
    //   3589: dup
    //   3590: bipush #15
    //   3592: sipush #520
    //   3595: iastore
    //   3596: dup
    //   3597: bipush #16
    //   3599: ldc 134217728
    //   3601: iastore
    //   3602: dup
    //   3603: bipush #17
    //   3605: bipush #8
    //   3607: iastore
    //   3608: dup
    //   3609: bipush #18
    //   3611: ldc 134349312
    //   3613: iastore
    //   3614: dup
    //   3615: bipush #19
    //   3617: sipush #512
    //   3620: iastore
    //   3621: dup
    //   3622: bipush #20
    //   3624: ldc 131584
    //   3626: iastore
    //   3627: dup
    //   3628: bipush #21
    //   3630: ldc 134348800
    //   3632: iastore
    //   3633: dup
    //   3634: bipush #22
    //   3636: ldc 134348808
    //   3638: iastore
    //   3639: dup
    //   3640: bipush #23
    //   3642: ldc 131592
    //   3644: iastore
    //   3645: dup
    //   3646: bipush #24
    //   3648: ldc 134218248
    //   3650: iastore
    //   3651: dup
    //   3652: bipush #25
    //   3654: ldc 131584
    //   3656: iastore
    //   3657: dup
    //   3658: bipush #26
    //   3660: ldc 131072
    //   3662: iastore
    //   3663: dup
    //   3664: bipush #27
    //   3666: ldc 134218248
    //   3668: iastore
    //   3669: dup
    //   3670: bipush #28
    //   3672: bipush #8
    //   3674: iastore
    //   3675: dup
    //   3676: bipush #29
    //   3678: ldc 134349320
    //   3680: iastore
    //   3681: dup
    //   3682: bipush #30
    //   3684: sipush #512
    //   3687: iastore
    //   3688: dup
    //   3689: bipush #31
    //   3691: ldc 134217728
    //   3693: iastore
    //   3694: dup
    //   3695: bipush #32
    //   3697: ldc 134349312
    //   3699: iastore
    //   3700: dup
    //   3701: bipush #33
    //   3703: ldc 134217728
    //   3705: iastore
    //   3706: dup
    //   3707: bipush #34
    //   3709: ldc 131080
    //   3711: iastore
    //   3712: dup
    //   3713: bipush #35
    //   3715: sipush #520
    //   3718: iastore
    //   3719: dup
    //   3720: bipush #36
    //   3722: ldc 131072
    //   3724: iastore
    //   3725: dup
    //   3726: bipush #37
    //   3728: ldc 134349312
    //   3730: iastore
    //   3731: dup
    //   3732: bipush #38
    //   3734: ldc 134218240
    //   3736: iastore
    //   3737: dup
    //   3738: bipush #39
    //   3740: iconst_0
    //   3741: iastore
    //   3742: dup
    //   3743: bipush #40
    //   3745: sipush #512
    //   3748: iastore
    //   3749: dup
    //   3750: bipush #41
    //   3752: ldc 131080
    //   3754: iastore
    //   3755: dup
    //   3756: bipush #42
    //   3758: ldc 134349320
    //   3760: iastore
    //   3761: dup
    //   3762: bipush #43
    //   3764: ldc 134218240
    //   3766: iastore
    //   3767: dup
    //   3768: bipush #44
    //   3770: ldc 134217736
    //   3772: iastore
    //   3773: dup
    //   3774: bipush #45
    //   3776: sipush #512
    //   3779: iastore
    //   3780: dup
    //   3781: bipush #46
    //   3783: iconst_0
    //   3784: iastore
    //   3785: dup
    //   3786: bipush #47
    //   3788: ldc 134348808
    //   3790: iastore
    //   3791: dup
    //   3792: bipush #48
    //   3794: ldc 134218248
    //   3796: iastore
    //   3797: dup
    //   3798: bipush #49
    //   3800: ldc 131072
    //   3802: iastore
    //   3803: dup
    //   3804: bipush #50
    //   3806: ldc 134217728
    //   3808: iastore
    //   3809: dup
    //   3810: bipush #51
    //   3812: ldc 134349320
    //   3814: iastore
    //   3815: dup
    //   3816: bipush #52
    //   3818: bipush #8
    //   3820: iastore
    //   3821: dup
    //   3822: bipush #53
    //   3824: ldc 131592
    //   3826: iastore
    //   3827: dup
    //   3828: bipush #54
    //   3830: ldc 131584
    //   3832: iastore
    //   3833: dup
    //   3834: bipush #55
    //   3836: ldc 134217736
    //   3838: iastore
    //   3839: dup
    //   3840: bipush #56
    //   3842: ldc 134348800
    //   3844: iastore
    //   3845: dup
    //   3846: bipush #57
    //   3848: ldc 134218248
    //   3850: iastore
    //   3851: dup
    //   3852: bipush #58
    //   3854: sipush #520
    //   3857: iastore
    //   3858: dup
    //   3859: bipush #59
    //   3861: ldc 134348800
    //   3863: iastore
    //   3864: dup
    //   3865: bipush #60
    //   3867: ldc 131592
    //   3869: iastore
    //   3870: dup
    //   3871: bipush #61
    //   3873: bipush #8
    //   3875: iastore
    //   3876: dup
    //   3877: bipush #62
    //   3879: ldc 134348808
    //   3881: iastore
    //   3882: dup
    //   3883: bipush #63
    //   3885: ldc 131584
    //   3887: iastore
    //   3888: astore #8
    //   3890: bipush #64
    //   3892: newarray int
    //   3894: dup
    //   3895: iconst_0
    //   3896: ldc 8396801
    //   3898: iastore
    //   3899: dup
    //   3900: iconst_1
    //   3901: sipush #8321
    //   3904: iastore
    //   3905: dup
    //   3906: iconst_2
    //   3907: sipush #8321
    //   3910: iastore
    //   3911: dup
    //   3912: iconst_3
    //   3913: sipush #128
    //   3916: iastore
    //   3917: dup
    //   3918: iconst_4
    //   3919: ldc 8396928
    //   3921: iastore
    //   3922: dup
    //   3923: iconst_5
    //   3924: ldc 8388737
    //   3926: iastore
    //   3927: dup
    //   3928: bipush #6
    //   3930: ldc 8388609
    //   3932: iastore
    //   3933: dup
    //   3934: bipush #7
    //   3936: sipush #8193
    //   3939: iastore
    //   3940: dup
    //   3941: bipush #8
    //   3943: iconst_0
    //   3944: iastore
    //   3945: dup
    //   3946: bipush #9
    //   3948: ldc 8396800
    //   3950: iastore
    //   3951: dup
    //   3952: bipush #10
    //   3954: ldc 8396800
    //   3956: iastore
    //   3957: dup
    //   3958: bipush #11
    //   3960: ldc 8396929
    //   3962: iastore
    //   3963: dup
    //   3964: bipush #12
    //   3966: sipush #129
    //   3969: iastore
    //   3970: dup
    //   3971: bipush #13
    //   3973: iconst_0
    //   3974: iastore
    //   3975: dup
    //   3976: bipush #14
    //   3978: ldc 8388736
    //   3980: iastore
    //   3981: dup
    //   3982: bipush #15
    //   3984: ldc 8388609
    //   3986: iastore
    //   3987: dup
    //   3988: bipush #16
    //   3990: iconst_1
    //   3991: iastore
    //   3992: dup
    //   3993: bipush #17
    //   3995: sipush #8192
    //   3998: iastore
    //   3999: dup
    //   4000: bipush #18
    //   4002: ldc 8388608
    //   4004: iastore
    //   4005: dup
    //   4006: bipush #19
    //   4008: ldc 8396801
    //   4010: iastore
    //   4011: dup
    //   4012: bipush #20
    //   4014: sipush #128
    //   4017: iastore
    //   4018: dup
    //   4019: bipush #21
    //   4021: ldc 8388608
    //   4023: iastore
    //   4024: dup
    //   4025: bipush #22
    //   4027: sipush #8193
    //   4030: iastore
    //   4031: dup
    //   4032: bipush #23
    //   4034: sipush #8320
    //   4037: iastore
    //   4038: dup
    //   4039: bipush #24
    //   4041: ldc 8388737
    //   4043: iastore
    //   4044: dup
    //   4045: bipush #25
    //   4047: iconst_1
    //   4048: iastore
    //   4049: dup
    //   4050: bipush #26
    //   4052: sipush #8320
    //   4055: iastore
    //   4056: dup
    //   4057: bipush #27
    //   4059: ldc 8388736
    //   4061: iastore
    //   4062: dup
    //   4063: bipush #28
    //   4065: sipush #8192
    //   4068: iastore
    //   4069: dup
    //   4070: bipush #29
    //   4072: ldc 8396928
    //   4074: iastore
    //   4075: dup
    //   4076: bipush #30
    //   4078: ldc 8396929
    //   4080: iastore
    //   4081: dup
    //   4082: bipush #31
    //   4084: sipush #129
    //   4087: iastore
    //   4088: dup
    //   4089: bipush #32
    //   4091: ldc 8388736
    //   4093: iastore
    //   4094: dup
    //   4095: bipush #33
    //   4097: ldc 8388609
    //   4099: iastore
    //   4100: dup
    //   4101: bipush #34
    //   4103: ldc 8396800
    //   4105: iastore
    //   4106: dup
    //   4107: bipush #35
    //   4109: ldc 8396929
    //   4111: iastore
    //   4112: dup
    //   4113: bipush #36
    //   4115: sipush #129
    //   4118: iastore
    //   4119: dup
    //   4120: bipush #37
    //   4122: iconst_0
    //   4123: iastore
    //   4124: dup
    //   4125: bipush #38
    //   4127: iconst_0
    //   4128: iastore
    //   4129: dup
    //   4130: bipush #39
    //   4132: ldc 8396800
    //   4134: iastore
    //   4135: dup
    //   4136: bipush #40
    //   4138: sipush #8320
    //   4141: iastore
    //   4142: dup
    //   4143: bipush #41
    //   4145: ldc 8388736
    //   4147: iastore
    //   4148: dup
    //   4149: bipush #42
    //   4151: ldc 8388737
    //   4153: iastore
    //   4154: dup
    //   4155: bipush #43
    //   4157: iconst_1
    //   4158: iastore
    //   4159: dup
    //   4160: bipush #44
    //   4162: ldc 8396801
    //   4164: iastore
    //   4165: dup
    //   4166: bipush #45
    //   4168: sipush #8321
    //   4171: iastore
    //   4172: dup
    //   4173: bipush #46
    //   4175: sipush #8321
    //   4178: iastore
    //   4179: dup
    //   4180: bipush #47
    //   4182: sipush #128
    //   4185: iastore
    //   4186: dup
    //   4187: bipush #48
    //   4189: ldc 8396929
    //   4191: iastore
    //   4192: dup
    //   4193: bipush #49
    //   4195: sipush #129
    //   4198: iastore
    //   4199: dup
    //   4200: bipush #50
    //   4202: iconst_1
    //   4203: iastore
    //   4204: dup
    //   4205: bipush #51
    //   4207: sipush #8192
    //   4210: iastore
    //   4211: dup
    //   4212: bipush #52
    //   4214: ldc 8388609
    //   4216: iastore
    //   4217: dup
    //   4218: bipush #53
    //   4220: sipush #8193
    //   4223: iastore
    //   4224: dup
    //   4225: bipush #54
    //   4227: ldc 8396928
    //   4229: iastore
    //   4230: dup
    //   4231: bipush #55
    //   4233: ldc 8388737
    //   4235: iastore
    //   4236: dup
    //   4237: bipush #56
    //   4239: sipush #8193
    //   4242: iastore
    //   4243: dup
    //   4244: bipush #57
    //   4246: sipush #8320
    //   4249: iastore
    //   4250: dup
    //   4251: bipush #58
    //   4253: ldc 8388608
    //   4255: iastore
    //   4256: dup
    //   4257: bipush #59
    //   4259: ldc 8396801
    //   4261: iastore
    //   4262: dup
    //   4263: bipush #60
    //   4265: sipush #128
    //   4268: iastore
    //   4269: dup
    //   4270: bipush #61
    //   4272: ldc 8388608
    //   4274: iastore
    //   4275: dup
    //   4276: bipush #62
    //   4278: sipush #8192
    //   4281: iastore
    //   4282: dup
    //   4283: bipush #63
    //   4285: ldc 8396928
    //   4287: iastore
    //   4288: astore #9
    //   4290: bipush #64
    //   4292: newarray int
    //   4294: dup
    //   4295: iconst_0
    //   4296: sipush #256
    //   4299: iastore
    //   4300: dup
    //   4301: iconst_1
    //   4302: ldc 34078976
    //   4304: iastore
    //   4305: dup
    //   4306: iconst_2
    //   4307: ldc 34078720
    //   4309: iastore
    //   4310: dup
    //   4311: iconst_3
    //   4312: ldc 1107296512
    //   4314: iastore
    //   4315: dup
    //   4316: iconst_4
    //   4317: ldc 524288
    //   4319: iastore
    //   4320: dup
    //   4321: iconst_5
    //   4322: sipush #256
    //   4325: iastore
    //   4326: dup
    //   4327: bipush #6
    //   4329: ldc 1073741824
    //   4331: iastore
    //   4332: dup
    //   4333: bipush #7
    //   4335: ldc 34078720
    //   4337: iastore
    //   4338: dup
    //   4339: bipush #8
    //   4341: ldc 1074266368
    //   4343: iastore
    //   4344: dup
    //   4345: bipush #9
    //   4347: ldc 524288
    //   4349: iastore
    //   4350: dup
    //   4351: bipush #10
    //   4353: ldc 33554688
    //   4355: iastore
    //   4356: dup
    //   4357: bipush #11
    //   4359: ldc 1074266368
    //   4361: iastore
    //   4362: dup
    //   4363: bipush #12
    //   4365: ldc 1107296512
    //   4367: iastore
    //   4368: dup
    //   4369: bipush #13
    //   4371: ldc 1107820544
    //   4373: iastore
    //   4374: dup
    //   4375: bipush #14
    //   4377: ldc 524544
    //   4379: iastore
    //   4380: dup
    //   4381: bipush #15
    //   4383: ldc 1073741824
    //   4385: iastore
    //   4386: dup
    //   4387: bipush #16
    //   4389: ldc 33554432
    //   4391: iastore
    //   4392: dup
    //   4393: bipush #17
    //   4395: ldc 1074266112
    //   4397: iastore
    //   4398: dup
    //   4399: bipush #18
    //   4401: ldc 1074266112
    //   4403: iastore
    //   4404: dup
    //   4405: bipush #19
    //   4407: iconst_0
    //   4408: iastore
    //   4409: dup
    //   4410: bipush #20
    //   4412: ldc 1073742080
    //   4414: iastore
    //   4415: dup
    //   4416: bipush #21
    //   4418: ldc 1107820800
    //   4420: iastore
    //   4421: dup
    //   4422: bipush #22
    //   4424: ldc 1107820800
    //   4426: iastore
    //   4427: dup
    //   4428: bipush #23
    //   4430: ldc 33554688
    //   4432: iastore
    //   4433: dup
    //   4434: bipush #24
    //   4436: ldc 1107820544
    //   4438: iastore
    //   4439: dup
    //   4440: bipush #25
    //   4442: ldc 1073742080
    //   4444: iastore
    //   4445: dup
    //   4446: bipush #26
    //   4448: iconst_0
    //   4449: iastore
    //   4450: dup
    //   4451: bipush #27
    //   4453: ldc 1107296256
    //   4455: iastore
    //   4456: dup
    //   4457: bipush #28
    //   4459: ldc 34078976
    //   4461: iastore
    //   4462: dup
    //   4463: bipush #29
    //   4465: ldc 33554432
    //   4467: iastore
    //   4468: dup
    //   4469: bipush #30
    //   4471: ldc 1107296256
    //   4473: iastore
    //   4474: dup
    //   4475: bipush #31
    //   4477: ldc 524544
    //   4479: iastore
    //   4480: dup
    //   4481: bipush #32
    //   4483: ldc 524288
    //   4485: iastore
    //   4486: dup
    //   4487: bipush #33
    //   4489: ldc 1107296512
    //   4491: iastore
    //   4492: dup
    //   4493: bipush #34
    //   4495: sipush #256
    //   4498: iastore
    //   4499: dup
    //   4500: bipush #35
    //   4502: ldc 33554432
    //   4504: iastore
    //   4505: dup
    //   4506: bipush #36
    //   4508: ldc 1073741824
    //   4510: iastore
    //   4511: dup
    //   4512: bipush #37
    //   4514: ldc 34078720
    //   4516: iastore
    //   4517: dup
    //   4518: bipush #38
    //   4520: ldc 1107296512
    //   4522: iastore
    //   4523: dup
    //   4524: bipush #39
    //   4526: ldc 1074266368
    //   4528: iastore
    //   4529: dup
    //   4530: bipush #40
    //   4532: ldc 33554688
    //   4534: iastore
    //   4535: dup
    //   4536: bipush #41
    //   4538: ldc 1073741824
    //   4540: iastore
    //   4541: dup
    //   4542: bipush #42
    //   4544: ldc 1107820544
    //   4546: iastore
    //   4547: dup
    //   4548: bipush #43
    //   4550: ldc 34078976
    //   4552: iastore
    //   4553: dup
    //   4554: bipush #44
    //   4556: ldc 1074266368
    //   4558: iastore
    //   4559: dup
    //   4560: bipush #45
    //   4562: sipush #256
    //   4565: iastore
    //   4566: dup
    //   4567: bipush #46
    //   4569: ldc 33554432
    //   4571: iastore
    //   4572: dup
    //   4573: bipush #47
    //   4575: ldc 1107820544
    //   4577: iastore
    //   4578: dup
    //   4579: bipush #48
    //   4581: ldc 1107820800
    //   4583: iastore
    //   4584: dup
    //   4585: bipush #49
    //   4587: ldc 524544
    //   4589: iastore
    //   4590: dup
    //   4591: bipush #50
    //   4593: ldc 1107296256
    //   4595: iastore
    //   4596: dup
    //   4597: bipush #51
    //   4599: ldc 1107820800
    //   4601: iastore
    //   4602: dup
    //   4603: bipush #52
    //   4605: ldc 34078720
    //   4607: iastore
    //   4608: dup
    //   4609: bipush #53
    //   4611: iconst_0
    //   4612: iastore
    //   4613: dup
    //   4614: bipush #54
    //   4616: ldc 1074266112
    //   4618: iastore
    //   4619: dup
    //   4620: bipush #55
    //   4622: ldc 1107296256
    //   4624: iastore
    //   4625: dup
    //   4626: bipush #56
    //   4628: ldc 524544
    //   4630: iastore
    //   4631: dup
    //   4632: bipush #57
    //   4634: ldc 33554688
    //   4636: iastore
    //   4637: dup
    //   4638: bipush #58
    //   4640: ldc 1073742080
    //   4642: iastore
    //   4643: dup
    //   4644: bipush #59
    //   4646: ldc 524288
    //   4648: iastore
    //   4649: dup
    //   4650: bipush #60
    //   4652: iconst_0
    //   4653: iastore
    //   4654: dup
    //   4655: bipush #61
    //   4657: ldc 1074266112
    //   4659: iastore
    //   4660: dup
    //   4661: bipush #62
    //   4663: ldc 34078976
    //   4665: iastore
    //   4666: dup
    //   4667: bipush #63
    //   4669: ldc 1073742080
    //   4671: iastore
    //   4672: astore #10
    //   4674: bipush #64
    //   4676: newarray int
    //   4678: dup
    //   4679: iconst_0
    //   4680: ldc 536870928
    //   4682: iastore
    //   4683: dup
    //   4684: iconst_1
    //   4685: ldc 541065216
    //   4687: iastore
    //   4688: dup
    //   4689: iconst_2
    //   4690: sipush #16384
    //   4693: iastore
    //   4694: dup
    //   4695: iconst_3
    //   4696: ldc 541081616
    //   4698: iastore
    //   4699: dup
    //   4700: iconst_4
    //   4701: ldc 541065216
    //   4703: iastore
    //   4704: dup
    //   4705: iconst_5
    //   4706: bipush #16
    //   4708: iastore
    //   4709: dup
    //   4710: bipush #6
    //   4712: ldc 541081616
    //   4714: iastore
    //   4715: dup
    //   4716: bipush #7
    //   4718: ldc 4194304
    //   4720: iastore
    //   4721: dup
    //   4722: bipush #8
    //   4724: ldc 536887296
    //   4726: iastore
    //   4727: dup
    //   4728: bipush #9
    //   4730: ldc 4210704
    //   4732: iastore
    //   4733: dup
    //   4734: bipush #10
    //   4736: ldc 4194304
    //   4738: iastore
    //   4739: dup
    //   4740: bipush #11
    //   4742: ldc 536870928
    //   4744: iastore
    //   4745: dup
    //   4746: bipush #12
    //   4748: ldc 4194320
    //   4750: iastore
    //   4751: dup
    //   4752: bipush #13
    //   4754: ldc 536887296
    //   4756: iastore
    //   4757: dup
    //   4758: bipush #14
    //   4760: ldc 536870912
    //   4762: iastore
    //   4763: dup
    //   4764: bipush #15
    //   4766: sipush #16400
    //   4769: iastore
    //   4770: dup
    //   4771: bipush #16
    //   4773: iconst_0
    //   4774: iastore
    //   4775: dup
    //   4776: bipush #17
    //   4778: ldc 4194320
    //   4780: iastore
    //   4781: dup
    //   4782: bipush #18
    //   4784: ldc 536887312
    //   4786: iastore
    //   4787: dup
    //   4788: bipush #19
    //   4790: sipush #16384
    //   4793: iastore
    //   4794: dup
    //   4795: bipush #20
    //   4797: ldc 4210688
    //   4799: iastore
    //   4800: dup
    //   4801: bipush #21
    //   4803: ldc 536887312
    //   4805: iastore
    //   4806: dup
    //   4807: bipush #22
    //   4809: bipush #16
    //   4811: iastore
    //   4812: dup
    //   4813: bipush #23
    //   4815: ldc 541065232
    //   4817: iastore
    //   4818: dup
    //   4819: bipush #24
    //   4821: ldc 541065232
    //   4823: iastore
    //   4824: dup
    //   4825: bipush #25
    //   4827: iconst_0
    //   4828: iastore
    //   4829: dup
    //   4830: bipush #26
    //   4832: ldc 4210704
    //   4834: iastore
    //   4835: dup
    //   4836: bipush #27
    //   4838: ldc 541081600
    //   4840: iastore
    //   4841: dup
    //   4842: bipush #28
    //   4844: sipush #16400
    //   4847: iastore
    //   4848: dup
    //   4849: bipush #29
    //   4851: ldc 4210688
    //   4853: iastore
    //   4854: dup
    //   4855: bipush #30
    //   4857: ldc 541081600
    //   4859: iastore
    //   4860: dup
    //   4861: bipush #31
    //   4863: ldc 536870912
    //   4865: iastore
    //   4866: dup
    //   4867: bipush #32
    //   4869: ldc 536887296
    //   4871: iastore
    //   4872: dup
    //   4873: bipush #33
    //   4875: bipush #16
    //   4877: iastore
    //   4878: dup
    //   4879: bipush #34
    //   4881: ldc 541065232
    //   4883: iastore
    //   4884: dup
    //   4885: bipush #35
    //   4887: ldc 4210688
    //   4889: iastore
    //   4890: dup
    //   4891: bipush #36
    //   4893: ldc 541081616
    //   4895: iastore
    //   4896: dup
    //   4897: bipush #37
    //   4899: ldc 4194304
    //   4901: iastore
    //   4902: dup
    //   4903: bipush #38
    //   4905: sipush #16400
    //   4908: iastore
    //   4909: dup
    //   4910: bipush #39
    //   4912: ldc 536870928
    //   4914: iastore
    //   4915: dup
    //   4916: bipush #40
    //   4918: ldc 4194304
    //   4920: iastore
    //   4921: dup
    //   4922: bipush #41
    //   4924: ldc 536887296
    //   4926: iastore
    //   4927: dup
    //   4928: bipush #42
    //   4930: ldc 536870912
    //   4932: iastore
    //   4933: dup
    //   4934: bipush #43
    //   4936: sipush #16400
    //   4939: iastore
    //   4940: dup
    //   4941: bipush #44
    //   4943: ldc 536870928
    //   4945: iastore
    //   4946: dup
    //   4947: bipush #45
    //   4949: ldc 541081616
    //   4951: iastore
    //   4952: dup
    //   4953: bipush #46
    //   4955: ldc 4210688
    //   4957: iastore
    //   4958: dup
    //   4959: bipush #47
    //   4961: ldc 541065216
    //   4963: iastore
    //   4964: dup
    //   4965: bipush #48
    //   4967: ldc 4210704
    //   4969: iastore
    //   4970: dup
    //   4971: bipush #49
    //   4973: ldc 541081600
    //   4975: iastore
    //   4976: dup
    //   4977: bipush #50
    //   4979: iconst_0
    //   4980: iastore
    //   4981: dup
    //   4982: bipush #51
    //   4984: ldc 541065232
    //   4986: iastore
    //   4987: dup
    //   4988: bipush #52
    //   4990: bipush #16
    //   4992: iastore
    //   4993: dup
    //   4994: bipush #53
    //   4996: sipush #16384
    //   4999: iastore
    //   5000: dup
    //   5001: bipush #54
    //   5003: ldc 541065216
    //   5005: iastore
    //   5006: dup
    //   5007: bipush #55
    //   5009: ldc 4210704
    //   5011: iastore
    //   5012: dup
    //   5013: bipush #56
    //   5015: sipush #16384
    //   5018: iastore
    //   5019: dup
    //   5020: bipush #57
    //   5022: ldc 4194320
    //   5024: iastore
    //   5025: dup
    //   5026: bipush #58
    //   5028: ldc 536887312
    //   5030: iastore
    //   5031: dup
    //   5032: bipush #59
    //   5034: iconst_0
    //   5035: iastore
    //   5036: dup
    //   5037: bipush #60
    //   5039: ldc 541081600
    //   5041: iastore
    //   5042: dup
    //   5043: bipush #61
    //   5045: ldc 536870912
    //   5047: iastore
    //   5048: dup
    //   5049: bipush #62
    //   5051: ldc 4194320
    //   5053: iastore
    //   5054: dup
    //   5055: bipush #63
    //   5057: ldc 536887312
    //   5059: iastore
    //   5060: astore #11
    //   5062: bipush #64
    //   5064: newarray int
    //   5066: dup
    //   5067: iconst_0
    //   5068: ldc 2097152
    //   5070: iastore
    //   5071: dup
    //   5072: iconst_1
    //   5073: ldc 69206018
    //   5075: iastore
    //   5076: dup
    //   5077: iconst_2
    //   5078: ldc 67110914
    //   5080: iastore
    //   5081: dup
    //   5082: iconst_3
    //   5083: iconst_0
    //   5084: iastore
    //   5085: dup
    //   5086: iconst_4
    //   5087: sipush #2048
    //   5090: iastore
    //   5091: dup
    //   5092: iconst_5
    //   5093: ldc 67110914
    //   5095: iastore
    //   5096: dup
    //   5097: bipush #6
    //   5099: ldc 2099202
    //   5101: iastore
    //   5102: dup
    //   5103: bipush #7
    //   5105: ldc 69208064
    //   5107: iastore
    //   5108: dup
    //   5109: bipush #8
    //   5111: ldc 69208066
    //   5113: iastore
    //   5114: dup
    //   5115: bipush #9
    //   5117: ldc 2097152
    //   5119: iastore
    //   5120: dup
    //   5121: bipush #10
    //   5123: iconst_0
    //   5124: iastore
    //   5125: dup
    //   5126: bipush #11
    //   5128: ldc 67108866
    //   5130: iastore
    //   5131: dup
    //   5132: bipush #12
    //   5134: iconst_2
    //   5135: iastore
    //   5136: dup
    //   5137: bipush #13
    //   5139: ldc 67108864
    //   5141: iastore
    //   5142: dup
    //   5143: bipush #14
    //   5145: ldc 69206018
    //   5147: iastore
    //   5148: dup
    //   5149: bipush #15
    //   5151: sipush #2050
    //   5154: iastore
    //   5155: dup
    //   5156: bipush #16
    //   5158: ldc 67110912
    //   5160: iastore
    //   5161: dup
    //   5162: bipush #17
    //   5164: ldc 2099202
    //   5166: iastore
    //   5167: dup
    //   5168: bipush #18
    //   5170: ldc 2097154
    //   5172: iastore
    //   5173: dup
    //   5174: bipush #19
    //   5176: ldc 67110912
    //   5178: iastore
    //   5179: dup
    //   5180: bipush #20
    //   5182: ldc 67108866
    //   5184: iastore
    //   5185: dup
    //   5186: bipush #21
    //   5188: ldc 69206016
    //   5190: iastore
    //   5191: dup
    //   5192: bipush #22
    //   5194: ldc 69208064
    //   5196: iastore
    //   5197: dup
    //   5198: bipush #23
    //   5200: ldc 2097154
    //   5202: iastore
    //   5203: dup
    //   5204: bipush #24
    //   5206: ldc 69206016
    //   5208: iastore
    //   5209: dup
    //   5210: bipush #25
    //   5212: sipush #2048
    //   5215: iastore
    //   5216: dup
    //   5217: bipush #26
    //   5219: sipush #2050
    //   5222: iastore
    //   5223: dup
    //   5224: bipush #27
    //   5226: ldc 69208066
    //   5228: iastore
    //   5229: dup
    //   5230: bipush #28
    //   5232: ldc 2099200
    //   5234: iastore
    //   5235: dup
    //   5236: bipush #29
    //   5238: iconst_2
    //   5239: iastore
    //   5240: dup
    //   5241: bipush #30
    //   5243: ldc 67108864
    //   5245: iastore
    //   5246: dup
    //   5247: bipush #31
    //   5249: ldc 2099200
    //   5251: iastore
    //   5252: dup
    //   5253: bipush #32
    //   5255: ldc 67108864
    //   5257: iastore
    //   5258: dup
    //   5259: bipush #33
    //   5261: ldc 2099200
    //   5263: iastore
    //   5264: dup
    //   5265: bipush #34
    //   5267: ldc 2097152
    //   5269: iastore
    //   5270: dup
    //   5271: bipush #35
    //   5273: ldc 67110914
    //   5275: iastore
    //   5276: dup
    //   5277: bipush #36
    //   5279: ldc 67110914
    //   5281: iastore
    //   5282: dup
    //   5283: bipush #37
    //   5285: ldc 69206018
    //   5287: iastore
    //   5288: dup
    //   5289: bipush #38
    //   5291: ldc 69206018
    //   5293: iastore
    //   5294: dup
    //   5295: bipush #39
    //   5297: iconst_2
    //   5298: iastore
    //   5299: dup
    //   5300: bipush #40
    //   5302: ldc 2097154
    //   5304: iastore
    //   5305: dup
    //   5306: bipush #41
    //   5308: ldc 67108864
    //   5310: iastore
    //   5311: dup
    //   5312: bipush #42
    //   5314: ldc 67110912
    //   5316: iastore
    //   5317: dup
    //   5318: bipush #43
    //   5320: ldc 2097152
    //   5322: iastore
    //   5323: dup
    //   5324: bipush #44
    //   5326: ldc 69208064
    //   5328: iastore
    //   5329: dup
    //   5330: bipush #45
    //   5332: sipush #2050
    //   5335: iastore
    //   5336: dup
    //   5337: bipush #46
    //   5339: ldc 2099202
    //   5341: iastore
    //   5342: dup
    //   5343: bipush #47
    //   5345: ldc 69208064
    //   5347: iastore
    //   5348: dup
    //   5349: bipush #48
    //   5351: sipush #2050
    //   5354: iastore
    //   5355: dup
    //   5356: bipush #49
    //   5358: ldc 67108866
    //   5360: iastore
    //   5361: dup
    //   5362: bipush #50
    //   5364: ldc 69208066
    //   5366: iastore
    //   5367: dup
    //   5368: bipush #51
    //   5370: ldc 69206016
    //   5372: iastore
    //   5373: dup
    //   5374: bipush #52
    //   5376: ldc 2099200
    //   5378: iastore
    //   5379: dup
    //   5380: bipush #53
    //   5382: iconst_0
    //   5383: iastore
    //   5384: dup
    //   5385: bipush #54
    //   5387: iconst_2
    //   5388: iastore
    //   5389: dup
    //   5390: bipush #55
    //   5392: ldc 69208066
    //   5394: iastore
    //   5395: dup
    //   5396: bipush #56
    //   5398: iconst_0
    //   5399: iastore
    //   5400: dup
    //   5401: bipush #57
    //   5403: ldc 2099202
    //   5405: iastore
    //   5406: dup
    //   5407: bipush #58
    //   5409: ldc 69206016
    //   5411: iastore
    //   5412: dup
    //   5413: bipush #59
    //   5415: sipush #2048
    //   5418: iastore
    //   5419: dup
    //   5420: bipush #60
    //   5422: ldc 67108866
    //   5424: iastore
    //   5425: dup
    //   5426: bipush #61
    //   5428: ldc 67110912
    //   5430: iastore
    //   5431: dup
    //   5432: bipush #62
    //   5434: sipush #2048
    //   5437: iastore
    //   5438: dup
    //   5439: bipush #63
    //   5441: ldc 2097154
    //   5443: iastore
    //   5444: astore #12
    //   5446: bipush #64
    //   5448: newarray int
    //   5450: dup
    //   5451: iconst_0
    //   5452: ldc 268439616
    //   5454: iastore
    //   5455: dup
    //   5456: iconst_1
    //   5457: sipush #4096
    //   5460: iastore
    //   5461: dup
    //   5462: iconst_2
    //   5463: ldc 262144
    //   5465: iastore
    //   5466: dup
    //   5467: iconst_3
    //   5468: ldc 268701760
    //   5470: iastore
    //   5471: dup
    //   5472: iconst_4
    //   5473: ldc 268435456
    //   5475: iastore
    //   5476: dup
    //   5477: iconst_5
    //   5478: ldc 268439616
    //   5480: iastore
    //   5481: dup
    //   5482: bipush #6
    //   5484: bipush #64
    //   5486: iastore
    //   5487: dup
    //   5488: bipush #7
    //   5490: ldc 268435456
    //   5492: iastore
    //   5493: dup
    //   5494: bipush #8
    //   5496: ldc 262208
    //   5498: iastore
    //   5499: dup
    //   5500: bipush #9
    //   5502: ldc 268697600
    //   5504: iastore
    //   5505: dup
    //   5506: bipush #10
    //   5508: ldc 268701760
    //   5510: iastore
    //   5511: dup
    //   5512: bipush #11
    //   5514: ldc 266240
    //   5516: iastore
    //   5517: dup
    //   5518: bipush #12
    //   5520: ldc 268701696
    //   5522: iastore
    //   5523: dup
    //   5524: bipush #13
    //   5526: ldc 266304
    //   5528: iastore
    //   5529: dup
    //   5530: bipush #14
    //   5532: sipush #4096
    //   5535: iastore
    //   5536: dup
    //   5537: bipush #15
    //   5539: bipush #64
    //   5541: iastore
    //   5542: dup
    //   5543: bipush #16
    //   5545: ldc 268697600
    //   5547: iastore
    //   5548: dup
    //   5549: bipush #17
    //   5551: ldc 268435520
    //   5553: iastore
    //   5554: dup
    //   5555: bipush #18
    //   5557: ldc 268439552
    //   5559: iastore
    //   5560: dup
    //   5561: bipush #19
    //   5563: sipush #4160
    //   5566: iastore
    //   5567: dup
    //   5568: bipush #20
    //   5570: ldc 266240
    //   5572: iastore
    //   5573: dup
    //   5574: bipush #21
    //   5576: ldc 262208
    //   5578: iastore
    //   5579: dup
    //   5580: bipush #22
    //   5582: ldc 268697664
    //   5584: iastore
    //   5585: dup
    //   5586: bipush #23
    //   5588: ldc 268701696
    //   5590: iastore
    //   5591: dup
    //   5592: bipush #24
    //   5594: sipush #4160
    //   5597: iastore
    //   5598: dup
    //   5599: bipush #25
    //   5601: iconst_0
    //   5602: iastore
    //   5603: dup
    //   5604: bipush #26
    //   5606: iconst_0
    //   5607: iastore
    //   5608: dup
    //   5609: bipush #27
    //   5611: ldc 268697664
    //   5613: iastore
    //   5614: dup
    //   5615: bipush #28
    //   5617: ldc 268435520
    //   5619: iastore
    //   5620: dup
    //   5621: bipush #29
    //   5623: ldc 268439552
    //   5625: iastore
    //   5626: dup
    //   5627: bipush #30
    //   5629: ldc 266304
    //   5631: iastore
    //   5632: dup
    //   5633: bipush #31
    //   5635: ldc 262144
    //   5637: iastore
    //   5638: dup
    //   5639: bipush #32
    //   5641: ldc 266304
    //   5643: iastore
    //   5644: dup
    //   5645: bipush #33
    //   5647: ldc 262144
    //   5649: iastore
    //   5650: dup
    //   5651: bipush #34
    //   5653: ldc 268701696
    //   5655: iastore
    //   5656: dup
    //   5657: bipush #35
    //   5659: sipush #4096
    //   5662: iastore
    //   5663: dup
    //   5664: bipush #36
    //   5666: bipush #64
    //   5668: iastore
    //   5669: dup
    //   5670: bipush #37
    //   5672: ldc 268697664
    //   5674: iastore
    //   5675: dup
    //   5676: bipush #38
    //   5678: sipush #4096
    //   5681: iastore
    //   5682: dup
    //   5683: bipush #39
    //   5685: ldc 266304
    //   5687: iastore
    //   5688: dup
    //   5689: bipush #40
    //   5691: ldc 268439552
    //   5693: iastore
    //   5694: dup
    //   5695: bipush #41
    //   5697: bipush #64
    //   5699: iastore
    //   5700: dup
    //   5701: bipush #42
    //   5703: ldc 268435520
    //   5705: iastore
    //   5706: dup
    //   5707: bipush #43
    //   5709: ldc 268697600
    //   5711: iastore
    //   5712: dup
    //   5713: bipush #44
    //   5715: ldc 268697664
    //   5717: iastore
    //   5718: dup
    //   5719: bipush #45
    //   5721: ldc 268435456
    //   5723: iastore
    //   5724: dup
    //   5725: bipush #46
    //   5727: ldc 262144
    //   5729: iastore
    //   5730: dup
    //   5731: bipush #47
    //   5733: ldc 268439616
    //   5735: iastore
    //   5736: dup
    //   5737: bipush #48
    //   5739: iconst_0
    //   5740: iastore
    //   5741: dup
    //   5742: bipush #49
    //   5744: ldc 268701760
    //   5746: iastore
    //   5747: dup
    //   5748: bipush #50
    //   5750: ldc 262208
    //   5752: iastore
    //   5753: dup
    //   5754: bipush #51
    //   5756: ldc 268435520
    //   5758: iastore
    //   5759: dup
    //   5760: bipush #52
    //   5762: ldc 268697600
    //   5764: iastore
    //   5765: dup
    //   5766: bipush #53
    //   5768: ldc 268439552
    //   5770: iastore
    //   5771: dup
    //   5772: bipush #54
    //   5774: ldc 268439616
    //   5776: iastore
    //   5777: dup
    //   5778: bipush #55
    //   5780: iconst_0
    //   5781: iastore
    //   5782: dup
    //   5783: bipush #56
    //   5785: ldc 268701760
    //   5787: iastore
    //   5788: dup
    //   5789: bipush #57
    //   5791: ldc 266240
    //   5793: iastore
    //   5794: dup
    //   5795: bipush #58
    //   5797: ldc 266240
    //   5799: iastore
    //   5800: dup
    //   5801: bipush #59
    //   5803: sipush #4160
    //   5806: iastore
    //   5807: dup
    //   5808: bipush #60
    //   5810: sipush #4160
    //   5813: iastore
    //   5814: dup
    //   5815: bipush #61
    //   5817: ldc 262208
    //   5819: iastore
    //   5820: dup
    //   5821: bipush #62
    //   5823: ldc 268435456
    //   5825: iastore
    //   5826: dup
    //   5827: bipush #63
    //   5829: ldc 268701696
    //   5831: iastore
    //   5832: astore #13
    //   5834: aload_3
    //   5835: arraylength
    //   5836: istore #14
    //   5838: iload #14
    //   5840: bipush #8
    //   5842: irem
    //   5843: ifeq -> 5867
    //   5846: new java/lang/Exception
    //   5849: dup
    //   5850: sipush #-2844
    //   5853: sipush #20968
    //   5856: invokestatic a : (II)Ljava/lang/String;
    //   5859: invokespecial <init> : (Ljava/lang/String;)V
    //   5862: athrow
    //   5863: invokestatic a : (Ljava/lang/Throwable;)Ljava/lang/Throwable;
    //   5866: athrow
    //   5867: iconst_2
    //   5868: newarray int
    //   5870: astore #15
    //   5872: iload #14
    //   5874: newarray byte
    //   5876: astore #16
    //   5878: iload #14
    //   5880: bipush #8
    //   5882: idiv
    //   5883: istore #17
    //   5885: iconst_0
    //   5886: istore #18
    //   5888: iload #18
    //   5890: iload #17
    //   5892: if_icmpge -> 6806
    //   5895: iload #18
    //   5897: bipush #8
    //   5899: imul
    //   5900: istore #19
    //   5902: iconst_0
    //   5903: istore #20
    //   5905: iload #20
    //   5907: iconst_2
    //   5908: if_icmpge -> 5993
    //   5911: aload #15
    //   5913: iload #20
    //   5915: aload_3
    //   5916: iload #19
    //   5918: iload #20
    //   5920: iconst_4
    //   5921: imul
    //   5922: iadd
    //   5923: baload
    //   5924: sipush #255
    //   5927: iand
    //   5928: bipush #24
    //   5930: ishl
    //   5931: aload_3
    //   5932: iload #19
    //   5934: iload #20
    //   5936: iconst_4
    //   5937: imul
    //   5938: iadd
    //   5939: iconst_1
    //   5940: iadd
    //   5941: baload
    //   5942: sipush #255
    //   5945: iand
    //   5946: bipush #16
    //   5948: ishl
    //   5949: ior
    //   5950: aload_3
    //   5951: iload #19
    //   5953: iload #20
    //   5955: iconst_4
    //   5956: imul
    //   5957: iadd
    //   5958: iconst_2
    //   5959: iadd
    //   5960: baload
    //   5961: sipush #255
    //   5964: iand
    //   5965: bipush #8
    //   5967: ishl
    //   5968: ior
    //   5969: aload_3
    //   5970: iload #19
    //   5972: iload #20
    //   5974: iconst_4
    //   5975: imul
    //   5976: iadd
    //   5977: iconst_3
    //   5978: iadd
    //   5979: baload
    //   5980: sipush #255
    //   5983: iand
    //   5984: ior
    //   5985: iastore
    //   5986: iinc #20, 1
    //   5989: iload_2
    //   5990: ifeq -> 5905
    //   5993: iconst_0
    //   5994: istore #25
    //   5996: aload #15
    //   5998: iconst_0
    //   5999: iaload
    //   6000: istore #23
    //   6002: aload #15
    //   6004: iconst_1
    //   6005: iaload
    //   6006: istore #22
    //   6008: iload #23
    //   6010: iconst_4
    //   6011: iushr
    //   6012: iload #22
    //   6014: ixor
    //   6015: ldc 252645135
    //   6017: iand
    //   6018: istore #21
    //   6020: iload #22
    //   6022: iload #21
    //   6024: ixor
    //   6025: istore #22
    //   6027: iload #23
    //   6029: iload #21
    //   6031: iconst_4
    //   6032: ishl
    //   6033: ixor
    //   6034: istore #23
    //   6036: iload #23
    //   6038: bipush #16
    //   6040: iushr
    //   6041: iload #22
    //   6043: ixor
    //   6044: ldc 65535
    //   6046: iand
    //   6047: istore #21
    //   6049: iload #22
    //   6051: iload #21
    //   6053: ixor
    //   6054: istore #22
    //   6056: iload #23
    //   6058: iload #21
    //   6060: bipush #16
    //   6062: ishl
    //   6063: ixor
    //   6064: istore #23
    //   6066: iload #22
    //   6068: iconst_2
    //   6069: iushr
    //   6070: iload #23
    //   6072: ixor
    //   6073: ldc 858993459
    //   6075: iand
    //   6076: istore #21
    //   6078: iload #23
    //   6080: iload #21
    //   6082: ixor
    //   6083: istore #23
    //   6085: iload #22
    //   6087: iload #21
    //   6089: iconst_2
    //   6090: ishl
    //   6091: ixor
    //   6092: istore #22
    //   6094: iload #22
    //   6096: bipush #8
    //   6098: iushr
    //   6099: iload #23
    //   6101: ixor
    //   6102: ldc 16711935
    //   6104: iand
    //   6105: istore #21
    //   6107: iload #23
    //   6109: iload #21
    //   6111: ixor
    //   6112: istore #23
    //   6114: iload #22
    //   6116: iload #21
    //   6118: bipush #8
    //   6120: ishl
    //   6121: ixor
    //   6122: istore #22
    //   6124: iload #22
    //   6126: iconst_1
    //   6127: ishl
    //   6128: iload #22
    //   6130: bipush #31
    //   6132: iushr
    //   6133: iconst_1
    //   6134: iand
    //   6135: ior
    //   6136: istore #22
    //   6138: iload #23
    //   6140: iload #22
    //   6142: ixor
    //   6143: ldc -1431655766
    //   6145: iand
    //   6146: istore #21
    //   6148: iload #23
    //   6150: iload #21
    //   6152: ixor
    //   6153: istore #23
    //   6155: iload #22
    //   6157: iload #21
    //   6159: ixor
    //   6160: istore #22
    //   6162: iload #23
    //   6164: iconst_1
    //   6165: ishl
    //   6166: iload #23
    //   6168: bipush #31
    //   6170: iushr
    //   6171: iconst_1
    //   6172: iand
    //   6173: ior
    //   6174: istore #23
    //   6176: iconst_0
    //   6177: istore #24
    //   6179: iload #24
    //   6181: bipush #8
    //   6183: if_icmpge -> 6521
    //   6186: iload #22
    //   6188: bipush #28
    //   6190: ishl
    //   6191: iload #22
    //   6193: iconst_4
    //   6194: iushr
    //   6195: ior
    //   6196: istore #21
    //   6198: iload #21
    //   6200: aload #5
    //   6202: iload #25
    //   6204: iinc #25, 1
    //   6207: iaload
    //   6208: ixor
    //   6209: istore #21
    //   6211: aload #12
    //   6213: iload #21
    //   6215: bipush #63
    //   6217: iand
    //   6218: iaload
    //   6219: istore #20
    //   6221: iload #20
    //   6223: aload #10
    //   6225: iload #21
    //   6227: bipush #8
    //   6229: iushr
    //   6230: bipush #63
    //   6232: iand
    //   6233: iaload
    //   6234: ior
    //   6235: istore #20
    //   6237: iload #20
    //   6239: aload #8
    //   6241: iload #21
    //   6243: bipush #16
    //   6245: iushr
    //   6246: bipush #63
    //   6248: iand
    //   6249: iaload
    //   6250: ior
    //   6251: istore #20
    //   6253: iload #20
    //   6255: aload #6
    //   6257: iload #21
    //   6259: bipush #24
    //   6261: iushr
    //   6262: bipush #63
    //   6264: iand
    //   6265: iaload
    //   6266: ior
    //   6267: istore #20
    //   6269: iload #22
    //   6271: aload #5
    //   6273: iload #25
    //   6275: iinc #25, 1
    //   6278: iaload
    //   6279: ixor
    //   6280: istore #21
    //   6282: iload #20
    //   6284: aload #13
    //   6286: iload #21
    //   6288: bipush #63
    //   6290: iand
    //   6291: iaload
    //   6292: ior
    //   6293: istore #20
    //   6295: iload #20
    //   6297: aload #11
    //   6299: iload #21
    //   6301: bipush #8
    //   6303: iushr
    //   6304: bipush #63
    //   6306: iand
    //   6307: iaload
    //   6308: ior
    //   6309: istore #20
    //   6311: iload #20
    //   6313: aload #9
    //   6315: iload #21
    //   6317: bipush #16
    //   6319: iushr
    //   6320: bipush #63
    //   6322: iand
    //   6323: iaload
    //   6324: ior
    //   6325: istore #20
    //   6327: iload #20
    //   6329: aload #7
    //   6331: iload #21
    //   6333: bipush #24
    //   6335: iushr
    //   6336: bipush #63
    //   6338: iand
    //   6339: iaload
    //   6340: ior
    //   6341: istore #20
    //   6343: iload #23
    //   6345: iload #20
    //   6347: ixor
    //   6348: istore #23
    //   6350: iload #23
    //   6352: bipush #28
    //   6354: ishl
    //   6355: iload #23
    //   6357: iconst_4
    //   6358: iushr
    //   6359: ior
    //   6360: istore #21
    //   6362: iload #21
    //   6364: aload #5
    //   6366: iload #25
    //   6368: iinc #25, 1
    //   6371: iaload
    //   6372: ixor
    //   6373: istore #21
    //   6375: aload #12
    //   6377: iload #21
    //   6379: bipush #63
    //   6381: iand
    //   6382: iaload
    //   6383: istore #20
    //   6385: iload #20
    //   6387: aload #10
    //   6389: iload #21
    //   6391: bipush #8
    //   6393: iushr
    //   6394: bipush #63
    //   6396: iand
    //   6397: iaload
    //   6398: ior
    //   6399: istore #20
    //   6401: iload #20
    //   6403: aload #8
    //   6405: iload #21
    //   6407: bipush #16
    //   6409: iushr
    //   6410: bipush #63
    //   6412: iand
    //   6413: iaload
    //   6414: ior
    //   6415: istore #20
    //   6417: iload #20
    //   6419: aload #6
    //   6421: iload #21
    //   6423: bipush #24
    //   6425: iushr
    //   6426: bipush #63
    //   6428: iand
    //   6429: iaload
    //   6430: ior
    //   6431: istore #20
    //   6433: iload #23
    //   6435: aload #5
    //   6437: iload #25
    //   6439: iinc #25, 1
    //   6442: iaload
    //   6443: ixor
    //   6444: istore #21
    //   6446: iload #20
    //   6448: aload #13
    //   6450: iload #21
    //   6452: bipush #63
    //   6454: iand
    //   6455: iaload
    //   6456: ior
    //   6457: istore #20
    //   6459: iload #20
    //   6461: aload #11
    //   6463: iload #21
    //   6465: bipush #8
    //   6467: iushr
    //   6468: bipush #63
    //   6470: iand
    //   6471: iaload
    //   6472: ior
    //   6473: istore #20
    //   6475: iload #20
    //   6477: aload #9
    //   6479: iload #21
    //   6481: bipush #16
    //   6483: iushr
    //   6484: bipush #63
    //   6486: iand
    //   6487: iaload
    //   6488: ior
    //   6489: istore #20
    //   6491: iload #20
    //   6493: aload #7
    //   6495: iload #21
    //   6497: bipush #24
    //   6499: iushr
    //   6500: bipush #63
    //   6502: iand
    //   6503: iaload
    //   6504: ior
    //   6505: istore #20
    //   6507: iload #22
    //   6509: iload #20
    //   6511: ixor
    //   6512: istore #22
    //   6514: iinc #24, 1
    //   6517: iload_2
    //   6518: ifeq -> 6179
    //   6521: iload #22
    //   6523: bipush #31
    //   6525: ishl
    //   6526: iload #22
    //   6528: iconst_1
    //   6529: iushr
    //   6530: ior
    //   6531: istore #22
    //   6533: iload #23
    //   6535: iload #22
    //   6537: ixor
    //   6538: ldc -1431655766
    //   6540: iand
    //   6541: istore #21
    //   6543: iload #23
    //   6545: iload #21
    //   6547: ixor
    //   6548: istore #23
    //   6550: iload #22
    //   6552: iload #21
    //   6554: ixor
    //   6555: istore #22
    //   6557: iload #23
    //   6559: bipush #31
    //   6561: ishl
    //   6562: iload #23
    //   6564: iconst_1
    //   6565: iushr
    //   6566: ior
    //   6567: istore #23
    //   6569: iload #23
    //   6571: bipush #8
    //   6573: iushr
    //   6574: iload #22
    //   6576: ixor
    //   6577: ldc 16711935
    //   6579: iand
    //   6580: istore #21
    //   6582: iload #22
    //   6584: iload #21
    //   6586: ixor
    //   6587: istore #22
    //   6589: iload #23
    //   6591: iload #21
    //   6593: bipush #8
    //   6595: ishl
    //   6596: ixor
    //   6597: istore #23
    //   6599: iload #23
    //   6601: iconst_2
    //   6602: iushr
    //   6603: iload #22
    //   6605: ixor
    //   6606: ldc 858993459
    //   6608: iand
    //   6609: istore #21
    //   6611: iload #22
    //   6613: iload #21
    //   6615: ixor
    //   6616: istore #22
    //   6618: iload #23
    //   6620: iload #21
    //   6622: iconst_2
    //   6623: ishl
    //   6624: ixor
    //   6625: istore #23
    //   6627: iload #22
    //   6629: bipush #16
    //   6631: iushr
    //   6632: iload #23
    //   6634: ixor
    //   6635: ldc 65535
    //   6637: iand
    //   6638: istore #21
    //   6640: iload #23
    //   6642: iload #21
    //   6644: ixor
    //   6645: istore #23
    //   6647: iload #22
    //   6649: iload #21
    //   6651: bipush #16
    //   6653: ishl
    //   6654: ixor
    //   6655: istore #22
    //   6657: iload #22
    //   6659: iconst_4
    //   6660: iushr
    //   6661: iload #23
    //   6663: ixor
    //   6664: ldc 252645135
    //   6666: iand
    //   6667: istore #21
    //   6669: iload #23
    //   6671: iload #21
    //   6673: ixor
    //   6674: istore #23
    //   6676: iload #22
    //   6678: iload #21
    //   6680: iconst_4
    //   6681: ishl
    //   6682: ixor
    //   6683: istore #22
    //   6685: aload #15
    //   6687: iconst_0
    //   6688: iload #22
    //   6690: iastore
    //   6691: aload #15
    //   6693: iconst_1
    //   6694: iload #23
    //   6696: iastore
    //   6697: iload #18
    //   6699: bipush #8
    //   6701: imul
    //   6702: istore #26
    //   6704: iconst_0
    //   6705: istore #27
    //   6707: iload #27
    //   6709: iconst_2
    //   6710: if_icmpge -> 6799
    //   6713: aload #16
    //   6715: iload #26
    //   6717: iload #27
    //   6719: iconst_4
    //   6720: imul
    //   6721: iadd
    //   6722: aload #15
    //   6724: iload #27
    //   6726: iaload
    //   6727: bipush #24
    //   6729: iushr
    //   6730: i2b
    //   6731: bastore
    //   6732: aload #16
    //   6734: iload #26
    //   6736: iload #27
    //   6738: iconst_4
    //   6739: imul
    //   6740: iadd
    //   6741: iconst_1
    //   6742: iadd
    //   6743: aload #15
    //   6745: iload #27
    //   6747: iaload
    //   6748: bipush #16
    //   6750: iushr
    //   6751: i2b
    //   6752: bastore
    //   6753: aload #16
    //   6755: iload #26
    //   6757: iload #27
    //   6759: iconst_4
    //   6760: imul
    //   6761: iadd
    //   6762: iconst_2
    //   6763: iadd
    //   6764: aload #15
    //   6766: iload #27
    //   6768: iaload
    //   6769: bipush #8
    //   6771: iushr
    //   6772: i2b
    //   6773: bastore
    //   6774: aload #16
    //   6776: iload #26
    //   6778: iload #27
    //   6780: iconst_4
    //   6781: imul
    //   6782: iadd
    //   6783: iconst_3
    //   6784: iadd
    //   6785: aload #15
    //   6787: iload #27
    //   6789: iaload
    //   6790: i2b
    //   6791: bastore
    //   6792: iinc #27, 1
    //   6795: iload_2
    //   6796: ifeq -> 6707
    //   6799: iinc #18, 1
    //   6802: iload_2
    //   6803: ifeq -> 5888
    //   6806: aload #16
    //   6808: aload #16
    //   6810: arraylength
    //   6811: iconst_1
    //   6812: isub
    //   6813: baload
    //   6814: istore #18
    //   6816: aload #16
    //   6818: arraylength
    //   6819: iload #18
    //   6821: isub
    //   6822: newarray byte
    //   6824: astore #4
    //   6826: aload #16
    //   6828: arraylength
    //   6829: aload #4
    //   6831: arraylength
    //   6832: if_icmpge -> 6856
    //   6835: new java/lang/Exception
    //   6838: dup
    //   6839: sipush #-2844
    //   6842: sipush #20968
    //   6845: invokestatic a : (II)Ljava/lang/String;
    //   6848: invokespecial <init> : (Ljava/lang/String;)V
    //   6851: athrow
    //   6852: invokestatic a : (Ljava/lang/Throwable;)Ljava/lang/Throwable;
    //   6855: athrow
    //   6856: iconst_0
    //   6857: istore #19
    //   6859: iload #19
    //   6861: aload #4
    //   6863: arraylength
    //   6864: if_icmpge -> 6884
    //   6867: aload #4
    //   6869: iload #19
    //   6871: aload #16
    //   6873: iload #19
    //   6875: baload
    //   6876: bastore
    //   6877: iinc #19, 1
    //   6880: iload_2
    //   6881: ifeq -> 6859
    //   6884: new java/math/BigInteger
    //   6887: dup
    //   6888: aload #4
    //   6890: invokespecial <init> : ([B)V
    //   6893: invokevirtual abs : ()Ljava/math/BigInteger;
    //   6896: putstatic burp/Zs9x.Zo : Ljava/lang/Object;
    //   6899: new java/io/ByteArrayOutputStream
    //   6902: dup
    //   6903: invokespecial <init> : ()V
    //   6906: astore_3
    //   6907: getstatic burp/Zec0.Zk : Ljava/lang/String;
    //   6910: astore #4
    //   6912: iconst_0
    //   6913: istore #5
    //   6915: iload #5
    //   6917: aload #4
    //   6919: invokevirtual length : ()I
    //   6922: if_icmpge -> 6952
    //   6925: aload_3
    //   6926: aload #4
    //   6928: iload #5
    //   6930: iload #5
    //   6932: iconst_2
    //   6933: iadd
    //   6934: invokevirtual substring : (II)Ljava/lang/String;
    //   6937: bipush #16
    //   6939: invokestatic parseInt : (Ljava/lang/String;I)I
    //   6942: invokevirtual write : (I)V
    //   6945: iinc #5, 2
    //   6948: iload_2
    //   6949: ifeq -> 6915
    //   6952: aload_3
    //   6953: invokevirtual toByteArray : ()[B
    //   6956: astore #5
    //   6958: getstatic burp/Zex5.Zb : Ljava/lang/Object;
    //   6961: checkcast java/math/BigInteger
    //   6964: invokevirtual toByteArray : ()[B
    //   6967: astore #6
    //   6969: sipush #256
    //   6972: newarray byte
    //   6974: astore #8
    //   6976: sipush #256
    //   6979: newarray int
    //   6981: astore #9
    //   6983: sipush #256
    //   6986: newarray int
    //   6988: astore #10
    //   6990: sipush #256
    //   6993: newarray int
    //   6995: astore #11
    //   6997: sipush #256
    //   7000: newarray int
    //   7002: astore #12
    //   7004: bipush #10
    //   7006: newarray int
    //   7008: astore #13
    //   7010: sipush #283
    //   7013: istore #14
    //   7015: iconst_0
    //   7016: istore #16
    //   7018: iload #16
    //   7020: sipush #256
    //   7023: if_icmpge -> 7257
    //   7026: sipush #-2848
    //   7029: sipush #24966
    //   7032: invokestatic a : (II)Ljava/lang/String;
    //   7035: iload #16
    //   7037: iconst_1
    //   7038: iushr
    //   7039: invokevirtual charAt : (I)C
    //   7042: istore #25
    //   7044: iload #16
    //   7046: iconst_1
    //   7047: iand
    //   7048: ifne -> 7063
    //   7051: iload #25
    //   7053: bipush #8
    //   7055: iushr
    //   7056: goto -> 7065
    //   7059: invokestatic a : (Ljava/lang/Throwable;)Ljava/lang/Throwable;
    //   7062: athrow
    //   7063: iload #25
    //   7065: i2b
    //   7066: sipush #255
    //   7069: iand
    //   7070: istore #15
    //   7072: iload #16
    //   7074: iconst_1
    //   7075: ishl
    //   7076: istore #17
    //   7078: iload #17
    //   7080: sipush #256
    //   7083: if_icmplt -> 7093
    //   7086: iload #17
    //   7088: iload #14
    //   7090: ixor
    //   7091: istore #17
    //   7093: iload #17
    //   7095: iconst_1
    //   7096: ishl
    //   7097: istore #18
    //   7099: iload #18
    //   7101: sipush #256
    //   7104: if_icmplt -> 7114
    //   7107: iload #18
    //   7109: iload #14
    //   7111: ixor
    //   7112: istore #18
    //   7114: iload #18
    //   7116: iconst_1
    //   7117: ishl
    //   7118: istore #19
    //   7120: iload #19
    //   7122: sipush #256
    //   7125: if_icmplt -> 7135
    //   7128: iload #19
    //   7130: iload #14
    //   7132: ixor
    //   7133: istore #19
    //   7135: iload #19
    //   7137: iload #16
    //   7139: ixor
    //   7140: istore #20
    //   7142: iload #20
    //   7144: iload #17
    //   7146: ixor
    //   7147: istore #21
    //   7149: iload #20
    //   7151: iload #18
    //   7153: ixor
    //   7154: istore #22
    //   7156: iload #19
    //   7158: iload #18
    //   7160: ixor
    //   7161: iload #17
    //   7163: ixor
    //   7164: istore #23
    //   7166: aload #8
    //   7168: iload #16
    //   7170: iload #15
    //   7172: i2b
    //   7173: bastore
    //   7174: aload #9
    //   7176: iload #15
    //   7178: iload #23
    //   7180: bipush #24
    //   7182: ishl
    //   7183: iload #20
    //   7185: bipush #16
    //   7187: ishl
    //   7188: ior
    //   7189: iload #22
    //   7191: bipush #8
    //   7193: ishl
    //   7194: ior
    //   7195: iload #21
    //   7197: ior
    //   7198: dup
    //   7199: istore #24
    //   7201: iastore
    //   7202: aload #10
    //   7204: iload #15
    //   7206: iload #24
    //   7208: bipush #8
    //   7210: iushr
    //   7211: iload #24
    //   7213: bipush #24
    //   7215: ishl
    //   7216: ior
    //   7217: iastore
    //   7218: aload #11
    //   7220: iload #15
    //   7222: iload #24
    //   7224: bipush #16
    //   7226: iushr
    //   7227: iload #24
    //   7229: bipush #16
    //   7231: ishl
    //   7232: ior
    //   7233: iastore
    //   7234: aload #12
    //   7236: iload #15
    //   7238: iload #24
    //   7240: bipush #24
    //   7242: iushr
    //   7243: iload #24
    //   7245: bipush #8
    //   7247: ishl
    //   7248: ior
    //   7249: iastore
    //   7250: iinc #16, 1
    //   7253: iload_2
    //   7254: ifeq -> 7018
    //   7257: iconst_1
    //   7258: istore #25
    //   7260: aload #13
    //   7262: iconst_0
    //   7263: iload #25
    //   7265: bipush #24
    //   7267: ishl
    //   7268: iastore
    //   7269: iconst_1
    //   7270: istore #26
    //   7272: iload #26
    //   7274: bipush #10
    //   7276: if_icmpge -> 7317
    //   7279: iload #25
    //   7281: iconst_1
    //   7282: ishl
    //   7283: istore #25
    //   7285: iload #25
    //   7287: sipush #256
    //   7290: if_icmplt -> 7300
    //   7293: iload #25
    //   7295: iload #14
    //   7297: ixor
    //   7298: istore #25
    //   7300: aload #13
    //   7302: iload #26
    //   7304: iload #25
    //   7306: bipush #24
    //   7308: ishl
    //   7309: iastore
    //   7310: iinc #26, 1
    //   7313: iload_2
    //   7314: ifeq -> 7272
    //   7317: iconst_4
    //   7318: istore #26
    //   7320: iload #26
    //   7322: bipush #6
    //   7324: iadd
    //   7325: istore #27
    //   7327: iconst_4
    //   7328: iload #27
    //   7330: iconst_1
    //   7331: iadd
    //   7332: imul
    //   7333: istore #28
    //   7335: iload #28
    //   7337: newarray int
    //   7339: astore #29
    //   7341: iload #28
    //   7343: newarray int
    //   7345: astore #30
    //   7347: iconst_0
    //   7348: istore #25
    //   7350: iconst_0
    //   7351: istore #32
    //   7353: iconst_0
    //   7354: istore #33
    //   7356: iload #32
    //   7358: iload #26
    //   7360: if_icmpge -> 7428
    //   7363: aload #29
    //   7365: iload #32
    //   7367: aload #5
    //   7369: iload #33
    //   7371: baload
    //   7372: bipush #24
    //   7374: ishl
    //   7375: aload #5
    //   7377: iload #33
    //   7379: iconst_1
    //   7380: iadd
    //   7381: baload
    //   7382: sipush #255
    //   7385: iand
    //   7386: bipush #16
    //   7388: ishl
    //   7389: ior
    //   7390: aload #5
    //   7392: iload #33
    //   7394: iconst_2
    //   7395: iadd
    //   7396: baload
    //   7397: sipush #255
    //   7400: iand
    //   7401: bipush #8
    //   7403: ishl
    //   7404: ior
    //   7405: aload #5
    //   7407: iload #33
    //   7409: iconst_3
    //   7410: iadd
    //   7411: baload
    //   7412: sipush #255
    //   7415: iand
    //   7416: ior
    //   7417: iastore
    //   7418: iinc #32, 1
    //   7421: iinc #33, 4
    //   7424: iload_2
    //   7425: ifeq -> 7356
    //   7428: iload #26
    //   7430: istore #32
    //   7432: iconst_0
    //   7433: istore #33
    //   7435: iload #32
    //   7437: iload #28
    //   7439: if_icmpge -> 7566
    //   7442: aload #29
    //   7444: iload #32
    //   7446: iconst_1
    //   7447: isub
    //   7448: iaload
    //   7449: istore #31
    //   7451: iload #33
    //   7453: ifne -> 7540
    //   7456: iload #26
    //   7458: istore #33
    //   7460: aload #8
    //   7462: iload #31
    //   7464: bipush #16
    //   7466: iushr
    //   7467: sipush #255
    //   7470: iand
    //   7471: baload
    //   7472: bipush #24
    //   7474: ishl
    //   7475: aload #8
    //   7477: iload #31
    //   7479: bipush #8
    //   7481: iushr
    //   7482: sipush #255
    //   7485: iand
    //   7486: baload
    //   7487: sipush #255
    //   7490: iand
    //   7491: bipush #16
    //   7493: ishl
    //   7494: ior
    //   7495: aload #8
    //   7497: iload #31
    //   7499: sipush #255
    //   7502: iand
    //   7503: baload
    //   7504: sipush #255
    //   7507: iand
    //   7508: bipush #8
    //   7510: ishl
    //   7511: ior
    //   7512: aload #8
    //   7514: iload #31
    //   7516: bipush #24
    //   7518: iushr
    //   7519: baload
    //   7520: sipush #255
    //   7523: iand
    //   7524: ior
    //   7525: istore #31
    //   7527: iload #31
    //   7529: aload #13
    //   7531: iload #25
    //   7533: iinc #25, 1
    //   7536: iaload
    //   7537: ixor
    //   7538: istore #31
    //   7540: aload #29
    //   7542: iload #32
    //   7544: aload #29
    //   7546: iload #32
    //   7548: iload #26
    //   7550: isub
    //   7551: iaload
    //   7552: iload #31
    //   7554: ixor
    //   7555: iastore
    //   7556: iinc #32, 1
    //   7559: iinc #33, -1
    //   7562: iload_2
    //   7563: ifeq -> 7435
    //   7566: iconst_0
    //   7567: istore #32
    //   7569: iconst_4
    //   7570: iload #27
    //   7572: imul
    //   7573: istore #33
    //   7575: aload #30
    //   7577: iload #32
    //   7579: aload #29
    //   7581: iload #33
    //   7583: iaload
    //   7584: iastore
    //   7585: aload #30
    //   7587: iload #32
    //   7589: iconst_1
    //   7590: iadd
    //   7591: aload #29
    //   7593: iload #33
    //   7595: iconst_1
    //   7596: iadd
    //   7597: iaload
    //   7598: iastore
    //   7599: aload #30
    //   7601: iload #32
    //   7603: iconst_2
    //   7604: iadd
    //   7605: aload #29
    //   7607: iload #33
    //   7609: iconst_2
    //   7610: iadd
    //   7611: iaload
    //   7612: iastore
    //   7613: aload #30
    //   7615: iload #32
    //   7617: iconst_3
    //   7618: iadd
    //   7619: aload #29
    //   7621: iload #33
    //   7623: iconst_3
    //   7624: iadd
    //   7625: iaload
    //   7626: iastore
    //   7627: iinc #32, 4
    //   7630: iinc #33, -4
    //   7633: iconst_1
    //   7634: istore #35
    //   7636: iload #35
    //   7638: iload #27
    //   7640: if_icmpge -> 8004
    //   7643: aload #29
    //   7645: iload #33
    //   7647: iaload
    //   7648: istore #34
    //   7650: aload #30
    //   7652: iload #32
    //   7654: aload #9
    //   7656: aload #8
    //   7658: iload #34
    //   7660: bipush #24
    //   7662: iushr
    //   7663: baload
    //   7664: sipush #255
    //   7667: iand
    //   7668: iaload
    //   7669: aload #10
    //   7671: aload #8
    //   7673: iload #34
    //   7675: bipush #16
    //   7677: iushr
    //   7678: sipush #255
    //   7681: iand
    //   7682: baload
    //   7683: sipush #255
    //   7686: iand
    //   7687: iaload
    //   7688: ixor
    //   7689: aload #11
    //   7691: aload #8
    //   7693: iload #34
    //   7695: bipush #8
    //   7697: iushr
    //   7698: sipush #255
    //   7701: iand
    //   7702: baload
    //   7703: sipush #255
    //   7706: iand
    //   7707: iaload
    //   7708: ixor
    //   7709: aload #12
    //   7711: aload #8
    //   7713: iload #34
    //   7715: sipush #255
    //   7718: iand
    //   7719: baload
    //   7720: sipush #255
    //   7723: iand
    //   7724: iaload
    //   7725: ixor
    //   7726: iastore
    //   7727: aload #29
    //   7729: iload #33
    //   7731: iconst_1
    //   7732: iadd
    //   7733: iaload
    //   7734: istore #34
    //   7736: aload #30
    //   7738: iload #32
    //   7740: iconst_1
    //   7741: iadd
    //   7742: aload #9
    //   7744: aload #8
    //   7746: iload #34
    //   7748: bipush #24
    //   7750: iushr
    //   7751: baload
    //   7752: sipush #255
    //   7755: iand
    //   7756: iaload
    //   7757: aload #10
    //   7759: aload #8
    //   7761: iload #34
    //   7763: bipush #16
    //   7765: iushr
    //   7766: sipush #255
    //   7769: iand
    //   7770: baload
    //   7771: sipush #255
    //   7774: iand
    //   7775: iaload
    //   7776: ixor
    //   7777: aload #11
    //   7779: aload #8
    //   7781: iload #34
    //   7783: bipush #8
    //   7785: iushr
    //   7786: sipush #255
    //   7789: iand
    //   7790: baload
    //   7791: sipush #255
    //   7794: iand
    //   7795: iaload
    //   7796: ixor
    //   7797: aload #12
    //   7799: aload #8
    //   7801: iload #34
    //   7803: sipush #255
    //   7806: iand
    //   7807: baload
    //   7808: sipush #255
    //   7811: iand
    //   7812: iaload
    //   7813: ixor
    //   7814: iastore
    //   7815: aload #29
    //   7817: iload #33
    //   7819: iconst_2
    //   7820: iadd
    //   7821: iaload
    //   7822: istore #34
    //   7824: aload #30
    //   7826: iload #32
    //   7828: iconst_2
    //   7829: iadd
    //   7830: aload #9
    //   7832: aload #8
    //   7834: iload #34
    //   7836: bipush #24
    //   7838: iushr
    //   7839: baload
    //   7840: sipush #255
    //   7843: iand
    //   7844: iaload
    //   7845: aload #10
    //   7847: aload #8
    //   7849: iload #34
    //   7851: bipush #16
    //   7853: iushr
    //   7854: sipush #255
    //   7857: iand
    //   7858: baload
    //   7859: sipush #255
    //   7862: iand
    //   7863: iaload
    //   7864: ixor
    //   7865: aload #11
    //   7867: aload #8
    //   7869: iload #34
    //   7871: bipush #8
    //   7873: iushr
    //   7874: sipush #255
    //   7877: iand
    //   7878: baload
    //   7879: sipush #255
    //   7882: iand
    //   7883: iaload
    //   7884: ixor
    //   7885: aload #12
    //   7887: aload #8
    //   7889: iload #34
    //   7891: sipush #255
    //   7894: iand
    //   7895: baload
    //   7896: sipush #255
    //   7899: iand
    //   7900: iaload
    //   7901: ixor
    //   7902: iastore
    //   7903: aload #29
    //   7905: iload #33
    //   7907: iconst_3
    //   7908: iadd
    //   7909: iaload
    //   7910: istore #34
    //   7912: aload #30
    //   7914: iload #32
    //   7916: iconst_3
    //   7917: iadd
    //   7918: aload #9
    //   7920: aload #8
    //   7922: iload #34
    //   7924: bipush #24
    //   7926: iushr
    //   7927: baload
    //   7928: sipush #255
    //   7931: iand
    //   7932: iaload
    //   7933: aload #10
    //   7935: aload #8
    //   7937: iload #34
    //   7939: bipush #16
    //   7941: iushr
    //   7942: sipush #255
    //   7945: iand
    //   7946: baload
    //   7947: sipush #255
    //   7950: iand
    //   7951: iaload
    //   7952: ixor
    //   7953: aload #11
    //   7955: aload #8
    //   7957: iload #34
    //   7959: bipush #8
    //   7961: iushr
    //   7962: sipush #255
    //   7965: iand
    //   7966: baload
    //   7967: sipush #255
    //   7970: iand
    //   7971: iaload
    //   7972: ixor
    //   7973: aload #12
    //   7975: aload #8
    //   7977: iload #34
    //   7979: sipush #255
    //   7982: iand
    //   7983: baload
    //   7984: sipush #255
    //   7987: iand
    //   7988: iaload
    //   7989: ixor
    //   7990: iastore
    //   7991: iinc #32, 4
    //   7994: iinc #33, -4
    //   7997: iinc #35, 1
    //   8000: iload_2
    //   8001: ifeq -> 7636
    //   8004: aload #30
    //   8006: iload #32
    //   8008: aload #29
    //   8010: iload #33
    //   8012: iaload
    //   8013: iastore
    //   8014: aload #30
    //   8016: iload #32
    //   8018: iconst_1
    //   8019: iadd
    //   8020: aload #29
    //   8022: iload #33
    //   8024: iconst_1
    //   8025: iadd
    //   8026: iaload
    //   8027: iastore
    //   8028: aload #30
    //   8030: iload #32
    //   8032: iconst_2
    //   8033: iadd
    //   8034: aload #29
    //   8036: iload #33
    //   8038: iconst_2
    //   8039: iadd
    //   8040: iaload
    //   8041: iastore
    //   8042: aload #30
    //   8044: iload #32
    //   8046: iconst_3
    //   8047: iadd
    //   8048: aload #29
    //   8050: iload #33
    //   8052: iconst_3
    //   8053: iadd
    //   8054: iaload
    //   8055: iastore
    //   8056: iconst_0
    //   8057: newarray byte
    //   8059: astore #35
    //   8061: aload #6
    //   8063: arraylength
    //   8064: bipush #16
    //   8066: irem
    //   8067: ifeq -> 8091
    //   8070: new java/lang/Exception
    //   8073: dup
    //   8074: sipush #-2844
    //   8077: sipush #20968
    //   8080: invokestatic a : (II)Ljava/lang/String;
    //   8083: invokespecial <init> : (Ljava/lang/String;)V
    //   8086: athrow
    //   8087: invokestatic a : (Ljava/lang/Throwable;)Ljava/lang/Throwable;
    //   8090: athrow
    //   8091: bipush #10
    //   8093: istore #36
    //   8095: sipush #-2848
    //   8098: sipush #256
    //   8101: newarray byte
    //   8103: astore #37
    //   8105: sipush #24966
    //   8108: sipush #256
    //   8111: newarray int
    //   8113: astore #38
    //   8115: sipush #256
    //   8118: newarray int
    //   8120: astore #39
    //   8122: sipush #256
    //   8125: newarray int
    //   8127: astore #40
    //   8129: sipush #256
    //   8132: newarray int
    //   8134: astore #41
    //   8136: sipush #283
    //   8139: istore #14
    //   8141: invokestatic a : (II)Ljava/lang/String;
    //   8144: astore #42
    //   8146: iconst_0
    //   8147: istore #16
    //   8149: iload #16
    //   8151: sipush #256
    //   8154: if_icmpge -> 8381
    //   8157: aload #42
    //   8159: iload #16
    //   8161: iconst_1
    //   8162: iushr
    //   8163: invokevirtual charAt : (I)C
    //   8166: istore #43
    //   8168: iload #16
    //   8170: iconst_1
    //   8171: iand
    //   8172: ifne -> 8187
    //   8175: iload #43
    //   8177: bipush #8
    //   8179: iushr
    //   8180: goto -> 8189
    //   8183: invokestatic a : (Ljava/lang/Throwable;)Ljava/lang/Throwable;
    //   8186: athrow
    //   8187: iload #43
    //   8189: i2b
    //   8190: sipush #255
    //   8193: iand
    //   8194: istore #15
    //   8196: iload #16
    //   8198: iconst_1
    //   8199: ishl
    //   8200: istore #17
    //   8202: iload #17
    //   8204: sipush #256
    //   8207: if_icmplt -> 8217
    //   8210: iload #17
    //   8212: iload #14
    //   8214: ixor
    //   8215: istore #17
    //   8217: iload #17
    //   8219: iconst_1
    //   8220: ishl
    //   8221: istore #18
    //   8223: iload #18
    //   8225: sipush #256
    //   8228: if_icmplt -> 8238
    //   8231: iload #18
    //   8233: iload #14
    //   8235: ixor
    //   8236: istore #18
    //   8238: iload #18
    //   8240: iconst_1
    //   8241: ishl
    //   8242: istore #19
    //   8244: iload #19
    //   8246: sipush #256
    //   8249: if_icmplt -> 8259
    //   8252: iload #19
    //   8254: iload #14
    //   8256: ixor
    //   8257: istore #19
    //   8259: iload #19
    //   8261: iload #16
    //   8263: ixor
    //   8264: istore #20
    //   8266: iload #20
    //   8268: iload #17
    //   8270: ixor
    //   8271: istore #21
    //   8273: iload #20
    //   8275: iload #18
    //   8277: ixor
    //   8278: istore #22
    //   8280: iload #19
    //   8282: iload #18
    //   8284: ixor
    //   8285: iload #17
    //   8287: ixor
    //   8288: istore #23
    //   8290: aload #37
    //   8292: iload #15
    //   8294: iload #16
    //   8296: i2b
    //   8297: bastore
    //   8298: aload #38
    //   8300: iload #15
    //   8302: iload #23
    //   8304: bipush #24
    //   8306: ishl
    //   8307: iload #20
    //   8309: bipush #16
    //   8311: ishl
    //   8312: ior
    //   8313: iload #22
    //   8315: bipush #8
    //   8317: ishl
    //   8318: ior
    //   8319: iload #21
    //   8321: ior
    //   8322: dup
    //   8323: istore #24
    //   8325: iastore
    //   8326: aload #39
    //   8328: iload #15
    //   8330: iload #24
    //   8332: bipush #8
    //   8334: iushr
    //   8335: iload #24
    //   8337: bipush #24
    //   8339: ishl
    //   8340: ior
    //   8341: iastore
    //   8342: aload #40
    //   8344: iload #15
    //   8346: iload #24
    //   8348: bipush #16
    //   8350: iushr
    //   8351: iload #24
    //   8353: bipush #16
    //   8355: ishl
    //   8356: ior
    //   8357: iastore
    //   8358: aload #41
    //   8360: iload #15
    //   8362: iload #24
    //   8364: bipush #24
    //   8366: iushr
    //   8367: iload #24
    //   8369: bipush #8
    //   8371: ishl
    //   8372: ior
    //   8373: iastore
    //   8374: iinc #16, 1
    //   8377: iload_2
    //   8378: ifeq -> 8149
    //   8381: aload #6
    //   8383: arraylength
    //   8384: newarray byte
    //   8386: astore #43
    //   8388: iconst_0
    //   8389: istore #44
    //   8391: iload #44
    //   8393: aload #6
    //   8395: arraylength
    //   8396: bipush #16
    //   8398: idiv
    //   8399: if_icmpge -> 9313
    //   8402: bipush #16
    //   8404: newarray byte
    //   8406: astore #45
    //   8408: bipush #16
    //   8410: newarray byte
    //   8412: astore #46
    //   8414: iconst_0
    //   8415: istore #47
    //   8417: iload #47
    //   8419: bipush #16
    //   8421: if_icmpge -> 8447
    //   8424: aload #45
    //   8426: iload #47
    //   8428: aload #6
    //   8430: iload #47
    //   8432: iload #44
    //   8434: bipush #16
    //   8436: imul
    //   8437: iadd
    //   8438: baload
    //   8439: bastore
    //   8440: iinc #47, 1
    //   8443: iload_2
    //   8444: ifeq -> 8417
    //   8447: iconst_0
    //   8448: istore #47
    //   8450: aload #45
    //   8452: iconst_0
    //   8453: baload
    //   8454: bipush #24
    //   8456: ishl
    //   8457: aload #45
    //   8459: iconst_1
    //   8460: baload
    //   8461: sipush #255
    //   8464: iand
    //   8465: bipush #16
    //   8467: ishl
    //   8468: ior
    //   8469: aload #45
    //   8471: iconst_2
    //   8472: baload
    //   8473: sipush #255
    //   8476: iand
    //   8477: bipush #8
    //   8479: ishl
    //   8480: ior
    //   8481: aload #45
    //   8483: iconst_3
    //   8484: baload
    //   8485: sipush #255
    //   8488: iand
    //   8489: ior
    //   8490: aload #30
    //   8492: iconst_0
    //   8493: iaload
    //   8494: ixor
    //   8495: istore #49
    //   8497: aload #45
    //   8499: iconst_4
    //   8500: baload
    //   8501: bipush #24
    //   8503: ishl
    //   8504: aload #45
    //   8506: iconst_5
    //   8507: baload
    //   8508: sipush #255
    //   8511: iand
    //   8512: bipush #16
    //   8514: ishl
    //   8515: ior
    //   8516: aload #45
    //   8518: bipush #6
    //   8520: baload
    //   8521: sipush #255
    //   8524: iand
    //   8525: bipush #8
    //   8527: ishl
    //   8528: ior
    //   8529: aload #45
    //   8531: bipush #7
    //   8533: baload
    //   8534: sipush #255
    //   8537: iand
    //   8538: ior
    //   8539: aload #30
    //   8541: iconst_1
    //   8542: iaload
    //   8543: ixor
    //   8544: istore #50
    //   8546: aload #45
    //   8548: bipush #8
    //   8550: baload
    //   8551: bipush #24
    //   8553: ishl
    //   8554: aload #45
    //   8556: bipush #9
    //   8558: baload
    //   8559: sipush #255
    //   8562: iand
    //   8563: bipush #16
    //   8565: ishl
    //   8566: ior
    //   8567: aload #45
    //   8569: bipush #10
    //   8571: baload
    //   8572: sipush #255
    //   8575: iand
    //   8576: bipush #8
    //   8578: ishl
    //   8579: ior
    //   8580: aload #45
    //   8582: bipush #11
    //   8584: baload
    //   8585: sipush #255
    //   8588: iand
    //   8589: ior
    //   8590: aload #30
    //   8592: iconst_2
    //   8593: iaload
    //   8594: ixor
    //   8595: istore #51
    //   8597: aload #45
    //   8599: bipush #12
    //   8601: baload
    //   8602: bipush #24
    //   8604: ishl
    //   8605: aload #45
    //   8607: bipush #13
    //   8609: baload
    //   8610: sipush #255
    //   8613: iand
    //   8614: bipush #16
    //   8616: ishl
    //   8617: ior
    //   8618: aload #45
    //   8620: bipush #14
    //   8622: baload
    //   8623: sipush #255
    //   8626: iand
    //   8627: bipush #8
    //   8629: ishl
    //   8630: ior
    //   8631: aload #45
    //   8633: bipush #15
    //   8635: baload
    //   8636: sipush #255
    //   8639: iand
    //   8640: ior
    //   8641: aload #30
    //   8643: iconst_3
    //   8644: iaload
    //   8645: ixor
    //   8646: istore #52
    //   8648: iconst_1
    //   8649: istore #53
    //   8651: iload #53
    //   8653: iload #36
    //   8655: if_icmpge -> 8898
    //   8658: iinc #47, 4
    //   8661: aload #38
    //   8663: iload #49
    //   8665: bipush #24
    //   8667: iushr
    //   8668: iaload
    //   8669: aload #39
    //   8671: iload #52
    //   8673: bipush #16
    //   8675: iushr
    //   8676: sipush #255
    //   8679: iand
    //   8680: iaload
    //   8681: ixor
    //   8682: aload #40
    //   8684: iload #51
    //   8686: bipush #8
    //   8688: iushr
    //   8689: sipush #255
    //   8692: iand
    //   8693: iaload
    //   8694: ixor
    //   8695: aload #41
    //   8697: iload #50
    //   8699: sipush #255
    //   8702: iand
    //   8703: iaload
    //   8704: ixor
    //   8705: aload #30
    //   8707: iload #47
    //   8709: iaload
    //   8710: ixor
    //   8711: istore #54
    //   8713: aload #38
    //   8715: iload #50
    //   8717: bipush #24
    //   8719: iushr
    //   8720: iaload
    //   8721: aload #39
    //   8723: iload #49
    //   8725: bipush #16
    //   8727: iushr
    //   8728: sipush #255
    //   8731: iand
    //   8732: iaload
    //   8733: ixor
    //   8734: aload #40
    //   8736: iload #52
    //   8738: bipush #8
    //   8740: iushr
    //   8741: sipush #255
    //   8744: iand
    //   8745: iaload
    //   8746: ixor
    //   8747: aload #41
    //   8749: iload #51
    //   8751: sipush #255
    //   8754: iand
    //   8755: iaload
    //   8756: ixor
    //   8757: aload #30
    //   8759: iload #47
    //   8761: iconst_1
    //   8762: iadd
    //   8763: iaload
    //   8764: ixor
    //   8765: istore #55
    //   8767: aload #38
    //   8769: iload #51
    //   8771: bipush #24
    //   8773: iushr
    //   8774: iaload
    //   8775: aload #39
    //   8777: iload #50
    //   8779: bipush #16
    //   8781: iushr
    //   8782: sipush #255
    //   8785: iand
    //   8786: iaload
    //   8787: ixor
    //   8788: aload #40
    //   8790: iload #49
    //   8792: bipush #8
    //   8794: iushr
    //   8795: sipush #255
    //   8798: iand
    //   8799: iaload
    //   8800: ixor
    //   8801: aload #41
    //   8803: iload #52
    //   8805: sipush #255
    //   8808: iand
    //   8809: iaload
    //   8810: ixor
    //   8811: aload #30
    //   8813: iload #47
    //   8815: iconst_2
    //   8816: iadd
    //   8817: iaload
    //   8818: ixor
    //   8819: istore #56
    //   8821: aload #38
    //   8823: iload #52
    //   8825: bipush #24
    //   8827: iushr
    //   8828: iaload
    //   8829: aload #39
    //   8831: iload #51
    //   8833: bipush #16
    //   8835: iushr
    //   8836: sipush #255
    //   8839: iand
    //   8840: iaload
    //   8841: ixor
    //   8842: aload #40
    //   8844: iload #50
    //   8846: bipush #8
    //   8848: iushr
    //   8849: sipush #255
    //   8852: iand
    //   8853: iaload
    //   8854: ixor
    //   8855: aload #41
    //   8857: iload #49
    //   8859: sipush #255
    //   8862: iand
    //   8863: iaload
    //   8864: ixor
    //   8865: aload #30
    //   8867: iload #47
    //   8869: iconst_3
    //   8870: iadd
    //   8871: iaload
    //   8872: ixor
    //   8873: istore #57
    //   8875: iload #54
    //   8877: istore #49
    //   8879: iload #55
    //   8881: istore #50
    //   8883: iload #56
    //   8885: istore #51
    //   8887: iload #57
    //   8889: istore #52
    //   8891: iinc #53, 1
    //   8894: iload_2
    //   8895: ifeq -> 8651
    //   8898: iinc #47, 4
    //   8901: aload #30
    //   8903: iload #47
    //   8905: iaload
    //   8906: istore #48
    //   8908: aload #46
    //   8910: iconst_0
    //   8911: aload #37
    //   8913: iload #49
    //   8915: bipush #24
    //   8917: iushr
    //   8918: baload
    //   8919: iload #48
    //   8921: bipush #24
    //   8923: iushr
    //   8924: ixor
    //   8925: i2b
    //   8926: bastore
    //   8927: aload #46
    //   8929: iconst_1
    //   8930: aload #37
    //   8932: iload #52
    //   8934: bipush #16
    //   8936: iushr
    //   8937: sipush #255
    //   8940: iand
    //   8941: baload
    //   8942: iload #48
    //   8944: bipush #16
    //   8946: iushr
    //   8947: ixor
    //   8948: i2b
    //   8949: bastore
    //   8950: aload #46
    //   8952: iconst_2
    //   8953: aload #37
    //   8955: iload #51
    //   8957: bipush #8
    //   8959: iushr
    //   8960: sipush #255
    //   8963: iand
    //   8964: baload
    //   8965: iload #48
    //   8967: bipush #8
    //   8969: iushr
    //   8970: ixor
    //   8971: i2b
    //   8972: bastore
    //   8973: aload #46
    //   8975: iconst_3
    //   8976: aload #37
    //   8978: iload #50
    //   8980: sipush #255
    //   8983: iand
    //   8984: baload
    //   8985: iload #48
    //   8987: ixor
    //   8988: i2b
    //   8989: bastore
    //   8990: aload #30
    //   8992: iload #47
    //   8994: iconst_1
    //   8995: iadd
    //   8996: iaload
    //   8997: istore #48
    //   8999: aload #46
    //   9001: iconst_4
    //   9002: aload #37
    //   9004: iload #50
    //   9006: bipush #24
    //   9008: iushr
    //   9009: baload
    //   9010: iload #48
    //   9012: bipush #24
    //   9014: iushr
    //   9015: ixor
    //   9016: i2b
    //   9017: bastore
    //   9018: aload #46
    //   9020: iconst_5
    //   9021: aload #37
    //   9023: iload #49
    //   9025: bipush #16
    //   9027: iushr
    //   9028: sipush #255
    //   9031: iand
    //   9032: baload
    //   9033: iload #48
    //   9035: bipush #16
    //   9037: iushr
    //   9038: ixor
    //   9039: i2b
    //   9040: bastore
    //   9041: aload #46
    //   9043: bipush #6
    //   9045: aload #37
    //   9047: iload #52
    //   9049: bipush #8
    //   9051: iushr
    //   9052: sipush #255
    //   9055: iand
    //   9056: baload
    //   9057: iload #48
    //   9059: bipush #8
    //   9061: iushr
    //   9062: ixor
    //   9063: i2b
    //   9064: bastore
    //   9065: aload #46
    //   9067: bipush #7
    //   9069: aload #37
    //   9071: iload #51
    //   9073: sipush #255
    //   9076: iand
    //   9077: baload
    //   9078: iload #48
    //   9080: ixor
    //   9081: i2b
    //   9082: bastore
    //   9083: aload #30
    //   9085: iload #47
    //   9087: iconst_2
    //   9088: iadd
    //   9089: iaload
    //   9090: istore #48
    //   9092: aload #46
    //   9094: bipush #8
    //   9096: aload #37
    //   9098: iload #51
    //   9100: bipush #24
    //   9102: iushr
    //   9103: baload
    //   9104: iload #48
    //   9106: bipush #24
    //   9108: iushr
    //   9109: ixor
    //   9110: i2b
    //   9111: bastore
    //   9112: aload #46
    //   9114: bipush #9
    //   9116: aload #37
    //   9118: iload #50
    //   9120: bipush #16
    //   9122: iushr
    //   9123: sipush #255
    //   9126: iand
    //   9127: baload
    //   9128: iload #48
    //   9130: bipush #16
    //   9132: iushr
    //   9133: ixor
    //   9134: i2b
    //   9135: bastore
    //   9136: aload #46
    //   9138: bipush #10
    //   9140: aload #37
    //   9142: iload #49
    //   9144: bipush #8
    //   9146: iushr
    //   9147: sipush #255
    //   9150: iand
    //   9151: baload
    //   9152: iload #48
    //   9154: bipush #8
    //   9156: iushr
    //   9157: ixor
    //   9158: i2b
    //   9159: bastore
    //   9160: aload #46
    //   9162: bipush #11
    //   9164: aload #37
    //   9166: iload #52
    //   9168: sipush #255
    //   9171: iand
    //   9172: baload
    //   9173: iload #48
    //   9175: ixor
    //   9176: i2b
    //   9177: bastore
    //   9178: aload #30
    //   9180: iload #47
    //   9182: iconst_3
    //   9183: iadd
    //   9184: iaload
    //   9185: istore #48
    //   9187: aload #46
    //   9189: bipush #12
    //   9191: aload #37
    //   9193: iload #52
    //   9195: bipush #24
    //   9197: iushr
    //   9198: baload
    //   9199: iload #48
    //   9201: bipush #24
    //   9203: iushr
    //   9204: ixor
    //   9205: i2b
    //   9206: bastore
    //   9207: aload #46
    //   9209: bipush #13
    //   9211: aload #37
    //   9213: iload #51
    //   9215: bipush #16
    //   9217: iushr
    //   9218: sipush #255
    //   9221: iand
    //   9222: baload
    //   9223: iload #48
    //   9225: bipush #16
    //   9227: iushr
    //   9228: ixor
    //   9229: i2b
    //   9230: bastore
    //   9231: aload #46
    //   9233: bipush #14
    //   9235: aload #37
    //   9237: iload #50
    //   9239: bipush #8
    //   9241: iushr
    //   9242: sipush #255
    //   9245: iand
    //   9246: baload
    //   9247: iload #48
    //   9249: bipush #8
    //   9251: iushr
    //   9252: ixor
    //   9253: i2b
    //   9254: bastore
    //   9255: aload #46
    //   9257: bipush #15
    //   9259: aload #37
    //   9261: iload #49
    //   9263: sipush #255
    //   9266: iand
    //   9267: baload
    //   9268: iload #48
    //   9270: ixor
    //   9271: i2b
    //   9272: bastore
    //   9273: iconst_0
    //   9274: istore #53
    //   9276: iload #53
    //   9278: bipush #16
    //   9280: if_icmpge -> 9306
    //   9283: aload #43
    //   9285: iload #53
    //   9287: iload #44
    //   9289: bipush #16
    //   9291: imul
    //   9292: iadd
    //   9293: aload #46
    //   9295: iload #53
    //   9297: baload
    //   9298: bastore
    //   9299: iinc #53, 1
    //   9302: iload_2
    //   9303: ifeq -> 9276
    //   9306: iinc #44, 1
    //   9309: iload_2
    //   9310: ifeq -> 8391
    //   9313: aload #43
    //   9315: arraylength
    //   9316: ifle -> 9397
    //   9319: aload #43
    //   9321: aload #43
    //   9323: arraylength
    //   9324: iconst_1
    //   9325: isub
    //   9326: baload
    //   9327: istore #44
    //   9329: iload #44
    //   9331: bipush #16
    //   9333: if_icmple -> 9344
    //   9336: aload #43
    //   9338: astore #35
    //   9340: iload_2
    //   9341: ifeq -> 9397
    //   9344: aload #43
    //   9346: arraylength
    //   9347: iload #44
    //   9349: isub
    //   9350: newarray byte
    //   9352: astore #35
    //   9354: iconst_0
    //   9355: istore #45
    //   9357: iload #45
    //   9359: aload #35
    //   9361: arraylength
    //   9362: if_icmpge -> 9397
    //   9365: iload #45
    //   9367: aload #43
    //   9369: arraylength
    //   9370: if_icmpge -> 9397
    //   9373: aload #35
    //   9375: iload #45
    //   9377: aload #43
    //   9379: iload #45
    //   9381: baload
    //   9382: bastore
    //   9383: iinc #45, 1
    //   9386: iload_2
    //   9387: ifeq -> 9357
    //   9390: goto -> 9397
    //   9393: invokestatic a : (Ljava/lang/Throwable;)Ljava/lang/Throwable;
    //   9396: athrow
    //   9397: aload #35
    //   9399: astore #7
    //   9401: sipush #-2846
    //   9404: new java/math/BigInteger
    //   9407: dup
    //   9408: aload #7
    //   9410: invokespecial <init> : ([B)V
    //   9413: invokevirtual abs : ()Ljava/math/BigInteger;
    //   9416: putstatic burp/Zlh2.Zc : Ljava/lang/Object;
    //   9419: sipush #29375
    //   9422: invokestatic a : (II)Ljava/lang/String;
    //   9425: iconst_1
    //   9426: ldc burp/Zbzc
    //   9428: invokevirtual getClassLoader : ()Ljava/lang/ClassLoader;
    //   9431: invokestatic forName : (Ljava/lang/String;ZLjava/lang/ClassLoader;)Ljava/lang/Class;
    //   9434: invokevirtual getDeclaredFields : ()[Ljava/lang/reflect/Field;
    //   9437: astore_3
    //   9438: aload_3
    //   9439: arraylength
    //   9440: istore #4
    //   9442: iconst_0
    //   9443: istore #5
    //   9445: iload #5
    //   9447: iload #4
    //   9449: if_icmpge -> 9586
    //   9452: aload_3
    //   9453: iload #5
    //   9455: aaload
    //   9456: astore #6
    //   9458: aload #6
    //   9460: invokevirtual getModifiers : ()I
    //   9463: invokestatic isStatic : (I)Z
    //   9466: ifne -> 9476
    //   9469: goto -> 9579
    //   9472: invokestatic a : (Ljava/lang/Throwable;)Ljava/lang/Throwable;
    //   9475: athrow
    //   9476: aload #6
    //   9478: invokevirtual getType : ()Ljava/lang/Class;
    //   9481: astore #7
    //   9483: aload #7
    //   9485: ifnull -> 9566
    //   9488: aload #7
    //   9490: invokevirtual isPrimitive : ()Z
    //   9493: ifne -> 9566
    //   9496: goto -> 9503
    //   9499: invokestatic a : (Ljava/lang/Throwable;)Ljava/lang/Throwable;
    //   9502: athrow
    //   9503: aload #7
    //   9505: invokevirtual getPackage : ()Ljava/lang/Package;
    //   9508: ifnull -> 9566
    //   9511: goto -> 9518
    //   9514: invokestatic a : (Ljava/lang/Throwable;)Ljava/lang/Throwable;
    //   9517: athrow
    //   9518: aload #7
    //   9520: invokevirtual getPackage : ()Ljava/lang/Package;
    //   9523: invokevirtual getName : ()Ljava/lang/String;
    //   9526: ifnull -> 9566
    //   9529: goto -> 9536
    //   9532: invokestatic a : (Ljava/lang/Throwable;)Ljava/lang/Throwable;
    //   9535: athrow
    //   9536: aload #7
    //   9538: invokevirtual getPackage : ()Ljava/lang/Package;
    //   9541: invokevirtual getName : ()Ljava/lang/String;
    //   9544: sipush #-2841
    //   9547: sipush #32290
    //   9550: invokestatic a : (II)Ljava/lang/String;
    //   9553: invokevirtual startsWith : (Ljava/lang/String;)Z
    //   9556: ifne -> 9566
    //   9559: goto -> 9566
    //   9562: invokestatic a : (Ljava/lang/Throwable;)Ljava/lang/Throwable;
    //   9565: athrow
    //   9566: aload #6
    //   9568: iconst_1
    //   9569: invokevirtual setAccessible : (Z)V
    //   9572: aload #6
    //   9574: aconst_null
    //   9575: invokevirtual get : (Ljava/lang/Object;)Ljava/lang/Object;
    //   9578: pop
    //   9579: iinc #5, 1
    //   9582: iload_2
    //   9583: ifeq -> 9445
    //   9586: sipush #-2837
    //   9589: sipush #-11372
    //   9592: invokestatic a : (II)Ljava/lang/String;
    //   9595: invokestatic forName : (Ljava/lang/String;)Ljava/lang/Class;
    //   9598: invokevirtual getDeclaredMethods : ()[Ljava/lang/reflect/Method;
    //   9601: astore_3
    //   9602: aload_3
    //   9603: arraylength
    //   9604: istore #4
    //   9606: iconst_0
    //   9607: istore #5
    //   9609: iload #5
    //   9611: iload #4
    //   9613: if_icmpge -> 9724
    //   9616: aload_3
    //   9617: iload #5
    //   9619: aaload
    //   9620: astore #6
    //   9622: aload #6
    //   9624: invokevirtual getParameterTypes : ()[Ljava/lang/Class;
    //   9627: pop
    //   9628: aload #6
    //   9630: invokevirtual getModifiers : ()I
    //   9633: invokestatic isStatic : (I)Z
    //   9636: ifeq -> 9710
    //   9639: aload #6
    //   9641: invokevirtual getParameterTypes : ()[Ljava/lang/Class;
    //   9644: arraylength
    //   9645: iconst_2
    //   9646: if_icmpne -> 9710
    //   9649: goto -> 9656
    //   9652: invokestatic a : (Ljava/lang/Throwable;)Ljava/lang/Throwable;
    //   9655: athrow
    //   9656: aload #6
    //   9658: invokevirtual getReturnType : ()Ljava/lang/Class;
    //   9661: getstatic java/lang/Boolean.TYPE : Ljava/lang/Class;
    //   9664: if_acmpne -> 9710
    //   9667: goto -> 9674
    //   9670: invokestatic a : (Ljava/lang/Throwable;)Ljava/lang/Throwable;
    //   9673: athrow
    //   9674: aload #6
    //   9676: iconst_1
    //   9677: invokevirtual setAccessible : (Z)V
    //   9680: aload #6
    //   9682: aconst_null
    //   9683: iconst_2
    //   9684: anewarray java/lang/Object
    //   9687: dup
    //   9688: iconst_0
    //   9689: aload_0
    //   9690: aastore
    //   9691: dup
    //   9692: iconst_1
    //   9693: aload_1
    //   9694: aastore
    //   9695: invokevirtual invoke : (Ljava/lang/Object;[Ljava/lang/Object;)Ljava/lang/Object;
    //   9698: pop
    //   9699: iload_2
    //   9700: ifeq -> 9724
    //   9703: goto -> 9710
    //   9706: invokestatic a : (Ljava/lang/Throwable;)Ljava/lang/Throwable;
    //   9709: athrow
    //   9710: iinc #5, 1
    //   9713: iload_2
    //   9714: ifeq -> 9609
    //   9717: goto -> 9724
    //   9720: invokestatic a : (Ljava/lang/Throwable;)Ljava/lang/Throwable;
    //   9723: athrow
    //   9724: sipush #-2842
    //   9727: sipush #3217
    //   9730: invokestatic a : (II)Ljava/lang/String;
    //   9733: iconst_1
    //   9734: ldc burp/Zsfj
    //   9736: invokevirtual getClassLoader : ()Ljava/lang/ClassLoader;
    //   9739: invokestatic forName : (Ljava/lang/String;ZLjava/lang/ClassLoader;)Ljava/lang/Class;
    //   9742: invokevirtual getDeclaredFields : ()[Ljava/lang/reflect/Field;
    //   9745: astore_3
    //   9746: aload_3
    //   9747: arraylength
    //   9748: istore #4
    //   9750: iconst_0
    //   9751: istore #5
    //   9753: iload #5
    //   9755: iload #4
    //   9757: if_icmpge -> 9894
    //   9760: aload_3
    //   9761: iload #5
    //   9763: aaload
    //   9764: astore #6
    //   9766: aload #6
    //   9768: invokevirtual getModifiers : ()I
    //   9771: invokestatic isStatic : (I)Z
    //   9774: ifne -> 9784
    //   9777: goto -> 9887
    //   9780: invokestatic a : (Ljava/lang/Throwable;)Ljava/lang/Throwable;
    //   9783: athrow
    //   9784: aload #6
    //   9786: invokevirtual getType : ()Ljava/lang/Class;
    //   9789: astore #7
    //   9791: aload #7
    //   9793: ifnull -> 9874
    //   9796: aload #7
    //   9798: invokevirtual isPrimitive : ()Z
    //   9801: ifne -> 9874
    //   9804: goto -> 9811
    //   9807: invokestatic a : (Ljava/lang/Throwable;)Ljava/lang/Throwable;
    //   9810: athrow
    //   9811: aload #7
    //   9813: invokevirtual getPackage : ()Ljava/lang/Package;
    //   9816: ifnull -> 9874
    //   9819: goto -> 9826
    //   9822: invokestatic a : (Ljava/lang/Throwable;)Ljava/lang/Throwable;
    //   9825: athrow
    //   9826: aload #7
    //   9828: invokevirtual getPackage : ()Ljava/lang/Package;
    //   9831: invokevirtual getName : ()Ljava/lang/String;
    //   9834: ifnull -> 9874
    //   9837: goto -> 9844
    //   9840: invokestatic a : (Ljava/lang/Throwable;)Ljava/lang/Throwable;
    //   9843: athrow
    //   9844: aload #7
    //   9846: invokevirtual getPackage : ()Ljava/lang/Package;
    //   9849: invokevirtual getName : ()Ljava/lang/String;
    //   9852: sipush #-2843
    //   9855: sipush #-25614
    //   9858: invokestatic a : (II)Ljava/lang/String;
    //   9861: invokevirtual startsWith : (Ljava/lang/String;)Z
    //   9864: ifne -> 9874
    //   9867: goto -> 9874
    //   9870: invokestatic a : (Ljava/lang/Throwable;)Ljava/lang/Throwable;
    //   9873: athrow
    //   9874: aload #6
    //   9876: iconst_1
    //   9877: invokevirtual setAccessible : (Z)V
    //   9880: aload #6
    //   9882: aconst_null
    //   9883: invokevirtual get : (Ljava/lang/Object;)Ljava/lang/Object;
    //   9886: pop
    //   9887: iinc #5, 1
    //   9890: iload_2
    //   9891: ifeq -> 9753
    //   9894: sipush #-2845
    //   9897: sipush #-24605
    //   9900: invokestatic a : (II)Ljava/lang/String;
    //   9903: invokestatic forName : (Ljava/lang/String;)Ljava/lang/Class;
    //   9906: invokevirtual getDeclaredMethods : ()[Ljava/lang/reflect/Method;
    //   9909: astore_3
    //   9910: aload_3
    //   9911: arraylength
    //   9912: istore #4
    //   9914: iconst_0
    //   9915: istore #5
    //   9917: iload #5
    //   9919: iload #4
    //   9921: if_icmpge -> 10053
    //   9924: aload_3
    //   9925: iload #5
    //   9927: aaload
    //   9928: astore #6
    //   9930: aload #6
    //   9932: invokevirtual getParameterTypes : ()[Ljava/lang/Class;
    //   9935: pop
    //   9936: aload #6
    //   9938: invokevirtual getModifiers : ()I
    //   9941: invokestatic isStatic : (I)Z
    //   9944: ifeq -> 10039
    //   9947: aload #6
    //   9949: invokevirtual getParameterTypes : ()[Ljava/lang/Class;
    //   9952: arraylength
    //   9953: iconst_2
    //   9954: if_icmpne -> 10039
    //   9957: goto -> 9964
    //   9960: invokestatic a : (Ljava/lang/Throwable;)Ljava/lang/Throwable;
    //   9963: athrow
    //   9964: aload #6
    //   9966: invokevirtual getReturnType : ()Ljava/lang/Class;
    //   9969: getstatic java/lang/Void.TYPE : Ljava/lang/Class;
    //   9972: invokevirtual equals : (Ljava/lang/Object;)Z
    //   9975: ifeq -> 10039
    //   9978: goto -> 9985
    //   9981: invokestatic a : (Ljava/lang/Throwable;)Ljava/lang/Throwable;
    //   9984: athrow
    //   9985: aload #6
    //   9987: iconst_1
    //   9988: invokevirtual setAccessible : (Z)V
    //   9991: aload #6
    //   9993: aconst_null
    //   9994: iconst_2
    //   9995: anewarray java/lang/Object
    //   9998: dup
    //   9999: iconst_0
    //   10000: aload_0
    //   10001: aastore
    //   10002: dup
    //   10003: iconst_1
    //   10004: aload_1
    //   10005: ifnonnull -> 10023
    //   10008: goto -> 10015
    //   10011: invokestatic a : (Ljava/lang/Throwable;)Ljava/lang/Throwable;
    //   10014: athrow
    //   10015: aload_1
    //   10016: goto -> 10030
    //   10019: invokestatic a : (Ljava/lang/Throwable;)Ljava/lang/Throwable;
    //   10022: athrow
    //   10023: aload_1
    //   10024: checkcast [B
    //   10027: invokevirtual clone : ()Ljava/lang/Object;
    //   10030: aastore
    //   10031: invokevirtual invoke : (Ljava/lang/Object;[Ljava/lang/Object;)Ljava/lang/Object;
    //   10034: pop
    //   10035: iload_2
    //   10036: ifeq -> 10053
    //   10039: iinc #5, 1
    //   10042: iload_2
    //   10043: ifeq -> 9917
    //   10046: goto -> 10053
    //   10049: invokestatic a : (Ljava/lang/Throwable;)Ljava/lang/Throwable;
    //   10052: athrow
    //   10053: getstatic burp/Zltp.ZY : Ljava/lang/String;
    //   10056: getstatic burp/Zz5l.Zb : Ljava/lang/Object;
    //   10059: checkcast java/math/BigInteger
    //   10062: invokevirtual intValue : ()I
    //   10065: bipush #32
    //   10067: irem
    //   10068: invokestatic abs : (I)I
    //   10071: invokevirtual charAt : (I)C
    //   10074: getstatic burp/Zlbd.Zq : Ljava/lang/String;
    //   10077: getstatic burp/Zgvl.ZK : Ljava/lang/Object;
    //   10080: checkcast java/math/BigInteger
    //   10083: invokevirtual intValue : ()I
    //   10086: bipush #32
    //   10088: irem
    //   10089: invokestatic abs : (I)I
    //   10092: invokevirtual charAt : (I)C
    //   10095: if_icmpgt -> 10210
    //   10098: getstatic burp/Zgt7.ZO : Ljava/lang/String;
    //   10101: getstatic burp/Zlqy.ZP : Ljava/lang/Object;
    //   10104: checkcast java/math/BigInteger
    //   10107: invokevirtual intValue : ()I
    //   10110: bipush #32
    //   10112: irem
    //   10113: invokestatic abs : (I)I
    //   10116: invokevirtual charAt : (I)C
    //   10119: getstatic burp/Ztid.Zz : Ljava/lang/String;
    //   10122: getstatic burp/Zlfg.Zv : Ljava/lang/Object;
    //   10125: checkcast java/math/BigInteger
    //   10128: invokevirtual intValue : ()I
    //   10131: bipush #32
    //   10133: irem
    //   10134: invokestatic abs : (I)I
    //   10137: invokevirtual charAt : (I)C
    //   10140: if_icmpgt -> 10210
    //   10143: goto -> 10150
    //   10146: invokestatic a : (Ljava/lang/Throwable;)Ljava/lang/Throwable;
    //   10149: athrow
    //   10150: getstatic burp/Zkco.Zz : Ljava/lang/String;
    //   10153: getstatic burp/Zrjw.Zu : Ljava/lang/Object;
    //   10156: checkcast java/math/BigInteger
    //   10159: invokevirtual intValue : ()I
    //   10162: bipush #32
    //   10164: irem
    //   10165: invokestatic abs : (I)I
    //   10168: invokevirtual charAt : (I)C
    //   10171: getstatic burp/Ztes.Zo : Ljava/lang/String;
    //   10174: getstatic burp/Zzap.ZL : Ljava/lang/Object;
    //   10177: checkcast java/math/BigInteger
    //   10180: invokevirtual intValue : ()I
    //   10183: bipush #32
    //   10185: irem
    //   10186: invokestatic abs : (I)I
    //   10189: invokevirtual charAt : (I)C
    //   10192: if_icmple -> 10210
    //   10195: goto -> 10202
    //   10198: invokestatic a : (Ljava/lang/Throwable;)Ljava/lang/Throwable;
    //   10201: athrow
    //   10202: iconst_1
    //   10203: goto -> 10211
    //   10206: invokestatic a : (Ljava/lang/Throwable;)Ljava/lang/Throwable;
    //   10209: athrow
    //   10210: iconst_0
    //   10211: ireturn
    //   10212: astore_3
    //   10213: new java/lang/Exception
    //   10216: dup
    //   10217: aload_3
    //   10218: invokevirtual getMessage : ()Ljava/lang/String;
    //   10221: invokespecial <init> : (Ljava/lang/String;)V
    //   10224: athrow
    // Exception table:
    //   from	to	target	type
    //   4	10211	10212	java/lang/Throwable
    //   164	179	179	java/lang/Throwable
    //   1181	1207	1207	java/lang/Throwable
    //   1288	1303	1303	java/lang/Throwable
    //   2485	2510	2513	java/lang/Throwable
    //   5838	5863	5863	java/lang/Throwable
    //   6826	6852	6852	java/lang/Throwable
    //   7044	7059	7059	java/lang/Throwable
    //   8061	8087	8087	java/lang/Throwable
    //   8168	8183	8183	java/lang/Throwable
    //   9365	9390	9393	java/lang/Throwable
    //   9458	9472	9472	java/lang/Throwable
    //   9483	9496	9499	java/lang/Throwable
    //   9488	9511	9514	java/lang/Throwable
    //   9503	9529	9532	java/lang/Throwable
    //   9518	9559	9562	java/lang/Throwable
    //   9622	9649	9652	java/lang/Throwable
    //   9639	9667	9670	java/lang/Throwable
    //   9656	9703	9706	java/lang/Throwable
    //   9674	9717	9720	java/lang/Throwable
    //   9766	9780	9780	java/lang/Throwable
    //   9791	9804	9807	java/lang/Throwable
    //   9796	9819	9822	java/lang/Throwable
    //   9811	9837	9840	java/lang/Throwable
    //   9826	9867	9870	java/lang/Throwable
    //   9930	9957	9960	java/lang/Throwable
    //   9947	9978	9981	java/lang/Throwable
    //   9964	10008	10011	java/lang/Throwable
    //   9985	10019	10019	java/lang/Throwable
    //   10030	10046	10049	java/lang/Throwable
    //   10053	10143	10146	java/lang/Throwable
    //   10098	10195	10198	java/lang/Throwable
    //   10150	10206	10206	java/lang/Throwable
  }
  
  static void Zn(Object paramObject) {
    Zty2.ZR = a(-2834, -10386);
    Zty2.Zl = new BigInteger(a(-2847, -11599));
    boolean bool = Zt2e.ZK();
    try {
      try {
        if (Zboa.Zq.charAt(Math.abs(((BigInteger)Ztfr.Zr).intValue() % 32)) > Zxjm.ZG.charAt(Math.abs(((BigInteger)Zk8g.Zb).intValue() % 32))) {
          try {
            Zly7.ZD(Class.forName(a(-2836, 15958)));
            if (bool)
              Zg8.ZV(Class.forName(a(-2839, 28872))); 
          } catch (Throwable throwable) {
            throw a(null);
          } 
          return;
        } 
      } catch (Throwable throwable) {
        throw a(null);
      } 
      Zg8.ZV(Class.forName(a(-2839, 28872)));
    } catch (Throwable throwable) {}
  }
  
  static {
    // Byte code:
    //   0: bipush #16
    //   2: anewarray java/lang/String
    //   5: astore #5
    //   7: iconst_0
    //   8: istore_3
    //   9: ldc '{SeXNl\\t\\f~%|)uI<c|B>am\\n]=7??\\tO4j\\r\\ti71G.Y+9XqJ.S9'\\tO\\tDc&\\t+B\\rRwC\\tP^f\\tz?) X`P;H,??\\tOc'
    //   11: dup
    //   12: astore_2
    //   13: invokevirtual length : ()I
    //   16: istore #4
    //   18: bipush #77
    //   20: istore_1
    //   21: iconst_m1
    //   22: istore_0
    //   23: iconst_1
    //   24: iinc #0, 1
    //   27: aload_2
    //   28: iload_0
    //   29: dup
    //   30: iload_1
    //   31: iadd
    //   32: invokevirtual substring : (II)Ljava/lang/String;
    //   35: iconst_m1
    //   36: goto -> 142
    //   39: aload #5
    //   41: swap
    //   42: iload_3
    //   43: iinc #3, 1
    //   46: swap
    //   47: aastore
    //   48: iload_0
    //   49: iload_1
    //   50: iadd
    //   51: dup
    //   52: istore_0
    //   53: iload #4
    //   55: if_icmpge -> 67
    //   58: aload_2
    //   59: iload_0
    //   60: invokevirtual charAt : (I)C
    //   63: istore_1
    //   64: goto -> 23
    //   67: ldc 'y A"7B|J3I4 =fN\\bmUt&U< ,XY\ hM-\'
    //   69: dup
    //   70: astore_2
    //   71: invokevirtual length : ()I
    //   74: istore #4
    //   76: bipush #32
    //   78: istore_1
    //   79: iconst_m1
    //   80: istore_0
    //   81: bipush #88
    //   83: iinc #0, 1
    //   86: aload_2
    //   87: iload_0
    //   88: dup
    //   89: iload_1
    //   90: iadd
    //   91: invokevirtual substring : (II)Ljava/lang/String;
    //   94: iconst_0
    //   95: goto -> 142
    //   98: aload #5
    //   100: swap
    //   101: iload_3
    //   102: iinc #3, 1
    //   105: swap
    //   106: aastore
    //   107: iload_0
    //   108: iload_1
    //   109: iadd
    //   110: dup
    //   111: istore_0
    //   112: iload #4
    //   114: if_icmpge -> 126
    //   117: aload_2
    //   118: iload_0
    //   119: invokevirtual charAt : (I)C
    //   122: istore_1
    //   123: goto -> 81
    //   126: aload #5
    //   128: putstatic burp/Zl4v.a : [Ljava/lang/String;
    //   131: bipush #16
    //   133: anewarray java/lang/String
    //   136: putstatic burp/Zl4v.b : [Ljava/lang/String;
    //   139: goto -> 300
    //   142: dup_x2
    //   143: pop
    //   144: invokevirtual toCharArray : ()[C
    //   147: dup_x1
    //   148: arraylength
    //   149: dup_x2
    //   150: pop
    //   151: iconst_0
    //   152: istore #6
    //   154: dup2_x1
    //   155: pop2
    //   156: dup_x2
    //   157: iconst_1
    //   158: if_icmpgt -> 260
    //   161: dup2
    //   162: swap
    //   163: iload #6
    //   165: dup2_x1
    //   166: caload
    //   167: swap
    //   168: iload #6
    //   170: bipush #7
    //   172: irem
    //   173: tableswitch default -> 242, 0 -> 212, 1 -> 217, 2 -> 222, 3 -> 227, 4 -> 232, 5 -> 237
    //   212: bipush #27
    //   214: goto -> 244
    //   217: bipush #16
    //   219: goto -> 244
    //   222: bipush #112
    //   224: goto -> 244
    //   227: bipush #57
    //   229: goto -> 244
    //   232: bipush #81
    //   234: goto -> 244
    //   237: bipush #56
    //   239: goto -> 244
    //   242: bipush #90
    //   244: ixor
    //   245: ixor
    //   246: i2c
    //   247: castore
    //   248: iinc #6, 1
    //   251: dup
    //   252: ifne -> 260
    //   255: dup2
    //   256: dup_x1
    //   257: goto -> 165
    //   260: dup2_x1
    //   261: pop2
    //   262: dup_x2
    //   263: iload #6
    //   265: if_icmpgt -> 161
    //   268: pop
    //   269: new java/lang/String
    //   272: dup_x1
    //   273: swap
    //   274: invokespecial <init> : ([C)V
    //   277: invokevirtual intern : ()Ljava/lang/String;
    //   280: swap
    //   281: pop
    //   282: swap
    //   283: tableswitch default -> 39, 0 -> 98
    //   300: new java/math/BigInteger
    //   303: dup
    //   304: iconst_1
    //   305: bipush #32
    //   307: newarray byte
    //   309: dup
    //   310: iconst_0
    //   311: bipush #102
    //   313: bastore
    //   314: dup
    //   315: iconst_1
    //   316: bipush #-44
    //   318: bastore
    //   319: dup
    //   320: iconst_2
    //   321: bipush #-46
    //   323: bastore
    //   324: dup
    //   325: iconst_3
    //   326: bipush #-32
    //   328: bastore
    //   329: dup
    //   330: iconst_4
    //   331: bipush #-52
    //   333: bastore
    //   334: dup
    //   335: iconst_5
    //   336: bipush #-14
    //   338: bastore
    //   339: dup
    //   340: bipush #6
    //   342: bipush #125
    //   344: bastore
    //   345: dup
    //   346: bipush #7
    //   348: bipush #65
    //   350: bastore
    //   351: dup
    //   352: bipush #8
    //   354: bipush #-104
    //   356: bastore
    //   357: dup
    //   358: bipush #9
    //   360: bipush #-4
    //   362: bastore
    //   363: dup
    //   364: bipush #10
    //   366: bipush #18
    //   368: bastore
    //   369: dup
    //   370: bipush #11
    //   372: bipush #-28
    //   374: bastore
    //   375: dup
    //   376: bipush #12
    //   378: bipush #64
    //   380: bastore
    //   381: dup
    //   382: bipush #13
    //   384: bipush #-107
    //   386: bastore
    //   387: dup
    //   388: bipush #14
    //   390: bipush #74
    //   392: bastore
    //   393: dup
    //   394: bipush #15
    //   396: bipush #67
    //   398: bastore
    //   399: dup
    //   400: bipush #16
    //   402: bipush #-122
    //   404: bastore
    //   405: dup
    //   406: bipush #17
    //   408: bipush #-35
    //   410: bastore
    //   411: dup
    //   412: bipush #18
    //   414: bipush #-22
    //   416: bastore
    //   417: dup
    //   418: bipush #19
    //   420: bipush #-110
    //   422: bastore
    //   423: dup
    //   424: bipush #20
    //   426: bipush #86
    //   428: bastore
    //   429: dup
    //   430: bipush #21
    //   432: bipush #-61
    //   434: bastore
    //   435: dup
    //   436: bipush #22
    //   438: bipush #-49
    //   440: bastore
    //   441: dup
    //   442: bipush #23
    //   444: bipush #37
    //   446: bastore
    //   447: dup
    //   448: bipush #24
    //   450: bipush #26
    //   452: bastore
    //   453: dup
    //   454: bipush #25
    //   456: bipush #-128
    //   458: bastore
    //   459: dup
    //   460: bipush #26
    //   462: bipush #-119
    //   464: bastore
    //   465: dup
    //   466: bipush #27
    //   468: bipush #103
    //   470: bastore
    //   471: dup
    //   472: bipush #28
    //   474: bipush #-40
    //   476: bastore
    //   477: dup
    //   478: bipush #29
    //   480: bipush #60
    //   482: bastore
    //   483: dup
    //   484: bipush #30
    //   486: iconst_0
    //   487: bastore
    //   488: dup
    //   489: bipush #31
    //   491: bipush #-36
    //   493: bastore
    //   494: invokespecial <init> : (I[B)V
    //   497: putstatic burp/Zl4v.ZT : Ljava/lang/Object;
    //   500: sipush #-2833
    //   503: sipush #22372
    //   506: invokestatic a : (II)Ljava/lang/String;
    //   509: putstatic burp/Zl4v.ZD : Ljava/lang/String;
    //   512: return
  }
  
  private static Throwable a(Throwable paramThrowable) {
    return paramThrowable;
  }
  
  private static String a(int paramInt1, int paramInt2) {
    int i = (paramInt1 ^ 0xFFFFF4E1) & 0xFFFF;
    if (b[i] == null) {
      char[] arrayOfChar = a[i].toCharArray();
      switch (arrayOfChar[0] & 0xFF) {
        case 0:
        
        case 1:
        
        case 2:
        
        case 3:
        
        case 4:
        
        case 5:
        
        case 6:
        
        case 7:
        
        case 8:
        
        case 9:
        
        case 10:
        
        case 11:
        
        case 12:
        
        case 13:
        
        case 14:
        
        case 15:
        
        case 16:
        
        case 17:
        
        case 18:
        
        case 19:
        
        case 20:
        
        case 21:
        
        case 22:
        
        case 23:
        
        case 24:
        
        case 25:
        
        case 26:
        
        case 27:
        
        case 28:
        
        case 29:
        
        case 30:
        
        case 31:
        
        case 32:
        
        case 33:
        
        case 34:
        
        case 35:
        
        case 36:
        
        case 37:
        
        case 38:
        
        case 39:
        
        case 40:
        
        case 41:
        
        case 42:
        
        case 43:
        
        case 44:
        
        case 45:
        
        case 46:
        
        case 47:
        
        case 48:
        
        case 49:
        
        case 50:
        
        case 51:
        
        case 52:
        
        case 53:
        
        case 54:
        
        case 55:
        
        case 56:
        
        case 57:
        
        case 58:
        
        case 59:
        
        case 60:
        
        case 61:
        
        case 62:
        
        case 63:
        
        case 64:
        
        case 65:
        
        case 66:
        
        case 67:
        
        case 68:
        
        case 69:
        
        case 70:
        
        case 71:
        
        case 72:
        
        case 73:
        
        case 74:
        
        case 75:
        
        case 76:
        
        case 77:
        
        case 78:
        
        case 79:
        
        case 80:
        
        case 81:
        
        case 82:
        
        case 83:
        
        case 84:
        
        case 85:
        
        case 86:
        
        case 87:
        
        case 88:
        
        case 89:
        
        case 90:
        
        case 91:
        
        case 92:
        
        case 93:
        
        case 94:
        
        case 95:
        
        case 96:
        
        case 97:
        
        case 98:
        
        case 99:
        
        case 100:
        
        case 101:
        
        case 102:
        
        case 103:
        
        case 104:
        
        case 105:
        
        case 106:
        
        case 107:
        
        case 108:
        
        case 109:
        
        case 110:
        
        case 111:
        
        case 112:
        
        case 113:
        
        case 114:
        
        case 115:
        
        case 116:
        
        case 117:
        
        case 118:
        
        case 119:
        
        case 120:
        
        case 121:
        
        case 122:
        
        case 123:
        
        case 124:
        
        case 125:
        
        case 126:
        
        case 127:
        
        case 128:
        
        case 129:
        
        case 130:
        
        case 131:
        
        case 132:
        
        case 133:
        
        case 134:
        
        case 135:
        
        case 136:
        
        case 137:
        
        case 138:
        
        case 139:
        
        case 140:
        
        case 141:
        
        case 142:
        
        case 143:
        
        case 144:
        
        case 145:
        
        case 146:
        
        case 147:
        
        case 148:
        
        case 149:
        
        case 150:
        
        case 151:
        
        case 152:
        
        case 153:
        
        case 154:
        
        case 155:
        
        case 156:
        
        case 157:
        
        case 158:
        
        case 159:
        
        case 160:
        
        case 161:
        
        case 162:
        
        case 163:
        
        case 164:
        
        case 165:
        
        case 166:
        
        case 167:
        
        case 168:
        
        case 169:
        
        case 170:
        
        case 171:
        
        case 172:
        
        case 173:
        
        case 174:
        
        case 175:
        
        case 176:
        
        case 177:
        
        case 178:
        
        case 179:
        
        case 180:
        
        case 181:
        
        case 182:
        
        case 183:
        
        case 184:
        
        case 185:
        
        case 186:
        
        case 187:
        
        case 188:
        
        case 189:
        
        case 190:
        
        case 191:
        
        case 192:
        
        case 193:
        
        case 194:
        
        case 195:
        
        case 196:
        
        case 197:
        
        case 198:
        
        case 199:
        
        case 200:
        
        case 201:
        
        case 202:
        
        case 203:
        
        case 204:
        
        case 205:
        
        case 206:
        
        case 207:
        
        case 208:
        
        case 209:
        
        case 210:
        
        case 211:
        
        case 212:
        
        case 213:
        
        case 214:
        
        case 215:
        
        case 216:
        
        case 217:
        
        case 218:
        
        case 219:
        
        case 220:
        
        case 221:
        
        case 222:
        
        case 223:
        
        case 224:
        
        case 225:
        
        case 226:
        
        case 227:
        
        case 228:
        
        case 229:
        
        case 230:
        
        case 231:
        
        case 232:
        
        case 233:
        
        case 234:
        
        case 235:
        
        case 236:
        
        case 237:
        
        case 238:
        
        case 239:
        
        case 240:
        
        case 241:
        
        case 242:
        
        case 243:
        
        case 244:
        
        case 245:
        
        case 246:
        
        case 247:
        
        case 248:
        
        case 249:
        
        case 250:
        
        case 251:
        
        case 252:
        
        case 253:
        
        case 254:
        
        default:
          break;
      } 
      char c = '';
      int j = (paramInt2 & 0xFF) - c;
      if (j < 0)
        j += 256; 
      int k = ((paramInt2 & 0xFFFF) >>> 8) - c;
      if (k < 0)
        k += 256; 
      for (byte b = 0; b < arrayOfChar.length; b++) {
        int m = b % 2;
        if (m == 0) {
          arrayOfChar[b] = (char)(arrayOfChar[b] ^ j);
          j = ((j >>> 3 | j << 5) ^ arrayOfChar[b]) & 0xFF;
        } else {
          arrayOfChar[b] = (char)(arrayOfChar[b] ^ k);
          k = ((k >>> 3 | k << 5) ^ arrayOfChar[b]) & 0xFF;
        } 
      } 
      b[i] = (new String(arrayOfChar)).intern();
    } 
    return b[i];
  }
}


/* Location:              C:\Program Files\BurpSuitePro\burpsuite_pro.jar!\burp\Zl4v.class
 * Java compiler version: 21 (65.0)
 * JD-Core Version:       1.1.3
 */