package burp;

import java.awt.BorderLayout;
import java.awt.Component;
import java.awt.GridBagConstraints;
import java.awt.GridBagLayout;
import java.awt.Insets;
import java.awt.Window;
import java.awt.event.ActionEvent;
import java.awt.event.WindowEvent;
import java.io.BufferedOutputStream;
import java.io.File;
import java.io.FileNotFoundException;
import java.io.FileOutputStream;
import java.io.IOException;
import java.util.List;
import java.util.concurrent.ThreadPoolExecutor;
import javax.swing.BorderFactory;
import javax.swing.BoxLayout;
import net.portswigger.Zah;
import net.portswigger.Zdo;
import net.portswigger.Zk_;
import net.portswigger.Zkb;

public class Zl4x extends Zl04 implements Zggn, Ztg9 {
  private final Zt4u ZX;
  
  private Zx_j Zr;
  
  private final Zb0h Zu;
  
  private final Ztwv Zrr;
  
  private Zbkh Z_;
  
  private boolean ZrK;
  
  private boolean ZA;
  
  private boolean Zrk;
  
  private Zgo2 ZV;
  
  private final List<byte[]> Zrw;
  
  private int ZE;
  
  private boolean Zd;
  
  private byte[][] Zy;
  
  private final Zqe ZM;
  
  private final ThreadPoolExecutor ZrI;
  
  private Zbup ZH;
  
  private Ze01 Zg;
  
  private Zbqc Zh;
  
  private Zbqc ZrB;
  
  private Zbqc ZY;
  
  private Zbqc ZrT;
  
  private Zbqc Zl;
  
  private Zbqc ZN;
  
  private Zbqc Zx;
  
  private Zbqc ZI;
  
  private Zbqc Zw;
  
  private Zbqc ZS;
  
  private Zbqc ZF;
  
  private Zbqc Zro;
  
  private Zbqc ZZ;
  
  private Zbqc Zn;
  
  private Zbqc ZU;
  
  private Zbqc ZQ;
  
  private Zbqc Zru;
  
  private Zbqc ZP;
  
  private Zbqc ZB;
  
  private Zbqc Zs;
  
  private Zbqc Zo;
  
  private Zbqc Zc;
  
  private Zbqc ZO;
  
  private Zbqc Zi;
  
  private Zbqc ZrS;
  
  private Zbqc ZG;
  
  private Zbqc ZT;
  
  private Zbqc Ze;
  
  private Zbqc Zb;
  
  private Zbqc ZR;
  
  private Zbqc ZrL;
  
  private Zbup Zre;
  
  private Zbup Zk;
  
  private Zbup ZrE;
  
  private Zbup Zrf;
  
  private Zbup Zv;
  
  private Zbup ZK;
  
  private Zbup ZrP;
  
  private Zbup ZL;
  
  private Zbup ZJ;
  
  private Zbup Za;
  
  private Zbup Zm;
  
  private Zbup Zq;
  
  private Zbup Zt;
  
  private Zbup Zz;
  
  private Zxer ZW;
  
  private Zxer Zr3;
  
  private Zxer ZC;
  
  private static int Zf;
  
  private static final String[] a;
  
  private static final String[] b;
  
  public Zl4x(Zt4u paramZt4u, Window paramWindow, String paramString, Zx_j paramZx_j, List<byte[]> paramList, Zb0h paramZb0h, Ztwv paramZtwv, Zr_4 paramZr_4, Zr1m paramZr1m) {
    // Byte code:
    //   0: aload_0
    //   1: invokespecial <init> : ()V
    //   4: aload_0
    //   5: aload_1
    //   6: putfield ZX : Lburp/Zt4u;
    //   9: aload_0
    //   10: aload #4
    //   12: putfield Zr : Lburp/Zx_j;
    //   15: invokestatic Zt : ()I
    //   18: aload_0
    //   19: aload #6
    //   21: putfield Zu : Lburp/Zb0h;
    //   24: istore #10
    //   26: aload_0
    //   27: aload #7
    //   29: putfield Zrr : Lburp/Ztwv;
    //   32: aload #8
    //   34: new burp/Zgiz
    //   37: dup
    //   38: invokespecial <init> : ()V
    //   41: invokeinterface ZH : (Lburp/Zsqx;)Lburp/Zgpi;
    //   46: checkcast burp/Zs0f
    //   49: astore #11
    //   51: aload_0
    //   52: new burp/Zxa_
    //   55: dup
    //   56: aload #11
    //   58: invokespecial <init> : (Lburp/Zs0f;)V
    //   61: putfield ZM : Lburp/Zqe;
    //   64: aload_0
    //   65: new java/util/concurrent/ThreadPoolExecutor
    //   68: dup
    //   69: iconst_1
    //   70: iconst_1
    //   71: lconst_0
    //   72: getstatic java/util/concurrent/TimeUnit.MILLISECONDS : Ljava/util/concurrent/TimeUnit;
    //   75: new burp/Zk81
    //   78: dup
    //   79: invokespecial <init> : ()V
    //   82: invokespecial <init> : (IIJLjava/util/concurrent/TimeUnit;Ljava/util/concurrent/BlockingQueue;)V
    //   85: putfield ZrI : Ljava/util/concurrent/ThreadPoolExecutor;
    //   88: aload #5
    //   90: ifnonnull -> 98
    //   93: aload_0
    //   94: iconst_1
    //   95: putfield ZrK : Z
    //   98: aload_0
    //   99: invokevirtual ZW : ()V
    //   102: aload_0
    //   103: getfield ZC : Lburp/Zxer;
    //   106: invokevirtual ZO : ()Ljavax/swing/JComponent;
    //   109: bipush #120
    //   111: bipush #40
    //   113: invokestatic Zf : (Ljava/awt/Component;II)V
    //   116: aload_0
    //   117: getfield Zr3 : Lburp/Zxer;
    //   120: invokevirtual ZO : ()Ljavax/swing/JComponent;
    //   123: bipush #100
    //   125: bipush #25
    //   127: invokestatic Zf : (Ljava/awt/Component;II)V
    //   130: aload_0
    //   131: aload_3
    //   132: sipush #-13939
    //   135: sipush #-8410
    //   138: invokestatic a : (II)Ljava/lang/String;
    //   141: swap
    //   142: <illegal opcode> makeConcatWithConstants : (Ljava/lang/String;Ljava/lang/String;)Ljava/lang/String;
    //   147: invokevirtual setTitle : (Ljava/lang/String;)V
    //   150: aload_0
    //   151: getfield ZM : Lburp/Zqe;
    //   154: aload #4
    //   156: invokeinterface Zb : (Lburp/Zx_j;)V
    //   161: aload_0
    //   162: getfield ZQ : Lburp/Zbqc;
    //   165: aload_0
    //   166: aload #9
    //   168: invokevirtual Zs : (Lburp/Zr1m;)Lburp/Zbqc;
    //   171: sipush #-13940
    //   174: sipush #-8835
    //   177: invokestatic a : (II)Ljava/lang/String;
    //   180: invokevirtual add : (Ljava/awt/Component;Ljava/lang/Object;)V
    //   183: aload_0
    //   184: getfield ZrK : Z
    //   187: ifeq -> 250
    //   190: aload_0
    //   191: new java/util/ArrayList
    //   194: dup
    //   195: invokespecial <init> : ()V
    //   198: putfield Zrw : Ljava/util/List;
    //   201: aload_0
    //   202: new burp/Zgo2
    //   205: dup
    //   206: aload_0
    //   207: invokespecial <init> : (Lburp/Zl4x;)V
    //   210: putfield ZV : Lburp/Zgo2;
    //   213: aload_0
    //   214: aload_0
    //   215: getfield ZV : Lburp/Zgo2;
    //   218: sipush #-13861
    //   221: sipush #21840
    //   224: invokestatic a : (II)Ljava/lang/String;
    //   227: invokevirtual add : (Ljava/awt/Component;Ljava/lang/Object;)V
    //   230: aload_0
    //   231: getfield ZC : Lburp/Zxer;
    //   234: iconst_0
    //   235: invokevirtual setEnabled : (Z)V
    //   238: iload #10
    //   240: ifeq -> 282
    //   243: iconst_1
    //   244: anewarray burp/Zbqc
    //   247: invokestatic Zr : ([Lburp/Zbqc;)V
    //   250: aload_0
    //   251: aconst_null
    //   252: putfield Zrw : Ljava/util/List;
    //   255: aload_0
    //   256: aload #5
    //   258: invokevirtual ZJ : (Ljava/util/List;)[[B
    //   261: astore #12
    //   263: aload_0
    //   264: aload #12
    //   266: invokevirtual ZP : ([[B)V
    //   269: aload_0
    //   270: aload #12
    //   272: aload_0
    //   273: getfield Zr : Lburp/Zx_j;
    //   276: invokevirtual ZL : ()Lburp/Zx_j;
    //   279: invokevirtual ZU : ([[BLburp/Zx_j;)V
    //   282: aload_0
    //   283: invokevirtual pack : ()V
    //   286: aload_0
    //   287: aload_2
    //   288: invokevirtual ZO : (Ljava/awt/Window;)V
    //   291: return
  }
  
  private Zbqc Zs(Zr1m paramZr1m) {
    Zbaz zbaz = new Zbaz(this.ZM, paramZr1m, this);
    Zba6 zba6 = new Zba6(this.ZM, paramZr1m, this);
    GridBagLayout gridBagLayout = new GridBagLayout();
    gridBagLayout.columnWidths = new int[] { 0, 5, 0 };
    gridBagLayout.rowHeights = new int[] { 
        0, 5, 0, 5, 0, 5, 0, 5, 0, 5, 
        0, 5, 0 };
    Zbqc zbqc = new Zbqc(gridBagLayout);
    zbqc.setBorder(BorderFactory.createEmptyBorder(20, 20, 20, 20));
    int i = 0;
    i = ZF(zbqc, zbaz, i);
    GridBagConstraints gridBagConstraints = new GridBagConstraints();
    gridBagConstraints.gridx = 0;
    gridBagConstraints.gridy = i;
    gridBagConstraints.anchor = 23;
    gridBagConstraints.gridwidth = 3;
    gridBagConstraints.fill = 2;
    gridBagConstraints.insets = new Insets(10, 0, 15, 0);
    zbqc.add(new Zem9(0), gridBagConstraints);
    ZF(zbqc, zba6, i + 2);
    return zbqc;
  }
  
  private int ZF(Zbqc paramZbqc, Zt3u paramZt3u, int paramInt) {
    GridBagConstraints gridBagConstraints = new GridBagConstraints();
    gridBagConstraints.gridx = 0;
    gridBagConstraints.gridy = paramInt;
    gridBagConstraints.anchor = 23;
    gridBagConstraints.gridheight = 5;
    gridBagConstraints.insets = new Insets(0, 0, 0, 5);
    paramZbqc.add(paramZt3u.ZjY(), gridBagConstraints);
    gridBagConstraints = new GridBagConstraints();
    gridBagConstraints.gridx = 2;
    gridBagConstraints.gridy = paramInt;
    gridBagConstraints.anchor = 21;
    gridBagConstraints.fill = 2;
    paramZbqc.add(new Zbkc(paramZt3u.Zjd()), gridBagConstraints);
    gridBagConstraints = new GridBagConstraints();
    gridBagConstraints.gridx = 2;
    paramInt += 2;
    gridBagConstraints.gridy = paramInt;
    gridBagConstraints.anchor = 23;
    gridBagConstraints.weightx = 1.0D;
    gridBagConstraints.fill = 1;
    paramZbqc.add(new Zl8w(paramZt3u.ZjS()), gridBagConstraints);
    gridBagConstraints = new GridBagConstraints();
    gridBagConstraints.gridx = 2;
    paramInt += 2;
    gridBagConstraints.gridy = paramInt;
    gridBagConstraints.anchor = 23;
    gridBagConstraints.fill = 1;
    paramZbqc.add(paramZt3u.Zz(), gridBagConstraints);
    return paramInt + 2;
  }
  
  void ZP(byte[][] paramArrayOfbyte) {
    this.Zy = paramArrayOfbyte;
  }
  
  private byte[][] ZJ(List<byte[]> paramList) {
    int i = Zt();
    if (paramList == null)
      return new byte[0][]; 
    int j = Math.min(paramList.size(), 20000);
    byte[][] arrayOfByte = new byte[j][];
    byte b = 0;
    while (b < j) {
      arrayOfByte[b] = paramList.get(b);
      b++;
      if (i != 0)
        break; 
    } 
    return arrayOfByte;
  }
  
  private void ZU(byte[][] paramArrayOfbyte, Zx_j paramZx_j) {
    // Byte code:
    //   0: aload_0
    //   1: getfield Zrr : Lburp/Ztwv;
    //   4: aload_0
    //   5: aload_1
    //   6: aload_2
    //   7: <illegal opcode> run : (Lburp/Zl4x;[[BLburp/Zx_j;)Ljava/lang/Runnable;
    //   12: invokeinterface Zx : (Ljava/lang/Runnable;)Ljava/util/concurrent/Future;
    //   17: pop
    //   18: return
  }
  
  private void ZV(byte[][] paramArrayOfbyte, Zx_j paramZx_j) {
    // Byte code:
    //   0: aload_0
    //   1: getfield Zrk : Z
    //   4: ifne -> 15
    //   7: aload_1
    //   8: arraylength
    //   9: sipush #20000
    //   12: if_icmplt -> 19
    //   15: iconst_1
    //   16: goto -> 20
    //   19: iconst_0
    //   20: istore_3
    //   21: aload_0
    //   22: getfield ZrI : Ljava/util/concurrent/ThreadPoolExecutor;
    //   25: aload_0
    //   26: aload_1
    //   27: aload_2
    //   28: iload_3
    //   29: <illegal opcode> run : (Lburp/Zl4x;[[BLburp/Zx_j;Z)Ljava/lang/Runnable;
    //   34: invokevirtual execute : (Ljava/lang/Runnable;)V
    //   37: return
  }
  
  private void Zi(byte[][] paramArrayOfbyte, Zx_j paramZx_j, boolean paramBoolean) {
    // Byte code:
    //   0: aload_0
    //   1: getfield Z_ : Lburp/Zbkh;
    //   4: ifnull -> 15
    //   7: aload_0
    //   8: aload_0
    //   9: getfield Z_ : Lburp/Zbkh;
    //   12: invokevirtual remove : (Ljava/awt/Component;)V
    //   15: aload_0
    //   16: new burp/Zbkh
    //   19: dup
    //   20: aconst_null
    //   21: iconst_1
    //   22: invokespecial <init> : (Ljava/awt/Window;Z)V
    //   25: putfield Z_ : Lburp/Zbkh;
    //   28: aload_0
    //   29: getfield Zru : Lburp/Zbqc;
    //   32: aload_0
    //   33: getfield Z_ : Lburp/Zbkh;
    //   36: sipush #-13861
    //   39: sipush #21840
    //   42: invokestatic a : (II)Ljava/lang/String;
    //   45: invokevirtual add : (Ljava/awt/Component;Ljava/lang/Object;)V
    //   48: aload_0
    //   49: invokevirtual validate : ()V
    //   52: new burp/Zt3j
    //   55: dup
    //   56: aload_1
    //   57: aload_2
    //   58: aload_0
    //   59: getfield Z_ : Lburp/Zbkh;
    //   62: invokespecial <init> : ([[BLburp/Zx_j;Lburp/Zlc8;)V
    //   65: astore #4
    //   67: aload #4
    //   69: invokevirtual Zk : ()V
    //   72: aload_0
    //   73: aload #4
    //   75: aload_2
    //   76: <illegal opcode> run : (Lburp/Zl4x;Lburp/Zt3j;Lburp/Zx_j;)Ljava/lang/Runnable;
    //   81: invokestatic invokeLater : (Ljava/lang/Runnable;)V
    //   84: iload_3
    //   85: ifeq -> 99
    //   88: aload_0
    //   89: getfield Zru : Lburp/Zbqc;
    //   92: aload_0
    //   93: getfield Z_ : Lburp/Zbkh;
    //   96: invokevirtual remove : (Ljava/awt/Component;)V
    //   99: aload_0
    //   100: getfield ZC : Lburp/Zxer;
    //   103: iconst_1
    //   104: invokevirtual setEnabled : (Z)V
    //   107: aload_0
    //   108: invokevirtual validate : ()V
    //   111: return
  }
  
  private void Z_(Zgt3 paramZgt3, Zx_j paramZx_j) {
    // Byte code:
    //   0: new java/util/ArrayList
    //   3: dup
    //   4: invokespecial <init> : ()V
    //   7: astore #4
    //   9: aload #4
    //   11: sipush #-13837
    //   14: sipush #-20656
    //   17: invokestatic a : (II)Ljava/lang/String;
    //   20: invokeinterface add : (Ljava/lang/Object;)Z
    //   25: pop
    //   26: aload #4
    //   28: sipush #-13829
    //   31: sipush #-4823
    //   34: invokestatic a : (II)Ljava/lang/String;
    //   37: invokeinterface add : (Ljava/lang/Object;)Z
    //   42: pop
    //   43: aload #4
    //   45: sipush #-13862
    //   48: sipush #-21827
    //   51: invokestatic a : (II)Ljava/lang/String;
    //   54: invokeinterface add : (Ljava/lang/Object;)Z
    //   59: pop
    //   60: invokestatic Zt : ()I
    //   63: aload #4
    //   65: sipush #-13949
    //   68: sipush #19521
    //   71: invokestatic a : (II)Ljava/lang/String;
    //   74: invokeinterface add : (Ljava/lang/Object;)Z
    //   79: pop
    //   80: istore_3
    //   81: aload #4
    //   83: sipush #-13924
    //   86: sipush #-9109
    //   89: invokestatic a : (II)Ljava/lang/String;
    //   92: invokeinterface add : (Ljava/lang/Object;)Z
    //   97: pop
    //   98: aload_0
    //   99: getfield ZrL : Lburp/Zbqc;
    //   102: invokevirtual removeAll : ()V
    //   105: aload_1
    //   106: getfield Zm : [D
    //   109: iconst_3
    //   110: daload
    //   111: dstore #6
    //   113: dload #6
    //   115: ldc2_w 16.0
    //   118: dcmpg
    //   119: ifge -> 137
    //   122: sipush #-13879
    //   125: sipush #-6817
    //   128: invokestatic a : (II)Ljava/lang/String;
    //   131: astore #8
    //   133: iload_3
    //   134: ifeq -> 268
    //   137: dload #6
    //   139: ldc2_w 24.0
    //   142: dcmpg
    //   143: ifge -> 161
    //   146: sipush #-13950
    //   149: sipush #29575
    //   152: invokestatic a : (II)Ljava/lang/String;
    //   155: astore #8
    //   157: iload_3
    //   158: ifeq -> 268
    //   161: dload #6
    //   163: ldc2_w 32.0
    //   166: dcmpg
    //   167: ifge -> 185
    //   170: sipush #-13848
    //   173: sipush #17949
    //   176: invokestatic a : (II)Ljava/lang/String;
    //   179: astore #8
    //   181: iload_3
    //   182: ifeq -> 268
    //   185: dload #6
    //   187: ldc2_w 40.0
    //   190: dcmpg
    //   191: ifge -> 209
    //   194: sipush #-13840
    //   197: sipush #20357
    //   200: invokestatic a : (II)Ljava/lang/String;
    //   203: astore #8
    //   205: iload_3
    //   206: ifeq -> 268
    //   209: dload #6
    //   211: ldc2_w 60.0
    //   214: dcmpg
    //   215: ifge -> 233
    //   218: sipush #-13833
    //   221: sipush #21318
    //   224: invokestatic a : (II)Ljava/lang/String;
    //   227: astore #8
    //   229: iload_3
    //   230: ifeq -> 268
    //   233: dload #6
    //   235: ldc2_w 80.0
    //   238: dcmpg
    //   239: ifge -> 257
    //   242: sipush #-13922
    //   245: sipush #4930
    //   248: invokestatic a : (II)Ljava/lang/String;
    //   251: astore #8
    //   253: iload_3
    //   254: ifeq -> 268
    //   257: sipush #-13860
    //   260: sipush #-9224
    //   263: invokestatic a : (II)Ljava/lang/String;
    //   266: astore #8
    //   268: aload #8
    //   270: dload #6
    //   272: invokestatic round : (D)J
    //   275: lstore #18
    //   277: astore #20
    //   279: sipush #-13944
    //   282: sipush #-6353
    //   285: invokestatic a : (II)Ljava/lang/String;
    //   288: aload #20
    //   290: sipush #-13889
    //   293: sipush #20642
    //   296: invokestatic a : (II)Ljava/lang/String;
    //   299: lload #18
    //   301: sipush #-13884
    //   304: sipush #-11038
    //   307: invokestatic a : (II)Ljava/lang/String;
    //   310: <illegal opcode> makeConcatWithConstants : (Ljava/lang/String;Ljava/lang/String;Ljava/lang/String;JLjava/lang/String;)Ljava/lang/String;
    //   315: astore #9
    //   317: new burp/Zgoq
    //   320: dup
    //   321: sipush #-13858
    //   324: sipush #-22772
    //   327: invokestatic a : (II)Ljava/lang/String;
    //   330: aload #9
    //   332: iconst_0
    //   333: invokespecial <init> : (Ljava/lang/String;Ljava/lang/String;I)V
    //   336: astore #10
    //   338: aload_0
    //   339: getfield ZrL : Lburp/Zbqc;
    //   342: aload #10
    //   344: invokevirtual add : (Ljava/awt/Component;)Ljava/awt/Component;
    //   347: pop
    //   348: aload_0
    //   349: getfield Zr : Lburp/Zx_j;
    //   352: getfield Z_ : Z
    //   355: ifne -> 368
    //   358: aload_0
    //   359: getfield Zr : Lburp/Zx_j;
    //   362: getfield Zf : Z
    //   365: ifeq -> 466
    //   368: aload_2
    //   369: getfield Z_ : Z
    //   372: ifne -> 466
    //   375: aload_2
    //   376: getfield Zf : Z
    //   379: ifne -> 466
    //   382: new burp/Zl8w
    //   385: dup
    //   386: sipush #-13853
    //   389: sipush #-20438
    //   392: invokestatic a : (II)Ljava/lang/String;
    //   395: invokespecial <init> : (Ljava/lang/String;)V
    //   398: astore #11
    //   400: aload #11
    //   402: iconst_1
    //   403: invokevirtual Zl : (Z)V
    //   406: new burp/Zbqc
    //   409: dup
    //   410: new java/awt/BorderLayout
    //   413: dup
    //   414: invokespecial <init> : ()V
    //   417: invokespecial <init> : (Ljava/awt/LayoutManager;)V
    //   420: astore #12
    //   422: aload #12
    //   424: new javax/swing/border/EmptyBorder
    //   427: dup
    //   428: iconst_5
    //   429: bipush #15
    //   431: iconst_0
    //   432: bipush #15
    //   434: invokespecial <init> : (IIII)V
    //   437: invokevirtual setBorder : (Ljavax/swing/border/Border;)V
    //   440: aload #12
    //   442: aload #11
    //   444: sipush #-13940
    //   447: sipush #-8835
    //   450: invokestatic a : (II)Ljava/lang/String;
    //   453: invokevirtual add : (Ljava/awt/Component;Ljava/lang/Object;)V
    //   456: aload_0
    //   457: getfield ZrL : Lburp/Zbqc;
    //   460: aload #12
    //   462: invokevirtual add : (Ljava/awt/Component;)Ljava/awt/Component;
    //   465: pop
    //   466: new burp/Zz_u
    //   469: dup
    //   470: iconst_1
    //   471: aload_1
    //   472: getfield Zm : [D
    //   475: sipush #-13929
    //   478: sipush #25944
    //   481: invokestatic a : (II)Ljava/lang/String;
    //   484: sipush #-13923
    //   487: sipush #29520
    //   490: invokestatic a : (II)Ljava/lang/String;
    //   493: iconst_0
    //   494: aload #4
    //   496: invokespecial <init> : (Z[DLjava/lang/String;Ljava/lang/String;ZLjava/lang/Object;)V
    //   499: astore #11
    //   501: new burp/Zgou
    //   504: dup
    //   505: sipush #-13881
    //   508: sipush #-161
    //   511: invokestatic a : (II)Ljava/lang/String;
    //   514: sipush #-13946
    //   517: sipush #-10269
    //   520: invokestatic a : (II)Ljava/lang/String;
    //   523: aload #11
    //   525: invokevirtual ZT : ()Lburp/Zbcc;
    //   528: invokespecial <init> : (Ljava/lang/String;Ljava/lang/String;Lburp/Zbcc;)V
    //   531: astore #12
    //   533: aload_0
    //   534: getfield ZrL : Lburp/Zbqc;
    //   537: aload #12
    //   539: invokevirtual add : (Ljava/awt/Component;)Ljava/awt/Component;
    //   542: pop
    //   543: aload_1
    //   544: getfield ZU : I
    //   547: sipush #200
    //   550: if_icmpge -> 568
    //   553: sipush #-13900
    //   556: sipush #-2009
    //   559: invokestatic a : (II)Ljava/lang/String;
    //   562: astore #13
    //   564: iload_3
    //   565: ifeq -> 679
    //   568: aload_1
    //   569: getfield ZU : I
    //   572: sipush #1000
    //   575: if_icmpge -> 593
    //   578: sipush #-13863
    //   581: sipush #-17895
    //   584: invokestatic a : (II)Ljava/lang/String;
    //   587: astore #13
    //   589: iload_3
    //   590: ifeq -> 679
    //   593: aload_1
    //   594: getfield ZU : I
    //   597: sipush #5000
    //   600: if_icmpge -> 618
    //   603: sipush #-13838
    //   606: sipush #25442
    //   609: invokestatic a : (II)Ljava/lang/String;
    //   612: astore #13
    //   614: iload_3
    //   615: ifeq -> 679
    //   618: aload_1
    //   619: getfield ZU : I
    //   622: sipush #10000
    //   625: if_icmpge -> 643
    //   628: sipush #-13928
    //   631: sipush #-30994
    //   634: invokestatic a : (II)Ljava/lang/String;
    //   637: astore #13
    //   639: iload_3
    //   640: ifeq -> 679
    //   643: aload_1
    //   644: getfield ZU : I
    //   647: sipush #20000
    //   650: if_icmpge -> 668
    //   653: sipush #-13867
    //   656: sipush #-12749
    //   659: invokestatic a : (II)Ljava/lang/String;
    //   662: astore #13
    //   664: iload_3
    //   665: ifeq -> 679
    //   668: sipush #-13926
    //   671: sipush #18067
    //   674: invokestatic a : (II)Ljava/lang/String;
    //   677: astore #13
    //   679: aload_1
    //   680: getfield ZU : I
    //   683: aload #13
    //   685: sipush #-13893
    //   688: sipush #23205
    //   691: invokestatic a : (II)Ljava/lang/String;
    //   694: dup_x2
    //   695: pop
    //   696: sipush #-13843
    //   699: sipush #7927
    //   702: invokestatic a : (II)Ljava/lang/String;
    //   705: swap
    //   706: sipush #-13839
    //   709: sipush #30394
    //   712: invokestatic a : (II)Ljava/lang/String;
    //   715: <illegal opcode> makeConcatWithConstants : (Ljava/lang/String;ILjava/lang/String;Ljava/lang/String;Ljava/lang/String;)Ljava/lang/String;
    //   720: astore #14
    //   722: new burp/Zgoq
    //   725: dup
    //   726: sipush #-13883
    //   729: sipush #22402
    //   732: invokestatic a : (II)Ljava/lang/String;
    //   735: aload #14
    //   737: iconst_0
    //   738: invokespecial <init> : (Ljava/lang/String;Ljava/lang/String;I)V
    //   741: astore #15
    //   743: aload_0
    //   744: getfield ZrL : Lburp/Zbqc;
    //   747: aload #15
    //   749: invokevirtual add : (Ljava/awt/Component;)Ljava/awt/Component;
    //   752: pop
    //   753: new java/lang/StringBuilder
    //   756: dup
    //   757: invokespecial <init> : ()V
    //   760: astore #16
    //   762: aload #16
    //   764: sipush #-13932
    //   767: sipush #-5830
    //   770: invokestatic a : (II)Ljava/lang/String;
    //   773: invokevirtual append : (Ljava/lang/String;)Ljava/lang/StringBuilder;
    //   776: pop
    //   777: aload #16
    //   779: aload_1
    //   780: getfield ZU : I
    //   783: invokevirtual append : (I)Ljava/lang/StringBuilder;
    //   786: pop
    //   787: aload #16
    //   789: sipush #-13945
    //   792: sipush #-13628
    //   795: invokestatic a : (II)Ljava/lang/String;
    //   798: invokevirtual append : (Ljava/lang/String;)Ljava/lang/StringBuilder;
    //   801: pop
    //   802: aload_1
    //   803: getfield ZJ : I
    //   806: aload_1
    //   807: getfield ZZ : I
    //   810: if_icmpne -> 857
    //   813: aload #16
    //   815: sipush #-13849
    //   818: sipush #31573
    //   821: invokestatic a : (II)Ljava/lang/String;
    //   824: invokevirtual append : (Ljava/lang/String;)Ljava/lang/StringBuilder;
    //   827: pop
    //   828: aload #16
    //   830: aload_1
    //   831: getfield ZZ : I
    //   834: invokevirtual append : (I)Ljava/lang/StringBuilder;
    //   837: pop
    //   838: aload #16
    //   840: sipush #-13851
    //   843: sipush #-27787
    //   846: invokestatic a : (II)Ljava/lang/String;
    //   849: invokevirtual append : (Ljava/lang/String;)Ljava/lang/StringBuilder;
    //   852: pop
    //   853: iload_3
    //   854: ifeq -> 1003
    //   857: aload #16
    //   859: sipush #-13934
    //   862: sipush #-3979
    //   865: invokestatic a : (II)Ljava/lang/String;
    //   868: invokevirtual append : (Ljava/lang/String;)Ljava/lang/StringBuilder;
    //   871: pop
    //   872: aload #16
    //   874: aload_1
    //   875: getfield ZJ : I
    //   878: invokevirtual append : (I)Ljava/lang/StringBuilder;
    //   881: pop
    //   882: aload #16
    //   884: ldc '-'
    //   886: invokevirtual append : (Ljava/lang/String;)Ljava/lang/StringBuilder;
    //   889: pop
    //   890: aload #16
    //   892: aload_1
    //   893: getfield ZZ : I
    //   896: invokevirtual append : (I)Ljava/lang/StringBuilder;
    //   899: pop
    //   900: aload #16
    //   902: sipush #-13851
    //   905: sipush #-27787
    //   908: invokestatic a : (II)Ljava/lang/String;
    //   911: invokevirtual append : (Ljava/lang/String;)Ljava/lang/StringBuilder;
    //   914: pop
    //   915: aload #16
    //   917: aload_1
    //   918: getfield Zk : I
    //   921: invokevirtual append : (I)Ljava/lang/StringBuilder;
    //   924: pop
    //   925: aload #16
    //   927: sipush #-13897
    //   930: sipush #-8042
    //   933: invokestatic a : (II)Ljava/lang/String;
    //   936: invokevirtual append : (Ljava/lang/String;)Ljava/lang/StringBuilder;
    //   939: pop
    //   940: aload #16
    //   942: aload_2
    //   943: getfield Zb : B
    //   946: i2s
    //   947: invokestatic ZY : (S)Ljava/lang/String;
    //   950: invokevirtual append : (Ljava/lang/String;)Ljava/lang/StringBuilder;
    //   953: pop
    //   954: aload #16
    //   956: sipush #-13898
    //   959: sipush #6428
    //   962: invokestatic a : (II)Ljava/lang/String;
    //   965: invokevirtual append : (Ljava/lang/String;)Ljava/lang/StringBuilder;
    //   968: pop
    //   969: aload #16
    //   971: aload_2
    //   972: getfield Zm : Z
    //   975: ifeq -> 990
    //   978: sipush #-13847
    //   981: sipush #-26570
    //   984: invokestatic a : (II)Ljava/lang/String;
    //   987: goto -> 999
    //   990: sipush #-13936
    //   993: sipush #9342
    //   996: invokestatic a : (II)Ljava/lang/String;
    //   999: invokevirtual append : (Ljava/lang/String;)Ljava/lang/StringBuilder;
    //   1002: pop
    //   1003: aload_2
    //   1004: getfield Zr : Z
    //   1007: ifeq -> 1025
    //   1010: aload #16
    //   1012: sipush #-13895
    //   1015: sipush #-5904
    //   1018: invokestatic a : (II)Ljava/lang/String;
    //   1021: invokevirtual append : (Ljava/lang/String;)Ljava/lang/StringBuilder;
    //   1024: pop
    //   1025: new burp/Zgoq
    //   1028: dup
    //   1029: sipush #-13859
    //   1032: sipush #-14663
    //   1035: invokestatic a : (II)Ljava/lang/String;
    //   1038: aload #16
    //   1040: invokevirtual toString : ()Ljava/lang/String;
    //   1043: bipush #25
    //   1045: invokespecial <init> : (Ljava/lang/String;Ljava/lang/String;I)V
    //   1048: astore #17
    //   1050: aload_0
    //   1051: getfield ZrL : Lburp/Zbqc;
    //   1054: aload #17
    //   1056: invokevirtual add : (Ljava/awt/Component;)Ljava/awt/Component;
    //   1059: pop
    //   1060: aload_2
    //   1061: getfield Z_ : Z
    //   1064: ifne -> 1074
    //   1067: aload_2
    //   1068: getfield Zf : Z
    //   1071: ifeq -> 1078
    //   1074: iconst_1
    //   1075: goto -> 1079
    //   1078: iconst_0
    //   1079: istore #6
    //   1081: iconst_0
    //   1082: istore #5
    //   1084: aload_0
    //   1085: getfield Zi : Lburp/Zbqc;
    //   1088: invokevirtual removeAll : ()V
    //   1091: iload #6
    //   1093: ifeq -> 1237
    //   1096: new burp/Zs1i
    //   1099: dup
    //   1100: aload_1
    //   1101: getfield Zb : [D
    //   1104: sipush #-13845
    //   1107: sipush #9224
    //   1110: invokestatic a : (II)Ljava/lang/String;
    //   1113: invokespecial <init> : ([DLjava/lang/String;)V
    //   1116: astore #7
    //   1118: new burp/Zgou
    //   1121: dup
    //   1122: sipush #-13894
    //   1125: sipush #-29628
    //   1128: invokestatic a : (II)Ljava/lang/String;
    //   1131: sipush #-13885
    //   1134: sipush #-10347
    //   1137: invokestatic a : (II)Ljava/lang/String;
    //   1140: aload #7
    //   1142: invokevirtual Zy : ()Lburp/Zbcc;
    //   1145: invokespecial <init> : (Ljava/lang/String;Ljava/lang/String;Lburp/Zbcc;)V
    //   1148: astore #8
    //   1150: aload_0
    //   1151: getfield Zi : Lburp/Zbqc;
    //   1154: aload #8
    //   1156: invokevirtual add : (Ljava/awt/Component;)Ljava/awt/Component;
    //   1159: pop
    //   1160: new burp/Zz_u
    //   1163: dup
    //   1164: iconst_1
    //   1165: aload_1
    //   1166: getfield ZQ : [D
    //   1169: sipush #-13942
    //   1172: sipush #5212
    //   1175: invokestatic a : (II)Ljava/lang/String;
    //   1178: sipush #-13850
    //   1181: sipush #25302
    //   1184: invokestatic a : (II)Ljava/lang/String;
    //   1187: iconst_0
    //   1188: aload #4
    //   1190: invokespecial <init> : (Z[DLjava/lang/String;Ljava/lang/String;ZLjava/lang/Object;)V
    //   1193: astore #9
    //   1195: new burp/Zgou
    //   1198: dup
    //   1199: sipush #-13836
    //   1202: sipush #-10148
    //   1205: invokestatic a : (II)Ljava/lang/String;
    //   1208: sipush #-13825
    //   1211: sipush #4577
    //   1214: invokestatic a : (II)Ljava/lang/String;
    //   1217: aload #9
    //   1219: invokevirtual ZT : ()Lburp/Zbcc;
    //   1222: invokespecial <init> : (Ljava/lang/String;Ljava/lang/String;Lburp/Zbcc;)V
    //   1225: astore #10
    //   1227: aload_0
    //   1228: getfield Zi : Lburp/Zbqc;
    //   1231: aload #10
    //   1233: invokevirtual add : (Ljava/awt/Component;)Ljava/awt/Component;
    //   1236: pop
    //   1237: aload_0
    //   1238: getfield Zr3 : Lburp/Zxer;
    //   1241: iload #5
    //   1243: iinc #5, 1
    //   1246: iload #6
    //   1248: invokevirtual setEnabledAt : (IZ)V
    //   1251: aload_0
    //   1252: getfield Zc : Lburp/Zbqc;
    //   1255: invokevirtual removeAll : ()V
    //   1258: aload_2
    //   1259: getfield Z_ : Z
    //   1262: ifeq -> 1337
    //   1265: new burp/Zs1i
    //   1268: dup
    //   1269: aload_1
    //   1270: getfield Za : [D
    //   1273: sipush #-13887
    //   1276: sipush #1981
    //   1279: invokestatic a : (II)Ljava/lang/String;
    //   1282: invokespecial <init> : ([DLjava/lang/String;)V
    //   1285: astore #7
    //   1287: new burp/Zgoi
    //   1290: dup
    //   1291: sipush #-13874
    //   1294: sipush #5999
    //   1297: invokestatic a : (II)Ljava/lang/String;
    //   1300: aload #7
    //   1302: invokevirtual Zy : ()Lburp/Zbcc;
    //   1305: aload_1
    //   1306: getfield ZK : Ljava/util/List;
    //   1309: aload_1
    //   1310: getfield Zq : I
    //   1313: sipush #-13931
    //   1316: sipush #1118
    //   1319: invokestatic a : (II)Ljava/lang/String;
    //   1322: invokespecial <init> : (Ljava/lang/String;Lburp/Zbcc;Ljava/util/List;ILjava/lang/String;)V
    //   1325: astore #8
    //   1327: aload_0
    //   1328: getfield Zc : Lburp/Zbqc;
    //   1331: aload #8
    //   1333: invokevirtual add : (Ljava/awt/Component;)Ljava/awt/Component;
    //   1336: pop
    //   1337: aload_0
    //   1338: getfield Zr3 : Lburp/Zxer;
    //   1341: iload #5
    //   1343: iinc #5, 1
    //   1346: aload_2
    //   1347: getfield Z_ : Z
    //   1350: invokevirtual setEnabledAt : (IZ)V
    //   1353: aload_0
    //   1354: getfield ZrS : Lburp/Zbqc;
    //   1357: invokevirtual removeAll : ()V
    //   1360: aload_2
    //   1361: getfield Zf : Z
    //   1364: ifeq -> 1439
    //   1367: new burp/Zs1i
    //   1370: dup
    //   1371: aload_1
    //   1372: getfield ZF : [D
    //   1375: sipush #-13887
    //   1378: sipush #1981
    //   1381: invokestatic a : (II)Ljava/lang/String;
    //   1384: invokespecial <init> : ([DLjava/lang/String;)V
    //   1387: astore #7
    //   1389: new burp/Zgoi
    //   1392: dup
    //   1393: sipush #-13855
    //   1396: sipush #-5998
    //   1399: invokestatic a : (II)Ljava/lang/String;
    //   1402: aload #7
    //   1404: invokevirtual Zy : ()Lburp/Zbcc;
    //   1407: aload_1
    //   1408: getfield ZS : Ljava/util/List;
    //   1411: aload_1
    //   1412: getfield ZG : I
    //   1415: sipush #-13890
    //   1418: sipush #20579
    //   1421: invokestatic a : (II)Ljava/lang/String;
    //   1424: invokespecial <init> : (Ljava/lang/String;Lburp/Zbcc;Ljava/util/List;ILjava/lang/String;)V
    //   1427: astore #8
    //   1429: aload_0
    //   1430: getfield ZrS : Lburp/Zbqc;
    //   1433: aload #8
    //   1435: invokevirtual add : (Ljava/awt/Component;)Ljava/awt/Component;
    //   1438: pop
    //   1439: aload_0
    //   1440: getfield Zr3 : Lburp/Zxer;
    //   1443: iload #5
    //   1445: iinc #5, 1
    //   1448: aload_2
    //   1449: getfield Zf : Z
    //   1452: invokevirtual setEnabledAt : (IZ)V
    //   1455: aload_0
    //   1456: getfield ZO : Lburp/Zbqc;
    //   1459: invokevirtual removeAll : ()V
    //   1462: iload #6
    //   1464: ifeq -> 1630
    //   1467: new burp/Zz_u
    //   1470: dup
    //   1471: iconst_0
    //   1472: aload_1
    //   1473: getfield ZI : [D
    //   1476: sipush #-13887
    //   1479: sipush #1981
    //   1482: invokestatic a : (II)Ljava/lang/String;
    //   1485: aconst_null
    //   1486: iconst_0
    //   1487: invokespecial <init> : (Z[DLjava/lang/String;Ljava/lang/String;Z)V
    //   1490: astore #7
    //   1492: new burp/Zgou
    //   1495: dup
    //   1496: sipush #-13930
    //   1499: sipush #-18514
    //   1502: invokestatic a : (II)Ljava/lang/String;
    //   1505: sipush #-13871
    //   1508: sipush #9452
    //   1511: invokestatic a : (II)Ljava/lang/String;
    //   1514: aload #7
    //   1516: invokevirtual ZT : ()Lburp/Zbcc;
    //   1519: invokespecial <init> : (Ljava/lang/String;Ljava/lang/String;Lburp/Zbcc;)V
    //   1522: astore #8
    //   1524: aload_0
    //   1525: getfield ZO : Lburp/Zbqc;
    //   1528: aload #8
    //   1530: invokevirtual add : (Ljava/awt/Component;)Ljava/awt/Component;
    //   1533: pop
    //   1534: new burp/Zz_u
    //   1537: dup
    //   1538: iconst_0
    //   1539: aload_1
    //   1540: getfield ZM : [D
    //   1543: sipush #-13887
    //   1546: sipush #1981
    //   1549: invokestatic a : (II)Ljava/lang/String;
    //   1552: aconst_null
    //   1553: iconst_1
    //   1554: invokespecial <init> : (Z[DLjava/lang/String;Ljava/lang/String;Z)V
    //   1557: astore #9
    //   1559: getstatic burp/Zlb0.ZY : Ljava/text/NumberFormat;
    //   1562: aload_1
    //   1563: getfield ZD : D
    //   1566: invokevirtual format : (D)Ljava/lang/String;
    //   1569: sipush #-13873
    //   1572: sipush #28304
    //   1575: invokestatic a : (II)Ljava/lang/String;
    //   1578: swap
    //   1579: sipush #-13941
    //   1582: sipush #-2901
    //   1585: invokestatic a : (II)Ljava/lang/String;
    //   1588: <illegal opcode> makeConcatWithConstants : (Ljava/lang/String;Ljava/lang/String;Ljava/lang/String;)Ljava/lang/String;
    //   1593: astore #10
    //   1595: new burp/Zgou
    //   1598: dup
    //   1599: sipush #-13828
    //   1602: sipush #-27933
    //   1605: invokestatic a : (II)Ljava/lang/String;
    //   1608: aload #10
    //   1610: aload #9
    //   1612: invokevirtual ZT : ()Lburp/Zbcc;
    //   1615: invokespecial <init> : (Ljava/lang/String;Ljava/lang/String;Lburp/Zbcc;)V
    //   1618: astore #11
    //   1620: aload_0
    //   1621: getfield ZO : Lburp/Zbqc;
    //   1624: aload #11
    //   1626: invokevirtual add : (Ljava/awt/Component;)Ljava/awt/Component;
    //   1629: pop
    //   1630: aload_0
    //   1631: getfield Zr3 : Lburp/Zxer;
    //   1634: iload #5
    //   1636: iinc #5, 1
    //   1639: iload #6
    //   1641: invokevirtual setEnabledAt : (IZ)V
    //   1644: aload_2
    //   1645: getfield ZH : Z
    //   1648: ifne -> 1693
    //   1651: aload_2
    //   1652: getfield Zy : Z
    //   1655: ifne -> 1693
    //   1658: aload_2
    //   1659: getfield Zh : Z
    //   1662: ifne -> 1693
    //   1665: aload_2
    //   1666: getfield ZM : Z
    //   1669: ifne -> 1693
    //   1672: aload_2
    //   1673: getfield ZA : Z
    //   1676: ifne -> 1693
    //   1679: aload_2
    //   1680: getfield Za : Z
    //   1683: ifne -> 1693
    //   1686: aload_2
    //   1687: getfield Zx : Z
    //   1690: ifeq -> 1697
    //   1693: iconst_1
    //   1694: goto -> 1698
    //   1697: iconst_0
    //   1698: istore #7
    //   1700: iconst_0
    //   1701: istore #5
    //   1703: aload_0
    //   1704: getfield Zs : Lburp/Zbqc;
    //   1707: invokevirtual removeAll : ()V
    //   1710: iload #7
    //   1712: ifeq -> 1856
    //   1715: new burp/Zs1i
    //   1718: dup
    //   1719: aload_1
    //   1720: getfield Zn : [D
    //   1723: sipush #-13938
    //   1726: sipush #-5562
    //   1729: invokestatic a : (II)Ljava/lang/String;
    //   1732: invokespecial <init> : ([DLjava/lang/String;)V
    //   1735: astore #8
    //   1737: new burp/Zgou
    //   1740: dup
    //   1741: sipush #-13857
    //   1744: sipush #32504
    //   1747: invokestatic a : (II)Ljava/lang/String;
    //   1750: sipush #-13903
    //   1753: sipush #536
    //   1756: invokestatic a : (II)Ljava/lang/String;
    //   1759: aload #8
    //   1761: invokevirtual Zy : ()Lburp/Zbcc;
    //   1764: invokespecial <init> : (Ljava/lang/String;Ljava/lang/String;Lburp/Zbcc;)V
    //   1767: astore #9
    //   1769: aload_0
    //   1770: getfield Zs : Lburp/Zbqc;
    //   1773: aload #9
    //   1775: invokevirtual add : (Ljava/awt/Component;)Ljava/awt/Component;
    //   1778: pop
    //   1779: new burp/Zz_u
    //   1782: dup
    //   1783: iconst_1
    //   1784: aload_1
    //   1785: getfield ZL : [D
    //   1788: sipush #-13942
    //   1791: sipush #5212
    //   1794: invokestatic a : (II)Ljava/lang/String;
    //   1797: sipush #-13850
    //   1800: sipush #25302
    //   1803: invokestatic a : (II)Ljava/lang/String;
    //   1806: iconst_0
    //   1807: aload #4
    //   1809: invokespecial <init> : (Z[DLjava/lang/String;Ljava/lang/String;ZLjava/lang/Object;)V
    //   1812: astore #10
    //   1814: new burp/Zgou
    //   1817: dup
    //   1818: sipush #-13836
    //   1821: sipush #-10148
    //   1824: invokestatic a : (II)Ljava/lang/String;
    //   1827: sipush #-13826
    //   1830: sipush #18025
    //   1833: invokestatic a : (II)Ljava/lang/String;
    //   1836: aload #10
    //   1838: invokevirtual ZT : ()Lburp/Zbcc;
    //   1841: invokespecial <init> : (Ljava/lang/String;Ljava/lang/String;Lburp/Zbcc;)V
    //   1844: astore #11
    //   1846: aload_0
    //   1847: getfield Zs : Lburp/Zbqc;
    //   1850: aload #11
    //   1852: invokevirtual add : (Ljava/awt/Component;)Ljava/awt/Component;
    //   1855: pop
    //   1856: aload_0
    //   1857: getfield ZW : Lburp/Zxer;
    //   1860: iload #5
    //   1862: iinc #5, 1
    //   1865: iload #7
    //   1867: invokevirtual setEnabledAt : (IZ)V
    //   1870: aload_0
    //   1871: getfield ZG : Lburp/Zbqc;
    //   1874: invokevirtual removeAll : ()V
    //   1877: aload_2
    //   1878: getfield ZH : Z
    //   1881: ifeq -> 1962
    //   1884: new burp/Zs1i
    //   1887: dup
    //   1888: aload_1
    //   1889: getfield ZO : [D
    //   1892: sipush #-13933
    //   1895: sipush #32456
    //   1898: invokestatic a : (II)Ljava/lang/String;
    //   1901: invokespecial <init> : ([DLjava/lang/String;)V
    //   1904: astore #8
    //   1906: new burp/Zgo9
    //   1909: dup
    //   1910: bipush #11
    //   1912: sipush #-13876
    //   1915: bipush #79
    //   1917: invokestatic a : (II)Ljava/lang/String;
    //   1920: aload #8
    //   1922: invokevirtual Zy : ()Lburp/Zbcc;
    //   1925: aload_1
    //   1926: getfield Zj : Ljava/util/List;
    //   1929: aload_1
    //   1930: getfield ZC : I
    //   1933: aload_1
    //   1934: getfield ZE : [Z
    //   1937: aconst_null
    //   1938: sipush #-13937
    //   1941: sipush #-13348
    //   1944: invokestatic a : (II)Ljava/lang/String;
    //   1947: invokespecial <init> : (BLjava/lang/String;Lburp/Zbcc;Ljava/util/List;I[ZLjava/lang/String;Ljava/lang/String;)V
    //   1950: astore #9
    //   1952: aload_0
    //   1953: getfield ZG : Lburp/Zbqc;
    //   1956: aload #9
    //   1958: invokevirtual add : (Ljava/awt/Component;)Ljava/awt/Component;
    //   1961: pop
    //   1962: aload_0
    //   1963: getfield ZW : Lburp/Zxer;
    //   1966: iload #5
    //   1968: iinc #5, 1
    //   1971: aload_2
    //   1972: getfield ZH : Z
    //   1975: invokevirtual setEnabledAt : (IZ)V
    //   1978: aload_0
    //   1979: getfield ZT : Lburp/Zbqc;
    //   1982: invokevirtual removeAll : ()V
    //   1985: aload_2
    //   1986: getfield Zy : Z
    //   1989: ifeq -> 2071
    //   1992: new burp/Zs1i
    //   1995: dup
    //   1996: aload_1
    //   1997: getfield Zh : [D
    //   2000: sipush #-13933
    //   2003: sipush #32456
    //   2006: invokestatic a : (II)Ljava/lang/String;
    //   2009: invokespecial <init> : ([DLjava/lang/String;)V
    //   2012: astore #8
    //   2014: new burp/Zgo9
    //   2017: dup
    //   2018: bipush #12
    //   2020: sipush #-13846
    //   2023: sipush #19828
    //   2026: invokestatic a : (II)Ljava/lang/String;
    //   2029: aload #8
    //   2031: invokevirtual Zy : ()Lburp/Zbcc;
    //   2034: aload_1
    //   2035: getfield Zc : Ljava/util/List;
    //   2038: aload_1
    //   2039: getfield Ze : I
    //   2042: aload_1
    //   2043: getfield Z_ : [Z
    //   2046: aconst_null
    //   2047: sipush #-13864
    //   2050: sipush #15239
    //   2053: invokestatic a : (II)Ljava/lang/String;
    //   2056: invokespecial <init> : (BLjava/lang/String;Lburp/Zbcc;Ljava/util/List;I[ZLjava/lang/String;Ljava/lang/String;)V
    //   2059: astore #9
    //   2061: aload_0
    //   2062: getfield ZT : Lburp/Zbqc;
    //   2065: aload #9
    //   2067: invokevirtual add : (Ljava/awt/Component;)Ljava/awt/Component;
    //   2070: pop
    //   2071: aload_0
    //   2072: getfield ZW : Lburp/Zxer;
    //   2075: iload #5
    //   2077: iinc #5, 1
    //   2080: aload_2
    //   2081: getfield Zy : Z
    //   2084: invokevirtual setEnabledAt : (IZ)V
    //   2087: aload_0
    //   2088: getfield Ze : Lburp/Zbqc;
    //   2091: invokevirtual removeAll : ()V
    //   2094: aload_2
    //   2095: getfield Zh : Z
    //   2098: ifeq -> 2180
    //   2101: new burp/Zs1i
    //   2104: dup
    //   2105: aload_1
    //   2106: getfield ZP : [D
    //   2109: sipush #-13933
    //   2112: sipush #32456
    //   2115: invokestatic a : (II)Ljava/lang/String;
    //   2118: invokespecial <init> : ([DLjava/lang/String;)V
    //   2121: astore #8
    //   2123: new burp/Zgo9
    //   2126: dup
    //   2127: bipush #13
    //   2129: sipush #-13882
    //   2132: sipush #3217
    //   2135: invokestatic a : (II)Ljava/lang/String;
    //   2138: aload #8
    //   2140: invokevirtual Zy : ()Lburp/Zbcc;
    //   2143: aload_1
    //   2144: getfield Zp : Ljava/util/List;
    //   2147: aload_1
    //   2148: getfield Zu : I
    //   2151: aload_1
    //   2152: getfield Zd : [Z
    //   2155: aconst_null
    //   2156: sipush #-13878
    //   2159: sipush #25306
    //   2162: invokestatic a : (II)Ljava/lang/String;
    //   2165: invokespecial <init> : (BLjava/lang/String;Lburp/Zbcc;Ljava/util/List;I[ZLjava/lang/String;Ljava/lang/String;)V
    //   2168: astore #9
    //   2170: aload_0
    //   2171: getfield Ze : Lburp/Zbqc;
    //   2174: aload #9
    //   2176: invokevirtual add : (Ljava/awt/Component;)Ljava/awt/Component;
    //   2179: pop
    //   2180: aload_0
    //   2181: getfield ZW : Lburp/Zxer;
    //   2184: iload #5
    //   2186: iinc #5, 1
    //   2189: aload_2
    //   2190: getfield Zh : Z
    //   2193: invokevirtual setEnabledAt : (IZ)V
    //   2196: aload_0
    //   2197: getfield Zb : Lburp/Zbqc;
    //   2200: invokevirtual removeAll : ()V
    //   2203: aload_2
    //   2204: getfield ZM : Z
    //   2207: ifeq -> 2297
    //   2210: new burp/Zs1i
    //   2213: dup
    //   2214: aload_1
    //   2215: getfield Zt : [D
    //   2218: sipush #-13933
    //   2221: sipush #32456
    //   2224: invokestatic a : (II)Ljava/lang/String;
    //   2227: invokespecial <init> : ([DLjava/lang/String;)V
    //   2230: astore #8
    //   2232: new burp/Zgo9
    //   2235: dup
    //   2236: bipush #14
    //   2238: sipush #-13842
    //   2241: sipush #-28106
    //   2244: invokestatic a : (II)Ljava/lang/String;
    //   2247: aload #8
    //   2249: invokevirtual Zy : ()Lburp/Zbcc;
    //   2252: aload_1
    //   2253: getfield Zy : Ljava/util/List;
    //   2256: aload_1
    //   2257: getfield ZB : I
    //   2260: aload_1
    //   2261: getfield ZT : [Z
    //   2264: sipush #-13943
    //   2267: sipush #-692
    //   2270: invokestatic a : (II)Ljava/lang/String;
    //   2273: sipush #-13951
    //   2276: sipush #-28220
    //   2279: invokestatic a : (II)Ljava/lang/String;
    //   2282: invokespecial <init> : (BLjava/lang/String;Lburp/Zbcc;Ljava/util/List;I[ZLjava/lang/String;Ljava/lang/String;)V
    //   2285: astore #9
    //   2287: aload_0
    //   2288: getfield Zb : Lburp/Zbqc;
    //   2291: aload #9
    //   2293: invokevirtual add : (Ljava/awt/Component;)Ljava/awt/Component;
    //   2296: pop
    //   2297: aload_0
    //   2298: getfield ZW : Lburp/Zxer;
    //   2301: iload #5
    //   2303: iinc #5, 1
    //   2306: aload_2
    //   2307: getfield ZM : Z
    //   2310: invokevirtual setEnabledAt : (IZ)V
    //   2313: aload_0
    //   2314: getfield ZR : Lburp/Zbqc;
    //   2317: invokevirtual removeAll : ()V
    //   2320: aload_2
    //   2321: getfield ZA : Z
    //   2324: ifeq -> 2399
    //   2327: new burp/Zs1i
    //   2330: dup
    //   2331: aload_1
    //   2332: getfield Zf : [D
    //   2335: sipush #-13933
    //   2338: sipush #32456
    //   2341: invokestatic a : (II)Ljava/lang/String;
    //   2344: invokespecial <init> : ([DLjava/lang/String;)V
    //   2347: astore #8
    //   2349: new burp/Zgoi
    //   2352: dup
    //   2353: sipush #-13841
    //   2356: sipush #29717
    //   2359: invokestatic a : (II)Ljava/lang/String;
    //   2362: aload #8
    //   2364: invokevirtual Zy : ()Lburp/Zbcc;
    //   2367: aload_1
    //   2368: getfield ZH : Ljava/util/List;
    //   2371: aload_1
    //   2372: getfield ZV : I
    //   2375: sipush #-13856
    //   2378: sipush #27228
    //   2381: invokestatic a : (II)Ljava/lang/String;
    //   2384: invokespecial <init> : (Ljava/lang/String;Lburp/Zbcc;Ljava/util/List;ILjava/lang/String;)V
    //   2387: astore #9
    //   2389: aload_0
    //   2390: getfield ZR : Lburp/Zbqc;
    //   2393: aload #9
    //   2395: invokevirtual add : (Ljava/awt/Component;)Ljava/awt/Component;
    //   2398: pop
    //   2399: aload_0
    //   2400: getfield ZW : Lburp/Zxer;
    //   2403: iload #5
    //   2405: iinc #5, 1
    //   2408: aload_2
    //   2409: getfield ZA : Z
    //   2412: invokevirtual setEnabledAt : (IZ)V
    //   2415: aload_0
    //   2416: getfield ZB : Lburp/Zbqc;
    //   2419: invokevirtual removeAll : ()V
    //   2422: aload_2
    //   2423: getfield Za : Z
    //   2426: ifeq -> 2501
    //   2429: new burp/Zs1i
    //   2432: dup
    //   2433: aload_1
    //   2434: getfield Zw : [D
    //   2437: sipush #-13933
    //   2440: sipush #32456
    //   2443: invokestatic a : (II)Ljava/lang/String;
    //   2446: invokespecial <init> : ([DLjava/lang/String;)V
    //   2449: astore #8
    //   2451: new burp/Zgoi
    //   2454: dup
    //   2455: sipush #-13947
    //   2458: sipush #-17255
    //   2461: invokestatic a : (II)Ljava/lang/String;
    //   2464: aload #8
    //   2466: invokevirtual Zy : ()Lburp/Zbcc;
    //   2469: aload_1
    //   2470: getfield Zz : Ljava/util/List;
    //   2473: aload_1
    //   2474: getfield Zx : I
    //   2477: sipush #-13866
    //   2480: sipush #-3715
    //   2483: invokestatic a : (II)Ljava/lang/String;
    //   2486: invokespecial <init> : (Ljava/lang/String;Lburp/Zbcc;Ljava/util/List;ILjava/lang/String;)V
    //   2489: astore #9
    //   2491: aload_0
    //   2492: getfield ZB : Lburp/Zbqc;
    //   2495: aload #9
    //   2497: invokevirtual add : (Ljava/awt/Component;)Ljava/awt/Component;
    //   2500: pop
    //   2501: aload_0
    //   2502: getfield ZW : Lburp/Zxer;
    //   2505: iload #5
    //   2507: iinc #5, 1
    //   2510: aload_2
    //   2511: getfield Za : Z
    //   2514: invokevirtual setEnabledAt : (IZ)V
    //   2517: aload_0
    //   2518: getfield ZP : Lburp/Zbqc;
    //   2521: invokevirtual removeAll : ()V
    //   2524: aload_2
    //   2525: getfield Zx : Z
    //   2528: ifeq -> 2603
    //   2531: new burp/Zgq0
    //   2534: dup
    //   2535: aload_1
    //   2536: getfield ZN : [D
    //   2539: sipush #-13933
    //   2542: sipush #32456
    //   2545: invokestatic a : (II)Ljava/lang/String;
    //   2548: invokespecial <init> : ([DLjava/lang/String;)V
    //   2551: astore #8
    //   2553: new burp/Zgoi
    //   2556: dup
    //   2557: sipush #-13870
    //   2560: sipush #15155
    //   2563: invokestatic a : (II)Ljava/lang/String;
    //   2566: aload #8
    //   2568: invokevirtual Zf : ()Lburp/Zbcc;
    //   2571: aload_1
    //   2572: getfield Zo : Ljava/util/List;
    //   2575: aload_1
    //   2576: getfield ZR : I
    //   2579: sipush #-13935
    //   2582: sipush #28039
    //   2585: invokestatic a : (II)Ljava/lang/String;
    //   2588: invokespecial <init> : (Ljava/lang/String;Lburp/Zbcc;Ljava/util/List;ILjava/lang/String;)V
    //   2591: astore #9
    //   2593: aload_0
    //   2594: getfield ZP : Lburp/Zbqc;
    //   2597: aload #9
    //   2599: invokevirtual add : (Ljava/awt/Component;)Ljava/awt/Component;
    //   2602: pop
    //   2603: aload_0
    //   2604: getfield ZW : Lburp/Zxer;
    //   2607: iload #5
    //   2609: iinc #5, 1
    //   2612: aload_2
    //   2613: getfield Zx : Z
    //   2616: invokevirtual setEnabledAt : (IZ)V
    //   2619: aload_0
    //   2620: getfield Zo : Lburp/Zbqc;
    //   2623: invokevirtual removeAll : ()V
    //   2626: iload #7
    //   2628: ifeq -> 2817
    //   2631: new java/lang/StringBuilder
    //   2634: dup
    //   2635: sipush #-13891
    //   2638: sipush #12591
    //   2641: invokestatic a : (II)Ljava/lang/String;
    //   2644: invokespecial <init> : (Ljava/lang/String;)V
    //   2647: astore #8
    //   2649: aload #8
    //   2651: aload_1
    //   2652: getfield ZY : I
    //   2655: invokevirtual append : (I)Ljava/lang/StringBuilder;
    //   2658: pop
    //   2659: aload #8
    //   2661: sipush #-13896
    //   2664: sipush #1600
    //   2667: invokestatic a : (II)Ljava/lang/String;
    //   2670: invokevirtual append : (Ljava/lang/String;)Ljava/lang/StringBuilder;
    //   2673: pop
    //   2674: aload_1
    //   2675: getfield ZY : I
    //   2678: i2d
    //   2679: aload_1
    //   2680: getfield ZD : D
    //   2683: dcmpg
    //   2684: ifge -> 2739
    //   2687: aload #8
    //   2689: sipush #-13868
    //   2692: sipush #-11784
    //   2695: invokestatic a : (II)Ljava/lang/String;
    //   2698: invokevirtual append : (Ljava/lang/String;)Ljava/lang/StringBuilder;
    //   2701: pop
    //   2702: aload #8
    //   2704: getstatic burp/Zlb0.ZY : Ljava/text/NumberFormat;
    //   2707: aload_1
    //   2708: getfield ZD : D
    //   2711: aload_1
    //   2712: getfield ZY : I
    //   2715: i2d
    //   2716: dsub
    //   2717: invokevirtual format : (D)Ljava/lang/String;
    //   2720: invokevirtual append : (Ljava/lang/String;)Ljava/lang/StringBuilder;
    //   2723: pop
    //   2724: aload #8
    //   2726: sipush #-13831
    //   2729: sipush #-18780
    //   2732: invokestatic a : (II)Ljava/lang/String;
    //   2735: invokevirtual append : (Ljava/lang/String;)Ljava/lang/StringBuilder;
    //   2738: pop
    //   2739: aload #8
    //   2741: sipush #-13888
    //   2744: sipush #-16738
    //   2747: invokestatic a : (II)Ljava/lang/String;
    //   2750: invokevirtual append : (Ljava/lang/String;)Ljava/lang/StringBuilder;
    //   2753: pop
    //   2754: new burp/Zz_u
    //   2757: dup
    //   2758: iconst_0
    //   2759: aload_1
    //   2760: getfield Zs : [D
    //   2763: sipush #-13887
    //   2766: sipush #1981
    //   2769: invokestatic a : (II)Ljava/lang/String;
    //   2772: aconst_null
    //   2773: iconst_0
    //   2774: invokespecial <init> : (Z[DLjava/lang/String;Ljava/lang/String;Z)V
    //   2777: astore #9
    //   2779: new burp/Zgou
    //   2782: dup
    //   2783: sipush #-13880
    //   2786: sipush #15947
    //   2789: invokestatic a : (II)Ljava/lang/String;
    //   2792: aload #8
    //   2794: invokevirtual toString : ()Ljava/lang/String;
    //   2797: aload #9
    //   2799: invokevirtual ZT : ()Lburp/Zbcc;
    //   2802: invokespecial <init> : (Ljava/lang/String;Ljava/lang/String;Lburp/Zbcc;)V
    //   2805: astore #10
    //   2807: aload_0
    //   2808: getfield Zo : Lburp/Zbqc;
    //   2811: aload #10
    //   2813: invokevirtual add : (Ljava/awt/Component;)Ljava/awt/Component;
    //   2816: pop
    //   2817: aload_0
    //   2818: getfield ZW : Lburp/Zxer;
    //   2821: iload #5
    //   2823: iinc #5, 1
    //   2826: iload #7
    //   2828: invokevirtual setEnabledAt : (IZ)V
    //   2831: return
  }
  
  public boolean ZE(byte[] paramArrayOfbyte) {
    try {
      if (this.ZrK)
        try {
          if (!this.Zrk) {
            this.Zrw.add(paramArrayOfbyte);
            int i = this.Zrw.size();
            try {
              if (i == Zgpg.Zf[this.ZE]) {
                try {
                  this.ZE++;
                  if (this.ZE < Zgpg.Zf.length)
                    this.ZV.Zl(Zgpg.Zf[this.ZE]); 
                } catch (Zs0j zs0j) {
                  throw a(null);
                } 
                if (this.Zd) {
                  try {
                    Zx_j zx_j = this.ZM.ZKV(false);
                    this.Zr = zx_j;
                  } catch (Zs0j zs0j) {
                    Zah.Zl(zs0j, Zk_.USER_ERROR);
                  } 
                  ZV(ZJ(this.Zrw), this.Zr.ZL());
                } 
              } 
            } catch (Zs0j zs0j) {
              throw a(null);
            } 
            try {
              if (i >= 20000)
                this.Zrk = true; 
            } catch (Zs0j zs0j) {
              throw a(null);
            } 
            try {
            
            } catch (Zs0j zs0j) {
              throw a(null);
            } 
            return !this.Zrk;
          } 
          return false;
        } catch (Zs0j zs0j) {
          throw a(null);
        }  
    } catch (Zs0j zs0j) {
      throw a(null);
    } 
    return false;
  }
  
  public boolean ZP(int paramInt1, int paramInt2) {
    this.ZV.ZH(this.Zrw.size(), paramInt1, paramInt2);
    if (this.ZA)
      synchronized (this.Zrw) {
        try {
          this.Zrw.wait();
        } catch (InterruptedException interruptedException) {
          Zah.Zl(interruptedException, Zk_.IGNORED);
        } 
      }  
    try {
    
    } catch (InterruptedException interruptedException) {
      throw a(null);
    } 
    return !this.Zrk;
  }
  
  public void Zf() {
    this.Zg.setEnabled(true);
  }
  
  void Zs() {
    this.ZA = true;
  }
  
  void ZE() {
    this.ZA = false;
    Zd();
  }
  
  void Zl() {
    this.Zrk = true;
    if (this.ZrK)
      Zd(); 
  }
  
  private void Zd() {
    synchronized (this.Zrw) {
      this.Zrw.notifyAll();
    } 
  }
  
  void ZX() {
    int i = Zt();
    synchronized (this.Zrw) {
      StringBuilder stringBuilder = new StringBuilder();
      for (byte[] arrayOfByte : this.Zrw) {
        stringBuilder.append(Zkb.ZG(arrayOfByte));
        stringBuilder.append(a(-13904, -26426));
        if (i != 0)
          break; 
      } 
      this.Zu.ZR(stringBuilder.toString());
    } 
  }
  
  void ZG() {
    int i = ZD();
    File file = Zs6n.Zp(Zg1m.DATA, this.ZX, this, 1, (String)null);
    try {
      if (file == null)
        return; 
    } catch (FileNotFoundException fileNotFoundException) {
      throw a(null);
    } 
    try {
      BufferedOutputStream bufferedOutputStream = new BufferedOutputStream(new FileOutputStream(file));
      for (byte[] arrayOfByte : this.Zrw) {
        bufferedOutputStream.write(arrayOfByte);
        bufferedOutputStream.write(Zdo.Zn);
        if (i == 0)
          break; 
      } 
      bufferedOutputStream.flush();
      bufferedOutputStream.close();
    } catch (FileNotFoundException fileNotFoundException) {
      Zah.Zl(fileNotFoundException, Zk_.USER_ERROR);
    } catch (IOException iOException) {
      Zah.Zl(iOException, Zk_.IMPOSSIBLE);
    } 
  }
  
  void ZQ(boolean paramBoolean) {
    this.Zd = paramBoolean;
  }
  
  void ZB() {
    byte[][] arrayOfByte = ZJ(this.Zrw);
    ZP(arrayOfByte);
    try {
      this.Zr = this.ZM.ZKV(false);
    } catch (Zs0j zs0j) {
      Zah.Zl(zs0j, Zk_.USER_ERROR);
    } 
    ZU(arrayOfByte, this.Zr.ZL());
  }
  
  private void ZW() {
    this.Zru = new Zbqc();
    this.ZC = new Zxer();
    this.Zz = new Zbup();
    this.ZN = new Zbqc();
    this.ZrL = new Zbqc();
    this.Zr3 = new Zxer();
    this.Za = new Zbup();
    this.ZZ = new Zbqc();
    this.Zi = new Zbqc();
    this.Zm = new Zbup();
    this.Zh = new Zbqc();
    this.Zc = new Zbqc();
    this.Zq = new Zbup();
    this.ZI = new Zbqc();
    this.ZrS = new Zbqc();
    this.Zt = new Zbup();
    this.Zro = new Zbqc();
    this.ZO = new Zbqc();
    this.ZW = new Zxer();
    this.Zre = new Zbup();
    this.Zw = new Zbqc();
    this.Zs = new Zbqc();
    this.Zk = new Zbup();
    this.ZF = new Zbqc();
    this.ZG = new Zbqc();
    this.ZrE = new Zbup();
    this.ZU = new Zbqc();
    this.ZT = new Zbqc();
    this.Zrf = new Zbup();
    this.ZrB = new Zbqc();
    this.Ze = new Zbqc();
    this.Zv = new Zbup();
    this.ZY = new Zbqc();
    this.Zb = new Zbqc();
    this.ZK = new Zbup();
    this.ZrT = new Zbqc();
    this.ZR = new Zbqc();
    this.ZrP = new Zbup();
    this.Zn = new Zbqc();
    this.ZB = new Zbqc();
    this.ZL = new Zbup();
    this.Zl = new Zbqc();
    this.ZP = new Zbqc();
    this.ZJ = new Zbup();
    this.ZS = new Zbqc();
    this.Zo = new Zbqc();
    this.ZH = new Zbup();
    this.Zx = new Zbqc();
    this.Zg = new Ze01();
    this.ZQ = new Zbqc();
    setDefaultCloseOperation(0);
    addWindowListener(new Zzcd(this));
    this.Zru.setLayout(new BorderLayout());
    this.ZN.setLayout(new BorderLayout());
    this.ZrL.setLayout(new BoxLayout(this.ZrL, 1));
    this.ZN.add(this.ZrL, a(-13830, -32637));
    this.Zz.setViewportView(this.ZN);
    this.ZC.addTab(a(-13835, 23395), this.Zz);
    this.ZZ.setLayout(new BorderLayout());
    this.Zi.setLayout(new BoxLayout(this.Zi, 1));
    this.ZZ.add(this.Zi, a(-13827, 30219));
    this.Za.setViewportView(this.ZZ);
    this.Zr3.addTab(a(-13875, 29718), this.Za);
    this.Zh.setLayout(new BorderLayout());
    this.Zc.setLayout(new BoxLayout(this.Zc, 1));
    this.Zh.add(this.Zc, a(-13861, 21840));
    this.Zm.setViewportView(this.Zh);
    this.Zr3.addTab(a(-13834, 27043), this.Zm);
    this.ZI.setLayout(new BorderLayout());
    this.ZrS.setLayout(new BoxLayout(this.ZrS, 1));
    this.ZI.add(this.ZrS, a(-13861, 21840));
    this.Zq.setViewportView(this.ZI);
    this.Zr3.addTab(a(-13899, -14122), this.Zq);
    this.Zro.setLayout(new BorderLayout());
    this.ZO.setLayout(new BoxLayout(this.ZO, 1));
    this.Zro.add(this.ZO, a(-13861, 21840));
    this.Zt.setViewportView(this.Zro);
    this.Zr3.addTab(a(-13844, 28444), this.Zt);
    this.ZC.addTab(a(-13925, -3116), (Component)this.Zr3);
    this.Zw.setLayout(new BorderLayout());
    this.Zs.setLayout(new BoxLayout(this.Zs, 1));
    this.Zw.add(this.Zs, a(-13861, 21840));
    this.Zre.setViewportView(this.Zw);
    this.ZW.addTab(a(-13875, 29718), this.Zre);
    this.ZF.setLayout(new BorderLayout());
    this.ZG.setLayout(new BoxLayout(this.ZG, 1));
    this.ZF.add(this.ZG, a(-13861, 21840));
    this.Zk.setViewportView(this.ZF);
    this.ZW.addTab(a(-13952, 2684), this.Zk);
    this.ZU.setLayout(new BorderLayout());
    this.ZT.setLayout(new BoxLayout(this.ZT, 1));
    this.ZU.add(this.ZT, a(-13861, 21840));
    this.ZrE.setViewportView(this.ZU);
    this.ZW.addTab(a(-13832, 8238), this.ZrE);
    this.ZrB.setLayout(new BorderLayout());
    this.Ze.setLayout(new BoxLayout(this.Ze, 1));
    this.ZrB.add(this.Ze, a(-13861, 21840));
    this.Zrf.setViewportView(this.ZrB);
    this.ZW.addTab(a(-13927, -11629), this.Zrf);
    this.ZY.setLayout(new BorderLayout());
    this.Zb.setLayout(new BoxLayout(this.Zb, 1));
    this.ZY.add(this.Zb, a(-13861, 21840));
    this.Zv.setViewportView(this.ZY);
    this.ZW.addTab(a(-13921, 18051), this.Zv);
    this.ZrT.setLayout(new BorderLayout());
    this.ZR.setLayout(new BoxLayout(this.ZR, 1));
    this.ZrT.add(this.ZR, a(-13861, 21840));
    this.ZK.setViewportView(this.ZrT);
    this.ZW.addTab(a(-13872, -21065), this.ZK);
    this.Zn.setLayout(new BorderLayout());
    this.ZB.setLayout(new BoxLayout(this.ZB, 1));
    this.Zn.add(this.ZB, a(-13861, 21840));
    this.ZrP.setViewportView(this.Zn);
    this.ZW.addTab(a(-13948, 27544), this.ZrP);
    this.Zl.setLayout(new BorderLayout());
    this.ZP.setLayout(new BoxLayout(this.ZP, 1));
    this.Zl.add(this.ZP, a(-13861, 21840));
    this.ZL.setViewportView(this.Zl);
    this.ZW.addTab(a(-13869, -22973), this.ZL);
    this.ZS.setLayout(new BorderLayout());
    this.Zo.setLayout(new BoxLayout(this.Zo, 1));
    this.ZS.add(this.Zo, a(-13861, 21840));
    this.ZJ.setViewportView(this.ZS);
    this.ZW.addTab(a(-13852, -19138), this.ZJ);
    this.ZC.addTab(a(-13877, -27248), (Component)this.ZW);
    GridBagLayout gridBagLayout = new GridBagLayout();
    gridBagLayout.columnWidths = new int[] { 0 };
    gridBagLayout.rowHeights = new int[] { 0, 0, 0 };
    this.Zx.setLayout(gridBagLayout);
    this.Zg.setText(a(-13854, 13496));
    this.Zg.setEnabled(false);
    this.Zg.addActionListener(new Zmrs(this));
    GridBagConstraints gridBagConstraints = new GridBagConstraints();
    gridBagConstraints.gridx = 0;
    gridBagConstraints.gridy = 2;
    gridBagConstraints.anchor = 23;
    gridBagConstraints.weighty = 1.0D;
    gridBagConstraints.insets = new Insets(20, 20, 20, 0);
    this.Zx.add(this.Zg, gridBagConstraints);
    this.ZQ.setLayout(new BorderLayout());
    gridBagConstraints = new GridBagConstraints();
    gridBagConstraints.gridx = 0;
    gridBagConstraints.gridy = 0;
    gridBagConstraints.fill = 2;
    gridBagConstraints.anchor = 23;
    gridBagConstraints.weightx = 1.0D;
    this.Zx.add(this.ZQ, gridBagConstraints);
    this.ZH.setViewportView(this.Zx);
    this.ZC.addTab(a(-13865, -10115), this.ZH);
    this.Zru.add((Component)this.ZC, a(-13940, -8835));
    getContentPane().add(this.Zru, a(-13940, -8835));
    pack();
  }
  
  private void ZK(ActionEvent paramActionEvent) {
    this.Zg.setEnabled(false);
    try {
      this.Zr = this.ZM.ZKV(true);
    } catch (Zs0j zs0j) {
      Zah.Zl(zs0j, Zk_.USER_ERROR);
      Zx6o.Zv(this, a(-13886, 32451), a(-13892, 9963));
      return;
    } 
    ZU(this.Zy, this.Zr.ZL());
  }
  
  private void Zb(WindowEvent paramWindowEvent) {
    if (this.Z_ != null)
      this.Z_.Zd(true); 
    this.ZrI.shutdown();
    Zl();
    setVisible(false);
    dispose();
  }
  
  private void lambda$performAnalysis$2(Zt3j paramZt3j, Zx_j paramZx_j) {
    if (!this.Z_.ZS())
      Z_(paramZt3j.Zy(), paramZx_j); 
  }
  
  private void lambda$doAutoAnalysis$1(byte[][] paramArrayOfbyte, Zx_j paramZx_j, boolean paramBoolean) {
    Zi(paramArrayOfbyte, paramZx_j, paramBoolean);
  }
  
  private void lambda$doAnalysis$0(byte[][] paramArrayOfbyte, Zx_j paramZx_j) {
    this.ZC.setEnabled(false);
    this.ZrL.removeAll();
    this.ZC.setSelectedIndex(0);
    Zi(paramArrayOfbyte, paramZx_j, true);
  }
  
  public static void Zt(int paramInt) {
    Zf = paramInt;
  }
  
  public static int Zt() {
    return Zf;
  }
  
  public static int ZD() {
    int i = Zt();
    return (i == 0) ? 27 : 0;
  }
  
  private static Exception a(Exception paramException) {
    return paramException;
  }
  
  static {
    // Byte code:
    //   0: bipush #110
    //   2: anewarray java/lang/String
    //   5: astore #5
    //   7: iconst_0
    //   8: iconst_0
    //   9: istore_3
    //   10: invokestatic Zt : (I)V
    //   13: ldc ')#G\\t1}8SMzS\\t5 /O7[[b:>'.IiVC$FBKro!/LdhgO!EVkn\\f|+uU40W9j[{i')%;n:\\r8U76Gm^C}%|3~g bWt*D{vKb8\|-'f\\bg?DX\\n; Z@|\\fChBCZ}6{\\bPsBNl3[r\\b|LE*{B.<E!]M(3hWKZ+)o`'AR;-*\\n."EwoYwkjh8KZ.;/{\\bl/yhp-,i<{8c-5<\\nB>Gl-8u~CWP M{{q'YGA)Hx\\f\`{>|N+:(zA "^xvm TTyl_=P>E/$Ju>vC-0;jbb'"OC=<m\\nCTt[@TgOmHWB3 P.$G\\t~*\\tnlvE5[5%."7e|ep?lHJiKh!==K}CtNad6TWH{\\n%p\\bk8-"\#k0:tB0<7aR8?6\\rU,)Tvv#N<P-C$j`,\\r\\f\\t[xwHb"*@\\r|~'GYw;s(}^fd;[lheAOc~O,"\\bz?^ooc)(>P_mlT6=((iXrO~t t\\tG3W%<DK/o<F\\f02Y79xw2HMZzGn{qGt]Jh\\bD/DTlMt%N\\rDaHcs\\r\\b,!X\\f`4c\\r\\bP?8bR9W_tV;Xl+@dnl0T~QTHwKh5SeXfn?\\f\g4O\\n2a"E/DLvna`l|\eoF'~ll}?kD_Q\\rT"WWv6 gh![,DM,;ejH)|SXT(W[vO\\rH\\tRTtCw7bzBX4\\f9wg)'J('O!yN=1*R  U"vs5$t\\r\\ftb;R?>V%Y["u2}Wh[Vru*D\\b\\b:0F8r>`H-+EN&>*[aZ3EH ciLw)'{@!YL#\\fF ZB[t].xL,0H,@{0KJd<elp/"r2%LQ>L2+\\tJ#c44[FHt C[KJB;i;z]cZ06ANh \\r"X:FfyGA\i5PJC>#xZu?.6\O\\t6?hF\\f,}Iw\\ruKe.'*=y$o[iTcV;8\\b\\rCI3I/>_ {%;/$s1\\fIhVTfjz7#zpXP$Tx}K\\rlT1xs^\\b NPz[f{YbUBN!*\\fL~'L/c\\tO,#uxuQHuLuN<yq^&Xie?FwN"?[\V*`f)[Zr'\\f%?\\r%I]L>/pN>vYclX{eJwxNqNoT>r"Y#1n[hjf[^g~d%Ac!CHo$mtBSELCDrj%>#owVH_Y_?!\\fvU\\n]itwmyH19sLM =;$<Py^wn.L\\rQ42pw7jv|\\n m>t'L?.~8sUuSo| K\\n&tGvGbWR6gF#oDe;<>'eX~'~eoR*8awDSlZ5$*B04ayH8LexDf,A1FJF8M Mf__\\r&O:T$a<"@7bqe66*X<7.B[&W\\broAIRbFo,&)v!,O)AYNR:\\n D^-w"a#v-@M!qGZ^Q&{ILo\\f\\r:CqI\RkOAT5s!&=,q(N_^XA\\f`/hPg<bltv(JbDVVEXo@T\Hs(keqkdu?6 "xIU8Cj81R>Qc$TV@ >qx_k1EoipG%RN>8|X,jpb $,4Wn!r?]J(L"*_\\bQV,"sG"\\r;)pVn!E%"_dSI}4Dn_0R;\\rs \\np[\\nN>I0QhM^8T4=XP\\b0\\nO 'xsW-x%~vN3Z-4ka~uPBXiB,B}P6AUF()\\nx\\r_=d)-\\nlV\\b?\\tWpP!OXbW_tCNX+=H;g2@CdC_Zk!@L4"q7])D7L+P?i\\r<{^a\,3aYYk\\nM@BwDt.<Ga*=q\\t-"=+<c/.=iPQ\\r;q_/`\\t+r,0%6-US(\\rLTX-cK673%,CqrEc9Og7JIy85y{VhGK(,+\LTKXErO,UObT}+\\t6%+];VZ\A;Zp944>kE.k\\bcO;W5X@Kr/x#6d:f\\n|H.\\f26J9Rgev95n]z.)tNJ:.T=e2gF-zm\\tE#!|"$NU~\\t,[@`u7*cC\\r$knM>MH#ea_s7^\\b0G+E~Tp\%>>agUz;/\i\\nVgDlF 3PV<Y5\\b\\fo@Bpabi\\nVOd`kXR\\rz$0+3g\\fI:V'`W-5 2tR;AVYlYGp5<0b4F\\bE\\tB*<sbBPm,d%C9\\rUO649VlSB+p'\\r[Y:<VYPxbw\\n&iG^CsaCTCm[j@.XHKG~Bs%)F'VE M;vcqY>\\nQ!8Ukx/p\oH1ODzy \\b[0FUs7[y0?U;='>Pep\J~jK^N3^}l}t%TD918\\n!^}e7  \\n3\\r81YVF@$Yp*'mFIgDK@+5x{Pt\\fsob\\\n8,j`|\\rC#mi~@'z|Y[.VAA0V(1\C*nd9.ps||a7|o+lq8JVyG?}kM%lSJ%IPt+tJ/.+ABdzc^{Ch\8~Ve7rKL!Yjx3J\\fEw=\\n^Sr^SlD cQP2aS#.Q\\f|5V)Z;E%r]1F\\rah7L1aiJ*&E#ydt^X|4j6`d\\bGqMxN&)(.VaY BV<-@X00fD\\f,19Ty(x{T{Zkh=wq#B?H%pQR>{PuQa3Hoeuba>"c.V+7|w\\n\\r/\\nVgx}>J]Y%;a,t!Fl5':b%zHqP,[OiM\\t 1\\bwUn[aZ6:>r8{oXg^<+*<>E1v$%X\\bg&}{B\\rFq{8:+F-~H|,=LlWlh+c? X>[V 8(\\tDV5rSnd{Z#/dYd[+l\\r~I+k8}hWw^@re&jm~m3+jX:=\\nP":136Y^m,oe!)a\\t'V\ORE+RDX\\r%DAS]I+ X+AJ\\n1m>Akc\\fmNtF\\f,\\tu{GA\\rb.)+Z40f\\b3A\\n(S^:Pt$!g_A\P$a]N"X::Fe\nuLVd41Gn%[QeHE[=\\bF.y*Av0FZ1yP sttD0T\\t_N!s>IBi,y?\\tG %pf$-<qHA\\f hMir1x6;Y=3!R<"n\\fgbe+mh\\b \\fAtr_RFal32qtR(_B5!\\reA/xRs{5'J=UcW8Akrn9(\\tH;$+BpnB}v%Pse9qv0a M5^IlFNJeH(,^:QGzC[<_bSLwG|d0--M}-G(R>XG\\rp[;$\\b4p,`y2ZZnE yq: b-^sIq,Y'p`3KQ\\r-^`nisgz\4,`C75jt_0CsHb?NJo8IM\\t3{q\\tFb*hM8< wJw?M'@KE t\\rC\k,UpCH\}rdy%N(@M669+36\yg$ 3M;\# 4kM \\b8<xkq9\\r  Smbk8\\r`m`"p`fmEAm\\r;(D/{I t\\bH>R%v\\f `JFp]|2&.;u5N1W?`M(t/?-8UqxNI~'4IC.ngP/J..B!rE;@JD\\r)_DPtIP51xYeT_v\\f5n"{k3+Ka4\\fiZUN?fp)5Mf\\b/E\plBw\\r$W[4l;-|.Xx\\f1{nBl2[MT;fU@&*6SK:j~FH4i0ao\\f"!;6>uM A3AA$m2c;5XQNn9lgj}%wshhY!5\\b"\\n[Kc|mLh"n RN2N\!"\!{8t;); 'w`zuJ-}oM,3D%sP9 Lf85;5KFfFYN#BA7*2ddF]\S`,4Ec54~l.'lKu)Bb9i|8*<>S5q0TW},#(Yq6m$;m!-!H5\\rKXR\<D\\fad|GBmhveP'DK{82*_y-yZb3BCg vo}D11X>~;12~dl<Cgd\\fq,{5NB/hn[`K.HMwWK("7xP#Du0 \U\\rP_e'V~PPtw>w>X-i2wXc1O9|V'no.sGI8-?6b}{p_2PNj V4GHRHU'W}B\\tbQm<O\\n\\r[s7Vk$gB-yl2N(Lb$?\\rNS.UlZf$8JE_\\b\\ncV{R"8s^^$nVO>JQ=\\t-' -O\\t;yy\c\\b6BNRv<)dhj"q#CnTQH:_Y} '(ZeXCN$gd\\f* Vt7QZBW-G(&m9qy+e{F\\fhVouL4zcN6o\\fukH=E{ HzpNx6`0DRT\\rS@WnymJW$Lmm"$QXnA;N|\j(j7E>k%\\r^<bnka4CM<Q[BcE35 :JyXDw\\b+n4+[=|[R&=O.hG? |1N _==pDm>q-gi%\\rX$.< ["i(h'Wnk7\\n1i;&tmEr=YmK2;zcQ\\rK[Gt20I7$.(W~lI!%k9$l!1T40\[a}4d6\\r\\\n:74E4\\r!L[^%E#;({=5nIl\\f25L{&lG^|($E7-JKL0Z;`pU.eo-aPJ.'$1$s4}8&*DCza9\\f?QR6^5uZ?d?{8wG#sf BNf'#C.2d@(4[71A\\rpwqP\\nT[A\ZcN>-9@r%Flk4\\rWMy!;`Zx( =i6j0Q0:cuG=:qCh/ybav^z;7q\LQ&Y0'MN3G NXt:/\\ndQf\\tN6*EU_bE}2kM)=2q\\nuW[STQN-_$v.(z`22 -jx[[<G)\\rgRX'<U8@VXZv\\rK]JMD#|rIvy6?&I~ECc<`SC1A@*#;:xx]Z5J4vD/RYQMC^<423KWc5FPI!3ghvuiq 2I_rm/\\r}PpTGQ\\n%U:O4~DrK~{6' uT,Di\\nYmIl4l-J3_^-3j'~f9 4\\rC\\nS/G5&`+S:!Yr. W8ZN<.m\\n'yH<\\r ;QQEe\\nK#>&Go"D,`!AAg[~US*=nXI\\bRs\T;)qJVc6$\\r7M?\\n)*oW5f'@-\\b}KG3/Ak##!x3J[D \\n[6l j=1;$ \\ntu4_|&/4)\L,%2\3DLT(Y5!F\\tCR:f%7\\n\\fnVWY"K{A^\\tc~a`*Axr7\\f,qzPU4T3|h\\b5./'
    //   15: dup
    //   16: astore_2
    //   17: invokevirtual length : ()I
    //   20: istore #4
    //   22: bipush #6
    //   24: istore_1
    //   25: iconst_m1
    //   26: istore_0
    //   27: bipush #101
    //   29: iinc #0, 1
    //   32: aload_2
    //   33: iload_0
    //   34: dup
    //   35: iload_1
    //   36: iadd
    //   37: invokevirtual substring : (II)Ljava/lang/String;
    //   40: iconst_m1
    //   41: goto -> 148
    //   44: aload #5
    //   46: swap
    //   47: iload_3
    //   48: iinc #3, 1
    //   51: swap
    //   52: aastore
    //   53: iload_0
    //   54: iload_1
    //   55: iadd
    //   56: dup
    //   57: istore_0
    //   58: iload #4
    //   60: if_icmpge -> 72
    //   63: aload_2
    //   64: iload_0
    //   65: invokevirtual charAt : (I)C
    //   68: istore_1
    //   69: goto -> 27
    //   72: ldc '|xSzK\\nmgXF\\n;z\\r%6cXCT2^JnU,UD8~(\\t2uJQJ\\f1xa 42nPmJP+,j{?z= :>\\t\\b*Pz7d:<!G|\\n^$'@\8\\n&(*\\n?;3x\\fIh 9s>\\n\\nyS<'
    //   74: dup
    //   75: astore_2
    //   76: invokevirtual length : ()I
    //   79: istore #4
    //   81: sipush #250
    //   84: istore_1
    //   85: iconst_m1
    //   86: istore_0
    //   87: bipush #70
    //   89: iinc #0, 1
    //   92: aload_2
    //   93: iload_0
    //   94: dup
    //   95: iload_1
    //   96: iadd
    //   97: invokevirtual substring : (II)Ljava/lang/String;
    //   100: iconst_0
    //   101: goto -> 148
    //   104: aload #5
    //   106: swap
    //   107: iload_3
    //   108: iinc #3, 1
    //   111: swap
    //   112: aastore
    //   113: iload_0
    //   114: iload_1
    //   115: iadd
    //   116: dup
    //   117: istore_0
    //   118: iload #4
    //   120: if_icmpge -> 132
    //   123: aload_2
    //   124: iload_0
    //   125: invokevirtual charAt : (I)C
    //   128: istore_1
    //   129: goto -> 87
    //   132: aload #5
    //   134: putstatic burp/Zl4x.a : [Ljava/lang/String;
    //   137: bipush #110
    //   139: anewarray java/lang/String
    //   142: putstatic burp/Zl4x.b : [Ljava/lang/String;
    //   145: goto -> 304
    //   148: dup_x2
    //   149: pop
    //   150: invokevirtual toCharArray : ()[C
    //   153: dup_x1
    //   154: arraylength
    //   155: dup_x2
    //   156: pop
    //   157: iconst_0
    //   158: istore #6
    //   160: dup2_x1
    //   161: pop2
    //   162: dup_x2
    //   163: iconst_1
    //   164: if_icmpgt -> 264
    //   167: dup2
    //   168: swap
    //   169: iload #6
    //   171: dup2_x1
    //   172: caload
    //   173: swap
    //   174: iload #6
    //   176: bipush #7
    //   178: irem
    //   179: tableswitch default -> 246, 0 -> 216, 1 -> 221, 2 -> 226, 3 -> 231, 4 -> 236, 5 -> 241
    //   216: bipush #110
    //   218: goto -> 248
    //   221: bipush #89
    //   223: goto -> 248
    //   226: bipush #50
    //   228: goto -> 248
    //   231: bipush #34
    //   233: goto -> 248
    //   236: bipush #61
    //   238: goto -> 248
    //   241: bipush #72
    //   243: goto -> 248
    //   246: bipush #35
    //   248: ixor
    //   249: ixor
    //   250: i2c
    //   251: castore
    //   252: iinc #6, 1
    //   255: dup
    //   256: ifne -> 264
    //   259: dup2
    //   260: dup_x1
    //   261: goto -> 171
    //   264: dup2_x1
    //   265: pop2
    //   266: dup_x2
    //   267: iload #6
    //   269: if_icmpgt -> 167
    //   272: pop
    //   273: new java/lang/String
    //   276: dup_x1
    //   277: swap
    //   278: invokespecial <init> : ([C)V
    //   281: invokevirtual intern : ()Ljava/lang/String;
    //   284: swap
    //   285: pop
    //   286: swap
    //   287: tableswitch default -> 44, 0 -> 104
    //   304: return
  }
  
  private static String a(int paramInt1, int paramInt2) {
    int i = (paramInt1 ^ 0xFFFFC9DD) & 0xFFFF;
    if (b[i] == null) {
      char[] arrayOfChar = a[i].toCharArray();
      switch (arrayOfChar[0] & 0xFF) {
        case 0:
        
        case 1:
        
        case 2:
        
        case 3:
        
        case 4:
        
        case 5:
        
        case 6:
        
        case 7:
        
        case 8:
        
        case 9:
        
        case 10:
        
        case 11:
        
        case 12:
        
        case 13:
        
        case 14:
        
        case 15:
        
        case 16:
        
        case 17:
        
        case 18:
        
        case 19:
        
        case 20:
        
        case 21:
        
        case 22:
        
        case 23:
        
        case 24:
        
        case 25:
        
        case 26:
        
        case 27:
        
        case 28:
        
        case 29:
        
        case 30:
        
        case 31:
        
        case 32:
        
        case 33:
        
        case 34:
        
        case 35:
        
        case 36:
        
        case 37:
        
        case 38:
        
        case 39:
        
        case 40:
        
        case 41:
        
        case 42:
        
        case 43:
        
        case 44:
        
        case 45:
        
        case 46:
        
        case 47:
        
        case 48:
        
        case 49:
        
        case 50:
        
        case 51:
        
        case 52:
        
        case 53:
        
        case 54:
        
        case 55:
        
        case 56:
        
        case 57:
        
        case 58:
        
        case 59:
        
        case 60:
        
        case 61:
        
        case 62:
        
        case 63:
        
        case 64:
        
        case 65:
        
        case 66:
        
        case 67:
        
        case 68:
        
        case 69:
        
        case 70:
        
        case 71:
        
        case 72:
        
        case 73:
        
        case 74:
        
        case 75:
        
        case 76:
        
        case 77:
        
        case 78:
        
        case 79:
        
        case 80:
        
        case 81:
        
        case 82:
        
        case 83:
        
        case 84:
        
        case 85:
        
        case 86:
        
        case 87:
        
        case 88:
        
        case 89:
        
        case 90:
        
        case 91:
        
        case 92:
        
        case 93:
        
        case 94:
        
        case 95:
        
        case 96:
        
        case 97:
        
        case 98:
        
        case 99:
        
        case 100:
        
        case 101:
        
        case 102:
        
        case 103:
        
        case 104:
        
        case 105:
        
        case 106:
        
        case 107:
        
        case 108:
        
        case 109:
        
        case 110:
        
        case 111:
        
        case 112:
        
        case 113:
        
        case 114:
        
        case 115:
        
        case 116:
        
        case 117:
        
        case 118:
        
        case 119:
        
        case 120:
        
        case 121:
        
        case 122:
        
        case 123:
        
        case 124:
        
        case 125:
        
        case 126:
        
        case 127:
        
        case 128:
        
        case 129:
        
        case 130:
        
        case 131:
        
        case 132:
        
        case 133:
        
        case 134:
        
        case 135:
        
        case 136:
        
        case 137:
        
        case 138:
        
        case 139:
        
        case 140:
        
        case 141:
        
        case 142:
        
        case 143:
        
        case 144:
        
        case 145:
        
        case 146:
        
        case 147:
        
        case 148:
        
        case 149:
        
        case 150:
        
        case 151:
        
        case 152:
        
        case 153:
        
        case 154:
        
        case 155:
        
        case 156:
        
        case 157:
        
        case 158:
        
        case 159:
        
        case 160:
        
        case 161:
        
        case 162:
        
        case 163:
        
        case 164:
        
        case 165:
        
        case 166:
        
        case 167:
        
        case 168:
        
        case 169:
        
        case 170:
        
        case 171:
        
        case 172:
        
        case 173:
        
        case 174:
        
        case 175:
        
        case 176:
        
        case 177:
        
        case 178:
        
        case 179:
        
        case 180:
        
        case 181:
        
        case 182:
        
        case 183:
        
        case 184:
        
        case 185:
        
        case 186:
        
        case 187:
        
        case 188:
        
        case 189:
        
        case 190:
        
        case 191:
        
        case 192:
        
        case 193:
        
        case 194:
        
        case 195:
        
        case 196:
        
        case 197:
        
        case 198:
        
        case 199:
        
        case 200:
        
        case 201:
        
        case 202:
        
        case 203:
        
        case 204:
        
        case 205:
        
        case 206:
        
        case 207:
        
        case 208:
        
        case 209:
        
        case 210:
        
        case 211:
        
        case 212:
        
        case 213:
        
        case 214:
        
        case 215:
        
        case 216:
        
        case 217:
        
        case 218:
        
        case 219:
        
        case 220:
        
        case 221:
        
        case 222:
        
        case 223:
        
        case 224:
        
        case 225:
        
        case 226:
        
        case 227:
        
        case 228:
        
        case 229:
        
        case 230:
        
        case 231:
        
        case 232:
        
        case 233:
        
        case 234:
        
        case 235:
        
        case 236:
        
        case 237:
        
        case 238:
        
        case 239:
        
        case 240:
        
        case 241:
        
        case 242:
        
        case 243:
        
        case 244:
        
        case 245:
        
        case 246:
        
        case 247:
        
        case 248:
        
        case 249:
        
        case 250:
        
        case 251:
        
        case 252:
        
        case 253:
        
        case 254:
        
        default:
          break;
      } 
      char c = '';
      int j = (paramInt2 & 0xFF) - c;
      if (j < 0)
        j += 256; 
      int k = ((paramInt2 & 0xFFFF) >>> 8) - c;
      if (k < 0)
        k += 256; 
      for (byte b = 0; b < arrayOfChar.length; b++) {
        int m = b % 2;
        if (m == 0) {
          arrayOfChar[b] = (char)(arrayOfChar[b] ^ j);
          j = ((j >>> 3 | j << 5) ^ arrayOfChar[b]) & 0xFF;
        } else {
          arrayOfChar[b] = (char)(arrayOfChar[b] ^ k);
          k = ((k >>> 3 | k << 5) ^ arrayOfChar[b]) & 0xFF;
        } 
      } 
      b[i] = (new String(arrayOfChar)).intern();
    } 
    return b[i];
  }
}


/* Location:              C:\Program Files\BurpSuitePro\burpsuite_pro.jar!\burp\Zl4x.class
 * Java compiler version: 21 (65.0)
 * JD-Core Version:       1.1.3
 */