package burp;

import java.math.BigInteger;

class Zl55 extends ClassLoader {
  static String Zp;
  
  static Object ZZ;
  
  private static final String[] a;
  
  private static final String[] b;
  
  static boolean Zi(Object[] paramArrayOfObject, Object paramObject) throws Throwable {
    // Byte code:
    //   0: invokestatic ZK : ()Z
    //   3: istore_2
    //   4: new java/lang/StringBuilder
    //   7: dup
    //   8: invokespecial <init> : ()V
    //   11: astore_3
    //   12: iconst_0
    //   13: istore #4
    //   15: iload #4
    //   17: bipush #32
    //   19: if_icmpge -> 1355
    //   22: iload #4
    //   24: tableswitch default -> 1348, 0 -> 168, 1 -> 205, 2 -> 242, 3 -> 279, 4 -> 316, 5 -> 353, 6 -> 390, 7 -> 427, 8 -> 464, 9 -> 501, 10 -> 538, 11 -> 575, 12 -> 612, 13 -> 649, 14 -> 686, 15 -> 723, 16 -> 760, 17 -> 797, 18 -> 834, 19 -> 871, 20 -> 908, 21 -> 945, 22 -> 982, 23 -> 1019, 24 -> 1056, 25 -> 1093, 26 -> 1130, 27 -> 1167, 28 -> 1204, 29 -> 1241, 30 -> 1278, 31 -> 1315
    //   168: aload_3
    //   169: getstatic burp/Zlfg.Zb : Ljava/lang/String;
    //   172: getstatic burp/Zxzt.ZY : Ljava/lang/Object;
    //   175: checkcast java/math/BigInteger
    //   178: invokevirtual intValue : ()I
    //   181: bipush #32
    //   183: irem
    //   184: invokestatic abs : (I)I
    //   187: invokevirtual charAt : (I)C
    //   190: invokevirtual append : (C)Ljava/lang/StringBuilder;
    //   193: pop
    //   194: iload_2
    //   195: ifeq -> 1348
    //   198: goto -> 205
    //   201: invokestatic a : (Ljava/lang/Throwable;)Ljava/lang/Throwable;
    //   204: athrow
    //   205: aload_3
    //   206: getstatic burp/Zkw.ZU : Ljava/lang/String;
    //   209: getstatic burp/Zg_i.ZQ : Ljava/lang/Object;
    //   212: checkcast java/math/BigInteger
    //   215: invokevirtual intValue : ()I
    //   218: bipush #32
    //   220: irem
    //   221: invokestatic abs : (I)I
    //   224: invokevirtual charAt : (I)C
    //   227: invokevirtual append : (C)Ljava/lang/StringBuilder;
    //   230: pop
    //   231: iload_2
    //   232: ifeq -> 1348
    //   235: goto -> 242
    //   238: invokestatic a : (Ljava/lang/Throwable;)Ljava/lang/Throwable;
    //   241: athrow
    //   242: aload_3
    //   243: getstatic burp/Zr64.Zj : Ljava/lang/String;
    //   246: getstatic burp/Zsvh.Zv : Ljava/lang/Object;
    //   249: checkcast java/math/BigInteger
    //   252: invokevirtual intValue : ()I
    //   255: bipush #32
    //   257: irem
    //   258: invokestatic abs : (I)I
    //   261: invokevirtual charAt : (I)C
    //   264: invokevirtual append : (C)Ljava/lang/StringBuilder;
    //   267: pop
    //   268: iload_2
    //   269: ifeq -> 1348
    //   272: goto -> 279
    //   275: invokestatic a : (Ljava/lang/Throwable;)Ljava/lang/Throwable;
    //   278: athrow
    //   279: aload_3
    //   280: getstatic burp/Zzi3.ZS : Ljava/lang/String;
    //   283: getstatic burp/Zgfq.Za : Ljava/lang/Object;
    //   286: checkcast java/math/BigInteger
    //   289: invokevirtual intValue : ()I
    //   292: bipush #32
    //   294: irem
    //   295: invokestatic abs : (I)I
    //   298: invokevirtual charAt : (I)C
    //   301: invokevirtual append : (C)Ljava/lang/StringBuilder;
    //   304: pop
    //   305: iload_2
    //   306: ifeq -> 1348
    //   309: goto -> 316
    //   312: invokestatic a : (Ljava/lang/Throwable;)Ljava/lang/Throwable;
    //   315: athrow
    //   316: aload_3
    //   317: getstatic burp/Zr_z.ZE : Ljava/lang/String;
    //   320: getstatic burp/Zstq.Zf : Ljava/lang/Object;
    //   323: checkcast java/math/BigInteger
    //   326: invokevirtual intValue : ()I
    //   329: bipush #32
    //   331: irem
    //   332: invokestatic abs : (I)I
    //   335: invokevirtual charAt : (I)C
    //   338: invokevirtual append : (C)Ljava/lang/StringBuilder;
    //   341: pop
    //   342: iload_2
    //   343: ifeq -> 1348
    //   346: goto -> 353
    //   349: invokestatic a : (Ljava/lang/Throwable;)Ljava/lang/Throwable;
    //   352: athrow
    //   353: aload_3
    //   354: getstatic burp/Zl8l.ZG : Ljava/lang/String;
    //   357: getstatic burp/Zl55.ZZ : Ljava/lang/Object;
    //   360: checkcast java/math/BigInteger
    //   363: invokevirtual intValue : ()I
    //   366: bipush #32
    //   368: irem
    //   369: invokestatic abs : (I)I
    //   372: invokevirtual charAt : (I)C
    //   375: invokevirtual append : (C)Ljava/lang/StringBuilder;
    //   378: pop
    //   379: iload_2
    //   380: ifeq -> 1348
    //   383: goto -> 390
    //   386: invokestatic a : (Ljava/lang/Throwable;)Ljava/lang/Throwable;
    //   389: athrow
    //   390: aload_3
    //   391: getstatic burp/Ztgt.ZQ : Ljava/lang/String;
    //   394: getstatic burp/Zgh3.ZZ : Ljava/lang/Object;
    //   397: checkcast java/math/BigInteger
    //   400: invokevirtual intValue : ()I
    //   403: bipush #32
    //   405: irem
    //   406: invokestatic abs : (I)I
    //   409: invokevirtual charAt : (I)C
    //   412: invokevirtual append : (C)Ljava/lang/StringBuilder;
    //   415: pop
    //   416: iload_2
    //   417: ifeq -> 1348
    //   420: goto -> 427
    //   423: invokestatic a : (Ljava/lang/Throwable;)Ljava/lang/Throwable;
    //   426: athrow
    //   427: aload_3
    //   428: getstatic burp/Zk7b.ZE : Ljava/lang/String;
    //   431: getstatic burp/Zgz1.ZX : Ljava/lang/Object;
    //   434: checkcast java/math/BigInteger
    //   437: invokevirtual intValue : ()I
    //   440: bipush #32
    //   442: irem
    //   443: invokestatic abs : (I)I
    //   446: invokevirtual charAt : (I)C
    //   449: invokevirtual append : (C)Ljava/lang/StringBuilder;
    //   452: pop
    //   453: iload_2
    //   454: ifeq -> 1348
    //   457: goto -> 464
    //   460: invokestatic a : (Ljava/lang/Throwable;)Ljava/lang/Throwable;
    //   463: athrow
    //   464: aload_3
    //   465: getstatic burp/Zm0v.Zd : Ljava/lang/String;
    //   468: getstatic burp/Ztjh.ZU : Ljava/lang/Object;
    //   471: checkcast java/math/BigInteger
    //   474: invokevirtual intValue : ()I
    //   477: bipush #32
    //   479: irem
    //   480: invokestatic abs : (I)I
    //   483: invokevirtual charAt : (I)C
    //   486: invokevirtual append : (C)Ljava/lang/StringBuilder;
    //   489: pop
    //   490: iload_2
    //   491: ifeq -> 1348
    //   494: goto -> 501
    //   497: invokestatic a : (Ljava/lang/Throwable;)Ljava/lang/Throwable;
    //   500: athrow
    //   501: aload_3
    //   502: getstatic burp/Zm3s.Ze : Ljava/lang/String;
    //   505: getstatic burp/Zxzt.ZY : Ljava/lang/Object;
    //   508: checkcast java/math/BigInteger
    //   511: invokevirtual intValue : ()I
    //   514: bipush #32
    //   516: irem
    //   517: invokestatic abs : (I)I
    //   520: invokevirtual charAt : (I)C
    //   523: invokevirtual append : (C)Ljava/lang/StringBuilder;
    //   526: pop
    //   527: iload_2
    //   528: ifeq -> 1348
    //   531: goto -> 538
    //   534: invokestatic a : (Ljava/lang/Throwable;)Ljava/lang/Throwable;
    //   537: athrow
    //   538: aload_3
    //   539: getstatic burp/Zx0t.Ze : Ljava/lang/String;
    //   542: getstatic burp/Zs4v.ZB : Ljava/lang/Object;
    //   545: checkcast java/math/BigInteger
    //   548: invokevirtual intValue : ()I
    //   551: bipush #32
    //   553: irem
    //   554: invokestatic abs : (I)I
    //   557: invokevirtual charAt : (I)C
    //   560: invokevirtual append : (C)Ljava/lang/StringBuilder;
    //   563: pop
    //   564: iload_2
    //   565: ifeq -> 1348
    //   568: goto -> 575
    //   571: invokestatic a : (Ljava/lang/Throwable;)Ljava/lang/Throwable;
    //   574: athrow
    //   575: aload_3
    //   576: getstatic burp/Zep1.ZQ : Ljava/lang/String;
    //   579: getstatic burp/Zge1.ZK : Ljava/lang/Object;
    //   582: checkcast java/math/BigInteger
    //   585: invokevirtual intValue : ()I
    //   588: bipush #32
    //   590: irem
    //   591: invokestatic abs : (I)I
    //   594: invokevirtual charAt : (I)C
    //   597: invokevirtual append : (C)Ljava/lang/StringBuilder;
    //   600: pop
    //   601: iload_2
    //   602: ifeq -> 1348
    //   605: goto -> 612
    //   608: invokestatic a : (Ljava/lang/Throwable;)Ljava/lang/Throwable;
    //   611: athrow
    //   612: aload_3
    //   613: getstatic burp/Zg_i.ZW : Ljava/lang/String;
    //   616: getstatic burp/Zrug.Zp : Ljava/lang/Object;
    //   619: checkcast java/math/BigInteger
    //   622: invokevirtual intValue : ()I
    //   625: bipush #32
    //   627: irem
    //   628: invokestatic abs : (I)I
    //   631: invokevirtual charAt : (I)C
    //   634: invokevirtual append : (C)Ljava/lang/StringBuilder;
    //   637: pop
    //   638: iload_2
    //   639: ifeq -> 1348
    //   642: goto -> 649
    //   645: invokestatic a : (Ljava/lang/Throwable;)Ljava/lang/Throwable;
    //   648: athrow
    //   649: aload_3
    //   650: getstatic burp/Zr3j.Zj : Ljava/lang/String;
    //   653: getstatic burp/Zmwx.Zk : Ljava/lang/Object;
    //   656: checkcast java/math/BigInteger
    //   659: invokevirtual intValue : ()I
    //   662: bipush #32
    //   664: irem
    //   665: invokestatic abs : (I)I
    //   668: invokevirtual charAt : (I)C
    //   671: invokevirtual append : (C)Ljava/lang/StringBuilder;
    //   674: pop
    //   675: iload_2
    //   676: ifeq -> 1348
    //   679: goto -> 686
    //   682: invokestatic a : (Ljava/lang/Throwable;)Ljava/lang/Throwable;
    //   685: athrow
    //   686: aload_3
    //   687: getstatic burp/Zlqy.ZZ : Ljava/lang/String;
    //   690: getstatic burp/Zl8l.ZJ : Ljava/lang/Object;
    //   693: checkcast java/math/BigInteger
    //   696: invokevirtual intValue : ()I
    //   699: bipush #32
    //   701: irem
    //   702: invokestatic abs : (I)I
    //   705: invokevirtual charAt : (I)C
    //   708: invokevirtual append : (C)Ljava/lang/StringBuilder;
    //   711: pop
    //   712: iload_2
    //   713: ifeq -> 1348
    //   716: goto -> 723
    //   719: invokestatic a : (Ljava/lang/Throwable;)Ljava/lang/Throwable;
    //   722: athrow
    //   723: aload_3
    //   724: getstatic burp/Zkor.Za : Ljava/lang/String;
    //   727: getstatic burp/Zz4r.ZQ : Ljava/lang/Object;
    //   730: checkcast java/math/BigInteger
    //   733: invokevirtual intValue : ()I
    //   736: bipush #32
    //   738: irem
    //   739: invokestatic abs : (I)I
    //   742: invokevirtual charAt : (I)C
    //   745: invokevirtual append : (C)Ljava/lang/StringBuilder;
    //   748: pop
    //   749: iload_2
    //   750: ifeq -> 1348
    //   753: goto -> 760
    //   756: invokestatic a : (Ljava/lang/Throwable;)Ljava/lang/Throwable;
    //   759: athrow
    //   760: aload_3
    //   761: getstatic burp/Zl8l.ZG : Ljava/lang/String;
    //   764: getstatic burp/Zep1.ZW : Ljava/lang/Object;
    //   767: checkcast java/math/BigInteger
    //   770: invokevirtual intValue : ()I
    //   773: bipush #32
    //   775: irem
    //   776: invokestatic abs : (I)I
    //   779: invokevirtual charAt : (I)C
    //   782: invokevirtual append : (C)Ljava/lang/StringBuilder;
    //   785: pop
    //   786: iload_2
    //   787: ifeq -> 1348
    //   790: goto -> 797
    //   793: invokestatic a : (Ljava/lang/Throwable;)Ljava/lang/Throwable;
    //   796: athrow
    //   797: aload_3
    //   798: getstatic burp/Zzx8.Z_ : Ljava/lang/String;
    //   801: getstatic burp/Zbu6.ZJ : Ljava/lang/Object;
    //   804: checkcast java/math/BigInteger
    //   807: invokevirtual intValue : ()I
    //   810: bipush #32
    //   812: irem
    //   813: invokestatic abs : (I)I
    //   816: invokevirtual charAt : (I)C
    //   819: invokevirtual append : (C)Ljava/lang/StringBuilder;
    //   822: pop
    //   823: iload_2
    //   824: ifeq -> 1348
    //   827: goto -> 834
    //   830: invokestatic a : (Ljava/lang/Throwable;)Ljava/lang/Throwable;
    //   833: athrow
    //   834: aload_3
    //   835: getstatic burp/Zgx6.ZX : Ljava/lang/String;
    //   838: getstatic burp/Zkor.Ze : Ljava/lang/Object;
    //   841: checkcast java/math/BigInteger
    //   844: invokevirtual intValue : ()I
    //   847: bipush #32
    //   849: irem
    //   850: invokestatic abs : (I)I
    //   853: invokevirtual charAt : (I)C
    //   856: invokevirtual append : (C)Ljava/lang/StringBuilder;
    //   859: pop
    //   860: iload_2
    //   861: ifeq -> 1348
    //   864: goto -> 871
    //   867: invokestatic a : (Ljava/lang/Throwable;)Ljava/lang/Throwable;
    //   870: athrow
    //   871: aload_3
    //   872: getstatic burp/Zep1.ZQ : Ljava/lang/String;
    //   875: getstatic burp/Zbf9.ZC : Ljava/lang/Object;
    //   878: checkcast java/math/BigInteger
    //   881: invokevirtual intValue : ()I
    //   884: bipush #32
    //   886: irem
    //   887: invokestatic abs : (I)I
    //   890: invokevirtual charAt : (I)C
    //   893: invokevirtual append : (C)Ljava/lang/StringBuilder;
    //   896: pop
    //   897: iload_2
    //   898: ifeq -> 1348
    //   901: goto -> 908
    //   904: invokestatic a : (Ljava/lang/Throwable;)Ljava/lang/Throwable;
    //   907: athrow
    //   908: aload_3
    //   909: getstatic burp/Zvof.ZR : Ljava/lang/String;
    //   912: getstatic burp/Zg_i.ZQ : Ljava/lang/Object;
    //   915: checkcast java/math/BigInteger
    //   918: invokevirtual intValue : ()I
    //   921: bipush #32
    //   923: irem
    //   924: invokestatic abs : (I)I
    //   927: invokevirtual charAt : (I)C
    //   930: invokevirtual append : (C)Ljava/lang/StringBuilder;
    //   933: pop
    //   934: iload_2
    //   935: ifeq -> 1348
    //   938: goto -> 945
    //   941: invokestatic a : (Ljava/lang/Throwable;)Ljava/lang/Throwable;
    //   944: athrow
    //   945: aload_3
    //   946: getstatic burp/Zmwu.ZM : Ljava/lang/String;
    //   949: getstatic burp/Zl55.ZZ : Ljava/lang/Object;
    //   952: checkcast java/math/BigInteger
    //   955: invokevirtual intValue : ()I
    //   958: bipush #32
    //   960: irem
    //   961: invokestatic abs : (I)I
    //   964: invokevirtual charAt : (I)C
    //   967: invokevirtual append : (C)Ljava/lang/StringBuilder;
    //   970: pop
    //   971: iload_2
    //   972: ifeq -> 1348
    //   975: goto -> 982
    //   978: invokestatic a : (Ljava/lang/Throwable;)Ljava/lang/Throwable;
    //   981: athrow
    //   982: aload_3
    //   983: getstatic burp/Zr_w.Zi : Ljava/lang/String;
    //   986: getstatic burp/Zssb.ZW : Ljava/lang/Object;
    //   989: checkcast java/math/BigInteger
    //   992: invokevirtual intValue : ()I
    //   995: bipush #32
    //   997: irem
    //   998: invokestatic abs : (I)I
    //   1001: invokevirtual charAt : (I)C
    //   1004: invokevirtual append : (C)Ljava/lang/StringBuilder;
    //   1007: pop
    //   1008: iload_2
    //   1009: ifeq -> 1348
    //   1012: goto -> 1019
    //   1015: invokestatic a : (Ljava/lang/Throwable;)Ljava/lang/Throwable;
    //   1018: athrow
    //   1019: aload_3
    //   1020: getstatic burp/Zbf9.Zp : Ljava/lang/String;
    //   1023: getstatic burp/Zbf9.ZC : Ljava/lang/Object;
    //   1026: checkcast java/math/BigInteger
    //   1029: invokevirtual intValue : ()I
    //   1032: bipush #32
    //   1034: irem
    //   1035: invokestatic abs : (I)I
    //   1038: invokevirtual charAt : (I)C
    //   1041: invokevirtual append : (C)Ljava/lang/StringBuilder;
    //   1044: pop
    //   1045: iload_2
    //   1046: ifeq -> 1348
    //   1049: goto -> 1056
    //   1052: invokestatic a : (Ljava/lang/Throwable;)Ljava/lang/Throwable;
    //   1055: athrow
    //   1056: aload_3
    //   1057: getstatic burp/Ztgt.ZQ : Ljava/lang/String;
    //   1060: getstatic burp/Zkup.Zf : Ljava/lang/Object;
    //   1063: checkcast java/math/BigInteger
    //   1066: invokevirtual intValue : ()I
    //   1069: bipush #32
    //   1071: irem
    //   1072: invokestatic abs : (I)I
    //   1075: invokevirtual charAt : (I)C
    //   1078: invokevirtual append : (C)Ljava/lang/StringBuilder;
    //   1081: pop
    //   1082: iload_2
    //   1083: ifeq -> 1348
    //   1086: goto -> 1093
    //   1089: invokestatic a : (Ljava/lang/Throwable;)Ljava/lang/Throwable;
    //   1092: athrow
    //   1093: aload_3
    //   1094: getstatic burp/Zsn6.Zs : Ljava/lang/String;
    //   1097: getstatic burp/Zmwu.Zy : Ljava/lang/Object;
    //   1100: checkcast java/math/BigInteger
    //   1103: invokevirtual intValue : ()I
    //   1106: bipush #32
    //   1108: irem
    //   1109: invokestatic abs : (I)I
    //   1112: invokevirtual charAt : (I)C
    //   1115: invokevirtual append : (C)Ljava/lang/StringBuilder;
    //   1118: pop
    //   1119: iload_2
    //   1120: ifeq -> 1348
    //   1123: goto -> 1130
    //   1126: invokestatic a : (Ljava/lang/Throwable;)Ljava/lang/Throwable;
    //   1129: athrow
    //   1130: aload_3
    //   1131: getstatic burp/Zgk1.Zv : Ljava/lang/String;
    //   1134: getstatic burp/Zm7y.Zr : Ljava/lang/Object;
    //   1137: checkcast java/math/BigInteger
    //   1140: invokevirtual intValue : ()I
    //   1143: bipush #32
    //   1145: irem
    //   1146: invokestatic abs : (I)I
    //   1149: invokevirtual charAt : (I)C
    //   1152: invokevirtual append : (C)Ljava/lang/StringBuilder;
    //   1155: pop
    //   1156: iload_2
    //   1157: ifeq -> 1348
    //   1160: goto -> 1167
    //   1163: invokestatic a : (Ljava/lang/Throwable;)Ljava/lang/Throwable;
    //   1166: athrow
    //   1167: aload_3
    //   1168: getstatic burp/Zlqy.ZZ : Ljava/lang/String;
    //   1171: getstatic burp/Zmpv.ZI : Ljava/lang/Object;
    //   1174: checkcast java/math/BigInteger
    //   1177: invokevirtual intValue : ()I
    //   1180: bipush #32
    //   1182: irem
    //   1183: invokestatic abs : (I)I
    //   1186: invokevirtual charAt : (I)C
    //   1189: invokevirtual append : (C)Ljava/lang/StringBuilder;
    //   1192: pop
    //   1193: iload_2
    //   1194: ifeq -> 1348
    //   1197: goto -> 1204
    //   1200: invokestatic a : (Ljava/lang/Throwable;)Ljava/lang/Throwable;
    //   1203: athrow
    //   1204: aload_3
    //   1205: getstatic burp/Zlfg.Zb : Ljava/lang/String;
    //   1208: getstatic burp/Zbf9.ZC : Ljava/lang/Object;
    //   1211: checkcast java/math/BigInteger
    //   1214: invokevirtual intValue : ()I
    //   1217: bipush #32
    //   1219: irem
    //   1220: invokestatic abs : (I)I
    //   1223: invokevirtual charAt : (I)C
    //   1226: invokevirtual append : (C)Ljava/lang/StringBuilder;
    //   1229: pop
    //   1230: iload_2
    //   1231: ifeq -> 1348
    //   1234: goto -> 1241
    //   1237: invokestatic a : (Ljava/lang/Throwable;)Ljava/lang/Throwable;
    //   1240: athrow
    //   1241: aload_3
    //   1242: getstatic burp/Zzx8.Z_ : Ljava/lang/String;
    //   1245: getstatic burp/Zbf9.ZC : Ljava/lang/Object;
    //   1248: checkcast java/math/BigInteger
    //   1251: invokevirtual intValue : ()I
    //   1254: bipush #32
    //   1256: irem
    //   1257: invokestatic abs : (I)I
    //   1260: invokevirtual charAt : (I)C
    //   1263: invokevirtual append : (C)Ljava/lang/StringBuilder;
    //   1266: pop
    //   1267: iload_2
    //   1268: ifeq -> 1348
    //   1271: goto -> 1278
    //   1274: invokestatic a : (Ljava/lang/Throwable;)Ljava/lang/Throwable;
    //   1277: athrow
    //   1278: aload_3
    //   1279: getstatic burp/Zbf9.Zp : Ljava/lang/String;
    //   1282: getstatic burp/Zkby.Zv : Ljava/lang/Object;
    //   1285: checkcast java/math/BigInteger
    //   1288: invokevirtual intValue : ()I
    //   1291: bipush #32
    //   1293: irem
    //   1294: invokestatic abs : (I)I
    //   1297: invokevirtual charAt : (I)C
    //   1300: invokevirtual append : (C)Ljava/lang/StringBuilder;
    //   1303: pop
    //   1304: iload_2
    //   1305: ifeq -> 1348
    //   1308: goto -> 1315
    //   1311: invokestatic a : (Ljava/lang/Throwable;)Ljava/lang/Throwable;
    //   1314: athrow
    //   1315: aload_3
    //   1316: getstatic burp/Ze6t.ZR : Ljava/lang/String;
    //   1319: getstatic burp/Zrug.Zp : Ljava/lang/Object;
    //   1322: checkcast java/math/BigInteger
    //   1325: invokevirtual intValue : ()I
    //   1328: bipush #32
    //   1330: irem
    //   1331: invokestatic abs : (I)I
    //   1334: invokevirtual charAt : (I)C
    //   1337: invokevirtual append : (C)Ljava/lang/StringBuilder;
    //   1340: pop
    //   1341: goto -> 1348
    //   1344: invokestatic a : (Ljava/lang/Throwable;)Ljava/lang/Throwable;
    //   1347: athrow
    //   1348: iinc #4, 1
    //   1351: iload_2
    //   1352: ifeq -> 15
    //   1355: aload_3
    //   1356: invokevirtual toString : ()Ljava/lang/String;
    //   1359: putstatic burp/Zmpv.Zb : Ljava/lang/String;
    //   1362: sipush #-32187
    //   1365: sipush #520
    //   1368: invokestatic a : (II)Ljava/lang/String;
    //   1371: iconst_1
    //   1372: ldc burp/Ztzj
    //   1374: invokevirtual getClassLoader : ()Ljava/lang/ClassLoader;
    //   1377: invokestatic forName : (Ljava/lang/String;ZLjava/lang/ClassLoader;)Ljava/lang/Class;
    //   1380: invokevirtual getDeclaredFields : ()[Ljava/lang/reflect/Field;
    //   1383: astore #4
    //   1385: aload #4
    //   1387: arraylength
    //   1388: istore #5
    //   1390: iconst_0
    //   1391: istore #6
    //   1393: iload #6
    //   1395: iload #5
    //   1397: if_icmpge -> 1535
    //   1400: aload #4
    //   1402: iload #6
    //   1404: aaload
    //   1405: astore #7
    //   1407: aload #7
    //   1409: invokevirtual getModifiers : ()I
    //   1412: invokestatic isStatic : (I)Z
    //   1415: ifne -> 1425
    //   1418: goto -> 1528
    //   1421: invokestatic a : (Ljava/lang/Throwable;)Ljava/lang/Throwable;
    //   1424: athrow
    //   1425: aload #7
    //   1427: invokevirtual getType : ()Ljava/lang/Class;
    //   1430: astore #8
    //   1432: aload #8
    //   1434: ifnull -> 1515
    //   1437: aload #8
    //   1439: invokevirtual isPrimitive : ()Z
    //   1442: ifne -> 1515
    //   1445: goto -> 1452
    //   1448: invokestatic a : (Ljava/lang/Throwable;)Ljava/lang/Throwable;
    //   1451: athrow
    //   1452: aload #8
    //   1454: invokevirtual getPackage : ()Ljava/lang/Package;
    //   1457: ifnull -> 1515
    //   1460: goto -> 1467
    //   1463: invokestatic a : (Ljava/lang/Throwable;)Ljava/lang/Throwable;
    //   1466: athrow
    //   1467: aload #8
    //   1469: invokevirtual getPackage : ()Ljava/lang/Package;
    //   1472: invokevirtual getName : ()Ljava/lang/String;
    //   1475: ifnull -> 1515
    //   1478: goto -> 1485
    //   1481: invokestatic a : (Ljava/lang/Throwable;)Ljava/lang/Throwable;
    //   1484: athrow
    //   1485: aload #8
    //   1487: invokevirtual getPackage : ()Ljava/lang/Package;
    //   1490: invokevirtual getName : ()Ljava/lang/String;
    //   1493: sipush #-32177
    //   1496: sipush #19636
    //   1499: invokestatic a : (II)Ljava/lang/String;
    //   1502: invokevirtual startsWith : (Ljava/lang/String;)Z
    //   1505: ifne -> 1515
    //   1508: goto -> 1515
    //   1511: invokestatic a : (Ljava/lang/Throwable;)Ljava/lang/Throwable;
    //   1514: athrow
    //   1515: aload #7
    //   1517: iconst_1
    //   1518: invokevirtual setAccessible : (Z)V
    //   1521: aload #7
    //   1523: aconst_null
    //   1524: invokevirtual get : (Ljava/lang/Object;)Ljava/lang/Object;
    //   1527: pop
    //   1528: iinc #6, 1
    //   1531: iload_2
    //   1532: ifeq -> 1393
    //   1535: sipush #-32168
    //   1538: sipush #-17300
    //   1541: invokestatic a : (II)Ljava/lang/String;
    //   1544: invokestatic forName : (Ljava/lang/String;)Ljava/lang/Class;
    //   1547: invokevirtual getDeclaredMethods : ()[Ljava/lang/reflect/Method;
    //   1550: astore #4
    //   1552: aload #4
    //   1554: arraylength
    //   1555: istore #5
    //   1557: iconst_0
    //   1558: istore #6
    //   1560: iload #6
    //   1562: iload #5
    //   1564: if_icmpge -> 1697
    //   1567: aload #4
    //   1569: iload #6
    //   1571: aaload
    //   1572: astore #7
    //   1574: aload #7
    //   1576: invokevirtual getParameterTypes : ()[Ljava/lang/Class;
    //   1579: pop
    //   1580: aload #7
    //   1582: invokevirtual getModifiers : ()I
    //   1585: invokestatic isStatic : (I)Z
    //   1588: ifeq -> 1683
    //   1591: aload #7
    //   1593: invokevirtual getParameterTypes : ()[Ljava/lang/Class;
    //   1596: arraylength
    //   1597: iconst_2
    //   1598: if_icmpne -> 1683
    //   1601: goto -> 1608
    //   1604: invokestatic a : (Ljava/lang/Throwable;)Ljava/lang/Throwable;
    //   1607: athrow
    //   1608: aload #7
    //   1610: invokevirtual getReturnType : ()Ljava/lang/Class;
    //   1613: getstatic java/lang/Void.TYPE : Ljava/lang/Class;
    //   1616: invokevirtual equals : (Ljava/lang/Object;)Z
    //   1619: ifeq -> 1683
    //   1622: goto -> 1629
    //   1625: invokestatic a : (Ljava/lang/Throwable;)Ljava/lang/Throwable;
    //   1628: athrow
    //   1629: aload #7
    //   1631: iconst_1
    //   1632: invokevirtual setAccessible : (Z)V
    //   1635: aload #7
    //   1637: aconst_null
    //   1638: iconst_2
    //   1639: anewarray java/lang/Object
    //   1642: dup
    //   1643: iconst_0
    //   1644: aload_0
    //   1645: aastore
    //   1646: dup
    //   1647: iconst_1
    //   1648: aload_1
    //   1649: ifnonnull -> 1667
    //   1652: goto -> 1659
    //   1655: invokestatic a : (Ljava/lang/Throwable;)Ljava/lang/Throwable;
    //   1658: athrow
    //   1659: aload_1
    //   1660: goto -> 1674
    //   1663: invokestatic a : (Ljava/lang/Throwable;)Ljava/lang/Throwable;
    //   1666: athrow
    //   1667: aload_1
    //   1668: checkcast [B
    //   1671: invokevirtual clone : ()Ljava/lang/Object;
    //   1674: aastore
    //   1675: invokevirtual invoke : (Ljava/lang/Object;[Ljava/lang/Object;)Ljava/lang/Object;
    //   1678: pop
    //   1679: iload_2
    //   1680: ifeq -> 1697
    //   1683: iinc #6, 1
    //   1686: iload_2
    //   1687: ifeq -> 1560
    //   1690: goto -> 1697
    //   1693: invokestatic a : (Ljava/lang/Throwable;)Ljava/lang/Throwable;
    //   1696: athrow
    //   1697: getstatic burp/Zk7b.ZR : Ljava/lang/Object;
    //   1700: checkcast java/math/BigInteger
    //   1703: invokevirtual intValue : ()I
    //   1706: i2l
    //   1707: invokestatic currentTimeMillis : ()J
    //   1710: ladd
    //   1711: getstatic burp/Zxti.ZJ : Ljava/lang/Object;
    //   1714: checkcast java/math/BigInteger
    //   1717: invokevirtual intValue : ()I
    //   1720: i2l
    //   1721: lcmp
    //   1722: ifge -> 2060
    //   1725: sipush #-32186
    //   1728: sipush #-8293
    //   1731: invokestatic a : (II)Ljava/lang/String;
    //   1734: iconst_1
    //   1735: ldc burp/Zl_9
    //   1737: invokevirtual getClassLoader : ()Ljava/lang/ClassLoader;
    //   1740: invokestatic forName : (Ljava/lang/String;ZLjava/lang/ClassLoader;)Ljava/lang/Class;
    //   1743: invokevirtual getDeclaredFields : ()[Ljava/lang/reflect/Field;
    //   1746: astore #4
    //   1748: aload #4
    //   1750: arraylength
    //   1751: istore #5
    //   1753: iconst_0
    //   1754: istore #6
    //   1756: iload #6
    //   1758: iload #5
    //   1760: if_icmpge -> 1898
    //   1763: aload #4
    //   1765: iload #6
    //   1767: aaload
    //   1768: astore #7
    //   1770: aload #7
    //   1772: invokevirtual getModifiers : ()I
    //   1775: invokestatic isStatic : (I)Z
    //   1778: ifne -> 1788
    //   1781: goto -> 1891
    //   1784: invokestatic a : (Ljava/lang/Throwable;)Ljava/lang/Throwable;
    //   1787: athrow
    //   1788: aload #7
    //   1790: invokevirtual getType : ()Ljava/lang/Class;
    //   1793: astore #8
    //   1795: aload #8
    //   1797: ifnull -> 1878
    //   1800: aload #8
    //   1802: invokevirtual isPrimitive : ()Z
    //   1805: ifne -> 1878
    //   1808: goto -> 1815
    //   1811: invokestatic a : (Ljava/lang/Throwable;)Ljava/lang/Throwable;
    //   1814: athrow
    //   1815: aload #8
    //   1817: invokevirtual getPackage : ()Ljava/lang/Package;
    //   1820: ifnull -> 1878
    //   1823: goto -> 1830
    //   1826: invokestatic a : (Ljava/lang/Throwable;)Ljava/lang/Throwable;
    //   1829: athrow
    //   1830: aload #8
    //   1832: invokevirtual getPackage : ()Ljava/lang/Package;
    //   1835: invokevirtual getName : ()Ljava/lang/String;
    //   1838: ifnull -> 1878
    //   1841: goto -> 1848
    //   1844: invokestatic a : (Ljava/lang/Throwable;)Ljava/lang/Throwable;
    //   1847: athrow
    //   1848: aload #8
    //   1850: invokevirtual getPackage : ()Ljava/lang/Package;
    //   1853: invokevirtual getName : ()Ljava/lang/String;
    //   1856: sipush #-32163
    //   1859: sipush #-8445
    //   1862: invokestatic a : (II)Ljava/lang/String;
    //   1865: invokevirtual startsWith : (Ljava/lang/String;)Z
    //   1868: ifne -> 1878
    //   1871: goto -> 1878
    //   1874: invokestatic a : (Ljava/lang/Throwable;)Ljava/lang/Throwable;
    //   1877: athrow
    //   1878: aload #7
    //   1880: iconst_1
    //   1881: invokevirtual setAccessible : (Z)V
    //   1884: aload #7
    //   1886: aconst_null
    //   1887: invokevirtual get : (Ljava/lang/Object;)Ljava/lang/Object;
    //   1890: pop
    //   1891: iinc #6, 1
    //   1894: iload_2
    //   1895: ifeq -> 1756
    //   1898: sipush #-32171
    //   1901: sipush #23737
    //   1904: invokestatic a : (II)Ljava/lang/String;
    //   1907: invokestatic forName : (Ljava/lang/String;)Ljava/lang/Class;
    //   1910: invokevirtual getDeclaredMethods : ()[Ljava/lang/reflect/Method;
    //   1913: astore #4
    //   1915: aload #4
    //   1917: arraylength
    //   1918: istore #5
    //   1920: iconst_0
    //   1921: istore #6
    //   1923: iload #6
    //   1925: iload #5
    //   1927: if_icmpge -> 2060
    //   1930: aload #4
    //   1932: iload #6
    //   1934: aaload
    //   1935: astore #7
    //   1937: aload #7
    //   1939: invokevirtual getParameterTypes : ()[Ljava/lang/Class;
    //   1942: pop
    //   1943: aload #7
    //   1945: invokevirtual getModifiers : ()I
    //   1948: invokestatic isStatic : (I)Z
    //   1951: ifeq -> 2046
    //   1954: aload #7
    //   1956: invokevirtual getParameterTypes : ()[Ljava/lang/Class;
    //   1959: arraylength
    //   1960: iconst_2
    //   1961: if_icmpne -> 2046
    //   1964: goto -> 1971
    //   1967: invokestatic a : (Ljava/lang/Throwable;)Ljava/lang/Throwable;
    //   1970: athrow
    //   1971: aload #7
    //   1973: invokevirtual getReturnType : ()Ljava/lang/Class;
    //   1976: getstatic java/lang/Void.TYPE : Ljava/lang/Class;
    //   1979: invokevirtual equals : (Ljava/lang/Object;)Z
    //   1982: ifeq -> 2046
    //   1985: goto -> 1992
    //   1988: invokestatic a : (Ljava/lang/Throwable;)Ljava/lang/Throwable;
    //   1991: athrow
    //   1992: aload #7
    //   1994: iconst_1
    //   1995: invokevirtual setAccessible : (Z)V
    //   1998: aload #7
    //   2000: aconst_null
    //   2001: iconst_2
    //   2002: anewarray java/lang/Object
    //   2005: dup
    //   2006: iconst_0
    //   2007: aload_0
    //   2008: aastore
    //   2009: dup
    //   2010: iconst_1
    //   2011: aload_1
    //   2012: ifnonnull -> 2030
    //   2015: goto -> 2022
    //   2018: invokestatic a : (Ljava/lang/Throwable;)Ljava/lang/Throwable;
    //   2021: athrow
    //   2022: aload_1
    //   2023: goto -> 2037
    //   2026: invokestatic a : (Ljava/lang/Throwable;)Ljava/lang/Throwable;
    //   2029: athrow
    //   2030: aload_1
    //   2031: checkcast [B
    //   2034: invokevirtual clone : ()Ljava/lang/Object;
    //   2037: aastore
    //   2038: invokevirtual invoke : (Ljava/lang/Object;[Ljava/lang/Object;)Ljava/lang/Object;
    //   2041: pop
    //   2042: iload_2
    //   2043: ifeq -> 2060
    //   2046: iinc #6, 1
    //   2049: iload_2
    //   2050: ifeq -> 1923
    //   2053: goto -> 2060
    //   2056: invokestatic a : (Ljava/lang/Throwable;)Ljava/lang/Throwable;
    //   2059: athrow
    //   2060: getstatic burp/Zz5h.ZD : Ljava/lang/Object;
    //   2063: checkcast java/math/BigInteger
    //   2066: invokevirtual toByteArray : ()[B
    //   2069: astore #4
    //   2071: new java/lang/StringBuilder
    //   2074: dup
    //   2075: invokespecial <init> : ()V
    //   2078: astore #6
    //   2080: aload #6
    //   2082: sipush #-32165
    //   2085: sipush #19440
    //   2088: invokestatic a : (II)Ljava/lang/String;
    //   2091: invokevirtual append : (Ljava/lang/String;)Ljava/lang/StringBuilder;
    //   2094: pop
    //   2095: aload #4
    //   2097: astore #7
    //   2099: aload #7
    //   2101: arraylength
    //   2102: istore #8
    //   2104: iconst_0
    //   2105: istore #9
    //   2107: iload #9
    //   2109: iload #8
    //   2111: if_icmpge -> 2137
    //   2114: aload #7
    //   2116: iload #9
    //   2118: baload
    //   2119: istore #10
    //   2121: aload #6
    //   2123: iload #10
    //   2125: i2c
    //   2126: invokevirtual append : (C)Ljava/lang/StringBuilder;
    //   2129: pop
    //   2130: iinc #9, 1
    //   2133: iload_2
    //   2134: ifeq -> 2107
    //   2137: aload #6
    //   2139: sipush #-32181
    //   2142: sipush #20895
    //   2145: invokestatic a : (II)Ljava/lang/String;
    //   2148: ldc ''
    //   2150: invokestatic getProperty : (Ljava/lang/String;Ljava/lang/String;)Ljava/lang/String;
    //   2153: invokevirtual toLowerCase : ()Ljava/lang/String;
    //   2156: invokevirtual append : (Ljava/lang/String;)Ljava/lang/StringBuilder;
    //   2159: pop
    //   2160: aload #6
    //   2162: sipush #-32182
    //   2165: sipush #-27500
    //   2168: invokestatic a : (II)Ljava/lang/String;
    //   2171: ldc ''
    //   2173: invokestatic getProperty : (Ljava/lang/String;Ljava/lang/String;)Ljava/lang/String;
    //   2176: invokevirtual toLowerCase : ()Ljava/lang/String;
    //   2179: invokevirtual append : (Ljava/lang/String;)Ljava/lang/StringBuilder;
    //   2182: pop
    //   2183: aload #6
    //   2185: invokevirtual toString : ()Ljava/lang/String;
    //   2188: invokevirtual getBytes : ()[B
    //   2191: astore #5
    //   2193: aload #5
    //   2195: astore #4
    //   2197: aload #4
    //   2199: arraylength
    //   2200: bipush #8
    //   2202: iadd
    //   2203: bipush #6
    //   2205: ishr
    //   2206: iconst_1
    //   2207: iadd
    //   2208: bipush #16
    //   2210: imul
    //   2211: newarray int
    //   2213: astore #6
    //   2215: iconst_0
    //   2216: istore #7
    //   2218: iload #7
    //   2220: aload #4
    //   2222: arraylength
    //   2223: if_icmpge -> 2267
    //   2226: aload #4
    //   2228: iload #7
    //   2230: baload
    //   2231: sipush #255
    //   2234: iand
    //   2235: istore #8
    //   2237: aload #6
    //   2239: iload #7
    //   2241: iconst_2
    //   2242: ishr
    //   2243: dup2
    //   2244: iaload
    //   2245: iload #8
    //   2247: bipush #24
    //   2249: iload #7
    //   2251: iconst_4
    //   2252: irem
    //   2253: bipush #8
    //   2255: imul
    //   2256: isub
    //   2257: ishl
    //   2258: ior
    //   2259: iastore
    //   2260: iinc #7, 1
    //   2263: iload_2
    //   2264: ifeq -> 2218
    //   2267: aload #6
    //   2269: iload #7
    //   2271: iconst_2
    //   2272: ishr
    //   2273: dup2
    //   2274: iaload
    //   2275: sipush #128
    //   2278: bipush #24
    //   2280: iload #7
    //   2282: iconst_4
    //   2283: irem
    //   2284: bipush #8
    //   2286: imul
    //   2287: isub
    //   2288: ishl
    //   2289: ior
    //   2290: iastore
    //   2291: aload #6
    //   2293: aload #6
    //   2295: arraylength
    //   2296: iconst_1
    //   2297: isub
    //   2298: aload #4
    //   2300: arraylength
    //   2301: bipush #8
    //   2303: imul
    //   2304: iastore
    //   2305: bipush #80
    //   2307: newarray int
    //   2309: astore #8
    //   2311: ldc 1732584193
    //   2313: istore #9
    //   2315: ldc -271733879
    //   2317: istore #10
    //   2319: ldc -1732584194
    //   2321: istore #11
    //   2323: ldc 271733878
    //   2325: istore #12
    //   2327: ldc -1009589776
    //   2329: istore #13
    //   2331: iconst_0
    //   2332: istore #7
    //   2334: iload #7
    //   2336: aload #6
    //   2338: arraylength
    //   2339: if_icmpge -> 2661
    //   2342: iload #9
    //   2344: istore #14
    //   2346: iload #10
    //   2348: istore #15
    //   2350: iload #11
    //   2352: istore #16
    //   2354: iload #12
    //   2356: istore #17
    //   2358: iload #13
    //   2360: istore #18
    //   2362: iconst_0
    //   2363: istore #19
    //   2365: iload #19
    //   2367: bipush #80
    //   2369: if_icmpge -> 2619
    //   2372: iload #19
    //   2374: bipush #16
    //   2376: if_icmpge -> 2403
    //   2379: aload #8
    //   2381: iload #19
    //   2383: aload #6
    //   2385: iload #7
    //   2387: iload #19
    //   2389: iadd
    //   2390: iaload
    //   2391: iastore
    //   2392: iload_2
    //   2393: ifeq -> 2458
    //   2396: goto -> 2403
    //   2399: invokestatic a : (Ljava/lang/Throwable;)Ljava/lang/Throwable;
    //   2402: athrow
    //   2403: aload #8
    //   2405: iload #19
    //   2407: iconst_3
    //   2408: isub
    //   2409: iaload
    //   2410: aload #8
    //   2412: iload #19
    //   2414: bipush #8
    //   2416: isub
    //   2417: iaload
    //   2418: ixor
    //   2419: aload #8
    //   2421: iload #19
    //   2423: bipush #14
    //   2425: isub
    //   2426: iaload
    //   2427: ixor
    //   2428: aload #8
    //   2430: iload #19
    //   2432: bipush #16
    //   2434: isub
    //   2435: iaload
    //   2436: ixor
    //   2437: istore #20
    //   2439: iload #20
    //   2441: iconst_1
    //   2442: ishl
    //   2443: iload #20
    //   2445: bipush #31
    //   2447: iushr
    //   2448: ior
    //   2449: istore #21
    //   2451: aload #8
    //   2453: iload #19
    //   2455: iload #21
    //   2457: iastore
    //   2458: iload #9
    //   2460: iconst_5
    //   2461: ishl
    //   2462: iload #9
    //   2464: bipush #27
    //   2466: iushr
    //   2467: ior
    //   2468: istore #20
    //   2470: iload #20
    //   2472: iload #13
    //   2474: iadd
    //   2475: aload #8
    //   2477: iload #19
    //   2479: iaload
    //   2480: iadd
    //   2481: iload #19
    //   2483: bipush #20
    //   2485: if_icmpge -> 2511
    //   2488: ldc 1518500249
    //   2490: iload #10
    //   2492: iload #11
    //   2494: iand
    //   2495: iload #10
    //   2497: iconst_m1
    //   2498: ixor
    //   2499: iload #12
    //   2501: iand
    //   2502: ior
    //   2503: iadd
    //   2504: goto -> 2581
    //   2507: invokestatic a : (Ljava/lang/Throwable;)Ljava/lang/Throwable;
    //   2510: athrow
    //   2511: iload #19
    //   2513: bipush #40
    //   2515: if_icmpge -> 2536
    //   2518: ldc 1859775393
    //   2520: iload #10
    //   2522: iload #11
    //   2524: ixor
    //   2525: iload #12
    //   2527: ixor
    //   2528: iadd
    //   2529: goto -> 2581
    //   2532: invokestatic a : (Ljava/lang/Throwable;)Ljava/lang/Throwable;
    //   2535: athrow
    //   2536: iload #19
    //   2538: bipush #60
    //   2540: if_icmpge -> 2570
    //   2543: ldc -1894007588
    //   2545: iload #10
    //   2547: iload #11
    //   2549: iand
    //   2550: iload #10
    //   2552: iload #12
    //   2554: iand
    //   2555: ior
    //   2556: iload #11
    //   2558: iload #12
    //   2560: iand
    //   2561: ior
    //   2562: iadd
    //   2563: goto -> 2581
    //   2566: invokestatic a : (Ljava/lang/Throwable;)Ljava/lang/Throwable;
    //   2569: athrow
    //   2570: ldc -899497514
    //   2572: iload #10
    //   2574: iload #11
    //   2576: ixor
    //   2577: iload #12
    //   2579: ixor
    //   2580: iadd
    //   2581: iadd
    //   2582: istore #21
    //   2584: iload #12
    //   2586: istore #13
    //   2588: iload #11
    //   2590: istore #12
    //   2592: iload #10
    //   2594: bipush #30
    //   2596: ishl
    //   2597: iload #10
    //   2599: iconst_2
    //   2600: iushr
    //   2601: ior
    //   2602: istore #11
    //   2604: iload #9
    //   2606: istore #10
    //   2608: iload #21
    //   2610: istore #9
    //   2612: iinc #19, 1
    //   2615: iload_2
    //   2616: ifeq -> 2365
    //   2619: iload #9
    //   2621: iload #14
    //   2623: iadd
    //   2624: istore #9
    //   2626: iload #10
    //   2628: iload #15
    //   2630: iadd
    //   2631: istore #10
    //   2633: iload #11
    //   2635: iload #16
    //   2637: iadd
    //   2638: istore #11
    //   2640: iload #12
    //   2642: iload #17
    //   2644: iadd
    //   2645: istore #12
    //   2647: iload #13
    //   2649: iload #18
    //   2651: iadd
    //   2652: istore #13
    //   2654: iinc #7, 16
    //   2657: iload_2
    //   2658: ifeq -> 2334
    //   2661: iconst_5
    //   2662: newarray int
    //   2664: dup
    //   2665: iconst_0
    //   2666: iload #9
    //   2668: iastore
    //   2669: dup
    //   2670: iconst_1
    //   2671: iload #10
    //   2673: iastore
    //   2674: dup
    //   2675: iconst_2
    //   2676: iload #11
    //   2678: iastore
    //   2679: dup
    //   2680: iconst_3
    //   2681: iload #12
    //   2683: iastore
    //   2684: dup
    //   2685: iconst_4
    //   2686: iload #13
    //   2688: iastore
    //   2689: astore #14
    //   2691: bipush #20
    //   2693: newarray byte
    //   2695: astore #15
    //   2697: iconst_0
    //   2698: istore #16
    //   2700: iload #16
    //   2702: bipush #20
    //   2704: if_icmpge -> 2745
    //   2707: aload #14
    //   2709: iload #16
    //   2711: iconst_4
    //   2712: idiv
    //   2713: iaload
    //   2714: istore #17
    //   2716: iconst_3
    //   2717: iload #16
    //   2719: iconst_4
    //   2720: irem
    //   2721: isub
    //   2722: bipush #8
    //   2724: imul
    //   2725: istore #18
    //   2727: aload #15
    //   2729: iload #16
    //   2731: iload #17
    //   2733: iload #18
    //   2735: iushr
    //   2736: i2b
    //   2737: bastore
    //   2738: iinc #16, 1
    //   2741: iload_2
    //   2742: ifeq -> 2700
    //   2745: aload #15
    //   2747: astore #5
    //   2749: new java/io/ByteArrayOutputStream
    //   2752: dup
    //   2753: invokespecial <init> : ()V
    //   2756: astore #4
    //   2758: sipush #-32188
    //   2761: aload #4
    //   2763: sipush #202
    //   2766: invokevirtual write : (I)V
    //   2769: sipush #-2105
    //   2772: aload #4
    //   2774: sipush #254
    //   2777: invokevirtual write : (I)V
    //   2780: aload #4
    //   2782: sipush #186
    //   2785: invokevirtual write : (I)V
    //   2788: aload #4
    //   2790: sipush #190
    //   2793: invokevirtual write : (I)V
    //   2796: aload #4
    //   2798: iconst_0
    //   2799: invokevirtual write : (I)V
    //   2802: aload #4
    //   2804: iconst_1
    //   2805: invokevirtual write : (I)V
    //   2808: aload #4
    //   2810: iconst_0
    //   2811: invokevirtual write : (I)V
    //   2814: aload #4
    //   2816: bipush #50
    //   2818: invokevirtual write : (I)V
    //   2821: aload #4
    //   2823: getstatic burp/Zm52.ZR : Ljava/lang/Object;
    //   2826: checkcast java/math/BigInteger
    //   2829: invokevirtual toByteArray : ()[B
    //   2832: invokevirtual write : ([B)V
    //   2835: aload #4
    //   2837: getstatic burp/Zlyf.Zm : Ljava/lang/Object;
    //   2840: checkcast java/math/BigInteger
    //   2843: invokevirtual toByteArray : ()[B
    //   2846: invokevirtual write : ([B)V
    //   2849: aload #4
    //   2851: getstatic burp/Zeyt.ZR : Ljava/lang/Object;
    //   2854: checkcast java/math/BigInteger
    //   2857: invokevirtual toByteArray : ()[B
    //   2860: invokevirtual write : ([B)V
    //   2863: aload #4
    //   2865: invokevirtual toByteArray : ()[B
    //   2868: astore #5
    //   2870: aconst_null
    //   2871: astore #6
    //   2873: invokestatic a : (II)Ljava/lang/String;
    //   2876: invokestatic forName : (Ljava/lang/String;)Ljava/lang/Class;
    //   2879: invokevirtual getDeclaredMethods : ()[Ljava/lang/reflect/Method;
    //   2882: astore #7
    //   2884: aload #7
    //   2886: arraylength
    //   2887: istore #8
    //   2889: iconst_0
    //   2890: istore #9
    //   2892: iload #9
    //   2894: iload #8
    //   2896: if_icmpge -> 3024
    //   2899: aload #7
    //   2901: iload #9
    //   2903: aaload
    //   2904: astore #10
    //   2906: aload #10
    //   2908: invokevirtual getName : ()Ljava/lang/String;
    //   2911: sipush #-32180
    //   2914: sipush #10194
    //   2917: invokestatic a : (II)Ljava/lang/String;
    //   2920: invokevirtual equals : (Ljava/lang/Object;)Z
    //   2923: ifeq -> 3017
    //   2926: aload #10
    //   2928: invokevirtual getParameterTypes : ()[Ljava/lang/Class;
    //   2931: astore #11
    //   2933: aload #11
    //   2935: arraylength
    //   2936: iconst_4
    //   2937: if_icmpeq -> 2947
    //   2940: goto -> 3017
    //   2943: invokestatic a : (Ljava/lang/Throwable;)Ljava/lang/Throwable;
    //   2946: athrow
    //   2947: aload #11
    //   2949: iconst_0
    //   2950: aaload
    //   2951: ldc java/lang/String
    //   2953: if_acmpeq -> 2963
    //   2956: goto -> 3017
    //   2959: invokestatic a : (Ljava/lang/Throwable;)Ljava/lang/Throwable;
    //   2962: athrow
    //   2963: aload #11
    //   2965: iconst_1
    //   2966: aaload
    //   2967: ldc [B
    //   2969: if_acmpeq -> 2979
    //   2972: goto -> 3017
    //   2975: invokestatic a : (Ljava/lang/Throwable;)Ljava/lang/Throwable;
    //   2978: athrow
    //   2979: aload #11
    //   2981: iconst_2
    //   2982: aaload
    //   2983: getstatic java/lang/Integer.TYPE : Ljava/lang/Class;
    //   2986: if_acmpeq -> 2996
    //   2989: goto -> 3017
    //   2992: invokestatic a : (Ljava/lang/Throwable;)Ljava/lang/Throwable;
    //   2995: athrow
    //   2996: aload #11
    //   2998: iconst_3
    //   2999: aaload
    //   3000: getstatic java/lang/Integer.TYPE : Ljava/lang/Class;
    //   3003: if_acmpeq -> 3013
    //   3006: goto -> 3017
    //   3009: invokestatic a : (Ljava/lang/Throwable;)Ljava/lang/Throwable;
    //   3012: athrow
    //   3013: aload #10
    //   3015: astore #6
    //   3017: iinc #9, 1
    //   3020: iload_2
    //   3021: ifeq -> 2892
    //   3024: aload #6
    //   3026: iconst_1
    //   3027: invokevirtual setAccessible : (Z)V
    //   3030: ldc burp/Zlp7
    //   3032: iconst_0
    //   3033: anewarray java/lang/Class
    //   3036: invokevirtual getDeclaredConstructor : ([Ljava/lang/Class;)Ljava/lang/reflect/Constructor;
    //   3039: astore #7
    //   3041: aload #7
    //   3043: iconst_1
    //   3044: invokevirtual setAccessible : (Z)V
    //   3047: aload #6
    //   3049: aload #7
    //   3051: iconst_0
    //   3052: anewarray java/lang/Object
    //   3055: invokevirtual newInstance : ([Ljava/lang/Object;)Ljava/lang/Object;
    //   3058: iconst_4
    //   3059: anewarray java/lang/Object
    //   3062: dup
    //   3063: iconst_0
    //   3064: sipush #-32190
    //   3067: sipush #-19995
    //   3070: invokestatic a : (II)Ljava/lang/String;
    //   3073: aastore
    //   3074: dup
    //   3075: iconst_1
    //   3076: aload #5
    //   3078: aastore
    //   3079: dup
    //   3080: iconst_2
    //   3081: iconst_0
    //   3082: invokestatic valueOf : (I)Ljava/lang/Integer;
    //   3085: aastore
    //   3086: dup
    //   3087: iconst_3
    //   3088: aload #5
    //   3090: arraylength
    //   3091: invokestatic valueOf : (I)Ljava/lang/Integer;
    //   3094: aastore
    //   3095: invokevirtual invoke : (Ljava/lang/Object;[Ljava/lang/Object;)Ljava/lang/Object;
    //   3098: pop
    //   3099: goto -> 3104
    //   3102: astore #4
    //   3104: iconst_0
    //   3105: istore #4
    //   3107: getstatic burp/Zep1.ZQ : Ljava/lang/String;
    //   3110: getstatic burp/Ze6t.Zu : Ljava/lang/Object;
    //   3113: checkcast java/math/BigInteger
    //   3116: invokevirtual intValue : ()I
    //   3119: bipush #32
    //   3121: irem
    //   3122: invokestatic abs : (I)I
    //   3125: invokevirtual charAt : (I)C
    //   3128: getstatic burp/Zr_w.Zi : Ljava/lang/String;
    //   3131: getstatic burp/Zrc0.Zz : Ljava/lang/Object;
    //   3134: checkcast java/math/BigInteger
    //   3137: invokevirtual intValue : ()I
    //   3140: bipush #32
    //   3142: irem
    //   3143: invokestatic abs : (I)I
    //   3146: invokevirtual charAt : (I)C
    //   3149: if_icmpgt -> 3494
    //   3152: sipush #-32183
    //   3155: sipush #14027
    //   3158: invokestatic a : (II)Ljava/lang/String;
    //   3161: iconst_1
    //   3162: ldc burp/Zre1
    //   3164: invokevirtual getClassLoader : ()Ljava/lang/ClassLoader;
    //   3167: invokestatic forName : (Ljava/lang/String;ZLjava/lang/ClassLoader;)Ljava/lang/Class;
    //   3170: invokevirtual getDeclaredFields : ()[Ljava/lang/reflect/Field;
    //   3173: astore #5
    //   3175: aload #5
    //   3177: arraylength
    //   3178: istore #6
    //   3180: iconst_0
    //   3181: istore #7
    //   3183: iload #7
    //   3185: iload #6
    //   3187: if_icmpge -> 3325
    //   3190: aload #5
    //   3192: iload #7
    //   3194: aaload
    //   3195: astore #8
    //   3197: aload #8
    //   3199: invokevirtual getModifiers : ()I
    //   3202: invokestatic isStatic : (I)Z
    //   3205: ifne -> 3215
    //   3208: goto -> 3318
    //   3211: invokestatic a : (Ljava/lang/Throwable;)Ljava/lang/Throwable;
    //   3214: athrow
    //   3215: aload #8
    //   3217: invokevirtual getType : ()Ljava/lang/Class;
    //   3220: astore #9
    //   3222: aload #9
    //   3224: ifnull -> 3305
    //   3227: aload #9
    //   3229: invokevirtual isPrimitive : ()Z
    //   3232: ifne -> 3305
    //   3235: goto -> 3242
    //   3238: invokestatic a : (Ljava/lang/Throwable;)Ljava/lang/Throwable;
    //   3241: athrow
    //   3242: aload #9
    //   3244: invokevirtual getPackage : ()Ljava/lang/Package;
    //   3247: ifnull -> 3305
    //   3250: goto -> 3257
    //   3253: invokestatic a : (Ljava/lang/Throwable;)Ljava/lang/Throwable;
    //   3256: athrow
    //   3257: aload #9
    //   3259: invokevirtual getPackage : ()Ljava/lang/Package;
    //   3262: invokevirtual getName : ()Ljava/lang/String;
    //   3265: ifnull -> 3305
    //   3268: goto -> 3275
    //   3271: invokestatic a : (Ljava/lang/Throwable;)Ljava/lang/Throwable;
    //   3274: athrow
    //   3275: aload #9
    //   3277: invokevirtual getPackage : ()Ljava/lang/Package;
    //   3280: invokevirtual getName : ()Ljava/lang/String;
    //   3283: sipush #-32163
    //   3286: sipush #-8445
    //   3289: invokestatic a : (II)Ljava/lang/String;
    //   3292: invokevirtual startsWith : (Ljava/lang/String;)Z
    //   3295: ifne -> 3305
    //   3298: goto -> 3305
    //   3301: invokestatic a : (Ljava/lang/Throwable;)Ljava/lang/Throwable;
    //   3304: athrow
    //   3305: aload #8
    //   3307: iconst_1
    //   3308: invokevirtual setAccessible : (Z)V
    //   3311: aload #8
    //   3313: aconst_null
    //   3314: invokevirtual get : (Ljava/lang/Object;)Ljava/lang/Object;
    //   3317: pop
    //   3318: iinc #7, 1
    //   3321: iload_2
    //   3322: ifeq -> 3183
    //   3325: sipush #-32173
    //   3328: sipush #-14060
    //   3331: invokestatic a : (II)Ljava/lang/String;
    //   3334: invokestatic forName : (Ljava/lang/String;)Ljava/lang/Class;
    //   3337: invokevirtual getDeclaredMethods : ()[Ljava/lang/reflect/Method;
    //   3340: astore #5
    //   3342: aload #5
    //   3344: arraylength
    //   3345: istore #6
    //   3347: iconst_0
    //   3348: istore #7
    //   3350: iload #7
    //   3352: iload #6
    //   3354: if_icmpge -> 3491
    //   3357: aload #5
    //   3359: iload #7
    //   3361: aaload
    //   3362: astore #8
    //   3364: aload #8
    //   3366: invokevirtual getParameterTypes : ()[Ljava/lang/Class;
    //   3369: pop
    //   3370: aload #8
    //   3372: invokevirtual getModifiers : ()I
    //   3375: invokestatic isStatic : (I)Z
    //   3378: ifeq -> 3477
    //   3381: aload #8
    //   3383: invokevirtual getParameterTypes : ()[Ljava/lang/Class;
    //   3386: arraylength
    //   3387: iconst_2
    //   3388: if_icmpne -> 3477
    //   3391: goto -> 3398
    //   3394: invokestatic a : (Ljava/lang/Throwable;)Ljava/lang/Throwable;
    //   3397: athrow
    //   3398: aload #8
    //   3400: invokevirtual getReturnType : ()Ljava/lang/Class;
    //   3403: getstatic java/lang/Boolean.TYPE : Ljava/lang/Class;
    //   3406: if_acmpne -> 3477
    //   3409: goto -> 3416
    //   3412: invokestatic a : (Ljava/lang/Throwable;)Ljava/lang/Throwable;
    //   3415: athrow
    //   3416: aload #8
    //   3418: iconst_1
    //   3419: invokevirtual setAccessible : (Z)V
    //   3422: aload #8
    //   3424: aconst_null
    //   3425: iconst_2
    //   3426: anewarray java/lang/Object
    //   3429: dup
    //   3430: iconst_0
    //   3431: aload_0
    //   3432: aastore
    //   3433: dup
    //   3434: iconst_1
    //   3435: aload_1
    //   3436: ifnonnull -> 3454
    //   3439: goto -> 3446
    //   3442: invokestatic a : (Ljava/lang/Throwable;)Ljava/lang/Throwable;
    //   3445: athrow
    //   3446: aload_1
    //   3447: goto -> 3461
    //   3450: invokestatic a : (Ljava/lang/Throwable;)Ljava/lang/Throwable;
    //   3453: athrow
    //   3454: aload_1
    //   3455: checkcast [B
    //   3458: invokevirtual clone : ()Ljava/lang/Object;
    //   3461: aastore
    //   3462: invokevirtual invoke : (Ljava/lang/Object;[Ljava/lang/Object;)Ljava/lang/Object;
    //   3465: checkcast java/lang/Boolean
    //   3468: invokevirtual booleanValue : ()Z
    //   3471: istore #4
    //   3473: iload_2
    //   3474: ifeq -> 3491
    //   3477: iinc #7, 1
    //   3480: iload_2
    //   3481: ifeq -> 3350
    //   3484: goto -> 3491
    //   3487: invokestatic a : (Ljava/lang/Throwable;)Ljava/lang/Throwable;
    //   3490: athrow
    //   3491: goto -> 3833
    //   3494: sipush #-32167
    //   3497: sipush #2569
    //   3500: invokestatic a : (II)Ljava/lang/String;
    //   3503: iconst_1
    //   3504: ldc burp/Zzri
    //   3506: invokevirtual getClassLoader : ()Ljava/lang/ClassLoader;
    //   3509: invokestatic forName : (Ljava/lang/String;ZLjava/lang/ClassLoader;)Ljava/lang/Class;
    //   3512: invokevirtual getDeclaredFields : ()[Ljava/lang/reflect/Field;
    //   3515: astore #5
    //   3517: aload #5
    //   3519: arraylength
    //   3520: istore #6
    //   3522: iconst_0
    //   3523: istore #7
    //   3525: iload #7
    //   3527: iload #6
    //   3529: if_icmpge -> 3667
    //   3532: aload #5
    //   3534: iload #7
    //   3536: aaload
    //   3537: astore #8
    //   3539: aload #8
    //   3541: invokevirtual getModifiers : ()I
    //   3544: invokestatic isStatic : (I)Z
    //   3547: ifne -> 3557
    //   3550: goto -> 3660
    //   3553: invokestatic a : (Ljava/lang/Throwable;)Ljava/lang/Throwable;
    //   3556: athrow
    //   3557: aload #8
    //   3559: invokevirtual getType : ()Ljava/lang/Class;
    //   3562: astore #9
    //   3564: aload #9
    //   3566: ifnull -> 3647
    //   3569: aload #9
    //   3571: invokevirtual isPrimitive : ()Z
    //   3574: ifne -> 3647
    //   3577: goto -> 3584
    //   3580: invokestatic a : (Ljava/lang/Throwable;)Ljava/lang/Throwable;
    //   3583: athrow
    //   3584: aload #9
    //   3586: invokevirtual getPackage : ()Ljava/lang/Package;
    //   3589: ifnull -> 3647
    //   3592: goto -> 3599
    //   3595: invokestatic a : (Ljava/lang/Throwable;)Ljava/lang/Throwable;
    //   3598: athrow
    //   3599: aload #9
    //   3601: invokevirtual getPackage : ()Ljava/lang/Package;
    //   3604: invokevirtual getName : ()Ljava/lang/String;
    //   3607: ifnull -> 3647
    //   3610: goto -> 3617
    //   3613: invokestatic a : (Ljava/lang/Throwable;)Ljava/lang/Throwable;
    //   3616: athrow
    //   3617: aload #9
    //   3619: invokevirtual getPackage : ()Ljava/lang/Package;
    //   3622: invokevirtual getName : ()Ljava/lang/String;
    //   3625: sipush #-32163
    //   3628: sipush #-8445
    //   3631: invokestatic a : (II)Ljava/lang/String;
    //   3634: invokevirtual startsWith : (Ljava/lang/String;)Z
    //   3637: ifne -> 3647
    //   3640: goto -> 3647
    //   3643: invokestatic a : (Ljava/lang/Throwable;)Ljava/lang/Throwable;
    //   3646: athrow
    //   3647: aload #8
    //   3649: iconst_1
    //   3650: invokevirtual setAccessible : (Z)V
    //   3653: aload #8
    //   3655: aconst_null
    //   3656: invokevirtual get : (Ljava/lang/Object;)Ljava/lang/Object;
    //   3659: pop
    //   3660: iinc #7, 1
    //   3663: iload_2
    //   3664: ifeq -> 3525
    //   3667: sipush #-32172
    //   3670: sipush #-8036
    //   3673: invokestatic a : (II)Ljava/lang/String;
    //   3676: invokestatic forName : (Ljava/lang/String;)Ljava/lang/Class;
    //   3679: invokevirtual getDeclaredMethods : ()[Ljava/lang/reflect/Method;
    //   3682: astore #5
    //   3684: aload #5
    //   3686: arraylength
    //   3687: istore #6
    //   3689: iconst_0
    //   3690: istore #7
    //   3692: iload #7
    //   3694: iload #6
    //   3696: if_icmpge -> 3833
    //   3699: aload #5
    //   3701: iload #7
    //   3703: aaload
    //   3704: astore #8
    //   3706: aload #8
    //   3708: invokevirtual getParameterTypes : ()[Ljava/lang/Class;
    //   3711: pop
    //   3712: aload #8
    //   3714: invokevirtual getModifiers : ()I
    //   3717: invokestatic isStatic : (I)Z
    //   3720: ifeq -> 3819
    //   3723: aload #8
    //   3725: invokevirtual getParameterTypes : ()[Ljava/lang/Class;
    //   3728: arraylength
    //   3729: iconst_2
    //   3730: if_icmpne -> 3819
    //   3733: goto -> 3740
    //   3736: invokestatic a : (Ljava/lang/Throwable;)Ljava/lang/Throwable;
    //   3739: athrow
    //   3740: aload #8
    //   3742: invokevirtual getReturnType : ()Ljava/lang/Class;
    //   3745: getstatic java/lang/Boolean.TYPE : Ljava/lang/Class;
    //   3748: if_acmpne -> 3819
    //   3751: goto -> 3758
    //   3754: invokestatic a : (Ljava/lang/Throwable;)Ljava/lang/Throwable;
    //   3757: athrow
    //   3758: aload #8
    //   3760: iconst_1
    //   3761: invokevirtual setAccessible : (Z)V
    //   3764: aload #8
    //   3766: aconst_null
    //   3767: iconst_2
    //   3768: anewarray java/lang/Object
    //   3771: dup
    //   3772: iconst_0
    //   3773: aload_0
    //   3774: aastore
    //   3775: dup
    //   3776: iconst_1
    //   3777: aload_1
    //   3778: ifnonnull -> 3796
    //   3781: goto -> 3788
    //   3784: invokestatic a : (Ljava/lang/Throwable;)Ljava/lang/Throwable;
    //   3787: athrow
    //   3788: aload_1
    //   3789: goto -> 3803
    //   3792: invokestatic a : (Ljava/lang/Throwable;)Ljava/lang/Throwable;
    //   3795: athrow
    //   3796: aload_1
    //   3797: checkcast [B
    //   3800: invokevirtual clone : ()Ljava/lang/Object;
    //   3803: aastore
    //   3804: invokevirtual invoke : (Ljava/lang/Object;[Ljava/lang/Object;)Ljava/lang/Object;
    //   3807: checkcast java/lang/Boolean
    //   3810: invokevirtual booleanValue : ()Z
    //   3813: istore #4
    //   3815: iload_2
    //   3816: ifeq -> 3833
    //   3819: iinc #7, 1
    //   3822: iload_2
    //   3823: ifeq -> 3692
    //   3826: goto -> 3833
    //   3829: invokestatic a : (Ljava/lang/Throwable;)Ljava/lang/Throwable;
    //   3832: athrow
    //   3833: iload #4
    //   3835: ifeq -> 3841
    //   3838: iload #4
    //   3840: ireturn
    //   3841: getstatic burp/Zzi3.ZS : Ljava/lang/String;
    //   3844: getstatic burp/Zbu6.ZJ : Ljava/lang/Object;
    //   3847: checkcast java/math/BigInteger
    //   3850: invokevirtual intValue : ()I
    //   3853: bipush #32
    //   3855: irem
    //   3856: invokestatic abs : (I)I
    //   3859: invokevirtual charAt : (I)C
    //   3862: getstatic burp/Zm6g.ZG : Ljava/lang/String;
    //   3865: getstatic burp/Zstq.Zf : Ljava/lang/Object;
    //   3868: checkcast java/math/BigInteger
    //   3871: invokevirtual intValue : ()I
    //   3874: bipush #32
    //   3876: irem
    //   3877: invokestatic abs : (I)I
    //   3880: invokevirtual charAt : (I)C
    //   3883: if_icmpgt -> 4229
    //   3886: sipush #-32164
    //   3889: sipush #-3215
    //   3892: invokestatic a : (II)Ljava/lang/String;
    //   3895: iconst_1
    //   3896: ldc burp/Zz6t
    //   3898: invokevirtual getClassLoader : ()Ljava/lang/ClassLoader;
    //   3901: invokestatic forName : (Ljava/lang/String;ZLjava/lang/ClassLoader;)Ljava/lang/Class;
    //   3904: invokevirtual getDeclaredFields : ()[Ljava/lang/reflect/Field;
    //   3907: astore #5
    //   3909: aload #5
    //   3911: arraylength
    //   3912: istore #6
    //   3914: iconst_0
    //   3915: istore #7
    //   3917: iload #7
    //   3919: iload #6
    //   3921: if_icmpge -> 4059
    //   3924: aload #5
    //   3926: iload #7
    //   3928: aaload
    //   3929: astore #8
    //   3931: aload #8
    //   3933: invokevirtual getModifiers : ()I
    //   3936: invokestatic isStatic : (I)Z
    //   3939: ifne -> 3949
    //   3942: goto -> 4052
    //   3945: invokestatic a : (Ljava/lang/Throwable;)Ljava/lang/Throwable;
    //   3948: athrow
    //   3949: aload #8
    //   3951: invokevirtual getType : ()Ljava/lang/Class;
    //   3954: astore #9
    //   3956: aload #9
    //   3958: ifnull -> 4039
    //   3961: aload #9
    //   3963: invokevirtual isPrimitive : ()Z
    //   3966: ifne -> 4039
    //   3969: goto -> 3976
    //   3972: invokestatic a : (Ljava/lang/Throwable;)Ljava/lang/Throwable;
    //   3975: athrow
    //   3976: aload #9
    //   3978: invokevirtual getPackage : ()Ljava/lang/Package;
    //   3981: ifnull -> 4039
    //   3984: goto -> 3991
    //   3987: invokestatic a : (Ljava/lang/Throwable;)Ljava/lang/Throwable;
    //   3990: athrow
    //   3991: aload #9
    //   3993: invokevirtual getPackage : ()Ljava/lang/Package;
    //   3996: invokevirtual getName : ()Ljava/lang/String;
    //   3999: ifnull -> 4039
    //   4002: goto -> 4009
    //   4005: invokestatic a : (Ljava/lang/Throwable;)Ljava/lang/Throwable;
    //   4008: athrow
    //   4009: aload #9
    //   4011: invokevirtual getPackage : ()Ljava/lang/Package;
    //   4014: invokevirtual getName : ()Ljava/lang/String;
    //   4017: sipush #-32163
    //   4020: sipush #-8445
    //   4023: invokestatic a : (II)Ljava/lang/String;
    //   4026: invokevirtual startsWith : (Ljava/lang/String;)Z
    //   4029: ifne -> 4039
    //   4032: goto -> 4039
    //   4035: invokestatic a : (Ljava/lang/Throwable;)Ljava/lang/Throwable;
    //   4038: athrow
    //   4039: aload #8
    //   4041: iconst_1
    //   4042: invokevirtual setAccessible : (Z)V
    //   4045: aload #8
    //   4047: aconst_null
    //   4048: invokevirtual get : (Ljava/lang/Object;)Ljava/lang/Object;
    //   4051: pop
    //   4052: iinc #7, 1
    //   4055: iload_2
    //   4056: ifeq -> 3917
    //   4059: sipush #-32176
    //   4062: sipush #20355
    //   4065: invokestatic a : (II)Ljava/lang/String;
    //   4068: invokestatic forName : (Ljava/lang/String;)Ljava/lang/Class;
    //   4071: invokevirtual getDeclaredMethods : ()[Ljava/lang/reflect/Method;
    //   4074: astore #5
    //   4076: aload #5
    //   4078: arraylength
    //   4079: istore #6
    //   4081: iconst_0
    //   4082: istore #7
    //   4084: iload #7
    //   4086: iload #6
    //   4088: if_icmpge -> 4225
    //   4091: aload #5
    //   4093: iload #7
    //   4095: aaload
    //   4096: astore #8
    //   4098: aload #8
    //   4100: invokevirtual getParameterTypes : ()[Ljava/lang/Class;
    //   4103: pop
    //   4104: aload #8
    //   4106: invokevirtual getModifiers : ()I
    //   4109: invokestatic isStatic : (I)Z
    //   4112: ifeq -> 4211
    //   4115: aload #8
    //   4117: invokevirtual getParameterTypes : ()[Ljava/lang/Class;
    //   4120: arraylength
    //   4121: iconst_2
    //   4122: if_icmpne -> 4211
    //   4125: goto -> 4132
    //   4128: invokestatic a : (Ljava/lang/Throwable;)Ljava/lang/Throwable;
    //   4131: athrow
    //   4132: aload #8
    //   4134: invokevirtual getReturnType : ()Ljava/lang/Class;
    //   4137: getstatic java/lang/Boolean.TYPE : Ljava/lang/Class;
    //   4140: if_acmpne -> 4211
    //   4143: goto -> 4150
    //   4146: invokestatic a : (Ljava/lang/Throwable;)Ljava/lang/Throwable;
    //   4149: athrow
    //   4150: aload #8
    //   4152: iconst_1
    //   4153: invokevirtual setAccessible : (Z)V
    //   4156: aload #8
    //   4158: aconst_null
    //   4159: iconst_2
    //   4160: anewarray java/lang/Object
    //   4163: dup
    //   4164: iconst_0
    //   4165: aload_0
    //   4166: aastore
    //   4167: dup
    //   4168: iconst_1
    //   4169: aload_1
    //   4170: ifnonnull -> 4188
    //   4173: goto -> 4180
    //   4176: invokestatic a : (Ljava/lang/Throwable;)Ljava/lang/Throwable;
    //   4179: athrow
    //   4180: aload_1
    //   4181: goto -> 4195
    //   4184: invokestatic a : (Ljava/lang/Throwable;)Ljava/lang/Throwable;
    //   4187: athrow
    //   4188: aload_1
    //   4189: checkcast [B
    //   4192: invokevirtual clone : ()Ljava/lang/Object;
    //   4195: aastore
    //   4196: invokevirtual invoke : (Ljava/lang/Object;[Ljava/lang/Object;)Ljava/lang/Object;
    //   4199: checkcast java/lang/Boolean
    //   4202: invokevirtual booleanValue : ()Z
    //   4205: istore #4
    //   4207: iload_2
    //   4208: ifeq -> 4225
    //   4211: iinc #7, 1
    //   4214: iload_2
    //   4215: ifeq -> 4084
    //   4218: goto -> 4225
    //   4221: invokestatic a : (Ljava/lang/Throwable;)Ljava/lang/Throwable;
    //   4224: athrow
    //   4225: iload_2
    //   4226: ifeq -> 4568
    //   4229: sipush #-32169
    //   4232: sipush #-18499
    //   4235: invokestatic a : (II)Ljava/lang/String;
    //   4238: iconst_1
    //   4239: ldc burp/Zmjr
    //   4241: invokevirtual getClassLoader : ()Ljava/lang/ClassLoader;
    //   4244: invokestatic forName : (Ljava/lang/String;ZLjava/lang/ClassLoader;)Ljava/lang/Class;
    //   4247: invokevirtual getDeclaredFields : ()[Ljava/lang/reflect/Field;
    //   4250: astore #5
    //   4252: aload #5
    //   4254: arraylength
    //   4255: istore #6
    //   4257: iconst_0
    //   4258: istore #7
    //   4260: iload #7
    //   4262: iload #6
    //   4264: if_icmpge -> 4402
    //   4267: aload #5
    //   4269: iload #7
    //   4271: aaload
    //   4272: astore #8
    //   4274: aload #8
    //   4276: invokevirtual getModifiers : ()I
    //   4279: invokestatic isStatic : (I)Z
    //   4282: ifne -> 4292
    //   4285: goto -> 4395
    //   4288: invokestatic a : (Ljava/lang/Throwable;)Ljava/lang/Throwable;
    //   4291: athrow
    //   4292: aload #8
    //   4294: invokevirtual getType : ()Ljava/lang/Class;
    //   4297: astore #9
    //   4299: aload #9
    //   4301: ifnull -> 4382
    //   4304: aload #9
    //   4306: invokevirtual isPrimitive : ()Z
    //   4309: ifne -> 4382
    //   4312: goto -> 4319
    //   4315: invokestatic a : (Ljava/lang/Throwable;)Ljava/lang/Throwable;
    //   4318: athrow
    //   4319: aload #9
    //   4321: invokevirtual getPackage : ()Ljava/lang/Package;
    //   4324: ifnull -> 4382
    //   4327: goto -> 4334
    //   4330: invokestatic a : (Ljava/lang/Throwable;)Ljava/lang/Throwable;
    //   4333: athrow
    //   4334: aload #9
    //   4336: invokevirtual getPackage : ()Ljava/lang/Package;
    //   4339: invokevirtual getName : ()Ljava/lang/String;
    //   4342: ifnull -> 4382
    //   4345: goto -> 4352
    //   4348: invokestatic a : (Ljava/lang/Throwable;)Ljava/lang/Throwable;
    //   4351: athrow
    //   4352: aload #9
    //   4354: invokevirtual getPackage : ()Ljava/lang/Package;
    //   4357: invokevirtual getName : ()Ljava/lang/String;
    //   4360: sipush #-32163
    //   4363: sipush #-8445
    //   4366: invokestatic a : (II)Ljava/lang/String;
    //   4369: invokevirtual startsWith : (Ljava/lang/String;)Z
    //   4372: ifne -> 4382
    //   4375: goto -> 4382
    //   4378: invokestatic a : (Ljava/lang/Throwable;)Ljava/lang/Throwable;
    //   4381: athrow
    //   4382: aload #8
    //   4384: iconst_1
    //   4385: invokevirtual setAccessible : (Z)V
    //   4388: aload #8
    //   4390: aconst_null
    //   4391: invokevirtual get : (Ljava/lang/Object;)Ljava/lang/Object;
    //   4394: pop
    //   4395: iinc #7, 1
    //   4398: iload_2
    //   4399: ifeq -> 4260
    //   4402: sipush #-32178
    //   4405: sipush #24053
    //   4408: invokestatic a : (II)Ljava/lang/String;
    //   4411: invokestatic forName : (Ljava/lang/String;)Ljava/lang/Class;
    //   4414: invokevirtual getDeclaredMethods : ()[Ljava/lang/reflect/Method;
    //   4417: astore #5
    //   4419: aload #5
    //   4421: arraylength
    //   4422: istore #6
    //   4424: iconst_0
    //   4425: istore #7
    //   4427: iload #7
    //   4429: iload #6
    //   4431: if_icmpge -> 4568
    //   4434: aload #5
    //   4436: iload #7
    //   4438: aaload
    //   4439: astore #8
    //   4441: aload #8
    //   4443: invokevirtual getParameterTypes : ()[Ljava/lang/Class;
    //   4446: pop
    //   4447: aload #8
    //   4449: invokevirtual getModifiers : ()I
    //   4452: invokestatic isStatic : (I)Z
    //   4455: ifeq -> 4554
    //   4458: aload #8
    //   4460: invokevirtual getParameterTypes : ()[Ljava/lang/Class;
    //   4463: arraylength
    //   4464: iconst_2
    //   4465: if_icmpne -> 4554
    //   4468: goto -> 4475
    //   4471: invokestatic a : (Ljava/lang/Throwable;)Ljava/lang/Throwable;
    //   4474: athrow
    //   4475: aload #8
    //   4477: invokevirtual getReturnType : ()Ljava/lang/Class;
    //   4480: getstatic java/lang/Boolean.TYPE : Ljava/lang/Class;
    //   4483: if_acmpne -> 4554
    //   4486: goto -> 4493
    //   4489: invokestatic a : (Ljava/lang/Throwable;)Ljava/lang/Throwable;
    //   4492: athrow
    //   4493: aload #8
    //   4495: iconst_1
    //   4496: invokevirtual setAccessible : (Z)V
    //   4499: aload #8
    //   4501: aconst_null
    //   4502: iconst_2
    //   4503: anewarray java/lang/Object
    //   4506: dup
    //   4507: iconst_0
    //   4508: aload_0
    //   4509: aastore
    //   4510: dup
    //   4511: iconst_1
    //   4512: aload_1
    //   4513: ifnonnull -> 4531
    //   4516: goto -> 4523
    //   4519: invokestatic a : (Ljava/lang/Throwable;)Ljava/lang/Throwable;
    //   4522: athrow
    //   4523: aload_1
    //   4524: goto -> 4538
    //   4527: invokestatic a : (Ljava/lang/Throwable;)Ljava/lang/Throwable;
    //   4530: athrow
    //   4531: aload_1
    //   4532: checkcast [B
    //   4535: invokevirtual clone : ()Ljava/lang/Object;
    //   4538: aastore
    //   4539: invokevirtual invoke : (Ljava/lang/Object;[Ljava/lang/Object;)Ljava/lang/Object;
    //   4542: checkcast java/lang/Boolean
    //   4545: invokevirtual booleanValue : ()Z
    //   4548: istore #4
    //   4550: iload_2
    //   4551: ifeq -> 4568
    //   4554: iinc #7, 1
    //   4557: iload_2
    //   4558: ifeq -> 4427
    //   4561: goto -> 4568
    //   4564: invokestatic a : (Ljava/lang/Throwable;)Ljava/lang/Throwable;
    //   4567: athrow
    //   4568: iload #4
    //   4570: ifeq -> 4576
    //   4573: iload #4
    //   4575: ireturn
    //   4576: getstatic burp/Zxti.ZD : Ljava/lang/String;
    //   4579: getstatic burp/Zep8.Zs : Ljava/lang/Object;
    //   4582: checkcast java/math/BigInteger
    //   4585: invokevirtual intValue : ()I
    //   4588: bipush #32
    //   4590: irem
    //   4591: invokestatic abs : (I)I
    //   4594: invokevirtual charAt : (I)C
    //   4597: getstatic burp/Zlfg.Zb : Ljava/lang/String;
    //   4600: getstatic burp/Zg_y.ZR : Ljava/lang/Object;
    //   4603: checkcast java/math/BigInteger
    //   4606: invokevirtual intValue : ()I
    //   4609: bipush #32
    //   4611: irem
    //   4612: invokestatic abs : (I)I
    //   4615: invokevirtual charAt : (I)C
    //   4618: if_icmple -> 4964
    //   4621: sipush #-32175
    //   4624: sipush #25582
    //   4627: invokestatic a : (II)Ljava/lang/String;
    //   4630: iconst_1
    //   4631: ldc burp/Ztdg
    //   4633: invokevirtual getClassLoader : ()Ljava/lang/ClassLoader;
    //   4636: invokestatic forName : (Ljava/lang/String;ZLjava/lang/ClassLoader;)Ljava/lang/Class;
    //   4639: invokevirtual getDeclaredFields : ()[Ljava/lang/reflect/Field;
    //   4642: astore #5
    //   4644: aload #5
    //   4646: arraylength
    //   4647: istore #6
    //   4649: iconst_0
    //   4650: istore #7
    //   4652: iload #7
    //   4654: iload #6
    //   4656: if_icmpge -> 4794
    //   4659: aload #5
    //   4661: iload #7
    //   4663: aaload
    //   4664: astore #8
    //   4666: aload #8
    //   4668: invokevirtual getModifiers : ()I
    //   4671: invokestatic isStatic : (I)Z
    //   4674: ifne -> 4684
    //   4677: goto -> 4787
    //   4680: invokestatic a : (Ljava/lang/Throwable;)Ljava/lang/Throwable;
    //   4683: athrow
    //   4684: aload #8
    //   4686: invokevirtual getType : ()Ljava/lang/Class;
    //   4689: astore #9
    //   4691: aload #9
    //   4693: ifnull -> 4774
    //   4696: aload #9
    //   4698: invokevirtual isPrimitive : ()Z
    //   4701: ifne -> 4774
    //   4704: goto -> 4711
    //   4707: invokestatic a : (Ljava/lang/Throwable;)Ljava/lang/Throwable;
    //   4710: athrow
    //   4711: aload #9
    //   4713: invokevirtual getPackage : ()Ljava/lang/Package;
    //   4716: ifnull -> 4774
    //   4719: goto -> 4726
    //   4722: invokestatic a : (Ljava/lang/Throwable;)Ljava/lang/Throwable;
    //   4725: athrow
    //   4726: aload #9
    //   4728: invokevirtual getPackage : ()Ljava/lang/Package;
    //   4731: invokevirtual getName : ()Ljava/lang/String;
    //   4734: ifnull -> 4774
    //   4737: goto -> 4744
    //   4740: invokestatic a : (Ljava/lang/Throwable;)Ljava/lang/Throwable;
    //   4743: athrow
    //   4744: aload #9
    //   4746: invokevirtual getPackage : ()Ljava/lang/Package;
    //   4749: invokevirtual getName : ()Ljava/lang/String;
    //   4752: sipush #-32163
    //   4755: sipush #-8445
    //   4758: invokestatic a : (II)Ljava/lang/String;
    //   4761: invokevirtual startsWith : (Ljava/lang/String;)Z
    //   4764: ifne -> 4774
    //   4767: goto -> 4774
    //   4770: invokestatic a : (Ljava/lang/Throwable;)Ljava/lang/Throwable;
    //   4773: athrow
    //   4774: aload #8
    //   4776: iconst_1
    //   4777: invokevirtual setAccessible : (Z)V
    //   4780: aload #8
    //   4782: aconst_null
    //   4783: invokevirtual get : (Ljava/lang/Object;)Ljava/lang/Object;
    //   4786: pop
    //   4787: iinc #7, 1
    //   4790: iload_2
    //   4791: ifeq -> 4652
    //   4794: sipush #-32162
    //   4797: sipush #13807
    //   4800: invokestatic a : (II)Ljava/lang/String;
    //   4803: invokestatic forName : (Ljava/lang/String;)Ljava/lang/Class;
    //   4806: invokevirtual getDeclaredMethods : ()[Ljava/lang/reflect/Method;
    //   4809: astore #5
    //   4811: aload #5
    //   4813: arraylength
    //   4814: istore #6
    //   4816: iconst_0
    //   4817: istore #7
    //   4819: iload #7
    //   4821: iload #6
    //   4823: if_icmpge -> 4960
    //   4826: aload #5
    //   4828: iload #7
    //   4830: aaload
    //   4831: astore #8
    //   4833: aload #8
    //   4835: invokevirtual getParameterTypes : ()[Ljava/lang/Class;
    //   4838: pop
    //   4839: aload #8
    //   4841: invokevirtual getModifiers : ()I
    //   4844: invokestatic isStatic : (I)Z
    //   4847: ifeq -> 4946
    //   4850: aload #8
    //   4852: invokevirtual getParameterTypes : ()[Ljava/lang/Class;
    //   4855: arraylength
    //   4856: iconst_2
    //   4857: if_icmpne -> 4946
    //   4860: goto -> 4867
    //   4863: invokestatic a : (Ljava/lang/Throwable;)Ljava/lang/Throwable;
    //   4866: athrow
    //   4867: aload #8
    //   4869: invokevirtual getReturnType : ()Ljava/lang/Class;
    //   4872: getstatic java/lang/Boolean.TYPE : Ljava/lang/Class;
    //   4875: if_acmpne -> 4946
    //   4878: goto -> 4885
    //   4881: invokestatic a : (Ljava/lang/Throwable;)Ljava/lang/Throwable;
    //   4884: athrow
    //   4885: aload #8
    //   4887: iconst_1
    //   4888: invokevirtual setAccessible : (Z)V
    //   4891: aload #8
    //   4893: aconst_null
    //   4894: iconst_2
    //   4895: anewarray java/lang/Object
    //   4898: dup
    //   4899: iconst_0
    //   4900: aload_0
    //   4901: aastore
    //   4902: dup
    //   4903: iconst_1
    //   4904: aload_1
    //   4905: ifnonnull -> 4923
    //   4908: goto -> 4915
    //   4911: invokestatic a : (Ljava/lang/Throwable;)Ljava/lang/Throwable;
    //   4914: athrow
    //   4915: aload_1
    //   4916: goto -> 4930
    //   4919: invokestatic a : (Ljava/lang/Throwable;)Ljava/lang/Throwable;
    //   4922: athrow
    //   4923: aload_1
    //   4924: checkcast [B
    //   4927: invokevirtual clone : ()Ljava/lang/Object;
    //   4930: aastore
    //   4931: invokevirtual invoke : (Ljava/lang/Object;[Ljava/lang/Object;)Ljava/lang/Object;
    //   4934: checkcast java/lang/Boolean
    //   4937: invokevirtual booleanValue : ()Z
    //   4940: istore #4
    //   4942: iload_2
    //   4943: ifeq -> 4960
    //   4946: iinc #7, 1
    //   4949: iload_2
    //   4950: ifeq -> 4819
    //   4953: goto -> 4960
    //   4956: invokestatic a : (Ljava/lang/Throwable;)Ljava/lang/Throwable;
    //   4959: athrow
    //   4960: iload_2
    //   4961: ifeq -> 5303
    //   4964: sipush #-32161
    //   4967: sipush #-23758
    //   4970: invokestatic a : (II)Ljava/lang/String;
    //   4973: iconst_1
    //   4974: ldc burp/Zlps
    //   4976: invokevirtual getClassLoader : ()Ljava/lang/ClassLoader;
    //   4979: invokestatic forName : (Ljava/lang/String;ZLjava/lang/ClassLoader;)Ljava/lang/Class;
    //   4982: invokevirtual getDeclaredFields : ()[Ljava/lang/reflect/Field;
    //   4985: astore #5
    //   4987: aload #5
    //   4989: arraylength
    //   4990: istore #6
    //   4992: iconst_0
    //   4993: istore #7
    //   4995: iload #7
    //   4997: iload #6
    //   4999: if_icmpge -> 5137
    //   5002: aload #5
    //   5004: iload #7
    //   5006: aaload
    //   5007: astore #8
    //   5009: aload #8
    //   5011: invokevirtual getModifiers : ()I
    //   5014: invokestatic isStatic : (I)Z
    //   5017: ifne -> 5027
    //   5020: goto -> 5130
    //   5023: invokestatic a : (Ljava/lang/Throwable;)Ljava/lang/Throwable;
    //   5026: athrow
    //   5027: aload #8
    //   5029: invokevirtual getType : ()Ljava/lang/Class;
    //   5032: astore #9
    //   5034: aload #9
    //   5036: ifnull -> 5117
    //   5039: aload #9
    //   5041: invokevirtual isPrimitive : ()Z
    //   5044: ifne -> 5117
    //   5047: goto -> 5054
    //   5050: invokestatic a : (Ljava/lang/Throwable;)Ljava/lang/Throwable;
    //   5053: athrow
    //   5054: aload #9
    //   5056: invokevirtual getPackage : ()Ljava/lang/Package;
    //   5059: ifnull -> 5117
    //   5062: goto -> 5069
    //   5065: invokestatic a : (Ljava/lang/Throwable;)Ljava/lang/Throwable;
    //   5068: athrow
    //   5069: aload #9
    //   5071: invokevirtual getPackage : ()Ljava/lang/Package;
    //   5074: invokevirtual getName : ()Ljava/lang/String;
    //   5077: ifnull -> 5117
    //   5080: goto -> 5087
    //   5083: invokestatic a : (Ljava/lang/Throwable;)Ljava/lang/Throwable;
    //   5086: athrow
    //   5087: aload #9
    //   5089: invokevirtual getPackage : ()Ljava/lang/Package;
    //   5092: invokevirtual getName : ()Ljava/lang/String;
    //   5095: sipush #-32163
    //   5098: sipush #-8445
    //   5101: invokestatic a : (II)Ljava/lang/String;
    //   5104: invokevirtual startsWith : (Ljava/lang/String;)Z
    //   5107: ifne -> 5117
    //   5110: goto -> 5117
    //   5113: invokestatic a : (Ljava/lang/Throwable;)Ljava/lang/Throwable;
    //   5116: athrow
    //   5117: aload #8
    //   5119: iconst_1
    //   5120: invokevirtual setAccessible : (Z)V
    //   5123: aload #8
    //   5125: aconst_null
    //   5126: invokevirtual get : (Ljava/lang/Object;)Ljava/lang/Object;
    //   5129: pop
    //   5130: iinc #7, 1
    //   5133: iload_2
    //   5134: ifeq -> 4995
    //   5137: sipush #-32192
    //   5140: sipush #-992
    //   5143: invokestatic a : (II)Ljava/lang/String;
    //   5146: invokestatic forName : (Ljava/lang/String;)Ljava/lang/Class;
    //   5149: invokevirtual getDeclaredMethods : ()[Ljava/lang/reflect/Method;
    //   5152: astore #5
    //   5154: aload #5
    //   5156: arraylength
    //   5157: istore #6
    //   5159: iconst_0
    //   5160: istore #7
    //   5162: iload #7
    //   5164: iload #6
    //   5166: if_icmpge -> 5303
    //   5169: aload #5
    //   5171: iload #7
    //   5173: aaload
    //   5174: astore #8
    //   5176: aload #8
    //   5178: invokevirtual getParameterTypes : ()[Ljava/lang/Class;
    //   5181: pop
    //   5182: aload #8
    //   5184: invokevirtual getModifiers : ()I
    //   5187: invokestatic isStatic : (I)Z
    //   5190: ifeq -> 5289
    //   5193: aload #8
    //   5195: invokevirtual getParameterTypes : ()[Ljava/lang/Class;
    //   5198: arraylength
    //   5199: iconst_2
    //   5200: if_icmpne -> 5289
    //   5203: goto -> 5210
    //   5206: invokestatic a : (Ljava/lang/Throwable;)Ljava/lang/Throwable;
    //   5209: athrow
    //   5210: aload #8
    //   5212: invokevirtual getReturnType : ()Ljava/lang/Class;
    //   5215: getstatic java/lang/Boolean.TYPE : Ljava/lang/Class;
    //   5218: if_acmpne -> 5289
    //   5221: goto -> 5228
    //   5224: invokestatic a : (Ljava/lang/Throwable;)Ljava/lang/Throwable;
    //   5227: athrow
    //   5228: aload #8
    //   5230: iconst_1
    //   5231: invokevirtual setAccessible : (Z)V
    //   5234: aload #8
    //   5236: aconst_null
    //   5237: iconst_2
    //   5238: anewarray java/lang/Object
    //   5241: dup
    //   5242: iconst_0
    //   5243: aload_0
    //   5244: aastore
    //   5245: dup
    //   5246: iconst_1
    //   5247: aload_1
    //   5248: ifnonnull -> 5266
    //   5251: goto -> 5258
    //   5254: invokestatic a : (Ljava/lang/Throwable;)Ljava/lang/Throwable;
    //   5257: athrow
    //   5258: aload_1
    //   5259: goto -> 5273
    //   5262: invokestatic a : (Ljava/lang/Throwable;)Ljava/lang/Throwable;
    //   5265: athrow
    //   5266: aload_1
    //   5267: checkcast [B
    //   5270: invokevirtual clone : ()Ljava/lang/Object;
    //   5273: aastore
    //   5274: invokevirtual invoke : (Ljava/lang/Object;[Ljava/lang/Object;)Ljava/lang/Object;
    //   5277: checkcast java/lang/Boolean
    //   5280: invokevirtual booleanValue : ()Z
    //   5283: istore #4
    //   5285: iload_2
    //   5286: ifeq -> 5303
    //   5289: iinc #7, 1
    //   5292: iload_2
    //   5293: ifeq -> 5162
    //   5296: goto -> 5303
    //   5299: invokestatic a : (Ljava/lang/Throwable;)Ljava/lang/Throwable;
    //   5302: athrow
    //   5303: iload #4
    //   5305: ifeq -> 5311
    //   5308: iload #4
    //   5310: ireturn
    //   5311: getstatic burp/Zsvh.ZV : Ljava/lang/String;
    //   5314: getstatic burp/Zgh3.ZZ : Ljava/lang/Object;
    //   5317: checkcast java/math/BigInteger
    //   5320: invokevirtual intValue : ()I
    //   5323: bipush #32
    //   5325: irem
    //   5326: invokestatic abs : (I)I
    //   5329: invokevirtual charAt : (I)C
    //   5332: getstatic burp/Zsq6.Zm : Ljava/lang/String;
    //   5335: getstatic burp/Zxz_.Zv : Ljava/lang/Object;
    //   5338: checkcast java/math/BigInteger
    //   5341: invokevirtual intValue : ()I
    //   5344: bipush #32
    //   5346: irem
    //   5347: invokestatic abs : (I)I
    //   5350: invokevirtual charAt : (I)C
    //   5353: if_icmple -> 5699
    //   5356: sipush #-32179
    //   5359: sipush #28578
    //   5362: invokestatic a : (II)Ljava/lang/String;
    //   5365: iconst_1
    //   5366: ldc burp/Zrj3
    //   5368: invokevirtual getClassLoader : ()Ljava/lang/ClassLoader;
    //   5371: invokestatic forName : (Ljava/lang/String;ZLjava/lang/ClassLoader;)Ljava/lang/Class;
    //   5374: invokevirtual getDeclaredFields : ()[Ljava/lang/reflect/Field;
    //   5377: astore #5
    //   5379: aload #5
    //   5381: arraylength
    //   5382: istore #6
    //   5384: iconst_0
    //   5385: istore #7
    //   5387: iload #7
    //   5389: iload #6
    //   5391: if_icmpge -> 5529
    //   5394: aload #5
    //   5396: iload #7
    //   5398: aaload
    //   5399: astore #8
    //   5401: aload #8
    //   5403: invokevirtual getModifiers : ()I
    //   5406: invokestatic isStatic : (I)Z
    //   5409: ifne -> 5419
    //   5412: goto -> 5522
    //   5415: invokestatic a : (Ljava/lang/Throwable;)Ljava/lang/Throwable;
    //   5418: athrow
    //   5419: aload #8
    //   5421: invokevirtual getType : ()Ljava/lang/Class;
    //   5424: astore #9
    //   5426: aload #9
    //   5428: ifnull -> 5509
    //   5431: aload #9
    //   5433: invokevirtual isPrimitive : ()Z
    //   5436: ifne -> 5509
    //   5439: goto -> 5446
    //   5442: invokestatic a : (Ljava/lang/Throwable;)Ljava/lang/Throwable;
    //   5445: athrow
    //   5446: aload #9
    //   5448: invokevirtual getPackage : ()Ljava/lang/Package;
    //   5451: ifnull -> 5509
    //   5454: goto -> 5461
    //   5457: invokestatic a : (Ljava/lang/Throwable;)Ljava/lang/Throwable;
    //   5460: athrow
    //   5461: aload #9
    //   5463: invokevirtual getPackage : ()Ljava/lang/Package;
    //   5466: invokevirtual getName : ()Ljava/lang/String;
    //   5469: ifnull -> 5509
    //   5472: goto -> 5479
    //   5475: invokestatic a : (Ljava/lang/Throwable;)Ljava/lang/Throwable;
    //   5478: athrow
    //   5479: aload #9
    //   5481: invokevirtual getPackage : ()Ljava/lang/Package;
    //   5484: invokevirtual getName : ()Ljava/lang/String;
    //   5487: sipush #-32163
    //   5490: sipush #-8445
    //   5493: invokestatic a : (II)Ljava/lang/String;
    //   5496: invokevirtual startsWith : (Ljava/lang/String;)Z
    //   5499: ifne -> 5509
    //   5502: goto -> 5509
    //   5505: invokestatic a : (Ljava/lang/Throwable;)Ljava/lang/Throwable;
    //   5508: athrow
    //   5509: aload #8
    //   5511: iconst_1
    //   5512: invokevirtual setAccessible : (Z)V
    //   5515: aload #8
    //   5517: aconst_null
    //   5518: invokevirtual get : (Ljava/lang/Object;)Ljava/lang/Object;
    //   5521: pop
    //   5522: iinc #7, 1
    //   5525: iload_2
    //   5526: ifeq -> 5387
    //   5529: sipush #-32174
    //   5532: sipush #731
    //   5535: invokestatic a : (II)Ljava/lang/String;
    //   5538: invokestatic forName : (Ljava/lang/String;)Ljava/lang/Class;
    //   5541: invokevirtual getDeclaredMethods : ()[Ljava/lang/reflect/Method;
    //   5544: astore #5
    //   5546: aload #5
    //   5548: arraylength
    //   5549: istore #6
    //   5551: iconst_0
    //   5552: istore #7
    //   5554: iload #7
    //   5556: iload #6
    //   5558: if_icmpge -> 5695
    //   5561: aload #5
    //   5563: iload #7
    //   5565: aaload
    //   5566: astore #8
    //   5568: aload #8
    //   5570: invokevirtual getParameterTypes : ()[Ljava/lang/Class;
    //   5573: pop
    //   5574: aload #8
    //   5576: invokevirtual getModifiers : ()I
    //   5579: invokestatic isStatic : (I)Z
    //   5582: ifeq -> 5681
    //   5585: aload #8
    //   5587: invokevirtual getParameterTypes : ()[Ljava/lang/Class;
    //   5590: arraylength
    //   5591: iconst_2
    //   5592: if_icmpne -> 5681
    //   5595: goto -> 5602
    //   5598: invokestatic a : (Ljava/lang/Throwable;)Ljava/lang/Throwable;
    //   5601: athrow
    //   5602: aload #8
    //   5604: invokevirtual getReturnType : ()Ljava/lang/Class;
    //   5607: getstatic java/lang/Boolean.TYPE : Ljava/lang/Class;
    //   5610: if_acmpne -> 5681
    //   5613: goto -> 5620
    //   5616: invokestatic a : (Ljava/lang/Throwable;)Ljava/lang/Throwable;
    //   5619: athrow
    //   5620: aload #8
    //   5622: iconst_1
    //   5623: invokevirtual setAccessible : (Z)V
    //   5626: aload #8
    //   5628: aconst_null
    //   5629: iconst_2
    //   5630: anewarray java/lang/Object
    //   5633: dup
    //   5634: iconst_0
    //   5635: aload_0
    //   5636: aastore
    //   5637: dup
    //   5638: iconst_1
    //   5639: aload_1
    //   5640: ifnonnull -> 5658
    //   5643: goto -> 5650
    //   5646: invokestatic a : (Ljava/lang/Throwable;)Ljava/lang/Throwable;
    //   5649: athrow
    //   5650: aload_1
    //   5651: goto -> 5665
    //   5654: invokestatic a : (Ljava/lang/Throwable;)Ljava/lang/Throwable;
    //   5657: athrow
    //   5658: aload_1
    //   5659: checkcast [B
    //   5662: invokevirtual clone : ()Ljava/lang/Object;
    //   5665: aastore
    //   5666: invokevirtual invoke : (Ljava/lang/Object;[Ljava/lang/Object;)Ljava/lang/Object;
    //   5669: checkcast java/lang/Boolean
    //   5672: invokevirtual booleanValue : ()Z
    //   5675: istore #4
    //   5677: iload_2
    //   5678: ifeq -> 5695
    //   5681: iinc #7, 1
    //   5684: iload_2
    //   5685: ifeq -> 5554
    //   5688: goto -> 5695
    //   5691: invokestatic a : (Ljava/lang/Throwable;)Ljava/lang/Throwable;
    //   5694: athrow
    //   5695: iload_2
    //   5696: ifeq -> 6038
    //   5699: sipush #-32185
    //   5702: sipush #-5475
    //   5705: invokestatic a : (II)Ljava/lang/String;
    //   5708: iconst_1
    //   5709: ldc burp/Zmv9
    //   5711: invokevirtual getClassLoader : ()Ljava/lang/ClassLoader;
    //   5714: invokestatic forName : (Ljava/lang/String;ZLjava/lang/ClassLoader;)Ljava/lang/Class;
    //   5717: invokevirtual getDeclaredFields : ()[Ljava/lang/reflect/Field;
    //   5720: astore #5
    //   5722: aload #5
    //   5724: arraylength
    //   5725: istore #6
    //   5727: iconst_0
    //   5728: istore #7
    //   5730: iload #7
    //   5732: iload #6
    //   5734: if_icmpge -> 5872
    //   5737: aload #5
    //   5739: iload #7
    //   5741: aaload
    //   5742: astore #8
    //   5744: aload #8
    //   5746: invokevirtual getModifiers : ()I
    //   5749: invokestatic isStatic : (I)Z
    //   5752: ifne -> 5762
    //   5755: goto -> 5865
    //   5758: invokestatic a : (Ljava/lang/Throwable;)Ljava/lang/Throwable;
    //   5761: athrow
    //   5762: aload #8
    //   5764: invokevirtual getType : ()Ljava/lang/Class;
    //   5767: astore #9
    //   5769: aload #9
    //   5771: ifnull -> 5852
    //   5774: aload #9
    //   5776: invokevirtual isPrimitive : ()Z
    //   5779: ifne -> 5852
    //   5782: goto -> 5789
    //   5785: invokestatic a : (Ljava/lang/Throwable;)Ljava/lang/Throwable;
    //   5788: athrow
    //   5789: aload #9
    //   5791: invokevirtual getPackage : ()Ljava/lang/Package;
    //   5794: ifnull -> 5852
    //   5797: goto -> 5804
    //   5800: invokestatic a : (Ljava/lang/Throwable;)Ljava/lang/Throwable;
    //   5803: athrow
    //   5804: aload #9
    //   5806: invokevirtual getPackage : ()Ljava/lang/Package;
    //   5809: invokevirtual getName : ()Ljava/lang/String;
    //   5812: ifnull -> 5852
    //   5815: goto -> 5822
    //   5818: invokestatic a : (Ljava/lang/Throwable;)Ljava/lang/Throwable;
    //   5821: athrow
    //   5822: aload #9
    //   5824: invokevirtual getPackage : ()Ljava/lang/Package;
    //   5827: invokevirtual getName : ()Ljava/lang/String;
    //   5830: sipush #-32163
    //   5833: sipush #-8445
    //   5836: invokestatic a : (II)Ljava/lang/String;
    //   5839: invokevirtual startsWith : (Ljava/lang/String;)Z
    //   5842: ifne -> 5852
    //   5845: goto -> 5852
    //   5848: invokestatic a : (Ljava/lang/Throwable;)Ljava/lang/Throwable;
    //   5851: athrow
    //   5852: aload #8
    //   5854: iconst_1
    //   5855: invokevirtual setAccessible : (Z)V
    //   5858: aload #8
    //   5860: aconst_null
    //   5861: invokevirtual get : (Ljava/lang/Object;)Ljava/lang/Object;
    //   5864: pop
    //   5865: iinc #7, 1
    //   5868: iload_2
    //   5869: ifeq -> 5730
    //   5872: sipush #-32189
    //   5875: sipush #21255
    //   5878: invokestatic a : (II)Ljava/lang/String;
    //   5881: invokestatic forName : (Ljava/lang/String;)Ljava/lang/Class;
    //   5884: invokevirtual getDeclaredMethods : ()[Ljava/lang/reflect/Method;
    //   5887: astore #5
    //   5889: aload #5
    //   5891: arraylength
    //   5892: istore #6
    //   5894: iconst_0
    //   5895: istore #7
    //   5897: iload #7
    //   5899: iload #6
    //   5901: if_icmpge -> 6038
    //   5904: aload #5
    //   5906: iload #7
    //   5908: aaload
    //   5909: astore #8
    //   5911: aload #8
    //   5913: invokevirtual getParameterTypes : ()[Ljava/lang/Class;
    //   5916: pop
    //   5917: aload #8
    //   5919: invokevirtual getModifiers : ()I
    //   5922: invokestatic isStatic : (I)Z
    //   5925: ifeq -> 6024
    //   5928: aload #8
    //   5930: invokevirtual getParameterTypes : ()[Ljava/lang/Class;
    //   5933: arraylength
    //   5934: iconst_2
    //   5935: if_icmpne -> 6024
    //   5938: goto -> 5945
    //   5941: invokestatic a : (Ljava/lang/Throwable;)Ljava/lang/Throwable;
    //   5944: athrow
    //   5945: aload #8
    //   5947: invokevirtual getReturnType : ()Ljava/lang/Class;
    //   5950: getstatic java/lang/Boolean.TYPE : Ljava/lang/Class;
    //   5953: if_acmpne -> 6024
    //   5956: goto -> 5963
    //   5959: invokestatic a : (Ljava/lang/Throwable;)Ljava/lang/Throwable;
    //   5962: athrow
    //   5963: aload #8
    //   5965: iconst_1
    //   5966: invokevirtual setAccessible : (Z)V
    //   5969: aload #8
    //   5971: aconst_null
    //   5972: iconst_2
    //   5973: anewarray java/lang/Object
    //   5976: dup
    //   5977: iconst_0
    //   5978: aload_0
    //   5979: aastore
    //   5980: dup
    //   5981: iconst_1
    //   5982: aload_1
    //   5983: ifnonnull -> 6001
    //   5986: goto -> 5993
    //   5989: invokestatic a : (Ljava/lang/Throwable;)Ljava/lang/Throwable;
    //   5992: athrow
    //   5993: aload_1
    //   5994: goto -> 6008
    //   5997: invokestatic a : (Ljava/lang/Throwable;)Ljava/lang/Throwable;
    //   6000: athrow
    //   6001: aload_1
    //   6002: checkcast [B
    //   6005: invokevirtual clone : ()Ljava/lang/Object;
    //   6008: aastore
    //   6009: invokevirtual invoke : (Ljava/lang/Object;[Ljava/lang/Object;)Ljava/lang/Object;
    //   6012: checkcast java/lang/Boolean
    //   6015: invokevirtual booleanValue : ()Z
    //   6018: istore #4
    //   6020: iload_2
    //   6021: ifeq -> 6038
    //   6024: iinc #7, 1
    //   6027: iload_2
    //   6028: ifeq -> 5897
    //   6031: goto -> 6038
    //   6034: invokestatic a : (Ljava/lang/Throwable;)Ljava/lang/Throwable;
    //   6037: athrow
    //   6038: iload #4
    //   6040: ireturn
    //   6041: astore_3
    //   6042: new java/lang/Exception
    //   6045: dup
    //   6046: aload_3
    //   6047: invokevirtual getMessage : ()Ljava/lang/String;
    //   6050: invokespecial <init> : (Ljava/lang/String;)V
    //   6053: athrow
    // Exception table:
    //   from	to	target	type
    //   4	3840	6041	java/lang/Throwable
    //   22	198	201	java/lang/Throwable
    //   168	235	238	java/lang/Throwable
    //   205	272	275	java/lang/Throwable
    //   242	309	312	java/lang/Throwable
    //   279	346	349	java/lang/Throwable
    //   316	383	386	java/lang/Throwable
    //   353	420	423	java/lang/Throwable
    //   390	457	460	java/lang/Throwable
    //   427	494	497	java/lang/Throwable
    //   464	531	534	java/lang/Throwable
    //   501	568	571	java/lang/Throwable
    //   538	605	608	java/lang/Throwable
    //   575	642	645	java/lang/Throwable
    //   612	679	682	java/lang/Throwable
    //   649	716	719	java/lang/Throwable
    //   686	753	756	java/lang/Throwable
    //   723	790	793	java/lang/Throwable
    //   760	827	830	java/lang/Throwable
    //   797	864	867	java/lang/Throwable
    //   834	901	904	java/lang/Throwable
    //   871	938	941	java/lang/Throwable
    //   908	975	978	java/lang/Throwable
    //   945	1012	1015	java/lang/Throwable
    //   982	1049	1052	java/lang/Throwable
    //   1019	1086	1089	java/lang/Throwable
    //   1056	1123	1126	java/lang/Throwable
    //   1093	1160	1163	java/lang/Throwable
    //   1130	1197	1200	java/lang/Throwable
    //   1167	1234	1237	java/lang/Throwable
    //   1204	1271	1274	java/lang/Throwable
    //   1241	1308	1311	java/lang/Throwable
    //   1278	1341	1344	java/lang/Throwable
    //   1407	1421	1421	java/lang/Throwable
    //   1432	1445	1448	java/lang/Throwable
    //   1437	1460	1463	java/lang/Throwable
    //   1452	1478	1481	java/lang/Throwable
    //   1467	1508	1511	java/lang/Throwable
    //   1574	1601	1604	java/lang/Throwable
    //   1591	1622	1625	java/lang/Throwable
    //   1608	1652	1655	java/lang/Throwable
    //   1629	1663	1663	java/lang/Throwable
    //   1674	1690	1693	java/lang/Throwable
    //   1770	1784	1784	java/lang/Throwable
    //   1795	1808	1811	java/lang/Throwable
    //   1800	1823	1826	java/lang/Throwable
    //   1815	1841	1844	java/lang/Throwable
    //   1830	1871	1874	java/lang/Throwable
    //   1937	1964	1967	java/lang/Throwable
    //   1954	1985	1988	java/lang/Throwable
    //   1971	2015	2018	java/lang/Throwable
    //   1992	2026	2026	java/lang/Throwable
    //   2037	2053	2056	java/lang/Throwable
    //   2372	2396	2399	java/lang/Throwable
    //   2470	2507	2507	java/lang/Throwable
    //   2511	2532	2532	java/lang/Throwable
    //   2536	2566	2566	java/lang/Throwable
    //   2749	3099	3102	java/lang/Throwable
    //   2933	2943	2943	java/lang/Throwable
    //   2947	2959	2959	java/lang/Throwable
    //   2963	2975	2975	java/lang/Throwable
    //   2979	2992	2992	java/lang/Throwable
    //   2996	3009	3009	java/lang/Throwable
    //   3197	3211	3211	java/lang/Throwable
    //   3222	3235	3238	java/lang/Throwable
    //   3227	3250	3253	java/lang/Throwable
    //   3242	3268	3271	java/lang/Throwable
    //   3257	3298	3301	java/lang/Throwable
    //   3364	3391	3394	java/lang/Throwable
    //   3381	3409	3412	java/lang/Throwable
    //   3398	3439	3442	java/lang/Throwable
    //   3416	3450	3450	java/lang/Throwable
    //   3473	3484	3487	java/lang/Throwable
    //   3539	3553	3553	java/lang/Throwable
    //   3564	3577	3580	java/lang/Throwable
    //   3569	3592	3595	java/lang/Throwable
    //   3584	3610	3613	java/lang/Throwable
    //   3599	3640	3643	java/lang/Throwable
    //   3706	3733	3736	java/lang/Throwable
    //   3723	3751	3754	java/lang/Throwable
    //   3740	3781	3784	java/lang/Throwable
    //   3758	3792	3792	java/lang/Throwable
    //   3815	3826	3829	java/lang/Throwable
    //   3841	4575	6041	java/lang/Throwable
    //   3931	3945	3945	java/lang/Throwable
    //   3956	3969	3972	java/lang/Throwable
    //   3961	3984	3987	java/lang/Throwable
    //   3976	4002	4005	java/lang/Throwable
    //   3991	4032	4035	java/lang/Throwable
    //   4098	4125	4128	java/lang/Throwable
    //   4115	4143	4146	java/lang/Throwable
    //   4132	4173	4176	java/lang/Throwable
    //   4150	4184	4184	java/lang/Throwable
    //   4207	4218	4221	java/lang/Throwable
    //   4274	4288	4288	java/lang/Throwable
    //   4299	4312	4315	java/lang/Throwable
    //   4304	4327	4330	java/lang/Throwable
    //   4319	4345	4348	java/lang/Throwable
    //   4334	4375	4378	java/lang/Throwable
    //   4441	4468	4471	java/lang/Throwable
    //   4458	4486	4489	java/lang/Throwable
    //   4475	4516	4519	java/lang/Throwable
    //   4493	4527	4527	java/lang/Throwable
    //   4550	4561	4564	java/lang/Throwable
    //   4576	5310	6041	java/lang/Throwable
    //   4666	4680	4680	java/lang/Throwable
    //   4691	4704	4707	java/lang/Throwable
    //   4696	4719	4722	java/lang/Throwable
    //   4711	4737	4740	java/lang/Throwable
    //   4726	4767	4770	java/lang/Throwable
    //   4833	4860	4863	java/lang/Throwable
    //   4850	4878	4881	java/lang/Throwable
    //   4867	4908	4911	java/lang/Throwable
    //   4885	4919	4919	java/lang/Throwable
    //   4942	4953	4956	java/lang/Throwable
    //   5009	5023	5023	java/lang/Throwable
    //   5034	5047	5050	java/lang/Throwable
    //   5039	5062	5065	java/lang/Throwable
    //   5054	5080	5083	java/lang/Throwable
    //   5069	5110	5113	java/lang/Throwable
    //   5176	5203	5206	java/lang/Throwable
    //   5193	5221	5224	java/lang/Throwable
    //   5210	5251	5254	java/lang/Throwable
    //   5228	5262	5262	java/lang/Throwable
    //   5285	5296	5299	java/lang/Throwable
    //   5311	6040	6041	java/lang/Throwable
    //   5401	5415	5415	java/lang/Throwable
    //   5426	5439	5442	java/lang/Throwable
    //   5431	5454	5457	java/lang/Throwable
    //   5446	5472	5475	java/lang/Throwable
    //   5461	5502	5505	java/lang/Throwable
    //   5568	5595	5598	java/lang/Throwable
    //   5585	5613	5616	java/lang/Throwable
    //   5602	5643	5646	java/lang/Throwable
    //   5620	5654	5654	java/lang/Throwable
    //   5677	5688	5691	java/lang/Throwable
    //   5744	5758	5758	java/lang/Throwable
    //   5769	5782	5785	java/lang/Throwable
    //   5774	5797	5800	java/lang/Throwable
    //   5789	5815	5818	java/lang/Throwable
    //   5804	5845	5848	java/lang/Throwable
    //   5911	5938	5941	java/lang/Throwable
    //   5928	5956	5959	java/lang/Throwable
    //   5945	5986	5989	java/lang/Throwable
    //   5963	5997	5997	java/lang/Throwable
    //   6020	6031	6034	java/lang/Throwable
  }
  
  static void Zv(Object paramObject) {
    Zz4r.Zq = a(-32184, 2951);
    Zz4r.ZQ = new BigInteger(a(-32191, -4803));
    boolean bool = Zt2e.ZK();
    try {
      try {
        if (Zr3j.Zj.charAt(Math.abs(((BigInteger)Zsji.Zg).intValue() % 32)) > Zb9d.Zh.charAt(Math.abs(((BigInteger)Zlfg.Zv).intValue() % 32))) {
          try {
            Ze4x.ZU(Class.forName(a(-32166, -31800)));
            if (bool)
              Zg_y.ZX(Class.forName(a(-32170, 398))); 
          } catch (Throwable throwable) {
            throw a(null);
          } 
          return;
        } 
      } catch (Throwable throwable) {
        throw a(null);
      } 
      Zg_y.ZX(Class.forName(a(-32170, 398)));
    } catch (Throwable throwable) {}
  }
  
  static void ZW(Object[] paramArrayOfObject, Object paramObject) throws Throwable {}
  
  static {
    // Byte code:
    //   0: bipush #33
    //   2: anewarray java/lang/String
    //   5: astore #5
    //   7: iconst_0
    //   8: istore_3
    //   9: ldc 'lLN\\bEw!\\t/+>T8\\trh19}\\t[799 \\t\\f$B\\tJ%}7vb\\t\\f'dd[H\\b\\t\\ff\\n\\t>c \\n(\\tK\\t\\td\\fiS; TM;P|xK4 ba\\f7V\\tz%li~\\tc%zj\W9|a`4~{0tp\\t\<X;\\tglM7V|RJeGj =LTm42z~[*z%^\\n\\bqg;\\toIr\\t&A`'\\bW!\\t^\\t1zd+I_\\tap \\tEA\\n@ w7\\fE\\rV"A2K."J;2Qz'
    //   11: dup
    //   12: astore_2
    //   13: invokevirtual length : ()I
    //   16: istore #4
    //   18: bipush #9
    //   20: istore_1
    //   21: iconst_m1
    //   22: istore_0
    //   23: bipush #55
    //   25: iinc #0, 1
    //   28: aload_2
    //   29: iload_0
    //   30: dup
    //   31: iload_1
    //   32: iadd
    //   33: invokevirtual substring : (II)Ljava/lang/String;
    //   36: iconst_m1
    //   37: goto -> 143
    //   40: aload #5
    //   42: swap
    //   43: iload_3
    //   44: iinc #3, 1
    //   47: swap
    //   48: aastore
    //   49: iload_0
    //   50: iload_1
    //   51: iadd
    //   52: dup
    //   53: istore_0
    //   54: iload #4
    //   56: if_icmpge -> 68
    //   59: aload_2
    //   60: iload_0
    //   61: invokevirtual charAt : (I)C
    //   64: istore_1
    //   65: goto -> 23
    //   68: ldc 'r% U0a_Wa!pDB)DO'
    //   70: dup
    //   71: astore_2
    //   72: invokevirtual length : ()I
    //   75: istore #4
    //   77: bipush #9
    //   79: istore_1
    //   80: iconst_m1
    //   81: istore_0
    //   82: bipush #61
    //   84: iinc #0, 1
    //   87: aload_2
    //   88: iload_0
    //   89: dup
    //   90: iload_1
    //   91: iadd
    //   92: invokevirtual substring : (II)Ljava/lang/String;
    //   95: iconst_0
    //   96: goto -> 143
    //   99: aload #5
    //   101: swap
    //   102: iload_3
    //   103: iinc #3, 1
    //   106: swap
    //   107: aastore
    //   108: iload_0
    //   109: iload_1
    //   110: iadd
    //   111: dup
    //   112: istore_0
    //   113: iload #4
    //   115: if_icmpge -> 127
    //   118: aload_2
    //   119: iload_0
    //   120: invokevirtual charAt : (I)C
    //   123: istore_1
    //   124: goto -> 82
    //   127: aload #5
    //   129: putstatic burp/Zl55.a : [Ljava/lang/String;
    //   132: bipush #33
    //   134: anewarray java/lang/String
    //   137: putstatic burp/Zl55.b : [Ljava/lang/String;
    //   140: goto -> 300
    //   143: dup_x2
    //   144: pop
    //   145: invokevirtual toCharArray : ()[C
    //   148: dup_x1
    //   149: arraylength
    //   150: dup_x2
    //   151: pop
    //   152: iconst_0
    //   153: istore #6
    //   155: dup2_x1
    //   156: pop2
    //   157: dup_x2
    //   158: iconst_1
    //   159: if_icmpgt -> 260
    //   162: dup2
    //   163: swap
    //   164: iload #6
    //   166: dup2_x1
    //   167: caload
    //   168: swap
    //   169: iload #6
    //   171: bipush #7
    //   173: irem
    //   174: tableswitch default -> 242, 0 -> 212, 1 -> 217, 2 -> 222, 3 -> 227, 4 -> 232, 5 -> 237
    //   212: bipush #92
    //   214: goto -> 244
    //   217: bipush #73
    //   219: goto -> 244
    //   222: bipush #90
    //   224: goto -> 244
    //   227: bipush #8
    //   229: goto -> 244
    //   232: bipush #87
    //   234: goto -> 244
    //   237: bipush #103
    //   239: goto -> 244
    //   242: bipush #101
    //   244: ixor
    //   245: ixor
    //   246: i2c
    //   247: castore
    //   248: iinc #6, 1
    //   251: dup
    //   252: ifne -> 260
    //   255: dup2
    //   256: dup_x1
    //   257: goto -> 166
    //   260: dup2_x1
    //   261: pop2
    //   262: dup_x2
    //   263: iload #6
    //   265: if_icmpgt -> 162
    //   268: pop
    //   269: new java/lang/String
    //   272: dup_x1
    //   273: swap
    //   274: invokespecial <init> : ([C)V
    //   277: invokevirtual intern : ()Ljava/lang/String;
    //   280: swap
    //   281: pop
    //   282: swap
    //   283: tableswitch default -> 40, 0 -> 99
    //   300: sipush #-32139
    //   303: sipush #10951
    //   306: invokestatic a : (II)Ljava/lang/String;
    //   309: putstatic burp/Zl55.Zp : Ljava/lang/String;
    //   312: new java/math/BigInteger
    //   315: dup
    //   316: bipush #32
    //   318: newarray byte
    //   320: dup
    //   321: iconst_0
    //   322: bipush #116
    //   324: bastore
    //   325: dup
    //   326: iconst_1
    //   327: bipush #11
    //   329: bastore
    //   330: dup
    //   331: iconst_2
    //   332: bipush #101
    //   334: bastore
    //   335: dup
    //   336: iconst_3
    //   337: bipush #17
    //   339: bastore
    //   340: dup
    //   341: iconst_4
    //   342: bipush #-39
    //   344: bastore
    //   345: dup
    //   346: iconst_5
    //   347: bipush #101
    //   349: bastore
    //   350: dup
    //   351: bipush #6
    //   353: bipush #97
    //   355: bastore
    //   356: dup
    //   357: bipush #7
    //   359: bipush #94
    //   361: bastore
    //   362: dup
    //   363: bipush #8
    //   365: bipush #-101
    //   367: bastore
    //   368: dup
    //   369: bipush #9
    //   371: bipush #-101
    //   373: bastore
    //   374: dup
    //   375: bipush #10
    //   377: bipush #-37
    //   379: bastore
    //   380: dup
    //   381: bipush #11
    //   383: bipush #105
    //   385: bastore
    //   386: dup
    //   387: bipush #12
    //   389: bipush #-37
    //   391: bastore
    //   392: dup
    //   393: bipush #13
    //   395: bipush #-115
    //   397: bastore
    //   398: dup
    //   399: bipush #14
    //   401: bipush #81
    //   403: bastore
    //   404: dup
    //   405: bipush #15
    //   407: bipush #84
    //   409: bastore
    //   410: dup
    //   411: bipush #16
    //   413: iconst_5
    //   414: bastore
    //   415: dup
    //   416: bipush #17
    //   418: bipush #-112
    //   420: bastore
    //   421: dup
    //   422: bipush #18
    //   424: bipush #-107
    //   426: bastore
    //   427: dup
    //   428: bipush #19
    //   430: bipush #11
    //   432: bastore
    //   433: dup
    //   434: bipush #20
    //   436: bipush #22
    //   438: bastore
    //   439: dup
    //   440: bipush #21
    //   442: bipush #-5
    //   444: bastore
    //   445: dup
    //   446: bipush #22
    //   448: bipush #-46
    //   450: bastore
    //   451: dup
    //   452: bipush #23
    //   454: bipush #70
    //   456: bastore
    //   457: dup
    //   458: bipush #24
    //   460: bipush #40
    //   462: bastore
    //   463: dup
    //   464: bipush #25
    //   466: bipush #-15
    //   468: bastore
    //   469: dup
    //   470: bipush #26
    //   472: bipush #-48
    //   474: bastore
    //   475: dup
    //   476: bipush #27
    //   478: bipush #-44
    //   480: bastore
    //   481: dup
    //   482: bipush #28
    //   484: bipush #67
    //   486: bastore
    //   487: dup
    //   488: bipush #29
    //   490: bipush #-36
    //   492: bastore
    //   493: dup
    //   494: bipush #30
    //   496: bipush #-69
    //   498: bastore
    //   499: dup
    //   500: bipush #31
    //   502: bipush #-29
    //   504: bastore
    //   505: invokespecial <init> : ([B)V
    //   508: putstatic burp/Zl55.ZZ : Ljava/lang/Object;
    //   511: return
  }
  
  private static Throwable a(Throwable paramThrowable) {
    return paramThrowable;
  }
  
  private static String a(int paramInt1, int paramInt2) {
    int i = (paramInt1 ^ 0xFFFF8255) & 0xFFFF;
    if (b[i] == null) {
      char[] arrayOfChar = a[i].toCharArray();
      switch (arrayOfChar[0] & 0xFF) {
        case 0:
        
        case 1:
        
        case 2:
        
        case 3:
        
        case 4:
        
        case 5:
        
        case 6:
        
        case 7:
        
        case 8:
        
        case 9:
        
        case 10:
        
        case 11:
        
        case 12:
        
        case 13:
        
        case 14:
        
        case 15:
        
        case 16:
        
        case 17:
        
        case 18:
        
        case 19:
        
        case 20:
        
        case 21:
        
        case 22:
        
        case 23:
        
        case 24:
        
        case 25:
        
        case 26:
        
        case 27:
        
        case 28:
        
        case 29:
        
        case 30:
        
        case 31:
        
        case 32:
        
        case 33:
        
        case 34:
        
        case 35:
        
        case 36:
        
        case 37:
        
        case 38:
        
        case 39:
        
        case 40:
        
        case 41:
        
        case 42:
        
        case 43:
        
        case 44:
        
        case 45:
        
        case 46:
        
        case 47:
        
        case 48:
        
        case 49:
        
        case 50:
        
        case 51:
        
        case 52:
        
        case 53:
        
        case 54:
        
        case 55:
        
        case 56:
        
        case 57:
        
        case 58:
        
        case 59:
        
        case 60:
        
        case 61:
        
        case 62:
        
        case 63:
        
        case 64:
        
        case 65:
        
        case 66:
        
        case 67:
        
        case 68:
        
        case 69:
        
        case 70:
        
        case 71:
        
        case 72:
        
        case 73:
        
        case 74:
        
        case 75:
        
        case 76:
        
        case 77:
        
        case 78:
        
        case 79:
        
        case 80:
        
        case 81:
        
        case 82:
        
        case 83:
        
        case 84:
        
        case 85:
        
        case 86:
        
        case 87:
        
        case 88:
        
        case 89:
        
        case 90:
        
        case 91:
        
        case 92:
        
        case 93:
        
        case 94:
        
        case 95:
        
        case 96:
        
        case 97:
        
        case 98:
        
        case 99:
        
        case 100:
        
        case 101:
        
        case 102:
        
        case 103:
        
        case 104:
        
        case 105:
        
        case 106:
        
        case 107:
        
        case 108:
        
        case 109:
        
        case 110:
        
        case 111:
        
        case 112:
        
        case 113:
        
        case 114:
        
        case 115:
        
        case 116:
        
        case 117:
        
        case 118:
        
        case 119:
        
        case 120:
        
        case 121:
        
        case 122:
        
        case 123:
        
        case 124:
        
        case 125:
        
        case 126:
        
        case 127:
        
        case 128:
        
        case 129:
        
        case 130:
        
        case 131:
        
        case 132:
        
        case 133:
        
        case 134:
        
        case 135:
        
        case 136:
        
        case 137:
        
        case 138:
        
        case 139:
        
        case 140:
        
        case 141:
        
        case 142:
        
        case 143:
        
        case 144:
        
        case 145:
        
        case 146:
        
        case 147:
        
        case 148:
        
        case 149:
        
        case 150:
        
        case 151:
        
        case 152:
        
        case 153:
        
        case 154:
        
        case 155:
        
        case 156:
        
        case 157:
        
        case 158:
        
        case 159:
        
        case 160:
        
        case 161:
        
        case 162:
        
        case 163:
        
        case 164:
        
        case 165:
        
        case 166:
        
        case 167:
        
        case 168:
        
        case 169:
        
        case 170:
        
        case 171:
        
        case 172:
        
        case 173:
        
        case 174:
        
        case 175:
        
        case 176:
        
        case 177:
        
        case 178:
        
        case 179:
        
        case 180:
        
        case 181:
        
        case 182:
        
        case 183:
        
        case 184:
        
        case 185:
        
        case 186:
        
        case 187:
        
        case 188:
        
        case 189:
        
        case 190:
        
        case 191:
        
        case 192:
        
        case 193:
        
        case 194:
        
        case 195:
        
        case 196:
        
        case 197:
        
        case 198:
        
        case 199:
        
        case 200:
        
        case 201:
        
        case 202:
        
        case 203:
        
        case 204:
        
        case 205:
        
        case 206:
        
        case 207:
        
        case 208:
        
        case 209:
        
        case 210:
        
        case 211:
        
        case 212:
        
        case 213:
        
        case 214:
        
        case 215:
        
        case 216:
        
        case 217:
        
        case 218:
        
        case 219:
        
        case 220:
        
        case 221:
        
        case 222:
        
        case 223:
        
        case 224:
        
        case 225:
        
        case 226:
        
        case 227:
        
        case 228:
        
        case 229:
        
        case 230:
        
        case 231:
        
        case 232:
        
        case 233:
        
        case 234:
        
        case 235:
        
        case 236:
        
        case 237:
        
        case 238:
        
        case 239:
        
        case 240:
        
        case 241:
        
        case 242:
        
        case 243:
        
        case 244:
        
        case 245:
        
        case 246:
        
        case 247:
        
        case 248:
        
        case 249:
        
        case 250:
        
        case 251:
        
        case 252:
        
        case 253:
        
        case 254:
        
        default:
          break;
      } 
      byte b1 = 108;
      int j = (paramInt2 & 0xFF) - b1;
      if (j < 0)
        j += 256; 
      int k = ((paramInt2 & 0xFFFF) >>> 8) - b1;
      if (k < 0)
        k += 256; 
      for (byte b2 = 0; b2 < arrayOfChar.length; b2++) {
        int m = b2 % 2;
        if (m == 0) {
          arrayOfChar[b2] = (char)(arrayOfChar[b2] ^ j);
          j = ((j >>> 3 | j << 5) ^ arrayOfChar[b2]) & 0xFF;
        } else {
          arrayOfChar[b2] = (char)(arrayOfChar[b2] ^ k);
          k = ((k >>> 3 | k << 5) ^ arrayOfChar[b2]) & 0xFF;
        } 
      } 
      b[i] = (new String(arrayOfChar)).intern();
    } 
    return b[i];
  }
}


/* Location:              C:\Program Files\BurpSuitePro\burpsuite_pro.jar!\burp\Zl55.class
 * Java compiler version: 21 (65.0)
 * JD-Core Version:       1.1.3
 */