package burp;

import java.math.BigInteger;

class Zl5b extends ClassLoader {
  static Object ZI;
  
  static String Zi;
  
  private static final String[] a;
  
  private static final String[] b;
  
  static boolean Zx(Object[] paramArrayOfObject, Object paramObject) throws Throwable {
    // Byte code:
    //   0: invokestatic ZN : ()Z
    //   3: istore_2
    //   4: sipush #-18100
    //   7: sipush #-18931
    //   10: invokestatic a : (II)Ljava/lang/String;
    //   13: invokestatic forName : (Ljava/lang/String;)Ljava/lang/Class;
    //   16: invokestatic ZM : (Ljava/lang/Object;)V
    //   19: new java/lang/StringBuilder
    //   22: dup
    //   23: invokespecial <init> : ()V
    //   26: astore_3
    //   27: iconst_0
    //   28: istore #4
    //   30: iload #4
    //   32: bipush #32
    //   34: if_icmpge -> 1367
    //   37: iload #4
    //   39: tableswitch default -> 1360, 0 -> 180, 1 -> 217, 2 -> 254, 3 -> 291, 4 -> 328, 5 -> 365, 6 -> 402, 7 -> 439, 8 -> 476, 9 -> 513, 10 -> 550, 11 -> 587, 12 -> 624, 13 -> 661, 14 -> 698, 15 -> 735, 16 -> 772, 17 -> 809, 18 -> 846, 19 -> 883, 20 -> 920, 21 -> 957, 22 -> 994, 23 -> 1031, 24 -> 1068, 25 -> 1105, 26 -> 1142, 27 -> 1179, 28 -> 1216, 29 -> 1253, 30 -> 1290, 31 -> 1327
    //   180: aload_3
    //   181: getstatic burp/Zxso.ZH : Ljava/lang/String;
    //   184: getstatic burp/Zx58.ZE : Ljava/lang/Object;
    //   187: checkcast java/math/BigInteger
    //   190: invokevirtual intValue : ()I
    //   193: bipush #32
    //   195: irem
    //   196: invokestatic abs : (I)I
    //   199: invokevirtual charAt : (I)C
    //   202: invokevirtual append : (C)Ljava/lang/StringBuilder;
    //   205: pop
    //   206: iload_2
    //   207: ifne -> 1360
    //   210: goto -> 217
    //   213: invokestatic a : (Ljava/lang/Throwable;)Ljava/lang/Throwable;
    //   216: athrow
    //   217: aload_3
    //   218: getstatic burp/Zg5.ZF : Ljava/lang/String;
    //   221: getstatic burp/Zmy3.Zx : Ljava/lang/Object;
    //   224: checkcast java/math/BigInteger
    //   227: invokevirtual intValue : ()I
    //   230: bipush #32
    //   232: irem
    //   233: invokestatic abs : (I)I
    //   236: invokevirtual charAt : (I)C
    //   239: invokevirtual append : (C)Ljava/lang/StringBuilder;
    //   242: pop
    //   243: iload_2
    //   244: ifne -> 1360
    //   247: goto -> 254
    //   250: invokestatic a : (Ljava/lang/Throwable;)Ljava/lang/Throwable;
    //   253: athrow
    //   254: aload_3
    //   255: getstatic burp/Zgpx.Z_ : Ljava/lang/String;
    //   258: getstatic burp/Zx4y.Zc : Ljava/lang/Object;
    //   261: checkcast java/math/BigInteger
    //   264: invokevirtual intValue : ()I
    //   267: bipush #32
    //   269: irem
    //   270: invokestatic abs : (I)I
    //   273: invokevirtual charAt : (I)C
    //   276: invokevirtual append : (C)Ljava/lang/StringBuilder;
    //   279: pop
    //   280: iload_2
    //   281: ifne -> 1360
    //   284: goto -> 291
    //   287: invokestatic a : (Ljava/lang/Throwable;)Ljava/lang/Throwable;
    //   290: athrow
    //   291: aload_3
    //   292: getstatic burp/Zl3n.Zy : Ljava/lang/String;
    //   295: getstatic burp/Zrjg.ZG : Ljava/lang/Object;
    //   298: checkcast java/math/BigInteger
    //   301: invokevirtual intValue : ()I
    //   304: bipush #32
    //   306: irem
    //   307: invokestatic abs : (I)I
    //   310: invokevirtual charAt : (I)C
    //   313: invokevirtual append : (C)Ljava/lang/StringBuilder;
    //   316: pop
    //   317: iload_2
    //   318: ifne -> 1360
    //   321: goto -> 328
    //   324: invokestatic a : (Ljava/lang/Throwable;)Ljava/lang/Throwable;
    //   327: athrow
    //   328: aload_3
    //   329: getstatic burp/Zso7.Zr : Ljava/lang/String;
    //   332: getstatic burp/Zejj.Zy : Ljava/lang/Object;
    //   335: checkcast java/math/BigInteger
    //   338: invokevirtual intValue : ()I
    //   341: bipush #32
    //   343: irem
    //   344: invokestatic abs : (I)I
    //   347: invokevirtual charAt : (I)C
    //   350: invokevirtual append : (C)Ljava/lang/StringBuilder;
    //   353: pop
    //   354: iload_2
    //   355: ifne -> 1360
    //   358: goto -> 365
    //   361: invokestatic a : (Ljava/lang/Throwable;)Ljava/lang/Throwable;
    //   364: athrow
    //   365: aload_3
    //   366: getstatic burp/Zz0b.ZD : Ljava/lang/String;
    //   369: getstatic burp/Zg2u.ZI : Ljava/lang/Object;
    //   372: checkcast java/math/BigInteger
    //   375: invokevirtual intValue : ()I
    //   378: bipush #32
    //   380: irem
    //   381: invokestatic abs : (I)I
    //   384: invokevirtual charAt : (I)C
    //   387: invokevirtual append : (C)Ljava/lang/StringBuilder;
    //   390: pop
    //   391: iload_2
    //   392: ifne -> 1360
    //   395: goto -> 402
    //   398: invokestatic a : (Ljava/lang/Throwable;)Ljava/lang/Throwable;
    //   401: athrow
    //   402: aload_3
    //   403: getstatic burp/Zlbd.Zq : Ljava/lang/String;
    //   406: getstatic burp/Ztjh.ZU : Ljava/lang/Object;
    //   409: checkcast java/math/BigInteger
    //   412: invokevirtual intValue : ()I
    //   415: bipush #32
    //   417: irem
    //   418: invokestatic abs : (I)I
    //   421: invokevirtual charAt : (I)C
    //   424: invokevirtual append : (C)Ljava/lang/StringBuilder;
    //   427: pop
    //   428: iload_2
    //   429: ifne -> 1360
    //   432: goto -> 439
    //   435: invokestatic a : (Ljava/lang/Throwable;)Ljava/lang/Throwable;
    //   438: athrow
    //   439: aload_3
    //   440: getstatic burp/Zmcb.Zl : Ljava/lang/String;
    //   443: getstatic burp/Zb_u.Zp : Ljava/lang/Object;
    //   446: checkcast java/math/BigInteger
    //   449: invokevirtual intValue : ()I
    //   452: bipush #32
    //   454: irem
    //   455: invokestatic abs : (I)I
    //   458: invokevirtual charAt : (I)C
    //   461: invokevirtual append : (C)Ljava/lang/StringBuilder;
    //   464: pop
    //   465: iload_2
    //   466: ifne -> 1360
    //   469: goto -> 476
    //   472: invokestatic a : (Ljava/lang/Throwable;)Ljava/lang/Throwable;
    //   475: athrow
    //   476: aload_3
    //   477: getstatic burp/Zlgh.Zm : Ljava/lang/String;
    //   480: getstatic burp/Zxl5.Zh : Ljava/lang/Object;
    //   483: checkcast java/math/BigInteger
    //   486: invokevirtual intValue : ()I
    //   489: bipush #32
    //   491: irem
    //   492: invokestatic abs : (I)I
    //   495: invokevirtual charAt : (I)C
    //   498: invokevirtual append : (C)Ljava/lang/StringBuilder;
    //   501: pop
    //   502: iload_2
    //   503: ifne -> 1360
    //   506: goto -> 513
    //   509: invokestatic a : (Ljava/lang/Throwable;)Ljava/lang/Throwable;
    //   512: athrow
    //   513: aload_3
    //   514: getstatic burp/Zl_u.Zc : Ljava/lang/String;
    //   517: getstatic burp/Zry7.ZZ : Ljava/lang/Object;
    //   520: checkcast java/math/BigInteger
    //   523: invokevirtual intValue : ()I
    //   526: bipush #32
    //   528: irem
    //   529: invokestatic abs : (I)I
    //   532: invokevirtual charAt : (I)C
    //   535: invokevirtual append : (C)Ljava/lang/StringBuilder;
    //   538: pop
    //   539: iload_2
    //   540: ifne -> 1360
    //   543: goto -> 550
    //   546: invokestatic a : (Ljava/lang/Throwable;)Ljava/lang/Throwable;
    //   549: athrow
    //   550: aload_3
    //   551: getstatic burp/Ze5f.Zt : Ljava/lang/String;
    //   554: getstatic burp/Zml2.Zo : Ljava/lang/Object;
    //   557: checkcast java/math/BigInteger
    //   560: invokevirtual intValue : ()I
    //   563: bipush #32
    //   565: irem
    //   566: invokestatic abs : (I)I
    //   569: invokevirtual charAt : (I)C
    //   572: invokevirtual append : (C)Ljava/lang/StringBuilder;
    //   575: pop
    //   576: iload_2
    //   577: ifne -> 1360
    //   580: goto -> 587
    //   583: invokestatic a : (Ljava/lang/Throwable;)Ljava/lang/Throwable;
    //   586: athrow
    //   587: aload_3
    //   588: getstatic burp/Zrnu.ZO : Ljava/lang/String;
    //   591: getstatic burp/Zgw7.Zi : Ljava/lang/Object;
    //   594: checkcast java/math/BigInteger
    //   597: invokevirtual intValue : ()I
    //   600: bipush #32
    //   602: irem
    //   603: invokestatic abs : (I)I
    //   606: invokevirtual charAt : (I)C
    //   609: invokevirtual append : (C)Ljava/lang/StringBuilder;
    //   612: pop
    //   613: iload_2
    //   614: ifne -> 1360
    //   617: goto -> 624
    //   620: invokestatic a : (Ljava/lang/Throwable;)Ljava/lang/Throwable;
    //   623: athrow
    //   624: aload_3
    //   625: getstatic burp/Zb29.Zf : Ljava/lang/String;
    //   628: getstatic burp/Zltb.ZL : Ljava/lang/Object;
    //   631: checkcast java/math/BigInteger
    //   634: invokevirtual intValue : ()I
    //   637: bipush #32
    //   639: irem
    //   640: invokestatic abs : (I)I
    //   643: invokevirtual charAt : (I)C
    //   646: invokevirtual append : (C)Ljava/lang/StringBuilder;
    //   649: pop
    //   650: iload_2
    //   651: ifne -> 1360
    //   654: goto -> 661
    //   657: invokestatic a : (Ljava/lang/Throwable;)Ljava/lang/Throwable;
    //   660: athrow
    //   661: aload_3
    //   662: getstatic burp/Zrc0.ZL : Ljava/lang/String;
    //   665: getstatic burp/Zsqi.Zf : Ljava/lang/Object;
    //   668: checkcast java/math/BigInteger
    //   671: invokevirtual intValue : ()I
    //   674: bipush #32
    //   676: irem
    //   677: invokestatic abs : (I)I
    //   680: invokevirtual charAt : (I)C
    //   683: invokevirtual append : (C)Ljava/lang/StringBuilder;
    //   686: pop
    //   687: iload_2
    //   688: ifne -> 1360
    //   691: goto -> 698
    //   694: invokestatic a : (Ljava/lang/Throwable;)Ljava/lang/Throwable;
    //   697: athrow
    //   698: aload_3
    //   699: getstatic burp/Zzou.ZN : Ljava/lang/String;
    //   702: getstatic burp/Zlp7.ZM : Ljava/lang/Object;
    //   705: checkcast java/math/BigInteger
    //   708: invokevirtual intValue : ()I
    //   711: bipush #32
    //   713: irem
    //   714: invokestatic abs : (I)I
    //   717: invokevirtual charAt : (I)C
    //   720: invokevirtual append : (C)Ljava/lang/StringBuilder;
    //   723: pop
    //   724: iload_2
    //   725: ifne -> 1360
    //   728: goto -> 735
    //   731: invokestatic a : (Ljava/lang/Throwable;)Ljava/lang/Throwable;
    //   734: athrow
    //   735: aload_3
    //   736: getstatic burp/Zx_u.Z_ : Ljava/lang/String;
    //   739: getstatic burp/Zb6b.ZU : Ljava/lang/Object;
    //   742: checkcast java/math/BigInteger
    //   745: invokevirtual intValue : ()I
    //   748: bipush #32
    //   750: irem
    //   751: invokestatic abs : (I)I
    //   754: invokevirtual charAt : (I)C
    //   757: invokevirtual append : (C)Ljava/lang/StringBuilder;
    //   760: pop
    //   761: iload_2
    //   762: ifne -> 1360
    //   765: goto -> 772
    //   768: invokestatic a : (Ljava/lang/Throwable;)Ljava/lang/Throwable;
    //   771: athrow
    //   772: aload_3
    //   773: getstatic burp/Zr9b.ZC : Ljava/lang/String;
    //   776: getstatic burp/Zl39.ZA : Ljava/lang/Object;
    //   779: checkcast java/math/BigInteger
    //   782: invokevirtual intValue : ()I
    //   785: bipush #32
    //   787: irem
    //   788: invokestatic abs : (I)I
    //   791: invokevirtual charAt : (I)C
    //   794: invokevirtual append : (C)Ljava/lang/StringBuilder;
    //   797: pop
    //   798: iload_2
    //   799: ifne -> 1360
    //   802: goto -> 809
    //   805: invokestatic a : (Ljava/lang/Throwable;)Ljava/lang/Throwable;
    //   808: athrow
    //   809: aload_3
    //   810: getstatic burp/Zs_3.ZC : Ljava/lang/String;
    //   813: getstatic burp/Zs9u.Zd : Ljava/lang/Object;
    //   816: checkcast java/math/BigInteger
    //   819: invokevirtual intValue : ()I
    //   822: bipush #32
    //   824: irem
    //   825: invokestatic abs : (I)I
    //   828: invokevirtual charAt : (I)C
    //   831: invokevirtual append : (C)Ljava/lang/StringBuilder;
    //   834: pop
    //   835: iload_2
    //   836: ifne -> 1360
    //   839: goto -> 846
    //   842: invokestatic a : (Ljava/lang/Throwable;)Ljava/lang/Throwable;
    //   845: athrow
    //   846: aload_3
    //   847: getstatic burp/Zkm0.ZL : Ljava/lang/String;
    //   850: getstatic burp/Zgz1.ZX : Ljava/lang/Object;
    //   853: checkcast java/math/BigInteger
    //   856: invokevirtual intValue : ()I
    //   859: bipush #32
    //   861: irem
    //   862: invokestatic abs : (I)I
    //   865: invokevirtual charAt : (I)C
    //   868: invokevirtual append : (C)Ljava/lang/StringBuilder;
    //   871: pop
    //   872: iload_2
    //   873: ifne -> 1360
    //   876: goto -> 883
    //   879: invokestatic a : (Ljava/lang/Throwable;)Ljava/lang/Throwable;
    //   882: athrow
    //   883: aload_3
    //   884: getstatic burp/Zlvx.Zr : Ljava/lang/String;
    //   887: getstatic burp/Zrka.Zr : Ljava/lang/Object;
    //   890: checkcast java/math/BigInteger
    //   893: invokevirtual intValue : ()I
    //   896: bipush #32
    //   898: irem
    //   899: invokestatic abs : (I)I
    //   902: invokevirtual charAt : (I)C
    //   905: invokevirtual append : (C)Ljava/lang/StringBuilder;
    //   908: pop
    //   909: iload_2
    //   910: ifne -> 1360
    //   913: goto -> 920
    //   916: invokestatic a : (Ljava/lang/Throwable;)Ljava/lang/Throwable;
    //   919: athrow
    //   920: aload_3
    //   921: getstatic burp/Ztex.Zx : Ljava/lang/String;
    //   924: getstatic burp/Zmlr.Zh : Ljava/lang/Object;
    //   927: checkcast java/math/BigInteger
    //   930: invokevirtual intValue : ()I
    //   933: bipush #32
    //   935: irem
    //   936: invokestatic abs : (I)I
    //   939: invokevirtual charAt : (I)C
    //   942: invokevirtual append : (C)Ljava/lang/StringBuilder;
    //   945: pop
    //   946: iload_2
    //   947: ifne -> 1360
    //   950: goto -> 957
    //   953: invokestatic a : (Ljava/lang/Throwable;)Ljava/lang/Throwable;
    //   956: athrow
    //   957: aload_3
    //   958: getstatic burp/Zezq.Zp : Ljava/lang/String;
    //   961: getstatic burp/Zlnq.ZO : Ljava/lang/Object;
    //   964: checkcast java/math/BigInteger
    //   967: invokevirtual intValue : ()I
    //   970: bipush #32
    //   972: irem
    //   973: invokestatic abs : (I)I
    //   976: invokevirtual charAt : (I)C
    //   979: invokevirtual append : (C)Ljava/lang/StringBuilder;
    //   982: pop
    //   983: iload_2
    //   984: ifne -> 1360
    //   987: goto -> 994
    //   990: invokestatic a : (Ljava/lang/Throwable;)Ljava/lang/Throwable;
    //   993: athrow
    //   994: aload_3
    //   995: getstatic burp/Zr9b.ZC : Ljava/lang/String;
    //   998: getstatic burp/Zer1.ZL : Ljava/lang/Object;
    //   1001: checkcast java/math/BigInteger
    //   1004: invokevirtual intValue : ()I
    //   1007: bipush #32
    //   1009: irem
    //   1010: invokestatic abs : (I)I
    //   1013: invokevirtual charAt : (I)C
    //   1016: invokevirtual append : (C)Ljava/lang/StringBuilder;
    //   1019: pop
    //   1020: iload_2
    //   1021: ifne -> 1360
    //   1024: goto -> 1031
    //   1027: invokestatic a : (Ljava/lang/Throwable;)Ljava/lang/Throwable;
    //   1030: athrow
    //   1031: aload_3
    //   1032: getstatic burp/Zgny.Zf : Ljava/lang/String;
    //   1035: getstatic burp/Zep1.ZW : Ljava/lang/Object;
    //   1038: checkcast java/math/BigInteger
    //   1041: invokevirtual intValue : ()I
    //   1044: bipush #32
    //   1046: irem
    //   1047: invokestatic abs : (I)I
    //   1050: invokevirtual charAt : (I)C
    //   1053: invokevirtual append : (C)Ljava/lang/StringBuilder;
    //   1056: pop
    //   1057: iload_2
    //   1058: ifne -> 1360
    //   1061: goto -> 1068
    //   1064: invokestatic a : (Ljava/lang/Throwable;)Ljava/lang/Throwable;
    //   1067: athrow
    //   1068: aload_3
    //   1069: getstatic burp/Zgds.ZA : Ljava/lang/String;
    //   1072: getstatic burp/Zro2.Zu : Ljava/lang/Object;
    //   1075: checkcast java/math/BigInteger
    //   1078: invokevirtual intValue : ()I
    //   1081: bipush #32
    //   1083: irem
    //   1084: invokestatic abs : (I)I
    //   1087: invokevirtual charAt : (I)C
    //   1090: invokevirtual append : (C)Ljava/lang/StringBuilder;
    //   1093: pop
    //   1094: iload_2
    //   1095: ifne -> 1360
    //   1098: goto -> 1105
    //   1101: invokestatic a : (Ljava/lang/Throwable;)Ljava/lang/Throwable;
    //   1104: athrow
    //   1105: aload_3
    //   1106: getstatic burp/Zm3x.Zu : Ljava/lang/String;
    //   1109: getstatic burp/Zlhu.ZJ : Ljava/lang/Object;
    //   1112: checkcast java/math/BigInteger
    //   1115: invokevirtual intValue : ()I
    //   1118: bipush #32
    //   1120: irem
    //   1121: invokestatic abs : (I)I
    //   1124: invokevirtual charAt : (I)C
    //   1127: invokevirtual append : (C)Ljava/lang/StringBuilder;
    //   1130: pop
    //   1131: iload_2
    //   1132: ifne -> 1360
    //   1135: goto -> 1142
    //   1138: invokestatic a : (Ljava/lang/Throwable;)Ljava/lang/Throwable;
    //   1141: athrow
    //   1142: aload_3
    //   1143: getstatic burp/Zgb9.Zk : Ljava/lang/String;
    //   1146: getstatic burp/Zrcu.Zs : Ljava/lang/Object;
    //   1149: checkcast java/math/BigInteger
    //   1152: invokevirtual intValue : ()I
    //   1155: bipush #32
    //   1157: irem
    //   1158: invokestatic abs : (I)I
    //   1161: invokevirtual charAt : (I)C
    //   1164: invokevirtual append : (C)Ljava/lang/StringBuilder;
    //   1167: pop
    //   1168: iload_2
    //   1169: ifne -> 1360
    //   1172: goto -> 1179
    //   1175: invokestatic a : (Ljava/lang/Throwable;)Ljava/lang/Throwable;
    //   1178: athrow
    //   1179: aload_3
    //   1180: getstatic burp/Zscz.ZJ : Ljava/lang/String;
    //   1183: getstatic burp/Zec_.ZN : Ljava/lang/Object;
    //   1186: checkcast java/math/BigInteger
    //   1189: invokevirtual intValue : ()I
    //   1192: bipush #32
    //   1194: irem
    //   1195: invokestatic abs : (I)I
    //   1198: invokevirtual charAt : (I)C
    //   1201: invokevirtual append : (C)Ljava/lang/StringBuilder;
    //   1204: pop
    //   1205: iload_2
    //   1206: ifne -> 1360
    //   1209: goto -> 1216
    //   1212: invokestatic a : (Ljava/lang/Throwable;)Ljava/lang/Throwable;
    //   1215: athrow
    //   1216: aload_3
    //   1217: getstatic burp/Zevf.ZL : Ljava/lang/String;
    //   1220: getstatic burp/Ztuj.Ze : Ljava/lang/Object;
    //   1223: checkcast java/math/BigInteger
    //   1226: invokevirtual intValue : ()I
    //   1229: bipush #32
    //   1231: irem
    //   1232: invokestatic abs : (I)I
    //   1235: invokevirtual charAt : (I)C
    //   1238: invokevirtual append : (C)Ljava/lang/StringBuilder;
    //   1241: pop
    //   1242: iload_2
    //   1243: ifne -> 1360
    //   1246: goto -> 1253
    //   1249: invokestatic a : (Ljava/lang/Throwable;)Ljava/lang/Throwable;
    //   1252: athrow
    //   1253: aload_3
    //   1254: getstatic burp/Zlyf.ZU : Ljava/lang/String;
    //   1257: getstatic burp/Zxn7.ZU : Ljava/lang/Object;
    //   1260: checkcast java/math/BigInteger
    //   1263: invokevirtual intValue : ()I
    //   1266: bipush #32
    //   1268: irem
    //   1269: invokestatic abs : (I)I
    //   1272: invokevirtual charAt : (I)C
    //   1275: invokevirtual append : (C)Ljava/lang/StringBuilder;
    //   1278: pop
    //   1279: iload_2
    //   1280: ifne -> 1360
    //   1283: goto -> 1290
    //   1286: invokestatic a : (Ljava/lang/Throwable;)Ljava/lang/Throwable;
    //   1289: athrow
    //   1290: aload_3
    //   1291: getstatic burp/Zmd.Zf : Ljava/lang/String;
    //   1294: getstatic burp/Ztsc.Zr : Ljava/lang/Object;
    //   1297: checkcast java/math/BigInteger
    //   1300: invokevirtual intValue : ()I
    //   1303: bipush #32
    //   1305: irem
    //   1306: invokestatic abs : (I)I
    //   1309: invokevirtual charAt : (I)C
    //   1312: invokevirtual append : (C)Ljava/lang/StringBuilder;
    //   1315: pop
    //   1316: iload_2
    //   1317: ifne -> 1360
    //   1320: goto -> 1327
    //   1323: invokestatic a : (Ljava/lang/Throwable;)Ljava/lang/Throwable;
    //   1326: athrow
    //   1327: aload_3
    //   1328: getstatic burp/Zejg.ZP : Ljava/lang/String;
    //   1331: getstatic burp/Zk7b.ZR : Ljava/lang/Object;
    //   1334: checkcast java/math/BigInteger
    //   1337: invokevirtual intValue : ()I
    //   1340: bipush #32
    //   1342: irem
    //   1343: invokestatic abs : (I)I
    //   1346: invokevirtual charAt : (I)C
    //   1349: invokevirtual append : (C)Ljava/lang/StringBuilder;
    //   1352: pop
    //   1353: goto -> 1360
    //   1356: invokestatic a : (Ljava/lang/Throwable;)Ljava/lang/Throwable;
    //   1359: athrow
    //   1360: iinc #4, 1
    //   1363: iload_2
    //   1364: ifne -> 30
    //   1367: aload_3
    //   1368: invokevirtual toString : ()Ljava/lang/String;
    //   1371: putstatic burp/Zmt_.ZH : Ljava/lang/String;
    //   1374: getstatic burp/Zb_c.ZN : Ljava/lang/Object;
    //   1377: checkcast java/math/BigInteger
    //   1380: invokevirtual toByteArray : ()[B
    //   1383: astore #4
    //   1385: iconst_0
    //   1386: istore #6
    //   1388: iconst_0
    //   1389: istore #7
    //   1391: iload #7
    //   1393: aload #4
    //   1395: arraylength
    //   1396: if_icmpge -> 1542
    //   1399: aload #4
    //   1401: iload #7
    //   1403: baload
    //   1404: istore #8
    //   1406: iload #8
    //   1408: bipush #48
    //   1410: if_icmplt -> 1427
    //   1413: iload #8
    //   1415: bipush #57
    //   1417: if_icmple -> 1525
    //   1420: goto -> 1427
    //   1423: invokestatic a : (Ljava/lang/Throwable;)Ljava/lang/Throwable;
    //   1426: athrow
    //   1427: iload #8
    //   1429: bipush #65
    //   1431: if_icmplt -> 1455
    //   1434: goto -> 1441
    //   1437: invokestatic a : (Ljava/lang/Throwable;)Ljava/lang/Throwable;
    //   1440: athrow
    //   1441: iload #8
    //   1443: bipush #90
    //   1445: if_icmple -> 1525
    //   1448: goto -> 1455
    //   1451: invokestatic a : (Ljava/lang/Throwable;)Ljava/lang/Throwable;
    //   1454: athrow
    //   1455: iload #8
    //   1457: bipush #97
    //   1459: if_icmplt -> 1483
    //   1462: goto -> 1469
    //   1465: invokestatic a : (Ljava/lang/Throwable;)Ljava/lang/Throwable;
    //   1468: athrow
    //   1469: iload #8
    //   1471: bipush #122
    //   1473: if_icmple -> 1525
    //   1476: goto -> 1483
    //   1479: invokestatic a : (Ljava/lang/Throwable;)Ljava/lang/Throwable;
    //   1482: athrow
    //   1483: iload #8
    //   1485: bipush #43
    //   1487: if_icmpeq -> 1525
    //   1490: goto -> 1497
    //   1493: invokestatic a : (Ljava/lang/Throwable;)Ljava/lang/Throwable;
    //   1496: athrow
    //   1497: iload #8
    //   1499: bipush #47
    //   1501: if_icmpeq -> 1525
    //   1504: goto -> 1511
    //   1507: invokestatic a : (Ljava/lang/Throwable;)Ljava/lang/Throwable;
    //   1510: athrow
    //   1511: iload #8
    //   1513: bipush #61
    //   1515: if_icmpne -> 1535
    //   1518: goto -> 1525
    //   1521: invokestatic a : (Ljava/lang/Throwable;)Ljava/lang/Throwable;
    //   1524: athrow
    //   1525: iinc #6, 1
    //   1528: goto -> 1535
    //   1531: invokestatic a : (Ljava/lang/Throwable;)Ljava/lang/Throwable;
    //   1534: athrow
    //   1535: iinc #7, 1
    //   1538: iload_2
    //   1539: ifne -> 1391
    //   1542: iload #6
    //   1544: newarray byte
    //   1546: astore #7
    //   1548: iconst_0
    //   1549: istore #8
    //   1551: iconst_0
    //   1552: istore #9
    //   1554: iload #9
    //   1556: aload #4
    //   1558: arraylength
    //   1559: if_icmpge -> 1712
    //   1562: aload #4
    //   1564: iload #9
    //   1566: baload
    //   1567: istore #10
    //   1569: iload #10
    //   1571: bipush #48
    //   1573: if_icmplt -> 1590
    //   1576: iload #10
    //   1578: bipush #57
    //   1580: if_icmple -> 1688
    //   1583: goto -> 1590
    //   1586: invokestatic a : (Ljava/lang/Throwable;)Ljava/lang/Throwable;
    //   1589: athrow
    //   1590: iload #10
    //   1592: bipush #65
    //   1594: if_icmplt -> 1618
    //   1597: goto -> 1604
    //   1600: invokestatic a : (Ljava/lang/Throwable;)Ljava/lang/Throwable;
    //   1603: athrow
    //   1604: iload #10
    //   1606: bipush #90
    //   1608: if_icmple -> 1688
    //   1611: goto -> 1618
    //   1614: invokestatic a : (Ljava/lang/Throwable;)Ljava/lang/Throwable;
    //   1617: athrow
    //   1618: iload #10
    //   1620: bipush #97
    //   1622: if_icmplt -> 1646
    //   1625: goto -> 1632
    //   1628: invokestatic a : (Ljava/lang/Throwable;)Ljava/lang/Throwable;
    //   1631: athrow
    //   1632: iload #10
    //   1634: bipush #122
    //   1636: if_icmple -> 1688
    //   1639: goto -> 1646
    //   1642: invokestatic a : (Ljava/lang/Throwable;)Ljava/lang/Throwable;
    //   1645: athrow
    //   1646: iload #10
    //   1648: bipush #43
    //   1650: if_icmpeq -> 1688
    //   1653: goto -> 1660
    //   1656: invokestatic a : (Ljava/lang/Throwable;)Ljava/lang/Throwable;
    //   1659: athrow
    //   1660: iload #10
    //   1662: bipush #47
    //   1664: if_icmpeq -> 1688
    //   1667: goto -> 1674
    //   1670: invokestatic a : (Ljava/lang/Throwable;)Ljava/lang/Throwable;
    //   1673: athrow
    //   1674: iload #10
    //   1676: bipush #61
    //   1678: if_icmpne -> 1705
    //   1681: goto -> 1688
    //   1684: invokestatic a : (Ljava/lang/Throwable;)Ljava/lang/Throwable;
    //   1687: athrow
    //   1688: aload #7
    //   1690: iload #8
    //   1692: iload #10
    //   1694: bastore
    //   1695: iinc #8, 1
    //   1698: goto -> 1705
    //   1701: invokestatic a : (Ljava/lang/Throwable;)Ljava/lang/Throwable;
    //   1704: athrow
    //   1705: iinc #9, 1
    //   1708: iload_2
    //   1709: ifne -> 1554
    //   1712: aload #7
    //   1714: astore #5
    //   1716: aload #5
    //   1718: astore #4
    //   1720: aload #4
    //   1722: arraylength
    //   1723: istore #6
    //   1725: aload #4
    //   1727: iload #6
    //   1729: iconst_1
    //   1730: isub
    //   1731: baload
    //   1732: bipush #61
    //   1734: if_icmpne -> 1744
    //   1737: iinc #6, -1
    //   1740: iload_2
    //   1741: ifne -> 1725
    //   1744: iload #6
    //   1746: aload #4
    //   1748: arraylength
    //   1749: iconst_4
    //   1750: idiv
    //   1751: isub
    //   1752: newarray byte
    //   1754: astore #7
    //   1756: iconst_0
    //   1757: istore #8
    //   1759: iload #8
    //   1761: aload #4
    //   1763: arraylength
    //   1764: if_icmpge -> 2044
    //   1767: aload #4
    //   1769: iload #8
    //   1771: baload
    //   1772: bipush #61
    //   1774: if_icmpne -> 1794
    //   1777: aload #4
    //   1779: iload #8
    //   1781: iconst_0
    //   1782: bastore
    //   1783: iload_2
    //   1784: ifne -> 2037
    //   1787: goto -> 1794
    //   1790: invokestatic a : (Ljava/lang/Throwable;)Ljava/lang/Throwable;
    //   1793: athrow
    //   1794: aload #4
    //   1796: iload #8
    //   1798: baload
    //   1799: bipush #47
    //   1801: if_icmpne -> 1829
    //   1804: goto -> 1811
    //   1807: invokestatic a : (Ljava/lang/Throwable;)Ljava/lang/Throwable;
    //   1810: athrow
    //   1811: aload #4
    //   1813: iload #8
    //   1815: bipush #63
    //   1817: bastore
    //   1818: iload_2
    //   1819: ifne -> 2037
    //   1822: goto -> 1829
    //   1825: invokestatic a : (Ljava/lang/Throwable;)Ljava/lang/Throwable;
    //   1828: athrow
    //   1829: aload #4
    //   1831: iload #8
    //   1833: baload
    //   1834: bipush #43
    //   1836: if_icmpne -> 1864
    //   1839: goto -> 1846
    //   1842: invokestatic a : (Ljava/lang/Throwable;)Ljava/lang/Throwable;
    //   1845: athrow
    //   1846: aload #4
    //   1848: iload #8
    //   1850: bipush #62
    //   1852: bastore
    //   1853: iload_2
    //   1854: ifne -> 2037
    //   1857: goto -> 1864
    //   1860: invokestatic a : (Ljava/lang/Throwable;)Ljava/lang/Throwable;
    //   1863: athrow
    //   1864: aload #4
    //   1866: iload #8
    //   1868: baload
    //   1869: bipush #48
    //   1871: if_icmplt -> 1923
    //   1874: goto -> 1881
    //   1877: invokestatic a : (Ljava/lang/Throwable;)Ljava/lang/Throwable;
    //   1880: athrow
    //   1881: aload #4
    //   1883: iload #8
    //   1885: baload
    //   1886: bipush #57
    //   1888: if_icmpgt -> 1923
    //   1891: goto -> 1898
    //   1894: invokestatic a : (Ljava/lang/Throwable;)Ljava/lang/Throwable;
    //   1897: athrow
    //   1898: aload #4
    //   1900: iload #8
    //   1902: aload #4
    //   1904: iload #8
    //   1906: baload
    //   1907: bipush #-4
    //   1909: isub
    //   1910: i2b
    //   1911: bastore
    //   1912: iload_2
    //   1913: ifne -> 2037
    //   1916: goto -> 1923
    //   1919: invokestatic a : (Ljava/lang/Throwable;)Ljava/lang/Throwable;
    //   1922: athrow
    //   1923: aload #4
    //   1925: iload #8
    //   1927: baload
    //   1928: bipush #97
    //   1930: if_icmplt -> 1982
    //   1933: goto -> 1940
    //   1936: invokestatic a : (Ljava/lang/Throwable;)Ljava/lang/Throwable;
    //   1939: athrow
    //   1940: aload #4
    //   1942: iload #8
    //   1944: baload
    //   1945: bipush #122
    //   1947: if_icmpgt -> 1982
    //   1950: goto -> 1957
    //   1953: invokestatic a : (Ljava/lang/Throwable;)Ljava/lang/Throwable;
    //   1956: athrow
    //   1957: aload #4
    //   1959: iload #8
    //   1961: aload #4
    //   1963: iload #8
    //   1965: baload
    //   1966: bipush #71
    //   1968: isub
    //   1969: i2b
    //   1970: bastore
    //   1971: iload_2
    //   1972: ifne -> 2037
    //   1975: goto -> 1982
    //   1978: invokestatic a : (Ljava/lang/Throwable;)Ljava/lang/Throwable;
    //   1981: athrow
    //   1982: aload #4
    //   1984: iload #8
    //   1986: baload
    //   1987: bipush #65
    //   1989: if_icmplt -> 2037
    //   1992: goto -> 1999
    //   1995: invokestatic a : (Ljava/lang/Throwable;)Ljava/lang/Throwable;
    //   1998: athrow
    //   1999: aload #4
    //   2001: iload #8
    //   2003: baload
    //   2004: bipush #90
    //   2006: if_icmpgt -> 2037
    //   2009: goto -> 2016
    //   2012: invokestatic a : (Ljava/lang/Throwable;)Ljava/lang/Throwable;
    //   2015: athrow
    //   2016: aload #4
    //   2018: iload #8
    //   2020: aload #4
    //   2022: iload #8
    //   2024: baload
    //   2025: bipush #65
    //   2027: isub
    //   2028: i2b
    //   2029: bastore
    //   2030: goto -> 2037
    //   2033: invokestatic a : (Ljava/lang/Throwable;)Ljava/lang/Throwable;
    //   2036: athrow
    //   2037: iinc #8, 1
    //   2040: iload_2
    //   2041: ifne -> 1759
    //   2044: iconst_0
    //   2045: istore #8
    //   2047: iconst_0
    //   2048: istore #9
    //   2050: iload #9
    //   2052: aload #7
    //   2054: arraylength
    //   2055: iconst_2
    //   2056: isub
    //   2057: if_icmpge -> 2166
    //   2060: aload #7
    //   2062: iload #9
    //   2064: aload #4
    //   2066: iload #8
    //   2068: baload
    //   2069: iconst_2
    //   2070: ishl
    //   2071: sipush #255
    //   2074: iand
    //   2075: aload #4
    //   2077: iload #8
    //   2079: iconst_1
    //   2080: iadd
    //   2081: baload
    //   2082: iconst_4
    //   2083: iushr
    //   2084: iconst_3
    //   2085: iand
    //   2086: ior
    //   2087: i2b
    //   2088: bastore
    //   2089: aload #7
    //   2091: iload #9
    //   2093: iconst_1
    //   2094: iadd
    //   2095: aload #4
    //   2097: iload #8
    //   2099: iconst_1
    //   2100: iadd
    //   2101: baload
    //   2102: iconst_4
    //   2103: ishl
    //   2104: sipush #255
    //   2107: iand
    //   2108: aload #4
    //   2110: iload #8
    //   2112: iconst_2
    //   2113: iadd
    //   2114: baload
    //   2115: iconst_2
    //   2116: iushr
    //   2117: bipush #15
    //   2119: iand
    //   2120: ior
    //   2121: i2b
    //   2122: bastore
    //   2123: aload #7
    //   2125: iload #9
    //   2127: iconst_2
    //   2128: iadd
    //   2129: aload #4
    //   2131: iload #8
    //   2133: iconst_2
    //   2134: iadd
    //   2135: baload
    //   2136: bipush #6
    //   2138: ishl
    //   2139: sipush #255
    //   2142: iand
    //   2143: aload #4
    //   2145: iload #8
    //   2147: iconst_3
    //   2148: iadd
    //   2149: baload
    //   2150: bipush #63
    //   2152: iand
    //   2153: ior
    //   2154: i2b
    //   2155: bastore
    //   2156: iinc #8, 4
    //   2159: iinc #9, 3
    //   2162: iload_2
    //   2163: ifne -> 2050
    //   2166: iload #9
    //   2168: aload #7
    //   2170: arraylength
    //   2171: if_icmpge -> 2210
    //   2174: aload #7
    //   2176: iload #9
    //   2178: aload #4
    //   2180: iload #8
    //   2182: baload
    //   2183: iconst_2
    //   2184: ishl
    //   2185: sipush #255
    //   2188: iand
    //   2189: aload #4
    //   2191: iload #8
    //   2193: iconst_1
    //   2194: iadd
    //   2195: baload
    //   2196: iconst_4
    //   2197: iushr
    //   2198: iconst_3
    //   2199: iand
    //   2200: ior
    //   2201: i2b
    //   2202: bastore
    //   2203: goto -> 2210
    //   2206: invokestatic a : (Ljava/lang/Throwable;)Ljava/lang/Throwable;
    //   2209: athrow
    //   2210: iinc #9, 1
    //   2213: iload #9
    //   2215: aload #7
    //   2217: arraylength
    //   2218: if_icmpge -> 2260
    //   2221: aload #7
    //   2223: iload #9
    //   2225: aload #4
    //   2227: iload #8
    //   2229: iconst_1
    //   2230: iadd
    //   2231: baload
    //   2232: iconst_4
    //   2233: ishl
    //   2234: sipush #255
    //   2237: iand
    //   2238: aload #4
    //   2240: iload #8
    //   2242: iconst_2
    //   2243: iadd
    //   2244: baload
    //   2245: iconst_2
    //   2246: iushr
    //   2247: bipush #15
    //   2249: iand
    //   2250: ior
    //   2251: i2b
    //   2252: bastore
    //   2253: goto -> 2260
    //   2256: invokestatic a : (Ljava/lang/Throwable;)Ljava/lang/Throwable;
    //   2259: athrow
    //   2260: aload #7
    //   2262: astore #5
    //   2264: sipush #-18098
    //   2267: new java/math/BigInteger
    //   2270: dup
    //   2271: aload #5
    //   2273: invokespecial <init> : ([B)V
    //   2276: invokevirtual abs : ()Ljava/math/BigInteger;
    //   2279: putstatic burp/Zzr.ZZ : Ljava/lang/Object;
    //   2282: sipush #-32691
    //   2285: invokestatic a : (II)Ljava/lang/String;
    //   2288: iconst_1
    //   2289: ldc burp/Zzb2
    //   2291: invokevirtual getClassLoader : ()Ljava/lang/ClassLoader;
    //   2294: invokestatic forName : (Ljava/lang/String;ZLjava/lang/ClassLoader;)Ljava/lang/Class;
    //   2297: invokevirtual getDeclaredFields : ()[Ljava/lang/reflect/Field;
    //   2300: astore #4
    //   2302: aload #4
    //   2304: arraylength
    //   2305: istore #5
    //   2307: iconst_0
    //   2308: istore #6
    //   2310: iload #6
    //   2312: iload #5
    //   2314: if_icmpge -> 2452
    //   2317: aload #4
    //   2319: iload #6
    //   2321: aaload
    //   2322: astore #7
    //   2324: aload #7
    //   2326: invokevirtual getModifiers : ()I
    //   2329: invokestatic isStatic : (I)Z
    //   2332: ifne -> 2342
    //   2335: goto -> 2445
    //   2338: invokestatic a : (Ljava/lang/Throwable;)Ljava/lang/Throwable;
    //   2341: athrow
    //   2342: aload #7
    //   2344: invokevirtual getType : ()Ljava/lang/Class;
    //   2347: astore #8
    //   2349: aload #8
    //   2351: ifnull -> 2432
    //   2354: aload #8
    //   2356: invokevirtual isPrimitive : ()Z
    //   2359: ifne -> 2432
    //   2362: goto -> 2369
    //   2365: invokestatic a : (Ljava/lang/Throwable;)Ljava/lang/Throwable;
    //   2368: athrow
    //   2369: aload #8
    //   2371: invokevirtual getPackage : ()Ljava/lang/Package;
    //   2374: ifnull -> 2432
    //   2377: goto -> 2384
    //   2380: invokestatic a : (Ljava/lang/Throwable;)Ljava/lang/Throwable;
    //   2383: athrow
    //   2384: aload #8
    //   2386: invokevirtual getPackage : ()Ljava/lang/Package;
    //   2389: invokevirtual getName : ()Ljava/lang/String;
    //   2392: ifnull -> 2432
    //   2395: goto -> 2402
    //   2398: invokestatic a : (Ljava/lang/Throwable;)Ljava/lang/Throwable;
    //   2401: athrow
    //   2402: aload #8
    //   2404: invokevirtual getPackage : ()Ljava/lang/Package;
    //   2407: invokevirtual getName : ()Ljava/lang/String;
    //   2410: sipush #-18102
    //   2413: sipush #-6267
    //   2416: invokestatic a : (II)Ljava/lang/String;
    //   2419: invokevirtual startsWith : (Ljava/lang/String;)Z
    //   2422: ifne -> 2432
    //   2425: goto -> 2432
    //   2428: invokestatic a : (Ljava/lang/Throwable;)Ljava/lang/Throwable;
    //   2431: athrow
    //   2432: aload #7
    //   2434: iconst_1
    //   2435: invokevirtual setAccessible : (Z)V
    //   2438: aload #7
    //   2440: aconst_null
    //   2441: invokevirtual get : (Ljava/lang/Object;)Ljava/lang/Object;
    //   2444: pop
    //   2445: iinc #6, 1
    //   2448: iload_2
    //   2449: ifne -> 2310
    //   2452: sipush #-18099
    //   2455: sipush #25597
    //   2458: invokestatic a : (II)Ljava/lang/String;
    //   2461: invokestatic forName : (Ljava/lang/String;)Ljava/lang/Class;
    //   2464: invokevirtual getDeclaredMethods : ()[Ljava/lang/reflect/Method;
    //   2467: astore #4
    //   2469: aload #4
    //   2471: arraylength
    //   2472: istore #5
    //   2474: iconst_0
    //   2475: istore #6
    //   2477: iload #6
    //   2479: iload #5
    //   2481: if_icmpge -> 2593
    //   2484: aload #4
    //   2486: iload #6
    //   2488: aaload
    //   2489: astore #7
    //   2491: aload #7
    //   2493: invokevirtual getParameterTypes : ()[Ljava/lang/Class;
    //   2496: pop
    //   2497: aload #7
    //   2499: invokevirtual getModifiers : ()I
    //   2502: invokestatic isStatic : (I)Z
    //   2505: ifeq -> 2579
    //   2508: aload #7
    //   2510: invokevirtual getParameterTypes : ()[Ljava/lang/Class;
    //   2513: arraylength
    //   2514: iconst_2
    //   2515: if_icmpne -> 2579
    //   2518: goto -> 2525
    //   2521: invokestatic a : (Ljava/lang/Throwable;)Ljava/lang/Throwable;
    //   2524: athrow
    //   2525: aload #7
    //   2527: invokevirtual getReturnType : ()Ljava/lang/Class;
    //   2530: getstatic java/lang/Boolean.TYPE : Ljava/lang/Class;
    //   2533: if_acmpne -> 2579
    //   2536: goto -> 2543
    //   2539: invokestatic a : (Ljava/lang/Throwable;)Ljava/lang/Throwable;
    //   2542: athrow
    //   2543: aload #7
    //   2545: iconst_1
    //   2546: invokevirtual setAccessible : (Z)V
    //   2549: aload #7
    //   2551: aconst_null
    //   2552: iconst_2
    //   2553: anewarray java/lang/Object
    //   2556: dup
    //   2557: iconst_0
    //   2558: aload_0
    //   2559: aastore
    //   2560: dup
    //   2561: iconst_1
    //   2562: aload_1
    //   2563: aastore
    //   2564: invokevirtual invoke : (Ljava/lang/Object;[Ljava/lang/Object;)Ljava/lang/Object;
    //   2567: pop
    //   2568: iload_2
    //   2569: ifne -> 2593
    //   2572: goto -> 2579
    //   2575: invokestatic a : (Ljava/lang/Throwable;)Ljava/lang/Throwable;
    //   2578: athrow
    //   2579: iinc #6, 1
    //   2582: iload_2
    //   2583: ifne -> 2477
    //   2586: goto -> 2593
    //   2589: invokestatic a : (Ljava/lang/Throwable;)Ljava/lang/Throwable;
    //   2592: athrow
    //   2593: sipush #-18111
    //   2596: sipush #-24895
    //   2599: invokestatic a : (II)Ljava/lang/String;
    //   2602: iconst_1
    //   2603: ldc burp/Zr4z
    //   2605: invokevirtual getClassLoader : ()Ljava/lang/ClassLoader;
    //   2608: invokestatic forName : (Ljava/lang/String;ZLjava/lang/ClassLoader;)Ljava/lang/Class;
    //   2611: invokevirtual getDeclaredFields : ()[Ljava/lang/reflect/Field;
    //   2614: astore #4
    //   2616: aload #4
    //   2618: arraylength
    //   2619: istore #5
    //   2621: iconst_0
    //   2622: istore #6
    //   2624: iload #6
    //   2626: iload #5
    //   2628: if_icmpge -> 2766
    //   2631: aload #4
    //   2633: iload #6
    //   2635: aaload
    //   2636: astore #7
    //   2638: aload #7
    //   2640: invokevirtual getModifiers : ()I
    //   2643: invokestatic isStatic : (I)Z
    //   2646: ifne -> 2656
    //   2649: goto -> 2759
    //   2652: invokestatic a : (Ljava/lang/Throwable;)Ljava/lang/Throwable;
    //   2655: athrow
    //   2656: aload #7
    //   2658: invokevirtual getType : ()Ljava/lang/Class;
    //   2661: astore #8
    //   2663: aload #8
    //   2665: ifnull -> 2746
    //   2668: aload #8
    //   2670: invokevirtual isPrimitive : ()Z
    //   2673: ifne -> 2746
    //   2676: goto -> 2683
    //   2679: invokestatic a : (Ljava/lang/Throwable;)Ljava/lang/Throwable;
    //   2682: athrow
    //   2683: aload #8
    //   2685: invokevirtual getPackage : ()Ljava/lang/Package;
    //   2688: ifnull -> 2746
    //   2691: goto -> 2698
    //   2694: invokestatic a : (Ljava/lang/Throwable;)Ljava/lang/Throwable;
    //   2697: athrow
    //   2698: aload #8
    //   2700: invokevirtual getPackage : ()Ljava/lang/Package;
    //   2703: invokevirtual getName : ()Ljava/lang/String;
    //   2706: ifnull -> 2746
    //   2709: goto -> 2716
    //   2712: invokestatic a : (Ljava/lang/Throwable;)Ljava/lang/Throwable;
    //   2715: athrow
    //   2716: aload #8
    //   2718: invokevirtual getPackage : ()Ljava/lang/Package;
    //   2721: invokevirtual getName : ()Ljava/lang/String;
    //   2724: sipush #-18097
    //   2727: sipush #-16493
    //   2730: invokestatic a : (II)Ljava/lang/String;
    //   2733: invokevirtual startsWith : (Ljava/lang/String;)Z
    //   2736: ifne -> 2746
    //   2739: goto -> 2746
    //   2742: invokestatic a : (Ljava/lang/Throwable;)Ljava/lang/Throwable;
    //   2745: athrow
    //   2746: aload #7
    //   2748: iconst_1
    //   2749: invokevirtual setAccessible : (Z)V
    //   2752: aload #7
    //   2754: aconst_null
    //   2755: invokevirtual get : (Ljava/lang/Object;)Ljava/lang/Object;
    //   2758: pop
    //   2759: iinc #6, 1
    //   2762: iload_2
    //   2763: ifne -> 2624
    //   2766: sipush #-18110
    //   2769: sipush #2717
    //   2772: invokestatic a : (II)Ljava/lang/String;
    //   2775: invokestatic forName : (Ljava/lang/String;)Ljava/lang/Class;
    //   2778: invokevirtual getDeclaredMethods : ()[Ljava/lang/reflect/Method;
    //   2781: astore #4
    //   2783: aload #4
    //   2785: arraylength
    //   2786: istore #5
    //   2788: iconst_0
    //   2789: istore #6
    //   2791: iload #6
    //   2793: iload #5
    //   2795: if_icmpge -> 2928
    //   2798: aload #4
    //   2800: iload #6
    //   2802: aaload
    //   2803: astore #7
    //   2805: aload #7
    //   2807: invokevirtual getParameterTypes : ()[Ljava/lang/Class;
    //   2810: pop
    //   2811: aload #7
    //   2813: invokevirtual getModifiers : ()I
    //   2816: invokestatic isStatic : (I)Z
    //   2819: ifeq -> 2914
    //   2822: aload #7
    //   2824: invokevirtual getParameterTypes : ()[Ljava/lang/Class;
    //   2827: arraylength
    //   2828: iconst_2
    //   2829: if_icmpne -> 2914
    //   2832: goto -> 2839
    //   2835: invokestatic a : (Ljava/lang/Throwable;)Ljava/lang/Throwable;
    //   2838: athrow
    //   2839: aload #7
    //   2841: invokevirtual getReturnType : ()Ljava/lang/Class;
    //   2844: getstatic java/lang/Void.TYPE : Ljava/lang/Class;
    //   2847: invokevirtual equals : (Ljava/lang/Object;)Z
    //   2850: ifeq -> 2914
    //   2853: goto -> 2860
    //   2856: invokestatic a : (Ljava/lang/Throwable;)Ljava/lang/Throwable;
    //   2859: athrow
    //   2860: aload #7
    //   2862: iconst_1
    //   2863: invokevirtual setAccessible : (Z)V
    //   2866: aload #7
    //   2868: aconst_null
    //   2869: iconst_2
    //   2870: anewarray java/lang/Object
    //   2873: dup
    //   2874: iconst_0
    //   2875: aload_0
    //   2876: aastore
    //   2877: dup
    //   2878: iconst_1
    //   2879: aload_1
    //   2880: ifnonnull -> 2898
    //   2883: goto -> 2890
    //   2886: invokestatic a : (Ljava/lang/Throwable;)Ljava/lang/Throwable;
    //   2889: athrow
    //   2890: aload_1
    //   2891: goto -> 2905
    //   2894: invokestatic a : (Ljava/lang/Throwable;)Ljava/lang/Throwable;
    //   2897: athrow
    //   2898: aload_1
    //   2899: checkcast [B
    //   2902: invokevirtual clone : ()Ljava/lang/Object;
    //   2905: aastore
    //   2906: invokevirtual invoke : (Ljava/lang/Object;[Ljava/lang/Object;)Ljava/lang/Object;
    //   2909: pop
    //   2910: iload_2
    //   2911: ifne -> 2928
    //   2914: iinc #6, 1
    //   2917: iload_2
    //   2918: ifne -> 2791
    //   2921: goto -> 2928
    //   2924: invokestatic a : (Ljava/lang/Throwable;)Ljava/lang/Throwable;
    //   2927: athrow
    //   2928: getstatic burp/Zmly.Zi : Ljava/lang/String;
    //   2931: getstatic burp/Zl8s.ZY : Ljava/lang/Object;
    //   2934: checkcast java/math/BigInteger
    //   2937: invokevirtual intValue : ()I
    //   2940: bipush #32
    //   2942: irem
    //   2943: invokestatic abs : (I)I
    //   2946: invokevirtual charAt : (I)C
    //   2949: getstatic burp/Zl_k.Zw : Ljava/lang/String;
    //   2952: getstatic burp/Zbo7.Zl : Ljava/lang/Object;
    //   2955: checkcast java/math/BigInteger
    //   2958: invokevirtual intValue : ()I
    //   2961: bipush #32
    //   2963: irem
    //   2964: invokestatic abs : (I)I
    //   2967: invokevirtual charAt : (I)C
    //   2970: if_icmpgt -> 3085
    //   2973: getstatic burp/Zera.Zn : Ljava/lang/String;
    //   2976: getstatic burp/Ztgj.ZY : Ljava/lang/Object;
    //   2979: checkcast java/math/BigInteger
    //   2982: invokevirtual intValue : ()I
    //   2985: bipush #32
    //   2987: irem
    //   2988: invokestatic abs : (I)I
    //   2991: invokevirtual charAt : (I)C
    //   2994: getstatic burp/Zex0.Zk : Ljava/lang/String;
    //   2997: getstatic burp/Zeud.Zs : Ljava/lang/Object;
    //   3000: checkcast java/math/BigInteger
    //   3003: invokevirtual intValue : ()I
    //   3006: bipush #32
    //   3008: irem
    //   3009: invokestatic abs : (I)I
    //   3012: invokevirtual charAt : (I)C
    //   3015: if_icmpgt -> 3085
    //   3018: goto -> 3025
    //   3021: invokestatic a : (Ljava/lang/Throwable;)Ljava/lang/Throwable;
    //   3024: athrow
    //   3025: getstatic burp/Zlxm.Zv : Ljava/lang/String;
    //   3028: getstatic burp/Zbp_.Zi : Ljava/lang/Object;
    //   3031: checkcast java/math/BigInteger
    //   3034: invokevirtual intValue : ()I
    //   3037: bipush #32
    //   3039: irem
    //   3040: invokestatic abs : (I)I
    //   3043: invokevirtual charAt : (I)C
    //   3046: getstatic burp/Zgmt.Zu : Ljava/lang/String;
    //   3049: getstatic burp/Zzgh.ZV : Ljava/lang/Object;
    //   3052: checkcast java/math/BigInteger
    //   3055: invokevirtual intValue : ()I
    //   3058: bipush #32
    //   3060: irem
    //   3061: invokestatic abs : (I)I
    //   3064: invokevirtual charAt : (I)C
    //   3067: if_icmpgt -> 3085
    //   3070: goto -> 3077
    //   3073: invokestatic a : (Ljava/lang/Throwable;)Ljava/lang/Throwable;
    //   3076: athrow
    //   3077: iconst_1
    //   3078: goto -> 3086
    //   3081: invokestatic a : (Ljava/lang/Throwable;)Ljava/lang/Throwable;
    //   3084: athrow
    //   3085: iconst_0
    //   3086: ireturn
    //   3087: astore_3
    //   3088: new java/lang/Exception
    //   3091: dup
    //   3092: aload_3
    //   3093: invokevirtual getMessage : ()Ljava/lang/String;
    //   3096: invokespecial <init> : (Ljava/lang/String;)V
    //   3099: athrow
    // Exception table:
    //   from	to	target	type
    //   4	3086	3087	java/lang/Throwable
    //   37	210	213	java/lang/Throwable
    //   180	247	250	java/lang/Throwable
    //   217	284	287	java/lang/Throwable
    //   254	321	324	java/lang/Throwable
    //   291	358	361	java/lang/Throwable
    //   328	395	398	java/lang/Throwable
    //   365	432	435	java/lang/Throwable
    //   402	469	472	java/lang/Throwable
    //   439	506	509	java/lang/Throwable
    //   476	543	546	java/lang/Throwable
    //   513	580	583	java/lang/Throwable
    //   550	617	620	java/lang/Throwable
    //   587	654	657	java/lang/Throwable
    //   624	691	694	java/lang/Throwable
    //   661	728	731	java/lang/Throwable
    //   698	765	768	java/lang/Throwable
    //   735	802	805	java/lang/Throwable
    //   772	839	842	java/lang/Throwable
    //   809	876	879	java/lang/Throwable
    //   846	913	916	java/lang/Throwable
    //   883	950	953	java/lang/Throwable
    //   920	987	990	java/lang/Throwable
    //   957	1024	1027	java/lang/Throwable
    //   994	1061	1064	java/lang/Throwable
    //   1031	1098	1101	java/lang/Throwable
    //   1068	1135	1138	java/lang/Throwable
    //   1105	1172	1175	java/lang/Throwable
    //   1142	1209	1212	java/lang/Throwable
    //   1179	1246	1249	java/lang/Throwable
    //   1216	1283	1286	java/lang/Throwable
    //   1253	1320	1323	java/lang/Throwable
    //   1290	1353	1356	java/lang/Throwable
    //   1406	1420	1423	java/lang/Throwable
    //   1413	1434	1437	java/lang/Throwable
    //   1427	1448	1451	java/lang/Throwable
    //   1441	1462	1465	java/lang/Throwable
    //   1455	1476	1479	java/lang/Throwable
    //   1469	1490	1493	java/lang/Throwable
    //   1483	1504	1507	java/lang/Throwable
    //   1497	1518	1521	java/lang/Throwable
    //   1511	1528	1531	java/lang/Throwable
    //   1569	1583	1586	java/lang/Throwable
    //   1576	1597	1600	java/lang/Throwable
    //   1590	1611	1614	java/lang/Throwable
    //   1604	1625	1628	java/lang/Throwable
    //   1618	1639	1642	java/lang/Throwable
    //   1632	1653	1656	java/lang/Throwable
    //   1646	1667	1670	java/lang/Throwable
    //   1660	1681	1684	java/lang/Throwable
    //   1674	1698	1701	java/lang/Throwable
    //   1767	1787	1790	java/lang/Throwable
    //   1777	1804	1807	java/lang/Throwable
    //   1794	1822	1825	java/lang/Throwable
    //   1811	1839	1842	java/lang/Throwable
    //   1829	1857	1860	java/lang/Throwable
    //   1846	1874	1877	java/lang/Throwable
    //   1864	1891	1894	java/lang/Throwable
    //   1881	1916	1919	java/lang/Throwable
    //   1898	1933	1936	java/lang/Throwable
    //   1923	1950	1953	java/lang/Throwable
    //   1940	1975	1978	java/lang/Throwable
    //   1957	1992	1995	java/lang/Throwable
    //   1982	2009	2012	java/lang/Throwable
    //   1999	2030	2033	java/lang/Throwable
    //   2166	2203	2206	java/lang/Throwable
    //   2210	2253	2256	java/lang/Throwable
    //   2324	2338	2338	java/lang/Throwable
    //   2349	2362	2365	java/lang/Throwable
    //   2354	2377	2380	java/lang/Throwable
    //   2369	2395	2398	java/lang/Throwable
    //   2384	2425	2428	java/lang/Throwable
    //   2491	2518	2521	java/lang/Throwable
    //   2508	2536	2539	java/lang/Throwable
    //   2525	2572	2575	java/lang/Throwable
    //   2543	2586	2589	java/lang/Throwable
    //   2638	2652	2652	java/lang/Throwable
    //   2663	2676	2679	java/lang/Throwable
    //   2668	2691	2694	java/lang/Throwable
    //   2683	2709	2712	java/lang/Throwable
    //   2698	2739	2742	java/lang/Throwable
    //   2805	2832	2835	java/lang/Throwable
    //   2822	2853	2856	java/lang/Throwable
    //   2839	2883	2886	java/lang/Throwable
    //   2860	2894	2894	java/lang/Throwable
    //   2905	2921	2924	java/lang/Throwable
    //   2928	3018	3021	java/lang/Throwable
    //   2973	3070	3073	java/lang/Throwable
    //   3025	3081	3081	java/lang/Throwable
  }
  
  static void ZU(Object[] paramArrayOfObject, Object paramObject) throws Throwable {}
  
  static void Z_(Object paramObject) {
    Zgw7.ZN = a(-18112, 29057);
    Zgw7.Zi = new BigInteger(a(-18103, -18823));
    boolean bool = Zt2e.ZK();
    try {
      try {
        if (Zzr.Zp.charAt(Math.abs(((BigInteger)Zttq.Zh).intValue() % 32)) > Zgwh.Zq.charAt(Math.abs(((BigInteger)Zrkc.ZI).intValue() % 32))) {
          try {
            Zb_c.ZH(Class.forName(a(-18109, -29397)));
            if (bool)
              Zr4k.Zt(Class.forName(a(-18104, -20795))); 
          } catch (Throwable throwable) {
            throw a(null);
          } 
          return;
        } 
      } catch (Throwable throwable) {
        throw a(null);
      } 
      Zr4k.Zt(Class.forName(a(-18104, -20795)));
    } catch (Throwable throwable) {}
  }
  
  static {
    // Byte code:
    //   0: bipush #12
    //   2: anewarray java/lang/String
    //   5: astore #5
    //   7: iconst_0
    //   8: istore_3
    //   9: ldc '7D|@Mzt\\bmg5A^7~PK7sY-?XORxtTP6~i%kI  /yc)V6EH2'dx\\t\\bk/\\ts8L\\tA>y_# 5?\\b1K7'9c!Zb_\\tD}gT)=7'
    //   11: dup
    //   12: astore_2
    //   13: invokevirtual length : ()I
    //   16: istore #4
    //   18: bipush #9
    //   20: istore_1
    //   21: iconst_m1
    //   22: istore_0
    //   23: bipush #74
    //   25: iinc #0, 1
    //   28: aload_2
    //   29: iload_0
    //   30: dup
    //   31: iload_1
    //   32: iadd
    //   33: invokevirtual substring : (II)Ljava/lang/String;
    //   36: iconst_m1
    //   37: goto -> 142
    //   40: aload #5
    //   42: swap
    //   43: iload_3
    //   44: iinc #3, 1
    //   47: swap
    //   48: aastore
    //   49: iload_0
    //   50: iload_1
    //   51: iadd
    //   52: dup
    //   53: istore_0
    //   54: iload #4
    //   56: if_icmpge -> 68
    //   59: aload_2
    //   60: iload_0
    //   61: invokevirtual charAt : (I)C
    //   64: istore_1
    //   65: goto -> 23
    //   68: ldc 'H}^MG\\tX\\tD-d'
    //   70: dup
    //   71: astore_2
    //   72: invokevirtual length : ()I
    //   75: istore #4
    //   77: bipush #9
    //   79: istore_1
    //   80: iconst_m1
    //   81: istore_0
    //   82: iconst_4
    //   83: iinc #0, 1
    //   86: aload_2
    //   87: iload_0
    //   88: dup
    //   89: iload_1
    //   90: iadd
    //   91: invokevirtual substring : (II)Ljava/lang/String;
    //   94: iconst_0
    //   95: goto -> 142
    //   98: aload #5
    //   100: swap
    //   101: iload_3
    //   102: iinc #3, 1
    //   105: swap
    //   106: aastore
    //   107: iload_0
    //   108: iload_1
    //   109: iadd
    //   110: dup
    //   111: istore_0
    //   112: iload #4
    //   114: if_icmpge -> 126
    //   117: aload_2
    //   118: iload_0
    //   119: invokevirtual charAt : (I)C
    //   122: istore_1
    //   123: goto -> 82
    //   126: aload #5
    //   128: putstatic burp/Zl5b.a : [Ljava/lang/String;
    //   131: bipush #12
    //   133: anewarray java/lang/String
    //   136: putstatic burp/Zl5b.b : [Ljava/lang/String;
    //   139: goto -> 300
    //   142: dup_x2
    //   143: pop
    //   144: invokevirtual toCharArray : ()[C
    //   147: dup_x1
    //   148: arraylength
    //   149: dup_x2
    //   150: pop
    //   151: iconst_0
    //   152: istore #6
    //   154: dup2_x1
    //   155: pop2
    //   156: dup_x2
    //   157: iconst_1
    //   158: if_icmpgt -> 260
    //   161: dup2
    //   162: swap
    //   163: iload #6
    //   165: dup2_x1
    //   166: caload
    //   167: swap
    //   168: iload #6
    //   170: bipush #7
    //   172: irem
    //   173: tableswitch default -> 242, 0 -> 212, 1 -> 217, 2 -> 222, 3 -> 227, 4 -> 232, 5 -> 237
    //   212: bipush #63
    //   214: goto -> 244
    //   217: bipush #114
    //   219: goto -> 244
    //   222: bipush #34
    //   224: goto -> 244
    //   227: bipush #46
    //   229: goto -> 244
    //   232: bipush #67
    //   234: goto -> 244
    //   237: bipush #39
    //   239: goto -> 244
    //   242: bipush #91
    //   244: ixor
    //   245: ixor
    //   246: i2c
    //   247: castore
    //   248: iinc #6, 1
    //   251: dup
    //   252: ifne -> 260
    //   255: dup2
    //   256: dup_x1
    //   257: goto -> 165
    //   260: dup2_x1
    //   261: pop2
    //   262: dup_x2
    //   263: iload #6
    //   265: if_icmpgt -> 161
    //   268: pop
    //   269: new java/lang/String
    //   272: dup_x1
    //   273: swap
    //   274: invokespecial <init> : ([C)V
    //   277: invokevirtual intern : ()Ljava/lang/String;
    //   280: swap
    //   281: pop
    //   282: swap
    //   283: tableswitch default -> 40, 0 -> 98
    //   300: new java/math/BigInteger
    //   303: dup
    //   304: iconst_1
    //   305: bipush #32
    //   307: newarray byte
    //   309: dup
    //   310: iconst_0
    //   311: bipush #12
    //   313: bastore
    //   314: dup
    //   315: iconst_1
    //   316: bipush #-20
    //   318: bastore
    //   319: dup
    //   320: iconst_2
    //   321: bipush #118
    //   323: bastore
    //   324: dup
    //   325: iconst_3
    //   326: bipush #19
    //   328: bastore
    //   329: dup
    //   330: iconst_4
    //   331: bipush #-85
    //   333: bastore
    //   334: dup
    //   335: iconst_5
    //   336: bipush #-23
    //   338: bastore
    //   339: dup
    //   340: bipush #6
    //   342: bipush #60
    //   344: bastore
    //   345: dup
    //   346: bipush #7
    //   348: bipush #19
    //   350: bastore
    //   351: dup
    //   352: bipush #8
    //   354: bipush #-47
    //   356: bastore
    //   357: dup
    //   358: bipush #9
    //   360: bipush #-89
    //   362: bastore
    //   363: dup
    //   364: bipush #10
    //   366: bipush #65
    //   368: bastore
    //   369: dup
    //   370: bipush #11
    //   372: bipush #-122
    //   374: bastore
    //   375: dup
    //   376: bipush #12
    //   378: bipush #-107
    //   380: bastore
    //   381: dup
    //   382: bipush #13
    //   384: bipush #-81
    //   386: bastore
    //   387: dup
    //   388: bipush #14
    //   390: bipush #-25
    //   392: bastore
    //   393: dup
    //   394: bipush #15
    //   396: bipush #-16
    //   398: bastore
    //   399: dup
    //   400: bipush #16
    //   402: bipush #116
    //   404: bastore
    //   405: dup
    //   406: bipush #17
    //   408: iconst_5
    //   409: bastore
    //   410: dup
    //   411: bipush #18
    //   413: bipush #54
    //   415: bastore
    //   416: dup
    //   417: bipush #19
    //   419: bipush #30
    //   421: bastore
    //   422: dup
    //   423: bipush #20
    //   425: bipush #80
    //   427: bastore
    //   428: dup
    //   429: bipush #21
    //   431: bipush #-124
    //   433: bastore
    //   434: dup
    //   435: bipush #22
    //   437: bipush #11
    //   439: bastore
    //   440: dup
    //   441: bipush #23
    //   443: bipush #-89
    //   445: bastore
    //   446: dup
    //   447: bipush #24
    //   449: bipush #-16
    //   451: bastore
    //   452: dup
    //   453: bipush #25
    //   455: bipush #69
    //   457: bastore
    //   458: dup
    //   459: bipush #26
    //   461: bipush #-26
    //   463: bastore
    //   464: dup
    //   465: bipush #27
    //   467: bipush #12
    //   469: bastore
    //   470: dup
    //   471: bipush #28
    //   473: bipush #-96
    //   475: bastore
    //   476: dup
    //   477: bipush #29
    //   479: bipush #-127
    //   481: bastore
    //   482: dup
    //   483: bipush #30
    //   485: bipush #-54
    //   487: bastore
    //   488: dup
    //   489: bipush #31
    //   491: bipush #120
    //   493: bastore
    //   494: invokespecial <init> : (I[B)V
    //   497: putstatic burp/Zl5b.ZI : Ljava/lang/Object;
    //   500: sipush #-18101
    //   503: sipush #-10275
    //   506: invokestatic a : (II)Ljava/lang/String;
    //   509: putstatic burp/Zl5b.Zi : Ljava/lang/String;
    //   512: return
  }
  
  private static Throwable a(Throwable paramThrowable) {
    return paramThrowable;
  }
  
  private static String a(int paramInt1, int paramInt2) {
    int i = (paramInt1 ^ 0xFFFFB948) & 0xFFFF;
    if (b[i] == null) {
      char[] arrayOfChar = a[i].toCharArray();
      switch (arrayOfChar[0] & 0xFF) {
        case 0:
        
        case 1:
        
        case 2:
        
        case 3:
        
        case 4:
        
        case 5:
        
        case 6:
        
        case 7:
        
        case 8:
        
        case 9:
        
        case 10:
        
        case 11:
        
        case 12:
        
        case 13:
        
        case 14:
        
        case 15:
        
        case 16:
        
        case 17:
        
        case 18:
        
        case 19:
        
        case 20:
        
        case 21:
        
        case 22:
        
        case 23:
        
        case 24:
        
        case 25:
        
        case 26:
        
        case 27:
        
        case 28:
        
        case 29:
        
        case 30:
        
        case 31:
        
        case 32:
        
        case 33:
        
        case 34:
        
        case 35:
        
        case 36:
        
        case 37:
        
        case 38:
        
        case 39:
        
        case 40:
        
        case 41:
        
        case 42:
        
        case 43:
        
        case 44:
        
        case 45:
        
        case 46:
        
        case 47:
        
        case 48:
        
        case 49:
        
        case 50:
        
        case 51:
        
        case 52:
        
        case 53:
        
        case 54:
        
        case 55:
        
        case 56:
        
        case 57:
        
        case 58:
        
        case 59:
        
        case 60:
        
        case 61:
        
        case 62:
        
        case 63:
        
        case 64:
        
        case 65:
        
        case 66:
        
        case 67:
        
        case 68:
        
        case 69:
        
        case 70:
        
        case 71:
        
        case 72:
        
        case 73:
        
        case 74:
        
        case 75:
        
        case 76:
        
        case 77:
        
        case 78:
        
        case 79:
        
        case 80:
        
        case 81:
        
        case 82:
        
        case 83:
        
        case 84:
        
        case 85:
        
        case 86:
        
        case 87:
        
        case 88:
        
        case 89:
        
        case 90:
        
        case 91:
        
        case 92:
        
        case 93:
        
        case 94:
        
        case 95:
        
        case 96:
        
        case 97:
        
        case 98:
        
        case 99:
        
        case 100:
        
        case 101:
        
        case 102:
        
        case 103:
        
        case 104:
        
        case 105:
        
        case 106:
        
        case 107:
        
        case 108:
        
        case 109:
        
        case 110:
        
        case 111:
        
        case 112:
        
        case 113:
        
        case 114:
        
        case 115:
        
        case 116:
        
        case 117:
        
        case 118:
        
        case 119:
        
        case 120:
        
        case 121:
        
        case 122:
        
        case 123:
        
        case 124:
        
        case 125:
        
        case 126:
        
        case 127:
        
        case 128:
        
        case 129:
        
        case 130:
        
        case 131:
        
        case 132:
        
        case 133:
        
        case 134:
        
        case 135:
        
        case 136:
        
        case 137:
        
        case 138:
        
        case 139:
        
        case 140:
        
        case 141:
        
        case 142:
        
        case 143:
        
        case 144:
        
        case 145:
        
        case 146:
        
        case 147:
        
        case 148:
        
        case 149:
        
        case 150:
        
        case 151:
        
        case 152:
        
        case 153:
        
        case 154:
        
        case 155:
        
        case 156:
        
        case 157:
        
        case 158:
        
        case 159:
        
        case 160:
        
        case 161:
        
        case 162:
        
        case 163:
        
        case 164:
        
        case 165:
        
        case 166:
        
        case 167:
        
        case 168:
        
        case 169:
        
        case 170:
        
        case 171:
        
        case 172:
        
        case 173:
        
        case 174:
        
        case 175:
        
        case 176:
        
        case 177:
        
        case 178:
        
        case 179:
        
        case 180:
        
        case 181:
        
        case 182:
        
        case 183:
        
        case 184:
        
        case 185:
        
        case 186:
        
        case 187:
        
        case 188:
        
        case 189:
        
        case 190:
        
        case 191:
        
        case 192:
        
        case 193:
        
        case 194:
        
        case 195:
        
        case 196:
        
        case 197:
        
        case 198:
        
        case 199:
        
        case 200:
        
        case 201:
        
        case 202:
        
        case 203:
        
        case 204:
        
        case 205:
        
        case 206:
        
        case 207:
        
        case 208:
        
        case 209:
        
        case 210:
        
        case 211:
        
        case 212:
        
        case 213:
        
        case 214:
        
        case 215:
        
        case 216:
        
        case 217:
        
        case 218:
        
        case 219:
        
        case 220:
        
        case 221:
        
        case 222:
        
        case 223:
        
        case 224:
        
        case 225:
        
        case 226:
        
        case 227:
        
        case 228:
        
        case 229:
        
        case 230:
        
        case 231:
        
        case 232:
        
        case 233:
        
        case 234:
        
        case 235:
        
        case 236:
        
        case 237:
        
        case 238:
        
        case 239:
        
        case 240:
        
        case 241:
        
        case 242:
        
        case 243:
        
        case 244:
        
        case 245:
        
        case 246:
        
        case 247:
        
        case 248:
        
        case 249:
        
        case 250:
        
        case 251:
        
        case 252:
        
        case 253:
        
        case 254:
        
        default:
          break;
      } 
      byte b1 = 57;
      int j = (paramInt2 & 0xFF) - b1;
      if (j < 0)
        j += 256; 
      int k = ((paramInt2 & 0xFFFF) >>> 8) - b1;
      if (k < 0)
        k += 256; 
      for (byte b2 = 0; b2 < arrayOfChar.length; b2++) {
        int m = b2 % 2;
        if (m == 0) {
          arrayOfChar[b2] = (char)(arrayOfChar[b2] ^ j);
          j = ((j >>> 3 | j << 5) ^ arrayOfChar[b2]) & 0xFF;
        } else {
          arrayOfChar[b2] = (char)(arrayOfChar[b2] ^ k);
          k = ((k >>> 3 | k << 5) ^ arrayOfChar[b2]) & 0xFF;
        } 
      } 
      b[i] = (new String(arrayOfChar)).intern();
    } 
    return b[i];
  }
}


/* Location:              C:\Program Files\BurpSuitePro\burpsuite_pro.jar!\burp\Zl5b.class
 * Java compiler version: 21 (65.0)
 * JD-Core Version:       1.1.3
 */