package burp;

import java.math.BigInteger;

class Zl88 extends ClassLoader {
  static String Zd;
  
  static Object ZK;
  
  private static final String[] a;
  
  private static final String[] b;
  
  static boolean ZL(Object[] paramArrayOfObject, Object paramObject) throws Throwable {
    // Byte code:
    //   0: invokestatic ZK : ()Z
    //   3: istore_2
    //   4: getstatic burp/Zlhm.ZT : Ljava/lang/Object;
    //   7: checkcast java/math/BigInteger
    //   10: getstatic burp/Zrdy.Zt : Ljava/lang/Object;
    //   13: checkcast java/math/BigInteger
    //   16: invokevirtual add : (Ljava/math/BigInteger;)Ljava/math/BigInteger;
    //   19: putstatic burp/Zl_u.ZR : Ljava/lang/Object;
    //   22: sipush #25873
    //   25: getstatic burp/Zb3z.ZR : Ljava/lang/Object;
    //   28: checkcast java/math/BigInteger
    //   31: getstatic burp/Zz1k.ZP : Ljava/lang/Object;
    //   34: checkcast java/math/BigInteger
    //   37: invokevirtual add : (Ljava/math/BigInteger;)Ljava/math/BigInteger;
    //   40: putstatic burp/Zg0j.ZV : Ljava/lang/Object;
    //   43: sipush #16298
    //   46: getstatic burp/Zl88.ZK : Ljava/lang/Object;
    //   49: checkcast java/math/BigInteger
    //   52: getstatic burp/Zt4g.Zv : Ljava/lang/Object;
    //   55: checkcast java/math/BigInteger
    //   58: invokevirtual add : (Ljava/math/BigInteger;)Ljava/math/BigInteger;
    //   61: putstatic burp/Zshq.ZK : Ljava/lang/Object;
    //   64: invokestatic a : (II)Ljava/lang/String;
    //   67: iconst_1
    //   68: ldc burp/Ztid
    //   70: invokevirtual getClassLoader : ()Ljava/lang/ClassLoader;
    //   73: invokestatic forName : (Ljava/lang/String;ZLjava/lang/ClassLoader;)Ljava/lang/Class;
    //   76: invokevirtual getDeclaredFields : ()[Ljava/lang/reflect/Field;
    //   79: astore_3
    //   80: aload_3
    //   81: arraylength
    //   82: istore #4
    //   84: iconst_0
    //   85: istore #5
    //   87: iload #5
    //   89: iload #4
    //   91: if_icmpge -> 228
    //   94: aload_3
    //   95: iload #5
    //   97: aaload
    //   98: astore #6
    //   100: aload #6
    //   102: invokevirtual getModifiers : ()I
    //   105: invokestatic isStatic : (I)Z
    //   108: ifne -> 118
    //   111: goto -> 221
    //   114: invokestatic a : (Ljava/lang/Throwable;)Ljava/lang/Throwable;
    //   117: athrow
    //   118: aload #6
    //   120: invokevirtual getType : ()Ljava/lang/Class;
    //   123: astore #7
    //   125: aload #7
    //   127: ifnull -> 208
    //   130: aload #7
    //   132: invokevirtual isPrimitive : ()Z
    //   135: ifne -> 208
    //   138: goto -> 145
    //   141: invokestatic a : (Ljava/lang/Throwable;)Ljava/lang/Throwable;
    //   144: athrow
    //   145: aload #7
    //   147: invokevirtual getPackage : ()Ljava/lang/Package;
    //   150: ifnull -> 208
    //   153: goto -> 160
    //   156: invokestatic a : (Ljava/lang/Throwable;)Ljava/lang/Throwable;
    //   159: athrow
    //   160: aload #7
    //   162: invokevirtual getPackage : ()Ljava/lang/Package;
    //   165: invokevirtual getName : ()Ljava/lang/String;
    //   168: ifnull -> 208
    //   171: goto -> 178
    //   174: invokestatic a : (Ljava/lang/Throwable;)Ljava/lang/Throwable;
    //   177: athrow
    //   178: aload #7
    //   180: invokevirtual getPackage : ()Ljava/lang/Package;
    //   183: invokevirtual getName : ()Ljava/lang/String;
    //   186: sipush #25879
    //   189: sipush #-30173
    //   192: invokestatic a : (II)Ljava/lang/String;
    //   195: invokevirtual startsWith : (Ljava/lang/String;)Z
    //   198: ifne -> 208
    //   201: goto -> 208
    //   204: invokestatic a : (Ljava/lang/Throwable;)Ljava/lang/Throwable;
    //   207: athrow
    //   208: aload #6
    //   210: iconst_1
    //   211: invokevirtual setAccessible : (Z)V
    //   214: aload #6
    //   216: aconst_null
    //   217: invokevirtual get : (Ljava/lang/Object;)Ljava/lang/Object;
    //   220: pop
    //   221: iinc #5, 1
    //   224: iload_2
    //   225: ifeq -> 87
    //   228: sipush #25874
    //   231: sipush #3030
    //   234: invokestatic a : (II)Ljava/lang/String;
    //   237: invokestatic forName : (Ljava/lang/String;)Ljava/lang/Class;
    //   240: invokevirtual getDeclaredMethods : ()[Ljava/lang/reflect/Method;
    //   243: astore_3
    //   244: aload_3
    //   245: arraylength
    //   246: istore #4
    //   248: iconst_0
    //   249: istore #5
    //   251: iload #5
    //   253: iload #4
    //   255: if_icmpge -> 387
    //   258: aload_3
    //   259: iload #5
    //   261: aaload
    //   262: astore #6
    //   264: aload #6
    //   266: invokevirtual getParameterTypes : ()[Ljava/lang/Class;
    //   269: pop
    //   270: aload #6
    //   272: invokevirtual getModifiers : ()I
    //   275: invokestatic isStatic : (I)Z
    //   278: ifeq -> 373
    //   281: aload #6
    //   283: invokevirtual getParameterTypes : ()[Ljava/lang/Class;
    //   286: arraylength
    //   287: iconst_2
    //   288: if_icmpne -> 373
    //   291: goto -> 298
    //   294: invokestatic a : (Ljava/lang/Throwable;)Ljava/lang/Throwable;
    //   297: athrow
    //   298: aload #6
    //   300: invokevirtual getReturnType : ()Ljava/lang/Class;
    //   303: getstatic java/lang/Void.TYPE : Ljava/lang/Class;
    //   306: invokevirtual equals : (Ljava/lang/Object;)Z
    //   309: ifeq -> 373
    //   312: goto -> 319
    //   315: invokestatic a : (Ljava/lang/Throwable;)Ljava/lang/Throwable;
    //   318: athrow
    //   319: aload #6
    //   321: iconst_1
    //   322: invokevirtual setAccessible : (Z)V
    //   325: aload #6
    //   327: aconst_null
    //   328: iconst_2
    //   329: anewarray java/lang/Object
    //   332: dup
    //   333: iconst_0
    //   334: aload_0
    //   335: aastore
    //   336: dup
    //   337: iconst_1
    //   338: aload_1
    //   339: ifnonnull -> 357
    //   342: goto -> 349
    //   345: invokestatic a : (Ljava/lang/Throwable;)Ljava/lang/Throwable;
    //   348: athrow
    //   349: aload_1
    //   350: goto -> 364
    //   353: invokestatic a : (Ljava/lang/Throwable;)Ljava/lang/Throwable;
    //   356: athrow
    //   357: aload_1
    //   358: checkcast [B
    //   361: invokevirtual clone : ()Ljava/lang/Object;
    //   364: aastore
    //   365: invokevirtual invoke : (Ljava/lang/Object;[Ljava/lang/Object;)Ljava/lang/Object;
    //   368: pop
    //   369: iload_2
    //   370: ifeq -> 387
    //   373: iinc #5, 1
    //   376: iload_2
    //   377: ifeq -> 251
    //   380: goto -> 387
    //   383: invokestatic a : (Ljava/lang/Throwable;)Ljava/lang/Throwable;
    //   386: athrow
    //   387: getstatic burp/Zeh9.ZF : Ljava/lang/String;
    //   390: getstatic burp/Zshq.ZK : Ljava/lang/Object;
    //   393: checkcast java/math/BigInteger
    //   396: invokevirtual intValue : ()I
    //   399: bipush #32
    //   401: irem
    //   402: invokestatic abs : (I)I
    //   405: invokevirtual charAt : (I)C
    //   408: getstatic burp/Zzqj.Zk : Ljava/lang/String;
    //   411: getstatic burp/Zkig.ZK : Ljava/lang/Object;
    //   414: checkcast java/math/BigInteger
    //   417: invokevirtual intValue : ()I
    //   420: bipush #32
    //   422: irem
    //   423: invokestatic abs : (I)I
    //   426: invokevirtual charAt : (I)C
    //   429: if_icmpgt -> 536
    //   432: getstatic burp/Zkig.ZE : Ljava/lang/String;
    //   435: getstatic burp/Zr8h.ZH : Ljava/lang/Object;
    //   438: checkcast java/math/BigInteger
    //   441: invokevirtual intValue : ()I
    //   444: bipush #32
    //   446: irem
    //   447: invokestatic abs : (I)I
    //   450: invokevirtual charAt : (I)C
    //   453: getstatic burp/Zedz.Zh : Ljava/lang/String;
    //   456: getstatic burp/Zedz.Za : Ljava/lang/Object;
    //   459: checkcast java/math/BigInteger
    //   462: invokevirtual intValue : ()I
    //   465: bipush #32
    //   467: irem
    //   468: invokestatic abs : (I)I
    //   471: invokevirtual charAt : (I)C
    //   474: if_icmpgt -> 536
    //   477: goto -> 484
    //   480: invokestatic a : (Ljava/lang/Throwable;)Ljava/lang/Throwable;
    //   483: athrow
    //   484: getstatic burp/Zxl5.Zq : Ljava/lang/String;
    //   487: getstatic burp/Zeh9.ZY : Ljava/lang/Object;
    //   490: checkcast java/math/BigInteger
    //   493: invokevirtual intValue : ()I
    //   496: bipush #32
    //   498: irem
    //   499: invokestatic abs : (I)I
    //   502: invokevirtual charAt : (I)C
    //   505: getstatic burp/Zshq.Zi : Ljava/lang/String;
    //   508: getstatic burp/Zgmt.ZX : Ljava/lang/Object;
    //   511: checkcast java/math/BigInteger
    //   514: invokevirtual intValue : ()I
    //   517: bipush #32
    //   519: irem
    //   520: invokestatic abs : (I)I
    //   523: invokevirtual charAt : (I)C
    //   526: if_icmple -> 544
    //   529: goto -> 536
    //   532: invokestatic a : (Ljava/lang/Throwable;)Ljava/lang/Throwable;
    //   535: athrow
    //   536: iconst_1
    //   537: goto -> 545
    //   540: invokestatic a : (Ljava/lang/Throwable;)Ljava/lang/Throwable;
    //   543: athrow
    //   544: iconst_0
    //   545: ireturn
    //   546: astore_3
    //   547: new java/lang/Exception
    //   550: dup
    //   551: aload_3
    //   552: invokevirtual getMessage : ()Ljava/lang/String;
    //   555: invokespecial <init> : (Ljava/lang/String;)V
    //   558: athrow
    // Exception table:
    //   from	to	target	type
    //   4	545	546	java/lang/Throwable
    //   100	114	114	java/lang/Throwable
    //   125	138	141	java/lang/Throwable
    //   130	153	156	java/lang/Throwable
    //   145	171	174	java/lang/Throwable
    //   160	201	204	java/lang/Throwable
    //   264	291	294	java/lang/Throwable
    //   281	312	315	java/lang/Throwable
    //   298	342	345	java/lang/Throwable
    //   319	353	353	java/lang/Throwable
    //   364	380	383	java/lang/Throwable
    //   387	477	480	java/lang/Throwable
    //   432	529	532	java/lang/Throwable
    //   484	540	540	java/lang/Throwable
  }
  
  static void ZI(Object paramObject) {
    Ze3d.ZL = a(25876, 19090);
    Ze3d.Ze = new BigInteger(a(25872, -16021));
    boolean bool = Zt2e.ZN();
    try {
      try {
        if (Zzip.Za.charAt(Math.abs(((BigInteger)Zbsr.ZD).intValue() % 32)) <= Zgmt.Zu.charAt(Math.abs(((BigInteger)Zllw.ZW).intValue() % 32))) {
          try {
            Zz8o.ZO(Class.forName(a(25877, 3040)));
            if (!bool)
              Zzap.ZW(Class.forName(a(25878, -17761))); 
          } catch (Throwable throwable) {
            throw a(null);
          } 
          return;
        } 
      } catch (Throwable throwable) {
        throw a(null);
      } 
      Zzap.ZW(Class.forName(a(25878, -17761)));
    } catch (Throwable throwable) {}
  }
  
  static void ZC(Object[] paramArrayOfObject, Object paramObject) throws Throwable {}
  
  static {
    // Byte code:
    //   0: bipush #8
    //   2: anewarray java/lang/String
    //   5: astore #5
    //   7: iconst_0
    //   8: istore_3
    //   9: ldc 'Ã–!Â›Â¡\\tx+NÃ LÃ"Â›\\tÂ“Â¦3QÃ£Ã·Ã™\\tÂ¨ Â€ÂªujÂ£S'\\f\\bÃ­ÃÃ—`H.Ã²Â™!-Â¡Â”Ã„Ã•9ÃÃ¶ Ãƒ>Ã‹T:Â¯Â–Â¬Â³Â¦Â¯ÂƒÃž$Â“GÃ·ÃyÃ¿Â‡-Â‰Ã³Ã½@l'\\t|\\tÃŽÂ¤\I:Ã’F'
    //   11: dup
    //   12: astore_2
    //   13: invokevirtual length : ()I
    //   16: istore #4
    //   18: iconst_4
    //   19: istore_1
    //   20: iconst_m1
    //   21: istore_0
    //   22: bipush #91
    //   24: iinc #0, 1
    //   27: aload_2
    //   28: iload_0
    //   29: dup
    //   30: iload_1
    //   31: iadd
    //   32: invokevirtual substring : (II)Ljava/lang/String;
    //   35: iconst_m1
    //   36: goto -> 142
    //   39: aload #5
    //   41: swap
    //   42: iload_3
    //   43: iinc #3, 1
    //   46: swap
    //   47: aastore
    //   48: iload_0
    //   49: iload_1
    //   50: iadd
    //   51: dup
    //   52: istore_0
    //   53: iload #4
    //   55: if_icmpge -> 67
    //   58: aload_2
    //   59: iload_0
    //   60: invokevirtual charAt : (I)C
    //   63: istore_1
    //   64: goto -> 22
    //   67: ldc 'Ã–Â¼Ã‚5Â¢0Âˆ MÃ»\\f\\bIÂ˜Ã“Ã´Ã§Ã•Ã©Â¸Â‹C]ÂœlÃªÂ‚ÂŽÂƒÃ¬|$^bQÃªÃ”ÂªÃžÂ§Â£,Â˜UJÂ _X_Ã´Â¬Â¦uÃ‰fÂŠ<Ã°RÃ‘445_'ÂœGÂ…Ã¶Ã¢ÃˆzÃ¥Â°Â¶'
    //   69: dup
    //   70: astore_2
    //   71: invokevirtual length : ()I
    //   74: istore #4
    //   76: bipush #9
    //   78: istore_1
    //   79: iconst_m1
    //   80: istore_0
    //   81: bipush #49
    //   83: iinc #0, 1
    //   86: aload_2
    //   87: iload_0
    //   88: dup
    //   89: iload_1
    //   90: iadd
    //   91: invokevirtual substring : (II)Ljava/lang/String;
    //   94: iconst_0
    //   95: goto -> 142
    //   98: aload #5
    //   100: swap
    //   101: iload_3
    //   102: iinc #3, 1
    //   105: swap
    //   106: aastore
    //   107: iload_0
    //   108: iload_1
    //   109: iadd
    //   110: dup
    //   111: istore_0
    //   112: iload #4
    //   114: if_icmpge -> 126
    //   117: aload_2
    //   118: iload_0
    //   119: invokevirtual charAt : (I)C
    //   122: istore_1
    //   123: goto -> 81
    //   126: aload #5
    //   128: putstatic burp/Zl88.a : [Ljava/lang/String;
    //   131: bipush #8
    //   133: anewarray java/lang/String
    //   136: putstatic burp/Zl88.b : [Ljava/lang/String;
    //   139: goto -> 300
    //   142: dup_x2
    //   143: pop
    //   144: invokevirtual toCharArray : ()[C
    //   147: dup_x1
    //   148: arraylength
    //   149: dup_x2
    //   150: pop
    //   151: iconst_0
    //   152: istore #6
    //   154: dup2_x1
    //   155: pop2
    //   156: dup_x2
    //   157: iconst_1
    //   158: if_icmpgt -> 259
    //   161: dup2
    //   162: swap
    //   163: iload #6
    //   165: dup2_x1
    //   166: caload
    //   167: swap
    //   168: iload #6
    //   170: bipush #7
    //   172: irem
    //   173: tableswitch default -> 241, 0 -> 212, 1 -> 216, 2 -> 221, 3 -> 226, 4 -> 231, 5 -> 236
    //   212: iconst_2
    //   213: goto -> 243
    //   216: bipush #91
    //   218: goto -> 243
    //   221: bipush #109
    //   223: goto -> 243
    //   226: bipush #117
    //   228: goto -> 243
    //   231: bipush #10
    //   233: goto -> 243
    //   236: bipush #103
    //   238: goto -> 243
    //   241: bipush #83
    //   243: ixor
    //   244: ixor
    //   245: i2c
    //   246: castore
    //   247: iinc #6, 1
    //   250: dup
    //   251: ifne -> 259
    //   254: dup2
    //   255: dup_x1
    //   256: goto -> 165
    //   259: dup2_x1
    //   260: pop2
    //   261: dup_x2
    //   262: iload #6
    //   264: if_icmpgt -> 161
    //   267: pop
    //   268: new java/lang/String
    //   271: dup_x1
    //   272: swap
    //   273: invokespecial <init> : ([C)V
    //   276: invokevirtual intern : ()Ljava/lang/String;
    //   279: swap
    //   280: pop
    //   281: swap
    //   282: tableswitch default -> 39, 0 -> 98
    //   300: sipush #25875
    //   303: sipush #1014
    //   306: invokestatic a : (II)Ljava/lang/String;
    //   309: putstatic burp/Zl88.Zd : Ljava/lang/String;
    //   312: new java/math/BigInteger
    //   315: dup
    //   316: bipush #32
    //   318: newarray byte
    //   320: dup
    //   321: iconst_0
    //   322: bipush #85
    //   324: bastore
    //   325: dup
    //   326: iconst_1
    //   327: bipush #-98
    //   329: bastore
    //   330: dup
    //   331: iconst_2
    //   332: bipush #107
    //   334: bastore
    //   335: dup
    //   336: iconst_3
    //   337: bipush #80
    //   339: bastore
    //   340: dup
    //   341: iconst_4
    //   342: bipush #106
    //   344: bastore
    //   345: dup
    //   346: iconst_5
    //   347: bipush #41
    //   349: bastore
    //   350: dup
    //   351: bipush #6
    //   353: bipush #49
    //   355: bastore
    //   356: dup
    //   357: bipush #7
    //   359: bipush #11
    //   361: bastore
    //   362: dup
    //   363: bipush #8
    //   365: bipush #44
    //   367: bastore
    //   368: dup
    //   369: bipush #9
    //   371: bipush #-15
    //   373: bastore
    //   374: dup
    //   375: bipush #10
    //   377: bipush #82
    //   379: bastore
    //   380: dup
    //   381: bipush #11
    //   383: bipush #25
    //   385: bastore
    //   386: dup
    //   387: bipush #12
    //   389: bipush #-112
    //   391: bastore
    //   392: dup
    //   393: bipush #13
    //   395: bipush #-119
    //   397: bastore
    //   398: dup
    //   399: bipush #14
    //   401: bipush #-50
    //   403: bastore
    //   404: dup
    //   405: bipush #15
    //   407: bipush #-116
    //   409: bastore
    //   410: dup
    //   411: bipush #16
    //   413: bipush #-52
    //   415: bastore
    //   416: dup
    //   417: bipush #17
    //   419: bipush #75
    //   421: bastore
    //   422: dup
    //   423: bipush #18
    //   425: bipush #-83
    //   427: bastore
    //   428: dup
    //   429: bipush #19
    //   431: bipush #109
    //   433: bastore
    //   434: dup
    //   435: bipush #20
    //   437: iconst_0
    //   438: bastore
    //   439: dup
    //   440: bipush #21
    //   442: bipush #18
    //   444: bastore
    //   445: dup
    //   446: bipush #22
    //   448: bipush #14
    //   450: bastore
    //   451: dup
    //   452: bipush #23
    //   454: bipush #13
    //   456: bastore
    //   457: dup
    //   458: bipush #24
    //   460: bipush #-54
    //   462: bastore
    //   463: dup
    //   464: bipush #25
    //   466: bipush #90
    //   468: bastore
    //   469: dup
    //   470: bipush #26
    //   472: bipush #63
    //   474: bastore
    //   475: dup
    //   476: bipush #27
    //   478: bipush #-67
    //   480: bastore
    //   481: dup
    //   482: bipush #28
    //   484: bipush #89
    //   486: bastore
    //   487: dup
    //   488: bipush #29
    //   490: bipush #67
    //   492: bastore
    //   493: dup
    //   494: bipush #30
    //   496: bipush #90
    //   498: bastore
    //   499: dup
    //   500: bipush #31
    //   502: bipush #-17
    //   504: bastore
    //   505: invokespecial <init> : ([B)V
    //   508: putstatic burp/Zl88.ZK : Ljava/lang/Object;
    //   511: return
  }
  
  private static Throwable a(Throwable paramThrowable) {
    return paramThrowable;
  }
  
  private static String a(int paramInt1, int paramInt2) {
    int i = (paramInt1 ^ 0x6517) & 0xFFFF;
    if (b[i] == null) {
      char[] arrayOfChar = a[i].toCharArray();
      switch (arrayOfChar[0] & 0xFF) {
        case 0:
        
        case 1:
        
        case 2:
        
        case 3:
        
        case 4:
        
        case 5:
        
        case 6:
        
        case 7:
        
        case 8:
        
        case 9:
        
        case 10:
        
        case 11:
        
        case 12:
        
        case 13:
        
        case 14:
        
        case 15:
        
        case 16:
        
        case 17:
        
        case 18:
        
        case 19:
        
        case 20:
        
        case 21:
        
        case 22:
        
        case 23:
        
        case 24:
        
        case 25:
        
        case 26:
        
        case 27:
        
        case 28:
        
        case 29:
        
        case 30:
        
        case 31:
        
        case 32:
        
        case 33:
        
        case 34:
        
        case 35:
        
        case 36:
        
        case 37:
        
        case 38:
        
        case 39:
        
        case 40:
        
        case 41:
        
        case 42:
        
        case 43:
        
        case 44:
        
        case 45:
        
        case 46:
        
        case 47:
        
        case 48:
        
        case 49:
        
        case 50:
        
        case 51:
        
        case 52:
        
        case 53:
        
        case 54:
        
        case 55:
        
        case 56:
        
        case 57:
        
        case 58:
        
        case 59:
        
        case 60:
        
        case 61:
        
        case 62:
        
        case 63:
        
        case 64:
        
        case 65:
        
        case 66:
        
        case 67:
        
        case 68:
        
        case 69:
        
        case 70:
        
        case 71:
        
        case 72:
        
        case 73:
        
        case 74:
        
        case 75:
        
        case 76:
        
        case 77:
        
        case 78:
        
        case 79:
        
        case 80:
        
        case 81:
        
        case 82:
        
        case 83:
        
        case 84:
        
        case 85:
        
        case 86:
        
        case 87:
        
        case 88:
        
        case 89:
        
        case 90:
        
        case 91:
        
        case 92:
        
        case 93:
        
        case 94:
        
        case 95:
        
        case 96:
        
        case 97:
        
        case 98:
        
        case 99:
        
        case 100:
        
        case 101:
        
        case 102:
        
        case 103:
        
        case 104:
        
        case 105:
        
        case 106:
        
        case 107:
        
        case 108:
        
        case 109:
        
        case 110:
        
        case 111:
        
        case 112:
        
        case 113:
        
        case 114:
        
        case 115:
        
        case 116:
        
        case 117:
        
        case 118:
        
        case 119:
        
        case 120:
        
        case 121:
        
        case 122:
        
        case 123:
        
        case 124:
        
        case 125:
        
        case 126:
        
        case 127:
        
        case 128:
        
        case 129:
        
        case 130:
        
        case 131:
        
        case 132:
        
        case 133:
        
        case 134:
        
        case 135:
        
        case 136:
        
        case 137:
        
        case 138:
        
        case 139:
        
        case 140:
        
        case 141:
        
        case 142:
        
        case 143:
        
        case 144:
        
        case 145:
        
        case 146:
        
        case 147:
        
        case 148:
        
        case 149:
        
        case 150:
        
        case 151:
        
        case 152:
        
        case 153:
        
        case 154:
        
        case 155:
        
        case 156:
        
        case 157:
        
        case 158:
        
        case 159:
        
        case 160:
        
        case 161:
        
        case 162:
        
        case 163:
        
        case 164:
        
        case 165:
        
        case 166:
        
        case 167:
        
        case 168:
        
        case 169:
        
        case 170:
        
        case 171:
        
        case 172:
        
        case 173:
        
        case 174:
        
        case 175:
        
        case 176:
        
        case 177:
        
        case 178:
        
        case 179:
        
        case 180:
        
        case 181:
        
        case 182:
        
        case 183:
        
        case 184:
        
        case 185:
        
        case 186:
        
        case 187:
        
        case 188:
        
        case 189:
        
        case 190:
        
        case 191:
        
        case 192:
        
        case 193:
        
        case 194:
        
        case 195:
        
        case 196:
        
        case 197:
        
        case 198:
        
        case 199:
        
        case 200:
        
        case 201:
        
        case 202:
        
        case 203:
        
        case 204:
        
        case 205:
        
        case 206:
        
        case 207:
        
        case 208:
        
        case 209:
        
        case 210:
        
        case 211:
        
        case 212:
        
        case 213:
        
        case 214:
        
        case 215:
        
        case 216:
        
        case 217:
        
        case 218:
        
        case 219:
        
        case 220:
        
        case 221:
        
        case 222:
        
        case 223:
        
        case 224:
        
        case 225:
        
        case 226:
        
        case 227:
        
        case 228:
        
        case 229:
        
        case 230:
        
        case 231:
        
        case 232:
        
        case 233:
        
        case 234:
        
        case 235:
        
        case 236:
        
        case 237:
        
        case 238:
        
        case 239:
        
        case 240:
        
        case 241:
        
        case 242:
        
        case 243:
        
        case 244:
        
        case 245:
        
        case 246:
        
        case 247:
        
        case 248:
        
        case 249:
        
        case 250:
        
        case 251:
        
        case 252:
        
        case 253:
        
        case 254:
        
        default:
          break;
      } 
      char c = 'Ã¤';
      int j = (paramInt2 & 0xFF) - c;
      if (j < 0)
        j += 256; 
      int k = ((paramInt2 & 0xFFFF) >>> 8) - c;
      if (k < 0)
        k += 256; 
      for (byte b = 0; b < arrayOfChar.length; b++) {
        int m = b % 2;
        if (m == 0) {
          arrayOfChar[b] = (char)(arrayOfChar[b] ^ j);
          j = ((j >>> 3 | j << 5) ^ arrayOfChar[b]) & 0xFF;
        } else {
          arrayOfChar[b] = (char)(arrayOfChar[b] ^ k);
          k = ((k >>> 3 | k << 5) ^ arrayOfChar[b]) & 0xFF;
        } 
      } 
      b[i] = (new String(arrayOfChar)).intern();
    } 
    return b[i];
  }
}


/* Location:              C:\Program Files\BurpSuitePro\burpsuite_pro.jar!\burp\Zl88.class
 * Java compiler version: 21 (65.0)
 * JD-Core Version:       1.1.3
 */