package burp;

import java.math.BigInteger;

class Zl8f extends ClassLoader {
  static Object ZA;
  
  static String ZK;
  
  private static final String[] a;
  
  private static final String[] b;
  
  static boolean ZH(Object[] paramArrayOfObject, Object paramObject) throws Throwable {
    // Byte code:
    //   0: invokestatic ZK : ()Z
    //   3: istore_2
    //   4: getstatic burp/Zrof.ZB : Ljava/lang/Object;
    //   7: checkcast java/math/BigInteger
    //   10: invokevirtual toByteArray : ()[B
    //   13: astore_3
    //   14: aload_3
    //   15: arraylength
    //   16: iconst_2
    //   17: iadd
    //   18: newarray byte
    //   20: astore #5
    //   22: iconst_0
    //   23: istore #6
    //   25: iload #6
    //   27: aload_3
    //   28: arraylength
    //   29: if_icmpge -> 48
    //   32: aload #5
    //   34: iload #6
    //   36: aload_3
    //   37: iload #6
    //   39: baload
    //   40: bastore
    //   41: iinc #6, 1
    //   44: iload_2
    //   45: ifeq -> 25
    //   48: aload #5
    //   50: arraylength
    //   51: iconst_3
    //   52: idiv
    //   53: iconst_4
    //   54: imul
    //   55: newarray byte
    //   57: astore #4
    //   59: iconst_0
    //   60: istore #6
    //   62: iconst_0
    //   63: istore #7
    //   65: iload #6
    //   67: aload_3
    //   68: arraylength
    //   69: if_icmpge -> 180
    //   72: aload #4
    //   74: iload #7
    //   76: aload #5
    //   78: iload #6
    //   80: baload
    //   81: iconst_2
    //   82: iushr
    //   83: bipush #63
    //   85: iand
    //   86: i2b
    //   87: bastore
    //   88: aload #4
    //   90: iload #7
    //   92: iconst_1
    //   93: iadd
    //   94: aload #5
    //   96: iload #6
    //   98: iconst_1
    //   99: iadd
    //   100: baload
    //   101: iconst_4
    //   102: iushr
    //   103: bipush #15
    //   105: iand
    //   106: aload #5
    //   108: iload #6
    //   110: baload
    //   111: iconst_4
    //   112: ishl
    //   113: bipush #63
    //   115: iand
    //   116: ior
    //   117: i2b
    //   118: bastore
    //   119: aload #4
    //   121: iload #7
    //   123: iconst_2
    //   124: iadd
    //   125: aload #5
    //   127: iload #6
    //   129: iconst_2
    //   130: iadd
    //   131: baload
    //   132: bipush #6
    //   134: iushr
    //   135: iconst_3
    //   136: iand
    //   137: aload #5
    //   139: iload #6
    //   141: iconst_1
    //   142: iadd
    //   143: baload
    //   144: iconst_2
    //   145: ishl
    //   146: bipush #63
    //   148: iand
    //   149: ior
    //   150: i2b
    //   151: bastore
    //   152: aload #4
    //   154: iload #7
    //   156: iconst_3
    //   157: iadd
    //   158: aload #5
    //   160: iload #6
    //   162: iconst_2
    //   163: iadd
    //   164: baload
    //   165: bipush #63
    //   167: iand
    //   168: i2b
    //   169: bastore
    //   170: iinc #6, 3
    //   173: iinc #7, 4
    //   176: iload_2
    //   177: ifeq -> 65
    //   180: iconst_0
    //   181: istore #6
    //   183: iload #6
    //   185: aload #4
    //   187: arraylength
    //   188: if_icmpge -> 372
    //   191: aload #4
    //   193: iload #6
    //   195: baload
    //   196: bipush #26
    //   198: if_icmpge -> 226
    //   201: aload #4
    //   203: iload #6
    //   205: aload #4
    //   207: iload #6
    //   209: baload
    //   210: bipush #65
    //   212: iadd
    //   213: i2b
    //   214: bastore
    //   215: iload_2
    //   216: ifeq -> 365
    //   219: goto -> 226
    //   222: invokestatic a : (Ljava/lang/Throwable;)Ljava/lang/Throwable;
    //   225: athrow
    //   226: aload #4
    //   228: iload #6
    //   230: baload
    //   231: bipush #52
    //   233: if_icmpge -> 271
    //   236: goto -> 243
    //   239: invokestatic a : (Ljava/lang/Throwable;)Ljava/lang/Throwable;
    //   242: athrow
    //   243: aload #4
    //   245: iload #6
    //   247: aload #4
    //   249: iload #6
    //   251: baload
    //   252: bipush #97
    //   254: iadd
    //   255: bipush #26
    //   257: isub
    //   258: i2b
    //   259: bastore
    //   260: iload_2
    //   261: ifeq -> 365
    //   264: goto -> 271
    //   267: invokestatic a : (Ljava/lang/Throwable;)Ljava/lang/Throwable;
    //   270: athrow
    //   271: aload #4
    //   273: iload #6
    //   275: baload
    //   276: bipush #62
    //   278: if_icmpge -> 316
    //   281: goto -> 288
    //   284: invokestatic a : (Ljava/lang/Throwable;)Ljava/lang/Throwable;
    //   287: athrow
    //   288: aload #4
    //   290: iload #6
    //   292: aload #4
    //   294: iload #6
    //   296: baload
    //   297: bipush #48
    //   299: iadd
    //   300: bipush #52
    //   302: isub
    //   303: i2b
    //   304: bastore
    //   305: iload_2
    //   306: ifeq -> 365
    //   309: goto -> 316
    //   312: invokestatic a : (Ljava/lang/Throwable;)Ljava/lang/Throwable;
    //   315: athrow
    //   316: aload #4
    //   318: iload #6
    //   320: baload
    //   321: bipush #63
    //   323: if_icmpge -> 351
    //   326: goto -> 333
    //   329: invokestatic a : (Ljava/lang/Throwable;)Ljava/lang/Throwable;
    //   332: athrow
    //   333: aload #4
    //   335: iload #6
    //   337: bipush #43
    //   339: bastore
    //   340: iload_2
    //   341: ifeq -> 365
    //   344: goto -> 351
    //   347: invokestatic a : (Ljava/lang/Throwable;)Ljava/lang/Throwable;
    //   350: athrow
    //   351: aload #4
    //   353: iload #6
    //   355: bipush #47
    //   357: bastore
    //   358: goto -> 365
    //   361: invokestatic a : (Ljava/lang/Throwable;)Ljava/lang/Throwable;
    //   364: athrow
    //   365: iinc #6, 1
    //   368: iload_2
    //   369: ifeq -> 183
    //   372: aload #4
    //   374: arraylength
    //   375: iconst_1
    //   376: isub
    //   377: istore #6
    //   379: iload #6
    //   381: aload_3
    //   382: arraylength
    //   383: iconst_4
    //   384: imul
    //   385: iconst_3
    //   386: idiv
    //   387: if_icmple -> 404
    //   390: aload #4
    //   392: iload #6
    //   394: bipush #61
    //   396: bastore
    //   397: iinc #6, -1
    //   400: iload_2
    //   401: ifeq -> 379
    //   404: new java/math/BigInteger
    //   407: dup
    //   408: aload #4
    //   410: invokespecial <init> : ([B)V
    //   413: invokevirtual abs : ()Ljava/math/BigInteger;
    //   416: putstatic burp/Zxo7.Zi : Ljava/lang/Object;
    //   419: getstatic burp/Zs_v.Zs : Ljava/lang/Object;
    //   422: checkcast java/math/BigInteger
    //   425: invokevirtual toByteArray : ()[B
    //   428: astore_3
    //   429: aload_3
    //   430: arraylength
    //   431: iconst_2
    //   432: iadd
    //   433: newarray byte
    //   435: astore #5
    //   437: iconst_0
    //   438: istore #6
    //   440: iload #6
    //   442: aload_3
    //   443: arraylength
    //   444: if_icmpge -> 463
    //   447: aload #5
    //   449: iload #6
    //   451: aload_3
    //   452: iload #6
    //   454: baload
    //   455: bastore
    //   456: iinc #6, 1
    //   459: iload_2
    //   460: ifeq -> 440
    //   463: aload #5
    //   465: arraylength
    //   466: iconst_3
    //   467: idiv
    //   468: iconst_4
    //   469: imul
    //   470: newarray byte
    //   472: astore #4
    //   474: iconst_0
    //   475: istore #6
    //   477: iconst_0
    //   478: istore #7
    //   480: iload #6
    //   482: aload_3
    //   483: arraylength
    //   484: if_icmpge -> 595
    //   487: aload #4
    //   489: iload #7
    //   491: aload #5
    //   493: iload #6
    //   495: baload
    //   496: iconst_2
    //   497: iushr
    //   498: bipush #63
    //   500: iand
    //   501: i2b
    //   502: bastore
    //   503: aload #4
    //   505: iload #7
    //   507: iconst_1
    //   508: iadd
    //   509: aload #5
    //   511: iload #6
    //   513: iconst_1
    //   514: iadd
    //   515: baload
    //   516: iconst_4
    //   517: iushr
    //   518: bipush #15
    //   520: iand
    //   521: aload #5
    //   523: iload #6
    //   525: baload
    //   526: iconst_4
    //   527: ishl
    //   528: bipush #63
    //   530: iand
    //   531: ior
    //   532: i2b
    //   533: bastore
    //   534: aload #4
    //   536: iload #7
    //   538: iconst_2
    //   539: iadd
    //   540: aload #5
    //   542: iload #6
    //   544: iconst_2
    //   545: iadd
    //   546: baload
    //   547: bipush #6
    //   549: iushr
    //   550: iconst_3
    //   551: iand
    //   552: aload #5
    //   554: iload #6
    //   556: iconst_1
    //   557: iadd
    //   558: baload
    //   559: iconst_2
    //   560: ishl
    //   561: bipush #63
    //   563: iand
    //   564: ior
    //   565: i2b
    //   566: bastore
    //   567: aload #4
    //   569: iload #7
    //   571: iconst_3
    //   572: iadd
    //   573: aload #5
    //   575: iload #6
    //   577: iconst_2
    //   578: iadd
    //   579: baload
    //   580: bipush #63
    //   582: iand
    //   583: i2b
    //   584: bastore
    //   585: iinc #6, 3
    //   588: iinc #7, 4
    //   591: iload_2
    //   592: ifeq -> 480
    //   595: iconst_0
    //   596: istore #6
    //   598: iload #6
    //   600: aload #4
    //   602: arraylength
    //   603: if_icmpge -> 787
    //   606: aload #4
    //   608: iload #6
    //   610: baload
    //   611: bipush #26
    //   613: if_icmpge -> 641
    //   616: aload #4
    //   618: iload #6
    //   620: aload #4
    //   622: iload #6
    //   624: baload
    //   625: bipush #65
    //   627: iadd
    //   628: i2b
    //   629: bastore
    //   630: iload_2
    //   631: ifeq -> 780
    //   634: goto -> 641
    //   637: invokestatic a : (Ljava/lang/Throwable;)Ljava/lang/Throwable;
    //   640: athrow
    //   641: aload #4
    //   643: iload #6
    //   645: baload
    //   646: bipush #52
    //   648: if_icmpge -> 686
    //   651: goto -> 658
    //   654: invokestatic a : (Ljava/lang/Throwable;)Ljava/lang/Throwable;
    //   657: athrow
    //   658: aload #4
    //   660: iload #6
    //   662: aload #4
    //   664: iload #6
    //   666: baload
    //   667: bipush #97
    //   669: iadd
    //   670: bipush #26
    //   672: isub
    //   673: i2b
    //   674: bastore
    //   675: iload_2
    //   676: ifeq -> 780
    //   679: goto -> 686
    //   682: invokestatic a : (Ljava/lang/Throwable;)Ljava/lang/Throwable;
    //   685: athrow
    //   686: aload #4
    //   688: iload #6
    //   690: baload
    //   691: bipush #62
    //   693: if_icmpge -> 731
    //   696: goto -> 703
    //   699: invokestatic a : (Ljava/lang/Throwable;)Ljava/lang/Throwable;
    //   702: athrow
    //   703: aload #4
    //   705: iload #6
    //   707: aload #4
    //   709: iload #6
    //   711: baload
    //   712: bipush #48
    //   714: iadd
    //   715: bipush #52
    //   717: isub
    //   718: i2b
    //   719: bastore
    //   720: iload_2
    //   721: ifeq -> 780
    //   724: goto -> 731
    //   727: invokestatic a : (Ljava/lang/Throwable;)Ljava/lang/Throwable;
    //   730: athrow
    //   731: aload #4
    //   733: iload #6
    //   735: baload
    //   736: bipush #63
    //   738: if_icmpge -> 766
    //   741: goto -> 748
    //   744: invokestatic a : (Ljava/lang/Throwable;)Ljava/lang/Throwable;
    //   747: athrow
    //   748: aload #4
    //   750: iload #6
    //   752: bipush #43
    //   754: bastore
    //   755: iload_2
    //   756: ifeq -> 780
    //   759: goto -> 766
    //   762: invokestatic a : (Ljava/lang/Throwable;)Ljava/lang/Throwable;
    //   765: athrow
    //   766: aload #4
    //   768: iload #6
    //   770: bipush #47
    //   772: bastore
    //   773: goto -> 780
    //   776: invokestatic a : (Ljava/lang/Throwable;)Ljava/lang/Throwable;
    //   779: athrow
    //   780: iinc #6, 1
    //   783: iload_2
    //   784: ifeq -> 598
    //   787: aload #4
    //   789: arraylength
    //   790: iconst_1
    //   791: isub
    //   792: istore #6
    //   794: iload #6
    //   796: aload_3
    //   797: arraylength
    //   798: iconst_4
    //   799: imul
    //   800: iconst_3
    //   801: idiv
    //   802: if_icmple -> 819
    //   805: aload #4
    //   807: iload #6
    //   809: bipush #61
    //   811: bastore
    //   812: iinc #6, -1
    //   815: iload_2
    //   816: ifeq -> 794
    //   819: new java/math/BigInteger
    //   822: dup
    //   823: aload #4
    //   825: invokespecial <init> : ([B)V
    //   828: invokevirtual abs : ()Ljava/math/BigInteger;
    //   831: putstatic burp/Zrjg.ZG : Ljava/lang/Object;
    //   834: new java/lang/StringBuilder
    //   837: dup
    //   838: invokespecial <init> : ()V
    //   841: astore_3
    //   842: iconst_0
    //   843: istore #4
    //   845: iload #4
    //   847: bipush #32
    //   849: if_icmpge -> 2183
    //   852: iload #4
    //   854: tableswitch default -> 2176, 0 -> 996, 1 -> 1033, 2 -> 1070, 3 -> 1107, 4 -> 1144, 5 -> 1181, 6 -> 1218, 7 -> 1255, 8 -> 1292, 9 -> 1329, 10 -> 1366, 11 -> 1403, 12 -> 1440, 13 -> 1477, 14 -> 1514, 15 -> 1551, 16 -> 1588, 17 -> 1625, 18 -> 1662, 19 -> 1699, 20 -> 1736, 21 -> 1773, 22 -> 1810, 23 -> 1847, 24 -> 1884, 25 -> 1921, 26 -> 1958, 27 -> 1995, 28 -> 2032, 29 -> 2069, 30 -> 2106, 31 -> 2143
    //   996: aload_3
    //   997: getstatic burp/Zzo5.ZX : Ljava/lang/String;
    //   1000: getstatic burp/Zg4k.ZE : Ljava/lang/Object;
    //   1003: checkcast java/math/BigInteger
    //   1006: invokevirtual intValue : ()I
    //   1009: bipush #32
    //   1011: irem
    //   1012: invokestatic abs : (I)I
    //   1015: invokevirtual charAt : (I)C
    //   1018: invokevirtual append : (C)Ljava/lang/StringBuilder;
    //   1021: pop
    //   1022: iload_2
    //   1023: ifeq -> 2176
    //   1026: goto -> 1033
    //   1029: invokestatic a : (Ljava/lang/Throwable;)Ljava/lang/Throwable;
    //   1032: athrow
    //   1033: aload_3
    //   1034: getstatic burp/Ze5f.Zt : Ljava/lang/String;
    //   1037: getstatic burp/Zlhq.Zw : Ljava/lang/Object;
    //   1040: checkcast java/math/BigInteger
    //   1043: invokevirtual intValue : ()I
    //   1046: bipush #32
    //   1048: irem
    //   1049: invokestatic abs : (I)I
    //   1052: invokevirtual charAt : (I)C
    //   1055: invokevirtual append : (C)Ljava/lang/StringBuilder;
    //   1058: pop
    //   1059: iload_2
    //   1060: ifeq -> 2176
    //   1063: goto -> 1070
    //   1066: invokestatic a : (Ljava/lang/Throwable;)Ljava/lang/Throwable;
    //   1069: athrow
    //   1070: aload_3
    //   1071: getstatic burp/Zlhy.ZS : Ljava/lang/String;
    //   1074: getstatic burp/Zlhq.Zw : Ljava/lang/Object;
    //   1077: checkcast java/math/BigInteger
    //   1080: invokevirtual intValue : ()I
    //   1083: bipush #32
    //   1085: irem
    //   1086: invokestatic abs : (I)I
    //   1089: invokevirtual charAt : (I)C
    //   1092: invokevirtual append : (C)Ljava/lang/StringBuilder;
    //   1095: pop
    //   1096: iload_2
    //   1097: ifeq -> 2176
    //   1100: goto -> 1107
    //   1103: invokestatic a : (Ljava/lang/Throwable;)Ljava/lang/Throwable;
    //   1106: athrow
    //   1107: aload_3
    //   1108: getstatic burp/Zlrm.Zt : Ljava/lang/String;
    //   1111: getstatic burp/Zs8y.ZG : Ljava/lang/Object;
    //   1114: checkcast java/math/BigInteger
    //   1117: invokevirtual intValue : ()I
    //   1120: bipush #32
    //   1122: irem
    //   1123: invokestatic abs : (I)I
    //   1126: invokevirtual charAt : (I)C
    //   1129: invokevirtual append : (C)Ljava/lang/StringBuilder;
    //   1132: pop
    //   1133: iload_2
    //   1134: ifeq -> 2176
    //   1137: goto -> 1144
    //   1140: invokestatic a : (Ljava/lang/Throwable;)Ljava/lang/Throwable;
    //   1143: athrow
    //   1144: aload_3
    //   1145: getstatic burp/Zmj8.ZL : Ljava/lang/String;
    //   1148: getstatic burp/Zmx6.ZJ : Ljava/lang/Object;
    //   1151: checkcast java/math/BigInteger
    //   1154: invokevirtual intValue : ()I
    //   1157: bipush #32
    //   1159: irem
    //   1160: invokestatic abs : (I)I
    //   1163: invokevirtual charAt : (I)C
    //   1166: invokevirtual append : (C)Ljava/lang/StringBuilder;
    //   1169: pop
    //   1170: iload_2
    //   1171: ifeq -> 2176
    //   1174: goto -> 1181
    //   1177: invokestatic a : (Ljava/lang/Throwable;)Ljava/lang/Throwable;
    //   1180: athrow
    //   1181: aload_3
    //   1182: getstatic burp/Zxg7.Zi : Ljava/lang/String;
    //   1185: getstatic burp/Zlo5.Zf : Ljava/lang/Object;
    //   1188: checkcast java/math/BigInteger
    //   1191: invokevirtual intValue : ()I
    //   1194: bipush #32
    //   1196: irem
    //   1197: invokestatic abs : (I)I
    //   1200: invokevirtual charAt : (I)C
    //   1203: invokevirtual append : (C)Ljava/lang/StringBuilder;
    //   1206: pop
    //   1207: iload_2
    //   1208: ifeq -> 2176
    //   1211: goto -> 1218
    //   1214: invokestatic a : (Ljava/lang/Throwable;)Ljava/lang/Throwable;
    //   1217: athrow
    //   1218: aload_3
    //   1219: getstatic burp/Zb8y.Zn : Ljava/lang/String;
    //   1222: getstatic burp/Zm52.ZR : Ljava/lang/Object;
    //   1225: checkcast java/math/BigInteger
    //   1228: invokevirtual intValue : ()I
    //   1231: bipush #32
    //   1233: irem
    //   1234: invokestatic abs : (I)I
    //   1237: invokevirtual charAt : (I)C
    //   1240: invokevirtual append : (C)Ljava/lang/StringBuilder;
    //   1243: pop
    //   1244: iload_2
    //   1245: ifeq -> 2176
    //   1248: goto -> 1255
    //   1251: invokestatic a : (Ljava/lang/Throwable;)Ljava/lang/Throwable;
    //   1254: athrow
    //   1255: aload_3
    //   1256: getstatic burp/Zzym.Zj : Ljava/lang/String;
    //   1259: getstatic burp/Zzox.Zq : Ljava/lang/Object;
    //   1262: checkcast java/math/BigInteger
    //   1265: invokevirtual intValue : ()I
    //   1268: bipush #32
    //   1270: irem
    //   1271: invokestatic abs : (I)I
    //   1274: invokevirtual charAt : (I)C
    //   1277: invokevirtual append : (C)Ljava/lang/StringBuilder;
    //   1280: pop
    //   1281: iload_2
    //   1282: ifeq -> 2176
    //   1285: goto -> 1292
    //   1288: invokestatic a : (Ljava/lang/Throwable;)Ljava/lang/Throwable;
    //   1291: athrow
    //   1292: aload_3
    //   1293: getstatic burp/Zs00.Zv : Ljava/lang/String;
    //   1296: getstatic burp/Ztkh.Zh : Ljava/lang/Object;
    //   1299: checkcast java/math/BigInteger
    //   1302: invokevirtual intValue : ()I
    //   1305: bipush #32
    //   1307: irem
    //   1308: invokestatic abs : (I)I
    //   1311: invokevirtual charAt : (I)C
    //   1314: invokevirtual append : (C)Ljava/lang/StringBuilder;
    //   1317: pop
    //   1318: iload_2
    //   1319: ifeq -> 2176
    //   1322: goto -> 1329
    //   1325: invokestatic a : (Ljava/lang/Throwable;)Ljava/lang/Throwable;
    //   1328: athrow
    //   1329: aload_3
    //   1330: getstatic burp/Zk7e.ZP : Ljava/lang/String;
    //   1333: getstatic burp/Zk12.Zh : Ljava/lang/Object;
    //   1336: checkcast java/math/BigInteger
    //   1339: invokevirtual intValue : ()I
    //   1342: bipush #32
    //   1344: irem
    //   1345: invokestatic abs : (I)I
    //   1348: invokevirtual charAt : (I)C
    //   1351: invokevirtual append : (C)Ljava/lang/StringBuilder;
    //   1354: pop
    //   1355: iload_2
    //   1356: ifeq -> 2176
    //   1359: goto -> 1366
    //   1362: invokestatic a : (Ljava/lang/Throwable;)Ljava/lang/Throwable;
    //   1365: athrow
    //   1366: aload_3
    //   1367: getstatic burp/Zrtv.ZA : Ljava/lang/String;
    //   1370: getstatic burp/Zlpj.Zc : Ljava/lang/Object;
    //   1373: checkcast java/math/BigInteger
    //   1376: invokevirtual intValue : ()I
    //   1379: bipush #32
    //   1381: irem
    //   1382: invokestatic abs : (I)I
    //   1385: invokevirtual charAt : (I)C
    //   1388: invokevirtual append : (C)Ljava/lang/StringBuilder;
    //   1391: pop
    //   1392: iload_2
    //   1393: ifeq -> 2176
    //   1396: goto -> 1403
    //   1399: invokestatic a : (Ljava/lang/Throwable;)Ljava/lang/Throwable;
    //   1402: athrow
    //   1403: aload_3
    //   1404: getstatic burp/Zt0t.ZR : Ljava/lang/String;
    //   1407: getstatic burp/Zrva.ZE : Ljava/lang/Object;
    //   1410: checkcast java/math/BigInteger
    //   1413: invokevirtual intValue : ()I
    //   1416: bipush #32
    //   1418: irem
    //   1419: invokestatic abs : (I)I
    //   1422: invokevirtual charAt : (I)C
    //   1425: invokevirtual append : (C)Ljava/lang/StringBuilder;
    //   1428: pop
    //   1429: iload_2
    //   1430: ifeq -> 2176
    //   1433: goto -> 1440
    //   1436: invokestatic a : (Ljava/lang/Throwable;)Ljava/lang/Throwable;
    //   1439: athrow
    //   1440: aload_3
    //   1441: getstatic burp/Ztdd.ZA : Ljava/lang/String;
    //   1444: getstatic burp/Zlhy.ZN : Ljava/lang/Object;
    //   1447: checkcast java/math/BigInteger
    //   1450: invokevirtual intValue : ()I
    //   1453: bipush #32
    //   1455: irem
    //   1456: invokestatic abs : (I)I
    //   1459: invokevirtual charAt : (I)C
    //   1462: invokevirtual append : (C)Ljava/lang/StringBuilder;
    //   1465: pop
    //   1466: iload_2
    //   1467: ifeq -> 2176
    //   1470: goto -> 1477
    //   1473: invokestatic a : (Ljava/lang/Throwable;)Ljava/lang/Throwable;
    //   1476: athrow
    //   1477: aload_3
    //   1478: getstatic burp/Ze54.ZU : Ljava/lang/String;
    //   1481: getstatic burp/Zt3f.Zp : Ljava/lang/Object;
    //   1484: checkcast java/math/BigInteger
    //   1487: invokevirtual intValue : ()I
    //   1490: bipush #32
    //   1492: irem
    //   1493: invokestatic abs : (I)I
    //   1496: invokevirtual charAt : (I)C
    //   1499: invokevirtual append : (C)Ljava/lang/StringBuilder;
    //   1502: pop
    //   1503: iload_2
    //   1504: ifeq -> 2176
    //   1507: goto -> 1514
    //   1510: invokestatic a : (Ljava/lang/Throwable;)Ljava/lang/Throwable;
    //   1513: athrow
    //   1514: aload_3
    //   1515: getstatic burp/Zlnm.ZL : Ljava/lang/String;
    //   1518: getstatic burp/Ztye.ZK : Ljava/lang/Object;
    //   1521: checkcast java/math/BigInteger
    //   1524: invokevirtual intValue : ()I
    //   1527: bipush #32
    //   1529: irem
    //   1530: invokestatic abs : (I)I
    //   1533: invokevirtual charAt : (I)C
    //   1536: invokevirtual append : (C)Ljava/lang/StringBuilder;
    //   1539: pop
    //   1540: iload_2
    //   1541: ifeq -> 2176
    //   1544: goto -> 1551
    //   1547: invokestatic a : (Ljava/lang/Throwable;)Ljava/lang/Throwable;
    //   1550: athrow
    //   1551: aload_3
    //   1552: getstatic burp/Zzo5.ZX : Ljava/lang/String;
    //   1555: getstatic burp/Zlh8.Zm : Ljava/lang/Object;
    //   1558: checkcast java/math/BigInteger
    //   1561: invokevirtual intValue : ()I
    //   1564: bipush #32
    //   1566: irem
    //   1567: invokestatic abs : (I)I
    //   1570: invokevirtual charAt : (I)C
    //   1573: invokevirtual append : (C)Ljava/lang/StringBuilder;
    //   1576: pop
    //   1577: iload_2
    //   1578: ifeq -> 2176
    //   1581: goto -> 1588
    //   1584: invokestatic a : (Ljava/lang/Throwable;)Ljava/lang/Throwable;
    //   1587: athrow
    //   1588: aload_3
    //   1589: getstatic burp/Ze54.ZU : Ljava/lang/String;
    //   1592: getstatic burp/Zxjk.Zk : Ljava/lang/Object;
    //   1595: checkcast java/math/BigInteger
    //   1598: invokevirtual intValue : ()I
    //   1601: bipush #32
    //   1603: irem
    //   1604: invokestatic abs : (I)I
    //   1607: invokevirtual charAt : (I)C
    //   1610: invokevirtual append : (C)Ljava/lang/StringBuilder;
    //   1613: pop
    //   1614: iload_2
    //   1615: ifeq -> 2176
    //   1618: goto -> 1625
    //   1621: invokestatic a : (Ljava/lang/Throwable;)Ljava/lang/Throwable;
    //   1624: athrow
    //   1625: aload_3
    //   1626: getstatic burp/Zl39.ZI : Ljava/lang/String;
    //   1629: getstatic burp/Zzyr.Za : Ljava/lang/Object;
    //   1632: checkcast java/math/BigInteger
    //   1635: invokevirtual intValue : ()I
    //   1638: bipush #32
    //   1640: irem
    //   1641: invokestatic abs : (I)I
    //   1644: invokevirtual charAt : (I)C
    //   1647: invokevirtual append : (C)Ljava/lang/StringBuilder;
    //   1650: pop
    //   1651: iload_2
    //   1652: ifeq -> 2176
    //   1655: goto -> 1662
    //   1658: invokestatic a : (Ljava/lang/Throwable;)Ljava/lang/Throwable;
    //   1661: athrow
    //   1662: aload_3
    //   1663: getstatic burp/Zs8q.Zs : Ljava/lang/String;
    //   1666: getstatic burp/Zsf7.Zg : Ljava/lang/Object;
    //   1669: checkcast java/math/BigInteger
    //   1672: invokevirtual intValue : ()I
    //   1675: bipush #32
    //   1677: irem
    //   1678: invokestatic abs : (I)I
    //   1681: invokevirtual charAt : (I)C
    //   1684: invokevirtual append : (C)Ljava/lang/StringBuilder;
    //   1687: pop
    //   1688: iload_2
    //   1689: ifeq -> 2176
    //   1692: goto -> 1699
    //   1695: invokestatic a : (Ljava/lang/Throwable;)Ljava/lang/Throwable;
    //   1698: athrow
    //   1699: aload_3
    //   1700: getstatic burp/Zzoi.ZR : Ljava/lang/String;
    //   1703: getstatic burp/Zest.Zq : Ljava/lang/Object;
    //   1706: checkcast java/math/BigInteger
    //   1709: invokevirtual intValue : ()I
    //   1712: bipush #32
    //   1714: irem
    //   1715: invokestatic abs : (I)I
    //   1718: invokevirtual charAt : (I)C
    //   1721: invokevirtual append : (C)Ljava/lang/StringBuilder;
    //   1724: pop
    //   1725: iload_2
    //   1726: ifeq -> 2176
    //   1729: goto -> 1736
    //   1732: invokestatic a : (Ljava/lang/Throwable;)Ljava/lang/Throwable;
    //   1735: athrow
    //   1736: aload_3
    //   1737: getstatic burp/Zl06.ZL : Ljava/lang/String;
    //   1740: getstatic burp/Zz20.ZN : Ljava/lang/Object;
    //   1743: checkcast java/math/BigInteger
    //   1746: invokevirtual intValue : ()I
    //   1749: bipush #32
    //   1751: irem
    //   1752: invokestatic abs : (I)I
    //   1755: invokevirtual charAt : (I)C
    //   1758: invokevirtual append : (C)Ljava/lang/StringBuilder;
    //   1761: pop
    //   1762: iload_2
    //   1763: ifeq -> 2176
    //   1766: goto -> 1773
    //   1769: invokestatic a : (Ljava/lang/Throwable;)Ljava/lang/Throwable;
    //   1772: athrow
    //   1773: aload_3
    //   1774: getstatic burp/Zzmu.ZF : Ljava/lang/String;
    //   1777: getstatic burp/Zs8q.ZI : Ljava/lang/Object;
    //   1780: checkcast java/math/BigInteger
    //   1783: invokevirtual intValue : ()I
    //   1786: bipush #32
    //   1788: irem
    //   1789: invokestatic abs : (I)I
    //   1792: invokevirtual charAt : (I)C
    //   1795: invokevirtual append : (C)Ljava/lang/StringBuilder;
    //   1798: pop
    //   1799: iload_2
    //   1800: ifeq -> 2176
    //   1803: goto -> 1810
    //   1806: invokestatic a : (Ljava/lang/Throwable;)Ljava/lang/Throwable;
    //   1809: athrow
    //   1810: aload_3
    //   1811: getstatic burp/Ztj5.Zt : Ljava/lang/String;
    //   1814: getstatic burp/Zs8s.ZG : Ljava/lang/Object;
    //   1817: checkcast java/math/BigInteger
    //   1820: invokevirtual intValue : ()I
    //   1823: bipush #32
    //   1825: irem
    //   1826: invokestatic abs : (I)I
    //   1829: invokevirtual charAt : (I)C
    //   1832: invokevirtual append : (C)Ljava/lang/StringBuilder;
    //   1835: pop
    //   1836: iload_2
    //   1837: ifeq -> 2176
    //   1840: goto -> 1847
    //   1843: invokestatic a : (Ljava/lang/Throwable;)Ljava/lang/Throwable;
    //   1846: athrow
    //   1847: aload_3
    //   1848: getstatic burp/Zbzk.ZS : Ljava/lang/String;
    //   1851: getstatic burp/Zrpu.Zi : Ljava/lang/Object;
    //   1854: checkcast java/math/BigInteger
    //   1857: invokevirtual intValue : ()I
    //   1860: bipush #32
    //   1862: irem
    //   1863: invokestatic abs : (I)I
    //   1866: invokevirtual charAt : (I)C
    //   1869: invokevirtual append : (C)Ljava/lang/StringBuilder;
    //   1872: pop
    //   1873: iload_2
    //   1874: ifeq -> 2176
    //   1877: goto -> 1884
    //   1880: invokestatic a : (Ljava/lang/Throwable;)Ljava/lang/Throwable;
    //   1883: athrow
    //   1884: aload_3
    //   1885: getstatic burp/Zzmw.Zd : Ljava/lang/String;
    //   1888: getstatic burp/Zs0_.Zu : Ljava/lang/Object;
    //   1891: checkcast java/math/BigInteger
    //   1894: invokevirtual intValue : ()I
    //   1897: bipush #32
    //   1899: irem
    //   1900: invokestatic abs : (I)I
    //   1903: invokevirtual charAt : (I)C
    //   1906: invokevirtual append : (C)Ljava/lang/StringBuilder;
    //   1909: pop
    //   1910: iload_2
    //   1911: ifeq -> 2176
    //   1914: goto -> 1921
    //   1917: invokestatic a : (Ljava/lang/Throwable;)Ljava/lang/Throwable;
    //   1920: athrow
    //   1921: aload_3
    //   1922: getstatic burp/Zeoy.ZS : Ljava/lang/String;
    //   1925: getstatic burp/Zk7f.Za : Ljava/lang/Object;
    //   1928: checkcast java/math/BigInteger
    //   1931: invokevirtual intValue : ()I
    //   1934: bipush #32
    //   1936: irem
    //   1937: invokestatic abs : (I)I
    //   1940: invokevirtual charAt : (I)C
    //   1943: invokevirtual append : (C)Ljava/lang/StringBuilder;
    //   1946: pop
    //   1947: iload_2
    //   1948: ifeq -> 2176
    //   1951: goto -> 1958
    //   1954: invokestatic a : (Ljava/lang/Throwable;)Ljava/lang/Throwable;
    //   1957: athrow
    //   1958: aload_3
    //   1959: getstatic burp/Zlx5.ZP : Ljava/lang/String;
    //   1962: getstatic burp/Zxo7.Zi : Ljava/lang/Object;
    //   1965: checkcast java/math/BigInteger
    //   1968: invokevirtual intValue : ()I
    //   1971: bipush #32
    //   1973: irem
    //   1974: invokestatic abs : (I)I
    //   1977: invokevirtual charAt : (I)C
    //   1980: invokevirtual append : (C)Ljava/lang/StringBuilder;
    //   1983: pop
    //   1984: iload_2
    //   1985: ifeq -> 2176
    //   1988: goto -> 1995
    //   1991: invokestatic a : (Ljava/lang/Throwable;)Ljava/lang/Throwable;
    //   1994: athrow
    //   1995: aload_3
    //   1996: getstatic burp/Zrcy.Zq : Ljava/lang/String;
    //   1999: getstatic burp/Zm4i.Zr : Ljava/lang/Object;
    //   2002: checkcast java/math/BigInteger
    //   2005: invokevirtual intValue : ()I
    //   2008: bipush #32
    //   2010: irem
    //   2011: invokestatic abs : (I)I
    //   2014: invokevirtual charAt : (I)C
    //   2017: invokevirtual append : (C)Ljava/lang/StringBuilder;
    //   2020: pop
    //   2021: iload_2
    //   2022: ifeq -> 2176
    //   2025: goto -> 2032
    //   2028: invokestatic a : (Ljava/lang/Throwable;)Ljava/lang/Throwable;
    //   2031: athrow
    //   2032: aload_3
    //   2033: getstatic burp/Zxjv.ZF : Ljava/lang/String;
    //   2036: getstatic burp/Zgzv.Zb : Ljava/lang/Object;
    //   2039: checkcast java/math/BigInteger
    //   2042: invokevirtual intValue : ()I
    //   2045: bipush #32
    //   2047: irem
    //   2048: invokestatic abs : (I)I
    //   2051: invokevirtual charAt : (I)C
    //   2054: invokevirtual append : (C)Ljava/lang/StringBuilder;
    //   2057: pop
    //   2058: iload_2
    //   2059: ifeq -> 2176
    //   2062: goto -> 2069
    //   2065: invokestatic a : (Ljava/lang/Throwable;)Ljava/lang/Throwable;
    //   2068: athrow
    //   2069: aload_3
    //   2070: getstatic burp/Ztkh.ZP : Ljava/lang/String;
    //   2073: getstatic burp/Zxe.Zg : Ljava/lang/Object;
    //   2076: checkcast java/math/BigInteger
    //   2079: invokevirtual intValue : ()I
    //   2082: bipush #32
    //   2084: irem
    //   2085: invokestatic abs : (I)I
    //   2088: invokevirtual charAt : (I)C
    //   2091: invokevirtual append : (C)Ljava/lang/StringBuilder;
    //   2094: pop
    //   2095: iload_2
    //   2096: ifeq -> 2176
    //   2099: goto -> 2106
    //   2102: invokestatic a : (Ljava/lang/Throwable;)Ljava/lang/Throwable;
    //   2105: athrow
    //   2106: aload_3
    //   2107: getstatic burp/Ze5t.ZX : Ljava/lang/String;
    //   2110: getstatic burp/Zrva.ZE : Ljava/lang/Object;
    //   2113: checkcast java/math/BigInteger
    //   2116: invokevirtual intValue : ()I
    //   2119: bipush #32
    //   2121: irem
    //   2122: invokestatic abs : (I)I
    //   2125: invokevirtual charAt : (I)C
    //   2128: invokevirtual append : (C)Ljava/lang/StringBuilder;
    //   2131: pop
    //   2132: iload_2
    //   2133: ifeq -> 2176
    //   2136: goto -> 2143
    //   2139: invokestatic a : (Ljava/lang/Throwable;)Ljava/lang/Throwable;
    //   2142: athrow
    //   2143: aload_3
    //   2144: getstatic burp/Zxn5.ZI : Ljava/lang/String;
    //   2147: getstatic burp/Ztfh.Zo : Ljava/lang/Object;
    //   2150: checkcast java/math/BigInteger
    //   2153: invokevirtual intValue : ()I
    //   2156: bipush #32
    //   2158: irem
    //   2159: invokestatic abs : (I)I
    //   2162: invokevirtual charAt : (I)C
    //   2165: invokevirtual append : (C)Ljava/lang/StringBuilder;
    //   2168: pop
    //   2169: goto -> 2176
    //   2172: invokestatic a : (Ljava/lang/Throwable;)Ljava/lang/Throwable;
    //   2175: athrow
    //   2176: iinc #4, 1
    //   2179: iload_2
    //   2180: ifeq -> 845
    //   2183: aload_3
    //   2184: invokevirtual toString : ()Ljava/lang/String;
    //   2187: putstatic burp/Zke7.Zl : Ljava/lang/String;
    //   2190: sipush #22064
    //   2193: sipush #-6111
    //   2196: invokestatic a : (II)Ljava/lang/String;
    //   2199: iconst_1
    //   2200: ldc burp/Zzxa
    //   2202: invokevirtual getClassLoader : ()Ljava/lang/ClassLoader;
    //   2205: invokestatic forName : (Ljava/lang/String;ZLjava/lang/ClassLoader;)Ljava/lang/Class;
    //   2208: invokevirtual getDeclaredFields : ()[Ljava/lang/reflect/Field;
    //   2211: astore #4
    //   2213: aload #4
    //   2215: arraylength
    //   2216: istore #5
    //   2218: iconst_0
    //   2219: istore #6
    //   2221: iload #6
    //   2223: iload #5
    //   2225: if_icmpge -> 2363
    //   2228: aload #4
    //   2230: iload #6
    //   2232: aaload
    //   2233: astore #7
    //   2235: aload #7
    //   2237: invokevirtual getModifiers : ()I
    //   2240: invokestatic isStatic : (I)Z
    //   2243: ifne -> 2253
    //   2246: goto -> 2356
    //   2249: invokestatic a : (Ljava/lang/Throwable;)Ljava/lang/Throwable;
    //   2252: athrow
    //   2253: aload #7
    //   2255: invokevirtual getType : ()Ljava/lang/Class;
    //   2258: astore #8
    //   2260: aload #8
    //   2262: ifnull -> 2343
    //   2265: aload #8
    //   2267: invokevirtual isPrimitive : ()Z
    //   2270: ifne -> 2343
    //   2273: goto -> 2280
    //   2276: invokestatic a : (Ljava/lang/Throwable;)Ljava/lang/Throwable;
    //   2279: athrow
    //   2280: aload #8
    //   2282: invokevirtual getPackage : ()Ljava/lang/Package;
    //   2285: ifnull -> 2343
    //   2288: goto -> 2295
    //   2291: invokestatic a : (Ljava/lang/Throwable;)Ljava/lang/Throwable;
    //   2294: athrow
    //   2295: aload #8
    //   2297: invokevirtual getPackage : ()Ljava/lang/Package;
    //   2300: invokevirtual getName : ()Ljava/lang/String;
    //   2303: ifnull -> 2343
    //   2306: goto -> 2313
    //   2309: invokestatic a : (Ljava/lang/Throwable;)Ljava/lang/Throwable;
    //   2312: athrow
    //   2313: aload #8
    //   2315: invokevirtual getPackage : ()Ljava/lang/Package;
    //   2318: invokevirtual getName : ()Ljava/lang/String;
    //   2321: sipush #22067
    //   2324: sipush #12676
    //   2327: invokestatic a : (II)Ljava/lang/String;
    //   2330: invokevirtual startsWith : (Ljava/lang/String;)Z
    //   2333: ifne -> 2343
    //   2336: goto -> 2343
    //   2339: invokestatic a : (Ljava/lang/Throwable;)Ljava/lang/Throwable;
    //   2342: athrow
    //   2343: aload #7
    //   2345: iconst_1
    //   2346: invokevirtual setAccessible : (Z)V
    //   2349: aload #7
    //   2351: aconst_null
    //   2352: invokevirtual get : (Ljava/lang/Object;)Ljava/lang/Object;
    //   2355: pop
    //   2356: iinc #6, 1
    //   2359: iload_2
    //   2360: ifeq -> 2221
    //   2363: sipush #22069
    //   2366: sipush #15812
    //   2369: invokestatic a : (II)Ljava/lang/String;
    //   2372: invokestatic forName : (Ljava/lang/String;)Ljava/lang/Class;
    //   2375: invokevirtual getDeclaredMethods : ()[Ljava/lang/reflect/Method;
    //   2378: astore #4
    //   2380: aload #4
    //   2382: arraylength
    //   2383: istore #5
    //   2385: iconst_0
    //   2386: istore #6
    //   2388: iload #6
    //   2390: iload #5
    //   2392: if_icmpge -> 2525
    //   2395: aload #4
    //   2397: iload #6
    //   2399: aaload
    //   2400: astore #7
    //   2402: aload #7
    //   2404: invokevirtual getParameterTypes : ()[Ljava/lang/Class;
    //   2407: pop
    //   2408: aload #7
    //   2410: invokevirtual getModifiers : ()I
    //   2413: invokestatic isStatic : (I)Z
    //   2416: ifeq -> 2511
    //   2419: aload #7
    //   2421: invokevirtual getParameterTypes : ()[Ljava/lang/Class;
    //   2424: arraylength
    //   2425: iconst_2
    //   2426: if_icmpne -> 2511
    //   2429: goto -> 2436
    //   2432: invokestatic a : (Ljava/lang/Throwable;)Ljava/lang/Throwable;
    //   2435: athrow
    //   2436: aload #7
    //   2438: invokevirtual getReturnType : ()Ljava/lang/Class;
    //   2441: getstatic java/lang/Void.TYPE : Ljava/lang/Class;
    //   2444: invokevirtual equals : (Ljava/lang/Object;)Z
    //   2447: ifeq -> 2511
    //   2450: goto -> 2457
    //   2453: invokestatic a : (Ljava/lang/Throwable;)Ljava/lang/Throwable;
    //   2456: athrow
    //   2457: aload #7
    //   2459: iconst_1
    //   2460: invokevirtual setAccessible : (Z)V
    //   2463: aload #7
    //   2465: aconst_null
    //   2466: iconst_2
    //   2467: anewarray java/lang/Object
    //   2470: dup
    //   2471: iconst_0
    //   2472: aload_0
    //   2473: aastore
    //   2474: dup
    //   2475: iconst_1
    //   2476: aload_1
    //   2477: ifnonnull -> 2495
    //   2480: goto -> 2487
    //   2483: invokestatic a : (Ljava/lang/Throwable;)Ljava/lang/Throwable;
    //   2486: athrow
    //   2487: aload_1
    //   2488: goto -> 2502
    //   2491: invokestatic a : (Ljava/lang/Throwable;)Ljava/lang/Throwable;
    //   2494: athrow
    //   2495: aload_1
    //   2496: checkcast [B
    //   2499: invokevirtual clone : ()Ljava/lang/Object;
    //   2502: aastore
    //   2503: invokevirtual invoke : (Ljava/lang/Object;[Ljava/lang/Object;)Ljava/lang/Object;
    //   2506: pop
    //   2507: iload_2
    //   2508: ifeq -> 2525
    //   2511: iinc #6, 1
    //   2514: iload_2
    //   2515: ifeq -> 2388
    //   2518: goto -> 2525
    //   2521: invokestatic a : (Ljava/lang/Throwable;)Ljava/lang/Throwable;
    //   2524: athrow
    //   2525: getstatic burp/Zl50.Zm : Ljava/lang/String;
    //   2528: getstatic burp/Zmr7.ZO : Ljava/lang/Object;
    //   2531: checkcast java/math/BigInteger
    //   2534: invokevirtual intValue : ()I
    //   2537: bipush #32
    //   2539: irem
    //   2540: invokestatic abs : (I)I
    //   2543: invokevirtual charAt : (I)C
    //   2546: getstatic burp/Zrcy.Zq : Ljava/lang/String;
    //   2549: getstatic burp/Zrtv.Zg : Ljava/lang/Object;
    //   2552: checkcast java/math/BigInteger
    //   2555: invokevirtual intValue : ()I
    //   2558: bipush #32
    //   2560: irem
    //   2561: invokestatic abs : (I)I
    //   2564: invokevirtual charAt : (I)C
    //   2567: if_icmpgt -> 2674
    //   2570: getstatic burp/Zr48.ZG : Ljava/lang/String;
    //   2573: getstatic burp/Zt5j.Zn : Ljava/lang/Object;
    //   2576: checkcast java/math/BigInteger
    //   2579: invokevirtual intValue : ()I
    //   2582: bipush #32
    //   2584: irem
    //   2585: invokestatic abs : (I)I
    //   2588: invokevirtual charAt : (I)C
    //   2591: getstatic burp/Zrcy.Zq : Ljava/lang/String;
    //   2594: getstatic burp/Zrpu.Zi : Ljava/lang/Object;
    //   2597: checkcast java/math/BigInteger
    //   2600: invokevirtual intValue : ()I
    //   2603: bipush #32
    //   2605: irem
    //   2606: invokestatic abs : (I)I
    //   2609: invokevirtual charAt : (I)C
    //   2612: if_icmpgt -> 2674
    //   2615: goto -> 2622
    //   2618: invokestatic a : (Ljava/lang/Throwable;)Ljava/lang/Throwable;
    //   2621: athrow
    //   2622: getstatic burp/Zzmw.Zd : Ljava/lang/String;
    //   2625: getstatic burp/Zm6h.ZB : Ljava/lang/Object;
    //   2628: checkcast java/math/BigInteger
    //   2631: invokevirtual intValue : ()I
    //   2634: bipush #32
    //   2636: irem
    //   2637: invokestatic abs : (I)I
    //   2640: invokevirtual charAt : (I)C
    //   2643: getstatic burp/Zztn.ZY : Ljava/lang/String;
    //   2646: getstatic burp/Zr2i.ZD : Ljava/lang/Object;
    //   2649: checkcast java/math/BigInteger
    //   2652: invokevirtual intValue : ()I
    //   2655: bipush #32
    //   2657: irem
    //   2658: invokestatic abs : (I)I
    //   2661: invokevirtual charAt : (I)C
    //   2664: if_icmpgt -> 2682
    //   2667: goto -> 2674
    //   2670: invokestatic a : (Ljava/lang/Throwable;)Ljava/lang/Throwable;
    //   2673: athrow
    //   2674: iconst_1
    //   2675: goto -> 2683
    //   2678: invokestatic a : (Ljava/lang/Throwable;)Ljava/lang/Throwable;
    //   2681: athrow
    //   2682: iconst_0
    //   2683: ireturn
    //   2684: astore_3
    //   2685: new java/lang/Exception
    //   2688: dup
    //   2689: aload_3
    //   2690: invokevirtual getMessage : ()Ljava/lang/String;
    //   2693: invokespecial <init> : (Ljava/lang/String;)V
    //   2696: athrow
    // Exception table:
    //   from	to	target	type
    //   4	2683	2684	java/lang/Throwable
    //   191	219	222	java/lang/Throwable
    //   201	236	239	java/lang/Throwable
    //   226	264	267	java/lang/Throwable
    //   243	281	284	java/lang/Throwable
    //   271	309	312	java/lang/Throwable
    //   288	326	329	java/lang/Throwable
    //   316	344	347	java/lang/Throwable
    //   333	358	361	java/lang/Throwable
    //   606	634	637	java/lang/Throwable
    //   616	651	654	java/lang/Throwable
    //   641	679	682	java/lang/Throwable
    //   658	696	699	java/lang/Throwable
    //   686	724	727	java/lang/Throwable
    //   703	741	744	java/lang/Throwable
    //   731	759	762	java/lang/Throwable
    //   748	773	776	java/lang/Throwable
    //   852	1026	1029	java/lang/Throwable
    //   996	1063	1066	java/lang/Throwable
    //   1033	1100	1103	java/lang/Throwable
    //   1070	1137	1140	java/lang/Throwable
    //   1107	1174	1177	java/lang/Throwable
    //   1144	1211	1214	java/lang/Throwable
    //   1181	1248	1251	java/lang/Throwable
    //   1218	1285	1288	java/lang/Throwable
    //   1255	1322	1325	java/lang/Throwable
    //   1292	1359	1362	java/lang/Throwable
    //   1329	1396	1399	java/lang/Throwable
    //   1366	1433	1436	java/lang/Throwable
    //   1403	1470	1473	java/lang/Throwable
    //   1440	1507	1510	java/lang/Throwable
    //   1477	1544	1547	java/lang/Throwable
    //   1514	1581	1584	java/lang/Throwable
    //   1551	1618	1621	java/lang/Throwable
    //   1588	1655	1658	java/lang/Throwable
    //   1625	1692	1695	java/lang/Throwable
    //   1662	1729	1732	java/lang/Throwable
    //   1699	1766	1769	java/lang/Throwable
    //   1736	1803	1806	java/lang/Throwable
    //   1773	1840	1843	java/lang/Throwable
    //   1810	1877	1880	java/lang/Throwable
    //   1847	1914	1917	java/lang/Throwable
    //   1884	1951	1954	java/lang/Throwable
    //   1921	1988	1991	java/lang/Throwable
    //   1958	2025	2028	java/lang/Throwable
    //   1995	2062	2065	java/lang/Throwable
    //   2032	2099	2102	java/lang/Throwable
    //   2069	2136	2139	java/lang/Throwable
    //   2106	2169	2172	java/lang/Throwable
    //   2235	2249	2249	java/lang/Throwable
    //   2260	2273	2276	java/lang/Throwable
    //   2265	2288	2291	java/lang/Throwable
    //   2280	2306	2309	java/lang/Throwable
    //   2295	2336	2339	java/lang/Throwable
    //   2402	2429	2432	java/lang/Throwable
    //   2419	2450	2453	java/lang/Throwable
    //   2436	2480	2483	java/lang/Throwable
    //   2457	2491	2491	java/lang/Throwable
    //   2502	2518	2521	java/lang/Throwable
    //   2525	2615	2618	java/lang/Throwable
    //   2570	2667	2670	java/lang/Throwable
    //   2622	2678	2678	java/lang/Throwable
  }
  
  static void Zn(Object paramObject) {
    Zkll.ZX = a(22070, -20524);
    Zkll.Zl = new BigInteger(a(22066, 10566));
    boolean bool = Zt2e.ZK();
    try {
      try {
        if (Zk7e.ZP.charAt(Math.abs(((BigInteger)Zkt7.ZY).intValue() % 32)) > Zkt7.ZM.charAt(Math.abs(((BigInteger)Zkt7.ZY).intValue() % 32))) {
          try {
            Zql.Zt(Class.forName(a(22068, 14531)));
            if (bool)
              Zmhi.ZC(Class.forName(a(22065, 19094))); 
          } catch (Throwable throwable) {
            throw a(null);
          } 
          return;
        } 
      } catch (Throwable throwable) {
        throw a(null);
      } 
      Zmhi.ZC(Class.forName(a(22065, 19094)));
    } catch (Throwable throwable) {}
  }
  
  static void ZL(Object[] paramArrayOfObject, Object paramObject) throws Throwable {}
  
  static {
    // Byte code:
    //   0: bipush #8
    //   2: anewarray java/lang/String
    //   5: astore #5
    //   7: iconst_0
    //   8: istore_3
    //   9: ldc 'ÃÂ³iÂ½ÂÃ‰j8=Â“Ã†)Ã¡Â¤L\\rÂ¶-Ã 1y_Ã˜Ã•:Â¨Ã³Ã–'JÃ·Ã¨g$Ã®Ã·Â«Â¨Ã´lÂ‡cÂ­t\\fÂˆÃ›bÃœ3Ã¥Â‘:Ã‹Â‘ouQÂ¥Ã‘aXÃµÂ¦Â€M[{uÂ·lÃˆÂ†ÃœÃž#\\t9o)UÂ£ÃŠ^Â¾\\tQÃ¨$Â¥Ã¾Â“) MÂ·Ã‡~iJÂ¦\\n\\r7Â•EÂ–vKÂ†Â³8uXÂ¸Ã‰Â‚Ã’Ã/rIÃ” Â‰Ã²rÃ¾uÂ‚Ã€Y_!Ã«Â‘Â‹WpYÂ¸cÃ‰Â·'+Â•Â‚N,Â™'
    //   11: dup
    //   12: astore_2
    //   13: invokevirtual length : ()I
    //   16: istore #4
    //   18: bipush #77
    //   20: istore_1
    //   21: iconst_m1
    //   22: istore_0
    //   23: bipush #110
    //   25: iinc #0, 1
    //   28: aload_2
    //   29: iload_0
    //   30: dup
    //   31: iload_1
    //   32: iadd
    //   33: invokevirtual substring : (II)Ljava/lang/String;
    //   36: iconst_m1
    //   37: goto -> 143
    //   40: aload #5
    //   42: swap
    //   43: iload_3
    //   44: iinc #3, 1
    //   47: swap
    //   48: aastore
    //   49: iload_0
    //   50: iload_1
    //   51: iadd
    //   52: dup
    //   53: istore_0
    //   54: iload #4
    //   56: if_icmpge -> 68
    //   59: aload_2
    //   60: iload_0
    //   61: invokevirtual charAt : (I)C
    //   64: istore_1
    //   65: goto -> 23
    //   68: ldc 'Â©)ÃgDÂ²Ã“=Â”\\tÃ¡ÃˆÃ eBÃ¨- '
    //   70: dup
    //   71: astore_2
    //   72: invokevirtual length : ()I
    //   75: istore #4
    //   77: bipush #9
    //   79: istore_1
    //   80: iconst_m1
    //   81: istore_0
    //   82: bipush #26
    //   84: iinc #0, 1
    //   87: aload_2
    //   88: iload_0
    //   89: dup
    //   90: iload_1
    //   91: iadd
    //   92: invokevirtual substring : (II)Ljava/lang/String;
    //   95: iconst_0
    //   96: goto -> 143
    //   99: aload #5
    //   101: swap
    //   102: iload_3
    //   103: iinc #3, 1
    //   106: swap
    //   107: aastore
    //   108: iload_0
    //   109: iload_1
    //   110: iadd
    //   111: dup
    //   112: istore_0
    //   113: iload #4
    //   115: if_icmpge -> 127
    //   118: aload_2
    //   119: iload_0
    //   120: invokevirtual charAt : (I)C
    //   123: istore_1
    //   124: goto -> 82
    //   127: aload #5
    //   129: putstatic burp/Zl8f.a : [Ljava/lang/String;
    //   132: bipush #8
    //   134: anewarray java/lang/String
    //   137: putstatic burp/Zl8f.b : [Ljava/lang/String;
    //   140: goto -> 300
    //   143: dup_x2
    //   144: pop
    //   145: invokevirtual toCharArray : ()[C
    //   148: dup_x1
    //   149: arraylength
    //   150: dup_x2
    //   151: pop
    //   152: iconst_0
    //   153: istore #6
    //   155: dup2_x1
    //   156: pop2
    //   157: dup_x2
    //   158: iconst_1
    //   159: if_icmpgt -> 260
    //   162: dup2
    //   163: swap
    //   164: iload #6
    //   166: dup2_x1
    //   167: caload
    //   168: swap
    //   169: iload #6
    //   171: bipush #7
    //   173: irem
    //   174: tableswitch default -> 242, 0 -> 212, 1 -> 217, 2 -> 222, 3 -> 227, 4 -> 232, 5 -> 237
    //   212: bipush #95
    //   214: goto -> 244
    //   217: bipush #69
    //   219: goto -> 244
    //   222: bipush #26
    //   224: goto -> 244
    //   227: bipush #24
    //   229: goto -> 244
    //   232: bipush #116
    //   234: goto -> 244
    //   237: bipush #32
    //   239: goto -> 244
    //   242: bipush #20
    //   244: ixor
    //   245: ixor
    //   246: i2c
    //   247: castore
    //   248: iinc #6, 1
    //   251: dup
    //   252: ifne -> 260
    //   255: dup2
    //   256: dup_x1
    //   257: goto -> 166
    //   260: dup2_x1
    //   261: pop2
    //   262: dup_x2
    //   263: iload #6
    //   265: if_icmpgt -> 162
    //   268: pop
    //   269: new java/lang/String
    //   272: dup_x1
    //   273: swap
    //   274: invokespecial <init> : ([C)V
    //   277: invokevirtual intern : ()Ljava/lang/String;
    //   280: swap
    //   281: pop
    //   282: swap
    //   283: tableswitch default -> 40, 0 -> 99
    //   300: new java/math/BigInteger
    //   303: dup
    //   304: iconst_1
    //   305: bipush #32
    //   307: newarray byte
    //   309: dup
    //   310: iconst_0
    //   311: bipush #56
    //   313: bastore
    //   314: dup
    //   315: iconst_1
    //   316: bipush #-73
    //   318: bastore
    //   319: dup
    //   320: iconst_2
    //   321: bipush #-120
    //   323: bastore
    //   324: dup
    //   325: iconst_3
    //   326: bipush #-127
    //   328: bastore
    //   329: dup
    //   330: iconst_4
    //   331: bipush #122
    //   333: bastore
    //   334: dup
    //   335: iconst_5
    //   336: bipush #29
    //   338: bastore
    //   339: dup
    //   340: bipush #6
    //   342: bipush #-45
    //   344: bastore
    //   345: dup
    //   346: bipush #7
    //   348: bipush #-65
    //   350: bastore
    //   351: dup
    //   352: bipush #8
    //   354: bipush #28
    //   356: bastore
    //   357: dup
    //   358: bipush #9
    //   360: bipush #107
    //   362: bastore
    //   363: dup
    //   364: bipush #10
    //   366: bipush #118
    //   368: bastore
    //   369: dup
    //   370: bipush #11
    //   372: bipush #62
    //   374: bastore
    //   375: dup
    //   376: bipush #12
    //   378: bipush #-83
    //   380: bastore
    //   381: dup
    //   382: bipush #13
    //   384: bipush #-110
    //   386: bastore
    //   387: dup
    //   388: bipush #14
    //   390: bipush #36
    //   392: bastore
    //   393: dup
    //   394: bipush #15
    //   396: bipush #49
    //   398: bastore
    //   399: dup
    //   400: bipush #16
    //   402: bipush #73
    //   404: bastore
    //   405: dup
    //   406: bipush #17
    //   408: bipush #-128
    //   410: bastore
    //   411: dup
    //   412: bipush #18
    //   414: bipush #80
    //   416: bastore
    //   417: dup
    //   418: bipush #19
    //   420: bipush #91
    //   422: bastore
    //   423: dup
    //   424: bipush #20
    //   426: bipush #-109
    //   428: bastore
    //   429: dup
    //   430: bipush #21
    //   432: bipush #65
    //   434: bastore
    //   435: dup
    //   436: bipush #22
    //   438: bipush #113
    //   440: bastore
    //   441: dup
    //   442: bipush #23
    //   444: bipush #83
    //   446: bastore
    //   447: dup
    //   448: bipush #24
    //   450: bipush #-61
    //   452: bastore
    //   453: dup
    //   454: bipush #25
    //   456: bipush #58
    //   458: bastore
    //   459: dup
    //   460: bipush #26
    //   462: bipush #-107
    //   464: bastore
    //   465: dup
    //   466: bipush #27
    //   468: bipush #-10
    //   470: bastore
    //   471: dup
    //   472: bipush #28
    //   474: bipush #64
    //   476: bastore
    //   477: dup
    //   478: bipush #29
    //   480: bipush #75
    //   482: bastore
    //   483: dup
    //   484: bipush #30
    //   486: bipush #-115
    //   488: bastore
    //   489: dup
    //   490: bipush #31
    //   492: bipush #74
    //   494: bastore
    //   495: invokespecial <init> : (I[B)V
    //   498: putstatic burp/Zl8f.ZA : Ljava/lang/Object;
    //   501: sipush #22071
    //   504: sipush #-20661
    //   507: invokestatic a : (II)Ljava/lang/String;
    //   510: putstatic burp/Zl8f.ZK : Ljava/lang/String;
    //   513: return
  }
  
  private static Throwable a(Throwable paramThrowable) {
    return paramThrowable;
  }
  
  private static String a(int paramInt1, int paramInt2) {
    int i = (paramInt1 ^ 0x5632) & 0xFFFF;
    if (b[i] == null) {
      char[] arrayOfChar = a[i].toCharArray();
      switch (arrayOfChar[0] & 0xFF) {
        case 0:
        
        case 1:
        
        case 2:
        
        case 3:
        
        case 4:
        
        case 5:
        
        case 6:
        
        case 7:
        
        case 8:
        
        case 9:
        
        case 10:
        
        case 11:
        
        case 12:
        
        case 13:
        
        case 14:
        
        case 15:
        
        case 16:
        
        case 17:
        
        case 18:
        
        case 19:
        
        case 20:
        
        case 21:
        
        case 22:
        
        case 23:
        
        case 24:
        
        case 25:
        
        case 26:
        
        case 27:
        
        case 28:
        
        case 29:
        
        case 30:
        
        case 31:
        
        case 32:
        
        case 33:
        
        case 34:
        
        case 35:
        
        case 36:
        
        case 37:
        
        case 38:
        
        case 39:
        
        case 40:
        
        case 41:
        
        case 42:
        
        case 43:
        
        case 44:
        
        case 45:
        
        case 46:
        
        case 47:
        
        case 48:
        
        case 49:
        
        case 50:
        
        case 51:
        
        case 52:
        
        case 53:
        
        case 54:
        
        case 55:
        
        case 56:
        
        case 57:
        
        case 58:
        
        case 59:
        
        case 60:
        
        case 61:
        
        case 62:
        
        case 63:
        
        case 64:
        
        case 65:
        
        case 66:
        
        case 67:
        
        case 68:
        
        case 69:
        
        case 70:
        
        case 71:
        
        case 72:
        
        case 73:
        
        case 74:
        
        case 75:
        
        case 76:
        
        case 77:
        
        case 78:
        
        case 79:
        
        case 80:
        
        case 81:
        
        case 82:
        
        case 83:
        
        case 84:
        
        case 85:
        
        case 86:
        
        case 87:
        
        case 88:
        
        case 89:
        
        case 90:
        
        case 91:
        
        case 92:
        
        case 93:
        
        case 94:
        
        case 95:
        
        case 96:
        
        case 97:
        
        case 98:
        
        case 99:
        
        case 100:
        
        case 101:
        
        case 102:
        
        case 103:
        
        case 104:
        
        case 105:
        
        case 106:
        
        case 107:
        
        case 108:
        
        case 109:
        
        case 110:
        
        case 111:
        
        case 112:
        
        case 113:
        
        case 114:
        
        case 115:
        
        case 116:
        
        case 117:
        
        case 118:
        
        case 119:
        
        case 120:
        
        case 121:
        
        case 122:
        
        case 123:
        
        case 124:
        
        case 125:
        
        case 126:
        
        case 127:
        
        case 128:
        
        case 129:
        
        case 130:
        
        case 131:
        
        case 132:
        
        case 133:
        
        case 134:
        
        case 135:
        
        case 136:
        
        case 137:
        
        case 138:
        
        case 139:
        
        case 140:
        
        case 141:
        
        case 142:
        
        case 143:
        
        case 144:
        
        case 145:
        
        case 146:
        
        case 147:
        
        case 148:
        
        case 149:
        
        case 150:
        
        case 151:
        
        case 152:
        
        case 153:
        
        case 154:
        
        case 155:
        
        case 156:
        
        case 157:
        
        case 158:
        
        case 159:
        
        case 160:
        
        case 161:
        
        case 162:
        
        case 163:
        
        case 164:
        
        case 165:
        
        case 166:
        
        case 167:
        
        case 168:
        
        case 169:
        
        case 170:
        
        case 171:
        
        case 172:
        
        case 173:
        
        case 174:
        
        case 175:
        
        case 176:
        
        case 177:
        
        case 178:
        
        case 179:
        
        case 180:
        
        case 181:
        
        case 182:
        
        case 183:
        
        case 184:
        
        case 185:
        
        case 186:
        
        case 187:
        
        case 188:
        
        case 189:
        
        case 190:
        
        case 191:
        
        case 192:
        
        case 193:
        
        case 194:
        
        case 195:
        
        case 196:
        
        case 197:
        
        case 198:
        
        case 199:
        
        case 200:
        
        case 201:
        
        case 202:
        
        case 203:
        
        case 204:
        
        case 205:
        
        case 206:
        
        case 207:
        
        case 208:
        
        case 209:
        
        case 210:
        
        case 211:
        
        case 212:
        
        case 213:
        
        case 214:
        
        case 215:
        
        case 216:
        
        case 217:
        
        case 218:
        
        case 219:
        
        case 220:
        
        case 221:
        
        case 222:
        
        case 223:
        
        case 224:
        
        case 225:
        
        case 226:
        
        case 227:
        
        case 228:
        
        case 229:
        
        case 230:
        
        case 231:
        
        case 232:
        
        case 233:
        
        case 234:
        
        case 235:
        
        case 236:
        
        case 237:
        
        case 238:
        
        case 239:
        
        case 240:
        
        case 241:
        
        case 242:
        
        case 243:
        
        case 244:
        
        case 245:
        
        case 246:
        
        case 247:
        
        case 248:
        
        case 249:
        
        case 250:
        
        case 251:
        
        case 252:
        
        case 253:
        
        case 254:
        
        default:
          break;
      } 
      byte b1 = 7;
      int j = (paramInt2 & 0xFF) - b1;
      if (j < 0)
        j += 256; 
      int k = ((paramInt2 & 0xFFFF) >>> 8) - b1;
      if (k < 0)
        k += 256; 
      for (byte b2 = 0; b2 < arrayOfChar.length; b2++) {
        int m = b2 % 2;
        if (m == 0) {
          arrayOfChar[b2] = (char)(arrayOfChar[b2] ^ j);
          j = ((j >>> 3 | j << 5) ^ arrayOfChar[b2]) & 0xFF;
        } else {
          arrayOfChar[b2] = (char)(arrayOfChar[b2] ^ k);
          k = ((k >>> 3 | k << 5) ^ arrayOfChar[b2]) & 0xFF;
        } 
      } 
      b[i] = (new String(arrayOfChar)).intern();
    } 
    return b[i];
  }
}


/* Location:              C:\Program Files\BurpSuitePro\burpsuite_pro.jar!\burp\Zl8f.class
 * Java compiler version: 21 (65.0)
 * JD-Core Version:       1.1.3
 */