package burp;

import java.math.BigInteger;

class Zl_u extends ClassLoader {
  static Object ZR;
  
  static String Zc;
  
  private static final String[] a;
  
  private static final String[] b;
  
  static void ZY(Object[] paramArrayOfObject, Object paramObject) throws Throwable {}
  
  static boolean Za(Object[] paramArrayOfObject, Object paramObject) throws Throwable {
    // Byte code:
    //   0: invokestatic ZK : ()Z
    //   3: istore_2
    //   4: getstatic burp/Zter.Zc : Ljava/lang/Object;
    //   7: checkcast java/math/BigInteger
    //   10: invokevirtual toByteArray : ()[B
    //   13: astore_3
    //   14: iconst_0
    //   15: istore #5
    //   17: iconst_0
    //   18: istore #6
    //   20: iload #6
    //   22: aload_3
    //   23: arraylength
    //   24: if_icmpge -> 169
    //   27: aload_3
    //   28: iload #6
    //   30: baload
    //   31: istore #7
    //   33: iload #7
    //   35: bipush #48
    //   37: if_icmplt -> 54
    //   40: iload #7
    //   42: bipush #57
    //   44: if_icmple -> 152
    //   47: goto -> 54
    //   50: invokestatic a : (Ljava/lang/Throwable;)Ljava/lang/Throwable;
    //   53: athrow
    //   54: iload #7
    //   56: bipush #65
    //   58: if_icmplt -> 82
    //   61: goto -> 68
    //   64: invokestatic a : (Ljava/lang/Throwable;)Ljava/lang/Throwable;
    //   67: athrow
    //   68: iload #7
    //   70: bipush #90
    //   72: if_icmple -> 152
    //   75: goto -> 82
    //   78: invokestatic a : (Ljava/lang/Throwable;)Ljava/lang/Throwable;
    //   81: athrow
    //   82: iload #7
    //   84: bipush #97
    //   86: if_icmplt -> 110
    //   89: goto -> 96
    //   92: invokestatic a : (Ljava/lang/Throwable;)Ljava/lang/Throwable;
    //   95: athrow
    //   96: iload #7
    //   98: bipush #122
    //   100: if_icmple -> 152
    //   103: goto -> 110
    //   106: invokestatic a : (Ljava/lang/Throwable;)Ljava/lang/Throwable;
    //   109: athrow
    //   110: iload #7
    //   112: bipush #43
    //   114: if_icmpeq -> 152
    //   117: goto -> 124
    //   120: invokestatic a : (Ljava/lang/Throwable;)Ljava/lang/Throwable;
    //   123: athrow
    //   124: iload #7
    //   126: bipush #47
    //   128: if_icmpeq -> 152
    //   131: goto -> 138
    //   134: invokestatic a : (Ljava/lang/Throwable;)Ljava/lang/Throwable;
    //   137: athrow
    //   138: iload #7
    //   140: bipush #61
    //   142: if_icmpne -> 162
    //   145: goto -> 152
    //   148: invokestatic a : (Ljava/lang/Throwable;)Ljava/lang/Throwable;
    //   151: athrow
    //   152: iinc #5, 1
    //   155: goto -> 162
    //   158: invokestatic a : (Ljava/lang/Throwable;)Ljava/lang/Throwable;
    //   161: athrow
    //   162: iinc #6, 1
    //   165: iload_2
    //   166: ifeq -> 20
    //   169: iload #5
    //   171: newarray byte
    //   173: astore #6
    //   175: iconst_0
    //   176: istore #7
    //   178: iconst_0
    //   179: istore #8
    //   181: iload #8
    //   183: aload_3
    //   184: arraylength
    //   185: if_icmpge -> 337
    //   188: aload_3
    //   189: iload #8
    //   191: baload
    //   192: istore #9
    //   194: iload #9
    //   196: bipush #48
    //   198: if_icmplt -> 215
    //   201: iload #9
    //   203: bipush #57
    //   205: if_icmple -> 313
    //   208: goto -> 215
    //   211: invokestatic a : (Ljava/lang/Throwable;)Ljava/lang/Throwable;
    //   214: athrow
    //   215: iload #9
    //   217: bipush #65
    //   219: if_icmplt -> 243
    //   222: goto -> 229
    //   225: invokestatic a : (Ljava/lang/Throwable;)Ljava/lang/Throwable;
    //   228: athrow
    //   229: iload #9
    //   231: bipush #90
    //   233: if_icmple -> 313
    //   236: goto -> 243
    //   239: invokestatic a : (Ljava/lang/Throwable;)Ljava/lang/Throwable;
    //   242: athrow
    //   243: iload #9
    //   245: bipush #97
    //   247: if_icmplt -> 271
    //   250: goto -> 257
    //   253: invokestatic a : (Ljava/lang/Throwable;)Ljava/lang/Throwable;
    //   256: athrow
    //   257: iload #9
    //   259: bipush #122
    //   261: if_icmple -> 313
    //   264: goto -> 271
    //   267: invokestatic a : (Ljava/lang/Throwable;)Ljava/lang/Throwable;
    //   270: athrow
    //   271: iload #9
    //   273: bipush #43
    //   275: if_icmpeq -> 313
    //   278: goto -> 285
    //   281: invokestatic a : (Ljava/lang/Throwable;)Ljava/lang/Throwable;
    //   284: athrow
    //   285: iload #9
    //   287: bipush #47
    //   289: if_icmpeq -> 313
    //   292: goto -> 299
    //   295: invokestatic a : (Ljava/lang/Throwable;)Ljava/lang/Throwable;
    //   298: athrow
    //   299: iload #9
    //   301: bipush #61
    //   303: if_icmpne -> 330
    //   306: goto -> 313
    //   309: invokestatic a : (Ljava/lang/Throwable;)Ljava/lang/Throwable;
    //   312: athrow
    //   313: aload #6
    //   315: iload #7
    //   317: iload #9
    //   319: bastore
    //   320: iinc #7, 1
    //   323: goto -> 330
    //   326: invokestatic a : (Ljava/lang/Throwable;)Ljava/lang/Throwable;
    //   329: athrow
    //   330: iinc #8, 1
    //   333: iload_2
    //   334: ifeq -> 181
    //   337: aload #6
    //   339: astore #4
    //   341: aload #4
    //   343: astore_3
    //   344: aload_3
    //   345: arraylength
    //   346: istore #5
    //   348: aload_3
    //   349: iload #5
    //   351: iconst_1
    //   352: isub
    //   353: baload
    //   354: bipush #61
    //   356: if_icmpne -> 366
    //   359: iinc #5, -1
    //   362: iload_2
    //   363: ifeq -> 348
    //   366: iload #5
    //   368: aload_3
    //   369: arraylength
    //   370: iconst_4
    //   371: idiv
    //   372: isub
    //   373: newarray byte
    //   375: astore #6
    //   377: iconst_0
    //   378: istore #7
    //   380: iload #7
    //   382: aload_3
    //   383: arraylength
    //   384: if_icmpge -> 646
    //   387: aload_3
    //   388: iload #7
    //   390: baload
    //   391: bipush #61
    //   393: if_icmpne -> 412
    //   396: aload_3
    //   397: iload #7
    //   399: iconst_0
    //   400: bastore
    //   401: iload_2
    //   402: ifeq -> 639
    //   405: goto -> 412
    //   408: invokestatic a : (Ljava/lang/Throwable;)Ljava/lang/Throwable;
    //   411: athrow
    //   412: aload_3
    //   413: iload #7
    //   415: baload
    //   416: bipush #47
    //   418: if_icmpne -> 445
    //   421: goto -> 428
    //   424: invokestatic a : (Ljava/lang/Throwable;)Ljava/lang/Throwable;
    //   427: athrow
    //   428: aload_3
    //   429: iload #7
    //   431: bipush #63
    //   433: bastore
    //   434: iload_2
    //   435: ifeq -> 639
    //   438: goto -> 445
    //   441: invokestatic a : (Ljava/lang/Throwable;)Ljava/lang/Throwable;
    //   444: athrow
    //   445: aload_3
    //   446: iload #7
    //   448: baload
    //   449: bipush #43
    //   451: if_icmpne -> 478
    //   454: goto -> 461
    //   457: invokestatic a : (Ljava/lang/Throwable;)Ljava/lang/Throwable;
    //   460: athrow
    //   461: aload_3
    //   462: iload #7
    //   464: bipush #62
    //   466: bastore
    //   467: iload_2
    //   468: ifeq -> 639
    //   471: goto -> 478
    //   474: invokestatic a : (Ljava/lang/Throwable;)Ljava/lang/Throwable;
    //   477: athrow
    //   478: aload_3
    //   479: iload #7
    //   481: baload
    //   482: bipush #48
    //   484: if_icmplt -> 533
    //   487: goto -> 494
    //   490: invokestatic a : (Ljava/lang/Throwable;)Ljava/lang/Throwable;
    //   493: athrow
    //   494: aload_3
    //   495: iload #7
    //   497: baload
    //   498: bipush #57
    //   500: if_icmpgt -> 533
    //   503: goto -> 510
    //   506: invokestatic a : (Ljava/lang/Throwable;)Ljava/lang/Throwable;
    //   509: athrow
    //   510: aload_3
    //   511: iload #7
    //   513: aload_3
    //   514: iload #7
    //   516: baload
    //   517: bipush #-4
    //   519: isub
    //   520: i2b
    //   521: bastore
    //   522: iload_2
    //   523: ifeq -> 639
    //   526: goto -> 533
    //   529: invokestatic a : (Ljava/lang/Throwable;)Ljava/lang/Throwable;
    //   532: athrow
    //   533: aload_3
    //   534: iload #7
    //   536: baload
    //   537: bipush #97
    //   539: if_icmplt -> 588
    //   542: goto -> 549
    //   545: invokestatic a : (Ljava/lang/Throwable;)Ljava/lang/Throwable;
    //   548: athrow
    //   549: aload_3
    //   550: iload #7
    //   552: baload
    //   553: bipush #122
    //   555: if_icmpgt -> 588
    //   558: goto -> 565
    //   561: invokestatic a : (Ljava/lang/Throwable;)Ljava/lang/Throwable;
    //   564: athrow
    //   565: aload_3
    //   566: iload #7
    //   568: aload_3
    //   569: iload #7
    //   571: baload
    //   572: bipush #71
    //   574: isub
    //   575: i2b
    //   576: bastore
    //   577: iload_2
    //   578: ifeq -> 639
    //   581: goto -> 588
    //   584: invokestatic a : (Ljava/lang/Throwable;)Ljava/lang/Throwable;
    //   587: athrow
    //   588: aload_3
    //   589: iload #7
    //   591: baload
    //   592: bipush #65
    //   594: if_icmplt -> 639
    //   597: goto -> 604
    //   600: invokestatic a : (Ljava/lang/Throwable;)Ljava/lang/Throwable;
    //   603: athrow
    //   604: aload_3
    //   605: iload #7
    //   607: baload
    //   608: bipush #90
    //   610: if_icmpgt -> 639
    //   613: goto -> 620
    //   616: invokestatic a : (Ljava/lang/Throwable;)Ljava/lang/Throwable;
    //   619: athrow
    //   620: aload_3
    //   621: iload #7
    //   623: aload_3
    //   624: iload #7
    //   626: baload
    //   627: bipush #65
    //   629: isub
    //   630: i2b
    //   631: bastore
    //   632: goto -> 639
    //   635: invokestatic a : (Ljava/lang/Throwable;)Ljava/lang/Throwable;
    //   638: athrow
    //   639: iinc #7, 1
    //   642: iload_2
    //   643: ifeq -> 380
    //   646: iconst_0
    //   647: istore #7
    //   649: iconst_0
    //   650: istore #8
    //   652: iload #8
    //   654: aload #6
    //   656: arraylength
    //   657: iconst_2
    //   658: isub
    //   659: if_icmpge -> 762
    //   662: aload #6
    //   664: iload #8
    //   666: aload_3
    //   667: iload #7
    //   669: baload
    //   670: iconst_2
    //   671: ishl
    //   672: sipush #255
    //   675: iand
    //   676: aload_3
    //   677: iload #7
    //   679: iconst_1
    //   680: iadd
    //   681: baload
    //   682: iconst_4
    //   683: iushr
    //   684: iconst_3
    //   685: iand
    //   686: ior
    //   687: i2b
    //   688: bastore
    //   689: aload #6
    //   691: iload #8
    //   693: iconst_1
    //   694: iadd
    //   695: aload_3
    //   696: iload #7
    //   698: iconst_1
    //   699: iadd
    //   700: baload
    //   701: iconst_4
    //   702: ishl
    //   703: sipush #255
    //   706: iand
    //   707: aload_3
    //   708: iload #7
    //   710: iconst_2
    //   711: iadd
    //   712: baload
    //   713: iconst_2
    //   714: iushr
    //   715: bipush #15
    //   717: iand
    //   718: ior
    //   719: i2b
    //   720: bastore
    //   721: aload #6
    //   723: iload #8
    //   725: iconst_2
    //   726: iadd
    //   727: aload_3
    //   728: iload #7
    //   730: iconst_2
    //   731: iadd
    //   732: baload
    //   733: bipush #6
    //   735: ishl
    //   736: sipush #255
    //   739: iand
    //   740: aload_3
    //   741: iload #7
    //   743: iconst_3
    //   744: iadd
    //   745: baload
    //   746: bipush #63
    //   748: iand
    //   749: ior
    //   750: i2b
    //   751: bastore
    //   752: iinc #7, 4
    //   755: iinc #8, 3
    //   758: iload_2
    //   759: ifeq -> 652
    //   762: iload #8
    //   764: aload #6
    //   766: arraylength
    //   767: if_icmpge -> 804
    //   770: aload #6
    //   772: iload #8
    //   774: aload_3
    //   775: iload #7
    //   777: baload
    //   778: iconst_2
    //   779: ishl
    //   780: sipush #255
    //   783: iand
    //   784: aload_3
    //   785: iload #7
    //   787: iconst_1
    //   788: iadd
    //   789: baload
    //   790: iconst_4
    //   791: iushr
    //   792: iconst_3
    //   793: iand
    //   794: ior
    //   795: i2b
    //   796: bastore
    //   797: goto -> 804
    //   800: invokestatic a : (Ljava/lang/Throwable;)Ljava/lang/Throwable;
    //   803: athrow
    //   804: iinc #8, 1
    //   807: iload #8
    //   809: aload #6
    //   811: arraylength
    //   812: if_icmpge -> 852
    //   815: aload #6
    //   817: iload #8
    //   819: aload_3
    //   820: iload #7
    //   822: iconst_1
    //   823: iadd
    //   824: baload
    //   825: iconst_4
    //   826: ishl
    //   827: sipush #255
    //   830: iand
    //   831: aload_3
    //   832: iload #7
    //   834: iconst_2
    //   835: iadd
    //   836: baload
    //   837: iconst_2
    //   838: iushr
    //   839: bipush #15
    //   841: iand
    //   842: ior
    //   843: i2b
    //   844: bastore
    //   845: goto -> 852
    //   848: invokestatic a : (Ljava/lang/Throwable;)Ljava/lang/Throwable;
    //   851: athrow
    //   852: aload #6
    //   854: astore #4
    //   856: new java/math/BigInteger
    //   859: dup
    //   860: aload #4
    //   862: invokespecial <init> : ([B)V
    //   865: invokevirtual abs : ()Ljava/math/BigInteger;
    //   868: putstatic burp/Zt4g.Zv : Ljava/lang/Object;
    //   871: new java/lang/StringBuilder
    //   874: dup
    //   875: invokespecial <init> : ()V
    //   878: astore_3
    //   879: iconst_0
    //   880: istore #4
    //   882: iload #4
    //   884: bipush #32
    //   886: if_icmpge -> 2219
    //   889: iload #4
    //   891: tableswitch default -> 2212, 0 -> 1032, 1 -> 1069, 2 -> 1106, 3 -> 1143, 4 -> 1180, 5 -> 1217, 6 -> 1254, 7 -> 1291, 8 -> 1328, 9 -> 1365, 10 -> 1402, 11 -> 1439, 12 -> 1476, 13 -> 1513, 14 -> 1550, 15 -> 1587, 16 -> 1624, 17 -> 1661, 18 -> 1698, 19 -> 1735, 20 -> 1772, 21 -> 1809, 22 -> 1846, 23 -> 1883, 24 -> 1920, 25 -> 1957, 26 -> 1994, 27 -> 2031, 28 -> 2068, 29 -> 2105, 30 -> 2142, 31 -> 2179
    //   1032: aload_3
    //   1033: getstatic burp/Zsxj.Zp : Ljava/lang/String;
    //   1036: getstatic burp/Zg99.ZZ : Ljava/lang/Object;
    //   1039: checkcast java/math/BigInteger
    //   1042: invokevirtual intValue : ()I
    //   1045: bipush #32
    //   1047: irem
    //   1048: invokestatic abs : (I)I
    //   1051: invokevirtual charAt : (I)C
    //   1054: invokevirtual append : (C)Ljava/lang/StringBuilder;
    //   1057: pop
    //   1058: iload_2
    //   1059: ifeq -> 2212
    //   1062: goto -> 1069
    //   1065: invokestatic a : (Ljava/lang/Throwable;)Ljava/lang/Throwable;
    //   1068: athrow
    //   1069: aload_3
    //   1070: getstatic burp/Zr3q.ZM : Ljava/lang/String;
    //   1073: getstatic burp/Zxl5.Zh : Ljava/lang/Object;
    //   1076: checkcast java/math/BigInteger
    //   1079: invokevirtual intValue : ()I
    //   1082: bipush #32
    //   1084: irem
    //   1085: invokestatic abs : (I)I
    //   1088: invokevirtual charAt : (I)C
    //   1091: invokevirtual append : (C)Ljava/lang/StringBuilder;
    //   1094: pop
    //   1095: iload_2
    //   1096: ifeq -> 2212
    //   1099: goto -> 1106
    //   1102: invokestatic a : (Ljava/lang/Throwable;)Ljava/lang/Throwable;
    //   1105: athrow
    //   1106: aload_3
    //   1107: getstatic burp/Zl_k.Zw : Ljava/lang/String;
    //   1110: getstatic burp/Zzqj.Zq : Ljava/lang/Object;
    //   1113: checkcast java/math/BigInteger
    //   1116: invokevirtual intValue : ()I
    //   1119: bipush #32
    //   1121: irem
    //   1122: invokestatic abs : (I)I
    //   1125: invokevirtual charAt : (I)C
    //   1128: invokevirtual append : (C)Ljava/lang/StringBuilder;
    //   1131: pop
    //   1132: iload_2
    //   1133: ifeq -> 2212
    //   1136: goto -> 1143
    //   1139: invokestatic a : (Ljava/lang/Throwable;)Ljava/lang/Throwable;
    //   1142: athrow
    //   1143: aload_3
    //   1144: getstatic burp/Zmj4.ZM : Ljava/lang/String;
    //   1147: getstatic burp/Zx4l.Zt : Ljava/lang/Object;
    //   1150: checkcast java/math/BigInteger
    //   1153: invokevirtual intValue : ()I
    //   1156: bipush #32
    //   1158: irem
    //   1159: invokestatic abs : (I)I
    //   1162: invokevirtual charAt : (I)C
    //   1165: invokevirtual append : (C)Ljava/lang/StringBuilder;
    //   1168: pop
    //   1169: iload_2
    //   1170: ifeq -> 2212
    //   1173: goto -> 1180
    //   1176: invokestatic a : (Ljava/lang/Throwable;)Ljava/lang/Throwable;
    //   1179: athrow
    //   1180: aload_3
    //   1181: getstatic burp/Zxfu.Zo : Ljava/lang/String;
    //   1184: getstatic burp/Zlhm.ZT : Ljava/lang/Object;
    //   1187: checkcast java/math/BigInteger
    //   1190: invokevirtual intValue : ()I
    //   1193: bipush #32
    //   1195: irem
    //   1196: invokestatic abs : (I)I
    //   1199: invokevirtual charAt : (I)C
    //   1202: invokevirtual append : (C)Ljava/lang/StringBuilder;
    //   1205: pop
    //   1206: iload_2
    //   1207: ifeq -> 2212
    //   1210: goto -> 1217
    //   1213: invokestatic a : (Ljava/lang/Throwable;)Ljava/lang/Throwable;
    //   1216: athrow
    //   1217: aload_3
    //   1218: getstatic burp/Zkfz.Zs : Ljava/lang/String;
    //   1221: getstatic burp/Zsgl.Zn : Ljava/lang/Object;
    //   1224: checkcast java/math/BigInteger
    //   1227: invokevirtual intValue : ()I
    //   1230: bipush #32
    //   1232: irem
    //   1233: invokestatic abs : (I)I
    //   1236: invokevirtual charAt : (I)C
    //   1239: invokevirtual append : (C)Ljava/lang/StringBuilder;
    //   1242: pop
    //   1243: iload_2
    //   1244: ifeq -> 2212
    //   1247: goto -> 1254
    //   1250: invokestatic a : (Ljava/lang/Throwable;)Ljava/lang/Throwable;
    //   1253: athrow
    //   1254: aload_3
    //   1255: getstatic burp/Zrdy.ZO : Ljava/lang/String;
    //   1258: getstatic burp/Zzk9.ZK : Ljava/lang/Object;
    //   1261: checkcast java/math/BigInteger
    //   1264: invokevirtual intValue : ()I
    //   1267: bipush #32
    //   1269: irem
    //   1270: invokestatic abs : (I)I
    //   1273: invokevirtual charAt : (I)C
    //   1276: invokevirtual append : (C)Ljava/lang/StringBuilder;
    //   1279: pop
    //   1280: iload_2
    //   1281: ifeq -> 2212
    //   1284: goto -> 1291
    //   1287: invokestatic a : (Ljava/lang/Throwable;)Ljava/lang/Throwable;
    //   1290: athrow
    //   1291: aload_3
    //   1292: getstatic burp/Zk8b.ZT : Ljava/lang/String;
    //   1295: getstatic burp/Zkfz.Zr : Ljava/lang/Object;
    //   1298: checkcast java/math/BigInteger
    //   1301: invokevirtual intValue : ()I
    //   1304: bipush #32
    //   1306: irem
    //   1307: invokestatic abs : (I)I
    //   1310: invokevirtual charAt : (I)C
    //   1313: invokevirtual append : (C)Ljava/lang/StringBuilder;
    //   1316: pop
    //   1317: iload_2
    //   1318: ifeq -> 2212
    //   1321: goto -> 1328
    //   1324: invokestatic a : (Ljava/lang/Throwable;)Ljava/lang/Throwable;
    //   1327: athrow
    //   1328: aload_3
    //   1329: getstatic burp/Ze7q.ZW : Ljava/lang/String;
    //   1332: getstatic burp/Zkmx.Zu : Ljava/lang/Object;
    //   1335: checkcast java/math/BigInteger
    //   1338: invokevirtual intValue : ()I
    //   1341: bipush #32
    //   1343: irem
    //   1344: invokestatic abs : (I)I
    //   1347: invokevirtual charAt : (I)C
    //   1350: invokevirtual append : (C)Ljava/lang/StringBuilder;
    //   1353: pop
    //   1354: iload_2
    //   1355: ifeq -> 2212
    //   1358: goto -> 1365
    //   1361: invokestatic a : (Ljava/lang/Throwable;)Ljava/lang/Throwable;
    //   1364: athrow
    //   1365: aload_3
    //   1366: getstatic burp/Zg7p.ZA : Ljava/lang/String;
    //   1369: getstatic burp/Zzqj.Zq : Ljava/lang/Object;
    //   1372: checkcast java/math/BigInteger
    //   1375: invokevirtual intValue : ()I
    //   1378: bipush #32
    //   1380: irem
    //   1381: invokestatic abs : (I)I
    //   1384: invokevirtual charAt : (I)C
    //   1387: invokevirtual append : (C)Ljava/lang/StringBuilder;
    //   1390: pop
    //   1391: iload_2
    //   1392: ifeq -> 2212
    //   1395: goto -> 1402
    //   1398: invokestatic a : (Ljava/lang/Throwable;)Ljava/lang/Throwable;
    //   1401: athrow
    //   1402: aload_3
    //   1403: getstatic burp/Zr8h.Zk : Ljava/lang/String;
    //   1406: getstatic burp/Zxzd.ZD : Ljava/lang/Object;
    //   1409: checkcast java/math/BigInteger
    //   1412: invokevirtual intValue : ()I
    //   1415: bipush #32
    //   1417: irem
    //   1418: invokestatic abs : (I)I
    //   1421: invokevirtual charAt : (I)C
    //   1424: invokevirtual append : (C)Ljava/lang/StringBuilder;
    //   1427: pop
    //   1428: iload_2
    //   1429: ifeq -> 2212
    //   1432: goto -> 1439
    //   1435: invokestatic a : (Ljava/lang/Throwable;)Ljava/lang/Throwable;
    //   1438: athrow
    //   1439: aload_3
    //   1440: getstatic burp/Zzai.Zy : Ljava/lang/String;
    //   1443: getstatic burp/Zeh9.ZY : Ljava/lang/Object;
    //   1446: checkcast java/math/BigInteger
    //   1449: invokevirtual intValue : ()I
    //   1452: bipush #32
    //   1454: irem
    //   1455: invokestatic abs : (I)I
    //   1458: invokevirtual charAt : (I)C
    //   1461: invokevirtual append : (C)Ljava/lang/StringBuilder;
    //   1464: pop
    //   1465: iload_2
    //   1466: ifeq -> 2212
    //   1469: goto -> 1476
    //   1472: invokestatic a : (Ljava/lang/Throwable;)Ljava/lang/Throwable;
    //   1475: athrow
    //   1476: aload_3
    //   1477: getstatic burp/Zl2g.ZI : Ljava/lang/String;
    //   1480: getstatic burp/Zb3z.ZR : Ljava/lang/Object;
    //   1483: checkcast java/math/BigInteger
    //   1486: invokevirtual intValue : ()I
    //   1489: bipush #32
    //   1491: irem
    //   1492: invokestatic abs : (I)I
    //   1495: invokevirtual charAt : (I)C
    //   1498: invokevirtual append : (C)Ljava/lang/StringBuilder;
    //   1501: pop
    //   1502: iload_2
    //   1503: ifeq -> 2212
    //   1506: goto -> 1513
    //   1509: invokestatic a : (Ljava/lang/Throwable;)Ljava/lang/Throwable;
    //   1512: athrow
    //   1513: aload_3
    //   1514: getstatic burp/Zl88.Zd : Ljava/lang/String;
    //   1517: getstatic burp/Zeh9.ZY : Ljava/lang/Object;
    //   1520: checkcast java/math/BigInteger
    //   1523: invokevirtual intValue : ()I
    //   1526: bipush #32
    //   1528: irem
    //   1529: invokestatic abs : (I)I
    //   1532: invokevirtual charAt : (I)C
    //   1535: invokevirtual append : (C)Ljava/lang/StringBuilder;
    //   1538: pop
    //   1539: iload_2
    //   1540: ifeq -> 2212
    //   1543: goto -> 1550
    //   1546: invokestatic a : (Ljava/lang/Throwable;)Ljava/lang/Throwable;
    //   1549: athrow
    //   1550: aload_3
    //   1551: getstatic burp/Ze7q.ZW : Ljava/lang/String;
    //   1554: getstatic burp/Zzai.Z_ : Ljava/lang/Object;
    //   1557: checkcast java/math/BigInteger
    //   1560: invokevirtual intValue : ()I
    //   1563: bipush #32
    //   1565: irem
    //   1566: invokestatic abs : (I)I
    //   1569: invokevirtual charAt : (I)C
    //   1572: invokevirtual append : (C)Ljava/lang/StringBuilder;
    //   1575: pop
    //   1576: iload_2
    //   1577: ifeq -> 2212
    //   1580: goto -> 1587
    //   1583: invokestatic a : (Ljava/lang/Throwable;)Ljava/lang/Throwable;
    //   1586: athrow
    //   1587: aload_3
    //   1588: getstatic burp/Zter.ZE : Ljava/lang/String;
    //   1591: getstatic burp/Zes_.ZJ : Ljava/lang/Object;
    //   1594: checkcast java/math/BigInteger
    //   1597: invokevirtual intValue : ()I
    //   1600: bipush #32
    //   1602: irem
    //   1603: invokestatic abs : (I)I
    //   1606: invokevirtual charAt : (I)C
    //   1609: invokevirtual append : (C)Ljava/lang/StringBuilder;
    //   1612: pop
    //   1613: iload_2
    //   1614: ifeq -> 2212
    //   1617: goto -> 1624
    //   1620: invokestatic a : (Ljava/lang/Throwable;)Ljava/lang/Throwable;
    //   1623: athrow
    //   1624: aload_3
    //   1625: getstatic burp/Zllw.Zg : Ljava/lang/String;
    //   1628: getstatic burp/Zg99.ZZ : Ljava/lang/Object;
    //   1631: checkcast java/math/BigInteger
    //   1634: invokevirtual intValue : ()I
    //   1637: bipush #32
    //   1639: irem
    //   1640: invokestatic abs : (I)I
    //   1643: invokevirtual charAt : (I)C
    //   1646: invokevirtual append : (C)Ljava/lang/StringBuilder;
    //   1649: pop
    //   1650: iload_2
    //   1651: ifeq -> 2212
    //   1654: goto -> 1661
    //   1657: invokestatic a : (Ljava/lang/Throwable;)Ljava/lang/Throwable;
    //   1660: athrow
    //   1661: aload_3
    //   1662: getstatic burp/Zehi.Zi : Ljava/lang/String;
    //   1665: getstatic burp/Ztuj.Ze : Ljava/lang/Object;
    //   1668: checkcast java/math/BigInteger
    //   1671: invokevirtual intValue : ()I
    //   1674: bipush #32
    //   1676: irem
    //   1677: invokestatic abs : (I)I
    //   1680: invokevirtual charAt : (I)C
    //   1683: invokevirtual append : (C)Ljava/lang/StringBuilder;
    //   1686: pop
    //   1687: iload_2
    //   1688: ifeq -> 2212
    //   1691: goto -> 1698
    //   1694: invokestatic a : (Ljava/lang/Throwable;)Ljava/lang/Throwable;
    //   1697: athrow
    //   1698: aload_3
    //   1699: getstatic burp/Zm0s.Zm : Ljava/lang/String;
    //   1702: getstatic burp/Zedz.Za : Ljava/lang/Object;
    //   1705: checkcast java/math/BigInteger
    //   1708: invokevirtual intValue : ()I
    //   1711: bipush #32
    //   1713: irem
    //   1714: invokestatic abs : (I)I
    //   1717: invokevirtual charAt : (I)C
    //   1720: invokevirtual append : (C)Ljava/lang/StringBuilder;
    //   1723: pop
    //   1724: iload_2
    //   1725: ifeq -> 2212
    //   1728: goto -> 1735
    //   1731: invokestatic a : (Ljava/lang/Throwable;)Ljava/lang/Throwable;
    //   1734: athrow
    //   1735: aload_3
    //   1736: getstatic burp/Zkbf.Zv : Ljava/lang/String;
    //   1739: getstatic burp/Ze3d.Ze : Ljava/lang/Object;
    //   1742: checkcast java/math/BigInteger
    //   1745: invokevirtual intValue : ()I
    //   1748: bipush #32
    //   1750: irem
    //   1751: invokestatic abs : (I)I
    //   1754: invokevirtual charAt : (I)C
    //   1757: invokevirtual append : (C)Ljava/lang/StringBuilder;
    //   1760: pop
    //   1761: iload_2
    //   1762: ifeq -> 2212
    //   1765: goto -> 1772
    //   1768: invokestatic a : (Ljava/lang/Throwable;)Ljava/lang/Throwable;
    //   1771: athrow
    //   1772: aload_3
    //   1773: getstatic burp/Ze3d.ZL : Ljava/lang/String;
    //   1776: getstatic burp/Zsm3.ZC : Ljava/lang/Object;
    //   1779: checkcast java/math/BigInteger
    //   1782: invokevirtual intValue : ()I
    //   1785: bipush #32
    //   1787: irem
    //   1788: invokestatic abs : (I)I
    //   1791: invokevirtual charAt : (I)C
    //   1794: invokevirtual append : (C)Ljava/lang/StringBuilder;
    //   1797: pop
    //   1798: iload_2
    //   1799: ifeq -> 2212
    //   1802: goto -> 1809
    //   1805: invokestatic a : (Ljava/lang/Throwable;)Ljava/lang/Throwable;
    //   1808: athrow
    //   1809: aload_3
    //   1810: getstatic burp/Zzap.ZA : Ljava/lang/String;
    //   1813: getstatic burp/Zsxj.Zi : Ljava/lang/Object;
    //   1816: checkcast java/math/BigInteger
    //   1819: invokevirtual intValue : ()I
    //   1822: bipush #32
    //   1824: irem
    //   1825: invokestatic abs : (I)I
    //   1828: invokevirtual charAt : (I)C
    //   1831: invokevirtual append : (C)Ljava/lang/StringBuilder;
    //   1834: pop
    //   1835: iload_2
    //   1836: ifeq -> 2212
    //   1839: goto -> 1846
    //   1842: invokestatic a : (Ljava/lang/Throwable;)Ljava/lang/Throwable;
    //   1845: athrow
    //   1846: aload_3
    //   1847: getstatic burp/Zxzj.ZZ : Ljava/lang/String;
    //   1850: getstatic burp/Zxso.ZF : Ljava/lang/Object;
    //   1853: checkcast java/math/BigInteger
    //   1856: invokevirtual intValue : ()I
    //   1859: bipush #32
    //   1861: irem
    //   1862: invokestatic abs : (I)I
    //   1865: invokevirtual charAt : (I)C
    //   1868: invokevirtual append : (C)Ljava/lang/StringBuilder;
    //   1871: pop
    //   1872: iload_2
    //   1873: ifeq -> 2212
    //   1876: goto -> 1883
    //   1879: invokestatic a : (Ljava/lang/Throwable;)Ljava/lang/Throwable;
    //   1882: athrow
    //   1883: aload_3
    //   1884: getstatic burp/Zgw0.ZL : Ljava/lang/String;
    //   1887: getstatic burp/Zer.Zk : Ljava/lang/Object;
    //   1890: checkcast java/math/BigInteger
    //   1893: invokevirtual intValue : ()I
    //   1896: bipush #32
    //   1898: irem
    //   1899: invokestatic abs : (I)I
    //   1902: invokevirtual charAt : (I)C
    //   1905: invokevirtual append : (C)Ljava/lang/StringBuilder;
    //   1908: pop
    //   1909: iload_2
    //   1910: ifeq -> 2212
    //   1913: goto -> 1920
    //   1916: invokestatic a : (Ljava/lang/Throwable;)Ljava/lang/Throwable;
    //   1919: athrow
    //   1920: aload_3
    //   1921: getstatic burp/Zxzj.ZZ : Ljava/lang/String;
    //   1924: getstatic burp/Ztnw.Zt : Ljava/lang/Object;
    //   1927: checkcast java/math/BigInteger
    //   1930: invokevirtual intValue : ()I
    //   1933: bipush #32
    //   1935: irem
    //   1936: invokestatic abs : (I)I
    //   1939: invokevirtual charAt : (I)C
    //   1942: invokevirtual append : (C)Ljava/lang/StringBuilder;
    //   1945: pop
    //   1946: iload_2
    //   1947: ifeq -> 2212
    //   1950: goto -> 1957
    //   1953: invokestatic a : (Ljava/lang/Throwable;)Ljava/lang/Throwable;
    //   1956: athrow
    //   1957: aload_3
    //   1958: getstatic burp/Zt4g.Zj : Ljava/lang/String;
    //   1961: getstatic burp/Zm__.Zz : Ljava/lang/Object;
    //   1964: checkcast java/math/BigInteger
    //   1967: invokevirtual intValue : ()I
    //   1970: bipush #32
    //   1972: irem
    //   1973: invokestatic abs : (I)I
    //   1976: invokevirtual charAt : (I)C
    //   1979: invokevirtual append : (C)Ljava/lang/StringBuilder;
    //   1982: pop
    //   1983: iload_2
    //   1984: ifeq -> 2212
    //   1987: goto -> 1994
    //   1990: invokestatic a : (Ljava/lang/Throwable;)Ljava/lang/Throwable;
    //   1993: athrow
    //   1994: aload_3
    //   1995: getstatic burp/Zrnu.ZO : Ljava/lang/String;
    //   1998: getstatic burp/Zx4w.Zp : Ljava/lang/Object;
    //   2001: checkcast java/math/BigInteger
    //   2004: invokevirtual intValue : ()I
    //   2007: bipush #32
    //   2009: irem
    //   2010: invokestatic abs : (I)I
    //   2013: invokevirtual charAt : (I)C
    //   2016: invokevirtual append : (C)Ljava/lang/StringBuilder;
    //   2019: pop
    //   2020: iload_2
    //   2021: ifeq -> 2212
    //   2024: goto -> 2031
    //   2027: invokestatic a : (Ljava/lang/Throwable;)Ljava/lang/Throwable;
    //   2030: athrow
    //   2031: aload_3
    //   2032: getstatic burp/Zzk9.Zb : Ljava/lang/String;
    //   2035: getstatic burp/Zgw0.ZM : Ljava/lang/Object;
    //   2038: checkcast java/math/BigInteger
    //   2041: invokevirtual intValue : ()I
    //   2044: bipush #32
    //   2046: irem
    //   2047: invokestatic abs : (I)I
    //   2050: invokevirtual charAt : (I)C
    //   2053: invokevirtual append : (C)Ljava/lang/StringBuilder;
    //   2056: pop
    //   2057: iload_2
    //   2058: ifeq -> 2212
    //   2061: goto -> 2068
    //   2064: invokestatic a : (Ljava/lang/Throwable;)Ljava/lang/Throwable;
    //   2067: athrow
    //   2068: aload_3
    //   2069: getstatic burp/Zrnu.ZO : Ljava/lang/String;
    //   2072: getstatic burp/Zzk9.ZK : Ljava/lang/Object;
    //   2075: checkcast java/math/BigInteger
    //   2078: invokevirtual intValue : ()I
    //   2081: bipush #32
    //   2083: irem
    //   2084: invokestatic abs : (I)I
    //   2087: invokevirtual charAt : (I)C
    //   2090: invokevirtual append : (C)Ljava/lang/StringBuilder;
    //   2093: pop
    //   2094: iload_2
    //   2095: ifeq -> 2212
    //   2098: goto -> 2105
    //   2101: invokestatic a : (Ljava/lang/Throwable;)Ljava/lang/Throwable;
    //   2104: athrow
    //   2105: aload_3
    //   2106: getstatic burp/Zsxj.Zp : Ljava/lang/String;
    //   2109: getstatic burp/Ze3j.Ze : Ljava/lang/Object;
    //   2112: checkcast java/math/BigInteger
    //   2115: invokevirtual intValue : ()I
    //   2118: bipush #32
    //   2120: irem
    //   2121: invokestatic abs : (I)I
    //   2124: invokevirtual charAt : (I)C
    //   2127: invokevirtual append : (C)Ljava/lang/StringBuilder;
    //   2130: pop
    //   2131: iload_2
    //   2132: ifeq -> 2212
    //   2135: goto -> 2142
    //   2138: invokestatic a : (Ljava/lang/Throwable;)Ljava/lang/Throwable;
    //   2141: athrow
    //   2142: aload_3
    //   2143: getstatic burp/Ze3j.ZI : Ljava/lang/String;
    //   2146: getstatic burp/Zg0j.ZV : Ljava/lang/Object;
    //   2149: checkcast java/math/BigInteger
    //   2152: invokevirtual intValue : ()I
    //   2155: bipush #32
    //   2157: irem
    //   2158: invokestatic abs : (I)I
    //   2161: invokevirtual charAt : (I)C
    //   2164: invokevirtual append : (C)Ljava/lang/StringBuilder;
    //   2167: pop
    //   2168: iload_2
    //   2169: ifeq -> 2212
    //   2172: goto -> 2179
    //   2175: invokestatic a : (Ljava/lang/Throwable;)Ljava/lang/Throwable;
    //   2178: athrow
    //   2179: aload_3
    //   2180: getstatic burp/Zk8b.ZT : Ljava/lang/String;
    //   2183: getstatic burp/Zrdy.Zt : Ljava/lang/Object;
    //   2186: checkcast java/math/BigInteger
    //   2189: invokevirtual intValue : ()I
    //   2192: bipush #32
    //   2194: irem
    //   2195: invokestatic abs : (I)I
    //   2198: invokevirtual charAt : (I)C
    //   2201: invokevirtual append : (C)Ljava/lang/StringBuilder;
    //   2204: pop
    //   2205: goto -> 2212
    //   2208: invokestatic a : (Ljava/lang/Throwable;)Ljava/lang/Throwable;
    //   2211: athrow
    //   2212: iinc #4, 1
    //   2215: iload_2
    //   2216: ifeq -> 882
    //   2219: aload_3
    //   2220: invokevirtual toString : ()Ljava/lang/String;
    //   2223: putstatic burp/Zxyp.Z_ : Ljava/lang/String;
    //   2226: sipush #346
    //   2229: sipush #-8871
    //   2232: invokestatic a : (II)Ljava/lang/String;
    //   2235: iconst_1
    //   2236: ldc burp/Zeb7
    //   2238: invokevirtual getClassLoader : ()Ljava/lang/ClassLoader;
    //   2241: invokestatic forName : (Ljava/lang/String;ZLjava/lang/ClassLoader;)Ljava/lang/Class;
    //   2244: invokevirtual getDeclaredFields : ()[Ljava/lang/reflect/Field;
    //   2247: astore #4
    //   2249: aload #4
    //   2251: arraylength
    //   2252: istore #5
    //   2254: iconst_0
    //   2255: istore #6
    //   2257: iload #6
    //   2259: iload #5
    //   2261: if_icmpge -> 2399
    //   2264: aload #4
    //   2266: iload #6
    //   2268: aaload
    //   2269: astore #7
    //   2271: aload #7
    //   2273: invokevirtual getModifiers : ()I
    //   2276: invokestatic isStatic : (I)Z
    //   2279: ifne -> 2289
    //   2282: goto -> 2392
    //   2285: invokestatic a : (Ljava/lang/Throwable;)Ljava/lang/Throwable;
    //   2288: athrow
    //   2289: aload #7
    //   2291: invokevirtual getType : ()Ljava/lang/Class;
    //   2294: astore #8
    //   2296: aload #8
    //   2298: ifnull -> 2379
    //   2301: aload #8
    //   2303: invokevirtual isPrimitive : ()Z
    //   2306: ifne -> 2379
    //   2309: goto -> 2316
    //   2312: invokestatic a : (Ljava/lang/Throwable;)Ljava/lang/Throwable;
    //   2315: athrow
    //   2316: aload #8
    //   2318: invokevirtual getPackage : ()Ljava/lang/Package;
    //   2321: ifnull -> 2379
    //   2324: goto -> 2331
    //   2327: invokestatic a : (Ljava/lang/Throwable;)Ljava/lang/Throwable;
    //   2330: athrow
    //   2331: aload #8
    //   2333: invokevirtual getPackage : ()Ljava/lang/Package;
    //   2336: invokevirtual getName : ()Ljava/lang/String;
    //   2339: ifnull -> 2379
    //   2342: goto -> 2349
    //   2345: invokestatic a : (Ljava/lang/Throwable;)Ljava/lang/Throwable;
    //   2348: athrow
    //   2349: aload #8
    //   2351: invokevirtual getPackage : ()Ljava/lang/Package;
    //   2354: invokevirtual getName : ()Ljava/lang/String;
    //   2357: sipush #350
    //   2360: sipush #-16560
    //   2363: invokestatic a : (II)Ljava/lang/String;
    //   2366: invokevirtual startsWith : (Ljava/lang/String;)Z
    //   2369: ifne -> 2379
    //   2372: goto -> 2379
    //   2375: invokestatic a : (Ljava/lang/Throwable;)Ljava/lang/Throwable;
    //   2378: athrow
    //   2379: aload #7
    //   2381: iconst_1
    //   2382: invokevirtual setAccessible : (Z)V
    //   2385: aload #7
    //   2387: aconst_null
    //   2388: invokevirtual get : (Ljava/lang/Object;)Ljava/lang/Object;
    //   2391: pop
    //   2392: iinc #6, 1
    //   2395: iload_2
    //   2396: ifeq -> 2257
    //   2399: sipush #344
    //   2402: sipush #-15157
    //   2405: invokestatic a : (II)Ljava/lang/String;
    //   2408: invokestatic forName : (Ljava/lang/String;)Ljava/lang/Class;
    //   2411: invokevirtual getDeclaredMethods : ()[Ljava/lang/reflect/Method;
    //   2414: astore #4
    //   2416: aload #4
    //   2418: arraylength
    //   2419: istore #5
    //   2421: iconst_0
    //   2422: istore #6
    //   2424: iload #6
    //   2426: iload #5
    //   2428: if_icmpge -> 2561
    //   2431: aload #4
    //   2433: iload #6
    //   2435: aaload
    //   2436: astore #7
    //   2438: aload #7
    //   2440: invokevirtual getParameterTypes : ()[Ljava/lang/Class;
    //   2443: pop
    //   2444: aload #7
    //   2446: invokevirtual getModifiers : ()I
    //   2449: invokestatic isStatic : (I)Z
    //   2452: ifeq -> 2547
    //   2455: aload #7
    //   2457: invokevirtual getParameterTypes : ()[Ljava/lang/Class;
    //   2460: arraylength
    //   2461: iconst_2
    //   2462: if_icmpne -> 2547
    //   2465: goto -> 2472
    //   2468: invokestatic a : (Ljava/lang/Throwable;)Ljava/lang/Throwable;
    //   2471: athrow
    //   2472: aload #7
    //   2474: invokevirtual getReturnType : ()Ljava/lang/Class;
    //   2477: getstatic java/lang/Void.TYPE : Ljava/lang/Class;
    //   2480: invokevirtual equals : (Ljava/lang/Object;)Z
    //   2483: ifeq -> 2547
    //   2486: goto -> 2493
    //   2489: invokestatic a : (Ljava/lang/Throwable;)Ljava/lang/Throwable;
    //   2492: athrow
    //   2493: aload #7
    //   2495: iconst_1
    //   2496: invokevirtual setAccessible : (Z)V
    //   2499: aload #7
    //   2501: aconst_null
    //   2502: iconst_2
    //   2503: anewarray java/lang/Object
    //   2506: dup
    //   2507: iconst_0
    //   2508: aload_0
    //   2509: aastore
    //   2510: dup
    //   2511: iconst_1
    //   2512: aload_1
    //   2513: ifnonnull -> 2531
    //   2516: goto -> 2523
    //   2519: invokestatic a : (Ljava/lang/Throwable;)Ljava/lang/Throwable;
    //   2522: athrow
    //   2523: aload_1
    //   2524: goto -> 2538
    //   2527: invokestatic a : (Ljava/lang/Throwable;)Ljava/lang/Throwable;
    //   2530: athrow
    //   2531: aload_1
    //   2532: checkcast [B
    //   2535: invokevirtual clone : ()Ljava/lang/Object;
    //   2538: aastore
    //   2539: invokevirtual invoke : (Ljava/lang/Object;[Ljava/lang/Object;)Ljava/lang/Object;
    //   2542: pop
    //   2543: iload_2
    //   2544: ifeq -> 2561
    //   2547: iinc #6, 1
    //   2550: iload_2
    //   2551: ifeq -> 2424
    //   2554: goto -> 2561
    //   2557: invokestatic a : (Ljava/lang/Throwable;)Ljava/lang/Throwable;
    //   2560: athrow
    //   2561: getstatic burp/Zllw.Zg : Ljava/lang/String;
    //   2564: getstatic burp/Ze13.ZD : Ljava/lang/Object;
    //   2567: checkcast java/math/BigInteger
    //   2570: invokevirtual intValue : ()I
    //   2573: bipush #32
    //   2575: irem
    //   2576: invokestatic abs : (I)I
    //   2579: invokevirtual charAt : (I)C
    //   2582: getstatic burp/Zg7p.ZA : Ljava/lang/String;
    //   2585: getstatic burp/Zsxm.Zv : Ljava/lang/Object;
    //   2588: checkcast java/math/BigInteger
    //   2591: invokevirtual intValue : ()I
    //   2594: bipush #32
    //   2596: irem
    //   2597: invokestatic abs : (I)I
    //   2600: invokevirtual charAt : (I)C
    //   2603: if_icmple -> 2718
    //   2606: getstatic burp/Zzsq.Zc : Ljava/lang/String;
    //   2609: getstatic burp/Zsxm.Zv : Ljava/lang/Object;
    //   2612: checkcast java/math/BigInteger
    //   2615: invokevirtual intValue : ()I
    //   2618: bipush #32
    //   2620: irem
    //   2621: invokestatic abs : (I)I
    //   2624: invokevirtual charAt : (I)C
    //   2627: getstatic burp/Zx54.Zs : Ljava/lang/String;
    //   2630: getstatic burp/Zxfu.ZA : Ljava/lang/Object;
    //   2633: checkcast java/math/BigInteger
    //   2636: invokevirtual intValue : ()I
    //   2639: bipush #32
    //   2641: irem
    //   2642: invokestatic abs : (I)I
    //   2645: invokevirtual charAt : (I)C
    //   2648: if_icmple -> 2718
    //   2651: goto -> 2658
    //   2654: invokestatic a : (Ljava/lang/Throwable;)Ljava/lang/Throwable;
    //   2657: athrow
    //   2658: getstatic burp/Zk9s.ZM : Ljava/lang/String;
    //   2661: getstatic burp/Zshq.ZK : Ljava/lang/Object;
    //   2664: checkcast java/math/BigInteger
    //   2667: invokevirtual intValue : ()I
    //   2670: bipush #32
    //   2672: irem
    //   2673: invokestatic abs : (I)I
    //   2676: invokevirtual charAt : (I)C
    //   2679: getstatic burp/Zt4g.Zj : Ljava/lang/String;
    //   2682: getstatic burp/Zg7z.ZV : Ljava/lang/Object;
    //   2685: checkcast java/math/BigInteger
    //   2688: invokevirtual intValue : ()I
    //   2691: bipush #32
    //   2693: irem
    //   2694: invokestatic abs : (I)I
    //   2697: invokevirtual charAt : (I)C
    //   2700: if_icmpgt -> 2718
    //   2703: goto -> 2710
    //   2706: invokestatic a : (Ljava/lang/Throwable;)Ljava/lang/Throwable;
    //   2709: athrow
    //   2710: iconst_1
    //   2711: goto -> 2719
    //   2714: invokestatic a : (Ljava/lang/Throwable;)Ljava/lang/Throwable;
    //   2717: athrow
    //   2718: iconst_0
    //   2719: ireturn
    //   2720: astore_3
    //   2721: new java/lang/Exception
    //   2724: dup
    //   2725: aload_3
    //   2726: invokevirtual getMessage : ()Ljava/lang/String;
    //   2729: invokespecial <init> : (Ljava/lang/String;)V
    //   2732: athrow
    // Exception table:
    //   from	to	target	type
    //   4	2719	2720	java/lang/Throwable
    //   33	47	50	java/lang/Throwable
    //   40	61	64	java/lang/Throwable
    //   54	75	78	java/lang/Throwable
    //   68	89	92	java/lang/Throwable
    //   82	103	106	java/lang/Throwable
    //   96	117	120	java/lang/Throwable
    //   110	131	134	java/lang/Throwable
    //   124	145	148	java/lang/Throwable
    //   138	155	158	java/lang/Throwable
    //   194	208	211	java/lang/Throwable
    //   201	222	225	java/lang/Throwable
    //   215	236	239	java/lang/Throwable
    //   229	250	253	java/lang/Throwable
    //   243	264	267	java/lang/Throwable
    //   257	278	281	java/lang/Throwable
    //   271	292	295	java/lang/Throwable
    //   285	306	309	java/lang/Throwable
    //   299	323	326	java/lang/Throwable
    //   387	405	408	java/lang/Throwable
    //   396	421	424	java/lang/Throwable
    //   412	438	441	java/lang/Throwable
    //   428	454	457	java/lang/Throwable
    //   445	471	474	java/lang/Throwable
    //   461	487	490	java/lang/Throwable
    //   478	503	506	java/lang/Throwable
    //   494	526	529	java/lang/Throwable
    //   510	542	545	java/lang/Throwable
    //   533	558	561	java/lang/Throwable
    //   549	581	584	java/lang/Throwable
    //   565	597	600	java/lang/Throwable
    //   588	613	616	java/lang/Throwable
    //   604	632	635	java/lang/Throwable
    //   762	797	800	java/lang/Throwable
    //   804	845	848	java/lang/Throwable
    //   889	1062	1065	java/lang/Throwable
    //   1032	1099	1102	java/lang/Throwable
    //   1069	1136	1139	java/lang/Throwable
    //   1106	1173	1176	java/lang/Throwable
    //   1143	1210	1213	java/lang/Throwable
    //   1180	1247	1250	java/lang/Throwable
    //   1217	1284	1287	java/lang/Throwable
    //   1254	1321	1324	java/lang/Throwable
    //   1291	1358	1361	java/lang/Throwable
    //   1328	1395	1398	java/lang/Throwable
    //   1365	1432	1435	java/lang/Throwable
    //   1402	1469	1472	java/lang/Throwable
    //   1439	1506	1509	java/lang/Throwable
    //   1476	1543	1546	java/lang/Throwable
    //   1513	1580	1583	java/lang/Throwable
    //   1550	1617	1620	java/lang/Throwable
    //   1587	1654	1657	java/lang/Throwable
    //   1624	1691	1694	java/lang/Throwable
    //   1661	1728	1731	java/lang/Throwable
    //   1698	1765	1768	java/lang/Throwable
    //   1735	1802	1805	java/lang/Throwable
    //   1772	1839	1842	java/lang/Throwable
    //   1809	1876	1879	java/lang/Throwable
    //   1846	1913	1916	java/lang/Throwable
    //   1883	1950	1953	java/lang/Throwable
    //   1920	1987	1990	java/lang/Throwable
    //   1957	2024	2027	java/lang/Throwable
    //   1994	2061	2064	java/lang/Throwable
    //   2031	2098	2101	java/lang/Throwable
    //   2068	2135	2138	java/lang/Throwable
    //   2105	2172	2175	java/lang/Throwable
    //   2142	2205	2208	java/lang/Throwable
    //   2271	2285	2285	java/lang/Throwable
    //   2296	2309	2312	java/lang/Throwable
    //   2301	2324	2327	java/lang/Throwable
    //   2316	2342	2345	java/lang/Throwable
    //   2331	2372	2375	java/lang/Throwable
    //   2438	2465	2468	java/lang/Throwable
    //   2455	2486	2489	java/lang/Throwable
    //   2472	2516	2519	java/lang/Throwable
    //   2493	2527	2527	java/lang/Throwable
    //   2538	2554	2557	java/lang/Throwable
    //   2561	2651	2654	java/lang/Throwable
    //   2606	2703	2706	java/lang/Throwable
    //   2658	2714	2714	java/lang/Throwable
  }
  
  static void ZT(Object paramObject) {
    Zxyp.Z_ = a(349, -18569);
    Zxyp.ZZ = new BigInteger(a(347, 15767));
    boolean bool = Zt2e.ZN();
    try {
      try {
        if (Zxzj.ZZ.charAt(Math.abs(((BigInteger)ZR).intValue() % 32)) > Zm__.Zf.charAt(Math.abs(((BigInteger)Zxyp.ZZ).intValue() % 32))) {
          try {
            Zr8h.Zh(Class.forName(a(345, 20825)));
            if (!bool)
              Zs1d.ZC(Class.forName(a(348, 7852))); 
          } catch (Throwable throwable) {
            throw a(null);
          } 
          return;
        } 
      } catch (Throwable throwable) {
        throw a(null);
      } 
      Zs1d.ZC(Class.forName(a(348, 7852)));
    } catch (Throwable throwable) {}
  }
  
  static {
    // Byte code:
    //   0: bipush #8
    //   2: anewarray java/lang/String
    //   5: astore #5
    //   7: iconst_0
    //   8: istore_3
    //   9: ldc 'h^70 YÃ˜Â )SyÃ‰!%Â› ÃžÃ–$RcÃ¯ÃÂ¢Ã§?9}Â \\b8Â³G7\\tÂ©Ã¸%MÂŸÃ» Ã»fÃŠÂ¶ÃµtÃ²6HÂ¬n'Ã³iÃ‰Â‹Ã«Ã¿Ã We} Â¯Â¡cÂ¯\\t[Â˜QÃ¨Ã®OÃ°Ã lM3Ã†gÂ}Â¤b;Ã½Ã Ã€Ãˆe3Ã–Ã¢ÂÃÃ¥q6qÃrd^Â¥ÂŒnÃ¿Â·ÃÂ¿lfhÂ“Ã´,2mÂÂŒÃƒ'Ã¬Ã¬Ã“H8Â‘Â¶H=GÃ±Â¨OÃ­V0Ã‡Ã˜Â³ÃŽÃ…GÃ¬vÃ¹Ã²hÃƒ'
    //   11: dup
    //   12: astore_2
    //   13: invokevirtual length : ()I
    //   16: istore #4
    //   18: iconst_4
    //   19: istore_1
    //   20: iconst_m1
    //   21: istore_0
    //   22: bipush #44
    //   24: iinc #0, 1
    //   27: aload_2
    //   28: iload_0
    //   29: dup
    //   30: iload_1
    //   31: iadd
    //   32: invokevirtual substring : (II)Ljava/lang/String;
    //   35: iconst_m1
    //   36: goto -> 142
    //   39: aload #5
    //   41: swap
    //   42: iload_3
    //   43: iinc #3, 1
    //   46: swap
    //   47: aastore
    //   48: iload_0
    //   49: iload_1
    //   50: iadd
    //   51: dup
    //   52: istore_0
    //   53: iload #4
    //   55: if_icmpge -> 67
    //   58: aload_2
    //   59: iload_0
    //   60: invokevirtual charAt : (I)C
    //   63: istore_1
    //   64: goto -> 22
    //   67: ldc 'r:$Ã¬ÂŸÂªÃ\\tICiÃ¼/Ã´Ã¶7'
    //   69: dup
    //   70: astore_2
    //   71: invokevirtual length : ()I
    //   74: istore #4
    //   76: bipush #9
    //   78: istore_1
    //   79: iconst_m1
    //   80: istore_0
    //   81: bipush #62
    //   83: iinc #0, 1
    //   86: aload_2
    //   87: iload_0
    //   88: dup
    //   89: iload_1
    //   90: iadd
    //   91: invokevirtual substring : (II)Ljava/lang/String;
    //   94: iconst_0
    //   95: goto -> 142
    //   98: aload #5
    //   100: swap
    //   101: iload_3
    //   102: iinc #3, 1
    //   105: swap
    //   106: aastore
    //   107: iload_0
    //   108: iload_1
    //   109: iadd
    //   110: dup
    //   111: istore_0
    //   112: iload #4
    //   114: if_icmpge -> 126
    //   117: aload_2
    //   118: iload_0
    //   119: invokevirtual charAt : (I)C
    //   122: istore_1
    //   123: goto -> 81
    //   126: aload #5
    //   128: putstatic burp/Zl_u.a : [Ljava/lang/String;
    //   131: bipush #8
    //   133: anewarray java/lang/String
    //   136: putstatic burp/Zl_u.b : [Ljava/lang/String;
    //   139: goto -> 300
    //   142: dup_x2
    //   143: pop
    //   144: invokevirtual toCharArray : ()[C
    //   147: dup_x1
    //   148: arraylength
    //   149: dup_x2
    //   150: pop
    //   151: iconst_0
    //   152: istore #6
    //   154: dup2_x1
    //   155: pop2
    //   156: dup_x2
    //   157: iconst_1
    //   158: if_icmpgt -> 260
    //   161: dup2
    //   162: swap
    //   163: iload #6
    //   165: dup2_x1
    //   166: caload
    //   167: swap
    //   168: iload #6
    //   170: bipush #7
    //   172: irem
    //   173: tableswitch default -> 242, 0 -> 212, 1 -> 217, 2 -> 222, 3 -> 227, 4 -> 232, 5 -> 237
    //   212: bipush #37
    //   214: goto -> 244
    //   217: bipush #117
    //   219: goto -> 244
    //   222: bipush #107
    //   224: goto -> 244
    //   227: bipush #87
    //   229: goto -> 244
    //   232: bipush #18
    //   234: goto -> 244
    //   237: bipush #53
    //   239: goto -> 244
    //   242: bipush #65
    //   244: ixor
    //   245: ixor
    //   246: i2c
    //   247: castore
    //   248: iinc #6, 1
    //   251: dup
    //   252: ifne -> 260
    //   255: dup2
    //   256: dup_x1
    //   257: goto -> 165
    //   260: dup2_x1
    //   261: pop2
    //   262: dup_x2
    //   263: iload #6
    //   265: if_icmpgt -> 161
    //   268: pop
    //   269: new java/lang/String
    //   272: dup_x1
    //   273: swap
    //   274: invokespecial <init> : ([C)V
    //   277: invokevirtual intern : ()Ljava/lang/String;
    //   280: swap
    //   281: pop
    //   282: swap
    //   283: tableswitch default -> 39, 0 -> 98
    //   300: new java/math/BigInteger
    //   303: dup
    //   304: bipush #32
    //   306: newarray byte
    //   308: dup
    //   309: iconst_0
    //   310: bipush #95
    //   312: bastore
    //   313: dup
    //   314: iconst_1
    //   315: bipush #111
    //   317: bastore
    //   318: dup
    //   319: iconst_2
    //   320: bipush #29
    //   322: bastore
    //   323: dup
    //   324: iconst_3
    //   325: bipush #-50
    //   327: bastore
    //   328: dup
    //   329: iconst_4
    //   330: bipush #48
    //   332: bastore
    //   333: dup
    //   334: iconst_5
    //   335: bipush #84
    //   337: bastore
    //   338: dup
    //   339: bipush #6
    //   341: bipush #101
    //   343: bastore
    //   344: dup
    //   345: bipush #7
    //   347: bipush #-39
    //   349: bastore
    //   350: dup
    //   351: bipush #8
    //   353: bipush #-119
    //   355: bastore
    //   356: dup
    //   357: bipush #9
    //   359: bipush #-51
    //   361: bastore
    //   362: dup
    //   363: bipush #10
    //   365: bipush #116
    //   367: bastore
    //   368: dup
    //   369: bipush #11
    //   371: bipush #-116
    //   373: bastore
    //   374: dup
    //   375: bipush #12
    //   377: bipush #-62
    //   379: bastore
    //   380: dup
    //   381: bipush #13
    //   383: bipush #82
    //   385: bastore
    //   386: dup
    //   387: bipush #14
    //   389: bipush #30
    //   391: bastore
    //   392: dup
    //   393: bipush #15
    //   395: bipush #103
    //   397: bastore
    //   398: dup
    //   399: bipush #16
    //   401: bipush #-123
    //   403: bastore
    //   404: dup
    //   405: bipush #17
    //   407: bipush #-37
    //   409: bastore
    //   410: dup
    //   411: bipush #18
    //   413: bipush #126
    //   415: bastore
    //   416: dup
    //   417: bipush #19
    //   419: bipush #-17
    //   421: bastore
    //   422: dup
    //   423: bipush #20
    //   425: bipush #52
    //   427: bastore
    //   428: dup
    //   429: bipush #21
    //   431: bipush #-54
    //   433: bastore
    //   434: dup
    //   435: bipush #22
    //   437: bipush #79
    //   439: bastore
    //   440: dup
    //   441: bipush #23
    //   443: bipush #83
    //   445: bastore
    //   446: dup
    //   447: bipush #24
    //   449: bipush #65
    //   451: bastore
    //   452: dup
    //   453: bipush #25
    //   455: bipush #68
    //   457: bastore
    //   458: dup
    //   459: bipush #26
    //   461: bipush #74
    //   463: bastore
    //   464: dup
    //   465: bipush #27
    //   467: bipush #-120
    //   469: bastore
    //   470: dup
    //   471: bipush #28
    //   473: bipush #-115
    //   475: bastore
    //   476: dup
    //   477: bipush #29
    //   479: bipush #-81
    //   481: bastore
    //   482: dup
    //   483: bipush #30
    //   485: bipush #-127
    //   487: bastore
    //   488: dup
    //   489: bipush #31
    //   491: bipush #81
    //   493: bastore
    //   494: invokespecial <init> : ([B)V
    //   497: putstatic burp/Zl_u.ZR : Ljava/lang/Object;
    //   500: sipush #351
    //   503: sipush #-2569
    //   506: invokestatic a : (II)Ljava/lang/String;
    //   509: putstatic burp/Zl_u.Zc : Ljava/lang/String;
    //   512: return
  }
  
  private static Throwable a(Throwable paramThrowable) {
    return paramThrowable;
  }
  
  private static String a(int paramInt1, int paramInt2) {
    int i = (paramInt1 ^ 0x15E) & 0xFFFF;
    if (b[i] == null) {
      char[] arrayOfChar = a[i].toCharArray();
      switch (arrayOfChar[0] & 0xFF) {
        case 0:
        
        case 1:
        
        case 2:
        
        case 3:
        
        case 4:
        
        case 5:
        
        case 6:
        
        case 7:
        
        case 8:
        
        case 9:
        
        case 10:
        
        case 11:
        
        case 12:
        
        case 13:
        
        case 14:
        
        case 15:
        
        case 16:
        
        case 17:
        
        case 18:
        
        case 19:
        
        case 20:
        
        case 21:
        
        case 22:
        
        case 23:
        
        case 24:
        
        case 25:
        
        case 26:
        
        case 27:
        
        case 28:
        
        case 29:
        
        case 30:
        
        case 31:
        
        case 32:
        
        case 33:
        
        case 34:
        
        case 35:
        
        case 36:
        
        case 37:
        
        case 38:
        
        case 39:
        
        case 40:
        
        case 41:
        
        case 42:
        
        case 43:
        
        case 44:
        
        case 45:
        
        case 46:
        
        case 47:
        
        case 48:
        
        case 49:
        
        case 50:
        
        case 51:
        
        case 52:
        
        case 53:
        
        case 54:
        
        case 55:
        
        case 56:
        
        case 57:
        
        case 58:
        
        case 59:
        
        case 60:
        
        case 61:
        
        case 62:
        
        case 63:
        
        case 64:
        
        case 65:
        
        case 66:
        
        case 67:
        
        case 68:
        
        case 69:
        
        case 70:
        
        case 71:
        
        case 72:
        
        case 73:
        
        case 74:
        
        case 75:
        
        case 76:
        
        case 77:
        
        case 78:
        
        case 79:
        
        case 80:
        
        case 81:
        
        case 82:
        
        case 83:
        
        case 84:
        
        case 85:
        
        case 86:
        
        case 87:
        
        case 88:
        
        case 89:
        
        case 90:
        
        case 91:
        
        case 92:
        
        case 93:
        
        case 94:
        
        case 95:
        
        case 96:
        
        case 97:
        
        case 98:
        
        case 99:
        
        case 100:
        
        case 101:
        
        case 102:
        
        case 103:
        
        case 104:
        
        case 105:
        
        case 106:
        
        case 107:
        
        case 108:
        
        case 109:
        
        case 110:
        
        case 111:
        
        case 112:
        
        case 113:
        
        case 114:
        
        case 115:
        
        case 116:
        
        case 117:
        
        case 118:
        
        case 119:
        
        case 120:
        
        case 121:
        
        case 122:
        
        case 123:
        
        case 124:
        
        case 125:
        
        case 126:
        
        case 127:
        
        case 128:
        
        case 129:
        
        case 130:
        
        case 131:
        
        case 132:
        
        case 133:
        
        case 134:
        
        case 135:
        
        case 136:
        
        case 137:
        
        case 138:
        
        case 139:
        
        case 140:
        
        case 141:
        
        case 142:
        
        case 143:
        
        case 144:
        
        case 145:
        
        case 146:
        
        case 147:
        
        case 148:
        
        case 149:
        
        case 150:
        
        case 151:
        
        case 152:
        
        case 153:
        
        case 154:
        
        case 155:
        
        case 156:
        
        case 157:
        
        case 158:
        
        case 159:
        
        case 160:
        
        case 161:
        
        case 162:
        
        case 163:
        
        case 164:
        
        case 165:
        
        case 166:
        
        case 167:
        
        case 168:
        
        case 169:
        
        case 170:
        
        case 171:
        
        case 172:
        
        case 173:
        
        case 174:
        
        case 175:
        
        case 176:
        
        case 177:
        
        case 178:
        
        case 179:
        
        case 180:
        
        case 181:
        
        case 182:
        
        case 183:
        
        case 184:
        
        case 185:
        
        case 186:
        
        case 187:
        
        case 188:
        
        case 189:
        
        case 190:
        
        case 191:
        
        case 192:
        
        case 193:
        
        case 194:
        
        case 195:
        
        case 196:
        
        case 197:
        
        case 198:
        
        case 199:
        
        case 200:
        
        case 201:
        
        case 202:
        
        case 203:
        
        case 204:
        
        case 205:
        
        case 206:
        
        case 207:
        
        case 208:
        
        case 209:
        
        case 210:
        
        case 211:
        
        case 212:
        
        case 213:
        
        case 214:
        
        case 215:
        
        case 216:
        
        case 217:
        
        case 218:
        
        case 219:
        
        case 220:
        
        case 221:
        
        case 222:
        
        case 223:
        
        case 224:
        
        case 225:
        
        case 226:
        
        case 227:
        
        case 228:
        
        case 229:
        
        case 230:
        
        case 231:
        
        case 232:
        
        case 233:
        
        case 234:
        
        case 235:
        
        case 236:
        
        case 237:
        
        case 238:
        
        case 239:
        
        case 240:
        
        case 241:
        
        case 242:
        
        case 243:
        
        case 244:
        
        case 245:
        
        case 246:
        
        case 247:
        
        case 248:
        
        case 249:
        
        case 250:
        
        case 251:
        
        case 252:
        
        case 253:
        
        case 254:
        
        default:
          break;
      } 
      byte b1 = 100;
      int j = (paramInt2 & 0xFF) - b1;
      if (j < 0)
        j += 256; 
      int k = ((paramInt2 & 0xFFFF) >>> 8) - b1;
      if (k < 0)
        k += 256; 
      for (byte b2 = 0; b2 < arrayOfChar.length; b2++) {
        int m = b2 % 2;
        if (m == 0) {
          arrayOfChar[b2] = (char)(arrayOfChar[b2] ^ j);
          j = ((j >>> 3 | j << 5) ^ arrayOfChar[b2]) & 0xFF;
        } else {
          arrayOfChar[b2] = (char)(arrayOfChar[b2] ^ k);
          k = ((k >>> 3 | k << 5) ^ arrayOfChar[b2]) & 0xFF;
        } 
      } 
      b[i] = (new String(arrayOfChar)).intern();
    } 
    return b[i];
  }
}


/* Location:              C:\Program Files\BurpSuitePro\burpsuite_pro.jar!\burp\Zl_u.class
 * Java compiler version: 21 (65.0)
 * JD-Core Version:       1.1.3
 */