package burp;

import java.awt.Color;
import java.text.DateFormat;
import java.text.NumberFormat;
import java.time.format.DateTimeFormatter;

public class Zlb0 {
  public static final NumberFormat Zl;
  
  public static final NumberFormat Zn;
  
  public static final NumberFormat ZY;
  
  public static final NumberFormat Zu;
  
  public static final String Zp;
  
  public static final byte[] Zk;
  
  public static final DateFormat Zd;
  
  public static final DateTimeFormatter ZH;
  
  public static final DateTimeFormatter ZV;
  
  public static final DateTimeFormatter Zo;
  
  public static final Color ZO;
  
  public static final Color Zj;
  
  public static final Color ZU;
  
  public static final Color ZQ;
  
  public static final Color Z_;
  
  public static final Color Zf;
  
  public static final Color ZR;
  
  public static final Color Zm;
  
  public static final Color Zi;
  
  public static final Color ZK;
  
  public static final Color Zh;
  
  public static final Color Za;
  
  public static final Color ZJ;
  
  public static final Color ZP;
  
  public static final Color ZM;
  
  public static final Color ZE;
  
  public static final Color Zs;
  
  public static final Color Zv;
  
  static {
    // Byte code:
    //   0: iconst_5
    //   1: anewarray java/lang/String
    //   4: astore_0
    //   5: iconst_0
    //   6: istore #4
    //   8: ldc 'N*E}uBE\\b/\\n'&XQ\\nbBle/gXjOML4vSI('
    //   10: dup
    //   11: astore_3
    //   12: invokevirtual length : ()I
    //   15: istore #5
    //   17: bipush #19
    //   19: istore_2
    //   20: iconst_m1
    //   21: istore_1
    //   22: bipush #77
    //   24: iinc #1, 1
    //   27: aload_3
    //   28: iload_1
    //   29: dup
    //   30: iload_2
    //   31: iadd
    //   32: invokevirtual substring : (II)Ljava/lang/String;
    //   35: iconst_m1
    //   36: goto -> 129
    //   39: aload_0
    //   40: swap
    //   41: iload #4
    //   43: iinc #4, 1
    //   46: swap
    //   47: aastore
    //   48: iload_1
    //   49: iload_2
    //   50: iadd
    //   51: dup
    //   52: istore_1
    //   53: iload #5
    //   55: if_icmpge -> 67
    //   58: aload_3
    //   59: iload_1
    //   60: invokevirtual charAt : (I)C
    //   63: istore_2
    //   64: goto -> 22
    //   67: ldc '\\riXL>Z6KlIdeXX$Q=Y\\riXL>Z6KlIdeXX'
    //   69: dup
    //   70: astore_3
    //   71: invokevirtual length : ()I
    //   74: istore #5
    //   76: bipush #23
    //   78: istore_2
    //   79: iconst_m1
    //   80: istore_1
    //   81: bipush #14
    //   83: iinc #1, 1
    //   86: aload_3
    //   87: iload_1
    //   88: dup
    //   89: iload_2
    //   90: iadd
    //   91: invokevirtual substring : (II)Ljava/lang/String;
    //   94: iconst_0
    //   95: goto -> 129
    //   98: aload_0
    //   99: swap
    //   100: iload #4
    //   102: iinc #4, 1
    //   105: swap
    //   106: aastore
    //   107: iload_1
    //   108: iload_2
    //   109: iadd
    //   110: dup
    //   111: istore_1
    //   112: iload #5
    //   114: if_icmpge -> 126
    //   117: aload_3
    //   118: iload_1
    //   119: invokevirtual charAt : (I)C
    //   122: istore_2
    //   123: goto -> 81
    //   126: goto -> 288
    //   129: dup_x2
    //   130: pop
    //   131: invokevirtual toCharArray : ()[C
    //   134: dup_x1
    //   135: arraylength
    //   136: dup_x2
    //   137: pop
    //   138: iconst_0
    //   139: istore #6
    //   141: dup2_x1
    //   142: pop2
    //   143: dup_x2
    //   144: iconst_1
    //   145: if_icmpgt -> 248
    //   148: dup2
    //   149: swap
    //   150: iload #6
    //   152: dup2_x1
    //   153: caload
    //   154: swap
    //   155: iload #6
    //   157: bipush #7
    //   159: irem
    //   160: tableswitch default -> 230, 0 -> 200, 1 -> 205, 2 -> 210, 3 -> 215, 4 -> 220, 5 -> 225
    //   200: bipush #75
    //   202: goto -> 232
    //   205: bipush #47
    //   207: goto -> 232
    //   210: bipush #108
    //   212: goto -> 232
    //   215: bipush #101
    //   217: goto -> 232
    //   220: bipush #47
    //   222: goto -> 232
    //   225: bipush #10
    //   227: goto -> 232
    //   230: bipush #39
    //   232: ixor
    //   233: ixor
    //   234: i2c
    //   235: castore
    //   236: iinc #6, 1
    //   239: dup
    //   240: ifne -> 248
    //   243: dup2
    //   244: dup_x1
    //   245: goto -> 152
    //   248: dup2_x1
    //   249: pop2
    //   250: dup_x2
    //   251: iload #6
    //   253: if_icmpgt -> 148
    //   256: pop
    //   257: new java/lang/String
    //   260: dup_x1
    //   261: swap
    //   262: invokespecial <init> : ([C)V
    //   265: invokevirtual intern : ()Ljava/lang/String;
    //   268: swap
    //   269: pop
    //   270: swap
    //   271: tableswitch default -> 39, 0 -> 98
    //   288: invokestatic getInstance : ()Ljava/text/NumberFormat;
    //   291: putstatic burp/Zlb0.Zl : Ljava/text/NumberFormat;
    //   294: invokestatic getInstance : ()Ljava/text/NumberFormat;
    //   297: putstatic burp/Zlb0.Zn : Ljava/text/NumberFormat;
    //   300: invokestatic getInstance : ()Ljava/text/NumberFormat;
    //   303: putstatic burp/Zlb0.ZY : Ljava/text/NumberFormat;
    //   306: invokestatic getInstance : ()Ljava/text/NumberFormat;
    //   309: putstatic burp/Zlb0.Zu : Ljava/text/NumberFormat;
    //   312: getstatic burp/Zlb0.Zn : Ljava/text/NumberFormat;
    //   315: iconst_1
    //   316: invokevirtual setGroupingUsed : (Z)V
    //   319: getstatic burp/Zlb0.ZY : Ljava/text/NumberFormat;
    //   322: iconst_2
    //   323: invokevirtual setMaximumFractionDigits : (I)V
    //   326: getstatic burp/Zlb0.Zu : Ljava/text/NumberFormat;
    //   329: iconst_2
    //   330: invokevirtual setMaximumFractionDigits : (I)V
    //   333: getstatic burp/Zlb0.Zu : Ljava/text/NumberFormat;
    //   336: iconst_2
    //   337: invokevirtual setMinimumFractionDigits : (I)V
    //   340: aload_0
    //   341: iconst_2
    //   342: aaload
    //   343: invokestatic getProperty : (Ljava/lang/String;)Ljava/lang/String;
    //   346: putstatic burp/Zlb0.Zp : Ljava/lang/String;
    //   349: getstatic burp/Zlb0.Zp : Ljava/lang/String;
    //   352: invokestatic Zy : (Ljava/lang/String;)[B
    //   355: putstatic burp/Zlb0.Zk : [B
    //   358: new java/text/SimpleDateFormat
    //   361: dup
    //   362: aload_0
    //   363: iconst_0
    //   364: aaload
    //   365: invokespecial <init> : (Ljava/lang/String;)V
    //   368: putstatic burp/Zlb0.Zd : Ljava/text/DateFormat;
    //   371: aload_0
    //   372: iconst_1
    //   373: aaload
    //   374: invokestatic ofPattern : (Ljava/lang/String;)Ljava/time/format/DateTimeFormatter;
    //   377: putstatic burp/Zlb0.ZH : Ljava/time/format/DateTimeFormatter;
    //   380: aload_0
    //   381: iconst_4
    //   382: aaload
    //   383: invokestatic ofPattern : (Ljava/lang/String;)Ljava/time/format/DateTimeFormatter;
    //   386: putstatic burp/Zlb0.ZV : Ljava/time/format/DateTimeFormatter;
    //   389: aload_0
    //   390: iconst_3
    //   391: aaload
    //   392: invokestatic ofPattern : (Ljava/lang/String;)Ljava/time/format/DateTimeFormatter;
    //   395: putstatic burp/Zlb0.Zo : Ljava/time/format/DateTimeFormatter;
    //   398: new java/awt/Color
    //   401: dup
    //   402: bipush #100
    //   404: bipush #100
    //   406: bipush #100
    //   408: sipush #255
    //   411: invokespecial <init> : (IIII)V
    //   414: putstatic burp/Zlb0.ZO : Ljava/awt/Color;
    //   417: new java/awt/Color
    //   420: dup
    //   421: sipush #180
    //   424: sipush #180
    //   427: sipush #180
    //   430: sipush #255
    //   433: invokespecial <init> : (IIII)V
    //   436: putstatic burp/Zlb0.Zj : Ljava/awt/Color;
    //   439: new java/awt/Color
    //   442: dup
    //   443: sipush #200
    //   446: sipush #200
    //   449: sipush #200
    //   452: invokespecial <init> : (III)V
    //   455: putstatic burp/Zlb0.ZU : Ljava/awt/Color;
    //   458: new java/awt/Color
    //   461: dup
    //   462: sipush #240
    //   465: sipush #240
    //   468: sipush #240
    //   471: invokespecial <init> : (III)V
    //   474: putstatic burp/Zlb0.ZQ : Ljava/awt/Color;
    //   477: new java/awt/Color
    //   480: dup
    //   481: sipush #255
    //   484: bipush #100
    //   486: bipush #100
    //   488: sipush #255
    //   491: invokespecial <init> : (IIII)V
    //   494: putstatic burp/Zlb0.Z_ : Ljava/awt/Color;
    //   497: new java/awt/Color
    //   500: dup
    //   501: sipush #255
    //   504: sipush #200
    //   507: bipush #100
    //   509: invokespecial <init> : (III)V
    //   512: putstatic burp/Zlb0.Zf : Ljava/awt/Color;
    //   515: new java/awt/Color
    //   518: dup
    //   519: sipush #255
    //   522: sipush #255
    //   525: bipush #100
    //   527: invokespecial <init> : (III)V
    //   530: putstatic burp/Zlb0.ZR : Ljava/awt/Color;
    //   533: new java/awt/Color
    //   536: dup
    //   537: bipush #100
    //   539: sipush #255
    //   542: bipush #100
    //   544: invokespecial <init> : (III)V
    //   547: putstatic burp/Zlb0.Zm : Ljava/awt/Color;
    //   550: new java/awt/Color
    //   553: dup
    //   554: bipush #100
    //   556: sipush #255
    //   559: sipush #255
    //   562: invokespecial <init> : (III)V
    //   565: putstatic burp/Zlb0.Zi : Ljava/awt/Color;
    //   568: new java/awt/Color
    //   571: dup
    //   572: bipush #100
    //   574: bipush #100
    //   576: sipush #255
    //   579: invokespecial <init> : (III)V
    //   582: putstatic burp/Zlb0.ZK : Ljava/awt/Color;
    //   585: new java/awt/Color
    //   588: dup
    //   589: sipush #255
    //   592: sipush #200
    //   595: sipush #200
    //   598: invokespecial <init> : (III)V
    //   601: putstatic burp/Zlb0.Zh : Ljava/awt/Color;
    //   604: new java/awt/Color
    //   607: dup
    //   608: sipush #255
    //   611: bipush #100
    //   613: sipush #255
    //   616: invokespecial <init> : (III)V
    //   619: putstatic burp/Zlb0.Za : Ljava/awt/Color;
    //   622: new java/awt/Color
    //   625: dup
    //   626: iconst_0
    //   627: sipush #155
    //   630: iconst_0
    //   631: invokespecial <init> : (III)V
    //   634: putstatic burp/Zlb0.ZJ : Ljava/awt/Color;
    //   637: new java/awt/Color
    //   640: dup
    //   641: iconst_0
    //   642: sipush #155
    //   645: sipush #155
    //   648: invokespecial <init> : (III)V
    //   651: putstatic burp/Zlb0.ZP : Ljava/awt/Color;
    //   654: new java/awt/Color
    //   657: dup
    //   658: sipush #205
    //   661: sipush #150
    //   664: iconst_0
    //   665: invokespecial <init> : (III)V
    //   668: putstatic burp/Zlb0.ZM : Ljava/awt/Color;
    //   671: new java/awt/Color
    //   674: dup
    //   675: sipush #205
    //   678: sipush #205
    //   681: iconst_0
    //   682: invokespecial <init> : (III)V
    //   685: putstatic burp/Zlb0.ZE : Ljava/awt/Color;
    //   688: new java/awt/Color
    //   691: dup
    //   692: sipush #205
    //   695: bipush #125
    //   697: bipush #125
    //   699: invokespecial <init> : (III)V
    //   702: putstatic burp/Zlb0.Zs : Ljava/awt/Color;
    //   705: new java/awt/Color
    //   708: dup
    //   709: sipush #200
    //   712: sipush #200
    //   715: sipush #255
    //   718: invokespecial <init> : (III)V
    //   721: putstatic burp/Zlb0.Zv : Ljava/awt/Color;
    //   724: return
  }
}


/* Location:              C:\Program Files\BurpSuitePro\burpsuite_pro.jar!\burp\Zlb0.class
 * Java compiler version: 21 (65.0)
 * JD-Core Version:       1.1.3
 */