package burp;

import java.math.BigInteger;

class Zlbt extends ClassLoader {
  static String ZE;
  
  static Object ZF;
  
  private static final String[] a;
  
  private static final String[] b;
  
  static void Zy(Object paramObject) {
    Zsts.ZI = a(-3520, 4703);
    Zsts.Zu = new BigInteger(a(-3517, -15712));
    boolean bool = Zt2e.ZN();
    try {
      try {
        if (Zb6a.ZY.charAt(Math.abs(((BigInteger)ZF).intValue() % 32)) <= Zlo4.Zn.charAt(Math.abs(((BigInteger)Ztsj.Zc).intValue() % 32))) {
          try {
            Zgja.ZL(Class.forName(a(-3511, -11997)));
            if (!bool)
              Zlo4.Zr(Class.forName(a(-3514, -13068))); 
          } catch (Throwable throwable) {
            throw a(null);
          } 
          return;
        } 
      } catch (Throwable throwable) {
        throw a(null);
      } 
      Zlo4.Zr(Class.forName(a(-3514, -13068)));
    } catch (Throwable throwable) {}
  }
  
  static void ZR(Object[] paramArrayOfObject, Object paramObject) throws Throwable {}
  
  static boolean Zl(Object[] paramArrayOfObject, Object paramObject) throws Throwable {
    // Byte code:
    //   0: invokestatic ZK : ()Z
    //   3: istore_2
    //   4: getstatic burp/Zxf8.Zz : Ljava/lang/Object;
    //   7: checkcast java/math/BigInteger
    //   10: getstatic burp/Zxx4.Zo : Ljava/lang/Object;
    //   13: checkcast java/math/BigInteger
    //   16: invokevirtual subtract : (Ljava/math/BigInteger;)Ljava/math/BigInteger;
    //   19: putstatic burp/Zxf8.Zz : Ljava/lang/Object;
    //   22: ldc2_w 8682522807148012
    //   25: invokestatic currentTimeMillis : ()J
    //   28: lxor
    //   29: lstore #4
    //   31: lload #4
    //   33: ldc2_w 25214903917
    //   36: lmul
    //   37: ldc2_w 11
    //   40: ladd
    //   41: ldc2_w 281474976710655
    //   44: land
    //   45: lstore #4
    //   47: lload #4
    //   49: bipush #32
    //   51: lshl
    //   52: lstore #6
    //   54: lload #4
    //   56: ldc2_w 25214903917
    //   59: lmul
    //   60: ldc2_w 11
    //   63: ladd
    //   64: ldc2_w 281474976710655
    //   67: land
    //   68: lstore #4
    //   70: lload #6
    //   72: lload #4
    //   74: ladd
    //   75: lstore #6
    //   77: bipush #16
    //   79: newarray byte
    //   81: dup
    //   82: iconst_0
    //   83: bipush #48
    //   85: bastore
    //   86: dup
    //   87: iconst_1
    //   88: bipush #49
    //   90: bastore
    //   91: dup
    //   92: iconst_2
    //   93: bipush #50
    //   95: bastore
    //   96: dup
    //   97: iconst_3
    //   98: bipush #51
    //   100: bastore
    //   101: dup
    //   102: iconst_4
    //   103: bipush #52
    //   105: bastore
    //   106: dup
    //   107: iconst_5
    //   108: bipush #53
    //   110: bastore
    //   111: dup
    //   112: bipush #6
    //   114: bipush #54
    //   116: bastore
    //   117: dup
    //   118: bipush #7
    //   120: bipush #55
    //   122: bastore
    //   123: dup
    //   124: bipush #8
    //   126: bipush #56
    //   128: bastore
    //   129: dup
    //   130: bipush #9
    //   132: bipush #57
    //   134: bastore
    //   135: dup
    //   136: bipush #10
    //   138: bipush #97
    //   140: bastore
    //   141: dup
    //   142: bipush #11
    //   144: bipush #98
    //   146: bastore
    //   147: dup
    //   148: bipush #12
    //   150: bipush #99
    //   152: bastore
    //   153: dup
    //   154: bipush #13
    //   156: bipush #100
    //   158: bastore
    //   159: dup
    //   160: bipush #14
    //   162: bipush #101
    //   164: bastore
    //   165: dup
    //   166: bipush #15
    //   168: bipush #102
    //   170: bastore
    //   171: astore #8
    //   173: bipush #64
    //   175: newarray byte
    //   177: astore #9
    //   179: bipush #64
    //   181: istore #10
    //   183: bipush #16
    //   185: istore #11
    //   187: iload #11
    //   189: iconst_1
    //   190: isub
    //   191: i2l
    //   192: lstore #12
    //   194: aload #9
    //   196: iinc #10, -1
    //   199: iload #10
    //   201: aload #8
    //   203: lload #6
    //   205: lload #12
    //   207: land
    //   208: l2i
    //   209: baload
    //   210: bastore
    //   211: lload #6
    //   213: iconst_4
    //   214: lushr
    //   215: lstore #6
    //   217: lload #6
    //   219: lconst_0
    //   220: lcmp
    //   221: ifne -> 194
    //   224: bipush #64
    //   226: iload #10
    //   228: isub
    //   229: newarray byte
    //   231: astore_3
    //   232: iconst_0
    //   233: istore #14
    //   235: iload #14
    //   237: aload_3
    //   238: arraylength
    //   239: if_icmpge -> 261
    //   242: aload_3
    //   243: iload #14
    //   245: aload #9
    //   247: iload #10
    //   249: iload #14
    //   251: iadd
    //   252: baload
    //   253: bastore
    //   254: iinc #14, 1
    //   257: iload_2
    //   258: ifeq -> 235
    //   261: aload_3
    //   262: arraylength
    //   263: bipush #10
    //   265: if_icmplt -> 31
    //   268: getstatic burp/Zb4m.Zp : Ljava/lang/Object;
    //   271: checkcast java/math/BigInteger
    //   274: invokevirtual toByteArray : ()[B
    //   277: astore_3
    //   278: new java/lang/StringBuilder
    //   281: dup
    //   282: invokespecial <init> : ()V
    //   285: astore #5
    //   287: aload #5
    //   289: sipush #-3507
    //   292: sipush #-15350
    //   295: invokestatic a : (II)Ljava/lang/String;
    //   298: invokevirtual append : (Ljava/lang/String;)Ljava/lang/StringBuilder;
    //   301: pop
    //   302: aload_3
    //   303: astore #6
    //   305: aload #6
    //   307: arraylength
    //   308: istore #7
    //   310: iconst_0
    //   311: istore #8
    //   313: iload #8
    //   315: iload #7
    //   317: if_icmpge -> 343
    //   320: aload #6
    //   322: iload #8
    //   324: baload
    //   325: istore #9
    //   327: aload #5
    //   329: iload #9
    //   331: i2c
    //   332: invokevirtual append : (C)Ljava/lang/StringBuilder;
    //   335: pop
    //   336: iinc #8, 1
    //   339: iload_2
    //   340: ifeq -> 313
    //   343: aload #5
    //   345: sipush #-3506
    //   348: sipush #-453
    //   351: invokestatic a : (II)Ljava/lang/String;
    //   354: ldc ''
    //   356: invokestatic getProperty : (Ljava/lang/String;Ljava/lang/String;)Ljava/lang/String;
    //   359: invokevirtual toLowerCase : ()Ljava/lang/String;
    //   362: invokevirtual append : (Ljava/lang/String;)Ljava/lang/StringBuilder;
    //   365: pop
    //   366: aload #5
    //   368: sipush #-3519
    //   371: sipush #5678
    //   374: invokestatic a : (II)Ljava/lang/String;
    //   377: ldc ''
    //   379: invokestatic getProperty : (Ljava/lang/String;Ljava/lang/String;)Ljava/lang/String;
    //   382: invokevirtual toLowerCase : ()Ljava/lang/String;
    //   385: invokevirtual append : (Ljava/lang/String;)Ljava/lang/StringBuilder;
    //   388: pop
    //   389: aload #5
    //   391: invokevirtual toString : ()Ljava/lang/String;
    //   394: invokevirtual getBytes : ()[B
    //   397: astore #4
    //   399: aload #4
    //   401: astore_3
    //   402: aload_3
    //   403: arraylength
    //   404: bipush #8
    //   406: iadd
    //   407: bipush #6
    //   409: ishr
    //   410: iconst_1
    //   411: iadd
    //   412: bipush #16
    //   414: imul
    //   415: newarray int
    //   417: astore #5
    //   419: iconst_0
    //   420: istore #6
    //   422: iload #6
    //   424: aload_3
    //   425: arraylength
    //   426: if_icmpge -> 469
    //   429: aload_3
    //   430: iload #6
    //   432: baload
    //   433: sipush #255
    //   436: iand
    //   437: istore #7
    //   439: aload #5
    //   441: iload #6
    //   443: iconst_2
    //   444: ishr
    //   445: dup2
    //   446: iaload
    //   447: iload #7
    //   449: bipush #24
    //   451: iload #6
    //   453: iconst_4
    //   454: irem
    //   455: bipush #8
    //   457: imul
    //   458: isub
    //   459: ishl
    //   460: ior
    //   461: iastore
    //   462: iinc #6, 1
    //   465: iload_2
    //   466: ifeq -> 422
    //   469: aload #5
    //   471: iload #6
    //   473: iconst_2
    //   474: ishr
    //   475: dup2
    //   476: iaload
    //   477: sipush #128
    //   480: bipush #24
    //   482: iload #6
    //   484: iconst_4
    //   485: irem
    //   486: bipush #8
    //   488: imul
    //   489: isub
    //   490: ishl
    //   491: ior
    //   492: iastore
    //   493: aload #5
    //   495: aload #5
    //   497: arraylength
    //   498: iconst_1
    //   499: isub
    //   500: aload_3
    //   501: arraylength
    //   502: bipush #8
    //   504: imul
    //   505: iastore
    //   506: bipush #80
    //   508: newarray int
    //   510: astore #7
    //   512: ldc 1732584193
    //   514: istore #8
    //   516: ldc -271733879
    //   518: istore #9
    //   520: ldc -1732584194
    //   522: istore #10
    //   524: ldc 271733878
    //   526: istore #11
    //   528: ldc -1009589776
    //   530: istore #12
    //   532: iconst_0
    //   533: istore #6
    //   535: iload #6
    //   537: aload #5
    //   539: arraylength
    //   540: if_icmpge -> 862
    //   543: iload #8
    //   545: istore #13
    //   547: iload #9
    //   549: istore #14
    //   551: iload #10
    //   553: istore #15
    //   555: iload #11
    //   557: istore #16
    //   559: iload #12
    //   561: istore #17
    //   563: iconst_0
    //   564: istore #18
    //   566: iload #18
    //   568: bipush #80
    //   570: if_icmpge -> 820
    //   573: iload #18
    //   575: bipush #16
    //   577: if_icmpge -> 604
    //   580: aload #7
    //   582: iload #18
    //   584: aload #5
    //   586: iload #6
    //   588: iload #18
    //   590: iadd
    //   591: iaload
    //   592: iastore
    //   593: iload_2
    //   594: ifeq -> 659
    //   597: goto -> 604
    //   600: invokestatic a : (Ljava/lang/Throwable;)Ljava/lang/Throwable;
    //   603: athrow
    //   604: aload #7
    //   606: iload #18
    //   608: iconst_3
    //   609: isub
    //   610: iaload
    //   611: aload #7
    //   613: iload #18
    //   615: bipush #8
    //   617: isub
    //   618: iaload
    //   619: ixor
    //   620: aload #7
    //   622: iload #18
    //   624: bipush #14
    //   626: isub
    //   627: iaload
    //   628: ixor
    //   629: aload #7
    //   631: iload #18
    //   633: bipush #16
    //   635: isub
    //   636: iaload
    //   637: ixor
    //   638: istore #19
    //   640: iload #19
    //   642: iconst_1
    //   643: ishl
    //   644: iload #19
    //   646: bipush #31
    //   648: iushr
    //   649: ior
    //   650: istore #20
    //   652: aload #7
    //   654: iload #18
    //   656: iload #20
    //   658: iastore
    //   659: iload #8
    //   661: iconst_5
    //   662: ishl
    //   663: iload #8
    //   665: bipush #27
    //   667: iushr
    //   668: ior
    //   669: istore #19
    //   671: iload #19
    //   673: iload #12
    //   675: iadd
    //   676: aload #7
    //   678: iload #18
    //   680: iaload
    //   681: iadd
    //   682: iload #18
    //   684: bipush #20
    //   686: if_icmpge -> 712
    //   689: ldc 1518500249
    //   691: iload #9
    //   693: iload #10
    //   695: iand
    //   696: iload #9
    //   698: iconst_m1
    //   699: ixor
    //   700: iload #11
    //   702: iand
    //   703: ior
    //   704: iadd
    //   705: goto -> 782
    //   708: invokestatic a : (Ljava/lang/Throwable;)Ljava/lang/Throwable;
    //   711: athrow
    //   712: iload #18
    //   714: bipush #40
    //   716: if_icmpge -> 737
    //   719: ldc 1859775393
    //   721: iload #9
    //   723: iload #10
    //   725: ixor
    //   726: iload #11
    //   728: ixor
    //   729: iadd
    //   730: goto -> 782
    //   733: invokestatic a : (Ljava/lang/Throwable;)Ljava/lang/Throwable;
    //   736: athrow
    //   737: iload #18
    //   739: bipush #60
    //   741: if_icmpge -> 771
    //   744: ldc -1894007588
    //   746: iload #9
    //   748: iload #10
    //   750: iand
    //   751: iload #9
    //   753: iload #11
    //   755: iand
    //   756: ior
    //   757: iload #10
    //   759: iload #11
    //   761: iand
    //   762: ior
    //   763: iadd
    //   764: goto -> 782
    //   767: invokestatic a : (Ljava/lang/Throwable;)Ljava/lang/Throwable;
    //   770: athrow
    //   771: ldc -899497514
    //   773: iload #9
    //   775: iload #10
    //   777: ixor
    //   778: iload #11
    //   780: ixor
    //   781: iadd
    //   782: iadd
    //   783: istore #20
    //   785: iload #11
    //   787: istore #12
    //   789: iload #10
    //   791: istore #11
    //   793: iload #9
    //   795: bipush #30
    //   797: ishl
    //   798: iload #9
    //   800: iconst_2
    //   801: iushr
    //   802: ior
    //   803: istore #10
    //   805: iload #8
    //   807: istore #9
    //   809: iload #20
    //   811: istore #8
    //   813: iinc #18, 1
    //   816: iload_2
    //   817: ifeq -> 566
    //   820: iload #8
    //   822: iload #13
    //   824: iadd
    //   825: istore #8
    //   827: iload #9
    //   829: iload #14
    //   831: iadd
    //   832: istore #9
    //   834: iload #10
    //   836: iload #15
    //   838: iadd
    //   839: istore #10
    //   841: iload #11
    //   843: iload #16
    //   845: iadd
    //   846: istore #11
    //   848: iload #12
    //   850: iload #17
    //   852: iadd
    //   853: istore #12
    //   855: iinc #6, 16
    //   858: iload_2
    //   859: ifeq -> 535
    //   862: iconst_5
    //   863: newarray int
    //   865: dup
    //   866: iconst_0
    //   867: iload #8
    //   869: iastore
    //   870: dup
    //   871: iconst_1
    //   872: iload #9
    //   874: iastore
    //   875: dup
    //   876: iconst_2
    //   877: iload #10
    //   879: iastore
    //   880: dup
    //   881: iconst_3
    //   882: iload #11
    //   884: iastore
    //   885: dup
    //   886: iconst_4
    //   887: iload #12
    //   889: iastore
    //   890: astore #13
    //   892: bipush #20
    //   894: newarray byte
    //   896: astore #14
    //   898: iconst_0
    //   899: istore #15
    //   901: iload #15
    //   903: bipush #20
    //   905: if_icmpge -> 946
    //   908: aload #13
    //   910: iload #15
    //   912: iconst_4
    //   913: idiv
    //   914: iaload
    //   915: istore #16
    //   917: iconst_3
    //   918: iload #15
    //   920: iconst_4
    //   921: irem
    //   922: isub
    //   923: bipush #8
    //   925: imul
    //   926: istore #17
    //   928: aload #14
    //   930: iload #15
    //   932: iload #16
    //   934: iload #17
    //   936: iushr
    //   937: i2b
    //   938: bastore
    //   939: iinc #15, 1
    //   942: iload_2
    //   943: ifeq -> 901
    //   946: aload #14
    //   948: astore #4
    //   950: new java/io/ByteArrayOutputStream
    //   953: dup
    //   954: invokespecial <init> : ()V
    //   957: astore_3
    //   958: getstatic burp/Zll8.ZZ : Ljava/lang/String;
    //   961: astore #4
    //   963: iconst_0
    //   964: istore #5
    //   966: iload #5
    //   968: aload #4
    //   970: invokevirtual length : ()I
    //   973: if_icmpge -> 1003
    //   976: aload_3
    //   977: aload #4
    //   979: iload #5
    //   981: iload #5
    //   983: iconst_2
    //   984: iadd
    //   985: invokevirtual substring : (II)Ljava/lang/String;
    //   988: bipush #16
    //   990: invokestatic parseInt : (Ljava/lang/String;I)I
    //   993: invokevirtual write : (I)V
    //   996: iinc #5, 2
    //   999: iload_2
    //   1000: ifeq -> 966
    //   1003: aload_3
    //   1004: invokevirtual toByteArray : ()[B
    //   1007: astore #5
    //   1009: getstatic burp/Zml.ZR : Ljava/lang/Object;
    //   1012: checkcast java/math/BigInteger
    //   1015: invokevirtual toByteArray : ()[B
    //   1018: astore #6
    //   1020: sipush #256
    //   1023: newarray byte
    //   1025: astore #8
    //   1027: sipush #256
    //   1030: newarray int
    //   1032: astore #9
    //   1034: sipush #256
    //   1037: newarray int
    //   1039: astore #10
    //   1041: sipush #256
    //   1044: newarray int
    //   1046: astore #11
    //   1048: sipush #256
    //   1051: newarray int
    //   1053: astore #12
    //   1055: bipush #10
    //   1057: newarray int
    //   1059: astore #13
    //   1061: sipush #283
    //   1064: istore #14
    //   1066: iconst_0
    //   1067: istore #16
    //   1069: iload #16
    //   1071: sipush #256
    //   1074: if_icmpge -> 1308
    //   1077: sipush #-3512
    //   1080: sipush #24502
    //   1083: invokestatic a : (II)Ljava/lang/String;
    //   1086: iload #16
    //   1088: iconst_1
    //   1089: iushr
    //   1090: invokevirtual charAt : (I)C
    //   1093: istore #25
    //   1095: iload #16
    //   1097: iconst_1
    //   1098: iand
    //   1099: ifne -> 1114
    //   1102: iload #25
    //   1104: bipush #8
    //   1106: iushr
    //   1107: goto -> 1116
    //   1110: invokestatic a : (Ljava/lang/Throwable;)Ljava/lang/Throwable;
    //   1113: athrow
    //   1114: iload #25
    //   1116: i2b
    //   1117: sipush #255
    //   1120: iand
    //   1121: istore #15
    //   1123: iload #16
    //   1125: iconst_1
    //   1126: ishl
    //   1127: istore #17
    //   1129: iload #17
    //   1131: sipush #256
    //   1134: if_icmplt -> 1144
    //   1137: iload #17
    //   1139: iload #14
    //   1141: ixor
    //   1142: istore #17
    //   1144: iload #17
    //   1146: iconst_1
    //   1147: ishl
    //   1148: istore #18
    //   1150: iload #18
    //   1152: sipush #256
    //   1155: if_icmplt -> 1165
    //   1158: iload #18
    //   1160: iload #14
    //   1162: ixor
    //   1163: istore #18
    //   1165: iload #18
    //   1167: iconst_1
    //   1168: ishl
    //   1169: istore #19
    //   1171: iload #19
    //   1173: sipush #256
    //   1176: if_icmplt -> 1186
    //   1179: iload #19
    //   1181: iload #14
    //   1183: ixor
    //   1184: istore #19
    //   1186: iload #19
    //   1188: iload #16
    //   1190: ixor
    //   1191: istore #20
    //   1193: iload #20
    //   1195: iload #17
    //   1197: ixor
    //   1198: istore #21
    //   1200: iload #20
    //   1202: iload #18
    //   1204: ixor
    //   1205: istore #22
    //   1207: iload #19
    //   1209: iload #18
    //   1211: ixor
    //   1212: iload #17
    //   1214: ixor
    //   1215: istore #23
    //   1217: aload #8
    //   1219: iload #16
    //   1221: iload #15
    //   1223: i2b
    //   1224: bastore
    //   1225: aload #9
    //   1227: iload #15
    //   1229: iload #23
    //   1231: bipush #24
    //   1233: ishl
    //   1234: iload #20
    //   1236: bipush #16
    //   1238: ishl
    //   1239: ior
    //   1240: iload #22
    //   1242: bipush #8
    //   1244: ishl
    //   1245: ior
    //   1246: iload #21
    //   1248: ior
    //   1249: dup
    //   1250: istore #24
    //   1252: iastore
    //   1253: aload #10
    //   1255: iload #15
    //   1257: iload #24
    //   1259: bipush #8
    //   1261: iushr
    //   1262: iload #24
    //   1264: bipush #24
    //   1266: ishl
    //   1267: ior
    //   1268: iastore
    //   1269: aload #11
    //   1271: iload #15
    //   1273: iload #24
    //   1275: bipush #16
    //   1277: iushr
    //   1278: iload #24
    //   1280: bipush #16
    //   1282: ishl
    //   1283: ior
    //   1284: iastore
    //   1285: aload #12
    //   1287: iload #15
    //   1289: iload #24
    //   1291: bipush #24
    //   1293: iushr
    //   1294: iload #24
    //   1296: bipush #8
    //   1298: ishl
    //   1299: ior
    //   1300: iastore
    //   1301: iinc #16, 1
    //   1304: iload_2
    //   1305: ifeq -> 1069
    //   1308: iconst_1
    //   1309: istore #25
    //   1311: aload #13
    //   1313: iconst_0
    //   1314: iload #25
    //   1316: bipush #24
    //   1318: ishl
    //   1319: iastore
    //   1320: iconst_1
    //   1321: istore #26
    //   1323: iload #26
    //   1325: bipush #10
    //   1327: if_icmpge -> 1368
    //   1330: iload #25
    //   1332: iconst_1
    //   1333: ishl
    //   1334: istore #25
    //   1336: iload #25
    //   1338: sipush #256
    //   1341: if_icmplt -> 1351
    //   1344: iload #25
    //   1346: iload #14
    //   1348: ixor
    //   1349: istore #25
    //   1351: aload #13
    //   1353: iload #26
    //   1355: iload #25
    //   1357: bipush #24
    //   1359: ishl
    //   1360: iastore
    //   1361: iinc #26, 1
    //   1364: iload_2
    //   1365: ifeq -> 1323
    //   1368: iconst_4
    //   1369: istore #26
    //   1371: iload #26
    //   1373: bipush #6
    //   1375: iadd
    //   1376: istore #27
    //   1378: iconst_4
    //   1379: iload #27
    //   1381: iconst_1
    //   1382: iadd
    //   1383: imul
    //   1384: istore #28
    //   1386: iload #28
    //   1388: newarray int
    //   1390: astore #29
    //   1392: iload #28
    //   1394: newarray int
    //   1396: astore #30
    //   1398: iconst_0
    //   1399: istore #25
    //   1401: iconst_0
    //   1402: istore #32
    //   1404: iconst_0
    //   1405: istore #33
    //   1407: iload #32
    //   1409: iload #26
    //   1411: if_icmpge -> 1479
    //   1414: aload #29
    //   1416: iload #32
    //   1418: aload #5
    //   1420: iload #33
    //   1422: baload
    //   1423: bipush #24
    //   1425: ishl
    //   1426: aload #5
    //   1428: iload #33
    //   1430: iconst_1
    //   1431: iadd
    //   1432: baload
    //   1433: sipush #255
    //   1436: iand
    //   1437: bipush #16
    //   1439: ishl
    //   1440: ior
    //   1441: aload #5
    //   1443: iload #33
    //   1445: iconst_2
    //   1446: iadd
    //   1447: baload
    //   1448: sipush #255
    //   1451: iand
    //   1452: bipush #8
    //   1454: ishl
    //   1455: ior
    //   1456: aload #5
    //   1458: iload #33
    //   1460: iconst_3
    //   1461: iadd
    //   1462: baload
    //   1463: sipush #255
    //   1466: iand
    //   1467: ior
    //   1468: iastore
    //   1469: iinc #32, 1
    //   1472: iinc #33, 4
    //   1475: iload_2
    //   1476: ifeq -> 1407
    //   1479: iload #26
    //   1481: istore #32
    //   1483: iconst_0
    //   1484: istore #33
    //   1486: iload #32
    //   1488: iload #28
    //   1490: if_icmpge -> 1617
    //   1493: aload #29
    //   1495: iload #32
    //   1497: iconst_1
    //   1498: isub
    //   1499: iaload
    //   1500: istore #31
    //   1502: iload #33
    //   1504: ifne -> 1591
    //   1507: iload #26
    //   1509: istore #33
    //   1511: aload #8
    //   1513: iload #31
    //   1515: bipush #16
    //   1517: iushr
    //   1518: sipush #255
    //   1521: iand
    //   1522: baload
    //   1523: bipush #24
    //   1525: ishl
    //   1526: aload #8
    //   1528: iload #31
    //   1530: bipush #8
    //   1532: iushr
    //   1533: sipush #255
    //   1536: iand
    //   1537: baload
    //   1538: sipush #255
    //   1541: iand
    //   1542: bipush #16
    //   1544: ishl
    //   1545: ior
    //   1546: aload #8
    //   1548: iload #31
    //   1550: sipush #255
    //   1553: iand
    //   1554: baload
    //   1555: sipush #255
    //   1558: iand
    //   1559: bipush #8
    //   1561: ishl
    //   1562: ior
    //   1563: aload #8
    //   1565: iload #31
    //   1567: bipush #24
    //   1569: iushr
    //   1570: baload
    //   1571: sipush #255
    //   1574: iand
    //   1575: ior
    //   1576: istore #31
    //   1578: iload #31
    //   1580: aload #13
    //   1582: iload #25
    //   1584: iinc #25, 1
    //   1587: iaload
    //   1588: ixor
    //   1589: istore #31
    //   1591: aload #29
    //   1593: iload #32
    //   1595: aload #29
    //   1597: iload #32
    //   1599: iload #26
    //   1601: isub
    //   1602: iaload
    //   1603: iload #31
    //   1605: ixor
    //   1606: iastore
    //   1607: iinc #32, 1
    //   1610: iinc #33, -1
    //   1613: iload_2
    //   1614: ifeq -> 1486
    //   1617: iconst_0
    //   1618: istore #32
    //   1620: iconst_4
    //   1621: iload #27
    //   1623: imul
    //   1624: istore #33
    //   1626: aload #30
    //   1628: iload #32
    //   1630: aload #29
    //   1632: iload #33
    //   1634: iaload
    //   1635: iastore
    //   1636: aload #30
    //   1638: iload #32
    //   1640: iconst_1
    //   1641: iadd
    //   1642: aload #29
    //   1644: iload #33
    //   1646: iconst_1
    //   1647: iadd
    //   1648: iaload
    //   1649: iastore
    //   1650: aload #30
    //   1652: iload #32
    //   1654: iconst_2
    //   1655: iadd
    //   1656: aload #29
    //   1658: iload #33
    //   1660: iconst_2
    //   1661: iadd
    //   1662: iaload
    //   1663: iastore
    //   1664: aload #30
    //   1666: iload #32
    //   1668: iconst_3
    //   1669: iadd
    //   1670: aload #29
    //   1672: iload #33
    //   1674: iconst_3
    //   1675: iadd
    //   1676: iaload
    //   1677: iastore
    //   1678: iinc #32, 4
    //   1681: iinc #33, -4
    //   1684: iconst_1
    //   1685: istore #35
    //   1687: iload #35
    //   1689: iload #27
    //   1691: if_icmpge -> 2055
    //   1694: aload #29
    //   1696: iload #33
    //   1698: iaload
    //   1699: istore #34
    //   1701: aload #30
    //   1703: iload #32
    //   1705: aload #9
    //   1707: aload #8
    //   1709: iload #34
    //   1711: bipush #24
    //   1713: iushr
    //   1714: baload
    //   1715: sipush #255
    //   1718: iand
    //   1719: iaload
    //   1720: aload #10
    //   1722: aload #8
    //   1724: iload #34
    //   1726: bipush #16
    //   1728: iushr
    //   1729: sipush #255
    //   1732: iand
    //   1733: baload
    //   1734: sipush #255
    //   1737: iand
    //   1738: iaload
    //   1739: ixor
    //   1740: aload #11
    //   1742: aload #8
    //   1744: iload #34
    //   1746: bipush #8
    //   1748: iushr
    //   1749: sipush #255
    //   1752: iand
    //   1753: baload
    //   1754: sipush #255
    //   1757: iand
    //   1758: iaload
    //   1759: ixor
    //   1760: aload #12
    //   1762: aload #8
    //   1764: iload #34
    //   1766: sipush #255
    //   1769: iand
    //   1770: baload
    //   1771: sipush #255
    //   1774: iand
    //   1775: iaload
    //   1776: ixor
    //   1777: iastore
    //   1778: aload #29
    //   1780: iload #33
    //   1782: iconst_1
    //   1783: iadd
    //   1784: iaload
    //   1785: istore #34
    //   1787: aload #30
    //   1789: iload #32
    //   1791: iconst_1
    //   1792: iadd
    //   1793: aload #9
    //   1795: aload #8
    //   1797: iload #34
    //   1799: bipush #24
    //   1801: iushr
    //   1802: baload
    //   1803: sipush #255
    //   1806: iand
    //   1807: iaload
    //   1808: aload #10
    //   1810: aload #8
    //   1812: iload #34
    //   1814: bipush #16
    //   1816: iushr
    //   1817: sipush #255
    //   1820: iand
    //   1821: baload
    //   1822: sipush #255
    //   1825: iand
    //   1826: iaload
    //   1827: ixor
    //   1828: aload #11
    //   1830: aload #8
    //   1832: iload #34
    //   1834: bipush #8
    //   1836: iushr
    //   1837: sipush #255
    //   1840: iand
    //   1841: baload
    //   1842: sipush #255
    //   1845: iand
    //   1846: iaload
    //   1847: ixor
    //   1848: aload #12
    //   1850: aload #8
    //   1852: iload #34
    //   1854: sipush #255
    //   1857: iand
    //   1858: baload
    //   1859: sipush #255
    //   1862: iand
    //   1863: iaload
    //   1864: ixor
    //   1865: iastore
    //   1866: aload #29
    //   1868: iload #33
    //   1870: iconst_2
    //   1871: iadd
    //   1872: iaload
    //   1873: istore #34
    //   1875: aload #30
    //   1877: iload #32
    //   1879: iconst_2
    //   1880: iadd
    //   1881: aload #9
    //   1883: aload #8
    //   1885: iload #34
    //   1887: bipush #24
    //   1889: iushr
    //   1890: baload
    //   1891: sipush #255
    //   1894: iand
    //   1895: iaload
    //   1896: aload #10
    //   1898: aload #8
    //   1900: iload #34
    //   1902: bipush #16
    //   1904: iushr
    //   1905: sipush #255
    //   1908: iand
    //   1909: baload
    //   1910: sipush #255
    //   1913: iand
    //   1914: iaload
    //   1915: ixor
    //   1916: aload #11
    //   1918: aload #8
    //   1920: iload #34
    //   1922: bipush #8
    //   1924: iushr
    //   1925: sipush #255
    //   1928: iand
    //   1929: baload
    //   1930: sipush #255
    //   1933: iand
    //   1934: iaload
    //   1935: ixor
    //   1936: aload #12
    //   1938: aload #8
    //   1940: iload #34
    //   1942: sipush #255
    //   1945: iand
    //   1946: baload
    //   1947: sipush #255
    //   1950: iand
    //   1951: iaload
    //   1952: ixor
    //   1953: iastore
    //   1954: aload #29
    //   1956: iload #33
    //   1958: iconst_3
    //   1959: iadd
    //   1960: iaload
    //   1961: istore #34
    //   1963: aload #30
    //   1965: iload #32
    //   1967: iconst_3
    //   1968: iadd
    //   1969: aload #9
    //   1971: aload #8
    //   1973: iload #34
    //   1975: bipush #24
    //   1977: iushr
    //   1978: baload
    //   1979: sipush #255
    //   1982: iand
    //   1983: iaload
    //   1984: aload #10
    //   1986: aload #8
    //   1988: iload #34
    //   1990: bipush #16
    //   1992: iushr
    //   1993: sipush #255
    //   1996: iand
    //   1997: baload
    //   1998: sipush #255
    //   2001: iand
    //   2002: iaload
    //   2003: ixor
    //   2004: aload #11
    //   2006: aload #8
    //   2008: iload #34
    //   2010: bipush #8
    //   2012: iushr
    //   2013: sipush #255
    //   2016: iand
    //   2017: baload
    //   2018: sipush #255
    //   2021: iand
    //   2022: iaload
    //   2023: ixor
    //   2024: aload #12
    //   2026: aload #8
    //   2028: iload #34
    //   2030: sipush #255
    //   2033: iand
    //   2034: baload
    //   2035: sipush #255
    //   2038: iand
    //   2039: iaload
    //   2040: ixor
    //   2041: iastore
    //   2042: iinc #32, 4
    //   2045: iinc #33, -4
    //   2048: iinc #35, 1
    //   2051: iload_2
    //   2052: ifeq -> 1687
    //   2055: aload #30
    //   2057: iload #32
    //   2059: aload #29
    //   2061: iload #33
    //   2063: iaload
    //   2064: iastore
    //   2065: aload #30
    //   2067: iload #32
    //   2069: iconst_1
    //   2070: iadd
    //   2071: aload #29
    //   2073: iload #33
    //   2075: iconst_1
    //   2076: iadd
    //   2077: iaload
    //   2078: iastore
    //   2079: aload #30
    //   2081: iload #32
    //   2083: iconst_2
    //   2084: iadd
    //   2085: aload #29
    //   2087: iload #33
    //   2089: iconst_2
    //   2090: iadd
    //   2091: iaload
    //   2092: iastore
    //   2093: aload #30
    //   2095: iload #32
    //   2097: iconst_3
    //   2098: iadd
    //   2099: aload #29
    //   2101: iload #33
    //   2103: iconst_3
    //   2104: iadd
    //   2105: iaload
    //   2106: iastore
    //   2107: iconst_0
    //   2108: newarray byte
    //   2110: astore #35
    //   2112: aload #6
    //   2114: arraylength
    //   2115: bipush #16
    //   2117: irem
    //   2118: ifeq -> 2142
    //   2121: new java/lang/Exception
    //   2124: dup
    //   2125: sipush #-3516
    //   2128: sipush #7232
    //   2131: invokestatic a : (II)Ljava/lang/String;
    //   2134: invokespecial <init> : (Ljava/lang/String;)V
    //   2137: athrow
    //   2138: invokestatic a : (Ljava/lang/Throwable;)Ljava/lang/Throwable;
    //   2141: athrow
    //   2142: bipush #10
    //   2144: istore #36
    //   2146: sipush #-3513
    //   2149: sipush #256
    //   2152: newarray byte
    //   2154: astore #37
    //   2156: sipush #3941
    //   2159: sipush #256
    //   2162: newarray int
    //   2164: astore #38
    //   2166: sipush #256
    //   2169: newarray int
    //   2171: astore #39
    //   2173: sipush #256
    //   2176: newarray int
    //   2178: astore #40
    //   2180: sipush #256
    //   2183: newarray int
    //   2185: astore #41
    //   2187: sipush #283
    //   2190: istore #14
    //   2192: invokestatic a : (II)Ljava/lang/String;
    //   2195: astore #42
    //   2197: iconst_0
    //   2198: istore #16
    //   2200: iload #16
    //   2202: sipush #256
    //   2205: if_icmpge -> 2432
    //   2208: aload #42
    //   2210: iload #16
    //   2212: iconst_1
    //   2213: iushr
    //   2214: invokevirtual charAt : (I)C
    //   2217: istore #43
    //   2219: iload #16
    //   2221: iconst_1
    //   2222: iand
    //   2223: ifne -> 2238
    //   2226: iload #43
    //   2228: bipush #8
    //   2230: iushr
    //   2231: goto -> 2240
    //   2234: invokestatic a : (Ljava/lang/Throwable;)Ljava/lang/Throwable;
    //   2237: athrow
    //   2238: iload #43
    //   2240: i2b
    //   2241: sipush #255
    //   2244: iand
    //   2245: istore #15
    //   2247: iload #16
    //   2249: iconst_1
    //   2250: ishl
    //   2251: istore #17
    //   2253: iload #17
    //   2255: sipush #256
    //   2258: if_icmplt -> 2268
    //   2261: iload #17
    //   2263: iload #14
    //   2265: ixor
    //   2266: istore #17
    //   2268: iload #17
    //   2270: iconst_1
    //   2271: ishl
    //   2272: istore #18
    //   2274: iload #18
    //   2276: sipush #256
    //   2279: if_icmplt -> 2289
    //   2282: iload #18
    //   2284: iload #14
    //   2286: ixor
    //   2287: istore #18
    //   2289: iload #18
    //   2291: iconst_1
    //   2292: ishl
    //   2293: istore #19
    //   2295: iload #19
    //   2297: sipush #256
    //   2300: if_icmplt -> 2310
    //   2303: iload #19
    //   2305: iload #14
    //   2307: ixor
    //   2308: istore #19
    //   2310: iload #19
    //   2312: iload #16
    //   2314: ixor
    //   2315: istore #20
    //   2317: iload #20
    //   2319: iload #17
    //   2321: ixor
    //   2322: istore #21
    //   2324: iload #20
    //   2326: iload #18
    //   2328: ixor
    //   2329: istore #22
    //   2331: iload #19
    //   2333: iload #18
    //   2335: ixor
    //   2336: iload #17
    //   2338: ixor
    //   2339: istore #23
    //   2341: aload #37
    //   2343: iload #15
    //   2345: iload #16
    //   2347: i2b
    //   2348: bastore
    //   2349: aload #38
    //   2351: iload #15
    //   2353: iload #23
    //   2355: bipush #24
    //   2357: ishl
    //   2358: iload #20
    //   2360: bipush #16
    //   2362: ishl
    //   2363: ior
    //   2364: iload #22
    //   2366: bipush #8
    //   2368: ishl
    //   2369: ior
    //   2370: iload #21
    //   2372: ior
    //   2373: dup
    //   2374: istore #24
    //   2376: iastore
    //   2377: aload #39
    //   2379: iload #15
    //   2381: iload #24
    //   2383: bipush #8
    //   2385: iushr
    //   2386: iload #24
    //   2388: bipush #24
    //   2390: ishl
    //   2391: ior
    //   2392: iastore
    //   2393: aload #40
    //   2395: iload #15
    //   2397: iload #24
    //   2399: bipush #16
    //   2401: iushr
    //   2402: iload #24
    //   2404: bipush #16
    //   2406: ishl
    //   2407: ior
    //   2408: iastore
    //   2409: aload #41
    //   2411: iload #15
    //   2413: iload #24
    //   2415: bipush #24
    //   2417: iushr
    //   2418: iload #24
    //   2420: bipush #8
    //   2422: ishl
    //   2423: ior
    //   2424: iastore
    //   2425: iinc #16, 1
    //   2428: iload_2
    //   2429: ifeq -> 2200
    //   2432: aload #6
    //   2434: arraylength
    //   2435: newarray byte
    //   2437: astore #43
    //   2439: iconst_0
    //   2440: istore #44
    //   2442: iload #44
    //   2444: aload #6
    //   2446: arraylength
    //   2447: bipush #16
    //   2449: idiv
    //   2450: if_icmpge -> 3364
    //   2453: bipush #16
    //   2455: newarray byte
    //   2457: astore #45
    //   2459: bipush #16
    //   2461: newarray byte
    //   2463: astore #46
    //   2465: iconst_0
    //   2466: istore #47
    //   2468: iload #47
    //   2470: bipush #16
    //   2472: if_icmpge -> 2498
    //   2475: aload #45
    //   2477: iload #47
    //   2479: aload #6
    //   2481: iload #47
    //   2483: iload #44
    //   2485: bipush #16
    //   2487: imul
    //   2488: iadd
    //   2489: baload
    //   2490: bastore
    //   2491: iinc #47, 1
    //   2494: iload_2
    //   2495: ifeq -> 2468
    //   2498: iconst_0
    //   2499: istore #47
    //   2501: aload #45
    //   2503: iconst_0
    //   2504: baload
    //   2505: bipush #24
    //   2507: ishl
    //   2508: aload #45
    //   2510: iconst_1
    //   2511: baload
    //   2512: sipush #255
    //   2515: iand
    //   2516: bipush #16
    //   2518: ishl
    //   2519: ior
    //   2520: aload #45
    //   2522: iconst_2
    //   2523: baload
    //   2524: sipush #255
    //   2527: iand
    //   2528: bipush #8
    //   2530: ishl
    //   2531: ior
    //   2532: aload #45
    //   2534: iconst_3
    //   2535: baload
    //   2536: sipush #255
    //   2539: iand
    //   2540: ior
    //   2541: aload #30
    //   2543: iconst_0
    //   2544: iaload
    //   2545: ixor
    //   2546: istore #49
    //   2548: aload #45
    //   2550: iconst_4
    //   2551: baload
    //   2552: bipush #24
    //   2554: ishl
    //   2555: aload #45
    //   2557: iconst_5
    //   2558: baload
    //   2559: sipush #255
    //   2562: iand
    //   2563: bipush #16
    //   2565: ishl
    //   2566: ior
    //   2567: aload #45
    //   2569: bipush #6
    //   2571: baload
    //   2572: sipush #255
    //   2575: iand
    //   2576: bipush #8
    //   2578: ishl
    //   2579: ior
    //   2580: aload #45
    //   2582: bipush #7
    //   2584: baload
    //   2585: sipush #255
    //   2588: iand
    //   2589: ior
    //   2590: aload #30
    //   2592: iconst_1
    //   2593: iaload
    //   2594: ixor
    //   2595: istore #50
    //   2597: aload #45
    //   2599: bipush #8
    //   2601: baload
    //   2602: bipush #24
    //   2604: ishl
    //   2605: aload #45
    //   2607: bipush #9
    //   2609: baload
    //   2610: sipush #255
    //   2613: iand
    //   2614: bipush #16
    //   2616: ishl
    //   2617: ior
    //   2618: aload #45
    //   2620: bipush #10
    //   2622: baload
    //   2623: sipush #255
    //   2626: iand
    //   2627: bipush #8
    //   2629: ishl
    //   2630: ior
    //   2631: aload #45
    //   2633: bipush #11
    //   2635: baload
    //   2636: sipush #255
    //   2639: iand
    //   2640: ior
    //   2641: aload #30
    //   2643: iconst_2
    //   2644: iaload
    //   2645: ixor
    //   2646: istore #51
    //   2648: aload #45
    //   2650: bipush #12
    //   2652: baload
    //   2653: bipush #24
    //   2655: ishl
    //   2656: aload #45
    //   2658: bipush #13
    //   2660: baload
    //   2661: sipush #255
    //   2664: iand
    //   2665: bipush #16
    //   2667: ishl
    //   2668: ior
    //   2669: aload #45
    //   2671: bipush #14
    //   2673: baload
    //   2674: sipush #255
    //   2677: iand
    //   2678: bipush #8
    //   2680: ishl
    //   2681: ior
    //   2682: aload #45
    //   2684: bipush #15
    //   2686: baload
    //   2687: sipush #255
    //   2690: iand
    //   2691: ior
    //   2692: aload #30
    //   2694: iconst_3
    //   2695: iaload
    //   2696: ixor
    //   2697: istore #52
    //   2699: iconst_1
    //   2700: istore #53
    //   2702: iload #53
    //   2704: iload #36
    //   2706: if_icmpge -> 2949
    //   2709: iinc #47, 4
    //   2712: aload #38
    //   2714: iload #49
    //   2716: bipush #24
    //   2718: iushr
    //   2719: iaload
    //   2720: aload #39
    //   2722: iload #52
    //   2724: bipush #16
    //   2726: iushr
    //   2727: sipush #255
    //   2730: iand
    //   2731: iaload
    //   2732: ixor
    //   2733: aload #40
    //   2735: iload #51
    //   2737: bipush #8
    //   2739: iushr
    //   2740: sipush #255
    //   2743: iand
    //   2744: iaload
    //   2745: ixor
    //   2746: aload #41
    //   2748: iload #50
    //   2750: sipush #255
    //   2753: iand
    //   2754: iaload
    //   2755: ixor
    //   2756: aload #30
    //   2758: iload #47
    //   2760: iaload
    //   2761: ixor
    //   2762: istore #54
    //   2764: aload #38
    //   2766: iload #50
    //   2768: bipush #24
    //   2770: iushr
    //   2771: iaload
    //   2772: aload #39
    //   2774: iload #49
    //   2776: bipush #16
    //   2778: iushr
    //   2779: sipush #255
    //   2782: iand
    //   2783: iaload
    //   2784: ixor
    //   2785: aload #40
    //   2787: iload #52
    //   2789: bipush #8
    //   2791: iushr
    //   2792: sipush #255
    //   2795: iand
    //   2796: iaload
    //   2797: ixor
    //   2798: aload #41
    //   2800: iload #51
    //   2802: sipush #255
    //   2805: iand
    //   2806: iaload
    //   2807: ixor
    //   2808: aload #30
    //   2810: iload #47
    //   2812: iconst_1
    //   2813: iadd
    //   2814: iaload
    //   2815: ixor
    //   2816: istore #55
    //   2818: aload #38
    //   2820: iload #51
    //   2822: bipush #24
    //   2824: iushr
    //   2825: iaload
    //   2826: aload #39
    //   2828: iload #50
    //   2830: bipush #16
    //   2832: iushr
    //   2833: sipush #255
    //   2836: iand
    //   2837: iaload
    //   2838: ixor
    //   2839: aload #40
    //   2841: iload #49
    //   2843: bipush #8
    //   2845: iushr
    //   2846: sipush #255
    //   2849: iand
    //   2850: iaload
    //   2851: ixor
    //   2852: aload #41
    //   2854: iload #52
    //   2856: sipush #255
    //   2859: iand
    //   2860: iaload
    //   2861: ixor
    //   2862: aload #30
    //   2864: iload #47
    //   2866: iconst_2
    //   2867: iadd
    //   2868: iaload
    //   2869: ixor
    //   2870: istore #56
    //   2872: aload #38
    //   2874: iload #52
    //   2876: bipush #24
    //   2878: iushr
    //   2879: iaload
    //   2880: aload #39
    //   2882: iload #51
    //   2884: bipush #16
    //   2886: iushr
    //   2887: sipush #255
    //   2890: iand
    //   2891: iaload
    //   2892: ixor
    //   2893: aload #40
    //   2895: iload #50
    //   2897: bipush #8
    //   2899: iushr
    //   2900: sipush #255
    //   2903: iand
    //   2904: iaload
    //   2905: ixor
    //   2906: aload #41
    //   2908: iload #49
    //   2910: sipush #255
    //   2913: iand
    //   2914: iaload
    //   2915: ixor
    //   2916: aload #30
    //   2918: iload #47
    //   2920: iconst_3
    //   2921: iadd
    //   2922: iaload
    //   2923: ixor
    //   2924: istore #57
    //   2926: iload #54
    //   2928: istore #49
    //   2930: iload #55
    //   2932: istore #50
    //   2934: iload #56
    //   2936: istore #51
    //   2938: iload #57
    //   2940: istore #52
    //   2942: iinc #53, 1
    //   2945: iload_2
    //   2946: ifeq -> 2702
    //   2949: iinc #47, 4
    //   2952: aload #30
    //   2954: iload #47
    //   2956: iaload
    //   2957: istore #48
    //   2959: aload #46
    //   2961: iconst_0
    //   2962: aload #37
    //   2964: iload #49
    //   2966: bipush #24
    //   2968: iushr
    //   2969: baload
    //   2970: iload #48
    //   2972: bipush #24
    //   2974: iushr
    //   2975: ixor
    //   2976: i2b
    //   2977: bastore
    //   2978: aload #46
    //   2980: iconst_1
    //   2981: aload #37
    //   2983: iload #52
    //   2985: bipush #16
    //   2987: iushr
    //   2988: sipush #255
    //   2991: iand
    //   2992: baload
    //   2993: iload #48
    //   2995: bipush #16
    //   2997: iushr
    //   2998: ixor
    //   2999: i2b
    //   3000: bastore
    //   3001: aload #46
    //   3003: iconst_2
    //   3004: aload #37
    //   3006: iload #51
    //   3008: bipush #8
    //   3010: iushr
    //   3011: sipush #255
    //   3014: iand
    //   3015: baload
    //   3016: iload #48
    //   3018: bipush #8
    //   3020: iushr
    //   3021: ixor
    //   3022: i2b
    //   3023: bastore
    //   3024: aload #46
    //   3026: iconst_3
    //   3027: aload #37
    //   3029: iload #50
    //   3031: sipush #255
    //   3034: iand
    //   3035: baload
    //   3036: iload #48
    //   3038: ixor
    //   3039: i2b
    //   3040: bastore
    //   3041: aload #30
    //   3043: iload #47
    //   3045: iconst_1
    //   3046: iadd
    //   3047: iaload
    //   3048: istore #48
    //   3050: aload #46
    //   3052: iconst_4
    //   3053: aload #37
    //   3055: iload #50
    //   3057: bipush #24
    //   3059: iushr
    //   3060: baload
    //   3061: iload #48
    //   3063: bipush #24
    //   3065: iushr
    //   3066: ixor
    //   3067: i2b
    //   3068: bastore
    //   3069: aload #46
    //   3071: iconst_5
    //   3072: aload #37
    //   3074: iload #49
    //   3076: bipush #16
    //   3078: iushr
    //   3079: sipush #255
    //   3082: iand
    //   3083: baload
    //   3084: iload #48
    //   3086: bipush #16
    //   3088: iushr
    //   3089: ixor
    //   3090: i2b
    //   3091: bastore
    //   3092: aload #46
    //   3094: bipush #6
    //   3096: aload #37
    //   3098: iload #52
    //   3100: bipush #8
    //   3102: iushr
    //   3103: sipush #255
    //   3106: iand
    //   3107: baload
    //   3108: iload #48
    //   3110: bipush #8
    //   3112: iushr
    //   3113: ixor
    //   3114: i2b
    //   3115: bastore
    //   3116: aload #46
    //   3118: bipush #7
    //   3120: aload #37
    //   3122: iload #51
    //   3124: sipush #255
    //   3127: iand
    //   3128: baload
    //   3129: iload #48
    //   3131: ixor
    //   3132: i2b
    //   3133: bastore
    //   3134: aload #30
    //   3136: iload #47
    //   3138: iconst_2
    //   3139: iadd
    //   3140: iaload
    //   3141: istore #48
    //   3143: aload #46
    //   3145: bipush #8
    //   3147: aload #37
    //   3149: iload #51
    //   3151: bipush #24
    //   3153: iushr
    //   3154: baload
    //   3155: iload #48
    //   3157: bipush #24
    //   3159: iushr
    //   3160: ixor
    //   3161: i2b
    //   3162: bastore
    //   3163: aload #46
    //   3165: bipush #9
    //   3167: aload #37
    //   3169: iload #50
    //   3171: bipush #16
    //   3173: iushr
    //   3174: sipush #255
    //   3177: iand
    //   3178: baload
    //   3179: iload #48
    //   3181: bipush #16
    //   3183: iushr
    //   3184: ixor
    //   3185: i2b
    //   3186: bastore
    //   3187: aload #46
    //   3189: bipush #10
    //   3191: aload #37
    //   3193: iload #49
    //   3195: bipush #8
    //   3197: iushr
    //   3198: sipush #255
    //   3201: iand
    //   3202: baload
    //   3203: iload #48
    //   3205: bipush #8
    //   3207: iushr
    //   3208: ixor
    //   3209: i2b
    //   3210: bastore
    //   3211: aload #46
    //   3213: bipush #11
    //   3215: aload #37
    //   3217: iload #52
    //   3219: sipush #255
    //   3222: iand
    //   3223: baload
    //   3224: iload #48
    //   3226: ixor
    //   3227: i2b
    //   3228: bastore
    //   3229: aload #30
    //   3231: iload #47
    //   3233: iconst_3
    //   3234: iadd
    //   3235: iaload
    //   3236: istore #48
    //   3238: aload #46
    //   3240: bipush #12
    //   3242: aload #37
    //   3244: iload #52
    //   3246: bipush #24
    //   3248: iushr
    //   3249: baload
    //   3250: iload #48
    //   3252: bipush #24
    //   3254: iushr
    //   3255: ixor
    //   3256: i2b
    //   3257: bastore
    //   3258: aload #46
    //   3260: bipush #13
    //   3262: aload #37
    //   3264: iload #51
    //   3266: bipush #16
    //   3268: iushr
    //   3269: sipush #255
    //   3272: iand
    //   3273: baload
    //   3274: iload #48
    //   3276: bipush #16
    //   3278: iushr
    //   3279: ixor
    //   3280: i2b
    //   3281: bastore
    //   3282: aload #46
    //   3284: bipush #14
    //   3286: aload #37
    //   3288: iload #50
    //   3290: bipush #8
    //   3292: iushr
    //   3293: sipush #255
    //   3296: iand
    //   3297: baload
    //   3298: iload #48
    //   3300: bipush #8
    //   3302: iushr
    //   3303: ixor
    //   3304: i2b
    //   3305: bastore
    //   3306: aload #46
    //   3308: bipush #15
    //   3310: aload #37
    //   3312: iload #49
    //   3314: sipush #255
    //   3317: iand
    //   3318: baload
    //   3319: iload #48
    //   3321: ixor
    //   3322: i2b
    //   3323: bastore
    //   3324: iconst_0
    //   3325: istore #53
    //   3327: iload #53
    //   3329: bipush #16
    //   3331: if_icmpge -> 3357
    //   3334: aload #43
    //   3336: iload #53
    //   3338: iload #44
    //   3340: bipush #16
    //   3342: imul
    //   3343: iadd
    //   3344: aload #46
    //   3346: iload #53
    //   3348: baload
    //   3349: bastore
    //   3350: iinc #53, 1
    //   3353: iload_2
    //   3354: ifeq -> 3327
    //   3357: iinc #44, 1
    //   3360: iload_2
    //   3361: ifeq -> 2442
    //   3364: aload #43
    //   3366: arraylength
    //   3367: ifle -> 3448
    //   3370: aload #43
    //   3372: aload #43
    //   3374: arraylength
    //   3375: iconst_1
    //   3376: isub
    //   3377: baload
    //   3378: istore #44
    //   3380: iload #44
    //   3382: bipush #16
    //   3384: if_icmple -> 3395
    //   3387: aload #43
    //   3389: astore #35
    //   3391: iload_2
    //   3392: ifeq -> 3448
    //   3395: aload #43
    //   3397: arraylength
    //   3398: iload #44
    //   3400: isub
    //   3401: newarray byte
    //   3403: astore #35
    //   3405: iconst_0
    //   3406: istore #45
    //   3408: iload #45
    //   3410: aload #35
    //   3412: arraylength
    //   3413: if_icmpge -> 3448
    //   3416: iload #45
    //   3418: aload #43
    //   3420: arraylength
    //   3421: if_icmpge -> 3448
    //   3424: aload #35
    //   3426: iload #45
    //   3428: aload #43
    //   3430: iload #45
    //   3432: baload
    //   3433: bastore
    //   3434: iinc #45, 1
    //   3437: iload_2
    //   3438: ifeq -> 3408
    //   3441: goto -> 3448
    //   3444: invokestatic a : (Ljava/lang/Throwable;)Ljava/lang/Throwable;
    //   3447: athrow
    //   3448: aload #35
    //   3450: astore #7
    //   3452: sipush #-3518
    //   3455: sipush #3388
    //   3458: invokestatic a : (II)Ljava/lang/String;
    //   3461: iconst_1
    //   3462: ldc burp/Zmz
    //   3464: invokevirtual getClassLoader : ()Ljava/lang/ClassLoader;
    //   3467: invokestatic forName : (Ljava/lang/String;ZLjava/lang/ClassLoader;)Ljava/lang/Class;
    //   3470: invokevirtual getDeclaredFields : ()[Ljava/lang/reflect/Field;
    //   3473: astore_3
    //   3474: aload_3
    //   3475: arraylength
    //   3476: istore #4
    //   3478: iconst_0
    //   3479: istore #5
    //   3481: iload #5
    //   3483: iload #4
    //   3485: if_icmpge -> 3622
    //   3488: aload_3
    //   3489: iload #5
    //   3491: aaload
    //   3492: astore #6
    //   3494: aload #6
    //   3496: invokevirtual getModifiers : ()I
    //   3499: invokestatic isStatic : (I)Z
    //   3502: ifne -> 3512
    //   3505: goto -> 3615
    //   3508: invokestatic a : (Ljava/lang/Throwable;)Ljava/lang/Throwable;
    //   3511: athrow
    //   3512: aload #6
    //   3514: invokevirtual getType : ()Ljava/lang/Class;
    //   3517: astore #7
    //   3519: aload #7
    //   3521: ifnull -> 3602
    //   3524: aload #7
    //   3526: invokevirtual isPrimitive : ()Z
    //   3529: ifne -> 3602
    //   3532: goto -> 3539
    //   3535: invokestatic a : (Ljava/lang/Throwable;)Ljava/lang/Throwable;
    //   3538: athrow
    //   3539: aload #7
    //   3541: invokevirtual getPackage : ()Ljava/lang/Package;
    //   3544: ifnull -> 3602
    //   3547: goto -> 3554
    //   3550: invokestatic a : (Ljava/lang/Throwable;)Ljava/lang/Throwable;
    //   3553: athrow
    //   3554: aload #7
    //   3556: invokevirtual getPackage : ()Ljava/lang/Package;
    //   3559: invokevirtual getName : ()Ljava/lang/String;
    //   3562: ifnull -> 3602
    //   3565: goto -> 3572
    //   3568: invokestatic a : (Ljava/lang/Throwable;)Ljava/lang/Throwable;
    //   3571: athrow
    //   3572: aload #7
    //   3574: invokevirtual getPackage : ()Ljava/lang/Package;
    //   3577: invokevirtual getName : ()Ljava/lang/String;
    //   3580: sipush #-3509
    //   3583: sipush #27591
    //   3586: invokestatic a : (II)Ljava/lang/String;
    //   3589: invokevirtual startsWith : (Ljava/lang/String;)Z
    //   3592: ifne -> 3602
    //   3595: goto -> 3602
    //   3598: invokestatic a : (Ljava/lang/Throwable;)Ljava/lang/Throwable;
    //   3601: athrow
    //   3602: aload #6
    //   3604: iconst_1
    //   3605: invokevirtual setAccessible : (Z)V
    //   3608: aload #6
    //   3610: aconst_null
    //   3611: invokevirtual get : (Ljava/lang/Object;)Ljava/lang/Object;
    //   3614: pop
    //   3615: iinc #5, 1
    //   3618: iload_2
    //   3619: ifeq -> 3481
    //   3622: sipush #-3510
    //   3625: sipush #-19455
    //   3628: invokestatic a : (II)Ljava/lang/String;
    //   3631: invokestatic forName : (Ljava/lang/String;)Ljava/lang/Class;
    //   3634: invokevirtual getDeclaredMethods : ()[Ljava/lang/reflect/Method;
    //   3637: astore_3
    //   3638: aload_3
    //   3639: arraylength
    //   3640: istore #4
    //   3642: iconst_0
    //   3643: istore #5
    //   3645: iload #5
    //   3647: iload #4
    //   3649: if_icmpge -> 3760
    //   3652: aload_3
    //   3653: iload #5
    //   3655: aaload
    //   3656: astore #6
    //   3658: aload #6
    //   3660: invokevirtual getParameterTypes : ()[Ljava/lang/Class;
    //   3663: pop
    //   3664: aload #6
    //   3666: invokevirtual getModifiers : ()I
    //   3669: invokestatic isStatic : (I)Z
    //   3672: ifeq -> 3746
    //   3675: aload #6
    //   3677: invokevirtual getParameterTypes : ()[Ljava/lang/Class;
    //   3680: arraylength
    //   3681: iconst_2
    //   3682: if_icmpne -> 3746
    //   3685: goto -> 3692
    //   3688: invokestatic a : (Ljava/lang/Throwable;)Ljava/lang/Throwable;
    //   3691: athrow
    //   3692: aload #6
    //   3694: invokevirtual getReturnType : ()Ljava/lang/Class;
    //   3697: getstatic java/lang/Boolean.TYPE : Ljava/lang/Class;
    //   3700: if_acmpne -> 3746
    //   3703: goto -> 3710
    //   3706: invokestatic a : (Ljava/lang/Throwable;)Ljava/lang/Throwable;
    //   3709: athrow
    //   3710: aload #6
    //   3712: iconst_1
    //   3713: invokevirtual setAccessible : (Z)V
    //   3716: aload #6
    //   3718: aconst_null
    //   3719: iconst_2
    //   3720: anewarray java/lang/Object
    //   3723: dup
    //   3724: iconst_0
    //   3725: aload_0
    //   3726: aastore
    //   3727: dup
    //   3728: iconst_1
    //   3729: aload_1
    //   3730: aastore
    //   3731: invokevirtual invoke : (Ljava/lang/Object;[Ljava/lang/Object;)Ljava/lang/Object;
    //   3734: pop
    //   3735: iload_2
    //   3736: ifeq -> 3760
    //   3739: goto -> 3746
    //   3742: invokestatic a : (Ljava/lang/Throwable;)Ljava/lang/Throwable;
    //   3745: athrow
    //   3746: iinc #5, 1
    //   3749: iload_2
    //   3750: ifeq -> 3645
    //   3753: goto -> 3760
    //   3756: invokestatic a : (Ljava/lang/Throwable;)Ljava/lang/Throwable;
    //   3759: athrow
    //   3760: getstatic burp/Zlot.ZD : Ljava/lang/String;
    //   3763: getstatic burp/Zsow.ZV : Ljava/lang/Object;
    //   3766: checkcast java/math/BigInteger
    //   3769: invokevirtual intValue : ()I
    //   3772: bipush #32
    //   3774: irem
    //   3775: invokestatic abs : (I)I
    //   3778: invokevirtual charAt : (I)C
    //   3781: getstatic burp/Zb6a.ZY : Ljava/lang/String;
    //   3784: getstatic burp/Zmgl.ZI : Ljava/lang/Object;
    //   3787: checkcast java/math/BigInteger
    //   3790: invokevirtual intValue : ()I
    //   3793: bipush #32
    //   3795: irem
    //   3796: invokestatic abs : (I)I
    //   3799: invokevirtual charAt : (I)C
    //   3802: if_icmple -> 3909
    //   3805: getstatic burp/Zkqx.Ze : Ljava/lang/String;
    //   3808: getstatic burp/Zva.Zu : Ljava/lang/Object;
    //   3811: checkcast java/math/BigInteger
    //   3814: invokevirtual intValue : ()I
    //   3817: bipush #32
    //   3819: irem
    //   3820: invokestatic abs : (I)I
    //   3823: invokevirtual charAt : (I)C
    //   3826: getstatic burp/Zsow.Zh : Ljava/lang/String;
    //   3829: getstatic burp/Zgja.ZD : Ljava/lang/Object;
    //   3832: checkcast java/math/BigInteger
    //   3835: invokevirtual intValue : ()I
    //   3838: bipush #32
    //   3840: irem
    //   3841: invokestatic abs : (I)I
    //   3844: invokevirtual charAt : (I)C
    //   3847: if_icmpgt -> 3909
    //   3850: goto -> 3857
    //   3853: invokestatic a : (Ljava/lang/Throwable;)Ljava/lang/Throwable;
    //   3856: athrow
    //   3857: getstatic burp/Ztzh.ZE : Ljava/lang/String;
    //   3860: getstatic burp/Zg8v.ZB : Ljava/lang/Object;
    //   3863: checkcast java/math/BigInteger
    //   3866: invokevirtual intValue : ()I
    //   3869: bipush #32
    //   3871: irem
    //   3872: invokestatic abs : (I)I
    //   3875: invokevirtual charAt : (I)C
    //   3878: getstatic burp/Zgp_.Zn : Ljava/lang/String;
    //   3881: getstatic burp/Zzh1.Zf : Ljava/lang/Object;
    //   3884: checkcast java/math/BigInteger
    //   3887: invokevirtual intValue : ()I
    //   3890: bipush #32
    //   3892: irem
    //   3893: invokestatic abs : (I)I
    //   3896: invokevirtual charAt : (I)C
    //   3899: if_icmple -> 3917
    //   3902: goto -> 3909
    //   3905: invokestatic a : (Ljava/lang/Throwable;)Ljava/lang/Throwable;
    //   3908: athrow
    //   3909: iconst_1
    //   3910: goto -> 3918
    //   3913: invokestatic a : (Ljava/lang/Throwable;)Ljava/lang/Throwable;
    //   3916: athrow
    //   3917: iconst_0
    //   3918: ireturn
    //   3919: astore_3
    //   3920: new java/lang/Exception
    //   3923: dup
    //   3924: aload_3
    //   3925: invokevirtual getMessage : ()Ljava/lang/String;
    //   3928: invokespecial <init> : (Ljava/lang/String;)V
    //   3931: athrow
    // Exception table:
    //   from	to	target	type
    //   4	3918	3919	java/lang/Throwable
    //   573	597	600	java/lang/Throwable
    //   671	708	708	java/lang/Throwable
    //   712	733	733	java/lang/Throwable
    //   737	767	767	java/lang/Throwable
    //   1095	1110	1110	java/lang/Throwable
    //   2112	2138	2138	java/lang/Throwable
    //   2219	2234	2234	java/lang/Throwable
    //   3416	3441	3444	java/lang/Throwable
    //   3494	3508	3508	java/lang/Throwable
    //   3519	3532	3535	java/lang/Throwable
    //   3524	3547	3550	java/lang/Throwable
    //   3539	3565	3568	java/lang/Throwable
    //   3554	3595	3598	java/lang/Throwable
    //   3658	3685	3688	java/lang/Throwable
    //   3675	3703	3706	java/lang/Throwable
    //   3692	3739	3742	java/lang/Throwable
    //   3710	3753	3756	java/lang/Throwable
    //   3760	3850	3853	java/lang/Throwable
    //   3805	3902	3905	java/lang/Throwable
    //   3857	3913	3913	java/lang/Throwable
  }
  
  static {
    // Byte code:
    //   0: bipush #15
    //   2: anewarray java/lang/String
    //   5: astore #5
    //   7: iconst_0
    //   8: istore_3
    //   9: ldc 'meW zDl@t@ZOXx&SkHjx\O\/o&'UwX\\teQ\\t?n|V B#6z~o`0MS?g|cYJ??\\t\\bxrE KycqeOH,GSX u^$\\t>Ku`}\\t|z??M~/t5-RwLOshi";ueME,?&ivQ,\\fv'
    //   11: dup
    //   12: astore_2
    //   13: invokevirtual length : ()I
    //   16: istore #4
    //   18: bipush #77
    //   20: istore_1
    //   21: iconst_m1
    //   22: istore_0
    //   23: bipush #90
    //   25: iinc #0, 1
    //   28: aload_2
    //   29: iload_0
    //   30: dup
    //   31: iload_1
    //   32: iadd
    //   33: invokevirtual substring : (II)Ljava/lang/String;
    //   36: iconst_m1
    //   37: goto -> 143
    //   40: aload #5
    //   42: swap
    //   43: iload_3
    //   44: iinc #3, 1
    //   47: swap
    //   48: aastore
    //   49: iload_0
    //   50: iload_1
    //   51: iadd
    //   52: dup
    //   53: istore_0
    //   54: iload #4
    //   56: if_icmpge -> 68
    //   59: aload_2
    //   60: iload_0
    //   61: invokevirtual charAt : (I)C
    //   64: istore_1
    //   65: goto -> 23
    //   68: ldc 'O9Q &j}rV\\teUg G?MT'
    //   70: dup
    //   71: astore_2
    //   72: invokevirtual length : ()I
    //   75: istore #4
    //   77: bipush #7
    //   79: istore_1
    //   80: iconst_m1
    //   81: istore_0
    //   82: bipush #64
    //   84: iinc #0, 1
    //   87: aload_2
    //   88: iload_0
    //   89: dup
    //   90: iload_1
    //   91: iadd
    //   92: invokevirtual substring : (II)Ljava/lang/String;
    //   95: iconst_0
    //   96: goto -> 143
    //   99: aload #5
    //   101: swap
    //   102: iload_3
    //   103: iinc #3, 1
    //   106: swap
    //   107: aastore
    //   108: iload_0
    //   109: iload_1
    //   110: iadd
    //   111: dup
    //   112: istore_0
    //   113: iload #4
    //   115: if_icmpge -> 127
    //   118: aload_2
    //   119: iload_0
    //   120: invokevirtual charAt : (I)C
    //   123: istore_1
    //   124: goto -> 82
    //   127: aload #5
    //   129: putstatic burp/Zlbt.a : [Ljava/lang/String;
    //   132: bipush #15
    //   134: anewarray java/lang/String
    //   137: putstatic burp/Zlbt.b : [Ljava/lang/String;
    //   140: goto -> 300
    //   143: dup_x2
    //   144: pop
    //   145: invokevirtual toCharArray : ()[C
    //   148: dup_x1
    //   149: arraylength
    //   150: dup_x2
    //   151: pop
    //   152: iconst_0
    //   153: istore #6
    //   155: dup2_x1
    //   156: pop2
    //   157: dup_x2
    //   158: iconst_1
    //   159: if_icmpgt -> 260
    //   162: dup2
    //   163: swap
    //   164: iload #6
    //   166: dup2_x1
    //   167: caload
    //   168: swap
    //   169: iload #6
    //   171: bipush #7
    //   173: irem
    //   174: tableswitch default -> 242, 0 -> 212, 1 -> 217, 2 -> 222, 3 -> 227, 4 -> 232, 5 -> 237
    //   212: bipush #89
    //   214: goto -> 244
    //   217: bipush #118
    //   219: goto -> 244
    //   222: bipush #31
    //   224: goto -> 244
    //   227: bipush #104
    //   229: goto -> 244
    //   232: bipush #87
    //   234: goto -> 244
    //   237: bipush #48
    //   239: goto -> 244
    //   242: bipush #6
    //   244: ixor
    //   245: ixor
    //   246: i2c
    //   247: castore
    //   248: iinc #6, 1
    //   251: dup
    //   252: ifne -> 260
    //   255: dup2
    //   256: dup_x1
    //   257: goto -> 166
    //   260: dup2_x1
    //   261: pop2
    //   262: dup_x2
    //   263: iload #6
    //   265: if_icmpgt -> 162
    //   268: pop
    //   269: new java/lang/String
    //   272: dup_x1
    //   273: swap
    //   274: invokespecial <init> : ([C)V
    //   277: invokevirtual intern : ()Ljava/lang/String;
    //   280: swap
    //   281: pop
    //   282: swap
    //   283: tableswitch default -> 40, 0 -> 99
    //   300: sipush #-3515
    //   303: sipush #-18612
    //   306: invokestatic a : (II)Ljava/lang/String;
    //   309: putstatic burp/Zlbt.ZE : Ljava/lang/String;
    //   312: new java/math/BigInteger
    //   315: dup
    //   316: sipush #-3505
    //   319: sipush #24331
    //   322: invokestatic a : (II)Ljava/lang/String;
    //   325: invokespecial <init> : (Ljava/lang/String;)V
    //   328: putstatic burp/Zlbt.ZF : Ljava/lang/Object;
    //   331: return
  }
  
  private static Throwable a(Throwable paramThrowable) {
    return paramThrowable;
  }
  
  private static String a(int paramInt1, int paramInt2) {
    int i = (paramInt1 ^ 0xFFFFF243) & 0xFFFF;
    if (b[i] == null) {
      char[] arrayOfChar = a[i].toCharArray();
      switch (arrayOfChar[0] & 0xFF) {
        case 0:
        
        case 1:
        
        case 2:
        
        case 3:
        
        case 4:
        
        case 5:
        
        case 6:
        
        case 7:
        
        case 8:
        
        case 9:
        
        case 10:
        
        case 11:
        
        case 12:
        
        case 13:
        
        case 14:
        
        case 15:
        
        case 16:
        
        case 17:
        
        case 18:
        
        case 19:
        
        case 20:
        
        case 21:
        
        case 22:
        
        case 23:
        
        case 24:
        
        case 25:
        
        case 26:
        
        case 27:
        
        case 28:
        
        case 29:
        
        case 30:
        
        case 31:
        
        case 32:
        
        case 33:
        
        case 34:
        
        case 35:
        
        case 36:
        
        case 37:
        
        case 38:
        
        case 39:
        
        case 40:
        
        case 41:
        
        case 42:
        
        case 43:
        
        case 44:
        
        case 45:
        
        case 46:
        
        case 47:
        
        case 48:
        
        case 49:
        
        case 50:
        
        case 51:
        
        case 52:
        
        case 53:
        
        case 54:
        
        case 55:
        
        case 56:
        
        case 57:
        
        case 58:
        
        case 59:
        
        case 60:
        
        case 61:
        
        case 62:
        
        case 63:
        
        case 64:
        
        case 65:
        
        case 66:
        
        case 67:
        
        case 68:
        
        case 69:
        
        case 70:
        
        case 71:
        
        case 72:
        
        case 73:
        
        case 74:
        
        case 75:
        
        case 76:
        
        case 77:
        
        case 78:
        
        case 79:
        
        case 80:
        
        case 81:
        
        case 82:
        
        case 83:
        
        case 84:
        
        case 85:
        
        case 86:
        
        case 87:
        
        case 88:
        
        case 89:
        
        case 90:
        
        case 91:
        
        case 92:
        
        case 93:
        
        case 94:
        
        case 95:
        
        case 96:
        
        case 97:
        
        case 98:
        
        case 99:
        
        case 100:
        
        case 101:
        
        case 102:
        
        case 103:
        
        case 104:
        
        case 105:
        
        case 106:
        
        case 107:
        
        case 108:
        
        case 109:
        
        case 110:
        
        case 111:
        
        case 112:
        
        case 113:
        
        case 114:
        
        case 115:
        
        case 116:
        
        case 117:
        
        case 118:
        
        case 119:
        
        case 120:
        
        case 121:
        
        case 122:
        
        case 123:
        
        case 124:
        
        case 125:
        
        case 126:
        
        case 127:
        
        case 128:
        
        case 129:
        
        case 130:
        
        case 131:
        
        case 132:
        
        case 133:
        
        case 134:
        
        case 135:
        
        case 136:
        
        case 137:
        
        case 138:
        
        case 139:
        
        case 140:
        
        case 141:
        
        case 142:
        
        case 143:
        
        case 144:
        
        case 145:
        
        case 146:
        
        case 147:
        
        case 148:
        
        case 149:
        
        case 150:
        
        case 151:
        
        case 152:
        
        case 153:
        
        case 154:
        
        case 155:
        
        case 156:
        
        case 157:
        
        case 158:
        
        case 159:
        
        case 160:
        
        case 161:
        
        case 162:
        
        case 163:
        
        case 164:
        
        case 165:
        
        case 166:
        
        case 167:
        
        case 168:
        
        case 169:
        
        case 170:
        
        case 171:
        
        case 172:
        
        case 173:
        
        case 174:
        
        case 175:
        
        case 176:
        
        case 177:
        
        case 178:
        
        case 179:
        
        case 180:
        
        case 181:
        
        case 182:
        
        case 183:
        
        case 184:
        
        case 185:
        
        case 186:
        
        case 187:
        
        case 188:
        
        case 189:
        
        case 190:
        
        case 191:
        
        case 192:
        
        case 193:
        
        case 194:
        
        case 195:
        
        case 196:
        
        case 197:
        
        case 198:
        
        case 199:
        
        case 200:
        
        case 201:
        
        case 202:
        
        case 203:
        
        case 204:
        
        case 205:
        
        case 206:
        
        case 207:
        
        case 208:
        
        case 209:
        
        case 210:
        
        case 211:
        
        case 212:
        
        case 213:
        
        case 214:
        
        case 215:
        
        case 216:
        
        case 217:
        
        case 218:
        
        case 219:
        
        case 220:
        
        case 221:
        
        case 222:
        
        case 223:
        
        case 224:
        
        case 225:
        
        case 226:
        
        case 227:
        
        case 228:
        
        case 229:
        
        case 230:
        
        case 231:
        
        case 232:
        
        case 233:
        
        case 234:
        
        case 235:
        
        case 236:
        
        case 237:
        
        case 238:
        
        case 239:
        
        case 240:
        
        case 241:
        
        case 242:
        
        case 243:
        
        case 244:
        
        case 245:
        
        case 246:
        
        case 247:
        
        case 248:
        
        case 249:
        
        case 250:
        
        case 251:
        
        case 252:
        
        case 253:
        
        case 254:
        
        default:
          break;
      } 
      byte b1 = 103;
      int j = (paramInt2 & 0xFF) - b1;
      if (j < 0)
        j += 256; 
      int k = ((paramInt2 & 0xFFFF) >>> 8) - b1;
      if (k < 0)
        k += 256; 
      for (byte b2 = 0; b2 < arrayOfChar.length; b2++) {
        int m = b2 % 2;
        if (m == 0) {
          arrayOfChar[b2] = (char)(arrayOfChar[b2] ^ j);
          j = ((j >>> 3 | j << 5) ^ arrayOfChar[b2]) & 0xFF;
        } else {
          arrayOfChar[b2] = (char)(arrayOfChar[b2] ^ k);
          k = ((k >>> 3 | k << 5) ^ arrayOfChar[b2]) & 0xFF;
        } 
      } 
      b[i] = (new String(arrayOfChar)).intern();
    } 
    return b[i];
  }
}


/* Location:              C:\Program Files\BurpSuitePro\burpsuite_pro.jar!\burp\Zlbt.class
 * Java compiler version: 21 (65.0)
 * JD-Core Version:       1.1.3
 */