package burp;

import java.math.BigInteger;

class Zlc2 extends ClassLoader {
  static Object ZQ;
  
  static String Zz;
  
  private static final String[] a;
  
  private static final String[] b;
  
  static void Z_(Object paramObject) {
    Zkdq.ZZ = a(-19527, 29344);
    Zkdq.ZG = new BigInteger(a(-19525, 27419));
    boolean bool = Zt2e.ZN();
    try {
      try {
        if (Zepy.Zg.charAt(Math.abs(((BigInteger)Zthx.ZH).intValue() % 32)) <= Zk92.Zc.charAt(Math.abs(((BigInteger)Zrw0.ZC).intValue() % 32))) {
          try {
            Zsq5.Zq(Class.forName(a(-19548, -30370)));
            if (!bool)
              Zthx.Zj(Class.forName(a(-19521, -28703))); 
          } catch (Throwable throwable) {
            throw a(null);
          } 
          return;
        } 
      } catch (Throwable throwable) {
        throw a(null);
      } 
      Zthx.Zj(Class.forName(a(-19521, -28703)));
    } catch (Throwable throwable) {}
  }
  
  static void ZW(Object[] paramArrayOfObject, Object paramObject) throws Throwable {}
  
  static boolean ZQ(Object[] paramArrayOfObject, Object paramObject) throws Throwable {
    // Byte code:
    //   0: invokestatic ZN : ()Z
    //   3: istore_2
    //   4: getstatic burp/Zml9.ZH : Ljava/lang/Object;
    //   7: checkcast java/math/BigInteger
    //   10: getstatic burp/Ztq8.Zm : Ljava/lang/Object;
    //   13: checkcast java/math/BigInteger
    //   16: invokevirtual add : (Ljava/math/BigInteger;)Ljava/math/BigInteger;
    //   19: putstatic burp/Zkjj.Zh : Ljava/lang/Object;
    //   22: getstatic burp/Zrov.Zk : Ljava/lang/Object;
    //   25: checkcast java/math/BigInteger
    //   28: invokevirtual toByteArray : ()[B
    //   31: astore_3
    //   32: bipush #64
    //   34: newarray byte
    //   36: dup
    //   37: iconst_0
    //   38: bipush #-128
    //   40: bastore
    //   41: dup
    //   42: iconst_1
    //   43: iconst_0
    //   44: bastore
    //   45: dup
    //   46: iconst_2
    //   47: iconst_0
    //   48: bastore
    //   49: dup
    //   50: iconst_3
    //   51: iconst_0
    //   52: bastore
    //   53: dup
    //   54: iconst_4
    //   55: iconst_0
    //   56: bastore
    //   57: dup
    //   58: iconst_5
    //   59: iconst_0
    //   60: bastore
    //   61: dup
    //   62: bipush #6
    //   64: iconst_0
    //   65: bastore
    //   66: dup
    //   67: bipush #7
    //   69: iconst_0
    //   70: bastore
    //   71: dup
    //   72: bipush #8
    //   74: iconst_0
    //   75: bastore
    //   76: dup
    //   77: bipush #9
    //   79: iconst_0
    //   80: bastore
    //   81: dup
    //   82: bipush #10
    //   84: iconst_0
    //   85: bastore
    //   86: dup
    //   87: bipush #11
    //   89: iconst_0
    //   90: bastore
    //   91: dup
    //   92: bipush #12
    //   94: iconst_0
    //   95: bastore
    //   96: dup
    //   97: bipush #13
    //   99: iconst_0
    //   100: bastore
    //   101: dup
    //   102: bipush #14
    //   104: iconst_0
    //   105: bastore
    //   106: dup
    //   107: bipush #15
    //   109: iconst_0
    //   110: bastore
    //   111: dup
    //   112: bipush #16
    //   114: iconst_0
    //   115: bastore
    //   116: dup
    //   117: bipush #17
    //   119: iconst_0
    //   120: bastore
    //   121: dup
    //   122: bipush #18
    //   124: iconst_0
    //   125: bastore
    //   126: dup
    //   127: bipush #19
    //   129: iconst_0
    //   130: bastore
    //   131: dup
    //   132: bipush #20
    //   134: iconst_0
    //   135: bastore
    //   136: dup
    //   137: bipush #21
    //   139: iconst_0
    //   140: bastore
    //   141: dup
    //   142: bipush #22
    //   144: iconst_0
    //   145: bastore
    //   146: dup
    //   147: bipush #23
    //   149: iconst_0
    //   150: bastore
    //   151: dup
    //   152: bipush #24
    //   154: iconst_0
    //   155: bastore
    //   156: dup
    //   157: bipush #25
    //   159: iconst_0
    //   160: bastore
    //   161: dup
    //   162: bipush #26
    //   164: iconst_0
    //   165: bastore
    //   166: dup
    //   167: bipush #27
    //   169: iconst_0
    //   170: bastore
    //   171: dup
    //   172: bipush #28
    //   174: iconst_0
    //   175: bastore
    //   176: dup
    //   177: bipush #29
    //   179: iconst_0
    //   180: bastore
    //   181: dup
    //   182: bipush #30
    //   184: iconst_0
    //   185: bastore
    //   186: dup
    //   187: bipush #31
    //   189: iconst_0
    //   190: bastore
    //   191: dup
    //   192: bipush #32
    //   194: iconst_0
    //   195: bastore
    //   196: dup
    //   197: bipush #33
    //   199: iconst_0
    //   200: bastore
    //   201: dup
    //   202: bipush #34
    //   204: iconst_0
    //   205: bastore
    //   206: dup
    //   207: bipush #35
    //   209: iconst_0
    //   210: bastore
    //   211: dup
    //   212: bipush #36
    //   214: iconst_0
    //   215: bastore
    //   216: dup
    //   217: bipush #37
    //   219: iconst_0
    //   220: bastore
    //   221: dup
    //   222: bipush #38
    //   224: iconst_0
    //   225: bastore
    //   226: dup
    //   227: bipush #39
    //   229: iconst_0
    //   230: bastore
    //   231: dup
    //   232: bipush #40
    //   234: iconst_0
    //   235: bastore
    //   236: dup
    //   237: bipush #41
    //   239: iconst_0
    //   240: bastore
    //   241: dup
    //   242: bipush #42
    //   244: iconst_0
    //   245: bastore
    //   246: dup
    //   247: bipush #43
    //   249: iconst_0
    //   250: bastore
    //   251: dup
    //   252: bipush #44
    //   254: iconst_0
    //   255: bastore
    //   256: dup
    //   257: bipush #45
    //   259: iconst_0
    //   260: bastore
    //   261: dup
    //   262: bipush #46
    //   264: iconst_0
    //   265: bastore
    //   266: dup
    //   267: bipush #47
    //   269: iconst_0
    //   270: bastore
    //   271: dup
    //   272: bipush #48
    //   274: iconst_0
    //   275: bastore
    //   276: dup
    //   277: bipush #49
    //   279: iconst_0
    //   280: bastore
    //   281: dup
    //   282: bipush #50
    //   284: iconst_0
    //   285: bastore
    //   286: dup
    //   287: bipush #51
    //   289: iconst_0
    //   290: bastore
    //   291: dup
    //   292: bipush #52
    //   294: iconst_0
    //   295: bastore
    //   296: dup
    //   297: bipush #53
    //   299: iconst_0
    //   300: bastore
    //   301: dup
    //   302: bipush #54
    //   304: iconst_0
    //   305: bastore
    //   306: dup
    //   307: bipush #55
    //   309: iconst_0
    //   310: bastore
    //   311: dup
    //   312: bipush #56
    //   314: iconst_0
    //   315: bastore
    //   316: dup
    //   317: bipush #57
    //   319: iconst_0
    //   320: bastore
    //   321: dup
    //   322: bipush #58
    //   324: iconst_0
    //   325: bastore
    //   326: dup
    //   327: bipush #59
    //   329: iconst_0
    //   330: bastore
    //   331: dup
    //   332: bipush #60
    //   334: iconst_0
    //   335: bastore
    //   336: dup
    //   337: bipush #61
    //   339: iconst_0
    //   340: bastore
    //   341: dup
    //   342: bipush #62
    //   344: iconst_0
    //   345: bastore
    //   346: dup
    //   347: bipush #63
    //   349: iconst_0
    //   350: bastore
    //   351: astore #5
    //   353: bipush #64
    //   355: newarray int
    //   357: dup
    //   358: iconst_0
    //   359: ldc 1116352408
    //   361: iastore
    //   362: dup
    //   363: iconst_1
    //   364: ldc 1899447441
    //   366: iastore
    //   367: dup
    //   368: iconst_2
    //   369: ldc -1245643825
    //   371: iastore
    //   372: dup
    //   373: iconst_3
    //   374: ldc -373957723
    //   376: iastore
    //   377: dup
    //   378: iconst_4
    //   379: ldc 961987163
    //   381: iastore
    //   382: dup
    //   383: iconst_5
    //   384: ldc 1508970993
    //   386: iastore
    //   387: dup
    //   388: bipush #6
    //   390: ldc -1841331548
    //   392: iastore
    //   393: dup
    //   394: bipush #7
    //   396: ldc -1424204075
    //   398: iastore
    //   399: dup
    //   400: bipush #8
    //   402: ldc -670586216
    //   404: iastore
    //   405: dup
    //   406: bipush #9
    //   408: ldc 310598401
    //   410: iastore
    //   411: dup
    //   412: bipush #10
    //   414: ldc 607225278
    //   416: iastore
    //   417: dup
    //   418: bipush #11
    //   420: ldc 1426881987
    //   422: iastore
    //   423: dup
    //   424: bipush #12
    //   426: ldc 1925078388
    //   428: iastore
    //   429: dup
    //   430: bipush #13
    //   432: ldc -2132889090
    //   434: iastore
    //   435: dup
    //   436: bipush #14
    //   438: ldc -1680079193
    //   440: iastore
    //   441: dup
    //   442: bipush #15
    //   444: ldc -1046744716
    //   446: iastore
    //   447: dup
    //   448: bipush #16
    //   450: ldc -459576895
    //   452: iastore
    //   453: dup
    //   454: bipush #17
    //   456: ldc -272742522
    //   458: iastore
    //   459: dup
    //   460: bipush #18
    //   462: ldc 264347078
    //   464: iastore
    //   465: dup
    //   466: bipush #19
    //   468: ldc 604807628
    //   470: iastore
    //   471: dup
    //   472: bipush #20
    //   474: ldc 770255983
    //   476: iastore
    //   477: dup
    //   478: bipush #21
    //   480: ldc 1249150122
    //   482: iastore
    //   483: dup
    //   484: bipush #22
    //   486: ldc 1555081692
    //   488: iastore
    //   489: dup
    //   490: bipush #23
    //   492: ldc 1996064986
    //   494: iastore
    //   495: dup
    //   496: bipush #24
    //   498: ldc -1740746414
    //   500: iastore
    //   501: dup
    //   502: bipush #25
    //   504: ldc -1473132947
    //   506: iastore
    //   507: dup
    //   508: bipush #26
    //   510: ldc -1341970488
    //   512: iastore
    //   513: dup
    //   514: bipush #27
    //   516: ldc -1084653625
    //   518: iastore
    //   519: dup
    //   520: bipush #28
    //   522: ldc -958395405
    //   524: iastore
    //   525: dup
    //   526: bipush #29
    //   528: ldc -710438585
    //   530: iastore
    //   531: dup
    //   532: bipush #30
    //   534: ldc 113926993
    //   536: iastore
    //   537: dup
    //   538: bipush #31
    //   540: ldc 338241895
    //   542: iastore
    //   543: dup
    //   544: bipush #32
    //   546: ldc 666307205
    //   548: iastore
    //   549: dup
    //   550: bipush #33
    //   552: ldc 773529912
    //   554: iastore
    //   555: dup
    //   556: bipush #34
    //   558: ldc 1294757372
    //   560: iastore
    //   561: dup
    //   562: bipush #35
    //   564: ldc 1396182291
    //   566: iastore
    //   567: dup
    //   568: bipush #36
    //   570: ldc 1695183700
    //   572: iastore
    //   573: dup
    //   574: bipush #37
    //   576: ldc 1986661051
    //   578: iastore
    //   579: dup
    //   580: bipush #38
    //   582: ldc -2117940946
    //   584: iastore
    //   585: dup
    //   586: bipush #39
    //   588: ldc -1838011259
    //   590: iastore
    //   591: dup
    //   592: bipush #40
    //   594: ldc -1564481375
    //   596: iastore
    //   597: dup
    //   598: bipush #41
    //   600: ldc -1474664885
    //   602: iastore
    //   603: dup
    //   604: bipush #42
    //   606: ldc -1035236496
    //   608: iastore
    //   609: dup
    //   610: bipush #43
    //   612: ldc -949202525
    //   614: iastore
    //   615: dup
    //   616: bipush #44
    //   618: ldc -778901479
    //   620: iastore
    //   621: dup
    //   622: bipush #45
    //   624: ldc -694614492
    //   626: iastore
    //   627: dup
    //   628: bipush #46
    //   630: ldc -200395387
    //   632: iastore
    //   633: dup
    //   634: bipush #47
    //   636: ldc 275423344
    //   638: iastore
    //   639: dup
    //   640: bipush #48
    //   642: ldc 430227734
    //   644: iastore
    //   645: dup
    //   646: bipush #49
    //   648: ldc 506948616
    //   650: iastore
    //   651: dup
    //   652: bipush #50
    //   654: ldc 659060556
    //   656: iastore
    //   657: dup
    //   658: bipush #51
    //   660: ldc 883997877
    //   662: iastore
    //   663: dup
    //   664: bipush #52
    //   666: ldc 958139571
    //   668: iastore
    //   669: dup
    //   670: bipush #53
    //   672: ldc 1322822218
    //   674: iastore
    //   675: dup
    //   676: bipush #54
    //   678: ldc 1537002063
    //   680: iastore
    //   681: dup
    //   682: bipush #55
    //   684: ldc 1747873779
    //   686: iastore
    //   687: dup
    //   688: bipush #56
    //   690: ldc 1955562222
    //   692: iastore
    //   693: dup
    //   694: bipush #57
    //   696: ldc 2024104815
    //   698: iastore
    //   699: dup
    //   700: bipush #58
    //   702: ldc -2067236844
    //   704: iastore
    //   705: dup
    //   706: bipush #59
    //   708: ldc -1933114872
    //   710: iastore
    //   711: dup
    //   712: bipush #60
    //   714: ldc -1866530822
    //   716: iastore
    //   717: dup
    //   718: bipush #61
    //   720: ldc -1538233109
    //   722: iastore
    //   723: dup
    //   724: bipush #62
    //   726: ldc -1090935817
    //   728: iastore
    //   729: dup
    //   730: bipush #63
    //   732: ldc -965641998
    //   734: iastore
    //   735: astore #6
    //   737: iconst_2
    //   738: newarray int
    //   740: dup
    //   741: iconst_0
    //   742: iconst_0
    //   743: iastore
    //   744: dup
    //   745: iconst_1
    //   746: iconst_0
    //   747: iastore
    //   748: astore #7
    //   750: bipush #8
    //   752: newarray int
    //   754: dup
    //   755: iconst_0
    //   756: ldc 1779033703
    //   758: iastore
    //   759: dup
    //   760: iconst_1
    //   761: ldc -1150833019
    //   763: iastore
    //   764: dup
    //   765: iconst_2
    //   766: ldc 1013904242
    //   768: iastore
    //   769: dup
    //   770: iconst_3
    //   771: ldc -1521486534
    //   773: iastore
    //   774: dup
    //   775: iconst_4
    //   776: ldc 1359893119
    //   778: iastore
    //   779: dup
    //   780: iconst_5
    //   781: ldc -1694144372
    //   783: iastore
    //   784: dup
    //   785: bipush #6
    //   787: ldc 528734635
    //   789: iastore
    //   790: dup
    //   791: bipush #7
    //   793: ldc 1541459225
    //   795: iastore
    //   796: astore #8
    //   798: bipush #64
    //   800: newarray byte
    //   802: astore #9
    //   804: bipush #64
    //   806: newarray byte
    //   808: astore #10
    //   810: aload_3
    //   811: arraylength
    //   812: istore #11
    //   814: aload #7
    //   816: iconst_0
    //   817: iaload
    //   818: bipush #63
    //   820: iand
    //   821: istore #12
    //   823: aload #7
    //   825: iconst_0
    //   826: dup2
    //   827: iaload
    //   828: iload #11
    //   830: iadd
    //   831: iastore
    //   832: aload #7
    //   834: iconst_0
    //   835: dup2
    //   836: iaload
    //   837: iconst_m1
    //   838: iand
    //   839: iastore
    //   840: aload #7
    //   842: iconst_0
    //   843: iaload
    //   844: iload #11
    //   846: if_icmpge -> 864
    //   849: aload #7
    //   851: iconst_1
    //   852: dup2
    //   853: iaload
    //   854: iconst_1
    //   855: iadd
    //   856: iastore
    //   857: goto -> 864
    //   860: invokestatic a : (Ljava/lang/Throwable;)Ljava/lang/Throwable;
    //   863: athrow
    //   864: iconst_0
    //   865: istore #13
    //   867: iload #11
    //   869: bipush #64
    //   871: if_icmplt -> 1480
    //   874: iconst_0
    //   875: istore #14
    //   877: iload #14
    //   879: bipush #64
    //   881: if_icmpge -> 903
    //   884: aload #10
    //   886: iload #14
    //   888: aload_3
    //   889: iload #13
    //   891: iload #14
    //   893: iadd
    //   894: baload
    //   895: bastore
    //   896: iinc #14, 1
    //   899: iload_2
    //   900: ifne -> 877
    //   903: bipush #64
    //   905: newarray int
    //   907: astore #14
    //   909: bipush #8
    //   911: newarray int
    //   913: astore #15
    //   915: iconst_0
    //   916: istore #16
    //   918: iload #16
    //   920: bipush #8
    //   922: if_icmpge -> 942
    //   925: aload #15
    //   927: iload #16
    //   929: aload #8
    //   931: iload #16
    //   933: iaload
    //   934: iastore
    //   935: iinc #16, 1
    //   938: iload_2
    //   939: ifne -> 918
    //   942: iconst_0
    //   943: istore #16
    //   945: iload #16
    //   947: bipush #64
    //   949: if_icmpge -> 1440
    //   952: iload #16
    //   954: bipush #16
    //   956: if_icmpge -> 1037
    //   959: aload #14
    //   961: iload #16
    //   963: aload #10
    //   965: iconst_4
    //   966: iload #16
    //   968: imul
    //   969: baload
    //   970: sipush #255
    //   973: iand
    //   974: bipush #24
    //   976: ishl
    //   977: aload #10
    //   979: iconst_4
    //   980: iload #16
    //   982: imul
    //   983: iconst_1
    //   984: iadd
    //   985: baload
    //   986: sipush #255
    //   989: iand
    //   990: bipush #16
    //   992: ishl
    //   993: ior
    //   994: aload #10
    //   996: iconst_4
    //   997: iload #16
    //   999: imul
    //   1000: iconst_2
    //   1001: iadd
    //   1002: baload
    //   1003: sipush #255
    //   1006: iand
    //   1007: bipush #8
    //   1009: ishl
    //   1010: ior
    //   1011: aload #10
    //   1013: iconst_4
    //   1014: iload #16
    //   1016: imul
    //   1017: iconst_3
    //   1018: iadd
    //   1019: baload
    //   1020: sipush #255
    //   1023: iand
    //   1024: ior
    //   1025: iastore
    //   1026: iload_2
    //   1027: ifne -> 1180
    //   1030: goto -> 1037
    //   1033: invokestatic a : (Ljava/lang/Throwable;)Ljava/lang/Throwable;
    //   1036: athrow
    //   1037: aload #14
    //   1039: iload #16
    //   1041: aload #14
    //   1043: iload #16
    //   1045: iconst_2
    //   1046: isub
    //   1047: iaload
    //   1048: bipush #17
    //   1050: iushr
    //   1051: aload #14
    //   1053: iload #16
    //   1055: iconst_2
    //   1056: isub
    //   1057: iaload
    //   1058: bipush #15
    //   1060: ishl
    //   1061: ior
    //   1062: aload #14
    //   1064: iload #16
    //   1066: iconst_2
    //   1067: isub
    //   1068: iaload
    //   1069: bipush #19
    //   1071: iushr
    //   1072: aload #14
    //   1074: iload #16
    //   1076: iconst_2
    //   1077: isub
    //   1078: iaload
    //   1079: bipush #13
    //   1081: ishl
    //   1082: ior
    //   1083: ixor
    //   1084: aload #14
    //   1086: iload #16
    //   1088: iconst_2
    //   1089: isub
    //   1090: iaload
    //   1091: bipush #10
    //   1093: iushr
    //   1094: ixor
    //   1095: aload #14
    //   1097: iload #16
    //   1099: bipush #7
    //   1101: isub
    //   1102: iaload
    //   1103: iadd
    //   1104: aload #14
    //   1106: iload #16
    //   1108: bipush #15
    //   1110: isub
    //   1111: iaload
    //   1112: bipush #7
    //   1114: iushr
    //   1115: aload #14
    //   1117: iload #16
    //   1119: bipush #15
    //   1121: isub
    //   1122: iaload
    //   1123: bipush #25
    //   1125: ishl
    //   1126: ior
    //   1127: aload #14
    //   1129: iload #16
    //   1131: bipush #15
    //   1133: isub
    //   1134: iaload
    //   1135: bipush #18
    //   1137: iushr
    //   1138: aload #14
    //   1140: iload #16
    //   1142: bipush #15
    //   1144: isub
    //   1145: iaload
    //   1146: bipush #14
    //   1148: ishl
    //   1149: ior
    //   1150: ixor
    //   1151: aload #14
    //   1153: iload #16
    //   1155: bipush #15
    //   1157: isub
    //   1158: iaload
    //   1159: iconst_3
    //   1160: iushr
    //   1161: ixor
    //   1162: iadd
    //   1163: aload #14
    //   1165: iload #16
    //   1167: bipush #16
    //   1169: isub
    //   1170: iaload
    //   1171: iadd
    //   1172: iastore
    //   1173: goto -> 1180
    //   1176: invokestatic a : (Ljava/lang/Throwable;)Ljava/lang/Throwable;
    //   1179: athrow
    //   1180: aload #15
    //   1182: bipush #7
    //   1184: iaload
    //   1185: aload #15
    //   1187: iconst_4
    //   1188: iaload
    //   1189: bipush #6
    //   1191: iushr
    //   1192: aload #15
    //   1194: iconst_4
    //   1195: iaload
    //   1196: bipush #26
    //   1198: ishl
    //   1199: ior
    //   1200: aload #15
    //   1202: iconst_4
    //   1203: iaload
    //   1204: bipush #11
    //   1206: iushr
    //   1207: aload #15
    //   1209: iconst_4
    //   1210: iaload
    //   1211: bipush #21
    //   1213: ishl
    //   1214: ior
    //   1215: ixor
    //   1216: aload #15
    //   1218: iconst_4
    //   1219: iaload
    //   1220: bipush #25
    //   1222: iushr
    //   1223: aload #15
    //   1225: iconst_4
    //   1226: iaload
    //   1227: bipush #7
    //   1229: ishl
    //   1230: ior
    //   1231: ixor
    //   1232: iadd
    //   1233: aload #15
    //   1235: bipush #6
    //   1237: iaload
    //   1238: aload #15
    //   1240: iconst_4
    //   1241: iaload
    //   1242: aload #15
    //   1244: iconst_5
    //   1245: iaload
    //   1246: aload #15
    //   1248: bipush #6
    //   1250: iaload
    //   1251: ixor
    //   1252: iand
    //   1253: ixor
    //   1254: iadd
    //   1255: aload #6
    //   1257: iload #16
    //   1259: iaload
    //   1260: iadd
    //   1261: aload #14
    //   1263: iload #16
    //   1265: iaload
    //   1266: iadd
    //   1267: istore #17
    //   1269: aload #15
    //   1271: iconst_0
    //   1272: iaload
    //   1273: iconst_2
    //   1274: iushr
    //   1275: aload #15
    //   1277: iconst_0
    //   1278: iaload
    //   1279: bipush #30
    //   1281: ishl
    //   1282: ior
    //   1283: aload #15
    //   1285: iconst_0
    //   1286: iaload
    //   1287: bipush #13
    //   1289: iushr
    //   1290: aload #15
    //   1292: iconst_0
    //   1293: iaload
    //   1294: bipush #19
    //   1296: ishl
    //   1297: ior
    //   1298: ixor
    //   1299: aload #15
    //   1301: iconst_0
    //   1302: iaload
    //   1303: bipush #22
    //   1305: iushr
    //   1306: aload #15
    //   1308: iconst_0
    //   1309: iaload
    //   1310: bipush #10
    //   1312: ishl
    //   1313: ior
    //   1314: ixor
    //   1315: aload #15
    //   1317: iconst_0
    //   1318: iaload
    //   1319: aload #15
    //   1321: iconst_1
    //   1322: iaload
    //   1323: iand
    //   1324: aload #15
    //   1326: iconst_2
    //   1327: iaload
    //   1328: aload #15
    //   1330: iconst_0
    //   1331: iaload
    //   1332: aload #15
    //   1334: iconst_1
    //   1335: iaload
    //   1336: ior
    //   1337: iand
    //   1338: ior
    //   1339: iadd
    //   1340: istore #18
    //   1342: aload #15
    //   1344: iconst_3
    //   1345: dup2
    //   1346: iaload
    //   1347: iload #17
    //   1349: iadd
    //   1350: iastore
    //   1351: aload #15
    //   1353: bipush #7
    //   1355: iload #17
    //   1357: iload #18
    //   1359: iadd
    //   1360: iastore
    //   1361: aload #15
    //   1363: bipush #7
    //   1365: iaload
    //   1366: istore #17
    //   1368: aload #15
    //   1370: bipush #7
    //   1372: aload #15
    //   1374: bipush #6
    //   1376: iaload
    //   1377: iastore
    //   1378: aload #15
    //   1380: bipush #6
    //   1382: aload #15
    //   1384: iconst_5
    //   1385: iaload
    //   1386: iastore
    //   1387: aload #15
    //   1389: iconst_5
    //   1390: aload #15
    //   1392: iconst_4
    //   1393: iaload
    //   1394: iastore
    //   1395: aload #15
    //   1397: iconst_4
    //   1398: aload #15
    //   1400: iconst_3
    //   1401: iaload
    //   1402: iastore
    //   1403: aload #15
    //   1405: iconst_3
    //   1406: aload #15
    //   1408: iconst_2
    //   1409: iaload
    //   1410: iastore
    //   1411: aload #15
    //   1413: iconst_2
    //   1414: aload #15
    //   1416: iconst_1
    //   1417: iaload
    //   1418: iastore
    //   1419: aload #15
    //   1421: iconst_1
    //   1422: aload #15
    //   1424: iconst_0
    //   1425: iaload
    //   1426: iastore
    //   1427: aload #15
    //   1429: iconst_0
    //   1430: iload #17
    //   1432: iastore
    //   1433: iinc #16, 1
    //   1436: iload_2
    //   1437: ifne -> 945
    //   1440: iconst_0
    //   1441: istore #16
    //   1443: iload #16
    //   1445: bipush #8
    //   1447: if_icmpge -> 1470
    //   1450: aload #8
    //   1452: iload #16
    //   1454: dup2
    //   1455: iaload
    //   1456: aload #15
    //   1458: iload #16
    //   1460: iaload
    //   1461: iadd
    //   1462: iastore
    //   1463: iinc #16, 1
    //   1466: iload_2
    //   1467: ifne -> 1443
    //   1470: iinc #13, 64
    //   1473: iinc #11, -64
    //   1476: iload_2
    //   1477: ifne -> 867
    //   1480: iload #11
    //   1482: ifle -> 1517
    //   1485: iconst_0
    //   1486: istore #14
    //   1488: iload #14
    //   1490: iload #11
    //   1492: if_icmpge -> 1517
    //   1495: aload #9
    //   1497: iload #12
    //   1499: iload #14
    //   1501: iadd
    //   1502: aload_3
    //   1503: iload #13
    //   1505: iload #14
    //   1507: iadd
    //   1508: baload
    //   1509: bastore
    //   1510: iinc #14, 1
    //   1513: iload_2
    //   1514: ifne -> 1488
    //   1517: aload #7
    //   1519: iconst_0
    //   1520: iaload
    //   1521: bipush #29
    //   1523: iushr
    //   1524: aload #7
    //   1526: iconst_1
    //   1527: iaload
    //   1528: iconst_3
    //   1529: ishl
    //   1530: ior
    //   1531: istore #14
    //   1533: aload #7
    //   1535: iconst_0
    //   1536: iaload
    //   1537: iconst_3
    //   1538: ishl
    //   1539: istore #15
    //   1541: aload #7
    //   1543: iconst_0
    //   1544: iaload
    //   1545: bipush #63
    //   1547: iand
    //   1548: istore #16
    //   1550: iload #16
    //   1552: bipush #56
    //   1554: if_icmpge -> 1569
    //   1557: bipush #56
    //   1559: iload #16
    //   1561: isub
    //   1562: goto -> 1574
    //   1565: invokestatic a : (Ljava/lang/Throwable;)Ljava/lang/Throwable;
    //   1568: athrow
    //   1569: bipush #120
    //   1571: iload #16
    //   1573: isub
    //   1574: istore #17
    //   1576: aload #7
    //   1578: iconst_0
    //   1579: iaload
    //   1580: bipush #63
    //   1582: iand
    //   1583: istore #12
    //   1585: bipush #64
    //   1587: iload #12
    //   1589: isub
    //   1590: istore #18
    //   1592: aload #7
    //   1594: iconst_0
    //   1595: dup2
    //   1596: iaload
    //   1597: iload #17
    //   1599: iadd
    //   1600: iastore
    //   1601: aload #7
    //   1603: iconst_0
    //   1604: dup2
    //   1605: iaload
    //   1606: iconst_m1
    //   1607: iand
    //   1608: iastore
    //   1609: aload #7
    //   1611: iconst_0
    //   1612: iaload
    //   1613: iload #17
    //   1615: if_icmpge -> 1633
    //   1618: aload #7
    //   1620: iconst_1
    //   1621: dup2
    //   1622: iaload
    //   1623: iconst_1
    //   1624: iadd
    //   1625: iastore
    //   1626: goto -> 1633
    //   1629: invokestatic a : (Ljava/lang/Throwable;)Ljava/lang/Throwable;
    //   1632: athrow
    //   1633: iconst_0
    //   1634: istore #13
    //   1636: iload #12
    //   1638: ifle -> 2269
    //   1641: iload #17
    //   1643: iload #18
    //   1645: if_icmplt -> 2269
    //   1648: goto -> 1655
    //   1651: invokestatic a : (Ljava/lang/Throwable;)Ljava/lang/Throwable;
    //   1654: athrow
    //   1655: iconst_0
    //   1656: istore #19
    //   1658: iload #19
    //   1660: iload #18
    //   1662: if_icmpge -> 1685
    //   1665: aload #9
    //   1667: iload #12
    //   1669: iload #19
    //   1671: iadd
    //   1672: aload #5
    //   1674: iload #19
    //   1676: baload
    //   1677: bastore
    //   1678: iinc #19, 1
    //   1681: iload_2
    //   1682: ifne -> 1658
    //   1685: bipush #64
    //   1687: newarray int
    //   1689: astore #19
    //   1691: bipush #8
    //   1693: newarray int
    //   1695: astore #20
    //   1697: iconst_0
    //   1698: istore #21
    //   1700: iload #21
    //   1702: bipush #8
    //   1704: if_icmpge -> 1724
    //   1707: aload #20
    //   1709: iload #21
    //   1711: aload #8
    //   1713: iload #21
    //   1715: iaload
    //   1716: iastore
    //   1717: iinc #21, 1
    //   1720: iload_2
    //   1721: ifne -> 1700
    //   1724: iconst_0
    //   1725: istore #21
    //   1727: iload #21
    //   1729: bipush #64
    //   1731: if_icmpge -> 2222
    //   1734: iload #21
    //   1736: bipush #16
    //   1738: if_icmpge -> 1819
    //   1741: aload #19
    //   1743: iload #21
    //   1745: aload #9
    //   1747: iconst_4
    //   1748: iload #21
    //   1750: imul
    //   1751: baload
    //   1752: sipush #255
    //   1755: iand
    //   1756: bipush #24
    //   1758: ishl
    //   1759: aload #9
    //   1761: iconst_4
    //   1762: iload #21
    //   1764: imul
    //   1765: iconst_1
    //   1766: iadd
    //   1767: baload
    //   1768: sipush #255
    //   1771: iand
    //   1772: bipush #16
    //   1774: ishl
    //   1775: ior
    //   1776: aload #9
    //   1778: iconst_4
    //   1779: iload #21
    //   1781: imul
    //   1782: iconst_2
    //   1783: iadd
    //   1784: baload
    //   1785: sipush #255
    //   1788: iand
    //   1789: bipush #8
    //   1791: ishl
    //   1792: ior
    //   1793: aload #9
    //   1795: iconst_4
    //   1796: iload #21
    //   1798: imul
    //   1799: iconst_3
    //   1800: iadd
    //   1801: baload
    //   1802: sipush #255
    //   1805: iand
    //   1806: ior
    //   1807: iastore
    //   1808: iload_2
    //   1809: ifne -> 1962
    //   1812: goto -> 1819
    //   1815: invokestatic a : (Ljava/lang/Throwable;)Ljava/lang/Throwable;
    //   1818: athrow
    //   1819: aload #19
    //   1821: iload #21
    //   1823: aload #19
    //   1825: iload #21
    //   1827: iconst_2
    //   1828: isub
    //   1829: iaload
    //   1830: bipush #17
    //   1832: iushr
    //   1833: aload #19
    //   1835: iload #21
    //   1837: iconst_2
    //   1838: isub
    //   1839: iaload
    //   1840: bipush #15
    //   1842: ishl
    //   1843: ior
    //   1844: aload #19
    //   1846: iload #21
    //   1848: iconst_2
    //   1849: isub
    //   1850: iaload
    //   1851: bipush #19
    //   1853: iushr
    //   1854: aload #19
    //   1856: iload #21
    //   1858: iconst_2
    //   1859: isub
    //   1860: iaload
    //   1861: bipush #13
    //   1863: ishl
    //   1864: ior
    //   1865: ixor
    //   1866: aload #19
    //   1868: iload #21
    //   1870: iconst_2
    //   1871: isub
    //   1872: iaload
    //   1873: bipush #10
    //   1875: iushr
    //   1876: ixor
    //   1877: aload #19
    //   1879: iload #21
    //   1881: bipush #7
    //   1883: isub
    //   1884: iaload
    //   1885: iadd
    //   1886: aload #19
    //   1888: iload #21
    //   1890: bipush #15
    //   1892: isub
    //   1893: iaload
    //   1894: bipush #7
    //   1896: iushr
    //   1897: aload #19
    //   1899: iload #21
    //   1901: bipush #15
    //   1903: isub
    //   1904: iaload
    //   1905: bipush #25
    //   1907: ishl
    //   1908: ior
    //   1909: aload #19
    //   1911: iload #21
    //   1913: bipush #15
    //   1915: isub
    //   1916: iaload
    //   1917: bipush #18
    //   1919: iushr
    //   1920: aload #19
    //   1922: iload #21
    //   1924: bipush #15
    //   1926: isub
    //   1927: iaload
    //   1928: bipush #14
    //   1930: ishl
    //   1931: ior
    //   1932: ixor
    //   1933: aload #19
    //   1935: iload #21
    //   1937: bipush #15
    //   1939: isub
    //   1940: iaload
    //   1941: iconst_3
    //   1942: iushr
    //   1943: ixor
    //   1944: iadd
    //   1945: aload #19
    //   1947: iload #21
    //   1949: bipush #16
    //   1951: isub
    //   1952: iaload
    //   1953: iadd
    //   1954: iastore
    //   1955: goto -> 1962
    //   1958: invokestatic a : (Ljava/lang/Throwable;)Ljava/lang/Throwable;
    //   1961: athrow
    //   1962: aload #20
    //   1964: bipush #7
    //   1966: iaload
    //   1967: aload #20
    //   1969: iconst_4
    //   1970: iaload
    //   1971: bipush #6
    //   1973: iushr
    //   1974: aload #20
    //   1976: iconst_4
    //   1977: iaload
    //   1978: bipush #26
    //   1980: ishl
    //   1981: ior
    //   1982: aload #20
    //   1984: iconst_4
    //   1985: iaload
    //   1986: bipush #11
    //   1988: iushr
    //   1989: aload #20
    //   1991: iconst_4
    //   1992: iaload
    //   1993: bipush #21
    //   1995: ishl
    //   1996: ior
    //   1997: ixor
    //   1998: aload #20
    //   2000: iconst_4
    //   2001: iaload
    //   2002: bipush #25
    //   2004: iushr
    //   2005: aload #20
    //   2007: iconst_4
    //   2008: iaload
    //   2009: bipush #7
    //   2011: ishl
    //   2012: ior
    //   2013: ixor
    //   2014: iadd
    //   2015: aload #20
    //   2017: bipush #6
    //   2019: iaload
    //   2020: aload #20
    //   2022: iconst_4
    //   2023: iaload
    //   2024: aload #20
    //   2026: iconst_5
    //   2027: iaload
    //   2028: aload #20
    //   2030: bipush #6
    //   2032: iaload
    //   2033: ixor
    //   2034: iand
    //   2035: ixor
    //   2036: iadd
    //   2037: aload #6
    //   2039: iload #21
    //   2041: iaload
    //   2042: iadd
    //   2043: aload #19
    //   2045: iload #21
    //   2047: iaload
    //   2048: iadd
    //   2049: istore #22
    //   2051: aload #20
    //   2053: iconst_0
    //   2054: iaload
    //   2055: iconst_2
    //   2056: iushr
    //   2057: aload #20
    //   2059: iconst_0
    //   2060: iaload
    //   2061: bipush #30
    //   2063: ishl
    //   2064: ior
    //   2065: aload #20
    //   2067: iconst_0
    //   2068: iaload
    //   2069: bipush #13
    //   2071: iushr
    //   2072: aload #20
    //   2074: iconst_0
    //   2075: iaload
    //   2076: bipush #19
    //   2078: ishl
    //   2079: ior
    //   2080: ixor
    //   2081: aload #20
    //   2083: iconst_0
    //   2084: iaload
    //   2085: bipush #22
    //   2087: iushr
    //   2088: aload #20
    //   2090: iconst_0
    //   2091: iaload
    //   2092: bipush #10
    //   2094: ishl
    //   2095: ior
    //   2096: ixor
    //   2097: aload #20
    //   2099: iconst_0
    //   2100: iaload
    //   2101: aload #20
    //   2103: iconst_1
    //   2104: iaload
    //   2105: iand
    //   2106: aload #20
    //   2108: iconst_2
    //   2109: iaload
    //   2110: aload #20
    //   2112: iconst_0
    //   2113: iaload
    //   2114: aload #20
    //   2116: iconst_1
    //   2117: iaload
    //   2118: ior
    //   2119: iand
    //   2120: ior
    //   2121: iadd
    //   2122: istore #23
    //   2124: aload #20
    //   2126: iconst_3
    //   2127: dup2
    //   2128: iaload
    //   2129: iload #22
    //   2131: iadd
    //   2132: iastore
    //   2133: aload #20
    //   2135: bipush #7
    //   2137: iload #22
    //   2139: iload #23
    //   2141: iadd
    //   2142: iastore
    //   2143: aload #20
    //   2145: bipush #7
    //   2147: iaload
    //   2148: istore #22
    //   2150: aload #20
    //   2152: bipush #7
    //   2154: aload #20
    //   2156: bipush #6
    //   2158: iaload
    //   2159: iastore
    //   2160: aload #20
    //   2162: bipush #6
    //   2164: aload #20
    //   2166: iconst_5
    //   2167: iaload
    //   2168: iastore
    //   2169: aload #20
    //   2171: iconst_5
    //   2172: aload #20
    //   2174: iconst_4
    //   2175: iaload
    //   2176: iastore
    //   2177: aload #20
    //   2179: iconst_4
    //   2180: aload #20
    //   2182: iconst_3
    //   2183: iaload
    //   2184: iastore
    //   2185: aload #20
    //   2187: iconst_3
    //   2188: aload #20
    //   2190: iconst_2
    //   2191: iaload
    //   2192: iastore
    //   2193: aload #20
    //   2195: iconst_2
    //   2196: aload #20
    //   2198: iconst_1
    //   2199: iaload
    //   2200: iastore
    //   2201: aload #20
    //   2203: iconst_1
    //   2204: aload #20
    //   2206: iconst_0
    //   2207: iaload
    //   2208: iastore
    //   2209: aload #20
    //   2211: iconst_0
    //   2212: iload #22
    //   2214: iastore
    //   2215: iinc #21, 1
    //   2218: iload_2
    //   2219: ifne -> 1727
    //   2222: iconst_0
    //   2223: istore #21
    //   2225: iload #21
    //   2227: bipush #8
    //   2229: if_icmpge -> 2252
    //   2232: aload #8
    //   2234: iload #21
    //   2236: dup2
    //   2237: iaload
    //   2238: aload #20
    //   2240: iload #21
    //   2242: iaload
    //   2243: iadd
    //   2244: iastore
    //   2245: iinc #21, 1
    //   2248: iload_2
    //   2249: ifne -> 2225
    //   2252: iload #13
    //   2254: iload #18
    //   2256: iadd
    //   2257: istore #13
    //   2259: iload #17
    //   2261: iload #18
    //   2263: isub
    //   2264: istore #17
    //   2266: iconst_0
    //   2267: istore #12
    //   2269: iload #17
    //   2271: bipush #64
    //   2273: if_icmplt -> 2883
    //   2276: iconst_0
    //   2277: istore #19
    //   2279: iload #19
    //   2281: bipush #64
    //   2283: if_icmpge -> 2306
    //   2286: aload #10
    //   2288: iload #19
    //   2290: aload #5
    //   2292: iload #13
    //   2294: iload #19
    //   2296: iadd
    //   2297: baload
    //   2298: bastore
    //   2299: iinc #19, 1
    //   2302: iload_2
    //   2303: ifne -> 2279
    //   2306: bipush #64
    //   2308: newarray int
    //   2310: astore #19
    //   2312: bipush #8
    //   2314: newarray int
    //   2316: astore #20
    //   2318: iconst_0
    //   2319: istore #21
    //   2321: iload #21
    //   2323: bipush #8
    //   2325: if_icmpge -> 2345
    //   2328: aload #20
    //   2330: iload #21
    //   2332: aload #8
    //   2334: iload #21
    //   2336: iaload
    //   2337: iastore
    //   2338: iinc #21, 1
    //   2341: iload_2
    //   2342: ifne -> 2321
    //   2345: iconst_0
    //   2346: istore #21
    //   2348: iload #21
    //   2350: bipush #64
    //   2352: if_icmpge -> 2843
    //   2355: iload #21
    //   2357: bipush #16
    //   2359: if_icmpge -> 2440
    //   2362: aload #19
    //   2364: iload #21
    //   2366: aload #10
    //   2368: iconst_4
    //   2369: iload #21
    //   2371: imul
    //   2372: baload
    //   2373: sipush #255
    //   2376: iand
    //   2377: bipush #24
    //   2379: ishl
    //   2380: aload #10
    //   2382: iconst_4
    //   2383: iload #21
    //   2385: imul
    //   2386: iconst_1
    //   2387: iadd
    //   2388: baload
    //   2389: sipush #255
    //   2392: iand
    //   2393: bipush #16
    //   2395: ishl
    //   2396: ior
    //   2397: aload #10
    //   2399: iconst_4
    //   2400: iload #21
    //   2402: imul
    //   2403: iconst_2
    //   2404: iadd
    //   2405: baload
    //   2406: sipush #255
    //   2409: iand
    //   2410: bipush #8
    //   2412: ishl
    //   2413: ior
    //   2414: aload #10
    //   2416: iconst_4
    //   2417: iload #21
    //   2419: imul
    //   2420: iconst_3
    //   2421: iadd
    //   2422: baload
    //   2423: sipush #255
    //   2426: iand
    //   2427: ior
    //   2428: iastore
    //   2429: iload_2
    //   2430: ifne -> 2583
    //   2433: goto -> 2440
    //   2436: invokestatic a : (Ljava/lang/Throwable;)Ljava/lang/Throwable;
    //   2439: athrow
    //   2440: aload #19
    //   2442: iload #21
    //   2444: aload #19
    //   2446: iload #21
    //   2448: iconst_2
    //   2449: isub
    //   2450: iaload
    //   2451: bipush #17
    //   2453: iushr
    //   2454: aload #19
    //   2456: iload #21
    //   2458: iconst_2
    //   2459: isub
    //   2460: iaload
    //   2461: bipush #15
    //   2463: ishl
    //   2464: ior
    //   2465: aload #19
    //   2467: iload #21
    //   2469: iconst_2
    //   2470: isub
    //   2471: iaload
    //   2472: bipush #19
    //   2474: iushr
    //   2475: aload #19
    //   2477: iload #21
    //   2479: iconst_2
    //   2480: isub
    //   2481: iaload
    //   2482: bipush #13
    //   2484: ishl
    //   2485: ior
    //   2486: ixor
    //   2487: aload #19
    //   2489: iload #21
    //   2491: iconst_2
    //   2492: isub
    //   2493: iaload
    //   2494: bipush #10
    //   2496: iushr
    //   2497: ixor
    //   2498: aload #19
    //   2500: iload #21
    //   2502: bipush #7
    //   2504: isub
    //   2505: iaload
    //   2506: iadd
    //   2507: aload #19
    //   2509: iload #21
    //   2511: bipush #15
    //   2513: isub
    //   2514: iaload
    //   2515: bipush #7
    //   2517: iushr
    //   2518: aload #19
    //   2520: iload #21
    //   2522: bipush #15
    //   2524: isub
    //   2525: iaload
    //   2526: bipush #25
    //   2528: ishl
    //   2529: ior
    //   2530: aload #19
    //   2532: iload #21
    //   2534: bipush #15
    //   2536: isub
    //   2537: iaload
    //   2538: bipush #18
    //   2540: iushr
    //   2541: aload #19
    //   2543: iload #21
    //   2545: bipush #15
    //   2547: isub
    //   2548: iaload
    //   2549: bipush #14
    //   2551: ishl
    //   2552: ior
    //   2553: ixor
    //   2554: aload #19
    //   2556: iload #21
    //   2558: bipush #15
    //   2560: isub
    //   2561: iaload
    //   2562: iconst_3
    //   2563: iushr
    //   2564: ixor
    //   2565: iadd
    //   2566: aload #19
    //   2568: iload #21
    //   2570: bipush #16
    //   2572: isub
    //   2573: iaload
    //   2574: iadd
    //   2575: iastore
    //   2576: goto -> 2583
    //   2579: invokestatic a : (Ljava/lang/Throwable;)Ljava/lang/Throwable;
    //   2582: athrow
    //   2583: aload #20
    //   2585: bipush #7
    //   2587: iaload
    //   2588: aload #20
    //   2590: iconst_4
    //   2591: iaload
    //   2592: bipush #6
    //   2594: iushr
    //   2595: aload #20
    //   2597: iconst_4
    //   2598: iaload
    //   2599: bipush #26
    //   2601: ishl
    //   2602: ior
    //   2603: aload #20
    //   2605: iconst_4
    //   2606: iaload
    //   2607: bipush #11
    //   2609: iushr
    //   2610: aload #20
    //   2612: iconst_4
    //   2613: iaload
    //   2614: bipush #21
    //   2616: ishl
    //   2617: ior
    //   2618: ixor
    //   2619: aload #20
    //   2621: iconst_4
    //   2622: iaload
    //   2623: bipush #25
    //   2625: iushr
    //   2626: aload #20
    //   2628: iconst_4
    //   2629: iaload
    //   2630: bipush #7
    //   2632: ishl
    //   2633: ior
    //   2634: ixor
    //   2635: iadd
    //   2636: aload #20
    //   2638: bipush #6
    //   2640: iaload
    //   2641: aload #20
    //   2643: iconst_4
    //   2644: iaload
    //   2645: aload #20
    //   2647: iconst_5
    //   2648: iaload
    //   2649: aload #20
    //   2651: bipush #6
    //   2653: iaload
    //   2654: ixor
    //   2655: iand
    //   2656: ixor
    //   2657: iadd
    //   2658: aload #6
    //   2660: iload #21
    //   2662: iaload
    //   2663: iadd
    //   2664: aload #19
    //   2666: iload #21
    //   2668: iaload
    //   2669: iadd
    //   2670: istore #22
    //   2672: aload #20
    //   2674: iconst_0
    //   2675: iaload
    //   2676: iconst_2
    //   2677: iushr
    //   2678: aload #20
    //   2680: iconst_0
    //   2681: iaload
    //   2682: bipush #30
    //   2684: ishl
    //   2685: ior
    //   2686: aload #20
    //   2688: iconst_0
    //   2689: iaload
    //   2690: bipush #13
    //   2692: iushr
    //   2693: aload #20
    //   2695: iconst_0
    //   2696: iaload
    //   2697: bipush #19
    //   2699: ishl
    //   2700: ior
    //   2701: ixor
    //   2702: aload #20
    //   2704: iconst_0
    //   2705: iaload
    //   2706: bipush #22
    //   2708: iushr
    //   2709: aload #20
    //   2711: iconst_0
    //   2712: iaload
    //   2713: bipush #10
    //   2715: ishl
    //   2716: ior
    //   2717: ixor
    //   2718: aload #20
    //   2720: iconst_0
    //   2721: iaload
    //   2722: aload #20
    //   2724: iconst_1
    //   2725: iaload
    //   2726: iand
    //   2727: aload #20
    //   2729: iconst_2
    //   2730: iaload
    //   2731: aload #20
    //   2733: iconst_0
    //   2734: iaload
    //   2735: aload #20
    //   2737: iconst_1
    //   2738: iaload
    //   2739: ior
    //   2740: iand
    //   2741: ior
    //   2742: iadd
    //   2743: istore #23
    //   2745: aload #20
    //   2747: iconst_3
    //   2748: dup2
    //   2749: iaload
    //   2750: iload #22
    //   2752: iadd
    //   2753: iastore
    //   2754: aload #20
    //   2756: bipush #7
    //   2758: iload #22
    //   2760: iload #23
    //   2762: iadd
    //   2763: iastore
    //   2764: aload #20
    //   2766: bipush #7
    //   2768: iaload
    //   2769: istore #22
    //   2771: aload #20
    //   2773: bipush #7
    //   2775: aload #20
    //   2777: bipush #6
    //   2779: iaload
    //   2780: iastore
    //   2781: aload #20
    //   2783: bipush #6
    //   2785: aload #20
    //   2787: iconst_5
    //   2788: iaload
    //   2789: iastore
    //   2790: aload #20
    //   2792: iconst_5
    //   2793: aload #20
    //   2795: iconst_4
    //   2796: iaload
    //   2797: iastore
    //   2798: aload #20
    //   2800: iconst_4
    //   2801: aload #20
    //   2803: iconst_3
    //   2804: iaload
    //   2805: iastore
    //   2806: aload #20
    //   2808: iconst_3
    //   2809: aload #20
    //   2811: iconst_2
    //   2812: iaload
    //   2813: iastore
    //   2814: aload #20
    //   2816: iconst_2
    //   2817: aload #20
    //   2819: iconst_1
    //   2820: iaload
    //   2821: iastore
    //   2822: aload #20
    //   2824: iconst_1
    //   2825: aload #20
    //   2827: iconst_0
    //   2828: iaload
    //   2829: iastore
    //   2830: aload #20
    //   2832: iconst_0
    //   2833: iload #22
    //   2835: iastore
    //   2836: iinc #21, 1
    //   2839: iload_2
    //   2840: ifne -> 2348
    //   2843: iconst_0
    //   2844: istore #21
    //   2846: iload #21
    //   2848: bipush #8
    //   2850: if_icmpge -> 2873
    //   2853: aload #8
    //   2855: iload #21
    //   2857: dup2
    //   2858: iaload
    //   2859: aload #20
    //   2861: iload #21
    //   2863: iaload
    //   2864: iadd
    //   2865: iastore
    //   2866: iinc #21, 1
    //   2869: iload_2
    //   2870: ifne -> 2846
    //   2873: iinc #13, 64
    //   2876: iinc #17, -64
    //   2879: iload_2
    //   2880: ifne -> 2269
    //   2883: iload #17
    //   2885: ifle -> 2921
    //   2888: iconst_0
    //   2889: istore #19
    //   2891: iload #19
    //   2893: iload #17
    //   2895: if_icmpge -> 2921
    //   2898: aload #9
    //   2900: iload #12
    //   2902: iload #19
    //   2904: iadd
    //   2905: aload #5
    //   2907: iload #13
    //   2909: iload #19
    //   2911: iadd
    //   2912: baload
    //   2913: bastore
    //   2914: iinc #19, 1
    //   2917: iload_2
    //   2918: ifne -> 2891
    //   2921: bipush #8
    //   2923: newarray byte
    //   2925: astore #19
    //   2927: aload #19
    //   2929: iconst_0
    //   2930: iload #14
    //   2932: bipush #24
    //   2934: iushr
    //   2935: i2b
    //   2936: bastore
    //   2937: aload #19
    //   2939: iconst_1
    //   2940: iload #14
    //   2942: bipush #16
    //   2944: iushr
    //   2945: i2b
    //   2946: bastore
    //   2947: aload #19
    //   2949: iconst_2
    //   2950: iload #14
    //   2952: bipush #8
    //   2954: iushr
    //   2955: i2b
    //   2956: bastore
    //   2957: aload #19
    //   2959: iconst_3
    //   2960: iload #14
    //   2962: i2b
    //   2963: bastore
    //   2964: aload #19
    //   2966: iconst_4
    //   2967: iload #15
    //   2969: bipush #24
    //   2971: iushr
    //   2972: i2b
    //   2973: bastore
    //   2974: aload #19
    //   2976: iconst_5
    //   2977: iload #15
    //   2979: bipush #16
    //   2981: iushr
    //   2982: i2b
    //   2983: bastore
    //   2984: aload #19
    //   2986: bipush #6
    //   2988: iload #15
    //   2990: bipush #8
    //   2992: iushr
    //   2993: i2b
    //   2994: bastore
    //   2995: aload #19
    //   2997: bipush #7
    //   2999: iload #15
    //   3001: i2b
    //   3002: bastore
    //   3003: bipush #8
    //   3005: istore #11
    //   3007: aload #7
    //   3009: iconst_0
    //   3010: iaload
    //   3011: bipush #63
    //   3013: iand
    //   3014: istore #12
    //   3016: bipush #64
    //   3018: iload #12
    //   3020: isub
    //   3021: istore #18
    //   3023: aload #7
    //   3025: iconst_0
    //   3026: dup2
    //   3027: iaload
    //   3028: iload #11
    //   3030: iadd
    //   3031: iastore
    //   3032: aload #7
    //   3034: iconst_0
    //   3035: dup2
    //   3036: iaload
    //   3037: iconst_m1
    //   3038: iand
    //   3039: iastore
    //   3040: aload #7
    //   3042: iconst_0
    //   3043: iaload
    //   3044: iload #11
    //   3046: if_icmpge -> 3064
    //   3049: aload #7
    //   3051: iconst_1
    //   3052: dup2
    //   3053: iaload
    //   3054: iconst_1
    //   3055: iadd
    //   3056: iastore
    //   3057: goto -> 3064
    //   3060: invokestatic a : (Ljava/lang/Throwable;)Ljava/lang/Throwable;
    //   3063: athrow
    //   3064: iload #12
    //   3066: ifle -> 3680
    //   3069: iload #11
    //   3071: iload #18
    //   3073: if_icmplt -> 3680
    //   3076: goto -> 3083
    //   3079: invokestatic a : (Ljava/lang/Throwable;)Ljava/lang/Throwable;
    //   3082: athrow
    //   3083: iconst_0
    //   3084: istore #20
    //   3086: iload #20
    //   3088: iload #18
    //   3090: if_icmpge -> 3113
    //   3093: aload #9
    //   3095: iload #12
    //   3097: iload #20
    //   3099: iadd
    //   3100: aload #19
    //   3102: iload #20
    //   3104: baload
    //   3105: bastore
    //   3106: iinc #20, 1
    //   3109: iload_2
    //   3110: ifne -> 3086
    //   3113: bipush #64
    //   3115: newarray int
    //   3117: astore #20
    //   3119: bipush #8
    //   3121: newarray int
    //   3123: astore #21
    //   3125: iconst_0
    //   3126: istore #22
    //   3128: iload #22
    //   3130: bipush #8
    //   3132: if_icmpge -> 3152
    //   3135: aload #21
    //   3137: iload #22
    //   3139: aload #8
    //   3141: iload #22
    //   3143: iaload
    //   3144: iastore
    //   3145: iinc #22, 1
    //   3148: iload_2
    //   3149: ifne -> 3128
    //   3152: iconst_0
    //   3153: istore #22
    //   3155: iload #22
    //   3157: bipush #64
    //   3159: if_icmpge -> 3650
    //   3162: iload #22
    //   3164: bipush #16
    //   3166: if_icmpge -> 3247
    //   3169: aload #20
    //   3171: iload #22
    //   3173: aload #9
    //   3175: iconst_4
    //   3176: iload #22
    //   3178: imul
    //   3179: baload
    //   3180: sipush #255
    //   3183: iand
    //   3184: bipush #24
    //   3186: ishl
    //   3187: aload #9
    //   3189: iconst_4
    //   3190: iload #22
    //   3192: imul
    //   3193: iconst_1
    //   3194: iadd
    //   3195: baload
    //   3196: sipush #255
    //   3199: iand
    //   3200: bipush #16
    //   3202: ishl
    //   3203: ior
    //   3204: aload #9
    //   3206: iconst_4
    //   3207: iload #22
    //   3209: imul
    //   3210: iconst_2
    //   3211: iadd
    //   3212: baload
    //   3213: sipush #255
    //   3216: iand
    //   3217: bipush #8
    //   3219: ishl
    //   3220: ior
    //   3221: aload #9
    //   3223: iconst_4
    //   3224: iload #22
    //   3226: imul
    //   3227: iconst_3
    //   3228: iadd
    //   3229: baload
    //   3230: sipush #255
    //   3233: iand
    //   3234: ior
    //   3235: iastore
    //   3236: iload_2
    //   3237: ifne -> 3390
    //   3240: goto -> 3247
    //   3243: invokestatic a : (Ljava/lang/Throwable;)Ljava/lang/Throwable;
    //   3246: athrow
    //   3247: aload #20
    //   3249: iload #22
    //   3251: aload #20
    //   3253: iload #22
    //   3255: iconst_2
    //   3256: isub
    //   3257: iaload
    //   3258: bipush #17
    //   3260: iushr
    //   3261: aload #20
    //   3263: iload #22
    //   3265: iconst_2
    //   3266: isub
    //   3267: iaload
    //   3268: bipush #15
    //   3270: ishl
    //   3271: ior
    //   3272: aload #20
    //   3274: iload #22
    //   3276: iconst_2
    //   3277: isub
    //   3278: iaload
    //   3279: bipush #19
    //   3281: iushr
    //   3282: aload #20
    //   3284: iload #22
    //   3286: iconst_2
    //   3287: isub
    //   3288: iaload
    //   3289: bipush #13
    //   3291: ishl
    //   3292: ior
    //   3293: ixor
    //   3294: aload #20
    //   3296: iload #22
    //   3298: iconst_2
    //   3299: isub
    //   3300: iaload
    //   3301: bipush #10
    //   3303: iushr
    //   3304: ixor
    //   3305: aload #20
    //   3307: iload #22
    //   3309: bipush #7
    //   3311: isub
    //   3312: iaload
    //   3313: iadd
    //   3314: aload #20
    //   3316: iload #22
    //   3318: bipush #15
    //   3320: isub
    //   3321: iaload
    //   3322: bipush #7
    //   3324: iushr
    //   3325: aload #20
    //   3327: iload #22
    //   3329: bipush #15
    //   3331: isub
    //   3332: iaload
    //   3333: bipush #25
    //   3335: ishl
    //   3336: ior
    //   3337: aload #20
    //   3339: iload #22
    //   3341: bipush #15
    //   3343: isub
    //   3344: iaload
    //   3345: bipush #18
    //   3347: iushr
    //   3348: aload #20
    //   3350: iload #22
    //   3352: bipush #15
    //   3354: isub
    //   3355: iaload
    //   3356: bipush #14
    //   3358: ishl
    //   3359: ior
    //   3360: ixor
    //   3361: aload #20
    //   3363: iload #22
    //   3365: bipush #15
    //   3367: isub
    //   3368: iaload
    //   3369: iconst_3
    //   3370: iushr
    //   3371: ixor
    //   3372: iadd
    //   3373: aload #20
    //   3375: iload #22
    //   3377: bipush #16
    //   3379: isub
    //   3380: iaload
    //   3381: iadd
    //   3382: iastore
    //   3383: goto -> 3390
    //   3386: invokestatic a : (Ljava/lang/Throwable;)Ljava/lang/Throwable;
    //   3389: athrow
    //   3390: aload #21
    //   3392: bipush #7
    //   3394: iaload
    //   3395: aload #21
    //   3397: iconst_4
    //   3398: iaload
    //   3399: bipush #6
    //   3401: iushr
    //   3402: aload #21
    //   3404: iconst_4
    //   3405: iaload
    //   3406: bipush #26
    //   3408: ishl
    //   3409: ior
    //   3410: aload #21
    //   3412: iconst_4
    //   3413: iaload
    //   3414: bipush #11
    //   3416: iushr
    //   3417: aload #21
    //   3419: iconst_4
    //   3420: iaload
    //   3421: bipush #21
    //   3423: ishl
    //   3424: ior
    //   3425: ixor
    //   3426: aload #21
    //   3428: iconst_4
    //   3429: iaload
    //   3430: bipush #25
    //   3432: iushr
    //   3433: aload #21
    //   3435: iconst_4
    //   3436: iaload
    //   3437: bipush #7
    //   3439: ishl
    //   3440: ior
    //   3441: ixor
    //   3442: iadd
    //   3443: aload #21
    //   3445: bipush #6
    //   3447: iaload
    //   3448: aload #21
    //   3450: iconst_4
    //   3451: iaload
    //   3452: aload #21
    //   3454: iconst_5
    //   3455: iaload
    //   3456: aload #21
    //   3458: bipush #6
    //   3460: iaload
    //   3461: ixor
    //   3462: iand
    //   3463: ixor
    //   3464: iadd
    //   3465: aload #6
    //   3467: iload #22
    //   3469: iaload
    //   3470: iadd
    //   3471: aload #20
    //   3473: iload #22
    //   3475: iaload
    //   3476: iadd
    //   3477: istore #23
    //   3479: aload #21
    //   3481: iconst_0
    //   3482: iaload
    //   3483: iconst_2
    //   3484: iushr
    //   3485: aload #21
    //   3487: iconst_0
    //   3488: iaload
    //   3489: bipush #30
    //   3491: ishl
    //   3492: ior
    //   3493: aload #21
    //   3495: iconst_0
    //   3496: iaload
    //   3497: bipush #13
    //   3499: iushr
    //   3500: aload #21
    //   3502: iconst_0
    //   3503: iaload
    //   3504: bipush #19
    //   3506: ishl
    //   3507: ior
    //   3508: ixor
    //   3509: aload #21
    //   3511: iconst_0
    //   3512: iaload
    //   3513: bipush #22
    //   3515: iushr
    //   3516: aload #21
    //   3518: iconst_0
    //   3519: iaload
    //   3520: bipush #10
    //   3522: ishl
    //   3523: ior
    //   3524: ixor
    //   3525: aload #21
    //   3527: iconst_0
    //   3528: iaload
    //   3529: aload #21
    //   3531: iconst_1
    //   3532: iaload
    //   3533: iand
    //   3534: aload #21
    //   3536: iconst_2
    //   3537: iaload
    //   3538: aload #21
    //   3540: iconst_0
    //   3541: iaload
    //   3542: aload #21
    //   3544: iconst_1
    //   3545: iaload
    //   3546: ior
    //   3547: iand
    //   3548: ior
    //   3549: iadd
    //   3550: istore #24
    //   3552: aload #21
    //   3554: iconst_3
    //   3555: dup2
    //   3556: iaload
    //   3557: iload #23
    //   3559: iadd
    //   3560: iastore
    //   3561: aload #21
    //   3563: bipush #7
    //   3565: iload #23
    //   3567: iload #24
    //   3569: iadd
    //   3570: iastore
    //   3571: aload #21
    //   3573: bipush #7
    //   3575: iaload
    //   3576: istore #23
    //   3578: aload #21
    //   3580: bipush #7
    //   3582: aload #21
    //   3584: bipush #6
    //   3586: iaload
    //   3587: iastore
    //   3588: aload #21
    //   3590: bipush #6
    //   3592: aload #21
    //   3594: iconst_5
    //   3595: iaload
    //   3596: iastore
    //   3597: aload #21
    //   3599: iconst_5
    //   3600: aload #21
    //   3602: iconst_4
    //   3603: iaload
    //   3604: iastore
    //   3605: aload #21
    //   3607: iconst_4
    //   3608: aload #21
    //   3610: iconst_3
    //   3611: iaload
    //   3612: iastore
    //   3613: aload #21
    //   3615: iconst_3
    //   3616: aload #21
    //   3618: iconst_2
    //   3619: iaload
    //   3620: iastore
    //   3621: aload #21
    //   3623: iconst_2
    //   3624: aload #21
    //   3626: iconst_1
    //   3627: iaload
    //   3628: iastore
    //   3629: aload #21
    //   3631: iconst_1
    //   3632: aload #21
    //   3634: iconst_0
    //   3635: iaload
    //   3636: iastore
    //   3637: aload #21
    //   3639: iconst_0
    //   3640: iload #23
    //   3642: iastore
    //   3643: iinc #22, 1
    //   3646: iload_2
    //   3647: ifne -> 3155
    //   3650: iconst_0
    //   3651: istore #22
    //   3653: iload #22
    //   3655: bipush #8
    //   3657: if_icmpge -> 3680
    //   3660: aload #8
    //   3662: iload #22
    //   3664: dup2
    //   3665: iaload
    //   3666: aload #21
    //   3668: iload #22
    //   3670: iaload
    //   3671: iadd
    //   3672: iastore
    //   3673: iinc #22, 1
    //   3676: iload_2
    //   3677: ifne -> 3653
    //   3680: bipush #32
    //   3682: newarray byte
    //   3684: astore #4
    //   3686: sipush #-19535
    //   3689: aload #4
    //   3691: iconst_0
    //   3692: aload #8
    //   3694: iconst_0
    //   3695: iaload
    //   3696: bipush #24
    //   3698: iushr
    //   3699: i2b
    //   3700: bastore
    //   3701: sipush #14042
    //   3704: aload #4
    //   3706: iconst_1
    //   3707: aload #8
    //   3709: iconst_0
    //   3710: iaload
    //   3711: bipush #16
    //   3713: iushr
    //   3714: i2b
    //   3715: bastore
    //   3716: aload #4
    //   3718: iconst_2
    //   3719: aload #8
    //   3721: iconst_0
    //   3722: iaload
    //   3723: bipush #8
    //   3725: iushr
    //   3726: i2b
    //   3727: bastore
    //   3728: aload #4
    //   3730: iconst_3
    //   3731: aload #8
    //   3733: iconst_0
    //   3734: iaload
    //   3735: i2b
    //   3736: bastore
    //   3737: aload #4
    //   3739: iconst_4
    //   3740: aload #8
    //   3742: iconst_1
    //   3743: iaload
    //   3744: bipush #24
    //   3746: iushr
    //   3747: i2b
    //   3748: bastore
    //   3749: aload #4
    //   3751: iconst_5
    //   3752: aload #8
    //   3754: iconst_1
    //   3755: iaload
    //   3756: bipush #16
    //   3758: iushr
    //   3759: i2b
    //   3760: bastore
    //   3761: aload #4
    //   3763: bipush #6
    //   3765: aload #8
    //   3767: iconst_1
    //   3768: iaload
    //   3769: bipush #8
    //   3771: iushr
    //   3772: i2b
    //   3773: bastore
    //   3774: aload #4
    //   3776: bipush #7
    //   3778: aload #8
    //   3780: iconst_1
    //   3781: iaload
    //   3782: i2b
    //   3783: bastore
    //   3784: aload #4
    //   3786: bipush #8
    //   3788: aload #8
    //   3790: iconst_2
    //   3791: iaload
    //   3792: bipush #24
    //   3794: iushr
    //   3795: i2b
    //   3796: bastore
    //   3797: aload #4
    //   3799: bipush #9
    //   3801: aload #8
    //   3803: iconst_2
    //   3804: iaload
    //   3805: bipush #16
    //   3807: iushr
    //   3808: i2b
    //   3809: bastore
    //   3810: aload #4
    //   3812: bipush #10
    //   3814: aload #8
    //   3816: iconst_2
    //   3817: iaload
    //   3818: bipush #8
    //   3820: iushr
    //   3821: i2b
    //   3822: bastore
    //   3823: aload #4
    //   3825: bipush #11
    //   3827: aload #8
    //   3829: iconst_2
    //   3830: iaload
    //   3831: i2b
    //   3832: bastore
    //   3833: aload #4
    //   3835: bipush #12
    //   3837: aload #8
    //   3839: iconst_3
    //   3840: iaload
    //   3841: bipush #24
    //   3843: iushr
    //   3844: i2b
    //   3845: bastore
    //   3846: aload #4
    //   3848: bipush #13
    //   3850: aload #8
    //   3852: iconst_3
    //   3853: iaload
    //   3854: bipush #16
    //   3856: iushr
    //   3857: i2b
    //   3858: bastore
    //   3859: aload #4
    //   3861: bipush #14
    //   3863: aload #8
    //   3865: iconst_3
    //   3866: iaload
    //   3867: bipush #8
    //   3869: iushr
    //   3870: i2b
    //   3871: bastore
    //   3872: aload #4
    //   3874: bipush #15
    //   3876: aload #8
    //   3878: iconst_3
    //   3879: iaload
    //   3880: i2b
    //   3881: bastore
    //   3882: aload #4
    //   3884: bipush #16
    //   3886: aload #8
    //   3888: iconst_4
    //   3889: iaload
    //   3890: bipush #24
    //   3892: iushr
    //   3893: i2b
    //   3894: bastore
    //   3895: aload #4
    //   3897: bipush #17
    //   3899: aload #8
    //   3901: iconst_4
    //   3902: iaload
    //   3903: bipush #16
    //   3905: iushr
    //   3906: i2b
    //   3907: bastore
    //   3908: aload #4
    //   3910: bipush #18
    //   3912: aload #8
    //   3914: iconst_4
    //   3915: iaload
    //   3916: bipush #8
    //   3918: iushr
    //   3919: i2b
    //   3920: bastore
    //   3921: aload #4
    //   3923: bipush #19
    //   3925: aload #8
    //   3927: iconst_4
    //   3928: iaload
    //   3929: i2b
    //   3930: bastore
    //   3931: aload #4
    //   3933: bipush #20
    //   3935: aload #8
    //   3937: iconst_5
    //   3938: iaload
    //   3939: bipush #24
    //   3941: iushr
    //   3942: i2b
    //   3943: bastore
    //   3944: aload #4
    //   3946: bipush #21
    //   3948: aload #8
    //   3950: iconst_5
    //   3951: iaload
    //   3952: bipush #16
    //   3954: iushr
    //   3955: i2b
    //   3956: bastore
    //   3957: aload #4
    //   3959: bipush #22
    //   3961: aload #8
    //   3963: iconst_5
    //   3964: iaload
    //   3965: bipush #8
    //   3967: iushr
    //   3968: i2b
    //   3969: bastore
    //   3970: aload #4
    //   3972: bipush #23
    //   3974: aload #8
    //   3976: iconst_5
    //   3977: iaload
    //   3978: i2b
    //   3979: bastore
    //   3980: aload #4
    //   3982: bipush #24
    //   3984: aload #8
    //   3986: bipush #6
    //   3988: iaload
    //   3989: bipush #24
    //   3991: iushr
    //   3992: i2b
    //   3993: bastore
    //   3994: aload #4
    //   3996: bipush #25
    //   3998: aload #8
    //   4000: bipush #6
    //   4002: iaload
    //   4003: bipush #16
    //   4005: iushr
    //   4006: i2b
    //   4007: bastore
    //   4008: aload #4
    //   4010: bipush #26
    //   4012: aload #8
    //   4014: bipush #6
    //   4016: iaload
    //   4017: bipush #8
    //   4019: iushr
    //   4020: i2b
    //   4021: bastore
    //   4022: aload #4
    //   4024: bipush #27
    //   4026: aload #8
    //   4028: bipush #6
    //   4030: iaload
    //   4031: i2b
    //   4032: bastore
    //   4033: aload #4
    //   4035: bipush #28
    //   4037: aload #8
    //   4039: bipush #7
    //   4041: iaload
    //   4042: bipush #24
    //   4044: iushr
    //   4045: i2b
    //   4046: bastore
    //   4047: aload #4
    //   4049: bipush #29
    //   4051: aload #8
    //   4053: bipush #7
    //   4055: iaload
    //   4056: bipush #16
    //   4058: iushr
    //   4059: i2b
    //   4060: bastore
    //   4061: aload #4
    //   4063: bipush #30
    //   4065: aload #8
    //   4067: bipush #7
    //   4069: iaload
    //   4070: bipush #8
    //   4072: iushr
    //   4073: i2b
    //   4074: bastore
    //   4075: aload #4
    //   4077: bipush #31
    //   4079: aload #8
    //   4081: bipush #7
    //   4083: iaload
    //   4084: i2b
    //   4085: bastore
    //   4086: new java/math/BigInteger
    //   4089: dup
    //   4090: aload #4
    //   4092: invokespecial <init> : ([B)V
    //   4095: invokevirtual abs : ()Ljava/math/BigInteger;
    //   4098: putstatic burp/Zenr.ZA : Ljava/lang/Object;
    //   4101: invokestatic a : (II)Ljava/lang/String;
    //   4104: iconst_1
    //   4105: ldc burp/Zg7z
    //   4107: invokevirtual getClassLoader : ()Ljava/lang/ClassLoader;
    //   4110: invokestatic forName : (Ljava/lang/String;ZLjava/lang/ClassLoader;)Ljava/lang/Class;
    //   4113: invokevirtual getDeclaredFields : ()[Ljava/lang/reflect/Field;
    //   4116: astore_3
    //   4117: aload_3
    //   4118: arraylength
    //   4119: istore #4
    //   4121: iconst_0
    //   4122: istore #5
    //   4124: iload #5
    //   4126: iload #4
    //   4128: if_icmpge -> 4265
    //   4131: aload_3
    //   4132: iload #5
    //   4134: aaload
    //   4135: astore #6
    //   4137: aload #6
    //   4139: invokevirtual getModifiers : ()I
    //   4142: invokestatic isStatic : (I)Z
    //   4145: ifne -> 4155
    //   4148: goto -> 4258
    //   4151: invokestatic a : (Ljava/lang/Throwable;)Ljava/lang/Throwable;
    //   4154: athrow
    //   4155: aload #6
    //   4157: invokevirtual getType : ()Ljava/lang/Class;
    //   4160: astore #7
    //   4162: aload #7
    //   4164: ifnull -> 4245
    //   4167: aload #7
    //   4169: invokevirtual isPrimitive : ()Z
    //   4172: ifne -> 4245
    //   4175: goto -> 4182
    //   4178: invokestatic a : (Ljava/lang/Throwable;)Ljava/lang/Throwable;
    //   4181: athrow
    //   4182: aload #7
    //   4184: invokevirtual getPackage : ()Ljava/lang/Package;
    //   4187: ifnull -> 4245
    //   4190: goto -> 4197
    //   4193: invokestatic a : (Ljava/lang/Throwable;)Ljava/lang/Throwable;
    //   4196: athrow
    //   4197: aload #7
    //   4199: invokevirtual getPackage : ()Ljava/lang/Package;
    //   4202: invokevirtual getName : ()Ljava/lang/String;
    //   4205: ifnull -> 4245
    //   4208: goto -> 4215
    //   4211: invokestatic a : (Ljava/lang/Throwable;)Ljava/lang/Throwable;
    //   4214: athrow
    //   4215: aload #7
    //   4217: invokevirtual getPackage : ()Ljava/lang/Package;
    //   4220: invokevirtual getName : ()Ljava/lang/String;
    //   4223: sipush #-19543
    //   4226: sipush #5335
    //   4229: invokestatic a : (II)Ljava/lang/String;
    //   4232: invokevirtual startsWith : (Ljava/lang/String;)Z
    //   4235: ifne -> 4245
    //   4238: goto -> 4245
    //   4241: invokestatic a : (Ljava/lang/Throwable;)Ljava/lang/Throwable;
    //   4244: athrow
    //   4245: aload #6
    //   4247: iconst_1
    //   4248: invokevirtual setAccessible : (Z)V
    //   4251: aload #6
    //   4253: aconst_null
    //   4254: invokevirtual get : (Ljava/lang/Object;)Ljava/lang/Object;
    //   4257: pop
    //   4258: iinc #5, 1
    //   4261: iload_2
    //   4262: ifne -> 4124
    //   4265: sipush #-19522
    //   4268: sipush #10727
    //   4271: invokestatic a : (II)Ljava/lang/String;
    //   4274: invokestatic forName : (Ljava/lang/String;)Ljava/lang/Class;
    //   4277: invokevirtual getDeclaredMethods : ()[Ljava/lang/reflect/Method;
    //   4280: astore_3
    //   4281: aload_3
    //   4282: arraylength
    //   4283: istore #4
    //   4285: iconst_0
    //   4286: istore #5
    //   4288: iload #5
    //   4290: iload #4
    //   4292: if_icmpge -> 4424
    //   4295: aload_3
    //   4296: iload #5
    //   4298: aaload
    //   4299: astore #6
    //   4301: aload #6
    //   4303: invokevirtual getParameterTypes : ()[Ljava/lang/Class;
    //   4306: pop
    //   4307: aload #6
    //   4309: invokevirtual getModifiers : ()I
    //   4312: invokestatic isStatic : (I)Z
    //   4315: ifeq -> 4410
    //   4318: aload #6
    //   4320: invokevirtual getParameterTypes : ()[Ljava/lang/Class;
    //   4323: arraylength
    //   4324: iconst_2
    //   4325: if_icmpne -> 4410
    //   4328: goto -> 4335
    //   4331: invokestatic a : (Ljava/lang/Throwable;)Ljava/lang/Throwable;
    //   4334: athrow
    //   4335: aload #6
    //   4337: invokevirtual getReturnType : ()Ljava/lang/Class;
    //   4340: getstatic java/lang/Void.TYPE : Ljava/lang/Class;
    //   4343: invokevirtual equals : (Ljava/lang/Object;)Z
    //   4346: ifeq -> 4410
    //   4349: goto -> 4356
    //   4352: invokestatic a : (Ljava/lang/Throwable;)Ljava/lang/Throwable;
    //   4355: athrow
    //   4356: aload #6
    //   4358: iconst_1
    //   4359: invokevirtual setAccessible : (Z)V
    //   4362: aload #6
    //   4364: aconst_null
    //   4365: iconst_2
    //   4366: anewarray java/lang/Object
    //   4369: dup
    //   4370: iconst_0
    //   4371: aload_0
    //   4372: aastore
    //   4373: dup
    //   4374: iconst_1
    //   4375: aload_1
    //   4376: ifnonnull -> 4394
    //   4379: goto -> 4386
    //   4382: invokestatic a : (Ljava/lang/Throwable;)Ljava/lang/Throwable;
    //   4385: athrow
    //   4386: aload_1
    //   4387: goto -> 4401
    //   4390: invokestatic a : (Ljava/lang/Throwable;)Ljava/lang/Throwable;
    //   4393: athrow
    //   4394: aload_1
    //   4395: checkcast [B
    //   4398: invokevirtual clone : ()Ljava/lang/Object;
    //   4401: aastore
    //   4402: invokevirtual invoke : (Ljava/lang/Object;[Ljava/lang/Object;)Ljava/lang/Object;
    //   4405: pop
    //   4406: iload_2
    //   4407: ifne -> 4424
    //   4410: iinc #5, 1
    //   4413: iload_2
    //   4414: ifne -> 4288
    //   4417: goto -> 4424
    //   4420: invokestatic a : (Ljava/lang/Throwable;)Ljava/lang/Throwable;
    //   4423: athrow
    //   4424: iconst_0
    //   4425: istore_3
    //   4426: getstatic burp/Zsko.Zd : Ljava/lang/String;
    //   4429: getstatic burp/Zxdy.ZZ : Ljava/lang/Object;
    //   4432: checkcast java/math/BigInteger
    //   4435: invokevirtual intValue : ()I
    //   4438: bipush #32
    //   4440: irem
    //   4441: invokestatic abs : (I)I
    //   4444: invokevirtual charAt : (I)C
    //   4447: getstatic burp/Zkql.ZR : Ljava/lang/String;
    //   4450: getstatic burp/Zzts.Zp : Ljava/lang/Object;
    //   4453: checkcast java/math/BigInteger
    //   4456: invokevirtual intValue : ()I
    //   4459: bipush #32
    //   4461: irem
    //   4462: invokestatic abs : (I)I
    //   4465: invokevirtual charAt : (I)C
    //   4468: if_icmpgt -> 4812
    //   4471: sipush #-19552
    //   4474: sipush #-22881
    //   4477: invokestatic a : (II)Ljava/lang/String;
    //   4480: iconst_1
    //   4481: ldc burp/Zxl5
    //   4483: invokevirtual getClassLoader : ()Ljava/lang/ClassLoader;
    //   4486: invokestatic forName : (Ljava/lang/String;ZLjava/lang/ClassLoader;)Ljava/lang/Class;
    //   4489: invokevirtual getDeclaredFields : ()[Ljava/lang/reflect/Field;
    //   4492: astore #4
    //   4494: aload #4
    //   4496: arraylength
    //   4497: istore #5
    //   4499: iconst_0
    //   4500: istore #6
    //   4502: iload #6
    //   4504: iload #5
    //   4506: if_icmpge -> 4644
    //   4509: aload #4
    //   4511: iload #6
    //   4513: aaload
    //   4514: astore #7
    //   4516: aload #7
    //   4518: invokevirtual getModifiers : ()I
    //   4521: invokestatic isStatic : (I)Z
    //   4524: ifne -> 4534
    //   4527: goto -> 4637
    //   4530: invokestatic a : (Ljava/lang/Throwable;)Ljava/lang/Throwable;
    //   4533: athrow
    //   4534: aload #7
    //   4536: invokevirtual getType : ()Ljava/lang/Class;
    //   4539: astore #8
    //   4541: aload #8
    //   4543: ifnull -> 4624
    //   4546: aload #8
    //   4548: invokevirtual isPrimitive : ()Z
    //   4551: ifne -> 4624
    //   4554: goto -> 4561
    //   4557: invokestatic a : (Ljava/lang/Throwable;)Ljava/lang/Throwable;
    //   4560: athrow
    //   4561: aload #8
    //   4563: invokevirtual getPackage : ()Ljava/lang/Package;
    //   4566: ifnull -> 4624
    //   4569: goto -> 4576
    //   4572: invokestatic a : (Ljava/lang/Throwable;)Ljava/lang/Throwable;
    //   4575: athrow
    //   4576: aload #8
    //   4578: invokevirtual getPackage : ()Ljava/lang/Package;
    //   4581: invokevirtual getName : ()Ljava/lang/String;
    //   4584: ifnull -> 4624
    //   4587: goto -> 4594
    //   4590: invokestatic a : (Ljava/lang/Throwable;)Ljava/lang/Throwable;
    //   4593: athrow
    //   4594: aload #8
    //   4596: invokevirtual getPackage : ()Ljava/lang/Package;
    //   4599: invokevirtual getName : ()Ljava/lang/String;
    //   4602: sipush #-19539
    //   4605: sipush #23209
    //   4608: invokestatic a : (II)Ljava/lang/String;
    //   4611: invokevirtual startsWith : (Ljava/lang/String;)Z
    //   4614: ifne -> 4624
    //   4617: goto -> 4624
    //   4620: invokestatic a : (Ljava/lang/Throwable;)Ljava/lang/Throwable;
    //   4623: athrow
    //   4624: aload #7
    //   4626: iconst_1
    //   4627: invokevirtual setAccessible : (Z)V
    //   4630: aload #7
    //   4632: aconst_null
    //   4633: invokevirtual get : (Ljava/lang/Object;)Ljava/lang/Object;
    //   4636: pop
    //   4637: iinc #6, 1
    //   4640: iload_2
    //   4641: ifne -> 4502
    //   4644: sipush #-19540
    //   4647: sipush #-11529
    //   4650: invokestatic a : (II)Ljava/lang/String;
    //   4653: invokestatic forName : (Ljava/lang/String;)Ljava/lang/Class;
    //   4656: invokevirtual getDeclaredMethods : ()[Ljava/lang/reflect/Method;
    //   4659: astore #4
    //   4661: aload #4
    //   4663: arraylength
    //   4664: istore #5
    //   4666: iconst_0
    //   4667: istore #6
    //   4669: iload #6
    //   4671: iload #5
    //   4673: if_icmpge -> 4809
    //   4676: aload #4
    //   4678: iload #6
    //   4680: aaload
    //   4681: astore #7
    //   4683: aload #7
    //   4685: invokevirtual getParameterTypes : ()[Ljava/lang/Class;
    //   4688: pop
    //   4689: aload #7
    //   4691: invokevirtual getModifiers : ()I
    //   4694: invokestatic isStatic : (I)Z
    //   4697: ifeq -> 4795
    //   4700: aload #7
    //   4702: invokevirtual getParameterTypes : ()[Ljava/lang/Class;
    //   4705: arraylength
    //   4706: iconst_2
    //   4707: if_icmpne -> 4795
    //   4710: goto -> 4717
    //   4713: invokestatic a : (Ljava/lang/Throwable;)Ljava/lang/Throwable;
    //   4716: athrow
    //   4717: aload #7
    //   4719: invokevirtual getReturnType : ()Ljava/lang/Class;
    //   4722: getstatic java/lang/Boolean.TYPE : Ljava/lang/Class;
    //   4725: if_acmpne -> 4795
    //   4728: goto -> 4735
    //   4731: invokestatic a : (Ljava/lang/Throwable;)Ljava/lang/Throwable;
    //   4734: athrow
    //   4735: aload #7
    //   4737: iconst_1
    //   4738: invokevirtual setAccessible : (Z)V
    //   4741: aload #7
    //   4743: aconst_null
    //   4744: iconst_2
    //   4745: anewarray java/lang/Object
    //   4748: dup
    //   4749: iconst_0
    //   4750: aload_0
    //   4751: aastore
    //   4752: dup
    //   4753: iconst_1
    //   4754: aload_1
    //   4755: ifnonnull -> 4773
    //   4758: goto -> 4765
    //   4761: invokestatic a : (Ljava/lang/Throwable;)Ljava/lang/Throwable;
    //   4764: athrow
    //   4765: aload_1
    //   4766: goto -> 4780
    //   4769: invokestatic a : (Ljava/lang/Throwable;)Ljava/lang/Throwable;
    //   4772: athrow
    //   4773: aload_1
    //   4774: checkcast [B
    //   4777: invokevirtual clone : ()Ljava/lang/Object;
    //   4780: aastore
    //   4781: invokevirtual invoke : (Ljava/lang/Object;[Ljava/lang/Object;)Ljava/lang/Object;
    //   4784: checkcast java/lang/Boolean
    //   4787: invokevirtual booleanValue : ()Z
    //   4790: istore_3
    //   4791: iload_2
    //   4792: ifne -> 4809
    //   4795: iinc #6, 1
    //   4798: iload_2
    //   4799: ifne -> 4669
    //   4802: goto -> 4809
    //   4805: invokestatic a : (Ljava/lang/Throwable;)Ljava/lang/Throwable;
    //   4808: athrow
    //   4809: goto -> 5150
    //   4812: sipush #-19526
    //   4815: sipush #15094
    //   4818: invokestatic a : (II)Ljava/lang/String;
    //   4821: iconst_1
    //   4822: ldc burp/Zec0
    //   4824: invokevirtual getClassLoader : ()Ljava/lang/ClassLoader;
    //   4827: invokestatic forName : (Ljava/lang/String;ZLjava/lang/ClassLoader;)Ljava/lang/Class;
    //   4830: invokevirtual getDeclaredFields : ()[Ljava/lang/reflect/Field;
    //   4833: astore #4
    //   4835: aload #4
    //   4837: arraylength
    //   4838: istore #5
    //   4840: iconst_0
    //   4841: istore #6
    //   4843: iload #6
    //   4845: iload #5
    //   4847: if_icmpge -> 4985
    //   4850: aload #4
    //   4852: iload #6
    //   4854: aaload
    //   4855: astore #7
    //   4857: aload #7
    //   4859: invokevirtual getModifiers : ()I
    //   4862: invokestatic isStatic : (I)Z
    //   4865: ifne -> 4875
    //   4868: goto -> 4978
    //   4871: invokestatic a : (Ljava/lang/Throwable;)Ljava/lang/Throwable;
    //   4874: athrow
    //   4875: aload #7
    //   4877: invokevirtual getType : ()Ljava/lang/Class;
    //   4880: astore #8
    //   4882: aload #8
    //   4884: ifnull -> 4965
    //   4887: aload #8
    //   4889: invokevirtual isPrimitive : ()Z
    //   4892: ifne -> 4965
    //   4895: goto -> 4902
    //   4898: invokestatic a : (Ljava/lang/Throwable;)Ljava/lang/Throwable;
    //   4901: athrow
    //   4902: aload #8
    //   4904: invokevirtual getPackage : ()Ljava/lang/Package;
    //   4907: ifnull -> 4965
    //   4910: goto -> 4917
    //   4913: invokestatic a : (Ljava/lang/Throwable;)Ljava/lang/Throwable;
    //   4916: athrow
    //   4917: aload #8
    //   4919: invokevirtual getPackage : ()Ljava/lang/Package;
    //   4922: invokevirtual getName : ()Ljava/lang/String;
    //   4925: ifnull -> 4965
    //   4928: goto -> 4935
    //   4931: invokestatic a : (Ljava/lang/Throwable;)Ljava/lang/Throwable;
    //   4934: athrow
    //   4935: aload #8
    //   4937: invokevirtual getPackage : ()Ljava/lang/Package;
    //   4940: invokevirtual getName : ()Ljava/lang/String;
    //   4943: sipush #-19539
    //   4946: sipush #23209
    //   4949: invokestatic a : (II)Ljava/lang/String;
    //   4952: invokevirtual startsWith : (Ljava/lang/String;)Z
    //   4955: ifne -> 4965
    //   4958: goto -> 4965
    //   4961: invokestatic a : (Ljava/lang/Throwable;)Ljava/lang/Throwable;
    //   4964: athrow
    //   4965: aload #7
    //   4967: iconst_1
    //   4968: invokevirtual setAccessible : (Z)V
    //   4971: aload #7
    //   4973: aconst_null
    //   4974: invokevirtual get : (Ljava/lang/Object;)Ljava/lang/Object;
    //   4977: pop
    //   4978: iinc #6, 1
    //   4981: iload_2
    //   4982: ifne -> 4843
    //   4985: sipush #-19537
    //   4988: sipush #-3364
    //   4991: invokestatic a : (II)Ljava/lang/String;
    //   4994: invokestatic forName : (Ljava/lang/String;)Ljava/lang/Class;
    //   4997: invokevirtual getDeclaredMethods : ()[Ljava/lang/reflect/Method;
    //   5000: astore #4
    //   5002: aload #4
    //   5004: arraylength
    //   5005: istore #5
    //   5007: iconst_0
    //   5008: istore #6
    //   5010: iload #6
    //   5012: iload #5
    //   5014: if_icmpge -> 5150
    //   5017: aload #4
    //   5019: iload #6
    //   5021: aaload
    //   5022: astore #7
    //   5024: aload #7
    //   5026: invokevirtual getParameterTypes : ()[Ljava/lang/Class;
    //   5029: pop
    //   5030: aload #7
    //   5032: invokevirtual getModifiers : ()I
    //   5035: invokestatic isStatic : (I)Z
    //   5038: ifeq -> 5136
    //   5041: aload #7
    //   5043: invokevirtual getParameterTypes : ()[Ljava/lang/Class;
    //   5046: arraylength
    //   5047: iconst_2
    //   5048: if_icmpne -> 5136
    //   5051: goto -> 5058
    //   5054: invokestatic a : (Ljava/lang/Throwable;)Ljava/lang/Throwable;
    //   5057: athrow
    //   5058: aload #7
    //   5060: invokevirtual getReturnType : ()Ljava/lang/Class;
    //   5063: getstatic java/lang/Boolean.TYPE : Ljava/lang/Class;
    //   5066: if_acmpne -> 5136
    //   5069: goto -> 5076
    //   5072: invokestatic a : (Ljava/lang/Throwable;)Ljava/lang/Throwable;
    //   5075: athrow
    //   5076: aload #7
    //   5078: iconst_1
    //   5079: invokevirtual setAccessible : (Z)V
    //   5082: aload #7
    //   5084: aconst_null
    //   5085: iconst_2
    //   5086: anewarray java/lang/Object
    //   5089: dup
    //   5090: iconst_0
    //   5091: aload_0
    //   5092: aastore
    //   5093: dup
    //   5094: iconst_1
    //   5095: aload_1
    //   5096: ifnonnull -> 5114
    //   5099: goto -> 5106
    //   5102: invokestatic a : (Ljava/lang/Throwable;)Ljava/lang/Throwable;
    //   5105: athrow
    //   5106: aload_1
    //   5107: goto -> 5121
    //   5110: invokestatic a : (Ljava/lang/Throwable;)Ljava/lang/Throwable;
    //   5113: athrow
    //   5114: aload_1
    //   5115: checkcast [B
    //   5118: invokevirtual clone : ()Ljava/lang/Object;
    //   5121: aastore
    //   5122: invokevirtual invoke : (Ljava/lang/Object;[Ljava/lang/Object;)Ljava/lang/Object;
    //   5125: checkcast java/lang/Boolean
    //   5128: invokevirtual booleanValue : ()Z
    //   5131: istore_3
    //   5132: iload_2
    //   5133: ifne -> 5150
    //   5136: iinc #6, 1
    //   5139: iload_2
    //   5140: ifne -> 5010
    //   5143: goto -> 5150
    //   5146: invokestatic a : (Ljava/lang/Throwable;)Ljava/lang/Throwable;
    //   5149: athrow
    //   5150: iload_3
    //   5151: ifeq -> 5156
    //   5154: iload_3
    //   5155: ireturn
    //   5156: getstatic burp/Zr60.ZQ : Ljava/lang/String;
    //   5159: getstatic burp/Ztgv.Zg : Ljava/lang/Object;
    //   5162: checkcast java/math/BigInteger
    //   5165: invokevirtual intValue : ()I
    //   5168: bipush #32
    //   5170: irem
    //   5171: invokestatic abs : (I)I
    //   5174: invokevirtual charAt : (I)C
    //   5177: getstatic burp/Zm83.Zq : Ljava/lang/String;
    //   5180: getstatic burp/Zex0.Ze : Ljava/lang/Object;
    //   5183: checkcast java/math/BigInteger
    //   5186: invokevirtual intValue : ()I
    //   5189: bipush #32
    //   5191: irem
    //   5192: invokestatic abs : (I)I
    //   5195: invokevirtual charAt : (I)C
    //   5198: if_icmpgt -> 5543
    //   5201: sipush #-19524
    //   5204: sipush #26735
    //   5207: invokestatic a : (II)Ljava/lang/String;
    //   5210: iconst_1
    //   5211: ldc burp/Zly7
    //   5213: invokevirtual getClassLoader : ()Ljava/lang/ClassLoader;
    //   5216: invokestatic forName : (Ljava/lang/String;ZLjava/lang/ClassLoader;)Ljava/lang/Class;
    //   5219: invokevirtual getDeclaredFields : ()[Ljava/lang/reflect/Field;
    //   5222: astore #4
    //   5224: aload #4
    //   5226: arraylength
    //   5227: istore #5
    //   5229: iconst_0
    //   5230: istore #6
    //   5232: iload #6
    //   5234: iload #5
    //   5236: if_icmpge -> 5374
    //   5239: aload #4
    //   5241: iload #6
    //   5243: aaload
    //   5244: astore #7
    //   5246: aload #7
    //   5248: invokevirtual getModifiers : ()I
    //   5251: invokestatic isStatic : (I)Z
    //   5254: ifne -> 5264
    //   5257: goto -> 5367
    //   5260: invokestatic a : (Ljava/lang/Throwable;)Ljava/lang/Throwable;
    //   5263: athrow
    //   5264: aload #7
    //   5266: invokevirtual getType : ()Ljava/lang/Class;
    //   5269: astore #8
    //   5271: aload #8
    //   5273: ifnull -> 5354
    //   5276: aload #8
    //   5278: invokevirtual isPrimitive : ()Z
    //   5281: ifne -> 5354
    //   5284: goto -> 5291
    //   5287: invokestatic a : (Ljava/lang/Throwable;)Ljava/lang/Throwable;
    //   5290: athrow
    //   5291: aload #8
    //   5293: invokevirtual getPackage : ()Ljava/lang/Package;
    //   5296: ifnull -> 5354
    //   5299: goto -> 5306
    //   5302: invokestatic a : (Ljava/lang/Throwable;)Ljava/lang/Throwable;
    //   5305: athrow
    //   5306: aload #8
    //   5308: invokevirtual getPackage : ()Ljava/lang/Package;
    //   5311: invokevirtual getName : ()Ljava/lang/String;
    //   5314: ifnull -> 5354
    //   5317: goto -> 5324
    //   5320: invokestatic a : (Ljava/lang/Throwable;)Ljava/lang/Throwable;
    //   5323: athrow
    //   5324: aload #8
    //   5326: invokevirtual getPackage : ()Ljava/lang/Package;
    //   5329: invokevirtual getName : ()Ljava/lang/String;
    //   5332: sipush #-19539
    //   5335: sipush #23209
    //   5338: invokestatic a : (II)Ljava/lang/String;
    //   5341: invokevirtual startsWith : (Ljava/lang/String;)Z
    //   5344: ifne -> 5354
    //   5347: goto -> 5354
    //   5350: invokestatic a : (Ljava/lang/Throwable;)Ljava/lang/Throwable;
    //   5353: athrow
    //   5354: aload #7
    //   5356: iconst_1
    //   5357: invokevirtual setAccessible : (Z)V
    //   5360: aload #7
    //   5362: aconst_null
    //   5363: invokevirtual get : (Ljava/lang/Object;)Ljava/lang/Object;
    //   5366: pop
    //   5367: iinc #6, 1
    //   5370: iload_2
    //   5371: ifne -> 5232
    //   5374: sipush #-19546
    //   5377: sipush #-29177
    //   5380: invokestatic a : (II)Ljava/lang/String;
    //   5383: invokestatic forName : (Ljava/lang/String;)Ljava/lang/Class;
    //   5386: invokevirtual getDeclaredMethods : ()[Ljava/lang/reflect/Method;
    //   5389: astore #4
    //   5391: aload #4
    //   5393: arraylength
    //   5394: istore #5
    //   5396: iconst_0
    //   5397: istore #6
    //   5399: iload #6
    //   5401: iload #5
    //   5403: if_icmpge -> 5539
    //   5406: aload #4
    //   5408: iload #6
    //   5410: aaload
    //   5411: astore #7
    //   5413: aload #7
    //   5415: invokevirtual getParameterTypes : ()[Ljava/lang/Class;
    //   5418: pop
    //   5419: aload #7
    //   5421: invokevirtual getModifiers : ()I
    //   5424: invokestatic isStatic : (I)Z
    //   5427: ifeq -> 5525
    //   5430: aload #7
    //   5432: invokevirtual getParameterTypes : ()[Ljava/lang/Class;
    //   5435: arraylength
    //   5436: iconst_2
    //   5437: if_icmpne -> 5525
    //   5440: goto -> 5447
    //   5443: invokestatic a : (Ljava/lang/Throwable;)Ljava/lang/Throwable;
    //   5446: athrow
    //   5447: aload #7
    //   5449: invokevirtual getReturnType : ()Ljava/lang/Class;
    //   5452: getstatic java/lang/Boolean.TYPE : Ljava/lang/Class;
    //   5455: if_acmpne -> 5525
    //   5458: goto -> 5465
    //   5461: invokestatic a : (Ljava/lang/Throwable;)Ljava/lang/Throwable;
    //   5464: athrow
    //   5465: aload #7
    //   5467: iconst_1
    //   5468: invokevirtual setAccessible : (Z)V
    //   5471: aload #7
    //   5473: aconst_null
    //   5474: iconst_2
    //   5475: anewarray java/lang/Object
    //   5478: dup
    //   5479: iconst_0
    //   5480: aload_0
    //   5481: aastore
    //   5482: dup
    //   5483: iconst_1
    //   5484: aload_1
    //   5485: ifnonnull -> 5503
    //   5488: goto -> 5495
    //   5491: invokestatic a : (Ljava/lang/Throwable;)Ljava/lang/Throwable;
    //   5494: athrow
    //   5495: aload_1
    //   5496: goto -> 5510
    //   5499: invokestatic a : (Ljava/lang/Throwable;)Ljava/lang/Throwable;
    //   5502: athrow
    //   5503: aload_1
    //   5504: checkcast [B
    //   5507: invokevirtual clone : ()Ljava/lang/Object;
    //   5510: aastore
    //   5511: invokevirtual invoke : (Ljava/lang/Object;[Ljava/lang/Object;)Ljava/lang/Object;
    //   5514: checkcast java/lang/Boolean
    //   5517: invokevirtual booleanValue : ()Z
    //   5520: istore_3
    //   5521: iload_2
    //   5522: ifne -> 5539
    //   5525: iinc #6, 1
    //   5528: iload_2
    //   5529: ifne -> 5399
    //   5532: goto -> 5539
    //   5535: invokestatic a : (Ljava/lang/Throwable;)Ljava/lang/Throwable;
    //   5538: athrow
    //   5539: iload_2
    //   5540: ifne -> 5881
    //   5543: sipush #-19542
    //   5546: sipush #11661
    //   5549: invokestatic a : (II)Ljava/lang/String;
    //   5552: iconst_1
    //   5553: ldc burp/Zs0b
    //   5555: invokevirtual getClassLoader : ()Ljava/lang/ClassLoader;
    //   5558: invokestatic forName : (Ljava/lang/String;ZLjava/lang/ClassLoader;)Ljava/lang/Class;
    //   5561: invokevirtual getDeclaredFields : ()[Ljava/lang/reflect/Field;
    //   5564: astore #4
    //   5566: aload #4
    //   5568: arraylength
    //   5569: istore #5
    //   5571: iconst_0
    //   5572: istore #6
    //   5574: iload #6
    //   5576: iload #5
    //   5578: if_icmpge -> 5716
    //   5581: aload #4
    //   5583: iload #6
    //   5585: aaload
    //   5586: astore #7
    //   5588: aload #7
    //   5590: invokevirtual getModifiers : ()I
    //   5593: invokestatic isStatic : (I)Z
    //   5596: ifne -> 5606
    //   5599: goto -> 5709
    //   5602: invokestatic a : (Ljava/lang/Throwable;)Ljava/lang/Throwable;
    //   5605: athrow
    //   5606: aload #7
    //   5608: invokevirtual getType : ()Ljava/lang/Class;
    //   5611: astore #8
    //   5613: aload #8
    //   5615: ifnull -> 5696
    //   5618: aload #8
    //   5620: invokevirtual isPrimitive : ()Z
    //   5623: ifne -> 5696
    //   5626: goto -> 5633
    //   5629: invokestatic a : (Ljava/lang/Throwable;)Ljava/lang/Throwable;
    //   5632: athrow
    //   5633: aload #8
    //   5635: invokevirtual getPackage : ()Ljava/lang/Package;
    //   5638: ifnull -> 5696
    //   5641: goto -> 5648
    //   5644: invokestatic a : (Ljava/lang/Throwable;)Ljava/lang/Throwable;
    //   5647: athrow
    //   5648: aload #8
    //   5650: invokevirtual getPackage : ()Ljava/lang/Package;
    //   5653: invokevirtual getName : ()Ljava/lang/String;
    //   5656: ifnull -> 5696
    //   5659: goto -> 5666
    //   5662: invokestatic a : (Ljava/lang/Throwable;)Ljava/lang/Throwable;
    //   5665: athrow
    //   5666: aload #8
    //   5668: invokevirtual getPackage : ()Ljava/lang/Package;
    //   5671: invokevirtual getName : ()Ljava/lang/String;
    //   5674: sipush #-19539
    //   5677: sipush #23209
    //   5680: invokestatic a : (II)Ljava/lang/String;
    //   5683: invokevirtual startsWith : (Ljava/lang/String;)Z
    //   5686: ifne -> 5696
    //   5689: goto -> 5696
    //   5692: invokestatic a : (Ljava/lang/Throwable;)Ljava/lang/Throwable;
    //   5695: athrow
    //   5696: aload #7
    //   5698: iconst_1
    //   5699: invokevirtual setAccessible : (Z)V
    //   5702: aload #7
    //   5704: aconst_null
    //   5705: invokevirtual get : (Ljava/lang/Object;)Ljava/lang/Object;
    //   5708: pop
    //   5709: iinc #6, 1
    //   5712: iload_2
    //   5713: ifne -> 5574
    //   5716: sipush #-19547
    //   5719: sipush #-2466
    //   5722: invokestatic a : (II)Ljava/lang/String;
    //   5725: invokestatic forName : (Ljava/lang/String;)Ljava/lang/Class;
    //   5728: invokevirtual getDeclaredMethods : ()[Ljava/lang/reflect/Method;
    //   5731: astore #4
    //   5733: aload #4
    //   5735: arraylength
    //   5736: istore #5
    //   5738: iconst_0
    //   5739: istore #6
    //   5741: iload #6
    //   5743: iload #5
    //   5745: if_icmpge -> 5881
    //   5748: aload #4
    //   5750: iload #6
    //   5752: aaload
    //   5753: astore #7
    //   5755: aload #7
    //   5757: invokevirtual getParameterTypes : ()[Ljava/lang/Class;
    //   5760: pop
    //   5761: aload #7
    //   5763: invokevirtual getModifiers : ()I
    //   5766: invokestatic isStatic : (I)Z
    //   5769: ifeq -> 5867
    //   5772: aload #7
    //   5774: invokevirtual getParameterTypes : ()[Ljava/lang/Class;
    //   5777: arraylength
    //   5778: iconst_2
    //   5779: if_icmpne -> 5867
    //   5782: goto -> 5789
    //   5785: invokestatic a : (Ljava/lang/Throwable;)Ljava/lang/Throwable;
    //   5788: athrow
    //   5789: aload #7
    //   5791: invokevirtual getReturnType : ()Ljava/lang/Class;
    //   5794: getstatic java/lang/Boolean.TYPE : Ljava/lang/Class;
    //   5797: if_acmpne -> 5867
    //   5800: goto -> 5807
    //   5803: invokestatic a : (Ljava/lang/Throwable;)Ljava/lang/Throwable;
    //   5806: athrow
    //   5807: aload #7
    //   5809: iconst_1
    //   5810: invokevirtual setAccessible : (Z)V
    //   5813: aload #7
    //   5815: aconst_null
    //   5816: iconst_2
    //   5817: anewarray java/lang/Object
    //   5820: dup
    //   5821: iconst_0
    //   5822: aload_0
    //   5823: aastore
    //   5824: dup
    //   5825: iconst_1
    //   5826: aload_1
    //   5827: ifnonnull -> 5845
    //   5830: goto -> 5837
    //   5833: invokestatic a : (Ljava/lang/Throwable;)Ljava/lang/Throwable;
    //   5836: athrow
    //   5837: aload_1
    //   5838: goto -> 5852
    //   5841: invokestatic a : (Ljava/lang/Throwable;)Ljava/lang/Throwable;
    //   5844: athrow
    //   5845: aload_1
    //   5846: checkcast [B
    //   5849: invokevirtual clone : ()Ljava/lang/Object;
    //   5852: aastore
    //   5853: invokevirtual invoke : (Ljava/lang/Object;[Ljava/lang/Object;)Ljava/lang/Object;
    //   5856: checkcast java/lang/Boolean
    //   5859: invokevirtual booleanValue : ()Z
    //   5862: istore_3
    //   5863: iload_2
    //   5864: ifne -> 5881
    //   5867: iinc #6, 1
    //   5870: iload_2
    //   5871: ifne -> 5741
    //   5874: goto -> 5881
    //   5877: invokestatic a : (Ljava/lang/Throwable;)Ljava/lang/Throwable;
    //   5880: athrow
    //   5881: iload_3
    //   5882: ifeq -> 5887
    //   5885: iload_3
    //   5886: ireturn
    //   5887: getstatic burp/Zlw8.Zs : Ljava/lang/String;
    //   5890: getstatic burp/Zr02.ZB : Ljava/lang/Object;
    //   5893: checkcast java/math/BigInteger
    //   5896: invokevirtual intValue : ()I
    //   5899: bipush #32
    //   5901: irem
    //   5902: invokestatic abs : (I)I
    //   5905: invokevirtual charAt : (I)C
    //   5908: getstatic burp/Zb3d.Zr : Ljava/lang/String;
    //   5911: getstatic burp/Ztq8.Zm : Ljava/lang/Object;
    //   5914: checkcast java/math/BigInteger
    //   5917: invokevirtual intValue : ()I
    //   5920: bipush #32
    //   5922: irem
    //   5923: invokestatic abs : (I)I
    //   5926: invokevirtual charAt : (I)C
    //   5929: if_icmple -> 6274
    //   5932: sipush #-19538
    //   5935: sipush #20287
    //   5938: invokestatic a : (II)Ljava/lang/String;
    //   5941: iconst_1
    //   5942: ldc burp/Zb9h
    //   5944: invokevirtual getClassLoader : ()Ljava/lang/ClassLoader;
    //   5947: invokestatic forName : (Ljava/lang/String;ZLjava/lang/ClassLoader;)Ljava/lang/Class;
    //   5950: invokevirtual getDeclaredFields : ()[Ljava/lang/reflect/Field;
    //   5953: astore #4
    //   5955: aload #4
    //   5957: arraylength
    //   5958: istore #5
    //   5960: iconst_0
    //   5961: istore #6
    //   5963: iload #6
    //   5965: iload #5
    //   5967: if_icmpge -> 6105
    //   5970: aload #4
    //   5972: iload #6
    //   5974: aaload
    //   5975: astore #7
    //   5977: aload #7
    //   5979: invokevirtual getModifiers : ()I
    //   5982: invokestatic isStatic : (I)Z
    //   5985: ifne -> 5995
    //   5988: goto -> 6098
    //   5991: invokestatic a : (Ljava/lang/Throwable;)Ljava/lang/Throwable;
    //   5994: athrow
    //   5995: aload #7
    //   5997: invokevirtual getType : ()Ljava/lang/Class;
    //   6000: astore #8
    //   6002: aload #8
    //   6004: ifnull -> 6085
    //   6007: aload #8
    //   6009: invokevirtual isPrimitive : ()Z
    //   6012: ifne -> 6085
    //   6015: goto -> 6022
    //   6018: invokestatic a : (Ljava/lang/Throwable;)Ljava/lang/Throwable;
    //   6021: athrow
    //   6022: aload #8
    //   6024: invokevirtual getPackage : ()Ljava/lang/Package;
    //   6027: ifnull -> 6085
    //   6030: goto -> 6037
    //   6033: invokestatic a : (Ljava/lang/Throwable;)Ljava/lang/Throwable;
    //   6036: athrow
    //   6037: aload #8
    //   6039: invokevirtual getPackage : ()Ljava/lang/Package;
    //   6042: invokevirtual getName : ()Ljava/lang/String;
    //   6045: ifnull -> 6085
    //   6048: goto -> 6055
    //   6051: invokestatic a : (Ljava/lang/Throwable;)Ljava/lang/Throwable;
    //   6054: athrow
    //   6055: aload #8
    //   6057: invokevirtual getPackage : ()Ljava/lang/Package;
    //   6060: invokevirtual getName : ()Ljava/lang/String;
    //   6063: sipush #-19539
    //   6066: sipush #23209
    //   6069: invokestatic a : (II)Ljava/lang/String;
    //   6072: invokevirtual startsWith : (Ljava/lang/String;)Z
    //   6075: ifne -> 6085
    //   6078: goto -> 6085
    //   6081: invokestatic a : (Ljava/lang/Throwable;)Ljava/lang/Throwable;
    //   6084: athrow
    //   6085: aload #7
    //   6087: iconst_1
    //   6088: invokevirtual setAccessible : (Z)V
    //   6091: aload #7
    //   6093: aconst_null
    //   6094: invokevirtual get : (Ljava/lang/Object;)Ljava/lang/Object;
    //   6097: pop
    //   6098: iinc #6, 1
    //   6101: iload_2
    //   6102: ifne -> 5963
    //   6105: sipush #-19545
    //   6108: sipush #30470
    //   6111: invokestatic a : (II)Ljava/lang/String;
    //   6114: invokestatic forName : (Ljava/lang/String;)Ljava/lang/Class;
    //   6117: invokevirtual getDeclaredMethods : ()[Ljava/lang/reflect/Method;
    //   6120: astore #4
    //   6122: aload #4
    //   6124: arraylength
    //   6125: istore #5
    //   6127: iconst_0
    //   6128: istore #6
    //   6130: iload #6
    //   6132: iload #5
    //   6134: if_icmpge -> 6270
    //   6137: aload #4
    //   6139: iload #6
    //   6141: aaload
    //   6142: astore #7
    //   6144: aload #7
    //   6146: invokevirtual getParameterTypes : ()[Ljava/lang/Class;
    //   6149: pop
    //   6150: aload #7
    //   6152: invokevirtual getModifiers : ()I
    //   6155: invokestatic isStatic : (I)Z
    //   6158: ifeq -> 6256
    //   6161: aload #7
    //   6163: invokevirtual getParameterTypes : ()[Ljava/lang/Class;
    //   6166: arraylength
    //   6167: iconst_2
    //   6168: if_icmpne -> 6256
    //   6171: goto -> 6178
    //   6174: invokestatic a : (Ljava/lang/Throwable;)Ljava/lang/Throwable;
    //   6177: athrow
    //   6178: aload #7
    //   6180: invokevirtual getReturnType : ()Ljava/lang/Class;
    //   6183: getstatic java/lang/Boolean.TYPE : Ljava/lang/Class;
    //   6186: if_acmpne -> 6256
    //   6189: goto -> 6196
    //   6192: invokestatic a : (Ljava/lang/Throwable;)Ljava/lang/Throwable;
    //   6195: athrow
    //   6196: aload #7
    //   6198: iconst_1
    //   6199: invokevirtual setAccessible : (Z)V
    //   6202: aload #7
    //   6204: aconst_null
    //   6205: iconst_2
    //   6206: anewarray java/lang/Object
    //   6209: dup
    //   6210: iconst_0
    //   6211: aload_0
    //   6212: aastore
    //   6213: dup
    //   6214: iconst_1
    //   6215: aload_1
    //   6216: ifnonnull -> 6234
    //   6219: goto -> 6226
    //   6222: invokestatic a : (Ljava/lang/Throwable;)Ljava/lang/Throwable;
    //   6225: athrow
    //   6226: aload_1
    //   6227: goto -> 6241
    //   6230: invokestatic a : (Ljava/lang/Throwable;)Ljava/lang/Throwable;
    //   6233: athrow
    //   6234: aload_1
    //   6235: checkcast [B
    //   6238: invokevirtual clone : ()Ljava/lang/Object;
    //   6241: aastore
    //   6242: invokevirtual invoke : (Ljava/lang/Object;[Ljava/lang/Object;)Ljava/lang/Object;
    //   6245: checkcast java/lang/Boolean
    //   6248: invokevirtual booleanValue : ()Z
    //   6251: istore_3
    //   6252: iload_2
    //   6253: ifne -> 6270
    //   6256: iinc #6, 1
    //   6259: iload_2
    //   6260: ifne -> 6130
    //   6263: goto -> 6270
    //   6266: invokestatic a : (Ljava/lang/Throwable;)Ljava/lang/Throwable;
    //   6269: athrow
    //   6270: iload_2
    //   6271: ifne -> 6612
    //   6274: sipush #-19541
    //   6277: sipush #3852
    //   6280: invokestatic a : (II)Ljava/lang/String;
    //   6283: iconst_1
    //   6284: ldc burp/Zgz1
    //   6286: invokevirtual getClassLoader : ()Ljava/lang/ClassLoader;
    //   6289: invokestatic forName : (Ljava/lang/String;ZLjava/lang/ClassLoader;)Ljava/lang/Class;
    //   6292: invokevirtual getDeclaredFields : ()[Ljava/lang/reflect/Field;
    //   6295: astore #4
    //   6297: aload #4
    //   6299: arraylength
    //   6300: istore #5
    //   6302: iconst_0
    //   6303: istore #6
    //   6305: iload #6
    //   6307: iload #5
    //   6309: if_icmpge -> 6447
    //   6312: aload #4
    //   6314: iload #6
    //   6316: aaload
    //   6317: astore #7
    //   6319: aload #7
    //   6321: invokevirtual getModifiers : ()I
    //   6324: invokestatic isStatic : (I)Z
    //   6327: ifne -> 6337
    //   6330: goto -> 6440
    //   6333: invokestatic a : (Ljava/lang/Throwable;)Ljava/lang/Throwable;
    //   6336: athrow
    //   6337: aload #7
    //   6339: invokevirtual getType : ()Ljava/lang/Class;
    //   6342: astore #8
    //   6344: aload #8
    //   6346: ifnull -> 6427
    //   6349: aload #8
    //   6351: invokevirtual isPrimitive : ()Z
    //   6354: ifne -> 6427
    //   6357: goto -> 6364
    //   6360: invokestatic a : (Ljava/lang/Throwable;)Ljava/lang/Throwable;
    //   6363: athrow
    //   6364: aload #8
    //   6366: invokevirtual getPackage : ()Ljava/lang/Package;
    //   6369: ifnull -> 6427
    //   6372: goto -> 6379
    //   6375: invokestatic a : (Ljava/lang/Throwable;)Ljava/lang/Throwable;
    //   6378: athrow
    //   6379: aload #8
    //   6381: invokevirtual getPackage : ()Ljava/lang/Package;
    //   6384: invokevirtual getName : ()Ljava/lang/String;
    //   6387: ifnull -> 6427
    //   6390: goto -> 6397
    //   6393: invokestatic a : (Ljava/lang/Throwable;)Ljava/lang/Throwable;
    //   6396: athrow
    //   6397: aload #8
    //   6399: invokevirtual getPackage : ()Ljava/lang/Package;
    //   6402: invokevirtual getName : ()Ljava/lang/String;
    //   6405: sipush #-19539
    //   6408: sipush #23209
    //   6411: invokestatic a : (II)Ljava/lang/String;
    //   6414: invokevirtual startsWith : (Ljava/lang/String;)Z
    //   6417: ifne -> 6427
    //   6420: goto -> 6427
    //   6423: invokestatic a : (Ljava/lang/Throwable;)Ljava/lang/Throwable;
    //   6426: athrow
    //   6427: aload #7
    //   6429: iconst_1
    //   6430: invokevirtual setAccessible : (Z)V
    //   6433: aload #7
    //   6435: aconst_null
    //   6436: invokevirtual get : (Ljava/lang/Object;)Ljava/lang/Object;
    //   6439: pop
    //   6440: iinc #6, 1
    //   6443: iload_2
    //   6444: ifne -> 6305
    //   6447: sipush #-19550
    //   6450: sipush #5033
    //   6453: invokestatic a : (II)Ljava/lang/String;
    //   6456: invokestatic forName : (Ljava/lang/String;)Ljava/lang/Class;
    //   6459: invokevirtual getDeclaredMethods : ()[Ljava/lang/reflect/Method;
    //   6462: astore #4
    //   6464: aload #4
    //   6466: arraylength
    //   6467: istore #5
    //   6469: iconst_0
    //   6470: istore #6
    //   6472: iload #6
    //   6474: iload #5
    //   6476: if_icmpge -> 6612
    //   6479: aload #4
    //   6481: iload #6
    //   6483: aaload
    //   6484: astore #7
    //   6486: aload #7
    //   6488: invokevirtual getParameterTypes : ()[Ljava/lang/Class;
    //   6491: pop
    //   6492: aload #7
    //   6494: invokevirtual getModifiers : ()I
    //   6497: invokestatic isStatic : (I)Z
    //   6500: ifeq -> 6598
    //   6503: aload #7
    //   6505: invokevirtual getParameterTypes : ()[Ljava/lang/Class;
    //   6508: arraylength
    //   6509: iconst_2
    //   6510: if_icmpne -> 6598
    //   6513: goto -> 6520
    //   6516: invokestatic a : (Ljava/lang/Throwable;)Ljava/lang/Throwable;
    //   6519: athrow
    //   6520: aload #7
    //   6522: invokevirtual getReturnType : ()Ljava/lang/Class;
    //   6525: getstatic java/lang/Boolean.TYPE : Ljava/lang/Class;
    //   6528: if_acmpne -> 6598
    //   6531: goto -> 6538
    //   6534: invokestatic a : (Ljava/lang/Throwable;)Ljava/lang/Throwable;
    //   6537: athrow
    //   6538: aload #7
    //   6540: iconst_1
    //   6541: invokevirtual setAccessible : (Z)V
    //   6544: aload #7
    //   6546: aconst_null
    //   6547: iconst_2
    //   6548: anewarray java/lang/Object
    //   6551: dup
    //   6552: iconst_0
    //   6553: aload_0
    //   6554: aastore
    //   6555: dup
    //   6556: iconst_1
    //   6557: aload_1
    //   6558: ifnonnull -> 6576
    //   6561: goto -> 6568
    //   6564: invokestatic a : (Ljava/lang/Throwable;)Ljava/lang/Throwable;
    //   6567: athrow
    //   6568: aload_1
    //   6569: goto -> 6583
    //   6572: invokestatic a : (Ljava/lang/Throwable;)Ljava/lang/Throwable;
    //   6575: athrow
    //   6576: aload_1
    //   6577: checkcast [B
    //   6580: invokevirtual clone : ()Ljava/lang/Object;
    //   6583: aastore
    //   6584: invokevirtual invoke : (Ljava/lang/Object;[Ljava/lang/Object;)Ljava/lang/Object;
    //   6587: checkcast java/lang/Boolean
    //   6590: invokevirtual booleanValue : ()Z
    //   6593: istore_3
    //   6594: iload_2
    //   6595: ifne -> 6612
    //   6598: iinc #6, 1
    //   6601: iload_2
    //   6602: ifne -> 6472
    //   6605: goto -> 6612
    //   6608: invokestatic a : (Ljava/lang/Throwable;)Ljava/lang/Throwable;
    //   6611: athrow
    //   6612: iload_3
    //   6613: ifeq -> 6618
    //   6616: iload_3
    //   6617: ireturn
    //   6618: getstatic burp/Zz4j.ZS : Ljava/lang/String;
    //   6621: getstatic burp/Zttd.Zi : Ljava/lang/Object;
    //   6624: checkcast java/math/BigInteger
    //   6627: invokevirtual intValue : ()I
    //   6630: bipush #32
    //   6632: irem
    //   6633: invokestatic abs : (I)I
    //   6636: invokevirtual charAt : (I)C
    //   6639: getstatic burp/Zt85.ZR : Ljava/lang/String;
    //   6642: getstatic burp/Zlbd.ZU : Ljava/lang/Object;
    //   6645: checkcast java/math/BigInteger
    //   6648: invokevirtual intValue : ()I
    //   6651: bipush #32
    //   6653: irem
    //   6654: invokestatic abs : (I)I
    //   6657: invokevirtual charAt : (I)C
    //   6660: if_icmple -> 7005
    //   6663: sipush #-19544
    //   6666: sipush #5175
    //   6669: invokestatic a : (II)Ljava/lang/String;
    //   6672: iconst_1
    //   6673: ldc burp/Zxyp
    //   6675: invokevirtual getClassLoader : ()Ljava/lang/ClassLoader;
    //   6678: invokestatic forName : (Ljava/lang/String;ZLjava/lang/ClassLoader;)Ljava/lang/Class;
    //   6681: invokevirtual getDeclaredFields : ()[Ljava/lang/reflect/Field;
    //   6684: astore #4
    //   6686: aload #4
    //   6688: arraylength
    //   6689: istore #5
    //   6691: iconst_0
    //   6692: istore #6
    //   6694: iload #6
    //   6696: iload #5
    //   6698: if_icmpge -> 6836
    //   6701: aload #4
    //   6703: iload #6
    //   6705: aaload
    //   6706: astore #7
    //   6708: aload #7
    //   6710: invokevirtual getModifiers : ()I
    //   6713: invokestatic isStatic : (I)Z
    //   6716: ifne -> 6726
    //   6719: goto -> 6829
    //   6722: invokestatic a : (Ljava/lang/Throwable;)Ljava/lang/Throwable;
    //   6725: athrow
    //   6726: aload #7
    //   6728: invokevirtual getType : ()Ljava/lang/Class;
    //   6731: astore #8
    //   6733: aload #8
    //   6735: ifnull -> 6816
    //   6738: aload #8
    //   6740: invokevirtual isPrimitive : ()Z
    //   6743: ifne -> 6816
    //   6746: goto -> 6753
    //   6749: invokestatic a : (Ljava/lang/Throwable;)Ljava/lang/Throwable;
    //   6752: athrow
    //   6753: aload #8
    //   6755: invokevirtual getPackage : ()Ljava/lang/Package;
    //   6758: ifnull -> 6816
    //   6761: goto -> 6768
    //   6764: invokestatic a : (Ljava/lang/Throwable;)Ljava/lang/Throwable;
    //   6767: athrow
    //   6768: aload #8
    //   6770: invokevirtual getPackage : ()Ljava/lang/Package;
    //   6773: invokevirtual getName : ()Ljava/lang/String;
    //   6776: ifnull -> 6816
    //   6779: goto -> 6786
    //   6782: invokestatic a : (Ljava/lang/Throwable;)Ljava/lang/Throwable;
    //   6785: athrow
    //   6786: aload #8
    //   6788: invokevirtual getPackage : ()Ljava/lang/Package;
    //   6791: invokevirtual getName : ()Ljava/lang/String;
    //   6794: sipush #-19539
    //   6797: sipush #23209
    //   6800: invokestatic a : (II)Ljava/lang/String;
    //   6803: invokevirtual startsWith : (Ljava/lang/String;)Z
    //   6806: ifne -> 6816
    //   6809: goto -> 6816
    //   6812: invokestatic a : (Ljava/lang/Throwable;)Ljava/lang/Throwable;
    //   6815: athrow
    //   6816: aload #7
    //   6818: iconst_1
    //   6819: invokevirtual setAccessible : (Z)V
    //   6822: aload #7
    //   6824: aconst_null
    //   6825: invokevirtual get : (Ljava/lang/Object;)Ljava/lang/Object;
    //   6828: pop
    //   6829: iinc #6, 1
    //   6832: iload_2
    //   6833: ifne -> 6694
    //   6836: sipush #-19523
    //   6839: sipush #-15401
    //   6842: invokestatic a : (II)Ljava/lang/String;
    //   6845: invokestatic forName : (Ljava/lang/String;)Ljava/lang/Class;
    //   6848: invokevirtual getDeclaredMethods : ()[Ljava/lang/reflect/Method;
    //   6851: astore #4
    //   6853: aload #4
    //   6855: arraylength
    //   6856: istore #5
    //   6858: iconst_0
    //   6859: istore #6
    //   6861: iload #6
    //   6863: iload #5
    //   6865: if_icmpge -> 7001
    //   6868: aload #4
    //   6870: iload #6
    //   6872: aaload
    //   6873: astore #7
    //   6875: aload #7
    //   6877: invokevirtual getParameterTypes : ()[Ljava/lang/Class;
    //   6880: pop
    //   6881: aload #7
    //   6883: invokevirtual getModifiers : ()I
    //   6886: invokestatic isStatic : (I)Z
    //   6889: ifeq -> 6987
    //   6892: aload #7
    //   6894: invokevirtual getParameterTypes : ()[Ljava/lang/Class;
    //   6897: arraylength
    //   6898: iconst_2
    //   6899: if_icmpne -> 6987
    //   6902: goto -> 6909
    //   6905: invokestatic a : (Ljava/lang/Throwable;)Ljava/lang/Throwable;
    //   6908: athrow
    //   6909: aload #7
    //   6911: invokevirtual getReturnType : ()Ljava/lang/Class;
    //   6914: getstatic java/lang/Boolean.TYPE : Ljava/lang/Class;
    //   6917: if_acmpne -> 6987
    //   6920: goto -> 6927
    //   6923: invokestatic a : (Ljava/lang/Throwable;)Ljava/lang/Throwable;
    //   6926: athrow
    //   6927: aload #7
    //   6929: iconst_1
    //   6930: invokevirtual setAccessible : (Z)V
    //   6933: aload #7
    //   6935: aconst_null
    //   6936: iconst_2
    //   6937: anewarray java/lang/Object
    //   6940: dup
    //   6941: iconst_0
    //   6942: aload_0
    //   6943: aastore
    //   6944: dup
    //   6945: iconst_1
    //   6946: aload_1
    //   6947: ifnonnull -> 6965
    //   6950: goto -> 6957
    //   6953: invokestatic a : (Ljava/lang/Throwable;)Ljava/lang/Throwable;
    //   6956: athrow
    //   6957: aload_1
    //   6958: goto -> 6972
    //   6961: invokestatic a : (Ljava/lang/Throwable;)Ljava/lang/Throwable;
    //   6964: athrow
    //   6965: aload_1
    //   6966: checkcast [B
    //   6969: invokevirtual clone : ()Ljava/lang/Object;
    //   6972: aastore
    //   6973: invokevirtual invoke : (Ljava/lang/Object;[Ljava/lang/Object;)Ljava/lang/Object;
    //   6976: checkcast java/lang/Boolean
    //   6979: invokevirtual booleanValue : ()Z
    //   6982: istore_3
    //   6983: iload_2
    //   6984: ifne -> 7001
    //   6987: iinc #6, 1
    //   6990: iload_2
    //   6991: ifne -> 6861
    //   6994: goto -> 7001
    //   6997: invokestatic a : (Ljava/lang/Throwable;)Ljava/lang/Throwable;
    //   7000: athrow
    //   7001: iload_2
    //   7002: ifne -> 7343
    //   7005: sipush #-19549
    //   7008: sipush #-30970
    //   7011: invokestatic a : (II)Ljava/lang/String;
    //   7014: iconst_1
    //   7015: ldc burp/Zk7f
    //   7017: invokevirtual getClassLoader : ()Ljava/lang/ClassLoader;
    //   7020: invokestatic forName : (Ljava/lang/String;ZLjava/lang/ClassLoader;)Ljava/lang/Class;
    //   7023: invokevirtual getDeclaredFields : ()[Ljava/lang/reflect/Field;
    //   7026: astore #4
    //   7028: aload #4
    //   7030: arraylength
    //   7031: istore #5
    //   7033: iconst_0
    //   7034: istore #6
    //   7036: iload #6
    //   7038: iload #5
    //   7040: if_icmpge -> 7178
    //   7043: aload #4
    //   7045: iload #6
    //   7047: aaload
    //   7048: astore #7
    //   7050: aload #7
    //   7052: invokevirtual getModifiers : ()I
    //   7055: invokestatic isStatic : (I)Z
    //   7058: ifne -> 7068
    //   7061: goto -> 7171
    //   7064: invokestatic a : (Ljava/lang/Throwable;)Ljava/lang/Throwable;
    //   7067: athrow
    //   7068: aload #7
    //   7070: invokevirtual getType : ()Ljava/lang/Class;
    //   7073: astore #8
    //   7075: aload #8
    //   7077: ifnull -> 7158
    //   7080: aload #8
    //   7082: invokevirtual isPrimitive : ()Z
    //   7085: ifne -> 7158
    //   7088: goto -> 7095
    //   7091: invokestatic a : (Ljava/lang/Throwable;)Ljava/lang/Throwable;
    //   7094: athrow
    //   7095: aload #8
    //   7097: invokevirtual getPackage : ()Ljava/lang/Package;
    //   7100: ifnull -> 7158
    //   7103: goto -> 7110
    //   7106: invokestatic a : (Ljava/lang/Throwable;)Ljava/lang/Throwable;
    //   7109: athrow
    //   7110: aload #8
    //   7112: invokevirtual getPackage : ()Ljava/lang/Package;
    //   7115: invokevirtual getName : ()Ljava/lang/String;
    //   7118: ifnull -> 7158
    //   7121: goto -> 7128
    //   7124: invokestatic a : (Ljava/lang/Throwable;)Ljava/lang/Throwable;
    //   7127: athrow
    //   7128: aload #8
    //   7130: invokevirtual getPackage : ()Ljava/lang/Package;
    //   7133: invokevirtual getName : ()Ljava/lang/String;
    //   7136: sipush #-19539
    //   7139: sipush #23209
    //   7142: invokestatic a : (II)Ljava/lang/String;
    //   7145: invokevirtual startsWith : (Ljava/lang/String;)Z
    //   7148: ifne -> 7158
    //   7151: goto -> 7158
    //   7154: invokestatic a : (Ljava/lang/Throwable;)Ljava/lang/Throwable;
    //   7157: athrow
    //   7158: aload #7
    //   7160: iconst_1
    //   7161: invokevirtual setAccessible : (Z)V
    //   7164: aload #7
    //   7166: aconst_null
    //   7167: invokevirtual get : (Ljava/lang/Object;)Ljava/lang/Object;
    //   7170: pop
    //   7171: iinc #6, 1
    //   7174: iload_2
    //   7175: ifne -> 7036
    //   7178: sipush #-19528
    //   7181: sipush #-24313
    //   7184: invokestatic a : (II)Ljava/lang/String;
    //   7187: invokestatic forName : (Ljava/lang/String;)Ljava/lang/Class;
    //   7190: invokevirtual getDeclaredMethods : ()[Ljava/lang/reflect/Method;
    //   7193: astore #4
    //   7195: aload #4
    //   7197: arraylength
    //   7198: istore #5
    //   7200: iconst_0
    //   7201: istore #6
    //   7203: iload #6
    //   7205: iload #5
    //   7207: if_icmpge -> 7343
    //   7210: aload #4
    //   7212: iload #6
    //   7214: aaload
    //   7215: astore #7
    //   7217: aload #7
    //   7219: invokevirtual getParameterTypes : ()[Ljava/lang/Class;
    //   7222: pop
    //   7223: aload #7
    //   7225: invokevirtual getModifiers : ()I
    //   7228: invokestatic isStatic : (I)Z
    //   7231: ifeq -> 7329
    //   7234: aload #7
    //   7236: invokevirtual getParameterTypes : ()[Ljava/lang/Class;
    //   7239: arraylength
    //   7240: iconst_2
    //   7241: if_icmpne -> 7329
    //   7244: goto -> 7251
    //   7247: invokestatic a : (Ljava/lang/Throwable;)Ljava/lang/Throwable;
    //   7250: athrow
    //   7251: aload #7
    //   7253: invokevirtual getReturnType : ()Ljava/lang/Class;
    //   7256: getstatic java/lang/Boolean.TYPE : Ljava/lang/Class;
    //   7259: if_acmpne -> 7329
    //   7262: goto -> 7269
    //   7265: invokestatic a : (Ljava/lang/Throwable;)Ljava/lang/Throwable;
    //   7268: athrow
    //   7269: aload #7
    //   7271: iconst_1
    //   7272: invokevirtual setAccessible : (Z)V
    //   7275: aload #7
    //   7277: aconst_null
    //   7278: iconst_2
    //   7279: anewarray java/lang/Object
    //   7282: dup
    //   7283: iconst_0
    //   7284: aload_0
    //   7285: aastore
    //   7286: dup
    //   7287: iconst_1
    //   7288: aload_1
    //   7289: ifnonnull -> 7307
    //   7292: goto -> 7299
    //   7295: invokestatic a : (Ljava/lang/Throwable;)Ljava/lang/Throwable;
    //   7298: athrow
    //   7299: aload_1
    //   7300: goto -> 7314
    //   7303: invokestatic a : (Ljava/lang/Throwable;)Ljava/lang/Throwable;
    //   7306: athrow
    //   7307: aload_1
    //   7308: checkcast [B
    //   7311: invokevirtual clone : ()Ljava/lang/Object;
    //   7314: aastore
    //   7315: invokevirtual invoke : (Ljava/lang/Object;[Ljava/lang/Object;)Ljava/lang/Object;
    //   7318: checkcast java/lang/Boolean
    //   7321: invokevirtual booleanValue : ()Z
    //   7324: istore_3
    //   7325: iload_2
    //   7326: ifne -> 7343
    //   7329: iinc #6, 1
    //   7332: iload_2
    //   7333: ifne -> 7203
    //   7336: goto -> 7343
    //   7339: invokestatic a : (Ljava/lang/Throwable;)Ljava/lang/Throwable;
    //   7342: athrow
    //   7343: iload_3
    //   7344: ireturn
    //   7345: astore_3
    //   7346: new java/lang/Exception
    //   7349: dup
    //   7350: aload_3
    //   7351: invokevirtual getMessage : ()Ljava/lang/String;
    //   7354: invokespecial <init> : (Ljava/lang/String;)V
    //   7357: athrow
    // Exception table:
    //   from	to	target	type
    //   4	5155	7345	java/lang/Throwable
    //   823	857	860	java/lang/Throwable
    //   952	1030	1033	java/lang/Throwable
    //   959	1173	1176	java/lang/Throwable
    //   1550	1565	1565	java/lang/Throwable
    //   1592	1626	1629	java/lang/Throwable
    //   1636	1648	1651	java/lang/Throwable
    //   1734	1812	1815	java/lang/Throwable
    //   1741	1955	1958	java/lang/Throwable
    //   2355	2433	2436	java/lang/Throwable
    //   2362	2576	2579	java/lang/Throwable
    //   3023	3057	3060	java/lang/Throwable
    //   3064	3076	3079	java/lang/Throwable
    //   3162	3240	3243	java/lang/Throwable
    //   3169	3383	3386	java/lang/Throwable
    //   4137	4151	4151	java/lang/Throwable
    //   4162	4175	4178	java/lang/Throwable
    //   4167	4190	4193	java/lang/Throwable
    //   4182	4208	4211	java/lang/Throwable
    //   4197	4238	4241	java/lang/Throwable
    //   4301	4328	4331	java/lang/Throwable
    //   4318	4349	4352	java/lang/Throwable
    //   4335	4379	4382	java/lang/Throwable
    //   4356	4390	4390	java/lang/Throwable
    //   4401	4417	4420	java/lang/Throwable
    //   4516	4530	4530	java/lang/Throwable
    //   4541	4554	4557	java/lang/Throwable
    //   4546	4569	4572	java/lang/Throwable
    //   4561	4587	4590	java/lang/Throwable
    //   4576	4617	4620	java/lang/Throwable
    //   4683	4710	4713	java/lang/Throwable
    //   4700	4728	4731	java/lang/Throwable
    //   4717	4758	4761	java/lang/Throwable
    //   4735	4769	4769	java/lang/Throwable
    //   4791	4802	4805	java/lang/Throwable
    //   4857	4871	4871	java/lang/Throwable
    //   4882	4895	4898	java/lang/Throwable
    //   4887	4910	4913	java/lang/Throwable
    //   4902	4928	4931	java/lang/Throwable
    //   4917	4958	4961	java/lang/Throwable
    //   5024	5051	5054	java/lang/Throwable
    //   5041	5069	5072	java/lang/Throwable
    //   5058	5099	5102	java/lang/Throwable
    //   5076	5110	5110	java/lang/Throwable
    //   5132	5143	5146	java/lang/Throwable
    //   5156	5886	7345	java/lang/Throwable
    //   5246	5260	5260	java/lang/Throwable
    //   5271	5284	5287	java/lang/Throwable
    //   5276	5299	5302	java/lang/Throwable
    //   5291	5317	5320	java/lang/Throwable
    //   5306	5347	5350	java/lang/Throwable
    //   5413	5440	5443	java/lang/Throwable
    //   5430	5458	5461	java/lang/Throwable
    //   5447	5488	5491	java/lang/Throwable
    //   5465	5499	5499	java/lang/Throwable
    //   5521	5532	5535	java/lang/Throwable
    //   5588	5602	5602	java/lang/Throwable
    //   5613	5626	5629	java/lang/Throwable
    //   5618	5641	5644	java/lang/Throwable
    //   5633	5659	5662	java/lang/Throwable
    //   5648	5689	5692	java/lang/Throwable
    //   5755	5782	5785	java/lang/Throwable
    //   5772	5800	5803	java/lang/Throwable
    //   5789	5830	5833	java/lang/Throwable
    //   5807	5841	5841	java/lang/Throwable
    //   5863	5874	5877	java/lang/Throwable
    //   5887	6617	7345	java/lang/Throwable
    //   5977	5991	5991	java/lang/Throwable
    //   6002	6015	6018	java/lang/Throwable
    //   6007	6030	6033	java/lang/Throwable
    //   6022	6048	6051	java/lang/Throwable
    //   6037	6078	6081	java/lang/Throwable
    //   6144	6171	6174	java/lang/Throwable
    //   6161	6189	6192	java/lang/Throwable
    //   6178	6219	6222	java/lang/Throwable
    //   6196	6230	6230	java/lang/Throwable
    //   6252	6263	6266	java/lang/Throwable
    //   6319	6333	6333	java/lang/Throwable
    //   6344	6357	6360	java/lang/Throwable
    //   6349	6372	6375	java/lang/Throwable
    //   6364	6390	6393	java/lang/Throwable
    //   6379	6420	6423	java/lang/Throwable
    //   6486	6513	6516	java/lang/Throwable
    //   6503	6531	6534	java/lang/Throwable
    //   6520	6561	6564	java/lang/Throwable
    //   6538	6572	6572	java/lang/Throwable
    //   6594	6605	6608	java/lang/Throwable
    //   6618	7344	7345	java/lang/Throwable
    //   6708	6722	6722	java/lang/Throwable
    //   6733	6746	6749	java/lang/Throwable
    //   6738	6761	6764	java/lang/Throwable
    //   6753	6779	6782	java/lang/Throwable
    //   6768	6809	6812	java/lang/Throwable
    //   6875	6902	6905	java/lang/Throwable
    //   6892	6920	6923	java/lang/Throwable
    //   6909	6950	6953	java/lang/Throwable
    //   6927	6961	6961	java/lang/Throwable
    //   6983	6994	6997	java/lang/Throwable
    //   7050	7064	7064	java/lang/Throwable
    //   7075	7088	7091	java/lang/Throwable
    //   7080	7103	7106	java/lang/Throwable
    //   7095	7121	7124	java/lang/Throwable
    //   7110	7151	7154	java/lang/Throwable
    //   7217	7244	7247	java/lang/Throwable
    //   7234	7262	7265	java/lang/Throwable
    //   7251	7292	7295	java/lang/Throwable
    //   7269	7303	7303	java/lang/Throwable
    //   7325	7336	7339	java/lang/Throwable
  }
  
  static {
    // Byte code:
    //   0: bipush #25
    //   2: anewarray java/lang/String
    //   5: astore #5
    //   7: iconst_0
    //   8: istore_3
    //   9: ldc '&\\t)-9\\tgX#-\\tBifp\\tNW]\\tV=\\tP$L@l dp&j(v96!yX#\\tMfs!\\td{r\\t\\t0X|B\\t?u|\\tp\\tMah\\tZj.\\rO\\t51>$O ="R[`k)8f#UP\\t(1JXMLz\\ni=@},S-fJ\\fWjY1(}'W\\b{!M .\\t-Z^}m\\t/-dm=\\t=}\\ttX'
    //   11: dup
    //   12: astore_2
    //   13: invokevirtual length : ()I
    //   16: istore #4
    //   18: iconst_4
    //   19: istore_1
    //   20: iconst_m1
    //   21: istore_0
    //   22: bipush #123
    //   24: iinc #0, 1
    //   27: aload_2
    //   28: iload_0
    //   29: dup
    //   30: iload_1
    //   31: iadd
    //   32: invokevirtual substring : (II)Ljava/lang/String;
    //   35: iconst_m1
    //   36: goto -> 142
    //   39: aload #5
    //   41: swap
    //   42: iload_3
    //   43: iinc #3, 1
    //   46: swap
    //   47: aastore
    //   48: iload_0
    //   49: iload_1
    //   50: iadd
    //   51: dup
    //   52: istore_0
    //   53: iload #4
    //   55: if_icmpge -> 67
    //   58: aload_2
    //   59: iload_0
    //   60: invokevirtual charAt : (I)C
    //   63: istore_1
    //   64: goto -> 22
    //   67: ldc ' *+g2\\tT\\rM!'
    //   69: dup
    //   70: astore_2
    //   71: invokevirtual length : ()I
    //   74: istore #4
    //   76: bipush #9
    //   78: istore_1
    //   79: iconst_m1
    //   80: istore_0
    //   81: bipush #52
    //   83: iinc #0, 1
    //   86: aload_2
    //   87: iload_0
    //   88: dup
    //   89: iload_1
    //   90: iadd
    //   91: invokevirtual substring : (II)Ljava/lang/String;
    //   94: iconst_0
    //   95: goto -> 142
    //   98: aload #5
    //   100: swap
    //   101: iload_3
    //   102: iinc #3, 1
    //   105: swap
    //   106: aastore
    //   107: iload_0
    //   108: iload_1
    //   109: iadd
    //   110: dup
    //   111: istore_0
    //   112: iload #4
    //   114: if_icmpge -> 126
    //   117: aload_2
    //   118: iload_0
    //   119: invokevirtual charAt : (I)C
    //   122: istore_1
    //   123: goto -> 81
    //   126: aload #5
    //   128: putstatic burp/Zlc2.a : [Ljava/lang/String;
    //   131: bipush #25
    //   133: anewarray java/lang/String
    //   136: putstatic burp/Zlc2.b : [Ljava/lang/String;
    //   139: goto -> 300
    //   142: dup_x2
    //   143: pop
    //   144: invokevirtual toCharArray : ()[C
    //   147: dup_x1
    //   148: arraylength
    //   149: dup_x2
    //   150: pop
    //   151: iconst_0
    //   152: istore #6
    //   154: dup2_x1
    //   155: pop2
    //   156: dup_x2
    //   157: iconst_1
    //   158: if_icmpgt -> 260
    //   161: dup2
    //   162: swap
    //   163: iload #6
    //   165: dup2_x1
    //   166: caload
    //   167: swap
    //   168: iload #6
    //   170: bipush #7
    //   172: irem
    //   173: tableswitch default -> 242, 0 -> 212, 1 -> 217, 2 -> 222, 3 -> 227, 4 -> 232, 5 -> 237
    //   212: bipush #57
    //   214: goto -> 244
    //   217: bipush #28
    //   219: goto -> 244
    //   222: bipush #78
    //   224: goto -> 244
    //   227: bipush #45
    //   229: goto -> 244
    //   232: bipush #98
    //   234: goto -> 244
    //   237: bipush #93
    //   239: goto -> 244
    //   242: bipush #96
    //   244: ixor
    //   245: ixor
    //   246: i2c
    //   247: castore
    //   248: iinc #6, 1
    //   251: dup
    //   252: ifne -> 260
    //   255: dup2
    //   256: dup_x1
    //   257: goto -> 165
    //   260: dup2_x1
    //   261: pop2
    //   262: dup_x2
    //   263: iload #6
    //   265: if_icmpgt -> 161
    //   268: pop
    //   269: new java/lang/String
    //   272: dup_x1
    //   273: swap
    //   274: invokespecial <init> : ([C)V
    //   277: invokevirtual intern : ()Ljava/lang/String;
    //   280: swap
    //   281: pop
    //   282: swap
    //   283: tableswitch default -> 39, 0 -> 98
    //   300: new java/math/BigInteger
    //   303: dup
    //   304: bipush #32
    //   306: newarray byte
    //   308: dup
    //   309: iconst_0
    //   310: bipush #40
    //   312: bastore
    //   313: dup
    //   314: iconst_1
    //   315: bipush #-67
    //   317: bastore
    //   318: dup
    //   319: iconst_2
    //   320: bipush #52
    //   322: bastore
    //   323: dup
    //   324: iconst_3
    //   325: bipush #88
    //   327: bastore
    //   328: dup
    //   329: iconst_4
    //   330: bipush #-127
    //   332: bastore
    //   333: dup
    //   334: iconst_5
    //   335: bipush #-120
    //   337: bastore
    //   338: dup
    //   339: bipush #6
    //   341: bipush #-11
    //   343: bastore
    //   344: dup
    //   345: bipush #7
    //   347: bipush #127
    //   349: bastore
    //   350: dup
    //   351: bipush #8
    //   353: bipush #-25
    //   355: bastore
    //   356: dup
    //   357: bipush #9
    //   359: bipush #-126
    //   361: bastore
    //   362: dup
    //   363: bipush #10
    //   365: bipush #53
    //   367: bastore
    //   368: dup
    //   369: bipush #11
    //   371: bipush #104
    //   373: bastore
    //   374: dup
    //   375: bipush #12
    //   377: bipush #63
    //   379: bastore
    //   380: dup
    //   381: bipush #13
    //   383: bipush #-9
    //   385: bastore
    //   386: dup
    //   387: bipush #14
    //   389: bipush #-79
    //   391: bastore
    //   392: dup
    //   393: bipush #15
    //   395: bipush #13
    //   397: bastore
    //   398: dup
    //   399: bipush #16
    //   401: bipush #120
    //   403: bastore
    //   404: dup
    //   405: bipush #17
    //   407: bipush #78
    //   409: bastore
    //   410: dup
    //   411: bipush #18
    //   413: bipush #-35
    //   415: bastore
    //   416: dup
    //   417: bipush #19
    //   419: bipush #96
    //   421: bastore
    //   422: dup
    //   423: bipush #20
    //   425: bipush #83
    //   427: bastore
    //   428: dup
    //   429: bipush #21
    //   431: bipush #42
    //   433: bastore
    //   434: dup
    //   435: bipush #22
    //   437: bipush #-51
    //   439: bastore
    //   440: dup
    //   441: bipush #23
    //   443: bipush #107
    //   445: bastore
    //   446: dup
    //   447: bipush #24
    //   449: bipush #26
    //   451: bastore
    //   452: dup
    //   453: bipush #25
    //   455: bipush #-22
    //   457: bastore
    //   458: dup
    //   459: bipush #26
    //   461: bipush #75
    //   463: bastore
    //   464: dup
    //   465: bipush #27
    //   467: bipush #-62
    //   469: bastore
    //   470: dup
    //   471: bipush #28
    //   473: bipush #122
    //   475: bastore
    //   476: dup
    //   477: bipush #29
    //   479: bipush #91
    //   481: bastore
    //   482: dup
    //   483: bipush #30
    //   485: iconst_1
    //   486: bastore
    //   487: dup
    //   488: bipush #31
    //   490: bipush #-59
    //   492: bastore
    //   493: invokespecial <init> : ([B)V
    //   496: putstatic burp/Zlc2.ZQ : Ljava/lang/Object;
    //   499: sipush #-19551
    //   502: sipush #6762
    //   505: invokestatic a : (II)Ljava/lang/String;
    //   508: putstatic burp/Zlc2.Zz : Ljava/lang/String;
    //   511: return
  }
  
  private static Throwable a(Throwable paramThrowable) {
    return paramThrowable;
  }
  
  private static String a(int paramInt1, int paramInt2) {
    int i = (paramInt1 ^ 0xFFFFB3A9) & 0xFFFF;
    if (b[i] == null) {
      char[] arrayOfChar = a[i].toCharArray();
      switch (arrayOfChar[0] & 0xFF) {
        case 0:
        
        case 1:
        
        case 2:
        
        case 3:
        
        case 4:
        
        case 5:
        
        case 6:
        
        case 7:
        
        case 8:
        
        case 9:
        
        case 10:
        
        case 11:
        
        case 12:
        
        case 13:
        
        case 14:
        
        case 15:
        
        case 16:
        
        case 17:
        
        case 18:
        
        case 19:
        
        case 20:
        
        case 21:
        
        case 22:
        
        case 23:
        
        case 24:
        
        case 25:
        
        case 26:
        
        case 27:
        
        case 28:
        
        case 29:
        
        case 30:
        
        case 31:
        
        case 32:
        
        case 33:
        
        case 34:
        
        case 35:
        
        case 36:
        
        case 37:
        
        case 38:
        
        case 39:
        
        case 40:
        
        case 41:
        
        case 42:
        
        case 43:
        
        case 44:
        
        case 45:
        
        case 46:
        
        case 47:
        
        case 48:
        
        case 49:
        
        case 50:
        
        case 51:
        
        case 52:
        
        case 53:
        
        case 54:
        
        case 55:
        
        case 56:
        
        case 57:
        
        case 58:
        
        case 59:
        
        case 60:
        
        case 61:
        
        case 62:
        
        case 63:
        
        case 64:
        
        case 65:
        
        case 66:
        
        case 67:
        
        case 68:
        
        case 69:
        
        case 70:
        
        case 71:
        
        case 72:
        
        case 73:
        
        case 74:
        
        case 75:
        
        case 76:
        
        case 77:
        
        case 78:
        
        case 79:
        
        case 80:
        
        case 81:
        
        case 82:
        
        case 83:
        
        case 84:
        
        case 85:
        
        case 86:
        
        case 87:
        
        case 88:
        
        case 89:
        
        case 90:
        
        case 91:
        
        case 92:
        
        case 93:
        
        case 94:
        
        case 95:
        
        case 96:
        
        case 97:
        
        case 98:
        
        case 99:
        
        case 100:
        
        case 101:
        
        case 102:
        
        case 103:
        
        case 104:
        
        case 105:
        
        case 106:
        
        case 107:
        
        case 108:
        
        case 109:
        
        case 110:
        
        case 111:
        
        case 112:
        
        case 113:
        
        case 114:
        
        case 115:
        
        case 116:
        
        case 117:
        
        case 118:
        
        case 119:
        
        case 120:
        
        case 121:
        
        case 122:
        
        case 123:
        
        case 124:
        
        case 125:
        
        case 126:
        
        case 127:
        
        case 128:
        
        case 129:
        
        case 130:
        
        case 131:
        
        case 132:
        
        case 133:
        
        case 134:
        
        case 135:
        
        case 136:
        
        case 137:
        
        case 138:
        
        case 139:
        
        case 140:
        
        case 141:
        
        case 142:
        
        case 143:
        
        case 144:
        
        case 145:
        
        case 146:
        
        case 147:
        
        case 148:
        
        case 149:
        
        case 150:
        
        case 151:
        
        case 152:
        
        case 153:
        
        case 154:
        
        case 155:
        
        case 156:
        
        case 157:
        
        case 158:
        
        case 159:
        
        case 160:
        
        case 161:
        
        case 162:
        
        case 163:
        
        case 164:
        
        case 165:
        
        case 166:
        
        case 167:
        
        case 168:
        
        case 169:
        
        case 170:
        
        case 171:
        
        case 172:
        
        case 173:
        
        case 174:
        
        case 175:
        
        case 176:
        
        case 177:
        
        case 178:
        
        case 179:
        
        case 180:
        
        case 181:
        
        case 182:
        
        case 183:
        
        case 184:
        
        case 185:
        
        case 186:
        
        case 187:
        
        case 188:
        
        case 189:
        
        case 190:
        
        case 191:
        
        case 192:
        
        case 193:
        
        case 194:
        
        case 195:
        
        case 196:
        
        case 197:
        
        case 198:
        
        case 199:
        
        case 200:
        
        case 201:
        
        case 202:
        
        case 203:
        
        case 204:
        
        case 205:
        
        case 206:
        
        case 207:
        
        case 208:
        
        case 209:
        
        case 210:
        
        case 211:
        
        case 212:
        
        case 213:
        
        case 214:
        
        case 215:
        
        case 216:
        
        case 217:
        
        case 218:
        
        case 219:
        
        case 220:
        
        case 221:
        
        case 222:
        
        case 223:
        
        case 224:
        
        case 225:
        
        case 226:
        
        case 227:
        
        case 228:
        
        case 229:
        
        case 230:
        
        case 231:
        
        case 232:
        
        case 233:
        
        case 234:
        
        case 235:
        
        case 236:
        
        case 237:
        
        case 238:
        
        case 239:
        
        case 240:
        
        case 241:
        
        case 242:
        
        case 243:
        
        case 244:
        
        case 245:
        
        case 246:
        
        case 247:
        
        case 248:
        
        case 249:
        
        case 250:
        
        case 251:
        
        case 252:
        
        case 253:
        
        case 254:
        
        default:
          break;
      } 
      char c = '';
      int j = (paramInt2 & 0xFF) - c;
      if (j < 0)
        j += 256; 
      int k = ((paramInt2 & 0xFFFF) >>> 8) - c;
      if (k < 0)
        k += 256; 
      for (byte b = 0; b < arrayOfChar.length; b++) {
        int m = b % 2;
        if (m == 0) {
          arrayOfChar[b] = (char)(arrayOfChar[b] ^ j);
          j = ((j >>> 3 | j << 5) ^ arrayOfChar[b]) & 0xFF;
        } else {
          arrayOfChar[b] = (char)(arrayOfChar[b] ^ k);
          k = ((k >>> 3 | k << 5) ^ arrayOfChar[b]) & 0xFF;
        } 
      } 
      b[i] = (new String(arrayOfChar)).intern();
    } 
    return b[i];
  }
}


/* Location:              C:\Program Files\BurpSuitePro\burpsuite_pro.jar!\burp\Zlc2.class
 * Java compiler version: 21 (65.0)
 * JD-Core Version:       1.1.3
 */