package burp;

import javax.swing.text.Segment;

public class Zldn {
  final Zlnz ZZ;
  
  final Zlnz Zk;
  
  final Zlnz Za;
  
  final Zlnz Zq;
  
  final Zlnz Zy;
  
  final Zlnz ZH;
  
  final Zlnz ZM;
  
  final Zlnz ZT;
  
  final Zlnz Zz;
  
  final Zlnz Ze;
  
  final Zlnz ZL;
  
  final Zlnz ZJ;
  
  final Zlnz Z_;
  
  final Zlnz ZO;
  
  final Zlnz ZW;
  
  final Zlnz ZB;
  
  final Zlnz ZG;
  
  final Zlnz Zw;
  
  final Zlnz Zi;
  
  final Zlnz ZK;
  
  final Zlnz Zf;
  
  final Zlnz Zd;
  
  final Zlnz Zc;
  
  final Zlnz ZR;
  
  final Zlnz ZC;
  
  private final Zmf8 ZV;
  
  private Zlnz ZA;
  
  private Zxgn Zm;
  
  private static String[] Zh;
  
  public Zldn(Segment paramSegment, Zska paramZska, int paramInt, Zmf8 paramZmf8, String paramString) {
    // Byte code:
    //   0: aload_0
    //   1: invokespecial <init> : ()V
    //   4: aload_0
    //   5: aload #4
    //   7: putfield ZV : Lburp/Zmf8;
    //   10: invokestatic ZS : ()[Ljava/lang/String;
    //   13: aload_0
    //   14: new burp/Zxgn
    //   17: dup
    //   18: aload_1
    //   19: aload_2
    //   20: iload_3
    //   21: aload #4
    //   23: invokespecial <init> : (Ljavax/swing/text/Segment;Lburp/Zska;ILburp/Zmf8;)V
    //   26: putfield Zm : Lburp/Zxgn;
    //   29: aload_0
    //   30: new burp/Zsrn
    //   33: dup
    //   34: aload_0
    //   35: aload_0
    //   36: getfield Zm : Lburp/Zxgn;
    //   39: aload #4
    //   41: invokespecial <init> : (Lburp/Zldn;Lburp/Zxgn;Lburp/Zmf8;)V
    //   44: putfield ZZ : Lburp/Zlnz;
    //   47: aload_0
    //   48: new burp/Zsrw
    //   51: dup
    //   52: aload_0
    //   53: aload_0
    //   54: getfield Zm : Lburp/Zxgn;
    //   57: aload #4
    //   59: invokespecial <init> : (Lburp/Zldn;Lburp/Zxgn;Lburp/Zmf8;)V
    //   62: putfield Zk : Lburp/Zlnz;
    //   65: aload_0
    //   66: new burp/Zsrx
    //   69: dup
    //   70: aload_0
    //   71: aload_0
    //   72: getfield Zm : Lburp/Zxgn;
    //   75: aload #4
    //   77: invokespecial <init> : (Lburp/Zldn;Lburp/Zxgn;Lburp/Zmf8;)V
    //   80: putfield Za : Lburp/Zlnz;
    //   83: astore #6
    //   85: aload_0
    //   86: new burp/Zsr_
    //   89: dup
    //   90: aload_0
    //   91: aload_0
    //   92: getfield Zm : Lburp/Zxgn;
    //   95: aload #4
    //   97: invokespecial <init> : (Lburp/Zldn;Lburp/Zxgn;Lburp/Zmf8;)V
    //   100: putfield Zq : Lburp/Zlnz;
    //   103: aload_0
    //   104: new burp/Zsr0
    //   107: dup
    //   108: aload_0
    //   109: aload_0
    //   110: getfield Zm : Lburp/Zxgn;
    //   113: aload #4
    //   115: invokespecial <init> : (Lburp/Zldn;Lburp/Zxgn;Lburp/Zmf8;)V
    //   118: putfield Zy : Lburp/Zlnz;
    //   121: aload_0
    //   122: new burp/Zsr6
    //   125: dup
    //   126: aload_0
    //   127: aload_0
    //   128: getfield Zm : Lburp/Zxgn;
    //   131: aload #4
    //   133: invokespecial <init> : (Lburp/Zldn;Lburp/Zxgn;Lburp/Zmf8;)V
    //   136: putfield ZH : Lburp/Zlnz;
    //   139: aload_0
    //   140: new burp/Zsrz
    //   143: dup
    //   144: aload_0
    //   145: aload_0
    //   146: getfield Zm : Lburp/Zxgn;
    //   149: aload #4
    //   151: invokespecial <init> : (Lburp/Zldn;Lburp/Zxgn;Lburp/Zmf8;)V
    //   154: putfield ZM : Lburp/Zlnz;
    //   157: aload_0
    //   158: new burp/Zsrl
    //   161: dup
    //   162: aload_0
    //   163: aload_0
    //   164: getfield Zm : Lburp/Zxgn;
    //   167: aload #4
    //   169: invokespecial <init> : (Lburp/Zldn;Lburp/Zxgn;Lburp/Zmf8;)V
    //   172: putfield ZT : Lburp/Zlnz;
    //   175: aload_0
    //   176: new burp/Zsr4
    //   179: dup
    //   180: aload_0
    //   181: aload_0
    //   182: getfield Zm : Lburp/Zxgn;
    //   185: aload #4
    //   187: invokespecial <init> : (Lburp/Zldn;Lburp/Zxgn;Lburp/Zmf8;)V
    //   190: putfield Zz : Lburp/Zlnz;
    //   193: aload_0
    //   194: new burp/Zsrm
    //   197: dup
    //   198: aload_0
    //   199: aload_0
    //   200: getfield Zm : Lburp/Zxgn;
    //   203: aload #4
    //   205: invokespecial <init> : (Lburp/Zldn;Lburp/Zxgn;Lburp/Zmf8;)V
    //   208: putfield Ze : Lburp/Zlnz;
    //   211: aload_0
    //   212: new burp/Zsrb
    //   215: dup
    //   216: aload_0
    //   217: aload_0
    //   218: getfield Zm : Lburp/Zxgn;
    //   221: aload #4
    //   223: aload #5
    //   225: invokespecial <init> : (Lburp/Zldn;Lburp/Zxgn;Lburp/Zmf8;Ljava/lang/String;)V
    //   228: putfield ZL : Lburp/Zlnz;
    //   231: aload_0
    //   232: new burp/Zsra
    //   235: dup
    //   236: aload_0
    //   237: aload_0
    //   238: getfield Zm : Lburp/Zxgn;
    //   241: aload #4
    //   243: invokespecial <init> : (Lburp/Zldn;Lburp/Zxgn;Lburp/Zmf8;)V
    //   246: putfield ZJ : Lburp/Zlnz;
    //   249: aload_0
    //   250: new burp/Zsrd
    //   253: dup
    //   254: aload_0
    //   255: aload_0
    //   256: getfield Zm : Lburp/Zxgn;
    //   259: aload #4
    //   261: invokespecial <init> : (Lburp/Zldn;Lburp/Zxgn;Lburp/Zmf8;)V
    //   264: putfield Z_ : Lburp/Zlnz;
    //   267: aload_0
    //   268: new burp/Zsrc
    //   271: dup
    //   272: aload_0
    //   273: aload_0
    //   274: getfield Zm : Lburp/Zxgn;
    //   277: aload #4
    //   279: invokespecial <init> : (Lburp/Zldn;Lburp/Zxgn;Lburp/Zmf8;)V
    //   282: putfield ZO : Lburp/Zlnz;
    //   285: aload_0
    //   286: new burp/Zsrk
    //   289: dup
    //   290: aload_0
    //   291: aload_0
    //   292: getfield Zm : Lburp/Zxgn;
    //   295: aload #4
    //   297: invokespecial <init> : (Lburp/Zldn;Lburp/Zxgn;Lburp/Zmf8;)V
    //   300: putfield ZW : Lburp/Zlnz;
    //   303: aload_0
    //   304: new burp/Zsr8
    //   307: dup
    //   308: aload_0
    //   309: aload_0
    //   310: getfield Zm : Lburp/Zxgn;
    //   313: aload #4
    //   315: invokespecial <init> : (Lburp/Zldn;Lburp/Zxgn;Lburp/Zmf8;)V
    //   318: putfield ZB : Lburp/Zlnz;
    //   321: aload_0
    //   322: new burp/Zsro
    //   325: dup
    //   326: aload_0
    //   327: aload_0
    //   328: getfield Zm : Lburp/Zxgn;
    //   331: aload #4
    //   333: invokespecial <init> : (Lburp/Zldn;Lburp/Zxgn;Lburp/Zmf8;)V
    //   336: putfield ZG : Lburp/Zlnz;
    //   339: aload_0
    //   340: new burp/Zsrj
    //   343: dup
    //   344: aload_0
    //   345: aload_0
    //   346: getfield Zm : Lburp/Zxgn;
    //   349: aload #4
    //   351: invokespecial <init> : (Lburp/Zldn;Lburp/Zxgn;Lburp/Zmf8;)V
    //   354: putfield Zw : Lburp/Zlnz;
    //   357: aload_0
    //   358: new burp/Zsrf
    //   361: dup
    //   362: aload_0
    //   363: aload_0
    //   364: getfield Zm : Lburp/Zxgn;
    //   367: aload #4
    //   369: invokespecial <init> : (Lburp/Zldn;Lburp/Zxgn;Lburp/Zmf8;)V
    //   372: putfield Zi : Lburp/Zlnz;
    //   375: aload_0
    //   376: new burp/Zsrs
    //   379: dup
    //   380: aload_0
    //   381: aload_0
    //   382: getfield Zm : Lburp/Zxgn;
    //   385: aload #4
    //   387: invokespecial <init> : (Lburp/Zldn;Lburp/Zxgn;Lburp/Zmf8;)V
    //   390: putfield ZK : Lburp/Zlnz;
    //   393: aload_0
    //   394: new burp/Zsre
    //   397: dup
    //   398: aload_0
    //   399: aload_0
    //   400: getfield Zm : Lburp/Zxgn;
    //   403: aload #4
    //   405: invokespecial <init> : (Lburp/Zldn;Lburp/Zxgn;Lburp/Zmf8;)V
    //   408: putfield Zf : Lburp/Zlnz;
    //   411: aload_0
    //   412: new burp/Zsrp
    //   415: dup
    //   416: aload_0
    //   417: aload_0
    //   418: getfield Zm : Lburp/Zxgn;
    //   421: aload #4
    //   423: invokespecial <init> : (Lburp/Zldn;Lburp/Zxgn;Lburp/Zmf8;)V
    //   426: putfield Zd : Lburp/Zlnz;
    //   429: aload_0
    //   430: new burp/Zsrg
    //   433: dup
    //   434: aload_0
    //   435: aload_0
    //   436: getfield Zm : Lburp/Zxgn;
    //   439: aload #4
    //   441: invokespecial <init> : (Lburp/Zldn;Lburp/Zxgn;Lburp/Zmf8;)V
    //   444: putfield Zc : Lburp/Zlnz;
    //   447: aload_0
    //   448: new burp/Zsrt
    //   451: dup
    //   452: aload_0
    //   453: aload_0
    //   454: getfield Zm : Lburp/Zxgn;
    //   457: aload #4
    //   459: invokespecial <init> : (Lburp/Zldn;Lburp/Zxgn;Lburp/Zmf8;)V
    //   462: putfield ZR : Lburp/Zlnz;
    //   465: aload_0
    //   466: new burp/Zsrr
    //   469: dup
    //   470: aload_0
    //   471: aload_0
    //   472: getfield Zm : Lburp/Zxgn;
    //   475: aload #4
    //   477: invokespecial <init> : (Lburp/Zldn;Lburp/Zxgn;Lburp/Zmf8;)V
    //   480: putfield ZC : Lburp/Zlnz;
    //   483: aload_0
    //   484: getfield Zm : Lburp/Zxgn;
    //   487: invokevirtual ZT : ()Z
    //   490: ifeq -> 538
    //   493: aload_0
    //   494: new burp/Zsrq
    //   497: dup
    //   498: aload_0
    //   499: aload_0
    //   500: getfield Zm : Lburp/Zxgn;
    //   503: aload #4
    //   505: invokespecial <init> : (Lburp/Zldn;Lburp/Zxgn;Lburp/Zmf8;)V
    //   508: putfield ZA : Lburp/Zlnz;
    //   511: aload #4
    //   513: iconst_1
    //   514: invokeinterface ZC : (I)V
    //   519: aload_0
    //   520: getfield Zm : Lburp/Zxgn;
    //   523: invokevirtual Zx : ()V
    //   526: aload #6
    //   528: ifnull -> 613
    //   531: iconst_5
    //   532: anewarray burp/Zbqc
    //   535: invokestatic Zr : ([Lburp/Zbqc;)V
    //   538: aload_0
    //   539: getfield Zm : Lburp/Zxgn;
    //   542: invokevirtual ZK : ()Z
    //   545: ifeq -> 586
    //   548: aload_0
    //   549: new burp/Zsr2
    //   552: dup
    //   553: aload_0
    //   554: aload_0
    //   555: getfield Zm : Lburp/Zxgn;
    //   558: aload #4
    //   560: invokespecial <init> : (Lburp/Zldn;Lburp/Zxgn;Lburp/Zmf8;)V
    //   563: putfield ZA : Lburp/Zlnz;
    //   566: aload #4
    //   568: iconst_2
    //   569: invokeinterface ZC : (I)V
    //   574: aload_0
    //   575: getfield Zm : Lburp/Zxgn;
    //   578: invokevirtual Zl : ()V
    //   581: aload #6
    //   583: ifnull -> 613
    //   586: aload #4
    //   588: iconst_0
    //   589: invokeinterface ZC : (I)V
    //   594: aload_0
    //   595: aload_0
    //   596: getfield Zm : Lburp/Zxgn;
    //   599: aload_0
    //   600: aload #4
    //   602: <illegal opcode> apply : (Lburp/Zldn;Lburp/Zmf8;)Ljava/util/function/Function;
    //   607: invokevirtual Z_ : (Ljava/util/function/Function;)Lburp/Zlnz;
    //   610: putfield ZA : Lburp/Zlnz;
    //   613: aload_0
    //   614: getfield Zm : Lburp/Zxgn;
    //   617: invokevirtual Zs : ()V
    //   620: return
  }
  
  public void ZT() {
    String[] arrayOfString = ZS();
    while (this.Zm.Zy() && this.ZA != null) {
      this.ZA = this.ZA.Zq(this.Zm.ZG());
      this.Zm.Zm();
      if (arrayOfString != null)
        break; 
    } 
    if (this.ZA != null) {
      if (!this.ZA.ZZ()) {
        this.ZA.ZR();
        this.Zm.ZE(this.ZA.Zl());
      } 
      Zp();
    } 
  }
  
  private void Zp() {
    // Byte code:
    //   0: invokestatic ZS : ()[Ljava/lang/String;
    //   3: astore_1
    //   4: aload_0
    //   5: getfield ZA : Lburp/Zlnz;
    //   8: invokeinterface Zk : ()Z
    //   13: ifeq -> 17
    //   16: return
    //   17: aload_0
    //   18: getfield Zm : Lburp/Zxgn;
    //   21: aload_0
    //   22: getfield ZA : Lburp/Zlnz;
    //   25: invokevirtual ZG : (Lburp/Zlnz;)I
    //   28: istore_2
    //   29: iload_2
    //   30: ifne -> 56
    //   33: aload_0
    //   34: getfield ZV : Lburp/Zmf8;
    //   37: invokeinterface Zf : ()Lburp/Zska;
    //   42: pop
    //   43: aload_0
    //   44: getfield ZA : Lburp/Zlnz;
    //   47: invokeinterface ZA : ()V
    //   52: aload_1
    //   53: ifnull -> 117
    //   56: aload_0
    //   57: getfield Zm : Lburp/Zxgn;
    //   60: getfield Zc : Z
    //   63: ifeq -> 75
    //   66: iload_2
    //   67: invokestatic Zu : (I)I
    //   70: istore_2
    //   71: aload_1
    //   72: ifnull -> 109
    //   75: aload_0
    //   76: getfield Zm : Lburp/Zxgn;
    //   79: getfield ZB : Z
    //   82: ifeq -> 94
    //   85: iload_2
    //   86: invokestatic ZV : (I)I
    //   89: istore_2
    //   90: aload_1
    //   91: ifnull -> 109
    //   94: aload_0
    //   95: getfield Zm : Lburp/Zxgn;
    //   98: getfield ZR : Z
    //   101: ifeq -> 109
    //   104: iload_2
    //   105: invokestatic ZE : (I)I
    //   108: istore_2
    //   109: aload_0
    //   110: getfield Zm : Lburp/Zxgn;
    //   113: iload_2
    //   114: invokevirtual ZE : (I)V
    //   117: return
  }
  
  private Zlnz ZY(int paramInt, Zmf8 paramZmf8) {
    switch (paramInt) {
      case -1:
        return new Zsr7(this, this.Zm, paramZmf8);
      case -2:
        return new Zsri(this, this.Zm, paramZmf8);
      case -3:
        return new Zsru(this, this.Zm, paramZmf8);
      case -4:
        return new Zsr3(this, this.Zm, paramZmf8);
      case -7:
      case -6:
      case -5:
        return new Zsr1(this, this.Zm, paramZmf8);
      case -8:
        return new Zsr9(this, this.Zm, paramZmf8);
      case -9:
        return new Zsrv(this, this.Zm, paramZmf8);
    } 
    return new Zsrh(this, this.Zm, paramZmf8);
  }
  
  private Zlnz lambda$new$0(Zmf8 paramZmf8, Integer paramInteger) {
    return ZY(paramInteger.intValue(), paramZmf8);
  }
  
  public static void Zw(String[] paramArrayOfString) {
    Zh = paramArrayOfString;
  }
  
  public static String[] ZS() {
    return Zh;
  }
  
  static {
    if (ZS() != null)
      Zw(new String[1]); 
  }
}


/* Location:              C:\Program Files\BurpSuitePro\burpsuite_pro.jar!\burp\Zldn.class
 * Java compiler version: 21 (65.0)
 * JD-Core Version:       1.1.3
 */