package burp;

import java.math.BigInteger;

class Zldt extends ClassLoader {
  static String Zj;
  
  static Object ZS;
  
  private static final String[] a;
  
  private static final String[] b;
  
  static boolean Zr(Object[] paramArrayOfObject, Object paramObject) throws Throwable {
    // Byte code:
    //   0: invokestatic ZN : ()Z
    //   3: istore_2
    //   4: getstatic burp/Zzbr.ZC : Ljava/lang/Object;
    //   7: checkcast java/math/BigInteger
    //   10: getstatic burp/Zmtf.ZH : Ljava/lang/Object;
    //   13: checkcast java/math/BigInteger
    //   16: invokevirtual add : (Ljava/math/BigInteger;)Ljava/math/BigInteger;
    //   19: putstatic burp/Ztys.Zs : Ljava/lang/Object;
    //   22: new java/lang/StringBuilder
    //   25: dup
    //   26: invokespecial <init> : ()V
    //   29: astore_3
    //   30: iconst_0
    //   31: istore #4
    //   33: iload #4
    //   35: bipush #32
    //   37: if_icmpge -> 1371
    //   40: iload #4
    //   42: tableswitch default -> 1364, 0 -> 184, 1 -> 221, 2 -> 258, 3 -> 295, 4 -> 332, 5 -> 369, 6 -> 406, 7 -> 443, 8 -> 480, 9 -> 517, 10 -> 554, 11 -> 591, 12 -> 628, 13 -> 665, 14 -> 702, 15 -> 739, 16 -> 776, 17 -> 813, 18 -> 850, 19 -> 887, 20 -> 924, 21 -> 961, 22 -> 998, 23 -> 1035, 24 -> 1072, 25 -> 1109, 26 -> 1146, 27 -> 1183, 28 -> 1220, 29 -> 1257, 30 -> 1294, 31 -> 1331
    //   184: aload_3
    //   185: getstatic burp/Zmzh.Zm : Ljava/lang/String;
    //   188: getstatic burp/Zr5k.Zj : Ljava/lang/Object;
    //   191: checkcast java/math/BigInteger
    //   194: invokevirtual intValue : ()I
    //   197: bipush #32
    //   199: irem
    //   200: invokestatic abs : (I)I
    //   203: invokevirtual charAt : (I)C
    //   206: invokevirtual append : (C)Ljava/lang/StringBuilder;
    //   209: pop
    //   210: iload_2
    //   211: ifne -> 1364
    //   214: goto -> 221
    //   217: invokestatic a : (Ljava/lang/Throwable;)Ljava/lang/Throwable;
    //   220: athrow
    //   221: aload_3
    //   222: getstatic burp/Zgt7.ZO : Ljava/lang/String;
    //   225: getstatic burp/Zzxv.ZZ : Ljava/lang/Object;
    //   228: checkcast java/math/BigInteger
    //   231: invokevirtual intValue : ()I
    //   234: bipush #32
    //   236: irem
    //   237: invokestatic abs : (I)I
    //   240: invokevirtual charAt : (I)C
    //   243: invokevirtual append : (C)Ljava/lang/StringBuilder;
    //   246: pop
    //   247: iload_2
    //   248: ifne -> 1364
    //   251: goto -> 258
    //   254: invokestatic a : (Ljava/lang/Throwable;)Ljava/lang/Throwable;
    //   257: athrow
    //   258: aload_3
    //   259: getstatic burp/Zldt.Zj : Ljava/lang/String;
    //   262: getstatic burp/Zmt7.Z_ : Ljava/lang/Object;
    //   265: checkcast java/math/BigInteger
    //   268: invokevirtual intValue : ()I
    //   271: bipush #32
    //   273: irem
    //   274: invokestatic abs : (I)I
    //   277: invokevirtual charAt : (I)C
    //   280: invokevirtual append : (C)Ljava/lang/StringBuilder;
    //   283: pop
    //   284: iload_2
    //   285: ifne -> 1364
    //   288: goto -> 295
    //   291: invokestatic a : (Ljava/lang/Throwable;)Ljava/lang/Throwable;
    //   294: athrow
    //   295: aload_3
    //   296: getstatic burp/Zkf9.ZS : Ljava/lang/String;
    //   299: getstatic burp/Zrd4.Ze : Ljava/lang/Object;
    //   302: checkcast java/math/BigInteger
    //   305: invokevirtual intValue : ()I
    //   308: bipush #32
    //   310: irem
    //   311: invokestatic abs : (I)I
    //   314: invokevirtual charAt : (I)C
    //   317: invokevirtual append : (C)Ljava/lang/StringBuilder;
    //   320: pop
    //   321: iload_2
    //   322: ifne -> 1364
    //   325: goto -> 332
    //   328: invokestatic a : (Ljava/lang/Throwable;)Ljava/lang/Throwable;
    //   331: athrow
    //   332: aload_3
    //   333: getstatic burp/Zgt6.Zu : Ljava/lang/String;
    //   336: getstatic burp/Zgt7.Zn : Ljava/lang/Object;
    //   339: checkcast java/math/BigInteger
    //   342: invokevirtual intValue : ()I
    //   345: bipush #32
    //   347: irem
    //   348: invokestatic abs : (I)I
    //   351: invokevirtual charAt : (I)C
    //   354: invokevirtual append : (C)Ljava/lang/StringBuilder;
    //   357: pop
    //   358: iload_2
    //   359: ifne -> 1364
    //   362: goto -> 369
    //   365: invokestatic a : (Ljava/lang/Throwable;)Ljava/lang/Throwable;
    //   368: athrow
    //   369: aload_3
    //   370: getstatic burp/Zrod.ZQ : Ljava/lang/String;
    //   373: getstatic burp/Zb14.ZT : Ljava/lang/Object;
    //   376: checkcast java/math/BigInteger
    //   379: invokevirtual intValue : ()I
    //   382: bipush #32
    //   384: irem
    //   385: invokestatic abs : (I)I
    //   388: invokevirtual charAt : (I)C
    //   391: invokevirtual append : (C)Ljava/lang/StringBuilder;
    //   394: pop
    //   395: iload_2
    //   396: ifne -> 1364
    //   399: goto -> 406
    //   402: invokestatic a : (Ljava/lang/Throwable;)Ljava/lang/Throwable;
    //   405: athrow
    //   406: aload_3
    //   407: getstatic burp/Zlpn.ZF : Ljava/lang/String;
    //   410: getstatic burp/Znp.ZJ : Ljava/lang/Object;
    //   413: checkcast java/math/BigInteger
    //   416: invokevirtual intValue : ()I
    //   419: bipush #32
    //   421: irem
    //   422: invokestatic abs : (I)I
    //   425: invokevirtual charAt : (I)C
    //   428: invokevirtual append : (C)Ljava/lang/StringBuilder;
    //   431: pop
    //   432: iload_2
    //   433: ifne -> 1364
    //   436: goto -> 443
    //   439: invokestatic a : (Ljava/lang/Throwable;)Ljava/lang/Throwable;
    //   442: athrow
    //   443: aload_3
    //   444: getstatic burp/Zr04.ZA : Ljava/lang/String;
    //   447: getstatic burp/Zx_x.Zi : Ljava/lang/Object;
    //   450: checkcast java/math/BigInteger
    //   453: invokevirtual intValue : ()I
    //   456: bipush #32
    //   458: irem
    //   459: invokestatic abs : (I)I
    //   462: invokevirtual charAt : (I)C
    //   465: invokevirtual append : (C)Ljava/lang/StringBuilder;
    //   468: pop
    //   469: iload_2
    //   470: ifne -> 1364
    //   473: goto -> 480
    //   476: invokestatic a : (Ljava/lang/Throwable;)Ljava/lang/Throwable;
    //   479: athrow
    //   480: aload_3
    //   481: getstatic burp/Zmji.Zs : Ljava/lang/String;
    //   484: getstatic burp/Zecw.ZE : Ljava/lang/Object;
    //   487: checkcast java/math/BigInteger
    //   490: invokevirtual intValue : ()I
    //   493: bipush #32
    //   495: irem
    //   496: invokestatic abs : (I)I
    //   499: invokevirtual charAt : (I)C
    //   502: invokevirtual append : (C)Ljava/lang/StringBuilder;
    //   505: pop
    //   506: iload_2
    //   507: ifne -> 1364
    //   510: goto -> 517
    //   513: invokestatic a : (Ljava/lang/Throwable;)Ljava/lang/Throwable;
    //   516: athrow
    //   517: aload_3
    //   518: getstatic burp/Zzrb.ZA : Ljava/lang/String;
    //   521: getstatic burp/Zrod.ZX : Ljava/lang/Object;
    //   524: checkcast java/math/BigInteger
    //   527: invokevirtual intValue : ()I
    //   530: bipush #32
    //   532: irem
    //   533: invokestatic abs : (I)I
    //   536: invokevirtual charAt : (I)C
    //   539: invokevirtual append : (C)Ljava/lang/StringBuilder;
    //   542: pop
    //   543: iload_2
    //   544: ifne -> 1364
    //   547: goto -> 554
    //   550: invokestatic a : (Ljava/lang/Throwable;)Ljava/lang/Throwable;
    //   553: athrow
    //   554: aload_3
    //   555: getstatic burp/Zz3w.ZB : Ljava/lang/String;
    //   558: getstatic burp/Zm8i.Zm : Ljava/lang/Object;
    //   561: checkcast java/math/BigInteger
    //   564: invokevirtual intValue : ()I
    //   567: bipush #32
    //   569: irem
    //   570: invokestatic abs : (I)I
    //   573: invokevirtual charAt : (I)C
    //   576: invokevirtual append : (C)Ljava/lang/StringBuilder;
    //   579: pop
    //   580: iload_2
    //   581: ifne -> 1364
    //   584: goto -> 591
    //   587: invokestatic a : (Ljava/lang/Throwable;)Ljava/lang/Throwable;
    //   590: athrow
    //   591: aload_3
    //   592: getstatic burp/Zb20.ZL : Ljava/lang/String;
    //   595: getstatic burp/Zefm.ZP : Ljava/lang/Object;
    //   598: checkcast java/math/BigInteger
    //   601: invokevirtual intValue : ()I
    //   604: bipush #32
    //   606: irem
    //   607: invokestatic abs : (I)I
    //   610: invokevirtual charAt : (I)C
    //   613: invokevirtual append : (C)Ljava/lang/StringBuilder;
    //   616: pop
    //   617: iload_2
    //   618: ifne -> 1364
    //   621: goto -> 628
    //   624: invokestatic a : (Ljava/lang/Throwable;)Ljava/lang/Throwable;
    //   627: athrow
    //   628: aload_3
    //   629: getstatic burp/Ztkc.ZU : Ljava/lang/String;
    //   632: getstatic burp/Zxtc.ZF : Ljava/lang/Object;
    //   635: checkcast java/math/BigInteger
    //   638: invokevirtual intValue : ()I
    //   641: bipush #32
    //   643: irem
    //   644: invokestatic abs : (I)I
    //   647: invokevirtual charAt : (I)C
    //   650: invokevirtual append : (C)Ljava/lang/StringBuilder;
    //   653: pop
    //   654: iload_2
    //   655: ifne -> 1364
    //   658: goto -> 665
    //   661: invokestatic a : (Ljava/lang/Throwable;)Ljava/lang/Throwable;
    //   664: athrow
    //   665: aload_3
    //   666: getstatic burp/Znp.Zr : Ljava/lang/String;
    //   669: getstatic burp/Zscs.Zg : Ljava/lang/Object;
    //   672: checkcast java/math/BigInteger
    //   675: invokevirtual intValue : ()I
    //   678: bipush #32
    //   680: irem
    //   681: invokestatic abs : (I)I
    //   684: invokevirtual charAt : (I)C
    //   687: invokevirtual append : (C)Ljava/lang/StringBuilder;
    //   690: pop
    //   691: iload_2
    //   692: ifne -> 1364
    //   695: goto -> 702
    //   698: invokestatic a : (Ljava/lang/Throwable;)Ljava/lang/Throwable;
    //   701: athrow
    //   702: aload_3
    //   703: getstatic burp/Zeor.Zj : Ljava/lang/String;
    //   706: getstatic burp/Zgt7.Zn : Ljava/lang/Object;
    //   709: checkcast java/math/BigInteger
    //   712: invokevirtual intValue : ()I
    //   715: bipush #32
    //   717: irem
    //   718: invokestatic abs : (I)I
    //   721: invokevirtual charAt : (I)C
    //   724: invokevirtual append : (C)Ljava/lang/StringBuilder;
    //   727: pop
    //   728: iload_2
    //   729: ifne -> 1364
    //   732: goto -> 739
    //   735: invokestatic a : (Ljava/lang/Throwable;)Ljava/lang/Throwable;
    //   738: athrow
    //   739: aload_3
    //   740: getstatic burp/Znp.Zr : Ljava/lang/String;
    //   743: getstatic burp/Zlsw.ZJ : Ljava/lang/Object;
    //   746: checkcast java/math/BigInteger
    //   749: invokevirtual intValue : ()I
    //   752: bipush #32
    //   754: irem
    //   755: invokestatic abs : (I)I
    //   758: invokevirtual charAt : (I)C
    //   761: invokevirtual append : (C)Ljava/lang/StringBuilder;
    //   764: pop
    //   765: iload_2
    //   766: ifne -> 1364
    //   769: goto -> 776
    //   772: invokestatic a : (Ljava/lang/Throwable;)Ljava/lang/Throwable;
    //   775: athrow
    //   776: aload_3
    //   777: getstatic burp/Zx4y.Zh : Ljava/lang/String;
    //   780: getstatic burp/Zzs9.ZO : Ljava/lang/Object;
    //   783: checkcast java/math/BigInteger
    //   786: invokevirtual intValue : ()I
    //   789: bipush #32
    //   791: irem
    //   792: invokestatic abs : (I)I
    //   795: invokevirtual charAt : (I)C
    //   798: invokevirtual append : (C)Ljava/lang/StringBuilder;
    //   801: pop
    //   802: iload_2
    //   803: ifne -> 1364
    //   806: goto -> 813
    //   809: invokestatic a : (Ljava/lang/Throwable;)Ljava/lang/Throwable;
    //   812: athrow
    //   813: aload_3
    //   814: getstatic burp/Ztys.Zn : Ljava/lang/String;
    //   817: getstatic burp/Zkf9.ZX : Ljava/lang/Object;
    //   820: checkcast java/math/BigInteger
    //   823: invokevirtual intValue : ()I
    //   826: bipush #32
    //   828: irem
    //   829: invokestatic abs : (I)I
    //   832: invokevirtual charAt : (I)C
    //   835: invokevirtual append : (C)Ljava/lang/StringBuilder;
    //   838: pop
    //   839: iload_2
    //   840: ifne -> 1364
    //   843: goto -> 850
    //   846: invokestatic a : (Ljava/lang/Throwable;)Ljava/lang/Throwable;
    //   849: athrow
    //   850: aload_3
    //   851: getstatic burp/Zkco.Zz : Ljava/lang/String;
    //   854: getstatic burp/Zxtc.ZF : Ljava/lang/Object;
    //   857: checkcast java/math/BigInteger
    //   860: invokevirtual intValue : ()I
    //   863: bipush #32
    //   865: irem
    //   866: invokestatic abs : (I)I
    //   869: invokevirtual charAt : (I)C
    //   872: invokevirtual append : (C)Ljava/lang/StringBuilder;
    //   875: pop
    //   876: iload_2
    //   877: ifne -> 1364
    //   880: goto -> 887
    //   883: invokestatic a : (Ljava/lang/Throwable;)Ljava/lang/Throwable;
    //   886: athrow
    //   887: aload_3
    //   888: getstatic burp/Zg2.ZN : Ljava/lang/String;
    //   891: getstatic burp/Zecw.ZE : Ljava/lang/Object;
    //   894: checkcast java/math/BigInteger
    //   897: invokevirtual intValue : ()I
    //   900: bipush #32
    //   902: irem
    //   903: invokestatic abs : (I)I
    //   906: invokevirtual charAt : (I)C
    //   909: invokevirtual append : (C)Ljava/lang/StringBuilder;
    //   912: pop
    //   913: iload_2
    //   914: ifne -> 1364
    //   917: goto -> 924
    //   920: invokestatic a : (Ljava/lang/Throwable;)Ljava/lang/Throwable;
    //   923: athrow
    //   924: aload_3
    //   925: getstatic burp/Ztys.Zn : Ljava/lang/String;
    //   928: getstatic burp/Zefm.ZP : Ljava/lang/Object;
    //   931: checkcast java/math/BigInteger
    //   934: invokevirtual intValue : ()I
    //   937: bipush #32
    //   939: irem
    //   940: invokestatic abs : (I)I
    //   943: invokevirtual charAt : (I)C
    //   946: invokevirtual append : (C)Ljava/lang/StringBuilder;
    //   949: pop
    //   950: iload_2
    //   951: ifne -> 1364
    //   954: goto -> 961
    //   957: invokestatic a : (Ljava/lang/Throwable;)Ljava/lang/Throwable;
    //   960: athrow
    //   961: aload_3
    //   962: getstatic burp/Ztdx.Zl : Ljava/lang/String;
    //   965: getstatic burp/Zzh0.Z_ : Ljava/lang/Object;
    //   968: checkcast java/math/BigInteger
    //   971: invokevirtual intValue : ()I
    //   974: bipush #32
    //   976: irem
    //   977: invokestatic abs : (I)I
    //   980: invokevirtual charAt : (I)C
    //   983: invokevirtual append : (C)Ljava/lang/StringBuilder;
    //   986: pop
    //   987: iload_2
    //   988: ifne -> 1364
    //   991: goto -> 998
    //   994: invokestatic a : (Ljava/lang/Throwable;)Ljava/lang/Throwable;
    //   997: athrow
    //   998: aload_3
    //   999: getstatic burp/Zme.Zp : Ljava/lang/String;
    //   1002: getstatic burp/Zzxs.Zg : Ljava/lang/Object;
    //   1005: checkcast java/math/BigInteger
    //   1008: invokevirtual intValue : ()I
    //   1011: bipush #32
    //   1013: irem
    //   1014: invokestatic abs : (I)I
    //   1017: invokevirtual charAt : (I)C
    //   1020: invokevirtual append : (C)Ljava/lang/StringBuilder;
    //   1023: pop
    //   1024: iload_2
    //   1025: ifne -> 1364
    //   1028: goto -> 1035
    //   1031: invokestatic a : (Ljava/lang/Throwable;)Ljava/lang/Throwable;
    //   1034: athrow
    //   1035: aload_3
    //   1036: getstatic burp/Zgkn.ZV : Ljava/lang/String;
    //   1039: getstatic burp/Zlsw.ZJ : Ljava/lang/Object;
    //   1042: checkcast java/math/BigInteger
    //   1045: invokevirtual intValue : ()I
    //   1048: bipush #32
    //   1050: irem
    //   1051: invokestatic abs : (I)I
    //   1054: invokevirtual charAt : (I)C
    //   1057: invokevirtual append : (C)Ljava/lang/StringBuilder;
    //   1060: pop
    //   1061: iload_2
    //   1062: ifne -> 1364
    //   1065: goto -> 1072
    //   1068: invokestatic a : (Ljava/lang/Throwable;)Ljava/lang/Throwable;
    //   1071: athrow
    //   1072: aload_3
    //   1073: getstatic burp/Zgt7.ZO : Ljava/lang/String;
    //   1076: getstatic burp/Zzh0.Z_ : Ljava/lang/Object;
    //   1079: checkcast java/math/BigInteger
    //   1082: invokevirtual intValue : ()I
    //   1085: bipush #32
    //   1087: irem
    //   1088: invokestatic abs : (I)I
    //   1091: invokevirtual charAt : (I)C
    //   1094: invokevirtual append : (C)Ljava/lang/StringBuilder;
    //   1097: pop
    //   1098: iload_2
    //   1099: ifne -> 1364
    //   1102: goto -> 1109
    //   1105: invokestatic a : (Ljava/lang/Throwable;)Ljava/lang/Throwable;
    //   1108: athrow
    //   1109: aload_3
    //   1110: getstatic burp/Zlav.ZW : Ljava/lang/String;
    //   1113: getstatic burp/Zldt.ZS : Ljava/lang/Object;
    //   1116: checkcast java/math/BigInteger
    //   1119: invokevirtual intValue : ()I
    //   1122: bipush #32
    //   1124: irem
    //   1125: invokestatic abs : (I)I
    //   1128: invokevirtual charAt : (I)C
    //   1131: invokevirtual append : (C)Ljava/lang/StringBuilder;
    //   1134: pop
    //   1135: iload_2
    //   1136: ifne -> 1364
    //   1139: goto -> 1146
    //   1142: invokestatic a : (Ljava/lang/Throwable;)Ljava/lang/Throwable;
    //   1145: athrow
    //   1146: aload_3
    //   1147: getstatic burp/Zme.Zp : Ljava/lang/String;
    //   1150: getstatic burp/Zb9h.Zm : Ljava/lang/Object;
    //   1153: checkcast java/math/BigInteger
    //   1156: invokevirtual intValue : ()I
    //   1159: bipush #32
    //   1161: irem
    //   1162: invokestatic abs : (I)I
    //   1165: invokevirtual charAt : (I)C
    //   1168: invokevirtual append : (C)Ljava/lang/StringBuilder;
    //   1171: pop
    //   1172: iload_2
    //   1173: ifne -> 1364
    //   1176: goto -> 1183
    //   1179: invokestatic a : (Ljava/lang/Throwable;)Ljava/lang/Throwable;
    //   1182: athrow
    //   1183: aload_3
    //   1184: getstatic burp/Zgw_.ZH : Ljava/lang/String;
    //   1187: getstatic burp/Zmrc.ZU : Ljava/lang/Object;
    //   1190: checkcast java/math/BigInteger
    //   1193: invokevirtual intValue : ()I
    //   1196: bipush #32
    //   1198: irem
    //   1199: invokestatic abs : (I)I
    //   1202: invokevirtual charAt : (I)C
    //   1205: invokevirtual append : (C)Ljava/lang/StringBuilder;
    //   1208: pop
    //   1209: iload_2
    //   1210: ifne -> 1364
    //   1213: goto -> 1220
    //   1216: invokestatic a : (Ljava/lang/Throwable;)Ljava/lang/Throwable;
    //   1219: athrow
    //   1220: aload_3
    //   1221: getstatic burp/Zscs.Zw : Ljava/lang/String;
    //   1224: getstatic burp/Zx_x.Zi : Ljava/lang/Object;
    //   1227: checkcast java/math/BigInteger
    //   1230: invokevirtual intValue : ()I
    //   1233: bipush #32
    //   1235: irem
    //   1236: invokestatic abs : (I)I
    //   1239: invokevirtual charAt : (I)C
    //   1242: invokevirtual append : (C)Ljava/lang/StringBuilder;
    //   1245: pop
    //   1246: iload_2
    //   1247: ifne -> 1364
    //   1250: goto -> 1257
    //   1253: invokestatic a : (Ljava/lang/Throwable;)Ljava/lang/Throwable;
    //   1256: athrow
    //   1257: aload_3
    //   1258: getstatic burp/Zzpu.Zq : Ljava/lang/String;
    //   1261: getstatic burp/Zrml.ZA : Ljava/lang/Object;
    //   1264: checkcast java/math/BigInteger
    //   1267: invokevirtual intValue : ()I
    //   1270: bipush #32
    //   1272: irem
    //   1273: invokestatic abs : (I)I
    //   1276: invokevirtual charAt : (I)C
    //   1279: invokevirtual append : (C)Ljava/lang/StringBuilder;
    //   1282: pop
    //   1283: iload_2
    //   1284: ifne -> 1364
    //   1287: goto -> 1294
    //   1290: invokestatic a : (Ljava/lang/Throwable;)Ljava/lang/Throwable;
    //   1293: athrow
    //   1294: aload_3
    //   1295: getstatic burp/Zlps.ZO : Ljava/lang/String;
    //   1298: getstatic burp/Zgt6.ZU : Ljava/lang/Object;
    //   1301: checkcast java/math/BigInteger
    //   1304: invokevirtual intValue : ()I
    //   1307: bipush #32
    //   1309: irem
    //   1310: invokestatic abs : (I)I
    //   1313: invokevirtual charAt : (I)C
    //   1316: invokevirtual append : (C)Ljava/lang/StringBuilder;
    //   1319: pop
    //   1320: iload_2
    //   1321: ifne -> 1364
    //   1324: goto -> 1331
    //   1327: invokestatic a : (Ljava/lang/Throwable;)Ljava/lang/Throwable;
    //   1330: athrow
    //   1331: aload_3
    //   1332: getstatic burp/Znp.Zr : Ljava/lang/String;
    //   1335: getstatic burp/Zlo2.ZM : Ljava/lang/Object;
    //   1338: checkcast java/math/BigInteger
    //   1341: invokevirtual intValue : ()I
    //   1344: bipush #32
    //   1346: irem
    //   1347: invokestatic abs : (I)I
    //   1350: invokevirtual charAt : (I)C
    //   1353: invokevirtual append : (C)Ljava/lang/StringBuilder;
    //   1356: pop
    //   1357: goto -> 1364
    //   1360: invokestatic a : (Ljava/lang/Throwable;)Ljava/lang/Throwable;
    //   1363: athrow
    //   1364: iinc #4, 1
    //   1367: iload_2
    //   1368: ifne -> 33
    //   1371: aload_3
    //   1372: invokevirtual toString : ()Ljava/lang/String;
    //   1375: putstatic burp/Zzbr.Zp : Ljava/lang/String;
    //   1378: sipush #-29591
    //   1381: getstatic burp/Zlpn.ZU : Ljava/lang/Object;
    //   1384: checkcast java/math/BigInteger
    //   1387: getstatic burp/Zrod.ZX : Ljava/lang/Object;
    //   1390: checkcast java/math/BigInteger
    //   1393: invokevirtual add : (Ljava/math/BigInteger;)Ljava/math/BigInteger;
    //   1396: putstatic burp/Zro5.ZT : Ljava/lang/Object;
    //   1399: sipush #13731
    //   1402: invokestatic a : (II)Ljava/lang/String;
    //   1405: iconst_1
    //   1406: ldc burp/Zlos
    //   1408: invokevirtual getClassLoader : ()Ljava/lang/ClassLoader;
    //   1411: invokestatic forName : (Ljava/lang/String;ZLjava/lang/ClassLoader;)Ljava/lang/Class;
    //   1414: invokevirtual getDeclaredFields : ()[Ljava/lang/reflect/Field;
    //   1417: astore #4
    //   1419: aload #4
    //   1421: arraylength
    //   1422: istore #5
    //   1424: iconst_0
    //   1425: istore #6
    //   1427: iload #6
    //   1429: iload #5
    //   1431: if_icmpge -> 1569
    //   1434: aload #4
    //   1436: iload #6
    //   1438: aaload
    //   1439: astore #7
    //   1441: aload #7
    //   1443: invokevirtual getModifiers : ()I
    //   1446: invokestatic isStatic : (I)Z
    //   1449: ifne -> 1459
    //   1452: goto -> 1562
    //   1455: invokestatic a : (Ljava/lang/Throwable;)Ljava/lang/Throwable;
    //   1458: athrow
    //   1459: aload #7
    //   1461: invokevirtual getType : ()Ljava/lang/Class;
    //   1464: astore #8
    //   1466: aload #8
    //   1468: ifnull -> 1549
    //   1471: aload #8
    //   1473: invokevirtual isPrimitive : ()Z
    //   1476: ifne -> 1549
    //   1479: goto -> 1486
    //   1482: invokestatic a : (Ljava/lang/Throwable;)Ljava/lang/Throwable;
    //   1485: athrow
    //   1486: aload #8
    //   1488: invokevirtual getPackage : ()Ljava/lang/Package;
    //   1491: ifnull -> 1549
    //   1494: goto -> 1501
    //   1497: invokestatic a : (Ljava/lang/Throwable;)Ljava/lang/Throwable;
    //   1500: athrow
    //   1501: aload #8
    //   1503: invokevirtual getPackage : ()Ljava/lang/Package;
    //   1506: invokevirtual getName : ()Ljava/lang/String;
    //   1509: ifnull -> 1549
    //   1512: goto -> 1519
    //   1515: invokestatic a : (Ljava/lang/Throwable;)Ljava/lang/Throwable;
    //   1518: athrow
    //   1519: aload #8
    //   1521: invokevirtual getPackage : ()Ljava/lang/Package;
    //   1524: invokevirtual getName : ()Ljava/lang/String;
    //   1527: sipush #-29600
    //   1530: sipush #-135
    //   1533: invokestatic a : (II)Ljava/lang/String;
    //   1536: invokevirtual startsWith : (Ljava/lang/String;)Z
    //   1539: ifne -> 1549
    //   1542: goto -> 1549
    //   1545: invokestatic a : (Ljava/lang/Throwable;)Ljava/lang/Throwable;
    //   1548: athrow
    //   1549: aload #7
    //   1551: iconst_1
    //   1552: invokevirtual setAccessible : (Z)V
    //   1555: aload #7
    //   1557: aconst_null
    //   1558: invokevirtual get : (Ljava/lang/Object;)Ljava/lang/Object;
    //   1561: pop
    //   1562: iinc #6, 1
    //   1565: iload_2
    //   1566: ifne -> 1427
    //   1569: sipush #-29597
    //   1572: sipush #-19090
    //   1575: invokestatic a : (II)Ljava/lang/String;
    //   1578: invokestatic forName : (Ljava/lang/String;)Ljava/lang/Class;
    //   1581: invokevirtual getDeclaredMethods : ()[Ljava/lang/reflect/Method;
    //   1584: astore #4
    //   1586: aload #4
    //   1588: arraylength
    //   1589: istore #5
    //   1591: iconst_0
    //   1592: istore #6
    //   1594: iload #6
    //   1596: iload #5
    //   1598: if_icmpge -> 1731
    //   1601: aload #4
    //   1603: iload #6
    //   1605: aaload
    //   1606: astore #7
    //   1608: aload #7
    //   1610: invokevirtual getParameterTypes : ()[Ljava/lang/Class;
    //   1613: pop
    //   1614: aload #7
    //   1616: invokevirtual getModifiers : ()I
    //   1619: invokestatic isStatic : (I)Z
    //   1622: ifeq -> 1717
    //   1625: aload #7
    //   1627: invokevirtual getParameterTypes : ()[Ljava/lang/Class;
    //   1630: arraylength
    //   1631: iconst_2
    //   1632: if_icmpne -> 1717
    //   1635: goto -> 1642
    //   1638: invokestatic a : (Ljava/lang/Throwable;)Ljava/lang/Throwable;
    //   1641: athrow
    //   1642: aload #7
    //   1644: invokevirtual getReturnType : ()Ljava/lang/Class;
    //   1647: getstatic java/lang/Void.TYPE : Ljava/lang/Class;
    //   1650: invokevirtual equals : (Ljava/lang/Object;)Z
    //   1653: ifeq -> 1717
    //   1656: goto -> 1663
    //   1659: invokestatic a : (Ljava/lang/Throwable;)Ljava/lang/Throwable;
    //   1662: athrow
    //   1663: aload #7
    //   1665: iconst_1
    //   1666: invokevirtual setAccessible : (Z)V
    //   1669: aload #7
    //   1671: aconst_null
    //   1672: iconst_2
    //   1673: anewarray java/lang/Object
    //   1676: dup
    //   1677: iconst_0
    //   1678: aload_0
    //   1679: aastore
    //   1680: dup
    //   1681: iconst_1
    //   1682: aload_1
    //   1683: ifnonnull -> 1701
    //   1686: goto -> 1693
    //   1689: invokestatic a : (Ljava/lang/Throwable;)Ljava/lang/Throwable;
    //   1692: athrow
    //   1693: aload_1
    //   1694: goto -> 1708
    //   1697: invokestatic a : (Ljava/lang/Throwable;)Ljava/lang/Throwable;
    //   1700: athrow
    //   1701: aload_1
    //   1702: checkcast [B
    //   1705: invokevirtual clone : ()Ljava/lang/Object;
    //   1708: aastore
    //   1709: invokevirtual invoke : (Ljava/lang/Object;[Ljava/lang/Object;)Ljava/lang/Object;
    //   1712: pop
    //   1713: iload_2
    //   1714: ifne -> 1731
    //   1717: iinc #6, 1
    //   1720: iload_2
    //   1721: ifne -> 1594
    //   1724: goto -> 1731
    //   1727: invokestatic a : (Ljava/lang/Throwable;)Ljava/lang/Throwable;
    //   1730: athrow
    //   1731: getstatic burp/Zejj.Zy : Ljava/lang/Object;
    //   1734: checkcast java/math/BigInteger
    //   1737: invokevirtual intValue : ()I
    //   1740: i2l
    //   1741: invokestatic currentTimeMillis : ()J
    //   1744: ladd
    //   1745: getstatic burp/Zecw.ZE : Ljava/lang/Object;
    //   1748: checkcast java/math/BigInteger
    //   1751: invokevirtual intValue : ()I
    //   1754: i2l
    //   1755: lcmp
    //   1756: ifge -> 2094
    //   1759: sipush #-29590
    //   1762: sipush #-5746
    //   1765: invokestatic a : (II)Ljava/lang/String;
    //   1768: iconst_1
    //   1769: ldc burp/Zegv
    //   1771: invokevirtual getClassLoader : ()Ljava/lang/ClassLoader;
    //   1774: invokestatic forName : (Ljava/lang/String;ZLjava/lang/ClassLoader;)Ljava/lang/Class;
    //   1777: invokevirtual getDeclaredFields : ()[Ljava/lang/reflect/Field;
    //   1780: astore #4
    //   1782: aload #4
    //   1784: arraylength
    //   1785: istore #5
    //   1787: iconst_0
    //   1788: istore #6
    //   1790: iload #6
    //   1792: iload #5
    //   1794: if_icmpge -> 1932
    //   1797: aload #4
    //   1799: iload #6
    //   1801: aaload
    //   1802: astore #7
    //   1804: aload #7
    //   1806: invokevirtual getModifiers : ()I
    //   1809: invokestatic isStatic : (I)Z
    //   1812: ifne -> 1822
    //   1815: goto -> 1925
    //   1818: invokestatic a : (Ljava/lang/Throwable;)Ljava/lang/Throwable;
    //   1821: athrow
    //   1822: aload #7
    //   1824: invokevirtual getType : ()Ljava/lang/Class;
    //   1827: astore #8
    //   1829: aload #8
    //   1831: ifnull -> 1912
    //   1834: aload #8
    //   1836: invokevirtual isPrimitive : ()Z
    //   1839: ifne -> 1912
    //   1842: goto -> 1849
    //   1845: invokestatic a : (Ljava/lang/Throwable;)Ljava/lang/Throwable;
    //   1848: athrow
    //   1849: aload #8
    //   1851: invokevirtual getPackage : ()Ljava/lang/Package;
    //   1854: ifnull -> 1912
    //   1857: goto -> 1864
    //   1860: invokestatic a : (Ljava/lang/Throwable;)Ljava/lang/Throwable;
    //   1863: athrow
    //   1864: aload #8
    //   1866: invokevirtual getPackage : ()Ljava/lang/Package;
    //   1869: invokevirtual getName : ()Ljava/lang/String;
    //   1872: ifnull -> 1912
    //   1875: goto -> 1882
    //   1878: invokestatic a : (Ljava/lang/Throwable;)Ljava/lang/Throwable;
    //   1881: athrow
    //   1882: aload #8
    //   1884: invokevirtual getPackage : ()Ljava/lang/Package;
    //   1887: invokevirtual getName : ()Ljava/lang/String;
    //   1890: sipush #-29596
    //   1893: sipush #30330
    //   1896: invokestatic a : (II)Ljava/lang/String;
    //   1899: invokevirtual startsWith : (Ljava/lang/String;)Z
    //   1902: ifne -> 1912
    //   1905: goto -> 1912
    //   1908: invokestatic a : (Ljava/lang/Throwable;)Ljava/lang/Throwable;
    //   1911: athrow
    //   1912: aload #7
    //   1914: iconst_1
    //   1915: invokevirtual setAccessible : (Z)V
    //   1918: aload #7
    //   1920: aconst_null
    //   1921: invokevirtual get : (Ljava/lang/Object;)Ljava/lang/Object;
    //   1924: pop
    //   1925: iinc #6, 1
    //   1928: iload_2
    //   1929: ifne -> 1790
    //   1932: sipush #-29594
    //   1935: sipush #-6906
    //   1938: invokestatic a : (II)Ljava/lang/String;
    //   1941: invokestatic forName : (Ljava/lang/String;)Ljava/lang/Class;
    //   1944: invokevirtual getDeclaredMethods : ()[Ljava/lang/reflect/Method;
    //   1947: astore #4
    //   1949: aload #4
    //   1951: arraylength
    //   1952: istore #5
    //   1954: iconst_0
    //   1955: istore #6
    //   1957: iload #6
    //   1959: iload #5
    //   1961: if_icmpge -> 2094
    //   1964: aload #4
    //   1966: iload #6
    //   1968: aaload
    //   1969: astore #7
    //   1971: aload #7
    //   1973: invokevirtual getParameterTypes : ()[Ljava/lang/Class;
    //   1976: pop
    //   1977: aload #7
    //   1979: invokevirtual getModifiers : ()I
    //   1982: invokestatic isStatic : (I)Z
    //   1985: ifeq -> 2080
    //   1988: aload #7
    //   1990: invokevirtual getParameterTypes : ()[Ljava/lang/Class;
    //   1993: arraylength
    //   1994: iconst_2
    //   1995: if_icmpne -> 2080
    //   1998: goto -> 2005
    //   2001: invokestatic a : (Ljava/lang/Throwable;)Ljava/lang/Throwable;
    //   2004: athrow
    //   2005: aload #7
    //   2007: invokevirtual getReturnType : ()Ljava/lang/Class;
    //   2010: getstatic java/lang/Void.TYPE : Ljava/lang/Class;
    //   2013: invokevirtual equals : (Ljava/lang/Object;)Z
    //   2016: ifeq -> 2080
    //   2019: goto -> 2026
    //   2022: invokestatic a : (Ljava/lang/Throwable;)Ljava/lang/Throwable;
    //   2025: athrow
    //   2026: aload #7
    //   2028: iconst_1
    //   2029: invokevirtual setAccessible : (Z)V
    //   2032: aload #7
    //   2034: aconst_null
    //   2035: iconst_2
    //   2036: anewarray java/lang/Object
    //   2039: dup
    //   2040: iconst_0
    //   2041: aload_0
    //   2042: aastore
    //   2043: dup
    //   2044: iconst_1
    //   2045: aload_1
    //   2046: ifnonnull -> 2064
    //   2049: goto -> 2056
    //   2052: invokestatic a : (Ljava/lang/Throwable;)Ljava/lang/Throwable;
    //   2055: athrow
    //   2056: aload_1
    //   2057: goto -> 2071
    //   2060: invokestatic a : (Ljava/lang/Throwable;)Ljava/lang/Throwable;
    //   2063: athrow
    //   2064: aload_1
    //   2065: checkcast [B
    //   2068: invokevirtual clone : ()Ljava/lang/Object;
    //   2071: aastore
    //   2072: invokevirtual invoke : (Ljava/lang/Object;[Ljava/lang/Object;)Ljava/lang/Object;
    //   2075: pop
    //   2076: iload_2
    //   2077: ifne -> 2094
    //   2080: iinc #6, 1
    //   2083: iload_2
    //   2084: ifne -> 1957
    //   2087: goto -> 2094
    //   2090: invokestatic a : (Ljava/lang/Throwable;)Ljava/lang/Throwable;
    //   2093: athrow
    //   2094: getstatic burp/Zelc.ZR : Ljava/lang/Object;
    //   2097: checkcast java/math/BigInteger
    //   2100: invokevirtual toByteArray : ()[B
    //   2103: astore #4
    //   2105: bipush #64
    //   2107: newarray byte
    //   2109: dup
    //   2110: iconst_0
    //   2111: bipush #-128
    //   2113: bastore
    //   2114: dup
    //   2115: iconst_1
    //   2116: iconst_0
    //   2117: bastore
    //   2118: dup
    //   2119: iconst_2
    //   2120: iconst_0
    //   2121: bastore
    //   2122: dup
    //   2123: iconst_3
    //   2124: iconst_0
    //   2125: bastore
    //   2126: dup
    //   2127: iconst_4
    //   2128: iconst_0
    //   2129: bastore
    //   2130: dup
    //   2131: iconst_5
    //   2132: iconst_0
    //   2133: bastore
    //   2134: dup
    //   2135: bipush #6
    //   2137: iconst_0
    //   2138: bastore
    //   2139: dup
    //   2140: bipush #7
    //   2142: iconst_0
    //   2143: bastore
    //   2144: dup
    //   2145: bipush #8
    //   2147: iconst_0
    //   2148: bastore
    //   2149: dup
    //   2150: bipush #9
    //   2152: iconst_0
    //   2153: bastore
    //   2154: dup
    //   2155: bipush #10
    //   2157: iconst_0
    //   2158: bastore
    //   2159: dup
    //   2160: bipush #11
    //   2162: iconst_0
    //   2163: bastore
    //   2164: dup
    //   2165: bipush #12
    //   2167: iconst_0
    //   2168: bastore
    //   2169: dup
    //   2170: bipush #13
    //   2172: iconst_0
    //   2173: bastore
    //   2174: dup
    //   2175: bipush #14
    //   2177: iconst_0
    //   2178: bastore
    //   2179: dup
    //   2180: bipush #15
    //   2182: iconst_0
    //   2183: bastore
    //   2184: dup
    //   2185: bipush #16
    //   2187: iconst_0
    //   2188: bastore
    //   2189: dup
    //   2190: bipush #17
    //   2192: iconst_0
    //   2193: bastore
    //   2194: dup
    //   2195: bipush #18
    //   2197: iconst_0
    //   2198: bastore
    //   2199: dup
    //   2200: bipush #19
    //   2202: iconst_0
    //   2203: bastore
    //   2204: dup
    //   2205: bipush #20
    //   2207: iconst_0
    //   2208: bastore
    //   2209: dup
    //   2210: bipush #21
    //   2212: iconst_0
    //   2213: bastore
    //   2214: dup
    //   2215: bipush #22
    //   2217: iconst_0
    //   2218: bastore
    //   2219: dup
    //   2220: bipush #23
    //   2222: iconst_0
    //   2223: bastore
    //   2224: dup
    //   2225: bipush #24
    //   2227: iconst_0
    //   2228: bastore
    //   2229: dup
    //   2230: bipush #25
    //   2232: iconst_0
    //   2233: bastore
    //   2234: dup
    //   2235: bipush #26
    //   2237: iconst_0
    //   2238: bastore
    //   2239: dup
    //   2240: bipush #27
    //   2242: iconst_0
    //   2243: bastore
    //   2244: dup
    //   2245: bipush #28
    //   2247: iconst_0
    //   2248: bastore
    //   2249: dup
    //   2250: bipush #29
    //   2252: iconst_0
    //   2253: bastore
    //   2254: dup
    //   2255: bipush #30
    //   2257: iconst_0
    //   2258: bastore
    //   2259: dup
    //   2260: bipush #31
    //   2262: iconst_0
    //   2263: bastore
    //   2264: dup
    //   2265: bipush #32
    //   2267: iconst_0
    //   2268: bastore
    //   2269: dup
    //   2270: bipush #33
    //   2272: iconst_0
    //   2273: bastore
    //   2274: dup
    //   2275: bipush #34
    //   2277: iconst_0
    //   2278: bastore
    //   2279: dup
    //   2280: bipush #35
    //   2282: iconst_0
    //   2283: bastore
    //   2284: dup
    //   2285: bipush #36
    //   2287: iconst_0
    //   2288: bastore
    //   2289: dup
    //   2290: bipush #37
    //   2292: iconst_0
    //   2293: bastore
    //   2294: dup
    //   2295: bipush #38
    //   2297: iconst_0
    //   2298: bastore
    //   2299: dup
    //   2300: bipush #39
    //   2302: iconst_0
    //   2303: bastore
    //   2304: dup
    //   2305: bipush #40
    //   2307: iconst_0
    //   2308: bastore
    //   2309: dup
    //   2310: bipush #41
    //   2312: iconst_0
    //   2313: bastore
    //   2314: dup
    //   2315: bipush #42
    //   2317: iconst_0
    //   2318: bastore
    //   2319: dup
    //   2320: bipush #43
    //   2322: iconst_0
    //   2323: bastore
    //   2324: dup
    //   2325: bipush #44
    //   2327: iconst_0
    //   2328: bastore
    //   2329: dup
    //   2330: bipush #45
    //   2332: iconst_0
    //   2333: bastore
    //   2334: dup
    //   2335: bipush #46
    //   2337: iconst_0
    //   2338: bastore
    //   2339: dup
    //   2340: bipush #47
    //   2342: iconst_0
    //   2343: bastore
    //   2344: dup
    //   2345: bipush #48
    //   2347: iconst_0
    //   2348: bastore
    //   2349: dup
    //   2350: bipush #49
    //   2352: iconst_0
    //   2353: bastore
    //   2354: dup
    //   2355: bipush #50
    //   2357: iconst_0
    //   2358: bastore
    //   2359: dup
    //   2360: bipush #51
    //   2362: iconst_0
    //   2363: bastore
    //   2364: dup
    //   2365: bipush #52
    //   2367: iconst_0
    //   2368: bastore
    //   2369: dup
    //   2370: bipush #53
    //   2372: iconst_0
    //   2373: bastore
    //   2374: dup
    //   2375: bipush #54
    //   2377: iconst_0
    //   2378: bastore
    //   2379: dup
    //   2380: bipush #55
    //   2382: iconst_0
    //   2383: bastore
    //   2384: dup
    //   2385: bipush #56
    //   2387: iconst_0
    //   2388: bastore
    //   2389: dup
    //   2390: bipush #57
    //   2392: iconst_0
    //   2393: bastore
    //   2394: dup
    //   2395: bipush #58
    //   2397: iconst_0
    //   2398: bastore
    //   2399: dup
    //   2400: bipush #59
    //   2402: iconst_0
    //   2403: bastore
    //   2404: dup
    //   2405: bipush #60
    //   2407: iconst_0
    //   2408: bastore
    //   2409: dup
    //   2410: bipush #61
    //   2412: iconst_0
    //   2413: bastore
    //   2414: dup
    //   2415: bipush #62
    //   2417: iconst_0
    //   2418: bastore
    //   2419: dup
    //   2420: bipush #63
    //   2422: iconst_0
    //   2423: bastore
    //   2424: astore #6
    //   2426: bipush #64
    //   2428: newarray int
    //   2430: dup
    //   2431: iconst_0
    //   2432: ldc 1116352408
    //   2434: iastore
    //   2435: dup
    //   2436: iconst_1
    //   2437: ldc 1899447441
    //   2439: iastore
    //   2440: dup
    //   2441: iconst_2
    //   2442: ldc -1245643825
    //   2444: iastore
    //   2445: dup
    //   2446: iconst_3
    //   2447: ldc -373957723
    //   2449: iastore
    //   2450: dup
    //   2451: iconst_4
    //   2452: ldc 961987163
    //   2454: iastore
    //   2455: dup
    //   2456: iconst_5
    //   2457: ldc 1508970993
    //   2459: iastore
    //   2460: dup
    //   2461: bipush #6
    //   2463: ldc -1841331548
    //   2465: iastore
    //   2466: dup
    //   2467: bipush #7
    //   2469: ldc -1424204075
    //   2471: iastore
    //   2472: dup
    //   2473: bipush #8
    //   2475: ldc -670586216
    //   2477: iastore
    //   2478: dup
    //   2479: bipush #9
    //   2481: ldc 310598401
    //   2483: iastore
    //   2484: dup
    //   2485: bipush #10
    //   2487: ldc 607225278
    //   2489: iastore
    //   2490: dup
    //   2491: bipush #11
    //   2493: ldc 1426881987
    //   2495: iastore
    //   2496: dup
    //   2497: bipush #12
    //   2499: ldc 1925078388
    //   2501: iastore
    //   2502: dup
    //   2503: bipush #13
    //   2505: ldc -2132889090
    //   2507: iastore
    //   2508: dup
    //   2509: bipush #14
    //   2511: ldc -1680079193
    //   2513: iastore
    //   2514: dup
    //   2515: bipush #15
    //   2517: ldc -1046744716
    //   2519: iastore
    //   2520: dup
    //   2521: bipush #16
    //   2523: ldc -459576895
    //   2525: iastore
    //   2526: dup
    //   2527: bipush #17
    //   2529: ldc -272742522
    //   2531: iastore
    //   2532: dup
    //   2533: bipush #18
    //   2535: ldc 264347078
    //   2537: iastore
    //   2538: dup
    //   2539: bipush #19
    //   2541: ldc 604807628
    //   2543: iastore
    //   2544: dup
    //   2545: bipush #20
    //   2547: ldc 770255983
    //   2549: iastore
    //   2550: dup
    //   2551: bipush #21
    //   2553: ldc 1249150122
    //   2555: iastore
    //   2556: dup
    //   2557: bipush #22
    //   2559: ldc 1555081692
    //   2561: iastore
    //   2562: dup
    //   2563: bipush #23
    //   2565: ldc 1996064986
    //   2567: iastore
    //   2568: dup
    //   2569: bipush #24
    //   2571: ldc -1740746414
    //   2573: iastore
    //   2574: dup
    //   2575: bipush #25
    //   2577: ldc -1473132947
    //   2579: iastore
    //   2580: dup
    //   2581: bipush #26
    //   2583: ldc -1341970488
    //   2585: iastore
    //   2586: dup
    //   2587: bipush #27
    //   2589: ldc -1084653625
    //   2591: iastore
    //   2592: dup
    //   2593: bipush #28
    //   2595: ldc -958395405
    //   2597: iastore
    //   2598: dup
    //   2599: bipush #29
    //   2601: ldc -710438585
    //   2603: iastore
    //   2604: dup
    //   2605: bipush #30
    //   2607: ldc 113926993
    //   2609: iastore
    //   2610: dup
    //   2611: bipush #31
    //   2613: ldc 338241895
    //   2615: iastore
    //   2616: dup
    //   2617: bipush #32
    //   2619: ldc 666307205
    //   2621: iastore
    //   2622: dup
    //   2623: bipush #33
    //   2625: ldc 773529912
    //   2627: iastore
    //   2628: dup
    //   2629: bipush #34
    //   2631: ldc 1294757372
    //   2633: iastore
    //   2634: dup
    //   2635: bipush #35
    //   2637: ldc 1396182291
    //   2639: iastore
    //   2640: dup
    //   2641: bipush #36
    //   2643: ldc 1695183700
    //   2645: iastore
    //   2646: dup
    //   2647: bipush #37
    //   2649: ldc 1986661051
    //   2651: iastore
    //   2652: dup
    //   2653: bipush #38
    //   2655: ldc -2117940946
    //   2657: iastore
    //   2658: dup
    //   2659: bipush #39
    //   2661: ldc -1838011259
    //   2663: iastore
    //   2664: dup
    //   2665: bipush #40
    //   2667: ldc -1564481375
    //   2669: iastore
    //   2670: dup
    //   2671: bipush #41
    //   2673: ldc -1474664885
    //   2675: iastore
    //   2676: dup
    //   2677: bipush #42
    //   2679: ldc -1035236496
    //   2681: iastore
    //   2682: dup
    //   2683: bipush #43
    //   2685: ldc -949202525
    //   2687: iastore
    //   2688: dup
    //   2689: bipush #44
    //   2691: ldc -778901479
    //   2693: iastore
    //   2694: dup
    //   2695: bipush #45
    //   2697: ldc -694614492
    //   2699: iastore
    //   2700: dup
    //   2701: bipush #46
    //   2703: ldc -200395387
    //   2705: iastore
    //   2706: dup
    //   2707: bipush #47
    //   2709: ldc 275423344
    //   2711: iastore
    //   2712: dup
    //   2713: bipush #48
    //   2715: ldc 430227734
    //   2717: iastore
    //   2718: dup
    //   2719: bipush #49
    //   2721: ldc 506948616
    //   2723: iastore
    //   2724: dup
    //   2725: bipush #50
    //   2727: ldc 659060556
    //   2729: iastore
    //   2730: dup
    //   2731: bipush #51
    //   2733: ldc 883997877
    //   2735: iastore
    //   2736: dup
    //   2737: bipush #52
    //   2739: ldc 958139571
    //   2741: iastore
    //   2742: dup
    //   2743: bipush #53
    //   2745: ldc 1322822218
    //   2747: iastore
    //   2748: dup
    //   2749: bipush #54
    //   2751: ldc 1537002063
    //   2753: iastore
    //   2754: dup
    //   2755: bipush #55
    //   2757: ldc 1747873779
    //   2759: iastore
    //   2760: dup
    //   2761: bipush #56
    //   2763: ldc 1955562222
    //   2765: iastore
    //   2766: dup
    //   2767: bipush #57
    //   2769: ldc 2024104815
    //   2771: iastore
    //   2772: dup
    //   2773: bipush #58
    //   2775: ldc -2067236844
    //   2777: iastore
    //   2778: dup
    //   2779: bipush #59
    //   2781: ldc -1933114872
    //   2783: iastore
    //   2784: dup
    //   2785: bipush #60
    //   2787: ldc -1866530822
    //   2789: iastore
    //   2790: dup
    //   2791: bipush #61
    //   2793: ldc -1538233109
    //   2795: iastore
    //   2796: dup
    //   2797: bipush #62
    //   2799: ldc -1090935817
    //   2801: iastore
    //   2802: dup
    //   2803: bipush #63
    //   2805: ldc -965641998
    //   2807: iastore
    //   2808: astore #7
    //   2810: iconst_2
    //   2811: newarray int
    //   2813: dup
    //   2814: iconst_0
    //   2815: iconst_0
    //   2816: iastore
    //   2817: dup
    //   2818: iconst_1
    //   2819: iconst_0
    //   2820: iastore
    //   2821: astore #8
    //   2823: bipush #8
    //   2825: newarray int
    //   2827: dup
    //   2828: iconst_0
    //   2829: ldc 1779033703
    //   2831: iastore
    //   2832: dup
    //   2833: iconst_1
    //   2834: ldc -1150833019
    //   2836: iastore
    //   2837: dup
    //   2838: iconst_2
    //   2839: ldc 1013904242
    //   2841: iastore
    //   2842: dup
    //   2843: iconst_3
    //   2844: ldc -1521486534
    //   2846: iastore
    //   2847: dup
    //   2848: iconst_4
    //   2849: ldc 1359893119
    //   2851: iastore
    //   2852: dup
    //   2853: iconst_5
    //   2854: ldc -1694144372
    //   2856: iastore
    //   2857: dup
    //   2858: bipush #6
    //   2860: ldc 528734635
    //   2862: iastore
    //   2863: dup
    //   2864: bipush #7
    //   2866: ldc 1541459225
    //   2868: iastore
    //   2869: astore #9
    //   2871: bipush #64
    //   2873: newarray byte
    //   2875: astore #10
    //   2877: bipush #64
    //   2879: newarray byte
    //   2881: astore #11
    //   2883: aload #4
    //   2885: arraylength
    //   2886: istore #12
    //   2888: aload #8
    //   2890: iconst_0
    //   2891: iaload
    //   2892: bipush #63
    //   2894: iand
    //   2895: istore #13
    //   2897: aload #8
    //   2899: iconst_0
    //   2900: dup2
    //   2901: iaload
    //   2902: iload #12
    //   2904: iadd
    //   2905: iastore
    //   2906: aload #8
    //   2908: iconst_0
    //   2909: dup2
    //   2910: iaload
    //   2911: iconst_m1
    //   2912: iand
    //   2913: iastore
    //   2914: aload #8
    //   2916: iconst_0
    //   2917: iaload
    //   2918: iload #12
    //   2920: if_icmpge -> 2938
    //   2923: aload #8
    //   2925: iconst_1
    //   2926: dup2
    //   2927: iaload
    //   2928: iconst_1
    //   2929: iadd
    //   2930: iastore
    //   2931: goto -> 2938
    //   2934: invokestatic a : (Ljava/lang/Throwable;)Ljava/lang/Throwable;
    //   2937: athrow
    //   2938: iconst_0
    //   2939: istore #14
    //   2941: iload #12
    //   2943: bipush #64
    //   2945: if_icmplt -> 3555
    //   2948: iconst_0
    //   2949: istore #15
    //   2951: iload #15
    //   2953: bipush #64
    //   2955: if_icmpge -> 2978
    //   2958: aload #11
    //   2960: iload #15
    //   2962: aload #4
    //   2964: iload #14
    //   2966: iload #15
    //   2968: iadd
    //   2969: baload
    //   2970: bastore
    //   2971: iinc #15, 1
    //   2974: iload_2
    //   2975: ifne -> 2951
    //   2978: bipush #64
    //   2980: newarray int
    //   2982: astore #15
    //   2984: bipush #8
    //   2986: newarray int
    //   2988: astore #16
    //   2990: iconst_0
    //   2991: istore #17
    //   2993: iload #17
    //   2995: bipush #8
    //   2997: if_icmpge -> 3017
    //   3000: aload #16
    //   3002: iload #17
    //   3004: aload #9
    //   3006: iload #17
    //   3008: iaload
    //   3009: iastore
    //   3010: iinc #17, 1
    //   3013: iload_2
    //   3014: ifne -> 2993
    //   3017: iconst_0
    //   3018: istore #17
    //   3020: iload #17
    //   3022: bipush #64
    //   3024: if_icmpge -> 3515
    //   3027: iload #17
    //   3029: bipush #16
    //   3031: if_icmpge -> 3112
    //   3034: aload #15
    //   3036: iload #17
    //   3038: aload #11
    //   3040: iconst_4
    //   3041: iload #17
    //   3043: imul
    //   3044: baload
    //   3045: sipush #255
    //   3048: iand
    //   3049: bipush #24
    //   3051: ishl
    //   3052: aload #11
    //   3054: iconst_4
    //   3055: iload #17
    //   3057: imul
    //   3058: iconst_1
    //   3059: iadd
    //   3060: baload
    //   3061: sipush #255
    //   3064: iand
    //   3065: bipush #16
    //   3067: ishl
    //   3068: ior
    //   3069: aload #11
    //   3071: iconst_4
    //   3072: iload #17
    //   3074: imul
    //   3075: iconst_2
    //   3076: iadd
    //   3077: baload
    //   3078: sipush #255
    //   3081: iand
    //   3082: bipush #8
    //   3084: ishl
    //   3085: ior
    //   3086: aload #11
    //   3088: iconst_4
    //   3089: iload #17
    //   3091: imul
    //   3092: iconst_3
    //   3093: iadd
    //   3094: baload
    //   3095: sipush #255
    //   3098: iand
    //   3099: ior
    //   3100: iastore
    //   3101: iload_2
    //   3102: ifne -> 3255
    //   3105: goto -> 3112
    //   3108: invokestatic a : (Ljava/lang/Throwable;)Ljava/lang/Throwable;
    //   3111: athrow
    //   3112: aload #15
    //   3114: iload #17
    //   3116: aload #15
    //   3118: iload #17
    //   3120: iconst_2
    //   3121: isub
    //   3122: iaload
    //   3123: bipush #17
    //   3125: iushr
    //   3126: aload #15
    //   3128: iload #17
    //   3130: iconst_2
    //   3131: isub
    //   3132: iaload
    //   3133: bipush #15
    //   3135: ishl
    //   3136: ior
    //   3137: aload #15
    //   3139: iload #17
    //   3141: iconst_2
    //   3142: isub
    //   3143: iaload
    //   3144: bipush #19
    //   3146: iushr
    //   3147: aload #15
    //   3149: iload #17
    //   3151: iconst_2
    //   3152: isub
    //   3153: iaload
    //   3154: bipush #13
    //   3156: ishl
    //   3157: ior
    //   3158: ixor
    //   3159: aload #15
    //   3161: iload #17
    //   3163: iconst_2
    //   3164: isub
    //   3165: iaload
    //   3166: bipush #10
    //   3168: iushr
    //   3169: ixor
    //   3170: aload #15
    //   3172: iload #17
    //   3174: bipush #7
    //   3176: isub
    //   3177: iaload
    //   3178: iadd
    //   3179: aload #15
    //   3181: iload #17
    //   3183: bipush #15
    //   3185: isub
    //   3186: iaload
    //   3187: bipush #7
    //   3189: iushr
    //   3190: aload #15
    //   3192: iload #17
    //   3194: bipush #15
    //   3196: isub
    //   3197: iaload
    //   3198: bipush #25
    //   3200: ishl
    //   3201: ior
    //   3202: aload #15
    //   3204: iload #17
    //   3206: bipush #15
    //   3208: isub
    //   3209: iaload
    //   3210: bipush #18
    //   3212: iushr
    //   3213: aload #15
    //   3215: iload #17
    //   3217: bipush #15
    //   3219: isub
    //   3220: iaload
    //   3221: bipush #14
    //   3223: ishl
    //   3224: ior
    //   3225: ixor
    //   3226: aload #15
    //   3228: iload #17
    //   3230: bipush #15
    //   3232: isub
    //   3233: iaload
    //   3234: iconst_3
    //   3235: iushr
    //   3236: ixor
    //   3237: iadd
    //   3238: aload #15
    //   3240: iload #17
    //   3242: bipush #16
    //   3244: isub
    //   3245: iaload
    //   3246: iadd
    //   3247: iastore
    //   3248: goto -> 3255
    //   3251: invokestatic a : (Ljava/lang/Throwable;)Ljava/lang/Throwable;
    //   3254: athrow
    //   3255: aload #16
    //   3257: bipush #7
    //   3259: iaload
    //   3260: aload #16
    //   3262: iconst_4
    //   3263: iaload
    //   3264: bipush #6
    //   3266: iushr
    //   3267: aload #16
    //   3269: iconst_4
    //   3270: iaload
    //   3271: bipush #26
    //   3273: ishl
    //   3274: ior
    //   3275: aload #16
    //   3277: iconst_4
    //   3278: iaload
    //   3279: bipush #11
    //   3281: iushr
    //   3282: aload #16
    //   3284: iconst_4
    //   3285: iaload
    //   3286: bipush #21
    //   3288: ishl
    //   3289: ior
    //   3290: ixor
    //   3291: aload #16
    //   3293: iconst_4
    //   3294: iaload
    //   3295: bipush #25
    //   3297: iushr
    //   3298: aload #16
    //   3300: iconst_4
    //   3301: iaload
    //   3302: bipush #7
    //   3304: ishl
    //   3305: ior
    //   3306: ixor
    //   3307: iadd
    //   3308: aload #16
    //   3310: bipush #6
    //   3312: iaload
    //   3313: aload #16
    //   3315: iconst_4
    //   3316: iaload
    //   3317: aload #16
    //   3319: iconst_5
    //   3320: iaload
    //   3321: aload #16
    //   3323: bipush #6
    //   3325: iaload
    //   3326: ixor
    //   3327: iand
    //   3328: ixor
    //   3329: iadd
    //   3330: aload #7
    //   3332: iload #17
    //   3334: iaload
    //   3335: iadd
    //   3336: aload #15
    //   3338: iload #17
    //   3340: iaload
    //   3341: iadd
    //   3342: istore #18
    //   3344: aload #16
    //   3346: iconst_0
    //   3347: iaload
    //   3348: iconst_2
    //   3349: iushr
    //   3350: aload #16
    //   3352: iconst_0
    //   3353: iaload
    //   3354: bipush #30
    //   3356: ishl
    //   3357: ior
    //   3358: aload #16
    //   3360: iconst_0
    //   3361: iaload
    //   3362: bipush #13
    //   3364: iushr
    //   3365: aload #16
    //   3367: iconst_0
    //   3368: iaload
    //   3369: bipush #19
    //   3371: ishl
    //   3372: ior
    //   3373: ixor
    //   3374: aload #16
    //   3376: iconst_0
    //   3377: iaload
    //   3378: bipush #22
    //   3380: iushr
    //   3381: aload #16
    //   3383: iconst_0
    //   3384: iaload
    //   3385: bipush #10
    //   3387: ishl
    //   3388: ior
    //   3389: ixor
    //   3390: aload #16
    //   3392: iconst_0
    //   3393: iaload
    //   3394: aload #16
    //   3396: iconst_1
    //   3397: iaload
    //   3398: iand
    //   3399: aload #16
    //   3401: iconst_2
    //   3402: iaload
    //   3403: aload #16
    //   3405: iconst_0
    //   3406: iaload
    //   3407: aload #16
    //   3409: iconst_1
    //   3410: iaload
    //   3411: ior
    //   3412: iand
    //   3413: ior
    //   3414: iadd
    //   3415: istore #19
    //   3417: aload #16
    //   3419: iconst_3
    //   3420: dup2
    //   3421: iaload
    //   3422: iload #18
    //   3424: iadd
    //   3425: iastore
    //   3426: aload #16
    //   3428: bipush #7
    //   3430: iload #18
    //   3432: iload #19
    //   3434: iadd
    //   3435: iastore
    //   3436: aload #16
    //   3438: bipush #7
    //   3440: iaload
    //   3441: istore #18
    //   3443: aload #16
    //   3445: bipush #7
    //   3447: aload #16
    //   3449: bipush #6
    //   3451: iaload
    //   3452: iastore
    //   3453: aload #16
    //   3455: bipush #6
    //   3457: aload #16
    //   3459: iconst_5
    //   3460: iaload
    //   3461: iastore
    //   3462: aload #16
    //   3464: iconst_5
    //   3465: aload #16
    //   3467: iconst_4
    //   3468: iaload
    //   3469: iastore
    //   3470: aload #16
    //   3472: iconst_4
    //   3473: aload #16
    //   3475: iconst_3
    //   3476: iaload
    //   3477: iastore
    //   3478: aload #16
    //   3480: iconst_3
    //   3481: aload #16
    //   3483: iconst_2
    //   3484: iaload
    //   3485: iastore
    //   3486: aload #16
    //   3488: iconst_2
    //   3489: aload #16
    //   3491: iconst_1
    //   3492: iaload
    //   3493: iastore
    //   3494: aload #16
    //   3496: iconst_1
    //   3497: aload #16
    //   3499: iconst_0
    //   3500: iaload
    //   3501: iastore
    //   3502: aload #16
    //   3504: iconst_0
    //   3505: iload #18
    //   3507: iastore
    //   3508: iinc #17, 1
    //   3511: iload_2
    //   3512: ifne -> 3020
    //   3515: iconst_0
    //   3516: istore #17
    //   3518: iload #17
    //   3520: bipush #8
    //   3522: if_icmpge -> 3545
    //   3525: aload #9
    //   3527: iload #17
    //   3529: dup2
    //   3530: iaload
    //   3531: aload #16
    //   3533: iload #17
    //   3535: iaload
    //   3536: iadd
    //   3537: iastore
    //   3538: iinc #17, 1
    //   3541: iload_2
    //   3542: ifne -> 3518
    //   3545: iinc #14, 64
    //   3548: iinc #12, -64
    //   3551: iload_2
    //   3552: ifne -> 2941
    //   3555: iload #12
    //   3557: ifle -> 3593
    //   3560: iconst_0
    //   3561: istore #15
    //   3563: iload #15
    //   3565: iload #12
    //   3567: if_icmpge -> 3593
    //   3570: aload #10
    //   3572: iload #13
    //   3574: iload #15
    //   3576: iadd
    //   3577: aload #4
    //   3579: iload #14
    //   3581: iload #15
    //   3583: iadd
    //   3584: baload
    //   3585: bastore
    //   3586: iinc #15, 1
    //   3589: iload_2
    //   3590: ifne -> 3563
    //   3593: aload #8
    //   3595: iconst_0
    //   3596: iaload
    //   3597: bipush #29
    //   3599: iushr
    //   3600: aload #8
    //   3602: iconst_1
    //   3603: iaload
    //   3604: iconst_3
    //   3605: ishl
    //   3606: ior
    //   3607: istore #15
    //   3609: aload #8
    //   3611: iconst_0
    //   3612: iaload
    //   3613: iconst_3
    //   3614: ishl
    //   3615: istore #16
    //   3617: aload #8
    //   3619: iconst_0
    //   3620: iaload
    //   3621: bipush #63
    //   3623: iand
    //   3624: istore #17
    //   3626: iload #17
    //   3628: bipush #56
    //   3630: if_icmpge -> 3645
    //   3633: bipush #56
    //   3635: iload #17
    //   3637: isub
    //   3638: goto -> 3650
    //   3641: invokestatic a : (Ljava/lang/Throwable;)Ljava/lang/Throwable;
    //   3644: athrow
    //   3645: bipush #120
    //   3647: iload #17
    //   3649: isub
    //   3650: istore #18
    //   3652: aload #8
    //   3654: iconst_0
    //   3655: iaload
    //   3656: bipush #63
    //   3658: iand
    //   3659: istore #13
    //   3661: bipush #64
    //   3663: iload #13
    //   3665: isub
    //   3666: istore #19
    //   3668: aload #8
    //   3670: iconst_0
    //   3671: dup2
    //   3672: iaload
    //   3673: iload #18
    //   3675: iadd
    //   3676: iastore
    //   3677: aload #8
    //   3679: iconst_0
    //   3680: dup2
    //   3681: iaload
    //   3682: iconst_m1
    //   3683: iand
    //   3684: iastore
    //   3685: aload #8
    //   3687: iconst_0
    //   3688: iaload
    //   3689: iload #18
    //   3691: if_icmpge -> 3709
    //   3694: aload #8
    //   3696: iconst_1
    //   3697: dup2
    //   3698: iaload
    //   3699: iconst_1
    //   3700: iadd
    //   3701: iastore
    //   3702: goto -> 3709
    //   3705: invokestatic a : (Ljava/lang/Throwable;)Ljava/lang/Throwable;
    //   3708: athrow
    //   3709: iconst_0
    //   3710: istore #14
    //   3712: iload #13
    //   3714: ifle -> 4345
    //   3717: iload #18
    //   3719: iload #19
    //   3721: if_icmplt -> 4345
    //   3724: goto -> 3731
    //   3727: invokestatic a : (Ljava/lang/Throwable;)Ljava/lang/Throwable;
    //   3730: athrow
    //   3731: iconst_0
    //   3732: istore #20
    //   3734: iload #20
    //   3736: iload #19
    //   3738: if_icmpge -> 3761
    //   3741: aload #10
    //   3743: iload #13
    //   3745: iload #20
    //   3747: iadd
    //   3748: aload #6
    //   3750: iload #20
    //   3752: baload
    //   3753: bastore
    //   3754: iinc #20, 1
    //   3757: iload_2
    //   3758: ifne -> 3734
    //   3761: bipush #64
    //   3763: newarray int
    //   3765: astore #20
    //   3767: bipush #8
    //   3769: newarray int
    //   3771: astore #21
    //   3773: iconst_0
    //   3774: istore #22
    //   3776: iload #22
    //   3778: bipush #8
    //   3780: if_icmpge -> 3800
    //   3783: aload #21
    //   3785: iload #22
    //   3787: aload #9
    //   3789: iload #22
    //   3791: iaload
    //   3792: iastore
    //   3793: iinc #22, 1
    //   3796: iload_2
    //   3797: ifne -> 3776
    //   3800: iconst_0
    //   3801: istore #22
    //   3803: iload #22
    //   3805: bipush #64
    //   3807: if_icmpge -> 4298
    //   3810: iload #22
    //   3812: bipush #16
    //   3814: if_icmpge -> 3895
    //   3817: aload #20
    //   3819: iload #22
    //   3821: aload #10
    //   3823: iconst_4
    //   3824: iload #22
    //   3826: imul
    //   3827: baload
    //   3828: sipush #255
    //   3831: iand
    //   3832: bipush #24
    //   3834: ishl
    //   3835: aload #10
    //   3837: iconst_4
    //   3838: iload #22
    //   3840: imul
    //   3841: iconst_1
    //   3842: iadd
    //   3843: baload
    //   3844: sipush #255
    //   3847: iand
    //   3848: bipush #16
    //   3850: ishl
    //   3851: ior
    //   3852: aload #10
    //   3854: iconst_4
    //   3855: iload #22
    //   3857: imul
    //   3858: iconst_2
    //   3859: iadd
    //   3860: baload
    //   3861: sipush #255
    //   3864: iand
    //   3865: bipush #8
    //   3867: ishl
    //   3868: ior
    //   3869: aload #10
    //   3871: iconst_4
    //   3872: iload #22
    //   3874: imul
    //   3875: iconst_3
    //   3876: iadd
    //   3877: baload
    //   3878: sipush #255
    //   3881: iand
    //   3882: ior
    //   3883: iastore
    //   3884: iload_2
    //   3885: ifne -> 4038
    //   3888: goto -> 3895
    //   3891: invokestatic a : (Ljava/lang/Throwable;)Ljava/lang/Throwable;
    //   3894: athrow
    //   3895: aload #20
    //   3897: iload #22
    //   3899: aload #20
    //   3901: iload #22
    //   3903: iconst_2
    //   3904: isub
    //   3905: iaload
    //   3906: bipush #17
    //   3908: iushr
    //   3909: aload #20
    //   3911: iload #22
    //   3913: iconst_2
    //   3914: isub
    //   3915: iaload
    //   3916: bipush #15
    //   3918: ishl
    //   3919: ior
    //   3920: aload #20
    //   3922: iload #22
    //   3924: iconst_2
    //   3925: isub
    //   3926: iaload
    //   3927: bipush #19
    //   3929: iushr
    //   3930: aload #20
    //   3932: iload #22
    //   3934: iconst_2
    //   3935: isub
    //   3936: iaload
    //   3937: bipush #13
    //   3939: ishl
    //   3940: ior
    //   3941: ixor
    //   3942: aload #20
    //   3944: iload #22
    //   3946: iconst_2
    //   3947: isub
    //   3948: iaload
    //   3949: bipush #10
    //   3951: iushr
    //   3952: ixor
    //   3953: aload #20
    //   3955: iload #22
    //   3957: bipush #7
    //   3959: isub
    //   3960: iaload
    //   3961: iadd
    //   3962: aload #20
    //   3964: iload #22
    //   3966: bipush #15
    //   3968: isub
    //   3969: iaload
    //   3970: bipush #7
    //   3972: iushr
    //   3973: aload #20
    //   3975: iload #22
    //   3977: bipush #15
    //   3979: isub
    //   3980: iaload
    //   3981: bipush #25
    //   3983: ishl
    //   3984: ior
    //   3985: aload #20
    //   3987: iload #22
    //   3989: bipush #15
    //   3991: isub
    //   3992: iaload
    //   3993: bipush #18
    //   3995: iushr
    //   3996: aload #20
    //   3998: iload #22
    //   4000: bipush #15
    //   4002: isub
    //   4003: iaload
    //   4004: bipush #14
    //   4006: ishl
    //   4007: ior
    //   4008: ixor
    //   4009: aload #20
    //   4011: iload #22
    //   4013: bipush #15
    //   4015: isub
    //   4016: iaload
    //   4017: iconst_3
    //   4018: iushr
    //   4019: ixor
    //   4020: iadd
    //   4021: aload #20
    //   4023: iload #22
    //   4025: bipush #16
    //   4027: isub
    //   4028: iaload
    //   4029: iadd
    //   4030: iastore
    //   4031: goto -> 4038
    //   4034: invokestatic a : (Ljava/lang/Throwable;)Ljava/lang/Throwable;
    //   4037: athrow
    //   4038: aload #21
    //   4040: bipush #7
    //   4042: iaload
    //   4043: aload #21
    //   4045: iconst_4
    //   4046: iaload
    //   4047: bipush #6
    //   4049: iushr
    //   4050: aload #21
    //   4052: iconst_4
    //   4053: iaload
    //   4054: bipush #26
    //   4056: ishl
    //   4057: ior
    //   4058: aload #21
    //   4060: iconst_4
    //   4061: iaload
    //   4062: bipush #11
    //   4064: iushr
    //   4065: aload #21
    //   4067: iconst_4
    //   4068: iaload
    //   4069: bipush #21
    //   4071: ishl
    //   4072: ior
    //   4073: ixor
    //   4074: aload #21
    //   4076: iconst_4
    //   4077: iaload
    //   4078: bipush #25
    //   4080: iushr
    //   4081: aload #21
    //   4083: iconst_4
    //   4084: iaload
    //   4085: bipush #7
    //   4087: ishl
    //   4088: ior
    //   4089: ixor
    //   4090: iadd
    //   4091: aload #21
    //   4093: bipush #6
    //   4095: iaload
    //   4096: aload #21
    //   4098: iconst_4
    //   4099: iaload
    //   4100: aload #21
    //   4102: iconst_5
    //   4103: iaload
    //   4104: aload #21
    //   4106: bipush #6
    //   4108: iaload
    //   4109: ixor
    //   4110: iand
    //   4111: ixor
    //   4112: iadd
    //   4113: aload #7
    //   4115: iload #22
    //   4117: iaload
    //   4118: iadd
    //   4119: aload #20
    //   4121: iload #22
    //   4123: iaload
    //   4124: iadd
    //   4125: istore #23
    //   4127: aload #21
    //   4129: iconst_0
    //   4130: iaload
    //   4131: iconst_2
    //   4132: iushr
    //   4133: aload #21
    //   4135: iconst_0
    //   4136: iaload
    //   4137: bipush #30
    //   4139: ishl
    //   4140: ior
    //   4141: aload #21
    //   4143: iconst_0
    //   4144: iaload
    //   4145: bipush #13
    //   4147: iushr
    //   4148: aload #21
    //   4150: iconst_0
    //   4151: iaload
    //   4152: bipush #19
    //   4154: ishl
    //   4155: ior
    //   4156: ixor
    //   4157: aload #21
    //   4159: iconst_0
    //   4160: iaload
    //   4161: bipush #22
    //   4163: iushr
    //   4164: aload #21
    //   4166: iconst_0
    //   4167: iaload
    //   4168: bipush #10
    //   4170: ishl
    //   4171: ior
    //   4172: ixor
    //   4173: aload #21
    //   4175: iconst_0
    //   4176: iaload
    //   4177: aload #21
    //   4179: iconst_1
    //   4180: iaload
    //   4181: iand
    //   4182: aload #21
    //   4184: iconst_2
    //   4185: iaload
    //   4186: aload #21
    //   4188: iconst_0
    //   4189: iaload
    //   4190: aload #21
    //   4192: iconst_1
    //   4193: iaload
    //   4194: ior
    //   4195: iand
    //   4196: ior
    //   4197: iadd
    //   4198: istore #24
    //   4200: aload #21
    //   4202: iconst_3
    //   4203: dup2
    //   4204: iaload
    //   4205: iload #23
    //   4207: iadd
    //   4208: iastore
    //   4209: aload #21
    //   4211: bipush #7
    //   4213: iload #23
    //   4215: iload #24
    //   4217: iadd
    //   4218: iastore
    //   4219: aload #21
    //   4221: bipush #7
    //   4223: iaload
    //   4224: istore #23
    //   4226: aload #21
    //   4228: bipush #7
    //   4230: aload #21
    //   4232: bipush #6
    //   4234: iaload
    //   4235: iastore
    //   4236: aload #21
    //   4238: bipush #6
    //   4240: aload #21
    //   4242: iconst_5
    //   4243: iaload
    //   4244: iastore
    //   4245: aload #21
    //   4247: iconst_5
    //   4248: aload #21
    //   4250: iconst_4
    //   4251: iaload
    //   4252: iastore
    //   4253: aload #21
    //   4255: iconst_4
    //   4256: aload #21
    //   4258: iconst_3
    //   4259: iaload
    //   4260: iastore
    //   4261: aload #21
    //   4263: iconst_3
    //   4264: aload #21
    //   4266: iconst_2
    //   4267: iaload
    //   4268: iastore
    //   4269: aload #21
    //   4271: iconst_2
    //   4272: aload #21
    //   4274: iconst_1
    //   4275: iaload
    //   4276: iastore
    //   4277: aload #21
    //   4279: iconst_1
    //   4280: aload #21
    //   4282: iconst_0
    //   4283: iaload
    //   4284: iastore
    //   4285: aload #21
    //   4287: iconst_0
    //   4288: iload #23
    //   4290: iastore
    //   4291: iinc #22, 1
    //   4294: iload_2
    //   4295: ifne -> 3803
    //   4298: iconst_0
    //   4299: istore #22
    //   4301: iload #22
    //   4303: bipush #8
    //   4305: if_icmpge -> 4328
    //   4308: aload #9
    //   4310: iload #22
    //   4312: dup2
    //   4313: iaload
    //   4314: aload #21
    //   4316: iload #22
    //   4318: iaload
    //   4319: iadd
    //   4320: iastore
    //   4321: iinc #22, 1
    //   4324: iload_2
    //   4325: ifne -> 4301
    //   4328: iload #14
    //   4330: iload #19
    //   4332: iadd
    //   4333: istore #14
    //   4335: iload #18
    //   4337: iload #19
    //   4339: isub
    //   4340: istore #18
    //   4342: iconst_0
    //   4343: istore #13
    //   4345: iload #18
    //   4347: bipush #64
    //   4349: if_icmplt -> 4959
    //   4352: iconst_0
    //   4353: istore #20
    //   4355: iload #20
    //   4357: bipush #64
    //   4359: if_icmpge -> 4382
    //   4362: aload #11
    //   4364: iload #20
    //   4366: aload #6
    //   4368: iload #14
    //   4370: iload #20
    //   4372: iadd
    //   4373: baload
    //   4374: bastore
    //   4375: iinc #20, 1
    //   4378: iload_2
    //   4379: ifne -> 4355
    //   4382: bipush #64
    //   4384: newarray int
    //   4386: astore #20
    //   4388: bipush #8
    //   4390: newarray int
    //   4392: astore #21
    //   4394: iconst_0
    //   4395: istore #22
    //   4397: iload #22
    //   4399: bipush #8
    //   4401: if_icmpge -> 4421
    //   4404: aload #21
    //   4406: iload #22
    //   4408: aload #9
    //   4410: iload #22
    //   4412: iaload
    //   4413: iastore
    //   4414: iinc #22, 1
    //   4417: iload_2
    //   4418: ifne -> 4397
    //   4421: iconst_0
    //   4422: istore #22
    //   4424: iload #22
    //   4426: bipush #64
    //   4428: if_icmpge -> 4919
    //   4431: iload #22
    //   4433: bipush #16
    //   4435: if_icmpge -> 4516
    //   4438: aload #20
    //   4440: iload #22
    //   4442: aload #11
    //   4444: iconst_4
    //   4445: iload #22
    //   4447: imul
    //   4448: baload
    //   4449: sipush #255
    //   4452: iand
    //   4453: bipush #24
    //   4455: ishl
    //   4456: aload #11
    //   4458: iconst_4
    //   4459: iload #22
    //   4461: imul
    //   4462: iconst_1
    //   4463: iadd
    //   4464: baload
    //   4465: sipush #255
    //   4468: iand
    //   4469: bipush #16
    //   4471: ishl
    //   4472: ior
    //   4473: aload #11
    //   4475: iconst_4
    //   4476: iload #22
    //   4478: imul
    //   4479: iconst_2
    //   4480: iadd
    //   4481: baload
    //   4482: sipush #255
    //   4485: iand
    //   4486: bipush #8
    //   4488: ishl
    //   4489: ior
    //   4490: aload #11
    //   4492: iconst_4
    //   4493: iload #22
    //   4495: imul
    //   4496: iconst_3
    //   4497: iadd
    //   4498: baload
    //   4499: sipush #255
    //   4502: iand
    //   4503: ior
    //   4504: iastore
    //   4505: iload_2
    //   4506: ifne -> 4659
    //   4509: goto -> 4516
    //   4512: invokestatic a : (Ljava/lang/Throwable;)Ljava/lang/Throwable;
    //   4515: athrow
    //   4516: aload #20
    //   4518: iload #22
    //   4520: aload #20
    //   4522: iload #22
    //   4524: iconst_2
    //   4525: isub
    //   4526: iaload
    //   4527: bipush #17
    //   4529: iushr
    //   4530: aload #20
    //   4532: iload #22
    //   4534: iconst_2
    //   4535: isub
    //   4536: iaload
    //   4537: bipush #15
    //   4539: ishl
    //   4540: ior
    //   4541: aload #20
    //   4543: iload #22
    //   4545: iconst_2
    //   4546: isub
    //   4547: iaload
    //   4548: bipush #19
    //   4550: iushr
    //   4551: aload #20
    //   4553: iload #22
    //   4555: iconst_2
    //   4556: isub
    //   4557: iaload
    //   4558: bipush #13
    //   4560: ishl
    //   4561: ior
    //   4562: ixor
    //   4563: aload #20
    //   4565: iload #22
    //   4567: iconst_2
    //   4568: isub
    //   4569: iaload
    //   4570: bipush #10
    //   4572: iushr
    //   4573: ixor
    //   4574: aload #20
    //   4576: iload #22
    //   4578: bipush #7
    //   4580: isub
    //   4581: iaload
    //   4582: iadd
    //   4583: aload #20
    //   4585: iload #22
    //   4587: bipush #15
    //   4589: isub
    //   4590: iaload
    //   4591: bipush #7
    //   4593: iushr
    //   4594: aload #20
    //   4596: iload #22
    //   4598: bipush #15
    //   4600: isub
    //   4601: iaload
    //   4602: bipush #25
    //   4604: ishl
    //   4605: ior
    //   4606: aload #20
    //   4608: iload #22
    //   4610: bipush #15
    //   4612: isub
    //   4613: iaload
    //   4614: bipush #18
    //   4616: iushr
    //   4617: aload #20
    //   4619: iload #22
    //   4621: bipush #15
    //   4623: isub
    //   4624: iaload
    //   4625: bipush #14
    //   4627: ishl
    //   4628: ior
    //   4629: ixor
    //   4630: aload #20
    //   4632: iload #22
    //   4634: bipush #15
    //   4636: isub
    //   4637: iaload
    //   4638: iconst_3
    //   4639: iushr
    //   4640: ixor
    //   4641: iadd
    //   4642: aload #20
    //   4644: iload #22
    //   4646: bipush #16
    //   4648: isub
    //   4649: iaload
    //   4650: iadd
    //   4651: iastore
    //   4652: goto -> 4659
    //   4655: invokestatic a : (Ljava/lang/Throwable;)Ljava/lang/Throwable;
    //   4658: athrow
    //   4659: aload #21
    //   4661: bipush #7
    //   4663: iaload
    //   4664: aload #21
    //   4666: iconst_4
    //   4667: iaload
    //   4668: bipush #6
    //   4670: iushr
    //   4671: aload #21
    //   4673: iconst_4
    //   4674: iaload
    //   4675: bipush #26
    //   4677: ishl
    //   4678: ior
    //   4679: aload #21
    //   4681: iconst_4
    //   4682: iaload
    //   4683: bipush #11
    //   4685: iushr
    //   4686: aload #21
    //   4688: iconst_4
    //   4689: iaload
    //   4690: bipush #21
    //   4692: ishl
    //   4693: ior
    //   4694: ixor
    //   4695: aload #21
    //   4697: iconst_4
    //   4698: iaload
    //   4699: bipush #25
    //   4701: iushr
    //   4702: aload #21
    //   4704: iconst_4
    //   4705: iaload
    //   4706: bipush #7
    //   4708: ishl
    //   4709: ior
    //   4710: ixor
    //   4711: iadd
    //   4712: aload #21
    //   4714: bipush #6
    //   4716: iaload
    //   4717: aload #21
    //   4719: iconst_4
    //   4720: iaload
    //   4721: aload #21
    //   4723: iconst_5
    //   4724: iaload
    //   4725: aload #21
    //   4727: bipush #6
    //   4729: iaload
    //   4730: ixor
    //   4731: iand
    //   4732: ixor
    //   4733: iadd
    //   4734: aload #7
    //   4736: iload #22
    //   4738: iaload
    //   4739: iadd
    //   4740: aload #20
    //   4742: iload #22
    //   4744: iaload
    //   4745: iadd
    //   4746: istore #23
    //   4748: aload #21
    //   4750: iconst_0
    //   4751: iaload
    //   4752: iconst_2
    //   4753: iushr
    //   4754: aload #21
    //   4756: iconst_0
    //   4757: iaload
    //   4758: bipush #30
    //   4760: ishl
    //   4761: ior
    //   4762: aload #21
    //   4764: iconst_0
    //   4765: iaload
    //   4766: bipush #13
    //   4768: iushr
    //   4769: aload #21
    //   4771: iconst_0
    //   4772: iaload
    //   4773: bipush #19
    //   4775: ishl
    //   4776: ior
    //   4777: ixor
    //   4778: aload #21
    //   4780: iconst_0
    //   4781: iaload
    //   4782: bipush #22
    //   4784: iushr
    //   4785: aload #21
    //   4787: iconst_0
    //   4788: iaload
    //   4789: bipush #10
    //   4791: ishl
    //   4792: ior
    //   4793: ixor
    //   4794: aload #21
    //   4796: iconst_0
    //   4797: iaload
    //   4798: aload #21
    //   4800: iconst_1
    //   4801: iaload
    //   4802: iand
    //   4803: aload #21
    //   4805: iconst_2
    //   4806: iaload
    //   4807: aload #21
    //   4809: iconst_0
    //   4810: iaload
    //   4811: aload #21
    //   4813: iconst_1
    //   4814: iaload
    //   4815: ior
    //   4816: iand
    //   4817: ior
    //   4818: iadd
    //   4819: istore #24
    //   4821: aload #21
    //   4823: iconst_3
    //   4824: dup2
    //   4825: iaload
    //   4826: iload #23
    //   4828: iadd
    //   4829: iastore
    //   4830: aload #21
    //   4832: bipush #7
    //   4834: iload #23
    //   4836: iload #24
    //   4838: iadd
    //   4839: iastore
    //   4840: aload #21
    //   4842: bipush #7
    //   4844: iaload
    //   4845: istore #23
    //   4847: aload #21
    //   4849: bipush #7
    //   4851: aload #21
    //   4853: bipush #6
    //   4855: iaload
    //   4856: iastore
    //   4857: aload #21
    //   4859: bipush #6
    //   4861: aload #21
    //   4863: iconst_5
    //   4864: iaload
    //   4865: iastore
    //   4866: aload #21
    //   4868: iconst_5
    //   4869: aload #21
    //   4871: iconst_4
    //   4872: iaload
    //   4873: iastore
    //   4874: aload #21
    //   4876: iconst_4
    //   4877: aload #21
    //   4879: iconst_3
    //   4880: iaload
    //   4881: iastore
    //   4882: aload #21
    //   4884: iconst_3
    //   4885: aload #21
    //   4887: iconst_2
    //   4888: iaload
    //   4889: iastore
    //   4890: aload #21
    //   4892: iconst_2
    //   4893: aload #21
    //   4895: iconst_1
    //   4896: iaload
    //   4897: iastore
    //   4898: aload #21
    //   4900: iconst_1
    //   4901: aload #21
    //   4903: iconst_0
    //   4904: iaload
    //   4905: iastore
    //   4906: aload #21
    //   4908: iconst_0
    //   4909: iload #23
    //   4911: iastore
    //   4912: iinc #22, 1
    //   4915: iload_2
    //   4916: ifne -> 4424
    //   4919: iconst_0
    //   4920: istore #22
    //   4922: iload #22
    //   4924: bipush #8
    //   4926: if_icmpge -> 4949
    //   4929: aload #9
    //   4931: iload #22
    //   4933: dup2
    //   4934: iaload
    //   4935: aload #21
    //   4937: iload #22
    //   4939: iaload
    //   4940: iadd
    //   4941: iastore
    //   4942: iinc #22, 1
    //   4945: iload_2
    //   4946: ifne -> 4922
    //   4949: iinc #14, 64
    //   4952: iinc #18, -64
    //   4955: iload_2
    //   4956: ifne -> 4345
    //   4959: iload #18
    //   4961: ifle -> 4997
    //   4964: iconst_0
    //   4965: istore #20
    //   4967: iload #20
    //   4969: iload #18
    //   4971: if_icmpge -> 4997
    //   4974: aload #10
    //   4976: iload #13
    //   4978: iload #20
    //   4980: iadd
    //   4981: aload #6
    //   4983: iload #14
    //   4985: iload #20
    //   4987: iadd
    //   4988: baload
    //   4989: bastore
    //   4990: iinc #20, 1
    //   4993: iload_2
    //   4994: ifne -> 4967
    //   4997: bipush #8
    //   4999: newarray byte
    //   5001: astore #20
    //   5003: aload #20
    //   5005: iconst_0
    //   5006: iload #15
    //   5008: bipush #24
    //   5010: iushr
    //   5011: i2b
    //   5012: bastore
    //   5013: aload #20
    //   5015: iconst_1
    //   5016: iload #15
    //   5018: bipush #16
    //   5020: iushr
    //   5021: i2b
    //   5022: bastore
    //   5023: aload #20
    //   5025: iconst_2
    //   5026: iload #15
    //   5028: bipush #8
    //   5030: iushr
    //   5031: i2b
    //   5032: bastore
    //   5033: aload #20
    //   5035: iconst_3
    //   5036: iload #15
    //   5038: i2b
    //   5039: bastore
    //   5040: aload #20
    //   5042: iconst_4
    //   5043: iload #16
    //   5045: bipush #24
    //   5047: iushr
    //   5048: i2b
    //   5049: bastore
    //   5050: aload #20
    //   5052: iconst_5
    //   5053: iload #16
    //   5055: bipush #16
    //   5057: iushr
    //   5058: i2b
    //   5059: bastore
    //   5060: aload #20
    //   5062: bipush #6
    //   5064: iload #16
    //   5066: bipush #8
    //   5068: iushr
    //   5069: i2b
    //   5070: bastore
    //   5071: aload #20
    //   5073: bipush #7
    //   5075: iload #16
    //   5077: i2b
    //   5078: bastore
    //   5079: bipush #8
    //   5081: istore #12
    //   5083: aload #8
    //   5085: iconst_0
    //   5086: iaload
    //   5087: bipush #63
    //   5089: iand
    //   5090: istore #13
    //   5092: bipush #64
    //   5094: iload #13
    //   5096: isub
    //   5097: istore #19
    //   5099: aload #8
    //   5101: iconst_0
    //   5102: dup2
    //   5103: iaload
    //   5104: iload #12
    //   5106: iadd
    //   5107: iastore
    //   5108: aload #8
    //   5110: iconst_0
    //   5111: dup2
    //   5112: iaload
    //   5113: iconst_m1
    //   5114: iand
    //   5115: iastore
    //   5116: aload #8
    //   5118: iconst_0
    //   5119: iaload
    //   5120: iload #12
    //   5122: if_icmpge -> 5140
    //   5125: aload #8
    //   5127: iconst_1
    //   5128: dup2
    //   5129: iaload
    //   5130: iconst_1
    //   5131: iadd
    //   5132: iastore
    //   5133: goto -> 5140
    //   5136: invokestatic a : (Ljava/lang/Throwable;)Ljava/lang/Throwable;
    //   5139: athrow
    //   5140: iload #13
    //   5142: ifle -> 5756
    //   5145: iload #12
    //   5147: iload #19
    //   5149: if_icmplt -> 5756
    //   5152: goto -> 5159
    //   5155: invokestatic a : (Ljava/lang/Throwable;)Ljava/lang/Throwable;
    //   5158: athrow
    //   5159: iconst_0
    //   5160: istore #21
    //   5162: iload #21
    //   5164: iload #19
    //   5166: if_icmpge -> 5189
    //   5169: aload #10
    //   5171: iload #13
    //   5173: iload #21
    //   5175: iadd
    //   5176: aload #20
    //   5178: iload #21
    //   5180: baload
    //   5181: bastore
    //   5182: iinc #21, 1
    //   5185: iload_2
    //   5186: ifne -> 5162
    //   5189: bipush #64
    //   5191: newarray int
    //   5193: astore #21
    //   5195: bipush #8
    //   5197: newarray int
    //   5199: astore #22
    //   5201: iconst_0
    //   5202: istore #23
    //   5204: iload #23
    //   5206: bipush #8
    //   5208: if_icmpge -> 5228
    //   5211: aload #22
    //   5213: iload #23
    //   5215: aload #9
    //   5217: iload #23
    //   5219: iaload
    //   5220: iastore
    //   5221: iinc #23, 1
    //   5224: iload_2
    //   5225: ifne -> 5204
    //   5228: iconst_0
    //   5229: istore #23
    //   5231: iload #23
    //   5233: bipush #64
    //   5235: if_icmpge -> 5726
    //   5238: iload #23
    //   5240: bipush #16
    //   5242: if_icmpge -> 5323
    //   5245: aload #21
    //   5247: iload #23
    //   5249: aload #10
    //   5251: iconst_4
    //   5252: iload #23
    //   5254: imul
    //   5255: baload
    //   5256: sipush #255
    //   5259: iand
    //   5260: bipush #24
    //   5262: ishl
    //   5263: aload #10
    //   5265: iconst_4
    //   5266: iload #23
    //   5268: imul
    //   5269: iconst_1
    //   5270: iadd
    //   5271: baload
    //   5272: sipush #255
    //   5275: iand
    //   5276: bipush #16
    //   5278: ishl
    //   5279: ior
    //   5280: aload #10
    //   5282: iconst_4
    //   5283: iload #23
    //   5285: imul
    //   5286: iconst_2
    //   5287: iadd
    //   5288: baload
    //   5289: sipush #255
    //   5292: iand
    //   5293: bipush #8
    //   5295: ishl
    //   5296: ior
    //   5297: aload #10
    //   5299: iconst_4
    //   5300: iload #23
    //   5302: imul
    //   5303: iconst_3
    //   5304: iadd
    //   5305: baload
    //   5306: sipush #255
    //   5309: iand
    //   5310: ior
    //   5311: iastore
    //   5312: iload_2
    //   5313: ifne -> 5466
    //   5316: goto -> 5323
    //   5319: invokestatic a : (Ljava/lang/Throwable;)Ljava/lang/Throwable;
    //   5322: athrow
    //   5323: aload #21
    //   5325: iload #23
    //   5327: aload #21
    //   5329: iload #23
    //   5331: iconst_2
    //   5332: isub
    //   5333: iaload
    //   5334: bipush #17
    //   5336: iushr
    //   5337: aload #21
    //   5339: iload #23
    //   5341: iconst_2
    //   5342: isub
    //   5343: iaload
    //   5344: bipush #15
    //   5346: ishl
    //   5347: ior
    //   5348: aload #21
    //   5350: iload #23
    //   5352: iconst_2
    //   5353: isub
    //   5354: iaload
    //   5355: bipush #19
    //   5357: iushr
    //   5358: aload #21
    //   5360: iload #23
    //   5362: iconst_2
    //   5363: isub
    //   5364: iaload
    //   5365: bipush #13
    //   5367: ishl
    //   5368: ior
    //   5369: ixor
    //   5370: aload #21
    //   5372: iload #23
    //   5374: iconst_2
    //   5375: isub
    //   5376: iaload
    //   5377: bipush #10
    //   5379: iushr
    //   5380: ixor
    //   5381: aload #21
    //   5383: iload #23
    //   5385: bipush #7
    //   5387: isub
    //   5388: iaload
    //   5389: iadd
    //   5390: aload #21
    //   5392: iload #23
    //   5394: bipush #15
    //   5396: isub
    //   5397: iaload
    //   5398: bipush #7
    //   5400: iushr
    //   5401: aload #21
    //   5403: iload #23
    //   5405: bipush #15
    //   5407: isub
    //   5408: iaload
    //   5409: bipush #25
    //   5411: ishl
    //   5412: ior
    //   5413: aload #21
    //   5415: iload #23
    //   5417: bipush #15
    //   5419: isub
    //   5420: iaload
    //   5421: bipush #18
    //   5423: iushr
    //   5424: aload #21
    //   5426: iload #23
    //   5428: bipush #15
    //   5430: isub
    //   5431: iaload
    //   5432: bipush #14
    //   5434: ishl
    //   5435: ior
    //   5436: ixor
    //   5437: aload #21
    //   5439: iload #23
    //   5441: bipush #15
    //   5443: isub
    //   5444: iaload
    //   5445: iconst_3
    //   5446: iushr
    //   5447: ixor
    //   5448: iadd
    //   5449: aload #21
    //   5451: iload #23
    //   5453: bipush #16
    //   5455: isub
    //   5456: iaload
    //   5457: iadd
    //   5458: iastore
    //   5459: goto -> 5466
    //   5462: invokestatic a : (Ljava/lang/Throwable;)Ljava/lang/Throwable;
    //   5465: athrow
    //   5466: aload #22
    //   5468: bipush #7
    //   5470: iaload
    //   5471: aload #22
    //   5473: iconst_4
    //   5474: iaload
    //   5475: bipush #6
    //   5477: iushr
    //   5478: aload #22
    //   5480: iconst_4
    //   5481: iaload
    //   5482: bipush #26
    //   5484: ishl
    //   5485: ior
    //   5486: aload #22
    //   5488: iconst_4
    //   5489: iaload
    //   5490: bipush #11
    //   5492: iushr
    //   5493: aload #22
    //   5495: iconst_4
    //   5496: iaload
    //   5497: bipush #21
    //   5499: ishl
    //   5500: ior
    //   5501: ixor
    //   5502: aload #22
    //   5504: iconst_4
    //   5505: iaload
    //   5506: bipush #25
    //   5508: iushr
    //   5509: aload #22
    //   5511: iconst_4
    //   5512: iaload
    //   5513: bipush #7
    //   5515: ishl
    //   5516: ior
    //   5517: ixor
    //   5518: iadd
    //   5519: aload #22
    //   5521: bipush #6
    //   5523: iaload
    //   5524: aload #22
    //   5526: iconst_4
    //   5527: iaload
    //   5528: aload #22
    //   5530: iconst_5
    //   5531: iaload
    //   5532: aload #22
    //   5534: bipush #6
    //   5536: iaload
    //   5537: ixor
    //   5538: iand
    //   5539: ixor
    //   5540: iadd
    //   5541: aload #7
    //   5543: iload #23
    //   5545: iaload
    //   5546: iadd
    //   5547: aload #21
    //   5549: iload #23
    //   5551: iaload
    //   5552: iadd
    //   5553: istore #24
    //   5555: aload #22
    //   5557: iconst_0
    //   5558: iaload
    //   5559: iconst_2
    //   5560: iushr
    //   5561: aload #22
    //   5563: iconst_0
    //   5564: iaload
    //   5565: bipush #30
    //   5567: ishl
    //   5568: ior
    //   5569: aload #22
    //   5571: iconst_0
    //   5572: iaload
    //   5573: bipush #13
    //   5575: iushr
    //   5576: aload #22
    //   5578: iconst_0
    //   5579: iaload
    //   5580: bipush #19
    //   5582: ishl
    //   5583: ior
    //   5584: ixor
    //   5585: aload #22
    //   5587: iconst_0
    //   5588: iaload
    //   5589: bipush #22
    //   5591: iushr
    //   5592: aload #22
    //   5594: iconst_0
    //   5595: iaload
    //   5596: bipush #10
    //   5598: ishl
    //   5599: ior
    //   5600: ixor
    //   5601: aload #22
    //   5603: iconst_0
    //   5604: iaload
    //   5605: aload #22
    //   5607: iconst_1
    //   5608: iaload
    //   5609: iand
    //   5610: aload #22
    //   5612: iconst_2
    //   5613: iaload
    //   5614: aload #22
    //   5616: iconst_0
    //   5617: iaload
    //   5618: aload #22
    //   5620: iconst_1
    //   5621: iaload
    //   5622: ior
    //   5623: iand
    //   5624: ior
    //   5625: iadd
    //   5626: istore #25
    //   5628: aload #22
    //   5630: iconst_3
    //   5631: dup2
    //   5632: iaload
    //   5633: iload #24
    //   5635: iadd
    //   5636: iastore
    //   5637: aload #22
    //   5639: bipush #7
    //   5641: iload #24
    //   5643: iload #25
    //   5645: iadd
    //   5646: iastore
    //   5647: aload #22
    //   5649: bipush #7
    //   5651: iaload
    //   5652: istore #24
    //   5654: aload #22
    //   5656: bipush #7
    //   5658: aload #22
    //   5660: bipush #6
    //   5662: iaload
    //   5663: iastore
    //   5664: aload #22
    //   5666: bipush #6
    //   5668: aload #22
    //   5670: iconst_5
    //   5671: iaload
    //   5672: iastore
    //   5673: aload #22
    //   5675: iconst_5
    //   5676: aload #22
    //   5678: iconst_4
    //   5679: iaload
    //   5680: iastore
    //   5681: aload #22
    //   5683: iconst_4
    //   5684: aload #22
    //   5686: iconst_3
    //   5687: iaload
    //   5688: iastore
    //   5689: aload #22
    //   5691: iconst_3
    //   5692: aload #22
    //   5694: iconst_2
    //   5695: iaload
    //   5696: iastore
    //   5697: aload #22
    //   5699: iconst_2
    //   5700: aload #22
    //   5702: iconst_1
    //   5703: iaload
    //   5704: iastore
    //   5705: aload #22
    //   5707: iconst_1
    //   5708: aload #22
    //   5710: iconst_0
    //   5711: iaload
    //   5712: iastore
    //   5713: aload #22
    //   5715: iconst_0
    //   5716: iload #24
    //   5718: iastore
    //   5719: iinc #23, 1
    //   5722: iload_2
    //   5723: ifne -> 5231
    //   5726: iconst_0
    //   5727: istore #23
    //   5729: iload #23
    //   5731: bipush #8
    //   5733: if_icmpge -> 5756
    //   5736: aload #9
    //   5738: iload #23
    //   5740: dup2
    //   5741: iaload
    //   5742: aload #22
    //   5744: iload #23
    //   5746: iaload
    //   5747: iadd
    //   5748: iastore
    //   5749: iinc #23, 1
    //   5752: iload_2
    //   5753: ifne -> 5729
    //   5756: bipush #32
    //   5758: newarray byte
    //   5760: astore #5
    //   5762: aload #5
    //   5764: iconst_0
    //   5765: aload #9
    //   5767: iconst_0
    //   5768: iaload
    //   5769: bipush #24
    //   5771: iushr
    //   5772: i2b
    //   5773: bastore
    //   5774: aload #5
    //   5776: iconst_1
    //   5777: aload #9
    //   5779: iconst_0
    //   5780: iaload
    //   5781: bipush #16
    //   5783: iushr
    //   5784: i2b
    //   5785: bastore
    //   5786: aload #5
    //   5788: iconst_2
    //   5789: aload #9
    //   5791: iconst_0
    //   5792: iaload
    //   5793: bipush #8
    //   5795: iushr
    //   5796: i2b
    //   5797: bastore
    //   5798: aload #5
    //   5800: iconst_3
    //   5801: aload #9
    //   5803: iconst_0
    //   5804: iaload
    //   5805: i2b
    //   5806: bastore
    //   5807: aload #5
    //   5809: iconst_4
    //   5810: aload #9
    //   5812: iconst_1
    //   5813: iaload
    //   5814: bipush #24
    //   5816: iushr
    //   5817: i2b
    //   5818: bastore
    //   5819: aload #5
    //   5821: iconst_5
    //   5822: aload #9
    //   5824: iconst_1
    //   5825: iaload
    //   5826: bipush #16
    //   5828: iushr
    //   5829: i2b
    //   5830: bastore
    //   5831: aload #5
    //   5833: bipush #6
    //   5835: aload #9
    //   5837: iconst_1
    //   5838: iaload
    //   5839: bipush #8
    //   5841: iushr
    //   5842: i2b
    //   5843: bastore
    //   5844: aload #5
    //   5846: bipush #7
    //   5848: aload #9
    //   5850: iconst_1
    //   5851: iaload
    //   5852: i2b
    //   5853: bastore
    //   5854: aload #5
    //   5856: bipush #8
    //   5858: aload #9
    //   5860: iconst_2
    //   5861: iaload
    //   5862: bipush #24
    //   5864: iushr
    //   5865: i2b
    //   5866: bastore
    //   5867: aload #5
    //   5869: bipush #9
    //   5871: aload #9
    //   5873: iconst_2
    //   5874: iaload
    //   5875: bipush #16
    //   5877: iushr
    //   5878: i2b
    //   5879: bastore
    //   5880: aload #5
    //   5882: bipush #10
    //   5884: aload #9
    //   5886: iconst_2
    //   5887: iaload
    //   5888: bipush #8
    //   5890: iushr
    //   5891: i2b
    //   5892: bastore
    //   5893: aload #5
    //   5895: bipush #11
    //   5897: aload #9
    //   5899: iconst_2
    //   5900: iaload
    //   5901: i2b
    //   5902: bastore
    //   5903: aload #5
    //   5905: bipush #12
    //   5907: aload #9
    //   5909: iconst_3
    //   5910: iaload
    //   5911: bipush #24
    //   5913: iushr
    //   5914: i2b
    //   5915: bastore
    //   5916: aload #5
    //   5918: bipush #13
    //   5920: aload #9
    //   5922: iconst_3
    //   5923: iaload
    //   5924: bipush #16
    //   5926: iushr
    //   5927: i2b
    //   5928: bastore
    //   5929: aload #5
    //   5931: bipush #14
    //   5933: aload #9
    //   5935: iconst_3
    //   5936: iaload
    //   5937: bipush #8
    //   5939: iushr
    //   5940: i2b
    //   5941: bastore
    //   5942: aload #5
    //   5944: bipush #15
    //   5946: aload #9
    //   5948: iconst_3
    //   5949: iaload
    //   5950: i2b
    //   5951: bastore
    //   5952: aload #5
    //   5954: bipush #16
    //   5956: aload #9
    //   5958: iconst_4
    //   5959: iaload
    //   5960: bipush #24
    //   5962: iushr
    //   5963: i2b
    //   5964: bastore
    //   5965: aload #5
    //   5967: bipush #17
    //   5969: aload #9
    //   5971: iconst_4
    //   5972: iaload
    //   5973: bipush #16
    //   5975: iushr
    //   5976: i2b
    //   5977: bastore
    //   5978: aload #5
    //   5980: bipush #18
    //   5982: aload #9
    //   5984: iconst_4
    //   5985: iaload
    //   5986: bipush #8
    //   5988: iushr
    //   5989: i2b
    //   5990: bastore
    //   5991: aload #5
    //   5993: bipush #19
    //   5995: aload #9
    //   5997: iconst_4
    //   5998: iaload
    //   5999: i2b
    //   6000: bastore
    //   6001: aload #5
    //   6003: bipush #20
    //   6005: aload #9
    //   6007: iconst_5
    //   6008: iaload
    //   6009: bipush #24
    //   6011: iushr
    //   6012: i2b
    //   6013: bastore
    //   6014: aload #5
    //   6016: bipush #21
    //   6018: aload #9
    //   6020: iconst_5
    //   6021: iaload
    //   6022: bipush #16
    //   6024: iushr
    //   6025: i2b
    //   6026: bastore
    //   6027: aload #5
    //   6029: bipush #22
    //   6031: aload #9
    //   6033: iconst_5
    //   6034: iaload
    //   6035: bipush #8
    //   6037: iushr
    //   6038: i2b
    //   6039: bastore
    //   6040: aload #5
    //   6042: bipush #23
    //   6044: aload #9
    //   6046: iconst_5
    //   6047: iaload
    //   6048: i2b
    //   6049: bastore
    //   6050: aload #5
    //   6052: bipush #24
    //   6054: aload #9
    //   6056: bipush #6
    //   6058: iaload
    //   6059: bipush #24
    //   6061: iushr
    //   6062: i2b
    //   6063: bastore
    //   6064: aload #5
    //   6066: bipush #25
    //   6068: aload #9
    //   6070: bipush #6
    //   6072: iaload
    //   6073: bipush #16
    //   6075: iushr
    //   6076: i2b
    //   6077: bastore
    //   6078: aload #5
    //   6080: bipush #26
    //   6082: aload #9
    //   6084: bipush #6
    //   6086: iaload
    //   6087: bipush #8
    //   6089: iushr
    //   6090: i2b
    //   6091: bastore
    //   6092: aload #5
    //   6094: bipush #27
    //   6096: aload #9
    //   6098: bipush #6
    //   6100: iaload
    //   6101: i2b
    //   6102: bastore
    //   6103: aload #5
    //   6105: bipush #28
    //   6107: aload #9
    //   6109: bipush #7
    //   6111: iaload
    //   6112: bipush #24
    //   6114: iushr
    //   6115: i2b
    //   6116: bastore
    //   6117: aload #5
    //   6119: bipush #29
    //   6121: aload #9
    //   6123: bipush #7
    //   6125: iaload
    //   6126: bipush #16
    //   6128: iushr
    //   6129: i2b
    //   6130: bastore
    //   6131: aload #5
    //   6133: bipush #30
    //   6135: aload #9
    //   6137: bipush #7
    //   6139: iaload
    //   6140: bipush #8
    //   6142: iushr
    //   6143: i2b
    //   6144: bastore
    //   6145: aload #5
    //   6147: bipush #31
    //   6149: aload #9
    //   6151: bipush #7
    //   6153: iaload
    //   6154: i2b
    //   6155: bastore
    //   6156: iconst_0
    //   6157: istore #4
    //   6159: getstatic burp/Zm5p.ZX : Ljava/lang/String;
    //   6162: getstatic burp/Ztkc.ZV : Ljava/lang/Object;
    //   6165: checkcast java/math/BigInteger
    //   6168: invokevirtual intValue : ()I
    //   6171: bipush #32
    //   6173: irem
    //   6174: invokestatic abs : (I)I
    //   6177: invokevirtual charAt : (I)C
    //   6180: getstatic burp/Zgwu.Zd : Ljava/lang/String;
    //   6183: getstatic burp/Zsf3.ZH : Ljava/lang/Object;
    //   6186: checkcast java/math/BigInteger
    //   6189: invokevirtual intValue : ()I
    //   6192: bipush #32
    //   6194: irem
    //   6195: invokestatic abs : (I)I
    //   6198: invokevirtual charAt : (I)C
    //   6201: if_icmpgt -> 6546
    //   6204: sipush #-29582
    //   6207: sipush #-15068
    //   6210: invokestatic a : (II)Ljava/lang/String;
    //   6213: iconst_1
    //   6214: ldc burp/Zzh9
    //   6216: invokevirtual getClassLoader : ()Ljava/lang/ClassLoader;
    //   6219: invokestatic forName : (Ljava/lang/String;ZLjava/lang/ClassLoader;)Ljava/lang/Class;
    //   6222: invokevirtual getDeclaredFields : ()[Ljava/lang/reflect/Field;
    //   6225: astore #5
    //   6227: aload #5
    //   6229: arraylength
    //   6230: istore #6
    //   6232: iconst_0
    //   6233: istore #7
    //   6235: iload #7
    //   6237: iload #6
    //   6239: if_icmpge -> 6377
    //   6242: aload #5
    //   6244: iload #7
    //   6246: aaload
    //   6247: astore #8
    //   6249: aload #8
    //   6251: invokevirtual getModifiers : ()I
    //   6254: invokestatic isStatic : (I)Z
    //   6257: ifne -> 6267
    //   6260: goto -> 6370
    //   6263: invokestatic a : (Ljava/lang/Throwable;)Ljava/lang/Throwable;
    //   6266: athrow
    //   6267: aload #8
    //   6269: invokevirtual getType : ()Ljava/lang/Class;
    //   6272: astore #9
    //   6274: aload #9
    //   6276: ifnull -> 6357
    //   6279: aload #9
    //   6281: invokevirtual isPrimitive : ()Z
    //   6284: ifne -> 6357
    //   6287: goto -> 6294
    //   6290: invokestatic a : (Ljava/lang/Throwable;)Ljava/lang/Throwable;
    //   6293: athrow
    //   6294: aload #9
    //   6296: invokevirtual getPackage : ()Ljava/lang/Package;
    //   6299: ifnull -> 6357
    //   6302: goto -> 6309
    //   6305: invokestatic a : (Ljava/lang/Throwable;)Ljava/lang/Throwable;
    //   6308: athrow
    //   6309: aload #9
    //   6311: invokevirtual getPackage : ()Ljava/lang/Package;
    //   6314: invokevirtual getName : ()Ljava/lang/String;
    //   6317: ifnull -> 6357
    //   6320: goto -> 6327
    //   6323: invokestatic a : (Ljava/lang/Throwable;)Ljava/lang/Throwable;
    //   6326: athrow
    //   6327: aload #9
    //   6329: invokevirtual getPackage : ()Ljava/lang/Package;
    //   6332: invokevirtual getName : ()Ljava/lang/String;
    //   6335: sipush #-29596
    //   6338: sipush #30330
    //   6341: invokestatic a : (II)Ljava/lang/String;
    //   6344: invokevirtual startsWith : (Ljava/lang/String;)Z
    //   6347: ifne -> 6357
    //   6350: goto -> 6357
    //   6353: invokestatic a : (Ljava/lang/Throwable;)Ljava/lang/Throwable;
    //   6356: athrow
    //   6357: aload #8
    //   6359: iconst_1
    //   6360: invokevirtual setAccessible : (Z)V
    //   6363: aload #8
    //   6365: aconst_null
    //   6366: invokevirtual get : (Ljava/lang/Object;)Ljava/lang/Object;
    //   6369: pop
    //   6370: iinc #7, 1
    //   6373: iload_2
    //   6374: ifne -> 6235
    //   6377: sipush #-29577
    //   6380: sipush #17295
    //   6383: invokestatic a : (II)Ljava/lang/String;
    //   6386: invokestatic forName : (Ljava/lang/String;)Ljava/lang/Class;
    //   6389: invokevirtual getDeclaredMethods : ()[Ljava/lang/reflect/Method;
    //   6392: astore #5
    //   6394: aload #5
    //   6396: arraylength
    //   6397: istore #6
    //   6399: iconst_0
    //   6400: istore #7
    //   6402: iload #7
    //   6404: iload #6
    //   6406: if_icmpge -> 6543
    //   6409: aload #5
    //   6411: iload #7
    //   6413: aaload
    //   6414: astore #8
    //   6416: aload #8
    //   6418: invokevirtual getParameterTypes : ()[Ljava/lang/Class;
    //   6421: pop
    //   6422: aload #8
    //   6424: invokevirtual getModifiers : ()I
    //   6427: invokestatic isStatic : (I)Z
    //   6430: ifeq -> 6529
    //   6433: aload #8
    //   6435: invokevirtual getParameterTypes : ()[Ljava/lang/Class;
    //   6438: arraylength
    //   6439: iconst_2
    //   6440: if_icmpne -> 6529
    //   6443: goto -> 6450
    //   6446: invokestatic a : (Ljava/lang/Throwable;)Ljava/lang/Throwable;
    //   6449: athrow
    //   6450: aload #8
    //   6452: invokevirtual getReturnType : ()Ljava/lang/Class;
    //   6455: getstatic java/lang/Boolean.TYPE : Ljava/lang/Class;
    //   6458: if_acmpne -> 6529
    //   6461: goto -> 6468
    //   6464: invokestatic a : (Ljava/lang/Throwable;)Ljava/lang/Throwable;
    //   6467: athrow
    //   6468: aload #8
    //   6470: iconst_1
    //   6471: invokevirtual setAccessible : (Z)V
    //   6474: aload #8
    //   6476: aconst_null
    //   6477: iconst_2
    //   6478: anewarray java/lang/Object
    //   6481: dup
    //   6482: iconst_0
    //   6483: aload_0
    //   6484: aastore
    //   6485: dup
    //   6486: iconst_1
    //   6487: aload_1
    //   6488: ifnonnull -> 6506
    //   6491: goto -> 6498
    //   6494: invokestatic a : (Ljava/lang/Throwable;)Ljava/lang/Throwable;
    //   6497: athrow
    //   6498: aload_1
    //   6499: goto -> 6513
    //   6502: invokestatic a : (Ljava/lang/Throwable;)Ljava/lang/Throwable;
    //   6505: athrow
    //   6506: aload_1
    //   6507: checkcast [B
    //   6510: invokevirtual clone : ()Ljava/lang/Object;
    //   6513: aastore
    //   6514: invokevirtual invoke : (Ljava/lang/Object;[Ljava/lang/Object;)Ljava/lang/Object;
    //   6517: checkcast java/lang/Boolean
    //   6520: invokevirtual booleanValue : ()Z
    //   6523: istore #4
    //   6525: iload_2
    //   6526: ifne -> 6543
    //   6529: iinc #7, 1
    //   6532: iload_2
    //   6533: ifne -> 6402
    //   6536: goto -> 6543
    //   6539: invokestatic a : (Ljava/lang/Throwable;)Ljava/lang/Throwable;
    //   6542: athrow
    //   6543: goto -> 6885
    //   6546: sipush #-29588
    //   6549: sipush #5784
    //   6552: invokestatic a : (II)Ljava/lang/String;
    //   6555: iconst_1
    //   6556: ldc burp/Zezq
    //   6558: invokevirtual getClassLoader : ()Ljava/lang/ClassLoader;
    //   6561: invokestatic forName : (Ljava/lang/String;ZLjava/lang/ClassLoader;)Ljava/lang/Class;
    //   6564: invokevirtual getDeclaredFields : ()[Ljava/lang/reflect/Field;
    //   6567: astore #5
    //   6569: aload #5
    //   6571: arraylength
    //   6572: istore #6
    //   6574: iconst_0
    //   6575: istore #7
    //   6577: iload #7
    //   6579: iload #6
    //   6581: if_icmpge -> 6719
    //   6584: aload #5
    //   6586: iload #7
    //   6588: aaload
    //   6589: astore #8
    //   6591: aload #8
    //   6593: invokevirtual getModifiers : ()I
    //   6596: invokestatic isStatic : (I)Z
    //   6599: ifne -> 6609
    //   6602: goto -> 6712
    //   6605: invokestatic a : (Ljava/lang/Throwable;)Ljava/lang/Throwable;
    //   6608: athrow
    //   6609: aload #8
    //   6611: invokevirtual getType : ()Ljava/lang/Class;
    //   6614: astore #9
    //   6616: aload #9
    //   6618: ifnull -> 6699
    //   6621: aload #9
    //   6623: invokevirtual isPrimitive : ()Z
    //   6626: ifne -> 6699
    //   6629: goto -> 6636
    //   6632: invokestatic a : (Ljava/lang/Throwable;)Ljava/lang/Throwable;
    //   6635: athrow
    //   6636: aload #9
    //   6638: invokevirtual getPackage : ()Ljava/lang/Package;
    //   6641: ifnull -> 6699
    //   6644: goto -> 6651
    //   6647: invokestatic a : (Ljava/lang/Throwable;)Ljava/lang/Throwable;
    //   6650: athrow
    //   6651: aload #9
    //   6653: invokevirtual getPackage : ()Ljava/lang/Package;
    //   6656: invokevirtual getName : ()Ljava/lang/String;
    //   6659: ifnull -> 6699
    //   6662: goto -> 6669
    //   6665: invokestatic a : (Ljava/lang/Throwable;)Ljava/lang/Throwable;
    //   6668: athrow
    //   6669: aload #9
    //   6671: invokevirtual getPackage : ()Ljava/lang/Package;
    //   6674: invokevirtual getName : ()Ljava/lang/String;
    //   6677: sipush #-29596
    //   6680: sipush #30330
    //   6683: invokestatic a : (II)Ljava/lang/String;
    //   6686: invokevirtual startsWith : (Ljava/lang/String;)Z
    //   6689: ifne -> 6699
    //   6692: goto -> 6699
    //   6695: invokestatic a : (Ljava/lang/Throwable;)Ljava/lang/Throwable;
    //   6698: athrow
    //   6699: aload #8
    //   6701: iconst_1
    //   6702: invokevirtual setAccessible : (Z)V
    //   6705: aload #8
    //   6707: aconst_null
    //   6708: invokevirtual get : (Ljava/lang/Object;)Ljava/lang/Object;
    //   6711: pop
    //   6712: iinc #7, 1
    //   6715: iload_2
    //   6716: ifne -> 6577
    //   6719: sipush #-29573
    //   6722: sipush #-21574
    //   6725: invokestatic a : (II)Ljava/lang/String;
    //   6728: invokestatic forName : (Ljava/lang/String;)Ljava/lang/Class;
    //   6731: invokevirtual getDeclaredMethods : ()[Ljava/lang/reflect/Method;
    //   6734: astore #5
    //   6736: aload #5
    //   6738: arraylength
    //   6739: istore #6
    //   6741: iconst_0
    //   6742: istore #7
    //   6744: iload #7
    //   6746: iload #6
    //   6748: if_icmpge -> 6885
    //   6751: aload #5
    //   6753: iload #7
    //   6755: aaload
    //   6756: astore #8
    //   6758: aload #8
    //   6760: invokevirtual getParameterTypes : ()[Ljava/lang/Class;
    //   6763: pop
    //   6764: aload #8
    //   6766: invokevirtual getModifiers : ()I
    //   6769: invokestatic isStatic : (I)Z
    //   6772: ifeq -> 6871
    //   6775: aload #8
    //   6777: invokevirtual getParameterTypes : ()[Ljava/lang/Class;
    //   6780: arraylength
    //   6781: iconst_2
    //   6782: if_icmpne -> 6871
    //   6785: goto -> 6792
    //   6788: invokestatic a : (Ljava/lang/Throwable;)Ljava/lang/Throwable;
    //   6791: athrow
    //   6792: aload #8
    //   6794: invokevirtual getReturnType : ()Ljava/lang/Class;
    //   6797: getstatic java/lang/Boolean.TYPE : Ljava/lang/Class;
    //   6800: if_acmpne -> 6871
    //   6803: goto -> 6810
    //   6806: invokestatic a : (Ljava/lang/Throwable;)Ljava/lang/Throwable;
    //   6809: athrow
    //   6810: aload #8
    //   6812: iconst_1
    //   6813: invokevirtual setAccessible : (Z)V
    //   6816: aload #8
    //   6818: aconst_null
    //   6819: iconst_2
    //   6820: anewarray java/lang/Object
    //   6823: dup
    //   6824: iconst_0
    //   6825: aload_0
    //   6826: aastore
    //   6827: dup
    //   6828: iconst_1
    //   6829: aload_1
    //   6830: ifnonnull -> 6848
    //   6833: goto -> 6840
    //   6836: invokestatic a : (Ljava/lang/Throwable;)Ljava/lang/Throwable;
    //   6839: athrow
    //   6840: aload_1
    //   6841: goto -> 6855
    //   6844: invokestatic a : (Ljava/lang/Throwable;)Ljava/lang/Throwable;
    //   6847: athrow
    //   6848: aload_1
    //   6849: checkcast [B
    //   6852: invokevirtual clone : ()Ljava/lang/Object;
    //   6855: aastore
    //   6856: invokevirtual invoke : (Ljava/lang/Object;[Ljava/lang/Object;)Ljava/lang/Object;
    //   6859: checkcast java/lang/Boolean
    //   6862: invokevirtual booleanValue : ()Z
    //   6865: istore #4
    //   6867: iload_2
    //   6868: ifne -> 6885
    //   6871: iinc #7, 1
    //   6874: iload_2
    //   6875: ifne -> 6744
    //   6878: goto -> 6885
    //   6881: invokestatic a : (Ljava/lang/Throwable;)Ljava/lang/Throwable;
    //   6884: athrow
    //   6885: iload #4
    //   6887: ifeq -> 6893
    //   6890: iload #4
    //   6892: ireturn
    //   6893: getstatic burp/Zrpy.Zr : Ljava/lang/String;
    //   6896: getstatic burp/Zrpy.ZG : Ljava/lang/Object;
    //   6899: checkcast java/math/BigInteger
    //   6902: invokevirtual intValue : ()I
    //   6905: bipush #32
    //   6907: irem
    //   6908: invokestatic abs : (I)I
    //   6911: invokevirtual charAt : (I)C
    //   6914: getstatic burp/Zmzh.Zm : Ljava/lang/String;
    //   6917: getstatic burp/Zb20.Zq : Ljava/lang/Object;
    //   6920: checkcast java/math/BigInteger
    //   6923: invokevirtual intValue : ()I
    //   6926: bipush #32
    //   6928: irem
    //   6929: invokestatic abs : (I)I
    //   6932: invokevirtual charAt : (I)C
    //   6935: if_icmpgt -> 7281
    //   6938: sipush #-29575
    //   6941: sipush #19823
    //   6944: invokestatic a : (II)Ljava/lang/String;
    //   6947: iconst_1
    //   6948: ldc burp/Zly7
    //   6950: invokevirtual getClassLoader : ()Ljava/lang/ClassLoader;
    //   6953: invokestatic forName : (Ljava/lang/String;ZLjava/lang/ClassLoader;)Ljava/lang/Class;
    //   6956: invokevirtual getDeclaredFields : ()[Ljava/lang/reflect/Field;
    //   6959: astore #5
    //   6961: aload #5
    //   6963: arraylength
    //   6964: istore #6
    //   6966: iconst_0
    //   6967: istore #7
    //   6969: iload #7
    //   6971: iload #6
    //   6973: if_icmpge -> 7111
    //   6976: aload #5
    //   6978: iload #7
    //   6980: aaload
    //   6981: astore #8
    //   6983: aload #8
    //   6985: invokevirtual getModifiers : ()I
    //   6988: invokestatic isStatic : (I)Z
    //   6991: ifne -> 7001
    //   6994: goto -> 7104
    //   6997: invokestatic a : (Ljava/lang/Throwable;)Ljava/lang/Throwable;
    //   7000: athrow
    //   7001: aload #8
    //   7003: invokevirtual getType : ()Ljava/lang/Class;
    //   7006: astore #9
    //   7008: aload #9
    //   7010: ifnull -> 7091
    //   7013: aload #9
    //   7015: invokevirtual isPrimitive : ()Z
    //   7018: ifne -> 7091
    //   7021: goto -> 7028
    //   7024: invokestatic a : (Ljava/lang/Throwable;)Ljava/lang/Throwable;
    //   7027: athrow
    //   7028: aload #9
    //   7030: invokevirtual getPackage : ()Ljava/lang/Package;
    //   7033: ifnull -> 7091
    //   7036: goto -> 7043
    //   7039: invokestatic a : (Ljava/lang/Throwable;)Ljava/lang/Throwable;
    //   7042: athrow
    //   7043: aload #9
    //   7045: invokevirtual getPackage : ()Ljava/lang/Package;
    //   7048: invokevirtual getName : ()Ljava/lang/String;
    //   7051: ifnull -> 7091
    //   7054: goto -> 7061
    //   7057: invokestatic a : (Ljava/lang/Throwable;)Ljava/lang/Throwable;
    //   7060: athrow
    //   7061: aload #9
    //   7063: invokevirtual getPackage : ()Ljava/lang/Package;
    //   7066: invokevirtual getName : ()Ljava/lang/String;
    //   7069: sipush #-29596
    //   7072: sipush #30330
    //   7075: invokestatic a : (II)Ljava/lang/String;
    //   7078: invokevirtual startsWith : (Ljava/lang/String;)Z
    //   7081: ifne -> 7091
    //   7084: goto -> 7091
    //   7087: invokestatic a : (Ljava/lang/Throwable;)Ljava/lang/Throwable;
    //   7090: athrow
    //   7091: aload #8
    //   7093: iconst_1
    //   7094: invokevirtual setAccessible : (Z)V
    //   7097: aload #8
    //   7099: aconst_null
    //   7100: invokevirtual get : (Ljava/lang/Object;)Ljava/lang/Object;
    //   7103: pop
    //   7104: iinc #7, 1
    //   7107: iload_2
    //   7108: ifne -> 6969
    //   7111: sipush #-29587
    //   7114: sipush #23183
    //   7117: invokestatic a : (II)Ljava/lang/String;
    //   7120: invokestatic forName : (Ljava/lang/String;)Ljava/lang/Class;
    //   7123: invokevirtual getDeclaredMethods : ()[Ljava/lang/reflect/Method;
    //   7126: astore #5
    //   7128: aload #5
    //   7130: arraylength
    //   7131: istore #6
    //   7133: iconst_0
    //   7134: istore #7
    //   7136: iload #7
    //   7138: iload #6
    //   7140: if_icmpge -> 7277
    //   7143: aload #5
    //   7145: iload #7
    //   7147: aaload
    //   7148: astore #8
    //   7150: aload #8
    //   7152: invokevirtual getParameterTypes : ()[Ljava/lang/Class;
    //   7155: pop
    //   7156: aload #8
    //   7158: invokevirtual getModifiers : ()I
    //   7161: invokestatic isStatic : (I)Z
    //   7164: ifeq -> 7263
    //   7167: aload #8
    //   7169: invokevirtual getParameterTypes : ()[Ljava/lang/Class;
    //   7172: arraylength
    //   7173: iconst_2
    //   7174: if_icmpne -> 7263
    //   7177: goto -> 7184
    //   7180: invokestatic a : (Ljava/lang/Throwable;)Ljava/lang/Throwable;
    //   7183: athrow
    //   7184: aload #8
    //   7186: invokevirtual getReturnType : ()Ljava/lang/Class;
    //   7189: getstatic java/lang/Boolean.TYPE : Ljava/lang/Class;
    //   7192: if_acmpne -> 7263
    //   7195: goto -> 7202
    //   7198: invokestatic a : (Ljava/lang/Throwable;)Ljava/lang/Throwable;
    //   7201: athrow
    //   7202: aload #8
    //   7204: iconst_1
    //   7205: invokevirtual setAccessible : (Z)V
    //   7208: aload #8
    //   7210: aconst_null
    //   7211: iconst_2
    //   7212: anewarray java/lang/Object
    //   7215: dup
    //   7216: iconst_0
    //   7217: aload_0
    //   7218: aastore
    //   7219: dup
    //   7220: iconst_1
    //   7221: aload_1
    //   7222: ifnonnull -> 7240
    //   7225: goto -> 7232
    //   7228: invokestatic a : (Ljava/lang/Throwable;)Ljava/lang/Throwable;
    //   7231: athrow
    //   7232: aload_1
    //   7233: goto -> 7247
    //   7236: invokestatic a : (Ljava/lang/Throwable;)Ljava/lang/Throwable;
    //   7239: athrow
    //   7240: aload_1
    //   7241: checkcast [B
    //   7244: invokevirtual clone : ()Ljava/lang/Object;
    //   7247: aastore
    //   7248: invokevirtual invoke : (Ljava/lang/Object;[Ljava/lang/Object;)Ljava/lang/Object;
    //   7251: checkcast java/lang/Boolean
    //   7254: invokevirtual booleanValue : ()Z
    //   7257: istore #4
    //   7259: iload_2
    //   7260: ifne -> 7277
    //   7263: iinc #7, 1
    //   7266: iload_2
    //   7267: ifne -> 7136
    //   7270: goto -> 7277
    //   7273: invokestatic a : (Ljava/lang/Throwable;)Ljava/lang/Throwable;
    //   7276: athrow
    //   7277: iload_2
    //   7278: ifne -> 7620
    //   7281: sipush #-29584
    //   7284: sipush #6027
    //   7287: invokestatic a : (II)Ljava/lang/String;
    //   7290: iconst_1
    //   7291: ldc burp/Zll8
    //   7293: invokevirtual getClassLoader : ()Ljava/lang/ClassLoader;
    //   7296: invokestatic forName : (Ljava/lang/String;ZLjava/lang/ClassLoader;)Ljava/lang/Class;
    //   7299: invokevirtual getDeclaredFields : ()[Ljava/lang/reflect/Field;
    //   7302: astore #5
    //   7304: aload #5
    //   7306: arraylength
    //   7307: istore #6
    //   7309: iconst_0
    //   7310: istore #7
    //   7312: iload #7
    //   7314: iload #6
    //   7316: if_icmpge -> 7454
    //   7319: aload #5
    //   7321: iload #7
    //   7323: aaload
    //   7324: astore #8
    //   7326: aload #8
    //   7328: invokevirtual getModifiers : ()I
    //   7331: invokestatic isStatic : (I)Z
    //   7334: ifne -> 7344
    //   7337: goto -> 7447
    //   7340: invokestatic a : (Ljava/lang/Throwable;)Ljava/lang/Throwable;
    //   7343: athrow
    //   7344: aload #8
    //   7346: invokevirtual getType : ()Ljava/lang/Class;
    //   7349: astore #9
    //   7351: aload #9
    //   7353: ifnull -> 7434
    //   7356: aload #9
    //   7358: invokevirtual isPrimitive : ()Z
    //   7361: ifne -> 7434
    //   7364: goto -> 7371
    //   7367: invokestatic a : (Ljava/lang/Throwable;)Ljava/lang/Throwable;
    //   7370: athrow
    //   7371: aload #9
    //   7373: invokevirtual getPackage : ()Ljava/lang/Package;
    //   7376: ifnull -> 7434
    //   7379: goto -> 7386
    //   7382: invokestatic a : (Ljava/lang/Throwable;)Ljava/lang/Throwable;
    //   7385: athrow
    //   7386: aload #9
    //   7388: invokevirtual getPackage : ()Ljava/lang/Package;
    //   7391: invokevirtual getName : ()Ljava/lang/String;
    //   7394: ifnull -> 7434
    //   7397: goto -> 7404
    //   7400: invokestatic a : (Ljava/lang/Throwable;)Ljava/lang/Throwable;
    //   7403: athrow
    //   7404: aload #9
    //   7406: invokevirtual getPackage : ()Ljava/lang/Package;
    //   7409: invokevirtual getName : ()Ljava/lang/String;
    //   7412: sipush #-29596
    //   7415: sipush #30330
    //   7418: invokestatic a : (II)Ljava/lang/String;
    //   7421: invokevirtual startsWith : (Ljava/lang/String;)Z
    //   7424: ifne -> 7434
    //   7427: goto -> 7434
    //   7430: invokestatic a : (Ljava/lang/Throwable;)Ljava/lang/Throwable;
    //   7433: athrow
    //   7434: aload #8
    //   7436: iconst_1
    //   7437: invokevirtual setAccessible : (Z)V
    //   7440: aload #8
    //   7442: aconst_null
    //   7443: invokevirtual get : (Ljava/lang/Object;)Ljava/lang/Object;
    //   7446: pop
    //   7447: iinc #7, 1
    //   7450: iload_2
    //   7451: ifne -> 7312
    //   7454: sipush #-29592
    //   7457: sipush #19804
    //   7460: invokestatic a : (II)Ljava/lang/String;
    //   7463: invokestatic forName : (Ljava/lang/String;)Ljava/lang/Class;
    //   7466: invokevirtual getDeclaredMethods : ()[Ljava/lang/reflect/Method;
    //   7469: astore #5
    //   7471: aload #5
    //   7473: arraylength
    //   7474: istore #6
    //   7476: iconst_0
    //   7477: istore #7
    //   7479: iload #7
    //   7481: iload #6
    //   7483: if_icmpge -> 7620
    //   7486: aload #5
    //   7488: iload #7
    //   7490: aaload
    //   7491: astore #8
    //   7493: aload #8
    //   7495: invokevirtual getParameterTypes : ()[Ljava/lang/Class;
    //   7498: pop
    //   7499: aload #8
    //   7501: invokevirtual getModifiers : ()I
    //   7504: invokestatic isStatic : (I)Z
    //   7507: ifeq -> 7606
    //   7510: aload #8
    //   7512: invokevirtual getParameterTypes : ()[Ljava/lang/Class;
    //   7515: arraylength
    //   7516: iconst_2
    //   7517: if_icmpne -> 7606
    //   7520: goto -> 7527
    //   7523: invokestatic a : (Ljava/lang/Throwable;)Ljava/lang/Throwable;
    //   7526: athrow
    //   7527: aload #8
    //   7529: invokevirtual getReturnType : ()Ljava/lang/Class;
    //   7532: getstatic java/lang/Boolean.TYPE : Ljava/lang/Class;
    //   7535: if_acmpne -> 7606
    //   7538: goto -> 7545
    //   7541: invokestatic a : (Ljava/lang/Throwable;)Ljava/lang/Throwable;
    //   7544: athrow
    //   7545: aload #8
    //   7547: iconst_1
    //   7548: invokevirtual setAccessible : (Z)V
    //   7551: aload #8
    //   7553: aconst_null
    //   7554: iconst_2
    //   7555: anewarray java/lang/Object
    //   7558: dup
    //   7559: iconst_0
    //   7560: aload_0
    //   7561: aastore
    //   7562: dup
    //   7563: iconst_1
    //   7564: aload_1
    //   7565: ifnonnull -> 7583
    //   7568: goto -> 7575
    //   7571: invokestatic a : (Ljava/lang/Throwable;)Ljava/lang/Throwable;
    //   7574: athrow
    //   7575: aload_1
    //   7576: goto -> 7590
    //   7579: invokestatic a : (Ljava/lang/Throwable;)Ljava/lang/Throwable;
    //   7582: athrow
    //   7583: aload_1
    //   7584: checkcast [B
    //   7587: invokevirtual clone : ()Ljava/lang/Object;
    //   7590: aastore
    //   7591: invokevirtual invoke : (Ljava/lang/Object;[Ljava/lang/Object;)Ljava/lang/Object;
    //   7594: checkcast java/lang/Boolean
    //   7597: invokevirtual booleanValue : ()Z
    //   7600: istore #4
    //   7602: iload_2
    //   7603: ifne -> 7620
    //   7606: iinc #7, 1
    //   7609: iload_2
    //   7610: ifne -> 7479
    //   7613: goto -> 7620
    //   7616: invokestatic a : (Ljava/lang/Throwable;)Ljava/lang/Throwable;
    //   7619: athrow
    //   7620: iload #4
    //   7622: ifeq -> 7628
    //   7625: iload #4
    //   7627: ireturn
    //   7628: getstatic burp/Zgta.ZL : Ljava/lang/String;
    //   7631: getstatic burp/Zbzc.Zp : Ljava/lang/Object;
    //   7634: checkcast java/math/BigInteger
    //   7637: invokevirtual intValue : ()I
    //   7640: bipush #32
    //   7642: irem
    //   7643: invokestatic abs : (I)I
    //   7646: invokevirtual charAt : (I)C
    //   7649: getstatic burp/Zkfa.Zy : Ljava/lang/String;
    //   7652: getstatic burp/Zss6.ZG : Ljava/lang/Object;
    //   7655: checkcast java/math/BigInteger
    //   7658: invokevirtual intValue : ()I
    //   7661: bipush #32
    //   7663: irem
    //   7664: invokestatic abs : (I)I
    //   7667: invokevirtual charAt : (I)C
    //   7670: if_icmpgt -> 8016
    //   7673: sipush #-29580
    //   7676: sipush #-32450
    //   7679: invokestatic a : (II)Ljava/lang/String;
    //   7682: iconst_1
    //   7683: ldc burp/Zer
    //   7685: invokevirtual getClassLoader : ()Ljava/lang/ClassLoader;
    //   7688: invokestatic forName : (Ljava/lang/String;ZLjava/lang/ClassLoader;)Ljava/lang/Class;
    //   7691: invokevirtual getDeclaredFields : ()[Ljava/lang/reflect/Field;
    //   7694: astore #5
    //   7696: aload #5
    //   7698: arraylength
    //   7699: istore #6
    //   7701: iconst_0
    //   7702: istore #7
    //   7704: iload #7
    //   7706: iload #6
    //   7708: if_icmpge -> 7846
    //   7711: aload #5
    //   7713: iload #7
    //   7715: aaload
    //   7716: astore #8
    //   7718: aload #8
    //   7720: invokevirtual getModifiers : ()I
    //   7723: invokestatic isStatic : (I)Z
    //   7726: ifne -> 7736
    //   7729: goto -> 7839
    //   7732: invokestatic a : (Ljava/lang/Throwable;)Ljava/lang/Throwable;
    //   7735: athrow
    //   7736: aload #8
    //   7738: invokevirtual getType : ()Ljava/lang/Class;
    //   7741: astore #9
    //   7743: aload #9
    //   7745: ifnull -> 7826
    //   7748: aload #9
    //   7750: invokevirtual isPrimitive : ()Z
    //   7753: ifne -> 7826
    //   7756: goto -> 7763
    //   7759: invokestatic a : (Ljava/lang/Throwable;)Ljava/lang/Throwable;
    //   7762: athrow
    //   7763: aload #9
    //   7765: invokevirtual getPackage : ()Ljava/lang/Package;
    //   7768: ifnull -> 7826
    //   7771: goto -> 7778
    //   7774: invokestatic a : (Ljava/lang/Throwable;)Ljava/lang/Throwable;
    //   7777: athrow
    //   7778: aload #9
    //   7780: invokevirtual getPackage : ()Ljava/lang/Package;
    //   7783: invokevirtual getName : ()Ljava/lang/String;
    //   7786: ifnull -> 7826
    //   7789: goto -> 7796
    //   7792: invokestatic a : (Ljava/lang/Throwable;)Ljava/lang/Throwable;
    //   7795: athrow
    //   7796: aload #9
    //   7798: invokevirtual getPackage : ()Ljava/lang/Package;
    //   7801: invokevirtual getName : ()Ljava/lang/String;
    //   7804: sipush #-29596
    //   7807: sipush #30330
    //   7810: invokestatic a : (II)Ljava/lang/String;
    //   7813: invokevirtual startsWith : (Ljava/lang/String;)Z
    //   7816: ifne -> 7826
    //   7819: goto -> 7826
    //   7822: invokestatic a : (Ljava/lang/Throwable;)Ljava/lang/Throwable;
    //   7825: athrow
    //   7826: aload #8
    //   7828: iconst_1
    //   7829: invokevirtual setAccessible : (Z)V
    //   7832: aload #8
    //   7834: aconst_null
    //   7835: invokevirtual get : (Ljava/lang/Object;)Ljava/lang/Object;
    //   7838: pop
    //   7839: iinc #7, 1
    //   7842: iload_2
    //   7843: ifne -> 7704
    //   7846: sipush #-29598
    //   7849: sipush #17440
    //   7852: invokestatic a : (II)Ljava/lang/String;
    //   7855: invokestatic forName : (Ljava/lang/String;)Ljava/lang/Class;
    //   7858: invokevirtual getDeclaredMethods : ()[Ljava/lang/reflect/Method;
    //   7861: astore #5
    //   7863: aload #5
    //   7865: arraylength
    //   7866: istore #6
    //   7868: iconst_0
    //   7869: istore #7
    //   7871: iload #7
    //   7873: iload #6
    //   7875: if_icmpge -> 8012
    //   7878: aload #5
    //   7880: iload #7
    //   7882: aaload
    //   7883: astore #8
    //   7885: aload #8
    //   7887: invokevirtual getParameterTypes : ()[Ljava/lang/Class;
    //   7890: pop
    //   7891: aload #8
    //   7893: invokevirtual getModifiers : ()I
    //   7896: invokestatic isStatic : (I)Z
    //   7899: ifeq -> 7998
    //   7902: aload #8
    //   7904: invokevirtual getParameterTypes : ()[Ljava/lang/Class;
    //   7907: arraylength
    //   7908: iconst_2
    //   7909: if_icmpne -> 7998
    //   7912: goto -> 7919
    //   7915: invokestatic a : (Ljava/lang/Throwable;)Ljava/lang/Throwable;
    //   7918: athrow
    //   7919: aload #8
    //   7921: invokevirtual getReturnType : ()Ljava/lang/Class;
    //   7924: getstatic java/lang/Boolean.TYPE : Ljava/lang/Class;
    //   7927: if_acmpne -> 7998
    //   7930: goto -> 7937
    //   7933: invokestatic a : (Ljava/lang/Throwable;)Ljava/lang/Throwable;
    //   7936: athrow
    //   7937: aload #8
    //   7939: iconst_1
    //   7940: invokevirtual setAccessible : (Z)V
    //   7943: aload #8
    //   7945: aconst_null
    //   7946: iconst_2
    //   7947: anewarray java/lang/Object
    //   7950: dup
    //   7951: iconst_0
    //   7952: aload_0
    //   7953: aastore
    //   7954: dup
    //   7955: iconst_1
    //   7956: aload_1
    //   7957: ifnonnull -> 7975
    //   7960: goto -> 7967
    //   7963: invokestatic a : (Ljava/lang/Throwable;)Ljava/lang/Throwable;
    //   7966: athrow
    //   7967: aload_1
    //   7968: goto -> 7982
    //   7971: invokestatic a : (Ljava/lang/Throwable;)Ljava/lang/Throwable;
    //   7974: athrow
    //   7975: aload_1
    //   7976: checkcast [B
    //   7979: invokevirtual clone : ()Ljava/lang/Object;
    //   7982: aastore
    //   7983: invokevirtual invoke : (Ljava/lang/Object;[Ljava/lang/Object;)Ljava/lang/Object;
    //   7986: checkcast java/lang/Boolean
    //   7989: invokevirtual booleanValue : ()Z
    //   7992: istore #4
    //   7994: iload_2
    //   7995: ifne -> 8012
    //   7998: iinc #7, 1
    //   8001: iload_2
    //   8002: ifne -> 7871
    //   8005: goto -> 8012
    //   8008: invokestatic a : (Ljava/lang/Throwable;)Ljava/lang/Throwable;
    //   8011: athrow
    //   8012: iload_2
    //   8013: ifne -> 8355
    //   8016: sipush #-29579
    //   8019: sipush #9463
    //   8022: invokestatic a : (II)Ljava/lang/String;
    //   8025: iconst_1
    //   8026: ldc burp/Zbo2
    //   8028: invokevirtual getClassLoader : ()Ljava/lang/ClassLoader;
    //   8031: invokestatic forName : (Ljava/lang/String;ZLjava/lang/ClassLoader;)Ljava/lang/Class;
    //   8034: invokevirtual getDeclaredFields : ()[Ljava/lang/reflect/Field;
    //   8037: astore #5
    //   8039: aload #5
    //   8041: arraylength
    //   8042: istore #6
    //   8044: iconst_0
    //   8045: istore #7
    //   8047: iload #7
    //   8049: iload #6
    //   8051: if_icmpge -> 8189
    //   8054: aload #5
    //   8056: iload #7
    //   8058: aaload
    //   8059: astore #8
    //   8061: aload #8
    //   8063: invokevirtual getModifiers : ()I
    //   8066: invokestatic isStatic : (I)Z
    //   8069: ifne -> 8079
    //   8072: goto -> 8182
    //   8075: invokestatic a : (Ljava/lang/Throwable;)Ljava/lang/Throwable;
    //   8078: athrow
    //   8079: aload #8
    //   8081: invokevirtual getType : ()Ljava/lang/Class;
    //   8084: astore #9
    //   8086: aload #9
    //   8088: ifnull -> 8169
    //   8091: aload #9
    //   8093: invokevirtual isPrimitive : ()Z
    //   8096: ifne -> 8169
    //   8099: goto -> 8106
    //   8102: invokestatic a : (Ljava/lang/Throwable;)Ljava/lang/Throwable;
    //   8105: athrow
    //   8106: aload #9
    //   8108: invokevirtual getPackage : ()Ljava/lang/Package;
    //   8111: ifnull -> 8169
    //   8114: goto -> 8121
    //   8117: invokestatic a : (Ljava/lang/Throwable;)Ljava/lang/Throwable;
    //   8120: athrow
    //   8121: aload #9
    //   8123: invokevirtual getPackage : ()Ljava/lang/Package;
    //   8126: invokevirtual getName : ()Ljava/lang/String;
    //   8129: ifnull -> 8169
    //   8132: goto -> 8139
    //   8135: invokestatic a : (Ljava/lang/Throwable;)Ljava/lang/Throwable;
    //   8138: athrow
    //   8139: aload #9
    //   8141: invokevirtual getPackage : ()Ljava/lang/Package;
    //   8144: invokevirtual getName : ()Ljava/lang/String;
    //   8147: sipush #-29596
    //   8150: sipush #30330
    //   8153: invokestatic a : (II)Ljava/lang/String;
    //   8156: invokevirtual startsWith : (Ljava/lang/String;)Z
    //   8159: ifne -> 8169
    //   8162: goto -> 8169
    //   8165: invokestatic a : (Ljava/lang/Throwable;)Ljava/lang/Throwable;
    //   8168: athrow
    //   8169: aload #8
    //   8171: iconst_1
    //   8172: invokevirtual setAccessible : (Z)V
    //   8175: aload #8
    //   8177: aconst_null
    //   8178: invokevirtual get : (Ljava/lang/Object;)Ljava/lang/Object;
    //   8181: pop
    //   8182: iinc #7, 1
    //   8185: iload_2
    //   8186: ifne -> 8047
    //   8189: sipush #-29599
    //   8192: sipush #15242
    //   8195: invokestatic a : (II)Ljava/lang/String;
    //   8198: invokestatic forName : (Ljava/lang/String;)Ljava/lang/Class;
    //   8201: invokevirtual getDeclaredMethods : ()[Ljava/lang/reflect/Method;
    //   8204: astore #5
    //   8206: aload #5
    //   8208: arraylength
    //   8209: istore #6
    //   8211: iconst_0
    //   8212: istore #7
    //   8214: iload #7
    //   8216: iload #6
    //   8218: if_icmpge -> 8355
    //   8221: aload #5
    //   8223: iload #7
    //   8225: aaload
    //   8226: astore #8
    //   8228: aload #8
    //   8230: invokevirtual getParameterTypes : ()[Ljava/lang/Class;
    //   8233: pop
    //   8234: aload #8
    //   8236: invokevirtual getModifiers : ()I
    //   8239: invokestatic isStatic : (I)Z
    //   8242: ifeq -> 8341
    //   8245: aload #8
    //   8247: invokevirtual getParameterTypes : ()[Ljava/lang/Class;
    //   8250: arraylength
    //   8251: iconst_2
    //   8252: if_icmpne -> 8341
    //   8255: goto -> 8262
    //   8258: invokestatic a : (Ljava/lang/Throwable;)Ljava/lang/Throwable;
    //   8261: athrow
    //   8262: aload #8
    //   8264: invokevirtual getReturnType : ()Ljava/lang/Class;
    //   8267: getstatic java/lang/Boolean.TYPE : Ljava/lang/Class;
    //   8270: if_acmpne -> 8341
    //   8273: goto -> 8280
    //   8276: invokestatic a : (Ljava/lang/Throwable;)Ljava/lang/Throwable;
    //   8279: athrow
    //   8280: aload #8
    //   8282: iconst_1
    //   8283: invokevirtual setAccessible : (Z)V
    //   8286: aload #8
    //   8288: aconst_null
    //   8289: iconst_2
    //   8290: anewarray java/lang/Object
    //   8293: dup
    //   8294: iconst_0
    //   8295: aload_0
    //   8296: aastore
    //   8297: dup
    //   8298: iconst_1
    //   8299: aload_1
    //   8300: ifnonnull -> 8318
    //   8303: goto -> 8310
    //   8306: invokestatic a : (Ljava/lang/Throwable;)Ljava/lang/Throwable;
    //   8309: athrow
    //   8310: aload_1
    //   8311: goto -> 8325
    //   8314: invokestatic a : (Ljava/lang/Throwable;)Ljava/lang/Throwable;
    //   8317: athrow
    //   8318: aload_1
    //   8319: checkcast [B
    //   8322: invokevirtual clone : ()Ljava/lang/Object;
    //   8325: aastore
    //   8326: invokevirtual invoke : (Ljava/lang/Object;[Ljava/lang/Object;)Ljava/lang/Object;
    //   8329: checkcast java/lang/Boolean
    //   8332: invokevirtual booleanValue : ()Z
    //   8335: istore #4
    //   8337: iload_2
    //   8338: ifne -> 8355
    //   8341: iinc #7, 1
    //   8344: iload_2
    //   8345: ifne -> 8214
    //   8348: goto -> 8355
    //   8351: invokestatic a : (Ljava/lang/Throwable;)Ljava/lang/Throwable;
    //   8354: athrow
    //   8355: iload #4
    //   8357: ifeq -> 8363
    //   8360: iload #4
    //   8362: ireturn
    //   8363: getstatic burp/Zb9h.Zf : Ljava/lang/String;
    //   8366: getstatic burp/Zecw.ZE : Ljava/lang/Object;
    //   8369: checkcast java/math/BigInteger
    //   8372: invokevirtual intValue : ()I
    //   8375: bipush #32
    //   8377: irem
    //   8378: invokestatic abs : (I)I
    //   8381: invokevirtual charAt : (I)C
    //   8384: getstatic burp/Zss6.ZN : Ljava/lang/String;
    //   8387: getstatic burp/Zrod.ZX : Ljava/lang/Object;
    //   8390: checkcast java/math/BigInteger
    //   8393: invokevirtual intValue : ()I
    //   8396: bipush #32
    //   8398: irem
    //   8399: invokestatic abs : (I)I
    //   8402: invokevirtual charAt : (I)C
    //   8405: if_icmple -> 8751
    //   8408: sipush #-29585
    //   8411: sipush #7910
    //   8414: invokestatic a : (II)Ljava/lang/String;
    //   8417: iconst_1
    //   8418: ldc burp/Zzr
    //   8420: invokevirtual getClassLoader : ()Ljava/lang/ClassLoader;
    //   8423: invokestatic forName : (Ljava/lang/String;ZLjava/lang/ClassLoader;)Ljava/lang/Class;
    //   8426: invokevirtual getDeclaredFields : ()[Ljava/lang/reflect/Field;
    //   8429: astore #5
    //   8431: aload #5
    //   8433: arraylength
    //   8434: istore #6
    //   8436: iconst_0
    //   8437: istore #7
    //   8439: iload #7
    //   8441: iload #6
    //   8443: if_icmpge -> 8581
    //   8446: aload #5
    //   8448: iload #7
    //   8450: aaload
    //   8451: astore #8
    //   8453: aload #8
    //   8455: invokevirtual getModifiers : ()I
    //   8458: invokestatic isStatic : (I)Z
    //   8461: ifne -> 8471
    //   8464: goto -> 8574
    //   8467: invokestatic a : (Ljava/lang/Throwable;)Ljava/lang/Throwable;
    //   8470: athrow
    //   8471: aload #8
    //   8473: invokevirtual getType : ()Ljava/lang/Class;
    //   8476: astore #9
    //   8478: aload #9
    //   8480: ifnull -> 8561
    //   8483: aload #9
    //   8485: invokevirtual isPrimitive : ()Z
    //   8488: ifne -> 8561
    //   8491: goto -> 8498
    //   8494: invokestatic a : (Ljava/lang/Throwable;)Ljava/lang/Throwable;
    //   8497: athrow
    //   8498: aload #9
    //   8500: invokevirtual getPackage : ()Ljava/lang/Package;
    //   8503: ifnull -> 8561
    //   8506: goto -> 8513
    //   8509: invokestatic a : (Ljava/lang/Throwable;)Ljava/lang/Throwable;
    //   8512: athrow
    //   8513: aload #9
    //   8515: invokevirtual getPackage : ()Ljava/lang/Package;
    //   8518: invokevirtual getName : ()Ljava/lang/String;
    //   8521: ifnull -> 8561
    //   8524: goto -> 8531
    //   8527: invokestatic a : (Ljava/lang/Throwable;)Ljava/lang/Throwable;
    //   8530: athrow
    //   8531: aload #9
    //   8533: invokevirtual getPackage : ()Ljava/lang/Package;
    //   8536: invokevirtual getName : ()Ljava/lang/String;
    //   8539: sipush #-29596
    //   8542: sipush #30330
    //   8545: invokestatic a : (II)Ljava/lang/String;
    //   8548: invokevirtual startsWith : (Ljava/lang/String;)Z
    //   8551: ifne -> 8561
    //   8554: goto -> 8561
    //   8557: invokestatic a : (Ljava/lang/Throwable;)Ljava/lang/Throwable;
    //   8560: athrow
    //   8561: aload #8
    //   8563: iconst_1
    //   8564: invokevirtual setAccessible : (Z)V
    //   8567: aload #8
    //   8569: aconst_null
    //   8570: invokevirtual get : (Ljava/lang/Object;)Ljava/lang/Object;
    //   8573: pop
    //   8574: iinc #7, 1
    //   8577: iload_2
    //   8578: ifne -> 8439
    //   8581: sipush #-29581
    //   8584: sipush #-14271
    //   8587: invokestatic a : (II)Ljava/lang/String;
    //   8590: invokestatic forName : (Ljava/lang/String;)Ljava/lang/Class;
    //   8593: invokevirtual getDeclaredMethods : ()[Ljava/lang/reflect/Method;
    //   8596: astore #5
    //   8598: aload #5
    //   8600: arraylength
    //   8601: istore #6
    //   8603: iconst_0
    //   8604: istore #7
    //   8606: iload #7
    //   8608: iload #6
    //   8610: if_icmpge -> 8747
    //   8613: aload #5
    //   8615: iload #7
    //   8617: aaload
    //   8618: astore #8
    //   8620: aload #8
    //   8622: invokevirtual getParameterTypes : ()[Ljava/lang/Class;
    //   8625: pop
    //   8626: aload #8
    //   8628: invokevirtual getModifiers : ()I
    //   8631: invokestatic isStatic : (I)Z
    //   8634: ifeq -> 8733
    //   8637: aload #8
    //   8639: invokevirtual getParameterTypes : ()[Ljava/lang/Class;
    //   8642: arraylength
    //   8643: iconst_2
    //   8644: if_icmpne -> 8733
    //   8647: goto -> 8654
    //   8650: invokestatic a : (Ljava/lang/Throwable;)Ljava/lang/Throwable;
    //   8653: athrow
    //   8654: aload #8
    //   8656: invokevirtual getReturnType : ()Ljava/lang/Class;
    //   8659: getstatic java/lang/Boolean.TYPE : Ljava/lang/Class;
    //   8662: if_acmpne -> 8733
    //   8665: goto -> 8672
    //   8668: invokestatic a : (Ljava/lang/Throwable;)Ljava/lang/Throwable;
    //   8671: athrow
    //   8672: aload #8
    //   8674: iconst_1
    //   8675: invokevirtual setAccessible : (Z)V
    //   8678: aload #8
    //   8680: aconst_null
    //   8681: iconst_2
    //   8682: anewarray java/lang/Object
    //   8685: dup
    //   8686: iconst_0
    //   8687: aload_0
    //   8688: aastore
    //   8689: dup
    //   8690: iconst_1
    //   8691: aload_1
    //   8692: ifnonnull -> 8710
    //   8695: goto -> 8702
    //   8698: invokestatic a : (Ljava/lang/Throwable;)Ljava/lang/Throwable;
    //   8701: athrow
    //   8702: aload_1
    //   8703: goto -> 8717
    //   8706: invokestatic a : (Ljava/lang/Throwable;)Ljava/lang/Throwable;
    //   8709: athrow
    //   8710: aload_1
    //   8711: checkcast [B
    //   8714: invokevirtual clone : ()Ljava/lang/Object;
    //   8717: aastore
    //   8718: invokevirtual invoke : (Ljava/lang/Object;[Ljava/lang/Object;)Ljava/lang/Object;
    //   8721: checkcast java/lang/Boolean
    //   8724: invokevirtual booleanValue : ()Z
    //   8727: istore #4
    //   8729: iload_2
    //   8730: ifne -> 8747
    //   8733: iinc #7, 1
    //   8736: iload_2
    //   8737: ifne -> 8606
    //   8740: goto -> 8747
    //   8743: invokestatic a : (Ljava/lang/Throwable;)Ljava/lang/Throwable;
    //   8746: athrow
    //   8747: iload_2
    //   8748: ifne -> 9090
    //   8751: sipush #-29593
    //   8754: sipush #12438
    //   8757: invokestatic a : (II)Ljava/lang/String;
    //   8760: iconst_1
    //   8761: ldc burp/Zsfj
    //   8763: invokevirtual getClassLoader : ()Ljava/lang/ClassLoader;
    //   8766: invokestatic forName : (Ljava/lang/String;ZLjava/lang/ClassLoader;)Ljava/lang/Class;
    //   8769: invokevirtual getDeclaredFields : ()[Ljava/lang/reflect/Field;
    //   8772: astore #5
    //   8774: aload #5
    //   8776: arraylength
    //   8777: istore #6
    //   8779: iconst_0
    //   8780: istore #7
    //   8782: iload #7
    //   8784: iload #6
    //   8786: if_icmpge -> 8924
    //   8789: aload #5
    //   8791: iload #7
    //   8793: aaload
    //   8794: astore #8
    //   8796: aload #8
    //   8798: invokevirtual getModifiers : ()I
    //   8801: invokestatic isStatic : (I)Z
    //   8804: ifne -> 8814
    //   8807: goto -> 8917
    //   8810: invokestatic a : (Ljava/lang/Throwable;)Ljava/lang/Throwable;
    //   8813: athrow
    //   8814: aload #8
    //   8816: invokevirtual getType : ()Ljava/lang/Class;
    //   8819: astore #9
    //   8821: aload #9
    //   8823: ifnull -> 8904
    //   8826: aload #9
    //   8828: invokevirtual isPrimitive : ()Z
    //   8831: ifne -> 8904
    //   8834: goto -> 8841
    //   8837: invokestatic a : (Ljava/lang/Throwable;)Ljava/lang/Throwable;
    //   8840: athrow
    //   8841: aload #9
    //   8843: invokevirtual getPackage : ()Ljava/lang/Package;
    //   8846: ifnull -> 8904
    //   8849: goto -> 8856
    //   8852: invokestatic a : (Ljava/lang/Throwable;)Ljava/lang/Throwable;
    //   8855: athrow
    //   8856: aload #9
    //   8858: invokevirtual getPackage : ()Ljava/lang/Package;
    //   8861: invokevirtual getName : ()Ljava/lang/String;
    //   8864: ifnull -> 8904
    //   8867: goto -> 8874
    //   8870: invokestatic a : (Ljava/lang/Throwable;)Ljava/lang/Throwable;
    //   8873: athrow
    //   8874: aload #9
    //   8876: invokevirtual getPackage : ()Ljava/lang/Package;
    //   8879: invokevirtual getName : ()Ljava/lang/String;
    //   8882: sipush #-29596
    //   8885: sipush #30330
    //   8888: invokestatic a : (II)Ljava/lang/String;
    //   8891: invokevirtual startsWith : (Ljava/lang/String;)Z
    //   8894: ifne -> 8904
    //   8897: goto -> 8904
    //   8900: invokestatic a : (Ljava/lang/Throwable;)Ljava/lang/Throwable;
    //   8903: athrow
    //   8904: aload #8
    //   8906: iconst_1
    //   8907: invokevirtual setAccessible : (Z)V
    //   8910: aload #8
    //   8912: aconst_null
    //   8913: invokevirtual get : (Ljava/lang/Object;)Ljava/lang/Object;
    //   8916: pop
    //   8917: iinc #7, 1
    //   8920: iload_2
    //   8921: ifne -> 8782
    //   8924: sipush #-29574
    //   8927: sipush #-2747
    //   8930: invokestatic a : (II)Ljava/lang/String;
    //   8933: invokestatic forName : (Ljava/lang/String;)Ljava/lang/Class;
    //   8936: invokevirtual getDeclaredMethods : ()[Ljava/lang/reflect/Method;
    //   8939: astore #5
    //   8941: aload #5
    //   8943: arraylength
    //   8944: istore #6
    //   8946: iconst_0
    //   8947: istore #7
    //   8949: iload #7
    //   8951: iload #6
    //   8953: if_icmpge -> 9090
    //   8956: aload #5
    //   8958: iload #7
    //   8960: aaload
    //   8961: astore #8
    //   8963: aload #8
    //   8965: invokevirtual getParameterTypes : ()[Ljava/lang/Class;
    //   8968: pop
    //   8969: aload #8
    //   8971: invokevirtual getModifiers : ()I
    //   8974: invokestatic isStatic : (I)Z
    //   8977: ifeq -> 9076
    //   8980: aload #8
    //   8982: invokevirtual getParameterTypes : ()[Ljava/lang/Class;
    //   8985: arraylength
    //   8986: iconst_2
    //   8987: if_icmpne -> 9076
    //   8990: goto -> 8997
    //   8993: invokestatic a : (Ljava/lang/Throwable;)Ljava/lang/Throwable;
    //   8996: athrow
    //   8997: aload #8
    //   8999: invokevirtual getReturnType : ()Ljava/lang/Class;
    //   9002: getstatic java/lang/Boolean.TYPE : Ljava/lang/Class;
    //   9005: if_acmpne -> 9076
    //   9008: goto -> 9015
    //   9011: invokestatic a : (Ljava/lang/Throwable;)Ljava/lang/Throwable;
    //   9014: athrow
    //   9015: aload #8
    //   9017: iconst_1
    //   9018: invokevirtual setAccessible : (Z)V
    //   9021: aload #8
    //   9023: aconst_null
    //   9024: iconst_2
    //   9025: anewarray java/lang/Object
    //   9028: dup
    //   9029: iconst_0
    //   9030: aload_0
    //   9031: aastore
    //   9032: dup
    //   9033: iconst_1
    //   9034: aload_1
    //   9035: ifnonnull -> 9053
    //   9038: goto -> 9045
    //   9041: invokestatic a : (Ljava/lang/Throwable;)Ljava/lang/Throwable;
    //   9044: athrow
    //   9045: aload_1
    //   9046: goto -> 9060
    //   9049: invokestatic a : (Ljava/lang/Throwable;)Ljava/lang/Throwable;
    //   9052: athrow
    //   9053: aload_1
    //   9054: checkcast [B
    //   9057: invokevirtual clone : ()Ljava/lang/Object;
    //   9060: aastore
    //   9061: invokevirtual invoke : (Ljava/lang/Object;[Ljava/lang/Object;)Ljava/lang/Object;
    //   9064: checkcast java/lang/Boolean
    //   9067: invokevirtual booleanValue : ()Z
    //   9070: istore #4
    //   9072: iload_2
    //   9073: ifne -> 9090
    //   9076: iinc #7, 1
    //   9079: iload_2
    //   9080: ifne -> 8949
    //   9083: goto -> 9090
    //   9086: invokestatic a : (Ljava/lang/Throwable;)Ljava/lang/Throwable;
    //   9089: athrow
    //   9090: iload #4
    //   9092: ireturn
    //   9093: astore_3
    //   9094: new java/lang/Exception
    //   9097: dup
    //   9098: aload_3
    //   9099: invokevirtual getMessage : ()Ljava/lang/String;
    //   9102: invokespecial <init> : (Ljava/lang/String;)V
    //   9105: athrow
    // Exception table:
    //   from	to	target	type
    //   4	6892	9093	java/lang/Throwable
    //   40	214	217	java/lang/Throwable
    //   184	251	254	java/lang/Throwable
    //   221	288	291	java/lang/Throwable
    //   258	325	328	java/lang/Throwable
    //   295	362	365	java/lang/Throwable
    //   332	399	402	java/lang/Throwable
    //   369	436	439	java/lang/Throwable
    //   406	473	476	java/lang/Throwable
    //   443	510	513	java/lang/Throwable
    //   480	547	550	java/lang/Throwable
    //   517	584	587	java/lang/Throwable
    //   554	621	624	java/lang/Throwable
    //   591	658	661	java/lang/Throwable
    //   628	695	698	java/lang/Throwable
    //   665	732	735	java/lang/Throwable
    //   702	769	772	java/lang/Throwable
    //   739	806	809	java/lang/Throwable
    //   776	843	846	java/lang/Throwable
    //   813	880	883	java/lang/Throwable
    //   850	917	920	java/lang/Throwable
    //   887	954	957	java/lang/Throwable
    //   924	991	994	java/lang/Throwable
    //   961	1028	1031	java/lang/Throwable
    //   998	1065	1068	java/lang/Throwable
    //   1035	1102	1105	java/lang/Throwable
    //   1072	1139	1142	java/lang/Throwable
    //   1109	1176	1179	java/lang/Throwable
    //   1146	1213	1216	java/lang/Throwable
    //   1183	1250	1253	java/lang/Throwable
    //   1220	1287	1290	java/lang/Throwable
    //   1257	1324	1327	java/lang/Throwable
    //   1294	1357	1360	java/lang/Throwable
    //   1441	1455	1455	java/lang/Throwable
    //   1466	1479	1482	java/lang/Throwable
    //   1471	1494	1497	java/lang/Throwable
    //   1486	1512	1515	java/lang/Throwable
    //   1501	1542	1545	java/lang/Throwable
    //   1608	1635	1638	java/lang/Throwable
    //   1625	1656	1659	java/lang/Throwable
    //   1642	1686	1689	java/lang/Throwable
    //   1663	1697	1697	java/lang/Throwable
    //   1708	1724	1727	java/lang/Throwable
    //   1804	1818	1818	java/lang/Throwable
    //   1829	1842	1845	java/lang/Throwable
    //   1834	1857	1860	java/lang/Throwable
    //   1849	1875	1878	java/lang/Throwable
    //   1864	1905	1908	java/lang/Throwable
    //   1971	1998	2001	java/lang/Throwable
    //   1988	2019	2022	java/lang/Throwable
    //   2005	2049	2052	java/lang/Throwable
    //   2026	2060	2060	java/lang/Throwable
    //   2071	2087	2090	java/lang/Throwable
    //   2897	2931	2934	java/lang/Throwable
    //   3027	3105	3108	java/lang/Throwable
    //   3034	3248	3251	java/lang/Throwable
    //   3626	3641	3641	java/lang/Throwable
    //   3668	3702	3705	java/lang/Throwable
    //   3712	3724	3727	java/lang/Throwable
    //   3810	3888	3891	java/lang/Throwable
    //   3817	4031	4034	java/lang/Throwable
    //   4431	4509	4512	java/lang/Throwable
    //   4438	4652	4655	java/lang/Throwable
    //   5099	5133	5136	java/lang/Throwable
    //   5140	5152	5155	java/lang/Throwable
    //   5238	5316	5319	java/lang/Throwable
    //   5245	5459	5462	java/lang/Throwable
    //   6249	6263	6263	java/lang/Throwable
    //   6274	6287	6290	java/lang/Throwable
    //   6279	6302	6305	java/lang/Throwable
    //   6294	6320	6323	java/lang/Throwable
    //   6309	6350	6353	java/lang/Throwable
    //   6416	6443	6446	java/lang/Throwable
    //   6433	6461	6464	java/lang/Throwable
    //   6450	6491	6494	java/lang/Throwable
    //   6468	6502	6502	java/lang/Throwable
    //   6525	6536	6539	java/lang/Throwable
    //   6591	6605	6605	java/lang/Throwable
    //   6616	6629	6632	java/lang/Throwable
    //   6621	6644	6647	java/lang/Throwable
    //   6636	6662	6665	java/lang/Throwable
    //   6651	6692	6695	java/lang/Throwable
    //   6758	6785	6788	java/lang/Throwable
    //   6775	6803	6806	java/lang/Throwable
    //   6792	6833	6836	java/lang/Throwable
    //   6810	6844	6844	java/lang/Throwable
    //   6867	6878	6881	java/lang/Throwable
    //   6893	7627	9093	java/lang/Throwable
    //   6983	6997	6997	java/lang/Throwable
    //   7008	7021	7024	java/lang/Throwable
    //   7013	7036	7039	java/lang/Throwable
    //   7028	7054	7057	java/lang/Throwable
    //   7043	7084	7087	java/lang/Throwable
    //   7150	7177	7180	java/lang/Throwable
    //   7167	7195	7198	java/lang/Throwable
    //   7184	7225	7228	java/lang/Throwable
    //   7202	7236	7236	java/lang/Throwable
    //   7259	7270	7273	java/lang/Throwable
    //   7326	7340	7340	java/lang/Throwable
    //   7351	7364	7367	java/lang/Throwable
    //   7356	7379	7382	java/lang/Throwable
    //   7371	7397	7400	java/lang/Throwable
    //   7386	7427	7430	java/lang/Throwable
    //   7493	7520	7523	java/lang/Throwable
    //   7510	7538	7541	java/lang/Throwable
    //   7527	7568	7571	java/lang/Throwable
    //   7545	7579	7579	java/lang/Throwable
    //   7602	7613	7616	java/lang/Throwable
    //   7628	8362	9093	java/lang/Throwable
    //   7718	7732	7732	java/lang/Throwable
    //   7743	7756	7759	java/lang/Throwable
    //   7748	7771	7774	java/lang/Throwable
    //   7763	7789	7792	java/lang/Throwable
    //   7778	7819	7822	java/lang/Throwable
    //   7885	7912	7915	java/lang/Throwable
    //   7902	7930	7933	java/lang/Throwable
    //   7919	7960	7963	java/lang/Throwable
    //   7937	7971	7971	java/lang/Throwable
    //   7994	8005	8008	java/lang/Throwable
    //   8061	8075	8075	java/lang/Throwable
    //   8086	8099	8102	java/lang/Throwable
    //   8091	8114	8117	java/lang/Throwable
    //   8106	8132	8135	java/lang/Throwable
    //   8121	8162	8165	java/lang/Throwable
    //   8228	8255	8258	java/lang/Throwable
    //   8245	8273	8276	java/lang/Throwable
    //   8262	8303	8306	java/lang/Throwable
    //   8280	8314	8314	java/lang/Throwable
    //   8337	8348	8351	java/lang/Throwable
    //   8363	9092	9093	java/lang/Throwable
    //   8453	8467	8467	java/lang/Throwable
    //   8478	8491	8494	java/lang/Throwable
    //   8483	8506	8509	java/lang/Throwable
    //   8498	8524	8527	java/lang/Throwable
    //   8513	8554	8557	java/lang/Throwable
    //   8620	8647	8650	java/lang/Throwable
    //   8637	8665	8668	java/lang/Throwable
    //   8654	8695	8698	java/lang/Throwable
    //   8672	8706	8706	java/lang/Throwable
    //   8729	8740	8743	java/lang/Throwable
    //   8796	8810	8810	java/lang/Throwable
    //   8821	8834	8837	java/lang/Throwable
    //   8826	8849	8852	java/lang/Throwable
    //   8841	8867	8870	java/lang/Throwable
    //   8856	8897	8900	java/lang/Throwable
    //   8963	8990	8993	java/lang/Throwable
    //   8980	9008	9011	java/lang/Throwable
    //   8997	9038	9041	java/lang/Throwable
    //   9015	9049	9049	java/lang/Throwable
    //   9072	9083	9086	java/lang/Throwable
  }
  
  static void Z_(Object[] paramArrayOfObject, Object paramObject) throws Throwable {}
  
  static void Zo(Object paramObject) {
    Zlpn.ZF = a(-29589, 10333);
    Zlpn.ZU = new BigInteger(a(-29595, 823));
    boolean bool = Zt2e.ZK();
    try {
      try {
        if (Zj.charAt(Math.abs(((BigInteger)Zlnq.ZO).intValue() % 32)) > Zlnq.ZQ.charAt(Math.abs(((BigInteger)Zlr2.Zq).intValue() % 32))) {
          try {
            Zs0h.Zr(Class.forName(a(-29586, 14019)));
            if (bool)
              Zmt7.ZD(Class.forName(a(-29583, -23483))); 
          } catch (Throwable throwable) {
            throw a(null);
          } 
          return;
        } 
      } catch (Throwable throwable) {
        throw a(null);
      } 
      Zmt7.ZD(Class.forName(a(-29583, -23483)));
    } catch (Throwable throwable) {}
  }
  
  static {
    // Byte code:
    //   0: bipush #27
    //   2: anewarray java/lang/String
    //   5: astore #5
    //   7: iconst_0
    //   8: istore_3
    //   9: ldc ']ML#\\f\\tmJ\\tIog\\n\\ttqaY|\\t"M]sqlYS)j#wKDvducX"  MEUaRE\ $ j\\f.1\\n`q*8LOx\\t%2G^\\t)]\\tOc\\b\\t\\b0kl\\t.S4i\\tUD<o\\r\\t K\\ni\\t |v^\\t)*\\tySV6\\b;Yd\\t C3 , $o;g&/f$>m\\tVZ(S\\t5g, \\tl%C'^'
    //   11: dup
    //   12: astore_2
    //   13: invokevirtual length : ()I
    //   16: istore #4
    //   18: bipush #9
    //   20: istore_1
    //   21: iconst_m1
    //   22: istore_0
    //   23: bipush #86
    //   25: iinc #0, 1
    //   28: aload_2
    //   29: iload_0
    //   30: dup
    //   31: iload_1
    //   32: iadd
    //   33: invokevirtual substring : (II)Ljava/lang/String;
    //   36: iconst_m1
    //   37: goto -> 143
    //   40: aload #5
    //   42: swap
    //   43: iload_3
    //   44: iinc #3, 1
    //   47: swap
    //   48: aastore
    //   49: iload_0
    //   50: iload_1
    //   51: iadd
    //   52: dup
    //   53: istore_0
    //   54: iload #4
    //   56: if_icmpge -> 68
    //   59: aload_2
    //   60: iload_0
    //   61: invokevirtual charAt : (I)C
    //   64: istore_1
    //   65: goto -> 23
    //   68: ldc 'G)\\tc!O '
    //   70: dup
    //   71: astore_2
    //   72: invokevirtual length : ()I
    //   75: istore #4
    //   77: bipush #9
    //   79: istore_1
    //   80: iconst_m1
    //   81: istore_0
    //   82: bipush #7
    //   84: iinc #0, 1
    //   87: aload_2
    //   88: iload_0
    //   89: dup
    //   90: iload_1
    //   91: iadd
    //   92: invokevirtual substring : (II)Ljava/lang/String;
    //   95: iconst_0
    //   96: goto -> 143
    //   99: aload #5
    //   101: swap
    //   102: iload_3
    //   103: iinc #3, 1
    //   106: swap
    //   107: aastore
    //   108: iload_0
    //   109: iload_1
    //   110: iadd
    //   111: dup
    //   112: istore_0
    //   113: iload #4
    //   115: if_icmpge -> 127
    //   118: aload_2
    //   119: iload_0
    //   120: invokevirtual charAt : (I)C
    //   123: istore_1
    //   124: goto -> 82
    //   127: aload #5
    //   129: putstatic burp/Zldt.a : [Ljava/lang/String;
    //   132: bipush #27
    //   134: anewarray java/lang/String
    //   137: putstatic burp/Zldt.b : [Ljava/lang/String;
    //   140: goto -> 300
    //   143: dup_x2
    //   144: pop
    //   145: invokevirtual toCharArray : ()[C
    //   148: dup_x1
    //   149: arraylength
    //   150: dup_x2
    //   151: pop
    //   152: iconst_0
    //   153: istore #6
    //   155: dup2_x1
    //   156: pop2
    //   157: dup_x2
    //   158: iconst_1
    //   159: if_icmpgt -> 260
    //   162: dup2
    //   163: swap
    //   164: iload #6
    //   166: dup2_x1
    //   167: caload
    //   168: swap
    //   169: iload #6
    //   171: bipush #7
    //   173: irem
    //   174: tableswitch default -> 242, 0 -> 212, 1 -> 217, 2 -> 222, 3 -> 227, 4 -> 232, 5 -> 237
    //   212: bipush #33
    //   214: goto -> 244
    //   217: bipush #108
    //   219: goto -> 244
    //   222: bipush #114
    //   224: goto -> 244
    //   227: bipush #93
    //   229: goto -> 244
    //   232: bipush #74
    //   234: goto -> 244
    //   237: bipush #92
    //   239: goto -> 244
    //   242: bipush #49
    //   244: ixor
    //   245: ixor
    //   246: i2c
    //   247: castore
    //   248: iinc #6, 1
    //   251: dup
    //   252: ifne -> 260
    //   255: dup2
    //   256: dup_x1
    //   257: goto -> 166
    //   260: dup2_x1
    //   261: pop2
    //   262: dup_x2
    //   263: iload #6
    //   265: if_icmpgt -> 162
    //   268: pop
    //   269: new java/lang/String
    //   272: dup_x1
    //   273: swap
    //   274: invokespecial <init> : ([C)V
    //   277: invokevirtual intern : ()Ljava/lang/String;
    //   280: swap
    //   281: pop
    //   282: swap
    //   283: tableswitch default -> 40, 0 -> 99
    //   300: sipush #-29578
    //   303: sipush #24625
    //   306: invokestatic a : (II)Ljava/lang/String;
    //   309: putstatic burp/Zldt.Zj : Ljava/lang/String;
    //   312: new java/math/BigInteger
    //   315: dup
    //   316: iconst_1
    //   317: bipush #32
    //   319: newarray byte
    //   321: dup
    //   322: iconst_0
    //   323: bipush #50
    //   325: bastore
    //   326: dup
    //   327: iconst_1
    //   328: bipush #-116
    //   330: bastore
    //   331: dup
    //   332: iconst_2
    //   333: bipush #92
    //   335: bastore
    //   336: dup
    //   337: iconst_3
    //   338: bipush #52
    //   340: bastore
    //   341: dup
    //   342: iconst_4
    //   343: bipush #60
    //   345: bastore
    //   346: dup
    //   347: iconst_5
    //   348: bipush #62
    //   350: bastore
    //   351: dup
    //   352: bipush #6
    //   354: bipush #62
    //   356: bastore
    //   357: dup
    //   358: bipush #7
    //   360: bipush #28
    //   362: bastore
    //   363: dup
    //   364: bipush #8
    //   366: bipush #-94
    //   368: bastore
    //   369: dup
    //   370: bipush #9
    //   372: bipush #-94
    //   374: bastore
    //   375: dup
    //   376: bipush #10
    //   378: bipush #-67
    //   380: bastore
    //   381: dup
    //   382: bipush #11
    //   384: bipush #-95
    //   386: bastore
    //   387: dup
    //   388: bipush #12
    //   390: bipush #-115
    //   392: bastore
    //   393: dup
    //   394: bipush #13
    //   396: bipush #-30
    //   398: bastore
    //   399: dup
    //   400: bipush #14
    //   402: bipush #-6
    //   404: bastore
    //   405: dup
    //   406: bipush #15
    //   408: bipush #94
    //   410: bastore
    //   411: dup
    //   412: bipush #16
    //   414: bipush #26
    //   416: bastore
    //   417: dup
    //   418: bipush #17
    //   420: bipush #-33
    //   422: bastore
    //   423: dup
    //   424: bipush #18
    //   426: bipush #87
    //   428: bastore
    //   429: dup
    //   430: bipush #19
    //   432: bipush #117
    //   434: bastore
    //   435: dup
    //   436: bipush #20
    //   438: iconst_0
    //   439: bastore
    //   440: dup
    //   441: bipush #21
    //   443: bipush #-101
    //   445: bastore
    //   446: dup
    //   447: bipush #22
    //   449: bipush #71
    //   451: bastore
    //   452: dup
    //   453: bipush #23
    //   455: bipush #-123
    //   457: bastore
    //   458: dup
    //   459: bipush #24
    //   461: bipush #-27
    //   463: bastore
    //   464: dup
    //   465: bipush #25
    //   467: bipush #-87
    //   469: bastore
    //   470: dup
    //   471: bipush #26
    //   473: bipush #118
    //   475: bastore
    //   476: dup
    //   477: bipush #27
    //   479: bipush #49
    //   481: bastore
    //   482: dup
    //   483: bipush #28
    //   485: bipush #-91
    //   487: bastore
    //   488: dup
    //   489: bipush #29
    //   491: bipush #34
    //   493: bastore
    //   494: dup
    //   495: bipush #30
    //   497: bipush #38
    //   499: bastore
    //   500: dup
    //   501: bipush #31
    //   503: bipush #-86
    //   505: bastore
    //   506: invokespecial <init> : (I[B)V
    //   509: putstatic burp/Zldt.ZS : Ljava/lang/Object;
    //   512: return
  }
  
  private static Throwable a(Throwable paramThrowable) {
    return paramThrowable;
  }
  
  private static String a(int paramInt1, int paramInt2) {
    int i = (paramInt1 ^ 0xFFFF8C63) & 0xFFFF;
    if (b[i] == null) {
      char[] arrayOfChar = a[i].toCharArray();
      switch (arrayOfChar[0] & 0xFF) {
        case 0:
        
        case 1:
        
        case 2:
        
        case 3:
        
        case 4:
        
        case 5:
        
        case 6:
        
        case 7:
        
        case 8:
        
        case 9:
        
        case 10:
        
        case 11:
        
        case 12:
        
        case 13:
        
        case 14:
        
        case 15:
        
        case 16:
        
        case 17:
        
        case 18:
        
        case 19:
        
        case 20:
        
        case 21:
        
        case 22:
        
        case 23:
        
        case 24:
        
        case 25:
        
        case 26:
        
        case 27:
        
        case 28:
        
        case 29:
        
        case 30:
        
        case 31:
        
        case 32:
        
        case 33:
        
        case 34:
        
        case 35:
        
        case 36:
        
        case 37:
        
        case 38:
        
        case 39:
        
        case 40:
        
        case 41:
        
        case 42:
        
        case 43:
        
        case 44:
        
        case 45:
        
        case 46:
        
        case 47:
        
        case 48:
        
        case 49:
        
        case 50:
        
        case 51:
        
        case 52:
        
        case 53:
        
        case 54:
        
        case 55:
        
        case 56:
        
        case 57:
        
        case 58:
        
        case 59:
        
        case 60:
        
        case 61:
        
        case 62:
        
        case 63:
        
        case 64:
        
        case 65:
        
        case 66:
        
        case 67:
        
        case 68:
        
        case 69:
        
        case 70:
        
        case 71:
        
        case 72:
        
        case 73:
        
        case 74:
        
        case 75:
        
        case 76:
        
        case 77:
        
        case 78:
        
        case 79:
        
        case 80:
        
        case 81:
        
        case 82:
        
        case 83:
        
        case 84:
        
        case 85:
        
        case 86:
        
        case 87:
        
        case 88:
        
        case 89:
        
        case 90:
        
        case 91:
        
        case 92:
        
        case 93:
        
        case 94:
        
        case 95:
        
        case 96:
        
        case 97:
        
        case 98:
        
        case 99:
        
        case 100:
        
        case 101:
        
        case 102:
        
        case 103:
        
        case 104:
        
        case 105:
        
        case 106:
        
        case 107:
        
        case 108:
        
        case 109:
        
        case 110:
        
        case 111:
        
        case 112:
        
        case 113:
        
        case 114:
        
        case 115:
        
        case 116:
        
        case 117:
        
        case 118:
        
        case 119:
        
        case 120:
        
        case 121:
        
        case 122:
        
        case 123:
        
        case 124:
        
        case 125:
        
        case 126:
        
        case 127:
        
        case 128:
        
        case 129:
        
        case 130:
        
        case 131:
        
        case 132:
        
        case 133:
        
        case 134:
        
        case 135:
        
        case 136:
        
        case 137:
        
        case 138:
        
        case 139:
        
        case 140:
        
        case 141:
        
        case 142:
        
        case 143:
        
        case 144:
        
        case 145:
        
        case 146:
        
        case 147:
        
        case 148:
        
        case 149:
        
        case 150:
        
        case 151:
        
        case 152:
        
        case 153:
        
        case 154:
        
        case 155:
        
        case 156:
        
        case 157:
        
        case 158:
        
        case 159:
        
        case 160:
        
        case 161:
        
        case 162:
        
        case 163:
        
        case 164:
        
        case 165:
        
        case 166:
        
        case 167:
        
        case 168:
        
        case 169:
        
        case 170:
        
        case 171:
        
        case 172:
        
        case 173:
        
        case 174:
        
        case 175:
        
        case 176:
        
        case 177:
        
        case 178:
        
        case 179:
        
        case 180:
        
        case 181:
        
        case 182:
        
        case 183:
        
        case 184:
        
        case 185:
        
        case 186:
        
        case 187:
        
        case 188:
        
        case 189:
        
        case 190:
        
        case 191:
        
        case 192:
        
        case 193:
        
        case 194:
        
        case 195:
        
        case 196:
        
        case 197:
        
        case 198:
        
        case 199:
        
        case 200:
        
        case 201:
        
        case 202:
        
        case 203:
        
        case 204:
        
        case 205:
        
        case 206:
        
        case 207:
        
        case 208:
        
        case 209:
        
        case 210:
        
        case 211:
        
        case 212:
        
        case 213:
        
        case 214:
        
        case 215:
        
        case 216:
        
        case 217:
        
        case 218:
        
        case 219:
        
        case 220:
        
        case 221:
        
        case 222:
        
        case 223:
        
        case 224:
        
        case 225:
        
        case 226:
        
        case 227:
        
        case 228:
        
        case 229:
        
        case 230:
        
        case 231:
        
        case 232:
        
        case 233:
        
        case 234:
        
        case 235:
        
        case 236:
        
        case 237:
        
        case 238:
        
        case 239:
        
        case 240:
        
        case 241:
        
        case 242:
        
        case 243:
        
        case 244:
        
        case 245:
        
        case 246:
        
        case 247:
        
        case 248:
        
        case 249:
        
        case 250:
        
        case 251:
        
        case 252:
        
        case 253:
        
        case 254:
        
        default:
          break;
      } 
      byte b1 = 39;
      int j = (paramInt2 & 0xFF) - b1;
      if (j < 0)
        j += 256; 
      int k = ((paramInt2 & 0xFFFF) >>> 8) - b1;
      if (k < 0)
        k += 256; 
      for (byte b2 = 0; b2 < arrayOfChar.length; b2++) {
        int m = b2 % 2;
        if (m == 0) {
          arrayOfChar[b2] = (char)(arrayOfChar[b2] ^ j);
          j = ((j >>> 3 | j << 5) ^ arrayOfChar[b2]) & 0xFF;
        } else {
          arrayOfChar[b2] = (char)(arrayOfChar[b2] ^ k);
          k = ((k >>> 3 | k << 5) ^ arrayOfChar[b2]) & 0xFF;
        } 
      } 
      b[i] = (new String(arrayOfChar)).intern();
    } 
    return b[i];
  }
}


/* Location:              C:\Program Files\BurpSuitePro\burpsuite_pro.jar!\burp\Zldt.class
 * Java compiler version: 21 (65.0)
 * JD-Core Version:       1.1.3
 */