package burp;

import java.math.BigInteger;

class Zle9 extends ClassLoader {
  static Object ZI;
  
  static String Zm;
  
  private static final String[] a;
  
  private static final String[] b;
  
  static void ZE(Object paramObject) {
    Zb_1.Zc = a(22151, 8123);
    Zb_1.ZK = new BigInteger(a(22170, -31601));
    boolean bool = Zt2e.ZK();
    try {
      try {
        if (Ze8j.ZU.charAt(Math.abs(((BigInteger)Zrom.ZF).intValue() % 32)) > Zs3m.Zl.charAt(Math.abs(((BigInteger)Zmli.Zh).intValue() % 32))) {
          try {
            Zlgh.Zg(Class.forName(a(22175, -3285)));
            if (bool)
              Ztys.ZG(Class.forName(a(22174, 3877))); 
          } catch (Throwable throwable) {
            throw a(null);
          } 
          return;
        } 
      } catch (Throwable throwable) {
        throw a(null);
      } 
      Ztys.ZG(Class.forName(a(22174, 3877)));
    } catch (Throwable throwable) {}
  }
  
  static void Zb(Object[] paramArrayOfObject, Object paramObject) throws Throwable {}
  
  static boolean ZR(Object[] paramArrayOfObject, Object paramObject) throws Throwable {
    // Byte code:
    //   0: invokestatic ZN : ()Z
    //   3: istore_2
    //   4: new java/lang/StringBuilder
    //   7: dup
    //   8: invokespecial <init> : ()V
    //   11: astore_3
    //   12: iconst_0
    //   13: istore #4
    //   15: iload #4
    //   17: bipush #32
    //   19: if_icmpge -> 1355
    //   22: iload #4
    //   24: tableswitch default -> 1348, 0 -> 168, 1 -> 205, 2 -> 242, 3 -> 279, 4 -> 316, 5 -> 353, 6 -> 390, 7 -> 427, 8 -> 464, 9 -> 501, 10 -> 538, 11 -> 575, 12 -> 612, 13 -> 649, 14 -> 686, 15 -> 723, 16 -> 760, 17 -> 797, 18 -> 834, 19 -> 871, 20 -> 908, 21 -> 945, 22 -> 982, 23 -> 1019, 24 -> 1056, 25 -> 1093, 26 -> 1130, 27 -> 1167, 28 -> 1204, 29 -> 1241, 30 -> 1278, 31 -> 1315
    //   168: aload_3
    //   169: getstatic burp/Zzk_.ZX : Ljava/lang/String;
    //   172: getstatic burp/Zskf.ZQ : Ljava/lang/Object;
    //   175: checkcast java/math/BigInteger
    //   178: invokevirtual intValue : ()I
    //   181: bipush #32
    //   183: irem
    //   184: invokestatic abs : (I)I
    //   187: invokevirtual charAt : (I)C
    //   190: invokevirtual append : (C)Ljava/lang/StringBuilder;
    //   193: pop
    //   194: iload_2
    //   195: ifne -> 1348
    //   198: goto -> 205
    //   201: invokestatic a : (Ljava/lang/Throwable;)Ljava/lang/Throwable;
    //   204: athrow
    //   205: aload_3
    //   206: getstatic burp/Ze25.Zp : Ljava/lang/String;
    //   209: getstatic burp/Zrd2.Zt : Ljava/lang/Object;
    //   212: checkcast java/math/BigInteger
    //   215: invokevirtual intValue : ()I
    //   218: bipush #32
    //   220: irem
    //   221: invokestatic abs : (I)I
    //   224: invokevirtual charAt : (I)C
    //   227: invokevirtual append : (C)Ljava/lang/StringBuilder;
    //   230: pop
    //   231: iload_2
    //   232: ifne -> 1348
    //   235: goto -> 242
    //   238: invokestatic a : (Ljava/lang/Throwable;)Ljava/lang/Throwable;
    //   241: athrow
    //   242: aload_3
    //   243: getstatic burp/Zmdf.Zo : Ljava/lang/String;
    //   246: getstatic burp/Zrtp.Zy : Ljava/lang/Object;
    //   249: checkcast java/math/BigInteger
    //   252: invokevirtual intValue : ()I
    //   255: bipush #32
    //   257: irem
    //   258: invokestatic abs : (I)I
    //   261: invokevirtual charAt : (I)C
    //   264: invokevirtual append : (C)Ljava/lang/StringBuilder;
    //   267: pop
    //   268: iload_2
    //   269: ifne -> 1348
    //   272: goto -> 279
    //   275: invokestatic a : (Ljava/lang/Throwable;)Ljava/lang/Throwable;
    //   278: athrow
    //   279: aload_3
    //   280: getstatic burp/Zxxh.Zm : Ljava/lang/String;
    //   283: getstatic burp/Zrle.Zl : Ljava/lang/Object;
    //   286: checkcast java/math/BigInteger
    //   289: invokevirtual intValue : ()I
    //   292: bipush #32
    //   294: irem
    //   295: invokestatic abs : (I)I
    //   298: invokevirtual charAt : (I)C
    //   301: invokevirtual append : (C)Ljava/lang/StringBuilder;
    //   304: pop
    //   305: iload_2
    //   306: ifne -> 1348
    //   309: goto -> 316
    //   312: invokestatic a : (Ljava/lang/Throwable;)Ljava/lang/Throwable;
    //   315: athrow
    //   316: aload_3
    //   317: getstatic burp/Zr36.Ze : Ljava/lang/String;
    //   320: getstatic burp/Zxcn.Zq : Ljava/lang/Object;
    //   323: checkcast java/math/BigInteger
    //   326: invokevirtual intValue : ()I
    //   329: bipush #32
    //   331: irem
    //   332: invokestatic abs : (I)I
    //   335: invokevirtual charAt : (I)C
    //   338: invokevirtual append : (C)Ljava/lang/StringBuilder;
    //   341: pop
    //   342: iload_2
    //   343: ifne -> 1348
    //   346: goto -> 353
    //   349: invokestatic a : (Ljava/lang/Throwable;)Ljava/lang/Throwable;
    //   352: athrow
    //   353: aload_3
    //   354: getstatic burp/Zrd3.Z_ : Ljava/lang/String;
    //   357: getstatic burp/Zsko.ZD : Ljava/lang/Object;
    //   360: checkcast java/math/BigInteger
    //   363: invokevirtual intValue : ()I
    //   366: bipush #32
    //   368: irem
    //   369: invokestatic abs : (I)I
    //   372: invokevirtual charAt : (I)C
    //   375: invokevirtual append : (C)Ljava/lang/StringBuilder;
    //   378: pop
    //   379: iload_2
    //   380: ifne -> 1348
    //   383: goto -> 390
    //   386: invokestatic a : (Ljava/lang/Throwable;)Ljava/lang/Throwable;
    //   389: athrow
    //   390: aload_3
    //   391: getstatic burp/Zr02.ZG : Ljava/lang/String;
    //   394: getstatic burp/Zesw.ZB : Ljava/lang/Object;
    //   397: checkcast java/math/BigInteger
    //   400: invokevirtual intValue : ()I
    //   403: bipush #32
    //   405: irem
    //   406: invokestatic abs : (I)I
    //   409: invokevirtual charAt : (I)C
    //   412: invokevirtual append : (C)Ljava/lang/StringBuilder;
    //   415: pop
    //   416: iload_2
    //   417: ifne -> 1348
    //   420: goto -> 427
    //   423: invokestatic a : (Ljava/lang/Throwable;)Ljava/lang/Throwable;
    //   426: athrow
    //   427: aload_3
    //   428: getstatic burp/Zegv.ZA : Ljava/lang/String;
    //   431: getstatic burp/Ze4w.Zd : Ljava/lang/Object;
    //   434: checkcast java/math/BigInteger
    //   437: invokevirtual intValue : ()I
    //   440: bipush #32
    //   442: irem
    //   443: invokestatic abs : (I)I
    //   446: invokevirtual charAt : (I)C
    //   449: invokevirtual append : (C)Ljava/lang/StringBuilder;
    //   452: pop
    //   453: iload_2
    //   454: ifne -> 1348
    //   457: goto -> 464
    //   460: invokestatic a : (Ljava/lang/Throwable;)Ljava/lang/Throwable;
    //   463: athrow
    //   464: aload_3
    //   465: getstatic burp/Zmlr.ZJ : Ljava/lang/String;
    //   468: getstatic burp/Zea.ZO : Ljava/lang/Object;
    //   471: checkcast java/math/BigInteger
    //   474: invokevirtual intValue : ()I
    //   477: bipush #32
    //   479: irem
    //   480: invokestatic abs : (I)I
    //   483: invokevirtual charAt : (I)C
    //   486: invokevirtual append : (C)Ljava/lang/StringBuilder;
    //   489: pop
    //   490: iload_2
    //   491: ifne -> 1348
    //   494: goto -> 501
    //   497: invokestatic a : (Ljava/lang/Throwable;)Ljava/lang/Throwable;
    //   500: athrow
    //   501: aload_3
    //   502: getstatic burp/Zkdx.Ze : Ljava/lang/String;
    //   505: getstatic burp/Zs0h.ZU : Ljava/lang/Object;
    //   508: checkcast java/math/BigInteger
    //   511: invokevirtual intValue : ()I
    //   514: bipush #32
    //   516: irem
    //   517: invokestatic abs : (I)I
    //   520: invokevirtual charAt : (I)C
    //   523: invokevirtual append : (C)Ljava/lang/StringBuilder;
    //   526: pop
    //   527: iload_2
    //   528: ifne -> 1348
    //   531: goto -> 538
    //   534: invokestatic a : (Ljava/lang/Throwable;)Ljava/lang/Throwable;
    //   537: athrow
    //   538: aload_3
    //   539: getstatic burp/Zrp2.ZJ : Ljava/lang/String;
    //   542: getstatic burp/Zs1d.Zo : Ljava/lang/Object;
    //   545: checkcast java/math/BigInteger
    //   548: invokevirtual intValue : ()I
    //   551: bipush #32
    //   553: irem
    //   554: invokestatic abs : (I)I
    //   557: invokevirtual charAt : (I)C
    //   560: invokevirtual append : (C)Ljava/lang/StringBuilder;
    //   563: pop
    //   564: iload_2
    //   565: ifne -> 1348
    //   568: goto -> 575
    //   571: invokestatic a : (Ljava/lang/Throwable;)Ljava/lang/Throwable;
    //   574: athrow
    //   575: aload_3
    //   576: getstatic burp/Zbjx.ZA : Ljava/lang/String;
    //   579: getstatic burp/Zv8d.ZN : Ljava/lang/Object;
    //   582: checkcast java/math/BigInteger
    //   585: invokevirtual intValue : ()I
    //   588: bipush #32
    //   590: irem
    //   591: invokestatic abs : (I)I
    //   594: invokevirtual charAt : (I)C
    //   597: invokevirtual append : (C)Ljava/lang/StringBuilder;
    //   600: pop
    //   601: iload_2
    //   602: ifne -> 1348
    //   605: goto -> 612
    //   608: invokestatic a : (Ljava/lang/Throwable;)Ljava/lang/Throwable;
    //   611: athrow
    //   612: aload_3
    //   613: getstatic burp/Zg2u.Zy : Ljava/lang/String;
    //   616: getstatic burp/Zr14.Zy : Ljava/lang/Object;
    //   619: checkcast java/math/BigInteger
    //   622: invokevirtual intValue : ()I
    //   625: bipush #32
    //   627: irem
    //   628: invokestatic abs : (I)I
    //   631: invokevirtual charAt : (I)C
    //   634: invokevirtual append : (C)Ljava/lang/StringBuilder;
    //   637: pop
    //   638: iload_2
    //   639: ifne -> 1348
    //   642: goto -> 649
    //   645: invokestatic a : (Ljava/lang/Throwable;)Ljava/lang/Throwable;
    //   648: athrow
    //   649: aload_3
    //   650: getstatic burp/Ztdl.ZK : Ljava/lang/String;
    //   653: getstatic burp/Zxc0.Zl : Ljava/lang/Object;
    //   656: checkcast java/math/BigInteger
    //   659: invokevirtual intValue : ()I
    //   662: bipush #32
    //   664: irem
    //   665: invokestatic abs : (I)I
    //   668: invokevirtual charAt : (I)C
    //   671: invokevirtual append : (C)Ljava/lang/StringBuilder;
    //   674: pop
    //   675: iload_2
    //   676: ifne -> 1348
    //   679: goto -> 686
    //   682: invokestatic a : (Ljava/lang/Throwable;)Ljava/lang/Throwable;
    //   685: athrow
    //   686: aload_3
    //   687: getstatic burp/Zz91.Zx : Ljava/lang/String;
    //   690: getstatic burp/Zl_a.ZP : Ljava/lang/Object;
    //   693: checkcast java/math/BigInteger
    //   696: invokevirtual intValue : ()I
    //   699: bipush #32
    //   701: irem
    //   702: invokestatic abs : (I)I
    //   705: invokevirtual charAt : (I)C
    //   708: invokevirtual append : (C)Ljava/lang/StringBuilder;
    //   711: pop
    //   712: iload_2
    //   713: ifne -> 1348
    //   716: goto -> 723
    //   719: invokestatic a : (Ljava/lang/Throwable;)Ljava/lang/Throwable;
    //   722: athrow
    //   723: aload_3
    //   724: getstatic burp/Zz7j.ZP : Ljava/lang/String;
    //   727: getstatic burp/Zoe.ZG : Ljava/lang/Object;
    //   730: checkcast java/math/BigInteger
    //   733: invokevirtual intValue : ()I
    //   736: bipush #32
    //   738: irem
    //   739: invokestatic abs : (I)I
    //   742: invokevirtual charAt : (I)C
    //   745: invokevirtual append : (C)Ljava/lang/StringBuilder;
    //   748: pop
    //   749: iload_2
    //   750: ifne -> 1348
    //   753: goto -> 760
    //   756: invokestatic a : (Ljava/lang/Throwable;)Ljava/lang/Throwable;
    //   759: athrow
    //   760: aload_3
    //   761: getstatic burp/Zttd.Ze : Ljava/lang/String;
    //   764: getstatic burp/Zedu.ZL : Ljava/lang/Object;
    //   767: checkcast java/math/BigInteger
    //   770: invokevirtual intValue : ()I
    //   773: bipush #32
    //   775: irem
    //   776: invokestatic abs : (I)I
    //   779: invokevirtual charAt : (I)C
    //   782: invokevirtual append : (C)Ljava/lang/StringBuilder;
    //   785: pop
    //   786: iload_2
    //   787: ifne -> 1348
    //   790: goto -> 797
    //   793: invokestatic a : (Ljava/lang/Throwable;)Ljava/lang/Throwable;
    //   796: athrow
    //   797: aload_3
    //   798: getstatic burp/Zrd2.Zj : Ljava/lang/String;
    //   801: getstatic burp/Zzyb.ZV : Ljava/lang/Object;
    //   804: checkcast java/math/BigInteger
    //   807: invokevirtual intValue : ()I
    //   810: bipush #32
    //   812: irem
    //   813: invokestatic abs : (I)I
    //   816: invokevirtual charAt : (I)C
    //   819: invokevirtual append : (C)Ljava/lang/StringBuilder;
    //   822: pop
    //   823: iload_2
    //   824: ifne -> 1348
    //   827: goto -> 834
    //   830: invokestatic a : (Ljava/lang/Throwable;)Ljava/lang/Throwable;
    //   833: athrow
    //   834: aload_3
    //   835: getstatic burp/Zgtx.ZN : Ljava/lang/String;
    //   838: getstatic burp/Ztr5.ZZ : Ljava/lang/Object;
    //   841: checkcast java/math/BigInteger
    //   844: invokevirtual intValue : ()I
    //   847: bipush #32
    //   849: irem
    //   850: invokestatic abs : (I)I
    //   853: invokevirtual charAt : (I)C
    //   856: invokevirtual append : (C)Ljava/lang/StringBuilder;
    //   859: pop
    //   860: iload_2
    //   861: ifne -> 1348
    //   864: goto -> 871
    //   867: invokestatic a : (Ljava/lang/Throwable;)Ljava/lang/Throwable;
    //   870: athrow
    //   871: aload_3
    //   872: getstatic burp/Zxcn.ZF : Ljava/lang/String;
    //   875: getstatic burp/Zrm6.Z_ : Ljava/lang/Object;
    //   878: checkcast java/math/BigInteger
    //   881: invokevirtual intValue : ()I
    //   884: bipush #32
    //   886: irem
    //   887: invokestatic abs : (I)I
    //   890: invokevirtual charAt : (I)C
    //   893: invokevirtual append : (C)Ljava/lang/StringBuilder;
    //   896: pop
    //   897: iload_2
    //   898: ifne -> 1348
    //   901: goto -> 908
    //   904: invokestatic a : (Ljava/lang/Throwable;)Ljava/lang/Throwable;
    //   907: athrow
    //   908: aload_3
    //   909: getstatic burp/Ztbn.Zx : Ljava/lang/String;
    //   912: getstatic burp/Zspg.ZJ : Ljava/lang/Object;
    //   915: checkcast java/math/BigInteger
    //   918: invokevirtual intValue : ()I
    //   921: bipush #32
    //   923: irem
    //   924: invokestatic abs : (I)I
    //   927: invokevirtual charAt : (I)C
    //   930: invokevirtual append : (C)Ljava/lang/StringBuilder;
    //   933: pop
    //   934: iload_2
    //   935: ifne -> 1348
    //   938: goto -> 945
    //   941: invokestatic a : (Ljava/lang/Throwable;)Ljava/lang/Throwable;
    //   944: athrow
    //   945: aload_3
    //   946: getstatic burp/Zrm6.ZV : Ljava/lang/String;
    //   949: getstatic burp/Zb4d.Ze : Ljava/lang/Object;
    //   952: checkcast java/math/BigInteger
    //   955: invokevirtual intValue : ()I
    //   958: bipush #32
    //   960: irem
    //   961: invokestatic abs : (I)I
    //   964: invokevirtual charAt : (I)C
    //   967: invokevirtual append : (C)Ljava/lang/StringBuilder;
    //   970: pop
    //   971: iload_2
    //   972: ifne -> 1348
    //   975: goto -> 982
    //   978: invokestatic a : (Ljava/lang/Throwable;)Ljava/lang/Throwable;
    //   981: athrow
    //   982: aload_3
    //   983: getstatic burp/Zzpm.Za : Ljava/lang/String;
    //   986: getstatic burp/Zkdq.ZG : Ljava/lang/Object;
    //   989: checkcast java/math/BigInteger
    //   992: invokevirtual intValue : ()I
    //   995: bipush #32
    //   997: irem
    //   998: invokestatic abs : (I)I
    //   1001: invokevirtual charAt : (I)C
    //   1004: invokevirtual append : (C)Ljava/lang/StringBuilder;
    //   1007: pop
    //   1008: iload_2
    //   1009: ifne -> 1348
    //   1012: goto -> 1019
    //   1015: invokestatic a : (Ljava/lang/Throwable;)Ljava/lang/Throwable;
    //   1018: athrow
    //   1019: aload_3
    //   1020: getstatic burp/Zspg.ZG : Ljava/lang/String;
    //   1023: getstatic burp/Zbss.Zh : Ljava/lang/Object;
    //   1026: checkcast java/math/BigInteger
    //   1029: invokevirtual intValue : ()I
    //   1032: bipush #32
    //   1034: irem
    //   1035: invokestatic abs : (I)I
    //   1038: invokevirtual charAt : (I)C
    //   1041: invokevirtual append : (C)Ljava/lang/StringBuilder;
    //   1044: pop
    //   1045: iload_2
    //   1046: ifne -> 1348
    //   1049: goto -> 1056
    //   1052: invokestatic a : (Ljava/lang/Throwable;)Ljava/lang/Throwable;
    //   1055: athrow
    //   1056: aload_3
    //   1057: getstatic burp/Zr6c.Zf : Ljava/lang/String;
    //   1060: getstatic burp/Zllk.Zi : Ljava/lang/Object;
    //   1063: checkcast java/math/BigInteger
    //   1066: invokevirtual intValue : ()I
    //   1069: bipush #32
    //   1071: irem
    //   1072: invokestatic abs : (I)I
    //   1075: invokevirtual charAt : (I)C
    //   1078: invokevirtual append : (C)Ljava/lang/StringBuilder;
    //   1081: pop
    //   1082: iload_2
    //   1083: ifne -> 1348
    //   1086: goto -> 1093
    //   1089: invokestatic a : (Ljava/lang/Throwable;)Ljava/lang/Throwable;
    //   1092: athrow
    //   1093: aload_3
    //   1094: getstatic burp/Zzr8.ZY : Ljava/lang/String;
    //   1097: getstatic burp/Zsdl.Zx : Ljava/lang/Object;
    //   1100: checkcast java/math/BigInteger
    //   1103: invokevirtual intValue : ()I
    //   1106: bipush #32
    //   1108: irem
    //   1109: invokestatic abs : (I)I
    //   1112: invokevirtual charAt : (I)C
    //   1115: invokevirtual append : (C)Ljava/lang/StringBuilder;
    //   1118: pop
    //   1119: iload_2
    //   1120: ifne -> 1348
    //   1123: goto -> 1130
    //   1126: invokestatic a : (Ljava/lang/Throwable;)Ljava/lang/Throwable;
    //   1129: athrow
    //   1130: aload_3
    //   1131: getstatic burp/Zsvd.ZB : Ljava/lang/String;
    //   1134: getstatic burp/Ztr5.ZZ : Ljava/lang/Object;
    //   1137: checkcast java/math/BigInteger
    //   1140: invokevirtual intValue : ()I
    //   1143: bipush #32
    //   1145: irem
    //   1146: invokestatic abs : (I)I
    //   1149: invokevirtual charAt : (I)C
    //   1152: invokevirtual append : (C)Ljava/lang/StringBuilder;
    //   1155: pop
    //   1156: iload_2
    //   1157: ifne -> 1348
    //   1160: goto -> 1167
    //   1163: invokestatic a : (Ljava/lang/Throwable;)Ljava/lang/Throwable;
    //   1166: athrow
    //   1167: aload_3
    //   1168: getstatic burp/Zg1l.Zl : Ljava/lang/String;
    //   1171: getstatic burp/Zspg.ZJ : Ljava/lang/Object;
    //   1174: checkcast java/math/BigInteger
    //   1177: invokevirtual intValue : ()I
    //   1180: bipush #32
    //   1182: irem
    //   1183: invokestatic abs : (I)I
    //   1186: invokevirtual charAt : (I)C
    //   1189: invokevirtual append : (C)Ljava/lang/StringBuilder;
    //   1192: pop
    //   1193: iload_2
    //   1194: ifne -> 1348
    //   1197: goto -> 1204
    //   1200: invokestatic a : (Ljava/lang/Throwable;)Ljava/lang/Throwable;
    //   1203: athrow
    //   1204: aload_3
    //   1205: getstatic burp/Ztr5.ZY : Ljava/lang/String;
    //   1208: getstatic burp/Zeqx.Zh : Ljava/lang/Object;
    //   1211: checkcast java/math/BigInteger
    //   1214: invokevirtual intValue : ()I
    //   1217: bipush #32
    //   1219: irem
    //   1220: invokestatic abs : (I)I
    //   1223: invokevirtual charAt : (I)C
    //   1226: invokevirtual append : (C)Ljava/lang/StringBuilder;
    //   1229: pop
    //   1230: iload_2
    //   1231: ifne -> 1348
    //   1234: goto -> 1241
    //   1237: invokestatic a : (Ljava/lang/Throwable;)Ljava/lang/Throwable;
    //   1240: athrow
    //   1241: aload_3
    //   1242: getstatic burp/Zlbd.Zq : Ljava/lang/String;
    //   1245: getstatic burp/Zemp.Zr : Ljava/lang/Object;
    //   1248: checkcast java/math/BigInteger
    //   1251: invokevirtual intValue : ()I
    //   1254: bipush #32
    //   1256: irem
    //   1257: invokestatic abs : (I)I
    //   1260: invokevirtual charAt : (I)C
    //   1263: invokevirtual append : (C)Ljava/lang/StringBuilder;
    //   1266: pop
    //   1267: iload_2
    //   1268: ifne -> 1348
    //   1271: goto -> 1278
    //   1274: invokestatic a : (Ljava/lang/Throwable;)Ljava/lang/Throwable;
    //   1277: athrow
    //   1278: aload_3
    //   1279: getstatic burp/Zk7o.Zb : Ljava/lang/String;
    //   1282: getstatic burp/Ztq8.Zm : Ljava/lang/Object;
    //   1285: checkcast java/math/BigInteger
    //   1288: invokevirtual intValue : ()I
    //   1291: bipush #32
    //   1293: irem
    //   1294: invokestatic abs : (I)I
    //   1297: invokevirtual charAt : (I)C
    //   1300: invokevirtual append : (C)Ljava/lang/StringBuilder;
    //   1303: pop
    //   1304: iload_2
    //   1305: ifne -> 1348
    //   1308: goto -> 1315
    //   1311: invokestatic a : (Ljava/lang/Throwable;)Ljava/lang/Throwable;
    //   1314: athrow
    //   1315: aload_3
    //   1316: getstatic burp/Zbsz.Zu : Ljava/lang/String;
    //   1319: getstatic burp/Zrb6.ZQ : Ljava/lang/Object;
    //   1322: checkcast java/math/BigInteger
    //   1325: invokevirtual intValue : ()I
    //   1328: bipush #32
    //   1330: irem
    //   1331: invokestatic abs : (I)I
    //   1334: invokevirtual charAt : (I)C
    //   1337: invokevirtual append : (C)Ljava/lang/StringBuilder;
    //   1340: pop
    //   1341: goto -> 1348
    //   1344: invokestatic a : (Ljava/lang/Throwable;)Ljava/lang/Throwable;
    //   1347: athrow
    //   1348: iinc #4, 1
    //   1351: iload_2
    //   1352: ifne -> 15
    //   1355: aload_3
    //   1356: invokevirtual toString : ()Ljava/lang/String;
    //   1359: putstatic burp/Ze4g.Zk : Ljava/lang/String;
    //   1362: getstatic burp/Zmt_.Zl : Ljava/lang/Object;
    //   1365: checkcast java/math/BigInteger
    //   1368: invokevirtual toByteArray : ()[B
    //   1371: astore #4
    //   1373: aload #4
    //   1375: arraylength
    //   1376: iconst_2
    //   1377: iadd
    //   1378: newarray byte
    //   1380: astore #6
    //   1382: iconst_0
    //   1383: istore #7
    //   1385: iload #7
    //   1387: aload #4
    //   1389: arraylength
    //   1390: if_icmpge -> 1410
    //   1393: aload #6
    //   1395: iload #7
    //   1397: aload #4
    //   1399: iload #7
    //   1401: baload
    //   1402: bastore
    //   1403: iinc #7, 1
    //   1406: iload_2
    //   1407: ifne -> 1385
    //   1410: aload #6
    //   1412: arraylength
    //   1413: iconst_3
    //   1414: idiv
    //   1415: iconst_4
    //   1416: imul
    //   1417: newarray byte
    //   1419: astore #5
    //   1421: iconst_0
    //   1422: istore #7
    //   1424: iconst_0
    //   1425: istore #8
    //   1427: iload #7
    //   1429: aload #4
    //   1431: arraylength
    //   1432: if_icmpge -> 1543
    //   1435: aload #5
    //   1437: iload #8
    //   1439: aload #6
    //   1441: iload #7
    //   1443: baload
    //   1444: iconst_2
    //   1445: iushr
    //   1446: bipush #63
    //   1448: iand
    //   1449: i2b
    //   1450: bastore
    //   1451: aload #5
    //   1453: iload #8
    //   1455: iconst_1
    //   1456: iadd
    //   1457: aload #6
    //   1459: iload #7
    //   1461: iconst_1
    //   1462: iadd
    //   1463: baload
    //   1464: iconst_4
    //   1465: iushr
    //   1466: bipush #15
    //   1468: iand
    //   1469: aload #6
    //   1471: iload #7
    //   1473: baload
    //   1474: iconst_4
    //   1475: ishl
    //   1476: bipush #63
    //   1478: iand
    //   1479: ior
    //   1480: i2b
    //   1481: bastore
    //   1482: aload #5
    //   1484: iload #8
    //   1486: iconst_2
    //   1487: iadd
    //   1488: aload #6
    //   1490: iload #7
    //   1492: iconst_2
    //   1493: iadd
    //   1494: baload
    //   1495: bipush #6
    //   1497: iushr
    //   1498: iconst_3
    //   1499: iand
    //   1500: aload #6
    //   1502: iload #7
    //   1504: iconst_1
    //   1505: iadd
    //   1506: baload
    //   1507: iconst_2
    //   1508: ishl
    //   1509: bipush #63
    //   1511: iand
    //   1512: ior
    //   1513: i2b
    //   1514: bastore
    //   1515: aload #5
    //   1517: iload #8
    //   1519: iconst_3
    //   1520: iadd
    //   1521: aload #6
    //   1523: iload #7
    //   1525: iconst_2
    //   1526: iadd
    //   1527: baload
    //   1528: bipush #63
    //   1530: iand
    //   1531: i2b
    //   1532: bastore
    //   1533: iinc #7, 3
    //   1536: iinc #8, 4
    //   1539: iload_2
    //   1540: ifne -> 1427
    //   1543: iconst_0
    //   1544: istore #7
    //   1546: iload #7
    //   1548: aload #5
    //   1550: arraylength
    //   1551: if_icmpge -> 1735
    //   1554: aload #5
    //   1556: iload #7
    //   1558: baload
    //   1559: bipush #26
    //   1561: if_icmpge -> 1589
    //   1564: aload #5
    //   1566: iload #7
    //   1568: aload #5
    //   1570: iload #7
    //   1572: baload
    //   1573: bipush #65
    //   1575: iadd
    //   1576: i2b
    //   1577: bastore
    //   1578: iload_2
    //   1579: ifne -> 1728
    //   1582: goto -> 1589
    //   1585: invokestatic a : (Ljava/lang/Throwable;)Ljava/lang/Throwable;
    //   1588: athrow
    //   1589: aload #5
    //   1591: iload #7
    //   1593: baload
    //   1594: bipush #52
    //   1596: if_icmpge -> 1634
    //   1599: goto -> 1606
    //   1602: invokestatic a : (Ljava/lang/Throwable;)Ljava/lang/Throwable;
    //   1605: athrow
    //   1606: aload #5
    //   1608: iload #7
    //   1610: aload #5
    //   1612: iload #7
    //   1614: baload
    //   1615: bipush #97
    //   1617: iadd
    //   1618: bipush #26
    //   1620: isub
    //   1621: i2b
    //   1622: bastore
    //   1623: iload_2
    //   1624: ifne -> 1728
    //   1627: goto -> 1634
    //   1630: invokestatic a : (Ljava/lang/Throwable;)Ljava/lang/Throwable;
    //   1633: athrow
    //   1634: aload #5
    //   1636: iload #7
    //   1638: baload
    //   1639: bipush #62
    //   1641: if_icmpge -> 1679
    //   1644: goto -> 1651
    //   1647: invokestatic a : (Ljava/lang/Throwable;)Ljava/lang/Throwable;
    //   1650: athrow
    //   1651: aload #5
    //   1653: iload #7
    //   1655: aload #5
    //   1657: iload #7
    //   1659: baload
    //   1660: bipush #48
    //   1662: iadd
    //   1663: bipush #52
    //   1665: isub
    //   1666: i2b
    //   1667: bastore
    //   1668: iload_2
    //   1669: ifne -> 1728
    //   1672: goto -> 1679
    //   1675: invokestatic a : (Ljava/lang/Throwable;)Ljava/lang/Throwable;
    //   1678: athrow
    //   1679: aload #5
    //   1681: iload #7
    //   1683: baload
    //   1684: bipush #63
    //   1686: if_icmpge -> 1714
    //   1689: goto -> 1696
    //   1692: invokestatic a : (Ljava/lang/Throwable;)Ljava/lang/Throwable;
    //   1695: athrow
    //   1696: aload #5
    //   1698: iload #7
    //   1700: bipush #43
    //   1702: bastore
    //   1703: iload_2
    //   1704: ifne -> 1728
    //   1707: goto -> 1714
    //   1710: invokestatic a : (Ljava/lang/Throwable;)Ljava/lang/Throwable;
    //   1713: athrow
    //   1714: aload #5
    //   1716: iload #7
    //   1718: bipush #47
    //   1720: bastore
    //   1721: goto -> 1728
    //   1724: invokestatic a : (Ljava/lang/Throwable;)Ljava/lang/Throwable;
    //   1727: athrow
    //   1728: iinc #7, 1
    //   1731: iload_2
    //   1732: ifne -> 1546
    //   1735: aload #5
    //   1737: arraylength
    //   1738: iconst_1
    //   1739: isub
    //   1740: istore #7
    //   1742: iload #7
    //   1744: aload #4
    //   1746: arraylength
    //   1747: iconst_4
    //   1748: imul
    //   1749: iconst_3
    //   1750: idiv
    //   1751: if_icmple -> 1768
    //   1754: aload #5
    //   1756: iload #7
    //   1758: bipush #61
    //   1760: bastore
    //   1761: iinc #7, -1
    //   1764: iload_2
    //   1765: ifne -> 1742
    //   1768: new java/math/BigInteger
    //   1771: dup
    //   1772: aload #5
    //   1774: invokespecial <init> : ([B)V
    //   1777: invokevirtual abs : ()Ljava/math/BigInteger;
    //   1780: putstatic burp/Zmkq.Zg : Ljava/lang/Object;
    //   1783: sipush #22164
    //   1786: sipush #-4020
    //   1789: invokestatic a : (II)Ljava/lang/String;
    //   1792: iconst_1
    //   1793: ldc burp/Zrml
    //   1795: invokevirtual getClassLoader : ()Ljava/lang/ClassLoader;
    //   1798: invokestatic forName : (Ljava/lang/String;ZLjava/lang/ClassLoader;)Ljava/lang/Class;
    //   1801: invokevirtual getDeclaredFields : ()[Ljava/lang/reflect/Field;
    //   1804: astore #4
    //   1806: aload #4
    //   1808: arraylength
    //   1809: istore #5
    //   1811: iconst_0
    //   1812: istore #6
    //   1814: iload #6
    //   1816: iload #5
    //   1818: if_icmpge -> 1956
    //   1821: aload #4
    //   1823: iload #6
    //   1825: aaload
    //   1826: astore #7
    //   1828: aload #7
    //   1830: invokevirtual getModifiers : ()I
    //   1833: invokestatic isStatic : (I)Z
    //   1836: ifne -> 1846
    //   1839: goto -> 1949
    //   1842: invokestatic a : (Ljava/lang/Throwable;)Ljava/lang/Throwable;
    //   1845: athrow
    //   1846: aload #7
    //   1848: invokevirtual getType : ()Ljava/lang/Class;
    //   1851: astore #8
    //   1853: aload #8
    //   1855: ifnull -> 1936
    //   1858: aload #8
    //   1860: invokevirtual isPrimitive : ()Z
    //   1863: ifne -> 1936
    //   1866: goto -> 1873
    //   1869: invokestatic a : (Ljava/lang/Throwable;)Ljava/lang/Throwable;
    //   1872: athrow
    //   1873: aload #8
    //   1875: invokevirtual getPackage : ()Ljava/lang/Package;
    //   1878: ifnull -> 1936
    //   1881: goto -> 1888
    //   1884: invokestatic a : (Ljava/lang/Throwable;)Ljava/lang/Throwable;
    //   1887: athrow
    //   1888: aload #8
    //   1890: invokevirtual getPackage : ()Ljava/lang/Package;
    //   1893: invokevirtual getName : ()Ljava/lang/String;
    //   1896: ifnull -> 1936
    //   1899: goto -> 1906
    //   1902: invokestatic a : (Ljava/lang/Throwable;)Ljava/lang/Throwable;
    //   1905: athrow
    //   1906: aload #8
    //   1908: invokevirtual getPackage : ()Ljava/lang/Package;
    //   1911: invokevirtual getName : ()Ljava/lang/String;
    //   1914: sipush #22168
    //   1917: sipush #-3780
    //   1920: invokestatic a : (II)Ljava/lang/String;
    //   1923: invokevirtual startsWith : (Ljava/lang/String;)Z
    //   1926: ifne -> 1936
    //   1929: goto -> 1936
    //   1932: invokestatic a : (Ljava/lang/Throwable;)Ljava/lang/Throwable;
    //   1935: athrow
    //   1936: aload #7
    //   1938: iconst_1
    //   1939: invokevirtual setAccessible : (Z)V
    //   1942: aload #7
    //   1944: aconst_null
    //   1945: invokevirtual get : (Ljava/lang/Object;)Ljava/lang/Object;
    //   1948: pop
    //   1949: iinc #6, 1
    //   1952: iload_2
    //   1953: ifne -> 1814
    //   1956: sipush #22173
    //   1959: sipush #20739
    //   1962: invokestatic a : (II)Ljava/lang/String;
    //   1965: invokestatic forName : (Ljava/lang/String;)Ljava/lang/Class;
    //   1968: invokevirtual getDeclaredMethods : ()[Ljava/lang/reflect/Method;
    //   1971: astore #4
    //   1973: aload #4
    //   1975: arraylength
    //   1976: istore #5
    //   1978: iconst_0
    //   1979: istore #6
    //   1981: iload #6
    //   1983: iload #5
    //   1985: if_icmpge -> 2118
    //   1988: aload #4
    //   1990: iload #6
    //   1992: aaload
    //   1993: astore #7
    //   1995: aload #7
    //   1997: invokevirtual getParameterTypes : ()[Ljava/lang/Class;
    //   2000: pop
    //   2001: aload #7
    //   2003: invokevirtual getModifiers : ()I
    //   2006: invokestatic isStatic : (I)Z
    //   2009: ifeq -> 2104
    //   2012: aload #7
    //   2014: invokevirtual getParameterTypes : ()[Ljava/lang/Class;
    //   2017: arraylength
    //   2018: iconst_2
    //   2019: if_icmpne -> 2104
    //   2022: goto -> 2029
    //   2025: invokestatic a : (Ljava/lang/Throwable;)Ljava/lang/Throwable;
    //   2028: athrow
    //   2029: aload #7
    //   2031: invokevirtual getReturnType : ()Ljava/lang/Class;
    //   2034: getstatic java/lang/Void.TYPE : Ljava/lang/Class;
    //   2037: invokevirtual equals : (Ljava/lang/Object;)Z
    //   2040: ifeq -> 2104
    //   2043: goto -> 2050
    //   2046: invokestatic a : (Ljava/lang/Throwable;)Ljava/lang/Throwable;
    //   2049: athrow
    //   2050: aload #7
    //   2052: iconst_1
    //   2053: invokevirtual setAccessible : (Z)V
    //   2056: aload #7
    //   2058: aconst_null
    //   2059: iconst_2
    //   2060: anewarray java/lang/Object
    //   2063: dup
    //   2064: iconst_0
    //   2065: aload_0
    //   2066: aastore
    //   2067: dup
    //   2068: iconst_1
    //   2069: aload_1
    //   2070: ifnonnull -> 2088
    //   2073: goto -> 2080
    //   2076: invokestatic a : (Ljava/lang/Throwable;)Ljava/lang/Throwable;
    //   2079: athrow
    //   2080: aload_1
    //   2081: goto -> 2095
    //   2084: invokestatic a : (Ljava/lang/Throwable;)Ljava/lang/Throwable;
    //   2087: athrow
    //   2088: aload_1
    //   2089: checkcast [B
    //   2092: invokevirtual clone : ()Ljava/lang/Object;
    //   2095: aastore
    //   2096: invokevirtual invoke : (Ljava/lang/Object;[Ljava/lang/Object;)Ljava/lang/Object;
    //   2099: pop
    //   2100: iload_2
    //   2101: ifne -> 2118
    //   2104: iinc #6, 1
    //   2107: iload_2
    //   2108: ifne -> 1981
    //   2111: goto -> 2118
    //   2114: invokestatic a : (Ljava/lang/Throwable;)Ljava/lang/Throwable;
    //   2117: athrow
    //   2118: iconst_0
    //   2119: istore #4
    //   2121: getstatic burp/Zz4m.ZI : Ljava/lang/String;
    //   2124: getstatic burp/Zt4p.Zh : Ljava/lang/Object;
    //   2127: checkcast java/math/BigInteger
    //   2130: invokevirtual intValue : ()I
    //   2133: bipush #32
    //   2135: irem
    //   2136: invokestatic abs : (I)I
    //   2139: invokevirtual charAt : (I)C
    //   2142: getstatic burp/Ztq2.Zt : Ljava/lang/String;
    //   2145: getstatic burp/Zt0m.Zt : Ljava/lang/Object;
    //   2148: checkcast java/math/BigInteger
    //   2151: invokevirtual intValue : ()I
    //   2154: bipush #32
    //   2156: irem
    //   2157: invokestatic abs : (I)I
    //   2160: invokevirtual charAt : (I)C
    //   2163: if_icmpgt -> 2508
    //   2166: sipush #22171
    //   2169: sipush #2606
    //   2172: invokestatic a : (II)Ljava/lang/String;
    //   2175: iconst_1
    //   2176: ldc burp/Zxx4
    //   2178: invokevirtual getClassLoader : ()Ljava/lang/ClassLoader;
    //   2181: invokestatic forName : (Ljava/lang/String;ZLjava/lang/ClassLoader;)Ljava/lang/Class;
    //   2184: invokevirtual getDeclaredFields : ()[Ljava/lang/reflect/Field;
    //   2187: astore #5
    //   2189: aload #5
    //   2191: arraylength
    //   2192: istore #6
    //   2194: iconst_0
    //   2195: istore #7
    //   2197: iload #7
    //   2199: iload #6
    //   2201: if_icmpge -> 2339
    //   2204: aload #5
    //   2206: iload #7
    //   2208: aaload
    //   2209: astore #8
    //   2211: aload #8
    //   2213: invokevirtual getModifiers : ()I
    //   2216: invokestatic isStatic : (I)Z
    //   2219: ifne -> 2229
    //   2222: goto -> 2332
    //   2225: invokestatic a : (Ljava/lang/Throwable;)Ljava/lang/Throwable;
    //   2228: athrow
    //   2229: aload #8
    //   2231: invokevirtual getType : ()Ljava/lang/Class;
    //   2234: astore #9
    //   2236: aload #9
    //   2238: ifnull -> 2319
    //   2241: aload #9
    //   2243: invokevirtual isPrimitive : ()Z
    //   2246: ifne -> 2319
    //   2249: goto -> 2256
    //   2252: invokestatic a : (Ljava/lang/Throwable;)Ljava/lang/Throwable;
    //   2255: athrow
    //   2256: aload #9
    //   2258: invokevirtual getPackage : ()Ljava/lang/Package;
    //   2261: ifnull -> 2319
    //   2264: goto -> 2271
    //   2267: invokestatic a : (Ljava/lang/Throwable;)Ljava/lang/Throwable;
    //   2270: athrow
    //   2271: aload #9
    //   2273: invokevirtual getPackage : ()Ljava/lang/Package;
    //   2276: invokevirtual getName : ()Ljava/lang/String;
    //   2279: ifnull -> 2319
    //   2282: goto -> 2289
    //   2285: invokestatic a : (Ljava/lang/Throwable;)Ljava/lang/Throwable;
    //   2288: athrow
    //   2289: aload #9
    //   2291: invokevirtual getPackage : ()Ljava/lang/Package;
    //   2294: invokevirtual getName : ()Ljava/lang/String;
    //   2297: sipush #22159
    //   2300: sipush #8641
    //   2303: invokestatic a : (II)Ljava/lang/String;
    //   2306: invokevirtual startsWith : (Ljava/lang/String;)Z
    //   2309: ifne -> 2319
    //   2312: goto -> 2319
    //   2315: invokestatic a : (Ljava/lang/Throwable;)Ljava/lang/Throwable;
    //   2318: athrow
    //   2319: aload #8
    //   2321: iconst_1
    //   2322: invokevirtual setAccessible : (Z)V
    //   2325: aload #8
    //   2327: aconst_null
    //   2328: invokevirtual get : (Ljava/lang/Object;)Ljava/lang/Object;
    //   2331: pop
    //   2332: iinc #7, 1
    //   2335: iload_2
    //   2336: ifne -> 2197
    //   2339: sipush #22163
    //   2342: sipush #-4188
    //   2345: invokestatic a : (II)Ljava/lang/String;
    //   2348: invokestatic forName : (Ljava/lang/String;)Ljava/lang/Class;
    //   2351: invokevirtual getDeclaredMethods : ()[Ljava/lang/reflect/Method;
    //   2354: astore #5
    //   2356: aload #5
    //   2358: arraylength
    //   2359: istore #6
    //   2361: iconst_0
    //   2362: istore #7
    //   2364: iload #7
    //   2366: iload #6
    //   2368: if_icmpge -> 2505
    //   2371: aload #5
    //   2373: iload #7
    //   2375: aaload
    //   2376: astore #8
    //   2378: aload #8
    //   2380: invokevirtual getParameterTypes : ()[Ljava/lang/Class;
    //   2383: pop
    //   2384: aload #8
    //   2386: invokevirtual getModifiers : ()I
    //   2389: invokestatic isStatic : (I)Z
    //   2392: ifeq -> 2491
    //   2395: aload #8
    //   2397: invokevirtual getParameterTypes : ()[Ljava/lang/Class;
    //   2400: arraylength
    //   2401: iconst_2
    //   2402: if_icmpne -> 2491
    //   2405: goto -> 2412
    //   2408: invokestatic a : (Ljava/lang/Throwable;)Ljava/lang/Throwable;
    //   2411: athrow
    //   2412: aload #8
    //   2414: invokevirtual getReturnType : ()Ljava/lang/Class;
    //   2417: getstatic java/lang/Boolean.TYPE : Ljava/lang/Class;
    //   2420: if_acmpne -> 2491
    //   2423: goto -> 2430
    //   2426: invokestatic a : (Ljava/lang/Throwable;)Ljava/lang/Throwable;
    //   2429: athrow
    //   2430: aload #8
    //   2432: iconst_1
    //   2433: invokevirtual setAccessible : (Z)V
    //   2436: aload #8
    //   2438: aconst_null
    //   2439: iconst_2
    //   2440: anewarray java/lang/Object
    //   2443: dup
    //   2444: iconst_0
    //   2445: aload_0
    //   2446: aastore
    //   2447: dup
    //   2448: iconst_1
    //   2449: aload_1
    //   2450: ifnonnull -> 2468
    //   2453: goto -> 2460
    //   2456: invokestatic a : (Ljava/lang/Throwable;)Ljava/lang/Throwable;
    //   2459: athrow
    //   2460: aload_1
    //   2461: goto -> 2475
    //   2464: invokestatic a : (Ljava/lang/Throwable;)Ljava/lang/Throwable;
    //   2467: athrow
    //   2468: aload_1
    //   2469: checkcast [B
    //   2472: invokevirtual clone : ()Ljava/lang/Object;
    //   2475: aastore
    //   2476: invokevirtual invoke : (Ljava/lang/Object;[Ljava/lang/Object;)Ljava/lang/Object;
    //   2479: checkcast java/lang/Boolean
    //   2482: invokevirtual booleanValue : ()Z
    //   2485: istore #4
    //   2487: iload_2
    //   2488: ifne -> 2505
    //   2491: iinc #7, 1
    //   2494: iload_2
    //   2495: ifne -> 2364
    //   2498: goto -> 2505
    //   2501: invokestatic a : (Ljava/lang/Throwable;)Ljava/lang/Throwable;
    //   2504: athrow
    //   2505: goto -> 2847
    //   2508: sipush #22160
    //   2511: sipush #3652
    //   2514: invokestatic a : (II)Ljava/lang/String;
    //   2517: iconst_1
    //   2518: ldc burp/Zgk1
    //   2520: invokevirtual getClassLoader : ()Ljava/lang/ClassLoader;
    //   2523: invokestatic forName : (Ljava/lang/String;ZLjava/lang/ClassLoader;)Ljava/lang/Class;
    //   2526: invokevirtual getDeclaredFields : ()[Ljava/lang/reflect/Field;
    //   2529: astore #5
    //   2531: aload #5
    //   2533: arraylength
    //   2534: istore #6
    //   2536: iconst_0
    //   2537: istore #7
    //   2539: iload #7
    //   2541: iload #6
    //   2543: if_icmpge -> 2681
    //   2546: aload #5
    //   2548: iload #7
    //   2550: aaload
    //   2551: astore #8
    //   2553: aload #8
    //   2555: invokevirtual getModifiers : ()I
    //   2558: invokestatic isStatic : (I)Z
    //   2561: ifne -> 2571
    //   2564: goto -> 2674
    //   2567: invokestatic a : (Ljava/lang/Throwable;)Ljava/lang/Throwable;
    //   2570: athrow
    //   2571: aload #8
    //   2573: invokevirtual getType : ()Ljava/lang/Class;
    //   2576: astore #9
    //   2578: aload #9
    //   2580: ifnull -> 2661
    //   2583: aload #9
    //   2585: invokevirtual isPrimitive : ()Z
    //   2588: ifne -> 2661
    //   2591: goto -> 2598
    //   2594: invokestatic a : (Ljava/lang/Throwable;)Ljava/lang/Throwable;
    //   2597: athrow
    //   2598: aload #9
    //   2600: invokevirtual getPackage : ()Ljava/lang/Package;
    //   2603: ifnull -> 2661
    //   2606: goto -> 2613
    //   2609: invokestatic a : (Ljava/lang/Throwable;)Ljava/lang/Throwable;
    //   2612: athrow
    //   2613: aload #9
    //   2615: invokevirtual getPackage : ()Ljava/lang/Package;
    //   2618: invokevirtual getName : ()Ljava/lang/String;
    //   2621: ifnull -> 2661
    //   2624: goto -> 2631
    //   2627: invokestatic a : (Ljava/lang/Throwable;)Ljava/lang/Throwable;
    //   2630: athrow
    //   2631: aload #9
    //   2633: invokevirtual getPackage : ()Ljava/lang/Package;
    //   2636: invokevirtual getName : ()Ljava/lang/String;
    //   2639: sipush #22159
    //   2642: sipush #8641
    //   2645: invokestatic a : (II)Ljava/lang/String;
    //   2648: invokevirtual startsWith : (Ljava/lang/String;)Z
    //   2651: ifne -> 2661
    //   2654: goto -> 2661
    //   2657: invokestatic a : (Ljava/lang/Throwable;)Ljava/lang/Throwable;
    //   2660: athrow
    //   2661: aload #8
    //   2663: iconst_1
    //   2664: invokevirtual setAccessible : (Z)V
    //   2667: aload #8
    //   2669: aconst_null
    //   2670: invokevirtual get : (Ljava/lang/Object;)Ljava/lang/Object;
    //   2673: pop
    //   2674: iinc #7, 1
    //   2677: iload_2
    //   2678: ifne -> 2539
    //   2681: sipush #22162
    //   2684: sipush #-19224
    //   2687: invokestatic a : (II)Ljava/lang/String;
    //   2690: invokestatic forName : (Ljava/lang/String;)Ljava/lang/Class;
    //   2693: invokevirtual getDeclaredMethods : ()[Ljava/lang/reflect/Method;
    //   2696: astore #5
    //   2698: aload #5
    //   2700: arraylength
    //   2701: istore #6
    //   2703: iconst_0
    //   2704: istore #7
    //   2706: iload #7
    //   2708: iload #6
    //   2710: if_icmpge -> 2847
    //   2713: aload #5
    //   2715: iload #7
    //   2717: aaload
    //   2718: astore #8
    //   2720: aload #8
    //   2722: invokevirtual getParameterTypes : ()[Ljava/lang/Class;
    //   2725: pop
    //   2726: aload #8
    //   2728: invokevirtual getModifiers : ()I
    //   2731: invokestatic isStatic : (I)Z
    //   2734: ifeq -> 2833
    //   2737: aload #8
    //   2739: invokevirtual getParameterTypes : ()[Ljava/lang/Class;
    //   2742: arraylength
    //   2743: iconst_2
    //   2744: if_icmpne -> 2833
    //   2747: goto -> 2754
    //   2750: invokestatic a : (Ljava/lang/Throwable;)Ljava/lang/Throwable;
    //   2753: athrow
    //   2754: aload #8
    //   2756: invokevirtual getReturnType : ()Ljava/lang/Class;
    //   2759: getstatic java/lang/Boolean.TYPE : Ljava/lang/Class;
    //   2762: if_acmpne -> 2833
    //   2765: goto -> 2772
    //   2768: invokestatic a : (Ljava/lang/Throwable;)Ljava/lang/Throwable;
    //   2771: athrow
    //   2772: aload #8
    //   2774: iconst_1
    //   2775: invokevirtual setAccessible : (Z)V
    //   2778: aload #8
    //   2780: aconst_null
    //   2781: iconst_2
    //   2782: anewarray java/lang/Object
    //   2785: dup
    //   2786: iconst_0
    //   2787: aload_0
    //   2788: aastore
    //   2789: dup
    //   2790: iconst_1
    //   2791: aload_1
    //   2792: ifnonnull -> 2810
    //   2795: goto -> 2802
    //   2798: invokestatic a : (Ljava/lang/Throwable;)Ljava/lang/Throwable;
    //   2801: athrow
    //   2802: aload_1
    //   2803: goto -> 2817
    //   2806: invokestatic a : (Ljava/lang/Throwable;)Ljava/lang/Throwable;
    //   2809: athrow
    //   2810: aload_1
    //   2811: checkcast [B
    //   2814: invokevirtual clone : ()Ljava/lang/Object;
    //   2817: aastore
    //   2818: invokevirtual invoke : (Ljava/lang/Object;[Ljava/lang/Object;)Ljava/lang/Object;
    //   2821: checkcast java/lang/Boolean
    //   2824: invokevirtual booleanValue : ()Z
    //   2827: istore #4
    //   2829: iload_2
    //   2830: ifne -> 2847
    //   2833: iinc #7, 1
    //   2836: iload_2
    //   2837: ifne -> 2706
    //   2840: goto -> 2847
    //   2843: invokestatic a : (Ljava/lang/Throwable;)Ljava/lang/Throwable;
    //   2846: athrow
    //   2847: iload #4
    //   2849: ifeq -> 2855
    //   2852: iload #4
    //   2854: ireturn
    //   2855: getstatic burp/Ze84.Zv : Ljava/lang/String;
    //   2858: getstatic burp/Zbx5.ZL : Ljava/lang/Object;
    //   2861: checkcast java/math/BigInteger
    //   2864: invokevirtual intValue : ()I
    //   2867: bipush #32
    //   2869: irem
    //   2870: invokestatic abs : (I)I
    //   2873: invokevirtual charAt : (I)C
    //   2876: getstatic burp/Zgtd.Zj : Ljava/lang/String;
    //   2879: getstatic burp/Zxt7.ZV : Ljava/lang/Object;
    //   2882: checkcast java/math/BigInteger
    //   2885: invokevirtual intValue : ()I
    //   2888: bipush #32
    //   2890: irem
    //   2891: invokestatic abs : (I)I
    //   2894: invokevirtual charAt : (I)C
    //   2897: if_icmpgt -> 3243
    //   2900: sipush #22166
    //   2903: sipush #-4758
    //   2906: invokestatic a : (II)Ljava/lang/String;
    //   2909: iconst_1
    //   2910: ldc burp/Zxxd
    //   2912: invokevirtual getClassLoader : ()Ljava/lang/ClassLoader;
    //   2915: invokestatic forName : (Ljava/lang/String;ZLjava/lang/ClassLoader;)Ljava/lang/Class;
    //   2918: invokevirtual getDeclaredFields : ()[Ljava/lang/reflect/Field;
    //   2921: astore #5
    //   2923: aload #5
    //   2925: arraylength
    //   2926: istore #6
    //   2928: iconst_0
    //   2929: istore #7
    //   2931: iload #7
    //   2933: iload #6
    //   2935: if_icmpge -> 3073
    //   2938: aload #5
    //   2940: iload #7
    //   2942: aaload
    //   2943: astore #8
    //   2945: aload #8
    //   2947: invokevirtual getModifiers : ()I
    //   2950: invokestatic isStatic : (I)Z
    //   2953: ifne -> 2963
    //   2956: goto -> 3066
    //   2959: invokestatic a : (Ljava/lang/Throwable;)Ljava/lang/Throwable;
    //   2962: athrow
    //   2963: aload #8
    //   2965: invokevirtual getType : ()Ljava/lang/Class;
    //   2968: astore #9
    //   2970: aload #9
    //   2972: ifnull -> 3053
    //   2975: aload #9
    //   2977: invokevirtual isPrimitive : ()Z
    //   2980: ifne -> 3053
    //   2983: goto -> 2990
    //   2986: invokestatic a : (Ljava/lang/Throwable;)Ljava/lang/Throwable;
    //   2989: athrow
    //   2990: aload #9
    //   2992: invokevirtual getPackage : ()Ljava/lang/Package;
    //   2995: ifnull -> 3053
    //   2998: goto -> 3005
    //   3001: invokestatic a : (Ljava/lang/Throwable;)Ljava/lang/Throwable;
    //   3004: athrow
    //   3005: aload #9
    //   3007: invokevirtual getPackage : ()Ljava/lang/Package;
    //   3010: invokevirtual getName : ()Ljava/lang/String;
    //   3013: ifnull -> 3053
    //   3016: goto -> 3023
    //   3019: invokestatic a : (Ljava/lang/Throwable;)Ljava/lang/Throwable;
    //   3022: athrow
    //   3023: aload #9
    //   3025: invokevirtual getPackage : ()Ljava/lang/Package;
    //   3028: invokevirtual getName : ()Ljava/lang/String;
    //   3031: sipush #22159
    //   3034: sipush #8641
    //   3037: invokestatic a : (II)Ljava/lang/String;
    //   3040: invokevirtual startsWith : (Ljava/lang/String;)Z
    //   3043: ifne -> 3053
    //   3046: goto -> 3053
    //   3049: invokestatic a : (Ljava/lang/Throwable;)Ljava/lang/Throwable;
    //   3052: athrow
    //   3053: aload #8
    //   3055: iconst_1
    //   3056: invokevirtual setAccessible : (Z)V
    //   3059: aload #8
    //   3061: aconst_null
    //   3062: invokevirtual get : (Ljava/lang/Object;)Ljava/lang/Object;
    //   3065: pop
    //   3066: iinc #7, 1
    //   3069: iload_2
    //   3070: ifne -> 2931
    //   3073: sipush #22144
    //   3076: sipush #28697
    //   3079: invokestatic a : (II)Ljava/lang/String;
    //   3082: invokestatic forName : (Ljava/lang/String;)Ljava/lang/Class;
    //   3085: invokevirtual getDeclaredMethods : ()[Ljava/lang/reflect/Method;
    //   3088: astore #5
    //   3090: aload #5
    //   3092: arraylength
    //   3093: istore #6
    //   3095: iconst_0
    //   3096: istore #7
    //   3098: iload #7
    //   3100: iload #6
    //   3102: if_icmpge -> 3239
    //   3105: aload #5
    //   3107: iload #7
    //   3109: aaload
    //   3110: astore #8
    //   3112: aload #8
    //   3114: invokevirtual getParameterTypes : ()[Ljava/lang/Class;
    //   3117: pop
    //   3118: aload #8
    //   3120: invokevirtual getModifiers : ()I
    //   3123: invokestatic isStatic : (I)Z
    //   3126: ifeq -> 3225
    //   3129: aload #8
    //   3131: invokevirtual getParameterTypes : ()[Ljava/lang/Class;
    //   3134: arraylength
    //   3135: iconst_2
    //   3136: if_icmpne -> 3225
    //   3139: goto -> 3146
    //   3142: invokestatic a : (Ljava/lang/Throwable;)Ljava/lang/Throwable;
    //   3145: athrow
    //   3146: aload #8
    //   3148: invokevirtual getReturnType : ()Ljava/lang/Class;
    //   3151: getstatic java/lang/Boolean.TYPE : Ljava/lang/Class;
    //   3154: if_acmpne -> 3225
    //   3157: goto -> 3164
    //   3160: invokestatic a : (Ljava/lang/Throwable;)Ljava/lang/Throwable;
    //   3163: athrow
    //   3164: aload #8
    //   3166: iconst_1
    //   3167: invokevirtual setAccessible : (Z)V
    //   3170: aload #8
    //   3172: aconst_null
    //   3173: iconst_2
    //   3174: anewarray java/lang/Object
    //   3177: dup
    //   3178: iconst_0
    //   3179: aload_0
    //   3180: aastore
    //   3181: dup
    //   3182: iconst_1
    //   3183: aload_1
    //   3184: ifnonnull -> 3202
    //   3187: goto -> 3194
    //   3190: invokestatic a : (Ljava/lang/Throwable;)Ljava/lang/Throwable;
    //   3193: athrow
    //   3194: aload_1
    //   3195: goto -> 3209
    //   3198: invokestatic a : (Ljava/lang/Throwable;)Ljava/lang/Throwable;
    //   3201: athrow
    //   3202: aload_1
    //   3203: checkcast [B
    //   3206: invokevirtual clone : ()Ljava/lang/Object;
    //   3209: aastore
    //   3210: invokevirtual invoke : (Ljava/lang/Object;[Ljava/lang/Object;)Ljava/lang/Object;
    //   3213: checkcast java/lang/Boolean
    //   3216: invokevirtual booleanValue : ()Z
    //   3219: istore #4
    //   3221: iload_2
    //   3222: ifne -> 3239
    //   3225: iinc #7, 1
    //   3228: iload_2
    //   3229: ifne -> 3098
    //   3232: goto -> 3239
    //   3235: invokestatic a : (Ljava/lang/Throwable;)Ljava/lang/Throwable;
    //   3238: athrow
    //   3239: iload_2
    //   3240: ifne -> 3582
    //   3243: sipush #22158
    //   3246: sipush #27881
    //   3249: invokestatic a : (II)Ljava/lang/String;
    //   3252: iconst_1
    //   3253: ldc burp/Zko9
    //   3255: invokevirtual getClassLoader : ()Ljava/lang/ClassLoader;
    //   3258: invokestatic forName : (Ljava/lang/String;ZLjava/lang/ClassLoader;)Ljava/lang/Class;
    //   3261: invokevirtual getDeclaredFields : ()[Ljava/lang/reflect/Field;
    //   3264: astore #5
    //   3266: aload #5
    //   3268: arraylength
    //   3269: istore #6
    //   3271: iconst_0
    //   3272: istore #7
    //   3274: iload #7
    //   3276: iload #6
    //   3278: if_icmpge -> 3416
    //   3281: aload #5
    //   3283: iload #7
    //   3285: aaload
    //   3286: astore #8
    //   3288: aload #8
    //   3290: invokevirtual getModifiers : ()I
    //   3293: invokestatic isStatic : (I)Z
    //   3296: ifne -> 3306
    //   3299: goto -> 3409
    //   3302: invokestatic a : (Ljava/lang/Throwable;)Ljava/lang/Throwable;
    //   3305: athrow
    //   3306: aload #8
    //   3308: invokevirtual getType : ()Ljava/lang/Class;
    //   3311: astore #9
    //   3313: aload #9
    //   3315: ifnull -> 3396
    //   3318: aload #9
    //   3320: invokevirtual isPrimitive : ()Z
    //   3323: ifne -> 3396
    //   3326: goto -> 3333
    //   3329: invokestatic a : (Ljava/lang/Throwable;)Ljava/lang/Throwable;
    //   3332: athrow
    //   3333: aload #9
    //   3335: invokevirtual getPackage : ()Ljava/lang/Package;
    //   3338: ifnull -> 3396
    //   3341: goto -> 3348
    //   3344: invokestatic a : (Ljava/lang/Throwable;)Ljava/lang/Throwable;
    //   3347: athrow
    //   3348: aload #9
    //   3350: invokevirtual getPackage : ()Ljava/lang/Package;
    //   3353: invokevirtual getName : ()Ljava/lang/String;
    //   3356: ifnull -> 3396
    //   3359: goto -> 3366
    //   3362: invokestatic a : (Ljava/lang/Throwable;)Ljava/lang/Throwable;
    //   3365: athrow
    //   3366: aload #9
    //   3368: invokevirtual getPackage : ()Ljava/lang/Package;
    //   3371: invokevirtual getName : ()Ljava/lang/String;
    //   3374: sipush #22159
    //   3377: sipush #8641
    //   3380: invokestatic a : (II)Ljava/lang/String;
    //   3383: invokevirtual startsWith : (Ljava/lang/String;)Z
    //   3386: ifne -> 3396
    //   3389: goto -> 3396
    //   3392: invokestatic a : (Ljava/lang/Throwable;)Ljava/lang/Throwable;
    //   3395: athrow
    //   3396: aload #8
    //   3398: iconst_1
    //   3399: invokevirtual setAccessible : (Z)V
    //   3402: aload #8
    //   3404: aconst_null
    //   3405: invokevirtual get : (Ljava/lang/Object;)Ljava/lang/Object;
    //   3408: pop
    //   3409: iinc #7, 1
    //   3412: iload_2
    //   3413: ifne -> 3274
    //   3416: sipush #22148
    //   3419: sipush #-5901
    //   3422: invokestatic a : (II)Ljava/lang/String;
    //   3425: invokestatic forName : (Ljava/lang/String;)Ljava/lang/Class;
    //   3428: invokevirtual getDeclaredMethods : ()[Ljava/lang/reflect/Method;
    //   3431: astore #5
    //   3433: aload #5
    //   3435: arraylength
    //   3436: istore #6
    //   3438: iconst_0
    //   3439: istore #7
    //   3441: iload #7
    //   3443: iload #6
    //   3445: if_icmpge -> 3582
    //   3448: aload #5
    //   3450: iload #7
    //   3452: aaload
    //   3453: astore #8
    //   3455: aload #8
    //   3457: invokevirtual getParameterTypes : ()[Ljava/lang/Class;
    //   3460: pop
    //   3461: aload #8
    //   3463: invokevirtual getModifiers : ()I
    //   3466: invokestatic isStatic : (I)Z
    //   3469: ifeq -> 3568
    //   3472: aload #8
    //   3474: invokevirtual getParameterTypes : ()[Ljava/lang/Class;
    //   3477: arraylength
    //   3478: iconst_2
    //   3479: if_icmpne -> 3568
    //   3482: goto -> 3489
    //   3485: invokestatic a : (Ljava/lang/Throwable;)Ljava/lang/Throwable;
    //   3488: athrow
    //   3489: aload #8
    //   3491: invokevirtual getReturnType : ()Ljava/lang/Class;
    //   3494: getstatic java/lang/Boolean.TYPE : Ljava/lang/Class;
    //   3497: if_acmpne -> 3568
    //   3500: goto -> 3507
    //   3503: invokestatic a : (Ljava/lang/Throwable;)Ljava/lang/Throwable;
    //   3506: athrow
    //   3507: aload #8
    //   3509: iconst_1
    //   3510: invokevirtual setAccessible : (Z)V
    //   3513: aload #8
    //   3515: aconst_null
    //   3516: iconst_2
    //   3517: anewarray java/lang/Object
    //   3520: dup
    //   3521: iconst_0
    //   3522: aload_0
    //   3523: aastore
    //   3524: dup
    //   3525: iconst_1
    //   3526: aload_1
    //   3527: ifnonnull -> 3545
    //   3530: goto -> 3537
    //   3533: invokestatic a : (Ljava/lang/Throwable;)Ljava/lang/Throwable;
    //   3536: athrow
    //   3537: aload_1
    //   3538: goto -> 3552
    //   3541: invokestatic a : (Ljava/lang/Throwable;)Ljava/lang/Throwable;
    //   3544: athrow
    //   3545: aload_1
    //   3546: checkcast [B
    //   3549: invokevirtual clone : ()Ljava/lang/Object;
    //   3552: aastore
    //   3553: invokevirtual invoke : (Ljava/lang/Object;[Ljava/lang/Object;)Ljava/lang/Object;
    //   3556: checkcast java/lang/Boolean
    //   3559: invokevirtual booleanValue : ()Z
    //   3562: istore #4
    //   3564: iload_2
    //   3565: ifne -> 3582
    //   3568: iinc #7, 1
    //   3571: iload_2
    //   3572: ifne -> 3441
    //   3575: goto -> 3582
    //   3578: invokestatic a : (Ljava/lang/Throwable;)Ljava/lang/Throwable;
    //   3581: athrow
    //   3582: iload #4
    //   3584: ifeq -> 3590
    //   3587: iload #4
    //   3589: ireturn
    //   3590: getstatic burp/Zthx.Ze : Ljava/lang/String;
    //   3593: getstatic burp/Zrd2.Zt : Ljava/lang/Object;
    //   3596: checkcast java/math/BigInteger
    //   3599: invokevirtual intValue : ()I
    //   3602: bipush #32
    //   3604: irem
    //   3605: invokestatic abs : (I)I
    //   3608: invokevirtual charAt : (I)C
    //   3611: getstatic burp/Zegw.Zn : Ljava/lang/String;
    //   3614: getstatic burp/Zsko.ZD : Ljava/lang/Object;
    //   3617: checkcast java/math/BigInteger
    //   3620: invokevirtual intValue : ()I
    //   3623: bipush #32
    //   3625: irem
    //   3626: invokestatic abs : (I)I
    //   3629: invokevirtual charAt : (I)C
    //   3632: if_icmpgt -> 3978
    //   3635: sipush #22145
    //   3638: sipush #27964
    //   3641: invokestatic a : (II)Ljava/lang/String;
    //   3644: iconst_1
    //   3645: ldc burp/Ze6t
    //   3647: invokevirtual getClassLoader : ()Ljava/lang/ClassLoader;
    //   3650: invokestatic forName : (Ljava/lang/String;ZLjava/lang/ClassLoader;)Ljava/lang/Class;
    //   3653: invokevirtual getDeclaredFields : ()[Ljava/lang/reflect/Field;
    //   3656: astore #5
    //   3658: aload #5
    //   3660: arraylength
    //   3661: istore #6
    //   3663: iconst_0
    //   3664: istore #7
    //   3666: iload #7
    //   3668: iload #6
    //   3670: if_icmpge -> 3808
    //   3673: aload #5
    //   3675: iload #7
    //   3677: aaload
    //   3678: astore #8
    //   3680: aload #8
    //   3682: invokevirtual getModifiers : ()I
    //   3685: invokestatic isStatic : (I)Z
    //   3688: ifne -> 3698
    //   3691: goto -> 3801
    //   3694: invokestatic a : (Ljava/lang/Throwable;)Ljava/lang/Throwable;
    //   3697: athrow
    //   3698: aload #8
    //   3700: invokevirtual getType : ()Ljava/lang/Class;
    //   3703: astore #9
    //   3705: aload #9
    //   3707: ifnull -> 3788
    //   3710: aload #9
    //   3712: invokevirtual isPrimitive : ()Z
    //   3715: ifne -> 3788
    //   3718: goto -> 3725
    //   3721: invokestatic a : (Ljava/lang/Throwable;)Ljava/lang/Throwable;
    //   3724: athrow
    //   3725: aload #9
    //   3727: invokevirtual getPackage : ()Ljava/lang/Package;
    //   3730: ifnull -> 3788
    //   3733: goto -> 3740
    //   3736: invokestatic a : (Ljava/lang/Throwable;)Ljava/lang/Throwable;
    //   3739: athrow
    //   3740: aload #9
    //   3742: invokevirtual getPackage : ()Ljava/lang/Package;
    //   3745: invokevirtual getName : ()Ljava/lang/String;
    //   3748: ifnull -> 3788
    //   3751: goto -> 3758
    //   3754: invokestatic a : (Ljava/lang/Throwable;)Ljava/lang/Throwable;
    //   3757: athrow
    //   3758: aload #9
    //   3760: invokevirtual getPackage : ()Ljava/lang/Package;
    //   3763: invokevirtual getName : ()Ljava/lang/String;
    //   3766: sipush #22159
    //   3769: sipush #8641
    //   3772: invokestatic a : (II)Ljava/lang/String;
    //   3775: invokevirtual startsWith : (Ljava/lang/String;)Z
    //   3778: ifne -> 3788
    //   3781: goto -> 3788
    //   3784: invokestatic a : (Ljava/lang/Throwable;)Ljava/lang/Throwable;
    //   3787: athrow
    //   3788: aload #8
    //   3790: iconst_1
    //   3791: invokevirtual setAccessible : (Z)V
    //   3794: aload #8
    //   3796: aconst_null
    //   3797: invokevirtual get : (Ljava/lang/Object;)Ljava/lang/Object;
    //   3800: pop
    //   3801: iinc #7, 1
    //   3804: iload_2
    //   3805: ifne -> 3666
    //   3808: sipush #22169
    //   3811: sipush #-20035
    //   3814: invokestatic a : (II)Ljava/lang/String;
    //   3817: invokestatic forName : (Ljava/lang/String;)Ljava/lang/Class;
    //   3820: invokevirtual getDeclaredMethods : ()[Ljava/lang/reflect/Method;
    //   3823: astore #5
    //   3825: aload #5
    //   3827: arraylength
    //   3828: istore #6
    //   3830: iconst_0
    //   3831: istore #7
    //   3833: iload #7
    //   3835: iload #6
    //   3837: if_icmpge -> 3974
    //   3840: aload #5
    //   3842: iload #7
    //   3844: aaload
    //   3845: astore #8
    //   3847: aload #8
    //   3849: invokevirtual getParameterTypes : ()[Ljava/lang/Class;
    //   3852: pop
    //   3853: aload #8
    //   3855: invokevirtual getModifiers : ()I
    //   3858: invokestatic isStatic : (I)Z
    //   3861: ifeq -> 3960
    //   3864: aload #8
    //   3866: invokevirtual getParameterTypes : ()[Ljava/lang/Class;
    //   3869: arraylength
    //   3870: iconst_2
    //   3871: if_icmpne -> 3960
    //   3874: goto -> 3881
    //   3877: invokestatic a : (Ljava/lang/Throwable;)Ljava/lang/Throwable;
    //   3880: athrow
    //   3881: aload #8
    //   3883: invokevirtual getReturnType : ()Ljava/lang/Class;
    //   3886: getstatic java/lang/Boolean.TYPE : Ljava/lang/Class;
    //   3889: if_acmpne -> 3960
    //   3892: goto -> 3899
    //   3895: invokestatic a : (Ljava/lang/Throwable;)Ljava/lang/Throwable;
    //   3898: athrow
    //   3899: aload #8
    //   3901: iconst_1
    //   3902: invokevirtual setAccessible : (Z)V
    //   3905: aload #8
    //   3907: aconst_null
    //   3908: iconst_2
    //   3909: anewarray java/lang/Object
    //   3912: dup
    //   3913: iconst_0
    //   3914: aload_0
    //   3915: aastore
    //   3916: dup
    //   3917: iconst_1
    //   3918: aload_1
    //   3919: ifnonnull -> 3937
    //   3922: goto -> 3929
    //   3925: invokestatic a : (Ljava/lang/Throwable;)Ljava/lang/Throwable;
    //   3928: athrow
    //   3929: aload_1
    //   3930: goto -> 3944
    //   3933: invokestatic a : (Ljava/lang/Throwable;)Ljava/lang/Throwable;
    //   3936: athrow
    //   3937: aload_1
    //   3938: checkcast [B
    //   3941: invokevirtual clone : ()Ljava/lang/Object;
    //   3944: aastore
    //   3945: invokevirtual invoke : (Ljava/lang/Object;[Ljava/lang/Object;)Ljava/lang/Object;
    //   3948: checkcast java/lang/Boolean
    //   3951: invokevirtual booleanValue : ()Z
    //   3954: istore #4
    //   3956: iload_2
    //   3957: ifne -> 3974
    //   3960: iinc #7, 1
    //   3963: iload_2
    //   3964: ifne -> 3833
    //   3967: goto -> 3974
    //   3970: invokestatic a : (Ljava/lang/Throwable;)Ljava/lang/Throwable;
    //   3973: athrow
    //   3974: iload_2
    //   3975: ifne -> 4317
    //   3978: sipush #22165
    //   3981: sipush #28033
    //   3984: invokestatic a : (II)Ljava/lang/String;
    //   3987: iconst_1
    //   3988: ldc burp/Zldx
    //   3990: invokevirtual getClassLoader : ()Ljava/lang/ClassLoader;
    //   3993: invokestatic forName : (Ljava/lang/String;ZLjava/lang/ClassLoader;)Ljava/lang/Class;
    //   3996: invokevirtual getDeclaredFields : ()[Ljava/lang/reflect/Field;
    //   3999: astore #5
    //   4001: aload #5
    //   4003: arraylength
    //   4004: istore #6
    //   4006: iconst_0
    //   4007: istore #7
    //   4009: iload #7
    //   4011: iload #6
    //   4013: if_icmpge -> 4151
    //   4016: aload #5
    //   4018: iload #7
    //   4020: aaload
    //   4021: astore #8
    //   4023: aload #8
    //   4025: invokevirtual getModifiers : ()I
    //   4028: invokestatic isStatic : (I)Z
    //   4031: ifne -> 4041
    //   4034: goto -> 4144
    //   4037: invokestatic a : (Ljava/lang/Throwable;)Ljava/lang/Throwable;
    //   4040: athrow
    //   4041: aload #8
    //   4043: invokevirtual getType : ()Ljava/lang/Class;
    //   4046: astore #9
    //   4048: aload #9
    //   4050: ifnull -> 4131
    //   4053: aload #9
    //   4055: invokevirtual isPrimitive : ()Z
    //   4058: ifne -> 4131
    //   4061: goto -> 4068
    //   4064: invokestatic a : (Ljava/lang/Throwable;)Ljava/lang/Throwable;
    //   4067: athrow
    //   4068: aload #9
    //   4070: invokevirtual getPackage : ()Ljava/lang/Package;
    //   4073: ifnull -> 4131
    //   4076: goto -> 4083
    //   4079: invokestatic a : (Ljava/lang/Throwable;)Ljava/lang/Throwable;
    //   4082: athrow
    //   4083: aload #9
    //   4085: invokevirtual getPackage : ()Ljava/lang/Package;
    //   4088: invokevirtual getName : ()Ljava/lang/String;
    //   4091: ifnull -> 4131
    //   4094: goto -> 4101
    //   4097: invokestatic a : (Ljava/lang/Throwable;)Ljava/lang/Throwable;
    //   4100: athrow
    //   4101: aload #9
    //   4103: invokevirtual getPackage : ()Ljava/lang/Package;
    //   4106: invokevirtual getName : ()Ljava/lang/String;
    //   4109: sipush #22159
    //   4112: sipush #8641
    //   4115: invokestatic a : (II)Ljava/lang/String;
    //   4118: invokevirtual startsWith : (Ljava/lang/String;)Z
    //   4121: ifne -> 4131
    //   4124: goto -> 4131
    //   4127: invokestatic a : (Ljava/lang/Throwable;)Ljava/lang/Throwable;
    //   4130: athrow
    //   4131: aload #8
    //   4133: iconst_1
    //   4134: invokevirtual setAccessible : (Z)V
    //   4137: aload #8
    //   4139: aconst_null
    //   4140: invokevirtual get : (Ljava/lang/Object;)Ljava/lang/Object;
    //   4143: pop
    //   4144: iinc #7, 1
    //   4147: iload_2
    //   4148: ifne -> 4009
    //   4151: sipush #22149
    //   4154: sipush #19134
    //   4157: invokestatic a : (II)Ljava/lang/String;
    //   4160: invokestatic forName : (Ljava/lang/String;)Ljava/lang/Class;
    //   4163: invokevirtual getDeclaredMethods : ()[Ljava/lang/reflect/Method;
    //   4166: astore #5
    //   4168: aload #5
    //   4170: arraylength
    //   4171: istore #6
    //   4173: iconst_0
    //   4174: istore #7
    //   4176: iload #7
    //   4178: iload #6
    //   4180: if_icmpge -> 4317
    //   4183: aload #5
    //   4185: iload #7
    //   4187: aaload
    //   4188: astore #8
    //   4190: aload #8
    //   4192: invokevirtual getParameterTypes : ()[Ljava/lang/Class;
    //   4195: pop
    //   4196: aload #8
    //   4198: invokevirtual getModifiers : ()I
    //   4201: invokestatic isStatic : (I)Z
    //   4204: ifeq -> 4303
    //   4207: aload #8
    //   4209: invokevirtual getParameterTypes : ()[Ljava/lang/Class;
    //   4212: arraylength
    //   4213: iconst_2
    //   4214: if_icmpne -> 4303
    //   4217: goto -> 4224
    //   4220: invokestatic a : (Ljava/lang/Throwable;)Ljava/lang/Throwable;
    //   4223: athrow
    //   4224: aload #8
    //   4226: invokevirtual getReturnType : ()Ljava/lang/Class;
    //   4229: getstatic java/lang/Boolean.TYPE : Ljava/lang/Class;
    //   4232: if_acmpne -> 4303
    //   4235: goto -> 4242
    //   4238: invokestatic a : (Ljava/lang/Throwable;)Ljava/lang/Throwable;
    //   4241: athrow
    //   4242: aload #8
    //   4244: iconst_1
    //   4245: invokevirtual setAccessible : (Z)V
    //   4248: aload #8
    //   4250: aconst_null
    //   4251: iconst_2
    //   4252: anewarray java/lang/Object
    //   4255: dup
    //   4256: iconst_0
    //   4257: aload_0
    //   4258: aastore
    //   4259: dup
    //   4260: iconst_1
    //   4261: aload_1
    //   4262: ifnonnull -> 4280
    //   4265: goto -> 4272
    //   4268: invokestatic a : (Ljava/lang/Throwable;)Ljava/lang/Throwable;
    //   4271: athrow
    //   4272: aload_1
    //   4273: goto -> 4287
    //   4276: invokestatic a : (Ljava/lang/Throwable;)Ljava/lang/Throwable;
    //   4279: athrow
    //   4280: aload_1
    //   4281: checkcast [B
    //   4284: invokevirtual clone : ()Ljava/lang/Object;
    //   4287: aastore
    //   4288: invokevirtual invoke : (Ljava/lang/Object;[Ljava/lang/Object;)Ljava/lang/Object;
    //   4291: checkcast java/lang/Boolean
    //   4294: invokevirtual booleanValue : ()Z
    //   4297: istore #4
    //   4299: iload_2
    //   4300: ifne -> 4317
    //   4303: iinc #7, 1
    //   4306: iload_2
    //   4307: ifne -> 4176
    //   4310: goto -> 4317
    //   4313: invokestatic a : (Ljava/lang/Throwable;)Ljava/lang/Throwable;
    //   4316: athrow
    //   4317: iload #4
    //   4319: ifeq -> 4325
    //   4322: iload #4
    //   4324: ireturn
    //   4325: getstatic burp/Zzef.Za : Ljava/lang/String;
    //   4328: getstatic burp/Zti4.Zi : Ljava/lang/Object;
    //   4331: checkcast java/math/BigInteger
    //   4334: invokevirtual intValue : ()I
    //   4337: bipush #32
    //   4339: irem
    //   4340: invokestatic abs : (I)I
    //   4343: invokevirtual charAt : (I)C
    //   4346: getstatic burp/Zb3d.Zr : Ljava/lang/String;
    //   4349: getstatic burp/Zst7.ZI : Ljava/lang/Object;
    //   4352: checkcast java/math/BigInteger
    //   4355: invokevirtual intValue : ()I
    //   4358: bipush #32
    //   4360: irem
    //   4361: invokestatic abs : (I)I
    //   4364: invokevirtual charAt : (I)C
    //   4367: if_icmpgt -> 4713
    //   4370: sipush #22147
    //   4373: sipush #15661
    //   4376: invokestatic a : (II)Ljava/lang/String;
    //   4379: iconst_1
    //   4380: ldc burp/Zs75
    //   4382: invokevirtual getClassLoader : ()Ljava/lang/ClassLoader;
    //   4385: invokestatic forName : (Ljava/lang/String;ZLjava/lang/ClassLoader;)Ljava/lang/Class;
    //   4388: invokevirtual getDeclaredFields : ()[Ljava/lang/reflect/Field;
    //   4391: astore #5
    //   4393: aload #5
    //   4395: arraylength
    //   4396: istore #6
    //   4398: iconst_0
    //   4399: istore #7
    //   4401: iload #7
    //   4403: iload #6
    //   4405: if_icmpge -> 4543
    //   4408: aload #5
    //   4410: iload #7
    //   4412: aaload
    //   4413: astore #8
    //   4415: aload #8
    //   4417: invokevirtual getModifiers : ()I
    //   4420: invokestatic isStatic : (I)Z
    //   4423: ifne -> 4433
    //   4426: goto -> 4536
    //   4429: invokestatic a : (Ljava/lang/Throwable;)Ljava/lang/Throwable;
    //   4432: athrow
    //   4433: aload #8
    //   4435: invokevirtual getType : ()Ljava/lang/Class;
    //   4438: astore #9
    //   4440: aload #9
    //   4442: ifnull -> 4523
    //   4445: aload #9
    //   4447: invokevirtual isPrimitive : ()Z
    //   4450: ifne -> 4523
    //   4453: goto -> 4460
    //   4456: invokestatic a : (Ljava/lang/Throwable;)Ljava/lang/Throwable;
    //   4459: athrow
    //   4460: aload #9
    //   4462: invokevirtual getPackage : ()Ljava/lang/Package;
    //   4465: ifnull -> 4523
    //   4468: goto -> 4475
    //   4471: invokestatic a : (Ljava/lang/Throwable;)Ljava/lang/Throwable;
    //   4474: athrow
    //   4475: aload #9
    //   4477: invokevirtual getPackage : ()Ljava/lang/Package;
    //   4480: invokevirtual getName : ()Ljava/lang/String;
    //   4483: ifnull -> 4523
    //   4486: goto -> 4493
    //   4489: invokestatic a : (Ljava/lang/Throwable;)Ljava/lang/Throwable;
    //   4492: athrow
    //   4493: aload #9
    //   4495: invokevirtual getPackage : ()Ljava/lang/Package;
    //   4498: invokevirtual getName : ()Ljava/lang/String;
    //   4501: sipush #22159
    //   4504: sipush #8641
    //   4507: invokestatic a : (II)Ljava/lang/String;
    //   4510: invokevirtual startsWith : (Ljava/lang/String;)Z
    //   4513: ifne -> 4523
    //   4516: goto -> 4523
    //   4519: invokestatic a : (Ljava/lang/Throwable;)Ljava/lang/Throwable;
    //   4522: athrow
    //   4523: aload #8
    //   4525: iconst_1
    //   4526: invokevirtual setAccessible : (Z)V
    //   4529: aload #8
    //   4531: aconst_null
    //   4532: invokevirtual get : (Ljava/lang/Object;)Ljava/lang/Object;
    //   4535: pop
    //   4536: iinc #7, 1
    //   4539: iload_2
    //   4540: ifne -> 4401
    //   4543: sipush #22167
    //   4546: sipush #31687
    //   4549: invokestatic a : (II)Ljava/lang/String;
    //   4552: invokestatic forName : (Ljava/lang/String;)Ljava/lang/Class;
    //   4555: invokevirtual getDeclaredMethods : ()[Ljava/lang/reflect/Method;
    //   4558: astore #5
    //   4560: aload #5
    //   4562: arraylength
    //   4563: istore #6
    //   4565: iconst_0
    //   4566: istore #7
    //   4568: iload #7
    //   4570: iload #6
    //   4572: if_icmpge -> 4709
    //   4575: aload #5
    //   4577: iload #7
    //   4579: aaload
    //   4580: astore #8
    //   4582: aload #8
    //   4584: invokevirtual getParameterTypes : ()[Ljava/lang/Class;
    //   4587: pop
    //   4588: aload #8
    //   4590: invokevirtual getModifiers : ()I
    //   4593: invokestatic isStatic : (I)Z
    //   4596: ifeq -> 4695
    //   4599: aload #8
    //   4601: invokevirtual getParameterTypes : ()[Ljava/lang/Class;
    //   4604: arraylength
    //   4605: iconst_2
    //   4606: if_icmpne -> 4695
    //   4609: goto -> 4616
    //   4612: invokestatic a : (Ljava/lang/Throwable;)Ljava/lang/Throwable;
    //   4615: athrow
    //   4616: aload #8
    //   4618: invokevirtual getReturnType : ()Ljava/lang/Class;
    //   4621: getstatic java/lang/Boolean.TYPE : Ljava/lang/Class;
    //   4624: if_acmpne -> 4695
    //   4627: goto -> 4634
    //   4630: invokestatic a : (Ljava/lang/Throwable;)Ljava/lang/Throwable;
    //   4633: athrow
    //   4634: aload #8
    //   4636: iconst_1
    //   4637: invokevirtual setAccessible : (Z)V
    //   4640: aload #8
    //   4642: aconst_null
    //   4643: iconst_2
    //   4644: anewarray java/lang/Object
    //   4647: dup
    //   4648: iconst_0
    //   4649: aload_0
    //   4650: aastore
    //   4651: dup
    //   4652: iconst_1
    //   4653: aload_1
    //   4654: ifnonnull -> 4672
    //   4657: goto -> 4664
    //   4660: invokestatic a : (Ljava/lang/Throwable;)Ljava/lang/Throwable;
    //   4663: athrow
    //   4664: aload_1
    //   4665: goto -> 4679
    //   4668: invokestatic a : (Ljava/lang/Throwable;)Ljava/lang/Throwable;
    //   4671: athrow
    //   4672: aload_1
    //   4673: checkcast [B
    //   4676: invokevirtual clone : ()Ljava/lang/Object;
    //   4679: aastore
    //   4680: invokevirtual invoke : (Ljava/lang/Object;[Ljava/lang/Object;)Ljava/lang/Object;
    //   4683: checkcast java/lang/Boolean
    //   4686: invokevirtual booleanValue : ()Z
    //   4689: istore #4
    //   4691: iload_2
    //   4692: ifne -> 4709
    //   4695: iinc #7, 1
    //   4698: iload_2
    //   4699: ifne -> 4568
    //   4702: goto -> 4709
    //   4705: invokestatic a : (Ljava/lang/Throwable;)Ljava/lang/Throwable;
    //   4708: athrow
    //   4709: iload_2
    //   4710: ifne -> 5052
    //   4713: sipush #22146
    //   4716: sipush #-18734
    //   4719: invokestatic a : (II)Ljava/lang/String;
    //   4722: iconst_1
    //   4723: ldc burp/Zshq
    //   4725: invokevirtual getClassLoader : ()Ljava/lang/ClassLoader;
    //   4728: invokestatic forName : (Ljava/lang/String;ZLjava/lang/ClassLoader;)Ljava/lang/Class;
    //   4731: invokevirtual getDeclaredFields : ()[Ljava/lang/reflect/Field;
    //   4734: astore #5
    //   4736: aload #5
    //   4738: arraylength
    //   4739: istore #6
    //   4741: iconst_0
    //   4742: istore #7
    //   4744: iload #7
    //   4746: iload #6
    //   4748: if_icmpge -> 4886
    //   4751: aload #5
    //   4753: iload #7
    //   4755: aaload
    //   4756: astore #8
    //   4758: aload #8
    //   4760: invokevirtual getModifiers : ()I
    //   4763: invokestatic isStatic : (I)Z
    //   4766: ifne -> 4776
    //   4769: goto -> 4879
    //   4772: invokestatic a : (Ljava/lang/Throwable;)Ljava/lang/Throwable;
    //   4775: athrow
    //   4776: aload #8
    //   4778: invokevirtual getType : ()Ljava/lang/Class;
    //   4781: astore #9
    //   4783: aload #9
    //   4785: ifnull -> 4866
    //   4788: aload #9
    //   4790: invokevirtual isPrimitive : ()Z
    //   4793: ifne -> 4866
    //   4796: goto -> 4803
    //   4799: invokestatic a : (Ljava/lang/Throwable;)Ljava/lang/Throwable;
    //   4802: athrow
    //   4803: aload #9
    //   4805: invokevirtual getPackage : ()Ljava/lang/Package;
    //   4808: ifnull -> 4866
    //   4811: goto -> 4818
    //   4814: invokestatic a : (Ljava/lang/Throwable;)Ljava/lang/Throwable;
    //   4817: athrow
    //   4818: aload #9
    //   4820: invokevirtual getPackage : ()Ljava/lang/Package;
    //   4823: invokevirtual getName : ()Ljava/lang/String;
    //   4826: ifnull -> 4866
    //   4829: goto -> 4836
    //   4832: invokestatic a : (Ljava/lang/Throwable;)Ljava/lang/Throwable;
    //   4835: athrow
    //   4836: aload #9
    //   4838: invokevirtual getPackage : ()Ljava/lang/Package;
    //   4841: invokevirtual getName : ()Ljava/lang/String;
    //   4844: sipush #22159
    //   4847: sipush #8641
    //   4850: invokestatic a : (II)Ljava/lang/String;
    //   4853: invokevirtual startsWith : (Ljava/lang/String;)Z
    //   4856: ifne -> 4866
    //   4859: goto -> 4866
    //   4862: invokestatic a : (Ljava/lang/Throwable;)Ljava/lang/Throwable;
    //   4865: athrow
    //   4866: aload #8
    //   4868: iconst_1
    //   4869: invokevirtual setAccessible : (Z)V
    //   4872: aload #8
    //   4874: aconst_null
    //   4875: invokevirtual get : (Ljava/lang/Object;)Ljava/lang/Object;
    //   4878: pop
    //   4879: iinc #7, 1
    //   4882: iload_2
    //   4883: ifne -> 4744
    //   4886: sipush #22150
    //   4889: sipush #13740
    //   4892: invokestatic a : (II)Ljava/lang/String;
    //   4895: invokestatic forName : (Ljava/lang/String;)Ljava/lang/Class;
    //   4898: invokevirtual getDeclaredMethods : ()[Ljava/lang/reflect/Method;
    //   4901: astore #5
    //   4903: aload #5
    //   4905: arraylength
    //   4906: istore #6
    //   4908: iconst_0
    //   4909: istore #7
    //   4911: iload #7
    //   4913: iload #6
    //   4915: if_icmpge -> 5052
    //   4918: aload #5
    //   4920: iload #7
    //   4922: aaload
    //   4923: astore #8
    //   4925: aload #8
    //   4927: invokevirtual getParameterTypes : ()[Ljava/lang/Class;
    //   4930: pop
    //   4931: aload #8
    //   4933: invokevirtual getModifiers : ()I
    //   4936: invokestatic isStatic : (I)Z
    //   4939: ifeq -> 5038
    //   4942: aload #8
    //   4944: invokevirtual getParameterTypes : ()[Ljava/lang/Class;
    //   4947: arraylength
    //   4948: iconst_2
    //   4949: if_icmpne -> 5038
    //   4952: goto -> 4959
    //   4955: invokestatic a : (Ljava/lang/Throwable;)Ljava/lang/Throwable;
    //   4958: athrow
    //   4959: aload #8
    //   4961: invokevirtual getReturnType : ()Ljava/lang/Class;
    //   4964: getstatic java/lang/Boolean.TYPE : Ljava/lang/Class;
    //   4967: if_acmpne -> 5038
    //   4970: goto -> 4977
    //   4973: invokestatic a : (Ljava/lang/Throwable;)Ljava/lang/Throwable;
    //   4976: athrow
    //   4977: aload #8
    //   4979: iconst_1
    //   4980: invokevirtual setAccessible : (Z)V
    //   4983: aload #8
    //   4985: aconst_null
    //   4986: iconst_2
    //   4987: anewarray java/lang/Object
    //   4990: dup
    //   4991: iconst_0
    //   4992: aload_0
    //   4993: aastore
    //   4994: dup
    //   4995: iconst_1
    //   4996: aload_1
    //   4997: ifnonnull -> 5015
    //   5000: goto -> 5007
    //   5003: invokestatic a : (Ljava/lang/Throwable;)Ljava/lang/Throwable;
    //   5006: athrow
    //   5007: aload_1
    //   5008: goto -> 5022
    //   5011: invokestatic a : (Ljava/lang/Throwable;)Ljava/lang/Throwable;
    //   5014: athrow
    //   5015: aload_1
    //   5016: checkcast [B
    //   5019: invokevirtual clone : ()Ljava/lang/Object;
    //   5022: aastore
    //   5023: invokevirtual invoke : (Ljava/lang/Object;[Ljava/lang/Object;)Ljava/lang/Object;
    //   5026: checkcast java/lang/Boolean
    //   5029: invokevirtual booleanValue : ()Z
    //   5032: istore #4
    //   5034: iload_2
    //   5035: ifne -> 5052
    //   5038: iinc #7, 1
    //   5041: iload_2
    //   5042: ifne -> 4911
    //   5045: goto -> 5052
    //   5048: invokestatic a : (Ljava/lang/Throwable;)Ljava/lang/Throwable;
    //   5051: athrow
    //   5052: iload #4
    //   5054: ireturn
    //   5055: astore_3
    //   5056: new java/lang/Exception
    //   5059: dup
    //   5060: aload_3
    //   5061: invokevirtual getMessage : ()Ljava/lang/String;
    //   5064: invokespecial <init> : (Ljava/lang/String;)V
    //   5067: athrow
    // Exception table:
    //   from	to	target	type
    //   4	2854	5055	java/lang/Throwable
    //   22	198	201	java/lang/Throwable
    //   168	235	238	java/lang/Throwable
    //   205	272	275	java/lang/Throwable
    //   242	309	312	java/lang/Throwable
    //   279	346	349	java/lang/Throwable
    //   316	383	386	java/lang/Throwable
    //   353	420	423	java/lang/Throwable
    //   390	457	460	java/lang/Throwable
    //   427	494	497	java/lang/Throwable
    //   464	531	534	java/lang/Throwable
    //   501	568	571	java/lang/Throwable
    //   538	605	608	java/lang/Throwable
    //   575	642	645	java/lang/Throwable
    //   612	679	682	java/lang/Throwable
    //   649	716	719	java/lang/Throwable
    //   686	753	756	java/lang/Throwable
    //   723	790	793	java/lang/Throwable
    //   760	827	830	java/lang/Throwable
    //   797	864	867	java/lang/Throwable
    //   834	901	904	java/lang/Throwable
    //   871	938	941	java/lang/Throwable
    //   908	975	978	java/lang/Throwable
    //   945	1012	1015	java/lang/Throwable
    //   982	1049	1052	java/lang/Throwable
    //   1019	1086	1089	java/lang/Throwable
    //   1056	1123	1126	java/lang/Throwable
    //   1093	1160	1163	java/lang/Throwable
    //   1130	1197	1200	java/lang/Throwable
    //   1167	1234	1237	java/lang/Throwable
    //   1204	1271	1274	java/lang/Throwable
    //   1241	1308	1311	java/lang/Throwable
    //   1278	1341	1344	java/lang/Throwable
    //   1554	1582	1585	java/lang/Throwable
    //   1564	1599	1602	java/lang/Throwable
    //   1589	1627	1630	java/lang/Throwable
    //   1606	1644	1647	java/lang/Throwable
    //   1634	1672	1675	java/lang/Throwable
    //   1651	1689	1692	java/lang/Throwable
    //   1679	1707	1710	java/lang/Throwable
    //   1696	1721	1724	java/lang/Throwable
    //   1828	1842	1842	java/lang/Throwable
    //   1853	1866	1869	java/lang/Throwable
    //   1858	1881	1884	java/lang/Throwable
    //   1873	1899	1902	java/lang/Throwable
    //   1888	1929	1932	java/lang/Throwable
    //   1995	2022	2025	java/lang/Throwable
    //   2012	2043	2046	java/lang/Throwable
    //   2029	2073	2076	java/lang/Throwable
    //   2050	2084	2084	java/lang/Throwable
    //   2095	2111	2114	java/lang/Throwable
    //   2211	2225	2225	java/lang/Throwable
    //   2236	2249	2252	java/lang/Throwable
    //   2241	2264	2267	java/lang/Throwable
    //   2256	2282	2285	java/lang/Throwable
    //   2271	2312	2315	java/lang/Throwable
    //   2378	2405	2408	java/lang/Throwable
    //   2395	2423	2426	java/lang/Throwable
    //   2412	2453	2456	java/lang/Throwable
    //   2430	2464	2464	java/lang/Throwable
    //   2487	2498	2501	java/lang/Throwable
    //   2553	2567	2567	java/lang/Throwable
    //   2578	2591	2594	java/lang/Throwable
    //   2583	2606	2609	java/lang/Throwable
    //   2598	2624	2627	java/lang/Throwable
    //   2613	2654	2657	java/lang/Throwable
    //   2720	2747	2750	java/lang/Throwable
    //   2737	2765	2768	java/lang/Throwable
    //   2754	2795	2798	java/lang/Throwable
    //   2772	2806	2806	java/lang/Throwable
    //   2829	2840	2843	java/lang/Throwable
    //   2855	3589	5055	java/lang/Throwable
    //   2945	2959	2959	java/lang/Throwable
    //   2970	2983	2986	java/lang/Throwable
    //   2975	2998	3001	java/lang/Throwable
    //   2990	3016	3019	java/lang/Throwable
    //   3005	3046	3049	java/lang/Throwable
    //   3112	3139	3142	java/lang/Throwable
    //   3129	3157	3160	java/lang/Throwable
    //   3146	3187	3190	java/lang/Throwable
    //   3164	3198	3198	java/lang/Throwable
    //   3221	3232	3235	java/lang/Throwable
    //   3288	3302	3302	java/lang/Throwable
    //   3313	3326	3329	java/lang/Throwable
    //   3318	3341	3344	java/lang/Throwable
    //   3333	3359	3362	java/lang/Throwable
    //   3348	3389	3392	java/lang/Throwable
    //   3455	3482	3485	java/lang/Throwable
    //   3472	3500	3503	java/lang/Throwable
    //   3489	3530	3533	java/lang/Throwable
    //   3507	3541	3541	java/lang/Throwable
    //   3564	3575	3578	java/lang/Throwable
    //   3590	4324	5055	java/lang/Throwable
    //   3680	3694	3694	java/lang/Throwable
    //   3705	3718	3721	java/lang/Throwable
    //   3710	3733	3736	java/lang/Throwable
    //   3725	3751	3754	java/lang/Throwable
    //   3740	3781	3784	java/lang/Throwable
    //   3847	3874	3877	java/lang/Throwable
    //   3864	3892	3895	java/lang/Throwable
    //   3881	3922	3925	java/lang/Throwable
    //   3899	3933	3933	java/lang/Throwable
    //   3956	3967	3970	java/lang/Throwable
    //   4023	4037	4037	java/lang/Throwable
    //   4048	4061	4064	java/lang/Throwable
    //   4053	4076	4079	java/lang/Throwable
    //   4068	4094	4097	java/lang/Throwable
    //   4083	4124	4127	java/lang/Throwable
    //   4190	4217	4220	java/lang/Throwable
    //   4207	4235	4238	java/lang/Throwable
    //   4224	4265	4268	java/lang/Throwable
    //   4242	4276	4276	java/lang/Throwable
    //   4299	4310	4313	java/lang/Throwable
    //   4325	5054	5055	java/lang/Throwable
    //   4415	4429	4429	java/lang/Throwable
    //   4440	4453	4456	java/lang/Throwable
    //   4445	4468	4471	java/lang/Throwable
    //   4460	4486	4489	java/lang/Throwable
    //   4475	4516	4519	java/lang/Throwable
    //   4582	4609	4612	java/lang/Throwable
    //   4599	4627	4630	java/lang/Throwable
    //   4616	4657	4660	java/lang/Throwable
    //   4634	4668	4668	java/lang/Throwable
    //   4691	4702	4705	java/lang/Throwable
    //   4758	4772	4772	java/lang/Throwable
    //   4783	4796	4799	java/lang/Throwable
    //   4788	4811	4814	java/lang/Throwable
    //   4803	4829	4832	java/lang/Throwable
    //   4818	4859	4862	java/lang/Throwable
    //   4925	4952	4955	java/lang/Throwable
    //   4942	4970	4973	java/lang/Throwable
    //   4959	5000	5003	java/lang/Throwable
    //   4977	5011	5011	java/lang/Throwable
    //   5034	5045	5048	java/lang/Throwable
  }
  
  static {
    // Byte code:
    //   0: bipush #26
    //   2: anewarray java/lang/String
    //   5: astore #5
    //   7: iconst_0
    //   8: istore_3
    //   9: ldc 'Yo\\t1Da\\t\\bE_JY}\\tt\\tw)a]]o\\tJ\\rCle^ zDvONb2N<K%F\\ty.v\\tV<c\\t~Q$}\\t1['MmdBdSE(\\n[zI@B1RJl~u@X0tO\\tJV\\tRo|=M7u%G@DRx3~uS =,A\\r s+E7?cWts>nO\U+S4\\t"=a\\b; @ GqFJh]/4l|a\\n\\tpI\\tW:&W;\\tr+R\\tYB\\fc]d\\tIf\\f]t\\tHt\\bYv,\\n'
    //   11: dup
    //   12: astore_2
    //   13: invokevirtual length : ()I
    //   16: istore #4
    //   18: bipush #9
    //   20: istore_1
    //   21: iconst_m1
    //   22: istore_0
    //   23: bipush #57
    //   25: iinc #0, 1
    //   28: aload_2
    //   29: iload_0
    //   30: dup
    //   31: iload_1
    //   32: iadd
    //   33: invokevirtual substring : (II)Ljava/lang/String;
    //   36: iconst_m1
    //   37: goto -> 142
    //   40: aload #5
    //   42: swap
    //   43: iload_3
    //   44: iinc #3, 1
    //   47: swap
    //   48: aastore
    //   49: iload_0
    //   50: iload_1
    //   51: iadd
    //   52: dup
    //   53: istore_0
    //   54: iload #4
    //   56: if_icmpge -> 68
    //   59: aload_2
    //   60: iload_0
    //   61: invokevirtual charAt : (I)C
    //   64: istore_1
    //   65: goto -> 23
    //   68: ldc '\\b\\tjrBH'
    //   70: dup
    //   71: astore_2
    //   72: invokevirtual length : ()I
    //   75: istore #4
    //   77: iconst_4
    //   78: istore_1
    //   79: iconst_m1
    //   80: istore_0
    //   81: bipush #124
    //   83: iinc #0, 1
    //   86: aload_2
    //   87: iload_0
    //   88: dup
    //   89: iload_1
    //   90: iadd
    //   91: invokevirtual substring : (II)Ljava/lang/String;
    //   94: iconst_0
    //   95: goto -> 142
    //   98: aload #5
    //   100: swap
    //   101: iload_3
    //   102: iinc #3, 1
    //   105: swap
    //   106: aastore
    //   107: iload_0
    //   108: iload_1
    //   109: iadd
    //   110: dup
    //   111: istore_0
    //   112: iload #4
    //   114: if_icmpge -> 126
    //   117: aload_2
    //   118: iload_0
    //   119: invokevirtual charAt : (I)C
    //   122: istore_1
    //   123: goto -> 81
    //   126: aload #5
    //   128: putstatic burp/Zle9.a : [Ljava/lang/String;
    //   131: bipush #26
    //   133: anewarray java/lang/String
    //   136: putstatic burp/Zle9.b : [Ljava/lang/String;
    //   139: goto -> 300
    //   142: dup_x2
    //   143: pop
    //   144: invokevirtual toCharArray : ()[C
    //   147: dup_x1
    //   148: arraylength
    //   149: dup_x2
    //   150: pop
    //   151: iconst_0
    //   152: istore #6
    //   154: dup2_x1
    //   155: pop2
    //   156: dup_x2
    //   157: iconst_1
    //   158: if_icmpgt -> 260
    //   161: dup2
    //   162: swap
    //   163: iload #6
    //   165: dup2_x1
    //   166: caload
    //   167: swap
    //   168: iload #6
    //   170: bipush #7
    //   172: irem
    //   173: tableswitch default -> 242, 0 -> 212, 1 -> 217, 2 -> 222, 3 -> 227, 4 -> 232, 5 -> 237
    //   212: bipush #41
    //   214: goto -> 244
    //   217: bipush #53
    //   219: goto -> 244
    //   222: bipush #66
    //   224: goto -> 244
    //   227: bipush #87
    //   229: goto -> 244
    //   232: bipush #96
    //   234: goto -> 244
    //   237: bipush #50
    //   239: goto -> 244
    //   242: bipush #117
    //   244: ixor
    //   245: ixor
    //   246: i2c
    //   247: castore
    //   248: iinc #6, 1
    //   251: dup
    //   252: ifne -> 260
    //   255: dup2
    //   256: dup_x1
    //   257: goto -> 165
    //   260: dup2_x1
    //   261: pop2
    //   262: dup_x2
    //   263: iload #6
    //   265: if_icmpgt -> 161
    //   268: pop
    //   269: new java/lang/String
    //   272: dup_x1
    //   273: swap
    //   274: invokespecial <init> : ([C)V
    //   277: invokevirtual intern : ()Ljava/lang/String;
    //   280: swap
    //   281: pop
    //   282: swap
    //   283: tableswitch default -> 40, 0 -> 98
    //   300: new java/math/BigInteger
    //   303: dup
    //   304: sipush #22172
    //   307: sipush #-8274
    //   310: invokestatic a : (II)Ljava/lang/String;
    //   313: invokespecial <init> : (Ljava/lang/String;)V
    //   316: putstatic burp/Zle9.ZI : Ljava/lang/Object;
    //   319: sipush #22161
    //   322: sipush #29429
    //   325: invokestatic a : (II)Ljava/lang/String;
    //   328: putstatic burp/Zle9.Zm : Ljava/lang/String;
    //   331: return
  }
  
  private static Throwable a(Throwable paramThrowable) {
    return paramThrowable;
  }
  
  private static String a(int paramInt1, int paramInt2) {
    int i = (paramInt1 ^ 0x5697) & 0xFFFF;
    if (b[i] == null) {
      char[] arrayOfChar = a[i].toCharArray();
      switch (arrayOfChar[0] & 0xFF) {
        case 0:
        
        case 1:
        
        case 2:
        
        case 3:
        
        case 4:
        
        case 5:
        
        case 6:
        
        case 7:
        
        case 8:
        
        case 9:
        
        case 10:
        
        case 11:
        
        case 12:
        
        case 13:
        
        case 14:
        
        case 15:
        
        case 16:
        
        case 17:
        
        case 18:
        
        case 19:
        
        case 20:
        
        case 21:
        
        case 22:
        
        case 23:
        
        case 24:
        
        case 25:
        
        case 26:
        
        case 27:
        
        case 28:
        
        case 29:
        
        case 30:
        
        case 31:
        
        case 32:
        
        case 33:
        
        case 34:
        
        case 35:
        
        case 36:
        
        case 37:
        
        case 38:
        
        case 39:
        
        case 40:
        
        case 41:
        
        case 42:
        
        case 43:
        
        case 44:
        
        case 45:
        
        case 46:
        
        case 47:
        
        case 48:
        
        case 49:
        
        case 50:
        
        case 51:
        
        case 52:
        
        case 53:
        
        case 54:
        
        case 55:
        
        case 56:
        
        case 57:
        
        case 58:
        
        case 59:
        
        case 60:
        
        case 61:
        
        case 62:
        
        case 63:
        
        case 64:
        
        case 65:
        
        case 66:
        
        case 67:
        
        case 68:
        
        case 69:
        
        case 70:
        
        case 71:
        
        case 72:
        
        case 73:
        
        case 74:
        
        case 75:
        
        case 76:
        
        case 77:
        
        case 78:
        
        case 79:
        
        case 80:
        
        case 81:
        
        case 82:
        
        case 83:
        
        case 84:
        
        case 85:
        
        case 86:
        
        case 87:
        
        case 88:
        
        case 89:
        
        case 90:
        
        case 91:
        
        case 92:
        
        case 93:
        
        case 94:
        
        case 95:
        
        case 96:
        
        case 97:
        
        case 98:
        
        case 99:
        
        case 100:
        
        case 101:
        
        case 102:
        
        case 103:
        
        case 104:
        
        case 105:
        
        case 106:
        
        case 107:
        
        case 108:
        
        case 109:
        
        case 110:
        
        case 111:
        
        case 112:
        
        case 113:
        
        case 114:
        
        case 115:
        
        case 116:
        
        case 117:
        
        case 118:
        
        case 119:
        
        case 120:
        
        case 121:
        
        case 122:
        
        case 123:
        
        case 124:
        
        case 125:
        
        case 126:
        
        case 127:
        
        case 128:
        
        case 129:
        
        case 130:
        
        case 131:
        
        case 132:
        
        case 133:
        
        case 134:
        
        case 135:
        
        case 136:
        
        case 137:
        
        case 138:
        
        case 139:
        
        case 140:
        
        case 141:
        
        case 142:
        
        case 143:
        
        case 144:
        
        case 145:
        
        case 146:
        
        case 147:
        
        case 148:
        
        case 149:
        
        case 150:
        
        case 151:
        
        case 152:
        
        case 153:
        
        case 154:
        
        case 155:
        
        case 156:
        
        case 157:
        
        case 158:
        
        case 159:
        
        case 160:
        
        case 161:
        
        case 162:
        
        case 163:
        
        case 164:
        
        case 165:
        
        case 166:
        
        case 167:
        
        case 168:
        
        case 169:
        
        case 170:
        
        case 171:
        
        case 172:
        
        case 173:
        
        case 174:
        
        case 175:
        
        case 176:
        
        case 177:
        
        case 178:
        
        case 179:
        
        case 180:
        
        case 181:
        
        case 182:
        
        case 183:
        
        case 184:
        
        case 185:
        
        case 186:
        
        case 187:
        
        case 188:
        
        case 189:
        
        case 190:
        
        case 191:
        
        case 192:
        
        case 193:
        
        case 194:
        
        case 195:
        
        case 196:
        
        case 197:
        
        case 198:
        
        case 199:
        
        case 200:
        
        case 201:
        
        case 202:
        
        case 203:
        
        case 204:
        
        case 205:
        
        case 206:
        
        case 207:
        
        case 208:
        
        case 209:
        
        case 210:
        
        case 211:
        
        case 212:
        
        case 213:
        
        case 214:
        
        case 215:
        
        case 216:
        
        case 217:
        
        case 218:
        
        case 219:
        
        case 220:
        
        case 221:
        
        case 222:
        
        case 223:
        
        case 224:
        
        case 225:
        
        case 226:
        
        case 227:
        
        case 228:
        
        case 229:
        
        case 230:
        
        case 231:
        
        case 232:
        
        case 233:
        
        case 234:
        
        case 235:
        
        case 236:
        
        case 237:
        
        case 238:
        
        case 239:
        
        case 240:
        
        case 241:
        
        case 242:
        
        case 243:
        
        case 244:
        
        case 245:
        
        case 246:
        
        case 247:
        
        case 248:
        
        case 249:
        
        case 250:
        
        case 251:
        
        case 252:
        
        case 253:
        
        case 254:
        
        default:
          break;
      } 
      byte b1 = 63;
      int j = (paramInt2 & 0xFF) - b1;
      if (j < 0)
        j += 256; 
      int k = ((paramInt2 & 0xFFFF) >>> 8) - b1;
      if (k < 0)
        k += 256; 
      for (byte b2 = 0; b2 < arrayOfChar.length; b2++) {
        int m = b2 % 2;
        if (m == 0) {
          arrayOfChar[b2] = (char)(arrayOfChar[b2] ^ j);
          j = ((j >>> 3 | j << 5) ^ arrayOfChar[b2]) & 0xFF;
        } else {
          arrayOfChar[b2] = (char)(arrayOfChar[b2] ^ k);
          k = ((k >>> 3 | k << 5) ^ arrayOfChar[b2]) & 0xFF;
        } 
      } 
      b[i] = (new String(arrayOfChar)).intern();
    } 
    return b[i];
  }
}


/* Location:              C:\Program Files\BurpSuitePro\burpsuite_pro.jar!\burp\Zle9.class
 * Java compiler version: 21 (65.0)
 * JD-Core Version:       1.1.3
 */