package burp;

import java.math.BigInteger;

class Zlhm extends ClassLoader {
  static String Zx;
  
  static Object ZT;
  
  private static final String[] a;
  
  private static final String[] b;
  
  static void Z_(Object paramObject) {
    Zd1.ZN = a(31850, 19637);
    Zd1.ZV = new BigInteger(a(31869, 13414));
    boolean bool = Zt2e.ZN();
    try {
      try {
        if (Zx.charAt(Math.abs(((BigInteger)Zxzd.ZD).intValue() % 32)) <= Zgmt.Zu.charAt(Math.abs(((BigInteger)Zlv6.ZN).intValue() % 32))) {
          try {
            Zgw0.Zu(Class.forName(a(31867, 4481)));
            if (!bool)
              Ztsj.Zf(Class.forName(a(31847, 8825))); 
          } catch (Throwable throwable) {
            throw a(null);
          } 
          return;
        } 
      } catch (Throwable throwable) {
        throw a(null);
      } 
      Ztsj.Zf(Class.forName(a(31847, 8825)));
    } catch (Throwable throwable) {}
  }
  
  static boolean ZW(Object[] paramArrayOfObject, Object paramObject) throws Throwable {
    // Byte code:
    //   0: invokestatic ZK : ()Z
    //   3: istore_2
    //   4: getstatic burp/Zzqj.Zq : Ljava/lang/Object;
    //   7: checkcast java/math/BigInteger
    //   10: getstatic burp/Zxl5.Zh : Ljava/lang/Object;
    //   13: checkcast java/math/BigInteger
    //   16: invokevirtual subtract : (Ljava/math/BigInteger;)Ljava/math/BigInteger;
    //   19: putstatic burp/Zbo7.Zl : Ljava/lang/Object;
    //   22: sipush #31854
    //   25: getstatic burp/Zkig.ZK : Ljava/lang/Object;
    //   28: checkcast java/math/BigInteger
    //   31: getstatic burp/Zzsq.Zh : Ljava/lang/Object;
    //   34: checkcast java/math/BigInteger
    //   37: invokevirtual subtract : (Ljava/math/BigInteger;)Ljava/math/BigInteger;
    //   40: putstatic burp/Zg0j.ZV : Ljava/lang/Object;
    //   43: sipush #-494
    //   46: invokestatic a : (II)Ljava/lang/String;
    //   49: iconst_1
    //   50: ldc burp/Zbwj
    //   52: invokevirtual getClassLoader : ()Ljava/lang/ClassLoader;
    //   55: invokestatic forName : (Ljava/lang/String;ZLjava/lang/ClassLoader;)Ljava/lang/Class;
    //   58: invokevirtual getDeclaredFields : ()[Ljava/lang/reflect/Field;
    //   61: astore_3
    //   62: aload_3
    //   63: arraylength
    //   64: istore #4
    //   66: iconst_0
    //   67: istore #5
    //   69: iload #5
    //   71: iload #4
    //   73: if_icmpge -> 210
    //   76: aload_3
    //   77: iload #5
    //   79: aaload
    //   80: astore #6
    //   82: aload #6
    //   84: invokevirtual getModifiers : ()I
    //   87: invokestatic isStatic : (I)Z
    //   90: ifne -> 100
    //   93: goto -> 203
    //   96: invokestatic a : (Ljava/lang/Throwable;)Ljava/lang/Throwable;
    //   99: athrow
    //   100: aload #6
    //   102: invokevirtual getType : ()Ljava/lang/Class;
    //   105: astore #7
    //   107: aload #7
    //   109: ifnull -> 190
    //   112: aload #7
    //   114: invokevirtual isPrimitive : ()Z
    //   117: ifne -> 190
    //   120: goto -> 127
    //   123: invokestatic a : (Ljava/lang/Throwable;)Ljava/lang/Throwable;
    //   126: athrow
    //   127: aload #7
    //   129: invokevirtual getPackage : ()Ljava/lang/Package;
    //   132: ifnull -> 190
    //   135: goto -> 142
    //   138: invokestatic a : (Ljava/lang/Throwable;)Ljava/lang/Throwable;
    //   141: athrow
    //   142: aload #7
    //   144: invokevirtual getPackage : ()Ljava/lang/Package;
    //   147: invokevirtual getName : ()Ljava/lang/String;
    //   150: ifnull -> 190
    //   153: goto -> 160
    //   156: invokestatic a : (Ljava/lang/Throwable;)Ljava/lang/Throwable;
    //   159: athrow
    //   160: aload #7
    //   162: invokevirtual getPackage : ()Ljava/lang/Package;
    //   165: invokevirtual getName : ()Ljava/lang/String;
    //   168: sipush #31870
    //   171: sipush #30887
    //   174: invokestatic a : (II)Ljava/lang/String;
    //   177: invokevirtual startsWith : (Ljava/lang/String;)Z
    //   180: ifne -> 190
    //   183: goto -> 190
    //   186: invokestatic a : (Ljava/lang/Throwable;)Ljava/lang/Throwable;
    //   189: athrow
    //   190: aload #6
    //   192: iconst_1
    //   193: invokevirtual setAccessible : (Z)V
    //   196: aload #6
    //   198: aconst_null
    //   199: invokevirtual get : (Ljava/lang/Object;)Ljava/lang/Object;
    //   202: pop
    //   203: iinc #5, 1
    //   206: iload_2
    //   207: ifeq -> 69
    //   210: sipush #31864
    //   213: sipush #25891
    //   216: invokestatic a : (II)Ljava/lang/String;
    //   219: invokestatic forName : (Ljava/lang/String;)Ljava/lang/Class;
    //   222: invokevirtual getDeclaredMethods : ()[Ljava/lang/reflect/Method;
    //   225: astore_3
    //   226: aload_3
    //   227: arraylength
    //   228: istore #4
    //   230: iconst_0
    //   231: istore #5
    //   233: iload #5
    //   235: iload #4
    //   237: if_icmpge -> 369
    //   240: aload_3
    //   241: iload #5
    //   243: aaload
    //   244: astore #6
    //   246: aload #6
    //   248: invokevirtual getParameterTypes : ()[Ljava/lang/Class;
    //   251: pop
    //   252: aload #6
    //   254: invokevirtual getModifiers : ()I
    //   257: invokestatic isStatic : (I)Z
    //   260: ifeq -> 355
    //   263: aload #6
    //   265: invokevirtual getParameterTypes : ()[Ljava/lang/Class;
    //   268: arraylength
    //   269: iconst_2
    //   270: if_icmpne -> 355
    //   273: goto -> 280
    //   276: invokestatic a : (Ljava/lang/Throwable;)Ljava/lang/Throwable;
    //   279: athrow
    //   280: aload #6
    //   282: invokevirtual getReturnType : ()Ljava/lang/Class;
    //   285: getstatic java/lang/Void.TYPE : Ljava/lang/Class;
    //   288: invokevirtual equals : (Ljava/lang/Object;)Z
    //   291: ifeq -> 355
    //   294: goto -> 301
    //   297: invokestatic a : (Ljava/lang/Throwable;)Ljava/lang/Throwable;
    //   300: athrow
    //   301: aload #6
    //   303: iconst_1
    //   304: invokevirtual setAccessible : (Z)V
    //   307: aload #6
    //   309: aconst_null
    //   310: iconst_2
    //   311: anewarray java/lang/Object
    //   314: dup
    //   315: iconst_0
    //   316: aload_0
    //   317: aastore
    //   318: dup
    //   319: iconst_1
    //   320: aload_1
    //   321: ifnonnull -> 339
    //   324: goto -> 331
    //   327: invokestatic a : (Ljava/lang/Throwable;)Ljava/lang/Throwable;
    //   330: athrow
    //   331: aload_1
    //   332: goto -> 346
    //   335: invokestatic a : (Ljava/lang/Throwable;)Ljava/lang/Throwable;
    //   338: athrow
    //   339: aload_1
    //   340: checkcast [B
    //   343: invokevirtual clone : ()Ljava/lang/Object;
    //   346: aastore
    //   347: invokevirtual invoke : (Ljava/lang/Object;[Ljava/lang/Object;)Ljava/lang/Object;
    //   350: pop
    //   351: iload_2
    //   352: ifeq -> 369
    //   355: iinc #5, 1
    //   358: iload_2
    //   359: ifeq -> 233
    //   362: goto -> 369
    //   365: invokestatic a : (Ljava/lang/Throwable;)Ljava/lang/Throwable;
    //   368: athrow
    //   369: new java/io/ByteArrayOutputStream
    //   372: dup
    //   373: invokespecial <init> : ()V
    //   376: astore_3
    //   377: sipush #31840
    //   380: aload_3
    //   381: sipush #202
    //   384: invokevirtual write : (I)V
    //   387: sipush #-12601
    //   390: aload_3
    //   391: sipush #254
    //   394: invokevirtual write : (I)V
    //   397: aload_3
    //   398: sipush #186
    //   401: invokevirtual write : (I)V
    //   404: aload_3
    //   405: sipush #190
    //   408: invokevirtual write : (I)V
    //   411: aload_3
    //   412: iconst_0
    //   413: invokevirtual write : (I)V
    //   416: aload_3
    //   417: iconst_1
    //   418: invokevirtual write : (I)V
    //   421: aload_3
    //   422: iconst_0
    //   423: invokevirtual write : (I)V
    //   426: aload_3
    //   427: bipush #50
    //   429: invokevirtual write : (I)V
    //   432: aload_3
    //   433: getstatic burp/Zg2z.ZU : Ljava/lang/Object;
    //   436: checkcast java/math/BigInteger
    //   439: invokevirtual toByteArray : ()[B
    //   442: invokevirtual write : ([B)V
    //   445: aload_3
    //   446: getstatic burp/Zrbp.Z_ : Ljava/lang/Object;
    //   449: checkcast java/math/BigInteger
    //   452: invokevirtual toByteArray : ()[B
    //   455: invokevirtual write : ([B)V
    //   458: aload_3
    //   459: getstatic burp/Zg_i.ZQ : Ljava/lang/Object;
    //   462: checkcast java/math/BigInteger
    //   465: invokevirtual toByteArray : ()[B
    //   468: invokevirtual write : ([B)V
    //   471: aload_3
    //   472: invokevirtual toByteArray : ()[B
    //   475: astore #4
    //   477: aconst_null
    //   478: astore #5
    //   480: invokestatic a : (II)Ljava/lang/String;
    //   483: invokestatic forName : (Ljava/lang/String;)Ljava/lang/Class;
    //   486: invokevirtual getDeclaredMethods : ()[Ljava/lang/reflect/Method;
    //   489: astore #6
    //   491: aload #6
    //   493: arraylength
    //   494: istore #7
    //   496: iconst_0
    //   497: istore #8
    //   499: iload #8
    //   501: iload #7
    //   503: if_icmpge -> 631
    //   506: aload #6
    //   508: iload #8
    //   510: aaload
    //   511: astore #9
    //   513: aload #9
    //   515: invokevirtual getName : ()Ljava/lang/String;
    //   518: sipush #31857
    //   521: sipush #14622
    //   524: invokestatic a : (II)Ljava/lang/String;
    //   527: invokevirtual equals : (Ljava/lang/Object;)Z
    //   530: ifeq -> 624
    //   533: aload #9
    //   535: invokevirtual getParameterTypes : ()[Ljava/lang/Class;
    //   538: astore #10
    //   540: aload #10
    //   542: arraylength
    //   543: iconst_4
    //   544: if_icmpeq -> 554
    //   547: goto -> 624
    //   550: invokestatic a : (Ljava/lang/Throwable;)Ljava/lang/Throwable;
    //   553: athrow
    //   554: aload #10
    //   556: iconst_0
    //   557: aaload
    //   558: ldc java/lang/String
    //   560: if_acmpeq -> 570
    //   563: goto -> 624
    //   566: invokestatic a : (Ljava/lang/Throwable;)Ljava/lang/Throwable;
    //   569: athrow
    //   570: aload #10
    //   572: iconst_1
    //   573: aaload
    //   574: ldc [B
    //   576: if_acmpeq -> 586
    //   579: goto -> 624
    //   582: invokestatic a : (Ljava/lang/Throwable;)Ljava/lang/Throwable;
    //   585: athrow
    //   586: aload #10
    //   588: iconst_2
    //   589: aaload
    //   590: getstatic java/lang/Integer.TYPE : Ljava/lang/Class;
    //   593: if_acmpeq -> 603
    //   596: goto -> 624
    //   599: invokestatic a : (Ljava/lang/Throwable;)Ljava/lang/Throwable;
    //   602: athrow
    //   603: aload #10
    //   605: iconst_3
    //   606: aaload
    //   607: getstatic java/lang/Integer.TYPE : Ljava/lang/Class;
    //   610: if_acmpeq -> 620
    //   613: goto -> 624
    //   616: invokestatic a : (Ljava/lang/Throwable;)Ljava/lang/Throwable;
    //   619: athrow
    //   620: aload #9
    //   622: astore #5
    //   624: iinc #8, 1
    //   627: iload_2
    //   628: ifeq -> 499
    //   631: aload #5
    //   633: iconst_1
    //   634: invokevirtual setAccessible : (Z)V
    //   637: ldc burp/Zlpu
    //   639: iconst_0
    //   640: anewarray java/lang/Class
    //   643: invokevirtual getDeclaredConstructor : ([Ljava/lang/Class;)Ljava/lang/reflect/Constructor;
    //   646: astore #6
    //   648: aload #6
    //   650: iconst_1
    //   651: invokevirtual setAccessible : (Z)V
    //   654: aload #5
    //   656: aload #6
    //   658: iconst_0
    //   659: anewarray java/lang/Object
    //   662: invokevirtual newInstance : ([Ljava/lang/Object;)Ljava/lang/Object;
    //   665: iconst_4
    //   666: anewarray java/lang/Object
    //   669: dup
    //   670: iconst_0
    //   671: sipush #31848
    //   674: sipush #16743
    //   677: invokestatic a : (II)Ljava/lang/String;
    //   680: aastore
    //   681: dup
    //   682: iconst_1
    //   683: aload #4
    //   685: aastore
    //   686: dup
    //   687: iconst_2
    //   688: iconst_0
    //   689: invokestatic valueOf : (I)Ljava/lang/Integer;
    //   692: aastore
    //   693: dup
    //   694: iconst_3
    //   695: aload #4
    //   697: arraylength
    //   698: invokestatic valueOf : (I)Ljava/lang/Integer;
    //   701: aastore
    //   702: invokevirtual invoke : (Ljava/lang/Object;[Ljava/lang/Object;)Ljava/lang/Object;
    //   705: pop
    //   706: goto -> 710
    //   709: astore_3
    //   710: iconst_0
    //   711: istore_3
    //   712: getstatic burp/Zxzd.ZM : Ljava/lang/String;
    //   715: getstatic burp/Zeh9.ZY : Ljava/lang/Object;
    //   718: checkcast java/math/BigInteger
    //   721: invokevirtual intValue : ()I
    //   724: bipush #32
    //   726: irem
    //   727: invokestatic abs : (I)I
    //   730: invokevirtual charAt : (I)C
    //   733: getstatic burp/Zbo7.ZZ : Ljava/lang/String;
    //   736: getstatic burp/Zxfu.ZA : Ljava/lang/Object;
    //   739: checkcast java/math/BigInteger
    //   742: invokevirtual intValue : ()I
    //   745: bipush #32
    //   747: irem
    //   748: invokestatic abs : (I)I
    //   751: invokevirtual charAt : (I)C
    //   754: if_icmpgt -> 1098
    //   757: sipush #31849
    //   760: sipush #-16534
    //   763: invokestatic a : (II)Ljava/lang/String;
    //   766: iconst_1
    //   767: ldc burp/Zxd0
    //   769: invokevirtual getClassLoader : ()Ljava/lang/ClassLoader;
    //   772: invokestatic forName : (Ljava/lang/String;ZLjava/lang/ClassLoader;)Ljava/lang/Class;
    //   775: invokevirtual getDeclaredFields : ()[Ljava/lang/reflect/Field;
    //   778: astore #4
    //   780: aload #4
    //   782: arraylength
    //   783: istore #5
    //   785: iconst_0
    //   786: istore #6
    //   788: iload #6
    //   790: iload #5
    //   792: if_icmpge -> 930
    //   795: aload #4
    //   797: iload #6
    //   799: aaload
    //   800: astore #7
    //   802: aload #7
    //   804: invokevirtual getModifiers : ()I
    //   807: invokestatic isStatic : (I)Z
    //   810: ifne -> 820
    //   813: goto -> 923
    //   816: invokestatic a : (Ljava/lang/Throwable;)Ljava/lang/Throwable;
    //   819: athrow
    //   820: aload #7
    //   822: invokevirtual getType : ()Ljava/lang/Class;
    //   825: astore #8
    //   827: aload #8
    //   829: ifnull -> 910
    //   832: aload #8
    //   834: invokevirtual isPrimitive : ()Z
    //   837: ifne -> 910
    //   840: goto -> 847
    //   843: invokestatic a : (Ljava/lang/Throwable;)Ljava/lang/Throwable;
    //   846: athrow
    //   847: aload #8
    //   849: invokevirtual getPackage : ()Ljava/lang/Package;
    //   852: ifnull -> 910
    //   855: goto -> 862
    //   858: invokestatic a : (Ljava/lang/Throwable;)Ljava/lang/Throwable;
    //   861: athrow
    //   862: aload #8
    //   864: invokevirtual getPackage : ()Ljava/lang/Package;
    //   867: invokevirtual getName : ()Ljava/lang/String;
    //   870: ifnull -> 910
    //   873: goto -> 880
    //   876: invokestatic a : (Ljava/lang/Throwable;)Ljava/lang/Throwable;
    //   879: athrow
    //   880: aload #8
    //   882: invokevirtual getPackage : ()Ljava/lang/Package;
    //   885: invokevirtual getName : ()Ljava/lang/String;
    //   888: sipush #31855
    //   891: sipush #6779
    //   894: invokestatic a : (II)Ljava/lang/String;
    //   897: invokevirtual startsWith : (Ljava/lang/String;)Z
    //   900: ifne -> 910
    //   903: goto -> 910
    //   906: invokestatic a : (Ljava/lang/Throwable;)Ljava/lang/Throwable;
    //   909: athrow
    //   910: aload #7
    //   912: iconst_1
    //   913: invokevirtual setAccessible : (Z)V
    //   916: aload #7
    //   918: aconst_null
    //   919: invokevirtual get : (Ljava/lang/Object;)Ljava/lang/Object;
    //   922: pop
    //   923: iinc #6, 1
    //   926: iload_2
    //   927: ifeq -> 788
    //   930: sipush #31859
    //   933: bipush #-70
    //   935: invokestatic a : (II)Ljava/lang/String;
    //   938: invokestatic forName : (Ljava/lang/String;)Ljava/lang/Class;
    //   941: invokevirtual getDeclaredMethods : ()[Ljava/lang/reflect/Method;
    //   944: astore #4
    //   946: aload #4
    //   948: arraylength
    //   949: istore #5
    //   951: iconst_0
    //   952: istore #6
    //   954: iload #6
    //   956: iload #5
    //   958: if_icmpge -> 1094
    //   961: aload #4
    //   963: iload #6
    //   965: aaload
    //   966: astore #7
    //   968: aload #7
    //   970: invokevirtual getParameterTypes : ()[Ljava/lang/Class;
    //   973: pop
    //   974: aload #7
    //   976: invokevirtual getModifiers : ()I
    //   979: invokestatic isStatic : (I)Z
    //   982: ifeq -> 1080
    //   985: aload #7
    //   987: invokevirtual getParameterTypes : ()[Ljava/lang/Class;
    //   990: arraylength
    //   991: iconst_2
    //   992: if_icmpne -> 1080
    //   995: goto -> 1002
    //   998: invokestatic a : (Ljava/lang/Throwable;)Ljava/lang/Throwable;
    //   1001: athrow
    //   1002: aload #7
    //   1004: invokevirtual getReturnType : ()Ljava/lang/Class;
    //   1007: getstatic java/lang/Boolean.TYPE : Ljava/lang/Class;
    //   1010: if_acmpne -> 1080
    //   1013: goto -> 1020
    //   1016: invokestatic a : (Ljava/lang/Throwable;)Ljava/lang/Throwable;
    //   1019: athrow
    //   1020: aload #7
    //   1022: iconst_1
    //   1023: invokevirtual setAccessible : (Z)V
    //   1026: aload #7
    //   1028: aconst_null
    //   1029: iconst_2
    //   1030: anewarray java/lang/Object
    //   1033: dup
    //   1034: iconst_0
    //   1035: aload_0
    //   1036: aastore
    //   1037: dup
    //   1038: iconst_1
    //   1039: aload_1
    //   1040: ifnonnull -> 1058
    //   1043: goto -> 1050
    //   1046: invokestatic a : (Ljava/lang/Throwable;)Ljava/lang/Throwable;
    //   1049: athrow
    //   1050: aload_1
    //   1051: goto -> 1065
    //   1054: invokestatic a : (Ljava/lang/Throwable;)Ljava/lang/Throwable;
    //   1057: athrow
    //   1058: aload_1
    //   1059: checkcast [B
    //   1062: invokevirtual clone : ()Ljava/lang/Object;
    //   1065: aastore
    //   1066: invokevirtual invoke : (Ljava/lang/Object;[Ljava/lang/Object;)Ljava/lang/Object;
    //   1069: checkcast java/lang/Boolean
    //   1072: invokevirtual booleanValue : ()Z
    //   1075: istore_3
    //   1076: iload_2
    //   1077: ifeq -> 1094
    //   1080: iinc #6, 1
    //   1083: iload_2
    //   1084: ifeq -> 954
    //   1087: goto -> 1094
    //   1090: invokestatic a : (Ljava/lang/Throwable;)Ljava/lang/Throwable;
    //   1093: athrow
    //   1094: iload_2
    //   1095: ifeq -> 1436
    //   1098: sipush #31866
    //   1101: sipush #-8345
    //   1104: invokestatic a : (II)Ljava/lang/String;
    //   1107: iconst_1
    //   1108: ldc burp/Zz5h
    //   1110: invokevirtual getClassLoader : ()Ljava/lang/ClassLoader;
    //   1113: invokestatic forName : (Ljava/lang/String;ZLjava/lang/ClassLoader;)Ljava/lang/Class;
    //   1116: invokevirtual getDeclaredFields : ()[Ljava/lang/reflect/Field;
    //   1119: astore #4
    //   1121: aload #4
    //   1123: arraylength
    //   1124: istore #5
    //   1126: iconst_0
    //   1127: istore #6
    //   1129: iload #6
    //   1131: iload #5
    //   1133: if_icmpge -> 1271
    //   1136: aload #4
    //   1138: iload #6
    //   1140: aaload
    //   1141: astore #7
    //   1143: aload #7
    //   1145: invokevirtual getModifiers : ()I
    //   1148: invokestatic isStatic : (I)Z
    //   1151: ifne -> 1161
    //   1154: goto -> 1264
    //   1157: invokestatic a : (Ljava/lang/Throwable;)Ljava/lang/Throwable;
    //   1160: athrow
    //   1161: aload #7
    //   1163: invokevirtual getType : ()Ljava/lang/Class;
    //   1166: astore #8
    //   1168: aload #8
    //   1170: ifnull -> 1251
    //   1173: aload #8
    //   1175: invokevirtual isPrimitive : ()Z
    //   1178: ifne -> 1251
    //   1181: goto -> 1188
    //   1184: invokestatic a : (Ljava/lang/Throwable;)Ljava/lang/Throwable;
    //   1187: athrow
    //   1188: aload #8
    //   1190: invokevirtual getPackage : ()Ljava/lang/Package;
    //   1193: ifnull -> 1251
    //   1196: goto -> 1203
    //   1199: invokestatic a : (Ljava/lang/Throwable;)Ljava/lang/Throwable;
    //   1202: athrow
    //   1203: aload #8
    //   1205: invokevirtual getPackage : ()Ljava/lang/Package;
    //   1208: invokevirtual getName : ()Ljava/lang/String;
    //   1211: ifnull -> 1251
    //   1214: goto -> 1221
    //   1217: invokestatic a : (Ljava/lang/Throwable;)Ljava/lang/Throwable;
    //   1220: athrow
    //   1221: aload #8
    //   1223: invokevirtual getPackage : ()Ljava/lang/Package;
    //   1226: invokevirtual getName : ()Ljava/lang/String;
    //   1229: sipush #31855
    //   1232: sipush #6779
    //   1235: invokestatic a : (II)Ljava/lang/String;
    //   1238: invokevirtual startsWith : (Ljava/lang/String;)Z
    //   1241: ifne -> 1251
    //   1244: goto -> 1251
    //   1247: invokestatic a : (Ljava/lang/Throwable;)Ljava/lang/Throwable;
    //   1250: athrow
    //   1251: aload #7
    //   1253: iconst_1
    //   1254: invokevirtual setAccessible : (Z)V
    //   1257: aload #7
    //   1259: aconst_null
    //   1260: invokevirtual get : (Ljava/lang/Object;)Ljava/lang/Object;
    //   1263: pop
    //   1264: iinc #6, 1
    //   1267: iload_2
    //   1268: ifeq -> 1129
    //   1271: sipush #31842
    //   1274: sipush #26234
    //   1277: invokestatic a : (II)Ljava/lang/String;
    //   1280: invokestatic forName : (Ljava/lang/String;)Ljava/lang/Class;
    //   1283: invokevirtual getDeclaredMethods : ()[Ljava/lang/reflect/Method;
    //   1286: astore #4
    //   1288: aload #4
    //   1290: arraylength
    //   1291: istore #5
    //   1293: iconst_0
    //   1294: istore #6
    //   1296: iload #6
    //   1298: iload #5
    //   1300: if_icmpge -> 1436
    //   1303: aload #4
    //   1305: iload #6
    //   1307: aaload
    //   1308: astore #7
    //   1310: aload #7
    //   1312: invokevirtual getParameterTypes : ()[Ljava/lang/Class;
    //   1315: pop
    //   1316: aload #7
    //   1318: invokevirtual getModifiers : ()I
    //   1321: invokestatic isStatic : (I)Z
    //   1324: ifeq -> 1422
    //   1327: aload #7
    //   1329: invokevirtual getParameterTypes : ()[Ljava/lang/Class;
    //   1332: arraylength
    //   1333: iconst_2
    //   1334: if_icmpne -> 1422
    //   1337: goto -> 1344
    //   1340: invokestatic a : (Ljava/lang/Throwable;)Ljava/lang/Throwable;
    //   1343: athrow
    //   1344: aload #7
    //   1346: invokevirtual getReturnType : ()Ljava/lang/Class;
    //   1349: getstatic java/lang/Boolean.TYPE : Ljava/lang/Class;
    //   1352: if_acmpne -> 1422
    //   1355: goto -> 1362
    //   1358: invokestatic a : (Ljava/lang/Throwable;)Ljava/lang/Throwable;
    //   1361: athrow
    //   1362: aload #7
    //   1364: iconst_1
    //   1365: invokevirtual setAccessible : (Z)V
    //   1368: aload #7
    //   1370: aconst_null
    //   1371: iconst_2
    //   1372: anewarray java/lang/Object
    //   1375: dup
    //   1376: iconst_0
    //   1377: aload_0
    //   1378: aastore
    //   1379: dup
    //   1380: iconst_1
    //   1381: aload_1
    //   1382: ifnonnull -> 1400
    //   1385: goto -> 1392
    //   1388: invokestatic a : (Ljava/lang/Throwable;)Ljava/lang/Throwable;
    //   1391: athrow
    //   1392: aload_1
    //   1393: goto -> 1407
    //   1396: invokestatic a : (Ljava/lang/Throwable;)Ljava/lang/Throwable;
    //   1399: athrow
    //   1400: aload_1
    //   1401: checkcast [B
    //   1404: invokevirtual clone : ()Ljava/lang/Object;
    //   1407: aastore
    //   1408: invokevirtual invoke : (Ljava/lang/Object;[Ljava/lang/Object;)Ljava/lang/Object;
    //   1411: checkcast java/lang/Boolean
    //   1414: invokevirtual booleanValue : ()Z
    //   1417: istore_3
    //   1418: iload_2
    //   1419: ifeq -> 1436
    //   1422: iinc #6, 1
    //   1425: iload_2
    //   1426: ifeq -> 1296
    //   1429: goto -> 1436
    //   1432: invokestatic a : (Ljava/lang/Throwable;)Ljava/lang/Throwable;
    //   1435: athrow
    //   1436: iload_3
    //   1437: ifeq -> 1442
    //   1440: iload_3
    //   1441: ireturn
    //   1442: getstatic burp/Zr0g.Zf : Ljava/lang/String;
    //   1445: getstatic burp/Zsm3.ZC : Ljava/lang/Object;
    //   1448: checkcast java/math/BigInteger
    //   1451: invokevirtual intValue : ()I
    //   1454: bipush #32
    //   1456: irem
    //   1457: invokestatic abs : (I)I
    //   1460: invokevirtual charAt : (I)C
    //   1463: getstatic burp/Zl2q.ZI : Ljava/lang/String;
    //   1466: getstatic burp/Zkmx.Zu : Ljava/lang/Object;
    //   1469: checkcast java/math/BigInteger
    //   1472: invokevirtual intValue : ()I
    //   1475: bipush #32
    //   1477: irem
    //   1478: invokestatic abs : (I)I
    //   1481: invokevirtual charAt : (I)C
    //   1484: if_icmpgt -> 1829
    //   1487: sipush #31858
    //   1490: sipush #-22936
    //   1493: invokestatic a : (II)Ljava/lang/String;
    //   1496: iconst_1
    //   1497: ldc burp/Zsf3
    //   1499: invokevirtual getClassLoader : ()Ljava/lang/ClassLoader;
    //   1502: invokestatic forName : (Ljava/lang/String;ZLjava/lang/ClassLoader;)Ljava/lang/Class;
    //   1505: invokevirtual getDeclaredFields : ()[Ljava/lang/reflect/Field;
    //   1508: astore #4
    //   1510: aload #4
    //   1512: arraylength
    //   1513: istore #5
    //   1515: iconst_0
    //   1516: istore #6
    //   1518: iload #6
    //   1520: iload #5
    //   1522: if_icmpge -> 1660
    //   1525: aload #4
    //   1527: iload #6
    //   1529: aaload
    //   1530: astore #7
    //   1532: aload #7
    //   1534: invokevirtual getModifiers : ()I
    //   1537: invokestatic isStatic : (I)Z
    //   1540: ifne -> 1550
    //   1543: goto -> 1653
    //   1546: invokestatic a : (Ljava/lang/Throwable;)Ljava/lang/Throwable;
    //   1549: athrow
    //   1550: aload #7
    //   1552: invokevirtual getType : ()Ljava/lang/Class;
    //   1555: astore #8
    //   1557: aload #8
    //   1559: ifnull -> 1640
    //   1562: aload #8
    //   1564: invokevirtual isPrimitive : ()Z
    //   1567: ifne -> 1640
    //   1570: goto -> 1577
    //   1573: invokestatic a : (Ljava/lang/Throwable;)Ljava/lang/Throwable;
    //   1576: athrow
    //   1577: aload #8
    //   1579: invokevirtual getPackage : ()Ljava/lang/Package;
    //   1582: ifnull -> 1640
    //   1585: goto -> 1592
    //   1588: invokestatic a : (Ljava/lang/Throwable;)Ljava/lang/Throwable;
    //   1591: athrow
    //   1592: aload #8
    //   1594: invokevirtual getPackage : ()Ljava/lang/Package;
    //   1597: invokevirtual getName : ()Ljava/lang/String;
    //   1600: ifnull -> 1640
    //   1603: goto -> 1610
    //   1606: invokestatic a : (Ljava/lang/Throwable;)Ljava/lang/Throwable;
    //   1609: athrow
    //   1610: aload #8
    //   1612: invokevirtual getPackage : ()Ljava/lang/Package;
    //   1615: invokevirtual getName : ()Ljava/lang/String;
    //   1618: sipush #31855
    //   1621: sipush #6779
    //   1624: invokestatic a : (II)Ljava/lang/String;
    //   1627: invokevirtual startsWith : (Ljava/lang/String;)Z
    //   1630: ifne -> 1640
    //   1633: goto -> 1640
    //   1636: invokestatic a : (Ljava/lang/Throwable;)Ljava/lang/Throwable;
    //   1639: athrow
    //   1640: aload #7
    //   1642: iconst_1
    //   1643: invokevirtual setAccessible : (Z)V
    //   1646: aload #7
    //   1648: aconst_null
    //   1649: invokevirtual get : (Ljava/lang/Object;)Ljava/lang/Object;
    //   1652: pop
    //   1653: iinc #6, 1
    //   1656: iload_2
    //   1657: ifeq -> 1518
    //   1660: sipush #31865
    //   1663: sipush #-7280
    //   1666: invokestatic a : (II)Ljava/lang/String;
    //   1669: invokestatic forName : (Ljava/lang/String;)Ljava/lang/Class;
    //   1672: invokevirtual getDeclaredMethods : ()[Ljava/lang/reflect/Method;
    //   1675: astore #4
    //   1677: aload #4
    //   1679: arraylength
    //   1680: istore #5
    //   1682: iconst_0
    //   1683: istore #6
    //   1685: iload #6
    //   1687: iload #5
    //   1689: if_icmpge -> 1825
    //   1692: aload #4
    //   1694: iload #6
    //   1696: aaload
    //   1697: astore #7
    //   1699: aload #7
    //   1701: invokevirtual getParameterTypes : ()[Ljava/lang/Class;
    //   1704: pop
    //   1705: aload #7
    //   1707: invokevirtual getModifiers : ()I
    //   1710: invokestatic isStatic : (I)Z
    //   1713: ifeq -> 1811
    //   1716: aload #7
    //   1718: invokevirtual getParameterTypes : ()[Ljava/lang/Class;
    //   1721: arraylength
    //   1722: iconst_2
    //   1723: if_icmpne -> 1811
    //   1726: goto -> 1733
    //   1729: invokestatic a : (Ljava/lang/Throwable;)Ljava/lang/Throwable;
    //   1732: athrow
    //   1733: aload #7
    //   1735: invokevirtual getReturnType : ()Ljava/lang/Class;
    //   1738: getstatic java/lang/Boolean.TYPE : Ljava/lang/Class;
    //   1741: if_acmpne -> 1811
    //   1744: goto -> 1751
    //   1747: invokestatic a : (Ljava/lang/Throwable;)Ljava/lang/Throwable;
    //   1750: athrow
    //   1751: aload #7
    //   1753: iconst_1
    //   1754: invokevirtual setAccessible : (Z)V
    //   1757: aload #7
    //   1759: aconst_null
    //   1760: iconst_2
    //   1761: anewarray java/lang/Object
    //   1764: dup
    //   1765: iconst_0
    //   1766: aload_0
    //   1767: aastore
    //   1768: dup
    //   1769: iconst_1
    //   1770: aload_1
    //   1771: ifnonnull -> 1789
    //   1774: goto -> 1781
    //   1777: invokestatic a : (Ljava/lang/Throwable;)Ljava/lang/Throwable;
    //   1780: athrow
    //   1781: aload_1
    //   1782: goto -> 1796
    //   1785: invokestatic a : (Ljava/lang/Throwable;)Ljava/lang/Throwable;
    //   1788: athrow
    //   1789: aload_1
    //   1790: checkcast [B
    //   1793: invokevirtual clone : ()Ljava/lang/Object;
    //   1796: aastore
    //   1797: invokevirtual invoke : (Ljava/lang/Object;[Ljava/lang/Object;)Ljava/lang/Object;
    //   1800: checkcast java/lang/Boolean
    //   1803: invokevirtual booleanValue : ()Z
    //   1806: istore_3
    //   1807: iload_2
    //   1808: ifeq -> 1825
    //   1811: iinc #6, 1
    //   1814: iload_2
    //   1815: ifeq -> 1685
    //   1818: goto -> 1825
    //   1821: invokestatic a : (Ljava/lang/Throwable;)Ljava/lang/Throwable;
    //   1824: athrow
    //   1825: iload_2
    //   1826: ifeq -> 2167
    //   1829: sipush #31846
    //   1832: sipush #-13240
    //   1835: invokestatic a : (II)Ljava/lang/String;
    //   1838: iconst_1
    //   1839: ldc burp/Zs0b
    //   1841: invokevirtual getClassLoader : ()Ljava/lang/ClassLoader;
    //   1844: invokestatic forName : (Ljava/lang/String;ZLjava/lang/ClassLoader;)Ljava/lang/Class;
    //   1847: invokevirtual getDeclaredFields : ()[Ljava/lang/reflect/Field;
    //   1850: astore #4
    //   1852: aload #4
    //   1854: arraylength
    //   1855: istore #5
    //   1857: iconst_0
    //   1858: istore #6
    //   1860: iload #6
    //   1862: iload #5
    //   1864: if_icmpge -> 2002
    //   1867: aload #4
    //   1869: iload #6
    //   1871: aaload
    //   1872: astore #7
    //   1874: aload #7
    //   1876: invokevirtual getModifiers : ()I
    //   1879: invokestatic isStatic : (I)Z
    //   1882: ifne -> 1892
    //   1885: goto -> 1995
    //   1888: invokestatic a : (Ljava/lang/Throwable;)Ljava/lang/Throwable;
    //   1891: athrow
    //   1892: aload #7
    //   1894: invokevirtual getType : ()Ljava/lang/Class;
    //   1897: astore #8
    //   1899: aload #8
    //   1901: ifnull -> 1982
    //   1904: aload #8
    //   1906: invokevirtual isPrimitive : ()Z
    //   1909: ifne -> 1982
    //   1912: goto -> 1919
    //   1915: invokestatic a : (Ljava/lang/Throwable;)Ljava/lang/Throwable;
    //   1918: athrow
    //   1919: aload #8
    //   1921: invokevirtual getPackage : ()Ljava/lang/Package;
    //   1924: ifnull -> 1982
    //   1927: goto -> 1934
    //   1930: invokestatic a : (Ljava/lang/Throwable;)Ljava/lang/Throwable;
    //   1933: athrow
    //   1934: aload #8
    //   1936: invokevirtual getPackage : ()Ljava/lang/Package;
    //   1939: invokevirtual getName : ()Ljava/lang/String;
    //   1942: ifnull -> 1982
    //   1945: goto -> 1952
    //   1948: invokestatic a : (Ljava/lang/Throwable;)Ljava/lang/Throwable;
    //   1951: athrow
    //   1952: aload #8
    //   1954: invokevirtual getPackage : ()Ljava/lang/Package;
    //   1957: invokevirtual getName : ()Ljava/lang/String;
    //   1960: sipush #31855
    //   1963: sipush #6779
    //   1966: invokestatic a : (II)Ljava/lang/String;
    //   1969: invokevirtual startsWith : (Ljava/lang/String;)Z
    //   1972: ifne -> 1982
    //   1975: goto -> 1982
    //   1978: invokestatic a : (Ljava/lang/Throwable;)Ljava/lang/Throwable;
    //   1981: athrow
    //   1982: aload #7
    //   1984: iconst_1
    //   1985: invokevirtual setAccessible : (Z)V
    //   1988: aload #7
    //   1990: aconst_null
    //   1991: invokevirtual get : (Ljava/lang/Object;)Ljava/lang/Object;
    //   1994: pop
    //   1995: iinc #6, 1
    //   1998: iload_2
    //   1999: ifeq -> 1860
    //   2002: sipush #31844
    //   2005: sipush #28476
    //   2008: invokestatic a : (II)Ljava/lang/String;
    //   2011: invokestatic forName : (Ljava/lang/String;)Ljava/lang/Class;
    //   2014: invokevirtual getDeclaredMethods : ()[Ljava/lang/reflect/Method;
    //   2017: astore #4
    //   2019: aload #4
    //   2021: arraylength
    //   2022: istore #5
    //   2024: iconst_0
    //   2025: istore #6
    //   2027: iload #6
    //   2029: iload #5
    //   2031: if_icmpge -> 2167
    //   2034: aload #4
    //   2036: iload #6
    //   2038: aaload
    //   2039: astore #7
    //   2041: aload #7
    //   2043: invokevirtual getParameterTypes : ()[Ljava/lang/Class;
    //   2046: pop
    //   2047: aload #7
    //   2049: invokevirtual getModifiers : ()I
    //   2052: invokestatic isStatic : (I)Z
    //   2055: ifeq -> 2153
    //   2058: aload #7
    //   2060: invokevirtual getParameterTypes : ()[Ljava/lang/Class;
    //   2063: arraylength
    //   2064: iconst_2
    //   2065: if_icmpne -> 2153
    //   2068: goto -> 2075
    //   2071: invokestatic a : (Ljava/lang/Throwable;)Ljava/lang/Throwable;
    //   2074: athrow
    //   2075: aload #7
    //   2077: invokevirtual getReturnType : ()Ljava/lang/Class;
    //   2080: getstatic java/lang/Boolean.TYPE : Ljava/lang/Class;
    //   2083: if_acmpne -> 2153
    //   2086: goto -> 2093
    //   2089: invokestatic a : (Ljava/lang/Throwable;)Ljava/lang/Throwable;
    //   2092: athrow
    //   2093: aload #7
    //   2095: iconst_1
    //   2096: invokevirtual setAccessible : (Z)V
    //   2099: aload #7
    //   2101: aconst_null
    //   2102: iconst_2
    //   2103: anewarray java/lang/Object
    //   2106: dup
    //   2107: iconst_0
    //   2108: aload_0
    //   2109: aastore
    //   2110: dup
    //   2111: iconst_1
    //   2112: aload_1
    //   2113: ifnonnull -> 2131
    //   2116: goto -> 2123
    //   2119: invokestatic a : (Ljava/lang/Throwable;)Ljava/lang/Throwable;
    //   2122: athrow
    //   2123: aload_1
    //   2124: goto -> 2138
    //   2127: invokestatic a : (Ljava/lang/Throwable;)Ljava/lang/Throwable;
    //   2130: athrow
    //   2131: aload_1
    //   2132: checkcast [B
    //   2135: invokevirtual clone : ()Ljava/lang/Object;
    //   2138: aastore
    //   2139: invokevirtual invoke : (Ljava/lang/Object;[Ljava/lang/Object;)Ljava/lang/Object;
    //   2142: checkcast java/lang/Boolean
    //   2145: invokevirtual booleanValue : ()Z
    //   2148: istore_3
    //   2149: iload_2
    //   2150: ifeq -> 2167
    //   2153: iinc #6, 1
    //   2156: iload_2
    //   2157: ifeq -> 2027
    //   2160: goto -> 2167
    //   2163: invokestatic a : (Ljava/lang/Throwable;)Ljava/lang/Throwable;
    //   2166: athrow
    //   2167: iload_3
    //   2168: ifeq -> 2173
    //   2171: iload_3
    //   2172: ireturn
    //   2173: getstatic burp/Zt3l.Zi : Ljava/lang/String;
    //   2176: getstatic burp/Zz1k.ZP : Ljava/lang/Object;
    //   2179: checkcast java/math/BigInteger
    //   2182: invokevirtual intValue : ()I
    //   2185: bipush #32
    //   2187: irem
    //   2188: invokestatic abs : (I)I
    //   2191: invokevirtual charAt : (I)C
    //   2194: getstatic burp/Zxyp.Z_ : Ljava/lang/String;
    //   2197: getstatic burp/Zx54.Zn : Ljava/lang/Object;
    //   2200: checkcast java/math/BigInteger
    //   2203: invokevirtual intValue : ()I
    //   2206: bipush #32
    //   2208: irem
    //   2209: invokestatic abs : (I)I
    //   2212: invokevirtual charAt : (I)C
    //   2215: if_icmpgt -> 2560
    //   2218: sipush #31853
    //   2221: sipush #-27941
    //   2224: invokestatic a : (II)Ljava/lang/String;
    //   2227: iconst_1
    //   2228: ldc burp/Zxo4
    //   2230: invokevirtual getClassLoader : ()Ljava/lang/ClassLoader;
    //   2233: invokestatic forName : (Ljava/lang/String;ZLjava/lang/ClassLoader;)Ljava/lang/Class;
    //   2236: invokevirtual getDeclaredFields : ()[Ljava/lang/reflect/Field;
    //   2239: astore #4
    //   2241: aload #4
    //   2243: arraylength
    //   2244: istore #5
    //   2246: iconst_0
    //   2247: istore #6
    //   2249: iload #6
    //   2251: iload #5
    //   2253: if_icmpge -> 2391
    //   2256: aload #4
    //   2258: iload #6
    //   2260: aaload
    //   2261: astore #7
    //   2263: aload #7
    //   2265: invokevirtual getModifiers : ()I
    //   2268: invokestatic isStatic : (I)Z
    //   2271: ifne -> 2281
    //   2274: goto -> 2384
    //   2277: invokestatic a : (Ljava/lang/Throwable;)Ljava/lang/Throwable;
    //   2280: athrow
    //   2281: aload #7
    //   2283: invokevirtual getType : ()Ljava/lang/Class;
    //   2286: astore #8
    //   2288: aload #8
    //   2290: ifnull -> 2371
    //   2293: aload #8
    //   2295: invokevirtual isPrimitive : ()Z
    //   2298: ifne -> 2371
    //   2301: goto -> 2308
    //   2304: invokestatic a : (Ljava/lang/Throwable;)Ljava/lang/Throwable;
    //   2307: athrow
    //   2308: aload #8
    //   2310: invokevirtual getPackage : ()Ljava/lang/Package;
    //   2313: ifnull -> 2371
    //   2316: goto -> 2323
    //   2319: invokestatic a : (Ljava/lang/Throwable;)Ljava/lang/Throwable;
    //   2322: athrow
    //   2323: aload #8
    //   2325: invokevirtual getPackage : ()Ljava/lang/Package;
    //   2328: invokevirtual getName : ()Ljava/lang/String;
    //   2331: ifnull -> 2371
    //   2334: goto -> 2341
    //   2337: invokestatic a : (Ljava/lang/Throwable;)Ljava/lang/Throwable;
    //   2340: athrow
    //   2341: aload #8
    //   2343: invokevirtual getPackage : ()Ljava/lang/Package;
    //   2346: invokevirtual getName : ()Ljava/lang/String;
    //   2349: sipush #31855
    //   2352: sipush #6779
    //   2355: invokestatic a : (II)Ljava/lang/String;
    //   2358: invokevirtual startsWith : (Ljava/lang/String;)Z
    //   2361: ifne -> 2371
    //   2364: goto -> 2371
    //   2367: invokestatic a : (Ljava/lang/Throwable;)Ljava/lang/Throwable;
    //   2370: athrow
    //   2371: aload #7
    //   2373: iconst_1
    //   2374: invokevirtual setAccessible : (Z)V
    //   2377: aload #7
    //   2379: aconst_null
    //   2380: invokevirtual get : (Ljava/lang/Object;)Ljava/lang/Object;
    //   2383: pop
    //   2384: iinc #6, 1
    //   2387: iload_2
    //   2388: ifeq -> 2249
    //   2391: sipush #31851
    //   2394: sipush #-4608
    //   2397: invokestatic a : (II)Ljava/lang/String;
    //   2400: invokestatic forName : (Ljava/lang/String;)Ljava/lang/Class;
    //   2403: invokevirtual getDeclaredMethods : ()[Ljava/lang/reflect/Method;
    //   2406: astore #4
    //   2408: aload #4
    //   2410: arraylength
    //   2411: istore #5
    //   2413: iconst_0
    //   2414: istore #6
    //   2416: iload #6
    //   2418: iload #5
    //   2420: if_icmpge -> 2556
    //   2423: aload #4
    //   2425: iload #6
    //   2427: aaload
    //   2428: astore #7
    //   2430: aload #7
    //   2432: invokevirtual getParameterTypes : ()[Ljava/lang/Class;
    //   2435: pop
    //   2436: aload #7
    //   2438: invokevirtual getModifiers : ()I
    //   2441: invokestatic isStatic : (I)Z
    //   2444: ifeq -> 2542
    //   2447: aload #7
    //   2449: invokevirtual getParameterTypes : ()[Ljava/lang/Class;
    //   2452: arraylength
    //   2453: iconst_2
    //   2454: if_icmpne -> 2542
    //   2457: goto -> 2464
    //   2460: invokestatic a : (Ljava/lang/Throwable;)Ljava/lang/Throwable;
    //   2463: athrow
    //   2464: aload #7
    //   2466: invokevirtual getReturnType : ()Ljava/lang/Class;
    //   2469: getstatic java/lang/Boolean.TYPE : Ljava/lang/Class;
    //   2472: if_acmpne -> 2542
    //   2475: goto -> 2482
    //   2478: invokestatic a : (Ljava/lang/Throwable;)Ljava/lang/Throwable;
    //   2481: athrow
    //   2482: aload #7
    //   2484: iconst_1
    //   2485: invokevirtual setAccessible : (Z)V
    //   2488: aload #7
    //   2490: aconst_null
    //   2491: iconst_2
    //   2492: anewarray java/lang/Object
    //   2495: dup
    //   2496: iconst_0
    //   2497: aload_0
    //   2498: aastore
    //   2499: dup
    //   2500: iconst_1
    //   2501: aload_1
    //   2502: ifnonnull -> 2520
    //   2505: goto -> 2512
    //   2508: invokestatic a : (Ljava/lang/Throwable;)Ljava/lang/Throwable;
    //   2511: athrow
    //   2512: aload_1
    //   2513: goto -> 2527
    //   2516: invokestatic a : (Ljava/lang/Throwable;)Ljava/lang/Throwable;
    //   2519: athrow
    //   2520: aload_1
    //   2521: checkcast [B
    //   2524: invokevirtual clone : ()Ljava/lang/Object;
    //   2527: aastore
    //   2528: invokevirtual invoke : (Ljava/lang/Object;[Ljava/lang/Object;)Ljava/lang/Object;
    //   2531: checkcast java/lang/Boolean
    //   2534: invokevirtual booleanValue : ()Z
    //   2537: istore_3
    //   2538: iload_2
    //   2539: ifeq -> 2556
    //   2542: iinc #6, 1
    //   2545: iload_2
    //   2546: ifeq -> 2416
    //   2549: goto -> 2556
    //   2552: invokestatic a : (Ljava/lang/Throwable;)Ljava/lang/Throwable;
    //   2555: athrow
    //   2556: iload_2
    //   2557: ifeq -> 2898
    //   2560: sipush #31852
    //   2563: sipush #7806
    //   2566: invokestatic a : (II)Ljava/lang/String;
    //   2569: iconst_1
    //   2570: ldc burp/Zry0
    //   2572: invokevirtual getClassLoader : ()Ljava/lang/ClassLoader;
    //   2575: invokestatic forName : (Ljava/lang/String;ZLjava/lang/ClassLoader;)Ljava/lang/Class;
    //   2578: invokevirtual getDeclaredFields : ()[Ljava/lang/reflect/Field;
    //   2581: astore #4
    //   2583: aload #4
    //   2585: arraylength
    //   2586: istore #5
    //   2588: iconst_0
    //   2589: istore #6
    //   2591: iload #6
    //   2593: iload #5
    //   2595: if_icmpge -> 2733
    //   2598: aload #4
    //   2600: iload #6
    //   2602: aaload
    //   2603: astore #7
    //   2605: aload #7
    //   2607: invokevirtual getModifiers : ()I
    //   2610: invokestatic isStatic : (I)Z
    //   2613: ifne -> 2623
    //   2616: goto -> 2726
    //   2619: invokestatic a : (Ljava/lang/Throwable;)Ljava/lang/Throwable;
    //   2622: athrow
    //   2623: aload #7
    //   2625: invokevirtual getType : ()Ljava/lang/Class;
    //   2628: astore #8
    //   2630: aload #8
    //   2632: ifnull -> 2713
    //   2635: aload #8
    //   2637: invokevirtual isPrimitive : ()Z
    //   2640: ifne -> 2713
    //   2643: goto -> 2650
    //   2646: invokestatic a : (Ljava/lang/Throwable;)Ljava/lang/Throwable;
    //   2649: athrow
    //   2650: aload #8
    //   2652: invokevirtual getPackage : ()Ljava/lang/Package;
    //   2655: ifnull -> 2713
    //   2658: goto -> 2665
    //   2661: invokestatic a : (Ljava/lang/Throwable;)Ljava/lang/Throwable;
    //   2664: athrow
    //   2665: aload #8
    //   2667: invokevirtual getPackage : ()Ljava/lang/Package;
    //   2670: invokevirtual getName : ()Ljava/lang/String;
    //   2673: ifnull -> 2713
    //   2676: goto -> 2683
    //   2679: invokestatic a : (Ljava/lang/Throwable;)Ljava/lang/Throwable;
    //   2682: athrow
    //   2683: aload #8
    //   2685: invokevirtual getPackage : ()Ljava/lang/Package;
    //   2688: invokevirtual getName : ()Ljava/lang/String;
    //   2691: sipush #31855
    //   2694: sipush #6779
    //   2697: invokestatic a : (II)Ljava/lang/String;
    //   2700: invokevirtual startsWith : (Ljava/lang/String;)Z
    //   2703: ifne -> 2713
    //   2706: goto -> 2713
    //   2709: invokestatic a : (Ljava/lang/Throwable;)Ljava/lang/Throwable;
    //   2712: athrow
    //   2713: aload #7
    //   2715: iconst_1
    //   2716: invokevirtual setAccessible : (Z)V
    //   2719: aload #7
    //   2721: aconst_null
    //   2722: invokevirtual get : (Ljava/lang/Object;)Ljava/lang/Object;
    //   2725: pop
    //   2726: iinc #6, 1
    //   2729: iload_2
    //   2730: ifeq -> 2591
    //   2733: sipush #31845
    //   2736: sipush #26003
    //   2739: invokestatic a : (II)Ljava/lang/String;
    //   2742: invokestatic forName : (Ljava/lang/String;)Ljava/lang/Class;
    //   2745: invokevirtual getDeclaredMethods : ()[Ljava/lang/reflect/Method;
    //   2748: astore #4
    //   2750: aload #4
    //   2752: arraylength
    //   2753: istore #5
    //   2755: iconst_0
    //   2756: istore #6
    //   2758: iload #6
    //   2760: iload #5
    //   2762: if_icmpge -> 2898
    //   2765: aload #4
    //   2767: iload #6
    //   2769: aaload
    //   2770: astore #7
    //   2772: aload #7
    //   2774: invokevirtual getParameterTypes : ()[Ljava/lang/Class;
    //   2777: pop
    //   2778: aload #7
    //   2780: invokevirtual getModifiers : ()I
    //   2783: invokestatic isStatic : (I)Z
    //   2786: ifeq -> 2884
    //   2789: aload #7
    //   2791: invokevirtual getParameterTypes : ()[Ljava/lang/Class;
    //   2794: arraylength
    //   2795: iconst_2
    //   2796: if_icmpne -> 2884
    //   2799: goto -> 2806
    //   2802: invokestatic a : (Ljava/lang/Throwable;)Ljava/lang/Throwable;
    //   2805: athrow
    //   2806: aload #7
    //   2808: invokevirtual getReturnType : ()Ljava/lang/Class;
    //   2811: getstatic java/lang/Boolean.TYPE : Ljava/lang/Class;
    //   2814: if_acmpne -> 2884
    //   2817: goto -> 2824
    //   2820: invokestatic a : (Ljava/lang/Throwable;)Ljava/lang/Throwable;
    //   2823: athrow
    //   2824: aload #7
    //   2826: iconst_1
    //   2827: invokevirtual setAccessible : (Z)V
    //   2830: aload #7
    //   2832: aconst_null
    //   2833: iconst_2
    //   2834: anewarray java/lang/Object
    //   2837: dup
    //   2838: iconst_0
    //   2839: aload_0
    //   2840: aastore
    //   2841: dup
    //   2842: iconst_1
    //   2843: aload_1
    //   2844: ifnonnull -> 2862
    //   2847: goto -> 2854
    //   2850: invokestatic a : (Ljava/lang/Throwable;)Ljava/lang/Throwable;
    //   2853: athrow
    //   2854: aload_1
    //   2855: goto -> 2869
    //   2858: invokestatic a : (Ljava/lang/Throwable;)Ljava/lang/Throwable;
    //   2861: athrow
    //   2862: aload_1
    //   2863: checkcast [B
    //   2866: invokevirtual clone : ()Ljava/lang/Object;
    //   2869: aastore
    //   2870: invokevirtual invoke : (Ljava/lang/Object;[Ljava/lang/Object;)Ljava/lang/Object;
    //   2873: checkcast java/lang/Boolean
    //   2876: invokevirtual booleanValue : ()Z
    //   2879: istore_3
    //   2880: iload_2
    //   2881: ifeq -> 2898
    //   2884: iinc #6, 1
    //   2887: iload_2
    //   2888: ifeq -> 2758
    //   2891: goto -> 2898
    //   2894: invokestatic a : (Ljava/lang/Throwable;)Ljava/lang/Throwable;
    //   2897: athrow
    //   2898: iload_3
    //   2899: ifeq -> 2904
    //   2902: iload_3
    //   2903: ireturn
    //   2904: getstatic burp/Zkyc.ZK : Ljava/lang/String;
    //   2907: getstatic burp/Zmj4.Zm : Ljava/lang/Object;
    //   2910: checkcast java/math/BigInteger
    //   2913: invokevirtual intValue : ()I
    //   2916: bipush #32
    //   2918: irem
    //   2919: invokestatic abs : (I)I
    //   2922: invokevirtual charAt : (I)C
    //   2925: getstatic burp/Zg_p.ZO : Ljava/lang/String;
    //   2928: getstatic burp/Zxfu.ZA : Ljava/lang/Object;
    //   2931: checkcast java/math/BigInteger
    //   2934: invokevirtual intValue : ()I
    //   2937: bipush #32
    //   2939: irem
    //   2940: invokestatic abs : (I)I
    //   2943: invokevirtual charAt : (I)C
    //   2946: if_icmple -> 3291
    //   2949: sipush #31856
    //   2952: sipush #15806
    //   2955: invokestatic a : (II)Ljava/lang/String;
    //   2958: iconst_1
    //   2959: ldc burp/Zrh1
    //   2961: invokevirtual getClassLoader : ()Ljava/lang/ClassLoader;
    //   2964: invokestatic forName : (Ljava/lang/String;ZLjava/lang/ClassLoader;)Ljava/lang/Class;
    //   2967: invokevirtual getDeclaredFields : ()[Ljava/lang/reflect/Field;
    //   2970: astore #4
    //   2972: aload #4
    //   2974: arraylength
    //   2975: istore #5
    //   2977: iconst_0
    //   2978: istore #6
    //   2980: iload #6
    //   2982: iload #5
    //   2984: if_icmpge -> 3122
    //   2987: aload #4
    //   2989: iload #6
    //   2991: aaload
    //   2992: astore #7
    //   2994: aload #7
    //   2996: invokevirtual getModifiers : ()I
    //   2999: invokestatic isStatic : (I)Z
    //   3002: ifne -> 3012
    //   3005: goto -> 3115
    //   3008: invokestatic a : (Ljava/lang/Throwable;)Ljava/lang/Throwable;
    //   3011: athrow
    //   3012: aload #7
    //   3014: invokevirtual getType : ()Ljava/lang/Class;
    //   3017: astore #8
    //   3019: aload #8
    //   3021: ifnull -> 3102
    //   3024: aload #8
    //   3026: invokevirtual isPrimitive : ()Z
    //   3029: ifne -> 3102
    //   3032: goto -> 3039
    //   3035: invokestatic a : (Ljava/lang/Throwable;)Ljava/lang/Throwable;
    //   3038: athrow
    //   3039: aload #8
    //   3041: invokevirtual getPackage : ()Ljava/lang/Package;
    //   3044: ifnull -> 3102
    //   3047: goto -> 3054
    //   3050: invokestatic a : (Ljava/lang/Throwable;)Ljava/lang/Throwable;
    //   3053: athrow
    //   3054: aload #8
    //   3056: invokevirtual getPackage : ()Ljava/lang/Package;
    //   3059: invokevirtual getName : ()Ljava/lang/String;
    //   3062: ifnull -> 3102
    //   3065: goto -> 3072
    //   3068: invokestatic a : (Ljava/lang/Throwable;)Ljava/lang/Throwable;
    //   3071: athrow
    //   3072: aload #8
    //   3074: invokevirtual getPackage : ()Ljava/lang/Package;
    //   3077: invokevirtual getName : ()Ljava/lang/String;
    //   3080: sipush #31855
    //   3083: sipush #6779
    //   3086: invokestatic a : (II)Ljava/lang/String;
    //   3089: invokevirtual startsWith : (Ljava/lang/String;)Z
    //   3092: ifne -> 3102
    //   3095: goto -> 3102
    //   3098: invokestatic a : (Ljava/lang/Throwable;)Ljava/lang/Throwable;
    //   3101: athrow
    //   3102: aload #7
    //   3104: iconst_1
    //   3105: invokevirtual setAccessible : (Z)V
    //   3108: aload #7
    //   3110: aconst_null
    //   3111: invokevirtual get : (Ljava/lang/Object;)Ljava/lang/Object;
    //   3114: pop
    //   3115: iinc #6, 1
    //   3118: iload_2
    //   3119: ifeq -> 2980
    //   3122: sipush #31841
    //   3125: sipush #-5251
    //   3128: invokestatic a : (II)Ljava/lang/String;
    //   3131: invokestatic forName : (Ljava/lang/String;)Ljava/lang/Class;
    //   3134: invokevirtual getDeclaredMethods : ()[Ljava/lang/reflect/Method;
    //   3137: astore #4
    //   3139: aload #4
    //   3141: arraylength
    //   3142: istore #5
    //   3144: iconst_0
    //   3145: istore #6
    //   3147: iload #6
    //   3149: iload #5
    //   3151: if_icmpge -> 3287
    //   3154: aload #4
    //   3156: iload #6
    //   3158: aaload
    //   3159: astore #7
    //   3161: aload #7
    //   3163: invokevirtual getParameterTypes : ()[Ljava/lang/Class;
    //   3166: pop
    //   3167: aload #7
    //   3169: invokevirtual getModifiers : ()I
    //   3172: invokestatic isStatic : (I)Z
    //   3175: ifeq -> 3273
    //   3178: aload #7
    //   3180: invokevirtual getParameterTypes : ()[Ljava/lang/Class;
    //   3183: arraylength
    //   3184: iconst_2
    //   3185: if_icmpne -> 3273
    //   3188: goto -> 3195
    //   3191: invokestatic a : (Ljava/lang/Throwable;)Ljava/lang/Throwable;
    //   3194: athrow
    //   3195: aload #7
    //   3197: invokevirtual getReturnType : ()Ljava/lang/Class;
    //   3200: getstatic java/lang/Boolean.TYPE : Ljava/lang/Class;
    //   3203: if_acmpne -> 3273
    //   3206: goto -> 3213
    //   3209: invokestatic a : (Ljava/lang/Throwable;)Ljava/lang/Throwable;
    //   3212: athrow
    //   3213: aload #7
    //   3215: iconst_1
    //   3216: invokevirtual setAccessible : (Z)V
    //   3219: aload #7
    //   3221: aconst_null
    //   3222: iconst_2
    //   3223: anewarray java/lang/Object
    //   3226: dup
    //   3227: iconst_0
    //   3228: aload_0
    //   3229: aastore
    //   3230: dup
    //   3231: iconst_1
    //   3232: aload_1
    //   3233: ifnonnull -> 3251
    //   3236: goto -> 3243
    //   3239: invokestatic a : (Ljava/lang/Throwable;)Ljava/lang/Throwable;
    //   3242: athrow
    //   3243: aload_1
    //   3244: goto -> 3258
    //   3247: invokestatic a : (Ljava/lang/Throwable;)Ljava/lang/Throwable;
    //   3250: athrow
    //   3251: aload_1
    //   3252: checkcast [B
    //   3255: invokevirtual clone : ()Ljava/lang/Object;
    //   3258: aastore
    //   3259: invokevirtual invoke : (Ljava/lang/Object;[Ljava/lang/Object;)Ljava/lang/Object;
    //   3262: checkcast java/lang/Boolean
    //   3265: invokevirtual booleanValue : ()Z
    //   3268: istore_3
    //   3269: iload_2
    //   3270: ifeq -> 3287
    //   3273: iinc #6, 1
    //   3276: iload_2
    //   3277: ifeq -> 3147
    //   3280: goto -> 3287
    //   3283: invokestatic a : (Ljava/lang/Throwable;)Ljava/lang/Throwable;
    //   3286: athrow
    //   3287: iload_2
    //   3288: ifeq -> 3629
    //   3291: sipush #31843
    //   3294: sipush #-15641
    //   3297: invokestatic a : (II)Ljava/lang/String;
    //   3300: iconst_1
    //   3301: ldc burp/Zkm0
    //   3303: invokevirtual getClassLoader : ()Ljava/lang/ClassLoader;
    //   3306: invokestatic forName : (Ljava/lang/String;ZLjava/lang/ClassLoader;)Ljava/lang/Class;
    //   3309: invokevirtual getDeclaredFields : ()[Ljava/lang/reflect/Field;
    //   3312: astore #4
    //   3314: aload #4
    //   3316: arraylength
    //   3317: istore #5
    //   3319: iconst_0
    //   3320: istore #6
    //   3322: iload #6
    //   3324: iload #5
    //   3326: if_icmpge -> 3464
    //   3329: aload #4
    //   3331: iload #6
    //   3333: aaload
    //   3334: astore #7
    //   3336: aload #7
    //   3338: invokevirtual getModifiers : ()I
    //   3341: invokestatic isStatic : (I)Z
    //   3344: ifne -> 3354
    //   3347: goto -> 3457
    //   3350: invokestatic a : (Ljava/lang/Throwable;)Ljava/lang/Throwable;
    //   3353: athrow
    //   3354: aload #7
    //   3356: invokevirtual getType : ()Ljava/lang/Class;
    //   3359: astore #8
    //   3361: aload #8
    //   3363: ifnull -> 3444
    //   3366: aload #8
    //   3368: invokevirtual isPrimitive : ()Z
    //   3371: ifne -> 3444
    //   3374: goto -> 3381
    //   3377: invokestatic a : (Ljava/lang/Throwable;)Ljava/lang/Throwable;
    //   3380: athrow
    //   3381: aload #8
    //   3383: invokevirtual getPackage : ()Ljava/lang/Package;
    //   3386: ifnull -> 3444
    //   3389: goto -> 3396
    //   3392: invokestatic a : (Ljava/lang/Throwable;)Ljava/lang/Throwable;
    //   3395: athrow
    //   3396: aload #8
    //   3398: invokevirtual getPackage : ()Ljava/lang/Package;
    //   3401: invokevirtual getName : ()Ljava/lang/String;
    //   3404: ifnull -> 3444
    //   3407: goto -> 3414
    //   3410: invokestatic a : (Ljava/lang/Throwable;)Ljava/lang/Throwable;
    //   3413: athrow
    //   3414: aload #8
    //   3416: invokevirtual getPackage : ()Ljava/lang/Package;
    //   3419: invokevirtual getName : ()Ljava/lang/String;
    //   3422: sipush #31855
    //   3425: sipush #6779
    //   3428: invokestatic a : (II)Ljava/lang/String;
    //   3431: invokevirtual startsWith : (Ljava/lang/String;)Z
    //   3434: ifne -> 3444
    //   3437: goto -> 3444
    //   3440: invokestatic a : (Ljava/lang/Throwable;)Ljava/lang/Throwable;
    //   3443: athrow
    //   3444: aload #7
    //   3446: iconst_1
    //   3447: invokevirtual setAccessible : (Z)V
    //   3450: aload #7
    //   3452: aconst_null
    //   3453: invokevirtual get : (Ljava/lang/Object;)Ljava/lang/Object;
    //   3456: pop
    //   3457: iinc #6, 1
    //   3460: iload_2
    //   3461: ifeq -> 3322
    //   3464: sipush #31868
    //   3467: sipush #1237
    //   3470: invokestatic a : (II)Ljava/lang/String;
    //   3473: invokestatic forName : (Ljava/lang/String;)Ljava/lang/Class;
    //   3476: invokevirtual getDeclaredMethods : ()[Ljava/lang/reflect/Method;
    //   3479: astore #4
    //   3481: aload #4
    //   3483: arraylength
    //   3484: istore #5
    //   3486: iconst_0
    //   3487: istore #6
    //   3489: iload #6
    //   3491: iload #5
    //   3493: if_icmpge -> 3629
    //   3496: aload #4
    //   3498: iload #6
    //   3500: aaload
    //   3501: astore #7
    //   3503: aload #7
    //   3505: invokevirtual getParameterTypes : ()[Ljava/lang/Class;
    //   3508: pop
    //   3509: aload #7
    //   3511: invokevirtual getModifiers : ()I
    //   3514: invokestatic isStatic : (I)Z
    //   3517: ifeq -> 3615
    //   3520: aload #7
    //   3522: invokevirtual getParameterTypes : ()[Ljava/lang/Class;
    //   3525: arraylength
    //   3526: iconst_2
    //   3527: if_icmpne -> 3615
    //   3530: goto -> 3537
    //   3533: invokestatic a : (Ljava/lang/Throwable;)Ljava/lang/Throwable;
    //   3536: athrow
    //   3537: aload #7
    //   3539: invokevirtual getReturnType : ()Ljava/lang/Class;
    //   3542: getstatic java/lang/Boolean.TYPE : Ljava/lang/Class;
    //   3545: if_acmpne -> 3615
    //   3548: goto -> 3555
    //   3551: invokestatic a : (Ljava/lang/Throwable;)Ljava/lang/Throwable;
    //   3554: athrow
    //   3555: aload #7
    //   3557: iconst_1
    //   3558: invokevirtual setAccessible : (Z)V
    //   3561: aload #7
    //   3563: aconst_null
    //   3564: iconst_2
    //   3565: anewarray java/lang/Object
    //   3568: dup
    //   3569: iconst_0
    //   3570: aload_0
    //   3571: aastore
    //   3572: dup
    //   3573: iconst_1
    //   3574: aload_1
    //   3575: ifnonnull -> 3593
    //   3578: goto -> 3585
    //   3581: invokestatic a : (Ljava/lang/Throwable;)Ljava/lang/Throwable;
    //   3584: athrow
    //   3585: aload_1
    //   3586: goto -> 3600
    //   3589: invokestatic a : (Ljava/lang/Throwable;)Ljava/lang/Throwable;
    //   3592: athrow
    //   3593: aload_1
    //   3594: checkcast [B
    //   3597: invokevirtual clone : ()Ljava/lang/Object;
    //   3600: aastore
    //   3601: invokevirtual invoke : (Ljava/lang/Object;[Ljava/lang/Object;)Ljava/lang/Object;
    //   3604: checkcast java/lang/Boolean
    //   3607: invokevirtual booleanValue : ()Z
    //   3610: istore_3
    //   3611: iload_2
    //   3612: ifeq -> 3629
    //   3615: iinc #6, 1
    //   3618: iload_2
    //   3619: ifeq -> 3489
    //   3622: goto -> 3629
    //   3625: invokestatic a : (Ljava/lang/Throwable;)Ljava/lang/Throwable;
    //   3628: athrow
    //   3629: iload_3
    //   3630: ireturn
    //   3631: astore_3
    //   3632: new java/lang/Exception
    //   3635: dup
    //   3636: aload_3
    //   3637: invokevirtual getMessage : ()Ljava/lang/String;
    //   3640: invokespecial <init> : (Ljava/lang/String;)V
    //   3643: athrow
    // Exception table:
    //   from	to	target	type
    //   4	1441	3631	java/lang/Throwable
    //   82	96	96	java/lang/Throwable
    //   107	120	123	java/lang/Throwable
    //   112	135	138	java/lang/Throwable
    //   127	153	156	java/lang/Throwable
    //   142	183	186	java/lang/Throwable
    //   246	273	276	java/lang/Throwable
    //   263	294	297	java/lang/Throwable
    //   280	324	327	java/lang/Throwable
    //   301	335	335	java/lang/Throwable
    //   346	362	365	java/lang/Throwable
    //   369	706	709	java/lang/Throwable
    //   540	550	550	java/lang/Throwable
    //   554	566	566	java/lang/Throwable
    //   570	582	582	java/lang/Throwable
    //   586	599	599	java/lang/Throwable
    //   603	616	616	java/lang/Throwable
    //   802	816	816	java/lang/Throwable
    //   827	840	843	java/lang/Throwable
    //   832	855	858	java/lang/Throwable
    //   847	873	876	java/lang/Throwable
    //   862	903	906	java/lang/Throwable
    //   968	995	998	java/lang/Throwable
    //   985	1013	1016	java/lang/Throwable
    //   1002	1043	1046	java/lang/Throwable
    //   1020	1054	1054	java/lang/Throwable
    //   1076	1087	1090	java/lang/Throwable
    //   1143	1157	1157	java/lang/Throwable
    //   1168	1181	1184	java/lang/Throwable
    //   1173	1196	1199	java/lang/Throwable
    //   1188	1214	1217	java/lang/Throwable
    //   1203	1244	1247	java/lang/Throwable
    //   1310	1337	1340	java/lang/Throwable
    //   1327	1355	1358	java/lang/Throwable
    //   1344	1385	1388	java/lang/Throwable
    //   1362	1396	1396	java/lang/Throwable
    //   1418	1429	1432	java/lang/Throwable
    //   1442	2172	3631	java/lang/Throwable
    //   1532	1546	1546	java/lang/Throwable
    //   1557	1570	1573	java/lang/Throwable
    //   1562	1585	1588	java/lang/Throwable
    //   1577	1603	1606	java/lang/Throwable
    //   1592	1633	1636	java/lang/Throwable
    //   1699	1726	1729	java/lang/Throwable
    //   1716	1744	1747	java/lang/Throwable
    //   1733	1774	1777	java/lang/Throwable
    //   1751	1785	1785	java/lang/Throwable
    //   1807	1818	1821	java/lang/Throwable
    //   1874	1888	1888	java/lang/Throwable
    //   1899	1912	1915	java/lang/Throwable
    //   1904	1927	1930	java/lang/Throwable
    //   1919	1945	1948	java/lang/Throwable
    //   1934	1975	1978	java/lang/Throwable
    //   2041	2068	2071	java/lang/Throwable
    //   2058	2086	2089	java/lang/Throwable
    //   2075	2116	2119	java/lang/Throwable
    //   2093	2127	2127	java/lang/Throwable
    //   2149	2160	2163	java/lang/Throwable
    //   2173	2903	3631	java/lang/Throwable
    //   2263	2277	2277	java/lang/Throwable
    //   2288	2301	2304	java/lang/Throwable
    //   2293	2316	2319	java/lang/Throwable
    //   2308	2334	2337	java/lang/Throwable
    //   2323	2364	2367	java/lang/Throwable
    //   2430	2457	2460	java/lang/Throwable
    //   2447	2475	2478	java/lang/Throwable
    //   2464	2505	2508	java/lang/Throwable
    //   2482	2516	2516	java/lang/Throwable
    //   2538	2549	2552	java/lang/Throwable
    //   2605	2619	2619	java/lang/Throwable
    //   2630	2643	2646	java/lang/Throwable
    //   2635	2658	2661	java/lang/Throwable
    //   2650	2676	2679	java/lang/Throwable
    //   2665	2706	2709	java/lang/Throwable
    //   2772	2799	2802	java/lang/Throwable
    //   2789	2817	2820	java/lang/Throwable
    //   2806	2847	2850	java/lang/Throwable
    //   2824	2858	2858	java/lang/Throwable
    //   2880	2891	2894	java/lang/Throwable
    //   2904	3630	3631	java/lang/Throwable
    //   2994	3008	3008	java/lang/Throwable
    //   3019	3032	3035	java/lang/Throwable
    //   3024	3047	3050	java/lang/Throwable
    //   3039	3065	3068	java/lang/Throwable
    //   3054	3095	3098	java/lang/Throwable
    //   3161	3188	3191	java/lang/Throwable
    //   3178	3206	3209	java/lang/Throwable
    //   3195	3236	3239	java/lang/Throwable
    //   3213	3247	3247	java/lang/Throwable
    //   3269	3280	3283	java/lang/Throwable
    //   3336	3350	3350	java/lang/Throwable
    //   3361	3374	3377	java/lang/Throwable
    //   3366	3389	3392	java/lang/Throwable
    //   3381	3407	3410	java/lang/Throwable
    //   3396	3437	3440	java/lang/Throwable
    //   3503	3530	3533	java/lang/Throwable
    //   3520	3548	3551	java/lang/Throwable
    //   3537	3578	3581	java/lang/Throwable
    //   3555	3589	3589	java/lang/Throwable
    //   3611	3622	3625	java/lang/Throwable
  }
  
  static void Zj(Object[] paramArrayOfObject, Object paramObject) throws Throwable {}
  
  static {
    // Byte code:
    //   0: bipush #28
    //   2: anewarray java/lang/String
    //   5: astore #5
    //   7: iconst_0
    //   8: istore_3
    //   9: ldc '.c>9P, SnyarT]kb+A\\tf].\\b\\n\\f'?I*[\\t\\ts&;lg\\t1kbi\\tF%i\\f.\\tC`F,\\t\\tdT8dy!&AZ\\\t3+`Yw\\t%\\n\\tEP\\bG!#>\\tb|\\t\\r+ =+\\tBfq\\tZ\\ts!  \\f}YAc9G}>DY ;lH[Mu]\\t\\b^4\\t\\fu\p#x\\t&\\rU\nj@S@K"\\t34@#|\\t34:\\tqcK<'
    //   11: dup
    //   12: astore_2
    //   13: invokevirtual length : ()I
    //   16: istore #4
    //   18: bipush #9
    //   20: istore_1
    //   21: iconst_m1
    //   22: istore_0
    //   23: bipush #39
    //   25: iinc #0, 1
    //   28: aload_2
    //   29: iload_0
    //   30: dup
    //   31: iload_1
    //   32: iadd
    //   33: invokevirtual substring : (II)Ljava/lang/String;
    //   36: iconst_m1
    //   37: goto -> 143
    //   40: aload #5
    //   42: swap
    //   43: iload_3
    //   44: iinc #3, 1
    //   47: swap
    //   48: aastore
    //   49: iload_0
    //   50: iload_1
    //   51: iadd
    //   52: dup
    //   53: istore_0
    //   54: iload #4
    //   56: if_icmpge -> 68
    //   59: aload_2
    //   60: iload_0
    //   61: invokevirtual charAt : (I)C
    //   64: istore_1
    //   65: goto -> 23
    //   68: ldc 'IBjE\\t\\be'
    //   70: dup
    //   71: astore_2
    //   72: invokevirtual length : ()I
    //   75: istore #4
    //   77: bipush #11
    //   79: istore_1
    //   80: iconst_m1
    //   81: istore_0
    //   82: bipush #8
    //   84: iinc #0, 1
    //   87: aload_2
    //   88: iload_0
    //   89: dup
    //   90: iload_1
    //   91: iadd
    //   92: invokevirtual substring : (II)Ljava/lang/String;
    //   95: iconst_0
    //   96: goto -> 143
    //   99: aload #5
    //   101: swap
    //   102: iload_3
    //   103: iinc #3, 1
    //   106: swap
    //   107: aastore
    //   108: iload_0
    //   109: iload_1
    //   110: iadd
    //   111: dup
    //   112: istore_0
    //   113: iload #4
    //   115: if_icmpge -> 127
    //   118: aload_2
    //   119: iload_0
    //   120: invokevirtual charAt : (I)C
    //   123: istore_1
    //   124: goto -> 82
    //   127: aload #5
    //   129: putstatic burp/Zlhm.a : [Ljava/lang/String;
    //   132: bipush #28
    //   134: anewarray java/lang/String
    //   137: putstatic burp/Zlhm.b : [Ljava/lang/String;
    //   140: goto -> 300
    //   143: dup_x2
    //   144: pop
    //   145: invokevirtual toCharArray : ()[C
    //   148: dup_x1
    //   149: arraylength
    //   150: dup_x2
    //   151: pop
    //   152: iconst_0
    //   153: istore #6
    //   155: dup2_x1
    //   156: pop2
    //   157: dup_x2
    //   158: iconst_1
    //   159: if_icmpgt -> 260
    //   162: dup2
    //   163: swap
    //   164: iload #6
    //   166: dup2_x1
    //   167: caload
    //   168: swap
    //   169: iload #6
    //   171: bipush #7
    //   173: irem
    //   174: tableswitch default -> 242, 0 -> 212, 1 -> 217, 2 -> 222, 3 -> 227, 4 -> 232, 5 -> 237
    //   212: bipush #78
    //   214: goto -> 244
    //   217: bipush #34
    //   219: goto -> 244
    //   222: bipush #27
    //   224: goto -> 244
    //   227: bipush #126
    //   229: goto -> 244
    //   232: bipush #39
    //   234: goto -> 244
    //   237: bipush #125
    //   239: goto -> 244
    //   242: bipush #22
    //   244: ixor
    //   245: ixor
    //   246: i2c
    //   247: castore
    //   248: iinc #6, 1
    //   251: dup
    //   252: ifne -> 260
    //   255: dup2
    //   256: dup_x1
    //   257: goto -> 166
    //   260: dup2_x1
    //   261: pop2
    //   262: dup_x2
    //   263: iload #6
    //   265: if_icmpgt -> 162
    //   268: pop
    //   269: new java/lang/String
    //   272: dup_x1
    //   273: swap
    //   274: invokespecial <init> : ([C)V
    //   277: invokevirtual intern : ()Ljava/lang/String;
    //   280: swap
    //   281: pop
    //   282: swap
    //   283: tableswitch default -> 40, 0 -> 99
    //   300: sipush #31871
    //   303: sipush #-30092
    //   306: invokestatic a : (II)Ljava/lang/String;
    //   309: putstatic burp/Zlhm.Zx : Ljava/lang/String;
    //   312: new java/math/BigInteger
    //   315: dup
    //   316: bipush #32
    //   318: newarray byte
    //   320: dup
    //   321: iconst_0
    //   322: bipush #74
    //   324: bastore
    //   325: dup
    //   326: iconst_1
    //   327: bipush #-77
    //   329: bastore
    //   330: dup
    //   331: iconst_2
    //   332: bipush #-52
    //   334: bastore
    //   335: dup
    //   336: iconst_3
    //   337: bipush #82
    //   339: bastore
    //   340: dup
    //   341: iconst_4
    //   342: iconst_0
    //   343: bastore
    //   344: dup
    //   345: iconst_5
    //   346: bipush #-119
    //   348: bastore
    //   349: dup
    //   350: bipush #6
    //   352: bipush #56
    //   354: bastore
    //   355: dup
    //   356: bipush #7
    //   358: bipush #-49
    //   360: bastore
    //   361: dup
    //   362: bipush #8
    //   364: bipush #-117
    //   366: bastore
    //   367: dup
    //   368: bipush #9
    //   370: bipush #31
    //   372: bastore
    //   373: dup
    //   374: bipush #10
    //   376: bipush #108
    //   378: bastore
    //   379: dup
    //   380: bipush #11
    //   382: bipush #-5
    //   384: bastore
    //   385: dup
    //   386: bipush #12
    //   388: bipush #85
    //   390: bastore
    //   391: dup
    //   392: bipush #13
    //   394: bipush #107
    //   396: bastore
    //   397: dup
    //   398: bipush #14
    //   400: bipush #72
    //   402: bastore
    //   403: dup
    //   404: bipush #15
    //   406: bipush #39
    //   408: bastore
    //   409: dup
    //   410: bipush #16
    //   412: bipush #34
    //   414: bastore
    //   415: dup
    //   416: bipush #17
    //   418: bipush #-101
    //   420: bastore
    //   421: dup
    //   422: bipush #18
    //   424: bipush #74
    //   426: bastore
    //   427: dup
    //   428: bipush #19
    //   430: bipush #-5
    //   432: bastore
    //   433: dup
    //   434: bipush #20
    //   436: bipush #101
    //   438: bastore
    //   439: dup
    //   440: bipush #21
    //   442: bipush #40
    //   444: bastore
    //   445: dup
    //   446: bipush #22
    //   448: bipush #-40
    //   450: bastore
    //   451: dup
    //   452: bipush #23
    //   454: bipush #-41
    //   456: bastore
    //   457: dup
    //   458: bipush #24
    //   460: bipush #75
    //   462: bastore
    //   463: dup
    //   464: bipush #25
    //   466: iconst_3
    //   467: bastore
    //   468: dup
    //   469: bipush #26
    //   471: bipush #-99
    //   473: bastore
    //   474: dup
    //   475: bipush #27
    //   477: bipush #-97
    //   479: bastore
    //   480: dup
    //   481: bipush #28
    //   483: bipush #90
    //   485: bastore
    //   486: dup
    //   487: bipush #29
    //   489: bipush #-49
    //   491: bastore
    //   492: dup
    //   493: bipush #30
    //   495: bipush #-118
    //   497: bastore
    //   498: dup
    //   499: bipush #31
    //   501: bipush #-30
    //   503: bastore
    //   504: invokespecial <init> : ([B)V
    //   507: putstatic burp/Zlhm.ZT : Ljava/lang/Object;
    //   510: return
  }
  
  private static Throwable a(Throwable paramThrowable) {
    return paramThrowable;
  }
  
  private static String a(int paramInt1, int paramInt2) {
    int i = (paramInt1 ^ 0x7C6B) & 0xFFFF;
    if (b[i] == null) {
      char[] arrayOfChar = a[i].toCharArray();
      switch (arrayOfChar[0] & 0xFF) {
        case 0:
        
        case 1:
        
        case 2:
        
        case 3:
        
        case 4:
        
        case 5:
        
        case 6:
        
        case 7:
        
        case 8:
        
        case 9:
        
        case 10:
        
        case 11:
        
        case 12:
        
        case 13:
        
        case 14:
        
        case 15:
        
        case 16:
        
        case 17:
        
        case 18:
        
        case 19:
        
        case 20:
        
        case 21:
        
        case 22:
        
        case 23:
        
        case 24:
        
        case 25:
        
        case 26:
        
        case 27:
        
        case 28:
        
        case 29:
        
        case 30:
        
        case 31:
        
        case 32:
        
        case 33:
        
        case 34:
        
        case 35:
        
        case 36:
        
        case 37:
        
        case 38:
        
        case 39:
        
        case 40:
        
        case 41:
        
        case 42:
        
        case 43:
        
        case 44:
        
        case 45:
        
        case 46:
        
        case 47:
        
        case 48:
        
        case 49:
        
        case 50:
        
        case 51:
        
        case 52:
        
        case 53:
        
        case 54:
        
        case 55:
        
        case 56:
        
        case 57:
        
        case 58:
        
        case 59:
        
        case 60:
        
        case 61:
        
        case 62:
        
        case 63:
        
        case 64:
        
        case 65:
        
        case 66:
        
        case 67:
        
        case 68:
        
        case 69:
        
        case 70:
        
        case 71:
        
        case 72:
        
        case 73:
        
        case 74:
        
        case 75:
        
        case 76:
        
        case 77:
        
        case 78:
        
        case 79:
        
        case 80:
        
        case 81:
        
        case 82:
        
        case 83:
        
        case 84:
        
        case 85:
        
        case 86:
        
        case 87:
        
        case 88:
        
        case 89:
        
        case 90:
        
        case 91:
        
        case 92:
        
        case 93:
        
        case 94:
        
        case 95:
        
        case 96:
        
        case 97:
        
        case 98:
        
        case 99:
        
        case 100:
        
        case 101:
        
        case 102:
        
        case 103:
        
        case 104:
        
        case 105:
        
        case 106:
        
        case 107:
        
        case 108:
        
        case 109:
        
        case 110:
        
        case 111:
        
        case 112:
        
        case 113:
        
        case 114:
        
        case 115:
        
        case 116:
        
        case 117:
        
        case 118:
        
        case 119:
        
        case 120:
        
        case 121:
        
        case 122:
        
        case 123:
        
        case 124:
        
        case 125:
        
        case 126:
        
        case 127:
        
        case 128:
        
        case 129:
        
        case 130:
        
        case 131:
        
        case 132:
        
        case 133:
        
        case 134:
        
        case 135:
        
        case 136:
        
        case 137:
        
        case 138:
        
        case 139:
        
        case 140:
        
        case 141:
        
        case 142:
        
        case 143:
        
        case 144:
        
        case 145:
        
        case 146:
        
        case 147:
        
        case 148:
        
        case 149:
        
        case 150:
        
        case 151:
        
        case 152:
        
        case 153:
        
        case 154:
        
        case 155:
        
        case 156:
        
        case 157:
        
        case 158:
        
        case 159:
        
        case 160:
        
        case 161:
        
        case 162:
        
        case 163:
        
        case 164:
        
        case 165:
        
        case 166:
        
        case 167:
        
        case 168:
        
        case 169:
        
        case 170:
        
        case 171:
        
        case 172:
        
        case 173:
        
        case 174:
        
        case 175:
        
        case 176:
        
        case 177:
        
        case 178:
        
        case 179:
        
        case 180:
        
        case 181:
        
        case 182:
        
        case 183:
        
        case 184:
        
        case 185:
        
        case 186:
        
        case 187:
        
        case 188:
        
        case 189:
        
        case 190:
        
        case 191:
        
        case 192:
        
        case 193:
        
        case 194:
        
        case 195:
        
        case 196:
        
        case 197:
        
        case 198:
        
        case 199:
        
        case 200:
        
        case 201:
        
        case 202:
        
        case 203:
        
        case 204:
        
        case 205:
        
        case 206:
        
        case 207:
        
        case 208:
        
        case 209:
        
        case 210:
        
        case 211:
        
        case 212:
        
        case 213:
        
        case 214:
        
        case 215:
        
        case 216:
        
        case 217:
        
        case 218:
        
        case 219:
        
        case 220:
        
        case 221:
        
        case 222:
        
        case 223:
        
        case 224:
        
        case 225:
        
        case 226:
        
        case 227:
        
        case 228:
        
        case 229:
        
        case 230:
        
        case 231:
        
        case 232:
        
        case 233:
        
        case 234:
        
        case 235:
        
        case 236:
        
        case 237:
        
        case 238:
        
        case 239:
        
        case 240:
        
        case 241:
        
        case 242:
        
        case 243:
        
        case 244:
        
        case 245:
        
        case 246:
        
        case 247:
        
        case 248:
        
        case 249:
        
        case 250:
        
        case 251:
        
        case 252:
        
        case 253:
        
        case 254:
        
        default:
          break;
      } 
      char c = '';
      int j = (paramInt2 & 0xFF) - c;
      if (j < 0)
        j += 256; 
      int k = ((paramInt2 & 0xFFFF) >>> 8) - c;
      if (k < 0)
        k += 256; 
      for (byte b = 0; b < arrayOfChar.length; b++) {
        int m = b % 2;
        if (m == 0) {
          arrayOfChar[b] = (char)(arrayOfChar[b] ^ j);
          j = ((j >>> 3 | j << 5) ^ arrayOfChar[b]) & 0xFF;
        } else {
          arrayOfChar[b] = (char)(arrayOfChar[b] ^ k);
          k = ((k >>> 3 | k << 5) ^ arrayOfChar[b]) & 0xFF;
        } 
      } 
      b[i] = (new String(arrayOfChar)).intern();
    } 
    return b[i];
  }
}


/* Location:              C:\Program Files\BurpSuitePro\burpsuite_pro.jar!\burp\Zlhm.class
 * Java compiler version: 21 (65.0)
 * JD-Core Version:       1.1.3
 */