package burp;

import java.math.BigInteger;

class Zlid extends ClassLoader {
  static String ZU;
  
  static Object Zx;
  
  private static final String[] a;
  
  private static final String[] b;
  
  static boolean ZY(Object[] paramArrayOfObject, Object paramObject) throws Throwable {
    // Byte code:
    //   0: invokestatic ZK : ()Z
    //   3: istore_2
    //   4: new java/lang/StringBuilder
    //   7: dup
    //   8: invokespecial <init> : ()V
    //   11: astore_3
    //   12: iconst_0
    //   13: istore #4
    //   15: iload #4
    //   17: bipush #32
    //   19: if_icmpge -> 1355
    //   22: iload #4
    //   24: tableswitch default -> 1348, 0 -> 168, 1 -> 205, 2 -> 242, 3 -> 279, 4 -> 316, 5 -> 353, 6 -> 390, 7 -> 427, 8 -> 464, 9 -> 501, 10 -> 538, 11 -> 575, 12 -> 612, 13 -> 649, 14 -> 686, 15 -> 723, 16 -> 760, 17 -> 797, 18 -> 834, 19 -> 871, 20 -> 908, 21 -> 945, 22 -> 982, 23 -> 1019, 24 -> 1056, 25 -> 1093, 26 -> 1130, 27 -> 1167, 28 -> 1204, 29 -> 1241, 30 -> 1278, 31 -> 1315
    //   168: aload_3
    //   169: getstatic burp/Zz7m.Zq : Ljava/lang/String;
    //   172: getstatic burp/Zm7v.ZP : Ljava/lang/Object;
    //   175: checkcast java/math/BigInteger
    //   178: invokevirtual intValue : ()I
    //   181: bipush #32
    //   183: irem
    //   184: invokestatic abs : (I)I
    //   187: invokevirtual charAt : (I)C
    //   190: invokevirtual append : (C)Ljava/lang/StringBuilder;
    //   193: pop
    //   194: iload_2
    //   195: ifeq -> 1348
    //   198: goto -> 205
    //   201: invokestatic a : (Ljava/lang/Throwable;)Ljava/lang/Throwable;
    //   204: athrow
    //   205: aload_3
    //   206: getstatic burp/Zzna.Zi : Ljava/lang/String;
    //   209: getstatic burp/Zrqi.Zb : Ljava/lang/Object;
    //   212: checkcast java/math/BigInteger
    //   215: invokevirtual intValue : ()I
    //   218: bipush #32
    //   220: irem
    //   221: invokestatic abs : (I)I
    //   224: invokevirtual charAt : (I)C
    //   227: invokevirtual append : (C)Ljava/lang/StringBuilder;
    //   230: pop
    //   231: iload_2
    //   232: ifeq -> 1348
    //   235: goto -> 242
    //   238: invokestatic a : (Ljava/lang/Throwable;)Ljava/lang/Throwable;
    //   241: athrow
    //   242: aload_3
    //   243: getstatic burp/Zl7b.Zv : Ljava/lang/String;
    //   246: getstatic burp/Zl_a.ZP : Ljava/lang/Object;
    //   249: checkcast java/math/BigInteger
    //   252: invokevirtual intValue : ()I
    //   255: bipush #32
    //   257: irem
    //   258: invokestatic abs : (I)I
    //   261: invokevirtual charAt : (I)C
    //   264: invokevirtual append : (C)Ljava/lang/StringBuilder;
    //   267: pop
    //   268: iload_2
    //   269: ifeq -> 1348
    //   272: goto -> 279
    //   275: invokestatic a : (Ljava/lang/Throwable;)Ljava/lang/Throwable;
    //   278: athrow
    //   279: aload_3
    //   280: getstatic burp/Zm7v.ZX : Ljava/lang/String;
    //   283: getstatic burp/Zb_1.ZK : Ljava/lang/Object;
    //   286: checkcast java/math/BigInteger
    //   289: invokevirtual intValue : ()I
    //   292: bipush #32
    //   294: irem
    //   295: invokestatic abs : (I)I
    //   298: invokevirtual charAt : (I)C
    //   301: invokevirtual append : (C)Ljava/lang/StringBuilder;
    //   304: pop
    //   305: iload_2
    //   306: ifeq -> 1348
    //   309: goto -> 316
    //   312: invokestatic a : (Ljava/lang/Throwable;)Ljava/lang/Throwable;
    //   315: athrow
    //   316: aload_3
    //   317: getstatic burp/Zrw0.Zj : Ljava/lang/String;
    //   320: getstatic burp/Zb_1.ZK : Ljava/lang/Object;
    //   323: checkcast java/math/BigInteger
    //   326: invokevirtual intValue : ()I
    //   329: bipush #32
    //   331: irem
    //   332: invokestatic abs : (I)I
    //   335: invokevirtual charAt : (I)C
    //   338: invokevirtual append : (C)Ljava/lang/StringBuilder;
    //   341: pop
    //   342: iload_2
    //   343: ifeq -> 1348
    //   346: goto -> 353
    //   349: invokestatic a : (Ljava/lang/Throwable;)Ljava/lang/Throwable;
    //   352: athrow
    //   353: aload_3
    //   354: getstatic burp/Zd9.Ze : Ljava/lang/String;
    //   357: getstatic burp/Ze84.Zj : Ljava/lang/Object;
    //   360: checkcast java/math/BigInteger
    //   363: invokevirtual intValue : ()I
    //   366: bipush #32
    //   368: irem
    //   369: invokestatic abs : (I)I
    //   372: invokevirtual charAt : (I)C
    //   375: invokevirtual append : (C)Ljava/lang/StringBuilder;
    //   378: pop
    //   379: iload_2
    //   380: ifeq -> 1348
    //   383: goto -> 390
    //   386: invokestatic a : (Ljava/lang/Throwable;)Ljava/lang/Throwable;
    //   389: athrow
    //   390: aload_3
    //   391: getstatic burp/Zrgo.Z_ : Ljava/lang/String;
    //   394: getstatic burp/Zv8d.ZN : Ljava/lang/Object;
    //   397: checkcast java/math/BigInteger
    //   400: invokevirtual intValue : ()I
    //   403: bipush #32
    //   405: irem
    //   406: invokestatic abs : (I)I
    //   409: invokevirtual charAt : (I)C
    //   412: invokevirtual append : (C)Ljava/lang/StringBuilder;
    //   415: pop
    //   416: iload_2
    //   417: ifeq -> 1348
    //   420: goto -> 427
    //   423: invokestatic a : (Ljava/lang/Throwable;)Ljava/lang/Throwable;
    //   426: athrow
    //   427: aload_3
    //   428: getstatic burp/Zzh5.Zc : Ljava/lang/String;
    //   431: getstatic burp/Zmui.Zz : Ljava/lang/Object;
    //   434: checkcast java/math/BigInteger
    //   437: invokevirtual intValue : ()I
    //   440: bipush #32
    //   442: irem
    //   443: invokestatic abs : (I)I
    //   446: invokevirtual charAt : (I)C
    //   449: invokevirtual append : (C)Ljava/lang/StringBuilder;
    //   452: pop
    //   453: iload_2
    //   454: ifeq -> 1348
    //   457: goto -> 464
    //   460: invokestatic a : (Ljava/lang/Throwable;)Ljava/lang/Throwable;
    //   463: athrow
    //   464: aload_3
    //   465: getstatic burp/Zrn4.ZY : Ljava/lang/String;
    //   468: getstatic burp/Zsdl.Zx : Ljava/lang/Object;
    //   471: checkcast java/math/BigInteger
    //   474: invokevirtual intValue : ()I
    //   477: bipush #32
    //   479: irem
    //   480: invokestatic abs : (I)I
    //   483: invokevirtual charAt : (I)C
    //   486: invokevirtual append : (C)Ljava/lang/StringBuilder;
    //   489: pop
    //   490: iload_2
    //   491: ifeq -> 1348
    //   494: goto -> 501
    //   497: invokestatic a : (Ljava/lang/Throwable;)Ljava/lang/Throwable;
    //   500: athrow
    //   501: aload_3
    //   502: getstatic burp/Zbun.ZS : Ljava/lang/String;
    //   505: getstatic burp/Zeub.ZD : Ljava/lang/Object;
    //   508: checkcast java/math/BigInteger
    //   511: invokevirtual intValue : ()I
    //   514: bipush #32
    //   516: irem
    //   517: invokestatic abs : (I)I
    //   520: invokevirtual charAt : (I)C
    //   523: invokevirtual append : (C)Ljava/lang/StringBuilder;
    //   526: pop
    //   527: iload_2
    //   528: ifeq -> 1348
    //   531: goto -> 538
    //   534: invokestatic a : (Ljava/lang/Throwable;)Ljava/lang/Throwable;
    //   537: athrow
    //   538: aload_3
    //   539: getstatic burp/Zmhq.Zy : Ljava/lang/String;
    //   542: getstatic burp/Zgtd.Zo : Ljava/lang/Object;
    //   545: checkcast java/math/BigInteger
    //   548: invokevirtual intValue : ()I
    //   551: bipush #32
    //   553: irem
    //   554: invokestatic abs : (I)I
    //   557: invokevirtual charAt : (I)C
    //   560: invokevirtual append : (C)Ljava/lang/StringBuilder;
    //   563: pop
    //   564: iload_2
    //   565: ifeq -> 1348
    //   568: goto -> 575
    //   571: invokestatic a : (Ljava/lang/Throwable;)Ljava/lang/Throwable;
    //   574: athrow
    //   575: aload_3
    //   576: getstatic burp/Zrjq.Zx : Ljava/lang/String;
    //   579: getstatic burp/Zle9.ZI : Ljava/lang/Object;
    //   582: checkcast java/math/BigInteger
    //   585: invokevirtual intValue : ()I
    //   588: bipush #32
    //   590: irem
    //   591: invokestatic abs : (I)I
    //   594: invokevirtual charAt : (I)C
    //   597: invokevirtual append : (C)Ljava/lang/StringBuilder;
    //   600: pop
    //   601: iload_2
    //   602: ifeq -> 1348
    //   605: goto -> 612
    //   608: invokestatic a : (Ljava/lang/Throwable;)Ljava/lang/Throwable;
    //   611: athrow
    //   612: aload_3
    //   613: getstatic burp/Zrzg.ZX : Ljava/lang/String;
    //   616: getstatic burp/Zrye.Zx : Ljava/lang/Object;
    //   619: checkcast java/math/BigInteger
    //   622: invokevirtual intValue : ()I
    //   625: bipush #32
    //   627: irem
    //   628: invokestatic abs : (I)I
    //   631: invokevirtual charAt : (I)C
    //   634: invokevirtual append : (C)Ljava/lang/StringBuilder;
    //   637: pop
    //   638: iload_2
    //   639: ifeq -> 1348
    //   642: goto -> 649
    //   645: invokestatic a : (Ljava/lang/Throwable;)Ljava/lang/Throwable;
    //   648: athrow
    //   649: aload_3
    //   650: getstatic burp/Zz66.ZM : Ljava/lang/String;
    //   653: getstatic burp/Zlw8.ZA : Ljava/lang/Object;
    //   656: checkcast java/math/BigInteger
    //   659: invokevirtual intValue : ()I
    //   662: bipush #32
    //   664: irem
    //   665: invokestatic abs : (I)I
    //   668: invokevirtual charAt : (I)C
    //   671: invokevirtual append : (C)Ljava/lang/StringBuilder;
    //   674: pop
    //   675: iload_2
    //   676: ifeq -> 1348
    //   679: goto -> 686
    //   682: invokestatic a : (Ljava/lang/Throwable;)Ljava/lang/Throwable;
    //   685: athrow
    //   686: aload_3
    //   687: getstatic burp/Zgrz.Zu : Ljava/lang/String;
    //   690: getstatic burp/Ze2w.ZA : Ljava/lang/Object;
    //   693: checkcast java/math/BigInteger
    //   696: invokevirtual intValue : ()I
    //   699: bipush #32
    //   701: irem
    //   702: invokestatic abs : (I)I
    //   705: invokevirtual charAt : (I)C
    //   708: invokevirtual append : (C)Ljava/lang/StringBuilder;
    //   711: pop
    //   712: iload_2
    //   713: ifeq -> 1348
    //   716: goto -> 723
    //   719: invokestatic a : (Ljava/lang/Throwable;)Ljava/lang/Throwable;
    //   722: athrow
    //   723: aload_3
    //   724: getstatic burp/Zl1e.Z_ : Ljava/lang/String;
    //   727: getstatic burp/Zscz.ZN : Ljava/lang/Object;
    //   730: checkcast java/math/BigInteger
    //   733: invokevirtual intValue : ()I
    //   736: bipush #32
    //   738: irem
    //   739: invokestatic abs : (I)I
    //   742: invokevirtual charAt : (I)C
    //   745: invokevirtual append : (C)Ljava/lang/StringBuilder;
    //   748: pop
    //   749: iload_2
    //   750: ifeq -> 1348
    //   753: goto -> 760
    //   756: invokestatic a : (Ljava/lang/Throwable;)Ljava/lang/Throwable;
    //   759: athrow
    //   760: aload_3
    //   761: getstatic burp/Zt81.ZL : Ljava/lang/String;
    //   764: getstatic burp/Zegv.ZL : Ljava/lang/Object;
    //   767: checkcast java/math/BigInteger
    //   770: invokevirtual intValue : ()I
    //   773: bipush #32
    //   775: irem
    //   776: invokestatic abs : (I)I
    //   779: invokevirtual charAt : (I)C
    //   782: invokevirtual append : (C)Ljava/lang/StringBuilder;
    //   785: pop
    //   786: iload_2
    //   787: ifeq -> 1348
    //   790: goto -> 797
    //   793: invokestatic a : (Ljava/lang/Throwable;)Ljava/lang/Throwable;
    //   796: athrow
    //   797: aload_3
    //   798: getstatic burp/Zzc9.Zv : Ljava/lang/String;
    //   801: getstatic burp/Zsdl.Zx : Ljava/lang/Object;
    //   804: checkcast java/math/BigInteger
    //   807: invokevirtual intValue : ()I
    //   810: bipush #32
    //   812: irem
    //   813: invokestatic abs : (I)I
    //   816: invokevirtual charAt : (I)C
    //   819: invokevirtual append : (C)Ljava/lang/StringBuilder;
    //   822: pop
    //   823: iload_2
    //   824: ifeq -> 1348
    //   827: goto -> 834
    //   830: invokestatic a : (Ljava/lang/Throwable;)Ljava/lang/Throwable;
    //   833: athrow
    //   834: aload_3
    //   835: getstatic burp/Zxwf.ZX : Ljava/lang/String;
    //   838: getstatic burp/Zx5w.Zo : Ljava/lang/Object;
    //   841: checkcast java/math/BigInteger
    //   844: invokevirtual intValue : ()I
    //   847: bipush #32
    //   849: irem
    //   850: invokestatic abs : (I)I
    //   853: invokevirtual charAt : (I)C
    //   856: invokevirtual append : (C)Ljava/lang/StringBuilder;
    //   859: pop
    //   860: iload_2
    //   861: ifeq -> 1348
    //   864: goto -> 871
    //   867: invokestatic a : (Ljava/lang/Throwable;)Ljava/lang/Throwable;
    //   870: athrow
    //   871: aload_3
    //   872: getstatic burp/Zbjx.ZA : Ljava/lang/String;
    //   875: getstatic burp/Zk8i.ZN : Ljava/lang/Object;
    //   878: checkcast java/math/BigInteger
    //   881: invokevirtual intValue : ()I
    //   884: bipush #32
    //   886: irem
    //   887: invokestatic abs : (I)I
    //   890: invokevirtual charAt : (I)C
    //   893: invokevirtual append : (C)Ljava/lang/StringBuilder;
    //   896: pop
    //   897: iload_2
    //   898: ifeq -> 1348
    //   901: goto -> 908
    //   904: invokestatic a : (Ljava/lang/Throwable;)Ljava/lang/Throwable;
    //   907: athrow
    //   908: aload_3
    //   909: getstatic burp/Zxcn.ZF : Ljava/lang/String;
    //   912: getstatic burp/Zs8w.ZW : Ljava/lang/Object;
    //   915: checkcast java/math/BigInteger
    //   918: invokevirtual intValue : ()I
    //   921: bipush #32
    //   923: irem
    //   924: invokestatic abs : (I)I
    //   927: invokevirtual charAt : (I)C
    //   930: invokevirtual append : (C)Ljava/lang/StringBuilder;
    //   933: pop
    //   934: iload_2
    //   935: ifeq -> 1348
    //   938: goto -> 945
    //   941: invokestatic a : (Ljava/lang/Throwable;)Ljava/lang/Throwable;
    //   944: athrow
    //   945: aload_3
    //   946: getstatic burp/Zmh3.Zy : Ljava/lang/String;
    //   949: getstatic burp/Zeig.ZA : Ljava/lang/Object;
    //   952: checkcast java/math/BigInteger
    //   955: invokevirtual intValue : ()I
    //   958: bipush #32
    //   960: irem
    //   961: invokestatic abs : (I)I
    //   964: invokevirtual charAt : (I)C
    //   967: invokevirtual append : (C)Ljava/lang/StringBuilder;
    //   970: pop
    //   971: iload_2
    //   972: ifeq -> 1348
    //   975: goto -> 982
    //   978: invokestatic a : (Ljava/lang/Throwable;)Ljava/lang/Throwable;
    //   981: athrow
    //   982: aload_3
    //   983: getstatic burp/Zea.Zj : Ljava/lang/String;
    //   986: getstatic burp/Ze4w.Zd : Ljava/lang/Object;
    //   989: checkcast java/math/BigInteger
    //   992: invokevirtual intValue : ()I
    //   995: bipush #32
    //   997: irem
    //   998: invokestatic abs : (I)I
    //   1001: invokevirtual charAt : (I)C
    //   1004: invokevirtual append : (C)Ljava/lang/StringBuilder;
    //   1007: pop
    //   1008: iload_2
    //   1009: ifeq -> 1348
    //   1012: goto -> 1019
    //   1015: invokestatic a : (Ljava/lang/Throwable;)Ljava/lang/Throwable;
    //   1018: athrow
    //   1019: aload_3
    //   1020: getstatic burp/Zxcn.ZF : Ljava/lang/String;
    //   1023: getstatic burp/Zg4l.ZI : Ljava/lang/Object;
    //   1026: checkcast java/math/BigInteger
    //   1029: invokevirtual intValue : ()I
    //   1032: bipush #32
    //   1034: irem
    //   1035: invokestatic abs : (I)I
    //   1038: invokevirtual charAt : (I)C
    //   1041: invokevirtual append : (C)Ljava/lang/StringBuilder;
    //   1044: pop
    //   1045: iload_2
    //   1046: ifeq -> 1348
    //   1049: goto -> 1056
    //   1052: invokestatic a : (Ljava/lang/Throwable;)Ljava/lang/Throwable;
    //   1055: athrow
    //   1056: aload_3
    //   1057: getstatic burp/Zxzv.ZI : Ljava/lang/String;
    //   1060: getstatic burp/Zxc0.Zl : Ljava/lang/Object;
    //   1063: checkcast java/math/BigInteger
    //   1066: invokevirtual intValue : ()I
    //   1069: bipush #32
    //   1071: irem
    //   1072: invokestatic abs : (I)I
    //   1075: invokevirtual charAt : (I)C
    //   1078: invokevirtual append : (C)Ljava/lang/StringBuilder;
    //   1081: pop
    //   1082: iload_2
    //   1083: ifeq -> 1348
    //   1086: goto -> 1093
    //   1089: invokestatic a : (Ljava/lang/Throwable;)Ljava/lang/Throwable;
    //   1092: athrow
    //   1093: aload_3
    //   1094: getstatic burp/Zzk_.ZX : Ljava/lang/String;
    //   1097: getstatic burp/Zz4a.ZB : Ljava/lang/Object;
    //   1100: checkcast java/math/BigInteger
    //   1103: invokevirtual intValue : ()I
    //   1106: bipush #32
    //   1108: irem
    //   1109: invokestatic abs : (I)I
    //   1112: invokevirtual charAt : (I)C
    //   1115: invokevirtual append : (C)Ljava/lang/StringBuilder;
    //   1118: pop
    //   1119: iload_2
    //   1120: ifeq -> 1348
    //   1123: goto -> 1130
    //   1126: invokestatic a : (Ljava/lang/Throwable;)Ljava/lang/Throwable;
    //   1129: athrow
    //   1130: aload_3
    //   1131: getstatic burp/Zsn3.ZS : Ljava/lang/String;
    //   1134: getstatic burp/Zrzg.ZA : Ljava/lang/Object;
    //   1137: checkcast java/math/BigInteger
    //   1140: invokevirtual intValue : ()I
    //   1143: bipush #32
    //   1145: irem
    //   1146: invokestatic abs : (I)I
    //   1149: invokevirtual charAt : (I)C
    //   1152: invokevirtual append : (C)Ljava/lang/StringBuilder;
    //   1155: pop
    //   1156: iload_2
    //   1157: ifeq -> 1348
    //   1160: goto -> 1167
    //   1163: invokestatic a : (Ljava/lang/Throwable;)Ljava/lang/Throwable;
    //   1166: athrow
    //   1167: aload_3
    //   1168: getstatic burp/Zrkd.ZL : Ljava/lang/String;
    //   1171: getstatic burp/Zz4j.Zu : Ljava/lang/Object;
    //   1174: checkcast java/math/BigInteger
    //   1177: invokevirtual intValue : ()I
    //   1180: bipush #32
    //   1182: irem
    //   1183: invokestatic abs : (I)I
    //   1186: invokevirtual charAt : (I)C
    //   1189: invokevirtual append : (C)Ljava/lang/StringBuilder;
    //   1192: pop
    //   1193: iload_2
    //   1194: ifeq -> 1348
    //   1197: goto -> 1204
    //   1200: invokestatic a : (Ljava/lang/Throwable;)Ljava/lang/Throwable;
    //   1203: athrow
    //   1204: aload_3
    //   1205: getstatic burp/Ze84.Zv : Ljava/lang/String;
    //   1208: getstatic burp/Zeig.ZA : Ljava/lang/Object;
    //   1211: checkcast java/math/BigInteger
    //   1214: invokevirtual intValue : ()I
    //   1217: bipush #32
    //   1219: irem
    //   1220: invokestatic abs : (I)I
    //   1223: invokevirtual charAt : (I)C
    //   1226: invokevirtual append : (C)Ljava/lang/StringBuilder;
    //   1229: pop
    //   1230: iload_2
    //   1231: ifeq -> 1348
    //   1234: goto -> 1241
    //   1237: invokestatic a : (Ljava/lang/Throwable;)Ljava/lang/Throwable;
    //   1240: athrow
    //   1241: aload_3
    //   1242: getstatic burp/Zenr.Z_ : Ljava/lang/String;
    //   1245: getstatic burp/Zbw5.ZR : Ljava/lang/Object;
    //   1248: checkcast java/math/BigInteger
    //   1251: invokevirtual intValue : ()I
    //   1254: bipush #32
    //   1256: irem
    //   1257: invokestatic abs : (I)I
    //   1260: invokevirtual charAt : (I)C
    //   1263: invokevirtual append : (C)Ljava/lang/StringBuilder;
    //   1266: pop
    //   1267: iload_2
    //   1268: ifeq -> 1348
    //   1271: goto -> 1278
    //   1274: invokestatic a : (Ljava/lang/Throwable;)Ljava/lang/Throwable;
    //   1277: athrow
    //   1278: aload_3
    //   1279: getstatic burp/Zr6c.Zf : Ljava/lang/String;
    //   1282: getstatic burp/Zlwm.Ze : Ljava/lang/Object;
    //   1285: checkcast java/math/BigInteger
    //   1288: invokevirtual intValue : ()I
    //   1291: bipush #32
    //   1293: irem
    //   1294: invokestatic abs : (I)I
    //   1297: invokevirtual charAt : (I)C
    //   1300: invokevirtual append : (C)Ljava/lang/StringBuilder;
    //   1303: pop
    //   1304: iload_2
    //   1305: ifeq -> 1348
    //   1308: goto -> 1315
    //   1311: invokestatic a : (Ljava/lang/Throwable;)Ljava/lang/Throwable;
    //   1314: athrow
    //   1315: aload_3
    //   1316: getstatic burp/Zzl4.ZT : Ljava/lang/String;
    //   1319: getstatic burp/Zmhq.ZK : Ljava/lang/Object;
    //   1322: checkcast java/math/BigInteger
    //   1325: invokevirtual intValue : ()I
    //   1328: bipush #32
    //   1330: irem
    //   1331: invokestatic abs : (I)I
    //   1334: invokevirtual charAt : (I)C
    //   1337: invokevirtual append : (C)Ljava/lang/StringBuilder;
    //   1340: pop
    //   1341: goto -> 1348
    //   1344: invokestatic a : (Ljava/lang/Throwable;)Ljava/lang/Throwable;
    //   1347: athrow
    //   1348: iinc #4, 1
    //   1351: iload_2
    //   1352: ifeq -> 15
    //   1355: aload_3
    //   1356: invokevirtual toString : ()Ljava/lang/String;
    //   1359: putstatic burp/Zz5e.Zd : Ljava/lang/String;
    //   1362: sipush #28565
    //   1365: sipush #29768
    //   1368: invokestatic a : (II)Ljava/lang/String;
    //   1371: iconst_1
    //   1372: ldc burp/Zmdm
    //   1374: invokevirtual getClassLoader : ()Ljava/lang/ClassLoader;
    //   1377: invokestatic forName : (Ljava/lang/String;ZLjava/lang/ClassLoader;)Ljava/lang/Class;
    //   1380: invokevirtual getDeclaredFields : ()[Ljava/lang/reflect/Field;
    //   1383: astore #4
    //   1385: aload #4
    //   1387: arraylength
    //   1388: istore #5
    //   1390: iconst_0
    //   1391: istore #6
    //   1393: iload #6
    //   1395: iload #5
    //   1397: if_icmpge -> 1535
    //   1400: aload #4
    //   1402: iload #6
    //   1404: aaload
    //   1405: astore #7
    //   1407: aload #7
    //   1409: invokevirtual getModifiers : ()I
    //   1412: invokestatic isStatic : (I)Z
    //   1415: ifne -> 1425
    //   1418: goto -> 1528
    //   1421: invokestatic a : (Ljava/lang/Throwable;)Ljava/lang/Throwable;
    //   1424: athrow
    //   1425: aload #7
    //   1427: invokevirtual getType : ()Ljava/lang/Class;
    //   1430: astore #8
    //   1432: aload #8
    //   1434: ifnull -> 1515
    //   1437: aload #8
    //   1439: invokevirtual isPrimitive : ()Z
    //   1442: ifne -> 1515
    //   1445: goto -> 1452
    //   1448: invokestatic a : (Ljava/lang/Throwable;)Ljava/lang/Throwable;
    //   1451: athrow
    //   1452: aload #8
    //   1454: invokevirtual getPackage : ()Ljava/lang/Package;
    //   1457: ifnull -> 1515
    //   1460: goto -> 1467
    //   1463: invokestatic a : (Ljava/lang/Throwable;)Ljava/lang/Throwable;
    //   1466: athrow
    //   1467: aload #8
    //   1469: invokevirtual getPackage : ()Ljava/lang/Package;
    //   1472: invokevirtual getName : ()Ljava/lang/String;
    //   1475: ifnull -> 1515
    //   1478: goto -> 1485
    //   1481: invokestatic a : (Ljava/lang/Throwable;)Ljava/lang/Throwable;
    //   1484: athrow
    //   1485: aload #8
    //   1487: invokevirtual getPackage : ()Ljava/lang/Package;
    //   1490: invokevirtual getName : ()Ljava/lang/String;
    //   1493: sipush #28558
    //   1496: sipush #20252
    //   1499: invokestatic a : (II)Ljava/lang/String;
    //   1502: invokevirtual startsWith : (Ljava/lang/String;)Z
    //   1505: ifne -> 1515
    //   1508: goto -> 1515
    //   1511: invokestatic a : (Ljava/lang/Throwable;)Ljava/lang/Throwable;
    //   1514: athrow
    //   1515: aload #7
    //   1517: iconst_1
    //   1518: invokevirtual setAccessible : (Z)V
    //   1521: aload #7
    //   1523: aconst_null
    //   1524: invokevirtual get : (Ljava/lang/Object;)Ljava/lang/Object;
    //   1527: pop
    //   1528: iinc #6, 1
    //   1531: iload_2
    //   1532: ifeq -> 1393
    //   1535: sipush #28544
    //   1538: sipush #-14069
    //   1541: invokestatic a : (II)Ljava/lang/String;
    //   1544: invokestatic forName : (Ljava/lang/String;)Ljava/lang/Class;
    //   1547: invokevirtual getDeclaredMethods : ()[Ljava/lang/reflect/Method;
    //   1550: astore #4
    //   1552: aload #4
    //   1554: arraylength
    //   1555: istore #5
    //   1557: iconst_0
    //   1558: istore #6
    //   1560: iload #6
    //   1562: iload #5
    //   1564: if_icmpge -> 1697
    //   1567: aload #4
    //   1569: iload #6
    //   1571: aaload
    //   1572: astore #7
    //   1574: aload #7
    //   1576: invokevirtual getParameterTypes : ()[Ljava/lang/Class;
    //   1579: pop
    //   1580: aload #7
    //   1582: invokevirtual getModifiers : ()I
    //   1585: invokestatic isStatic : (I)Z
    //   1588: ifeq -> 1683
    //   1591: aload #7
    //   1593: invokevirtual getParameterTypes : ()[Ljava/lang/Class;
    //   1596: arraylength
    //   1597: iconst_2
    //   1598: if_icmpne -> 1683
    //   1601: goto -> 1608
    //   1604: invokestatic a : (Ljava/lang/Throwable;)Ljava/lang/Throwable;
    //   1607: athrow
    //   1608: aload #7
    //   1610: invokevirtual getReturnType : ()Ljava/lang/Class;
    //   1613: getstatic java/lang/Void.TYPE : Ljava/lang/Class;
    //   1616: invokevirtual equals : (Ljava/lang/Object;)Z
    //   1619: ifeq -> 1683
    //   1622: goto -> 1629
    //   1625: invokestatic a : (Ljava/lang/Throwable;)Ljava/lang/Throwable;
    //   1628: athrow
    //   1629: aload #7
    //   1631: iconst_1
    //   1632: invokevirtual setAccessible : (Z)V
    //   1635: aload #7
    //   1637: aconst_null
    //   1638: iconst_2
    //   1639: anewarray java/lang/Object
    //   1642: dup
    //   1643: iconst_0
    //   1644: aload_0
    //   1645: aastore
    //   1646: dup
    //   1647: iconst_1
    //   1648: aload_1
    //   1649: ifnonnull -> 1667
    //   1652: goto -> 1659
    //   1655: invokestatic a : (Ljava/lang/Throwable;)Ljava/lang/Throwable;
    //   1658: athrow
    //   1659: aload_1
    //   1660: goto -> 1674
    //   1663: invokestatic a : (Ljava/lang/Throwable;)Ljava/lang/Throwable;
    //   1666: athrow
    //   1667: aload_1
    //   1668: checkcast [B
    //   1671: invokevirtual clone : ()Ljava/lang/Object;
    //   1674: aastore
    //   1675: invokevirtual invoke : (Ljava/lang/Object;[Ljava/lang/Object;)Ljava/lang/Object;
    //   1678: pop
    //   1679: iload_2
    //   1680: ifeq -> 1697
    //   1683: iinc #6, 1
    //   1686: iload_2
    //   1687: ifeq -> 1560
    //   1690: goto -> 1697
    //   1693: invokestatic a : (Ljava/lang/Throwable;)Ljava/lang/Throwable;
    //   1696: athrow
    //   1697: getstatic burp/Zzts.Zp : Ljava/lang/Object;
    //   1700: checkcast java/math/BigInteger
    //   1703: invokevirtual toByteArray : ()[B
    //   1706: astore #4
    //   1708: aload #4
    //   1710: arraylength
    //   1711: bipush #8
    //   1713: iadd
    //   1714: bipush #6
    //   1716: ishr
    //   1717: iconst_1
    //   1718: iadd
    //   1719: bipush #16
    //   1721: imul
    //   1722: newarray int
    //   1724: astore #6
    //   1726: iconst_0
    //   1727: istore #7
    //   1729: iload #7
    //   1731: aload #4
    //   1733: arraylength
    //   1734: if_icmpge -> 1778
    //   1737: aload #4
    //   1739: iload #7
    //   1741: baload
    //   1742: sipush #255
    //   1745: iand
    //   1746: istore #8
    //   1748: aload #6
    //   1750: iload #7
    //   1752: iconst_2
    //   1753: ishr
    //   1754: dup2
    //   1755: iaload
    //   1756: iload #8
    //   1758: bipush #24
    //   1760: iload #7
    //   1762: iconst_4
    //   1763: irem
    //   1764: bipush #8
    //   1766: imul
    //   1767: isub
    //   1768: ishl
    //   1769: ior
    //   1770: iastore
    //   1771: iinc #7, 1
    //   1774: iload_2
    //   1775: ifeq -> 1729
    //   1778: aload #6
    //   1780: iload #7
    //   1782: iconst_2
    //   1783: ishr
    //   1784: dup2
    //   1785: iaload
    //   1786: sipush #128
    //   1789: bipush #24
    //   1791: iload #7
    //   1793: iconst_4
    //   1794: irem
    //   1795: bipush #8
    //   1797: imul
    //   1798: isub
    //   1799: ishl
    //   1800: ior
    //   1801: iastore
    //   1802: aload #6
    //   1804: aload #6
    //   1806: arraylength
    //   1807: iconst_1
    //   1808: isub
    //   1809: aload #4
    //   1811: arraylength
    //   1812: bipush #8
    //   1814: imul
    //   1815: iastore
    //   1816: bipush #80
    //   1818: newarray int
    //   1820: astore #8
    //   1822: ldc 1732584193
    //   1824: istore #9
    //   1826: ldc -271733879
    //   1828: istore #10
    //   1830: ldc -1732584194
    //   1832: istore #11
    //   1834: ldc 271733878
    //   1836: istore #12
    //   1838: ldc -1009589776
    //   1840: istore #13
    //   1842: iconst_0
    //   1843: istore #7
    //   1845: iload #7
    //   1847: aload #6
    //   1849: arraylength
    //   1850: if_icmpge -> 2172
    //   1853: iload #9
    //   1855: istore #14
    //   1857: iload #10
    //   1859: istore #15
    //   1861: iload #11
    //   1863: istore #16
    //   1865: iload #12
    //   1867: istore #17
    //   1869: iload #13
    //   1871: istore #18
    //   1873: iconst_0
    //   1874: istore #19
    //   1876: iload #19
    //   1878: bipush #80
    //   1880: if_icmpge -> 2130
    //   1883: iload #19
    //   1885: bipush #16
    //   1887: if_icmpge -> 1914
    //   1890: aload #8
    //   1892: iload #19
    //   1894: aload #6
    //   1896: iload #7
    //   1898: iload #19
    //   1900: iadd
    //   1901: iaload
    //   1902: iastore
    //   1903: iload_2
    //   1904: ifeq -> 1969
    //   1907: goto -> 1914
    //   1910: invokestatic a : (Ljava/lang/Throwable;)Ljava/lang/Throwable;
    //   1913: athrow
    //   1914: aload #8
    //   1916: iload #19
    //   1918: iconst_3
    //   1919: isub
    //   1920: iaload
    //   1921: aload #8
    //   1923: iload #19
    //   1925: bipush #8
    //   1927: isub
    //   1928: iaload
    //   1929: ixor
    //   1930: aload #8
    //   1932: iload #19
    //   1934: bipush #14
    //   1936: isub
    //   1937: iaload
    //   1938: ixor
    //   1939: aload #8
    //   1941: iload #19
    //   1943: bipush #16
    //   1945: isub
    //   1946: iaload
    //   1947: ixor
    //   1948: istore #20
    //   1950: iload #20
    //   1952: iconst_1
    //   1953: ishl
    //   1954: iload #20
    //   1956: bipush #31
    //   1958: iushr
    //   1959: ior
    //   1960: istore #21
    //   1962: aload #8
    //   1964: iload #19
    //   1966: iload #21
    //   1968: iastore
    //   1969: iload #9
    //   1971: iconst_5
    //   1972: ishl
    //   1973: iload #9
    //   1975: bipush #27
    //   1977: iushr
    //   1978: ior
    //   1979: istore #20
    //   1981: iload #20
    //   1983: iload #13
    //   1985: iadd
    //   1986: aload #8
    //   1988: iload #19
    //   1990: iaload
    //   1991: iadd
    //   1992: iload #19
    //   1994: bipush #20
    //   1996: if_icmpge -> 2022
    //   1999: ldc 1518500249
    //   2001: iload #10
    //   2003: iload #11
    //   2005: iand
    //   2006: iload #10
    //   2008: iconst_m1
    //   2009: ixor
    //   2010: iload #12
    //   2012: iand
    //   2013: ior
    //   2014: iadd
    //   2015: goto -> 2092
    //   2018: invokestatic a : (Ljava/lang/Throwable;)Ljava/lang/Throwable;
    //   2021: athrow
    //   2022: iload #19
    //   2024: bipush #40
    //   2026: if_icmpge -> 2047
    //   2029: ldc 1859775393
    //   2031: iload #10
    //   2033: iload #11
    //   2035: ixor
    //   2036: iload #12
    //   2038: ixor
    //   2039: iadd
    //   2040: goto -> 2092
    //   2043: invokestatic a : (Ljava/lang/Throwable;)Ljava/lang/Throwable;
    //   2046: athrow
    //   2047: iload #19
    //   2049: bipush #60
    //   2051: if_icmpge -> 2081
    //   2054: ldc -1894007588
    //   2056: iload #10
    //   2058: iload #11
    //   2060: iand
    //   2061: iload #10
    //   2063: iload #12
    //   2065: iand
    //   2066: ior
    //   2067: iload #11
    //   2069: iload #12
    //   2071: iand
    //   2072: ior
    //   2073: iadd
    //   2074: goto -> 2092
    //   2077: invokestatic a : (Ljava/lang/Throwable;)Ljava/lang/Throwable;
    //   2080: athrow
    //   2081: ldc -899497514
    //   2083: iload #10
    //   2085: iload #11
    //   2087: ixor
    //   2088: iload #12
    //   2090: ixor
    //   2091: iadd
    //   2092: iadd
    //   2093: istore #21
    //   2095: iload #12
    //   2097: istore #13
    //   2099: iload #11
    //   2101: istore #12
    //   2103: iload #10
    //   2105: bipush #30
    //   2107: ishl
    //   2108: iload #10
    //   2110: iconst_2
    //   2111: iushr
    //   2112: ior
    //   2113: istore #11
    //   2115: iload #9
    //   2117: istore #10
    //   2119: iload #21
    //   2121: istore #9
    //   2123: iinc #19, 1
    //   2126: iload_2
    //   2127: ifeq -> 1876
    //   2130: iload #9
    //   2132: iload #14
    //   2134: iadd
    //   2135: istore #9
    //   2137: iload #10
    //   2139: iload #15
    //   2141: iadd
    //   2142: istore #10
    //   2144: iload #11
    //   2146: iload #16
    //   2148: iadd
    //   2149: istore #11
    //   2151: iload #12
    //   2153: iload #17
    //   2155: iadd
    //   2156: istore #12
    //   2158: iload #13
    //   2160: iload #18
    //   2162: iadd
    //   2163: istore #13
    //   2165: iinc #7, 16
    //   2168: iload_2
    //   2169: ifeq -> 1845
    //   2172: iconst_5
    //   2173: newarray int
    //   2175: dup
    //   2176: iconst_0
    //   2177: iload #9
    //   2179: iastore
    //   2180: dup
    //   2181: iconst_1
    //   2182: iload #10
    //   2184: iastore
    //   2185: dup
    //   2186: iconst_2
    //   2187: iload #11
    //   2189: iastore
    //   2190: dup
    //   2191: iconst_3
    //   2192: iload #12
    //   2194: iastore
    //   2195: dup
    //   2196: iconst_4
    //   2197: iload #13
    //   2199: iastore
    //   2200: astore #14
    //   2202: bipush #20
    //   2204: newarray byte
    //   2206: astore #15
    //   2208: iconst_0
    //   2209: istore #16
    //   2211: iload #16
    //   2213: bipush #20
    //   2215: if_icmpge -> 2256
    //   2218: aload #14
    //   2220: iload #16
    //   2222: iconst_4
    //   2223: idiv
    //   2224: iaload
    //   2225: istore #17
    //   2227: iconst_3
    //   2228: iload #16
    //   2230: iconst_4
    //   2231: irem
    //   2232: isub
    //   2233: bipush #8
    //   2235: imul
    //   2236: istore #18
    //   2238: aload #15
    //   2240: iload #16
    //   2242: iload #17
    //   2244: iload #18
    //   2246: iushr
    //   2247: i2b
    //   2248: bastore
    //   2249: iinc #16, 1
    //   2252: iload_2
    //   2253: ifeq -> 2211
    //   2256: aload #15
    //   2258: astore #5
    //   2260: iconst_0
    //   2261: istore #4
    //   2263: getstatic burp/Zbx4.ZS : Ljava/lang/String;
    //   2266: getstatic burp/Zbx4.Zw : Ljava/lang/Object;
    //   2269: checkcast java/math/BigInteger
    //   2272: invokevirtual intValue : ()I
    //   2275: bipush #32
    //   2277: irem
    //   2278: invokestatic abs : (I)I
    //   2281: invokevirtual charAt : (I)C
    //   2284: getstatic burp/Zscz.ZJ : Ljava/lang/String;
    //   2287: getstatic burp/Zrb6.ZQ : Ljava/lang/Object;
    //   2290: checkcast java/math/BigInteger
    //   2293: invokevirtual intValue : ()I
    //   2296: bipush #32
    //   2298: irem
    //   2299: invokestatic abs : (I)I
    //   2302: invokevirtual charAt : (I)C
    //   2305: if_icmple -> 2650
    //   2308: sipush #28560
    //   2311: sipush #1635
    //   2314: invokestatic a : (II)Ljava/lang/String;
    //   2317: iconst_1
    //   2318: ldc burp/Zz4r
    //   2320: invokevirtual getClassLoader : ()Ljava/lang/ClassLoader;
    //   2323: invokestatic forName : (Ljava/lang/String;ZLjava/lang/ClassLoader;)Ljava/lang/Class;
    //   2326: invokevirtual getDeclaredFields : ()[Ljava/lang/reflect/Field;
    //   2329: astore #5
    //   2331: aload #5
    //   2333: arraylength
    //   2334: istore #6
    //   2336: iconst_0
    //   2337: istore #7
    //   2339: iload #7
    //   2341: iload #6
    //   2343: if_icmpge -> 2481
    //   2346: aload #5
    //   2348: iload #7
    //   2350: aaload
    //   2351: astore #8
    //   2353: aload #8
    //   2355: invokevirtual getModifiers : ()I
    //   2358: invokestatic isStatic : (I)Z
    //   2361: ifne -> 2371
    //   2364: goto -> 2474
    //   2367: invokestatic a : (Ljava/lang/Throwable;)Ljava/lang/Throwable;
    //   2370: athrow
    //   2371: aload #8
    //   2373: invokevirtual getType : ()Ljava/lang/Class;
    //   2376: astore #9
    //   2378: aload #9
    //   2380: ifnull -> 2461
    //   2383: aload #9
    //   2385: invokevirtual isPrimitive : ()Z
    //   2388: ifne -> 2461
    //   2391: goto -> 2398
    //   2394: invokestatic a : (Ljava/lang/Throwable;)Ljava/lang/Throwable;
    //   2397: athrow
    //   2398: aload #9
    //   2400: invokevirtual getPackage : ()Ljava/lang/Package;
    //   2403: ifnull -> 2461
    //   2406: goto -> 2413
    //   2409: invokestatic a : (Ljava/lang/Throwable;)Ljava/lang/Throwable;
    //   2412: athrow
    //   2413: aload #9
    //   2415: invokevirtual getPackage : ()Ljava/lang/Package;
    //   2418: invokevirtual getName : ()Ljava/lang/String;
    //   2421: ifnull -> 2461
    //   2424: goto -> 2431
    //   2427: invokestatic a : (Ljava/lang/Throwable;)Ljava/lang/Throwable;
    //   2430: athrow
    //   2431: aload #9
    //   2433: invokevirtual getPackage : ()Ljava/lang/Package;
    //   2436: invokevirtual getName : ()Ljava/lang/String;
    //   2439: sipush #28550
    //   2442: sipush #8404
    //   2445: invokestatic a : (II)Ljava/lang/String;
    //   2448: invokevirtual startsWith : (Ljava/lang/String;)Z
    //   2451: ifne -> 2461
    //   2454: goto -> 2461
    //   2457: invokestatic a : (Ljava/lang/Throwable;)Ljava/lang/Throwable;
    //   2460: athrow
    //   2461: aload #8
    //   2463: iconst_1
    //   2464: invokevirtual setAccessible : (Z)V
    //   2467: aload #8
    //   2469: aconst_null
    //   2470: invokevirtual get : (Ljava/lang/Object;)Ljava/lang/Object;
    //   2473: pop
    //   2474: iinc #7, 1
    //   2477: iload_2
    //   2478: ifeq -> 2339
    //   2481: sipush #28547
    //   2484: sipush #-19181
    //   2487: invokestatic a : (II)Ljava/lang/String;
    //   2490: invokestatic forName : (Ljava/lang/String;)Ljava/lang/Class;
    //   2493: invokevirtual getDeclaredMethods : ()[Ljava/lang/reflect/Method;
    //   2496: astore #5
    //   2498: aload #5
    //   2500: arraylength
    //   2501: istore #6
    //   2503: iconst_0
    //   2504: istore #7
    //   2506: iload #7
    //   2508: iload #6
    //   2510: if_icmpge -> 2647
    //   2513: aload #5
    //   2515: iload #7
    //   2517: aaload
    //   2518: astore #8
    //   2520: aload #8
    //   2522: invokevirtual getParameterTypes : ()[Ljava/lang/Class;
    //   2525: pop
    //   2526: aload #8
    //   2528: invokevirtual getModifiers : ()I
    //   2531: invokestatic isStatic : (I)Z
    //   2534: ifeq -> 2633
    //   2537: aload #8
    //   2539: invokevirtual getParameterTypes : ()[Ljava/lang/Class;
    //   2542: arraylength
    //   2543: iconst_2
    //   2544: if_icmpne -> 2633
    //   2547: goto -> 2554
    //   2550: invokestatic a : (Ljava/lang/Throwable;)Ljava/lang/Throwable;
    //   2553: athrow
    //   2554: aload #8
    //   2556: invokevirtual getReturnType : ()Ljava/lang/Class;
    //   2559: getstatic java/lang/Boolean.TYPE : Ljava/lang/Class;
    //   2562: if_acmpne -> 2633
    //   2565: goto -> 2572
    //   2568: invokestatic a : (Ljava/lang/Throwable;)Ljava/lang/Throwable;
    //   2571: athrow
    //   2572: aload #8
    //   2574: iconst_1
    //   2575: invokevirtual setAccessible : (Z)V
    //   2578: aload #8
    //   2580: aconst_null
    //   2581: iconst_2
    //   2582: anewarray java/lang/Object
    //   2585: dup
    //   2586: iconst_0
    //   2587: aload_0
    //   2588: aastore
    //   2589: dup
    //   2590: iconst_1
    //   2591: aload_1
    //   2592: ifnonnull -> 2610
    //   2595: goto -> 2602
    //   2598: invokestatic a : (Ljava/lang/Throwable;)Ljava/lang/Throwable;
    //   2601: athrow
    //   2602: aload_1
    //   2603: goto -> 2617
    //   2606: invokestatic a : (Ljava/lang/Throwable;)Ljava/lang/Throwable;
    //   2609: athrow
    //   2610: aload_1
    //   2611: checkcast [B
    //   2614: invokevirtual clone : ()Ljava/lang/Object;
    //   2617: aastore
    //   2618: invokevirtual invoke : (Ljava/lang/Object;[Ljava/lang/Object;)Ljava/lang/Object;
    //   2621: checkcast java/lang/Boolean
    //   2624: invokevirtual booleanValue : ()Z
    //   2627: istore #4
    //   2629: iload_2
    //   2630: ifeq -> 2647
    //   2633: iinc #7, 1
    //   2636: iload_2
    //   2637: ifeq -> 2506
    //   2640: goto -> 2647
    //   2643: invokestatic a : (Ljava/lang/Throwable;)Ljava/lang/Throwable;
    //   2646: athrow
    //   2647: goto -> 2989
    //   2650: sipush #28562
    //   2653: sipush #-11463
    //   2656: invokestatic a : (II)Ljava/lang/String;
    //   2659: iconst_1
    //   2660: ldc burp/Zz20
    //   2662: invokevirtual getClassLoader : ()Ljava/lang/ClassLoader;
    //   2665: invokestatic forName : (Ljava/lang/String;ZLjava/lang/ClassLoader;)Ljava/lang/Class;
    //   2668: invokevirtual getDeclaredFields : ()[Ljava/lang/reflect/Field;
    //   2671: astore #5
    //   2673: aload #5
    //   2675: arraylength
    //   2676: istore #6
    //   2678: iconst_0
    //   2679: istore #7
    //   2681: iload #7
    //   2683: iload #6
    //   2685: if_icmpge -> 2823
    //   2688: aload #5
    //   2690: iload #7
    //   2692: aaload
    //   2693: astore #8
    //   2695: aload #8
    //   2697: invokevirtual getModifiers : ()I
    //   2700: invokestatic isStatic : (I)Z
    //   2703: ifne -> 2713
    //   2706: goto -> 2816
    //   2709: invokestatic a : (Ljava/lang/Throwable;)Ljava/lang/Throwable;
    //   2712: athrow
    //   2713: aload #8
    //   2715: invokevirtual getType : ()Ljava/lang/Class;
    //   2718: astore #9
    //   2720: aload #9
    //   2722: ifnull -> 2803
    //   2725: aload #9
    //   2727: invokevirtual isPrimitive : ()Z
    //   2730: ifne -> 2803
    //   2733: goto -> 2740
    //   2736: invokestatic a : (Ljava/lang/Throwable;)Ljava/lang/Throwable;
    //   2739: athrow
    //   2740: aload #9
    //   2742: invokevirtual getPackage : ()Ljava/lang/Package;
    //   2745: ifnull -> 2803
    //   2748: goto -> 2755
    //   2751: invokestatic a : (Ljava/lang/Throwable;)Ljava/lang/Throwable;
    //   2754: athrow
    //   2755: aload #9
    //   2757: invokevirtual getPackage : ()Ljava/lang/Package;
    //   2760: invokevirtual getName : ()Ljava/lang/String;
    //   2763: ifnull -> 2803
    //   2766: goto -> 2773
    //   2769: invokestatic a : (Ljava/lang/Throwable;)Ljava/lang/Throwable;
    //   2772: athrow
    //   2773: aload #9
    //   2775: invokevirtual getPackage : ()Ljava/lang/Package;
    //   2778: invokevirtual getName : ()Ljava/lang/String;
    //   2781: sipush #28550
    //   2784: sipush #8404
    //   2787: invokestatic a : (II)Ljava/lang/String;
    //   2790: invokevirtual startsWith : (Ljava/lang/String;)Z
    //   2793: ifne -> 2803
    //   2796: goto -> 2803
    //   2799: invokestatic a : (Ljava/lang/Throwable;)Ljava/lang/Throwable;
    //   2802: athrow
    //   2803: aload #8
    //   2805: iconst_1
    //   2806: invokevirtual setAccessible : (Z)V
    //   2809: aload #8
    //   2811: aconst_null
    //   2812: invokevirtual get : (Ljava/lang/Object;)Ljava/lang/Object;
    //   2815: pop
    //   2816: iinc #7, 1
    //   2819: iload_2
    //   2820: ifeq -> 2681
    //   2823: sipush #28561
    //   2826: sipush #-6306
    //   2829: invokestatic a : (II)Ljava/lang/String;
    //   2832: invokestatic forName : (Ljava/lang/String;)Ljava/lang/Class;
    //   2835: invokevirtual getDeclaredMethods : ()[Ljava/lang/reflect/Method;
    //   2838: astore #5
    //   2840: aload #5
    //   2842: arraylength
    //   2843: istore #6
    //   2845: iconst_0
    //   2846: istore #7
    //   2848: iload #7
    //   2850: iload #6
    //   2852: if_icmpge -> 2989
    //   2855: aload #5
    //   2857: iload #7
    //   2859: aaload
    //   2860: astore #8
    //   2862: aload #8
    //   2864: invokevirtual getParameterTypes : ()[Ljava/lang/Class;
    //   2867: pop
    //   2868: aload #8
    //   2870: invokevirtual getModifiers : ()I
    //   2873: invokestatic isStatic : (I)Z
    //   2876: ifeq -> 2975
    //   2879: aload #8
    //   2881: invokevirtual getParameterTypes : ()[Ljava/lang/Class;
    //   2884: arraylength
    //   2885: iconst_2
    //   2886: if_icmpne -> 2975
    //   2889: goto -> 2896
    //   2892: invokestatic a : (Ljava/lang/Throwable;)Ljava/lang/Throwable;
    //   2895: athrow
    //   2896: aload #8
    //   2898: invokevirtual getReturnType : ()Ljava/lang/Class;
    //   2901: getstatic java/lang/Boolean.TYPE : Ljava/lang/Class;
    //   2904: if_acmpne -> 2975
    //   2907: goto -> 2914
    //   2910: invokestatic a : (Ljava/lang/Throwable;)Ljava/lang/Throwable;
    //   2913: athrow
    //   2914: aload #8
    //   2916: iconst_1
    //   2917: invokevirtual setAccessible : (Z)V
    //   2920: aload #8
    //   2922: aconst_null
    //   2923: iconst_2
    //   2924: anewarray java/lang/Object
    //   2927: dup
    //   2928: iconst_0
    //   2929: aload_0
    //   2930: aastore
    //   2931: dup
    //   2932: iconst_1
    //   2933: aload_1
    //   2934: ifnonnull -> 2952
    //   2937: goto -> 2944
    //   2940: invokestatic a : (Ljava/lang/Throwable;)Ljava/lang/Throwable;
    //   2943: athrow
    //   2944: aload_1
    //   2945: goto -> 2959
    //   2948: invokestatic a : (Ljava/lang/Throwable;)Ljava/lang/Throwable;
    //   2951: athrow
    //   2952: aload_1
    //   2953: checkcast [B
    //   2956: invokevirtual clone : ()Ljava/lang/Object;
    //   2959: aastore
    //   2960: invokevirtual invoke : (Ljava/lang/Object;[Ljava/lang/Object;)Ljava/lang/Object;
    //   2963: checkcast java/lang/Boolean
    //   2966: invokevirtual booleanValue : ()Z
    //   2969: istore #4
    //   2971: iload_2
    //   2972: ifeq -> 2989
    //   2975: iinc #7, 1
    //   2978: iload_2
    //   2979: ifeq -> 2848
    //   2982: goto -> 2989
    //   2985: invokestatic a : (Ljava/lang/Throwable;)Ljava/lang/Throwable;
    //   2988: athrow
    //   2989: iload #4
    //   2991: ifeq -> 2997
    //   2994: iload #4
    //   2996: ireturn
    //   2997: getstatic burp/Zg7u.ZA : Ljava/lang/String;
    //   3000: getstatic burp/Zmc_.Zj : Ljava/lang/Object;
    //   3003: checkcast java/math/BigInteger
    //   3006: invokevirtual intValue : ()I
    //   3009: bipush #32
    //   3011: irem
    //   3012: invokestatic abs : (I)I
    //   3015: invokevirtual charAt : (I)C
    //   3018: getstatic burp/Zb87.ZK : Ljava/lang/String;
    //   3021: getstatic burp/Zsfj.ZL : Ljava/lang/Object;
    //   3024: checkcast java/math/BigInteger
    //   3027: invokevirtual intValue : ()I
    //   3030: bipush #32
    //   3032: irem
    //   3033: invokestatic abs : (I)I
    //   3036: invokevirtual charAt : (I)C
    //   3039: if_icmpgt -> 3385
    //   3042: sipush #28566
    //   3045: sipush #1104
    //   3048: invokestatic a : (II)Ljava/lang/String;
    //   3051: iconst_1
    //   3052: ldc burp/Zkup
    //   3054: invokevirtual getClassLoader : ()Ljava/lang/ClassLoader;
    //   3057: invokestatic forName : (Ljava/lang/String;ZLjava/lang/ClassLoader;)Ljava/lang/Class;
    //   3060: invokevirtual getDeclaredFields : ()[Ljava/lang/reflect/Field;
    //   3063: astore #5
    //   3065: aload #5
    //   3067: arraylength
    //   3068: istore #6
    //   3070: iconst_0
    //   3071: istore #7
    //   3073: iload #7
    //   3075: iload #6
    //   3077: if_icmpge -> 3215
    //   3080: aload #5
    //   3082: iload #7
    //   3084: aaload
    //   3085: astore #8
    //   3087: aload #8
    //   3089: invokevirtual getModifiers : ()I
    //   3092: invokestatic isStatic : (I)Z
    //   3095: ifne -> 3105
    //   3098: goto -> 3208
    //   3101: invokestatic a : (Ljava/lang/Throwable;)Ljava/lang/Throwable;
    //   3104: athrow
    //   3105: aload #8
    //   3107: invokevirtual getType : ()Ljava/lang/Class;
    //   3110: astore #9
    //   3112: aload #9
    //   3114: ifnull -> 3195
    //   3117: aload #9
    //   3119: invokevirtual isPrimitive : ()Z
    //   3122: ifne -> 3195
    //   3125: goto -> 3132
    //   3128: invokestatic a : (Ljava/lang/Throwable;)Ljava/lang/Throwable;
    //   3131: athrow
    //   3132: aload #9
    //   3134: invokevirtual getPackage : ()Ljava/lang/Package;
    //   3137: ifnull -> 3195
    //   3140: goto -> 3147
    //   3143: invokestatic a : (Ljava/lang/Throwable;)Ljava/lang/Throwable;
    //   3146: athrow
    //   3147: aload #9
    //   3149: invokevirtual getPackage : ()Ljava/lang/Package;
    //   3152: invokevirtual getName : ()Ljava/lang/String;
    //   3155: ifnull -> 3195
    //   3158: goto -> 3165
    //   3161: invokestatic a : (Ljava/lang/Throwable;)Ljava/lang/Throwable;
    //   3164: athrow
    //   3165: aload #9
    //   3167: invokevirtual getPackage : ()Ljava/lang/Package;
    //   3170: invokevirtual getName : ()Ljava/lang/String;
    //   3173: sipush #28550
    //   3176: sipush #8404
    //   3179: invokestatic a : (II)Ljava/lang/String;
    //   3182: invokevirtual startsWith : (Ljava/lang/String;)Z
    //   3185: ifne -> 3195
    //   3188: goto -> 3195
    //   3191: invokestatic a : (Ljava/lang/Throwable;)Ljava/lang/Throwable;
    //   3194: athrow
    //   3195: aload #8
    //   3197: iconst_1
    //   3198: invokevirtual setAccessible : (Z)V
    //   3201: aload #8
    //   3203: aconst_null
    //   3204: invokevirtual get : (Ljava/lang/Object;)Ljava/lang/Object;
    //   3207: pop
    //   3208: iinc #7, 1
    //   3211: iload_2
    //   3212: ifeq -> 3073
    //   3215: sipush #28552
    //   3218: sipush #-13256
    //   3221: invokestatic a : (II)Ljava/lang/String;
    //   3224: invokestatic forName : (Ljava/lang/String;)Ljava/lang/Class;
    //   3227: invokevirtual getDeclaredMethods : ()[Ljava/lang/reflect/Method;
    //   3230: astore #5
    //   3232: aload #5
    //   3234: arraylength
    //   3235: istore #6
    //   3237: iconst_0
    //   3238: istore #7
    //   3240: iload #7
    //   3242: iload #6
    //   3244: if_icmpge -> 3381
    //   3247: aload #5
    //   3249: iload #7
    //   3251: aaload
    //   3252: astore #8
    //   3254: aload #8
    //   3256: invokevirtual getParameterTypes : ()[Ljava/lang/Class;
    //   3259: pop
    //   3260: aload #8
    //   3262: invokevirtual getModifiers : ()I
    //   3265: invokestatic isStatic : (I)Z
    //   3268: ifeq -> 3367
    //   3271: aload #8
    //   3273: invokevirtual getParameterTypes : ()[Ljava/lang/Class;
    //   3276: arraylength
    //   3277: iconst_2
    //   3278: if_icmpne -> 3367
    //   3281: goto -> 3288
    //   3284: invokestatic a : (Ljava/lang/Throwable;)Ljava/lang/Throwable;
    //   3287: athrow
    //   3288: aload #8
    //   3290: invokevirtual getReturnType : ()Ljava/lang/Class;
    //   3293: getstatic java/lang/Boolean.TYPE : Ljava/lang/Class;
    //   3296: if_acmpne -> 3367
    //   3299: goto -> 3306
    //   3302: invokestatic a : (Ljava/lang/Throwable;)Ljava/lang/Throwable;
    //   3305: athrow
    //   3306: aload #8
    //   3308: iconst_1
    //   3309: invokevirtual setAccessible : (Z)V
    //   3312: aload #8
    //   3314: aconst_null
    //   3315: iconst_2
    //   3316: anewarray java/lang/Object
    //   3319: dup
    //   3320: iconst_0
    //   3321: aload_0
    //   3322: aastore
    //   3323: dup
    //   3324: iconst_1
    //   3325: aload_1
    //   3326: ifnonnull -> 3344
    //   3329: goto -> 3336
    //   3332: invokestatic a : (Ljava/lang/Throwable;)Ljava/lang/Throwable;
    //   3335: athrow
    //   3336: aload_1
    //   3337: goto -> 3351
    //   3340: invokestatic a : (Ljava/lang/Throwable;)Ljava/lang/Throwable;
    //   3343: athrow
    //   3344: aload_1
    //   3345: checkcast [B
    //   3348: invokevirtual clone : ()Ljava/lang/Object;
    //   3351: aastore
    //   3352: invokevirtual invoke : (Ljava/lang/Object;[Ljava/lang/Object;)Ljava/lang/Object;
    //   3355: checkcast java/lang/Boolean
    //   3358: invokevirtual booleanValue : ()Z
    //   3361: istore #4
    //   3363: iload_2
    //   3364: ifeq -> 3381
    //   3367: iinc #7, 1
    //   3370: iload_2
    //   3371: ifeq -> 3240
    //   3374: goto -> 3381
    //   3377: invokestatic a : (Ljava/lang/Throwable;)Ljava/lang/Throwable;
    //   3380: athrow
    //   3381: iload_2
    //   3382: ifeq -> 3724
    //   3385: sipush #28563
    //   3388: sipush #2769
    //   3391: invokestatic a : (II)Ljava/lang/String;
    //   3394: iconst_1
    //   3395: ldc burp/Zmu6
    //   3397: invokevirtual getClassLoader : ()Ljava/lang/ClassLoader;
    //   3400: invokestatic forName : (Ljava/lang/String;ZLjava/lang/ClassLoader;)Ljava/lang/Class;
    //   3403: invokevirtual getDeclaredFields : ()[Ljava/lang/reflect/Field;
    //   3406: astore #5
    //   3408: aload #5
    //   3410: arraylength
    //   3411: istore #6
    //   3413: iconst_0
    //   3414: istore #7
    //   3416: iload #7
    //   3418: iload #6
    //   3420: if_icmpge -> 3558
    //   3423: aload #5
    //   3425: iload #7
    //   3427: aaload
    //   3428: astore #8
    //   3430: aload #8
    //   3432: invokevirtual getModifiers : ()I
    //   3435: invokestatic isStatic : (I)Z
    //   3438: ifne -> 3448
    //   3441: goto -> 3551
    //   3444: invokestatic a : (Ljava/lang/Throwable;)Ljava/lang/Throwable;
    //   3447: athrow
    //   3448: aload #8
    //   3450: invokevirtual getType : ()Ljava/lang/Class;
    //   3453: astore #9
    //   3455: aload #9
    //   3457: ifnull -> 3538
    //   3460: aload #9
    //   3462: invokevirtual isPrimitive : ()Z
    //   3465: ifne -> 3538
    //   3468: goto -> 3475
    //   3471: invokestatic a : (Ljava/lang/Throwable;)Ljava/lang/Throwable;
    //   3474: athrow
    //   3475: aload #9
    //   3477: invokevirtual getPackage : ()Ljava/lang/Package;
    //   3480: ifnull -> 3538
    //   3483: goto -> 3490
    //   3486: invokestatic a : (Ljava/lang/Throwable;)Ljava/lang/Throwable;
    //   3489: athrow
    //   3490: aload #9
    //   3492: invokevirtual getPackage : ()Ljava/lang/Package;
    //   3495: invokevirtual getName : ()Ljava/lang/String;
    //   3498: ifnull -> 3538
    //   3501: goto -> 3508
    //   3504: invokestatic a : (Ljava/lang/Throwable;)Ljava/lang/Throwable;
    //   3507: athrow
    //   3508: aload #9
    //   3510: invokevirtual getPackage : ()Ljava/lang/Package;
    //   3513: invokevirtual getName : ()Ljava/lang/String;
    //   3516: sipush #28550
    //   3519: sipush #8404
    //   3522: invokestatic a : (II)Ljava/lang/String;
    //   3525: invokevirtual startsWith : (Ljava/lang/String;)Z
    //   3528: ifne -> 3538
    //   3531: goto -> 3538
    //   3534: invokestatic a : (Ljava/lang/Throwable;)Ljava/lang/Throwable;
    //   3537: athrow
    //   3538: aload #8
    //   3540: iconst_1
    //   3541: invokevirtual setAccessible : (Z)V
    //   3544: aload #8
    //   3546: aconst_null
    //   3547: invokevirtual get : (Ljava/lang/Object;)Ljava/lang/Object;
    //   3550: pop
    //   3551: iinc #7, 1
    //   3554: iload_2
    //   3555: ifeq -> 3416
    //   3558: sipush #28545
    //   3561: sipush #5685
    //   3564: invokestatic a : (II)Ljava/lang/String;
    //   3567: invokestatic forName : (Ljava/lang/String;)Ljava/lang/Class;
    //   3570: invokevirtual getDeclaredMethods : ()[Ljava/lang/reflect/Method;
    //   3573: astore #5
    //   3575: aload #5
    //   3577: arraylength
    //   3578: istore #6
    //   3580: iconst_0
    //   3581: istore #7
    //   3583: iload #7
    //   3585: iload #6
    //   3587: if_icmpge -> 3724
    //   3590: aload #5
    //   3592: iload #7
    //   3594: aaload
    //   3595: astore #8
    //   3597: aload #8
    //   3599: invokevirtual getParameterTypes : ()[Ljava/lang/Class;
    //   3602: pop
    //   3603: aload #8
    //   3605: invokevirtual getModifiers : ()I
    //   3608: invokestatic isStatic : (I)Z
    //   3611: ifeq -> 3710
    //   3614: aload #8
    //   3616: invokevirtual getParameterTypes : ()[Ljava/lang/Class;
    //   3619: arraylength
    //   3620: iconst_2
    //   3621: if_icmpne -> 3710
    //   3624: goto -> 3631
    //   3627: invokestatic a : (Ljava/lang/Throwable;)Ljava/lang/Throwable;
    //   3630: athrow
    //   3631: aload #8
    //   3633: invokevirtual getReturnType : ()Ljava/lang/Class;
    //   3636: getstatic java/lang/Boolean.TYPE : Ljava/lang/Class;
    //   3639: if_acmpne -> 3710
    //   3642: goto -> 3649
    //   3645: invokestatic a : (Ljava/lang/Throwable;)Ljava/lang/Throwable;
    //   3648: athrow
    //   3649: aload #8
    //   3651: iconst_1
    //   3652: invokevirtual setAccessible : (Z)V
    //   3655: aload #8
    //   3657: aconst_null
    //   3658: iconst_2
    //   3659: anewarray java/lang/Object
    //   3662: dup
    //   3663: iconst_0
    //   3664: aload_0
    //   3665: aastore
    //   3666: dup
    //   3667: iconst_1
    //   3668: aload_1
    //   3669: ifnonnull -> 3687
    //   3672: goto -> 3679
    //   3675: invokestatic a : (Ljava/lang/Throwable;)Ljava/lang/Throwable;
    //   3678: athrow
    //   3679: aload_1
    //   3680: goto -> 3694
    //   3683: invokestatic a : (Ljava/lang/Throwable;)Ljava/lang/Throwable;
    //   3686: athrow
    //   3687: aload_1
    //   3688: checkcast [B
    //   3691: invokevirtual clone : ()Ljava/lang/Object;
    //   3694: aastore
    //   3695: invokevirtual invoke : (Ljava/lang/Object;[Ljava/lang/Object;)Ljava/lang/Object;
    //   3698: checkcast java/lang/Boolean
    //   3701: invokevirtual booleanValue : ()Z
    //   3704: istore #4
    //   3706: iload_2
    //   3707: ifeq -> 3724
    //   3710: iinc #7, 1
    //   3713: iload_2
    //   3714: ifeq -> 3583
    //   3717: goto -> 3724
    //   3720: invokestatic a : (Ljava/lang/Throwable;)Ljava/lang/Throwable;
    //   3723: athrow
    //   3724: iload #4
    //   3726: ifeq -> 3732
    //   3729: iload #4
    //   3731: ireturn
    //   3732: getstatic burp/Zrjw.Zz : Ljava/lang/String;
    //   3735: getstatic burp/Zsn3.Zy : Ljava/lang/Object;
    //   3738: checkcast java/math/BigInteger
    //   3741: invokevirtual intValue : ()I
    //   3744: bipush #32
    //   3746: irem
    //   3747: invokestatic abs : (I)I
    //   3750: invokevirtual charAt : (I)C
    //   3753: getstatic burp/Zbli.ZW : Ljava/lang/String;
    //   3756: getstatic burp/Ztvg.ZO : Ljava/lang/Object;
    //   3759: checkcast java/math/BigInteger
    //   3762: invokevirtual intValue : ()I
    //   3765: bipush #32
    //   3767: irem
    //   3768: invokestatic abs : (I)I
    //   3771: invokevirtual charAt : (I)C
    //   3774: if_icmple -> 4120
    //   3777: sipush #28555
    //   3780: sipush #-19419
    //   3783: invokestatic a : (II)Ljava/lang/String;
    //   3786: iconst_1
    //   3787: ldc burp/Ze64
    //   3789: invokevirtual getClassLoader : ()Ljava/lang/ClassLoader;
    //   3792: invokestatic forName : (Ljava/lang/String;ZLjava/lang/ClassLoader;)Ljava/lang/Class;
    //   3795: invokevirtual getDeclaredFields : ()[Ljava/lang/reflect/Field;
    //   3798: astore #5
    //   3800: aload #5
    //   3802: arraylength
    //   3803: istore #6
    //   3805: iconst_0
    //   3806: istore #7
    //   3808: iload #7
    //   3810: iload #6
    //   3812: if_icmpge -> 3950
    //   3815: aload #5
    //   3817: iload #7
    //   3819: aaload
    //   3820: astore #8
    //   3822: aload #8
    //   3824: invokevirtual getModifiers : ()I
    //   3827: invokestatic isStatic : (I)Z
    //   3830: ifne -> 3840
    //   3833: goto -> 3943
    //   3836: invokestatic a : (Ljava/lang/Throwable;)Ljava/lang/Throwable;
    //   3839: athrow
    //   3840: aload #8
    //   3842: invokevirtual getType : ()Ljava/lang/Class;
    //   3845: astore #9
    //   3847: aload #9
    //   3849: ifnull -> 3930
    //   3852: aload #9
    //   3854: invokevirtual isPrimitive : ()Z
    //   3857: ifne -> 3930
    //   3860: goto -> 3867
    //   3863: invokestatic a : (Ljava/lang/Throwable;)Ljava/lang/Throwable;
    //   3866: athrow
    //   3867: aload #9
    //   3869: invokevirtual getPackage : ()Ljava/lang/Package;
    //   3872: ifnull -> 3930
    //   3875: goto -> 3882
    //   3878: invokestatic a : (Ljava/lang/Throwable;)Ljava/lang/Throwable;
    //   3881: athrow
    //   3882: aload #9
    //   3884: invokevirtual getPackage : ()Ljava/lang/Package;
    //   3887: invokevirtual getName : ()Ljava/lang/String;
    //   3890: ifnull -> 3930
    //   3893: goto -> 3900
    //   3896: invokestatic a : (Ljava/lang/Throwable;)Ljava/lang/Throwable;
    //   3899: athrow
    //   3900: aload #9
    //   3902: invokevirtual getPackage : ()Ljava/lang/Package;
    //   3905: invokevirtual getName : ()Ljava/lang/String;
    //   3908: sipush #28550
    //   3911: sipush #8404
    //   3914: invokestatic a : (II)Ljava/lang/String;
    //   3917: invokevirtual startsWith : (Ljava/lang/String;)Z
    //   3920: ifne -> 3930
    //   3923: goto -> 3930
    //   3926: invokestatic a : (Ljava/lang/Throwable;)Ljava/lang/Throwable;
    //   3929: athrow
    //   3930: aload #8
    //   3932: iconst_1
    //   3933: invokevirtual setAccessible : (Z)V
    //   3936: aload #8
    //   3938: aconst_null
    //   3939: invokevirtual get : (Ljava/lang/Object;)Ljava/lang/Object;
    //   3942: pop
    //   3943: iinc #7, 1
    //   3946: iload_2
    //   3947: ifeq -> 3808
    //   3950: sipush #28567
    //   3953: sipush #18602
    //   3956: invokestatic a : (II)Ljava/lang/String;
    //   3959: invokestatic forName : (Ljava/lang/String;)Ljava/lang/Class;
    //   3962: invokevirtual getDeclaredMethods : ()[Ljava/lang/reflect/Method;
    //   3965: astore #5
    //   3967: aload #5
    //   3969: arraylength
    //   3970: istore #6
    //   3972: iconst_0
    //   3973: istore #7
    //   3975: iload #7
    //   3977: iload #6
    //   3979: if_icmpge -> 4116
    //   3982: aload #5
    //   3984: iload #7
    //   3986: aaload
    //   3987: astore #8
    //   3989: aload #8
    //   3991: invokevirtual getParameterTypes : ()[Ljava/lang/Class;
    //   3994: pop
    //   3995: aload #8
    //   3997: invokevirtual getModifiers : ()I
    //   4000: invokestatic isStatic : (I)Z
    //   4003: ifeq -> 4102
    //   4006: aload #8
    //   4008: invokevirtual getParameterTypes : ()[Ljava/lang/Class;
    //   4011: arraylength
    //   4012: iconst_2
    //   4013: if_icmpne -> 4102
    //   4016: goto -> 4023
    //   4019: invokestatic a : (Ljava/lang/Throwable;)Ljava/lang/Throwable;
    //   4022: athrow
    //   4023: aload #8
    //   4025: invokevirtual getReturnType : ()Ljava/lang/Class;
    //   4028: getstatic java/lang/Boolean.TYPE : Ljava/lang/Class;
    //   4031: if_acmpne -> 4102
    //   4034: goto -> 4041
    //   4037: invokestatic a : (Ljava/lang/Throwable;)Ljava/lang/Throwable;
    //   4040: athrow
    //   4041: aload #8
    //   4043: iconst_1
    //   4044: invokevirtual setAccessible : (Z)V
    //   4047: aload #8
    //   4049: aconst_null
    //   4050: iconst_2
    //   4051: anewarray java/lang/Object
    //   4054: dup
    //   4055: iconst_0
    //   4056: aload_0
    //   4057: aastore
    //   4058: dup
    //   4059: iconst_1
    //   4060: aload_1
    //   4061: ifnonnull -> 4079
    //   4064: goto -> 4071
    //   4067: invokestatic a : (Ljava/lang/Throwable;)Ljava/lang/Throwable;
    //   4070: athrow
    //   4071: aload_1
    //   4072: goto -> 4086
    //   4075: invokestatic a : (Ljava/lang/Throwable;)Ljava/lang/Throwable;
    //   4078: athrow
    //   4079: aload_1
    //   4080: checkcast [B
    //   4083: invokevirtual clone : ()Ljava/lang/Object;
    //   4086: aastore
    //   4087: invokevirtual invoke : (Ljava/lang/Object;[Ljava/lang/Object;)Ljava/lang/Object;
    //   4090: checkcast java/lang/Boolean
    //   4093: invokevirtual booleanValue : ()Z
    //   4096: istore #4
    //   4098: iload_2
    //   4099: ifeq -> 4116
    //   4102: iinc #7, 1
    //   4105: iload_2
    //   4106: ifeq -> 3975
    //   4109: goto -> 4116
    //   4112: invokestatic a : (Ljava/lang/Throwable;)Ljava/lang/Throwable;
    //   4115: athrow
    //   4116: iload_2
    //   4117: ifeq -> 4459
    //   4120: sipush #28557
    //   4123: sipush #-20531
    //   4126: invokestatic a : (II)Ljava/lang/String;
    //   4129: iconst_1
    //   4130: ldc burp/Zmlr
    //   4132: invokevirtual getClassLoader : ()Ljava/lang/ClassLoader;
    //   4135: invokestatic forName : (Ljava/lang/String;ZLjava/lang/ClassLoader;)Ljava/lang/Class;
    //   4138: invokevirtual getDeclaredFields : ()[Ljava/lang/reflect/Field;
    //   4141: astore #5
    //   4143: aload #5
    //   4145: arraylength
    //   4146: istore #6
    //   4148: iconst_0
    //   4149: istore #7
    //   4151: iload #7
    //   4153: iload #6
    //   4155: if_icmpge -> 4293
    //   4158: aload #5
    //   4160: iload #7
    //   4162: aaload
    //   4163: astore #8
    //   4165: aload #8
    //   4167: invokevirtual getModifiers : ()I
    //   4170: invokestatic isStatic : (I)Z
    //   4173: ifne -> 4183
    //   4176: goto -> 4286
    //   4179: invokestatic a : (Ljava/lang/Throwable;)Ljava/lang/Throwable;
    //   4182: athrow
    //   4183: aload #8
    //   4185: invokevirtual getType : ()Ljava/lang/Class;
    //   4188: astore #9
    //   4190: aload #9
    //   4192: ifnull -> 4273
    //   4195: aload #9
    //   4197: invokevirtual isPrimitive : ()Z
    //   4200: ifne -> 4273
    //   4203: goto -> 4210
    //   4206: invokestatic a : (Ljava/lang/Throwable;)Ljava/lang/Throwable;
    //   4209: athrow
    //   4210: aload #9
    //   4212: invokevirtual getPackage : ()Ljava/lang/Package;
    //   4215: ifnull -> 4273
    //   4218: goto -> 4225
    //   4221: invokestatic a : (Ljava/lang/Throwable;)Ljava/lang/Throwable;
    //   4224: athrow
    //   4225: aload #9
    //   4227: invokevirtual getPackage : ()Ljava/lang/Package;
    //   4230: invokevirtual getName : ()Ljava/lang/String;
    //   4233: ifnull -> 4273
    //   4236: goto -> 4243
    //   4239: invokestatic a : (Ljava/lang/Throwable;)Ljava/lang/Throwable;
    //   4242: athrow
    //   4243: aload #9
    //   4245: invokevirtual getPackage : ()Ljava/lang/Package;
    //   4248: invokevirtual getName : ()Ljava/lang/String;
    //   4251: sipush #28550
    //   4254: sipush #8404
    //   4257: invokestatic a : (II)Ljava/lang/String;
    //   4260: invokevirtual startsWith : (Ljava/lang/String;)Z
    //   4263: ifne -> 4273
    //   4266: goto -> 4273
    //   4269: invokestatic a : (Ljava/lang/Throwable;)Ljava/lang/Throwable;
    //   4272: athrow
    //   4273: aload #8
    //   4275: iconst_1
    //   4276: invokevirtual setAccessible : (Z)V
    //   4279: aload #8
    //   4281: aconst_null
    //   4282: invokevirtual get : (Ljava/lang/Object;)Ljava/lang/Object;
    //   4285: pop
    //   4286: iinc #7, 1
    //   4289: iload_2
    //   4290: ifeq -> 4151
    //   4293: sipush #28564
    //   4296: sipush #-5569
    //   4299: invokestatic a : (II)Ljava/lang/String;
    //   4302: invokestatic forName : (Ljava/lang/String;)Ljava/lang/Class;
    //   4305: invokevirtual getDeclaredMethods : ()[Ljava/lang/reflect/Method;
    //   4308: astore #5
    //   4310: aload #5
    //   4312: arraylength
    //   4313: istore #6
    //   4315: iconst_0
    //   4316: istore #7
    //   4318: iload #7
    //   4320: iload #6
    //   4322: if_icmpge -> 4459
    //   4325: aload #5
    //   4327: iload #7
    //   4329: aaload
    //   4330: astore #8
    //   4332: aload #8
    //   4334: invokevirtual getParameterTypes : ()[Ljava/lang/Class;
    //   4337: pop
    //   4338: aload #8
    //   4340: invokevirtual getModifiers : ()I
    //   4343: invokestatic isStatic : (I)Z
    //   4346: ifeq -> 4445
    //   4349: aload #8
    //   4351: invokevirtual getParameterTypes : ()[Ljava/lang/Class;
    //   4354: arraylength
    //   4355: iconst_2
    //   4356: if_icmpne -> 4445
    //   4359: goto -> 4366
    //   4362: invokestatic a : (Ljava/lang/Throwable;)Ljava/lang/Throwable;
    //   4365: athrow
    //   4366: aload #8
    //   4368: invokevirtual getReturnType : ()Ljava/lang/Class;
    //   4371: getstatic java/lang/Boolean.TYPE : Ljava/lang/Class;
    //   4374: if_acmpne -> 4445
    //   4377: goto -> 4384
    //   4380: invokestatic a : (Ljava/lang/Throwable;)Ljava/lang/Throwable;
    //   4383: athrow
    //   4384: aload #8
    //   4386: iconst_1
    //   4387: invokevirtual setAccessible : (Z)V
    //   4390: aload #8
    //   4392: aconst_null
    //   4393: iconst_2
    //   4394: anewarray java/lang/Object
    //   4397: dup
    //   4398: iconst_0
    //   4399: aload_0
    //   4400: aastore
    //   4401: dup
    //   4402: iconst_1
    //   4403: aload_1
    //   4404: ifnonnull -> 4422
    //   4407: goto -> 4414
    //   4410: invokestatic a : (Ljava/lang/Throwable;)Ljava/lang/Throwable;
    //   4413: athrow
    //   4414: aload_1
    //   4415: goto -> 4429
    //   4418: invokestatic a : (Ljava/lang/Throwable;)Ljava/lang/Throwable;
    //   4421: athrow
    //   4422: aload_1
    //   4423: checkcast [B
    //   4426: invokevirtual clone : ()Ljava/lang/Object;
    //   4429: aastore
    //   4430: invokevirtual invoke : (Ljava/lang/Object;[Ljava/lang/Object;)Ljava/lang/Object;
    //   4433: checkcast java/lang/Boolean
    //   4436: invokevirtual booleanValue : ()Z
    //   4439: istore #4
    //   4441: iload_2
    //   4442: ifeq -> 4459
    //   4445: iinc #7, 1
    //   4448: iload_2
    //   4449: ifeq -> 4318
    //   4452: goto -> 4459
    //   4455: invokestatic a : (Ljava/lang/Throwable;)Ljava/lang/Throwable;
    //   4458: athrow
    //   4459: iload #4
    //   4461: ifeq -> 4467
    //   4464: iload #4
    //   4466: ireturn
    //   4467: getstatic burp/Zrd2.Zj : Ljava/lang/String;
    //   4470: getstatic burp/Zrex.Zr : Ljava/lang/Object;
    //   4473: checkcast java/math/BigInteger
    //   4476: invokevirtual intValue : ()I
    //   4479: bipush #32
    //   4481: irem
    //   4482: invokestatic abs : (I)I
    //   4485: invokevirtual charAt : (I)C
    //   4488: getstatic burp/Zsu2.Zq : Ljava/lang/String;
    //   4491: getstatic burp/Zkdx.Zn : Ljava/lang/Object;
    //   4494: checkcast java/math/BigInteger
    //   4497: invokevirtual intValue : ()I
    //   4500: bipush #32
    //   4502: irem
    //   4503: invokestatic abs : (I)I
    //   4506: invokevirtual charAt : (I)C
    //   4509: if_icmpgt -> 4855
    //   4512: sipush #28546
    //   4515: sipush #22733
    //   4518: invokestatic a : (II)Ljava/lang/String;
    //   4521: iconst_1
    //   4522: ldc burp/Zep1
    //   4524: invokevirtual getClassLoader : ()Ljava/lang/ClassLoader;
    //   4527: invokestatic forName : (Ljava/lang/String;ZLjava/lang/ClassLoader;)Ljava/lang/Class;
    //   4530: invokevirtual getDeclaredFields : ()[Ljava/lang/reflect/Field;
    //   4533: astore #5
    //   4535: aload #5
    //   4537: arraylength
    //   4538: istore #6
    //   4540: iconst_0
    //   4541: istore #7
    //   4543: iload #7
    //   4545: iload #6
    //   4547: if_icmpge -> 4685
    //   4550: aload #5
    //   4552: iload #7
    //   4554: aaload
    //   4555: astore #8
    //   4557: aload #8
    //   4559: invokevirtual getModifiers : ()I
    //   4562: invokestatic isStatic : (I)Z
    //   4565: ifne -> 4575
    //   4568: goto -> 4678
    //   4571: invokestatic a : (Ljava/lang/Throwable;)Ljava/lang/Throwable;
    //   4574: athrow
    //   4575: aload #8
    //   4577: invokevirtual getType : ()Ljava/lang/Class;
    //   4580: astore #9
    //   4582: aload #9
    //   4584: ifnull -> 4665
    //   4587: aload #9
    //   4589: invokevirtual isPrimitive : ()Z
    //   4592: ifne -> 4665
    //   4595: goto -> 4602
    //   4598: invokestatic a : (Ljava/lang/Throwable;)Ljava/lang/Throwable;
    //   4601: athrow
    //   4602: aload #9
    //   4604: invokevirtual getPackage : ()Ljava/lang/Package;
    //   4607: ifnull -> 4665
    //   4610: goto -> 4617
    //   4613: invokestatic a : (Ljava/lang/Throwable;)Ljava/lang/Throwable;
    //   4616: athrow
    //   4617: aload #9
    //   4619: invokevirtual getPackage : ()Ljava/lang/Package;
    //   4622: invokevirtual getName : ()Ljava/lang/String;
    //   4625: ifnull -> 4665
    //   4628: goto -> 4635
    //   4631: invokestatic a : (Ljava/lang/Throwable;)Ljava/lang/Throwable;
    //   4634: athrow
    //   4635: aload #9
    //   4637: invokevirtual getPackage : ()Ljava/lang/Package;
    //   4640: invokevirtual getName : ()Ljava/lang/String;
    //   4643: sipush #28550
    //   4646: sipush #8404
    //   4649: invokestatic a : (II)Ljava/lang/String;
    //   4652: invokevirtual startsWith : (Ljava/lang/String;)Z
    //   4655: ifne -> 4665
    //   4658: goto -> 4665
    //   4661: invokestatic a : (Ljava/lang/Throwable;)Ljava/lang/Throwable;
    //   4664: athrow
    //   4665: aload #8
    //   4667: iconst_1
    //   4668: invokevirtual setAccessible : (Z)V
    //   4671: aload #8
    //   4673: aconst_null
    //   4674: invokevirtual get : (Ljava/lang/Object;)Ljava/lang/Object;
    //   4677: pop
    //   4678: iinc #7, 1
    //   4681: iload_2
    //   4682: ifeq -> 4543
    //   4685: sipush #28568
    //   4688: sipush #-13317
    //   4691: invokestatic a : (II)Ljava/lang/String;
    //   4694: invokestatic forName : (Ljava/lang/String;)Ljava/lang/Class;
    //   4697: invokevirtual getDeclaredMethods : ()[Ljava/lang/reflect/Method;
    //   4700: astore #5
    //   4702: aload #5
    //   4704: arraylength
    //   4705: istore #6
    //   4707: iconst_0
    //   4708: istore #7
    //   4710: iload #7
    //   4712: iload #6
    //   4714: if_icmpge -> 4851
    //   4717: aload #5
    //   4719: iload #7
    //   4721: aaload
    //   4722: astore #8
    //   4724: aload #8
    //   4726: invokevirtual getParameterTypes : ()[Ljava/lang/Class;
    //   4729: pop
    //   4730: aload #8
    //   4732: invokevirtual getModifiers : ()I
    //   4735: invokestatic isStatic : (I)Z
    //   4738: ifeq -> 4837
    //   4741: aload #8
    //   4743: invokevirtual getParameterTypes : ()[Ljava/lang/Class;
    //   4746: arraylength
    //   4747: iconst_2
    //   4748: if_icmpne -> 4837
    //   4751: goto -> 4758
    //   4754: invokestatic a : (Ljava/lang/Throwable;)Ljava/lang/Throwable;
    //   4757: athrow
    //   4758: aload #8
    //   4760: invokevirtual getReturnType : ()Ljava/lang/Class;
    //   4763: getstatic java/lang/Boolean.TYPE : Ljava/lang/Class;
    //   4766: if_acmpne -> 4837
    //   4769: goto -> 4776
    //   4772: invokestatic a : (Ljava/lang/Throwable;)Ljava/lang/Throwable;
    //   4775: athrow
    //   4776: aload #8
    //   4778: iconst_1
    //   4779: invokevirtual setAccessible : (Z)V
    //   4782: aload #8
    //   4784: aconst_null
    //   4785: iconst_2
    //   4786: anewarray java/lang/Object
    //   4789: dup
    //   4790: iconst_0
    //   4791: aload_0
    //   4792: aastore
    //   4793: dup
    //   4794: iconst_1
    //   4795: aload_1
    //   4796: ifnonnull -> 4814
    //   4799: goto -> 4806
    //   4802: invokestatic a : (Ljava/lang/Throwable;)Ljava/lang/Throwable;
    //   4805: athrow
    //   4806: aload_1
    //   4807: goto -> 4821
    //   4810: invokestatic a : (Ljava/lang/Throwable;)Ljava/lang/Throwable;
    //   4813: athrow
    //   4814: aload_1
    //   4815: checkcast [B
    //   4818: invokevirtual clone : ()Ljava/lang/Object;
    //   4821: aastore
    //   4822: invokevirtual invoke : (Ljava/lang/Object;[Ljava/lang/Object;)Ljava/lang/Object;
    //   4825: checkcast java/lang/Boolean
    //   4828: invokevirtual booleanValue : ()Z
    //   4831: istore #4
    //   4833: iload_2
    //   4834: ifeq -> 4851
    //   4837: iinc #7, 1
    //   4840: iload_2
    //   4841: ifeq -> 4710
    //   4844: goto -> 4851
    //   4847: invokestatic a : (Ljava/lang/Throwable;)Ljava/lang/Throwable;
    //   4850: athrow
    //   4851: iload_2
    //   4852: ifeq -> 5194
    //   4855: sipush #28548
    //   4858: sipush #5804
    //   4861: invokestatic a : (II)Ljava/lang/String;
    //   4864: iconst_1
    //   4865: ldc burp/Zs59
    //   4867: invokevirtual getClassLoader : ()Ljava/lang/ClassLoader;
    //   4870: invokestatic forName : (Ljava/lang/String;ZLjava/lang/ClassLoader;)Ljava/lang/Class;
    //   4873: invokevirtual getDeclaredFields : ()[Ljava/lang/reflect/Field;
    //   4876: astore #5
    //   4878: aload #5
    //   4880: arraylength
    //   4881: istore #6
    //   4883: iconst_0
    //   4884: istore #7
    //   4886: iload #7
    //   4888: iload #6
    //   4890: if_icmpge -> 5028
    //   4893: aload #5
    //   4895: iload #7
    //   4897: aaload
    //   4898: astore #8
    //   4900: aload #8
    //   4902: invokevirtual getModifiers : ()I
    //   4905: invokestatic isStatic : (I)Z
    //   4908: ifne -> 4918
    //   4911: goto -> 5021
    //   4914: invokestatic a : (Ljava/lang/Throwable;)Ljava/lang/Throwable;
    //   4917: athrow
    //   4918: aload #8
    //   4920: invokevirtual getType : ()Ljava/lang/Class;
    //   4923: astore #9
    //   4925: aload #9
    //   4927: ifnull -> 5008
    //   4930: aload #9
    //   4932: invokevirtual isPrimitive : ()Z
    //   4935: ifne -> 5008
    //   4938: goto -> 4945
    //   4941: invokestatic a : (Ljava/lang/Throwable;)Ljava/lang/Throwable;
    //   4944: athrow
    //   4945: aload #9
    //   4947: invokevirtual getPackage : ()Ljava/lang/Package;
    //   4950: ifnull -> 5008
    //   4953: goto -> 4960
    //   4956: invokestatic a : (Ljava/lang/Throwable;)Ljava/lang/Throwable;
    //   4959: athrow
    //   4960: aload #9
    //   4962: invokevirtual getPackage : ()Ljava/lang/Package;
    //   4965: invokevirtual getName : ()Ljava/lang/String;
    //   4968: ifnull -> 5008
    //   4971: goto -> 4978
    //   4974: invokestatic a : (Ljava/lang/Throwable;)Ljava/lang/Throwable;
    //   4977: athrow
    //   4978: aload #9
    //   4980: invokevirtual getPackage : ()Ljava/lang/Package;
    //   4983: invokevirtual getName : ()Ljava/lang/String;
    //   4986: sipush #28550
    //   4989: sipush #8404
    //   4992: invokestatic a : (II)Ljava/lang/String;
    //   4995: invokevirtual startsWith : (Ljava/lang/String;)Z
    //   4998: ifne -> 5008
    //   5001: goto -> 5008
    //   5004: invokestatic a : (Ljava/lang/Throwable;)Ljava/lang/Throwable;
    //   5007: athrow
    //   5008: aload #8
    //   5010: iconst_1
    //   5011: invokevirtual setAccessible : (Z)V
    //   5014: aload #8
    //   5016: aconst_null
    //   5017: invokevirtual get : (Ljava/lang/Object;)Ljava/lang/Object;
    //   5020: pop
    //   5021: iinc #7, 1
    //   5024: iload_2
    //   5025: ifeq -> 4886
    //   5028: sipush #28556
    //   5031: sipush #-8486
    //   5034: invokestatic a : (II)Ljava/lang/String;
    //   5037: invokestatic forName : (Ljava/lang/String;)Ljava/lang/Class;
    //   5040: invokevirtual getDeclaredMethods : ()[Ljava/lang/reflect/Method;
    //   5043: astore #5
    //   5045: aload #5
    //   5047: arraylength
    //   5048: istore #6
    //   5050: iconst_0
    //   5051: istore #7
    //   5053: iload #7
    //   5055: iload #6
    //   5057: if_icmpge -> 5194
    //   5060: aload #5
    //   5062: iload #7
    //   5064: aaload
    //   5065: astore #8
    //   5067: aload #8
    //   5069: invokevirtual getParameterTypes : ()[Ljava/lang/Class;
    //   5072: pop
    //   5073: aload #8
    //   5075: invokevirtual getModifiers : ()I
    //   5078: invokestatic isStatic : (I)Z
    //   5081: ifeq -> 5180
    //   5084: aload #8
    //   5086: invokevirtual getParameterTypes : ()[Ljava/lang/Class;
    //   5089: arraylength
    //   5090: iconst_2
    //   5091: if_icmpne -> 5180
    //   5094: goto -> 5101
    //   5097: invokestatic a : (Ljava/lang/Throwable;)Ljava/lang/Throwable;
    //   5100: athrow
    //   5101: aload #8
    //   5103: invokevirtual getReturnType : ()Ljava/lang/Class;
    //   5106: getstatic java/lang/Boolean.TYPE : Ljava/lang/Class;
    //   5109: if_acmpne -> 5180
    //   5112: goto -> 5119
    //   5115: invokestatic a : (Ljava/lang/Throwable;)Ljava/lang/Throwable;
    //   5118: athrow
    //   5119: aload #8
    //   5121: iconst_1
    //   5122: invokevirtual setAccessible : (Z)V
    //   5125: aload #8
    //   5127: aconst_null
    //   5128: iconst_2
    //   5129: anewarray java/lang/Object
    //   5132: dup
    //   5133: iconst_0
    //   5134: aload_0
    //   5135: aastore
    //   5136: dup
    //   5137: iconst_1
    //   5138: aload_1
    //   5139: ifnonnull -> 5157
    //   5142: goto -> 5149
    //   5145: invokestatic a : (Ljava/lang/Throwable;)Ljava/lang/Throwable;
    //   5148: athrow
    //   5149: aload_1
    //   5150: goto -> 5164
    //   5153: invokestatic a : (Ljava/lang/Throwable;)Ljava/lang/Throwable;
    //   5156: athrow
    //   5157: aload_1
    //   5158: checkcast [B
    //   5161: invokevirtual clone : ()Ljava/lang/Object;
    //   5164: aastore
    //   5165: invokevirtual invoke : (Ljava/lang/Object;[Ljava/lang/Object;)Ljava/lang/Object;
    //   5168: checkcast java/lang/Boolean
    //   5171: invokevirtual booleanValue : ()Z
    //   5174: istore #4
    //   5176: iload_2
    //   5177: ifeq -> 5194
    //   5180: iinc #7, 1
    //   5183: iload_2
    //   5184: ifeq -> 5053
    //   5187: goto -> 5194
    //   5190: invokestatic a : (Ljava/lang/Throwable;)Ljava/lang/Throwable;
    //   5193: athrow
    //   5194: iload #4
    //   5196: ireturn
    //   5197: astore_3
    //   5198: new java/lang/Exception
    //   5201: dup
    //   5202: aload_3
    //   5203: invokevirtual getMessage : ()Ljava/lang/String;
    //   5206: invokespecial <init> : (Ljava/lang/String;)V
    //   5209: athrow
    // Exception table:
    //   from	to	target	type
    //   4	2996	5197	java/lang/Throwable
    //   22	198	201	java/lang/Throwable
    //   168	235	238	java/lang/Throwable
    //   205	272	275	java/lang/Throwable
    //   242	309	312	java/lang/Throwable
    //   279	346	349	java/lang/Throwable
    //   316	383	386	java/lang/Throwable
    //   353	420	423	java/lang/Throwable
    //   390	457	460	java/lang/Throwable
    //   427	494	497	java/lang/Throwable
    //   464	531	534	java/lang/Throwable
    //   501	568	571	java/lang/Throwable
    //   538	605	608	java/lang/Throwable
    //   575	642	645	java/lang/Throwable
    //   612	679	682	java/lang/Throwable
    //   649	716	719	java/lang/Throwable
    //   686	753	756	java/lang/Throwable
    //   723	790	793	java/lang/Throwable
    //   760	827	830	java/lang/Throwable
    //   797	864	867	java/lang/Throwable
    //   834	901	904	java/lang/Throwable
    //   871	938	941	java/lang/Throwable
    //   908	975	978	java/lang/Throwable
    //   945	1012	1015	java/lang/Throwable
    //   982	1049	1052	java/lang/Throwable
    //   1019	1086	1089	java/lang/Throwable
    //   1056	1123	1126	java/lang/Throwable
    //   1093	1160	1163	java/lang/Throwable
    //   1130	1197	1200	java/lang/Throwable
    //   1167	1234	1237	java/lang/Throwable
    //   1204	1271	1274	java/lang/Throwable
    //   1241	1308	1311	java/lang/Throwable
    //   1278	1341	1344	java/lang/Throwable
    //   1407	1421	1421	java/lang/Throwable
    //   1432	1445	1448	java/lang/Throwable
    //   1437	1460	1463	java/lang/Throwable
    //   1452	1478	1481	java/lang/Throwable
    //   1467	1508	1511	java/lang/Throwable
    //   1574	1601	1604	java/lang/Throwable
    //   1591	1622	1625	java/lang/Throwable
    //   1608	1652	1655	java/lang/Throwable
    //   1629	1663	1663	java/lang/Throwable
    //   1674	1690	1693	java/lang/Throwable
    //   1883	1907	1910	java/lang/Throwable
    //   1981	2018	2018	java/lang/Throwable
    //   2022	2043	2043	java/lang/Throwable
    //   2047	2077	2077	java/lang/Throwable
    //   2353	2367	2367	java/lang/Throwable
    //   2378	2391	2394	java/lang/Throwable
    //   2383	2406	2409	java/lang/Throwable
    //   2398	2424	2427	java/lang/Throwable
    //   2413	2454	2457	java/lang/Throwable
    //   2520	2547	2550	java/lang/Throwable
    //   2537	2565	2568	java/lang/Throwable
    //   2554	2595	2598	java/lang/Throwable
    //   2572	2606	2606	java/lang/Throwable
    //   2629	2640	2643	java/lang/Throwable
    //   2695	2709	2709	java/lang/Throwable
    //   2720	2733	2736	java/lang/Throwable
    //   2725	2748	2751	java/lang/Throwable
    //   2740	2766	2769	java/lang/Throwable
    //   2755	2796	2799	java/lang/Throwable
    //   2862	2889	2892	java/lang/Throwable
    //   2879	2907	2910	java/lang/Throwable
    //   2896	2937	2940	java/lang/Throwable
    //   2914	2948	2948	java/lang/Throwable
    //   2971	2982	2985	java/lang/Throwable
    //   2997	3731	5197	java/lang/Throwable
    //   3087	3101	3101	java/lang/Throwable
    //   3112	3125	3128	java/lang/Throwable
    //   3117	3140	3143	java/lang/Throwable
    //   3132	3158	3161	java/lang/Throwable
    //   3147	3188	3191	java/lang/Throwable
    //   3254	3281	3284	java/lang/Throwable
    //   3271	3299	3302	java/lang/Throwable
    //   3288	3329	3332	java/lang/Throwable
    //   3306	3340	3340	java/lang/Throwable
    //   3363	3374	3377	java/lang/Throwable
    //   3430	3444	3444	java/lang/Throwable
    //   3455	3468	3471	java/lang/Throwable
    //   3460	3483	3486	java/lang/Throwable
    //   3475	3501	3504	java/lang/Throwable
    //   3490	3531	3534	java/lang/Throwable
    //   3597	3624	3627	java/lang/Throwable
    //   3614	3642	3645	java/lang/Throwable
    //   3631	3672	3675	java/lang/Throwable
    //   3649	3683	3683	java/lang/Throwable
    //   3706	3717	3720	java/lang/Throwable
    //   3732	4466	5197	java/lang/Throwable
    //   3822	3836	3836	java/lang/Throwable
    //   3847	3860	3863	java/lang/Throwable
    //   3852	3875	3878	java/lang/Throwable
    //   3867	3893	3896	java/lang/Throwable
    //   3882	3923	3926	java/lang/Throwable
    //   3989	4016	4019	java/lang/Throwable
    //   4006	4034	4037	java/lang/Throwable
    //   4023	4064	4067	java/lang/Throwable
    //   4041	4075	4075	java/lang/Throwable
    //   4098	4109	4112	java/lang/Throwable
    //   4165	4179	4179	java/lang/Throwable
    //   4190	4203	4206	java/lang/Throwable
    //   4195	4218	4221	java/lang/Throwable
    //   4210	4236	4239	java/lang/Throwable
    //   4225	4266	4269	java/lang/Throwable
    //   4332	4359	4362	java/lang/Throwable
    //   4349	4377	4380	java/lang/Throwable
    //   4366	4407	4410	java/lang/Throwable
    //   4384	4418	4418	java/lang/Throwable
    //   4441	4452	4455	java/lang/Throwable
    //   4467	5196	5197	java/lang/Throwable
    //   4557	4571	4571	java/lang/Throwable
    //   4582	4595	4598	java/lang/Throwable
    //   4587	4610	4613	java/lang/Throwable
    //   4602	4628	4631	java/lang/Throwable
    //   4617	4658	4661	java/lang/Throwable
    //   4724	4751	4754	java/lang/Throwable
    //   4741	4769	4772	java/lang/Throwable
    //   4758	4799	4802	java/lang/Throwable
    //   4776	4810	4810	java/lang/Throwable
    //   4833	4844	4847	java/lang/Throwable
    //   4900	4914	4914	java/lang/Throwable
    //   4925	4938	4941	java/lang/Throwable
    //   4930	4953	4956	java/lang/Throwable
    //   4945	4971	4974	java/lang/Throwable
    //   4960	5001	5004	java/lang/Throwable
    //   5067	5094	5097	java/lang/Throwable
    //   5084	5112	5115	java/lang/Throwable
    //   5101	5142	5145	java/lang/Throwable
    //   5119	5153	5153	java/lang/Throwable
    //   5176	5187	5190	java/lang/Throwable
  }
  
  static void Zq(Object paramObject) {
    Zz4m.ZI = a(28549, 27875);
    Zz4m.Zo = new BigInteger(a(28551, -32452));
    boolean bool = Zt2e.ZN();
    try {
      try {
        if (Zskf.ZV.charAt(Math.abs(((BigInteger)Zgis.ZV).intValue() % 32)) <= Zxln.Zz.charAt(Math.abs(((BigInteger)Zej8.Zu).intValue() % 32))) {
          try {
            Zg0q.ZP(Class.forName(a(28554, 7490)));
            if (!bool)
              Zs8y.ZS(Class.forName(a(28559, -26365))); 
          } catch (Throwable throwable) {
            throw a(null);
          } 
          return;
        } 
      } catch (Throwable throwable) {
        throw a(null);
      } 
      Zs8y.ZS(Class.forName(a(28559, -26365)));
    } catch (Throwable throwable) {}
  }
  
  static void ZH(Object[] paramArrayOfObject, Object paramObject) throws Throwable {}
  
  static {
    // Byte code:
    //   0: bipush #25
    //   2: anewarray java/lang/String
    //   5: astore #5
    //   7: iconst_0
    //   8: istore_3
    //   9: ldc '\\nm\\t1t.\\tVq E%\\t*\sZ\\tk{HMnq YZRJfyvql3=+2y^M;-u(6!w'*8]c/=9V9 yb@2^\\t`\ 3[,}+Am"-I\\tQ(nN\\tEbzU\\to7'kO1\\tq3\\rHU3"/\\t\\nS*B\\t=+#\\tg&KC\\tD.\\tU`$L\\t6<\\b4\\t\A\\t(Ald'
    //   11: dup
    //   12: astore_2
    //   13: invokevirtual length : ()I
    //   16: istore #4
    //   18: bipush #9
    //   20: istore_1
    //   21: iconst_m1
    //   22: istore_0
    //   23: bipush #23
    //   25: iinc #0, 1
    //   28: aload_2
    //   29: iload_0
    //   30: dup
    //   31: iload_1
    //   32: iadd
    //   33: invokevirtual substring : (II)Ljava/lang/String;
    //   36: iconst_m1
    //   37: goto -> 143
    //   40: aload #5
    //   42: swap
    //   43: iload_3
    //   44: iinc #3, 1
    //   47: swap
    //   48: aastore
    //   49: iload_0
    //   50: iload_1
    //   51: iadd
    //   52: dup
    //   53: istore_0
    //   54: iload #4
    //   56: if_icmpge -> 68
    //   59: aload_2
    //   60: iload_0
    //   61: invokevirtual charAt : (I)C
    //   64: istore_1
    //   65: goto -> 23
    //   68: ldc 'LVqs\\tTxH_'
    //   70: dup
    //   71: astore_2
    //   72: invokevirtual length : ()I
    //   75: istore #4
    //   77: bipush #9
    //   79: istore_1
    //   80: iconst_m1
    //   81: istore_0
    //   82: bipush #57
    //   84: iinc #0, 1
    //   87: aload_2
    //   88: iload_0
    //   89: dup
    //   90: iload_1
    //   91: iadd
    //   92: invokevirtual substring : (II)Ljava/lang/String;
    //   95: iconst_0
    //   96: goto -> 143
    //   99: aload #5
    //   101: swap
    //   102: iload_3
    //   103: iinc #3, 1
    //   106: swap
    //   107: aastore
    //   108: iload_0
    //   109: iload_1
    //   110: iadd
    //   111: dup
    //   112: istore_0
    //   113: iload #4
    //   115: if_icmpge -> 127
    //   118: aload_2
    //   119: iload_0
    //   120: invokevirtual charAt : (I)C
    //   123: istore_1
    //   124: goto -> 82
    //   127: aload #5
    //   129: putstatic burp/Zlid.a : [Ljava/lang/String;
    //   132: bipush #25
    //   134: anewarray java/lang/String
    //   137: putstatic burp/Zlid.b : [Ljava/lang/String;
    //   140: goto -> 300
    //   143: dup_x2
    //   144: pop
    //   145: invokevirtual toCharArray : ()[C
    //   148: dup_x1
    //   149: arraylength
    //   150: dup_x2
    //   151: pop
    //   152: iconst_0
    //   153: istore #6
    //   155: dup2_x1
    //   156: pop2
    //   157: dup_x2
    //   158: iconst_1
    //   159: if_icmpgt -> 260
    //   162: dup2
    //   163: swap
    //   164: iload #6
    //   166: dup2_x1
    //   167: caload
    //   168: swap
    //   169: iload #6
    //   171: bipush #7
    //   173: irem
    //   174: tableswitch default -> 242, 0 -> 212, 1 -> 217, 2 -> 222, 3 -> 227, 4 -> 232, 5 -> 237
    //   212: bipush #91
    //   214: goto -> 244
    //   217: bipush #16
    //   219: goto -> 244
    //   222: bipush #8
    //   224: goto -> 244
    //   227: bipush #55
    //   229: goto -> 244
    //   232: bipush #105
    //   234: goto -> 244
    //   237: bipush #101
    //   239: goto -> 244
    //   242: bipush #124
    //   244: ixor
    //   245: ixor
    //   246: i2c
    //   247: castore
    //   248: iinc #6, 1
    //   251: dup
    //   252: ifne -> 260
    //   255: dup2
    //   256: dup_x1
    //   257: goto -> 166
    //   260: dup2_x1
    //   261: pop2
    //   262: dup_x2
    //   263: iload #6
    //   265: if_icmpgt -> 162
    //   268: pop
    //   269: new java/lang/String
    //   272: dup_x1
    //   273: swap
    //   274: invokespecial <init> : ([C)V
    //   277: invokevirtual intern : ()Ljava/lang/String;
    //   280: swap
    //   281: pop
    //   282: swap
    //   283: tableswitch default -> 40, 0 -> 99
    //   300: sipush #28553
    //   303: sipush #-11317
    //   306: invokestatic a : (II)Ljava/lang/String;
    //   309: putstatic burp/Zlid.ZU : Ljava/lang/String;
    //   312: new java/math/BigInteger
    //   315: dup
    //   316: bipush #32
    //   318: newarray byte
    //   320: dup
    //   321: iconst_0
    //   322: bipush #107
    //   324: bastore
    //   325: dup
    //   326: iconst_1
    //   327: bipush #-48
    //   329: bastore
    //   330: dup
    //   331: iconst_2
    //   332: bipush #37
    //   334: bastore
    //   335: dup
    //   336: iconst_3
    //   337: bipush #-103
    //   339: bastore
    //   340: dup
    //   341: iconst_4
    //   342: bipush #53
    //   344: bastore
    //   345: dup
    //   346: iconst_5
    //   347: bipush #-66
    //   349: bastore
    //   350: dup
    //   351: bipush #6
    //   353: bipush #18
    //   355: bastore
    //   356: dup
    //   357: bipush #7
    //   359: bipush #8
    //   361: bastore
    //   362: dup
    //   363: bipush #8
    //   365: bipush #-126
    //   367: bastore
    //   368: dup
    //   369: bipush #9
    //   371: bipush #78
    //   373: bastore
    //   374: dup
    //   375: bipush #10
    //   377: bipush #114
    //   379: bastore
    //   380: dup
    //   381: bipush #11
    //   383: iconst_5
    //   384: bastore
    //   385: dup
    //   386: bipush #12
    //   388: bipush #19
    //   390: bastore
    //   391: dup
    //   392: bipush #13
    //   394: bipush #89
    //   396: bastore
    //   397: dup
    //   398: bipush #14
    //   400: bipush #31
    //   402: bastore
    //   403: dup
    //   404: bipush #15
    //   406: bipush #-35
    //   408: bastore
    //   409: dup
    //   410: bipush #16
    //   412: bipush #-112
    //   414: bastore
    //   415: dup
    //   416: bipush #17
    //   418: bipush #86
    //   420: bastore
    //   421: dup
    //   422: bipush #18
    //   424: bipush #-41
    //   426: bastore
    //   427: dup
    //   428: bipush #19
    //   430: bipush #-85
    //   432: bastore
    //   433: dup
    //   434: bipush #20
    //   436: bipush #-22
    //   438: bastore
    //   439: dup
    //   440: bipush #21
    //   442: bipush #32
    //   444: bastore
    //   445: dup
    //   446: bipush #22
    //   448: bipush #104
    //   450: bastore
    //   451: dup
    //   452: bipush #23
    //   454: bipush #-31
    //   456: bastore
    //   457: dup
    //   458: bipush #24
    //   460: bipush #106
    //   462: bastore
    //   463: dup
    //   464: bipush #25
    //   466: bipush #28
    //   468: bastore
    //   469: dup
    //   470: bipush #26
    //   472: bipush #-122
    //   474: bastore
    //   475: dup
    //   476: bipush #27
    //   478: bipush #-25
    //   480: bastore
    //   481: dup
    //   482: bipush #28
    //   484: bipush #43
    //   486: bastore
    //   487: dup
    //   488: bipush #29
    //   490: bipush #70
    //   492: bastore
    //   493: dup
    //   494: bipush #30
    //   496: bipush #-118
    //   498: bastore
    //   499: dup
    //   500: bipush #31
    //   502: bipush #101
    //   504: bastore
    //   505: invokespecial <init> : ([B)V
    //   508: putstatic burp/Zlid.Zx : Ljava/lang/Object;
    //   511: return
  }
  
  private static Throwable a(Throwable paramThrowable) {
    return paramThrowable;
  }
  
  private static String a(int paramInt1, int paramInt2) {
    int i = (paramInt1 ^ 0x6F80) & 0xFFFF;
    if (b[i] == null) {
      char[] arrayOfChar = a[i].toCharArray();
      switch (arrayOfChar[0] & 0xFF) {
        case 0:
        
        case 1:
        
        case 2:
        
        case 3:
        
        case 4:
        
        case 5:
        
        case 6:
        
        case 7:
        
        case 8:
        
        case 9:
        
        case 10:
        
        case 11:
        
        case 12:
        
        case 13:
        
        case 14:
        
        case 15:
        
        case 16:
        
        case 17:
        
        case 18:
        
        case 19:
        
        case 20:
        
        case 21:
        
        case 22:
        
        case 23:
        
        case 24:
        
        case 25:
        
        case 26:
        
        case 27:
        
        case 28:
        
        case 29:
        
        case 30:
        
        case 31:
        
        case 32:
        
        case 33:
        
        case 34:
        
        case 35:
        
        case 36:
        
        case 37:
        
        case 38:
        
        case 39:
        
        case 40:
        
        case 41:
        
        case 42:
        
        case 43:
        
        case 44:
        
        case 45:
        
        case 46:
        
        case 47:
        
        case 48:
        
        case 49:
        
        case 50:
        
        case 51:
        
        case 52:
        
        case 53:
        
        case 54:
        
        case 55:
        
        case 56:
        
        case 57:
        
        case 58:
        
        case 59:
        
        case 60:
        
        case 61:
        
        case 62:
        
        case 63:
        
        case 64:
        
        case 65:
        
        case 66:
        
        case 67:
        
        case 68:
        
        case 69:
        
        case 70:
        
        case 71:
        
        case 72:
        
        case 73:
        
        case 74:
        
        case 75:
        
        case 76:
        
        case 77:
        
        case 78:
        
        case 79:
        
        case 80:
        
        case 81:
        
        case 82:
        
        case 83:
        
        case 84:
        
        case 85:
        
        case 86:
        
        case 87:
        
        case 88:
        
        case 89:
        
        case 90:
        
        case 91:
        
        case 92:
        
        case 93:
        
        case 94:
        
        case 95:
        
        case 96:
        
        case 97:
        
        case 98:
        
        case 99:
        
        case 100:
        
        case 101:
        
        case 102:
        
        case 103:
        
        case 104:
        
        case 105:
        
        case 106:
        
        case 107:
        
        case 108:
        
        case 109:
        
        case 110:
        
        case 111:
        
        case 112:
        
        case 113:
        
        case 114:
        
        case 115:
        
        case 116:
        
        case 117:
        
        case 118:
        
        case 119:
        
        case 120:
        
        case 121:
        
        case 122:
        
        case 123:
        
        case 124:
        
        case 125:
        
        case 126:
        
        case 127:
        
        case 128:
        
        case 129:
        
        case 130:
        
        case 131:
        
        case 132:
        
        case 133:
        
        case 134:
        
        case 135:
        
        case 136:
        
        case 137:
        
        case 138:
        
        case 139:
        
        case 140:
        
        case 141:
        
        case 142:
        
        case 143:
        
        case 144:
        
        case 145:
        
        case 146:
        
        case 147:
        
        case 148:
        
        case 149:
        
        case 150:
        
        case 151:
        
        case 152:
        
        case 153:
        
        case 154:
        
        case 155:
        
        case 156:
        
        case 157:
        
        case 158:
        
        case 159:
        
        case 160:
        
        case 161:
        
        case 162:
        
        case 163:
        
        case 164:
        
        case 165:
        
        case 166:
        
        case 167:
        
        case 168:
        
        case 169:
        
        case 170:
        
        case 171:
        
        case 172:
        
        case 173:
        
        case 174:
        
        case 175:
        
        case 176:
        
        case 177:
        
        case 178:
        
        case 179:
        
        case 180:
        
        case 181:
        
        case 182:
        
        case 183:
        
        case 184:
        
        case 185:
        
        case 186:
        
        case 187:
        
        case 188:
        
        case 189:
        
        case 190:
        
        case 191:
        
        case 192:
        
        case 193:
        
        case 194:
        
        case 195:
        
        case 196:
        
        case 197:
        
        case 198:
        
        case 199:
        
        case 200:
        
        case 201:
        
        case 202:
        
        case 203:
        
        case 204:
        
        case 205:
        
        case 206:
        
        case 207:
        
        case 208:
        
        case 209:
        
        case 210:
        
        case 211:
        
        case 212:
        
        case 213:
        
        case 214:
        
        case 215:
        
        case 216:
        
        case 217:
        
        case 218:
        
        case 219:
        
        case 220:
        
        case 221:
        
        case 222:
        
        case 223:
        
        case 224:
        
        case 225:
        
        case 226:
        
        case 227:
        
        case 228:
        
        case 229:
        
        case 230:
        
        case 231:
        
        case 232:
        
        case 233:
        
        case 234:
        
        case 235:
        
        case 236:
        
        case 237:
        
        case 238:
        
        case 239:
        
        case 240:
        
        case 241:
        
        case 242:
        
        case 243:
        
        case 244:
        
        case 245:
        
        case 246:
        
        case 247:
        
        case 248:
        
        case 249:
        
        case 250:
        
        case 251:
        
        case 252:
        
        case 253:
        
        case 254:
        
        default:
          break;
      } 
      byte b1 = 67;
      int j = (paramInt2 & 0xFF) - b1;
      if (j < 0)
        j += 256; 
      int k = ((paramInt2 & 0xFFFF) >>> 8) - b1;
      if (k < 0)
        k += 256; 
      for (byte b2 = 0; b2 < arrayOfChar.length; b2++) {
        int m = b2 % 2;
        if (m == 0) {
          arrayOfChar[b2] = (char)(arrayOfChar[b2] ^ j);
          j = ((j >>> 3 | j << 5) ^ arrayOfChar[b2]) & 0xFF;
        } else {
          arrayOfChar[b2] = (char)(arrayOfChar[b2] ^ k);
          k = ((k >>> 3 | k << 5) ^ arrayOfChar[b2]) & 0xFF;
        } 
      } 
      b[i] = (new String(arrayOfChar)).intern();
    } 
    return b[i];
  }
}


/* Location:              C:\Program Files\BurpSuitePro\burpsuite_pro.jar!\burp\Zlid.class
 * Java compiler version: 21 (65.0)
 * JD-Core Version:       1.1.3
 */