package burp;

public class Zlk {
  private static final Ztt4 ZI;
  
  private final Zg1n Zg;
  
  private final Zlhe ZJ;
  
  private final Zl3v Zw;
  
  private static final String a;
  
  public Zlk(Zg1n paramZg1n, Zlhe paramZlhe, Zl3v paramZl3v) {
    this.Zg = paramZg1n;
    this.ZJ = paramZlhe;
    this.Zw = paramZl3v;
  }
  
  public Zg4u ZX(Zgp8 paramZgp8) {
    // Byte code:
    //   0: invokestatic Zp : ()[Lburp/Zbqc;
    //   3: new java/util/ArrayList
    //   6: dup
    //   7: invokespecial <init> : ()V
    //   10: astore_3
    //   11: aload_1
    //   12: invokeinterface Zt : ()I
    //   17: invokestatic newFixedThreadPool : (I)Ljava/util/concurrent/ExecutorService;
    //   20: astore #4
    //   22: astore_2
    //   23: aload_1
    //   24: invokeinterface ZF : ()Ljava/util/List;
    //   29: invokeinterface isEmpty : ()Z
    //   34: ifne -> 221
    //   37: new burp/Ztwa
    //   40: dup
    //   41: aload_1
    //   42: invokeinterface Zb : ()Lburp/Ztog;
    //   47: aload_1
    //   48: invokeinterface ZF : ()Ljava/util/List;
    //   53: aload_1
    //   54: invokeinterface ZR : ()Lburp/Ztog;
    //   59: aload_1
    //   60: invokeinterface Zz : ()Lburp/Zl9f;
    //   65: aload_1
    //   66: invokeinterface ZW : ()Ljava/util/Collection;
    //   71: aload_1
    //   72: invokeinterface Zc : ()I
    //   77: aload_1
    //   78: invokeinterface ZM : ()I
    //   83: invokespecial <init> : (Lburp/Ztog;Ljava/util/List;Lburp/Ztog;Lburp/Zl9f;Ljava/util/Collection;II)V
    //   86: astore #5
    //   88: new burp/Zzd8
    //   91: dup
    //   92: aload_0
    //   93: getfield ZJ : Lburp/Zlhe;
    //   96: aload #5
    //   98: aload_0
    //   99: getfield Zw : Lburp/Zl3v;
    //   102: invokespecial <init> : (Lburp/Zlhe;Lburp/Ztwa;Lburp/Zl3v;)V
    //   105: astore #6
    //   107: aload_1
    //   108: invokeinterface Zv : ()Ljava/util/Collection;
    //   113: invokeinterface iterator : ()Ljava/util/Iterator;
    //   118: astore #7
    //   120: aload #7
    //   122: invokeinterface hasNext : ()Z
    //   127: ifeq -> 217
    //   130: aload #7
    //   132: invokeinterface next : ()Ljava/lang/Object;
    //   137: checkcast java/net/InetAddress
    //   140: astore #8
    //   142: aload_1
    //   143: invokeinterface Zy : ()Ljava/util/Collection;
    //   148: invokeinterface iterator : ()Ljava/util/Iterator;
    //   153: astore #9
    //   155: aload #9
    //   157: invokeinterface hasNext : ()Z
    //   162: ifeq -> 213
    //   165: aload #9
    //   167: invokeinterface next : ()Ljava/lang/Object;
    //   172: checkcast java/lang/Integer
    //   175: astore #10
    //   177: aload_3
    //   178: new burp/Zleh
    //   181: dup
    //   182: aload #4
    //   184: aload #10
    //   186: invokevirtual intValue : ()I
    //   189: aload #6
    //   191: aload #8
    //   193: invokespecial <init> : (Ljava/util/concurrent/ExecutorService;ILburp/Zzd8;Ljava/net/InetAddress;)V
    //   196: invokeinterface add : (Ljava/lang/Object;)Z
    //   201: pop
    //   202: aload_2
    //   203: ifnull -> 155
    //   206: iconst_5
    //   207: anewarray burp/Zbqc
    //   210: invokestatic Zr : ([Lburp/Zbqc;)V
    //   213: aload_2
    //   214: ifnull -> 120
    //   217: aload_2
    //   218: ifnull -> 232
    //   221: getstatic burp/Zlk.ZI : Lburp/Ztt4;
    //   224: getstatic burp/Zlk.a : Ljava/lang/String;
    //   227: invokeinterface ZJ : (Ljava/lang/String;)V
    //   232: aload_1
    //   233: invokeinterface ZI : ()Lburp/Zreh;
    //   238: invokestatic ZA : (Lburp/Zreh;)Lburp/Zg6d;
    //   241: astore #5
    //   243: aload_1
    //   244: invokeinterface Zi : ()Lburp/Zreh;
    //   249: invokestatic ZA : (Lburp/Zreh;)Lburp/Zg6d;
    //   252: astore #6
    //   254: new burp/Zzkb
    //   257: dup
    //   258: aload #5
    //   260: invokespecial <init> : (Lburp/Zg6d;)V
    //   263: astore #7
    //   265: new burp/Zx5k
    //   268: dup
    //   269: aload #7
    //   271: invokespecial <init> : (Lburp/Zzkb;)V
    //   274: astore #8
    //   276: aload_0
    //   277: getfield Zg : Lburp/Zg1n;
    //   280: aload_1
    //   281: invokeinterface Zw : ()Lburp/Zzsi;
    //   286: invokeinterface ZP : (Lburp/Zzsi;)Lburp/Zg73;
    //   291: astore #9
    //   293: new burp/Zko_
    //   296: dup
    //   297: aload #9
    //   299: getfield Zi : Lburp/Zxo0;
    //   302: aload_0
    //   303: getfield Zw : Lburp/Zl3v;
    //   306: aload_1
    //   307: invokeinterface Zn : ()Lburp/Zs_b;
    //   312: invokevirtual ZA : ()J
    //   315: invokespecial <init> : (Lburp/Zxo0;Lburp/Zl3v;J)V
    //   318: astore #10
    //   320: new burp/Zko_
    //   323: dup
    //   324: aload #9
    //   326: getfield Zi : Lburp/Zxo0;
    //   329: aload_0
    //   330: getfield Zw : Lburp/Zl3v;
    //   333: aload_1
    //   334: invokeinterface Zn : ()Lburp/Zs_b;
    //   339: invokevirtual ZA : ()J
    //   342: invokespecial <init> : (Lburp/Zxo0;Lburp/Zl3v;J)V
    //   345: astore #11
    //   347: aload_1
    //   348: invokeinterface Ze : ()Ljava/util/Collection;
    //   353: invokeinterface iterator : ()Ljava/util/Iterator;
    //   358: astore #12
    //   360: aload #12
    //   362: invokeinterface hasNext : ()Z
    //   367: ifeq -> 738
    //   370: aload #12
    //   372: invokeinterface next : ()Ljava/lang/Object;
    //   377: checkcast java/net/InetAddress
    //   380: astore #13
    //   382: aload_1
    //   383: invokeinterface ZY : ()Ljava/util/Collection;
    //   388: invokeinterface iterator : ()Ljava/util/Iterator;
    //   393: astore #14
    //   395: aload #14
    //   397: invokeinterface hasNext : ()Z
    //   402: ifeq -> 460
    //   405: aload #14
    //   407: invokeinterface next : ()Ljava/lang/Object;
    //   412: checkcast java/lang/Integer
    //   415: astore #15
    //   417: new burp/Ztv_
    //   420: dup
    //   421: aload #15
    //   423: invokevirtual intValue : ()I
    //   426: aload #13
    //   428: invokespecial <init> : (ILjava/net/InetAddress;)V
    //   431: astore #16
    //   433: aload_3
    //   434: new burp/Zge4
    //   437: dup
    //   438: aload #4
    //   440: aload #16
    //   442: aload #10
    //   444: getstatic burp/Zb25.HTTP : Lburp/Zb25;
    //   447: invokespecial <init> : (Ljava/util/concurrent/ExecutorService;Lburp/Ztv_;Lburp/Zz0u;Lburp/Zb25;)V
    //   450: invokeinterface add : (Ljava/lang/Object;)Z
    //   455: pop
    //   456: aload_2
    //   457: ifnull -> 395
    //   460: aload_1
    //   461: invokeinterface ZN : ()Ljava/util/Collection;
    //   466: invokeinterface iterator : ()Ljava/util/Iterator;
    //   471: astore #14
    //   473: aload #14
    //   475: invokeinterface hasNext : ()Z
    //   480: ifeq -> 541
    //   483: aload #14
    //   485: invokeinterface next : ()Ljava/lang/Object;
    //   490: checkcast java/lang/Integer
    //   493: astore #15
    //   495: new burp/Zxkc
    //   498: dup
    //   499: aload #15
    //   501: invokevirtual intValue : ()I
    //   504: aload #13
    //   506: aload #7
    //   508: iconst_0
    //   509: invokespecial <init> : (ILjava/net/InetAddress;Lburp/Zzkb;Z)V
    //   512: astore #16
    //   514: aload_3
    //   515: new burp/Zgv7
    //   518: dup
    //   519: aload #4
    //   521: aload #16
    //   523: aload #11
    //   525: getstatic burp/Zb25.HTTPS : Lburp/Zb25;
    //   528: invokespecial <init> : (Ljava/util/concurrent/ExecutorService;Lburp/Zxkc;Lburp/Zz0u;Lburp/Zb25;)V
    //   531: invokeinterface add : (Ljava/lang/Object;)Z
    //   536: pop
    //   537: aload_2
    //   538: ifnull -> 473
    //   541: new burp/Zg07
    //   544: dup
    //   545: aload_0
    //   546: getfield ZJ : Lburp/Zlhe;
    //   549: aload_0
    //   550: getfield Zw : Lburp/Zl3v;
    //   553: aload #8
    //   555: aload_1
    //   556: invokeinterface ZF : ()Ljava/util/List;
    //   561: aload_1
    //   562: invokeinterface Zn : ()Lburp/Zs_b;
    //   567: invokevirtual ZO : ()J
    //   570: invokespecial <init> : (Lburp/Zlhe;Lburp/Zl3v;Lburp/Zx5k;Ljava/util/List;J)V
    //   573: astore #14
    //   575: aload_1
    //   576: invokeinterface ZT : ()Ljava/util/Collection;
    //   581: invokeinterface iterator : ()Ljava/util/Iterator;
    //   586: astore #15
    //   588: aload #15
    //   590: invokeinterface hasNext : ()Z
    //   595: ifeq -> 653
    //   598: aload #15
    //   600: invokeinterface next : ()Ljava/lang/Object;
    //   605: checkcast java/lang/Integer
    //   608: astore #16
    //   610: new burp/Ztv_
    //   613: dup
    //   614: aload #16
    //   616: invokevirtual intValue : ()I
    //   619: aload #13
    //   621: invokespecial <init> : (ILjava/net/InetAddress;)V
    //   624: astore #17
    //   626: aload_3
    //   627: new burp/Zge4
    //   630: dup
    //   631: aload #4
    //   633: aload #17
    //   635: aload #14
    //   637: getstatic burp/Zb25.SMTP : Lburp/Zb25;
    //   640: invokespecial <init> : (Ljava/util/concurrent/ExecutorService;Lburp/Ztv_;Lburp/Zz0u;Lburp/Zb25;)V
    //   643: invokeinterface add : (Ljava/lang/Object;)Z
    //   648: pop
    //   649: aload_2
    //   650: ifnull -> 588
    //   653: aload_1
    //   654: invokeinterface ZK : ()Ljava/util/Collection;
    //   659: invokeinterface iterator : ()Ljava/util/Iterator;
    //   664: astore #15
    //   666: aload #15
    //   668: invokeinterface hasNext : ()Z
    //   673: ifeq -> 734
    //   676: aload #15
    //   678: invokeinterface next : ()Ljava/lang/Object;
    //   683: checkcast java/lang/Integer
    //   686: astore #16
    //   688: new burp/Zxkc
    //   691: dup
    //   692: aload #16
    //   694: invokevirtual intValue : ()I
    //   697: aload #13
    //   699: aload #7
    //   701: iconst_0
    //   702: invokespecial <init> : (ILjava/net/InetAddress;Lburp/Zzkb;Z)V
    //   705: astore #17
    //   707: aload_3
    //   708: new burp/Zgv7
    //   711: dup
    //   712: aload #4
    //   714: aload #17
    //   716: aload #14
    //   718: getstatic burp/Zb25.SMTPS : Lburp/Zb25;
    //   721: invokespecial <init> : (Ljava/util/concurrent/ExecutorService;Lburp/Zxkc;Lburp/Zz0u;Lburp/Zb25;)V
    //   724: invokeinterface add : (Ljava/lang/Object;)Z
    //   729: pop
    //   730: aload_2
    //   731: ifnull -> 666
    //   734: aload_2
    //   735: ifnull -> 360
    //   738: aload_1
    //   739: invokeinterface Zh : ()Ljava/net/InetAddress;
    //   744: ifnull -> 911
    //   747: aload #9
    //   749: getfield ZD : Lburp/Zxo0;
    //   752: ifnull -> 911
    //   755: new burp/Zko_
    //   758: dup
    //   759: aload #9
    //   761: getfield ZD : Lburp/Zxo0;
    //   764: aload_0
    //   765: getfield Zw : Lburp/Zl3v;
    //   768: aload_1
    //   769: invokeinterface Zn : ()Lburp/Zs_b;
    //   774: invokevirtual ZA : ()J
    //   777: invokespecial <init> : (Lburp/Zxo0;Lburp/Zl3v;J)V
    //   780: astore #12
    //   782: new burp/Zko_
    //   785: dup
    //   786: aload #9
    //   788: getfield ZD : Lburp/Zxo0;
    //   791: aload_0
    //   792: getfield Zw : Lburp/Zl3v;
    //   795: aload_1
    //   796: invokeinterface Zn : ()Lburp/Zs_b;
    //   801: invokevirtual ZA : ()J
    //   804: invokespecial <init> : (Lburp/Zxo0;Lburp/Zl3v;J)V
    //   807: astore #13
    //   809: new burp/Zzkb
    //   812: dup
    //   813: aload #6
    //   815: invokespecial <init> : (Lburp/Zg6d;)V
    //   818: astore #14
    //   820: new burp/Ztv_
    //   823: dup
    //   824: aload_1
    //   825: invokeinterface ZE : ()I
    //   830: aload_1
    //   831: invokeinterface Zh : ()Ljava/net/InetAddress;
    //   836: invokespecial <init> : (ILjava/net/InetAddress;)V
    //   839: astore #15
    //   841: aload_3
    //   842: new burp/Zge4
    //   845: dup
    //   846: aload #4
    //   848: aload #15
    //   850: aload #12
    //   852: getstatic burp/Zb25.HTTP : Lburp/Zb25;
    //   855: invokespecial <init> : (Ljava/util/concurrent/ExecutorService;Lburp/Ztv_;Lburp/Zz0u;Lburp/Zb25;)V
    //   858: invokeinterface add : (Ljava/lang/Object;)Z
    //   863: pop
    //   864: new burp/Zxkc
    //   867: dup
    //   868: aload_1
    //   869: invokeinterface Zk : ()I
    //   874: aload_1
    //   875: invokeinterface Zh : ()Ljava/net/InetAddress;
    //   880: aload #14
    //   882: iconst_1
    //   883: invokespecial <init> : (ILjava/net/InetAddress;Lburp/Zzkb;Z)V
    //   886: astore #16
    //   888: aload_3
    //   889: new burp/Zgv7
    //   892: dup
    //   893: aload #4
    //   895: aload #16
    //   897: aload #13
    //   899: getstatic burp/Zb25.HTTPS : Lburp/Zb25;
    //   902: invokespecial <init> : (Ljava/util/concurrent/ExecutorService;Lburp/Zxkc;Lburp/Zz0u;Lburp/Zb25;)V
    //   905: invokeinterface add : (Ljava/lang/Object;)Z
    //   910: pop
    //   911: new burp/Zg4u
    //   914: dup
    //   915: aload_3
    //   916: invokespecial <init> : (Ljava/util/List;)V
    //   919: areturn
  }
  
  static {
    // Byte code:
    //   0: bipush #30
    //   2: ldc ' M~g!~<EmlsS \\bbvsJ!Ml':F,j60Gb\\fk4O!Ixm=5A`,s~{,\\fw=Y'Acc?S'Q,k?VsFc"$U!C"'
    //   4: iconst_m1
    //   5: goto -> 14
    //   8: putstatic burp/Zlk.a : Ljava/lang/String;
    //   11: goto -> 154
    //   14: dup_x2
    //   15: pop
    //   16: invokevirtual toCharArray : ()[C
    //   19: dup_x1
    //   20: arraylength
    //   21: dup_x2
    //   22: pop
    //   23: iconst_0
    //   24: istore_0
    //   25: dup2_x1
    //   26: pop2
    //   27: dup_x2
    //   28: iconst_1
    //   29: if_icmpgt -> 128
    //   32: dup2
    //   33: swap
    //   34: iload_0
    //   35: dup2_x1
    //   36: caload
    //   37: swap
    //   38: iload_0
    //   39: bipush #7
    //   41: irem
    //   42: tableswitch default -> 110, 0 -> 80, 1 -> 85, 2 -> 90, 3 -> 95, 4 -> 100, 5 -> 105
    //   80: bipush #77
    //   82: goto -> 112
    //   85: bipush #54
    //   87: goto -> 112
    //   90: bipush #18
    //   92: goto -> 112
    //   95: bipush #116
    //   97: goto -> 112
    //   100: bipush #28
    //   102: goto -> 112
    //   105: bipush #77
    //   107: goto -> 112
    //   110: bipush #36
    //   112: ixor
    //   113: ixor
    //   114: i2c
    //   115: castore
    //   116: iinc #0, 1
    //   119: dup
    //   120: ifne -> 128
    //   123: dup2
    //   124: dup_x1
    //   125: goto -> 35
    //   128: dup2_x1
    //   129: pop2
    //   130: dup_x2
    //   131: iload_0
    //   132: if_icmpgt -> 32
    //   135: pop
    //   136: new java/lang/String
    //   139: dup_x1
    //   140: swap
    //   141: invokespecial <init> : ([C)V
    //   144: invokevirtual intern : ()Ljava/lang/String;
    //   147: swap
    //   148: pop
    //   149: swap
    //   150: pop
    //   151: goto -> 8
    //   154: invokestatic Zr : ()Lburp/Ztt4;
    //   157: putstatic burp/Zlk.ZI : Lburp/Ztt4;
    //   160: return
  }
}


/* Location:              C:\Program Files\BurpSuitePro\burpsuite_pro.jar!\burp\Zlk.class
 * Java compiler version: 21 (65.0)
 * JD-Core Version:       1.1.3
 */