package burp;

import java.math.BigInteger;

class Zlkm extends ClassLoader {
  static Object ZQ;
  
  static String ZH;
  
  private static final String[] a;
  
  private static final String[] b;
  
  static void ZW(Object paramObject) {
    Zle6.Zh = a(-11084, -3607);
    Zle6.ZM = new BigInteger(a(-11088, 15289));
    boolean bool = Zt2e.ZK();
    try {
      try {
        if (Zxc.Zx.charAt(Math.abs(((BigInteger)Zzmo.ZI).intValue() % 32)) > Zxc.Zx.charAt(Math.abs(((BigInteger)Zf.Zh).intValue() % 32))) {
          try {
            Zle4.ZJ(Class.forName(a(-11083, -10935)));
            if (bool)
              Zmze.Zx(Class.forName(a(-11094, -26814))); 
          } catch (Throwable throwable) {
            throw a(null);
          } 
          return;
        } 
      } catch (Throwable throwable) {
        throw a(null);
      } 
      Zmze.Zx(Class.forName(a(-11094, -26814)));
    } catch (Throwable throwable) {}
  }
  
  static boolean Zr(Object[] paramArrayOfObject, Object paramObject) throws Throwable {
    // Byte code:
    //   0: invokestatic ZN : ()Z
    //   3: istore_2
    //   4: getstatic burp/Zbo2.ZQ : Ljava/lang/Object;
    //   7: checkcast java/math/BigInteger
    //   10: getstatic burp/Zb6a.Zz : Ljava/lang/Object;
    //   13: checkcast java/math/BigInteger
    //   16: invokevirtual subtract : (Ljava/math/BigInteger;)Ljava/math/BigInteger;
    //   19: putstatic burp/Zt7j.ZH : Ljava/lang/Object;
    //   22: getstatic burp/Zl8i.ZY : Ljava/lang/Object;
    //   25: checkcast java/math/BigInteger
    //   28: getstatic burp/Zb4m.Zp : Ljava/lang/Object;
    //   31: checkcast java/math/BigInteger
    //   34: invokevirtual subtract : (Ljava/math/BigInteger;)Ljava/math/BigInteger;
    //   37: putstatic burp/Zgjs.Za : Ljava/lang/Object;
    //   40: new java/lang/StringBuilder
    //   43: dup
    //   44: invokespecial <init> : ()V
    //   47: astore_3
    //   48: iconst_0
    //   49: istore #4
    //   51: iload #4
    //   53: bipush #32
    //   55: if_icmpge -> 1391
    //   58: iload #4
    //   60: tableswitch default -> 1384, 0 -> 204, 1 -> 241, 2 -> 278, 3 -> 315, 4 -> 352, 5 -> 389, 6 -> 426, 7 -> 463, 8 -> 500, 9 -> 537, 10 -> 574, 11 -> 611, 12 -> 648, 13 -> 685, 14 -> 722, 15 -> 759, 16 -> 796, 17 -> 833, 18 -> 870, 19 -> 907, 20 -> 944, 21 -> 981, 22 -> 1018, 23 -> 1055, 24 -> 1092, 25 -> 1129, 26 -> 1166, 27 -> 1203, 28 -> 1240, 29 -> 1277, 30 -> 1314, 31 -> 1351
    //   204: aload_3
    //   205: getstatic burp/Zbj.ZD : Ljava/lang/String;
    //   208: getstatic burp/Zgia.Zx : Ljava/lang/Object;
    //   211: checkcast java/math/BigInteger
    //   214: invokevirtual intValue : ()I
    //   217: bipush #32
    //   219: irem
    //   220: invokestatic abs : (I)I
    //   223: invokevirtual charAt : (I)C
    //   226: invokevirtual append : (C)Ljava/lang/StringBuilder;
    //   229: pop
    //   230: iload_2
    //   231: ifne -> 1384
    //   234: goto -> 241
    //   237: invokestatic a : (Ljava/lang/Throwable;)Ljava/lang/Throwable;
    //   240: athrow
    //   241: aload_3
    //   242: getstatic burp/Zeuz.Zb : Ljava/lang/String;
    //   245: getstatic burp/Zbqk.ZT : Ljava/lang/Object;
    //   248: checkcast java/math/BigInteger
    //   251: invokevirtual intValue : ()I
    //   254: bipush #32
    //   256: irem
    //   257: invokestatic abs : (I)I
    //   260: invokevirtual charAt : (I)C
    //   263: invokevirtual append : (C)Ljava/lang/StringBuilder;
    //   266: pop
    //   267: iload_2
    //   268: ifne -> 1384
    //   271: goto -> 278
    //   274: invokestatic a : (Ljava/lang/Throwable;)Ljava/lang/Throwable;
    //   277: athrow
    //   278: aload_3
    //   279: getstatic burp/Ztgj.Zw : Ljava/lang/String;
    //   282: getstatic burp/Zez0.ZT : Ljava/lang/Object;
    //   285: checkcast java/math/BigInteger
    //   288: invokevirtual intValue : ()I
    //   291: bipush #32
    //   293: irem
    //   294: invokestatic abs : (I)I
    //   297: invokevirtual charAt : (I)C
    //   300: invokevirtual append : (C)Ljava/lang/StringBuilder;
    //   303: pop
    //   304: iload_2
    //   305: ifne -> 1384
    //   308: goto -> 315
    //   311: invokestatic a : (Ljava/lang/Throwable;)Ljava/lang/Throwable;
    //   314: athrow
    //   315: aload_3
    //   316: getstatic burp/Zvk.ZG : Ljava/lang/String;
    //   319: getstatic burp/Zez0.ZT : Ljava/lang/Object;
    //   322: checkcast java/math/BigInteger
    //   325: invokevirtual intValue : ()I
    //   328: bipush #32
    //   330: irem
    //   331: invokestatic abs : (I)I
    //   334: invokevirtual charAt : (I)C
    //   337: invokevirtual append : (C)Ljava/lang/StringBuilder;
    //   340: pop
    //   341: iload_2
    //   342: ifne -> 1384
    //   345: goto -> 352
    //   348: invokestatic a : (Ljava/lang/Throwable;)Ljava/lang/Throwable;
    //   351: athrow
    //   352: aload_3
    //   353: getstatic burp/Zrn0.Zd : Ljava/lang/String;
    //   356: getstatic burp/Zgds.Z_ : Ljava/lang/Object;
    //   359: checkcast java/math/BigInteger
    //   362: invokevirtual intValue : ()I
    //   365: bipush #32
    //   367: irem
    //   368: invokestatic abs : (I)I
    //   371: invokevirtual charAt : (I)C
    //   374: invokevirtual append : (C)Ljava/lang/StringBuilder;
    //   377: pop
    //   378: iload_2
    //   379: ifne -> 1384
    //   382: goto -> 389
    //   385: invokestatic a : (Ljava/lang/Throwable;)Ljava/lang/Throwable;
    //   388: athrow
    //   389: aload_3
    //   390: getstatic burp/Zmuj.ZG : Ljava/lang/String;
    //   393: getstatic burp/Zlot.ZJ : Ljava/lang/Object;
    //   396: checkcast java/math/BigInteger
    //   399: invokevirtual intValue : ()I
    //   402: bipush #32
    //   404: irem
    //   405: invokestatic abs : (I)I
    //   408: invokevirtual charAt : (I)C
    //   411: invokevirtual append : (C)Ljava/lang/StringBuilder;
    //   414: pop
    //   415: iload_2
    //   416: ifne -> 1384
    //   419: goto -> 426
    //   422: invokestatic a : (Ljava/lang/Throwable;)Ljava/lang/Throwable;
    //   425: athrow
    //   426: aload_3
    //   427: getstatic burp/Zkgp.ZM : Ljava/lang/String;
    //   430: getstatic burp/Zbj.ZY : Ljava/lang/Object;
    //   433: checkcast java/math/BigInteger
    //   436: invokevirtual intValue : ()I
    //   439: bipush #32
    //   441: irem
    //   442: invokestatic abs : (I)I
    //   445: invokevirtual charAt : (I)C
    //   448: invokevirtual append : (C)Ljava/lang/StringBuilder;
    //   451: pop
    //   452: iload_2
    //   453: ifne -> 1384
    //   456: goto -> 463
    //   459: invokestatic a : (Ljava/lang/Throwable;)Ljava/lang/Throwable;
    //   462: athrow
    //   463: aload_3
    //   464: getstatic burp/Zsjo.Zu : Ljava/lang/String;
    //   467: getstatic burp/Zsjo.ZB : Ljava/lang/Object;
    //   470: checkcast java/math/BigInteger
    //   473: invokevirtual intValue : ()I
    //   476: bipush #32
    //   478: irem
    //   479: invokestatic abs : (I)I
    //   482: invokevirtual charAt : (I)C
    //   485: invokevirtual append : (C)Ljava/lang/StringBuilder;
    //   488: pop
    //   489: iload_2
    //   490: ifne -> 1384
    //   493: goto -> 500
    //   496: invokestatic a : (Ljava/lang/Throwable;)Ljava/lang/Throwable;
    //   499: athrow
    //   500: aload_3
    //   501: getstatic burp/Zmv9.Zm : Ljava/lang/String;
    //   504: getstatic burp/Zt5b.Zc : Ljava/lang/Object;
    //   507: checkcast java/math/BigInteger
    //   510: invokevirtual intValue : ()I
    //   513: bipush #32
    //   515: irem
    //   516: invokestatic abs : (I)I
    //   519: invokevirtual charAt : (I)C
    //   522: invokevirtual append : (C)Ljava/lang/StringBuilder;
    //   525: pop
    //   526: iload_2
    //   527: ifne -> 1384
    //   530: goto -> 537
    //   533: invokestatic a : (Ljava/lang/Throwable;)Ljava/lang/Throwable;
    //   536: athrow
    //   537: aload_3
    //   538: getstatic burp/Zg8v.Zd : Ljava/lang/String;
    //   541: getstatic burp/Zl8i.ZY : Ljava/lang/Object;
    //   544: checkcast java/math/BigInteger
    //   547: invokevirtual intValue : ()I
    //   550: bipush #32
    //   552: irem
    //   553: invokestatic abs : (I)I
    //   556: invokevirtual charAt : (I)C
    //   559: invokevirtual append : (C)Ljava/lang/StringBuilder;
    //   562: pop
    //   563: iload_2
    //   564: ifne -> 1384
    //   567: goto -> 574
    //   570: invokestatic a : (Ljava/lang/Throwable;)Ljava/lang/Throwable;
    //   573: athrow
    //   574: aload_3
    //   575: getstatic burp/Zxf8.Zq : Ljava/lang/String;
    //   578: getstatic burp/Zgjs.Za : Ljava/lang/Object;
    //   581: checkcast java/math/BigInteger
    //   584: invokevirtual intValue : ()I
    //   587: bipush #32
    //   589: irem
    //   590: invokestatic abs : (I)I
    //   593: invokevirtual charAt : (I)C
    //   596: invokevirtual append : (C)Ljava/lang/StringBuilder;
    //   599: pop
    //   600: iload_2
    //   601: ifne -> 1384
    //   604: goto -> 611
    //   607: invokestatic a : (Ljava/lang/Throwable;)Ljava/lang/Throwable;
    //   610: athrow
    //   611: aload_3
    //   612: getstatic burp/Zgjj.Zi : Ljava/lang/String;
    //   615: getstatic burp/Zbo2.ZQ : Ljava/lang/Object;
    //   618: checkcast java/math/BigInteger
    //   621: invokevirtual intValue : ()I
    //   624: bipush #32
    //   626: irem
    //   627: invokestatic abs : (I)I
    //   630: invokevirtual charAt : (I)C
    //   633: invokevirtual append : (C)Ljava/lang/StringBuilder;
    //   636: pop
    //   637: iload_2
    //   638: ifne -> 1384
    //   641: goto -> 648
    //   644: invokestatic a : (Ljava/lang/Throwable;)Ljava/lang/Throwable;
    //   647: athrow
    //   648: aload_3
    //   649: getstatic burp/Zgrf.ZE : Ljava/lang/String;
    //   652: getstatic burp/Zkqx.ZW : Ljava/lang/Object;
    //   655: checkcast java/math/BigInteger
    //   658: invokevirtual intValue : ()I
    //   661: bipush #32
    //   663: irem
    //   664: invokestatic abs : (I)I
    //   667: invokevirtual charAt : (I)C
    //   670: invokevirtual append : (C)Ljava/lang/StringBuilder;
    //   673: pop
    //   674: iload_2
    //   675: ifne -> 1384
    //   678: goto -> 685
    //   681: invokestatic a : (Ljava/lang/Throwable;)Ljava/lang/Throwable;
    //   684: athrow
    //   685: aload_3
    //   686: getstatic burp/Zrka.Zy : Ljava/lang/String;
    //   689: getstatic burp/Zro2.Zu : Ljava/lang/Object;
    //   692: checkcast java/math/BigInteger
    //   695: invokevirtual intValue : ()I
    //   698: bipush #32
    //   700: irem
    //   701: invokestatic abs : (I)I
    //   704: invokevirtual charAt : (I)C
    //   707: invokevirtual append : (C)Ljava/lang/StringBuilder;
    //   710: pop
    //   711: iload_2
    //   712: ifne -> 1384
    //   715: goto -> 722
    //   718: invokestatic a : (Ljava/lang/Throwable;)Ljava/lang/Throwable;
    //   721: athrow
    //   722: aload_3
    //   723: getstatic burp/Zlkm.ZH : Ljava/lang/String;
    //   726: getstatic burp/Zzri.ZG : Ljava/lang/Object;
    //   729: checkcast java/math/BigInteger
    //   732: invokevirtual intValue : ()I
    //   735: bipush #32
    //   737: irem
    //   738: invokestatic abs : (I)I
    //   741: invokevirtual charAt : (I)C
    //   744: invokevirtual append : (C)Ljava/lang/StringBuilder;
    //   747: pop
    //   748: iload_2
    //   749: ifne -> 1384
    //   752: goto -> 759
    //   755: invokestatic a : (Ljava/lang/Throwable;)Ljava/lang/Throwable;
    //   758: athrow
    //   759: aload_3
    //   760: getstatic burp/Zg7w.ZI : Ljava/lang/String;
    //   763: getstatic burp/Zxf8.Zz : Ljava/lang/Object;
    //   766: checkcast java/math/BigInteger
    //   769: invokevirtual intValue : ()I
    //   772: bipush #32
    //   774: irem
    //   775: invokestatic abs : (I)I
    //   778: invokevirtual charAt : (I)C
    //   781: invokevirtual append : (C)Ljava/lang/StringBuilder;
    //   784: pop
    //   785: iload_2
    //   786: ifne -> 1384
    //   789: goto -> 796
    //   792: invokestatic a : (Ljava/lang/Throwable;)Ljava/lang/Throwable;
    //   795: athrow
    //   796: aload_3
    //   797: getstatic burp/Zb4m.ZQ : Ljava/lang/String;
    //   800: getstatic burp/Zxd4.Zt : Ljava/lang/Object;
    //   803: checkcast java/math/BigInteger
    //   806: invokevirtual intValue : ()I
    //   809: bipush #32
    //   811: irem
    //   812: invokestatic abs : (I)I
    //   815: invokevirtual charAt : (I)C
    //   818: invokevirtual append : (C)Ljava/lang/StringBuilder;
    //   821: pop
    //   822: iload_2
    //   823: ifne -> 1384
    //   826: goto -> 833
    //   829: invokestatic a : (Ljava/lang/Throwable;)Ljava/lang/Throwable;
    //   832: athrow
    //   833: aload_3
    //   834: getstatic burp/Zva.Zi : Ljava/lang/String;
    //   837: getstatic burp/Zmv9.Zw : Ljava/lang/Object;
    //   840: checkcast java/math/BigInteger
    //   843: invokevirtual intValue : ()I
    //   846: bipush #32
    //   848: irem
    //   849: invokestatic abs : (I)I
    //   852: invokevirtual charAt : (I)C
    //   855: invokevirtual append : (C)Ljava/lang/StringBuilder;
    //   858: pop
    //   859: iload_2
    //   860: ifne -> 1384
    //   863: goto -> 870
    //   866: invokestatic a : (Ljava/lang/Throwable;)Ljava/lang/Throwable;
    //   869: athrow
    //   870: aload_3
    //   871: getstatic burp/Zb2p.ZV : Ljava/lang/String;
    //   874: getstatic burp/Zll8.ZE : Ljava/lang/Object;
    //   877: checkcast java/math/BigInteger
    //   880: invokevirtual intValue : ()I
    //   883: bipush #32
    //   885: irem
    //   886: invokestatic abs : (I)I
    //   889: invokevirtual charAt : (I)C
    //   892: invokevirtual append : (C)Ljava/lang/StringBuilder;
    //   895: pop
    //   896: iload_2
    //   897: ifne -> 1384
    //   900: goto -> 907
    //   903: invokestatic a : (Ljava/lang/Throwable;)Ljava/lang/Throwable;
    //   906: athrow
    //   907: aload_3
    //   908: getstatic burp/Zle6.Zh : Ljava/lang/String;
    //   911: getstatic burp/Zls0.ZZ : Ljava/lang/Object;
    //   914: checkcast java/math/BigInteger
    //   917: invokevirtual intValue : ()I
    //   920: bipush #32
    //   922: irem
    //   923: invokestatic abs : (I)I
    //   926: invokevirtual charAt : (I)C
    //   929: invokevirtual append : (C)Ljava/lang/StringBuilder;
    //   932: pop
    //   933: iload_2
    //   934: ifne -> 1384
    //   937: goto -> 944
    //   940: invokestatic a : (Ljava/lang/Throwable;)Ljava/lang/Throwable;
    //   943: athrow
    //   944: aload_3
    //   945: getstatic burp/Zkk2.ZI : Ljava/lang/String;
    //   948: getstatic burp/Zbz_.ZU : Ljava/lang/Object;
    //   951: checkcast java/math/BigInteger
    //   954: invokevirtual intValue : ()I
    //   957: bipush #32
    //   959: irem
    //   960: invokestatic abs : (I)I
    //   963: invokevirtual charAt : (I)C
    //   966: invokevirtual append : (C)Ljava/lang/StringBuilder;
    //   969: pop
    //   970: iload_2
    //   971: ifne -> 1384
    //   974: goto -> 981
    //   977: invokestatic a : (Ljava/lang/Throwable;)Ljava/lang/Throwable;
    //   980: athrow
    //   981: aload_3
    //   982: getstatic burp/Ztip.Z_ : Ljava/lang/String;
    //   985: getstatic burp/Zmv9.Zw : Ljava/lang/Object;
    //   988: checkcast java/math/BigInteger
    //   991: invokevirtual intValue : ()I
    //   994: bipush #32
    //   996: irem
    //   997: invokestatic abs : (I)I
    //   1000: invokevirtual charAt : (I)C
    //   1003: invokevirtual append : (C)Ljava/lang/StringBuilder;
    //   1006: pop
    //   1007: iload_2
    //   1008: ifne -> 1384
    //   1011: goto -> 1018
    //   1014: invokestatic a : (Ljava/lang/Throwable;)Ljava/lang/Throwable;
    //   1017: athrow
    //   1018: aload_3
    //   1019: getstatic burp/Zxd4.Zf : Ljava/lang/String;
    //   1022: getstatic burp/Zkgp.Zw : Ljava/lang/Object;
    //   1025: checkcast java/math/BigInteger
    //   1028: invokevirtual intValue : ()I
    //   1031: bipush #32
    //   1033: irem
    //   1034: invokestatic abs : (I)I
    //   1037: invokevirtual charAt : (I)C
    //   1040: invokevirtual append : (C)Ljava/lang/StringBuilder;
    //   1043: pop
    //   1044: iload_2
    //   1045: ifne -> 1384
    //   1048: goto -> 1055
    //   1051: invokestatic a : (Ljava/lang/Throwable;)Ljava/lang/Throwable;
    //   1054: athrow
    //   1055: aload_3
    //   1056: getstatic burp/Zgrf.ZE : Ljava/lang/String;
    //   1059: getstatic burp/Zkq9.Ze : Ljava/lang/Object;
    //   1062: checkcast java/math/BigInteger
    //   1065: invokevirtual intValue : ()I
    //   1068: bipush #32
    //   1070: irem
    //   1071: invokestatic abs : (I)I
    //   1074: invokevirtual charAt : (I)C
    //   1077: invokevirtual append : (C)Ljava/lang/StringBuilder;
    //   1080: pop
    //   1081: iload_2
    //   1082: ifne -> 1384
    //   1085: goto -> 1092
    //   1088: invokestatic a : (Ljava/lang/Throwable;)Ljava/lang/Throwable;
    //   1091: athrow
    //   1092: aload_3
    //   1093: getstatic burp/Zrka.Zy : Ljava/lang/String;
    //   1096: getstatic burp/Zf.Zh : Ljava/lang/Object;
    //   1099: checkcast java/math/BigInteger
    //   1102: invokevirtual intValue : ()I
    //   1105: bipush #32
    //   1107: irem
    //   1108: invokestatic abs : (I)I
    //   1111: invokevirtual charAt : (I)C
    //   1114: invokevirtual append : (C)Ljava/lang/StringBuilder;
    //   1117: pop
    //   1118: iload_2
    //   1119: ifne -> 1384
    //   1122: goto -> 1129
    //   1125: invokestatic a : (Ljava/lang/Throwable;)Ljava/lang/Throwable;
    //   1128: athrow
    //   1129: aload_3
    //   1130: getstatic burp/Zmgl.Zh : Ljava/lang/String;
    //   1133: getstatic burp/Zva.Zu : Ljava/lang/Object;
    //   1136: checkcast java/math/BigInteger
    //   1139: invokevirtual intValue : ()I
    //   1142: bipush #32
    //   1144: irem
    //   1145: invokestatic abs : (I)I
    //   1148: invokevirtual charAt : (I)C
    //   1151: invokevirtual append : (C)Ljava/lang/StringBuilder;
    //   1154: pop
    //   1155: iload_2
    //   1156: ifne -> 1384
    //   1159: goto -> 1166
    //   1162: invokestatic a : (Ljava/lang/Throwable;)Ljava/lang/Throwable;
    //   1165: athrow
    //   1166: aload_3
    //   1167: getstatic burp/Zlp8.ZW : Ljava/lang/String;
    //   1170: getstatic burp/Zxd4.Zt : Ljava/lang/Object;
    //   1173: checkcast java/math/BigInteger
    //   1176: invokevirtual intValue : ()I
    //   1179: bipush #32
    //   1181: irem
    //   1182: invokestatic abs : (I)I
    //   1185: invokevirtual charAt : (I)C
    //   1188: invokevirtual append : (C)Ljava/lang/StringBuilder;
    //   1191: pop
    //   1192: iload_2
    //   1193: ifne -> 1384
    //   1196: goto -> 1203
    //   1199: invokestatic a : (Ljava/lang/Throwable;)Ljava/lang/Throwable;
    //   1202: athrow
    //   1203: aload_3
    //   1204: getstatic burp/Zmgl.Zh : Ljava/lang/String;
    //   1207: getstatic burp/Zb38.ZC : Ljava/lang/Object;
    //   1210: checkcast java/math/BigInteger
    //   1213: invokevirtual intValue : ()I
    //   1216: bipush #32
    //   1218: irem
    //   1219: invokestatic abs : (I)I
    //   1222: invokevirtual charAt : (I)C
    //   1225: invokevirtual append : (C)Ljava/lang/StringBuilder;
    //   1228: pop
    //   1229: iload_2
    //   1230: ifne -> 1384
    //   1233: goto -> 1240
    //   1236: invokestatic a : (Ljava/lang/Throwable;)Ljava/lang/Throwable;
    //   1239: athrow
    //   1240: aload_3
    //   1241: getstatic burp/Zls0.ZI : Ljava/lang/String;
    //   1244: getstatic burp/Zb6a.Zz : Ljava/lang/Object;
    //   1247: checkcast java/math/BigInteger
    //   1250: invokevirtual intValue : ()I
    //   1253: bipush #32
    //   1255: irem
    //   1256: invokestatic abs : (I)I
    //   1259: invokevirtual charAt : (I)C
    //   1262: invokevirtual append : (C)Ljava/lang/StringBuilder;
    //   1265: pop
    //   1266: iload_2
    //   1267: ifne -> 1384
    //   1270: goto -> 1277
    //   1273: invokestatic a : (Ljava/lang/Throwable;)Ljava/lang/Throwable;
    //   1276: athrow
    //   1277: aload_3
    //   1278: getstatic burp/Zb2p.ZV : Ljava/lang/String;
    //   1281: getstatic burp/Zxt5.ZG : Ljava/lang/Object;
    //   1284: checkcast java/math/BigInteger
    //   1287: invokevirtual intValue : ()I
    //   1290: bipush #32
    //   1292: irem
    //   1293: invokestatic abs : (I)I
    //   1296: invokevirtual charAt : (I)C
    //   1299: invokevirtual append : (C)Ljava/lang/StringBuilder;
    //   1302: pop
    //   1303: iload_2
    //   1304: ifne -> 1384
    //   1307: goto -> 1314
    //   1310: invokestatic a : (Ljava/lang/Throwable;)Ljava/lang/Throwable;
    //   1313: athrow
    //   1314: aload_3
    //   1315: getstatic burp/Zgja.Zb : Ljava/lang/String;
    //   1318: getstatic burp/Zgds.Z_ : Ljava/lang/Object;
    //   1321: checkcast java/math/BigInteger
    //   1324: invokevirtual intValue : ()I
    //   1327: bipush #32
    //   1329: irem
    //   1330: invokestatic abs : (I)I
    //   1333: invokevirtual charAt : (I)C
    //   1336: invokevirtual append : (C)Ljava/lang/StringBuilder;
    //   1339: pop
    //   1340: iload_2
    //   1341: ifne -> 1384
    //   1344: goto -> 1351
    //   1347: invokestatic a : (Ljava/lang/Throwable;)Ljava/lang/Throwable;
    //   1350: athrow
    //   1351: aload_3
    //   1352: getstatic burp/Zgrf.ZE : Ljava/lang/String;
    //   1355: getstatic burp/Zez0.ZT : Ljava/lang/Object;
    //   1358: checkcast java/math/BigInteger
    //   1361: invokevirtual intValue : ()I
    //   1364: bipush #32
    //   1366: irem
    //   1367: invokestatic abs : (I)I
    //   1370: invokevirtual charAt : (I)C
    //   1373: invokevirtual append : (C)Ljava/lang/StringBuilder;
    //   1376: pop
    //   1377: goto -> 1384
    //   1380: invokestatic a : (Ljava/lang/Throwable;)Ljava/lang/Throwable;
    //   1383: athrow
    //   1384: iinc #4, 1
    //   1387: iload_2
    //   1388: ifne -> 51
    //   1391: aload_3
    //   1392: invokevirtual toString : ()Ljava/lang/String;
    //   1395: putstatic burp/Zgp_.Zn : Ljava/lang/String;
    //   1398: sipush #-11089
    //   1401: sipush #9959
    //   1404: invokestatic a : (II)Ljava/lang/String;
    //   1407: iconst_1
    //   1408: ldc burp/Zm5s
    //   1410: invokevirtual getClassLoader : ()Ljava/lang/ClassLoader;
    //   1413: invokestatic forName : (Ljava/lang/String;ZLjava/lang/ClassLoader;)Ljava/lang/Class;
    //   1416: invokevirtual getDeclaredFields : ()[Ljava/lang/reflect/Field;
    //   1419: astore #4
    //   1421: aload #4
    //   1423: arraylength
    //   1424: istore #5
    //   1426: iconst_0
    //   1427: istore #6
    //   1429: iload #6
    //   1431: iload #5
    //   1433: if_icmpge -> 1571
    //   1436: aload #4
    //   1438: iload #6
    //   1440: aaload
    //   1441: astore #7
    //   1443: aload #7
    //   1445: invokevirtual getModifiers : ()I
    //   1448: invokestatic isStatic : (I)Z
    //   1451: ifne -> 1461
    //   1454: goto -> 1564
    //   1457: invokestatic a : (Ljava/lang/Throwable;)Ljava/lang/Throwable;
    //   1460: athrow
    //   1461: aload #7
    //   1463: invokevirtual getType : ()Ljava/lang/Class;
    //   1466: astore #8
    //   1468: aload #8
    //   1470: ifnull -> 1551
    //   1473: aload #8
    //   1475: invokevirtual isPrimitive : ()Z
    //   1478: ifne -> 1551
    //   1481: goto -> 1488
    //   1484: invokestatic a : (Ljava/lang/Throwable;)Ljava/lang/Throwable;
    //   1487: athrow
    //   1488: aload #8
    //   1490: invokevirtual getPackage : ()Ljava/lang/Package;
    //   1493: ifnull -> 1551
    //   1496: goto -> 1503
    //   1499: invokestatic a : (Ljava/lang/Throwable;)Ljava/lang/Throwable;
    //   1502: athrow
    //   1503: aload #8
    //   1505: invokevirtual getPackage : ()Ljava/lang/Package;
    //   1508: invokevirtual getName : ()Ljava/lang/String;
    //   1511: ifnull -> 1551
    //   1514: goto -> 1521
    //   1517: invokestatic a : (Ljava/lang/Throwable;)Ljava/lang/Throwable;
    //   1520: athrow
    //   1521: aload #8
    //   1523: invokevirtual getPackage : ()Ljava/lang/Package;
    //   1526: invokevirtual getName : ()Ljava/lang/String;
    //   1529: sipush #-11099
    //   1532: sipush #-23954
    //   1535: invokestatic a : (II)Ljava/lang/String;
    //   1538: invokevirtual startsWith : (Ljava/lang/String;)Z
    //   1541: ifne -> 1551
    //   1544: goto -> 1551
    //   1547: invokestatic a : (Ljava/lang/Throwable;)Ljava/lang/Throwable;
    //   1550: athrow
    //   1551: aload #7
    //   1553: iconst_1
    //   1554: invokevirtual setAccessible : (Z)V
    //   1557: aload #7
    //   1559: aconst_null
    //   1560: invokevirtual get : (Ljava/lang/Object;)Ljava/lang/Object;
    //   1563: pop
    //   1564: iinc #6, 1
    //   1567: iload_2
    //   1568: ifne -> 1429
    //   1571: sipush #-11101
    //   1574: sipush #-11509
    //   1577: invokestatic a : (II)Ljava/lang/String;
    //   1580: invokestatic forName : (Ljava/lang/String;)Ljava/lang/Class;
    //   1583: invokevirtual getDeclaredMethods : ()[Ljava/lang/reflect/Method;
    //   1586: astore #4
    //   1588: aload #4
    //   1590: arraylength
    //   1591: istore #5
    //   1593: iconst_0
    //   1594: istore #6
    //   1596: iload #6
    //   1598: iload #5
    //   1600: if_icmpge -> 1733
    //   1603: aload #4
    //   1605: iload #6
    //   1607: aaload
    //   1608: astore #7
    //   1610: aload #7
    //   1612: invokevirtual getParameterTypes : ()[Ljava/lang/Class;
    //   1615: pop
    //   1616: aload #7
    //   1618: invokevirtual getModifiers : ()I
    //   1621: invokestatic isStatic : (I)Z
    //   1624: ifeq -> 1719
    //   1627: aload #7
    //   1629: invokevirtual getParameterTypes : ()[Ljava/lang/Class;
    //   1632: arraylength
    //   1633: iconst_2
    //   1634: if_icmpne -> 1719
    //   1637: goto -> 1644
    //   1640: invokestatic a : (Ljava/lang/Throwable;)Ljava/lang/Throwable;
    //   1643: athrow
    //   1644: aload #7
    //   1646: invokevirtual getReturnType : ()Ljava/lang/Class;
    //   1649: getstatic java/lang/Void.TYPE : Ljava/lang/Class;
    //   1652: invokevirtual equals : (Ljava/lang/Object;)Z
    //   1655: ifeq -> 1719
    //   1658: goto -> 1665
    //   1661: invokestatic a : (Ljava/lang/Throwable;)Ljava/lang/Throwable;
    //   1664: athrow
    //   1665: aload #7
    //   1667: iconst_1
    //   1668: invokevirtual setAccessible : (Z)V
    //   1671: aload #7
    //   1673: aconst_null
    //   1674: iconst_2
    //   1675: anewarray java/lang/Object
    //   1678: dup
    //   1679: iconst_0
    //   1680: aload_0
    //   1681: aastore
    //   1682: dup
    //   1683: iconst_1
    //   1684: aload_1
    //   1685: ifnonnull -> 1703
    //   1688: goto -> 1695
    //   1691: invokestatic a : (Ljava/lang/Throwable;)Ljava/lang/Throwable;
    //   1694: athrow
    //   1695: aload_1
    //   1696: goto -> 1710
    //   1699: invokestatic a : (Ljava/lang/Throwable;)Ljava/lang/Throwable;
    //   1702: athrow
    //   1703: aload_1
    //   1704: checkcast [B
    //   1707: invokevirtual clone : ()Ljava/lang/Object;
    //   1710: aastore
    //   1711: invokevirtual invoke : (Ljava/lang/Object;[Ljava/lang/Object;)Ljava/lang/Object;
    //   1714: pop
    //   1715: iload_2
    //   1716: ifne -> 1733
    //   1719: iinc #6, 1
    //   1722: iload_2
    //   1723: ifne -> 1596
    //   1726: goto -> 1733
    //   1729: invokestatic a : (Ljava/lang/Throwable;)Ljava/lang/Throwable;
    //   1732: athrow
    //   1733: getstatic burp/Zgyc.ZT : Ljava/lang/Object;
    //   1736: checkcast java/math/BigInteger
    //   1739: invokevirtual intValue : ()I
    //   1742: i2l
    //   1743: invokestatic currentTimeMillis : ()J
    //   1746: ladd
    //   1747: getstatic burp/Zrpm.ZR : Ljava/lang/Object;
    //   1750: checkcast java/math/BigInteger
    //   1753: invokevirtual intValue : ()I
    //   1756: i2l
    //   1757: lcmp
    //   1758: ifge -> 2096
    //   1761: sipush #-11077
    //   1764: sipush #-7850
    //   1767: invokestatic a : (II)Ljava/lang/String;
    //   1770: iconst_1
    //   1771: ldc burp/Zmcb
    //   1773: invokevirtual getClassLoader : ()Ljava/lang/ClassLoader;
    //   1776: invokestatic forName : (Ljava/lang/String;ZLjava/lang/ClassLoader;)Ljava/lang/Class;
    //   1779: invokevirtual getDeclaredFields : ()[Ljava/lang/reflect/Field;
    //   1782: astore #4
    //   1784: aload #4
    //   1786: arraylength
    //   1787: istore #5
    //   1789: iconst_0
    //   1790: istore #6
    //   1792: iload #6
    //   1794: iload #5
    //   1796: if_icmpge -> 1934
    //   1799: aload #4
    //   1801: iload #6
    //   1803: aaload
    //   1804: astore #7
    //   1806: aload #7
    //   1808: invokevirtual getModifiers : ()I
    //   1811: invokestatic isStatic : (I)Z
    //   1814: ifne -> 1824
    //   1817: goto -> 1927
    //   1820: invokestatic a : (Ljava/lang/Throwable;)Ljava/lang/Throwable;
    //   1823: athrow
    //   1824: aload #7
    //   1826: invokevirtual getType : ()Ljava/lang/Class;
    //   1829: astore #8
    //   1831: aload #8
    //   1833: ifnull -> 1914
    //   1836: aload #8
    //   1838: invokevirtual isPrimitive : ()Z
    //   1841: ifne -> 1914
    //   1844: goto -> 1851
    //   1847: invokestatic a : (Ljava/lang/Throwable;)Ljava/lang/Throwable;
    //   1850: athrow
    //   1851: aload #8
    //   1853: invokevirtual getPackage : ()Ljava/lang/Package;
    //   1856: ifnull -> 1914
    //   1859: goto -> 1866
    //   1862: invokestatic a : (Ljava/lang/Throwable;)Ljava/lang/Throwable;
    //   1865: athrow
    //   1866: aload #8
    //   1868: invokevirtual getPackage : ()Ljava/lang/Package;
    //   1871: invokevirtual getName : ()Ljava/lang/String;
    //   1874: ifnull -> 1914
    //   1877: goto -> 1884
    //   1880: invokestatic a : (Ljava/lang/Throwable;)Ljava/lang/Throwable;
    //   1883: athrow
    //   1884: aload #8
    //   1886: invokevirtual getPackage : ()Ljava/lang/Package;
    //   1889: invokevirtual getName : ()Ljava/lang/String;
    //   1892: sipush #-11082
    //   1895: sipush #-22000
    //   1898: invokestatic a : (II)Ljava/lang/String;
    //   1901: invokevirtual startsWith : (Ljava/lang/String;)Z
    //   1904: ifne -> 1914
    //   1907: goto -> 1914
    //   1910: invokestatic a : (Ljava/lang/Throwable;)Ljava/lang/Throwable;
    //   1913: athrow
    //   1914: aload #7
    //   1916: iconst_1
    //   1917: invokevirtual setAccessible : (Z)V
    //   1920: aload #7
    //   1922: aconst_null
    //   1923: invokevirtual get : (Ljava/lang/Object;)Ljava/lang/Object;
    //   1926: pop
    //   1927: iinc #6, 1
    //   1930: iload_2
    //   1931: ifne -> 1792
    //   1934: sipush #-11091
    //   1937: sipush #6891
    //   1940: invokestatic a : (II)Ljava/lang/String;
    //   1943: invokestatic forName : (Ljava/lang/String;)Ljava/lang/Class;
    //   1946: invokevirtual getDeclaredMethods : ()[Ljava/lang/reflect/Method;
    //   1949: astore #4
    //   1951: aload #4
    //   1953: arraylength
    //   1954: istore #5
    //   1956: iconst_0
    //   1957: istore #6
    //   1959: iload #6
    //   1961: iload #5
    //   1963: if_icmpge -> 2096
    //   1966: aload #4
    //   1968: iload #6
    //   1970: aaload
    //   1971: astore #7
    //   1973: aload #7
    //   1975: invokevirtual getParameterTypes : ()[Ljava/lang/Class;
    //   1978: pop
    //   1979: aload #7
    //   1981: invokevirtual getModifiers : ()I
    //   1984: invokestatic isStatic : (I)Z
    //   1987: ifeq -> 2082
    //   1990: aload #7
    //   1992: invokevirtual getParameterTypes : ()[Ljava/lang/Class;
    //   1995: arraylength
    //   1996: iconst_2
    //   1997: if_icmpne -> 2082
    //   2000: goto -> 2007
    //   2003: invokestatic a : (Ljava/lang/Throwable;)Ljava/lang/Throwable;
    //   2006: athrow
    //   2007: aload #7
    //   2009: invokevirtual getReturnType : ()Ljava/lang/Class;
    //   2012: getstatic java/lang/Void.TYPE : Ljava/lang/Class;
    //   2015: invokevirtual equals : (Ljava/lang/Object;)Z
    //   2018: ifeq -> 2082
    //   2021: goto -> 2028
    //   2024: invokestatic a : (Ljava/lang/Throwable;)Ljava/lang/Throwable;
    //   2027: athrow
    //   2028: aload #7
    //   2030: iconst_1
    //   2031: invokevirtual setAccessible : (Z)V
    //   2034: aload #7
    //   2036: aconst_null
    //   2037: iconst_2
    //   2038: anewarray java/lang/Object
    //   2041: dup
    //   2042: iconst_0
    //   2043: aload_0
    //   2044: aastore
    //   2045: dup
    //   2046: iconst_1
    //   2047: aload_1
    //   2048: ifnonnull -> 2066
    //   2051: goto -> 2058
    //   2054: invokestatic a : (Ljava/lang/Throwable;)Ljava/lang/Throwable;
    //   2057: athrow
    //   2058: aload_1
    //   2059: goto -> 2073
    //   2062: invokestatic a : (Ljava/lang/Throwable;)Ljava/lang/Throwable;
    //   2065: athrow
    //   2066: aload_1
    //   2067: checkcast [B
    //   2070: invokevirtual clone : ()Ljava/lang/Object;
    //   2073: aastore
    //   2074: invokevirtual invoke : (Ljava/lang/Object;[Ljava/lang/Object;)Ljava/lang/Object;
    //   2077: pop
    //   2078: iload_2
    //   2079: ifne -> 2096
    //   2082: iinc #6, 1
    //   2085: iload_2
    //   2086: ifne -> 1959
    //   2089: goto -> 2096
    //   2092: invokestatic a : (Ljava/lang/Throwable;)Ljava/lang/Throwable;
    //   2095: athrow
    //   2096: iconst_0
    //   2097: istore #4
    //   2099: getstatic burp/Zll8.ZZ : Ljava/lang/String;
    //   2102: getstatic burp/Zzh1.Zf : Ljava/lang/Object;
    //   2105: checkcast java/math/BigInteger
    //   2108: invokevirtual intValue : ()I
    //   2111: bipush #32
    //   2113: irem
    //   2114: invokestatic abs : (I)I
    //   2117: invokevirtual charAt : (I)C
    //   2120: getstatic burp/Zgds.ZA : Ljava/lang/String;
    //   2123: getstatic burp/Zgjs.Za : Ljava/lang/Object;
    //   2126: checkcast java/math/BigInteger
    //   2129: invokevirtual intValue : ()I
    //   2132: bipush #32
    //   2134: irem
    //   2135: invokestatic abs : (I)I
    //   2138: invokevirtual charAt : (I)C
    //   2141: if_icmpgt -> 2486
    //   2144: sipush #-11104
    //   2147: sipush #26411
    //   2150: invokestatic a : (II)Ljava/lang/String;
    //   2153: iconst_1
    //   2154: ldc burp/Zmdi
    //   2156: invokevirtual getClassLoader : ()Ljava/lang/ClassLoader;
    //   2159: invokestatic forName : (Ljava/lang/String;ZLjava/lang/ClassLoader;)Ljava/lang/Class;
    //   2162: invokevirtual getDeclaredFields : ()[Ljava/lang/reflect/Field;
    //   2165: astore #5
    //   2167: aload #5
    //   2169: arraylength
    //   2170: istore #6
    //   2172: iconst_0
    //   2173: istore #7
    //   2175: iload #7
    //   2177: iload #6
    //   2179: if_icmpge -> 2317
    //   2182: aload #5
    //   2184: iload #7
    //   2186: aaload
    //   2187: astore #8
    //   2189: aload #8
    //   2191: invokevirtual getModifiers : ()I
    //   2194: invokestatic isStatic : (I)Z
    //   2197: ifne -> 2207
    //   2200: goto -> 2310
    //   2203: invokestatic a : (Ljava/lang/Throwable;)Ljava/lang/Throwable;
    //   2206: athrow
    //   2207: aload #8
    //   2209: invokevirtual getType : ()Ljava/lang/Class;
    //   2212: astore #9
    //   2214: aload #9
    //   2216: ifnull -> 2297
    //   2219: aload #9
    //   2221: invokevirtual isPrimitive : ()Z
    //   2224: ifne -> 2297
    //   2227: goto -> 2234
    //   2230: invokestatic a : (Ljava/lang/Throwable;)Ljava/lang/Throwable;
    //   2233: athrow
    //   2234: aload #9
    //   2236: invokevirtual getPackage : ()Ljava/lang/Package;
    //   2239: ifnull -> 2297
    //   2242: goto -> 2249
    //   2245: invokestatic a : (Ljava/lang/Throwable;)Ljava/lang/Throwable;
    //   2248: athrow
    //   2249: aload #9
    //   2251: invokevirtual getPackage : ()Ljava/lang/Package;
    //   2254: invokevirtual getName : ()Ljava/lang/String;
    //   2257: ifnull -> 2297
    //   2260: goto -> 2267
    //   2263: invokestatic a : (Ljava/lang/Throwable;)Ljava/lang/Throwable;
    //   2266: athrow
    //   2267: aload #9
    //   2269: invokevirtual getPackage : ()Ljava/lang/Package;
    //   2272: invokevirtual getName : ()Ljava/lang/String;
    //   2275: sipush #-11082
    //   2278: sipush #-22000
    //   2281: invokestatic a : (II)Ljava/lang/String;
    //   2284: invokevirtual startsWith : (Ljava/lang/String;)Z
    //   2287: ifne -> 2297
    //   2290: goto -> 2297
    //   2293: invokestatic a : (Ljava/lang/Throwable;)Ljava/lang/Throwable;
    //   2296: athrow
    //   2297: aload #8
    //   2299: iconst_1
    //   2300: invokevirtual setAccessible : (Z)V
    //   2303: aload #8
    //   2305: aconst_null
    //   2306: invokevirtual get : (Ljava/lang/Object;)Ljava/lang/Object;
    //   2309: pop
    //   2310: iinc #7, 1
    //   2313: iload_2
    //   2314: ifne -> 2175
    //   2317: sipush #-11086
    //   2320: sipush #-3712
    //   2323: invokestatic a : (II)Ljava/lang/String;
    //   2326: invokestatic forName : (Ljava/lang/String;)Ljava/lang/Class;
    //   2329: invokevirtual getDeclaredMethods : ()[Ljava/lang/reflect/Method;
    //   2332: astore #5
    //   2334: aload #5
    //   2336: arraylength
    //   2337: istore #6
    //   2339: iconst_0
    //   2340: istore #7
    //   2342: iload #7
    //   2344: iload #6
    //   2346: if_icmpge -> 2483
    //   2349: aload #5
    //   2351: iload #7
    //   2353: aaload
    //   2354: astore #8
    //   2356: aload #8
    //   2358: invokevirtual getParameterTypes : ()[Ljava/lang/Class;
    //   2361: pop
    //   2362: aload #8
    //   2364: invokevirtual getModifiers : ()I
    //   2367: invokestatic isStatic : (I)Z
    //   2370: ifeq -> 2469
    //   2373: aload #8
    //   2375: invokevirtual getParameterTypes : ()[Ljava/lang/Class;
    //   2378: arraylength
    //   2379: iconst_2
    //   2380: if_icmpne -> 2469
    //   2383: goto -> 2390
    //   2386: invokestatic a : (Ljava/lang/Throwable;)Ljava/lang/Throwable;
    //   2389: athrow
    //   2390: aload #8
    //   2392: invokevirtual getReturnType : ()Ljava/lang/Class;
    //   2395: getstatic java/lang/Boolean.TYPE : Ljava/lang/Class;
    //   2398: if_acmpne -> 2469
    //   2401: goto -> 2408
    //   2404: invokestatic a : (Ljava/lang/Throwable;)Ljava/lang/Throwable;
    //   2407: athrow
    //   2408: aload #8
    //   2410: iconst_1
    //   2411: invokevirtual setAccessible : (Z)V
    //   2414: aload #8
    //   2416: aconst_null
    //   2417: iconst_2
    //   2418: anewarray java/lang/Object
    //   2421: dup
    //   2422: iconst_0
    //   2423: aload_0
    //   2424: aastore
    //   2425: dup
    //   2426: iconst_1
    //   2427: aload_1
    //   2428: ifnonnull -> 2446
    //   2431: goto -> 2438
    //   2434: invokestatic a : (Ljava/lang/Throwable;)Ljava/lang/Throwable;
    //   2437: athrow
    //   2438: aload_1
    //   2439: goto -> 2453
    //   2442: invokestatic a : (Ljava/lang/Throwable;)Ljava/lang/Throwable;
    //   2445: athrow
    //   2446: aload_1
    //   2447: checkcast [B
    //   2450: invokevirtual clone : ()Ljava/lang/Object;
    //   2453: aastore
    //   2454: invokevirtual invoke : (Ljava/lang/Object;[Ljava/lang/Object;)Ljava/lang/Object;
    //   2457: checkcast java/lang/Boolean
    //   2460: invokevirtual booleanValue : ()Z
    //   2463: istore #4
    //   2465: iload_2
    //   2466: ifne -> 2483
    //   2469: iinc #7, 1
    //   2472: iload_2
    //   2473: ifne -> 2342
    //   2476: goto -> 2483
    //   2479: invokestatic a : (Ljava/lang/Throwable;)Ljava/lang/Throwable;
    //   2482: athrow
    //   2483: goto -> 2825
    //   2486: sipush #-11100
    //   2489: sipush #-10038
    //   2492: invokestatic a : (II)Ljava/lang/String;
    //   2495: iconst_1
    //   2496: ldc burp/Zlsw
    //   2498: invokevirtual getClassLoader : ()Ljava/lang/ClassLoader;
    //   2501: invokestatic forName : (Ljava/lang/String;ZLjava/lang/ClassLoader;)Ljava/lang/Class;
    //   2504: invokevirtual getDeclaredFields : ()[Ljava/lang/reflect/Field;
    //   2507: astore #5
    //   2509: aload #5
    //   2511: arraylength
    //   2512: istore #6
    //   2514: iconst_0
    //   2515: istore #7
    //   2517: iload #7
    //   2519: iload #6
    //   2521: if_icmpge -> 2659
    //   2524: aload #5
    //   2526: iload #7
    //   2528: aaload
    //   2529: astore #8
    //   2531: aload #8
    //   2533: invokevirtual getModifiers : ()I
    //   2536: invokestatic isStatic : (I)Z
    //   2539: ifne -> 2549
    //   2542: goto -> 2652
    //   2545: invokestatic a : (Ljava/lang/Throwable;)Ljava/lang/Throwable;
    //   2548: athrow
    //   2549: aload #8
    //   2551: invokevirtual getType : ()Ljava/lang/Class;
    //   2554: astore #9
    //   2556: aload #9
    //   2558: ifnull -> 2639
    //   2561: aload #9
    //   2563: invokevirtual isPrimitive : ()Z
    //   2566: ifne -> 2639
    //   2569: goto -> 2576
    //   2572: invokestatic a : (Ljava/lang/Throwable;)Ljava/lang/Throwable;
    //   2575: athrow
    //   2576: aload #9
    //   2578: invokevirtual getPackage : ()Ljava/lang/Package;
    //   2581: ifnull -> 2639
    //   2584: goto -> 2591
    //   2587: invokestatic a : (Ljava/lang/Throwable;)Ljava/lang/Throwable;
    //   2590: athrow
    //   2591: aload #9
    //   2593: invokevirtual getPackage : ()Ljava/lang/Package;
    //   2596: invokevirtual getName : ()Ljava/lang/String;
    //   2599: ifnull -> 2639
    //   2602: goto -> 2609
    //   2605: invokestatic a : (Ljava/lang/Throwable;)Ljava/lang/Throwable;
    //   2608: athrow
    //   2609: aload #9
    //   2611: invokevirtual getPackage : ()Ljava/lang/Package;
    //   2614: invokevirtual getName : ()Ljava/lang/String;
    //   2617: sipush #-11082
    //   2620: sipush #-22000
    //   2623: invokestatic a : (II)Ljava/lang/String;
    //   2626: invokevirtual startsWith : (Ljava/lang/String;)Z
    //   2629: ifne -> 2639
    //   2632: goto -> 2639
    //   2635: invokestatic a : (Ljava/lang/Throwable;)Ljava/lang/Throwable;
    //   2638: athrow
    //   2639: aload #8
    //   2641: iconst_1
    //   2642: invokevirtual setAccessible : (Z)V
    //   2645: aload #8
    //   2647: aconst_null
    //   2648: invokevirtual get : (Ljava/lang/Object;)Ljava/lang/Object;
    //   2651: pop
    //   2652: iinc #7, 1
    //   2655: iload_2
    //   2656: ifne -> 2517
    //   2659: sipush #-11103
    //   2662: sipush #30737
    //   2665: invokestatic a : (II)Ljava/lang/String;
    //   2668: invokestatic forName : (Ljava/lang/String;)Ljava/lang/Class;
    //   2671: invokevirtual getDeclaredMethods : ()[Ljava/lang/reflect/Method;
    //   2674: astore #5
    //   2676: aload #5
    //   2678: arraylength
    //   2679: istore #6
    //   2681: iconst_0
    //   2682: istore #7
    //   2684: iload #7
    //   2686: iload #6
    //   2688: if_icmpge -> 2825
    //   2691: aload #5
    //   2693: iload #7
    //   2695: aaload
    //   2696: astore #8
    //   2698: aload #8
    //   2700: invokevirtual getParameterTypes : ()[Ljava/lang/Class;
    //   2703: pop
    //   2704: aload #8
    //   2706: invokevirtual getModifiers : ()I
    //   2709: invokestatic isStatic : (I)Z
    //   2712: ifeq -> 2811
    //   2715: aload #8
    //   2717: invokevirtual getParameterTypes : ()[Ljava/lang/Class;
    //   2720: arraylength
    //   2721: iconst_2
    //   2722: if_icmpne -> 2811
    //   2725: goto -> 2732
    //   2728: invokestatic a : (Ljava/lang/Throwable;)Ljava/lang/Throwable;
    //   2731: athrow
    //   2732: aload #8
    //   2734: invokevirtual getReturnType : ()Ljava/lang/Class;
    //   2737: getstatic java/lang/Boolean.TYPE : Ljava/lang/Class;
    //   2740: if_acmpne -> 2811
    //   2743: goto -> 2750
    //   2746: invokestatic a : (Ljava/lang/Throwable;)Ljava/lang/Throwable;
    //   2749: athrow
    //   2750: aload #8
    //   2752: iconst_1
    //   2753: invokevirtual setAccessible : (Z)V
    //   2756: aload #8
    //   2758: aconst_null
    //   2759: iconst_2
    //   2760: anewarray java/lang/Object
    //   2763: dup
    //   2764: iconst_0
    //   2765: aload_0
    //   2766: aastore
    //   2767: dup
    //   2768: iconst_1
    //   2769: aload_1
    //   2770: ifnonnull -> 2788
    //   2773: goto -> 2780
    //   2776: invokestatic a : (Ljava/lang/Throwable;)Ljava/lang/Throwable;
    //   2779: athrow
    //   2780: aload_1
    //   2781: goto -> 2795
    //   2784: invokestatic a : (Ljava/lang/Throwable;)Ljava/lang/Throwable;
    //   2787: athrow
    //   2788: aload_1
    //   2789: checkcast [B
    //   2792: invokevirtual clone : ()Ljava/lang/Object;
    //   2795: aastore
    //   2796: invokevirtual invoke : (Ljava/lang/Object;[Ljava/lang/Object;)Ljava/lang/Object;
    //   2799: checkcast java/lang/Boolean
    //   2802: invokevirtual booleanValue : ()Z
    //   2805: istore #4
    //   2807: iload_2
    //   2808: ifne -> 2825
    //   2811: iinc #7, 1
    //   2814: iload_2
    //   2815: ifne -> 2684
    //   2818: goto -> 2825
    //   2821: invokestatic a : (Ljava/lang/Throwable;)Ljava/lang/Throwable;
    //   2824: athrow
    //   2825: iload #4
    //   2827: ifeq -> 2833
    //   2830: iload #4
    //   2832: ireturn
    //   2833: getstatic burp/Zb38.Zr : Ljava/lang/String;
    //   2836: getstatic burp/Zxf8.Zz : Ljava/lang/Object;
    //   2839: checkcast java/math/BigInteger
    //   2842: invokevirtual intValue : ()I
    //   2845: bipush #32
    //   2847: irem
    //   2848: invokestatic abs : (I)I
    //   2851: invokevirtual charAt : (I)C
    //   2854: getstatic burp/Zxx4.Zq : Ljava/lang/String;
    //   2857: getstatic burp/Ztgj.ZY : Ljava/lang/Object;
    //   2860: checkcast java/math/BigInteger
    //   2863: invokevirtual intValue : ()I
    //   2866: bipush #32
    //   2868: irem
    //   2869: invokestatic abs : (I)I
    //   2872: invokevirtual charAt : (I)C
    //   2875: if_icmpgt -> 3221
    //   2878: sipush #-11092
    //   2881: sipush #-30002
    //   2884: invokestatic a : (II)Ljava/lang/String;
    //   2887: iconst_1
    //   2888: ldc burp/Zegv
    //   2890: invokevirtual getClassLoader : ()Ljava/lang/ClassLoader;
    //   2893: invokestatic forName : (Ljava/lang/String;ZLjava/lang/ClassLoader;)Ljava/lang/Class;
    //   2896: invokevirtual getDeclaredFields : ()[Ljava/lang/reflect/Field;
    //   2899: astore #5
    //   2901: aload #5
    //   2903: arraylength
    //   2904: istore #6
    //   2906: iconst_0
    //   2907: istore #7
    //   2909: iload #7
    //   2911: iload #6
    //   2913: if_icmpge -> 3051
    //   2916: aload #5
    //   2918: iload #7
    //   2920: aaload
    //   2921: astore #8
    //   2923: aload #8
    //   2925: invokevirtual getModifiers : ()I
    //   2928: invokestatic isStatic : (I)Z
    //   2931: ifne -> 2941
    //   2934: goto -> 3044
    //   2937: invokestatic a : (Ljava/lang/Throwable;)Ljava/lang/Throwable;
    //   2940: athrow
    //   2941: aload #8
    //   2943: invokevirtual getType : ()Ljava/lang/Class;
    //   2946: astore #9
    //   2948: aload #9
    //   2950: ifnull -> 3031
    //   2953: aload #9
    //   2955: invokevirtual isPrimitive : ()Z
    //   2958: ifne -> 3031
    //   2961: goto -> 2968
    //   2964: invokestatic a : (Ljava/lang/Throwable;)Ljava/lang/Throwable;
    //   2967: athrow
    //   2968: aload #9
    //   2970: invokevirtual getPackage : ()Ljava/lang/Package;
    //   2973: ifnull -> 3031
    //   2976: goto -> 2983
    //   2979: invokestatic a : (Ljava/lang/Throwable;)Ljava/lang/Throwable;
    //   2982: athrow
    //   2983: aload #9
    //   2985: invokevirtual getPackage : ()Ljava/lang/Package;
    //   2988: invokevirtual getName : ()Ljava/lang/String;
    //   2991: ifnull -> 3031
    //   2994: goto -> 3001
    //   2997: invokestatic a : (Ljava/lang/Throwable;)Ljava/lang/Throwable;
    //   3000: athrow
    //   3001: aload #9
    //   3003: invokevirtual getPackage : ()Ljava/lang/Package;
    //   3006: invokevirtual getName : ()Ljava/lang/String;
    //   3009: sipush #-11082
    //   3012: sipush #-22000
    //   3015: invokestatic a : (II)Ljava/lang/String;
    //   3018: invokevirtual startsWith : (Ljava/lang/String;)Z
    //   3021: ifne -> 3031
    //   3024: goto -> 3031
    //   3027: invokestatic a : (Ljava/lang/Throwable;)Ljava/lang/Throwable;
    //   3030: athrow
    //   3031: aload #8
    //   3033: iconst_1
    //   3034: invokevirtual setAccessible : (Z)V
    //   3037: aload #8
    //   3039: aconst_null
    //   3040: invokevirtual get : (Ljava/lang/Object;)Ljava/lang/Object;
    //   3043: pop
    //   3044: iinc #7, 1
    //   3047: iload_2
    //   3048: ifne -> 2909
    //   3051: sipush #-11090
    //   3054: sipush #-16474
    //   3057: invokestatic a : (II)Ljava/lang/String;
    //   3060: invokestatic forName : (Ljava/lang/String;)Ljava/lang/Class;
    //   3063: invokevirtual getDeclaredMethods : ()[Ljava/lang/reflect/Method;
    //   3066: astore #5
    //   3068: aload #5
    //   3070: arraylength
    //   3071: istore #6
    //   3073: iconst_0
    //   3074: istore #7
    //   3076: iload #7
    //   3078: iload #6
    //   3080: if_icmpge -> 3217
    //   3083: aload #5
    //   3085: iload #7
    //   3087: aaload
    //   3088: astore #8
    //   3090: aload #8
    //   3092: invokevirtual getParameterTypes : ()[Ljava/lang/Class;
    //   3095: pop
    //   3096: aload #8
    //   3098: invokevirtual getModifiers : ()I
    //   3101: invokestatic isStatic : (I)Z
    //   3104: ifeq -> 3203
    //   3107: aload #8
    //   3109: invokevirtual getParameterTypes : ()[Ljava/lang/Class;
    //   3112: arraylength
    //   3113: iconst_2
    //   3114: if_icmpne -> 3203
    //   3117: goto -> 3124
    //   3120: invokestatic a : (Ljava/lang/Throwable;)Ljava/lang/Throwable;
    //   3123: athrow
    //   3124: aload #8
    //   3126: invokevirtual getReturnType : ()Ljava/lang/Class;
    //   3129: getstatic java/lang/Boolean.TYPE : Ljava/lang/Class;
    //   3132: if_acmpne -> 3203
    //   3135: goto -> 3142
    //   3138: invokestatic a : (Ljava/lang/Throwable;)Ljava/lang/Throwable;
    //   3141: athrow
    //   3142: aload #8
    //   3144: iconst_1
    //   3145: invokevirtual setAccessible : (Z)V
    //   3148: aload #8
    //   3150: aconst_null
    //   3151: iconst_2
    //   3152: anewarray java/lang/Object
    //   3155: dup
    //   3156: iconst_0
    //   3157: aload_0
    //   3158: aastore
    //   3159: dup
    //   3160: iconst_1
    //   3161: aload_1
    //   3162: ifnonnull -> 3180
    //   3165: goto -> 3172
    //   3168: invokestatic a : (Ljava/lang/Throwable;)Ljava/lang/Throwable;
    //   3171: athrow
    //   3172: aload_1
    //   3173: goto -> 3187
    //   3176: invokestatic a : (Ljava/lang/Throwable;)Ljava/lang/Throwable;
    //   3179: athrow
    //   3180: aload_1
    //   3181: checkcast [B
    //   3184: invokevirtual clone : ()Ljava/lang/Object;
    //   3187: aastore
    //   3188: invokevirtual invoke : (Ljava/lang/Object;[Ljava/lang/Object;)Ljava/lang/Object;
    //   3191: checkcast java/lang/Boolean
    //   3194: invokevirtual booleanValue : ()Z
    //   3197: istore #4
    //   3199: iload_2
    //   3200: ifne -> 3217
    //   3203: iinc #7, 1
    //   3206: iload_2
    //   3207: ifne -> 3076
    //   3210: goto -> 3217
    //   3213: invokestatic a : (Ljava/lang/Throwable;)Ljava/lang/Throwable;
    //   3216: athrow
    //   3217: iload_2
    //   3218: ifne -> 3560
    //   3221: sipush #-11087
    //   3224: sipush #26803
    //   3227: invokestatic a : (II)Ljava/lang/String;
    //   3230: iconst_1
    //   3231: ldc burp/Zkcd
    //   3233: invokevirtual getClassLoader : ()Ljava/lang/ClassLoader;
    //   3236: invokestatic forName : (Ljava/lang/String;ZLjava/lang/ClassLoader;)Ljava/lang/Class;
    //   3239: invokevirtual getDeclaredFields : ()[Ljava/lang/reflect/Field;
    //   3242: astore #5
    //   3244: aload #5
    //   3246: arraylength
    //   3247: istore #6
    //   3249: iconst_0
    //   3250: istore #7
    //   3252: iload #7
    //   3254: iload #6
    //   3256: if_icmpge -> 3394
    //   3259: aload #5
    //   3261: iload #7
    //   3263: aaload
    //   3264: astore #8
    //   3266: aload #8
    //   3268: invokevirtual getModifiers : ()I
    //   3271: invokestatic isStatic : (I)Z
    //   3274: ifne -> 3284
    //   3277: goto -> 3387
    //   3280: invokestatic a : (Ljava/lang/Throwable;)Ljava/lang/Throwable;
    //   3283: athrow
    //   3284: aload #8
    //   3286: invokevirtual getType : ()Ljava/lang/Class;
    //   3289: astore #9
    //   3291: aload #9
    //   3293: ifnull -> 3374
    //   3296: aload #9
    //   3298: invokevirtual isPrimitive : ()Z
    //   3301: ifne -> 3374
    //   3304: goto -> 3311
    //   3307: invokestatic a : (Ljava/lang/Throwable;)Ljava/lang/Throwable;
    //   3310: athrow
    //   3311: aload #9
    //   3313: invokevirtual getPackage : ()Ljava/lang/Package;
    //   3316: ifnull -> 3374
    //   3319: goto -> 3326
    //   3322: invokestatic a : (Ljava/lang/Throwable;)Ljava/lang/Throwable;
    //   3325: athrow
    //   3326: aload #9
    //   3328: invokevirtual getPackage : ()Ljava/lang/Package;
    //   3331: invokevirtual getName : ()Ljava/lang/String;
    //   3334: ifnull -> 3374
    //   3337: goto -> 3344
    //   3340: invokestatic a : (Ljava/lang/Throwable;)Ljava/lang/Throwable;
    //   3343: athrow
    //   3344: aload #9
    //   3346: invokevirtual getPackage : ()Ljava/lang/Package;
    //   3349: invokevirtual getName : ()Ljava/lang/String;
    //   3352: sipush #-11082
    //   3355: sipush #-22000
    //   3358: invokestatic a : (II)Ljava/lang/String;
    //   3361: invokevirtual startsWith : (Ljava/lang/String;)Z
    //   3364: ifne -> 3374
    //   3367: goto -> 3374
    //   3370: invokestatic a : (Ljava/lang/Throwable;)Ljava/lang/Throwable;
    //   3373: athrow
    //   3374: aload #8
    //   3376: iconst_1
    //   3377: invokevirtual setAccessible : (Z)V
    //   3380: aload #8
    //   3382: aconst_null
    //   3383: invokevirtual get : (Ljava/lang/Object;)Ljava/lang/Object;
    //   3386: pop
    //   3387: iinc #7, 1
    //   3390: iload_2
    //   3391: ifne -> 3252
    //   3394: sipush #-11093
    //   3397: sipush #-12507
    //   3400: invokestatic a : (II)Ljava/lang/String;
    //   3403: invokestatic forName : (Ljava/lang/String;)Ljava/lang/Class;
    //   3406: invokevirtual getDeclaredMethods : ()[Ljava/lang/reflect/Method;
    //   3409: astore #5
    //   3411: aload #5
    //   3413: arraylength
    //   3414: istore #6
    //   3416: iconst_0
    //   3417: istore #7
    //   3419: iload #7
    //   3421: iload #6
    //   3423: if_icmpge -> 3560
    //   3426: aload #5
    //   3428: iload #7
    //   3430: aaload
    //   3431: astore #8
    //   3433: aload #8
    //   3435: invokevirtual getParameterTypes : ()[Ljava/lang/Class;
    //   3438: pop
    //   3439: aload #8
    //   3441: invokevirtual getModifiers : ()I
    //   3444: invokestatic isStatic : (I)Z
    //   3447: ifeq -> 3546
    //   3450: aload #8
    //   3452: invokevirtual getParameterTypes : ()[Ljava/lang/Class;
    //   3455: arraylength
    //   3456: iconst_2
    //   3457: if_icmpne -> 3546
    //   3460: goto -> 3467
    //   3463: invokestatic a : (Ljava/lang/Throwable;)Ljava/lang/Throwable;
    //   3466: athrow
    //   3467: aload #8
    //   3469: invokevirtual getReturnType : ()Ljava/lang/Class;
    //   3472: getstatic java/lang/Boolean.TYPE : Ljava/lang/Class;
    //   3475: if_acmpne -> 3546
    //   3478: goto -> 3485
    //   3481: invokestatic a : (Ljava/lang/Throwable;)Ljava/lang/Throwable;
    //   3484: athrow
    //   3485: aload #8
    //   3487: iconst_1
    //   3488: invokevirtual setAccessible : (Z)V
    //   3491: aload #8
    //   3493: aconst_null
    //   3494: iconst_2
    //   3495: anewarray java/lang/Object
    //   3498: dup
    //   3499: iconst_0
    //   3500: aload_0
    //   3501: aastore
    //   3502: dup
    //   3503: iconst_1
    //   3504: aload_1
    //   3505: ifnonnull -> 3523
    //   3508: goto -> 3515
    //   3511: invokestatic a : (Ljava/lang/Throwable;)Ljava/lang/Throwable;
    //   3514: athrow
    //   3515: aload_1
    //   3516: goto -> 3530
    //   3519: invokestatic a : (Ljava/lang/Throwable;)Ljava/lang/Throwable;
    //   3522: athrow
    //   3523: aload_1
    //   3524: checkcast [B
    //   3527: invokevirtual clone : ()Ljava/lang/Object;
    //   3530: aastore
    //   3531: invokevirtual invoke : (Ljava/lang/Object;[Ljava/lang/Object;)Ljava/lang/Object;
    //   3534: checkcast java/lang/Boolean
    //   3537: invokevirtual booleanValue : ()Z
    //   3540: istore #4
    //   3542: iload_2
    //   3543: ifne -> 3560
    //   3546: iinc #7, 1
    //   3549: iload_2
    //   3550: ifne -> 3419
    //   3553: goto -> 3560
    //   3556: invokestatic a : (Ljava/lang/Throwable;)Ljava/lang/Throwable;
    //   3559: athrow
    //   3560: iload #4
    //   3562: ifeq -> 3568
    //   3565: iload #4
    //   3567: ireturn
    //   3568: getstatic burp/Zle6.Zh : Ljava/lang/String;
    //   3571: getstatic burp/Zb2p.ZQ : Ljava/lang/Object;
    //   3574: checkcast java/math/BigInteger
    //   3577: invokevirtual intValue : ()I
    //   3580: bipush #32
    //   3582: irem
    //   3583: invokestatic abs : (I)I
    //   3586: invokevirtual charAt : (I)C
    //   3589: getstatic burp/Zgja.Zb : Ljava/lang/String;
    //   3592: getstatic burp/Zxd4.Zt : Ljava/lang/Object;
    //   3595: checkcast java/math/BigInteger
    //   3598: invokevirtual intValue : ()I
    //   3601: bipush #32
    //   3603: irem
    //   3604: invokestatic abs : (I)I
    //   3607: invokevirtual charAt : (I)C
    //   3610: if_icmple -> 3956
    //   3613: sipush #-11097
    //   3616: sipush #12956
    //   3619: invokestatic a : (II)Ljava/lang/String;
    //   3622: iconst_1
    //   3623: ldc burp/Zg5
    //   3625: invokevirtual getClassLoader : ()Ljava/lang/ClassLoader;
    //   3628: invokestatic forName : (Ljava/lang/String;ZLjava/lang/ClassLoader;)Ljava/lang/Class;
    //   3631: invokevirtual getDeclaredFields : ()[Ljava/lang/reflect/Field;
    //   3634: astore #5
    //   3636: aload #5
    //   3638: arraylength
    //   3639: istore #6
    //   3641: iconst_0
    //   3642: istore #7
    //   3644: iload #7
    //   3646: iload #6
    //   3648: if_icmpge -> 3786
    //   3651: aload #5
    //   3653: iload #7
    //   3655: aaload
    //   3656: astore #8
    //   3658: aload #8
    //   3660: invokevirtual getModifiers : ()I
    //   3663: invokestatic isStatic : (I)Z
    //   3666: ifne -> 3676
    //   3669: goto -> 3779
    //   3672: invokestatic a : (Ljava/lang/Throwable;)Ljava/lang/Throwable;
    //   3675: athrow
    //   3676: aload #8
    //   3678: invokevirtual getType : ()Ljava/lang/Class;
    //   3681: astore #9
    //   3683: aload #9
    //   3685: ifnull -> 3766
    //   3688: aload #9
    //   3690: invokevirtual isPrimitive : ()Z
    //   3693: ifne -> 3766
    //   3696: goto -> 3703
    //   3699: invokestatic a : (Ljava/lang/Throwable;)Ljava/lang/Throwable;
    //   3702: athrow
    //   3703: aload #9
    //   3705: invokevirtual getPackage : ()Ljava/lang/Package;
    //   3708: ifnull -> 3766
    //   3711: goto -> 3718
    //   3714: invokestatic a : (Ljava/lang/Throwable;)Ljava/lang/Throwable;
    //   3717: athrow
    //   3718: aload #9
    //   3720: invokevirtual getPackage : ()Ljava/lang/Package;
    //   3723: invokevirtual getName : ()Ljava/lang/String;
    //   3726: ifnull -> 3766
    //   3729: goto -> 3736
    //   3732: invokestatic a : (Ljava/lang/Throwable;)Ljava/lang/Throwable;
    //   3735: athrow
    //   3736: aload #9
    //   3738: invokevirtual getPackage : ()Ljava/lang/Package;
    //   3741: invokevirtual getName : ()Ljava/lang/String;
    //   3744: sipush #-11082
    //   3747: sipush #-22000
    //   3750: invokestatic a : (II)Ljava/lang/String;
    //   3753: invokevirtual startsWith : (Ljava/lang/String;)Z
    //   3756: ifne -> 3766
    //   3759: goto -> 3766
    //   3762: invokestatic a : (Ljava/lang/Throwable;)Ljava/lang/Throwable;
    //   3765: athrow
    //   3766: aload #8
    //   3768: iconst_1
    //   3769: invokevirtual setAccessible : (Z)V
    //   3772: aload #8
    //   3774: aconst_null
    //   3775: invokevirtual get : (Ljava/lang/Object;)Ljava/lang/Object;
    //   3778: pop
    //   3779: iinc #7, 1
    //   3782: iload_2
    //   3783: ifne -> 3644
    //   3786: sipush #-11095
    //   3789: sipush #-21434
    //   3792: invokestatic a : (II)Ljava/lang/String;
    //   3795: invokestatic forName : (Ljava/lang/String;)Ljava/lang/Class;
    //   3798: invokevirtual getDeclaredMethods : ()[Ljava/lang/reflect/Method;
    //   3801: astore #5
    //   3803: aload #5
    //   3805: arraylength
    //   3806: istore #6
    //   3808: iconst_0
    //   3809: istore #7
    //   3811: iload #7
    //   3813: iload #6
    //   3815: if_icmpge -> 3952
    //   3818: aload #5
    //   3820: iload #7
    //   3822: aaload
    //   3823: astore #8
    //   3825: aload #8
    //   3827: invokevirtual getParameterTypes : ()[Ljava/lang/Class;
    //   3830: pop
    //   3831: aload #8
    //   3833: invokevirtual getModifiers : ()I
    //   3836: invokestatic isStatic : (I)Z
    //   3839: ifeq -> 3938
    //   3842: aload #8
    //   3844: invokevirtual getParameterTypes : ()[Ljava/lang/Class;
    //   3847: arraylength
    //   3848: iconst_2
    //   3849: if_icmpne -> 3938
    //   3852: goto -> 3859
    //   3855: invokestatic a : (Ljava/lang/Throwable;)Ljava/lang/Throwable;
    //   3858: athrow
    //   3859: aload #8
    //   3861: invokevirtual getReturnType : ()Ljava/lang/Class;
    //   3864: getstatic java/lang/Boolean.TYPE : Ljava/lang/Class;
    //   3867: if_acmpne -> 3938
    //   3870: goto -> 3877
    //   3873: invokestatic a : (Ljava/lang/Throwable;)Ljava/lang/Throwable;
    //   3876: athrow
    //   3877: aload #8
    //   3879: iconst_1
    //   3880: invokevirtual setAccessible : (Z)V
    //   3883: aload #8
    //   3885: aconst_null
    //   3886: iconst_2
    //   3887: anewarray java/lang/Object
    //   3890: dup
    //   3891: iconst_0
    //   3892: aload_0
    //   3893: aastore
    //   3894: dup
    //   3895: iconst_1
    //   3896: aload_1
    //   3897: ifnonnull -> 3915
    //   3900: goto -> 3907
    //   3903: invokestatic a : (Ljava/lang/Throwable;)Ljava/lang/Throwable;
    //   3906: athrow
    //   3907: aload_1
    //   3908: goto -> 3922
    //   3911: invokestatic a : (Ljava/lang/Throwable;)Ljava/lang/Throwable;
    //   3914: athrow
    //   3915: aload_1
    //   3916: checkcast [B
    //   3919: invokevirtual clone : ()Ljava/lang/Object;
    //   3922: aastore
    //   3923: invokevirtual invoke : (Ljava/lang/Object;[Ljava/lang/Object;)Ljava/lang/Object;
    //   3926: checkcast java/lang/Boolean
    //   3929: invokevirtual booleanValue : ()Z
    //   3932: istore #4
    //   3934: iload_2
    //   3935: ifne -> 3952
    //   3938: iinc #7, 1
    //   3941: iload_2
    //   3942: ifne -> 3811
    //   3945: goto -> 3952
    //   3948: invokestatic a : (Ljava/lang/Throwable;)Ljava/lang/Throwable;
    //   3951: athrow
    //   3952: iload_2
    //   3953: ifne -> 4295
    //   3956: sipush #-11078
    //   3959: sipush #14197
    //   3962: invokestatic a : (II)Ljava/lang/String;
    //   3965: iconst_1
    //   3966: ldc burp/Zr4z
    //   3968: invokevirtual getClassLoader : ()Ljava/lang/ClassLoader;
    //   3971: invokestatic forName : (Ljava/lang/String;ZLjava/lang/ClassLoader;)Ljava/lang/Class;
    //   3974: invokevirtual getDeclaredFields : ()[Ljava/lang/reflect/Field;
    //   3977: astore #5
    //   3979: aload #5
    //   3981: arraylength
    //   3982: istore #6
    //   3984: iconst_0
    //   3985: istore #7
    //   3987: iload #7
    //   3989: iload #6
    //   3991: if_icmpge -> 4129
    //   3994: aload #5
    //   3996: iload #7
    //   3998: aaload
    //   3999: astore #8
    //   4001: aload #8
    //   4003: invokevirtual getModifiers : ()I
    //   4006: invokestatic isStatic : (I)Z
    //   4009: ifne -> 4019
    //   4012: goto -> 4122
    //   4015: invokestatic a : (Ljava/lang/Throwable;)Ljava/lang/Throwable;
    //   4018: athrow
    //   4019: aload #8
    //   4021: invokevirtual getType : ()Ljava/lang/Class;
    //   4024: astore #9
    //   4026: aload #9
    //   4028: ifnull -> 4109
    //   4031: aload #9
    //   4033: invokevirtual isPrimitive : ()Z
    //   4036: ifne -> 4109
    //   4039: goto -> 4046
    //   4042: invokestatic a : (Ljava/lang/Throwable;)Ljava/lang/Throwable;
    //   4045: athrow
    //   4046: aload #9
    //   4048: invokevirtual getPackage : ()Ljava/lang/Package;
    //   4051: ifnull -> 4109
    //   4054: goto -> 4061
    //   4057: invokestatic a : (Ljava/lang/Throwable;)Ljava/lang/Throwable;
    //   4060: athrow
    //   4061: aload #9
    //   4063: invokevirtual getPackage : ()Ljava/lang/Package;
    //   4066: invokevirtual getName : ()Ljava/lang/String;
    //   4069: ifnull -> 4109
    //   4072: goto -> 4079
    //   4075: invokestatic a : (Ljava/lang/Throwable;)Ljava/lang/Throwable;
    //   4078: athrow
    //   4079: aload #9
    //   4081: invokevirtual getPackage : ()Ljava/lang/Package;
    //   4084: invokevirtual getName : ()Ljava/lang/String;
    //   4087: sipush #-11082
    //   4090: sipush #-22000
    //   4093: invokestatic a : (II)Ljava/lang/String;
    //   4096: invokevirtual startsWith : (Ljava/lang/String;)Z
    //   4099: ifne -> 4109
    //   4102: goto -> 4109
    //   4105: invokestatic a : (Ljava/lang/Throwable;)Ljava/lang/Throwable;
    //   4108: athrow
    //   4109: aload #8
    //   4111: iconst_1
    //   4112: invokevirtual setAccessible : (Z)V
    //   4115: aload #8
    //   4117: aconst_null
    //   4118: invokevirtual get : (Ljava/lang/Object;)Ljava/lang/Object;
    //   4121: pop
    //   4122: iinc #7, 1
    //   4125: iload_2
    //   4126: ifne -> 3987
    //   4129: sipush #-11080
    //   4132: sipush #20997
    //   4135: invokestatic a : (II)Ljava/lang/String;
    //   4138: invokestatic forName : (Ljava/lang/String;)Ljava/lang/Class;
    //   4141: invokevirtual getDeclaredMethods : ()[Ljava/lang/reflect/Method;
    //   4144: astore #5
    //   4146: aload #5
    //   4148: arraylength
    //   4149: istore #6
    //   4151: iconst_0
    //   4152: istore #7
    //   4154: iload #7
    //   4156: iload #6
    //   4158: if_icmpge -> 4295
    //   4161: aload #5
    //   4163: iload #7
    //   4165: aaload
    //   4166: astore #8
    //   4168: aload #8
    //   4170: invokevirtual getParameterTypes : ()[Ljava/lang/Class;
    //   4173: pop
    //   4174: aload #8
    //   4176: invokevirtual getModifiers : ()I
    //   4179: invokestatic isStatic : (I)Z
    //   4182: ifeq -> 4281
    //   4185: aload #8
    //   4187: invokevirtual getParameterTypes : ()[Ljava/lang/Class;
    //   4190: arraylength
    //   4191: iconst_2
    //   4192: if_icmpne -> 4281
    //   4195: goto -> 4202
    //   4198: invokestatic a : (Ljava/lang/Throwable;)Ljava/lang/Throwable;
    //   4201: athrow
    //   4202: aload #8
    //   4204: invokevirtual getReturnType : ()Ljava/lang/Class;
    //   4207: getstatic java/lang/Boolean.TYPE : Ljava/lang/Class;
    //   4210: if_acmpne -> 4281
    //   4213: goto -> 4220
    //   4216: invokestatic a : (Ljava/lang/Throwable;)Ljava/lang/Throwable;
    //   4219: athrow
    //   4220: aload #8
    //   4222: iconst_1
    //   4223: invokevirtual setAccessible : (Z)V
    //   4226: aload #8
    //   4228: aconst_null
    //   4229: iconst_2
    //   4230: anewarray java/lang/Object
    //   4233: dup
    //   4234: iconst_0
    //   4235: aload_0
    //   4236: aastore
    //   4237: dup
    //   4238: iconst_1
    //   4239: aload_1
    //   4240: ifnonnull -> 4258
    //   4243: goto -> 4250
    //   4246: invokestatic a : (Ljava/lang/Throwable;)Ljava/lang/Throwable;
    //   4249: athrow
    //   4250: aload_1
    //   4251: goto -> 4265
    //   4254: invokestatic a : (Ljava/lang/Throwable;)Ljava/lang/Throwable;
    //   4257: athrow
    //   4258: aload_1
    //   4259: checkcast [B
    //   4262: invokevirtual clone : ()Ljava/lang/Object;
    //   4265: aastore
    //   4266: invokevirtual invoke : (Ljava/lang/Object;[Ljava/lang/Object;)Ljava/lang/Object;
    //   4269: checkcast java/lang/Boolean
    //   4272: invokevirtual booleanValue : ()Z
    //   4275: istore #4
    //   4277: iload_2
    //   4278: ifne -> 4295
    //   4281: iinc #7, 1
    //   4284: iload_2
    //   4285: ifne -> 4154
    //   4288: goto -> 4295
    //   4291: invokestatic a : (Ljava/lang/Throwable;)Ljava/lang/Throwable;
    //   4294: athrow
    //   4295: iload #4
    //   4297: ifeq -> 4303
    //   4300: iload #4
    //   4302: ireturn
    //   4303: getstatic burp/Zmu6.Zl : Ljava/lang/String;
    //   4306: getstatic burp/Ztsj.Zc : Ljava/lang/Object;
    //   4309: checkcast java/math/BigInteger
    //   4312: invokevirtual intValue : ()I
    //   4315: bipush #32
    //   4317: irem
    //   4318: invokestatic abs : (I)I
    //   4321: invokevirtual charAt : (I)C
    //   4324: getstatic burp/Zrn0.Zd : Ljava/lang/String;
    //   4327: getstatic burp/Zkqx.ZW : Ljava/lang/Object;
    //   4330: checkcast java/math/BigInteger
    //   4333: invokevirtual intValue : ()I
    //   4336: bipush #32
    //   4338: irem
    //   4339: invokestatic abs : (I)I
    //   4342: invokevirtual charAt : (I)C
    //   4345: if_icmple -> 4691
    //   4348: sipush #-11096
    //   4351: sipush #31478
    //   4354: invokestatic a : (II)Ljava/lang/String;
    //   4357: iconst_1
    //   4358: ldc burp/Zzri
    //   4360: invokevirtual getClassLoader : ()Ljava/lang/ClassLoader;
    //   4363: invokestatic forName : (Ljava/lang/String;ZLjava/lang/ClassLoader;)Ljava/lang/Class;
    //   4366: invokevirtual getDeclaredFields : ()[Ljava/lang/reflect/Field;
    //   4369: astore #5
    //   4371: aload #5
    //   4373: arraylength
    //   4374: istore #6
    //   4376: iconst_0
    //   4377: istore #7
    //   4379: iload #7
    //   4381: iload #6
    //   4383: if_icmpge -> 4521
    //   4386: aload #5
    //   4388: iload #7
    //   4390: aaload
    //   4391: astore #8
    //   4393: aload #8
    //   4395: invokevirtual getModifiers : ()I
    //   4398: invokestatic isStatic : (I)Z
    //   4401: ifne -> 4411
    //   4404: goto -> 4514
    //   4407: invokestatic a : (Ljava/lang/Throwable;)Ljava/lang/Throwable;
    //   4410: athrow
    //   4411: aload #8
    //   4413: invokevirtual getType : ()Ljava/lang/Class;
    //   4416: astore #9
    //   4418: aload #9
    //   4420: ifnull -> 4501
    //   4423: aload #9
    //   4425: invokevirtual isPrimitive : ()Z
    //   4428: ifne -> 4501
    //   4431: goto -> 4438
    //   4434: invokestatic a : (Ljava/lang/Throwable;)Ljava/lang/Throwable;
    //   4437: athrow
    //   4438: aload #9
    //   4440: invokevirtual getPackage : ()Ljava/lang/Package;
    //   4443: ifnull -> 4501
    //   4446: goto -> 4453
    //   4449: invokestatic a : (Ljava/lang/Throwable;)Ljava/lang/Throwable;
    //   4452: athrow
    //   4453: aload #9
    //   4455: invokevirtual getPackage : ()Ljava/lang/Package;
    //   4458: invokevirtual getName : ()Ljava/lang/String;
    //   4461: ifnull -> 4501
    //   4464: goto -> 4471
    //   4467: invokestatic a : (Ljava/lang/Throwable;)Ljava/lang/Throwable;
    //   4470: athrow
    //   4471: aload #9
    //   4473: invokevirtual getPackage : ()Ljava/lang/Package;
    //   4476: invokevirtual getName : ()Ljava/lang/String;
    //   4479: sipush #-11082
    //   4482: sipush #-22000
    //   4485: invokestatic a : (II)Ljava/lang/String;
    //   4488: invokevirtual startsWith : (Ljava/lang/String;)Z
    //   4491: ifne -> 4501
    //   4494: goto -> 4501
    //   4497: invokestatic a : (Ljava/lang/Throwable;)Ljava/lang/Throwable;
    //   4500: athrow
    //   4501: aload #8
    //   4503: iconst_1
    //   4504: invokevirtual setAccessible : (Z)V
    //   4507: aload #8
    //   4509: aconst_null
    //   4510: invokevirtual get : (Ljava/lang/Object;)Ljava/lang/Object;
    //   4513: pop
    //   4514: iinc #7, 1
    //   4517: iload_2
    //   4518: ifne -> 4379
    //   4521: sipush #-11085
    //   4524: sipush #-13786
    //   4527: invokestatic a : (II)Ljava/lang/String;
    //   4530: invokestatic forName : (Ljava/lang/String;)Ljava/lang/Class;
    //   4533: invokevirtual getDeclaredMethods : ()[Ljava/lang/reflect/Method;
    //   4536: astore #5
    //   4538: aload #5
    //   4540: arraylength
    //   4541: istore #6
    //   4543: iconst_0
    //   4544: istore #7
    //   4546: iload #7
    //   4548: iload #6
    //   4550: if_icmpge -> 4687
    //   4553: aload #5
    //   4555: iload #7
    //   4557: aaload
    //   4558: astore #8
    //   4560: aload #8
    //   4562: invokevirtual getParameterTypes : ()[Ljava/lang/Class;
    //   4565: pop
    //   4566: aload #8
    //   4568: invokevirtual getModifiers : ()I
    //   4571: invokestatic isStatic : (I)Z
    //   4574: ifeq -> 4673
    //   4577: aload #8
    //   4579: invokevirtual getParameterTypes : ()[Ljava/lang/Class;
    //   4582: arraylength
    //   4583: iconst_2
    //   4584: if_icmpne -> 4673
    //   4587: goto -> 4594
    //   4590: invokestatic a : (Ljava/lang/Throwable;)Ljava/lang/Throwable;
    //   4593: athrow
    //   4594: aload #8
    //   4596: invokevirtual getReturnType : ()Ljava/lang/Class;
    //   4599: getstatic java/lang/Boolean.TYPE : Ljava/lang/Class;
    //   4602: if_acmpne -> 4673
    //   4605: goto -> 4612
    //   4608: invokestatic a : (Ljava/lang/Throwable;)Ljava/lang/Throwable;
    //   4611: athrow
    //   4612: aload #8
    //   4614: iconst_1
    //   4615: invokevirtual setAccessible : (Z)V
    //   4618: aload #8
    //   4620: aconst_null
    //   4621: iconst_2
    //   4622: anewarray java/lang/Object
    //   4625: dup
    //   4626: iconst_0
    //   4627: aload_0
    //   4628: aastore
    //   4629: dup
    //   4630: iconst_1
    //   4631: aload_1
    //   4632: ifnonnull -> 4650
    //   4635: goto -> 4642
    //   4638: invokestatic a : (Ljava/lang/Throwable;)Ljava/lang/Throwable;
    //   4641: athrow
    //   4642: aload_1
    //   4643: goto -> 4657
    //   4646: invokestatic a : (Ljava/lang/Throwable;)Ljava/lang/Throwable;
    //   4649: athrow
    //   4650: aload_1
    //   4651: checkcast [B
    //   4654: invokevirtual clone : ()Ljava/lang/Object;
    //   4657: aastore
    //   4658: invokevirtual invoke : (Ljava/lang/Object;[Ljava/lang/Object;)Ljava/lang/Object;
    //   4661: checkcast java/lang/Boolean
    //   4664: invokevirtual booleanValue : ()Z
    //   4667: istore #4
    //   4669: iload_2
    //   4670: ifne -> 4687
    //   4673: iinc #7, 1
    //   4676: iload_2
    //   4677: ifne -> 4546
    //   4680: goto -> 4687
    //   4683: invokestatic a : (Ljava/lang/Throwable;)Ljava/lang/Throwable;
    //   4686: athrow
    //   4687: iload_2
    //   4688: ifne -> 5030
    //   4691: sipush #-11081
    //   4694: sipush #-22578
    //   4697: invokestatic a : (II)Ljava/lang/String;
    //   4700: iconst_1
    //   4701: ldc burp/Zg1k
    //   4703: invokevirtual getClassLoader : ()Ljava/lang/ClassLoader;
    //   4706: invokestatic forName : (Ljava/lang/String;ZLjava/lang/ClassLoader;)Ljava/lang/Class;
    //   4709: invokevirtual getDeclaredFields : ()[Ljava/lang/reflect/Field;
    //   4712: astore #5
    //   4714: aload #5
    //   4716: arraylength
    //   4717: istore #6
    //   4719: iconst_0
    //   4720: istore #7
    //   4722: iload #7
    //   4724: iload #6
    //   4726: if_icmpge -> 4864
    //   4729: aload #5
    //   4731: iload #7
    //   4733: aaload
    //   4734: astore #8
    //   4736: aload #8
    //   4738: invokevirtual getModifiers : ()I
    //   4741: invokestatic isStatic : (I)Z
    //   4744: ifne -> 4754
    //   4747: goto -> 4857
    //   4750: invokestatic a : (Ljava/lang/Throwable;)Ljava/lang/Throwable;
    //   4753: athrow
    //   4754: aload #8
    //   4756: invokevirtual getType : ()Ljava/lang/Class;
    //   4759: astore #9
    //   4761: aload #9
    //   4763: ifnull -> 4844
    //   4766: aload #9
    //   4768: invokevirtual isPrimitive : ()Z
    //   4771: ifne -> 4844
    //   4774: goto -> 4781
    //   4777: invokestatic a : (Ljava/lang/Throwable;)Ljava/lang/Throwable;
    //   4780: athrow
    //   4781: aload #9
    //   4783: invokevirtual getPackage : ()Ljava/lang/Package;
    //   4786: ifnull -> 4844
    //   4789: goto -> 4796
    //   4792: invokestatic a : (Ljava/lang/Throwable;)Ljava/lang/Throwable;
    //   4795: athrow
    //   4796: aload #9
    //   4798: invokevirtual getPackage : ()Ljava/lang/Package;
    //   4801: invokevirtual getName : ()Ljava/lang/String;
    //   4804: ifnull -> 4844
    //   4807: goto -> 4814
    //   4810: invokestatic a : (Ljava/lang/Throwable;)Ljava/lang/Throwable;
    //   4813: athrow
    //   4814: aload #9
    //   4816: invokevirtual getPackage : ()Ljava/lang/Package;
    //   4819: invokevirtual getName : ()Ljava/lang/String;
    //   4822: sipush #-11082
    //   4825: sipush #-22000
    //   4828: invokestatic a : (II)Ljava/lang/String;
    //   4831: invokevirtual startsWith : (Ljava/lang/String;)Z
    //   4834: ifne -> 4844
    //   4837: goto -> 4844
    //   4840: invokestatic a : (Ljava/lang/Throwable;)Ljava/lang/Throwable;
    //   4843: athrow
    //   4844: aload #8
    //   4846: iconst_1
    //   4847: invokevirtual setAccessible : (Z)V
    //   4850: aload #8
    //   4852: aconst_null
    //   4853: invokevirtual get : (Ljava/lang/Object;)Ljava/lang/Object;
    //   4856: pop
    //   4857: iinc #7, 1
    //   4860: iload_2
    //   4861: ifne -> 4722
    //   4864: sipush #-11102
    //   4867: sipush #-2890
    //   4870: invokestatic a : (II)Ljava/lang/String;
    //   4873: invokestatic forName : (Ljava/lang/String;)Ljava/lang/Class;
    //   4876: invokevirtual getDeclaredMethods : ()[Ljava/lang/reflect/Method;
    //   4879: astore #5
    //   4881: aload #5
    //   4883: arraylength
    //   4884: istore #6
    //   4886: iconst_0
    //   4887: istore #7
    //   4889: iload #7
    //   4891: iload #6
    //   4893: if_icmpge -> 5030
    //   4896: aload #5
    //   4898: iload #7
    //   4900: aaload
    //   4901: astore #8
    //   4903: aload #8
    //   4905: invokevirtual getParameterTypes : ()[Ljava/lang/Class;
    //   4908: pop
    //   4909: aload #8
    //   4911: invokevirtual getModifiers : ()I
    //   4914: invokestatic isStatic : (I)Z
    //   4917: ifeq -> 5016
    //   4920: aload #8
    //   4922: invokevirtual getParameterTypes : ()[Ljava/lang/Class;
    //   4925: arraylength
    //   4926: iconst_2
    //   4927: if_icmpne -> 5016
    //   4930: goto -> 4937
    //   4933: invokestatic a : (Ljava/lang/Throwable;)Ljava/lang/Throwable;
    //   4936: athrow
    //   4937: aload #8
    //   4939: invokevirtual getReturnType : ()Ljava/lang/Class;
    //   4942: getstatic java/lang/Boolean.TYPE : Ljava/lang/Class;
    //   4945: if_acmpne -> 5016
    //   4948: goto -> 4955
    //   4951: invokestatic a : (Ljava/lang/Throwable;)Ljava/lang/Throwable;
    //   4954: athrow
    //   4955: aload #8
    //   4957: iconst_1
    //   4958: invokevirtual setAccessible : (Z)V
    //   4961: aload #8
    //   4963: aconst_null
    //   4964: iconst_2
    //   4965: anewarray java/lang/Object
    //   4968: dup
    //   4969: iconst_0
    //   4970: aload_0
    //   4971: aastore
    //   4972: dup
    //   4973: iconst_1
    //   4974: aload_1
    //   4975: ifnonnull -> 4993
    //   4978: goto -> 4985
    //   4981: invokestatic a : (Ljava/lang/Throwable;)Ljava/lang/Throwable;
    //   4984: athrow
    //   4985: aload_1
    //   4986: goto -> 5000
    //   4989: invokestatic a : (Ljava/lang/Throwable;)Ljava/lang/Throwable;
    //   4992: athrow
    //   4993: aload_1
    //   4994: checkcast [B
    //   4997: invokevirtual clone : ()Ljava/lang/Object;
    //   5000: aastore
    //   5001: invokevirtual invoke : (Ljava/lang/Object;[Ljava/lang/Object;)Ljava/lang/Object;
    //   5004: checkcast java/lang/Boolean
    //   5007: invokevirtual booleanValue : ()Z
    //   5010: istore #4
    //   5012: iload_2
    //   5013: ifne -> 5030
    //   5016: iinc #7, 1
    //   5019: iload_2
    //   5020: ifne -> 4889
    //   5023: goto -> 5030
    //   5026: invokestatic a : (Ljava/lang/Throwable;)Ljava/lang/Throwable;
    //   5029: athrow
    //   5030: iload #4
    //   5032: ireturn
    //   5033: astore_3
    //   5034: new java/lang/Exception
    //   5037: dup
    //   5038: aload_3
    //   5039: invokevirtual getMessage : ()Ljava/lang/String;
    //   5042: invokespecial <init> : (Ljava/lang/String;)V
    //   5045: athrow
    // Exception table:
    //   from	to	target	type
    //   4	2832	5033	java/lang/Throwable
    //   58	234	237	java/lang/Throwable
    //   204	271	274	java/lang/Throwable
    //   241	308	311	java/lang/Throwable
    //   278	345	348	java/lang/Throwable
    //   315	382	385	java/lang/Throwable
    //   352	419	422	java/lang/Throwable
    //   389	456	459	java/lang/Throwable
    //   426	493	496	java/lang/Throwable
    //   463	530	533	java/lang/Throwable
    //   500	567	570	java/lang/Throwable
    //   537	604	607	java/lang/Throwable
    //   574	641	644	java/lang/Throwable
    //   611	678	681	java/lang/Throwable
    //   648	715	718	java/lang/Throwable
    //   685	752	755	java/lang/Throwable
    //   722	789	792	java/lang/Throwable
    //   759	826	829	java/lang/Throwable
    //   796	863	866	java/lang/Throwable
    //   833	900	903	java/lang/Throwable
    //   870	937	940	java/lang/Throwable
    //   907	974	977	java/lang/Throwable
    //   944	1011	1014	java/lang/Throwable
    //   981	1048	1051	java/lang/Throwable
    //   1018	1085	1088	java/lang/Throwable
    //   1055	1122	1125	java/lang/Throwable
    //   1092	1159	1162	java/lang/Throwable
    //   1129	1196	1199	java/lang/Throwable
    //   1166	1233	1236	java/lang/Throwable
    //   1203	1270	1273	java/lang/Throwable
    //   1240	1307	1310	java/lang/Throwable
    //   1277	1344	1347	java/lang/Throwable
    //   1314	1377	1380	java/lang/Throwable
    //   1443	1457	1457	java/lang/Throwable
    //   1468	1481	1484	java/lang/Throwable
    //   1473	1496	1499	java/lang/Throwable
    //   1488	1514	1517	java/lang/Throwable
    //   1503	1544	1547	java/lang/Throwable
    //   1610	1637	1640	java/lang/Throwable
    //   1627	1658	1661	java/lang/Throwable
    //   1644	1688	1691	java/lang/Throwable
    //   1665	1699	1699	java/lang/Throwable
    //   1710	1726	1729	java/lang/Throwable
    //   1806	1820	1820	java/lang/Throwable
    //   1831	1844	1847	java/lang/Throwable
    //   1836	1859	1862	java/lang/Throwable
    //   1851	1877	1880	java/lang/Throwable
    //   1866	1907	1910	java/lang/Throwable
    //   1973	2000	2003	java/lang/Throwable
    //   1990	2021	2024	java/lang/Throwable
    //   2007	2051	2054	java/lang/Throwable
    //   2028	2062	2062	java/lang/Throwable
    //   2073	2089	2092	java/lang/Throwable
    //   2189	2203	2203	java/lang/Throwable
    //   2214	2227	2230	java/lang/Throwable
    //   2219	2242	2245	java/lang/Throwable
    //   2234	2260	2263	java/lang/Throwable
    //   2249	2290	2293	java/lang/Throwable
    //   2356	2383	2386	java/lang/Throwable
    //   2373	2401	2404	java/lang/Throwable
    //   2390	2431	2434	java/lang/Throwable
    //   2408	2442	2442	java/lang/Throwable
    //   2465	2476	2479	java/lang/Throwable
    //   2531	2545	2545	java/lang/Throwable
    //   2556	2569	2572	java/lang/Throwable
    //   2561	2584	2587	java/lang/Throwable
    //   2576	2602	2605	java/lang/Throwable
    //   2591	2632	2635	java/lang/Throwable
    //   2698	2725	2728	java/lang/Throwable
    //   2715	2743	2746	java/lang/Throwable
    //   2732	2773	2776	java/lang/Throwable
    //   2750	2784	2784	java/lang/Throwable
    //   2807	2818	2821	java/lang/Throwable
    //   2833	3567	5033	java/lang/Throwable
    //   2923	2937	2937	java/lang/Throwable
    //   2948	2961	2964	java/lang/Throwable
    //   2953	2976	2979	java/lang/Throwable
    //   2968	2994	2997	java/lang/Throwable
    //   2983	3024	3027	java/lang/Throwable
    //   3090	3117	3120	java/lang/Throwable
    //   3107	3135	3138	java/lang/Throwable
    //   3124	3165	3168	java/lang/Throwable
    //   3142	3176	3176	java/lang/Throwable
    //   3199	3210	3213	java/lang/Throwable
    //   3266	3280	3280	java/lang/Throwable
    //   3291	3304	3307	java/lang/Throwable
    //   3296	3319	3322	java/lang/Throwable
    //   3311	3337	3340	java/lang/Throwable
    //   3326	3367	3370	java/lang/Throwable
    //   3433	3460	3463	java/lang/Throwable
    //   3450	3478	3481	java/lang/Throwable
    //   3467	3508	3511	java/lang/Throwable
    //   3485	3519	3519	java/lang/Throwable
    //   3542	3553	3556	java/lang/Throwable
    //   3568	4302	5033	java/lang/Throwable
    //   3658	3672	3672	java/lang/Throwable
    //   3683	3696	3699	java/lang/Throwable
    //   3688	3711	3714	java/lang/Throwable
    //   3703	3729	3732	java/lang/Throwable
    //   3718	3759	3762	java/lang/Throwable
    //   3825	3852	3855	java/lang/Throwable
    //   3842	3870	3873	java/lang/Throwable
    //   3859	3900	3903	java/lang/Throwable
    //   3877	3911	3911	java/lang/Throwable
    //   3934	3945	3948	java/lang/Throwable
    //   4001	4015	4015	java/lang/Throwable
    //   4026	4039	4042	java/lang/Throwable
    //   4031	4054	4057	java/lang/Throwable
    //   4046	4072	4075	java/lang/Throwable
    //   4061	4102	4105	java/lang/Throwable
    //   4168	4195	4198	java/lang/Throwable
    //   4185	4213	4216	java/lang/Throwable
    //   4202	4243	4246	java/lang/Throwable
    //   4220	4254	4254	java/lang/Throwable
    //   4277	4288	4291	java/lang/Throwable
    //   4303	5032	5033	java/lang/Throwable
    //   4393	4407	4407	java/lang/Throwable
    //   4418	4431	4434	java/lang/Throwable
    //   4423	4446	4449	java/lang/Throwable
    //   4438	4464	4467	java/lang/Throwable
    //   4453	4494	4497	java/lang/Throwable
    //   4560	4587	4590	java/lang/Throwable
    //   4577	4605	4608	java/lang/Throwable
    //   4594	4635	4638	java/lang/Throwable
    //   4612	4646	4646	java/lang/Throwable
    //   4669	4680	4683	java/lang/Throwable
    //   4736	4750	4750	java/lang/Throwable
    //   4761	4774	4777	java/lang/Throwable
    //   4766	4789	4792	java/lang/Throwable
    //   4781	4807	4810	java/lang/Throwable
    //   4796	4837	4840	java/lang/Throwable
    //   4903	4930	4933	java/lang/Throwable
    //   4920	4948	4951	java/lang/Throwable
    //   4937	4978	4981	java/lang/Throwable
    //   4955	4989	4989	java/lang/Throwable
    //   5012	5023	5026	java/lang/Throwable
  }
  
  static void ZS(Object[] paramArrayOfObject, Object paramObject) throws Throwable {}
  
  static {
    // Byte code:
    //   0: bipush #27
    //   2: anewarray java/lang/String
    //   5: astore #5
    //   7: iconst_0
    //   8: istore_3
    //   9: ldc '(:,BU \\r\\tT_i\\ts\\t/nN W|I\\t_E\E\\tT{~},\\t%Ga25\\t9\\bzf- G\\t M\\t-As\\t#x\\tzJR;W\\tYS\\t~\\fS-\\tq0l`\\tD?7>s+M0N-\\bfk<XjNutPUd4W%O|'AuQ@)5Yw$NMk)\\bS|jd\\t76L F!FM(Jt\\n)jKR4?{z\\tK@q&\\t_M9'
    //   11: dup
    //   12: astore_2
    //   13: invokevirtual length : ()I
    //   16: istore #4
    //   18: bipush #9
    //   20: istore_1
    //   21: iconst_m1
    //   22: istore_0
    //   23: bipush #71
    //   25: iinc #0, 1
    //   28: aload_2
    //   29: iload_0
    //   30: dup
    //   31: iload_1
    //   32: iadd
    //   33: invokevirtual substring : (II)Ljava/lang/String;
    //   36: iconst_m1
    //   37: goto -> 143
    //   40: aload #5
    //   42: swap
    //   43: iload_3
    //   44: iinc #3, 1
    //   47: swap
    //   48: aastore
    //   49: iload_0
    //   50: iload_1
    //   51: iadd
    //   52: dup
    //   53: istore_0
    //   54: iload #4
    //   56: if_icmpge -> 68
    //   59: aload_2
    //   60: iload_0
    //   61: invokevirtual charAt : (I)C
    //   64: istore_1
    //   65: goto -> 23
    //   68: ldc 'i,}\\tu;)'
    //   70: dup
    //   71: astore_2
    //   72: invokevirtual length : ()I
    //   75: istore #4
    //   77: bipush #9
    //   79: istore_1
    //   80: iconst_m1
    //   81: istore_0
    //   82: bipush #78
    //   84: iinc #0, 1
    //   87: aload_2
    //   88: iload_0
    //   89: dup
    //   90: iload_1
    //   91: iadd
    //   92: invokevirtual substring : (II)Ljava/lang/String;
    //   95: iconst_0
    //   96: goto -> 143
    //   99: aload #5
    //   101: swap
    //   102: iload_3
    //   103: iinc #3, 1
    //   106: swap
    //   107: aastore
    //   108: iload_0
    //   109: iload_1
    //   110: iadd
    //   111: dup
    //   112: istore_0
    //   113: iload #4
    //   115: if_icmpge -> 127
    //   118: aload_2
    //   119: iload_0
    //   120: invokevirtual charAt : (I)C
    //   123: istore_1
    //   124: goto -> 82
    //   127: aload #5
    //   129: putstatic burp/Zlkm.a : [Ljava/lang/String;
    //   132: bipush #27
    //   134: anewarray java/lang/String
    //   137: putstatic burp/Zlkm.b : [Ljava/lang/String;
    //   140: goto -> 300
    //   143: dup_x2
    //   144: pop
    //   145: invokevirtual toCharArray : ()[C
    //   148: dup_x1
    //   149: arraylength
    //   150: dup_x2
    //   151: pop
    //   152: iconst_0
    //   153: istore #6
    //   155: dup2_x1
    //   156: pop2
    //   157: dup_x2
    //   158: iconst_1
    //   159: if_icmpgt -> 260
    //   162: dup2
    //   163: swap
    //   164: iload #6
    //   166: dup2_x1
    //   167: caload
    //   168: swap
    //   169: iload #6
    //   171: bipush #7
    //   173: irem
    //   174: tableswitch default -> 242, 0 -> 212, 1 -> 217, 2 -> 222, 3 -> 227, 4 -> 232, 5 -> 237
    //   212: bipush #30
    //   214: goto -> 244
    //   217: bipush #89
    //   219: goto -> 244
    //   222: bipush #25
    //   224: goto -> 244
    //   227: bipush #42
    //   229: goto -> 244
    //   232: bipush #78
    //   234: goto -> 244
    //   237: bipush #65
    //   239: goto -> 244
    //   242: bipush #108
    //   244: ixor
    //   245: ixor
    //   246: i2c
    //   247: castore
    //   248: iinc #6, 1
    //   251: dup
    //   252: ifne -> 260
    //   255: dup2
    //   256: dup_x1
    //   257: goto -> 166
    //   260: dup2_x1
    //   261: pop2
    //   262: dup_x2
    //   263: iload #6
    //   265: if_icmpgt -> 162
    //   268: pop
    //   269: new java/lang/String
    //   272: dup_x1
    //   273: swap
    //   274: invokespecial <init> : ([C)V
    //   277: invokevirtual intern : ()Ljava/lang/String;
    //   280: swap
    //   281: pop
    //   282: swap
    //   283: tableswitch default -> 40, 0 -> 99
    //   300: new java/math/BigInteger
    //   303: dup
    //   304: iconst_1
    //   305: bipush #32
    //   307: newarray byte
    //   309: dup
    //   310: iconst_0
    //   311: bipush #37
    //   313: bastore
    //   314: dup
    //   315: iconst_1
    //   316: bipush #-38
    //   318: bastore
    //   319: dup
    //   320: iconst_2
    //   321: bipush #30
    //   323: bastore
    //   324: dup
    //   325: iconst_3
    //   326: bipush #85
    //   328: bastore
    //   329: dup
    //   330: iconst_4
    //   331: bipush #118
    //   333: bastore
    //   334: dup
    //   335: iconst_5
    //   336: bipush #88
    //   338: bastore
    //   339: dup
    //   340: bipush #6
    //   342: bipush #-56
    //   344: bastore
    //   345: dup
    //   346: bipush #7
    //   348: bipush #-91
    //   350: bastore
    //   351: dup
    //   352: bipush #8
    //   354: bipush #86
    //   356: bastore
    //   357: dup
    //   358: bipush #9
    //   360: bipush #-96
    //   362: bastore
    //   363: dup
    //   364: bipush #10
    //   366: bipush #-16
    //   368: bastore
    //   369: dup
    //   370: bipush #11
    //   372: bipush #-42
    //   374: bastore
    //   375: dup
    //   376: bipush #12
    //   378: bipush #35
    //   380: bastore
    //   381: dup
    //   382: bipush #13
    //   384: bipush #15
    //   386: bastore
    //   387: dup
    //   388: bipush #14
    //   390: bipush #61
    //   392: bastore
    //   393: dup
    //   394: bipush #15
    //   396: bipush #101
    //   398: bastore
    //   399: dup
    //   400: bipush #16
    //   402: bipush #-41
    //   404: bastore
    //   405: dup
    //   406: bipush #17
    //   408: bipush #-93
    //   410: bastore
    //   411: dup
    //   412: bipush #18
    //   414: bipush #-115
    //   416: bastore
    //   417: dup
    //   418: bipush #19
    //   420: bipush #33
    //   422: bastore
    //   423: dup
    //   424: bipush #20
    //   426: bipush #-25
    //   428: bastore
    //   429: dup
    //   430: bipush #21
    //   432: iconst_5
    //   433: bastore
    //   434: dup
    //   435: bipush #22
    //   437: bipush #121
    //   439: bastore
    //   440: dup
    //   441: bipush #23
    //   443: bipush #-65
    //   445: bastore
    //   446: dup
    //   447: bipush #24
    //   449: bipush #-21
    //   451: bastore
    //   452: dup
    //   453: bipush #25
    //   455: bipush #-8
    //   457: bastore
    //   458: dup
    //   459: bipush #26
    //   461: bipush #35
    //   463: bastore
    //   464: dup
    //   465: bipush #27
    //   467: bipush #-116
    //   469: bastore
    //   470: dup
    //   471: bipush #28
    //   473: bipush #59
    //   475: bastore
    //   476: dup
    //   477: bipush #29
    //   479: bipush #9
    //   481: bastore
    //   482: dup
    //   483: bipush #30
    //   485: bipush #-43
    //   487: bastore
    //   488: dup
    //   489: bipush #31
    //   491: bipush #-88
    //   493: bastore
    //   494: invokespecial <init> : (I[B)V
    //   497: putstatic burp/Zlkm.ZQ : Ljava/lang/Object;
    //   500: sipush #-11098
    //   503: sipush #17783
    //   506: invokestatic a : (II)Ljava/lang/String;
    //   509: putstatic burp/Zlkm.ZH : Ljava/lang/String;
    //   512: return
  }
  
  private static Throwable a(Throwable paramThrowable) {
    return paramThrowable;
  }
  
  private static String a(int paramInt1, int paramInt2) {
    int i = (paramInt1 ^ 0xFFFFD4A2) & 0xFFFF;
    if (b[i] == null) {
      char[] arrayOfChar = a[i].toCharArray();
      switch (arrayOfChar[0] & 0xFF) {
        case 0:
        
        case 1:
        
        case 2:
        
        case 3:
        
        case 4:
        
        case 5:
        
        case 6:
        
        case 7:
        
        case 8:
        
        case 9:
        
        case 10:
        
        case 11:
        
        case 12:
        
        case 13:
        
        case 14:
        
        case 15:
        
        case 16:
        
        case 17:
        
        case 18:
        
        case 19:
        
        case 20:
        
        case 21:
        
        case 22:
        
        case 23:
        
        case 24:
        
        case 25:
        
        case 26:
        
        case 27:
        
        case 28:
        
        case 29:
        
        case 30:
        
        case 31:
        
        case 32:
        
        case 33:
        
        case 34:
        
        case 35:
        
        case 36:
        
        case 37:
        
        case 38:
        
        case 39:
        
        case 40:
        
        case 41:
        
        case 42:
        
        case 43:
        
        case 44:
        
        case 45:
        
        case 46:
        
        case 47:
        
        case 48:
        
        case 49:
        
        case 50:
        
        case 51:
        
        case 52:
        
        case 53:
        
        case 54:
        
        case 55:
        
        case 56:
        
        case 57:
        
        case 58:
        
        case 59:
        
        case 60:
        
        case 61:
        
        case 62:
        
        case 63:
        
        case 64:
        
        case 65:
        
        case 66:
        
        case 67:
        
        case 68:
        
        case 69:
        
        case 70:
        
        case 71:
        
        case 72:
        
        case 73:
        
        case 74:
        
        case 75:
        
        case 76:
        
        case 77:
        
        case 78:
        
        case 79:
        
        case 80:
        
        case 81:
        
        case 82:
        
        case 83:
        
        case 84:
        
        case 85:
        
        case 86:
        
        case 87:
        
        case 88:
        
        case 89:
        
        case 90:
        
        case 91:
        
        case 92:
        
        case 93:
        
        case 94:
        
        case 95:
        
        case 96:
        
        case 97:
        
        case 98:
        
        case 99:
        
        case 100:
        
        case 101:
        
        case 102:
        
        case 103:
        
        case 104:
        
        case 105:
        
        case 106:
        
        case 107:
        
        case 108:
        
        case 109:
        
        case 110:
        
        case 111:
        
        case 112:
        
        case 113:
        
        case 114:
        
        case 115:
        
        case 116:
        
        case 117:
        
        case 118:
        
        case 119:
        
        case 120:
        
        case 121:
        
        case 122:
        
        case 123:
        
        case 124:
        
        case 125:
        
        case 126:
        
        case 127:
        
        case 128:
        
        case 129:
        
        case 130:
        
        case 131:
        
        case 132:
        
        case 133:
        
        case 134:
        
        case 135:
        
        case 136:
        
        case 137:
        
        case 138:
        
        case 139:
        
        case 140:
        
        case 141:
        
        case 142:
        
        case 143:
        
        case 144:
        
        case 145:
        
        case 146:
        
        case 147:
        
        case 148:
        
        case 149:
        
        case 150:
        
        case 151:
        
        case 152:
        
        case 153:
        
        case 154:
        
        case 155:
        
        case 156:
        
        case 157:
        
        case 158:
        
        case 159:
        
        case 160:
        
        case 161:
        
        case 162:
        
        case 163:
        
        case 164:
        
        case 165:
        
        case 166:
        
        case 167:
        
        case 168:
        
        case 169:
        
        case 170:
        
        case 171:
        
        case 172:
        
        case 173:
        
        case 174:
        
        case 175:
        
        case 176:
        
        case 177:
        
        case 178:
        
        case 179:
        
        case 180:
        
        case 181:
        
        case 182:
        
        case 183:
        
        case 184:
        
        case 185:
        
        case 186:
        
        case 187:
        
        case 188:
        
        case 189:
        
        case 190:
        
        case 191:
        
        case 192:
        
        case 193:
        
        case 194:
        
        case 195:
        
        case 196:
        
        case 197:
        
        case 198:
        
        case 199:
        
        case 200:
        
        case 201:
        
        case 202:
        
        case 203:
        
        case 204:
        
        case 205:
        
        case 206:
        
        case 207:
        
        case 208:
        
        case 209:
        
        case 210:
        
        case 211:
        
        case 212:
        
        case 213:
        
        case 214:
        
        case 215:
        
        case 216:
        
        case 217:
        
        case 218:
        
        case 219:
        
        case 220:
        
        case 221:
        
        case 222:
        
        case 223:
        
        case 224:
        
        case 225:
        
        case 226:
        
        case 227:
        
        case 228:
        
        case 229:
        
        case 230:
        
        case 231:
        
        case 232:
        
        case 233:
        
        case 234:
        
        case 235:
        
        case 236:
        
        case 237:
        
        case 238:
        
        case 239:
        
        case 240:
        
        case 241:
        
        case 242:
        
        case 243:
        
        case 244:
        
        case 245:
        
        case 246:
        
        case 247:
        
        case 248:
        
        case 249:
        
        case 250:
        
        case 251:
        
        case 252:
        
        case 253:
        
        case 254:
        
        default:
          break;
      } 
      byte b1 = 65;
      int j = (paramInt2 & 0xFF) - b1;
      if (j < 0)
        j += 256; 
      int k = ((paramInt2 & 0xFFFF) >>> 8) - b1;
      if (k < 0)
        k += 256; 
      for (byte b2 = 0; b2 < arrayOfChar.length; b2++) {
        int m = b2 % 2;
        if (m == 0) {
          arrayOfChar[b2] = (char)(arrayOfChar[b2] ^ j);
          j = ((j >>> 3 | j << 5) ^ arrayOfChar[b2]) & 0xFF;
        } else {
          arrayOfChar[b2] = (char)(arrayOfChar[b2] ^ k);
          k = ((k >>> 3 | k << 5) ^ arrayOfChar[b2]) & 0xFF;
        } 
      } 
      b[i] = (new String(arrayOfChar)).intern();
    } 
    return b[i];
  }
}


/* Location:              C:\Program Files\BurpSuitePro\burpsuite_pro.jar!\burp\Zlkm.class
 * Java compiler version: 21 (65.0)
 * JD-Core Version:       1.1.3
 */