package burp;

import java.math.BigInteger;

class Zllk extends ClassLoader {
  static Object Zi;
  
  static String Zs;
  
  private static final String[] a;
  
  private static final String[] b;
  
  static void Zb(Object paramObject) {
    Ze25.Zp = a(30214, 5093);
    Ze25.ZW = new BigInteger(a(30235, -32352));
    boolean bool = Zt2e.ZN();
    try {
      try {
        if (Zrom.ZD.charAt(Math.abs(((BigInteger)Zz4a.ZB).intValue() % 32)) > Zzgb.ZT.charAt(Math.abs(((BigInteger)Zz7m.Zh).intValue() % 32))) {
          try {
            Zs0h.Zr(Class.forName(a(30221, 365)));
            if (!bool)
              Zzah.Zf(Class.forName(a(30220, -8591))); 
          } catch (Throwable throwable) {
            throw a(null);
          } 
          return;
        } 
      } catch (Throwable throwable) {
        throw a(null);
      } 
      Zzah.Zf(Class.forName(a(30220, -8591)));
    } catch (Throwable throwable) {}
  }
  
  static boolean Zp(Object[] paramArrayOfObject, Object paramObject) throws Throwable {
    // Byte code:
    //   0: invokestatic ZK : ()Z
    //   3: istore_2
    //   4: getstatic burp/Znu.Zf : Ljava/lang/Object;
    //   7: checkcast java/math/BigInteger
    //   10: invokevirtual toByteArray : ()[B
    //   13: astore_3
    //   14: new java/lang/StringBuilder
    //   17: dup
    //   18: invokespecial <init> : ()V
    //   21: astore #5
    //   23: aload #5
    //   25: sipush #30226
    //   28: sipush #7421
    //   31: invokestatic a : (II)Ljava/lang/String;
    //   34: invokevirtual append : (Ljava/lang/String;)Ljava/lang/StringBuilder;
    //   37: pop
    //   38: aload_3
    //   39: astore #6
    //   41: aload #6
    //   43: arraylength
    //   44: istore #7
    //   46: iconst_0
    //   47: istore #8
    //   49: iload #8
    //   51: iload #7
    //   53: if_icmpge -> 79
    //   56: aload #6
    //   58: iload #8
    //   60: baload
    //   61: istore #9
    //   63: aload #5
    //   65: iload #9
    //   67: i2c
    //   68: invokevirtual append : (C)Ljava/lang/StringBuilder;
    //   71: pop
    //   72: iinc #8, 1
    //   75: iload_2
    //   76: ifeq -> 49
    //   79: aload #5
    //   81: sipush #30211
    //   84: sipush #10469
    //   87: invokestatic a : (II)Ljava/lang/String;
    //   90: ldc ''
    //   92: invokestatic getProperty : (Ljava/lang/String;Ljava/lang/String;)Ljava/lang/String;
    //   95: invokevirtual toLowerCase : ()Ljava/lang/String;
    //   98: invokevirtual append : (Ljava/lang/String;)Ljava/lang/StringBuilder;
    //   101: pop
    //   102: aload #5
    //   104: sipush #30224
    //   107: sipush #26011
    //   110: invokestatic a : (II)Ljava/lang/String;
    //   113: ldc ''
    //   115: invokestatic getProperty : (Ljava/lang/String;Ljava/lang/String;)Ljava/lang/String;
    //   118: invokevirtual toLowerCase : ()Ljava/lang/String;
    //   121: invokevirtual append : (Ljava/lang/String;)Ljava/lang/StringBuilder;
    //   124: pop
    //   125: aload #5
    //   127: invokevirtual toString : ()Ljava/lang/String;
    //   130: invokevirtual getBytes : ()[B
    //   133: astore #4
    //   135: aload #4
    //   137: astore_3
    //   138: aload_3
    //   139: arraylength
    //   140: bipush #8
    //   142: iadd
    //   143: bipush #6
    //   145: ishr
    //   146: iconst_1
    //   147: iadd
    //   148: bipush #16
    //   150: imul
    //   151: newarray int
    //   153: astore #5
    //   155: iconst_0
    //   156: istore #6
    //   158: iload #6
    //   160: aload_3
    //   161: arraylength
    //   162: if_icmpge -> 205
    //   165: aload_3
    //   166: iload #6
    //   168: baload
    //   169: sipush #255
    //   172: iand
    //   173: istore #7
    //   175: aload #5
    //   177: iload #6
    //   179: iconst_2
    //   180: ishr
    //   181: dup2
    //   182: iaload
    //   183: iload #7
    //   185: bipush #24
    //   187: iload #6
    //   189: iconst_4
    //   190: irem
    //   191: bipush #8
    //   193: imul
    //   194: isub
    //   195: ishl
    //   196: ior
    //   197: iastore
    //   198: iinc #6, 1
    //   201: iload_2
    //   202: ifeq -> 158
    //   205: aload #5
    //   207: iload #6
    //   209: iconst_2
    //   210: ishr
    //   211: dup2
    //   212: iaload
    //   213: sipush #128
    //   216: bipush #24
    //   218: iload #6
    //   220: iconst_4
    //   221: irem
    //   222: bipush #8
    //   224: imul
    //   225: isub
    //   226: ishl
    //   227: ior
    //   228: iastore
    //   229: aload #5
    //   231: aload #5
    //   233: arraylength
    //   234: iconst_1
    //   235: isub
    //   236: aload_3
    //   237: arraylength
    //   238: bipush #8
    //   240: imul
    //   241: iastore
    //   242: bipush #80
    //   244: newarray int
    //   246: astore #7
    //   248: ldc 1732584193
    //   250: istore #8
    //   252: ldc -271733879
    //   254: istore #9
    //   256: ldc -1732584194
    //   258: istore #10
    //   260: ldc 271733878
    //   262: istore #11
    //   264: ldc -1009589776
    //   266: istore #12
    //   268: iconst_0
    //   269: istore #6
    //   271: iload #6
    //   273: aload #5
    //   275: arraylength
    //   276: if_icmpge -> 598
    //   279: iload #8
    //   281: istore #13
    //   283: iload #9
    //   285: istore #14
    //   287: iload #10
    //   289: istore #15
    //   291: iload #11
    //   293: istore #16
    //   295: iload #12
    //   297: istore #17
    //   299: iconst_0
    //   300: istore #18
    //   302: iload #18
    //   304: bipush #80
    //   306: if_icmpge -> 556
    //   309: iload #18
    //   311: bipush #16
    //   313: if_icmpge -> 340
    //   316: aload #7
    //   318: iload #18
    //   320: aload #5
    //   322: iload #6
    //   324: iload #18
    //   326: iadd
    //   327: iaload
    //   328: iastore
    //   329: iload_2
    //   330: ifeq -> 395
    //   333: goto -> 340
    //   336: invokestatic a : (Ljava/lang/Throwable;)Ljava/lang/Throwable;
    //   339: athrow
    //   340: aload #7
    //   342: iload #18
    //   344: iconst_3
    //   345: isub
    //   346: iaload
    //   347: aload #7
    //   349: iload #18
    //   351: bipush #8
    //   353: isub
    //   354: iaload
    //   355: ixor
    //   356: aload #7
    //   358: iload #18
    //   360: bipush #14
    //   362: isub
    //   363: iaload
    //   364: ixor
    //   365: aload #7
    //   367: iload #18
    //   369: bipush #16
    //   371: isub
    //   372: iaload
    //   373: ixor
    //   374: istore #19
    //   376: iload #19
    //   378: iconst_1
    //   379: ishl
    //   380: iload #19
    //   382: bipush #31
    //   384: iushr
    //   385: ior
    //   386: istore #20
    //   388: aload #7
    //   390: iload #18
    //   392: iload #20
    //   394: iastore
    //   395: iload #8
    //   397: iconst_5
    //   398: ishl
    //   399: iload #8
    //   401: bipush #27
    //   403: iushr
    //   404: ior
    //   405: istore #19
    //   407: iload #19
    //   409: iload #12
    //   411: iadd
    //   412: aload #7
    //   414: iload #18
    //   416: iaload
    //   417: iadd
    //   418: iload #18
    //   420: bipush #20
    //   422: if_icmpge -> 448
    //   425: ldc 1518500249
    //   427: iload #9
    //   429: iload #10
    //   431: iand
    //   432: iload #9
    //   434: iconst_m1
    //   435: ixor
    //   436: iload #11
    //   438: iand
    //   439: ior
    //   440: iadd
    //   441: goto -> 518
    //   444: invokestatic a : (Ljava/lang/Throwable;)Ljava/lang/Throwable;
    //   447: athrow
    //   448: iload #18
    //   450: bipush #40
    //   452: if_icmpge -> 473
    //   455: ldc 1859775393
    //   457: iload #9
    //   459: iload #10
    //   461: ixor
    //   462: iload #11
    //   464: ixor
    //   465: iadd
    //   466: goto -> 518
    //   469: invokestatic a : (Ljava/lang/Throwable;)Ljava/lang/Throwable;
    //   472: athrow
    //   473: iload #18
    //   475: bipush #60
    //   477: if_icmpge -> 507
    //   480: ldc -1894007588
    //   482: iload #9
    //   484: iload #10
    //   486: iand
    //   487: iload #9
    //   489: iload #11
    //   491: iand
    //   492: ior
    //   493: iload #10
    //   495: iload #11
    //   497: iand
    //   498: ior
    //   499: iadd
    //   500: goto -> 518
    //   503: invokestatic a : (Ljava/lang/Throwable;)Ljava/lang/Throwable;
    //   506: athrow
    //   507: ldc -899497514
    //   509: iload #9
    //   511: iload #10
    //   513: ixor
    //   514: iload #11
    //   516: ixor
    //   517: iadd
    //   518: iadd
    //   519: istore #20
    //   521: iload #11
    //   523: istore #12
    //   525: iload #10
    //   527: istore #11
    //   529: iload #9
    //   531: bipush #30
    //   533: ishl
    //   534: iload #9
    //   536: iconst_2
    //   537: iushr
    //   538: ior
    //   539: istore #10
    //   541: iload #8
    //   543: istore #9
    //   545: iload #20
    //   547: istore #8
    //   549: iinc #18, 1
    //   552: iload_2
    //   553: ifeq -> 302
    //   556: iload #8
    //   558: iload #13
    //   560: iadd
    //   561: istore #8
    //   563: iload #9
    //   565: iload #14
    //   567: iadd
    //   568: istore #9
    //   570: iload #10
    //   572: iload #15
    //   574: iadd
    //   575: istore #10
    //   577: iload #11
    //   579: iload #16
    //   581: iadd
    //   582: istore #11
    //   584: iload #12
    //   586: iload #17
    //   588: iadd
    //   589: istore #12
    //   591: iinc #6, 16
    //   594: iload_2
    //   595: ifeq -> 271
    //   598: iconst_5
    //   599: newarray int
    //   601: dup
    //   602: iconst_0
    //   603: iload #8
    //   605: iastore
    //   606: dup
    //   607: iconst_1
    //   608: iload #9
    //   610: iastore
    //   611: dup
    //   612: iconst_2
    //   613: iload #10
    //   615: iastore
    //   616: dup
    //   617: iconst_3
    //   618: iload #11
    //   620: iastore
    //   621: dup
    //   622: iconst_4
    //   623: iload #12
    //   625: iastore
    //   626: astore #13
    //   628: bipush #20
    //   630: newarray byte
    //   632: astore #14
    //   634: iconst_0
    //   635: istore #15
    //   637: iload #15
    //   639: bipush #20
    //   641: if_icmpge -> 682
    //   644: aload #13
    //   646: iload #15
    //   648: iconst_4
    //   649: idiv
    //   650: iaload
    //   651: istore #16
    //   653: iconst_3
    //   654: iload #15
    //   656: iconst_4
    //   657: irem
    //   658: isub
    //   659: bipush #8
    //   661: imul
    //   662: istore #17
    //   664: aload #14
    //   666: iload #15
    //   668: iload #16
    //   670: iload #17
    //   672: iushr
    //   673: i2b
    //   674: bastore
    //   675: iinc #15, 1
    //   678: iload_2
    //   679: ifeq -> 637
    //   682: aload #14
    //   684: astore #4
    //   686: getstatic burp/Zscf.ZG : Ljava/lang/Object;
    //   689: checkcast java/math/BigInteger
    //   692: invokevirtual toByteArray : ()[B
    //   695: astore_3
    //   696: bipush #64
    //   698: newarray byte
    //   700: dup
    //   701: iconst_0
    //   702: bipush #-128
    //   704: bastore
    //   705: dup
    //   706: iconst_1
    //   707: iconst_0
    //   708: bastore
    //   709: dup
    //   710: iconst_2
    //   711: iconst_0
    //   712: bastore
    //   713: dup
    //   714: iconst_3
    //   715: iconst_0
    //   716: bastore
    //   717: dup
    //   718: iconst_4
    //   719: iconst_0
    //   720: bastore
    //   721: dup
    //   722: iconst_5
    //   723: iconst_0
    //   724: bastore
    //   725: dup
    //   726: bipush #6
    //   728: iconst_0
    //   729: bastore
    //   730: dup
    //   731: bipush #7
    //   733: iconst_0
    //   734: bastore
    //   735: dup
    //   736: bipush #8
    //   738: iconst_0
    //   739: bastore
    //   740: dup
    //   741: bipush #9
    //   743: iconst_0
    //   744: bastore
    //   745: dup
    //   746: bipush #10
    //   748: iconst_0
    //   749: bastore
    //   750: dup
    //   751: bipush #11
    //   753: iconst_0
    //   754: bastore
    //   755: dup
    //   756: bipush #12
    //   758: iconst_0
    //   759: bastore
    //   760: dup
    //   761: bipush #13
    //   763: iconst_0
    //   764: bastore
    //   765: dup
    //   766: bipush #14
    //   768: iconst_0
    //   769: bastore
    //   770: dup
    //   771: bipush #15
    //   773: iconst_0
    //   774: bastore
    //   775: dup
    //   776: bipush #16
    //   778: iconst_0
    //   779: bastore
    //   780: dup
    //   781: bipush #17
    //   783: iconst_0
    //   784: bastore
    //   785: dup
    //   786: bipush #18
    //   788: iconst_0
    //   789: bastore
    //   790: dup
    //   791: bipush #19
    //   793: iconst_0
    //   794: bastore
    //   795: dup
    //   796: bipush #20
    //   798: iconst_0
    //   799: bastore
    //   800: dup
    //   801: bipush #21
    //   803: iconst_0
    //   804: bastore
    //   805: dup
    //   806: bipush #22
    //   808: iconst_0
    //   809: bastore
    //   810: dup
    //   811: bipush #23
    //   813: iconst_0
    //   814: bastore
    //   815: dup
    //   816: bipush #24
    //   818: iconst_0
    //   819: bastore
    //   820: dup
    //   821: bipush #25
    //   823: iconst_0
    //   824: bastore
    //   825: dup
    //   826: bipush #26
    //   828: iconst_0
    //   829: bastore
    //   830: dup
    //   831: bipush #27
    //   833: iconst_0
    //   834: bastore
    //   835: dup
    //   836: bipush #28
    //   838: iconst_0
    //   839: bastore
    //   840: dup
    //   841: bipush #29
    //   843: iconst_0
    //   844: bastore
    //   845: dup
    //   846: bipush #30
    //   848: iconst_0
    //   849: bastore
    //   850: dup
    //   851: bipush #31
    //   853: iconst_0
    //   854: bastore
    //   855: dup
    //   856: bipush #32
    //   858: iconst_0
    //   859: bastore
    //   860: dup
    //   861: bipush #33
    //   863: iconst_0
    //   864: bastore
    //   865: dup
    //   866: bipush #34
    //   868: iconst_0
    //   869: bastore
    //   870: dup
    //   871: bipush #35
    //   873: iconst_0
    //   874: bastore
    //   875: dup
    //   876: bipush #36
    //   878: iconst_0
    //   879: bastore
    //   880: dup
    //   881: bipush #37
    //   883: iconst_0
    //   884: bastore
    //   885: dup
    //   886: bipush #38
    //   888: iconst_0
    //   889: bastore
    //   890: dup
    //   891: bipush #39
    //   893: iconst_0
    //   894: bastore
    //   895: dup
    //   896: bipush #40
    //   898: iconst_0
    //   899: bastore
    //   900: dup
    //   901: bipush #41
    //   903: iconst_0
    //   904: bastore
    //   905: dup
    //   906: bipush #42
    //   908: iconst_0
    //   909: bastore
    //   910: dup
    //   911: bipush #43
    //   913: iconst_0
    //   914: bastore
    //   915: dup
    //   916: bipush #44
    //   918: iconst_0
    //   919: bastore
    //   920: dup
    //   921: bipush #45
    //   923: iconst_0
    //   924: bastore
    //   925: dup
    //   926: bipush #46
    //   928: iconst_0
    //   929: bastore
    //   930: dup
    //   931: bipush #47
    //   933: iconst_0
    //   934: bastore
    //   935: dup
    //   936: bipush #48
    //   938: iconst_0
    //   939: bastore
    //   940: dup
    //   941: bipush #49
    //   943: iconst_0
    //   944: bastore
    //   945: dup
    //   946: bipush #50
    //   948: iconst_0
    //   949: bastore
    //   950: dup
    //   951: bipush #51
    //   953: iconst_0
    //   954: bastore
    //   955: dup
    //   956: bipush #52
    //   958: iconst_0
    //   959: bastore
    //   960: dup
    //   961: bipush #53
    //   963: iconst_0
    //   964: bastore
    //   965: dup
    //   966: bipush #54
    //   968: iconst_0
    //   969: bastore
    //   970: dup
    //   971: bipush #55
    //   973: iconst_0
    //   974: bastore
    //   975: dup
    //   976: bipush #56
    //   978: iconst_0
    //   979: bastore
    //   980: dup
    //   981: bipush #57
    //   983: iconst_0
    //   984: bastore
    //   985: dup
    //   986: bipush #58
    //   988: iconst_0
    //   989: bastore
    //   990: dup
    //   991: bipush #59
    //   993: iconst_0
    //   994: bastore
    //   995: dup
    //   996: bipush #60
    //   998: iconst_0
    //   999: bastore
    //   1000: dup
    //   1001: bipush #61
    //   1003: iconst_0
    //   1004: bastore
    //   1005: dup
    //   1006: bipush #62
    //   1008: iconst_0
    //   1009: bastore
    //   1010: dup
    //   1011: bipush #63
    //   1013: iconst_0
    //   1014: bastore
    //   1015: astore #5
    //   1017: bipush #64
    //   1019: newarray int
    //   1021: dup
    //   1022: iconst_0
    //   1023: ldc 1116352408
    //   1025: iastore
    //   1026: dup
    //   1027: iconst_1
    //   1028: ldc 1899447441
    //   1030: iastore
    //   1031: dup
    //   1032: iconst_2
    //   1033: ldc -1245643825
    //   1035: iastore
    //   1036: dup
    //   1037: iconst_3
    //   1038: ldc -373957723
    //   1040: iastore
    //   1041: dup
    //   1042: iconst_4
    //   1043: ldc 961987163
    //   1045: iastore
    //   1046: dup
    //   1047: iconst_5
    //   1048: ldc 1508970993
    //   1050: iastore
    //   1051: dup
    //   1052: bipush #6
    //   1054: ldc -1841331548
    //   1056: iastore
    //   1057: dup
    //   1058: bipush #7
    //   1060: ldc -1424204075
    //   1062: iastore
    //   1063: dup
    //   1064: bipush #8
    //   1066: ldc -670586216
    //   1068: iastore
    //   1069: dup
    //   1070: bipush #9
    //   1072: ldc 310598401
    //   1074: iastore
    //   1075: dup
    //   1076: bipush #10
    //   1078: ldc 607225278
    //   1080: iastore
    //   1081: dup
    //   1082: bipush #11
    //   1084: ldc 1426881987
    //   1086: iastore
    //   1087: dup
    //   1088: bipush #12
    //   1090: ldc 1925078388
    //   1092: iastore
    //   1093: dup
    //   1094: bipush #13
    //   1096: ldc -2132889090
    //   1098: iastore
    //   1099: dup
    //   1100: bipush #14
    //   1102: ldc -1680079193
    //   1104: iastore
    //   1105: dup
    //   1106: bipush #15
    //   1108: ldc -1046744716
    //   1110: iastore
    //   1111: dup
    //   1112: bipush #16
    //   1114: ldc -459576895
    //   1116: iastore
    //   1117: dup
    //   1118: bipush #17
    //   1120: ldc -272742522
    //   1122: iastore
    //   1123: dup
    //   1124: bipush #18
    //   1126: ldc 264347078
    //   1128: iastore
    //   1129: dup
    //   1130: bipush #19
    //   1132: ldc 604807628
    //   1134: iastore
    //   1135: dup
    //   1136: bipush #20
    //   1138: ldc 770255983
    //   1140: iastore
    //   1141: dup
    //   1142: bipush #21
    //   1144: ldc 1249150122
    //   1146: iastore
    //   1147: dup
    //   1148: bipush #22
    //   1150: ldc 1555081692
    //   1152: iastore
    //   1153: dup
    //   1154: bipush #23
    //   1156: ldc 1996064986
    //   1158: iastore
    //   1159: dup
    //   1160: bipush #24
    //   1162: ldc -1740746414
    //   1164: iastore
    //   1165: dup
    //   1166: bipush #25
    //   1168: ldc -1473132947
    //   1170: iastore
    //   1171: dup
    //   1172: bipush #26
    //   1174: ldc -1341970488
    //   1176: iastore
    //   1177: dup
    //   1178: bipush #27
    //   1180: ldc -1084653625
    //   1182: iastore
    //   1183: dup
    //   1184: bipush #28
    //   1186: ldc -958395405
    //   1188: iastore
    //   1189: dup
    //   1190: bipush #29
    //   1192: ldc -710438585
    //   1194: iastore
    //   1195: dup
    //   1196: bipush #30
    //   1198: ldc 113926993
    //   1200: iastore
    //   1201: dup
    //   1202: bipush #31
    //   1204: ldc 338241895
    //   1206: iastore
    //   1207: dup
    //   1208: bipush #32
    //   1210: ldc 666307205
    //   1212: iastore
    //   1213: dup
    //   1214: bipush #33
    //   1216: ldc 773529912
    //   1218: iastore
    //   1219: dup
    //   1220: bipush #34
    //   1222: ldc 1294757372
    //   1224: iastore
    //   1225: dup
    //   1226: bipush #35
    //   1228: ldc 1396182291
    //   1230: iastore
    //   1231: dup
    //   1232: bipush #36
    //   1234: ldc 1695183700
    //   1236: iastore
    //   1237: dup
    //   1238: bipush #37
    //   1240: ldc 1986661051
    //   1242: iastore
    //   1243: dup
    //   1244: bipush #38
    //   1246: ldc -2117940946
    //   1248: iastore
    //   1249: dup
    //   1250: bipush #39
    //   1252: ldc -1838011259
    //   1254: iastore
    //   1255: dup
    //   1256: bipush #40
    //   1258: ldc -1564481375
    //   1260: iastore
    //   1261: dup
    //   1262: bipush #41
    //   1264: ldc -1474664885
    //   1266: iastore
    //   1267: dup
    //   1268: bipush #42
    //   1270: ldc -1035236496
    //   1272: iastore
    //   1273: dup
    //   1274: bipush #43
    //   1276: ldc -949202525
    //   1278: iastore
    //   1279: dup
    //   1280: bipush #44
    //   1282: ldc -778901479
    //   1284: iastore
    //   1285: dup
    //   1286: bipush #45
    //   1288: ldc -694614492
    //   1290: iastore
    //   1291: dup
    //   1292: bipush #46
    //   1294: ldc -200395387
    //   1296: iastore
    //   1297: dup
    //   1298: bipush #47
    //   1300: ldc 275423344
    //   1302: iastore
    //   1303: dup
    //   1304: bipush #48
    //   1306: ldc 430227734
    //   1308: iastore
    //   1309: dup
    //   1310: bipush #49
    //   1312: ldc 506948616
    //   1314: iastore
    //   1315: dup
    //   1316: bipush #50
    //   1318: ldc 659060556
    //   1320: iastore
    //   1321: dup
    //   1322: bipush #51
    //   1324: ldc 883997877
    //   1326: iastore
    //   1327: dup
    //   1328: bipush #52
    //   1330: ldc 958139571
    //   1332: iastore
    //   1333: dup
    //   1334: bipush #53
    //   1336: ldc 1322822218
    //   1338: iastore
    //   1339: dup
    //   1340: bipush #54
    //   1342: ldc 1537002063
    //   1344: iastore
    //   1345: dup
    //   1346: bipush #55
    //   1348: ldc 1747873779
    //   1350: iastore
    //   1351: dup
    //   1352: bipush #56
    //   1354: ldc 1955562222
    //   1356: iastore
    //   1357: dup
    //   1358: bipush #57
    //   1360: ldc 2024104815
    //   1362: iastore
    //   1363: dup
    //   1364: bipush #58
    //   1366: ldc -2067236844
    //   1368: iastore
    //   1369: dup
    //   1370: bipush #59
    //   1372: ldc -1933114872
    //   1374: iastore
    //   1375: dup
    //   1376: bipush #60
    //   1378: ldc -1866530822
    //   1380: iastore
    //   1381: dup
    //   1382: bipush #61
    //   1384: ldc -1538233109
    //   1386: iastore
    //   1387: dup
    //   1388: bipush #62
    //   1390: ldc -1090935817
    //   1392: iastore
    //   1393: dup
    //   1394: bipush #63
    //   1396: ldc -965641998
    //   1398: iastore
    //   1399: astore #6
    //   1401: iconst_2
    //   1402: newarray int
    //   1404: dup
    //   1405: iconst_0
    //   1406: iconst_0
    //   1407: iastore
    //   1408: dup
    //   1409: iconst_1
    //   1410: iconst_0
    //   1411: iastore
    //   1412: astore #7
    //   1414: bipush #8
    //   1416: newarray int
    //   1418: dup
    //   1419: iconst_0
    //   1420: ldc 1779033703
    //   1422: iastore
    //   1423: dup
    //   1424: iconst_1
    //   1425: ldc -1150833019
    //   1427: iastore
    //   1428: dup
    //   1429: iconst_2
    //   1430: ldc 1013904242
    //   1432: iastore
    //   1433: dup
    //   1434: iconst_3
    //   1435: ldc -1521486534
    //   1437: iastore
    //   1438: dup
    //   1439: iconst_4
    //   1440: ldc 1359893119
    //   1442: iastore
    //   1443: dup
    //   1444: iconst_5
    //   1445: ldc -1694144372
    //   1447: iastore
    //   1448: dup
    //   1449: bipush #6
    //   1451: ldc 528734635
    //   1453: iastore
    //   1454: dup
    //   1455: bipush #7
    //   1457: ldc 1541459225
    //   1459: iastore
    //   1460: astore #8
    //   1462: bipush #64
    //   1464: newarray byte
    //   1466: astore #9
    //   1468: bipush #64
    //   1470: newarray byte
    //   1472: astore #10
    //   1474: aload_3
    //   1475: arraylength
    //   1476: istore #11
    //   1478: aload #7
    //   1480: iconst_0
    //   1481: iaload
    //   1482: bipush #63
    //   1484: iand
    //   1485: istore #12
    //   1487: aload #7
    //   1489: iconst_0
    //   1490: dup2
    //   1491: iaload
    //   1492: iload #11
    //   1494: iadd
    //   1495: iastore
    //   1496: aload #7
    //   1498: iconst_0
    //   1499: dup2
    //   1500: iaload
    //   1501: iconst_m1
    //   1502: iand
    //   1503: iastore
    //   1504: aload #7
    //   1506: iconst_0
    //   1507: iaload
    //   1508: iload #11
    //   1510: if_icmpge -> 1528
    //   1513: aload #7
    //   1515: iconst_1
    //   1516: dup2
    //   1517: iaload
    //   1518: iconst_1
    //   1519: iadd
    //   1520: iastore
    //   1521: goto -> 1528
    //   1524: invokestatic a : (Ljava/lang/Throwable;)Ljava/lang/Throwable;
    //   1527: athrow
    //   1528: iconst_0
    //   1529: istore #13
    //   1531: iload #11
    //   1533: bipush #64
    //   1535: if_icmplt -> 2144
    //   1538: iconst_0
    //   1539: istore #14
    //   1541: iload #14
    //   1543: bipush #64
    //   1545: if_icmpge -> 1567
    //   1548: aload #10
    //   1550: iload #14
    //   1552: aload_3
    //   1553: iload #13
    //   1555: iload #14
    //   1557: iadd
    //   1558: baload
    //   1559: bastore
    //   1560: iinc #14, 1
    //   1563: iload_2
    //   1564: ifeq -> 1541
    //   1567: bipush #64
    //   1569: newarray int
    //   1571: astore #14
    //   1573: bipush #8
    //   1575: newarray int
    //   1577: astore #15
    //   1579: iconst_0
    //   1580: istore #16
    //   1582: iload #16
    //   1584: bipush #8
    //   1586: if_icmpge -> 1606
    //   1589: aload #15
    //   1591: iload #16
    //   1593: aload #8
    //   1595: iload #16
    //   1597: iaload
    //   1598: iastore
    //   1599: iinc #16, 1
    //   1602: iload_2
    //   1603: ifeq -> 1582
    //   1606: iconst_0
    //   1607: istore #16
    //   1609: iload #16
    //   1611: bipush #64
    //   1613: if_icmpge -> 2104
    //   1616: iload #16
    //   1618: bipush #16
    //   1620: if_icmpge -> 1701
    //   1623: aload #14
    //   1625: iload #16
    //   1627: aload #10
    //   1629: iconst_4
    //   1630: iload #16
    //   1632: imul
    //   1633: baload
    //   1634: sipush #255
    //   1637: iand
    //   1638: bipush #24
    //   1640: ishl
    //   1641: aload #10
    //   1643: iconst_4
    //   1644: iload #16
    //   1646: imul
    //   1647: iconst_1
    //   1648: iadd
    //   1649: baload
    //   1650: sipush #255
    //   1653: iand
    //   1654: bipush #16
    //   1656: ishl
    //   1657: ior
    //   1658: aload #10
    //   1660: iconst_4
    //   1661: iload #16
    //   1663: imul
    //   1664: iconst_2
    //   1665: iadd
    //   1666: baload
    //   1667: sipush #255
    //   1670: iand
    //   1671: bipush #8
    //   1673: ishl
    //   1674: ior
    //   1675: aload #10
    //   1677: iconst_4
    //   1678: iload #16
    //   1680: imul
    //   1681: iconst_3
    //   1682: iadd
    //   1683: baload
    //   1684: sipush #255
    //   1687: iand
    //   1688: ior
    //   1689: iastore
    //   1690: iload_2
    //   1691: ifeq -> 1844
    //   1694: goto -> 1701
    //   1697: invokestatic a : (Ljava/lang/Throwable;)Ljava/lang/Throwable;
    //   1700: athrow
    //   1701: aload #14
    //   1703: iload #16
    //   1705: aload #14
    //   1707: iload #16
    //   1709: iconst_2
    //   1710: isub
    //   1711: iaload
    //   1712: bipush #17
    //   1714: iushr
    //   1715: aload #14
    //   1717: iload #16
    //   1719: iconst_2
    //   1720: isub
    //   1721: iaload
    //   1722: bipush #15
    //   1724: ishl
    //   1725: ior
    //   1726: aload #14
    //   1728: iload #16
    //   1730: iconst_2
    //   1731: isub
    //   1732: iaload
    //   1733: bipush #19
    //   1735: iushr
    //   1736: aload #14
    //   1738: iload #16
    //   1740: iconst_2
    //   1741: isub
    //   1742: iaload
    //   1743: bipush #13
    //   1745: ishl
    //   1746: ior
    //   1747: ixor
    //   1748: aload #14
    //   1750: iload #16
    //   1752: iconst_2
    //   1753: isub
    //   1754: iaload
    //   1755: bipush #10
    //   1757: iushr
    //   1758: ixor
    //   1759: aload #14
    //   1761: iload #16
    //   1763: bipush #7
    //   1765: isub
    //   1766: iaload
    //   1767: iadd
    //   1768: aload #14
    //   1770: iload #16
    //   1772: bipush #15
    //   1774: isub
    //   1775: iaload
    //   1776: bipush #7
    //   1778: iushr
    //   1779: aload #14
    //   1781: iload #16
    //   1783: bipush #15
    //   1785: isub
    //   1786: iaload
    //   1787: bipush #25
    //   1789: ishl
    //   1790: ior
    //   1791: aload #14
    //   1793: iload #16
    //   1795: bipush #15
    //   1797: isub
    //   1798: iaload
    //   1799: bipush #18
    //   1801: iushr
    //   1802: aload #14
    //   1804: iload #16
    //   1806: bipush #15
    //   1808: isub
    //   1809: iaload
    //   1810: bipush #14
    //   1812: ishl
    //   1813: ior
    //   1814: ixor
    //   1815: aload #14
    //   1817: iload #16
    //   1819: bipush #15
    //   1821: isub
    //   1822: iaload
    //   1823: iconst_3
    //   1824: iushr
    //   1825: ixor
    //   1826: iadd
    //   1827: aload #14
    //   1829: iload #16
    //   1831: bipush #16
    //   1833: isub
    //   1834: iaload
    //   1835: iadd
    //   1836: iastore
    //   1837: goto -> 1844
    //   1840: invokestatic a : (Ljava/lang/Throwable;)Ljava/lang/Throwable;
    //   1843: athrow
    //   1844: aload #15
    //   1846: bipush #7
    //   1848: iaload
    //   1849: aload #15
    //   1851: iconst_4
    //   1852: iaload
    //   1853: bipush #6
    //   1855: iushr
    //   1856: aload #15
    //   1858: iconst_4
    //   1859: iaload
    //   1860: bipush #26
    //   1862: ishl
    //   1863: ior
    //   1864: aload #15
    //   1866: iconst_4
    //   1867: iaload
    //   1868: bipush #11
    //   1870: iushr
    //   1871: aload #15
    //   1873: iconst_4
    //   1874: iaload
    //   1875: bipush #21
    //   1877: ishl
    //   1878: ior
    //   1879: ixor
    //   1880: aload #15
    //   1882: iconst_4
    //   1883: iaload
    //   1884: bipush #25
    //   1886: iushr
    //   1887: aload #15
    //   1889: iconst_4
    //   1890: iaload
    //   1891: bipush #7
    //   1893: ishl
    //   1894: ior
    //   1895: ixor
    //   1896: iadd
    //   1897: aload #15
    //   1899: bipush #6
    //   1901: iaload
    //   1902: aload #15
    //   1904: iconst_4
    //   1905: iaload
    //   1906: aload #15
    //   1908: iconst_5
    //   1909: iaload
    //   1910: aload #15
    //   1912: bipush #6
    //   1914: iaload
    //   1915: ixor
    //   1916: iand
    //   1917: ixor
    //   1918: iadd
    //   1919: aload #6
    //   1921: iload #16
    //   1923: iaload
    //   1924: iadd
    //   1925: aload #14
    //   1927: iload #16
    //   1929: iaload
    //   1930: iadd
    //   1931: istore #17
    //   1933: aload #15
    //   1935: iconst_0
    //   1936: iaload
    //   1937: iconst_2
    //   1938: iushr
    //   1939: aload #15
    //   1941: iconst_0
    //   1942: iaload
    //   1943: bipush #30
    //   1945: ishl
    //   1946: ior
    //   1947: aload #15
    //   1949: iconst_0
    //   1950: iaload
    //   1951: bipush #13
    //   1953: iushr
    //   1954: aload #15
    //   1956: iconst_0
    //   1957: iaload
    //   1958: bipush #19
    //   1960: ishl
    //   1961: ior
    //   1962: ixor
    //   1963: aload #15
    //   1965: iconst_0
    //   1966: iaload
    //   1967: bipush #22
    //   1969: iushr
    //   1970: aload #15
    //   1972: iconst_0
    //   1973: iaload
    //   1974: bipush #10
    //   1976: ishl
    //   1977: ior
    //   1978: ixor
    //   1979: aload #15
    //   1981: iconst_0
    //   1982: iaload
    //   1983: aload #15
    //   1985: iconst_1
    //   1986: iaload
    //   1987: iand
    //   1988: aload #15
    //   1990: iconst_2
    //   1991: iaload
    //   1992: aload #15
    //   1994: iconst_0
    //   1995: iaload
    //   1996: aload #15
    //   1998: iconst_1
    //   1999: iaload
    //   2000: ior
    //   2001: iand
    //   2002: ior
    //   2003: iadd
    //   2004: istore #18
    //   2006: aload #15
    //   2008: iconst_3
    //   2009: dup2
    //   2010: iaload
    //   2011: iload #17
    //   2013: iadd
    //   2014: iastore
    //   2015: aload #15
    //   2017: bipush #7
    //   2019: iload #17
    //   2021: iload #18
    //   2023: iadd
    //   2024: iastore
    //   2025: aload #15
    //   2027: bipush #7
    //   2029: iaload
    //   2030: istore #17
    //   2032: aload #15
    //   2034: bipush #7
    //   2036: aload #15
    //   2038: bipush #6
    //   2040: iaload
    //   2041: iastore
    //   2042: aload #15
    //   2044: bipush #6
    //   2046: aload #15
    //   2048: iconst_5
    //   2049: iaload
    //   2050: iastore
    //   2051: aload #15
    //   2053: iconst_5
    //   2054: aload #15
    //   2056: iconst_4
    //   2057: iaload
    //   2058: iastore
    //   2059: aload #15
    //   2061: iconst_4
    //   2062: aload #15
    //   2064: iconst_3
    //   2065: iaload
    //   2066: iastore
    //   2067: aload #15
    //   2069: iconst_3
    //   2070: aload #15
    //   2072: iconst_2
    //   2073: iaload
    //   2074: iastore
    //   2075: aload #15
    //   2077: iconst_2
    //   2078: aload #15
    //   2080: iconst_1
    //   2081: iaload
    //   2082: iastore
    //   2083: aload #15
    //   2085: iconst_1
    //   2086: aload #15
    //   2088: iconst_0
    //   2089: iaload
    //   2090: iastore
    //   2091: aload #15
    //   2093: iconst_0
    //   2094: iload #17
    //   2096: iastore
    //   2097: iinc #16, 1
    //   2100: iload_2
    //   2101: ifeq -> 1609
    //   2104: iconst_0
    //   2105: istore #16
    //   2107: iload #16
    //   2109: bipush #8
    //   2111: if_icmpge -> 2134
    //   2114: aload #8
    //   2116: iload #16
    //   2118: dup2
    //   2119: iaload
    //   2120: aload #15
    //   2122: iload #16
    //   2124: iaload
    //   2125: iadd
    //   2126: iastore
    //   2127: iinc #16, 1
    //   2130: iload_2
    //   2131: ifeq -> 2107
    //   2134: iinc #13, 64
    //   2137: iinc #11, -64
    //   2140: iload_2
    //   2141: ifeq -> 1531
    //   2144: iload #11
    //   2146: ifle -> 2181
    //   2149: iconst_0
    //   2150: istore #14
    //   2152: iload #14
    //   2154: iload #11
    //   2156: if_icmpge -> 2181
    //   2159: aload #9
    //   2161: iload #12
    //   2163: iload #14
    //   2165: iadd
    //   2166: aload_3
    //   2167: iload #13
    //   2169: iload #14
    //   2171: iadd
    //   2172: baload
    //   2173: bastore
    //   2174: iinc #14, 1
    //   2177: iload_2
    //   2178: ifeq -> 2152
    //   2181: aload #7
    //   2183: iconst_0
    //   2184: iaload
    //   2185: bipush #29
    //   2187: iushr
    //   2188: aload #7
    //   2190: iconst_1
    //   2191: iaload
    //   2192: iconst_3
    //   2193: ishl
    //   2194: ior
    //   2195: istore #14
    //   2197: aload #7
    //   2199: iconst_0
    //   2200: iaload
    //   2201: iconst_3
    //   2202: ishl
    //   2203: istore #15
    //   2205: aload #7
    //   2207: iconst_0
    //   2208: iaload
    //   2209: bipush #63
    //   2211: iand
    //   2212: istore #16
    //   2214: iload #16
    //   2216: bipush #56
    //   2218: if_icmpge -> 2233
    //   2221: bipush #56
    //   2223: iload #16
    //   2225: isub
    //   2226: goto -> 2238
    //   2229: invokestatic a : (Ljava/lang/Throwable;)Ljava/lang/Throwable;
    //   2232: athrow
    //   2233: bipush #120
    //   2235: iload #16
    //   2237: isub
    //   2238: istore #17
    //   2240: aload #7
    //   2242: iconst_0
    //   2243: iaload
    //   2244: bipush #63
    //   2246: iand
    //   2247: istore #12
    //   2249: bipush #64
    //   2251: iload #12
    //   2253: isub
    //   2254: istore #18
    //   2256: aload #7
    //   2258: iconst_0
    //   2259: dup2
    //   2260: iaload
    //   2261: iload #17
    //   2263: iadd
    //   2264: iastore
    //   2265: aload #7
    //   2267: iconst_0
    //   2268: dup2
    //   2269: iaload
    //   2270: iconst_m1
    //   2271: iand
    //   2272: iastore
    //   2273: aload #7
    //   2275: iconst_0
    //   2276: iaload
    //   2277: iload #17
    //   2279: if_icmpge -> 2297
    //   2282: aload #7
    //   2284: iconst_1
    //   2285: dup2
    //   2286: iaload
    //   2287: iconst_1
    //   2288: iadd
    //   2289: iastore
    //   2290: goto -> 2297
    //   2293: invokestatic a : (Ljava/lang/Throwable;)Ljava/lang/Throwable;
    //   2296: athrow
    //   2297: iconst_0
    //   2298: istore #13
    //   2300: iload #12
    //   2302: ifle -> 2933
    //   2305: iload #17
    //   2307: iload #18
    //   2309: if_icmplt -> 2933
    //   2312: goto -> 2319
    //   2315: invokestatic a : (Ljava/lang/Throwable;)Ljava/lang/Throwable;
    //   2318: athrow
    //   2319: iconst_0
    //   2320: istore #19
    //   2322: iload #19
    //   2324: iload #18
    //   2326: if_icmpge -> 2349
    //   2329: aload #9
    //   2331: iload #12
    //   2333: iload #19
    //   2335: iadd
    //   2336: aload #5
    //   2338: iload #19
    //   2340: baload
    //   2341: bastore
    //   2342: iinc #19, 1
    //   2345: iload_2
    //   2346: ifeq -> 2322
    //   2349: bipush #64
    //   2351: newarray int
    //   2353: astore #19
    //   2355: bipush #8
    //   2357: newarray int
    //   2359: astore #20
    //   2361: iconst_0
    //   2362: istore #21
    //   2364: iload #21
    //   2366: bipush #8
    //   2368: if_icmpge -> 2388
    //   2371: aload #20
    //   2373: iload #21
    //   2375: aload #8
    //   2377: iload #21
    //   2379: iaload
    //   2380: iastore
    //   2381: iinc #21, 1
    //   2384: iload_2
    //   2385: ifeq -> 2364
    //   2388: iconst_0
    //   2389: istore #21
    //   2391: iload #21
    //   2393: bipush #64
    //   2395: if_icmpge -> 2886
    //   2398: iload #21
    //   2400: bipush #16
    //   2402: if_icmpge -> 2483
    //   2405: aload #19
    //   2407: iload #21
    //   2409: aload #9
    //   2411: iconst_4
    //   2412: iload #21
    //   2414: imul
    //   2415: baload
    //   2416: sipush #255
    //   2419: iand
    //   2420: bipush #24
    //   2422: ishl
    //   2423: aload #9
    //   2425: iconst_4
    //   2426: iload #21
    //   2428: imul
    //   2429: iconst_1
    //   2430: iadd
    //   2431: baload
    //   2432: sipush #255
    //   2435: iand
    //   2436: bipush #16
    //   2438: ishl
    //   2439: ior
    //   2440: aload #9
    //   2442: iconst_4
    //   2443: iload #21
    //   2445: imul
    //   2446: iconst_2
    //   2447: iadd
    //   2448: baload
    //   2449: sipush #255
    //   2452: iand
    //   2453: bipush #8
    //   2455: ishl
    //   2456: ior
    //   2457: aload #9
    //   2459: iconst_4
    //   2460: iload #21
    //   2462: imul
    //   2463: iconst_3
    //   2464: iadd
    //   2465: baload
    //   2466: sipush #255
    //   2469: iand
    //   2470: ior
    //   2471: iastore
    //   2472: iload_2
    //   2473: ifeq -> 2626
    //   2476: goto -> 2483
    //   2479: invokestatic a : (Ljava/lang/Throwable;)Ljava/lang/Throwable;
    //   2482: athrow
    //   2483: aload #19
    //   2485: iload #21
    //   2487: aload #19
    //   2489: iload #21
    //   2491: iconst_2
    //   2492: isub
    //   2493: iaload
    //   2494: bipush #17
    //   2496: iushr
    //   2497: aload #19
    //   2499: iload #21
    //   2501: iconst_2
    //   2502: isub
    //   2503: iaload
    //   2504: bipush #15
    //   2506: ishl
    //   2507: ior
    //   2508: aload #19
    //   2510: iload #21
    //   2512: iconst_2
    //   2513: isub
    //   2514: iaload
    //   2515: bipush #19
    //   2517: iushr
    //   2518: aload #19
    //   2520: iload #21
    //   2522: iconst_2
    //   2523: isub
    //   2524: iaload
    //   2525: bipush #13
    //   2527: ishl
    //   2528: ior
    //   2529: ixor
    //   2530: aload #19
    //   2532: iload #21
    //   2534: iconst_2
    //   2535: isub
    //   2536: iaload
    //   2537: bipush #10
    //   2539: iushr
    //   2540: ixor
    //   2541: aload #19
    //   2543: iload #21
    //   2545: bipush #7
    //   2547: isub
    //   2548: iaload
    //   2549: iadd
    //   2550: aload #19
    //   2552: iload #21
    //   2554: bipush #15
    //   2556: isub
    //   2557: iaload
    //   2558: bipush #7
    //   2560: iushr
    //   2561: aload #19
    //   2563: iload #21
    //   2565: bipush #15
    //   2567: isub
    //   2568: iaload
    //   2569: bipush #25
    //   2571: ishl
    //   2572: ior
    //   2573: aload #19
    //   2575: iload #21
    //   2577: bipush #15
    //   2579: isub
    //   2580: iaload
    //   2581: bipush #18
    //   2583: iushr
    //   2584: aload #19
    //   2586: iload #21
    //   2588: bipush #15
    //   2590: isub
    //   2591: iaload
    //   2592: bipush #14
    //   2594: ishl
    //   2595: ior
    //   2596: ixor
    //   2597: aload #19
    //   2599: iload #21
    //   2601: bipush #15
    //   2603: isub
    //   2604: iaload
    //   2605: iconst_3
    //   2606: iushr
    //   2607: ixor
    //   2608: iadd
    //   2609: aload #19
    //   2611: iload #21
    //   2613: bipush #16
    //   2615: isub
    //   2616: iaload
    //   2617: iadd
    //   2618: iastore
    //   2619: goto -> 2626
    //   2622: invokestatic a : (Ljava/lang/Throwable;)Ljava/lang/Throwable;
    //   2625: athrow
    //   2626: aload #20
    //   2628: bipush #7
    //   2630: iaload
    //   2631: aload #20
    //   2633: iconst_4
    //   2634: iaload
    //   2635: bipush #6
    //   2637: iushr
    //   2638: aload #20
    //   2640: iconst_4
    //   2641: iaload
    //   2642: bipush #26
    //   2644: ishl
    //   2645: ior
    //   2646: aload #20
    //   2648: iconst_4
    //   2649: iaload
    //   2650: bipush #11
    //   2652: iushr
    //   2653: aload #20
    //   2655: iconst_4
    //   2656: iaload
    //   2657: bipush #21
    //   2659: ishl
    //   2660: ior
    //   2661: ixor
    //   2662: aload #20
    //   2664: iconst_4
    //   2665: iaload
    //   2666: bipush #25
    //   2668: iushr
    //   2669: aload #20
    //   2671: iconst_4
    //   2672: iaload
    //   2673: bipush #7
    //   2675: ishl
    //   2676: ior
    //   2677: ixor
    //   2678: iadd
    //   2679: aload #20
    //   2681: bipush #6
    //   2683: iaload
    //   2684: aload #20
    //   2686: iconst_4
    //   2687: iaload
    //   2688: aload #20
    //   2690: iconst_5
    //   2691: iaload
    //   2692: aload #20
    //   2694: bipush #6
    //   2696: iaload
    //   2697: ixor
    //   2698: iand
    //   2699: ixor
    //   2700: iadd
    //   2701: aload #6
    //   2703: iload #21
    //   2705: iaload
    //   2706: iadd
    //   2707: aload #19
    //   2709: iload #21
    //   2711: iaload
    //   2712: iadd
    //   2713: istore #22
    //   2715: aload #20
    //   2717: iconst_0
    //   2718: iaload
    //   2719: iconst_2
    //   2720: iushr
    //   2721: aload #20
    //   2723: iconst_0
    //   2724: iaload
    //   2725: bipush #30
    //   2727: ishl
    //   2728: ior
    //   2729: aload #20
    //   2731: iconst_0
    //   2732: iaload
    //   2733: bipush #13
    //   2735: iushr
    //   2736: aload #20
    //   2738: iconst_0
    //   2739: iaload
    //   2740: bipush #19
    //   2742: ishl
    //   2743: ior
    //   2744: ixor
    //   2745: aload #20
    //   2747: iconst_0
    //   2748: iaload
    //   2749: bipush #22
    //   2751: iushr
    //   2752: aload #20
    //   2754: iconst_0
    //   2755: iaload
    //   2756: bipush #10
    //   2758: ishl
    //   2759: ior
    //   2760: ixor
    //   2761: aload #20
    //   2763: iconst_0
    //   2764: iaload
    //   2765: aload #20
    //   2767: iconst_1
    //   2768: iaload
    //   2769: iand
    //   2770: aload #20
    //   2772: iconst_2
    //   2773: iaload
    //   2774: aload #20
    //   2776: iconst_0
    //   2777: iaload
    //   2778: aload #20
    //   2780: iconst_1
    //   2781: iaload
    //   2782: ior
    //   2783: iand
    //   2784: ior
    //   2785: iadd
    //   2786: istore #23
    //   2788: aload #20
    //   2790: iconst_3
    //   2791: dup2
    //   2792: iaload
    //   2793: iload #22
    //   2795: iadd
    //   2796: iastore
    //   2797: aload #20
    //   2799: bipush #7
    //   2801: iload #22
    //   2803: iload #23
    //   2805: iadd
    //   2806: iastore
    //   2807: aload #20
    //   2809: bipush #7
    //   2811: iaload
    //   2812: istore #22
    //   2814: aload #20
    //   2816: bipush #7
    //   2818: aload #20
    //   2820: bipush #6
    //   2822: iaload
    //   2823: iastore
    //   2824: aload #20
    //   2826: bipush #6
    //   2828: aload #20
    //   2830: iconst_5
    //   2831: iaload
    //   2832: iastore
    //   2833: aload #20
    //   2835: iconst_5
    //   2836: aload #20
    //   2838: iconst_4
    //   2839: iaload
    //   2840: iastore
    //   2841: aload #20
    //   2843: iconst_4
    //   2844: aload #20
    //   2846: iconst_3
    //   2847: iaload
    //   2848: iastore
    //   2849: aload #20
    //   2851: iconst_3
    //   2852: aload #20
    //   2854: iconst_2
    //   2855: iaload
    //   2856: iastore
    //   2857: aload #20
    //   2859: iconst_2
    //   2860: aload #20
    //   2862: iconst_1
    //   2863: iaload
    //   2864: iastore
    //   2865: aload #20
    //   2867: iconst_1
    //   2868: aload #20
    //   2870: iconst_0
    //   2871: iaload
    //   2872: iastore
    //   2873: aload #20
    //   2875: iconst_0
    //   2876: iload #22
    //   2878: iastore
    //   2879: iinc #21, 1
    //   2882: iload_2
    //   2883: ifeq -> 2391
    //   2886: iconst_0
    //   2887: istore #21
    //   2889: iload #21
    //   2891: bipush #8
    //   2893: if_icmpge -> 2916
    //   2896: aload #8
    //   2898: iload #21
    //   2900: dup2
    //   2901: iaload
    //   2902: aload #20
    //   2904: iload #21
    //   2906: iaload
    //   2907: iadd
    //   2908: iastore
    //   2909: iinc #21, 1
    //   2912: iload_2
    //   2913: ifeq -> 2889
    //   2916: iload #13
    //   2918: iload #18
    //   2920: iadd
    //   2921: istore #13
    //   2923: iload #17
    //   2925: iload #18
    //   2927: isub
    //   2928: istore #17
    //   2930: iconst_0
    //   2931: istore #12
    //   2933: iload #17
    //   2935: bipush #64
    //   2937: if_icmplt -> 3547
    //   2940: iconst_0
    //   2941: istore #19
    //   2943: iload #19
    //   2945: bipush #64
    //   2947: if_icmpge -> 2970
    //   2950: aload #10
    //   2952: iload #19
    //   2954: aload #5
    //   2956: iload #13
    //   2958: iload #19
    //   2960: iadd
    //   2961: baload
    //   2962: bastore
    //   2963: iinc #19, 1
    //   2966: iload_2
    //   2967: ifeq -> 2943
    //   2970: bipush #64
    //   2972: newarray int
    //   2974: astore #19
    //   2976: bipush #8
    //   2978: newarray int
    //   2980: astore #20
    //   2982: iconst_0
    //   2983: istore #21
    //   2985: iload #21
    //   2987: bipush #8
    //   2989: if_icmpge -> 3009
    //   2992: aload #20
    //   2994: iload #21
    //   2996: aload #8
    //   2998: iload #21
    //   3000: iaload
    //   3001: iastore
    //   3002: iinc #21, 1
    //   3005: iload_2
    //   3006: ifeq -> 2985
    //   3009: iconst_0
    //   3010: istore #21
    //   3012: iload #21
    //   3014: bipush #64
    //   3016: if_icmpge -> 3507
    //   3019: iload #21
    //   3021: bipush #16
    //   3023: if_icmpge -> 3104
    //   3026: aload #19
    //   3028: iload #21
    //   3030: aload #10
    //   3032: iconst_4
    //   3033: iload #21
    //   3035: imul
    //   3036: baload
    //   3037: sipush #255
    //   3040: iand
    //   3041: bipush #24
    //   3043: ishl
    //   3044: aload #10
    //   3046: iconst_4
    //   3047: iload #21
    //   3049: imul
    //   3050: iconst_1
    //   3051: iadd
    //   3052: baload
    //   3053: sipush #255
    //   3056: iand
    //   3057: bipush #16
    //   3059: ishl
    //   3060: ior
    //   3061: aload #10
    //   3063: iconst_4
    //   3064: iload #21
    //   3066: imul
    //   3067: iconst_2
    //   3068: iadd
    //   3069: baload
    //   3070: sipush #255
    //   3073: iand
    //   3074: bipush #8
    //   3076: ishl
    //   3077: ior
    //   3078: aload #10
    //   3080: iconst_4
    //   3081: iload #21
    //   3083: imul
    //   3084: iconst_3
    //   3085: iadd
    //   3086: baload
    //   3087: sipush #255
    //   3090: iand
    //   3091: ior
    //   3092: iastore
    //   3093: iload_2
    //   3094: ifeq -> 3247
    //   3097: goto -> 3104
    //   3100: invokestatic a : (Ljava/lang/Throwable;)Ljava/lang/Throwable;
    //   3103: athrow
    //   3104: aload #19
    //   3106: iload #21
    //   3108: aload #19
    //   3110: iload #21
    //   3112: iconst_2
    //   3113: isub
    //   3114: iaload
    //   3115: bipush #17
    //   3117: iushr
    //   3118: aload #19
    //   3120: iload #21
    //   3122: iconst_2
    //   3123: isub
    //   3124: iaload
    //   3125: bipush #15
    //   3127: ishl
    //   3128: ior
    //   3129: aload #19
    //   3131: iload #21
    //   3133: iconst_2
    //   3134: isub
    //   3135: iaload
    //   3136: bipush #19
    //   3138: iushr
    //   3139: aload #19
    //   3141: iload #21
    //   3143: iconst_2
    //   3144: isub
    //   3145: iaload
    //   3146: bipush #13
    //   3148: ishl
    //   3149: ior
    //   3150: ixor
    //   3151: aload #19
    //   3153: iload #21
    //   3155: iconst_2
    //   3156: isub
    //   3157: iaload
    //   3158: bipush #10
    //   3160: iushr
    //   3161: ixor
    //   3162: aload #19
    //   3164: iload #21
    //   3166: bipush #7
    //   3168: isub
    //   3169: iaload
    //   3170: iadd
    //   3171: aload #19
    //   3173: iload #21
    //   3175: bipush #15
    //   3177: isub
    //   3178: iaload
    //   3179: bipush #7
    //   3181: iushr
    //   3182: aload #19
    //   3184: iload #21
    //   3186: bipush #15
    //   3188: isub
    //   3189: iaload
    //   3190: bipush #25
    //   3192: ishl
    //   3193: ior
    //   3194: aload #19
    //   3196: iload #21
    //   3198: bipush #15
    //   3200: isub
    //   3201: iaload
    //   3202: bipush #18
    //   3204: iushr
    //   3205: aload #19
    //   3207: iload #21
    //   3209: bipush #15
    //   3211: isub
    //   3212: iaload
    //   3213: bipush #14
    //   3215: ishl
    //   3216: ior
    //   3217: ixor
    //   3218: aload #19
    //   3220: iload #21
    //   3222: bipush #15
    //   3224: isub
    //   3225: iaload
    //   3226: iconst_3
    //   3227: iushr
    //   3228: ixor
    //   3229: iadd
    //   3230: aload #19
    //   3232: iload #21
    //   3234: bipush #16
    //   3236: isub
    //   3237: iaload
    //   3238: iadd
    //   3239: iastore
    //   3240: goto -> 3247
    //   3243: invokestatic a : (Ljava/lang/Throwable;)Ljava/lang/Throwable;
    //   3246: athrow
    //   3247: aload #20
    //   3249: bipush #7
    //   3251: iaload
    //   3252: aload #20
    //   3254: iconst_4
    //   3255: iaload
    //   3256: bipush #6
    //   3258: iushr
    //   3259: aload #20
    //   3261: iconst_4
    //   3262: iaload
    //   3263: bipush #26
    //   3265: ishl
    //   3266: ior
    //   3267: aload #20
    //   3269: iconst_4
    //   3270: iaload
    //   3271: bipush #11
    //   3273: iushr
    //   3274: aload #20
    //   3276: iconst_4
    //   3277: iaload
    //   3278: bipush #21
    //   3280: ishl
    //   3281: ior
    //   3282: ixor
    //   3283: aload #20
    //   3285: iconst_4
    //   3286: iaload
    //   3287: bipush #25
    //   3289: iushr
    //   3290: aload #20
    //   3292: iconst_4
    //   3293: iaload
    //   3294: bipush #7
    //   3296: ishl
    //   3297: ior
    //   3298: ixor
    //   3299: iadd
    //   3300: aload #20
    //   3302: bipush #6
    //   3304: iaload
    //   3305: aload #20
    //   3307: iconst_4
    //   3308: iaload
    //   3309: aload #20
    //   3311: iconst_5
    //   3312: iaload
    //   3313: aload #20
    //   3315: bipush #6
    //   3317: iaload
    //   3318: ixor
    //   3319: iand
    //   3320: ixor
    //   3321: iadd
    //   3322: aload #6
    //   3324: iload #21
    //   3326: iaload
    //   3327: iadd
    //   3328: aload #19
    //   3330: iload #21
    //   3332: iaload
    //   3333: iadd
    //   3334: istore #22
    //   3336: aload #20
    //   3338: iconst_0
    //   3339: iaload
    //   3340: iconst_2
    //   3341: iushr
    //   3342: aload #20
    //   3344: iconst_0
    //   3345: iaload
    //   3346: bipush #30
    //   3348: ishl
    //   3349: ior
    //   3350: aload #20
    //   3352: iconst_0
    //   3353: iaload
    //   3354: bipush #13
    //   3356: iushr
    //   3357: aload #20
    //   3359: iconst_0
    //   3360: iaload
    //   3361: bipush #19
    //   3363: ishl
    //   3364: ior
    //   3365: ixor
    //   3366: aload #20
    //   3368: iconst_0
    //   3369: iaload
    //   3370: bipush #22
    //   3372: iushr
    //   3373: aload #20
    //   3375: iconst_0
    //   3376: iaload
    //   3377: bipush #10
    //   3379: ishl
    //   3380: ior
    //   3381: ixor
    //   3382: aload #20
    //   3384: iconst_0
    //   3385: iaload
    //   3386: aload #20
    //   3388: iconst_1
    //   3389: iaload
    //   3390: iand
    //   3391: aload #20
    //   3393: iconst_2
    //   3394: iaload
    //   3395: aload #20
    //   3397: iconst_0
    //   3398: iaload
    //   3399: aload #20
    //   3401: iconst_1
    //   3402: iaload
    //   3403: ior
    //   3404: iand
    //   3405: ior
    //   3406: iadd
    //   3407: istore #23
    //   3409: aload #20
    //   3411: iconst_3
    //   3412: dup2
    //   3413: iaload
    //   3414: iload #22
    //   3416: iadd
    //   3417: iastore
    //   3418: aload #20
    //   3420: bipush #7
    //   3422: iload #22
    //   3424: iload #23
    //   3426: iadd
    //   3427: iastore
    //   3428: aload #20
    //   3430: bipush #7
    //   3432: iaload
    //   3433: istore #22
    //   3435: aload #20
    //   3437: bipush #7
    //   3439: aload #20
    //   3441: bipush #6
    //   3443: iaload
    //   3444: iastore
    //   3445: aload #20
    //   3447: bipush #6
    //   3449: aload #20
    //   3451: iconst_5
    //   3452: iaload
    //   3453: iastore
    //   3454: aload #20
    //   3456: iconst_5
    //   3457: aload #20
    //   3459: iconst_4
    //   3460: iaload
    //   3461: iastore
    //   3462: aload #20
    //   3464: iconst_4
    //   3465: aload #20
    //   3467: iconst_3
    //   3468: iaload
    //   3469: iastore
    //   3470: aload #20
    //   3472: iconst_3
    //   3473: aload #20
    //   3475: iconst_2
    //   3476: iaload
    //   3477: iastore
    //   3478: aload #20
    //   3480: iconst_2
    //   3481: aload #20
    //   3483: iconst_1
    //   3484: iaload
    //   3485: iastore
    //   3486: aload #20
    //   3488: iconst_1
    //   3489: aload #20
    //   3491: iconst_0
    //   3492: iaload
    //   3493: iastore
    //   3494: aload #20
    //   3496: iconst_0
    //   3497: iload #22
    //   3499: iastore
    //   3500: iinc #21, 1
    //   3503: iload_2
    //   3504: ifeq -> 3012
    //   3507: iconst_0
    //   3508: istore #21
    //   3510: iload #21
    //   3512: bipush #8
    //   3514: if_icmpge -> 3537
    //   3517: aload #8
    //   3519: iload #21
    //   3521: dup2
    //   3522: iaload
    //   3523: aload #20
    //   3525: iload #21
    //   3527: iaload
    //   3528: iadd
    //   3529: iastore
    //   3530: iinc #21, 1
    //   3533: iload_2
    //   3534: ifeq -> 3510
    //   3537: iinc #13, 64
    //   3540: iinc #17, -64
    //   3543: iload_2
    //   3544: ifeq -> 2933
    //   3547: iload #17
    //   3549: ifle -> 3585
    //   3552: iconst_0
    //   3553: istore #19
    //   3555: iload #19
    //   3557: iload #17
    //   3559: if_icmpge -> 3585
    //   3562: aload #9
    //   3564: iload #12
    //   3566: iload #19
    //   3568: iadd
    //   3569: aload #5
    //   3571: iload #13
    //   3573: iload #19
    //   3575: iadd
    //   3576: baload
    //   3577: bastore
    //   3578: iinc #19, 1
    //   3581: iload_2
    //   3582: ifeq -> 3555
    //   3585: bipush #8
    //   3587: newarray byte
    //   3589: astore #19
    //   3591: aload #19
    //   3593: iconst_0
    //   3594: iload #14
    //   3596: bipush #24
    //   3598: iushr
    //   3599: i2b
    //   3600: bastore
    //   3601: aload #19
    //   3603: iconst_1
    //   3604: iload #14
    //   3606: bipush #16
    //   3608: iushr
    //   3609: i2b
    //   3610: bastore
    //   3611: aload #19
    //   3613: iconst_2
    //   3614: iload #14
    //   3616: bipush #8
    //   3618: iushr
    //   3619: i2b
    //   3620: bastore
    //   3621: aload #19
    //   3623: iconst_3
    //   3624: iload #14
    //   3626: i2b
    //   3627: bastore
    //   3628: aload #19
    //   3630: iconst_4
    //   3631: iload #15
    //   3633: bipush #24
    //   3635: iushr
    //   3636: i2b
    //   3637: bastore
    //   3638: aload #19
    //   3640: iconst_5
    //   3641: iload #15
    //   3643: bipush #16
    //   3645: iushr
    //   3646: i2b
    //   3647: bastore
    //   3648: aload #19
    //   3650: bipush #6
    //   3652: iload #15
    //   3654: bipush #8
    //   3656: iushr
    //   3657: i2b
    //   3658: bastore
    //   3659: aload #19
    //   3661: bipush #7
    //   3663: iload #15
    //   3665: i2b
    //   3666: bastore
    //   3667: bipush #8
    //   3669: istore #11
    //   3671: aload #7
    //   3673: iconst_0
    //   3674: iaload
    //   3675: bipush #63
    //   3677: iand
    //   3678: istore #12
    //   3680: bipush #64
    //   3682: iload #12
    //   3684: isub
    //   3685: istore #18
    //   3687: aload #7
    //   3689: iconst_0
    //   3690: dup2
    //   3691: iaload
    //   3692: iload #11
    //   3694: iadd
    //   3695: iastore
    //   3696: aload #7
    //   3698: iconst_0
    //   3699: dup2
    //   3700: iaload
    //   3701: iconst_m1
    //   3702: iand
    //   3703: iastore
    //   3704: aload #7
    //   3706: iconst_0
    //   3707: iaload
    //   3708: iload #11
    //   3710: if_icmpge -> 3728
    //   3713: aload #7
    //   3715: iconst_1
    //   3716: dup2
    //   3717: iaload
    //   3718: iconst_1
    //   3719: iadd
    //   3720: iastore
    //   3721: goto -> 3728
    //   3724: invokestatic a : (Ljava/lang/Throwable;)Ljava/lang/Throwable;
    //   3727: athrow
    //   3728: iload #12
    //   3730: ifle -> 4344
    //   3733: iload #11
    //   3735: iload #18
    //   3737: if_icmplt -> 4344
    //   3740: goto -> 3747
    //   3743: invokestatic a : (Ljava/lang/Throwable;)Ljava/lang/Throwable;
    //   3746: athrow
    //   3747: iconst_0
    //   3748: istore #20
    //   3750: iload #20
    //   3752: iload #18
    //   3754: if_icmpge -> 3777
    //   3757: aload #9
    //   3759: iload #12
    //   3761: iload #20
    //   3763: iadd
    //   3764: aload #19
    //   3766: iload #20
    //   3768: baload
    //   3769: bastore
    //   3770: iinc #20, 1
    //   3773: iload_2
    //   3774: ifeq -> 3750
    //   3777: bipush #64
    //   3779: newarray int
    //   3781: astore #20
    //   3783: bipush #8
    //   3785: newarray int
    //   3787: astore #21
    //   3789: iconst_0
    //   3790: istore #22
    //   3792: iload #22
    //   3794: bipush #8
    //   3796: if_icmpge -> 3816
    //   3799: aload #21
    //   3801: iload #22
    //   3803: aload #8
    //   3805: iload #22
    //   3807: iaload
    //   3808: iastore
    //   3809: iinc #22, 1
    //   3812: iload_2
    //   3813: ifeq -> 3792
    //   3816: iconst_0
    //   3817: istore #22
    //   3819: iload #22
    //   3821: bipush #64
    //   3823: if_icmpge -> 4314
    //   3826: iload #22
    //   3828: bipush #16
    //   3830: if_icmpge -> 3911
    //   3833: aload #20
    //   3835: iload #22
    //   3837: aload #9
    //   3839: iconst_4
    //   3840: iload #22
    //   3842: imul
    //   3843: baload
    //   3844: sipush #255
    //   3847: iand
    //   3848: bipush #24
    //   3850: ishl
    //   3851: aload #9
    //   3853: iconst_4
    //   3854: iload #22
    //   3856: imul
    //   3857: iconst_1
    //   3858: iadd
    //   3859: baload
    //   3860: sipush #255
    //   3863: iand
    //   3864: bipush #16
    //   3866: ishl
    //   3867: ior
    //   3868: aload #9
    //   3870: iconst_4
    //   3871: iload #22
    //   3873: imul
    //   3874: iconst_2
    //   3875: iadd
    //   3876: baload
    //   3877: sipush #255
    //   3880: iand
    //   3881: bipush #8
    //   3883: ishl
    //   3884: ior
    //   3885: aload #9
    //   3887: iconst_4
    //   3888: iload #22
    //   3890: imul
    //   3891: iconst_3
    //   3892: iadd
    //   3893: baload
    //   3894: sipush #255
    //   3897: iand
    //   3898: ior
    //   3899: iastore
    //   3900: iload_2
    //   3901: ifeq -> 4054
    //   3904: goto -> 3911
    //   3907: invokestatic a : (Ljava/lang/Throwable;)Ljava/lang/Throwable;
    //   3910: athrow
    //   3911: aload #20
    //   3913: iload #22
    //   3915: aload #20
    //   3917: iload #22
    //   3919: iconst_2
    //   3920: isub
    //   3921: iaload
    //   3922: bipush #17
    //   3924: iushr
    //   3925: aload #20
    //   3927: iload #22
    //   3929: iconst_2
    //   3930: isub
    //   3931: iaload
    //   3932: bipush #15
    //   3934: ishl
    //   3935: ior
    //   3936: aload #20
    //   3938: iload #22
    //   3940: iconst_2
    //   3941: isub
    //   3942: iaload
    //   3943: bipush #19
    //   3945: iushr
    //   3946: aload #20
    //   3948: iload #22
    //   3950: iconst_2
    //   3951: isub
    //   3952: iaload
    //   3953: bipush #13
    //   3955: ishl
    //   3956: ior
    //   3957: ixor
    //   3958: aload #20
    //   3960: iload #22
    //   3962: iconst_2
    //   3963: isub
    //   3964: iaload
    //   3965: bipush #10
    //   3967: iushr
    //   3968: ixor
    //   3969: aload #20
    //   3971: iload #22
    //   3973: bipush #7
    //   3975: isub
    //   3976: iaload
    //   3977: iadd
    //   3978: aload #20
    //   3980: iload #22
    //   3982: bipush #15
    //   3984: isub
    //   3985: iaload
    //   3986: bipush #7
    //   3988: iushr
    //   3989: aload #20
    //   3991: iload #22
    //   3993: bipush #15
    //   3995: isub
    //   3996: iaload
    //   3997: bipush #25
    //   3999: ishl
    //   4000: ior
    //   4001: aload #20
    //   4003: iload #22
    //   4005: bipush #15
    //   4007: isub
    //   4008: iaload
    //   4009: bipush #18
    //   4011: iushr
    //   4012: aload #20
    //   4014: iload #22
    //   4016: bipush #15
    //   4018: isub
    //   4019: iaload
    //   4020: bipush #14
    //   4022: ishl
    //   4023: ior
    //   4024: ixor
    //   4025: aload #20
    //   4027: iload #22
    //   4029: bipush #15
    //   4031: isub
    //   4032: iaload
    //   4033: iconst_3
    //   4034: iushr
    //   4035: ixor
    //   4036: iadd
    //   4037: aload #20
    //   4039: iload #22
    //   4041: bipush #16
    //   4043: isub
    //   4044: iaload
    //   4045: iadd
    //   4046: iastore
    //   4047: goto -> 4054
    //   4050: invokestatic a : (Ljava/lang/Throwable;)Ljava/lang/Throwable;
    //   4053: athrow
    //   4054: aload #21
    //   4056: bipush #7
    //   4058: iaload
    //   4059: aload #21
    //   4061: iconst_4
    //   4062: iaload
    //   4063: bipush #6
    //   4065: iushr
    //   4066: aload #21
    //   4068: iconst_4
    //   4069: iaload
    //   4070: bipush #26
    //   4072: ishl
    //   4073: ior
    //   4074: aload #21
    //   4076: iconst_4
    //   4077: iaload
    //   4078: bipush #11
    //   4080: iushr
    //   4081: aload #21
    //   4083: iconst_4
    //   4084: iaload
    //   4085: bipush #21
    //   4087: ishl
    //   4088: ior
    //   4089: ixor
    //   4090: aload #21
    //   4092: iconst_4
    //   4093: iaload
    //   4094: bipush #25
    //   4096: iushr
    //   4097: aload #21
    //   4099: iconst_4
    //   4100: iaload
    //   4101: bipush #7
    //   4103: ishl
    //   4104: ior
    //   4105: ixor
    //   4106: iadd
    //   4107: aload #21
    //   4109: bipush #6
    //   4111: iaload
    //   4112: aload #21
    //   4114: iconst_4
    //   4115: iaload
    //   4116: aload #21
    //   4118: iconst_5
    //   4119: iaload
    //   4120: aload #21
    //   4122: bipush #6
    //   4124: iaload
    //   4125: ixor
    //   4126: iand
    //   4127: ixor
    //   4128: iadd
    //   4129: aload #6
    //   4131: iload #22
    //   4133: iaload
    //   4134: iadd
    //   4135: aload #20
    //   4137: iload #22
    //   4139: iaload
    //   4140: iadd
    //   4141: istore #23
    //   4143: aload #21
    //   4145: iconst_0
    //   4146: iaload
    //   4147: iconst_2
    //   4148: iushr
    //   4149: aload #21
    //   4151: iconst_0
    //   4152: iaload
    //   4153: bipush #30
    //   4155: ishl
    //   4156: ior
    //   4157: aload #21
    //   4159: iconst_0
    //   4160: iaload
    //   4161: bipush #13
    //   4163: iushr
    //   4164: aload #21
    //   4166: iconst_0
    //   4167: iaload
    //   4168: bipush #19
    //   4170: ishl
    //   4171: ior
    //   4172: ixor
    //   4173: aload #21
    //   4175: iconst_0
    //   4176: iaload
    //   4177: bipush #22
    //   4179: iushr
    //   4180: aload #21
    //   4182: iconst_0
    //   4183: iaload
    //   4184: bipush #10
    //   4186: ishl
    //   4187: ior
    //   4188: ixor
    //   4189: aload #21
    //   4191: iconst_0
    //   4192: iaload
    //   4193: aload #21
    //   4195: iconst_1
    //   4196: iaload
    //   4197: iand
    //   4198: aload #21
    //   4200: iconst_2
    //   4201: iaload
    //   4202: aload #21
    //   4204: iconst_0
    //   4205: iaload
    //   4206: aload #21
    //   4208: iconst_1
    //   4209: iaload
    //   4210: ior
    //   4211: iand
    //   4212: ior
    //   4213: iadd
    //   4214: istore #24
    //   4216: aload #21
    //   4218: iconst_3
    //   4219: dup2
    //   4220: iaload
    //   4221: iload #23
    //   4223: iadd
    //   4224: iastore
    //   4225: aload #21
    //   4227: bipush #7
    //   4229: iload #23
    //   4231: iload #24
    //   4233: iadd
    //   4234: iastore
    //   4235: aload #21
    //   4237: bipush #7
    //   4239: iaload
    //   4240: istore #23
    //   4242: aload #21
    //   4244: bipush #7
    //   4246: aload #21
    //   4248: bipush #6
    //   4250: iaload
    //   4251: iastore
    //   4252: aload #21
    //   4254: bipush #6
    //   4256: aload #21
    //   4258: iconst_5
    //   4259: iaload
    //   4260: iastore
    //   4261: aload #21
    //   4263: iconst_5
    //   4264: aload #21
    //   4266: iconst_4
    //   4267: iaload
    //   4268: iastore
    //   4269: aload #21
    //   4271: iconst_4
    //   4272: aload #21
    //   4274: iconst_3
    //   4275: iaload
    //   4276: iastore
    //   4277: aload #21
    //   4279: iconst_3
    //   4280: aload #21
    //   4282: iconst_2
    //   4283: iaload
    //   4284: iastore
    //   4285: aload #21
    //   4287: iconst_2
    //   4288: aload #21
    //   4290: iconst_1
    //   4291: iaload
    //   4292: iastore
    //   4293: aload #21
    //   4295: iconst_1
    //   4296: aload #21
    //   4298: iconst_0
    //   4299: iaload
    //   4300: iastore
    //   4301: aload #21
    //   4303: iconst_0
    //   4304: iload #23
    //   4306: iastore
    //   4307: iinc #22, 1
    //   4310: iload_2
    //   4311: ifeq -> 3819
    //   4314: iconst_0
    //   4315: istore #22
    //   4317: iload #22
    //   4319: bipush #8
    //   4321: if_icmpge -> 4344
    //   4324: aload #8
    //   4326: iload #22
    //   4328: dup2
    //   4329: iaload
    //   4330: aload #21
    //   4332: iload #22
    //   4334: iaload
    //   4335: iadd
    //   4336: iastore
    //   4337: iinc #22, 1
    //   4340: iload_2
    //   4341: ifeq -> 4317
    //   4344: bipush #32
    //   4346: newarray byte
    //   4348: astore #4
    //   4350: aload #4
    //   4352: iconst_0
    //   4353: aload #8
    //   4355: iconst_0
    //   4356: iaload
    //   4357: bipush #24
    //   4359: iushr
    //   4360: i2b
    //   4361: bastore
    //   4362: aload #4
    //   4364: iconst_1
    //   4365: aload #8
    //   4367: iconst_0
    //   4368: iaload
    //   4369: bipush #16
    //   4371: iushr
    //   4372: i2b
    //   4373: bastore
    //   4374: aload #4
    //   4376: iconst_2
    //   4377: aload #8
    //   4379: iconst_0
    //   4380: iaload
    //   4381: bipush #8
    //   4383: iushr
    //   4384: i2b
    //   4385: bastore
    //   4386: aload #4
    //   4388: iconst_3
    //   4389: aload #8
    //   4391: iconst_0
    //   4392: iaload
    //   4393: i2b
    //   4394: bastore
    //   4395: aload #4
    //   4397: iconst_4
    //   4398: aload #8
    //   4400: iconst_1
    //   4401: iaload
    //   4402: bipush #24
    //   4404: iushr
    //   4405: i2b
    //   4406: bastore
    //   4407: aload #4
    //   4409: iconst_5
    //   4410: aload #8
    //   4412: iconst_1
    //   4413: iaload
    //   4414: bipush #16
    //   4416: iushr
    //   4417: i2b
    //   4418: bastore
    //   4419: aload #4
    //   4421: bipush #6
    //   4423: aload #8
    //   4425: iconst_1
    //   4426: iaload
    //   4427: bipush #8
    //   4429: iushr
    //   4430: i2b
    //   4431: bastore
    //   4432: aload #4
    //   4434: bipush #7
    //   4436: aload #8
    //   4438: iconst_1
    //   4439: iaload
    //   4440: i2b
    //   4441: bastore
    //   4442: aload #4
    //   4444: bipush #8
    //   4446: aload #8
    //   4448: iconst_2
    //   4449: iaload
    //   4450: bipush #24
    //   4452: iushr
    //   4453: i2b
    //   4454: bastore
    //   4455: aload #4
    //   4457: bipush #9
    //   4459: aload #8
    //   4461: iconst_2
    //   4462: iaload
    //   4463: bipush #16
    //   4465: iushr
    //   4466: i2b
    //   4467: bastore
    //   4468: aload #4
    //   4470: bipush #10
    //   4472: aload #8
    //   4474: iconst_2
    //   4475: iaload
    //   4476: bipush #8
    //   4478: iushr
    //   4479: i2b
    //   4480: bastore
    //   4481: aload #4
    //   4483: bipush #11
    //   4485: aload #8
    //   4487: iconst_2
    //   4488: iaload
    //   4489: i2b
    //   4490: bastore
    //   4491: aload #4
    //   4493: bipush #12
    //   4495: aload #8
    //   4497: iconst_3
    //   4498: iaload
    //   4499: bipush #24
    //   4501: iushr
    //   4502: i2b
    //   4503: bastore
    //   4504: aload #4
    //   4506: bipush #13
    //   4508: aload #8
    //   4510: iconst_3
    //   4511: iaload
    //   4512: bipush #16
    //   4514: iushr
    //   4515: i2b
    //   4516: bastore
    //   4517: aload #4
    //   4519: bipush #14
    //   4521: aload #8
    //   4523: iconst_3
    //   4524: iaload
    //   4525: bipush #8
    //   4527: iushr
    //   4528: i2b
    //   4529: bastore
    //   4530: aload #4
    //   4532: bipush #15
    //   4534: aload #8
    //   4536: iconst_3
    //   4537: iaload
    //   4538: i2b
    //   4539: bastore
    //   4540: aload #4
    //   4542: bipush #16
    //   4544: aload #8
    //   4546: iconst_4
    //   4547: iaload
    //   4548: bipush #24
    //   4550: iushr
    //   4551: i2b
    //   4552: bastore
    //   4553: aload #4
    //   4555: bipush #17
    //   4557: aload #8
    //   4559: iconst_4
    //   4560: iaload
    //   4561: bipush #16
    //   4563: iushr
    //   4564: i2b
    //   4565: bastore
    //   4566: aload #4
    //   4568: bipush #18
    //   4570: aload #8
    //   4572: iconst_4
    //   4573: iaload
    //   4574: bipush #8
    //   4576: iushr
    //   4577: i2b
    //   4578: bastore
    //   4579: aload #4
    //   4581: bipush #19
    //   4583: aload #8
    //   4585: iconst_4
    //   4586: iaload
    //   4587: i2b
    //   4588: bastore
    //   4589: aload #4
    //   4591: bipush #20
    //   4593: aload #8
    //   4595: iconst_5
    //   4596: iaload
    //   4597: bipush #24
    //   4599: iushr
    //   4600: i2b
    //   4601: bastore
    //   4602: aload #4
    //   4604: bipush #21
    //   4606: aload #8
    //   4608: iconst_5
    //   4609: iaload
    //   4610: bipush #16
    //   4612: iushr
    //   4613: i2b
    //   4614: bastore
    //   4615: aload #4
    //   4617: bipush #22
    //   4619: aload #8
    //   4621: iconst_5
    //   4622: iaload
    //   4623: bipush #8
    //   4625: iushr
    //   4626: i2b
    //   4627: bastore
    //   4628: aload #4
    //   4630: bipush #23
    //   4632: aload #8
    //   4634: iconst_5
    //   4635: iaload
    //   4636: i2b
    //   4637: bastore
    //   4638: aload #4
    //   4640: bipush #24
    //   4642: aload #8
    //   4644: bipush #6
    //   4646: iaload
    //   4647: bipush #24
    //   4649: iushr
    //   4650: i2b
    //   4651: bastore
    //   4652: aload #4
    //   4654: bipush #25
    //   4656: aload #8
    //   4658: bipush #6
    //   4660: iaload
    //   4661: bipush #16
    //   4663: iushr
    //   4664: i2b
    //   4665: bastore
    //   4666: aload #4
    //   4668: bipush #26
    //   4670: aload #8
    //   4672: bipush #6
    //   4674: iaload
    //   4675: bipush #8
    //   4677: iushr
    //   4678: i2b
    //   4679: bastore
    //   4680: aload #4
    //   4682: bipush #27
    //   4684: aload #8
    //   4686: bipush #6
    //   4688: iaload
    //   4689: i2b
    //   4690: bastore
    //   4691: aload #4
    //   4693: bipush #28
    //   4695: aload #8
    //   4697: bipush #7
    //   4699: iaload
    //   4700: bipush #24
    //   4702: iushr
    //   4703: i2b
    //   4704: bastore
    //   4705: aload #4
    //   4707: bipush #29
    //   4709: aload #8
    //   4711: bipush #7
    //   4713: iaload
    //   4714: bipush #16
    //   4716: iushr
    //   4717: i2b
    //   4718: bastore
    //   4719: aload #4
    //   4721: bipush #30
    //   4723: aload #8
    //   4725: bipush #7
    //   4727: iaload
    //   4728: bipush #8
    //   4730: iushr
    //   4731: i2b
    //   4732: bastore
    //   4733: aload #4
    //   4735: bipush #31
    //   4737: aload #8
    //   4739: bipush #7
    //   4741: iaload
    //   4742: i2b
    //   4743: bastore
    //   4744: new java/math/BigInteger
    //   4747: dup
    //   4748: aload #4
    //   4750: invokespecial <init> : ([B)V
    //   4753: invokevirtual abs : ()Ljava/math/BigInteger;
    //   4756: putstatic burp/Zmdf.ZH : Ljava/lang/Object;
    //   4759: new java/lang/StringBuilder
    //   4762: dup
    //   4763: invokespecial <init> : ()V
    //   4766: astore_3
    //   4767: iconst_0
    //   4768: istore #4
    //   4770: iload #4
    //   4772: bipush #32
    //   4774: if_icmpge -> 6107
    //   4777: iload #4
    //   4779: tableswitch default -> 6100, 0 -> 4920, 1 -> 4957, 2 -> 4994, 3 -> 5031, 4 -> 5068, 5 -> 5105, 6 -> 5142, 7 -> 5179, 8 -> 5216, 9 -> 5253, 10 -> 5290, 11 -> 5327, 12 -> 5364, 13 -> 5401, 14 -> 5438, 15 -> 5475, 16 -> 5512, 17 -> 5549, 18 -> 5586, 19 -> 5623, 20 -> 5660, 21 -> 5697, 22 -> 5734, 23 -> 5771, 24 -> 5808, 25 -> 5845, 26 -> 5882, 27 -> 5919, 28 -> 5956, 29 -> 5993, 30 -> 6030, 31 -> 6067
    //   4920: aload_3
    //   4921: getstatic burp/Zzl4.ZT : Ljava/lang/String;
    //   4924: getstatic burp/Zkeb.ZH : Ljava/lang/Object;
    //   4927: checkcast java/math/BigInteger
    //   4930: invokevirtual intValue : ()I
    //   4933: bipush #32
    //   4935: irem
    //   4936: invokestatic abs : (I)I
    //   4939: invokevirtual charAt : (I)C
    //   4942: invokevirtual append : (C)Ljava/lang/StringBuilder;
    //   4945: pop
    //   4946: iload_2
    //   4947: ifeq -> 6100
    //   4950: goto -> 4957
    //   4953: invokestatic a : (Ljava/lang/Throwable;)Ljava/lang/Throwable;
    //   4956: athrow
    //   4957: aload_3
    //   4958: getstatic burp/Zrkd.ZL : Ljava/lang/String;
    //   4961: getstatic burp/Zk92.Zn : Ljava/lang/Object;
    //   4964: checkcast java/math/BigInteger
    //   4967: invokevirtual intValue : ()I
    //   4970: bipush #32
    //   4972: irem
    //   4973: invokestatic abs : (I)I
    //   4976: invokevirtual charAt : (I)C
    //   4979: invokevirtual append : (C)Ljava/lang/StringBuilder;
    //   4982: pop
    //   4983: iload_2
    //   4984: ifeq -> 6100
    //   4987: goto -> 4994
    //   4990: invokestatic a : (Ljava/lang/Throwable;)Ljava/lang/Throwable;
    //   4993: athrow
    //   4994: aload_3
    //   4995: getstatic burp/Zzl4.ZT : Ljava/lang/String;
    //   4998: getstatic burp/Zgu4.Zs : Ljava/lang/Object;
    //   5001: checkcast java/math/BigInteger
    //   5004: invokevirtual intValue : ()I
    //   5007: bipush #32
    //   5009: irem
    //   5010: invokestatic abs : (I)I
    //   5013: invokevirtual charAt : (I)C
    //   5016: invokevirtual append : (C)Ljava/lang/StringBuilder;
    //   5019: pop
    //   5020: iload_2
    //   5021: ifeq -> 6100
    //   5024: goto -> 5031
    //   5027: invokestatic a : (Ljava/lang/Throwable;)Ljava/lang/Throwable;
    //   5030: athrow
    //   5031: aload_3
    //   5032: getstatic burp/Zmpx.ZC : Ljava/lang/String;
    //   5035: getstatic burp/Zg2u.ZI : Ljava/lang/Object;
    //   5038: checkcast java/math/BigInteger
    //   5041: invokevirtual intValue : ()I
    //   5044: bipush #32
    //   5046: irem
    //   5047: invokestatic abs : (I)I
    //   5050: invokevirtual charAt : (I)C
    //   5053: invokevirtual append : (C)Ljava/lang/StringBuilder;
    //   5056: pop
    //   5057: iload_2
    //   5058: ifeq -> 6100
    //   5061: goto -> 5068
    //   5064: invokestatic a : (Ljava/lang/Throwable;)Ljava/lang/Throwable;
    //   5067: athrow
    //   5068: aload_3
    //   5069: getstatic burp/Zv8d.Zi : Ljava/lang/String;
    //   5072: getstatic burp/Zm_u.Zf : Ljava/lang/Object;
    //   5075: checkcast java/math/BigInteger
    //   5078: invokevirtual intValue : ()I
    //   5081: bipush #32
    //   5083: irem
    //   5084: invokestatic abs : (I)I
    //   5087: invokevirtual charAt : (I)C
    //   5090: invokevirtual append : (C)Ljava/lang/StringBuilder;
    //   5093: pop
    //   5094: iload_2
    //   5095: ifeq -> 6100
    //   5098: goto -> 5105
    //   5101: invokestatic a : (Ljava/lang/Throwable;)Ljava/lang/Throwable;
    //   5104: athrow
    //   5105: aload_3
    //   5106: getstatic burp/Zm83.Zq : Ljava/lang/String;
    //   5109: getstatic burp/Ze4a.ZP : Ljava/lang/Object;
    //   5112: checkcast java/math/BigInteger
    //   5115: invokevirtual intValue : ()I
    //   5118: bipush #32
    //   5120: irem
    //   5121: invokestatic abs : (I)I
    //   5124: invokevirtual charAt : (I)C
    //   5127: invokevirtual append : (C)Ljava/lang/StringBuilder;
    //   5130: pop
    //   5131: iload_2
    //   5132: ifeq -> 6100
    //   5135: goto -> 5142
    //   5138: invokestatic a : (Ljava/lang/Throwable;)Ljava/lang/Throwable;
    //   5141: athrow
    //   5142: aload_3
    //   5143: getstatic burp/Zeqz.ZV : Ljava/lang/String;
    //   5146: getstatic burp/Zegw.ZW : Ljava/lang/Object;
    //   5149: checkcast java/math/BigInteger
    //   5152: invokevirtual intValue : ()I
    //   5155: bipush #32
    //   5157: irem
    //   5158: invokestatic abs : (I)I
    //   5161: invokevirtual charAt : (I)C
    //   5164: invokevirtual append : (C)Ljava/lang/StringBuilder;
    //   5167: pop
    //   5168: iload_2
    //   5169: ifeq -> 6100
    //   5172: goto -> 5179
    //   5175: invokestatic a : (Ljava/lang/Throwable;)Ljava/lang/Throwable;
    //   5178: athrow
    //   5179: aload_3
    //   5180: getstatic burp/Zm7v.ZX : Ljava/lang/String;
    //   5183: getstatic burp/Zkdq.ZG : Ljava/lang/Object;
    //   5186: checkcast java/math/BigInteger
    //   5189: invokevirtual intValue : ()I
    //   5192: bipush #32
    //   5194: irem
    //   5195: invokestatic abs : (I)I
    //   5198: invokevirtual charAt : (I)C
    //   5201: invokevirtual append : (C)Ljava/lang/StringBuilder;
    //   5204: pop
    //   5205: iload_2
    //   5206: ifeq -> 6100
    //   5209: goto -> 5216
    //   5212: invokestatic a : (Ljava/lang/Throwable;)Ljava/lang/Throwable;
    //   5215: athrow
    //   5216: aload_3
    //   5217: getstatic burp/Zebe.ZW : Ljava/lang/String;
    //   5220: getstatic burp/Zkf6.ZS : Ljava/lang/Object;
    //   5223: checkcast java/math/BigInteger
    //   5226: invokevirtual intValue : ()I
    //   5229: bipush #32
    //   5231: irem
    //   5232: invokestatic abs : (I)I
    //   5235: invokevirtual charAt : (I)C
    //   5238: invokevirtual append : (C)Ljava/lang/StringBuilder;
    //   5241: pop
    //   5242: iload_2
    //   5243: ifeq -> 6100
    //   5246: goto -> 5253
    //   5249: invokestatic a : (Ljava/lang/Throwable;)Ljava/lang/Throwable;
    //   5252: athrow
    //   5253: aload_3
    //   5254: getstatic burp/Zxju.Zt : Ljava/lang/String;
    //   5257: getstatic burp/Zz7j.ZR : Ljava/lang/Object;
    //   5260: checkcast java/math/BigInteger
    //   5263: invokevirtual intValue : ()I
    //   5266: bipush #32
    //   5268: irem
    //   5269: invokestatic abs : (I)I
    //   5272: invokevirtual charAt : (I)C
    //   5275: invokevirtual append : (C)Ljava/lang/StringBuilder;
    //   5278: pop
    //   5279: iload_2
    //   5280: ifeq -> 6100
    //   5283: goto -> 5290
    //   5286: invokestatic a : (Ljava/lang/Throwable;)Ljava/lang/Throwable;
    //   5289: athrow
    //   5290: aload_3
    //   5291: getstatic burp/Zlwm.Zj : Ljava/lang/String;
    //   5294: getstatic burp/Ztr5.ZZ : Ljava/lang/Object;
    //   5297: checkcast java/math/BigInteger
    //   5300: invokevirtual intValue : ()I
    //   5303: bipush #32
    //   5305: irem
    //   5306: invokestatic abs : (I)I
    //   5309: invokevirtual charAt : (I)C
    //   5312: invokevirtual append : (C)Ljava/lang/StringBuilder;
    //   5315: pop
    //   5316: iload_2
    //   5317: ifeq -> 6100
    //   5320: goto -> 5327
    //   5323: invokestatic a : (Ljava/lang/Throwable;)Ljava/lang/Throwable;
    //   5326: athrow
    //   5327: aload_3
    //   5328: getstatic burp/Zka9.ZM : Ljava/lang/String;
    //   5331: getstatic burp/Ze5h.Zn : Ljava/lang/Object;
    //   5334: checkcast java/math/BigInteger
    //   5337: invokevirtual intValue : ()I
    //   5340: bipush #32
    //   5342: irem
    //   5343: invokestatic abs : (I)I
    //   5346: invokevirtual charAt : (I)C
    //   5349: invokevirtual append : (C)Ljava/lang/StringBuilder;
    //   5352: pop
    //   5353: iload_2
    //   5354: ifeq -> 6100
    //   5357: goto -> 5364
    //   5360: invokestatic a : (Ljava/lang/Throwable;)Ljava/lang/Throwable;
    //   5363: athrow
    //   5364: aload_3
    //   5365: getstatic burp/Zb87.ZK : Ljava/lang/String;
    //   5368: getstatic burp/Zmzj.Zm : Ljava/lang/Object;
    //   5371: checkcast java/math/BigInteger
    //   5374: invokevirtual intValue : ()I
    //   5377: bipush #32
    //   5379: irem
    //   5380: invokestatic abs : (I)I
    //   5383: invokevirtual charAt : (I)C
    //   5386: invokevirtual append : (C)Ljava/lang/StringBuilder;
    //   5389: pop
    //   5390: iload_2
    //   5391: ifeq -> 6100
    //   5394: goto -> 5401
    //   5397: invokestatic a : (Ljava/lang/Throwable;)Ljava/lang/Throwable;
    //   5400: athrow
    //   5401: aload_3
    //   5402: getstatic burp/Ztwp.ZK : Ljava/lang/String;
    //   5405: getstatic burp/Zb3r.ZI : Ljava/lang/Object;
    //   5408: checkcast java/math/BigInteger
    //   5411: invokevirtual intValue : ()I
    //   5414: bipush #32
    //   5416: irem
    //   5417: invokestatic abs : (I)I
    //   5420: invokevirtual charAt : (I)C
    //   5423: invokevirtual append : (C)Ljava/lang/StringBuilder;
    //   5426: pop
    //   5427: iload_2
    //   5428: ifeq -> 6100
    //   5431: goto -> 5438
    //   5434: invokestatic a : (Ljava/lang/Throwable;)Ljava/lang/Throwable;
    //   5437: athrow
    //   5438: aload_3
    //   5439: getstatic burp/Zmf6.Zn : Ljava/lang/String;
    //   5442: getstatic burp/Zlab.ZM : Ljava/lang/Object;
    //   5445: checkcast java/math/BigInteger
    //   5448: invokevirtual intValue : ()I
    //   5451: bipush #32
    //   5453: irem
    //   5454: invokestatic abs : (I)I
    //   5457: invokevirtual charAt : (I)C
    //   5460: invokevirtual append : (C)Ljava/lang/StringBuilder;
    //   5463: pop
    //   5464: iload_2
    //   5465: ifeq -> 6100
    //   5468: goto -> 5475
    //   5471: invokestatic a : (Ljava/lang/Throwable;)Ljava/lang/Throwable;
    //   5474: athrow
    //   5475: aload_3
    //   5476: getstatic burp/Zt0m.ZH : Ljava/lang/String;
    //   5479: getstatic burp/Zk92.Zn : Ljava/lang/Object;
    //   5482: checkcast java/math/BigInteger
    //   5485: invokevirtual intValue : ()I
    //   5488: bipush #32
    //   5490: irem
    //   5491: invokestatic abs : (I)I
    //   5494: invokevirtual charAt : (I)C
    //   5497: invokevirtual append : (C)Ljava/lang/StringBuilder;
    //   5500: pop
    //   5501: iload_2
    //   5502: ifeq -> 6100
    //   5505: goto -> 5512
    //   5508: invokestatic a : (Ljava/lang/Throwable;)Ljava/lang/Throwable;
    //   5511: athrow
    //   5512: aload_3
    //   5513: getstatic burp/Zlo0.ZD : Ljava/lang/String;
    //   5516: getstatic burp/Zb9q.ZI : Ljava/lang/Object;
    //   5519: checkcast java/math/BigInteger
    //   5522: invokevirtual intValue : ()I
    //   5525: bipush #32
    //   5527: irem
    //   5528: invokestatic abs : (I)I
    //   5531: invokevirtual charAt : (I)C
    //   5534: invokevirtual append : (C)Ljava/lang/StringBuilder;
    //   5537: pop
    //   5538: iload_2
    //   5539: ifeq -> 6100
    //   5542: goto -> 5549
    //   5545: invokestatic a : (Ljava/lang/Throwable;)Ljava/lang/Throwable;
    //   5548: athrow
    //   5549: aload_3
    //   5550: getstatic burp/Zs3m.Zl : Ljava/lang/String;
    //   5553: getstatic burp/Zzr8.ZC : Ljava/lang/Object;
    //   5556: checkcast java/math/BigInteger
    //   5559: invokevirtual intValue : ()I
    //   5562: bipush #32
    //   5564: irem
    //   5565: invokestatic abs : (I)I
    //   5568: invokevirtual charAt : (I)C
    //   5571: invokevirtual append : (C)Ljava/lang/StringBuilder;
    //   5574: pop
    //   5575: iload_2
    //   5576: ifeq -> 6100
    //   5579: goto -> 5586
    //   5582: invokestatic a : (Ljava/lang/Throwable;)Ljava/lang/Throwable;
    //   5585: athrow
    //   5586: aload_3
    //   5587: getstatic burp/Zg2u.Zy : Ljava/lang/String;
    //   5590: getstatic burp/Zes.Zx : Ljava/lang/Object;
    //   5593: checkcast java/math/BigInteger
    //   5596: invokevirtual intValue : ()I
    //   5599: bipush #32
    //   5601: irem
    //   5602: invokestatic abs : (I)I
    //   5605: invokevirtual charAt : (I)C
    //   5608: invokevirtual append : (C)Ljava/lang/StringBuilder;
    //   5611: pop
    //   5612: iload_2
    //   5613: ifeq -> 6100
    //   5616: goto -> 5623
    //   5619: invokestatic a : (Ljava/lang/Throwable;)Ljava/lang/Throwable;
    //   5622: athrow
    //   5623: aload_3
    //   5624: getstatic burp/Zlxw.ZC : Ljava/lang/String;
    //   5627: getstatic burp/Zmh3.ZF : Ljava/lang/Object;
    //   5630: checkcast java/math/BigInteger
    //   5633: invokevirtual intValue : ()I
    //   5636: bipush #32
    //   5638: irem
    //   5639: invokestatic abs : (I)I
    //   5642: invokevirtual charAt : (I)C
    //   5645: invokevirtual append : (C)Ljava/lang/StringBuilder;
    //   5648: pop
    //   5649: iload_2
    //   5650: ifeq -> 6100
    //   5653: goto -> 5660
    //   5656: invokestatic a : (Ljava/lang/Throwable;)Ljava/lang/Throwable;
    //   5659: athrow
    //   5660: aload_3
    //   5661: getstatic burp/Zk8f.ZV : Ljava/lang/String;
    //   5664: getstatic burp/Zt81.ZY : Ljava/lang/Object;
    //   5667: checkcast java/math/BigInteger
    //   5670: invokevirtual intValue : ()I
    //   5673: bipush #32
    //   5675: irem
    //   5676: invokestatic abs : (I)I
    //   5679: invokevirtual charAt : (I)C
    //   5682: invokevirtual append : (C)Ljava/lang/StringBuilder;
    //   5685: pop
    //   5686: iload_2
    //   5687: ifeq -> 6100
    //   5690: goto -> 5697
    //   5693: invokestatic a : (Ljava/lang/Throwable;)Ljava/lang/Throwable;
    //   5696: athrow
    //   5697: aload_3
    //   5698: getstatic burp/Zg1l.Zl : Ljava/lang/String;
    //   5701: getstatic burp/Zsn3.Zy : Ljava/lang/Object;
    //   5704: checkcast java/math/BigInteger
    //   5707: invokevirtual intValue : ()I
    //   5710: bipush #32
    //   5712: irem
    //   5713: invokestatic abs : (I)I
    //   5716: invokevirtual charAt : (I)C
    //   5719: invokevirtual append : (C)Ljava/lang/StringBuilder;
    //   5722: pop
    //   5723: iload_2
    //   5724: ifeq -> 6100
    //   5727: goto -> 5734
    //   5730: invokestatic a : (Ljava/lang/Throwable;)Ljava/lang/Throwable;
    //   5733: athrow
    //   5734: aload_3
    //   5735: getstatic burp/Zssc.ZR : Ljava/lang/String;
    //   5738: getstatic burp/Zmt_.Zl : Ljava/lang/Object;
    //   5741: checkcast java/math/BigInteger
    //   5744: invokevirtual intValue : ()I
    //   5747: bipush #32
    //   5749: irem
    //   5750: invokestatic abs : (I)I
    //   5753: invokevirtual charAt : (I)C
    //   5756: invokevirtual append : (C)Ljava/lang/StringBuilder;
    //   5759: pop
    //   5760: iload_2
    //   5761: ifeq -> 6100
    //   5764: goto -> 5771
    //   5767: invokestatic a : (Ljava/lang/Throwable;)Ljava/lang/Throwable;
    //   5770: athrow
    //   5771: aload_3
    //   5772: getstatic burp/Zbwj.ZP : Ljava/lang/String;
    //   5775: getstatic burp/Zrzg.ZA : Ljava/lang/Object;
    //   5778: checkcast java/math/BigInteger
    //   5781: invokevirtual intValue : ()I
    //   5784: bipush #32
    //   5786: irem
    //   5787: invokestatic abs : (I)I
    //   5790: invokevirtual charAt : (I)C
    //   5793: invokevirtual append : (C)Ljava/lang/StringBuilder;
    //   5796: pop
    //   5797: iload_2
    //   5798: ifeq -> 6100
    //   5801: goto -> 5808
    //   5804: invokestatic a : (Ljava/lang/Throwable;)Ljava/lang/Throwable;
    //   5807: athrow
    //   5808: aload_3
    //   5809: getstatic burp/Zepy.Zg : Ljava/lang/String;
    //   5812: getstatic burp/Zzl4.ZX : Ljava/lang/Object;
    //   5815: checkcast java/math/BigInteger
    //   5818: invokevirtual intValue : ()I
    //   5821: bipush #32
    //   5823: irem
    //   5824: invokestatic abs : (I)I
    //   5827: invokevirtual charAt : (I)C
    //   5830: invokevirtual append : (C)Ljava/lang/StringBuilder;
    //   5833: pop
    //   5834: iload_2
    //   5835: ifeq -> 6100
    //   5838: goto -> 5845
    //   5841: invokestatic a : (Ljava/lang/Throwable;)Ljava/lang/Throwable;
    //   5844: athrow
    //   5845: aload_3
    //   5846: getstatic burp/Zr14.ZL : Ljava/lang/String;
    //   5849: getstatic burp/Zbli.Zo : Ljava/lang/Object;
    //   5852: checkcast java/math/BigInteger
    //   5855: invokevirtual intValue : ()I
    //   5858: bipush #32
    //   5860: irem
    //   5861: invokestatic abs : (I)I
    //   5864: invokevirtual charAt : (I)C
    //   5867: invokevirtual append : (C)Ljava/lang/StringBuilder;
    //   5870: pop
    //   5871: iload_2
    //   5872: ifeq -> 6100
    //   5875: goto -> 5882
    //   5878: invokestatic a : (Ljava/lang/Throwable;)Ljava/lang/Throwable;
    //   5881: athrow
    //   5882: aload_3
    //   5883: getstatic burp/Zr36.Ze : Ljava/lang/String;
    //   5886: getstatic burp/Zzr8.ZC : Ljava/lang/Object;
    //   5889: checkcast java/math/BigInteger
    //   5892: invokevirtual intValue : ()I
    //   5895: bipush #32
    //   5897: irem
    //   5898: invokestatic abs : (I)I
    //   5901: invokevirtual charAt : (I)C
    //   5904: invokevirtual append : (C)Ljava/lang/StringBuilder;
    //   5907: pop
    //   5908: iload_2
    //   5909: ifeq -> 6100
    //   5912: goto -> 5919
    //   5915: invokestatic a : (Ljava/lang/Throwable;)Ljava/lang/Throwable;
    //   5918: athrow
    //   5919: aload_3
    //   5920: getstatic burp/Zebe.ZW : Ljava/lang/String;
    //   5923: getstatic burp/Zzr8.ZC : Ljava/lang/Object;
    //   5926: checkcast java/math/BigInteger
    //   5929: invokevirtual intValue : ()I
    //   5932: bipush #32
    //   5934: irem
    //   5935: invokestatic abs : (I)I
    //   5938: invokevirtual charAt : (I)C
    //   5941: invokevirtual append : (C)Ljava/lang/StringBuilder;
    //   5944: pop
    //   5945: iload_2
    //   5946: ifeq -> 6100
    //   5949: goto -> 5956
    //   5952: invokestatic a : (Ljava/lang/Throwable;)Ljava/lang/Throwable;
    //   5955: athrow
    //   5956: aload_3
    //   5957: getstatic burp/Zmyk.Zx : Ljava/lang/String;
    //   5960: getstatic burp/Zlg2.ZO : Ljava/lang/Object;
    //   5963: checkcast java/math/BigInteger
    //   5966: invokevirtual intValue : ()I
    //   5969: bipush #32
    //   5971: irem
    //   5972: invokestatic abs : (I)I
    //   5975: invokevirtual charAt : (I)C
    //   5978: invokevirtual append : (C)Ljava/lang/StringBuilder;
    //   5981: pop
    //   5982: iload_2
    //   5983: ifeq -> 6100
    //   5986: goto -> 5993
    //   5989: invokestatic a : (Ljava/lang/Throwable;)Ljava/lang/Throwable;
    //   5992: athrow
    //   5993: aload_3
    //   5994: getstatic burp/Zst7.Zi : Ljava/lang/String;
    //   5997: getstatic burp/Zea9.Zt : Ljava/lang/Object;
    //   6000: checkcast java/math/BigInteger
    //   6003: invokevirtual intValue : ()I
    //   6006: bipush #32
    //   6008: irem
    //   6009: invokestatic abs : (I)I
    //   6012: invokevirtual charAt : (I)C
    //   6015: invokevirtual append : (C)Ljava/lang/StringBuilder;
    //   6018: pop
    //   6019: iload_2
    //   6020: ifeq -> 6100
    //   6023: goto -> 6030
    //   6026: invokestatic a : (Ljava/lang/Throwable;)Ljava/lang/Throwable;
    //   6029: athrow
    //   6030: aload_3
    //   6031: getstatic burp/Zzht.Zv : Ljava/lang/String;
    //   6034: getstatic burp/Zscz.ZN : Ljava/lang/Object;
    //   6037: checkcast java/math/BigInteger
    //   6040: invokevirtual intValue : ()I
    //   6043: bipush #32
    //   6045: irem
    //   6046: invokestatic abs : (I)I
    //   6049: invokevirtual charAt : (I)C
    //   6052: invokevirtual append : (C)Ljava/lang/StringBuilder;
    //   6055: pop
    //   6056: iload_2
    //   6057: ifeq -> 6100
    //   6060: goto -> 6067
    //   6063: invokestatic a : (Ljava/lang/Throwable;)Ljava/lang/Throwable;
    //   6066: athrow
    //   6067: aload_3
    //   6068: getstatic burp/Zz4j.ZS : Ljava/lang/String;
    //   6071: getstatic burp/Zb0q.ZK : Ljava/lang/Object;
    //   6074: checkcast java/math/BigInteger
    //   6077: invokevirtual intValue : ()I
    //   6080: bipush #32
    //   6082: irem
    //   6083: invokestatic abs : (I)I
    //   6086: invokevirtual charAt : (I)C
    //   6089: invokevirtual append : (C)Ljava/lang/StringBuilder;
    //   6092: pop
    //   6093: goto -> 6100
    //   6096: invokestatic a : (Ljava/lang/Throwable;)Ljava/lang/Throwable;
    //   6099: athrow
    //   6100: iinc #4, 1
    //   6103: iload_2
    //   6104: ifeq -> 4770
    //   6107: aload_3
    //   6108: invokevirtual toString : ()Ljava/lang/String;
    //   6111: putstatic burp/Ze4g.Zk : Ljava/lang/String;
    //   6114: sipush #30216
    //   6117: sipush #-1962
    //   6120: invokestatic a : (II)Ljava/lang/String;
    //   6123: iconst_1
    //   6124: ldc burp/Zgs6
    //   6126: invokevirtual getClassLoader : ()Ljava/lang/ClassLoader;
    //   6129: invokestatic forName : (Ljava/lang/String;ZLjava/lang/ClassLoader;)Ljava/lang/Class;
    //   6132: invokevirtual getDeclaredFields : ()[Ljava/lang/reflect/Field;
    //   6135: astore #4
    //   6137: aload #4
    //   6139: arraylength
    //   6140: istore #5
    //   6142: iconst_0
    //   6143: istore #6
    //   6145: iload #6
    //   6147: iload #5
    //   6149: if_icmpge -> 6287
    //   6152: aload #4
    //   6154: iload #6
    //   6156: aaload
    //   6157: astore #7
    //   6159: aload #7
    //   6161: invokevirtual getModifiers : ()I
    //   6164: invokestatic isStatic : (I)Z
    //   6167: ifne -> 6177
    //   6170: goto -> 6280
    //   6173: invokestatic a : (Ljava/lang/Throwable;)Ljava/lang/Throwable;
    //   6176: athrow
    //   6177: aload #7
    //   6179: invokevirtual getType : ()Ljava/lang/Class;
    //   6182: astore #8
    //   6184: aload #8
    //   6186: ifnull -> 6267
    //   6189: aload #8
    //   6191: invokevirtual isPrimitive : ()Z
    //   6194: ifne -> 6267
    //   6197: goto -> 6204
    //   6200: invokestatic a : (Ljava/lang/Throwable;)Ljava/lang/Throwable;
    //   6203: athrow
    //   6204: aload #8
    //   6206: invokevirtual getPackage : ()Ljava/lang/Package;
    //   6209: ifnull -> 6267
    //   6212: goto -> 6219
    //   6215: invokestatic a : (Ljava/lang/Throwable;)Ljava/lang/Throwable;
    //   6218: athrow
    //   6219: aload #8
    //   6221: invokevirtual getPackage : ()Ljava/lang/Package;
    //   6224: invokevirtual getName : ()Ljava/lang/String;
    //   6227: ifnull -> 6267
    //   6230: goto -> 6237
    //   6233: invokestatic a : (Ljava/lang/Throwable;)Ljava/lang/Throwable;
    //   6236: athrow
    //   6237: aload #8
    //   6239: invokevirtual getPackage : ()Ljava/lang/Package;
    //   6242: invokevirtual getName : ()Ljava/lang/String;
    //   6245: sipush #30210
    //   6248: sipush #-19668
    //   6251: invokestatic a : (II)Ljava/lang/String;
    //   6254: invokevirtual startsWith : (Ljava/lang/String;)Z
    //   6257: ifne -> 6267
    //   6260: goto -> 6267
    //   6263: invokestatic a : (Ljava/lang/Throwable;)Ljava/lang/Throwable;
    //   6266: athrow
    //   6267: aload #7
    //   6269: iconst_1
    //   6270: invokevirtual setAccessible : (Z)V
    //   6273: aload #7
    //   6275: aconst_null
    //   6276: invokevirtual get : (Ljava/lang/Object;)Ljava/lang/Object;
    //   6279: pop
    //   6280: iinc #6, 1
    //   6283: iload_2
    //   6284: ifeq -> 6145
    //   6287: sipush #30239
    //   6290: sipush #16411
    //   6293: invokestatic a : (II)Ljava/lang/String;
    //   6296: invokestatic forName : (Ljava/lang/String;)Ljava/lang/Class;
    //   6299: invokevirtual getDeclaredMethods : ()[Ljava/lang/reflect/Method;
    //   6302: astore #4
    //   6304: aload #4
    //   6306: arraylength
    //   6307: istore #5
    //   6309: iconst_0
    //   6310: istore #6
    //   6312: iload #6
    //   6314: iload #5
    //   6316: if_icmpge -> 6449
    //   6319: aload #4
    //   6321: iload #6
    //   6323: aaload
    //   6324: astore #7
    //   6326: aload #7
    //   6328: invokevirtual getParameterTypes : ()[Ljava/lang/Class;
    //   6331: pop
    //   6332: aload #7
    //   6334: invokevirtual getModifiers : ()I
    //   6337: invokestatic isStatic : (I)Z
    //   6340: ifeq -> 6435
    //   6343: aload #7
    //   6345: invokevirtual getParameterTypes : ()[Ljava/lang/Class;
    //   6348: arraylength
    //   6349: iconst_2
    //   6350: if_icmpne -> 6435
    //   6353: goto -> 6360
    //   6356: invokestatic a : (Ljava/lang/Throwable;)Ljava/lang/Throwable;
    //   6359: athrow
    //   6360: aload #7
    //   6362: invokevirtual getReturnType : ()Ljava/lang/Class;
    //   6365: getstatic java/lang/Void.TYPE : Ljava/lang/Class;
    //   6368: invokevirtual equals : (Ljava/lang/Object;)Z
    //   6371: ifeq -> 6435
    //   6374: goto -> 6381
    //   6377: invokestatic a : (Ljava/lang/Throwable;)Ljava/lang/Throwable;
    //   6380: athrow
    //   6381: aload #7
    //   6383: iconst_1
    //   6384: invokevirtual setAccessible : (Z)V
    //   6387: aload #7
    //   6389: aconst_null
    //   6390: iconst_2
    //   6391: anewarray java/lang/Object
    //   6394: dup
    //   6395: iconst_0
    //   6396: aload_0
    //   6397: aastore
    //   6398: dup
    //   6399: iconst_1
    //   6400: aload_1
    //   6401: ifnonnull -> 6419
    //   6404: goto -> 6411
    //   6407: invokestatic a : (Ljava/lang/Throwable;)Ljava/lang/Throwable;
    //   6410: athrow
    //   6411: aload_1
    //   6412: goto -> 6426
    //   6415: invokestatic a : (Ljava/lang/Throwable;)Ljava/lang/Throwable;
    //   6418: athrow
    //   6419: aload_1
    //   6420: checkcast [B
    //   6423: invokevirtual clone : ()Ljava/lang/Object;
    //   6426: aastore
    //   6427: invokevirtual invoke : (Ljava/lang/Object;[Ljava/lang/Object;)Ljava/lang/Object;
    //   6430: pop
    //   6431: iload_2
    //   6432: ifeq -> 6449
    //   6435: iinc #6, 1
    //   6438: iload_2
    //   6439: ifeq -> 6312
    //   6442: goto -> 6449
    //   6445: invokestatic a : (Ljava/lang/Throwable;)Ljava/lang/Throwable;
    //   6448: athrow
    //   6449: getstatic burp/Ztq4.ZA : Ljava/lang/Object;
    //   6452: checkcast java/math/BigInteger
    //   6455: invokevirtual toByteArray : ()[B
    //   6458: astore #4
    //   6460: new java/lang/StringBuilder
    //   6463: dup
    //   6464: invokespecial <init> : ()V
    //   6467: astore #6
    //   6469: aload #6
    //   6471: sipush #30233
    //   6474: sipush #-1230
    //   6477: invokestatic a : (II)Ljava/lang/String;
    //   6480: invokevirtual append : (Ljava/lang/String;)Ljava/lang/StringBuilder;
    //   6483: pop
    //   6484: aload #4
    //   6486: astore #7
    //   6488: aload #7
    //   6490: arraylength
    //   6491: istore #8
    //   6493: iconst_0
    //   6494: istore #9
    //   6496: iload #9
    //   6498: iload #8
    //   6500: if_icmpge -> 6526
    //   6503: aload #7
    //   6505: iload #9
    //   6507: baload
    //   6508: istore #10
    //   6510: aload #6
    //   6512: iload #10
    //   6514: i2c
    //   6515: invokevirtual append : (C)Ljava/lang/StringBuilder;
    //   6518: pop
    //   6519: iinc #9, 1
    //   6522: iload_2
    //   6523: ifeq -> 6496
    //   6526: aload #6
    //   6528: sipush #30227
    //   6531: sipush #23668
    //   6534: invokestatic a : (II)Ljava/lang/String;
    //   6537: ldc ''
    //   6539: invokestatic getProperty : (Ljava/lang/String;Ljava/lang/String;)Ljava/lang/String;
    //   6542: invokevirtual toLowerCase : ()Ljava/lang/String;
    //   6545: invokevirtual append : (Ljava/lang/String;)Ljava/lang/StringBuilder;
    //   6548: pop
    //   6549: aload #6
    //   6551: sipush #30212
    //   6554: sipush #-1220
    //   6557: invokestatic a : (II)Ljava/lang/String;
    //   6560: ldc ''
    //   6562: invokestatic getProperty : (Ljava/lang/String;Ljava/lang/String;)Ljava/lang/String;
    //   6565: invokevirtual toLowerCase : ()Ljava/lang/String;
    //   6568: invokevirtual append : (Ljava/lang/String;)Ljava/lang/StringBuilder;
    //   6571: pop
    //   6572: aload #6
    //   6574: invokevirtual toString : ()Ljava/lang/String;
    //   6577: invokevirtual getBytes : ()[B
    //   6580: astore #5
    //   6582: aload #5
    //   6584: astore #4
    //   6586: aload #4
    //   6588: arraylength
    //   6589: bipush #8
    //   6591: iadd
    //   6592: bipush #6
    //   6594: ishr
    //   6595: iconst_1
    //   6596: iadd
    //   6597: bipush #16
    //   6599: imul
    //   6600: newarray int
    //   6602: astore #6
    //   6604: iconst_0
    //   6605: istore #7
    //   6607: iload #7
    //   6609: aload #4
    //   6611: arraylength
    //   6612: if_icmpge -> 6656
    //   6615: aload #4
    //   6617: iload #7
    //   6619: baload
    //   6620: sipush #255
    //   6623: iand
    //   6624: istore #8
    //   6626: aload #6
    //   6628: iload #7
    //   6630: iconst_2
    //   6631: ishr
    //   6632: dup2
    //   6633: iaload
    //   6634: iload #8
    //   6636: bipush #24
    //   6638: iload #7
    //   6640: iconst_4
    //   6641: irem
    //   6642: bipush #8
    //   6644: imul
    //   6645: isub
    //   6646: ishl
    //   6647: ior
    //   6648: iastore
    //   6649: iinc #7, 1
    //   6652: iload_2
    //   6653: ifeq -> 6607
    //   6656: aload #6
    //   6658: iload #7
    //   6660: iconst_2
    //   6661: ishr
    //   6662: dup2
    //   6663: iaload
    //   6664: sipush #128
    //   6667: bipush #24
    //   6669: iload #7
    //   6671: iconst_4
    //   6672: irem
    //   6673: bipush #8
    //   6675: imul
    //   6676: isub
    //   6677: ishl
    //   6678: ior
    //   6679: iastore
    //   6680: aload #6
    //   6682: aload #6
    //   6684: arraylength
    //   6685: iconst_1
    //   6686: isub
    //   6687: aload #4
    //   6689: arraylength
    //   6690: bipush #8
    //   6692: imul
    //   6693: iastore
    //   6694: bipush #80
    //   6696: newarray int
    //   6698: astore #8
    //   6700: ldc 1732584193
    //   6702: istore #9
    //   6704: ldc -271733879
    //   6706: istore #10
    //   6708: ldc -1732584194
    //   6710: istore #11
    //   6712: ldc 271733878
    //   6714: istore #12
    //   6716: ldc -1009589776
    //   6718: istore #13
    //   6720: iconst_0
    //   6721: istore #7
    //   6723: iload #7
    //   6725: aload #6
    //   6727: arraylength
    //   6728: if_icmpge -> 7050
    //   6731: iload #9
    //   6733: istore #14
    //   6735: iload #10
    //   6737: istore #15
    //   6739: iload #11
    //   6741: istore #16
    //   6743: iload #12
    //   6745: istore #17
    //   6747: iload #13
    //   6749: istore #18
    //   6751: iconst_0
    //   6752: istore #19
    //   6754: iload #19
    //   6756: bipush #80
    //   6758: if_icmpge -> 7008
    //   6761: iload #19
    //   6763: bipush #16
    //   6765: if_icmpge -> 6792
    //   6768: aload #8
    //   6770: iload #19
    //   6772: aload #6
    //   6774: iload #7
    //   6776: iload #19
    //   6778: iadd
    //   6779: iaload
    //   6780: iastore
    //   6781: iload_2
    //   6782: ifeq -> 6847
    //   6785: goto -> 6792
    //   6788: invokestatic a : (Ljava/lang/Throwable;)Ljava/lang/Throwable;
    //   6791: athrow
    //   6792: aload #8
    //   6794: iload #19
    //   6796: iconst_3
    //   6797: isub
    //   6798: iaload
    //   6799: aload #8
    //   6801: iload #19
    //   6803: bipush #8
    //   6805: isub
    //   6806: iaload
    //   6807: ixor
    //   6808: aload #8
    //   6810: iload #19
    //   6812: bipush #14
    //   6814: isub
    //   6815: iaload
    //   6816: ixor
    //   6817: aload #8
    //   6819: iload #19
    //   6821: bipush #16
    //   6823: isub
    //   6824: iaload
    //   6825: ixor
    //   6826: istore #20
    //   6828: iload #20
    //   6830: iconst_1
    //   6831: ishl
    //   6832: iload #20
    //   6834: bipush #31
    //   6836: iushr
    //   6837: ior
    //   6838: istore #21
    //   6840: aload #8
    //   6842: iload #19
    //   6844: iload #21
    //   6846: iastore
    //   6847: iload #9
    //   6849: iconst_5
    //   6850: ishl
    //   6851: iload #9
    //   6853: bipush #27
    //   6855: iushr
    //   6856: ior
    //   6857: istore #20
    //   6859: iload #20
    //   6861: iload #13
    //   6863: iadd
    //   6864: aload #8
    //   6866: iload #19
    //   6868: iaload
    //   6869: iadd
    //   6870: iload #19
    //   6872: bipush #20
    //   6874: if_icmpge -> 6900
    //   6877: ldc 1518500249
    //   6879: iload #10
    //   6881: iload #11
    //   6883: iand
    //   6884: iload #10
    //   6886: iconst_m1
    //   6887: ixor
    //   6888: iload #12
    //   6890: iand
    //   6891: ior
    //   6892: iadd
    //   6893: goto -> 6970
    //   6896: invokestatic a : (Ljava/lang/Throwable;)Ljava/lang/Throwable;
    //   6899: athrow
    //   6900: iload #19
    //   6902: bipush #40
    //   6904: if_icmpge -> 6925
    //   6907: ldc 1859775393
    //   6909: iload #10
    //   6911: iload #11
    //   6913: ixor
    //   6914: iload #12
    //   6916: ixor
    //   6917: iadd
    //   6918: goto -> 6970
    //   6921: invokestatic a : (Ljava/lang/Throwable;)Ljava/lang/Throwable;
    //   6924: athrow
    //   6925: iload #19
    //   6927: bipush #60
    //   6929: if_icmpge -> 6959
    //   6932: ldc -1894007588
    //   6934: iload #10
    //   6936: iload #11
    //   6938: iand
    //   6939: iload #10
    //   6941: iload #12
    //   6943: iand
    //   6944: ior
    //   6945: iload #11
    //   6947: iload #12
    //   6949: iand
    //   6950: ior
    //   6951: iadd
    //   6952: goto -> 6970
    //   6955: invokestatic a : (Ljava/lang/Throwable;)Ljava/lang/Throwable;
    //   6958: athrow
    //   6959: ldc -899497514
    //   6961: iload #10
    //   6963: iload #11
    //   6965: ixor
    //   6966: iload #12
    //   6968: ixor
    //   6969: iadd
    //   6970: iadd
    //   6971: istore #21
    //   6973: iload #12
    //   6975: istore #13
    //   6977: iload #11
    //   6979: istore #12
    //   6981: iload #10
    //   6983: bipush #30
    //   6985: ishl
    //   6986: iload #10
    //   6988: iconst_2
    //   6989: iushr
    //   6990: ior
    //   6991: istore #11
    //   6993: iload #9
    //   6995: istore #10
    //   6997: iload #21
    //   6999: istore #9
    //   7001: iinc #19, 1
    //   7004: iload_2
    //   7005: ifeq -> 6754
    //   7008: iload #9
    //   7010: iload #14
    //   7012: iadd
    //   7013: istore #9
    //   7015: iload #10
    //   7017: iload #15
    //   7019: iadd
    //   7020: istore #10
    //   7022: iload #11
    //   7024: iload #16
    //   7026: iadd
    //   7027: istore #11
    //   7029: iload #12
    //   7031: iload #17
    //   7033: iadd
    //   7034: istore #12
    //   7036: iload #13
    //   7038: iload #18
    //   7040: iadd
    //   7041: istore #13
    //   7043: iinc #7, 16
    //   7046: iload_2
    //   7047: ifeq -> 6723
    //   7050: iconst_5
    //   7051: newarray int
    //   7053: dup
    //   7054: iconst_0
    //   7055: iload #9
    //   7057: iastore
    //   7058: dup
    //   7059: iconst_1
    //   7060: iload #10
    //   7062: iastore
    //   7063: dup
    //   7064: iconst_2
    //   7065: iload #11
    //   7067: iastore
    //   7068: dup
    //   7069: iconst_3
    //   7070: iload #12
    //   7072: iastore
    //   7073: dup
    //   7074: iconst_4
    //   7075: iload #13
    //   7077: iastore
    //   7078: astore #14
    //   7080: bipush #20
    //   7082: newarray byte
    //   7084: astore #15
    //   7086: iconst_0
    //   7087: istore #16
    //   7089: iload #16
    //   7091: bipush #20
    //   7093: if_icmpge -> 7134
    //   7096: aload #14
    //   7098: iload #16
    //   7100: iconst_4
    //   7101: idiv
    //   7102: iaload
    //   7103: istore #17
    //   7105: iconst_3
    //   7106: iload #16
    //   7108: iconst_4
    //   7109: irem
    //   7110: isub
    //   7111: bipush #8
    //   7113: imul
    //   7114: istore #18
    //   7116: aload #15
    //   7118: iload #16
    //   7120: iload #17
    //   7122: iload #18
    //   7124: iushr
    //   7125: i2b
    //   7126: bastore
    //   7127: iinc #16, 1
    //   7130: iload_2
    //   7131: ifeq -> 7089
    //   7134: aload #15
    //   7136: astore #5
    //   7138: iconst_0
    //   7139: istore #4
    //   7141: getstatic burp/Zreu.ZI : Ljava/lang/String;
    //   7144: getstatic burp/Zbwj.ZW : Ljava/lang/Object;
    //   7147: checkcast java/math/BigInteger
    //   7150: invokevirtual intValue : ()I
    //   7153: bipush #32
    //   7155: irem
    //   7156: invokestatic abs : (I)I
    //   7159: invokevirtual charAt : (I)C
    //   7162: getstatic burp/Zlo0.ZD : Ljava/lang/String;
    //   7165: getstatic burp/Zepy.Ze : Ljava/lang/Object;
    //   7168: checkcast java/math/BigInteger
    //   7171: invokevirtual intValue : ()I
    //   7174: bipush #32
    //   7176: irem
    //   7177: invokestatic abs : (I)I
    //   7180: invokevirtual charAt : (I)C
    //   7183: if_icmpgt -> 7528
    //   7186: sipush #30225
    //   7189: sipush #-31701
    //   7192: invokestatic a : (II)Ljava/lang/String;
    //   7195: iconst_1
    //   7196: ldc burp/Zl22
    //   7198: invokevirtual getClassLoader : ()Ljava/lang/ClassLoader;
    //   7201: invokestatic forName : (Ljava/lang/String;ZLjava/lang/ClassLoader;)Ljava/lang/Class;
    //   7204: invokevirtual getDeclaredFields : ()[Ljava/lang/reflect/Field;
    //   7207: astore #5
    //   7209: aload #5
    //   7211: arraylength
    //   7212: istore #6
    //   7214: iconst_0
    //   7215: istore #7
    //   7217: iload #7
    //   7219: iload #6
    //   7221: if_icmpge -> 7359
    //   7224: aload #5
    //   7226: iload #7
    //   7228: aaload
    //   7229: astore #8
    //   7231: aload #8
    //   7233: invokevirtual getModifiers : ()I
    //   7236: invokestatic isStatic : (I)Z
    //   7239: ifne -> 7249
    //   7242: goto -> 7352
    //   7245: invokestatic a : (Ljava/lang/Throwable;)Ljava/lang/Throwable;
    //   7248: athrow
    //   7249: aload #8
    //   7251: invokevirtual getType : ()Ljava/lang/Class;
    //   7254: astore #9
    //   7256: aload #9
    //   7258: ifnull -> 7339
    //   7261: aload #9
    //   7263: invokevirtual isPrimitive : ()Z
    //   7266: ifne -> 7339
    //   7269: goto -> 7276
    //   7272: invokestatic a : (Ljava/lang/Throwable;)Ljava/lang/Throwable;
    //   7275: athrow
    //   7276: aload #9
    //   7278: invokevirtual getPackage : ()Ljava/lang/Package;
    //   7281: ifnull -> 7339
    //   7284: goto -> 7291
    //   7287: invokestatic a : (Ljava/lang/Throwable;)Ljava/lang/Throwable;
    //   7290: athrow
    //   7291: aload #9
    //   7293: invokevirtual getPackage : ()Ljava/lang/Package;
    //   7296: invokevirtual getName : ()Ljava/lang/String;
    //   7299: ifnull -> 7339
    //   7302: goto -> 7309
    //   7305: invokestatic a : (Ljava/lang/Throwable;)Ljava/lang/Throwable;
    //   7308: athrow
    //   7309: aload #9
    //   7311: invokevirtual getPackage : ()Ljava/lang/Package;
    //   7314: invokevirtual getName : ()Ljava/lang/String;
    //   7317: sipush #30219
    //   7320: sipush #24900
    //   7323: invokestatic a : (II)Ljava/lang/String;
    //   7326: invokevirtual startsWith : (Ljava/lang/String;)Z
    //   7329: ifne -> 7339
    //   7332: goto -> 7339
    //   7335: invokestatic a : (Ljava/lang/Throwable;)Ljava/lang/Throwable;
    //   7338: athrow
    //   7339: aload #8
    //   7341: iconst_1
    //   7342: invokevirtual setAccessible : (Z)V
    //   7345: aload #8
    //   7347: aconst_null
    //   7348: invokevirtual get : (Ljava/lang/Object;)Ljava/lang/Object;
    //   7351: pop
    //   7352: iinc #7, 1
    //   7355: iload_2
    //   7356: ifeq -> 7217
    //   7359: sipush #30223
    //   7362: sipush #-21196
    //   7365: invokestatic a : (II)Ljava/lang/String;
    //   7368: invokestatic forName : (Ljava/lang/String;)Ljava/lang/Class;
    //   7371: invokevirtual getDeclaredMethods : ()[Ljava/lang/reflect/Method;
    //   7374: astore #5
    //   7376: aload #5
    //   7378: arraylength
    //   7379: istore #6
    //   7381: iconst_0
    //   7382: istore #7
    //   7384: iload #7
    //   7386: iload #6
    //   7388: if_icmpge -> 7525
    //   7391: aload #5
    //   7393: iload #7
    //   7395: aaload
    //   7396: astore #8
    //   7398: aload #8
    //   7400: invokevirtual getParameterTypes : ()[Ljava/lang/Class;
    //   7403: pop
    //   7404: aload #8
    //   7406: invokevirtual getModifiers : ()I
    //   7409: invokestatic isStatic : (I)Z
    //   7412: ifeq -> 7511
    //   7415: aload #8
    //   7417: invokevirtual getParameterTypes : ()[Ljava/lang/Class;
    //   7420: arraylength
    //   7421: iconst_2
    //   7422: if_icmpne -> 7511
    //   7425: goto -> 7432
    //   7428: invokestatic a : (Ljava/lang/Throwable;)Ljava/lang/Throwable;
    //   7431: athrow
    //   7432: aload #8
    //   7434: invokevirtual getReturnType : ()Ljava/lang/Class;
    //   7437: getstatic java/lang/Boolean.TYPE : Ljava/lang/Class;
    //   7440: if_acmpne -> 7511
    //   7443: goto -> 7450
    //   7446: invokestatic a : (Ljava/lang/Throwable;)Ljava/lang/Throwable;
    //   7449: athrow
    //   7450: aload #8
    //   7452: iconst_1
    //   7453: invokevirtual setAccessible : (Z)V
    //   7456: aload #8
    //   7458: aconst_null
    //   7459: iconst_2
    //   7460: anewarray java/lang/Object
    //   7463: dup
    //   7464: iconst_0
    //   7465: aload_0
    //   7466: aastore
    //   7467: dup
    //   7468: iconst_1
    //   7469: aload_1
    //   7470: ifnonnull -> 7488
    //   7473: goto -> 7480
    //   7476: invokestatic a : (Ljava/lang/Throwable;)Ljava/lang/Throwable;
    //   7479: athrow
    //   7480: aload_1
    //   7481: goto -> 7495
    //   7484: invokestatic a : (Ljava/lang/Throwable;)Ljava/lang/Throwable;
    //   7487: athrow
    //   7488: aload_1
    //   7489: checkcast [B
    //   7492: invokevirtual clone : ()Ljava/lang/Object;
    //   7495: aastore
    //   7496: invokevirtual invoke : (Ljava/lang/Object;[Ljava/lang/Object;)Ljava/lang/Object;
    //   7499: checkcast java/lang/Boolean
    //   7502: invokevirtual booleanValue : ()Z
    //   7505: istore #4
    //   7507: iload_2
    //   7508: ifeq -> 7525
    //   7511: iinc #7, 1
    //   7514: iload_2
    //   7515: ifeq -> 7384
    //   7518: goto -> 7525
    //   7521: invokestatic a : (Ljava/lang/Throwable;)Ljava/lang/Throwable;
    //   7524: athrow
    //   7525: goto -> 7867
    //   7528: sipush #30229
    //   7531: sipush #26977
    //   7534: invokestatic a : (II)Ljava/lang/String;
    //   7537: iconst_1
    //   7538: ldc burp/Zkc8
    //   7540: invokevirtual getClassLoader : ()Ljava/lang/ClassLoader;
    //   7543: invokestatic forName : (Ljava/lang/String;ZLjava/lang/ClassLoader;)Ljava/lang/Class;
    //   7546: invokevirtual getDeclaredFields : ()[Ljava/lang/reflect/Field;
    //   7549: astore #5
    //   7551: aload #5
    //   7553: arraylength
    //   7554: istore #6
    //   7556: iconst_0
    //   7557: istore #7
    //   7559: iload #7
    //   7561: iload #6
    //   7563: if_icmpge -> 7701
    //   7566: aload #5
    //   7568: iload #7
    //   7570: aaload
    //   7571: astore #8
    //   7573: aload #8
    //   7575: invokevirtual getModifiers : ()I
    //   7578: invokestatic isStatic : (I)Z
    //   7581: ifne -> 7591
    //   7584: goto -> 7694
    //   7587: invokestatic a : (Ljava/lang/Throwable;)Ljava/lang/Throwable;
    //   7590: athrow
    //   7591: aload #8
    //   7593: invokevirtual getType : ()Ljava/lang/Class;
    //   7596: astore #9
    //   7598: aload #9
    //   7600: ifnull -> 7681
    //   7603: aload #9
    //   7605: invokevirtual isPrimitive : ()Z
    //   7608: ifne -> 7681
    //   7611: goto -> 7618
    //   7614: invokestatic a : (Ljava/lang/Throwable;)Ljava/lang/Throwable;
    //   7617: athrow
    //   7618: aload #9
    //   7620: invokevirtual getPackage : ()Ljava/lang/Package;
    //   7623: ifnull -> 7681
    //   7626: goto -> 7633
    //   7629: invokestatic a : (Ljava/lang/Throwable;)Ljava/lang/Throwable;
    //   7632: athrow
    //   7633: aload #9
    //   7635: invokevirtual getPackage : ()Ljava/lang/Package;
    //   7638: invokevirtual getName : ()Ljava/lang/String;
    //   7641: ifnull -> 7681
    //   7644: goto -> 7651
    //   7647: invokestatic a : (Ljava/lang/Throwable;)Ljava/lang/Throwable;
    //   7650: athrow
    //   7651: aload #9
    //   7653: invokevirtual getPackage : ()Ljava/lang/Package;
    //   7656: invokevirtual getName : ()Ljava/lang/String;
    //   7659: sipush #30219
    //   7662: sipush #24900
    //   7665: invokestatic a : (II)Ljava/lang/String;
    //   7668: invokevirtual startsWith : (Ljava/lang/String;)Z
    //   7671: ifne -> 7681
    //   7674: goto -> 7681
    //   7677: invokestatic a : (Ljava/lang/Throwable;)Ljava/lang/Throwable;
    //   7680: athrow
    //   7681: aload #8
    //   7683: iconst_1
    //   7684: invokevirtual setAccessible : (Z)V
    //   7687: aload #8
    //   7689: aconst_null
    //   7690: invokevirtual get : (Ljava/lang/Object;)Ljava/lang/Object;
    //   7693: pop
    //   7694: iinc #7, 1
    //   7697: iload_2
    //   7698: ifeq -> 7559
    //   7701: sipush #30218
    //   7704: sipush #21691
    //   7707: invokestatic a : (II)Ljava/lang/String;
    //   7710: invokestatic forName : (Ljava/lang/String;)Ljava/lang/Class;
    //   7713: invokevirtual getDeclaredMethods : ()[Ljava/lang/reflect/Method;
    //   7716: astore #5
    //   7718: aload #5
    //   7720: arraylength
    //   7721: istore #6
    //   7723: iconst_0
    //   7724: istore #7
    //   7726: iload #7
    //   7728: iload #6
    //   7730: if_icmpge -> 7867
    //   7733: aload #5
    //   7735: iload #7
    //   7737: aaload
    //   7738: astore #8
    //   7740: aload #8
    //   7742: invokevirtual getParameterTypes : ()[Ljava/lang/Class;
    //   7745: pop
    //   7746: aload #8
    //   7748: invokevirtual getModifiers : ()I
    //   7751: invokestatic isStatic : (I)Z
    //   7754: ifeq -> 7853
    //   7757: aload #8
    //   7759: invokevirtual getParameterTypes : ()[Ljava/lang/Class;
    //   7762: arraylength
    //   7763: iconst_2
    //   7764: if_icmpne -> 7853
    //   7767: goto -> 7774
    //   7770: invokestatic a : (Ljava/lang/Throwable;)Ljava/lang/Throwable;
    //   7773: athrow
    //   7774: aload #8
    //   7776: invokevirtual getReturnType : ()Ljava/lang/Class;
    //   7779: getstatic java/lang/Boolean.TYPE : Ljava/lang/Class;
    //   7782: if_acmpne -> 7853
    //   7785: goto -> 7792
    //   7788: invokestatic a : (Ljava/lang/Throwable;)Ljava/lang/Throwable;
    //   7791: athrow
    //   7792: aload #8
    //   7794: iconst_1
    //   7795: invokevirtual setAccessible : (Z)V
    //   7798: aload #8
    //   7800: aconst_null
    //   7801: iconst_2
    //   7802: anewarray java/lang/Object
    //   7805: dup
    //   7806: iconst_0
    //   7807: aload_0
    //   7808: aastore
    //   7809: dup
    //   7810: iconst_1
    //   7811: aload_1
    //   7812: ifnonnull -> 7830
    //   7815: goto -> 7822
    //   7818: invokestatic a : (Ljava/lang/Throwable;)Ljava/lang/Throwable;
    //   7821: athrow
    //   7822: aload_1
    //   7823: goto -> 7837
    //   7826: invokestatic a : (Ljava/lang/Throwable;)Ljava/lang/Throwable;
    //   7829: athrow
    //   7830: aload_1
    //   7831: checkcast [B
    //   7834: invokevirtual clone : ()Ljava/lang/Object;
    //   7837: aastore
    //   7838: invokevirtual invoke : (Ljava/lang/Object;[Ljava/lang/Object;)Ljava/lang/Object;
    //   7841: checkcast java/lang/Boolean
    //   7844: invokevirtual booleanValue : ()Z
    //   7847: istore #4
    //   7849: iload_2
    //   7850: ifeq -> 7867
    //   7853: iinc #7, 1
    //   7856: iload_2
    //   7857: ifeq -> 7726
    //   7860: goto -> 7867
    //   7863: invokestatic a : (Ljava/lang/Throwable;)Ljava/lang/Throwable;
    //   7866: athrow
    //   7867: iload #4
    //   7869: ifeq -> 7875
    //   7872: iload #4
    //   7874: ireturn
    //   7875: getstatic burp/Zsfg.Zh : Ljava/lang/String;
    //   7878: getstatic burp/Zxdy.ZZ : Ljava/lang/Object;
    //   7881: checkcast java/math/BigInteger
    //   7884: invokevirtual intValue : ()I
    //   7887: bipush #32
    //   7889: irem
    //   7890: invokestatic abs : (I)I
    //   7893: invokevirtual charAt : (I)C
    //   7896: getstatic burp/Zbnk.Zg : Ljava/lang/String;
    //   7899: getstatic burp/Zxju.ZN : Ljava/lang/Object;
    //   7902: checkcast java/math/BigInteger
    //   7905: invokevirtual intValue : ()I
    //   7908: bipush #32
    //   7910: irem
    //   7911: invokestatic abs : (I)I
    //   7914: invokevirtual charAt : (I)C
    //   7917: if_icmpgt -> 8263
    //   7920: sipush #30231
    //   7923: sipush #9485
    //   7926: invokestatic a : (II)Ljava/lang/String;
    //   7929: iconst_1
    //   7930: ldc burp/Zzym
    //   7932: invokevirtual getClassLoader : ()Ljava/lang/ClassLoader;
    //   7935: invokestatic forName : (Ljava/lang/String;ZLjava/lang/ClassLoader;)Ljava/lang/Class;
    //   7938: invokevirtual getDeclaredFields : ()[Ljava/lang/reflect/Field;
    //   7941: astore #5
    //   7943: aload #5
    //   7945: arraylength
    //   7946: istore #6
    //   7948: iconst_0
    //   7949: istore #7
    //   7951: iload #7
    //   7953: iload #6
    //   7955: if_icmpge -> 8093
    //   7958: aload #5
    //   7960: iload #7
    //   7962: aaload
    //   7963: astore #8
    //   7965: aload #8
    //   7967: invokevirtual getModifiers : ()I
    //   7970: invokestatic isStatic : (I)Z
    //   7973: ifne -> 7983
    //   7976: goto -> 8086
    //   7979: invokestatic a : (Ljava/lang/Throwable;)Ljava/lang/Throwable;
    //   7982: athrow
    //   7983: aload #8
    //   7985: invokevirtual getType : ()Ljava/lang/Class;
    //   7988: astore #9
    //   7990: aload #9
    //   7992: ifnull -> 8073
    //   7995: aload #9
    //   7997: invokevirtual isPrimitive : ()Z
    //   8000: ifne -> 8073
    //   8003: goto -> 8010
    //   8006: invokestatic a : (Ljava/lang/Throwable;)Ljava/lang/Throwable;
    //   8009: athrow
    //   8010: aload #9
    //   8012: invokevirtual getPackage : ()Ljava/lang/Package;
    //   8015: ifnull -> 8073
    //   8018: goto -> 8025
    //   8021: invokestatic a : (Ljava/lang/Throwable;)Ljava/lang/Throwable;
    //   8024: athrow
    //   8025: aload #9
    //   8027: invokevirtual getPackage : ()Ljava/lang/Package;
    //   8030: invokevirtual getName : ()Ljava/lang/String;
    //   8033: ifnull -> 8073
    //   8036: goto -> 8043
    //   8039: invokestatic a : (Ljava/lang/Throwable;)Ljava/lang/Throwable;
    //   8042: athrow
    //   8043: aload #9
    //   8045: invokevirtual getPackage : ()Ljava/lang/Package;
    //   8048: invokevirtual getName : ()Ljava/lang/String;
    //   8051: sipush #30219
    //   8054: sipush #24900
    //   8057: invokestatic a : (II)Ljava/lang/String;
    //   8060: invokevirtual startsWith : (Ljava/lang/String;)Z
    //   8063: ifne -> 8073
    //   8066: goto -> 8073
    //   8069: invokestatic a : (Ljava/lang/Throwable;)Ljava/lang/Throwable;
    //   8072: athrow
    //   8073: aload #8
    //   8075: iconst_1
    //   8076: invokevirtual setAccessible : (Z)V
    //   8079: aload #8
    //   8081: aconst_null
    //   8082: invokevirtual get : (Ljava/lang/Object;)Ljava/lang/Object;
    //   8085: pop
    //   8086: iinc #7, 1
    //   8089: iload_2
    //   8090: ifeq -> 7951
    //   8093: sipush #30238
    //   8096: sipush #-3897
    //   8099: invokestatic a : (II)Ljava/lang/String;
    //   8102: invokestatic forName : (Ljava/lang/String;)Ljava/lang/Class;
    //   8105: invokevirtual getDeclaredMethods : ()[Ljava/lang/reflect/Method;
    //   8108: astore #5
    //   8110: aload #5
    //   8112: arraylength
    //   8113: istore #6
    //   8115: iconst_0
    //   8116: istore #7
    //   8118: iload #7
    //   8120: iload #6
    //   8122: if_icmpge -> 8259
    //   8125: aload #5
    //   8127: iload #7
    //   8129: aaload
    //   8130: astore #8
    //   8132: aload #8
    //   8134: invokevirtual getParameterTypes : ()[Ljava/lang/Class;
    //   8137: pop
    //   8138: aload #8
    //   8140: invokevirtual getModifiers : ()I
    //   8143: invokestatic isStatic : (I)Z
    //   8146: ifeq -> 8245
    //   8149: aload #8
    //   8151: invokevirtual getParameterTypes : ()[Ljava/lang/Class;
    //   8154: arraylength
    //   8155: iconst_2
    //   8156: if_icmpne -> 8245
    //   8159: goto -> 8166
    //   8162: invokestatic a : (Ljava/lang/Throwable;)Ljava/lang/Throwable;
    //   8165: athrow
    //   8166: aload #8
    //   8168: invokevirtual getReturnType : ()Ljava/lang/Class;
    //   8171: getstatic java/lang/Boolean.TYPE : Ljava/lang/Class;
    //   8174: if_acmpne -> 8245
    //   8177: goto -> 8184
    //   8180: invokestatic a : (Ljava/lang/Throwable;)Ljava/lang/Throwable;
    //   8183: athrow
    //   8184: aload #8
    //   8186: iconst_1
    //   8187: invokevirtual setAccessible : (Z)V
    //   8190: aload #8
    //   8192: aconst_null
    //   8193: iconst_2
    //   8194: anewarray java/lang/Object
    //   8197: dup
    //   8198: iconst_0
    //   8199: aload_0
    //   8200: aastore
    //   8201: dup
    //   8202: iconst_1
    //   8203: aload_1
    //   8204: ifnonnull -> 8222
    //   8207: goto -> 8214
    //   8210: invokestatic a : (Ljava/lang/Throwable;)Ljava/lang/Throwable;
    //   8213: athrow
    //   8214: aload_1
    //   8215: goto -> 8229
    //   8218: invokestatic a : (Ljava/lang/Throwable;)Ljava/lang/Throwable;
    //   8221: athrow
    //   8222: aload_1
    //   8223: checkcast [B
    //   8226: invokevirtual clone : ()Ljava/lang/Object;
    //   8229: aastore
    //   8230: invokevirtual invoke : (Ljava/lang/Object;[Ljava/lang/Object;)Ljava/lang/Object;
    //   8233: checkcast java/lang/Boolean
    //   8236: invokevirtual booleanValue : ()Z
    //   8239: istore #4
    //   8241: iload_2
    //   8242: ifeq -> 8259
    //   8245: iinc #7, 1
    //   8248: iload_2
    //   8249: ifeq -> 8118
    //   8252: goto -> 8259
    //   8255: invokestatic a : (Ljava/lang/Throwable;)Ljava/lang/Throwable;
    //   8258: athrow
    //   8259: iload_2
    //   8260: ifeq -> 8602
    //   8263: sipush #30222
    //   8266: sipush #-20168
    //   8269: invokestatic a : (II)Ljava/lang/String;
    //   8272: iconst_1
    //   8273: ldc burp/Zer1
    //   8275: invokevirtual getClassLoader : ()Ljava/lang/ClassLoader;
    //   8278: invokestatic forName : (Ljava/lang/String;ZLjava/lang/ClassLoader;)Ljava/lang/Class;
    //   8281: invokevirtual getDeclaredFields : ()[Ljava/lang/reflect/Field;
    //   8284: astore #5
    //   8286: aload #5
    //   8288: arraylength
    //   8289: istore #6
    //   8291: iconst_0
    //   8292: istore #7
    //   8294: iload #7
    //   8296: iload #6
    //   8298: if_icmpge -> 8436
    //   8301: aload #5
    //   8303: iload #7
    //   8305: aaload
    //   8306: astore #8
    //   8308: aload #8
    //   8310: invokevirtual getModifiers : ()I
    //   8313: invokestatic isStatic : (I)Z
    //   8316: ifne -> 8326
    //   8319: goto -> 8429
    //   8322: invokestatic a : (Ljava/lang/Throwable;)Ljava/lang/Throwable;
    //   8325: athrow
    //   8326: aload #8
    //   8328: invokevirtual getType : ()Ljava/lang/Class;
    //   8331: astore #9
    //   8333: aload #9
    //   8335: ifnull -> 8416
    //   8338: aload #9
    //   8340: invokevirtual isPrimitive : ()Z
    //   8343: ifne -> 8416
    //   8346: goto -> 8353
    //   8349: invokestatic a : (Ljava/lang/Throwable;)Ljava/lang/Throwable;
    //   8352: athrow
    //   8353: aload #9
    //   8355: invokevirtual getPackage : ()Ljava/lang/Package;
    //   8358: ifnull -> 8416
    //   8361: goto -> 8368
    //   8364: invokestatic a : (Ljava/lang/Throwable;)Ljava/lang/Throwable;
    //   8367: athrow
    //   8368: aload #9
    //   8370: invokevirtual getPackage : ()Ljava/lang/Package;
    //   8373: invokevirtual getName : ()Ljava/lang/String;
    //   8376: ifnull -> 8416
    //   8379: goto -> 8386
    //   8382: invokestatic a : (Ljava/lang/Throwable;)Ljava/lang/Throwable;
    //   8385: athrow
    //   8386: aload #9
    //   8388: invokevirtual getPackage : ()Ljava/lang/Package;
    //   8391: invokevirtual getName : ()Ljava/lang/String;
    //   8394: sipush #30219
    //   8397: sipush #24900
    //   8400: invokestatic a : (II)Ljava/lang/String;
    //   8403: invokevirtual startsWith : (Ljava/lang/String;)Z
    //   8406: ifne -> 8416
    //   8409: goto -> 8416
    //   8412: invokestatic a : (Ljava/lang/Throwable;)Ljava/lang/Throwable;
    //   8415: athrow
    //   8416: aload #8
    //   8418: iconst_1
    //   8419: invokevirtual setAccessible : (Z)V
    //   8422: aload #8
    //   8424: aconst_null
    //   8425: invokevirtual get : (Ljava/lang/Object;)Ljava/lang/Object;
    //   8428: pop
    //   8429: iinc #7, 1
    //   8432: iload_2
    //   8433: ifeq -> 8294
    //   8436: sipush #30213
    //   8439: sipush #-22158
    //   8442: invokestatic a : (II)Ljava/lang/String;
    //   8445: invokestatic forName : (Ljava/lang/String;)Ljava/lang/Class;
    //   8448: invokevirtual getDeclaredMethods : ()[Ljava/lang/reflect/Method;
    //   8451: astore #5
    //   8453: aload #5
    //   8455: arraylength
    //   8456: istore #6
    //   8458: iconst_0
    //   8459: istore #7
    //   8461: iload #7
    //   8463: iload #6
    //   8465: if_icmpge -> 8602
    //   8468: aload #5
    //   8470: iload #7
    //   8472: aaload
    //   8473: astore #8
    //   8475: aload #8
    //   8477: invokevirtual getParameterTypes : ()[Ljava/lang/Class;
    //   8480: pop
    //   8481: aload #8
    //   8483: invokevirtual getModifiers : ()I
    //   8486: invokestatic isStatic : (I)Z
    //   8489: ifeq -> 8588
    //   8492: aload #8
    //   8494: invokevirtual getParameterTypes : ()[Ljava/lang/Class;
    //   8497: arraylength
    //   8498: iconst_2
    //   8499: if_icmpne -> 8588
    //   8502: goto -> 8509
    //   8505: invokestatic a : (Ljava/lang/Throwable;)Ljava/lang/Throwable;
    //   8508: athrow
    //   8509: aload #8
    //   8511: invokevirtual getReturnType : ()Ljava/lang/Class;
    //   8514: getstatic java/lang/Boolean.TYPE : Ljava/lang/Class;
    //   8517: if_acmpne -> 8588
    //   8520: goto -> 8527
    //   8523: invokestatic a : (Ljava/lang/Throwable;)Ljava/lang/Throwable;
    //   8526: athrow
    //   8527: aload #8
    //   8529: iconst_1
    //   8530: invokevirtual setAccessible : (Z)V
    //   8533: aload #8
    //   8535: aconst_null
    //   8536: iconst_2
    //   8537: anewarray java/lang/Object
    //   8540: dup
    //   8541: iconst_0
    //   8542: aload_0
    //   8543: aastore
    //   8544: dup
    //   8545: iconst_1
    //   8546: aload_1
    //   8547: ifnonnull -> 8565
    //   8550: goto -> 8557
    //   8553: invokestatic a : (Ljava/lang/Throwable;)Ljava/lang/Throwable;
    //   8556: athrow
    //   8557: aload_1
    //   8558: goto -> 8572
    //   8561: invokestatic a : (Ljava/lang/Throwable;)Ljava/lang/Throwable;
    //   8564: athrow
    //   8565: aload_1
    //   8566: checkcast [B
    //   8569: invokevirtual clone : ()Ljava/lang/Object;
    //   8572: aastore
    //   8573: invokevirtual invoke : (Ljava/lang/Object;[Ljava/lang/Object;)Ljava/lang/Object;
    //   8576: checkcast java/lang/Boolean
    //   8579: invokevirtual booleanValue : ()Z
    //   8582: istore #4
    //   8584: iload_2
    //   8585: ifeq -> 8602
    //   8588: iinc #7, 1
    //   8591: iload_2
    //   8592: ifeq -> 8461
    //   8595: goto -> 8602
    //   8598: invokestatic a : (Ljava/lang/Throwable;)Ljava/lang/Throwable;
    //   8601: athrow
    //   8602: iload #4
    //   8604: ifeq -> 8610
    //   8607: iload #4
    //   8609: ireturn
    //   8610: getstatic burp/Zdv.Zz : Ljava/lang/String;
    //   8613: getstatic burp/Ztq4.ZA : Ljava/lang/Object;
    //   8616: checkcast java/math/BigInteger
    //   8619: invokevirtual intValue : ()I
    //   8622: bipush #32
    //   8624: irem
    //   8625: invokestatic abs : (I)I
    //   8628: invokevirtual charAt : (I)C
    //   8631: getstatic burp/Zzah.Zs : Ljava/lang/String;
    //   8634: getstatic burp/Zbw5.ZR : Ljava/lang/Object;
    //   8637: checkcast java/math/BigInteger
    //   8640: invokevirtual intValue : ()I
    //   8643: bipush #32
    //   8645: irem
    //   8646: invokestatic abs : (I)I
    //   8649: invokevirtual charAt : (I)C
    //   8652: if_icmple -> 8998
    //   8655: sipush #30236
    //   8658: sipush #-3886
    //   8661: invokestatic a : (II)Ljava/lang/String;
    //   8664: iconst_1
    //   8665: ldc burp/Zeoi
    //   8667: invokevirtual getClassLoader : ()Ljava/lang/ClassLoader;
    //   8670: invokestatic forName : (Ljava/lang/String;ZLjava/lang/ClassLoader;)Ljava/lang/Class;
    //   8673: invokevirtual getDeclaredFields : ()[Ljava/lang/reflect/Field;
    //   8676: astore #5
    //   8678: aload #5
    //   8680: arraylength
    //   8681: istore #6
    //   8683: iconst_0
    //   8684: istore #7
    //   8686: iload #7
    //   8688: iload #6
    //   8690: if_icmpge -> 8828
    //   8693: aload #5
    //   8695: iload #7
    //   8697: aaload
    //   8698: astore #8
    //   8700: aload #8
    //   8702: invokevirtual getModifiers : ()I
    //   8705: invokestatic isStatic : (I)Z
    //   8708: ifne -> 8718
    //   8711: goto -> 8821
    //   8714: invokestatic a : (Ljava/lang/Throwable;)Ljava/lang/Throwable;
    //   8717: athrow
    //   8718: aload #8
    //   8720: invokevirtual getType : ()Ljava/lang/Class;
    //   8723: astore #9
    //   8725: aload #9
    //   8727: ifnull -> 8808
    //   8730: aload #9
    //   8732: invokevirtual isPrimitive : ()Z
    //   8735: ifne -> 8808
    //   8738: goto -> 8745
    //   8741: invokestatic a : (Ljava/lang/Throwable;)Ljava/lang/Throwable;
    //   8744: athrow
    //   8745: aload #9
    //   8747: invokevirtual getPackage : ()Ljava/lang/Package;
    //   8750: ifnull -> 8808
    //   8753: goto -> 8760
    //   8756: invokestatic a : (Ljava/lang/Throwable;)Ljava/lang/Throwable;
    //   8759: athrow
    //   8760: aload #9
    //   8762: invokevirtual getPackage : ()Ljava/lang/Package;
    //   8765: invokevirtual getName : ()Ljava/lang/String;
    //   8768: ifnull -> 8808
    //   8771: goto -> 8778
    //   8774: invokestatic a : (Ljava/lang/Throwable;)Ljava/lang/Throwable;
    //   8777: athrow
    //   8778: aload #9
    //   8780: invokevirtual getPackage : ()Ljava/lang/Package;
    //   8783: invokevirtual getName : ()Ljava/lang/String;
    //   8786: sipush #30219
    //   8789: sipush #24900
    //   8792: invokestatic a : (II)Ljava/lang/String;
    //   8795: invokevirtual startsWith : (Ljava/lang/String;)Z
    //   8798: ifne -> 8808
    //   8801: goto -> 8808
    //   8804: invokestatic a : (Ljava/lang/Throwable;)Ljava/lang/Throwable;
    //   8807: athrow
    //   8808: aload #8
    //   8810: iconst_1
    //   8811: invokevirtual setAccessible : (Z)V
    //   8814: aload #8
    //   8816: aconst_null
    //   8817: invokevirtual get : (Ljava/lang/Object;)Ljava/lang/Object;
    //   8820: pop
    //   8821: iinc #7, 1
    //   8824: iload_2
    //   8825: ifeq -> 8686
    //   8828: sipush #30237
    //   8831: sipush #-26293
    //   8834: invokestatic a : (II)Ljava/lang/String;
    //   8837: invokestatic forName : (Ljava/lang/String;)Ljava/lang/Class;
    //   8840: invokevirtual getDeclaredMethods : ()[Ljava/lang/reflect/Method;
    //   8843: astore #5
    //   8845: aload #5
    //   8847: arraylength
    //   8848: istore #6
    //   8850: iconst_0
    //   8851: istore #7
    //   8853: iload #7
    //   8855: iload #6
    //   8857: if_icmpge -> 8994
    //   8860: aload #5
    //   8862: iload #7
    //   8864: aaload
    //   8865: astore #8
    //   8867: aload #8
    //   8869: invokevirtual getParameterTypes : ()[Ljava/lang/Class;
    //   8872: pop
    //   8873: aload #8
    //   8875: invokevirtual getModifiers : ()I
    //   8878: invokestatic isStatic : (I)Z
    //   8881: ifeq -> 8980
    //   8884: aload #8
    //   8886: invokevirtual getParameterTypes : ()[Ljava/lang/Class;
    //   8889: arraylength
    //   8890: iconst_2
    //   8891: if_icmpne -> 8980
    //   8894: goto -> 8901
    //   8897: invokestatic a : (Ljava/lang/Throwable;)Ljava/lang/Throwable;
    //   8900: athrow
    //   8901: aload #8
    //   8903: invokevirtual getReturnType : ()Ljava/lang/Class;
    //   8906: getstatic java/lang/Boolean.TYPE : Ljava/lang/Class;
    //   8909: if_acmpne -> 8980
    //   8912: goto -> 8919
    //   8915: invokestatic a : (Ljava/lang/Throwable;)Ljava/lang/Throwable;
    //   8918: athrow
    //   8919: aload #8
    //   8921: iconst_1
    //   8922: invokevirtual setAccessible : (Z)V
    //   8925: aload #8
    //   8927: aconst_null
    //   8928: iconst_2
    //   8929: anewarray java/lang/Object
    //   8932: dup
    //   8933: iconst_0
    //   8934: aload_0
    //   8935: aastore
    //   8936: dup
    //   8937: iconst_1
    //   8938: aload_1
    //   8939: ifnonnull -> 8957
    //   8942: goto -> 8949
    //   8945: invokestatic a : (Ljava/lang/Throwable;)Ljava/lang/Throwable;
    //   8948: athrow
    //   8949: aload_1
    //   8950: goto -> 8964
    //   8953: invokestatic a : (Ljava/lang/Throwable;)Ljava/lang/Throwable;
    //   8956: athrow
    //   8957: aload_1
    //   8958: checkcast [B
    //   8961: invokevirtual clone : ()Ljava/lang/Object;
    //   8964: aastore
    //   8965: invokevirtual invoke : (Ljava/lang/Object;[Ljava/lang/Object;)Ljava/lang/Object;
    //   8968: checkcast java/lang/Boolean
    //   8971: invokevirtual booleanValue : ()Z
    //   8974: istore #4
    //   8976: iload_2
    //   8977: ifeq -> 8994
    //   8980: iinc #7, 1
    //   8983: iload_2
    //   8984: ifeq -> 8853
    //   8987: goto -> 8994
    //   8990: invokestatic a : (Ljava/lang/Throwable;)Ljava/lang/Throwable;
    //   8993: athrow
    //   8994: iload_2
    //   8995: ifeq -> 9337
    //   8998: sipush #30232
    //   9001: sipush #-8025
    //   9004: invokestatic a : (II)Ljava/lang/String;
    //   9007: iconst_1
    //   9008: ldc burp/Ze6t
    //   9010: invokevirtual getClassLoader : ()Ljava/lang/ClassLoader;
    //   9013: invokestatic forName : (Ljava/lang/String;ZLjava/lang/ClassLoader;)Ljava/lang/Class;
    //   9016: invokevirtual getDeclaredFields : ()[Ljava/lang/reflect/Field;
    //   9019: astore #5
    //   9021: aload #5
    //   9023: arraylength
    //   9024: istore #6
    //   9026: iconst_0
    //   9027: istore #7
    //   9029: iload #7
    //   9031: iload #6
    //   9033: if_icmpge -> 9171
    //   9036: aload #5
    //   9038: iload #7
    //   9040: aaload
    //   9041: astore #8
    //   9043: aload #8
    //   9045: invokevirtual getModifiers : ()I
    //   9048: invokestatic isStatic : (I)Z
    //   9051: ifne -> 9061
    //   9054: goto -> 9164
    //   9057: invokestatic a : (Ljava/lang/Throwable;)Ljava/lang/Throwable;
    //   9060: athrow
    //   9061: aload #8
    //   9063: invokevirtual getType : ()Ljava/lang/Class;
    //   9066: astore #9
    //   9068: aload #9
    //   9070: ifnull -> 9151
    //   9073: aload #9
    //   9075: invokevirtual isPrimitive : ()Z
    //   9078: ifne -> 9151
    //   9081: goto -> 9088
    //   9084: invokestatic a : (Ljava/lang/Throwable;)Ljava/lang/Throwable;
    //   9087: athrow
    //   9088: aload #9
    //   9090: invokevirtual getPackage : ()Ljava/lang/Package;
    //   9093: ifnull -> 9151
    //   9096: goto -> 9103
    //   9099: invokestatic a : (Ljava/lang/Throwable;)Ljava/lang/Throwable;
    //   9102: athrow
    //   9103: aload #9
    //   9105: invokevirtual getPackage : ()Ljava/lang/Package;
    //   9108: invokevirtual getName : ()Ljava/lang/String;
    //   9111: ifnull -> 9151
    //   9114: goto -> 9121
    //   9117: invokestatic a : (Ljava/lang/Throwable;)Ljava/lang/Throwable;
    //   9120: athrow
    //   9121: aload #9
    //   9123: invokevirtual getPackage : ()Ljava/lang/Package;
    //   9126: invokevirtual getName : ()Ljava/lang/String;
    //   9129: sipush #30219
    //   9132: sipush #24900
    //   9135: invokestatic a : (II)Ljava/lang/String;
    //   9138: invokevirtual startsWith : (Ljava/lang/String;)Z
    //   9141: ifne -> 9151
    //   9144: goto -> 9151
    //   9147: invokestatic a : (Ljava/lang/Throwable;)Ljava/lang/Throwable;
    //   9150: athrow
    //   9151: aload #8
    //   9153: iconst_1
    //   9154: invokevirtual setAccessible : (Z)V
    //   9157: aload #8
    //   9159: aconst_null
    //   9160: invokevirtual get : (Ljava/lang/Object;)Ljava/lang/Object;
    //   9163: pop
    //   9164: iinc #7, 1
    //   9167: iload_2
    //   9168: ifeq -> 9029
    //   9171: sipush #30208
    //   9174: sipush #-30851
    //   9177: invokestatic a : (II)Ljava/lang/String;
    //   9180: invokestatic forName : (Ljava/lang/String;)Ljava/lang/Class;
    //   9183: invokevirtual getDeclaredMethods : ()[Ljava/lang/reflect/Method;
    //   9186: astore #5
    //   9188: aload #5
    //   9190: arraylength
    //   9191: istore #6
    //   9193: iconst_0
    //   9194: istore #7
    //   9196: iload #7
    //   9198: iload #6
    //   9200: if_icmpge -> 9337
    //   9203: aload #5
    //   9205: iload #7
    //   9207: aaload
    //   9208: astore #8
    //   9210: aload #8
    //   9212: invokevirtual getParameterTypes : ()[Ljava/lang/Class;
    //   9215: pop
    //   9216: aload #8
    //   9218: invokevirtual getModifiers : ()I
    //   9221: invokestatic isStatic : (I)Z
    //   9224: ifeq -> 9323
    //   9227: aload #8
    //   9229: invokevirtual getParameterTypes : ()[Ljava/lang/Class;
    //   9232: arraylength
    //   9233: iconst_2
    //   9234: if_icmpne -> 9323
    //   9237: goto -> 9244
    //   9240: invokestatic a : (Ljava/lang/Throwable;)Ljava/lang/Throwable;
    //   9243: athrow
    //   9244: aload #8
    //   9246: invokevirtual getReturnType : ()Ljava/lang/Class;
    //   9249: getstatic java/lang/Boolean.TYPE : Ljava/lang/Class;
    //   9252: if_acmpne -> 9323
    //   9255: goto -> 9262
    //   9258: invokestatic a : (Ljava/lang/Throwable;)Ljava/lang/Throwable;
    //   9261: athrow
    //   9262: aload #8
    //   9264: iconst_1
    //   9265: invokevirtual setAccessible : (Z)V
    //   9268: aload #8
    //   9270: aconst_null
    //   9271: iconst_2
    //   9272: anewarray java/lang/Object
    //   9275: dup
    //   9276: iconst_0
    //   9277: aload_0
    //   9278: aastore
    //   9279: dup
    //   9280: iconst_1
    //   9281: aload_1
    //   9282: ifnonnull -> 9300
    //   9285: goto -> 9292
    //   9288: invokestatic a : (Ljava/lang/Throwable;)Ljava/lang/Throwable;
    //   9291: athrow
    //   9292: aload_1
    //   9293: goto -> 9307
    //   9296: invokestatic a : (Ljava/lang/Throwable;)Ljava/lang/Throwable;
    //   9299: athrow
    //   9300: aload_1
    //   9301: checkcast [B
    //   9304: invokevirtual clone : ()Ljava/lang/Object;
    //   9307: aastore
    //   9308: invokevirtual invoke : (Ljava/lang/Object;[Ljava/lang/Object;)Ljava/lang/Object;
    //   9311: checkcast java/lang/Boolean
    //   9314: invokevirtual booleanValue : ()Z
    //   9317: istore #4
    //   9319: iload_2
    //   9320: ifeq -> 9337
    //   9323: iinc #7, 1
    //   9326: iload_2
    //   9327: ifeq -> 9196
    //   9330: goto -> 9337
    //   9333: invokestatic a : (Ljava/lang/Throwable;)Ljava/lang/Throwable;
    //   9336: athrow
    //   9337: iload #4
    //   9339: ifeq -> 9345
    //   9342: iload #4
    //   9344: ireturn
    //   9345: getstatic burp/Zrp2.ZJ : Ljava/lang/String;
    //   9348: getstatic burp/Zrw0.ZC : Ljava/lang/Object;
    //   9351: checkcast java/math/BigInteger
    //   9354: invokevirtual intValue : ()I
    //   9357: bipush #32
    //   9359: irem
    //   9360: invokestatic abs : (I)I
    //   9363: invokevirtual charAt : (I)C
    //   9366: getstatic burp/Zx63.ZT : Ljava/lang/String;
    //   9369: getstatic burp/Zkhf.ZU : Ljava/lang/Object;
    //   9372: checkcast java/math/BigInteger
    //   9375: invokevirtual intValue : ()I
    //   9378: bipush #32
    //   9380: irem
    //   9381: invokestatic abs : (I)I
    //   9384: invokevirtual charAt : (I)C
    //   9387: if_icmple -> 9733
    //   9390: sipush #30230
    //   9393: sipush #14149
    //   9396: invokestatic a : (II)Ljava/lang/String;
    //   9399: iconst_1
    //   9400: ldc burp/Zgsy
    //   9402: invokevirtual getClassLoader : ()Ljava/lang/ClassLoader;
    //   9405: invokestatic forName : (Ljava/lang/String;ZLjava/lang/ClassLoader;)Ljava/lang/Class;
    //   9408: invokevirtual getDeclaredFields : ()[Ljava/lang/reflect/Field;
    //   9411: astore #5
    //   9413: aload #5
    //   9415: arraylength
    //   9416: istore #6
    //   9418: iconst_0
    //   9419: istore #7
    //   9421: iload #7
    //   9423: iload #6
    //   9425: if_icmpge -> 9563
    //   9428: aload #5
    //   9430: iload #7
    //   9432: aaload
    //   9433: astore #8
    //   9435: aload #8
    //   9437: invokevirtual getModifiers : ()I
    //   9440: invokestatic isStatic : (I)Z
    //   9443: ifne -> 9453
    //   9446: goto -> 9556
    //   9449: invokestatic a : (Ljava/lang/Throwable;)Ljava/lang/Throwable;
    //   9452: athrow
    //   9453: aload #8
    //   9455: invokevirtual getType : ()Ljava/lang/Class;
    //   9458: astore #9
    //   9460: aload #9
    //   9462: ifnull -> 9543
    //   9465: aload #9
    //   9467: invokevirtual isPrimitive : ()Z
    //   9470: ifne -> 9543
    //   9473: goto -> 9480
    //   9476: invokestatic a : (Ljava/lang/Throwable;)Ljava/lang/Throwable;
    //   9479: athrow
    //   9480: aload #9
    //   9482: invokevirtual getPackage : ()Ljava/lang/Package;
    //   9485: ifnull -> 9543
    //   9488: goto -> 9495
    //   9491: invokestatic a : (Ljava/lang/Throwable;)Ljava/lang/Throwable;
    //   9494: athrow
    //   9495: aload #9
    //   9497: invokevirtual getPackage : ()Ljava/lang/Package;
    //   9500: invokevirtual getName : ()Ljava/lang/String;
    //   9503: ifnull -> 9543
    //   9506: goto -> 9513
    //   9509: invokestatic a : (Ljava/lang/Throwable;)Ljava/lang/Throwable;
    //   9512: athrow
    //   9513: aload #9
    //   9515: invokevirtual getPackage : ()Ljava/lang/Package;
    //   9518: invokevirtual getName : ()Ljava/lang/String;
    //   9521: sipush #30219
    //   9524: sipush #24900
    //   9527: invokestatic a : (II)Ljava/lang/String;
    //   9530: invokevirtual startsWith : (Ljava/lang/String;)Z
    //   9533: ifne -> 9543
    //   9536: goto -> 9543
    //   9539: invokestatic a : (Ljava/lang/Throwable;)Ljava/lang/Throwable;
    //   9542: athrow
    //   9543: aload #8
    //   9545: iconst_1
    //   9546: invokevirtual setAccessible : (Z)V
    //   9549: aload #8
    //   9551: aconst_null
    //   9552: invokevirtual get : (Ljava/lang/Object;)Ljava/lang/Object;
    //   9555: pop
    //   9556: iinc #7, 1
    //   9559: iload_2
    //   9560: ifeq -> 9421
    //   9563: sipush #30215
    //   9566: sipush #21665
    //   9569: invokestatic a : (II)Ljava/lang/String;
    //   9572: invokestatic forName : (Ljava/lang/String;)Ljava/lang/Class;
    //   9575: invokevirtual getDeclaredMethods : ()[Ljava/lang/reflect/Method;
    //   9578: astore #5
    //   9580: aload #5
    //   9582: arraylength
    //   9583: istore #6
    //   9585: iconst_0
    //   9586: istore #7
    //   9588: iload #7
    //   9590: iload #6
    //   9592: if_icmpge -> 9729
    //   9595: aload #5
    //   9597: iload #7
    //   9599: aaload
    //   9600: astore #8
    //   9602: aload #8
    //   9604: invokevirtual getParameterTypes : ()[Ljava/lang/Class;
    //   9607: pop
    //   9608: aload #8
    //   9610: invokevirtual getModifiers : ()I
    //   9613: invokestatic isStatic : (I)Z
    //   9616: ifeq -> 9715
    //   9619: aload #8
    //   9621: invokevirtual getParameterTypes : ()[Ljava/lang/Class;
    //   9624: arraylength
    //   9625: iconst_2
    //   9626: if_icmpne -> 9715
    //   9629: goto -> 9636
    //   9632: invokestatic a : (Ljava/lang/Throwable;)Ljava/lang/Throwable;
    //   9635: athrow
    //   9636: aload #8
    //   9638: invokevirtual getReturnType : ()Ljava/lang/Class;
    //   9641: getstatic java/lang/Boolean.TYPE : Ljava/lang/Class;
    //   9644: if_acmpne -> 9715
    //   9647: goto -> 9654
    //   9650: invokestatic a : (Ljava/lang/Throwable;)Ljava/lang/Throwable;
    //   9653: athrow
    //   9654: aload #8
    //   9656: iconst_1
    //   9657: invokevirtual setAccessible : (Z)V
    //   9660: aload #8
    //   9662: aconst_null
    //   9663: iconst_2
    //   9664: anewarray java/lang/Object
    //   9667: dup
    //   9668: iconst_0
    //   9669: aload_0
    //   9670: aastore
    //   9671: dup
    //   9672: iconst_1
    //   9673: aload_1
    //   9674: ifnonnull -> 9692
    //   9677: goto -> 9684
    //   9680: invokestatic a : (Ljava/lang/Throwable;)Ljava/lang/Throwable;
    //   9683: athrow
    //   9684: aload_1
    //   9685: goto -> 9699
    //   9688: invokestatic a : (Ljava/lang/Throwable;)Ljava/lang/Throwable;
    //   9691: athrow
    //   9692: aload_1
    //   9693: checkcast [B
    //   9696: invokevirtual clone : ()Ljava/lang/Object;
    //   9699: aastore
    //   9700: invokevirtual invoke : (Ljava/lang/Object;[Ljava/lang/Object;)Ljava/lang/Object;
    //   9703: checkcast java/lang/Boolean
    //   9706: invokevirtual booleanValue : ()Z
    //   9709: istore #4
    //   9711: iload_2
    //   9712: ifeq -> 9729
    //   9715: iinc #7, 1
    //   9718: iload_2
    //   9719: ifeq -> 9588
    //   9722: goto -> 9729
    //   9725: invokestatic a : (Ljava/lang/Throwable;)Ljava/lang/Throwable;
    //   9728: athrow
    //   9729: iload_2
    //   9730: ifeq -> 10072
    //   9733: sipush #30209
    //   9736: sipush #-6489
    //   9739: invokestatic a : (II)Ljava/lang/String;
    //   9742: iconst_1
    //   9743: ldc burp/Zb6e
    //   9745: invokevirtual getClassLoader : ()Ljava/lang/ClassLoader;
    //   9748: invokestatic forName : (Ljava/lang/String;ZLjava/lang/ClassLoader;)Ljava/lang/Class;
    //   9751: invokevirtual getDeclaredFields : ()[Ljava/lang/reflect/Field;
    //   9754: astore #5
    //   9756: aload #5
    //   9758: arraylength
    //   9759: istore #6
    //   9761: iconst_0
    //   9762: istore #7
    //   9764: iload #7
    //   9766: iload #6
    //   9768: if_icmpge -> 9906
    //   9771: aload #5
    //   9773: iload #7
    //   9775: aaload
    //   9776: astore #8
    //   9778: aload #8
    //   9780: invokevirtual getModifiers : ()I
    //   9783: invokestatic isStatic : (I)Z
    //   9786: ifne -> 9796
    //   9789: goto -> 9899
    //   9792: invokestatic a : (Ljava/lang/Throwable;)Ljava/lang/Throwable;
    //   9795: athrow
    //   9796: aload #8
    //   9798: invokevirtual getType : ()Ljava/lang/Class;
    //   9801: astore #9
    //   9803: aload #9
    //   9805: ifnull -> 9886
    //   9808: aload #9
    //   9810: invokevirtual isPrimitive : ()Z
    //   9813: ifne -> 9886
    //   9816: goto -> 9823
    //   9819: invokestatic a : (Ljava/lang/Throwable;)Ljava/lang/Throwable;
    //   9822: athrow
    //   9823: aload #9
    //   9825: invokevirtual getPackage : ()Ljava/lang/Package;
    //   9828: ifnull -> 9886
    //   9831: goto -> 9838
    //   9834: invokestatic a : (Ljava/lang/Throwable;)Ljava/lang/Throwable;
    //   9837: athrow
    //   9838: aload #9
    //   9840: invokevirtual getPackage : ()Ljava/lang/Package;
    //   9843: invokevirtual getName : ()Ljava/lang/String;
    //   9846: ifnull -> 9886
    //   9849: goto -> 9856
    //   9852: invokestatic a : (Ljava/lang/Throwable;)Ljava/lang/Throwable;
    //   9855: athrow
    //   9856: aload #9
    //   9858: invokevirtual getPackage : ()Ljava/lang/Package;
    //   9861: invokevirtual getName : ()Ljava/lang/String;
    //   9864: sipush #30219
    //   9867: sipush #24900
    //   9870: invokestatic a : (II)Ljava/lang/String;
    //   9873: invokevirtual startsWith : (Ljava/lang/String;)Z
    //   9876: ifne -> 9886
    //   9879: goto -> 9886
    //   9882: invokestatic a : (Ljava/lang/Throwable;)Ljava/lang/Throwable;
    //   9885: athrow
    //   9886: aload #8
    //   9888: iconst_1
    //   9889: invokevirtual setAccessible : (Z)V
    //   9892: aload #8
    //   9894: aconst_null
    //   9895: invokevirtual get : (Ljava/lang/Object;)Ljava/lang/Object;
    //   9898: pop
    //   9899: iinc #7, 1
    //   9902: iload_2
    //   9903: ifeq -> 9764
    //   9906: sipush #30217
    //   9909: sipush #-21497
    //   9912: invokestatic a : (II)Ljava/lang/String;
    //   9915: invokestatic forName : (Ljava/lang/String;)Ljava/lang/Class;
    //   9918: invokevirtual getDeclaredMethods : ()[Ljava/lang/reflect/Method;
    //   9921: astore #5
    //   9923: aload #5
    //   9925: arraylength
    //   9926: istore #6
    //   9928: iconst_0
    //   9929: istore #7
    //   9931: iload #7
    //   9933: iload #6
    //   9935: if_icmpge -> 10072
    //   9938: aload #5
    //   9940: iload #7
    //   9942: aaload
    //   9943: astore #8
    //   9945: aload #8
    //   9947: invokevirtual getParameterTypes : ()[Ljava/lang/Class;
    //   9950: pop
    //   9951: aload #8
    //   9953: invokevirtual getModifiers : ()I
    //   9956: invokestatic isStatic : (I)Z
    //   9959: ifeq -> 10058
    //   9962: aload #8
    //   9964: invokevirtual getParameterTypes : ()[Ljava/lang/Class;
    //   9967: arraylength
    //   9968: iconst_2
    //   9969: if_icmpne -> 10058
    //   9972: goto -> 9979
    //   9975: invokestatic a : (Ljava/lang/Throwable;)Ljava/lang/Throwable;
    //   9978: athrow
    //   9979: aload #8
    //   9981: invokevirtual getReturnType : ()Ljava/lang/Class;
    //   9984: getstatic java/lang/Boolean.TYPE : Ljava/lang/Class;
    //   9987: if_acmpne -> 10058
    //   9990: goto -> 9997
    //   9993: invokestatic a : (Ljava/lang/Throwable;)Ljava/lang/Throwable;
    //   9996: athrow
    //   9997: aload #8
    //   9999: iconst_1
    //   10000: invokevirtual setAccessible : (Z)V
    //   10003: aload #8
    //   10005: aconst_null
    //   10006: iconst_2
    //   10007: anewarray java/lang/Object
    //   10010: dup
    //   10011: iconst_0
    //   10012: aload_0
    //   10013: aastore
    //   10014: dup
    //   10015: iconst_1
    //   10016: aload_1
    //   10017: ifnonnull -> 10035
    //   10020: goto -> 10027
    //   10023: invokestatic a : (Ljava/lang/Throwable;)Ljava/lang/Throwable;
    //   10026: athrow
    //   10027: aload_1
    //   10028: goto -> 10042
    //   10031: invokestatic a : (Ljava/lang/Throwable;)Ljava/lang/Throwable;
    //   10034: athrow
    //   10035: aload_1
    //   10036: checkcast [B
    //   10039: invokevirtual clone : ()Ljava/lang/Object;
    //   10042: aastore
    //   10043: invokevirtual invoke : (Ljava/lang/Object;[Ljava/lang/Object;)Ljava/lang/Object;
    //   10046: checkcast java/lang/Boolean
    //   10049: invokevirtual booleanValue : ()Z
    //   10052: istore #4
    //   10054: iload_2
    //   10055: ifeq -> 10072
    //   10058: iinc #7, 1
    //   10061: iload_2
    //   10062: ifeq -> 9931
    //   10065: goto -> 10072
    //   10068: invokestatic a : (Ljava/lang/Throwable;)Ljava/lang/Throwable;
    //   10071: athrow
    //   10072: iload #4
    //   10074: ireturn
    //   10075: astore_3
    //   10076: new java/lang/Exception
    //   10079: dup
    //   10080: aload_3
    //   10081: invokevirtual getMessage : ()Ljava/lang/String;
    //   10084: invokespecial <init> : (Ljava/lang/String;)V
    //   10087: athrow
    // Exception table:
    //   from	to	target	type
    //   4	7874	10075	java/lang/Throwable
    //   309	333	336	java/lang/Throwable
    //   407	444	444	java/lang/Throwable
    //   448	469	469	java/lang/Throwable
    //   473	503	503	java/lang/Throwable
    //   1487	1521	1524	java/lang/Throwable
    //   1616	1694	1697	java/lang/Throwable
    //   1623	1837	1840	java/lang/Throwable
    //   2214	2229	2229	java/lang/Throwable
    //   2256	2290	2293	java/lang/Throwable
    //   2300	2312	2315	java/lang/Throwable
    //   2398	2476	2479	java/lang/Throwable
    //   2405	2619	2622	java/lang/Throwable
    //   3019	3097	3100	java/lang/Throwable
    //   3026	3240	3243	java/lang/Throwable
    //   3687	3721	3724	java/lang/Throwable
    //   3728	3740	3743	java/lang/Throwable
    //   3826	3904	3907	java/lang/Throwable
    //   3833	4047	4050	java/lang/Throwable
    //   4777	4950	4953	java/lang/Throwable
    //   4920	4987	4990	java/lang/Throwable
    //   4957	5024	5027	java/lang/Throwable
    //   4994	5061	5064	java/lang/Throwable
    //   5031	5098	5101	java/lang/Throwable
    //   5068	5135	5138	java/lang/Throwable
    //   5105	5172	5175	java/lang/Throwable
    //   5142	5209	5212	java/lang/Throwable
    //   5179	5246	5249	java/lang/Throwable
    //   5216	5283	5286	java/lang/Throwable
    //   5253	5320	5323	java/lang/Throwable
    //   5290	5357	5360	java/lang/Throwable
    //   5327	5394	5397	java/lang/Throwable
    //   5364	5431	5434	java/lang/Throwable
    //   5401	5468	5471	java/lang/Throwable
    //   5438	5505	5508	java/lang/Throwable
    //   5475	5542	5545	java/lang/Throwable
    //   5512	5579	5582	java/lang/Throwable
    //   5549	5616	5619	java/lang/Throwable
    //   5586	5653	5656	java/lang/Throwable
    //   5623	5690	5693	java/lang/Throwable
    //   5660	5727	5730	java/lang/Throwable
    //   5697	5764	5767	java/lang/Throwable
    //   5734	5801	5804	java/lang/Throwable
    //   5771	5838	5841	java/lang/Throwable
    //   5808	5875	5878	java/lang/Throwable
    //   5845	5912	5915	java/lang/Throwable
    //   5882	5949	5952	java/lang/Throwable
    //   5919	5986	5989	java/lang/Throwable
    //   5956	6023	6026	java/lang/Throwable
    //   5993	6060	6063	java/lang/Throwable
    //   6030	6093	6096	java/lang/Throwable
    //   6159	6173	6173	java/lang/Throwable
    //   6184	6197	6200	java/lang/Throwable
    //   6189	6212	6215	java/lang/Throwable
    //   6204	6230	6233	java/lang/Throwable
    //   6219	6260	6263	java/lang/Throwable
    //   6326	6353	6356	java/lang/Throwable
    //   6343	6374	6377	java/lang/Throwable
    //   6360	6404	6407	java/lang/Throwable
    //   6381	6415	6415	java/lang/Throwable
    //   6426	6442	6445	java/lang/Throwable
    //   6761	6785	6788	java/lang/Throwable
    //   6859	6896	6896	java/lang/Throwable
    //   6900	6921	6921	java/lang/Throwable
    //   6925	6955	6955	java/lang/Throwable
    //   7231	7245	7245	java/lang/Throwable
    //   7256	7269	7272	java/lang/Throwable
    //   7261	7284	7287	java/lang/Throwable
    //   7276	7302	7305	java/lang/Throwable
    //   7291	7332	7335	java/lang/Throwable
    //   7398	7425	7428	java/lang/Throwable
    //   7415	7443	7446	java/lang/Throwable
    //   7432	7473	7476	java/lang/Throwable
    //   7450	7484	7484	java/lang/Throwable
    //   7507	7518	7521	java/lang/Throwable
    //   7573	7587	7587	java/lang/Throwable
    //   7598	7611	7614	java/lang/Throwable
    //   7603	7626	7629	java/lang/Throwable
    //   7618	7644	7647	java/lang/Throwable
    //   7633	7674	7677	java/lang/Throwable
    //   7740	7767	7770	java/lang/Throwable
    //   7757	7785	7788	java/lang/Throwable
    //   7774	7815	7818	java/lang/Throwable
    //   7792	7826	7826	java/lang/Throwable
    //   7849	7860	7863	java/lang/Throwable
    //   7875	8609	10075	java/lang/Throwable
    //   7965	7979	7979	java/lang/Throwable
    //   7990	8003	8006	java/lang/Throwable
    //   7995	8018	8021	java/lang/Throwable
    //   8010	8036	8039	java/lang/Throwable
    //   8025	8066	8069	java/lang/Throwable
    //   8132	8159	8162	java/lang/Throwable
    //   8149	8177	8180	java/lang/Throwable
    //   8166	8207	8210	java/lang/Throwable
    //   8184	8218	8218	java/lang/Throwable
    //   8241	8252	8255	java/lang/Throwable
    //   8308	8322	8322	java/lang/Throwable
    //   8333	8346	8349	java/lang/Throwable
    //   8338	8361	8364	java/lang/Throwable
    //   8353	8379	8382	java/lang/Throwable
    //   8368	8409	8412	java/lang/Throwable
    //   8475	8502	8505	java/lang/Throwable
    //   8492	8520	8523	java/lang/Throwable
    //   8509	8550	8553	java/lang/Throwable
    //   8527	8561	8561	java/lang/Throwable
    //   8584	8595	8598	java/lang/Throwable
    //   8610	9344	10075	java/lang/Throwable
    //   8700	8714	8714	java/lang/Throwable
    //   8725	8738	8741	java/lang/Throwable
    //   8730	8753	8756	java/lang/Throwable
    //   8745	8771	8774	java/lang/Throwable
    //   8760	8801	8804	java/lang/Throwable
    //   8867	8894	8897	java/lang/Throwable
    //   8884	8912	8915	java/lang/Throwable
    //   8901	8942	8945	java/lang/Throwable
    //   8919	8953	8953	java/lang/Throwable
    //   8976	8987	8990	java/lang/Throwable
    //   9043	9057	9057	java/lang/Throwable
    //   9068	9081	9084	java/lang/Throwable
    //   9073	9096	9099	java/lang/Throwable
    //   9088	9114	9117	java/lang/Throwable
    //   9103	9144	9147	java/lang/Throwable
    //   9210	9237	9240	java/lang/Throwable
    //   9227	9255	9258	java/lang/Throwable
    //   9244	9285	9288	java/lang/Throwable
    //   9262	9296	9296	java/lang/Throwable
    //   9319	9330	9333	java/lang/Throwable
    //   9345	10074	10075	java/lang/Throwable
    //   9435	9449	9449	java/lang/Throwable
    //   9460	9473	9476	java/lang/Throwable
    //   9465	9488	9491	java/lang/Throwable
    //   9480	9506	9509	java/lang/Throwable
    //   9495	9536	9539	java/lang/Throwable
    //   9602	9629	9632	java/lang/Throwable
    //   9619	9647	9650	java/lang/Throwable
    //   9636	9677	9680	java/lang/Throwable
    //   9654	9688	9688	java/lang/Throwable
    //   9711	9722	9725	java/lang/Throwable
    //   9778	9792	9792	java/lang/Throwable
    //   9803	9816	9819	java/lang/Throwable
    //   9808	9831	9834	java/lang/Throwable
    //   9823	9849	9852	java/lang/Throwable
    //   9838	9879	9882	java/lang/Throwable
    //   9945	9972	9975	java/lang/Throwable
    //   9962	9990	9993	java/lang/Throwable
    //   9979	10020	10023	java/lang/Throwable
    //   9997	10031	10031	java/lang/Throwable
    //   10054	10065	10068	java/lang/Throwable
  }
  
  static void ZO(Object[] paramArrayOfObject, Object paramObject) throws Throwable {}
  
  static {
    // Byte code:
    //   0: bipush #31
    //   2: anewarray java/lang/String
    //   5: astore #5
    //   7: iconst_0
    //   8: istore_3
    //   9: ldc 'm,G\\t}=\\t)N( ahy# pH-E3Hl}\\t{Xu5Yn\\t.P`\\n~\\bj@k88G\\ta\6j]!\\th3yb\\t0i\\tfKPo\\tt7\\tcR\\t<&@L eJ2YZQ#]\\tYy1IC\\t\\b\\ttU\\thL) |hja.\l,=i\\tB]RJ\\t^O*rf\\tE[N\\tz5v @ K]?+M0,)'#'
    //   11: dup
    //   12: astore_2
    //   13: invokevirtual length : ()I
    //   16: istore #4
    //   18: bipush #9
    //   20: istore_1
    //   21: iconst_m1
    //   22: istore_0
    //   23: bipush #41
    //   25: iinc #0, 1
    //   28: aload_2
    //   29: iload_0
    //   30: dup
    //   31: iload_1
    //   32: iadd
    //   33: invokevirtual substring : (II)Ljava/lang/String;
    //   36: iconst_m1
    //   37: goto -> 143
    //   40: aload #5
    //   42: swap
    //   43: iload_3
    //   44: iinc #3, 1
    //   47: swap
    //   48: aastore
    //   49: iload_0
    //   50: iload_1
    //   51: iadd
    //   52: dup
    //   53: istore_0
    //   54: iload #4
    //   56: if_icmpge -> 68
    //   59: aload_2
    //   60: iload_0
    //   61: invokevirtual charAt : (I)C
    //   64: istore_1
    //   65: goto -> 23
    //   68: ldc 'OV<=MhAzs&$RV2a~Uq**d|m} yK,&\\bUxNEe'
    //   70: dup
    //   71: astore_2
    //   72: invokevirtual length : ()I
    //   75: istore #4
    //   77: bipush #9
    //   79: istore_1
    //   80: iconst_m1
    //   81: istore_0
    //   82: bipush #39
    //   84: iinc #0, 1
    //   87: aload_2
    //   88: iload_0
    //   89: dup
    //   90: iload_1
    //   91: iadd
    //   92: invokevirtual substring : (II)Ljava/lang/String;
    //   95: iconst_0
    //   96: goto -> 143
    //   99: aload #5
    //   101: swap
    //   102: iload_3
    //   103: iinc #3, 1
    //   106: swap
    //   107: aastore
    //   108: iload_0
    //   109: iload_1
    //   110: iadd
    //   111: dup
    //   112: istore_0
    //   113: iload #4
    //   115: if_icmpge -> 127
    //   118: aload_2
    //   119: iload_0
    //   120: invokevirtual charAt : (I)C
    //   123: istore_1
    //   124: goto -> 82
    //   127: aload #5
    //   129: putstatic burp/Zllk.a : [Ljava/lang/String;
    //   132: bipush #31
    //   134: anewarray java/lang/String
    //   137: putstatic burp/Zllk.b : [Ljava/lang/String;
    //   140: goto -> 300
    //   143: dup_x2
    //   144: pop
    //   145: invokevirtual toCharArray : ()[C
    //   148: dup_x1
    //   149: arraylength
    //   150: dup_x2
    //   151: pop
    //   152: iconst_0
    //   153: istore #6
    //   155: dup2_x1
    //   156: pop2
    //   157: dup_x2
    //   158: iconst_1
    //   159: if_icmpgt -> 259
    //   162: dup2
    //   163: swap
    //   164: iload #6
    //   166: dup2_x1
    //   167: caload
    //   168: swap
    //   169: iload #6
    //   171: bipush #7
    //   173: irem
    //   174: tableswitch default -> 241, 0 -> 212, 1 -> 216, 2 -> 221, 3 -> 226, 4 -> 231, 5 -> 236
    //   212: iconst_3
    //   213: goto -> 243
    //   216: bipush #6
    //   218: goto -> 243
    //   221: bipush #61
    //   223: goto -> 243
    //   226: bipush #125
    //   228: goto -> 243
    //   231: bipush #88
    //   233: goto -> 243
    //   236: bipush #28
    //   238: goto -> 243
    //   241: bipush #27
    //   243: ixor
    //   244: ixor
    //   245: i2c
    //   246: castore
    //   247: iinc #6, 1
    //   250: dup
    //   251: ifne -> 259
    //   254: dup2
    //   255: dup_x1
    //   256: goto -> 166
    //   259: dup2_x1
    //   260: pop2
    //   261: dup_x2
    //   262: iload #6
    //   264: if_icmpgt -> 162
    //   267: pop
    //   268: new java/lang/String
    //   271: dup_x1
    //   272: swap
    //   273: invokespecial <init> : ([C)V
    //   276: invokevirtual intern : ()Ljava/lang/String;
    //   279: swap
    //   280: pop
    //   281: swap
    //   282: tableswitch default -> 40, 0 -> 99
    //   300: new java/math/BigInteger
    //   303: dup
    //   304: bipush #32
    //   306: newarray byte
    //   308: dup
    //   309: iconst_0
    //   310: bipush #44
    //   312: bastore
    //   313: dup
    //   314: iconst_1
    //   315: bipush #-18
    //   317: bastore
    //   318: dup
    //   319: iconst_2
    //   320: bipush #10
    //   322: bastore
    //   323: dup
    //   324: iconst_3
    //   325: bipush #46
    //   327: bastore
    //   328: dup
    //   329: iconst_4
    //   330: bipush #-96
    //   332: bastore
    //   333: dup
    //   334: iconst_5
    //   335: bipush #92
    //   337: bastore
    //   338: dup
    //   339: bipush #6
    //   341: bipush #-67
    //   343: bastore
    //   344: dup
    //   345: bipush #7
    //   347: bipush #-128
    //   349: bastore
    //   350: dup
    //   351: bipush #8
    //   353: bipush #-64
    //   355: bastore
    //   356: dup
    //   357: bipush #9
    //   359: bipush #39
    //   361: bastore
    //   362: dup
    //   363: bipush #10
    //   365: iconst_m1
    //   366: bastore
    //   367: dup
    //   368: bipush #11
    //   370: bipush #-16
    //   372: bastore
    //   373: dup
    //   374: bipush #12
    //   376: bipush #31
    //   378: bastore
    //   379: dup
    //   380: bipush #13
    //   382: bipush #-21
    //   384: bastore
    //   385: dup
    //   386: bipush #14
    //   388: bipush #-37
    //   390: bastore
    //   391: dup
    //   392: bipush #15
    //   394: bipush #38
    //   396: bastore
    //   397: dup
    //   398: bipush #16
    //   400: bipush #-28
    //   402: bastore
    //   403: dup
    //   404: bipush #17
    //   406: bipush #75
    //   408: bastore
    //   409: dup
    //   410: bipush #18
    //   412: bipush #-86
    //   414: bastore
    //   415: dup
    //   416: bipush #19
    //   418: iconst_4
    //   419: bastore
    //   420: dup
    //   421: bipush #20
    //   423: bipush #88
    //   425: bastore
    //   426: dup
    //   427: bipush #21
    //   429: bipush #105
    //   431: bastore
    //   432: dup
    //   433: bipush #22
    //   435: bipush #83
    //   437: bastore
    //   438: dup
    //   439: bipush #23
    //   441: bipush #43
    //   443: bastore
    //   444: dup
    //   445: bipush #24
    //   447: bipush #103
    //   449: bastore
    //   450: dup
    //   451: bipush #25
    //   453: bipush #-126
    //   455: bastore
    //   456: dup
    //   457: bipush #26
    //   459: bipush #91
    //   461: bastore
    //   462: dup
    //   463: bipush #27
    //   465: bipush #29
    //   467: bastore
    //   468: dup
    //   469: bipush #28
    //   471: bipush #63
    //   473: bastore
    //   474: dup
    //   475: bipush #29
    //   477: bipush #-92
    //   479: bastore
    //   480: dup
    //   481: bipush #30
    //   483: bipush #41
    //   485: bastore
    //   486: dup
    //   487: bipush #31
    //   489: bipush #75
    //   491: bastore
    //   492: invokespecial <init> : ([B)V
    //   495: putstatic burp/Zllk.Zi : Ljava/lang/Object;
    //   498: sipush #30228
    //   501: sipush #-5781
    //   504: invokestatic a : (II)Ljava/lang/String;
    //   507: putstatic burp/Zllk.Zs : Ljava/lang/String;
    //   510: return
  }
  
  private static Throwable a(Throwable paramThrowable) {
    return paramThrowable;
  }
  
  private static String a(int paramInt1, int paramInt2) {
    int i = (paramInt1 ^ 0x7605) & 0xFFFF;
    if (b[i] == null) {
      char[] arrayOfChar = a[i].toCharArray();
      switch (arrayOfChar[0] & 0xFF) {
        case 0:
        
        case 1:
        
        case 2:
        
        case 3:
        
        case 4:
        
        case 5:
        
        case 6:
        
        case 7:
        
        case 8:
        
        case 9:
        
        case 10:
        
        case 11:
        
        case 12:
        
        case 13:
        
        case 14:
        
        case 15:
        
        case 16:
        
        case 17:
        
        case 18:
        
        case 19:
        
        case 20:
        
        case 21:
        
        case 22:
        
        case 23:
        
        case 24:
        
        case 25:
        
        case 26:
        
        case 27:
        
        case 28:
        
        case 29:
        
        case 30:
        
        case 31:
        
        case 32:
        
        case 33:
        
        case 34:
        
        case 35:
        
        case 36:
        
        case 37:
        
        case 38:
        
        case 39:
        
        case 40:
        
        case 41:
        
        case 42:
        
        case 43:
        
        case 44:
        
        case 45:
        
        case 46:
        
        case 47:
        
        case 48:
        
        case 49:
        
        case 50:
        
        case 51:
        
        case 52:
        
        case 53:
        
        case 54:
        
        case 55:
        
        case 56:
        
        case 57:
        
        case 58:
        
        case 59:
        
        case 60:
        
        case 61:
        
        case 62:
        
        case 63:
        
        case 64:
        
        case 65:
        
        case 66:
        
        case 67:
        
        case 68:
        
        case 69:
        
        case 70:
        
        case 71:
        
        case 72:
        
        case 73:
        
        case 74:
        
        case 75:
        
        case 76:
        
        case 77:
        
        case 78:
        
        case 79:
        
        case 80:
        
        case 81:
        
        case 82:
        
        case 83:
        
        case 84:
        
        case 85:
        
        case 86:
        
        case 87:
        
        case 88:
        
        case 89:
        
        case 90:
        
        case 91:
        
        case 92:
        
        case 93:
        
        case 94:
        
        case 95:
        
        case 96:
        
        case 97:
        
        case 98:
        
        case 99:
        
        case 100:
        
        case 101:
        
        case 102:
        
        case 103:
        
        case 104:
        
        case 105:
        
        case 106:
        
        case 107:
        
        case 108:
        
        case 109:
        
        case 110:
        
        case 111:
        
        case 112:
        
        case 113:
        
        case 114:
        
        case 115:
        
        case 116:
        
        case 117:
        
        case 118:
        
        case 119:
        
        case 120:
        
        case 121:
        
        case 122:
        
        case 123:
        
        case 124:
        
        case 125:
        
        case 126:
        
        case 127:
        
        case 128:
        
        case 129:
        
        case 130:
        
        case 131:
        
        case 132:
        
        case 133:
        
        case 134:
        
        case 135:
        
        case 136:
        
        case 137:
        
        case 138:
        
        case 139:
        
        case 140:
        
        case 141:
        
        case 142:
        
        case 143:
        
        case 144:
        
        case 145:
        
        case 146:
        
        case 147:
        
        case 148:
        
        case 149:
        
        case 150:
        
        case 151:
        
        case 152:
        
        case 153:
        
        case 154:
        
        case 155:
        
        case 156:
        
        case 157:
        
        case 158:
        
        case 159:
        
        case 160:
        
        case 161:
        
        case 162:
        
        case 163:
        
        case 164:
        
        case 165:
        
        case 166:
        
        case 167:
        
        case 168:
        
        case 169:
        
        case 170:
        
        case 171:
        
        case 172:
        
        case 173:
        
        case 174:
        
        case 175:
        
        case 176:
        
        case 177:
        
        case 178:
        
        case 179:
        
        case 180:
        
        case 181:
        
        case 182:
        
        case 183:
        
        case 184:
        
        case 185:
        
        case 186:
        
        case 187:
        
        case 188:
        
        case 189:
        
        case 190:
        
        case 191:
        
        case 192:
        
        case 193:
        
        case 194:
        
        case 195:
        
        case 196:
        
        case 197:
        
        case 198:
        
        case 199:
        
        case 200:
        
        case 201:
        
        case 202:
        
        case 203:
        
        case 204:
        
        case 205:
        
        case 206:
        
        case 207:
        
        case 208:
        
        case 209:
        
        case 210:
        
        case 211:
        
        case 212:
        
        case 213:
        
        case 214:
        
        case 215:
        
        case 216:
        
        case 217:
        
        case 218:
        
        case 219:
        
        case 220:
        
        case 221:
        
        case 222:
        
        case 223:
        
        case 224:
        
        case 225:
        
        case 226:
        
        case 227:
        
        case 228:
        
        case 229:
        
        case 230:
        
        case 231:
        
        case 232:
        
        case 233:
        
        case 234:
        
        case 235:
        
        case 236:
        
        case 237:
        
        case 238:
        
        case 239:
        
        case 240:
        
        case 241:
        
        case 242:
        
        case 243:
        
        case 244:
        
        case 245:
        
        case 246:
        
        case 247:
        
        case 248:
        
        case 249:
        
        case 250:
        
        case 251:
        
        case 252:
        
        case 253:
        
        case 254:
        
        default:
          break;
      } 
      char c = '';
      int j = (paramInt2 & 0xFF) - c;
      if (j < 0)
        j += 256; 
      int k = ((paramInt2 & 0xFFFF) >>> 8) - c;
      if (k < 0)
        k += 256; 
      for (byte b = 0; b < arrayOfChar.length; b++) {
        int m = b % 2;
        if (m == 0) {
          arrayOfChar[b] = (char)(arrayOfChar[b] ^ j);
          j = ((j >>> 3 | j << 5) ^ arrayOfChar[b]) & 0xFF;
        } else {
          arrayOfChar[b] = (char)(arrayOfChar[b] ^ k);
          k = ((k >>> 3 | k << 5) ^ arrayOfChar[b]) & 0xFF;
        } 
      } 
      b[i] = (new String(arrayOfChar)).intern();
    } 
    return b[i];
  }
}


/* Location:              C:\Program Files\BurpSuitePro\burpsuite_pro.jar!\burp\Zllk.class
 * Java compiler version: 21 (65.0)
 * JD-Core Version:       1.1.3
 */