package burp;

import java.math.BigInteger;

class Zlnm extends ClassLoader {
  static String ZL;
  
  static Object Zn;
  
  private static final String[] a;
  
  private static final String[] b;
  
  static void ZF(Object[] paramArrayOfObject, Object paramObject) throws Throwable {}
  
  static boolean ZS(Object[] paramArrayOfObject, Object paramObject) throws Throwable {
    // Byte code:
    //   0: invokestatic ZN : ()Z
    //   3: istore_2
    //   4: new java/io/ByteArrayOutputStream
    //   7: dup
    //   8: invokespecial <init> : ()V
    //   11: astore_3
    //   12: getstatic burp/Ztsu.ZE : Ljava/lang/String;
    //   15: astore #4
    //   17: iconst_0
    //   18: istore #5
    //   20: iload #5
    //   22: aload #4
    //   24: invokevirtual length : ()I
    //   27: if_icmpge -> 57
    //   30: aload_3
    //   31: aload #4
    //   33: iload #5
    //   35: iload #5
    //   37: iconst_2
    //   38: iadd
    //   39: invokevirtual substring : (II)Ljava/lang/String;
    //   42: bipush #16
    //   44: invokestatic parseInt : (Ljava/lang/String;I)I
    //   47: invokevirtual write : (I)V
    //   50: iinc #5, 2
    //   53: iload_2
    //   54: ifne -> 20
    //   57: aload_3
    //   58: invokevirtual toByteArray : ()[B
    //   61: astore #5
    //   63: getstatic burp/Zm8v.ZU : Ljava/lang/Object;
    //   66: checkcast java/math/BigInteger
    //   69: invokevirtual toByteArray : ()[B
    //   72: astore #6
    //   74: sipush #256
    //   77: newarray byte
    //   79: astore #8
    //   81: sipush #256
    //   84: newarray int
    //   86: astore #9
    //   88: sipush #256
    //   91: newarray int
    //   93: astore #10
    //   95: sipush #256
    //   98: newarray int
    //   100: astore #11
    //   102: sipush #256
    //   105: newarray int
    //   107: astore #12
    //   109: bipush #10
    //   111: newarray int
    //   113: astore #13
    //   115: sipush #283
    //   118: istore #14
    //   120: iconst_0
    //   121: istore #16
    //   123: iload #16
    //   125: sipush #256
    //   128: if_icmpge -> 362
    //   131: sipush #-1568
    //   134: sipush #19370
    //   137: invokestatic a : (II)Ljava/lang/String;
    //   140: iload #16
    //   142: iconst_1
    //   143: iushr
    //   144: invokevirtual charAt : (I)C
    //   147: istore #25
    //   149: iload #16
    //   151: iconst_1
    //   152: iand
    //   153: ifne -> 168
    //   156: iload #25
    //   158: bipush #8
    //   160: iushr
    //   161: goto -> 170
    //   164: invokestatic a : (Ljava/lang/Throwable;)Ljava/lang/Throwable;
    //   167: athrow
    //   168: iload #25
    //   170: i2b
    //   171: sipush #255
    //   174: iand
    //   175: istore #15
    //   177: iload #16
    //   179: iconst_1
    //   180: ishl
    //   181: istore #17
    //   183: iload #17
    //   185: sipush #256
    //   188: if_icmplt -> 198
    //   191: iload #17
    //   193: iload #14
    //   195: ixor
    //   196: istore #17
    //   198: iload #17
    //   200: iconst_1
    //   201: ishl
    //   202: istore #18
    //   204: iload #18
    //   206: sipush #256
    //   209: if_icmplt -> 219
    //   212: iload #18
    //   214: iload #14
    //   216: ixor
    //   217: istore #18
    //   219: iload #18
    //   221: iconst_1
    //   222: ishl
    //   223: istore #19
    //   225: iload #19
    //   227: sipush #256
    //   230: if_icmplt -> 240
    //   233: iload #19
    //   235: iload #14
    //   237: ixor
    //   238: istore #19
    //   240: iload #19
    //   242: iload #16
    //   244: ixor
    //   245: istore #20
    //   247: iload #20
    //   249: iload #17
    //   251: ixor
    //   252: istore #21
    //   254: iload #20
    //   256: iload #18
    //   258: ixor
    //   259: istore #22
    //   261: iload #19
    //   263: iload #18
    //   265: ixor
    //   266: iload #17
    //   268: ixor
    //   269: istore #23
    //   271: aload #8
    //   273: iload #16
    //   275: iload #15
    //   277: i2b
    //   278: bastore
    //   279: aload #9
    //   281: iload #15
    //   283: iload #23
    //   285: bipush #24
    //   287: ishl
    //   288: iload #20
    //   290: bipush #16
    //   292: ishl
    //   293: ior
    //   294: iload #22
    //   296: bipush #8
    //   298: ishl
    //   299: ior
    //   300: iload #21
    //   302: ior
    //   303: dup
    //   304: istore #24
    //   306: iastore
    //   307: aload #10
    //   309: iload #15
    //   311: iload #24
    //   313: bipush #8
    //   315: iushr
    //   316: iload #24
    //   318: bipush #24
    //   320: ishl
    //   321: ior
    //   322: iastore
    //   323: aload #11
    //   325: iload #15
    //   327: iload #24
    //   329: bipush #16
    //   331: iushr
    //   332: iload #24
    //   334: bipush #16
    //   336: ishl
    //   337: ior
    //   338: iastore
    //   339: aload #12
    //   341: iload #15
    //   343: iload #24
    //   345: bipush #24
    //   347: iushr
    //   348: iload #24
    //   350: bipush #8
    //   352: ishl
    //   353: ior
    //   354: iastore
    //   355: iinc #16, 1
    //   358: iload_2
    //   359: ifne -> 123
    //   362: iconst_1
    //   363: istore #25
    //   365: aload #13
    //   367: iconst_0
    //   368: iload #25
    //   370: bipush #24
    //   372: ishl
    //   373: iastore
    //   374: iconst_1
    //   375: istore #26
    //   377: iload #26
    //   379: bipush #10
    //   381: if_icmpge -> 422
    //   384: iload #25
    //   386: iconst_1
    //   387: ishl
    //   388: istore #25
    //   390: iload #25
    //   392: sipush #256
    //   395: if_icmplt -> 405
    //   398: iload #25
    //   400: iload #14
    //   402: ixor
    //   403: istore #25
    //   405: aload #13
    //   407: iload #26
    //   409: iload #25
    //   411: bipush #24
    //   413: ishl
    //   414: iastore
    //   415: iinc #26, 1
    //   418: iload_2
    //   419: ifne -> 377
    //   422: iconst_4
    //   423: istore #26
    //   425: iload #26
    //   427: bipush #6
    //   429: iadd
    //   430: istore #27
    //   432: iconst_4
    //   433: iload #27
    //   435: iconst_1
    //   436: iadd
    //   437: imul
    //   438: istore #28
    //   440: iload #28
    //   442: newarray int
    //   444: astore #29
    //   446: iload #28
    //   448: newarray int
    //   450: astore #30
    //   452: iconst_0
    //   453: istore #25
    //   455: iconst_0
    //   456: istore #32
    //   458: iconst_0
    //   459: istore #33
    //   461: iload #32
    //   463: iload #26
    //   465: if_icmpge -> 533
    //   468: aload #29
    //   470: iload #32
    //   472: aload #5
    //   474: iload #33
    //   476: baload
    //   477: bipush #24
    //   479: ishl
    //   480: aload #5
    //   482: iload #33
    //   484: iconst_1
    //   485: iadd
    //   486: baload
    //   487: sipush #255
    //   490: iand
    //   491: bipush #16
    //   493: ishl
    //   494: ior
    //   495: aload #5
    //   497: iload #33
    //   499: iconst_2
    //   500: iadd
    //   501: baload
    //   502: sipush #255
    //   505: iand
    //   506: bipush #8
    //   508: ishl
    //   509: ior
    //   510: aload #5
    //   512: iload #33
    //   514: iconst_3
    //   515: iadd
    //   516: baload
    //   517: sipush #255
    //   520: iand
    //   521: ior
    //   522: iastore
    //   523: iinc #32, 1
    //   526: iinc #33, 4
    //   529: iload_2
    //   530: ifne -> 461
    //   533: iload #26
    //   535: istore #32
    //   537: iconst_0
    //   538: istore #33
    //   540: iload #32
    //   542: iload #28
    //   544: if_icmpge -> 671
    //   547: aload #29
    //   549: iload #32
    //   551: iconst_1
    //   552: isub
    //   553: iaload
    //   554: istore #31
    //   556: iload #33
    //   558: ifne -> 645
    //   561: iload #26
    //   563: istore #33
    //   565: aload #8
    //   567: iload #31
    //   569: bipush #16
    //   571: iushr
    //   572: sipush #255
    //   575: iand
    //   576: baload
    //   577: bipush #24
    //   579: ishl
    //   580: aload #8
    //   582: iload #31
    //   584: bipush #8
    //   586: iushr
    //   587: sipush #255
    //   590: iand
    //   591: baload
    //   592: sipush #255
    //   595: iand
    //   596: bipush #16
    //   598: ishl
    //   599: ior
    //   600: aload #8
    //   602: iload #31
    //   604: sipush #255
    //   607: iand
    //   608: baload
    //   609: sipush #255
    //   612: iand
    //   613: bipush #8
    //   615: ishl
    //   616: ior
    //   617: aload #8
    //   619: iload #31
    //   621: bipush #24
    //   623: iushr
    //   624: baload
    //   625: sipush #255
    //   628: iand
    //   629: ior
    //   630: istore #31
    //   632: iload #31
    //   634: aload #13
    //   636: iload #25
    //   638: iinc #25, 1
    //   641: iaload
    //   642: ixor
    //   643: istore #31
    //   645: aload #29
    //   647: iload #32
    //   649: aload #29
    //   651: iload #32
    //   653: iload #26
    //   655: isub
    //   656: iaload
    //   657: iload #31
    //   659: ixor
    //   660: iastore
    //   661: iinc #32, 1
    //   664: iinc #33, -1
    //   667: iload_2
    //   668: ifne -> 540
    //   671: iconst_0
    //   672: istore #32
    //   674: iconst_4
    //   675: iload #27
    //   677: imul
    //   678: istore #33
    //   680: aload #30
    //   682: iload #32
    //   684: aload #29
    //   686: iload #33
    //   688: iaload
    //   689: iastore
    //   690: aload #30
    //   692: iload #32
    //   694: iconst_1
    //   695: iadd
    //   696: aload #29
    //   698: iload #33
    //   700: iconst_1
    //   701: iadd
    //   702: iaload
    //   703: iastore
    //   704: aload #30
    //   706: iload #32
    //   708: iconst_2
    //   709: iadd
    //   710: aload #29
    //   712: iload #33
    //   714: iconst_2
    //   715: iadd
    //   716: iaload
    //   717: iastore
    //   718: aload #30
    //   720: iload #32
    //   722: iconst_3
    //   723: iadd
    //   724: aload #29
    //   726: iload #33
    //   728: iconst_3
    //   729: iadd
    //   730: iaload
    //   731: iastore
    //   732: iinc #32, 4
    //   735: iinc #33, -4
    //   738: iconst_1
    //   739: istore #35
    //   741: iload #35
    //   743: iload #27
    //   745: if_icmpge -> 1109
    //   748: aload #29
    //   750: iload #33
    //   752: iaload
    //   753: istore #34
    //   755: aload #30
    //   757: iload #32
    //   759: aload #9
    //   761: aload #8
    //   763: iload #34
    //   765: bipush #24
    //   767: iushr
    //   768: baload
    //   769: sipush #255
    //   772: iand
    //   773: iaload
    //   774: aload #10
    //   776: aload #8
    //   778: iload #34
    //   780: bipush #16
    //   782: iushr
    //   783: sipush #255
    //   786: iand
    //   787: baload
    //   788: sipush #255
    //   791: iand
    //   792: iaload
    //   793: ixor
    //   794: aload #11
    //   796: aload #8
    //   798: iload #34
    //   800: bipush #8
    //   802: iushr
    //   803: sipush #255
    //   806: iand
    //   807: baload
    //   808: sipush #255
    //   811: iand
    //   812: iaload
    //   813: ixor
    //   814: aload #12
    //   816: aload #8
    //   818: iload #34
    //   820: sipush #255
    //   823: iand
    //   824: baload
    //   825: sipush #255
    //   828: iand
    //   829: iaload
    //   830: ixor
    //   831: iastore
    //   832: aload #29
    //   834: iload #33
    //   836: iconst_1
    //   837: iadd
    //   838: iaload
    //   839: istore #34
    //   841: aload #30
    //   843: iload #32
    //   845: iconst_1
    //   846: iadd
    //   847: aload #9
    //   849: aload #8
    //   851: iload #34
    //   853: bipush #24
    //   855: iushr
    //   856: baload
    //   857: sipush #255
    //   860: iand
    //   861: iaload
    //   862: aload #10
    //   864: aload #8
    //   866: iload #34
    //   868: bipush #16
    //   870: iushr
    //   871: sipush #255
    //   874: iand
    //   875: baload
    //   876: sipush #255
    //   879: iand
    //   880: iaload
    //   881: ixor
    //   882: aload #11
    //   884: aload #8
    //   886: iload #34
    //   888: bipush #8
    //   890: iushr
    //   891: sipush #255
    //   894: iand
    //   895: baload
    //   896: sipush #255
    //   899: iand
    //   900: iaload
    //   901: ixor
    //   902: aload #12
    //   904: aload #8
    //   906: iload #34
    //   908: sipush #255
    //   911: iand
    //   912: baload
    //   913: sipush #255
    //   916: iand
    //   917: iaload
    //   918: ixor
    //   919: iastore
    //   920: aload #29
    //   922: iload #33
    //   924: iconst_2
    //   925: iadd
    //   926: iaload
    //   927: istore #34
    //   929: aload #30
    //   931: iload #32
    //   933: iconst_2
    //   934: iadd
    //   935: aload #9
    //   937: aload #8
    //   939: iload #34
    //   941: bipush #24
    //   943: iushr
    //   944: baload
    //   945: sipush #255
    //   948: iand
    //   949: iaload
    //   950: aload #10
    //   952: aload #8
    //   954: iload #34
    //   956: bipush #16
    //   958: iushr
    //   959: sipush #255
    //   962: iand
    //   963: baload
    //   964: sipush #255
    //   967: iand
    //   968: iaload
    //   969: ixor
    //   970: aload #11
    //   972: aload #8
    //   974: iload #34
    //   976: bipush #8
    //   978: iushr
    //   979: sipush #255
    //   982: iand
    //   983: baload
    //   984: sipush #255
    //   987: iand
    //   988: iaload
    //   989: ixor
    //   990: aload #12
    //   992: aload #8
    //   994: iload #34
    //   996: sipush #255
    //   999: iand
    //   1000: baload
    //   1001: sipush #255
    //   1004: iand
    //   1005: iaload
    //   1006: ixor
    //   1007: iastore
    //   1008: aload #29
    //   1010: iload #33
    //   1012: iconst_3
    //   1013: iadd
    //   1014: iaload
    //   1015: istore #34
    //   1017: aload #30
    //   1019: iload #32
    //   1021: iconst_3
    //   1022: iadd
    //   1023: aload #9
    //   1025: aload #8
    //   1027: iload #34
    //   1029: bipush #24
    //   1031: iushr
    //   1032: baload
    //   1033: sipush #255
    //   1036: iand
    //   1037: iaload
    //   1038: aload #10
    //   1040: aload #8
    //   1042: iload #34
    //   1044: bipush #16
    //   1046: iushr
    //   1047: sipush #255
    //   1050: iand
    //   1051: baload
    //   1052: sipush #255
    //   1055: iand
    //   1056: iaload
    //   1057: ixor
    //   1058: aload #11
    //   1060: aload #8
    //   1062: iload #34
    //   1064: bipush #8
    //   1066: iushr
    //   1067: sipush #255
    //   1070: iand
    //   1071: baload
    //   1072: sipush #255
    //   1075: iand
    //   1076: iaload
    //   1077: ixor
    //   1078: aload #12
    //   1080: aload #8
    //   1082: iload #34
    //   1084: sipush #255
    //   1087: iand
    //   1088: baload
    //   1089: sipush #255
    //   1092: iand
    //   1093: iaload
    //   1094: ixor
    //   1095: iastore
    //   1096: iinc #32, 4
    //   1099: iinc #33, -4
    //   1102: iinc #35, 1
    //   1105: iload_2
    //   1106: ifne -> 741
    //   1109: aload #30
    //   1111: iload #32
    //   1113: aload #29
    //   1115: iload #33
    //   1117: iaload
    //   1118: iastore
    //   1119: aload #30
    //   1121: iload #32
    //   1123: iconst_1
    //   1124: iadd
    //   1125: aload #29
    //   1127: iload #33
    //   1129: iconst_1
    //   1130: iadd
    //   1131: iaload
    //   1132: iastore
    //   1133: aload #30
    //   1135: iload #32
    //   1137: iconst_2
    //   1138: iadd
    //   1139: aload #29
    //   1141: iload #33
    //   1143: iconst_2
    //   1144: iadd
    //   1145: iaload
    //   1146: iastore
    //   1147: aload #30
    //   1149: iload #32
    //   1151: iconst_3
    //   1152: iadd
    //   1153: aload #29
    //   1155: iload #33
    //   1157: iconst_3
    //   1158: iadd
    //   1159: iaload
    //   1160: iastore
    //   1161: iconst_0
    //   1162: newarray byte
    //   1164: astore #35
    //   1166: aload #6
    //   1168: arraylength
    //   1169: bipush #16
    //   1171: irem
    //   1172: ifeq -> 1196
    //   1175: new java/lang/Exception
    //   1178: dup
    //   1179: sipush #-1554
    //   1182: sipush #-2966
    //   1185: invokestatic a : (II)Ljava/lang/String;
    //   1188: invokespecial <init> : (Ljava/lang/String;)V
    //   1191: athrow
    //   1192: invokestatic a : (Ljava/lang/Throwable;)Ljava/lang/Throwable;
    //   1195: athrow
    //   1196: bipush #10
    //   1198: istore #36
    //   1200: sipush #-1557
    //   1203: sipush #256
    //   1206: newarray byte
    //   1208: astore #37
    //   1210: sipush #-3898
    //   1213: sipush #256
    //   1216: newarray int
    //   1218: astore #38
    //   1220: sipush #256
    //   1223: newarray int
    //   1225: astore #39
    //   1227: sipush #256
    //   1230: newarray int
    //   1232: astore #40
    //   1234: sipush #256
    //   1237: newarray int
    //   1239: astore #41
    //   1241: sipush #283
    //   1244: istore #14
    //   1246: invokestatic a : (II)Ljava/lang/String;
    //   1249: astore #42
    //   1251: iconst_0
    //   1252: istore #16
    //   1254: iload #16
    //   1256: sipush #256
    //   1259: if_icmpge -> 1486
    //   1262: aload #42
    //   1264: iload #16
    //   1266: iconst_1
    //   1267: iushr
    //   1268: invokevirtual charAt : (I)C
    //   1271: istore #43
    //   1273: iload #16
    //   1275: iconst_1
    //   1276: iand
    //   1277: ifne -> 1292
    //   1280: iload #43
    //   1282: bipush #8
    //   1284: iushr
    //   1285: goto -> 1294
    //   1288: invokestatic a : (Ljava/lang/Throwable;)Ljava/lang/Throwable;
    //   1291: athrow
    //   1292: iload #43
    //   1294: i2b
    //   1295: sipush #255
    //   1298: iand
    //   1299: istore #15
    //   1301: iload #16
    //   1303: iconst_1
    //   1304: ishl
    //   1305: istore #17
    //   1307: iload #17
    //   1309: sipush #256
    //   1312: if_icmplt -> 1322
    //   1315: iload #17
    //   1317: iload #14
    //   1319: ixor
    //   1320: istore #17
    //   1322: iload #17
    //   1324: iconst_1
    //   1325: ishl
    //   1326: istore #18
    //   1328: iload #18
    //   1330: sipush #256
    //   1333: if_icmplt -> 1343
    //   1336: iload #18
    //   1338: iload #14
    //   1340: ixor
    //   1341: istore #18
    //   1343: iload #18
    //   1345: iconst_1
    //   1346: ishl
    //   1347: istore #19
    //   1349: iload #19
    //   1351: sipush #256
    //   1354: if_icmplt -> 1364
    //   1357: iload #19
    //   1359: iload #14
    //   1361: ixor
    //   1362: istore #19
    //   1364: iload #19
    //   1366: iload #16
    //   1368: ixor
    //   1369: istore #20
    //   1371: iload #20
    //   1373: iload #17
    //   1375: ixor
    //   1376: istore #21
    //   1378: iload #20
    //   1380: iload #18
    //   1382: ixor
    //   1383: istore #22
    //   1385: iload #19
    //   1387: iload #18
    //   1389: ixor
    //   1390: iload #17
    //   1392: ixor
    //   1393: istore #23
    //   1395: aload #37
    //   1397: iload #15
    //   1399: iload #16
    //   1401: i2b
    //   1402: bastore
    //   1403: aload #38
    //   1405: iload #15
    //   1407: iload #23
    //   1409: bipush #24
    //   1411: ishl
    //   1412: iload #20
    //   1414: bipush #16
    //   1416: ishl
    //   1417: ior
    //   1418: iload #22
    //   1420: bipush #8
    //   1422: ishl
    //   1423: ior
    //   1424: iload #21
    //   1426: ior
    //   1427: dup
    //   1428: istore #24
    //   1430: iastore
    //   1431: aload #39
    //   1433: iload #15
    //   1435: iload #24
    //   1437: bipush #8
    //   1439: iushr
    //   1440: iload #24
    //   1442: bipush #24
    //   1444: ishl
    //   1445: ior
    //   1446: iastore
    //   1447: aload #40
    //   1449: iload #15
    //   1451: iload #24
    //   1453: bipush #16
    //   1455: iushr
    //   1456: iload #24
    //   1458: bipush #16
    //   1460: ishl
    //   1461: ior
    //   1462: iastore
    //   1463: aload #41
    //   1465: iload #15
    //   1467: iload #24
    //   1469: bipush #24
    //   1471: iushr
    //   1472: iload #24
    //   1474: bipush #8
    //   1476: ishl
    //   1477: ior
    //   1478: iastore
    //   1479: iinc #16, 1
    //   1482: iload_2
    //   1483: ifne -> 1254
    //   1486: aload #6
    //   1488: arraylength
    //   1489: newarray byte
    //   1491: astore #43
    //   1493: iconst_0
    //   1494: istore #44
    //   1496: iload #44
    //   1498: aload #6
    //   1500: arraylength
    //   1501: bipush #16
    //   1503: idiv
    //   1504: if_icmpge -> 2418
    //   1507: bipush #16
    //   1509: newarray byte
    //   1511: astore #45
    //   1513: bipush #16
    //   1515: newarray byte
    //   1517: astore #46
    //   1519: iconst_0
    //   1520: istore #47
    //   1522: iload #47
    //   1524: bipush #16
    //   1526: if_icmpge -> 1552
    //   1529: aload #45
    //   1531: iload #47
    //   1533: aload #6
    //   1535: iload #47
    //   1537: iload #44
    //   1539: bipush #16
    //   1541: imul
    //   1542: iadd
    //   1543: baload
    //   1544: bastore
    //   1545: iinc #47, 1
    //   1548: iload_2
    //   1549: ifne -> 1522
    //   1552: iconst_0
    //   1553: istore #47
    //   1555: aload #45
    //   1557: iconst_0
    //   1558: baload
    //   1559: bipush #24
    //   1561: ishl
    //   1562: aload #45
    //   1564: iconst_1
    //   1565: baload
    //   1566: sipush #255
    //   1569: iand
    //   1570: bipush #16
    //   1572: ishl
    //   1573: ior
    //   1574: aload #45
    //   1576: iconst_2
    //   1577: baload
    //   1578: sipush #255
    //   1581: iand
    //   1582: bipush #8
    //   1584: ishl
    //   1585: ior
    //   1586: aload #45
    //   1588: iconst_3
    //   1589: baload
    //   1590: sipush #255
    //   1593: iand
    //   1594: ior
    //   1595: aload #30
    //   1597: iconst_0
    //   1598: iaload
    //   1599: ixor
    //   1600: istore #49
    //   1602: aload #45
    //   1604: iconst_4
    //   1605: baload
    //   1606: bipush #24
    //   1608: ishl
    //   1609: aload #45
    //   1611: iconst_5
    //   1612: baload
    //   1613: sipush #255
    //   1616: iand
    //   1617: bipush #16
    //   1619: ishl
    //   1620: ior
    //   1621: aload #45
    //   1623: bipush #6
    //   1625: baload
    //   1626: sipush #255
    //   1629: iand
    //   1630: bipush #8
    //   1632: ishl
    //   1633: ior
    //   1634: aload #45
    //   1636: bipush #7
    //   1638: baload
    //   1639: sipush #255
    //   1642: iand
    //   1643: ior
    //   1644: aload #30
    //   1646: iconst_1
    //   1647: iaload
    //   1648: ixor
    //   1649: istore #50
    //   1651: aload #45
    //   1653: bipush #8
    //   1655: baload
    //   1656: bipush #24
    //   1658: ishl
    //   1659: aload #45
    //   1661: bipush #9
    //   1663: baload
    //   1664: sipush #255
    //   1667: iand
    //   1668: bipush #16
    //   1670: ishl
    //   1671: ior
    //   1672: aload #45
    //   1674: bipush #10
    //   1676: baload
    //   1677: sipush #255
    //   1680: iand
    //   1681: bipush #8
    //   1683: ishl
    //   1684: ior
    //   1685: aload #45
    //   1687: bipush #11
    //   1689: baload
    //   1690: sipush #255
    //   1693: iand
    //   1694: ior
    //   1695: aload #30
    //   1697: iconst_2
    //   1698: iaload
    //   1699: ixor
    //   1700: istore #51
    //   1702: aload #45
    //   1704: bipush #12
    //   1706: baload
    //   1707: bipush #24
    //   1709: ishl
    //   1710: aload #45
    //   1712: bipush #13
    //   1714: baload
    //   1715: sipush #255
    //   1718: iand
    //   1719: bipush #16
    //   1721: ishl
    //   1722: ior
    //   1723: aload #45
    //   1725: bipush #14
    //   1727: baload
    //   1728: sipush #255
    //   1731: iand
    //   1732: bipush #8
    //   1734: ishl
    //   1735: ior
    //   1736: aload #45
    //   1738: bipush #15
    //   1740: baload
    //   1741: sipush #255
    //   1744: iand
    //   1745: ior
    //   1746: aload #30
    //   1748: iconst_3
    //   1749: iaload
    //   1750: ixor
    //   1751: istore #52
    //   1753: iconst_1
    //   1754: istore #53
    //   1756: iload #53
    //   1758: iload #36
    //   1760: if_icmpge -> 2003
    //   1763: iinc #47, 4
    //   1766: aload #38
    //   1768: iload #49
    //   1770: bipush #24
    //   1772: iushr
    //   1773: iaload
    //   1774: aload #39
    //   1776: iload #52
    //   1778: bipush #16
    //   1780: iushr
    //   1781: sipush #255
    //   1784: iand
    //   1785: iaload
    //   1786: ixor
    //   1787: aload #40
    //   1789: iload #51
    //   1791: bipush #8
    //   1793: iushr
    //   1794: sipush #255
    //   1797: iand
    //   1798: iaload
    //   1799: ixor
    //   1800: aload #41
    //   1802: iload #50
    //   1804: sipush #255
    //   1807: iand
    //   1808: iaload
    //   1809: ixor
    //   1810: aload #30
    //   1812: iload #47
    //   1814: iaload
    //   1815: ixor
    //   1816: istore #54
    //   1818: aload #38
    //   1820: iload #50
    //   1822: bipush #24
    //   1824: iushr
    //   1825: iaload
    //   1826: aload #39
    //   1828: iload #49
    //   1830: bipush #16
    //   1832: iushr
    //   1833: sipush #255
    //   1836: iand
    //   1837: iaload
    //   1838: ixor
    //   1839: aload #40
    //   1841: iload #52
    //   1843: bipush #8
    //   1845: iushr
    //   1846: sipush #255
    //   1849: iand
    //   1850: iaload
    //   1851: ixor
    //   1852: aload #41
    //   1854: iload #51
    //   1856: sipush #255
    //   1859: iand
    //   1860: iaload
    //   1861: ixor
    //   1862: aload #30
    //   1864: iload #47
    //   1866: iconst_1
    //   1867: iadd
    //   1868: iaload
    //   1869: ixor
    //   1870: istore #55
    //   1872: aload #38
    //   1874: iload #51
    //   1876: bipush #24
    //   1878: iushr
    //   1879: iaload
    //   1880: aload #39
    //   1882: iload #50
    //   1884: bipush #16
    //   1886: iushr
    //   1887: sipush #255
    //   1890: iand
    //   1891: iaload
    //   1892: ixor
    //   1893: aload #40
    //   1895: iload #49
    //   1897: bipush #8
    //   1899: iushr
    //   1900: sipush #255
    //   1903: iand
    //   1904: iaload
    //   1905: ixor
    //   1906: aload #41
    //   1908: iload #52
    //   1910: sipush #255
    //   1913: iand
    //   1914: iaload
    //   1915: ixor
    //   1916: aload #30
    //   1918: iload #47
    //   1920: iconst_2
    //   1921: iadd
    //   1922: iaload
    //   1923: ixor
    //   1924: istore #56
    //   1926: aload #38
    //   1928: iload #52
    //   1930: bipush #24
    //   1932: iushr
    //   1933: iaload
    //   1934: aload #39
    //   1936: iload #51
    //   1938: bipush #16
    //   1940: iushr
    //   1941: sipush #255
    //   1944: iand
    //   1945: iaload
    //   1946: ixor
    //   1947: aload #40
    //   1949: iload #50
    //   1951: bipush #8
    //   1953: iushr
    //   1954: sipush #255
    //   1957: iand
    //   1958: iaload
    //   1959: ixor
    //   1960: aload #41
    //   1962: iload #49
    //   1964: sipush #255
    //   1967: iand
    //   1968: iaload
    //   1969: ixor
    //   1970: aload #30
    //   1972: iload #47
    //   1974: iconst_3
    //   1975: iadd
    //   1976: iaload
    //   1977: ixor
    //   1978: istore #57
    //   1980: iload #54
    //   1982: istore #49
    //   1984: iload #55
    //   1986: istore #50
    //   1988: iload #56
    //   1990: istore #51
    //   1992: iload #57
    //   1994: istore #52
    //   1996: iinc #53, 1
    //   1999: iload_2
    //   2000: ifne -> 1756
    //   2003: iinc #47, 4
    //   2006: aload #30
    //   2008: iload #47
    //   2010: iaload
    //   2011: istore #48
    //   2013: aload #46
    //   2015: iconst_0
    //   2016: aload #37
    //   2018: iload #49
    //   2020: bipush #24
    //   2022: iushr
    //   2023: baload
    //   2024: iload #48
    //   2026: bipush #24
    //   2028: iushr
    //   2029: ixor
    //   2030: i2b
    //   2031: bastore
    //   2032: aload #46
    //   2034: iconst_1
    //   2035: aload #37
    //   2037: iload #52
    //   2039: bipush #16
    //   2041: iushr
    //   2042: sipush #255
    //   2045: iand
    //   2046: baload
    //   2047: iload #48
    //   2049: bipush #16
    //   2051: iushr
    //   2052: ixor
    //   2053: i2b
    //   2054: bastore
    //   2055: aload #46
    //   2057: iconst_2
    //   2058: aload #37
    //   2060: iload #51
    //   2062: bipush #8
    //   2064: iushr
    //   2065: sipush #255
    //   2068: iand
    //   2069: baload
    //   2070: iload #48
    //   2072: bipush #8
    //   2074: iushr
    //   2075: ixor
    //   2076: i2b
    //   2077: bastore
    //   2078: aload #46
    //   2080: iconst_3
    //   2081: aload #37
    //   2083: iload #50
    //   2085: sipush #255
    //   2088: iand
    //   2089: baload
    //   2090: iload #48
    //   2092: ixor
    //   2093: i2b
    //   2094: bastore
    //   2095: aload #30
    //   2097: iload #47
    //   2099: iconst_1
    //   2100: iadd
    //   2101: iaload
    //   2102: istore #48
    //   2104: aload #46
    //   2106: iconst_4
    //   2107: aload #37
    //   2109: iload #50
    //   2111: bipush #24
    //   2113: iushr
    //   2114: baload
    //   2115: iload #48
    //   2117: bipush #24
    //   2119: iushr
    //   2120: ixor
    //   2121: i2b
    //   2122: bastore
    //   2123: aload #46
    //   2125: iconst_5
    //   2126: aload #37
    //   2128: iload #49
    //   2130: bipush #16
    //   2132: iushr
    //   2133: sipush #255
    //   2136: iand
    //   2137: baload
    //   2138: iload #48
    //   2140: bipush #16
    //   2142: iushr
    //   2143: ixor
    //   2144: i2b
    //   2145: bastore
    //   2146: aload #46
    //   2148: bipush #6
    //   2150: aload #37
    //   2152: iload #52
    //   2154: bipush #8
    //   2156: iushr
    //   2157: sipush #255
    //   2160: iand
    //   2161: baload
    //   2162: iload #48
    //   2164: bipush #8
    //   2166: iushr
    //   2167: ixor
    //   2168: i2b
    //   2169: bastore
    //   2170: aload #46
    //   2172: bipush #7
    //   2174: aload #37
    //   2176: iload #51
    //   2178: sipush #255
    //   2181: iand
    //   2182: baload
    //   2183: iload #48
    //   2185: ixor
    //   2186: i2b
    //   2187: bastore
    //   2188: aload #30
    //   2190: iload #47
    //   2192: iconst_2
    //   2193: iadd
    //   2194: iaload
    //   2195: istore #48
    //   2197: aload #46
    //   2199: bipush #8
    //   2201: aload #37
    //   2203: iload #51
    //   2205: bipush #24
    //   2207: iushr
    //   2208: baload
    //   2209: iload #48
    //   2211: bipush #24
    //   2213: iushr
    //   2214: ixor
    //   2215: i2b
    //   2216: bastore
    //   2217: aload #46
    //   2219: bipush #9
    //   2221: aload #37
    //   2223: iload #50
    //   2225: bipush #16
    //   2227: iushr
    //   2228: sipush #255
    //   2231: iand
    //   2232: baload
    //   2233: iload #48
    //   2235: bipush #16
    //   2237: iushr
    //   2238: ixor
    //   2239: i2b
    //   2240: bastore
    //   2241: aload #46
    //   2243: bipush #10
    //   2245: aload #37
    //   2247: iload #49
    //   2249: bipush #8
    //   2251: iushr
    //   2252: sipush #255
    //   2255: iand
    //   2256: baload
    //   2257: iload #48
    //   2259: bipush #8
    //   2261: iushr
    //   2262: ixor
    //   2263: i2b
    //   2264: bastore
    //   2265: aload #46
    //   2267: bipush #11
    //   2269: aload #37
    //   2271: iload #52
    //   2273: sipush #255
    //   2276: iand
    //   2277: baload
    //   2278: iload #48
    //   2280: ixor
    //   2281: i2b
    //   2282: bastore
    //   2283: aload #30
    //   2285: iload #47
    //   2287: iconst_3
    //   2288: iadd
    //   2289: iaload
    //   2290: istore #48
    //   2292: aload #46
    //   2294: bipush #12
    //   2296: aload #37
    //   2298: iload #52
    //   2300: bipush #24
    //   2302: iushr
    //   2303: baload
    //   2304: iload #48
    //   2306: bipush #24
    //   2308: iushr
    //   2309: ixor
    //   2310: i2b
    //   2311: bastore
    //   2312: aload #46
    //   2314: bipush #13
    //   2316: aload #37
    //   2318: iload #51
    //   2320: bipush #16
    //   2322: iushr
    //   2323: sipush #255
    //   2326: iand
    //   2327: baload
    //   2328: iload #48
    //   2330: bipush #16
    //   2332: iushr
    //   2333: ixor
    //   2334: i2b
    //   2335: bastore
    //   2336: aload #46
    //   2338: bipush #14
    //   2340: aload #37
    //   2342: iload #50
    //   2344: bipush #8
    //   2346: iushr
    //   2347: sipush #255
    //   2350: iand
    //   2351: baload
    //   2352: iload #48
    //   2354: bipush #8
    //   2356: iushr
    //   2357: ixor
    //   2358: i2b
    //   2359: bastore
    //   2360: aload #46
    //   2362: bipush #15
    //   2364: aload #37
    //   2366: iload #49
    //   2368: sipush #255
    //   2371: iand
    //   2372: baload
    //   2373: iload #48
    //   2375: ixor
    //   2376: i2b
    //   2377: bastore
    //   2378: iconst_0
    //   2379: istore #53
    //   2381: iload #53
    //   2383: bipush #16
    //   2385: if_icmpge -> 2411
    //   2388: aload #43
    //   2390: iload #53
    //   2392: iload #44
    //   2394: bipush #16
    //   2396: imul
    //   2397: iadd
    //   2398: aload #46
    //   2400: iload #53
    //   2402: baload
    //   2403: bastore
    //   2404: iinc #53, 1
    //   2407: iload_2
    //   2408: ifne -> 2381
    //   2411: iinc #44, 1
    //   2414: iload_2
    //   2415: ifne -> 1496
    //   2418: aload #43
    //   2420: arraylength
    //   2421: ifle -> 2502
    //   2424: aload #43
    //   2426: aload #43
    //   2428: arraylength
    //   2429: iconst_1
    //   2430: isub
    //   2431: baload
    //   2432: istore #44
    //   2434: iload #44
    //   2436: bipush #16
    //   2438: if_icmple -> 2449
    //   2441: aload #43
    //   2443: astore #35
    //   2445: iload_2
    //   2446: ifne -> 2502
    //   2449: aload #43
    //   2451: arraylength
    //   2452: iload #44
    //   2454: isub
    //   2455: newarray byte
    //   2457: astore #35
    //   2459: iconst_0
    //   2460: istore #45
    //   2462: iload #45
    //   2464: aload #35
    //   2466: arraylength
    //   2467: if_icmpge -> 2502
    //   2470: iload #45
    //   2472: aload #43
    //   2474: arraylength
    //   2475: if_icmpge -> 2502
    //   2478: aload #35
    //   2480: iload #45
    //   2482: aload #43
    //   2484: iload #45
    //   2486: baload
    //   2487: bastore
    //   2488: iinc #45, 1
    //   2491: iload_2
    //   2492: ifne -> 2462
    //   2495: goto -> 2502
    //   2498: invokestatic a : (Ljava/lang/Throwable;)Ljava/lang/Throwable;
    //   2501: athrow
    //   2502: aload #35
    //   2504: astore #7
    //   2506: new java/math/BigInteger
    //   2509: dup
    //   2510: aload #7
    //   2512: invokespecial <init> : ([B)V
    //   2515: invokevirtual abs : ()Ljava/math/BigInteger;
    //   2518: putstatic burp/Zgzv.Zb : Ljava/lang/Object;
    //   2521: new java/lang/StringBuilder
    //   2524: dup
    //   2525: invokespecial <init> : ()V
    //   2528: astore_3
    //   2529: iconst_0
    //   2530: istore #4
    //   2532: iload #4
    //   2534: bipush #32
    //   2536: if_icmpge -> 3871
    //   2539: iload #4
    //   2541: tableswitch default -> 3864, 0 -> 2684, 1 -> 2721, 2 -> 2758, 3 -> 2795, 4 -> 2832, 5 -> 2869, 6 -> 2906, 7 -> 2943, 8 -> 2980, 9 -> 3017, 10 -> 3054, 11 -> 3091, 12 -> 3128, 13 -> 3165, 14 -> 3202, 15 -> 3239, 16 -> 3276, 17 -> 3313, 18 -> 3350, 19 -> 3387, 20 -> 3424, 21 -> 3461, 22 -> 3498, 23 -> 3535, 24 -> 3572, 25 -> 3609, 26 -> 3646, 27 -> 3683, 28 -> 3720, 29 -> 3757, 30 -> 3794, 31 -> 3831
    //   2684: aload_3
    //   2685: getstatic burp/Zeb7.ZH : Ljava/lang/String;
    //   2688: getstatic burp/Zmr7.ZO : Ljava/lang/Object;
    //   2691: checkcast java/math/BigInteger
    //   2694: invokevirtual intValue : ()I
    //   2697: bipush #32
    //   2699: irem
    //   2700: invokestatic abs : (I)I
    //   2703: invokevirtual charAt : (I)C
    //   2706: invokevirtual append : (C)Ljava/lang/StringBuilder;
    //   2709: pop
    //   2710: iload_2
    //   2711: ifne -> 3864
    //   2714: goto -> 2721
    //   2717: invokestatic a : (Ljava/lang/Throwable;)Ljava/lang/Throwable;
    //   2720: athrow
    //   2721: aload_3
    //   2722: getstatic burp/Zzmw.Zd : Ljava/lang/String;
    //   2725: getstatic burp/Zlo5.Zf : Ljava/lang/Object;
    //   2728: checkcast java/math/BigInteger
    //   2731: invokevirtual intValue : ()I
    //   2734: bipush #32
    //   2736: irem
    //   2737: invokestatic abs : (I)I
    //   2740: invokevirtual charAt : (I)C
    //   2743: invokevirtual append : (C)Ljava/lang/StringBuilder;
    //   2746: pop
    //   2747: iload_2
    //   2748: ifne -> 3864
    //   2751: goto -> 2758
    //   2754: invokestatic a : (Ljava/lang/Throwable;)Ljava/lang/Throwable;
    //   2757: athrow
    //   2758: aload_3
    //   2759: getstatic burp/Zkjr.Zg : Ljava/lang/String;
    //   2762: getstatic burp/Zm8w.Zz : Ljava/lang/Object;
    //   2765: checkcast java/math/BigInteger
    //   2768: invokevirtual intValue : ()I
    //   2771: bipush #32
    //   2773: irem
    //   2774: invokestatic abs : (I)I
    //   2777: invokevirtual charAt : (I)C
    //   2780: invokevirtual append : (C)Ljava/lang/StringBuilder;
    //   2783: pop
    //   2784: iload_2
    //   2785: ifne -> 3864
    //   2788: goto -> 2795
    //   2791: invokestatic a : (Ljava/lang/Throwable;)Ljava/lang/Throwable;
    //   2794: athrow
    //   2795: aload_3
    //   2796: getstatic burp/Zg_5.ZG : Ljava/lang/String;
    //   2799: getstatic burp/Ze_t.Za : Ljava/lang/Object;
    //   2802: checkcast java/math/BigInteger
    //   2805: invokevirtual intValue : ()I
    //   2808: bipush #32
    //   2810: irem
    //   2811: invokestatic abs : (I)I
    //   2814: invokevirtual charAt : (I)C
    //   2817: invokevirtual append : (C)Ljava/lang/StringBuilder;
    //   2820: pop
    //   2821: iload_2
    //   2822: ifne -> 3864
    //   2825: goto -> 2832
    //   2828: invokestatic a : (Ljava/lang/Throwable;)Ljava/lang/Throwable;
    //   2831: athrow
    //   2832: aload_3
    //   2833: getstatic burp/Ze5f.Zt : Ljava/lang/String;
    //   2836: getstatic burp/Zz75.ZX : Ljava/lang/Object;
    //   2839: checkcast java/math/BigInteger
    //   2842: invokevirtual intValue : ()I
    //   2845: bipush #32
    //   2847: irem
    //   2848: invokestatic abs : (I)I
    //   2851: invokevirtual charAt : (I)C
    //   2854: invokevirtual append : (C)Ljava/lang/StringBuilder;
    //   2857: pop
    //   2858: iload_2
    //   2859: ifne -> 3864
    //   2862: goto -> 2869
    //   2865: invokestatic a : (Ljava/lang/Throwable;)Ljava/lang/Throwable;
    //   2868: athrow
    //   2869: aload_3
    //   2870: getstatic burp/Zli5.Zq : Ljava/lang/String;
    //   2873: getstatic burp/Zv8c.Zx : Ljava/lang/Object;
    //   2876: checkcast java/math/BigInteger
    //   2879: invokevirtual intValue : ()I
    //   2882: bipush #32
    //   2884: irem
    //   2885: invokestatic abs : (I)I
    //   2888: invokevirtual charAt : (I)C
    //   2891: invokevirtual append : (C)Ljava/lang/StringBuilder;
    //   2894: pop
    //   2895: iload_2
    //   2896: ifne -> 3864
    //   2899: goto -> 2906
    //   2902: invokestatic a : (Ljava/lang/Throwable;)Ljava/lang/Throwable;
    //   2905: athrow
    //   2906: aload_3
    //   2907: getstatic burp/Ztye.ZR : Ljava/lang/String;
    //   2910: getstatic burp/Zt3f.Zp : Ljava/lang/Object;
    //   2913: checkcast java/math/BigInteger
    //   2916: invokevirtual intValue : ()I
    //   2919: bipush #32
    //   2921: irem
    //   2922: invokestatic abs : (I)I
    //   2925: invokevirtual charAt : (I)C
    //   2928: invokevirtual append : (C)Ljava/lang/StringBuilder;
    //   2931: pop
    //   2932: iload_2
    //   2933: ifne -> 3864
    //   2936: goto -> 2943
    //   2939: invokestatic a : (Ljava/lang/Throwable;)Ljava/lang/Throwable;
    //   2942: athrow
    //   2943: aload_3
    //   2944: getstatic burp/Zex.Zn : Ljava/lang/String;
    //   2947: getstatic burp/Zm3p.Zz : Ljava/lang/Object;
    //   2950: checkcast java/math/BigInteger
    //   2953: invokevirtual intValue : ()I
    //   2956: bipush #32
    //   2958: irem
    //   2959: invokestatic abs : (I)I
    //   2962: invokevirtual charAt : (I)C
    //   2965: invokevirtual append : (C)Ljava/lang/StringBuilder;
    //   2968: pop
    //   2969: iload_2
    //   2970: ifne -> 3864
    //   2973: goto -> 2980
    //   2976: invokestatic a : (Ljava/lang/Throwable;)Ljava/lang/Throwable;
    //   2979: athrow
    //   2980: aload_3
    //   2981: getstatic burp/Zvo3.Z_ : Ljava/lang/String;
    //   2984: getstatic burp/Zvo3.Ze : Ljava/lang/Object;
    //   2987: checkcast java/math/BigInteger
    //   2990: invokevirtual intValue : ()I
    //   2993: bipush #32
    //   2995: irem
    //   2996: invokestatic abs : (I)I
    //   2999: invokevirtual charAt : (I)C
    //   3002: invokevirtual append : (C)Ljava/lang/StringBuilder;
    //   3005: pop
    //   3006: iload_2
    //   3007: ifne -> 3864
    //   3010: goto -> 3017
    //   3013: invokestatic a : (Ljava/lang/Throwable;)Ljava/lang/Throwable;
    //   3016: athrow
    //   3017: aload_3
    //   3018: getstatic burp/Ze5f.Zt : Ljava/lang/String;
    //   3021: getstatic burp/Ztj5.Zj : Ljava/lang/Object;
    //   3024: checkcast java/math/BigInteger
    //   3027: invokevirtual intValue : ()I
    //   3030: bipush #32
    //   3032: irem
    //   3033: invokestatic abs : (I)I
    //   3036: invokevirtual charAt : (I)C
    //   3039: invokevirtual append : (C)Ljava/lang/StringBuilder;
    //   3042: pop
    //   3043: iload_2
    //   3044: ifne -> 3864
    //   3047: goto -> 3054
    //   3050: invokestatic a : (Ljava/lang/Throwable;)Ljava/lang/Throwable;
    //   3053: athrow
    //   3054: aload_3
    //   3055: getstatic burp/Zxzz.ZT : Ljava/lang/String;
    //   3058: getstatic burp/Ze5t.Zc : Ljava/lang/Object;
    //   3061: checkcast java/math/BigInteger
    //   3064: invokevirtual intValue : ()I
    //   3067: bipush #32
    //   3069: irem
    //   3070: invokestatic abs : (I)I
    //   3073: invokevirtual charAt : (I)C
    //   3076: invokevirtual append : (C)Ljava/lang/StringBuilder;
    //   3079: pop
    //   3080: iload_2
    //   3081: ifne -> 3864
    //   3084: goto -> 3091
    //   3087: invokestatic a : (Ljava/lang/Throwable;)Ljava/lang/Throwable;
    //   3090: athrow
    //   3091: aload_3
    //   3092: getstatic burp/Ze64.ZM : Ljava/lang/String;
    //   3095: getstatic burp/Zram.ZF : Ljava/lang/Object;
    //   3098: checkcast java/math/BigInteger
    //   3101: invokevirtual intValue : ()I
    //   3104: bipush #32
    //   3106: irem
    //   3107: invokestatic abs : (I)I
    //   3110: invokevirtual charAt : (I)C
    //   3113: invokevirtual append : (C)Ljava/lang/StringBuilder;
    //   3116: pop
    //   3117: iload_2
    //   3118: ifne -> 3864
    //   3121: goto -> 3128
    //   3124: invokestatic a : (Ljava/lang/Throwable;)Ljava/lang/Throwable;
    //   3127: athrow
    //   3128: aload_3
    //   3129: getstatic burp/Zs4z.Zs : Ljava/lang/String;
    //   3132: getstatic burp/Zkm0.ZI : Ljava/lang/Object;
    //   3135: checkcast java/math/BigInteger
    //   3138: invokevirtual intValue : ()I
    //   3141: bipush #32
    //   3143: irem
    //   3144: invokestatic abs : (I)I
    //   3147: invokevirtual charAt : (I)C
    //   3150: invokevirtual append : (C)Ljava/lang/StringBuilder;
    //   3153: pop
    //   3154: iload_2
    //   3155: ifne -> 3864
    //   3158: goto -> 3165
    //   3161: invokestatic a : (Ljava/lang/Throwable;)Ljava/lang/Throwable;
    //   3164: athrow
    //   3165: aload_3
    //   3166: getstatic burp/Zef0.ZR : Ljava/lang/String;
    //   3169: getstatic burp/Ze5t.Zc : Ljava/lang/Object;
    //   3172: checkcast java/math/BigInteger
    //   3175: invokevirtual intValue : ()I
    //   3178: bipush #32
    //   3180: irem
    //   3181: invokestatic abs : (I)I
    //   3184: invokevirtual charAt : (I)C
    //   3187: invokevirtual append : (C)Ljava/lang/StringBuilder;
    //   3190: pop
    //   3191: iload_2
    //   3192: ifne -> 3864
    //   3195: goto -> 3202
    //   3198: invokestatic a : (Ljava/lang/Throwable;)Ljava/lang/Throwable;
    //   3201: athrow
    //   3202: aload_3
    //   3203: getstatic burp/Zk7f.ZA : Ljava/lang/String;
    //   3206: getstatic burp/Ztkh.Zh : Ljava/lang/Object;
    //   3209: checkcast java/math/BigInteger
    //   3212: invokevirtual intValue : ()I
    //   3215: bipush #32
    //   3217: irem
    //   3218: invokestatic abs : (I)I
    //   3221: invokevirtual charAt : (I)C
    //   3224: invokevirtual append : (C)Ljava/lang/StringBuilder;
    //   3227: pop
    //   3228: iload_2
    //   3229: ifne -> 3864
    //   3232: goto -> 3239
    //   3235: invokestatic a : (Ljava/lang/Throwable;)Ljava/lang/Throwable;
    //   3238: athrow
    //   3239: aload_3
    //   3240: getstatic burp/Zess.Zc : Ljava/lang/String;
    //   3243: getstatic burp/Zel.ZB : Ljava/lang/Object;
    //   3246: checkcast java/math/BigInteger
    //   3249: invokevirtual intValue : ()I
    //   3252: bipush #32
    //   3254: irem
    //   3255: invokestatic abs : (I)I
    //   3258: invokevirtual charAt : (I)C
    //   3261: invokevirtual append : (C)Ljava/lang/StringBuilder;
    //   3264: pop
    //   3265: iload_2
    //   3266: ifne -> 3864
    //   3269: goto -> 3276
    //   3272: invokestatic a : (Ljava/lang/Throwable;)Ljava/lang/Throwable;
    //   3275: athrow
    //   3276: aload_3
    //   3277: getstatic burp/Zr48.ZG : Ljava/lang/String;
    //   3280: getstatic burp/Zm52.ZR : Ljava/lang/Object;
    //   3283: checkcast java/math/BigInteger
    //   3286: invokevirtual intValue : ()I
    //   3289: bipush #32
    //   3291: irem
    //   3292: invokestatic abs : (I)I
    //   3295: invokevirtual charAt : (I)C
    //   3298: invokevirtual append : (C)Ljava/lang/StringBuilder;
    //   3301: pop
    //   3302: iload_2
    //   3303: ifne -> 3864
    //   3306: goto -> 3313
    //   3309: invokestatic a : (Ljava/lang/Throwable;)Ljava/lang/Throwable;
    //   3312: athrow
    //   3313: aload_3
    //   3314: getstatic burp/Zram.Ze : Ljava/lang/String;
    //   3317: getstatic burp/Ztfh.Zo : Ljava/lang/Object;
    //   3320: checkcast java/math/BigInteger
    //   3323: invokevirtual intValue : ()I
    //   3326: bipush #32
    //   3328: irem
    //   3329: invokestatic abs : (I)I
    //   3332: invokevirtual charAt : (I)C
    //   3335: invokevirtual append : (C)Ljava/lang/StringBuilder;
    //   3338: pop
    //   3339: iload_2
    //   3340: ifne -> 3864
    //   3343: goto -> 3350
    //   3346: invokestatic a : (Ljava/lang/Throwable;)Ljava/lang/Throwable;
    //   3349: athrow
    //   3350: aload_3
    //   3351: getstatic burp/Zlo5.ZJ : Ljava/lang/String;
    //   3354: getstatic burp/Zs_v.Zs : Ljava/lang/Object;
    //   3357: checkcast java/math/BigInteger
    //   3360: invokevirtual intValue : ()I
    //   3363: bipush #32
    //   3365: irem
    //   3366: invokestatic abs : (I)I
    //   3369: invokevirtual charAt : (I)C
    //   3372: invokevirtual append : (C)Ljava/lang/StringBuilder;
    //   3375: pop
    //   3376: iload_2
    //   3377: ifne -> 3864
    //   3380: goto -> 3387
    //   3383: invokestatic a : (Ljava/lang/Throwable;)Ljava/lang/Throwable;
    //   3386: athrow
    //   3387: aload_3
    //   3388: getstatic burp/Zt3f.ZU : Ljava/lang/String;
    //   3391: getstatic burp/Zz2e.Zm : Ljava/lang/Object;
    //   3394: checkcast java/math/BigInteger
    //   3397: invokevirtual intValue : ()I
    //   3400: bipush #32
    //   3402: irem
    //   3403: invokestatic abs : (I)I
    //   3406: invokevirtual charAt : (I)C
    //   3409: invokevirtual append : (C)Ljava/lang/StringBuilder;
    //   3412: pop
    //   3413: iload_2
    //   3414: ifne -> 3864
    //   3417: goto -> 3424
    //   3420: invokestatic a : (Ljava/lang/Throwable;)Ljava/lang/Throwable;
    //   3423: athrow
    //   3424: aload_3
    //   3425: getstatic burp/Zl8f.ZK : Ljava/lang/String;
    //   3428: getstatic burp/Zgnp.Zm : Ljava/lang/Object;
    //   3431: checkcast java/math/BigInteger
    //   3434: invokevirtual intValue : ()I
    //   3437: bipush #32
    //   3439: irem
    //   3440: invokestatic abs : (I)I
    //   3443: invokevirtual charAt : (I)C
    //   3446: invokevirtual append : (C)Ljava/lang/StringBuilder;
    //   3449: pop
    //   3450: iload_2
    //   3451: ifne -> 3864
    //   3454: goto -> 3461
    //   3457: invokestatic a : (Ljava/lang/Throwable;)Ljava/lang/Throwable;
    //   3460: athrow
    //   3461: aload_3
    //   3462: getstatic burp/Ztdd.ZA : Ljava/lang/String;
    //   3465: getstatic burp/Ze_t.Za : Ljava/lang/Object;
    //   3468: checkcast java/math/BigInteger
    //   3471: invokevirtual intValue : ()I
    //   3474: bipush #32
    //   3476: irem
    //   3477: invokestatic abs : (I)I
    //   3480: invokevirtual charAt : (I)C
    //   3483: invokevirtual append : (C)Ljava/lang/StringBuilder;
    //   3486: pop
    //   3487: iload_2
    //   3488: ifne -> 3864
    //   3491: goto -> 3498
    //   3494: invokestatic a : (Ljava/lang/Throwable;)Ljava/lang/Throwable;
    //   3497: athrow
    //   3498: aload_3
    //   3499: getstatic burp/Zkm0.ZL : Ljava/lang/String;
    //   3502: getstatic burp/Zeqg.Zm : Ljava/lang/Object;
    //   3505: checkcast java/math/BigInteger
    //   3508: invokevirtual intValue : ()I
    //   3511: bipush #32
    //   3513: irem
    //   3514: invokestatic abs : (I)I
    //   3517: invokevirtual charAt : (I)C
    //   3520: invokevirtual append : (C)Ljava/lang/StringBuilder;
    //   3523: pop
    //   3524: iload_2
    //   3525: ifne -> 3864
    //   3528: goto -> 3535
    //   3531: invokestatic a : (Ljava/lang/Throwable;)Ljava/lang/Throwable;
    //   3534: athrow
    //   3535: aload_3
    //   3536: getstatic burp/Zx6d.ZP : Ljava/lang/String;
    //   3539: getstatic burp/Zxg7.Zy : Ljava/lang/Object;
    //   3542: checkcast java/math/BigInteger
    //   3545: invokevirtual intValue : ()I
    //   3548: bipush #32
    //   3550: irem
    //   3551: invokestatic abs : (I)I
    //   3554: invokevirtual charAt : (I)C
    //   3557: invokevirtual append : (C)Ljava/lang/StringBuilder;
    //   3560: pop
    //   3561: iload_2
    //   3562: ifne -> 3864
    //   3565: goto -> 3572
    //   3568: invokestatic a : (Ljava/lang/Throwable;)Ljava/lang/Throwable;
    //   3571: athrow
    //   3572: aload_3
    //   3573: getstatic burp/Ztj5.Zt : Ljava/lang/String;
    //   3576: getstatic burp/Zkjr.Zw : Ljava/lang/Object;
    //   3579: checkcast java/math/BigInteger
    //   3582: invokevirtual intValue : ()I
    //   3585: bipush #32
    //   3587: irem
    //   3588: invokestatic abs : (I)I
    //   3591: invokevirtual charAt : (I)C
    //   3594: invokevirtual append : (C)Ljava/lang/StringBuilder;
    //   3597: pop
    //   3598: iload_2
    //   3599: ifne -> 3864
    //   3602: goto -> 3609
    //   3605: invokestatic a : (Ljava/lang/Throwable;)Ljava/lang/Throwable;
    //   3608: athrow
    //   3609: aload_3
    //   3610: getstatic burp/Zstb.Zd : Ljava/lang/String;
    //   3613: getstatic burp/Ztex.Z_ : Ljava/lang/Object;
    //   3616: checkcast java/math/BigInteger
    //   3619: invokevirtual intValue : ()I
    //   3622: bipush #32
    //   3624: irem
    //   3625: invokestatic abs : (I)I
    //   3628: invokevirtual charAt : (I)C
    //   3631: invokevirtual append : (C)Ljava/lang/StringBuilder;
    //   3634: pop
    //   3635: iload_2
    //   3636: ifne -> 3864
    //   3639: goto -> 3646
    //   3642: invokestatic a : (Ljava/lang/Throwable;)Ljava/lang/Throwable;
    //   3645: athrow
    //   3646: aload_3
    //   3647: getstatic burp/Zk7e.ZP : Ljava/lang/String;
    //   3650: getstatic burp/Zess.Zj : Ljava/lang/Object;
    //   3653: checkcast java/math/BigInteger
    //   3656: invokevirtual intValue : ()I
    //   3659: bipush #32
    //   3661: irem
    //   3662: invokestatic abs : (I)I
    //   3665: invokevirtual charAt : (I)C
    //   3668: invokevirtual append : (C)Ljava/lang/StringBuilder;
    //   3671: pop
    //   3672: iload_2
    //   3673: ifne -> 3864
    //   3676: goto -> 3683
    //   3679: invokestatic a : (Ljava/lang/Throwable;)Ljava/lang/Throwable;
    //   3682: athrow
    //   3683: aload_3
    //   3684: getstatic burp/Zltz.Za : Ljava/lang/String;
    //   3687: getstatic burp/Zsxh.Zk : Ljava/lang/Object;
    //   3690: checkcast java/math/BigInteger
    //   3693: invokevirtual intValue : ()I
    //   3696: bipush #32
    //   3698: irem
    //   3699: invokestatic abs : (I)I
    //   3702: invokevirtual charAt : (I)C
    //   3705: invokevirtual append : (C)Ljava/lang/StringBuilder;
    //   3708: pop
    //   3709: iload_2
    //   3710: ifne -> 3864
    //   3713: goto -> 3720
    //   3716: invokestatic a : (Ljava/lang/Throwable;)Ljava/lang/Throwable;
    //   3719: athrow
    //   3720: aload_3
    //   3721: getstatic burp/Zevr.Zk : Ljava/lang/String;
    //   3724: getstatic burp/Zlvb.ZN : Ljava/lang/Object;
    //   3727: checkcast java/math/BigInteger
    //   3730: invokevirtual intValue : ()I
    //   3733: bipush #32
    //   3735: irem
    //   3736: invokestatic abs : (I)I
    //   3739: invokevirtual charAt : (I)C
    //   3742: invokevirtual append : (C)Ljava/lang/StringBuilder;
    //   3745: pop
    //   3746: iload_2
    //   3747: ifne -> 3864
    //   3750: goto -> 3757
    //   3753: invokestatic a : (Ljava/lang/Throwable;)Ljava/lang/Throwable;
    //   3756: athrow
    //   3757: aload_3
    //   3758: getstatic burp/Zsf7.ZS : Ljava/lang/String;
    //   3761: getstatic burp/Zzo5.Zf : Ljava/lang/Object;
    //   3764: checkcast java/math/BigInteger
    //   3767: invokevirtual intValue : ()I
    //   3770: bipush #32
    //   3772: irem
    //   3773: invokestatic abs : (I)I
    //   3776: invokevirtual charAt : (I)C
    //   3779: invokevirtual append : (C)Ljava/lang/StringBuilder;
    //   3782: pop
    //   3783: iload_2
    //   3784: ifne -> 3864
    //   3787: goto -> 3794
    //   3790: invokestatic a : (Ljava/lang/Throwable;)Ljava/lang/Throwable;
    //   3793: athrow
    //   3794: aload_3
    //   3795: getstatic burp/Zeqg.Zh : Ljava/lang/String;
    //   3798: getstatic burp/Zzgh.ZV : Ljava/lang/Object;
    //   3801: checkcast java/math/BigInteger
    //   3804: invokevirtual intValue : ()I
    //   3807: bipush #32
    //   3809: irem
    //   3810: invokestatic abs : (I)I
    //   3813: invokevirtual charAt : (I)C
    //   3816: invokevirtual append : (C)Ljava/lang/StringBuilder;
    //   3819: pop
    //   3820: iload_2
    //   3821: ifne -> 3864
    //   3824: goto -> 3831
    //   3827: invokestatic a : (Ljava/lang/Throwable;)Ljava/lang/Throwable;
    //   3830: athrow
    //   3831: aload_3
    //   3832: getstatic burp/Ze5f.Zt : Ljava/lang/String;
    //   3835: getstatic burp/Zmhi.ZZ : Ljava/lang/Object;
    //   3838: checkcast java/math/BigInteger
    //   3841: invokevirtual intValue : ()I
    //   3844: bipush #32
    //   3846: irem
    //   3847: invokestatic abs : (I)I
    //   3850: invokevirtual charAt : (I)C
    //   3853: invokevirtual append : (C)Ljava/lang/StringBuilder;
    //   3856: pop
    //   3857: goto -> 3864
    //   3860: invokestatic a : (Ljava/lang/Throwable;)Ljava/lang/Throwable;
    //   3863: athrow
    //   3864: iinc #4, 1
    //   3867: iload_2
    //   3868: ifne -> 2532
    //   3871: aload_3
    //   3872: invokevirtual toString : ()Ljava/lang/String;
    //   3875: putstatic burp/Zevr.Zk : Ljava/lang/String;
    //   3878: getstatic burp/Zmj8.Zz : Ljava/lang/Object;
    //   3881: checkcast java/math/BigInteger
    //   3884: invokevirtual toByteArray : ()[B
    //   3887: astore #4
    //   3889: aload #4
    //   3891: arraylength
    //   3892: iconst_2
    //   3893: iadd
    //   3894: newarray byte
    //   3896: astore #6
    //   3898: iconst_0
    //   3899: istore #7
    //   3901: iload #7
    //   3903: aload #4
    //   3905: arraylength
    //   3906: if_icmpge -> 3926
    //   3909: aload #6
    //   3911: iload #7
    //   3913: aload #4
    //   3915: iload #7
    //   3917: baload
    //   3918: bastore
    //   3919: iinc #7, 1
    //   3922: iload_2
    //   3923: ifne -> 3901
    //   3926: aload #6
    //   3928: arraylength
    //   3929: iconst_3
    //   3930: idiv
    //   3931: iconst_4
    //   3932: imul
    //   3933: newarray byte
    //   3935: astore #5
    //   3937: iconst_0
    //   3938: istore #7
    //   3940: iconst_0
    //   3941: istore #8
    //   3943: iload #7
    //   3945: aload #4
    //   3947: arraylength
    //   3948: if_icmpge -> 4059
    //   3951: aload #5
    //   3953: iload #8
    //   3955: aload #6
    //   3957: iload #7
    //   3959: baload
    //   3960: iconst_2
    //   3961: iushr
    //   3962: bipush #63
    //   3964: iand
    //   3965: i2b
    //   3966: bastore
    //   3967: aload #5
    //   3969: iload #8
    //   3971: iconst_1
    //   3972: iadd
    //   3973: aload #6
    //   3975: iload #7
    //   3977: iconst_1
    //   3978: iadd
    //   3979: baload
    //   3980: iconst_4
    //   3981: iushr
    //   3982: bipush #15
    //   3984: iand
    //   3985: aload #6
    //   3987: iload #7
    //   3989: baload
    //   3990: iconst_4
    //   3991: ishl
    //   3992: bipush #63
    //   3994: iand
    //   3995: ior
    //   3996: i2b
    //   3997: bastore
    //   3998: aload #5
    //   4000: iload #8
    //   4002: iconst_2
    //   4003: iadd
    //   4004: aload #6
    //   4006: iload #7
    //   4008: iconst_2
    //   4009: iadd
    //   4010: baload
    //   4011: bipush #6
    //   4013: iushr
    //   4014: iconst_3
    //   4015: iand
    //   4016: aload #6
    //   4018: iload #7
    //   4020: iconst_1
    //   4021: iadd
    //   4022: baload
    //   4023: iconst_2
    //   4024: ishl
    //   4025: bipush #63
    //   4027: iand
    //   4028: ior
    //   4029: i2b
    //   4030: bastore
    //   4031: aload #5
    //   4033: iload #8
    //   4035: iconst_3
    //   4036: iadd
    //   4037: aload #6
    //   4039: iload #7
    //   4041: iconst_2
    //   4042: iadd
    //   4043: baload
    //   4044: bipush #63
    //   4046: iand
    //   4047: i2b
    //   4048: bastore
    //   4049: iinc #7, 3
    //   4052: iinc #8, 4
    //   4055: iload_2
    //   4056: ifne -> 3943
    //   4059: iconst_0
    //   4060: istore #7
    //   4062: iload #7
    //   4064: aload #5
    //   4066: arraylength
    //   4067: if_icmpge -> 4251
    //   4070: aload #5
    //   4072: iload #7
    //   4074: baload
    //   4075: bipush #26
    //   4077: if_icmpge -> 4105
    //   4080: aload #5
    //   4082: iload #7
    //   4084: aload #5
    //   4086: iload #7
    //   4088: baload
    //   4089: bipush #65
    //   4091: iadd
    //   4092: i2b
    //   4093: bastore
    //   4094: iload_2
    //   4095: ifne -> 4244
    //   4098: goto -> 4105
    //   4101: invokestatic a : (Ljava/lang/Throwable;)Ljava/lang/Throwable;
    //   4104: athrow
    //   4105: aload #5
    //   4107: iload #7
    //   4109: baload
    //   4110: bipush #52
    //   4112: if_icmpge -> 4150
    //   4115: goto -> 4122
    //   4118: invokestatic a : (Ljava/lang/Throwable;)Ljava/lang/Throwable;
    //   4121: athrow
    //   4122: aload #5
    //   4124: iload #7
    //   4126: aload #5
    //   4128: iload #7
    //   4130: baload
    //   4131: bipush #97
    //   4133: iadd
    //   4134: bipush #26
    //   4136: isub
    //   4137: i2b
    //   4138: bastore
    //   4139: iload_2
    //   4140: ifne -> 4244
    //   4143: goto -> 4150
    //   4146: invokestatic a : (Ljava/lang/Throwable;)Ljava/lang/Throwable;
    //   4149: athrow
    //   4150: aload #5
    //   4152: iload #7
    //   4154: baload
    //   4155: bipush #62
    //   4157: if_icmpge -> 4195
    //   4160: goto -> 4167
    //   4163: invokestatic a : (Ljava/lang/Throwable;)Ljava/lang/Throwable;
    //   4166: athrow
    //   4167: aload #5
    //   4169: iload #7
    //   4171: aload #5
    //   4173: iload #7
    //   4175: baload
    //   4176: bipush #48
    //   4178: iadd
    //   4179: bipush #52
    //   4181: isub
    //   4182: i2b
    //   4183: bastore
    //   4184: iload_2
    //   4185: ifne -> 4244
    //   4188: goto -> 4195
    //   4191: invokestatic a : (Ljava/lang/Throwable;)Ljava/lang/Throwable;
    //   4194: athrow
    //   4195: aload #5
    //   4197: iload #7
    //   4199: baload
    //   4200: bipush #63
    //   4202: if_icmpge -> 4230
    //   4205: goto -> 4212
    //   4208: invokestatic a : (Ljava/lang/Throwable;)Ljava/lang/Throwable;
    //   4211: athrow
    //   4212: aload #5
    //   4214: iload #7
    //   4216: bipush #43
    //   4218: bastore
    //   4219: iload_2
    //   4220: ifne -> 4244
    //   4223: goto -> 4230
    //   4226: invokestatic a : (Ljava/lang/Throwable;)Ljava/lang/Throwable;
    //   4229: athrow
    //   4230: aload #5
    //   4232: iload #7
    //   4234: bipush #47
    //   4236: bastore
    //   4237: goto -> 4244
    //   4240: invokestatic a : (Ljava/lang/Throwable;)Ljava/lang/Throwable;
    //   4243: athrow
    //   4244: iinc #7, 1
    //   4247: iload_2
    //   4248: ifne -> 4062
    //   4251: aload #5
    //   4253: arraylength
    //   4254: iconst_1
    //   4255: isub
    //   4256: istore #7
    //   4258: iload #7
    //   4260: aload #4
    //   4262: arraylength
    //   4263: iconst_4
    //   4264: imul
    //   4265: iconst_3
    //   4266: idiv
    //   4267: if_icmple -> 4284
    //   4270: aload #5
    //   4272: iload #7
    //   4274: bipush #61
    //   4276: bastore
    //   4277: iinc #7, -1
    //   4280: iload_2
    //   4281: ifne -> 4258
    //   4284: new java/math/BigInteger
    //   4287: dup
    //   4288: aload #5
    //   4290: invokespecial <init> : ([B)V
    //   4293: invokevirtual abs : ()Ljava/math/BigInteger;
    //   4296: putstatic burp/Zl50.ZV : Ljava/lang/Object;
    //   4299: sipush #-1565
    //   4302: sipush #2790
    //   4305: invokestatic a : (II)Ljava/lang/String;
    //   4308: iconst_1
    //   4309: ldc burp/Zmcq
    //   4311: invokevirtual getClassLoader : ()Ljava/lang/ClassLoader;
    //   4314: invokestatic forName : (Ljava/lang/String;ZLjava/lang/ClassLoader;)Ljava/lang/Class;
    //   4317: invokevirtual getDeclaredFields : ()[Ljava/lang/reflect/Field;
    //   4320: astore #4
    //   4322: aload #4
    //   4324: arraylength
    //   4325: istore #5
    //   4327: iconst_0
    //   4328: istore #6
    //   4330: iload #6
    //   4332: iload #5
    //   4334: if_icmpge -> 4472
    //   4337: aload #4
    //   4339: iload #6
    //   4341: aaload
    //   4342: astore #7
    //   4344: aload #7
    //   4346: invokevirtual getModifiers : ()I
    //   4349: invokestatic isStatic : (I)Z
    //   4352: ifne -> 4362
    //   4355: goto -> 4465
    //   4358: invokestatic a : (Ljava/lang/Throwable;)Ljava/lang/Throwable;
    //   4361: athrow
    //   4362: aload #7
    //   4364: invokevirtual getType : ()Ljava/lang/Class;
    //   4367: astore #8
    //   4369: aload #8
    //   4371: ifnull -> 4452
    //   4374: aload #8
    //   4376: invokevirtual isPrimitive : ()Z
    //   4379: ifne -> 4452
    //   4382: goto -> 4389
    //   4385: invokestatic a : (Ljava/lang/Throwable;)Ljava/lang/Throwable;
    //   4388: athrow
    //   4389: aload #8
    //   4391: invokevirtual getPackage : ()Ljava/lang/Package;
    //   4394: ifnull -> 4452
    //   4397: goto -> 4404
    //   4400: invokestatic a : (Ljava/lang/Throwable;)Ljava/lang/Throwable;
    //   4403: athrow
    //   4404: aload #8
    //   4406: invokevirtual getPackage : ()Ljava/lang/Package;
    //   4409: invokevirtual getName : ()Ljava/lang/String;
    //   4412: ifnull -> 4452
    //   4415: goto -> 4422
    //   4418: invokestatic a : (Ljava/lang/Throwable;)Ljava/lang/Throwable;
    //   4421: athrow
    //   4422: aload #8
    //   4424: invokevirtual getPackage : ()Ljava/lang/Package;
    //   4427: invokevirtual getName : ()Ljava/lang/String;
    //   4430: sipush #-1560
    //   4433: sipush #29674
    //   4436: invokestatic a : (II)Ljava/lang/String;
    //   4439: invokevirtual startsWith : (Ljava/lang/String;)Z
    //   4442: ifne -> 4452
    //   4445: goto -> 4452
    //   4448: invokestatic a : (Ljava/lang/Throwable;)Ljava/lang/Throwable;
    //   4451: athrow
    //   4452: aload #7
    //   4454: iconst_1
    //   4455: invokevirtual setAccessible : (Z)V
    //   4458: aload #7
    //   4460: aconst_null
    //   4461: invokevirtual get : (Ljava/lang/Object;)Ljava/lang/Object;
    //   4464: pop
    //   4465: iinc #6, 1
    //   4468: iload_2
    //   4469: ifne -> 4330
    //   4472: sipush #-1558
    //   4475: sipush #-8812
    //   4478: invokestatic a : (II)Ljava/lang/String;
    //   4481: invokestatic forName : (Ljava/lang/String;)Ljava/lang/Class;
    //   4484: invokevirtual getDeclaredMethods : ()[Ljava/lang/reflect/Method;
    //   4487: astore #4
    //   4489: aload #4
    //   4491: arraylength
    //   4492: istore #5
    //   4494: iconst_0
    //   4495: istore #6
    //   4497: iload #6
    //   4499: iload #5
    //   4501: if_icmpge -> 4634
    //   4504: aload #4
    //   4506: iload #6
    //   4508: aaload
    //   4509: astore #7
    //   4511: aload #7
    //   4513: invokevirtual getParameterTypes : ()[Ljava/lang/Class;
    //   4516: pop
    //   4517: aload #7
    //   4519: invokevirtual getModifiers : ()I
    //   4522: invokestatic isStatic : (I)Z
    //   4525: ifeq -> 4620
    //   4528: aload #7
    //   4530: invokevirtual getParameterTypes : ()[Ljava/lang/Class;
    //   4533: arraylength
    //   4534: iconst_2
    //   4535: if_icmpne -> 4620
    //   4538: goto -> 4545
    //   4541: invokestatic a : (Ljava/lang/Throwable;)Ljava/lang/Throwable;
    //   4544: athrow
    //   4545: aload #7
    //   4547: invokevirtual getReturnType : ()Ljava/lang/Class;
    //   4550: getstatic java/lang/Void.TYPE : Ljava/lang/Class;
    //   4553: invokevirtual equals : (Ljava/lang/Object;)Z
    //   4556: ifeq -> 4620
    //   4559: goto -> 4566
    //   4562: invokestatic a : (Ljava/lang/Throwable;)Ljava/lang/Throwable;
    //   4565: athrow
    //   4566: aload #7
    //   4568: iconst_1
    //   4569: invokevirtual setAccessible : (Z)V
    //   4572: aload #7
    //   4574: aconst_null
    //   4575: iconst_2
    //   4576: anewarray java/lang/Object
    //   4579: dup
    //   4580: iconst_0
    //   4581: aload_0
    //   4582: aastore
    //   4583: dup
    //   4584: iconst_1
    //   4585: aload_1
    //   4586: ifnonnull -> 4604
    //   4589: goto -> 4596
    //   4592: invokestatic a : (Ljava/lang/Throwable;)Ljava/lang/Throwable;
    //   4595: athrow
    //   4596: aload_1
    //   4597: goto -> 4611
    //   4600: invokestatic a : (Ljava/lang/Throwable;)Ljava/lang/Throwable;
    //   4603: athrow
    //   4604: aload_1
    //   4605: checkcast [B
    //   4608: invokevirtual clone : ()Ljava/lang/Object;
    //   4611: aastore
    //   4612: invokevirtual invoke : (Ljava/lang/Object;[Ljava/lang/Object;)Ljava/lang/Object;
    //   4615: pop
    //   4616: iload_2
    //   4617: ifne -> 4634
    //   4620: iinc #6, 1
    //   4623: iload_2
    //   4624: ifne -> 4497
    //   4627: goto -> 4634
    //   4630: invokestatic a : (Ljava/lang/Throwable;)Ljava/lang/Throwable;
    //   4633: athrow
    //   4634: getstatic burp/Zstb.Zd : Ljava/lang/String;
    //   4637: getstatic burp/Zkll.Zl : Ljava/lang/Object;
    //   4640: checkcast java/math/BigInteger
    //   4643: invokevirtual intValue : ()I
    //   4646: bipush #32
    //   4648: irem
    //   4649: invokestatic abs : (I)I
    //   4652: invokevirtual charAt : (I)C
    //   4655: getstatic burp/Zgqi.Zv : Ljava/lang/String;
    //   4658: getstatic burp/Zkll.Zl : Ljava/lang/Object;
    //   4661: checkcast java/math/BigInteger
    //   4664: invokevirtual intValue : ()I
    //   4667: bipush #32
    //   4669: irem
    //   4670: invokestatic abs : (I)I
    //   4673: invokevirtual charAt : (I)C
    //   4676: if_icmpgt -> 4783
    //   4679: getstatic burp/Zs_3.ZC : Ljava/lang/String;
    //   4682: getstatic burp/Zzym.ZK : Ljava/lang/Object;
    //   4685: checkcast java/math/BigInteger
    //   4688: invokevirtual intValue : ()I
    //   4691: bipush #32
    //   4693: irem
    //   4694: invokestatic abs : (I)I
    //   4697: invokevirtual charAt : (I)C
    //   4700: getstatic burp/Zs8s.Za : Ljava/lang/String;
    //   4703: getstatic burp/Zsxo.Za : Ljava/lang/Object;
    //   4706: checkcast java/math/BigInteger
    //   4709: invokevirtual intValue : ()I
    //   4712: bipush #32
    //   4714: irem
    //   4715: invokestatic abs : (I)I
    //   4718: invokevirtual charAt : (I)C
    //   4721: if_icmpgt -> 4783
    //   4724: goto -> 4731
    //   4727: invokestatic a : (Ljava/lang/Throwable;)Ljava/lang/Throwable;
    //   4730: athrow
    //   4731: getstatic burp/Zs2n.ZI : Ljava/lang/String;
    //   4734: getstatic burp/Zxe.Zg : Ljava/lang/Object;
    //   4737: checkcast java/math/BigInteger
    //   4740: invokevirtual intValue : ()I
    //   4743: bipush #32
    //   4745: irem
    //   4746: invokestatic abs : (I)I
    //   4749: invokevirtual charAt : (I)C
    //   4752: getstatic burp/Zza8.Zm : Ljava/lang/String;
    //   4755: getstatic burp/Zs_3.ZZ : Ljava/lang/Object;
    //   4758: checkcast java/math/BigInteger
    //   4761: invokevirtual intValue : ()I
    //   4764: bipush #32
    //   4766: irem
    //   4767: invokestatic abs : (I)I
    //   4770: invokevirtual charAt : (I)C
    //   4773: if_icmple -> 4791
    //   4776: goto -> 4783
    //   4779: invokestatic a : (Ljava/lang/Throwable;)Ljava/lang/Throwable;
    //   4782: athrow
    //   4783: iconst_1
    //   4784: goto -> 4792
    //   4787: invokestatic a : (Ljava/lang/Throwable;)Ljava/lang/Throwable;
    //   4790: athrow
    //   4791: iconst_0
    //   4792: ireturn
    //   4793: astore_3
    //   4794: new java/lang/Exception
    //   4797: dup
    //   4798: aload_3
    //   4799: invokevirtual getMessage : ()Ljava/lang/String;
    //   4802: invokespecial <init> : (Ljava/lang/String;)V
    //   4805: athrow
    // Exception table:
    //   from	to	target	type
    //   4	4792	4793	java/lang/Throwable
    //   149	164	164	java/lang/Throwable
    //   1166	1192	1192	java/lang/Throwable
    //   1273	1288	1288	java/lang/Throwable
    //   2470	2495	2498	java/lang/Throwable
    //   2539	2714	2717	java/lang/Throwable
    //   2684	2751	2754	java/lang/Throwable
    //   2721	2788	2791	java/lang/Throwable
    //   2758	2825	2828	java/lang/Throwable
    //   2795	2862	2865	java/lang/Throwable
    //   2832	2899	2902	java/lang/Throwable
    //   2869	2936	2939	java/lang/Throwable
    //   2906	2973	2976	java/lang/Throwable
    //   2943	3010	3013	java/lang/Throwable
    //   2980	3047	3050	java/lang/Throwable
    //   3017	3084	3087	java/lang/Throwable
    //   3054	3121	3124	java/lang/Throwable
    //   3091	3158	3161	java/lang/Throwable
    //   3128	3195	3198	java/lang/Throwable
    //   3165	3232	3235	java/lang/Throwable
    //   3202	3269	3272	java/lang/Throwable
    //   3239	3306	3309	java/lang/Throwable
    //   3276	3343	3346	java/lang/Throwable
    //   3313	3380	3383	java/lang/Throwable
    //   3350	3417	3420	java/lang/Throwable
    //   3387	3454	3457	java/lang/Throwable
    //   3424	3491	3494	java/lang/Throwable
    //   3461	3528	3531	java/lang/Throwable
    //   3498	3565	3568	java/lang/Throwable
    //   3535	3602	3605	java/lang/Throwable
    //   3572	3639	3642	java/lang/Throwable
    //   3609	3676	3679	java/lang/Throwable
    //   3646	3713	3716	java/lang/Throwable
    //   3683	3750	3753	java/lang/Throwable
    //   3720	3787	3790	java/lang/Throwable
    //   3757	3824	3827	java/lang/Throwable
    //   3794	3857	3860	java/lang/Throwable
    //   4070	4098	4101	java/lang/Throwable
    //   4080	4115	4118	java/lang/Throwable
    //   4105	4143	4146	java/lang/Throwable
    //   4122	4160	4163	java/lang/Throwable
    //   4150	4188	4191	java/lang/Throwable
    //   4167	4205	4208	java/lang/Throwable
    //   4195	4223	4226	java/lang/Throwable
    //   4212	4237	4240	java/lang/Throwable
    //   4344	4358	4358	java/lang/Throwable
    //   4369	4382	4385	java/lang/Throwable
    //   4374	4397	4400	java/lang/Throwable
    //   4389	4415	4418	java/lang/Throwable
    //   4404	4445	4448	java/lang/Throwable
    //   4511	4538	4541	java/lang/Throwable
    //   4528	4559	4562	java/lang/Throwable
    //   4545	4589	4592	java/lang/Throwable
    //   4566	4600	4600	java/lang/Throwable
    //   4611	4627	4630	java/lang/Throwable
    //   4634	4724	4727	java/lang/Throwable
    //   4679	4776	4779	java/lang/Throwable
    //   4731	4787	4787	java/lang/Throwable
  }
  
  static void ZC(Object paramObject) {
    Zlck.ZL = a(-1567, 5658);
    Zlck.Zr = new BigInteger(a(-1559, 19086));
    boolean bool = Zt2e.ZK();
    try {
      try {
        if (Zk7f.ZA.charAt(Math.abs(((BigInteger)Zef0.ZX).intValue() % 32)) <= Zkll.ZX.charAt(Math.abs(((BigInteger)Zess.Zj).intValue() % 32))) {
          try {
            Zg4w.Za(Class.forName(a(-1555, 27269)));
            if (bool)
              Zg6f.Ze(Class.forName(a(-1556, -26342))); 
          } catch (Throwable throwable) {
            throw a(null);
          } 
          return;
        } 
      } catch (Throwable throwable) {
        throw a(null);
      } 
      Zg6f.Ze(Class.forName(a(-1556, -26342)));
    } catch (Throwable throwable) {}
  }
  
  static {
    // Byte code:
    //   0: bipush #12
    //   2: anewarray java/lang/String
    //   5: astore #5
    //   7: iconst_0
    //   8: istore_3
    //   9: ldc '=4ZM?Sna6\\nEQyqP*U>("K``ggOc!\\t-2X{??\\t4\\r`~b\\t[cMHYPb\\nl#d w(6#G]^*n)qY?? 4\p7HXL~AIr=+K+'
    //   11: dup
    //   12: astore_2
    //   13: invokevirtual length : ()I
    //   16: istore #4
    //   18: iconst_4
    //   19: istore_1
    //   20: iconst_m1
    //   21: istore_0
    //   22: bipush #101
    //   24: iinc #0, 1
    //   27: aload_2
    //   28: iload_0
    //   29: dup
    //   30: iload_1
    //   31: iadd
    //   32: invokevirtual substring : (II)Ljava/lang/String;
    //   35: iconst_m1
    //   36: goto -> 142
    //   39: aload #5
    //   41: swap
    //   42: iload_3
    //   43: iinc #3, 1
    //   46: swap
    //   47: aastore
    //   48: iload_0
    //   49: iload_1
    //   50: iadd
    //   51: dup
    //   52: istore_0
    //   53: iload #4
    //   55: if_icmpge -> 67
    //   58: aload_2
    //   59: iload_0
    //   60: invokevirtual charAt : (I)C
    //   63: istore_1
    //   64: goto -> 22
    //   67: ldc 'oB.\\b}0IS._'8UxY[/O>\\f8G{A\\fQd]eq\\tSv5['
    //   69: dup
    //   70: astore_2
    //   71: invokevirtual length : ()I
    //   74: istore #4
    //   76: bipush #77
    //   78: istore_1
    //   79: iconst_m1
    //   80: istore_0
    //   81: bipush #108
    //   83: iinc #0, 1
    //   86: aload_2
    //   87: iload_0
    //   88: dup
    //   89: iload_1
    //   90: iadd
    //   91: invokevirtual substring : (II)Ljava/lang/String;
    //   94: iconst_0
    //   95: goto -> 142
    //   98: aload #5
    //   100: swap
    //   101: iload_3
    //   102: iinc #3, 1
    //   105: swap
    //   106: aastore
    //   107: iload_0
    //   108: iload_1
    //   109: iadd
    //   110: dup
    //   111: istore_0
    //   112: iload #4
    //   114: if_icmpge -> 126
    //   117: aload_2
    //   118: iload_0
    //   119: invokevirtual charAt : (I)C
    //   122: istore_1
    //   123: goto -> 81
    //   126: aload #5
    //   128: putstatic burp/Zlnm.a : [Ljava/lang/String;
    //   131: bipush #12
    //   133: anewarray java/lang/String
    //   136: putstatic burp/Zlnm.b : [Ljava/lang/String;
    //   139: goto -> 300
    //   142: dup_x2
    //   143: pop
    //   144: invokevirtual toCharArray : ()[C
    //   147: dup_x1
    //   148: arraylength
    //   149: dup_x2
    //   150: pop
    //   151: iconst_0
    //   152: istore #6
    //   154: dup2_x1
    //   155: pop2
    //   156: dup_x2
    //   157: iconst_1
    //   158: if_icmpgt -> 260
    //   161: dup2
    //   162: swap
    //   163: iload #6
    //   165: dup2_x1
    //   166: caload
    //   167: swap
    //   168: iload #6
    //   170: bipush #7
    //   172: irem
    //   173: tableswitch default -> 242, 0 -> 212, 1 -> 217, 2 -> 222, 3 -> 227, 4 -> 232, 5 -> 237
    //   212: bipush #114
    //   214: goto -> 244
    //   217: bipush #60
    //   219: goto -> 244
    //   222: bipush #80
    //   224: goto -> 244
    //   227: bipush #24
    //   229: goto -> 244
    //   232: bipush #14
    //   234: goto -> 244
    //   237: bipush #125
    //   239: goto -> 244
    //   242: bipush #93
    //   244: ixor
    //   245: ixor
    //   246: i2c
    //   247: castore
    //   248: iinc #6, 1
    //   251: dup
    //   252: ifne -> 260
    //   255: dup2
    //   256: dup_x1
    //   257: goto -> 165
    //   260: dup2_x1
    //   261: pop2
    //   262: dup_x2
    //   263: iload #6
    //   265: if_icmpgt -> 161
    //   268: pop
    //   269: new java/lang/String
    //   272: dup_x1
    //   273: swap
    //   274: invokespecial <init> : ([C)V
    //   277: invokevirtual intern : ()Ljava/lang/String;
    //   280: swap
    //   281: pop
    //   282: swap
    //   283: tableswitch default -> 39, 0 -> 98
    //   300: sipush #-1553
    //   303: sipush #-25206
    //   306: invokestatic a : (II)Ljava/lang/String;
    //   309: putstatic burp/Zlnm.ZL : Ljava/lang/String;
    //   312: new java/math/BigInteger
    //   315: dup
    //   316: sipush #-1566
    //   319: sipush #-8240
    //   322: invokestatic a : (II)Ljava/lang/String;
    //   325: invokespecial <init> : (Ljava/lang/String;)V
    //   328: putstatic burp/Zlnm.Zn : Ljava/lang/Object;
    //   331: return
  }
  
  private static Throwable a(Throwable paramThrowable) {
    return paramThrowable;
  }
  
  private static String a(int paramInt1, int paramInt2) {
    int i = (paramInt1 ^ 0xFFFFF9E8) & 0xFFFF;
    if (b[i] == null) {
      char[] arrayOfChar = a[i].toCharArray();
      switch (arrayOfChar[0] & 0xFF) {
        case 0:
        
        case 1:
        
        case 2:
        
        case 3:
        
        case 4:
        
        case 5:
        
        case 6:
        
        case 7:
        
        case 8:
        
        case 9:
        
        case 10:
        
        case 11:
        
        case 12:
        
        case 13:
        
        case 14:
        
        case 15:
        
        case 16:
        
        case 17:
        
        case 18:
        
        case 19:
        
        case 20:
        
        case 21:
        
        case 22:
        
        case 23:
        
        case 24:
        
        case 25:
        
        case 26:
        
        case 27:
        
        case 28:
        
        case 29:
        
        case 30:
        
        case 31:
        
        case 32:
        
        case 33:
        
        case 34:
        
        case 35:
        
        case 36:
        
        case 37:
        
        case 38:
        
        case 39:
        
        case 40:
        
        case 41:
        
        case 42:
        
        case 43:
        
        case 44:
        
        case 45:
        
        case 46:
        
        case 47:
        
        case 48:
        
        case 49:
        
        case 50:
        
        case 51:
        
        case 52:
        
        case 53:
        
        case 54:
        
        case 55:
        
        case 56:
        
        case 57:
        
        case 58:
        
        case 59:
        
        case 60:
        
        case 61:
        
        case 62:
        
        case 63:
        
        case 64:
        
        case 65:
        
        case 66:
        
        case 67:
        
        case 68:
        
        case 69:
        
        case 70:
        
        case 71:
        
        case 72:
        
        case 73:
        
        case 74:
        
        case 75:
        
        case 76:
        
        case 77:
        
        case 78:
        
        case 79:
        
        case 80:
        
        case 81:
        
        case 82:
        
        case 83:
        
        case 84:
        
        case 85:
        
        case 86:
        
        case 87:
        
        case 88:
        
        case 89:
        
        case 90:
        
        case 91:
        
        case 92:
        
        case 93:
        
        case 94:
        
        case 95:
        
        case 96:
        
        case 97:
        
        case 98:
        
        case 99:
        
        case 100:
        
        case 101:
        
        case 102:
        
        case 103:
        
        case 104:
        
        case 105:
        
        case 106:
        
        case 107:
        
        case 108:
        
        case 109:
        
        case 110:
        
        case 111:
        
        case 112:
        
        case 113:
        
        case 114:
        
        case 115:
        
        case 116:
        
        case 117:
        
        case 118:
        
        case 119:
        
        case 120:
        
        case 121:
        
        case 122:
        
        case 123:
        
        case 124:
        
        case 125:
        
        case 126:
        
        case 127:
        
        case 128:
        
        case 129:
        
        case 130:
        
        case 131:
        
        case 132:
        
        case 133:
        
        case 134:
        
        case 135:
        
        case 136:
        
        case 137:
        
        case 138:
        
        case 139:
        
        case 140:
        
        case 141:
        
        case 142:
        
        case 143:
        
        case 144:
        
        case 145:
        
        case 146:
        
        case 147:
        
        case 148:
        
        case 149:
        
        case 150:
        
        case 151:
        
        case 152:
        
        case 153:
        
        case 154:
        
        case 155:
        
        case 156:
        
        case 157:
        
        case 158:
        
        case 159:
        
        case 160:
        
        case 161:
        
        case 162:
        
        case 163:
        
        case 164:
        
        case 165:
        
        case 166:
        
        case 167:
        
        case 168:
        
        case 169:
        
        case 170:
        
        case 171:
        
        case 172:
        
        case 173:
        
        case 174:
        
        case 175:
        
        case 176:
        
        case 177:
        
        case 178:
        
        case 179:
        
        case 180:
        
        case 181:
        
        case 182:
        
        case 183:
        
        case 184:
        
        case 185:
        
        case 186:
        
        case 187:
        
        case 188:
        
        case 189:
        
        case 190:
        
        case 191:
        
        case 192:
        
        case 193:
        
        case 194:
        
        case 195:
        
        case 196:
        
        case 197:
        
        case 198:
        
        case 199:
        
        case 200:
        
        case 201:
        
        case 202:
        
        case 203:
        
        case 204:
        
        case 205:
        
        case 206:
        
        case 207:
        
        case 208:
        
        case 209:
        
        case 210:
        
        case 211:
        
        case 212:
        
        case 213:
        
        case 214:
        
        case 215:
        
        case 216:
        
        case 217:
        
        case 218:
        
        case 219:
        
        case 220:
        
        case 221:
        
        case 222:
        
        case 223:
        
        case 224:
        
        case 225:
        
        case 226:
        
        case 227:
        
        case 228:
        
        case 229:
        
        case 230:
        
        case 231:
        
        case 232:
        
        case 233:
        
        case 234:
        
        case 235:
        
        case 236:
        
        case 237:
        
        case 238:
        
        case 239:
        
        case 240:
        
        case 241:
        
        case 242:
        
        case 243:
        
        case 244:
        
        case 245:
        
        case 246:
        
        case 247:
        
        case 248:
        
        case 249:
        
        case 250:
        
        case 251:
        
        case 252:
        
        case 253:
        
        case 254:
        
        default:
          break;
      } 
      byte b1 = 88;
      int j = (paramInt2 & 0xFF) - b1;
      if (j < 0)
        j += 256; 
      int k = ((paramInt2 & 0xFFFF) >>> 8) - b1;
      if (k < 0)
        k += 256; 
      for (byte b2 = 0; b2 < arrayOfChar.length; b2++) {
        int m = b2 % 2;
        if (m == 0) {
          arrayOfChar[b2] = (char)(arrayOfChar[b2] ^ j);
          j = ((j >>> 3 | j << 5) ^ arrayOfChar[b2]) & 0xFF;
        } else {
          arrayOfChar[b2] = (char)(arrayOfChar[b2] ^ k);
          k = ((k >>> 3 | k << 5) ^ arrayOfChar[b2]) & 0xFF;
        } 
      } 
      b[i] = (new String(arrayOfChar)).intern();
    } 
    return b[i];
  }
}


/* Location:              C:\Program Files\BurpSuitePro\burpsuite_pro.jar!\burp\Zlnm.class
 * Java compiler version: 21 (65.0)
 * JD-Core Version:       1.1.3
 */