package burp;

import java.math.BigInteger;

class Zlno extends ClassLoader {
  static Object ZU;
  
  static String ZM;
  
  private static final String[] a;
  
  private static final String[] b;
  
  static boolean ZE(Object[] paramArrayOfObject, Object paramObject) throws Throwable {
    // Byte code:
    //   0: invokestatic ZK : ()Z
    //   3: istore_2
    //   4: getstatic burp/Zxtn.ZY : Ljava/lang/Object;
    //   7: checkcast java/math/BigInteger
    //   10: getstatic burp/Zlyf.Zm : Ljava/lang/Object;
    //   13: checkcast java/math/BigInteger
    //   16: invokevirtual subtract : (Ljava/math/BigInteger;)Ljava/math/BigInteger;
    //   19: putstatic burp/Ze3t.Zp : Ljava/lang/Object;
    //   22: sipush #19054
    //   25: sipush #31519
    //   28: invokestatic a : (II)Ljava/lang/String;
    //   31: iconst_1
    //   32: ldc burp/Zxrd
    //   34: invokevirtual getClassLoader : ()Ljava/lang/ClassLoader;
    //   37: invokestatic forName : (Ljava/lang/String;ZLjava/lang/ClassLoader;)Ljava/lang/Class;
    //   40: invokevirtual getDeclaredFields : ()[Ljava/lang/reflect/Field;
    //   43: astore_3
    //   44: aload_3
    //   45: arraylength
    //   46: istore #4
    //   48: iconst_0
    //   49: istore #5
    //   51: iload #5
    //   53: iload #4
    //   55: if_icmpge -> 192
    //   58: aload_3
    //   59: iload #5
    //   61: aaload
    //   62: astore #6
    //   64: aload #6
    //   66: invokevirtual getModifiers : ()I
    //   69: invokestatic isStatic : (I)Z
    //   72: ifne -> 82
    //   75: goto -> 185
    //   78: invokestatic a : (Ljava/lang/Throwable;)Ljava/lang/Throwable;
    //   81: athrow
    //   82: aload #6
    //   84: invokevirtual getType : ()Ljava/lang/Class;
    //   87: astore #7
    //   89: aload #7
    //   91: ifnull -> 172
    //   94: aload #7
    //   96: invokevirtual isPrimitive : ()Z
    //   99: ifne -> 172
    //   102: goto -> 109
    //   105: invokestatic a : (Ljava/lang/Throwable;)Ljava/lang/Throwable;
    //   108: athrow
    //   109: aload #7
    //   111: invokevirtual getPackage : ()Ljava/lang/Package;
    //   114: ifnull -> 172
    //   117: goto -> 124
    //   120: invokestatic a : (Ljava/lang/Throwable;)Ljava/lang/Throwable;
    //   123: athrow
    //   124: aload #7
    //   126: invokevirtual getPackage : ()Ljava/lang/Package;
    //   129: invokevirtual getName : ()Ljava/lang/String;
    //   132: ifnull -> 172
    //   135: goto -> 142
    //   138: invokestatic a : (Ljava/lang/Throwable;)Ljava/lang/Throwable;
    //   141: athrow
    //   142: aload #7
    //   144: invokevirtual getPackage : ()Ljava/lang/Package;
    //   147: invokevirtual getName : ()Ljava/lang/String;
    //   150: sipush #19051
    //   153: sipush #-27841
    //   156: invokestatic a : (II)Ljava/lang/String;
    //   159: invokevirtual startsWith : (Ljava/lang/String;)Z
    //   162: ifne -> 172
    //   165: goto -> 172
    //   168: invokestatic a : (Ljava/lang/Throwable;)Ljava/lang/Throwable;
    //   171: athrow
    //   172: aload #6
    //   174: iconst_1
    //   175: invokevirtual setAccessible : (Z)V
    //   178: aload #6
    //   180: aconst_null
    //   181: invokevirtual get : (Ljava/lang/Object;)Ljava/lang/Object;
    //   184: pop
    //   185: iinc #5, 1
    //   188: iload_2
    //   189: ifeq -> 51
    //   192: sipush #19055
    //   195: sipush #-29494
    //   198: invokestatic a : (II)Ljava/lang/String;
    //   201: invokestatic forName : (Ljava/lang/String;)Ljava/lang/Class;
    //   204: invokevirtual getDeclaredMethods : ()[Ljava/lang/reflect/Method;
    //   207: astore_3
    //   208: aload_3
    //   209: arraylength
    //   210: istore #4
    //   212: iconst_0
    //   213: istore #5
    //   215: iload #5
    //   217: iload #4
    //   219: if_icmpge -> 351
    //   222: aload_3
    //   223: iload #5
    //   225: aaload
    //   226: astore #6
    //   228: aload #6
    //   230: invokevirtual getParameterTypes : ()[Ljava/lang/Class;
    //   233: pop
    //   234: aload #6
    //   236: invokevirtual getModifiers : ()I
    //   239: invokestatic isStatic : (I)Z
    //   242: ifeq -> 337
    //   245: aload #6
    //   247: invokevirtual getParameterTypes : ()[Ljava/lang/Class;
    //   250: arraylength
    //   251: iconst_2
    //   252: if_icmpne -> 337
    //   255: goto -> 262
    //   258: invokestatic a : (Ljava/lang/Throwable;)Ljava/lang/Throwable;
    //   261: athrow
    //   262: aload #6
    //   264: invokevirtual getReturnType : ()Ljava/lang/Class;
    //   267: getstatic java/lang/Void.TYPE : Ljava/lang/Class;
    //   270: invokevirtual equals : (Ljava/lang/Object;)Z
    //   273: ifeq -> 337
    //   276: goto -> 283
    //   279: invokestatic a : (Ljava/lang/Throwable;)Ljava/lang/Throwable;
    //   282: athrow
    //   283: aload #6
    //   285: iconst_1
    //   286: invokevirtual setAccessible : (Z)V
    //   289: aload #6
    //   291: aconst_null
    //   292: iconst_2
    //   293: anewarray java/lang/Object
    //   296: dup
    //   297: iconst_0
    //   298: aload_0
    //   299: aastore
    //   300: dup
    //   301: iconst_1
    //   302: aload_1
    //   303: ifnonnull -> 321
    //   306: goto -> 313
    //   309: invokestatic a : (Ljava/lang/Throwable;)Ljava/lang/Throwable;
    //   312: athrow
    //   313: aload_1
    //   314: goto -> 328
    //   317: invokestatic a : (Ljava/lang/Throwable;)Ljava/lang/Throwable;
    //   320: athrow
    //   321: aload_1
    //   322: checkcast [B
    //   325: invokevirtual clone : ()Ljava/lang/Object;
    //   328: aastore
    //   329: invokevirtual invoke : (Ljava/lang/Object;[Ljava/lang/Object;)Ljava/lang/Object;
    //   332: pop
    //   333: iload_2
    //   334: ifeq -> 351
    //   337: iinc #5, 1
    //   340: iload_2
    //   341: ifeq -> 215
    //   344: goto -> 351
    //   347: invokestatic a : (Ljava/lang/Throwable;)Ljava/lang/Throwable;
    //   350: athrow
    //   351: getstatic burp/Zblv.Zf : Ljava/lang/Object;
    //   354: checkcast java/math/BigInteger
    //   357: invokevirtual intValue : ()I
    //   360: i2l
    //   361: invokestatic currentTimeMillis : ()J
    //   364: ladd
    //   365: getstatic burp/Zkvr.Zb : Ljava/lang/Object;
    //   368: checkcast java/math/BigInteger
    //   371: invokevirtual intValue : ()I
    //   374: i2l
    //   375: lcmp
    //   376: ifge -> 708
    //   379: sipush #19053
    //   382: sipush #19164
    //   385: invokestatic a : (II)Ljava/lang/String;
    //   388: iconst_1
    //   389: ldc burp/Zlno
    //   391: invokevirtual getClassLoader : ()Ljava/lang/ClassLoader;
    //   394: invokestatic forName : (Ljava/lang/String;ZLjava/lang/ClassLoader;)Ljava/lang/Class;
    //   397: invokevirtual getDeclaredFields : ()[Ljava/lang/reflect/Field;
    //   400: astore_3
    //   401: aload_3
    //   402: arraylength
    //   403: istore #4
    //   405: iconst_0
    //   406: istore #5
    //   408: iload #5
    //   410: iload #4
    //   412: if_icmpge -> 549
    //   415: aload_3
    //   416: iload #5
    //   418: aaload
    //   419: astore #6
    //   421: aload #6
    //   423: invokevirtual getModifiers : ()I
    //   426: invokestatic isStatic : (I)Z
    //   429: ifne -> 439
    //   432: goto -> 542
    //   435: invokestatic a : (Ljava/lang/Throwable;)Ljava/lang/Throwable;
    //   438: athrow
    //   439: aload #6
    //   441: invokevirtual getType : ()Ljava/lang/Class;
    //   444: astore #7
    //   446: aload #7
    //   448: ifnull -> 529
    //   451: aload #7
    //   453: invokevirtual isPrimitive : ()Z
    //   456: ifne -> 529
    //   459: goto -> 466
    //   462: invokestatic a : (Ljava/lang/Throwable;)Ljava/lang/Throwable;
    //   465: athrow
    //   466: aload #7
    //   468: invokevirtual getPackage : ()Ljava/lang/Package;
    //   471: ifnull -> 529
    //   474: goto -> 481
    //   477: invokestatic a : (Ljava/lang/Throwable;)Ljava/lang/Throwable;
    //   480: athrow
    //   481: aload #7
    //   483: invokevirtual getPackage : ()Ljava/lang/Package;
    //   486: invokevirtual getName : ()Ljava/lang/String;
    //   489: ifnull -> 529
    //   492: goto -> 499
    //   495: invokestatic a : (Ljava/lang/Throwable;)Ljava/lang/Throwable;
    //   498: athrow
    //   499: aload #7
    //   501: invokevirtual getPackage : ()Ljava/lang/Package;
    //   504: invokevirtual getName : ()Ljava/lang/String;
    //   507: sipush #19046
    //   510: sipush #-188
    //   513: invokestatic a : (II)Ljava/lang/String;
    //   516: invokevirtual startsWith : (Ljava/lang/String;)Z
    //   519: ifne -> 529
    //   522: goto -> 529
    //   525: invokestatic a : (Ljava/lang/Throwable;)Ljava/lang/Throwable;
    //   528: athrow
    //   529: aload #6
    //   531: iconst_1
    //   532: invokevirtual setAccessible : (Z)V
    //   535: aload #6
    //   537: aconst_null
    //   538: invokevirtual get : (Ljava/lang/Object;)Ljava/lang/Object;
    //   541: pop
    //   542: iinc #5, 1
    //   545: iload_2
    //   546: ifeq -> 408
    //   549: sipush #19052
    //   552: sipush #9415
    //   555: invokestatic a : (II)Ljava/lang/String;
    //   558: invokestatic forName : (Ljava/lang/String;)Ljava/lang/Class;
    //   561: invokevirtual getDeclaredMethods : ()[Ljava/lang/reflect/Method;
    //   564: astore_3
    //   565: aload_3
    //   566: arraylength
    //   567: istore #4
    //   569: iconst_0
    //   570: istore #5
    //   572: iload #5
    //   574: iload #4
    //   576: if_icmpge -> 708
    //   579: aload_3
    //   580: iload #5
    //   582: aaload
    //   583: astore #6
    //   585: aload #6
    //   587: invokevirtual getParameterTypes : ()[Ljava/lang/Class;
    //   590: pop
    //   591: aload #6
    //   593: invokevirtual getModifiers : ()I
    //   596: invokestatic isStatic : (I)Z
    //   599: ifeq -> 694
    //   602: aload #6
    //   604: invokevirtual getParameterTypes : ()[Ljava/lang/Class;
    //   607: arraylength
    //   608: iconst_2
    //   609: if_icmpne -> 694
    //   612: goto -> 619
    //   615: invokestatic a : (Ljava/lang/Throwable;)Ljava/lang/Throwable;
    //   618: athrow
    //   619: aload #6
    //   621: invokevirtual getReturnType : ()Ljava/lang/Class;
    //   624: getstatic java/lang/Void.TYPE : Ljava/lang/Class;
    //   627: invokevirtual equals : (Ljava/lang/Object;)Z
    //   630: ifeq -> 694
    //   633: goto -> 640
    //   636: invokestatic a : (Ljava/lang/Throwable;)Ljava/lang/Throwable;
    //   639: athrow
    //   640: aload #6
    //   642: iconst_1
    //   643: invokevirtual setAccessible : (Z)V
    //   646: aload #6
    //   648: aconst_null
    //   649: iconst_2
    //   650: anewarray java/lang/Object
    //   653: dup
    //   654: iconst_0
    //   655: aload_0
    //   656: aastore
    //   657: dup
    //   658: iconst_1
    //   659: aload_1
    //   660: ifnonnull -> 678
    //   663: goto -> 670
    //   666: invokestatic a : (Ljava/lang/Throwable;)Ljava/lang/Throwable;
    //   669: athrow
    //   670: aload_1
    //   671: goto -> 685
    //   674: invokestatic a : (Ljava/lang/Throwable;)Ljava/lang/Throwable;
    //   677: athrow
    //   678: aload_1
    //   679: checkcast [B
    //   682: invokevirtual clone : ()Ljava/lang/Object;
    //   685: aastore
    //   686: invokevirtual invoke : (Ljava/lang/Object;[Ljava/lang/Object;)Ljava/lang/Object;
    //   689: pop
    //   690: iload_2
    //   691: ifeq -> 708
    //   694: iinc #5, 1
    //   697: iload_2
    //   698: ifeq -> 572
    //   701: goto -> 708
    //   704: invokestatic a : (Ljava/lang/Throwable;)Ljava/lang/Throwable;
    //   707: athrow
    //   708: getstatic burp/Zz9p.ZC : Ljava/lang/String;
    //   711: getstatic burp/Zei_.Za : Ljava/lang/Object;
    //   714: checkcast java/math/BigInteger
    //   717: invokevirtual intValue : ()I
    //   720: bipush #32
    //   722: irem
    //   723: invokestatic abs : (I)I
    //   726: invokevirtual charAt : (I)C
    //   729: getstatic burp/Zmhx.ZD : Ljava/lang/String;
    //   732: getstatic burp/Zead.ZI : Ljava/lang/Object;
    //   735: checkcast java/math/BigInteger
    //   738: invokevirtual intValue : ()I
    //   741: bipush #32
    //   743: irem
    //   744: invokestatic abs : (I)I
    //   747: invokevirtual charAt : (I)C
    //   750: if_icmpgt -> 857
    //   753: getstatic burp/Ze3t.ZG : Ljava/lang/String;
    //   756: getstatic burp/Ztpa.Zv : Ljava/lang/Object;
    //   759: checkcast java/math/BigInteger
    //   762: invokevirtual intValue : ()I
    //   765: bipush #32
    //   767: irem
    //   768: invokestatic abs : (I)I
    //   771: invokevirtual charAt : (I)C
    //   774: getstatic burp/Zmt6.Zx : Ljava/lang/String;
    //   777: getstatic burp/Zmjr.ZU : Ljava/lang/Object;
    //   780: checkcast java/math/BigInteger
    //   783: invokevirtual intValue : ()I
    //   786: bipush #32
    //   788: irem
    //   789: invokestatic abs : (I)I
    //   792: invokevirtual charAt : (I)C
    //   795: if_icmpgt -> 857
    //   798: goto -> 805
    //   801: invokestatic a : (Ljava/lang/Throwable;)Ljava/lang/Throwable;
    //   804: athrow
    //   805: getstatic burp/Zkv2.Z_ : Ljava/lang/String;
    //   808: getstatic burp/Zz67.ZE : Ljava/lang/Object;
    //   811: checkcast java/math/BigInteger
    //   814: invokevirtual intValue : ()I
    //   817: bipush #32
    //   819: irem
    //   820: invokestatic abs : (I)I
    //   823: invokevirtual charAt : (I)C
    //   826: getstatic burp/Zttj.ZN : Ljava/lang/String;
    //   829: getstatic burp/Zm06.ZU : Ljava/lang/Object;
    //   832: checkcast java/math/BigInteger
    //   835: invokevirtual intValue : ()I
    //   838: bipush #32
    //   840: irem
    //   841: invokestatic abs : (I)I
    //   844: invokevirtual charAt : (I)C
    //   847: if_icmple -> 865
    //   850: goto -> 857
    //   853: invokestatic a : (Ljava/lang/Throwable;)Ljava/lang/Throwable;
    //   856: athrow
    //   857: iconst_1
    //   858: goto -> 866
    //   861: invokestatic a : (Ljava/lang/Throwable;)Ljava/lang/Throwable;
    //   864: athrow
    //   865: iconst_0
    //   866: ireturn
    //   867: astore_3
    //   868: new java/lang/Exception
    //   871: dup
    //   872: aload_3
    //   873: invokevirtual getMessage : ()Ljava/lang/String;
    //   876: invokespecial <init> : (Ljava/lang/String;)V
    //   879: athrow
    // Exception table:
    //   from	to	target	type
    //   4	866	867	java/lang/Throwable
    //   64	78	78	java/lang/Throwable
    //   89	102	105	java/lang/Throwable
    //   94	117	120	java/lang/Throwable
    //   109	135	138	java/lang/Throwable
    //   124	165	168	java/lang/Throwable
    //   228	255	258	java/lang/Throwable
    //   245	276	279	java/lang/Throwable
    //   262	306	309	java/lang/Throwable
    //   283	317	317	java/lang/Throwable
    //   328	344	347	java/lang/Throwable
    //   421	435	435	java/lang/Throwable
    //   446	459	462	java/lang/Throwable
    //   451	474	477	java/lang/Throwable
    //   466	492	495	java/lang/Throwable
    //   481	522	525	java/lang/Throwable
    //   585	612	615	java/lang/Throwable
    //   602	633	636	java/lang/Throwable
    //   619	663	666	java/lang/Throwable
    //   640	674	674	java/lang/Throwable
    //   685	701	704	java/lang/Throwable
    //   708	798	801	java/lang/Throwable
    //   753	850	853	java/lang/Throwable
    //   805	861	861	java/lang/Throwable
  }
  
  static void Zw(Object[] paramArrayOfObject, Object paramObject) throws Throwable {}
  
  static void ZF(Object paramObject) {
    Zzy5.ZD = a(19044, -23103);
    Zzy5.ZG = new BigInteger(a(19045, -17322));
    boolean bool = Zt2e.ZK();
    try {
      try {
        if (Zxd0.Zc.charAt(Math.abs(((BigInteger)Zb9k.Zi).intValue() % 32)) <= Zl_9.ZP.charAt(Math.abs(((BigInteger)Zl_9.ZM).intValue() % 32))) {
          try {
            Zlp8.Zs(Class.forName(a(19048, -12450)));
            if (bool)
              Zm06.Zm(Class.forName(a(19047, 19899))); 
          } catch (Throwable throwable) {
            throw a(null);
          } 
          return;
        } 
      } catch (Throwable throwable) {
        throw a(null);
      } 
      Zm06.Zm(Class.forName(a(19047, 19899)));
    } catch (Throwable throwable) {}
  }
  
  static {
    // Byte code:
    //   0: bipush #12
    //   2: anewarray java/lang/String
    //   5: astore #5
    //   7: iconst_0
    //   8: istore_3
    //   9: ldc 'VÃ¯Â=Ã½ÂŒÃ¸Â¾\\tqÃ½kÂšÂµÃ±ÃŒ\\tÃ—ÂºÂ¿Â— Â¨FPÂ \\tÂ¢!Ã¤Ã•Ã†Ã¼ÂÃ·K=@ÂŸ"ÃžÂ\\bWs$Â¤9nbÂ¾Â’ÃÃ¢g\\fÂ²ÂˆÃ—Âˆ\\nÃºjgÃ¯Ã–DÃ½Ã›Ã…Â˜Â´h\Ã›Â»7pÂœÂ¶Ã¼Â£Â¡Ã»Ã¶Â¤*wÃ—Ã—sÃ¼vÂŒÂ¸"WÂ†3&Ã‚Ã‹\\fÂš\\toÃ³Â¨Â¾Ã¢ÂÃ%LÂ¦I Ã»ÂŸqWÃ²iFÂ„Ã²ÂŽDÂ Ã†NÂ›ÃµÂ‘L\ÂˆÂŸ1Â¦Ã„CmÂ«Â¤MÂ®4Ã¨Ã‹Âœc'UÃ˜ÃÂ¹Â€ÂÃ°ÂƒG[ÂÂŸ-ÃŸ6ÃkRÃ’Â´WaÃ¹`}wÃ´Â«h-fÃ¢tÂ­iÂ¬Â—Ã@Ã¹Ã‰Ã«dvh;G]5Â¦ÃƒÃ‰Ã¤Ã™No"_Â®Â€Ãº[Â… t:Â Â¶#0Â‰Ã˜Â¨Â¼Â»Â”ÃšIÂÂ–Â›RÂ›wÃ˜neEMÂ°Ã’'
    //   11: dup
    //   12: astore_2
    //   13: invokevirtual length : ()I
    //   16: istore #4
    //   18: bipush #9
    //   20: istore_1
    //   21: iconst_m1
    //   22: istore_0
    //   23: bipush #105
    //   25: iinc #0, 1
    //   28: aload_2
    //   29: iload_0
    //   30: dup
    //   31: iload_1
    //   32: iadd
    //   33: invokevirtual substring : (II)Ljava/lang/String;
    //   36: iconst_m1
    //   37: goto -> 143
    //   40: aload #5
    //   42: swap
    //   43: iload_3
    //   44: iinc #3, 1
    //   47: swap
    //   48: aastore
    //   49: iload_0
    //   50: iload_1
    //   51: iadd
    //   52: dup
    //   53: istore_0
    //   54: iload #4
    //   56: if_icmpge -> 68
    //   59: aload_2
    //   60: iload_0
    //   61: invokevirtual charAt : (I)C
    //   64: istore_1
    //   65: goto -> 23
    //   68: ldc '\\bÂµÂ£Â‘dÂ:+Ã±Â•ÂœÂ•'
    //   70: dup
    //   71: astore_2
    //   72: invokevirtual length : ()I
    //   75: istore #4
    //   77: bipush #9
    //   79: istore_1
    //   80: iconst_m1
    //   81: istore_0
    //   82: bipush #110
    //   84: iinc #0, 1
    //   87: aload_2
    //   88: iload_0
    //   89: dup
    //   90: iload_1
    //   91: iadd
    //   92: invokevirtual substring : (II)Ljava/lang/String;
    //   95: iconst_0
    //   96: goto -> 143
    //   99: aload #5
    //   101: swap
    //   102: iload_3
    //   103: iinc #3, 1
    //   106: swap
    //   107: aastore
    //   108: iload_0
    //   109: iload_1
    //   110: iadd
    //   111: dup
    //   112: istore_0
    //   113: iload #4
    //   115: if_icmpge -> 127
    //   118: aload_2
    //   119: iload_0
    //   120: invokevirtual charAt : (I)C
    //   123: istore_1
    //   124: goto -> 82
    //   127: aload #5
    //   129: putstatic burp/Zlno.a : [Ljava/lang/String;
    //   132: bipush #12
    //   134: anewarray java/lang/String
    //   137: putstatic burp/Zlno.b : [Ljava/lang/String;
    //   140: goto -> 300
    //   143: dup_x2
    //   144: pop
    //   145: invokevirtual toCharArray : ()[C
    //   148: dup_x1
    //   149: arraylength
    //   150: dup_x2
    //   151: pop
    //   152: iconst_0
    //   153: istore #6
    //   155: dup2_x1
    //   156: pop2
    //   157: dup_x2
    //   158: iconst_1
    //   159: if_icmpgt -> 259
    //   162: dup2
    //   163: swap
    //   164: iload #6
    //   166: dup2_x1
    //   167: caload
    //   168: swap
    //   169: iload #6
    //   171: bipush #7
    //   173: irem
    //   174: tableswitch default -> 241, 0 -> 212, 1 -> 216, 2 -> 221, 3 -> 226, 4 -> 231, 5 -> 236
    //   212: iconst_1
    //   213: goto -> 243
    //   216: bipush #57
    //   218: goto -> 243
    //   221: bipush #125
    //   223: goto -> 243
    //   226: bipush #8
    //   228: goto -> 243
    //   231: bipush #14
    //   233: goto -> 243
    //   236: bipush #59
    //   238: goto -> 243
    //   241: bipush #90
    //   243: ixor
    //   244: ixor
    //   245: i2c
    //   246: castore
    //   247: iinc #6, 1
    //   250: dup
    //   251: ifne -> 259
    //   254: dup2
    //   255: dup_x1
    //   256: goto -> 166
    //   259: dup2_x1
    //   260: pop2
    //   261: dup_x2
    //   262: iload #6
    //   264: if_icmpgt -> 162
    //   267: pop
    //   268: new java/lang/String
    //   271: dup_x1
    //   272: swap
    //   273: invokespecial <init> : ([C)V
    //   276: invokevirtual intern : ()Ljava/lang/String;
    //   279: swap
    //   280: pop
    //   281: swap
    //   282: tableswitch default -> 40, 0 -> 99
    //   300: new java/math/BigInteger
    //   303: dup
    //   304: sipush #19049
    //   307: sipush #-25121
    //   310: invokestatic a : (II)Ljava/lang/String;
    //   313: invokespecial <init> : (Ljava/lang/String;)V
    //   316: putstatic burp/Zlno.ZU : Ljava/lang/Object;
    //   319: sipush #19050
    //   322: sipush #-25452
    //   325: invokestatic a : (II)Ljava/lang/String;
    //   328: putstatic burp/Zlno.ZM : Ljava/lang/String;
    //   331: return
  }
  
  private static Throwable a(Throwable paramThrowable) {
    return paramThrowable;
  }
  
  private static String a(int paramInt1, int paramInt2) {
    int i = (paramInt1 ^ 0x4A6D) & 0xFFFF;
    if (b[i] == null) {
      char[] arrayOfChar = a[i].toCharArray();
      switch (arrayOfChar[0] & 0xFF) {
        case 0:
        
        case 1:
        
        case 2:
        
        case 3:
        
        case 4:
        
        case 5:
        
        case 6:
        
        case 7:
        
        case 8:
        
        case 9:
        
        case 10:
        
        case 11:
        
        case 12:
        
        case 13:
        
        case 14:
        
        case 15:
        
        case 16:
        
        case 17:
        
        case 18:
        
        case 19:
        
        case 20:
        
        case 21:
        
        case 22:
        
        case 23:
        
        case 24:
        
        case 25:
        
        case 26:
        
        case 27:
        
        case 28:
        
        case 29:
        
        case 30:
        
        case 31:
        
        case 32:
        
        case 33:
        
        case 34:
        
        case 35:
        
        case 36:
        
        case 37:
        
        case 38:
        
        case 39:
        
        case 40:
        
        case 41:
        
        case 42:
        
        case 43:
        
        case 44:
        
        case 45:
        
        case 46:
        
        case 47:
        
        case 48:
        
        case 49:
        
        case 50:
        
        case 51:
        
        case 52:
        
        case 53:
        
        case 54:
        
        case 55:
        
        case 56:
        
        case 57:
        
        case 58:
        
        case 59:
        
        case 60:
        
        case 61:
        
        case 62:
        
        case 63:
        
        case 64:
        
        case 65:
        
        case 66:
        
        case 67:
        
        case 68:
        
        case 69:
        
        case 70:
        
        case 71:
        
        case 72:
        
        case 73:
        
        case 74:
        
        case 75:
        
        case 76:
        
        case 77:
        
        case 78:
        
        case 79:
        
        case 80:
        
        case 81:
        
        case 82:
        
        case 83:
        
        case 84:
        
        case 85:
        
        case 86:
        
        case 87:
        
        case 88:
        
        case 89:
        
        case 90:
        
        case 91:
        
        case 92:
        
        case 93:
        
        case 94:
        
        case 95:
        
        case 96:
        
        case 97:
        
        case 98:
        
        case 99:
        
        case 100:
        
        case 101:
        
        case 102:
        
        case 103:
        
        case 104:
        
        case 105:
        
        case 106:
        
        case 107:
        
        case 108:
        
        case 109:
        
        case 110:
        
        case 111:
        
        case 112:
        
        case 113:
        
        case 114:
        
        case 115:
        
        case 116:
        
        case 117:
        
        case 118:
        
        case 119:
        
        case 120:
        
        case 121:
        
        case 122:
        
        case 123:
        
        case 124:
        
        case 125:
        
        case 126:
        
        case 127:
        
        case 128:
        
        case 129:
        
        case 130:
        
        case 131:
        
        case 132:
        
        case 133:
        
        case 134:
        
        case 135:
        
        case 136:
        
        case 137:
        
        case 138:
        
        case 139:
        
        case 140:
        
        case 141:
        
        case 142:
        
        case 143:
        
        case 144:
        
        case 145:
        
        case 146:
        
        case 147:
        
        case 148:
        
        case 149:
        
        case 150:
        
        case 151:
        
        case 152:
        
        case 153:
        
        case 154:
        
        case 155:
        
        case 156:
        
        case 157:
        
        case 158:
        
        case 159:
        
        case 160:
        
        case 161:
        
        case 162:
        
        case 163:
        
        case 164:
        
        case 165:
        
        case 166:
        
        case 167:
        
        case 168:
        
        case 169:
        
        case 170:
        
        case 171:
        
        case 172:
        
        case 173:
        
        case 174:
        
        case 175:
        
        case 176:
        
        case 177:
        
        case 178:
        
        case 179:
        
        case 180:
        
        case 181:
        
        case 182:
        
        case 183:
        
        case 184:
        
        case 185:
        
        case 186:
        
        case 187:
        
        case 188:
        
        case 189:
        
        case 190:
        
        case 191:
        
        case 192:
        
        case 193:
        
        case 194:
        
        case 195:
        
        case 196:
        
        case 197:
        
        case 198:
        
        case 199:
        
        case 200:
        
        case 201:
        
        case 202:
        
        case 203:
        
        case 204:
        
        case 205:
        
        case 206:
        
        case 207:
        
        case 208:
        
        case 209:
        
        case 210:
        
        case 211:
        
        case 212:
        
        case 213:
        
        case 214:
        
        case 215:
        
        case 216:
        
        case 217:
        
        case 218:
        
        case 219:
        
        case 220:
        
        case 221:
        
        case 222:
        
        case 223:
        
        case 224:
        
        case 225:
        
        case 226:
        
        case 227:
        
        case 228:
        
        case 229:
        
        case 230:
        
        case 231:
        
        case 232:
        
        case 233:
        
        case 234:
        
        case 235:
        
        case 236:
        
        case 237:
        
        case 238:
        
        case 239:
        
        case 240:
        
        case 241:
        
        case 242:
        
        case 243:
        
        case 244:
        
        case 245:
        
        case 246:
        
        case 247:
        
        case 248:
        
        case 249:
        
        case 250:
        
        case 251:
        
        case 252:
        
        case 253:
        
        case 254:
        
        default:
          break;
      } 
      char c = 'Â­';
      int j = (paramInt2 & 0xFF) - c;
      if (j < 0)
        j += 256; 
      int k = ((paramInt2 & 0xFFFF) >>> 8) - c;
      if (k < 0)
        k += 256; 
      for (byte b = 0; b < arrayOfChar.length; b++) {
        int m = b % 2;
        if (m == 0) {
          arrayOfChar[b] = (char)(arrayOfChar[b] ^ j);
          j = ((j >>> 3 | j << 5) ^ arrayOfChar[b]) & 0xFF;
        } else {
          arrayOfChar[b] = (char)(arrayOfChar[b] ^ k);
          k = ((k >>> 3 | k << 5) ^ arrayOfChar[b]) & 0xFF;
        } 
      } 
      b[i] = (new String(arrayOfChar)).intern();
    } 
    return b[i];
  }
}


/* Location:              C:\Program Files\BurpSuitePro\burpsuite_pro.jar!\burp\Zlno.class
 * Java compiler version: 21 (65.0)
 * JD-Core Version:       1.1.3
 */