package burp;

class Zlqe implements Zg90 {
  private final Zbkv ZP;
  
  private final Zgtp ZT;
  
  private Zgu3 Ze;
  
  Zlqe(Zbkv paramZbkv, Zgtp paramZgtp) {
    this.ZP = paramZbkv;
    this.ZT = paramZgtp;
  }
  
  void Zp(Zgu3 paramZgu3) {
    this.Ze = paramZgu3;
  }
  
  public void Zf(int[] paramArrayOfint) {
    // Byte code:
    //   0: invokestatic ZM : ()[I
    //   3: astore_2
    //   4: aload_0
    //   5: getfield Ze : Lburp/Zgu3;
    //   8: ifnonnull -> 12
    //   11: return
    //   12: getstatic burp/Zr3g.Z_ : [I
    //   15: aload_0
    //   16: getfield Ze : Lburp/Zgu3;
    //   19: invokevirtual ordinal : ()I
    //   22: iaload
    //   23: tableswitch default -> 125, 1 -> 48, 2 -> 74, 3 -> 100
    //   48: aload_0
    //   49: getfield ZT : Lburp/Zgtp;
    //   52: aload_1
    //   53: iconst_0
    //   54: iaload
    //   55: aload_1
    //   56: iconst_1
    //   57: iaload
    //   58: aload_0
    //   59: getfield ZP : Lburp/Zbkv;
    //   62: invokevirtual Zy : ()Ljava/lang/String;
    //   65: invokeinterface Zj : (IILjava/lang/String;)V
    //   70: aload_2
    //   71: ifnull -> 125
    //   74: aload_0
    //   75: getfield ZT : Lburp/Zgtp;
    //   78: aload_1
    //   79: iconst_0
    //   80: iaload
    //   81: aload_1
    //   82: iconst_1
    //   83: iaload
    //   84: aload_0
    //   85: getfield ZP : Lburp/Zbkv;
    //   88: invokevirtual Zy : ()Ljava/lang/String;
    //   91: invokeinterface ZO : (IILjava/lang/String;)V
    //   96: aload_2
    //   97: ifnull -> 125
    //   100: aload_0
    //   101: getfield ZT : Lburp/Zgtp;
    //   104: aload_1
    //   105: iconst_0
    //   106: iaload
    //   107: aload_1
    //   108: iconst_1
    //   109: iaload
    //   110: aload_0
    //   111: getfield ZP : Lburp/Zbkv;
    //   114: invokevirtual Zy : ()Ljava/lang/String;
    //   117: invokeinterface Zz : (IILjava/lang/String;)V
    //   122: goto -> 125
    //   125: return
  }
}


/* Location:              C:\Program Files\BurpSuitePro\burpsuite_pro.jar!\burp\Zlqe.class
 * Java compiler version: 21 (65.0)
 * JD-Core Version:       1.1.3
 */