package burp;

import java.math.BigInteger;

class Zlsw extends ClassLoader {
  static Object ZJ;
  
  static String ZE;
  
  private static final String[] a;
  
  private static final String[] b;
  
  static void Zi(Object[] paramArrayOfObject, Object paramObject) throws Throwable {}
  
  static boolean ZQ(Object[] paramArrayOfObject, Object paramObject) throws Throwable {
    // Byte code:
    //   0: invokestatic ZK : ()Z
    //   3: istore_2
    //   4: new java/lang/StringBuilder
    //   7: dup
    //   8: invokespecial <init> : ()V
    //   11: astore_3
    //   12: iconst_0
    //   13: istore #4
    //   15: iload #4
    //   17: bipush #32
    //   19: if_icmpge -> 1355
    //   22: iload #4
    //   24: tableswitch default -> 1348, 0 -> 168, 1 -> 205, 2 -> 242, 3 -> 279, 4 -> 316, 5 -> 353, 6 -> 390, 7 -> 427, 8 -> 464, 9 -> 501, 10 -> 538, 11 -> 575, 12 -> 612, 13 -> 649, 14 -> 686, 15 -> 723, 16 -> 760, 17 -> 797, 18 -> 834, 19 -> 871, 20 -> 908, 21 -> 945, 22 -> 982, 23 -> 1019, 24 -> 1056, 25 -> 1093, 26 -> 1130, 27 -> 1167, 28 -> 1204, 29 -> 1241, 30 -> 1278, 31 -> 1315
    //   168: aload_3
    //   169: getstatic burp/Zrod.ZQ : Ljava/lang/String;
    //   172: getstatic burp/Zb0z.ZQ : Ljava/lang/Object;
    //   175: checkcast java/math/BigInteger
    //   178: invokevirtual intValue : ()I
    //   181: bipush #32
    //   183: irem
    //   184: invokestatic abs : (I)I
    //   187: invokevirtual charAt : (I)C
    //   190: invokevirtual append : (C)Ljava/lang/StringBuilder;
    //   193: pop
    //   194: iload_2
    //   195: ifeq -> 1348
    //   198: goto -> 205
    //   201: invokestatic a : (Ljava/lang/Throwable;)Ljava/lang/Throwable;
    //   204: athrow
    //   205: aload_3
    //   206: getstatic burp/Zmzh.Zm : Ljava/lang/String;
    //   209: getstatic burp/Zbzc.Zp : Ljava/lang/Object;
    //   212: checkcast java/math/BigInteger
    //   215: invokevirtual intValue : ()I
    //   218: bipush #32
    //   220: irem
    //   221: invokestatic abs : (I)I
    //   224: invokevirtual charAt : (I)C
    //   227: invokevirtual append : (C)Ljava/lang/StringBuilder;
    //   230: pop
    //   231: iload_2
    //   232: ifeq -> 1348
    //   235: goto -> 242
    //   238: invokestatic a : (Ljava/lang/Throwable;)Ljava/lang/Throwable;
    //   241: athrow
    //   242: aload_3
    //   243: getstatic burp/Zmpp.Zk : Ljava/lang/String;
    //   246: getstatic burp/Zejj.Zy : Ljava/lang/Object;
    //   249: checkcast java/math/BigInteger
    //   252: invokevirtual intValue : ()I
    //   255: bipush #32
    //   257: irem
    //   258: invokestatic abs : (I)I
    //   261: invokevirtual charAt : (I)C
    //   264: invokevirtual append : (C)Ljava/lang/StringBuilder;
    //   267: pop
    //   268: iload_2
    //   269: ifeq -> 1348
    //   272: goto -> 279
    //   275: invokestatic a : (Ljava/lang/Throwable;)Ljava/lang/Throwable;
    //   278: athrow
    //   279: aload_3
    //   280: getstatic burp/Zzxv.Z_ : Ljava/lang/String;
    //   283: getstatic burp/Zlps.ZU : Ljava/lang/Object;
    //   286: checkcast java/math/BigInteger
    //   289: invokevirtual intValue : ()I
    //   292: bipush #32
    //   294: irem
    //   295: invokestatic abs : (I)I
    //   298: invokevirtual charAt : (I)C
    //   301: invokevirtual append : (C)Ljava/lang/StringBuilder;
    //   304: pop
    //   305: iload_2
    //   306: ifeq -> 1348
    //   309: goto -> 316
    //   312: invokestatic a : (Ljava/lang/Throwable;)Ljava/lang/Throwable;
    //   315: athrow
    //   316: aload_3
    //   317: getstatic burp/Zzbr.Zp : Ljava/lang/String;
    //   320: getstatic burp/Zxpb.Zo : Ljava/lang/Object;
    //   323: checkcast java/math/BigInteger
    //   326: invokevirtual intValue : ()I
    //   329: bipush #32
    //   331: irem
    //   332: invokestatic abs : (I)I
    //   335: invokevirtual charAt : (I)C
    //   338: invokevirtual append : (C)Ljava/lang/StringBuilder;
    //   341: pop
    //   342: iload_2
    //   343: ifeq -> 1348
    //   346: goto -> 353
    //   349: invokestatic a : (Ljava/lang/Throwable;)Ljava/lang/Throwable;
    //   352: athrow
    //   353: aload_3
    //   354: getstatic burp/Zx_x.Zv : Ljava/lang/String;
    //   357: getstatic burp/Zzrb.Zj : Ljava/lang/Object;
    //   360: checkcast java/math/BigInteger
    //   363: invokevirtual intValue : ()I
    //   366: bipush #32
    //   368: irem
    //   369: invokestatic abs : (I)I
    //   372: invokevirtual charAt : (I)C
    //   375: invokevirtual append : (C)Ljava/lang/StringBuilder;
    //   378: pop
    //   379: iload_2
    //   380: ifeq -> 1348
    //   383: goto -> 390
    //   386: invokestatic a : (Ljava/lang/Throwable;)Ljava/lang/Throwable;
    //   389: athrow
    //   390: aload_3
    //   391: getstatic burp/Zb2k.Zu : Ljava/lang/String;
    //   394: getstatic burp/Zxpb.Zo : Ljava/lang/Object;
    //   397: checkcast java/math/BigInteger
    //   400: invokevirtual intValue : ()I
    //   403: bipush #32
    //   405: irem
    //   406: invokestatic abs : (I)I
    //   409: invokevirtual charAt : (I)C
    //   412: invokevirtual append : (C)Ljava/lang/StringBuilder;
    //   415: pop
    //   416: iload_2
    //   417: ifeq -> 1348
    //   420: goto -> 427
    //   423: invokestatic a : (Ljava/lang/Throwable;)Ljava/lang/Throwable;
    //   426: athrow
    //   427: aload_3
    //   428: getstatic burp/Zbp_.ZQ : Ljava/lang/String;
    //   431: getstatic burp/Zscs.Zg : Ljava/lang/Object;
    //   434: checkcast java/math/BigInteger
    //   437: invokevirtual intValue : ()I
    //   440: bipush #32
    //   442: irem
    //   443: invokestatic abs : (I)I
    //   446: invokevirtual charAt : (I)C
    //   449: invokevirtual append : (C)Ljava/lang/StringBuilder;
    //   452: pop
    //   453: iload_2
    //   454: ifeq -> 1348
    //   457: goto -> 464
    //   460: invokestatic a : (Ljava/lang/Throwable;)Ljava/lang/Throwable;
    //   463: athrow
    //   464: aload_3
    //   465: getstatic burp/Zlna.Zo : Ljava/lang/String;
    //   468: getstatic burp/Zldt.ZS : Ljava/lang/Object;
    //   471: checkcast java/math/BigInteger
    //   474: invokevirtual intValue : ()I
    //   477: bipush #32
    //   479: irem
    //   480: invokestatic abs : (I)I
    //   483: invokevirtual charAt : (I)C
    //   486: invokevirtual append : (C)Ljava/lang/StringBuilder;
    //   489: pop
    //   490: iload_2
    //   491: ifeq -> 1348
    //   494: goto -> 501
    //   497: invokestatic a : (Ljava/lang/Throwable;)Ljava/lang/Throwable;
    //   500: athrow
    //   501: aload_3
    //   502: getstatic burp/Zztz.Zp : Ljava/lang/String;
    //   505: getstatic burp/Zx8t.ZA : Ljava/lang/Object;
    //   508: checkcast java/math/BigInteger
    //   511: invokevirtual intValue : ()I
    //   514: bipush #32
    //   516: irem
    //   517: invokestatic abs : (I)I
    //   520: invokevirtual charAt : (I)C
    //   523: invokevirtual append : (C)Ljava/lang/StringBuilder;
    //   526: pop
    //   527: iload_2
    //   528: ifeq -> 1348
    //   531: goto -> 538
    //   534: invokestatic a : (Ljava/lang/Throwable;)Ljava/lang/Throwable;
    //   537: athrow
    //   538: aload_3
    //   539: getstatic burp/Zr04.ZA : Ljava/lang/String;
    //   542: getstatic burp/Znp.ZJ : Ljava/lang/Object;
    //   545: checkcast java/math/BigInteger
    //   548: invokevirtual intValue : ()I
    //   551: bipush #32
    //   553: irem
    //   554: invokestatic abs : (I)I
    //   557: invokevirtual charAt : (I)C
    //   560: invokevirtual append : (C)Ljava/lang/StringBuilder;
    //   563: pop
    //   564: iload_2
    //   565: ifeq -> 1348
    //   568: goto -> 575
    //   571: invokestatic a : (Ljava/lang/Throwable;)Ljava/lang/Throwable;
    //   574: athrow
    //   575: aload_3
    //   576: getstatic burp/Zzou.ZN : Ljava/lang/String;
    //   579: getstatic burp/Zr04.ZB : Ljava/lang/Object;
    //   582: checkcast java/math/BigInteger
    //   585: invokevirtual intValue : ()I
    //   588: bipush #32
    //   590: irem
    //   591: invokestatic abs : (I)I
    //   594: invokevirtual charAt : (I)C
    //   597: invokevirtual append : (C)Ljava/lang/StringBuilder;
    //   600: pop
    //   601: iload_2
    //   602: ifeq -> 1348
    //   605: goto -> 612
    //   608: invokestatic a : (Ljava/lang/Throwable;)Ljava/lang/Throwable;
    //   611: athrow
    //   612: aload_3
    //   613: getstatic burp/Zkf9.ZS : Ljava/lang/String;
    //   616: getstatic burp/Zgt7.Zn : Ljava/lang/Object;
    //   619: checkcast java/math/BigInteger
    //   622: invokevirtual intValue : ()I
    //   625: bipush #32
    //   627: irem
    //   628: invokestatic abs : (I)I
    //   631: invokevirtual charAt : (I)C
    //   634: invokevirtual append : (C)Ljava/lang/StringBuilder;
    //   637: pop
    //   638: iload_2
    //   639: ifeq -> 1348
    //   642: goto -> 649
    //   645: invokestatic a : (Ljava/lang/Throwable;)Ljava/lang/Throwable;
    //   648: athrow
    //   649: aload_3
    //   650: getstatic burp/Zlsw.ZE : Ljava/lang/String;
    //   653: getstatic burp/Zro5.ZT : Ljava/lang/Object;
    //   656: checkcast java/math/BigInteger
    //   659: invokevirtual intValue : ()I
    //   662: bipush #32
    //   664: irem
    //   665: invokestatic abs : (I)I
    //   668: invokevirtual charAt : (I)C
    //   671: invokevirtual append : (C)Ljava/lang/StringBuilder;
    //   674: pop
    //   675: iload_2
    //   676: ifeq -> 1348
    //   679: goto -> 686
    //   682: invokestatic a : (Ljava/lang/Throwable;)Ljava/lang/Throwable;
    //   685: athrow
    //   686: aload_3
    //   687: getstatic burp/Zx8t.Zi : Ljava/lang/String;
    //   690: getstatic burp/Ztys.Zs : Ljava/lang/Object;
    //   693: checkcast java/math/BigInteger
    //   696: invokevirtual intValue : ()I
    //   699: bipush #32
    //   701: irem
    //   702: invokestatic abs : (I)I
    //   705: invokevirtual charAt : (I)C
    //   708: invokevirtual append : (C)Ljava/lang/StringBuilder;
    //   711: pop
    //   712: iload_2
    //   713: ifeq -> 1348
    //   716: goto -> 723
    //   719: invokestatic a : (Ljava/lang/Throwable;)Ljava/lang/Throwable;
    //   722: athrow
    //   723: aload_3
    //   724: getstatic burp/Zmt7.Zl : Ljava/lang/String;
    //   727: getstatic burp/Zlb6.Zz : Ljava/lang/Object;
    //   730: checkcast java/math/BigInteger
    //   733: invokevirtual intValue : ()I
    //   736: bipush #32
    //   738: irem
    //   739: invokestatic abs : (I)I
    //   742: invokevirtual charAt : (I)C
    //   745: invokevirtual append : (C)Ljava/lang/StringBuilder;
    //   748: pop
    //   749: iload_2
    //   750: ifeq -> 1348
    //   753: goto -> 760
    //   756: invokestatic a : (Ljava/lang/Throwable;)Ljava/lang/Throwable;
    //   759: athrow
    //   760: aload_3
    //   761: getstatic burp/Zg2.ZN : Ljava/lang/String;
    //   764: getstatic burp/Znp.ZJ : Ljava/lang/Object;
    //   767: checkcast java/math/BigInteger
    //   770: invokevirtual intValue : ()I
    //   773: bipush #32
    //   775: irem
    //   776: invokestatic abs : (I)I
    //   779: invokevirtual charAt : (I)C
    //   782: invokevirtual append : (C)Ljava/lang/StringBuilder;
    //   785: pop
    //   786: iload_2
    //   787: ifeq -> 1348
    //   790: goto -> 797
    //   793: invokestatic a : (Ljava/lang/Throwable;)Ljava/lang/Throwable;
    //   796: athrow
    //   797: aload_3
    //   798: getstatic burp/Zmrc.Zx : Ljava/lang/String;
    //   801: getstatic burp/Zss6.ZG : Ljava/lang/Object;
    //   804: checkcast java/math/BigInteger
    //   807: invokevirtual intValue : ()I
    //   810: bipush #32
    //   812: irem
    //   813: invokestatic abs : (I)I
    //   816: invokevirtual charAt : (I)C
    //   819: invokevirtual append : (C)Ljava/lang/StringBuilder;
    //   822: pop
    //   823: iload_2
    //   824: ifeq -> 1348
    //   827: goto -> 834
    //   830: invokestatic a : (Ljava/lang/Throwable;)Ljava/lang/Throwable;
    //   833: athrow
    //   834: aload_3
    //   835: getstatic burp/Zscs.Zw : Ljava/lang/String;
    //   838: getstatic burp/Zlsw.ZJ : Ljava/lang/Object;
    //   841: checkcast java/math/BigInteger
    //   844: invokevirtual intValue : ()I
    //   847: bipush #32
    //   849: irem
    //   850: invokestatic abs : (I)I
    //   853: invokevirtual charAt : (I)C
    //   856: invokevirtual append : (C)Ljava/lang/StringBuilder;
    //   859: pop
    //   860: iload_2
    //   861: ifeq -> 1348
    //   864: goto -> 871
    //   867: invokestatic a : (Ljava/lang/Throwable;)Ljava/lang/Throwable;
    //   870: athrow
    //   871: aload_3
    //   872: getstatic burp/Zzs9.Zg : Ljava/lang/String;
    //   875: getstatic burp/Zl8y.ZD : Ljava/lang/Object;
    //   878: checkcast java/math/BigInteger
    //   881: invokevirtual intValue : ()I
    //   884: bipush #32
    //   886: irem
    //   887: invokestatic abs : (I)I
    //   890: invokevirtual charAt : (I)C
    //   893: invokevirtual append : (C)Ljava/lang/StringBuilder;
    //   896: pop
    //   897: iload_2
    //   898: ifeq -> 1348
    //   901: goto -> 908
    //   904: invokestatic a : (Ljava/lang/Throwable;)Ljava/lang/Throwable;
    //   907: athrow
    //   908: aload_3
    //   909: getstatic burp/Zzbr.Zp : Ljava/lang/String;
    //   912: getstatic burp/Zzxs.Zg : Ljava/lang/Object;
    //   915: checkcast java/math/BigInteger
    //   918: invokevirtual intValue : ()I
    //   921: bipush #32
    //   923: irem
    //   924: invokestatic abs : (I)I
    //   927: invokevirtual charAt : (I)C
    //   930: invokevirtual append : (C)Ljava/lang/StringBuilder;
    //   933: pop
    //   934: iload_2
    //   935: ifeq -> 1348
    //   938: goto -> 945
    //   941: invokestatic a : (Ljava/lang/Throwable;)Ljava/lang/Throwable;
    //   944: athrow
    //   945: aload_3
    //   946: getstatic burp/Zb2k.Zu : Ljava/lang/String;
    //   949: getstatic burp/Zeb3.Zb : Ljava/lang/Object;
    //   952: checkcast java/math/BigInteger
    //   955: invokevirtual intValue : ()I
    //   958: bipush #32
    //   960: irem
    //   961: invokestatic abs : (I)I
    //   964: invokevirtual charAt : (I)C
    //   967: invokevirtual append : (C)Ljava/lang/StringBuilder;
    //   970: pop
    //   971: iload_2
    //   972: ifeq -> 1348
    //   975: goto -> 982
    //   978: invokestatic a : (Ljava/lang/Throwable;)Ljava/lang/Throwable;
    //   981: athrow
    //   982: aload_3
    //   983: getstatic burp/Zefm.ZK : Ljava/lang/String;
    //   986: getstatic burp/Zzs9.ZO : Ljava/lang/Object;
    //   989: checkcast java/math/BigInteger
    //   992: invokevirtual intValue : ()I
    //   995: bipush #32
    //   997: irem
    //   998: invokestatic abs : (I)I
    //   1001: invokevirtual charAt : (I)C
    //   1004: invokevirtual append : (C)Ljava/lang/StringBuilder;
    //   1007: pop
    //   1008: iload_2
    //   1009: ifeq -> 1348
    //   1012: goto -> 1019
    //   1015: invokestatic a : (Ljava/lang/Throwable;)Ljava/lang/Throwable;
    //   1018: athrow
    //   1019: aload_3
    //   1020: getstatic burp/Zscs.Zw : Ljava/lang/String;
    //   1023: getstatic burp/Znp.ZJ : Ljava/lang/Object;
    //   1026: checkcast java/math/BigInteger
    //   1029: invokevirtual intValue : ()I
    //   1032: bipush #32
    //   1034: irem
    //   1035: invokestatic abs : (I)I
    //   1038: invokevirtual charAt : (I)C
    //   1041: invokevirtual append : (C)Ljava/lang/StringBuilder;
    //   1044: pop
    //   1045: iload_2
    //   1046: ifeq -> 1348
    //   1049: goto -> 1056
    //   1052: invokestatic a : (Ljava/lang/Throwable;)Ljava/lang/Throwable;
    //   1055: athrow
    //   1056: aload_3
    //   1057: getstatic burp/Zbzc.ZL : Ljava/lang/String;
    //   1060: getstatic burp/Zb2k.ZZ : Ljava/lang/Object;
    //   1063: checkcast java/math/BigInteger
    //   1066: invokevirtual intValue : ()I
    //   1069: bipush #32
    //   1071: irem
    //   1072: invokestatic abs : (I)I
    //   1075: invokevirtual charAt : (I)C
    //   1078: invokevirtual append : (C)Ljava/lang/StringBuilder;
    //   1081: pop
    //   1082: iload_2
    //   1083: ifeq -> 1348
    //   1086: goto -> 1093
    //   1089: invokestatic a : (Ljava/lang/Throwable;)Ljava/lang/Throwable;
    //   1092: athrow
    //   1093: aload_3
    //   1094: getstatic burp/Zgt7.ZO : Ljava/lang/String;
    //   1097: getstatic burp/Zeor.Zb : Ljava/lang/Object;
    //   1100: checkcast java/math/BigInteger
    //   1103: invokevirtual intValue : ()I
    //   1106: bipush #32
    //   1108: irem
    //   1109: invokestatic abs : (I)I
    //   1112: invokevirtual charAt : (I)C
    //   1115: invokevirtual append : (C)Ljava/lang/StringBuilder;
    //   1118: pop
    //   1119: iload_2
    //   1120: ifeq -> 1348
    //   1123: goto -> 1130
    //   1126: invokestatic a : (Ljava/lang/Throwable;)Ljava/lang/Throwable;
    //   1129: athrow
    //   1130: aload_3
    //   1131: getstatic burp/Zlps.ZO : Ljava/lang/String;
    //   1134: getstatic burp/Ztd3.ZX : Ljava/lang/Object;
    //   1137: checkcast java/math/BigInteger
    //   1140: invokevirtual intValue : ()I
    //   1143: bipush #32
    //   1145: irem
    //   1146: invokestatic abs : (I)I
    //   1149: invokevirtual charAt : (I)C
    //   1152: invokevirtual append : (C)Ljava/lang/StringBuilder;
    //   1155: pop
    //   1156: iload_2
    //   1157: ifeq -> 1348
    //   1160: goto -> 1167
    //   1163: invokestatic a : (Ljava/lang/Throwable;)Ljava/lang/Throwable;
    //   1166: athrow
    //   1167: aload_3
    //   1168: getstatic burp/Zeqo.Zw : Ljava/lang/String;
    //   1171: getstatic burp/Zrod.ZX : Ljava/lang/Object;
    //   1174: checkcast java/math/BigInteger
    //   1177: invokevirtual intValue : ()I
    //   1180: bipush #32
    //   1182: irem
    //   1183: invokestatic abs : (I)I
    //   1186: invokevirtual charAt : (I)C
    //   1189: invokevirtual append : (C)Ljava/lang/StringBuilder;
    //   1192: pop
    //   1193: iload_2
    //   1194: ifeq -> 1348
    //   1197: goto -> 1204
    //   1200: invokestatic a : (Ljava/lang/Throwable;)Ljava/lang/Throwable;
    //   1203: athrow
    //   1204: aload_3
    //   1205: getstatic burp/Zzok.ZC : Ljava/lang/String;
    //   1208: getstatic burp/Zlps.ZU : Ljava/lang/Object;
    //   1211: checkcast java/math/BigInteger
    //   1214: invokevirtual intValue : ()I
    //   1217: bipush #32
    //   1219: irem
    //   1220: invokestatic abs : (I)I
    //   1223: invokevirtual charAt : (I)C
    //   1226: invokevirtual append : (C)Ljava/lang/StringBuilder;
    //   1229: pop
    //   1230: iload_2
    //   1231: ifeq -> 1348
    //   1234: goto -> 1241
    //   1237: invokestatic a : (Ljava/lang/Throwable;)Ljava/lang/Throwable;
    //   1240: athrow
    //   1241: aload_3
    //   1242: getstatic burp/Znp.Zr : Ljava/lang/String;
    //   1245: getstatic burp/Zrhu.Zs : Ljava/lang/Object;
    //   1248: checkcast java/math/BigInteger
    //   1251: invokevirtual intValue : ()I
    //   1254: bipush #32
    //   1256: irem
    //   1257: invokestatic abs : (I)I
    //   1260: invokevirtual charAt : (I)C
    //   1263: invokevirtual append : (C)Ljava/lang/StringBuilder;
    //   1266: pop
    //   1267: iload_2
    //   1268: ifeq -> 1348
    //   1271: goto -> 1278
    //   1274: invokestatic a : (Ljava/lang/Throwable;)Ljava/lang/Throwable;
    //   1277: athrow
    //   1278: aload_3
    //   1279: getstatic burp/Zmji.Zs : Ljava/lang/String;
    //   1282: getstatic burp/Zeqo.ZZ : Ljava/lang/Object;
    //   1285: checkcast java/math/BigInteger
    //   1288: invokevirtual intValue : ()I
    //   1291: bipush #32
    //   1293: irem
    //   1294: invokestatic abs : (I)I
    //   1297: invokevirtual charAt : (I)C
    //   1300: invokevirtual append : (C)Ljava/lang/StringBuilder;
    //   1303: pop
    //   1304: iload_2
    //   1305: ifeq -> 1348
    //   1308: goto -> 1315
    //   1311: invokestatic a : (Ljava/lang/Throwable;)Ljava/lang/Throwable;
    //   1314: athrow
    //   1315: aload_3
    //   1316: getstatic burp/Zg2.ZN : Ljava/lang/String;
    //   1319: getstatic burp/Zss6.ZG : Ljava/lang/Object;
    //   1322: checkcast java/math/BigInteger
    //   1325: invokevirtual intValue : ()I
    //   1328: bipush #32
    //   1330: irem
    //   1331: invokestatic abs : (I)I
    //   1334: invokevirtual charAt : (I)C
    //   1337: invokevirtual append : (C)Ljava/lang/StringBuilder;
    //   1340: pop
    //   1341: goto -> 1348
    //   1344: invokestatic a : (Ljava/lang/Throwable;)Ljava/lang/Throwable;
    //   1347: athrow
    //   1348: iinc #4, 1
    //   1351: iload_2
    //   1352: ifeq -> 15
    //   1355: aload_3
    //   1356: invokevirtual toString : ()Ljava/lang/String;
    //   1359: putstatic burp/Zry0.Zz : Ljava/lang/String;
    //   1362: new java/io/ByteArrayOutputStream
    //   1365: dup
    //   1366: invokespecial <init> : ()V
    //   1369: astore #4
    //   1371: getstatic burp/Zrs0.Zt : Ljava/lang/String;
    //   1374: astore #5
    //   1376: iconst_0
    //   1377: istore #6
    //   1379: iload #6
    //   1381: aload #5
    //   1383: invokevirtual length : ()I
    //   1386: if_icmpge -> 1417
    //   1389: aload #4
    //   1391: aload #5
    //   1393: iload #6
    //   1395: iload #6
    //   1397: iconst_2
    //   1398: iadd
    //   1399: invokevirtual substring : (II)Ljava/lang/String;
    //   1402: bipush #16
    //   1404: invokestatic parseInt : (Ljava/lang/String;I)I
    //   1407: invokevirtual write : (I)V
    //   1410: iinc #6, 2
    //   1413: iload_2
    //   1414: ifeq -> 1379
    //   1417: aload #4
    //   1419: invokevirtual toByteArray : ()[B
    //   1422: astore #6
    //   1424: getstatic burp/Zeor.Zb : Ljava/lang/Object;
    //   1427: checkcast java/math/BigInteger
    //   1430: invokevirtual toByteArray : ()[B
    //   1433: astore #7
    //   1435: sipush #256
    //   1438: newarray byte
    //   1440: astore #9
    //   1442: sipush #256
    //   1445: newarray int
    //   1447: astore #10
    //   1449: sipush #256
    //   1452: newarray int
    //   1454: astore #11
    //   1456: sipush #256
    //   1459: newarray int
    //   1461: astore #12
    //   1463: sipush #256
    //   1466: newarray int
    //   1468: astore #13
    //   1470: bipush #10
    //   1472: newarray int
    //   1474: astore #14
    //   1476: sipush #283
    //   1479: istore #15
    //   1481: iconst_0
    //   1482: istore #17
    //   1484: iload #17
    //   1486: sipush #256
    //   1489: if_icmpge -> 1723
    //   1492: sipush #-6891
    //   1495: sipush #23226
    //   1498: invokestatic a : (II)Ljava/lang/String;
    //   1501: iload #17
    //   1503: iconst_1
    //   1504: iushr
    //   1505: invokevirtual charAt : (I)C
    //   1508: istore #26
    //   1510: iload #17
    //   1512: iconst_1
    //   1513: iand
    //   1514: ifne -> 1529
    //   1517: iload #26
    //   1519: bipush #8
    //   1521: iushr
    //   1522: goto -> 1531
    //   1525: invokestatic a : (Ljava/lang/Throwable;)Ljava/lang/Throwable;
    //   1528: athrow
    //   1529: iload #26
    //   1531: i2b
    //   1532: sipush #255
    //   1535: iand
    //   1536: istore #16
    //   1538: iload #17
    //   1540: iconst_1
    //   1541: ishl
    //   1542: istore #18
    //   1544: iload #18
    //   1546: sipush #256
    //   1549: if_icmplt -> 1559
    //   1552: iload #18
    //   1554: iload #15
    //   1556: ixor
    //   1557: istore #18
    //   1559: iload #18
    //   1561: iconst_1
    //   1562: ishl
    //   1563: istore #19
    //   1565: iload #19
    //   1567: sipush #256
    //   1570: if_icmplt -> 1580
    //   1573: iload #19
    //   1575: iload #15
    //   1577: ixor
    //   1578: istore #19
    //   1580: iload #19
    //   1582: iconst_1
    //   1583: ishl
    //   1584: istore #20
    //   1586: iload #20
    //   1588: sipush #256
    //   1591: if_icmplt -> 1601
    //   1594: iload #20
    //   1596: iload #15
    //   1598: ixor
    //   1599: istore #20
    //   1601: iload #20
    //   1603: iload #17
    //   1605: ixor
    //   1606: istore #21
    //   1608: iload #21
    //   1610: iload #18
    //   1612: ixor
    //   1613: istore #22
    //   1615: iload #21
    //   1617: iload #19
    //   1619: ixor
    //   1620: istore #23
    //   1622: iload #20
    //   1624: iload #19
    //   1626: ixor
    //   1627: iload #18
    //   1629: ixor
    //   1630: istore #24
    //   1632: aload #9
    //   1634: iload #17
    //   1636: iload #16
    //   1638: i2b
    //   1639: bastore
    //   1640: aload #10
    //   1642: iload #16
    //   1644: iload #24
    //   1646: bipush #24
    //   1648: ishl
    //   1649: iload #21
    //   1651: bipush #16
    //   1653: ishl
    //   1654: ior
    //   1655: iload #23
    //   1657: bipush #8
    //   1659: ishl
    //   1660: ior
    //   1661: iload #22
    //   1663: ior
    //   1664: dup
    //   1665: istore #25
    //   1667: iastore
    //   1668: aload #11
    //   1670: iload #16
    //   1672: iload #25
    //   1674: bipush #8
    //   1676: iushr
    //   1677: iload #25
    //   1679: bipush #24
    //   1681: ishl
    //   1682: ior
    //   1683: iastore
    //   1684: aload #12
    //   1686: iload #16
    //   1688: iload #25
    //   1690: bipush #16
    //   1692: iushr
    //   1693: iload #25
    //   1695: bipush #16
    //   1697: ishl
    //   1698: ior
    //   1699: iastore
    //   1700: aload #13
    //   1702: iload #16
    //   1704: iload #25
    //   1706: bipush #24
    //   1708: iushr
    //   1709: iload #25
    //   1711: bipush #8
    //   1713: ishl
    //   1714: ior
    //   1715: iastore
    //   1716: iinc #17, 1
    //   1719: iload_2
    //   1720: ifeq -> 1484
    //   1723: iconst_1
    //   1724: istore #26
    //   1726: aload #14
    //   1728: iconst_0
    //   1729: iload #26
    //   1731: bipush #24
    //   1733: ishl
    //   1734: iastore
    //   1735: iconst_1
    //   1736: istore #27
    //   1738: iload #27
    //   1740: bipush #10
    //   1742: if_icmpge -> 1783
    //   1745: iload #26
    //   1747: iconst_1
    //   1748: ishl
    //   1749: istore #26
    //   1751: iload #26
    //   1753: sipush #256
    //   1756: if_icmplt -> 1766
    //   1759: iload #26
    //   1761: iload #15
    //   1763: ixor
    //   1764: istore #26
    //   1766: aload #14
    //   1768: iload #27
    //   1770: iload #26
    //   1772: bipush #24
    //   1774: ishl
    //   1775: iastore
    //   1776: iinc #27, 1
    //   1779: iload_2
    //   1780: ifeq -> 1738
    //   1783: iconst_4
    //   1784: istore #27
    //   1786: iload #27
    //   1788: bipush #6
    //   1790: iadd
    //   1791: istore #28
    //   1793: iconst_4
    //   1794: iload #28
    //   1796: iconst_1
    //   1797: iadd
    //   1798: imul
    //   1799: istore #29
    //   1801: iload #29
    //   1803: newarray int
    //   1805: astore #30
    //   1807: iload #29
    //   1809: newarray int
    //   1811: astore #31
    //   1813: iconst_0
    //   1814: istore #26
    //   1816: iconst_0
    //   1817: istore #33
    //   1819: iconst_0
    //   1820: istore #34
    //   1822: iload #33
    //   1824: iload #27
    //   1826: if_icmpge -> 1894
    //   1829: aload #30
    //   1831: iload #33
    //   1833: aload #6
    //   1835: iload #34
    //   1837: baload
    //   1838: bipush #24
    //   1840: ishl
    //   1841: aload #6
    //   1843: iload #34
    //   1845: iconst_1
    //   1846: iadd
    //   1847: baload
    //   1848: sipush #255
    //   1851: iand
    //   1852: bipush #16
    //   1854: ishl
    //   1855: ior
    //   1856: aload #6
    //   1858: iload #34
    //   1860: iconst_2
    //   1861: iadd
    //   1862: baload
    //   1863: sipush #255
    //   1866: iand
    //   1867: bipush #8
    //   1869: ishl
    //   1870: ior
    //   1871: aload #6
    //   1873: iload #34
    //   1875: iconst_3
    //   1876: iadd
    //   1877: baload
    //   1878: sipush #255
    //   1881: iand
    //   1882: ior
    //   1883: iastore
    //   1884: iinc #33, 1
    //   1887: iinc #34, 4
    //   1890: iload_2
    //   1891: ifeq -> 1822
    //   1894: iload #27
    //   1896: istore #33
    //   1898: iconst_0
    //   1899: istore #34
    //   1901: iload #33
    //   1903: iload #29
    //   1905: if_icmpge -> 2032
    //   1908: aload #30
    //   1910: iload #33
    //   1912: iconst_1
    //   1913: isub
    //   1914: iaload
    //   1915: istore #32
    //   1917: iload #34
    //   1919: ifne -> 2006
    //   1922: iload #27
    //   1924: istore #34
    //   1926: aload #9
    //   1928: iload #32
    //   1930: bipush #16
    //   1932: iushr
    //   1933: sipush #255
    //   1936: iand
    //   1937: baload
    //   1938: bipush #24
    //   1940: ishl
    //   1941: aload #9
    //   1943: iload #32
    //   1945: bipush #8
    //   1947: iushr
    //   1948: sipush #255
    //   1951: iand
    //   1952: baload
    //   1953: sipush #255
    //   1956: iand
    //   1957: bipush #16
    //   1959: ishl
    //   1960: ior
    //   1961: aload #9
    //   1963: iload #32
    //   1965: sipush #255
    //   1968: iand
    //   1969: baload
    //   1970: sipush #255
    //   1973: iand
    //   1974: bipush #8
    //   1976: ishl
    //   1977: ior
    //   1978: aload #9
    //   1980: iload #32
    //   1982: bipush #24
    //   1984: iushr
    //   1985: baload
    //   1986: sipush #255
    //   1989: iand
    //   1990: ior
    //   1991: istore #32
    //   1993: iload #32
    //   1995: aload #14
    //   1997: iload #26
    //   1999: iinc #26, 1
    //   2002: iaload
    //   2003: ixor
    //   2004: istore #32
    //   2006: aload #30
    //   2008: iload #33
    //   2010: aload #30
    //   2012: iload #33
    //   2014: iload #27
    //   2016: isub
    //   2017: iaload
    //   2018: iload #32
    //   2020: ixor
    //   2021: iastore
    //   2022: iinc #33, 1
    //   2025: iinc #34, -1
    //   2028: iload_2
    //   2029: ifeq -> 1901
    //   2032: iconst_0
    //   2033: istore #33
    //   2035: iconst_4
    //   2036: iload #28
    //   2038: imul
    //   2039: istore #34
    //   2041: aload #31
    //   2043: iload #33
    //   2045: aload #30
    //   2047: iload #34
    //   2049: iaload
    //   2050: iastore
    //   2051: aload #31
    //   2053: iload #33
    //   2055: iconst_1
    //   2056: iadd
    //   2057: aload #30
    //   2059: iload #34
    //   2061: iconst_1
    //   2062: iadd
    //   2063: iaload
    //   2064: iastore
    //   2065: aload #31
    //   2067: iload #33
    //   2069: iconst_2
    //   2070: iadd
    //   2071: aload #30
    //   2073: iload #34
    //   2075: iconst_2
    //   2076: iadd
    //   2077: iaload
    //   2078: iastore
    //   2079: aload #31
    //   2081: iload #33
    //   2083: iconst_3
    //   2084: iadd
    //   2085: aload #30
    //   2087: iload #34
    //   2089: iconst_3
    //   2090: iadd
    //   2091: iaload
    //   2092: iastore
    //   2093: iinc #33, 4
    //   2096: iinc #34, -4
    //   2099: iconst_1
    //   2100: istore #36
    //   2102: iload #36
    //   2104: iload #28
    //   2106: if_icmpge -> 2470
    //   2109: aload #30
    //   2111: iload #34
    //   2113: iaload
    //   2114: istore #35
    //   2116: aload #31
    //   2118: iload #33
    //   2120: aload #10
    //   2122: aload #9
    //   2124: iload #35
    //   2126: bipush #24
    //   2128: iushr
    //   2129: baload
    //   2130: sipush #255
    //   2133: iand
    //   2134: iaload
    //   2135: aload #11
    //   2137: aload #9
    //   2139: iload #35
    //   2141: bipush #16
    //   2143: iushr
    //   2144: sipush #255
    //   2147: iand
    //   2148: baload
    //   2149: sipush #255
    //   2152: iand
    //   2153: iaload
    //   2154: ixor
    //   2155: aload #12
    //   2157: aload #9
    //   2159: iload #35
    //   2161: bipush #8
    //   2163: iushr
    //   2164: sipush #255
    //   2167: iand
    //   2168: baload
    //   2169: sipush #255
    //   2172: iand
    //   2173: iaload
    //   2174: ixor
    //   2175: aload #13
    //   2177: aload #9
    //   2179: iload #35
    //   2181: sipush #255
    //   2184: iand
    //   2185: baload
    //   2186: sipush #255
    //   2189: iand
    //   2190: iaload
    //   2191: ixor
    //   2192: iastore
    //   2193: aload #30
    //   2195: iload #34
    //   2197: iconst_1
    //   2198: iadd
    //   2199: iaload
    //   2200: istore #35
    //   2202: aload #31
    //   2204: iload #33
    //   2206: iconst_1
    //   2207: iadd
    //   2208: aload #10
    //   2210: aload #9
    //   2212: iload #35
    //   2214: bipush #24
    //   2216: iushr
    //   2217: baload
    //   2218: sipush #255
    //   2221: iand
    //   2222: iaload
    //   2223: aload #11
    //   2225: aload #9
    //   2227: iload #35
    //   2229: bipush #16
    //   2231: iushr
    //   2232: sipush #255
    //   2235: iand
    //   2236: baload
    //   2237: sipush #255
    //   2240: iand
    //   2241: iaload
    //   2242: ixor
    //   2243: aload #12
    //   2245: aload #9
    //   2247: iload #35
    //   2249: bipush #8
    //   2251: iushr
    //   2252: sipush #255
    //   2255: iand
    //   2256: baload
    //   2257: sipush #255
    //   2260: iand
    //   2261: iaload
    //   2262: ixor
    //   2263: aload #13
    //   2265: aload #9
    //   2267: iload #35
    //   2269: sipush #255
    //   2272: iand
    //   2273: baload
    //   2274: sipush #255
    //   2277: iand
    //   2278: iaload
    //   2279: ixor
    //   2280: iastore
    //   2281: aload #30
    //   2283: iload #34
    //   2285: iconst_2
    //   2286: iadd
    //   2287: iaload
    //   2288: istore #35
    //   2290: aload #31
    //   2292: iload #33
    //   2294: iconst_2
    //   2295: iadd
    //   2296: aload #10
    //   2298: aload #9
    //   2300: iload #35
    //   2302: bipush #24
    //   2304: iushr
    //   2305: baload
    //   2306: sipush #255
    //   2309: iand
    //   2310: iaload
    //   2311: aload #11
    //   2313: aload #9
    //   2315: iload #35
    //   2317: bipush #16
    //   2319: iushr
    //   2320: sipush #255
    //   2323: iand
    //   2324: baload
    //   2325: sipush #255
    //   2328: iand
    //   2329: iaload
    //   2330: ixor
    //   2331: aload #12
    //   2333: aload #9
    //   2335: iload #35
    //   2337: bipush #8
    //   2339: iushr
    //   2340: sipush #255
    //   2343: iand
    //   2344: baload
    //   2345: sipush #255
    //   2348: iand
    //   2349: iaload
    //   2350: ixor
    //   2351: aload #13
    //   2353: aload #9
    //   2355: iload #35
    //   2357: sipush #255
    //   2360: iand
    //   2361: baload
    //   2362: sipush #255
    //   2365: iand
    //   2366: iaload
    //   2367: ixor
    //   2368: iastore
    //   2369: aload #30
    //   2371: iload #34
    //   2373: iconst_3
    //   2374: iadd
    //   2375: iaload
    //   2376: istore #35
    //   2378: aload #31
    //   2380: iload #33
    //   2382: iconst_3
    //   2383: iadd
    //   2384: aload #10
    //   2386: aload #9
    //   2388: iload #35
    //   2390: bipush #24
    //   2392: iushr
    //   2393: baload
    //   2394: sipush #255
    //   2397: iand
    //   2398: iaload
    //   2399: aload #11
    //   2401: aload #9
    //   2403: iload #35
    //   2405: bipush #16
    //   2407: iushr
    //   2408: sipush #255
    //   2411: iand
    //   2412: baload
    //   2413: sipush #255
    //   2416: iand
    //   2417: iaload
    //   2418: ixor
    //   2419: aload #12
    //   2421: aload #9
    //   2423: iload #35
    //   2425: bipush #8
    //   2427: iushr
    //   2428: sipush #255
    //   2431: iand
    //   2432: baload
    //   2433: sipush #255
    //   2436: iand
    //   2437: iaload
    //   2438: ixor
    //   2439: aload #13
    //   2441: aload #9
    //   2443: iload #35
    //   2445: sipush #255
    //   2448: iand
    //   2449: baload
    //   2450: sipush #255
    //   2453: iand
    //   2454: iaload
    //   2455: ixor
    //   2456: iastore
    //   2457: iinc #33, 4
    //   2460: iinc #34, -4
    //   2463: iinc #36, 1
    //   2466: iload_2
    //   2467: ifeq -> 2102
    //   2470: aload #31
    //   2472: iload #33
    //   2474: aload #30
    //   2476: iload #34
    //   2478: iaload
    //   2479: iastore
    //   2480: aload #31
    //   2482: iload #33
    //   2484: iconst_1
    //   2485: iadd
    //   2486: aload #30
    //   2488: iload #34
    //   2490: iconst_1
    //   2491: iadd
    //   2492: iaload
    //   2493: iastore
    //   2494: aload #31
    //   2496: iload #33
    //   2498: iconst_2
    //   2499: iadd
    //   2500: aload #30
    //   2502: iload #34
    //   2504: iconst_2
    //   2505: iadd
    //   2506: iaload
    //   2507: iastore
    //   2508: aload #31
    //   2510: iload #33
    //   2512: iconst_3
    //   2513: iadd
    //   2514: aload #30
    //   2516: iload #34
    //   2518: iconst_3
    //   2519: iadd
    //   2520: iaload
    //   2521: iastore
    //   2522: iconst_0
    //   2523: newarray byte
    //   2525: astore #36
    //   2527: aload #7
    //   2529: arraylength
    //   2530: bipush #16
    //   2532: irem
    //   2533: ifeq -> 2557
    //   2536: new java/lang/Exception
    //   2539: dup
    //   2540: sipush #-6890
    //   2543: sipush #-25195
    //   2546: invokestatic a : (II)Ljava/lang/String;
    //   2549: invokespecial <init> : (Ljava/lang/String;)V
    //   2552: athrow
    //   2553: invokestatic a : (Ljava/lang/Throwable;)Ljava/lang/Throwable;
    //   2556: athrow
    //   2557: bipush #10
    //   2559: istore #37
    //   2561: sipush #-6894
    //   2564: sipush #256
    //   2567: newarray byte
    //   2569: astore #38
    //   2571: sipush #-29861
    //   2574: sipush #256
    //   2577: newarray int
    //   2579: astore #39
    //   2581: sipush #256
    //   2584: newarray int
    //   2586: astore #40
    //   2588: sipush #256
    //   2591: newarray int
    //   2593: astore #41
    //   2595: sipush #256
    //   2598: newarray int
    //   2600: astore #42
    //   2602: sipush #283
    //   2605: istore #15
    //   2607: invokestatic a : (II)Ljava/lang/String;
    //   2610: astore #43
    //   2612: iconst_0
    //   2613: istore #17
    //   2615: iload #17
    //   2617: sipush #256
    //   2620: if_icmpge -> 2847
    //   2623: aload #43
    //   2625: iload #17
    //   2627: iconst_1
    //   2628: iushr
    //   2629: invokevirtual charAt : (I)C
    //   2632: istore #44
    //   2634: iload #17
    //   2636: iconst_1
    //   2637: iand
    //   2638: ifne -> 2653
    //   2641: iload #44
    //   2643: bipush #8
    //   2645: iushr
    //   2646: goto -> 2655
    //   2649: invokestatic a : (Ljava/lang/Throwable;)Ljava/lang/Throwable;
    //   2652: athrow
    //   2653: iload #44
    //   2655: i2b
    //   2656: sipush #255
    //   2659: iand
    //   2660: istore #16
    //   2662: iload #17
    //   2664: iconst_1
    //   2665: ishl
    //   2666: istore #18
    //   2668: iload #18
    //   2670: sipush #256
    //   2673: if_icmplt -> 2683
    //   2676: iload #18
    //   2678: iload #15
    //   2680: ixor
    //   2681: istore #18
    //   2683: iload #18
    //   2685: iconst_1
    //   2686: ishl
    //   2687: istore #19
    //   2689: iload #19
    //   2691: sipush #256
    //   2694: if_icmplt -> 2704
    //   2697: iload #19
    //   2699: iload #15
    //   2701: ixor
    //   2702: istore #19
    //   2704: iload #19
    //   2706: iconst_1
    //   2707: ishl
    //   2708: istore #20
    //   2710: iload #20
    //   2712: sipush #256
    //   2715: if_icmplt -> 2725
    //   2718: iload #20
    //   2720: iload #15
    //   2722: ixor
    //   2723: istore #20
    //   2725: iload #20
    //   2727: iload #17
    //   2729: ixor
    //   2730: istore #21
    //   2732: iload #21
    //   2734: iload #18
    //   2736: ixor
    //   2737: istore #22
    //   2739: iload #21
    //   2741: iload #19
    //   2743: ixor
    //   2744: istore #23
    //   2746: iload #20
    //   2748: iload #19
    //   2750: ixor
    //   2751: iload #18
    //   2753: ixor
    //   2754: istore #24
    //   2756: aload #38
    //   2758: iload #16
    //   2760: iload #17
    //   2762: i2b
    //   2763: bastore
    //   2764: aload #39
    //   2766: iload #16
    //   2768: iload #24
    //   2770: bipush #24
    //   2772: ishl
    //   2773: iload #21
    //   2775: bipush #16
    //   2777: ishl
    //   2778: ior
    //   2779: iload #23
    //   2781: bipush #8
    //   2783: ishl
    //   2784: ior
    //   2785: iload #22
    //   2787: ior
    //   2788: dup
    //   2789: istore #25
    //   2791: iastore
    //   2792: aload #40
    //   2794: iload #16
    //   2796: iload #25
    //   2798: bipush #8
    //   2800: iushr
    //   2801: iload #25
    //   2803: bipush #24
    //   2805: ishl
    //   2806: ior
    //   2807: iastore
    //   2808: aload #41
    //   2810: iload #16
    //   2812: iload #25
    //   2814: bipush #16
    //   2816: iushr
    //   2817: iload #25
    //   2819: bipush #16
    //   2821: ishl
    //   2822: ior
    //   2823: iastore
    //   2824: aload #42
    //   2826: iload #16
    //   2828: iload #25
    //   2830: bipush #24
    //   2832: iushr
    //   2833: iload #25
    //   2835: bipush #8
    //   2837: ishl
    //   2838: ior
    //   2839: iastore
    //   2840: iinc #17, 1
    //   2843: iload_2
    //   2844: ifeq -> 2615
    //   2847: aload #7
    //   2849: arraylength
    //   2850: newarray byte
    //   2852: astore #44
    //   2854: iconst_0
    //   2855: istore #45
    //   2857: iload #45
    //   2859: aload #7
    //   2861: arraylength
    //   2862: bipush #16
    //   2864: idiv
    //   2865: if_icmpge -> 3779
    //   2868: bipush #16
    //   2870: newarray byte
    //   2872: astore #46
    //   2874: bipush #16
    //   2876: newarray byte
    //   2878: astore #47
    //   2880: iconst_0
    //   2881: istore #48
    //   2883: iload #48
    //   2885: bipush #16
    //   2887: if_icmpge -> 2913
    //   2890: aload #46
    //   2892: iload #48
    //   2894: aload #7
    //   2896: iload #48
    //   2898: iload #45
    //   2900: bipush #16
    //   2902: imul
    //   2903: iadd
    //   2904: baload
    //   2905: bastore
    //   2906: iinc #48, 1
    //   2909: iload_2
    //   2910: ifeq -> 2883
    //   2913: iconst_0
    //   2914: istore #48
    //   2916: aload #46
    //   2918: iconst_0
    //   2919: baload
    //   2920: bipush #24
    //   2922: ishl
    //   2923: aload #46
    //   2925: iconst_1
    //   2926: baload
    //   2927: sipush #255
    //   2930: iand
    //   2931: bipush #16
    //   2933: ishl
    //   2934: ior
    //   2935: aload #46
    //   2937: iconst_2
    //   2938: baload
    //   2939: sipush #255
    //   2942: iand
    //   2943: bipush #8
    //   2945: ishl
    //   2946: ior
    //   2947: aload #46
    //   2949: iconst_3
    //   2950: baload
    //   2951: sipush #255
    //   2954: iand
    //   2955: ior
    //   2956: aload #31
    //   2958: iconst_0
    //   2959: iaload
    //   2960: ixor
    //   2961: istore #50
    //   2963: aload #46
    //   2965: iconst_4
    //   2966: baload
    //   2967: bipush #24
    //   2969: ishl
    //   2970: aload #46
    //   2972: iconst_5
    //   2973: baload
    //   2974: sipush #255
    //   2977: iand
    //   2978: bipush #16
    //   2980: ishl
    //   2981: ior
    //   2982: aload #46
    //   2984: bipush #6
    //   2986: baload
    //   2987: sipush #255
    //   2990: iand
    //   2991: bipush #8
    //   2993: ishl
    //   2994: ior
    //   2995: aload #46
    //   2997: bipush #7
    //   2999: baload
    //   3000: sipush #255
    //   3003: iand
    //   3004: ior
    //   3005: aload #31
    //   3007: iconst_1
    //   3008: iaload
    //   3009: ixor
    //   3010: istore #51
    //   3012: aload #46
    //   3014: bipush #8
    //   3016: baload
    //   3017: bipush #24
    //   3019: ishl
    //   3020: aload #46
    //   3022: bipush #9
    //   3024: baload
    //   3025: sipush #255
    //   3028: iand
    //   3029: bipush #16
    //   3031: ishl
    //   3032: ior
    //   3033: aload #46
    //   3035: bipush #10
    //   3037: baload
    //   3038: sipush #255
    //   3041: iand
    //   3042: bipush #8
    //   3044: ishl
    //   3045: ior
    //   3046: aload #46
    //   3048: bipush #11
    //   3050: baload
    //   3051: sipush #255
    //   3054: iand
    //   3055: ior
    //   3056: aload #31
    //   3058: iconst_2
    //   3059: iaload
    //   3060: ixor
    //   3061: istore #52
    //   3063: aload #46
    //   3065: bipush #12
    //   3067: baload
    //   3068: bipush #24
    //   3070: ishl
    //   3071: aload #46
    //   3073: bipush #13
    //   3075: baload
    //   3076: sipush #255
    //   3079: iand
    //   3080: bipush #16
    //   3082: ishl
    //   3083: ior
    //   3084: aload #46
    //   3086: bipush #14
    //   3088: baload
    //   3089: sipush #255
    //   3092: iand
    //   3093: bipush #8
    //   3095: ishl
    //   3096: ior
    //   3097: aload #46
    //   3099: bipush #15
    //   3101: baload
    //   3102: sipush #255
    //   3105: iand
    //   3106: ior
    //   3107: aload #31
    //   3109: iconst_3
    //   3110: iaload
    //   3111: ixor
    //   3112: istore #53
    //   3114: iconst_1
    //   3115: istore #54
    //   3117: iload #54
    //   3119: iload #37
    //   3121: if_icmpge -> 3364
    //   3124: iinc #48, 4
    //   3127: aload #39
    //   3129: iload #50
    //   3131: bipush #24
    //   3133: iushr
    //   3134: iaload
    //   3135: aload #40
    //   3137: iload #53
    //   3139: bipush #16
    //   3141: iushr
    //   3142: sipush #255
    //   3145: iand
    //   3146: iaload
    //   3147: ixor
    //   3148: aload #41
    //   3150: iload #52
    //   3152: bipush #8
    //   3154: iushr
    //   3155: sipush #255
    //   3158: iand
    //   3159: iaload
    //   3160: ixor
    //   3161: aload #42
    //   3163: iload #51
    //   3165: sipush #255
    //   3168: iand
    //   3169: iaload
    //   3170: ixor
    //   3171: aload #31
    //   3173: iload #48
    //   3175: iaload
    //   3176: ixor
    //   3177: istore #55
    //   3179: aload #39
    //   3181: iload #51
    //   3183: bipush #24
    //   3185: iushr
    //   3186: iaload
    //   3187: aload #40
    //   3189: iload #50
    //   3191: bipush #16
    //   3193: iushr
    //   3194: sipush #255
    //   3197: iand
    //   3198: iaload
    //   3199: ixor
    //   3200: aload #41
    //   3202: iload #53
    //   3204: bipush #8
    //   3206: iushr
    //   3207: sipush #255
    //   3210: iand
    //   3211: iaload
    //   3212: ixor
    //   3213: aload #42
    //   3215: iload #52
    //   3217: sipush #255
    //   3220: iand
    //   3221: iaload
    //   3222: ixor
    //   3223: aload #31
    //   3225: iload #48
    //   3227: iconst_1
    //   3228: iadd
    //   3229: iaload
    //   3230: ixor
    //   3231: istore #56
    //   3233: aload #39
    //   3235: iload #52
    //   3237: bipush #24
    //   3239: iushr
    //   3240: iaload
    //   3241: aload #40
    //   3243: iload #51
    //   3245: bipush #16
    //   3247: iushr
    //   3248: sipush #255
    //   3251: iand
    //   3252: iaload
    //   3253: ixor
    //   3254: aload #41
    //   3256: iload #50
    //   3258: bipush #8
    //   3260: iushr
    //   3261: sipush #255
    //   3264: iand
    //   3265: iaload
    //   3266: ixor
    //   3267: aload #42
    //   3269: iload #53
    //   3271: sipush #255
    //   3274: iand
    //   3275: iaload
    //   3276: ixor
    //   3277: aload #31
    //   3279: iload #48
    //   3281: iconst_2
    //   3282: iadd
    //   3283: iaload
    //   3284: ixor
    //   3285: istore #57
    //   3287: aload #39
    //   3289: iload #53
    //   3291: bipush #24
    //   3293: iushr
    //   3294: iaload
    //   3295: aload #40
    //   3297: iload #52
    //   3299: bipush #16
    //   3301: iushr
    //   3302: sipush #255
    //   3305: iand
    //   3306: iaload
    //   3307: ixor
    //   3308: aload #41
    //   3310: iload #51
    //   3312: bipush #8
    //   3314: iushr
    //   3315: sipush #255
    //   3318: iand
    //   3319: iaload
    //   3320: ixor
    //   3321: aload #42
    //   3323: iload #50
    //   3325: sipush #255
    //   3328: iand
    //   3329: iaload
    //   3330: ixor
    //   3331: aload #31
    //   3333: iload #48
    //   3335: iconst_3
    //   3336: iadd
    //   3337: iaload
    //   3338: ixor
    //   3339: istore #58
    //   3341: iload #55
    //   3343: istore #50
    //   3345: iload #56
    //   3347: istore #51
    //   3349: iload #57
    //   3351: istore #52
    //   3353: iload #58
    //   3355: istore #53
    //   3357: iinc #54, 1
    //   3360: iload_2
    //   3361: ifeq -> 3117
    //   3364: iinc #48, 4
    //   3367: aload #31
    //   3369: iload #48
    //   3371: iaload
    //   3372: istore #49
    //   3374: aload #47
    //   3376: iconst_0
    //   3377: aload #38
    //   3379: iload #50
    //   3381: bipush #24
    //   3383: iushr
    //   3384: baload
    //   3385: iload #49
    //   3387: bipush #24
    //   3389: iushr
    //   3390: ixor
    //   3391: i2b
    //   3392: bastore
    //   3393: aload #47
    //   3395: iconst_1
    //   3396: aload #38
    //   3398: iload #53
    //   3400: bipush #16
    //   3402: iushr
    //   3403: sipush #255
    //   3406: iand
    //   3407: baload
    //   3408: iload #49
    //   3410: bipush #16
    //   3412: iushr
    //   3413: ixor
    //   3414: i2b
    //   3415: bastore
    //   3416: aload #47
    //   3418: iconst_2
    //   3419: aload #38
    //   3421: iload #52
    //   3423: bipush #8
    //   3425: iushr
    //   3426: sipush #255
    //   3429: iand
    //   3430: baload
    //   3431: iload #49
    //   3433: bipush #8
    //   3435: iushr
    //   3436: ixor
    //   3437: i2b
    //   3438: bastore
    //   3439: aload #47
    //   3441: iconst_3
    //   3442: aload #38
    //   3444: iload #51
    //   3446: sipush #255
    //   3449: iand
    //   3450: baload
    //   3451: iload #49
    //   3453: ixor
    //   3454: i2b
    //   3455: bastore
    //   3456: aload #31
    //   3458: iload #48
    //   3460: iconst_1
    //   3461: iadd
    //   3462: iaload
    //   3463: istore #49
    //   3465: aload #47
    //   3467: iconst_4
    //   3468: aload #38
    //   3470: iload #51
    //   3472: bipush #24
    //   3474: iushr
    //   3475: baload
    //   3476: iload #49
    //   3478: bipush #24
    //   3480: iushr
    //   3481: ixor
    //   3482: i2b
    //   3483: bastore
    //   3484: aload #47
    //   3486: iconst_5
    //   3487: aload #38
    //   3489: iload #50
    //   3491: bipush #16
    //   3493: iushr
    //   3494: sipush #255
    //   3497: iand
    //   3498: baload
    //   3499: iload #49
    //   3501: bipush #16
    //   3503: iushr
    //   3504: ixor
    //   3505: i2b
    //   3506: bastore
    //   3507: aload #47
    //   3509: bipush #6
    //   3511: aload #38
    //   3513: iload #53
    //   3515: bipush #8
    //   3517: iushr
    //   3518: sipush #255
    //   3521: iand
    //   3522: baload
    //   3523: iload #49
    //   3525: bipush #8
    //   3527: iushr
    //   3528: ixor
    //   3529: i2b
    //   3530: bastore
    //   3531: aload #47
    //   3533: bipush #7
    //   3535: aload #38
    //   3537: iload #52
    //   3539: sipush #255
    //   3542: iand
    //   3543: baload
    //   3544: iload #49
    //   3546: ixor
    //   3547: i2b
    //   3548: bastore
    //   3549: aload #31
    //   3551: iload #48
    //   3553: iconst_2
    //   3554: iadd
    //   3555: iaload
    //   3556: istore #49
    //   3558: aload #47
    //   3560: bipush #8
    //   3562: aload #38
    //   3564: iload #52
    //   3566: bipush #24
    //   3568: iushr
    //   3569: baload
    //   3570: iload #49
    //   3572: bipush #24
    //   3574: iushr
    //   3575: ixor
    //   3576: i2b
    //   3577: bastore
    //   3578: aload #47
    //   3580: bipush #9
    //   3582: aload #38
    //   3584: iload #51
    //   3586: bipush #16
    //   3588: iushr
    //   3589: sipush #255
    //   3592: iand
    //   3593: baload
    //   3594: iload #49
    //   3596: bipush #16
    //   3598: iushr
    //   3599: ixor
    //   3600: i2b
    //   3601: bastore
    //   3602: aload #47
    //   3604: bipush #10
    //   3606: aload #38
    //   3608: iload #50
    //   3610: bipush #8
    //   3612: iushr
    //   3613: sipush #255
    //   3616: iand
    //   3617: baload
    //   3618: iload #49
    //   3620: bipush #8
    //   3622: iushr
    //   3623: ixor
    //   3624: i2b
    //   3625: bastore
    //   3626: aload #47
    //   3628: bipush #11
    //   3630: aload #38
    //   3632: iload #53
    //   3634: sipush #255
    //   3637: iand
    //   3638: baload
    //   3639: iload #49
    //   3641: ixor
    //   3642: i2b
    //   3643: bastore
    //   3644: aload #31
    //   3646: iload #48
    //   3648: iconst_3
    //   3649: iadd
    //   3650: iaload
    //   3651: istore #49
    //   3653: aload #47
    //   3655: bipush #12
    //   3657: aload #38
    //   3659: iload #53
    //   3661: bipush #24
    //   3663: iushr
    //   3664: baload
    //   3665: iload #49
    //   3667: bipush #24
    //   3669: iushr
    //   3670: ixor
    //   3671: i2b
    //   3672: bastore
    //   3673: aload #47
    //   3675: bipush #13
    //   3677: aload #38
    //   3679: iload #52
    //   3681: bipush #16
    //   3683: iushr
    //   3684: sipush #255
    //   3687: iand
    //   3688: baload
    //   3689: iload #49
    //   3691: bipush #16
    //   3693: iushr
    //   3694: ixor
    //   3695: i2b
    //   3696: bastore
    //   3697: aload #47
    //   3699: bipush #14
    //   3701: aload #38
    //   3703: iload #51
    //   3705: bipush #8
    //   3707: iushr
    //   3708: sipush #255
    //   3711: iand
    //   3712: baload
    //   3713: iload #49
    //   3715: bipush #8
    //   3717: iushr
    //   3718: ixor
    //   3719: i2b
    //   3720: bastore
    //   3721: aload #47
    //   3723: bipush #15
    //   3725: aload #38
    //   3727: iload #50
    //   3729: sipush #255
    //   3732: iand
    //   3733: baload
    //   3734: iload #49
    //   3736: ixor
    //   3737: i2b
    //   3738: bastore
    //   3739: iconst_0
    //   3740: istore #54
    //   3742: iload #54
    //   3744: bipush #16
    //   3746: if_icmpge -> 3772
    //   3749: aload #44
    //   3751: iload #54
    //   3753: iload #45
    //   3755: bipush #16
    //   3757: imul
    //   3758: iadd
    //   3759: aload #47
    //   3761: iload #54
    //   3763: baload
    //   3764: bastore
    //   3765: iinc #54, 1
    //   3768: iload_2
    //   3769: ifeq -> 3742
    //   3772: iinc #45, 1
    //   3775: iload_2
    //   3776: ifeq -> 2857
    //   3779: aload #44
    //   3781: arraylength
    //   3782: ifle -> 3863
    //   3785: aload #44
    //   3787: aload #44
    //   3789: arraylength
    //   3790: iconst_1
    //   3791: isub
    //   3792: baload
    //   3793: istore #45
    //   3795: iload #45
    //   3797: bipush #16
    //   3799: if_icmple -> 3810
    //   3802: aload #44
    //   3804: astore #36
    //   3806: iload_2
    //   3807: ifeq -> 3863
    //   3810: aload #44
    //   3812: arraylength
    //   3813: iload #45
    //   3815: isub
    //   3816: newarray byte
    //   3818: astore #36
    //   3820: iconst_0
    //   3821: istore #46
    //   3823: iload #46
    //   3825: aload #36
    //   3827: arraylength
    //   3828: if_icmpge -> 3863
    //   3831: iload #46
    //   3833: aload #44
    //   3835: arraylength
    //   3836: if_icmpge -> 3863
    //   3839: aload #36
    //   3841: iload #46
    //   3843: aload #44
    //   3845: iload #46
    //   3847: baload
    //   3848: bastore
    //   3849: iinc #46, 1
    //   3852: iload_2
    //   3853: ifeq -> 3823
    //   3856: goto -> 3863
    //   3859: invokestatic a : (Ljava/lang/Throwable;)Ljava/lang/Throwable;
    //   3862: athrow
    //   3863: aload #36
    //   3865: astore #8
    //   3867: sipush #-6892
    //   3870: new java/math/BigInteger
    //   3873: dup
    //   3874: aload #8
    //   3876: invokespecial <init> : ([B)V
    //   3879: invokevirtual abs : ()Ljava/math/BigInteger;
    //   3882: putstatic burp/Zejj.Zy : Ljava/lang/Object;
    //   3885: sipush #-18975
    //   3888: invokestatic a : (II)Ljava/lang/String;
    //   3891: iconst_1
    //   3892: ldc burp/Zsuw
    //   3894: invokevirtual getClassLoader : ()Ljava/lang/ClassLoader;
    //   3897: invokestatic forName : (Ljava/lang/String;ZLjava/lang/ClassLoader;)Ljava/lang/Class;
    //   3900: invokevirtual getDeclaredFields : ()[Ljava/lang/reflect/Field;
    //   3903: astore #4
    //   3905: aload #4
    //   3907: arraylength
    //   3908: istore #5
    //   3910: iconst_0
    //   3911: istore #6
    //   3913: iload #6
    //   3915: iload #5
    //   3917: if_icmpge -> 4055
    //   3920: aload #4
    //   3922: iload #6
    //   3924: aaload
    //   3925: astore #7
    //   3927: aload #7
    //   3929: invokevirtual getModifiers : ()I
    //   3932: invokestatic isStatic : (I)Z
    //   3935: ifne -> 3945
    //   3938: goto -> 4048
    //   3941: invokestatic a : (Ljava/lang/Throwable;)Ljava/lang/Throwable;
    //   3944: athrow
    //   3945: aload #7
    //   3947: invokevirtual getType : ()Ljava/lang/Class;
    //   3950: astore #8
    //   3952: aload #8
    //   3954: ifnull -> 4035
    //   3957: aload #8
    //   3959: invokevirtual isPrimitive : ()Z
    //   3962: ifne -> 4035
    //   3965: goto -> 3972
    //   3968: invokestatic a : (Ljava/lang/Throwable;)Ljava/lang/Throwable;
    //   3971: athrow
    //   3972: aload #8
    //   3974: invokevirtual getPackage : ()Ljava/lang/Package;
    //   3977: ifnull -> 4035
    //   3980: goto -> 3987
    //   3983: invokestatic a : (Ljava/lang/Throwable;)Ljava/lang/Throwable;
    //   3986: athrow
    //   3987: aload #8
    //   3989: invokevirtual getPackage : ()Ljava/lang/Package;
    //   3992: invokevirtual getName : ()Ljava/lang/String;
    //   3995: ifnull -> 4035
    //   3998: goto -> 4005
    //   4001: invokestatic a : (Ljava/lang/Throwable;)Ljava/lang/Throwable;
    //   4004: athrow
    //   4005: aload #8
    //   4007: invokevirtual getPackage : ()Ljava/lang/Package;
    //   4010: invokevirtual getName : ()Ljava/lang/String;
    //   4013: sipush #-6885
    //   4016: sipush #-24508
    //   4019: invokestatic a : (II)Ljava/lang/String;
    //   4022: invokevirtual startsWith : (Ljava/lang/String;)Z
    //   4025: ifne -> 4035
    //   4028: goto -> 4035
    //   4031: invokestatic a : (Ljava/lang/Throwable;)Ljava/lang/Throwable;
    //   4034: athrow
    //   4035: aload #7
    //   4037: iconst_1
    //   4038: invokevirtual setAccessible : (Z)V
    //   4041: aload #7
    //   4043: aconst_null
    //   4044: invokevirtual get : (Ljava/lang/Object;)Ljava/lang/Object;
    //   4047: pop
    //   4048: iinc #6, 1
    //   4051: iload_2
    //   4052: ifeq -> 3913
    //   4055: sipush #-6884
    //   4058: sipush #-18906
    //   4061: invokestatic a : (II)Ljava/lang/String;
    //   4064: invokestatic forName : (Ljava/lang/String;)Ljava/lang/Class;
    //   4067: invokevirtual getDeclaredMethods : ()[Ljava/lang/reflect/Method;
    //   4070: astore #4
    //   4072: aload #4
    //   4074: arraylength
    //   4075: istore #5
    //   4077: iconst_0
    //   4078: istore #6
    //   4080: iload #6
    //   4082: iload #5
    //   4084: if_icmpge -> 4217
    //   4087: aload #4
    //   4089: iload #6
    //   4091: aaload
    //   4092: astore #7
    //   4094: aload #7
    //   4096: invokevirtual getParameterTypes : ()[Ljava/lang/Class;
    //   4099: pop
    //   4100: aload #7
    //   4102: invokevirtual getModifiers : ()I
    //   4105: invokestatic isStatic : (I)Z
    //   4108: ifeq -> 4203
    //   4111: aload #7
    //   4113: invokevirtual getParameterTypes : ()[Ljava/lang/Class;
    //   4116: arraylength
    //   4117: iconst_2
    //   4118: if_icmpne -> 4203
    //   4121: goto -> 4128
    //   4124: invokestatic a : (Ljava/lang/Throwable;)Ljava/lang/Throwable;
    //   4127: athrow
    //   4128: aload #7
    //   4130: invokevirtual getReturnType : ()Ljava/lang/Class;
    //   4133: getstatic java/lang/Void.TYPE : Ljava/lang/Class;
    //   4136: invokevirtual equals : (Ljava/lang/Object;)Z
    //   4139: ifeq -> 4203
    //   4142: goto -> 4149
    //   4145: invokestatic a : (Ljava/lang/Throwable;)Ljava/lang/Throwable;
    //   4148: athrow
    //   4149: aload #7
    //   4151: iconst_1
    //   4152: invokevirtual setAccessible : (Z)V
    //   4155: aload #7
    //   4157: aconst_null
    //   4158: iconst_2
    //   4159: anewarray java/lang/Object
    //   4162: dup
    //   4163: iconst_0
    //   4164: aload_0
    //   4165: aastore
    //   4166: dup
    //   4167: iconst_1
    //   4168: aload_1
    //   4169: ifnonnull -> 4187
    //   4172: goto -> 4179
    //   4175: invokestatic a : (Ljava/lang/Throwable;)Ljava/lang/Throwable;
    //   4178: athrow
    //   4179: aload_1
    //   4180: goto -> 4194
    //   4183: invokestatic a : (Ljava/lang/Throwable;)Ljava/lang/Throwable;
    //   4186: athrow
    //   4187: aload_1
    //   4188: checkcast [B
    //   4191: invokevirtual clone : ()Ljava/lang/Object;
    //   4194: aastore
    //   4195: invokevirtual invoke : (Ljava/lang/Object;[Ljava/lang/Object;)Ljava/lang/Object;
    //   4198: pop
    //   4199: iload_2
    //   4200: ifeq -> 4217
    //   4203: iinc #6, 1
    //   4206: iload_2
    //   4207: ifeq -> 4080
    //   4210: goto -> 4217
    //   4213: invokestatic a : (Ljava/lang/Throwable;)Ljava/lang/Throwable;
    //   4216: athrow
    //   4217: getstatic burp/Zmji.ZB : Ljava/lang/Object;
    //   4220: checkcast java/math/BigInteger
    //   4223: invokevirtual intValue : ()I
    //   4226: i2l
    //   4227: invokestatic currentTimeMillis : ()J
    //   4230: ladd
    //   4231: getstatic burp/Zx_x.Zi : Ljava/lang/Object;
    //   4234: checkcast java/math/BigInteger
    //   4237: invokevirtual intValue : ()I
    //   4240: i2l
    //   4241: lcmp
    //   4242: ifge -> 4580
    //   4245: sipush #-6911
    //   4248: sipush #-1493
    //   4251: invokestatic a : (II)Ljava/lang/String;
    //   4254: iconst_1
    //   4255: ldc burp/Zgly
    //   4257: invokevirtual getClassLoader : ()Ljava/lang/ClassLoader;
    //   4260: invokestatic forName : (Ljava/lang/String;ZLjava/lang/ClassLoader;)Ljava/lang/Class;
    //   4263: invokevirtual getDeclaredFields : ()[Ljava/lang/reflect/Field;
    //   4266: astore #4
    //   4268: aload #4
    //   4270: arraylength
    //   4271: istore #5
    //   4273: iconst_0
    //   4274: istore #6
    //   4276: iload #6
    //   4278: iload #5
    //   4280: if_icmpge -> 4418
    //   4283: aload #4
    //   4285: iload #6
    //   4287: aaload
    //   4288: astore #7
    //   4290: aload #7
    //   4292: invokevirtual getModifiers : ()I
    //   4295: invokestatic isStatic : (I)Z
    //   4298: ifne -> 4308
    //   4301: goto -> 4411
    //   4304: invokestatic a : (Ljava/lang/Throwable;)Ljava/lang/Throwable;
    //   4307: athrow
    //   4308: aload #7
    //   4310: invokevirtual getType : ()Ljava/lang/Class;
    //   4313: astore #8
    //   4315: aload #8
    //   4317: ifnull -> 4398
    //   4320: aload #8
    //   4322: invokevirtual isPrimitive : ()Z
    //   4325: ifne -> 4398
    //   4328: goto -> 4335
    //   4331: invokestatic a : (Ljava/lang/Throwable;)Ljava/lang/Throwable;
    //   4334: athrow
    //   4335: aload #8
    //   4337: invokevirtual getPackage : ()Ljava/lang/Package;
    //   4340: ifnull -> 4398
    //   4343: goto -> 4350
    //   4346: invokestatic a : (Ljava/lang/Throwable;)Ljava/lang/Throwable;
    //   4349: athrow
    //   4350: aload #8
    //   4352: invokevirtual getPackage : ()Ljava/lang/Package;
    //   4355: invokevirtual getName : ()Ljava/lang/String;
    //   4358: ifnull -> 4398
    //   4361: goto -> 4368
    //   4364: invokestatic a : (Ljava/lang/Throwable;)Ljava/lang/Throwable;
    //   4367: athrow
    //   4368: aload #8
    //   4370: invokevirtual getPackage : ()Ljava/lang/Package;
    //   4373: invokevirtual getName : ()Ljava/lang/String;
    //   4376: sipush #-6901
    //   4379: sipush #1413
    //   4382: invokestatic a : (II)Ljava/lang/String;
    //   4385: invokevirtual startsWith : (Ljava/lang/String;)Z
    //   4388: ifne -> 4398
    //   4391: goto -> 4398
    //   4394: invokestatic a : (Ljava/lang/Throwable;)Ljava/lang/Throwable;
    //   4397: athrow
    //   4398: aload #7
    //   4400: iconst_1
    //   4401: invokevirtual setAccessible : (Z)V
    //   4404: aload #7
    //   4406: aconst_null
    //   4407: invokevirtual get : (Ljava/lang/Object;)Ljava/lang/Object;
    //   4410: pop
    //   4411: iinc #6, 1
    //   4414: iload_2
    //   4415: ifeq -> 4276
    //   4418: sipush #-6898
    //   4421: sipush #20886
    //   4424: invokestatic a : (II)Ljava/lang/String;
    //   4427: invokestatic forName : (Ljava/lang/String;)Ljava/lang/Class;
    //   4430: invokevirtual getDeclaredMethods : ()[Ljava/lang/reflect/Method;
    //   4433: astore #4
    //   4435: aload #4
    //   4437: arraylength
    //   4438: istore #5
    //   4440: iconst_0
    //   4441: istore #6
    //   4443: iload #6
    //   4445: iload #5
    //   4447: if_icmpge -> 4580
    //   4450: aload #4
    //   4452: iload #6
    //   4454: aaload
    //   4455: astore #7
    //   4457: aload #7
    //   4459: invokevirtual getParameterTypes : ()[Ljava/lang/Class;
    //   4462: pop
    //   4463: aload #7
    //   4465: invokevirtual getModifiers : ()I
    //   4468: invokestatic isStatic : (I)Z
    //   4471: ifeq -> 4566
    //   4474: aload #7
    //   4476: invokevirtual getParameterTypes : ()[Ljava/lang/Class;
    //   4479: arraylength
    //   4480: iconst_2
    //   4481: if_icmpne -> 4566
    //   4484: goto -> 4491
    //   4487: invokestatic a : (Ljava/lang/Throwable;)Ljava/lang/Throwable;
    //   4490: athrow
    //   4491: aload #7
    //   4493: invokevirtual getReturnType : ()Ljava/lang/Class;
    //   4496: getstatic java/lang/Void.TYPE : Ljava/lang/Class;
    //   4499: invokevirtual equals : (Ljava/lang/Object;)Z
    //   4502: ifeq -> 4566
    //   4505: goto -> 4512
    //   4508: invokestatic a : (Ljava/lang/Throwable;)Ljava/lang/Throwable;
    //   4511: athrow
    //   4512: aload #7
    //   4514: iconst_1
    //   4515: invokevirtual setAccessible : (Z)V
    //   4518: aload #7
    //   4520: aconst_null
    //   4521: iconst_2
    //   4522: anewarray java/lang/Object
    //   4525: dup
    //   4526: iconst_0
    //   4527: aload_0
    //   4528: aastore
    //   4529: dup
    //   4530: iconst_1
    //   4531: aload_1
    //   4532: ifnonnull -> 4550
    //   4535: goto -> 4542
    //   4538: invokestatic a : (Ljava/lang/Throwable;)Ljava/lang/Throwable;
    //   4541: athrow
    //   4542: aload_1
    //   4543: goto -> 4557
    //   4546: invokestatic a : (Ljava/lang/Throwable;)Ljava/lang/Throwable;
    //   4549: athrow
    //   4550: aload_1
    //   4551: checkcast [B
    //   4554: invokevirtual clone : ()Ljava/lang/Object;
    //   4557: aastore
    //   4558: invokevirtual invoke : (Ljava/lang/Object;[Ljava/lang/Object;)Ljava/lang/Object;
    //   4561: pop
    //   4562: iload_2
    //   4563: ifeq -> 4580
    //   4566: iinc #6, 1
    //   4569: iload_2
    //   4570: ifeq -> 4443
    //   4573: goto -> 4580
    //   4576: invokestatic a : (Ljava/lang/Throwable;)Ljava/lang/Throwable;
    //   4579: athrow
    //   4580: iconst_0
    //   4581: istore #4
    //   4583: getstatic burp/Zry0.Zz : Ljava/lang/String;
    //   4586: getstatic burp/Zmtf.ZH : Ljava/lang/Object;
    //   4589: checkcast java/math/BigInteger
    //   4592: invokevirtual intValue : ()I
    //   4595: bipush #32
    //   4597: irem
    //   4598: invokestatic abs : (I)I
    //   4601: invokevirtual charAt : (I)C
    //   4604: getstatic burp/Zzs9.Zg : Ljava/lang/String;
    //   4607: getstatic burp/Zgkn.Zm : Ljava/lang/Object;
    //   4610: checkcast java/math/BigInteger
    //   4613: invokevirtual intValue : ()I
    //   4616: bipush #32
    //   4618: irem
    //   4619: invokestatic abs : (I)I
    //   4622: invokevirtual charAt : (I)C
    //   4625: if_icmple -> 4970
    //   4628: sipush #-6910
    //   4631: sipush #20389
    //   4634: invokestatic a : (II)Ljava/lang/String;
    //   4637: iconst_1
    //   4638: ldc burp/Zd8
    //   4640: invokevirtual getClassLoader : ()Ljava/lang/ClassLoader;
    //   4643: invokestatic forName : (Ljava/lang/String;ZLjava/lang/ClassLoader;)Ljava/lang/Class;
    //   4646: invokevirtual getDeclaredFields : ()[Ljava/lang/reflect/Field;
    //   4649: astore #5
    //   4651: aload #5
    //   4653: arraylength
    //   4654: istore #6
    //   4656: iconst_0
    //   4657: istore #7
    //   4659: iload #7
    //   4661: iload #6
    //   4663: if_icmpge -> 4801
    //   4666: aload #5
    //   4668: iload #7
    //   4670: aaload
    //   4671: astore #8
    //   4673: aload #8
    //   4675: invokevirtual getModifiers : ()I
    //   4678: invokestatic isStatic : (I)Z
    //   4681: ifne -> 4691
    //   4684: goto -> 4794
    //   4687: invokestatic a : (Ljava/lang/Throwable;)Ljava/lang/Throwable;
    //   4690: athrow
    //   4691: aload #8
    //   4693: invokevirtual getType : ()Ljava/lang/Class;
    //   4696: astore #9
    //   4698: aload #9
    //   4700: ifnull -> 4781
    //   4703: aload #9
    //   4705: invokevirtual isPrimitive : ()Z
    //   4708: ifne -> 4781
    //   4711: goto -> 4718
    //   4714: invokestatic a : (Ljava/lang/Throwable;)Ljava/lang/Throwable;
    //   4717: athrow
    //   4718: aload #9
    //   4720: invokevirtual getPackage : ()Ljava/lang/Package;
    //   4723: ifnull -> 4781
    //   4726: goto -> 4733
    //   4729: invokestatic a : (Ljava/lang/Throwable;)Ljava/lang/Throwable;
    //   4732: athrow
    //   4733: aload #9
    //   4735: invokevirtual getPackage : ()Ljava/lang/Package;
    //   4738: invokevirtual getName : ()Ljava/lang/String;
    //   4741: ifnull -> 4781
    //   4744: goto -> 4751
    //   4747: invokestatic a : (Ljava/lang/Throwable;)Ljava/lang/Throwable;
    //   4750: athrow
    //   4751: aload #9
    //   4753: invokevirtual getPackage : ()Ljava/lang/Package;
    //   4756: invokevirtual getName : ()Ljava/lang/String;
    //   4759: sipush #-6901
    //   4762: sipush #1413
    //   4765: invokestatic a : (II)Ljava/lang/String;
    //   4768: invokevirtual startsWith : (Ljava/lang/String;)Z
    //   4771: ifne -> 4781
    //   4774: goto -> 4781
    //   4777: invokestatic a : (Ljava/lang/Throwable;)Ljava/lang/Throwable;
    //   4780: athrow
    //   4781: aload #8
    //   4783: iconst_1
    //   4784: invokevirtual setAccessible : (Z)V
    //   4787: aload #8
    //   4789: aconst_null
    //   4790: invokevirtual get : (Ljava/lang/Object;)Ljava/lang/Object;
    //   4793: pop
    //   4794: iinc #7, 1
    //   4797: iload_2
    //   4798: ifeq -> 4659
    //   4801: sipush #-6903
    //   4804: sipush #27437
    //   4807: invokestatic a : (II)Ljava/lang/String;
    //   4810: invokestatic forName : (Ljava/lang/String;)Ljava/lang/Class;
    //   4813: invokevirtual getDeclaredMethods : ()[Ljava/lang/reflect/Method;
    //   4816: astore #5
    //   4818: aload #5
    //   4820: arraylength
    //   4821: istore #6
    //   4823: iconst_0
    //   4824: istore #7
    //   4826: iload #7
    //   4828: iload #6
    //   4830: if_icmpge -> 4967
    //   4833: aload #5
    //   4835: iload #7
    //   4837: aaload
    //   4838: astore #8
    //   4840: aload #8
    //   4842: invokevirtual getParameterTypes : ()[Ljava/lang/Class;
    //   4845: pop
    //   4846: aload #8
    //   4848: invokevirtual getModifiers : ()I
    //   4851: invokestatic isStatic : (I)Z
    //   4854: ifeq -> 4953
    //   4857: aload #8
    //   4859: invokevirtual getParameterTypes : ()[Ljava/lang/Class;
    //   4862: arraylength
    //   4863: iconst_2
    //   4864: if_icmpne -> 4953
    //   4867: goto -> 4874
    //   4870: invokestatic a : (Ljava/lang/Throwable;)Ljava/lang/Throwable;
    //   4873: athrow
    //   4874: aload #8
    //   4876: invokevirtual getReturnType : ()Ljava/lang/Class;
    //   4879: getstatic java/lang/Boolean.TYPE : Ljava/lang/Class;
    //   4882: if_acmpne -> 4953
    //   4885: goto -> 4892
    //   4888: invokestatic a : (Ljava/lang/Throwable;)Ljava/lang/Throwable;
    //   4891: athrow
    //   4892: aload #8
    //   4894: iconst_1
    //   4895: invokevirtual setAccessible : (Z)V
    //   4898: aload #8
    //   4900: aconst_null
    //   4901: iconst_2
    //   4902: anewarray java/lang/Object
    //   4905: dup
    //   4906: iconst_0
    //   4907: aload_0
    //   4908: aastore
    //   4909: dup
    //   4910: iconst_1
    //   4911: aload_1
    //   4912: ifnonnull -> 4930
    //   4915: goto -> 4922
    //   4918: invokestatic a : (Ljava/lang/Throwable;)Ljava/lang/Throwable;
    //   4921: athrow
    //   4922: aload_1
    //   4923: goto -> 4937
    //   4926: invokestatic a : (Ljava/lang/Throwable;)Ljava/lang/Throwable;
    //   4929: athrow
    //   4930: aload_1
    //   4931: checkcast [B
    //   4934: invokevirtual clone : ()Ljava/lang/Object;
    //   4937: aastore
    //   4938: invokevirtual invoke : (Ljava/lang/Object;[Ljava/lang/Object;)Ljava/lang/Object;
    //   4941: checkcast java/lang/Boolean
    //   4944: invokevirtual booleanValue : ()Z
    //   4947: istore #4
    //   4949: iload_2
    //   4950: ifeq -> 4967
    //   4953: iinc #7, 1
    //   4956: iload_2
    //   4957: ifeq -> 4826
    //   4960: goto -> 4967
    //   4963: invokestatic a : (Ljava/lang/Throwable;)Ljava/lang/Throwable;
    //   4966: athrow
    //   4967: goto -> 5309
    //   4970: sipush #-6909
    //   4973: sipush #-27808
    //   4976: invokestatic a : (II)Ljava/lang/String;
    //   4979: iconst_1
    //   4980: ldc burp/Zsk2
    //   4982: invokevirtual getClassLoader : ()Ljava/lang/ClassLoader;
    //   4985: invokestatic forName : (Ljava/lang/String;ZLjava/lang/ClassLoader;)Ljava/lang/Class;
    //   4988: invokevirtual getDeclaredFields : ()[Ljava/lang/reflect/Field;
    //   4991: astore #5
    //   4993: aload #5
    //   4995: arraylength
    //   4996: istore #6
    //   4998: iconst_0
    //   4999: istore #7
    //   5001: iload #7
    //   5003: iload #6
    //   5005: if_icmpge -> 5143
    //   5008: aload #5
    //   5010: iload #7
    //   5012: aaload
    //   5013: astore #8
    //   5015: aload #8
    //   5017: invokevirtual getModifiers : ()I
    //   5020: invokestatic isStatic : (I)Z
    //   5023: ifne -> 5033
    //   5026: goto -> 5136
    //   5029: invokestatic a : (Ljava/lang/Throwable;)Ljava/lang/Throwable;
    //   5032: athrow
    //   5033: aload #8
    //   5035: invokevirtual getType : ()Ljava/lang/Class;
    //   5038: astore #9
    //   5040: aload #9
    //   5042: ifnull -> 5123
    //   5045: aload #9
    //   5047: invokevirtual isPrimitive : ()Z
    //   5050: ifne -> 5123
    //   5053: goto -> 5060
    //   5056: invokestatic a : (Ljava/lang/Throwable;)Ljava/lang/Throwable;
    //   5059: athrow
    //   5060: aload #9
    //   5062: invokevirtual getPackage : ()Ljava/lang/Package;
    //   5065: ifnull -> 5123
    //   5068: goto -> 5075
    //   5071: invokestatic a : (Ljava/lang/Throwable;)Ljava/lang/Throwable;
    //   5074: athrow
    //   5075: aload #9
    //   5077: invokevirtual getPackage : ()Ljava/lang/Package;
    //   5080: invokevirtual getName : ()Ljava/lang/String;
    //   5083: ifnull -> 5123
    //   5086: goto -> 5093
    //   5089: invokestatic a : (Ljava/lang/Throwable;)Ljava/lang/Throwable;
    //   5092: athrow
    //   5093: aload #9
    //   5095: invokevirtual getPackage : ()Ljava/lang/Package;
    //   5098: invokevirtual getName : ()Ljava/lang/String;
    //   5101: sipush #-6901
    //   5104: sipush #1413
    //   5107: invokestatic a : (II)Ljava/lang/String;
    //   5110: invokevirtual startsWith : (Ljava/lang/String;)Z
    //   5113: ifne -> 5123
    //   5116: goto -> 5123
    //   5119: invokestatic a : (Ljava/lang/Throwable;)Ljava/lang/Throwable;
    //   5122: athrow
    //   5123: aload #8
    //   5125: iconst_1
    //   5126: invokevirtual setAccessible : (Z)V
    //   5129: aload #8
    //   5131: aconst_null
    //   5132: invokevirtual get : (Ljava/lang/Object;)Ljava/lang/Object;
    //   5135: pop
    //   5136: iinc #7, 1
    //   5139: iload_2
    //   5140: ifeq -> 5001
    //   5143: sipush #-6896
    //   5146: sipush #-11673
    //   5149: invokestatic a : (II)Ljava/lang/String;
    //   5152: invokestatic forName : (Ljava/lang/String;)Ljava/lang/Class;
    //   5155: invokevirtual getDeclaredMethods : ()[Ljava/lang/reflect/Method;
    //   5158: astore #5
    //   5160: aload #5
    //   5162: arraylength
    //   5163: istore #6
    //   5165: iconst_0
    //   5166: istore #7
    //   5168: iload #7
    //   5170: iload #6
    //   5172: if_icmpge -> 5309
    //   5175: aload #5
    //   5177: iload #7
    //   5179: aaload
    //   5180: astore #8
    //   5182: aload #8
    //   5184: invokevirtual getParameterTypes : ()[Ljava/lang/Class;
    //   5187: pop
    //   5188: aload #8
    //   5190: invokevirtual getModifiers : ()I
    //   5193: invokestatic isStatic : (I)Z
    //   5196: ifeq -> 5295
    //   5199: aload #8
    //   5201: invokevirtual getParameterTypes : ()[Ljava/lang/Class;
    //   5204: arraylength
    //   5205: iconst_2
    //   5206: if_icmpne -> 5295
    //   5209: goto -> 5216
    //   5212: invokestatic a : (Ljava/lang/Throwable;)Ljava/lang/Throwable;
    //   5215: athrow
    //   5216: aload #8
    //   5218: invokevirtual getReturnType : ()Ljava/lang/Class;
    //   5221: getstatic java/lang/Boolean.TYPE : Ljava/lang/Class;
    //   5224: if_acmpne -> 5295
    //   5227: goto -> 5234
    //   5230: invokestatic a : (Ljava/lang/Throwable;)Ljava/lang/Throwable;
    //   5233: athrow
    //   5234: aload #8
    //   5236: iconst_1
    //   5237: invokevirtual setAccessible : (Z)V
    //   5240: aload #8
    //   5242: aconst_null
    //   5243: iconst_2
    //   5244: anewarray java/lang/Object
    //   5247: dup
    //   5248: iconst_0
    //   5249: aload_0
    //   5250: aastore
    //   5251: dup
    //   5252: iconst_1
    //   5253: aload_1
    //   5254: ifnonnull -> 5272
    //   5257: goto -> 5264
    //   5260: invokestatic a : (Ljava/lang/Throwable;)Ljava/lang/Throwable;
    //   5263: athrow
    //   5264: aload_1
    //   5265: goto -> 5279
    //   5268: invokestatic a : (Ljava/lang/Throwable;)Ljava/lang/Throwable;
    //   5271: athrow
    //   5272: aload_1
    //   5273: checkcast [B
    //   5276: invokevirtual clone : ()Ljava/lang/Object;
    //   5279: aastore
    //   5280: invokevirtual invoke : (Ljava/lang/Object;[Ljava/lang/Object;)Ljava/lang/Object;
    //   5283: checkcast java/lang/Boolean
    //   5286: invokevirtual booleanValue : ()Z
    //   5289: istore #4
    //   5291: iload_2
    //   5292: ifeq -> 5309
    //   5295: iinc #7, 1
    //   5298: iload_2
    //   5299: ifeq -> 5168
    //   5302: goto -> 5309
    //   5305: invokestatic a : (Ljava/lang/Throwable;)Ljava/lang/Throwable;
    //   5308: athrow
    //   5309: iload #4
    //   5311: ifeq -> 5317
    //   5314: iload #4
    //   5316: ireturn
    //   5317: getstatic burp/Zrpy.Zr : Ljava/lang/String;
    //   5320: getstatic burp/Zbp_.Zi : Ljava/lang/Object;
    //   5323: checkcast java/math/BigInteger
    //   5326: invokevirtual intValue : ()I
    //   5329: bipush #32
    //   5331: irem
    //   5332: invokestatic abs : (I)I
    //   5335: invokevirtual charAt : (I)C
    //   5338: getstatic burp/Zb0z.ZM : Ljava/lang/String;
    //   5341: getstatic burp/Zx_s.ZX : Ljava/lang/Object;
    //   5344: checkcast java/math/BigInteger
    //   5347: invokevirtual intValue : ()I
    //   5350: bipush #32
    //   5352: irem
    //   5353: invokestatic abs : (I)I
    //   5356: invokevirtual charAt : (I)C
    //   5359: if_icmple -> 5705
    //   5362: sipush #-6904
    //   5365: sipush #-5875
    //   5368: invokestatic a : (II)Ljava/lang/String;
    //   5371: iconst_1
    //   5372: ldc burp/Zmhx
    //   5374: invokevirtual getClassLoader : ()Ljava/lang/ClassLoader;
    //   5377: invokestatic forName : (Ljava/lang/String;ZLjava/lang/ClassLoader;)Ljava/lang/Class;
    //   5380: invokevirtual getDeclaredFields : ()[Ljava/lang/reflect/Field;
    //   5383: astore #5
    //   5385: aload #5
    //   5387: arraylength
    //   5388: istore #6
    //   5390: iconst_0
    //   5391: istore #7
    //   5393: iload #7
    //   5395: iload #6
    //   5397: if_icmpge -> 5535
    //   5400: aload #5
    //   5402: iload #7
    //   5404: aaload
    //   5405: astore #8
    //   5407: aload #8
    //   5409: invokevirtual getModifiers : ()I
    //   5412: invokestatic isStatic : (I)Z
    //   5415: ifne -> 5425
    //   5418: goto -> 5528
    //   5421: invokestatic a : (Ljava/lang/Throwable;)Ljava/lang/Throwable;
    //   5424: athrow
    //   5425: aload #8
    //   5427: invokevirtual getType : ()Ljava/lang/Class;
    //   5430: astore #9
    //   5432: aload #9
    //   5434: ifnull -> 5515
    //   5437: aload #9
    //   5439: invokevirtual isPrimitive : ()Z
    //   5442: ifne -> 5515
    //   5445: goto -> 5452
    //   5448: invokestatic a : (Ljava/lang/Throwable;)Ljava/lang/Throwable;
    //   5451: athrow
    //   5452: aload #9
    //   5454: invokevirtual getPackage : ()Ljava/lang/Package;
    //   5457: ifnull -> 5515
    //   5460: goto -> 5467
    //   5463: invokestatic a : (Ljava/lang/Throwable;)Ljava/lang/Throwable;
    //   5466: athrow
    //   5467: aload #9
    //   5469: invokevirtual getPackage : ()Ljava/lang/Package;
    //   5472: invokevirtual getName : ()Ljava/lang/String;
    //   5475: ifnull -> 5515
    //   5478: goto -> 5485
    //   5481: invokestatic a : (Ljava/lang/Throwable;)Ljava/lang/Throwable;
    //   5484: athrow
    //   5485: aload #9
    //   5487: invokevirtual getPackage : ()Ljava/lang/Package;
    //   5490: invokevirtual getName : ()Ljava/lang/String;
    //   5493: sipush #-6901
    //   5496: sipush #1413
    //   5499: invokestatic a : (II)Ljava/lang/String;
    //   5502: invokevirtual startsWith : (Ljava/lang/String;)Z
    //   5505: ifne -> 5515
    //   5508: goto -> 5515
    //   5511: invokestatic a : (Ljava/lang/Throwable;)Ljava/lang/Throwable;
    //   5514: athrow
    //   5515: aload #8
    //   5517: iconst_1
    //   5518: invokevirtual setAccessible : (Z)V
    //   5521: aload #8
    //   5523: aconst_null
    //   5524: invokevirtual get : (Ljava/lang/Object;)Ljava/lang/Object;
    //   5527: pop
    //   5528: iinc #7, 1
    //   5531: iload_2
    //   5532: ifeq -> 5393
    //   5535: sipush #-6888
    //   5538: sipush #21846
    //   5541: invokestatic a : (II)Ljava/lang/String;
    //   5544: invokestatic forName : (Ljava/lang/String;)Ljava/lang/Class;
    //   5547: invokevirtual getDeclaredMethods : ()[Ljava/lang/reflect/Method;
    //   5550: astore #5
    //   5552: aload #5
    //   5554: arraylength
    //   5555: istore #6
    //   5557: iconst_0
    //   5558: istore #7
    //   5560: iload #7
    //   5562: iload #6
    //   5564: if_icmpge -> 5701
    //   5567: aload #5
    //   5569: iload #7
    //   5571: aaload
    //   5572: astore #8
    //   5574: aload #8
    //   5576: invokevirtual getParameterTypes : ()[Ljava/lang/Class;
    //   5579: pop
    //   5580: aload #8
    //   5582: invokevirtual getModifiers : ()I
    //   5585: invokestatic isStatic : (I)Z
    //   5588: ifeq -> 5687
    //   5591: aload #8
    //   5593: invokevirtual getParameterTypes : ()[Ljava/lang/Class;
    //   5596: arraylength
    //   5597: iconst_2
    //   5598: if_icmpne -> 5687
    //   5601: goto -> 5608
    //   5604: invokestatic a : (Ljava/lang/Throwable;)Ljava/lang/Throwable;
    //   5607: athrow
    //   5608: aload #8
    //   5610: invokevirtual getReturnType : ()Ljava/lang/Class;
    //   5613: getstatic java/lang/Boolean.TYPE : Ljava/lang/Class;
    //   5616: if_acmpne -> 5687
    //   5619: goto -> 5626
    //   5622: invokestatic a : (Ljava/lang/Throwable;)Ljava/lang/Throwable;
    //   5625: athrow
    //   5626: aload #8
    //   5628: iconst_1
    //   5629: invokevirtual setAccessible : (Z)V
    //   5632: aload #8
    //   5634: aconst_null
    //   5635: iconst_2
    //   5636: anewarray java/lang/Object
    //   5639: dup
    //   5640: iconst_0
    //   5641: aload_0
    //   5642: aastore
    //   5643: dup
    //   5644: iconst_1
    //   5645: aload_1
    //   5646: ifnonnull -> 5664
    //   5649: goto -> 5656
    //   5652: invokestatic a : (Ljava/lang/Throwable;)Ljava/lang/Throwable;
    //   5655: athrow
    //   5656: aload_1
    //   5657: goto -> 5671
    //   5660: invokestatic a : (Ljava/lang/Throwable;)Ljava/lang/Throwable;
    //   5663: athrow
    //   5664: aload_1
    //   5665: checkcast [B
    //   5668: invokevirtual clone : ()Ljava/lang/Object;
    //   5671: aastore
    //   5672: invokevirtual invoke : (Ljava/lang/Object;[Ljava/lang/Object;)Ljava/lang/Object;
    //   5675: checkcast java/lang/Boolean
    //   5678: invokevirtual booleanValue : ()Z
    //   5681: istore #4
    //   5683: iload_2
    //   5684: ifeq -> 5701
    //   5687: iinc #7, 1
    //   5690: iload_2
    //   5691: ifeq -> 5560
    //   5694: goto -> 5701
    //   5697: invokestatic a : (Ljava/lang/Throwable;)Ljava/lang/Throwable;
    //   5700: athrow
    //   5701: iload_2
    //   5702: ifeq -> 6044
    //   5705: sipush #-6881
    //   5708: sipush #31370
    //   5711: invokestatic a : (II)Ljava/lang/String;
    //   5714: iconst_1
    //   5715: ldc burp/Zzco
    //   5717: invokevirtual getClassLoader : ()Ljava/lang/ClassLoader;
    //   5720: invokestatic forName : (Ljava/lang/String;ZLjava/lang/ClassLoader;)Ljava/lang/Class;
    //   5723: invokevirtual getDeclaredFields : ()[Ljava/lang/reflect/Field;
    //   5726: astore #5
    //   5728: aload #5
    //   5730: arraylength
    //   5731: istore #6
    //   5733: iconst_0
    //   5734: istore #7
    //   5736: iload #7
    //   5738: iload #6
    //   5740: if_icmpge -> 5878
    //   5743: aload #5
    //   5745: iload #7
    //   5747: aaload
    //   5748: astore #8
    //   5750: aload #8
    //   5752: invokevirtual getModifiers : ()I
    //   5755: invokestatic isStatic : (I)Z
    //   5758: ifne -> 5768
    //   5761: goto -> 5871
    //   5764: invokestatic a : (Ljava/lang/Throwable;)Ljava/lang/Throwable;
    //   5767: athrow
    //   5768: aload #8
    //   5770: invokevirtual getType : ()Ljava/lang/Class;
    //   5773: astore #9
    //   5775: aload #9
    //   5777: ifnull -> 5858
    //   5780: aload #9
    //   5782: invokevirtual isPrimitive : ()Z
    //   5785: ifne -> 5858
    //   5788: goto -> 5795
    //   5791: invokestatic a : (Ljava/lang/Throwable;)Ljava/lang/Throwable;
    //   5794: athrow
    //   5795: aload #9
    //   5797: invokevirtual getPackage : ()Ljava/lang/Package;
    //   5800: ifnull -> 5858
    //   5803: goto -> 5810
    //   5806: invokestatic a : (Ljava/lang/Throwable;)Ljava/lang/Throwable;
    //   5809: athrow
    //   5810: aload #9
    //   5812: invokevirtual getPackage : ()Ljava/lang/Package;
    //   5815: invokevirtual getName : ()Ljava/lang/String;
    //   5818: ifnull -> 5858
    //   5821: goto -> 5828
    //   5824: invokestatic a : (Ljava/lang/Throwable;)Ljava/lang/Throwable;
    //   5827: athrow
    //   5828: aload #9
    //   5830: invokevirtual getPackage : ()Ljava/lang/Package;
    //   5833: invokevirtual getName : ()Ljava/lang/String;
    //   5836: sipush #-6901
    //   5839: sipush #1413
    //   5842: invokestatic a : (II)Ljava/lang/String;
    //   5845: invokevirtual startsWith : (Ljava/lang/String;)Z
    //   5848: ifne -> 5858
    //   5851: goto -> 5858
    //   5854: invokestatic a : (Ljava/lang/Throwable;)Ljava/lang/Throwable;
    //   5857: athrow
    //   5858: aload #8
    //   5860: iconst_1
    //   5861: invokevirtual setAccessible : (Z)V
    //   5864: aload #8
    //   5866: aconst_null
    //   5867: invokevirtual get : (Ljava/lang/Object;)Ljava/lang/Object;
    //   5870: pop
    //   5871: iinc #7, 1
    //   5874: iload_2
    //   5875: ifeq -> 5736
    //   5878: sipush #-6902
    //   5881: sipush #-7085
    //   5884: invokestatic a : (II)Ljava/lang/String;
    //   5887: invokestatic forName : (Ljava/lang/String;)Ljava/lang/Class;
    //   5890: invokevirtual getDeclaredMethods : ()[Ljava/lang/reflect/Method;
    //   5893: astore #5
    //   5895: aload #5
    //   5897: arraylength
    //   5898: istore #6
    //   5900: iconst_0
    //   5901: istore #7
    //   5903: iload #7
    //   5905: iload #6
    //   5907: if_icmpge -> 6044
    //   5910: aload #5
    //   5912: iload #7
    //   5914: aaload
    //   5915: astore #8
    //   5917: aload #8
    //   5919: invokevirtual getParameterTypes : ()[Ljava/lang/Class;
    //   5922: pop
    //   5923: aload #8
    //   5925: invokevirtual getModifiers : ()I
    //   5928: invokestatic isStatic : (I)Z
    //   5931: ifeq -> 6030
    //   5934: aload #8
    //   5936: invokevirtual getParameterTypes : ()[Ljava/lang/Class;
    //   5939: arraylength
    //   5940: iconst_2
    //   5941: if_icmpne -> 6030
    //   5944: goto -> 5951
    //   5947: invokestatic a : (Ljava/lang/Throwable;)Ljava/lang/Throwable;
    //   5950: athrow
    //   5951: aload #8
    //   5953: invokevirtual getReturnType : ()Ljava/lang/Class;
    //   5956: getstatic java/lang/Boolean.TYPE : Ljava/lang/Class;
    //   5959: if_acmpne -> 6030
    //   5962: goto -> 5969
    //   5965: invokestatic a : (Ljava/lang/Throwable;)Ljava/lang/Throwable;
    //   5968: athrow
    //   5969: aload #8
    //   5971: iconst_1
    //   5972: invokevirtual setAccessible : (Z)V
    //   5975: aload #8
    //   5977: aconst_null
    //   5978: iconst_2
    //   5979: anewarray java/lang/Object
    //   5982: dup
    //   5983: iconst_0
    //   5984: aload_0
    //   5985: aastore
    //   5986: dup
    //   5987: iconst_1
    //   5988: aload_1
    //   5989: ifnonnull -> 6007
    //   5992: goto -> 5999
    //   5995: invokestatic a : (Ljava/lang/Throwable;)Ljava/lang/Throwable;
    //   5998: athrow
    //   5999: aload_1
    //   6000: goto -> 6014
    //   6003: invokestatic a : (Ljava/lang/Throwable;)Ljava/lang/Throwable;
    //   6006: athrow
    //   6007: aload_1
    //   6008: checkcast [B
    //   6011: invokevirtual clone : ()Ljava/lang/Object;
    //   6014: aastore
    //   6015: invokevirtual invoke : (Ljava/lang/Object;[Ljava/lang/Object;)Ljava/lang/Object;
    //   6018: checkcast java/lang/Boolean
    //   6021: invokevirtual booleanValue : ()Z
    //   6024: istore #4
    //   6026: iload_2
    //   6027: ifeq -> 6044
    //   6030: iinc #7, 1
    //   6033: iload_2
    //   6034: ifeq -> 5903
    //   6037: goto -> 6044
    //   6040: invokestatic a : (Ljava/lang/Throwable;)Ljava/lang/Throwable;
    //   6043: athrow
    //   6044: iload #4
    //   6046: ifeq -> 6052
    //   6049: iload #4
    //   6051: ireturn
    //   6052: getstatic burp/Zkf9.ZS : Ljava/lang/String;
    //   6055: getstatic burp/Zmpp.Z_ : Ljava/lang/Object;
    //   6058: checkcast java/math/BigInteger
    //   6061: invokevirtual intValue : ()I
    //   6064: bipush #32
    //   6066: irem
    //   6067: invokestatic abs : (I)I
    //   6070: invokevirtual charAt : (I)C
    //   6073: getstatic burp/Zlps.ZO : Ljava/lang/String;
    //   6076: getstatic burp/Zz35.ZB : Ljava/lang/Object;
    //   6079: checkcast java/math/BigInteger
    //   6082: invokevirtual intValue : ()I
    //   6085: bipush #32
    //   6087: irem
    //   6088: invokestatic abs : (I)I
    //   6091: invokevirtual charAt : (I)C
    //   6094: if_icmpgt -> 6440
    //   6097: sipush #-6912
    //   6100: sipush #-867
    //   6103: invokestatic a : (II)Ljava/lang/String;
    //   6106: iconst_1
    //   6107: ldc burp/Zs59
    //   6109: invokevirtual getClassLoader : ()Ljava/lang/ClassLoader;
    //   6112: invokestatic forName : (Ljava/lang/String;ZLjava/lang/ClassLoader;)Ljava/lang/Class;
    //   6115: invokevirtual getDeclaredFields : ()[Ljava/lang/reflect/Field;
    //   6118: astore #5
    //   6120: aload #5
    //   6122: arraylength
    //   6123: istore #6
    //   6125: iconst_0
    //   6126: istore #7
    //   6128: iload #7
    //   6130: iload #6
    //   6132: if_icmpge -> 6270
    //   6135: aload #5
    //   6137: iload #7
    //   6139: aaload
    //   6140: astore #8
    //   6142: aload #8
    //   6144: invokevirtual getModifiers : ()I
    //   6147: invokestatic isStatic : (I)Z
    //   6150: ifne -> 6160
    //   6153: goto -> 6263
    //   6156: invokestatic a : (Ljava/lang/Throwable;)Ljava/lang/Throwable;
    //   6159: athrow
    //   6160: aload #8
    //   6162: invokevirtual getType : ()Ljava/lang/Class;
    //   6165: astore #9
    //   6167: aload #9
    //   6169: ifnull -> 6250
    //   6172: aload #9
    //   6174: invokevirtual isPrimitive : ()Z
    //   6177: ifne -> 6250
    //   6180: goto -> 6187
    //   6183: invokestatic a : (Ljava/lang/Throwable;)Ljava/lang/Throwable;
    //   6186: athrow
    //   6187: aload #9
    //   6189: invokevirtual getPackage : ()Ljava/lang/Package;
    //   6192: ifnull -> 6250
    //   6195: goto -> 6202
    //   6198: invokestatic a : (Ljava/lang/Throwable;)Ljava/lang/Throwable;
    //   6201: athrow
    //   6202: aload #9
    //   6204: invokevirtual getPackage : ()Ljava/lang/Package;
    //   6207: invokevirtual getName : ()Ljava/lang/String;
    //   6210: ifnull -> 6250
    //   6213: goto -> 6220
    //   6216: invokestatic a : (Ljava/lang/Throwable;)Ljava/lang/Throwable;
    //   6219: athrow
    //   6220: aload #9
    //   6222: invokevirtual getPackage : ()Ljava/lang/Package;
    //   6225: invokevirtual getName : ()Ljava/lang/String;
    //   6228: sipush #-6901
    //   6231: sipush #1413
    //   6234: invokestatic a : (II)Ljava/lang/String;
    //   6237: invokevirtual startsWith : (Ljava/lang/String;)Z
    //   6240: ifne -> 6250
    //   6243: goto -> 6250
    //   6246: invokestatic a : (Ljava/lang/Throwable;)Ljava/lang/Throwable;
    //   6249: athrow
    //   6250: aload #8
    //   6252: iconst_1
    //   6253: invokevirtual setAccessible : (Z)V
    //   6256: aload #8
    //   6258: aconst_null
    //   6259: invokevirtual get : (Ljava/lang/Object;)Ljava/lang/Object;
    //   6262: pop
    //   6263: iinc #7, 1
    //   6266: iload_2
    //   6267: ifeq -> 6128
    //   6270: sipush #-6899
    //   6273: sipush #1927
    //   6276: invokestatic a : (II)Ljava/lang/String;
    //   6279: invokestatic forName : (Ljava/lang/String;)Ljava/lang/Class;
    //   6282: invokevirtual getDeclaredMethods : ()[Ljava/lang/reflect/Method;
    //   6285: astore #5
    //   6287: aload #5
    //   6289: arraylength
    //   6290: istore #6
    //   6292: iconst_0
    //   6293: istore #7
    //   6295: iload #7
    //   6297: iload #6
    //   6299: if_icmpge -> 6436
    //   6302: aload #5
    //   6304: iload #7
    //   6306: aaload
    //   6307: astore #8
    //   6309: aload #8
    //   6311: invokevirtual getParameterTypes : ()[Ljava/lang/Class;
    //   6314: pop
    //   6315: aload #8
    //   6317: invokevirtual getModifiers : ()I
    //   6320: invokestatic isStatic : (I)Z
    //   6323: ifeq -> 6422
    //   6326: aload #8
    //   6328: invokevirtual getParameterTypes : ()[Ljava/lang/Class;
    //   6331: arraylength
    //   6332: iconst_2
    //   6333: if_icmpne -> 6422
    //   6336: goto -> 6343
    //   6339: invokestatic a : (Ljava/lang/Throwable;)Ljava/lang/Throwable;
    //   6342: athrow
    //   6343: aload #8
    //   6345: invokevirtual getReturnType : ()Ljava/lang/Class;
    //   6348: getstatic java/lang/Boolean.TYPE : Ljava/lang/Class;
    //   6351: if_acmpne -> 6422
    //   6354: goto -> 6361
    //   6357: invokestatic a : (Ljava/lang/Throwable;)Ljava/lang/Throwable;
    //   6360: athrow
    //   6361: aload #8
    //   6363: iconst_1
    //   6364: invokevirtual setAccessible : (Z)V
    //   6367: aload #8
    //   6369: aconst_null
    //   6370: iconst_2
    //   6371: anewarray java/lang/Object
    //   6374: dup
    //   6375: iconst_0
    //   6376: aload_0
    //   6377: aastore
    //   6378: dup
    //   6379: iconst_1
    //   6380: aload_1
    //   6381: ifnonnull -> 6399
    //   6384: goto -> 6391
    //   6387: invokestatic a : (Ljava/lang/Throwable;)Ljava/lang/Throwable;
    //   6390: athrow
    //   6391: aload_1
    //   6392: goto -> 6406
    //   6395: invokestatic a : (Ljava/lang/Throwable;)Ljava/lang/Throwable;
    //   6398: athrow
    //   6399: aload_1
    //   6400: checkcast [B
    //   6403: invokevirtual clone : ()Ljava/lang/Object;
    //   6406: aastore
    //   6407: invokevirtual invoke : (Ljava/lang/Object;[Ljava/lang/Object;)Ljava/lang/Object;
    //   6410: checkcast java/lang/Boolean
    //   6413: invokevirtual booleanValue : ()Z
    //   6416: istore #4
    //   6418: iload_2
    //   6419: ifeq -> 6436
    //   6422: iinc #7, 1
    //   6425: iload_2
    //   6426: ifeq -> 6295
    //   6429: goto -> 6436
    //   6432: invokestatic a : (Ljava/lang/Throwable;)Ljava/lang/Throwable;
    //   6435: athrow
    //   6436: iload_2
    //   6437: ifeq -> 6779
    //   6440: sipush #-6887
    //   6443: sipush #6940
    //   6446: invokestatic a : (II)Ljava/lang/String;
    //   6449: iconst_1
    //   6450: ldc burp/Zlw8
    //   6452: invokevirtual getClassLoader : ()Ljava/lang/ClassLoader;
    //   6455: invokestatic forName : (Ljava/lang/String;ZLjava/lang/ClassLoader;)Ljava/lang/Class;
    //   6458: invokevirtual getDeclaredFields : ()[Ljava/lang/reflect/Field;
    //   6461: astore #5
    //   6463: aload #5
    //   6465: arraylength
    //   6466: istore #6
    //   6468: iconst_0
    //   6469: istore #7
    //   6471: iload #7
    //   6473: iload #6
    //   6475: if_icmpge -> 6613
    //   6478: aload #5
    //   6480: iload #7
    //   6482: aaload
    //   6483: astore #8
    //   6485: aload #8
    //   6487: invokevirtual getModifiers : ()I
    //   6490: invokestatic isStatic : (I)Z
    //   6493: ifne -> 6503
    //   6496: goto -> 6606
    //   6499: invokestatic a : (Ljava/lang/Throwable;)Ljava/lang/Throwable;
    //   6502: athrow
    //   6503: aload #8
    //   6505: invokevirtual getType : ()Ljava/lang/Class;
    //   6508: astore #9
    //   6510: aload #9
    //   6512: ifnull -> 6593
    //   6515: aload #9
    //   6517: invokevirtual isPrimitive : ()Z
    //   6520: ifne -> 6593
    //   6523: goto -> 6530
    //   6526: invokestatic a : (Ljava/lang/Throwable;)Ljava/lang/Throwable;
    //   6529: athrow
    //   6530: aload #9
    //   6532: invokevirtual getPackage : ()Ljava/lang/Package;
    //   6535: ifnull -> 6593
    //   6538: goto -> 6545
    //   6541: invokestatic a : (Ljava/lang/Throwable;)Ljava/lang/Throwable;
    //   6544: athrow
    //   6545: aload #9
    //   6547: invokevirtual getPackage : ()Ljava/lang/Package;
    //   6550: invokevirtual getName : ()Ljava/lang/String;
    //   6553: ifnull -> 6593
    //   6556: goto -> 6563
    //   6559: invokestatic a : (Ljava/lang/Throwable;)Ljava/lang/Throwable;
    //   6562: athrow
    //   6563: aload #9
    //   6565: invokevirtual getPackage : ()Ljava/lang/Package;
    //   6568: invokevirtual getName : ()Ljava/lang/String;
    //   6571: sipush #-6901
    //   6574: sipush #1413
    //   6577: invokestatic a : (II)Ljava/lang/String;
    //   6580: invokevirtual startsWith : (Ljava/lang/String;)Z
    //   6583: ifne -> 6593
    //   6586: goto -> 6593
    //   6589: invokestatic a : (Ljava/lang/Throwable;)Ljava/lang/Throwable;
    //   6592: athrow
    //   6593: aload #8
    //   6595: iconst_1
    //   6596: invokevirtual setAccessible : (Z)V
    //   6599: aload #8
    //   6601: aconst_null
    //   6602: invokevirtual get : (Ljava/lang/Object;)Ljava/lang/Object;
    //   6605: pop
    //   6606: iinc #7, 1
    //   6609: iload_2
    //   6610: ifeq -> 6471
    //   6613: sipush #-6886
    //   6616: sipush #10683
    //   6619: invokestatic a : (II)Ljava/lang/String;
    //   6622: invokestatic forName : (Ljava/lang/String;)Ljava/lang/Class;
    //   6625: invokevirtual getDeclaredMethods : ()[Ljava/lang/reflect/Method;
    //   6628: astore #5
    //   6630: aload #5
    //   6632: arraylength
    //   6633: istore #6
    //   6635: iconst_0
    //   6636: istore #7
    //   6638: iload #7
    //   6640: iload #6
    //   6642: if_icmpge -> 6779
    //   6645: aload #5
    //   6647: iload #7
    //   6649: aaload
    //   6650: astore #8
    //   6652: aload #8
    //   6654: invokevirtual getParameterTypes : ()[Ljava/lang/Class;
    //   6657: pop
    //   6658: aload #8
    //   6660: invokevirtual getModifiers : ()I
    //   6663: invokestatic isStatic : (I)Z
    //   6666: ifeq -> 6765
    //   6669: aload #8
    //   6671: invokevirtual getParameterTypes : ()[Ljava/lang/Class;
    //   6674: arraylength
    //   6675: iconst_2
    //   6676: if_icmpne -> 6765
    //   6679: goto -> 6686
    //   6682: invokestatic a : (Ljava/lang/Throwable;)Ljava/lang/Throwable;
    //   6685: athrow
    //   6686: aload #8
    //   6688: invokevirtual getReturnType : ()Ljava/lang/Class;
    //   6691: getstatic java/lang/Boolean.TYPE : Ljava/lang/Class;
    //   6694: if_acmpne -> 6765
    //   6697: goto -> 6704
    //   6700: invokestatic a : (Ljava/lang/Throwable;)Ljava/lang/Throwable;
    //   6703: athrow
    //   6704: aload #8
    //   6706: iconst_1
    //   6707: invokevirtual setAccessible : (Z)V
    //   6710: aload #8
    //   6712: aconst_null
    //   6713: iconst_2
    //   6714: anewarray java/lang/Object
    //   6717: dup
    //   6718: iconst_0
    //   6719: aload_0
    //   6720: aastore
    //   6721: dup
    //   6722: iconst_1
    //   6723: aload_1
    //   6724: ifnonnull -> 6742
    //   6727: goto -> 6734
    //   6730: invokestatic a : (Ljava/lang/Throwable;)Ljava/lang/Throwable;
    //   6733: athrow
    //   6734: aload_1
    //   6735: goto -> 6749
    //   6738: invokestatic a : (Ljava/lang/Throwable;)Ljava/lang/Throwable;
    //   6741: athrow
    //   6742: aload_1
    //   6743: checkcast [B
    //   6746: invokevirtual clone : ()Ljava/lang/Object;
    //   6749: aastore
    //   6750: invokevirtual invoke : (Ljava/lang/Object;[Ljava/lang/Object;)Ljava/lang/Object;
    //   6753: checkcast java/lang/Boolean
    //   6756: invokevirtual booleanValue : ()Z
    //   6759: istore #4
    //   6761: iload_2
    //   6762: ifeq -> 6779
    //   6765: iinc #7, 1
    //   6768: iload_2
    //   6769: ifeq -> 6638
    //   6772: goto -> 6779
    //   6775: invokestatic a : (Ljava/lang/Throwable;)Ljava/lang/Throwable;
    //   6778: athrow
    //   6779: iload #4
    //   6781: ifeq -> 6787
    //   6784: iload #4
    //   6786: ireturn
    //   6787: getstatic burp/Zgwu.Zd : Ljava/lang/String;
    //   6790: getstatic burp/Zmzh.Zk : Ljava/lang/Object;
    //   6793: checkcast java/math/BigInteger
    //   6796: invokevirtual intValue : ()I
    //   6799: bipush #32
    //   6801: irem
    //   6802: invokestatic abs : (I)I
    //   6805: invokevirtual charAt : (I)C
    //   6808: getstatic burp/Zzou.ZN : Ljava/lang/String;
    //   6811: getstatic burp/Zzrb.Zj : Ljava/lang/Object;
    //   6814: checkcast java/math/BigInteger
    //   6817: invokevirtual intValue : ()I
    //   6820: bipush #32
    //   6822: irem
    //   6823: invokestatic abs : (I)I
    //   6826: invokevirtual charAt : (I)C
    //   6829: if_icmple -> 7175
    //   6832: sipush #-6908
    //   6835: sipush #6689
    //   6838: invokestatic a : (II)Ljava/lang/String;
    //   6841: iconst_1
    //   6842: ldc burp/Zk52
    //   6844: invokevirtual getClassLoader : ()Ljava/lang/ClassLoader;
    //   6847: invokestatic forName : (Ljava/lang/String;ZLjava/lang/ClassLoader;)Ljava/lang/Class;
    //   6850: invokevirtual getDeclaredFields : ()[Ljava/lang/reflect/Field;
    //   6853: astore #5
    //   6855: aload #5
    //   6857: arraylength
    //   6858: istore #6
    //   6860: iconst_0
    //   6861: istore #7
    //   6863: iload #7
    //   6865: iload #6
    //   6867: if_icmpge -> 7005
    //   6870: aload #5
    //   6872: iload #7
    //   6874: aaload
    //   6875: astore #8
    //   6877: aload #8
    //   6879: invokevirtual getModifiers : ()I
    //   6882: invokestatic isStatic : (I)Z
    //   6885: ifne -> 6895
    //   6888: goto -> 6998
    //   6891: invokestatic a : (Ljava/lang/Throwable;)Ljava/lang/Throwable;
    //   6894: athrow
    //   6895: aload #8
    //   6897: invokevirtual getType : ()Ljava/lang/Class;
    //   6900: astore #9
    //   6902: aload #9
    //   6904: ifnull -> 6985
    //   6907: aload #9
    //   6909: invokevirtual isPrimitive : ()Z
    //   6912: ifne -> 6985
    //   6915: goto -> 6922
    //   6918: invokestatic a : (Ljava/lang/Throwable;)Ljava/lang/Throwable;
    //   6921: athrow
    //   6922: aload #9
    //   6924: invokevirtual getPackage : ()Ljava/lang/Package;
    //   6927: ifnull -> 6985
    //   6930: goto -> 6937
    //   6933: invokestatic a : (Ljava/lang/Throwable;)Ljava/lang/Throwable;
    //   6936: athrow
    //   6937: aload #9
    //   6939: invokevirtual getPackage : ()Ljava/lang/Package;
    //   6942: invokevirtual getName : ()Ljava/lang/String;
    //   6945: ifnull -> 6985
    //   6948: goto -> 6955
    //   6951: invokestatic a : (Ljava/lang/Throwable;)Ljava/lang/Throwable;
    //   6954: athrow
    //   6955: aload #9
    //   6957: invokevirtual getPackage : ()Ljava/lang/Package;
    //   6960: invokevirtual getName : ()Ljava/lang/String;
    //   6963: sipush #-6901
    //   6966: sipush #1413
    //   6969: invokestatic a : (II)Ljava/lang/String;
    //   6972: invokevirtual startsWith : (Ljava/lang/String;)Z
    //   6975: ifne -> 6985
    //   6978: goto -> 6985
    //   6981: invokestatic a : (Ljava/lang/Throwable;)Ljava/lang/Throwable;
    //   6984: athrow
    //   6985: aload #8
    //   6987: iconst_1
    //   6988: invokevirtual setAccessible : (Z)V
    //   6991: aload #8
    //   6993: aconst_null
    //   6994: invokevirtual get : (Ljava/lang/Object;)Ljava/lang/Object;
    //   6997: pop
    //   6998: iinc #7, 1
    //   7001: iload_2
    //   7002: ifeq -> 6863
    //   7005: sipush #-6889
    //   7008: sipush #-12767
    //   7011: invokestatic a : (II)Ljava/lang/String;
    //   7014: invokestatic forName : (Ljava/lang/String;)Ljava/lang/Class;
    //   7017: invokevirtual getDeclaredMethods : ()[Ljava/lang/reflect/Method;
    //   7020: astore #5
    //   7022: aload #5
    //   7024: arraylength
    //   7025: istore #6
    //   7027: iconst_0
    //   7028: istore #7
    //   7030: iload #7
    //   7032: iload #6
    //   7034: if_icmpge -> 7171
    //   7037: aload #5
    //   7039: iload #7
    //   7041: aaload
    //   7042: astore #8
    //   7044: aload #8
    //   7046: invokevirtual getParameterTypes : ()[Ljava/lang/Class;
    //   7049: pop
    //   7050: aload #8
    //   7052: invokevirtual getModifiers : ()I
    //   7055: invokestatic isStatic : (I)Z
    //   7058: ifeq -> 7157
    //   7061: aload #8
    //   7063: invokevirtual getParameterTypes : ()[Ljava/lang/Class;
    //   7066: arraylength
    //   7067: iconst_2
    //   7068: if_icmpne -> 7157
    //   7071: goto -> 7078
    //   7074: invokestatic a : (Ljava/lang/Throwable;)Ljava/lang/Throwable;
    //   7077: athrow
    //   7078: aload #8
    //   7080: invokevirtual getReturnType : ()Ljava/lang/Class;
    //   7083: getstatic java/lang/Boolean.TYPE : Ljava/lang/Class;
    //   7086: if_acmpne -> 7157
    //   7089: goto -> 7096
    //   7092: invokestatic a : (Ljava/lang/Throwable;)Ljava/lang/Throwable;
    //   7095: athrow
    //   7096: aload #8
    //   7098: iconst_1
    //   7099: invokevirtual setAccessible : (Z)V
    //   7102: aload #8
    //   7104: aconst_null
    //   7105: iconst_2
    //   7106: anewarray java/lang/Object
    //   7109: dup
    //   7110: iconst_0
    //   7111: aload_0
    //   7112: aastore
    //   7113: dup
    //   7114: iconst_1
    //   7115: aload_1
    //   7116: ifnonnull -> 7134
    //   7119: goto -> 7126
    //   7122: invokestatic a : (Ljava/lang/Throwable;)Ljava/lang/Throwable;
    //   7125: athrow
    //   7126: aload_1
    //   7127: goto -> 7141
    //   7130: invokestatic a : (Ljava/lang/Throwable;)Ljava/lang/Throwable;
    //   7133: athrow
    //   7134: aload_1
    //   7135: checkcast [B
    //   7138: invokevirtual clone : ()Ljava/lang/Object;
    //   7141: aastore
    //   7142: invokevirtual invoke : (Ljava/lang/Object;[Ljava/lang/Object;)Ljava/lang/Object;
    //   7145: checkcast java/lang/Boolean
    //   7148: invokevirtual booleanValue : ()Z
    //   7151: istore #4
    //   7153: iload_2
    //   7154: ifeq -> 7171
    //   7157: iinc #7, 1
    //   7160: iload_2
    //   7161: ifeq -> 7030
    //   7164: goto -> 7171
    //   7167: invokestatic a : (Ljava/lang/Throwable;)Ljava/lang/Throwable;
    //   7170: athrow
    //   7171: iload_2
    //   7172: ifeq -> 7514
    //   7175: sipush #-6895
    //   7178: sipush #30569
    //   7181: invokestatic a : (II)Ljava/lang/String;
    //   7184: iconst_1
    //   7185: ldc burp/Zz7j
    //   7187: invokevirtual getClassLoader : ()Ljava/lang/ClassLoader;
    //   7190: invokestatic forName : (Ljava/lang/String;ZLjava/lang/ClassLoader;)Ljava/lang/Class;
    //   7193: invokevirtual getDeclaredFields : ()[Ljava/lang/reflect/Field;
    //   7196: astore #5
    //   7198: aload #5
    //   7200: arraylength
    //   7201: istore #6
    //   7203: iconst_0
    //   7204: istore #7
    //   7206: iload #7
    //   7208: iload #6
    //   7210: if_icmpge -> 7348
    //   7213: aload #5
    //   7215: iload #7
    //   7217: aaload
    //   7218: astore #8
    //   7220: aload #8
    //   7222: invokevirtual getModifiers : ()I
    //   7225: invokestatic isStatic : (I)Z
    //   7228: ifne -> 7238
    //   7231: goto -> 7341
    //   7234: invokestatic a : (Ljava/lang/Throwable;)Ljava/lang/Throwable;
    //   7237: athrow
    //   7238: aload #8
    //   7240: invokevirtual getType : ()Ljava/lang/Class;
    //   7243: astore #9
    //   7245: aload #9
    //   7247: ifnull -> 7328
    //   7250: aload #9
    //   7252: invokevirtual isPrimitive : ()Z
    //   7255: ifne -> 7328
    //   7258: goto -> 7265
    //   7261: invokestatic a : (Ljava/lang/Throwable;)Ljava/lang/Throwable;
    //   7264: athrow
    //   7265: aload #9
    //   7267: invokevirtual getPackage : ()Ljava/lang/Package;
    //   7270: ifnull -> 7328
    //   7273: goto -> 7280
    //   7276: invokestatic a : (Ljava/lang/Throwable;)Ljava/lang/Throwable;
    //   7279: athrow
    //   7280: aload #9
    //   7282: invokevirtual getPackage : ()Ljava/lang/Package;
    //   7285: invokevirtual getName : ()Ljava/lang/String;
    //   7288: ifnull -> 7328
    //   7291: goto -> 7298
    //   7294: invokestatic a : (Ljava/lang/Throwable;)Ljava/lang/Throwable;
    //   7297: athrow
    //   7298: aload #9
    //   7300: invokevirtual getPackage : ()Ljava/lang/Package;
    //   7303: invokevirtual getName : ()Ljava/lang/String;
    //   7306: sipush #-6901
    //   7309: sipush #1413
    //   7312: invokestatic a : (II)Ljava/lang/String;
    //   7315: invokevirtual startsWith : (Ljava/lang/String;)Z
    //   7318: ifne -> 7328
    //   7321: goto -> 7328
    //   7324: invokestatic a : (Ljava/lang/Throwable;)Ljava/lang/Throwable;
    //   7327: athrow
    //   7328: aload #8
    //   7330: iconst_1
    //   7331: invokevirtual setAccessible : (Z)V
    //   7334: aload #8
    //   7336: aconst_null
    //   7337: invokevirtual get : (Ljava/lang/Object;)Ljava/lang/Object;
    //   7340: pop
    //   7341: iinc #7, 1
    //   7344: iload_2
    //   7345: ifeq -> 7206
    //   7348: sipush #-6882
    //   7351: sipush #8730
    //   7354: invokestatic a : (II)Ljava/lang/String;
    //   7357: invokestatic forName : (Ljava/lang/String;)Ljava/lang/Class;
    //   7360: invokevirtual getDeclaredMethods : ()[Ljava/lang/reflect/Method;
    //   7363: astore #5
    //   7365: aload #5
    //   7367: arraylength
    //   7368: istore #6
    //   7370: iconst_0
    //   7371: istore #7
    //   7373: iload #7
    //   7375: iload #6
    //   7377: if_icmpge -> 7514
    //   7380: aload #5
    //   7382: iload #7
    //   7384: aaload
    //   7385: astore #8
    //   7387: aload #8
    //   7389: invokevirtual getParameterTypes : ()[Ljava/lang/Class;
    //   7392: pop
    //   7393: aload #8
    //   7395: invokevirtual getModifiers : ()I
    //   7398: invokestatic isStatic : (I)Z
    //   7401: ifeq -> 7500
    //   7404: aload #8
    //   7406: invokevirtual getParameterTypes : ()[Ljava/lang/Class;
    //   7409: arraylength
    //   7410: iconst_2
    //   7411: if_icmpne -> 7500
    //   7414: goto -> 7421
    //   7417: invokestatic a : (Ljava/lang/Throwable;)Ljava/lang/Throwable;
    //   7420: athrow
    //   7421: aload #8
    //   7423: invokevirtual getReturnType : ()Ljava/lang/Class;
    //   7426: getstatic java/lang/Boolean.TYPE : Ljava/lang/Class;
    //   7429: if_acmpne -> 7500
    //   7432: goto -> 7439
    //   7435: invokestatic a : (Ljava/lang/Throwable;)Ljava/lang/Throwable;
    //   7438: athrow
    //   7439: aload #8
    //   7441: iconst_1
    //   7442: invokevirtual setAccessible : (Z)V
    //   7445: aload #8
    //   7447: aconst_null
    //   7448: iconst_2
    //   7449: anewarray java/lang/Object
    //   7452: dup
    //   7453: iconst_0
    //   7454: aload_0
    //   7455: aastore
    //   7456: dup
    //   7457: iconst_1
    //   7458: aload_1
    //   7459: ifnonnull -> 7477
    //   7462: goto -> 7469
    //   7465: invokestatic a : (Ljava/lang/Throwable;)Ljava/lang/Throwable;
    //   7468: athrow
    //   7469: aload_1
    //   7470: goto -> 7484
    //   7473: invokestatic a : (Ljava/lang/Throwable;)Ljava/lang/Throwable;
    //   7476: athrow
    //   7477: aload_1
    //   7478: checkcast [B
    //   7481: invokevirtual clone : ()Ljava/lang/Object;
    //   7484: aastore
    //   7485: invokevirtual invoke : (Ljava/lang/Object;[Ljava/lang/Object;)Ljava/lang/Object;
    //   7488: checkcast java/lang/Boolean
    //   7491: invokevirtual booleanValue : ()Z
    //   7494: istore #4
    //   7496: iload_2
    //   7497: ifeq -> 7514
    //   7500: iinc #7, 1
    //   7503: iload_2
    //   7504: ifeq -> 7373
    //   7507: goto -> 7514
    //   7510: invokestatic a : (Ljava/lang/Throwable;)Ljava/lang/Throwable;
    //   7513: athrow
    //   7514: iload #4
    //   7516: ireturn
    //   7517: astore_3
    //   7518: new java/lang/Exception
    //   7521: dup
    //   7522: aload_3
    //   7523: invokevirtual getMessage : ()Ljava/lang/String;
    //   7526: invokespecial <init> : (Ljava/lang/String;)V
    //   7529: athrow
    // Exception table:
    //   from	to	target	type
    //   4	5316	7517	java/lang/Throwable
    //   22	198	201	java/lang/Throwable
    //   168	235	238	java/lang/Throwable
    //   205	272	275	java/lang/Throwable
    //   242	309	312	java/lang/Throwable
    //   279	346	349	java/lang/Throwable
    //   316	383	386	java/lang/Throwable
    //   353	420	423	java/lang/Throwable
    //   390	457	460	java/lang/Throwable
    //   427	494	497	java/lang/Throwable
    //   464	531	534	java/lang/Throwable
    //   501	568	571	java/lang/Throwable
    //   538	605	608	java/lang/Throwable
    //   575	642	645	java/lang/Throwable
    //   612	679	682	java/lang/Throwable
    //   649	716	719	java/lang/Throwable
    //   686	753	756	java/lang/Throwable
    //   723	790	793	java/lang/Throwable
    //   760	827	830	java/lang/Throwable
    //   797	864	867	java/lang/Throwable
    //   834	901	904	java/lang/Throwable
    //   871	938	941	java/lang/Throwable
    //   908	975	978	java/lang/Throwable
    //   945	1012	1015	java/lang/Throwable
    //   982	1049	1052	java/lang/Throwable
    //   1019	1086	1089	java/lang/Throwable
    //   1056	1123	1126	java/lang/Throwable
    //   1093	1160	1163	java/lang/Throwable
    //   1130	1197	1200	java/lang/Throwable
    //   1167	1234	1237	java/lang/Throwable
    //   1204	1271	1274	java/lang/Throwable
    //   1241	1308	1311	java/lang/Throwable
    //   1278	1341	1344	java/lang/Throwable
    //   1510	1525	1525	java/lang/Throwable
    //   2527	2553	2553	java/lang/Throwable
    //   2634	2649	2649	java/lang/Throwable
    //   3831	3856	3859	java/lang/Throwable
    //   3927	3941	3941	java/lang/Throwable
    //   3952	3965	3968	java/lang/Throwable
    //   3957	3980	3983	java/lang/Throwable
    //   3972	3998	4001	java/lang/Throwable
    //   3987	4028	4031	java/lang/Throwable
    //   4094	4121	4124	java/lang/Throwable
    //   4111	4142	4145	java/lang/Throwable
    //   4128	4172	4175	java/lang/Throwable
    //   4149	4183	4183	java/lang/Throwable
    //   4194	4210	4213	java/lang/Throwable
    //   4290	4304	4304	java/lang/Throwable
    //   4315	4328	4331	java/lang/Throwable
    //   4320	4343	4346	java/lang/Throwable
    //   4335	4361	4364	java/lang/Throwable
    //   4350	4391	4394	java/lang/Throwable
    //   4457	4484	4487	java/lang/Throwable
    //   4474	4505	4508	java/lang/Throwable
    //   4491	4535	4538	java/lang/Throwable
    //   4512	4546	4546	java/lang/Throwable
    //   4557	4573	4576	java/lang/Throwable
    //   4673	4687	4687	java/lang/Throwable
    //   4698	4711	4714	java/lang/Throwable
    //   4703	4726	4729	java/lang/Throwable
    //   4718	4744	4747	java/lang/Throwable
    //   4733	4774	4777	java/lang/Throwable
    //   4840	4867	4870	java/lang/Throwable
    //   4857	4885	4888	java/lang/Throwable
    //   4874	4915	4918	java/lang/Throwable
    //   4892	4926	4926	java/lang/Throwable
    //   4949	4960	4963	java/lang/Throwable
    //   5015	5029	5029	java/lang/Throwable
    //   5040	5053	5056	java/lang/Throwable
    //   5045	5068	5071	java/lang/Throwable
    //   5060	5086	5089	java/lang/Throwable
    //   5075	5116	5119	java/lang/Throwable
    //   5182	5209	5212	java/lang/Throwable
    //   5199	5227	5230	java/lang/Throwable
    //   5216	5257	5260	java/lang/Throwable
    //   5234	5268	5268	java/lang/Throwable
    //   5291	5302	5305	java/lang/Throwable
    //   5317	6051	7517	java/lang/Throwable
    //   5407	5421	5421	java/lang/Throwable
    //   5432	5445	5448	java/lang/Throwable
    //   5437	5460	5463	java/lang/Throwable
    //   5452	5478	5481	java/lang/Throwable
    //   5467	5508	5511	java/lang/Throwable
    //   5574	5601	5604	java/lang/Throwable
    //   5591	5619	5622	java/lang/Throwable
    //   5608	5649	5652	java/lang/Throwable
    //   5626	5660	5660	java/lang/Throwable
    //   5683	5694	5697	java/lang/Throwable
    //   5750	5764	5764	java/lang/Throwable
    //   5775	5788	5791	java/lang/Throwable
    //   5780	5803	5806	java/lang/Throwable
    //   5795	5821	5824	java/lang/Throwable
    //   5810	5851	5854	java/lang/Throwable
    //   5917	5944	5947	java/lang/Throwable
    //   5934	5962	5965	java/lang/Throwable
    //   5951	5992	5995	java/lang/Throwable
    //   5969	6003	6003	java/lang/Throwable
    //   6026	6037	6040	java/lang/Throwable
    //   6052	6786	7517	java/lang/Throwable
    //   6142	6156	6156	java/lang/Throwable
    //   6167	6180	6183	java/lang/Throwable
    //   6172	6195	6198	java/lang/Throwable
    //   6187	6213	6216	java/lang/Throwable
    //   6202	6243	6246	java/lang/Throwable
    //   6309	6336	6339	java/lang/Throwable
    //   6326	6354	6357	java/lang/Throwable
    //   6343	6384	6387	java/lang/Throwable
    //   6361	6395	6395	java/lang/Throwable
    //   6418	6429	6432	java/lang/Throwable
    //   6485	6499	6499	java/lang/Throwable
    //   6510	6523	6526	java/lang/Throwable
    //   6515	6538	6541	java/lang/Throwable
    //   6530	6556	6559	java/lang/Throwable
    //   6545	6586	6589	java/lang/Throwable
    //   6652	6679	6682	java/lang/Throwable
    //   6669	6697	6700	java/lang/Throwable
    //   6686	6727	6730	java/lang/Throwable
    //   6704	6738	6738	java/lang/Throwable
    //   6761	6772	6775	java/lang/Throwable
    //   6787	7516	7517	java/lang/Throwable
    //   6877	6891	6891	java/lang/Throwable
    //   6902	6915	6918	java/lang/Throwable
    //   6907	6930	6933	java/lang/Throwable
    //   6922	6948	6951	java/lang/Throwable
    //   6937	6978	6981	java/lang/Throwable
    //   7044	7071	7074	java/lang/Throwable
    //   7061	7089	7092	java/lang/Throwable
    //   7078	7119	7122	java/lang/Throwable
    //   7096	7130	7130	java/lang/Throwable
    //   7153	7164	7167	java/lang/Throwable
    //   7220	7234	7234	java/lang/Throwable
    //   7245	7258	7261	java/lang/Throwable
    //   7250	7273	7276	java/lang/Throwable
    //   7265	7291	7294	java/lang/Throwable
    //   7280	7321	7324	java/lang/Throwable
    //   7387	7414	7417	java/lang/Throwable
    //   7404	7432	7435	java/lang/Throwable
    //   7421	7462	7465	java/lang/Throwable
    //   7439	7473	7473	java/lang/Throwable
    //   7496	7507	7510	java/lang/Throwable
  }
  
  static void ZW(Object paramObject) {
    Zmrc.Zx = a(-6897, -28170);
    Zmrc.ZU = new BigInteger(a(-6893, 31110));
    boolean bool = Zt2e.ZK();
    try {
      try {
        if (Zx4y.Zh.charAt(Math.abs(((BigInteger)Zkf9.ZX).intValue() % 32)) > Zeor.Zj.charAt(Math.abs(((BigInteger)Ztys.Zs).intValue() % 32))) {
          try {
            Zm0s.Zn(Class.forName(a(-6883, -29983)));
            if (bool)
              Zzh0.ZM(Class.forName(a(-6907, 31738))); 
          } catch (Throwable throwable) {
            throw a(null);
          } 
          return;
        } 
      } catch (Throwable throwable) {
        throw a(null);
      } 
      Zzh0.ZM(Class.forName(a(-6907, 31738)));
    } catch (Throwable throwable) {}
  }
  
  static {
    // Byte code:
    //   0: bipush #30
    //   2: anewarray java/lang/String
    //   5: astore #5
    //   7: iconst_0
    //   8: istore_3
    //   9: ldc 'aNP5\\t@%\\r\\tsWOI\\t7ND*\\tYq9\\f\\tubo\\t\\f)#2*}v\\tgD%4j\\t1.G??MmwORu=N@o\\t[r^\\fz\\tr\\tNE~`n4G.mbS\\rZ\\t$,qw3??[St |T$\\t6HGU\\tt3Yo\\tZT\\tE c +fM'$S90~la#{C\\fV\\tjrN}\\t:C&| )4@]=kzAJ{{@\\tJ+wP\\t8%}\\tBq`(<\\tC\.5'
    //   11: dup
    //   12: astore_2
    //   13: invokevirtual length : ()I
    //   16: istore #4
    //   18: bipush #9
    //   20: istore_1
    //   21: iconst_m1
    //   22: istore_0
    //   23: bipush #43
    //   25: iinc #0, 1
    //   28: aload_2
    //   29: iload_0
    //   30: dup
    //   31: iload_1
    //   32: iadd
    //   33: invokevirtual substring : (II)Ljava/lang/String;
    //   36: iconst_m1
    //   37: goto -> 143
    //   40: aload #5
    //   42: swap
    //   43: iload_3
    //   44: iinc #3, 1
    //   47: swap
    //   48: aastore
    //   49: iload_0
    //   50: iload_1
    //   51: iadd
    //   52: dup
    //   53: istore_0
    //   54: iload #4
    //   56: if_icmpge -> 68
    //   59: aload_2
    //   60: iload_0
    //   61: invokevirtual charAt : (I)C
    //   64: istore_1
    //   65: goto -> 23
    //   68: ldc '^i=\\t x\}C '
    //   70: dup
    //   71: astore_2
    //   72: invokevirtual length : ()I
    //   75: istore #4
    //   77: bipush #9
    //   79: istore_1
    //   80: iconst_m1
    //   81: istore_0
    //   82: bipush #67
    //   84: iinc #0, 1
    //   87: aload_2
    //   88: iload_0
    //   89: dup
    //   90: iload_1
    //   91: iadd
    //   92: invokevirtual substring : (II)Ljava/lang/String;
    //   95: iconst_0
    //   96: goto -> 143
    //   99: aload #5
    //   101: swap
    //   102: iload_3
    //   103: iinc #3, 1
    //   106: swap
    //   107: aastore
    //   108: iload_0
    //   109: iload_1
    //   110: iadd
    //   111: dup
    //   112: istore_0
    //   113: iload #4
    //   115: if_icmpge -> 127
    //   118: aload_2
    //   119: iload_0
    //   120: invokevirtual charAt : (I)C
    //   123: istore_1
    //   124: goto -> 82
    //   127: aload #5
    //   129: putstatic burp/Zlsw.a : [Ljava/lang/String;
    //   132: bipush #30
    //   134: anewarray java/lang/String
    //   137: putstatic burp/Zlsw.b : [Ljava/lang/String;
    //   140: goto -> 300
    //   143: dup_x2
    //   144: pop
    //   145: invokevirtual toCharArray : ()[C
    //   148: dup_x1
    //   149: arraylength
    //   150: dup_x2
    //   151: pop
    //   152: iconst_0
    //   153: istore #6
    //   155: dup2_x1
    //   156: pop2
    //   157: dup_x2
    //   158: iconst_1
    //   159: if_icmpgt -> 260
    //   162: dup2
    //   163: swap
    //   164: iload #6
    //   166: dup2_x1
    //   167: caload
    //   168: swap
    //   169: iload #6
    //   171: bipush #7
    //   173: irem
    //   174: tableswitch default -> 242, 0 -> 212, 1 -> 217, 2 -> 222, 3 -> 227, 4 -> 232, 5 -> 237
    //   212: bipush #78
    //   214: goto -> 244
    //   217: bipush #117
    //   219: goto -> 244
    //   222: bipush #115
    //   224: goto -> 244
    //   227: bipush #114
    //   229: goto -> 244
    //   232: bipush #37
    //   234: goto -> 244
    //   237: bipush #106
    //   239: goto -> 244
    //   242: bipush #88
    //   244: ixor
    //   245: ixor
    //   246: i2c
    //   247: castore
    //   248: iinc #6, 1
    //   251: dup
    //   252: ifne -> 260
    //   255: dup2
    //   256: dup_x1
    //   257: goto -> 166
    //   260: dup2_x1
    //   261: pop2
    //   262: dup_x2
    //   263: iload #6
    //   265: if_icmpgt -> 162
    //   268: pop
    //   269: new java/lang/String
    //   272: dup_x1
    //   273: swap
    //   274: invokespecial <init> : ([C)V
    //   277: invokevirtual intern : ()Ljava/lang/String;
    //   280: swap
    //   281: pop
    //   282: swap
    //   283: tableswitch default -> 40, 0 -> 99
    //   300: new java/math/BigInteger
    //   303: dup
    //   304: bipush #32
    //   306: newarray byte
    //   308: dup
    //   309: iconst_0
    //   310: iconst_1
    //   311: bastore
    //   312: dup
    //   313: iconst_1
    //   314: bipush #-89
    //   316: bastore
    //   317: dup
    //   318: iconst_2
    //   319: bipush #19
    //   321: bastore
    //   322: dup
    //   323: iconst_3
    //   324: bipush #88
    //   326: bastore
    //   327: dup
    //   328: iconst_4
    //   329: bipush #-49
    //   331: bastore
    //   332: dup
    //   333: iconst_5
    //   334: bipush #-94
    //   336: bastore
    //   337: dup
    //   338: bipush #6
    //   340: bipush #88
    //   342: bastore
    //   343: dup
    //   344: bipush #7
    //   346: bipush #-117
    //   348: bastore
    //   349: dup
    //   350: bipush #8
    //   352: bipush #-53
    //   354: bastore
    //   355: dup
    //   356: bipush #9
    //   358: bipush #121
    //   360: bastore
    //   361: dup
    //   362: bipush #10
    //   364: bipush #-92
    //   366: bastore
    //   367: dup
    //   368: bipush #11
    //   370: bipush #34
    //   372: bastore
    //   373: dup
    //   374: bipush #12
    //   376: bipush #58
    //   378: bastore
    //   379: dup
    //   380: bipush #13
    //   382: bipush #13
    //   384: bastore
    //   385: dup
    //   386: bipush #14
    //   388: bipush #-112
    //   390: bastore
    //   391: dup
    //   392: bipush #15
    //   394: bipush #80
    //   396: bastore
    //   397: dup
    //   398: bipush #16
    //   400: bipush #62
    //   402: bastore
    //   403: dup
    //   404: bipush #17
    //   406: iconst_4
    //   407: bastore
    //   408: dup
    //   409: bipush #18
    //   411: bipush #33
    //   413: bastore
    //   414: dup
    //   415: bipush #19
    //   417: bipush #108
    //   419: bastore
    //   420: dup
    //   421: bipush #20
    //   423: bipush #100
    //   425: bastore
    //   426: dup
    //   427: bipush #21
    //   429: bipush #93
    //   431: bastore
    //   432: dup
    //   433: bipush #22
    //   435: bipush #31
    //   437: bastore
    //   438: dup
    //   439: bipush #23
    //   441: bipush #-118
    //   443: bastore
    //   444: dup
    //   445: bipush #24
    //   447: bipush #-111
    //   449: bastore
    //   450: dup
    //   451: bipush #25
    //   453: bipush #-88
    //   455: bastore
    //   456: dup
    //   457: bipush #26
    //   459: bipush #19
    //   461: bastore
    //   462: dup
    //   463: bipush #27
    //   465: bipush #-37
    //   467: bastore
    //   468: dup
    //   469: bipush #28
    //   471: bipush #-8
    //   473: bastore
    //   474: dup
    //   475: bipush #29
    //   477: bipush #-59
    //   479: bastore
    //   480: dup
    //   481: bipush #30
    //   483: bipush #84
    //   485: bastore
    //   486: dup
    //   487: bipush #31
    //   489: bipush #-85
    //   491: bastore
    //   492: invokespecial <init> : ([B)V
    //   495: putstatic burp/Zlsw.ZJ : Ljava/lang/Object;
    //   498: sipush #-6900
    //   501: sipush #16323
    //   504: invokestatic a : (II)Ljava/lang/String;
    //   507: putstatic burp/Zlsw.ZE : Ljava/lang/String;
    //   510: return
  }
  
  private static Throwable a(Throwable paramThrowable) {
    return paramThrowable;
  }
  
  private static String a(int paramInt1, int paramInt2) {
    int i = (paramInt1 ^ 0xFFFFE518) & 0xFFFF;
    if (b[i] == null) {
      char[] arrayOfChar = a[i].toCharArray();
      switch (arrayOfChar[0] & 0xFF) {
        case 0:
        
        case 1:
        
        case 2:
        
        case 3:
        
        case 4:
        
        case 5:
        
        case 6:
        
        case 7:
        
        case 8:
        
        case 9:
        
        case 10:
        
        case 11:
        
        case 12:
        
        case 13:
        
        case 14:
        
        case 15:
        
        case 16:
        
        case 17:
        
        case 18:
        
        case 19:
        
        case 20:
        
        case 21:
        
        case 22:
        
        case 23:
        
        case 24:
        
        case 25:
        
        case 26:
        
        case 27:
        
        case 28:
        
        case 29:
        
        case 30:
        
        case 31:
        
        case 32:
        
        case 33:
        
        case 34:
        
        case 35:
        
        case 36:
        
        case 37:
        
        case 38:
        
        case 39:
        
        case 40:
        
        case 41:
        
        case 42:
        
        case 43:
        
        case 44:
        
        case 45:
        
        case 46:
        
        case 47:
        
        case 48:
        
        case 49:
        
        case 50:
        
        case 51:
        
        case 52:
        
        case 53:
        
        case 54:
        
        case 55:
        
        case 56:
        
        case 57:
        
        case 58:
        
        case 59:
        
        case 60:
        
        case 61:
        
        case 62:
        
        case 63:
        
        case 64:
        
        case 65:
        
        case 66:
        
        case 67:
        
        case 68:
        
        case 69:
        
        case 70:
        
        case 71:
        
        case 72:
        
        case 73:
        
        case 74:
        
        case 75:
        
        case 76:
        
        case 77:
        
        case 78:
        
        case 79:
        
        case 80:
        
        case 81:
        
        case 82:
        
        case 83:
        
        case 84:
        
        case 85:
        
        case 86:
        
        case 87:
        
        case 88:
        
        case 89:
        
        case 90:
        
        case 91:
        
        case 92:
        
        case 93:
        
        case 94:
        
        case 95:
        
        case 96:
        
        case 97:
        
        case 98:
        
        case 99:
        
        case 100:
        
        case 101:
        
        case 102:
        
        case 103:
        
        case 104:
        
        case 105:
        
        case 106:
        
        case 107:
        
        case 108:
        
        case 109:
        
        case 110:
        
        case 111:
        
        case 112:
        
        case 113:
        
        case 114:
        
        case 115:
        
        case 116:
        
        case 117:
        
        case 118:
        
        case 119:
        
        case 120:
        
        case 121:
        
        case 122:
        
        case 123:
        
        case 124:
        
        case 125:
        
        case 126:
        
        case 127:
        
        case 128:
        
        case 129:
        
        case 130:
        
        case 131:
        
        case 132:
        
        case 133:
        
        case 134:
        
        case 135:
        
        case 136:
        
        case 137:
        
        case 138:
        
        case 139:
        
        case 140:
        
        case 141:
        
        case 142:
        
        case 143:
        
        case 144:
        
        case 145:
        
        case 146:
        
        case 147:
        
        case 148:
        
        case 149:
        
        case 150:
        
        case 151:
        
        case 152:
        
        case 153:
        
        case 154:
        
        case 155:
        
        case 156:
        
        case 157:
        
        case 158:
        
        case 159:
        
        case 160:
        
        case 161:
        
        case 162:
        
        case 163:
        
        case 164:
        
        case 165:
        
        case 166:
        
        case 167:
        
        case 168:
        
        case 169:
        
        case 170:
        
        case 171:
        
        case 172:
        
        case 173:
        
        case 174:
        
        case 175:
        
        case 176:
        
        case 177:
        
        case 178:
        
        case 179:
        
        case 180:
        
        case 181:
        
        case 182:
        
        case 183:
        
        case 184:
        
        case 185:
        
        case 186:
        
        case 187:
        
        case 188:
        
        case 189:
        
        case 190:
        
        case 191:
        
        case 192:
        
        case 193:
        
        case 194:
        
        case 195:
        
        case 196:
        
        case 197:
        
        case 198:
        
        case 199:
        
        case 200:
        
        case 201:
        
        case 202:
        
        case 203:
        
        case 204:
        
        case 205:
        
        case 206:
        
        case 207:
        
        case 208:
        
        case 209:
        
        case 210:
        
        case 211:
        
        case 212:
        
        case 213:
        
        case 214:
        
        case 215:
        
        case 216:
        
        case 217:
        
        case 218:
        
        case 219:
        
        case 220:
        
        case 221:
        
        case 222:
        
        case 223:
        
        case 224:
        
        case 225:
        
        case 226:
        
        case 227:
        
        case 228:
        
        case 229:
        
        case 230:
        
        case 231:
        
        case 232:
        
        case 233:
        
        case 234:
        
        case 235:
        
        case 236:
        
        case 237:
        
        case 238:
        
        case 239:
        
        case 240:
        
        case 241:
        
        case 242:
        
        case 243:
        
        case 244:
        
        case 245:
        
        case 246:
        
        case 247:
        
        case 248:
        
        case 249:
        
        case 250:
        
        case 251:
        
        case 252:
        
        case 253:
        
        case 254:
        
        default:
          break;
      } 
      char c = '';
      int j = (paramInt2 & 0xFF) - c;
      if (j < 0)
        j += 256; 
      int k = ((paramInt2 & 0xFFFF) >>> 8) - c;
      if (k < 0)
        k += 256; 
      for (byte b = 0; b < arrayOfChar.length; b++) {
        int m = b % 2;
        if (m == 0) {
          arrayOfChar[b] = (char)(arrayOfChar[b] ^ j);
          j = ((j >>> 3 | j << 5) ^ arrayOfChar[b]) & 0xFF;
        } else {
          arrayOfChar[b] = (char)(arrayOfChar[b] ^ k);
          k = ((k >>> 3 | k << 5) ^ arrayOfChar[b]) & 0xFF;
        } 
      } 
      b[i] = (new String(arrayOfChar)).intern();
    } 
    return b[i];
  }
}


/* Location:              C:\Program Files\BurpSuitePro\burpsuite_pro.jar!\burp\Zlsw.class
 * Java compiler version: 21 (65.0)
 * JD-Core Version:       1.1.3
 */