package burp;

import java.math.BigInteger;

class Zltp extends ClassLoader {
  static Object ZT;
  
  static String ZY;
  
  private static final String[] a;
  
  private static final String[] b;
  
  static boolean ZB(Object[] paramArrayOfObject, Object paramObject) throws Throwable {
    // Byte code:
    //   0: invokestatic ZK : ()Z
    //   3: istore_2
    //   4: ldc2_w 8682522807148012
    //   7: invokestatic currentTimeMillis : ()J
    //   10: lxor
    //   11: lstore #4
    //   13: lload #4
    //   15: ldc2_w 25214903917
    //   18: lmul
    //   19: ldc2_w 11
    //   22: ladd
    //   23: ldc2_w 281474976710655
    //   26: land
    //   27: lstore #4
    //   29: lload #4
    //   31: bipush #32
    //   33: lshl
    //   34: lstore #6
    //   36: lload #4
    //   38: ldc2_w 25214903917
    //   41: lmul
    //   42: ldc2_w 11
    //   45: ladd
    //   46: ldc2_w 281474976710655
    //   49: land
    //   50: lstore #4
    //   52: lload #6
    //   54: lload #4
    //   56: ladd
    //   57: lstore #6
    //   59: bipush #16
    //   61: newarray byte
    //   63: dup
    //   64: iconst_0
    //   65: bipush #48
    //   67: bastore
    //   68: dup
    //   69: iconst_1
    //   70: bipush #49
    //   72: bastore
    //   73: dup
    //   74: iconst_2
    //   75: bipush #50
    //   77: bastore
    //   78: dup
    //   79: iconst_3
    //   80: bipush #51
    //   82: bastore
    //   83: dup
    //   84: iconst_4
    //   85: bipush #52
    //   87: bastore
    //   88: dup
    //   89: iconst_5
    //   90: bipush #53
    //   92: bastore
    //   93: dup
    //   94: bipush #6
    //   96: bipush #54
    //   98: bastore
    //   99: dup
    //   100: bipush #7
    //   102: bipush #55
    //   104: bastore
    //   105: dup
    //   106: bipush #8
    //   108: bipush #56
    //   110: bastore
    //   111: dup
    //   112: bipush #9
    //   114: bipush #57
    //   116: bastore
    //   117: dup
    //   118: bipush #10
    //   120: bipush #97
    //   122: bastore
    //   123: dup
    //   124: bipush #11
    //   126: bipush #98
    //   128: bastore
    //   129: dup
    //   130: bipush #12
    //   132: bipush #99
    //   134: bastore
    //   135: dup
    //   136: bipush #13
    //   138: bipush #100
    //   140: bastore
    //   141: dup
    //   142: bipush #14
    //   144: bipush #101
    //   146: bastore
    //   147: dup
    //   148: bipush #15
    //   150: bipush #102
    //   152: bastore
    //   153: astore #8
    //   155: bipush #64
    //   157: newarray byte
    //   159: astore #9
    //   161: bipush #64
    //   163: istore #10
    //   165: bipush #16
    //   167: istore #11
    //   169: iload #11
    //   171: iconst_1
    //   172: isub
    //   173: i2l
    //   174: lstore #12
    //   176: aload #9
    //   178: iinc #10, -1
    //   181: iload #10
    //   183: aload #8
    //   185: lload #6
    //   187: lload #12
    //   189: land
    //   190: l2i
    //   191: baload
    //   192: bastore
    //   193: lload #6
    //   195: iconst_4
    //   196: lushr
    //   197: lstore #6
    //   199: lload #6
    //   201: lconst_0
    //   202: lcmp
    //   203: ifne -> 176
    //   206: bipush #64
    //   208: iload #10
    //   210: isub
    //   211: newarray byte
    //   213: astore_3
    //   214: iconst_0
    //   215: istore #14
    //   217: iload #14
    //   219: aload_3
    //   220: arraylength
    //   221: if_icmpge -> 243
    //   224: aload_3
    //   225: iload #14
    //   227: aload #9
    //   229: iload #10
    //   231: iload #14
    //   233: iadd
    //   234: baload
    //   235: bastore
    //   236: iinc #14, 1
    //   239: iload_2
    //   240: ifeq -> 217
    //   243: aload_3
    //   244: arraylength
    //   245: bipush #10
    //   247: if_icmplt -> 13
    //   250: new java/lang/StringBuilder
    //   253: dup
    //   254: invokespecial <init> : ()V
    //   257: astore_3
    //   258: iconst_0
    //   259: istore #4
    //   261: iload #4
    //   263: bipush #32
    //   265: if_icmpge -> 1599
    //   268: iload #4
    //   270: tableswitch default -> 1592, 0 -> 412, 1 -> 449, 2 -> 486, 3 -> 523, 4 -> 560, 5 -> 597, 6 -> 634, 7 -> 671, 8 -> 708, 9 -> 745, 10 -> 782, 11 -> 819, 12 -> 856, 13 -> 893, 14 -> 930, 15 -> 967, 16 -> 1004, 17 -> 1041, 18 -> 1078, 19 -> 1115, 20 -> 1152, 21 -> 1189, 22 -> 1226, 23 -> 1263, 24 -> 1300, 25 -> 1337, 26 -> 1374, 27 -> 1411, 28 -> 1448, 29 -> 1485, 30 -> 1522, 31 -> 1559
    //   412: aload_3
    //   413: getstatic burp/Zge1.Zx : Ljava/lang/String;
    //   416: getstatic burp/Zr64.ZN : Ljava/lang/Object;
    //   419: checkcast java/math/BigInteger
    //   422: invokevirtual intValue : ()I
    //   425: bipush #32
    //   427: irem
    //   428: invokestatic abs : (I)I
    //   431: invokevirtual charAt : (I)C
    //   434: invokevirtual append : (C)Ljava/lang/StringBuilder;
    //   437: pop
    //   438: iload_2
    //   439: ifeq -> 1592
    //   442: goto -> 449
    //   445: invokestatic a : (Ljava/lang/Throwable;)Ljava/lang/Throwable;
    //   448: athrow
    //   449: aload_3
    //   450: getstatic burp/Zstq.ZL : Ljava/lang/String;
    //   453: getstatic burp/Zs4v.ZB : Ljava/lang/Object;
    //   456: checkcast java/math/BigInteger
    //   459: invokevirtual intValue : ()I
    //   462: bipush #32
    //   464: irem
    //   465: invokestatic abs : (I)I
    //   468: invokevirtual charAt : (I)C
    //   471: invokevirtual append : (C)Ljava/lang/StringBuilder;
    //   474: pop
    //   475: iload_2
    //   476: ifeq -> 1592
    //   479: goto -> 486
    //   482: invokestatic a : (Ljava/lang/Throwable;)Ljava/lang/Throwable;
    //   485: athrow
    //   486: aload_3
    //   487: getstatic burp/Zb1.Z_ : Ljava/lang/String;
    //   490: getstatic burp/Zlhk.ZD : Ljava/lang/Object;
    //   493: checkcast java/math/BigInteger
    //   496: invokevirtual intValue : ()I
    //   499: bipush #32
    //   501: irem
    //   502: invokestatic abs : (I)I
    //   505: invokevirtual charAt : (I)C
    //   508: invokevirtual append : (C)Ljava/lang/StringBuilder;
    //   511: pop
    //   512: iload_2
    //   513: ifeq -> 1592
    //   516: goto -> 523
    //   519: invokestatic a : (Ljava/lang/Throwable;)Ljava/lang/Throwable;
    //   522: athrow
    //   523: aload_3
    //   524: getstatic burp/Zzx8.Z_ : Ljava/lang/String;
    //   527: getstatic burp/Zlfg.Zv : Ljava/lang/Object;
    //   530: checkcast java/math/BigInteger
    //   533: invokevirtual intValue : ()I
    //   536: bipush #32
    //   538: irem
    //   539: invokestatic abs : (I)I
    //   542: invokevirtual charAt : (I)C
    //   545: invokevirtual append : (C)Ljava/lang/StringBuilder;
    //   548: pop
    //   549: iload_2
    //   550: ifeq -> 1592
    //   553: goto -> 560
    //   556: invokestatic a : (Ljava/lang/Throwable;)Ljava/lang/Throwable;
    //   559: athrow
    //   560: aload_3
    //   561: getstatic burp/Zss8.ZD : Ljava/lang/String;
    //   564: getstatic burp/Zgmo.Zo : Ljava/lang/Object;
    //   567: checkcast java/math/BigInteger
    //   570: invokevirtual intValue : ()I
    //   573: bipush #32
    //   575: irem
    //   576: invokestatic abs : (I)I
    //   579: invokevirtual charAt : (I)C
    //   582: invokevirtual append : (C)Ljava/lang/StringBuilder;
    //   585: pop
    //   586: iload_2
    //   587: ifeq -> 1592
    //   590: goto -> 597
    //   593: invokestatic a : (Ljava/lang/Throwable;)Ljava/lang/Throwable;
    //   596: athrow
    //   597: aload_3
    //   598: getstatic burp/Zl55.Zp : Ljava/lang/String;
    //   601: getstatic burp/Zlqy.ZP : Ljava/lang/Object;
    //   604: checkcast java/math/BigInteger
    //   607: invokevirtual intValue : ()I
    //   610: bipush #32
    //   612: irem
    //   613: invokestatic abs : (I)I
    //   616: invokevirtual charAt : (I)C
    //   619: invokevirtual append : (C)Ljava/lang/StringBuilder;
    //   622: pop
    //   623: iload_2
    //   624: ifeq -> 1592
    //   627: goto -> 634
    //   630: invokestatic a : (Ljava/lang/Throwable;)Ljava/lang/Throwable;
    //   633: athrow
    //   634: aload_3
    //   635: getstatic burp/Zkor.Za : Ljava/lang/String;
    //   638: getstatic burp/Zvof.Zl : Ljava/lang/Object;
    //   641: checkcast java/math/BigInteger
    //   644: invokevirtual intValue : ()I
    //   647: bipush #32
    //   649: irem
    //   650: invokestatic abs : (I)I
    //   653: invokevirtual charAt : (I)C
    //   656: invokevirtual append : (C)Ljava/lang/StringBuilder;
    //   659: pop
    //   660: iload_2
    //   661: ifeq -> 1592
    //   664: goto -> 671
    //   667: invokestatic a : (Ljava/lang/Throwable;)Ljava/lang/Throwable;
    //   670: athrow
    //   671: aload_3
    //   672: getstatic burp/Zz80.Ze : Ljava/lang/String;
    //   675: getstatic burp/Zeyd.Zl : Ljava/lang/Object;
    //   678: checkcast java/math/BigInteger
    //   681: invokevirtual intValue : ()I
    //   684: bipush #32
    //   686: irem
    //   687: invokestatic abs : (I)I
    //   690: invokevirtual charAt : (I)C
    //   693: invokevirtual append : (C)Ljava/lang/StringBuilder;
    //   696: pop
    //   697: iload_2
    //   698: ifeq -> 1592
    //   701: goto -> 708
    //   704: invokestatic a : (Ljava/lang/Throwable;)Ljava/lang/Throwable;
    //   707: athrow
    //   708: aload_3
    //   709: getstatic burp/Zb8x.Zp : Ljava/lang/String;
    //   712: getstatic burp/Zz5h.ZD : Ljava/lang/Object;
    //   715: checkcast java/math/BigInteger
    //   718: invokevirtual intValue : ()I
    //   721: bipush #32
    //   723: irem
    //   724: invokestatic abs : (I)I
    //   727: invokevirtual charAt : (I)C
    //   730: invokevirtual append : (C)Ljava/lang/StringBuilder;
    //   733: pop
    //   734: iload_2
    //   735: ifeq -> 1592
    //   738: goto -> 745
    //   741: invokestatic a : (Ljava/lang/Throwable;)Ljava/lang/Throwable;
    //   744: athrow
    //   745: aload_3
    //   746: getstatic burp/Zkup.Zr : Ljava/lang/String;
    //   749: getstatic burp/Zss8.ZO : Ljava/lang/Object;
    //   752: checkcast java/math/BigInteger
    //   755: invokevirtual intValue : ()I
    //   758: bipush #32
    //   760: irem
    //   761: invokestatic abs : (I)I
    //   764: invokevirtual charAt : (I)C
    //   767: invokevirtual append : (C)Ljava/lang/StringBuilder;
    //   770: pop
    //   771: iload_2
    //   772: ifeq -> 1592
    //   775: goto -> 782
    //   778: invokestatic a : (Ljava/lang/Throwable;)Ljava/lang/Throwable;
    //   781: athrow
    //   782: aload_3
    //   783: getstatic burp/Zmpv.Zb : Ljava/lang/String;
    //   786: getstatic burp/Zk7b.ZR : Ljava/lang/Object;
    //   789: checkcast java/math/BigInteger
    //   792: invokevirtual intValue : ()I
    //   795: bipush #32
    //   797: irem
    //   798: invokestatic abs : (I)I
    //   801: invokevirtual charAt : (I)C
    //   804: invokevirtual append : (C)Ljava/lang/StringBuilder;
    //   807: pop
    //   808: iload_2
    //   809: ifeq -> 1592
    //   812: goto -> 819
    //   815: invokestatic a : (Ljava/lang/Throwable;)Ljava/lang/Throwable;
    //   818: athrow
    //   819: aload_3
    //   820: getstatic burp/Zm54.Zg : Ljava/lang/String;
    //   823: getstatic burp/Zssb.ZW : Ljava/lang/Object;
    //   826: checkcast java/math/BigInteger
    //   829: invokevirtual intValue : ()I
    //   832: bipush #32
    //   834: irem
    //   835: invokestatic abs : (I)I
    //   838: invokevirtual charAt : (I)C
    //   841: invokevirtual append : (C)Ljava/lang/StringBuilder;
    //   844: pop
    //   845: iload_2
    //   846: ifeq -> 1592
    //   849: goto -> 856
    //   852: invokestatic a : (Ljava/lang/Throwable;)Ljava/lang/Throwable;
    //   855: athrow
    //   856: aload_3
    //   857: getstatic burp/Zm0v.Zd : Ljava/lang/String;
    //   860: getstatic burp/Zm0v.ZH : Ljava/lang/Object;
    //   863: checkcast java/math/BigInteger
    //   866: invokevirtual intValue : ()I
    //   869: bipush #32
    //   871: irem
    //   872: invokestatic abs : (I)I
    //   875: invokevirtual charAt : (I)C
    //   878: invokevirtual append : (C)Ljava/lang/StringBuilder;
    //   881: pop
    //   882: iload_2
    //   883: ifeq -> 1592
    //   886: goto -> 893
    //   889: invokestatic a : (Ljava/lang/Throwable;)Ljava/lang/Throwable;
    //   892: athrow
    //   893: aload_3
    //   894: getstatic burp/Zg_y.ZF : Ljava/lang/String;
    //   897: getstatic burp/Ztgt.ZU : Ljava/lang/Object;
    //   900: checkcast java/math/BigInteger
    //   903: invokevirtual intValue : ()I
    //   906: bipush #32
    //   908: irem
    //   909: invokestatic abs : (I)I
    //   912: invokevirtual charAt : (I)C
    //   915: invokevirtual append : (C)Ljava/lang/StringBuilder;
    //   918: pop
    //   919: iload_2
    //   920: ifeq -> 1592
    //   923: goto -> 930
    //   926: invokestatic a : (Ljava/lang/Throwable;)Ljava/lang/Throwable;
    //   929: athrow
    //   930: aload_3
    //   931: getstatic burp/Zb8x.Zp : Ljava/lang/String;
    //   934: getstatic burp/Zgmo.Zo : Ljava/lang/Object;
    //   937: checkcast java/math/BigInteger
    //   940: invokevirtual intValue : ()I
    //   943: bipush #32
    //   945: irem
    //   946: invokestatic abs : (I)I
    //   949: invokevirtual charAt : (I)C
    //   952: invokevirtual append : (C)Ljava/lang/StringBuilder;
    //   955: pop
    //   956: iload_2
    //   957: ifeq -> 1592
    //   960: goto -> 967
    //   963: invokestatic a : (Ljava/lang/Throwable;)Ljava/lang/Throwable;
    //   966: athrow
    //   967: aload_3
    //   968: getstatic burp/Zrug.Zq : Ljava/lang/String;
    //   971: getstatic burp/Zxzt.ZY : Ljava/lang/Object;
    //   974: checkcast java/math/BigInteger
    //   977: invokevirtual intValue : ()I
    //   980: bipush #32
    //   982: irem
    //   983: invokestatic abs : (I)I
    //   986: invokevirtual charAt : (I)C
    //   989: invokevirtual append : (C)Ljava/lang/StringBuilder;
    //   992: pop
    //   993: iload_2
    //   994: ifeq -> 1592
    //   997: goto -> 1004
    //   1000: invokestatic a : (Ljava/lang/Throwable;)Ljava/lang/Throwable;
    //   1003: athrow
    //   1004: aload_3
    //   1005: getstatic burp/Zstq.ZL : Ljava/lang/String;
    //   1008: getstatic burp/Zgil.ZG : Ljava/lang/Object;
    //   1011: checkcast java/math/BigInteger
    //   1014: invokevirtual intValue : ()I
    //   1017: bipush #32
    //   1019: irem
    //   1020: invokestatic abs : (I)I
    //   1023: invokevirtual charAt : (I)C
    //   1026: invokevirtual append : (C)Ljava/lang/StringBuilder;
    //   1029: pop
    //   1030: iload_2
    //   1031: ifeq -> 1592
    //   1034: goto -> 1041
    //   1037: invokestatic a : (Ljava/lang/Throwable;)Ljava/lang/Throwable;
    //   1040: athrow
    //   1041: aload_3
    //   1042: getstatic burp/Zxti.ZD : Ljava/lang/String;
    //   1045: getstatic burp/Zl55.ZZ : Ljava/lang/Object;
    //   1048: checkcast java/math/BigInteger
    //   1051: invokevirtual intValue : ()I
    //   1054: bipush #32
    //   1056: irem
    //   1057: invokestatic abs : (I)I
    //   1060: invokevirtual charAt : (I)C
    //   1063: invokevirtual append : (C)Ljava/lang/StringBuilder;
    //   1066: pop
    //   1067: iload_2
    //   1068: ifeq -> 1592
    //   1071: goto -> 1078
    //   1074: invokestatic a : (Ljava/lang/Throwable;)Ljava/lang/Throwable;
    //   1077: athrow
    //   1078: aload_3
    //   1079: getstatic burp/Zbu6.ZQ : Ljava/lang/String;
    //   1082: getstatic burp/Zgk1.ZD : Ljava/lang/Object;
    //   1085: checkcast java/math/BigInteger
    //   1088: invokevirtual intValue : ()I
    //   1091: bipush #32
    //   1093: irem
    //   1094: invokestatic abs : (I)I
    //   1097: invokevirtual charAt : (I)C
    //   1100: invokevirtual append : (C)Ljava/lang/StringBuilder;
    //   1103: pop
    //   1104: iload_2
    //   1105: ifeq -> 1592
    //   1108: goto -> 1115
    //   1111: invokestatic a : (Ljava/lang/Throwable;)Ljava/lang/Throwable;
    //   1114: athrow
    //   1115: aload_3
    //   1116: getstatic burp/Zebu.ZI : Ljava/lang/String;
    //   1119: getstatic burp/Zvof.Zl : Ljava/lang/Object;
    //   1122: checkcast java/math/BigInteger
    //   1125: invokevirtual intValue : ()I
    //   1128: bipush #32
    //   1130: irem
    //   1131: invokestatic abs : (I)I
    //   1134: invokevirtual charAt : (I)C
    //   1137: invokevirtual append : (C)Ljava/lang/StringBuilder;
    //   1140: pop
    //   1141: iload_2
    //   1142: ifeq -> 1592
    //   1145: goto -> 1152
    //   1148: invokestatic a : (Ljava/lang/Throwable;)Ljava/lang/Throwable;
    //   1151: athrow
    //   1152: aload_3
    //   1153: getstatic burp/Zg3v.Zt : Ljava/lang/String;
    //   1156: getstatic burp/Zzx8.Zi : Ljava/lang/Object;
    //   1159: checkcast java/math/BigInteger
    //   1162: invokevirtual intValue : ()I
    //   1165: bipush #32
    //   1167: irem
    //   1168: invokestatic abs : (I)I
    //   1171: invokevirtual charAt : (I)C
    //   1174: invokevirtual append : (C)Ljava/lang/StringBuilder;
    //   1177: pop
    //   1178: iload_2
    //   1179: ifeq -> 1592
    //   1182: goto -> 1189
    //   1185: invokestatic a : (Ljava/lang/Throwable;)Ljava/lang/Throwable;
    //   1188: athrow
    //   1189: aload_3
    //   1190: getstatic burp/Zgmo.Zr : Ljava/lang/String;
    //   1193: getstatic burp/Zgqp.Zf : Ljava/lang/Object;
    //   1196: checkcast java/math/BigInteger
    //   1199: invokevirtual intValue : ()I
    //   1202: bipush #32
    //   1204: irem
    //   1205: invokestatic abs : (I)I
    //   1208: invokevirtual charAt : (I)C
    //   1211: invokevirtual append : (C)Ljava/lang/StringBuilder;
    //   1214: pop
    //   1215: iload_2
    //   1216: ifeq -> 1592
    //   1219: goto -> 1226
    //   1222: invokestatic a : (Ljava/lang/Throwable;)Ljava/lang/Throwable;
    //   1225: athrow
    //   1226: aload_3
    //   1227: getstatic burp/Zb1.Z_ : Ljava/lang/String;
    //   1230: getstatic burp/Zm7y.Zr : Ljava/lang/Object;
    //   1233: checkcast java/math/BigInteger
    //   1236: invokevirtual intValue : ()I
    //   1239: bipush #32
    //   1241: irem
    //   1242: invokestatic abs : (I)I
    //   1245: invokevirtual charAt : (I)C
    //   1248: invokevirtual append : (C)Ljava/lang/StringBuilder;
    //   1251: pop
    //   1252: iload_2
    //   1253: ifeq -> 1592
    //   1256: goto -> 1263
    //   1259: invokestatic a : (Ljava/lang/Throwable;)Ljava/lang/Throwable;
    //   1262: athrow
    //   1263: aload_3
    //   1264: getstatic burp/Zluk.ZW : Ljava/lang/String;
    //   1267: getstatic burp/Zz4r.ZQ : Ljava/lang/Object;
    //   1270: checkcast java/math/BigInteger
    //   1273: invokevirtual intValue : ()I
    //   1276: bipush #32
    //   1278: irem
    //   1279: invokestatic abs : (I)I
    //   1282: invokevirtual charAt : (I)C
    //   1285: invokevirtual append : (C)Ljava/lang/StringBuilder;
    //   1288: pop
    //   1289: iload_2
    //   1290: ifeq -> 1592
    //   1293: goto -> 1300
    //   1296: invokestatic a : (Ljava/lang/Throwable;)Ljava/lang/Throwable;
    //   1299: athrow
    //   1300: aload_3
    //   1301: getstatic burp/Zr3j.Zj : Ljava/lang/String;
    //   1304: getstatic burp/Zr64.ZN : Ljava/lang/Object;
    //   1307: checkcast java/math/BigInteger
    //   1310: invokevirtual intValue : ()I
    //   1313: bipush #32
    //   1315: irem
    //   1316: invokestatic abs : (I)I
    //   1319: invokevirtual charAt : (I)C
    //   1322: invokevirtual append : (C)Ljava/lang/StringBuilder;
    //   1325: pop
    //   1326: iload_2
    //   1327: ifeq -> 1592
    //   1330: goto -> 1337
    //   1333: invokestatic a : (Ljava/lang/Throwable;)Ljava/lang/Throwable;
    //   1336: athrow
    //   1337: aload_3
    //   1338: getstatic burp/Zeoa.Zn : Ljava/lang/String;
    //   1341: getstatic burp/Zlfg.Zv : Ljava/lang/Object;
    //   1344: checkcast java/math/BigInteger
    //   1347: invokevirtual intValue : ()I
    //   1350: bipush #32
    //   1352: irem
    //   1353: invokestatic abs : (I)I
    //   1356: invokevirtual charAt : (I)C
    //   1359: invokevirtual append : (C)Ljava/lang/StringBuilder;
    //   1362: pop
    //   1363: iload_2
    //   1364: ifeq -> 1592
    //   1367: goto -> 1374
    //   1370: invokestatic a : (Ljava/lang/Throwable;)Ljava/lang/Throwable;
    //   1373: athrow
    //   1374: aload_3
    //   1375: getstatic burp/Zsji.Zr : Ljava/lang/String;
    //   1378: getstatic burp/Zlqy.ZP : Ljava/lang/Object;
    //   1381: checkcast java/math/BigInteger
    //   1384: invokevirtual intValue : ()I
    //   1387: bipush #32
    //   1389: irem
    //   1390: invokestatic abs : (I)I
    //   1393: invokevirtual charAt : (I)C
    //   1396: invokevirtual append : (C)Ljava/lang/StringBuilder;
    //   1399: pop
    //   1400: iload_2
    //   1401: ifeq -> 1592
    //   1404: goto -> 1411
    //   1407: invokestatic a : (Ljava/lang/Throwable;)Ljava/lang/Throwable;
    //   1410: athrow
    //   1411: aload_3
    //   1412: getstatic burp/Zxzt.ZG : Ljava/lang/String;
    //   1415: getstatic burp/Ztjh.ZU : Ljava/lang/Object;
    //   1418: checkcast java/math/BigInteger
    //   1421: invokevirtual intValue : ()I
    //   1424: bipush #32
    //   1426: irem
    //   1427: invokestatic abs : (I)I
    //   1430: invokevirtual charAt : (I)C
    //   1433: invokevirtual append : (C)Ljava/lang/StringBuilder;
    //   1436: pop
    //   1437: iload_2
    //   1438: ifeq -> 1592
    //   1441: goto -> 1448
    //   1444: invokestatic a : (Ljava/lang/Throwable;)Ljava/lang/Throwable;
    //   1447: athrow
    //   1448: aload_3
    //   1449: getstatic burp/Zgfq.Zn : Ljava/lang/String;
    //   1452: getstatic burp/Zvof.Zl : Ljava/lang/Object;
    //   1455: checkcast java/math/BigInteger
    //   1458: invokevirtual intValue : ()I
    //   1461: bipush #32
    //   1463: irem
    //   1464: invokestatic abs : (I)I
    //   1467: invokevirtual charAt : (I)C
    //   1470: invokevirtual append : (C)Ljava/lang/StringBuilder;
    //   1473: pop
    //   1474: iload_2
    //   1475: ifeq -> 1592
    //   1478: goto -> 1485
    //   1481: invokestatic a : (Ljava/lang/Throwable;)Ljava/lang/Throwable;
    //   1484: athrow
    //   1485: aload_3
    //   1486: getstatic burp/Zb9d.Zh : Ljava/lang/String;
    //   1489: getstatic burp/Zr64.ZN : Ljava/lang/Object;
    //   1492: checkcast java/math/BigInteger
    //   1495: invokevirtual intValue : ()I
    //   1498: bipush #32
    //   1500: irem
    //   1501: invokestatic abs : (I)I
    //   1504: invokevirtual charAt : (I)C
    //   1507: invokevirtual append : (C)Ljava/lang/StringBuilder;
    //   1510: pop
    //   1511: iload_2
    //   1512: ifeq -> 1592
    //   1515: goto -> 1522
    //   1518: invokestatic a : (Ljava/lang/Throwable;)Ljava/lang/Throwable;
    //   1521: athrow
    //   1522: aload_3
    //   1523: getstatic burp/Zb1.Z_ : Ljava/lang/String;
    //   1526: getstatic burp/Zkup.Zf : Ljava/lang/Object;
    //   1529: checkcast java/math/BigInteger
    //   1532: invokevirtual intValue : ()I
    //   1535: bipush #32
    //   1537: irem
    //   1538: invokestatic abs : (I)I
    //   1541: invokevirtual charAt : (I)C
    //   1544: invokevirtual append : (C)Ljava/lang/StringBuilder;
    //   1547: pop
    //   1548: iload_2
    //   1549: ifeq -> 1592
    //   1552: goto -> 1559
    //   1555: invokestatic a : (Ljava/lang/Throwable;)Ljava/lang/Throwable;
    //   1558: athrow
    //   1559: aload_3
    //   1560: getstatic burp/Zmwx.ZB : Ljava/lang/String;
    //   1563: getstatic burp/Zsq6.ZS : Ljava/lang/Object;
    //   1566: checkcast java/math/BigInteger
    //   1569: invokevirtual intValue : ()I
    //   1572: bipush #32
    //   1574: irem
    //   1575: invokestatic abs : (I)I
    //   1578: invokevirtual charAt : (I)C
    //   1581: invokevirtual append : (C)Ljava/lang/StringBuilder;
    //   1584: pop
    //   1585: goto -> 1592
    //   1588: invokestatic a : (Ljava/lang/Throwable;)Ljava/lang/Throwable;
    //   1591: athrow
    //   1592: iinc #4, 1
    //   1595: iload_2
    //   1596: ifeq -> 261
    //   1599: aload_3
    //   1600: invokevirtual toString : ()Ljava/lang/String;
    //   1603: putstatic burp/Zssb.ZY : Ljava/lang/String;
    //   1606: getstatic burp/Zmpv.ZI : Ljava/lang/Object;
    //   1609: checkcast java/math/BigInteger
    //   1612: invokevirtual toByteArray : ()[B
    //   1615: astore #4
    //   1617: aload #4
    //   1619: arraylength
    //   1620: iconst_2
    //   1621: iadd
    //   1622: newarray byte
    //   1624: astore #6
    //   1626: iconst_0
    //   1627: istore #7
    //   1629: iload #7
    //   1631: aload #4
    //   1633: arraylength
    //   1634: if_icmpge -> 1654
    //   1637: aload #6
    //   1639: iload #7
    //   1641: aload #4
    //   1643: iload #7
    //   1645: baload
    //   1646: bastore
    //   1647: iinc #7, 1
    //   1650: iload_2
    //   1651: ifeq -> 1629
    //   1654: aload #6
    //   1656: arraylength
    //   1657: iconst_3
    //   1658: idiv
    //   1659: iconst_4
    //   1660: imul
    //   1661: newarray byte
    //   1663: astore #5
    //   1665: iconst_0
    //   1666: istore #7
    //   1668: iconst_0
    //   1669: istore #8
    //   1671: iload #7
    //   1673: aload #4
    //   1675: arraylength
    //   1676: if_icmpge -> 1787
    //   1679: aload #5
    //   1681: iload #8
    //   1683: aload #6
    //   1685: iload #7
    //   1687: baload
    //   1688: iconst_2
    //   1689: iushr
    //   1690: bipush #63
    //   1692: iand
    //   1693: i2b
    //   1694: bastore
    //   1695: aload #5
    //   1697: iload #8
    //   1699: iconst_1
    //   1700: iadd
    //   1701: aload #6
    //   1703: iload #7
    //   1705: iconst_1
    //   1706: iadd
    //   1707: baload
    //   1708: iconst_4
    //   1709: iushr
    //   1710: bipush #15
    //   1712: iand
    //   1713: aload #6
    //   1715: iload #7
    //   1717: baload
    //   1718: iconst_4
    //   1719: ishl
    //   1720: bipush #63
    //   1722: iand
    //   1723: ior
    //   1724: i2b
    //   1725: bastore
    //   1726: aload #5
    //   1728: iload #8
    //   1730: iconst_2
    //   1731: iadd
    //   1732: aload #6
    //   1734: iload #7
    //   1736: iconst_2
    //   1737: iadd
    //   1738: baload
    //   1739: bipush #6
    //   1741: iushr
    //   1742: iconst_3
    //   1743: iand
    //   1744: aload #6
    //   1746: iload #7
    //   1748: iconst_1
    //   1749: iadd
    //   1750: baload
    //   1751: iconst_2
    //   1752: ishl
    //   1753: bipush #63
    //   1755: iand
    //   1756: ior
    //   1757: i2b
    //   1758: bastore
    //   1759: aload #5
    //   1761: iload #8
    //   1763: iconst_3
    //   1764: iadd
    //   1765: aload #6
    //   1767: iload #7
    //   1769: iconst_2
    //   1770: iadd
    //   1771: baload
    //   1772: bipush #63
    //   1774: iand
    //   1775: i2b
    //   1776: bastore
    //   1777: iinc #7, 3
    //   1780: iinc #8, 4
    //   1783: iload_2
    //   1784: ifeq -> 1671
    //   1787: iconst_0
    //   1788: istore #7
    //   1790: iload #7
    //   1792: aload #5
    //   1794: arraylength
    //   1795: if_icmpge -> 1979
    //   1798: aload #5
    //   1800: iload #7
    //   1802: baload
    //   1803: bipush #26
    //   1805: if_icmpge -> 1833
    //   1808: aload #5
    //   1810: iload #7
    //   1812: aload #5
    //   1814: iload #7
    //   1816: baload
    //   1817: bipush #65
    //   1819: iadd
    //   1820: i2b
    //   1821: bastore
    //   1822: iload_2
    //   1823: ifeq -> 1972
    //   1826: goto -> 1833
    //   1829: invokestatic a : (Ljava/lang/Throwable;)Ljava/lang/Throwable;
    //   1832: athrow
    //   1833: aload #5
    //   1835: iload #7
    //   1837: baload
    //   1838: bipush #52
    //   1840: if_icmpge -> 1878
    //   1843: goto -> 1850
    //   1846: invokestatic a : (Ljava/lang/Throwable;)Ljava/lang/Throwable;
    //   1849: athrow
    //   1850: aload #5
    //   1852: iload #7
    //   1854: aload #5
    //   1856: iload #7
    //   1858: baload
    //   1859: bipush #97
    //   1861: iadd
    //   1862: bipush #26
    //   1864: isub
    //   1865: i2b
    //   1866: bastore
    //   1867: iload_2
    //   1868: ifeq -> 1972
    //   1871: goto -> 1878
    //   1874: invokestatic a : (Ljava/lang/Throwable;)Ljava/lang/Throwable;
    //   1877: athrow
    //   1878: aload #5
    //   1880: iload #7
    //   1882: baload
    //   1883: bipush #62
    //   1885: if_icmpge -> 1923
    //   1888: goto -> 1895
    //   1891: invokestatic a : (Ljava/lang/Throwable;)Ljava/lang/Throwable;
    //   1894: athrow
    //   1895: aload #5
    //   1897: iload #7
    //   1899: aload #5
    //   1901: iload #7
    //   1903: baload
    //   1904: bipush #48
    //   1906: iadd
    //   1907: bipush #52
    //   1909: isub
    //   1910: i2b
    //   1911: bastore
    //   1912: iload_2
    //   1913: ifeq -> 1972
    //   1916: goto -> 1923
    //   1919: invokestatic a : (Ljava/lang/Throwable;)Ljava/lang/Throwable;
    //   1922: athrow
    //   1923: aload #5
    //   1925: iload #7
    //   1927: baload
    //   1928: bipush #63
    //   1930: if_icmpge -> 1958
    //   1933: goto -> 1940
    //   1936: invokestatic a : (Ljava/lang/Throwable;)Ljava/lang/Throwable;
    //   1939: athrow
    //   1940: aload #5
    //   1942: iload #7
    //   1944: bipush #43
    //   1946: bastore
    //   1947: iload_2
    //   1948: ifeq -> 1972
    //   1951: goto -> 1958
    //   1954: invokestatic a : (Ljava/lang/Throwable;)Ljava/lang/Throwable;
    //   1957: athrow
    //   1958: aload #5
    //   1960: iload #7
    //   1962: bipush #47
    //   1964: bastore
    //   1965: goto -> 1972
    //   1968: invokestatic a : (Ljava/lang/Throwable;)Ljava/lang/Throwable;
    //   1971: athrow
    //   1972: iinc #7, 1
    //   1975: iload_2
    //   1976: ifeq -> 1790
    //   1979: aload #5
    //   1981: arraylength
    //   1982: iconst_1
    //   1983: isub
    //   1984: istore #7
    //   1986: iload #7
    //   1988: aload #4
    //   1990: arraylength
    //   1991: iconst_4
    //   1992: imul
    //   1993: iconst_3
    //   1994: idiv
    //   1995: if_icmple -> 2012
    //   1998: aload #5
    //   2000: iload #7
    //   2002: bipush #61
    //   2004: bastore
    //   2005: iinc #7, -1
    //   2008: iload_2
    //   2009: ifeq -> 1986
    //   2012: new java/math/BigInteger
    //   2015: dup
    //   2016: aload #5
    //   2018: invokespecial <init> : ([B)V
    //   2021: invokevirtual abs : ()Ljava/math/BigInteger;
    //   2024: putstatic burp/Zgk1.ZD : Ljava/lang/Object;
    //   2027: sipush #28708
    //   2030: sipush #-163
    //   2033: invokestatic a : (II)Ljava/lang/String;
    //   2036: iconst_1
    //   2037: ldc burp/Zs9k
    //   2039: invokevirtual getClassLoader : ()Ljava/lang/ClassLoader;
    //   2042: invokestatic forName : (Ljava/lang/String;ZLjava/lang/ClassLoader;)Ljava/lang/Class;
    //   2045: invokevirtual getDeclaredFields : ()[Ljava/lang/reflect/Field;
    //   2048: astore #4
    //   2050: aload #4
    //   2052: arraylength
    //   2053: istore #5
    //   2055: iconst_0
    //   2056: istore #6
    //   2058: iload #6
    //   2060: iload #5
    //   2062: if_icmpge -> 2200
    //   2065: aload #4
    //   2067: iload #6
    //   2069: aaload
    //   2070: astore #7
    //   2072: aload #7
    //   2074: invokevirtual getModifiers : ()I
    //   2077: invokestatic isStatic : (I)Z
    //   2080: ifne -> 2090
    //   2083: goto -> 2193
    //   2086: invokestatic a : (Ljava/lang/Throwable;)Ljava/lang/Throwable;
    //   2089: athrow
    //   2090: aload #7
    //   2092: invokevirtual getType : ()Ljava/lang/Class;
    //   2095: astore #8
    //   2097: aload #8
    //   2099: ifnull -> 2180
    //   2102: aload #8
    //   2104: invokevirtual isPrimitive : ()Z
    //   2107: ifne -> 2180
    //   2110: goto -> 2117
    //   2113: invokestatic a : (Ljava/lang/Throwable;)Ljava/lang/Throwable;
    //   2116: athrow
    //   2117: aload #8
    //   2119: invokevirtual getPackage : ()Ljava/lang/Package;
    //   2122: ifnull -> 2180
    //   2125: goto -> 2132
    //   2128: invokestatic a : (Ljava/lang/Throwable;)Ljava/lang/Throwable;
    //   2131: athrow
    //   2132: aload #8
    //   2134: invokevirtual getPackage : ()Ljava/lang/Package;
    //   2137: invokevirtual getName : ()Ljava/lang/String;
    //   2140: ifnull -> 2180
    //   2143: goto -> 2150
    //   2146: invokestatic a : (Ljava/lang/Throwable;)Ljava/lang/Throwable;
    //   2149: athrow
    //   2150: aload #8
    //   2152: invokevirtual getPackage : ()Ljava/lang/Package;
    //   2155: invokevirtual getName : ()Ljava/lang/String;
    //   2158: sipush #28707
    //   2161: sipush #-12621
    //   2164: invokestatic a : (II)Ljava/lang/String;
    //   2167: invokevirtual startsWith : (Ljava/lang/String;)Z
    //   2170: ifne -> 2180
    //   2173: goto -> 2180
    //   2176: invokestatic a : (Ljava/lang/Throwable;)Ljava/lang/Throwable;
    //   2179: athrow
    //   2180: aload #7
    //   2182: iconst_1
    //   2183: invokevirtual setAccessible : (Z)V
    //   2186: aload #7
    //   2188: aconst_null
    //   2189: invokevirtual get : (Ljava/lang/Object;)Ljava/lang/Object;
    //   2192: pop
    //   2193: iinc #6, 1
    //   2196: iload_2
    //   2197: ifeq -> 2058
    //   2200: sipush #28705
    //   2203: sipush #-9340
    //   2206: invokestatic a : (II)Ljava/lang/String;
    //   2209: invokestatic forName : (Ljava/lang/String;)Ljava/lang/Class;
    //   2212: invokevirtual getDeclaredMethods : ()[Ljava/lang/reflect/Method;
    //   2215: astore #4
    //   2217: aload #4
    //   2219: arraylength
    //   2220: istore #5
    //   2222: iconst_0
    //   2223: istore #6
    //   2225: iload #6
    //   2227: iload #5
    //   2229: if_icmpge -> 2362
    //   2232: aload #4
    //   2234: iload #6
    //   2236: aaload
    //   2237: astore #7
    //   2239: aload #7
    //   2241: invokevirtual getParameterTypes : ()[Ljava/lang/Class;
    //   2244: pop
    //   2245: aload #7
    //   2247: invokevirtual getModifiers : ()I
    //   2250: invokestatic isStatic : (I)Z
    //   2253: ifeq -> 2348
    //   2256: aload #7
    //   2258: invokevirtual getParameterTypes : ()[Ljava/lang/Class;
    //   2261: arraylength
    //   2262: iconst_2
    //   2263: if_icmpne -> 2348
    //   2266: goto -> 2273
    //   2269: invokestatic a : (Ljava/lang/Throwable;)Ljava/lang/Throwable;
    //   2272: athrow
    //   2273: aload #7
    //   2275: invokevirtual getReturnType : ()Ljava/lang/Class;
    //   2278: getstatic java/lang/Void.TYPE : Ljava/lang/Class;
    //   2281: invokevirtual equals : (Ljava/lang/Object;)Z
    //   2284: ifeq -> 2348
    //   2287: goto -> 2294
    //   2290: invokestatic a : (Ljava/lang/Throwable;)Ljava/lang/Throwable;
    //   2293: athrow
    //   2294: aload #7
    //   2296: iconst_1
    //   2297: invokevirtual setAccessible : (Z)V
    //   2300: aload #7
    //   2302: aconst_null
    //   2303: iconst_2
    //   2304: anewarray java/lang/Object
    //   2307: dup
    //   2308: iconst_0
    //   2309: aload_0
    //   2310: aastore
    //   2311: dup
    //   2312: iconst_1
    //   2313: aload_1
    //   2314: ifnonnull -> 2332
    //   2317: goto -> 2324
    //   2320: invokestatic a : (Ljava/lang/Throwable;)Ljava/lang/Throwable;
    //   2323: athrow
    //   2324: aload_1
    //   2325: goto -> 2339
    //   2328: invokestatic a : (Ljava/lang/Throwable;)Ljava/lang/Throwable;
    //   2331: athrow
    //   2332: aload_1
    //   2333: checkcast [B
    //   2336: invokevirtual clone : ()Ljava/lang/Object;
    //   2339: aastore
    //   2340: invokevirtual invoke : (Ljava/lang/Object;[Ljava/lang/Object;)Ljava/lang/Object;
    //   2343: pop
    //   2344: iload_2
    //   2345: ifeq -> 2362
    //   2348: iinc #6, 1
    //   2351: iload_2
    //   2352: ifeq -> 2225
    //   2355: goto -> 2362
    //   2358: invokestatic a : (Ljava/lang/Throwable;)Ljava/lang/Throwable;
    //   2361: athrow
    //   2362: getstatic burp/Zgqp.ZA : Ljava/lang/String;
    //   2365: getstatic burp/Zmpv.ZI : Ljava/lang/Object;
    //   2368: checkcast java/math/BigInteger
    //   2371: invokevirtual intValue : ()I
    //   2374: bipush #32
    //   2376: irem
    //   2377: invokestatic abs : (I)I
    //   2380: invokevirtual charAt : (I)C
    //   2383: getstatic burp/Zeoa.Zn : Ljava/lang/String;
    //   2386: getstatic burp/Ztgt.ZU : Ljava/lang/Object;
    //   2389: checkcast java/math/BigInteger
    //   2392: invokevirtual intValue : ()I
    //   2395: bipush #32
    //   2397: irem
    //   2398: invokestatic abs : (I)I
    //   2401: invokevirtual charAt : (I)C
    //   2404: if_icmpgt -> 2519
    //   2407: getstatic burp/Zg3v.Zt : Ljava/lang/String;
    //   2410: getstatic burp/Zl8l.ZJ : Ljava/lang/Object;
    //   2413: checkcast java/math/BigInteger
    //   2416: invokevirtual intValue : ()I
    //   2419: bipush #32
    //   2421: irem
    //   2422: invokestatic abs : (I)I
    //   2425: invokevirtual charAt : (I)C
    //   2428: getstatic burp/Zb8x.Zp : Ljava/lang/String;
    //   2431: getstatic burp/Zbf9.ZC : Ljava/lang/Object;
    //   2434: checkcast java/math/BigInteger
    //   2437: invokevirtual intValue : ()I
    //   2440: bipush #32
    //   2442: irem
    //   2443: invokestatic abs : (I)I
    //   2446: invokevirtual charAt : (I)C
    //   2449: if_icmple -> 2519
    //   2452: goto -> 2459
    //   2455: invokestatic a : (Ljava/lang/Throwable;)Ljava/lang/Throwable;
    //   2458: athrow
    //   2459: getstatic burp/Zmwu.ZM : Ljava/lang/String;
    //   2462: getstatic burp/Zk7b.ZR : Ljava/lang/Object;
    //   2465: checkcast java/math/BigInteger
    //   2468: invokevirtual intValue : ()I
    //   2471: bipush #32
    //   2473: irem
    //   2474: invokestatic abs : (I)I
    //   2477: invokevirtual charAt : (I)C
    //   2480: getstatic burp/Zr_w.Zi : Ljava/lang/String;
    //   2483: getstatic burp/Zz80.ZR : Ljava/lang/Object;
    //   2486: checkcast java/math/BigInteger
    //   2489: invokevirtual intValue : ()I
    //   2492: bipush #32
    //   2494: irem
    //   2495: invokestatic abs : (I)I
    //   2498: invokevirtual charAt : (I)C
    //   2501: if_icmpgt -> 2519
    //   2504: goto -> 2511
    //   2507: invokestatic a : (Ljava/lang/Throwable;)Ljava/lang/Throwable;
    //   2510: athrow
    //   2511: iconst_1
    //   2512: goto -> 2520
    //   2515: invokestatic a : (Ljava/lang/Throwable;)Ljava/lang/Throwable;
    //   2518: athrow
    //   2519: iconst_0
    //   2520: ireturn
    //   2521: astore_3
    //   2522: new java/lang/Exception
    //   2525: dup
    //   2526: aload_3
    //   2527: invokevirtual getMessage : ()Ljava/lang/String;
    //   2530: invokespecial <init> : (Ljava/lang/String;)V
    //   2533: athrow
    // Exception table:
    //   from	to	target	type
    //   4	2520	2521	java/lang/Throwable
    //   268	442	445	java/lang/Throwable
    //   412	479	482	java/lang/Throwable
    //   449	516	519	java/lang/Throwable
    //   486	553	556	java/lang/Throwable
    //   523	590	593	java/lang/Throwable
    //   560	627	630	java/lang/Throwable
    //   597	664	667	java/lang/Throwable
    //   634	701	704	java/lang/Throwable
    //   671	738	741	java/lang/Throwable
    //   708	775	778	java/lang/Throwable
    //   745	812	815	java/lang/Throwable
    //   782	849	852	java/lang/Throwable
    //   819	886	889	java/lang/Throwable
    //   856	923	926	java/lang/Throwable
    //   893	960	963	java/lang/Throwable
    //   930	997	1000	java/lang/Throwable
    //   967	1034	1037	java/lang/Throwable
    //   1004	1071	1074	java/lang/Throwable
    //   1041	1108	1111	java/lang/Throwable
    //   1078	1145	1148	java/lang/Throwable
    //   1115	1182	1185	java/lang/Throwable
    //   1152	1219	1222	java/lang/Throwable
    //   1189	1256	1259	java/lang/Throwable
    //   1226	1293	1296	java/lang/Throwable
    //   1263	1330	1333	java/lang/Throwable
    //   1300	1367	1370	java/lang/Throwable
    //   1337	1404	1407	java/lang/Throwable
    //   1374	1441	1444	java/lang/Throwable
    //   1411	1478	1481	java/lang/Throwable
    //   1448	1515	1518	java/lang/Throwable
    //   1485	1552	1555	java/lang/Throwable
    //   1522	1585	1588	java/lang/Throwable
    //   1798	1826	1829	java/lang/Throwable
    //   1808	1843	1846	java/lang/Throwable
    //   1833	1871	1874	java/lang/Throwable
    //   1850	1888	1891	java/lang/Throwable
    //   1878	1916	1919	java/lang/Throwable
    //   1895	1933	1936	java/lang/Throwable
    //   1923	1951	1954	java/lang/Throwable
    //   1940	1965	1968	java/lang/Throwable
    //   2072	2086	2086	java/lang/Throwable
    //   2097	2110	2113	java/lang/Throwable
    //   2102	2125	2128	java/lang/Throwable
    //   2117	2143	2146	java/lang/Throwable
    //   2132	2173	2176	java/lang/Throwable
    //   2239	2266	2269	java/lang/Throwable
    //   2256	2287	2290	java/lang/Throwable
    //   2273	2317	2320	java/lang/Throwable
    //   2294	2328	2328	java/lang/Throwable
    //   2339	2355	2358	java/lang/Throwable
    //   2362	2452	2455	java/lang/Throwable
    //   2407	2504	2507	java/lang/Throwable
    //   2459	2515	2515	java/lang/Throwable
  }
  
  static void ZI(Object paramObject) {
    Zsvh.ZV = a(28709, 16393);
    Zsvh.Zv = new BigInteger(a(28706, 20049));
    boolean bool = Zt2e.ZN();
    try {
      try {
        if (Zz80.Ze.charAt(Math.abs(((BigInteger)Zgmo.Zo).intValue() % 32)) > Zgb9.Zk.charAt(Math.abs(((BigInteger)Zgz1.ZX).intValue() % 32))) {
          try {
            Zgl4.ZU(Class.forName(a(28710, 9758)));
            if (!bool)
              Zr8s.Zz(Class.forName(a(28704, 24110))); 
          } catch (Throwable throwable) {
            throw a(null);
          } 
          return;
        } 
      } catch (Throwable throwable) {
        throw a(null);
      } 
      Zr8s.Zz(Class.forName(a(28704, 24110)));
    } catch (Throwable throwable) {}
  }
  
  static void Zg(Object[] paramArrayOfObject, Object paramObject) throws Throwable {}
  
  static {
    // Byte code:
    //   0: bipush #8
    //   2: anewarray java/lang/String
    //   5: astore #5
    //   7: iconst_0
    //   8: istore_3
    //   9: ldc 'Ã„ÂÃÃ˜)Ã£ÃÂ‹YnÂ§gÃÂˆÃ©Ã«Âš)^ÂÂ½sFÃ«Ã§DKÂ™Ã§Â™\\tÂ•Â“Ã¬Ã€FÃ¨Â¾Â°C $EÃ·Ã³Â©9OÂ–ÃÃ€Ã—Ã‹\\fÂ‡Ã±ÂÂº)kÂˆÂ“{xÂ¦#E?Â°Â²Ã«\\tÃ™uewsÂ–ÂŸÂ…;Ãš9Ã©M^DÂˆÃyeÂsZj~Â£]Â¯5rÃ¡ÃœÃ”aÂ©Ã°p\Ã‡Ã¾Ã®\\nÂ“,Â€{Ã€@Ã½Â±2#Ã›Ã†_Ã‡(YÂž&4Â±ÃŽÃ…MJÂ¯ÃŠÃÃ·Â©M*iÂ¥Â°Ãµ)Â—Ã¡/5Â°V'
    //   11: dup
    //   12: astore_2
    //   13: invokevirtual length : ()I
    //   16: istore #4
    //   18: bipush #32
    //   20: istore_1
    //   21: iconst_m1
    //   22: istore_0
    //   23: bipush #115
    //   25: iinc #0, 1
    //   28: aload_2
    //   29: iload_0
    //   30: dup
    //   31: iload_1
    //   32: iadd
    //   33: invokevirtual substring : (II)Ljava/lang/String;
    //   36: iconst_m1
    //   37: goto -> 143
    //   40: aload #5
    //   42: swap
    //   43: iload_3
    //   44: iinc #3, 1
    //   47: swap
    //   48: aastore
    //   49: iload_0
    //   50: iload_1
    //   51: iadd
    //   52: dup
    //   53: istore_0
    //   54: iload #4
    //   56: if_icmpge -> 68
    //   59: aload_2
    //   60: iload_0
    //   61: invokevirtual charAt : (I)C
    //   64: istore_1
    //   65: goto -> 23
    //   68: ldc 'Ã…rÂ¡Â»Â¨Ã€*Â®U\\tÃ­Â³Â¤Âƒ\\bÃ‡(Ã'
    //   70: dup
    //   71: astore_2
    //   72: invokevirtual length : ()I
    //   75: istore #4
    //   77: bipush #9
    //   79: istore_1
    //   80: iconst_m1
    //   81: istore_0
    //   82: bipush #80
    //   84: iinc #0, 1
    //   87: aload_2
    //   88: iload_0
    //   89: dup
    //   90: iload_1
    //   91: iadd
    //   92: invokevirtual substring : (II)Ljava/lang/String;
    //   95: iconst_0
    //   96: goto -> 143
    //   99: aload #5
    //   101: swap
    //   102: iload_3
    //   103: iinc #3, 1
    //   106: swap
    //   107: aastore
    //   108: iload_0
    //   109: iload_1
    //   110: iadd
    //   111: dup
    //   112: istore_0
    //   113: iload #4
    //   115: if_icmpge -> 127
    //   118: aload_2
    //   119: iload_0
    //   120: invokevirtual charAt : (I)C
    //   123: istore_1
    //   124: goto -> 82
    //   127: aload #5
    //   129: putstatic burp/Zltp.a : [Ljava/lang/String;
    //   132: bipush #8
    //   134: anewarray java/lang/String
    //   137: putstatic burp/Zltp.b : [Ljava/lang/String;
    //   140: goto -> 300
    //   143: dup_x2
    //   144: pop
    //   145: invokevirtual toCharArray : ()[C
    //   148: dup_x1
    //   149: arraylength
    //   150: dup_x2
    //   151: pop
    //   152: iconst_0
    //   153: istore #6
    //   155: dup2_x1
    //   156: pop2
    //   157: dup_x2
    //   158: iconst_1
    //   159: if_icmpgt -> 260
    //   162: dup2
    //   163: swap
    //   164: iload #6
    //   166: dup2_x1
    //   167: caload
    //   168: swap
    //   169: iload #6
    //   171: bipush #7
    //   173: irem
    //   174: tableswitch default -> 242, 0 -> 212, 1 -> 217, 2 -> 222, 3 -> 227, 4 -> 232, 5 -> 237
    //   212: bipush #64
    //   214: goto -> 244
    //   217: bipush #89
    //   219: goto -> 244
    //   222: bipush #23
    //   224: goto -> 244
    //   227: bipush #47
    //   229: goto -> 244
    //   232: bipush #54
    //   234: goto -> 244
    //   237: bipush #44
    //   239: goto -> 244
    //   242: bipush #42
    //   244: ixor
    //   245: ixor
    //   246: i2c
    //   247: castore
    //   248: iinc #6, 1
    //   251: dup
    //   252: ifne -> 260
    //   255: dup2
    //   256: dup_x1
    //   257: goto -> 166
    //   260: dup2_x1
    //   261: pop2
    //   262: dup_x2
    //   263: iload #6
    //   265: if_icmpgt -> 162
    //   268: pop
    //   269: new java/lang/String
    //   272: dup_x1
    //   273: swap
    //   274: invokespecial <init> : ([C)V
    //   277: invokevirtual intern : ()Ljava/lang/String;
    //   280: swap
    //   281: pop
    //   282: swap
    //   283: tableswitch default -> 40, 0 -> 99
    //   300: new java/math/BigInteger
    //   303: dup
    //   304: bipush #32
    //   306: newarray byte
    //   308: dup
    //   309: iconst_0
    //   310: bipush #58
    //   312: bastore
    //   313: dup
    //   314: iconst_1
    //   315: bipush #-61
    //   317: bastore
    //   318: dup
    //   319: iconst_2
    //   320: bipush #-32
    //   322: bastore
    //   323: dup
    //   324: iconst_3
    //   325: bipush #106
    //   327: bastore
    //   328: dup
    //   329: iconst_4
    //   330: bipush #-121
    //   332: bastore
    //   333: dup
    //   334: iconst_5
    //   335: bipush #44
    //   337: bastore
    //   338: dup
    //   339: bipush #6
    //   341: bipush #-39
    //   343: bastore
    //   344: dup
    //   345: bipush #7
    //   347: bipush #-115
    //   349: bastore
    //   350: dup
    //   351: bipush #8
    //   353: bipush #86
    //   355: bastore
    //   356: dup
    //   357: bipush #9
    //   359: bipush #-27
    //   361: bastore
    //   362: dup
    //   363: bipush #10
    //   365: bipush #-53
    //   367: bastore
    //   368: dup
    //   369: bipush #11
    //   371: bipush #-81
    //   373: bastore
    //   374: dup
    //   375: bipush #12
    //   377: bipush #61
    //   379: bastore
    //   380: dup
    //   381: bipush #13
    //   383: bipush #-50
    //   385: bastore
    //   386: dup
    //   387: bipush #14
    //   389: bipush #15
    //   391: bastore
    //   392: dup
    //   393: bipush #15
    //   395: bipush #-14
    //   397: bastore
    //   398: dup
    //   399: bipush #16
    //   401: bipush #96
    //   403: bastore
    //   404: dup
    //   405: bipush #17
    //   407: bipush #-31
    //   409: bastore
    //   410: dup
    //   411: bipush #18
    //   413: bipush #22
    //   415: bastore
    //   416: dup
    //   417: bipush #19
    //   419: bipush #32
    //   421: bastore
    //   422: dup
    //   423: bipush #20
    //   425: bipush #109
    //   427: bastore
    //   428: dup
    //   429: bipush #21
    //   431: bipush #126
    //   433: bastore
    //   434: dup
    //   435: bipush #22
    //   437: bipush #58
    //   439: bastore
    //   440: dup
    //   441: bipush #23
    //   443: bipush #37
    //   445: bastore
    //   446: dup
    //   447: bipush #24
    //   449: bipush #-106
    //   451: bastore
    //   452: dup
    //   453: bipush #25
    //   455: bipush #100
    //   457: bastore
    //   458: dup
    //   459: bipush #26
    //   461: bipush #26
    //   463: bastore
    //   464: dup
    //   465: bipush #27
    //   467: bipush #34
    //   469: bastore
    //   470: dup
    //   471: bipush #28
    //   473: bipush #-5
    //   475: bastore
    //   476: dup
    //   477: bipush #29
    //   479: bipush #38
    //   481: bastore
    //   482: dup
    //   483: bipush #30
    //   485: bipush #77
    //   487: bastore
    //   488: dup
    //   489: bipush #31
    //   491: bipush #-125
    //   493: bastore
    //   494: invokespecial <init> : ([B)V
    //   497: putstatic burp/Zltp.ZT : Ljava/lang/Object;
    //   500: sipush #28711
    //   503: sipush #11373
    //   506: invokestatic a : (II)Ljava/lang/String;
    //   509: putstatic burp/Zltp.ZY : Ljava/lang/String;
    //   512: return
  }
  
  private static Throwable a(Throwable paramThrowable) {
    return paramThrowable;
  }
  
  private static String a(int paramInt1, int paramInt2) {
    int i = (paramInt1 ^ 0x7027) & 0xFFFF;
    if (b[i] == null) {
      char[] arrayOfChar = a[i].toCharArray();
      switch (arrayOfChar[0] & 0xFF) {
        case 0:
        
        case 1:
        
        case 2:
        
        case 3:
        
        case 4:
        
        case 5:
        
        case 6:
        
        case 7:
        
        case 8:
        
        case 9:
        
        case 10:
        
        case 11:
        
        case 12:
        
        case 13:
        
        case 14:
        
        case 15:
        
        case 16:
        
        case 17:
        
        case 18:
        
        case 19:
        
        case 20:
        
        case 21:
        
        case 22:
        
        case 23:
        
        case 24:
        
        case 25:
        
        case 26:
        
        case 27:
        
        case 28:
        
        case 29:
        
        case 30:
        
        case 31:
        
        case 32:
        
        case 33:
        
        case 34:
        
        case 35:
        
        case 36:
        
        case 37:
        
        case 38:
        
        case 39:
        
        case 40:
        
        case 41:
        
        case 42:
        
        case 43:
        
        case 44:
        
        case 45:
        
        case 46:
        
        case 47:
        
        case 48:
        
        case 49:
        
        case 50:
        
        case 51:
        
        case 52:
        
        case 53:
        
        case 54:
        
        case 55:
        
        case 56:
        
        case 57:
        
        case 58:
        
        case 59:
        
        case 60:
        
        case 61:
        
        case 62:
        
        case 63:
        
        case 64:
        
        case 65:
        
        case 66:
        
        case 67:
        
        case 68:
        
        case 69:
        
        case 70:
        
        case 71:
        
        case 72:
        
        case 73:
        
        case 74:
        
        case 75:
        
        case 76:
        
        case 77:
        
        case 78:
        
        case 79:
        
        case 80:
        
        case 81:
        
        case 82:
        
        case 83:
        
        case 84:
        
        case 85:
        
        case 86:
        
        case 87:
        
        case 88:
        
        case 89:
        
        case 90:
        
        case 91:
        
        case 92:
        
        case 93:
        
        case 94:
        
        case 95:
        
        case 96:
        
        case 97:
        
        case 98:
        
        case 99:
        
        case 100:
        
        case 101:
        
        case 102:
        
        case 103:
        
        case 104:
        
        case 105:
        
        case 106:
        
        case 107:
        
        case 108:
        
        case 109:
        
        case 110:
        
        case 111:
        
        case 112:
        
        case 113:
        
        case 114:
        
        case 115:
        
        case 116:
        
        case 117:
        
        case 118:
        
        case 119:
        
        case 120:
        
        case 121:
        
        case 122:
        
        case 123:
        
        case 124:
        
        case 125:
        
        case 126:
        
        case 127:
        
        case 128:
        
        case 129:
        
        case 130:
        
        case 131:
        
        case 132:
        
        case 133:
        
        case 134:
        
        case 135:
        
        case 136:
        
        case 137:
        
        case 138:
        
        case 139:
        
        case 140:
        
        case 141:
        
        case 142:
        
        case 143:
        
        case 144:
        
        case 145:
        
        case 146:
        
        case 147:
        
        case 148:
        
        case 149:
        
        case 150:
        
        case 151:
        
        case 152:
        
        case 153:
        
        case 154:
        
        case 155:
        
        case 156:
        
        case 157:
        
        case 158:
        
        case 159:
        
        case 160:
        
        case 161:
        
        case 162:
        
        case 163:
        
        case 164:
        
        case 165:
        
        case 166:
        
        case 167:
        
        case 168:
        
        case 169:
        
        case 170:
        
        case 171:
        
        case 172:
        
        case 173:
        
        case 174:
        
        case 175:
        
        case 176:
        
        case 177:
        
        case 178:
        
        case 179:
        
        case 180:
        
        case 181:
        
        case 182:
        
        case 183:
        
        case 184:
        
        case 185:
        
        case 186:
        
        case 187:
        
        case 188:
        
        case 189:
        
        case 190:
        
        case 191:
        
        case 192:
        
        case 193:
        
        case 194:
        
        case 195:
        
        case 196:
        
        case 197:
        
        case 198:
        
        case 199:
        
        case 200:
        
        case 201:
        
        case 202:
        
        case 203:
        
        case 204:
        
        case 205:
        
        case 206:
        
        case 207:
        
        case 208:
        
        case 209:
        
        case 210:
        
        case 211:
        
        case 212:
        
        case 213:
        
        case 214:
        
        case 215:
        
        case 216:
        
        case 217:
        
        case 218:
        
        case 219:
        
        case 220:
        
        case 221:
        
        case 222:
        
        case 223:
        
        case 224:
        
        case 225:
        
        case 226:
        
        case 227:
        
        case 228:
        
        case 229:
        
        case 230:
        
        case 231:
        
        case 232:
        
        case 233:
        
        case 234:
        
        case 235:
        
        case 236:
        
        case 237:
        
        case 238:
        
        case 239:
        
        case 240:
        
        case 241:
        
        case 242:
        
        case 243:
        
        case 244:
        
        case 245:
        
        case 246:
        
        case 247:
        
        case 248:
        
        case 249:
        
        case 250:
        
        case 251:
        
        case 252:
        
        case 253:
        
        case 254:
        
        default:
          break;
      } 
      char c = 'Â³';
      int j = (paramInt2 & 0xFF) - c;
      if (j < 0)
        j += 256; 
      int k = ((paramInt2 & 0xFFFF) >>> 8) - c;
      if (k < 0)
        k += 256; 
      for (byte b = 0; b < arrayOfChar.length; b++) {
        int m = b % 2;
        if (m == 0) {
          arrayOfChar[b] = (char)(arrayOfChar[b] ^ j);
          j = ((j >>> 3 | j << 5) ^ arrayOfChar[b]) & 0xFF;
        } else {
          arrayOfChar[b] = (char)(arrayOfChar[b] ^ k);
          k = ((k >>> 3 | k << 5) ^ arrayOfChar[b]) & 0xFF;
        } 
      } 
      b[i] = (new String(arrayOfChar)).intern();
    } 
    return b[i];
  }
}


/* Location:              C:\Program Files\BurpSuitePro\burpsuite_pro.jar!\burp\Zltp.class
 * Java compiler version: 21 (65.0)
 * JD-Core Version:       1.1.3
 */