package burp;

import java.math.BigInteger;

class Zlwc extends ClassLoader {
  static String ZM;
  
  static Object ZG;
  
  private static final String[] a;
  
  private static final String[] b;
  
  static void Zc(Object[] paramArrayOfObject, Object paramObject) throws Throwable {}
  
  static boolean Zd(Object[] paramArrayOfObject, Object paramObject) throws Throwable {
    // Byte code:
    //   0: invokestatic ZK : ()Z
    //   3: istore_2
    //   4: new java/lang/StringBuilder
    //   7: dup
    //   8: invokespecial <init> : ()V
    //   11: astore_3
    //   12: iconst_0
    //   13: istore #4
    //   15: iload #4
    //   17: bipush #32
    //   19: if_icmpge -> 1355
    //   22: iload #4
    //   24: tableswitch default -> 1348, 0 -> 168, 1 -> 205, 2 -> 242, 3 -> 279, 4 -> 316, 5 -> 353, 6 -> 390, 7 -> 427, 8 -> 464, 9 -> 501, 10 -> 538, 11 -> 575, 12 -> 612, 13 -> 649, 14 -> 686, 15 -> 723, 16 -> 760, 17 -> 797, 18 -> 834, 19 -> 871, 20 -> 908, 21 -> 945, 22 -> 982, 23 -> 1019, 24 -> 1056, 25 -> 1093, 26 -> 1130, 27 -> 1167, 28 -> 1204, 29 -> 1241, 30 -> 1278, 31 -> 1315
    //   168: aload_3
    //   169: getstatic burp/Zrov.ZU : Ljava/lang/String;
    //   172: getstatic burp/Zr9u.ZX : Ljava/lang/Object;
    //   175: checkcast java/math/BigInteger
    //   178: invokevirtual intValue : ()I
    //   181: bipush #32
    //   183: irem
    //   184: invokestatic abs : (I)I
    //   187: invokevirtual charAt : (I)C
    //   190: invokevirtual append : (C)Ljava/lang/StringBuilder;
    //   193: pop
    //   194: iload_2
    //   195: ifeq -> 1348
    //   198: goto -> 205
    //   201: invokestatic a : (Ljava/lang/Throwable;)Ljava/lang/Throwable;
    //   204: athrow
    //   205: aload_3
    //   206: getstatic burp/Zrtp.Zq : Ljava/lang/String;
    //   209: getstatic burp/Zkjj.Zh : Ljava/lang/Object;
    //   212: checkcast java/math/BigInteger
    //   215: invokevirtual intValue : ()I
    //   218: bipush #32
    //   220: irem
    //   221: invokestatic abs : (I)I
    //   224: invokevirtual charAt : (I)C
    //   227: invokevirtual append : (C)Ljava/lang/StringBuilder;
    //   230: pop
    //   231: iload_2
    //   232: ifeq -> 1348
    //   235: goto -> 242
    //   238: invokestatic a : (Ljava/lang/Throwable;)Ljava/lang/Throwable;
    //   241: athrow
    //   242: aload_3
    //   243: getstatic burp/Zzht.Zv : Ljava/lang/String;
    //   246: getstatic burp/Zgis.ZV : Ljava/lang/Object;
    //   249: checkcast java/math/BigInteger
    //   252: invokevirtual intValue : ()I
    //   255: bipush #32
    //   257: irem
    //   258: invokestatic abs : (I)I
    //   261: invokevirtual charAt : (I)C
    //   264: invokevirtual append : (C)Ljava/lang/StringBuilder;
    //   267: pop
    //   268: iload_2
    //   269: ifeq -> 1348
    //   272: goto -> 279
    //   275: invokestatic a : (Ljava/lang/Throwable;)Ljava/lang/Throwable;
    //   278: athrow
    //   279: aload_3
    //   280: getstatic burp/Zsp9.ZA : Ljava/lang/String;
    //   283: getstatic burp/Zz0y.Zp : Ljava/lang/Object;
    //   286: checkcast java/math/BigInteger
    //   289: invokevirtual intValue : ()I
    //   292: bipush #32
    //   294: irem
    //   295: invokestatic abs : (I)I
    //   298: invokevirtual charAt : (I)C
    //   301: invokevirtual append : (C)Ljava/lang/StringBuilder;
    //   304: pop
    //   305: iload_2
    //   306: ifeq -> 1348
    //   309: goto -> 316
    //   312: invokestatic a : (Ljava/lang/Throwable;)Ljava/lang/Throwable;
    //   315: athrow
    //   316: aload_3
    //   317: getstatic burp/Ztnn.ZS : Ljava/lang/String;
    //   320: getstatic burp/Zejz.ZF : Ljava/lang/Object;
    //   323: checkcast java/math/BigInteger
    //   326: invokevirtual intValue : ()I
    //   329: bipush #32
    //   331: irem
    //   332: invokestatic abs : (I)I
    //   335: invokevirtual charAt : (I)C
    //   338: invokevirtual append : (C)Ljava/lang/StringBuilder;
    //   341: pop
    //   342: iload_2
    //   343: ifeq -> 1348
    //   346: goto -> 353
    //   349: invokestatic a : (Ljava/lang/Throwable;)Ljava/lang/Throwable;
    //   352: athrow
    //   353: aload_3
    //   354: getstatic burp/Zesw.ZC : Ljava/lang/String;
    //   357: getstatic burp/Zsdl.Zx : Ljava/lang/Object;
    //   360: checkcast java/math/BigInteger
    //   363: invokevirtual intValue : ()I
    //   366: bipush #32
    //   368: irem
    //   369: invokestatic abs : (I)I
    //   372: invokevirtual charAt : (I)C
    //   375: invokevirtual append : (C)Ljava/lang/StringBuilder;
    //   378: pop
    //   379: iload_2
    //   380: ifeq -> 1348
    //   383: goto -> 390
    //   386: invokestatic a : (Ljava/lang/Throwable;)Ljava/lang/Throwable;
    //   389: athrow
    //   390: aload_3
    //   391: getstatic burp/Zgrz.Zu : Ljava/lang/String;
    //   394: getstatic burp/Zeqz.ZG : Ljava/lang/Object;
    //   397: checkcast java/math/BigInteger
    //   400: invokevirtual intValue : ()I
    //   403: bipush #32
    //   405: irem
    //   406: invokestatic abs : (I)I
    //   409: invokevirtual charAt : (I)C
    //   412: invokevirtual append : (C)Ljava/lang/StringBuilder;
    //   415: pop
    //   416: iload_2
    //   417: ifeq -> 1348
    //   420: goto -> 427
    //   423: invokestatic a : (Ljava/lang/Throwable;)Ljava/lang/Throwable;
    //   426: athrow
    //   427: aload_3
    //   428: getstatic burp/Zsbv.Zr : Ljava/lang/String;
    //   431: getstatic burp/Zsfj.ZL : Ljava/lang/Object;
    //   434: checkcast java/math/BigInteger
    //   437: invokevirtual intValue : ()I
    //   440: bipush #32
    //   442: irem
    //   443: invokestatic abs : (I)I
    //   446: invokevirtual charAt : (I)C
    //   449: invokevirtual append : (C)Ljava/lang/StringBuilder;
    //   452: pop
    //   453: iload_2
    //   454: ifeq -> 1348
    //   457: goto -> 464
    //   460: invokestatic a : (Ljava/lang/Throwable;)Ljava/lang/Throwable;
    //   463: athrow
    //   464: aload_3
    //   465: getstatic burp/Zebc.ZC : Ljava/lang/String;
    //   468: getstatic burp/Zxc0.Zl : Ljava/lang/Object;
    //   471: checkcast java/math/BigInteger
    //   474: invokevirtual intValue : ()I
    //   477: bipush #32
    //   479: irem
    //   480: invokestatic abs : (I)I
    //   483: invokevirtual charAt : (I)C
    //   486: invokevirtual append : (C)Ljava/lang/StringBuilder;
    //   489: pop
    //   490: iload_2
    //   491: ifeq -> 1348
    //   494: goto -> 501
    //   497: invokestatic a : (Ljava/lang/Throwable;)Ljava/lang/Throwable;
    //   500: athrow
    //   501: aload_3
    //   502: getstatic burp/Zzi_.ZG : Ljava/lang/String;
    //   505: getstatic burp/Zepy.Ze : Ljava/lang/Object;
    //   508: checkcast java/math/BigInteger
    //   511: invokevirtual intValue : ()I
    //   514: bipush #32
    //   516: irem
    //   517: invokestatic abs : (I)I
    //   520: invokevirtual charAt : (I)C
    //   523: invokevirtual append : (C)Ljava/lang/StringBuilder;
    //   526: pop
    //   527: iload_2
    //   528: ifeq -> 1348
    //   531: goto -> 538
    //   534: invokestatic a : (Ljava/lang/Throwable;)Ljava/lang/Throwable;
    //   537: athrow
    //   538: aload_3
    //   539: getstatic burp/Ztq8.ZI : Ljava/lang/String;
    //   542: getstatic burp/Zea8.ZF : Ljava/lang/Object;
    //   545: checkcast java/math/BigInteger
    //   548: invokevirtual intValue : ()I
    //   551: bipush #32
    //   553: irem
    //   554: invokestatic abs : (I)I
    //   557: invokevirtual charAt : (I)C
    //   560: invokevirtual append : (C)Ljava/lang/StringBuilder;
    //   563: pop
    //   564: iload_2
    //   565: ifeq -> 1348
    //   568: goto -> 575
    //   571: invokestatic a : (Ljava/lang/Throwable;)Ljava/lang/Throwable;
    //   574: athrow
    //   575: aload_3
    //   576: getstatic burp/Zz0b.ZD : Ljava/lang/String;
    //   579: getstatic burp/Zg6z.ZS : Ljava/lang/Object;
    //   582: checkcast java/math/BigInteger
    //   585: invokevirtual intValue : ()I
    //   588: bipush #32
    //   590: irem
    //   591: invokestatic abs : (I)I
    //   594: invokevirtual charAt : (I)C
    //   597: invokevirtual append : (C)Ljava/lang/StringBuilder;
    //   600: pop
    //   601: iload_2
    //   602: ifeq -> 1348
    //   605: goto -> 612
    //   608: invokestatic a : (Ljava/lang/Throwable;)Ljava/lang/Throwable;
    //   611: athrow
    //   612: aload_3
    //   613: getstatic burp/Zzc9.Zv : Ljava/lang/String;
    //   616: getstatic burp/Zea8.ZF : Ljava/lang/Object;
    //   619: checkcast java/math/BigInteger
    //   622: invokevirtual intValue : ()I
    //   625: bipush #32
    //   627: irem
    //   628: invokestatic abs : (I)I
    //   631: invokevirtual charAt : (I)C
    //   634: invokevirtual append : (C)Ljava/lang/StringBuilder;
    //   637: pop
    //   638: iload_2
    //   639: ifeq -> 1348
    //   642: goto -> 649
    //   645: invokestatic a : (Ljava/lang/Throwable;)Ljava/lang/Throwable;
    //   648: athrow
    //   649: aload_3
    //   650: getstatic burp/Zs8w.ZR : Ljava/lang/String;
    //   653: getstatic burp/Zkkl.ZE : Ljava/lang/Object;
    //   656: checkcast java/math/BigInteger
    //   659: invokevirtual intValue : ()I
    //   662: bipush #32
    //   664: irem
    //   665: invokestatic abs : (I)I
    //   668: invokevirtual charAt : (I)C
    //   671: invokevirtual append : (C)Ljava/lang/StringBuilder;
    //   674: pop
    //   675: iload_2
    //   676: ifeq -> 1348
    //   679: goto -> 686
    //   682: invokestatic a : (Ljava/lang/Throwable;)Ljava/lang/Throwable;
    //   685: athrow
    //   686: aload_3
    //   687: getstatic burp/Zmyk.Zx : Ljava/lang/String;
    //   690: getstatic burp/Zt4p.Zh : Ljava/lang/Object;
    //   693: checkcast java/math/BigInteger
    //   696: invokevirtual intValue : ()I
    //   699: bipush #32
    //   701: irem
    //   702: invokestatic abs : (I)I
    //   705: invokevirtual charAt : (I)C
    //   708: invokevirtual append : (C)Ljava/lang/StringBuilder;
    //   711: pop
    //   712: iload_2
    //   713: ifeq -> 1348
    //   716: goto -> 723
    //   719: invokestatic a : (Ljava/lang/Throwable;)Ljava/lang/Throwable;
    //   722: athrow
    //   723: aload_3
    //   724: getstatic burp/Zql.Zf : Ljava/lang/String;
    //   727: getstatic burp/Zbze.ZM : Ljava/lang/Object;
    //   730: checkcast java/math/BigInteger
    //   733: invokevirtual intValue : ()I
    //   736: bipush #32
    //   738: irem
    //   739: invokestatic abs : (I)I
    //   742: invokevirtual charAt : (I)C
    //   745: invokevirtual append : (C)Ljava/lang/StringBuilder;
    //   748: pop
    //   749: iload_2
    //   750: ifeq -> 1348
    //   753: goto -> 760
    //   756: invokestatic a : (Ljava/lang/Throwable;)Ljava/lang/Throwable;
    //   759: athrow
    //   760: aload_3
    //   761: getstatic burp/Zzi_.ZG : Ljava/lang/String;
    //   764: getstatic burp/Zrip.ZB : Ljava/lang/Object;
    //   767: checkcast java/math/BigInteger
    //   770: invokevirtual intValue : ()I
    //   773: bipush #32
    //   775: irem
    //   776: invokestatic abs : (I)I
    //   779: invokevirtual charAt : (I)C
    //   782: invokevirtual append : (C)Ljava/lang/StringBuilder;
    //   785: pop
    //   786: iload_2
    //   787: ifeq -> 1348
    //   790: goto -> 797
    //   793: invokestatic a : (Ljava/lang/Throwable;)Ljava/lang/Throwable;
    //   796: athrow
    //   797: aload_3
    //   798: getstatic burp/Zebe.ZW : Ljava/lang/String;
    //   801: getstatic burp/Zm69.Zg : Ljava/lang/Object;
    //   804: checkcast java/math/BigInteger
    //   807: invokevirtual intValue : ()I
    //   810: bipush #32
    //   812: irem
    //   813: invokestatic abs : (I)I
    //   816: invokevirtual charAt : (I)C
    //   819: invokevirtual append : (C)Ljava/lang/StringBuilder;
    //   822: pop
    //   823: iload_2
    //   824: ifeq -> 1348
    //   827: goto -> 834
    //   830: invokestatic a : (Ljava/lang/Throwable;)Ljava/lang/Throwable;
    //   833: athrow
    //   834: aload_3
    //   835: getstatic burp/Ze2w.Za : Ljava/lang/String;
    //   838: getstatic burp/Zku9.Zp : Ljava/lang/Object;
    //   841: checkcast java/math/BigInteger
    //   844: invokevirtual intValue : ()I
    //   847: bipush #32
    //   849: irem
    //   850: invokestatic abs : (I)I
    //   853: invokevirtual charAt : (I)C
    //   856: invokevirtual append : (C)Ljava/lang/StringBuilder;
    //   859: pop
    //   860: iload_2
    //   861: ifeq -> 1348
    //   864: goto -> 871
    //   867: invokestatic a : (Ljava/lang/Throwable;)Ljava/lang/Throwable;
    //   870: athrow
    //   871: aload_3
    //   872: getstatic burp/Zxd1.ZQ : Ljava/lang/String;
    //   875: getstatic burp/Zl7b.ZK : Ljava/lang/Object;
    //   878: checkcast java/math/BigInteger
    //   881: invokevirtual intValue : ()I
    //   884: bipush #32
    //   886: irem
    //   887: invokestatic abs : (I)I
    //   890: invokevirtual charAt : (I)C
    //   893: invokevirtual append : (C)Ljava/lang/StringBuilder;
    //   896: pop
    //   897: iload_2
    //   898: ifeq -> 1348
    //   901: goto -> 908
    //   904: invokestatic a : (Ljava/lang/Throwable;)Ljava/lang/Throwable;
    //   907: athrow
    //   908: aload_3
    //   909: getstatic burp/Zlw8.Zs : Ljava/lang/String;
    //   912: getstatic burp/Zgtx.Z_ : Ljava/lang/Object;
    //   915: checkcast java/math/BigInteger
    //   918: invokevirtual intValue : ()I
    //   921: bipush #32
    //   923: irem
    //   924: invokestatic abs : (I)I
    //   927: invokevirtual charAt : (I)C
    //   930: invokevirtual append : (C)Ljava/lang/StringBuilder;
    //   933: pop
    //   934: iload_2
    //   935: ifeq -> 1348
    //   938: goto -> 945
    //   941: invokestatic a : (Ljava/lang/Throwable;)Ljava/lang/Throwable;
    //   944: athrow
    //   945: aload_3
    //   946: getstatic burp/Zxp1.Zg : Ljava/lang/String;
    //   949: getstatic burp/Zk92.Zn : Ljava/lang/Object;
    //   952: checkcast java/math/BigInteger
    //   955: invokevirtual intValue : ()I
    //   958: bipush #32
    //   960: irem
    //   961: invokestatic abs : (I)I
    //   964: invokevirtual charAt : (I)C
    //   967: invokevirtual append : (C)Ljava/lang/StringBuilder;
    //   970: pop
    //   971: iload_2
    //   972: ifeq -> 1348
    //   975: goto -> 982
    //   978: invokestatic a : (Ljava/lang/Throwable;)Ljava/lang/Throwable;
    //   981: athrow
    //   982: aload_3
    //   983: getstatic burp/Ztzj.ZB : Ljava/lang/String;
    //   986: getstatic burp/Zrjq.ZU : Ljava/lang/Object;
    //   989: checkcast java/math/BigInteger
    //   992: invokevirtual intValue : ()I
    //   995: bipush #32
    //   997: irem
    //   998: invokestatic abs : (I)I
    //   1001: invokevirtual charAt : (I)C
    //   1004: invokevirtual append : (C)Ljava/lang/StringBuilder;
    //   1007: pop
    //   1008: iload_2
    //   1009: ifeq -> 1348
    //   1012: goto -> 1019
    //   1015: invokestatic a : (Ljava/lang/Throwable;)Ljava/lang/Throwable;
    //   1018: athrow
    //   1019: aload_3
    //   1020: getstatic burp/Zbx4.ZS : Ljava/lang/String;
    //   1023: getstatic burp/Zr60.Ze : Ljava/lang/Object;
    //   1026: checkcast java/math/BigInteger
    //   1029: invokevirtual intValue : ()I
    //   1032: bipush #32
    //   1034: irem
    //   1035: invokestatic abs : (I)I
    //   1038: invokevirtual charAt : (I)C
    //   1041: invokevirtual append : (C)Ljava/lang/StringBuilder;
    //   1044: pop
    //   1045: iload_2
    //   1046: ifeq -> 1348
    //   1049: goto -> 1056
    //   1052: invokestatic a : (Ljava/lang/Throwable;)Ljava/lang/Throwable;
    //   1055: athrow
    //   1056: aload_3
    //   1057: getstatic burp/Zbow.Zr : Ljava/lang/String;
    //   1060: getstatic burp/Zl1e.Zp : Ljava/lang/Object;
    //   1063: checkcast java/math/BigInteger
    //   1066: invokevirtual intValue : ()I
    //   1069: bipush #32
    //   1071: irem
    //   1072: invokestatic abs : (I)I
    //   1075: invokevirtual charAt : (I)C
    //   1078: invokevirtual append : (C)Ljava/lang/StringBuilder;
    //   1081: pop
    //   1082: iload_2
    //   1083: ifeq -> 1348
    //   1086: goto -> 1093
    //   1089: invokestatic a : (Ljava/lang/Throwable;)Ljava/lang/Throwable;
    //   1092: athrow
    //   1093: aload_3
    //   1094: getstatic burp/Zxdp.ZN : Ljava/lang/String;
    //   1097: getstatic burp/Zvh.Zb : Ljava/lang/Object;
    //   1100: checkcast java/math/BigInteger
    //   1103: invokevirtual intValue : ()I
    //   1106: bipush #32
    //   1108: irem
    //   1109: invokestatic abs : (I)I
    //   1112: invokevirtual charAt : (I)C
    //   1115: invokevirtual append : (C)Ljava/lang/StringBuilder;
    //   1118: pop
    //   1119: iload_2
    //   1120: ifeq -> 1348
    //   1123: goto -> 1130
    //   1126: invokestatic a : (Ljava/lang/Throwable;)Ljava/lang/Throwable;
    //   1129: athrow
    //   1130: aload_3
    //   1131: getstatic burp/Zkhf.Zb : Ljava/lang/String;
    //   1134: getstatic burp/Zegj.ZT : Ljava/lang/Object;
    //   1137: checkcast java/math/BigInteger
    //   1140: invokevirtual intValue : ()I
    //   1143: bipush #32
    //   1145: irem
    //   1146: invokestatic abs : (I)I
    //   1149: invokevirtual charAt : (I)C
    //   1152: invokevirtual append : (C)Ljava/lang/StringBuilder;
    //   1155: pop
    //   1156: iload_2
    //   1157: ifeq -> 1348
    //   1160: goto -> 1167
    //   1163: invokestatic a : (Ljava/lang/Throwable;)Ljava/lang/Throwable;
    //   1166: athrow
    //   1167: aload_3
    //   1168: getstatic burp/Zzc9.Zv : Ljava/lang/String;
    //   1171: getstatic burp/Zzhx.ZB : Ljava/lang/Object;
    //   1174: checkcast java/math/BigInteger
    //   1177: invokevirtual intValue : ()I
    //   1180: bipush #32
    //   1182: irem
    //   1183: invokestatic abs : (I)I
    //   1186: invokevirtual charAt : (I)C
    //   1189: invokevirtual append : (C)Ljava/lang/StringBuilder;
    //   1192: pop
    //   1193: iload_2
    //   1194: ifeq -> 1348
    //   1197: goto -> 1204
    //   1200: invokestatic a : (Ljava/lang/Throwable;)Ljava/lang/Throwable;
    //   1203: athrow
    //   1204: aload_3
    //   1205: getstatic burp/Zz66.ZM : Ljava/lang/String;
    //   1208: getstatic burp/Zebe.Zw : Ljava/lang/Object;
    //   1211: checkcast java/math/BigInteger
    //   1214: invokevirtual intValue : ()I
    //   1217: bipush #32
    //   1219: irem
    //   1220: invokestatic abs : (I)I
    //   1223: invokevirtual charAt : (I)C
    //   1226: invokevirtual append : (C)Ljava/lang/StringBuilder;
    //   1229: pop
    //   1230: iload_2
    //   1231: ifeq -> 1348
    //   1234: goto -> 1241
    //   1237: invokestatic a : (Ljava/lang/Throwable;)Ljava/lang/Throwable;
    //   1240: athrow
    //   1241: aload_3
    //   1242: getstatic burp/Zsn3.ZS : Ljava/lang/String;
    //   1245: getstatic burp/Zk8f.ZG : Ljava/lang/Object;
    //   1248: checkcast java/math/BigInteger
    //   1251: invokevirtual intValue : ()I
    //   1254: bipush #32
    //   1256: irem
    //   1257: invokestatic abs : (I)I
    //   1260: invokevirtual charAt : (I)C
    //   1263: invokevirtual append : (C)Ljava/lang/StringBuilder;
    //   1266: pop
    //   1267: iload_2
    //   1268: ifeq -> 1348
    //   1271: goto -> 1278
    //   1274: invokestatic a : (Ljava/lang/Throwable;)Ljava/lang/Throwable;
    //   1277: athrow
    //   1278: aload_3
    //   1279: getstatic burp/Zk1.Zg : Ljava/lang/String;
    //   1282: getstatic burp/Zz0y.Zp : Ljava/lang/Object;
    //   1285: checkcast java/math/BigInteger
    //   1288: invokevirtual intValue : ()I
    //   1291: bipush #32
    //   1293: irem
    //   1294: invokestatic abs : (I)I
    //   1297: invokevirtual charAt : (I)C
    //   1300: invokevirtual append : (C)Ljava/lang/StringBuilder;
    //   1303: pop
    //   1304: iload_2
    //   1305: ifeq -> 1348
    //   1308: goto -> 1315
    //   1311: invokestatic a : (Ljava/lang/Throwable;)Ljava/lang/Throwable;
    //   1314: athrow
    //   1315: aload_3
    //   1316: getstatic burp/Zlo0.ZD : Ljava/lang/String;
    //   1319: getstatic burp/Zsbv.Zl : Ljava/lang/Object;
    //   1322: checkcast java/math/BigInteger
    //   1325: invokevirtual intValue : ()I
    //   1328: bipush #32
    //   1330: irem
    //   1331: invokestatic abs : (I)I
    //   1334: invokevirtual charAt : (I)C
    //   1337: invokevirtual append : (C)Ljava/lang/StringBuilder;
    //   1340: pop
    //   1341: goto -> 1348
    //   1344: invokestatic a : (Ljava/lang/Throwable;)Ljava/lang/Throwable;
    //   1347: athrow
    //   1348: iinc #4, 1
    //   1351: iload_2
    //   1352: ifeq -> 15
    //   1355: aload_3
    //   1356: invokevirtual toString : ()Ljava/lang/String;
    //   1359: putstatic burp/Zz0f.ZW : Ljava/lang/String;
    //   1362: sipush #-27685
    //   1365: sipush #16088
    //   1368: invokestatic a : (II)Ljava/lang/String;
    //   1371: iconst_1
    //   1372: ldc burp/Zecw
    //   1374: invokevirtual getClassLoader : ()Ljava/lang/ClassLoader;
    //   1377: invokestatic forName : (Ljava/lang/String;ZLjava/lang/ClassLoader;)Ljava/lang/Class;
    //   1380: invokevirtual getDeclaredFields : ()[Ljava/lang/reflect/Field;
    //   1383: astore #4
    //   1385: aload #4
    //   1387: arraylength
    //   1388: istore #5
    //   1390: iconst_0
    //   1391: istore #6
    //   1393: iload #6
    //   1395: iload #5
    //   1397: if_icmpge -> 1535
    //   1400: aload #4
    //   1402: iload #6
    //   1404: aaload
    //   1405: astore #7
    //   1407: aload #7
    //   1409: invokevirtual getModifiers : ()I
    //   1412: invokestatic isStatic : (I)Z
    //   1415: ifne -> 1425
    //   1418: goto -> 1528
    //   1421: invokestatic a : (Ljava/lang/Throwable;)Ljava/lang/Throwable;
    //   1424: athrow
    //   1425: aload #7
    //   1427: invokevirtual getType : ()Ljava/lang/Class;
    //   1430: astore #8
    //   1432: aload #8
    //   1434: ifnull -> 1515
    //   1437: aload #8
    //   1439: invokevirtual isPrimitive : ()Z
    //   1442: ifne -> 1515
    //   1445: goto -> 1452
    //   1448: invokestatic a : (Ljava/lang/Throwable;)Ljava/lang/Throwable;
    //   1451: athrow
    //   1452: aload #8
    //   1454: invokevirtual getPackage : ()Ljava/lang/Package;
    //   1457: ifnull -> 1515
    //   1460: goto -> 1467
    //   1463: invokestatic a : (Ljava/lang/Throwable;)Ljava/lang/Throwable;
    //   1466: athrow
    //   1467: aload #8
    //   1469: invokevirtual getPackage : ()Ljava/lang/Package;
    //   1472: invokevirtual getName : ()Ljava/lang/String;
    //   1475: ifnull -> 1515
    //   1478: goto -> 1485
    //   1481: invokestatic a : (Ljava/lang/Throwable;)Ljava/lang/Throwable;
    //   1484: athrow
    //   1485: aload #8
    //   1487: invokevirtual getPackage : ()Ljava/lang/Package;
    //   1490: invokevirtual getName : ()Ljava/lang/String;
    //   1493: sipush #-27700
    //   1496: sipush #-4142
    //   1499: invokestatic a : (II)Ljava/lang/String;
    //   1502: invokevirtual startsWith : (Ljava/lang/String;)Z
    //   1505: ifne -> 1515
    //   1508: goto -> 1515
    //   1511: invokestatic a : (Ljava/lang/Throwable;)Ljava/lang/Throwable;
    //   1514: athrow
    //   1515: aload #7
    //   1517: iconst_1
    //   1518: invokevirtual setAccessible : (Z)V
    //   1521: aload #7
    //   1523: aconst_null
    //   1524: invokevirtual get : (Ljava/lang/Object;)Ljava/lang/Object;
    //   1527: pop
    //   1528: iinc #6, 1
    //   1531: iload_2
    //   1532: ifeq -> 1393
    //   1535: sipush #-27703
    //   1538: sipush #22212
    //   1541: invokestatic a : (II)Ljava/lang/String;
    //   1544: invokestatic forName : (Ljava/lang/String;)Ljava/lang/Class;
    //   1547: invokevirtual getDeclaredMethods : ()[Ljava/lang/reflect/Method;
    //   1550: astore #4
    //   1552: aload #4
    //   1554: arraylength
    //   1555: istore #5
    //   1557: iconst_0
    //   1558: istore #6
    //   1560: iload #6
    //   1562: iload #5
    //   1564: if_icmpge -> 1697
    //   1567: aload #4
    //   1569: iload #6
    //   1571: aaload
    //   1572: astore #7
    //   1574: aload #7
    //   1576: invokevirtual getParameterTypes : ()[Ljava/lang/Class;
    //   1579: pop
    //   1580: aload #7
    //   1582: invokevirtual getModifiers : ()I
    //   1585: invokestatic isStatic : (I)Z
    //   1588: ifeq -> 1683
    //   1591: aload #7
    //   1593: invokevirtual getParameterTypes : ()[Ljava/lang/Class;
    //   1596: arraylength
    //   1597: iconst_2
    //   1598: if_icmpne -> 1683
    //   1601: goto -> 1608
    //   1604: invokestatic a : (Ljava/lang/Throwable;)Ljava/lang/Throwable;
    //   1607: athrow
    //   1608: aload #7
    //   1610: invokevirtual getReturnType : ()Ljava/lang/Class;
    //   1613: getstatic java/lang/Void.TYPE : Ljava/lang/Class;
    //   1616: invokevirtual equals : (Ljava/lang/Object;)Z
    //   1619: ifeq -> 1683
    //   1622: goto -> 1629
    //   1625: invokestatic a : (Ljava/lang/Throwable;)Ljava/lang/Throwable;
    //   1628: athrow
    //   1629: aload #7
    //   1631: iconst_1
    //   1632: invokevirtual setAccessible : (Z)V
    //   1635: aload #7
    //   1637: aconst_null
    //   1638: iconst_2
    //   1639: anewarray java/lang/Object
    //   1642: dup
    //   1643: iconst_0
    //   1644: aload_0
    //   1645: aastore
    //   1646: dup
    //   1647: iconst_1
    //   1648: aload_1
    //   1649: ifnonnull -> 1667
    //   1652: goto -> 1659
    //   1655: invokestatic a : (Ljava/lang/Throwable;)Ljava/lang/Throwable;
    //   1658: athrow
    //   1659: aload_1
    //   1660: goto -> 1674
    //   1663: invokestatic a : (Ljava/lang/Throwable;)Ljava/lang/Throwable;
    //   1666: athrow
    //   1667: aload_1
    //   1668: checkcast [B
    //   1671: invokevirtual clone : ()Ljava/lang/Object;
    //   1674: aastore
    //   1675: invokevirtual invoke : (Ljava/lang/Object;[Ljava/lang/Object;)Ljava/lang/Object;
    //   1678: pop
    //   1679: iload_2
    //   1680: ifeq -> 1697
    //   1683: iinc #6, 1
    //   1686: iload_2
    //   1687: ifeq -> 1560
    //   1690: goto -> 1697
    //   1693: invokestatic a : (Ljava/lang/Throwable;)Ljava/lang/Throwable;
    //   1696: athrow
    //   1697: iconst_0
    //   1698: istore #4
    //   1700: getstatic burp/Zg0q.Ze : Ljava/lang/String;
    //   1703: getstatic burp/Zsbo.ZG : Ljava/lang/Object;
    //   1706: checkcast java/math/BigInteger
    //   1709: invokevirtual intValue : ()I
    //   1712: bipush #32
    //   1714: irem
    //   1715: invokestatic abs : (I)I
    //   1718: invokevirtual charAt : (I)C
    //   1721: getstatic burp/Zm8j.Zp : Ljava/lang/String;
    //   1724: getstatic burp/Zb6m.ZQ : Ljava/lang/Object;
    //   1727: checkcast java/math/BigInteger
    //   1730: invokevirtual intValue : ()I
    //   1733: bipush #32
    //   1735: irem
    //   1736: invokestatic abs : (I)I
    //   1739: invokevirtual charAt : (I)C
    //   1742: if_icmple -> 2087
    //   1745: sipush #-27689
    //   1748: sipush #1763
    //   1751: invokestatic a : (II)Ljava/lang/String;
    //   1754: iconst_1
    //   1755: ldc burp/Zls0
    //   1757: invokevirtual getClassLoader : ()Ljava/lang/ClassLoader;
    //   1760: invokestatic forName : (Ljava/lang/String;ZLjava/lang/ClassLoader;)Ljava/lang/Class;
    //   1763: invokevirtual getDeclaredFields : ()[Ljava/lang/reflect/Field;
    //   1766: astore #5
    //   1768: aload #5
    //   1770: arraylength
    //   1771: istore #6
    //   1773: iconst_0
    //   1774: istore #7
    //   1776: iload #7
    //   1778: iload #6
    //   1780: if_icmpge -> 1918
    //   1783: aload #5
    //   1785: iload #7
    //   1787: aaload
    //   1788: astore #8
    //   1790: aload #8
    //   1792: invokevirtual getModifiers : ()I
    //   1795: invokestatic isStatic : (I)Z
    //   1798: ifne -> 1808
    //   1801: goto -> 1911
    //   1804: invokestatic a : (Ljava/lang/Throwable;)Ljava/lang/Throwable;
    //   1807: athrow
    //   1808: aload #8
    //   1810: invokevirtual getType : ()Ljava/lang/Class;
    //   1813: astore #9
    //   1815: aload #9
    //   1817: ifnull -> 1898
    //   1820: aload #9
    //   1822: invokevirtual isPrimitive : ()Z
    //   1825: ifne -> 1898
    //   1828: goto -> 1835
    //   1831: invokestatic a : (Ljava/lang/Throwable;)Ljava/lang/Throwable;
    //   1834: athrow
    //   1835: aload #9
    //   1837: invokevirtual getPackage : ()Ljava/lang/Package;
    //   1840: ifnull -> 1898
    //   1843: goto -> 1850
    //   1846: invokestatic a : (Ljava/lang/Throwable;)Ljava/lang/Throwable;
    //   1849: athrow
    //   1850: aload #9
    //   1852: invokevirtual getPackage : ()Ljava/lang/Package;
    //   1855: invokevirtual getName : ()Ljava/lang/String;
    //   1858: ifnull -> 1898
    //   1861: goto -> 1868
    //   1864: invokestatic a : (Ljava/lang/Throwable;)Ljava/lang/Throwable;
    //   1867: athrow
    //   1868: aload #9
    //   1870: invokevirtual getPackage : ()Ljava/lang/Package;
    //   1873: invokevirtual getName : ()Ljava/lang/String;
    //   1876: sipush #-27710
    //   1879: sipush #4662
    //   1882: invokestatic a : (II)Ljava/lang/String;
    //   1885: invokevirtual startsWith : (Ljava/lang/String;)Z
    //   1888: ifne -> 1898
    //   1891: goto -> 1898
    //   1894: invokestatic a : (Ljava/lang/Throwable;)Ljava/lang/Throwable;
    //   1897: athrow
    //   1898: aload #8
    //   1900: iconst_1
    //   1901: invokevirtual setAccessible : (Z)V
    //   1904: aload #8
    //   1906: aconst_null
    //   1907: invokevirtual get : (Ljava/lang/Object;)Ljava/lang/Object;
    //   1910: pop
    //   1911: iinc #7, 1
    //   1914: iload_2
    //   1915: ifeq -> 1776
    //   1918: sipush #-27683
    //   1921: sipush #32554
    //   1924: invokestatic a : (II)Ljava/lang/String;
    //   1927: invokestatic forName : (Ljava/lang/String;)Ljava/lang/Class;
    //   1930: invokevirtual getDeclaredMethods : ()[Ljava/lang/reflect/Method;
    //   1933: astore #5
    //   1935: aload #5
    //   1937: arraylength
    //   1938: istore #6
    //   1940: iconst_0
    //   1941: istore #7
    //   1943: iload #7
    //   1945: iload #6
    //   1947: if_icmpge -> 2084
    //   1950: aload #5
    //   1952: iload #7
    //   1954: aaload
    //   1955: astore #8
    //   1957: aload #8
    //   1959: invokevirtual getParameterTypes : ()[Ljava/lang/Class;
    //   1962: pop
    //   1963: aload #8
    //   1965: invokevirtual getModifiers : ()I
    //   1968: invokestatic isStatic : (I)Z
    //   1971: ifeq -> 2070
    //   1974: aload #8
    //   1976: invokevirtual getParameterTypes : ()[Ljava/lang/Class;
    //   1979: arraylength
    //   1980: iconst_2
    //   1981: if_icmpne -> 2070
    //   1984: goto -> 1991
    //   1987: invokestatic a : (Ljava/lang/Throwable;)Ljava/lang/Throwable;
    //   1990: athrow
    //   1991: aload #8
    //   1993: invokevirtual getReturnType : ()Ljava/lang/Class;
    //   1996: getstatic java/lang/Boolean.TYPE : Ljava/lang/Class;
    //   1999: if_acmpne -> 2070
    //   2002: goto -> 2009
    //   2005: invokestatic a : (Ljava/lang/Throwable;)Ljava/lang/Throwable;
    //   2008: athrow
    //   2009: aload #8
    //   2011: iconst_1
    //   2012: invokevirtual setAccessible : (Z)V
    //   2015: aload #8
    //   2017: aconst_null
    //   2018: iconst_2
    //   2019: anewarray java/lang/Object
    //   2022: dup
    //   2023: iconst_0
    //   2024: aload_0
    //   2025: aastore
    //   2026: dup
    //   2027: iconst_1
    //   2028: aload_1
    //   2029: ifnonnull -> 2047
    //   2032: goto -> 2039
    //   2035: invokestatic a : (Ljava/lang/Throwable;)Ljava/lang/Throwable;
    //   2038: athrow
    //   2039: aload_1
    //   2040: goto -> 2054
    //   2043: invokestatic a : (Ljava/lang/Throwable;)Ljava/lang/Throwable;
    //   2046: athrow
    //   2047: aload_1
    //   2048: checkcast [B
    //   2051: invokevirtual clone : ()Ljava/lang/Object;
    //   2054: aastore
    //   2055: invokevirtual invoke : (Ljava/lang/Object;[Ljava/lang/Object;)Ljava/lang/Object;
    //   2058: checkcast java/lang/Boolean
    //   2061: invokevirtual booleanValue : ()Z
    //   2064: istore #4
    //   2066: iload_2
    //   2067: ifeq -> 2084
    //   2070: iinc #7, 1
    //   2073: iload_2
    //   2074: ifeq -> 1943
    //   2077: goto -> 2084
    //   2080: invokestatic a : (Ljava/lang/Throwable;)Ljava/lang/Throwable;
    //   2083: athrow
    //   2084: goto -> 2425
    //   2087: sipush #-27704
    //   2090: bipush #-48
    //   2092: invokestatic a : (II)Ljava/lang/String;
    //   2095: iconst_1
    //   2096: ldc burp/Zgwq
    //   2098: invokevirtual getClassLoader : ()Ljava/lang/ClassLoader;
    //   2101: invokestatic forName : (Ljava/lang/String;ZLjava/lang/ClassLoader;)Ljava/lang/Class;
    //   2104: invokevirtual getDeclaredFields : ()[Ljava/lang/reflect/Field;
    //   2107: astore #5
    //   2109: aload #5
    //   2111: arraylength
    //   2112: istore #6
    //   2114: iconst_0
    //   2115: istore #7
    //   2117: iload #7
    //   2119: iload #6
    //   2121: if_icmpge -> 2259
    //   2124: aload #5
    //   2126: iload #7
    //   2128: aaload
    //   2129: astore #8
    //   2131: aload #8
    //   2133: invokevirtual getModifiers : ()I
    //   2136: invokestatic isStatic : (I)Z
    //   2139: ifne -> 2149
    //   2142: goto -> 2252
    //   2145: invokestatic a : (Ljava/lang/Throwable;)Ljava/lang/Throwable;
    //   2148: athrow
    //   2149: aload #8
    //   2151: invokevirtual getType : ()Ljava/lang/Class;
    //   2154: astore #9
    //   2156: aload #9
    //   2158: ifnull -> 2239
    //   2161: aload #9
    //   2163: invokevirtual isPrimitive : ()Z
    //   2166: ifne -> 2239
    //   2169: goto -> 2176
    //   2172: invokestatic a : (Ljava/lang/Throwable;)Ljava/lang/Throwable;
    //   2175: athrow
    //   2176: aload #9
    //   2178: invokevirtual getPackage : ()Ljava/lang/Package;
    //   2181: ifnull -> 2239
    //   2184: goto -> 2191
    //   2187: invokestatic a : (Ljava/lang/Throwable;)Ljava/lang/Throwable;
    //   2190: athrow
    //   2191: aload #9
    //   2193: invokevirtual getPackage : ()Ljava/lang/Package;
    //   2196: invokevirtual getName : ()Ljava/lang/String;
    //   2199: ifnull -> 2239
    //   2202: goto -> 2209
    //   2205: invokestatic a : (Ljava/lang/Throwable;)Ljava/lang/Throwable;
    //   2208: athrow
    //   2209: aload #9
    //   2211: invokevirtual getPackage : ()Ljava/lang/Package;
    //   2214: invokevirtual getName : ()Ljava/lang/String;
    //   2217: sipush #-27710
    //   2220: sipush #4662
    //   2223: invokestatic a : (II)Ljava/lang/String;
    //   2226: invokevirtual startsWith : (Ljava/lang/String;)Z
    //   2229: ifne -> 2239
    //   2232: goto -> 2239
    //   2235: invokestatic a : (Ljava/lang/Throwable;)Ljava/lang/Throwable;
    //   2238: athrow
    //   2239: aload #8
    //   2241: iconst_1
    //   2242: invokevirtual setAccessible : (Z)V
    //   2245: aload #8
    //   2247: aconst_null
    //   2248: invokevirtual get : (Ljava/lang/Object;)Ljava/lang/Object;
    //   2251: pop
    //   2252: iinc #7, 1
    //   2255: iload_2
    //   2256: ifeq -> 2117
    //   2259: sipush #-27695
    //   2262: sipush #30033
    //   2265: invokestatic a : (II)Ljava/lang/String;
    //   2268: invokestatic forName : (Ljava/lang/String;)Ljava/lang/Class;
    //   2271: invokevirtual getDeclaredMethods : ()[Ljava/lang/reflect/Method;
    //   2274: astore #5
    //   2276: aload #5
    //   2278: arraylength
    //   2279: istore #6
    //   2281: iconst_0
    //   2282: istore #7
    //   2284: iload #7
    //   2286: iload #6
    //   2288: if_icmpge -> 2425
    //   2291: aload #5
    //   2293: iload #7
    //   2295: aaload
    //   2296: astore #8
    //   2298: aload #8
    //   2300: invokevirtual getParameterTypes : ()[Ljava/lang/Class;
    //   2303: pop
    //   2304: aload #8
    //   2306: invokevirtual getModifiers : ()I
    //   2309: invokestatic isStatic : (I)Z
    //   2312: ifeq -> 2411
    //   2315: aload #8
    //   2317: invokevirtual getParameterTypes : ()[Ljava/lang/Class;
    //   2320: arraylength
    //   2321: iconst_2
    //   2322: if_icmpne -> 2411
    //   2325: goto -> 2332
    //   2328: invokestatic a : (Ljava/lang/Throwable;)Ljava/lang/Throwable;
    //   2331: athrow
    //   2332: aload #8
    //   2334: invokevirtual getReturnType : ()Ljava/lang/Class;
    //   2337: getstatic java/lang/Boolean.TYPE : Ljava/lang/Class;
    //   2340: if_acmpne -> 2411
    //   2343: goto -> 2350
    //   2346: invokestatic a : (Ljava/lang/Throwable;)Ljava/lang/Throwable;
    //   2349: athrow
    //   2350: aload #8
    //   2352: iconst_1
    //   2353: invokevirtual setAccessible : (Z)V
    //   2356: aload #8
    //   2358: aconst_null
    //   2359: iconst_2
    //   2360: anewarray java/lang/Object
    //   2363: dup
    //   2364: iconst_0
    //   2365: aload_0
    //   2366: aastore
    //   2367: dup
    //   2368: iconst_1
    //   2369: aload_1
    //   2370: ifnonnull -> 2388
    //   2373: goto -> 2380
    //   2376: invokestatic a : (Ljava/lang/Throwable;)Ljava/lang/Throwable;
    //   2379: athrow
    //   2380: aload_1
    //   2381: goto -> 2395
    //   2384: invokestatic a : (Ljava/lang/Throwable;)Ljava/lang/Throwable;
    //   2387: athrow
    //   2388: aload_1
    //   2389: checkcast [B
    //   2392: invokevirtual clone : ()Ljava/lang/Object;
    //   2395: aastore
    //   2396: invokevirtual invoke : (Ljava/lang/Object;[Ljava/lang/Object;)Ljava/lang/Object;
    //   2399: checkcast java/lang/Boolean
    //   2402: invokevirtual booleanValue : ()Z
    //   2405: istore #4
    //   2407: iload_2
    //   2408: ifeq -> 2425
    //   2411: iinc #7, 1
    //   2414: iload_2
    //   2415: ifeq -> 2284
    //   2418: goto -> 2425
    //   2421: invokestatic a : (Ljava/lang/Throwable;)Ljava/lang/Throwable;
    //   2424: athrow
    //   2425: iload #4
    //   2427: ifeq -> 2433
    //   2430: iload #4
    //   2432: ireturn
    //   2433: getstatic burp/Zsn9.Zp : Ljava/lang/String;
    //   2436: getstatic burp/Zreu.Zi : Ljava/lang/Object;
    //   2439: checkcast java/math/BigInteger
    //   2442: invokevirtual intValue : ()I
    //   2445: bipush #32
    //   2447: irem
    //   2448: invokestatic abs : (I)I
    //   2451: invokevirtual charAt : (I)C
    //   2454: getstatic burp/Zb9q.Zk : Ljava/lang/String;
    //   2457: getstatic burp/Zg4z.ZB : Ljava/lang/Object;
    //   2460: checkcast java/math/BigInteger
    //   2463: invokevirtual intValue : ()I
    //   2466: bipush #32
    //   2468: irem
    //   2469: invokestatic abs : (I)I
    //   2472: invokevirtual charAt : (I)C
    //   2475: if_icmple -> 2821
    //   2478: sipush #-27694
    //   2481: sipush #-32160
    //   2484: invokestatic a : (II)Ljava/lang/String;
    //   2487: iconst_1
    //   2488: ldc burp/Zep1
    //   2490: invokevirtual getClassLoader : ()Ljava/lang/ClassLoader;
    //   2493: invokestatic forName : (Ljava/lang/String;ZLjava/lang/ClassLoader;)Ljava/lang/Class;
    //   2496: invokevirtual getDeclaredFields : ()[Ljava/lang/reflect/Field;
    //   2499: astore #5
    //   2501: aload #5
    //   2503: arraylength
    //   2504: istore #6
    //   2506: iconst_0
    //   2507: istore #7
    //   2509: iload #7
    //   2511: iload #6
    //   2513: if_icmpge -> 2651
    //   2516: aload #5
    //   2518: iload #7
    //   2520: aaload
    //   2521: astore #8
    //   2523: aload #8
    //   2525: invokevirtual getModifiers : ()I
    //   2528: invokestatic isStatic : (I)Z
    //   2531: ifne -> 2541
    //   2534: goto -> 2644
    //   2537: invokestatic a : (Ljava/lang/Throwable;)Ljava/lang/Throwable;
    //   2540: athrow
    //   2541: aload #8
    //   2543: invokevirtual getType : ()Ljava/lang/Class;
    //   2546: astore #9
    //   2548: aload #9
    //   2550: ifnull -> 2631
    //   2553: aload #9
    //   2555: invokevirtual isPrimitive : ()Z
    //   2558: ifne -> 2631
    //   2561: goto -> 2568
    //   2564: invokestatic a : (Ljava/lang/Throwable;)Ljava/lang/Throwable;
    //   2567: athrow
    //   2568: aload #9
    //   2570: invokevirtual getPackage : ()Ljava/lang/Package;
    //   2573: ifnull -> 2631
    //   2576: goto -> 2583
    //   2579: invokestatic a : (Ljava/lang/Throwable;)Ljava/lang/Throwable;
    //   2582: athrow
    //   2583: aload #9
    //   2585: invokevirtual getPackage : ()Ljava/lang/Package;
    //   2588: invokevirtual getName : ()Ljava/lang/String;
    //   2591: ifnull -> 2631
    //   2594: goto -> 2601
    //   2597: invokestatic a : (Ljava/lang/Throwable;)Ljava/lang/Throwable;
    //   2600: athrow
    //   2601: aload #9
    //   2603: invokevirtual getPackage : ()Ljava/lang/Package;
    //   2606: invokevirtual getName : ()Ljava/lang/String;
    //   2609: sipush #-27710
    //   2612: sipush #4662
    //   2615: invokestatic a : (II)Ljava/lang/String;
    //   2618: invokevirtual startsWith : (Ljava/lang/String;)Z
    //   2621: ifne -> 2631
    //   2624: goto -> 2631
    //   2627: invokestatic a : (Ljava/lang/Throwable;)Ljava/lang/Throwable;
    //   2630: athrow
    //   2631: aload #8
    //   2633: iconst_1
    //   2634: invokevirtual setAccessible : (Z)V
    //   2637: aload #8
    //   2639: aconst_null
    //   2640: invokevirtual get : (Ljava/lang/Object;)Ljava/lang/Object;
    //   2643: pop
    //   2644: iinc #7, 1
    //   2647: iload_2
    //   2648: ifeq -> 2509
    //   2651: sipush #-27691
    //   2654: sipush #-4647
    //   2657: invokestatic a : (II)Ljava/lang/String;
    //   2660: invokestatic forName : (Ljava/lang/String;)Ljava/lang/Class;
    //   2663: invokevirtual getDeclaredMethods : ()[Ljava/lang/reflect/Method;
    //   2666: astore #5
    //   2668: aload #5
    //   2670: arraylength
    //   2671: istore #6
    //   2673: iconst_0
    //   2674: istore #7
    //   2676: iload #7
    //   2678: iload #6
    //   2680: if_icmpge -> 2817
    //   2683: aload #5
    //   2685: iload #7
    //   2687: aaload
    //   2688: astore #8
    //   2690: aload #8
    //   2692: invokevirtual getParameterTypes : ()[Ljava/lang/Class;
    //   2695: pop
    //   2696: aload #8
    //   2698: invokevirtual getModifiers : ()I
    //   2701: invokestatic isStatic : (I)Z
    //   2704: ifeq -> 2803
    //   2707: aload #8
    //   2709: invokevirtual getParameterTypes : ()[Ljava/lang/Class;
    //   2712: arraylength
    //   2713: iconst_2
    //   2714: if_icmpne -> 2803
    //   2717: goto -> 2724
    //   2720: invokestatic a : (Ljava/lang/Throwable;)Ljava/lang/Throwable;
    //   2723: athrow
    //   2724: aload #8
    //   2726: invokevirtual getReturnType : ()Ljava/lang/Class;
    //   2729: getstatic java/lang/Boolean.TYPE : Ljava/lang/Class;
    //   2732: if_acmpne -> 2803
    //   2735: goto -> 2742
    //   2738: invokestatic a : (Ljava/lang/Throwable;)Ljava/lang/Throwable;
    //   2741: athrow
    //   2742: aload #8
    //   2744: iconst_1
    //   2745: invokevirtual setAccessible : (Z)V
    //   2748: aload #8
    //   2750: aconst_null
    //   2751: iconst_2
    //   2752: anewarray java/lang/Object
    //   2755: dup
    //   2756: iconst_0
    //   2757: aload_0
    //   2758: aastore
    //   2759: dup
    //   2760: iconst_1
    //   2761: aload_1
    //   2762: ifnonnull -> 2780
    //   2765: goto -> 2772
    //   2768: invokestatic a : (Ljava/lang/Throwable;)Ljava/lang/Throwable;
    //   2771: athrow
    //   2772: aload_1
    //   2773: goto -> 2787
    //   2776: invokestatic a : (Ljava/lang/Throwable;)Ljava/lang/Throwable;
    //   2779: athrow
    //   2780: aload_1
    //   2781: checkcast [B
    //   2784: invokevirtual clone : ()Ljava/lang/Object;
    //   2787: aastore
    //   2788: invokevirtual invoke : (Ljava/lang/Object;[Ljava/lang/Object;)Ljava/lang/Object;
    //   2791: checkcast java/lang/Boolean
    //   2794: invokevirtual booleanValue : ()Z
    //   2797: istore #4
    //   2799: iload_2
    //   2800: ifeq -> 2817
    //   2803: iinc #7, 1
    //   2806: iload_2
    //   2807: ifeq -> 2676
    //   2810: goto -> 2817
    //   2813: invokestatic a : (Ljava/lang/Throwable;)Ljava/lang/Throwable;
    //   2816: athrow
    //   2817: iload_2
    //   2818: ifeq -> 3160
    //   2821: sipush #-27684
    //   2824: sipush #-28762
    //   2827: invokestatic a : (II)Ljava/lang/String;
    //   2830: iconst_1
    //   2831: ldc burp/Zdm
    //   2833: invokevirtual getClassLoader : ()Ljava/lang/ClassLoader;
    //   2836: invokestatic forName : (Ljava/lang/String;ZLjava/lang/ClassLoader;)Ljava/lang/Class;
    //   2839: invokevirtual getDeclaredFields : ()[Ljava/lang/reflect/Field;
    //   2842: astore #5
    //   2844: aload #5
    //   2846: arraylength
    //   2847: istore #6
    //   2849: iconst_0
    //   2850: istore #7
    //   2852: iload #7
    //   2854: iload #6
    //   2856: if_icmpge -> 2994
    //   2859: aload #5
    //   2861: iload #7
    //   2863: aaload
    //   2864: astore #8
    //   2866: aload #8
    //   2868: invokevirtual getModifiers : ()I
    //   2871: invokestatic isStatic : (I)Z
    //   2874: ifne -> 2884
    //   2877: goto -> 2987
    //   2880: invokestatic a : (Ljava/lang/Throwable;)Ljava/lang/Throwable;
    //   2883: athrow
    //   2884: aload #8
    //   2886: invokevirtual getType : ()Ljava/lang/Class;
    //   2889: astore #9
    //   2891: aload #9
    //   2893: ifnull -> 2974
    //   2896: aload #9
    //   2898: invokevirtual isPrimitive : ()Z
    //   2901: ifne -> 2974
    //   2904: goto -> 2911
    //   2907: invokestatic a : (Ljava/lang/Throwable;)Ljava/lang/Throwable;
    //   2910: athrow
    //   2911: aload #9
    //   2913: invokevirtual getPackage : ()Ljava/lang/Package;
    //   2916: ifnull -> 2974
    //   2919: goto -> 2926
    //   2922: invokestatic a : (Ljava/lang/Throwable;)Ljava/lang/Throwable;
    //   2925: athrow
    //   2926: aload #9
    //   2928: invokevirtual getPackage : ()Ljava/lang/Package;
    //   2931: invokevirtual getName : ()Ljava/lang/String;
    //   2934: ifnull -> 2974
    //   2937: goto -> 2944
    //   2940: invokestatic a : (Ljava/lang/Throwable;)Ljava/lang/Throwable;
    //   2943: athrow
    //   2944: aload #9
    //   2946: invokevirtual getPackage : ()Ljava/lang/Package;
    //   2949: invokevirtual getName : ()Ljava/lang/String;
    //   2952: sipush #-27710
    //   2955: sipush #4662
    //   2958: invokestatic a : (II)Ljava/lang/String;
    //   2961: invokevirtual startsWith : (Ljava/lang/String;)Z
    //   2964: ifne -> 2974
    //   2967: goto -> 2974
    //   2970: invokestatic a : (Ljava/lang/Throwable;)Ljava/lang/Throwable;
    //   2973: athrow
    //   2974: aload #8
    //   2976: iconst_1
    //   2977: invokevirtual setAccessible : (Z)V
    //   2980: aload #8
    //   2982: aconst_null
    //   2983: invokevirtual get : (Ljava/lang/Object;)Ljava/lang/Object;
    //   2986: pop
    //   2987: iinc #7, 1
    //   2990: iload_2
    //   2991: ifeq -> 2852
    //   2994: sipush #-27698
    //   2997: sipush #14661
    //   3000: invokestatic a : (II)Ljava/lang/String;
    //   3003: invokestatic forName : (Ljava/lang/String;)Ljava/lang/Class;
    //   3006: invokevirtual getDeclaredMethods : ()[Ljava/lang/reflect/Method;
    //   3009: astore #5
    //   3011: aload #5
    //   3013: arraylength
    //   3014: istore #6
    //   3016: iconst_0
    //   3017: istore #7
    //   3019: iload #7
    //   3021: iload #6
    //   3023: if_icmpge -> 3160
    //   3026: aload #5
    //   3028: iload #7
    //   3030: aaload
    //   3031: astore #8
    //   3033: aload #8
    //   3035: invokevirtual getParameterTypes : ()[Ljava/lang/Class;
    //   3038: pop
    //   3039: aload #8
    //   3041: invokevirtual getModifiers : ()I
    //   3044: invokestatic isStatic : (I)Z
    //   3047: ifeq -> 3146
    //   3050: aload #8
    //   3052: invokevirtual getParameterTypes : ()[Ljava/lang/Class;
    //   3055: arraylength
    //   3056: iconst_2
    //   3057: if_icmpne -> 3146
    //   3060: goto -> 3067
    //   3063: invokestatic a : (Ljava/lang/Throwable;)Ljava/lang/Throwable;
    //   3066: athrow
    //   3067: aload #8
    //   3069: invokevirtual getReturnType : ()Ljava/lang/Class;
    //   3072: getstatic java/lang/Boolean.TYPE : Ljava/lang/Class;
    //   3075: if_acmpne -> 3146
    //   3078: goto -> 3085
    //   3081: invokestatic a : (Ljava/lang/Throwable;)Ljava/lang/Throwable;
    //   3084: athrow
    //   3085: aload #8
    //   3087: iconst_1
    //   3088: invokevirtual setAccessible : (Z)V
    //   3091: aload #8
    //   3093: aconst_null
    //   3094: iconst_2
    //   3095: anewarray java/lang/Object
    //   3098: dup
    //   3099: iconst_0
    //   3100: aload_0
    //   3101: aastore
    //   3102: dup
    //   3103: iconst_1
    //   3104: aload_1
    //   3105: ifnonnull -> 3123
    //   3108: goto -> 3115
    //   3111: invokestatic a : (Ljava/lang/Throwable;)Ljava/lang/Throwable;
    //   3114: athrow
    //   3115: aload_1
    //   3116: goto -> 3130
    //   3119: invokestatic a : (Ljava/lang/Throwable;)Ljava/lang/Throwable;
    //   3122: athrow
    //   3123: aload_1
    //   3124: checkcast [B
    //   3127: invokevirtual clone : ()Ljava/lang/Object;
    //   3130: aastore
    //   3131: invokevirtual invoke : (Ljava/lang/Object;[Ljava/lang/Object;)Ljava/lang/Object;
    //   3134: checkcast java/lang/Boolean
    //   3137: invokevirtual booleanValue : ()Z
    //   3140: istore #4
    //   3142: iload_2
    //   3143: ifeq -> 3160
    //   3146: iinc #7, 1
    //   3149: iload_2
    //   3150: ifeq -> 3019
    //   3153: goto -> 3160
    //   3156: invokestatic a : (Ljava/lang/Throwable;)Ljava/lang/Throwable;
    //   3159: athrow
    //   3160: iload #4
    //   3162: ifeq -> 3168
    //   3165: iload #4
    //   3167: ireturn
    //   3168: getstatic burp/Zsn9.Zp : Ljava/lang/String;
    //   3171: getstatic burp/Zld5.ZX : Ljava/lang/Object;
    //   3174: checkcast java/math/BigInteger
    //   3177: invokevirtual intValue : ()I
    //   3180: bipush #32
    //   3182: irem
    //   3183: invokestatic abs : (I)I
    //   3186: invokevirtual charAt : (I)C
    //   3189: getstatic burp/Zeig.Zg : Ljava/lang/String;
    //   3192: getstatic burp/Zbnz.Zb : Ljava/lang/Object;
    //   3195: checkcast java/math/BigInteger
    //   3198: invokevirtual intValue : ()I
    //   3201: bipush #32
    //   3203: irem
    //   3204: invokestatic abs : (I)I
    //   3207: invokevirtual charAt : (I)C
    //   3210: if_icmple -> 3556
    //   3213: sipush #-27688
    //   3216: sipush #17990
    //   3219: invokestatic a : (II)Ljava/lang/String;
    //   3222: iconst_1
    //   3223: ldc burp/Zlzo
    //   3225: invokevirtual getClassLoader : ()Ljava/lang/ClassLoader;
    //   3228: invokestatic forName : (Ljava/lang/String;ZLjava/lang/ClassLoader;)Ljava/lang/Class;
    //   3231: invokevirtual getDeclaredFields : ()[Ljava/lang/reflect/Field;
    //   3234: astore #5
    //   3236: aload #5
    //   3238: arraylength
    //   3239: istore #6
    //   3241: iconst_0
    //   3242: istore #7
    //   3244: iload #7
    //   3246: iload #6
    //   3248: if_icmpge -> 3386
    //   3251: aload #5
    //   3253: iload #7
    //   3255: aaload
    //   3256: astore #8
    //   3258: aload #8
    //   3260: invokevirtual getModifiers : ()I
    //   3263: invokestatic isStatic : (I)Z
    //   3266: ifne -> 3276
    //   3269: goto -> 3379
    //   3272: invokestatic a : (Ljava/lang/Throwable;)Ljava/lang/Throwable;
    //   3275: athrow
    //   3276: aload #8
    //   3278: invokevirtual getType : ()Ljava/lang/Class;
    //   3281: astore #9
    //   3283: aload #9
    //   3285: ifnull -> 3366
    //   3288: aload #9
    //   3290: invokevirtual isPrimitive : ()Z
    //   3293: ifne -> 3366
    //   3296: goto -> 3303
    //   3299: invokestatic a : (Ljava/lang/Throwable;)Ljava/lang/Throwable;
    //   3302: athrow
    //   3303: aload #9
    //   3305: invokevirtual getPackage : ()Ljava/lang/Package;
    //   3308: ifnull -> 3366
    //   3311: goto -> 3318
    //   3314: invokestatic a : (Ljava/lang/Throwable;)Ljava/lang/Throwable;
    //   3317: athrow
    //   3318: aload #9
    //   3320: invokevirtual getPackage : ()Ljava/lang/Package;
    //   3323: invokevirtual getName : ()Ljava/lang/String;
    //   3326: ifnull -> 3366
    //   3329: goto -> 3336
    //   3332: invokestatic a : (Ljava/lang/Throwable;)Ljava/lang/Throwable;
    //   3335: athrow
    //   3336: aload #9
    //   3338: invokevirtual getPackage : ()Ljava/lang/Package;
    //   3341: invokevirtual getName : ()Ljava/lang/String;
    //   3344: sipush #-27710
    //   3347: sipush #4662
    //   3350: invokestatic a : (II)Ljava/lang/String;
    //   3353: invokevirtual startsWith : (Ljava/lang/String;)Z
    //   3356: ifne -> 3366
    //   3359: goto -> 3366
    //   3362: invokestatic a : (Ljava/lang/Throwable;)Ljava/lang/Throwable;
    //   3365: athrow
    //   3366: aload #8
    //   3368: iconst_1
    //   3369: invokevirtual setAccessible : (Z)V
    //   3372: aload #8
    //   3374: aconst_null
    //   3375: invokevirtual get : (Ljava/lang/Object;)Ljava/lang/Object;
    //   3378: pop
    //   3379: iinc #7, 1
    //   3382: iload_2
    //   3383: ifeq -> 3244
    //   3386: sipush #-27699
    //   3389: sipush #-11395
    //   3392: invokestatic a : (II)Ljava/lang/String;
    //   3395: invokestatic forName : (Ljava/lang/String;)Ljava/lang/Class;
    //   3398: invokevirtual getDeclaredMethods : ()[Ljava/lang/reflect/Method;
    //   3401: astore #5
    //   3403: aload #5
    //   3405: arraylength
    //   3406: istore #6
    //   3408: iconst_0
    //   3409: istore #7
    //   3411: iload #7
    //   3413: iload #6
    //   3415: if_icmpge -> 3552
    //   3418: aload #5
    //   3420: iload #7
    //   3422: aaload
    //   3423: astore #8
    //   3425: aload #8
    //   3427: invokevirtual getParameterTypes : ()[Ljava/lang/Class;
    //   3430: pop
    //   3431: aload #8
    //   3433: invokevirtual getModifiers : ()I
    //   3436: invokestatic isStatic : (I)Z
    //   3439: ifeq -> 3538
    //   3442: aload #8
    //   3444: invokevirtual getParameterTypes : ()[Ljava/lang/Class;
    //   3447: arraylength
    //   3448: iconst_2
    //   3449: if_icmpne -> 3538
    //   3452: goto -> 3459
    //   3455: invokestatic a : (Ljava/lang/Throwable;)Ljava/lang/Throwable;
    //   3458: athrow
    //   3459: aload #8
    //   3461: invokevirtual getReturnType : ()Ljava/lang/Class;
    //   3464: getstatic java/lang/Boolean.TYPE : Ljava/lang/Class;
    //   3467: if_acmpne -> 3538
    //   3470: goto -> 3477
    //   3473: invokestatic a : (Ljava/lang/Throwable;)Ljava/lang/Throwable;
    //   3476: athrow
    //   3477: aload #8
    //   3479: iconst_1
    //   3480: invokevirtual setAccessible : (Z)V
    //   3483: aload #8
    //   3485: aconst_null
    //   3486: iconst_2
    //   3487: anewarray java/lang/Object
    //   3490: dup
    //   3491: iconst_0
    //   3492: aload_0
    //   3493: aastore
    //   3494: dup
    //   3495: iconst_1
    //   3496: aload_1
    //   3497: ifnonnull -> 3515
    //   3500: goto -> 3507
    //   3503: invokestatic a : (Ljava/lang/Throwable;)Ljava/lang/Throwable;
    //   3506: athrow
    //   3507: aload_1
    //   3508: goto -> 3522
    //   3511: invokestatic a : (Ljava/lang/Throwable;)Ljava/lang/Throwable;
    //   3514: athrow
    //   3515: aload_1
    //   3516: checkcast [B
    //   3519: invokevirtual clone : ()Ljava/lang/Object;
    //   3522: aastore
    //   3523: invokevirtual invoke : (Ljava/lang/Object;[Ljava/lang/Object;)Ljava/lang/Object;
    //   3526: checkcast java/lang/Boolean
    //   3529: invokevirtual booleanValue : ()Z
    //   3532: istore #4
    //   3534: iload_2
    //   3535: ifeq -> 3552
    //   3538: iinc #7, 1
    //   3541: iload_2
    //   3542: ifeq -> 3411
    //   3545: goto -> 3552
    //   3548: invokestatic a : (Ljava/lang/Throwable;)Ljava/lang/Throwable;
    //   3551: athrow
    //   3552: iload_2
    //   3553: ifeq -> 3895
    //   3556: sipush #-27690
    //   3559: sipush #-22909
    //   3562: invokestatic a : (II)Ljava/lang/String;
    //   3565: iconst_1
    //   3566: ldc burp/Zgl2
    //   3568: invokevirtual getClassLoader : ()Ljava/lang/ClassLoader;
    //   3571: invokestatic forName : (Ljava/lang/String;ZLjava/lang/ClassLoader;)Ljava/lang/Class;
    //   3574: invokevirtual getDeclaredFields : ()[Ljava/lang/reflect/Field;
    //   3577: astore #5
    //   3579: aload #5
    //   3581: arraylength
    //   3582: istore #6
    //   3584: iconst_0
    //   3585: istore #7
    //   3587: iload #7
    //   3589: iload #6
    //   3591: if_icmpge -> 3729
    //   3594: aload #5
    //   3596: iload #7
    //   3598: aaload
    //   3599: astore #8
    //   3601: aload #8
    //   3603: invokevirtual getModifiers : ()I
    //   3606: invokestatic isStatic : (I)Z
    //   3609: ifne -> 3619
    //   3612: goto -> 3722
    //   3615: invokestatic a : (Ljava/lang/Throwable;)Ljava/lang/Throwable;
    //   3618: athrow
    //   3619: aload #8
    //   3621: invokevirtual getType : ()Ljava/lang/Class;
    //   3624: astore #9
    //   3626: aload #9
    //   3628: ifnull -> 3709
    //   3631: aload #9
    //   3633: invokevirtual isPrimitive : ()Z
    //   3636: ifne -> 3709
    //   3639: goto -> 3646
    //   3642: invokestatic a : (Ljava/lang/Throwable;)Ljava/lang/Throwable;
    //   3645: athrow
    //   3646: aload #9
    //   3648: invokevirtual getPackage : ()Ljava/lang/Package;
    //   3651: ifnull -> 3709
    //   3654: goto -> 3661
    //   3657: invokestatic a : (Ljava/lang/Throwable;)Ljava/lang/Throwable;
    //   3660: athrow
    //   3661: aload #9
    //   3663: invokevirtual getPackage : ()Ljava/lang/Package;
    //   3666: invokevirtual getName : ()Ljava/lang/String;
    //   3669: ifnull -> 3709
    //   3672: goto -> 3679
    //   3675: invokestatic a : (Ljava/lang/Throwable;)Ljava/lang/Throwable;
    //   3678: athrow
    //   3679: aload #9
    //   3681: invokevirtual getPackage : ()Ljava/lang/Package;
    //   3684: invokevirtual getName : ()Ljava/lang/String;
    //   3687: sipush #-27710
    //   3690: sipush #4662
    //   3693: invokestatic a : (II)Ljava/lang/String;
    //   3696: invokevirtual startsWith : (Ljava/lang/String;)Z
    //   3699: ifne -> 3709
    //   3702: goto -> 3709
    //   3705: invokestatic a : (Ljava/lang/Throwable;)Ljava/lang/Throwable;
    //   3708: athrow
    //   3709: aload #8
    //   3711: iconst_1
    //   3712: invokevirtual setAccessible : (Z)V
    //   3715: aload #8
    //   3717: aconst_null
    //   3718: invokevirtual get : (Ljava/lang/Object;)Ljava/lang/Object;
    //   3721: pop
    //   3722: iinc #7, 1
    //   3725: iload_2
    //   3726: ifeq -> 3587
    //   3729: sipush #-27702
    //   3732: sipush #32309
    //   3735: invokestatic a : (II)Ljava/lang/String;
    //   3738: invokestatic forName : (Ljava/lang/String;)Ljava/lang/Class;
    //   3741: invokevirtual getDeclaredMethods : ()[Ljava/lang/reflect/Method;
    //   3744: astore #5
    //   3746: aload #5
    //   3748: arraylength
    //   3749: istore #6
    //   3751: iconst_0
    //   3752: istore #7
    //   3754: iload #7
    //   3756: iload #6
    //   3758: if_icmpge -> 3895
    //   3761: aload #5
    //   3763: iload #7
    //   3765: aaload
    //   3766: astore #8
    //   3768: aload #8
    //   3770: invokevirtual getParameterTypes : ()[Ljava/lang/Class;
    //   3773: pop
    //   3774: aload #8
    //   3776: invokevirtual getModifiers : ()I
    //   3779: invokestatic isStatic : (I)Z
    //   3782: ifeq -> 3881
    //   3785: aload #8
    //   3787: invokevirtual getParameterTypes : ()[Ljava/lang/Class;
    //   3790: arraylength
    //   3791: iconst_2
    //   3792: if_icmpne -> 3881
    //   3795: goto -> 3802
    //   3798: invokestatic a : (Ljava/lang/Throwable;)Ljava/lang/Throwable;
    //   3801: athrow
    //   3802: aload #8
    //   3804: invokevirtual getReturnType : ()Ljava/lang/Class;
    //   3807: getstatic java/lang/Boolean.TYPE : Ljava/lang/Class;
    //   3810: if_acmpne -> 3881
    //   3813: goto -> 3820
    //   3816: invokestatic a : (Ljava/lang/Throwable;)Ljava/lang/Throwable;
    //   3819: athrow
    //   3820: aload #8
    //   3822: iconst_1
    //   3823: invokevirtual setAccessible : (Z)V
    //   3826: aload #8
    //   3828: aconst_null
    //   3829: iconst_2
    //   3830: anewarray java/lang/Object
    //   3833: dup
    //   3834: iconst_0
    //   3835: aload_0
    //   3836: aastore
    //   3837: dup
    //   3838: iconst_1
    //   3839: aload_1
    //   3840: ifnonnull -> 3858
    //   3843: goto -> 3850
    //   3846: invokestatic a : (Ljava/lang/Throwable;)Ljava/lang/Throwable;
    //   3849: athrow
    //   3850: aload_1
    //   3851: goto -> 3865
    //   3854: invokestatic a : (Ljava/lang/Throwable;)Ljava/lang/Throwable;
    //   3857: athrow
    //   3858: aload_1
    //   3859: checkcast [B
    //   3862: invokevirtual clone : ()Ljava/lang/Object;
    //   3865: aastore
    //   3866: invokevirtual invoke : (Ljava/lang/Object;[Ljava/lang/Object;)Ljava/lang/Object;
    //   3869: checkcast java/lang/Boolean
    //   3872: invokevirtual booleanValue : ()Z
    //   3875: istore #4
    //   3877: iload_2
    //   3878: ifeq -> 3895
    //   3881: iinc #7, 1
    //   3884: iload_2
    //   3885: ifeq -> 3754
    //   3888: goto -> 3895
    //   3891: invokestatic a : (Ljava/lang/Throwable;)Ljava/lang/Throwable;
    //   3894: athrow
    //   3895: iload #4
    //   3897: ifeq -> 3903
    //   3900: iload #4
    //   3902: ireturn
    //   3903: getstatic burp/Zg1l.Zl : Ljava/lang/String;
    //   3906: getstatic burp/Zxn9.ZN : Ljava/lang/Object;
    //   3909: checkcast java/math/BigInteger
    //   3912: invokevirtual intValue : ()I
    //   3915: bipush #32
    //   3917: irem
    //   3918: invokestatic abs : (I)I
    //   3921: invokevirtual charAt : (I)C
    //   3924: getstatic burp/Ztwp.ZK : Ljava/lang/String;
    //   3927: getstatic burp/Zxy6.Zd : Ljava/lang/Object;
    //   3930: checkcast java/math/BigInteger
    //   3933: invokevirtual intValue : ()I
    //   3936: bipush #32
    //   3938: irem
    //   3939: invokestatic abs : (I)I
    //   3942: invokevirtual charAt : (I)C
    //   3945: if_icmpgt -> 4291
    //   3948: sipush #-27687
    //   3951: sipush #30981
    //   3954: invokestatic a : (II)Ljava/lang/String;
    //   3957: iconst_1
    //   3958: ldc burp/Zxti
    //   3960: invokevirtual getClassLoader : ()Ljava/lang/ClassLoader;
    //   3963: invokestatic forName : (Ljava/lang/String;ZLjava/lang/ClassLoader;)Ljava/lang/Class;
    //   3966: invokevirtual getDeclaredFields : ()[Ljava/lang/reflect/Field;
    //   3969: astore #5
    //   3971: aload #5
    //   3973: arraylength
    //   3974: istore #6
    //   3976: iconst_0
    //   3977: istore #7
    //   3979: iload #7
    //   3981: iload #6
    //   3983: if_icmpge -> 4121
    //   3986: aload #5
    //   3988: iload #7
    //   3990: aaload
    //   3991: astore #8
    //   3993: aload #8
    //   3995: invokevirtual getModifiers : ()I
    //   3998: invokestatic isStatic : (I)Z
    //   4001: ifne -> 4011
    //   4004: goto -> 4114
    //   4007: invokestatic a : (Ljava/lang/Throwable;)Ljava/lang/Throwable;
    //   4010: athrow
    //   4011: aload #8
    //   4013: invokevirtual getType : ()Ljava/lang/Class;
    //   4016: astore #9
    //   4018: aload #9
    //   4020: ifnull -> 4101
    //   4023: aload #9
    //   4025: invokevirtual isPrimitive : ()Z
    //   4028: ifne -> 4101
    //   4031: goto -> 4038
    //   4034: invokestatic a : (Ljava/lang/Throwable;)Ljava/lang/Throwable;
    //   4037: athrow
    //   4038: aload #9
    //   4040: invokevirtual getPackage : ()Ljava/lang/Package;
    //   4043: ifnull -> 4101
    //   4046: goto -> 4053
    //   4049: invokestatic a : (Ljava/lang/Throwable;)Ljava/lang/Throwable;
    //   4052: athrow
    //   4053: aload #9
    //   4055: invokevirtual getPackage : ()Ljava/lang/Package;
    //   4058: invokevirtual getName : ()Ljava/lang/String;
    //   4061: ifnull -> 4101
    //   4064: goto -> 4071
    //   4067: invokestatic a : (Ljava/lang/Throwable;)Ljava/lang/Throwable;
    //   4070: athrow
    //   4071: aload #9
    //   4073: invokevirtual getPackage : ()Ljava/lang/Package;
    //   4076: invokevirtual getName : ()Ljava/lang/String;
    //   4079: sipush #-27710
    //   4082: sipush #4662
    //   4085: invokestatic a : (II)Ljava/lang/String;
    //   4088: invokevirtual startsWith : (Ljava/lang/String;)Z
    //   4091: ifne -> 4101
    //   4094: goto -> 4101
    //   4097: invokestatic a : (Ljava/lang/Throwable;)Ljava/lang/Throwable;
    //   4100: athrow
    //   4101: aload #8
    //   4103: iconst_1
    //   4104: invokevirtual setAccessible : (Z)V
    //   4107: aload #8
    //   4109: aconst_null
    //   4110: invokevirtual get : (Ljava/lang/Object;)Ljava/lang/Object;
    //   4113: pop
    //   4114: iinc #7, 1
    //   4117: iload_2
    //   4118: ifeq -> 3979
    //   4121: sipush #-27709
    //   4124: sipush #-8881
    //   4127: invokestatic a : (II)Ljava/lang/String;
    //   4130: invokestatic forName : (Ljava/lang/String;)Ljava/lang/Class;
    //   4133: invokevirtual getDeclaredMethods : ()[Ljava/lang/reflect/Method;
    //   4136: astore #5
    //   4138: aload #5
    //   4140: arraylength
    //   4141: istore #6
    //   4143: iconst_0
    //   4144: istore #7
    //   4146: iload #7
    //   4148: iload #6
    //   4150: if_icmpge -> 4287
    //   4153: aload #5
    //   4155: iload #7
    //   4157: aaload
    //   4158: astore #8
    //   4160: aload #8
    //   4162: invokevirtual getParameterTypes : ()[Ljava/lang/Class;
    //   4165: pop
    //   4166: aload #8
    //   4168: invokevirtual getModifiers : ()I
    //   4171: invokestatic isStatic : (I)Z
    //   4174: ifeq -> 4273
    //   4177: aload #8
    //   4179: invokevirtual getParameterTypes : ()[Ljava/lang/Class;
    //   4182: arraylength
    //   4183: iconst_2
    //   4184: if_icmpne -> 4273
    //   4187: goto -> 4194
    //   4190: invokestatic a : (Ljava/lang/Throwable;)Ljava/lang/Throwable;
    //   4193: athrow
    //   4194: aload #8
    //   4196: invokevirtual getReturnType : ()Ljava/lang/Class;
    //   4199: getstatic java/lang/Boolean.TYPE : Ljava/lang/Class;
    //   4202: if_acmpne -> 4273
    //   4205: goto -> 4212
    //   4208: invokestatic a : (Ljava/lang/Throwable;)Ljava/lang/Throwable;
    //   4211: athrow
    //   4212: aload #8
    //   4214: iconst_1
    //   4215: invokevirtual setAccessible : (Z)V
    //   4218: aload #8
    //   4220: aconst_null
    //   4221: iconst_2
    //   4222: anewarray java/lang/Object
    //   4225: dup
    //   4226: iconst_0
    //   4227: aload_0
    //   4228: aastore
    //   4229: dup
    //   4230: iconst_1
    //   4231: aload_1
    //   4232: ifnonnull -> 4250
    //   4235: goto -> 4242
    //   4238: invokestatic a : (Ljava/lang/Throwable;)Ljava/lang/Throwable;
    //   4241: athrow
    //   4242: aload_1
    //   4243: goto -> 4257
    //   4246: invokestatic a : (Ljava/lang/Throwable;)Ljava/lang/Throwable;
    //   4249: athrow
    //   4250: aload_1
    //   4251: checkcast [B
    //   4254: invokevirtual clone : ()Ljava/lang/Object;
    //   4257: aastore
    //   4258: invokevirtual invoke : (Ljava/lang/Object;[Ljava/lang/Object;)Ljava/lang/Object;
    //   4261: checkcast java/lang/Boolean
    //   4264: invokevirtual booleanValue : ()Z
    //   4267: istore #4
    //   4269: iload_2
    //   4270: ifeq -> 4287
    //   4273: iinc #7, 1
    //   4276: iload_2
    //   4277: ifeq -> 4146
    //   4280: goto -> 4287
    //   4283: invokestatic a : (Ljava/lang/Throwable;)Ljava/lang/Throwable;
    //   4286: athrow
    //   4287: iload_2
    //   4288: ifeq -> 4630
    //   4291: sipush #-27681
    //   4294: sipush #-25034
    //   4297: invokestatic a : (II)Ljava/lang/String;
    //   4300: iconst_1
    //   4301: ldc burp/Zl_9
    //   4303: invokevirtual getClassLoader : ()Ljava/lang/ClassLoader;
    //   4306: invokestatic forName : (Ljava/lang/String;ZLjava/lang/ClassLoader;)Ljava/lang/Class;
    //   4309: invokevirtual getDeclaredFields : ()[Ljava/lang/reflect/Field;
    //   4312: astore #5
    //   4314: aload #5
    //   4316: arraylength
    //   4317: istore #6
    //   4319: iconst_0
    //   4320: istore #7
    //   4322: iload #7
    //   4324: iload #6
    //   4326: if_icmpge -> 4464
    //   4329: aload #5
    //   4331: iload #7
    //   4333: aaload
    //   4334: astore #8
    //   4336: aload #8
    //   4338: invokevirtual getModifiers : ()I
    //   4341: invokestatic isStatic : (I)Z
    //   4344: ifne -> 4354
    //   4347: goto -> 4457
    //   4350: invokestatic a : (Ljava/lang/Throwable;)Ljava/lang/Throwable;
    //   4353: athrow
    //   4354: aload #8
    //   4356: invokevirtual getType : ()Ljava/lang/Class;
    //   4359: astore #9
    //   4361: aload #9
    //   4363: ifnull -> 4444
    //   4366: aload #9
    //   4368: invokevirtual isPrimitive : ()Z
    //   4371: ifne -> 4444
    //   4374: goto -> 4381
    //   4377: invokestatic a : (Ljava/lang/Throwable;)Ljava/lang/Throwable;
    //   4380: athrow
    //   4381: aload #9
    //   4383: invokevirtual getPackage : ()Ljava/lang/Package;
    //   4386: ifnull -> 4444
    //   4389: goto -> 4396
    //   4392: invokestatic a : (Ljava/lang/Throwable;)Ljava/lang/Throwable;
    //   4395: athrow
    //   4396: aload #9
    //   4398: invokevirtual getPackage : ()Ljava/lang/Package;
    //   4401: invokevirtual getName : ()Ljava/lang/String;
    //   4404: ifnull -> 4444
    //   4407: goto -> 4414
    //   4410: invokestatic a : (Ljava/lang/Throwable;)Ljava/lang/Throwable;
    //   4413: athrow
    //   4414: aload #9
    //   4416: invokevirtual getPackage : ()Ljava/lang/Package;
    //   4419: invokevirtual getName : ()Ljava/lang/String;
    //   4422: sipush #-27710
    //   4425: sipush #4662
    //   4428: invokestatic a : (II)Ljava/lang/String;
    //   4431: invokevirtual startsWith : (Ljava/lang/String;)Z
    //   4434: ifne -> 4444
    //   4437: goto -> 4444
    //   4440: invokestatic a : (Ljava/lang/Throwable;)Ljava/lang/Throwable;
    //   4443: athrow
    //   4444: aload #8
    //   4446: iconst_1
    //   4447: invokevirtual setAccessible : (Z)V
    //   4450: aload #8
    //   4452: aconst_null
    //   4453: invokevirtual get : (Ljava/lang/Object;)Ljava/lang/Object;
    //   4456: pop
    //   4457: iinc #7, 1
    //   4460: iload_2
    //   4461: ifeq -> 4322
    //   4464: sipush #-27697
    //   4467: sipush #30963
    //   4470: invokestatic a : (II)Ljava/lang/String;
    //   4473: invokestatic forName : (Ljava/lang/String;)Ljava/lang/Class;
    //   4476: invokevirtual getDeclaredMethods : ()[Ljava/lang/reflect/Method;
    //   4479: astore #5
    //   4481: aload #5
    //   4483: arraylength
    //   4484: istore #6
    //   4486: iconst_0
    //   4487: istore #7
    //   4489: iload #7
    //   4491: iload #6
    //   4493: if_icmpge -> 4630
    //   4496: aload #5
    //   4498: iload #7
    //   4500: aaload
    //   4501: astore #8
    //   4503: aload #8
    //   4505: invokevirtual getParameterTypes : ()[Ljava/lang/Class;
    //   4508: pop
    //   4509: aload #8
    //   4511: invokevirtual getModifiers : ()I
    //   4514: invokestatic isStatic : (I)Z
    //   4517: ifeq -> 4616
    //   4520: aload #8
    //   4522: invokevirtual getParameterTypes : ()[Ljava/lang/Class;
    //   4525: arraylength
    //   4526: iconst_2
    //   4527: if_icmpne -> 4616
    //   4530: goto -> 4537
    //   4533: invokestatic a : (Ljava/lang/Throwable;)Ljava/lang/Throwable;
    //   4536: athrow
    //   4537: aload #8
    //   4539: invokevirtual getReturnType : ()Ljava/lang/Class;
    //   4542: getstatic java/lang/Boolean.TYPE : Ljava/lang/Class;
    //   4545: if_acmpne -> 4616
    //   4548: goto -> 4555
    //   4551: invokestatic a : (Ljava/lang/Throwable;)Ljava/lang/Throwable;
    //   4554: athrow
    //   4555: aload #8
    //   4557: iconst_1
    //   4558: invokevirtual setAccessible : (Z)V
    //   4561: aload #8
    //   4563: aconst_null
    //   4564: iconst_2
    //   4565: anewarray java/lang/Object
    //   4568: dup
    //   4569: iconst_0
    //   4570: aload_0
    //   4571: aastore
    //   4572: dup
    //   4573: iconst_1
    //   4574: aload_1
    //   4575: ifnonnull -> 4593
    //   4578: goto -> 4585
    //   4581: invokestatic a : (Ljava/lang/Throwable;)Ljava/lang/Throwable;
    //   4584: athrow
    //   4585: aload_1
    //   4586: goto -> 4600
    //   4589: invokestatic a : (Ljava/lang/Throwable;)Ljava/lang/Throwable;
    //   4592: athrow
    //   4593: aload_1
    //   4594: checkcast [B
    //   4597: invokevirtual clone : ()Ljava/lang/Object;
    //   4600: aastore
    //   4601: invokevirtual invoke : (Ljava/lang/Object;[Ljava/lang/Object;)Ljava/lang/Object;
    //   4604: checkcast java/lang/Boolean
    //   4607: invokevirtual booleanValue : ()Z
    //   4610: istore #4
    //   4612: iload_2
    //   4613: ifeq -> 4630
    //   4616: iinc #7, 1
    //   4619: iload_2
    //   4620: ifeq -> 4489
    //   4623: goto -> 4630
    //   4626: invokestatic a : (Ljava/lang/Throwable;)Ljava/lang/Throwable;
    //   4629: athrow
    //   4630: iload #4
    //   4632: ireturn
    //   4633: astore_3
    //   4634: new java/lang/Exception
    //   4637: dup
    //   4638: aload_3
    //   4639: invokevirtual getMessage : ()Ljava/lang/String;
    //   4642: invokespecial <init> : (Ljava/lang/String;)V
    //   4645: athrow
    // Exception table:
    //   from	to	target	type
    //   4	2432	4633	java/lang/Throwable
    //   22	198	201	java/lang/Throwable
    //   168	235	238	java/lang/Throwable
    //   205	272	275	java/lang/Throwable
    //   242	309	312	java/lang/Throwable
    //   279	346	349	java/lang/Throwable
    //   316	383	386	java/lang/Throwable
    //   353	420	423	java/lang/Throwable
    //   390	457	460	java/lang/Throwable
    //   427	494	497	java/lang/Throwable
    //   464	531	534	java/lang/Throwable
    //   501	568	571	java/lang/Throwable
    //   538	605	608	java/lang/Throwable
    //   575	642	645	java/lang/Throwable
    //   612	679	682	java/lang/Throwable
    //   649	716	719	java/lang/Throwable
    //   686	753	756	java/lang/Throwable
    //   723	790	793	java/lang/Throwable
    //   760	827	830	java/lang/Throwable
    //   797	864	867	java/lang/Throwable
    //   834	901	904	java/lang/Throwable
    //   871	938	941	java/lang/Throwable
    //   908	975	978	java/lang/Throwable
    //   945	1012	1015	java/lang/Throwable
    //   982	1049	1052	java/lang/Throwable
    //   1019	1086	1089	java/lang/Throwable
    //   1056	1123	1126	java/lang/Throwable
    //   1093	1160	1163	java/lang/Throwable
    //   1130	1197	1200	java/lang/Throwable
    //   1167	1234	1237	java/lang/Throwable
    //   1204	1271	1274	java/lang/Throwable
    //   1241	1308	1311	java/lang/Throwable
    //   1278	1341	1344	java/lang/Throwable
    //   1407	1421	1421	java/lang/Throwable
    //   1432	1445	1448	java/lang/Throwable
    //   1437	1460	1463	java/lang/Throwable
    //   1452	1478	1481	java/lang/Throwable
    //   1467	1508	1511	java/lang/Throwable
    //   1574	1601	1604	java/lang/Throwable
    //   1591	1622	1625	java/lang/Throwable
    //   1608	1652	1655	java/lang/Throwable
    //   1629	1663	1663	java/lang/Throwable
    //   1674	1690	1693	java/lang/Throwable
    //   1790	1804	1804	java/lang/Throwable
    //   1815	1828	1831	java/lang/Throwable
    //   1820	1843	1846	java/lang/Throwable
    //   1835	1861	1864	java/lang/Throwable
    //   1850	1891	1894	java/lang/Throwable
    //   1957	1984	1987	java/lang/Throwable
    //   1974	2002	2005	java/lang/Throwable
    //   1991	2032	2035	java/lang/Throwable
    //   2009	2043	2043	java/lang/Throwable
    //   2066	2077	2080	java/lang/Throwable
    //   2131	2145	2145	java/lang/Throwable
    //   2156	2169	2172	java/lang/Throwable
    //   2161	2184	2187	java/lang/Throwable
    //   2176	2202	2205	java/lang/Throwable
    //   2191	2232	2235	java/lang/Throwable
    //   2298	2325	2328	java/lang/Throwable
    //   2315	2343	2346	java/lang/Throwable
    //   2332	2373	2376	java/lang/Throwable
    //   2350	2384	2384	java/lang/Throwable
    //   2407	2418	2421	java/lang/Throwable
    //   2433	3167	4633	java/lang/Throwable
    //   2523	2537	2537	java/lang/Throwable
    //   2548	2561	2564	java/lang/Throwable
    //   2553	2576	2579	java/lang/Throwable
    //   2568	2594	2597	java/lang/Throwable
    //   2583	2624	2627	java/lang/Throwable
    //   2690	2717	2720	java/lang/Throwable
    //   2707	2735	2738	java/lang/Throwable
    //   2724	2765	2768	java/lang/Throwable
    //   2742	2776	2776	java/lang/Throwable
    //   2799	2810	2813	java/lang/Throwable
    //   2866	2880	2880	java/lang/Throwable
    //   2891	2904	2907	java/lang/Throwable
    //   2896	2919	2922	java/lang/Throwable
    //   2911	2937	2940	java/lang/Throwable
    //   2926	2967	2970	java/lang/Throwable
    //   3033	3060	3063	java/lang/Throwable
    //   3050	3078	3081	java/lang/Throwable
    //   3067	3108	3111	java/lang/Throwable
    //   3085	3119	3119	java/lang/Throwable
    //   3142	3153	3156	java/lang/Throwable
    //   3168	3902	4633	java/lang/Throwable
    //   3258	3272	3272	java/lang/Throwable
    //   3283	3296	3299	java/lang/Throwable
    //   3288	3311	3314	java/lang/Throwable
    //   3303	3329	3332	java/lang/Throwable
    //   3318	3359	3362	java/lang/Throwable
    //   3425	3452	3455	java/lang/Throwable
    //   3442	3470	3473	java/lang/Throwable
    //   3459	3500	3503	java/lang/Throwable
    //   3477	3511	3511	java/lang/Throwable
    //   3534	3545	3548	java/lang/Throwable
    //   3601	3615	3615	java/lang/Throwable
    //   3626	3639	3642	java/lang/Throwable
    //   3631	3654	3657	java/lang/Throwable
    //   3646	3672	3675	java/lang/Throwable
    //   3661	3702	3705	java/lang/Throwable
    //   3768	3795	3798	java/lang/Throwable
    //   3785	3813	3816	java/lang/Throwable
    //   3802	3843	3846	java/lang/Throwable
    //   3820	3854	3854	java/lang/Throwable
    //   3877	3888	3891	java/lang/Throwable
    //   3903	4632	4633	java/lang/Throwable
    //   3993	4007	4007	java/lang/Throwable
    //   4018	4031	4034	java/lang/Throwable
    //   4023	4046	4049	java/lang/Throwable
    //   4038	4064	4067	java/lang/Throwable
    //   4053	4094	4097	java/lang/Throwable
    //   4160	4187	4190	java/lang/Throwable
    //   4177	4205	4208	java/lang/Throwable
    //   4194	4235	4238	java/lang/Throwable
    //   4212	4246	4246	java/lang/Throwable
    //   4269	4280	4283	java/lang/Throwable
    //   4336	4350	4350	java/lang/Throwable
    //   4361	4374	4377	java/lang/Throwable
    //   4366	4389	4392	java/lang/Throwable
    //   4381	4407	4410	java/lang/Throwable
    //   4396	4437	4440	java/lang/Throwable
    //   4503	4530	4533	java/lang/Throwable
    //   4520	4548	4551	java/lang/Throwable
    //   4537	4578	4581	java/lang/Throwable
    //   4555	4589	4589	java/lang/Throwable
    //   4612	4623	4626	java/lang/Throwable
  }
  
  static void Zd(Object paramObject) {
    Ze2k.ZY = a(-27701, -10554);
    Ze2k.ZK = new BigInteger(a(-27686, -18859));
    boolean bool = Zt2e.ZN();
    try {
      try {
        if (Zlg2.ZL.charAt(Math.abs(((BigInteger)Zl7x.Za).intValue() % 32)) <= Zkf6.ZO.charAt(Math.abs(((BigInteger)Zzgb.ZG).intValue() % 32))) {
          try {
            Zry1.ZZ(Class.forName(a(-27682, -5945)));
            if (!bool)
              Zefm.ZP(Class.forName(a(-27696, -6771))); 
          } catch (Throwable throwable) {
            throw a(null);
          } 
          return;
        } 
      } catch (Throwable throwable) {
        throw a(null);
      } 
      Zefm.ZP(Class.forName(a(-27696, -6771)));
    } catch (Throwable throwable) {}
  }
  
  static {
    // Byte code:
    //   0: bipush #26
    //   2: anewarray java/lang/String
    //   5: astore #5
    //   7: iconst_0
    //   8: istore_3
    //   9: ldc 'kmQ!tF<e\\rmy=(|i \\n\\n@{bBky\]*\\t4Mn+A\\tE'\\tF/y\\f}\\t2Ld\\t\\rS\\tigK8d\\t5r\\tv:NDd'`*MfHDme(9)2WF^:c\\nm*F]eFWW'Q5b*[aGhc 8\\t?aZ\\t7y&Ai!\\tvzv\\tl /WM\\t\\rr@Z@2\\t{\\r%p\\t>), TwZ}=<cii/ARY*mEH\\t\\fzBJ\\t>WeG\\t\\fbEL\\tXCG?'`\\t3,xQf'
    //   11: dup
    //   12: astore_2
    //   13: invokevirtual length : ()I
    //   16: istore #4
    //   18: bipush #77
    //   20: istore_1
    //   21: iconst_m1
    //   22: istore_0
    //   23: bipush #26
    //   25: iinc #0, 1
    //   28: aload_2
    //   29: iload_0
    //   30: dup
    //   31: iload_1
    //   32: iadd
    //   33: invokevirtual substring : (II)Ljava/lang/String;
    //   36: iconst_m1
    //   37: goto -> 142
    //   40: aload #5
    //   42: swap
    //   43: iload_3
    //   44: iinc #3, 1
    //   47: swap
    //   48: aastore
    //   49: iload_0
    //   50: iload_1
    //   51: iadd
    //   52: dup
    //   53: istore_0
    //   54: iload #4
    //   56: if_icmpge -> 68
    //   59: aload_2
    //   60: iload_0
    //   61: invokevirtual charAt : (I)C
    //   64: istore_1
    //   65: goto -> 23
    //   68: ldc '%#m\\tn5MO'
    //   70: dup
    //   71: astore_2
    //   72: invokevirtual length : ()I
    //   75: istore #4
    //   77: iconst_4
    //   78: istore_1
    //   79: iconst_m1
    //   80: istore_0
    //   81: bipush #26
    //   83: iinc #0, 1
    //   86: aload_2
    //   87: iload_0
    //   88: dup
    //   89: iload_1
    //   90: iadd
    //   91: invokevirtual substring : (II)Ljava/lang/String;
    //   94: iconst_0
    //   95: goto -> 142
    //   98: aload #5
    //   100: swap
    //   101: iload_3
    //   102: iinc #3, 1
    //   105: swap
    //   106: aastore
    //   107: iload_0
    //   108: iload_1
    //   109: iadd
    //   110: dup
    //   111: istore_0
    //   112: iload #4
    //   114: if_icmpge -> 126
    //   117: aload_2
    //   118: iload_0
    //   119: invokevirtual charAt : (I)C
    //   122: istore_1
    //   123: goto -> 81
    //   126: aload #5
    //   128: putstatic burp/Zlwc.a : [Ljava/lang/String;
    //   131: bipush #26
    //   133: anewarray java/lang/String
    //   136: putstatic burp/Zlwc.b : [Ljava/lang/String;
    //   139: goto -> 300
    //   142: dup_x2
    //   143: pop
    //   144: invokevirtual toCharArray : ()[C
    //   147: dup_x1
    //   148: arraylength
    //   149: dup_x2
    //   150: pop
    //   151: iconst_0
    //   152: istore #6
    //   154: dup2_x1
    //   155: pop2
    //   156: dup_x2
    //   157: iconst_1
    //   158: if_icmpgt -> 260
    //   161: dup2
    //   162: swap
    //   163: iload #6
    //   165: dup2_x1
    //   166: caload
    //   167: swap
    //   168: iload #6
    //   170: bipush #7
    //   172: irem
    //   173: tableswitch default -> 242, 0 -> 212, 1 -> 217, 2 -> 222, 3 -> 227, 4 -> 232, 5 -> 237
    //   212: bipush #9
    //   214: goto -> 244
    //   217: bipush #124
    //   219: goto -> 244
    //   222: bipush #110
    //   224: goto -> 244
    //   227: bipush #116
    //   229: goto -> 244
    //   232: bipush #82
    //   234: goto -> 244
    //   237: bipush #94
    //   239: goto -> 244
    //   242: bipush #37
    //   244: ixor
    //   245: ixor
    //   246: i2c
    //   247: castore
    //   248: iinc #6, 1
    //   251: dup
    //   252: ifne -> 260
    //   255: dup2
    //   256: dup_x1
    //   257: goto -> 165
    //   260: dup2_x1
    //   261: pop2
    //   262: dup_x2
    //   263: iload #6
    //   265: if_icmpgt -> 161
    //   268: pop
    //   269: new java/lang/String
    //   272: dup_x1
    //   273: swap
    //   274: invokespecial <init> : ([C)V
    //   277: invokevirtual intern : ()Ljava/lang/String;
    //   280: swap
    //   281: pop
    //   282: swap
    //   283: tableswitch default -> 40, 0 -> 98
    //   300: sipush #-27692
    //   303: sipush #4812
    //   306: invokestatic a : (II)Ljava/lang/String;
    //   309: putstatic burp/Zlwc.ZM : Ljava/lang/String;
    //   312: new java/math/BigInteger
    //   315: dup
    //   316: sipush #-27693
    //   319: sipush #-8247
    //   322: invokestatic a : (II)Ljava/lang/String;
    //   325: invokespecial <init> : (Ljava/lang/String;)V
    //   328: putstatic burp/Zlwc.ZG : Ljava/lang/Object;
    //   331: return
  }
  
  private static Throwable a(Throwable paramThrowable) {
    return paramThrowable;
  }
  
  private static String a(int paramInt1, int paramInt2) {
    int i = (paramInt1 ^ 0xFFFF93DA) & 0xFFFF;
    if (b[i] == null) {
      char[] arrayOfChar = a[i].toCharArray();
      switch (arrayOfChar[0] & 0xFF) {
        case 0:
        
        case 1:
        
        case 2:
        
        case 3:
        
        case 4:
        
        case 5:
        
        case 6:
        
        case 7:
        
        case 8:
        
        case 9:
        
        case 10:
        
        case 11:
        
        case 12:
        
        case 13:
        
        case 14:
        
        case 15:
        
        case 16:
        
        case 17:
        
        case 18:
        
        case 19:
        
        case 20:
        
        case 21:
        
        case 22:
        
        case 23:
        
        case 24:
        
        case 25:
        
        case 26:
        
        case 27:
        
        case 28:
        
        case 29:
        
        case 30:
        
        case 31:
        
        case 32:
        
        case 33:
        
        case 34:
        
        case 35:
        
        case 36:
        
        case 37:
        
        case 38:
        
        case 39:
        
        case 40:
        
        case 41:
        
        case 42:
        
        case 43:
        
        case 44:
        
        case 45:
        
        case 46:
        
        case 47:
        
        case 48:
        
        case 49:
        
        case 50:
        
        case 51:
        
        case 52:
        
        case 53:
        
        case 54:
        
        case 55:
        
        case 56:
        
        case 57:
        
        case 58:
        
        case 59:
        
        case 60:
        
        case 61:
        
        case 62:
        
        case 63:
        
        case 64:
        
        case 65:
        
        case 66:
        
        case 67:
        
        case 68:
        
        case 69:
        
        case 70:
        
        case 71:
        
        case 72:
        
        case 73:
        
        case 74:
        
        case 75:
        
        case 76:
        
        case 77:
        
        case 78:
        
        case 79:
        
        case 80:
        
        case 81:
        
        case 82:
        
        case 83:
        
        case 84:
        
        case 85:
        
        case 86:
        
        case 87:
        
        case 88:
        
        case 89:
        
        case 90:
        
        case 91:
        
        case 92:
        
        case 93:
        
        case 94:
        
        case 95:
        
        case 96:
        
        case 97:
        
        case 98:
        
        case 99:
        
        case 100:
        
        case 101:
        
        case 102:
        
        case 103:
        
        case 104:
        
        case 105:
        
        case 106:
        
        case 107:
        
        case 108:
        
        case 109:
        
        case 110:
        
        case 111:
        
        case 112:
        
        case 113:
        
        case 114:
        
        case 115:
        
        case 116:
        
        case 117:
        
        case 118:
        
        case 119:
        
        case 120:
        
        case 121:
        
        case 122:
        
        case 123:
        
        case 124:
        
        case 125:
        
        case 126:
        
        case 127:
        
        case 128:
        
        case 129:
        
        case 130:
        
        case 131:
        
        case 132:
        
        case 133:
        
        case 134:
        
        case 135:
        
        case 136:
        
        case 137:
        
        case 138:
        
        case 139:
        
        case 140:
        
        case 141:
        
        case 142:
        
        case 143:
        
        case 144:
        
        case 145:
        
        case 146:
        
        case 147:
        
        case 148:
        
        case 149:
        
        case 150:
        
        case 151:
        
        case 152:
        
        case 153:
        
        case 154:
        
        case 155:
        
        case 156:
        
        case 157:
        
        case 158:
        
        case 159:
        
        case 160:
        
        case 161:
        
        case 162:
        
        case 163:
        
        case 164:
        
        case 165:
        
        case 166:
        
        case 167:
        
        case 168:
        
        case 169:
        
        case 170:
        
        case 171:
        
        case 172:
        
        case 173:
        
        case 174:
        
        case 175:
        
        case 176:
        
        case 177:
        
        case 178:
        
        case 179:
        
        case 180:
        
        case 181:
        
        case 182:
        
        case 183:
        
        case 184:
        
        case 185:
        
        case 186:
        
        case 187:
        
        case 188:
        
        case 189:
        
        case 190:
        
        case 191:
        
        case 192:
        
        case 193:
        
        case 194:
        
        case 195:
        
        case 196:
        
        case 197:
        
        case 198:
        
        case 199:
        
        case 200:
        
        case 201:
        
        case 202:
        
        case 203:
        
        case 204:
        
        case 205:
        
        case 206:
        
        case 207:
        
        case 208:
        
        case 209:
        
        case 210:
        
        case 211:
        
        case 212:
        
        case 213:
        
        case 214:
        
        case 215:
        
        case 216:
        
        case 217:
        
        case 218:
        
        case 219:
        
        case 220:
        
        case 221:
        
        case 222:
        
        case 223:
        
        case 224:
        
        case 225:
        
        case 226:
        
        case 227:
        
        case 228:
        
        case 229:
        
        case 230:
        
        case 231:
        
        case 232:
        
        case 233:
        
        case 234:
        
        case 235:
        
        case 236:
        
        case 237:
        
        case 238:
        
        case 239:
        
        case 240:
        
        case 241:
        
        case 242:
        
        case 243:
        
        case 244:
        
        case 245:
        
        case 246:
        
        case 247:
        
        case 248:
        
        case 249:
        
        case 250:
        
        case 251:
        
        case 252:
        
        case 253:
        
        case 254:
        
        default:
          break;
      } 
      byte b1 = 127;
      int j = (paramInt2 & 0xFF) - b1;
      if (j < 0)
        j += 256; 
      int k = ((paramInt2 & 0xFFFF) >>> 8) - b1;
      if (k < 0)
        k += 256; 
      for (byte b2 = 0; b2 < arrayOfChar.length; b2++) {
        int m = b2 % 2;
        if (m == 0) {
          arrayOfChar[b2] = (char)(arrayOfChar[b2] ^ j);
          j = ((j >>> 3 | j << 5) ^ arrayOfChar[b2]) & 0xFF;
        } else {
          arrayOfChar[b2] = (char)(arrayOfChar[b2] ^ k);
          k = ((k >>> 3 | k << 5) ^ arrayOfChar[b2]) & 0xFF;
        } 
      } 
      b[i] = (new String(arrayOfChar)).intern();
    } 
    return b[i];
  }
}


/* Location:              C:\Program Files\BurpSuitePro\burpsuite_pro.jar!\burp\Zlwc.class
 * Java compiler version: 21 (65.0)
 * JD-Core Version:       1.1.3
 */