package burp;

import java.math.BigInteger;

class Zly7 extends ClassLoader {
  static String ZC;
  
  static Object Zt;
  
  private static final String[] a;
  
  private static final String[] b;
  
  static void ZD(Object paramObject) {
    Zsuw.ZK = a(16428, 1396);
    Zsuw.ZB = new BigInteger(a(16430, 9765));
    boolean bool = Zt2e.ZK();
    try {
      try {
        if (Zl1q.ZY.charAt(Math.abs(((BigInteger)Zg27.ZQ).intValue() % 32)) <= Zgco.Zh.charAt(Math.abs(((BigInteger)Ze08.ZJ).intValue() % 32))) {
          try {
            Zl6e.ZB(Class.forName(a(16425, 27536)));
            if (bool)
              Zeor.Zz(Class.forName(a(16421, -10565))); 
          } catch (Throwable throwable) {
            throw a(null);
          } 
          return;
        } 
      } catch (Throwable throwable) {
        throw a(null);
      } 
      Zeor.Zz(Class.forName(a(16421, -10565)));
    } catch (Throwable throwable) {}
  }
  
  static void Zb(Object[] paramArrayOfObject, Object paramObject) throws Throwable {}
  
  static boolean Zs(Object[] paramArrayOfObject, Object paramObject) throws Throwable {
    // Byte code:
    //   0: invokestatic ZK : ()Z
    //   3: istore_2
    //   4: sipush #16446
    //   7: bipush #121
    //   9: invokestatic a : (II)Ljava/lang/String;
    //   12: invokestatic forName : (Ljava/lang/String;)Ljava/lang/Class;
    //   15: invokestatic Zo : (Ljava/lang/Object;)V
    //   18: new java/lang/StringBuilder
    //   21: dup
    //   22: invokespecial <init> : ()V
    //   25: astore_3
    //   26: iconst_0
    //   27: istore #4
    //   29: iload #4
    //   31: bipush #32
    //   33: if_icmpge -> 1367
    //   36: iload #4
    //   38: tableswitch default -> 1360, 0 -> 180, 1 -> 217, 2 -> 254, 3 -> 291, 4 -> 328, 5 -> 365, 6 -> 402, 7 -> 439, 8 -> 476, 9 -> 513, 10 -> 550, 11 -> 587, 12 -> 624, 13 -> 661, 14 -> 698, 15 -> 735, 16 -> 772, 17 -> 809, 18 -> 846, 19 -> 883, 20 -> 920, 21 -> 957, 22 -> 994, 23 -> 1031, 24 -> 1068, 25 -> 1105, 26 -> 1142, 27 -> 1179, 28 -> 1216, 29 -> 1253, 30 -> 1290, 31 -> 1327
    //   180: aload_3
    //   181: getstatic burp/Zlpu.ZA : Ljava/lang/String;
    //   184: getstatic burp/Zt7w.ZF : Ljava/lang/Object;
    //   187: checkcast java/math/BigInteger
    //   190: invokevirtual intValue : ()I
    //   193: bipush #32
    //   195: irem
    //   196: invokestatic abs : (I)I
    //   199: invokevirtual charAt : (I)C
    //   202: invokevirtual append : (C)Ljava/lang/StringBuilder;
    //   205: pop
    //   206: iload_2
    //   207: ifeq -> 1360
    //   210: goto -> 217
    //   213: invokestatic a : (Ljava/lang/Throwable;)Ljava/lang/Throwable;
    //   216: athrow
    //   217: aload_3
    //   218: getstatic burp/Zsyu.ZJ : Ljava/lang/String;
    //   221: getstatic burp/Zmpc.Zc : Ljava/lang/Object;
    //   224: checkcast java/math/BigInteger
    //   227: invokevirtual intValue : ()I
    //   230: bipush #32
    //   232: irem
    //   233: invokestatic abs : (I)I
    //   236: invokevirtual charAt : (I)C
    //   239: invokevirtual append : (C)Ljava/lang/StringBuilder;
    //   242: pop
    //   243: iload_2
    //   244: ifeq -> 1360
    //   247: goto -> 254
    //   250: invokestatic a : (Ljava/lang/Throwable;)Ljava/lang/Throwable;
    //   253: athrow
    //   254: aload_3
    //   255: getstatic burp/Zsbd.ZA : Ljava/lang/String;
    //   258: getstatic burp/Zgr4.ZL : Ljava/lang/Object;
    //   261: checkcast java/math/BigInteger
    //   264: invokevirtual intValue : ()I
    //   267: bipush #32
    //   269: irem
    //   270: invokestatic abs : (I)I
    //   273: invokevirtual charAt : (I)C
    //   276: invokevirtual append : (C)Ljava/lang/StringBuilder;
    //   279: pop
    //   280: iload_2
    //   281: ifeq -> 1360
    //   284: goto -> 291
    //   287: invokestatic a : (Ljava/lang/Throwable;)Ljava/lang/Throwable;
    //   290: athrow
    //   291: aload_3
    //   292: getstatic burp/Zt7w.Zi : Ljava/lang/String;
    //   295: getstatic burp/Zrcx.Za : Ljava/lang/Object;
    //   298: checkcast java/math/BigInteger
    //   301: invokevirtual intValue : ()I
    //   304: bipush #32
    //   306: irem
    //   307: invokestatic abs : (I)I
    //   310: invokevirtual charAt : (I)C
    //   313: invokevirtual append : (C)Ljava/lang/StringBuilder;
    //   316: pop
    //   317: iload_2
    //   318: ifeq -> 1360
    //   321: goto -> 328
    //   324: invokestatic a : (Ljava/lang/Throwable;)Ljava/lang/Throwable;
    //   327: athrow
    //   328: aload_3
    //   329: getstatic burp/Ztvp.ZZ : Ljava/lang/String;
    //   332: getstatic burp/Zelz.Z_ : Ljava/lang/Object;
    //   335: checkcast java/math/BigInteger
    //   338: invokevirtual intValue : ()I
    //   341: bipush #32
    //   343: irem
    //   344: invokestatic abs : (I)I
    //   347: invokevirtual charAt : (I)C
    //   350: invokevirtual append : (C)Ljava/lang/StringBuilder;
    //   353: pop
    //   354: iload_2
    //   355: ifeq -> 1360
    //   358: goto -> 365
    //   361: invokestatic a : (Ljava/lang/Throwable;)Ljava/lang/Throwable;
    //   364: athrow
    //   365: aload_3
    //   366: getstatic burp/Zlpu.ZA : Ljava/lang/String;
    //   369: getstatic burp/Zec_.ZN : Ljava/lang/Object;
    //   372: checkcast java/math/BigInteger
    //   375: invokevirtual intValue : ()I
    //   378: bipush #32
    //   380: irem
    //   381: invokestatic abs : (I)I
    //   384: invokevirtual charAt : (I)C
    //   387: invokevirtual append : (C)Ljava/lang/StringBuilder;
    //   390: pop
    //   391: iload_2
    //   392: ifeq -> 1360
    //   395: goto -> 402
    //   398: invokestatic a : (Ljava/lang/Throwable;)Ljava/lang/Throwable;
    //   401: athrow
    //   402: aload_3
    //   403: getstatic burp/Zlbr.Zr : Ljava/lang/String;
    //   406: getstatic burp/Zz16.ZK : Ljava/lang/Object;
    //   409: checkcast java/math/BigInteger
    //   412: invokevirtual intValue : ()I
    //   415: bipush #32
    //   417: irem
    //   418: invokestatic abs : (I)I
    //   421: invokevirtual charAt : (I)C
    //   424: invokevirtual append : (C)Ljava/lang/StringBuilder;
    //   427: pop
    //   428: iload_2
    //   429: ifeq -> 1360
    //   432: goto -> 439
    //   435: invokestatic a : (Ljava/lang/Throwable;)Ljava/lang/Throwable;
    //   438: athrow
    //   439: aload_3
    //   440: getstatic burp/Zevf.ZL : Ljava/lang/String;
    //   443: getstatic burp/Zkde.Zk : Ljava/lang/Object;
    //   446: checkcast java/math/BigInteger
    //   449: invokevirtual intValue : ()I
    //   452: bipush #32
    //   454: irem
    //   455: invokestatic abs : (I)I
    //   458: invokevirtual charAt : (I)C
    //   461: invokevirtual append : (C)Ljava/lang/StringBuilder;
    //   464: pop
    //   465: iload_2
    //   466: ifeq -> 1360
    //   469: goto -> 476
    //   472: invokestatic a : (Ljava/lang/Throwable;)Ljava/lang/Throwable;
    //   475: athrow
    //   476: aload_3
    //   477: getstatic burp/Zl5d.Zh : Ljava/lang/String;
    //   480: getstatic burp/Ze6k.Zs : Ljava/lang/Object;
    //   483: checkcast java/math/BigInteger
    //   486: invokevirtual intValue : ()I
    //   489: bipush #32
    //   491: irem
    //   492: invokestatic abs : (I)I
    //   495: invokevirtual charAt : (I)C
    //   498: invokevirtual append : (C)Ljava/lang/StringBuilder;
    //   501: pop
    //   502: iload_2
    //   503: ifeq -> 1360
    //   506: goto -> 513
    //   509: invokestatic a : (Ljava/lang/Throwable;)Ljava/lang/Throwable;
    //   512: athrow
    //   513: aload_3
    //   514: getstatic burp/Zl5d.Zh : Ljava/lang/String;
    //   517: getstatic burp/Zsqi.Zf : Ljava/lang/Object;
    //   520: checkcast java/math/BigInteger
    //   523: invokevirtual intValue : ()I
    //   526: bipush #32
    //   528: irem
    //   529: invokestatic abs : (I)I
    //   532: invokevirtual charAt : (I)C
    //   535: invokevirtual append : (C)Ljava/lang/StringBuilder;
    //   538: pop
    //   539: iload_2
    //   540: ifeq -> 1360
    //   543: goto -> 550
    //   546: invokestatic a : (Ljava/lang/Throwable;)Ljava/lang/Throwable;
    //   549: athrow
    //   550: aload_3
    //   551: getstatic burp/Zl1n.ZZ : Ljava/lang/String;
    //   554: getstatic burp/Zgr4.ZL : Ljava/lang/Object;
    //   557: checkcast java/math/BigInteger
    //   560: invokevirtual intValue : ()I
    //   563: bipush #32
    //   565: irem
    //   566: invokestatic abs : (I)I
    //   569: invokevirtual charAt : (I)C
    //   572: invokevirtual append : (C)Ljava/lang/StringBuilder;
    //   575: pop
    //   576: iload_2
    //   577: ifeq -> 1360
    //   580: goto -> 587
    //   583: invokestatic a : (Ljava/lang/Throwable;)Ljava/lang/Throwable;
    //   586: athrow
    //   587: aload_3
    //   588: getstatic burp/Zrcx.ZW : Ljava/lang/String;
    //   591: getstatic burp/Zsk4.Ze : Ljava/lang/Object;
    //   594: checkcast java/math/BigInteger
    //   597: invokevirtual intValue : ()I
    //   600: bipush #32
    //   602: irem
    //   603: invokestatic abs : (I)I
    //   606: invokevirtual charAt : (I)C
    //   609: invokevirtual append : (C)Ljava/lang/StringBuilder;
    //   612: pop
    //   613: iload_2
    //   614: ifeq -> 1360
    //   617: goto -> 624
    //   620: invokestatic a : (Ljava/lang/Throwable;)Ljava/lang/Throwable;
    //   623: athrow
    //   624: aload_3
    //   625: getstatic burp/Zec_.Zv : Ljava/lang/String;
    //   628: getstatic burp/Zly7.Zt : Ljava/lang/Object;
    //   631: checkcast java/math/BigInteger
    //   634: invokevirtual intValue : ()I
    //   637: bipush #32
    //   639: irem
    //   640: invokestatic abs : (I)I
    //   643: invokevirtual charAt : (I)C
    //   646: invokevirtual append : (C)Ljava/lang/StringBuilder;
    //   649: pop
    //   650: iload_2
    //   651: ifeq -> 1360
    //   654: goto -> 661
    //   657: invokestatic a : (Ljava/lang/Throwable;)Ljava/lang/Throwable;
    //   660: athrow
    //   661: aload_3
    //   662: getstatic burp/Zl1n.ZZ : Ljava/lang/String;
    //   665: getstatic burp/Zsyu.Zj : Ljava/lang/Object;
    //   668: checkcast java/math/BigInteger
    //   671: invokevirtual intValue : ()I
    //   674: bipush #32
    //   676: irem
    //   677: invokestatic abs : (I)I
    //   680: invokevirtual charAt : (I)C
    //   683: invokevirtual append : (C)Ljava/lang/StringBuilder;
    //   686: pop
    //   687: iload_2
    //   688: ifeq -> 1360
    //   691: goto -> 698
    //   694: invokestatic a : (Ljava/lang/Throwable;)Ljava/lang/Throwable;
    //   697: athrow
    //   698: aload_3
    //   699: getstatic burp/Zsk4.ZH : Ljava/lang/String;
    //   702: getstatic burp/Zx_u.Zy : Ljava/lang/Object;
    //   705: checkcast java/math/BigInteger
    //   708: invokevirtual intValue : ()I
    //   711: bipush #32
    //   713: irem
    //   714: invokestatic abs : (I)I
    //   717: invokevirtual charAt : (I)C
    //   720: invokevirtual append : (C)Ljava/lang/StringBuilder;
    //   723: pop
    //   724: iload_2
    //   725: ifeq -> 1360
    //   728: goto -> 735
    //   731: invokestatic a : (Ljava/lang/Throwable;)Ljava/lang/Throwable;
    //   734: athrow
    //   735: aload_3
    //   736: getstatic burp/Zg27.ZP : Ljava/lang/String;
    //   739: getstatic burp/Zgde.ZG : Ljava/lang/Object;
    //   742: checkcast java/math/BigInteger
    //   745: invokevirtual intValue : ()I
    //   748: bipush #32
    //   750: irem
    //   751: invokestatic abs : (I)I
    //   754: invokevirtual charAt : (I)C
    //   757: invokevirtual append : (C)Ljava/lang/StringBuilder;
    //   760: pop
    //   761: iload_2
    //   762: ifeq -> 1360
    //   765: goto -> 772
    //   768: invokestatic a : (Ljava/lang/Throwable;)Ljava/lang/Throwable;
    //   771: athrow
    //   772: aload_3
    //   773: getstatic burp/Zlum.ZW : Ljava/lang/String;
    //   776: getstatic burp/Zx_u.Zy : Ljava/lang/Object;
    //   779: checkcast java/math/BigInteger
    //   782: invokevirtual intValue : ()I
    //   785: bipush #32
    //   787: irem
    //   788: invokestatic abs : (I)I
    //   791: invokevirtual charAt : (I)C
    //   794: invokevirtual append : (C)Ljava/lang/StringBuilder;
    //   797: pop
    //   798: iload_2
    //   799: ifeq -> 1360
    //   802: goto -> 809
    //   805: invokestatic a : (Ljava/lang/Throwable;)Ljava/lang/Throwable;
    //   808: athrow
    //   809: aload_3
    //   810: getstatic burp/Zgfm.ZE : Ljava/lang/String;
    //   813: getstatic burp/Zgr4.ZL : Ljava/lang/Object;
    //   816: checkcast java/math/BigInteger
    //   819: invokevirtual intValue : ()I
    //   822: bipush #32
    //   824: irem
    //   825: invokestatic abs : (I)I
    //   828: invokevirtual charAt : (I)C
    //   831: invokevirtual append : (C)Ljava/lang/StringBuilder;
    //   834: pop
    //   835: iload_2
    //   836: ifeq -> 1360
    //   839: goto -> 846
    //   842: invokestatic a : (Ljava/lang/Throwable;)Ljava/lang/Throwable;
    //   845: athrow
    //   846: aload_3
    //   847: getstatic burp/Zs9x.ZY : Ljava/lang/String;
    //   850: getstatic burp/Zsk4.Ze : Ljava/lang/Object;
    //   853: checkcast java/math/BigInteger
    //   856: invokevirtual intValue : ()I
    //   859: bipush #32
    //   861: irem
    //   862: invokestatic abs : (I)I
    //   865: invokevirtual charAt : (I)C
    //   868: invokevirtual append : (C)Ljava/lang/StringBuilder;
    //   871: pop
    //   872: iload_2
    //   873: ifeq -> 1360
    //   876: goto -> 883
    //   879: invokestatic a : (Ljava/lang/Throwable;)Ljava/lang/Throwable;
    //   882: athrow
    //   883: aload_3
    //   884: getstatic burp/Zeqr.Zb : Ljava/lang/String;
    //   887: getstatic burp/Zz16.ZK : Ljava/lang/Object;
    //   890: checkcast java/math/BigInteger
    //   893: invokevirtual intValue : ()I
    //   896: bipush #32
    //   898: irem
    //   899: invokestatic abs : (I)I
    //   902: invokevirtual charAt : (I)C
    //   905: invokevirtual append : (C)Ljava/lang/StringBuilder;
    //   908: pop
    //   909: iload_2
    //   910: ifeq -> 1360
    //   913: goto -> 920
    //   916: invokestatic a : (Ljava/lang/Throwable;)Ljava/lang/Throwable;
    //   919: athrow
    //   920: aload_3
    //   921: getstatic burp/Ze6k.ZM : Ljava/lang/String;
    //   924: getstatic burp/Zsyu.Zj : Ljava/lang/Object;
    //   927: checkcast java/math/BigInteger
    //   930: invokevirtual intValue : ()I
    //   933: bipush #32
    //   935: irem
    //   936: invokestatic abs : (I)I
    //   939: invokevirtual charAt : (I)C
    //   942: invokevirtual append : (C)Ljava/lang/StringBuilder;
    //   945: pop
    //   946: iload_2
    //   947: ifeq -> 1360
    //   950: goto -> 957
    //   953: invokestatic a : (Ljava/lang/Throwable;)Ljava/lang/Throwable;
    //   956: athrow
    //   957: aload_3
    //   958: getstatic burp/Zgr4.Zi : Ljava/lang/String;
    //   961: getstatic burp/Ze3z.Zf : Ljava/lang/Object;
    //   964: checkcast java/math/BigInteger
    //   967: invokevirtual intValue : ()I
    //   970: bipush #32
    //   972: irem
    //   973: invokestatic abs : (I)I
    //   976: invokevirtual charAt : (I)C
    //   979: invokevirtual append : (C)Ljava/lang/StringBuilder;
    //   982: pop
    //   983: iload_2
    //   984: ifeq -> 1360
    //   987: goto -> 994
    //   990: invokestatic a : (Ljava/lang/Throwable;)Ljava/lang/Throwable;
    //   993: athrow
    //   994: aload_3
    //   995: getstatic burp/Ze40.Zr : Ljava/lang/String;
    //   998: getstatic burp/Zty2.Zl : Ljava/lang/Object;
    //   1001: checkcast java/math/BigInteger
    //   1004: invokevirtual intValue : ()I
    //   1007: bipush #32
    //   1009: irem
    //   1010: invokestatic abs : (I)I
    //   1013: invokevirtual charAt : (I)C
    //   1016: invokevirtual append : (C)Ljava/lang/StringBuilder;
    //   1019: pop
    //   1020: iload_2
    //   1021: ifeq -> 1360
    //   1024: goto -> 1031
    //   1027: invokestatic a : (Ljava/lang/Throwable;)Ljava/lang/Throwable;
    //   1030: athrow
    //   1031: aload_3
    //   1032: getstatic burp/Zlum.ZW : Ljava/lang/String;
    //   1035: getstatic burp/Ztfr.Zr : Ljava/lang/Object;
    //   1038: checkcast java/math/BigInteger
    //   1041: invokevirtual intValue : ()I
    //   1044: bipush #32
    //   1046: irem
    //   1047: invokestatic abs : (I)I
    //   1050: invokevirtual charAt : (I)C
    //   1053: invokevirtual append : (C)Ljava/lang/StringBuilder;
    //   1056: pop
    //   1057: iload_2
    //   1058: ifeq -> 1360
    //   1061: goto -> 1068
    //   1064: invokestatic a : (Ljava/lang/Throwable;)Ljava/lang/Throwable;
    //   1067: athrow
    //   1068: aload_3
    //   1069: getstatic burp/Zs15.Zs : Ljava/lang/String;
    //   1072: getstatic burp/Zgfm.ZV : Ljava/lang/Object;
    //   1075: checkcast java/math/BigInteger
    //   1078: invokevirtual intValue : ()I
    //   1081: bipush #32
    //   1083: irem
    //   1084: invokestatic abs : (I)I
    //   1087: invokevirtual charAt : (I)C
    //   1090: invokevirtual append : (C)Ljava/lang/StringBuilder;
    //   1093: pop
    //   1094: iload_2
    //   1095: ifeq -> 1360
    //   1098: goto -> 1105
    //   1101: invokestatic a : (Ljava/lang/Throwable;)Ljava/lang/Throwable;
    //   1104: athrow
    //   1105: aload_3
    //   1106: getstatic burp/Zevf.ZL : Ljava/lang/String;
    //   1109: getstatic burp/Zeoi.ZE : Ljava/lang/Object;
    //   1112: checkcast java/math/BigInteger
    //   1115: invokevirtual intValue : ()I
    //   1118: bipush #32
    //   1120: irem
    //   1121: invokestatic abs : (I)I
    //   1124: invokevirtual charAt : (I)C
    //   1127: invokevirtual append : (C)Ljava/lang/StringBuilder;
    //   1130: pop
    //   1131: iload_2
    //   1132: ifeq -> 1360
    //   1135: goto -> 1142
    //   1138: invokestatic a : (Ljava/lang/Throwable;)Ljava/lang/Throwable;
    //   1141: athrow
    //   1142: aload_3
    //   1143: getstatic burp/Zs9x.ZY : Ljava/lang/String;
    //   1146: getstatic burp/Zlum.Zj : Ljava/lang/Object;
    //   1149: checkcast java/math/BigInteger
    //   1152: invokevirtual intValue : ()I
    //   1155: bipush #32
    //   1157: irem
    //   1158: invokestatic abs : (I)I
    //   1161: invokevirtual charAt : (I)C
    //   1164: invokevirtual append : (C)Ljava/lang/StringBuilder;
    //   1167: pop
    //   1168: iload_2
    //   1169: ifeq -> 1360
    //   1172: goto -> 1179
    //   1175: invokestatic a : (Ljava/lang/Throwable;)Ljava/lang/Throwable;
    //   1178: athrow
    //   1179: aload_3
    //   1180: getstatic burp/Zx_b.ZD : Ljava/lang/String;
    //   1183: getstatic burp/Zgco.Zx : Ljava/lang/Object;
    //   1186: checkcast java/math/BigInteger
    //   1189: invokevirtual intValue : ()I
    //   1192: bipush #32
    //   1194: irem
    //   1195: invokestatic abs : (I)I
    //   1198: invokevirtual charAt : (I)C
    //   1201: invokevirtual append : (C)Ljava/lang/StringBuilder;
    //   1204: pop
    //   1205: iload_2
    //   1206: ifeq -> 1360
    //   1209: goto -> 1216
    //   1212: invokestatic a : (Ljava/lang/Throwable;)Ljava/lang/Throwable;
    //   1215: athrow
    //   1216: aload_3
    //   1217: getstatic burp/Zlxh.ZG : Ljava/lang/String;
    //   1220: getstatic burp/Zb9m.ZK : Ljava/lang/Object;
    //   1223: checkcast java/math/BigInteger
    //   1226: invokevirtual intValue : ()I
    //   1229: bipush #32
    //   1231: irem
    //   1232: invokestatic abs : (I)I
    //   1235: invokevirtual charAt : (I)C
    //   1238: invokevirtual append : (C)Ljava/lang/StringBuilder;
    //   1241: pop
    //   1242: iload_2
    //   1243: ifeq -> 1360
    //   1246: goto -> 1253
    //   1249: invokestatic a : (Ljava/lang/Throwable;)Ljava/lang/Throwable;
    //   1252: athrow
    //   1253: aload_3
    //   1254: getstatic burp/Zvi.ZR : Ljava/lang/String;
    //   1257: getstatic burp/Zvi.Zs : Ljava/lang/Object;
    //   1260: checkcast java/math/BigInteger
    //   1263: invokevirtual intValue : ()I
    //   1266: bipush #32
    //   1268: irem
    //   1269: invokestatic abs : (I)I
    //   1272: invokevirtual charAt : (I)C
    //   1275: invokevirtual append : (C)Ljava/lang/StringBuilder;
    //   1278: pop
    //   1279: iload_2
    //   1280: ifeq -> 1360
    //   1283: goto -> 1290
    //   1286: invokestatic a : (Ljava/lang/Throwable;)Ljava/lang/Throwable;
    //   1289: athrow
    //   1290: aload_3
    //   1291: getstatic burp/Zex5.Zh : Ljava/lang/String;
    //   1294: getstatic burp/Zrfl.Z_ : Ljava/lang/Object;
    //   1297: checkcast java/math/BigInteger
    //   1300: invokevirtual intValue : ()I
    //   1303: bipush #32
    //   1305: irem
    //   1306: invokestatic abs : (I)I
    //   1309: invokevirtual charAt : (I)C
    //   1312: invokevirtual append : (C)Ljava/lang/StringBuilder;
    //   1315: pop
    //   1316: iload_2
    //   1317: ifeq -> 1360
    //   1320: goto -> 1327
    //   1323: invokestatic a : (Ljava/lang/Throwable;)Ljava/lang/Throwable;
    //   1326: athrow
    //   1327: aload_3
    //   1328: getstatic burp/Zsx6.ZJ : Ljava/lang/String;
    //   1331: getstatic burp/Zb9m.ZK : Ljava/lang/Object;
    //   1334: checkcast java/math/BigInteger
    //   1337: invokevirtual intValue : ()I
    //   1340: bipush #32
    //   1342: irem
    //   1343: invokestatic abs : (I)I
    //   1346: invokevirtual charAt : (I)C
    //   1349: invokevirtual append : (C)Ljava/lang/StringBuilder;
    //   1352: pop
    //   1353: goto -> 1360
    //   1356: invokestatic a : (Ljava/lang/Throwable;)Ljava/lang/Throwable;
    //   1359: athrow
    //   1360: iinc #4, 1
    //   1363: iload_2
    //   1364: ifeq -> 29
    //   1367: aload_3
    //   1368: invokevirtual toString : ()Ljava/lang/String;
    //   1371: putstatic burp/Zd0.Zi : Ljava/lang/String;
    //   1374: getstatic burp/Zlxh.ZU : Ljava/lang/Object;
    //   1377: checkcast java/math/BigInteger
    //   1380: getstatic burp/Ze7y.Zh : Ljava/lang/Object;
    //   1383: checkcast java/math/BigInteger
    //   1386: invokevirtual subtract : (Ljava/math/BigInteger;)Ljava/math/BigInteger;
    //   1389: putstatic burp/Zxof.Zi : Ljava/lang/Object;
    //   1392: getstatic burp/Zlh2.Zc : Ljava/lang/Object;
    //   1395: checkcast java/math/BigInteger
    //   1398: invokevirtual toByteArray : ()[B
    //   1401: astore #4
    //   1403: iconst_0
    //   1404: istore #6
    //   1406: iconst_0
    //   1407: istore #7
    //   1409: iload #7
    //   1411: aload #4
    //   1413: arraylength
    //   1414: if_icmpge -> 1560
    //   1417: aload #4
    //   1419: iload #7
    //   1421: baload
    //   1422: istore #8
    //   1424: iload #8
    //   1426: bipush #48
    //   1428: if_icmplt -> 1445
    //   1431: iload #8
    //   1433: bipush #57
    //   1435: if_icmple -> 1543
    //   1438: goto -> 1445
    //   1441: invokestatic a : (Ljava/lang/Throwable;)Ljava/lang/Throwable;
    //   1444: athrow
    //   1445: iload #8
    //   1447: bipush #65
    //   1449: if_icmplt -> 1473
    //   1452: goto -> 1459
    //   1455: invokestatic a : (Ljava/lang/Throwable;)Ljava/lang/Throwable;
    //   1458: athrow
    //   1459: iload #8
    //   1461: bipush #90
    //   1463: if_icmple -> 1543
    //   1466: goto -> 1473
    //   1469: invokestatic a : (Ljava/lang/Throwable;)Ljava/lang/Throwable;
    //   1472: athrow
    //   1473: iload #8
    //   1475: bipush #97
    //   1477: if_icmplt -> 1501
    //   1480: goto -> 1487
    //   1483: invokestatic a : (Ljava/lang/Throwable;)Ljava/lang/Throwable;
    //   1486: athrow
    //   1487: iload #8
    //   1489: bipush #122
    //   1491: if_icmple -> 1543
    //   1494: goto -> 1501
    //   1497: invokestatic a : (Ljava/lang/Throwable;)Ljava/lang/Throwable;
    //   1500: athrow
    //   1501: iload #8
    //   1503: bipush #43
    //   1505: if_icmpeq -> 1543
    //   1508: goto -> 1515
    //   1511: invokestatic a : (Ljava/lang/Throwable;)Ljava/lang/Throwable;
    //   1514: athrow
    //   1515: iload #8
    //   1517: bipush #47
    //   1519: if_icmpeq -> 1543
    //   1522: goto -> 1529
    //   1525: invokestatic a : (Ljava/lang/Throwable;)Ljava/lang/Throwable;
    //   1528: athrow
    //   1529: iload #8
    //   1531: bipush #61
    //   1533: if_icmpne -> 1553
    //   1536: goto -> 1543
    //   1539: invokestatic a : (Ljava/lang/Throwable;)Ljava/lang/Throwable;
    //   1542: athrow
    //   1543: iinc #6, 1
    //   1546: goto -> 1553
    //   1549: invokestatic a : (Ljava/lang/Throwable;)Ljava/lang/Throwable;
    //   1552: athrow
    //   1553: iinc #7, 1
    //   1556: iload_2
    //   1557: ifeq -> 1409
    //   1560: iload #6
    //   1562: newarray byte
    //   1564: astore #7
    //   1566: iconst_0
    //   1567: istore #8
    //   1569: iconst_0
    //   1570: istore #9
    //   1572: iload #9
    //   1574: aload #4
    //   1576: arraylength
    //   1577: if_icmpge -> 1730
    //   1580: aload #4
    //   1582: iload #9
    //   1584: baload
    //   1585: istore #10
    //   1587: iload #10
    //   1589: bipush #48
    //   1591: if_icmplt -> 1608
    //   1594: iload #10
    //   1596: bipush #57
    //   1598: if_icmple -> 1706
    //   1601: goto -> 1608
    //   1604: invokestatic a : (Ljava/lang/Throwable;)Ljava/lang/Throwable;
    //   1607: athrow
    //   1608: iload #10
    //   1610: bipush #65
    //   1612: if_icmplt -> 1636
    //   1615: goto -> 1622
    //   1618: invokestatic a : (Ljava/lang/Throwable;)Ljava/lang/Throwable;
    //   1621: athrow
    //   1622: iload #10
    //   1624: bipush #90
    //   1626: if_icmple -> 1706
    //   1629: goto -> 1636
    //   1632: invokestatic a : (Ljava/lang/Throwable;)Ljava/lang/Throwable;
    //   1635: athrow
    //   1636: iload #10
    //   1638: bipush #97
    //   1640: if_icmplt -> 1664
    //   1643: goto -> 1650
    //   1646: invokestatic a : (Ljava/lang/Throwable;)Ljava/lang/Throwable;
    //   1649: athrow
    //   1650: iload #10
    //   1652: bipush #122
    //   1654: if_icmple -> 1706
    //   1657: goto -> 1664
    //   1660: invokestatic a : (Ljava/lang/Throwable;)Ljava/lang/Throwable;
    //   1663: athrow
    //   1664: iload #10
    //   1666: bipush #43
    //   1668: if_icmpeq -> 1706
    //   1671: goto -> 1678
    //   1674: invokestatic a : (Ljava/lang/Throwable;)Ljava/lang/Throwable;
    //   1677: athrow
    //   1678: iload #10
    //   1680: bipush #47
    //   1682: if_icmpeq -> 1706
    //   1685: goto -> 1692
    //   1688: invokestatic a : (Ljava/lang/Throwable;)Ljava/lang/Throwable;
    //   1691: athrow
    //   1692: iload #10
    //   1694: bipush #61
    //   1696: if_icmpne -> 1723
    //   1699: goto -> 1706
    //   1702: invokestatic a : (Ljava/lang/Throwable;)Ljava/lang/Throwable;
    //   1705: athrow
    //   1706: aload #7
    //   1708: iload #8
    //   1710: iload #10
    //   1712: bastore
    //   1713: iinc #8, 1
    //   1716: goto -> 1723
    //   1719: invokestatic a : (Ljava/lang/Throwable;)Ljava/lang/Throwable;
    //   1722: athrow
    //   1723: iinc #9, 1
    //   1726: iload_2
    //   1727: ifeq -> 1572
    //   1730: aload #7
    //   1732: astore #5
    //   1734: aload #5
    //   1736: astore #4
    //   1738: aload #4
    //   1740: arraylength
    //   1741: istore #6
    //   1743: aload #4
    //   1745: iload #6
    //   1747: iconst_1
    //   1748: isub
    //   1749: baload
    //   1750: bipush #61
    //   1752: if_icmpne -> 1762
    //   1755: iinc #6, -1
    //   1758: iload_2
    //   1759: ifeq -> 1743
    //   1762: iload #6
    //   1764: aload #4
    //   1766: arraylength
    //   1767: iconst_4
    //   1768: idiv
    //   1769: isub
    //   1770: newarray byte
    //   1772: astore #7
    //   1774: iconst_0
    //   1775: istore #8
    //   1777: iload #8
    //   1779: aload #4
    //   1781: arraylength
    //   1782: if_icmpge -> 2062
    //   1785: aload #4
    //   1787: iload #8
    //   1789: baload
    //   1790: bipush #61
    //   1792: if_icmpne -> 1812
    //   1795: aload #4
    //   1797: iload #8
    //   1799: iconst_0
    //   1800: bastore
    //   1801: iload_2
    //   1802: ifeq -> 2055
    //   1805: goto -> 1812
    //   1808: invokestatic a : (Ljava/lang/Throwable;)Ljava/lang/Throwable;
    //   1811: athrow
    //   1812: aload #4
    //   1814: iload #8
    //   1816: baload
    //   1817: bipush #47
    //   1819: if_icmpne -> 1847
    //   1822: goto -> 1829
    //   1825: invokestatic a : (Ljava/lang/Throwable;)Ljava/lang/Throwable;
    //   1828: athrow
    //   1829: aload #4
    //   1831: iload #8
    //   1833: bipush #63
    //   1835: bastore
    //   1836: iload_2
    //   1837: ifeq -> 2055
    //   1840: goto -> 1847
    //   1843: invokestatic a : (Ljava/lang/Throwable;)Ljava/lang/Throwable;
    //   1846: athrow
    //   1847: aload #4
    //   1849: iload #8
    //   1851: baload
    //   1852: bipush #43
    //   1854: if_icmpne -> 1882
    //   1857: goto -> 1864
    //   1860: invokestatic a : (Ljava/lang/Throwable;)Ljava/lang/Throwable;
    //   1863: athrow
    //   1864: aload #4
    //   1866: iload #8
    //   1868: bipush #62
    //   1870: bastore
    //   1871: iload_2
    //   1872: ifeq -> 2055
    //   1875: goto -> 1882
    //   1878: invokestatic a : (Ljava/lang/Throwable;)Ljava/lang/Throwable;
    //   1881: athrow
    //   1882: aload #4
    //   1884: iload #8
    //   1886: baload
    //   1887: bipush #48
    //   1889: if_icmplt -> 1941
    //   1892: goto -> 1899
    //   1895: invokestatic a : (Ljava/lang/Throwable;)Ljava/lang/Throwable;
    //   1898: athrow
    //   1899: aload #4
    //   1901: iload #8
    //   1903: baload
    //   1904: bipush #57
    //   1906: if_icmpgt -> 1941
    //   1909: goto -> 1916
    //   1912: invokestatic a : (Ljava/lang/Throwable;)Ljava/lang/Throwable;
    //   1915: athrow
    //   1916: aload #4
    //   1918: iload #8
    //   1920: aload #4
    //   1922: iload #8
    //   1924: baload
    //   1925: bipush #-4
    //   1927: isub
    //   1928: i2b
    //   1929: bastore
    //   1930: iload_2
    //   1931: ifeq -> 2055
    //   1934: goto -> 1941
    //   1937: invokestatic a : (Ljava/lang/Throwable;)Ljava/lang/Throwable;
    //   1940: athrow
    //   1941: aload #4
    //   1943: iload #8
    //   1945: baload
    //   1946: bipush #97
    //   1948: if_icmplt -> 2000
    //   1951: goto -> 1958
    //   1954: invokestatic a : (Ljava/lang/Throwable;)Ljava/lang/Throwable;
    //   1957: athrow
    //   1958: aload #4
    //   1960: iload #8
    //   1962: baload
    //   1963: bipush #122
    //   1965: if_icmpgt -> 2000
    //   1968: goto -> 1975
    //   1971: invokestatic a : (Ljava/lang/Throwable;)Ljava/lang/Throwable;
    //   1974: athrow
    //   1975: aload #4
    //   1977: iload #8
    //   1979: aload #4
    //   1981: iload #8
    //   1983: baload
    //   1984: bipush #71
    //   1986: isub
    //   1987: i2b
    //   1988: bastore
    //   1989: iload_2
    //   1990: ifeq -> 2055
    //   1993: goto -> 2000
    //   1996: invokestatic a : (Ljava/lang/Throwable;)Ljava/lang/Throwable;
    //   1999: athrow
    //   2000: aload #4
    //   2002: iload #8
    //   2004: baload
    //   2005: bipush #65
    //   2007: if_icmplt -> 2055
    //   2010: goto -> 2017
    //   2013: invokestatic a : (Ljava/lang/Throwable;)Ljava/lang/Throwable;
    //   2016: athrow
    //   2017: aload #4
    //   2019: iload #8
    //   2021: baload
    //   2022: bipush #90
    //   2024: if_icmpgt -> 2055
    //   2027: goto -> 2034
    //   2030: invokestatic a : (Ljava/lang/Throwable;)Ljava/lang/Throwable;
    //   2033: athrow
    //   2034: aload #4
    //   2036: iload #8
    //   2038: aload #4
    //   2040: iload #8
    //   2042: baload
    //   2043: bipush #65
    //   2045: isub
    //   2046: i2b
    //   2047: bastore
    //   2048: goto -> 2055
    //   2051: invokestatic a : (Ljava/lang/Throwable;)Ljava/lang/Throwable;
    //   2054: athrow
    //   2055: iinc #8, 1
    //   2058: iload_2
    //   2059: ifeq -> 1777
    //   2062: iconst_0
    //   2063: istore #8
    //   2065: iconst_0
    //   2066: istore #9
    //   2068: iload #9
    //   2070: aload #7
    //   2072: arraylength
    //   2073: iconst_2
    //   2074: isub
    //   2075: if_icmpge -> 2184
    //   2078: aload #7
    //   2080: iload #9
    //   2082: aload #4
    //   2084: iload #8
    //   2086: baload
    //   2087: iconst_2
    //   2088: ishl
    //   2089: sipush #255
    //   2092: iand
    //   2093: aload #4
    //   2095: iload #8
    //   2097: iconst_1
    //   2098: iadd
    //   2099: baload
    //   2100: iconst_4
    //   2101: iushr
    //   2102: iconst_3
    //   2103: iand
    //   2104: ior
    //   2105: i2b
    //   2106: bastore
    //   2107: aload #7
    //   2109: iload #9
    //   2111: iconst_1
    //   2112: iadd
    //   2113: aload #4
    //   2115: iload #8
    //   2117: iconst_1
    //   2118: iadd
    //   2119: baload
    //   2120: iconst_4
    //   2121: ishl
    //   2122: sipush #255
    //   2125: iand
    //   2126: aload #4
    //   2128: iload #8
    //   2130: iconst_2
    //   2131: iadd
    //   2132: baload
    //   2133: iconst_2
    //   2134: iushr
    //   2135: bipush #15
    //   2137: iand
    //   2138: ior
    //   2139: i2b
    //   2140: bastore
    //   2141: aload #7
    //   2143: iload #9
    //   2145: iconst_2
    //   2146: iadd
    //   2147: aload #4
    //   2149: iload #8
    //   2151: iconst_2
    //   2152: iadd
    //   2153: baload
    //   2154: bipush #6
    //   2156: ishl
    //   2157: sipush #255
    //   2160: iand
    //   2161: aload #4
    //   2163: iload #8
    //   2165: iconst_3
    //   2166: iadd
    //   2167: baload
    //   2168: bipush #63
    //   2170: iand
    //   2171: ior
    //   2172: i2b
    //   2173: bastore
    //   2174: iinc #8, 4
    //   2177: iinc #9, 3
    //   2180: iload_2
    //   2181: ifeq -> 2068
    //   2184: iload #9
    //   2186: aload #7
    //   2188: arraylength
    //   2189: if_icmpge -> 2228
    //   2192: aload #7
    //   2194: iload #9
    //   2196: aload #4
    //   2198: iload #8
    //   2200: baload
    //   2201: iconst_2
    //   2202: ishl
    //   2203: sipush #255
    //   2206: iand
    //   2207: aload #4
    //   2209: iload #8
    //   2211: iconst_1
    //   2212: iadd
    //   2213: baload
    //   2214: iconst_4
    //   2215: iushr
    //   2216: iconst_3
    //   2217: iand
    //   2218: ior
    //   2219: i2b
    //   2220: bastore
    //   2221: goto -> 2228
    //   2224: invokestatic a : (Ljava/lang/Throwable;)Ljava/lang/Throwable;
    //   2227: athrow
    //   2228: iinc #9, 1
    //   2231: iload #9
    //   2233: aload #7
    //   2235: arraylength
    //   2236: if_icmpge -> 2278
    //   2239: aload #7
    //   2241: iload #9
    //   2243: aload #4
    //   2245: iload #8
    //   2247: iconst_1
    //   2248: iadd
    //   2249: baload
    //   2250: iconst_4
    //   2251: ishl
    //   2252: sipush #255
    //   2255: iand
    //   2256: aload #4
    //   2258: iload #8
    //   2260: iconst_2
    //   2261: iadd
    //   2262: baload
    //   2263: iconst_2
    //   2264: iushr
    //   2265: bipush #15
    //   2267: iand
    //   2268: ior
    //   2269: i2b
    //   2270: bastore
    //   2271: goto -> 2278
    //   2274: invokestatic a : (Ljava/lang/Throwable;)Ljava/lang/Throwable;
    //   2277: athrow
    //   2278: aload #7
    //   2280: astore #5
    //   2282: sipush #16429
    //   2285: new java/math/BigInteger
    //   2288: dup
    //   2289: aload #5
    //   2291: invokespecial <init> : ([B)V
    //   2294: invokevirtual abs : ()Ljava/math/BigInteger;
    //   2297: putstatic burp/Zszz.ZG : Ljava/lang/Object;
    //   2300: sipush #-29027
    //   2303: invokestatic a : (II)Ljava/lang/String;
    //   2306: iconst_1
    //   2307: ldc burp/Zry0
    //   2309: invokevirtual getClassLoader : ()Ljava/lang/ClassLoader;
    //   2312: invokestatic forName : (Ljava/lang/String;ZLjava/lang/ClassLoader;)Ljava/lang/Class;
    //   2315: invokevirtual getDeclaredFields : ()[Ljava/lang/reflect/Field;
    //   2318: astore #4
    //   2320: aload #4
    //   2322: arraylength
    //   2323: istore #5
    //   2325: iconst_0
    //   2326: istore #6
    //   2328: iload #6
    //   2330: iload #5
    //   2332: if_icmpge -> 2470
    //   2335: aload #4
    //   2337: iload #6
    //   2339: aaload
    //   2340: astore #7
    //   2342: aload #7
    //   2344: invokevirtual getModifiers : ()I
    //   2347: invokestatic isStatic : (I)Z
    //   2350: ifne -> 2360
    //   2353: goto -> 2463
    //   2356: invokestatic a : (Ljava/lang/Throwable;)Ljava/lang/Throwable;
    //   2359: athrow
    //   2360: aload #7
    //   2362: invokevirtual getType : ()Ljava/lang/Class;
    //   2365: astore #8
    //   2367: aload #8
    //   2369: ifnull -> 2450
    //   2372: aload #8
    //   2374: invokevirtual isPrimitive : ()Z
    //   2377: ifne -> 2450
    //   2380: goto -> 2387
    //   2383: invokestatic a : (Ljava/lang/Throwable;)Ljava/lang/Throwable;
    //   2386: athrow
    //   2387: aload #8
    //   2389: invokevirtual getPackage : ()Ljava/lang/Package;
    //   2392: ifnull -> 2450
    //   2395: goto -> 2402
    //   2398: invokestatic a : (Ljava/lang/Throwable;)Ljava/lang/Throwable;
    //   2401: athrow
    //   2402: aload #8
    //   2404: invokevirtual getPackage : ()Ljava/lang/Package;
    //   2407: invokevirtual getName : ()Ljava/lang/String;
    //   2410: ifnull -> 2450
    //   2413: goto -> 2420
    //   2416: invokestatic a : (Ljava/lang/Throwable;)Ljava/lang/Throwable;
    //   2419: athrow
    //   2420: aload #8
    //   2422: invokevirtual getPackage : ()Ljava/lang/Package;
    //   2425: invokevirtual getName : ()Ljava/lang/String;
    //   2428: sipush #16436
    //   2431: sipush #20378
    //   2434: invokestatic a : (II)Ljava/lang/String;
    //   2437: invokevirtual startsWith : (Ljava/lang/String;)Z
    //   2440: ifne -> 2450
    //   2443: goto -> 2450
    //   2446: invokestatic a : (Ljava/lang/Throwable;)Ljava/lang/Throwable;
    //   2449: athrow
    //   2450: aload #7
    //   2452: iconst_1
    //   2453: invokevirtual setAccessible : (Z)V
    //   2456: aload #7
    //   2458: aconst_null
    //   2459: invokevirtual get : (Ljava/lang/Object;)Ljava/lang/Object;
    //   2462: pop
    //   2463: iinc #6, 1
    //   2466: iload_2
    //   2467: ifeq -> 2328
    //   2470: sipush #16442
    //   2473: sipush #-13167
    //   2476: invokestatic a : (II)Ljava/lang/String;
    //   2479: invokestatic forName : (Ljava/lang/String;)Ljava/lang/Class;
    //   2482: invokevirtual getDeclaredMethods : ()[Ljava/lang/reflect/Method;
    //   2485: astore #4
    //   2487: aload #4
    //   2489: arraylength
    //   2490: istore #5
    //   2492: iconst_0
    //   2493: istore #6
    //   2495: iload #6
    //   2497: iload #5
    //   2499: if_icmpge -> 2632
    //   2502: aload #4
    //   2504: iload #6
    //   2506: aaload
    //   2507: astore #7
    //   2509: aload #7
    //   2511: invokevirtual getParameterTypes : ()[Ljava/lang/Class;
    //   2514: pop
    //   2515: aload #7
    //   2517: invokevirtual getModifiers : ()I
    //   2520: invokestatic isStatic : (I)Z
    //   2523: ifeq -> 2618
    //   2526: aload #7
    //   2528: invokevirtual getParameterTypes : ()[Ljava/lang/Class;
    //   2531: arraylength
    //   2532: iconst_2
    //   2533: if_icmpne -> 2618
    //   2536: goto -> 2543
    //   2539: invokestatic a : (Ljava/lang/Throwable;)Ljava/lang/Throwable;
    //   2542: athrow
    //   2543: aload #7
    //   2545: invokevirtual getReturnType : ()Ljava/lang/Class;
    //   2548: getstatic java/lang/Void.TYPE : Ljava/lang/Class;
    //   2551: invokevirtual equals : (Ljava/lang/Object;)Z
    //   2554: ifeq -> 2618
    //   2557: goto -> 2564
    //   2560: invokestatic a : (Ljava/lang/Throwable;)Ljava/lang/Throwable;
    //   2563: athrow
    //   2564: aload #7
    //   2566: iconst_1
    //   2567: invokevirtual setAccessible : (Z)V
    //   2570: aload #7
    //   2572: aconst_null
    //   2573: iconst_2
    //   2574: anewarray java/lang/Object
    //   2577: dup
    //   2578: iconst_0
    //   2579: aload_0
    //   2580: aastore
    //   2581: dup
    //   2582: iconst_1
    //   2583: aload_1
    //   2584: ifnonnull -> 2602
    //   2587: goto -> 2594
    //   2590: invokestatic a : (Ljava/lang/Throwable;)Ljava/lang/Throwable;
    //   2593: athrow
    //   2594: aload_1
    //   2595: goto -> 2609
    //   2598: invokestatic a : (Ljava/lang/Throwable;)Ljava/lang/Throwable;
    //   2601: athrow
    //   2602: aload_1
    //   2603: checkcast [B
    //   2606: invokevirtual clone : ()Ljava/lang/Object;
    //   2609: aastore
    //   2610: invokevirtual invoke : (Ljava/lang/Object;[Ljava/lang/Object;)Ljava/lang/Object;
    //   2613: pop
    //   2614: iload_2
    //   2615: ifeq -> 2632
    //   2618: iinc #6, 1
    //   2621: iload_2
    //   2622: ifeq -> 2495
    //   2625: goto -> 2632
    //   2628: invokestatic a : (Ljava/lang/Throwable;)Ljava/lang/Throwable;
    //   2631: athrow
    //   2632: getstatic burp/Zty2.Zl : Ljava/lang/Object;
    //   2635: checkcast java/math/BigInteger
    //   2638: invokevirtual toByteArray : ()[B
    //   2641: astore #4
    //   2643: aload #4
    //   2645: arraylength
    //   2646: iconst_2
    //   2647: iadd
    //   2648: newarray byte
    //   2650: astore #6
    //   2652: iconst_0
    //   2653: istore #7
    //   2655: iload #7
    //   2657: aload #4
    //   2659: arraylength
    //   2660: if_icmpge -> 2680
    //   2663: aload #6
    //   2665: iload #7
    //   2667: aload #4
    //   2669: iload #7
    //   2671: baload
    //   2672: bastore
    //   2673: iinc #7, 1
    //   2676: iload_2
    //   2677: ifeq -> 2655
    //   2680: aload #6
    //   2682: arraylength
    //   2683: iconst_3
    //   2684: idiv
    //   2685: iconst_4
    //   2686: imul
    //   2687: newarray byte
    //   2689: astore #5
    //   2691: iconst_0
    //   2692: istore #7
    //   2694: iconst_0
    //   2695: istore #8
    //   2697: iload #7
    //   2699: aload #4
    //   2701: arraylength
    //   2702: if_icmpge -> 2813
    //   2705: aload #5
    //   2707: iload #8
    //   2709: aload #6
    //   2711: iload #7
    //   2713: baload
    //   2714: iconst_2
    //   2715: iushr
    //   2716: bipush #63
    //   2718: iand
    //   2719: i2b
    //   2720: bastore
    //   2721: aload #5
    //   2723: iload #8
    //   2725: iconst_1
    //   2726: iadd
    //   2727: aload #6
    //   2729: iload #7
    //   2731: iconst_1
    //   2732: iadd
    //   2733: baload
    //   2734: iconst_4
    //   2735: iushr
    //   2736: bipush #15
    //   2738: iand
    //   2739: aload #6
    //   2741: iload #7
    //   2743: baload
    //   2744: iconst_4
    //   2745: ishl
    //   2746: bipush #63
    //   2748: iand
    //   2749: ior
    //   2750: i2b
    //   2751: bastore
    //   2752: aload #5
    //   2754: iload #8
    //   2756: iconst_2
    //   2757: iadd
    //   2758: aload #6
    //   2760: iload #7
    //   2762: iconst_2
    //   2763: iadd
    //   2764: baload
    //   2765: bipush #6
    //   2767: iushr
    //   2768: iconst_3
    //   2769: iand
    //   2770: aload #6
    //   2772: iload #7
    //   2774: iconst_1
    //   2775: iadd
    //   2776: baload
    //   2777: iconst_2
    //   2778: ishl
    //   2779: bipush #63
    //   2781: iand
    //   2782: ior
    //   2783: i2b
    //   2784: bastore
    //   2785: aload #5
    //   2787: iload #8
    //   2789: iconst_3
    //   2790: iadd
    //   2791: aload #6
    //   2793: iload #7
    //   2795: iconst_2
    //   2796: iadd
    //   2797: baload
    //   2798: bipush #63
    //   2800: iand
    //   2801: i2b
    //   2802: bastore
    //   2803: iinc #7, 3
    //   2806: iinc #8, 4
    //   2809: iload_2
    //   2810: ifeq -> 2697
    //   2813: iconst_0
    //   2814: istore #7
    //   2816: iload #7
    //   2818: aload #5
    //   2820: arraylength
    //   2821: if_icmpge -> 3005
    //   2824: aload #5
    //   2826: iload #7
    //   2828: baload
    //   2829: bipush #26
    //   2831: if_icmpge -> 2859
    //   2834: aload #5
    //   2836: iload #7
    //   2838: aload #5
    //   2840: iload #7
    //   2842: baload
    //   2843: bipush #65
    //   2845: iadd
    //   2846: i2b
    //   2847: bastore
    //   2848: iload_2
    //   2849: ifeq -> 2998
    //   2852: goto -> 2859
    //   2855: invokestatic a : (Ljava/lang/Throwable;)Ljava/lang/Throwable;
    //   2858: athrow
    //   2859: aload #5
    //   2861: iload #7
    //   2863: baload
    //   2864: bipush #52
    //   2866: if_icmpge -> 2904
    //   2869: goto -> 2876
    //   2872: invokestatic a : (Ljava/lang/Throwable;)Ljava/lang/Throwable;
    //   2875: athrow
    //   2876: aload #5
    //   2878: iload #7
    //   2880: aload #5
    //   2882: iload #7
    //   2884: baload
    //   2885: bipush #97
    //   2887: iadd
    //   2888: bipush #26
    //   2890: isub
    //   2891: i2b
    //   2892: bastore
    //   2893: iload_2
    //   2894: ifeq -> 2998
    //   2897: goto -> 2904
    //   2900: invokestatic a : (Ljava/lang/Throwable;)Ljava/lang/Throwable;
    //   2903: athrow
    //   2904: aload #5
    //   2906: iload #7
    //   2908: baload
    //   2909: bipush #62
    //   2911: if_icmpge -> 2949
    //   2914: goto -> 2921
    //   2917: invokestatic a : (Ljava/lang/Throwable;)Ljava/lang/Throwable;
    //   2920: athrow
    //   2921: aload #5
    //   2923: iload #7
    //   2925: aload #5
    //   2927: iload #7
    //   2929: baload
    //   2930: bipush #48
    //   2932: iadd
    //   2933: bipush #52
    //   2935: isub
    //   2936: i2b
    //   2937: bastore
    //   2938: iload_2
    //   2939: ifeq -> 2998
    //   2942: goto -> 2949
    //   2945: invokestatic a : (Ljava/lang/Throwable;)Ljava/lang/Throwable;
    //   2948: athrow
    //   2949: aload #5
    //   2951: iload #7
    //   2953: baload
    //   2954: bipush #63
    //   2956: if_icmpge -> 2984
    //   2959: goto -> 2966
    //   2962: invokestatic a : (Ljava/lang/Throwable;)Ljava/lang/Throwable;
    //   2965: athrow
    //   2966: aload #5
    //   2968: iload #7
    //   2970: bipush #43
    //   2972: bastore
    //   2973: iload_2
    //   2974: ifeq -> 2998
    //   2977: goto -> 2984
    //   2980: invokestatic a : (Ljava/lang/Throwable;)Ljava/lang/Throwable;
    //   2983: athrow
    //   2984: aload #5
    //   2986: iload #7
    //   2988: bipush #47
    //   2990: bastore
    //   2991: goto -> 2998
    //   2994: invokestatic a : (Ljava/lang/Throwable;)Ljava/lang/Throwable;
    //   2997: athrow
    //   2998: iinc #7, 1
    //   3001: iload_2
    //   3002: ifeq -> 2816
    //   3005: aload #5
    //   3007: arraylength
    //   3008: iconst_1
    //   3009: isub
    //   3010: istore #7
    //   3012: iload #7
    //   3014: aload #4
    //   3016: arraylength
    //   3017: iconst_4
    //   3018: imul
    //   3019: iconst_3
    //   3020: idiv
    //   3021: if_icmple -> 3038
    //   3024: aload #5
    //   3026: iload #7
    //   3028: bipush #61
    //   3030: bastore
    //   3031: iinc #7, -1
    //   3034: iload_2
    //   3035: ifeq -> 3012
    //   3038: iconst_0
    //   3039: istore #4
    //   3041: getstatic burp/Zevf.ZL : Ljava/lang/String;
    //   3044: getstatic burp/Zsk4.Ze : Ljava/lang/Object;
    //   3047: checkcast java/math/BigInteger
    //   3050: invokevirtual intValue : ()I
    //   3053: bipush #32
    //   3055: irem
    //   3056: invokestatic abs : (I)I
    //   3059: invokevirtual charAt : (I)C
    //   3062: getstatic burp/Zsyu.ZJ : Ljava/lang/String;
    //   3065: getstatic burp/Zsmn.Zq : Ljava/lang/Object;
    //   3068: checkcast java/math/BigInteger
    //   3071: invokevirtual intValue : ()I
    //   3074: bipush #32
    //   3076: irem
    //   3077: invokestatic abs : (I)I
    //   3080: invokevirtual charAt : (I)C
    //   3083: if_icmpgt -> 3428
    //   3086: sipush #16437
    //   3089: sipush #-16275
    //   3092: invokestatic a : (II)Ljava/lang/String;
    //   3095: iconst_1
    //   3096: ldc burp/Ze4x
    //   3098: invokevirtual getClassLoader : ()Ljava/lang/ClassLoader;
    //   3101: invokestatic forName : (Ljava/lang/String;ZLjava/lang/ClassLoader;)Ljava/lang/Class;
    //   3104: invokevirtual getDeclaredFields : ()[Ljava/lang/reflect/Field;
    //   3107: astore #5
    //   3109: aload #5
    //   3111: arraylength
    //   3112: istore #6
    //   3114: iconst_0
    //   3115: istore #7
    //   3117: iload #7
    //   3119: iload #6
    //   3121: if_icmpge -> 3259
    //   3124: aload #5
    //   3126: iload #7
    //   3128: aaload
    //   3129: astore #8
    //   3131: aload #8
    //   3133: invokevirtual getModifiers : ()I
    //   3136: invokestatic isStatic : (I)Z
    //   3139: ifne -> 3149
    //   3142: goto -> 3252
    //   3145: invokestatic a : (Ljava/lang/Throwable;)Ljava/lang/Throwable;
    //   3148: athrow
    //   3149: aload #8
    //   3151: invokevirtual getType : ()Ljava/lang/Class;
    //   3154: astore #9
    //   3156: aload #9
    //   3158: ifnull -> 3239
    //   3161: aload #9
    //   3163: invokevirtual isPrimitive : ()Z
    //   3166: ifne -> 3239
    //   3169: goto -> 3176
    //   3172: invokestatic a : (Ljava/lang/Throwable;)Ljava/lang/Throwable;
    //   3175: athrow
    //   3176: aload #9
    //   3178: invokevirtual getPackage : ()Ljava/lang/Package;
    //   3181: ifnull -> 3239
    //   3184: goto -> 3191
    //   3187: invokestatic a : (Ljava/lang/Throwable;)Ljava/lang/Throwable;
    //   3190: athrow
    //   3191: aload #9
    //   3193: invokevirtual getPackage : ()Ljava/lang/Package;
    //   3196: invokevirtual getName : ()Ljava/lang/String;
    //   3199: ifnull -> 3239
    //   3202: goto -> 3209
    //   3205: invokestatic a : (Ljava/lang/Throwable;)Ljava/lang/Throwable;
    //   3208: athrow
    //   3209: aload #9
    //   3211: invokevirtual getPackage : ()Ljava/lang/Package;
    //   3214: invokevirtual getName : ()Ljava/lang/String;
    //   3217: sipush #16439
    //   3220: sipush #11030
    //   3223: invokestatic a : (II)Ljava/lang/String;
    //   3226: invokevirtual startsWith : (Ljava/lang/String;)Z
    //   3229: ifne -> 3239
    //   3232: goto -> 3239
    //   3235: invokestatic a : (Ljava/lang/Throwable;)Ljava/lang/Throwable;
    //   3238: athrow
    //   3239: aload #8
    //   3241: iconst_1
    //   3242: invokevirtual setAccessible : (Z)V
    //   3245: aload #8
    //   3247: aconst_null
    //   3248: invokevirtual get : (Ljava/lang/Object;)Ljava/lang/Object;
    //   3251: pop
    //   3252: iinc #7, 1
    //   3255: iload_2
    //   3256: ifeq -> 3117
    //   3259: sipush #16447
    //   3262: sipush #-5277
    //   3265: invokestatic a : (II)Ljava/lang/String;
    //   3268: invokestatic forName : (Ljava/lang/String;)Ljava/lang/Class;
    //   3271: invokevirtual getDeclaredMethods : ()[Ljava/lang/reflect/Method;
    //   3274: astore #5
    //   3276: aload #5
    //   3278: arraylength
    //   3279: istore #6
    //   3281: iconst_0
    //   3282: istore #7
    //   3284: iload #7
    //   3286: iload #6
    //   3288: if_icmpge -> 3425
    //   3291: aload #5
    //   3293: iload #7
    //   3295: aaload
    //   3296: astore #8
    //   3298: aload #8
    //   3300: invokevirtual getParameterTypes : ()[Ljava/lang/Class;
    //   3303: pop
    //   3304: aload #8
    //   3306: invokevirtual getModifiers : ()I
    //   3309: invokestatic isStatic : (I)Z
    //   3312: ifeq -> 3411
    //   3315: aload #8
    //   3317: invokevirtual getParameterTypes : ()[Ljava/lang/Class;
    //   3320: arraylength
    //   3321: iconst_2
    //   3322: if_icmpne -> 3411
    //   3325: goto -> 3332
    //   3328: invokestatic a : (Ljava/lang/Throwable;)Ljava/lang/Throwable;
    //   3331: athrow
    //   3332: aload #8
    //   3334: invokevirtual getReturnType : ()Ljava/lang/Class;
    //   3337: getstatic java/lang/Boolean.TYPE : Ljava/lang/Class;
    //   3340: if_acmpne -> 3411
    //   3343: goto -> 3350
    //   3346: invokestatic a : (Ljava/lang/Throwable;)Ljava/lang/Throwable;
    //   3349: athrow
    //   3350: aload #8
    //   3352: iconst_1
    //   3353: invokevirtual setAccessible : (Z)V
    //   3356: aload #8
    //   3358: aconst_null
    //   3359: iconst_2
    //   3360: anewarray java/lang/Object
    //   3363: dup
    //   3364: iconst_0
    //   3365: aload_0
    //   3366: aastore
    //   3367: dup
    //   3368: iconst_1
    //   3369: aload_1
    //   3370: ifnonnull -> 3388
    //   3373: goto -> 3380
    //   3376: invokestatic a : (Ljava/lang/Throwable;)Ljava/lang/Throwable;
    //   3379: athrow
    //   3380: aload_1
    //   3381: goto -> 3395
    //   3384: invokestatic a : (Ljava/lang/Throwable;)Ljava/lang/Throwable;
    //   3387: athrow
    //   3388: aload_1
    //   3389: checkcast [B
    //   3392: invokevirtual clone : ()Ljava/lang/Object;
    //   3395: aastore
    //   3396: invokevirtual invoke : (Ljava/lang/Object;[Ljava/lang/Object;)Ljava/lang/Object;
    //   3399: checkcast java/lang/Boolean
    //   3402: invokevirtual booleanValue : ()Z
    //   3405: istore #4
    //   3407: iload_2
    //   3408: ifeq -> 3425
    //   3411: iinc #7, 1
    //   3414: iload_2
    //   3415: ifeq -> 3284
    //   3418: goto -> 3425
    //   3421: invokestatic a : (Ljava/lang/Throwable;)Ljava/lang/Throwable;
    //   3424: athrow
    //   3425: goto -> 3767
    //   3428: sipush #16438
    //   3431: sipush #28416
    //   3434: invokestatic a : (II)Ljava/lang/String;
    //   3437: iconst_1
    //   3438: ldc burp/Zs8s
    //   3440: invokevirtual getClassLoader : ()Ljava/lang/ClassLoader;
    //   3443: invokestatic forName : (Ljava/lang/String;ZLjava/lang/ClassLoader;)Ljava/lang/Class;
    //   3446: invokevirtual getDeclaredFields : ()[Ljava/lang/reflect/Field;
    //   3449: astore #5
    //   3451: aload #5
    //   3453: arraylength
    //   3454: istore #6
    //   3456: iconst_0
    //   3457: istore #7
    //   3459: iload #7
    //   3461: iload #6
    //   3463: if_icmpge -> 3601
    //   3466: aload #5
    //   3468: iload #7
    //   3470: aaload
    //   3471: astore #8
    //   3473: aload #8
    //   3475: invokevirtual getModifiers : ()I
    //   3478: invokestatic isStatic : (I)Z
    //   3481: ifne -> 3491
    //   3484: goto -> 3594
    //   3487: invokestatic a : (Ljava/lang/Throwable;)Ljava/lang/Throwable;
    //   3490: athrow
    //   3491: aload #8
    //   3493: invokevirtual getType : ()Ljava/lang/Class;
    //   3496: astore #9
    //   3498: aload #9
    //   3500: ifnull -> 3581
    //   3503: aload #9
    //   3505: invokevirtual isPrimitive : ()Z
    //   3508: ifne -> 3581
    //   3511: goto -> 3518
    //   3514: invokestatic a : (Ljava/lang/Throwable;)Ljava/lang/Throwable;
    //   3517: athrow
    //   3518: aload #9
    //   3520: invokevirtual getPackage : ()Ljava/lang/Package;
    //   3523: ifnull -> 3581
    //   3526: goto -> 3533
    //   3529: invokestatic a : (Ljava/lang/Throwable;)Ljava/lang/Throwable;
    //   3532: athrow
    //   3533: aload #9
    //   3535: invokevirtual getPackage : ()Ljava/lang/Package;
    //   3538: invokevirtual getName : ()Ljava/lang/String;
    //   3541: ifnull -> 3581
    //   3544: goto -> 3551
    //   3547: invokestatic a : (Ljava/lang/Throwable;)Ljava/lang/Throwable;
    //   3550: athrow
    //   3551: aload #9
    //   3553: invokevirtual getPackage : ()Ljava/lang/Package;
    //   3556: invokevirtual getName : ()Ljava/lang/String;
    //   3559: sipush #16439
    //   3562: sipush #11030
    //   3565: invokestatic a : (II)Ljava/lang/String;
    //   3568: invokevirtual startsWith : (Ljava/lang/String;)Z
    //   3571: ifne -> 3581
    //   3574: goto -> 3581
    //   3577: invokestatic a : (Ljava/lang/Throwable;)Ljava/lang/Throwable;
    //   3580: athrow
    //   3581: aload #8
    //   3583: iconst_1
    //   3584: invokevirtual setAccessible : (Z)V
    //   3587: aload #8
    //   3589: aconst_null
    //   3590: invokevirtual get : (Ljava/lang/Object;)Ljava/lang/Object;
    //   3593: pop
    //   3594: iinc #7, 1
    //   3597: iload_2
    //   3598: ifeq -> 3459
    //   3601: sipush #16440
    //   3604: sipush #-28464
    //   3607: invokestatic a : (II)Ljava/lang/String;
    //   3610: invokestatic forName : (Ljava/lang/String;)Ljava/lang/Class;
    //   3613: invokevirtual getDeclaredMethods : ()[Ljava/lang/reflect/Method;
    //   3616: astore #5
    //   3618: aload #5
    //   3620: arraylength
    //   3621: istore #6
    //   3623: iconst_0
    //   3624: istore #7
    //   3626: iload #7
    //   3628: iload #6
    //   3630: if_icmpge -> 3767
    //   3633: aload #5
    //   3635: iload #7
    //   3637: aaload
    //   3638: astore #8
    //   3640: aload #8
    //   3642: invokevirtual getParameterTypes : ()[Ljava/lang/Class;
    //   3645: pop
    //   3646: aload #8
    //   3648: invokevirtual getModifiers : ()I
    //   3651: invokestatic isStatic : (I)Z
    //   3654: ifeq -> 3753
    //   3657: aload #8
    //   3659: invokevirtual getParameterTypes : ()[Ljava/lang/Class;
    //   3662: arraylength
    //   3663: iconst_2
    //   3664: if_icmpne -> 3753
    //   3667: goto -> 3674
    //   3670: invokestatic a : (Ljava/lang/Throwable;)Ljava/lang/Throwable;
    //   3673: athrow
    //   3674: aload #8
    //   3676: invokevirtual getReturnType : ()Ljava/lang/Class;
    //   3679: getstatic java/lang/Boolean.TYPE : Ljava/lang/Class;
    //   3682: if_acmpne -> 3753
    //   3685: goto -> 3692
    //   3688: invokestatic a : (Ljava/lang/Throwable;)Ljava/lang/Throwable;
    //   3691: athrow
    //   3692: aload #8
    //   3694: iconst_1
    //   3695: invokevirtual setAccessible : (Z)V
    //   3698: aload #8
    //   3700: aconst_null
    //   3701: iconst_2
    //   3702: anewarray java/lang/Object
    //   3705: dup
    //   3706: iconst_0
    //   3707: aload_0
    //   3708: aastore
    //   3709: dup
    //   3710: iconst_1
    //   3711: aload_1
    //   3712: ifnonnull -> 3730
    //   3715: goto -> 3722
    //   3718: invokestatic a : (Ljava/lang/Throwable;)Ljava/lang/Throwable;
    //   3721: athrow
    //   3722: aload_1
    //   3723: goto -> 3737
    //   3726: invokestatic a : (Ljava/lang/Throwable;)Ljava/lang/Throwable;
    //   3729: athrow
    //   3730: aload_1
    //   3731: checkcast [B
    //   3734: invokevirtual clone : ()Ljava/lang/Object;
    //   3737: aastore
    //   3738: invokevirtual invoke : (Ljava/lang/Object;[Ljava/lang/Object;)Ljava/lang/Object;
    //   3741: checkcast java/lang/Boolean
    //   3744: invokevirtual booleanValue : ()Z
    //   3747: istore #4
    //   3749: iload_2
    //   3750: ifeq -> 3767
    //   3753: iinc #7, 1
    //   3756: iload_2
    //   3757: ifeq -> 3626
    //   3760: goto -> 3767
    //   3763: invokestatic a : (Ljava/lang/Throwable;)Ljava/lang/Throwable;
    //   3766: athrow
    //   3767: iload #4
    //   3769: ifeq -> 3775
    //   3772: iload #4
    //   3774: ireturn
    //   3775: getstatic burp/Zlpu.ZA : Ljava/lang/String;
    //   3778: getstatic burp/Zg2z.ZU : Ljava/lang/Object;
    //   3781: checkcast java/math/BigInteger
    //   3784: invokevirtual intValue : ()I
    //   3787: bipush #32
    //   3789: irem
    //   3790: invokestatic abs : (I)I
    //   3793: invokevirtual charAt : (I)C
    //   3796: getstatic burp/Zvi.ZR : Ljava/lang/String;
    //   3799: getstatic burp/Zs9x.Zo : Ljava/lang/Object;
    //   3802: checkcast java/math/BigInteger
    //   3805: invokevirtual intValue : ()I
    //   3808: bipush #32
    //   3810: irem
    //   3811: invokestatic abs : (I)I
    //   3814: invokevirtual charAt : (I)C
    //   3817: if_icmpgt -> 4163
    //   3820: sipush #16426
    //   3823: sipush #-12514
    //   3826: invokestatic a : (II)Ljava/lang/String;
    //   3829: iconst_1
    //   3830: ldc burp/Zmgl
    //   3832: invokevirtual getClassLoader : ()Ljava/lang/ClassLoader;
    //   3835: invokestatic forName : (Ljava/lang/String;ZLjava/lang/ClassLoader;)Ljava/lang/Class;
    //   3838: invokevirtual getDeclaredFields : ()[Ljava/lang/reflect/Field;
    //   3841: astore #5
    //   3843: aload #5
    //   3845: arraylength
    //   3846: istore #6
    //   3848: iconst_0
    //   3849: istore #7
    //   3851: iload #7
    //   3853: iload #6
    //   3855: if_icmpge -> 3993
    //   3858: aload #5
    //   3860: iload #7
    //   3862: aaload
    //   3863: astore #8
    //   3865: aload #8
    //   3867: invokevirtual getModifiers : ()I
    //   3870: invokestatic isStatic : (I)Z
    //   3873: ifne -> 3883
    //   3876: goto -> 3986
    //   3879: invokestatic a : (Ljava/lang/Throwable;)Ljava/lang/Throwable;
    //   3882: athrow
    //   3883: aload #8
    //   3885: invokevirtual getType : ()Ljava/lang/Class;
    //   3888: astore #9
    //   3890: aload #9
    //   3892: ifnull -> 3973
    //   3895: aload #9
    //   3897: invokevirtual isPrimitive : ()Z
    //   3900: ifne -> 3973
    //   3903: goto -> 3910
    //   3906: invokestatic a : (Ljava/lang/Throwable;)Ljava/lang/Throwable;
    //   3909: athrow
    //   3910: aload #9
    //   3912: invokevirtual getPackage : ()Ljava/lang/Package;
    //   3915: ifnull -> 3973
    //   3918: goto -> 3925
    //   3921: invokestatic a : (Ljava/lang/Throwable;)Ljava/lang/Throwable;
    //   3924: athrow
    //   3925: aload #9
    //   3927: invokevirtual getPackage : ()Ljava/lang/Package;
    //   3930: invokevirtual getName : ()Ljava/lang/String;
    //   3933: ifnull -> 3973
    //   3936: goto -> 3943
    //   3939: invokestatic a : (Ljava/lang/Throwable;)Ljava/lang/Throwable;
    //   3942: athrow
    //   3943: aload #9
    //   3945: invokevirtual getPackage : ()Ljava/lang/Package;
    //   3948: invokevirtual getName : ()Ljava/lang/String;
    //   3951: sipush #16439
    //   3954: sipush #11030
    //   3957: invokestatic a : (II)Ljava/lang/String;
    //   3960: invokevirtual startsWith : (Ljava/lang/String;)Z
    //   3963: ifne -> 3973
    //   3966: goto -> 3973
    //   3969: invokestatic a : (Ljava/lang/Throwable;)Ljava/lang/Throwable;
    //   3972: athrow
    //   3973: aload #8
    //   3975: iconst_1
    //   3976: invokevirtual setAccessible : (Z)V
    //   3979: aload #8
    //   3981: aconst_null
    //   3982: invokevirtual get : (Ljava/lang/Object;)Ljava/lang/Object;
    //   3985: pop
    //   3986: iinc #7, 1
    //   3989: iload_2
    //   3990: ifeq -> 3851
    //   3993: sipush #16435
    //   3996: sipush #-22216
    //   3999: invokestatic a : (II)Ljava/lang/String;
    //   4002: invokestatic forName : (Ljava/lang/String;)Ljava/lang/Class;
    //   4005: invokevirtual getDeclaredMethods : ()[Ljava/lang/reflect/Method;
    //   4008: astore #5
    //   4010: aload #5
    //   4012: arraylength
    //   4013: istore #6
    //   4015: iconst_0
    //   4016: istore #7
    //   4018: iload #7
    //   4020: iload #6
    //   4022: if_icmpge -> 4159
    //   4025: aload #5
    //   4027: iload #7
    //   4029: aaload
    //   4030: astore #8
    //   4032: aload #8
    //   4034: invokevirtual getParameterTypes : ()[Ljava/lang/Class;
    //   4037: pop
    //   4038: aload #8
    //   4040: invokevirtual getModifiers : ()I
    //   4043: invokestatic isStatic : (I)Z
    //   4046: ifeq -> 4145
    //   4049: aload #8
    //   4051: invokevirtual getParameterTypes : ()[Ljava/lang/Class;
    //   4054: arraylength
    //   4055: iconst_2
    //   4056: if_icmpne -> 4145
    //   4059: goto -> 4066
    //   4062: invokestatic a : (Ljava/lang/Throwable;)Ljava/lang/Throwable;
    //   4065: athrow
    //   4066: aload #8
    //   4068: invokevirtual getReturnType : ()Ljava/lang/Class;
    //   4071: getstatic java/lang/Boolean.TYPE : Ljava/lang/Class;
    //   4074: if_acmpne -> 4145
    //   4077: goto -> 4084
    //   4080: invokestatic a : (Ljava/lang/Throwable;)Ljava/lang/Throwable;
    //   4083: athrow
    //   4084: aload #8
    //   4086: iconst_1
    //   4087: invokevirtual setAccessible : (Z)V
    //   4090: aload #8
    //   4092: aconst_null
    //   4093: iconst_2
    //   4094: anewarray java/lang/Object
    //   4097: dup
    //   4098: iconst_0
    //   4099: aload_0
    //   4100: aastore
    //   4101: dup
    //   4102: iconst_1
    //   4103: aload_1
    //   4104: ifnonnull -> 4122
    //   4107: goto -> 4114
    //   4110: invokestatic a : (Ljava/lang/Throwable;)Ljava/lang/Throwable;
    //   4113: athrow
    //   4114: aload_1
    //   4115: goto -> 4129
    //   4118: invokestatic a : (Ljava/lang/Throwable;)Ljava/lang/Throwable;
    //   4121: athrow
    //   4122: aload_1
    //   4123: checkcast [B
    //   4126: invokevirtual clone : ()Ljava/lang/Object;
    //   4129: aastore
    //   4130: invokevirtual invoke : (Ljava/lang/Object;[Ljava/lang/Object;)Ljava/lang/Object;
    //   4133: checkcast java/lang/Boolean
    //   4136: invokevirtual booleanValue : ()Z
    //   4139: istore #4
    //   4141: iload_2
    //   4142: ifeq -> 4159
    //   4145: iinc #7, 1
    //   4148: iload_2
    //   4149: ifeq -> 4018
    //   4152: goto -> 4159
    //   4155: invokestatic a : (Ljava/lang/Throwable;)Ljava/lang/Throwable;
    //   4158: athrow
    //   4159: iload_2
    //   4160: ifeq -> 4502
    //   4163: sipush #16443
    //   4166: sipush #27949
    //   4169: invokestatic a : (II)Ljava/lang/String;
    //   4172: iconst_1
    //   4173: ldc burp/Ztjh
    //   4175: invokevirtual getClassLoader : ()Ljava/lang/ClassLoader;
    //   4178: invokestatic forName : (Ljava/lang/String;ZLjava/lang/ClassLoader;)Ljava/lang/Class;
    //   4181: invokevirtual getDeclaredFields : ()[Ljava/lang/reflect/Field;
    //   4184: astore #5
    //   4186: aload #5
    //   4188: arraylength
    //   4189: istore #6
    //   4191: iconst_0
    //   4192: istore #7
    //   4194: iload #7
    //   4196: iload #6
    //   4198: if_icmpge -> 4336
    //   4201: aload #5
    //   4203: iload #7
    //   4205: aaload
    //   4206: astore #8
    //   4208: aload #8
    //   4210: invokevirtual getModifiers : ()I
    //   4213: invokestatic isStatic : (I)Z
    //   4216: ifne -> 4226
    //   4219: goto -> 4329
    //   4222: invokestatic a : (Ljava/lang/Throwable;)Ljava/lang/Throwable;
    //   4225: athrow
    //   4226: aload #8
    //   4228: invokevirtual getType : ()Ljava/lang/Class;
    //   4231: astore #9
    //   4233: aload #9
    //   4235: ifnull -> 4316
    //   4238: aload #9
    //   4240: invokevirtual isPrimitive : ()Z
    //   4243: ifne -> 4316
    //   4246: goto -> 4253
    //   4249: invokestatic a : (Ljava/lang/Throwable;)Ljava/lang/Throwable;
    //   4252: athrow
    //   4253: aload #9
    //   4255: invokevirtual getPackage : ()Ljava/lang/Package;
    //   4258: ifnull -> 4316
    //   4261: goto -> 4268
    //   4264: invokestatic a : (Ljava/lang/Throwable;)Ljava/lang/Throwable;
    //   4267: athrow
    //   4268: aload #9
    //   4270: invokevirtual getPackage : ()Ljava/lang/Package;
    //   4273: invokevirtual getName : ()Ljava/lang/String;
    //   4276: ifnull -> 4316
    //   4279: goto -> 4286
    //   4282: invokestatic a : (Ljava/lang/Throwable;)Ljava/lang/Throwable;
    //   4285: athrow
    //   4286: aload #9
    //   4288: invokevirtual getPackage : ()Ljava/lang/Package;
    //   4291: invokevirtual getName : ()Ljava/lang/String;
    //   4294: sipush #16439
    //   4297: sipush #11030
    //   4300: invokestatic a : (II)Ljava/lang/String;
    //   4303: invokevirtual startsWith : (Ljava/lang/String;)Z
    //   4306: ifne -> 4316
    //   4309: goto -> 4316
    //   4312: invokestatic a : (Ljava/lang/Throwable;)Ljava/lang/Throwable;
    //   4315: athrow
    //   4316: aload #8
    //   4318: iconst_1
    //   4319: invokevirtual setAccessible : (Z)V
    //   4322: aload #8
    //   4324: aconst_null
    //   4325: invokevirtual get : (Ljava/lang/Object;)Ljava/lang/Object;
    //   4328: pop
    //   4329: iinc #7, 1
    //   4332: iload_2
    //   4333: ifeq -> 4194
    //   4336: sipush #16427
    //   4339: sipush #-28222
    //   4342: invokestatic a : (II)Ljava/lang/String;
    //   4345: invokestatic forName : (Ljava/lang/String;)Ljava/lang/Class;
    //   4348: invokevirtual getDeclaredMethods : ()[Ljava/lang/reflect/Method;
    //   4351: astore #5
    //   4353: aload #5
    //   4355: arraylength
    //   4356: istore #6
    //   4358: iconst_0
    //   4359: istore #7
    //   4361: iload #7
    //   4363: iload #6
    //   4365: if_icmpge -> 4502
    //   4368: aload #5
    //   4370: iload #7
    //   4372: aaload
    //   4373: astore #8
    //   4375: aload #8
    //   4377: invokevirtual getParameterTypes : ()[Ljava/lang/Class;
    //   4380: pop
    //   4381: aload #8
    //   4383: invokevirtual getModifiers : ()I
    //   4386: invokestatic isStatic : (I)Z
    //   4389: ifeq -> 4488
    //   4392: aload #8
    //   4394: invokevirtual getParameterTypes : ()[Ljava/lang/Class;
    //   4397: arraylength
    //   4398: iconst_2
    //   4399: if_icmpne -> 4488
    //   4402: goto -> 4409
    //   4405: invokestatic a : (Ljava/lang/Throwable;)Ljava/lang/Throwable;
    //   4408: athrow
    //   4409: aload #8
    //   4411: invokevirtual getReturnType : ()Ljava/lang/Class;
    //   4414: getstatic java/lang/Boolean.TYPE : Ljava/lang/Class;
    //   4417: if_acmpne -> 4488
    //   4420: goto -> 4427
    //   4423: invokestatic a : (Ljava/lang/Throwable;)Ljava/lang/Throwable;
    //   4426: athrow
    //   4427: aload #8
    //   4429: iconst_1
    //   4430: invokevirtual setAccessible : (Z)V
    //   4433: aload #8
    //   4435: aconst_null
    //   4436: iconst_2
    //   4437: anewarray java/lang/Object
    //   4440: dup
    //   4441: iconst_0
    //   4442: aload_0
    //   4443: aastore
    //   4444: dup
    //   4445: iconst_1
    //   4446: aload_1
    //   4447: ifnonnull -> 4465
    //   4450: goto -> 4457
    //   4453: invokestatic a : (Ljava/lang/Throwable;)Ljava/lang/Throwable;
    //   4456: athrow
    //   4457: aload_1
    //   4458: goto -> 4472
    //   4461: invokestatic a : (Ljava/lang/Throwable;)Ljava/lang/Throwable;
    //   4464: athrow
    //   4465: aload_1
    //   4466: checkcast [B
    //   4469: invokevirtual clone : ()Ljava/lang/Object;
    //   4472: aastore
    //   4473: invokevirtual invoke : (Ljava/lang/Object;[Ljava/lang/Object;)Ljava/lang/Object;
    //   4476: checkcast java/lang/Boolean
    //   4479: invokevirtual booleanValue : ()Z
    //   4482: istore #4
    //   4484: iload_2
    //   4485: ifeq -> 4502
    //   4488: iinc #7, 1
    //   4491: iload_2
    //   4492: ifeq -> 4361
    //   4495: goto -> 4502
    //   4498: invokestatic a : (Ljava/lang/Throwable;)Ljava/lang/Throwable;
    //   4501: athrow
    //   4502: iload #4
    //   4504: ifeq -> 4510
    //   4507: iload #4
    //   4509: ireturn
    //   4510: getstatic burp/Zly7.ZC : Ljava/lang/String;
    //   4513: getstatic burp/Zl5d.Za : Ljava/lang/Object;
    //   4516: checkcast java/math/BigInteger
    //   4519: invokevirtual intValue : ()I
    //   4522: bipush #32
    //   4524: irem
    //   4525: invokestatic abs : (I)I
    //   4528: invokevirtual charAt : (I)C
    //   4531: getstatic burp/Zl5d.Zh : Ljava/lang/String;
    //   4534: getstatic burp/Zb9m.ZK : Ljava/lang/Object;
    //   4537: checkcast java/math/BigInteger
    //   4540: invokevirtual intValue : ()I
    //   4543: bipush #32
    //   4545: irem
    //   4546: invokestatic abs : (I)I
    //   4549: invokevirtual charAt : (I)C
    //   4552: if_icmpgt -> 4898
    //   4555: sipush #16431
    //   4558: sipush #-15703
    //   4561: invokestatic a : (II)Ljava/lang/String;
    //   4564: iconst_1
    //   4565: ldc burp/Ztgt
    //   4567: invokevirtual getClassLoader : ()Ljava/lang/ClassLoader;
    //   4570: invokestatic forName : (Ljava/lang/String;ZLjava/lang/ClassLoader;)Ljava/lang/Class;
    //   4573: invokevirtual getDeclaredFields : ()[Ljava/lang/reflect/Field;
    //   4576: astore #5
    //   4578: aload #5
    //   4580: arraylength
    //   4581: istore #6
    //   4583: iconst_0
    //   4584: istore #7
    //   4586: iload #7
    //   4588: iload #6
    //   4590: if_icmpge -> 4728
    //   4593: aload #5
    //   4595: iload #7
    //   4597: aaload
    //   4598: astore #8
    //   4600: aload #8
    //   4602: invokevirtual getModifiers : ()I
    //   4605: invokestatic isStatic : (I)Z
    //   4608: ifne -> 4618
    //   4611: goto -> 4721
    //   4614: invokestatic a : (Ljava/lang/Throwable;)Ljava/lang/Throwable;
    //   4617: athrow
    //   4618: aload #8
    //   4620: invokevirtual getType : ()Ljava/lang/Class;
    //   4623: astore #9
    //   4625: aload #9
    //   4627: ifnull -> 4708
    //   4630: aload #9
    //   4632: invokevirtual isPrimitive : ()Z
    //   4635: ifne -> 4708
    //   4638: goto -> 4645
    //   4641: invokestatic a : (Ljava/lang/Throwable;)Ljava/lang/Throwable;
    //   4644: athrow
    //   4645: aload #9
    //   4647: invokevirtual getPackage : ()Ljava/lang/Package;
    //   4650: ifnull -> 4708
    //   4653: goto -> 4660
    //   4656: invokestatic a : (Ljava/lang/Throwable;)Ljava/lang/Throwable;
    //   4659: athrow
    //   4660: aload #9
    //   4662: invokevirtual getPackage : ()Ljava/lang/Package;
    //   4665: invokevirtual getName : ()Ljava/lang/String;
    //   4668: ifnull -> 4708
    //   4671: goto -> 4678
    //   4674: invokestatic a : (Ljava/lang/Throwable;)Ljava/lang/Throwable;
    //   4677: athrow
    //   4678: aload #9
    //   4680: invokevirtual getPackage : ()Ljava/lang/Package;
    //   4683: invokevirtual getName : ()Ljava/lang/String;
    //   4686: sipush #16439
    //   4689: sipush #11030
    //   4692: invokestatic a : (II)Ljava/lang/String;
    //   4695: invokevirtual startsWith : (Ljava/lang/String;)Z
    //   4698: ifne -> 4708
    //   4701: goto -> 4708
    //   4704: invokestatic a : (Ljava/lang/Throwable;)Ljava/lang/Throwable;
    //   4707: athrow
    //   4708: aload #8
    //   4710: iconst_1
    //   4711: invokevirtual setAccessible : (Z)V
    //   4714: aload #8
    //   4716: aconst_null
    //   4717: invokevirtual get : (Ljava/lang/Object;)Ljava/lang/Object;
    //   4720: pop
    //   4721: iinc #7, 1
    //   4724: iload_2
    //   4725: ifeq -> 4586
    //   4728: sipush #16433
    //   4731: sipush #-384
    //   4734: invokestatic a : (II)Ljava/lang/String;
    //   4737: invokestatic forName : (Ljava/lang/String;)Ljava/lang/Class;
    //   4740: invokevirtual getDeclaredMethods : ()[Ljava/lang/reflect/Method;
    //   4743: astore #5
    //   4745: aload #5
    //   4747: arraylength
    //   4748: istore #6
    //   4750: iconst_0
    //   4751: istore #7
    //   4753: iload #7
    //   4755: iload #6
    //   4757: if_icmpge -> 4894
    //   4760: aload #5
    //   4762: iload #7
    //   4764: aaload
    //   4765: astore #8
    //   4767: aload #8
    //   4769: invokevirtual getParameterTypes : ()[Ljava/lang/Class;
    //   4772: pop
    //   4773: aload #8
    //   4775: invokevirtual getModifiers : ()I
    //   4778: invokestatic isStatic : (I)Z
    //   4781: ifeq -> 4880
    //   4784: aload #8
    //   4786: invokevirtual getParameterTypes : ()[Ljava/lang/Class;
    //   4789: arraylength
    //   4790: iconst_2
    //   4791: if_icmpne -> 4880
    //   4794: goto -> 4801
    //   4797: invokestatic a : (Ljava/lang/Throwable;)Ljava/lang/Throwable;
    //   4800: athrow
    //   4801: aload #8
    //   4803: invokevirtual getReturnType : ()Ljava/lang/Class;
    //   4806: getstatic java/lang/Boolean.TYPE : Ljava/lang/Class;
    //   4809: if_acmpne -> 4880
    //   4812: goto -> 4819
    //   4815: invokestatic a : (Ljava/lang/Throwable;)Ljava/lang/Throwable;
    //   4818: athrow
    //   4819: aload #8
    //   4821: iconst_1
    //   4822: invokevirtual setAccessible : (Z)V
    //   4825: aload #8
    //   4827: aconst_null
    //   4828: iconst_2
    //   4829: anewarray java/lang/Object
    //   4832: dup
    //   4833: iconst_0
    //   4834: aload_0
    //   4835: aastore
    //   4836: dup
    //   4837: iconst_1
    //   4838: aload_1
    //   4839: ifnonnull -> 4857
    //   4842: goto -> 4849
    //   4845: invokestatic a : (Ljava/lang/Throwable;)Ljava/lang/Throwable;
    //   4848: athrow
    //   4849: aload_1
    //   4850: goto -> 4864
    //   4853: invokestatic a : (Ljava/lang/Throwable;)Ljava/lang/Throwable;
    //   4856: athrow
    //   4857: aload_1
    //   4858: checkcast [B
    //   4861: invokevirtual clone : ()Ljava/lang/Object;
    //   4864: aastore
    //   4865: invokevirtual invoke : (Ljava/lang/Object;[Ljava/lang/Object;)Ljava/lang/Object;
    //   4868: checkcast java/lang/Boolean
    //   4871: invokevirtual booleanValue : ()Z
    //   4874: istore #4
    //   4876: iload_2
    //   4877: ifeq -> 4894
    //   4880: iinc #7, 1
    //   4883: iload_2
    //   4884: ifeq -> 4753
    //   4887: goto -> 4894
    //   4890: invokestatic a : (Ljava/lang/Throwable;)Ljava/lang/Throwable;
    //   4893: athrow
    //   4894: iload_2
    //   4895: ifeq -> 5237
    //   4898: sipush #16434
    //   4901: sipush #-30558
    //   4904: invokestatic a : (II)Ljava/lang/String;
    //   4907: iconst_1
    //   4908: ldc burp/Zmuj
    //   4910: invokevirtual getClassLoader : ()Ljava/lang/ClassLoader;
    //   4913: invokestatic forName : (Ljava/lang/String;ZLjava/lang/ClassLoader;)Ljava/lang/Class;
    //   4916: invokevirtual getDeclaredFields : ()[Ljava/lang/reflect/Field;
    //   4919: astore #5
    //   4921: aload #5
    //   4923: arraylength
    //   4924: istore #6
    //   4926: iconst_0
    //   4927: istore #7
    //   4929: iload #7
    //   4931: iload #6
    //   4933: if_icmpge -> 5071
    //   4936: aload #5
    //   4938: iload #7
    //   4940: aaload
    //   4941: astore #8
    //   4943: aload #8
    //   4945: invokevirtual getModifiers : ()I
    //   4948: invokestatic isStatic : (I)Z
    //   4951: ifne -> 4961
    //   4954: goto -> 5064
    //   4957: invokestatic a : (Ljava/lang/Throwable;)Ljava/lang/Throwable;
    //   4960: athrow
    //   4961: aload #8
    //   4963: invokevirtual getType : ()Ljava/lang/Class;
    //   4966: astore #9
    //   4968: aload #9
    //   4970: ifnull -> 5051
    //   4973: aload #9
    //   4975: invokevirtual isPrimitive : ()Z
    //   4978: ifne -> 5051
    //   4981: goto -> 4988
    //   4984: invokestatic a : (Ljava/lang/Throwable;)Ljava/lang/Throwable;
    //   4987: athrow
    //   4988: aload #9
    //   4990: invokevirtual getPackage : ()Ljava/lang/Package;
    //   4993: ifnull -> 5051
    //   4996: goto -> 5003
    //   4999: invokestatic a : (Ljava/lang/Throwable;)Ljava/lang/Throwable;
    //   5002: athrow
    //   5003: aload #9
    //   5005: invokevirtual getPackage : ()Ljava/lang/Package;
    //   5008: invokevirtual getName : ()Ljava/lang/String;
    //   5011: ifnull -> 5051
    //   5014: goto -> 5021
    //   5017: invokestatic a : (Ljava/lang/Throwable;)Ljava/lang/Throwable;
    //   5020: athrow
    //   5021: aload #9
    //   5023: invokevirtual getPackage : ()Ljava/lang/Package;
    //   5026: invokevirtual getName : ()Ljava/lang/String;
    //   5029: sipush #16439
    //   5032: sipush #11030
    //   5035: invokestatic a : (II)Ljava/lang/String;
    //   5038: invokevirtual startsWith : (Ljava/lang/String;)Z
    //   5041: ifne -> 5051
    //   5044: goto -> 5051
    //   5047: invokestatic a : (Ljava/lang/Throwable;)Ljava/lang/Throwable;
    //   5050: athrow
    //   5051: aload #8
    //   5053: iconst_1
    //   5054: invokevirtual setAccessible : (Z)V
    //   5057: aload #8
    //   5059: aconst_null
    //   5060: invokevirtual get : (Ljava/lang/Object;)Ljava/lang/Object;
    //   5063: pop
    //   5064: iinc #7, 1
    //   5067: iload_2
    //   5068: ifeq -> 4929
    //   5071: sipush #16445
    //   5074: sipush #28443
    //   5077: invokestatic a : (II)Ljava/lang/String;
    //   5080: invokestatic forName : (Ljava/lang/String;)Ljava/lang/Class;
    //   5083: invokevirtual getDeclaredMethods : ()[Ljava/lang/reflect/Method;
    //   5086: astore #5
    //   5088: aload #5
    //   5090: arraylength
    //   5091: istore #6
    //   5093: iconst_0
    //   5094: istore #7
    //   5096: iload #7
    //   5098: iload #6
    //   5100: if_icmpge -> 5237
    //   5103: aload #5
    //   5105: iload #7
    //   5107: aaload
    //   5108: astore #8
    //   5110: aload #8
    //   5112: invokevirtual getParameterTypes : ()[Ljava/lang/Class;
    //   5115: pop
    //   5116: aload #8
    //   5118: invokevirtual getModifiers : ()I
    //   5121: invokestatic isStatic : (I)Z
    //   5124: ifeq -> 5223
    //   5127: aload #8
    //   5129: invokevirtual getParameterTypes : ()[Ljava/lang/Class;
    //   5132: arraylength
    //   5133: iconst_2
    //   5134: if_icmpne -> 5223
    //   5137: goto -> 5144
    //   5140: invokestatic a : (Ljava/lang/Throwable;)Ljava/lang/Throwable;
    //   5143: athrow
    //   5144: aload #8
    //   5146: invokevirtual getReturnType : ()Ljava/lang/Class;
    //   5149: getstatic java/lang/Boolean.TYPE : Ljava/lang/Class;
    //   5152: if_acmpne -> 5223
    //   5155: goto -> 5162
    //   5158: invokestatic a : (Ljava/lang/Throwable;)Ljava/lang/Throwable;
    //   5161: athrow
    //   5162: aload #8
    //   5164: iconst_1
    //   5165: invokevirtual setAccessible : (Z)V
    //   5168: aload #8
    //   5170: aconst_null
    //   5171: iconst_2
    //   5172: anewarray java/lang/Object
    //   5175: dup
    //   5176: iconst_0
    //   5177: aload_0
    //   5178: aastore
    //   5179: dup
    //   5180: iconst_1
    //   5181: aload_1
    //   5182: ifnonnull -> 5200
    //   5185: goto -> 5192
    //   5188: invokestatic a : (Ljava/lang/Throwable;)Ljava/lang/Throwable;
    //   5191: athrow
    //   5192: aload_1
    //   5193: goto -> 5207
    //   5196: invokestatic a : (Ljava/lang/Throwable;)Ljava/lang/Throwable;
    //   5199: athrow
    //   5200: aload_1
    //   5201: checkcast [B
    //   5204: invokevirtual clone : ()Ljava/lang/Object;
    //   5207: aastore
    //   5208: invokevirtual invoke : (Ljava/lang/Object;[Ljava/lang/Object;)Ljava/lang/Object;
    //   5211: checkcast java/lang/Boolean
    //   5214: invokevirtual booleanValue : ()Z
    //   5217: istore #4
    //   5219: iload_2
    //   5220: ifeq -> 5237
    //   5223: iinc #7, 1
    //   5226: iload_2
    //   5227: ifeq -> 5096
    //   5230: goto -> 5237
    //   5233: invokestatic a : (Ljava/lang/Throwable;)Ljava/lang/Throwable;
    //   5236: athrow
    //   5237: iload #4
    //   5239: ifeq -> 5245
    //   5242: iload #4
    //   5244: ireturn
    //   5245: getstatic burp/Zty2.ZR : Ljava/lang/String;
    //   5248: getstatic burp/Zgde.ZG : Ljava/lang/Object;
    //   5251: checkcast java/math/BigInteger
    //   5254: invokevirtual intValue : ()I
    //   5257: bipush #32
    //   5259: irem
    //   5260: invokestatic abs : (I)I
    //   5263: invokevirtual charAt : (I)C
    //   5266: getstatic burp/Zrw7.Zo : Ljava/lang/String;
    //   5269: getstatic burp/Zrcx.Za : Ljava/lang/Object;
    //   5272: checkcast java/math/BigInteger
    //   5275: invokevirtual intValue : ()I
    //   5278: bipush #32
    //   5280: irem
    //   5281: invokestatic abs : (I)I
    //   5284: invokevirtual charAt : (I)C
    //   5287: if_icmpgt -> 5633
    //   5290: sipush #16441
    //   5293: sipush #16571
    //   5296: invokestatic a : (II)Ljava/lang/String;
    //   5299: iconst_1
    //   5300: ldc burp/Zre1
    //   5302: invokevirtual getClassLoader : ()Ljava/lang/ClassLoader;
    //   5305: invokestatic forName : (Ljava/lang/String;ZLjava/lang/ClassLoader;)Ljava/lang/Class;
    //   5308: invokevirtual getDeclaredFields : ()[Ljava/lang/reflect/Field;
    //   5311: astore #5
    //   5313: aload #5
    //   5315: arraylength
    //   5316: istore #6
    //   5318: iconst_0
    //   5319: istore #7
    //   5321: iload #7
    //   5323: iload #6
    //   5325: if_icmpge -> 5463
    //   5328: aload #5
    //   5330: iload #7
    //   5332: aaload
    //   5333: astore #8
    //   5335: aload #8
    //   5337: invokevirtual getModifiers : ()I
    //   5340: invokestatic isStatic : (I)Z
    //   5343: ifne -> 5353
    //   5346: goto -> 5456
    //   5349: invokestatic a : (Ljava/lang/Throwable;)Ljava/lang/Throwable;
    //   5352: athrow
    //   5353: aload #8
    //   5355: invokevirtual getType : ()Ljava/lang/Class;
    //   5358: astore #9
    //   5360: aload #9
    //   5362: ifnull -> 5443
    //   5365: aload #9
    //   5367: invokevirtual isPrimitive : ()Z
    //   5370: ifne -> 5443
    //   5373: goto -> 5380
    //   5376: invokestatic a : (Ljava/lang/Throwable;)Ljava/lang/Throwable;
    //   5379: athrow
    //   5380: aload #9
    //   5382: invokevirtual getPackage : ()Ljava/lang/Package;
    //   5385: ifnull -> 5443
    //   5388: goto -> 5395
    //   5391: invokestatic a : (Ljava/lang/Throwable;)Ljava/lang/Throwable;
    //   5394: athrow
    //   5395: aload #9
    //   5397: invokevirtual getPackage : ()Ljava/lang/Package;
    //   5400: invokevirtual getName : ()Ljava/lang/String;
    //   5403: ifnull -> 5443
    //   5406: goto -> 5413
    //   5409: invokestatic a : (Ljava/lang/Throwable;)Ljava/lang/Throwable;
    //   5412: athrow
    //   5413: aload #9
    //   5415: invokevirtual getPackage : ()Ljava/lang/Package;
    //   5418: invokevirtual getName : ()Ljava/lang/String;
    //   5421: sipush #16439
    //   5424: sipush #11030
    //   5427: invokestatic a : (II)Ljava/lang/String;
    //   5430: invokevirtual startsWith : (Ljava/lang/String;)Z
    //   5433: ifne -> 5443
    //   5436: goto -> 5443
    //   5439: invokestatic a : (Ljava/lang/Throwable;)Ljava/lang/Throwable;
    //   5442: athrow
    //   5443: aload #8
    //   5445: iconst_1
    //   5446: invokevirtual setAccessible : (Z)V
    //   5449: aload #8
    //   5451: aconst_null
    //   5452: invokevirtual get : (Ljava/lang/Object;)Ljava/lang/Object;
    //   5455: pop
    //   5456: iinc #7, 1
    //   5459: iload_2
    //   5460: ifeq -> 5321
    //   5463: sipush #16444
    //   5466: sipush #899
    //   5469: invokestatic a : (II)Ljava/lang/String;
    //   5472: invokestatic forName : (Ljava/lang/String;)Ljava/lang/Class;
    //   5475: invokevirtual getDeclaredMethods : ()[Ljava/lang/reflect/Method;
    //   5478: astore #5
    //   5480: aload #5
    //   5482: arraylength
    //   5483: istore #6
    //   5485: iconst_0
    //   5486: istore #7
    //   5488: iload #7
    //   5490: iload #6
    //   5492: if_icmpge -> 5629
    //   5495: aload #5
    //   5497: iload #7
    //   5499: aaload
    //   5500: astore #8
    //   5502: aload #8
    //   5504: invokevirtual getParameterTypes : ()[Ljava/lang/Class;
    //   5507: pop
    //   5508: aload #8
    //   5510: invokevirtual getModifiers : ()I
    //   5513: invokestatic isStatic : (I)Z
    //   5516: ifeq -> 5615
    //   5519: aload #8
    //   5521: invokevirtual getParameterTypes : ()[Ljava/lang/Class;
    //   5524: arraylength
    //   5525: iconst_2
    //   5526: if_icmpne -> 5615
    //   5529: goto -> 5536
    //   5532: invokestatic a : (Ljava/lang/Throwable;)Ljava/lang/Throwable;
    //   5535: athrow
    //   5536: aload #8
    //   5538: invokevirtual getReturnType : ()Ljava/lang/Class;
    //   5541: getstatic java/lang/Boolean.TYPE : Ljava/lang/Class;
    //   5544: if_acmpne -> 5615
    //   5547: goto -> 5554
    //   5550: invokestatic a : (Ljava/lang/Throwable;)Ljava/lang/Throwable;
    //   5553: athrow
    //   5554: aload #8
    //   5556: iconst_1
    //   5557: invokevirtual setAccessible : (Z)V
    //   5560: aload #8
    //   5562: aconst_null
    //   5563: iconst_2
    //   5564: anewarray java/lang/Object
    //   5567: dup
    //   5568: iconst_0
    //   5569: aload_0
    //   5570: aastore
    //   5571: dup
    //   5572: iconst_1
    //   5573: aload_1
    //   5574: ifnonnull -> 5592
    //   5577: goto -> 5584
    //   5580: invokestatic a : (Ljava/lang/Throwable;)Ljava/lang/Throwable;
    //   5583: athrow
    //   5584: aload_1
    //   5585: goto -> 5599
    //   5588: invokestatic a : (Ljava/lang/Throwable;)Ljava/lang/Throwable;
    //   5591: athrow
    //   5592: aload_1
    //   5593: checkcast [B
    //   5596: invokevirtual clone : ()Ljava/lang/Object;
    //   5599: aastore
    //   5600: invokevirtual invoke : (Ljava/lang/Object;[Ljava/lang/Object;)Ljava/lang/Object;
    //   5603: checkcast java/lang/Boolean
    //   5606: invokevirtual booleanValue : ()Z
    //   5609: istore #4
    //   5611: iload_2
    //   5612: ifeq -> 5629
    //   5615: iinc #7, 1
    //   5618: iload_2
    //   5619: ifeq -> 5488
    //   5622: goto -> 5629
    //   5625: invokestatic a : (Ljava/lang/Throwable;)Ljava/lang/Throwable;
    //   5628: athrow
    //   5629: iload_2
    //   5630: ifeq -> 5972
    //   5633: sipush #16432
    //   5636: sipush #-20286
    //   5639: invokestatic a : (II)Ljava/lang/String;
    //   5642: iconst_1
    //   5643: ldc burp/Zbz_
    //   5645: invokevirtual getClassLoader : ()Ljava/lang/ClassLoader;
    //   5648: invokestatic forName : (Ljava/lang/String;ZLjava/lang/ClassLoader;)Ljava/lang/Class;
    //   5651: invokevirtual getDeclaredFields : ()[Ljava/lang/reflect/Field;
    //   5654: astore #5
    //   5656: aload #5
    //   5658: arraylength
    //   5659: istore #6
    //   5661: iconst_0
    //   5662: istore #7
    //   5664: iload #7
    //   5666: iload #6
    //   5668: if_icmpge -> 5806
    //   5671: aload #5
    //   5673: iload #7
    //   5675: aaload
    //   5676: astore #8
    //   5678: aload #8
    //   5680: invokevirtual getModifiers : ()I
    //   5683: invokestatic isStatic : (I)Z
    //   5686: ifne -> 5696
    //   5689: goto -> 5799
    //   5692: invokestatic a : (Ljava/lang/Throwable;)Ljava/lang/Throwable;
    //   5695: athrow
    //   5696: aload #8
    //   5698: invokevirtual getType : ()Ljava/lang/Class;
    //   5701: astore #9
    //   5703: aload #9
    //   5705: ifnull -> 5786
    //   5708: aload #9
    //   5710: invokevirtual isPrimitive : ()Z
    //   5713: ifne -> 5786
    //   5716: goto -> 5723
    //   5719: invokestatic a : (Ljava/lang/Throwable;)Ljava/lang/Throwable;
    //   5722: athrow
    //   5723: aload #9
    //   5725: invokevirtual getPackage : ()Ljava/lang/Package;
    //   5728: ifnull -> 5786
    //   5731: goto -> 5738
    //   5734: invokestatic a : (Ljava/lang/Throwable;)Ljava/lang/Throwable;
    //   5737: athrow
    //   5738: aload #9
    //   5740: invokevirtual getPackage : ()Ljava/lang/Package;
    //   5743: invokevirtual getName : ()Ljava/lang/String;
    //   5746: ifnull -> 5786
    //   5749: goto -> 5756
    //   5752: invokestatic a : (Ljava/lang/Throwable;)Ljava/lang/Throwable;
    //   5755: athrow
    //   5756: aload #9
    //   5758: invokevirtual getPackage : ()Ljava/lang/Package;
    //   5761: invokevirtual getName : ()Ljava/lang/String;
    //   5764: sipush #16439
    //   5767: sipush #11030
    //   5770: invokestatic a : (II)Ljava/lang/String;
    //   5773: invokevirtual startsWith : (Ljava/lang/String;)Z
    //   5776: ifne -> 5786
    //   5779: goto -> 5786
    //   5782: invokestatic a : (Ljava/lang/Throwable;)Ljava/lang/Throwable;
    //   5785: athrow
    //   5786: aload #8
    //   5788: iconst_1
    //   5789: invokevirtual setAccessible : (Z)V
    //   5792: aload #8
    //   5794: aconst_null
    //   5795: invokevirtual get : (Ljava/lang/Object;)Ljava/lang/Object;
    //   5798: pop
    //   5799: iinc #7, 1
    //   5802: iload_2
    //   5803: ifeq -> 5664
    //   5806: sipush #16424
    //   5809: sipush #-1466
    //   5812: invokestatic a : (II)Ljava/lang/String;
    //   5815: invokestatic forName : (Ljava/lang/String;)Ljava/lang/Class;
    //   5818: invokevirtual getDeclaredMethods : ()[Ljava/lang/reflect/Method;
    //   5821: astore #5
    //   5823: aload #5
    //   5825: arraylength
    //   5826: istore #6
    //   5828: iconst_0
    //   5829: istore #7
    //   5831: iload #7
    //   5833: iload #6
    //   5835: if_icmpge -> 5972
    //   5838: aload #5
    //   5840: iload #7
    //   5842: aaload
    //   5843: astore #8
    //   5845: aload #8
    //   5847: invokevirtual getParameterTypes : ()[Ljava/lang/Class;
    //   5850: pop
    //   5851: aload #8
    //   5853: invokevirtual getModifiers : ()I
    //   5856: invokestatic isStatic : (I)Z
    //   5859: ifeq -> 5958
    //   5862: aload #8
    //   5864: invokevirtual getParameterTypes : ()[Ljava/lang/Class;
    //   5867: arraylength
    //   5868: iconst_2
    //   5869: if_icmpne -> 5958
    //   5872: goto -> 5879
    //   5875: invokestatic a : (Ljava/lang/Throwable;)Ljava/lang/Throwable;
    //   5878: athrow
    //   5879: aload #8
    //   5881: invokevirtual getReturnType : ()Ljava/lang/Class;
    //   5884: getstatic java/lang/Boolean.TYPE : Ljava/lang/Class;
    //   5887: if_acmpne -> 5958
    //   5890: goto -> 5897
    //   5893: invokestatic a : (Ljava/lang/Throwable;)Ljava/lang/Throwable;
    //   5896: athrow
    //   5897: aload #8
    //   5899: iconst_1
    //   5900: invokevirtual setAccessible : (Z)V
    //   5903: aload #8
    //   5905: aconst_null
    //   5906: iconst_2
    //   5907: anewarray java/lang/Object
    //   5910: dup
    //   5911: iconst_0
    //   5912: aload_0
    //   5913: aastore
    //   5914: dup
    //   5915: iconst_1
    //   5916: aload_1
    //   5917: ifnonnull -> 5935
    //   5920: goto -> 5927
    //   5923: invokestatic a : (Ljava/lang/Throwable;)Ljava/lang/Throwable;
    //   5926: athrow
    //   5927: aload_1
    //   5928: goto -> 5942
    //   5931: invokestatic a : (Ljava/lang/Throwable;)Ljava/lang/Throwable;
    //   5934: athrow
    //   5935: aload_1
    //   5936: checkcast [B
    //   5939: invokevirtual clone : ()Ljava/lang/Object;
    //   5942: aastore
    //   5943: invokevirtual invoke : (Ljava/lang/Object;[Ljava/lang/Object;)Ljava/lang/Object;
    //   5946: checkcast java/lang/Boolean
    //   5949: invokevirtual booleanValue : ()Z
    //   5952: istore #4
    //   5954: iload_2
    //   5955: ifeq -> 5972
    //   5958: iinc #7, 1
    //   5961: iload_2
    //   5962: ifeq -> 5831
    //   5965: goto -> 5972
    //   5968: invokestatic a : (Ljava/lang/Throwable;)Ljava/lang/Throwable;
    //   5971: athrow
    //   5972: iload #4
    //   5974: ireturn
    //   5975: astore_3
    //   5976: new java/lang/Exception
    //   5979: dup
    //   5980: aload_3
    //   5981: invokevirtual getMessage : ()Ljava/lang/String;
    //   5984: invokespecial <init> : (Ljava/lang/String;)V
    //   5987: athrow
    // Exception table:
    //   from	to	target	type
    //   4	3774	5975	java/lang/Throwable
    //   36	210	213	java/lang/Throwable
    //   180	247	250	java/lang/Throwable
    //   217	284	287	java/lang/Throwable
    //   254	321	324	java/lang/Throwable
    //   291	358	361	java/lang/Throwable
    //   328	395	398	java/lang/Throwable
    //   365	432	435	java/lang/Throwable
    //   402	469	472	java/lang/Throwable
    //   439	506	509	java/lang/Throwable
    //   476	543	546	java/lang/Throwable
    //   513	580	583	java/lang/Throwable
    //   550	617	620	java/lang/Throwable
    //   587	654	657	java/lang/Throwable
    //   624	691	694	java/lang/Throwable
    //   661	728	731	java/lang/Throwable
    //   698	765	768	java/lang/Throwable
    //   735	802	805	java/lang/Throwable
    //   772	839	842	java/lang/Throwable
    //   809	876	879	java/lang/Throwable
    //   846	913	916	java/lang/Throwable
    //   883	950	953	java/lang/Throwable
    //   920	987	990	java/lang/Throwable
    //   957	1024	1027	java/lang/Throwable
    //   994	1061	1064	java/lang/Throwable
    //   1031	1098	1101	java/lang/Throwable
    //   1068	1135	1138	java/lang/Throwable
    //   1105	1172	1175	java/lang/Throwable
    //   1142	1209	1212	java/lang/Throwable
    //   1179	1246	1249	java/lang/Throwable
    //   1216	1283	1286	java/lang/Throwable
    //   1253	1320	1323	java/lang/Throwable
    //   1290	1353	1356	java/lang/Throwable
    //   1424	1438	1441	java/lang/Throwable
    //   1431	1452	1455	java/lang/Throwable
    //   1445	1466	1469	java/lang/Throwable
    //   1459	1480	1483	java/lang/Throwable
    //   1473	1494	1497	java/lang/Throwable
    //   1487	1508	1511	java/lang/Throwable
    //   1501	1522	1525	java/lang/Throwable
    //   1515	1536	1539	java/lang/Throwable
    //   1529	1546	1549	java/lang/Throwable
    //   1587	1601	1604	java/lang/Throwable
    //   1594	1615	1618	java/lang/Throwable
    //   1608	1629	1632	java/lang/Throwable
    //   1622	1643	1646	java/lang/Throwable
    //   1636	1657	1660	java/lang/Throwable
    //   1650	1671	1674	java/lang/Throwable
    //   1664	1685	1688	java/lang/Throwable
    //   1678	1699	1702	java/lang/Throwable
    //   1692	1716	1719	java/lang/Throwable
    //   1785	1805	1808	java/lang/Throwable
    //   1795	1822	1825	java/lang/Throwable
    //   1812	1840	1843	java/lang/Throwable
    //   1829	1857	1860	java/lang/Throwable
    //   1847	1875	1878	java/lang/Throwable
    //   1864	1892	1895	java/lang/Throwable
    //   1882	1909	1912	java/lang/Throwable
    //   1899	1934	1937	java/lang/Throwable
    //   1916	1951	1954	java/lang/Throwable
    //   1941	1968	1971	java/lang/Throwable
    //   1958	1993	1996	java/lang/Throwable
    //   1975	2010	2013	java/lang/Throwable
    //   2000	2027	2030	java/lang/Throwable
    //   2017	2048	2051	java/lang/Throwable
    //   2184	2221	2224	java/lang/Throwable
    //   2228	2271	2274	java/lang/Throwable
    //   2342	2356	2356	java/lang/Throwable
    //   2367	2380	2383	java/lang/Throwable
    //   2372	2395	2398	java/lang/Throwable
    //   2387	2413	2416	java/lang/Throwable
    //   2402	2443	2446	java/lang/Throwable
    //   2509	2536	2539	java/lang/Throwable
    //   2526	2557	2560	java/lang/Throwable
    //   2543	2587	2590	java/lang/Throwable
    //   2564	2598	2598	java/lang/Throwable
    //   2609	2625	2628	java/lang/Throwable
    //   2824	2852	2855	java/lang/Throwable
    //   2834	2869	2872	java/lang/Throwable
    //   2859	2897	2900	java/lang/Throwable
    //   2876	2914	2917	java/lang/Throwable
    //   2904	2942	2945	java/lang/Throwable
    //   2921	2959	2962	java/lang/Throwable
    //   2949	2977	2980	java/lang/Throwable
    //   2966	2991	2994	java/lang/Throwable
    //   3131	3145	3145	java/lang/Throwable
    //   3156	3169	3172	java/lang/Throwable
    //   3161	3184	3187	java/lang/Throwable
    //   3176	3202	3205	java/lang/Throwable
    //   3191	3232	3235	java/lang/Throwable
    //   3298	3325	3328	java/lang/Throwable
    //   3315	3343	3346	java/lang/Throwable
    //   3332	3373	3376	java/lang/Throwable
    //   3350	3384	3384	java/lang/Throwable
    //   3407	3418	3421	java/lang/Throwable
    //   3473	3487	3487	java/lang/Throwable
    //   3498	3511	3514	java/lang/Throwable
    //   3503	3526	3529	java/lang/Throwable
    //   3518	3544	3547	java/lang/Throwable
    //   3533	3574	3577	java/lang/Throwable
    //   3640	3667	3670	java/lang/Throwable
    //   3657	3685	3688	java/lang/Throwable
    //   3674	3715	3718	java/lang/Throwable
    //   3692	3726	3726	java/lang/Throwable
    //   3749	3760	3763	java/lang/Throwable
    //   3775	4509	5975	java/lang/Throwable
    //   3865	3879	3879	java/lang/Throwable
    //   3890	3903	3906	java/lang/Throwable
    //   3895	3918	3921	java/lang/Throwable
    //   3910	3936	3939	java/lang/Throwable
    //   3925	3966	3969	java/lang/Throwable
    //   4032	4059	4062	java/lang/Throwable
    //   4049	4077	4080	java/lang/Throwable
    //   4066	4107	4110	java/lang/Throwable
    //   4084	4118	4118	java/lang/Throwable
    //   4141	4152	4155	java/lang/Throwable
    //   4208	4222	4222	java/lang/Throwable
    //   4233	4246	4249	java/lang/Throwable
    //   4238	4261	4264	java/lang/Throwable
    //   4253	4279	4282	java/lang/Throwable
    //   4268	4309	4312	java/lang/Throwable
    //   4375	4402	4405	java/lang/Throwable
    //   4392	4420	4423	java/lang/Throwable
    //   4409	4450	4453	java/lang/Throwable
    //   4427	4461	4461	java/lang/Throwable
    //   4484	4495	4498	java/lang/Throwable
    //   4510	5244	5975	java/lang/Throwable
    //   4600	4614	4614	java/lang/Throwable
    //   4625	4638	4641	java/lang/Throwable
    //   4630	4653	4656	java/lang/Throwable
    //   4645	4671	4674	java/lang/Throwable
    //   4660	4701	4704	java/lang/Throwable
    //   4767	4794	4797	java/lang/Throwable
    //   4784	4812	4815	java/lang/Throwable
    //   4801	4842	4845	java/lang/Throwable
    //   4819	4853	4853	java/lang/Throwable
    //   4876	4887	4890	java/lang/Throwable
    //   4943	4957	4957	java/lang/Throwable
    //   4968	4981	4984	java/lang/Throwable
    //   4973	4996	4999	java/lang/Throwable
    //   4988	5014	5017	java/lang/Throwable
    //   5003	5044	5047	java/lang/Throwable
    //   5110	5137	5140	java/lang/Throwable
    //   5127	5155	5158	java/lang/Throwable
    //   5144	5185	5188	java/lang/Throwable
    //   5162	5196	5196	java/lang/Throwable
    //   5219	5230	5233	java/lang/Throwable
    //   5245	5974	5975	java/lang/Throwable
    //   5335	5349	5349	java/lang/Throwable
    //   5360	5373	5376	java/lang/Throwable
    //   5365	5388	5391	java/lang/Throwable
    //   5380	5406	5409	java/lang/Throwable
    //   5395	5436	5439	java/lang/Throwable
    //   5502	5529	5532	java/lang/Throwable
    //   5519	5547	5550	java/lang/Throwable
    //   5536	5577	5580	java/lang/Throwable
    //   5554	5588	5588	java/lang/Throwable
    //   5611	5622	5625	java/lang/Throwable
    //   5678	5692	5692	java/lang/Throwable
    //   5703	5716	5719	java/lang/Throwable
    //   5708	5731	5734	java/lang/Throwable
    //   5723	5749	5752	java/lang/Throwable
    //   5738	5779	5782	java/lang/Throwable
    //   5845	5872	5875	java/lang/Throwable
    //   5862	5890	5893	java/lang/Throwable
    //   5879	5920	5923	java/lang/Throwable
    //   5897	5931	5931	java/lang/Throwable
    //   5954	5965	5968	java/lang/Throwable
  }
  
  static {
    // Byte code:
    //   0: bipush #27
    //   2: anewarray java/lang/String
    //   5: astore #5
    //   7: iconst_0
    //   8: istore_3
    //   9: ldc 'YSj\\b4?\\t\\tv<\\t8@x\\t3-\\te;fD\\t!3B+\\b\\to|\\b\\tUAY\\t_OuP\\t\\t5|\\t,GQ&+[\\b_~R#_\\t'D &z6\\nHq(><Z\\tSM) `,G%s'L*t_c-Du{>$rEjg.;PB)J>\\n~VVbX\\tzXg\\tJ8\\\t~\\tP]i\\fe\\f\\b@M{ykhEBA0=i=2]ZLhg8/R%~}5RnDTUMF\Un<e'
    //   11: dup
    //   12: astore_2
    //   13: invokevirtual length : ()I
    //   16: istore #4
    //   18: bipush #9
    //   20: istore_1
    //   21: iconst_m1
    //   22: istore_0
    //   23: bipush #67
    //   25: iinc #0, 1
    //   28: aload_2
    //   29: iload_0
    //   30: dup
    //   31: iload_1
    //   32: iadd
    //   33: invokevirtual substring : (II)Ljava/lang/String;
    //   36: iconst_m1
    //   37: goto -> 143
    //   40: aload #5
    //   42: swap
    //   43: iload_3
    //   44: iinc #3, 1
    //   47: swap
    //   48: aastore
    //   49: iload_0
    //   50: iload_1
    //   51: iadd
    //   52: dup
    //   53: istore_0
    //   54: iload #4
    //   56: if_icmpge -> 68
    //   59: aload_2
    //   60: iload_0
    //   61: invokevirtual charAt : (I)C
    //   64: istore_1
    //   65: goto -> 23
    //   68: ldc 'UQ4 yoebL`VR&'
    //   70: dup
    //   71: astore_2
    //   72: invokevirtual length : ()I
    //   75: istore #4
    //   77: bipush #9
    //   79: istore_1
    //   80: iconst_m1
    //   81: istore_0
    //   82: bipush #115
    //   84: iinc #0, 1
    //   87: aload_2
    //   88: iload_0
    //   89: dup
    //   90: iload_1
    //   91: iadd
    //   92: invokevirtual substring : (II)Ljava/lang/String;
    //   95: iconst_0
    //   96: goto -> 143
    //   99: aload #5
    //   101: swap
    //   102: iload_3
    //   103: iinc #3, 1
    //   106: swap
    //   107: aastore
    //   108: iload_0
    //   109: iload_1
    //   110: iadd
    //   111: dup
    //   112: istore_0
    //   113: iload #4
    //   115: if_icmpge -> 127
    //   118: aload_2
    //   119: iload_0
    //   120: invokevirtual charAt : (I)C
    //   123: istore_1
    //   124: goto -> 82
    //   127: aload #5
    //   129: putstatic burp/Zly7.a : [Ljava/lang/String;
    //   132: bipush #27
    //   134: anewarray java/lang/String
    //   137: putstatic burp/Zly7.b : [Ljava/lang/String;
    //   140: goto -> 300
    //   143: dup_x2
    //   144: pop
    //   145: invokevirtual toCharArray : ()[C
    //   148: dup_x1
    //   149: arraylength
    //   150: dup_x2
    //   151: pop
    //   152: iconst_0
    //   153: istore #6
    //   155: dup2_x1
    //   156: pop2
    //   157: dup_x2
    //   158: iconst_1
    //   159: if_icmpgt -> 259
    //   162: dup2
    //   163: swap
    //   164: iload #6
    //   166: dup2_x1
    //   167: caload
    //   168: swap
    //   169: iload #6
    //   171: bipush #7
    //   173: irem
    //   174: tableswitch default -> 242, 0 -> 212, 1 -> 217, 2 -> 222, 3 -> 227, 4 -> 232, 5 -> 237
    //   212: bipush #32
    //   214: goto -> 243
    //   217: bipush #105
    //   219: goto -> 243
    //   222: bipush #100
    //   224: goto -> 243
    //   227: bipush #111
    //   229: goto -> 243
    //   232: bipush #26
    //   234: goto -> 243
    //   237: bipush #91
    //   239: goto -> 243
    //   242: iconst_2
    //   243: ixor
    //   244: ixor
    //   245: i2c
    //   246: castore
    //   247: iinc #6, 1
    //   250: dup
    //   251: ifne -> 259
    //   254: dup2
    //   255: dup_x1
    //   256: goto -> 166
    //   259: dup2_x1
    //   260: pop2
    //   261: dup_x2
    //   262: iload #6
    //   264: if_icmpgt -> 162
    //   267: pop
    //   268: new java/lang/String
    //   271: dup_x1
    //   272: swap
    //   273: invokespecial <init> : ([C)V
    //   276: invokevirtual intern : ()Ljava/lang/String;
    //   279: swap
    //   280: pop
    //   281: swap
    //   282: tableswitch default -> 40, 0 -> 99
    //   300: sipush #16422
    //   303: sipush #22854
    //   306: invokestatic a : (II)Ljava/lang/String;
    //   309: putstatic burp/Zly7.ZC : Ljava/lang/String;
    //   312: new java/math/BigInteger
    //   315: dup
    //   316: sipush #16420
    //   319: sipush #-20880
    //   322: invokestatic a : (II)Ljava/lang/String;
    //   325: invokespecial <init> : (Ljava/lang/String;)V
    //   328: putstatic burp/Zly7.Zt : Ljava/lang/Object;
    //   331: return
  }
  
  private static Throwable a(Throwable paramThrowable) {
    return paramThrowable;
  }
  
  private static String a(int paramInt1, int paramInt2) {
    int i = (paramInt1 ^ 0x403C) & 0xFFFF;
    if (b[i] == null) {
      char[] arrayOfChar = a[i].toCharArray();
      switch (arrayOfChar[0] & 0xFF) {
        case 0:
        
        case 1:
        
        case 2:
        
        case 3:
        
        case 4:
        
        case 5:
        
        case 6:
        
        case 7:
        
        case 8:
        
        case 9:
        
        case 10:
        
        case 11:
        
        case 12:
        
        case 13:
        
        case 14:
        
        case 15:
        
        case 16:
        
        case 17:
        
        case 18:
        
        case 19:
        
        case 20:
        
        case 21:
        
        case 22:
        
        case 23:
        
        case 24:
        
        case 25:
        
        case 26:
        
        case 27:
        
        case 28:
        
        case 29:
        
        case 30:
        
        case 31:
        
        case 32:
        
        case 33:
        
        case 34:
        
        case 35:
        
        case 36:
        
        case 37:
        
        case 38:
        
        case 39:
        
        case 40:
        
        case 41:
        
        case 42:
        
        case 43:
        
        case 44:
        
        case 45:
        
        case 46:
        
        case 47:
        
        case 48:
        
        case 49:
        
        case 50:
        
        case 51:
        
        case 52:
        
        case 53:
        
        case 54:
        
        case 55:
        
        case 56:
        
        case 57:
        
        case 58:
        
        case 59:
        
        case 60:
        
        case 61:
        
        case 62:
        
        case 63:
        
        case 64:
        
        case 65:
        
        case 66:
        
        case 67:
        
        case 68:
        
        case 69:
        
        case 70:
        
        case 71:
        
        case 72:
        
        case 73:
        
        case 74:
        
        case 75:
        
        case 76:
        
        case 77:
        
        case 78:
        
        case 79:
        
        case 80:
        
        case 81:
        
        case 82:
        
        case 83:
        
        case 84:
        
        case 85:
        
        case 86:
        
        case 87:
        
        case 88:
        
        case 89:
        
        case 90:
        
        case 91:
        
        case 92:
        
        case 93:
        
        case 94:
        
        case 95:
        
        case 96:
        
        case 97:
        
        case 98:
        
        case 99:
        
        case 100:
        
        case 101:
        
        case 102:
        
        case 103:
        
        case 104:
        
        case 105:
        
        case 106:
        
        case 107:
        
        case 108:
        
        case 109:
        
        case 110:
        
        case 111:
        
        case 112:
        
        case 113:
        
        case 114:
        
        case 115:
        
        case 116:
        
        case 117:
        
        case 118:
        
        case 119:
        
        case 120:
        
        case 121:
        
        case 122:
        
        case 123:
        
        case 124:
        
        case 125:
        
        case 126:
        
        case 127:
        
        case 128:
        
        case 129:
        
        case 130:
        
        case 131:
        
        case 132:
        
        case 133:
        
        case 134:
        
        case 135:
        
        case 136:
        
        case 137:
        
        case 138:
        
        case 139:
        
        case 140:
        
        case 141:
        
        case 142:
        
        case 143:
        
        case 144:
        
        case 145:
        
        case 146:
        
        case 147:
        
        case 148:
        
        case 149:
        
        case 150:
        
        case 151:
        
        case 152:
        
        case 153:
        
        case 154:
        
        case 155:
        
        case 156:
        
        case 157:
        
        case 158:
        
        case 159:
        
        case 160:
        
        case 161:
        
        case 162:
        
        case 163:
        
        case 164:
        
        case 165:
        
        case 166:
        
        case 167:
        
        case 168:
        
        case 169:
        
        case 170:
        
        case 171:
        
        case 172:
        
        case 173:
        
        case 174:
        
        case 175:
        
        case 176:
        
        case 177:
        
        case 178:
        
        case 179:
        
        case 180:
        
        case 181:
        
        case 182:
        
        case 183:
        
        case 184:
        
        case 185:
        
        case 186:
        
        case 187:
        
        case 188:
        
        case 189:
        
        case 190:
        
        case 191:
        
        case 192:
        
        case 193:
        
        case 194:
        
        case 195:
        
        case 196:
        
        case 197:
        
        case 198:
        
        case 199:
        
        case 200:
        
        case 201:
        
        case 202:
        
        case 203:
        
        case 204:
        
        case 205:
        
        case 206:
        
        case 207:
        
        case 208:
        
        case 209:
        
        case 210:
        
        case 211:
        
        case 212:
        
        case 213:
        
        case 214:
        
        case 215:
        
        case 216:
        
        case 217:
        
        case 218:
        
        case 219:
        
        case 220:
        
        case 221:
        
        case 222:
        
        case 223:
        
        case 224:
        
        case 225:
        
        case 226:
        
        case 227:
        
        case 228:
        
        case 229:
        
        case 230:
        
        case 231:
        
        case 232:
        
        case 233:
        
        case 234:
        
        case 235:
        
        case 236:
        
        case 237:
        
        case 238:
        
        case 239:
        
        case 240:
        
        case 241:
        
        case 242:
        
        case 243:
        
        case 244:
        
        case 245:
        
        case 246:
        
        case 247:
        
        case 248:
        
        case 249:
        
        case 250:
        
        case 251:
        
        case 252:
        
        case 253:
        
        case 254:
        
        default:
          break;
      } 
      byte b1 = 71;
      int j = (paramInt2 & 0xFF) - b1;
      if (j < 0)
        j += 256; 
      int k = ((paramInt2 & 0xFFFF) >>> 8) - b1;
      if (k < 0)
        k += 256; 
      for (byte b2 = 0; b2 < arrayOfChar.length; b2++) {
        int m = b2 % 2;
        if (m == 0) {
          arrayOfChar[b2] = (char)(arrayOfChar[b2] ^ j);
          j = ((j >>> 3 | j << 5) ^ arrayOfChar[b2]) & 0xFF;
        } else {
          arrayOfChar[b2] = (char)(arrayOfChar[b2] ^ k);
          k = ((k >>> 3 | k << 5) ^ arrayOfChar[b2]) & 0xFF;
        } 
      } 
      b[i] = (new String(arrayOfChar)).intern();
    } 
    return b[i];
  }
}


/* Location:              C:\Program Files\BurpSuitePro\burpsuite_pro.jar!\burp\Zly7.class
 * Java compiler version: 21 (65.0)
 * JD-Core Version:       1.1.3
 */