package burp;

import java.io.IOException;

public class Zlzq {
  private static Zbqc[] ZE;
  
  private static final String[] a;
  
  private static final String[] b;
  
  public static void ZD(Zs4f paramZs4f, Zsxg paramZsxg) throws IOException {
    Zefg<Zstu> zefg = paramZsxg.ZJb();
    byte b1 = 0;
    Zbqc[] arrayOfZbqc = ZE();
    while (b1 < zefg.size()) {
      paramZs4f.Ze("l", zefg.get(b1));
      b1++;
      if (arrayOfZbqc != null)
        break; 
    } 
    paramZs4f.Zb(a(-9508, 16227), paramZsxg.ZJl());
    Zstu zstu1 = paramZsxg.ZJJ();
    try {
      if (zstu1 != null)
        paramZs4f.Ze("f", zstu1); 
    } catch (IOException iOException) {
      throw a(null);
    } 
    Zstu zstu2 = paramZsxg.ZJa();
    try {
      if (zstu2 != null)
        paramZs4f.Ze("l", zstu2); 
    } catch (IOException iOException) {
      throw a(null);
    } 
    Zstu zstu3 = paramZsxg.ZJx();
    try {
      if (zstu3 != null)
        paramZs4f.Ze("s", zstu3); 
    } catch (IOException iOException) {
      throw a(null);
    } 
    Zmyi zmyi = paramZsxg.ZJ9();
    byte b2 = 0;
    while (b2 < zmyi.Zpu()) {
      paramZs4f.Zb("t", zmyi.ZN(b2));
      b2++;
      if (arrayOfZbqc != null)
        break; 
    } 
    try {
      paramZs4f.Zb(a(-9506, -11103), paramZsxg.ZJu());
      paramZs4f.Zb(a(-9507, 9032), paramZsxg.ZJc());
      if (Zbqc.Zwu() == null)
        Zl(new Zbqc[5]); 
    } catch (IOException iOException) {
      throw a(null);
    } 
  }
  
  static void Zc(Zsxg paramZsxg) {
    int i = paramZsxg.ZJl();
    if (i < 1 || i > 100)
      i = 100; 
    byte b = (paramZsxg.ZJb() == null) ? 0 : paramZsxg.ZJb().size();
    paramZsxg.ZvH(i * b);
  }
  
  public static void ZT(Zsxg paramZsxg) throws Zs7w {
    try {
      if (paramZsxg.ZJb().isEmpty())
        throw new Zs7w(a(-9505, 1071)); 
    } catch (Zs7w zs7w) {
      throw a(null);
    } 
  }
  
  public static void ZX(Zsxg paramZsxg) {
    paramZsxg.ZMb(0);
    paramZsxg.ZM0(0);
    Zbqc[] arrayOfZbqc = ZE();
    Zmyi zmyi = paramZsxg.ZJ9();
    byte b = 0;
    while (b < zmyi.Zpu()) {
      zmyi.ZX(b, 0);
      b++;
      if (arrayOfZbqc != null)
        break; 
    } 
    paramZsxg.Zv(zmyi);
    paramZsxg.ZP((Zstu)null);
  }
  
  public static void Zl(Zbqc[] paramArrayOfZbqc) {
    ZE = paramArrayOfZbqc;
  }
  
  public static Zbqc[] ZE() {
    return ZE;
  }
  
  private static Exception a(Exception paramException) {
    return paramException;
  }
  
  static {
    // Byte code:
    //   0: iconst_4
    //   1: anewarray java/lang/String
    //   4: astore #5
    //   6: aconst_null
    //   7: iconst_0
    //   8: istore_3
    //   9: invokestatic Zl : ([Lburp/Zbqc;)V
    //   12: ldc 'fè`'
    //   14: dup
    //   15: astore_2
    //   16: invokevirtual length : ()I
    //   19: istore #4
    //   21: iconst_2
    //   22: istore_1
    //   23: iconst_m1
    //   24: istore_0
    //   25: bipush #107
    //   27: iinc #0, 1
    //   30: aload_2
    //   31: iload_0
    //   32: dup
    //   33: iload_1
    //   34: iadd
    //   35: invokevirtual substring : (II)Ljava/lang/String;
    //   38: iconst_m1
    //   39: goto -> 142
    //   42: aload #5
    //   44: swap
    //   45: iload_3
    //   46: iinc #3, 1
    //   49: swap
    //   50: aastore
    //   51: iload_0
    //   52: iload_1
    //   53: iadd
    //   54: dup
    //   55: istore_0
    //   56: iload #4
    //   58: if_icmpge -> 70
    //   61: aload_2
    //   62: iload_0
    //   63: invokevirtual charAt : (I)C
    //   66: istore_1
    //   67: goto -> 25
    //   70: ldc '\\ráP' d¹ 6.ÙPÇX8ùwR¨{æÛ±'
    //   72: dup
    //   73: astore_2
    //   74: invokevirtual length : ()I
    //   77: istore #4
    //   79: iconst_3
    //   80: istore_1
    //   81: iconst_m1
    //   82: istore_0
    //   83: iconst_5
    //   84: iinc #0, 1
    //   87: aload_2
    //   88: iload_0
    //   89: dup
    //   90: iload_1
    //   91: iadd
    //   92: invokevirtual substring : (II)Ljava/lang/String;
    //   95: iconst_0
    //   96: goto -> 142
    //   99: aload #5
    //   101: swap
    //   102: iload_3
    //   103: iinc #3, 1
    //   106: swap
    //   107: aastore
    //   108: iload_0
    //   109: iload_1
    //   110: iadd
    //   111: dup
    //   112: istore_0
    //   113: iload #4
    //   115: if_icmpge -> 127
    //   118: aload_2
    //   119: iload_0
    //   120: invokevirtual charAt : (I)C
    //   123: istore_1
    //   124: goto -> 83
    //   127: aload #5
    //   129: putstatic burp/Zlzq.a : [Ljava/lang/String;
    //   132: iconst_4
    //   133: anewarray java/lang/String
    //   136: putstatic burp/Zlzq.b : [Ljava/lang/String;
    //   139: goto -> 300
    //   142: dup_x2
    //   143: pop
    //   144: invokevirtual toCharArray : ()[C
    //   147: dup_x1
    //   148: arraylength
    //   149: dup_x2
    //   150: pop
    //   151: iconst_0
    //   152: istore #6
    //   154: dup2_x1
    //   155: pop2
    //   156: dup_x2
    //   157: iconst_1
    //   158: if_icmpgt -> 260
    //   161: dup2
    //   162: swap
    //   163: iload #6
    //   165: dup2_x1
    //   166: caload
    //   167: swap
    //   168: iload #6
    //   170: bipush #7
    //   172: irem
    //   173: tableswitch default -> 242, 0 -> 212, 1 -> 217, 2 -> 222, 3 -> 227, 4 -> 232, 5 -> 237
    //   212: bipush #112
    //   214: goto -> 244
    //   217: bipush #55
    //   219: goto -> 244
    //   222: bipush #33
    //   224: goto -> 244
    //   227: bipush #46
    //   229: goto -> 244
    //   232: bipush #76
    //   234: goto -> 244
    //   237: bipush #79
    //   239: goto -> 244
    //   242: bipush #48
    //   244: ixor
    //   245: ixor
    //   246: i2c
    //   247: castore
    //   248: iinc #6, 1
    //   251: dup
    //   252: ifne -> 260
    //   255: dup2
    //   256: dup_x1
    //   257: goto -> 165
    //   260: dup2_x1
    //   261: pop2
    //   262: dup_x2
    //   263: iload #6
    //   265: if_icmpgt -> 161
    //   268: pop
    //   269: new java/lang/String
    //   272: dup_x1
    //   273: swap
    //   274: invokespecial <init> : ([C)V
    //   277: invokevirtual intern : ()Ljava/lang/String;
    //   280: swap
    //   281: pop
    //   282: swap
    //   283: tableswitch default -> 42, 0 -> 99
    //   300: return
  }
  
  private static String a(int paramInt1, int paramInt2) {
    int i = (paramInt1 ^ 0xFFFFDADC) & 0xFFFF;
    if (b[i] == null) {
      char[] arrayOfChar = a[i].toCharArray();
      switch (arrayOfChar[0] & 0xFF) {
        case 0:
        
        case 1:
        
        case 2:
        
        case 3:
        
        case 4:
        
        case 5:
        
        case 6:
        
        case 7:
        
        case 8:
        
        case 9:
        
        case 10:
        
        case 11:
        
        case 12:
        
        case 13:
        
        case 14:
        
        case 15:
        
        case 16:
        
        case 17:
        
        case 18:
        
        case 19:
        
        case 20:
        
        case 21:
        
        case 22:
        
        case 23:
        
        case 24:
        
        case 25:
        
        case 26:
        
        case 27:
        
        case 28:
        
        case 29:
        
        case 30:
        
        case 31:
        
        case 32:
        
        case 33:
        
        case 34:
        
        case 35:
        
        case 36:
        
        case 37:
        
        case 38:
        
        case 39:
        
        case 40:
        
        case 41:
        
        case 42:
        
        case 43:
        
        case 44:
        
        case 45:
        
        case 46:
        
        case 47:
        
        case 48:
        
        case 49:
        
        case 50:
        
        case 51:
        
        case 52:
        
        case 53:
        
        case 54:
        
        case 55:
        
        case 56:
        
        case 57:
        
        case 58:
        
        case 59:
        
        case 60:
        
        case 61:
        
        case 62:
        
        case 63:
        
        case 64:
        
        case 65:
        
        case 66:
        
        case 67:
        
        case 68:
        
        case 69:
        
        case 70:
        
        case 71:
        
        case 72:
        
        case 73:
        
        case 74:
        
        case 75:
        
        case 76:
        
        case 77:
        
        case 78:
        
        case 79:
        
        case 80:
        
        case 81:
        
        case 82:
        
        case 83:
        
        case 84:
        
        case 85:
        
        case 86:
        
        case 87:
        
        case 88:
        
        case 89:
        
        case 90:
        
        case 91:
        
        case 92:
        
        case 93:
        
        case 94:
        
        case 95:
        
        case 96:
        
        case 97:
        
        case 98:
        
        case 99:
        
        case 100:
        
        case 101:
        
        case 102:
        
        case 103:
        
        case 104:
        
        case 105:
        
        case 106:
        
        case 107:
        
        case 108:
        
        case 109:
        
        case 110:
        
        case 111:
        
        case 112:
        
        case 113:
        
        case 114:
        
        case 115:
        
        case 116:
        
        case 117:
        
        case 118:
        
        case 119:
        
        case 120:
        
        case 121:
        
        case 122:
        
        case 123:
        
        case 124:
        
        case 125:
        
        case 126:
        
        case 127:
        
        case 128:
        
        case 129:
        
        case 130:
        
        case 131:
        
        case 132:
        
        case 133:
        
        case 134:
        
        case 135:
        
        case 136:
        
        case 137:
        
        case 138:
        
        case 139:
        
        case 140:
        
        case 141:
        
        case 142:
        
        case 143:
        
        case 144:
        
        case 145:
        
        case 146:
        
        case 147:
        
        case 148:
        
        case 149:
        
        case 150:
        
        case 151:
        
        case 152:
        
        case 153:
        
        case 154:
        
        case 155:
        
        case 156:
        
        case 157:
        
        case 158:
        
        case 159:
        
        case 160:
        
        case 161:
        
        case 162:
        
        case 163:
        
        case 164:
        
        case 165:
        
        case 166:
        
        case 167:
        
        case 168:
        
        case 169:
        
        case 170:
        
        case 171:
        
        case 172:
        
        case 173:
        
        case 174:
        
        case 175:
        
        case 176:
        
        case 177:
        
        case 178:
        
        case 179:
        
        case 180:
        
        case 181:
        
        case 182:
        
        case 183:
        
        case 184:
        
        case 185:
        
        case 186:
        
        case 187:
        
        case 188:
        
        case 189:
        
        case 190:
        
        case 191:
        
        case 192:
        
        case 193:
        
        case 194:
        
        case 195:
        
        case 196:
        
        case 197:
        
        case 198:
        
        case 199:
        
        case 200:
        
        case 201:
        
        case 202:
        
        case 203:
        
        case 204:
        
        case 205:
        
        case 206:
        
        case 207:
        
        case 208:
        
        case 209:
        
        case 210:
        
        case 211:
        
        case 212:
        
        case 213:
        
        case 214:
        
        case 215:
        
        case 216:
        
        case 217:
        
        case 218:
        
        case 219:
        
        case 220:
        
        case 221:
        
        case 222:
        
        case 223:
        
        case 224:
        
        case 225:
        
        case 226:
        
        case 227:
        
        case 228:
        
        case 229:
        
        case 230:
        
        case 231:
        
        case 232:
        
        case 233:
        
        case 234:
        
        case 235:
        
        case 236:
        
        case 237:
        
        case 238:
        
        case 239:
        
        case 240:
        
        case 241:
        
        case 242:
        
        case 243:
        
        case 244:
        
        case 245:
        
        case 246:
        
        case 247:
        
        case 248:
        
        case 249:
        
        case 250:
        
        case 251:
        
        case 252:
        
        case 253:
        
        case 254:
        
        default:
          break;
      } 
      byte b1 = 85;
      int j = (paramInt2 & 0xFF) - b1;
      if (j < 0)
        j += 256; 
      int k = ((paramInt2 & 0xFFFF) >>> 8) - b1;
      if (k < 0)
        k += 256; 
      for (byte b2 = 0; b2 < arrayOfChar.length; b2++) {
        int m = b2 % 2;
        if (m == 0) {
          arrayOfChar[b2] = (char)(arrayOfChar[b2] ^ j);
          j = ((j >>> 3 | j << 5) ^ arrayOfChar[b2]) & 0xFF;
        } else {
          arrayOfChar[b2] = (char)(arrayOfChar[b2] ^ k);
          k = ((k >>> 3 | k << 5) ^ arrayOfChar[b2]) & 0xFF;
        } 
      } 
      b[i] = (new String(arrayOfChar)).intern();
    } 
    return b[i];
  }
}


/* Location:              C:\Program Files\BurpSuitePro\burpsuite_pro.jar!\burp\Zlzq.class
 * Java compiler version: 21 (65.0)
 * JD-Core Version:       1.1.3
 */