package burp;

public class Zm47 extends Zm4h<Zg0z, Zvb> {
  private static final String b;
  
  Zm47(Zlog paramZlog, Zzcu paramZzcu, Zz1m<Zt18> paramZz1m, Ze73 paramZe73, Zlas paramZlas, Zr69 paramZr69, Zt1g paramZt1g, Zzu3 paramZzu3, Zskh paramZskh, Zz1m<Zt35> paramZz1m1, Zez7 paramZez7, Zzs_ paramZzs_, Zxf2 paramZxf2) {
    super(Zn(paramZlog, paramZzcu, paramZe73, paramZlas, paramZr69, paramZzu3, paramZz1m, paramZskh, paramZt1g, paramZez7, paramZz1m1, paramZxf2, paramZzs_));
  }
  
  private static Zejc<Zg0z, Zvb> Zn(Zlog paramZlog, Zzcu paramZzcu, Ze73 paramZe73, Zlas paramZlas, Zr69 paramZr69, Zzu3 paramZzu3, Zz1m<Zt18> paramZz1m, Zskh paramZskh, Zt1g paramZt1g, Zez7 paramZez7, Zz1m<Zt35> paramZz1m1, Zxf2 paramZxf2, Zzs_ paramZzs_) {
    Zl7h zl7h = paramZlog.ZnH();
    Zv89 zv89 = new Zv89(zl7h, paramZzcu, paramZz1m1, paramZr69, paramZez7);
    Zv8i zv8i = new Zv8i(paramZzcu, paramZez7, paramZz1m1, paramZzu3);
    Zv82 zv82 = new Zv82(paramZlas);
    Zv8q zv8q = new Zv8q(zl7h, paramZr69, paramZz1m);
    Zzsa zzsa = new Zzsa(paramZlas, paramZz1m, paramZskh);
    Zv8s zv8s = new Zv8s(paramZe73);
    Zslr zslr = new Zslr(paramZxf2, paramZlas, zl7h, paramZr69, paramZzs_, paramZe73);
    Zv83 zv83 = new Zv83(paramZxf2);
    Zv81 zv81 = new Zv81(paramZxf2);
    Zv8u zv8u = new Zv8u(paramZxf2);
    Zv8w zv8w = new Zv8w(zl7h, paramZr69, paramZz1m1, paramZez7, paramZlas, paramZt1g);
    Zv8n zv8n = new Zv8n(zl7h, paramZr69, paramZz1m1, paramZez7, paramZlas, paramZt1g);
    return Zejc.<Zg0z, Zvb>Zb(Zg0z.class, Zvb.class).ZQ(b + b).ZB(new Zg0z[] { 
          zv89, zv8i, zv82, zv8q, zzsa, zv8s, zslr, zv83, zv81, zv8u, 
          zv8w, zv8n }).Zz(zv89).Zs(zv89, (Class)Zbo4.class, zv82).Zs(zv89, (Class)Ze8_.class, zv8w).Zs(zv89, (Class)Zljv.class, zv8w).Zs(zv89, (Class)Zmkm.class, zv8n).Zs(zv82, (Class)Ze8_.class, zv8w).Zs(zv82, (Class)Zx64.class, zv8q).Zs(zv8q, (Class)Zgec.class, zv8n).Zs(zv8q, (Class)Zx64.class, zzsa).Zs(zzsa, (Class)Zx6_.class, zv8s).Zs(zzsa, (Class)Zmkm.class, zv8n).Zs(zv8s, (Class)Zx66.class, zv83).Zs(zv8s, (Class)Zx6z.class, zv81).Zs(zv8s, (Class)Zx6x.class, zv8u).Zs(zv83, (Class)Zx64.class, zzsa).Zs(zv83, (Class)Ze79.class, zv8i).Zs(zv81, (Class)Zx64.class, zzsa).Zs(zv81, (Class)Ze79.class, zv8i).Zs(zv8u, (Class)Zx6j.class, zslr).Zs(zv8u, (Class)Zx64.class, zzsa).Zs(zv8u, (Class)Ze79.class, zv8i).Zs(zslr, (Class)Ze79.class, zv8i).Zs(zv8i, (Class)Zbo4.class, zv82).Zs(zv8i, (Class)Ze8_.class, zv8w).Zs(zv8i, (Class)Zmnv.class, zv8w).Zs(zv8i, (Class)Zmkm.class, zv8n).ZS(paramZr69::lambda$buildPathWalkerMachine$0).Zx(zv8w).ZS();
  }
  
  private static void lambda$buildPathWalkerMachine$0(Zr69 paramZr69, Zg0z paramZg0z1, Zvb paramZvb, Zg0z paramZg0z2) {
    paramZr69.ZD().Zy(Zrp6.TRACE, Zlq7.PATH_WALKER_STATE_TRANSITION, new Object[] { paramZvb, paramZg0z1, paramZg0z2 });
  }
  
  static {
    // Byte code:
    //   0: bipush #80
    //   2: ldc 'e;Q7r\\fs^?WrQ\\fl^w'
    //   4: iconst_m1
    //   5: goto -> 14
    //   8: putstatic burp/Zm47.b : Ljava/lang/String;
    //   11: goto -> 154
    //   14: dup_x2
    //   15: pop
    //   16: invokevirtual toCharArray : ()[C
    //   19: dup_x1
    //   20: arraylength
    //   21: dup_x2
    //   22: pop
    //   23: iconst_0
    //   24: istore_0
    //   25: dup2_x1
    //   26: pop2
    //   27: dup_x2
    //   28: iconst_1
    //   29: if_icmpgt -> 128
    //   32: dup2
    //   33: swap
    //   34: iload_0
    //   35: dup2_x1
    //   36: caload
    //   37: swap
    //   38: iload_0
    //   39: bipush #7
    //   41: irem
    //   42: tableswitch default -> 110, 0 -> 80, 1 -> 85, 2 -> 90, 3 -> 95, 4 -> 100, 5 -> 105
    //   80: bipush #101
    //   82: goto -> 112
    //   85: bipush #10
    //   87: goto -> 112
    //   90: bipush #117
    //   92: goto -> 112
    //   95: bipush #15
    //   97: goto -> 112
    //   100: bipush #117
    //   102: goto -> 112
    //   105: bipush #61
    //   107: goto -> 112
    //   110: bipush #79
    //   112: ixor
    //   113: ixor
    //   114: i2c
    //   115: castore
    //   116: iinc #0, 1
    //   119: dup
    //   120: ifne -> 128
    //   123: dup2
    //   124: dup_x1
    //   125: goto -> 35
    //   128: dup2_x1
    //   129: pop2
    //   130: dup_x2
    //   131: iload_0
    //   132: if_icmpgt -> 32
    //   135: pop
    //   136: new java/lang/String
    //   139: dup_x1
    //   140: swap
    //   141: invokespecial <init> : ([C)V
    //   144: invokevirtual intern : ()Ljava/lang/String;
    //   147: swap
    //   148: pop
    //   149: swap
    //   150: pop
    //   151: goto -> 8
    //   154: return
  }
}


/* Location:              C:\Program Files\BurpSuitePro\burpsuite_pro.jar!\burp\Zm47.class
 * Java compiler version: 21 (65.0)
 * JD-Core Version:       1.1.3
 */