package burp;

import java.math.BigInteger;

class Zm52 extends ClassLoader {
  static String Ze;
  
  static Object ZR;
  
  private static final String[] a;
  
  private static final String[] b;
  
  static boolean Zn(Object[] paramArrayOfObject, Object paramObject) throws Throwable {
    // Byte code:
    //   0: invokestatic ZK : ()Z
    //   3: istore_2
    //   4: getstatic burp/Zkb_.ZG : Ljava/lang/Object;
    //   7: checkcast java/math/BigInteger
    //   10: invokevirtual toByteArray : ()[B
    //   13: astore_3
    //   14: iconst_0
    //   15: istore #5
    //   17: iconst_0
    //   18: istore #6
    //   20: iload #6
    //   22: aload_3
    //   23: arraylength
    //   24: if_icmpge -> 169
    //   27: aload_3
    //   28: iload #6
    //   30: baload
    //   31: istore #7
    //   33: iload #7
    //   35: bipush #48
    //   37: if_icmplt -> 54
    //   40: iload #7
    //   42: bipush #57
    //   44: if_icmple -> 152
    //   47: goto -> 54
    //   50: invokestatic a : (Ljava/lang/Throwable;)Ljava/lang/Throwable;
    //   53: athrow
    //   54: iload #7
    //   56: bipush #65
    //   58: if_icmplt -> 82
    //   61: goto -> 68
    //   64: invokestatic a : (Ljava/lang/Throwable;)Ljava/lang/Throwable;
    //   67: athrow
    //   68: iload #7
    //   70: bipush #90
    //   72: if_icmple -> 152
    //   75: goto -> 82
    //   78: invokestatic a : (Ljava/lang/Throwable;)Ljava/lang/Throwable;
    //   81: athrow
    //   82: iload #7
    //   84: bipush #97
    //   86: if_icmplt -> 110
    //   89: goto -> 96
    //   92: invokestatic a : (Ljava/lang/Throwable;)Ljava/lang/Throwable;
    //   95: athrow
    //   96: iload #7
    //   98: bipush #122
    //   100: if_icmple -> 152
    //   103: goto -> 110
    //   106: invokestatic a : (Ljava/lang/Throwable;)Ljava/lang/Throwable;
    //   109: athrow
    //   110: iload #7
    //   112: bipush #43
    //   114: if_icmpeq -> 152
    //   117: goto -> 124
    //   120: invokestatic a : (Ljava/lang/Throwable;)Ljava/lang/Throwable;
    //   123: athrow
    //   124: iload #7
    //   126: bipush #47
    //   128: if_icmpeq -> 152
    //   131: goto -> 138
    //   134: invokestatic a : (Ljava/lang/Throwable;)Ljava/lang/Throwable;
    //   137: athrow
    //   138: iload #7
    //   140: bipush #61
    //   142: if_icmpne -> 162
    //   145: goto -> 152
    //   148: invokestatic a : (Ljava/lang/Throwable;)Ljava/lang/Throwable;
    //   151: athrow
    //   152: iinc #5, 1
    //   155: goto -> 162
    //   158: invokestatic a : (Ljava/lang/Throwable;)Ljava/lang/Throwable;
    //   161: athrow
    //   162: iinc #6, 1
    //   165: iload_2
    //   166: ifeq -> 20
    //   169: iload #5
    //   171: newarray byte
    //   173: astore #6
    //   175: iconst_0
    //   176: istore #7
    //   178: iconst_0
    //   179: istore #8
    //   181: iload #8
    //   183: aload_3
    //   184: arraylength
    //   185: if_icmpge -> 337
    //   188: aload_3
    //   189: iload #8
    //   191: baload
    //   192: istore #9
    //   194: iload #9
    //   196: bipush #48
    //   198: if_icmplt -> 215
    //   201: iload #9
    //   203: bipush #57
    //   205: if_icmple -> 313
    //   208: goto -> 215
    //   211: invokestatic a : (Ljava/lang/Throwable;)Ljava/lang/Throwable;
    //   214: athrow
    //   215: iload #9
    //   217: bipush #65
    //   219: if_icmplt -> 243
    //   222: goto -> 229
    //   225: invokestatic a : (Ljava/lang/Throwable;)Ljava/lang/Throwable;
    //   228: athrow
    //   229: iload #9
    //   231: bipush #90
    //   233: if_icmple -> 313
    //   236: goto -> 243
    //   239: invokestatic a : (Ljava/lang/Throwable;)Ljava/lang/Throwable;
    //   242: athrow
    //   243: iload #9
    //   245: bipush #97
    //   247: if_icmplt -> 271
    //   250: goto -> 257
    //   253: invokestatic a : (Ljava/lang/Throwable;)Ljava/lang/Throwable;
    //   256: athrow
    //   257: iload #9
    //   259: bipush #122
    //   261: if_icmple -> 313
    //   264: goto -> 271
    //   267: invokestatic a : (Ljava/lang/Throwable;)Ljava/lang/Throwable;
    //   270: athrow
    //   271: iload #9
    //   273: bipush #43
    //   275: if_icmpeq -> 313
    //   278: goto -> 285
    //   281: invokestatic a : (Ljava/lang/Throwable;)Ljava/lang/Throwable;
    //   284: athrow
    //   285: iload #9
    //   287: bipush #47
    //   289: if_icmpeq -> 313
    //   292: goto -> 299
    //   295: invokestatic a : (Ljava/lang/Throwable;)Ljava/lang/Throwable;
    //   298: athrow
    //   299: iload #9
    //   301: bipush #61
    //   303: if_icmpne -> 330
    //   306: goto -> 313
    //   309: invokestatic a : (Ljava/lang/Throwable;)Ljava/lang/Throwable;
    //   312: athrow
    //   313: aload #6
    //   315: iload #7
    //   317: iload #9
    //   319: bastore
    //   320: iinc #7, 1
    //   323: goto -> 330
    //   326: invokestatic a : (Ljava/lang/Throwable;)Ljava/lang/Throwable;
    //   329: athrow
    //   330: iinc #8, 1
    //   333: iload_2
    //   334: ifeq -> 181
    //   337: aload #6
    //   339: astore #4
    //   341: aload #4
    //   343: astore_3
    //   344: aload_3
    //   345: arraylength
    //   346: istore #5
    //   348: aload_3
    //   349: iload #5
    //   351: iconst_1
    //   352: isub
    //   353: baload
    //   354: bipush #61
    //   356: if_icmpne -> 366
    //   359: iinc #5, -1
    //   362: iload_2
    //   363: ifeq -> 348
    //   366: iload #5
    //   368: aload_3
    //   369: arraylength
    //   370: iconst_4
    //   371: idiv
    //   372: isub
    //   373: newarray byte
    //   375: astore #6
    //   377: iconst_0
    //   378: istore #7
    //   380: iload #7
    //   382: aload_3
    //   383: arraylength
    //   384: if_icmpge -> 646
    //   387: aload_3
    //   388: iload #7
    //   390: baload
    //   391: bipush #61
    //   393: if_icmpne -> 412
    //   396: aload_3
    //   397: iload #7
    //   399: iconst_0
    //   400: bastore
    //   401: iload_2
    //   402: ifeq -> 639
    //   405: goto -> 412
    //   408: invokestatic a : (Ljava/lang/Throwable;)Ljava/lang/Throwable;
    //   411: athrow
    //   412: aload_3
    //   413: iload #7
    //   415: baload
    //   416: bipush #47
    //   418: if_icmpne -> 445
    //   421: goto -> 428
    //   424: invokestatic a : (Ljava/lang/Throwable;)Ljava/lang/Throwable;
    //   427: athrow
    //   428: aload_3
    //   429: iload #7
    //   431: bipush #63
    //   433: bastore
    //   434: iload_2
    //   435: ifeq -> 639
    //   438: goto -> 445
    //   441: invokestatic a : (Ljava/lang/Throwable;)Ljava/lang/Throwable;
    //   444: athrow
    //   445: aload_3
    //   446: iload #7
    //   448: baload
    //   449: bipush #43
    //   451: if_icmpne -> 478
    //   454: goto -> 461
    //   457: invokestatic a : (Ljava/lang/Throwable;)Ljava/lang/Throwable;
    //   460: athrow
    //   461: aload_3
    //   462: iload #7
    //   464: bipush #62
    //   466: bastore
    //   467: iload_2
    //   468: ifeq -> 639
    //   471: goto -> 478
    //   474: invokestatic a : (Ljava/lang/Throwable;)Ljava/lang/Throwable;
    //   477: athrow
    //   478: aload_3
    //   479: iload #7
    //   481: baload
    //   482: bipush #48
    //   484: if_icmplt -> 533
    //   487: goto -> 494
    //   490: invokestatic a : (Ljava/lang/Throwable;)Ljava/lang/Throwable;
    //   493: athrow
    //   494: aload_3
    //   495: iload #7
    //   497: baload
    //   498: bipush #57
    //   500: if_icmpgt -> 533
    //   503: goto -> 510
    //   506: invokestatic a : (Ljava/lang/Throwable;)Ljava/lang/Throwable;
    //   509: athrow
    //   510: aload_3
    //   511: iload #7
    //   513: aload_3
    //   514: iload #7
    //   516: baload
    //   517: bipush #-4
    //   519: isub
    //   520: i2b
    //   521: bastore
    //   522: iload_2
    //   523: ifeq -> 639
    //   526: goto -> 533
    //   529: invokestatic a : (Ljava/lang/Throwable;)Ljava/lang/Throwable;
    //   532: athrow
    //   533: aload_3
    //   534: iload #7
    //   536: baload
    //   537: bipush #97
    //   539: if_icmplt -> 588
    //   542: goto -> 549
    //   545: invokestatic a : (Ljava/lang/Throwable;)Ljava/lang/Throwable;
    //   548: athrow
    //   549: aload_3
    //   550: iload #7
    //   552: baload
    //   553: bipush #122
    //   555: if_icmpgt -> 588
    //   558: goto -> 565
    //   561: invokestatic a : (Ljava/lang/Throwable;)Ljava/lang/Throwable;
    //   564: athrow
    //   565: aload_3
    //   566: iload #7
    //   568: aload_3
    //   569: iload #7
    //   571: baload
    //   572: bipush #71
    //   574: isub
    //   575: i2b
    //   576: bastore
    //   577: iload_2
    //   578: ifeq -> 639
    //   581: goto -> 588
    //   584: invokestatic a : (Ljava/lang/Throwable;)Ljava/lang/Throwable;
    //   587: athrow
    //   588: aload_3
    //   589: iload #7
    //   591: baload
    //   592: bipush #65
    //   594: if_icmplt -> 639
    //   597: goto -> 604
    //   600: invokestatic a : (Ljava/lang/Throwable;)Ljava/lang/Throwable;
    //   603: athrow
    //   604: aload_3
    //   605: iload #7
    //   607: baload
    //   608: bipush #90
    //   610: if_icmpgt -> 639
    //   613: goto -> 620
    //   616: invokestatic a : (Ljava/lang/Throwable;)Ljava/lang/Throwable;
    //   619: athrow
    //   620: aload_3
    //   621: iload #7
    //   623: aload_3
    //   624: iload #7
    //   626: baload
    //   627: bipush #65
    //   629: isub
    //   630: i2b
    //   631: bastore
    //   632: goto -> 639
    //   635: invokestatic a : (Ljava/lang/Throwable;)Ljava/lang/Throwable;
    //   638: athrow
    //   639: iinc #7, 1
    //   642: iload_2
    //   643: ifeq -> 380
    //   646: iconst_0
    //   647: istore #7
    //   649: iconst_0
    //   650: istore #8
    //   652: iload #8
    //   654: aload #6
    //   656: arraylength
    //   657: iconst_2
    //   658: isub
    //   659: if_icmpge -> 762
    //   662: aload #6
    //   664: iload #8
    //   666: aload_3
    //   667: iload #7
    //   669: baload
    //   670: iconst_2
    //   671: ishl
    //   672: sipush #255
    //   675: iand
    //   676: aload_3
    //   677: iload #7
    //   679: iconst_1
    //   680: iadd
    //   681: baload
    //   682: iconst_4
    //   683: iushr
    //   684: iconst_3
    //   685: iand
    //   686: ior
    //   687: i2b
    //   688: bastore
    //   689: aload #6
    //   691: iload #8
    //   693: iconst_1
    //   694: iadd
    //   695: aload_3
    //   696: iload #7
    //   698: iconst_1
    //   699: iadd
    //   700: baload
    //   701: iconst_4
    //   702: ishl
    //   703: sipush #255
    //   706: iand
    //   707: aload_3
    //   708: iload #7
    //   710: iconst_2
    //   711: iadd
    //   712: baload
    //   713: iconst_2
    //   714: iushr
    //   715: bipush #15
    //   717: iand
    //   718: ior
    //   719: i2b
    //   720: bastore
    //   721: aload #6
    //   723: iload #8
    //   725: iconst_2
    //   726: iadd
    //   727: aload_3
    //   728: iload #7
    //   730: iconst_2
    //   731: iadd
    //   732: baload
    //   733: bipush #6
    //   735: ishl
    //   736: sipush #255
    //   739: iand
    //   740: aload_3
    //   741: iload #7
    //   743: iconst_3
    //   744: iadd
    //   745: baload
    //   746: bipush #63
    //   748: iand
    //   749: ior
    //   750: i2b
    //   751: bastore
    //   752: iinc #7, 4
    //   755: iinc #8, 3
    //   758: iload_2
    //   759: ifeq -> 652
    //   762: iload #8
    //   764: aload #6
    //   766: arraylength
    //   767: if_icmpge -> 804
    //   770: aload #6
    //   772: iload #8
    //   774: aload_3
    //   775: iload #7
    //   777: baload
    //   778: iconst_2
    //   779: ishl
    //   780: sipush #255
    //   783: iand
    //   784: aload_3
    //   785: iload #7
    //   787: iconst_1
    //   788: iadd
    //   789: baload
    //   790: iconst_4
    //   791: iushr
    //   792: iconst_3
    //   793: iand
    //   794: ior
    //   795: i2b
    //   796: bastore
    //   797: goto -> 804
    //   800: invokestatic a : (Ljava/lang/Throwable;)Ljava/lang/Throwable;
    //   803: athrow
    //   804: iinc #8, 1
    //   807: iload #8
    //   809: aload #6
    //   811: arraylength
    //   812: if_icmpge -> 852
    //   815: aload #6
    //   817: iload #8
    //   819: aload_3
    //   820: iload #7
    //   822: iconst_1
    //   823: iadd
    //   824: baload
    //   825: iconst_4
    //   826: ishl
    //   827: sipush #255
    //   830: iand
    //   831: aload_3
    //   832: iload #7
    //   834: iconst_2
    //   835: iadd
    //   836: baload
    //   837: iconst_2
    //   838: iushr
    //   839: bipush #15
    //   841: iand
    //   842: ior
    //   843: i2b
    //   844: bastore
    //   845: goto -> 852
    //   848: invokestatic a : (Ljava/lang/Throwable;)Ljava/lang/Throwable;
    //   851: athrow
    //   852: aload #6
    //   854: astore #4
    //   856: new java/math/BigInteger
    //   859: dup
    //   860: aload #4
    //   862: invokespecial <init> : ([B)V
    //   865: invokevirtual abs : ()Ljava/math/BigInteger;
    //   868: putstatic burp/Zgqi.Zp : Ljava/lang/Object;
    //   871: getstatic burp/Zg_5.ZA : Ljava/lang/Object;
    //   874: checkcast java/math/BigInteger
    //   877: invokevirtual toByteArray : ()[B
    //   880: astore_3
    //   881: bipush #64
    //   883: newarray byte
    //   885: dup
    //   886: iconst_0
    //   887: bipush #-128
    //   889: bastore
    //   890: dup
    //   891: iconst_1
    //   892: iconst_0
    //   893: bastore
    //   894: dup
    //   895: iconst_2
    //   896: iconst_0
    //   897: bastore
    //   898: dup
    //   899: iconst_3
    //   900: iconst_0
    //   901: bastore
    //   902: dup
    //   903: iconst_4
    //   904: iconst_0
    //   905: bastore
    //   906: dup
    //   907: iconst_5
    //   908: iconst_0
    //   909: bastore
    //   910: dup
    //   911: bipush #6
    //   913: iconst_0
    //   914: bastore
    //   915: dup
    //   916: bipush #7
    //   918: iconst_0
    //   919: bastore
    //   920: dup
    //   921: bipush #8
    //   923: iconst_0
    //   924: bastore
    //   925: dup
    //   926: bipush #9
    //   928: iconst_0
    //   929: bastore
    //   930: dup
    //   931: bipush #10
    //   933: iconst_0
    //   934: bastore
    //   935: dup
    //   936: bipush #11
    //   938: iconst_0
    //   939: bastore
    //   940: dup
    //   941: bipush #12
    //   943: iconst_0
    //   944: bastore
    //   945: dup
    //   946: bipush #13
    //   948: iconst_0
    //   949: bastore
    //   950: dup
    //   951: bipush #14
    //   953: iconst_0
    //   954: bastore
    //   955: dup
    //   956: bipush #15
    //   958: iconst_0
    //   959: bastore
    //   960: dup
    //   961: bipush #16
    //   963: iconst_0
    //   964: bastore
    //   965: dup
    //   966: bipush #17
    //   968: iconst_0
    //   969: bastore
    //   970: dup
    //   971: bipush #18
    //   973: iconst_0
    //   974: bastore
    //   975: dup
    //   976: bipush #19
    //   978: iconst_0
    //   979: bastore
    //   980: dup
    //   981: bipush #20
    //   983: iconst_0
    //   984: bastore
    //   985: dup
    //   986: bipush #21
    //   988: iconst_0
    //   989: bastore
    //   990: dup
    //   991: bipush #22
    //   993: iconst_0
    //   994: bastore
    //   995: dup
    //   996: bipush #23
    //   998: iconst_0
    //   999: bastore
    //   1000: dup
    //   1001: bipush #24
    //   1003: iconst_0
    //   1004: bastore
    //   1005: dup
    //   1006: bipush #25
    //   1008: iconst_0
    //   1009: bastore
    //   1010: dup
    //   1011: bipush #26
    //   1013: iconst_0
    //   1014: bastore
    //   1015: dup
    //   1016: bipush #27
    //   1018: iconst_0
    //   1019: bastore
    //   1020: dup
    //   1021: bipush #28
    //   1023: iconst_0
    //   1024: bastore
    //   1025: dup
    //   1026: bipush #29
    //   1028: iconst_0
    //   1029: bastore
    //   1030: dup
    //   1031: bipush #30
    //   1033: iconst_0
    //   1034: bastore
    //   1035: dup
    //   1036: bipush #31
    //   1038: iconst_0
    //   1039: bastore
    //   1040: dup
    //   1041: bipush #32
    //   1043: iconst_0
    //   1044: bastore
    //   1045: dup
    //   1046: bipush #33
    //   1048: iconst_0
    //   1049: bastore
    //   1050: dup
    //   1051: bipush #34
    //   1053: iconst_0
    //   1054: bastore
    //   1055: dup
    //   1056: bipush #35
    //   1058: iconst_0
    //   1059: bastore
    //   1060: dup
    //   1061: bipush #36
    //   1063: iconst_0
    //   1064: bastore
    //   1065: dup
    //   1066: bipush #37
    //   1068: iconst_0
    //   1069: bastore
    //   1070: dup
    //   1071: bipush #38
    //   1073: iconst_0
    //   1074: bastore
    //   1075: dup
    //   1076: bipush #39
    //   1078: iconst_0
    //   1079: bastore
    //   1080: dup
    //   1081: bipush #40
    //   1083: iconst_0
    //   1084: bastore
    //   1085: dup
    //   1086: bipush #41
    //   1088: iconst_0
    //   1089: bastore
    //   1090: dup
    //   1091: bipush #42
    //   1093: iconst_0
    //   1094: bastore
    //   1095: dup
    //   1096: bipush #43
    //   1098: iconst_0
    //   1099: bastore
    //   1100: dup
    //   1101: bipush #44
    //   1103: iconst_0
    //   1104: bastore
    //   1105: dup
    //   1106: bipush #45
    //   1108: iconst_0
    //   1109: bastore
    //   1110: dup
    //   1111: bipush #46
    //   1113: iconst_0
    //   1114: bastore
    //   1115: dup
    //   1116: bipush #47
    //   1118: iconst_0
    //   1119: bastore
    //   1120: dup
    //   1121: bipush #48
    //   1123: iconst_0
    //   1124: bastore
    //   1125: dup
    //   1126: bipush #49
    //   1128: iconst_0
    //   1129: bastore
    //   1130: dup
    //   1131: bipush #50
    //   1133: iconst_0
    //   1134: bastore
    //   1135: dup
    //   1136: bipush #51
    //   1138: iconst_0
    //   1139: bastore
    //   1140: dup
    //   1141: bipush #52
    //   1143: iconst_0
    //   1144: bastore
    //   1145: dup
    //   1146: bipush #53
    //   1148: iconst_0
    //   1149: bastore
    //   1150: dup
    //   1151: bipush #54
    //   1153: iconst_0
    //   1154: bastore
    //   1155: dup
    //   1156: bipush #55
    //   1158: iconst_0
    //   1159: bastore
    //   1160: dup
    //   1161: bipush #56
    //   1163: iconst_0
    //   1164: bastore
    //   1165: dup
    //   1166: bipush #57
    //   1168: iconst_0
    //   1169: bastore
    //   1170: dup
    //   1171: bipush #58
    //   1173: iconst_0
    //   1174: bastore
    //   1175: dup
    //   1176: bipush #59
    //   1178: iconst_0
    //   1179: bastore
    //   1180: dup
    //   1181: bipush #60
    //   1183: iconst_0
    //   1184: bastore
    //   1185: dup
    //   1186: bipush #61
    //   1188: iconst_0
    //   1189: bastore
    //   1190: dup
    //   1191: bipush #62
    //   1193: iconst_0
    //   1194: bastore
    //   1195: dup
    //   1196: bipush #63
    //   1198: iconst_0
    //   1199: bastore
    //   1200: astore #5
    //   1202: bipush #64
    //   1204: newarray int
    //   1206: dup
    //   1207: iconst_0
    //   1208: ldc 1116352408
    //   1210: iastore
    //   1211: dup
    //   1212: iconst_1
    //   1213: ldc 1899447441
    //   1215: iastore
    //   1216: dup
    //   1217: iconst_2
    //   1218: ldc -1245643825
    //   1220: iastore
    //   1221: dup
    //   1222: iconst_3
    //   1223: ldc -373957723
    //   1225: iastore
    //   1226: dup
    //   1227: iconst_4
    //   1228: ldc 961987163
    //   1230: iastore
    //   1231: dup
    //   1232: iconst_5
    //   1233: ldc 1508970993
    //   1235: iastore
    //   1236: dup
    //   1237: bipush #6
    //   1239: ldc -1841331548
    //   1241: iastore
    //   1242: dup
    //   1243: bipush #7
    //   1245: ldc -1424204075
    //   1247: iastore
    //   1248: dup
    //   1249: bipush #8
    //   1251: ldc -670586216
    //   1253: iastore
    //   1254: dup
    //   1255: bipush #9
    //   1257: ldc 310598401
    //   1259: iastore
    //   1260: dup
    //   1261: bipush #10
    //   1263: ldc 607225278
    //   1265: iastore
    //   1266: dup
    //   1267: bipush #11
    //   1269: ldc 1426881987
    //   1271: iastore
    //   1272: dup
    //   1273: bipush #12
    //   1275: ldc 1925078388
    //   1277: iastore
    //   1278: dup
    //   1279: bipush #13
    //   1281: ldc -2132889090
    //   1283: iastore
    //   1284: dup
    //   1285: bipush #14
    //   1287: ldc -1680079193
    //   1289: iastore
    //   1290: dup
    //   1291: bipush #15
    //   1293: ldc -1046744716
    //   1295: iastore
    //   1296: dup
    //   1297: bipush #16
    //   1299: ldc -459576895
    //   1301: iastore
    //   1302: dup
    //   1303: bipush #17
    //   1305: ldc -272742522
    //   1307: iastore
    //   1308: dup
    //   1309: bipush #18
    //   1311: ldc 264347078
    //   1313: iastore
    //   1314: dup
    //   1315: bipush #19
    //   1317: ldc 604807628
    //   1319: iastore
    //   1320: dup
    //   1321: bipush #20
    //   1323: ldc 770255983
    //   1325: iastore
    //   1326: dup
    //   1327: bipush #21
    //   1329: ldc 1249150122
    //   1331: iastore
    //   1332: dup
    //   1333: bipush #22
    //   1335: ldc 1555081692
    //   1337: iastore
    //   1338: dup
    //   1339: bipush #23
    //   1341: ldc 1996064986
    //   1343: iastore
    //   1344: dup
    //   1345: bipush #24
    //   1347: ldc -1740746414
    //   1349: iastore
    //   1350: dup
    //   1351: bipush #25
    //   1353: ldc -1473132947
    //   1355: iastore
    //   1356: dup
    //   1357: bipush #26
    //   1359: ldc -1341970488
    //   1361: iastore
    //   1362: dup
    //   1363: bipush #27
    //   1365: ldc -1084653625
    //   1367: iastore
    //   1368: dup
    //   1369: bipush #28
    //   1371: ldc -958395405
    //   1373: iastore
    //   1374: dup
    //   1375: bipush #29
    //   1377: ldc -710438585
    //   1379: iastore
    //   1380: dup
    //   1381: bipush #30
    //   1383: ldc 113926993
    //   1385: iastore
    //   1386: dup
    //   1387: bipush #31
    //   1389: ldc 338241895
    //   1391: iastore
    //   1392: dup
    //   1393: bipush #32
    //   1395: ldc 666307205
    //   1397: iastore
    //   1398: dup
    //   1399: bipush #33
    //   1401: ldc 773529912
    //   1403: iastore
    //   1404: dup
    //   1405: bipush #34
    //   1407: ldc 1294757372
    //   1409: iastore
    //   1410: dup
    //   1411: bipush #35
    //   1413: ldc 1396182291
    //   1415: iastore
    //   1416: dup
    //   1417: bipush #36
    //   1419: ldc 1695183700
    //   1421: iastore
    //   1422: dup
    //   1423: bipush #37
    //   1425: ldc 1986661051
    //   1427: iastore
    //   1428: dup
    //   1429: bipush #38
    //   1431: ldc -2117940946
    //   1433: iastore
    //   1434: dup
    //   1435: bipush #39
    //   1437: ldc -1838011259
    //   1439: iastore
    //   1440: dup
    //   1441: bipush #40
    //   1443: ldc -1564481375
    //   1445: iastore
    //   1446: dup
    //   1447: bipush #41
    //   1449: ldc -1474664885
    //   1451: iastore
    //   1452: dup
    //   1453: bipush #42
    //   1455: ldc -1035236496
    //   1457: iastore
    //   1458: dup
    //   1459: bipush #43
    //   1461: ldc -949202525
    //   1463: iastore
    //   1464: dup
    //   1465: bipush #44
    //   1467: ldc -778901479
    //   1469: iastore
    //   1470: dup
    //   1471: bipush #45
    //   1473: ldc -694614492
    //   1475: iastore
    //   1476: dup
    //   1477: bipush #46
    //   1479: ldc -200395387
    //   1481: iastore
    //   1482: dup
    //   1483: bipush #47
    //   1485: ldc 275423344
    //   1487: iastore
    //   1488: dup
    //   1489: bipush #48
    //   1491: ldc 430227734
    //   1493: iastore
    //   1494: dup
    //   1495: bipush #49
    //   1497: ldc 506948616
    //   1499: iastore
    //   1500: dup
    //   1501: bipush #50
    //   1503: ldc 659060556
    //   1505: iastore
    //   1506: dup
    //   1507: bipush #51
    //   1509: ldc 883997877
    //   1511: iastore
    //   1512: dup
    //   1513: bipush #52
    //   1515: ldc 958139571
    //   1517: iastore
    //   1518: dup
    //   1519: bipush #53
    //   1521: ldc 1322822218
    //   1523: iastore
    //   1524: dup
    //   1525: bipush #54
    //   1527: ldc 1537002063
    //   1529: iastore
    //   1530: dup
    //   1531: bipush #55
    //   1533: ldc 1747873779
    //   1535: iastore
    //   1536: dup
    //   1537: bipush #56
    //   1539: ldc 1955562222
    //   1541: iastore
    //   1542: dup
    //   1543: bipush #57
    //   1545: ldc 2024104815
    //   1547: iastore
    //   1548: dup
    //   1549: bipush #58
    //   1551: ldc -2067236844
    //   1553: iastore
    //   1554: dup
    //   1555: bipush #59
    //   1557: ldc -1933114872
    //   1559: iastore
    //   1560: dup
    //   1561: bipush #60
    //   1563: ldc -1866530822
    //   1565: iastore
    //   1566: dup
    //   1567: bipush #61
    //   1569: ldc -1538233109
    //   1571: iastore
    //   1572: dup
    //   1573: bipush #62
    //   1575: ldc -1090935817
    //   1577: iastore
    //   1578: dup
    //   1579: bipush #63
    //   1581: ldc -965641998
    //   1583: iastore
    //   1584: astore #6
    //   1586: iconst_2
    //   1587: newarray int
    //   1589: dup
    //   1590: iconst_0
    //   1591: iconst_0
    //   1592: iastore
    //   1593: dup
    //   1594: iconst_1
    //   1595: iconst_0
    //   1596: iastore
    //   1597: astore #7
    //   1599: bipush #8
    //   1601: newarray int
    //   1603: dup
    //   1604: iconst_0
    //   1605: ldc 1779033703
    //   1607: iastore
    //   1608: dup
    //   1609: iconst_1
    //   1610: ldc -1150833019
    //   1612: iastore
    //   1613: dup
    //   1614: iconst_2
    //   1615: ldc 1013904242
    //   1617: iastore
    //   1618: dup
    //   1619: iconst_3
    //   1620: ldc -1521486534
    //   1622: iastore
    //   1623: dup
    //   1624: iconst_4
    //   1625: ldc 1359893119
    //   1627: iastore
    //   1628: dup
    //   1629: iconst_5
    //   1630: ldc -1694144372
    //   1632: iastore
    //   1633: dup
    //   1634: bipush #6
    //   1636: ldc 528734635
    //   1638: iastore
    //   1639: dup
    //   1640: bipush #7
    //   1642: ldc 1541459225
    //   1644: iastore
    //   1645: astore #8
    //   1647: bipush #64
    //   1649: newarray byte
    //   1651: astore #9
    //   1653: bipush #64
    //   1655: newarray byte
    //   1657: astore #10
    //   1659: aload_3
    //   1660: arraylength
    //   1661: istore #11
    //   1663: aload #7
    //   1665: iconst_0
    //   1666: iaload
    //   1667: bipush #63
    //   1669: iand
    //   1670: istore #12
    //   1672: aload #7
    //   1674: iconst_0
    //   1675: dup2
    //   1676: iaload
    //   1677: iload #11
    //   1679: iadd
    //   1680: iastore
    //   1681: aload #7
    //   1683: iconst_0
    //   1684: dup2
    //   1685: iaload
    //   1686: iconst_m1
    //   1687: iand
    //   1688: iastore
    //   1689: aload #7
    //   1691: iconst_0
    //   1692: iaload
    //   1693: iload #11
    //   1695: if_icmpge -> 1713
    //   1698: aload #7
    //   1700: iconst_1
    //   1701: dup2
    //   1702: iaload
    //   1703: iconst_1
    //   1704: iadd
    //   1705: iastore
    //   1706: goto -> 1713
    //   1709: invokestatic a : (Ljava/lang/Throwable;)Ljava/lang/Throwable;
    //   1712: athrow
    //   1713: iconst_0
    //   1714: istore #13
    //   1716: iload #11
    //   1718: bipush #64
    //   1720: if_icmplt -> 2329
    //   1723: iconst_0
    //   1724: istore #14
    //   1726: iload #14
    //   1728: bipush #64
    //   1730: if_icmpge -> 1752
    //   1733: aload #10
    //   1735: iload #14
    //   1737: aload_3
    //   1738: iload #13
    //   1740: iload #14
    //   1742: iadd
    //   1743: baload
    //   1744: bastore
    //   1745: iinc #14, 1
    //   1748: iload_2
    //   1749: ifeq -> 1726
    //   1752: bipush #64
    //   1754: newarray int
    //   1756: astore #14
    //   1758: bipush #8
    //   1760: newarray int
    //   1762: astore #15
    //   1764: iconst_0
    //   1765: istore #16
    //   1767: iload #16
    //   1769: bipush #8
    //   1771: if_icmpge -> 1791
    //   1774: aload #15
    //   1776: iload #16
    //   1778: aload #8
    //   1780: iload #16
    //   1782: iaload
    //   1783: iastore
    //   1784: iinc #16, 1
    //   1787: iload_2
    //   1788: ifeq -> 1767
    //   1791: iconst_0
    //   1792: istore #16
    //   1794: iload #16
    //   1796: bipush #64
    //   1798: if_icmpge -> 2289
    //   1801: iload #16
    //   1803: bipush #16
    //   1805: if_icmpge -> 1886
    //   1808: aload #14
    //   1810: iload #16
    //   1812: aload #10
    //   1814: iconst_4
    //   1815: iload #16
    //   1817: imul
    //   1818: baload
    //   1819: sipush #255
    //   1822: iand
    //   1823: bipush #24
    //   1825: ishl
    //   1826: aload #10
    //   1828: iconst_4
    //   1829: iload #16
    //   1831: imul
    //   1832: iconst_1
    //   1833: iadd
    //   1834: baload
    //   1835: sipush #255
    //   1838: iand
    //   1839: bipush #16
    //   1841: ishl
    //   1842: ior
    //   1843: aload #10
    //   1845: iconst_4
    //   1846: iload #16
    //   1848: imul
    //   1849: iconst_2
    //   1850: iadd
    //   1851: baload
    //   1852: sipush #255
    //   1855: iand
    //   1856: bipush #8
    //   1858: ishl
    //   1859: ior
    //   1860: aload #10
    //   1862: iconst_4
    //   1863: iload #16
    //   1865: imul
    //   1866: iconst_3
    //   1867: iadd
    //   1868: baload
    //   1869: sipush #255
    //   1872: iand
    //   1873: ior
    //   1874: iastore
    //   1875: iload_2
    //   1876: ifeq -> 2029
    //   1879: goto -> 1886
    //   1882: invokestatic a : (Ljava/lang/Throwable;)Ljava/lang/Throwable;
    //   1885: athrow
    //   1886: aload #14
    //   1888: iload #16
    //   1890: aload #14
    //   1892: iload #16
    //   1894: iconst_2
    //   1895: isub
    //   1896: iaload
    //   1897: bipush #17
    //   1899: iushr
    //   1900: aload #14
    //   1902: iload #16
    //   1904: iconst_2
    //   1905: isub
    //   1906: iaload
    //   1907: bipush #15
    //   1909: ishl
    //   1910: ior
    //   1911: aload #14
    //   1913: iload #16
    //   1915: iconst_2
    //   1916: isub
    //   1917: iaload
    //   1918: bipush #19
    //   1920: iushr
    //   1921: aload #14
    //   1923: iload #16
    //   1925: iconst_2
    //   1926: isub
    //   1927: iaload
    //   1928: bipush #13
    //   1930: ishl
    //   1931: ior
    //   1932: ixor
    //   1933: aload #14
    //   1935: iload #16
    //   1937: iconst_2
    //   1938: isub
    //   1939: iaload
    //   1940: bipush #10
    //   1942: iushr
    //   1943: ixor
    //   1944: aload #14
    //   1946: iload #16
    //   1948: bipush #7
    //   1950: isub
    //   1951: iaload
    //   1952: iadd
    //   1953: aload #14
    //   1955: iload #16
    //   1957: bipush #15
    //   1959: isub
    //   1960: iaload
    //   1961: bipush #7
    //   1963: iushr
    //   1964: aload #14
    //   1966: iload #16
    //   1968: bipush #15
    //   1970: isub
    //   1971: iaload
    //   1972: bipush #25
    //   1974: ishl
    //   1975: ior
    //   1976: aload #14
    //   1978: iload #16
    //   1980: bipush #15
    //   1982: isub
    //   1983: iaload
    //   1984: bipush #18
    //   1986: iushr
    //   1987: aload #14
    //   1989: iload #16
    //   1991: bipush #15
    //   1993: isub
    //   1994: iaload
    //   1995: bipush #14
    //   1997: ishl
    //   1998: ior
    //   1999: ixor
    //   2000: aload #14
    //   2002: iload #16
    //   2004: bipush #15
    //   2006: isub
    //   2007: iaload
    //   2008: iconst_3
    //   2009: iushr
    //   2010: ixor
    //   2011: iadd
    //   2012: aload #14
    //   2014: iload #16
    //   2016: bipush #16
    //   2018: isub
    //   2019: iaload
    //   2020: iadd
    //   2021: iastore
    //   2022: goto -> 2029
    //   2025: invokestatic a : (Ljava/lang/Throwable;)Ljava/lang/Throwable;
    //   2028: athrow
    //   2029: aload #15
    //   2031: bipush #7
    //   2033: iaload
    //   2034: aload #15
    //   2036: iconst_4
    //   2037: iaload
    //   2038: bipush #6
    //   2040: iushr
    //   2041: aload #15
    //   2043: iconst_4
    //   2044: iaload
    //   2045: bipush #26
    //   2047: ishl
    //   2048: ior
    //   2049: aload #15
    //   2051: iconst_4
    //   2052: iaload
    //   2053: bipush #11
    //   2055: iushr
    //   2056: aload #15
    //   2058: iconst_4
    //   2059: iaload
    //   2060: bipush #21
    //   2062: ishl
    //   2063: ior
    //   2064: ixor
    //   2065: aload #15
    //   2067: iconst_4
    //   2068: iaload
    //   2069: bipush #25
    //   2071: iushr
    //   2072: aload #15
    //   2074: iconst_4
    //   2075: iaload
    //   2076: bipush #7
    //   2078: ishl
    //   2079: ior
    //   2080: ixor
    //   2081: iadd
    //   2082: aload #15
    //   2084: bipush #6
    //   2086: iaload
    //   2087: aload #15
    //   2089: iconst_4
    //   2090: iaload
    //   2091: aload #15
    //   2093: iconst_5
    //   2094: iaload
    //   2095: aload #15
    //   2097: bipush #6
    //   2099: iaload
    //   2100: ixor
    //   2101: iand
    //   2102: ixor
    //   2103: iadd
    //   2104: aload #6
    //   2106: iload #16
    //   2108: iaload
    //   2109: iadd
    //   2110: aload #14
    //   2112: iload #16
    //   2114: iaload
    //   2115: iadd
    //   2116: istore #17
    //   2118: aload #15
    //   2120: iconst_0
    //   2121: iaload
    //   2122: iconst_2
    //   2123: iushr
    //   2124: aload #15
    //   2126: iconst_0
    //   2127: iaload
    //   2128: bipush #30
    //   2130: ishl
    //   2131: ior
    //   2132: aload #15
    //   2134: iconst_0
    //   2135: iaload
    //   2136: bipush #13
    //   2138: iushr
    //   2139: aload #15
    //   2141: iconst_0
    //   2142: iaload
    //   2143: bipush #19
    //   2145: ishl
    //   2146: ior
    //   2147: ixor
    //   2148: aload #15
    //   2150: iconst_0
    //   2151: iaload
    //   2152: bipush #22
    //   2154: iushr
    //   2155: aload #15
    //   2157: iconst_0
    //   2158: iaload
    //   2159: bipush #10
    //   2161: ishl
    //   2162: ior
    //   2163: ixor
    //   2164: aload #15
    //   2166: iconst_0
    //   2167: iaload
    //   2168: aload #15
    //   2170: iconst_1
    //   2171: iaload
    //   2172: iand
    //   2173: aload #15
    //   2175: iconst_2
    //   2176: iaload
    //   2177: aload #15
    //   2179: iconst_0
    //   2180: iaload
    //   2181: aload #15
    //   2183: iconst_1
    //   2184: iaload
    //   2185: ior
    //   2186: iand
    //   2187: ior
    //   2188: iadd
    //   2189: istore #18
    //   2191: aload #15
    //   2193: iconst_3
    //   2194: dup2
    //   2195: iaload
    //   2196: iload #17
    //   2198: iadd
    //   2199: iastore
    //   2200: aload #15
    //   2202: bipush #7
    //   2204: iload #17
    //   2206: iload #18
    //   2208: iadd
    //   2209: iastore
    //   2210: aload #15
    //   2212: bipush #7
    //   2214: iaload
    //   2215: istore #17
    //   2217: aload #15
    //   2219: bipush #7
    //   2221: aload #15
    //   2223: bipush #6
    //   2225: iaload
    //   2226: iastore
    //   2227: aload #15
    //   2229: bipush #6
    //   2231: aload #15
    //   2233: iconst_5
    //   2234: iaload
    //   2235: iastore
    //   2236: aload #15
    //   2238: iconst_5
    //   2239: aload #15
    //   2241: iconst_4
    //   2242: iaload
    //   2243: iastore
    //   2244: aload #15
    //   2246: iconst_4
    //   2247: aload #15
    //   2249: iconst_3
    //   2250: iaload
    //   2251: iastore
    //   2252: aload #15
    //   2254: iconst_3
    //   2255: aload #15
    //   2257: iconst_2
    //   2258: iaload
    //   2259: iastore
    //   2260: aload #15
    //   2262: iconst_2
    //   2263: aload #15
    //   2265: iconst_1
    //   2266: iaload
    //   2267: iastore
    //   2268: aload #15
    //   2270: iconst_1
    //   2271: aload #15
    //   2273: iconst_0
    //   2274: iaload
    //   2275: iastore
    //   2276: aload #15
    //   2278: iconst_0
    //   2279: iload #17
    //   2281: iastore
    //   2282: iinc #16, 1
    //   2285: iload_2
    //   2286: ifeq -> 1794
    //   2289: iconst_0
    //   2290: istore #16
    //   2292: iload #16
    //   2294: bipush #8
    //   2296: if_icmpge -> 2319
    //   2299: aload #8
    //   2301: iload #16
    //   2303: dup2
    //   2304: iaload
    //   2305: aload #15
    //   2307: iload #16
    //   2309: iaload
    //   2310: iadd
    //   2311: iastore
    //   2312: iinc #16, 1
    //   2315: iload_2
    //   2316: ifeq -> 2292
    //   2319: iinc #13, 64
    //   2322: iinc #11, -64
    //   2325: iload_2
    //   2326: ifeq -> 1716
    //   2329: iload #11
    //   2331: ifle -> 2366
    //   2334: iconst_0
    //   2335: istore #14
    //   2337: iload #14
    //   2339: iload #11
    //   2341: if_icmpge -> 2366
    //   2344: aload #9
    //   2346: iload #12
    //   2348: iload #14
    //   2350: iadd
    //   2351: aload_3
    //   2352: iload #13
    //   2354: iload #14
    //   2356: iadd
    //   2357: baload
    //   2358: bastore
    //   2359: iinc #14, 1
    //   2362: iload_2
    //   2363: ifeq -> 2337
    //   2366: aload #7
    //   2368: iconst_0
    //   2369: iaload
    //   2370: bipush #29
    //   2372: iushr
    //   2373: aload #7
    //   2375: iconst_1
    //   2376: iaload
    //   2377: iconst_3
    //   2378: ishl
    //   2379: ior
    //   2380: istore #14
    //   2382: aload #7
    //   2384: iconst_0
    //   2385: iaload
    //   2386: iconst_3
    //   2387: ishl
    //   2388: istore #15
    //   2390: aload #7
    //   2392: iconst_0
    //   2393: iaload
    //   2394: bipush #63
    //   2396: iand
    //   2397: istore #16
    //   2399: iload #16
    //   2401: bipush #56
    //   2403: if_icmpge -> 2418
    //   2406: bipush #56
    //   2408: iload #16
    //   2410: isub
    //   2411: goto -> 2423
    //   2414: invokestatic a : (Ljava/lang/Throwable;)Ljava/lang/Throwable;
    //   2417: athrow
    //   2418: bipush #120
    //   2420: iload #16
    //   2422: isub
    //   2423: istore #17
    //   2425: aload #7
    //   2427: iconst_0
    //   2428: iaload
    //   2429: bipush #63
    //   2431: iand
    //   2432: istore #12
    //   2434: bipush #64
    //   2436: iload #12
    //   2438: isub
    //   2439: istore #18
    //   2441: aload #7
    //   2443: iconst_0
    //   2444: dup2
    //   2445: iaload
    //   2446: iload #17
    //   2448: iadd
    //   2449: iastore
    //   2450: aload #7
    //   2452: iconst_0
    //   2453: dup2
    //   2454: iaload
    //   2455: iconst_m1
    //   2456: iand
    //   2457: iastore
    //   2458: aload #7
    //   2460: iconst_0
    //   2461: iaload
    //   2462: iload #17
    //   2464: if_icmpge -> 2482
    //   2467: aload #7
    //   2469: iconst_1
    //   2470: dup2
    //   2471: iaload
    //   2472: iconst_1
    //   2473: iadd
    //   2474: iastore
    //   2475: goto -> 2482
    //   2478: invokestatic a : (Ljava/lang/Throwable;)Ljava/lang/Throwable;
    //   2481: athrow
    //   2482: iconst_0
    //   2483: istore #13
    //   2485: iload #12
    //   2487: ifle -> 3118
    //   2490: iload #17
    //   2492: iload #18
    //   2494: if_icmplt -> 3118
    //   2497: goto -> 2504
    //   2500: invokestatic a : (Ljava/lang/Throwable;)Ljava/lang/Throwable;
    //   2503: athrow
    //   2504: iconst_0
    //   2505: istore #19
    //   2507: iload #19
    //   2509: iload #18
    //   2511: if_icmpge -> 2534
    //   2514: aload #9
    //   2516: iload #12
    //   2518: iload #19
    //   2520: iadd
    //   2521: aload #5
    //   2523: iload #19
    //   2525: baload
    //   2526: bastore
    //   2527: iinc #19, 1
    //   2530: iload_2
    //   2531: ifeq -> 2507
    //   2534: bipush #64
    //   2536: newarray int
    //   2538: astore #19
    //   2540: bipush #8
    //   2542: newarray int
    //   2544: astore #20
    //   2546: iconst_0
    //   2547: istore #21
    //   2549: iload #21
    //   2551: bipush #8
    //   2553: if_icmpge -> 2573
    //   2556: aload #20
    //   2558: iload #21
    //   2560: aload #8
    //   2562: iload #21
    //   2564: iaload
    //   2565: iastore
    //   2566: iinc #21, 1
    //   2569: iload_2
    //   2570: ifeq -> 2549
    //   2573: iconst_0
    //   2574: istore #21
    //   2576: iload #21
    //   2578: bipush #64
    //   2580: if_icmpge -> 3071
    //   2583: iload #21
    //   2585: bipush #16
    //   2587: if_icmpge -> 2668
    //   2590: aload #19
    //   2592: iload #21
    //   2594: aload #9
    //   2596: iconst_4
    //   2597: iload #21
    //   2599: imul
    //   2600: baload
    //   2601: sipush #255
    //   2604: iand
    //   2605: bipush #24
    //   2607: ishl
    //   2608: aload #9
    //   2610: iconst_4
    //   2611: iload #21
    //   2613: imul
    //   2614: iconst_1
    //   2615: iadd
    //   2616: baload
    //   2617: sipush #255
    //   2620: iand
    //   2621: bipush #16
    //   2623: ishl
    //   2624: ior
    //   2625: aload #9
    //   2627: iconst_4
    //   2628: iload #21
    //   2630: imul
    //   2631: iconst_2
    //   2632: iadd
    //   2633: baload
    //   2634: sipush #255
    //   2637: iand
    //   2638: bipush #8
    //   2640: ishl
    //   2641: ior
    //   2642: aload #9
    //   2644: iconst_4
    //   2645: iload #21
    //   2647: imul
    //   2648: iconst_3
    //   2649: iadd
    //   2650: baload
    //   2651: sipush #255
    //   2654: iand
    //   2655: ior
    //   2656: iastore
    //   2657: iload_2
    //   2658: ifeq -> 2811
    //   2661: goto -> 2668
    //   2664: invokestatic a : (Ljava/lang/Throwable;)Ljava/lang/Throwable;
    //   2667: athrow
    //   2668: aload #19
    //   2670: iload #21
    //   2672: aload #19
    //   2674: iload #21
    //   2676: iconst_2
    //   2677: isub
    //   2678: iaload
    //   2679: bipush #17
    //   2681: iushr
    //   2682: aload #19
    //   2684: iload #21
    //   2686: iconst_2
    //   2687: isub
    //   2688: iaload
    //   2689: bipush #15
    //   2691: ishl
    //   2692: ior
    //   2693: aload #19
    //   2695: iload #21
    //   2697: iconst_2
    //   2698: isub
    //   2699: iaload
    //   2700: bipush #19
    //   2702: iushr
    //   2703: aload #19
    //   2705: iload #21
    //   2707: iconst_2
    //   2708: isub
    //   2709: iaload
    //   2710: bipush #13
    //   2712: ishl
    //   2713: ior
    //   2714: ixor
    //   2715: aload #19
    //   2717: iload #21
    //   2719: iconst_2
    //   2720: isub
    //   2721: iaload
    //   2722: bipush #10
    //   2724: iushr
    //   2725: ixor
    //   2726: aload #19
    //   2728: iload #21
    //   2730: bipush #7
    //   2732: isub
    //   2733: iaload
    //   2734: iadd
    //   2735: aload #19
    //   2737: iload #21
    //   2739: bipush #15
    //   2741: isub
    //   2742: iaload
    //   2743: bipush #7
    //   2745: iushr
    //   2746: aload #19
    //   2748: iload #21
    //   2750: bipush #15
    //   2752: isub
    //   2753: iaload
    //   2754: bipush #25
    //   2756: ishl
    //   2757: ior
    //   2758: aload #19
    //   2760: iload #21
    //   2762: bipush #15
    //   2764: isub
    //   2765: iaload
    //   2766: bipush #18
    //   2768: iushr
    //   2769: aload #19
    //   2771: iload #21
    //   2773: bipush #15
    //   2775: isub
    //   2776: iaload
    //   2777: bipush #14
    //   2779: ishl
    //   2780: ior
    //   2781: ixor
    //   2782: aload #19
    //   2784: iload #21
    //   2786: bipush #15
    //   2788: isub
    //   2789: iaload
    //   2790: iconst_3
    //   2791: iushr
    //   2792: ixor
    //   2793: iadd
    //   2794: aload #19
    //   2796: iload #21
    //   2798: bipush #16
    //   2800: isub
    //   2801: iaload
    //   2802: iadd
    //   2803: iastore
    //   2804: goto -> 2811
    //   2807: invokestatic a : (Ljava/lang/Throwable;)Ljava/lang/Throwable;
    //   2810: athrow
    //   2811: aload #20
    //   2813: bipush #7
    //   2815: iaload
    //   2816: aload #20
    //   2818: iconst_4
    //   2819: iaload
    //   2820: bipush #6
    //   2822: iushr
    //   2823: aload #20
    //   2825: iconst_4
    //   2826: iaload
    //   2827: bipush #26
    //   2829: ishl
    //   2830: ior
    //   2831: aload #20
    //   2833: iconst_4
    //   2834: iaload
    //   2835: bipush #11
    //   2837: iushr
    //   2838: aload #20
    //   2840: iconst_4
    //   2841: iaload
    //   2842: bipush #21
    //   2844: ishl
    //   2845: ior
    //   2846: ixor
    //   2847: aload #20
    //   2849: iconst_4
    //   2850: iaload
    //   2851: bipush #25
    //   2853: iushr
    //   2854: aload #20
    //   2856: iconst_4
    //   2857: iaload
    //   2858: bipush #7
    //   2860: ishl
    //   2861: ior
    //   2862: ixor
    //   2863: iadd
    //   2864: aload #20
    //   2866: bipush #6
    //   2868: iaload
    //   2869: aload #20
    //   2871: iconst_4
    //   2872: iaload
    //   2873: aload #20
    //   2875: iconst_5
    //   2876: iaload
    //   2877: aload #20
    //   2879: bipush #6
    //   2881: iaload
    //   2882: ixor
    //   2883: iand
    //   2884: ixor
    //   2885: iadd
    //   2886: aload #6
    //   2888: iload #21
    //   2890: iaload
    //   2891: iadd
    //   2892: aload #19
    //   2894: iload #21
    //   2896: iaload
    //   2897: iadd
    //   2898: istore #22
    //   2900: aload #20
    //   2902: iconst_0
    //   2903: iaload
    //   2904: iconst_2
    //   2905: iushr
    //   2906: aload #20
    //   2908: iconst_0
    //   2909: iaload
    //   2910: bipush #30
    //   2912: ishl
    //   2913: ior
    //   2914: aload #20
    //   2916: iconst_0
    //   2917: iaload
    //   2918: bipush #13
    //   2920: iushr
    //   2921: aload #20
    //   2923: iconst_0
    //   2924: iaload
    //   2925: bipush #19
    //   2927: ishl
    //   2928: ior
    //   2929: ixor
    //   2930: aload #20
    //   2932: iconst_0
    //   2933: iaload
    //   2934: bipush #22
    //   2936: iushr
    //   2937: aload #20
    //   2939: iconst_0
    //   2940: iaload
    //   2941: bipush #10
    //   2943: ishl
    //   2944: ior
    //   2945: ixor
    //   2946: aload #20
    //   2948: iconst_0
    //   2949: iaload
    //   2950: aload #20
    //   2952: iconst_1
    //   2953: iaload
    //   2954: iand
    //   2955: aload #20
    //   2957: iconst_2
    //   2958: iaload
    //   2959: aload #20
    //   2961: iconst_0
    //   2962: iaload
    //   2963: aload #20
    //   2965: iconst_1
    //   2966: iaload
    //   2967: ior
    //   2968: iand
    //   2969: ior
    //   2970: iadd
    //   2971: istore #23
    //   2973: aload #20
    //   2975: iconst_3
    //   2976: dup2
    //   2977: iaload
    //   2978: iload #22
    //   2980: iadd
    //   2981: iastore
    //   2982: aload #20
    //   2984: bipush #7
    //   2986: iload #22
    //   2988: iload #23
    //   2990: iadd
    //   2991: iastore
    //   2992: aload #20
    //   2994: bipush #7
    //   2996: iaload
    //   2997: istore #22
    //   2999: aload #20
    //   3001: bipush #7
    //   3003: aload #20
    //   3005: bipush #6
    //   3007: iaload
    //   3008: iastore
    //   3009: aload #20
    //   3011: bipush #6
    //   3013: aload #20
    //   3015: iconst_5
    //   3016: iaload
    //   3017: iastore
    //   3018: aload #20
    //   3020: iconst_5
    //   3021: aload #20
    //   3023: iconst_4
    //   3024: iaload
    //   3025: iastore
    //   3026: aload #20
    //   3028: iconst_4
    //   3029: aload #20
    //   3031: iconst_3
    //   3032: iaload
    //   3033: iastore
    //   3034: aload #20
    //   3036: iconst_3
    //   3037: aload #20
    //   3039: iconst_2
    //   3040: iaload
    //   3041: iastore
    //   3042: aload #20
    //   3044: iconst_2
    //   3045: aload #20
    //   3047: iconst_1
    //   3048: iaload
    //   3049: iastore
    //   3050: aload #20
    //   3052: iconst_1
    //   3053: aload #20
    //   3055: iconst_0
    //   3056: iaload
    //   3057: iastore
    //   3058: aload #20
    //   3060: iconst_0
    //   3061: iload #22
    //   3063: iastore
    //   3064: iinc #21, 1
    //   3067: iload_2
    //   3068: ifeq -> 2576
    //   3071: iconst_0
    //   3072: istore #21
    //   3074: iload #21
    //   3076: bipush #8
    //   3078: if_icmpge -> 3101
    //   3081: aload #8
    //   3083: iload #21
    //   3085: dup2
    //   3086: iaload
    //   3087: aload #20
    //   3089: iload #21
    //   3091: iaload
    //   3092: iadd
    //   3093: iastore
    //   3094: iinc #21, 1
    //   3097: iload_2
    //   3098: ifeq -> 3074
    //   3101: iload #13
    //   3103: iload #18
    //   3105: iadd
    //   3106: istore #13
    //   3108: iload #17
    //   3110: iload #18
    //   3112: isub
    //   3113: istore #17
    //   3115: iconst_0
    //   3116: istore #12
    //   3118: iload #17
    //   3120: bipush #64
    //   3122: if_icmplt -> 3732
    //   3125: iconst_0
    //   3126: istore #19
    //   3128: iload #19
    //   3130: bipush #64
    //   3132: if_icmpge -> 3155
    //   3135: aload #10
    //   3137: iload #19
    //   3139: aload #5
    //   3141: iload #13
    //   3143: iload #19
    //   3145: iadd
    //   3146: baload
    //   3147: bastore
    //   3148: iinc #19, 1
    //   3151: iload_2
    //   3152: ifeq -> 3128
    //   3155: bipush #64
    //   3157: newarray int
    //   3159: astore #19
    //   3161: bipush #8
    //   3163: newarray int
    //   3165: astore #20
    //   3167: iconst_0
    //   3168: istore #21
    //   3170: iload #21
    //   3172: bipush #8
    //   3174: if_icmpge -> 3194
    //   3177: aload #20
    //   3179: iload #21
    //   3181: aload #8
    //   3183: iload #21
    //   3185: iaload
    //   3186: iastore
    //   3187: iinc #21, 1
    //   3190: iload_2
    //   3191: ifeq -> 3170
    //   3194: iconst_0
    //   3195: istore #21
    //   3197: iload #21
    //   3199: bipush #64
    //   3201: if_icmpge -> 3692
    //   3204: iload #21
    //   3206: bipush #16
    //   3208: if_icmpge -> 3289
    //   3211: aload #19
    //   3213: iload #21
    //   3215: aload #10
    //   3217: iconst_4
    //   3218: iload #21
    //   3220: imul
    //   3221: baload
    //   3222: sipush #255
    //   3225: iand
    //   3226: bipush #24
    //   3228: ishl
    //   3229: aload #10
    //   3231: iconst_4
    //   3232: iload #21
    //   3234: imul
    //   3235: iconst_1
    //   3236: iadd
    //   3237: baload
    //   3238: sipush #255
    //   3241: iand
    //   3242: bipush #16
    //   3244: ishl
    //   3245: ior
    //   3246: aload #10
    //   3248: iconst_4
    //   3249: iload #21
    //   3251: imul
    //   3252: iconst_2
    //   3253: iadd
    //   3254: baload
    //   3255: sipush #255
    //   3258: iand
    //   3259: bipush #8
    //   3261: ishl
    //   3262: ior
    //   3263: aload #10
    //   3265: iconst_4
    //   3266: iload #21
    //   3268: imul
    //   3269: iconst_3
    //   3270: iadd
    //   3271: baload
    //   3272: sipush #255
    //   3275: iand
    //   3276: ior
    //   3277: iastore
    //   3278: iload_2
    //   3279: ifeq -> 3432
    //   3282: goto -> 3289
    //   3285: invokestatic a : (Ljava/lang/Throwable;)Ljava/lang/Throwable;
    //   3288: athrow
    //   3289: aload #19
    //   3291: iload #21
    //   3293: aload #19
    //   3295: iload #21
    //   3297: iconst_2
    //   3298: isub
    //   3299: iaload
    //   3300: bipush #17
    //   3302: iushr
    //   3303: aload #19
    //   3305: iload #21
    //   3307: iconst_2
    //   3308: isub
    //   3309: iaload
    //   3310: bipush #15
    //   3312: ishl
    //   3313: ior
    //   3314: aload #19
    //   3316: iload #21
    //   3318: iconst_2
    //   3319: isub
    //   3320: iaload
    //   3321: bipush #19
    //   3323: iushr
    //   3324: aload #19
    //   3326: iload #21
    //   3328: iconst_2
    //   3329: isub
    //   3330: iaload
    //   3331: bipush #13
    //   3333: ishl
    //   3334: ior
    //   3335: ixor
    //   3336: aload #19
    //   3338: iload #21
    //   3340: iconst_2
    //   3341: isub
    //   3342: iaload
    //   3343: bipush #10
    //   3345: iushr
    //   3346: ixor
    //   3347: aload #19
    //   3349: iload #21
    //   3351: bipush #7
    //   3353: isub
    //   3354: iaload
    //   3355: iadd
    //   3356: aload #19
    //   3358: iload #21
    //   3360: bipush #15
    //   3362: isub
    //   3363: iaload
    //   3364: bipush #7
    //   3366: iushr
    //   3367: aload #19
    //   3369: iload #21
    //   3371: bipush #15
    //   3373: isub
    //   3374: iaload
    //   3375: bipush #25
    //   3377: ishl
    //   3378: ior
    //   3379: aload #19
    //   3381: iload #21
    //   3383: bipush #15
    //   3385: isub
    //   3386: iaload
    //   3387: bipush #18
    //   3389: iushr
    //   3390: aload #19
    //   3392: iload #21
    //   3394: bipush #15
    //   3396: isub
    //   3397: iaload
    //   3398: bipush #14
    //   3400: ishl
    //   3401: ior
    //   3402: ixor
    //   3403: aload #19
    //   3405: iload #21
    //   3407: bipush #15
    //   3409: isub
    //   3410: iaload
    //   3411: iconst_3
    //   3412: iushr
    //   3413: ixor
    //   3414: iadd
    //   3415: aload #19
    //   3417: iload #21
    //   3419: bipush #16
    //   3421: isub
    //   3422: iaload
    //   3423: iadd
    //   3424: iastore
    //   3425: goto -> 3432
    //   3428: invokestatic a : (Ljava/lang/Throwable;)Ljava/lang/Throwable;
    //   3431: athrow
    //   3432: aload #20
    //   3434: bipush #7
    //   3436: iaload
    //   3437: aload #20
    //   3439: iconst_4
    //   3440: iaload
    //   3441: bipush #6
    //   3443: iushr
    //   3444: aload #20
    //   3446: iconst_4
    //   3447: iaload
    //   3448: bipush #26
    //   3450: ishl
    //   3451: ior
    //   3452: aload #20
    //   3454: iconst_4
    //   3455: iaload
    //   3456: bipush #11
    //   3458: iushr
    //   3459: aload #20
    //   3461: iconst_4
    //   3462: iaload
    //   3463: bipush #21
    //   3465: ishl
    //   3466: ior
    //   3467: ixor
    //   3468: aload #20
    //   3470: iconst_4
    //   3471: iaload
    //   3472: bipush #25
    //   3474: iushr
    //   3475: aload #20
    //   3477: iconst_4
    //   3478: iaload
    //   3479: bipush #7
    //   3481: ishl
    //   3482: ior
    //   3483: ixor
    //   3484: iadd
    //   3485: aload #20
    //   3487: bipush #6
    //   3489: iaload
    //   3490: aload #20
    //   3492: iconst_4
    //   3493: iaload
    //   3494: aload #20
    //   3496: iconst_5
    //   3497: iaload
    //   3498: aload #20
    //   3500: bipush #6
    //   3502: iaload
    //   3503: ixor
    //   3504: iand
    //   3505: ixor
    //   3506: iadd
    //   3507: aload #6
    //   3509: iload #21
    //   3511: iaload
    //   3512: iadd
    //   3513: aload #19
    //   3515: iload #21
    //   3517: iaload
    //   3518: iadd
    //   3519: istore #22
    //   3521: aload #20
    //   3523: iconst_0
    //   3524: iaload
    //   3525: iconst_2
    //   3526: iushr
    //   3527: aload #20
    //   3529: iconst_0
    //   3530: iaload
    //   3531: bipush #30
    //   3533: ishl
    //   3534: ior
    //   3535: aload #20
    //   3537: iconst_0
    //   3538: iaload
    //   3539: bipush #13
    //   3541: iushr
    //   3542: aload #20
    //   3544: iconst_0
    //   3545: iaload
    //   3546: bipush #19
    //   3548: ishl
    //   3549: ior
    //   3550: ixor
    //   3551: aload #20
    //   3553: iconst_0
    //   3554: iaload
    //   3555: bipush #22
    //   3557: iushr
    //   3558: aload #20
    //   3560: iconst_0
    //   3561: iaload
    //   3562: bipush #10
    //   3564: ishl
    //   3565: ior
    //   3566: ixor
    //   3567: aload #20
    //   3569: iconst_0
    //   3570: iaload
    //   3571: aload #20
    //   3573: iconst_1
    //   3574: iaload
    //   3575: iand
    //   3576: aload #20
    //   3578: iconst_2
    //   3579: iaload
    //   3580: aload #20
    //   3582: iconst_0
    //   3583: iaload
    //   3584: aload #20
    //   3586: iconst_1
    //   3587: iaload
    //   3588: ior
    //   3589: iand
    //   3590: ior
    //   3591: iadd
    //   3592: istore #23
    //   3594: aload #20
    //   3596: iconst_3
    //   3597: dup2
    //   3598: iaload
    //   3599: iload #22
    //   3601: iadd
    //   3602: iastore
    //   3603: aload #20
    //   3605: bipush #7
    //   3607: iload #22
    //   3609: iload #23
    //   3611: iadd
    //   3612: iastore
    //   3613: aload #20
    //   3615: bipush #7
    //   3617: iaload
    //   3618: istore #22
    //   3620: aload #20
    //   3622: bipush #7
    //   3624: aload #20
    //   3626: bipush #6
    //   3628: iaload
    //   3629: iastore
    //   3630: aload #20
    //   3632: bipush #6
    //   3634: aload #20
    //   3636: iconst_5
    //   3637: iaload
    //   3638: iastore
    //   3639: aload #20
    //   3641: iconst_5
    //   3642: aload #20
    //   3644: iconst_4
    //   3645: iaload
    //   3646: iastore
    //   3647: aload #20
    //   3649: iconst_4
    //   3650: aload #20
    //   3652: iconst_3
    //   3653: iaload
    //   3654: iastore
    //   3655: aload #20
    //   3657: iconst_3
    //   3658: aload #20
    //   3660: iconst_2
    //   3661: iaload
    //   3662: iastore
    //   3663: aload #20
    //   3665: iconst_2
    //   3666: aload #20
    //   3668: iconst_1
    //   3669: iaload
    //   3670: iastore
    //   3671: aload #20
    //   3673: iconst_1
    //   3674: aload #20
    //   3676: iconst_0
    //   3677: iaload
    //   3678: iastore
    //   3679: aload #20
    //   3681: iconst_0
    //   3682: iload #22
    //   3684: iastore
    //   3685: iinc #21, 1
    //   3688: iload_2
    //   3689: ifeq -> 3197
    //   3692: iconst_0
    //   3693: istore #21
    //   3695: iload #21
    //   3697: bipush #8
    //   3699: if_icmpge -> 3722
    //   3702: aload #8
    //   3704: iload #21
    //   3706: dup2
    //   3707: iaload
    //   3708: aload #20
    //   3710: iload #21
    //   3712: iaload
    //   3713: iadd
    //   3714: iastore
    //   3715: iinc #21, 1
    //   3718: iload_2
    //   3719: ifeq -> 3695
    //   3722: iinc #13, 64
    //   3725: iinc #17, -64
    //   3728: iload_2
    //   3729: ifeq -> 3118
    //   3732: iload #17
    //   3734: ifle -> 3770
    //   3737: iconst_0
    //   3738: istore #19
    //   3740: iload #19
    //   3742: iload #17
    //   3744: if_icmpge -> 3770
    //   3747: aload #9
    //   3749: iload #12
    //   3751: iload #19
    //   3753: iadd
    //   3754: aload #5
    //   3756: iload #13
    //   3758: iload #19
    //   3760: iadd
    //   3761: baload
    //   3762: bastore
    //   3763: iinc #19, 1
    //   3766: iload_2
    //   3767: ifeq -> 3740
    //   3770: bipush #8
    //   3772: newarray byte
    //   3774: astore #19
    //   3776: aload #19
    //   3778: iconst_0
    //   3779: iload #14
    //   3781: bipush #24
    //   3783: iushr
    //   3784: i2b
    //   3785: bastore
    //   3786: aload #19
    //   3788: iconst_1
    //   3789: iload #14
    //   3791: bipush #16
    //   3793: iushr
    //   3794: i2b
    //   3795: bastore
    //   3796: aload #19
    //   3798: iconst_2
    //   3799: iload #14
    //   3801: bipush #8
    //   3803: iushr
    //   3804: i2b
    //   3805: bastore
    //   3806: aload #19
    //   3808: iconst_3
    //   3809: iload #14
    //   3811: i2b
    //   3812: bastore
    //   3813: aload #19
    //   3815: iconst_4
    //   3816: iload #15
    //   3818: bipush #24
    //   3820: iushr
    //   3821: i2b
    //   3822: bastore
    //   3823: aload #19
    //   3825: iconst_5
    //   3826: iload #15
    //   3828: bipush #16
    //   3830: iushr
    //   3831: i2b
    //   3832: bastore
    //   3833: aload #19
    //   3835: bipush #6
    //   3837: iload #15
    //   3839: bipush #8
    //   3841: iushr
    //   3842: i2b
    //   3843: bastore
    //   3844: aload #19
    //   3846: bipush #7
    //   3848: iload #15
    //   3850: i2b
    //   3851: bastore
    //   3852: bipush #8
    //   3854: istore #11
    //   3856: aload #7
    //   3858: iconst_0
    //   3859: iaload
    //   3860: bipush #63
    //   3862: iand
    //   3863: istore #12
    //   3865: bipush #64
    //   3867: iload #12
    //   3869: isub
    //   3870: istore #18
    //   3872: aload #7
    //   3874: iconst_0
    //   3875: dup2
    //   3876: iaload
    //   3877: iload #11
    //   3879: iadd
    //   3880: iastore
    //   3881: aload #7
    //   3883: iconst_0
    //   3884: dup2
    //   3885: iaload
    //   3886: iconst_m1
    //   3887: iand
    //   3888: iastore
    //   3889: aload #7
    //   3891: iconst_0
    //   3892: iaload
    //   3893: iload #11
    //   3895: if_icmpge -> 3913
    //   3898: aload #7
    //   3900: iconst_1
    //   3901: dup2
    //   3902: iaload
    //   3903: iconst_1
    //   3904: iadd
    //   3905: iastore
    //   3906: goto -> 3913
    //   3909: invokestatic a : (Ljava/lang/Throwable;)Ljava/lang/Throwable;
    //   3912: athrow
    //   3913: iload #12
    //   3915: ifle -> 4529
    //   3918: iload #11
    //   3920: iload #18
    //   3922: if_icmplt -> 4529
    //   3925: goto -> 3932
    //   3928: invokestatic a : (Ljava/lang/Throwable;)Ljava/lang/Throwable;
    //   3931: athrow
    //   3932: iconst_0
    //   3933: istore #20
    //   3935: iload #20
    //   3937: iload #18
    //   3939: if_icmpge -> 3962
    //   3942: aload #9
    //   3944: iload #12
    //   3946: iload #20
    //   3948: iadd
    //   3949: aload #19
    //   3951: iload #20
    //   3953: baload
    //   3954: bastore
    //   3955: iinc #20, 1
    //   3958: iload_2
    //   3959: ifeq -> 3935
    //   3962: bipush #64
    //   3964: newarray int
    //   3966: astore #20
    //   3968: bipush #8
    //   3970: newarray int
    //   3972: astore #21
    //   3974: iconst_0
    //   3975: istore #22
    //   3977: iload #22
    //   3979: bipush #8
    //   3981: if_icmpge -> 4001
    //   3984: aload #21
    //   3986: iload #22
    //   3988: aload #8
    //   3990: iload #22
    //   3992: iaload
    //   3993: iastore
    //   3994: iinc #22, 1
    //   3997: iload_2
    //   3998: ifeq -> 3977
    //   4001: iconst_0
    //   4002: istore #22
    //   4004: iload #22
    //   4006: bipush #64
    //   4008: if_icmpge -> 4499
    //   4011: iload #22
    //   4013: bipush #16
    //   4015: if_icmpge -> 4096
    //   4018: aload #20
    //   4020: iload #22
    //   4022: aload #9
    //   4024: iconst_4
    //   4025: iload #22
    //   4027: imul
    //   4028: baload
    //   4029: sipush #255
    //   4032: iand
    //   4033: bipush #24
    //   4035: ishl
    //   4036: aload #9
    //   4038: iconst_4
    //   4039: iload #22
    //   4041: imul
    //   4042: iconst_1
    //   4043: iadd
    //   4044: baload
    //   4045: sipush #255
    //   4048: iand
    //   4049: bipush #16
    //   4051: ishl
    //   4052: ior
    //   4053: aload #9
    //   4055: iconst_4
    //   4056: iload #22
    //   4058: imul
    //   4059: iconst_2
    //   4060: iadd
    //   4061: baload
    //   4062: sipush #255
    //   4065: iand
    //   4066: bipush #8
    //   4068: ishl
    //   4069: ior
    //   4070: aload #9
    //   4072: iconst_4
    //   4073: iload #22
    //   4075: imul
    //   4076: iconst_3
    //   4077: iadd
    //   4078: baload
    //   4079: sipush #255
    //   4082: iand
    //   4083: ior
    //   4084: iastore
    //   4085: iload_2
    //   4086: ifeq -> 4239
    //   4089: goto -> 4096
    //   4092: invokestatic a : (Ljava/lang/Throwable;)Ljava/lang/Throwable;
    //   4095: athrow
    //   4096: aload #20
    //   4098: iload #22
    //   4100: aload #20
    //   4102: iload #22
    //   4104: iconst_2
    //   4105: isub
    //   4106: iaload
    //   4107: bipush #17
    //   4109: iushr
    //   4110: aload #20
    //   4112: iload #22
    //   4114: iconst_2
    //   4115: isub
    //   4116: iaload
    //   4117: bipush #15
    //   4119: ishl
    //   4120: ior
    //   4121: aload #20
    //   4123: iload #22
    //   4125: iconst_2
    //   4126: isub
    //   4127: iaload
    //   4128: bipush #19
    //   4130: iushr
    //   4131: aload #20
    //   4133: iload #22
    //   4135: iconst_2
    //   4136: isub
    //   4137: iaload
    //   4138: bipush #13
    //   4140: ishl
    //   4141: ior
    //   4142: ixor
    //   4143: aload #20
    //   4145: iload #22
    //   4147: iconst_2
    //   4148: isub
    //   4149: iaload
    //   4150: bipush #10
    //   4152: iushr
    //   4153: ixor
    //   4154: aload #20
    //   4156: iload #22
    //   4158: bipush #7
    //   4160: isub
    //   4161: iaload
    //   4162: iadd
    //   4163: aload #20
    //   4165: iload #22
    //   4167: bipush #15
    //   4169: isub
    //   4170: iaload
    //   4171: bipush #7
    //   4173: iushr
    //   4174: aload #20
    //   4176: iload #22
    //   4178: bipush #15
    //   4180: isub
    //   4181: iaload
    //   4182: bipush #25
    //   4184: ishl
    //   4185: ior
    //   4186: aload #20
    //   4188: iload #22
    //   4190: bipush #15
    //   4192: isub
    //   4193: iaload
    //   4194: bipush #18
    //   4196: iushr
    //   4197: aload #20
    //   4199: iload #22
    //   4201: bipush #15
    //   4203: isub
    //   4204: iaload
    //   4205: bipush #14
    //   4207: ishl
    //   4208: ior
    //   4209: ixor
    //   4210: aload #20
    //   4212: iload #22
    //   4214: bipush #15
    //   4216: isub
    //   4217: iaload
    //   4218: iconst_3
    //   4219: iushr
    //   4220: ixor
    //   4221: iadd
    //   4222: aload #20
    //   4224: iload #22
    //   4226: bipush #16
    //   4228: isub
    //   4229: iaload
    //   4230: iadd
    //   4231: iastore
    //   4232: goto -> 4239
    //   4235: invokestatic a : (Ljava/lang/Throwable;)Ljava/lang/Throwable;
    //   4238: athrow
    //   4239: aload #21
    //   4241: bipush #7
    //   4243: iaload
    //   4244: aload #21
    //   4246: iconst_4
    //   4247: iaload
    //   4248: bipush #6
    //   4250: iushr
    //   4251: aload #21
    //   4253: iconst_4
    //   4254: iaload
    //   4255: bipush #26
    //   4257: ishl
    //   4258: ior
    //   4259: aload #21
    //   4261: iconst_4
    //   4262: iaload
    //   4263: bipush #11
    //   4265: iushr
    //   4266: aload #21
    //   4268: iconst_4
    //   4269: iaload
    //   4270: bipush #21
    //   4272: ishl
    //   4273: ior
    //   4274: ixor
    //   4275: aload #21
    //   4277: iconst_4
    //   4278: iaload
    //   4279: bipush #25
    //   4281: iushr
    //   4282: aload #21
    //   4284: iconst_4
    //   4285: iaload
    //   4286: bipush #7
    //   4288: ishl
    //   4289: ior
    //   4290: ixor
    //   4291: iadd
    //   4292: aload #21
    //   4294: bipush #6
    //   4296: iaload
    //   4297: aload #21
    //   4299: iconst_4
    //   4300: iaload
    //   4301: aload #21
    //   4303: iconst_5
    //   4304: iaload
    //   4305: aload #21
    //   4307: bipush #6
    //   4309: iaload
    //   4310: ixor
    //   4311: iand
    //   4312: ixor
    //   4313: iadd
    //   4314: aload #6
    //   4316: iload #22
    //   4318: iaload
    //   4319: iadd
    //   4320: aload #20
    //   4322: iload #22
    //   4324: iaload
    //   4325: iadd
    //   4326: istore #23
    //   4328: aload #21
    //   4330: iconst_0
    //   4331: iaload
    //   4332: iconst_2
    //   4333: iushr
    //   4334: aload #21
    //   4336: iconst_0
    //   4337: iaload
    //   4338: bipush #30
    //   4340: ishl
    //   4341: ior
    //   4342: aload #21
    //   4344: iconst_0
    //   4345: iaload
    //   4346: bipush #13
    //   4348: iushr
    //   4349: aload #21
    //   4351: iconst_0
    //   4352: iaload
    //   4353: bipush #19
    //   4355: ishl
    //   4356: ior
    //   4357: ixor
    //   4358: aload #21
    //   4360: iconst_0
    //   4361: iaload
    //   4362: bipush #22
    //   4364: iushr
    //   4365: aload #21
    //   4367: iconst_0
    //   4368: iaload
    //   4369: bipush #10
    //   4371: ishl
    //   4372: ior
    //   4373: ixor
    //   4374: aload #21
    //   4376: iconst_0
    //   4377: iaload
    //   4378: aload #21
    //   4380: iconst_1
    //   4381: iaload
    //   4382: iand
    //   4383: aload #21
    //   4385: iconst_2
    //   4386: iaload
    //   4387: aload #21
    //   4389: iconst_0
    //   4390: iaload
    //   4391: aload #21
    //   4393: iconst_1
    //   4394: iaload
    //   4395: ior
    //   4396: iand
    //   4397: ior
    //   4398: iadd
    //   4399: istore #24
    //   4401: aload #21
    //   4403: iconst_3
    //   4404: dup2
    //   4405: iaload
    //   4406: iload #23
    //   4408: iadd
    //   4409: iastore
    //   4410: aload #21
    //   4412: bipush #7
    //   4414: iload #23
    //   4416: iload #24
    //   4418: iadd
    //   4419: iastore
    //   4420: aload #21
    //   4422: bipush #7
    //   4424: iaload
    //   4425: istore #23
    //   4427: aload #21
    //   4429: bipush #7
    //   4431: aload #21
    //   4433: bipush #6
    //   4435: iaload
    //   4436: iastore
    //   4437: aload #21
    //   4439: bipush #6
    //   4441: aload #21
    //   4443: iconst_5
    //   4444: iaload
    //   4445: iastore
    //   4446: aload #21
    //   4448: iconst_5
    //   4449: aload #21
    //   4451: iconst_4
    //   4452: iaload
    //   4453: iastore
    //   4454: aload #21
    //   4456: iconst_4
    //   4457: aload #21
    //   4459: iconst_3
    //   4460: iaload
    //   4461: iastore
    //   4462: aload #21
    //   4464: iconst_3
    //   4465: aload #21
    //   4467: iconst_2
    //   4468: iaload
    //   4469: iastore
    //   4470: aload #21
    //   4472: iconst_2
    //   4473: aload #21
    //   4475: iconst_1
    //   4476: iaload
    //   4477: iastore
    //   4478: aload #21
    //   4480: iconst_1
    //   4481: aload #21
    //   4483: iconst_0
    //   4484: iaload
    //   4485: iastore
    //   4486: aload #21
    //   4488: iconst_0
    //   4489: iload #23
    //   4491: iastore
    //   4492: iinc #22, 1
    //   4495: iload_2
    //   4496: ifeq -> 4004
    //   4499: iconst_0
    //   4500: istore #22
    //   4502: iload #22
    //   4504: bipush #8
    //   4506: if_icmpge -> 4529
    //   4509: aload #8
    //   4511: iload #22
    //   4513: dup2
    //   4514: iaload
    //   4515: aload #21
    //   4517: iload #22
    //   4519: iaload
    //   4520: iadd
    //   4521: iastore
    //   4522: iinc #22, 1
    //   4525: iload_2
    //   4526: ifeq -> 4502
    //   4529: bipush #32
    //   4531: newarray byte
    //   4533: astore #4
    //   4535: sipush #13678
    //   4538: aload #4
    //   4540: iconst_0
    //   4541: aload #8
    //   4543: iconst_0
    //   4544: iaload
    //   4545: bipush #24
    //   4547: iushr
    //   4548: i2b
    //   4549: bastore
    //   4550: sipush #7041
    //   4553: aload #4
    //   4555: iconst_1
    //   4556: aload #8
    //   4558: iconst_0
    //   4559: iaload
    //   4560: bipush #16
    //   4562: iushr
    //   4563: i2b
    //   4564: bastore
    //   4565: aload #4
    //   4567: iconst_2
    //   4568: aload #8
    //   4570: iconst_0
    //   4571: iaload
    //   4572: bipush #8
    //   4574: iushr
    //   4575: i2b
    //   4576: bastore
    //   4577: aload #4
    //   4579: iconst_3
    //   4580: aload #8
    //   4582: iconst_0
    //   4583: iaload
    //   4584: i2b
    //   4585: bastore
    //   4586: aload #4
    //   4588: iconst_4
    //   4589: aload #8
    //   4591: iconst_1
    //   4592: iaload
    //   4593: bipush #24
    //   4595: iushr
    //   4596: i2b
    //   4597: bastore
    //   4598: aload #4
    //   4600: iconst_5
    //   4601: aload #8
    //   4603: iconst_1
    //   4604: iaload
    //   4605: bipush #16
    //   4607: iushr
    //   4608: i2b
    //   4609: bastore
    //   4610: aload #4
    //   4612: bipush #6
    //   4614: aload #8
    //   4616: iconst_1
    //   4617: iaload
    //   4618: bipush #8
    //   4620: iushr
    //   4621: i2b
    //   4622: bastore
    //   4623: aload #4
    //   4625: bipush #7
    //   4627: aload #8
    //   4629: iconst_1
    //   4630: iaload
    //   4631: i2b
    //   4632: bastore
    //   4633: aload #4
    //   4635: bipush #8
    //   4637: aload #8
    //   4639: iconst_2
    //   4640: iaload
    //   4641: bipush #24
    //   4643: iushr
    //   4644: i2b
    //   4645: bastore
    //   4646: aload #4
    //   4648: bipush #9
    //   4650: aload #8
    //   4652: iconst_2
    //   4653: iaload
    //   4654: bipush #16
    //   4656: iushr
    //   4657: i2b
    //   4658: bastore
    //   4659: aload #4
    //   4661: bipush #10
    //   4663: aload #8
    //   4665: iconst_2
    //   4666: iaload
    //   4667: bipush #8
    //   4669: iushr
    //   4670: i2b
    //   4671: bastore
    //   4672: aload #4
    //   4674: bipush #11
    //   4676: aload #8
    //   4678: iconst_2
    //   4679: iaload
    //   4680: i2b
    //   4681: bastore
    //   4682: aload #4
    //   4684: bipush #12
    //   4686: aload #8
    //   4688: iconst_3
    //   4689: iaload
    //   4690: bipush #24
    //   4692: iushr
    //   4693: i2b
    //   4694: bastore
    //   4695: aload #4
    //   4697: bipush #13
    //   4699: aload #8
    //   4701: iconst_3
    //   4702: iaload
    //   4703: bipush #16
    //   4705: iushr
    //   4706: i2b
    //   4707: bastore
    //   4708: aload #4
    //   4710: bipush #14
    //   4712: aload #8
    //   4714: iconst_3
    //   4715: iaload
    //   4716: bipush #8
    //   4718: iushr
    //   4719: i2b
    //   4720: bastore
    //   4721: aload #4
    //   4723: bipush #15
    //   4725: aload #8
    //   4727: iconst_3
    //   4728: iaload
    //   4729: i2b
    //   4730: bastore
    //   4731: aload #4
    //   4733: bipush #16
    //   4735: aload #8
    //   4737: iconst_4
    //   4738: iaload
    //   4739: bipush #24
    //   4741: iushr
    //   4742: i2b
    //   4743: bastore
    //   4744: aload #4
    //   4746: bipush #17
    //   4748: aload #8
    //   4750: iconst_4
    //   4751: iaload
    //   4752: bipush #16
    //   4754: iushr
    //   4755: i2b
    //   4756: bastore
    //   4757: aload #4
    //   4759: bipush #18
    //   4761: aload #8
    //   4763: iconst_4
    //   4764: iaload
    //   4765: bipush #8
    //   4767: iushr
    //   4768: i2b
    //   4769: bastore
    //   4770: aload #4
    //   4772: bipush #19
    //   4774: aload #8
    //   4776: iconst_4
    //   4777: iaload
    //   4778: i2b
    //   4779: bastore
    //   4780: aload #4
    //   4782: bipush #20
    //   4784: aload #8
    //   4786: iconst_5
    //   4787: iaload
    //   4788: bipush #24
    //   4790: iushr
    //   4791: i2b
    //   4792: bastore
    //   4793: aload #4
    //   4795: bipush #21
    //   4797: aload #8
    //   4799: iconst_5
    //   4800: iaload
    //   4801: bipush #16
    //   4803: iushr
    //   4804: i2b
    //   4805: bastore
    //   4806: aload #4
    //   4808: bipush #22
    //   4810: aload #8
    //   4812: iconst_5
    //   4813: iaload
    //   4814: bipush #8
    //   4816: iushr
    //   4817: i2b
    //   4818: bastore
    //   4819: aload #4
    //   4821: bipush #23
    //   4823: aload #8
    //   4825: iconst_5
    //   4826: iaload
    //   4827: i2b
    //   4828: bastore
    //   4829: aload #4
    //   4831: bipush #24
    //   4833: aload #8
    //   4835: bipush #6
    //   4837: iaload
    //   4838: bipush #24
    //   4840: iushr
    //   4841: i2b
    //   4842: bastore
    //   4843: aload #4
    //   4845: bipush #25
    //   4847: aload #8
    //   4849: bipush #6
    //   4851: iaload
    //   4852: bipush #16
    //   4854: iushr
    //   4855: i2b
    //   4856: bastore
    //   4857: aload #4
    //   4859: bipush #26
    //   4861: aload #8
    //   4863: bipush #6
    //   4865: iaload
    //   4866: bipush #8
    //   4868: iushr
    //   4869: i2b
    //   4870: bastore
    //   4871: aload #4
    //   4873: bipush #27
    //   4875: aload #8
    //   4877: bipush #6
    //   4879: iaload
    //   4880: i2b
    //   4881: bastore
    //   4882: aload #4
    //   4884: bipush #28
    //   4886: aload #8
    //   4888: bipush #7
    //   4890: iaload
    //   4891: bipush #24
    //   4893: iushr
    //   4894: i2b
    //   4895: bastore
    //   4896: aload #4
    //   4898: bipush #29
    //   4900: aload #8
    //   4902: bipush #7
    //   4904: iaload
    //   4905: bipush #16
    //   4907: iushr
    //   4908: i2b
    //   4909: bastore
    //   4910: aload #4
    //   4912: bipush #30
    //   4914: aload #8
    //   4916: bipush #7
    //   4918: iaload
    //   4919: bipush #8
    //   4921: iushr
    //   4922: i2b
    //   4923: bastore
    //   4924: aload #4
    //   4926: bipush #31
    //   4928: aload #8
    //   4930: bipush #7
    //   4932: iaload
    //   4933: i2b
    //   4934: bastore
    //   4935: new java/math/BigInteger
    //   4938: dup
    //   4939: aload #4
    //   4941: invokespecial <init> : ([B)V
    //   4944: invokevirtual abs : ()Ljava/math/BigInteger;
    //   4947: putstatic burp/Ze54.Zx : Ljava/lang/Object;
    //   4950: getstatic burp/Ztsu.Zr : Ljava/lang/Object;
    //   4953: checkcast java/math/BigInteger
    //   4956: getstatic burp/Zlem.ZI : Ljava/lang/Object;
    //   4959: checkcast java/math/BigInteger
    //   4962: invokevirtual subtract : (Ljava/math/BigInteger;)Ljava/math/BigInteger;
    //   4965: putstatic burp/Zb8y.ZI : Ljava/lang/Object;
    //   4968: invokestatic a : (II)Ljava/lang/String;
    //   4971: iconst_1
    //   4972: ldc burp/Zt3l
    //   4974: invokevirtual getClassLoader : ()Ljava/lang/ClassLoader;
    //   4977: invokestatic forName : (Ljava/lang/String;ZLjava/lang/ClassLoader;)Ljava/lang/Class;
    //   4980: invokevirtual getDeclaredFields : ()[Ljava/lang/reflect/Field;
    //   4983: astore_3
    //   4984: aload_3
    //   4985: arraylength
    //   4986: istore #4
    //   4988: iconst_0
    //   4989: istore #5
    //   4991: iload #5
    //   4993: iload #4
    //   4995: if_icmpge -> 5132
    //   4998: aload_3
    //   4999: iload #5
    //   5001: aaload
    //   5002: astore #6
    //   5004: aload #6
    //   5006: invokevirtual getModifiers : ()I
    //   5009: invokestatic isStatic : (I)Z
    //   5012: ifne -> 5022
    //   5015: goto -> 5125
    //   5018: invokestatic a : (Ljava/lang/Throwable;)Ljava/lang/Throwable;
    //   5021: athrow
    //   5022: aload #6
    //   5024: invokevirtual getType : ()Ljava/lang/Class;
    //   5027: astore #7
    //   5029: aload #7
    //   5031: ifnull -> 5112
    //   5034: aload #7
    //   5036: invokevirtual isPrimitive : ()Z
    //   5039: ifne -> 5112
    //   5042: goto -> 5049
    //   5045: invokestatic a : (Ljava/lang/Throwable;)Ljava/lang/Throwable;
    //   5048: athrow
    //   5049: aload #7
    //   5051: invokevirtual getPackage : ()Ljava/lang/Package;
    //   5054: ifnull -> 5112
    //   5057: goto -> 5064
    //   5060: invokestatic a : (Ljava/lang/Throwable;)Ljava/lang/Throwable;
    //   5063: athrow
    //   5064: aload #7
    //   5066: invokevirtual getPackage : ()Ljava/lang/Package;
    //   5069: invokevirtual getName : ()Ljava/lang/String;
    //   5072: ifnull -> 5112
    //   5075: goto -> 5082
    //   5078: invokestatic a : (Ljava/lang/Throwable;)Ljava/lang/Throwable;
    //   5081: athrow
    //   5082: aload #7
    //   5084: invokevirtual getPackage : ()Ljava/lang/Package;
    //   5087: invokevirtual getName : ()Ljava/lang/String;
    //   5090: sipush #13666
    //   5093: sipush #-17470
    //   5096: invokestatic a : (II)Ljava/lang/String;
    //   5099: invokevirtual startsWith : (Ljava/lang/String;)Z
    //   5102: ifne -> 5112
    //   5105: goto -> 5112
    //   5108: invokestatic a : (Ljava/lang/Throwable;)Ljava/lang/Throwable;
    //   5111: athrow
    //   5112: aload #6
    //   5114: iconst_1
    //   5115: invokevirtual setAccessible : (Z)V
    //   5118: aload #6
    //   5120: aconst_null
    //   5121: invokevirtual get : (Ljava/lang/Object;)Ljava/lang/Object;
    //   5124: pop
    //   5125: iinc #5, 1
    //   5128: iload_2
    //   5129: ifeq -> 4991
    //   5132: sipush #13669
    //   5135: sipush #-11257
    //   5138: invokestatic a : (II)Ljava/lang/String;
    //   5141: invokestatic forName : (Ljava/lang/String;)Ljava/lang/Class;
    //   5144: invokevirtual getDeclaredMethods : ()[Ljava/lang/reflect/Method;
    //   5147: astore_3
    //   5148: aload_3
    //   5149: arraylength
    //   5150: istore #4
    //   5152: iconst_0
    //   5153: istore #5
    //   5155: iload #5
    //   5157: iload #4
    //   5159: if_icmpge -> 5291
    //   5162: aload_3
    //   5163: iload #5
    //   5165: aaload
    //   5166: astore #6
    //   5168: aload #6
    //   5170: invokevirtual getParameterTypes : ()[Ljava/lang/Class;
    //   5173: pop
    //   5174: aload #6
    //   5176: invokevirtual getModifiers : ()I
    //   5179: invokestatic isStatic : (I)Z
    //   5182: ifeq -> 5277
    //   5185: aload #6
    //   5187: invokevirtual getParameterTypes : ()[Ljava/lang/Class;
    //   5190: arraylength
    //   5191: iconst_2
    //   5192: if_icmpne -> 5277
    //   5195: goto -> 5202
    //   5198: invokestatic a : (Ljava/lang/Throwable;)Ljava/lang/Throwable;
    //   5201: athrow
    //   5202: aload #6
    //   5204: invokevirtual getReturnType : ()Ljava/lang/Class;
    //   5207: getstatic java/lang/Void.TYPE : Ljava/lang/Class;
    //   5210: invokevirtual equals : (Ljava/lang/Object;)Z
    //   5213: ifeq -> 5277
    //   5216: goto -> 5223
    //   5219: invokestatic a : (Ljava/lang/Throwable;)Ljava/lang/Throwable;
    //   5222: athrow
    //   5223: aload #6
    //   5225: iconst_1
    //   5226: invokevirtual setAccessible : (Z)V
    //   5229: aload #6
    //   5231: aconst_null
    //   5232: iconst_2
    //   5233: anewarray java/lang/Object
    //   5236: dup
    //   5237: iconst_0
    //   5238: aload_0
    //   5239: aastore
    //   5240: dup
    //   5241: iconst_1
    //   5242: aload_1
    //   5243: ifnonnull -> 5261
    //   5246: goto -> 5253
    //   5249: invokestatic a : (Ljava/lang/Throwable;)Ljava/lang/Throwable;
    //   5252: athrow
    //   5253: aload_1
    //   5254: goto -> 5268
    //   5257: invokestatic a : (Ljava/lang/Throwable;)Ljava/lang/Throwable;
    //   5260: athrow
    //   5261: aload_1
    //   5262: checkcast [B
    //   5265: invokevirtual clone : ()Ljava/lang/Object;
    //   5268: aastore
    //   5269: invokevirtual invoke : (Ljava/lang/Object;[Ljava/lang/Object;)Ljava/lang/Object;
    //   5272: pop
    //   5273: iload_2
    //   5274: ifeq -> 5291
    //   5277: iinc #5, 1
    //   5280: iload_2
    //   5281: ifeq -> 5155
    //   5284: goto -> 5291
    //   5287: invokestatic a : (Ljava/lang/Throwable;)Ljava/lang/Throwable;
    //   5290: athrow
    //   5291: new java/io/ByteArrayOutputStream
    //   5294: dup
    //   5295: invokespecial <init> : ()V
    //   5298: astore_3
    //   5299: sipush #13668
    //   5302: aload_3
    //   5303: sipush #202
    //   5306: invokevirtual write : (I)V
    //   5309: sipush #1394
    //   5312: aload_3
    //   5313: sipush #254
    //   5316: invokevirtual write : (I)V
    //   5319: aload_3
    //   5320: sipush #186
    //   5323: invokevirtual write : (I)V
    //   5326: aload_3
    //   5327: sipush #190
    //   5330: invokevirtual write : (I)V
    //   5333: aload_3
    //   5334: iconst_0
    //   5335: invokevirtual write : (I)V
    //   5338: aload_3
    //   5339: iconst_1
    //   5340: invokevirtual write : (I)V
    //   5343: aload_3
    //   5344: iconst_0
    //   5345: invokevirtual write : (I)V
    //   5348: aload_3
    //   5349: bipush #50
    //   5351: invokevirtual write : (I)V
    //   5354: aload_3
    //   5355: getstatic burp/Zme.Zd : Ljava/lang/Object;
    //   5358: checkcast java/math/BigInteger
    //   5361: invokevirtual toByteArray : ()[B
    //   5364: invokevirtual write : ([B)V
    //   5367: aload_3
    //   5368: getstatic burp/Ztpg.Z_ : Ljava/lang/Object;
    //   5371: checkcast java/math/BigInteger
    //   5374: invokevirtual toByteArray : ()[B
    //   5377: invokevirtual write : ([B)V
    //   5380: aload_3
    //   5381: getstatic burp/Zmli.Zh : Ljava/lang/Object;
    //   5384: checkcast java/math/BigInteger
    //   5387: invokevirtual toByteArray : ()[B
    //   5390: invokevirtual write : ([B)V
    //   5393: aload_3
    //   5394: invokevirtual toByteArray : ()[B
    //   5397: astore #4
    //   5399: aconst_null
    //   5400: astore #5
    //   5402: invokestatic a : (II)Ljava/lang/String;
    //   5405: invokestatic forName : (Ljava/lang/String;)Ljava/lang/Class;
    //   5408: invokevirtual getDeclaredMethods : ()[Ljava/lang/reflect/Method;
    //   5411: astore #6
    //   5413: aload #6
    //   5415: arraylength
    //   5416: istore #7
    //   5418: iconst_0
    //   5419: istore #8
    //   5421: iload #8
    //   5423: iload #7
    //   5425: if_icmpge -> 5553
    //   5428: aload #6
    //   5430: iload #8
    //   5432: aaload
    //   5433: astore #9
    //   5435: aload #9
    //   5437: invokevirtual getName : ()Ljava/lang/String;
    //   5440: sipush #13670
    //   5443: sipush #1554
    //   5446: invokestatic a : (II)Ljava/lang/String;
    //   5449: invokevirtual equals : (Ljava/lang/Object;)Z
    //   5452: ifeq -> 5546
    //   5455: aload #9
    //   5457: invokevirtual getParameterTypes : ()[Ljava/lang/Class;
    //   5460: astore #10
    //   5462: aload #10
    //   5464: arraylength
    //   5465: iconst_4
    //   5466: if_icmpeq -> 5476
    //   5469: goto -> 5546
    //   5472: invokestatic a : (Ljava/lang/Throwable;)Ljava/lang/Throwable;
    //   5475: athrow
    //   5476: aload #10
    //   5478: iconst_0
    //   5479: aaload
    //   5480: ldc java/lang/String
    //   5482: if_acmpeq -> 5492
    //   5485: goto -> 5546
    //   5488: invokestatic a : (Ljava/lang/Throwable;)Ljava/lang/Throwable;
    //   5491: athrow
    //   5492: aload #10
    //   5494: iconst_1
    //   5495: aaload
    //   5496: ldc [B
    //   5498: if_acmpeq -> 5508
    //   5501: goto -> 5546
    //   5504: invokestatic a : (Ljava/lang/Throwable;)Ljava/lang/Throwable;
    //   5507: athrow
    //   5508: aload #10
    //   5510: iconst_2
    //   5511: aaload
    //   5512: getstatic java/lang/Integer.TYPE : Ljava/lang/Class;
    //   5515: if_acmpeq -> 5525
    //   5518: goto -> 5546
    //   5521: invokestatic a : (Ljava/lang/Throwable;)Ljava/lang/Throwable;
    //   5524: athrow
    //   5525: aload #10
    //   5527: iconst_3
    //   5528: aaload
    //   5529: getstatic java/lang/Integer.TYPE : Ljava/lang/Class;
    //   5532: if_acmpeq -> 5542
    //   5535: goto -> 5546
    //   5538: invokestatic a : (Ljava/lang/Throwable;)Ljava/lang/Throwable;
    //   5541: athrow
    //   5542: aload #9
    //   5544: astore #5
    //   5546: iinc #8, 1
    //   5549: iload_2
    //   5550: ifeq -> 5421
    //   5553: aload #5
    //   5555: iconst_1
    //   5556: invokevirtual setAccessible : (Z)V
    //   5559: ldc burp/Zeyt
    //   5561: iconst_0
    //   5562: anewarray java/lang/Class
    //   5565: invokevirtual getDeclaredConstructor : ([Ljava/lang/Class;)Ljava/lang/reflect/Constructor;
    //   5568: astore #6
    //   5570: aload #6
    //   5572: iconst_1
    //   5573: invokevirtual setAccessible : (Z)V
    //   5576: aload #5
    //   5578: aload #6
    //   5580: iconst_0
    //   5581: anewarray java/lang/Object
    //   5584: invokevirtual newInstance : ([Ljava/lang/Object;)Ljava/lang/Object;
    //   5587: iconst_4
    //   5588: anewarray java/lang/Object
    //   5591: dup
    //   5592: iconst_0
    //   5593: sipush #13676
    //   5596: sipush #-25489
    //   5599: invokestatic a : (II)Ljava/lang/String;
    //   5602: aastore
    //   5603: dup
    //   5604: iconst_1
    //   5605: aload #4
    //   5607: aastore
    //   5608: dup
    //   5609: iconst_2
    //   5610: iconst_0
    //   5611: invokestatic valueOf : (I)Ljava/lang/Integer;
    //   5614: aastore
    //   5615: dup
    //   5616: iconst_3
    //   5617: aload #4
    //   5619: arraylength
    //   5620: invokestatic valueOf : (I)Ljava/lang/Integer;
    //   5623: aastore
    //   5624: invokevirtual invoke : (Ljava/lang/Object;[Ljava/lang/Object;)Ljava/lang/Object;
    //   5627: pop
    //   5628: goto -> 5632
    //   5631: astore_3
    //   5632: getstatic burp/Ztfh.ZU : Ljava/lang/String;
    //   5635: getstatic burp/Zsxh.Zk : Ljava/lang/Object;
    //   5638: checkcast java/math/BigInteger
    //   5641: invokevirtual intValue : ()I
    //   5644: bipush #32
    //   5646: irem
    //   5647: invokestatic abs : (I)I
    //   5650: invokevirtual charAt : (I)C
    //   5653: getstatic burp/Zlrm.Zt : Ljava/lang/String;
    //   5656: getstatic burp/Ze82.ZR : Ljava/lang/Object;
    //   5659: checkcast java/math/BigInteger
    //   5662: invokevirtual intValue : ()I
    //   5665: bipush #32
    //   5667: irem
    //   5668: invokestatic abs : (I)I
    //   5671: invokevirtual charAt : (I)C
    //   5674: if_icmpgt -> 5789
    //   5677: getstatic burp/Ze8i.ZM : Ljava/lang/String;
    //   5680: getstatic burp/Zm8v.ZU : Ljava/lang/Object;
    //   5683: checkcast java/math/BigInteger
    //   5686: invokevirtual intValue : ()I
    //   5689: bipush #32
    //   5691: irem
    //   5692: invokestatic abs : (I)I
    //   5695: invokevirtual charAt : (I)C
    //   5698: getstatic burp/Zeqg.Zh : Ljava/lang/String;
    //   5701: getstatic burp/Zeuc.Zd : Ljava/lang/Object;
    //   5704: checkcast java/math/BigInteger
    //   5707: invokevirtual intValue : ()I
    //   5710: bipush #32
    //   5712: irem
    //   5713: invokestatic abs : (I)I
    //   5716: invokevirtual charAt : (I)C
    //   5719: if_icmpgt -> 5789
    //   5722: goto -> 5729
    //   5725: invokestatic a : (Ljava/lang/Throwable;)Ljava/lang/Throwable;
    //   5728: athrow
    //   5729: getstatic burp/Zr48.ZG : Ljava/lang/String;
    //   5732: getstatic burp/Zlck.Zr : Ljava/lang/Object;
    //   5735: checkcast java/math/BigInteger
    //   5738: invokevirtual intValue : ()I
    //   5741: bipush #32
    //   5743: irem
    //   5744: invokestatic abs : (I)I
    //   5747: invokevirtual charAt : (I)C
    //   5750: getstatic burp/Zrtv.ZA : Ljava/lang/String;
    //   5753: getstatic burp/Zmyg.Zj : Ljava/lang/Object;
    //   5756: checkcast java/math/BigInteger
    //   5759: invokevirtual intValue : ()I
    //   5762: bipush #32
    //   5764: irem
    //   5765: invokestatic abs : (I)I
    //   5768: invokevirtual charAt : (I)C
    //   5771: if_icmple -> 5789
    //   5774: goto -> 5781
    //   5777: invokestatic a : (Ljava/lang/Throwable;)Ljava/lang/Throwable;
    //   5780: athrow
    //   5781: iconst_1
    //   5782: goto -> 5790
    //   5785: invokestatic a : (Ljava/lang/Throwable;)Ljava/lang/Throwable;
    //   5788: athrow
    //   5789: iconst_0
    //   5790: ireturn
    //   5791: astore_3
    //   5792: new java/lang/Exception
    //   5795: dup
    //   5796: aload_3
    //   5797: invokevirtual getMessage : ()Ljava/lang/String;
    //   5800: invokespecial <init> : (Ljava/lang/String;)V
    //   5803: athrow
    // Exception table:
    //   from	to	target	type
    //   4	5790	5791	java/lang/Throwable
    //   33	47	50	java/lang/Throwable
    //   40	61	64	java/lang/Throwable
    //   54	75	78	java/lang/Throwable
    //   68	89	92	java/lang/Throwable
    //   82	103	106	java/lang/Throwable
    //   96	117	120	java/lang/Throwable
    //   110	131	134	java/lang/Throwable
    //   124	145	148	java/lang/Throwable
    //   138	155	158	java/lang/Throwable
    //   194	208	211	java/lang/Throwable
    //   201	222	225	java/lang/Throwable
    //   215	236	239	java/lang/Throwable
    //   229	250	253	java/lang/Throwable
    //   243	264	267	java/lang/Throwable
    //   257	278	281	java/lang/Throwable
    //   271	292	295	java/lang/Throwable
    //   285	306	309	java/lang/Throwable
    //   299	323	326	java/lang/Throwable
    //   387	405	408	java/lang/Throwable
    //   396	421	424	java/lang/Throwable
    //   412	438	441	java/lang/Throwable
    //   428	454	457	java/lang/Throwable
    //   445	471	474	java/lang/Throwable
    //   461	487	490	java/lang/Throwable
    //   478	503	506	java/lang/Throwable
    //   494	526	529	java/lang/Throwable
    //   510	542	545	java/lang/Throwable
    //   533	558	561	java/lang/Throwable
    //   549	581	584	java/lang/Throwable
    //   565	597	600	java/lang/Throwable
    //   588	613	616	java/lang/Throwable
    //   604	632	635	java/lang/Throwable
    //   762	797	800	java/lang/Throwable
    //   804	845	848	java/lang/Throwable
    //   1672	1706	1709	java/lang/Throwable
    //   1801	1879	1882	java/lang/Throwable
    //   1808	2022	2025	java/lang/Throwable
    //   2399	2414	2414	java/lang/Throwable
    //   2441	2475	2478	java/lang/Throwable
    //   2485	2497	2500	java/lang/Throwable
    //   2583	2661	2664	java/lang/Throwable
    //   2590	2804	2807	java/lang/Throwable
    //   3204	3282	3285	java/lang/Throwable
    //   3211	3425	3428	java/lang/Throwable
    //   3872	3906	3909	java/lang/Throwable
    //   3913	3925	3928	java/lang/Throwable
    //   4011	4089	4092	java/lang/Throwable
    //   4018	4232	4235	java/lang/Throwable
    //   5004	5018	5018	java/lang/Throwable
    //   5029	5042	5045	java/lang/Throwable
    //   5034	5057	5060	java/lang/Throwable
    //   5049	5075	5078	java/lang/Throwable
    //   5064	5105	5108	java/lang/Throwable
    //   5168	5195	5198	java/lang/Throwable
    //   5185	5216	5219	java/lang/Throwable
    //   5202	5246	5249	java/lang/Throwable
    //   5223	5257	5257	java/lang/Throwable
    //   5268	5284	5287	java/lang/Throwable
    //   5291	5628	5631	java/lang/Throwable
    //   5462	5472	5472	java/lang/Throwable
    //   5476	5488	5488	java/lang/Throwable
    //   5492	5504	5504	java/lang/Throwable
    //   5508	5521	5521	java/lang/Throwable
    //   5525	5538	5538	java/lang/Throwable
    //   5632	5722	5725	java/lang/Throwable
    //   5677	5774	5777	java/lang/Throwable
    //   5729	5785	5785	java/lang/Throwable
  }
  
  static void Zj(Object[] paramArrayOfObject, Object paramObject) throws Throwable {}
  
  static void ZC(Object paramObject) {
    Zstb.Zd = a(13667, -32216);
    Zstb.ZC = new BigInteger(a(13679, -31227));
    boolean bool = Zt2e.ZN();
    try {
      try {
        if (Zztk.Zf.charAt(Math.abs(((BigInteger)Zm8v.ZU).intValue() % 32)) > Zel.Zi.charAt(Math.abs(((BigInteger)Zzym.ZK).intValue() % 32))) {
          try {
            Zr48.ZM(Class.forName(a(13671, -7140)));
            if (!bool)
              Zt4g.Zz(Class.forName(a(13664, -20256))); 
          } catch (Throwable throwable) {
            throw a(null);
          } 
          return;
        } 
      } catch (Throwable throwable) {
        throw a(null);
      } 
      Zt4g.Zz(Class.forName(a(13664, -20256)));
    } catch (Throwable throwable) {}
  }
  
  static {
    // Byte code:
    //   0: bipush #11
    //   2: anewarray java/lang/String
    //   5: astore #5
    //   7: iconst_0
    //   8: istore_3
    //   9: ldc ')Xn^o\\ta@YS]jJa$#~ka;y0\\t.\\r&= V\\r^'\OE"'C\\tv\\tfO Ic?9(v/>'oo\\t7%$'
    //   11: dup
    //   12: astore_2
    //   13: invokevirtual length : ()I
    //   16: istore #4
    //   18: bipush #11
    //   20: istore_1
    //   21: iconst_m1
    //   22: istore_0
    //   23: iconst_4
    //   24: iinc #0, 1
    //   27: aload_2
    //   28: iload_0
    //   29: dup
    //   30: iload_1
    //   31: iadd
    //   32: invokevirtual substring : (II)Ljava/lang/String;
    //   35: iconst_m1
    //   36: goto -> 142
    //   39: aload #5
    //   41: swap
    //   42: iload_3
    //   43: iinc #3, 1
    //   46: swap
    //   47: aastore
    //   48: iload_0
    //   49: iload_1
    //   50: iadd
    //   51: dup
    //   52: istore_0
    //   53: iload #4
    //   55: if_icmpge -> 67
    //   58: aload_2
    //   59: iload_0
    //   60: invokevirtual charAt : (I)C
    //   63: istore_1
    //   64: goto -> 23
    //   67: ldc '56^eF1l"EJ@HRg<EWPN\\bu\\f'
    //   69: dup
    //   70: astore_2
    //   71: invokevirtual length : ()I
    //   74: istore #4
    //   76: bipush #77
    //   78: istore_1
    //   79: iconst_m1
    //   80: istore_0
    //   81: bipush #83
    //   83: iinc #0, 1
    //   86: aload_2
    //   87: iload_0
    //   88: dup
    //   89: iload_1
    //   90: iadd
    //   91: invokevirtual substring : (II)Ljava/lang/String;
    //   94: iconst_0
    //   95: goto -> 142
    //   98: aload #5
    //   100: swap
    //   101: iload_3
    //   102: iinc #3, 1
    //   105: swap
    //   106: aastore
    //   107: iload_0
    //   108: iload_1
    //   109: iadd
    //   110: dup
    //   111: istore_0
    //   112: iload #4
    //   114: if_icmpge -> 126
    //   117: aload_2
    //   118: iload_0
    //   119: invokevirtual charAt : (I)C
    //   122: istore_1
    //   123: goto -> 81
    //   126: aload #5
    //   128: putstatic burp/Zm52.a : [Ljava/lang/String;
    //   131: bipush #11
    //   133: anewarray java/lang/String
    //   136: putstatic burp/Zm52.b : [Ljava/lang/String;
    //   139: goto -> 300
    //   142: dup_x2
    //   143: pop
    //   144: invokevirtual toCharArray : ()[C
    //   147: dup_x1
    //   148: arraylength
    //   149: dup_x2
    //   150: pop
    //   151: iconst_0
    //   152: istore #6
    //   154: dup2_x1
    //   155: pop2
    //   156: dup_x2
    //   157: iconst_1
    //   158: if_icmpgt -> 260
    //   161: dup2
    //   162: swap
    //   163: iload #6
    //   165: dup2_x1
    //   166: caload
    //   167: swap
    //   168: iload #6
    //   170: bipush #7
    //   172: irem
    //   173: tableswitch default -> 242, 0 -> 212, 1 -> 217, 2 -> 222, 3 -> 227, 4 -> 232, 5 -> 237
    //   212: bipush #126
    //   214: goto -> 244
    //   217: bipush #112
    //   219: goto -> 244
    //   222: bipush #98
    //   224: goto -> 244
    //   227: bipush #122
    //   229: goto -> 244
    //   232: bipush #67
    //   234: goto -> 244
    //   237: bipush #124
    //   239: goto -> 244
    //   242: bipush #105
    //   244: ixor
    //   245: ixor
    //   246: i2c
    //   247: castore
    //   248: iinc #6, 1
    //   251: dup
    //   252: ifne -> 260
    //   255: dup2
    //   256: dup_x1
    //   257: goto -> 165
    //   260: dup2_x1
    //   261: pop2
    //   262: dup_x2
    //   263: iload #6
    //   265: if_icmpgt -> 161
    //   268: pop
    //   269: new java/lang/String
    //   272: dup_x1
    //   273: swap
    //   274: invokespecial <init> : ([C)V
    //   277: invokevirtual intern : ()Ljava/lang/String;
    //   280: swap
    //   281: pop
    //   282: swap
    //   283: tableswitch default -> 39, 0 -> 98
    //   300: sipush #13665
    //   303: sipush #-3955
    //   306: invokestatic a : (II)Ljava/lang/String;
    //   309: putstatic burp/Zm52.Ze : Ljava/lang/String;
    //   312: new java/math/BigInteger
    //   315: dup
    //   316: iconst_1
    //   317: bipush #32
    //   319: newarray byte
    //   321: dup
    //   322: iconst_0
    //   323: bipush #89
    //   325: bastore
    //   326: dup
    //   327: iconst_1
    //   328: bipush #-35
    //   330: bastore
    //   331: dup
    //   332: iconst_2
    //   333: bipush #-13
    //   335: bastore
    //   336: dup
    //   337: iconst_3
    //   338: bipush #105
    //   340: bastore
    //   341: dup
    //   342: iconst_4
    //   343: bipush #97
    //   345: bastore
    //   346: dup
    //   347: iconst_5
    //   348: bipush #-67
    //   350: bastore
    //   351: dup
    //   352: bipush #6
    //   354: bipush #-8
    //   356: bastore
    //   357: dup
    //   358: bipush #7
    //   360: bipush #17
    //   362: bastore
    //   363: dup
    //   364: bipush #8
    //   366: bipush #53
    //   368: bastore
    //   369: dup
    //   370: bipush #9
    //   372: bipush #-128
    //   374: bastore
    //   375: dup
    //   376: bipush #10
    //   378: bipush #-37
    //   380: bastore
    //   381: dup
    //   382: bipush #11
    //   384: bipush #-55
    //   386: bastore
    //   387: dup
    //   388: bipush #12
    //   390: bipush #-41
    //   392: bastore
    //   393: dup
    //   394: bipush #13
    //   396: bipush #50
    //   398: bastore
    //   399: dup
    //   400: bipush #14
    //   402: bipush #40
    //   404: bastore
    //   405: dup
    //   406: bipush #15
    //   408: bipush #-20
    //   410: bastore
    //   411: dup
    //   412: bipush #16
    //   414: bipush #80
    //   416: bastore
    //   417: dup
    //   418: bipush #17
    //   420: bipush #106
    //   422: bastore
    //   423: dup
    //   424: bipush #18
    //   426: bipush #60
    //   428: bastore
    //   429: dup
    //   430: bipush #19
    //   432: bipush #-18
    //   434: bastore
    //   435: dup
    //   436: bipush #20
    //   438: iconst_m1
    //   439: bastore
    //   440: dup
    //   441: bipush #21
    //   443: bipush #-20
    //   445: bastore
    //   446: dup
    //   447: bipush #22
    //   449: bipush #-104
    //   451: bastore
    //   452: dup
    //   453: bipush #23
    //   455: bipush #49
    //   457: bastore
    //   458: dup
    //   459: bipush #24
    //   461: bipush #-127
    //   463: bastore
    //   464: dup
    //   465: bipush #25
    //   467: bipush #-101
    //   469: bastore
    //   470: dup
    //   471: bipush #26
    //   473: bipush #-2
    //   475: bastore
    //   476: dup
    //   477: bipush #27
    //   479: bipush #102
    //   481: bastore
    //   482: dup
    //   483: bipush #28
    //   485: bipush #-27
    //   487: bastore
    //   488: dup
    //   489: bipush #29
    //   491: bipush #-81
    //   493: bastore
    //   494: dup
    //   495: bipush #30
    //   497: bipush #-67
    //   499: bastore
    //   500: dup
    //   501: bipush #31
    //   503: bipush #-73
    //   505: bastore
    //   506: invokespecial <init> : (I[B)V
    //   509: putstatic burp/Zm52.ZR : Ljava/lang/Object;
    //   512: return
  }
  
  private static Throwable a(Throwable paramThrowable) {
    return paramThrowable;
  }
  
  private static String a(int paramInt1, int paramInt2) {
    int i = (paramInt1 ^ 0x3566) & 0xFFFF;
    if (b[i] == null) {
      char[] arrayOfChar = a[i].toCharArray();
      switch (arrayOfChar[0] & 0xFF) {
        case 0:
        
        case 1:
        
        case 2:
        
        case 3:
        
        case 4:
        
        case 5:
        
        case 6:
        
        case 7:
        
        case 8:
        
        case 9:
        
        case 10:
        
        case 11:
        
        case 12:
        
        case 13:
        
        case 14:
        
        case 15:
        
        case 16:
        
        case 17:
        
        case 18:
        
        case 19:
        
        case 20:
        
        case 21:
        
        case 22:
        
        case 23:
        
        case 24:
        
        case 25:
        
        case 26:
        
        case 27:
        
        case 28:
        
        case 29:
        
        case 30:
        
        case 31:
        
        case 32:
        
        case 33:
        
        case 34:
        
        case 35:
        
        case 36:
        
        case 37:
        
        case 38:
        
        case 39:
        
        case 40:
        
        case 41:
        
        case 42:
        
        case 43:
        
        case 44:
        
        case 45:
        
        case 46:
        
        case 47:
        
        case 48:
        
        case 49:
        
        case 50:
        
        case 51:
        
        case 52:
        
        case 53:
        
        case 54:
        
        case 55:
        
        case 56:
        
        case 57:
        
        case 58:
        
        case 59:
        
        case 60:
        
        case 61:
        
        case 62:
        
        case 63:
        
        case 64:
        
        case 65:
        
        case 66:
        
        case 67:
        
        case 68:
        
        case 69:
        
        case 70:
        
        case 71:
        
        case 72:
        
        case 73:
        
        case 74:
        
        case 75:
        
        case 76:
        
        case 77:
        
        case 78:
        
        case 79:
        
        case 80:
        
        case 81:
        
        case 82:
        
        case 83:
        
        case 84:
        
        case 85:
        
        case 86:
        
        case 87:
        
        case 88:
        
        case 89:
        
        case 90:
        
        case 91:
        
        case 92:
        
        case 93:
        
        case 94:
        
        case 95:
        
        case 96:
        
        case 97:
        
        case 98:
        
        case 99:
        
        case 100:
        
        case 101:
        
        case 102:
        
        case 103:
        
        case 104:
        
        case 105:
        
        case 106:
        
        case 107:
        
        case 108:
        
        case 109:
        
        case 110:
        
        case 111:
        
        case 112:
        
        case 113:
        
        case 114:
        
        case 115:
        
        case 116:
        
        case 117:
        
        case 118:
        
        case 119:
        
        case 120:
        
        case 121:
        
        case 122:
        
        case 123:
        
        case 124:
        
        case 125:
        
        case 126:
        
        case 127:
        
        case 128:
        
        case 129:
        
        case 130:
        
        case 131:
        
        case 132:
        
        case 133:
        
        case 134:
        
        case 135:
        
        case 136:
        
        case 137:
        
        case 138:
        
        case 139:
        
        case 140:
        
        case 141:
        
        case 142:
        
        case 143:
        
        case 144:
        
        case 145:
        
        case 146:
        
        case 147:
        
        case 148:
        
        case 149:
        
        case 150:
        
        case 151:
        
        case 152:
        
        case 153:
        
        case 154:
        
        case 155:
        
        case 156:
        
        case 157:
        
        case 158:
        
        case 159:
        
        case 160:
        
        case 161:
        
        case 162:
        
        case 163:
        
        case 164:
        
        case 165:
        
        case 166:
        
        case 167:
        
        case 168:
        
        case 169:
        
        case 170:
        
        case 171:
        
        case 172:
        
        case 173:
        
        case 174:
        
        case 175:
        
        case 176:
        
        case 177:
        
        case 178:
        
        case 179:
        
        case 180:
        
        case 181:
        
        case 182:
        
        case 183:
        
        case 184:
        
        case 185:
        
        case 186:
        
        case 187:
        
        case 188:
        
        case 189:
        
        case 190:
        
        case 191:
        
        case 192:
        
        case 193:
        
        case 194:
        
        case 195:
        
        case 196:
        
        case 197:
        
        case 198:
        
        case 199:
        
        case 200:
        
        case 201:
        
        case 202:
        
        case 203:
        
        case 204:
        
        case 205:
        
        case 206:
        
        case 207:
        
        case 208:
        
        case 209:
        
        case 210:
        
        case 211:
        
        case 212:
        
        case 213:
        
        case 214:
        
        case 215:
        
        case 216:
        
        case 217:
        
        case 218:
        
        case 219:
        
        case 220:
        
        case 221:
        
        case 222:
        
        case 223:
        
        case 224:
        
        case 225:
        
        case 226:
        
        case 227:
        
        case 228:
        
        case 229:
        
        case 230:
        
        case 231:
        
        case 232:
        
        case 233:
        
        case 234:
        
        case 235:
        
        case 236:
        
        case 237:
        
        case 238:
        
        case 239:
        
        case 240:
        
        case 241:
        
        case 242:
        
        case 243:
        
        case 244:
        
        case 245:
        
        case 246:
        
        case 247:
        
        case 248:
        
        case 249:
        
        case 250:
        
        case 251:
        
        case 252:
        
        case 253:
        
        case 254:
        
        default:
          break;
      } 
      byte b1 = 31;
      int j = (paramInt2 & 0xFF) - b1;
      if (j < 0)
        j += 256; 
      int k = ((paramInt2 & 0xFFFF) >>> 8) - b1;
      if (k < 0)
        k += 256; 
      for (byte b2 = 0; b2 < arrayOfChar.length; b2++) {
        int m = b2 % 2;
        if (m == 0) {
          arrayOfChar[b2] = (char)(arrayOfChar[b2] ^ j);
          j = ((j >>> 3 | j << 5) ^ arrayOfChar[b2]) & 0xFF;
        } else {
          arrayOfChar[b2] = (char)(arrayOfChar[b2] ^ k);
          k = ((k >>> 3 | k << 5) ^ arrayOfChar[b2]) & 0xFF;
        } 
      } 
      b[i] = (new String(arrayOfChar)).intern();
    } 
    return b[i];
  }
}


/* Location:              C:\Program Files\BurpSuitePro\burpsuite_pro.jar!\burp\Zm52.class
 * Java compiler version: 21 (65.0)
 * JD-Core Version:       1.1.3
 */