package burp;

import java.math.BigInteger;

class Zm63 extends ClassLoader {
  static Object ZT;
  
  static String Zs;
  
  private static final String[] a;
  
  private static final String[] b;
  
  static boolean Zs(Object[] paramArrayOfObject, Object paramObject) throws Throwable {
    // Byte code:
    //   0: invokestatic ZK : ()Z
    //   3: istore_2
    //   4: getstatic burp/Zs_m.Z_ : Ljava/lang/Object;
    //   7: checkcast java/math/BigInteger
    //   10: invokevirtual toByteArray : ()[B
    //   13: astore_3
    //   14: bipush #32
    //   16: newarray int
    //   18: dup
    //   19: iconst_0
    //   20: ldc 943331329
    //   22: iastore
    //   23: dup
    //   24: iconst_1
    //   25: ldc 170788368
    //   27: iastore
    //   28: dup
    //   29: iconst_2
    //   30: ldc 1008414755
    //   32: iastore
    //   33: dup
    //   34: iconst_3
    //   35: ldc 187049985
    //   37: iastore
    //   38: dup
    //   39: iconst_4
    //   40: ldc 1010368540
    //   42: iastore
    //   43: dup
    //   44: iconst_5
    //   45: ldc 220604441
    //   47: iastore
    //   48: dup
    //   49: bipush #6
    //   51: ldc 940377620
    //   53: iastore
    //   54: dup
    //   55: bipush #7
    //   57: ldc 255209728
    //   59: iastore
    //   60: dup
    //   61: bipush #8
    //   63: ldc 689771012
    //   65: iastore
    //   66: dup
    //   67: bipush #9
    //   69: ldc 221709344
    //   71: iastore
    //   72: dup
    //   73: bipush #10
    //   75: ldc 957157408
    //   77: iastore
    //   78: dup
    //   79: bipush #11
    //   81: ldc 892536332
    //   83: iastore
    //   84: dup
    //   85: bipush #12
    //   87: ldc 722417666
    //   89: iastore
    //   90: dup
    //   91: bipush #13
    //   93: ldc 1026621720
    //   95: iastore
    //   96: dup
    //   97: bipush #14
    //   99: ldc 655302664
    //   101: iastore
    //   102: dup
    //   103: bipush #15
    //   105: ldc 890966315
    //   107: iastore
    //   108: dup
    //   109: bipush #16
    //   111: ldc 187632156
    //   113: iastore
    //   114: dup
    //   115: bipush #17
    //   117: ldc 874189824
    //   119: iastore
    //   120: dup
    //   121: bipush #18
    //   123: ldc 254150144
    //   125: iastore
    //   126: dup
    //   127: bipush #19
    //   129: ldc 924386310
    //   131: iastore
    //   132: dup
    //   133: bipush #20
    //   135: ldc 121057538
    //   137: iastore
    //   138: dup
    //   139: bipush #21
    //   141: ldc 840500228
    //   143: iastore
    //   144: dup
    //   145: bipush #22
    //   147: ldc 389160971
    //   149: iastore
    //   150: dup
    //   151: bipush #23
    //   153: ldc 907870729
    //   155: iastore
    //   156: dup
    //   157: bipush #24
    //   159: ldc 389426184
    //   161: iastore
    //   162: dup
    //   163: bipush #25
    //   165: ldc 973875457
    //   167: iastore
    //   168: dup
    //   169: bipush #26
    //   171: ldc 372376604
    //   173: iastore
    //   174: dup
    //   175: bipush #27
    //   177: ldc 707731490
    //   179: iastore
    //   180: dup
    //   181: bipush #28
    //   183: ldc 1043334948
    //   185: iastore
    //   186: dup
    //   187: bipush #29
    //   189: ldc 439222784
    //   191: iastore
    //   192: dup
    //   193: bipush #30
    //   195: ldc 876216579
    //   197: iastore
    //   198: dup
    //   199: bipush #31
    //   201: ldc 455999525
    //   203: iastore
    //   204: astore #5
    //   206: bipush #8
    //   208: aload_3
    //   209: arraylength
    //   210: bipush #8
    //   212: irem
    //   213: isub
    //   214: istore #6
    //   216: aload_3
    //   217: arraylength
    //   218: iload #6
    //   220: iadd
    //   221: newarray byte
    //   223: astore #7
    //   225: iconst_0
    //   226: istore #8
    //   228: iload #8
    //   230: aload_3
    //   231: arraylength
    //   232: if_icmpge -> 251
    //   235: aload #7
    //   237: iload #8
    //   239: aload_3
    //   240: iload #8
    //   242: baload
    //   243: bastore
    //   244: iinc #8, 1
    //   247: iload_2
    //   248: ifeq -> 228
    //   251: aload_3
    //   252: arraylength
    //   253: istore #8
    //   255: iload #8
    //   257: aload #7
    //   259: arraylength
    //   260: if_icmpge -> 278
    //   263: aload #7
    //   265: iload #8
    //   267: iload #6
    //   269: i2b
    //   270: bastore
    //   271: iinc #8, 1
    //   274: iload_2
    //   275: ifeq -> 255
    //   278: aload #7
    //   280: astore_3
    //   281: bipush #64
    //   283: newarray int
    //   285: dup
    //   286: iconst_0
    //   287: ldc 16843776
    //   289: iastore
    //   290: dup
    //   291: iconst_1
    //   292: iconst_0
    //   293: iastore
    //   294: dup
    //   295: iconst_2
    //   296: ldc 65536
    //   298: iastore
    //   299: dup
    //   300: iconst_3
    //   301: ldc 16843780
    //   303: iastore
    //   304: dup
    //   305: iconst_4
    //   306: ldc 16842756
    //   308: iastore
    //   309: dup
    //   310: iconst_5
    //   311: ldc 66564
    //   313: iastore
    //   314: dup
    //   315: bipush #6
    //   317: iconst_4
    //   318: iastore
    //   319: dup
    //   320: bipush #7
    //   322: ldc 65536
    //   324: iastore
    //   325: dup
    //   326: bipush #8
    //   328: sipush #1024
    //   331: iastore
    //   332: dup
    //   333: bipush #9
    //   335: ldc 16843776
    //   337: iastore
    //   338: dup
    //   339: bipush #10
    //   341: ldc 16843780
    //   343: iastore
    //   344: dup
    //   345: bipush #11
    //   347: sipush #1024
    //   350: iastore
    //   351: dup
    //   352: bipush #12
    //   354: ldc 16778244
    //   356: iastore
    //   357: dup
    //   358: bipush #13
    //   360: ldc 16842756
    //   362: iastore
    //   363: dup
    //   364: bipush #14
    //   366: ldc 16777216
    //   368: iastore
    //   369: dup
    //   370: bipush #15
    //   372: iconst_4
    //   373: iastore
    //   374: dup
    //   375: bipush #16
    //   377: sipush #1028
    //   380: iastore
    //   381: dup
    //   382: bipush #17
    //   384: ldc 16778240
    //   386: iastore
    //   387: dup
    //   388: bipush #18
    //   390: ldc 16778240
    //   392: iastore
    //   393: dup
    //   394: bipush #19
    //   396: ldc 66560
    //   398: iastore
    //   399: dup
    //   400: bipush #20
    //   402: ldc 66560
    //   404: iastore
    //   405: dup
    //   406: bipush #21
    //   408: ldc 16842752
    //   410: iastore
    //   411: dup
    //   412: bipush #22
    //   414: ldc 16842752
    //   416: iastore
    //   417: dup
    //   418: bipush #23
    //   420: ldc 16778244
    //   422: iastore
    //   423: dup
    //   424: bipush #24
    //   426: ldc 65540
    //   428: iastore
    //   429: dup
    //   430: bipush #25
    //   432: ldc 16777220
    //   434: iastore
    //   435: dup
    //   436: bipush #26
    //   438: ldc 16777220
    //   440: iastore
    //   441: dup
    //   442: bipush #27
    //   444: ldc 65540
    //   446: iastore
    //   447: dup
    //   448: bipush #28
    //   450: iconst_0
    //   451: iastore
    //   452: dup
    //   453: bipush #29
    //   455: sipush #1028
    //   458: iastore
    //   459: dup
    //   460: bipush #30
    //   462: ldc 66564
    //   464: iastore
    //   465: dup
    //   466: bipush #31
    //   468: ldc 16777216
    //   470: iastore
    //   471: dup
    //   472: bipush #32
    //   474: ldc 65536
    //   476: iastore
    //   477: dup
    //   478: bipush #33
    //   480: ldc 16843780
    //   482: iastore
    //   483: dup
    //   484: bipush #34
    //   486: iconst_4
    //   487: iastore
    //   488: dup
    //   489: bipush #35
    //   491: ldc 16842752
    //   493: iastore
    //   494: dup
    //   495: bipush #36
    //   497: ldc 16843776
    //   499: iastore
    //   500: dup
    //   501: bipush #37
    //   503: ldc 16777216
    //   505: iastore
    //   506: dup
    //   507: bipush #38
    //   509: ldc 16777216
    //   511: iastore
    //   512: dup
    //   513: bipush #39
    //   515: sipush #1024
    //   518: iastore
    //   519: dup
    //   520: bipush #40
    //   522: ldc 16842756
    //   524: iastore
    //   525: dup
    //   526: bipush #41
    //   528: ldc 65536
    //   530: iastore
    //   531: dup
    //   532: bipush #42
    //   534: ldc 66560
    //   536: iastore
    //   537: dup
    //   538: bipush #43
    //   540: ldc 16777220
    //   542: iastore
    //   543: dup
    //   544: bipush #44
    //   546: sipush #1024
    //   549: iastore
    //   550: dup
    //   551: bipush #45
    //   553: iconst_4
    //   554: iastore
    //   555: dup
    //   556: bipush #46
    //   558: ldc 16778244
    //   560: iastore
    //   561: dup
    //   562: bipush #47
    //   564: ldc 66564
    //   566: iastore
    //   567: dup
    //   568: bipush #48
    //   570: ldc 16843780
    //   572: iastore
    //   573: dup
    //   574: bipush #49
    //   576: ldc 65540
    //   578: iastore
    //   579: dup
    //   580: bipush #50
    //   582: ldc 16842752
    //   584: iastore
    //   585: dup
    //   586: bipush #51
    //   588: ldc 16778244
    //   590: iastore
    //   591: dup
    //   592: bipush #52
    //   594: ldc 16777220
    //   596: iastore
    //   597: dup
    //   598: bipush #53
    //   600: sipush #1028
    //   603: iastore
    //   604: dup
    //   605: bipush #54
    //   607: ldc 66564
    //   609: iastore
    //   610: dup
    //   611: bipush #55
    //   613: ldc 16843776
    //   615: iastore
    //   616: dup
    //   617: bipush #56
    //   619: sipush #1028
    //   622: iastore
    //   623: dup
    //   624: bipush #57
    //   626: ldc 16778240
    //   628: iastore
    //   629: dup
    //   630: bipush #58
    //   632: ldc 16778240
    //   634: iastore
    //   635: dup
    //   636: bipush #59
    //   638: iconst_0
    //   639: iastore
    //   640: dup
    //   641: bipush #60
    //   643: ldc 65540
    //   645: iastore
    //   646: dup
    //   647: bipush #61
    //   649: ldc 66560
    //   651: iastore
    //   652: dup
    //   653: bipush #62
    //   655: iconst_0
    //   656: iastore
    //   657: dup
    //   658: bipush #63
    //   660: ldc 16842756
    //   662: iastore
    //   663: astore #8
    //   665: bipush #64
    //   667: newarray int
    //   669: dup
    //   670: iconst_0
    //   671: ldc -2146402272
    //   673: iastore
    //   674: dup
    //   675: iconst_1
    //   676: ldc -2147450880
    //   678: iastore
    //   679: dup
    //   680: iconst_2
    //   681: ldc 32768
    //   683: iastore
    //   684: dup
    //   685: iconst_3
    //   686: ldc 1081376
    //   688: iastore
    //   689: dup
    //   690: iconst_4
    //   691: ldc 1048576
    //   693: iastore
    //   694: dup
    //   695: iconst_5
    //   696: bipush #32
    //   698: iastore
    //   699: dup
    //   700: bipush #6
    //   702: ldc -2146435040
    //   704: iastore
    //   705: dup
    //   706: bipush #7
    //   708: ldc -2147450848
    //   710: iastore
    //   711: dup
    //   712: bipush #8
    //   714: ldc -2147483616
    //   716: iastore
    //   717: dup
    //   718: bipush #9
    //   720: ldc -2146402272
    //   722: iastore
    //   723: dup
    //   724: bipush #10
    //   726: ldc -2146402304
    //   728: iastore
    //   729: dup
    //   730: bipush #11
    //   732: ldc -2147483648
    //   734: iastore
    //   735: dup
    //   736: bipush #12
    //   738: ldc -2147450880
    //   740: iastore
    //   741: dup
    //   742: bipush #13
    //   744: ldc 1048576
    //   746: iastore
    //   747: dup
    //   748: bipush #14
    //   750: bipush #32
    //   752: iastore
    //   753: dup
    //   754: bipush #15
    //   756: ldc -2146435040
    //   758: iastore
    //   759: dup
    //   760: bipush #16
    //   762: ldc 1081344
    //   764: iastore
    //   765: dup
    //   766: bipush #17
    //   768: ldc 1048608
    //   770: iastore
    //   771: dup
    //   772: bipush #18
    //   774: ldc -2147450848
    //   776: iastore
    //   777: dup
    //   778: bipush #19
    //   780: iconst_0
    //   781: iastore
    //   782: dup
    //   783: bipush #20
    //   785: ldc -2147483648
    //   787: iastore
    //   788: dup
    //   789: bipush #21
    //   791: ldc 32768
    //   793: iastore
    //   794: dup
    //   795: bipush #22
    //   797: ldc 1081376
    //   799: iastore
    //   800: dup
    //   801: bipush #23
    //   803: ldc -2146435072
    //   805: iastore
    //   806: dup
    //   807: bipush #24
    //   809: ldc 1048608
    //   811: iastore
    //   812: dup
    //   813: bipush #25
    //   815: ldc -2147483616
    //   817: iastore
    //   818: dup
    //   819: bipush #26
    //   821: iconst_0
    //   822: iastore
    //   823: dup
    //   824: bipush #27
    //   826: ldc 1081344
    //   828: iastore
    //   829: dup
    //   830: bipush #28
    //   832: ldc 32800
    //   834: iastore
    //   835: dup
    //   836: bipush #29
    //   838: ldc -2146402304
    //   840: iastore
    //   841: dup
    //   842: bipush #30
    //   844: ldc -2146435072
    //   846: iastore
    //   847: dup
    //   848: bipush #31
    //   850: ldc 32800
    //   852: iastore
    //   853: dup
    //   854: bipush #32
    //   856: iconst_0
    //   857: iastore
    //   858: dup
    //   859: bipush #33
    //   861: ldc 1081376
    //   863: iastore
    //   864: dup
    //   865: bipush #34
    //   867: ldc -2146435040
    //   869: iastore
    //   870: dup
    //   871: bipush #35
    //   873: ldc 1048576
    //   875: iastore
    //   876: dup
    //   877: bipush #36
    //   879: ldc -2147450848
    //   881: iastore
    //   882: dup
    //   883: bipush #37
    //   885: ldc -2146435072
    //   887: iastore
    //   888: dup
    //   889: bipush #38
    //   891: ldc -2146402304
    //   893: iastore
    //   894: dup
    //   895: bipush #39
    //   897: ldc 32768
    //   899: iastore
    //   900: dup
    //   901: bipush #40
    //   903: ldc -2146435072
    //   905: iastore
    //   906: dup
    //   907: bipush #41
    //   909: ldc -2147450880
    //   911: iastore
    //   912: dup
    //   913: bipush #42
    //   915: bipush #32
    //   917: iastore
    //   918: dup
    //   919: bipush #43
    //   921: ldc -2146402272
    //   923: iastore
    //   924: dup
    //   925: bipush #44
    //   927: ldc 1081376
    //   929: iastore
    //   930: dup
    //   931: bipush #45
    //   933: bipush #32
    //   935: iastore
    //   936: dup
    //   937: bipush #46
    //   939: ldc 32768
    //   941: iastore
    //   942: dup
    //   943: bipush #47
    //   945: ldc -2147483648
    //   947: iastore
    //   948: dup
    //   949: bipush #48
    //   951: ldc 32800
    //   953: iastore
    //   954: dup
    //   955: bipush #49
    //   957: ldc -2146402304
    //   959: iastore
    //   960: dup
    //   961: bipush #50
    //   963: ldc 1048576
    //   965: iastore
    //   966: dup
    //   967: bipush #51
    //   969: ldc -2147483616
    //   971: iastore
    //   972: dup
    //   973: bipush #52
    //   975: ldc 1048608
    //   977: iastore
    //   978: dup
    //   979: bipush #53
    //   981: ldc -2147450848
    //   983: iastore
    //   984: dup
    //   985: bipush #54
    //   987: ldc -2147483616
    //   989: iastore
    //   990: dup
    //   991: bipush #55
    //   993: ldc 1048608
    //   995: iastore
    //   996: dup
    //   997: bipush #56
    //   999: ldc 1081344
    //   1001: iastore
    //   1002: dup
    //   1003: bipush #57
    //   1005: iconst_0
    //   1006: iastore
    //   1007: dup
    //   1008: bipush #58
    //   1010: ldc -2147450880
    //   1012: iastore
    //   1013: dup
    //   1014: bipush #59
    //   1016: ldc 32800
    //   1018: iastore
    //   1019: dup
    //   1020: bipush #60
    //   1022: ldc -2147483648
    //   1024: iastore
    //   1025: dup
    //   1026: bipush #61
    //   1028: ldc -2146435040
    //   1030: iastore
    //   1031: dup
    //   1032: bipush #62
    //   1034: ldc -2146402272
    //   1036: iastore
    //   1037: dup
    //   1038: bipush #63
    //   1040: ldc 1081344
    //   1042: iastore
    //   1043: astore #9
    //   1045: bipush #64
    //   1047: newarray int
    //   1049: dup
    //   1050: iconst_0
    //   1051: sipush #520
    //   1054: iastore
    //   1055: dup
    //   1056: iconst_1
    //   1057: ldc 134349312
    //   1059: iastore
    //   1060: dup
    //   1061: iconst_2
    //   1062: iconst_0
    //   1063: iastore
    //   1064: dup
    //   1065: iconst_3
    //   1066: ldc 134348808
    //   1068: iastore
    //   1069: dup
    //   1070: iconst_4
    //   1071: ldc 134218240
    //   1073: iastore
    //   1074: dup
    //   1075: iconst_5
    //   1076: iconst_0
    //   1077: iastore
    //   1078: dup
    //   1079: bipush #6
    //   1081: ldc 131592
    //   1083: iastore
    //   1084: dup
    //   1085: bipush #7
    //   1087: ldc 134218240
    //   1089: iastore
    //   1090: dup
    //   1091: bipush #8
    //   1093: ldc 131080
    //   1095: iastore
    //   1096: dup
    //   1097: bipush #9
    //   1099: ldc 134217736
    //   1101: iastore
    //   1102: dup
    //   1103: bipush #10
    //   1105: ldc 134217736
    //   1107: iastore
    //   1108: dup
    //   1109: bipush #11
    //   1111: ldc 131072
    //   1113: iastore
    //   1114: dup
    //   1115: bipush #12
    //   1117: ldc 134349320
    //   1119: iastore
    //   1120: dup
    //   1121: bipush #13
    //   1123: ldc 131080
    //   1125: iastore
    //   1126: dup
    //   1127: bipush #14
    //   1129: ldc 134348800
    //   1131: iastore
    //   1132: dup
    //   1133: bipush #15
    //   1135: sipush #520
    //   1138: iastore
    //   1139: dup
    //   1140: bipush #16
    //   1142: ldc 134217728
    //   1144: iastore
    //   1145: dup
    //   1146: bipush #17
    //   1148: bipush #8
    //   1150: iastore
    //   1151: dup
    //   1152: bipush #18
    //   1154: ldc 134349312
    //   1156: iastore
    //   1157: dup
    //   1158: bipush #19
    //   1160: sipush #512
    //   1163: iastore
    //   1164: dup
    //   1165: bipush #20
    //   1167: ldc 131584
    //   1169: iastore
    //   1170: dup
    //   1171: bipush #21
    //   1173: ldc 134348800
    //   1175: iastore
    //   1176: dup
    //   1177: bipush #22
    //   1179: ldc 134348808
    //   1181: iastore
    //   1182: dup
    //   1183: bipush #23
    //   1185: ldc 131592
    //   1187: iastore
    //   1188: dup
    //   1189: bipush #24
    //   1191: ldc 134218248
    //   1193: iastore
    //   1194: dup
    //   1195: bipush #25
    //   1197: ldc 131584
    //   1199: iastore
    //   1200: dup
    //   1201: bipush #26
    //   1203: ldc 131072
    //   1205: iastore
    //   1206: dup
    //   1207: bipush #27
    //   1209: ldc 134218248
    //   1211: iastore
    //   1212: dup
    //   1213: bipush #28
    //   1215: bipush #8
    //   1217: iastore
    //   1218: dup
    //   1219: bipush #29
    //   1221: ldc 134349320
    //   1223: iastore
    //   1224: dup
    //   1225: bipush #30
    //   1227: sipush #512
    //   1230: iastore
    //   1231: dup
    //   1232: bipush #31
    //   1234: ldc 134217728
    //   1236: iastore
    //   1237: dup
    //   1238: bipush #32
    //   1240: ldc 134349312
    //   1242: iastore
    //   1243: dup
    //   1244: bipush #33
    //   1246: ldc 134217728
    //   1248: iastore
    //   1249: dup
    //   1250: bipush #34
    //   1252: ldc 131080
    //   1254: iastore
    //   1255: dup
    //   1256: bipush #35
    //   1258: sipush #520
    //   1261: iastore
    //   1262: dup
    //   1263: bipush #36
    //   1265: ldc 131072
    //   1267: iastore
    //   1268: dup
    //   1269: bipush #37
    //   1271: ldc 134349312
    //   1273: iastore
    //   1274: dup
    //   1275: bipush #38
    //   1277: ldc 134218240
    //   1279: iastore
    //   1280: dup
    //   1281: bipush #39
    //   1283: iconst_0
    //   1284: iastore
    //   1285: dup
    //   1286: bipush #40
    //   1288: sipush #512
    //   1291: iastore
    //   1292: dup
    //   1293: bipush #41
    //   1295: ldc 131080
    //   1297: iastore
    //   1298: dup
    //   1299: bipush #42
    //   1301: ldc 134349320
    //   1303: iastore
    //   1304: dup
    //   1305: bipush #43
    //   1307: ldc 134218240
    //   1309: iastore
    //   1310: dup
    //   1311: bipush #44
    //   1313: ldc 134217736
    //   1315: iastore
    //   1316: dup
    //   1317: bipush #45
    //   1319: sipush #512
    //   1322: iastore
    //   1323: dup
    //   1324: bipush #46
    //   1326: iconst_0
    //   1327: iastore
    //   1328: dup
    //   1329: bipush #47
    //   1331: ldc 134348808
    //   1333: iastore
    //   1334: dup
    //   1335: bipush #48
    //   1337: ldc 134218248
    //   1339: iastore
    //   1340: dup
    //   1341: bipush #49
    //   1343: ldc 131072
    //   1345: iastore
    //   1346: dup
    //   1347: bipush #50
    //   1349: ldc 134217728
    //   1351: iastore
    //   1352: dup
    //   1353: bipush #51
    //   1355: ldc 134349320
    //   1357: iastore
    //   1358: dup
    //   1359: bipush #52
    //   1361: bipush #8
    //   1363: iastore
    //   1364: dup
    //   1365: bipush #53
    //   1367: ldc 131592
    //   1369: iastore
    //   1370: dup
    //   1371: bipush #54
    //   1373: ldc 131584
    //   1375: iastore
    //   1376: dup
    //   1377: bipush #55
    //   1379: ldc 134217736
    //   1381: iastore
    //   1382: dup
    //   1383: bipush #56
    //   1385: ldc 134348800
    //   1387: iastore
    //   1388: dup
    //   1389: bipush #57
    //   1391: ldc 134218248
    //   1393: iastore
    //   1394: dup
    //   1395: bipush #58
    //   1397: sipush #520
    //   1400: iastore
    //   1401: dup
    //   1402: bipush #59
    //   1404: ldc 134348800
    //   1406: iastore
    //   1407: dup
    //   1408: bipush #60
    //   1410: ldc 131592
    //   1412: iastore
    //   1413: dup
    //   1414: bipush #61
    //   1416: bipush #8
    //   1418: iastore
    //   1419: dup
    //   1420: bipush #62
    //   1422: ldc 134348808
    //   1424: iastore
    //   1425: dup
    //   1426: bipush #63
    //   1428: ldc 131584
    //   1430: iastore
    //   1431: astore #10
    //   1433: bipush #64
    //   1435: newarray int
    //   1437: dup
    //   1438: iconst_0
    //   1439: ldc 8396801
    //   1441: iastore
    //   1442: dup
    //   1443: iconst_1
    //   1444: sipush #8321
    //   1447: iastore
    //   1448: dup
    //   1449: iconst_2
    //   1450: sipush #8321
    //   1453: iastore
    //   1454: dup
    //   1455: iconst_3
    //   1456: sipush #128
    //   1459: iastore
    //   1460: dup
    //   1461: iconst_4
    //   1462: ldc 8396928
    //   1464: iastore
    //   1465: dup
    //   1466: iconst_5
    //   1467: ldc 8388737
    //   1469: iastore
    //   1470: dup
    //   1471: bipush #6
    //   1473: ldc 8388609
    //   1475: iastore
    //   1476: dup
    //   1477: bipush #7
    //   1479: sipush #8193
    //   1482: iastore
    //   1483: dup
    //   1484: bipush #8
    //   1486: iconst_0
    //   1487: iastore
    //   1488: dup
    //   1489: bipush #9
    //   1491: ldc 8396800
    //   1493: iastore
    //   1494: dup
    //   1495: bipush #10
    //   1497: ldc 8396800
    //   1499: iastore
    //   1500: dup
    //   1501: bipush #11
    //   1503: ldc 8396929
    //   1505: iastore
    //   1506: dup
    //   1507: bipush #12
    //   1509: sipush #129
    //   1512: iastore
    //   1513: dup
    //   1514: bipush #13
    //   1516: iconst_0
    //   1517: iastore
    //   1518: dup
    //   1519: bipush #14
    //   1521: ldc 8388736
    //   1523: iastore
    //   1524: dup
    //   1525: bipush #15
    //   1527: ldc 8388609
    //   1529: iastore
    //   1530: dup
    //   1531: bipush #16
    //   1533: iconst_1
    //   1534: iastore
    //   1535: dup
    //   1536: bipush #17
    //   1538: sipush #8192
    //   1541: iastore
    //   1542: dup
    //   1543: bipush #18
    //   1545: ldc 8388608
    //   1547: iastore
    //   1548: dup
    //   1549: bipush #19
    //   1551: ldc 8396801
    //   1553: iastore
    //   1554: dup
    //   1555: bipush #20
    //   1557: sipush #128
    //   1560: iastore
    //   1561: dup
    //   1562: bipush #21
    //   1564: ldc 8388608
    //   1566: iastore
    //   1567: dup
    //   1568: bipush #22
    //   1570: sipush #8193
    //   1573: iastore
    //   1574: dup
    //   1575: bipush #23
    //   1577: sipush #8320
    //   1580: iastore
    //   1581: dup
    //   1582: bipush #24
    //   1584: ldc 8388737
    //   1586: iastore
    //   1587: dup
    //   1588: bipush #25
    //   1590: iconst_1
    //   1591: iastore
    //   1592: dup
    //   1593: bipush #26
    //   1595: sipush #8320
    //   1598: iastore
    //   1599: dup
    //   1600: bipush #27
    //   1602: ldc 8388736
    //   1604: iastore
    //   1605: dup
    //   1606: bipush #28
    //   1608: sipush #8192
    //   1611: iastore
    //   1612: dup
    //   1613: bipush #29
    //   1615: ldc 8396928
    //   1617: iastore
    //   1618: dup
    //   1619: bipush #30
    //   1621: ldc 8396929
    //   1623: iastore
    //   1624: dup
    //   1625: bipush #31
    //   1627: sipush #129
    //   1630: iastore
    //   1631: dup
    //   1632: bipush #32
    //   1634: ldc 8388736
    //   1636: iastore
    //   1637: dup
    //   1638: bipush #33
    //   1640: ldc 8388609
    //   1642: iastore
    //   1643: dup
    //   1644: bipush #34
    //   1646: ldc 8396800
    //   1648: iastore
    //   1649: dup
    //   1650: bipush #35
    //   1652: ldc 8396929
    //   1654: iastore
    //   1655: dup
    //   1656: bipush #36
    //   1658: sipush #129
    //   1661: iastore
    //   1662: dup
    //   1663: bipush #37
    //   1665: iconst_0
    //   1666: iastore
    //   1667: dup
    //   1668: bipush #38
    //   1670: iconst_0
    //   1671: iastore
    //   1672: dup
    //   1673: bipush #39
    //   1675: ldc 8396800
    //   1677: iastore
    //   1678: dup
    //   1679: bipush #40
    //   1681: sipush #8320
    //   1684: iastore
    //   1685: dup
    //   1686: bipush #41
    //   1688: ldc 8388736
    //   1690: iastore
    //   1691: dup
    //   1692: bipush #42
    //   1694: ldc 8388737
    //   1696: iastore
    //   1697: dup
    //   1698: bipush #43
    //   1700: iconst_1
    //   1701: iastore
    //   1702: dup
    //   1703: bipush #44
    //   1705: ldc 8396801
    //   1707: iastore
    //   1708: dup
    //   1709: bipush #45
    //   1711: sipush #8321
    //   1714: iastore
    //   1715: dup
    //   1716: bipush #46
    //   1718: sipush #8321
    //   1721: iastore
    //   1722: dup
    //   1723: bipush #47
    //   1725: sipush #128
    //   1728: iastore
    //   1729: dup
    //   1730: bipush #48
    //   1732: ldc 8396929
    //   1734: iastore
    //   1735: dup
    //   1736: bipush #49
    //   1738: sipush #129
    //   1741: iastore
    //   1742: dup
    //   1743: bipush #50
    //   1745: iconst_1
    //   1746: iastore
    //   1747: dup
    //   1748: bipush #51
    //   1750: sipush #8192
    //   1753: iastore
    //   1754: dup
    //   1755: bipush #52
    //   1757: ldc 8388609
    //   1759: iastore
    //   1760: dup
    //   1761: bipush #53
    //   1763: sipush #8193
    //   1766: iastore
    //   1767: dup
    //   1768: bipush #54
    //   1770: ldc 8396928
    //   1772: iastore
    //   1773: dup
    //   1774: bipush #55
    //   1776: ldc 8388737
    //   1778: iastore
    //   1779: dup
    //   1780: bipush #56
    //   1782: sipush #8193
    //   1785: iastore
    //   1786: dup
    //   1787: bipush #57
    //   1789: sipush #8320
    //   1792: iastore
    //   1793: dup
    //   1794: bipush #58
    //   1796: ldc 8388608
    //   1798: iastore
    //   1799: dup
    //   1800: bipush #59
    //   1802: ldc 8396801
    //   1804: iastore
    //   1805: dup
    //   1806: bipush #60
    //   1808: sipush #128
    //   1811: iastore
    //   1812: dup
    //   1813: bipush #61
    //   1815: ldc 8388608
    //   1817: iastore
    //   1818: dup
    //   1819: bipush #62
    //   1821: sipush #8192
    //   1824: iastore
    //   1825: dup
    //   1826: bipush #63
    //   1828: ldc 8396928
    //   1830: iastore
    //   1831: astore #11
    //   1833: bipush #64
    //   1835: newarray int
    //   1837: dup
    //   1838: iconst_0
    //   1839: sipush #256
    //   1842: iastore
    //   1843: dup
    //   1844: iconst_1
    //   1845: ldc 34078976
    //   1847: iastore
    //   1848: dup
    //   1849: iconst_2
    //   1850: ldc 34078720
    //   1852: iastore
    //   1853: dup
    //   1854: iconst_3
    //   1855: ldc 1107296512
    //   1857: iastore
    //   1858: dup
    //   1859: iconst_4
    //   1860: ldc 524288
    //   1862: iastore
    //   1863: dup
    //   1864: iconst_5
    //   1865: sipush #256
    //   1868: iastore
    //   1869: dup
    //   1870: bipush #6
    //   1872: ldc 1073741824
    //   1874: iastore
    //   1875: dup
    //   1876: bipush #7
    //   1878: ldc 34078720
    //   1880: iastore
    //   1881: dup
    //   1882: bipush #8
    //   1884: ldc 1074266368
    //   1886: iastore
    //   1887: dup
    //   1888: bipush #9
    //   1890: ldc 524288
    //   1892: iastore
    //   1893: dup
    //   1894: bipush #10
    //   1896: ldc 33554688
    //   1898: iastore
    //   1899: dup
    //   1900: bipush #11
    //   1902: ldc 1074266368
    //   1904: iastore
    //   1905: dup
    //   1906: bipush #12
    //   1908: ldc 1107296512
    //   1910: iastore
    //   1911: dup
    //   1912: bipush #13
    //   1914: ldc 1107820544
    //   1916: iastore
    //   1917: dup
    //   1918: bipush #14
    //   1920: ldc 524544
    //   1922: iastore
    //   1923: dup
    //   1924: bipush #15
    //   1926: ldc 1073741824
    //   1928: iastore
    //   1929: dup
    //   1930: bipush #16
    //   1932: ldc 33554432
    //   1934: iastore
    //   1935: dup
    //   1936: bipush #17
    //   1938: ldc 1074266112
    //   1940: iastore
    //   1941: dup
    //   1942: bipush #18
    //   1944: ldc 1074266112
    //   1946: iastore
    //   1947: dup
    //   1948: bipush #19
    //   1950: iconst_0
    //   1951: iastore
    //   1952: dup
    //   1953: bipush #20
    //   1955: ldc 1073742080
    //   1957: iastore
    //   1958: dup
    //   1959: bipush #21
    //   1961: ldc 1107820800
    //   1963: iastore
    //   1964: dup
    //   1965: bipush #22
    //   1967: ldc 1107820800
    //   1969: iastore
    //   1970: dup
    //   1971: bipush #23
    //   1973: ldc 33554688
    //   1975: iastore
    //   1976: dup
    //   1977: bipush #24
    //   1979: ldc 1107820544
    //   1981: iastore
    //   1982: dup
    //   1983: bipush #25
    //   1985: ldc 1073742080
    //   1987: iastore
    //   1988: dup
    //   1989: bipush #26
    //   1991: iconst_0
    //   1992: iastore
    //   1993: dup
    //   1994: bipush #27
    //   1996: ldc 1107296256
    //   1998: iastore
    //   1999: dup
    //   2000: bipush #28
    //   2002: ldc 34078976
    //   2004: iastore
    //   2005: dup
    //   2006: bipush #29
    //   2008: ldc 33554432
    //   2010: iastore
    //   2011: dup
    //   2012: bipush #30
    //   2014: ldc 1107296256
    //   2016: iastore
    //   2017: dup
    //   2018: bipush #31
    //   2020: ldc 524544
    //   2022: iastore
    //   2023: dup
    //   2024: bipush #32
    //   2026: ldc 524288
    //   2028: iastore
    //   2029: dup
    //   2030: bipush #33
    //   2032: ldc 1107296512
    //   2034: iastore
    //   2035: dup
    //   2036: bipush #34
    //   2038: sipush #256
    //   2041: iastore
    //   2042: dup
    //   2043: bipush #35
    //   2045: ldc 33554432
    //   2047: iastore
    //   2048: dup
    //   2049: bipush #36
    //   2051: ldc 1073741824
    //   2053: iastore
    //   2054: dup
    //   2055: bipush #37
    //   2057: ldc 34078720
    //   2059: iastore
    //   2060: dup
    //   2061: bipush #38
    //   2063: ldc 1107296512
    //   2065: iastore
    //   2066: dup
    //   2067: bipush #39
    //   2069: ldc 1074266368
    //   2071: iastore
    //   2072: dup
    //   2073: bipush #40
    //   2075: ldc 33554688
    //   2077: iastore
    //   2078: dup
    //   2079: bipush #41
    //   2081: ldc 1073741824
    //   2083: iastore
    //   2084: dup
    //   2085: bipush #42
    //   2087: ldc 1107820544
    //   2089: iastore
    //   2090: dup
    //   2091: bipush #43
    //   2093: ldc 34078976
    //   2095: iastore
    //   2096: dup
    //   2097: bipush #44
    //   2099: ldc 1074266368
    //   2101: iastore
    //   2102: dup
    //   2103: bipush #45
    //   2105: sipush #256
    //   2108: iastore
    //   2109: dup
    //   2110: bipush #46
    //   2112: ldc 33554432
    //   2114: iastore
    //   2115: dup
    //   2116: bipush #47
    //   2118: ldc 1107820544
    //   2120: iastore
    //   2121: dup
    //   2122: bipush #48
    //   2124: ldc 1107820800
    //   2126: iastore
    //   2127: dup
    //   2128: bipush #49
    //   2130: ldc 524544
    //   2132: iastore
    //   2133: dup
    //   2134: bipush #50
    //   2136: ldc 1107296256
    //   2138: iastore
    //   2139: dup
    //   2140: bipush #51
    //   2142: ldc 1107820800
    //   2144: iastore
    //   2145: dup
    //   2146: bipush #52
    //   2148: ldc 34078720
    //   2150: iastore
    //   2151: dup
    //   2152: bipush #53
    //   2154: iconst_0
    //   2155: iastore
    //   2156: dup
    //   2157: bipush #54
    //   2159: ldc 1074266112
    //   2161: iastore
    //   2162: dup
    //   2163: bipush #55
    //   2165: ldc 1107296256
    //   2167: iastore
    //   2168: dup
    //   2169: bipush #56
    //   2171: ldc 524544
    //   2173: iastore
    //   2174: dup
    //   2175: bipush #57
    //   2177: ldc 33554688
    //   2179: iastore
    //   2180: dup
    //   2181: bipush #58
    //   2183: ldc 1073742080
    //   2185: iastore
    //   2186: dup
    //   2187: bipush #59
    //   2189: ldc 524288
    //   2191: iastore
    //   2192: dup
    //   2193: bipush #60
    //   2195: iconst_0
    //   2196: iastore
    //   2197: dup
    //   2198: bipush #61
    //   2200: ldc 1074266112
    //   2202: iastore
    //   2203: dup
    //   2204: bipush #62
    //   2206: ldc 34078976
    //   2208: iastore
    //   2209: dup
    //   2210: bipush #63
    //   2212: ldc 1073742080
    //   2214: iastore
    //   2215: astore #12
    //   2217: bipush #64
    //   2219: newarray int
    //   2221: dup
    //   2222: iconst_0
    //   2223: ldc 536870928
    //   2225: iastore
    //   2226: dup
    //   2227: iconst_1
    //   2228: ldc 541065216
    //   2230: iastore
    //   2231: dup
    //   2232: iconst_2
    //   2233: sipush #16384
    //   2236: iastore
    //   2237: dup
    //   2238: iconst_3
    //   2239: ldc 541081616
    //   2241: iastore
    //   2242: dup
    //   2243: iconst_4
    //   2244: ldc 541065216
    //   2246: iastore
    //   2247: dup
    //   2248: iconst_5
    //   2249: bipush #16
    //   2251: iastore
    //   2252: dup
    //   2253: bipush #6
    //   2255: ldc 541081616
    //   2257: iastore
    //   2258: dup
    //   2259: bipush #7
    //   2261: ldc 4194304
    //   2263: iastore
    //   2264: dup
    //   2265: bipush #8
    //   2267: ldc 536887296
    //   2269: iastore
    //   2270: dup
    //   2271: bipush #9
    //   2273: ldc 4210704
    //   2275: iastore
    //   2276: dup
    //   2277: bipush #10
    //   2279: ldc 4194304
    //   2281: iastore
    //   2282: dup
    //   2283: bipush #11
    //   2285: ldc 536870928
    //   2287: iastore
    //   2288: dup
    //   2289: bipush #12
    //   2291: ldc 4194320
    //   2293: iastore
    //   2294: dup
    //   2295: bipush #13
    //   2297: ldc 536887296
    //   2299: iastore
    //   2300: dup
    //   2301: bipush #14
    //   2303: ldc 536870912
    //   2305: iastore
    //   2306: dup
    //   2307: bipush #15
    //   2309: sipush #16400
    //   2312: iastore
    //   2313: dup
    //   2314: bipush #16
    //   2316: iconst_0
    //   2317: iastore
    //   2318: dup
    //   2319: bipush #17
    //   2321: ldc 4194320
    //   2323: iastore
    //   2324: dup
    //   2325: bipush #18
    //   2327: ldc 536887312
    //   2329: iastore
    //   2330: dup
    //   2331: bipush #19
    //   2333: sipush #16384
    //   2336: iastore
    //   2337: dup
    //   2338: bipush #20
    //   2340: ldc 4210688
    //   2342: iastore
    //   2343: dup
    //   2344: bipush #21
    //   2346: ldc 536887312
    //   2348: iastore
    //   2349: dup
    //   2350: bipush #22
    //   2352: bipush #16
    //   2354: iastore
    //   2355: dup
    //   2356: bipush #23
    //   2358: ldc 541065232
    //   2360: iastore
    //   2361: dup
    //   2362: bipush #24
    //   2364: ldc 541065232
    //   2366: iastore
    //   2367: dup
    //   2368: bipush #25
    //   2370: iconst_0
    //   2371: iastore
    //   2372: dup
    //   2373: bipush #26
    //   2375: ldc 4210704
    //   2377: iastore
    //   2378: dup
    //   2379: bipush #27
    //   2381: ldc 541081600
    //   2383: iastore
    //   2384: dup
    //   2385: bipush #28
    //   2387: sipush #16400
    //   2390: iastore
    //   2391: dup
    //   2392: bipush #29
    //   2394: ldc 4210688
    //   2396: iastore
    //   2397: dup
    //   2398: bipush #30
    //   2400: ldc 541081600
    //   2402: iastore
    //   2403: dup
    //   2404: bipush #31
    //   2406: ldc 536870912
    //   2408: iastore
    //   2409: dup
    //   2410: bipush #32
    //   2412: ldc 536887296
    //   2414: iastore
    //   2415: dup
    //   2416: bipush #33
    //   2418: bipush #16
    //   2420: iastore
    //   2421: dup
    //   2422: bipush #34
    //   2424: ldc 541065232
    //   2426: iastore
    //   2427: dup
    //   2428: bipush #35
    //   2430: ldc 4210688
    //   2432: iastore
    //   2433: dup
    //   2434: bipush #36
    //   2436: ldc 541081616
    //   2438: iastore
    //   2439: dup
    //   2440: bipush #37
    //   2442: ldc 4194304
    //   2444: iastore
    //   2445: dup
    //   2446: bipush #38
    //   2448: sipush #16400
    //   2451: iastore
    //   2452: dup
    //   2453: bipush #39
    //   2455: ldc 536870928
    //   2457: iastore
    //   2458: dup
    //   2459: bipush #40
    //   2461: ldc 4194304
    //   2463: iastore
    //   2464: dup
    //   2465: bipush #41
    //   2467: ldc 536887296
    //   2469: iastore
    //   2470: dup
    //   2471: bipush #42
    //   2473: ldc 536870912
    //   2475: iastore
    //   2476: dup
    //   2477: bipush #43
    //   2479: sipush #16400
    //   2482: iastore
    //   2483: dup
    //   2484: bipush #44
    //   2486: ldc 536870928
    //   2488: iastore
    //   2489: dup
    //   2490: bipush #45
    //   2492: ldc 541081616
    //   2494: iastore
    //   2495: dup
    //   2496: bipush #46
    //   2498: ldc 4210688
    //   2500: iastore
    //   2501: dup
    //   2502: bipush #47
    //   2504: ldc 541065216
    //   2506: iastore
    //   2507: dup
    //   2508: bipush #48
    //   2510: ldc 4210704
    //   2512: iastore
    //   2513: dup
    //   2514: bipush #49
    //   2516: ldc 541081600
    //   2518: iastore
    //   2519: dup
    //   2520: bipush #50
    //   2522: iconst_0
    //   2523: iastore
    //   2524: dup
    //   2525: bipush #51
    //   2527: ldc 541065232
    //   2529: iastore
    //   2530: dup
    //   2531: bipush #52
    //   2533: bipush #16
    //   2535: iastore
    //   2536: dup
    //   2537: bipush #53
    //   2539: sipush #16384
    //   2542: iastore
    //   2543: dup
    //   2544: bipush #54
    //   2546: ldc 541065216
    //   2548: iastore
    //   2549: dup
    //   2550: bipush #55
    //   2552: ldc 4210704
    //   2554: iastore
    //   2555: dup
    //   2556: bipush #56
    //   2558: sipush #16384
    //   2561: iastore
    //   2562: dup
    //   2563: bipush #57
    //   2565: ldc 4194320
    //   2567: iastore
    //   2568: dup
    //   2569: bipush #58
    //   2571: ldc 536887312
    //   2573: iastore
    //   2574: dup
    //   2575: bipush #59
    //   2577: iconst_0
    //   2578: iastore
    //   2579: dup
    //   2580: bipush #60
    //   2582: ldc 541081600
    //   2584: iastore
    //   2585: dup
    //   2586: bipush #61
    //   2588: ldc 536870912
    //   2590: iastore
    //   2591: dup
    //   2592: bipush #62
    //   2594: ldc 4194320
    //   2596: iastore
    //   2597: dup
    //   2598: bipush #63
    //   2600: ldc 536887312
    //   2602: iastore
    //   2603: astore #13
    //   2605: bipush #64
    //   2607: newarray int
    //   2609: dup
    //   2610: iconst_0
    //   2611: ldc 2097152
    //   2613: iastore
    //   2614: dup
    //   2615: iconst_1
    //   2616: ldc 69206018
    //   2618: iastore
    //   2619: dup
    //   2620: iconst_2
    //   2621: ldc 67110914
    //   2623: iastore
    //   2624: dup
    //   2625: iconst_3
    //   2626: iconst_0
    //   2627: iastore
    //   2628: dup
    //   2629: iconst_4
    //   2630: sipush #2048
    //   2633: iastore
    //   2634: dup
    //   2635: iconst_5
    //   2636: ldc 67110914
    //   2638: iastore
    //   2639: dup
    //   2640: bipush #6
    //   2642: ldc 2099202
    //   2644: iastore
    //   2645: dup
    //   2646: bipush #7
    //   2648: ldc 69208064
    //   2650: iastore
    //   2651: dup
    //   2652: bipush #8
    //   2654: ldc 69208066
    //   2656: iastore
    //   2657: dup
    //   2658: bipush #9
    //   2660: ldc 2097152
    //   2662: iastore
    //   2663: dup
    //   2664: bipush #10
    //   2666: iconst_0
    //   2667: iastore
    //   2668: dup
    //   2669: bipush #11
    //   2671: ldc 67108866
    //   2673: iastore
    //   2674: dup
    //   2675: bipush #12
    //   2677: iconst_2
    //   2678: iastore
    //   2679: dup
    //   2680: bipush #13
    //   2682: ldc 67108864
    //   2684: iastore
    //   2685: dup
    //   2686: bipush #14
    //   2688: ldc 69206018
    //   2690: iastore
    //   2691: dup
    //   2692: bipush #15
    //   2694: sipush #2050
    //   2697: iastore
    //   2698: dup
    //   2699: bipush #16
    //   2701: ldc 67110912
    //   2703: iastore
    //   2704: dup
    //   2705: bipush #17
    //   2707: ldc 2099202
    //   2709: iastore
    //   2710: dup
    //   2711: bipush #18
    //   2713: ldc 2097154
    //   2715: iastore
    //   2716: dup
    //   2717: bipush #19
    //   2719: ldc 67110912
    //   2721: iastore
    //   2722: dup
    //   2723: bipush #20
    //   2725: ldc 67108866
    //   2727: iastore
    //   2728: dup
    //   2729: bipush #21
    //   2731: ldc 69206016
    //   2733: iastore
    //   2734: dup
    //   2735: bipush #22
    //   2737: ldc 69208064
    //   2739: iastore
    //   2740: dup
    //   2741: bipush #23
    //   2743: ldc 2097154
    //   2745: iastore
    //   2746: dup
    //   2747: bipush #24
    //   2749: ldc 69206016
    //   2751: iastore
    //   2752: dup
    //   2753: bipush #25
    //   2755: sipush #2048
    //   2758: iastore
    //   2759: dup
    //   2760: bipush #26
    //   2762: sipush #2050
    //   2765: iastore
    //   2766: dup
    //   2767: bipush #27
    //   2769: ldc 69208066
    //   2771: iastore
    //   2772: dup
    //   2773: bipush #28
    //   2775: ldc 2099200
    //   2777: iastore
    //   2778: dup
    //   2779: bipush #29
    //   2781: iconst_2
    //   2782: iastore
    //   2783: dup
    //   2784: bipush #30
    //   2786: ldc 67108864
    //   2788: iastore
    //   2789: dup
    //   2790: bipush #31
    //   2792: ldc 2099200
    //   2794: iastore
    //   2795: dup
    //   2796: bipush #32
    //   2798: ldc 67108864
    //   2800: iastore
    //   2801: dup
    //   2802: bipush #33
    //   2804: ldc 2099200
    //   2806: iastore
    //   2807: dup
    //   2808: bipush #34
    //   2810: ldc 2097152
    //   2812: iastore
    //   2813: dup
    //   2814: bipush #35
    //   2816: ldc 67110914
    //   2818: iastore
    //   2819: dup
    //   2820: bipush #36
    //   2822: ldc 67110914
    //   2824: iastore
    //   2825: dup
    //   2826: bipush #37
    //   2828: ldc 69206018
    //   2830: iastore
    //   2831: dup
    //   2832: bipush #38
    //   2834: ldc 69206018
    //   2836: iastore
    //   2837: dup
    //   2838: bipush #39
    //   2840: iconst_2
    //   2841: iastore
    //   2842: dup
    //   2843: bipush #40
    //   2845: ldc 2097154
    //   2847: iastore
    //   2848: dup
    //   2849: bipush #41
    //   2851: ldc 67108864
    //   2853: iastore
    //   2854: dup
    //   2855: bipush #42
    //   2857: ldc 67110912
    //   2859: iastore
    //   2860: dup
    //   2861: bipush #43
    //   2863: ldc 2097152
    //   2865: iastore
    //   2866: dup
    //   2867: bipush #44
    //   2869: ldc 69208064
    //   2871: iastore
    //   2872: dup
    //   2873: bipush #45
    //   2875: sipush #2050
    //   2878: iastore
    //   2879: dup
    //   2880: bipush #46
    //   2882: ldc 2099202
    //   2884: iastore
    //   2885: dup
    //   2886: bipush #47
    //   2888: ldc 69208064
    //   2890: iastore
    //   2891: dup
    //   2892: bipush #48
    //   2894: sipush #2050
    //   2897: iastore
    //   2898: dup
    //   2899: bipush #49
    //   2901: ldc 67108866
    //   2903: iastore
    //   2904: dup
    //   2905: bipush #50
    //   2907: ldc 69208066
    //   2909: iastore
    //   2910: dup
    //   2911: bipush #51
    //   2913: ldc 69206016
    //   2915: iastore
    //   2916: dup
    //   2917: bipush #52
    //   2919: ldc 2099200
    //   2921: iastore
    //   2922: dup
    //   2923: bipush #53
    //   2925: iconst_0
    //   2926: iastore
    //   2927: dup
    //   2928: bipush #54
    //   2930: iconst_2
    //   2931: iastore
    //   2932: dup
    //   2933: bipush #55
    //   2935: ldc 69208066
    //   2937: iastore
    //   2938: dup
    //   2939: bipush #56
    //   2941: iconst_0
    //   2942: iastore
    //   2943: dup
    //   2944: bipush #57
    //   2946: ldc 2099202
    //   2948: iastore
    //   2949: dup
    //   2950: bipush #58
    //   2952: ldc 69206016
    //   2954: iastore
    //   2955: dup
    //   2956: bipush #59
    //   2958: sipush #2048
    //   2961: iastore
    //   2962: dup
    //   2963: bipush #60
    //   2965: ldc 67108866
    //   2967: iastore
    //   2968: dup
    //   2969: bipush #61
    //   2971: ldc 67110912
    //   2973: iastore
    //   2974: dup
    //   2975: bipush #62
    //   2977: sipush #2048
    //   2980: iastore
    //   2981: dup
    //   2982: bipush #63
    //   2984: ldc 2097154
    //   2986: iastore
    //   2987: astore #14
    //   2989: bipush #64
    //   2991: newarray int
    //   2993: dup
    //   2994: iconst_0
    //   2995: ldc 268439616
    //   2997: iastore
    //   2998: dup
    //   2999: iconst_1
    //   3000: sipush #4096
    //   3003: iastore
    //   3004: dup
    //   3005: iconst_2
    //   3006: ldc 262144
    //   3008: iastore
    //   3009: dup
    //   3010: iconst_3
    //   3011: ldc 268701760
    //   3013: iastore
    //   3014: dup
    //   3015: iconst_4
    //   3016: ldc 268435456
    //   3018: iastore
    //   3019: dup
    //   3020: iconst_5
    //   3021: ldc 268439616
    //   3023: iastore
    //   3024: dup
    //   3025: bipush #6
    //   3027: bipush #64
    //   3029: iastore
    //   3030: dup
    //   3031: bipush #7
    //   3033: ldc 268435456
    //   3035: iastore
    //   3036: dup
    //   3037: bipush #8
    //   3039: ldc 262208
    //   3041: iastore
    //   3042: dup
    //   3043: bipush #9
    //   3045: ldc 268697600
    //   3047: iastore
    //   3048: dup
    //   3049: bipush #10
    //   3051: ldc 268701760
    //   3053: iastore
    //   3054: dup
    //   3055: bipush #11
    //   3057: ldc 266240
    //   3059: iastore
    //   3060: dup
    //   3061: bipush #12
    //   3063: ldc 268701696
    //   3065: iastore
    //   3066: dup
    //   3067: bipush #13
    //   3069: ldc 266304
    //   3071: iastore
    //   3072: dup
    //   3073: bipush #14
    //   3075: sipush #4096
    //   3078: iastore
    //   3079: dup
    //   3080: bipush #15
    //   3082: bipush #64
    //   3084: iastore
    //   3085: dup
    //   3086: bipush #16
    //   3088: ldc 268697600
    //   3090: iastore
    //   3091: dup
    //   3092: bipush #17
    //   3094: ldc 268435520
    //   3096: iastore
    //   3097: dup
    //   3098: bipush #18
    //   3100: ldc 268439552
    //   3102: iastore
    //   3103: dup
    //   3104: bipush #19
    //   3106: sipush #4160
    //   3109: iastore
    //   3110: dup
    //   3111: bipush #20
    //   3113: ldc 266240
    //   3115: iastore
    //   3116: dup
    //   3117: bipush #21
    //   3119: ldc 262208
    //   3121: iastore
    //   3122: dup
    //   3123: bipush #22
    //   3125: ldc 268697664
    //   3127: iastore
    //   3128: dup
    //   3129: bipush #23
    //   3131: ldc 268701696
    //   3133: iastore
    //   3134: dup
    //   3135: bipush #24
    //   3137: sipush #4160
    //   3140: iastore
    //   3141: dup
    //   3142: bipush #25
    //   3144: iconst_0
    //   3145: iastore
    //   3146: dup
    //   3147: bipush #26
    //   3149: iconst_0
    //   3150: iastore
    //   3151: dup
    //   3152: bipush #27
    //   3154: ldc 268697664
    //   3156: iastore
    //   3157: dup
    //   3158: bipush #28
    //   3160: ldc 268435520
    //   3162: iastore
    //   3163: dup
    //   3164: bipush #29
    //   3166: ldc 268439552
    //   3168: iastore
    //   3169: dup
    //   3170: bipush #30
    //   3172: ldc 266304
    //   3174: iastore
    //   3175: dup
    //   3176: bipush #31
    //   3178: ldc 262144
    //   3180: iastore
    //   3181: dup
    //   3182: bipush #32
    //   3184: ldc 266304
    //   3186: iastore
    //   3187: dup
    //   3188: bipush #33
    //   3190: ldc 262144
    //   3192: iastore
    //   3193: dup
    //   3194: bipush #34
    //   3196: ldc 268701696
    //   3198: iastore
    //   3199: dup
    //   3200: bipush #35
    //   3202: sipush #4096
    //   3205: iastore
    //   3206: dup
    //   3207: bipush #36
    //   3209: bipush #64
    //   3211: iastore
    //   3212: dup
    //   3213: bipush #37
    //   3215: ldc 268697664
    //   3217: iastore
    //   3218: dup
    //   3219: bipush #38
    //   3221: sipush #4096
    //   3224: iastore
    //   3225: dup
    //   3226: bipush #39
    //   3228: ldc 266304
    //   3230: iastore
    //   3231: dup
    //   3232: bipush #40
    //   3234: ldc 268439552
    //   3236: iastore
    //   3237: dup
    //   3238: bipush #41
    //   3240: bipush #64
    //   3242: iastore
    //   3243: dup
    //   3244: bipush #42
    //   3246: ldc 268435520
    //   3248: iastore
    //   3249: dup
    //   3250: bipush #43
    //   3252: ldc 268697600
    //   3254: iastore
    //   3255: dup
    //   3256: bipush #44
    //   3258: ldc 268697664
    //   3260: iastore
    //   3261: dup
    //   3262: bipush #45
    //   3264: ldc 268435456
    //   3266: iastore
    //   3267: dup
    //   3268: bipush #46
    //   3270: ldc 262144
    //   3272: iastore
    //   3273: dup
    //   3274: bipush #47
    //   3276: ldc 268439616
    //   3278: iastore
    //   3279: dup
    //   3280: bipush #48
    //   3282: iconst_0
    //   3283: iastore
    //   3284: dup
    //   3285: bipush #49
    //   3287: ldc 268701760
    //   3289: iastore
    //   3290: dup
    //   3291: bipush #50
    //   3293: ldc 262208
    //   3295: iastore
    //   3296: dup
    //   3297: bipush #51
    //   3299: ldc 268435520
    //   3301: iastore
    //   3302: dup
    //   3303: bipush #52
    //   3305: ldc 268697600
    //   3307: iastore
    //   3308: dup
    //   3309: bipush #53
    //   3311: ldc 268439552
    //   3313: iastore
    //   3314: dup
    //   3315: bipush #54
    //   3317: ldc 268439616
    //   3319: iastore
    //   3320: dup
    //   3321: bipush #55
    //   3323: iconst_0
    //   3324: iastore
    //   3325: dup
    //   3326: bipush #56
    //   3328: ldc 268701760
    //   3330: iastore
    //   3331: dup
    //   3332: bipush #57
    //   3334: ldc 266240
    //   3336: iastore
    //   3337: dup
    //   3338: bipush #58
    //   3340: ldc 266240
    //   3342: iastore
    //   3343: dup
    //   3344: bipush #59
    //   3346: sipush #4160
    //   3349: iastore
    //   3350: dup
    //   3351: bipush #60
    //   3353: sipush #4160
    //   3356: iastore
    //   3357: dup
    //   3358: bipush #61
    //   3360: ldc 262208
    //   3362: iastore
    //   3363: dup
    //   3364: bipush #62
    //   3366: ldc 268435456
    //   3368: iastore
    //   3369: dup
    //   3370: bipush #63
    //   3372: ldc 268701696
    //   3374: iastore
    //   3375: astore #15
    //   3377: aload_3
    //   3378: arraylength
    //   3379: istore #16
    //   3381: iconst_2
    //   3382: newarray int
    //   3384: astore #17
    //   3386: iload #16
    //   3388: newarray byte
    //   3390: astore #4
    //   3392: iload #16
    //   3394: bipush #8
    //   3396: idiv
    //   3397: istore #18
    //   3399: iconst_0
    //   3400: istore #19
    //   3402: iload #19
    //   3404: iload #18
    //   3406: if_icmpge -> 4320
    //   3409: iload #19
    //   3411: bipush #8
    //   3413: imul
    //   3414: istore #20
    //   3416: iconst_0
    //   3417: istore #21
    //   3419: iload #21
    //   3421: iconst_2
    //   3422: if_icmpge -> 3507
    //   3425: aload #17
    //   3427: iload #21
    //   3429: aload_3
    //   3430: iload #20
    //   3432: iload #21
    //   3434: iconst_4
    //   3435: imul
    //   3436: iadd
    //   3437: baload
    //   3438: sipush #255
    //   3441: iand
    //   3442: bipush #24
    //   3444: ishl
    //   3445: aload_3
    //   3446: iload #20
    //   3448: iload #21
    //   3450: iconst_4
    //   3451: imul
    //   3452: iadd
    //   3453: iconst_1
    //   3454: iadd
    //   3455: baload
    //   3456: sipush #255
    //   3459: iand
    //   3460: bipush #16
    //   3462: ishl
    //   3463: ior
    //   3464: aload_3
    //   3465: iload #20
    //   3467: iload #21
    //   3469: iconst_4
    //   3470: imul
    //   3471: iadd
    //   3472: iconst_2
    //   3473: iadd
    //   3474: baload
    //   3475: sipush #255
    //   3478: iand
    //   3479: bipush #8
    //   3481: ishl
    //   3482: ior
    //   3483: aload_3
    //   3484: iload #20
    //   3486: iload #21
    //   3488: iconst_4
    //   3489: imul
    //   3490: iadd
    //   3491: iconst_3
    //   3492: iadd
    //   3493: baload
    //   3494: sipush #255
    //   3497: iand
    //   3498: ior
    //   3499: iastore
    //   3500: iinc #21, 1
    //   3503: iload_2
    //   3504: ifeq -> 3419
    //   3507: iconst_0
    //   3508: istore #26
    //   3510: aload #17
    //   3512: iconst_0
    //   3513: iaload
    //   3514: istore #24
    //   3516: aload #17
    //   3518: iconst_1
    //   3519: iaload
    //   3520: istore #23
    //   3522: iload #24
    //   3524: iconst_4
    //   3525: iushr
    //   3526: iload #23
    //   3528: ixor
    //   3529: ldc 252645135
    //   3531: iand
    //   3532: istore #22
    //   3534: iload #23
    //   3536: iload #22
    //   3538: ixor
    //   3539: istore #23
    //   3541: iload #24
    //   3543: iload #22
    //   3545: iconst_4
    //   3546: ishl
    //   3547: ixor
    //   3548: istore #24
    //   3550: iload #24
    //   3552: bipush #16
    //   3554: iushr
    //   3555: iload #23
    //   3557: ixor
    //   3558: ldc 65535
    //   3560: iand
    //   3561: istore #22
    //   3563: iload #23
    //   3565: iload #22
    //   3567: ixor
    //   3568: istore #23
    //   3570: iload #24
    //   3572: iload #22
    //   3574: bipush #16
    //   3576: ishl
    //   3577: ixor
    //   3578: istore #24
    //   3580: iload #23
    //   3582: iconst_2
    //   3583: iushr
    //   3584: iload #24
    //   3586: ixor
    //   3587: ldc 858993459
    //   3589: iand
    //   3590: istore #22
    //   3592: iload #24
    //   3594: iload #22
    //   3596: ixor
    //   3597: istore #24
    //   3599: iload #23
    //   3601: iload #22
    //   3603: iconst_2
    //   3604: ishl
    //   3605: ixor
    //   3606: istore #23
    //   3608: iload #23
    //   3610: bipush #8
    //   3612: iushr
    //   3613: iload #24
    //   3615: ixor
    //   3616: ldc 16711935
    //   3618: iand
    //   3619: istore #22
    //   3621: iload #24
    //   3623: iload #22
    //   3625: ixor
    //   3626: istore #24
    //   3628: iload #23
    //   3630: iload #22
    //   3632: bipush #8
    //   3634: ishl
    //   3635: ixor
    //   3636: istore #23
    //   3638: iload #23
    //   3640: iconst_1
    //   3641: ishl
    //   3642: iload #23
    //   3644: bipush #31
    //   3646: iushr
    //   3647: iconst_1
    //   3648: iand
    //   3649: ior
    //   3650: istore #23
    //   3652: iload #24
    //   3654: iload #23
    //   3656: ixor
    //   3657: ldc -1431655766
    //   3659: iand
    //   3660: istore #22
    //   3662: iload #24
    //   3664: iload #22
    //   3666: ixor
    //   3667: istore #24
    //   3669: iload #23
    //   3671: iload #22
    //   3673: ixor
    //   3674: istore #23
    //   3676: iload #24
    //   3678: iconst_1
    //   3679: ishl
    //   3680: iload #24
    //   3682: bipush #31
    //   3684: iushr
    //   3685: iconst_1
    //   3686: iand
    //   3687: ior
    //   3688: istore #24
    //   3690: iconst_0
    //   3691: istore #25
    //   3693: iload #25
    //   3695: bipush #8
    //   3697: if_icmpge -> 4035
    //   3700: iload #23
    //   3702: bipush #28
    //   3704: ishl
    //   3705: iload #23
    //   3707: iconst_4
    //   3708: iushr
    //   3709: ior
    //   3710: istore #22
    //   3712: iload #22
    //   3714: aload #5
    //   3716: iload #26
    //   3718: iinc #26, 1
    //   3721: iaload
    //   3722: ixor
    //   3723: istore #22
    //   3725: aload #14
    //   3727: iload #22
    //   3729: bipush #63
    //   3731: iand
    //   3732: iaload
    //   3733: istore #21
    //   3735: iload #21
    //   3737: aload #12
    //   3739: iload #22
    //   3741: bipush #8
    //   3743: iushr
    //   3744: bipush #63
    //   3746: iand
    //   3747: iaload
    //   3748: ior
    //   3749: istore #21
    //   3751: iload #21
    //   3753: aload #10
    //   3755: iload #22
    //   3757: bipush #16
    //   3759: iushr
    //   3760: bipush #63
    //   3762: iand
    //   3763: iaload
    //   3764: ior
    //   3765: istore #21
    //   3767: iload #21
    //   3769: aload #8
    //   3771: iload #22
    //   3773: bipush #24
    //   3775: iushr
    //   3776: bipush #63
    //   3778: iand
    //   3779: iaload
    //   3780: ior
    //   3781: istore #21
    //   3783: iload #23
    //   3785: aload #5
    //   3787: iload #26
    //   3789: iinc #26, 1
    //   3792: iaload
    //   3793: ixor
    //   3794: istore #22
    //   3796: iload #21
    //   3798: aload #15
    //   3800: iload #22
    //   3802: bipush #63
    //   3804: iand
    //   3805: iaload
    //   3806: ior
    //   3807: istore #21
    //   3809: iload #21
    //   3811: aload #13
    //   3813: iload #22
    //   3815: bipush #8
    //   3817: iushr
    //   3818: bipush #63
    //   3820: iand
    //   3821: iaload
    //   3822: ior
    //   3823: istore #21
    //   3825: iload #21
    //   3827: aload #11
    //   3829: iload #22
    //   3831: bipush #16
    //   3833: iushr
    //   3834: bipush #63
    //   3836: iand
    //   3837: iaload
    //   3838: ior
    //   3839: istore #21
    //   3841: iload #21
    //   3843: aload #9
    //   3845: iload #22
    //   3847: bipush #24
    //   3849: iushr
    //   3850: bipush #63
    //   3852: iand
    //   3853: iaload
    //   3854: ior
    //   3855: istore #21
    //   3857: iload #24
    //   3859: iload #21
    //   3861: ixor
    //   3862: istore #24
    //   3864: iload #24
    //   3866: bipush #28
    //   3868: ishl
    //   3869: iload #24
    //   3871: iconst_4
    //   3872: iushr
    //   3873: ior
    //   3874: istore #22
    //   3876: iload #22
    //   3878: aload #5
    //   3880: iload #26
    //   3882: iinc #26, 1
    //   3885: iaload
    //   3886: ixor
    //   3887: istore #22
    //   3889: aload #14
    //   3891: iload #22
    //   3893: bipush #63
    //   3895: iand
    //   3896: iaload
    //   3897: istore #21
    //   3899: iload #21
    //   3901: aload #12
    //   3903: iload #22
    //   3905: bipush #8
    //   3907: iushr
    //   3908: bipush #63
    //   3910: iand
    //   3911: iaload
    //   3912: ior
    //   3913: istore #21
    //   3915: iload #21
    //   3917: aload #10
    //   3919: iload #22
    //   3921: bipush #16
    //   3923: iushr
    //   3924: bipush #63
    //   3926: iand
    //   3927: iaload
    //   3928: ior
    //   3929: istore #21
    //   3931: iload #21
    //   3933: aload #8
    //   3935: iload #22
    //   3937: bipush #24
    //   3939: iushr
    //   3940: bipush #63
    //   3942: iand
    //   3943: iaload
    //   3944: ior
    //   3945: istore #21
    //   3947: iload #24
    //   3949: aload #5
    //   3951: iload #26
    //   3953: iinc #26, 1
    //   3956: iaload
    //   3957: ixor
    //   3958: istore #22
    //   3960: iload #21
    //   3962: aload #15
    //   3964: iload #22
    //   3966: bipush #63
    //   3968: iand
    //   3969: iaload
    //   3970: ior
    //   3971: istore #21
    //   3973: iload #21
    //   3975: aload #13
    //   3977: iload #22
    //   3979: bipush #8
    //   3981: iushr
    //   3982: bipush #63
    //   3984: iand
    //   3985: iaload
    //   3986: ior
    //   3987: istore #21
    //   3989: iload #21
    //   3991: aload #11
    //   3993: iload #22
    //   3995: bipush #16
    //   3997: iushr
    //   3998: bipush #63
    //   4000: iand
    //   4001: iaload
    //   4002: ior
    //   4003: istore #21
    //   4005: iload #21
    //   4007: aload #9
    //   4009: iload #22
    //   4011: bipush #24
    //   4013: iushr
    //   4014: bipush #63
    //   4016: iand
    //   4017: iaload
    //   4018: ior
    //   4019: istore #21
    //   4021: iload #23
    //   4023: iload #21
    //   4025: ixor
    //   4026: istore #23
    //   4028: iinc #25, 1
    //   4031: iload_2
    //   4032: ifeq -> 3693
    //   4035: iload #23
    //   4037: bipush #31
    //   4039: ishl
    //   4040: iload #23
    //   4042: iconst_1
    //   4043: iushr
    //   4044: ior
    //   4045: istore #23
    //   4047: iload #24
    //   4049: iload #23
    //   4051: ixor
    //   4052: ldc -1431655766
    //   4054: iand
    //   4055: istore #22
    //   4057: iload #24
    //   4059: iload #22
    //   4061: ixor
    //   4062: istore #24
    //   4064: iload #23
    //   4066: iload #22
    //   4068: ixor
    //   4069: istore #23
    //   4071: iload #24
    //   4073: bipush #31
    //   4075: ishl
    //   4076: iload #24
    //   4078: iconst_1
    //   4079: iushr
    //   4080: ior
    //   4081: istore #24
    //   4083: iload #24
    //   4085: bipush #8
    //   4087: iushr
    //   4088: iload #23
    //   4090: ixor
    //   4091: ldc 16711935
    //   4093: iand
    //   4094: istore #22
    //   4096: iload #23
    //   4098: iload #22
    //   4100: ixor
    //   4101: istore #23
    //   4103: iload #24
    //   4105: iload #22
    //   4107: bipush #8
    //   4109: ishl
    //   4110: ixor
    //   4111: istore #24
    //   4113: iload #24
    //   4115: iconst_2
    //   4116: iushr
    //   4117: iload #23
    //   4119: ixor
    //   4120: ldc 858993459
    //   4122: iand
    //   4123: istore #22
    //   4125: iload #23
    //   4127: iload #22
    //   4129: ixor
    //   4130: istore #23
    //   4132: iload #24
    //   4134: iload #22
    //   4136: iconst_2
    //   4137: ishl
    //   4138: ixor
    //   4139: istore #24
    //   4141: iload #23
    //   4143: bipush #16
    //   4145: iushr
    //   4146: iload #24
    //   4148: ixor
    //   4149: ldc 65535
    //   4151: iand
    //   4152: istore #22
    //   4154: iload #24
    //   4156: iload #22
    //   4158: ixor
    //   4159: istore #24
    //   4161: iload #23
    //   4163: iload #22
    //   4165: bipush #16
    //   4167: ishl
    //   4168: ixor
    //   4169: istore #23
    //   4171: iload #23
    //   4173: iconst_4
    //   4174: iushr
    //   4175: iload #24
    //   4177: ixor
    //   4178: ldc 252645135
    //   4180: iand
    //   4181: istore #22
    //   4183: iload #24
    //   4185: iload #22
    //   4187: ixor
    //   4188: istore #24
    //   4190: iload #23
    //   4192: iload #22
    //   4194: iconst_4
    //   4195: ishl
    //   4196: ixor
    //   4197: istore #23
    //   4199: aload #17
    //   4201: iconst_0
    //   4202: iload #23
    //   4204: iastore
    //   4205: aload #17
    //   4207: iconst_1
    //   4208: iload #24
    //   4210: iastore
    //   4211: iload #19
    //   4213: bipush #8
    //   4215: imul
    //   4216: istore #27
    //   4218: iconst_0
    //   4219: istore #28
    //   4221: iload #28
    //   4223: iconst_2
    //   4224: if_icmpge -> 4313
    //   4227: aload #4
    //   4229: iload #27
    //   4231: iload #28
    //   4233: iconst_4
    //   4234: imul
    //   4235: iadd
    //   4236: aload #17
    //   4238: iload #28
    //   4240: iaload
    //   4241: bipush #24
    //   4243: iushr
    //   4244: i2b
    //   4245: bastore
    //   4246: aload #4
    //   4248: iload #27
    //   4250: iload #28
    //   4252: iconst_4
    //   4253: imul
    //   4254: iadd
    //   4255: iconst_1
    //   4256: iadd
    //   4257: aload #17
    //   4259: iload #28
    //   4261: iaload
    //   4262: bipush #16
    //   4264: iushr
    //   4265: i2b
    //   4266: bastore
    //   4267: aload #4
    //   4269: iload #27
    //   4271: iload #28
    //   4273: iconst_4
    //   4274: imul
    //   4275: iadd
    //   4276: iconst_2
    //   4277: iadd
    //   4278: aload #17
    //   4280: iload #28
    //   4282: iaload
    //   4283: bipush #8
    //   4285: iushr
    //   4286: i2b
    //   4287: bastore
    //   4288: aload #4
    //   4290: iload #27
    //   4292: iload #28
    //   4294: iconst_4
    //   4295: imul
    //   4296: iadd
    //   4297: iconst_3
    //   4298: iadd
    //   4299: aload #17
    //   4301: iload #28
    //   4303: iaload
    //   4304: i2b
    //   4305: bastore
    //   4306: iinc #28, 1
    //   4309: iload_2
    //   4310: ifeq -> 4221
    //   4313: iinc #19, 1
    //   4316: iload_2
    //   4317: ifeq -> 3402
    //   4320: new java/math/BigInteger
    //   4323: dup
    //   4324: aload #4
    //   4326: invokespecial <init> : ([B)V
    //   4329: invokevirtual abs : ()Ljava/math/BigInteger;
    //   4332: putstatic burp/Zxan.ZX : Ljava/lang/Object;
    //   4335: sipush #-11454
    //   4338: getstatic burp/Zgrz.ZX : Ljava/lang/Object;
    //   4341: checkcast java/math/BigInteger
    //   4344: getstatic burp/Zgio.ZP : Ljava/lang/Object;
    //   4347: checkcast java/math/BigInteger
    //   4350: invokevirtual add : (Ljava/math/BigInteger;)Ljava/math/BigInteger;
    //   4353: putstatic burp/Ze6w.Ze : Ljava/lang/Object;
    //   4356: sipush #-28224
    //   4359: getstatic burp/Zrww.ZN : Ljava/lang/Object;
    //   4362: checkcast java/math/BigInteger
    //   4365: getstatic burp/Ze8j.ZQ : Ljava/lang/Object;
    //   4368: checkcast java/math/BigInteger
    //   4371: invokevirtual subtract : (Ljava/math/BigInteger;)Ljava/math/BigInteger;
    //   4374: putstatic burp/Zxcn.Zq : Ljava/lang/Object;
    //   4377: invokestatic a : (II)Ljava/lang/String;
    //   4380: iconst_1
    //   4381: ldc burp/Zeno
    //   4383: invokevirtual getClassLoader : ()Ljava/lang/ClassLoader;
    //   4386: invokestatic forName : (Ljava/lang/String;ZLjava/lang/ClassLoader;)Ljava/lang/Class;
    //   4389: invokevirtual getDeclaredFields : ()[Ljava/lang/reflect/Field;
    //   4392: astore_3
    //   4393: aload_3
    //   4394: arraylength
    //   4395: istore #4
    //   4397: iconst_0
    //   4398: istore #5
    //   4400: iload #5
    //   4402: iload #4
    //   4404: if_icmpge -> 4541
    //   4407: aload_3
    //   4408: iload #5
    //   4410: aaload
    //   4411: astore #6
    //   4413: aload #6
    //   4415: invokevirtual getModifiers : ()I
    //   4418: invokestatic isStatic : (I)Z
    //   4421: ifne -> 4431
    //   4424: goto -> 4534
    //   4427: invokestatic a : (Ljava/lang/Throwable;)Ljava/lang/Throwable;
    //   4430: athrow
    //   4431: aload #6
    //   4433: invokevirtual getType : ()Ljava/lang/Class;
    //   4436: astore #7
    //   4438: aload #7
    //   4440: ifnull -> 4521
    //   4443: aload #7
    //   4445: invokevirtual isPrimitive : ()Z
    //   4448: ifne -> 4521
    //   4451: goto -> 4458
    //   4454: invokestatic a : (Ljava/lang/Throwable;)Ljava/lang/Throwable;
    //   4457: athrow
    //   4458: aload #7
    //   4460: invokevirtual getPackage : ()Ljava/lang/Package;
    //   4463: ifnull -> 4521
    //   4466: goto -> 4473
    //   4469: invokestatic a : (Ljava/lang/Throwable;)Ljava/lang/Throwable;
    //   4472: athrow
    //   4473: aload #7
    //   4475: invokevirtual getPackage : ()Ljava/lang/Package;
    //   4478: invokevirtual getName : ()Ljava/lang/String;
    //   4481: ifnull -> 4521
    //   4484: goto -> 4491
    //   4487: invokestatic a : (Ljava/lang/Throwable;)Ljava/lang/Throwable;
    //   4490: athrow
    //   4491: aload #7
    //   4493: invokevirtual getPackage : ()Ljava/lang/Package;
    //   4496: invokevirtual getName : ()Ljava/lang/String;
    //   4499: sipush #-11452
    //   4502: sipush #714
    //   4505: invokestatic a : (II)Ljava/lang/String;
    //   4508: invokevirtual startsWith : (Ljava/lang/String;)Z
    //   4511: ifne -> 4521
    //   4514: goto -> 4521
    //   4517: invokestatic a : (Ljava/lang/Throwable;)Ljava/lang/Throwable;
    //   4520: athrow
    //   4521: aload #6
    //   4523: iconst_1
    //   4524: invokevirtual setAccessible : (Z)V
    //   4527: aload #6
    //   4529: aconst_null
    //   4530: invokevirtual get : (Ljava/lang/Object;)Ljava/lang/Object;
    //   4533: pop
    //   4534: iinc #5, 1
    //   4537: iload_2
    //   4538: ifeq -> 4400
    //   4541: sipush #-11448
    //   4544: sipush #-17823
    //   4547: invokestatic a : (II)Ljava/lang/String;
    //   4550: invokestatic forName : (Ljava/lang/String;)Ljava/lang/Class;
    //   4553: invokevirtual getDeclaredMethods : ()[Ljava/lang/reflect/Method;
    //   4556: astore_3
    //   4557: aload_3
    //   4558: arraylength
    //   4559: istore #4
    //   4561: iconst_0
    //   4562: istore #5
    //   4564: iload #5
    //   4566: iload #4
    //   4568: if_icmpge -> 4700
    //   4571: aload_3
    //   4572: iload #5
    //   4574: aaload
    //   4575: astore #6
    //   4577: aload #6
    //   4579: invokevirtual getParameterTypes : ()[Ljava/lang/Class;
    //   4582: pop
    //   4583: aload #6
    //   4585: invokevirtual getModifiers : ()I
    //   4588: invokestatic isStatic : (I)Z
    //   4591: ifeq -> 4686
    //   4594: aload #6
    //   4596: invokevirtual getParameterTypes : ()[Ljava/lang/Class;
    //   4599: arraylength
    //   4600: iconst_2
    //   4601: if_icmpne -> 4686
    //   4604: goto -> 4611
    //   4607: invokestatic a : (Ljava/lang/Throwable;)Ljava/lang/Throwable;
    //   4610: athrow
    //   4611: aload #6
    //   4613: invokevirtual getReturnType : ()Ljava/lang/Class;
    //   4616: getstatic java/lang/Void.TYPE : Ljava/lang/Class;
    //   4619: invokevirtual equals : (Ljava/lang/Object;)Z
    //   4622: ifeq -> 4686
    //   4625: goto -> 4632
    //   4628: invokestatic a : (Ljava/lang/Throwable;)Ljava/lang/Throwable;
    //   4631: athrow
    //   4632: aload #6
    //   4634: iconst_1
    //   4635: invokevirtual setAccessible : (Z)V
    //   4638: aload #6
    //   4640: aconst_null
    //   4641: iconst_2
    //   4642: anewarray java/lang/Object
    //   4645: dup
    //   4646: iconst_0
    //   4647: aload_0
    //   4648: aastore
    //   4649: dup
    //   4650: iconst_1
    //   4651: aload_1
    //   4652: ifnonnull -> 4670
    //   4655: goto -> 4662
    //   4658: invokestatic a : (Ljava/lang/Throwable;)Ljava/lang/Throwable;
    //   4661: athrow
    //   4662: aload_1
    //   4663: goto -> 4677
    //   4666: invokestatic a : (Ljava/lang/Throwable;)Ljava/lang/Throwable;
    //   4669: athrow
    //   4670: aload_1
    //   4671: checkcast [B
    //   4674: invokevirtual clone : ()Ljava/lang/Object;
    //   4677: aastore
    //   4678: invokevirtual invoke : (Ljava/lang/Object;[Ljava/lang/Object;)Ljava/lang/Object;
    //   4681: pop
    //   4682: iload_2
    //   4683: ifeq -> 4700
    //   4686: iinc #5, 1
    //   4689: iload_2
    //   4690: ifeq -> 4564
    //   4693: goto -> 4700
    //   4696: invokestatic a : (Ljava/lang/Throwable;)Ljava/lang/Throwable;
    //   4699: athrow
    //   4700: getstatic burp/Zr36.Za : Ljava/lang/Object;
    //   4703: checkcast java/math/BigInteger
    //   4706: invokevirtual toByteArray : ()[B
    //   4709: astore_3
    //   4710: bipush #32
    //   4712: newarray int
    //   4714: dup
    //   4715: iconst_0
    //   4716: ldc 876216579
    //   4718: iastore
    //   4719: dup
    //   4720: iconst_1
    //   4721: ldc 455999525
    //   4723: iastore
    //   4724: dup
    //   4725: iconst_2
    //   4726: ldc 1043334948
    //   4728: iastore
    //   4729: dup
    //   4730: iconst_3
    //   4731: ldc 439222784
    //   4733: iastore
    //   4734: dup
    //   4735: iconst_4
    //   4736: ldc 372376604
    //   4738: iastore
    //   4739: dup
    //   4740: iconst_5
    //   4741: ldc 707731490
    //   4743: iastore
    //   4744: dup
    //   4745: bipush #6
    //   4747: ldc 389426184
    //   4749: iastore
    //   4750: dup
    //   4751: bipush #7
    //   4753: ldc 973875457
    //   4755: iastore
    //   4756: dup
    //   4757: bipush #8
    //   4759: ldc 389160971
    //   4761: iastore
    //   4762: dup
    //   4763: bipush #9
    //   4765: ldc 907870729
    //   4767: iastore
    //   4768: dup
    //   4769: bipush #10
    //   4771: ldc 121057538
    //   4773: iastore
    //   4774: dup
    //   4775: bipush #11
    //   4777: ldc 840500228
    //   4779: iastore
    //   4780: dup
    //   4781: bipush #12
    //   4783: ldc 254150144
    //   4785: iastore
    //   4786: dup
    //   4787: bipush #13
    //   4789: ldc 924386310
    //   4791: iastore
    //   4792: dup
    //   4793: bipush #14
    //   4795: ldc 187632156
    //   4797: iastore
    //   4798: dup
    //   4799: bipush #15
    //   4801: ldc 874189824
    //   4803: iastore
    //   4804: dup
    //   4805: bipush #16
    //   4807: ldc 655302664
    //   4809: iastore
    //   4810: dup
    //   4811: bipush #17
    //   4813: ldc 890966315
    //   4815: iastore
    //   4816: dup
    //   4817: bipush #18
    //   4819: ldc 722417666
    //   4821: iastore
    //   4822: dup
    //   4823: bipush #19
    //   4825: ldc 1026621720
    //   4827: iastore
    //   4828: dup
    //   4829: bipush #20
    //   4831: ldc 957157408
    //   4833: iastore
    //   4834: dup
    //   4835: bipush #21
    //   4837: ldc 892536332
    //   4839: iastore
    //   4840: dup
    //   4841: bipush #22
    //   4843: ldc 689771012
    //   4845: iastore
    //   4846: dup
    //   4847: bipush #23
    //   4849: ldc 221709344
    //   4851: iastore
    //   4852: dup
    //   4853: bipush #24
    //   4855: ldc 940377620
    //   4857: iastore
    //   4858: dup
    //   4859: bipush #25
    //   4861: ldc 255209728
    //   4863: iastore
    //   4864: dup
    //   4865: bipush #26
    //   4867: ldc 1010368540
    //   4869: iastore
    //   4870: dup
    //   4871: bipush #27
    //   4873: ldc 220604441
    //   4875: iastore
    //   4876: dup
    //   4877: bipush #28
    //   4879: ldc 1008414755
    //   4881: iastore
    //   4882: dup
    //   4883: bipush #29
    //   4885: ldc 187049985
    //   4887: iastore
    //   4888: dup
    //   4889: bipush #30
    //   4891: ldc 943331329
    //   4893: iastore
    //   4894: dup
    //   4895: bipush #31
    //   4897: ldc 170788368
    //   4899: iastore
    //   4900: astore #5
    //   4902: bipush #64
    //   4904: newarray int
    //   4906: dup
    //   4907: iconst_0
    //   4908: ldc 16843776
    //   4910: iastore
    //   4911: dup
    //   4912: iconst_1
    //   4913: iconst_0
    //   4914: iastore
    //   4915: dup
    //   4916: iconst_2
    //   4917: ldc 65536
    //   4919: iastore
    //   4920: dup
    //   4921: iconst_3
    //   4922: ldc 16843780
    //   4924: iastore
    //   4925: dup
    //   4926: iconst_4
    //   4927: ldc 16842756
    //   4929: iastore
    //   4930: dup
    //   4931: iconst_5
    //   4932: ldc 66564
    //   4934: iastore
    //   4935: dup
    //   4936: bipush #6
    //   4938: iconst_4
    //   4939: iastore
    //   4940: dup
    //   4941: bipush #7
    //   4943: ldc 65536
    //   4945: iastore
    //   4946: dup
    //   4947: bipush #8
    //   4949: sipush #1024
    //   4952: iastore
    //   4953: dup
    //   4954: bipush #9
    //   4956: ldc 16843776
    //   4958: iastore
    //   4959: dup
    //   4960: bipush #10
    //   4962: ldc 16843780
    //   4964: iastore
    //   4965: dup
    //   4966: bipush #11
    //   4968: sipush #1024
    //   4971: iastore
    //   4972: dup
    //   4973: bipush #12
    //   4975: ldc 16778244
    //   4977: iastore
    //   4978: dup
    //   4979: bipush #13
    //   4981: ldc 16842756
    //   4983: iastore
    //   4984: dup
    //   4985: bipush #14
    //   4987: ldc 16777216
    //   4989: iastore
    //   4990: dup
    //   4991: bipush #15
    //   4993: iconst_4
    //   4994: iastore
    //   4995: dup
    //   4996: bipush #16
    //   4998: sipush #1028
    //   5001: iastore
    //   5002: dup
    //   5003: bipush #17
    //   5005: ldc 16778240
    //   5007: iastore
    //   5008: dup
    //   5009: bipush #18
    //   5011: ldc 16778240
    //   5013: iastore
    //   5014: dup
    //   5015: bipush #19
    //   5017: ldc 66560
    //   5019: iastore
    //   5020: dup
    //   5021: bipush #20
    //   5023: ldc 66560
    //   5025: iastore
    //   5026: dup
    //   5027: bipush #21
    //   5029: ldc 16842752
    //   5031: iastore
    //   5032: dup
    //   5033: bipush #22
    //   5035: ldc 16842752
    //   5037: iastore
    //   5038: dup
    //   5039: bipush #23
    //   5041: ldc 16778244
    //   5043: iastore
    //   5044: dup
    //   5045: bipush #24
    //   5047: ldc 65540
    //   5049: iastore
    //   5050: dup
    //   5051: bipush #25
    //   5053: ldc 16777220
    //   5055: iastore
    //   5056: dup
    //   5057: bipush #26
    //   5059: ldc 16777220
    //   5061: iastore
    //   5062: dup
    //   5063: bipush #27
    //   5065: ldc 65540
    //   5067: iastore
    //   5068: dup
    //   5069: bipush #28
    //   5071: iconst_0
    //   5072: iastore
    //   5073: dup
    //   5074: bipush #29
    //   5076: sipush #1028
    //   5079: iastore
    //   5080: dup
    //   5081: bipush #30
    //   5083: ldc 66564
    //   5085: iastore
    //   5086: dup
    //   5087: bipush #31
    //   5089: ldc 16777216
    //   5091: iastore
    //   5092: dup
    //   5093: bipush #32
    //   5095: ldc 65536
    //   5097: iastore
    //   5098: dup
    //   5099: bipush #33
    //   5101: ldc 16843780
    //   5103: iastore
    //   5104: dup
    //   5105: bipush #34
    //   5107: iconst_4
    //   5108: iastore
    //   5109: dup
    //   5110: bipush #35
    //   5112: ldc 16842752
    //   5114: iastore
    //   5115: dup
    //   5116: bipush #36
    //   5118: ldc 16843776
    //   5120: iastore
    //   5121: dup
    //   5122: bipush #37
    //   5124: ldc 16777216
    //   5126: iastore
    //   5127: dup
    //   5128: bipush #38
    //   5130: ldc 16777216
    //   5132: iastore
    //   5133: dup
    //   5134: bipush #39
    //   5136: sipush #1024
    //   5139: iastore
    //   5140: dup
    //   5141: bipush #40
    //   5143: ldc 16842756
    //   5145: iastore
    //   5146: dup
    //   5147: bipush #41
    //   5149: ldc 65536
    //   5151: iastore
    //   5152: dup
    //   5153: bipush #42
    //   5155: ldc 66560
    //   5157: iastore
    //   5158: dup
    //   5159: bipush #43
    //   5161: ldc 16777220
    //   5163: iastore
    //   5164: dup
    //   5165: bipush #44
    //   5167: sipush #1024
    //   5170: iastore
    //   5171: dup
    //   5172: bipush #45
    //   5174: iconst_4
    //   5175: iastore
    //   5176: dup
    //   5177: bipush #46
    //   5179: ldc 16778244
    //   5181: iastore
    //   5182: dup
    //   5183: bipush #47
    //   5185: ldc 66564
    //   5187: iastore
    //   5188: dup
    //   5189: bipush #48
    //   5191: ldc 16843780
    //   5193: iastore
    //   5194: dup
    //   5195: bipush #49
    //   5197: ldc 65540
    //   5199: iastore
    //   5200: dup
    //   5201: bipush #50
    //   5203: ldc 16842752
    //   5205: iastore
    //   5206: dup
    //   5207: bipush #51
    //   5209: ldc 16778244
    //   5211: iastore
    //   5212: dup
    //   5213: bipush #52
    //   5215: ldc 16777220
    //   5217: iastore
    //   5218: dup
    //   5219: bipush #53
    //   5221: sipush #1028
    //   5224: iastore
    //   5225: dup
    //   5226: bipush #54
    //   5228: ldc 66564
    //   5230: iastore
    //   5231: dup
    //   5232: bipush #55
    //   5234: ldc 16843776
    //   5236: iastore
    //   5237: dup
    //   5238: bipush #56
    //   5240: sipush #1028
    //   5243: iastore
    //   5244: dup
    //   5245: bipush #57
    //   5247: ldc 16778240
    //   5249: iastore
    //   5250: dup
    //   5251: bipush #58
    //   5253: ldc 16778240
    //   5255: iastore
    //   5256: dup
    //   5257: bipush #59
    //   5259: iconst_0
    //   5260: iastore
    //   5261: dup
    //   5262: bipush #60
    //   5264: ldc 65540
    //   5266: iastore
    //   5267: dup
    //   5268: bipush #61
    //   5270: ldc 66560
    //   5272: iastore
    //   5273: dup
    //   5274: bipush #62
    //   5276: iconst_0
    //   5277: iastore
    //   5278: dup
    //   5279: bipush #63
    //   5281: ldc 16842756
    //   5283: iastore
    //   5284: astore #6
    //   5286: bipush #64
    //   5288: newarray int
    //   5290: dup
    //   5291: iconst_0
    //   5292: ldc -2146402272
    //   5294: iastore
    //   5295: dup
    //   5296: iconst_1
    //   5297: ldc -2147450880
    //   5299: iastore
    //   5300: dup
    //   5301: iconst_2
    //   5302: ldc 32768
    //   5304: iastore
    //   5305: dup
    //   5306: iconst_3
    //   5307: ldc 1081376
    //   5309: iastore
    //   5310: dup
    //   5311: iconst_4
    //   5312: ldc 1048576
    //   5314: iastore
    //   5315: dup
    //   5316: iconst_5
    //   5317: bipush #32
    //   5319: iastore
    //   5320: dup
    //   5321: bipush #6
    //   5323: ldc -2146435040
    //   5325: iastore
    //   5326: dup
    //   5327: bipush #7
    //   5329: ldc -2147450848
    //   5331: iastore
    //   5332: dup
    //   5333: bipush #8
    //   5335: ldc -2147483616
    //   5337: iastore
    //   5338: dup
    //   5339: bipush #9
    //   5341: ldc -2146402272
    //   5343: iastore
    //   5344: dup
    //   5345: bipush #10
    //   5347: ldc -2146402304
    //   5349: iastore
    //   5350: dup
    //   5351: bipush #11
    //   5353: ldc -2147483648
    //   5355: iastore
    //   5356: dup
    //   5357: bipush #12
    //   5359: ldc -2147450880
    //   5361: iastore
    //   5362: dup
    //   5363: bipush #13
    //   5365: ldc 1048576
    //   5367: iastore
    //   5368: dup
    //   5369: bipush #14
    //   5371: bipush #32
    //   5373: iastore
    //   5374: dup
    //   5375: bipush #15
    //   5377: ldc -2146435040
    //   5379: iastore
    //   5380: dup
    //   5381: bipush #16
    //   5383: ldc 1081344
    //   5385: iastore
    //   5386: dup
    //   5387: bipush #17
    //   5389: ldc 1048608
    //   5391: iastore
    //   5392: dup
    //   5393: bipush #18
    //   5395: ldc -2147450848
    //   5397: iastore
    //   5398: dup
    //   5399: bipush #19
    //   5401: iconst_0
    //   5402: iastore
    //   5403: dup
    //   5404: bipush #20
    //   5406: ldc -2147483648
    //   5408: iastore
    //   5409: dup
    //   5410: bipush #21
    //   5412: ldc 32768
    //   5414: iastore
    //   5415: dup
    //   5416: bipush #22
    //   5418: ldc 1081376
    //   5420: iastore
    //   5421: dup
    //   5422: bipush #23
    //   5424: ldc -2146435072
    //   5426: iastore
    //   5427: dup
    //   5428: bipush #24
    //   5430: ldc 1048608
    //   5432: iastore
    //   5433: dup
    //   5434: bipush #25
    //   5436: ldc -2147483616
    //   5438: iastore
    //   5439: dup
    //   5440: bipush #26
    //   5442: iconst_0
    //   5443: iastore
    //   5444: dup
    //   5445: bipush #27
    //   5447: ldc 1081344
    //   5449: iastore
    //   5450: dup
    //   5451: bipush #28
    //   5453: ldc 32800
    //   5455: iastore
    //   5456: dup
    //   5457: bipush #29
    //   5459: ldc -2146402304
    //   5461: iastore
    //   5462: dup
    //   5463: bipush #30
    //   5465: ldc -2146435072
    //   5467: iastore
    //   5468: dup
    //   5469: bipush #31
    //   5471: ldc 32800
    //   5473: iastore
    //   5474: dup
    //   5475: bipush #32
    //   5477: iconst_0
    //   5478: iastore
    //   5479: dup
    //   5480: bipush #33
    //   5482: ldc 1081376
    //   5484: iastore
    //   5485: dup
    //   5486: bipush #34
    //   5488: ldc -2146435040
    //   5490: iastore
    //   5491: dup
    //   5492: bipush #35
    //   5494: ldc 1048576
    //   5496: iastore
    //   5497: dup
    //   5498: bipush #36
    //   5500: ldc -2147450848
    //   5502: iastore
    //   5503: dup
    //   5504: bipush #37
    //   5506: ldc -2146435072
    //   5508: iastore
    //   5509: dup
    //   5510: bipush #38
    //   5512: ldc -2146402304
    //   5514: iastore
    //   5515: dup
    //   5516: bipush #39
    //   5518: ldc 32768
    //   5520: iastore
    //   5521: dup
    //   5522: bipush #40
    //   5524: ldc -2146435072
    //   5526: iastore
    //   5527: dup
    //   5528: bipush #41
    //   5530: ldc -2147450880
    //   5532: iastore
    //   5533: dup
    //   5534: bipush #42
    //   5536: bipush #32
    //   5538: iastore
    //   5539: dup
    //   5540: bipush #43
    //   5542: ldc -2146402272
    //   5544: iastore
    //   5545: dup
    //   5546: bipush #44
    //   5548: ldc 1081376
    //   5550: iastore
    //   5551: dup
    //   5552: bipush #45
    //   5554: bipush #32
    //   5556: iastore
    //   5557: dup
    //   5558: bipush #46
    //   5560: ldc 32768
    //   5562: iastore
    //   5563: dup
    //   5564: bipush #47
    //   5566: ldc -2147483648
    //   5568: iastore
    //   5569: dup
    //   5570: bipush #48
    //   5572: ldc 32800
    //   5574: iastore
    //   5575: dup
    //   5576: bipush #49
    //   5578: ldc -2146402304
    //   5580: iastore
    //   5581: dup
    //   5582: bipush #50
    //   5584: ldc 1048576
    //   5586: iastore
    //   5587: dup
    //   5588: bipush #51
    //   5590: ldc -2147483616
    //   5592: iastore
    //   5593: dup
    //   5594: bipush #52
    //   5596: ldc 1048608
    //   5598: iastore
    //   5599: dup
    //   5600: bipush #53
    //   5602: ldc -2147450848
    //   5604: iastore
    //   5605: dup
    //   5606: bipush #54
    //   5608: ldc -2147483616
    //   5610: iastore
    //   5611: dup
    //   5612: bipush #55
    //   5614: ldc 1048608
    //   5616: iastore
    //   5617: dup
    //   5618: bipush #56
    //   5620: ldc 1081344
    //   5622: iastore
    //   5623: dup
    //   5624: bipush #57
    //   5626: iconst_0
    //   5627: iastore
    //   5628: dup
    //   5629: bipush #58
    //   5631: ldc -2147450880
    //   5633: iastore
    //   5634: dup
    //   5635: bipush #59
    //   5637: ldc 32800
    //   5639: iastore
    //   5640: dup
    //   5641: bipush #60
    //   5643: ldc -2147483648
    //   5645: iastore
    //   5646: dup
    //   5647: bipush #61
    //   5649: ldc -2146435040
    //   5651: iastore
    //   5652: dup
    //   5653: bipush #62
    //   5655: ldc -2146402272
    //   5657: iastore
    //   5658: dup
    //   5659: bipush #63
    //   5661: ldc 1081344
    //   5663: iastore
    //   5664: astore #7
    //   5666: bipush #64
    //   5668: newarray int
    //   5670: dup
    //   5671: iconst_0
    //   5672: sipush #520
    //   5675: iastore
    //   5676: dup
    //   5677: iconst_1
    //   5678: ldc 134349312
    //   5680: iastore
    //   5681: dup
    //   5682: iconst_2
    //   5683: iconst_0
    //   5684: iastore
    //   5685: dup
    //   5686: iconst_3
    //   5687: ldc 134348808
    //   5689: iastore
    //   5690: dup
    //   5691: iconst_4
    //   5692: ldc 134218240
    //   5694: iastore
    //   5695: dup
    //   5696: iconst_5
    //   5697: iconst_0
    //   5698: iastore
    //   5699: dup
    //   5700: bipush #6
    //   5702: ldc 131592
    //   5704: iastore
    //   5705: dup
    //   5706: bipush #7
    //   5708: ldc 134218240
    //   5710: iastore
    //   5711: dup
    //   5712: bipush #8
    //   5714: ldc 131080
    //   5716: iastore
    //   5717: dup
    //   5718: bipush #9
    //   5720: ldc 134217736
    //   5722: iastore
    //   5723: dup
    //   5724: bipush #10
    //   5726: ldc 134217736
    //   5728: iastore
    //   5729: dup
    //   5730: bipush #11
    //   5732: ldc 131072
    //   5734: iastore
    //   5735: dup
    //   5736: bipush #12
    //   5738: ldc 134349320
    //   5740: iastore
    //   5741: dup
    //   5742: bipush #13
    //   5744: ldc 131080
    //   5746: iastore
    //   5747: dup
    //   5748: bipush #14
    //   5750: ldc 134348800
    //   5752: iastore
    //   5753: dup
    //   5754: bipush #15
    //   5756: sipush #520
    //   5759: iastore
    //   5760: dup
    //   5761: bipush #16
    //   5763: ldc 134217728
    //   5765: iastore
    //   5766: dup
    //   5767: bipush #17
    //   5769: bipush #8
    //   5771: iastore
    //   5772: dup
    //   5773: bipush #18
    //   5775: ldc 134349312
    //   5777: iastore
    //   5778: dup
    //   5779: bipush #19
    //   5781: sipush #512
    //   5784: iastore
    //   5785: dup
    //   5786: bipush #20
    //   5788: ldc 131584
    //   5790: iastore
    //   5791: dup
    //   5792: bipush #21
    //   5794: ldc 134348800
    //   5796: iastore
    //   5797: dup
    //   5798: bipush #22
    //   5800: ldc 134348808
    //   5802: iastore
    //   5803: dup
    //   5804: bipush #23
    //   5806: ldc 131592
    //   5808: iastore
    //   5809: dup
    //   5810: bipush #24
    //   5812: ldc 134218248
    //   5814: iastore
    //   5815: dup
    //   5816: bipush #25
    //   5818: ldc 131584
    //   5820: iastore
    //   5821: dup
    //   5822: bipush #26
    //   5824: ldc 131072
    //   5826: iastore
    //   5827: dup
    //   5828: bipush #27
    //   5830: ldc 134218248
    //   5832: iastore
    //   5833: dup
    //   5834: bipush #28
    //   5836: bipush #8
    //   5838: iastore
    //   5839: dup
    //   5840: bipush #29
    //   5842: ldc 134349320
    //   5844: iastore
    //   5845: dup
    //   5846: bipush #30
    //   5848: sipush #512
    //   5851: iastore
    //   5852: dup
    //   5853: bipush #31
    //   5855: ldc 134217728
    //   5857: iastore
    //   5858: dup
    //   5859: bipush #32
    //   5861: ldc 134349312
    //   5863: iastore
    //   5864: dup
    //   5865: bipush #33
    //   5867: ldc 134217728
    //   5869: iastore
    //   5870: dup
    //   5871: bipush #34
    //   5873: ldc 131080
    //   5875: iastore
    //   5876: dup
    //   5877: bipush #35
    //   5879: sipush #520
    //   5882: iastore
    //   5883: dup
    //   5884: bipush #36
    //   5886: ldc 131072
    //   5888: iastore
    //   5889: dup
    //   5890: bipush #37
    //   5892: ldc 134349312
    //   5894: iastore
    //   5895: dup
    //   5896: bipush #38
    //   5898: ldc 134218240
    //   5900: iastore
    //   5901: dup
    //   5902: bipush #39
    //   5904: iconst_0
    //   5905: iastore
    //   5906: dup
    //   5907: bipush #40
    //   5909: sipush #512
    //   5912: iastore
    //   5913: dup
    //   5914: bipush #41
    //   5916: ldc 131080
    //   5918: iastore
    //   5919: dup
    //   5920: bipush #42
    //   5922: ldc 134349320
    //   5924: iastore
    //   5925: dup
    //   5926: bipush #43
    //   5928: ldc 134218240
    //   5930: iastore
    //   5931: dup
    //   5932: bipush #44
    //   5934: ldc 134217736
    //   5936: iastore
    //   5937: dup
    //   5938: bipush #45
    //   5940: sipush #512
    //   5943: iastore
    //   5944: dup
    //   5945: bipush #46
    //   5947: iconst_0
    //   5948: iastore
    //   5949: dup
    //   5950: bipush #47
    //   5952: ldc 134348808
    //   5954: iastore
    //   5955: dup
    //   5956: bipush #48
    //   5958: ldc 134218248
    //   5960: iastore
    //   5961: dup
    //   5962: bipush #49
    //   5964: ldc 131072
    //   5966: iastore
    //   5967: dup
    //   5968: bipush #50
    //   5970: ldc 134217728
    //   5972: iastore
    //   5973: dup
    //   5974: bipush #51
    //   5976: ldc 134349320
    //   5978: iastore
    //   5979: dup
    //   5980: bipush #52
    //   5982: bipush #8
    //   5984: iastore
    //   5985: dup
    //   5986: bipush #53
    //   5988: ldc 131592
    //   5990: iastore
    //   5991: dup
    //   5992: bipush #54
    //   5994: ldc 131584
    //   5996: iastore
    //   5997: dup
    //   5998: bipush #55
    //   6000: ldc 134217736
    //   6002: iastore
    //   6003: dup
    //   6004: bipush #56
    //   6006: ldc 134348800
    //   6008: iastore
    //   6009: dup
    //   6010: bipush #57
    //   6012: ldc 134218248
    //   6014: iastore
    //   6015: dup
    //   6016: bipush #58
    //   6018: sipush #520
    //   6021: iastore
    //   6022: dup
    //   6023: bipush #59
    //   6025: ldc 134348800
    //   6027: iastore
    //   6028: dup
    //   6029: bipush #60
    //   6031: ldc 131592
    //   6033: iastore
    //   6034: dup
    //   6035: bipush #61
    //   6037: bipush #8
    //   6039: iastore
    //   6040: dup
    //   6041: bipush #62
    //   6043: ldc 134348808
    //   6045: iastore
    //   6046: dup
    //   6047: bipush #63
    //   6049: ldc 131584
    //   6051: iastore
    //   6052: astore #8
    //   6054: bipush #64
    //   6056: newarray int
    //   6058: dup
    //   6059: iconst_0
    //   6060: ldc 8396801
    //   6062: iastore
    //   6063: dup
    //   6064: iconst_1
    //   6065: sipush #8321
    //   6068: iastore
    //   6069: dup
    //   6070: iconst_2
    //   6071: sipush #8321
    //   6074: iastore
    //   6075: dup
    //   6076: iconst_3
    //   6077: sipush #128
    //   6080: iastore
    //   6081: dup
    //   6082: iconst_4
    //   6083: ldc 8396928
    //   6085: iastore
    //   6086: dup
    //   6087: iconst_5
    //   6088: ldc 8388737
    //   6090: iastore
    //   6091: dup
    //   6092: bipush #6
    //   6094: ldc 8388609
    //   6096: iastore
    //   6097: dup
    //   6098: bipush #7
    //   6100: sipush #8193
    //   6103: iastore
    //   6104: dup
    //   6105: bipush #8
    //   6107: iconst_0
    //   6108: iastore
    //   6109: dup
    //   6110: bipush #9
    //   6112: ldc 8396800
    //   6114: iastore
    //   6115: dup
    //   6116: bipush #10
    //   6118: ldc 8396800
    //   6120: iastore
    //   6121: dup
    //   6122: bipush #11
    //   6124: ldc 8396929
    //   6126: iastore
    //   6127: dup
    //   6128: bipush #12
    //   6130: sipush #129
    //   6133: iastore
    //   6134: dup
    //   6135: bipush #13
    //   6137: iconst_0
    //   6138: iastore
    //   6139: dup
    //   6140: bipush #14
    //   6142: ldc 8388736
    //   6144: iastore
    //   6145: dup
    //   6146: bipush #15
    //   6148: ldc 8388609
    //   6150: iastore
    //   6151: dup
    //   6152: bipush #16
    //   6154: iconst_1
    //   6155: iastore
    //   6156: dup
    //   6157: bipush #17
    //   6159: sipush #8192
    //   6162: iastore
    //   6163: dup
    //   6164: bipush #18
    //   6166: ldc 8388608
    //   6168: iastore
    //   6169: dup
    //   6170: bipush #19
    //   6172: ldc 8396801
    //   6174: iastore
    //   6175: dup
    //   6176: bipush #20
    //   6178: sipush #128
    //   6181: iastore
    //   6182: dup
    //   6183: bipush #21
    //   6185: ldc 8388608
    //   6187: iastore
    //   6188: dup
    //   6189: bipush #22
    //   6191: sipush #8193
    //   6194: iastore
    //   6195: dup
    //   6196: bipush #23
    //   6198: sipush #8320
    //   6201: iastore
    //   6202: dup
    //   6203: bipush #24
    //   6205: ldc 8388737
    //   6207: iastore
    //   6208: dup
    //   6209: bipush #25
    //   6211: iconst_1
    //   6212: iastore
    //   6213: dup
    //   6214: bipush #26
    //   6216: sipush #8320
    //   6219: iastore
    //   6220: dup
    //   6221: bipush #27
    //   6223: ldc 8388736
    //   6225: iastore
    //   6226: dup
    //   6227: bipush #28
    //   6229: sipush #8192
    //   6232: iastore
    //   6233: dup
    //   6234: bipush #29
    //   6236: ldc 8396928
    //   6238: iastore
    //   6239: dup
    //   6240: bipush #30
    //   6242: ldc 8396929
    //   6244: iastore
    //   6245: dup
    //   6246: bipush #31
    //   6248: sipush #129
    //   6251: iastore
    //   6252: dup
    //   6253: bipush #32
    //   6255: ldc 8388736
    //   6257: iastore
    //   6258: dup
    //   6259: bipush #33
    //   6261: ldc 8388609
    //   6263: iastore
    //   6264: dup
    //   6265: bipush #34
    //   6267: ldc 8396800
    //   6269: iastore
    //   6270: dup
    //   6271: bipush #35
    //   6273: ldc 8396929
    //   6275: iastore
    //   6276: dup
    //   6277: bipush #36
    //   6279: sipush #129
    //   6282: iastore
    //   6283: dup
    //   6284: bipush #37
    //   6286: iconst_0
    //   6287: iastore
    //   6288: dup
    //   6289: bipush #38
    //   6291: iconst_0
    //   6292: iastore
    //   6293: dup
    //   6294: bipush #39
    //   6296: ldc 8396800
    //   6298: iastore
    //   6299: dup
    //   6300: bipush #40
    //   6302: sipush #8320
    //   6305: iastore
    //   6306: dup
    //   6307: bipush #41
    //   6309: ldc 8388736
    //   6311: iastore
    //   6312: dup
    //   6313: bipush #42
    //   6315: ldc 8388737
    //   6317: iastore
    //   6318: dup
    //   6319: bipush #43
    //   6321: iconst_1
    //   6322: iastore
    //   6323: dup
    //   6324: bipush #44
    //   6326: ldc 8396801
    //   6328: iastore
    //   6329: dup
    //   6330: bipush #45
    //   6332: sipush #8321
    //   6335: iastore
    //   6336: dup
    //   6337: bipush #46
    //   6339: sipush #8321
    //   6342: iastore
    //   6343: dup
    //   6344: bipush #47
    //   6346: sipush #128
    //   6349: iastore
    //   6350: dup
    //   6351: bipush #48
    //   6353: ldc 8396929
    //   6355: iastore
    //   6356: dup
    //   6357: bipush #49
    //   6359: sipush #129
    //   6362: iastore
    //   6363: dup
    //   6364: bipush #50
    //   6366: iconst_1
    //   6367: iastore
    //   6368: dup
    //   6369: bipush #51
    //   6371: sipush #8192
    //   6374: iastore
    //   6375: dup
    //   6376: bipush #52
    //   6378: ldc 8388609
    //   6380: iastore
    //   6381: dup
    //   6382: bipush #53
    //   6384: sipush #8193
    //   6387: iastore
    //   6388: dup
    //   6389: bipush #54
    //   6391: ldc 8396928
    //   6393: iastore
    //   6394: dup
    //   6395: bipush #55
    //   6397: ldc 8388737
    //   6399: iastore
    //   6400: dup
    //   6401: bipush #56
    //   6403: sipush #8193
    //   6406: iastore
    //   6407: dup
    //   6408: bipush #57
    //   6410: sipush #8320
    //   6413: iastore
    //   6414: dup
    //   6415: bipush #58
    //   6417: ldc 8388608
    //   6419: iastore
    //   6420: dup
    //   6421: bipush #59
    //   6423: ldc 8396801
    //   6425: iastore
    //   6426: dup
    //   6427: bipush #60
    //   6429: sipush #128
    //   6432: iastore
    //   6433: dup
    //   6434: bipush #61
    //   6436: ldc 8388608
    //   6438: iastore
    //   6439: dup
    //   6440: bipush #62
    //   6442: sipush #8192
    //   6445: iastore
    //   6446: dup
    //   6447: bipush #63
    //   6449: ldc 8396928
    //   6451: iastore
    //   6452: astore #9
    //   6454: bipush #64
    //   6456: newarray int
    //   6458: dup
    //   6459: iconst_0
    //   6460: sipush #256
    //   6463: iastore
    //   6464: dup
    //   6465: iconst_1
    //   6466: ldc 34078976
    //   6468: iastore
    //   6469: dup
    //   6470: iconst_2
    //   6471: ldc 34078720
    //   6473: iastore
    //   6474: dup
    //   6475: iconst_3
    //   6476: ldc 1107296512
    //   6478: iastore
    //   6479: dup
    //   6480: iconst_4
    //   6481: ldc 524288
    //   6483: iastore
    //   6484: dup
    //   6485: iconst_5
    //   6486: sipush #256
    //   6489: iastore
    //   6490: dup
    //   6491: bipush #6
    //   6493: ldc 1073741824
    //   6495: iastore
    //   6496: dup
    //   6497: bipush #7
    //   6499: ldc 34078720
    //   6501: iastore
    //   6502: dup
    //   6503: bipush #8
    //   6505: ldc 1074266368
    //   6507: iastore
    //   6508: dup
    //   6509: bipush #9
    //   6511: ldc 524288
    //   6513: iastore
    //   6514: dup
    //   6515: bipush #10
    //   6517: ldc 33554688
    //   6519: iastore
    //   6520: dup
    //   6521: bipush #11
    //   6523: ldc 1074266368
    //   6525: iastore
    //   6526: dup
    //   6527: bipush #12
    //   6529: ldc 1107296512
    //   6531: iastore
    //   6532: dup
    //   6533: bipush #13
    //   6535: ldc 1107820544
    //   6537: iastore
    //   6538: dup
    //   6539: bipush #14
    //   6541: ldc 524544
    //   6543: iastore
    //   6544: dup
    //   6545: bipush #15
    //   6547: ldc 1073741824
    //   6549: iastore
    //   6550: dup
    //   6551: bipush #16
    //   6553: ldc 33554432
    //   6555: iastore
    //   6556: dup
    //   6557: bipush #17
    //   6559: ldc 1074266112
    //   6561: iastore
    //   6562: dup
    //   6563: bipush #18
    //   6565: ldc 1074266112
    //   6567: iastore
    //   6568: dup
    //   6569: bipush #19
    //   6571: iconst_0
    //   6572: iastore
    //   6573: dup
    //   6574: bipush #20
    //   6576: ldc 1073742080
    //   6578: iastore
    //   6579: dup
    //   6580: bipush #21
    //   6582: ldc 1107820800
    //   6584: iastore
    //   6585: dup
    //   6586: bipush #22
    //   6588: ldc 1107820800
    //   6590: iastore
    //   6591: dup
    //   6592: bipush #23
    //   6594: ldc 33554688
    //   6596: iastore
    //   6597: dup
    //   6598: bipush #24
    //   6600: ldc 1107820544
    //   6602: iastore
    //   6603: dup
    //   6604: bipush #25
    //   6606: ldc 1073742080
    //   6608: iastore
    //   6609: dup
    //   6610: bipush #26
    //   6612: iconst_0
    //   6613: iastore
    //   6614: dup
    //   6615: bipush #27
    //   6617: ldc 1107296256
    //   6619: iastore
    //   6620: dup
    //   6621: bipush #28
    //   6623: ldc 34078976
    //   6625: iastore
    //   6626: dup
    //   6627: bipush #29
    //   6629: ldc 33554432
    //   6631: iastore
    //   6632: dup
    //   6633: bipush #30
    //   6635: ldc 1107296256
    //   6637: iastore
    //   6638: dup
    //   6639: bipush #31
    //   6641: ldc 524544
    //   6643: iastore
    //   6644: dup
    //   6645: bipush #32
    //   6647: ldc 524288
    //   6649: iastore
    //   6650: dup
    //   6651: bipush #33
    //   6653: ldc 1107296512
    //   6655: iastore
    //   6656: dup
    //   6657: bipush #34
    //   6659: sipush #256
    //   6662: iastore
    //   6663: dup
    //   6664: bipush #35
    //   6666: ldc 33554432
    //   6668: iastore
    //   6669: dup
    //   6670: bipush #36
    //   6672: ldc 1073741824
    //   6674: iastore
    //   6675: dup
    //   6676: bipush #37
    //   6678: ldc 34078720
    //   6680: iastore
    //   6681: dup
    //   6682: bipush #38
    //   6684: ldc 1107296512
    //   6686: iastore
    //   6687: dup
    //   6688: bipush #39
    //   6690: ldc 1074266368
    //   6692: iastore
    //   6693: dup
    //   6694: bipush #40
    //   6696: ldc 33554688
    //   6698: iastore
    //   6699: dup
    //   6700: bipush #41
    //   6702: ldc 1073741824
    //   6704: iastore
    //   6705: dup
    //   6706: bipush #42
    //   6708: ldc 1107820544
    //   6710: iastore
    //   6711: dup
    //   6712: bipush #43
    //   6714: ldc 34078976
    //   6716: iastore
    //   6717: dup
    //   6718: bipush #44
    //   6720: ldc 1074266368
    //   6722: iastore
    //   6723: dup
    //   6724: bipush #45
    //   6726: sipush #256
    //   6729: iastore
    //   6730: dup
    //   6731: bipush #46
    //   6733: ldc 33554432
    //   6735: iastore
    //   6736: dup
    //   6737: bipush #47
    //   6739: ldc 1107820544
    //   6741: iastore
    //   6742: dup
    //   6743: bipush #48
    //   6745: ldc 1107820800
    //   6747: iastore
    //   6748: dup
    //   6749: bipush #49
    //   6751: ldc 524544
    //   6753: iastore
    //   6754: dup
    //   6755: bipush #50
    //   6757: ldc 1107296256
    //   6759: iastore
    //   6760: dup
    //   6761: bipush #51
    //   6763: ldc 1107820800
    //   6765: iastore
    //   6766: dup
    //   6767: bipush #52
    //   6769: ldc 34078720
    //   6771: iastore
    //   6772: dup
    //   6773: bipush #53
    //   6775: iconst_0
    //   6776: iastore
    //   6777: dup
    //   6778: bipush #54
    //   6780: ldc 1074266112
    //   6782: iastore
    //   6783: dup
    //   6784: bipush #55
    //   6786: ldc 1107296256
    //   6788: iastore
    //   6789: dup
    //   6790: bipush #56
    //   6792: ldc 524544
    //   6794: iastore
    //   6795: dup
    //   6796: bipush #57
    //   6798: ldc 33554688
    //   6800: iastore
    //   6801: dup
    //   6802: bipush #58
    //   6804: ldc 1073742080
    //   6806: iastore
    //   6807: dup
    //   6808: bipush #59
    //   6810: ldc 524288
    //   6812: iastore
    //   6813: dup
    //   6814: bipush #60
    //   6816: iconst_0
    //   6817: iastore
    //   6818: dup
    //   6819: bipush #61
    //   6821: ldc 1074266112
    //   6823: iastore
    //   6824: dup
    //   6825: bipush #62
    //   6827: ldc 34078976
    //   6829: iastore
    //   6830: dup
    //   6831: bipush #63
    //   6833: ldc 1073742080
    //   6835: iastore
    //   6836: astore #10
    //   6838: bipush #64
    //   6840: newarray int
    //   6842: dup
    //   6843: iconst_0
    //   6844: ldc 536870928
    //   6846: iastore
    //   6847: dup
    //   6848: iconst_1
    //   6849: ldc 541065216
    //   6851: iastore
    //   6852: dup
    //   6853: iconst_2
    //   6854: sipush #16384
    //   6857: iastore
    //   6858: dup
    //   6859: iconst_3
    //   6860: ldc 541081616
    //   6862: iastore
    //   6863: dup
    //   6864: iconst_4
    //   6865: ldc 541065216
    //   6867: iastore
    //   6868: dup
    //   6869: iconst_5
    //   6870: bipush #16
    //   6872: iastore
    //   6873: dup
    //   6874: bipush #6
    //   6876: ldc 541081616
    //   6878: iastore
    //   6879: dup
    //   6880: bipush #7
    //   6882: ldc 4194304
    //   6884: iastore
    //   6885: dup
    //   6886: bipush #8
    //   6888: ldc 536887296
    //   6890: iastore
    //   6891: dup
    //   6892: bipush #9
    //   6894: ldc 4210704
    //   6896: iastore
    //   6897: dup
    //   6898: bipush #10
    //   6900: ldc 4194304
    //   6902: iastore
    //   6903: dup
    //   6904: bipush #11
    //   6906: ldc 536870928
    //   6908: iastore
    //   6909: dup
    //   6910: bipush #12
    //   6912: ldc 4194320
    //   6914: iastore
    //   6915: dup
    //   6916: bipush #13
    //   6918: ldc 536887296
    //   6920: iastore
    //   6921: dup
    //   6922: bipush #14
    //   6924: ldc 536870912
    //   6926: iastore
    //   6927: dup
    //   6928: bipush #15
    //   6930: sipush #16400
    //   6933: iastore
    //   6934: dup
    //   6935: bipush #16
    //   6937: iconst_0
    //   6938: iastore
    //   6939: dup
    //   6940: bipush #17
    //   6942: ldc 4194320
    //   6944: iastore
    //   6945: dup
    //   6946: bipush #18
    //   6948: ldc 536887312
    //   6950: iastore
    //   6951: dup
    //   6952: bipush #19
    //   6954: sipush #16384
    //   6957: iastore
    //   6958: dup
    //   6959: bipush #20
    //   6961: ldc 4210688
    //   6963: iastore
    //   6964: dup
    //   6965: bipush #21
    //   6967: ldc 536887312
    //   6969: iastore
    //   6970: dup
    //   6971: bipush #22
    //   6973: bipush #16
    //   6975: iastore
    //   6976: dup
    //   6977: bipush #23
    //   6979: ldc 541065232
    //   6981: iastore
    //   6982: dup
    //   6983: bipush #24
    //   6985: ldc 541065232
    //   6987: iastore
    //   6988: dup
    //   6989: bipush #25
    //   6991: iconst_0
    //   6992: iastore
    //   6993: dup
    //   6994: bipush #26
    //   6996: ldc 4210704
    //   6998: iastore
    //   6999: dup
    //   7000: bipush #27
    //   7002: ldc 541081600
    //   7004: iastore
    //   7005: dup
    //   7006: bipush #28
    //   7008: sipush #16400
    //   7011: iastore
    //   7012: dup
    //   7013: bipush #29
    //   7015: ldc 4210688
    //   7017: iastore
    //   7018: dup
    //   7019: bipush #30
    //   7021: ldc 541081600
    //   7023: iastore
    //   7024: dup
    //   7025: bipush #31
    //   7027: ldc 536870912
    //   7029: iastore
    //   7030: dup
    //   7031: bipush #32
    //   7033: ldc 536887296
    //   7035: iastore
    //   7036: dup
    //   7037: bipush #33
    //   7039: bipush #16
    //   7041: iastore
    //   7042: dup
    //   7043: bipush #34
    //   7045: ldc 541065232
    //   7047: iastore
    //   7048: dup
    //   7049: bipush #35
    //   7051: ldc 4210688
    //   7053: iastore
    //   7054: dup
    //   7055: bipush #36
    //   7057: ldc 541081616
    //   7059: iastore
    //   7060: dup
    //   7061: bipush #37
    //   7063: ldc 4194304
    //   7065: iastore
    //   7066: dup
    //   7067: bipush #38
    //   7069: sipush #16400
    //   7072: iastore
    //   7073: dup
    //   7074: bipush #39
    //   7076: ldc 536870928
    //   7078: iastore
    //   7079: dup
    //   7080: bipush #40
    //   7082: ldc 4194304
    //   7084: iastore
    //   7085: dup
    //   7086: bipush #41
    //   7088: ldc 536887296
    //   7090: iastore
    //   7091: dup
    //   7092: bipush #42
    //   7094: ldc 536870912
    //   7096: iastore
    //   7097: dup
    //   7098: bipush #43
    //   7100: sipush #16400
    //   7103: iastore
    //   7104: dup
    //   7105: bipush #44
    //   7107: ldc 536870928
    //   7109: iastore
    //   7110: dup
    //   7111: bipush #45
    //   7113: ldc 541081616
    //   7115: iastore
    //   7116: dup
    //   7117: bipush #46
    //   7119: ldc 4210688
    //   7121: iastore
    //   7122: dup
    //   7123: bipush #47
    //   7125: ldc 541065216
    //   7127: iastore
    //   7128: dup
    //   7129: bipush #48
    //   7131: ldc 4210704
    //   7133: iastore
    //   7134: dup
    //   7135: bipush #49
    //   7137: ldc 541081600
    //   7139: iastore
    //   7140: dup
    //   7141: bipush #50
    //   7143: iconst_0
    //   7144: iastore
    //   7145: dup
    //   7146: bipush #51
    //   7148: ldc 541065232
    //   7150: iastore
    //   7151: dup
    //   7152: bipush #52
    //   7154: bipush #16
    //   7156: iastore
    //   7157: dup
    //   7158: bipush #53
    //   7160: sipush #16384
    //   7163: iastore
    //   7164: dup
    //   7165: bipush #54
    //   7167: ldc 541065216
    //   7169: iastore
    //   7170: dup
    //   7171: bipush #55
    //   7173: ldc 4210704
    //   7175: iastore
    //   7176: dup
    //   7177: bipush #56
    //   7179: sipush #16384
    //   7182: iastore
    //   7183: dup
    //   7184: bipush #57
    //   7186: ldc 4194320
    //   7188: iastore
    //   7189: dup
    //   7190: bipush #58
    //   7192: ldc 536887312
    //   7194: iastore
    //   7195: dup
    //   7196: bipush #59
    //   7198: iconst_0
    //   7199: iastore
    //   7200: dup
    //   7201: bipush #60
    //   7203: ldc 541081600
    //   7205: iastore
    //   7206: dup
    //   7207: bipush #61
    //   7209: ldc 536870912
    //   7211: iastore
    //   7212: dup
    //   7213: bipush #62
    //   7215: ldc 4194320
    //   7217: iastore
    //   7218: dup
    //   7219: bipush #63
    //   7221: ldc 536887312
    //   7223: iastore
    //   7224: astore #11
    //   7226: bipush #64
    //   7228: newarray int
    //   7230: dup
    //   7231: iconst_0
    //   7232: ldc 2097152
    //   7234: iastore
    //   7235: dup
    //   7236: iconst_1
    //   7237: ldc 69206018
    //   7239: iastore
    //   7240: dup
    //   7241: iconst_2
    //   7242: ldc 67110914
    //   7244: iastore
    //   7245: dup
    //   7246: iconst_3
    //   7247: iconst_0
    //   7248: iastore
    //   7249: dup
    //   7250: iconst_4
    //   7251: sipush #2048
    //   7254: iastore
    //   7255: dup
    //   7256: iconst_5
    //   7257: ldc 67110914
    //   7259: iastore
    //   7260: dup
    //   7261: bipush #6
    //   7263: ldc 2099202
    //   7265: iastore
    //   7266: dup
    //   7267: bipush #7
    //   7269: ldc 69208064
    //   7271: iastore
    //   7272: dup
    //   7273: bipush #8
    //   7275: ldc 69208066
    //   7277: iastore
    //   7278: dup
    //   7279: bipush #9
    //   7281: ldc 2097152
    //   7283: iastore
    //   7284: dup
    //   7285: bipush #10
    //   7287: iconst_0
    //   7288: iastore
    //   7289: dup
    //   7290: bipush #11
    //   7292: ldc 67108866
    //   7294: iastore
    //   7295: dup
    //   7296: bipush #12
    //   7298: iconst_2
    //   7299: iastore
    //   7300: dup
    //   7301: bipush #13
    //   7303: ldc 67108864
    //   7305: iastore
    //   7306: dup
    //   7307: bipush #14
    //   7309: ldc 69206018
    //   7311: iastore
    //   7312: dup
    //   7313: bipush #15
    //   7315: sipush #2050
    //   7318: iastore
    //   7319: dup
    //   7320: bipush #16
    //   7322: ldc 67110912
    //   7324: iastore
    //   7325: dup
    //   7326: bipush #17
    //   7328: ldc 2099202
    //   7330: iastore
    //   7331: dup
    //   7332: bipush #18
    //   7334: ldc 2097154
    //   7336: iastore
    //   7337: dup
    //   7338: bipush #19
    //   7340: ldc 67110912
    //   7342: iastore
    //   7343: dup
    //   7344: bipush #20
    //   7346: ldc 67108866
    //   7348: iastore
    //   7349: dup
    //   7350: bipush #21
    //   7352: ldc 69206016
    //   7354: iastore
    //   7355: dup
    //   7356: bipush #22
    //   7358: ldc 69208064
    //   7360: iastore
    //   7361: dup
    //   7362: bipush #23
    //   7364: ldc 2097154
    //   7366: iastore
    //   7367: dup
    //   7368: bipush #24
    //   7370: ldc 69206016
    //   7372: iastore
    //   7373: dup
    //   7374: bipush #25
    //   7376: sipush #2048
    //   7379: iastore
    //   7380: dup
    //   7381: bipush #26
    //   7383: sipush #2050
    //   7386: iastore
    //   7387: dup
    //   7388: bipush #27
    //   7390: ldc 69208066
    //   7392: iastore
    //   7393: dup
    //   7394: bipush #28
    //   7396: ldc 2099200
    //   7398: iastore
    //   7399: dup
    //   7400: bipush #29
    //   7402: iconst_2
    //   7403: iastore
    //   7404: dup
    //   7405: bipush #30
    //   7407: ldc 67108864
    //   7409: iastore
    //   7410: dup
    //   7411: bipush #31
    //   7413: ldc 2099200
    //   7415: iastore
    //   7416: dup
    //   7417: bipush #32
    //   7419: ldc 67108864
    //   7421: iastore
    //   7422: dup
    //   7423: bipush #33
    //   7425: ldc 2099200
    //   7427: iastore
    //   7428: dup
    //   7429: bipush #34
    //   7431: ldc 2097152
    //   7433: iastore
    //   7434: dup
    //   7435: bipush #35
    //   7437: ldc 67110914
    //   7439: iastore
    //   7440: dup
    //   7441: bipush #36
    //   7443: ldc 67110914
    //   7445: iastore
    //   7446: dup
    //   7447: bipush #37
    //   7449: ldc 69206018
    //   7451: iastore
    //   7452: dup
    //   7453: bipush #38
    //   7455: ldc 69206018
    //   7457: iastore
    //   7458: dup
    //   7459: bipush #39
    //   7461: iconst_2
    //   7462: iastore
    //   7463: dup
    //   7464: bipush #40
    //   7466: ldc 2097154
    //   7468: iastore
    //   7469: dup
    //   7470: bipush #41
    //   7472: ldc 67108864
    //   7474: iastore
    //   7475: dup
    //   7476: bipush #42
    //   7478: ldc 67110912
    //   7480: iastore
    //   7481: dup
    //   7482: bipush #43
    //   7484: ldc 2097152
    //   7486: iastore
    //   7487: dup
    //   7488: bipush #44
    //   7490: ldc 69208064
    //   7492: iastore
    //   7493: dup
    //   7494: bipush #45
    //   7496: sipush #2050
    //   7499: iastore
    //   7500: dup
    //   7501: bipush #46
    //   7503: ldc 2099202
    //   7505: iastore
    //   7506: dup
    //   7507: bipush #47
    //   7509: ldc 69208064
    //   7511: iastore
    //   7512: dup
    //   7513: bipush #48
    //   7515: sipush #2050
    //   7518: iastore
    //   7519: dup
    //   7520: bipush #49
    //   7522: ldc 67108866
    //   7524: iastore
    //   7525: dup
    //   7526: bipush #50
    //   7528: ldc 69208066
    //   7530: iastore
    //   7531: dup
    //   7532: bipush #51
    //   7534: ldc 69206016
    //   7536: iastore
    //   7537: dup
    //   7538: bipush #52
    //   7540: ldc 2099200
    //   7542: iastore
    //   7543: dup
    //   7544: bipush #53
    //   7546: iconst_0
    //   7547: iastore
    //   7548: dup
    //   7549: bipush #54
    //   7551: iconst_2
    //   7552: iastore
    //   7553: dup
    //   7554: bipush #55
    //   7556: ldc 69208066
    //   7558: iastore
    //   7559: dup
    //   7560: bipush #56
    //   7562: iconst_0
    //   7563: iastore
    //   7564: dup
    //   7565: bipush #57
    //   7567: ldc 2099202
    //   7569: iastore
    //   7570: dup
    //   7571: bipush #58
    //   7573: ldc 69206016
    //   7575: iastore
    //   7576: dup
    //   7577: bipush #59
    //   7579: sipush #2048
    //   7582: iastore
    //   7583: dup
    //   7584: bipush #60
    //   7586: ldc 67108866
    //   7588: iastore
    //   7589: dup
    //   7590: bipush #61
    //   7592: ldc 67110912
    //   7594: iastore
    //   7595: dup
    //   7596: bipush #62
    //   7598: sipush #2048
    //   7601: iastore
    //   7602: dup
    //   7603: bipush #63
    //   7605: ldc 2097154
    //   7607: iastore
    //   7608: astore #12
    //   7610: bipush #64
    //   7612: newarray int
    //   7614: dup
    //   7615: iconst_0
    //   7616: ldc 268439616
    //   7618: iastore
    //   7619: dup
    //   7620: iconst_1
    //   7621: sipush #4096
    //   7624: iastore
    //   7625: dup
    //   7626: iconst_2
    //   7627: ldc 262144
    //   7629: iastore
    //   7630: dup
    //   7631: iconst_3
    //   7632: ldc 268701760
    //   7634: iastore
    //   7635: dup
    //   7636: iconst_4
    //   7637: ldc 268435456
    //   7639: iastore
    //   7640: dup
    //   7641: iconst_5
    //   7642: ldc 268439616
    //   7644: iastore
    //   7645: dup
    //   7646: bipush #6
    //   7648: bipush #64
    //   7650: iastore
    //   7651: dup
    //   7652: bipush #7
    //   7654: ldc 268435456
    //   7656: iastore
    //   7657: dup
    //   7658: bipush #8
    //   7660: ldc 262208
    //   7662: iastore
    //   7663: dup
    //   7664: bipush #9
    //   7666: ldc 268697600
    //   7668: iastore
    //   7669: dup
    //   7670: bipush #10
    //   7672: ldc 268701760
    //   7674: iastore
    //   7675: dup
    //   7676: bipush #11
    //   7678: ldc 266240
    //   7680: iastore
    //   7681: dup
    //   7682: bipush #12
    //   7684: ldc 268701696
    //   7686: iastore
    //   7687: dup
    //   7688: bipush #13
    //   7690: ldc 266304
    //   7692: iastore
    //   7693: dup
    //   7694: bipush #14
    //   7696: sipush #4096
    //   7699: iastore
    //   7700: dup
    //   7701: bipush #15
    //   7703: bipush #64
    //   7705: iastore
    //   7706: dup
    //   7707: bipush #16
    //   7709: ldc 268697600
    //   7711: iastore
    //   7712: dup
    //   7713: bipush #17
    //   7715: ldc 268435520
    //   7717: iastore
    //   7718: dup
    //   7719: bipush #18
    //   7721: ldc 268439552
    //   7723: iastore
    //   7724: dup
    //   7725: bipush #19
    //   7727: sipush #4160
    //   7730: iastore
    //   7731: dup
    //   7732: bipush #20
    //   7734: ldc 266240
    //   7736: iastore
    //   7737: dup
    //   7738: bipush #21
    //   7740: ldc 262208
    //   7742: iastore
    //   7743: dup
    //   7744: bipush #22
    //   7746: ldc 268697664
    //   7748: iastore
    //   7749: dup
    //   7750: bipush #23
    //   7752: ldc 268701696
    //   7754: iastore
    //   7755: dup
    //   7756: bipush #24
    //   7758: sipush #4160
    //   7761: iastore
    //   7762: dup
    //   7763: bipush #25
    //   7765: iconst_0
    //   7766: iastore
    //   7767: dup
    //   7768: bipush #26
    //   7770: iconst_0
    //   7771: iastore
    //   7772: dup
    //   7773: bipush #27
    //   7775: ldc 268697664
    //   7777: iastore
    //   7778: dup
    //   7779: bipush #28
    //   7781: ldc 268435520
    //   7783: iastore
    //   7784: dup
    //   7785: bipush #29
    //   7787: ldc 268439552
    //   7789: iastore
    //   7790: dup
    //   7791: bipush #30
    //   7793: ldc 266304
    //   7795: iastore
    //   7796: dup
    //   7797: bipush #31
    //   7799: ldc 262144
    //   7801: iastore
    //   7802: dup
    //   7803: bipush #32
    //   7805: ldc 266304
    //   7807: iastore
    //   7808: dup
    //   7809: bipush #33
    //   7811: ldc 262144
    //   7813: iastore
    //   7814: dup
    //   7815: bipush #34
    //   7817: ldc 268701696
    //   7819: iastore
    //   7820: dup
    //   7821: bipush #35
    //   7823: sipush #4096
    //   7826: iastore
    //   7827: dup
    //   7828: bipush #36
    //   7830: bipush #64
    //   7832: iastore
    //   7833: dup
    //   7834: bipush #37
    //   7836: ldc 268697664
    //   7838: iastore
    //   7839: dup
    //   7840: bipush #38
    //   7842: sipush #4096
    //   7845: iastore
    //   7846: dup
    //   7847: bipush #39
    //   7849: ldc 266304
    //   7851: iastore
    //   7852: dup
    //   7853: bipush #40
    //   7855: ldc 268439552
    //   7857: iastore
    //   7858: dup
    //   7859: bipush #41
    //   7861: bipush #64
    //   7863: iastore
    //   7864: dup
    //   7865: bipush #42
    //   7867: ldc 268435520
    //   7869: iastore
    //   7870: dup
    //   7871: bipush #43
    //   7873: ldc 268697600
    //   7875: iastore
    //   7876: dup
    //   7877: bipush #44
    //   7879: ldc 268697664
    //   7881: iastore
    //   7882: dup
    //   7883: bipush #45
    //   7885: ldc 268435456
    //   7887: iastore
    //   7888: dup
    //   7889: bipush #46
    //   7891: ldc 262144
    //   7893: iastore
    //   7894: dup
    //   7895: bipush #47
    //   7897: ldc 268439616
    //   7899: iastore
    //   7900: dup
    //   7901: bipush #48
    //   7903: iconst_0
    //   7904: iastore
    //   7905: dup
    //   7906: bipush #49
    //   7908: ldc 268701760
    //   7910: iastore
    //   7911: dup
    //   7912: bipush #50
    //   7914: ldc 262208
    //   7916: iastore
    //   7917: dup
    //   7918: bipush #51
    //   7920: ldc 268435520
    //   7922: iastore
    //   7923: dup
    //   7924: bipush #52
    //   7926: ldc 268697600
    //   7928: iastore
    //   7929: dup
    //   7930: bipush #53
    //   7932: ldc 268439552
    //   7934: iastore
    //   7935: dup
    //   7936: bipush #54
    //   7938: ldc 268439616
    //   7940: iastore
    //   7941: dup
    //   7942: bipush #55
    //   7944: iconst_0
    //   7945: iastore
    //   7946: dup
    //   7947: bipush #56
    //   7949: ldc 268701760
    //   7951: iastore
    //   7952: dup
    //   7953: bipush #57
    //   7955: ldc 266240
    //   7957: iastore
    //   7958: dup
    //   7959: bipush #58
    //   7961: ldc 266240
    //   7963: iastore
    //   7964: dup
    //   7965: bipush #59
    //   7967: sipush #4160
    //   7970: iastore
    //   7971: dup
    //   7972: bipush #60
    //   7974: sipush #4160
    //   7977: iastore
    //   7978: dup
    //   7979: bipush #61
    //   7981: ldc 262208
    //   7983: iastore
    //   7984: dup
    //   7985: bipush #62
    //   7987: ldc 268435456
    //   7989: iastore
    //   7990: dup
    //   7991: bipush #63
    //   7993: ldc 268701696
    //   7995: iastore
    //   7996: astore #13
    //   7998: aload_3
    //   7999: arraylength
    //   8000: istore #14
    //   8002: iload #14
    //   8004: bipush #8
    //   8006: irem
    //   8007: ifeq -> 8031
    //   8010: new java/lang/Exception
    //   8013: dup
    //   8014: sipush #-11455
    //   8017: sipush #25123
    //   8020: invokestatic a : (II)Ljava/lang/String;
    //   8023: invokespecial <init> : (Ljava/lang/String;)V
    //   8026: athrow
    //   8027: invokestatic a : (Ljava/lang/Throwable;)Ljava/lang/Throwable;
    //   8030: athrow
    //   8031: iconst_2
    //   8032: newarray int
    //   8034: astore #15
    //   8036: iload #14
    //   8038: newarray byte
    //   8040: astore #16
    //   8042: iload #14
    //   8044: bipush #8
    //   8046: idiv
    //   8047: istore #17
    //   8049: iconst_0
    //   8050: istore #18
    //   8052: iload #18
    //   8054: iload #17
    //   8056: if_icmpge -> 8970
    //   8059: iload #18
    //   8061: bipush #8
    //   8063: imul
    //   8064: istore #19
    //   8066: iconst_0
    //   8067: istore #20
    //   8069: iload #20
    //   8071: iconst_2
    //   8072: if_icmpge -> 8157
    //   8075: aload #15
    //   8077: iload #20
    //   8079: aload_3
    //   8080: iload #19
    //   8082: iload #20
    //   8084: iconst_4
    //   8085: imul
    //   8086: iadd
    //   8087: baload
    //   8088: sipush #255
    //   8091: iand
    //   8092: bipush #24
    //   8094: ishl
    //   8095: aload_3
    //   8096: iload #19
    //   8098: iload #20
    //   8100: iconst_4
    //   8101: imul
    //   8102: iadd
    //   8103: iconst_1
    //   8104: iadd
    //   8105: baload
    //   8106: sipush #255
    //   8109: iand
    //   8110: bipush #16
    //   8112: ishl
    //   8113: ior
    //   8114: aload_3
    //   8115: iload #19
    //   8117: iload #20
    //   8119: iconst_4
    //   8120: imul
    //   8121: iadd
    //   8122: iconst_2
    //   8123: iadd
    //   8124: baload
    //   8125: sipush #255
    //   8128: iand
    //   8129: bipush #8
    //   8131: ishl
    //   8132: ior
    //   8133: aload_3
    //   8134: iload #19
    //   8136: iload #20
    //   8138: iconst_4
    //   8139: imul
    //   8140: iadd
    //   8141: iconst_3
    //   8142: iadd
    //   8143: baload
    //   8144: sipush #255
    //   8147: iand
    //   8148: ior
    //   8149: iastore
    //   8150: iinc #20, 1
    //   8153: iload_2
    //   8154: ifeq -> 8069
    //   8157: iconst_0
    //   8158: istore #25
    //   8160: aload #15
    //   8162: iconst_0
    //   8163: iaload
    //   8164: istore #23
    //   8166: aload #15
    //   8168: iconst_1
    //   8169: iaload
    //   8170: istore #22
    //   8172: iload #23
    //   8174: iconst_4
    //   8175: iushr
    //   8176: iload #22
    //   8178: ixor
    //   8179: ldc 252645135
    //   8181: iand
    //   8182: istore #21
    //   8184: iload #22
    //   8186: iload #21
    //   8188: ixor
    //   8189: istore #22
    //   8191: iload #23
    //   8193: iload #21
    //   8195: iconst_4
    //   8196: ishl
    //   8197: ixor
    //   8198: istore #23
    //   8200: iload #23
    //   8202: bipush #16
    //   8204: iushr
    //   8205: iload #22
    //   8207: ixor
    //   8208: ldc 65535
    //   8210: iand
    //   8211: istore #21
    //   8213: iload #22
    //   8215: iload #21
    //   8217: ixor
    //   8218: istore #22
    //   8220: iload #23
    //   8222: iload #21
    //   8224: bipush #16
    //   8226: ishl
    //   8227: ixor
    //   8228: istore #23
    //   8230: iload #22
    //   8232: iconst_2
    //   8233: iushr
    //   8234: iload #23
    //   8236: ixor
    //   8237: ldc 858993459
    //   8239: iand
    //   8240: istore #21
    //   8242: iload #23
    //   8244: iload #21
    //   8246: ixor
    //   8247: istore #23
    //   8249: iload #22
    //   8251: iload #21
    //   8253: iconst_2
    //   8254: ishl
    //   8255: ixor
    //   8256: istore #22
    //   8258: iload #22
    //   8260: bipush #8
    //   8262: iushr
    //   8263: iload #23
    //   8265: ixor
    //   8266: ldc 16711935
    //   8268: iand
    //   8269: istore #21
    //   8271: iload #23
    //   8273: iload #21
    //   8275: ixor
    //   8276: istore #23
    //   8278: iload #22
    //   8280: iload #21
    //   8282: bipush #8
    //   8284: ishl
    //   8285: ixor
    //   8286: istore #22
    //   8288: iload #22
    //   8290: iconst_1
    //   8291: ishl
    //   8292: iload #22
    //   8294: bipush #31
    //   8296: iushr
    //   8297: iconst_1
    //   8298: iand
    //   8299: ior
    //   8300: istore #22
    //   8302: iload #23
    //   8304: iload #22
    //   8306: ixor
    //   8307: ldc -1431655766
    //   8309: iand
    //   8310: istore #21
    //   8312: iload #23
    //   8314: iload #21
    //   8316: ixor
    //   8317: istore #23
    //   8319: iload #22
    //   8321: iload #21
    //   8323: ixor
    //   8324: istore #22
    //   8326: iload #23
    //   8328: iconst_1
    //   8329: ishl
    //   8330: iload #23
    //   8332: bipush #31
    //   8334: iushr
    //   8335: iconst_1
    //   8336: iand
    //   8337: ior
    //   8338: istore #23
    //   8340: iconst_0
    //   8341: istore #24
    //   8343: iload #24
    //   8345: bipush #8
    //   8347: if_icmpge -> 8685
    //   8350: iload #22
    //   8352: bipush #28
    //   8354: ishl
    //   8355: iload #22
    //   8357: iconst_4
    //   8358: iushr
    //   8359: ior
    //   8360: istore #21
    //   8362: iload #21
    //   8364: aload #5
    //   8366: iload #25
    //   8368: iinc #25, 1
    //   8371: iaload
    //   8372: ixor
    //   8373: istore #21
    //   8375: aload #12
    //   8377: iload #21
    //   8379: bipush #63
    //   8381: iand
    //   8382: iaload
    //   8383: istore #20
    //   8385: iload #20
    //   8387: aload #10
    //   8389: iload #21
    //   8391: bipush #8
    //   8393: iushr
    //   8394: bipush #63
    //   8396: iand
    //   8397: iaload
    //   8398: ior
    //   8399: istore #20
    //   8401: iload #20
    //   8403: aload #8
    //   8405: iload #21
    //   8407: bipush #16
    //   8409: iushr
    //   8410: bipush #63
    //   8412: iand
    //   8413: iaload
    //   8414: ior
    //   8415: istore #20
    //   8417: iload #20
    //   8419: aload #6
    //   8421: iload #21
    //   8423: bipush #24
    //   8425: iushr
    //   8426: bipush #63
    //   8428: iand
    //   8429: iaload
    //   8430: ior
    //   8431: istore #20
    //   8433: iload #22
    //   8435: aload #5
    //   8437: iload #25
    //   8439: iinc #25, 1
    //   8442: iaload
    //   8443: ixor
    //   8444: istore #21
    //   8446: iload #20
    //   8448: aload #13
    //   8450: iload #21
    //   8452: bipush #63
    //   8454: iand
    //   8455: iaload
    //   8456: ior
    //   8457: istore #20
    //   8459: iload #20
    //   8461: aload #11
    //   8463: iload #21
    //   8465: bipush #8
    //   8467: iushr
    //   8468: bipush #63
    //   8470: iand
    //   8471: iaload
    //   8472: ior
    //   8473: istore #20
    //   8475: iload #20
    //   8477: aload #9
    //   8479: iload #21
    //   8481: bipush #16
    //   8483: iushr
    //   8484: bipush #63
    //   8486: iand
    //   8487: iaload
    //   8488: ior
    //   8489: istore #20
    //   8491: iload #20
    //   8493: aload #7
    //   8495: iload #21
    //   8497: bipush #24
    //   8499: iushr
    //   8500: bipush #63
    //   8502: iand
    //   8503: iaload
    //   8504: ior
    //   8505: istore #20
    //   8507: iload #23
    //   8509: iload #20
    //   8511: ixor
    //   8512: istore #23
    //   8514: iload #23
    //   8516: bipush #28
    //   8518: ishl
    //   8519: iload #23
    //   8521: iconst_4
    //   8522: iushr
    //   8523: ior
    //   8524: istore #21
    //   8526: iload #21
    //   8528: aload #5
    //   8530: iload #25
    //   8532: iinc #25, 1
    //   8535: iaload
    //   8536: ixor
    //   8537: istore #21
    //   8539: aload #12
    //   8541: iload #21
    //   8543: bipush #63
    //   8545: iand
    //   8546: iaload
    //   8547: istore #20
    //   8549: iload #20
    //   8551: aload #10
    //   8553: iload #21
    //   8555: bipush #8
    //   8557: iushr
    //   8558: bipush #63
    //   8560: iand
    //   8561: iaload
    //   8562: ior
    //   8563: istore #20
    //   8565: iload #20
    //   8567: aload #8
    //   8569: iload #21
    //   8571: bipush #16
    //   8573: iushr
    //   8574: bipush #63
    //   8576: iand
    //   8577: iaload
    //   8578: ior
    //   8579: istore #20
    //   8581: iload #20
    //   8583: aload #6
    //   8585: iload #21
    //   8587: bipush #24
    //   8589: iushr
    //   8590: bipush #63
    //   8592: iand
    //   8593: iaload
    //   8594: ior
    //   8595: istore #20
    //   8597: iload #23
    //   8599: aload #5
    //   8601: iload #25
    //   8603: iinc #25, 1
    //   8606: iaload
    //   8607: ixor
    //   8608: istore #21
    //   8610: iload #20
    //   8612: aload #13
    //   8614: iload #21
    //   8616: bipush #63
    //   8618: iand
    //   8619: iaload
    //   8620: ior
    //   8621: istore #20
    //   8623: iload #20
    //   8625: aload #11
    //   8627: iload #21
    //   8629: bipush #8
    //   8631: iushr
    //   8632: bipush #63
    //   8634: iand
    //   8635: iaload
    //   8636: ior
    //   8637: istore #20
    //   8639: iload #20
    //   8641: aload #9
    //   8643: iload #21
    //   8645: bipush #16
    //   8647: iushr
    //   8648: bipush #63
    //   8650: iand
    //   8651: iaload
    //   8652: ior
    //   8653: istore #20
    //   8655: iload #20
    //   8657: aload #7
    //   8659: iload #21
    //   8661: bipush #24
    //   8663: iushr
    //   8664: bipush #63
    //   8666: iand
    //   8667: iaload
    //   8668: ior
    //   8669: istore #20
    //   8671: iload #22
    //   8673: iload #20
    //   8675: ixor
    //   8676: istore #22
    //   8678: iinc #24, 1
    //   8681: iload_2
    //   8682: ifeq -> 8343
    //   8685: iload #22
    //   8687: bipush #31
    //   8689: ishl
    //   8690: iload #22
    //   8692: iconst_1
    //   8693: iushr
    //   8694: ior
    //   8695: istore #22
    //   8697: iload #23
    //   8699: iload #22
    //   8701: ixor
    //   8702: ldc -1431655766
    //   8704: iand
    //   8705: istore #21
    //   8707: iload #23
    //   8709: iload #21
    //   8711: ixor
    //   8712: istore #23
    //   8714: iload #22
    //   8716: iload #21
    //   8718: ixor
    //   8719: istore #22
    //   8721: iload #23
    //   8723: bipush #31
    //   8725: ishl
    //   8726: iload #23
    //   8728: iconst_1
    //   8729: iushr
    //   8730: ior
    //   8731: istore #23
    //   8733: iload #23
    //   8735: bipush #8
    //   8737: iushr
    //   8738: iload #22
    //   8740: ixor
    //   8741: ldc 16711935
    //   8743: iand
    //   8744: istore #21
    //   8746: iload #22
    //   8748: iload #21
    //   8750: ixor
    //   8751: istore #22
    //   8753: iload #23
    //   8755: iload #21
    //   8757: bipush #8
    //   8759: ishl
    //   8760: ixor
    //   8761: istore #23
    //   8763: iload #23
    //   8765: iconst_2
    //   8766: iushr
    //   8767: iload #22
    //   8769: ixor
    //   8770: ldc 858993459
    //   8772: iand
    //   8773: istore #21
    //   8775: iload #22
    //   8777: iload #21
    //   8779: ixor
    //   8780: istore #22
    //   8782: iload #23
    //   8784: iload #21
    //   8786: iconst_2
    //   8787: ishl
    //   8788: ixor
    //   8789: istore #23
    //   8791: iload #22
    //   8793: bipush #16
    //   8795: iushr
    //   8796: iload #23
    //   8798: ixor
    //   8799: ldc 65535
    //   8801: iand
    //   8802: istore #21
    //   8804: iload #23
    //   8806: iload #21
    //   8808: ixor
    //   8809: istore #23
    //   8811: iload #22
    //   8813: iload #21
    //   8815: bipush #16
    //   8817: ishl
    //   8818: ixor
    //   8819: istore #22
    //   8821: iload #22
    //   8823: iconst_4
    //   8824: iushr
    //   8825: iload #23
    //   8827: ixor
    //   8828: ldc 252645135
    //   8830: iand
    //   8831: istore #21
    //   8833: iload #23
    //   8835: iload #21
    //   8837: ixor
    //   8838: istore #23
    //   8840: iload #22
    //   8842: iload #21
    //   8844: iconst_4
    //   8845: ishl
    //   8846: ixor
    //   8847: istore #22
    //   8849: aload #15
    //   8851: iconst_0
    //   8852: iload #22
    //   8854: iastore
    //   8855: aload #15
    //   8857: iconst_1
    //   8858: iload #23
    //   8860: iastore
    //   8861: iload #18
    //   8863: bipush #8
    //   8865: imul
    //   8866: istore #26
    //   8868: iconst_0
    //   8869: istore #27
    //   8871: iload #27
    //   8873: iconst_2
    //   8874: if_icmpge -> 8963
    //   8877: aload #16
    //   8879: iload #26
    //   8881: iload #27
    //   8883: iconst_4
    //   8884: imul
    //   8885: iadd
    //   8886: aload #15
    //   8888: iload #27
    //   8890: iaload
    //   8891: bipush #24
    //   8893: iushr
    //   8894: i2b
    //   8895: bastore
    //   8896: aload #16
    //   8898: iload #26
    //   8900: iload #27
    //   8902: iconst_4
    //   8903: imul
    //   8904: iadd
    //   8905: iconst_1
    //   8906: iadd
    //   8907: aload #15
    //   8909: iload #27
    //   8911: iaload
    //   8912: bipush #16
    //   8914: iushr
    //   8915: i2b
    //   8916: bastore
    //   8917: aload #16
    //   8919: iload #26
    //   8921: iload #27
    //   8923: iconst_4
    //   8924: imul
    //   8925: iadd
    //   8926: iconst_2
    //   8927: iadd
    //   8928: aload #15
    //   8930: iload #27
    //   8932: iaload
    //   8933: bipush #8
    //   8935: iushr
    //   8936: i2b
    //   8937: bastore
    //   8938: aload #16
    //   8940: iload #26
    //   8942: iload #27
    //   8944: iconst_4
    //   8945: imul
    //   8946: iadd
    //   8947: iconst_3
    //   8948: iadd
    //   8949: aload #15
    //   8951: iload #27
    //   8953: iaload
    //   8954: i2b
    //   8955: bastore
    //   8956: iinc #27, 1
    //   8959: iload_2
    //   8960: ifeq -> 8871
    //   8963: iinc #18, 1
    //   8966: iload_2
    //   8967: ifeq -> 8052
    //   8970: aload #16
    //   8972: aload #16
    //   8974: arraylength
    //   8975: iconst_1
    //   8976: isub
    //   8977: baload
    //   8978: istore #18
    //   8980: aload #16
    //   8982: arraylength
    //   8983: iload #18
    //   8985: isub
    //   8986: newarray byte
    //   8988: astore #4
    //   8990: aload #16
    //   8992: arraylength
    //   8993: aload #4
    //   8995: arraylength
    //   8996: if_icmpge -> 9020
    //   8999: new java/lang/Exception
    //   9002: dup
    //   9003: sipush #-11449
    //   9006: sipush #-9595
    //   9009: invokestatic a : (II)Ljava/lang/String;
    //   9012: invokespecial <init> : (Ljava/lang/String;)V
    //   9015: athrow
    //   9016: invokestatic a : (Ljava/lang/Throwable;)Ljava/lang/Throwable;
    //   9019: athrow
    //   9020: iconst_0
    //   9021: istore #19
    //   9023: iload #19
    //   9025: aload #4
    //   9027: arraylength
    //   9028: if_icmpge -> 9048
    //   9031: aload #4
    //   9033: iload #19
    //   9035: aload #16
    //   9037: iload #19
    //   9039: baload
    //   9040: bastore
    //   9041: iinc #19, 1
    //   9044: iload_2
    //   9045: ifeq -> 9023
    //   9048: getstatic burp/Zk5k.Zx : Ljava/lang/String;
    //   9051: getstatic burp/Zek4.ZR : Ljava/lang/Object;
    //   9054: checkcast java/math/BigInteger
    //   9057: invokevirtual intValue : ()I
    //   9060: bipush #32
    //   9062: irem
    //   9063: invokestatic abs : (I)I
    //   9066: invokevirtual charAt : (I)C
    //   9069: getstatic burp/Zmtr.Zd : Ljava/lang/String;
    //   9072: getstatic burp/Zek4.ZR : Ljava/lang/Object;
    //   9075: checkcast java/math/BigInteger
    //   9078: invokevirtual intValue : ()I
    //   9081: bipush #32
    //   9083: irem
    //   9084: invokestatic abs : (I)I
    //   9087: invokevirtual charAt : (I)C
    //   9090: if_icmpgt -> 9197
    //   9093: getstatic burp/Zlo0.ZD : Ljava/lang/String;
    //   9096: getstatic burp/Zxju.ZN : Ljava/lang/Object;
    //   9099: checkcast java/math/BigInteger
    //   9102: invokevirtual intValue : ()I
    //   9105: bipush #32
    //   9107: irem
    //   9108: invokestatic abs : (I)I
    //   9111: invokevirtual charAt : (I)C
    //   9114: getstatic burp/Zzi_.ZG : Ljava/lang/String;
    //   9117: getstatic burp/Zxy6.Zd : Ljava/lang/Object;
    //   9120: checkcast java/math/BigInteger
    //   9123: invokevirtual intValue : ()I
    //   9126: bipush #32
    //   9128: irem
    //   9129: invokestatic abs : (I)I
    //   9132: invokevirtual charAt : (I)C
    //   9135: if_icmpgt -> 9197
    //   9138: goto -> 9145
    //   9141: invokestatic a : (Ljava/lang/Throwable;)Ljava/lang/Throwable;
    //   9144: athrow
    //   9145: getstatic burp/Ze1k.ZI : Ljava/lang/String;
    //   9148: getstatic burp/Zrkd.ZO : Ljava/lang/Object;
    //   9151: checkcast java/math/BigInteger
    //   9154: invokevirtual intValue : ()I
    //   9157: bipush #32
    //   9159: irem
    //   9160: invokestatic abs : (I)I
    //   9163: invokevirtual charAt : (I)C
    //   9166: getstatic burp/Zssc.ZR : Ljava/lang/String;
    //   9169: getstatic burp/Zxn9.ZN : Ljava/lang/Object;
    //   9172: checkcast java/math/BigInteger
    //   9175: invokevirtual intValue : ()I
    //   9178: bipush #32
    //   9180: irem
    //   9181: invokestatic abs : (I)I
    //   9184: invokevirtual charAt : (I)C
    //   9187: if_icmpgt -> 9205
    //   9190: goto -> 9197
    //   9193: invokestatic a : (Ljava/lang/Throwable;)Ljava/lang/Throwable;
    //   9196: athrow
    //   9197: iconst_1
    //   9198: goto -> 9206
    //   9201: invokestatic a : (Ljava/lang/Throwable;)Ljava/lang/Throwable;
    //   9204: athrow
    //   9205: iconst_0
    //   9206: ireturn
    //   9207: astore_3
    //   9208: new java/lang/Exception
    //   9211: dup
    //   9212: aload_3
    //   9213: invokevirtual getMessage : ()Ljava/lang/String;
    //   9216: invokespecial <init> : (Ljava/lang/String;)V
    //   9219: athrow
    // Exception table:
    //   from	to	target	type
    //   4	9206	9207	java/lang/Throwable
    //   4413	4427	4427	java/lang/Throwable
    //   4438	4451	4454	java/lang/Throwable
    //   4443	4466	4469	java/lang/Throwable
    //   4458	4484	4487	java/lang/Throwable
    //   4473	4514	4517	java/lang/Throwable
    //   4577	4604	4607	java/lang/Throwable
    //   4594	4625	4628	java/lang/Throwable
    //   4611	4655	4658	java/lang/Throwable
    //   4632	4666	4666	java/lang/Throwable
    //   4677	4693	4696	java/lang/Throwable
    //   8002	8027	8027	java/lang/Throwable
    //   8990	9016	9016	java/lang/Throwable
    //   9048	9138	9141	java/lang/Throwable
    //   9093	9190	9193	java/lang/Throwable
    //   9145	9201	9201	java/lang/Throwable
  }
  
  static void Zd(Object paramObject) {
    Zzht.Zv = a(-11451, 12411);
    Zzht.Zb = new BigInteger(a(-11456, 6886));
    boolean bool = Zt2e.ZK();
    try {
      try {
        if (Ze6w.ZY.charAt(Math.abs(((BigInteger)Zkeb.ZH).intValue() % 32)) > Zl_f.ZF.charAt(Math.abs(((BigInteger)Ztgv.Zg).intValue() % 32))) {
          try {
            Zbx5.Zh(Class.forName(a(-11453, 23578)));
            if (bool)
              Zry0.ZO(Class.forName(a(-11450, 16343))); 
          } catch (Throwable throwable) {
            throw a(null);
          } 
          return;
        } 
      } catch (Throwable throwable) {
        throw a(null);
      } 
      Zry0.ZO(Class.forName(a(-11450, 16343)));
    } catch (Throwable throwable) {}
  }
  
  static void ZM(Object[] paramArrayOfObject, Object paramObject) throws Throwable {}
  
  static {
    // Byte code:
    //   0: bipush #10
    //   2: anewarray java/lang/String
    //   5: astore #5
    //   7: iconst_0
    //   8: istore_3
    //   9: ldc ']CcX9Kn,Mt&0B\\b0c,/P.<eyGc\\tH:*{BP;dBO`lu8\\t}" t\\tw X'og3m>J'%Z+jy~:0-fb5d5TLA%\\t(K'
    //   11: dup
    //   12: astore_2
    //   13: invokevirtual length : ()I
    //   16: istore #4
    //   18: bipush #19
    //   20: istore_1
    //   21: iconst_m1
    //   22: istore_0
    //   23: bipush #123
    //   25: iinc #0, 1
    //   28: aload_2
    //   29: iload_0
    //   30: dup
    //   31: iload_1
    //   32: iadd
    //   33: invokevirtual substring : (II)Ljava/lang/String;
    //   36: iconst_m1
    //   37: goto -> 143
    //   40: aload #5
    //   42: swap
    //   43: iload_3
    //   44: iinc #3, 1
    //   47: swap
    //   48: aastore
    //   49: iload_0
    //   50: iload_1
    //   51: iadd
    //   52: dup
    //   53: istore_0
    //   54: iload #4
    //   56: if_icmpge -> 68
    //   59: aload_2
    //   60: iload_0
    //   61: invokevirtual charAt : (I)C
    //   64: istore_1
    //   65: goto -> 23
    //   68: ldc 'qu(&_Wq_#{A,7)i\\t8U4@'
    //   70: dup
    //   71: astore_2
    //   72: invokevirtual length : ()I
    //   75: istore #4
    //   77: bipush #32
    //   79: istore_1
    //   80: iconst_m1
    //   81: istore_0
    //   82: bipush #57
    //   84: iinc #0, 1
    //   87: aload_2
    //   88: iload_0
    //   89: dup
    //   90: iload_1
    //   91: iadd
    //   92: invokevirtual substring : (II)Ljava/lang/String;
    //   95: iconst_0
    //   96: goto -> 143
    //   99: aload #5
    //   101: swap
    //   102: iload_3
    //   103: iinc #3, 1
    //   106: swap
    //   107: aastore
    //   108: iload_0
    //   109: iload_1
    //   110: iadd
    //   111: dup
    //   112: istore_0
    //   113: iload #4
    //   115: if_icmpge -> 127
    //   118: aload_2
    //   119: iload_0
    //   120: invokevirtual charAt : (I)C
    //   123: istore_1
    //   124: goto -> 82
    //   127: aload #5
    //   129: putstatic burp/Zm63.a : [Ljava/lang/String;
    //   132: bipush #10
    //   134: anewarray java/lang/String
    //   137: putstatic burp/Zm63.b : [Ljava/lang/String;
    //   140: goto -> 300
    //   143: dup_x2
    //   144: pop
    //   145: invokevirtual toCharArray : ()[C
    //   148: dup_x1
    //   149: arraylength
    //   150: dup_x2
    //   151: pop
    //   152: iconst_0
    //   153: istore #6
    //   155: dup2_x1
    //   156: pop2
    //   157: dup_x2
    //   158: iconst_1
    //   159: if_icmpgt -> 260
    //   162: dup2
    //   163: swap
    //   164: iload #6
    //   166: dup2_x1
    //   167: caload
    //   168: swap
    //   169: iload #6
    //   171: bipush #7
    //   173: irem
    //   174: tableswitch default -> 242, 0 -> 212, 1 -> 217, 2 -> 222, 3 -> 227, 4 -> 232, 5 -> 237
    //   212: bipush #22
    //   214: goto -> 244
    //   217: bipush #64
    //   219: goto -> 244
    //   222: bipush #7
    //   224: goto -> 244
    //   227: bipush #28
    //   229: goto -> 244
    //   232: bipush #114
    //   234: goto -> 244
    //   237: bipush #45
    //   239: goto -> 244
    //   242: bipush #79
    //   244: ixor
    //   245: ixor
    //   246: i2c
    //   247: castore
    //   248: iinc #6, 1
    //   251: dup
    //   252: ifne -> 260
    //   255: dup2
    //   256: dup_x1
    //   257: goto -> 166
    //   260: dup2_x1
    //   261: pop2
    //   262: dup_x2
    //   263: iload #6
    //   265: if_icmpgt -> 162
    //   268: pop
    //   269: new java/lang/String
    //   272: dup_x1
    //   273: swap
    //   274: invokespecial <init> : ([C)V
    //   277: invokevirtual intern : ()Ljava/lang/String;
    //   280: swap
    //   281: pop
    //   282: swap
    //   283: tableswitch default -> 40, 0 -> 99
    //   300: new java/math/BigInteger
    //   303: dup
    //   304: iconst_1
    //   305: bipush #32
    //   307: newarray byte
    //   309: dup
    //   310: iconst_0
    //   311: bipush #70
    //   313: bastore
    //   314: dup
    //   315: iconst_1
    //   316: iconst_4
    //   317: bastore
    //   318: dup
    //   319: iconst_2
    //   320: bipush #6
    //   322: bastore
    //   323: dup
    //   324: iconst_3
    //   325: bipush #-114
    //   327: bastore
    //   328: dup
    //   329: iconst_4
    //   330: bipush #33
    //   332: bastore
    //   333: dup
    //   334: iconst_5
    //   335: bipush #75
    //   337: bastore
    //   338: dup
    //   339: bipush #6
    //   341: bipush #45
    //   343: bastore
    //   344: dup
    //   345: bipush #7
    //   347: iconst_3
    //   348: bastore
    //   349: dup
    //   350: bipush #8
    //   352: bipush #35
    //   354: bastore
    //   355: dup
    //   356: bipush #9
    //   358: bipush #-41
    //   360: bastore
    //   361: dup
    //   362: bipush #10
    //   364: bipush #-55
    //   366: bastore
    //   367: dup
    //   368: bipush #11
    //   370: bipush #-21
    //   372: bastore
    //   373: dup
    //   374: bipush #12
    //   376: bipush #90
    //   378: bastore
    //   379: dup
    //   380: bipush #13
    //   382: bipush #109
    //   384: bastore
    //   385: dup
    //   386: bipush #14
    //   388: bipush #-100
    //   390: bastore
    //   391: dup
    //   392: bipush #15
    //   394: bipush #-78
    //   396: bastore
    //   397: dup
    //   398: bipush #16
    //   400: bipush #35
    //   402: bastore
    //   403: dup
    //   404: bipush #17
    //   406: bipush #123
    //   408: bastore
    //   409: dup
    //   410: bipush #18
    //   412: bipush #90
    //   414: bastore
    //   415: dup
    //   416: bipush #19
    //   418: bipush #75
    //   420: bastore
    //   421: dup
    //   422: bipush #20
    //   424: bipush #104
    //   426: bastore
    //   427: dup
    //   428: bipush #21
    //   430: bipush #-73
    //   432: bastore
    //   433: dup
    //   434: bipush #22
    //   436: bipush #-24
    //   438: bastore
    //   439: dup
    //   440: bipush #23
    //   442: bipush #121
    //   444: bastore
    //   445: dup
    //   446: bipush #24
    //   448: bipush #-9
    //   450: bastore
    //   451: dup
    //   452: bipush #25
    //   454: bipush #-128
    //   456: bastore
    //   457: dup
    //   458: bipush #26
    //   460: bipush #-120
    //   462: bastore
    //   463: dup
    //   464: bipush #27
    //   466: bipush #90
    //   468: bastore
    //   469: dup
    //   470: bipush #28
    //   472: bipush #-36
    //   474: bastore
    //   475: dup
    //   476: bipush #29
    //   478: bipush #-35
    //   480: bastore
    //   481: dup
    //   482: bipush #30
    //   484: iconst_1
    //   485: bastore
    //   486: dup
    //   487: bipush #31
    //   489: bipush #-36
    //   491: bastore
    //   492: invokespecial <init> : (I[B)V
    //   495: putstatic burp/Zm63.ZT : Ljava/lang/Object;
    //   498: sipush #-11447
    //   501: sipush #17261
    //   504: invokestatic a : (II)Ljava/lang/String;
    //   507: putstatic burp/Zm63.Zs : Ljava/lang/String;
    //   510: return
  }
  
  private static Throwable a(Throwable paramThrowable) {
    return paramThrowable;
  }
  
  private static String a(int paramInt1, int paramInt2) {
    int i = (paramInt1 ^ 0xFFFFD341) & 0xFFFF;
    if (b[i] == null) {
      char[] arrayOfChar = a[i].toCharArray();
      switch (arrayOfChar[0] & 0xFF) {
        case 0:
        
        case 1:
        
        case 2:
        
        case 3:
        
        case 4:
        
        case 5:
        
        case 6:
        
        case 7:
        
        case 8:
        
        case 9:
        
        case 10:
        
        case 11:
        
        case 12:
        
        case 13:
        
        case 14:
        
        case 15:
        
        case 16:
        
        case 17:
        
        case 18:
        
        case 19:
        
        case 20:
        
        case 21:
        
        case 22:
        
        case 23:
        
        case 24:
        
        case 25:
        
        case 26:
        
        case 27:
        
        case 28:
        
        case 29:
        
        case 30:
        
        case 31:
        
        case 32:
        
        case 33:
        
        case 34:
        
        case 35:
        
        case 36:
        
        case 37:
        
        case 38:
        
        case 39:
        
        case 40:
        
        case 41:
        
        case 42:
        
        case 43:
        
        case 44:
        
        case 45:
        
        case 46:
        
        case 47:
        
        case 48:
        
        case 49:
        
        case 50:
        
        case 51:
        
        case 52:
        
        case 53:
        
        case 54:
        
        case 55:
        
        case 56:
        
        case 57:
        
        case 58:
        
        case 59:
        
        case 60:
        
        case 61:
        
        case 62:
        
        case 63:
        
        case 64:
        
        case 65:
        
        case 66:
        
        case 67:
        
        case 68:
        
        case 69:
        
        case 70:
        
        case 71:
        
        case 72:
        
        case 73:
        
        case 74:
        
        case 75:
        
        case 76:
        
        case 77:
        
        case 78:
        
        case 79:
        
        case 80:
        
        case 81:
        
        case 82:
        
        case 83:
        
        case 84:
        
        case 85:
        
        case 86:
        
        case 87:
        
        case 88:
        
        case 89:
        
        case 90:
        
        case 91:
        
        case 92:
        
        case 93:
        
        case 94:
        
        case 95:
        
        case 96:
        
        case 97:
        
        case 98:
        
        case 99:
        
        case 100:
        
        case 101:
        
        case 102:
        
        case 103:
        
        case 104:
        
        case 105:
        
        case 106:
        
        case 107:
        
        case 108:
        
        case 109:
        
        case 110:
        
        case 111:
        
        case 112:
        
        case 113:
        
        case 114:
        
        case 115:
        
        case 116:
        
        case 117:
        
        case 118:
        
        case 119:
        
        case 120:
        
        case 121:
        
        case 122:
        
        case 123:
        
        case 124:
        
        case 125:
        
        case 126:
        
        case 127:
        
        case 128:
        
        case 129:
        
        case 130:
        
        case 131:
        
        case 132:
        
        case 133:
        
        case 134:
        
        case 135:
        
        case 136:
        
        case 137:
        
        case 138:
        
        case 139:
        
        case 140:
        
        case 141:
        
        case 142:
        
        case 143:
        
        case 144:
        
        case 145:
        
        case 146:
        
        case 147:
        
        case 148:
        
        case 149:
        
        case 150:
        
        case 151:
        
        case 152:
        
        case 153:
        
        case 154:
        
        case 155:
        
        case 156:
        
        case 157:
        
        case 158:
        
        case 159:
        
        case 160:
        
        case 161:
        
        case 162:
        
        case 163:
        
        case 164:
        
        case 165:
        
        case 166:
        
        case 167:
        
        case 168:
        
        case 169:
        
        case 170:
        
        case 171:
        
        case 172:
        
        case 173:
        
        case 174:
        
        case 175:
        
        case 176:
        
        case 177:
        
        case 178:
        
        case 179:
        
        case 180:
        
        case 181:
        
        case 182:
        
        case 183:
        
        case 184:
        
        case 185:
        
        case 186:
        
        case 187:
        
        case 188:
        
        case 189:
        
        case 190:
        
        case 191:
        
        case 192:
        
        case 193:
        
        case 194:
        
        case 195:
        
        case 196:
        
        case 197:
        
        case 198:
        
        case 199:
        
        case 200:
        
        case 201:
        
        case 202:
        
        case 203:
        
        case 204:
        
        case 205:
        
        case 206:
        
        case 207:
        
        case 208:
        
        case 209:
        
        case 210:
        
        case 211:
        
        case 212:
        
        case 213:
        
        case 214:
        
        case 215:
        
        case 216:
        
        case 217:
        
        case 218:
        
        case 219:
        
        case 220:
        
        case 221:
        
        case 222:
        
        case 223:
        
        case 224:
        
        case 225:
        
        case 226:
        
        case 227:
        
        case 228:
        
        case 229:
        
        case 230:
        
        case 231:
        
        case 232:
        
        case 233:
        
        case 234:
        
        case 235:
        
        case 236:
        
        case 237:
        
        case 238:
        
        case 239:
        
        case 240:
        
        case 241:
        
        case 242:
        
        case 243:
        
        case 244:
        
        case 245:
        
        case 246:
        
        case 247:
        
        case 248:
        
        case 249:
        
        case 250:
        
        case 251:
        
        case 252:
        
        case 253:
        
        case 254:
        
        default:
          break;
      } 
      char c = '';
      int j = (paramInt2 & 0xFF) - c;
      if (j < 0)
        j += 256; 
      int k = ((paramInt2 & 0xFFFF) >>> 8) - c;
      if (k < 0)
        k += 256; 
      for (byte b = 0; b < arrayOfChar.length; b++) {
        int m = b % 2;
        if (m == 0) {
          arrayOfChar[b] = (char)(arrayOfChar[b] ^ j);
          j = ((j >>> 3 | j << 5) ^ arrayOfChar[b]) & 0xFF;
        } else {
          arrayOfChar[b] = (char)(arrayOfChar[b] ^ k);
          k = ((k >>> 3 | k << 5) ^ arrayOfChar[b]) & 0xFF;
        } 
      } 
      b[i] = (new String(arrayOfChar)).intern();
    } 
    return b[i];
  }
}


/* Location:              C:\Program Files\BurpSuitePro\burpsuite_pro.jar!\burp\Zm63.class
 * Java compiler version: 21 (65.0)
 * JD-Core Version:       1.1.3
 */