package burp;

import java.math.BigInteger;

class Zm69 extends ClassLoader {
  static Object Zg;
  
  static String ZE;
  
  private static final String[] a;
  
  private static final String[] b;
  
  static void ZP(Object paramObject) {
    Zm83.Zq = a(2844, -31610);
    Zm83.Zl = new BigInteger(a(2847, -26595));
    boolean bool = Zt2e.ZK();
    try {
      try {
        if (Zb3l.Zz.charAt(Math.abs(((BigInteger)Ztq4.ZA).intValue() % 32)) > Zsjc.ZO.charAt(Math.abs(((BigInteger)Zz66.ZQ).intValue() % 32))) {
          try {
            Zld5.Zt(Class.forName(a(2833, -31253)));
            if (bool)
              Zzo5.ZS(Class.forName(a(2846, -31489))); 
          } catch (Throwable throwable) {
            throw a(null);
          } 
          return;
        } 
      } catch (Throwable throwable) {
        throw a(null);
      } 
      Zzo5.ZS(Class.forName(a(2846, -31489)));
    } catch (Throwable throwable) {}
  }
  
  static boolean Zb(Object[] paramArrayOfObject, Object paramObject) throws Throwable {
    // Byte code:
    //   0: invokestatic ZK : ()Z
    //   3: istore_2
    //   4: getstatic burp/Zb3r.ZI : Ljava/lang/Object;
    //   7: checkcast java/math/BigInteger
    //   10: invokevirtual toByteArray : ()[B
    //   13: astore_3
    //   14: new java/lang/StringBuilder
    //   17: dup
    //   18: invokespecial <init> : ()V
    //   21: astore #5
    //   23: aload #5
    //   25: sipush #2827
    //   28: sipush #20165
    //   31: invokestatic a : (II)Ljava/lang/String;
    //   34: invokevirtual append : (Ljava/lang/String;)Ljava/lang/StringBuilder;
    //   37: pop
    //   38: aload_3
    //   39: astore #6
    //   41: aload #6
    //   43: arraylength
    //   44: istore #7
    //   46: iconst_0
    //   47: istore #8
    //   49: iload #8
    //   51: iload #7
    //   53: if_icmpge -> 79
    //   56: aload #6
    //   58: iload #8
    //   60: baload
    //   61: istore #9
    //   63: aload #5
    //   65: iload #9
    //   67: i2c
    //   68: invokevirtual append : (C)Ljava/lang/StringBuilder;
    //   71: pop
    //   72: iinc #8, 1
    //   75: iload_2
    //   76: ifeq -> 49
    //   79: aload #5
    //   81: sipush #2830
    //   84: sipush #-4788
    //   87: invokestatic a : (II)Ljava/lang/String;
    //   90: ldc ''
    //   92: invokestatic getProperty : (Ljava/lang/String;Ljava/lang/String;)Ljava/lang/String;
    //   95: invokevirtual toLowerCase : ()Ljava/lang/String;
    //   98: invokevirtual append : (Ljava/lang/String;)Ljava/lang/StringBuilder;
    //   101: pop
    //   102: aload #5
    //   104: sipush #2838
    //   107: sipush #-29950
    //   110: invokestatic a : (II)Ljava/lang/String;
    //   113: ldc ''
    //   115: invokestatic getProperty : (Ljava/lang/String;Ljava/lang/String;)Ljava/lang/String;
    //   118: invokevirtual toLowerCase : ()Ljava/lang/String;
    //   121: invokevirtual append : (Ljava/lang/String;)Ljava/lang/StringBuilder;
    //   124: pop
    //   125: aload #5
    //   127: invokevirtual toString : ()Ljava/lang/String;
    //   130: invokevirtual getBytes : ()[B
    //   133: astore #4
    //   135: aload #4
    //   137: astore_3
    //   138: aload_3
    //   139: arraylength
    //   140: bipush #8
    //   142: iadd
    //   143: bipush #6
    //   145: ishr
    //   146: iconst_1
    //   147: iadd
    //   148: bipush #16
    //   150: imul
    //   151: newarray int
    //   153: astore #5
    //   155: iconst_0
    //   156: istore #6
    //   158: iload #6
    //   160: aload_3
    //   161: arraylength
    //   162: if_icmpge -> 205
    //   165: aload_3
    //   166: iload #6
    //   168: baload
    //   169: sipush #255
    //   172: iand
    //   173: istore #7
    //   175: aload #5
    //   177: iload #6
    //   179: iconst_2
    //   180: ishr
    //   181: dup2
    //   182: iaload
    //   183: iload #7
    //   185: bipush #24
    //   187: iload #6
    //   189: iconst_4
    //   190: irem
    //   191: bipush #8
    //   193: imul
    //   194: isub
    //   195: ishl
    //   196: ior
    //   197: iastore
    //   198: iinc #6, 1
    //   201: iload_2
    //   202: ifeq -> 158
    //   205: aload #5
    //   207: iload #6
    //   209: iconst_2
    //   210: ishr
    //   211: dup2
    //   212: iaload
    //   213: sipush #128
    //   216: bipush #24
    //   218: iload #6
    //   220: iconst_4
    //   221: irem
    //   222: bipush #8
    //   224: imul
    //   225: isub
    //   226: ishl
    //   227: ior
    //   228: iastore
    //   229: aload #5
    //   231: aload #5
    //   233: arraylength
    //   234: iconst_1
    //   235: isub
    //   236: aload_3
    //   237: arraylength
    //   238: bipush #8
    //   240: imul
    //   241: iastore
    //   242: bipush #80
    //   244: newarray int
    //   246: astore #7
    //   248: ldc 1732584193
    //   250: istore #8
    //   252: ldc -271733879
    //   254: istore #9
    //   256: ldc -1732584194
    //   258: istore #10
    //   260: ldc 271733878
    //   262: istore #11
    //   264: ldc -1009589776
    //   266: istore #12
    //   268: iconst_0
    //   269: istore #6
    //   271: iload #6
    //   273: aload #5
    //   275: arraylength
    //   276: if_icmpge -> 598
    //   279: iload #8
    //   281: istore #13
    //   283: iload #9
    //   285: istore #14
    //   287: iload #10
    //   289: istore #15
    //   291: iload #11
    //   293: istore #16
    //   295: iload #12
    //   297: istore #17
    //   299: iconst_0
    //   300: istore #18
    //   302: iload #18
    //   304: bipush #80
    //   306: if_icmpge -> 556
    //   309: iload #18
    //   311: bipush #16
    //   313: if_icmpge -> 340
    //   316: aload #7
    //   318: iload #18
    //   320: aload #5
    //   322: iload #6
    //   324: iload #18
    //   326: iadd
    //   327: iaload
    //   328: iastore
    //   329: iload_2
    //   330: ifeq -> 395
    //   333: goto -> 340
    //   336: invokestatic a : (Ljava/lang/Throwable;)Ljava/lang/Throwable;
    //   339: athrow
    //   340: aload #7
    //   342: iload #18
    //   344: iconst_3
    //   345: isub
    //   346: iaload
    //   347: aload #7
    //   349: iload #18
    //   351: bipush #8
    //   353: isub
    //   354: iaload
    //   355: ixor
    //   356: aload #7
    //   358: iload #18
    //   360: bipush #14
    //   362: isub
    //   363: iaload
    //   364: ixor
    //   365: aload #7
    //   367: iload #18
    //   369: bipush #16
    //   371: isub
    //   372: iaload
    //   373: ixor
    //   374: istore #19
    //   376: iload #19
    //   378: iconst_1
    //   379: ishl
    //   380: iload #19
    //   382: bipush #31
    //   384: iushr
    //   385: ior
    //   386: istore #20
    //   388: aload #7
    //   390: iload #18
    //   392: iload #20
    //   394: iastore
    //   395: iload #8
    //   397: iconst_5
    //   398: ishl
    //   399: iload #8
    //   401: bipush #27
    //   403: iushr
    //   404: ior
    //   405: istore #19
    //   407: iload #19
    //   409: iload #12
    //   411: iadd
    //   412: aload #7
    //   414: iload #18
    //   416: iaload
    //   417: iadd
    //   418: iload #18
    //   420: bipush #20
    //   422: if_icmpge -> 448
    //   425: ldc 1518500249
    //   427: iload #9
    //   429: iload #10
    //   431: iand
    //   432: iload #9
    //   434: iconst_m1
    //   435: ixor
    //   436: iload #11
    //   438: iand
    //   439: ior
    //   440: iadd
    //   441: goto -> 518
    //   444: invokestatic a : (Ljava/lang/Throwable;)Ljava/lang/Throwable;
    //   447: athrow
    //   448: iload #18
    //   450: bipush #40
    //   452: if_icmpge -> 473
    //   455: ldc 1859775393
    //   457: iload #9
    //   459: iload #10
    //   461: ixor
    //   462: iload #11
    //   464: ixor
    //   465: iadd
    //   466: goto -> 518
    //   469: invokestatic a : (Ljava/lang/Throwable;)Ljava/lang/Throwable;
    //   472: athrow
    //   473: iload #18
    //   475: bipush #60
    //   477: if_icmpge -> 507
    //   480: ldc -1894007588
    //   482: iload #9
    //   484: iload #10
    //   486: iand
    //   487: iload #9
    //   489: iload #11
    //   491: iand
    //   492: ior
    //   493: iload #10
    //   495: iload #11
    //   497: iand
    //   498: ior
    //   499: iadd
    //   500: goto -> 518
    //   503: invokestatic a : (Ljava/lang/Throwable;)Ljava/lang/Throwable;
    //   506: athrow
    //   507: ldc -899497514
    //   509: iload #9
    //   511: iload #10
    //   513: ixor
    //   514: iload #11
    //   516: ixor
    //   517: iadd
    //   518: iadd
    //   519: istore #20
    //   521: iload #11
    //   523: istore #12
    //   525: iload #10
    //   527: istore #11
    //   529: iload #9
    //   531: bipush #30
    //   533: ishl
    //   534: iload #9
    //   536: iconst_2
    //   537: iushr
    //   538: ior
    //   539: istore #10
    //   541: iload #8
    //   543: istore #9
    //   545: iload #20
    //   547: istore #8
    //   549: iinc #18, 1
    //   552: iload_2
    //   553: ifeq -> 302
    //   556: iload #8
    //   558: iload #13
    //   560: iadd
    //   561: istore #8
    //   563: iload #9
    //   565: iload #14
    //   567: iadd
    //   568: istore #9
    //   570: iload #10
    //   572: iload #15
    //   574: iadd
    //   575: istore #10
    //   577: iload #11
    //   579: iload #16
    //   581: iadd
    //   582: istore #11
    //   584: iload #12
    //   586: iload #17
    //   588: iadd
    //   589: istore #12
    //   591: iinc #6, 16
    //   594: iload_2
    //   595: ifeq -> 271
    //   598: iconst_5
    //   599: newarray int
    //   601: dup
    //   602: iconst_0
    //   603: iload #8
    //   605: iastore
    //   606: dup
    //   607: iconst_1
    //   608: iload #9
    //   610: iastore
    //   611: dup
    //   612: iconst_2
    //   613: iload #10
    //   615: iastore
    //   616: dup
    //   617: iconst_3
    //   618: iload #11
    //   620: iastore
    //   621: dup
    //   622: iconst_4
    //   623: iload #12
    //   625: iastore
    //   626: astore #13
    //   628: bipush #20
    //   630: newarray byte
    //   632: astore #14
    //   634: iconst_0
    //   635: istore #15
    //   637: iload #15
    //   639: bipush #20
    //   641: if_icmpge -> 682
    //   644: aload #13
    //   646: iload #15
    //   648: iconst_4
    //   649: idiv
    //   650: iaload
    //   651: istore #16
    //   653: iconst_3
    //   654: iload #15
    //   656: iconst_4
    //   657: irem
    //   658: isub
    //   659: bipush #8
    //   661: imul
    //   662: istore #17
    //   664: aload #14
    //   666: iload #15
    //   668: iload #16
    //   670: iload #17
    //   672: iushr
    //   673: i2b
    //   674: bastore
    //   675: iinc #15, 1
    //   678: iload_2
    //   679: ifeq -> 637
    //   682: aload #14
    //   684: astore #4
    //   686: getstatic burp/Zzah.Za : Ljava/lang/Object;
    //   689: checkcast java/math/BigInteger
    //   692: invokevirtual toByteArray : ()[B
    //   695: astore_3
    //   696: bipush #32
    //   698: newarray int
    //   700: dup
    //   701: iconst_0
    //   702: ldc 943331329
    //   704: iastore
    //   705: dup
    //   706: iconst_1
    //   707: ldc 170788368
    //   709: iastore
    //   710: dup
    //   711: iconst_2
    //   712: ldc 1008414755
    //   714: iastore
    //   715: dup
    //   716: iconst_3
    //   717: ldc 187049985
    //   719: iastore
    //   720: dup
    //   721: iconst_4
    //   722: ldc 1010368540
    //   724: iastore
    //   725: dup
    //   726: iconst_5
    //   727: ldc 220604441
    //   729: iastore
    //   730: dup
    //   731: bipush #6
    //   733: ldc 940377620
    //   735: iastore
    //   736: dup
    //   737: bipush #7
    //   739: ldc 255209728
    //   741: iastore
    //   742: dup
    //   743: bipush #8
    //   745: ldc 689771012
    //   747: iastore
    //   748: dup
    //   749: bipush #9
    //   751: ldc 221709344
    //   753: iastore
    //   754: dup
    //   755: bipush #10
    //   757: ldc 957157408
    //   759: iastore
    //   760: dup
    //   761: bipush #11
    //   763: ldc 892536332
    //   765: iastore
    //   766: dup
    //   767: bipush #12
    //   769: ldc 722417666
    //   771: iastore
    //   772: dup
    //   773: bipush #13
    //   775: ldc 1026621720
    //   777: iastore
    //   778: dup
    //   779: bipush #14
    //   781: ldc 655302664
    //   783: iastore
    //   784: dup
    //   785: bipush #15
    //   787: ldc 890966315
    //   789: iastore
    //   790: dup
    //   791: bipush #16
    //   793: ldc 187632156
    //   795: iastore
    //   796: dup
    //   797: bipush #17
    //   799: ldc 874189824
    //   801: iastore
    //   802: dup
    //   803: bipush #18
    //   805: ldc 254150144
    //   807: iastore
    //   808: dup
    //   809: bipush #19
    //   811: ldc 924386310
    //   813: iastore
    //   814: dup
    //   815: bipush #20
    //   817: ldc 121057538
    //   819: iastore
    //   820: dup
    //   821: bipush #21
    //   823: ldc 840500228
    //   825: iastore
    //   826: dup
    //   827: bipush #22
    //   829: ldc 389160971
    //   831: iastore
    //   832: dup
    //   833: bipush #23
    //   835: ldc 907870729
    //   837: iastore
    //   838: dup
    //   839: bipush #24
    //   841: ldc 389426184
    //   843: iastore
    //   844: dup
    //   845: bipush #25
    //   847: ldc 973875457
    //   849: iastore
    //   850: dup
    //   851: bipush #26
    //   853: ldc 372376604
    //   855: iastore
    //   856: dup
    //   857: bipush #27
    //   859: ldc 707731490
    //   861: iastore
    //   862: dup
    //   863: bipush #28
    //   865: ldc 1043334948
    //   867: iastore
    //   868: dup
    //   869: bipush #29
    //   871: ldc 439222784
    //   873: iastore
    //   874: dup
    //   875: bipush #30
    //   877: ldc 876216579
    //   879: iastore
    //   880: dup
    //   881: bipush #31
    //   883: ldc 455999525
    //   885: iastore
    //   886: astore #5
    //   888: bipush #8
    //   890: aload_3
    //   891: arraylength
    //   892: bipush #8
    //   894: irem
    //   895: isub
    //   896: istore #6
    //   898: aload_3
    //   899: arraylength
    //   900: iload #6
    //   902: iadd
    //   903: newarray byte
    //   905: astore #7
    //   907: iconst_0
    //   908: istore #8
    //   910: iload #8
    //   912: aload_3
    //   913: arraylength
    //   914: if_icmpge -> 933
    //   917: aload #7
    //   919: iload #8
    //   921: aload_3
    //   922: iload #8
    //   924: baload
    //   925: bastore
    //   926: iinc #8, 1
    //   929: iload_2
    //   930: ifeq -> 910
    //   933: aload_3
    //   934: arraylength
    //   935: istore #8
    //   937: iload #8
    //   939: aload #7
    //   941: arraylength
    //   942: if_icmpge -> 960
    //   945: aload #7
    //   947: iload #8
    //   949: iload #6
    //   951: i2b
    //   952: bastore
    //   953: iinc #8, 1
    //   956: iload_2
    //   957: ifeq -> 937
    //   960: aload #7
    //   962: astore_3
    //   963: bipush #64
    //   965: newarray int
    //   967: dup
    //   968: iconst_0
    //   969: ldc 16843776
    //   971: iastore
    //   972: dup
    //   973: iconst_1
    //   974: iconst_0
    //   975: iastore
    //   976: dup
    //   977: iconst_2
    //   978: ldc 65536
    //   980: iastore
    //   981: dup
    //   982: iconst_3
    //   983: ldc 16843780
    //   985: iastore
    //   986: dup
    //   987: iconst_4
    //   988: ldc 16842756
    //   990: iastore
    //   991: dup
    //   992: iconst_5
    //   993: ldc 66564
    //   995: iastore
    //   996: dup
    //   997: bipush #6
    //   999: iconst_4
    //   1000: iastore
    //   1001: dup
    //   1002: bipush #7
    //   1004: ldc 65536
    //   1006: iastore
    //   1007: dup
    //   1008: bipush #8
    //   1010: sipush #1024
    //   1013: iastore
    //   1014: dup
    //   1015: bipush #9
    //   1017: ldc 16843776
    //   1019: iastore
    //   1020: dup
    //   1021: bipush #10
    //   1023: ldc 16843780
    //   1025: iastore
    //   1026: dup
    //   1027: bipush #11
    //   1029: sipush #1024
    //   1032: iastore
    //   1033: dup
    //   1034: bipush #12
    //   1036: ldc 16778244
    //   1038: iastore
    //   1039: dup
    //   1040: bipush #13
    //   1042: ldc 16842756
    //   1044: iastore
    //   1045: dup
    //   1046: bipush #14
    //   1048: ldc 16777216
    //   1050: iastore
    //   1051: dup
    //   1052: bipush #15
    //   1054: iconst_4
    //   1055: iastore
    //   1056: dup
    //   1057: bipush #16
    //   1059: sipush #1028
    //   1062: iastore
    //   1063: dup
    //   1064: bipush #17
    //   1066: ldc 16778240
    //   1068: iastore
    //   1069: dup
    //   1070: bipush #18
    //   1072: ldc 16778240
    //   1074: iastore
    //   1075: dup
    //   1076: bipush #19
    //   1078: ldc 66560
    //   1080: iastore
    //   1081: dup
    //   1082: bipush #20
    //   1084: ldc 66560
    //   1086: iastore
    //   1087: dup
    //   1088: bipush #21
    //   1090: ldc 16842752
    //   1092: iastore
    //   1093: dup
    //   1094: bipush #22
    //   1096: ldc 16842752
    //   1098: iastore
    //   1099: dup
    //   1100: bipush #23
    //   1102: ldc 16778244
    //   1104: iastore
    //   1105: dup
    //   1106: bipush #24
    //   1108: ldc 65540
    //   1110: iastore
    //   1111: dup
    //   1112: bipush #25
    //   1114: ldc 16777220
    //   1116: iastore
    //   1117: dup
    //   1118: bipush #26
    //   1120: ldc 16777220
    //   1122: iastore
    //   1123: dup
    //   1124: bipush #27
    //   1126: ldc 65540
    //   1128: iastore
    //   1129: dup
    //   1130: bipush #28
    //   1132: iconst_0
    //   1133: iastore
    //   1134: dup
    //   1135: bipush #29
    //   1137: sipush #1028
    //   1140: iastore
    //   1141: dup
    //   1142: bipush #30
    //   1144: ldc 66564
    //   1146: iastore
    //   1147: dup
    //   1148: bipush #31
    //   1150: ldc 16777216
    //   1152: iastore
    //   1153: dup
    //   1154: bipush #32
    //   1156: ldc 65536
    //   1158: iastore
    //   1159: dup
    //   1160: bipush #33
    //   1162: ldc 16843780
    //   1164: iastore
    //   1165: dup
    //   1166: bipush #34
    //   1168: iconst_4
    //   1169: iastore
    //   1170: dup
    //   1171: bipush #35
    //   1173: ldc 16842752
    //   1175: iastore
    //   1176: dup
    //   1177: bipush #36
    //   1179: ldc 16843776
    //   1181: iastore
    //   1182: dup
    //   1183: bipush #37
    //   1185: ldc 16777216
    //   1187: iastore
    //   1188: dup
    //   1189: bipush #38
    //   1191: ldc 16777216
    //   1193: iastore
    //   1194: dup
    //   1195: bipush #39
    //   1197: sipush #1024
    //   1200: iastore
    //   1201: dup
    //   1202: bipush #40
    //   1204: ldc 16842756
    //   1206: iastore
    //   1207: dup
    //   1208: bipush #41
    //   1210: ldc 65536
    //   1212: iastore
    //   1213: dup
    //   1214: bipush #42
    //   1216: ldc 66560
    //   1218: iastore
    //   1219: dup
    //   1220: bipush #43
    //   1222: ldc 16777220
    //   1224: iastore
    //   1225: dup
    //   1226: bipush #44
    //   1228: sipush #1024
    //   1231: iastore
    //   1232: dup
    //   1233: bipush #45
    //   1235: iconst_4
    //   1236: iastore
    //   1237: dup
    //   1238: bipush #46
    //   1240: ldc 16778244
    //   1242: iastore
    //   1243: dup
    //   1244: bipush #47
    //   1246: ldc 66564
    //   1248: iastore
    //   1249: dup
    //   1250: bipush #48
    //   1252: ldc 16843780
    //   1254: iastore
    //   1255: dup
    //   1256: bipush #49
    //   1258: ldc 65540
    //   1260: iastore
    //   1261: dup
    //   1262: bipush #50
    //   1264: ldc 16842752
    //   1266: iastore
    //   1267: dup
    //   1268: bipush #51
    //   1270: ldc 16778244
    //   1272: iastore
    //   1273: dup
    //   1274: bipush #52
    //   1276: ldc 16777220
    //   1278: iastore
    //   1279: dup
    //   1280: bipush #53
    //   1282: sipush #1028
    //   1285: iastore
    //   1286: dup
    //   1287: bipush #54
    //   1289: ldc 66564
    //   1291: iastore
    //   1292: dup
    //   1293: bipush #55
    //   1295: ldc 16843776
    //   1297: iastore
    //   1298: dup
    //   1299: bipush #56
    //   1301: sipush #1028
    //   1304: iastore
    //   1305: dup
    //   1306: bipush #57
    //   1308: ldc 16778240
    //   1310: iastore
    //   1311: dup
    //   1312: bipush #58
    //   1314: ldc 16778240
    //   1316: iastore
    //   1317: dup
    //   1318: bipush #59
    //   1320: iconst_0
    //   1321: iastore
    //   1322: dup
    //   1323: bipush #60
    //   1325: ldc 65540
    //   1327: iastore
    //   1328: dup
    //   1329: bipush #61
    //   1331: ldc 66560
    //   1333: iastore
    //   1334: dup
    //   1335: bipush #62
    //   1337: iconst_0
    //   1338: iastore
    //   1339: dup
    //   1340: bipush #63
    //   1342: ldc 16842756
    //   1344: iastore
    //   1345: astore #8
    //   1347: bipush #64
    //   1349: newarray int
    //   1351: dup
    //   1352: iconst_0
    //   1353: ldc -2146402272
    //   1355: iastore
    //   1356: dup
    //   1357: iconst_1
    //   1358: ldc -2147450880
    //   1360: iastore
    //   1361: dup
    //   1362: iconst_2
    //   1363: ldc 32768
    //   1365: iastore
    //   1366: dup
    //   1367: iconst_3
    //   1368: ldc 1081376
    //   1370: iastore
    //   1371: dup
    //   1372: iconst_4
    //   1373: ldc 1048576
    //   1375: iastore
    //   1376: dup
    //   1377: iconst_5
    //   1378: bipush #32
    //   1380: iastore
    //   1381: dup
    //   1382: bipush #6
    //   1384: ldc -2146435040
    //   1386: iastore
    //   1387: dup
    //   1388: bipush #7
    //   1390: ldc -2147450848
    //   1392: iastore
    //   1393: dup
    //   1394: bipush #8
    //   1396: ldc -2147483616
    //   1398: iastore
    //   1399: dup
    //   1400: bipush #9
    //   1402: ldc -2146402272
    //   1404: iastore
    //   1405: dup
    //   1406: bipush #10
    //   1408: ldc -2146402304
    //   1410: iastore
    //   1411: dup
    //   1412: bipush #11
    //   1414: ldc -2147483648
    //   1416: iastore
    //   1417: dup
    //   1418: bipush #12
    //   1420: ldc -2147450880
    //   1422: iastore
    //   1423: dup
    //   1424: bipush #13
    //   1426: ldc 1048576
    //   1428: iastore
    //   1429: dup
    //   1430: bipush #14
    //   1432: bipush #32
    //   1434: iastore
    //   1435: dup
    //   1436: bipush #15
    //   1438: ldc -2146435040
    //   1440: iastore
    //   1441: dup
    //   1442: bipush #16
    //   1444: ldc 1081344
    //   1446: iastore
    //   1447: dup
    //   1448: bipush #17
    //   1450: ldc 1048608
    //   1452: iastore
    //   1453: dup
    //   1454: bipush #18
    //   1456: ldc -2147450848
    //   1458: iastore
    //   1459: dup
    //   1460: bipush #19
    //   1462: iconst_0
    //   1463: iastore
    //   1464: dup
    //   1465: bipush #20
    //   1467: ldc -2147483648
    //   1469: iastore
    //   1470: dup
    //   1471: bipush #21
    //   1473: ldc 32768
    //   1475: iastore
    //   1476: dup
    //   1477: bipush #22
    //   1479: ldc 1081376
    //   1481: iastore
    //   1482: dup
    //   1483: bipush #23
    //   1485: ldc -2146435072
    //   1487: iastore
    //   1488: dup
    //   1489: bipush #24
    //   1491: ldc 1048608
    //   1493: iastore
    //   1494: dup
    //   1495: bipush #25
    //   1497: ldc -2147483616
    //   1499: iastore
    //   1500: dup
    //   1501: bipush #26
    //   1503: iconst_0
    //   1504: iastore
    //   1505: dup
    //   1506: bipush #27
    //   1508: ldc 1081344
    //   1510: iastore
    //   1511: dup
    //   1512: bipush #28
    //   1514: ldc 32800
    //   1516: iastore
    //   1517: dup
    //   1518: bipush #29
    //   1520: ldc -2146402304
    //   1522: iastore
    //   1523: dup
    //   1524: bipush #30
    //   1526: ldc -2146435072
    //   1528: iastore
    //   1529: dup
    //   1530: bipush #31
    //   1532: ldc 32800
    //   1534: iastore
    //   1535: dup
    //   1536: bipush #32
    //   1538: iconst_0
    //   1539: iastore
    //   1540: dup
    //   1541: bipush #33
    //   1543: ldc 1081376
    //   1545: iastore
    //   1546: dup
    //   1547: bipush #34
    //   1549: ldc -2146435040
    //   1551: iastore
    //   1552: dup
    //   1553: bipush #35
    //   1555: ldc 1048576
    //   1557: iastore
    //   1558: dup
    //   1559: bipush #36
    //   1561: ldc -2147450848
    //   1563: iastore
    //   1564: dup
    //   1565: bipush #37
    //   1567: ldc -2146435072
    //   1569: iastore
    //   1570: dup
    //   1571: bipush #38
    //   1573: ldc -2146402304
    //   1575: iastore
    //   1576: dup
    //   1577: bipush #39
    //   1579: ldc 32768
    //   1581: iastore
    //   1582: dup
    //   1583: bipush #40
    //   1585: ldc -2146435072
    //   1587: iastore
    //   1588: dup
    //   1589: bipush #41
    //   1591: ldc -2147450880
    //   1593: iastore
    //   1594: dup
    //   1595: bipush #42
    //   1597: bipush #32
    //   1599: iastore
    //   1600: dup
    //   1601: bipush #43
    //   1603: ldc -2146402272
    //   1605: iastore
    //   1606: dup
    //   1607: bipush #44
    //   1609: ldc 1081376
    //   1611: iastore
    //   1612: dup
    //   1613: bipush #45
    //   1615: bipush #32
    //   1617: iastore
    //   1618: dup
    //   1619: bipush #46
    //   1621: ldc 32768
    //   1623: iastore
    //   1624: dup
    //   1625: bipush #47
    //   1627: ldc -2147483648
    //   1629: iastore
    //   1630: dup
    //   1631: bipush #48
    //   1633: ldc 32800
    //   1635: iastore
    //   1636: dup
    //   1637: bipush #49
    //   1639: ldc -2146402304
    //   1641: iastore
    //   1642: dup
    //   1643: bipush #50
    //   1645: ldc 1048576
    //   1647: iastore
    //   1648: dup
    //   1649: bipush #51
    //   1651: ldc -2147483616
    //   1653: iastore
    //   1654: dup
    //   1655: bipush #52
    //   1657: ldc 1048608
    //   1659: iastore
    //   1660: dup
    //   1661: bipush #53
    //   1663: ldc -2147450848
    //   1665: iastore
    //   1666: dup
    //   1667: bipush #54
    //   1669: ldc -2147483616
    //   1671: iastore
    //   1672: dup
    //   1673: bipush #55
    //   1675: ldc 1048608
    //   1677: iastore
    //   1678: dup
    //   1679: bipush #56
    //   1681: ldc 1081344
    //   1683: iastore
    //   1684: dup
    //   1685: bipush #57
    //   1687: iconst_0
    //   1688: iastore
    //   1689: dup
    //   1690: bipush #58
    //   1692: ldc -2147450880
    //   1694: iastore
    //   1695: dup
    //   1696: bipush #59
    //   1698: ldc 32800
    //   1700: iastore
    //   1701: dup
    //   1702: bipush #60
    //   1704: ldc -2147483648
    //   1706: iastore
    //   1707: dup
    //   1708: bipush #61
    //   1710: ldc -2146435040
    //   1712: iastore
    //   1713: dup
    //   1714: bipush #62
    //   1716: ldc -2146402272
    //   1718: iastore
    //   1719: dup
    //   1720: bipush #63
    //   1722: ldc 1081344
    //   1724: iastore
    //   1725: astore #9
    //   1727: bipush #64
    //   1729: newarray int
    //   1731: dup
    //   1732: iconst_0
    //   1733: sipush #520
    //   1736: iastore
    //   1737: dup
    //   1738: iconst_1
    //   1739: ldc 134349312
    //   1741: iastore
    //   1742: dup
    //   1743: iconst_2
    //   1744: iconst_0
    //   1745: iastore
    //   1746: dup
    //   1747: iconst_3
    //   1748: ldc 134348808
    //   1750: iastore
    //   1751: dup
    //   1752: iconst_4
    //   1753: ldc 134218240
    //   1755: iastore
    //   1756: dup
    //   1757: iconst_5
    //   1758: iconst_0
    //   1759: iastore
    //   1760: dup
    //   1761: bipush #6
    //   1763: ldc 131592
    //   1765: iastore
    //   1766: dup
    //   1767: bipush #7
    //   1769: ldc 134218240
    //   1771: iastore
    //   1772: dup
    //   1773: bipush #8
    //   1775: ldc 131080
    //   1777: iastore
    //   1778: dup
    //   1779: bipush #9
    //   1781: ldc 134217736
    //   1783: iastore
    //   1784: dup
    //   1785: bipush #10
    //   1787: ldc 134217736
    //   1789: iastore
    //   1790: dup
    //   1791: bipush #11
    //   1793: ldc 131072
    //   1795: iastore
    //   1796: dup
    //   1797: bipush #12
    //   1799: ldc 134349320
    //   1801: iastore
    //   1802: dup
    //   1803: bipush #13
    //   1805: ldc 131080
    //   1807: iastore
    //   1808: dup
    //   1809: bipush #14
    //   1811: ldc 134348800
    //   1813: iastore
    //   1814: dup
    //   1815: bipush #15
    //   1817: sipush #520
    //   1820: iastore
    //   1821: dup
    //   1822: bipush #16
    //   1824: ldc 134217728
    //   1826: iastore
    //   1827: dup
    //   1828: bipush #17
    //   1830: bipush #8
    //   1832: iastore
    //   1833: dup
    //   1834: bipush #18
    //   1836: ldc 134349312
    //   1838: iastore
    //   1839: dup
    //   1840: bipush #19
    //   1842: sipush #512
    //   1845: iastore
    //   1846: dup
    //   1847: bipush #20
    //   1849: ldc 131584
    //   1851: iastore
    //   1852: dup
    //   1853: bipush #21
    //   1855: ldc 134348800
    //   1857: iastore
    //   1858: dup
    //   1859: bipush #22
    //   1861: ldc 134348808
    //   1863: iastore
    //   1864: dup
    //   1865: bipush #23
    //   1867: ldc 131592
    //   1869: iastore
    //   1870: dup
    //   1871: bipush #24
    //   1873: ldc 134218248
    //   1875: iastore
    //   1876: dup
    //   1877: bipush #25
    //   1879: ldc 131584
    //   1881: iastore
    //   1882: dup
    //   1883: bipush #26
    //   1885: ldc 131072
    //   1887: iastore
    //   1888: dup
    //   1889: bipush #27
    //   1891: ldc 134218248
    //   1893: iastore
    //   1894: dup
    //   1895: bipush #28
    //   1897: bipush #8
    //   1899: iastore
    //   1900: dup
    //   1901: bipush #29
    //   1903: ldc 134349320
    //   1905: iastore
    //   1906: dup
    //   1907: bipush #30
    //   1909: sipush #512
    //   1912: iastore
    //   1913: dup
    //   1914: bipush #31
    //   1916: ldc 134217728
    //   1918: iastore
    //   1919: dup
    //   1920: bipush #32
    //   1922: ldc 134349312
    //   1924: iastore
    //   1925: dup
    //   1926: bipush #33
    //   1928: ldc 134217728
    //   1930: iastore
    //   1931: dup
    //   1932: bipush #34
    //   1934: ldc 131080
    //   1936: iastore
    //   1937: dup
    //   1938: bipush #35
    //   1940: sipush #520
    //   1943: iastore
    //   1944: dup
    //   1945: bipush #36
    //   1947: ldc 131072
    //   1949: iastore
    //   1950: dup
    //   1951: bipush #37
    //   1953: ldc 134349312
    //   1955: iastore
    //   1956: dup
    //   1957: bipush #38
    //   1959: ldc 134218240
    //   1961: iastore
    //   1962: dup
    //   1963: bipush #39
    //   1965: iconst_0
    //   1966: iastore
    //   1967: dup
    //   1968: bipush #40
    //   1970: sipush #512
    //   1973: iastore
    //   1974: dup
    //   1975: bipush #41
    //   1977: ldc 131080
    //   1979: iastore
    //   1980: dup
    //   1981: bipush #42
    //   1983: ldc 134349320
    //   1985: iastore
    //   1986: dup
    //   1987: bipush #43
    //   1989: ldc 134218240
    //   1991: iastore
    //   1992: dup
    //   1993: bipush #44
    //   1995: ldc 134217736
    //   1997: iastore
    //   1998: dup
    //   1999: bipush #45
    //   2001: sipush #512
    //   2004: iastore
    //   2005: dup
    //   2006: bipush #46
    //   2008: iconst_0
    //   2009: iastore
    //   2010: dup
    //   2011: bipush #47
    //   2013: ldc 134348808
    //   2015: iastore
    //   2016: dup
    //   2017: bipush #48
    //   2019: ldc 134218248
    //   2021: iastore
    //   2022: dup
    //   2023: bipush #49
    //   2025: ldc 131072
    //   2027: iastore
    //   2028: dup
    //   2029: bipush #50
    //   2031: ldc 134217728
    //   2033: iastore
    //   2034: dup
    //   2035: bipush #51
    //   2037: ldc 134349320
    //   2039: iastore
    //   2040: dup
    //   2041: bipush #52
    //   2043: bipush #8
    //   2045: iastore
    //   2046: dup
    //   2047: bipush #53
    //   2049: ldc 131592
    //   2051: iastore
    //   2052: dup
    //   2053: bipush #54
    //   2055: ldc 131584
    //   2057: iastore
    //   2058: dup
    //   2059: bipush #55
    //   2061: ldc 134217736
    //   2063: iastore
    //   2064: dup
    //   2065: bipush #56
    //   2067: ldc 134348800
    //   2069: iastore
    //   2070: dup
    //   2071: bipush #57
    //   2073: ldc 134218248
    //   2075: iastore
    //   2076: dup
    //   2077: bipush #58
    //   2079: sipush #520
    //   2082: iastore
    //   2083: dup
    //   2084: bipush #59
    //   2086: ldc 134348800
    //   2088: iastore
    //   2089: dup
    //   2090: bipush #60
    //   2092: ldc 131592
    //   2094: iastore
    //   2095: dup
    //   2096: bipush #61
    //   2098: bipush #8
    //   2100: iastore
    //   2101: dup
    //   2102: bipush #62
    //   2104: ldc 134348808
    //   2106: iastore
    //   2107: dup
    //   2108: bipush #63
    //   2110: ldc 131584
    //   2112: iastore
    //   2113: astore #10
    //   2115: bipush #64
    //   2117: newarray int
    //   2119: dup
    //   2120: iconst_0
    //   2121: ldc 8396801
    //   2123: iastore
    //   2124: dup
    //   2125: iconst_1
    //   2126: sipush #8321
    //   2129: iastore
    //   2130: dup
    //   2131: iconst_2
    //   2132: sipush #8321
    //   2135: iastore
    //   2136: dup
    //   2137: iconst_3
    //   2138: sipush #128
    //   2141: iastore
    //   2142: dup
    //   2143: iconst_4
    //   2144: ldc 8396928
    //   2146: iastore
    //   2147: dup
    //   2148: iconst_5
    //   2149: ldc 8388737
    //   2151: iastore
    //   2152: dup
    //   2153: bipush #6
    //   2155: ldc 8388609
    //   2157: iastore
    //   2158: dup
    //   2159: bipush #7
    //   2161: sipush #8193
    //   2164: iastore
    //   2165: dup
    //   2166: bipush #8
    //   2168: iconst_0
    //   2169: iastore
    //   2170: dup
    //   2171: bipush #9
    //   2173: ldc 8396800
    //   2175: iastore
    //   2176: dup
    //   2177: bipush #10
    //   2179: ldc 8396800
    //   2181: iastore
    //   2182: dup
    //   2183: bipush #11
    //   2185: ldc 8396929
    //   2187: iastore
    //   2188: dup
    //   2189: bipush #12
    //   2191: sipush #129
    //   2194: iastore
    //   2195: dup
    //   2196: bipush #13
    //   2198: iconst_0
    //   2199: iastore
    //   2200: dup
    //   2201: bipush #14
    //   2203: ldc 8388736
    //   2205: iastore
    //   2206: dup
    //   2207: bipush #15
    //   2209: ldc 8388609
    //   2211: iastore
    //   2212: dup
    //   2213: bipush #16
    //   2215: iconst_1
    //   2216: iastore
    //   2217: dup
    //   2218: bipush #17
    //   2220: sipush #8192
    //   2223: iastore
    //   2224: dup
    //   2225: bipush #18
    //   2227: ldc 8388608
    //   2229: iastore
    //   2230: dup
    //   2231: bipush #19
    //   2233: ldc 8396801
    //   2235: iastore
    //   2236: dup
    //   2237: bipush #20
    //   2239: sipush #128
    //   2242: iastore
    //   2243: dup
    //   2244: bipush #21
    //   2246: ldc 8388608
    //   2248: iastore
    //   2249: dup
    //   2250: bipush #22
    //   2252: sipush #8193
    //   2255: iastore
    //   2256: dup
    //   2257: bipush #23
    //   2259: sipush #8320
    //   2262: iastore
    //   2263: dup
    //   2264: bipush #24
    //   2266: ldc 8388737
    //   2268: iastore
    //   2269: dup
    //   2270: bipush #25
    //   2272: iconst_1
    //   2273: iastore
    //   2274: dup
    //   2275: bipush #26
    //   2277: sipush #8320
    //   2280: iastore
    //   2281: dup
    //   2282: bipush #27
    //   2284: ldc 8388736
    //   2286: iastore
    //   2287: dup
    //   2288: bipush #28
    //   2290: sipush #8192
    //   2293: iastore
    //   2294: dup
    //   2295: bipush #29
    //   2297: ldc 8396928
    //   2299: iastore
    //   2300: dup
    //   2301: bipush #30
    //   2303: ldc 8396929
    //   2305: iastore
    //   2306: dup
    //   2307: bipush #31
    //   2309: sipush #129
    //   2312: iastore
    //   2313: dup
    //   2314: bipush #32
    //   2316: ldc 8388736
    //   2318: iastore
    //   2319: dup
    //   2320: bipush #33
    //   2322: ldc 8388609
    //   2324: iastore
    //   2325: dup
    //   2326: bipush #34
    //   2328: ldc 8396800
    //   2330: iastore
    //   2331: dup
    //   2332: bipush #35
    //   2334: ldc 8396929
    //   2336: iastore
    //   2337: dup
    //   2338: bipush #36
    //   2340: sipush #129
    //   2343: iastore
    //   2344: dup
    //   2345: bipush #37
    //   2347: iconst_0
    //   2348: iastore
    //   2349: dup
    //   2350: bipush #38
    //   2352: iconst_0
    //   2353: iastore
    //   2354: dup
    //   2355: bipush #39
    //   2357: ldc 8396800
    //   2359: iastore
    //   2360: dup
    //   2361: bipush #40
    //   2363: sipush #8320
    //   2366: iastore
    //   2367: dup
    //   2368: bipush #41
    //   2370: ldc 8388736
    //   2372: iastore
    //   2373: dup
    //   2374: bipush #42
    //   2376: ldc 8388737
    //   2378: iastore
    //   2379: dup
    //   2380: bipush #43
    //   2382: iconst_1
    //   2383: iastore
    //   2384: dup
    //   2385: bipush #44
    //   2387: ldc 8396801
    //   2389: iastore
    //   2390: dup
    //   2391: bipush #45
    //   2393: sipush #8321
    //   2396: iastore
    //   2397: dup
    //   2398: bipush #46
    //   2400: sipush #8321
    //   2403: iastore
    //   2404: dup
    //   2405: bipush #47
    //   2407: sipush #128
    //   2410: iastore
    //   2411: dup
    //   2412: bipush #48
    //   2414: ldc 8396929
    //   2416: iastore
    //   2417: dup
    //   2418: bipush #49
    //   2420: sipush #129
    //   2423: iastore
    //   2424: dup
    //   2425: bipush #50
    //   2427: iconst_1
    //   2428: iastore
    //   2429: dup
    //   2430: bipush #51
    //   2432: sipush #8192
    //   2435: iastore
    //   2436: dup
    //   2437: bipush #52
    //   2439: ldc 8388609
    //   2441: iastore
    //   2442: dup
    //   2443: bipush #53
    //   2445: sipush #8193
    //   2448: iastore
    //   2449: dup
    //   2450: bipush #54
    //   2452: ldc 8396928
    //   2454: iastore
    //   2455: dup
    //   2456: bipush #55
    //   2458: ldc 8388737
    //   2460: iastore
    //   2461: dup
    //   2462: bipush #56
    //   2464: sipush #8193
    //   2467: iastore
    //   2468: dup
    //   2469: bipush #57
    //   2471: sipush #8320
    //   2474: iastore
    //   2475: dup
    //   2476: bipush #58
    //   2478: ldc 8388608
    //   2480: iastore
    //   2481: dup
    //   2482: bipush #59
    //   2484: ldc 8396801
    //   2486: iastore
    //   2487: dup
    //   2488: bipush #60
    //   2490: sipush #128
    //   2493: iastore
    //   2494: dup
    //   2495: bipush #61
    //   2497: ldc 8388608
    //   2499: iastore
    //   2500: dup
    //   2501: bipush #62
    //   2503: sipush #8192
    //   2506: iastore
    //   2507: dup
    //   2508: bipush #63
    //   2510: ldc 8396928
    //   2512: iastore
    //   2513: astore #11
    //   2515: bipush #64
    //   2517: newarray int
    //   2519: dup
    //   2520: iconst_0
    //   2521: sipush #256
    //   2524: iastore
    //   2525: dup
    //   2526: iconst_1
    //   2527: ldc 34078976
    //   2529: iastore
    //   2530: dup
    //   2531: iconst_2
    //   2532: ldc 34078720
    //   2534: iastore
    //   2535: dup
    //   2536: iconst_3
    //   2537: ldc 1107296512
    //   2539: iastore
    //   2540: dup
    //   2541: iconst_4
    //   2542: ldc 524288
    //   2544: iastore
    //   2545: dup
    //   2546: iconst_5
    //   2547: sipush #256
    //   2550: iastore
    //   2551: dup
    //   2552: bipush #6
    //   2554: ldc 1073741824
    //   2556: iastore
    //   2557: dup
    //   2558: bipush #7
    //   2560: ldc 34078720
    //   2562: iastore
    //   2563: dup
    //   2564: bipush #8
    //   2566: ldc 1074266368
    //   2568: iastore
    //   2569: dup
    //   2570: bipush #9
    //   2572: ldc 524288
    //   2574: iastore
    //   2575: dup
    //   2576: bipush #10
    //   2578: ldc 33554688
    //   2580: iastore
    //   2581: dup
    //   2582: bipush #11
    //   2584: ldc 1074266368
    //   2586: iastore
    //   2587: dup
    //   2588: bipush #12
    //   2590: ldc 1107296512
    //   2592: iastore
    //   2593: dup
    //   2594: bipush #13
    //   2596: ldc 1107820544
    //   2598: iastore
    //   2599: dup
    //   2600: bipush #14
    //   2602: ldc 524544
    //   2604: iastore
    //   2605: dup
    //   2606: bipush #15
    //   2608: ldc 1073741824
    //   2610: iastore
    //   2611: dup
    //   2612: bipush #16
    //   2614: ldc 33554432
    //   2616: iastore
    //   2617: dup
    //   2618: bipush #17
    //   2620: ldc 1074266112
    //   2622: iastore
    //   2623: dup
    //   2624: bipush #18
    //   2626: ldc 1074266112
    //   2628: iastore
    //   2629: dup
    //   2630: bipush #19
    //   2632: iconst_0
    //   2633: iastore
    //   2634: dup
    //   2635: bipush #20
    //   2637: ldc 1073742080
    //   2639: iastore
    //   2640: dup
    //   2641: bipush #21
    //   2643: ldc 1107820800
    //   2645: iastore
    //   2646: dup
    //   2647: bipush #22
    //   2649: ldc 1107820800
    //   2651: iastore
    //   2652: dup
    //   2653: bipush #23
    //   2655: ldc 33554688
    //   2657: iastore
    //   2658: dup
    //   2659: bipush #24
    //   2661: ldc 1107820544
    //   2663: iastore
    //   2664: dup
    //   2665: bipush #25
    //   2667: ldc 1073742080
    //   2669: iastore
    //   2670: dup
    //   2671: bipush #26
    //   2673: iconst_0
    //   2674: iastore
    //   2675: dup
    //   2676: bipush #27
    //   2678: ldc 1107296256
    //   2680: iastore
    //   2681: dup
    //   2682: bipush #28
    //   2684: ldc 34078976
    //   2686: iastore
    //   2687: dup
    //   2688: bipush #29
    //   2690: ldc 33554432
    //   2692: iastore
    //   2693: dup
    //   2694: bipush #30
    //   2696: ldc 1107296256
    //   2698: iastore
    //   2699: dup
    //   2700: bipush #31
    //   2702: ldc 524544
    //   2704: iastore
    //   2705: dup
    //   2706: bipush #32
    //   2708: ldc 524288
    //   2710: iastore
    //   2711: dup
    //   2712: bipush #33
    //   2714: ldc 1107296512
    //   2716: iastore
    //   2717: dup
    //   2718: bipush #34
    //   2720: sipush #256
    //   2723: iastore
    //   2724: dup
    //   2725: bipush #35
    //   2727: ldc 33554432
    //   2729: iastore
    //   2730: dup
    //   2731: bipush #36
    //   2733: ldc 1073741824
    //   2735: iastore
    //   2736: dup
    //   2737: bipush #37
    //   2739: ldc 34078720
    //   2741: iastore
    //   2742: dup
    //   2743: bipush #38
    //   2745: ldc 1107296512
    //   2747: iastore
    //   2748: dup
    //   2749: bipush #39
    //   2751: ldc 1074266368
    //   2753: iastore
    //   2754: dup
    //   2755: bipush #40
    //   2757: ldc 33554688
    //   2759: iastore
    //   2760: dup
    //   2761: bipush #41
    //   2763: ldc 1073741824
    //   2765: iastore
    //   2766: dup
    //   2767: bipush #42
    //   2769: ldc 1107820544
    //   2771: iastore
    //   2772: dup
    //   2773: bipush #43
    //   2775: ldc 34078976
    //   2777: iastore
    //   2778: dup
    //   2779: bipush #44
    //   2781: ldc 1074266368
    //   2783: iastore
    //   2784: dup
    //   2785: bipush #45
    //   2787: sipush #256
    //   2790: iastore
    //   2791: dup
    //   2792: bipush #46
    //   2794: ldc 33554432
    //   2796: iastore
    //   2797: dup
    //   2798: bipush #47
    //   2800: ldc 1107820544
    //   2802: iastore
    //   2803: dup
    //   2804: bipush #48
    //   2806: ldc 1107820800
    //   2808: iastore
    //   2809: dup
    //   2810: bipush #49
    //   2812: ldc 524544
    //   2814: iastore
    //   2815: dup
    //   2816: bipush #50
    //   2818: ldc 1107296256
    //   2820: iastore
    //   2821: dup
    //   2822: bipush #51
    //   2824: ldc 1107820800
    //   2826: iastore
    //   2827: dup
    //   2828: bipush #52
    //   2830: ldc 34078720
    //   2832: iastore
    //   2833: dup
    //   2834: bipush #53
    //   2836: iconst_0
    //   2837: iastore
    //   2838: dup
    //   2839: bipush #54
    //   2841: ldc 1074266112
    //   2843: iastore
    //   2844: dup
    //   2845: bipush #55
    //   2847: ldc 1107296256
    //   2849: iastore
    //   2850: dup
    //   2851: bipush #56
    //   2853: ldc 524544
    //   2855: iastore
    //   2856: dup
    //   2857: bipush #57
    //   2859: ldc 33554688
    //   2861: iastore
    //   2862: dup
    //   2863: bipush #58
    //   2865: ldc 1073742080
    //   2867: iastore
    //   2868: dup
    //   2869: bipush #59
    //   2871: ldc 524288
    //   2873: iastore
    //   2874: dup
    //   2875: bipush #60
    //   2877: iconst_0
    //   2878: iastore
    //   2879: dup
    //   2880: bipush #61
    //   2882: ldc 1074266112
    //   2884: iastore
    //   2885: dup
    //   2886: bipush #62
    //   2888: ldc 34078976
    //   2890: iastore
    //   2891: dup
    //   2892: bipush #63
    //   2894: ldc 1073742080
    //   2896: iastore
    //   2897: astore #12
    //   2899: bipush #64
    //   2901: newarray int
    //   2903: dup
    //   2904: iconst_0
    //   2905: ldc 536870928
    //   2907: iastore
    //   2908: dup
    //   2909: iconst_1
    //   2910: ldc 541065216
    //   2912: iastore
    //   2913: dup
    //   2914: iconst_2
    //   2915: sipush #16384
    //   2918: iastore
    //   2919: dup
    //   2920: iconst_3
    //   2921: ldc 541081616
    //   2923: iastore
    //   2924: dup
    //   2925: iconst_4
    //   2926: ldc 541065216
    //   2928: iastore
    //   2929: dup
    //   2930: iconst_5
    //   2931: bipush #16
    //   2933: iastore
    //   2934: dup
    //   2935: bipush #6
    //   2937: ldc 541081616
    //   2939: iastore
    //   2940: dup
    //   2941: bipush #7
    //   2943: ldc 4194304
    //   2945: iastore
    //   2946: dup
    //   2947: bipush #8
    //   2949: ldc 536887296
    //   2951: iastore
    //   2952: dup
    //   2953: bipush #9
    //   2955: ldc 4210704
    //   2957: iastore
    //   2958: dup
    //   2959: bipush #10
    //   2961: ldc 4194304
    //   2963: iastore
    //   2964: dup
    //   2965: bipush #11
    //   2967: ldc 536870928
    //   2969: iastore
    //   2970: dup
    //   2971: bipush #12
    //   2973: ldc 4194320
    //   2975: iastore
    //   2976: dup
    //   2977: bipush #13
    //   2979: ldc 536887296
    //   2981: iastore
    //   2982: dup
    //   2983: bipush #14
    //   2985: ldc 536870912
    //   2987: iastore
    //   2988: dup
    //   2989: bipush #15
    //   2991: sipush #16400
    //   2994: iastore
    //   2995: dup
    //   2996: bipush #16
    //   2998: iconst_0
    //   2999: iastore
    //   3000: dup
    //   3001: bipush #17
    //   3003: ldc 4194320
    //   3005: iastore
    //   3006: dup
    //   3007: bipush #18
    //   3009: ldc 536887312
    //   3011: iastore
    //   3012: dup
    //   3013: bipush #19
    //   3015: sipush #16384
    //   3018: iastore
    //   3019: dup
    //   3020: bipush #20
    //   3022: ldc 4210688
    //   3024: iastore
    //   3025: dup
    //   3026: bipush #21
    //   3028: ldc 536887312
    //   3030: iastore
    //   3031: dup
    //   3032: bipush #22
    //   3034: bipush #16
    //   3036: iastore
    //   3037: dup
    //   3038: bipush #23
    //   3040: ldc 541065232
    //   3042: iastore
    //   3043: dup
    //   3044: bipush #24
    //   3046: ldc 541065232
    //   3048: iastore
    //   3049: dup
    //   3050: bipush #25
    //   3052: iconst_0
    //   3053: iastore
    //   3054: dup
    //   3055: bipush #26
    //   3057: ldc 4210704
    //   3059: iastore
    //   3060: dup
    //   3061: bipush #27
    //   3063: ldc 541081600
    //   3065: iastore
    //   3066: dup
    //   3067: bipush #28
    //   3069: sipush #16400
    //   3072: iastore
    //   3073: dup
    //   3074: bipush #29
    //   3076: ldc 4210688
    //   3078: iastore
    //   3079: dup
    //   3080: bipush #30
    //   3082: ldc 541081600
    //   3084: iastore
    //   3085: dup
    //   3086: bipush #31
    //   3088: ldc 536870912
    //   3090: iastore
    //   3091: dup
    //   3092: bipush #32
    //   3094: ldc 536887296
    //   3096: iastore
    //   3097: dup
    //   3098: bipush #33
    //   3100: bipush #16
    //   3102: iastore
    //   3103: dup
    //   3104: bipush #34
    //   3106: ldc 541065232
    //   3108: iastore
    //   3109: dup
    //   3110: bipush #35
    //   3112: ldc 4210688
    //   3114: iastore
    //   3115: dup
    //   3116: bipush #36
    //   3118: ldc 541081616
    //   3120: iastore
    //   3121: dup
    //   3122: bipush #37
    //   3124: ldc 4194304
    //   3126: iastore
    //   3127: dup
    //   3128: bipush #38
    //   3130: sipush #16400
    //   3133: iastore
    //   3134: dup
    //   3135: bipush #39
    //   3137: ldc 536870928
    //   3139: iastore
    //   3140: dup
    //   3141: bipush #40
    //   3143: ldc 4194304
    //   3145: iastore
    //   3146: dup
    //   3147: bipush #41
    //   3149: ldc 536887296
    //   3151: iastore
    //   3152: dup
    //   3153: bipush #42
    //   3155: ldc 536870912
    //   3157: iastore
    //   3158: dup
    //   3159: bipush #43
    //   3161: sipush #16400
    //   3164: iastore
    //   3165: dup
    //   3166: bipush #44
    //   3168: ldc 536870928
    //   3170: iastore
    //   3171: dup
    //   3172: bipush #45
    //   3174: ldc 541081616
    //   3176: iastore
    //   3177: dup
    //   3178: bipush #46
    //   3180: ldc 4210688
    //   3182: iastore
    //   3183: dup
    //   3184: bipush #47
    //   3186: ldc 541065216
    //   3188: iastore
    //   3189: dup
    //   3190: bipush #48
    //   3192: ldc 4210704
    //   3194: iastore
    //   3195: dup
    //   3196: bipush #49
    //   3198: ldc 541081600
    //   3200: iastore
    //   3201: dup
    //   3202: bipush #50
    //   3204: iconst_0
    //   3205: iastore
    //   3206: dup
    //   3207: bipush #51
    //   3209: ldc 541065232
    //   3211: iastore
    //   3212: dup
    //   3213: bipush #52
    //   3215: bipush #16
    //   3217: iastore
    //   3218: dup
    //   3219: bipush #53
    //   3221: sipush #16384
    //   3224: iastore
    //   3225: dup
    //   3226: bipush #54
    //   3228: ldc 541065216
    //   3230: iastore
    //   3231: dup
    //   3232: bipush #55
    //   3234: ldc 4210704
    //   3236: iastore
    //   3237: dup
    //   3238: bipush #56
    //   3240: sipush #16384
    //   3243: iastore
    //   3244: dup
    //   3245: bipush #57
    //   3247: ldc 4194320
    //   3249: iastore
    //   3250: dup
    //   3251: bipush #58
    //   3253: ldc 536887312
    //   3255: iastore
    //   3256: dup
    //   3257: bipush #59
    //   3259: iconst_0
    //   3260: iastore
    //   3261: dup
    //   3262: bipush #60
    //   3264: ldc 541081600
    //   3266: iastore
    //   3267: dup
    //   3268: bipush #61
    //   3270: ldc 536870912
    //   3272: iastore
    //   3273: dup
    //   3274: bipush #62
    //   3276: ldc 4194320
    //   3278: iastore
    //   3279: dup
    //   3280: bipush #63
    //   3282: ldc 536887312
    //   3284: iastore
    //   3285: astore #13
    //   3287: bipush #64
    //   3289: newarray int
    //   3291: dup
    //   3292: iconst_0
    //   3293: ldc 2097152
    //   3295: iastore
    //   3296: dup
    //   3297: iconst_1
    //   3298: ldc 69206018
    //   3300: iastore
    //   3301: dup
    //   3302: iconst_2
    //   3303: ldc 67110914
    //   3305: iastore
    //   3306: dup
    //   3307: iconst_3
    //   3308: iconst_0
    //   3309: iastore
    //   3310: dup
    //   3311: iconst_4
    //   3312: sipush #2048
    //   3315: iastore
    //   3316: dup
    //   3317: iconst_5
    //   3318: ldc 67110914
    //   3320: iastore
    //   3321: dup
    //   3322: bipush #6
    //   3324: ldc 2099202
    //   3326: iastore
    //   3327: dup
    //   3328: bipush #7
    //   3330: ldc 69208064
    //   3332: iastore
    //   3333: dup
    //   3334: bipush #8
    //   3336: ldc 69208066
    //   3338: iastore
    //   3339: dup
    //   3340: bipush #9
    //   3342: ldc 2097152
    //   3344: iastore
    //   3345: dup
    //   3346: bipush #10
    //   3348: iconst_0
    //   3349: iastore
    //   3350: dup
    //   3351: bipush #11
    //   3353: ldc 67108866
    //   3355: iastore
    //   3356: dup
    //   3357: bipush #12
    //   3359: iconst_2
    //   3360: iastore
    //   3361: dup
    //   3362: bipush #13
    //   3364: ldc 67108864
    //   3366: iastore
    //   3367: dup
    //   3368: bipush #14
    //   3370: ldc 69206018
    //   3372: iastore
    //   3373: dup
    //   3374: bipush #15
    //   3376: sipush #2050
    //   3379: iastore
    //   3380: dup
    //   3381: bipush #16
    //   3383: ldc 67110912
    //   3385: iastore
    //   3386: dup
    //   3387: bipush #17
    //   3389: ldc 2099202
    //   3391: iastore
    //   3392: dup
    //   3393: bipush #18
    //   3395: ldc 2097154
    //   3397: iastore
    //   3398: dup
    //   3399: bipush #19
    //   3401: ldc 67110912
    //   3403: iastore
    //   3404: dup
    //   3405: bipush #20
    //   3407: ldc 67108866
    //   3409: iastore
    //   3410: dup
    //   3411: bipush #21
    //   3413: ldc 69206016
    //   3415: iastore
    //   3416: dup
    //   3417: bipush #22
    //   3419: ldc 69208064
    //   3421: iastore
    //   3422: dup
    //   3423: bipush #23
    //   3425: ldc 2097154
    //   3427: iastore
    //   3428: dup
    //   3429: bipush #24
    //   3431: ldc 69206016
    //   3433: iastore
    //   3434: dup
    //   3435: bipush #25
    //   3437: sipush #2048
    //   3440: iastore
    //   3441: dup
    //   3442: bipush #26
    //   3444: sipush #2050
    //   3447: iastore
    //   3448: dup
    //   3449: bipush #27
    //   3451: ldc 69208066
    //   3453: iastore
    //   3454: dup
    //   3455: bipush #28
    //   3457: ldc 2099200
    //   3459: iastore
    //   3460: dup
    //   3461: bipush #29
    //   3463: iconst_2
    //   3464: iastore
    //   3465: dup
    //   3466: bipush #30
    //   3468: ldc 67108864
    //   3470: iastore
    //   3471: dup
    //   3472: bipush #31
    //   3474: ldc 2099200
    //   3476: iastore
    //   3477: dup
    //   3478: bipush #32
    //   3480: ldc 67108864
    //   3482: iastore
    //   3483: dup
    //   3484: bipush #33
    //   3486: ldc 2099200
    //   3488: iastore
    //   3489: dup
    //   3490: bipush #34
    //   3492: ldc 2097152
    //   3494: iastore
    //   3495: dup
    //   3496: bipush #35
    //   3498: ldc 67110914
    //   3500: iastore
    //   3501: dup
    //   3502: bipush #36
    //   3504: ldc 67110914
    //   3506: iastore
    //   3507: dup
    //   3508: bipush #37
    //   3510: ldc 69206018
    //   3512: iastore
    //   3513: dup
    //   3514: bipush #38
    //   3516: ldc 69206018
    //   3518: iastore
    //   3519: dup
    //   3520: bipush #39
    //   3522: iconst_2
    //   3523: iastore
    //   3524: dup
    //   3525: bipush #40
    //   3527: ldc 2097154
    //   3529: iastore
    //   3530: dup
    //   3531: bipush #41
    //   3533: ldc 67108864
    //   3535: iastore
    //   3536: dup
    //   3537: bipush #42
    //   3539: ldc 67110912
    //   3541: iastore
    //   3542: dup
    //   3543: bipush #43
    //   3545: ldc 2097152
    //   3547: iastore
    //   3548: dup
    //   3549: bipush #44
    //   3551: ldc 69208064
    //   3553: iastore
    //   3554: dup
    //   3555: bipush #45
    //   3557: sipush #2050
    //   3560: iastore
    //   3561: dup
    //   3562: bipush #46
    //   3564: ldc 2099202
    //   3566: iastore
    //   3567: dup
    //   3568: bipush #47
    //   3570: ldc 69208064
    //   3572: iastore
    //   3573: dup
    //   3574: bipush #48
    //   3576: sipush #2050
    //   3579: iastore
    //   3580: dup
    //   3581: bipush #49
    //   3583: ldc 67108866
    //   3585: iastore
    //   3586: dup
    //   3587: bipush #50
    //   3589: ldc 69208066
    //   3591: iastore
    //   3592: dup
    //   3593: bipush #51
    //   3595: ldc 69206016
    //   3597: iastore
    //   3598: dup
    //   3599: bipush #52
    //   3601: ldc 2099200
    //   3603: iastore
    //   3604: dup
    //   3605: bipush #53
    //   3607: iconst_0
    //   3608: iastore
    //   3609: dup
    //   3610: bipush #54
    //   3612: iconst_2
    //   3613: iastore
    //   3614: dup
    //   3615: bipush #55
    //   3617: ldc 69208066
    //   3619: iastore
    //   3620: dup
    //   3621: bipush #56
    //   3623: iconst_0
    //   3624: iastore
    //   3625: dup
    //   3626: bipush #57
    //   3628: ldc 2099202
    //   3630: iastore
    //   3631: dup
    //   3632: bipush #58
    //   3634: ldc 69206016
    //   3636: iastore
    //   3637: dup
    //   3638: bipush #59
    //   3640: sipush #2048
    //   3643: iastore
    //   3644: dup
    //   3645: bipush #60
    //   3647: ldc 67108866
    //   3649: iastore
    //   3650: dup
    //   3651: bipush #61
    //   3653: ldc 67110912
    //   3655: iastore
    //   3656: dup
    //   3657: bipush #62
    //   3659: sipush #2048
    //   3662: iastore
    //   3663: dup
    //   3664: bipush #63
    //   3666: ldc 2097154
    //   3668: iastore
    //   3669: astore #14
    //   3671: bipush #64
    //   3673: newarray int
    //   3675: dup
    //   3676: iconst_0
    //   3677: ldc 268439616
    //   3679: iastore
    //   3680: dup
    //   3681: iconst_1
    //   3682: sipush #4096
    //   3685: iastore
    //   3686: dup
    //   3687: iconst_2
    //   3688: ldc 262144
    //   3690: iastore
    //   3691: dup
    //   3692: iconst_3
    //   3693: ldc 268701760
    //   3695: iastore
    //   3696: dup
    //   3697: iconst_4
    //   3698: ldc 268435456
    //   3700: iastore
    //   3701: dup
    //   3702: iconst_5
    //   3703: ldc 268439616
    //   3705: iastore
    //   3706: dup
    //   3707: bipush #6
    //   3709: bipush #64
    //   3711: iastore
    //   3712: dup
    //   3713: bipush #7
    //   3715: ldc 268435456
    //   3717: iastore
    //   3718: dup
    //   3719: bipush #8
    //   3721: ldc 262208
    //   3723: iastore
    //   3724: dup
    //   3725: bipush #9
    //   3727: ldc 268697600
    //   3729: iastore
    //   3730: dup
    //   3731: bipush #10
    //   3733: ldc 268701760
    //   3735: iastore
    //   3736: dup
    //   3737: bipush #11
    //   3739: ldc 266240
    //   3741: iastore
    //   3742: dup
    //   3743: bipush #12
    //   3745: ldc 268701696
    //   3747: iastore
    //   3748: dup
    //   3749: bipush #13
    //   3751: ldc 266304
    //   3753: iastore
    //   3754: dup
    //   3755: bipush #14
    //   3757: sipush #4096
    //   3760: iastore
    //   3761: dup
    //   3762: bipush #15
    //   3764: bipush #64
    //   3766: iastore
    //   3767: dup
    //   3768: bipush #16
    //   3770: ldc 268697600
    //   3772: iastore
    //   3773: dup
    //   3774: bipush #17
    //   3776: ldc 268435520
    //   3778: iastore
    //   3779: dup
    //   3780: bipush #18
    //   3782: ldc 268439552
    //   3784: iastore
    //   3785: dup
    //   3786: bipush #19
    //   3788: sipush #4160
    //   3791: iastore
    //   3792: dup
    //   3793: bipush #20
    //   3795: ldc 266240
    //   3797: iastore
    //   3798: dup
    //   3799: bipush #21
    //   3801: ldc 262208
    //   3803: iastore
    //   3804: dup
    //   3805: bipush #22
    //   3807: ldc 268697664
    //   3809: iastore
    //   3810: dup
    //   3811: bipush #23
    //   3813: ldc 268701696
    //   3815: iastore
    //   3816: dup
    //   3817: bipush #24
    //   3819: sipush #4160
    //   3822: iastore
    //   3823: dup
    //   3824: bipush #25
    //   3826: iconst_0
    //   3827: iastore
    //   3828: dup
    //   3829: bipush #26
    //   3831: iconst_0
    //   3832: iastore
    //   3833: dup
    //   3834: bipush #27
    //   3836: ldc 268697664
    //   3838: iastore
    //   3839: dup
    //   3840: bipush #28
    //   3842: ldc 268435520
    //   3844: iastore
    //   3845: dup
    //   3846: bipush #29
    //   3848: ldc 268439552
    //   3850: iastore
    //   3851: dup
    //   3852: bipush #30
    //   3854: ldc 266304
    //   3856: iastore
    //   3857: dup
    //   3858: bipush #31
    //   3860: ldc 262144
    //   3862: iastore
    //   3863: dup
    //   3864: bipush #32
    //   3866: ldc 266304
    //   3868: iastore
    //   3869: dup
    //   3870: bipush #33
    //   3872: ldc 262144
    //   3874: iastore
    //   3875: dup
    //   3876: bipush #34
    //   3878: ldc 268701696
    //   3880: iastore
    //   3881: dup
    //   3882: bipush #35
    //   3884: sipush #4096
    //   3887: iastore
    //   3888: dup
    //   3889: bipush #36
    //   3891: bipush #64
    //   3893: iastore
    //   3894: dup
    //   3895: bipush #37
    //   3897: ldc 268697664
    //   3899: iastore
    //   3900: dup
    //   3901: bipush #38
    //   3903: sipush #4096
    //   3906: iastore
    //   3907: dup
    //   3908: bipush #39
    //   3910: ldc 266304
    //   3912: iastore
    //   3913: dup
    //   3914: bipush #40
    //   3916: ldc 268439552
    //   3918: iastore
    //   3919: dup
    //   3920: bipush #41
    //   3922: bipush #64
    //   3924: iastore
    //   3925: dup
    //   3926: bipush #42
    //   3928: ldc 268435520
    //   3930: iastore
    //   3931: dup
    //   3932: bipush #43
    //   3934: ldc 268697600
    //   3936: iastore
    //   3937: dup
    //   3938: bipush #44
    //   3940: ldc 268697664
    //   3942: iastore
    //   3943: dup
    //   3944: bipush #45
    //   3946: ldc 268435456
    //   3948: iastore
    //   3949: dup
    //   3950: bipush #46
    //   3952: ldc 262144
    //   3954: iastore
    //   3955: dup
    //   3956: bipush #47
    //   3958: ldc 268439616
    //   3960: iastore
    //   3961: dup
    //   3962: bipush #48
    //   3964: iconst_0
    //   3965: iastore
    //   3966: dup
    //   3967: bipush #49
    //   3969: ldc 268701760
    //   3971: iastore
    //   3972: dup
    //   3973: bipush #50
    //   3975: ldc 262208
    //   3977: iastore
    //   3978: dup
    //   3979: bipush #51
    //   3981: ldc 268435520
    //   3983: iastore
    //   3984: dup
    //   3985: bipush #52
    //   3987: ldc 268697600
    //   3989: iastore
    //   3990: dup
    //   3991: bipush #53
    //   3993: ldc 268439552
    //   3995: iastore
    //   3996: dup
    //   3997: bipush #54
    //   3999: ldc 268439616
    //   4001: iastore
    //   4002: dup
    //   4003: bipush #55
    //   4005: iconst_0
    //   4006: iastore
    //   4007: dup
    //   4008: bipush #56
    //   4010: ldc 268701760
    //   4012: iastore
    //   4013: dup
    //   4014: bipush #57
    //   4016: ldc 266240
    //   4018: iastore
    //   4019: dup
    //   4020: bipush #58
    //   4022: ldc 266240
    //   4024: iastore
    //   4025: dup
    //   4026: bipush #59
    //   4028: sipush #4160
    //   4031: iastore
    //   4032: dup
    //   4033: bipush #60
    //   4035: sipush #4160
    //   4038: iastore
    //   4039: dup
    //   4040: bipush #61
    //   4042: ldc 262208
    //   4044: iastore
    //   4045: dup
    //   4046: bipush #62
    //   4048: ldc 268435456
    //   4050: iastore
    //   4051: dup
    //   4052: bipush #63
    //   4054: ldc 268701696
    //   4056: iastore
    //   4057: astore #15
    //   4059: aload_3
    //   4060: arraylength
    //   4061: istore #16
    //   4063: iconst_2
    //   4064: newarray int
    //   4066: astore #17
    //   4068: iload #16
    //   4070: newarray byte
    //   4072: astore #4
    //   4074: iload #16
    //   4076: bipush #8
    //   4078: idiv
    //   4079: istore #18
    //   4081: iconst_0
    //   4082: istore #19
    //   4084: iload #19
    //   4086: iload #18
    //   4088: if_icmpge -> 5002
    //   4091: iload #19
    //   4093: bipush #8
    //   4095: imul
    //   4096: istore #20
    //   4098: iconst_0
    //   4099: istore #21
    //   4101: iload #21
    //   4103: iconst_2
    //   4104: if_icmpge -> 4189
    //   4107: aload #17
    //   4109: iload #21
    //   4111: aload_3
    //   4112: iload #20
    //   4114: iload #21
    //   4116: iconst_4
    //   4117: imul
    //   4118: iadd
    //   4119: baload
    //   4120: sipush #255
    //   4123: iand
    //   4124: bipush #24
    //   4126: ishl
    //   4127: aload_3
    //   4128: iload #20
    //   4130: iload #21
    //   4132: iconst_4
    //   4133: imul
    //   4134: iadd
    //   4135: iconst_1
    //   4136: iadd
    //   4137: baload
    //   4138: sipush #255
    //   4141: iand
    //   4142: bipush #16
    //   4144: ishl
    //   4145: ior
    //   4146: aload_3
    //   4147: iload #20
    //   4149: iload #21
    //   4151: iconst_4
    //   4152: imul
    //   4153: iadd
    //   4154: iconst_2
    //   4155: iadd
    //   4156: baload
    //   4157: sipush #255
    //   4160: iand
    //   4161: bipush #8
    //   4163: ishl
    //   4164: ior
    //   4165: aload_3
    //   4166: iload #20
    //   4168: iload #21
    //   4170: iconst_4
    //   4171: imul
    //   4172: iadd
    //   4173: iconst_3
    //   4174: iadd
    //   4175: baload
    //   4176: sipush #255
    //   4179: iand
    //   4180: ior
    //   4181: iastore
    //   4182: iinc #21, 1
    //   4185: iload_2
    //   4186: ifeq -> 4101
    //   4189: iconst_0
    //   4190: istore #26
    //   4192: aload #17
    //   4194: iconst_0
    //   4195: iaload
    //   4196: istore #24
    //   4198: aload #17
    //   4200: iconst_1
    //   4201: iaload
    //   4202: istore #23
    //   4204: iload #24
    //   4206: iconst_4
    //   4207: iushr
    //   4208: iload #23
    //   4210: ixor
    //   4211: ldc 252645135
    //   4213: iand
    //   4214: istore #22
    //   4216: iload #23
    //   4218: iload #22
    //   4220: ixor
    //   4221: istore #23
    //   4223: iload #24
    //   4225: iload #22
    //   4227: iconst_4
    //   4228: ishl
    //   4229: ixor
    //   4230: istore #24
    //   4232: iload #24
    //   4234: bipush #16
    //   4236: iushr
    //   4237: iload #23
    //   4239: ixor
    //   4240: ldc 65535
    //   4242: iand
    //   4243: istore #22
    //   4245: iload #23
    //   4247: iload #22
    //   4249: ixor
    //   4250: istore #23
    //   4252: iload #24
    //   4254: iload #22
    //   4256: bipush #16
    //   4258: ishl
    //   4259: ixor
    //   4260: istore #24
    //   4262: iload #23
    //   4264: iconst_2
    //   4265: iushr
    //   4266: iload #24
    //   4268: ixor
    //   4269: ldc 858993459
    //   4271: iand
    //   4272: istore #22
    //   4274: iload #24
    //   4276: iload #22
    //   4278: ixor
    //   4279: istore #24
    //   4281: iload #23
    //   4283: iload #22
    //   4285: iconst_2
    //   4286: ishl
    //   4287: ixor
    //   4288: istore #23
    //   4290: iload #23
    //   4292: bipush #8
    //   4294: iushr
    //   4295: iload #24
    //   4297: ixor
    //   4298: ldc 16711935
    //   4300: iand
    //   4301: istore #22
    //   4303: iload #24
    //   4305: iload #22
    //   4307: ixor
    //   4308: istore #24
    //   4310: iload #23
    //   4312: iload #22
    //   4314: bipush #8
    //   4316: ishl
    //   4317: ixor
    //   4318: istore #23
    //   4320: iload #23
    //   4322: iconst_1
    //   4323: ishl
    //   4324: iload #23
    //   4326: bipush #31
    //   4328: iushr
    //   4329: iconst_1
    //   4330: iand
    //   4331: ior
    //   4332: istore #23
    //   4334: iload #24
    //   4336: iload #23
    //   4338: ixor
    //   4339: ldc -1431655766
    //   4341: iand
    //   4342: istore #22
    //   4344: iload #24
    //   4346: iload #22
    //   4348: ixor
    //   4349: istore #24
    //   4351: iload #23
    //   4353: iload #22
    //   4355: ixor
    //   4356: istore #23
    //   4358: iload #24
    //   4360: iconst_1
    //   4361: ishl
    //   4362: iload #24
    //   4364: bipush #31
    //   4366: iushr
    //   4367: iconst_1
    //   4368: iand
    //   4369: ior
    //   4370: istore #24
    //   4372: iconst_0
    //   4373: istore #25
    //   4375: iload #25
    //   4377: bipush #8
    //   4379: if_icmpge -> 4717
    //   4382: iload #23
    //   4384: bipush #28
    //   4386: ishl
    //   4387: iload #23
    //   4389: iconst_4
    //   4390: iushr
    //   4391: ior
    //   4392: istore #22
    //   4394: iload #22
    //   4396: aload #5
    //   4398: iload #26
    //   4400: iinc #26, 1
    //   4403: iaload
    //   4404: ixor
    //   4405: istore #22
    //   4407: aload #14
    //   4409: iload #22
    //   4411: bipush #63
    //   4413: iand
    //   4414: iaload
    //   4415: istore #21
    //   4417: iload #21
    //   4419: aload #12
    //   4421: iload #22
    //   4423: bipush #8
    //   4425: iushr
    //   4426: bipush #63
    //   4428: iand
    //   4429: iaload
    //   4430: ior
    //   4431: istore #21
    //   4433: iload #21
    //   4435: aload #10
    //   4437: iload #22
    //   4439: bipush #16
    //   4441: iushr
    //   4442: bipush #63
    //   4444: iand
    //   4445: iaload
    //   4446: ior
    //   4447: istore #21
    //   4449: iload #21
    //   4451: aload #8
    //   4453: iload #22
    //   4455: bipush #24
    //   4457: iushr
    //   4458: bipush #63
    //   4460: iand
    //   4461: iaload
    //   4462: ior
    //   4463: istore #21
    //   4465: iload #23
    //   4467: aload #5
    //   4469: iload #26
    //   4471: iinc #26, 1
    //   4474: iaload
    //   4475: ixor
    //   4476: istore #22
    //   4478: iload #21
    //   4480: aload #15
    //   4482: iload #22
    //   4484: bipush #63
    //   4486: iand
    //   4487: iaload
    //   4488: ior
    //   4489: istore #21
    //   4491: iload #21
    //   4493: aload #13
    //   4495: iload #22
    //   4497: bipush #8
    //   4499: iushr
    //   4500: bipush #63
    //   4502: iand
    //   4503: iaload
    //   4504: ior
    //   4505: istore #21
    //   4507: iload #21
    //   4509: aload #11
    //   4511: iload #22
    //   4513: bipush #16
    //   4515: iushr
    //   4516: bipush #63
    //   4518: iand
    //   4519: iaload
    //   4520: ior
    //   4521: istore #21
    //   4523: iload #21
    //   4525: aload #9
    //   4527: iload #22
    //   4529: bipush #24
    //   4531: iushr
    //   4532: bipush #63
    //   4534: iand
    //   4535: iaload
    //   4536: ior
    //   4537: istore #21
    //   4539: iload #24
    //   4541: iload #21
    //   4543: ixor
    //   4544: istore #24
    //   4546: iload #24
    //   4548: bipush #28
    //   4550: ishl
    //   4551: iload #24
    //   4553: iconst_4
    //   4554: iushr
    //   4555: ior
    //   4556: istore #22
    //   4558: iload #22
    //   4560: aload #5
    //   4562: iload #26
    //   4564: iinc #26, 1
    //   4567: iaload
    //   4568: ixor
    //   4569: istore #22
    //   4571: aload #14
    //   4573: iload #22
    //   4575: bipush #63
    //   4577: iand
    //   4578: iaload
    //   4579: istore #21
    //   4581: iload #21
    //   4583: aload #12
    //   4585: iload #22
    //   4587: bipush #8
    //   4589: iushr
    //   4590: bipush #63
    //   4592: iand
    //   4593: iaload
    //   4594: ior
    //   4595: istore #21
    //   4597: iload #21
    //   4599: aload #10
    //   4601: iload #22
    //   4603: bipush #16
    //   4605: iushr
    //   4606: bipush #63
    //   4608: iand
    //   4609: iaload
    //   4610: ior
    //   4611: istore #21
    //   4613: iload #21
    //   4615: aload #8
    //   4617: iload #22
    //   4619: bipush #24
    //   4621: iushr
    //   4622: bipush #63
    //   4624: iand
    //   4625: iaload
    //   4626: ior
    //   4627: istore #21
    //   4629: iload #24
    //   4631: aload #5
    //   4633: iload #26
    //   4635: iinc #26, 1
    //   4638: iaload
    //   4639: ixor
    //   4640: istore #22
    //   4642: iload #21
    //   4644: aload #15
    //   4646: iload #22
    //   4648: bipush #63
    //   4650: iand
    //   4651: iaload
    //   4652: ior
    //   4653: istore #21
    //   4655: iload #21
    //   4657: aload #13
    //   4659: iload #22
    //   4661: bipush #8
    //   4663: iushr
    //   4664: bipush #63
    //   4666: iand
    //   4667: iaload
    //   4668: ior
    //   4669: istore #21
    //   4671: iload #21
    //   4673: aload #11
    //   4675: iload #22
    //   4677: bipush #16
    //   4679: iushr
    //   4680: bipush #63
    //   4682: iand
    //   4683: iaload
    //   4684: ior
    //   4685: istore #21
    //   4687: iload #21
    //   4689: aload #9
    //   4691: iload #22
    //   4693: bipush #24
    //   4695: iushr
    //   4696: bipush #63
    //   4698: iand
    //   4699: iaload
    //   4700: ior
    //   4701: istore #21
    //   4703: iload #23
    //   4705: iload #21
    //   4707: ixor
    //   4708: istore #23
    //   4710: iinc #25, 1
    //   4713: iload_2
    //   4714: ifeq -> 4375
    //   4717: iload #23
    //   4719: bipush #31
    //   4721: ishl
    //   4722: iload #23
    //   4724: iconst_1
    //   4725: iushr
    //   4726: ior
    //   4727: istore #23
    //   4729: iload #24
    //   4731: iload #23
    //   4733: ixor
    //   4734: ldc -1431655766
    //   4736: iand
    //   4737: istore #22
    //   4739: iload #24
    //   4741: iload #22
    //   4743: ixor
    //   4744: istore #24
    //   4746: iload #23
    //   4748: iload #22
    //   4750: ixor
    //   4751: istore #23
    //   4753: iload #24
    //   4755: bipush #31
    //   4757: ishl
    //   4758: iload #24
    //   4760: iconst_1
    //   4761: iushr
    //   4762: ior
    //   4763: istore #24
    //   4765: iload #24
    //   4767: bipush #8
    //   4769: iushr
    //   4770: iload #23
    //   4772: ixor
    //   4773: ldc 16711935
    //   4775: iand
    //   4776: istore #22
    //   4778: iload #23
    //   4780: iload #22
    //   4782: ixor
    //   4783: istore #23
    //   4785: iload #24
    //   4787: iload #22
    //   4789: bipush #8
    //   4791: ishl
    //   4792: ixor
    //   4793: istore #24
    //   4795: iload #24
    //   4797: iconst_2
    //   4798: iushr
    //   4799: iload #23
    //   4801: ixor
    //   4802: ldc 858993459
    //   4804: iand
    //   4805: istore #22
    //   4807: iload #23
    //   4809: iload #22
    //   4811: ixor
    //   4812: istore #23
    //   4814: iload #24
    //   4816: iload #22
    //   4818: iconst_2
    //   4819: ishl
    //   4820: ixor
    //   4821: istore #24
    //   4823: iload #23
    //   4825: bipush #16
    //   4827: iushr
    //   4828: iload #24
    //   4830: ixor
    //   4831: ldc 65535
    //   4833: iand
    //   4834: istore #22
    //   4836: iload #24
    //   4838: iload #22
    //   4840: ixor
    //   4841: istore #24
    //   4843: iload #23
    //   4845: iload #22
    //   4847: bipush #16
    //   4849: ishl
    //   4850: ixor
    //   4851: istore #23
    //   4853: iload #23
    //   4855: iconst_4
    //   4856: iushr
    //   4857: iload #24
    //   4859: ixor
    //   4860: ldc 252645135
    //   4862: iand
    //   4863: istore #22
    //   4865: iload #24
    //   4867: iload #22
    //   4869: ixor
    //   4870: istore #24
    //   4872: iload #23
    //   4874: iload #22
    //   4876: iconst_4
    //   4877: ishl
    //   4878: ixor
    //   4879: istore #23
    //   4881: aload #17
    //   4883: iconst_0
    //   4884: iload #23
    //   4886: iastore
    //   4887: aload #17
    //   4889: iconst_1
    //   4890: iload #24
    //   4892: iastore
    //   4893: iload #19
    //   4895: bipush #8
    //   4897: imul
    //   4898: istore #27
    //   4900: iconst_0
    //   4901: istore #28
    //   4903: iload #28
    //   4905: iconst_2
    //   4906: if_icmpge -> 4995
    //   4909: aload #4
    //   4911: iload #27
    //   4913: iload #28
    //   4915: iconst_4
    //   4916: imul
    //   4917: iadd
    //   4918: aload #17
    //   4920: iload #28
    //   4922: iaload
    //   4923: bipush #24
    //   4925: iushr
    //   4926: i2b
    //   4927: bastore
    //   4928: aload #4
    //   4930: iload #27
    //   4932: iload #28
    //   4934: iconst_4
    //   4935: imul
    //   4936: iadd
    //   4937: iconst_1
    //   4938: iadd
    //   4939: aload #17
    //   4941: iload #28
    //   4943: iaload
    //   4944: bipush #16
    //   4946: iushr
    //   4947: i2b
    //   4948: bastore
    //   4949: aload #4
    //   4951: iload #27
    //   4953: iload #28
    //   4955: iconst_4
    //   4956: imul
    //   4957: iadd
    //   4958: iconst_2
    //   4959: iadd
    //   4960: aload #17
    //   4962: iload #28
    //   4964: iaload
    //   4965: bipush #8
    //   4967: iushr
    //   4968: i2b
    //   4969: bastore
    //   4970: aload #4
    //   4972: iload #27
    //   4974: iload #28
    //   4976: iconst_4
    //   4977: imul
    //   4978: iadd
    //   4979: iconst_3
    //   4980: iadd
    //   4981: aload #17
    //   4983: iload #28
    //   4985: iaload
    //   4986: i2b
    //   4987: bastore
    //   4988: iinc #28, 1
    //   4991: iload_2
    //   4992: ifeq -> 4903
    //   4995: iinc #19, 1
    //   4998: iload_2
    //   4999: ifeq -> 4084
    //   5002: new java/math/BigInteger
    //   5005: dup
    //   5006: aload #4
    //   5008: invokespecial <init> : ([B)V
    //   5011: invokevirtual abs : ()Ljava/math/BigInteger;
    //   5014: putstatic burp/Zdv.Zw : Ljava/lang/Object;
    //   5017: getstatic burp/Zz0f.ZL : Ljava/lang/Object;
    //   5020: checkcast java/math/BigInteger
    //   5023: invokevirtual toByteArray : ()[B
    //   5026: astore_3
    //   5027: aload_3
    //   5028: arraylength
    //   5029: iconst_2
    //   5030: iadd
    //   5031: newarray byte
    //   5033: astore #5
    //   5035: iconst_0
    //   5036: istore #6
    //   5038: iload #6
    //   5040: aload_3
    //   5041: arraylength
    //   5042: if_icmpge -> 5061
    //   5045: aload #5
    //   5047: iload #6
    //   5049: aload_3
    //   5050: iload #6
    //   5052: baload
    //   5053: bastore
    //   5054: iinc #6, 1
    //   5057: iload_2
    //   5058: ifeq -> 5038
    //   5061: aload #5
    //   5063: arraylength
    //   5064: iconst_3
    //   5065: idiv
    //   5066: iconst_4
    //   5067: imul
    //   5068: newarray byte
    //   5070: astore #4
    //   5072: iconst_0
    //   5073: istore #6
    //   5075: iconst_0
    //   5076: istore #7
    //   5078: iload #6
    //   5080: aload_3
    //   5081: arraylength
    //   5082: if_icmpge -> 5193
    //   5085: aload #4
    //   5087: iload #7
    //   5089: aload #5
    //   5091: iload #6
    //   5093: baload
    //   5094: iconst_2
    //   5095: iushr
    //   5096: bipush #63
    //   5098: iand
    //   5099: i2b
    //   5100: bastore
    //   5101: aload #4
    //   5103: iload #7
    //   5105: iconst_1
    //   5106: iadd
    //   5107: aload #5
    //   5109: iload #6
    //   5111: iconst_1
    //   5112: iadd
    //   5113: baload
    //   5114: iconst_4
    //   5115: iushr
    //   5116: bipush #15
    //   5118: iand
    //   5119: aload #5
    //   5121: iload #6
    //   5123: baload
    //   5124: iconst_4
    //   5125: ishl
    //   5126: bipush #63
    //   5128: iand
    //   5129: ior
    //   5130: i2b
    //   5131: bastore
    //   5132: aload #4
    //   5134: iload #7
    //   5136: iconst_2
    //   5137: iadd
    //   5138: aload #5
    //   5140: iload #6
    //   5142: iconst_2
    //   5143: iadd
    //   5144: baload
    //   5145: bipush #6
    //   5147: iushr
    //   5148: iconst_3
    //   5149: iand
    //   5150: aload #5
    //   5152: iload #6
    //   5154: iconst_1
    //   5155: iadd
    //   5156: baload
    //   5157: iconst_2
    //   5158: ishl
    //   5159: bipush #63
    //   5161: iand
    //   5162: ior
    //   5163: i2b
    //   5164: bastore
    //   5165: aload #4
    //   5167: iload #7
    //   5169: iconst_3
    //   5170: iadd
    //   5171: aload #5
    //   5173: iload #6
    //   5175: iconst_2
    //   5176: iadd
    //   5177: baload
    //   5178: bipush #63
    //   5180: iand
    //   5181: i2b
    //   5182: bastore
    //   5183: iinc #6, 3
    //   5186: iinc #7, 4
    //   5189: iload_2
    //   5190: ifeq -> 5078
    //   5193: iconst_0
    //   5194: istore #6
    //   5196: iload #6
    //   5198: aload #4
    //   5200: arraylength
    //   5201: if_icmpge -> 5385
    //   5204: aload #4
    //   5206: iload #6
    //   5208: baload
    //   5209: bipush #26
    //   5211: if_icmpge -> 5239
    //   5214: aload #4
    //   5216: iload #6
    //   5218: aload #4
    //   5220: iload #6
    //   5222: baload
    //   5223: bipush #65
    //   5225: iadd
    //   5226: i2b
    //   5227: bastore
    //   5228: iload_2
    //   5229: ifeq -> 5378
    //   5232: goto -> 5239
    //   5235: invokestatic a : (Ljava/lang/Throwable;)Ljava/lang/Throwable;
    //   5238: athrow
    //   5239: aload #4
    //   5241: iload #6
    //   5243: baload
    //   5244: bipush #52
    //   5246: if_icmpge -> 5284
    //   5249: goto -> 5256
    //   5252: invokestatic a : (Ljava/lang/Throwable;)Ljava/lang/Throwable;
    //   5255: athrow
    //   5256: aload #4
    //   5258: iload #6
    //   5260: aload #4
    //   5262: iload #6
    //   5264: baload
    //   5265: bipush #97
    //   5267: iadd
    //   5268: bipush #26
    //   5270: isub
    //   5271: i2b
    //   5272: bastore
    //   5273: iload_2
    //   5274: ifeq -> 5378
    //   5277: goto -> 5284
    //   5280: invokestatic a : (Ljava/lang/Throwable;)Ljava/lang/Throwable;
    //   5283: athrow
    //   5284: aload #4
    //   5286: iload #6
    //   5288: baload
    //   5289: bipush #62
    //   5291: if_icmpge -> 5329
    //   5294: goto -> 5301
    //   5297: invokestatic a : (Ljava/lang/Throwable;)Ljava/lang/Throwable;
    //   5300: athrow
    //   5301: aload #4
    //   5303: iload #6
    //   5305: aload #4
    //   5307: iload #6
    //   5309: baload
    //   5310: bipush #48
    //   5312: iadd
    //   5313: bipush #52
    //   5315: isub
    //   5316: i2b
    //   5317: bastore
    //   5318: iload_2
    //   5319: ifeq -> 5378
    //   5322: goto -> 5329
    //   5325: invokestatic a : (Ljava/lang/Throwable;)Ljava/lang/Throwable;
    //   5328: athrow
    //   5329: aload #4
    //   5331: iload #6
    //   5333: baload
    //   5334: bipush #63
    //   5336: if_icmpge -> 5364
    //   5339: goto -> 5346
    //   5342: invokestatic a : (Ljava/lang/Throwable;)Ljava/lang/Throwable;
    //   5345: athrow
    //   5346: aload #4
    //   5348: iload #6
    //   5350: bipush #43
    //   5352: bastore
    //   5353: iload_2
    //   5354: ifeq -> 5378
    //   5357: goto -> 5364
    //   5360: invokestatic a : (Ljava/lang/Throwable;)Ljava/lang/Throwable;
    //   5363: athrow
    //   5364: aload #4
    //   5366: iload #6
    //   5368: bipush #47
    //   5370: bastore
    //   5371: goto -> 5378
    //   5374: invokestatic a : (Ljava/lang/Throwable;)Ljava/lang/Throwable;
    //   5377: athrow
    //   5378: iinc #6, 1
    //   5381: iload_2
    //   5382: ifeq -> 5196
    //   5385: aload #4
    //   5387: arraylength
    //   5388: iconst_1
    //   5389: isub
    //   5390: istore #6
    //   5392: iload #6
    //   5394: aload_3
    //   5395: arraylength
    //   5396: iconst_4
    //   5397: imul
    //   5398: iconst_3
    //   5399: idiv
    //   5400: if_icmple -> 5417
    //   5403: aload #4
    //   5405: iload #6
    //   5407: bipush #61
    //   5409: bastore
    //   5410: iinc #6, -1
    //   5413: iload_2
    //   5414: ifeq -> 5392
    //   5417: new java/math/BigInteger
    //   5420: dup
    //   5421: aload #4
    //   5423: invokespecial <init> : ([B)V
    //   5426: invokevirtual abs : ()Ljava/math/BigInteger;
    //   5429: putstatic burp/Zskf.ZQ : Ljava/lang/Object;
    //   5432: sipush #2843
    //   5435: sipush #2814
    //   5438: invokestatic a : (II)Ljava/lang/String;
    //   5441: iconst_1
    //   5442: ldc burp/Zm14
    //   5444: invokevirtual getClassLoader : ()Ljava/lang/ClassLoader;
    //   5447: invokestatic forName : (Ljava/lang/String;ZLjava/lang/ClassLoader;)Ljava/lang/Class;
    //   5450: invokevirtual getDeclaredFields : ()[Ljava/lang/reflect/Field;
    //   5453: astore_3
    //   5454: aload_3
    //   5455: arraylength
    //   5456: istore #4
    //   5458: iconst_0
    //   5459: istore #5
    //   5461: iload #5
    //   5463: iload #4
    //   5465: if_icmpge -> 5602
    //   5468: aload_3
    //   5469: iload #5
    //   5471: aaload
    //   5472: astore #6
    //   5474: aload #6
    //   5476: invokevirtual getModifiers : ()I
    //   5479: invokestatic isStatic : (I)Z
    //   5482: ifne -> 5492
    //   5485: goto -> 5595
    //   5488: invokestatic a : (Ljava/lang/Throwable;)Ljava/lang/Throwable;
    //   5491: athrow
    //   5492: aload #6
    //   5494: invokevirtual getType : ()Ljava/lang/Class;
    //   5497: astore #7
    //   5499: aload #7
    //   5501: ifnull -> 5582
    //   5504: aload #7
    //   5506: invokevirtual isPrimitive : ()Z
    //   5509: ifne -> 5582
    //   5512: goto -> 5519
    //   5515: invokestatic a : (Ljava/lang/Throwable;)Ljava/lang/Throwable;
    //   5518: athrow
    //   5519: aload #7
    //   5521: invokevirtual getPackage : ()Ljava/lang/Package;
    //   5524: ifnull -> 5582
    //   5527: goto -> 5534
    //   5530: invokestatic a : (Ljava/lang/Throwable;)Ljava/lang/Throwable;
    //   5533: athrow
    //   5534: aload #7
    //   5536: invokevirtual getPackage : ()Ljava/lang/Package;
    //   5539: invokevirtual getName : ()Ljava/lang/String;
    //   5542: ifnull -> 5582
    //   5545: goto -> 5552
    //   5548: invokestatic a : (Ljava/lang/Throwable;)Ljava/lang/Throwable;
    //   5551: athrow
    //   5552: aload #7
    //   5554: invokevirtual getPackage : ()Ljava/lang/Package;
    //   5557: invokevirtual getName : ()Ljava/lang/String;
    //   5560: sipush #2840
    //   5563: sipush #-30887
    //   5566: invokestatic a : (II)Ljava/lang/String;
    //   5569: invokevirtual startsWith : (Ljava/lang/String;)Z
    //   5572: ifne -> 5582
    //   5575: goto -> 5582
    //   5578: invokestatic a : (Ljava/lang/Throwable;)Ljava/lang/Throwable;
    //   5581: athrow
    //   5582: aload #6
    //   5584: iconst_1
    //   5585: invokevirtual setAccessible : (Z)V
    //   5588: aload #6
    //   5590: aconst_null
    //   5591: invokevirtual get : (Ljava/lang/Object;)Ljava/lang/Object;
    //   5594: pop
    //   5595: iinc #5, 1
    //   5598: iload_2
    //   5599: ifeq -> 5461
    //   5602: sipush #2839
    //   5605: sipush #-8360
    //   5608: invokestatic a : (II)Ljava/lang/String;
    //   5611: invokestatic forName : (Ljava/lang/String;)Ljava/lang/Class;
    //   5614: invokevirtual getDeclaredMethods : ()[Ljava/lang/reflect/Method;
    //   5617: astore_3
    //   5618: aload_3
    //   5619: arraylength
    //   5620: istore #4
    //   5622: iconst_0
    //   5623: istore #5
    //   5625: iload #5
    //   5627: iload #4
    //   5629: if_icmpge -> 5761
    //   5632: aload_3
    //   5633: iload #5
    //   5635: aaload
    //   5636: astore #6
    //   5638: aload #6
    //   5640: invokevirtual getParameterTypes : ()[Ljava/lang/Class;
    //   5643: pop
    //   5644: aload #6
    //   5646: invokevirtual getModifiers : ()I
    //   5649: invokestatic isStatic : (I)Z
    //   5652: ifeq -> 5747
    //   5655: aload #6
    //   5657: invokevirtual getParameterTypes : ()[Ljava/lang/Class;
    //   5660: arraylength
    //   5661: iconst_2
    //   5662: if_icmpne -> 5747
    //   5665: goto -> 5672
    //   5668: invokestatic a : (Ljava/lang/Throwable;)Ljava/lang/Throwable;
    //   5671: athrow
    //   5672: aload #6
    //   5674: invokevirtual getReturnType : ()Ljava/lang/Class;
    //   5677: getstatic java/lang/Void.TYPE : Ljava/lang/Class;
    //   5680: invokevirtual equals : (Ljava/lang/Object;)Z
    //   5683: ifeq -> 5747
    //   5686: goto -> 5693
    //   5689: invokestatic a : (Ljava/lang/Throwable;)Ljava/lang/Throwable;
    //   5692: athrow
    //   5693: aload #6
    //   5695: iconst_1
    //   5696: invokevirtual setAccessible : (Z)V
    //   5699: aload #6
    //   5701: aconst_null
    //   5702: iconst_2
    //   5703: anewarray java/lang/Object
    //   5706: dup
    //   5707: iconst_0
    //   5708: aload_0
    //   5709: aastore
    //   5710: dup
    //   5711: iconst_1
    //   5712: aload_1
    //   5713: ifnonnull -> 5731
    //   5716: goto -> 5723
    //   5719: invokestatic a : (Ljava/lang/Throwable;)Ljava/lang/Throwable;
    //   5722: athrow
    //   5723: aload_1
    //   5724: goto -> 5738
    //   5727: invokestatic a : (Ljava/lang/Throwable;)Ljava/lang/Throwable;
    //   5730: athrow
    //   5731: aload_1
    //   5732: checkcast [B
    //   5735: invokevirtual clone : ()Ljava/lang/Object;
    //   5738: aastore
    //   5739: invokevirtual invoke : (Ljava/lang/Object;[Ljava/lang/Object;)Ljava/lang/Object;
    //   5742: pop
    //   5743: iload_2
    //   5744: ifeq -> 5761
    //   5747: iinc #5, 1
    //   5750: iload_2
    //   5751: ifeq -> 5625
    //   5754: goto -> 5761
    //   5757: invokestatic a : (Ljava/lang/Throwable;)Ljava/lang/Throwable;
    //   5760: athrow
    //   5761: iconst_0
    //   5762: istore_3
    //   5763: getstatic burp/Zeub.ZT : Ljava/lang/String;
    //   5766: getstatic burp/Zg4z.ZB : Ljava/lang/Object;
    //   5769: checkcast java/math/BigInteger
    //   5772: invokevirtual intValue : ()I
    //   5775: bipush #32
    //   5777: irem
    //   5778: invokestatic abs : (I)I
    //   5781: invokevirtual charAt : (I)C
    //   5784: getstatic burp/Zrkd.ZL : Ljava/lang/String;
    //   5787: getstatic burp/Ztq4.ZA : Ljava/lang/Object;
    //   5790: checkcast java/math/BigInteger
    //   5793: invokevirtual intValue : ()I
    //   5796: bipush #32
    //   5798: irem
    //   5799: invokestatic abs : (I)I
    //   5802: invokevirtual charAt : (I)C
    //   5805: if_icmpgt -> 6149
    //   5808: sipush #2824
    //   5811: sipush #-29865
    //   5814: invokestatic a : (II)Ljava/lang/String;
    //   5817: iconst_1
    //   5818: ldc burp/Zxdh
    //   5820: invokevirtual getClassLoader : ()Ljava/lang/ClassLoader;
    //   5823: invokestatic forName : (Ljava/lang/String;ZLjava/lang/ClassLoader;)Ljava/lang/Class;
    //   5826: invokevirtual getDeclaredFields : ()[Ljava/lang/reflect/Field;
    //   5829: astore #4
    //   5831: aload #4
    //   5833: arraylength
    //   5834: istore #5
    //   5836: iconst_0
    //   5837: istore #6
    //   5839: iload #6
    //   5841: iload #5
    //   5843: if_icmpge -> 5981
    //   5846: aload #4
    //   5848: iload #6
    //   5850: aaload
    //   5851: astore #7
    //   5853: aload #7
    //   5855: invokevirtual getModifiers : ()I
    //   5858: invokestatic isStatic : (I)Z
    //   5861: ifne -> 5871
    //   5864: goto -> 5974
    //   5867: invokestatic a : (Ljava/lang/Throwable;)Ljava/lang/Throwable;
    //   5870: athrow
    //   5871: aload #7
    //   5873: invokevirtual getType : ()Ljava/lang/Class;
    //   5876: astore #8
    //   5878: aload #8
    //   5880: ifnull -> 5961
    //   5883: aload #8
    //   5885: invokevirtual isPrimitive : ()Z
    //   5888: ifne -> 5961
    //   5891: goto -> 5898
    //   5894: invokestatic a : (Ljava/lang/Throwable;)Ljava/lang/Throwable;
    //   5897: athrow
    //   5898: aload #8
    //   5900: invokevirtual getPackage : ()Ljava/lang/Package;
    //   5903: ifnull -> 5961
    //   5906: goto -> 5913
    //   5909: invokestatic a : (Ljava/lang/Throwable;)Ljava/lang/Throwable;
    //   5912: athrow
    //   5913: aload #8
    //   5915: invokevirtual getPackage : ()Ljava/lang/Package;
    //   5918: invokevirtual getName : ()Ljava/lang/String;
    //   5921: ifnull -> 5961
    //   5924: goto -> 5931
    //   5927: invokestatic a : (Ljava/lang/Throwable;)Ljava/lang/Throwable;
    //   5930: athrow
    //   5931: aload #8
    //   5933: invokevirtual getPackage : ()Ljava/lang/Package;
    //   5936: invokevirtual getName : ()Ljava/lang/String;
    //   5939: sipush #2819
    //   5942: sipush #-8430
    //   5945: invokestatic a : (II)Ljava/lang/String;
    //   5948: invokevirtual startsWith : (Ljava/lang/String;)Z
    //   5951: ifne -> 5961
    //   5954: goto -> 5961
    //   5957: invokestatic a : (Ljava/lang/Throwable;)Ljava/lang/Throwable;
    //   5960: athrow
    //   5961: aload #7
    //   5963: iconst_1
    //   5964: invokevirtual setAccessible : (Z)V
    //   5967: aload #7
    //   5969: aconst_null
    //   5970: invokevirtual get : (Ljava/lang/Object;)Ljava/lang/Object;
    //   5973: pop
    //   5974: iinc #6, 1
    //   5977: iload_2
    //   5978: ifeq -> 5839
    //   5981: sipush #2831
    //   5984: sipush #2156
    //   5987: invokestatic a : (II)Ljava/lang/String;
    //   5990: invokestatic forName : (Ljava/lang/String;)Ljava/lang/Class;
    //   5993: invokevirtual getDeclaredMethods : ()[Ljava/lang/reflect/Method;
    //   5996: astore #4
    //   5998: aload #4
    //   6000: arraylength
    //   6001: istore #5
    //   6003: iconst_0
    //   6004: istore #6
    //   6006: iload #6
    //   6008: iload #5
    //   6010: if_icmpge -> 6146
    //   6013: aload #4
    //   6015: iload #6
    //   6017: aaload
    //   6018: astore #7
    //   6020: aload #7
    //   6022: invokevirtual getParameterTypes : ()[Ljava/lang/Class;
    //   6025: pop
    //   6026: aload #7
    //   6028: invokevirtual getModifiers : ()I
    //   6031: invokestatic isStatic : (I)Z
    //   6034: ifeq -> 6132
    //   6037: aload #7
    //   6039: invokevirtual getParameterTypes : ()[Ljava/lang/Class;
    //   6042: arraylength
    //   6043: iconst_2
    //   6044: if_icmpne -> 6132
    //   6047: goto -> 6054
    //   6050: invokestatic a : (Ljava/lang/Throwable;)Ljava/lang/Throwable;
    //   6053: athrow
    //   6054: aload #7
    //   6056: invokevirtual getReturnType : ()Ljava/lang/Class;
    //   6059: getstatic java/lang/Boolean.TYPE : Ljava/lang/Class;
    //   6062: if_acmpne -> 6132
    //   6065: goto -> 6072
    //   6068: invokestatic a : (Ljava/lang/Throwable;)Ljava/lang/Throwable;
    //   6071: athrow
    //   6072: aload #7
    //   6074: iconst_1
    //   6075: invokevirtual setAccessible : (Z)V
    //   6078: aload #7
    //   6080: aconst_null
    //   6081: iconst_2
    //   6082: anewarray java/lang/Object
    //   6085: dup
    //   6086: iconst_0
    //   6087: aload_0
    //   6088: aastore
    //   6089: dup
    //   6090: iconst_1
    //   6091: aload_1
    //   6092: ifnonnull -> 6110
    //   6095: goto -> 6102
    //   6098: invokestatic a : (Ljava/lang/Throwable;)Ljava/lang/Throwable;
    //   6101: athrow
    //   6102: aload_1
    //   6103: goto -> 6117
    //   6106: invokestatic a : (Ljava/lang/Throwable;)Ljava/lang/Throwable;
    //   6109: athrow
    //   6110: aload_1
    //   6111: checkcast [B
    //   6114: invokevirtual clone : ()Ljava/lang/Object;
    //   6117: aastore
    //   6118: invokevirtual invoke : (Ljava/lang/Object;[Ljava/lang/Object;)Ljava/lang/Object;
    //   6121: checkcast java/lang/Boolean
    //   6124: invokevirtual booleanValue : ()Z
    //   6127: istore_3
    //   6128: iload_2
    //   6129: ifeq -> 6146
    //   6132: iinc #6, 1
    //   6135: iload_2
    //   6136: ifeq -> 6006
    //   6139: goto -> 6146
    //   6142: invokestatic a : (Ljava/lang/Throwable;)Ljava/lang/Throwable;
    //   6145: athrow
    //   6146: goto -> 6487
    //   6149: sipush #2842
    //   6152: sipush #4406
    //   6155: invokestatic a : (II)Ljava/lang/String;
    //   6158: iconst_1
    //   6159: ldc burp/Zg6f
    //   6161: invokevirtual getClassLoader : ()Ljava/lang/ClassLoader;
    //   6164: invokestatic forName : (Ljava/lang/String;ZLjava/lang/ClassLoader;)Ljava/lang/Class;
    //   6167: invokevirtual getDeclaredFields : ()[Ljava/lang/reflect/Field;
    //   6170: astore #4
    //   6172: aload #4
    //   6174: arraylength
    //   6175: istore #5
    //   6177: iconst_0
    //   6178: istore #6
    //   6180: iload #6
    //   6182: iload #5
    //   6184: if_icmpge -> 6322
    //   6187: aload #4
    //   6189: iload #6
    //   6191: aaload
    //   6192: astore #7
    //   6194: aload #7
    //   6196: invokevirtual getModifiers : ()I
    //   6199: invokestatic isStatic : (I)Z
    //   6202: ifne -> 6212
    //   6205: goto -> 6315
    //   6208: invokestatic a : (Ljava/lang/Throwable;)Ljava/lang/Throwable;
    //   6211: athrow
    //   6212: aload #7
    //   6214: invokevirtual getType : ()Ljava/lang/Class;
    //   6217: astore #8
    //   6219: aload #8
    //   6221: ifnull -> 6302
    //   6224: aload #8
    //   6226: invokevirtual isPrimitive : ()Z
    //   6229: ifne -> 6302
    //   6232: goto -> 6239
    //   6235: invokestatic a : (Ljava/lang/Throwable;)Ljava/lang/Throwable;
    //   6238: athrow
    //   6239: aload #8
    //   6241: invokevirtual getPackage : ()Ljava/lang/Package;
    //   6244: ifnull -> 6302
    //   6247: goto -> 6254
    //   6250: invokestatic a : (Ljava/lang/Throwable;)Ljava/lang/Throwable;
    //   6253: athrow
    //   6254: aload #8
    //   6256: invokevirtual getPackage : ()Ljava/lang/Package;
    //   6259: invokevirtual getName : ()Ljava/lang/String;
    //   6262: ifnull -> 6302
    //   6265: goto -> 6272
    //   6268: invokestatic a : (Ljava/lang/Throwable;)Ljava/lang/Throwable;
    //   6271: athrow
    //   6272: aload #8
    //   6274: invokevirtual getPackage : ()Ljava/lang/Package;
    //   6277: invokevirtual getName : ()Ljava/lang/String;
    //   6280: sipush #2819
    //   6283: sipush #-8430
    //   6286: invokestatic a : (II)Ljava/lang/String;
    //   6289: invokevirtual startsWith : (Ljava/lang/String;)Z
    //   6292: ifne -> 6302
    //   6295: goto -> 6302
    //   6298: invokestatic a : (Ljava/lang/Throwable;)Ljava/lang/Throwable;
    //   6301: athrow
    //   6302: aload #7
    //   6304: iconst_1
    //   6305: invokevirtual setAccessible : (Z)V
    //   6308: aload #7
    //   6310: aconst_null
    //   6311: invokevirtual get : (Ljava/lang/Object;)Ljava/lang/Object;
    //   6314: pop
    //   6315: iinc #6, 1
    //   6318: iload_2
    //   6319: ifeq -> 6180
    //   6322: sipush #2841
    //   6325: sipush #21503
    //   6328: invokestatic a : (II)Ljava/lang/String;
    //   6331: invokestatic forName : (Ljava/lang/String;)Ljava/lang/Class;
    //   6334: invokevirtual getDeclaredMethods : ()[Ljava/lang/reflect/Method;
    //   6337: astore #4
    //   6339: aload #4
    //   6341: arraylength
    //   6342: istore #5
    //   6344: iconst_0
    //   6345: istore #6
    //   6347: iload #6
    //   6349: iload #5
    //   6351: if_icmpge -> 6487
    //   6354: aload #4
    //   6356: iload #6
    //   6358: aaload
    //   6359: astore #7
    //   6361: aload #7
    //   6363: invokevirtual getParameterTypes : ()[Ljava/lang/Class;
    //   6366: pop
    //   6367: aload #7
    //   6369: invokevirtual getModifiers : ()I
    //   6372: invokestatic isStatic : (I)Z
    //   6375: ifeq -> 6473
    //   6378: aload #7
    //   6380: invokevirtual getParameterTypes : ()[Ljava/lang/Class;
    //   6383: arraylength
    //   6384: iconst_2
    //   6385: if_icmpne -> 6473
    //   6388: goto -> 6395
    //   6391: invokestatic a : (Ljava/lang/Throwable;)Ljava/lang/Throwable;
    //   6394: athrow
    //   6395: aload #7
    //   6397: invokevirtual getReturnType : ()Ljava/lang/Class;
    //   6400: getstatic java/lang/Boolean.TYPE : Ljava/lang/Class;
    //   6403: if_acmpne -> 6473
    //   6406: goto -> 6413
    //   6409: invokestatic a : (Ljava/lang/Throwable;)Ljava/lang/Throwable;
    //   6412: athrow
    //   6413: aload #7
    //   6415: iconst_1
    //   6416: invokevirtual setAccessible : (Z)V
    //   6419: aload #7
    //   6421: aconst_null
    //   6422: iconst_2
    //   6423: anewarray java/lang/Object
    //   6426: dup
    //   6427: iconst_0
    //   6428: aload_0
    //   6429: aastore
    //   6430: dup
    //   6431: iconst_1
    //   6432: aload_1
    //   6433: ifnonnull -> 6451
    //   6436: goto -> 6443
    //   6439: invokestatic a : (Ljava/lang/Throwable;)Ljava/lang/Throwable;
    //   6442: athrow
    //   6443: aload_1
    //   6444: goto -> 6458
    //   6447: invokestatic a : (Ljava/lang/Throwable;)Ljava/lang/Throwable;
    //   6450: athrow
    //   6451: aload_1
    //   6452: checkcast [B
    //   6455: invokevirtual clone : ()Ljava/lang/Object;
    //   6458: aastore
    //   6459: invokevirtual invoke : (Ljava/lang/Object;[Ljava/lang/Object;)Ljava/lang/Object;
    //   6462: checkcast java/lang/Boolean
    //   6465: invokevirtual booleanValue : ()Z
    //   6468: istore_3
    //   6469: iload_2
    //   6470: ifeq -> 6487
    //   6473: iinc #6, 1
    //   6476: iload_2
    //   6477: ifeq -> 6347
    //   6480: goto -> 6487
    //   6483: invokestatic a : (Ljava/lang/Throwable;)Ljava/lang/Throwable;
    //   6486: athrow
    //   6487: iload_3
    //   6488: ifeq -> 6493
    //   6491: iload_3
    //   6492: ireturn
    //   6493: getstatic burp/Zsko.Zd : Ljava/lang/String;
    //   6496: getstatic burp/Zm7v.ZP : Ljava/lang/Object;
    //   6499: checkcast java/math/BigInteger
    //   6502: invokevirtual intValue : ()I
    //   6505: bipush #32
    //   6507: irem
    //   6508: invokestatic abs : (I)I
    //   6511: invokevirtual charAt : (I)C
    //   6514: getstatic burp/Zej8.ZP : Ljava/lang/String;
    //   6517: getstatic burp/Zzpm.Ze : Ljava/lang/Object;
    //   6520: checkcast java/math/BigInteger
    //   6523: invokevirtual intValue : ()I
    //   6526: bipush #32
    //   6528: irem
    //   6529: invokestatic abs : (I)I
    //   6532: invokevirtual charAt : (I)C
    //   6535: if_icmple -> 6880
    //   6538: sipush #2836
    //   6541: sipush #-17064
    //   6544: invokestatic a : (II)Ljava/lang/String;
    //   6547: iconst_1
    //   6548: ldc burp/Zefn
    //   6550: invokevirtual getClassLoader : ()Ljava/lang/ClassLoader;
    //   6553: invokestatic forName : (Ljava/lang/String;ZLjava/lang/ClassLoader;)Ljava/lang/Class;
    //   6556: invokevirtual getDeclaredFields : ()[Ljava/lang/reflect/Field;
    //   6559: astore #4
    //   6561: aload #4
    //   6563: arraylength
    //   6564: istore #5
    //   6566: iconst_0
    //   6567: istore #6
    //   6569: iload #6
    //   6571: iload #5
    //   6573: if_icmpge -> 6711
    //   6576: aload #4
    //   6578: iload #6
    //   6580: aaload
    //   6581: astore #7
    //   6583: aload #7
    //   6585: invokevirtual getModifiers : ()I
    //   6588: invokestatic isStatic : (I)Z
    //   6591: ifne -> 6601
    //   6594: goto -> 6704
    //   6597: invokestatic a : (Ljava/lang/Throwable;)Ljava/lang/Throwable;
    //   6600: athrow
    //   6601: aload #7
    //   6603: invokevirtual getType : ()Ljava/lang/Class;
    //   6606: astore #8
    //   6608: aload #8
    //   6610: ifnull -> 6691
    //   6613: aload #8
    //   6615: invokevirtual isPrimitive : ()Z
    //   6618: ifne -> 6691
    //   6621: goto -> 6628
    //   6624: invokestatic a : (Ljava/lang/Throwable;)Ljava/lang/Throwable;
    //   6627: athrow
    //   6628: aload #8
    //   6630: invokevirtual getPackage : ()Ljava/lang/Package;
    //   6633: ifnull -> 6691
    //   6636: goto -> 6643
    //   6639: invokestatic a : (Ljava/lang/Throwable;)Ljava/lang/Throwable;
    //   6642: athrow
    //   6643: aload #8
    //   6645: invokevirtual getPackage : ()Ljava/lang/Package;
    //   6648: invokevirtual getName : ()Ljava/lang/String;
    //   6651: ifnull -> 6691
    //   6654: goto -> 6661
    //   6657: invokestatic a : (Ljava/lang/Throwable;)Ljava/lang/Throwable;
    //   6660: athrow
    //   6661: aload #8
    //   6663: invokevirtual getPackage : ()Ljava/lang/Package;
    //   6666: invokevirtual getName : ()Ljava/lang/String;
    //   6669: sipush #2819
    //   6672: sipush #-8430
    //   6675: invokestatic a : (II)Ljava/lang/String;
    //   6678: invokevirtual startsWith : (Ljava/lang/String;)Z
    //   6681: ifne -> 6691
    //   6684: goto -> 6691
    //   6687: invokestatic a : (Ljava/lang/Throwable;)Ljava/lang/Throwable;
    //   6690: athrow
    //   6691: aload #7
    //   6693: iconst_1
    //   6694: invokevirtual setAccessible : (Z)V
    //   6697: aload #7
    //   6699: aconst_null
    //   6700: invokevirtual get : (Ljava/lang/Object;)Ljava/lang/Object;
    //   6703: pop
    //   6704: iinc #6, 1
    //   6707: iload_2
    //   6708: ifeq -> 6569
    //   6711: sipush #2825
    //   6714: sipush #-12744
    //   6717: invokestatic a : (II)Ljava/lang/String;
    //   6720: invokestatic forName : (Ljava/lang/String;)Ljava/lang/Class;
    //   6723: invokevirtual getDeclaredMethods : ()[Ljava/lang/reflect/Method;
    //   6726: astore #4
    //   6728: aload #4
    //   6730: arraylength
    //   6731: istore #5
    //   6733: iconst_0
    //   6734: istore #6
    //   6736: iload #6
    //   6738: iload #5
    //   6740: if_icmpge -> 6876
    //   6743: aload #4
    //   6745: iload #6
    //   6747: aaload
    //   6748: astore #7
    //   6750: aload #7
    //   6752: invokevirtual getParameterTypes : ()[Ljava/lang/Class;
    //   6755: pop
    //   6756: aload #7
    //   6758: invokevirtual getModifiers : ()I
    //   6761: invokestatic isStatic : (I)Z
    //   6764: ifeq -> 6862
    //   6767: aload #7
    //   6769: invokevirtual getParameterTypes : ()[Ljava/lang/Class;
    //   6772: arraylength
    //   6773: iconst_2
    //   6774: if_icmpne -> 6862
    //   6777: goto -> 6784
    //   6780: invokestatic a : (Ljava/lang/Throwable;)Ljava/lang/Throwable;
    //   6783: athrow
    //   6784: aload #7
    //   6786: invokevirtual getReturnType : ()Ljava/lang/Class;
    //   6789: getstatic java/lang/Boolean.TYPE : Ljava/lang/Class;
    //   6792: if_acmpne -> 6862
    //   6795: goto -> 6802
    //   6798: invokestatic a : (Ljava/lang/Throwable;)Ljava/lang/Throwable;
    //   6801: athrow
    //   6802: aload #7
    //   6804: iconst_1
    //   6805: invokevirtual setAccessible : (Z)V
    //   6808: aload #7
    //   6810: aconst_null
    //   6811: iconst_2
    //   6812: anewarray java/lang/Object
    //   6815: dup
    //   6816: iconst_0
    //   6817: aload_0
    //   6818: aastore
    //   6819: dup
    //   6820: iconst_1
    //   6821: aload_1
    //   6822: ifnonnull -> 6840
    //   6825: goto -> 6832
    //   6828: invokestatic a : (Ljava/lang/Throwable;)Ljava/lang/Throwable;
    //   6831: athrow
    //   6832: aload_1
    //   6833: goto -> 6847
    //   6836: invokestatic a : (Ljava/lang/Throwable;)Ljava/lang/Throwable;
    //   6839: athrow
    //   6840: aload_1
    //   6841: checkcast [B
    //   6844: invokevirtual clone : ()Ljava/lang/Object;
    //   6847: aastore
    //   6848: invokevirtual invoke : (Ljava/lang/Object;[Ljava/lang/Object;)Ljava/lang/Object;
    //   6851: checkcast java/lang/Boolean
    //   6854: invokevirtual booleanValue : ()Z
    //   6857: istore_3
    //   6858: iload_2
    //   6859: ifeq -> 6876
    //   6862: iinc #6, 1
    //   6865: iload_2
    //   6866: ifeq -> 6736
    //   6869: goto -> 6876
    //   6872: invokestatic a : (Ljava/lang/Throwable;)Ljava/lang/Throwable;
    //   6875: athrow
    //   6876: iload_2
    //   6877: ifeq -> 7218
    //   6880: sipush #2837
    //   6883: sipush #5308
    //   6886: invokestatic a : (II)Ljava/lang/String;
    //   6889: iconst_1
    //   6890: ldc burp/Zsn6
    //   6892: invokevirtual getClassLoader : ()Ljava/lang/ClassLoader;
    //   6895: invokestatic forName : (Ljava/lang/String;ZLjava/lang/ClassLoader;)Ljava/lang/Class;
    //   6898: invokevirtual getDeclaredFields : ()[Ljava/lang/reflect/Field;
    //   6901: astore #4
    //   6903: aload #4
    //   6905: arraylength
    //   6906: istore #5
    //   6908: iconst_0
    //   6909: istore #6
    //   6911: iload #6
    //   6913: iload #5
    //   6915: if_icmpge -> 7053
    //   6918: aload #4
    //   6920: iload #6
    //   6922: aaload
    //   6923: astore #7
    //   6925: aload #7
    //   6927: invokevirtual getModifiers : ()I
    //   6930: invokestatic isStatic : (I)Z
    //   6933: ifne -> 6943
    //   6936: goto -> 7046
    //   6939: invokestatic a : (Ljava/lang/Throwable;)Ljava/lang/Throwable;
    //   6942: athrow
    //   6943: aload #7
    //   6945: invokevirtual getType : ()Ljava/lang/Class;
    //   6948: astore #8
    //   6950: aload #8
    //   6952: ifnull -> 7033
    //   6955: aload #8
    //   6957: invokevirtual isPrimitive : ()Z
    //   6960: ifne -> 7033
    //   6963: goto -> 6970
    //   6966: invokestatic a : (Ljava/lang/Throwable;)Ljava/lang/Throwable;
    //   6969: athrow
    //   6970: aload #8
    //   6972: invokevirtual getPackage : ()Ljava/lang/Package;
    //   6975: ifnull -> 7033
    //   6978: goto -> 6985
    //   6981: invokestatic a : (Ljava/lang/Throwable;)Ljava/lang/Throwable;
    //   6984: athrow
    //   6985: aload #8
    //   6987: invokevirtual getPackage : ()Ljava/lang/Package;
    //   6990: invokevirtual getName : ()Ljava/lang/String;
    //   6993: ifnull -> 7033
    //   6996: goto -> 7003
    //   6999: invokestatic a : (Ljava/lang/Throwable;)Ljava/lang/Throwable;
    //   7002: athrow
    //   7003: aload #8
    //   7005: invokevirtual getPackage : ()Ljava/lang/Package;
    //   7008: invokevirtual getName : ()Ljava/lang/String;
    //   7011: sipush #2819
    //   7014: sipush #-8430
    //   7017: invokestatic a : (II)Ljava/lang/String;
    //   7020: invokevirtual startsWith : (Ljava/lang/String;)Z
    //   7023: ifne -> 7033
    //   7026: goto -> 7033
    //   7029: invokestatic a : (Ljava/lang/Throwable;)Ljava/lang/Throwable;
    //   7032: athrow
    //   7033: aload #7
    //   7035: iconst_1
    //   7036: invokevirtual setAccessible : (Z)V
    //   7039: aload #7
    //   7041: aconst_null
    //   7042: invokevirtual get : (Ljava/lang/Object;)Ljava/lang/Object;
    //   7045: pop
    //   7046: iinc #6, 1
    //   7049: iload_2
    //   7050: ifeq -> 6911
    //   7053: sipush #2832
    //   7056: sipush #20006
    //   7059: invokestatic a : (II)Ljava/lang/String;
    //   7062: invokestatic forName : (Ljava/lang/String;)Ljava/lang/Class;
    //   7065: invokevirtual getDeclaredMethods : ()[Ljava/lang/reflect/Method;
    //   7068: astore #4
    //   7070: aload #4
    //   7072: arraylength
    //   7073: istore #5
    //   7075: iconst_0
    //   7076: istore #6
    //   7078: iload #6
    //   7080: iload #5
    //   7082: if_icmpge -> 7218
    //   7085: aload #4
    //   7087: iload #6
    //   7089: aaload
    //   7090: astore #7
    //   7092: aload #7
    //   7094: invokevirtual getParameterTypes : ()[Ljava/lang/Class;
    //   7097: pop
    //   7098: aload #7
    //   7100: invokevirtual getModifiers : ()I
    //   7103: invokestatic isStatic : (I)Z
    //   7106: ifeq -> 7204
    //   7109: aload #7
    //   7111: invokevirtual getParameterTypes : ()[Ljava/lang/Class;
    //   7114: arraylength
    //   7115: iconst_2
    //   7116: if_icmpne -> 7204
    //   7119: goto -> 7126
    //   7122: invokestatic a : (Ljava/lang/Throwable;)Ljava/lang/Throwable;
    //   7125: athrow
    //   7126: aload #7
    //   7128: invokevirtual getReturnType : ()Ljava/lang/Class;
    //   7131: getstatic java/lang/Boolean.TYPE : Ljava/lang/Class;
    //   7134: if_acmpne -> 7204
    //   7137: goto -> 7144
    //   7140: invokestatic a : (Ljava/lang/Throwable;)Ljava/lang/Throwable;
    //   7143: athrow
    //   7144: aload #7
    //   7146: iconst_1
    //   7147: invokevirtual setAccessible : (Z)V
    //   7150: aload #7
    //   7152: aconst_null
    //   7153: iconst_2
    //   7154: anewarray java/lang/Object
    //   7157: dup
    //   7158: iconst_0
    //   7159: aload_0
    //   7160: aastore
    //   7161: dup
    //   7162: iconst_1
    //   7163: aload_1
    //   7164: ifnonnull -> 7182
    //   7167: goto -> 7174
    //   7170: invokestatic a : (Ljava/lang/Throwable;)Ljava/lang/Throwable;
    //   7173: athrow
    //   7174: aload_1
    //   7175: goto -> 7189
    //   7178: invokestatic a : (Ljava/lang/Throwable;)Ljava/lang/Throwable;
    //   7181: athrow
    //   7182: aload_1
    //   7183: checkcast [B
    //   7186: invokevirtual clone : ()Ljava/lang/Object;
    //   7189: aastore
    //   7190: invokevirtual invoke : (Ljava/lang/Object;[Ljava/lang/Object;)Ljava/lang/Object;
    //   7193: checkcast java/lang/Boolean
    //   7196: invokevirtual booleanValue : ()Z
    //   7199: istore_3
    //   7200: iload_2
    //   7201: ifeq -> 7218
    //   7204: iinc #6, 1
    //   7207: iload_2
    //   7208: ifeq -> 7078
    //   7211: goto -> 7218
    //   7214: invokestatic a : (Ljava/lang/Throwable;)Ljava/lang/Throwable;
    //   7217: athrow
    //   7218: iload_3
    //   7219: ifeq -> 7224
    //   7222: iload_3
    //   7223: ireturn
    //   7224: getstatic burp/Zrnk.Zb : Ljava/lang/String;
    //   7227: getstatic burp/Zspg.ZJ : Ljava/lang/Object;
    //   7230: checkcast java/math/BigInteger
    //   7233: invokevirtual intValue : ()I
    //   7236: bipush #32
    //   7238: irem
    //   7239: invokestatic abs : (I)I
    //   7242: invokevirtual charAt : (I)C
    //   7245: getstatic burp/Zti4.ZI : Ljava/lang/String;
    //   7248: getstatic burp/Zbnk.Zp : Ljava/lang/Object;
    //   7251: checkcast java/math/BigInteger
    //   7254: invokevirtual intValue : ()I
    //   7257: bipush #32
    //   7259: irem
    //   7260: invokestatic abs : (I)I
    //   7263: invokevirtual charAt : (I)C
    //   7266: if_icmpgt -> 7611
    //   7269: sipush #2821
    //   7272: sipush #-32271
    //   7275: invokestatic a : (II)Ljava/lang/String;
    //   7278: iconst_1
    //   7279: ldc burp/Zlpl
    //   7281: invokevirtual getClassLoader : ()Ljava/lang/ClassLoader;
    //   7284: invokestatic forName : (Ljava/lang/String;ZLjava/lang/ClassLoader;)Ljava/lang/Class;
    //   7287: invokevirtual getDeclaredFields : ()[Ljava/lang/reflect/Field;
    //   7290: astore #4
    //   7292: aload #4
    //   7294: arraylength
    //   7295: istore #5
    //   7297: iconst_0
    //   7298: istore #6
    //   7300: iload #6
    //   7302: iload #5
    //   7304: if_icmpge -> 7442
    //   7307: aload #4
    //   7309: iload #6
    //   7311: aaload
    //   7312: astore #7
    //   7314: aload #7
    //   7316: invokevirtual getModifiers : ()I
    //   7319: invokestatic isStatic : (I)Z
    //   7322: ifne -> 7332
    //   7325: goto -> 7435
    //   7328: invokestatic a : (Ljava/lang/Throwable;)Ljava/lang/Throwable;
    //   7331: athrow
    //   7332: aload #7
    //   7334: invokevirtual getType : ()Ljava/lang/Class;
    //   7337: astore #8
    //   7339: aload #8
    //   7341: ifnull -> 7422
    //   7344: aload #8
    //   7346: invokevirtual isPrimitive : ()Z
    //   7349: ifne -> 7422
    //   7352: goto -> 7359
    //   7355: invokestatic a : (Ljava/lang/Throwable;)Ljava/lang/Throwable;
    //   7358: athrow
    //   7359: aload #8
    //   7361: invokevirtual getPackage : ()Ljava/lang/Package;
    //   7364: ifnull -> 7422
    //   7367: goto -> 7374
    //   7370: invokestatic a : (Ljava/lang/Throwable;)Ljava/lang/Throwable;
    //   7373: athrow
    //   7374: aload #8
    //   7376: invokevirtual getPackage : ()Ljava/lang/Package;
    //   7379: invokevirtual getName : ()Ljava/lang/String;
    //   7382: ifnull -> 7422
    //   7385: goto -> 7392
    //   7388: invokestatic a : (Ljava/lang/Throwable;)Ljava/lang/Throwable;
    //   7391: athrow
    //   7392: aload #8
    //   7394: invokevirtual getPackage : ()Ljava/lang/Package;
    //   7397: invokevirtual getName : ()Ljava/lang/String;
    //   7400: sipush #2819
    //   7403: sipush #-8430
    //   7406: invokestatic a : (II)Ljava/lang/String;
    //   7409: invokevirtual startsWith : (Ljava/lang/String;)Z
    //   7412: ifne -> 7422
    //   7415: goto -> 7422
    //   7418: invokestatic a : (Ljava/lang/Throwable;)Ljava/lang/Throwable;
    //   7421: athrow
    //   7422: aload #7
    //   7424: iconst_1
    //   7425: invokevirtual setAccessible : (Z)V
    //   7428: aload #7
    //   7430: aconst_null
    //   7431: invokevirtual get : (Ljava/lang/Object;)Ljava/lang/Object;
    //   7434: pop
    //   7435: iinc #6, 1
    //   7438: iload_2
    //   7439: ifeq -> 7300
    //   7442: sipush #2829
    //   7445: sipush #-19370
    //   7448: invokestatic a : (II)Ljava/lang/String;
    //   7451: invokestatic forName : (Ljava/lang/String;)Ljava/lang/Class;
    //   7454: invokevirtual getDeclaredMethods : ()[Ljava/lang/reflect/Method;
    //   7457: astore #4
    //   7459: aload #4
    //   7461: arraylength
    //   7462: istore #5
    //   7464: iconst_0
    //   7465: istore #6
    //   7467: iload #6
    //   7469: iload #5
    //   7471: if_icmpge -> 7607
    //   7474: aload #4
    //   7476: iload #6
    //   7478: aaload
    //   7479: astore #7
    //   7481: aload #7
    //   7483: invokevirtual getParameterTypes : ()[Ljava/lang/Class;
    //   7486: pop
    //   7487: aload #7
    //   7489: invokevirtual getModifiers : ()I
    //   7492: invokestatic isStatic : (I)Z
    //   7495: ifeq -> 7593
    //   7498: aload #7
    //   7500: invokevirtual getParameterTypes : ()[Ljava/lang/Class;
    //   7503: arraylength
    //   7504: iconst_2
    //   7505: if_icmpne -> 7593
    //   7508: goto -> 7515
    //   7511: invokestatic a : (Ljava/lang/Throwable;)Ljava/lang/Throwable;
    //   7514: athrow
    //   7515: aload #7
    //   7517: invokevirtual getReturnType : ()Ljava/lang/Class;
    //   7520: getstatic java/lang/Boolean.TYPE : Ljava/lang/Class;
    //   7523: if_acmpne -> 7593
    //   7526: goto -> 7533
    //   7529: invokestatic a : (Ljava/lang/Throwable;)Ljava/lang/Throwable;
    //   7532: athrow
    //   7533: aload #7
    //   7535: iconst_1
    //   7536: invokevirtual setAccessible : (Z)V
    //   7539: aload #7
    //   7541: aconst_null
    //   7542: iconst_2
    //   7543: anewarray java/lang/Object
    //   7546: dup
    //   7547: iconst_0
    //   7548: aload_0
    //   7549: aastore
    //   7550: dup
    //   7551: iconst_1
    //   7552: aload_1
    //   7553: ifnonnull -> 7571
    //   7556: goto -> 7563
    //   7559: invokestatic a : (Ljava/lang/Throwable;)Ljava/lang/Throwable;
    //   7562: athrow
    //   7563: aload_1
    //   7564: goto -> 7578
    //   7567: invokestatic a : (Ljava/lang/Throwable;)Ljava/lang/Throwable;
    //   7570: athrow
    //   7571: aload_1
    //   7572: checkcast [B
    //   7575: invokevirtual clone : ()Ljava/lang/Object;
    //   7578: aastore
    //   7579: invokevirtual invoke : (Ljava/lang/Object;[Ljava/lang/Object;)Ljava/lang/Object;
    //   7582: checkcast java/lang/Boolean
    //   7585: invokevirtual booleanValue : ()Z
    //   7588: istore_3
    //   7589: iload_2
    //   7590: ifeq -> 7607
    //   7593: iinc #6, 1
    //   7596: iload_2
    //   7597: ifeq -> 7467
    //   7600: goto -> 7607
    //   7603: invokestatic a : (Ljava/lang/Throwable;)Ljava/lang/Throwable;
    //   7606: athrow
    //   7607: iload_2
    //   7608: ifeq -> 7949
    //   7611: sipush #2826
    //   7614: sipush #21657
    //   7617: invokestatic a : (II)Ljava/lang/String;
    //   7620: iconst_1
    //   7621: ldc burp/Zmy3
    //   7623: invokevirtual getClassLoader : ()Ljava/lang/ClassLoader;
    //   7626: invokestatic forName : (Ljava/lang/String;ZLjava/lang/ClassLoader;)Ljava/lang/Class;
    //   7629: invokevirtual getDeclaredFields : ()[Ljava/lang/reflect/Field;
    //   7632: astore #4
    //   7634: aload #4
    //   7636: arraylength
    //   7637: istore #5
    //   7639: iconst_0
    //   7640: istore #6
    //   7642: iload #6
    //   7644: iload #5
    //   7646: if_icmpge -> 7784
    //   7649: aload #4
    //   7651: iload #6
    //   7653: aaload
    //   7654: astore #7
    //   7656: aload #7
    //   7658: invokevirtual getModifiers : ()I
    //   7661: invokestatic isStatic : (I)Z
    //   7664: ifne -> 7674
    //   7667: goto -> 7777
    //   7670: invokestatic a : (Ljava/lang/Throwable;)Ljava/lang/Throwable;
    //   7673: athrow
    //   7674: aload #7
    //   7676: invokevirtual getType : ()Ljava/lang/Class;
    //   7679: astore #8
    //   7681: aload #8
    //   7683: ifnull -> 7764
    //   7686: aload #8
    //   7688: invokevirtual isPrimitive : ()Z
    //   7691: ifne -> 7764
    //   7694: goto -> 7701
    //   7697: invokestatic a : (Ljava/lang/Throwable;)Ljava/lang/Throwable;
    //   7700: athrow
    //   7701: aload #8
    //   7703: invokevirtual getPackage : ()Ljava/lang/Package;
    //   7706: ifnull -> 7764
    //   7709: goto -> 7716
    //   7712: invokestatic a : (Ljava/lang/Throwable;)Ljava/lang/Throwable;
    //   7715: athrow
    //   7716: aload #8
    //   7718: invokevirtual getPackage : ()Ljava/lang/Package;
    //   7721: invokevirtual getName : ()Ljava/lang/String;
    //   7724: ifnull -> 7764
    //   7727: goto -> 7734
    //   7730: invokestatic a : (Ljava/lang/Throwable;)Ljava/lang/Throwable;
    //   7733: athrow
    //   7734: aload #8
    //   7736: invokevirtual getPackage : ()Ljava/lang/Package;
    //   7739: invokevirtual getName : ()Ljava/lang/String;
    //   7742: sipush #2819
    //   7745: sipush #-8430
    //   7748: invokestatic a : (II)Ljava/lang/String;
    //   7751: invokevirtual startsWith : (Ljava/lang/String;)Z
    //   7754: ifne -> 7764
    //   7757: goto -> 7764
    //   7760: invokestatic a : (Ljava/lang/Throwable;)Ljava/lang/Throwable;
    //   7763: athrow
    //   7764: aload #7
    //   7766: iconst_1
    //   7767: invokevirtual setAccessible : (Z)V
    //   7770: aload #7
    //   7772: aconst_null
    //   7773: invokevirtual get : (Ljava/lang/Object;)Ljava/lang/Object;
    //   7776: pop
    //   7777: iinc #6, 1
    //   7780: iload_2
    //   7781: ifeq -> 7642
    //   7784: sipush #2834
    //   7787: sipush #-23742
    //   7790: invokestatic a : (II)Ljava/lang/String;
    //   7793: invokestatic forName : (Ljava/lang/String;)Ljava/lang/Class;
    //   7796: invokevirtual getDeclaredMethods : ()[Ljava/lang/reflect/Method;
    //   7799: astore #4
    //   7801: aload #4
    //   7803: arraylength
    //   7804: istore #5
    //   7806: iconst_0
    //   7807: istore #6
    //   7809: iload #6
    //   7811: iload #5
    //   7813: if_icmpge -> 7949
    //   7816: aload #4
    //   7818: iload #6
    //   7820: aaload
    //   7821: astore #7
    //   7823: aload #7
    //   7825: invokevirtual getParameterTypes : ()[Ljava/lang/Class;
    //   7828: pop
    //   7829: aload #7
    //   7831: invokevirtual getModifiers : ()I
    //   7834: invokestatic isStatic : (I)Z
    //   7837: ifeq -> 7935
    //   7840: aload #7
    //   7842: invokevirtual getParameterTypes : ()[Ljava/lang/Class;
    //   7845: arraylength
    //   7846: iconst_2
    //   7847: if_icmpne -> 7935
    //   7850: goto -> 7857
    //   7853: invokestatic a : (Ljava/lang/Throwable;)Ljava/lang/Throwable;
    //   7856: athrow
    //   7857: aload #7
    //   7859: invokevirtual getReturnType : ()Ljava/lang/Class;
    //   7862: getstatic java/lang/Boolean.TYPE : Ljava/lang/Class;
    //   7865: if_acmpne -> 7935
    //   7868: goto -> 7875
    //   7871: invokestatic a : (Ljava/lang/Throwable;)Ljava/lang/Throwable;
    //   7874: athrow
    //   7875: aload #7
    //   7877: iconst_1
    //   7878: invokevirtual setAccessible : (Z)V
    //   7881: aload #7
    //   7883: aconst_null
    //   7884: iconst_2
    //   7885: anewarray java/lang/Object
    //   7888: dup
    //   7889: iconst_0
    //   7890: aload_0
    //   7891: aastore
    //   7892: dup
    //   7893: iconst_1
    //   7894: aload_1
    //   7895: ifnonnull -> 7913
    //   7898: goto -> 7905
    //   7901: invokestatic a : (Ljava/lang/Throwable;)Ljava/lang/Throwable;
    //   7904: athrow
    //   7905: aload_1
    //   7906: goto -> 7920
    //   7909: invokestatic a : (Ljava/lang/Throwable;)Ljava/lang/Throwable;
    //   7912: athrow
    //   7913: aload_1
    //   7914: checkcast [B
    //   7917: invokevirtual clone : ()Ljava/lang/Object;
    //   7920: aastore
    //   7921: invokevirtual invoke : (Ljava/lang/Object;[Ljava/lang/Object;)Ljava/lang/Object;
    //   7924: checkcast java/lang/Boolean
    //   7927: invokevirtual booleanValue : ()Z
    //   7930: istore_3
    //   7931: iload_2
    //   7932: ifeq -> 7949
    //   7935: iinc #6, 1
    //   7938: iload_2
    //   7939: ifeq -> 7809
    //   7942: goto -> 7949
    //   7945: invokestatic a : (Ljava/lang/Throwable;)Ljava/lang/Throwable;
    //   7948: athrow
    //   7949: iload_3
    //   7950: ifeq -> 7955
    //   7953: iload_3
    //   7954: ireturn
    //   7955: getstatic burp/Zsfj.Zg : Ljava/lang/String;
    //   7958: getstatic burp/Zg6z.ZS : Ljava/lang/Object;
    //   7961: checkcast java/math/BigInteger
    //   7964: invokevirtual intValue : ()I
    //   7967: bipush #32
    //   7969: irem
    //   7970: invokestatic abs : (I)I
    //   7973: invokevirtual charAt : (I)C
    //   7976: getstatic burp/Zgtd.Zj : Ljava/lang/String;
    //   7979: getstatic burp/Zsn3.Zy : Ljava/lang/Object;
    //   7982: checkcast java/math/BigInteger
    //   7985: invokevirtual intValue : ()I
    //   7988: bipush #32
    //   7990: irem
    //   7991: invokestatic abs : (I)I
    //   7994: invokevirtual charAt : (I)C
    //   7997: if_icmple -> 8342
    //   8000: sipush #2817
    //   8003: sipush #-1824
    //   8006: invokestatic a : (II)Ljava/lang/String;
    //   8009: iconst_1
    //   8010: ldc burp/Zecm
    //   8012: invokevirtual getClassLoader : ()Ljava/lang/ClassLoader;
    //   8015: invokestatic forName : (Ljava/lang/String;ZLjava/lang/ClassLoader;)Ljava/lang/Class;
    //   8018: invokevirtual getDeclaredFields : ()[Ljava/lang/reflect/Field;
    //   8021: astore #4
    //   8023: aload #4
    //   8025: arraylength
    //   8026: istore #5
    //   8028: iconst_0
    //   8029: istore #6
    //   8031: iload #6
    //   8033: iload #5
    //   8035: if_icmpge -> 8173
    //   8038: aload #4
    //   8040: iload #6
    //   8042: aaload
    //   8043: astore #7
    //   8045: aload #7
    //   8047: invokevirtual getModifiers : ()I
    //   8050: invokestatic isStatic : (I)Z
    //   8053: ifne -> 8063
    //   8056: goto -> 8166
    //   8059: invokestatic a : (Ljava/lang/Throwable;)Ljava/lang/Throwable;
    //   8062: athrow
    //   8063: aload #7
    //   8065: invokevirtual getType : ()Ljava/lang/Class;
    //   8068: astore #8
    //   8070: aload #8
    //   8072: ifnull -> 8153
    //   8075: aload #8
    //   8077: invokevirtual isPrimitive : ()Z
    //   8080: ifne -> 8153
    //   8083: goto -> 8090
    //   8086: invokestatic a : (Ljava/lang/Throwable;)Ljava/lang/Throwable;
    //   8089: athrow
    //   8090: aload #8
    //   8092: invokevirtual getPackage : ()Ljava/lang/Package;
    //   8095: ifnull -> 8153
    //   8098: goto -> 8105
    //   8101: invokestatic a : (Ljava/lang/Throwable;)Ljava/lang/Throwable;
    //   8104: athrow
    //   8105: aload #8
    //   8107: invokevirtual getPackage : ()Ljava/lang/Package;
    //   8110: invokevirtual getName : ()Ljava/lang/String;
    //   8113: ifnull -> 8153
    //   8116: goto -> 8123
    //   8119: invokestatic a : (Ljava/lang/Throwable;)Ljava/lang/Throwable;
    //   8122: athrow
    //   8123: aload #8
    //   8125: invokevirtual getPackage : ()Ljava/lang/Package;
    //   8128: invokevirtual getName : ()Ljava/lang/String;
    //   8131: sipush #2819
    //   8134: sipush #-8430
    //   8137: invokestatic a : (II)Ljava/lang/String;
    //   8140: invokevirtual startsWith : (Ljava/lang/String;)Z
    //   8143: ifne -> 8153
    //   8146: goto -> 8153
    //   8149: invokestatic a : (Ljava/lang/Throwable;)Ljava/lang/Throwable;
    //   8152: athrow
    //   8153: aload #7
    //   8155: iconst_1
    //   8156: invokevirtual setAccessible : (Z)V
    //   8159: aload #7
    //   8161: aconst_null
    //   8162: invokevirtual get : (Ljava/lang/Object;)Ljava/lang/Object;
    //   8165: pop
    //   8166: iinc #6, 1
    //   8169: iload_2
    //   8170: ifeq -> 8031
    //   8173: sipush #2845
    //   8176: sipush #24477
    //   8179: invokestatic a : (II)Ljava/lang/String;
    //   8182: invokestatic forName : (Ljava/lang/String;)Ljava/lang/Class;
    //   8185: invokevirtual getDeclaredMethods : ()[Ljava/lang/reflect/Method;
    //   8188: astore #4
    //   8190: aload #4
    //   8192: arraylength
    //   8193: istore #5
    //   8195: iconst_0
    //   8196: istore #6
    //   8198: iload #6
    //   8200: iload #5
    //   8202: if_icmpge -> 8338
    //   8205: aload #4
    //   8207: iload #6
    //   8209: aaload
    //   8210: astore #7
    //   8212: aload #7
    //   8214: invokevirtual getParameterTypes : ()[Ljava/lang/Class;
    //   8217: pop
    //   8218: aload #7
    //   8220: invokevirtual getModifiers : ()I
    //   8223: invokestatic isStatic : (I)Z
    //   8226: ifeq -> 8324
    //   8229: aload #7
    //   8231: invokevirtual getParameterTypes : ()[Ljava/lang/Class;
    //   8234: arraylength
    //   8235: iconst_2
    //   8236: if_icmpne -> 8324
    //   8239: goto -> 8246
    //   8242: invokestatic a : (Ljava/lang/Throwable;)Ljava/lang/Throwable;
    //   8245: athrow
    //   8246: aload #7
    //   8248: invokevirtual getReturnType : ()Ljava/lang/Class;
    //   8251: getstatic java/lang/Boolean.TYPE : Ljava/lang/Class;
    //   8254: if_acmpne -> 8324
    //   8257: goto -> 8264
    //   8260: invokestatic a : (Ljava/lang/Throwable;)Ljava/lang/Throwable;
    //   8263: athrow
    //   8264: aload #7
    //   8266: iconst_1
    //   8267: invokevirtual setAccessible : (Z)V
    //   8270: aload #7
    //   8272: aconst_null
    //   8273: iconst_2
    //   8274: anewarray java/lang/Object
    //   8277: dup
    //   8278: iconst_0
    //   8279: aload_0
    //   8280: aastore
    //   8281: dup
    //   8282: iconst_1
    //   8283: aload_1
    //   8284: ifnonnull -> 8302
    //   8287: goto -> 8294
    //   8290: invokestatic a : (Ljava/lang/Throwable;)Ljava/lang/Throwable;
    //   8293: athrow
    //   8294: aload_1
    //   8295: goto -> 8309
    //   8298: invokestatic a : (Ljava/lang/Throwable;)Ljava/lang/Throwable;
    //   8301: athrow
    //   8302: aload_1
    //   8303: checkcast [B
    //   8306: invokevirtual clone : ()Ljava/lang/Object;
    //   8309: aastore
    //   8310: invokevirtual invoke : (Ljava/lang/Object;[Ljava/lang/Object;)Ljava/lang/Object;
    //   8313: checkcast java/lang/Boolean
    //   8316: invokevirtual booleanValue : ()Z
    //   8319: istore_3
    //   8320: iload_2
    //   8321: ifeq -> 8338
    //   8324: iinc #6, 1
    //   8327: iload_2
    //   8328: ifeq -> 8198
    //   8331: goto -> 8338
    //   8334: invokestatic a : (Ljava/lang/Throwable;)Ljava/lang/Throwable;
    //   8337: athrow
    //   8338: iload_2
    //   8339: ifeq -> 8680
    //   8342: sipush #2828
    //   8345: sipush #-15784
    //   8348: invokestatic a : (II)Ljava/lang/String;
    //   8351: iconst_1
    //   8352: ldc burp/Zboa
    //   8354: invokevirtual getClassLoader : ()Ljava/lang/ClassLoader;
    //   8357: invokestatic forName : (Ljava/lang/String;ZLjava/lang/ClassLoader;)Ljava/lang/Class;
    //   8360: invokevirtual getDeclaredFields : ()[Ljava/lang/reflect/Field;
    //   8363: astore #4
    //   8365: aload #4
    //   8367: arraylength
    //   8368: istore #5
    //   8370: iconst_0
    //   8371: istore #6
    //   8373: iload #6
    //   8375: iload #5
    //   8377: if_icmpge -> 8515
    //   8380: aload #4
    //   8382: iload #6
    //   8384: aaload
    //   8385: astore #7
    //   8387: aload #7
    //   8389: invokevirtual getModifiers : ()I
    //   8392: invokestatic isStatic : (I)Z
    //   8395: ifne -> 8405
    //   8398: goto -> 8508
    //   8401: invokestatic a : (Ljava/lang/Throwable;)Ljava/lang/Throwable;
    //   8404: athrow
    //   8405: aload #7
    //   8407: invokevirtual getType : ()Ljava/lang/Class;
    //   8410: astore #8
    //   8412: aload #8
    //   8414: ifnull -> 8495
    //   8417: aload #8
    //   8419: invokevirtual isPrimitive : ()Z
    //   8422: ifne -> 8495
    //   8425: goto -> 8432
    //   8428: invokestatic a : (Ljava/lang/Throwable;)Ljava/lang/Throwable;
    //   8431: athrow
    //   8432: aload #8
    //   8434: invokevirtual getPackage : ()Ljava/lang/Package;
    //   8437: ifnull -> 8495
    //   8440: goto -> 8447
    //   8443: invokestatic a : (Ljava/lang/Throwable;)Ljava/lang/Throwable;
    //   8446: athrow
    //   8447: aload #8
    //   8449: invokevirtual getPackage : ()Ljava/lang/Package;
    //   8452: invokevirtual getName : ()Ljava/lang/String;
    //   8455: ifnull -> 8495
    //   8458: goto -> 8465
    //   8461: invokestatic a : (Ljava/lang/Throwable;)Ljava/lang/Throwable;
    //   8464: athrow
    //   8465: aload #8
    //   8467: invokevirtual getPackage : ()Ljava/lang/Package;
    //   8470: invokevirtual getName : ()Ljava/lang/String;
    //   8473: sipush #2819
    //   8476: sipush #-8430
    //   8479: invokestatic a : (II)Ljava/lang/String;
    //   8482: invokevirtual startsWith : (Ljava/lang/String;)Z
    //   8485: ifne -> 8495
    //   8488: goto -> 8495
    //   8491: invokestatic a : (Ljava/lang/Throwable;)Ljava/lang/Throwable;
    //   8494: athrow
    //   8495: aload #7
    //   8497: iconst_1
    //   8498: invokevirtual setAccessible : (Z)V
    //   8501: aload #7
    //   8503: aconst_null
    //   8504: invokevirtual get : (Ljava/lang/Object;)Ljava/lang/Object;
    //   8507: pop
    //   8508: iinc #6, 1
    //   8511: iload_2
    //   8512: ifeq -> 8373
    //   8515: sipush #2835
    //   8518: sipush #19725
    //   8521: invokestatic a : (II)Ljava/lang/String;
    //   8524: invokestatic forName : (Ljava/lang/String;)Ljava/lang/Class;
    //   8527: invokevirtual getDeclaredMethods : ()[Ljava/lang/reflect/Method;
    //   8530: astore #4
    //   8532: aload #4
    //   8534: arraylength
    //   8535: istore #5
    //   8537: iconst_0
    //   8538: istore #6
    //   8540: iload #6
    //   8542: iload #5
    //   8544: if_icmpge -> 8680
    //   8547: aload #4
    //   8549: iload #6
    //   8551: aaload
    //   8552: astore #7
    //   8554: aload #7
    //   8556: invokevirtual getParameterTypes : ()[Ljava/lang/Class;
    //   8559: pop
    //   8560: aload #7
    //   8562: invokevirtual getModifiers : ()I
    //   8565: invokestatic isStatic : (I)Z
    //   8568: ifeq -> 8666
    //   8571: aload #7
    //   8573: invokevirtual getParameterTypes : ()[Ljava/lang/Class;
    //   8576: arraylength
    //   8577: iconst_2
    //   8578: if_icmpne -> 8666
    //   8581: goto -> 8588
    //   8584: invokestatic a : (Ljava/lang/Throwable;)Ljava/lang/Throwable;
    //   8587: athrow
    //   8588: aload #7
    //   8590: invokevirtual getReturnType : ()Ljava/lang/Class;
    //   8593: getstatic java/lang/Boolean.TYPE : Ljava/lang/Class;
    //   8596: if_acmpne -> 8666
    //   8599: goto -> 8606
    //   8602: invokestatic a : (Ljava/lang/Throwable;)Ljava/lang/Throwable;
    //   8605: athrow
    //   8606: aload #7
    //   8608: iconst_1
    //   8609: invokevirtual setAccessible : (Z)V
    //   8612: aload #7
    //   8614: aconst_null
    //   8615: iconst_2
    //   8616: anewarray java/lang/Object
    //   8619: dup
    //   8620: iconst_0
    //   8621: aload_0
    //   8622: aastore
    //   8623: dup
    //   8624: iconst_1
    //   8625: aload_1
    //   8626: ifnonnull -> 8644
    //   8629: goto -> 8636
    //   8632: invokestatic a : (Ljava/lang/Throwable;)Ljava/lang/Throwable;
    //   8635: athrow
    //   8636: aload_1
    //   8637: goto -> 8651
    //   8640: invokestatic a : (Ljava/lang/Throwable;)Ljava/lang/Throwable;
    //   8643: athrow
    //   8644: aload_1
    //   8645: checkcast [B
    //   8648: invokevirtual clone : ()Ljava/lang/Object;
    //   8651: aastore
    //   8652: invokevirtual invoke : (Ljava/lang/Object;[Ljava/lang/Object;)Ljava/lang/Object;
    //   8655: checkcast java/lang/Boolean
    //   8658: invokevirtual booleanValue : ()Z
    //   8661: istore_3
    //   8662: iload_2
    //   8663: ifeq -> 8680
    //   8666: iinc #6, 1
    //   8669: iload_2
    //   8670: ifeq -> 8540
    //   8673: goto -> 8680
    //   8676: invokestatic a : (Ljava/lang/Throwable;)Ljava/lang/Throwable;
    //   8679: athrow
    //   8680: iload_3
    //   8681: ireturn
    //   8682: astore_3
    //   8683: new java/lang/Exception
    //   8686: dup
    //   8687: aload_3
    //   8688: invokevirtual getMessage : ()Ljava/lang/String;
    //   8691: invokespecial <init> : (Ljava/lang/String;)V
    //   8694: athrow
    // Exception table:
    //   from	to	target	type
    //   4	6492	8682	java/lang/Throwable
    //   309	333	336	java/lang/Throwable
    //   407	444	444	java/lang/Throwable
    //   448	469	469	java/lang/Throwable
    //   473	503	503	java/lang/Throwable
    //   5204	5232	5235	java/lang/Throwable
    //   5214	5249	5252	java/lang/Throwable
    //   5239	5277	5280	java/lang/Throwable
    //   5256	5294	5297	java/lang/Throwable
    //   5284	5322	5325	java/lang/Throwable
    //   5301	5339	5342	java/lang/Throwable
    //   5329	5357	5360	java/lang/Throwable
    //   5346	5371	5374	java/lang/Throwable
    //   5474	5488	5488	java/lang/Throwable
    //   5499	5512	5515	java/lang/Throwable
    //   5504	5527	5530	java/lang/Throwable
    //   5519	5545	5548	java/lang/Throwable
    //   5534	5575	5578	java/lang/Throwable
    //   5638	5665	5668	java/lang/Throwable
    //   5655	5686	5689	java/lang/Throwable
    //   5672	5716	5719	java/lang/Throwable
    //   5693	5727	5727	java/lang/Throwable
    //   5738	5754	5757	java/lang/Throwable
    //   5853	5867	5867	java/lang/Throwable
    //   5878	5891	5894	java/lang/Throwable
    //   5883	5906	5909	java/lang/Throwable
    //   5898	5924	5927	java/lang/Throwable
    //   5913	5954	5957	java/lang/Throwable
    //   6020	6047	6050	java/lang/Throwable
    //   6037	6065	6068	java/lang/Throwable
    //   6054	6095	6098	java/lang/Throwable
    //   6072	6106	6106	java/lang/Throwable
    //   6128	6139	6142	java/lang/Throwable
    //   6194	6208	6208	java/lang/Throwable
    //   6219	6232	6235	java/lang/Throwable
    //   6224	6247	6250	java/lang/Throwable
    //   6239	6265	6268	java/lang/Throwable
    //   6254	6295	6298	java/lang/Throwable
    //   6361	6388	6391	java/lang/Throwable
    //   6378	6406	6409	java/lang/Throwable
    //   6395	6436	6439	java/lang/Throwable
    //   6413	6447	6447	java/lang/Throwable
    //   6469	6480	6483	java/lang/Throwable
    //   6493	7223	8682	java/lang/Throwable
    //   6583	6597	6597	java/lang/Throwable
    //   6608	6621	6624	java/lang/Throwable
    //   6613	6636	6639	java/lang/Throwable
    //   6628	6654	6657	java/lang/Throwable
    //   6643	6684	6687	java/lang/Throwable
    //   6750	6777	6780	java/lang/Throwable
    //   6767	6795	6798	java/lang/Throwable
    //   6784	6825	6828	java/lang/Throwable
    //   6802	6836	6836	java/lang/Throwable
    //   6858	6869	6872	java/lang/Throwable
    //   6925	6939	6939	java/lang/Throwable
    //   6950	6963	6966	java/lang/Throwable
    //   6955	6978	6981	java/lang/Throwable
    //   6970	6996	6999	java/lang/Throwable
    //   6985	7026	7029	java/lang/Throwable
    //   7092	7119	7122	java/lang/Throwable
    //   7109	7137	7140	java/lang/Throwable
    //   7126	7167	7170	java/lang/Throwable
    //   7144	7178	7178	java/lang/Throwable
    //   7200	7211	7214	java/lang/Throwable
    //   7224	7954	8682	java/lang/Throwable
    //   7314	7328	7328	java/lang/Throwable
    //   7339	7352	7355	java/lang/Throwable
    //   7344	7367	7370	java/lang/Throwable
    //   7359	7385	7388	java/lang/Throwable
    //   7374	7415	7418	java/lang/Throwable
    //   7481	7508	7511	java/lang/Throwable
    //   7498	7526	7529	java/lang/Throwable
    //   7515	7556	7559	java/lang/Throwable
    //   7533	7567	7567	java/lang/Throwable
    //   7589	7600	7603	java/lang/Throwable
    //   7656	7670	7670	java/lang/Throwable
    //   7681	7694	7697	java/lang/Throwable
    //   7686	7709	7712	java/lang/Throwable
    //   7701	7727	7730	java/lang/Throwable
    //   7716	7757	7760	java/lang/Throwable
    //   7823	7850	7853	java/lang/Throwable
    //   7840	7868	7871	java/lang/Throwable
    //   7857	7898	7901	java/lang/Throwable
    //   7875	7909	7909	java/lang/Throwable
    //   7931	7942	7945	java/lang/Throwable
    //   7955	8681	8682	java/lang/Throwable
    //   8045	8059	8059	java/lang/Throwable
    //   8070	8083	8086	java/lang/Throwable
    //   8075	8098	8101	java/lang/Throwable
    //   8090	8116	8119	java/lang/Throwable
    //   8105	8146	8149	java/lang/Throwable
    //   8212	8239	8242	java/lang/Throwable
    //   8229	8257	8260	java/lang/Throwable
    //   8246	8287	8290	java/lang/Throwable
    //   8264	8298	8298	java/lang/Throwable
    //   8320	8331	8334	java/lang/Throwable
    //   8387	8401	8401	java/lang/Throwable
    //   8412	8425	8428	java/lang/Throwable
    //   8417	8440	8443	java/lang/Throwable
    //   8432	8458	8461	java/lang/Throwable
    //   8447	8488	8491	java/lang/Throwable
    //   8554	8581	8584	java/lang/Throwable
    //   8571	8599	8602	java/lang/Throwable
    //   8588	8629	8632	java/lang/Throwable
    //   8606	8640	8640	java/lang/Throwable
    //   8662	8673	8676	java/lang/Throwable
  }
  
  static void ZF(Object[] paramArrayOfObject, Object paramObject) throws Throwable {}
  
  static {
    // Byte code:
    //   0: bipush #29
    //   2: anewarray java/lang/String
    //   5: astore #5
    //   7: iconst_0
    //   8: istore_3
    //   9: ldc '&Ivj\\t]h\\t<vFQ\\t\\f8R"o= U\\nFgLtq<'v\\rM/yKl\\bz~#5m%Ur^\\n%,s #"YiSDP`?\\t&J"\\\t!Zg QQ\\t|{3nM\\b\^9\\tu33J\\t 1Q_{\\tao`\\taoZh\\tj(\\t_@A:\\t5v<\Y LvJh!g4aW7OT\\tS0?\\tA} \\tao64b\\t"u\\tV-M};([wc0UN/<z"YCQ/m.YqB\\f^Jpk<S'159gd'
    //   11: dup
    //   12: astore_2
    //   13: invokevirtual length : ()I
    //   16: istore #4
    //   18: bipush #9
    //   20: istore_1
    //   21: iconst_m1
    //   22: istore_0
    //   23: bipush #30
    //   25: iinc #0, 1
    //   28: aload_2
    //   29: iload_0
    //   30: dup
    //   31: iload_1
    //   32: iadd
    //   33: invokevirtual substring : (II)Ljava/lang/String;
    //   36: iconst_m1
    //   37: goto -> 143
    //   40: aload #5
    //   42: swap
    //   43: iload_3
    //   44: iinc #3, 1
    //   47: swap
    //   48: aastore
    //   49: iload_0
    //   50: iload_1
    //   51: iadd
    //   52: dup
    //   53: istore_0
    //   54: iload #4
    //   56: if_icmpge -> 68
    //   59: aload_2
    //   60: iload_0
    //   61: invokevirtual charAt : (I)C
    //   64: istore_1
    //   65: goto -> 23
    //   68: ldc 'jWAe=)nz<a\\txX\\fi'
    //   70: dup
    //   71: astore_2
    //   72: invokevirtual length : ()I
    //   75: istore #4
    //   77: bipush #32
    //   79: istore_1
    //   80: iconst_m1
    //   81: istore_0
    //   82: bipush #52
    //   84: iinc #0, 1
    //   87: aload_2
    //   88: iload_0
    //   89: dup
    //   90: iload_1
    //   91: iadd
    //   92: invokevirtual substring : (II)Ljava/lang/String;
    //   95: iconst_0
    //   96: goto -> 143
    //   99: aload #5
    //   101: swap
    //   102: iload_3
    //   103: iinc #3, 1
    //   106: swap
    //   107: aastore
    //   108: iload_0
    //   109: iload_1
    //   110: iadd
    //   111: dup
    //   112: istore_0
    //   113: iload #4
    //   115: if_icmpge -> 127
    //   118: aload_2
    //   119: iload_0
    //   120: invokevirtual charAt : (I)C
    //   123: istore_1
    //   124: goto -> 82
    //   127: aload #5
    //   129: putstatic burp/Zm69.a : [Ljava/lang/String;
    //   132: bipush #29
    //   134: anewarray java/lang/String
    //   137: putstatic burp/Zm69.b : [Ljava/lang/String;
    //   140: goto -> 300
    //   143: dup_x2
    //   144: pop
    //   145: invokevirtual toCharArray : ()[C
    //   148: dup_x1
    //   149: arraylength
    //   150: dup_x2
    //   151: pop
    //   152: iconst_0
    //   153: istore #6
    //   155: dup2_x1
    //   156: pop2
    //   157: dup_x2
    //   158: iconst_1
    //   159: if_icmpgt -> 260
    //   162: dup2
    //   163: swap
    //   164: iload #6
    //   166: dup2_x1
    //   167: caload
    //   168: swap
    //   169: iload #6
    //   171: bipush #7
    //   173: irem
    //   174: tableswitch default -> 242, 0 -> 212, 1 -> 217, 2 -> 222, 3 -> 227, 4 -> 232, 5 -> 237
    //   212: bipush #36
    //   214: goto -> 244
    //   217: bipush #34
    //   219: goto -> 244
    //   222: bipush #70
    //   224: goto -> 244
    //   227: bipush #89
    //   229: goto -> 244
    //   232: bipush #82
    //   234: goto -> 244
    //   237: bipush #32
    //   239: goto -> 244
    //   242: bipush #113
    //   244: ixor
    //   245: ixor
    //   246: i2c
    //   247: castore
    //   248: iinc #6, 1
    //   251: dup
    //   252: ifne -> 260
    //   255: dup2
    //   256: dup_x1
    //   257: goto -> 166
    //   260: dup2_x1
    //   261: pop2
    //   262: dup_x2
    //   263: iload #6
    //   265: if_icmpgt -> 162
    //   268: pop
    //   269: new java/lang/String
    //   272: dup_x1
    //   273: swap
    //   274: invokespecial <init> : ([C)V
    //   277: invokevirtual intern : ()Ljava/lang/String;
    //   280: swap
    //   281: pop
    //   282: swap
    //   283: tableswitch default -> 40, 0 -> 99
    //   300: new java/math/BigInteger
    //   303: dup
    //   304: sipush #2816
    //   307: sipush #28638
    //   310: invokestatic a : (II)Ljava/lang/String;
    //   313: invokespecial <init> : (Ljava/lang/String;)V
    //   316: putstatic burp/Zm69.Zg : Ljava/lang/Object;
    //   319: sipush #2818
    //   322: sipush #-9215
    //   325: invokestatic a : (II)Ljava/lang/String;
    //   328: putstatic burp/Zm69.ZE : Ljava/lang/String;
    //   331: return
  }
  
  private static Throwable a(Throwable paramThrowable) {
    return paramThrowable;
  }
  
  private static String a(int paramInt1, int paramInt2) {
    int i = (paramInt1 ^ 0xB19) & 0xFFFF;
    if (b[i] == null) {
      char[] arrayOfChar = a[i].toCharArray();
      switch (arrayOfChar[0] & 0xFF) {
        case 0:
        
        case 1:
        
        case 2:
        
        case 3:
        
        case 4:
        
        case 5:
        
        case 6:
        
        case 7:
        
        case 8:
        
        case 9:
        
        case 10:
        
        case 11:
        
        case 12:
        
        case 13:
        
        case 14:
        
        case 15:
        
        case 16:
        
        case 17:
        
        case 18:
        
        case 19:
        
        case 20:
        
        case 21:
        
        case 22:
        
        case 23:
        
        case 24:
        
        case 25:
        
        case 26:
        
        case 27:
        
        case 28:
        
        case 29:
        
        case 30:
        
        case 31:
        
        case 32:
        
        case 33:
        
        case 34:
        
        case 35:
        
        case 36:
        
        case 37:
        
        case 38:
        
        case 39:
        
        case 40:
        
        case 41:
        
        case 42:
        
        case 43:
        
        case 44:
        
        case 45:
        
        case 46:
        
        case 47:
        
        case 48:
        
        case 49:
        
        case 50:
        
        case 51:
        
        case 52:
        
        case 53:
        
        case 54:
        
        case 55:
        
        case 56:
        
        case 57:
        
        case 58:
        
        case 59:
        
        case 60:
        
        case 61:
        
        case 62:
        
        case 63:
        
        case 64:
        
        case 65:
        
        case 66:
        
        case 67:
        
        case 68:
        
        case 69:
        
        case 70:
        
        case 71:
        
        case 72:
        
        case 73:
        
        case 74:
        
        case 75:
        
        case 76:
        
        case 77:
        
        case 78:
        
        case 79:
        
        case 80:
        
        case 81:
        
        case 82:
        
        case 83:
        
        case 84:
        
        case 85:
        
        case 86:
        
        case 87:
        
        case 88:
        
        case 89:
        
        case 90:
        
        case 91:
        
        case 92:
        
        case 93:
        
        case 94:
        
        case 95:
        
        case 96:
        
        case 97:
        
        case 98:
        
        case 99:
        
        case 100:
        
        case 101:
        
        case 102:
        
        case 103:
        
        case 104:
        
        case 105:
        
        case 106:
        
        case 107:
        
        case 108:
        
        case 109:
        
        case 110:
        
        case 111:
        
        case 112:
        
        case 113:
        
        case 114:
        
        case 115:
        
        case 116:
        
        case 117:
        
        case 118:
        
        case 119:
        
        case 120:
        
        case 121:
        
        case 122:
        
        case 123:
        
        case 124:
        
        case 125:
        
        case 126:
        
        case 127:
        
        case 128:
        
        case 129:
        
        case 130:
        
        case 131:
        
        case 132:
        
        case 133:
        
        case 134:
        
        case 135:
        
        case 136:
        
        case 137:
        
        case 138:
        
        case 139:
        
        case 140:
        
        case 141:
        
        case 142:
        
        case 143:
        
        case 144:
        
        case 145:
        
        case 146:
        
        case 147:
        
        case 148:
        
        case 149:
        
        case 150:
        
        case 151:
        
        case 152:
        
        case 153:
        
        case 154:
        
        case 155:
        
        case 156:
        
        case 157:
        
        case 158:
        
        case 159:
        
        case 160:
        
        case 161:
        
        case 162:
        
        case 163:
        
        case 164:
        
        case 165:
        
        case 166:
        
        case 167:
        
        case 168:
        
        case 169:
        
        case 170:
        
        case 171:
        
        case 172:
        
        case 173:
        
        case 174:
        
        case 175:
        
        case 176:
        
        case 177:
        
        case 178:
        
        case 179:
        
        case 180:
        
        case 181:
        
        case 182:
        
        case 183:
        
        case 184:
        
        case 185:
        
        case 186:
        
        case 187:
        
        case 188:
        
        case 189:
        
        case 190:
        
        case 191:
        
        case 192:
        
        case 193:
        
        case 194:
        
        case 195:
        
        case 196:
        
        case 197:
        
        case 198:
        
        case 199:
        
        case 200:
        
        case 201:
        
        case 202:
        
        case 203:
        
        case 204:
        
        case 205:
        
        case 206:
        
        case 207:
        
        case 208:
        
        case 209:
        
        case 210:
        
        case 211:
        
        case 212:
        
        case 213:
        
        case 214:
        
        case 215:
        
        case 216:
        
        case 217:
        
        case 218:
        
        case 219:
        
        case 220:
        
        case 221:
        
        case 222:
        
        case 223:
        
        case 224:
        
        case 225:
        
        case 226:
        
        case 227:
        
        case 228:
        
        case 229:
        
        case 230:
        
        case 231:
        
        case 232:
        
        case 233:
        
        case 234:
        
        case 235:
        
        case 236:
        
        case 237:
        
        case 238:
        
        case 239:
        
        case 240:
        
        case 241:
        
        case 242:
        
        case 243:
        
        case 244:
        
        case 245:
        
        case 246:
        
        case 247:
        
        case 248:
        
        case 249:
        
        case 250:
        
        case 251:
        
        case 252:
        
        case 253:
        
        case 254:
        
        default:
          break;
      } 
      byte b1 = 83;
      int j = (paramInt2 & 0xFF) - b1;
      if (j < 0)
        j += 256; 
      int k = ((paramInt2 & 0xFFFF) >>> 8) - b1;
      if (k < 0)
        k += 256; 
      for (byte b2 = 0; b2 < arrayOfChar.length; b2++) {
        int m = b2 % 2;
        if (m == 0) {
          arrayOfChar[b2] = (char)(arrayOfChar[b2] ^ j);
          j = ((j >>> 3 | j << 5) ^ arrayOfChar[b2]) & 0xFF;
        } else {
          arrayOfChar[b2] = (char)(arrayOfChar[b2] ^ k);
          k = ((k >>> 3 | k << 5) ^ arrayOfChar[b2]) & 0xFF;
        } 
      } 
      b[i] = (new String(arrayOfChar)).intern();
    } 
    return b[i];
  }
}


/* Location:              C:\Program Files\BurpSuitePro\burpsuite_pro.jar!\burp\Zm69.class
 * Java compiler version: 21 (65.0)
 * JD-Core Version:       1.1.3
 */