package burp;

import java.math.BigInteger;

class Zm81 extends ClassLoader {
  static Object Zy;
  
  static String ZY;
  
  private static final String[] a;
  
  private static final String[] b;
  
  static boolean Zo(Object[] paramArrayOfObject, Object paramObject) throws Throwable {
    // Byte code:
    //   0: invokestatic ZN : ()Z
    //   3: istore_2
    //   4: new java/lang/StringBuilder
    //   7: dup
    //   8: invokespecial <init> : ()V
    //   11: astore_3
    //   12: iconst_0
    //   13: istore #4
    //   15: iload #4
    //   17: bipush #32
    //   19: if_icmpge -> 1355
    //   22: iload #4
    //   24: tableswitch default -> 1348, 0 -> 168, 1 -> 205, 2 -> 242, 3 -> 279, 4 -> 316, 5 -> 353, 6 -> 390, 7 -> 427, 8 -> 464, 9 -> 501, 10 -> 538, 11 -> 575, 12 -> 612, 13 -> 649, 14 -> 686, 15 -> 723, 16 -> 760, 17 -> 797, 18 -> 834, 19 -> 871, 20 -> 908, 21 -> 945, 22 -> 982, 23 -> 1019, 24 -> 1056, 25 -> 1093, 26 -> 1130, 27 -> 1167, 28 -> 1204, 29 -> 1241, 30 -> 1278, 31 -> 1315
    //   168: aload_3
    //   169: getstatic burp/Zr0u.Z_ : Ljava/lang/String;
    //   172: getstatic burp/Zg_y.ZR : Ljava/lang/Object;
    //   175: checkcast java/math/BigInteger
    //   178: invokevirtual intValue : ()I
    //   181: bipush #32
    //   183: irem
    //   184: invokestatic abs : (I)I
    //   187: invokevirtual charAt : (I)C
    //   190: invokevirtual append : (C)Ljava/lang/StringBuilder;
    //   193: pop
    //   194: iload_2
    //   195: ifne -> 1348
    //   198: goto -> 205
    //   201: invokestatic a : (Ljava/lang/Throwable;)Ljava/lang/Throwable;
    //   204: athrow
    //   205: aload_3
    //   206: getstatic burp/Zscf.Zu : Ljava/lang/String;
    //   209: getstatic burp/Ztfr.Zr : Ljava/lang/Object;
    //   212: checkcast java/math/BigInteger
    //   215: invokevirtual intValue : ()I
    //   218: bipush #32
    //   220: irem
    //   221: invokestatic abs : (I)I
    //   224: invokevirtual charAt : (I)C
    //   227: invokevirtual append : (C)Ljava/lang/StringBuilder;
    //   230: pop
    //   231: iload_2
    //   232: ifne -> 1348
    //   235: goto -> 242
    //   238: invokestatic a : (Ljava/lang/Throwable;)Ljava/lang/Throwable;
    //   241: athrow
    //   242: aload_3
    //   243: getstatic burp/Zttq.ZO : Ljava/lang/String;
    //   246: getstatic burp/Zl8l.ZJ : Ljava/lang/Object;
    //   249: checkcast java/math/BigInteger
    //   252: invokevirtual intValue : ()I
    //   255: bipush #32
    //   257: irem
    //   258: invokestatic abs : (I)I
    //   261: invokevirtual charAt : (I)C
    //   264: invokevirtual append : (C)Ljava/lang/StringBuilder;
    //   267: pop
    //   268: iload_2
    //   269: ifne -> 1348
    //   272: goto -> 279
    //   275: invokestatic a : (Ljava/lang/Throwable;)Ljava/lang/Throwable;
    //   278: athrow
    //   279: aload_3
    //   280: getstatic burp/Zkmx.Zg : Ljava/lang/String;
    //   283: getstatic burp/Zkc5.ZZ : Ljava/lang/Object;
    //   286: checkcast java/math/BigInteger
    //   289: invokevirtual intValue : ()I
    //   292: bipush #32
    //   294: irem
    //   295: invokestatic abs : (I)I
    //   298: invokevirtual charAt : (I)C
    //   301: invokevirtual append : (C)Ljava/lang/StringBuilder;
    //   304: pop
    //   305: iload_2
    //   306: ifne -> 1348
    //   309: goto -> 316
    //   312: invokestatic a : (Ljava/lang/Throwable;)Ljava/lang/Throwable;
    //   315: athrow
    //   316: aload_3
    //   317: getstatic burp/Zz6t.Zx : Ljava/lang/String;
    //   320: getstatic burp/Zr0.ZX : Ljava/lang/Object;
    //   323: checkcast java/math/BigInteger
    //   326: invokevirtual intValue : ()I
    //   329: bipush #32
    //   331: irem
    //   332: invokestatic abs : (I)I
    //   335: invokevirtual charAt : (I)C
    //   338: invokevirtual append : (C)Ljava/lang/StringBuilder;
    //   341: pop
    //   342: iload_2
    //   343: ifne -> 1348
    //   346: goto -> 353
    //   349: invokestatic a : (Ljava/lang/Throwable;)Ljava/lang/Throwable;
    //   352: athrow
    //   353: aload_3
    //   354: getstatic burp/Zx4k.ZC : Ljava/lang/String;
    //   357: getstatic burp/Zva.Zu : Ljava/lang/Object;
    //   360: checkcast java/math/BigInteger
    //   363: invokevirtual intValue : ()I
    //   366: bipush #32
    //   368: irem
    //   369: invokestatic abs : (I)I
    //   372: invokevirtual charAt : (I)C
    //   375: invokevirtual append : (C)Ljava/lang/StringBuilder;
    //   378: pop
    //   379: iload_2
    //   380: ifne -> 1348
    //   383: goto -> 390
    //   386: invokestatic a : (Ljava/lang/Throwable;)Ljava/lang/Throwable;
    //   389: athrow
    //   390: aload_3
    //   391: getstatic burp/Zepm.Zl : Ljava/lang/String;
    //   394: getstatic burp/Zmlr.Zh : Ljava/lang/Object;
    //   397: checkcast java/math/BigInteger
    //   400: invokevirtual intValue : ()I
    //   403: bipush #32
    //   405: irem
    //   406: invokestatic abs : (I)I
    //   409: invokevirtual charAt : (I)C
    //   412: invokevirtual append : (C)Ljava/lang/StringBuilder;
    //   415: pop
    //   416: iload_2
    //   417: ifne -> 1348
    //   420: goto -> 427
    //   423: invokestatic a : (Ljava/lang/Throwable;)Ljava/lang/Throwable;
    //   426: athrow
    //   427: aload_3
    //   428: getstatic burp/Zrhu.ZJ : Ljava/lang/String;
    //   431: getstatic burp/Zxo6.Zw : Ljava/lang/Object;
    //   434: checkcast java/math/BigInteger
    //   437: invokevirtual intValue : ()I
    //   440: bipush #32
    //   442: irem
    //   443: invokestatic abs : (I)I
    //   446: invokevirtual charAt : (I)C
    //   449: invokevirtual append : (C)Ljava/lang/StringBuilder;
    //   452: pop
    //   453: iload_2
    //   454: ifne -> 1348
    //   457: goto -> 464
    //   460: invokestatic a : (Ljava/lang/Throwable;)Ljava/lang/Throwable;
    //   463: athrow
    //   464: aload_3
    //   465: getstatic burp/Zmir.ZI : Ljava/lang/String;
    //   468: getstatic burp/Zbli.Zo : Ljava/lang/Object;
    //   471: checkcast java/math/BigInteger
    //   474: invokevirtual intValue : ()I
    //   477: bipush #32
    //   479: irem
    //   480: invokestatic abs : (I)I
    //   483: invokevirtual charAt : (I)C
    //   486: invokevirtual append : (C)Ljava/lang/StringBuilder;
    //   489: pop
    //   490: iload_2
    //   491: ifne -> 1348
    //   494: goto -> 501
    //   497: invokestatic a : (Ljava/lang/Throwable;)Ljava/lang/Throwable;
    //   500: athrow
    //   501: aload_3
    //   502: getstatic burp/Zxt5.ZM : Ljava/lang/String;
    //   505: getstatic burp/Zmgl.ZI : Ljava/lang/Object;
    //   508: checkcast java/math/BigInteger
    //   511: invokevirtual intValue : ()I
    //   514: bipush #32
    //   516: irem
    //   517: invokestatic abs : (I)I
    //   520: invokevirtual charAt : (I)C
    //   523: invokevirtual append : (C)Ljava/lang/StringBuilder;
    //   526: pop
    //   527: iload_2
    //   528: ifne -> 1348
    //   531: goto -> 538
    //   534: invokestatic a : (Ljava/lang/Throwable;)Ljava/lang/Throwable;
    //   537: athrow
    //   538: aload_3
    //   539: getstatic burp/Zkhy.Zu : Ljava/lang/String;
    //   542: getstatic burp/Zgly.ZN : Ljava/lang/Object;
    //   545: checkcast java/math/BigInteger
    //   548: invokevirtual intValue : ()I
    //   551: bipush #32
    //   553: irem
    //   554: invokestatic abs : (I)I
    //   557: invokevirtual charAt : (I)C
    //   560: invokevirtual append : (C)Ljava/lang/StringBuilder;
    //   563: pop
    //   564: iload_2
    //   565: ifne -> 1348
    //   568: goto -> 575
    //   571: invokestatic a : (Ljava/lang/Throwable;)Ljava/lang/Throwable;
    //   574: athrow
    //   575: aload_3
    //   576: getstatic burp/Zei_.ZZ : Ljava/lang/String;
    //   579: getstatic burp/Zlp8.Zu : Ljava/lang/Object;
    //   582: checkcast java/math/BigInteger
    //   585: invokevirtual intValue : ()I
    //   588: bipush #32
    //   590: irem
    //   591: invokestatic abs : (I)I
    //   594: invokevirtual charAt : (I)C
    //   597: invokevirtual append : (C)Ljava/lang/StringBuilder;
    //   600: pop
    //   601: iload_2
    //   602: ifne -> 1348
    //   605: goto -> 612
    //   608: invokestatic a : (Ljava/lang/Throwable;)Ljava/lang/Throwable;
    //   611: athrow
    //   612: aload_3
    //   613: getstatic burp/Zkcd.Zj : Ljava/lang/String;
    //   616: getstatic burp/Zgta.ZF : Ljava/lang/Object;
    //   619: checkcast java/math/BigInteger
    //   622: invokevirtual intValue : ()I
    //   625: bipush #32
    //   627: irem
    //   628: invokestatic abs : (I)I
    //   631: invokevirtual charAt : (I)C
    //   634: invokevirtual append : (C)Ljava/lang/StringBuilder;
    //   637: pop
    //   638: iload_2
    //   639: ifne -> 1348
    //   642: goto -> 649
    //   645: invokestatic a : (Ljava/lang/Throwable;)Ljava/lang/Throwable;
    //   648: athrow
    //   649: aload_3
    //   650: getstatic burp/Zmgl.Zh : Ljava/lang/String;
    //   653: getstatic burp/Zzip.ZW : Ljava/lang/Object;
    //   656: checkcast java/math/BigInteger
    //   659: invokevirtual intValue : ()I
    //   662: bipush #32
    //   664: irem
    //   665: invokestatic abs : (I)I
    //   668: invokevirtual charAt : (I)C
    //   671: invokevirtual append : (C)Ljava/lang/StringBuilder;
    //   674: pop
    //   675: iload_2
    //   676: ifne -> 1348
    //   679: goto -> 686
    //   682: invokestatic a : (Ljava/lang/Throwable;)Ljava/lang/Throwable;
    //   685: athrow
    //   686: aload_3
    //   687: getstatic burp/Zrye.Za : Ljava/lang/String;
    //   690: getstatic burp/Zegk.ZR : Ljava/lang/Object;
    //   693: checkcast java/math/BigInteger
    //   696: invokevirtual intValue : ()I
    //   699: bipush #32
    //   701: irem
    //   702: invokestatic abs : (I)I
    //   705: invokevirtual charAt : (I)C
    //   708: invokevirtual append : (C)Ljava/lang/StringBuilder;
    //   711: pop
    //   712: iload_2
    //   713: ifne -> 1348
    //   716: goto -> 723
    //   719: invokestatic a : (Ljava/lang/Throwable;)Ljava/lang/Throwable;
    //   722: athrow
    //   723: aload_3
    //   724: getstatic burp/Zlzo.Zs : Ljava/lang/String;
    //   727: getstatic burp/Zr3j.ZT : Ljava/lang/Object;
    //   730: checkcast java/math/BigInteger
    //   733: invokevirtual intValue : ()I
    //   736: bipush #32
    //   738: irem
    //   739: invokestatic abs : (I)I
    //   742: invokevirtual charAt : (I)C
    //   745: invokevirtual append : (C)Ljava/lang/StringBuilder;
    //   748: pop
    //   749: iload_2
    //   750: ifne -> 1348
    //   753: goto -> 760
    //   756: invokestatic a : (Ljava/lang/Throwable;)Ljava/lang/Throwable;
    //   759: athrow
    //   760: aload_3
    //   761: getstatic burp/Zzmo.Zx : Ljava/lang/String;
    //   764: getstatic burp/Ztbf.Zv : Ljava/lang/Object;
    //   767: checkcast java/math/BigInteger
    //   770: invokevirtual intValue : ()I
    //   773: bipush #32
    //   775: irem
    //   776: invokestatic abs : (I)I
    //   779: invokevirtual charAt : (I)C
    //   782: invokevirtual append : (C)Ljava/lang/StringBuilder;
    //   785: pop
    //   786: iload_2
    //   787: ifne -> 1348
    //   790: goto -> 797
    //   793: invokestatic a : (Ljava/lang/Throwable;)Ljava/lang/Throwable;
    //   796: athrow
    //   797: aload_3
    //   798: getstatic burp/Zod.ZS : Ljava/lang/String;
    //   801: getstatic burp/Zbxa.ZS : Ljava/lang/Object;
    //   804: checkcast java/math/BigInteger
    //   807: invokevirtual intValue : ()I
    //   810: bipush #32
    //   812: irem
    //   813: invokestatic abs : (I)I
    //   816: invokevirtual charAt : (I)C
    //   819: invokevirtual append : (C)Ljava/lang/StringBuilder;
    //   822: pop
    //   823: iload_2
    //   824: ifne -> 1348
    //   827: goto -> 834
    //   830: invokestatic a : (Ljava/lang/Throwable;)Ljava/lang/Throwable;
    //   833: athrow
    //   834: aload_3
    //   835: getstatic burp/Zbxp.ZS : Ljava/lang/String;
    //   838: getstatic burp/Zg27.ZQ : Ljava/lang/Object;
    //   841: checkcast java/math/BigInteger
    //   844: invokevirtual intValue : ()I
    //   847: bipush #32
    //   849: irem
    //   850: invokestatic abs : (I)I
    //   853: invokevirtual charAt : (I)C
    //   856: invokevirtual append : (C)Ljava/lang/StringBuilder;
    //   859: pop
    //   860: iload_2
    //   861: ifne -> 1348
    //   864: goto -> 871
    //   867: invokestatic a : (Ljava/lang/Throwable;)Ljava/lang/Throwable;
    //   870: athrow
    //   871: aload_3
    //   872: getstatic burp/Zsq5.ZA : Ljava/lang/String;
    //   875: getstatic burp/Zlem.ZI : Ljava/lang/Object;
    //   878: checkcast java/math/BigInteger
    //   881: invokevirtual intValue : ()I
    //   884: bipush #32
    //   886: irem
    //   887: invokestatic abs : (I)I
    //   890: invokevirtual charAt : (I)C
    //   893: invokevirtual append : (C)Ljava/lang/StringBuilder;
    //   896: pop
    //   897: iload_2
    //   898: ifne -> 1348
    //   901: goto -> 908
    //   904: invokestatic a : (Ljava/lang/Throwable;)Ljava/lang/Throwable;
    //   907: athrow
    //   908: aload_3
    //   909: getstatic burp/Zrxf.ZG : Ljava/lang/String;
    //   912: getstatic burp/Zr5k.Zj : Ljava/lang/Object;
    //   915: checkcast java/math/BigInteger
    //   918: invokevirtual intValue : ()I
    //   921: bipush #32
    //   923: irem
    //   924: invokestatic abs : (I)I
    //   927: invokevirtual charAt : (I)C
    //   930: invokevirtual append : (C)Ljava/lang/StringBuilder;
    //   933: pop
    //   934: iload_2
    //   935: ifne -> 1348
    //   938: goto -> 945
    //   941: invokestatic a : (Ljava/lang/Throwable;)Ljava/lang/Throwable;
    //   944: athrow
    //   945: aload_3
    //   946: getstatic burp/Zk12.Zu : Ljava/lang/String;
    //   949: getstatic burp/Ztes.ZX : Ljava/lang/Object;
    //   952: checkcast java/math/BigInteger
    //   955: invokevirtual intValue : ()I
    //   958: bipush #32
    //   960: irem
    //   961: invokestatic abs : (I)I
    //   964: invokevirtual charAt : (I)C
    //   967: invokevirtual append : (C)Ljava/lang/StringBuilder;
    //   970: pop
    //   971: iload_2
    //   972: ifne -> 1348
    //   975: goto -> 982
    //   978: invokestatic a : (Ljava/lang/Throwable;)Ljava/lang/Throwable;
    //   981: athrow
    //   982: aload_3
    //   983: getstatic burp/Zgw7.ZN : Ljava/lang/String;
    //   986: getstatic burp/Zemp.Zr : Ljava/lang/Object;
    //   989: checkcast java/math/BigInteger
    //   992: invokevirtual intValue : ()I
    //   995: bipush #32
    //   997: irem
    //   998: invokestatic abs : (I)I
    //   1001: invokevirtual charAt : (I)C
    //   1004: invokevirtual append : (C)Ljava/lang/StringBuilder;
    //   1007: pop
    //   1008: iload_2
    //   1009: ifne -> 1348
    //   1012: goto -> 1019
    //   1015: invokestatic a : (Ljava/lang/Throwable;)Ljava/lang/Throwable;
    //   1018: athrow
    //   1019: aload_3
    //   1020: getstatic burp/Zgjj.Zi : Ljava/lang/String;
    //   1023: getstatic burp/Zs0b.ZI : Ljava/lang/Object;
    //   1026: checkcast java/math/BigInteger
    //   1029: invokevirtual intValue : ()I
    //   1032: bipush #32
    //   1034: irem
    //   1035: invokestatic abs : (I)I
    //   1038: invokevirtual charAt : (I)C
    //   1041: invokevirtual append : (C)Ljava/lang/StringBuilder;
    //   1044: pop
    //   1045: iload_2
    //   1046: ifne -> 1348
    //   1049: goto -> 1056
    //   1052: invokestatic a : (Ljava/lang/Throwable;)Ljava/lang/Throwable;
    //   1055: athrow
    //   1056: aload_3
    //   1057: getstatic burp/Zl1u.ZO : Ljava/lang/String;
    //   1060: getstatic burp/Zebj.Zf : Ljava/lang/Object;
    //   1063: checkcast java/math/BigInteger
    //   1066: invokevirtual intValue : ()I
    //   1069: bipush #32
    //   1071: irem
    //   1072: invokestatic abs : (I)I
    //   1075: invokevirtual charAt : (I)C
    //   1078: invokevirtual append : (C)Ljava/lang/StringBuilder;
    //   1081: pop
    //   1082: iload_2
    //   1083: ifne -> 1348
    //   1086: goto -> 1093
    //   1089: invokestatic a : (Ljava/lang/Throwable;)Ljava/lang/Throwable;
    //   1092: athrow
    //   1093: aload_3
    //   1094: getstatic burp/Zm8i.Z_ : Ljava/lang/String;
    //   1097: getstatic burp/Zgs6.Za : Ljava/lang/Object;
    //   1100: checkcast java/math/BigInteger
    //   1103: invokevirtual intValue : ()I
    //   1106: bipush #32
    //   1108: irem
    //   1109: invokestatic abs : (I)I
    //   1112: invokevirtual charAt : (I)C
    //   1115: invokevirtual append : (C)Ljava/lang/StringBuilder;
    //   1118: pop
    //   1119: iload_2
    //   1120: ifne -> 1348
    //   1123: goto -> 1130
    //   1126: invokestatic a : (Ljava/lang/Throwable;)Ljava/lang/Throwable;
    //   1129: athrow
    //   1130: aload_3
    //   1131: getstatic burp/Zs9x.ZY : Ljava/lang/String;
    //   1134: getstatic burp/Zeb7.ZJ : Ljava/lang/Object;
    //   1137: checkcast java/math/BigInteger
    //   1140: invokevirtual intValue : ()I
    //   1143: bipush #32
    //   1145: irem
    //   1146: invokestatic abs : (I)I
    //   1149: invokevirtual charAt : (I)C
    //   1152: invokevirtual append : (C)Ljava/lang/StringBuilder;
    //   1155: pop
    //   1156: iload_2
    //   1157: ifne -> 1348
    //   1160: goto -> 1167
    //   1163: invokestatic a : (Ljava/lang/Throwable;)Ljava/lang/Throwable;
    //   1166: athrow
    //   1167: aload_3
    //   1168: getstatic burp/Zgk1.Zv : Ljava/lang/String;
    //   1171: getstatic burp/Zz9p.Zw : Ljava/lang/Object;
    //   1174: checkcast java/math/BigInteger
    //   1177: invokevirtual intValue : ()I
    //   1180: bipush #32
    //   1182: irem
    //   1183: invokestatic abs : (I)I
    //   1186: invokevirtual charAt : (I)C
    //   1189: invokevirtual append : (C)Ljava/lang/StringBuilder;
    //   1192: pop
    //   1193: iload_2
    //   1194: ifne -> 1348
    //   1197: goto -> 1204
    //   1200: invokestatic a : (Ljava/lang/Throwable;)Ljava/lang/Throwable;
    //   1203: athrow
    //   1204: aload_3
    //   1205: getstatic burp/Zr04.ZA : Ljava/lang/String;
    //   1208: getstatic burp/Zrd3.ZI : Ljava/lang/Object;
    //   1211: checkcast java/math/BigInteger
    //   1214: invokevirtual intValue : ()I
    //   1217: bipush #32
    //   1219: irem
    //   1220: invokestatic abs : (I)I
    //   1223: invokevirtual charAt : (I)C
    //   1226: invokevirtual append : (C)Ljava/lang/StringBuilder;
    //   1229: pop
    //   1230: iload_2
    //   1231: ifne -> 1348
    //   1234: goto -> 1241
    //   1237: invokestatic a : (Ljava/lang/Throwable;)Ljava/lang/Throwable;
    //   1240: athrow
    //   1241: aload_3
    //   1242: getstatic burp/Zrom.ZD : Ljava/lang/String;
    //   1245: getstatic burp/Zemp.Zr : Ljava/lang/Object;
    //   1248: checkcast java/math/BigInteger
    //   1251: invokevirtual intValue : ()I
    //   1254: bipush #32
    //   1256: irem
    //   1257: invokestatic abs : (I)I
    //   1260: invokevirtual charAt : (I)C
    //   1263: invokevirtual append : (C)Ljava/lang/StringBuilder;
    //   1266: pop
    //   1267: iload_2
    //   1268: ifne -> 1348
    //   1271: goto -> 1278
    //   1274: invokestatic a : (Ljava/lang/Throwable;)Ljava/lang/Throwable;
    //   1277: athrow
    //   1278: aload_3
    //   1279: getstatic burp/Zmv9.Zm : Ljava/lang/String;
    //   1282: getstatic burp/Zsin.Za : Ljava/lang/Object;
    //   1285: checkcast java/math/BigInteger
    //   1288: invokevirtual intValue : ()I
    //   1291: bipush #32
    //   1293: irem
    //   1294: invokestatic abs : (I)I
    //   1297: invokevirtual charAt : (I)C
    //   1300: invokevirtual append : (C)Ljava/lang/StringBuilder;
    //   1303: pop
    //   1304: iload_2
    //   1305: ifne -> 1348
    //   1308: goto -> 1315
    //   1311: invokestatic a : (Ljava/lang/Throwable;)Ljava/lang/Throwable;
    //   1314: athrow
    //   1315: aload_3
    //   1316: getstatic burp/Zl3j.Zr : Ljava/lang/String;
    //   1319: getstatic burp/Zeb7.ZJ : Ljava/lang/Object;
    //   1322: checkcast java/math/BigInteger
    //   1325: invokevirtual intValue : ()I
    //   1328: bipush #32
    //   1330: irem
    //   1331: invokestatic abs : (I)I
    //   1334: invokevirtual charAt : (I)C
    //   1337: invokevirtual append : (C)Ljava/lang/StringBuilder;
    //   1340: pop
    //   1341: goto -> 1348
    //   1344: invokestatic a : (Ljava/lang/Throwable;)Ljava/lang/Throwable;
    //   1347: athrow
    //   1348: iinc #4, 1
    //   1351: iload_2
    //   1352: ifne -> 15
    //   1355: aload_3
    //   1356: invokevirtual toString : ()Ljava/lang/String;
    //   1359: putstatic burp/Zzoi.ZR : Ljava/lang/String;
    //   1362: new java/lang/StringBuilder
    //   1365: dup
    //   1366: invokespecial <init> : ()V
    //   1369: astore #4
    //   1371: iconst_0
    //   1372: istore #5
    //   1374: iload #5
    //   1376: bipush #32
    //   1378: if_icmpge -> 2743
    //   1381: iload #5
    //   1383: tableswitch default -> 2736, 0 -> 1524, 1 -> 1562, 2 -> 1600, 3 -> 1638, 4 -> 1676, 5 -> 1714, 6 -> 1752, 7 -> 1790, 8 -> 1828, 9 -> 1866, 10 -> 1904, 11 -> 1942, 12 -> 1980, 13 -> 2018, 14 -> 2056, 15 -> 2094, 16 -> 2132, 17 -> 2170, 18 -> 2208, 19 -> 2246, 20 -> 2284, 21 -> 2322, 22 -> 2360, 23 -> 2398, 24 -> 2436, 25 -> 2474, 26 -> 2512, 27 -> 2550, 28 -> 2588, 29 -> 2626, 30 -> 2664, 31 -> 2702
    //   1524: aload #4
    //   1526: getstatic burp/Zle6.Zh : Ljava/lang/String;
    //   1529: getstatic burp/Zgmo.Zo : Ljava/lang/Object;
    //   1532: checkcast java/math/BigInteger
    //   1535: invokevirtual intValue : ()I
    //   1538: bipush #32
    //   1540: irem
    //   1541: invokestatic abs : (I)I
    //   1544: invokevirtual charAt : (I)C
    //   1547: invokevirtual append : (C)Ljava/lang/StringBuilder;
    //   1550: pop
    //   1551: iload_2
    //   1552: ifne -> 2736
    //   1555: goto -> 1562
    //   1558: invokestatic a : (Ljava/lang/Throwable;)Ljava/lang/Throwable;
    //   1561: athrow
    //   1562: aload #4
    //   1564: getstatic burp/Zmzh.Zm : Ljava/lang/String;
    //   1567: getstatic burp/Zxl5.Zh : Ljava/lang/Object;
    //   1570: checkcast java/math/BigInteger
    //   1573: invokevirtual intValue : ()I
    //   1576: bipush #32
    //   1578: irem
    //   1579: invokestatic abs : (I)I
    //   1582: invokevirtual charAt : (I)C
    //   1585: invokevirtual append : (C)Ljava/lang/StringBuilder;
    //   1588: pop
    //   1589: iload_2
    //   1590: ifne -> 2736
    //   1593: goto -> 1600
    //   1596: invokestatic a : (Ljava/lang/Throwable;)Ljava/lang/Throwable;
    //   1599: athrow
    //   1600: aload #4
    //   1602: getstatic burp/Zgsy.Zv : Ljava/lang/String;
    //   1605: getstatic burp/Zt7w.ZF : Ljava/lang/Object;
    //   1608: checkcast java/math/BigInteger
    //   1611: invokevirtual intValue : ()I
    //   1614: bipush #32
    //   1616: irem
    //   1617: invokestatic abs : (I)I
    //   1620: invokevirtual charAt : (I)C
    //   1623: invokevirtual append : (C)Ljava/lang/StringBuilder;
    //   1626: pop
    //   1627: iload_2
    //   1628: ifne -> 2736
    //   1631: goto -> 1638
    //   1634: invokestatic a : (Ljava/lang/Throwable;)Ljava/lang/Throwable;
    //   1637: athrow
    //   1638: aload #4
    //   1640: getstatic burp/Zljx.ZD : Ljava/lang/String;
    //   1643: getstatic burp/Zxof.Zi : Ljava/lang/Object;
    //   1646: checkcast java/math/BigInteger
    //   1649: invokevirtual intValue : ()I
    //   1652: bipush #32
    //   1654: irem
    //   1655: invokestatic abs : (I)I
    //   1658: invokevirtual charAt : (I)C
    //   1661: invokevirtual append : (C)Ljava/lang/StringBuilder;
    //   1664: pop
    //   1665: iload_2
    //   1666: ifne -> 2736
    //   1669: goto -> 1676
    //   1672: invokestatic a : (Ljava/lang/Throwable;)Ljava/lang/Throwable;
    //   1675: athrow
    //   1676: aload #4
    //   1678: getstatic burp/Zly0.ZE : Ljava/lang/String;
    //   1681: getstatic burp/Zm4k.Zm : Ljava/lang/Object;
    //   1684: checkcast java/math/BigInteger
    //   1687: invokevirtual intValue : ()I
    //   1690: bipush #32
    //   1692: irem
    //   1693: invokestatic abs : (I)I
    //   1696: invokevirtual charAt : (I)C
    //   1699: invokevirtual append : (C)Ljava/lang/StringBuilder;
    //   1702: pop
    //   1703: iload_2
    //   1704: ifne -> 2736
    //   1707: goto -> 1714
    //   1710: invokestatic a : (Ljava/lang/Throwable;)Ljava/lang/Throwable;
    //   1713: athrow
    //   1714: aload #4
    //   1716: getstatic burp/Zmlu.ZF : Ljava/lang/String;
    //   1719: getstatic burp/Zmvk.ZK : Ljava/lang/Object;
    //   1722: checkcast java/math/BigInteger
    //   1725: invokevirtual intValue : ()I
    //   1728: bipush #32
    //   1730: irem
    //   1731: invokestatic abs : (I)I
    //   1734: invokevirtual charAt : (I)C
    //   1737: invokevirtual append : (C)Ljava/lang/StringBuilder;
    //   1740: pop
    //   1741: iload_2
    //   1742: ifne -> 2736
    //   1745: goto -> 1752
    //   1748: invokestatic a : (Ljava/lang/Throwable;)Ljava/lang/Throwable;
    //   1751: athrow
    //   1752: aload #4
    //   1754: getstatic burp/Zxdy.Zm : Ljava/lang/String;
    //   1757: getstatic burp/Zb_c.ZN : Ljava/lang/Object;
    //   1760: checkcast java/math/BigInteger
    //   1763: invokevirtual intValue : ()I
    //   1766: bipush #32
    //   1768: irem
    //   1769: invokestatic abs : (I)I
    //   1772: invokevirtual charAt : (I)C
    //   1775: invokevirtual append : (C)Ljava/lang/StringBuilder;
    //   1778: pop
    //   1779: iload_2
    //   1780: ifne -> 2736
    //   1783: goto -> 1790
    //   1786: invokestatic a : (Ljava/lang/Throwable;)Ljava/lang/Throwable;
    //   1789: athrow
    //   1790: aload #4
    //   1792: getstatic burp/Zezn.Ze : Ljava/lang/String;
    //   1795: getstatic burp/Zz58.ZD : Ljava/lang/Object;
    //   1798: checkcast java/math/BigInteger
    //   1801: invokevirtual intValue : ()I
    //   1804: bipush #32
    //   1806: irem
    //   1807: invokestatic abs : (I)I
    //   1810: invokevirtual charAt : (I)C
    //   1813: invokevirtual append : (C)Ljava/lang/StringBuilder;
    //   1816: pop
    //   1817: iload_2
    //   1818: ifne -> 2736
    //   1821: goto -> 1828
    //   1824: invokestatic a : (Ljava/lang/Throwable;)Ljava/lang/Throwable;
    //   1827: athrow
    //   1828: aload #4
    //   1830: getstatic burp/Zkor.Za : Ljava/lang/String;
    //   1833: getstatic burp/Ze3j.Ze : Ljava/lang/Object;
    //   1836: checkcast java/math/BigInteger
    //   1839: invokevirtual intValue : ()I
    //   1842: bipush #32
    //   1844: irem
    //   1845: invokestatic abs : (I)I
    //   1848: invokevirtual charAt : (I)C
    //   1851: invokevirtual append : (C)Ljava/lang/StringBuilder;
    //   1854: pop
    //   1855: iload_2
    //   1856: ifne -> 2736
    //   1859: goto -> 1866
    //   1862: invokestatic a : (Ljava/lang/Throwable;)Ljava/lang/Throwable;
    //   1865: athrow
    //   1866: aload #4
    //   1868: getstatic burp/Zzco.Zu : Ljava/lang/String;
    //   1871: getstatic burp/Zx_x.Zi : Ljava/lang/Object;
    //   1874: checkcast java/math/BigInteger
    //   1877: invokevirtual intValue : ()I
    //   1880: bipush #32
    //   1882: irem
    //   1883: invokestatic abs : (I)I
    //   1886: invokevirtual charAt : (I)C
    //   1889: invokevirtual append : (C)Ljava/lang/StringBuilder;
    //   1892: pop
    //   1893: iload_2
    //   1894: ifne -> 2736
    //   1897: goto -> 1904
    //   1900: invokestatic a : (Ljava/lang/Throwable;)Ljava/lang/Throwable;
    //   1903: athrow
    //   1904: aload #4
    //   1906: getstatic burp/Zl_u.Zc : Ljava/lang/String;
    //   1909: getstatic burp/Zxti.ZJ : Ljava/lang/Object;
    //   1912: checkcast java/math/BigInteger
    //   1915: invokevirtual intValue : ()I
    //   1918: bipush #32
    //   1920: irem
    //   1921: invokestatic abs : (I)I
    //   1924: invokevirtual charAt : (I)C
    //   1927: invokevirtual append : (C)Ljava/lang/StringBuilder;
    //   1930: pop
    //   1931: iload_2
    //   1932: ifne -> 2736
    //   1935: goto -> 1942
    //   1938: invokestatic a : (Ljava/lang/Throwable;)Ljava/lang/Throwable;
    //   1941: athrow
    //   1942: aload #4
    //   1944: getstatic burp/Zgrz.Zu : Ljava/lang/String;
    //   1947: getstatic burp/Zkc8.ZW : Ljava/lang/Object;
    //   1950: checkcast java/math/BigInteger
    //   1953: invokevirtual intValue : ()I
    //   1956: bipush #32
    //   1958: irem
    //   1959: invokestatic abs : (I)I
    //   1962: invokevirtual charAt : (I)C
    //   1965: invokevirtual append : (C)Ljava/lang/StringBuilder;
    //   1968: pop
    //   1969: iload_2
    //   1970: ifne -> 2736
    //   1973: goto -> 1980
    //   1976: invokestatic a : (Ljava/lang/Throwable;)Ljava/lang/Throwable;
    //   1979: athrow
    //   1980: aload #4
    //   1982: getstatic burp/Zzuh.ZX : Ljava/lang/String;
    //   1985: getstatic burp/Ztpg.Z_ : Ljava/lang/Object;
    //   1988: checkcast java/math/BigInteger
    //   1991: invokevirtual intValue : ()I
    //   1994: bipush #32
    //   1996: irem
    //   1997: invokestatic abs : (I)I
    //   2000: invokevirtual charAt : (I)C
    //   2003: invokevirtual append : (C)Ljava/lang/StringBuilder;
    //   2006: pop
    //   2007: iload_2
    //   2008: ifne -> 2736
    //   2011: goto -> 2018
    //   2014: invokestatic a : (Ljava/lang/Throwable;)Ljava/lang/Throwable;
    //   2017: athrow
    //   2018: aload #4
    //   2020: getstatic burp/Ztjh.ZZ : Ljava/lang/String;
    //   2023: getstatic burp/Zkca.ZQ : Ljava/lang/Object;
    //   2026: checkcast java/math/BigInteger
    //   2029: invokevirtual intValue : ()I
    //   2032: bipush #32
    //   2034: irem
    //   2035: invokestatic abs : (I)I
    //   2038: invokevirtual charAt : (I)C
    //   2041: invokevirtual append : (C)Ljava/lang/StringBuilder;
    //   2044: pop
    //   2045: iload_2
    //   2046: ifne -> 2736
    //   2049: goto -> 2056
    //   2052: invokestatic a : (Ljava/lang/Throwable;)Ljava/lang/Throwable;
    //   2055: athrow
    //   2056: aload #4
    //   2058: getstatic burp/Zr3x.ZM : Ljava/lang/String;
    //   2061: getstatic burp/Zscf.ZG : Ljava/lang/Object;
    //   2064: checkcast java/math/BigInteger
    //   2067: invokevirtual intValue : ()I
    //   2070: bipush #32
    //   2072: irem
    //   2073: invokestatic abs : (I)I
    //   2076: invokevirtual charAt : (I)C
    //   2079: invokevirtual append : (C)Ljava/lang/StringBuilder;
    //   2082: pop
    //   2083: iload_2
    //   2084: ifne -> 2736
    //   2087: goto -> 2094
    //   2090: invokestatic a : (Ljava/lang/Throwable;)Ljava/lang/Throwable;
    //   2093: athrow
    //   2094: aload #4
    //   2096: getstatic burp/Zke7.Zl : Ljava/lang/String;
    //   2099: getstatic burp/Zlqm.Zw : Ljava/lang/Object;
    //   2102: checkcast java/math/BigInteger
    //   2105: invokevirtual intValue : ()I
    //   2108: bipush #32
    //   2110: irem
    //   2111: invokestatic abs : (I)I
    //   2114: invokevirtual charAt : (I)C
    //   2117: invokevirtual append : (C)Ljava/lang/StringBuilder;
    //   2120: pop
    //   2121: iload_2
    //   2122: ifne -> 2736
    //   2125: goto -> 2132
    //   2128: invokestatic a : (Ljava/lang/Throwable;)Ljava/lang/Throwable;
    //   2131: athrow
    //   2132: aload #4
    //   2134: getstatic burp/Zl3j.Zr : Ljava/lang/String;
    //   2137: getstatic burp/Ztdg.ZE : Ljava/lang/Object;
    //   2140: checkcast java/math/BigInteger
    //   2143: invokevirtual intValue : ()I
    //   2146: bipush #32
    //   2148: irem
    //   2149: invokestatic abs : (I)I
    //   2152: invokevirtual charAt : (I)C
    //   2155: invokevirtual append : (C)Ljava/lang/StringBuilder;
    //   2158: pop
    //   2159: iload_2
    //   2160: ifne -> 2736
    //   2163: goto -> 2170
    //   2166: invokestatic a : (Ljava/lang/Throwable;)Ljava/lang/Throwable;
    //   2169: athrow
    //   2170: aload #4
    //   2172: getstatic burp/Zzb2.ZJ : Ljava/lang/String;
    //   2175: getstatic burp/Zmlu.Zi : Ljava/lang/Object;
    //   2178: checkcast java/math/BigInteger
    //   2181: invokevirtual intValue : ()I
    //   2184: bipush #32
    //   2186: irem
    //   2187: invokestatic abs : (I)I
    //   2190: invokevirtual charAt : (I)C
    //   2193: invokevirtual append : (C)Ljava/lang/StringBuilder;
    //   2196: pop
    //   2197: iload_2
    //   2198: ifne -> 2736
    //   2201: goto -> 2208
    //   2204: invokestatic a : (Ljava/lang/Throwable;)Ljava/lang/Throwable;
    //   2207: athrow
    //   2208: aload #4
    //   2210: getstatic burp/Ze57.ZV : Ljava/lang/String;
    //   2213: getstatic burp/Zl1u.Zq : Ljava/lang/Object;
    //   2216: checkcast java/math/BigInteger
    //   2219: invokevirtual intValue : ()I
    //   2222: bipush #32
    //   2224: irem
    //   2225: invokestatic abs : (I)I
    //   2228: invokevirtual charAt : (I)C
    //   2231: invokevirtual append : (C)Ljava/lang/StringBuilder;
    //   2234: pop
    //   2235: iload_2
    //   2236: ifne -> 2736
    //   2239: goto -> 2246
    //   2242: invokestatic a : (Ljava/lang/Throwable;)Ljava/lang/Throwable;
    //   2245: athrow
    //   2246: aload #4
    //   2248: getstatic burp/Zg_5.ZG : Ljava/lang/String;
    //   2251: getstatic burp/Zkff.Zr : Ljava/lang/Object;
    //   2254: checkcast java/math/BigInteger
    //   2257: invokevirtual intValue : ()I
    //   2260: bipush #32
    //   2262: irem
    //   2263: invokestatic abs : (I)I
    //   2266: invokevirtual charAt : (I)C
    //   2269: invokevirtual append : (C)Ljava/lang/StringBuilder;
    //   2272: pop
    //   2273: iload_2
    //   2274: ifne -> 2736
    //   2277: goto -> 2284
    //   2280: invokestatic a : (Ljava/lang/Throwable;)Ljava/lang/Throwable;
    //   2283: athrow
    //   2284: aload #4
    //   2286: getstatic burp/Ztip.Z_ : Ljava/lang/String;
    //   2289: getstatic burp/Zz7j.ZR : Ljava/lang/Object;
    //   2292: checkcast java/math/BigInteger
    //   2295: invokevirtual intValue : ()I
    //   2298: bipush #32
    //   2300: irem
    //   2301: invokestatic abs : (I)I
    //   2304: invokevirtual charAt : (I)C
    //   2307: invokevirtual append : (C)Ljava/lang/StringBuilder;
    //   2310: pop
    //   2311: iload_2
    //   2312: ifne -> 2736
    //   2315: goto -> 2322
    //   2318: invokestatic a : (Ljava/lang/Throwable;)Ljava/lang/Throwable;
    //   2321: athrow
    //   2322: aload #4
    //   2324: getstatic burp/Zm3x.Zu : Ljava/lang/String;
    //   2327: getstatic burp/Zl6e.Zo : Ljava/lang/Object;
    //   2330: checkcast java/math/BigInteger
    //   2333: invokevirtual intValue : ()I
    //   2336: bipush #32
    //   2338: irem
    //   2339: invokestatic abs : (I)I
    //   2342: invokevirtual charAt : (I)C
    //   2345: invokevirtual append : (C)Ljava/lang/StringBuilder;
    //   2348: pop
    //   2349: iload_2
    //   2350: ifne -> 2736
    //   2353: goto -> 2360
    //   2356: invokestatic a : (Ljava/lang/Throwable;)Ljava/lang/Throwable;
    //   2359: athrow
    //   2360: aload #4
    //   2362: getstatic burp/Zl3n.Zy : Ljava/lang/String;
    //   2365: getstatic burp/Zrh1.ZF : Ljava/lang/Object;
    //   2368: checkcast java/math/BigInteger
    //   2371: invokevirtual intValue : ()I
    //   2374: bipush #32
    //   2376: irem
    //   2377: invokestatic abs : (I)I
    //   2380: invokevirtual charAt : (I)C
    //   2383: invokevirtual append : (C)Ljava/lang/StringBuilder;
    //   2386: pop
    //   2387: iload_2
    //   2388: ifne -> 2736
    //   2391: goto -> 2398
    //   2394: invokestatic a : (Ljava/lang/Throwable;)Ljava/lang/Throwable;
    //   2397: athrow
    //   2398: aload #4
    //   2400: getstatic burp/Zkvr.Zm : Ljava/lang/String;
    //   2403: getstatic burp/Zkff.Zr : Ljava/lang/Object;
    //   2406: checkcast java/math/BigInteger
    //   2409: invokevirtual intValue : ()I
    //   2412: bipush #32
    //   2414: irem
    //   2415: invokestatic abs : (I)I
    //   2418: invokevirtual charAt : (I)C
    //   2421: invokevirtual append : (C)Ljava/lang/StringBuilder;
    //   2424: pop
    //   2425: iload_2
    //   2426: ifne -> 2736
    //   2429: goto -> 2436
    //   2432: invokestatic a : (Ljava/lang/Throwable;)Ljava/lang/Throwable;
    //   2435: athrow
    //   2436: aload #4
    //   2438: getstatic burp/Zsuw.ZK : Ljava/lang/String;
    //   2441: getstatic burp/Zxsb.ZN : Ljava/lang/Object;
    //   2444: checkcast java/math/BigInteger
    //   2447: invokevirtual intValue : ()I
    //   2450: bipush #32
    //   2452: irem
    //   2453: invokestatic abs : (I)I
    //   2456: invokevirtual charAt : (I)C
    //   2459: invokevirtual append : (C)Ljava/lang/StringBuilder;
    //   2462: pop
    //   2463: iload_2
    //   2464: ifne -> 2736
    //   2467: goto -> 2474
    //   2470: invokestatic a : (Ljava/lang/Throwable;)Ljava/lang/Throwable;
    //   2473: athrow
    //   2474: aload #4
    //   2476: getstatic burp/Zb8x.Zp : Ljava/lang/String;
    //   2479: getstatic burp/Zehi.Zb : Ljava/lang/Object;
    //   2482: checkcast java/math/BigInteger
    //   2485: invokevirtual intValue : ()I
    //   2488: bipush #32
    //   2490: irem
    //   2491: invokestatic abs : (I)I
    //   2494: invokevirtual charAt : (I)C
    //   2497: invokevirtual append : (C)Ljava/lang/StringBuilder;
    //   2500: pop
    //   2501: iload_2
    //   2502: ifne -> 2736
    //   2505: goto -> 2512
    //   2508: invokestatic a : (Ljava/lang/Throwable;)Ljava/lang/Throwable;
    //   2511: athrow
    //   2512: aload #4
    //   2514: getstatic burp/Ze3d.ZL : Ljava/lang/String;
    //   2517: getstatic burp/Zgia.Zx : Ljava/lang/Object;
    //   2520: checkcast java/math/BigInteger
    //   2523: invokevirtual intValue : ()I
    //   2526: bipush #32
    //   2528: irem
    //   2529: invokestatic abs : (I)I
    //   2532: invokevirtual charAt : (I)C
    //   2535: invokevirtual append : (C)Ljava/lang/StringBuilder;
    //   2538: pop
    //   2539: iload_2
    //   2540: ifne -> 2736
    //   2543: goto -> 2550
    //   2546: invokestatic a : (Ljava/lang/Throwable;)Ljava/lang/Throwable;
    //   2549: athrow
    //   2550: aload #4
    //   2552: getstatic burp/Zsfj.Zg : Ljava/lang/String;
    //   2555: getstatic burp/Zkq9.Ze : Ljava/lang/Object;
    //   2558: checkcast java/math/BigInteger
    //   2561: invokevirtual intValue : ()I
    //   2564: bipush #32
    //   2566: irem
    //   2567: invokestatic abs : (I)I
    //   2570: invokevirtual charAt : (I)C
    //   2573: invokevirtual append : (C)Ljava/lang/StringBuilder;
    //   2576: pop
    //   2577: iload_2
    //   2578: ifne -> 2736
    //   2581: goto -> 2588
    //   2584: invokestatic a : (Ljava/lang/Throwable;)Ljava/lang/Throwable;
    //   2587: athrow
    //   2588: aload #4
    //   2590: getstatic burp/Zxn7.ZG : Ljava/lang/String;
    //   2593: getstatic burp/Zlhy.ZN : Ljava/lang/Object;
    //   2596: checkcast java/math/BigInteger
    //   2599: invokevirtual intValue : ()I
    //   2602: bipush #32
    //   2604: irem
    //   2605: invokestatic abs : (I)I
    //   2608: invokevirtual charAt : (I)C
    //   2611: invokevirtual append : (C)Ljava/lang/StringBuilder;
    //   2614: pop
    //   2615: iload_2
    //   2616: ifne -> 2736
    //   2619: goto -> 2626
    //   2622: invokestatic a : (Ljava/lang/Throwable;)Ljava/lang/Throwable;
    //   2625: athrow
    //   2626: aload #4
    //   2628: getstatic burp/Zea9.Zd : Ljava/lang/String;
    //   2631: getstatic burp/Zg6f.Zl : Ljava/lang/Object;
    //   2634: checkcast java/math/BigInteger
    //   2637: invokevirtual intValue : ()I
    //   2640: bipush #32
    //   2642: irem
    //   2643: invokestatic abs : (I)I
    //   2646: invokevirtual charAt : (I)C
    //   2649: invokevirtual append : (C)Ljava/lang/StringBuilder;
    //   2652: pop
    //   2653: iload_2
    //   2654: ifne -> 2736
    //   2657: goto -> 2664
    //   2660: invokestatic a : (Ljava/lang/Throwable;)Ljava/lang/Throwable;
    //   2663: athrow
    //   2664: aload #4
    //   2666: getstatic burp/Zlps.ZO : Ljava/lang/String;
    //   2669: getstatic burp/Zz0.ZJ : Ljava/lang/Object;
    //   2672: checkcast java/math/BigInteger
    //   2675: invokevirtual intValue : ()I
    //   2678: bipush #32
    //   2680: irem
    //   2681: invokestatic abs : (I)I
    //   2684: invokevirtual charAt : (I)C
    //   2687: invokevirtual append : (C)Ljava/lang/StringBuilder;
    //   2690: pop
    //   2691: iload_2
    //   2692: ifne -> 2736
    //   2695: goto -> 2702
    //   2698: invokestatic a : (Ljava/lang/Throwable;)Ljava/lang/Throwable;
    //   2701: athrow
    //   2702: aload #4
    //   2704: getstatic burp/Zgfm.ZE : Ljava/lang/String;
    //   2707: getstatic burp/Zmir.ZF : Ljava/lang/Object;
    //   2710: checkcast java/math/BigInteger
    //   2713: invokevirtual intValue : ()I
    //   2716: bipush #32
    //   2718: irem
    //   2719: invokestatic abs : (I)I
    //   2722: invokevirtual charAt : (I)C
    //   2725: invokevirtual append : (C)Ljava/lang/StringBuilder;
    //   2728: pop
    //   2729: goto -> 2736
    //   2732: invokestatic a : (Ljava/lang/Throwable;)Ljava/lang/Throwable;
    //   2735: athrow
    //   2736: iinc #5, 1
    //   2739: iload_2
    //   2740: ifne -> 1374
    //   2743: aload #4
    //   2745: invokevirtual toString : ()Ljava/lang/String;
    //   2748: putstatic burp/Zlsg.Zs : Ljava/lang/String;
    //   2751: getstatic burp/Zty4.ZQ : Ljava/lang/Object;
    //   2754: checkcast java/math/BigInteger
    //   2757: invokevirtual toByteArray : ()[B
    //   2760: astore #5
    //   2762: aload #5
    //   2764: arraylength
    //   2765: bipush #8
    //   2767: iadd
    //   2768: bipush #6
    //   2770: ishr
    //   2771: iconst_1
    //   2772: iadd
    //   2773: bipush #16
    //   2775: imul
    //   2776: newarray int
    //   2778: astore #7
    //   2780: iconst_0
    //   2781: istore #8
    //   2783: iload #8
    //   2785: aload #5
    //   2787: arraylength
    //   2788: if_icmpge -> 2832
    //   2791: aload #5
    //   2793: iload #8
    //   2795: baload
    //   2796: sipush #255
    //   2799: iand
    //   2800: istore #9
    //   2802: aload #7
    //   2804: iload #8
    //   2806: iconst_2
    //   2807: ishr
    //   2808: dup2
    //   2809: iaload
    //   2810: iload #9
    //   2812: bipush #24
    //   2814: iload #8
    //   2816: iconst_4
    //   2817: irem
    //   2818: bipush #8
    //   2820: imul
    //   2821: isub
    //   2822: ishl
    //   2823: ior
    //   2824: iastore
    //   2825: iinc #8, 1
    //   2828: iload_2
    //   2829: ifne -> 2783
    //   2832: aload #7
    //   2834: iload #8
    //   2836: iconst_2
    //   2837: ishr
    //   2838: dup2
    //   2839: iaload
    //   2840: sipush #128
    //   2843: bipush #24
    //   2845: iload #8
    //   2847: iconst_4
    //   2848: irem
    //   2849: bipush #8
    //   2851: imul
    //   2852: isub
    //   2853: ishl
    //   2854: ior
    //   2855: iastore
    //   2856: aload #7
    //   2858: aload #7
    //   2860: arraylength
    //   2861: iconst_1
    //   2862: isub
    //   2863: aload #5
    //   2865: arraylength
    //   2866: bipush #8
    //   2868: imul
    //   2869: iastore
    //   2870: bipush #80
    //   2872: newarray int
    //   2874: astore #9
    //   2876: ldc 1732584193
    //   2878: istore #10
    //   2880: ldc -271733879
    //   2882: istore #11
    //   2884: ldc -1732584194
    //   2886: istore #12
    //   2888: ldc 271733878
    //   2890: istore #13
    //   2892: ldc -1009589776
    //   2894: istore #14
    //   2896: iconst_0
    //   2897: istore #8
    //   2899: iload #8
    //   2901: aload #7
    //   2903: arraylength
    //   2904: if_icmpge -> 3226
    //   2907: iload #10
    //   2909: istore #15
    //   2911: iload #11
    //   2913: istore #16
    //   2915: iload #12
    //   2917: istore #17
    //   2919: iload #13
    //   2921: istore #18
    //   2923: iload #14
    //   2925: istore #19
    //   2927: iconst_0
    //   2928: istore #20
    //   2930: iload #20
    //   2932: bipush #80
    //   2934: if_icmpge -> 3184
    //   2937: iload #20
    //   2939: bipush #16
    //   2941: if_icmpge -> 2968
    //   2944: aload #9
    //   2946: iload #20
    //   2948: aload #7
    //   2950: iload #8
    //   2952: iload #20
    //   2954: iadd
    //   2955: iaload
    //   2956: iastore
    //   2957: iload_2
    //   2958: ifne -> 3023
    //   2961: goto -> 2968
    //   2964: invokestatic a : (Ljava/lang/Throwable;)Ljava/lang/Throwable;
    //   2967: athrow
    //   2968: aload #9
    //   2970: iload #20
    //   2972: iconst_3
    //   2973: isub
    //   2974: iaload
    //   2975: aload #9
    //   2977: iload #20
    //   2979: bipush #8
    //   2981: isub
    //   2982: iaload
    //   2983: ixor
    //   2984: aload #9
    //   2986: iload #20
    //   2988: bipush #14
    //   2990: isub
    //   2991: iaload
    //   2992: ixor
    //   2993: aload #9
    //   2995: iload #20
    //   2997: bipush #16
    //   2999: isub
    //   3000: iaload
    //   3001: ixor
    //   3002: istore #21
    //   3004: iload #21
    //   3006: iconst_1
    //   3007: ishl
    //   3008: iload #21
    //   3010: bipush #31
    //   3012: iushr
    //   3013: ior
    //   3014: istore #22
    //   3016: aload #9
    //   3018: iload #20
    //   3020: iload #22
    //   3022: iastore
    //   3023: iload #10
    //   3025: iconst_5
    //   3026: ishl
    //   3027: iload #10
    //   3029: bipush #27
    //   3031: iushr
    //   3032: ior
    //   3033: istore #21
    //   3035: iload #21
    //   3037: iload #14
    //   3039: iadd
    //   3040: aload #9
    //   3042: iload #20
    //   3044: iaload
    //   3045: iadd
    //   3046: iload #20
    //   3048: bipush #20
    //   3050: if_icmpge -> 3076
    //   3053: ldc 1518500249
    //   3055: iload #11
    //   3057: iload #12
    //   3059: iand
    //   3060: iload #11
    //   3062: iconst_m1
    //   3063: ixor
    //   3064: iload #13
    //   3066: iand
    //   3067: ior
    //   3068: iadd
    //   3069: goto -> 3146
    //   3072: invokestatic a : (Ljava/lang/Throwable;)Ljava/lang/Throwable;
    //   3075: athrow
    //   3076: iload #20
    //   3078: bipush #40
    //   3080: if_icmpge -> 3101
    //   3083: ldc 1859775393
    //   3085: iload #11
    //   3087: iload #12
    //   3089: ixor
    //   3090: iload #13
    //   3092: ixor
    //   3093: iadd
    //   3094: goto -> 3146
    //   3097: invokestatic a : (Ljava/lang/Throwable;)Ljava/lang/Throwable;
    //   3100: athrow
    //   3101: iload #20
    //   3103: bipush #60
    //   3105: if_icmpge -> 3135
    //   3108: ldc -1894007588
    //   3110: iload #11
    //   3112: iload #12
    //   3114: iand
    //   3115: iload #11
    //   3117: iload #13
    //   3119: iand
    //   3120: ior
    //   3121: iload #12
    //   3123: iload #13
    //   3125: iand
    //   3126: ior
    //   3127: iadd
    //   3128: goto -> 3146
    //   3131: invokestatic a : (Ljava/lang/Throwable;)Ljava/lang/Throwable;
    //   3134: athrow
    //   3135: ldc -899497514
    //   3137: iload #11
    //   3139: iload #12
    //   3141: ixor
    //   3142: iload #13
    //   3144: ixor
    //   3145: iadd
    //   3146: iadd
    //   3147: istore #22
    //   3149: iload #13
    //   3151: istore #14
    //   3153: iload #12
    //   3155: istore #13
    //   3157: iload #11
    //   3159: bipush #30
    //   3161: ishl
    //   3162: iload #11
    //   3164: iconst_2
    //   3165: iushr
    //   3166: ior
    //   3167: istore #12
    //   3169: iload #10
    //   3171: istore #11
    //   3173: iload #22
    //   3175: istore #10
    //   3177: iinc #20, 1
    //   3180: iload_2
    //   3181: ifne -> 2930
    //   3184: iload #10
    //   3186: iload #15
    //   3188: iadd
    //   3189: istore #10
    //   3191: iload #11
    //   3193: iload #16
    //   3195: iadd
    //   3196: istore #11
    //   3198: iload #12
    //   3200: iload #17
    //   3202: iadd
    //   3203: istore #12
    //   3205: iload #13
    //   3207: iload #18
    //   3209: iadd
    //   3210: istore #13
    //   3212: iload #14
    //   3214: iload #19
    //   3216: iadd
    //   3217: istore #14
    //   3219: iinc #8, 16
    //   3222: iload_2
    //   3223: ifne -> 2899
    //   3226: iconst_5
    //   3227: newarray int
    //   3229: dup
    //   3230: iconst_0
    //   3231: iload #10
    //   3233: iastore
    //   3234: dup
    //   3235: iconst_1
    //   3236: iload #11
    //   3238: iastore
    //   3239: dup
    //   3240: iconst_2
    //   3241: iload #12
    //   3243: iastore
    //   3244: dup
    //   3245: iconst_3
    //   3246: iload #13
    //   3248: iastore
    //   3249: dup
    //   3250: iconst_4
    //   3251: iload #14
    //   3253: iastore
    //   3254: astore #15
    //   3256: bipush #20
    //   3258: newarray byte
    //   3260: astore #16
    //   3262: iconst_0
    //   3263: istore #17
    //   3265: iload #17
    //   3267: bipush #20
    //   3269: if_icmpge -> 3310
    //   3272: aload #15
    //   3274: iload #17
    //   3276: iconst_4
    //   3277: idiv
    //   3278: iaload
    //   3279: istore #18
    //   3281: iconst_3
    //   3282: iload #17
    //   3284: iconst_4
    //   3285: irem
    //   3286: isub
    //   3287: bipush #8
    //   3289: imul
    //   3290: istore #19
    //   3292: aload #16
    //   3294: iload #17
    //   3296: iload #18
    //   3298: iload #19
    //   3300: iushr
    //   3301: i2b
    //   3302: bastore
    //   3303: iinc #17, 1
    //   3306: iload_2
    //   3307: ifne -> 3265
    //   3310: aload #16
    //   3312: astore #6
    //   3314: sipush #26760
    //   3317: new java/math/BigInteger
    //   3320: dup
    //   3321: aload #6
    //   3323: invokespecial <init> : ([B)V
    //   3326: invokevirtual abs : ()Ljava/math/BigInteger;
    //   3329: putstatic burp/Ze6k.Zs : Ljava/lang/Object;
    //   3332: sipush #-3282
    //   3335: invokestatic a : (II)Ljava/lang/String;
    //   3338: iconst_1
    //   3339: ldc burp/Zedz
    //   3341: invokevirtual getClassLoader : ()Ljava/lang/ClassLoader;
    //   3344: invokestatic forName : (Ljava/lang/String;ZLjava/lang/ClassLoader;)Ljava/lang/Class;
    //   3347: invokevirtual getDeclaredFields : ()[Ljava/lang/reflect/Field;
    //   3350: astore #5
    //   3352: aload #5
    //   3354: arraylength
    //   3355: istore #6
    //   3357: iconst_0
    //   3358: istore #7
    //   3360: iload #7
    //   3362: iload #6
    //   3364: if_icmpge -> 3502
    //   3367: aload #5
    //   3369: iload #7
    //   3371: aaload
    //   3372: astore #8
    //   3374: aload #8
    //   3376: invokevirtual getModifiers : ()I
    //   3379: invokestatic isStatic : (I)Z
    //   3382: ifne -> 3392
    //   3385: goto -> 3495
    //   3388: invokestatic a : (Ljava/lang/Throwable;)Ljava/lang/Throwable;
    //   3391: athrow
    //   3392: aload #8
    //   3394: invokevirtual getType : ()Ljava/lang/Class;
    //   3397: astore #9
    //   3399: aload #9
    //   3401: ifnull -> 3482
    //   3404: aload #9
    //   3406: invokevirtual isPrimitive : ()Z
    //   3409: ifne -> 3482
    //   3412: goto -> 3419
    //   3415: invokestatic a : (Ljava/lang/Throwable;)Ljava/lang/Throwable;
    //   3418: athrow
    //   3419: aload #9
    //   3421: invokevirtual getPackage : ()Ljava/lang/Package;
    //   3424: ifnull -> 3482
    //   3427: goto -> 3434
    //   3430: invokestatic a : (Ljava/lang/Throwable;)Ljava/lang/Throwable;
    //   3433: athrow
    //   3434: aload #9
    //   3436: invokevirtual getPackage : ()Ljava/lang/Package;
    //   3439: invokevirtual getName : ()Ljava/lang/String;
    //   3442: ifnull -> 3482
    //   3445: goto -> 3452
    //   3448: invokestatic a : (Ljava/lang/Throwable;)Ljava/lang/Throwable;
    //   3451: athrow
    //   3452: aload #9
    //   3454: invokevirtual getPackage : ()Ljava/lang/Package;
    //   3457: invokevirtual getName : ()Ljava/lang/String;
    //   3460: sipush #26763
    //   3463: sipush #-7056
    //   3466: invokestatic a : (II)Ljava/lang/String;
    //   3469: invokevirtual startsWith : (Ljava/lang/String;)Z
    //   3472: ifne -> 3482
    //   3475: goto -> 3482
    //   3478: invokestatic a : (Ljava/lang/Throwable;)Ljava/lang/Throwable;
    //   3481: athrow
    //   3482: aload #8
    //   3484: iconst_1
    //   3485: invokevirtual setAccessible : (Z)V
    //   3488: aload #8
    //   3490: aconst_null
    //   3491: invokevirtual get : (Ljava/lang/Object;)Ljava/lang/Object;
    //   3494: pop
    //   3495: iinc #7, 1
    //   3498: iload_2
    //   3499: ifne -> 3360
    //   3502: sipush #26755
    //   3505: sipush #-1567
    //   3508: invokestatic a : (II)Ljava/lang/String;
    //   3511: invokestatic forName : (Ljava/lang/String;)Ljava/lang/Class;
    //   3514: invokevirtual getDeclaredMethods : ()[Ljava/lang/reflect/Method;
    //   3517: astore #5
    //   3519: aload #5
    //   3521: arraylength
    //   3522: istore #6
    //   3524: iconst_0
    //   3525: istore #7
    //   3527: iload #7
    //   3529: iload #6
    //   3531: if_icmpge -> 3643
    //   3534: aload #5
    //   3536: iload #7
    //   3538: aaload
    //   3539: astore #8
    //   3541: aload #8
    //   3543: invokevirtual getParameterTypes : ()[Ljava/lang/Class;
    //   3546: pop
    //   3547: aload #8
    //   3549: invokevirtual getModifiers : ()I
    //   3552: invokestatic isStatic : (I)Z
    //   3555: ifeq -> 3629
    //   3558: aload #8
    //   3560: invokevirtual getParameterTypes : ()[Ljava/lang/Class;
    //   3563: arraylength
    //   3564: iconst_2
    //   3565: if_icmpne -> 3629
    //   3568: goto -> 3575
    //   3571: invokestatic a : (Ljava/lang/Throwable;)Ljava/lang/Throwable;
    //   3574: athrow
    //   3575: aload #8
    //   3577: invokevirtual getReturnType : ()Ljava/lang/Class;
    //   3580: getstatic java/lang/Boolean.TYPE : Ljava/lang/Class;
    //   3583: if_acmpne -> 3629
    //   3586: goto -> 3593
    //   3589: invokestatic a : (Ljava/lang/Throwable;)Ljava/lang/Throwable;
    //   3592: athrow
    //   3593: aload #8
    //   3595: iconst_1
    //   3596: invokevirtual setAccessible : (Z)V
    //   3599: aload #8
    //   3601: aconst_null
    //   3602: iconst_2
    //   3603: anewarray java/lang/Object
    //   3606: dup
    //   3607: iconst_0
    //   3608: aload_0
    //   3609: aastore
    //   3610: dup
    //   3611: iconst_1
    //   3612: aload_1
    //   3613: aastore
    //   3614: invokevirtual invoke : (Ljava/lang/Object;[Ljava/lang/Object;)Ljava/lang/Object;
    //   3617: pop
    //   3618: iload_2
    //   3619: ifne -> 3643
    //   3622: goto -> 3629
    //   3625: invokestatic a : (Ljava/lang/Throwable;)Ljava/lang/Throwable;
    //   3628: athrow
    //   3629: iinc #7, 1
    //   3632: iload_2
    //   3633: ifne -> 3527
    //   3636: goto -> 3643
    //   3639: invokestatic a : (Ljava/lang/Throwable;)Ljava/lang/Throwable;
    //   3642: athrow
    //   3643: sipush #26766
    //   3646: sipush #-28162
    //   3649: invokestatic a : (II)Ljava/lang/String;
    //   3652: iconst_1
    //   3653: ldc burp/Zmnb
    //   3655: invokevirtual getClassLoader : ()Ljava/lang/ClassLoader;
    //   3658: invokestatic forName : (Ljava/lang/String;ZLjava/lang/ClassLoader;)Ljava/lang/Class;
    //   3661: invokevirtual getDeclaredFields : ()[Ljava/lang/reflect/Field;
    //   3664: astore #5
    //   3666: aload #5
    //   3668: arraylength
    //   3669: istore #6
    //   3671: iconst_0
    //   3672: istore #7
    //   3674: iload #7
    //   3676: iload #6
    //   3678: if_icmpge -> 3816
    //   3681: aload #5
    //   3683: iload #7
    //   3685: aaload
    //   3686: astore #8
    //   3688: aload #8
    //   3690: invokevirtual getModifiers : ()I
    //   3693: invokestatic isStatic : (I)Z
    //   3696: ifne -> 3706
    //   3699: goto -> 3809
    //   3702: invokestatic a : (Ljava/lang/Throwable;)Ljava/lang/Throwable;
    //   3705: athrow
    //   3706: aload #8
    //   3708: invokevirtual getType : ()Ljava/lang/Class;
    //   3711: astore #9
    //   3713: aload #9
    //   3715: ifnull -> 3796
    //   3718: aload #9
    //   3720: invokevirtual isPrimitive : ()Z
    //   3723: ifne -> 3796
    //   3726: goto -> 3733
    //   3729: invokestatic a : (Ljava/lang/Throwable;)Ljava/lang/Throwable;
    //   3732: athrow
    //   3733: aload #9
    //   3735: invokevirtual getPackage : ()Ljava/lang/Package;
    //   3738: ifnull -> 3796
    //   3741: goto -> 3748
    //   3744: invokestatic a : (Ljava/lang/Throwable;)Ljava/lang/Throwable;
    //   3747: athrow
    //   3748: aload #9
    //   3750: invokevirtual getPackage : ()Ljava/lang/Package;
    //   3753: invokevirtual getName : ()Ljava/lang/String;
    //   3756: ifnull -> 3796
    //   3759: goto -> 3766
    //   3762: invokestatic a : (Ljava/lang/Throwable;)Ljava/lang/Throwable;
    //   3765: athrow
    //   3766: aload #9
    //   3768: invokevirtual getPackage : ()Ljava/lang/Package;
    //   3771: invokevirtual getName : ()Ljava/lang/String;
    //   3774: sipush #26762
    //   3777: sipush #31061
    //   3780: invokestatic a : (II)Ljava/lang/String;
    //   3783: invokevirtual startsWith : (Ljava/lang/String;)Z
    //   3786: ifne -> 3796
    //   3789: goto -> 3796
    //   3792: invokestatic a : (Ljava/lang/Throwable;)Ljava/lang/Throwable;
    //   3795: athrow
    //   3796: aload #8
    //   3798: iconst_1
    //   3799: invokevirtual setAccessible : (Z)V
    //   3802: aload #8
    //   3804: aconst_null
    //   3805: invokevirtual get : (Ljava/lang/Object;)Ljava/lang/Object;
    //   3808: pop
    //   3809: iinc #7, 1
    //   3812: iload_2
    //   3813: ifne -> 3674
    //   3816: sipush #26752
    //   3819: sipush #538
    //   3822: invokestatic a : (II)Ljava/lang/String;
    //   3825: invokestatic forName : (Ljava/lang/String;)Ljava/lang/Class;
    //   3828: invokevirtual getDeclaredMethods : ()[Ljava/lang/reflect/Method;
    //   3831: astore #5
    //   3833: aload #5
    //   3835: arraylength
    //   3836: istore #6
    //   3838: iconst_0
    //   3839: istore #7
    //   3841: iload #7
    //   3843: iload #6
    //   3845: if_icmpge -> 3978
    //   3848: aload #5
    //   3850: iload #7
    //   3852: aaload
    //   3853: astore #8
    //   3855: aload #8
    //   3857: invokevirtual getParameterTypes : ()[Ljava/lang/Class;
    //   3860: pop
    //   3861: aload #8
    //   3863: invokevirtual getModifiers : ()I
    //   3866: invokestatic isStatic : (I)Z
    //   3869: ifeq -> 3964
    //   3872: aload #8
    //   3874: invokevirtual getParameterTypes : ()[Ljava/lang/Class;
    //   3877: arraylength
    //   3878: iconst_2
    //   3879: if_icmpne -> 3964
    //   3882: goto -> 3889
    //   3885: invokestatic a : (Ljava/lang/Throwable;)Ljava/lang/Throwable;
    //   3888: athrow
    //   3889: aload #8
    //   3891: invokevirtual getReturnType : ()Ljava/lang/Class;
    //   3894: getstatic java/lang/Void.TYPE : Ljava/lang/Class;
    //   3897: invokevirtual equals : (Ljava/lang/Object;)Z
    //   3900: ifeq -> 3964
    //   3903: goto -> 3910
    //   3906: invokestatic a : (Ljava/lang/Throwable;)Ljava/lang/Throwable;
    //   3909: athrow
    //   3910: aload #8
    //   3912: iconst_1
    //   3913: invokevirtual setAccessible : (Z)V
    //   3916: aload #8
    //   3918: aconst_null
    //   3919: iconst_2
    //   3920: anewarray java/lang/Object
    //   3923: dup
    //   3924: iconst_0
    //   3925: aload_0
    //   3926: aastore
    //   3927: dup
    //   3928: iconst_1
    //   3929: aload_1
    //   3930: ifnonnull -> 3948
    //   3933: goto -> 3940
    //   3936: invokestatic a : (Ljava/lang/Throwable;)Ljava/lang/Throwable;
    //   3939: athrow
    //   3940: aload_1
    //   3941: goto -> 3955
    //   3944: invokestatic a : (Ljava/lang/Throwable;)Ljava/lang/Throwable;
    //   3947: athrow
    //   3948: aload_1
    //   3949: checkcast [B
    //   3952: invokevirtual clone : ()Ljava/lang/Object;
    //   3955: aastore
    //   3956: invokevirtual invoke : (Ljava/lang/Object;[Ljava/lang/Object;)Ljava/lang/Object;
    //   3959: pop
    //   3960: iload_2
    //   3961: ifne -> 3978
    //   3964: iinc #7, 1
    //   3967: iload_2
    //   3968: ifne -> 3841
    //   3971: goto -> 3978
    //   3974: invokestatic a : (Ljava/lang/Throwable;)Ljava/lang/Throwable;
    //   3977: athrow
    //   3978: getstatic burp/Zty2.Zl : Ljava/lang/Object;
    //   3981: checkcast java/math/BigInteger
    //   3984: invokevirtual toByteArray : ()[B
    //   3987: astore #5
    //   3989: iconst_0
    //   3990: istore #7
    //   3992: iconst_0
    //   3993: istore #8
    //   3995: iload #8
    //   3997: aload #5
    //   3999: arraylength
    //   4000: if_icmpge -> 4146
    //   4003: aload #5
    //   4005: iload #8
    //   4007: baload
    //   4008: istore #9
    //   4010: iload #9
    //   4012: bipush #48
    //   4014: if_icmplt -> 4031
    //   4017: iload #9
    //   4019: bipush #57
    //   4021: if_icmple -> 4129
    //   4024: goto -> 4031
    //   4027: invokestatic a : (Ljava/lang/Throwable;)Ljava/lang/Throwable;
    //   4030: athrow
    //   4031: iload #9
    //   4033: bipush #65
    //   4035: if_icmplt -> 4059
    //   4038: goto -> 4045
    //   4041: invokestatic a : (Ljava/lang/Throwable;)Ljava/lang/Throwable;
    //   4044: athrow
    //   4045: iload #9
    //   4047: bipush #90
    //   4049: if_icmple -> 4129
    //   4052: goto -> 4059
    //   4055: invokestatic a : (Ljava/lang/Throwable;)Ljava/lang/Throwable;
    //   4058: athrow
    //   4059: iload #9
    //   4061: bipush #97
    //   4063: if_icmplt -> 4087
    //   4066: goto -> 4073
    //   4069: invokestatic a : (Ljava/lang/Throwable;)Ljava/lang/Throwable;
    //   4072: athrow
    //   4073: iload #9
    //   4075: bipush #122
    //   4077: if_icmple -> 4129
    //   4080: goto -> 4087
    //   4083: invokestatic a : (Ljava/lang/Throwable;)Ljava/lang/Throwable;
    //   4086: athrow
    //   4087: iload #9
    //   4089: bipush #43
    //   4091: if_icmpeq -> 4129
    //   4094: goto -> 4101
    //   4097: invokestatic a : (Ljava/lang/Throwable;)Ljava/lang/Throwable;
    //   4100: athrow
    //   4101: iload #9
    //   4103: bipush #47
    //   4105: if_icmpeq -> 4129
    //   4108: goto -> 4115
    //   4111: invokestatic a : (Ljava/lang/Throwable;)Ljava/lang/Throwable;
    //   4114: athrow
    //   4115: iload #9
    //   4117: bipush #61
    //   4119: if_icmpne -> 4139
    //   4122: goto -> 4129
    //   4125: invokestatic a : (Ljava/lang/Throwable;)Ljava/lang/Throwable;
    //   4128: athrow
    //   4129: iinc #7, 1
    //   4132: goto -> 4139
    //   4135: invokestatic a : (Ljava/lang/Throwable;)Ljava/lang/Throwable;
    //   4138: athrow
    //   4139: iinc #8, 1
    //   4142: iload_2
    //   4143: ifne -> 3995
    //   4146: iload #7
    //   4148: newarray byte
    //   4150: astore #8
    //   4152: iconst_0
    //   4153: istore #9
    //   4155: iconst_0
    //   4156: istore #10
    //   4158: iload #10
    //   4160: aload #5
    //   4162: arraylength
    //   4163: if_icmpge -> 4316
    //   4166: aload #5
    //   4168: iload #10
    //   4170: baload
    //   4171: istore #11
    //   4173: iload #11
    //   4175: bipush #48
    //   4177: if_icmplt -> 4194
    //   4180: iload #11
    //   4182: bipush #57
    //   4184: if_icmple -> 4292
    //   4187: goto -> 4194
    //   4190: invokestatic a : (Ljava/lang/Throwable;)Ljava/lang/Throwable;
    //   4193: athrow
    //   4194: iload #11
    //   4196: bipush #65
    //   4198: if_icmplt -> 4222
    //   4201: goto -> 4208
    //   4204: invokestatic a : (Ljava/lang/Throwable;)Ljava/lang/Throwable;
    //   4207: athrow
    //   4208: iload #11
    //   4210: bipush #90
    //   4212: if_icmple -> 4292
    //   4215: goto -> 4222
    //   4218: invokestatic a : (Ljava/lang/Throwable;)Ljava/lang/Throwable;
    //   4221: athrow
    //   4222: iload #11
    //   4224: bipush #97
    //   4226: if_icmplt -> 4250
    //   4229: goto -> 4236
    //   4232: invokestatic a : (Ljava/lang/Throwable;)Ljava/lang/Throwable;
    //   4235: athrow
    //   4236: iload #11
    //   4238: bipush #122
    //   4240: if_icmple -> 4292
    //   4243: goto -> 4250
    //   4246: invokestatic a : (Ljava/lang/Throwable;)Ljava/lang/Throwable;
    //   4249: athrow
    //   4250: iload #11
    //   4252: bipush #43
    //   4254: if_icmpeq -> 4292
    //   4257: goto -> 4264
    //   4260: invokestatic a : (Ljava/lang/Throwable;)Ljava/lang/Throwable;
    //   4263: athrow
    //   4264: iload #11
    //   4266: bipush #47
    //   4268: if_icmpeq -> 4292
    //   4271: goto -> 4278
    //   4274: invokestatic a : (Ljava/lang/Throwable;)Ljava/lang/Throwable;
    //   4277: athrow
    //   4278: iload #11
    //   4280: bipush #61
    //   4282: if_icmpne -> 4309
    //   4285: goto -> 4292
    //   4288: invokestatic a : (Ljava/lang/Throwable;)Ljava/lang/Throwable;
    //   4291: athrow
    //   4292: aload #8
    //   4294: iload #9
    //   4296: iload #11
    //   4298: bastore
    //   4299: iinc #9, 1
    //   4302: goto -> 4309
    //   4305: invokestatic a : (Ljava/lang/Throwable;)Ljava/lang/Throwable;
    //   4308: athrow
    //   4309: iinc #10, 1
    //   4312: iload_2
    //   4313: ifne -> 4158
    //   4316: aload #8
    //   4318: astore #6
    //   4320: aload #6
    //   4322: astore #5
    //   4324: aload #5
    //   4326: arraylength
    //   4327: istore #7
    //   4329: aload #5
    //   4331: iload #7
    //   4333: iconst_1
    //   4334: isub
    //   4335: baload
    //   4336: bipush #61
    //   4338: if_icmpne -> 4348
    //   4341: iinc #7, -1
    //   4344: iload_2
    //   4345: ifne -> 4329
    //   4348: iload #7
    //   4350: aload #5
    //   4352: arraylength
    //   4353: iconst_4
    //   4354: idiv
    //   4355: isub
    //   4356: newarray byte
    //   4358: astore #8
    //   4360: iconst_0
    //   4361: istore #9
    //   4363: iload #9
    //   4365: aload #5
    //   4367: arraylength
    //   4368: if_icmpge -> 4648
    //   4371: aload #5
    //   4373: iload #9
    //   4375: baload
    //   4376: bipush #61
    //   4378: if_icmpne -> 4398
    //   4381: aload #5
    //   4383: iload #9
    //   4385: iconst_0
    //   4386: bastore
    //   4387: iload_2
    //   4388: ifne -> 4641
    //   4391: goto -> 4398
    //   4394: invokestatic a : (Ljava/lang/Throwable;)Ljava/lang/Throwable;
    //   4397: athrow
    //   4398: aload #5
    //   4400: iload #9
    //   4402: baload
    //   4403: bipush #47
    //   4405: if_icmpne -> 4433
    //   4408: goto -> 4415
    //   4411: invokestatic a : (Ljava/lang/Throwable;)Ljava/lang/Throwable;
    //   4414: athrow
    //   4415: aload #5
    //   4417: iload #9
    //   4419: bipush #63
    //   4421: bastore
    //   4422: iload_2
    //   4423: ifne -> 4641
    //   4426: goto -> 4433
    //   4429: invokestatic a : (Ljava/lang/Throwable;)Ljava/lang/Throwable;
    //   4432: athrow
    //   4433: aload #5
    //   4435: iload #9
    //   4437: baload
    //   4438: bipush #43
    //   4440: if_icmpne -> 4468
    //   4443: goto -> 4450
    //   4446: invokestatic a : (Ljava/lang/Throwable;)Ljava/lang/Throwable;
    //   4449: athrow
    //   4450: aload #5
    //   4452: iload #9
    //   4454: bipush #62
    //   4456: bastore
    //   4457: iload_2
    //   4458: ifne -> 4641
    //   4461: goto -> 4468
    //   4464: invokestatic a : (Ljava/lang/Throwable;)Ljava/lang/Throwable;
    //   4467: athrow
    //   4468: aload #5
    //   4470: iload #9
    //   4472: baload
    //   4473: bipush #48
    //   4475: if_icmplt -> 4527
    //   4478: goto -> 4485
    //   4481: invokestatic a : (Ljava/lang/Throwable;)Ljava/lang/Throwable;
    //   4484: athrow
    //   4485: aload #5
    //   4487: iload #9
    //   4489: baload
    //   4490: bipush #57
    //   4492: if_icmpgt -> 4527
    //   4495: goto -> 4502
    //   4498: invokestatic a : (Ljava/lang/Throwable;)Ljava/lang/Throwable;
    //   4501: athrow
    //   4502: aload #5
    //   4504: iload #9
    //   4506: aload #5
    //   4508: iload #9
    //   4510: baload
    //   4511: bipush #-4
    //   4513: isub
    //   4514: i2b
    //   4515: bastore
    //   4516: iload_2
    //   4517: ifne -> 4641
    //   4520: goto -> 4527
    //   4523: invokestatic a : (Ljava/lang/Throwable;)Ljava/lang/Throwable;
    //   4526: athrow
    //   4527: aload #5
    //   4529: iload #9
    //   4531: baload
    //   4532: bipush #97
    //   4534: if_icmplt -> 4586
    //   4537: goto -> 4544
    //   4540: invokestatic a : (Ljava/lang/Throwable;)Ljava/lang/Throwable;
    //   4543: athrow
    //   4544: aload #5
    //   4546: iload #9
    //   4548: baload
    //   4549: bipush #122
    //   4551: if_icmpgt -> 4586
    //   4554: goto -> 4561
    //   4557: invokestatic a : (Ljava/lang/Throwable;)Ljava/lang/Throwable;
    //   4560: athrow
    //   4561: aload #5
    //   4563: iload #9
    //   4565: aload #5
    //   4567: iload #9
    //   4569: baload
    //   4570: bipush #71
    //   4572: isub
    //   4573: i2b
    //   4574: bastore
    //   4575: iload_2
    //   4576: ifne -> 4641
    //   4579: goto -> 4586
    //   4582: invokestatic a : (Ljava/lang/Throwable;)Ljava/lang/Throwable;
    //   4585: athrow
    //   4586: aload #5
    //   4588: iload #9
    //   4590: baload
    //   4591: bipush #65
    //   4593: if_icmplt -> 4641
    //   4596: goto -> 4603
    //   4599: invokestatic a : (Ljava/lang/Throwable;)Ljava/lang/Throwable;
    //   4602: athrow
    //   4603: aload #5
    //   4605: iload #9
    //   4607: baload
    //   4608: bipush #90
    //   4610: if_icmpgt -> 4641
    //   4613: goto -> 4620
    //   4616: invokestatic a : (Ljava/lang/Throwable;)Ljava/lang/Throwable;
    //   4619: athrow
    //   4620: aload #5
    //   4622: iload #9
    //   4624: aload #5
    //   4626: iload #9
    //   4628: baload
    //   4629: bipush #65
    //   4631: isub
    //   4632: i2b
    //   4633: bastore
    //   4634: goto -> 4641
    //   4637: invokestatic a : (Ljava/lang/Throwable;)Ljava/lang/Throwable;
    //   4640: athrow
    //   4641: iinc #9, 1
    //   4644: iload_2
    //   4645: ifne -> 4363
    //   4648: iconst_0
    //   4649: istore #9
    //   4651: iconst_0
    //   4652: istore #10
    //   4654: iload #10
    //   4656: aload #8
    //   4658: arraylength
    //   4659: iconst_2
    //   4660: isub
    //   4661: if_icmpge -> 4770
    //   4664: aload #8
    //   4666: iload #10
    //   4668: aload #5
    //   4670: iload #9
    //   4672: baload
    //   4673: iconst_2
    //   4674: ishl
    //   4675: sipush #255
    //   4678: iand
    //   4679: aload #5
    //   4681: iload #9
    //   4683: iconst_1
    //   4684: iadd
    //   4685: baload
    //   4686: iconst_4
    //   4687: iushr
    //   4688: iconst_3
    //   4689: iand
    //   4690: ior
    //   4691: i2b
    //   4692: bastore
    //   4693: aload #8
    //   4695: iload #10
    //   4697: iconst_1
    //   4698: iadd
    //   4699: aload #5
    //   4701: iload #9
    //   4703: iconst_1
    //   4704: iadd
    //   4705: baload
    //   4706: iconst_4
    //   4707: ishl
    //   4708: sipush #255
    //   4711: iand
    //   4712: aload #5
    //   4714: iload #9
    //   4716: iconst_2
    //   4717: iadd
    //   4718: baload
    //   4719: iconst_2
    //   4720: iushr
    //   4721: bipush #15
    //   4723: iand
    //   4724: ior
    //   4725: i2b
    //   4726: bastore
    //   4727: aload #8
    //   4729: iload #10
    //   4731: iconst_2
    //   4732: iadd
    //   4733: aload #5
    //   4735: iload #9
    //   4737: iconst_2
    //   4738: iadd
    //   4739: baload
    //   4740: bipush #6
    //   4742: ishl
    //   4743: sipush #255
    //   4746: iand
    //   4747: aload #5
    //   4749: iload #9
    //   4751: iconst_3
    //   4752: iadd
    //   4753: baload
    //   4754: bipush #63
    //   4756: iand
    //   4757: ior
    //   4758: i2b
    //   4759: bastore
    //   4760: iinc #9, 4
    //   4763: iinc #10, 3
    //   4766: iload_2
    //   4767: ifne -> 4654
    //   4770: iload #10
    //   4772: aload #8
    //   4774: arraylength
    //   4775: if_icmpge -> 4814
    //   4778: aload #8
    //   4780: iload #10
    //   4782: aload #5
    //   4784: iload #9
    //   4786: baload
    //   4787: iconst_2
    //   4788: ishl
    //   4789: sipush #255
    //   4792: iand
    //   4793: aload #5
    //   4795: iload #9
    //   4797: iconst_1
    //   4798: iadd
    //   4799: baload
    //   4800: iconst_4
    //   4801: iushr
    //   4802: iconst_3
    //   4803: iand
    //   4804: ior
    //   4805: i2b
    //   4806: bastore
    //   4807: goto -> 4814
    //   4810: invokestatic a : (Ljava/lang/Throwable;)Ljava/lang/Throwable;
    //   4813: athrow
    //   4814: iinc #10, 1
    //   4817: iload #10
    //   4819: aload #8
    //   4821: arraylength
    //   4822: if_icmpge -> 4864
    //   4825: aload #8
    //   4827: iload #10
    //   4829: aload #5
    //   4831: iload #9
    //   4833: iconst_1
    //   4834: iadd
    //   4835: baload
    //   4836: iconst_4
    //   4837: ishl
    //   4838: sipush #255
    //   4841: iand
    //   4842: aload #5
    //   4844: iload #9
    //   4846: iconst_2
    //   4847: iadd
    //   4848: baload
    //   4849: iconst_2
    //   4850: iushr
    //   4851: bipush #15
    //   4853: iand
    //   4854: ior
    //   4855: i2b
    //   4856: bastore
    //   4857: goto -> 4864
    //   4860: invokestatic a : (Ljava/lang/Throwable;)Ljava/lang/Throwable;
    //   4863: athrow
    //   4864: aload #8
    //   4866: astore #6
    //   4868: sipush #26756
    //   4871: iconst_0
    //   4872: istore #5
    //   4874: sipush #16997
    //   4877: invokestatic a : (II)Ljava/lang/String;
    //   4880: iconst_1
    //   4881: ldc burp/Zlgh
    //   4883: invokevirtual getClassLoader : ()Ljava/lang/ClassLoader;
    //   4886: invokestatic forName : (Ljava/lang/String;ZLjava/lang/ClassLoader;)Ljava/lang/Class;
    //   4889: invokevirtual getDeclaredFields : ()[Ljava/lang/reflect/Field;
    //   4892: astore #6
    //   4894: aload #6
    //   4896: arraylength
    //   4897: istore #7
    //   4899: iconst_0
    //   4900: istore #8
    //   4902: iload #8
    //   4904: iload #7
    //   4906: if_icmpge -> 5044
    //   4909: aload #6
    //   4911: iload #8
    //   4913: aaload
    //   4914: astore #9
    //   4916: aload #9
    //   4918: invokevirtual getModifiers : ()I
    //   4921: invokestatic isStatic : (I)Z
    //   4924: ifne -> 4934
    //   4927: goto -> 5037
    //   4930: invokestatic a : (Ljava/lang/Throwable;)Ljava/lang/Throwable;
    //   4933: athrow
    //   4934: aload #9
    //   4936: invokevirtual getType : ()Ljava/lang/Class;
    //   4939: astore #10
    //   4941: aload #10
    //   4943: ifnull -> 5024
    //   4946: aload #10
    //   4948: invokevirtual isPrimitive : ()Z
    //   4951: ifne -> 5024
    //   4954: goto -> 4961
    //   4957: invokestatic a : (Ljava/lang/Throwable;)Ljava/lang/Throwable;
    //   4960: athrow
    //   4961: aload #10
    //   4963: invokevirtual getPackage : ()Ljava/lang/Package;
    //   4966: ifnull -> 5024
    //   4969: goto -> 4976
    //   4972: invokestatic a : (Ljava/lang/Throwable;)Ljava/lang/Throwable;
    //   4975: athrow
    //   4976: aload #10
    //   4978: invokevirtual getPackage : ()Ljava/lang/Package;
    //   4981: invokevirtual getName : ()Ljava/lang/String;
    //   4984: ifnull -> 5024
    //   4987: goto -> 4994
    //   4990: invokestatic a : (Ljava/lang/Throwable;)Ljava/lang/Throwable;
    //   4993: athrow
    //   4994: aload #10
    //   4996: invokevirtual getPackage : ()Ljava/lang/Package;
    //   4999: invokevirtual getName : ()Ljava/lang/String;
    //   5002: sipush #26762
    //   5005: sipush #31061
    //   5008: invokestatic a : (II)Ljava/lang/String;
    //   5011: invokevirtual startsWith : (Ljava/lang/String;)Z
    //   5014: ifne -> 5024
    //   5017: goto -> 5024
    //   5020: invokestatic a : (Ljava/lang/Throwable;)Ljava/lang/Throwable;
    //   5023: athrow
    //   5024: aload #9
    //   5026: iconst_1
    //   5027: invokevirtual setAccessible : (Z)V
    //   5030: aload #9
    //   5032: aconst_null
    //   5033: invokevirtual get : (Ljava/lang/Object;)Ljava/lang/Object;
    //   5036: pop
    //   5037: iinc #8, 1
    //   5040: iload_2
    //   5041: ifne -> 4902
    //   5044: sipush #26758
    //   5047: sipush #10033
    //   5050: invokestatic a : (II)Ljava/lang/String;
    //   5053: invokestatic forName : (Ljava/lang/String;)Ljava/lang/Class;
    //   5056: invokevirtual getDeclaredMethods : ()[Ljava/lang/reflect/Method;
    //   5059: astore #6
    //   5061: aload #6
    //   5063: arraylength
    //   5064: istore #7
    //   5066: iconst_0
    //   5067: istore #8
    //   5069: iload #8
    //   5071: iload #7
    //   5073: if_icmpge -> 5210
    //   5076: aload #6
    //   5078: iload #8
    //   5080: aaload
    //   5081: astore #9
    //   5083: aload #9
    //   5085: invokevirtual getParameterTypes : ()[Ljava/lang/Class;
    //   5088: pop
    //   5089: aload #9
    //   5091: invokevirtual getModifiers : ()I
    //   5094: invokestatic isStatic : (I)Z
    //   5097: ifeq -> 5196
    //   5100: aload #9
    //   5102: invokevirtual getParameterTypes : ()[Ljava/lang/Class;
    //   5105: arraylength
    //   5106: iconst_2
    //   5107: if_icmpne -> 5196
    //   5110: goto -> 5117
    //   5113: invokestatic a : (Ljava/lang/Throwable;)Ljava/lang/Throwable;
    //   5116: athrow
    //   5117: aload #9
    //   5119: invokevirtual getReturnType : ()Ljava/lang/Class;
    //   5122: getstatic java/lang/Boolean.TYPE : Ljava/lang/Class;
    //   5125: if_acmpne -> 5196
    //   5128: goto -> 5135
    //   5131: invokestatic a : (Ljava/lang/Throwable;)Ljava/lang/Throwable;
    //   5134: athrow
    //   5135: aload #9
    //   5137: iconst_1
    //   5138: invokevirtual setAccessible : (Z)V
    //   5141: aload #9
    //   5143: aconst_null
    //   5144: iconst_2
    //   5145: anewarray java/lang/Object
    //   5148: dup
    //   5149: iconst_0
    //   5150: aload_0
    //   5151: aastore
    //   5152: dup
    //   5153: iconst_1
    //   5154: aload_1
    //   5155: ifnonnull -> 5173
    //   5158: goto -> 5165
    //   5161: invokestatic a : (Ljava/lang/Throwable;)Ljava/lang/Throwable;
    //   5164: athrow
    //   5165: aload_1
    //   5166: goto -> 5180
    //   5169: invokestatic a : (Ljava/lang/Throwable;)Ljava/lang/Throwable;
    //   5172: athrow
    //   5173: aload_1
    //   5174: checkcast [B
    //   5177: invokevirtual clone : ()Ljava/lang/Object;
    //   5180: aastore
    //   5181: invokevirtual invoke : (Ljava/lang/Object;[Ljava/lang/Object;)Ljava/lang/Object;
    //   5184: checkcast java/lang/Boolean
    //   5187: invokevirtual booleanValue : ()Z
    //   5190: istore #5
    //   5192: iload_2
    //   5193: ifne -> 5210
    //   5196: iinc #8, 1
    //   5199: iload_2
    //   5200: ifne -> 5069
    //   5203: goto -> 5210
    //   5206: invokestatic a : (Ljava/lang/Throwable;)Ljava/lang/Throwable;
    //   5209: athrow
    //   5210: iload #5
    //   5212: ireturn
    //   5213: astore_3
    //   5214: new java/lang/Exception
    //   5217: dup
    //   5218: aload_3
    //   5219: invokevirtual getMessage : ()Ljava/lang/String;
    //   5222: invokespecial <init> : (Ljava/lang/String;)V
    //   5225: athrow
    // Exception table:
    //   from	to	target	type
    //   4	5212	5213	java/lang/Throwable
    //   22	198	201	java/lang/Throwable
    //   168	235	238	java/lang/Throwable
    //   205	272	275	java/lang/Throwable
    //   242	309	312	java/lang/Throwable
    //   279	346	349	java/lang/Throwable
    //   316	383	386	java/lang/Throwable
    //   353	420	423	java/lang/Throwable
    //   390	457	460	java/lang/Throwable
    //   427	494	497	java/lang/Throwable
    //   464	531	534	java/lang/Throwable
    //   501	568	571	java/lang/Throwable
    //   538	605	608	java/lang/Throwable
    //   575	642	645	java/lang/Throwable
    //   612	679	682	java/lang/Throwable
    //   649	716	719	java/lang/Throwable
    //   686	753	756	java/lang/Throwable
    //   723	790	793	java/lang/Throwable
    //   760	827	830	java/lang/Throwable
    //   797	864	867	java/lang/Throwable
    //   834	901	904	java/lang/Throwable
    //   871	938	941	java/lang/Throwable
    //   908	975	978	java/lang/Throwable
    //   945	1012	1015	java/lang/Throwable
    //   982	1049	1052	java/lang/Throwable
    //   1019	1086	1089	java/lang/Throwable
    //   1056	1123	1126	java/lang/Throwable
    //   1093	1160	1163	java/lang/Throwable
    //   1130	1197	1200	java/lang/Throwable
    //   1167	1234	1237	java/lang/Throwable
    //   1204	1271	1274	java/lang/Throwable
    //   1241	1308	1311	java/lang/Throwable
    //   1278	1341	1344	java/lang/Throwable
    //   1381	1555	1558	java/lang/Throwable
    //   1524	1593	1596	java/lang/Throwable
    //   1562	1631	1634	java/lang/Throwable
    //   1600	1669	1672	java/lang/Throwable
    //   1638	1707	1710	java/lang/Throwable
    //   1676	1745	1748	java/lang/Throwable
    //   1714	1783	1786	java/lang/Throwable
    //   1752	1821	1824	java/lang/Throwable
    //   1790	1859	1862	java/lang/Throwable
    //   1828	1897	1900	java/lang/Throwable
    //   1866	1935	1938	java/lang/Throwable
    //   1904	1973	1976	java/lang/Throwable
    //   1942	2011	2014	java/lang/Throwable
    //   1980	2049	2052	java/lang/Throwable
    //   2018	2087	2090	java/lang/Throwable
    //   2056	2125	2128	java/lang/Throwable
    //   2094	2163	2166	java/lang/Throwable
    //   2132	2201	2204	java/lang/Throwable
    //   2170	2239	2242	java/lang/Throwable
    //   2208	2277	2280	java/lang/Throwable
    //   2246	2315	2318	java/lang/Throwable
    //   2284	2353	2356	java/lang/Throwable
    //   2322	2391	2394	java/lang/Throwable
    //   2360	2429	2432	java/lang/Throwable
    //   2398	2467	2470	java/lang/Throwable
    //   2436	2505	2508	java/lang/Throwable
    //   2474	2543	2546	java/lang/Throwable
    //   2512	2581	2584	java/lang/Throwable
    //   2550	2619	2622	java/lang/Throwable
    //   2588	2657	2660	java/lang/Throwable
    //   2626	2695	2698	java/lang/Throwable
    //   2664	2729	2732	java/lang/Throwable
    //   2937	2961	2964	java/lang/Throwable
    //   3035	3072	3072	java/lang/Throwable
    //   3076	3097	3097	java/lang/Throwable
    //   3101	3131	3131	java/lang/Throwable
    //   3374	3388	3388	java/lang/Throwable
    //   3399	3412	3415	java/lang/Throwable
    //   3404	3427	3430	java/lang/Throwable
    //   3419	3445	3448	java/lang/Throwable
    //   3434	3475	3478	java/lang/Throwable
    //   3541	3568	3571	java/lang/Throwable
    //   3558	3586	3589	java/lang/Throwable
    //   3575	3622	3625	java/lang/Throwable
    //   3593	3636	3639	java/lang/Throwable
    //   3688	3702	3702	java/lang/Throwable
    //   3713	3726	3729	java/lang/Throwable
    //   3718	3741	3744	java/lang/Throwable
    //   3733	3759	3762	java/lang/Throwable
    //   3748	3789	3792	java/lang/Throwable
    //   3855	3882	3885	java/lang/Throwable
    //   3872	3903	3906	java/lang/Throwable
    //   3889	3933	3936	java/lang/Throwable
    //   3910	3944	3944	java/lang/Throwable
    //   3955	3971	3974	java/lang/Throwable
    //   4010	4024	4027	java/lang/Throwable
    //   4017	4038	4041	java/lang/Throwable
    //   4031	4052	4055	java/lang/Throwable
    //   4045	4066	4069	java/lang/Throwable
    //   4059	4080	4083	java/lang/Throwable
    //   4073	4094	4097	java/lang/Throwable
    //   4087	4108	4111	java/lang/Throwable
    //   4101	4122	4125	java/lang/Throwable
    //   4115	4132	4135	java/lang/Throwable
    //   4173	4187	4190	java/lang/Throwable
    //   4180	4201	4204	java/lang/Throwable
    //   4194	4215	4218	java/lang/Throwable
    //   4208	4229	4232	java/lang/Throwable
    //   4222	4243	4246	java/lang/Throwable
    //   4236	4257	4260	java/lang/Throwable
    //   4250	4271	4274	java/lang/Throwable
    //   4264	4285	4288	java/lang/Throwable
    //   4278	4302	4305	java/lang/Throwable
    //   4371	4391	4394	java/lang/Throwable
    //   4381	4408	4411	java/lang/Throwable
    //   4398	4426	4429	java/lang/Throwable
    //   4415	4443	4446	java/lang/Throwable
    //   4433	4461	4464	java/lang/Throwable
    //   4450	4478	4481	java/lang/Throwable
    //   4468	4495	4498	java/lang/Throwable
    //   4485	4520	4523	java/lang/Throwable
    //   4502	4537	4540	java/lang/Throwable
    //   4527	4554	4557	java/lang/Throwable
    //   4544	4579	4582	java/lang/Throwable
    //   4561	4596	4599	java/lang/Throwable
    //   4586	4613	4616	java/lang/Throwable
    //   4603	4634	4637	java/lang/Throwable
    //   4770	4807	4810	java/lang/Throwable
    //   4814	4857	4860	java/lang/Throwable
    //   4916	4930	4930	java/lang/Throwable
    //   4941	4954	4957	java/lang/Throwable
    //   4946	4969	4972	java/lang/Throwable
    //   4961	4987	4990	java/lang/Throwable
    //   4976	5017	5020	java/lang/Throwable
    //   5083	5110	5113	java/lang/Throwable
    //   5100	5128	5131	java/lang/Throwable
    //   5117	5158	5161	java/lang/Throwable
    //   5135	5169	5169	java/lang/Throwable
    //   5192	5203	5206	java/lang/Throwable
  }
  
  static void Zu(Object[] paramArrayOfObject, Object paramObject) throws Throwable {}
  
  static void ZZ(Object paramObject) {
    Ze40.Zr = a(26757, 21331);
    Ze40.ZO = new BigInteger(a(26753, 20832));
    boolean bool = Zt2e.ZN();
    try {
      try {
        if (Zmpc.ZT.charAt(Math.abs(((BigInteger)Zboa.Zh).intValue() % 32)) > Zkff.Zs.charAt(Math.abs(((BigInteger)Zsdn.ZE).intValue() % 32))) {
          try {
            Zk7b.ZX(Class.forName(a(26761, -12514)));
            if (!bool)
              Zs15.ZS(Class.forName(a(26754, -29878))); 
          } catch (Throwable throwable) {
            throw a(null);
          } 
          return;
        } 
      } catch (Throwable throwable) {
        throw a(null);
      } 
      Zs15.ZS(Class.forName(a(26754, -29878)));
    } catch (Throwable throwable) {}
  }
  
  static {
    // Byte code:
    //   0: bipush #13
    //   2: anewarray java/lang/String
    //   5: astore #5
    //   7: iconst_0
    //   8: istore_3
    //   9: ldc '>J^1R\\t\\tt$n|M  cF<#;%RrxB8 T|Qh~=>\vWJ\\nv*\\fq>\\nJW=O\\t/ j9}i/81<;ssJ\\tt[e !#p\\rukZ/s}_($CX\-\\tfB'
    //   11: dup
    //   12: astore_2
    //   13: invokevirtual length : ()I
    //   16: istore #4
    //   18: bipush #9
    //   20: istore_1
    //   21: iconst_m1
    //   22: istore_0
    //   23: bipush #88
    //   25: iinc #0, 1
    //   28: aload_2
    //   29: iload_0
    //   30: dup
    //   31: iload_1
    //   32: iadd
    //   33: invokevirtual substring : (II)Ljava/lang/String;
    //   36: iconst_m1
    //   37: goto -> 143
    //   40: aload #5
    //   42: swap
    //   43: iload_3
    //   44: iinc #3, 1
    //   47: swap
    //   48: aastore
    //   49: iload_0
    //   50: iload_1
    //   51: iadd
    //   52: dup
    //   53: istore_0
    //   54: iload #4
    //   56: if_icmpge -> 68
    //   59: aload_2
    //   60: iload_0
    //   61: invokevirtual charAt : (I)C
    //   64: istore_1
    //   65: goto -> 23
    //   68: ldc '80\\tyv'
    //   70: dup
    //   71: astore_2
    //   72: invokevirtual length : ()I
    //   75: istore #4
    //   77: bipush #9
    //   79: istore_1
    //   80: iconst_m1
    //   81: istore_0
    //   82: bipush #66
    //   84: iinc #0, 1
    //   87: aload_2
    //   88: iload_0
    //   89: dup
    //   90: iload_1
    //   91: iadd
    //   92: invokevirtual substring : (II)Ljava/lang/String;
    //   95: iconst_0
    //   96: goto -> 143
    //   99: aload #5
    //   101: swap
    //   102: iload_3
    //   103: iinc #3, 1
    //   106: swap
    //   107: aastore
    //   108: iload_0
    //   109: iload_1
    //   110: iadd
    //   111: dup
    //   112: istore_0
    //   113: iload #4
    //   115: if_icmpge -> 127
    //   118: aload_2
    //   119: iload_0
    //   120: invokevirtual charAt : (I)C
    //   123: istore_1
    //   124: goto -> 82
    //   127: aload #5
    //   129: putstatic burp/Zm81.a : [Ljava/lang/String;
    //   132: bipush #13
    //   134: anewarray java/lang/String
    //   137: putstatic burp/Zm81.b : [Ljava/lang/String;
    //   140: goto -> 300
    //   143: dup_x2
    //   144: pop
    //   145: invokevirtual toCharArray : ()[C
    //   148: dup_x1
    //   149: arraylength
    //   150: dup_x2
    //   151: pop
    //   152: iconst_0
    //   153: istore #6
    //   155: dup2_x1
    //   156: pop2
    //   157: dup_x2
    //   158: iconst_1
    //   159: if_icmpgt -> 260
    //   162: dup2
    //   163: swap
    //   164: iload #6
    //   166: dup2_x1
    //   167: caload
    //   168: swap
    //   169: iload #6
    //   171: bipush #7
    //   173: irem
    //   174: tableswitch default -> 242, 0 -> 212, 1 -> 217, 2 -> 222, 3 -> 227, 4 -> 232, 5 -> 237
    //   212: bipush #72
    //   214: goto -> 244
    //   217: bipush #42
    //   219: goto -> 244
    //   222: bipush #29
    //   224: goto -> 244
    //   227: bipush #36
    //   229: goto -> 244
    //   232: bipush #8
    //   234: goto -> 244
    //   237: bipush #9
    //   239: goto -> 244
    //   242: bipush #101
    //   244: ixor
    //   245: ixor
    //   246: i2c
    //   247: castore
    //   248: iinc #6, 1
    //   251: dup
    //   252: ifne -> 260
    //   255: dup2
    //   256: dup_x1
    //   257: goto -> 166
    //   260: dup2_x1
    //   261: pop2
    //   262: dup_x2
    //   263: iload #6
    //   265: if_icmpgt -> 162
    //   268: pop
    //   269: new java/lang/String
    //   272: dup_x1
    //   273: swap
    //   274: invokespecial <init> : ([C)V
    //   277: invokevirtual intern : ()Ljava/lang/String;
    //   280: swap
    //   281: pop
    //   282: swap
    //   283: tableswitch default -> 40, 0 -> 99
    //   300: new java/math/BigInteger
    //   303: dup
    //   304: bipush #32
    //   306: newarray byte
    //   308: dup
    //   309: iconst_0
    //   310: bipush #40
    //   312: bastore
    //   313: dup
    //   314: iconst_1
    //   315: bipush #31
    //   317: bastore
    //   318: dup
    //   319: iconst_2
    //   320: bipush #89
    //   322: bastore
    //   323: dup
    //   324: iconst_3
    //   325: bipush #-54
    //   327: bastore
    //   328: dup
    //   329: iconst_4
    //   330: bipush #26
    //   332: bastore
    //   333: dup
    //   334: iconst_5
    //   335: bipush #-51
    //   337: bastore
    //   338: dup
    //   339: bipush #6
    //   341: bipush #-59
    //   343: bastore
    //   344: dup
    //   345: bipush #7
    //   347: bipush #-35
    //   349: bastore
    //   350: dup
    //   351: bipush #8
    //   353: bipush #89
    //   355: bastore
    //   356: dup
    //   357: bipush #9
    //   359: bipush #70
    //   361: bastore
    //   362: dup
    //   363: bipush #10
    //   365: bipush #-32
    //   367: bastore
    //   368: dup
    //   369: bipush #11
    //   371: bipush #-84
    //   373: bastore
    //   374: dup
    //   375: bipush #12
    //   377: bipush #123
    //   379: bastore
    //   380: dup
    //   381: bipush #13
    //   383: bipush #-84
    //   385: bastore
    //   386: dup
    //   387: bipush #14
    //   389: bipush #-52
    //   391: bastore
    //   392: dup
    //   393: bipush #15
    //   395: bipush #-61
    //   397: bastore
    //   398: dup
    //   399: bipush #16
    //   401: bipush #92
    //   403: bastore
    //   404: dup
    //   405: bipush #17
    //   407: bipush #-67
    //   409: bastore
    //   410: dup
    //   411: bipush #18
    //   413: bipush #-123
    //   415: bastore
    //   416: dup
    //   417: bipush #19
    //   419: bipush #-77
    //   421: bastore
    //   422: dup
    //   423: bipush #20
    //   425: bipush #-108
    //   427: bastore
    //   428: dup
    //   429: bipush #21
    //   431: bipush #-71
    //   433: bastore
    //   434: dup
    //   435: bipush #22
    //   437: bipush #-40
    //   439: bastore
    //   440: dup
    //   441: bipush #23
    //   443: bipush #-101
    //   445: bastore
    //   446: dup
    //   447: bipush #24
    //   449: bipush #86
    //   451: bastore
    //   452: dup
    //   453: bipush #25
    //   455: bipush #33
    //   457: bastore
    //   458: dup
    //   459: bipush #26
    //   461: bipush #-68
    //   463: bastore
    //   464: dup
    //   465: bipush #27
    //   467: bipush #63
    //   469: bastore
    //   470: dup
    //   471: bipush #28
    //   473: bipush #-13
    //   475: bastore
    //   476: dup
    //   477: bipush #29
    //   479: bipush #-125
    //   481: bastore
    //   482: dup
    //   483: bipush #30
    //   485: bipush #-111
    //   487: bastore
    //   488: dup
    //   489: bipush #31
    //   491: bipush #81
    //   493: bastore
    //   494: invokespecial <init> : ([B)V
    //   497: putstatic burp/Zm81.Zy : Ljava/lang/Object;
    //   500: sipush #26759
    //   503: sipush #31791
    //   506: invokestatic a : (II)Ljava/lang/String;
    //   509: putstatic burp/Zm81.ZY : Ljava/lang/String;
    //   512: return
  }
  
  private static Throwable a(Throwable paramThrowable) {
    return paramThrowable;
  }
  
  private static String a(int paramInt1, int paramInt2) {
    int i = (paramInt1 ^ 0x6882) & 0xFFFF;
    if (b[i] == null) {
      char[] arrayOfChar = a[i].toCharArray();
      switch (arrayOfChar[0] & 0xFF) {
        case 0:
        
        case 1:
        
        case 2:
        
        case 3:
        
        case 4:
        
        case 5:
        
        case 6:
        
        case 7:
        
        case 8:
        
        case 9:
        
        case 10:
        
        case 11:
        
        case 12:
        
        case 13:
        
        case 14:
        
        case 15:
        
        case 16:
        
        case 17:
        
        case 18:
        
        case 19:
        
        case 20:
        
        case 21:
        
        case 22:
        
        case 23:
        
        case 24:
        
        case 25:
        
        case 26:
        
        case 27:
        
        case 28:
        
        case 29:
        
        case 30:
        
        case 31:
        
        case 32:
        
        case 33:
        
        case 34:
        
        case 35:
        
        case 36:
        
        case 37:
        
        case 38:
        
        case 39:
        
        case 40:
        
        case 41:
        
        case 42:
        
        case 43:
        
        case 44:
        
        case 45:
        
        case 46:
        
        case 47:
        
        case 48:
        
        case 49:
        
        case 50:
        
        case 51:
        
        case 52:
        
        case 53:
        
        case 54:
        
        case 55:
        
        case 56:
        
        case 57:
        
        case 58:
        
        case 59:
        
        case 60:
        
        case 61:
        
        case 62:
        
        case 63:
        
        case 64:
        
        case 65:
        
        case 66:
        
        case 67:
        
        case 68:
        
        case 69:
        
        case 70:
        
        case 71:
        
        case 72:
        
        case 73:
        
        case 74:
        
        case 75:
        
        case 76:
        
        case 77:
        
        case 78:
        
        case 79:
        
        case 80:
        
        case 81:
        
        case 82:
        
        case 83:
        
        case 84:
        
        case 85:
        
        case 86:
        
        case 87:
        
        case 88:
        
        case 89:
        
        case 90:
        
        case 91:
        
        case 92:
        
        case 93:
        
        case 94:
        
        case 95:
        
        case 96:
        
        case 97:
        
        case 98:
        
        case 99:
        
        case 100:
        
        case 101:
        
        case 102:
        
        case 103:
        
        case 104:
        
        case 105:
        
        case 106:
        
        case 107:
        
        case 108:
        
        case 109:
        
        case 110:
        
        case 111:
        
        case 112:
        
        case 113:
        
        case 114:
        
        case 115:
        
        case 116:
        
        case 117:
        
        case 118:
        
        case 119:
        
        case 120:
        
        case 121:
        
        case 122:
        
        case 123:
        
        case 124:
        
        case 125:
        
        case 126:
        
        case 127:
        
        case 128:
        
        case 129:
        
        case 130:
        
        case 131:
        
        case 132:
        
        case 133:
        
        case 134:
        
        case 135:
        
        case 136:
        
        case 137:
        
        case 138:
        
        case 139:
        
        case 140:
        
        case 141:
        
        case 142:
        
        case 143:
        
        case 144:
        
        case 145:
        
        case 146:
        
        case 147:
        
        case 148:
        
        case 149:
        
        case 150:
        
        case 151:
        
        case 152:
        
        case 153:
        
        case 154:
        
        case 155:
        
        case 156:
        
        case 157:
        
        case 158:
        
        case 159:
        
        case 160:
        
        case 161:
        
        case 162:
        
        case 163:
        
        case 164:
        
        case 165:
        
        case 166:
        
        case 167:
        
        case 168:
        
        case 169:
        
        case 170:
        
        case 171:
        
        case 172:
        
        case 173:
        
        case 174:
        
        case 175:
        
        case 176:
        
        case 177:
        
        case 178:
        
        case 179:
        
        case 180:
        
        case 181:
        
        case 182:
        
        case 183:
        
        case 184:
        
        case 185:
        
        case 186:
        
        case 187:
        
        case 188:
        
        case 189:
        
        case 190:
        
        case 191:
        
        case 192:
        
        case 193:
        
        case 194:
        
        case 195:
        
        case 196:
        
        case 197:
        
        case 198:
        
        case 199:
        
        case 200:
        
        case 201:
        
        case 202:
        
        case 203:
        
        case 204:
        
        case 205:
        
        case 206:
        
        case 207:
        
        case 208:
        
        case 209:
        
        case 210:
        
        case 211:
        
        case 212:
        
        case 213:
        
        case 214:
        
        case 215:
        
        case 216:
        
        case 217:
        
        case 218:
        
        case 219:
        
        case 220:
        
        case 221:
        
        case 222:
        
        case 223:
        
        case 224:
        
        case 225:
        
        case 226:
        
        case 227:
        
        case 228:
        
        case 229:
        
        case 230:
        
        case 231:
        
        case 232:
        
        case 233:
        
        case 234:
        
        case 235:
        
        case 236:
        
        case 237:
        
        case 238:
        
        case 239:
        
        case 240:
        
        case 241:
        
        case 242:
        
        case 243:
        
        case 244:
        
        case 245:
        
        case 246:
        
        case 247:
        
        case 248:
        
        case 249:
        
        case 250:
        
        case 251:
        
        case 252:
        
        case 253:
        
        case 254:
        
        default:
          break;
      } 
      byte b1 = 63;
      int j = (paramInt2 & 0xFF) - b1;
      if (j < 0)
        j += 256; 
      int k = ((paramInt2 & 0xFFFF) >>> 8) - b1;
      if (k < 0)
        k += 256; 
      for (byte b2 = 0; b2 < arrayOfChar.length; b2++) {
        int m = b2 % 2;
        if (m == 0) {
          arrayOfChar[b2] = (char)(arrayOfChar[b2] ^ j);
          j = ((j >>> 3 | j << 5) ^ arrayOfChar[b2]) & 0xFF;
        } else {
          arrayOfChar[b2] = (char)(arrayOfChar[b2] ^ k);
          k = ((k >>> 3 | k << 5) ^ arrayOfChar[b2]) & 0xFF;
        } 
      } 
      b[i] = (new String(arrayOfChar)).intern();
    } 
    return b[i];
  }
}


/* Location:              C:\Program Files\BurpSuitePro\burpsuite_pro.jar!\burp\Zm81.class
 * Java compiler version: 21 (65.0)
 * JD-Core Version:       1.1.3
 */