package burp;

import java.math.BigInteger;

class Zm83 extends ClassLoader {
  static String Zq;
  
  static Object Zl;
  
  private static final String[] a;
  
  private static final String[] b;
  
  static boolean Zp(Object[] paramArrayOfObject, Object paramObject) throws Throwable {
    // Byte code:
    //   0: invokestatic ZK : ()Z
    //   3: istore_2
    //   4: getstatic burp/Zgis.ZV : Ljava/lang/Object;
    //   7: checkcast java/math/BigInteger
    //   10: getstatic burp/Zz41.Zv : Ljava/lang/Object;
    //   13: checkcast java/math/BigInteger
    //   16: invokevirtual subtract : (Ljava/math/BigInteger;)Ljava/math/BigInteger;
    //   19: putstatic burp/Zb2u.ZY : Ljava/lang/Object;
    //   22: sipush #-3102
    //   25: getstatic burp/Zsu2.ZG : Ljava/lang/Object;
    //   28: checkcast java/math/BigInteger
    //   31: getstatic burp/Zz0f.ZL : Ljava/lang/Object;
    //   34: checkcast java/math/BigInteger
    //   37: invokevirtual add : (Ljava/math/BigInteger;)Ljava/math/BigInteger;
    //   40: putstatic burp/Zmlr.Zh : Ljava/lang/Object;
    //   43: sipush #-3611
    //   46: invokestatic a : (II)Ljava/lang/String;
    //   49: iconst_1
    //   50: ldc burp/Zrt9
    //   52: invokevirtual getClassLoader : ()Ljava/lang/ClassLoader;
    //   55: invokestatic forName : (Ljava/lang/String;ZLjava/lang/ClassLoader;)Ljava/lang/Class;
    //   58: invokevirtual getDeclaredFields : ()[Ljava/lang/reflect/Field;
    //   61: astore_3
    //   62: aload_3
    //   63: arraylength
    //   64: istore #4
    //   66: iconst_0
    //   67: istore #5
    //   69: iload #5
    //   71: iload #4
    //   73: if_icmpge -> 210
    //   76: aload_3
    //   77: iload #5
    //   79: aaload
    //   80: astore #6
    //   82: aload #6
    //   84: invokevirtual getModifiers : ()I
    //   87: invokestatic isStatic : (I)Z
    //   90: ifne -> 100
    //   93: goto -> 203
    //   96: invokestatic a : (Ljava/lang/Throwable;)Ljava/lang/Throwable;
    //   99: athrow
    //   100: aload #6
    //   102: invokevirtual getType : ()Ljava/lang/Class;
    //   105: astore #7
    //   107: aload #7
    //   109: ifnull -> 190
    //   112: aload #7
    //   114: invokevirtual isPrimitive : ()Z
    //   117: ifne -> 190
    //   120: goto -> 127
    //   123: invokestatic a : (Ljava/lang/Throwable;)Ljava/lang/Throwable;
    //   126: athrow
    //   127: aload #7
    //   129: invokevirtual getPackage : ()Ljava/lang/Package;
    //   132: ifnull -> 190
    //   135: goto -> 142
    //   138: invokestatic a : (Ljava/lang/Throwable;)Ljava/lang/Throwable;
    //   141: athrow
    //   142: aload #7
    //   144: invokevirtual getPackage : ()Ljava/lang/Package;
    //   147: invokevirtual getName : ()Ljava/lang/String;
    //   150: ifnull -> 190
    //   153: goto -> 160
    //   156: invokestatic a : (Ljava/lang/Throwable;)Ljava/lang/Throwable;
    //   159: athrow
    //   160: aload #7
    //   162: invokevirtual getPackage : ()Ljava/lang/Package;
    //   165: invokevirtual getName : ()Ljava/lang/String;
    //   168: sipush #-3101
    //   171: sipush #28051
    //   174: invokestatic a : (II)Ljava/lang/String;
    //   177: invokevirtual startsWith : (Ljava/lang/String;)Z
    //   180: ifne -> 190
    //   183: goto -> 190
    //   186: invokestatic a : (Ljava/lang/Throwable;)Ljava/lang/Throwable;
    //   189: athrow
    //   190: aload #6
    //   192: iconst_1
    //   193: invokevirtual setAccessible : (Z)V
    //   196: aload #6
    //   198: aconst_null
    //   199: invokevirtual get : (Ljava/lang/Object;)Ljava/lang/Object;
    //   202: pop
    //   203: iinc #5, 1
    //   206: iload_2
    //   207: ifeq -> 69
    //   210: sipush #-3104
    //   213: sipush #-26381
    //   216: invokestatic a : (II)Ljava/lang/String;
    //   219: invokestatic forName : (Ljava/lang/String;)Ljava/lang/Class;
    //   222: invokevirtual getDeclaredMethods : ()[Ljava/lang/reflect/Method;
    //   225: astore_3
    //   226: aload_3
    //   227: arraylength
    //   228: istore #4
    //   230: iconst_0
    //   231: istore #5
    //   233: iload #5
    //   235: iload #4
    //   237: if_icmpge -> 369
    //   240: aload_3
    //   241: iload #5
    //   243: aaload
    //   244: astore #6
    //   246: aload #6
    //   248: invokevirtual getParameterTypes : ()[Ljava/lang/Class;
    //   251: pop
    //   252: aload #6
    //   254: invokevirtual getModifiers : ()I
    //   257: invokestatic isStatic : (I)Z
    //   260: ifeq -> 355
    //   263: aload #6
    //   265: invokevirtual getParameterTypes : ()[Ljava/lang/Class;
    //   268: arraylength
    //   269: iconst_2
    //   270: if_icmpne -> 355
    //   273: goto -> 280
    //   276: invokestatic a : (Ljava/lang/Throwable;)Ljava/lang/Throwable;
    //   279: athrow
    //   280: aload #6
    //   282: invokevirtual getReturnType : ()Ljava/lang/Class;
    //   285: getstatic java/lang/Void.TYPE : Ljava/lang/Class;
    //   288: invokevirtual equals : (Ljava/lang/Object;)Z
    //   291: ifeq -> 355
    //   294: goto -> 301
    //   297: invokestatic a : (Ljava/lang/Throwable;)Ljava/lang/Throwable;
    //   300: athrow
    //   301: aload #6
    //   303: iconst_1
    //   304: invokevirtual setAccessible : (Z)V
    //   307: aload #6
    //   309: aconst_null
    //   310: iconst_2
    //   311: anewarray java/lang/Object
    //   314: dup
    //   315: iconst_0
    //   316: aload_0
    //   317: aastore
    //   318: dup
    //   319: iconst_1
    //   320: aload_1
    //   321: ifnonnull -> 339
    //   324: goto -> 331
    //   327: invokestatic a : (Ljava/lang/Throwable;)Ljava/lang/Throwable;
    //   330: athrow
    //   331: aload_1
    //   332: goto -> 346
    //   335: invokestatic a : (Ljava/lang/Throwable;)Ljava/lang/Throwable;
    //   338: athrow
    //   339: aload_1
    //   340: checkcast [B
    //   343: invokevirtual clone : ()Ljava/lang/Object;
    //   346: aastore
    //   347: invokevirtual invoke : (Ljava/lang/Object;[Ljava/lang/Object;)Ljava/lang/Object;
    //   350: pop
    //   351: iload_2
    //   352: ifeq -> 369
    //   355: iinc #5, 1
    //   358: iload_2
    //   359: ifeq -> 233
    //   362: goto -> 369
    //   365: invokestatic a : (Ljava/lang/Throwable;)Ljava/lang/Throwable;
    //   368: athrow
    //   369: getstatic burp/Zlg2.ZO : Ljava/lang/Object;
    //   372: checkcast java/math/BigInteger
    //   375: invokevirtual toByteArray : ()[B
    //   378: astore_3
    //   379: bipush #32
    //   381: newarray int
    //   383: dup
    //   384: iconst_0
    //   385: ldc 943331329
    //   387: iastore
    //   388: dup
    //   389: iconst_1
    //   390: ldc 170788368
    //   392: iastore
    //   393: dup
    //   394: iconst_2
    //   395: ldc 1008414755
    //   397: iastore
    //   398: dup
    //   399: iconst_3
    //   400: ldc 187049985
    //   402: iastore
    //   403: dup
    //   404: iconst_4
    //   405: ldc 1010368540
    //   407: iastore
    //   408: dup
    //   409: iconst_5
    //   410: ldc 220604441
    //   412: iastore
    //   413: dup
    //   414: bipush #6
    //   416: ldc 940377620
    //   418: iastore
    //   419: dup
    //   420: bipush #7
    //   422: ldc 255209728
    //   424: iastore
    //   425: dup
    //   426: bipush #8
    //   428: ldc 689771012
    //   430: iastore
    //   431: dup
    //   432: bipush #9
    //   434: ldc 221709344
    //   436: iastore
    //   437: dup
    //   438: bipush #10
    //   440: ldc 957157408
    //   442: iastore
    //   443: dup
    //   444: bipush #11
    //   446: ldc 892536332
    //   448: iastore
    //   449: dup
    //   450: bipush #12
    //   452: ldc 722417666
    //   454: iastore
    //   455: dup
    //   456: bipush #13
    //   458: ldc 1026621720
    //   460: iastore
    //   461: dup
    //   462: bipush #14
    //   464: ldc 655302664
    //   466: iastore
    //   467: dup
    //   468: bipush #15
    //   470: ldc 890966315
    //   472: iastore
    //   473: dup
    //   474: bipush #16
    //   476: ldc 187632156
    //   478: iastore
    //   479: dup
    //   480: bipush #17
    //   482: ldc 874189824
    //   484: iastore
    //   485: dup
    //   486: bipush #18
    //   488: ldc 254150144
    //   490: iastore
    //   491: dup
    //   492: bipush #19
    //   494: ldc 924386310
    //   496: iastore
    //   497: dup
    //   498: bipush #20
    //   500: ldc 121057538
    //   502: iastore
    //   503: dup
    //   504: bipush #21
    //   506: ldc 840500228
    //   508: iastore
    //   509: dup
    //   510: bipush #22
    //   512: ldc 389160971
    //   514: iastore
    //   515: dup
    //   516: bipush #23
    //   518: ldc 907870729
    //   520: iastore
    //   521: dup
    //   522: bipush #24
    //   524: ldc 389426184
    //   526: iastore
    //   527: dup
    //   528: bipush #25
    //   530: ldc 973875457
    //   532: iastore
    //   533: dup
    //   534: bipush #26
    //   536: ldc 372376604
    //   538: iastore
    //   539: dup
    //   540: bipush #27
    //   542: ldc 707731490
    //   544: iastore
    //   545: dup
    //   546: bipush #28
    //   548: ldc 1043334948
    //   550: iastore
    //   551: dup
    //   552: bipush #29
    //   554: ldc 439222784
    //   556: iastore
    //   557: dup
    //   558: bipush #30
    //   560: ldc 876216579
    //   562: iastore
    //   563: dup
    //   564: bipush #31
    //   566: ldc 455999525
    //   568: iastore
    //   569: astore #5
    //   571: bipush #8
    //   573: aload_3
    //   574: arraylength
    //   575: bipush #8
    //   577: irem
    //   578: isub
    //   579: istore #6
    //   581: aload_3
    //   582: arraylength
    //   583: iload #6
    //   585: iadd
    //   586: newarray byte
    //   588: astore #7
    //   590: iconst_0
    //   591: istore #8
    //   593: iload #8
    //   595: aload_3
    //   596: arraylength
    //   597: if_icmpge -> 616
    //   600: aload #7
    //   602: iload #8
    //   604: aload_3
    //   605: iload #8
    //   607: baload
    //   608: bastore
    //   609: iinc #8, 1
    //   612: iload_2
    //   613: ifeq -> 593
    //   616: aload_3
    //   617: arraylength
    //   618: istore #8
    //   620: iload #8
    //   622: aload #7
    //   624: arraylength
    //   625: if_icmpge -> 643
    //   628: aload #7
    //   630: iload #8
    //   632: iload #6
    //   634: i2b
    //   635: bastore
    //   636: iinc #8, 1
    //   639: iload_2
    //   640: ifeq -> 620
    //   643: aload #7
    //   645: astore_3
    //   646: bipush #64
    //   648: newarray int
    //   650: dup
    //   651: iconst_0
    //   652: ldc 16843776
    //   654: iastore
    //   655: dup
    //   656: iconst_1
    //   657: iconst_0
    //   658: iastore
    //   659: dup
    //   660: iconst_2
    //   661: ldc 65536
    //   663: iastore
    //   664: dup
    //   665: iconst_3
    //   666: ldc 16843780
    //   668: iastore
    //   669: dup
    //   670: iconst_4
    //   671: ldc 16842756
    //   673: iastore
    //   674: dup
    //   675: iconst_5
    //   676: ldc 66564
    //   678: iastore
    //   679: dup
    //   680: bipush #6
    //   682: iconst_4
    //   683: iastore
    //   684: dup
    //   685: bipush #7
    //   687: ldc 65536
    //   689: iastore
    //   690: dup
    //   691: bipush #8
    //   693: sipush #1024
    //   696: iastore
    //   697: dup
    //   698: bipush #9
    //   700: ldc 16843776
    //   702: iastore
    //   703: dup
    //   704: bipush #10
    //   706: ldc 16843780
    //   708: iastore
    //   709: dup
    //   710: bipush #11
    //   712: sipush #1024
    //   715: iastore
    //   716: dup
    //   717: bipush #12
    //   719: ldc 16778244
    //   721: iastore
    //   722: dup
    //   723: bipush #13
    //   725: ldc 16842756
    //   727: iastore
    //   728: dup
    //   729: bipush #14
    //   731: ldc 16777216
    //   733: iastore
    //   734: dup
    //   735: bipush #15
    //   737: iconst_4
    //   738: iastore
    //   739: dup
    //   740: bipush #16
    //   742: sipush #1028
    //   745: iastore
    //   746: dup
    //   747: bipush #17
    //   749: ldc 16778240
    //   751: iastore
    //   752: dup
    //   753: bipush #18
    //   755: ldc 16778240
    //   757: iastore
    //   758: dup
    //   759: bipush #19
    //   761: ldc 66560
    //   763: iastore
    //   764: dup
    //   765: bipush #20
    //   767: ldc 66560
    //   769: iastore
    //   770: dup
    //   771: bipush #21
    //   773: ldc 16842752
    //   775: iastore
    //   776: dup
    //   777: bipush #22
    //   779: ldc 16842752
    //   781: iastore
    //   782: dup
    //   783: bipush #23
    //   785: ldc 16778244
    //   787: iastore
    //   788: dup
    //   789: bipush #24
    //   791: ldc 65540
    //   793: iastore
    //   794: dup
    //   795: bipush #25
    //   797: ldc 16777220
    //   799: iastore
    //   800: dup
    //   801: bipush #26
    //   803: ldc 16777220
    //   805: iastore
    //   806: dup
    //   807: bipush #27
    //   809: ldc 65540
    //   811: iastore
    //   812: dup
    //   813: bipush #28
    //   815: iconst_0
    //   816: iastore
    //   817: dup
    //   818: bipush #29
    //   820: sipush #1028
    //   823: iastore
    //   824: dup
    //   825: bipush #30
    //   827: ldc 66564
    //   829: iastore
    //   830: dup
    //   831: bipush #31
    //   833: ldc 16777216
    //   835: iastore
    //   836: dup
    //   837: bipush #32
    //   839: ldc 65536
    //   841: iastore
    //   842: dup
    //   843: bipush #33
    //   845: ldc 16843780
    //   847: iastore
    //   848: dup
    //   849: bipush #34
    //   851: iconst_4
    //   852: iastore
    //   853: dup
    //   854: bipush #35
    //   856: ldc 16842752
    //   858: iastore
    //   859: dup
    //   860: bipush #36
    //   862: ldc 16843776
    //   864: iastore
    //   865: dup
    //   866: bipush #37
    //   868: ldc 16777216
    //   870: iastore
    //   871: dup
    //   872: bipush #38
    //   874: ldc 16777216
    //   876: iastore
    //   877: dup
    //   878: bipush #39
    //   880: sipush #1024
    //   883: iastore
    //   884: dup
    //   885: bipush #40
    //   887: ldc 16842756
    //   889: iastore
    //   890: dup
    //   891: bipush #41
    //   893: ldc 65536
    //   895: iastore
    //   896: dup
    //   897: bipush #42
    //   899: ldc 66560
    //   901: iastore
    //   902: dup
    //   903: bipush #43
    //   905: ldc 16777220
    //   907: iastore
    //   908: dup
    //   909: bipush #44
    //   911: sipush #1024
    //   914: iastore
    //   915: dup
    //   916: bipush #45
    //   918: iconst_4
    //   919: iastore
    //   920: dup
    //   921: bipush #46
    //   923: ldc 16778244
    //   925: iastore
    //   926: dup
    //   927: bipush #47
    //   929: ldc 66564
    //   931: iastore
    //   932: dup
    //   933: bipush #48
    //   935: ldc 16843780
    //   937: iastore
    //   938: dup
    //   939: bipush #49
    //   941: ldc 65540
    //   943: iastore
    //   944: dup
    //   945: bipush #50
    //   947: ldc 16842752
    //   949: iastore
    //   950: dup
    //   951: bipush #51
    //   953: ldc 16778244
    //   955: iastore
    //   956: dup
    //   957: bipush #52
    //   959: ldc 16777220
    //   961: iastore
    //   962: dup
    //   963: bipush #53
    //   965: sipush #1028
    //   968: iastore
    //   969: dup
    //   970: bipush #54
    //   972: ldc 66564
    //   974: iastore
    //   975: dup
    //   976: bipush #55
    //   978: ldc 16843776
    //   980: iastore
    //   981: dup
    //   982: bipush #56
    //   984: sipush #1028
    //   987: iastore
    //   988: dup
    //   989: bipush #57
    //   991: ldc 16778240
    //   993: iastore
    //   994: dup
    //   995: bipush #58
    //   997: ldc 16778240
    //   999: iastore
    //   1000: dup
    //   1001: bipush #59
    //   1003: iconst_0
    //   1004: iastore
    //   1005: dup
    //   1006: bipush #60
    //   1008: ldc 65540
    //   1010: iastore
    //   1011: dup
    //   1012: bipush #61
    //   1014: ldc 66560
    //   1016: iastore
    //   1017: dup
    //   1018: bipush #62
    //   1020: iconst_0
    //   1021: iastore
    //   1022: dup
    //   1023: bipush #63
    //   1025: ldc 16842756
    //   1027: iastore
    //   1028: astore #8
    //   1030: bipush #64
    //   1032: newarray int
    //   1034: dup
    //   1035: iconst_0
    //   1036: ldc -2146402272
    //   1038: iastore
    //   1039: dup
    //   1040: iconst_1
    //   1041: ldc -2147450880
    //   1043: iastore
    //   1044: dup
    //   1045: iconst_2
    //   1046: ldc 32768
    //   1048: iastore
    //   1049: dup
    //   1050: iconst_3
    //   1051: ldc 1081376
    //   1053: iastore
    //   1054: dup
    //   1055: iconst_4
    //   1056: ldc 1048576
    //   1058: iastore
    //   1059: dup
    //   1060: iconst_5
    //   1061: bipush #32
    //   1063: iastore
    //   1064: dup
    //   1065: bipush #6
    //   1067: ldc -2146435040
    //   1069: iastore
    //   1070: dup
    //   1071: bipush #7
    //   1073: ldc -2147450848
    //   1075: iastore
    //   1076: dup
    //   1077: bipush #8
    //   1079: ldc -2147483616
    //   1081: iastore
    //   1082: dup
    //   1083: bipush #9
    //   1085: ldc -2146402272
    //   1087: iastore
    //   1088: dup
    //   1089: bipush #10
    //   1091: ldc -2146402304
    //   1093: iastore
    //   1094: dup
    //   1095: bipush #11
    //   1097: ldc -2147483648
    //   1099: iastore
    //   1100: dup
    //   1101: bipush #12
    //   1103: ldc -2147450880
    //   1105: iastore
    //   1106: dup
    //   1107: bipush #13
    //   1109: ldc 1048576
    //   1111: iastore
    //   1112: dup
    //   1113: bipush #14
    //   1115: bipush #32
    //   1117: iastore
    //   1118: dup
    //   1119: bipush #15
    //   1121: ldc -2146435040
    //   1123: iastore
    //   1124: dup
    //   1125: bipush #16
    //   1127: ldc 1081344
    //   1129: iastore
    //   1130: dup
    //   1131: bipush #17
    //   1133: ldc 1048608
    //   1135: iastore
    //   1136: dup
    //   1137: bipush #18
    //   1139: ldc -2147450848
    //   1141: iastore
    //   1142: dup
    //   1143: bipush #19
    //   1145: iconst_0
    //   1146: iastore
    //   1147: dup
    //   1148: bipush #20
    //   1150: ldc -2147483648
    //   1152: iastore
    //   1153: dup
    //   1154: bipush #21
    //   1156: ldc 32768
    //   1158: iastore
    //   1159: dup
    //   1160: bipush #22
    //   1162: ldc 1081376
    //   1164: iastore
    //   1165: dup
    //   1166: bipush #23
    //   1168: ldc -2146435072
    //   1170: iastore
    //   1171: dup
    //   1172: bipush #24
    //   1174: ldc 1048608
    //   1176: iastore
    //   1177: dup
    //   1178: bipush #25
    //   1180: ldc -2147483616
    //   1182: iastore
    //   1183: dup
    //   1184: bipush #26
    //   1186: iconst_0
    //   1187: iastore
    //   1188: dup
    //   1189: bipush #27
    //   1191: ldc 1081344
    //   1193: iastore
    //   1194: dup
    //   1195: bipush #28
    //   1197: ldc 32800
    //   1199: iastore
    //   1200: dup
    //   1201: bipush #29
    //   1203: ldc -2146402304
    //   1205: iastore
    //   1206: dup
    //   1207: bipush #30
    //   1209: ldc -2146435072
    //   1211: iastore
    //   1212: dup
    //   1213: bipush #31
    //   1215: ldc 32800
    //   1217: iastore
    //   1218: dup
    //   1219: bipush #32
    //   1221: iconst_0
    //   1222: iastore
    //   1223: dup
    //   1224: bipush #33
    //   1226: ldc 1081376
    //   1228: iastore
    //   1229: dup
    //   1230: bipush #34
    //   1232: ldc -2146435040
    //   1234: iastore
    //   1235: dup
    //   1236: bipush #35
    //   1238: ldc 1048576
    //   1240: iastore
    //   1241: dup
    //   1242: bipush #36
    //   1244: ldc -2147450848
    //   1246: iastore
    //   1247: dup
    //   1248: bipush #37
    //   1250: ldc -2146435072
    //   1252: iastore
    //   1253: dup
    //   1254: bipush #38
    //   1256: ldc -2146402304
    //   1258: iastore
    //   1259: dup
    //   1260: bipush #39
    //   1262: ldc 32768
    //   1264: iastore
    //   1265: dup
    //   1266: bipush #40
    //   1268: ldc -2146435072
    //   1270: iastore
    //   1271: dup
    //   1272: bipush #41
    //   1274: ldc -2147450880
    //   1276: iastore
    //   1277: dup
    //   1278: bipush #42
    //   1280: bipush #32
    //   1282: iastore
    //   1283: dup
    //   1284: bipush #43
    //   1286: ldc -2146402272
    //   1288: iastore
    //   1289: dup
    //   1290: bipush #44
    //   1292: ldc 1081376
    //   1294: iastore
    //   1295: dup
    //   1296: bipush #45
    //   1298: bipush #32
    //   1300: iastore
    //   1301: dup
    //   1302: bipush #46
    //   1304: ldc 32768
    //   1306: iastore
    //   1307: dup
    //   1308: bipush #47
    //   1310: ldc -2147483648
    //   1312: iastore
    //   1313: dup
    //   1314: bipush #48
    //   1316: ldc 32800
    //   1318: iastore
    //   1319: dup
    //   1320: bipush #49
    //   1322: ldc -2146402304
    //   1324: iastore
    //   1325: dup
    //   1326: bipush #50
    //   1328: ldc 1048576
    //   1330: iastore
    //   1331: dup
    //   1332: bipush #51
    //   1334: ldc -2147483616
    //   1336: iastore
    //   1337: dup
    //   1338: bipush #52
    //   1340: ldc 1048608
    //   1342: iastore
    //   1343: dup
    //   1344: bipush #53
    //   1346: ldc -2147450848
    //   1348: iastore
    //   1349: dup
    //   1350: bipush #54
    //   1352: ldc -2147483616
    //   1354: iastore
    //   1355: dup
    //   1356: bipush #55
    //   1358: ldc 1048608
    //   1360: iastore
    //   1361: dup
    //   1362: bipush #56
    //   1364: ldc 1081344
    //   1366: iastore
    //   1367: dup
    //   1368: bipush #57
    //   1370: iconst_0
    //   1371: iastore
    //   1372: dup
    //   1373: bipush #58
    //   1375: ldc -2147450880
    //   1377: iastore
    //   1378: dup
    //   1379: bipush #59
    //   1381: ldc 32800
    //   1383: iastore
    //   1384: dup
    //   1385: bipush #60
    //   1387: ldc -2147483648
    //   1389: iastore
    //   1390: dup
    //   1391: bipush #61
    //   1393: ldc -2146435040
    //   1395: iastore
    //   1396: dup
    //   1397: bipush #62
    //   1399: ldc -2146402272
    //   1401: iastore
    //   1402: dup
    //   1403: bipush #63
    //   1405: ldc 1081344
    //   1407: iastore
    //   1408: astore #9
    //   1410: bipush #64
    //   1412: newarray int
    //   1414: dup
    //   1415: iconst_0
    //   1416: sipush #520
    //   1419: iastore
    //   1420: dup
    //   1421: iconst_1
    //   1422: ldc 134349312
    //   1424: iastore
    //   1425: dup
    //   1426: iconst_2
    //   1427: iconst_0
    //   1428: iastore
    //   1429: dup
    //   1430: iconst_3
    //   1431: ldc 134348808
    //   1433: iastore
    //   1434: dup
    //   1435: iconst_4
    //   1436: ldc 134218240
    //   1438: iastore
    //   1439: dup
    //   1440: iconst_5
    //   1441: iconst_0
    //   1442: iastore
    //   1443: dup
    //   1444: bipush #6
    //   1446: ldc 131592
    //   1448: iastore
    //   1449: dup
    //   1450: bipush #7
    //   1452: ldc 134218240
    //   1454: iastore
    //   1455: dup
    //   1456: bipush #8
    //   1458: ldc 131080
    //   1460: iastore
    //   1461: dup
    //   1462: bipush #9
    //   1464: ldc 134217736
    //   1466: iastore
    //   1467: dup
    //   1468: bipush #10
    //   1470: ldc 134217736
    //   1472: iastore
    //   1473: dup
    //   1474: bipush #11
    //   1476: ldc 131072
    //   1478: iastore
    //   1479: dup
    //   1480: bipush #12
    //   1482: ldc 134349320
    //   1484: iastore
    //   1485: dup
    //   1486: bipush #13
    //   1488: ldc 131080
    //   1490: iastore
    //   1491: dup
    //   1492: bipush #14
    //   1494: ldc 134348800
    //   1496: iastore
    //   1497: dup
    //   1498: bipush #15
    //   1500: sipush #520
    //   1503: iastore
    //   1504: dup
    //   1505: bipush #16
    //   1507: ldc 134217728
    //   1509: iastore
    //   1510: dup
    //   1511: bipush #17
    //   1513: bipush #8
    //   1515: iastore
    //   1516: dup
    //   1517: bipush #18
    //   1519: ldc 134349312
    //   1521: iastore
    //   1522: dup
    //   1523: bipush #19
    //   1525: sipush #512
    //   1528: iastore
    //   1529: dup
    //   1530: bipush #20
    //   1532: ldc 131584
    //   1534: iastore
    //   1535: dup
    //   1536: bipush #21
    //   1538: ldc 134348800
    //   1540: iastore
    //   1541: dup
    //   1542: bipush #22
    //   1544: ldc 134348808
    //   1546: iastore
    //   1547: dup
    //   1548: bipush #23
    //   1550: ldc 131592
    //   1552: iastore
    //   1553: dup
    //   1554: bipush #24
    //   1556: ldc 134218248
    //   1558: iastore
    //   1559: dup
    //   1560: bipush #25
    //   1562: ldc 131584
    //   1564: iastore
    //   1565: dup
    //   1566: bipush #26
    //   1568: ldc 131072
    //   1570: iastore
    //   1571: dup
    //   1572: bipush #27
    //   1574: ldc 134218248
    //   1576: iastore
    //   1577: dup
    //   1578: bipush #28
    //   1580: bipush #8
    //   1582: iastore
    //   1583: dup
    //   1584: bipush #29
    //   1586: ldc 134349320
    //   1588: iastore
    //   1589: dup
    //   1590: bipush #30
    //   1592: sipush #512
    //   1595: iastore
    //   1596: dup
    //   1597: bipush #31
    //   1599: ldc 134217728
    //   1601: iastore
    //   1602: dup
    //   1603: bipush #32
    //   1605: ldc 134349312
    //   1607: iastore
    //   1608: dup
    //   1609: bipush #33
    //   1611: ldc 134217728
    //   1613: iastore
    //   1614: dup
    //   1615: bipush #34
    //   1617: ldc 131080
    //   1619: iastore
    //   1620: dup
    //   1621: bipush #35
    //   1623: sipush #520
    //   1626: iastore
    //   1627: dup
    //   1628: bipush #36
    //   1630: ldc 131072
    //   1632: iastore
    //   1633: dup
    //   1634: bipush #37
    //   1636: ldc 134349312
    //   1638: iastore
    //   1639: dup
    //   1640: bipush #38
    //   1642: ldc 134218240
    //   1644: iastore
    //   1645: dup
    //   1646: bipush #39
    //   1648: iconst_0
    //   1649: iastore
    //   1650: dup
    //   1651: bipush #40
    //   1653: sipush #512
    //   1656: iastore
    //   1657: dup
    //   1658: bipush #41
    //   1660: ldc 131080
    //   1662: iastore
    //   1663: dup
    //   1664: bipush #42
    //   1666: ldc 134349320
    //   1668: iastore
    //   1669: dup
    //   1670: bipush #43
    //   1672: ldc 134218240
    //   1674: iastore
    //   1675: dup
    //   1676: bipush #44
    //   1678: ldc 134217736
    //   1680: iastore
    //   1681: dup
    //   1682: bipush #45
    //   1684: sipush #512
    //   1687: iastore
    //   1688: dup
    //   1689: bipush #46
    //   1691: iconst_0
    //   1692: iastore
    //   1693: dup
    //   1694: bipush #47
    //   1696: ldc 134348808
    //   1698: iastore
    //   1699: dup
    //   1700: bipush #48
    //   1702: ldc 134218248
    //   1704: iastore
    //   1705: dup
    //   1706: bipush #49
    //   1708: ldc 131072
    //   1710: iastore
    //   1711: dup
    //   1712: bipush #50
    //   1714: ldc 134217728
    //   1716: iastore
    //   1717: dup
    //   1718: bipush #51
    //   1720: ldc 134349320
    //   1722: iastore
    //   1723: dup
    //   1724: bipush #52
    //   1726: bipush #8
    //   1728: iastore
    //   1729: dup
    //   1730: bipush #53
    //   1732: ldc 131592
    //   1734: iastore
    //   1735: dup
    //   1736: bipush #54
    //   1738: ldc 131584
    //   1740: iastore
    //   1741: dup
    //   1742: bipush #55
    //   1744: ldc 134217736
    //   1746: iastore
    //   1747: dup
    //   1748: bipush #56
    //   1750: ldc 134348800
    //   1752: iastore
    //   1753: dup
    //   1754: bipush #57
    //   1756: ldc 134218248
    //   1758: iastore
    //   1759: dup
    //   1760: bipush #58
    //   1762: sipush #520
    //   1765: iastore
    //   1766: dup
    //   1767: bipush #59
    //   1769: ldc 134348800
    //   1771: iastore
    //   1772: dup
    //   1773: bipush #60
    //   1775: ldc 131592
    //   1777: iastore
    //   1778: dup
    //   1779: bipush #61
    //   1781: bipush #8
    //   1783: iastore
    //   1784: dup
    //   1785: bipush #62
    //   1787: ldc 134348808
    //   1789: iastore
    //   1790: dup
    //   1791: bipush #63
    //   1793: ldc 131584
    //   1795: iastore
    //   1796: astore #10
    //   1798: bipush #64
    //   1800: newarray int
    //   1802: dup
    //   1803: iconst_0
    //   1804: ldc 8396801
    //   1806: iastore
    //   1807: dup
    //   1808: iconst_1
    //   1809: sipush #8321
    //   1812: iastore
    //   1813: dup
    //   1814: iconst_2
    //   1815: sipush #8321
    //   1818: iastore
    //   1819: dup
    //   1820: iconst_3
    //   1821: sipush #128
    //   1824: iastore
    //   1825: dup
    //   1826: iconst_4
    //   1827: ldc 8396928
    //   1829: iastore
    //   1830: dup
    //   1831: iconst_5
    //   1832: ldc 8388737
    //   1834: iastore
    //   1835: dup
    //   1836: bipush #6
    //   1838: ldc 8388609
    //   1840: iastore
    //   1841: dup
    //   1842: bipush #7
    //   1844: sipush #8193
    //   1847: iastore
    //   1848: dup
    //   1849: bipush #8
    //   1851: iconst_0
    //   1852: iastore
    //   1853: dup
    //   1854: bipush #9
    //   1856: ldc 8396800
    //   1858: iastore
    //   1859: dup
    //   1860: bipush #10
    //   1862: ldc 8396800
    //   1864: iastore
    //   1865: dup
    //   1866: bipush #11
    //   1868: ldc 8396929
    //   1870: iastore
    //   1871: dup
    //   1872: bipush #12
    //   1874: sipush #129
    //   1877: iastore
    //   1878: dup
    //   1879: bipush #13
    //   1881: iconst_0
    //   1882: iastore
    //   1883: dup
    //   1884: bipush #14
    //   1886: ldc 8388736
    //   1888: iastore
    //   1889: dup
    //   1890: bipush #15
    //   1892: ldc 8388609
    //   1894: iastore
    //   1895: dup
    //   1896: bipush #16
    //   1898: iconst_1
    //   1899: iastore
    //   1900: dup
    //   1901: bipush #17
    //   1903: sipush #8192
    //   1906: iastore
    //   1907: dup
    //   1908: bipush #18
    //   1910: ldc 8388608
    //   1912: iastore
    //   1913: dup
    //   1914: bipush #19
    //   1916: ldc 8396801
    //   1918: iastore
    //   1919: dup
    //   1920: bipush #20
    //   1922: sipush #128
    //   1925: iastore
    //   1926: dup
    //   1927: bipush #21
    //   1929: ldc 8388608
    //   1931: iastore
    //   1932: dup
    //   1933: bipush #22
    //   1935: sipush #8193
    //   1938: iastore
    //   1939: dup
    //   1940: bipush #23
    //   1942: sipush #8320
    //   1945: iastore
    //   1946: dup
    //   1947: bipush #24
    //   1949: ldc 8388737
    //   1951: iastore
    //   1952: dup
    //   1953: bipush #25
    //   1955: iconst_1
    //   1956: iastore
    //   1957: dup
    //   1958: bipush #26
    //   1960: sipush #8320
    //   1963: iastore
    //   1964: dup
    //   1965: bipush #27
    //   1967: ldc 8388736
    //   1969: iastore
    //   1970: dup
    //   1971: bipush #28
    //   1973: sipush #8192
    //   1976: iastore
    //   1977: dup
    //   1978: bipush #29
    //   1980: ldc 8396928
    //   1982: iastore
    //   1983: dup
    //   1984: bipush #30
    //   1986: ldc 8396929
    //   1988: iastore
    //   1989: dup
    //   1990: bipush #31
    //   1992: sipush #129
    //   1995: iastore
    //   1996: dup
    //   1997: bipush #32
    //   1999: ldc 8388736
    //   2001: iastore
    //   2002: dup
    //   2003: bipush #33
    //   2005: ldc 8388609
    //   2007: iastore
    //   2008: dup
    //   2009: bipush #34
    //   2011: ldc 8396800
    //   2013: iastore
    //   2014: dup
    //   2015: bipush #35
    //   2017: ldc 8396929
    //   2019: iastore
    //   2020: dup
    //   2021: bipush #36
    //   2023: sipush #129
    //   2026: iastore
    //   2027: dup
    //   2028: bipush #37
    //   2030: iconst_0
    //   2031: iastore
    //   2032: dup
    //   2033: bipush #38
    //   2035: iconst_0
    //   2036: iastore
    //   2037: dup
    //   2038: bipush #39
    //   2040: ldc 8396800
    //   2042: iastore
    //   2043: dup
    //   2044: bipush #40
    //   2046: sipush #8320
    //   2049: iastore
    //   2050: dup
    //   2051: bipush #41
    //   2053: ldc 8388736
    //   2055: iastore
    //   2056: dup
    //   2057: bipush #42
    //   2059: ldc 8388737
    //   2061: iastore
    //   2062: dup
    //   2063: bipush #43
    //   2065: iconst_1
    //   2066: iastore
    //   2067: dup
    //   2068: bipush #44
    //   2070: ldc 8396801
    //   2072: iastore
    //   2073: dup
    //   2074: bipush #45
    //   2076: sipush #8321
    //   2079: iastore
    //   2080: dup
    //   2081: bipush #46
    //   2083: sipush #8321
    //   2086: iastore
    //   2087: dup
    //   2088: bipush #47
    //   2090: sipush #128
    //   2093: iastore
    //   2094: dup
    //   2095: bipush #48
    //   2097: ldc 8396929
    //   2099: iastore
    //   2100: dup
    //   2101: bipush #49
    //   2103: sipush #129
    //   2106: iastore
    //   2107: dup
    //   2108: bipush #50
    //   2110: iconst_1
    //   2111: iastore
    //   2112: dup
    //   2113: bipush #51
    //   2115: sipush #8192
    //   2118: iastore
    //   2119: dup
    //   2120: bipush #52
    //   2122: ldc 8388609
    //   2124: iastore
    //   2125: dup
    //   2126: bipush #53
    //   2128: sipush #8193
    //   2131: iastore
    //   2132: dup
    //   2133: bipush #54
    //   2135: ldc 8396928
    //   2137: iastore
    //   2138: dup
    //   2139: bipush #55
    //   2141: ldc 8388737
    //   2143: iastore
    //   2144: dup
    //   2145: bipush #56
    //   2147: sipush #8193
    //   2150: iastore
    //   2151: dup
    //   2152: bipush #57
    //   2154: sipush #8320
    //   2157: iastore
    //   2158: dup
    //   2159: bipush #58
    //   2161: ldc 8388608
    //   2163: iastore
    //   2164: dup
    //   2165: bipush #59
    //   2167: ldc 8396801
    //   2169: iastore
    //   2170: dup
    //   2171: bipush #60
    //   2173: sipush #128
    //   2176: iastore
    //   2177: dup
    //   2178: bipush #61
    //   2180: ldc 8388608
    //   2182: iastore
    //   2183: dup
    //   2184: bipush #62
    //   2186: sipush #8192
    //   2189: iastore
    //   2190: dup
    //   2191: bipush #63
    //   2193: ldc 8396928
    //   2195: iastore
    //   2196: astore #11
    //   2198: bipush #64
    //   2200: newarray int
    //   2202: dup
    //   2203: iconst_0
    //   2204: sipush #256
    //   2207: iastore
    //   2208: dup
    //   2209: iconst_1
    //   2210: ldc 34078976
    //   2212: iastore
    //   2213: dup
    //   2214: iconst_2
    //   2215: ldc 34078720
    //   2217: iastore
    //   2218: dup
    //   2219: iconst_3
    //   2220: ldc 1107296512
    //   2222: iastore
    //   2223: dup
    //   2224: iconst_4
    //   2225: ldc 524288
    //   2227: iastore
    //   2228: dup
    //   2229: iconst_5
    //   2230: sipush #256
    //   2233: iastore
    //   2234: dup
    //   2235: bipush #6
    //   2237: ldc 1073741824
    //   2239: iastore
    //   2240: dup
    //   2241: bipush #7
    //   2243: ldc 34078720
    //   2245: iastore
    //   2246: dup
    //   2247: bipush #8
    //   2249: ldc 1074266368
    //   2251: iastore
    //   2252: dup
    //   2253: bipush #9
    //   2255: ldc 524288
    //   2257: iastore
    //   2258: dup
    //   2259: bipush #10
    //   2261: ldc 33554688
    //   2263: iastore
    //   2264: dup
    //   2265: bipush #11
    //   2267: ldc 1074266368
    //   2269: iastore
    //   2270: dup
    //   2271: bipush #12
    //   2273: ldc 1107296512
    //   2275: iastore
    //   2276: dup
    //   2277: bipush #13
    //   2279: ldc 1107820544
    //   2281: iastore
    //   2282: dup
    //   2283: bipush #14
    //   2285: ldc 524544
    //   2287: iastore
    //   2288: dup
    //   2289: bipush #15
    //   2291: ldc 1073741824
    //   2293: iastore
    //   2294: dup
    //   2295: bipush #16
    //   2297: ldc 33554432
    //   2299: iastore
    //   2300: dup
    //   2301: bipush #17
    //   2303: ldc 1074266112
    //   2305: iastore
    //   2306: dup
    //   2307: bipush #18
    //   2309: ldc 1074266112
    //   2311: iastore
    //   2312: dup
    //   2313: bipush #19
    //   2315: iconst_0
    //   2316: iastore
    //   2317: dup
    //   2318: bipush #20
    //   2320: ldc 1073742080
    //   2322: iastore
    //   2323: dup
    //   2324: bipush #21
    //   2326: ldc 1107820800
    //   2328: iastore
    //   2329: dup
    //   2330: bipush #22
    //   2332: ldc 1107820800
    //   2334: iastore
    //   2335: dup
    //   2336: bipush #23
    //   2338: ldc 33554688
    //   2340: iastore
    //   2341: dup
    //   2342: bipush #24
    //   2344: ldc 1107820544
    //   2346: iastore
    //   2347: dup
    //   2348: bipush #25
    //   2350: ldc 1073742080
    //   2352: iastore
    //   2353: dup
    //   2354: bipush #26
    //   2356: iconst_0
    //   2357: iastore
    //   2358: dup
    //   2359: bipush #27
    //   2361: ldc 1107296256
    //   2363: iastore
    //   2364: dup
    //   2365: bipush #28
    //   2367: ldc 34078976
    //   2369: iastore
    //   2370: dup
    //   2371: bipush #29
    //   2373: ldc 33554432
    //   2375: iastore
    //   2376: dup
    //   2377: bipush #30
    //   2379: ldc 1107296256
    //   2381: iastore
    //   2382: dup
    //   2383: bipush #31
    //   2385: ldc 524544
    //   2387: iastore
    //   2388: dup
    //   2389: bipush #32
    //   2391: ldc 524288
    //   2393: iastore
    //   2394: dup
    //   2395: bipush #33
    //   2397: ldc 1107296512
    //   2399: iastore
    //   2400: dup
    //   2401: bipush #34
    //   2403: sipush #256
    //   2406: iastore
    //   2407: dup
    //   2408: bipush #35
    //   2410: ldc 33554432
    //   2412: iastore
    //   2413: dup
    //   2414: bipush #36
    //   2416: ldc 1073741824
    //   2418: iastore
    //   2419: dup
    //   2420: bipush #37
    //   2422: ldc 34078720
    //   2424: iastore
    //   2425: dup
    //   2426: bipush #38
    //   2428: ldc 1107296512
    //   2430: iastore
    //   2431: dup
    //   2432: bipush #39
    //   2434: ldc 1074266368
    //   2436: iastore
    //   2437: dup
    //   2438: bipush #40
    //   2440: ldc 33554688
    //   2442: iastore
    //   2443: dup
    //   2444: bipush #41
    //   2446: ldc 1073741824
    //   2448: iastore
    //   2449: dup
    //   2450: bipush #42
    //   2452: ldc 1107820544
    //   2454: iastore
    //   2455: dup
    //   2456: bipush #43
    //   2458: ldc 34078976
    //   2460: iastore
    //   2461: dup
    //   2462: bipush #44
    //   2464: ldc 1074266368
    //   2466: iastore
    //   2467: dup
    //   2468: bipush #45
    //   2470: sipush #256
    //   2473: iastore
    //   2474: dup
    //   2475: bipush #46
    //   2477: ldc 33554432
    //   2479: iastore
    //   2480: dup
    //   2481: bipush #47
    //   2483: ldc 1107820544
    //   2485: iastore
    //   2486: dup
    //   2487: bipush #48
    //   2489: ldc 1107820800
    //   2491: iastore
    //   2492: dup
    //   2493: bipush #49
    //   2495: ldc 524544
    //   2497: iastore
    //   2498: dup
    //   2499: bipush #50
    //   2501: ldc 1107296256
    //   2503: iastore
    //   2504: dup
    //   2505: bipush #51
    //   2507: ldc 1107820800
    //   2509: iastore
    //   2510: dup
    //   2511: bipush #52
    //   2513: ldc 34078720
    //   2515: iastore
    //   2516: dup
    //   2517: bipush #53
    //   2519: iconst_0
    //   2520: iastore
    //   2521: dup
    //   2522: bipush #54
    //   2524: ldc 1074266112
    //   2526: iastore
    //   2527: dup
    //   2528: bipush #55
    //   2530: ldc 1107296256
    //   2532: iastore
    //   2533: dup
    //   2534: bipush #56
    //   2536: ldc 524544
    //   2538: iastore
    //   2539: dup
    //   2540: bipush #57
    //   2542: ldc 33554688
    //   2544: iastore
    //   2545: dup
    //   2546: bipush #58
    //   2548: ldc 1073742080
    //   2550: iastore
    //   2551: dup
    //   2552: bipush #59
    //   2554: ldc 524288
    //   2556: iastore
    //   2557: dup
    //   2558: bipush #60
    //   2560: iconst_0
    //   2561: iastore
    //   2562: dup
    //   2563: bipush #61
    //   2565: ldc 1074266112
    //   2567: iastore
    //   2568: dup
    //   2569: bipush #62
    //   2571: ldc 34078976
    //   2573: iastore
    //   2574: dup
    //   2575: bipush #63
    //   2577: ldc 1073742080
    //   2579: iastore
    //   2580: astore #12
    //   2582: bipush #64
    //   2584: newarray int
    //   2586: dup
    //   2587: iconst_0
    //   2588: ldc 536870928
    //   2590: iastore
    //   2591: dup
    //   2592: iconst_1
    //   2593: ldc 541065216
    //   2595: iastore
    //   2596: dup
    //   2597: iconst_2
    //   2598: sipush #16384
    //   2601: iastore
    //   2602: dup
    //   2603: iconst_3
    //   2604: ldc 541081616
    //   2606: iastore
    //   2607: dup
    //   2608: iconst_4
    //   2609: ldc 541065216
    //   2611: iastore
    //   2612: dup
    //   2613: iconst_5
    //   2614: bipush #16
    //   2616: iastore
    //   2617: dup
    //   2618: bipush #6
    //   2620: ldc 541081616
    //   2622: iastore
    //   2623: dup
    //   2624: bipush #7
    //   2626: ldc 4194304
    //   2628: iastore
    //   2629: dup
    //   2630: bipush #8
    //   2632: ldc 536887296
    //   2634: iastore
    //   2635: dup
    //   2636: bipush #9
    //   2638: ldc 4210704
    //   2640: iastore
    //   2641: dup
    //   2642: bipush #10
    //   2644: ldc 4194304
    //   2646: iastore
    //   2647: dup
    //   2648: bipush #11
    //   2650: ldc 536870928
    //   2652: iastore
    //   2653: dup
    //   2654: bipush #12
    //   2656: ldc 4194320
    //   2658: iastore
    //   2659: dup
    //   2660: bipush #13
    //   2662: ldc 536887296
    //   2664: iastore
    //   2665: dup
    //   2666: bipush #14
    //   2668: ldc 536870912
    //   2670: iastore
    //   2671: dup
    //   2672: bipush #15
    //   2674: sipush #16400
    //   2677: iastore
    //   2678: dup
    //   2679: bipush #16
    //   2681: iconst_0
    //   2682: iastore
    //   2683: dup
    //   2684: bipush #17
    //   2686: ldc 4194320
    //   2688: iastore
    //   2689: dup
    //   2690: bipush #18
    //   2692: ldc 536887312
    //   2694: iastore
    //   2695: dup
    //   2696: bipush #19
    //   2698: sipush #16384
    //   2701: iastore
    //   2702: dup
    //   2703: bipush #20
    //   2705: ldc 4210688
    //   2707: iastore
    //   2708: dup
    //   2709: bipush #21
    //   2711: ldc 536887312
    //   2713: iastore
    //   2714: dup
    //   2715: bipush #22
    //   2717: bipush #16
    //   2719: iastore
    //   2720: dup
    //   2721: bipush #23
    //   2723: ldc 541065232
    //   2725: iastore
    //   2726: dup
    //   2727: bipush #24
    //   2729: ldc 541065232
    //   2731: iastore
    //   2732: dup
    //   2733: bipush #25
    //   2735: iconst_0
    //   2736: iastore
    //   2737: dup
    //   2738: bipush #26
    //   2740: ldc 4210704
    //   2742: iastore
    //   2743: dup
    //   2744: bipush #27
    //   2746: ldc 541081600
    //   2748: iastore
    //   2749: dup
    //   2750: bipush #28
    //   2752: sipush #16400
    //   2755: iastore
    //   2756: dup
    //   2757: bipush #29
    //   2759: ldc 4210688
    //   2761: iastore
    //   2762: dup
    //   2763: bipush #30
    //   2765: ldc 541081600
    //   2767: iastore
    //   2768: dup
    //   2769: bipush #31
    //   2771: ldc 536870912
    //   2773: iastore
    //   2774: dup
    //   2775: bipush #32
    //   2777: ldc 536887296
    //   2779: iastore
    //   2780: dup
    //   2781: bipush #33
    //   2783: bipush #16
    //   2785: iastore
    //   2786: dup
    //   2787: bipush #34
    //   2789: ldc 541065232
    //   2791: iastore
    //   2792: dup
    //   2793: bipush #35
    //   2795: ldc 4210688
    //   2797: iastore
    //   2798: dup
    //   2799: bipush #36
    //   2801: ldc 541081616
    //   2803: iastore
    //   2804: dup
    //   2805: bipush #37
    //   2807: ldc 4194304
    //   2809: iastore
    //   2810: dup
    //   2811: bipush #38
    //   2813: sipush #16400
    //   2816: iastore
    //   2817: dup
    //   2818: bipush #39
    //   2820: ldc 536870928
    //   2822: iastore
    //   2823: dup
    //   2824: bipush #40
    //   2826: ldc 4194304
    //   2828: iastore
    //   2829: dup
    //   2830: bipush #41
    //   2832: ldc 536887296
    //   2834: iastore
    //   2835: dup
    //   2836: bipush #42
    //   2838: ldc 536870912
    //   2840: iastore
    //   2841: dup
    //   2842: bipush #43
    //   2844: sipush #16400
    //   2847: iastore
    //   2848: dup
    //   2849: bipush #44
    //   2851: ldc 536870928
    //   2853: iastore
    //   2854: dup
    //   2855: bipush #45
    //   2857: ldc 541081616
    //   2859: iastore
    //   2860: dup
    //   2861: bipush #46
    //   2863: ldc 4210688
    //   2865: iastore
    //   2866: dup
    //   2867: bipush #47
    //   2869: ldc 541065216
    //   2871: iastore
    //   2872: dup
    //   2873: bipush #48
    //   2875: ldc 4210704
    //   2877: iastore
    //   2878: dup
    //   2879: bipush #49
    //   2881: ldc 541081600
    //   2883: iastore
    //   2884: dup
    //   2885: bipush #50
    //   2887: iconst_0
    //   2888: iastore
    //   2889: dup
    //   2890: bipush #51
    //   2892: ldc 541065232
    //   2894: iastore
    //   2895: dup
    //   2896: bipush #52
    //   2898: bipush #16
    //   2900: iastore
    //   2901: dup
    //   2902: bipush #53
    //   2904: sipush #16384
    //   2907: iastore
    //   2908: dup
    //   2909: bipush #54
    //   2911: ldc 541065216
    //   2913: iastore
    //   2914: dup
    //   2915: bipush #55
    //   2917: ldc 4210704
    //   2919: iastore
    //   2920: dup
    //   2921: bipush #56
    //   2923: sipush #16384
    //   2926: iastore
    //   2927: dup
    //   2928: bipush #57
    //   2930: ldc 4194320
    //   2932: iastore
    //   2933: dup
    //   2934: bipush #58
    //   2936: ldc 536887312
    //   2938: iastore
    //   2939: dup
    //   2940: bipush #59
    //   2942: iconst_0
    //   2943: iastore
    //   2944: dup
    //   2945: bipush #60
    //   2947: ldc 541081600
    //   2949: iastore
    //   2950: dup
    //   2951: bipush #61
    //   2953: ldc 536870912
    //   2955: iastore
    //   2956: dup
    //   2957: bipush #62
    //   2959: ldc 4194320
    //   2961: iastore
    //   2962: dup
    //   2963: bipush #63
    //   2965: ldc 536887312
    //   2967: iastore
    //   2968: astore #13
    //   2970: bipush #64
    //   2972: newarray int
    //   2974: dup
    //   2975: iconst_0
    //   2976: ldc 2097152
    //   2978: iastore
    //   2979: dup
    //   2980: iconst_1
    //   2981: ldc 69206018
    //   2983: iastore
    //   2984: dup
    //   2985: iconst_2
    //   2986: ldc 67110914
    //   2988: iastore
    //   2989: dup
    //   2990: iconst_3
    //   2991: iconst_0
    //   2992: iastore
    //   2993: dup
    //   2994: iconst_4
    //   2995: sipush #2048
    //   2998: iastore
    //   2999: dup
    //   3000: iconst_5
    //   3001: ldc 67110914
    //   3003: iastore
    //   3004: dup
    //   3005: bipush #6
    //   3007: ldc 2099202
    //   3009: iastore
    //   3010: dup
    //   3011: bipush #7
    //   3013: ldc 69208064
    //   3015: iastore
    //   3016: dup
    //   3017: bipush #8
    //   3019: ldc 69208066
    //   3021: iastore
    //   3022: dup
    //   3023: bipush #9
    //   3025: ldc 2097152
    //   3027: iastore
    //   3028: dup
    //   3029: bipush #10
    //   3031: iconst_0
    //   3032: iastore
    //   3033: dup
    //   3034: bipush #11
    //   3036: ldc 67108866
    //   3038: iastore
    //   3039: dup
    //   3040: bipush #12
    //   3042: iconst_2
    //   3043: iastore
    //   3044: dup
    //   3045: bipush #13
    //   3047: ldc 67108864
    //   3049: iastore
    //   3050: dup
    //   3051: bipush #14
    //   3053: ldc 69206018
    //   3055: iastore
    //   3056: dup
    //   3057: bipush #15
    //   3059: sipush #2050
    //   3062: iastore
    //   3063: dup
    //   3064: bipush #16
    //   3066: ldc 67110912
    //   3068: iastore
    //   3069: dup
    //   3070: bipush #17
    //   3072: ldc 2099202
    //   3074: iastore
    //   3075: dup
    //   3076: bipush #18
    //   3078: ldc 2097154
    //   3080: iastore
    //   3081: dup
    //   3082: bipush #19
    //   3084: ldc 67110912
    //   3086: iastore
    //   3087: dup
    //   3088: bipush #20
    //   3090: ldc 67108866
    //   3092: iastore
    //   3093: dup
    //   3094: bipush #21
    //   3096: ldc 69206016
    //   3098: iastore
    //   3099: dup
    //   3100: bipush #22
    //   3102: ldc 69208064
    //   3104: iastore
    //   3105: dup
    //   3106: bipush #23
    //   3108: ldc 2097154
    //   3110: iastore
    //   3111: dup
    //   3112: bipush #24
    //   3114: ldc 69206016
    //   3116: iastore
    //   3117: dup
    //   3118: bipush #25
    //   3120: sipush #2048
    //   3123: iastore
    //   3124: dup
    //   3125: bipush #26
    //   3127: sipush #2050
    //   3130: iastore
    //   3131: dup
    //   3132: bipush #27
    //   3134: ldc 69208066
    //   3136: iastore
    //   3137: dup
    //   3138: bipush #28
    //   3140: ldc 2099200
    //   3142: iastore
    //   3143: dup
    //   3144: bipush #29
    //   3146: iconst_2
    //   3147: iastore
    //   3148: dup
    //   3149: bipush #30
    //   3151: ldc 67108864
    //   3153: iastore
    //   3154: dup
    //   3155: bipush #31
    //   3157: ldc 2099200
    //   3159: iastore
    //   3160: dup
    //   3161: bipush #32
    //   3163: ldc 67108864
    //   3165: iastore
    //   3166: dup
    //   3167: bipush #33
    //   3169: ldc 2099200
    //   3171: iastore
    //   3172: dup
    //   3173: bipush #34
    //   3175: ldc 2097152
    //   3177: iastore
    //   3178: dup
    //   3179: bipush #35
    //   3181: ldc 67110914
    //   3183: iastore
    //   3184: dup
    //   3185: bipush #36
    //   3187: ldc 67110914
    //   3189: iastore
    //   3190: dup
    //   3191: bipush #37
    //   3193: ldc 69206018
    //   3195: iastore
    //   3196: dup
    //   3197: bipush #38
    //   3199: ldc 69206018
    //   3201: iastore
    //   3202: dup
    //   3203: bipush #39
    //   3205: iconst_2
    //   3206: iastore
    //   3207: dup
    //   3208: bipush #40
    //   3210: ldc 2097154
    //   3212: iastore
    //   3213: dup
    //   3214: bipush #41
    //   3216: ldc 67108864
    //   3218: iastore
    //   3219: dup
    //   3220: bipush #42
    //   3222: ldc 67110912
    //   3224: iastore
    //   3225: dup
    //   3226: bipush #43
    //   3228: ldc 2097152
    //   3230: iastore
    //   3231: dup
    //   3232: bipush #44
    //   3234: ldc 69208064
    //   3236: iastore
    //   3237: dup
    //   3238: bipush #45
    //   3240: sipush #2050
    //   3243: iastore
    //   3244: dup
    //   3245: bipush #46
    //   3247: ldc 2099202
    //   3249: iastore
    //   3250: dup
    //   3251: bipush #47
    //   3253: ldc 69208064
    //   3255: iastore
    //   3256: dup
    //   3257: bipush #48
    //   3259: sipush #2050
    //   3262: iastore
    //   3263: dup
    //   3264: bipush #49
    //   3266: ldc 67108866
    //   3268: iastore
    //   3269: dup
    //   3270: bipush #50
    //   3272: ldc 69208066
    //   3274: iastore
    //   3275: dup
    //   3276: bipush #51
    //   3278: ldc 69206016
    //   3280: iastore
    //   3281: dup
    //   3282: bipush #52
    //   3284: ldc 2099200
    //   3286: iastore
    //   3287: dup
    //   3288: bipush #53
    //   3290: iconst_0
    //   3291: iastore
    //   3292: dup
    //   3293: bipush #54
    //   3295: iconst_2
    //   3296: iastore
    //   3297: dup
    //   3298: bipush #55
    //   3300: ldc 69208066
    //   3302: iastore
    //   3303: dup
    //   3304: bipush #56
    //   3306: iconst_0
    //   3307: iastore
    //   3308: dup
    //   3309: bipush #57
    //   3311: ldc 2099202
    //   3313: iastore
    //   3314: dup
    //   3315: bipush #58
    //   3317: ldc 69206016
    //   3319: iastore
    //   3320: dup
    //   3321: bipush #59
    //   3323: sipush #2048
    //   3326: iastore
    //   3327: dup
    //   3328: bipush #60
    //   3330: ldc 67108866
    //   3332: iastore
    //   3333: dup
    //   3334: bipush #61
    //   3336: ldc 67110912
    //   3338: iastore
    //   3339: dup
    //   3340: bipush #62
    //   3342: sipush #2048
    //   3345: iastore
    //   3346: dup
    //   3347: bipush #63
    //   3349: ldc 2097154
    //   3351: iastore
    //   3352: astore #14
    //   3354: bipush #64
    //   3356: newarray int
    //   3358: dup
    //   3359: iconst_0
    //   3360: ldc 268439616
    //   3362: iastore
    //   3363: dup
    //   3364: iconst_1
    //   3365: sipush #4096
    //   3368: iastore
    //   3369: dup
    //   3370: iconst_2
    //   3371: ldc 262144
    //   3373: iastore
    //   3374: dup
    //   3375: iconst_3
    //   3376: ldc 268701760
    //   3378: iastore
    //   3379: dup
    //   3380: iconst_4
    //   3381: ldc 268435456
    //   3383: iastore
    //   3384: dup
    //   3385: iconst_5
    //   3386: ldc 268439616
    //   3388: iastore
    //   3389: dup
    //   3390: bipush #6
    //   3392: bipush #64
    //   3394: iastore
    //   3395: dup
    //   3396: bipush #7
    //   3398: ldc 268435456
    //   3400: iastore
    //   3401: dup
    //   3402: bipush #8
    //   3404: ldc 262208
    //   3406: iastore
    //   3407: dup
    //   3408: bipush #9
    //   3410: ldc 268697600
    //   3412: iastore
    //   3413: dup
    //   3414: bipush #10
    //   3416: ldc 268701760
    //   3418: iastore
    //   3419: dup
    //   3420: bipush #11
    //   3422: ldc 266240
    //   3424: iastore
    //   3425: dup
    //   3426: bipush #12
    //   3428: ldc 268701696
    //   3430: iastore
    //   3431: dup
    //   3432: bipush #13
    //   3434: ldc 266304
    //   3436: iastore
    //   3437: dup
    //   3438: bipush #14
    //   3440: sipush #4096
    //   3443: iastore
    //   3444: dup
    //   3445: bipush #15
    //   3447: bipush #64
    //   3449: iastore
    //   3450: dup
    //   3451: bipush #16
    //   3453: ldc 268697600
    //   3455: iastore
    //   3456: dup
    //   3457: bipush #17
    //   3459: ldc 268435520
    //   3461: iastore
    //   3462: dup
    //   3463: bipush #18
    //   3465: ldc 268439552
    //   3467: iastore
    //   3468: dup
    //   3469: bipush #19
    //   3471: sipush #4160
    //   3474: iastore
    //   3475: dup
    //   3476: bipush #20
    //   3478: ldc 266240
    //   3480: iastore
    //   3481: dup
    //   3482: bipush #21
    //   3484: ldc 262208
    //   3486: iastore
    //   3487: dup
    //   3488: bipush #22
    //   3490: ldc 268697664
    //   3492: iastore
    //   3493: dup
    //   3494: bipush #23
    //   3496: ldc 268701696
    //   3498: iastore
    //   3499: dup
    //   3500: bipush #24
    //   3502: sipush #4160
    //   3505: iastore
    //   3506: dup
    //   3507: bipush #25
    //   3509: iconst_0
    //   3510: iastore
    //   3511: dup
    //   3512: bipush #26
    //   3514: iconst_0
    //   3515: iastore
    //   3516: dup
    //   3517: bipush #27
    //   3519: ldc 268697664
    //   3521: iastore
    //   3522: dup
    //   3523: bipush #28
    //   3525: ldc 268435520
    //   3527: iastore
    //   3528: dup
    //   3529: bipush #29
    //   3531: ldc 268439552
    //   3533: iastore
    //   3534: dup
    //   3535: bipush #30
    //   3537: ldc 266304
    //   3539: iastore
    //   3540: dup
    //   3541: bipush #31
    //   3543: ldc 262144
    //   3545: iastore
    //   3546: dup
    //   3547: bipush #32
    //   3549: ldc 266304
    //   3551: iastore
    //   3552: dup
    //   3553: bipush #33
    //   3555: ldc 262144
    //   3557: iastore
    //   3558: dup
    //   3559: bipush #34
    //   3561: ldc 268701696
    //   3563: iastore
    //   3564: dup
    //   3565: bipush #35
    //   3567: sipush #4096
    //   3570: iastore
    //   3571: dup
    //   3572: bipush #36
    //   3574: bipush #64
    //   3576: iastore
    //   3577: dup
    //   3578: bipush #37
    //   3580: ldc 268697664
    //   3582: iastore
    //   3583: dup
    //   3584: bipush #38
    //   3586: sipush #4096
    //   3589: iastore
    //   3590: dup
    //   3591: bipush #39
    //   3593: ldc 266304
    //   3595: iastore
    //   3596: dup
    //   3597: bipush #40
    //   3599: ldc 268439552
    //   3601: iastore
    //   3602: dup
    //   3603: bipush #41
    //   3605: bipush #64
    //   3607: iastore
    //   3608: dup
    //   3609: bipush #42
    //   3611: ldc 268435520
    //   3613: iastore
    //   3614: dup
    //   3615: bipush #43
    //   3617: ldc 268697600
    //   3619: iastore
    //   3620: dup
    //   3621: bipush #44
    //   3623: ldc 268697664
    //   3625: iastore
    //   3626: dup
    //   3627: bipush #45
    //   3629: ldc 268435456
    //   3631: iastore
    //   3632: dup
    //   3633: bipush #46
    //   3635: ldc 262144
    //   3637: iastore
    //   3638: dup
    //   3639: bipush #47
    //   3641: ldc 268439616
    //   3643: iastore
    //   3644: dup
    //   3645: bipush #48
    //   3647: iconst_0
    //   3648: iastore
    //   3649: dup
    //   3650: bipush #49
    //   3652: ldc 268701760
    //   3654: iastore
    //   3655: dup
    //   3656: bipush #50
    //   3658: ldc 262208
    //   3660: iastore
    //   3661: dup
    //   3662: bipush #51
    //   3664: ldc 268435520
    //   3666: iastore
    //   3667: dup
    //   3668: bipush #52
    //   3670: ldc 268697600
    //   3672: iastore
    //   3673: dup
    //   3674: bipush #53
    //   3676: ldc 268439552
    //   3678: iastore
    //   3679: dup
    //   3680: bipush #54
    //   3682: ldc 268439616
    //   3684: iastore
    //   3685: dup
    //   3686: bipush #55
    //   3688: iconst_0
    //   3689: iastore
    //   3690: dup
    //   3691: bipush #56
    //   3693: ldc 268701760
    //   3695: iastore
    //   3696: dup
    //   3697: bipush #57
    //   3699: ldc 266240
    //   3701: iastore
    //   3702: dup
    //   3703: bipush #58
    //   3705: ldc 266240
    //   3707: iastore
    //   3708: dup
    //   3709: bipush #59
    //   3711: sipush #4160
    //   3714: iastore
    //   3715: dup
    //   3716: bipush #60
    //   3718: sipush #4160
    //   3721: iastore
    //   3722: dup
    //   3723: bipush #61
    //   3725: ldc 262208
    //   3727: iastore
    //   3728: dup
    //   3729: bipush #62
    //   3731: ldc 268435456
    //   3733: iastore
    //   3734: dup
    //   3735: bipush #63
    //   3737: ldc 268701696
    //   3739: iastore
    //   3740: astore #15
    //   3742: aload_3
    //   3743: arraylength
    //   3744: istore #16
    //   3746: iconst_2
    //   3747: newarray int
    //   3749: astore #17
    //   3751: iload #16
    //   3753: newarray byte
    //   3755: astore #4
    //   3757: iload #16
    //   3759: bipush #8
    //   3761: idiv
    //   3762: istore #18
    //   3764: iconst_0
    //   3765: istore #19
    //   3767: iload #19
    //   3769: iload #18
    //   3771: if_icmpge -> 4685
    //   3774: iload #19
    //   3776: bipush #8
    //   3778: imul
    //   3779: istore #20
    //   3781: iconst_0
    //   3782: istore #21
    //   3784: iload #21
    //   3786: iconst_2
    //   3787: if_icmpge -> 3872
    //   3790: aload #17
    //   3792: iload #21
    //   3794: aload_3
    //   3795: iload #20
    //   3797: iload #21
    //   3799: iconst_4
    //   3800: imul
    //   3801: iadd
    //   3802: baload
    //   3803: sipush #255
    //   3806: iand
    //   3807: bipush #24
    //   3809: ishl
    //   3810: aload_3
    //   3811: iload #20
    //   3813: iload #21
    //   3815: iconst_4
    //   3816: imul
    //   3817: iadd
    //   3818: iconst_1
    //   3819: iadd
    //   3820: baload
    //   3821: sipush #255
    //   3824: iand
    //   3825: bipush #16
    //   3827: ishl
    //   3828: ior
    //   3829: aload_3
    //   3830: iload #20
    //   3832: iload #21
    //   3834: iconst_4
    //   3835: imul
    //   3836: iadd
    //   3837: iconst_2
    //   3838: iadd
    //   3839: baload
    //   3840: sipush #255
    //   3843: iand
    //   3844: bipush #8
    //   3846: ishl
    //   3847: ior
    //   3848: aload_3
    //   3849: iload #20
    //   3851: iload #21
    //   3853: iconst_4
    //   3854: imul
    //   3855: iadd
    //   3856: iconst_3
    //   3857: iadd
    //   3858: baload
    //   3859: sipush #255
    //   3862: iand
    //   3863: ior
    //   3864: iastore
    //   3865: iinc #21, 1
    //   3868: iload_2
    //   3869: ifeq -> 3784
    //   3872: iconst_0
    //   3873: istore #26
    //   3875: aload #17
    //   3877: iconst_0
    //   3878: iaload
    //   3879: istore #24
    //   3881: aload #17
    //   3883: iconst_1
    //   3884: iaload
    //   3885: istore #23
    //   3887: iload #24
    //   3889: iconst_4
    //   3890: iushr
    //   3891: iload #23
    //   3893: ixor
    //   3894: ldc 252645135
    //   3896: iand
    //   3897: istore #22
    //   3899: iload #23
    //   3901: iload #22
    //   3903: ixor
    //   3904: istore #23
    //   3906: iload #24
    //   3908: iload #22
    //   3910: iconst_4
    //   3911: ishl
    //   3912: ixor
    //   3913: istore #24
    //   3915: iload #24
    //   3917: bipush #16
    //   3919: iushr
    //   3920: iload #23
    //   3922: ixor
    //   3923: ldc 65535
    //   3925: iand
    //   3926: istore #22
    //   3928: iload #23
    //   3930: iload #22
    //   3932: ixor
    //   3933: istore #23
    //   3935: iload #24
    //   3937: iload #22
    //   3939: bipush #16
    //   3941: ishl
    //   3942: ixor
    //   3943: istore #24
    //   3945: iload #23
    //   3947: iconst_2
    //   3948: iushr
    //   3949: iload #24
    //   3951: ixor
    //   3952: ldc 858993459
    //   3954: iand
    //   3955: istore #22
    //   3957: iload #24
    //   3959: iload #22
    //   3961: ixor
    //   3962: istore #24
    //   3964: iload #23
    //   3966: iload #22
    //   3968: iconst_2
    //   3969: ishl
    //   3970: ixor
    //   3971: istore #23
    //   3973: iload #23
    //   3975: bipush #8
    //   3977: iushr
    //   3978: iload #24
    //   3980: ixor
    //   3981: ldc 16711935
    //   3983: iand
    //   3984: istore #22
    //   3986: iload #24
    //   3988: iload #22
    //   3990: ixor
    //   3991: istore #24
    //   3993: iload #23
    //   3995: iload #22
    //   3997: bipush #8
    //   3999: ishl
    //   4000: ixor
    //   4001: istore #23
    //   4003: iload #23
    //   4005: iconst_1
    //   4006: ishl
    //   4007: iload #23
    //   4009: bipush #31
    //   4011: iushr
    //   4012: iconst_1
    //   4013: iand
    //   4014: ior
    //   4015: istore #23
    //   4017: iload #24
    //   4019: iload #23
    //   4021: ixor
    //   4022: ldc -1431655766
    //   4024: iand
    //   4025: istore #22
    //   4027: iload #24
    //   4029: iload #22
    //   4031: ixor
    //   4032: istore #24
    //   4034: iload #23
    //   4036: iload #22
    //   4038: ixor
    //   4039: istore #23
    //   4041: iload #24
    //   4043: iconst_1
    //   4044: ishl
    //   4045: iload #24
    //   4047: bipush #31
    //   4049: iushr
    //   4050: iconst_1
    //   4051: iand
    //   4052: ior
    //   4053: istore #24
    //   4055: iconst_0
    //   4056: istore #25
    //   4058: iload #25
    //   4060: bipush #8
    //   4062: if_icmpge -> 4400
    //   4065: iload #23
    //   4067: bipush #28
    //   4069: ishl
    //   4070: iload #23
    //   4072: iconst_4
    //   4073: iushr
    //   4074: ior
    //   4075: istore #22
    //   4077: iload #22
    //   4079: aload #5
    //   4081: iload #26
    //   4083: iinc #26, 1
    //   4086: iaload
    //   4087: ixor
    //   4088: istore #22
    //   4090: aload #14
    //   4092: iload #22
    //   4094: bipush #63
    //   4096: iand
    //   4097: iaload
    //   4098: istore #21
    //   4100: iload #21
    //   4102: aload #12
    //   4104: iload #22
    //   4106: bipush #8
    //   4108: iushr
    //   4109: bipush #63
    //   4111: iand
    //   4112: iaload
    //   4113: ior
    //   4114: istore #21
    //   4116: iload #21
    //   4118: aload #10
    //   4120: iload #22
    //   4122: bipush #16
    //   4124: iushr
    //   4125: bipush #63
    //   4127: iand
    //   4128: iaload
    //   4129: ior
    //   4130: istore #21
    //   4132: iload #21
    //   4134: aload #8
    //   4136: iload #22
    //   4138: bipush #24
    //   4140: iushr
    //   4141: bipush #63
    //   4143: iand
    //   4144: iaload
    //   4145: ior
    //   4146: istore #21
    //   4148: iload #23
    //   4150: aload #5
    //   4152: iload #26
    //   4154: iinc #26, 1
    //   4157: iaload
    //   4158: ixor
    //   4159: istore #22
    //   4161: iload #21
    //   4163: aload #15
    //   4165: iload #22
    //   4167: bipush #63
    //   4169: iand
    //   4170: iaload
    //   4171: ior
    //   4172: istore #21
    //   4174: iload #21
    //   4176: aload #13
    //   4178: iload #22
    //   4180: bipush #8
    //   4182: iushr
    //   4183: bipush #63
    //   4185: iand
    //   4186: iaload
    //   4187: ior
    //   4188: istore #21
    //   4190: iload #21
    //   4192: aload #11
    //   4194: iload #22
    //   4196: bipush #16
    //   4198: iushr
    //   4199: bipush #63
    //   4201: iand
    //   4202: iaload
    //   4203: ior
    //   4204: istore #21
    //   4206: iload #21
    //   4208: aload #9
    //   4210: iload #22
    //   4212: bipush #24
    //   4214: iushr
    //   4215: bipush #63
    //   4217: iand
    //   4218: iaload
    //   4219: ior
    //   4220: istore #21
    //   4222: iload #24
    //   4224: iload #21
    //   4226: ixor
    //   4227: istore #24
    //   4229: iload #24
    //   4231: bipush #28
    //   4233: ishl
    //   4234: iload #24
    //   4236: iconst_4
    //   4237: iushr
    //   4238: ior
    //   4239: istore #22
    //   4241: iload #22
    //   4243: aload #5
    //   4245: iload #26
    //   4247: iinc #26, 1
    //   4250: iaload
    //   4251: ixor
    //   4252: istore #22
    //   4254: aload #14
    //   4256: iload #22
    //   4258: bipush #63
    //   4260: iand
    //   4261: iaload
    //   4262: istore #21
    //   4264: iload #21
    //   4266: aload #12
    //   4268: iload #22
    //   4270: bipush #8
    //   4272: iushr
    //   4273: bipush #63
    //   4275: iand
    //   4276: iaload
    //   4277: ior
    //   4278: istore #21
    //   4280: iload #21
    //   4282: aload #10
    //   4284: iload #22
    //   4286: bipush #16
    //   4288: iushr
    //   4289: bipush #63
    //   4291: iand
    //   4292: iaload
    //   4293: ior
    //   4294: istore #21
    //   4296: iload #21
    //   4298: aload #8
    //   4300: iload #22
    //   4302: bipush #24
    //   4304: iushr
    //   4305: bipush #63
    //   4307: iand
    //   4308: iaload
    //   4309: ior
    //   4310: istore #21
    //   4312: iload #24
    //   4314: aload #5
    //   4316: iload #26
    //   4318: iinc #26, 1
    //   4321: iaload
    //   4322: ixor
    //   4323: istore #22
    //   4325: iload #21
    //   4327: aload #15
    //   4329: iload #22
    //   4331: bipush #63
    //   4333: iand
    //   4334: iaload
    //   4335: ior
    //   4336: istore #21
    //   4338: iload #21
    //   4340: aload #13
    //   4342: iload #22
    //   4344: bipush #8
    //   4346: iushr
    //   4347: bipush #63
    //   4349: iand
    //   4350: iaload
    //   4351: ior
    //   4352: istore #21
    //   4354: iload #21
    //   4356: aload #11
    //   4358: iload #22
    //   4360: bipush #16
    //   4362: iushr
    //   4363: bipush #63
    //   4365: iand
    //   4366: iaload
    //   4367: ior
    //   4368: istore #21
    //   4370: iload #21
    //   4372: aload #9
    //   4374: iload #22
    //   4376: bipush #24
    //   4378: iushr
    //   4379: bipush #63
    //   4381: iand
    //   4382: iaload
    //   4383: ior
    //   4384: istore #21
    //   4386: iload #23
    //   4388: iload #21
    //   4390: ixor
    //   4391: istore #23
    //   4393: iinc #25, 1
    //   4396: iload_2
    //   4397: ifeq -> 4058
    //   4400: iload #23
    //   4402: bipush #31
    //   4404: ishl
    //   4405: iload #23
    //   4407: iconst_1
    //   4408: iushr
    //   4409: ior
    //   4410: istore #23
    //   4412: iload #24
    //   4414: iload #23
    //   4416: ixor
    //   4417: ldc -1431655766
    //   4419: iand
    //   4420: istore #22
    //   4422: iload #24
    //   4424: iload #22
    //   4426: ixor
    //   4427: istore #24
    //   4429: iload #23
    //   4431: iload #22
    //   4433: ixor
    //   4434: istore #23
    //   4436: iload #24
    //   4438: bipush #31
    //   4440: ishl
    //   4441: iload #24
    //   4443: iconst_1
    //   4444: iushr
    //   4445: ior
    //   4446: istore #24
    //   4448: iload #24
    //   4450: bipush #8
    //   4452: iushr
    //   4453: iload #23
    //   4455: ixor
    //   4456: ldc 16711935
    //   4458: iand
    //   4459: istore #22
    //   4461: iload #23
    //   4463: iload #22
    //   4465: ixor
    //   4466: istore #23
    //   4468: iload #24
    //   4470: iload #22
    //   4472: bipush #8
    //   4474: ishl
    //   4475: ixor
    //   4476: istore #24
    //   4478: iload #24
    //   4480: iconst_2
    //   4481: iushr
    //   4482: iload #23
    //   4484: ixor
    //   4485: ldc 858993459
    //   4487: iand
    //   4488: istore #22
    //   4490: iload #23
    //   4492: iload #22
    //   4494: ixor
    //   4495: istore #23
    //   4497: iload #24
    //   4499: iload #22
    //   4501: iconst_2
    //   4502: ishl
    //   4503: ixor
    //   4504: istore #24
    //   4506: iload #23
    //   4508: bipush #16
    //   4510: iushr
    //   4511: iload #24
    //   4513: ixor
    //   4514: ldc 65535
    //   4516: iand
    //   4517: istore #22
    //   4519: iload #24
    //   4521: iload #22
    //   4523: ixor
    //   4524: istore #24
    //   4526: iload #23
    //   4528: iload #22
    //   4530: bipush #16
    //   4532: ishl
    //   4533: ixor
    //   4534: istore #23
    //   4536: iload #23
    //   4538: iconst_4
    //   4539: iushr
    //   4540: iload #24
    //   4542: ixor
    //   4543: ldc 252645135
    //   4545: iand
    //   4546: istore #22
    //   4548: iload #24
    //   4550: iload #22
    //   4552: ixor
    //   4553: istore #24
    //   4555: iload #23
    //   4557: iload #22
    //   4559: iconst_4
    //   4560: ishl
    //   4561: ixor
    //   4562: istore #23
    //   4564: aload #17
    //   4566: iconst_0
    //   4567: iload #23
    //   4569: iastore
    //   4570: aload #17
    //   4572: iconst_1
    //   4573: iload #24
    //   4575: iastore
    //   4576: iload #19
    //   4578: bipush #8
    //   4580: imul
    //   4581: istore #27
    //   4583: iconst_0
    //   4584: istore #28
    //   4586: iload #28
    //   4588: iconst_2
    //   4589: if_icmpge -> 4678
    //   4592: aload #4
    //   4594: iload #27
    //   4596: iload #28
    //   4598: iconst_4
    //   4599: imul
    //   4600: iadd
    //   4601: aload #17
    //   4603: iload #28
    //   4605: iaload
    //   4606: bipush #24
    //   4608: iushr
    //   4609: i2b
    //   4610: bastore
    //   4611: aload #4
    //   4613: iload #27
    //   4615: iload #28
    //   4617: iconst_4
    //   4618: imul
    //   4619: iadd
    //   4620: iconst_1
    //   4621: iadd
    //   4622: aload #17
    //   4624: iload #28
    //   4626: iaload
    //   4627: bipush #16
    //   4629: iushr
    //   4630: i2b
    //   4631: bastore
    //   4632: aload #4
    //   4634: iload #27
    //   4636: iload #28
    //   4638: iconst_4
    //   4639: imul
    //   4640: iadd
    //   4641: iconst_2
    //   4642: iadd
    //   4643: aload #17
    //   4645: iload #28
    //   4647: iaload
    //   4648: bipush #8
    //   4650: iushr
    //   4651: i2b
    //   4652: bastore
    //   4653: aload #4
    //   4655: iload #27
    //   4657: iload #28
    //   4659: iconst_4
    //   4660: imul
    //   4661: iadd
    //   4662: iconst_3
    //   4663: iadd
    //   4664: aload #17
    //   4666: iload #28
    //   4668: iaload
    //   4669: i2b
    //   4670: bastore
    //   4671: iinc #28, 1
    //   4674: iload_2
    //   4675: ifeq -> 4586
    //   4678: iinc #19, 1
    //   4681: iload_2
    //   4682: ifeq -> 3767
    //   4685: getstatic burp/Zkjj.ZT : Ljava/lang/String;
    //   4688: getstatic burp/Zk1.Z_ : Ljava/lang/Object;
    //   4691: checkcast java/math/BigInteger
    //   4694: invokevirtual intValue : ()I
    //   4697: bipush #32
    //   4699: irem
    //   4700: invokestatic abs : (I)I
    //   4703: invokevirtual charAt : (I)C
    //   4706: getstatic burp/Zedu.ZD : Ljava/lang/String;
    //   4709: getstatic burp/Zle9.ZI : Ljava/lang/Object;
    //   4712: checkcast java/math/BigInteger
    //   4715: invokevirtual intValue : ()I
    //   4718: bipush #32
    //   4720: irem
    //   4721: invokestatic abs : (I)I
    //   4724: invokevirtual charAt : (I)C
    //   4727: if_icmpgt -> 4842
    //   4730: getstatic burp/Zmdi.ZA : Ljava/lang/String;
    //   4733: getstatic burp/Zgio.ZP : Ljava/lang/Object;
    //   4736: checkcast java/math/BigInteger
    //   4739: invokevirtual intValue : ()I
    //   4742: bipush #32
    //   4744: irem
    //   4745: invokestatic abs : (I)I
    //   4748: invokevirtual charAt : (I)C
    //   4751: getstatic burp/Zbun.ZS : Ljava/lang/String;
    //   4754: getstatic burp/Zxd1.Zc : Ljava/lang/Object;
    //   4757: checkcast java/math/BigInteger
    //   4760: invokevirtual intValue : ()I
    //   4763: bipush #32
    //   4765: irem
    //   4766: invokestatic abs : (I)I
    //   4769: invokevirtual charAt : (I)C
    //   4772: if_icmple -> 4842
    //   4775: goto -> 4782
    //   4778: invokestatic a : (Ljava/lang/Throwable;)Ljava/lang/Throwable;
    //   4781: athrow
    //   4782: getstatic burp/Zbjx.ZA : Ljava/lang/String;
    //   4785: getstatic burp/Ztl6.ZQ : Ljava/lang/Object;
    //   4788: checkcast java/math/BigInteger
    //   4791: invokevirtual intValue : ()I
    //   4794: bipush #32
    //   4796: irem
    //   4797: invokestatic abs : (I)I
    //   4800: invokevirtual charAt : (I)C
    //   4803: getstatic burp/Zeub.ZT : Ljava/lang/String;
    //   4806: getstatic burp/Zs1d.Zo : Ljava/lang/Object;
    //   4809: checkcast java/math/BigInteger
    //   4812: invokevirtual intValue : ()I
    //   4815: bipush #32
    //   4817: irem
    //   4818: invokestatic abs : (I)I
    //   4821: invokevirtual charAt : (I)C
    //   4824: if_icmple -> 4842
    //   4827: goto -> 4834
    //   4830: invokestatic a : (Ljava/lang/Throwable;)Ljava/lang/Throwable;
    //   4833: athrow
    //   4834: iconst_1
    //   4835: goto -> 4843
    //   4838: invokestatic a : (Ljava/lang/Throwable;)Ljava/lang/Throwable;
    //   4841: athrow
    //   4842: iconst_0
    //   4843: ireturn
    //   4844: astore_3
    //   4845: new java/lang/Exception
    //   4848: dup
    //   4849: aload_3
    //   4850: invokevirtual getMessage : ()Ljava/lang/String;
    //   4853: invokespecial <init> : (Ljava/lang/String;)V
    //   4856: athrow
    // Exception table:
    //   from	to	target	type
    //   4	4843	4844	java/lang/Throwable
    //   82	96	96	java/lang/Throwable
    //   107	120	123	java/lang/Throwable
    //   112	135	138	java/lang/Throwable
    //   127	153	156	java/lang/Throwable
    //   142	183	186	java/lang/Throwable
    //   246	273	276	java/lang/Throwable
    //   263	294	297	java/lang/Throwable
    //   280	324	327	java/lang/Throwable
    //   301	335	335	java/lang/Throwable
    //   346	362	365	java/lang/Throwable
    //   4685	4775	4778	java/lang/Throwable
    //   4730	4827	4830	java/lang/Throwable
    //   4782	4838	4838	java/lang/Throwable
  }
  
  static void Zt(Object paramObject) {
    Zxxh.Zm = a(-3098, 29517);
    Zxxh.Za = new BigInteger(a(-3097, 25149));
    boolean bool = Zt2e.ZK();
    try {
      try {
        if (Zs8w.ZR.charAt(Math.abs(((BigInteger)Zlgh.Zd).intValue() % 32)) <= Zgu4.Za.charAt(Math.abs(((BigInteger)Ztl6.ZQ).intValue() % 32))) {
          try {
            Zk8b.Zg(Class.forName(a(-3103, 6856)));
            if (bool)
              Zb3r.Zl(Class.forName(a(-3099, 5391))); 
          } catch (Throwable throwable) {
            throw a(null);
          } 
          return;
        } 
      } catch (Throwable throwable) {
        throw a(null);
      } 
      Zb3r.Zl(Class.forName(a(-3099, 5391)));
    } catch (Throwable throwable) {}
  }
  
  static void Za(Object[] paramArrayOfObject, Object paramObject) throws Throwable {}
  
  static {
    // Byte code:
    //   0: bipush #8
    //   2: anewarray java/lang/String
    //   5: astore #5
    //   7: iconst_0
    //   8: istore_3
    //   9: ldc 'Ze@kLGij\\t "GpV\\t }yS :=8dQHiDB<R<w*~@M"4 5SfH{(@3uhTy 83-',~)4X`">t _'
    //   11: dup
    //   12: astore_2
    //   13: invokevirtual length : ()I
    //   16: istore #4
    //   18: bipush #9
    //   20: istore_1
    //   21: iconst_m1
    //   22: istore_0
    //   23: bipush #112
    //   25: iinc #0, 1
    //   28: aload_2
    //   29: iload_0
    //   30: dup
    //   31: iload_1
    //   32: iadd
    //   33: invokevirtual substring : (II)Ljava/lang/String;
    //   36: iconst_m1
    //   37: goto -> 142
    //   40: aload #5
    //   42: swap
    //   43: iload_3
    //   44: iinc #3, 1
    //   47: swap
    //   48: aastore
    //   49: iload_0
    //   50: iload_1
    //   51: iadd
    //   52: dup
    //   53: istore_0
    //   54: iload #4
    //   56: if_icmpge -> 68
    //   59: aload_2
    //   60: iload_0
    //   61: invokevirtual charAt : (I)C
    //   64: istore_1
    //   65: goto -> 23
    //   68: ldc 'U=e}t:9f`#,~i{\\t;f=('
    //   70: dup
    //   71: astore_2
    //   72: invokevirtual length : ()I
    //   75: istore #4
    //   77: bipush #32
    //   79: istore_1
    //   80: iconst_m1
    //   81: istore_0
    //   82: iconst_3
    //   83: iinc #0, 1
    //   86: aload_2
    //   87: iload_0
    //   88: dup
    //   89: iload_1
    //   90: iadd
    //   91: invokevirtual substring : (II)Ljava/lang/String;
    //   94: iconst_0
    //   95: goto -> 142
    //   98: aload #5
    //   100: swap
    //   101: iload_3
    //   102: iinc #3, 1
    //   105: swap
    //   106: aastore
    //   107: iload_0
    //   108: iload_1
    //   109: iadd
    //   110: dup
    //   111: istore_0
    //   112: iload #4
    //   114: if_icmpge -> 126
    //   117: aload_2
    //   118: iload_0
    //   119: invokevirtual charAt : (I)C
    //   122: istore_1
    //   123: goto -> 82
    //   126: aload #5
    //   128: putstatic burp/Zm83.a : [Ljava/lang/String;
    //   131: bipush #8
    //   133: anewarray java/lang/String
    //   136: putstatic burp/Zm83.b : [Ljava/lang/String;
    //   139: goto -> 300
    //   142: dup_x2
    //   143: pop
    //   144: invokevirtual toCharArray : ()[C
    //   147: dup_x1
    //   148: arraylength
    //   149: dup_x2
    //   150: pop
    //   151: iconst_0
    //   152: istore #6
    //   154: dup2_x1
    //   155: pop2
    //   156: dup_x2
    //   157: iconst_1
    //   158: if_icmpgt -> 260
    //   161: dup2
    //   162: swap
    //   163: iload #6
    //   165: dup2_x1
    //   166: caload
    //   167: swap
    //   168: iload #6
    //   170: bipush #7
    //   172: irem
    //   173: tableswitch default -> 242, 0 -> 212, 1 -> 217, 2 -> 222, 3 -> 227, 4 -> 232, 5 -> 237
    //   212: bipush #112
    //   214: goto -> 244
    //   217: bipush #32
    //   219: goto -> 244
    //   222: bipush #107
    //   224: goto -> 244
    //   227: bipush #40
    //   229: goto -> 244
    //   232: bipush #34
    //   234: goto -> 244
    //   237: bipush #73
    //   239: goto -> 244
    //   242: bipush #44
    //   244: ixor
    //   245: ixor
    //   246: i2c
    //   247: castore
    //   248: iinc #6, 1
    //   251: dup
    //   252: ifne -> 260
    //   255: dup2
    //   256: dup_x1
    //   257: goto -> 165
    //   260: dup2_x1
    //   261: pop2
    //   262: dup_x2
    //   263: iload #6
    //   265: if_icmpgt -> 161
    //   268: pop
    //   269: new java/lang/String
    //   272: dup_x1
    //   273: swap
    //   274: invokespecial <init> : ([C)V
    //   277: invokevirtual intern : ()Ljava/lang/String;
    //   280: swap
    //   281: pop
    //   282: swap
    //   283: tableswitch default -> 40, 0 -> 98
    //   300: sipush #-3100
    //   303: sipush #-10498
    //   306: invokestatic a : (II)Ljava/lang/String;
    //   309: putstatic burp/Zm83.Zq : Ljava/lang/String;
    //   312: new java/math/BigInteger
    //   315: dup
    //   316: iconst_1
    //   317: bipush #32
    //   319: newarray byte
    //   321: dup
    //   322: iconst_0
    //   323: bipush #67
    //   325: bastore
    //   326: dup
    //   327: iconst_1
    //   328: bipush #73
    //   330: bastore
    //   331: dup
    //   332: iconst_2
    //   333: bipush #100
    //   335: bastore
    //   336: dup
    //   337: iconst_3
    //   338: bipush #90
    //   340: bastore
    //   341: dup
    //   342: iconst_4
    //   343: bipush #-107
    //   345: bastore
    //   346: dup
    //   347: iconst_5
    //   348: bipush #69
    //   350: bastore
    //   351: dup
    //   352: bipush #6
    //   354: bipush #78
    //   356: bastore
    //   357: dup
    //   358: bipush #7
    //   360: iconst_3
    //   361: bastore
    //   362: dup
    //   363: bipush #8
    //   365: bipush #73
    //   367: bastore
    //   368: dup
    //   369: bipush #9
    //   371: bipush #-65
    //   373: bastore
    //   374: dup
    //   375: bipush #10
    //   377: bipush #89
    //   379: bastore
    //   380: dup
    //   381: bipush #11
    //   383: iconst_4
    //   384: bastore
    //   385: dup
    //   386: bipush #12
    //   388: bipush #26
    //   390: bastore
    //   391: dup
    //   392: bipush #13
    //   394: bipush #-45
    //   396: bastore
    //   397: dup
    //   398: bipush #14
    //   400: bipush #77
    //   402: bastore
    //   403: dup
    //   404: bipush #15
    //   406: bipush #94
    //   408: bastore
    //   409: dup
    //   410: bipush #16
    //   412: bipush #31
    //   414: bastore
    //   415: dup
    //   416: bipush #17
    //   418: bipush #-56
    //   420: bastore
    //   421: dup
    //   422: bipush #18
    //   424: bipush #116
    //   426: bastore
    //   427: dup
    //   428: bipush #19
    //   430: bipush #50
    //   432: bastore
    //   433: dup
    //   434: bipush #20
    //   436: bipush #81
    //   438: bastore
    //   439: dup
    //   440: bipush #21
    //   442: bipush #29
    //   444: bastore
    //   445: dup
    //   446: bipush #22
    //   448: bipush #94
    //   450: bastore
    //   451: dup
    //   452: bipush #23
    //   454: bipush #87
    //   456: bastore
    //   457: dup
    //   458: bipush #24
    //   460: bipush #-100
    //   462: bastore
    //   463: dup
    //   464: bipush #25
    //   466: bipush #-128
    //   468: bastore
    //   469: dup
    //   470: bipush #26
    //   472: bipush #81
    //   474: bastore
    //   475: dup
    //   476: bipush #27
    //   478: bipush #-55
    //   480: bastore
    //   481: dup
    //   482: bipush #28
    //   484: bipush #-128
    //   486: bastore
    //   487: dup
    //   488: bipush #29
    //   490: bipush #50
    //   492: bastore
    //   493: dup
    //   494: bipush #30
    //   496: bipush #-122
    //   498: bastore
    //   499: dup
    //   500: bipush #31
    //   502: bipush #83
    //   504: bastore
    //   505: invokespecial <init> : (I[B)V
    //   508: putstatic burp/Zm83.Zl : Ljava/lang/Object;
    //   511: return
  }
  
  private static Throwable a(Throwable paramThrowable) {
    return paramThrowable;
  }
  
  private static String a(int paramInt1, int paramInt2) {
    int i = (paramInt1 ^ 0xFFFFF3E2) & 0xFFFF;
    if (b[i] == null) {
      char[] arrayOfChar = a[i].toCharArray();
      switch (arrayOfChar[0] & 0xFF) {
        case 0:
        
        case 1:
        
        case 2:
        
        case 3:
        
        case 4:
        
        case 5:
        
        case 6:
        
        case 7:
        
        case 8:
        
        case 9:
        
        case 10:
        
        case 11:
        
        case 12:
        
        case 13:
        
        case 14:
        
        case 15:
        
        case 16:
        
        case 17:
        
        case 18:
        
        case 19:
        
        case 20:
        
        case 21:
        
        case 22:
        
        case 23:
        
        case 24:
        
        case 25:
        
        case 26:
        
        case 27:
        
        case 28:
        
        case 29:
        
        case 30:
        
        case 31:
        
        case 32:
        
        case 33:
        
        case 34:
        
        case 35:
        
        case 36:
        
        case 37:
        
        case 38:
        
        case 39:
        
        case 40:
        
        case 41:
        
        case 42:
        
        case 43:
        
        case 44:
        
        case 45:
        
        case 46:
        
        case 47:
        
        case 48:
        
        case 49:
        
        case 50:
        
        case 51:
        
        case 52:
        
        case 53:
        
        case 54:
        
        case 55:
        
        case 56:
        
        case 57:
        
        case 58:
        
        case 59:
        
        case 60:
        
        case 61:
        
        case 62:
        
        case 63:
        
        case 64:
        
        case 65:
        
        case 66:
        
        case 67:
        
        case 68:
        
        case 69:
        
        case 70:
        
        case 71:
        
        case 72:
        
        case 73:
        
        case 74:
        
        case 75:
        
        case 76:
        
        case 77:
        
        case 78:
        
        case 79:
        
        case 80:
        
        case 81:
        
        case 82:
        
        case 83:
        
        case 84:
        
        case 85:
        
        case 86:
        
        case 87:
        
        case 88:
        
        case 89:
        
        case 90:
        
        case 91:
        
        case 92:
        
        case 93:
        
        case 94:
        
        case 95:
        
        case 96:
        
        case 97:
        
        case 98:
        
        case 99:
        
        case 100:
        
        case 101:
        
        case 102:
        
        case 103:
        
        case 104:
        
        case 105:
        
        case 106:
        
        case 107:
        
        case 108:
        
        case 109:
        
        case 110:
        
        case 111:
        
        case 112:
        
        case 113:
        
        case 114:
        
        case 115:
        
        case 116:
        
        case 117:
        
        case 118:
        
        case 119:
        
        case 120:
        
        case 121:
        
        case 122:
        
        case 123:
        
        case 124:
        
        case 125:
        
        case 126:
        
        case 127:
        
        case 128:
        
        case 129:
        
        case 130:
        
        case 131:
        
        case 132:
        
        case 133:
        
        case 134:
        
        case 135:
        
        case 136:
        
        case 137:
        
        case 138:
        
        case 139:
        
        case 140:
        
        case 141:
        
        case 142:
        
        case 143:
        
        case 144:
        
        case 145:
        
        case 146:
        
        case 147:
        
        case 148:
        
        case 149:
        
        case 150:
        
        case 151:
        
        case 152:
        
        case 153:
        
        case 154:
        
        case 155:
        
        case 156:
        
        case 157:
        
        case 158:
        
        case 159:
        
        case 160:
        
        case 161:
        
        case 162:
        
        case 163:
        
        case 164:
        
        case 165:
        
        case 166:
        
        case 167:
        
        case 168:
        
        case 169:
        
        case 170:
        
        case 171:
        
        case 172:
        
        case 173:
        
        case 174:
        
        case 175:
        
        case 176:
        
        case 177:
        
        case 178:
        
        case 179:
        
        case 180:
        
        case 181:
        
        case 182:
        
        case 183:
        
        case 184:
        
        case 185:
        
        case 186:
        
        case 187:
        
        case 188:
        
        case 189:
        
        case 190:
        
        case 191:
        
        case 192:
        
        case 193:
        
        case 194:
        
        case 195:
        
        case 196:
        
        case 197:
        
        case 198:
        
        case 199:
        
        case 200:
        
        case 201:
        
        case 202:
        
        case 203:
        
        case 204:
        
        case 205:
        
        case 206:
        
        case 207:
        
        case 208:
        
        case 209:
        
        case 210:
        
        case 211:
        
        case 212:
        
        case 213:
        
        case 214:
        
        case 215:
        
        case 216:
        
        case 217:
        
        case 218:
        
        case 219:
        
        case 220:
        
        case 221:
        
        case 222:
        
        case 223:
        
        case 224:
        
        case 225:
        
        case 226:
        
        case 227:
        
        case 228:
        
        case 229:
        
        case 230:
        
        case 231:
        
        case 232:
        
        case 233:
        
        case 234:
        
        case 235:
        
        case 236:
        
        case 237:
        
        case 238:
        
        case 239:
        
        case 240:
        
        case 241:
        
        case 242:
        
        case 243:
        
        case 244:
        
        case 245:
        
        case 246:
        
        case 247:
        
        case 248:
        
        case 249:
        
        case 250:
        
        case 251:
        
        case 252:
        
        case 253:
        
        case 254:
        
        default:
          break;
      } 
      byte b1 = 36;
      int j = (paramInt2 & 0xFF) - b1;
      if (j < 0)
        j += 256; 
      int k = ((paramInt2 & 0xFFFF) >>> 8) - b1;
      if (k < 0)
        k += 256; 
      for (byte b2 = 0; b2 < arrayOfChar.length; b2++) {
        int m = b2 % 2;
        if (m == 0) {
          arrayOfChar[b2] = (char)(arrayOfChar[b2] ^ j);
          j = ((j >>> 3 | j << 5) ^ arrayOfChar[b2]) & 0xFF;
        } else {
          arrayOfChar[b2] = (char)(arrayOfChar[b2] ^ k);
          k = ((k >>> 3 | k << 5) ^ arrayOfChar[b2]) & 0xFF;
        } 
      } 
      b[i] = (new String(arrayOfChar)).intern();
    } 
    return b[i];
  }
}


/* Location:              C:\Program Files\BurpSuitePro\burpsuite_pro.jar!\burp\Zm83.class
 * Java compiler version: 21 (65.0)
 * JD-Core Version:       1.1.3
 */