package burp;

import java.math.BigInteger;

class Zm84 extends ClassLoader {
  static Object Zf;
  
  static String Zd;
  
  private static final String[] a;
  
  private static final String[] b;
  
  static boolean ZW(Object[] paramArrayOfObject, Object paramObject) throws Throwable {
    // Byte code:
    //   0: invokestatic ZK : ()Z
    //   3: istore_2
    //   4: new java/lang/StringBuilder
    //   7: dup
    //   8: invokespecial <init> : ()V
    //   11: astore_3
    //   12: iconst_0
    //   13: istore #4
    //   15: iload #4
    //   17: bipush #32
    //   19: if_icmpge -> 1355
    //   22: iload #4
    //   24: tableswitch default -> 1348, 0 -> 168, 1 -> 205, 2 -> 242, 3 -> 279, 4 -> 316, 5 -> 353, 6 -> 390, 7 -> 427, 8 -> 464, 9 -> 501, 10 -> 538, 11 -> 575, 12 -> 612, 13 -> 649, 14 -> 686, 15 -> 723, 16 -> 760, 17 -> 797, 18 -> 834, 19 -> 871, 20 -> 908, 21 -> 945, 22 -> 982, 23 -> 1019, 24 -> 1056, 25 -> 1093, 26 -> 1130, 27 -> 1167, 28 -> 1204, 29 -> 1241, 30 -> 1278, 31 -> 1315
    //   168: aload_3
    //   169: getstatic burp/Zeno.ZL : Ljava/lang/String;
    //   172: getstatic burp/Zero.ZE : Ljava/lang/Object;
    //   175: checkcast java/math/BigInteger
    //   178: invokevirtual intValue : ()I
    //   181: bipush #32
    //   183: irem
    //   184: invokestatic abs : (I)I
    //   187: invokevirtual charAt : (I)C
    //   190: invokevirtual append : (C)Ljava/lang/StringBuilder;
    //   193: pop
    //   194: iload_2
    //   195: ifeq -> 1348
    //   198: goto -> 205
    //   201: invokestatic a : (Ljava/lang/Throwable;)Ljava/lang/Throwable;
    //   204: athrow
    //   205: aload_3
    //   206: getstatic burp/Zgw7.ZN : Ljava/lang/String;
    //   209: getstatic burp/Zrxm.ZL : Ljava/lang/Object;
    //   212: checkcast java/math/BigInteger
    //   215: invokevirtual intValue : ()I
    //   218: bipush #32
    //   220: irem
    //   221: invokestatic abs : (I)I
    //   224: invokevirtual charAt : (I)C
    //   227: invokevirtual append : (C)Ljava/lang/StringBuilder;
    //   230: pop
    //   231: iload_2
    //   232: ifeq -> 1348
    //   235: goto -> 242
    //   238: invokestatic a : (Ljava/lang/Throwable;)Ljava/lang/Throwable;
    //   241: athrow
    //   242: aload_3
    //   243: getstatic burp/Zl22.ZL : Ljava/lang/String;
    //   246: getstatic burp/Ztap.ZK : Ljava/lang/Object;
    //   249: checkcast java/math/BigInteger
    //   252: invokevirtual intValue : ()I
    //   255: bipush #32
    //   257: irem
    //   258: invokestatic abs : (I)I
    //   261: invokevirtual charAt : (I)C
    //   264: invokevirtual append : (C)Ljava/lang/StringBuilder;
    //   267: pop
    //   268: iload_2
    //   269: ifeq -> 1348
    //   272: goto -> 279
    //   275: invokestatic a : (Ljava/lang/Throwable;)Ljava/lang/Throwable;
    //   278: athrow
    //   279: aload_3
    //   280: getstatic burp/Zldx.Zm : Ljava/lang/String;
    //   283: getstatic burp/Zsk2.ZD : Ljava/lang/Object;
    //   286: checkcast java/math/BigInteger
    //   289: invokevirtual intValue : ()I
    //   292: bipush #32
    //   294: irem
    //   295: invokestatic abs : (I)I
    //   298: invokevirtual charAt : (I)C
    //   301: invokevirtual append : (C)Ljava/lang/StringBuilder;
    //   304: pop
    //   305: iload_2
    //   306: ifeq -> 1348
    //   309: goto -> 316
    //   312: invokestatic a : (Ljava/lang/Throwable;)Ljava/lang/Throwable;
    //   315: athrow
    //   316: aload_3
    //   317: getstatic burp/Ztap.Zk : Ljava/lang/String;
    //   320: getstatic burp/Zkk6.Zb : Ljava/lang/Object;
    //   323: checkcast java/math/BigInteger
    //   326: invokevirtual intValue : ()I
    //   329: bipush #32
    //   331: irem
    //   332: invokestatic abs : (I)I
    //   335: invokevirtual charAt : (I)C
    //   338: invokevirtual append : (C)Ljava/lang/StringBuilder;
    //   341: pop
    //   342: iload_2
    //   343: ifeq -> 1348
    //   346: goto -> 353
    //   349: invokestatic a : (Ljava/lang/Throwable;)Ljava/lang/Throwable;
    //   352: athrow
    //   353: aload_3
    //   354: getstatic burp/Zeno.ZL : Ljava/lang/String;
    //   357: getstatic burp/Zetv.ZI : Ljava/lang/Object;
    //   360: checkcast java/math/BigInteger
    //   363: invokevirtual intValue : ()I
    //   366: bipush #32
    //   368: irem
    //   369: invokestatic abs : (I)I
    //   372: invokevirtual charAt : (I)C
    //   375: invokevirtual append : (C)Ljava/lang/StringBuilder;
    //   378: pop
    //   379: iload_2
    //   380: ifeq -> 1348
    //   383: goto -> 390
    //   386: invokestatic a : (Ljava/lang/Throwable;)Ljava/lang/Throwable;
    //   389: athrow
    //   390: aload_3
    //   391: getstatic burp/Zl3n.Zy : Ljava/lang/String;
    //   394: getstatic burp/Zezq.Zu : Ljava/lang/Object;
    //   397: checkcast java/math/BigInteger
    //   400: invokevirtual intValue : ()I
    //   403: bipush #32
    //   405: irem
    //   406: invokestatic abs : (I)I
    //   409: invokevirtual charAt : (I)C
    //   412: invokevirtual append : (C)Ljava/lang/StringBuilder;
    //   415: pop
    //   416: iload_2
    //   417: ifeq -> 1348
    //   420: goto -> 427
    //   423: invokestatic a : (Ljava/lang/Throwable;)Ljava/lang/Throwable;
    //   426: athrow
    //   427: aload_3
    //   428: getstatic burp/Zsk2.ZE : Ljava/lang/String;
    //   431: getstatic burp/Zgvl.ZK : Ljava/lang/Object;
    //   434: checkcast java/math/BigInteger
    //   437: invokevirtual intValue : ()I
    //   440: bipush #32
    //   442: irem
    //   443: invokestatic abs : (I)I
    //   446: invokevirtual charAt : (I)C
    //   449: invokevirtual append : (C)Ljava/lang/StringBuilder;
    //   452: pop
    //   453: iload_2
    //   454: ifeq -> 1348
    //   457: goto -> 464
    //   460: invokestatic a : (Ljava/lang/Throwable;)Ljava/lang/Throwable;
    //   463: athrow
    //   464: aload_3
    //   465: getstatic burp/Ztt0.Zl : Ljava/lang/String;
    //   468: getstatic burp/Zbnb.ZZ : Ljava/lang/Object;
    //   471: checkcast java/math/BigInteger
    //   474: invokevirtual intValue : ()I
    //   477: bipush #32
    //   479: irem
    //   480: invokestatic abs : (I)I
    //   483: invokevirtual charAt : (I)C
    //   486: invokevirtual append : (C)Ljava/lang/StringBuilder;
    //   489: pop
    //   490: iload_2
    //   491: ifeq -> 1348
    //   494: goto -> 501
    //   497: invokestatic a : (Ljava/lang/Throwable;)Ljava/lang/Throwable;
    //   500: athrow
    //   501: aload_3
    //   502: getstatic burp/Zz5s.ZL : Ljava/lang/String;
    //   505: getstatic burp/Ztod.ZP : Ljava/lang/Object;
    //   508: checkcast java/math/BigInteger
    //   511: invokevirtual intValue : ()I
    //   514: bipush #32
    //   516: irem
    //   517: invokestatic abs : (I)I
    //   520: invokevirtual charAt : (I)C
    //   523: invokevirtual append : (C)Ljava/lang/StringBuilder;
    //   526: pop
    //   527: iload_2
    //   528: ifeq -> 1348
    //   531: goto -> 538
    //   534: invokestatic a : (Ljava/lang/Throwable;)Ljava/lang/Throwable;
    //   537: athrow
    //   538: aload_3
    //   539: getstatic burp/Zl22.ZL : Ljava/lang/String;
    //   542: getstatic burp/Zmh5.ZN : Ljava/lang/Object;
    //   545: checkcast java/math/BigInteger
    //   548: invokevirtual intValue : ()I
    //   551: bipush #32
    //   553: irem
    //   554: invokestatic abs : (I)I
    //   557: invokevirtual charAt : (I)C
    //   560: invokevirtual append : (C)Ljava/lang/StringBuilder;
    //   563: pop
    //   564: iload_2
    //   565: ifeq -> 1348
    //   568: goto -> 575
    //   571: invokestatic a : (Ljava/lang/Throwable;)Ljava/lang/Throwable;
    //   574: athrow
    //   575: aload_3
    //   576: getstatic burp/Ztev.Zp : Ljava/lang/String;
    //   579: getstatic burp/Zete.Zm : Ljava/lang/Object;
    //   582: checkcast java/math/BigInteger
    //   585: invokevirtual intValue : ()I
    //   588: bipush #32
    //   590: irem
    //   591: invokestatic abs : (I)I
    //   594: invokevirtual charAt : (I)C
    //   597: invokevirtual append : (C)Ljava/lang/StringBuilder;
    //   600: pop
    //   601: iload_2
    //   602: ifeq -> 1348
    //   605: goto -> 612
    //   608: invokestatic a : (Ljava/lang/Throwable;)Ljava/lang/Throwable;
    //   611: athrow
    //   612: aload_3
    //   613: getstatic burp/Zlhz.Zo : Ljava/lang/String;
    //   616: getstatic burp/Zdm.ZA : Ljava/lang/Object;
    //   619: checkcast java/math/BigInteger
    //   622: invokevirtual intValue : ()I
    //   625: bipush #32
    //   627: irem
    //   628: invokestatic abs : (I)I
    //   631: invokevirtual charAt : (I)C
    //   634: invokevirtual append : (C)Ljava/lang/StringBuilder;
    //   637: pop
    //   638: iload_2
    //   639: ifeq -> 1348
    //   642: goto -> 649
    //   645: invokestatic a : (Ljava/lang/Throwable;)Ljava/lang/Throwable;
    //   648: athrow
    //   649: aload_3
    //   650: getstatic burp/Ztap.Zk : Ljava/lang/String;
    //   653: getstatic burp/Zx4k.ZE : Ljava/lang/Object;
    //   656: checkcast java/math/BigInteger
    //   659: invokevirtual intValue : ()I
    //   662: bipush #32
    //   664: irem
    //   665: invokestatic abs : (I)I
    //   668: invokevirtual charAt : (I)C
    //   671: invokevirtual append : (C)Ljava/lang/StringBuilder;
    //   674: pop
    //   675: iload_2
    //   676: ifeq -> 1348
    //   679: goto -> 686
    //   682: invokestatic a : (Ljava/lang/Throwable;)Ljava/lang/Throwable;
    //   685: athrow
    //   686: aload_3
    //   687: getstatic burp/Zlxm.Zv : Ljava/lang/String;
    //   690: getstatic burp/Zbqo.Zb : Ljava/lang/Object;
    //   693: checkcast java/math/BigInteger
    //   696: invokevirtual intValue : ()I
    //   699: bipush #32
    //   701: irem
    //   702: invokestatic abs : (I)I
    //   705: invokevirtual charAt : (I)C
    //   708: invokevirtual append : (C)Ljava/lang/StringBuilder;
    //   711: pop
    //   712: iload_2
    //   713: ifeq -> 1348
    //   716: goto -> 723
    //   719: invokestatic a : (Ljava/lang/Throwable;)Ljava/lang/Throwable;
    //   722: athrow
    //   723: aload_3
    //   724: getstatic burp/Zkaw.ZI : Ljava/lang/String;
    //   727: getstatic burp/Zz9v.Zl : Ljava/lang/Object;
    //   730: checkcast java/math/BigInteger
    //   733: invokevirtual intValue : ()I
    //   736: bipush #32
    //   738: irem
    //   739: invokestatic abs : (I)I
    //   742: invokevirtual charAt : (I)C
    //   745: invokevirtual append : (C)Ljava/lang/StringBuilder;
    //   748: pop
    //   749: iload_2
    //   750: ifeq -> 1348
    //   753: goto -> 760
    //   756: invokestatic a : (Ljava/lang/Throwable;)Ljava/lang/Throwable;
    //   759: athrow
    //   760: aload_3
    //   761: getstatic burp/Zz5s.ZL : Ljava/lang/String;
    //   764: getstatic burp/Ztod.ZP : Ljava/lang/Object;
    //   767: checkcast java/math/BigInteger
    //   770: invokevirtual intValue : ()I
    //   773: bipush #32
    //   775: irem
    //   776: invokestatic abs : (I)I
    //   779: invokevirtual charAt : (I)C
    //   782: invokevirtual append : (C)Ljava/lang/StringBuilder;
    //   785: pop
    //   786: iload_2
    //   787: ifeq -> 1348
    //   790: goto -> 797
    //   793: invokestatic a : (Ljava/lang/Throwable;)Ljava/lang/Throwable;
    //   796: athrow
    //   797: aload_3
    //   798: getstatic burp/Zkcd.Zj : Ljava/lang/String;
    //   801: getstatic burp/Zexu.ZI : Ljava/lang/Object;
    //   804: checkcast java/math/BigInteger
    //   807: invokevirtual intValue : ()I
    //   810: bipush #32
    //   812: irem
    //   813: invokestatic abs : (I)I
    //   816: invokevirtual charAt : (I)C
    //   819: invokevirtual append : (C)Ljava/lang/StringBuilder;
    //   822: pop
    //   823: iload_2
    //   824: ifeq -> 1348
    //   827: goto -> 834
    //   830: invokestatic a : (Ljava/lang/Throwable;)Ljava/lang/Throwable;
    //   833: athrow
    //   834: aload_3
    //   835: getstatic burp/Ztod.Zj : Ljava/lang/String;
    //   838: getstatic burp/Zb_c.ZN : Ljava/lang/Object;
    //   841: checkcast java/math/BigInteger
    //   844: invokevirtual intValue : ()I
    //   847: bipush #32
    //   849: irem
    //   850: invokestatic abs : (I)I
    //   853: invokevirtual charAt : (I)C
    //   856: invokevirtual append : (C)Ljava/lang/StringBuilder;
    //   859: pop
    //   860: iload_2
    //   861: ifeq -> 1348
    //   864: goto -> 871
    //   867: invokestatic a : (Ljava/lang/Throwable;)Ljava/lang/Throwable;
    //   870: athrow
    //   871: aload_3
    //   872: getstatic burp/Zrkc.ZE : Ljava/lang/String;
    //   875: getstatic burp/Zgkp.Zp : Ljava/lang/Object;
    //   878: checkcast java/math/BigInteger
    //   881: invokevirtual intValue : ()I
    //   884: bipush #32
    //   886: irem
    //   887: invokestatic abs : (I)I
    //   890: invokevirtual charAt : (I)C
    //   893: invokevirtual append : (C)Ljava/lang/StringBuilder;
    //   896: pop
    //   897: iload_2
    //   898: ifeq -> 1348
    //   901: goto -> 908
    //   904: invokestatic a : (Ljava/lang/Throwable;)Ljava/lang/Throwable;
    //   907: athrow
    //   908: aload_3
    //   909: getstatic burp/Zry7.Z_ : Ljava/lang/String;
    //   912: getstatic burp/Zr0.ZX : Ljava/lang/Object;
    //   915: checkcast java/math/BigInteger
    //   918: invokevirtual intValue : ()I
    //   921: bipush #32
    //   923: irem
    //   924: invokestatic abs : (I)I
    //   927: invokevirtual charAt : (I)C
    //   930: invokevirtual append : (C)Ljava/lang/StringBuilder;
    //   933: pop
    //   934: iload_2
    //   935: ifeq -> 1348
    //   938: goto -> 945
    //   941: invokestatic a : (Ljava/lang/Throwable;)Ljava/lang/Throwable;
    //   944: athrow
    //   945: aload_3
    //   946: getstatic burp/Zb29.Zf : Ljava/lang/String;
    //   949: getstatic burp/Zl5b.ZI : Ljava/lang/Object;
    //   952: checkcast java/math/BigInteger
    //   955: invokevirtual intValue : ()I
    //   958: bipush #32
    //   960: irem
    //   961: invokestatic abs : (I)I
    //   964: invokevirtual charAt : (I)C
    //   967: invokevirtual append : (C)Ljava/lang/StringBuilder;
    //   970: pop
    //   971: iload_2
    //   972: ifeq -> 1348
    //   975: goto -> 982
    //   978: invokestatic a : (Ljava/lang/Throwable;)Ljava/lang/Throwable;
    //   981: athrow
    //   982: aload_3
    //   983: getstatic burp/Zeud.Za : Ljava/lang/String;
    //   986: getstatic burp/Zgvl.ZK : Ljava/lang/Object;
    //   989: checkcast java/math/BigInteger
    //   992: invokevirtual intValue : ()I
    //   995: bipush #32
    //   997: irem
    //   998: invokestatic abs : (I)I
    //   1001: invokevirtual charAt : (I)C
    //   1004: invokevirtual append : (C)Ljava/lang/StringBuilder;
    //   1007: pop
    //   1008: iload_2
    //   1009: ifeq -> 1348
    //   1012: goto -> 1019
    //   1015: invokestatic a : (Ljava/lang/Throwable;)Ljava/lang/Throwable;
    //   1018: athrow
    //   1019: aload_3
    //   1020: getstatic burp/Zxjw.Zv : Ljava/lang/String;
    //   1023: getstatic burp/Zb29.ZM : Ljava/lang/Object;
    //   1026: checkcast java/math/BigInteger
    //   1029: invokevirtual intValue : ()I
    //   1032: bipush #32
    //   1034: irem
    //   1035: invokestatic abs : (I)I
    //   1038: invokevirtual charAt : (I)C
    //   1041: invokevirtual append : (C)Ljava/lang/StringBuilder;
    //   1044: pop
    //   1045: iload_2
    //   1046: ifeq -> 1348
    //   1049: goto -> 1056
    //   1052: invokestatic a : (Ljava/lang/Throwable;)Ljava/lang/Throwable;
    //   1055: athrow
    //   1056: aload_3
    //   1057: getstatic burp/Zm84.Zd : Ljava/lang/String;
    //   1060: getstatic burp/Zl3n.Zh : Ljava/lang/Object;
    //   1063: checkcast java/math/BigInteger
    //   1066: invokevirtual intValue : ()I
    //   1069: bipush #32
    //   1071: irem
    //   1072: invokestatic abs : (I)I
    //   1075: invokevirtual charAt : (I)C
    //   1078: invokevirtual append : (C)Ljava/lang/StringBuilder;
    //   1081: pop
    //   1082: iload_2
    //   1083: ifeq -> 1348
    //   1086: goto -> 1093
    //   1089: invokestatic a : (Ljava/lang/Throwable;)Ljava/lang/Throwable;
    //   1092: athrow
    //   1093: aload_3
    //   1094: getstatic burp/Zlp7.ZO : Ljava/lang/String;
    //   1097: getstatic burp/Zkcd.ZE : Ljava/lang/Object;
    //   1100: checkcast java/math/BigInteger
    //   1103: invokevirtual intValue : ()I
    //   1106: bipush #32
    //   1108: irem
    //   1109: invokestatic abs : (I)I
    //   1112: invokevirtual charAt : (I)C
    //   1115: invokevirtual append : (C)Ljava/lang/StringBuilder;
    //   1118: pop
    //   1119: iload_2
    //   1120: ifeq -> 1348
    //   1123: goto -> 1130
    //   1126: invokestatic a : (Ljava/lang/Throwable;)Ljava/lang/Throwable;
    //   1129: athrow
    //   1130: aload_3
    //   1131: getstatic burp/Zr0.ZH : Ljava/lang/String;
    //   1134: getstatic burp/Ze0w.ZU : Ljava/lang/Object;
    //   1137: checkcast java/math/BigInteger
    //   1140: invokevirtual intValue : ()I
    //   1143: bipush #32
    //   1145: irem
    //   1146: invokestatic abs : (I)I
    //   1149: invokevirtual charAt : (I)C
    //   1152: invokevirtual append : (C)Ljava/lang/StringBuilder;
    //   1155: pop
    //   1156: iload_2
    //   1157: ifeq -> 1348
    //   1160: goto -> 1167
    //   1163: invokestatic a : (Ljava/lang/Throwable;)Ljava/lang/Throwable;
    //   1166: athrow
    //   1167: aload_3
    //   1168: getstatic burp/Zexu.Zp : Ljava/lang/String;
    //   1171: getstatic burp/Zrd0.Zs : Ljava/lang/Object;
    //   1174: checkcast java/math/BigInteger
    //   1177: invokevirtual intValue : ()I
    //   1180: bipush #32
    //   1182: irem
    //   1183: invokestatic abs : (I)I
    //   1186: invokevirtual charAt : (I)C
    //   1189: invokevirtual append : (C)Ljava/lang/StringBuilder;
    //   1192: pop
    //   1193: iload_2
    //   1194: ifeq -> 1348
    //   1197: goto -> 1204
    //   1200: invokestatic a : (Ljava/lang/Throwable;)Ljava/lang/Throwable;
    //   1203: athrow
    //   1204: aload_3
    //   1205: getstatic burp/Zttq.ZO : Ljava/lang/String;
    //   1208: getstatic burp/Zsk2.ZD : Ljava/lang/Object;
    //   1211: checkcast java/math/BigInteger
    //   1214: invokevirtual intValue : ()I
    //   1217: bipush #32
    //   1219: irem
    //   1220: invokestatic abs : (I)I
    //   1223: invokevirtual charAt : (I)C
    //   1226: invokevirtual append : (C)Ljava/lang/StringBuilder;
    //   1229: pop
    //   1230: iload_2
    //   1231: ifeq -> 1348
    //   1234: goto -> 1241
    //   1237: invokestatic a : (Ljava/lang/Throwable;)Ljava/lang/Throwable;
    //   1240: athrow
    //   1241: aload_3
    //   1242: getstatic burp/Zldx.Zm : Ljava/lang/String;
    //   1245: getstatic burp/Zlhz.Zy : Ljava/lang/Object;
    //   1248: checkcast java/math/BigInteger
    //   1251: invokevirtual intValue : ()I
    //   1254: bipush #32
    //   1256: irem
    //   1257: invokestatic abs : (I)I
    //   1260: invokevirtual charAt : (I)C
    //   1263: invokevirtual append : (C)Ljava/lang/StringBuilder;
    //   1266: pop
    //   1267: iload_2
    //   1268: ifeq -> 1348
    //   1271: goto -> 1278
    //   1274: invokestatic a : (Ljava/lang/Throwable;)Ljava/lang/Throwable;
    //   1277: athrow
    //   1278: aload_3
    //   1279: getstatic burp/Zkcd.Zj : Ljava/lang/String;
    //   1282: getstatic burp/Zlpl.Ze : Ljava/lang/Object;
    //   1285: checkcast java/math/BigInteger
    //   1288: invokevirtual intValue : ()I
    //   1291: bipush #32
    //   1293: irem
    //   1294: invokestatic abs : (I)I
    //   1297: invokevirtual charAt : (I)C
    //   1300: invokevirtual append : (C)Ljava/lang/StringBuilder;
    //   1303: pop
    //   1304: iload_2
    //   1305: ifeq -> 1348
    //   1308: goto -> 1315
    //   1311: invokestatic a : (Ljava/lang/Throwable;)Ljava/lang/Throwable;
    //   1314: athrow
    //   1315: aload_3
    //   1316: getstatic burp/Zexu.Zp : Ljava/lang/String;
    //   1319: getstatic burp/Zrkc.ZI : Ljava/lang/Object;
    //   1322: checkcast java/math/BigInteger
    //   1325: invokevirtual intValue : ()I
    //   1328: bipush #32
    //   1330: irem
    //   1331: invokestatic abs : (I)I
    //   1334: invokevirtual charAt : (I)C
    //   1337: invokevirtual append : (C)Ljava/lang/StringBuilder;
    //   1340: pop
    //   1341: goto -> 1348
    //   1344: invokestatic a : (Ljava/lang/Throwable;)Ljava/lang/Throwable;
    //   1347: athrow
    //   1348: iinc #4, 1
    //   1351: iload_2
    //   1352: ifeq -> 15
    //   1355: aload_3
    //   1356: invokevirtual toString : ()Ljava/lang/String;
    //   1359: putstatic burp/Zbqo.ZS : Ljava/lang/String;
    //   1362: getstatic burp/Zgyk.ZO : Ljava/lang/Object;
    //   1365: checkcast java/math/BigInteger
    //   1368: invokevirtual toByteArray : ()[B
    //   1371: astore #4
    //   1373: bipush #32
    //   1375: newarray int
    //   1377: dup
    //   1378: iconst_0
    //   1379: ldc 943331329
    //   1381: iastore
    //   1382: dup
    //   1383: iconst_1
    //   1384: ldc 170788368
    //   1386: iastore
    //   1387: dup
    //   1388: iconst_2
    //   1389: ldc 1008414755
    //   1391: iastore
    //   1392: dup
    //   1393: iconst_3
    //   1394: ldc 187049985
    //   1396: iastore
    //   1397: dup
    //   1398: iconst_4
    //   1399: ldc 1010368540
    //   1401: iastore
    //   1402: dup
    //   1403: iconst_5
    //   1404: ldc 220604441
    //   1406: iastore
    //   1407: dup
    //   1408: bipush #6
    //   1410: ldc 940377620
    //   1412: iastore
    //   1413: dup
    //   1414: bipush #7
    //   1416: ldc 255209728
    //   1418: iastore
    //   1419: dup
    //   1420: bipush #8
    //   1422: ldc 689771012
    //   1424: iastore
    //   1425: dup
    //   1426: bipush #9
    //   1428: ldc 221709344
    //   1430: iastore
    //   1431: dup
    //   1432: bipush #10
    //   1434: ldc 957157408
    //   1436: iastore
    //   1437: dup
    //   1438: bipush #11
    //   1440: ldc 892536332
    //   1442: iastore
    //   1443: dup
    //   1444: bipush #12
    //   1446: ldc 722417666
    //   1448: iastore
    //   1449: dup
    //   1450: bipush #13
    //   1452: ldc 1026621720
    //   1454: iastore
    //   1455: dup
    //   1456: bipush #14
    //   1458: ldc 655302664
    //   1460: iastore
    //   1461: dup
    //   1462: bipush #15
    //   1464: ldc 890966315
    //   1466: iastore
    //   1467: dup
    //   1468: bipush #16
    //   1470: ldc 187632156
    //   1472: iastore
    //   1473: dup
    //   1474: bipush #17
    //   1476: ldc 874189824
    //   1478: iastore
    //   1479: dup
    //   1480: bipush #18
    //   1482: ldc 254150144
    //   1484: iastore
    //   1485: dup
    //   1486: bipush #19
    //   1488: ldc 924386310
    //   1490: iastore
    //   1491: dup
    //   1492: bipush #20
    //   1494: ldc 121057538
    //   1496: iastore
    //   1497: dup
    //   1498: bipush #21
    //   1500: ldc 840500228
    //   1502: iastore
    //   1503: dup
    //   1504: bipush #22
    //   1506: ldc 389160971
    //   1508: iastore
    //   1509: dup
    //   1510: bipush #23
    //   1512: ldc 907870729
    //   1514: iastore
    //   1515: dup
    //   1516: bipush #24
    //   1518: ldc 389426184
    //   1520: iastore
    //   1521: dup
    //   1522: bipush #25
    //   1524: ldc 973875457
    //   1526: iastore
    //   1527: dup
    //   1528: bipush #26
    //   1530: ldc 372376604
    //   1532: iastore
    //   1533: dup
    //   1534: bipush #27
    //   1536: ldc 707731490
    //   1538: iastore
    //   1539: dup
    //   1540: bipush #28
    //   1542: ldc 1043334948
    //   1544: iastore
    //   1545: dup
    //   1546: bipush #29
    //   1548: ldc 439222784
    //   1550: iastore
    //   1551: dup
    //   1552: bipush #30
    //   1554: ldc 876216579
    //   1556: iastore
    //   1557: dup
    //   1558: bipush #31
    //   1560: ldc 455999525
    //   1562: iastore
    //   1563: astore #6
    //   1565: bipush #8
    //   1567: aload #4
    //   1569: arraylength
    //   1570: bipush #8
    //   1572: irem
    //   1573: isub
    //   1574: istore #7
    //   1576: aload #4
    //   1578: arraylength
    //   1579: iload #7
    //   1581: iadd
    //   1582: newarray byte
    //   1584: astore #8
    //   1586: iconst_0
    //   1587: istore #9
    //   1589: iload #9
    //   1591: aload #4
    //   1593: arraylength
    //   1594: if_icmpge -> 1614
    //   1597: aload #8
    //   1599: iload #9
    //   1601: aload #4
    //   1603: iload #9
    //   1605: baload
    //   1606: bastore
    //   1607: iinc #9, 1
    //   1610: iload_2
    //   1611: ifeq -> 1589
    //   1614: aload #4
    //   1616: arraylength
    //   1617: istore #9
    //   1619: iload #9
    //   1621: aload #8
    //   1623: arraylength
    //   1624: if_icmpge -> 1642
    //   1627: aload #8
    //   1629: iload #9
    //   1631: iload #7
    //   1633: i2b
    //   1634: bastore
    //   1635: iinc #9, 1
    //   1638: iload_2
    //   1639: ifeq -> 1619
    //   1642: aload #8
    //   1644: astore #4
    //   1646: bipush #64
    //   1648: newarray int
    //   1650: dup
    //   1651: iconst_0
    //   1652: ldc 16843776
    //   1654: iastore
    //   1655: dup
    //   1656: iconst_1
    //   1657: iconst_0
    //   1658: iastore
    //   1659: dup
    //   1660: iconst_2
    //   1661: ldc 65536
    //   1663: iastore
    //   1664: dup
    //   1665: iconst_3
    //   1666: ldc 16843780
    //   1668: iastore
    //   1669: dup
    //   1670: iconst_4
    //   1671: ldc 16842756
    //   1673: iastore
    //   1674: dup
    //   1675: iconst_5
    //   1676: ldc 66564
    //   1678: iastore
    //   1679: dup
    //   1680: bipush #6
    //   1682: iconst_4
    //   1683: iastore
    //   1684: dup
    //   1685: bipush #7
    //   1687: ldc 65536
    //   1689: iastore
    //   1690: dup
    //   1691: bipush #8
    //   1693: sipush #1024
    //   1696: iastore
    //   1697: dup
    //   1698: bipush #9
    //   1700: ldc 16843776
    //   1702: iastore
    //   1703: dup
    //   1704: bipush #10
    //   1706: ldc 16843780
    //   1708: iastore
    //   1709: dup
    //   1710: bipush #11
    //   1712: sipush #1024
    //   1715: iastore
    //   1716: dup
    //   1717: bipush #12
    //   1719: ldc 16778244
    //   1721: iastore
    //   1722: dup
    //   1723: bipush #13
    //   1725: ldc 16842756
    //   1727: iastore
    //   1728: dup
    //   1729: bipush #14
    //   1731: ldc 16777216
    //   1733: iastore
    //   1734: dup
    //   1735: bipush #15
    //   1737: iconst_4
    //   1738: iastore
    //   1739: dup
    //   1740: bipush #16
    //   1742: sipush #1028
    //   1745: iastore
    //   1746: dup
    //   1747: bipush #17
    //   1749: ldc 16778240
    //   1751: iastore
    //   1752: dup
    //   1753: bipush #18
    //   1755: ldc 16778240
    //   1757: iastore
    //   1758: dup
    //   1759: bipush #19
    //   1761: ldc 66560
    //   1763: iastore
    //   1764: dup
    //   1765: bipush #20
    //   1767: ldc 66560
    //   1769: iastore
    //   1770: dup
    //   1771: bipush #21
    //   1773: ldc 16842752
    //   1775: iastore
    //   1776: dup
    //   1777: bipush #22
    //   1779: ldc 16842752
    //   1781: iastore
    //   1782: dup
    //   1783: bipush #23
    //   1785: ldc 16778244
    //   1787: iastore
    //   1788: dup
    //   1789: bipush #24
    //   1791: ldc 65540
    //   1793: iastore
    //   1794: dup
    //   1795: bipush #25
    //   1797: ldc 16777220
    //   1799: iastore
    //   1800: dup
    //   1801: bipush #26
    //   1803: ldc 16777220
    //   1805: iastore
    //   1806: dup
    //   1807: bipush #27
    //   1809: ldc 65540
    //   1811: iastore
    //   1812: dup
    //   1813: bipush #28
    //   1815: iconst_0
    //   1816: iastore
    //   1817: dup
    //   1818: bipush #29
    //   1820: sipush #1028
    //   1823: iastore
    //   1824: dup
    //   1825: bipush #30
    //   1827: ldc 66564
    //   1829: iastore
    //   1830: dup
    //   1831: bipush #31
    //   1833: ldc 16777216
    //   1835: iastore
    //   1836: dup
    //   1837: bipush #32
    //   1839: ldc 65536
    //   1841: iastore
    //   1842: dup
    //   1843: bipush #33
    //   1845: ldc 16843780
    //   1847: iastore
    //   1848: dup
    //   1849: bipush #34
    //   1851: iconst_4
    //   1852: iastore
    //   1853: dup
    //   1854: bipush #35
    //   1856: ldc 16842752
    //   1858: iastore
    //   1859: dup
    //   1860: bipush #36
    //   1862: ldc 16843776
    //   1864: iastore
    //   1865: dup
    //   1866: bipush #37
    //   1868: ldc 16777216
    //   1870: iastore
    //   1871: dup
    //   1872: bipush #38
    //   1874: ldc 16777216
    //   1876: iastore
    //   1877: dup
    //   1878: bipush #39
    //   1880: sipush #1024
    //   1883: iastore
    //   1884: dup
    //   1885: bipush #40
    //   1887: ldc 16842756
    //   1889: iastore
    //   1890: dup
    //   1891: bipush #41
    //   1893: ldc 65536
    //   1895: iastore
    //   1896: dup
    //   1897: bipush #42
    //   1899: ldc 66560
    //   1901: iastore
    //   1902: dup
    //   1903: bipush #43
    //   1905: ldc 16777220
    //   1907: iastore
    //   1908: dup
    //   1909: bipush #44
    //   1911: sipush #1024
    //   1914: iastore
    //   1915: dup
    //   1916: bipush #45
    //   1918: iconst_4
    //   1919: iastore
    //   1920: dup
    //   1921: bipush #46
    //   1923: ldc 16778244
    //   1925: iastore
    //   1926: dup
    //   1927: bipush #47
    //   1929: ldc 66564
    //   1931: iastore
    //   1932: dup
    //   1933: bipush #48
    //   1935: ldc 16843780
    //   1937: iastore
    //   1938: dup
    //   1939: bipush #49
    //   1941: ldc 65540
    //   1943: iastore
    //   1944: dup
    //   1945: bipush #50
    //   1947: ldc 16842752
    //   1949: iastore
    //   1950: dup
    //   1951: bipush #51
    //   1953: ldc 16778244
    //   1955: iastore
    //   1956: dup
    //   1957: bipush #52
    //   1959: ldc 16777220
    //   1961: iastore
    //   1962: dup
    //   1963: bipush #53
    //   1965: sipush #1028
    //   1968: iastore
    //   1969: dup
    //   1970: bipush #54
    //   1972: ldc 66564
    //   1974: iastore
    //   1975: dup
    //   1976: bipush #55
    //   1978: ldc 16843776
    //   1980: iastore
    //   1981: dup
    //   1982: bipush #56
    //   1984: sipush #1028
    //   1987: iastore
    //   1988: dup
    //   1989: bipush #57
    //   1991: ldc 16778240
    //   1993: iastore
    //   1994: dup
    //   1995: bipush #58
    //   1997: ldc 16778240
    //   1999: iastore
    //   2000: dup
    //   2001: bipush #59
    //   2003: iconst_0
    //   2004: iastore
    //   2005: dup
    //   2006: bipush #60
    //   2008: ldc 65540
    //   2010: iastore
    //   2011: dup
    //   2012: bipush #61
    //   2014: ldc 66560
    //   2016: iastore
    //   2017: dup
    //   2018: bipush #62
    //   2020: iconst_0
    //   2021: iastore
    //   2022: dup
    //   2023: bipush #63
    //   2025: ldc 16842756
    //   2027: iastore
    //   2028: astore #9
    //   2030: bipush #64
    //   2032: newarray int
    //   2034: dup
    //   2035: iconst_0
    //   2036: ldc -2146402272
    //   2038: iastore
    //   2039: dup
    //   2040: iconst_1
    //   2041: ldc -2147450880
    //   2043: iastore
    //   2044: dup
    //   2045: iconst_2
    //   2046: ldc 32768
    //   2048: iastore
    //   2049: dup
    //   2050: iconst_3
    //   2051: ldc 1081376
    //   2053: iastore
    //   2054: dup
    //   2055: iconst_4
    //   2056: ldc 1048576
    //   2058: iastore
    //   2059: dup
    //   2060: iconst_5
    //   2061: bipush #32
    //   2063: iastore
    //   2064: dup
    //   2065: bipush #6
    //   2067: ldc -2146435040
    //   2069: iastore
    //   2070: dup
    //   2071: bipush #7
    //   2073: ldc -2147450848
    //   2075: iastore
    //   2076: dup
    //   2077: bipush #8
    //   2079: ldc -2147483616
    //   2081: iastore
    //   2082: dup
    //   2083: bipush #9
    //   2085: ldc -2146402272
    //   2087: iastore
    //   2088: dup
    //   2089: bipush #10
    //   2091: ldc -2146402304
    //   2093: iastore
    //   2094: dup
    //   2095: bipush #11
    //   2097: ldc -2147483648
    //   2099: iastore
    //   2100: dup
    //   2101: bipush #12
    //   2103: ldc -2147450880
    //   2105: iastore
    //   2106: dup
    //   2107: bipush #13
    //   2109: ldc 1048576
    //   2111: iastore
    //   2112: dup
    //   2113: bipush #14
    //   2115: bipush #32
    //   2117: iastore
    //   2118: dup
    //   2119: bipush #15
    //   2121: ldc -2146435040
    //   2123: iastore
    //   2124: dup
    //   2125: bipush #16
    //   2127: ldc 1081344
    //   2129: iastore
    //   2130: dup
    //   2131: bipush #17
    //   2133: ldc 1048608
    //   2135: iastore
    //   2136: dup
    //   2137: bipush #18
    //   2139: ldc -2147450848
    //   2141: iastore
    //   2142: dup
    //   2143: bipush #19
    //   2145: iconst_0
    //   2146: iastore
    //   2147: dup
    //   2148: bipush #20
    //   2150: ldc -2147483648
    //   2152: iastore
    //   2153: dup
    //   2154: bipush #21
    //   2156: ldc 32768
    //   2158: iastore
    //   2159: dup
    //   2160: bipush #22
    //   2162: ldc 1081376
    //   2164: iastore
    //   2165: dup
    //   2166: bipush #23
    //   2168: ldc -2146435072
    //   2170: iastore
    //   2171: dup
    //   2172: bipush #24
    //   2174: ldc 1048608
    //   2176: iastore
    //   2177: dup
    //   2178: bipush #25
    //   2180: ldc -2147483616
    //   2182: iastore
    //   2183: dup
    //   2184: bipush #26
    //   2186: iconst_0
    //   2187: iastore
    //   2188: dup
    //   2189: bipush #27
    //   2191: ldc 1081344
    //   2193: iastore
    //   2194: dup
    //   2195: bipush #28
    //   2197: ldc 32800
    //   2199: iastore
    //   2200: dup
    //   2201: bipush #29
    //   2203: ldc -2146402304
    //   2205: iastore
    //   2206: dup
    //   2207: bipush #30
    //   2209: ldc -2146435072
    //   2211: iastore
    //   2212: dup
    //   2213: bipush #31
    //   2215: ldc 32800
    //   2217: iastore
    //   2218: dup
    //   2219: bipush #32
    //   2221: iconst_0
    //   2222: iastore
    //   2223: dup
    //   2224: bipush #33
    //   2226: ldc 1081376
    //   2228: iastore
    //   2229: dup
    //   2230: bipush #34
    //   2232: ldc -2146435040
    //   2234: iastore
    //   2235: dup
    //   2236: bipush #35
    //   2238: ldc 1048576
    //   2240: iastore
    //   2241: dup
    //   2242: bipush #36
    //   2244: ldc -2147450848
    //   2246: iastore
    //   2247: dup
    //   2248: bipush #37
    //   2250: ldc -2146435072
    //   2252: iastore
    //   2253: dup
    //   2254: bipush #38
    //   2256: ldc -2146402304
    //   2258: iastore
    //   2259: dup
    //   2260: bipush #39
    //   2262: ldc 32768
    //   2264: iastore
    //   2265: dup
    //   2266: bipush #40
    //   2268: ldc -2146435072
    //   2270: iastore
    //   2271: dup
    //   2272: bipush #41
    //   2274: ldc -2147450880
    //   2276: iastore
    //   2277: dup
    //   2278: bipush #42
    //   2280: bipush #32
    //   2282: iastore
    //   2283: dup
    //   2284: bipush #43
    //   2286: ldc -2146402272
    //   2288: iastore
    //   2289: dup
    //   2290: bipush #44
    //   2292: ldc 1081376
    //   2294: iastore
    //   2295: dup
    //   2296: bipush #45
    //   2298: bipush #32
    //   2300: iastore
    //   2301: dup
    //   2302: bipush #46
    //   2304: ldc 32768
    //   2306: iastore
    //   2307: dup
    //   2308: bipush #47
    //   2310: ldc -2147483648
    //   2312: iastore
    //   2313: dup
    //   2314: bipush #48
    //   2316: ldc 32800
    //   2318: iastore
    //   2319: dup
    //   2320: bipush #49
    //   2322: ldc -2146402304
    //   2324: iastore
    //   2325: dup
    //   2326: bipush #50
    //   2328: ldc 1048576
    //   2330: iastore
    //   2331: dup
    //   2332: bipush #51
    //   2334: ldc -2147483616
    //   2336: iastore
    //   2337: dup
    //   2338: bipush #52
    //   2340: ldc 1048608
    //   2342: iastore
    //   2343: dup
    //   2344: bipush #53
    //   2346: ldc -2147450848
    //   2348: iastore
    //   2349: dup
    //   2350: bipush #54
    //   2352: ldc -2147483616
    //   2354: iastore
    //   2355: dup
    //   2356: bipush #55
    //   2358: ldc 1048608
    //   2360: iastore
    //   2361: dup
    //   2362: bipush #56
    //   2364: ldc 1081344
    //   2366: iastore
    //   2367: dup
    //   2368: bipush #57
    //   2370: iconst_0
    //   2371: iastore
    //   2372: dup
    //   2373: bipush #58
    //   2375: ldc -2147450880
    //   2377: iastore
    //   2378: dup
    //   2379: bipush #59
    //   2381: ldc 32800
    //   2383: iastore
    //   2384: dup
    //   2385: bipush #60
    //   2387: ldc -2147483648
    //   2389: iastore
    //   2390: dup
    //   2391: bipush #61
    //   2393: ldc -2146435040
    //   2395: iastore
    //   2396: dup
    //   2397: bipush #62
    //   2399: ldc -2146402272
    //   2401: iastore
    //   2402: dup
    //   2403: bipush #63
    //   2405: ldc 1081344
    //   2407: iastore
    //   2408: astore #10
    //   2410: bipush #64
    //   2412: newarray int
    //   2414: dup
    //   2415: iconst_0
    //   2416: sipush #520
    //   2419: iastore
    //   2420: dup
    //   2421: iconst_1
    //   2422: ldc 134349312
    //   2424: iastore
    //   2425: dup
    //   2426: iconst_2
    //   2427: iconst_0
    //   2428: iastore
    //   2429: dup
    //   2430: iconst_3
    //   2431: ldc 134348808
    //   2433: iastore
    //   2434: dup
    //   2435: iconst_4
    //   2436: ldc 134218240
    //   2438: iastore
    //   2439: dup
    //   2440: iconst_5
    //   2441: iconst_0
    //   2442: iastore
    //   2443: dup
    //   2444: bipush #6
    //   2446: ldc 131592
    //   2448: iastore
    //   2449: dup
    //   2450: bipush #7
    //   2452: ldc 134218240
    //   2454: iastore
    //   2455: dup
    //   2456: bipush #8
    //   2458: ldc 131080
    //   2460: iastore
    //   2461: dup
    //   2462: bipush #9
    //   2464: ldc 134217736
    //   2466: iastore
    //   2467: dup
    //   2468: bipush #10
    //   2470: ldc 134217736
    //   2472: iastore
    //   2473: dup
    //   2474: bipush #11
    //   2476: ldc 131072
    //   2478: iastore
    //   2479: dup
    //   2480: bipush #12
    //   2482: ldc 134349320
    //   2484: iastore
    //   2485: dup
    //   2486: bipush #13
    //   2488: ldc 131080
    //   2490: iastore
    //   2491: dup
    //   2492: bipush #14
    //   2494: ldc 134348800
    //   2496: iastore
    //   2497: dup
    //   2498: bipush #15
    //   2500: sipush #520
    //   2503: iastore
    //   2504: dup
    //   2505: bipush #16
    //   2507: ldc 134217728
    //   2509: iastore
    //   2510: dup
    //   2511: bipush #17
    //   2513: bipush #8
    //   2515: iastore
    //   2516: dup
    //   2517: bipush #18
    //   2519: ldc 134349312
    //   2521: iastore
    //   2522: dup
    //   2523: bipush #19
    //   2525: sipush #512
    //   2528: iastore
    //   2529: dup
    //   2530: bipush #20
    //   2532: ldc 131584
    //   2534: iastore
    //   2535: dup
    //   2536: bipush #21
    //   2538: ldc 134348800
    //   2540: iastore
    //   2541: dup
    //   2542: bipush #22
    //   2544: ldc 134348808
    //   2546: iastore
    //   2547: dup
    //   2548: bipush #23
    //   2550: ldc 131592
    //   2552: iastore
    //   2553: dup
    //   2554: bipush #24
    //   2556: ldc 134218248
    //   2558: iastore
    //   2559: dup
    //   2560: bipush #25
    //   2562: ldc 131584
    //   2564: iastore
    //   2565: dup
    //   2566: bipush #26
    //   2568: ldc 131072
    //   2570: iastore
    //   2571: dup
    //   2572: bipush #27
    //   2574: ldc 134218248
    //   2576: iastore
    //   2577: dup
    //   2578: bipush #28
    //   2580: bipush #8
    //   2582: iastore
    //   2583: dup
    //   2584: bipush #29
    //   2586: ldc 134349320
    //   2588: iastore
    //   2589: dup
    //   2590: bipush #30
    //   2592: sipush #512
    //   2595: iastore
    //   2596: dup
    //   2597: bipush #31
    //   2599: ldc 134217728
    //   2601: iastore
    //   2602: dup
    //   2603: bipush #32
    //   2605: ldc 134349312
    //   2607: iastore
    //   2608: dup
    //   2609: bipush #33
    //   2611: ldc 134217728
    //   2613: iastore
    //   2614: dup
    //   2615: bipush #34
    //   2617: ldc 131080
    //   2619: iastore
    //   2620: dup
    //   2621: bipush #35
    //   2623: sipush #520
    //   2626: iastore
    //   2627: dup
    //   2628: bipush #36
    //   2630: ldc 131072
    //   2632: iastore
    //   2633: dup
    //   2634: bipush #37
    //   2636: ldc 134349312
    //   2638: iastore
    //   2639: dup
    //   2640: bipush #38
    //   2642: ldc 134218240
    //   2644: iastore
    //   2645: dup
    //   2646: bipush #39
    //   2648: iconst_0
    //   2649: iastore
    //   2650: dup
    //   2651: bipush #40
    //   2653: sipush #512
    //   2656: iastore
    //   2657: dup
    //   2658: bipush #41
    //   2660: ldc 131080
    //   2662: iastore
    //   2663: dup
    //   2664: bipush #42
    //   2666: ldc 134349320
    //   2668: iastore
    //   2669: dup
    //   2670: bipush #43
    //   2672: ldc 134218240
    //   2674: iastore
    //   2675: dup
    //   2676: bipush #44
    //   2678: ldc 134217736
    //   2680: iastore
    //   2681: dup
    //   2682: bipush #45
    //   2684: sipush #512
    //   2687: iastore
    //   2688: dup
    //   2689: bipush #46
    //   2691: iconst_0
    //   2692: iastore
    //   2693: dup
    //   2694: bipush #47
    //   2696: ldc 134348808
    //   2698: iastore
    //   2699: dup
    //   2700: bipush #48
    //   2702: ldc 134218248
    //   2704: iastore
    //   2705: dup
    //   2706: bipush #49
    //   2708: ldc 131072
    //   2710: iastore
    //   2711: dup
    //   2712: bipush #50
    //   2714: ldc 134217728
    //   2716: iastore
    //   2717: dup
    //   2718: bipush #51
    //   2720: ldc 134349320
    //   2722: iastore
    //   2723: dup
    //   2724: bipush #52
    //   2726: bipush #8
    //   2728: iastore
    //   2729: dup
    //   2730: bipush #53
    //   2732: ldc 131592
    //   2734: iastore
    //   2735: dup
    //   2736: bipush #54
    //   2738: ldc 131584
    //   2740: iastore
    //   2741: dup
    //   2742: bipush #55
    //   2744: ldc 134217736
    //   2746: iastore
    //   2747: dup
    //   2748: bipush #56
    //   2750: ldc 134348800
    //   2752: iastore
    //   2753: dup
    //   2754: bipush #57
    //   2756: ldc 134218248
    //   2758: iastore
    //   2759: dup
    //   2760: bipush #58
    //   2762: sipush #520
    //   2765: iastore
    //   2766: dup
    //   2767: bipush #59
    //   2769: ldc 134348800
    //   2771: iastore
    //   2772: dup
    //   2773: bipush #60
    //   2775: ldc 131592
    //   2777: iastore
    //   2778: dup
    //   2779: bipush #61
    //   2781: bipush #8
    //   2783: iastore
    //   2784: dup
    //   2785: bipush #62
    //   2787: ldc 134348808
    //   2789: iastore
    //   2790: dup
    //   2791: bipush #63
    //   2793: ldc 131584
    //   2795: iastore
    //   2796: astore #11
    //   2798: bipush #64
    //   2800: newarray int
    //   2802: dup
    //   2803: iconst_0
    //   2804: ldc 8396801
    //   2806: iastore
    //   2807: dup
    //   2808: iconst_1
    //   2809: sipush #8321
    //   2812: iastore
    //   2813: dup
    //   2814: iconst_2
    //   2815: sipush #8321
    //   2818: iastore
    //   2819: dup
    //   2820: iconst_3
    //   2821: sipush #128
    //   2824: iastore
    //   2825: dup
    //   2826: iconst_4
    //   2827: ldc 8396928
    //   2829: iastore
    //   2830: dup
    //   2831: iconst_5
    //   2832: ldc 8388737
    //   2834: iastore
    //   2835: dup
    //   2836: bipush #6
    //   2838: ldc 8388609
    //   2840: iastore
    //   2841: dup
    //   2842: bipush #7
    //   2844: sipush #8193
    //   2847: iastore
    //   2848: dup
    //   2849: bipush #8
    //   2851: iconst_0
    //   2852: iastore
    //   2853: dup
    //   2854: bipush #9
    //   2856: ldc 8396800
    //   2858: iastore
    //   2859: dup
    //   2860: bipush #10
    //   2862: ldc 8396800
    //   2864: iastore
    //   2865: dup
    //   2866: bipush #11
    //   2868: ldc 8396929
    //   2870: iastore
    //   2871: dup
    //   2872: bipush #12
    //   2874: sipush #129
    //   2877: iastore
    //   2878: dup
    //   2879: bipush #13
    //   2881: iconst_0
    //   2882: iastore
    //   2883: dup
    //   2884: bipush #14
    //   2886: ldc 8388736
    //   2888: iastore
    //   2889: dup
    //   2890: bipush #15
    //   2892: ldc 8388609
    //   2894: iastore
    //   2895: dup
    //   2896: bipush #16
    //   2898: iconst_1
    //   2899: iastore
    //   2900: dup
    //   2901: bipush #17
    //   2903: sipush #8192
    //   2906: iastore
    //   2907: dup
    //   2908: bipush #18
    //   2910: ldc 8388608
    //   2912: iastore
    //   2913: dup
    //   2914: bipush #19
    //   2916: ldc 8396801
    //   2918: iastore
    //   2919: dup
    //   2920: bipush #20
    //   2922: sipush #128
    //   2925: iastore
    //   2926: dup
    //   2927: bipush #21
    //   2929: ldc 8388608
    //   2931: iastore
    //   2932: dup
    //   2933: bipush #22
    //   2935: sipush #8193
    //   2938: iastore
    //   2939: dup
    //   2940: bipush #23
    //   2942: sipush #8320
    //   2945: iastore
    //   2946: dup
    //   2947: bipush #24
    //   2949: ldc 8388737
    //   2951: iastore
    //   2952: dup
    //   2953: bipush #25
    //   2955: iconst_1
    //   2956: iastore
    //   2957: dup
    //   2958: bipush #26
    //   2960: sipush #8320
    //   2963: iastore
    //   2964: dup
    //   2965: bipush #27
    //   2967: ldc 8388736
    //   2969: iastore
    //   2970: dup
    //   2971: bipush #28
    //   2973: sipush #8192
    //   2976: iastore
    //   2977: dup
    //   2978: bipush #29
    //   2980: ldc 8396928
    //   2982: iastore
    //   2983: dup
    //   2984: bipush #30
    //   2986: ldc 8396929
    //   2988: iastore
    //   2989: dup
    //   2990: bipush #31
    //   2992: sipush #129
    //   2995: iastore
    //   2996: dup
    //   2997: bipush #32
    //   2999: ldc 8388736
    //   3001: iastore
    //   3002: dup
    //   3003: bipush #33
    //   3005: ldc 8388609
    //   3007: iastore
    //   3008: dup
    //   3009: bipush #34
    //   3011: ldc 8396800
    //   3013: iastore
    //   3014: dup
    //   3015: bipush #35
    //   3017: ldc 8396929
    //   3019: iastore
    //   3020: dup
    //   3021: bipush #36
    //   3023: sipush #129
    //   3026: iastore
    //   3027: dup
    //   3028: bipush #37
    //   3030: iconst_0
    //   3031: iastore
    //   3032: dup
    //   3033: bipush #38
    //   3035: iconst_0
    //   3036: iastore
    //   3037: dup
    //   3038: bipush #39
    //   3040: ldc 8396800
    //   3042: iastore
    //   3043: dup
    //   3044: bipush #40
    //   3046: sipush #8320
    //   3049: iastore
    //   3050: dup
    //   3051: bipush #41
    //   3053: ldc 8388736
    //   3055: iastore
    //   3056: dup
    //   3057: bipush #42
    //   3059: ldc 8388737
    //   3061: iastore
    //   3062: dup
    //   3063: bipush #43
    //   3065: iconst_1
    //   3066: iastore
    //   3067: dup
    //   3068: bipush #44
    //   3070: ldc 8396801
    //   3072: iastore
    //   3073: dup
    //   3074: bipush #45
    //   3076: sipush #8321
    //   3079: iastore
    //   3080: dup
    //   3081: bipush #46
    //   3083: sipush #8321
    //   3086: iastore
    //   3087: dup
    //   3088: bipush #47
    //   3090: sipush #128
    //   3093: iastore
    //   3094: dup
    //   3095: bipush #48
    //   3097: ldc 8396929
    //   3099: iastore
    //   3100: dup
    //   3101: bipush #49
    //   3103: sipush #129
    //   3106: iastore
    //   3107: dup
    //   3108: bipush #50
    //   3110: iconst_1
    //   3111: iastore
    //   3112: dup
    //   3113: bipush #51
    //   3115: sipush #8192
    //   3118: iastore
    //   3119: dup
    //   3120: bipush #52
    //   3122: ldc 8388609
    //   3124: iastore
    //   3125: dup
    //   3126: bipush #53
    //   3128: sipush #8193
    //   3131: iastore
    //   3132: dup
    //   3133: bipush #54
    //   3135: ldc 8396928
    //   3137: iastore
    //   3138: dup
    //   3139: bipush #55
    //   3141: ldc 8388737
    //   3143: iastore
    //   3144: dup
    //   3145: bipush #56
    //   3147: sipush #8193
    //   3150: iastore
    //   3151: dup
    //   3152: bipush #57
    //   3154: sipush #8320
    //   3157: iastore
    //   3158: dup
    //   3159: bipush #58
    //   3161: ldc 8388608
    //   3163: iastore
    //   3164: dup
    //   3165: bipush #59
    //   3167: ldc 8396801
    //   3169: iastore
    //   3170: dup
    //   3171: bipush #60
    //   3173: sipush #128
    //   3176: iastore
    //   3177: dup
    //   3178: bipush #61
    //   3180: ldc 8388608
    //   3182: iastore
    //   3183: dup
    //   3184: bipush #62
    //   3186: sipush #8192
    //   3189: iastore
    //   3190: dup
    //   3191: bipush #63
    //   3193: ldc 8396928
    //   3195: iastore
    //   3196: astore #12
    //   3198: bipush #64
    //   3200: newarray int
    //   3202: dup
    //   3203: iconst_0
    //   3204: sipush #256
    //   3207: iastore
    //   3208: dup
    //   3209: iconst_1
    //   3210: ldc 34078976
    //   3212: iastore
    //   3213: dup
    //   3214: iconst_2
    //   3215: ldc 34078720
    //   3217: iastore
    //   3218: dup
    //   3219: iconst_3
    //   3220: ldc 1107296512
    //   3222: iastore
    //   3223: dup
    //   3224: iconst_4
    //   3225: ldc 524288
    //   3227: iastore
    //   3228: dup
    //   3229: iconst_5
    //   3230: sipush #256
    //   3233: iastore
    //   3234: dup
    //   3235: bipush #6
    //   3237: ldc 1073741824
    //   3239: iastore
    //   3240: dup
    //   3241: bipush #7
    //   3243: ldc 34078720
    //   3245: iastore
    //   3246: dup
    //   3247: bipush #8
    //   3249: ldc 1074266368
    //   3251: iastore
    //   3252: dup
    //   3253: bipush #9
    //   3255: ldc 524288
    //   3257: iastore
    //   3258: dup
    //   3259: bipush #10
    //   3261: ldc 33554688
    //   3263: iastore
    //   3264: dup
    //   3265: bipush #11
    //   3267: ldc 1074266368
    //   3269: iastore
    //   3270: dup
    //   3271: bipush #12
    //   3273: ldc 1107296512
    //   3275: iastore
    //   3276: dup
    //   3277: bipush #13
    //   3279: ldc 1107820544
    //   3281: iastore
    //   3282: dup
    //   3283: bipush #14
    //   3285: ldc 524544
    //   3287: iastore
    //   3288: dup
    //   3289: bipush #15
    //   3291: ldc 1073741824
    //   3293: iastore
    //   3294: dup
    //   3295: bipush #16
    //   3297: ldc 33554432
    //   3299: iastore
    //   3300: dup
    //   3301: bipush #17
    //   3303: ldc 1074266112
    //   3305: iastore
    //   3306: dup
    //   3307: bipush #18
    //   3309: ldc 1074266112
    //   3311: iastore
    //   3312: dup
    //   3313: bipush #19
    //   3315: iconst_0
    //   3316: iastore
    //   3317: dup
    //   3318: bipush #20
    //   3320: ldc 1073742080
    //   3322: iastore
    //   3323: dup
    //   3324: bipush #21
    //   3326: ldc 1107820800
    //   3328: iastore
    //   3329: dup
    //   3330: bipush #22
    //   3332: ldc 1107820800
    //   3334: iastore
    //   3335: dup
    //   3336: bipush #23
    //   3338: ldc 33554688
    //   3340: iastore
    //   3341: dup
    //   3342: bipush #24
    //   3344: ldc 1107820544
    //   3346: iastore
    //   3347: dup
    //   3348: bipush #25
    //   3350: ldc 1073742080
    //   3352: iastore
    //   3353: dup
    //   3354: bipush #26
    //   3356: iconst_0
    //   3357: iastore
    //   3358: dup
    //   3359: bipush #27
    //   3361: ldc 1107296256
    //   3363: iastore
    //   3364: dup
    //   3365: bipush #28
    //   3367: ldc 34078976
    //   3369: iastore
    //   3370: dup
    //   3371: bipush #29
    //   3373: ldc 33554432
    //   3375: iastore
    //   3376: dup
    //   3377: bipush #30
    //   3379: ldc 1107296256
    //   3381: iastore
    //   3382: dup
    //   3383: bipush #31
    //   3385: ldc 524544
    //   3387: iastore
    //   3388: dup
    //   3389: bipush #32
    //   3391: ldc 524288
    //   3393: iastore
    //   3394: dup
    //   3395: bipush #33
    //   3397: ldc 1107296512
    //   3399: iastore
    //   3400: dup
    //   3401: bipush #34
    //   3403: sipush #256
    //   3406: iastore
    //   3407: dup
    //   3408: bipush #35
    //   3410: ldc 33554432
    //   3412: iastore
    //   3413: dup
    //   3414: bipush #36
    //   3416: ldc 1073741824
    //   3418: iastore
    //   3419: dup
    //   3420: bipush #37
    //   3422: ldc 34078720
    //   3424: iastore
    //   3425: dup
    //   3426: bipush #38
    //   3428: ldc 1107296512
    //   3430: iastore
    //   3431: dup
    //   3432: bipush #39
    //   3434: ldc 1074266368
    //   3436: iastore
    //   3437: dup
    //   3438: bipush #40
    //   3440: ldc 33554688
    //   3442: iastore
    //   3443: dup
    //   3444: bipush #41
    //   3446: ldc 1073741824
    //   3448: iastore
    //   3449: dup
    //   3450: bipush #42
    //   3452: ldc 1107820544
    //   3454: iastore
    //   3455: dup
    //   3456: bipush #43
    //   3458: ldc 34078976
    //   3460: iastore
    //   3461: dup
    //   3462: bipush #44
    //   3464: ldc 1074266368
    //   3466: iastore
    //   3467: dup
    //   3468: bipush #45
    //   3470: sipush #256
    //   3473: iastore
    //   3474: dup
    //   3475: bipush #46
    //   3477: ldc 33554432
    //   3479: iastore
    //   3480: dup
    //   3481: bipush #47
    //   3483: ldc 1107820544
    //   3485: iastore
    //   3486: dup
    //   3487: bipush #48
    //   3489: ldc 1107820800
    //   3491: iastore
    //   3492: dup
    //   3493: bipush #49
    //   3495: ldc 524544
    //   3497: iastore
    //   3498: dup
    //   3499: bipush #50
    //   3501: ldc 1107296256
    //   3503: iastore
    //   3504: dup
    //   3505: bipush #51
    //   3507: ldc 1107820800
    //   3509: iastore
    //   3510: dup
    //   3511: bipush #52
    //   3513: ldc 34078720
    //   3515: iastore
    //   3516: dup
    //   3517: bipush #53
    //   3519: iconst_0
    //   3520: iastore
    //   3521: dup
    //   3522: bipush #54
    //   3524: ldc 1074266112
    //   3526: iastore
    //   3527: dup
    //   3528: bipush #55
    //   3530: ldc 1107296256
    //   3532: iastore
    //   3533: dup
    //   3534: bipush #56
    //   3536: ldc 524544
    //   3538: iastore
    //   3539: dup
    //   3540: bipush #57
    //   3542: ldc 33554688
    //   3544: iastore
    //   3545: dup
    //   3546: bipush #58
    //   3548: ldc 1073742080
    //   3550: iastore
    //   3551: dup
    //   3552: bipush #59
    //   3554: ldc 524288
    //   3556: iastore
    //   3557: dup
    //   3558: bipush #60
    //   3560: iconst_0
    //   3561: iastore
    //   3562: dup
    //   3563: bipush #61
    //   3565: ldc 1074266112
    //   3567: iastore
    //   3568: dup
    //   3569: bipush #62
    //   3571: ldc 34078976
    //   3573: iastore
    //   3574: dup
    //   3575: bipush #63
    //   3577: ldc 1073742080
    //   3579: iastore
    //   3580: astore #13
    //   3582: bipush #64
    //   3584: newarray int
    //   3586: dup
    //   3587: iconst_0
    //   3588: ldc 536870928
    //   3590: iastore
    //   3591: dup
    //   3592: iconst_1
    //   3593: ldc 541065216
    //   3595: iastore
    //   3596: dup
    //   3597: iconst_2
    //   3598: sipush #16384
    //   3601: iastore
    //   3602: dup
    //   3603: iconst_3
    //   3604: ldc 541081616
    //   3606: iastore
    //   3607: dup
    //   3608: iconst_4
    //   3609: ldc 541065216
    //   3611: iastore
    //   3612: dup
    //   3613: iconst_5
    //   3614: bipush #16
    //   3616: iastore
    //   3617: dup
    //   3618: bipush #6
    //   3620: ldc 541081616
    //   3622: iastore
    //   3623: dup
    //   3624: bipush #7
    //   3626: ldc 4194304
    //   3628: iastore
    //   3629: dup
    //   3630: bipush #8
    //   3632: ldc 536887296
    //   3634: iastore
    //   3635: dup
    //   3636: bipush #9
    //   3638: ldc 4210704
    //   3640: iastore
    //   3641: dup
    //   3642: bipush #10
    //   3644: ldc 4194304
    //   3646: iastore
    //   3647: dup
    //   3648: bipush #11
    //   3650: ldc 536870928
    //   3652: iastore
    //   3653: dup
    //   3654: bipush #12
    //   3656: ldc 4194320
    //   3658: iastore
    //   3659: dup
    //   3660: bipush #13
    //   3662: ldc 536887296
    //   3664: iastore
    //   3665: dup
    //   3666: bipush #14
    //   3668: ldc 536870912
    //   3670: iastore
    //   3671: dup
    //   3672: bipush #15
    //   3674: sipush #16400
    //   3677: iastore
    //   3678: dup
    //   3679: bipush #16
    //   3681: iconst_0
    //   3682: iastore
    //   3683: dup
    //   3684: bipush #17
    //   3686: ldc 4194320
    //   3688: iastore
    //   3689: dup
    //   3690: bipush #18
    //   3692: ldc 536887312
    //   3694: iastore
    //   3695: dup
    //   3696: bipush #19
    //   3698: sipush #16384
    //   3701: iastore
    //   3702: dup
    //   3703: bipush #20
    //   3705: ldc 4210688
    //   3707: iastore
    //   3708: dup
    //   3709: bipush #21
    //   3711: ldc 536887312
    //   3713: iastore
    //   3714: dup
    //   3715: bipush #22
    //   3717: bipush #16
    //   3719: iastore
    //   3720: dup
    //   3721: bipush #23
    //   3723: ldc 541065232
    //   3725: iastore
    //   3726: dup
    //   3727: bipush #24
    //   3729: ldc 541065232
    //   3731: iastore
    //   3732: dup
    //   3733: bipush #25
    //   3735: iconst_0
    //   3736: iastore
    //   3737: dup
    //   3738: bipush #26
    //   3740: ldc 4210704
    //   3742: iastore
    //   3743: dup
    //   3744: bipush #27
    //   3746: ldc 541081600
    //   3748: iastore
    //   3749: dup
    //   3750: bipush #28
    //   3752: sipush #16400
    //   3755: iastore
    //   3756: dup
    //   3757: bipush #29
    //   3759: ldc 4210688
    //   3761: iastore
    //   3762: dup
    //   3763: bipush #30
    //   3765: ldc 541081600
    //   3767: iastore
    //   3768: dup
    //   3769: bipush #31
    //   3771: ldc 536870912
    //   3773: iastore
    //   3774: dup
    //   3775: bipush #32
    //   3777: ldc 536887296
    //   3779: iastore
    //   3780: dup
    //   3781: bipush #33
    //   3783: bipush #16
    //   3785: iastore
    //   3786: dup
    //   3787: bipush #34
    //   3789: ldc 541065232
    //   3791: iastore
    //   3792: dup
    //   3793: bipush #35
    //   3795: ldc 4210688
    //   3797: iastore
    //   3798: dup
    //   3799: bipush #36
    //   3801: ldc 541081616
    //   3803: iastore
    //   3804: dup
    //   3805: bipush #37
    //   3807: ldc 4194304
    //   3809: iastore
    //   3810: dup
    //   3811: bipush #38
    //   3813: sipush #16400
    //   3816: iastore
    //   3817: dup
    //   3818: bipush #39
    //   3820: ldc 536870928
    //   3822: iastore
    //   3823: dup
    //   3824: bipush #40
    //   3826: ldc 4194304
    //   3828: iastore
    //   3829: dup
    //   3830: bipush #41
    //   3832: ldc 536887296
    //   3834: iastore
    //   3835: dup
    //   3836: bipush #42
    //   3838: ldc 536870912
    //   3840: iastore
    //   3841: dup
    //   3842: bipush #43
    //   3844: sipush #16400
    //   3847: iastore
    //   3848: dup
    //   3849: bipush #44
    //   3851: ldc 536870928
    //   3853: iastore
    //   3854: dup
    //   3855: bipush #45
    //   3857: ldc 541081616
    //   3859: iastore
    //   3860: dup
    //   3861: bipush #46
    //   3863: ldc 4210688
    //   3865: iastore
    //   3866: dup
    //   3867: bipush #47
    //   3869: ldc 541065216
    //   3871: iastore
    //   3872: dup
    //   3873: bipush #48
    //   3875: ldc 4210704
    //   3877: iastore
    //   3878: dup
    //   3879: bipush #49
    //   3881: ldc 541081600
    //   3883: iastore
    //   3884: dup
    //   3885: bipush #50
    //   3887: iconst_0
    //   3888: iastore
    //   3889: dup
    //   3890: bipush #51
    //   3892: ldc 541065232
    //   3894: iastore
    //   3895: dup
    //   3896: bipush #52
    //   3898: bipush #16
    //   3900: iastore
    //   3901: dup
    //   3902: bipush #53
    //   3904: sipush #16384
    //   3907: iastore
    //   3908: dup
    //   3909: bipush #54
    //   3911: ldc 541065216
    //   3913: iastore
    //   3914: dup
    //   3915: bipush #55
    //   3917: ldc 4210704
    //   3919: iastore
    //   3920: dup
    //   3921: bipush #56
    //   3923: sipush #16384
    //   3926: iastore
    //   3927: dup
    //   3928: bipush #57
    //   3930: ldc 4194320
    //   3932: iastore
    //   3933: dup
    //   3934: bipush #58
    //   3936: ldc 536887312
    //   3938: iastore
    //   3939: dup
    //   3940: bipush #59
    //   3942: iconst_0
    //   3943: iastore
    //   3944: dup
    //   3945: bipush #60
    //   3947: ldc 541081600
    //   3949: iastore
    //   3950: dup
    //   3951: bipush #61
    //   3953: ldc 536870912
    //   3955: iastore
    //   3956: dup
    //   3957: bipush #62
    //   3959: ldc 4194320
    //   3961: iastore
    //   3962: dup
    //   3963: bipush #63
    //   3965: ldc 536887312
    //   3967: iastore
    //   3968: astore #14
    //   3970: bipush #64
    //   3972: newarray int
    //   3974: dup
    //   3975: iconst_0
    //   3976: ldc 2097152
    //   3978: iastore
    //   3979: dup
    //   3980: iconst_1
    //   3981: ldc 69206018
    //   3983: iastore
    //   3984: dup
    //   3985: iconst_2
    //   3986: ldc 67110914
    //   3988: iastore
    //   3989: dup
    //   3990: iconst_3
    //   3991: iconst_0
    //   3992: iastore
    //   3993: dup
    //   3994: iconst_4
    //   3995: sipush #2048
    //   3998: iastore
    //   3999: dup
    //   4000: iconst_5
    //   4001: ldc 67110914
    //   4003: iastore
    //   4004: dup
    //   4005: bipush #6
    //   4007: ldc 2099202
    //   4009: iastore
    //   4010: dup
    //   4011: bipush #7
    //   4013: ldc 69208064
    //   4015: iastore
    //   4016: dup
    //   4017: bipush #8
    //   4019: ldc 69208066
    //   4021: iastore
    //   4022: dup
    //   4023: bipush #9
    //   4025: ldc 2097152
    //   4027: iastore
    //   4028: dup
    //   4029: bipush #10
    //   4031: iconst_0
    //   4032: iastore
    //   4033: dup
    //   4034: bipush #11
    //   4036: ldc 67108866
    //   4038: iastore
    //   4039: dup
    //   4040: bipush #12
    //   4042: iconst_2
    //   4043: iastore
    //   4044: dup
    //   4045: bipush #13
    //   4047: ldc 67108864
    //   4049: iastore
    //   4050: dup
    //   4051: bipush #14
    //   4053: ldc 69206018
    //   4055: iastore
    //   4056: dup
    //   4057: bipush #15
    //   4059: sipush #2050
    //   4062: iastore
    //   4063: dup
    //   4064: bipush #16
    //   4066: ldc 67110912
    //   4068: iastore
    //   4069: dup
    //   4070: bipush #17
    //   4072: ldc 2099202
    //   4074: iastore
    //   4075: dup
    //   4076: bipush #18
    //   4078: ldc 2097154
    //   4080: iastore
    //   4081: dup
    //   4082: bipush #19
    //   4084: ldc 67110912
    //   4086: iastore
    //   4087: dup
    //   4088: bipush #20
    //   4090: ldc 67108866
    //   4092: iastore
    //   4093: dup
    //   4094: bipush #21
    //   4096: ldc 69206016
    //   4098: iastore
    //   4099: dup
    //   4100: bipush #22
    //   4102: ldc 69208064
    //   4104: iastore
    //   4105: dup
    //   4106: bipush #23
    //   4108: ldc 2097154
    //   4110: iastore
    //   4111: dup
    //   4112: bipush #24
    //   4114: ldc 69206016
    //   4116: iastore
    //   4117: dup
    //   4118: bipush #25
    //   4120: sipush #2048
    //   4123: iastore
    //   4124: dup
    //   4125: bipush #26
    //   4127: sipush #2050
    //   4130: iastore
    //   4131: dup
    //   4132: bipush #27
    //   4134: ldc 69208066
    //   4136: iastore
    //   4137: dup
    //   4138: bipush #28
    //   4140: ldc 2099200
    //   4142: iastore
    //   4143: dup
    //   4144: bipush #29
    //   4146: iconst_2
    //   4147: iastore
    //   4148: dup
    //   4149: bipush #30
    //   4151: ldc 67108864
    //   4153: iastore
    //   4154: dup
    //   4155: bipush #31
    //   4157: ldc 2099200
    //   4159: iastore
    //   4160: dup
    //   4161: bipush #32
    //   4163: ldc 67108864
    //   4165: iastore
    //   4166: dup
    //   4167: bipush #33
    //   4169: ldc 2099200
    //   4171: iastore
    //   4172: dup
    //   4173: bipush #34
    //   4175: ldc 2097152
    //   4177: iastore
    //   4178: dup
    //   4179: bipush #35
    //   4181: ldc 67110914
    //   4183: iastore
    //   4184: dup
    //   4185: bipush #36
    //   4187: ldc 67110914
    //   4189: iastore
    //   4190: dup
    //   4191: bipush #37
    //   4193: ldc 69206018
    //   4195: iastore
    //   4196: dup
    //   4197: bipush #38
    //   4199: ldc 69206018
    //   4201: iastore
    //   4202: dup
    //   4203: bipush #39
    //   4205: iconst_2
    //   4206: iastore
    //   4207: dup
    //   4208: bipush #40
    //   4210: ldc 2097154
    //   4212: iastore
    //   4213: dup
    //   4214: bipush #41
    //   4216: ldc 67108864
    //   4218: iastore
    //   4219: dup
    //   4220: bipush #42
    //   4222: ldc 67110912
    //   4224: iastore
    //   4225: dup
    //   4226: bipush #43
    //   4228: ldc 2097152
    //   4230: iastore
    //   4231: dup
    //   4232: bipush #44
    //   4234: ldc 69208064
    //   4236: iastore
    //   4237: dup
    //   4238: bipush #45
    //   4240: sipush #2050
    //   4243: iastore
    //   4244: dup
    //   4245: bipush #46
    //   4247: ldc 2099202
    //   4249: iastore
    //   4250: dup
    //   4251: bipush #47
    //   4253: ldc 69208064
    //   4255: iastore
    //   4256: dup
    //   4257: bipush #48
    //   4259: sipush #2050
    //   4262: iastore
    //   4263: dup
    //   4264: bipush #49
    //   4266: ldc 67108866
    //   4268: iastore
    //   4269: dup
    //   4270: bipush #50
    //   4272: ldc 69208066
    //   4274: iastore
    //   4275: dup
    //   4276: bipush #51
    //   4278: ldc 69206016
    //   4280: iastore
    //   4281: dup
    //   4282: bipush #52
    //   4284: ldc 2099200
    //   4286: iastore
    //   4287: dup
    //   4288: bipush #53
    //   4290: iconst_0
    //   4291: iastore
    //   4292: dup
    //   4293: bipush #54
    //   4295: iconst_2
    //   4296: iastore
    //   4297: dup
    //   4298: bipush #55
    //   4300: ldc 69208066
    //   4302: iastore
    //   4303: dup
    //   4304: bipush #56
    //   4306: iconst_0
    //   4307: iastore
    //   4308: dup
    //   4309: bipush #57
    //   4311: ldc 2099202
    //   4313: iastore
    //   4314: dup
    //   4315: bipush #58
    //   4317: ldc 69206016
    //   4319: iastore
    //   4320: dup
    //   4321: bipush #59
    //   4323: sipush #2048
    //   4326: iastore
    //   4327: dup
    //   4328: bipush #60
    //   4330: ldc 67108866
    //   4332: iastore
    //   4333: dup
    //   4334: bipush #61
    //   4336: ldc 67110912
    //   4338: iastore
    //   4339: dup
    //   4340: bipush #62
    //   4342: sipush #2048
    //   4345: iastore
    //   4346: dup
    //   4347: bipush #63
    //   4349: ldc 2097154
    //   4351: iastore
    //   4352: astore #15
    //   4354: bipush #64
    //   4356: newarray int
    //   4358: dup
    //   4359: iconst_0
    //   4360: ldc 268439616
    //   4362: iastore
    //   4363: dup
    //   4364: iconst_1
    //   4365: sipush #4096
    //   4368: iastore
    //   4369: dup
    //   4370: iconst_2
    //   4371: ldc 262144
    //   4373: iastore
    //   4374: dup
    //   4375: iconst_3
    //   4376: ldc 268701760
    //   4378: iastore
    //   4379: dup
    //   4380: iconst_4
    //   4381: ldc 268435456
    //   4383: iastore
    //   4384: dup
    //   4385: iconst_5
    //   4386: ldc 268439616
    //   4388: iastore
    //   4389: dup
    //   4390: bipush #6
    //   4392: bipush #64
    //   4394: iastore
    //   4395: dup
    //   4396: bipush #7
    //   4398: ldc 268435456
    //   4400: iastore
    //   4401: dup
    //   4402: bipush #8
    //   4404: ldc 262208
    //   4406: iastore
    //   4407: dup
    //   4408: bipush #9
    //   4410: ldc 268697600
    //   4412: iastore
    //   4413: dup
    //   4414: bipush #10
    //   4416: ldc 268701760
    //   4418: iastore
    //   4419: dup
    //   4420: bipush #11
    //   4422: ldc 266240
    //   4424: iastore
    //   4425: dup
    //   4426: bipush #12
    //   4428: ldc 268701696
    //   4430: iastore
    //   4431: dup
    //   4432: bipush #13
    //   4434: ldc 266304
    //   4436: iastore
    //   4437: dup
    //   4438: bipush #14
    //   4440: sipush #4096
    //   4443: iastore
    //   4444: dup
    //   4445: bipush #15
    //   4447: bipush #64
    //   4449: iastore
    //   4450: dup
    //   4451: bipush #16
    //   4453: ldc 268697600
    //   4455: iastore
    //   4456: dup
    //   4457: bipush #17
    //   4459: ldc 268435520
    //   4461: iastore
    //   4462: dup
    //   4463: bipush #18
    //   4465: ldc 268439552
    //   4467: iastore
    //   4468: dup
    //   4469: bipush #19
    //   4471: sipush #4160
    //   4474: iastore
    //   4475: dup
    //   4476: bipush #20
    //   4478: ldc 266240
    //   4480: iastore
    //   4481: dup
    //   4482: bipush #21
    //   4484: ldc 262208
    //   4486: iastore
    //   4487: dup
    //   4488: bipush #22
    //   4490: ldc 268697664
    //   4492: iastore
    //   4493: dup
    //   4494: bipush #23
    //   4496: ldc 268701696
    //   4498: iastore
    //   4499: dup
    //   4500: bipush #24
    //   4502: sipush #4160
    //   4505: iastore
    //   4506: dup
    //   4507: bipush #25
    //   4509: iconst_0
    //   4510: iastore
    //   4511: dup
    //   4512: bipush #26
    //   4514: iconst_0
    //   4515: iastore
    //   4516: dup
    //   4517: bipush #27
    //   4519: ldc 268697664
    //   4521: iastore
    //   4522: dup
    //   4523: bipush #28
    //   4525: ldc 268435520
    //   4527: iastore
    //   4528: dup
    //   4529: bipush #29
    //   4531: ldc 268439552
    //   4533: iastore
    //   4534: dup
    //   4535: bipush #30
    //   4537: ldc 266304
    //   4539: iastore
    //   4540: dup
    //   4541: bipush #31
    //   4543: ldc 262144
    //   4545: iastore
    //   4546: dup
    //   4547: bipush #32
    //   4549: ldc 266304
    //   4551: iastore
    //   4552: dup
    //   4553: bipush #33
    //   4555: ldc 262144
    //   4557: iastore
    //   4558: dup
    //   4559: bipush #34
    //   4561: ldc 268701696
    //   4563: iastore
    //   4564: dup
    //   4565: bipush #35
    //   4567: sipush #4096
    //   4570: iastore
    //   4571: dup
    //   4572: bipush #36
    //   4574: bipush #64
    //   4576: iastore
    //   4577: dup
    //   4578: bipush #37
    //   4580: ldc 268697664
    //   4582: iastore
    //   4583: dup
    //   4584: bipush #38
    //   4586: sipush #4096
    //   4589: iastore
    //   4590: dup
    //   4591: bipush #39
    //   4593: ldc 266304
    //   4595: iastore
    //   4596: dup
    //   4597: bipush #40
    //   4599: ldc 268439552
    //   4601: iastore
    //   4602: dup
    //   4603: bipush #41
    //   4605: bipush #64
    //   4607: iastore
    //   4608: dup
    //   4609: bipush #42
    //   4611: ldc 268435520
    //   4613: iastore
    //   4614: dup
    //   4615: bipush #43
    //   4617: ldc 268697600
    //   4619: iastore
    //   4620: dup
    //   4621: bipush #44
    //   4623: ldc 268697664
    //   4625: iastore
    //   4626: dup
    //   4627: bipush #45
    //   4629: ldc 268435456
    //   4631: iastore
    //   4632: dup
    //   4633: bipush #46
    //   4635: ldc 262144
    //   4637: iastore
    //   4638: dup
    //   4639: bipush #47
    //   4641: ldc 268439616
    //   4643: iastore
    //   4644: dup
    //   4645: bipush #48
    //   4647: iconst_0
    //   4648: iastore
    //   4649: dup
    //   4650: bipush #49
    //   4652: ldc 268701760
    //   4654: iastore
    //   4655: dup
    //   4656: bipush #50
    //   4658: ldc 262208
    //   4660: iastore
    //   4661: dup
    //   4662: bipush #51
    //   4664: ldc 268435520
    //   4666: iastore
    //   4667: dup
    //   4668: bipush #52
    //   4670: ldc 268697600
    //   4672: iastore
    //   4673: dup
    //   4674: bipush #53
    //   4676: ldc 268439552
    //   4678: iastore
    //   4679: dup
    //   4680: bipush #54
    //   4682: ldc 268439616
    //   4684: iastore
    //   4685: dup
    //   4686: bipush #55
    //   4688: iconst_0
    //   4689: iastore
    //   4690: dup
    //   4691: bipush #56
    //   4693: ldc 268701760
    //   4695: iastore
    //   4696: dup
    //   4697: bipush #57
    //   4699: ldc 266240
    //   4701: iastore
    //   4702: dup
    //   4703: bipush #58
    //   4705: ldc 266240
    //   4707: iastore
    //   4708: dup
    //   4709: bipush #59
    //   4711: sipush #4160
    //   4714: iastore
    //   4715: dup
    //   4716: bipush #60
    //   4718: sipush #4160
    //   4721: iastore
    //   4722: dup
    //   4723: bipush #61
    //   4725: ldc 262208
    //   4727: iastore
    //   4728: dup
    //   4729: bipush #62
    //   4731: ldc 268435456
    //   4733: iastore
    //   4734: dup
    //   4735: bipush #63
    //   4737: ldc 268701696
    //   4739: iastore
    //   4740: astore #16
    //   4742: aload #4
    //   4744: arraylength
    //   4745: istore #17
    //   4747: iconst_2
    //   4748: newarray int
    //   4750: astore #18
    //   4752: iload #17
    //   4754: newarray byte
    //   4756: astore #5
    //   4758: iload #17
    //   4760: bipush #8
    //   4762: idiv
    //   4763: istore #19
    //   4765: iconst_0
    //   4766: istore #20
    //   4768: iload #20
    //   4770: iload #19
    //   4772: if_icmpge -> 5690
    //   4775: iload #20
    //   4777: bipush #8
    //   4779: imul
    //   4780: istore #21
    //   4782: iconst_0
    //   4783: istore #22
    //   4785: iload #22
    //   4787: iconst_2
    //   4788: if_icmpge -> 4877
    //   4791: aload #18
    //   4793: iload #22
    //   4795: aload #4
    //   4797: iload #21
    //   4799: iload #22
    //   4801: iconst_4
    //   4802: imul
    //   4803: iadd
    //   4804: baload
    //   4805: sipush #255
    //   4808: iand
    //   4809: bipush #24
    //   4811: ishl
    //   4812: aload #4
    //   4814: iload #21
    //   4816: iload #22
    //   4818: iconst_4
    //   4819: imul
    //   4820: iadd
    //   4821: iconst_1
    //   4822: iadd
    //   4823: baload
    //   4824: sipush #255
    //   4827: iand
    //   4828: bipush #16
    //   4830: ishl
    //   4831: ior
    //   4832: aload #4
    //   4834: iload #21
    //   4836: iload #22
    //   4838: iconst_4
    //   4839: imul
    //   4840: iadd
    //   4841: iconst_2
    //   4842: iadd
    //   4843: baload
    //   4844: sipush #255
    //   4847: iand
    //   4848: bipush #8
    //   4850: ishl
    //   4851: ior
    //   4852: aload #4
    //   4854: iload #21
    //   4856: iload #22
    //   4858: iconst_4
    //   4859: imul
    //   4860: iadd
    //   4861: iconst_3
    //   4862: iadd
    //   4863: baload
    //   4864: sipush #255
    //   4867: iand
    //   4868: ior
    //   4869: iastore
    //   4870: iinc #22, 1
    //   4873: iload_2
    //   4874: ifeq -> 4785
    //   4877: iconst_0
    //   4878: istore #27
    //   4880: aload #18
    //   4882: iconst_0
    //   4883: iaload
    //   4884: istore #25
    //   4886: aload #18
    //   4888: iconst_1
    //   4889: iaload
    //   4890: istore #24
    //   4892: iload #25
    //   4894: iconst_4
    //   4895: iushr
    //   4896: iload #24
    //   4898: ixor
    //   4899: ldc 252645135
    //   4901: iand
    //   4902: istore #23
    //   4904: iload #24
    //   4906: iload #23
    //   4908: ixor
    //   4909: istore #24
    //   4911: iload #25
    //   4913: iload #23
    //   4915: iconst_4
    //   4916: ishl
    //   4917: ixor
    //   4918: istore #25
    //   4920: iload #25
    //   4922: bipush #16
    //   4924: iushr
    //   4925: iload #24
    //   4927: ixor
    //   4928: ldc 65535
    //   4930: iand
    //   4931: istore #23
    //   4933: iload #24
    //   4935: iload #23
    //   4937: ixor
    //   4938: istore #24
    //   4940: iload #25
    //   4942: iload #23
    //   4944: bipush #16
    //   4946: ishl
    //   4947: ixor
    //   4948: istore #25
    //   4950: iload #24
    //   4952: iconst_2
    //   4953: iushr
    //   4954: iload #25
    //   4956: ixor
    //   4957: ldc 858993459
    //   4959: iand
    //   4960: istore #23
    //   4962: iload #25
    //   4964: iload #23
    //   4966: ixor
    //   4967: istore #25
    //   4969: iload #24
    //   4971: iload #23
    //   4973: iconst_2
    //   4974: ishl
    //   4975: ixor
    //   4976: istore #24
    //   4978: iload #24
    //   4980: bipush #8
    //   4982: iushr
    //   4983: iload #25
    //   4985: ixor
    //   4986: ldc 16711935
    //   4988: iand
    //   4989: istore #23
    //   4991: iload #25
    //   4993: iload #23
    //   4995: ixor
    //   4996: istore #25
    //   4998: iload #24
    //   5000: iload #23
    //   5002: bipush #8
    //   5004: ishl
    //   5005: ixor
    //   5006: istore #24
    //   5008: iload #24
    //   5010: iconst_1
    //   5011: ishl
    //   5012: iload #24
    //   5014: bipush #31
    //   5016: iushr
    //   5017: iconst_1
    //   5018: iand
    //   5019: ior
    //   5020: istore #24
    //   5022: iload #25
    //   5024: iload #24
    //   5026: ixor
    //   5027: ldc -1431655766
    //   5029: iand
    //   5030: istore #23
    //   5032: iload #25
    //   5034: iload #23
    //   5036: ixor
    //   5037: istore #25
    //   5039: iload #24
    //   5041: iload #23
    //   5043: ixor
    //   5044: istore #24
    //   5046: iload #25
    //   5048: iconst_1
    //   5049: ishl
    //   5050: iload #25
    //   5052: bipush #31
    //   5054: iushr
    //   5055: iconst_1
    //   5056: iand
    //   5057: ior
    //   5058: istore #25
    //   5060: iconst_0
    //   5061: istore #26
    //   5063: iload #26
    //   5065: bipush #8
    //   5067: if_icmpge -> 5405
    //   5070: iload #24
    //   5072: bipush #28
    //   5074: ishl
    //   5075: iload #24
    //   5077: iconst_4
    //   5078: iushr
    //   5079: ior
    //   5080: istore #23
    //   5082: iload #23
    //   5084: aload #6
    //   5086: iload #27
    //   5088: iinc #27, 1
    //   5091: iaload
    //   5092: ixor
    //   5093: istore #23
    //   5095: aload #15
    //   5097: iload #23
    //   5099: bipush #63
    //   5101: iand
    //   5102: iaload
    //   5103: istore #22
    //   5105: iload #22
    //   5107: aload #13
    //   5109: iload #23
    //   5111: bipush #8
    //   5113: iushr
    //   5114: bipush #63
    //   5116: iand
    //   5117: iaload
    //   5118: ior
    //   5119: istore #22
    //   5121: iload #22
    //   5123: aload #11
    //   5125: iload #23
    //   5127: bipush #16
    //   5129: iushr
    //   5130: bipush #63
    //   5132: iand
    //   5133: iaload
    //   5134: ior
    //   5135: istore #22
    //   5137: iload #22
    //   5139: aload #9
    //   5141: iload #23
    //   5143: bipush #24
    //   5145: iushr
    //   5146: bipush #63
    //   5148: iand
    //   5149: iaload
    //   5150: ior
    //   5151: istore #22
    //   5153: iload #24
    //   5155: aload #6
    //   5157: iload #27
    //   5159: iinc #27, 1
    //   5162: iaload
    //   5163: ixor
    //   5164: istore #23
    //   5166: iload #22
    //   5168: aload #16
    //   5170: iload #23
    //   5172: bipush #63
    //   5174: iand
    //   5175: iaload
    //   5176: ior
    //   5177: istore #22
    //   5179: iload #22
    //   5181: aload #14
    //   5183: iload #23
    //   5185: bipush #8
    //   5187: iushr
    //   5188: bipush #63
    //   5190: iand
    //   5191: iaload
    //   5192: ior
    //   5193: istore #22
    //   5195: iload #22
    //   5197: aload #12
    //   5199: iload #23
    //   5201: bipush #16
    //   5203: iushr
    //   5204: bipush #63
    //   5206: iand
    //   5207: iaload
    //   5208: ior
    //   5209: istore #22
    //   5211: iload #22
    //   5213: aload #10
    //   5215: iload #23
    //   5217: bipush #24
    //   5219: iushr
    //   5220: bipush #63
    //   5222: iand
    //   5223: iaload
    //   5224: ior
    //   5225: istore #22
    //   5227: iload #25
    //   5229: iload #22
    //   5231: ixor
    //   5232: istore #25
    //   5234: iload #25
    //   5236: bipush #28
    //   5238: ishl
    //   5239: iload #25
    //   5241: iconst_4
    //   5242: iushr
    //   5243: ior
    //   5244: istore #23
    //   5246: iload #23
    //   5248: aload #6
    //   5250: iload #27
    //   5252: iinc #27, 1
    //   5255: iaload
    //   5256: ixor
    //   5257: istore #23
    //   5259: aload #15
    //   5261: iload #23
    //   5263: bipush #63
    //   5265: iand
    //   5266: iaload
    //   5267: istore #22
    //   5269: iload #22
    //   5271: aload #13
    //   5273: iload #23
    //   5275: bipush #8
    //   5277: iushr
    //   5278: bipush #63
    //   5280: iand
    //   5281: iaload
    //   5282: ior
    //   5283: istore #22
    //   5285: iload #22
    //   5287: aload #11
    //   5289: iload #23
    //   5291: bipush #16
    //   5293: iushr
    //   5294: bipush #63
    //   5296: iand
    //   5297: iaload
    //   5298: ior
    //   5299: istore #22
    //   5301: iload #22
    //   5303: aload #9
    //   5305: iload #23
    //   5307: bipush #24
    //   5309: iushr
    //   5310: bipush #63
    //   5312: iand
    //   5313: iaload
    //   5314: ior
    //   5315: istore #22
    //   5317: iload #25
    //   5319: aload #6
    //   5321: iload #27
    //   5323: iinc #27, 1
    //   5326: iaload
    //   5327: ixor
    //   5328: istore #23
    //   5330: iload #22
    //   5332: aload #16
    //   5334: iload #23
    //   5336: bipush #63
    //   5338: iand
    //   5339: iaload
    //   5340: ior
    //   5341: istore #22
    //   5343: iload #22
    //   5345: aload #14
    //   5347: iload #23
    //   5349: bipush #8
    //   5351: iushr
    //   5352: bipush #63
    //   5354: iand
    //   5355: iaload
    //   5356: ior
    //   5357: istore #22
    //   5359: iload #22
    //   5361: aload #12
    //   5363: iload #23
    //   5365: bipush #16
    //   5367: iushr
    //   5368: bipush #63
    //   5370: iand
    //   5371: iaload
    //   5372: ior
    //   5373: istore #22
    //   5375: iload #22
    //   5377: aload #10
    //   5379: iload #23
    //   5381: bipush #24
    //   5383: iushr
    //   5384: bipush #63
    //   5386: iand
    //   5387: iaload
    //   5388: ior
    //   5389: istore #22
    //   5391: iload #24
    //   5393: iload #22
    //   5395: ixor
    //   5396: istore #24
    //   5398: iinc #26, 1
    //   5401: iload_2
    //   5402: ifeq -> 5063
    //   5405: iload #24
    //   5407: bipush #31
    //   5409: ishl
    //   5410: iload #24
    //   5412: iconst_1
    //   5413: iushr
    //   5414: ior
    //   5415: istore #24
    //   5417: iload #25
    //   5419: iload #24
    //   5421: ixor
    //   5422: ldc -1431655766
    //   5424: iand
    //   5425: istore #23
    //   5427: iload #25
    //   5429: iload #23
    //   5431: ixor
    //   5432: istore #25
    //   5434: iload #24
    //   5436: iload #23
    //   5438: ixor
    //   5439: istore #24
    //   5441: iload #25
    //   5443: bipush #31
    //   5445: ishl
    //   5446: iload #25
    //   5448: iconst_1
    //   5449: iushr
    //   5450: ior
    //   5451: istore #25
    //   5453: iload #25
    //   5455: bipush #8
    //   5457: iushr
    //   5458: iload #24
    //   5460: ixor
    //   5461: ldc 16711935
    //   5463: iand
    //   5464: istore #23
    //   5466: iload #24
    //   5468: iload #23
    //   5470: ixor
    //   5471: istore #24
    //   5473: iload #25
    //   5475: iload #23
    //   5477: bipush #8
    //   5479: ishl
    //   5480: ixor
    //   5481: istore #25
    //   5483: iload #25
    //   5485: iconst_2
    //   5486: iushr
    //   5487: iload #24
    //   5489: ixor
    //   5490: ldc 858993459
    //   5492: iand
    //   5493: istore #23
    //   5495: iload #24
    //   5497: iload #23
    //   5499: ixor
    //   5500: istore #24
    //   5502: iload #25
    //   5504: iload #23
    //   5506: iconst_2
    //   5507: ishl
    //   5508: ixor
    //   5509: istore #25
    //   5511: iload #24
    //   5513: bipush #16
    //   5515: iushr
    //   5516: iload #25
    //   5518: ixor
    //   5519: ldc 65535
    //   5521: iand
    //   5522: istore #23
    //   5524: iload #25
    //   5526: iload #23
    //   5528: ixor
    //   5529: istore #25
    //   5531: iload #24
    //   5533: iload #23
    //   5535: bipush #16
    //   5537: ishl
    //   5538: ixor
    //   5539: istore #24
    //   5541: iload #24
    //   5543: iconst_4
    //   5544: iushr
    //   5545: iload #25
    //   5547: ixor
    //   5548: ldc 252645135
    //   5550: iand
    //   5551: istore #23
    //   5553: iload #25
    //   5555: iload #23
    //   5557: ixor
    //   5558: istore #25
    //   5560: iload #24
    //   5562: iload #23
    //   5564: iconst_4
    //   5565: ishl
    //   5566: ixor
    //   5567: istore #24
    //   5569: aload #18
    //   5571: iconst_0
    //   5572: iload #24
    //   5574: iastore
    //   5575: aload #18
    //   5577: iconst_1
    //   5578: iload #25
    //   5580: iastore
    //   5581: iload #20
    //   5583: bipush #8
    //   5585: imul
    //   5586: istore #28
    //   5588: iconst_0
    //   5589: istore #29
    //   5591: iload #29
    //   5593: iconst_2
    //   5594: if_icmpge -> 5683
    //   5597: aload #5
    //   5599: iload #28
    //   5601: iload #29
    //   5603: iconst_4
    //   5604: imul
    //   5605: iadd
    //   5606: aload #18
    //   5608: iload #29
    //   5610: iaload
    //   5611: bipush #24
    //   5613: iushr
    //   5614: i2b
    //   5615: bastore
    //   5616: aload #5
    //   5618: iload #28
    //   5620: iload #29
    //   5622: iconst_4
    //   5623: imul
    //   5624: iadd
    //   5625: iconst_1
    //   5626: iadd
    //   5627: aload #18
    //   5629: iload #29
    //   5631: iaload
    //   5632: bipush #16
    //   5634: iushr
    //   5635: i2b
    //   5636: bastore
    //   5637: aload #5
    //   5639: iload #28
    //   5641: iload #29
    //   5643: iconst_4
    //   5644: imul
    //   5645: iadd
    //   5646: iconst_2
    //   5647: iadd
    //   5648: aload #18
    //   5650: iload #29
    //   5652: iaload
    //   5653: bipush #8
    //   5655: iushr
    //   5656: i2b
    //   5657: bastore
    //   5658: aload #5
    //   5660: iload #28
    //   5662: iload #29
    //   5664: iconst_4
    //   5665: imul
    //   5666: iadd
    //   5667: iconst_3
    //   5668: iadd
    //   5669: aload #18
    //   5671: iload #29
    //   5673: iaload
    //   5674: i2b
    //   5675: bastore
    //   5676: iinc #29, 1
    //   5679: iload_2
    //   5680: ifeq -> 5591
    //   5683: iinc #20, 1
    //   5686: iload_2
    //   5687: ifeq -> 4768
    //   5690: new java/math/BigInteger
    //   5693: dup
    //   5694: aload #5
    //   5696: invokespecial <init> : ([B)V
    //   5699: invokevirtual abs : ()Ljava/math/BigInteger;
    //   5702: putstatic burp/Zezn.Zh : Ljava/lang/Object;
    //   5705: sipush #19311
    //   5708: sipush #23626
    //   5711: invokestatic a : (II)Ljava/lang/String;
    //   5714: iconst_1
    //   5715: ldc burp/Zrt9
    //   5717: invokevirtual getClassLoader : ()Ljava/lang/ClassLoader;
    //   5720: invokestatic forName : (Ljava/lang/String;ZLjava/lang/ClassLoader;)Ljava/lang/Class;
    //   5723: invokevirtual getDeclaredFields : ()[Ljava/lang/reflect/Field;
    //   5726: astore #4
    //   5728: aload #4
    //   5730: arraylength
    //   5731: istore #5
    //   5733: iconst_0
    //   5734: istore #6
    //   5736: iload #6
    //   5738: iload #5
    //   5740: if_icmpge -> 5878
    //   5743: aload #4
    //   5745: iload #6
    //   5747: aaload
    //   5748: astore #7
    //   5750: aload #7
    //   5752: invokevirtual getModifiers : ()I
    //   5755: invokestatic isStatic : (I)Z
    //   5758: ifne -> 5768
    //   5761: goto -> 5871
    //   5764: invokestatic a : (Ljava/lang/Throwable;)Ljava/lang/Throwable;
    //   5767: athrow
    //   5768: aload #7
    //   5770: invokevirtual getType : ()Ljava/lang/Class;
    //   5773: astore #8
    //   5775: aload #8
    //   5777: ifnull -> 5858
    //   5780: aload #8
    //   5782: invokevirtual isPrimitive : ()Z
    //   5785: ifne -> 5858
    //   5788: goto -> 5795
    //   5791: invokestatic a : (Ljava/lang/Throwable;)Ljava/lang/Throwable;
    //   5794: athrow
    //   5795: aload #8
    //   5797: invokevirtual getPackage : ()Ljava/lang/Package;
    //   5800: ifnull -> 5858
    //   5803: goto -> 5810
    //   5806: invokestatic a : (Ljava/lang/Throwable;)Ljava/lang/Throwable;
    //   5809: athrow
    //   5810: aload #8
    //   5812: invokevirtual getPackage : ()Ljava/lang/Package;
    //   5815: invokevirtual getName : ()Ljava/lang/String;
    //   5818: ifnull -> 5858
    //   5821: goto -> 5828
    //   5824: invokestatic a : (Ljava/lang/Throwable;)Ljava/lang/Throwable;
    //   5827: athrow
    //   5828: aload #8
    //   5830: invokevirtual getPackage : ()Ljava/lang/Package;
    //   5833: invokevirtual getName : ()Ljava/lang/String;
    //   5836: sipush #19316
    //   5839: sipush #12425
    //   5842: invokestatic a : (II)Ljava/lang/String;
    //   5845: invokevirtual startsWith : (Ljava/lang/String;)Z
    //   5848: ifne -> 5858
    //   5851: goto -> 5858
    //   5854: invokestatic a : (Ljava/lang/Throwable;)Ljava/lang/Throwable;
    //   5857: athrow
    //   5858: aload #7
    //   5860: iconst_1
    //   5861: invokevirtual setAccessible : (Z)V
    //   5864: aload #7
    //   5866: aconst_null
    //   5867: invokevirtual get : (Ljava/lang/Object;)Ljava/lang/Object;
    //   5870: pop
    //   5871: iinc #6, 1
    //   5874: iload_2
    //   5875: ifeq -> 5736
    //   5878: sipush #19308
    //   5881: sipush #18519
    //   5884: invokestatic a : (II)Ljava/lang/String;
    //   5887: invokestatic forName : (Ljava/lang/String;)Ljava/lang/Class;
    //   5890: invokevirtual getDeclaredMethods : ()[Ljava/lang/reflect/Method;
    //   5893: astore #4
    //   5895: aload #4
    //   5897: arraylength
    //   5898: istore #5
    //   5900: iconst_0
    //   5901: istore #6
    //   5903: iload #6
    //   5905: iload #5
    //   5907: if_icmpge -> 6040
    //   5910: aload #4
    //   5912: iload #6
    //   5914: aaload
    //   5915: astore #7
    //   5917: aload #7
    //   5919: invokevirtual getParameterTypes : ()[Ljava/lang/Class;
    //   5922: pop
    //   5923: aload #7
    //   5925: invokevirtual getModifiers : ()I
    //   5928: invokestatic isStatic : (I)Z
    //   5931: ifeq -> 6026
    //   5934: aload #7
    //   5936: invokevirtual getParameterTypes : ()[Ljava/lang/Class;
    //   5939: arraylength
    //   5940: iconst_2
    //   5941: if_icmpne -> 6026
    //   5944: goto -> 5951
    //   5947: invokestatic a : (Ljava/lang/Throwable;)Ljava/lang/Throwable;
    //   5950: athrow
    //   5951: aload #7
    //   5953: invokevirtual getReturnType : ()Ljava/lang/Class;
    //   5956: getstatic java/lang/Void.TYPE : Ljava/lang/Class;
    //   5959: invokevirtual equals : (Ljava/lang/Object;)Z
    //   5962: ifeq -> 6026
    //   5965: goto -> 5972
    //   5968: invokestatic a : (Ljava/lang/Throwable;)Ljava/lang/Throwable;
    //   5971: athrow
    //   5972: aload #7
    //   5974: iconst_1
    //   5975: invokevirtual setAccessible : (Z)V
    //   5978: aload #7
    //   5980: aconst_null
    //   5981: iconst_2
    //   5982: anewarray java/lang/Object
    //   5985: dup
    //   5986: iconst_0
    //   5987: aload_0
    //   5988: aastore
    //   5989: dup
    //   5990: iconst_1
    //   5991: aload_1
    //   5992: ifnonnull -> 6010
    //   5995: goto -> 6002
    //   5998: invokestatic a : (Ljava/lang/Throwable;)Ljava/lang/Throwable;
    //   6001: athrow
    //   6002: aload_1
    //   6003: goto -> 6017
    //   6006: invokestatic a : (Ljava/lang/Throwable;)Ljava/lang/Throwable;
    //   6009: athrow
    //   6010: aload_1
    //   6011: checkcast [B
    //   6014: invokevirtual clone : ()Ljava/lang/Object;
    //   6017: aastore
    //   6018: invokevirtual invoke : (Ljava/lang/Object;[Ljava/lang/Object;)Ljava/lang/Object;
    //   6021: pop
    //   6022: iload_2
    //   6023: ifeq -> 6040
    //   6026: iinc #6, 1
    //   6029: iload_2
    //   6030: ifeq -> 5903
    //   6033: goto -> 6040
    //   6036: invokestatic a : (Ljava/lang/Throwable;)Ljava/lang/Throwable;
    //   6039: athrow
    //   6040: iconst_0
    //   6041: istore #4
    //   6043: getstatic burp/Zkhy.Zu : Ljava/lang/String;
    //   6046: getstatic burp/Ztod.ZP : Ljava/lang/Object;
    //   6049: checkcast java/math/BigInteger
    //   6052: invokevirtual intValue : ()I
    //   6055: bipush #32
    //   6057: irem
    //   6058: invokestatic abs : (I)I
    //   6061: invokevirtual charAt : (I)C
    //   6064: getstatic burp/Zrxm.Zp : Ljava/lang/String;
    //   6067: getstatic burp/Ze_b.Zp : Ljava/lang/Object;
    //   6070: checkcast java/math/BigInteger
    //   6073: invokevirtual intValue : ()I
    //   6076: bipush #32
    //   6078: irem
    //   6079: invokestatic abs : (I)I
    //   6082: invokevirtual charAt : (I)C
    //   6085: if_icmpgt -> 6430
    //   6088: sipush #19314
    //   6091: sipush #-22632
    //   6094: invokestatic a : (II)Ljava/lang/String;
    //   6097: iconst_1
    //   6098: ldc burp/Ze7y
    //   6100: invokevirtual getClassLoader : ()Ljava/lang/ClassLoader;
    //   6103: invokestatic forName : (Ljava/lang/String;ZLjava/lang/ClassLoader;)Ljava/lang/Class;
    //   6106: invokevirtual getDeclaredFields : ()[Ljava/lang/reflect/Field;
    //   6109: astore #5
    //   6111: aload #5
    //   6113: arraylength
    //   6114: istore #6
    //   6116: iconst_0
    //   6117: istore #7
    //   6119: iload #7
    //   6121: iload #6
    //   6123: if_icmpge -> 6261
    //   6126: aload #5
    //   6128: iload #7
    //   6130: aaload
    //   6131: astore #8
    //   6133: aload #8
    //   6135: invokevirtual getModifiers : ()I
    //   6138: invokestatic isStatic : (I)Z
    //   6141: ifne -> 6151
    //   6144: goto -> 6254
    //   6147: invokestatic a : (Ljava/lang/Throwable;)Ljava/lang/Throwable;
    //   6150: athrow
    //   6151: aload #8
    //   6153: invokevirtual getType : ()Ljava/lang/Class;
    //   6156: astore #9
    //   6158: aload #9
    //   6160: ifnull -> 6241
    //   6163: aload #9
    //   6165: invokevirtual isPrimitive : ()Z
    //   6168: ifne -> 6241
    //   6171: goto -> 6178
    //   6174: invokestatic a : (Ljava/lang/Throwable;)Ljava/lang/Throwable;
    //   6177: athrow
    //   6178: aload #9
    //   6180: invokevirtual getPackage : ()Ljava/lang/Package;
    //   6183: ifnull -> 6241
    //   6186: goto -> 6193
    //   6189: invokestatic a : (Ljava/lang/Throwable;)Ljava/lang/Throwable;
    //   6192: athrow
    //   6193: aload #9
    //   6195: invokevirtual getPackage : ()Ljava/lang/Package;
    //   6198: invokevirtual getName : ()Ljava/lang/String;
    //   6201: ifnull -> 6241
    //   6204: goto -> 6211
    //   6207: invokestatic a : (Ljava/lang/Throwable;)Ljava/lang/Throwable;
    //   6210: athrow
    //   6211: aload #9
    //   6213: invokevirtual getPackage : ()Ljava/lang/Package;
    //   6216: invokevirtual getName : ()Ljava/lang/String;
    //   6219: sipush #19302
    //   6222: sipush #-21379
    //   6225: invokestatic a : (II)Ljava/lang/String;
    //   6228: invokevirtual startsWith : (Ljava/lang/String;)Z
    //   6231: ifne -> 6241
    //   6234: goto -> 6241
    //   6237: invokestatic a : (Ljava/lang/Throwable;)Ljava/lang/Throwable;
    //   6240: athrow
    //   6241: aload #8
    //   6243: iconst_1
    //   6244: invokevirtual setAccessible : (Z)V
    //   6247: aload #8
    //   6249: aconst_null
    //   6250: invokevirtual get : (Ljava/lang/Object;)Ljava/lang/Object;
    //   6253: pop
    //   6254: iinc #7, 1
    //   6257: iload_2
    //   6258: ifeq -> 6119
    //   6261: sipush #19301
    //   6264: sipush #29123
    //   6267: invokestatic a : (II)Ljava/lang/String;
    //   6270: invokestatic forName : (Ljava/lang/String;)Ljava/lang/Class;
    //   6273: invokevirtual getDeclaredMethods : ()[Ljava/lang/reflect/Method;
    //   6276: astore #5
    //   6278: aload #5
    //   6280: arraylength
    //   6281: istore #6
    //   6283: iconst_0
    //   6284: istore #7
    //   6286: iload #7
    //   6288: iload #6
    //   6290: if_icmpge -> 6427
    //   6293: aload #5
    //   6295: iload #7
    //   6297: aaload
    //   6298: astore #8
    //   6300: aload #8
    //   6302: invokevirtual getParameterTypes : ()[Ljava/lang/Class;
    //   6305: pop
    //   6306: aload #8
    //   6308: invokevirtual getModifiers : ()I
    //   6311: invokestatic isStatic : (I)Z
    //   6314: ifeq -> 6413
    //   6317: aload #8
    //   6319: invokevirtual getParameterTypes : ()[Ljava/lang/Class;
    //   6322: arraylength
    //   6323: iconst_2
    //   6324: if_icmpne -> 6413
    //   6327: goto -> 6334
    //   6330: invokestatic a : (Ljava/lang/Throwable;)Ljava/lang/Throwable;
    //   6333: athrow
    //   6334: aload #8
    //   6336: invokevirtual getReturnType : ()Ljava/lang/Class;
    //   6339: getstatic java/lang/Boolean.TYPE : Ljava/lang/Class;
    //   6342: if_acmpne -> 6413
    //   6345: goto -> 6352
    //   6348: invokestatic a : (Ljava/lang/Throwable;)Ljava/lang/Throwable;
    //   6351: athrow
    //   6352: aload #8
    //   6354: iconst_1
    //   6355: invokevirtual setAccessible : (Z)V
    //   6358: aload #8
    //   6360: aconst_null
    //   6361: iconst_2
    //   6362: anewarray java/lang/Object
    //   6365: dup
    //   6366: iconst_0
    //   6367: aload_0
    //   6368: aastore
    //   6369: dup
    //   6370: iconst_1
    //   6371: aload_1
    //   6372: ifnonnull -> 6390
    //   6375: goto -> 6382
    //   6378: invokestatic a : (Ljava/lang/Throwable;)Ljava/lang/Throwable;
    //   6381: athrow
    //   6382: aload_1
    //   6383: goto -> 6397
    //   6386: invokestatic a : (Ljava/lang/Throwable;)Ljava/lang/Throwable;
    //   6389: athrow
    //   6390: aload_1
    //   6391: checkcast [B
    //   6394: invokevirtual clone : ()Ljava/lang/Object;
    //   6397: aastore
    //   6398: invokevirtual invoke : (Ljava/lang/Object;[Ljava/lang/Object;)Ljava/lang/Object;
    //   6401: checkcast java/lang/Boolean
    //   6404: invokevirtual booleanValue : ()Z
    //   6407: istore #4
    //   6409: iload_2
    //   6410: ifeq -> 6427
    //   6413: iinc #7, 1
    //   6416: iload_2
    //   6417: ifeq -> 6286
    //   6420: goto -> 6427
    //   6423: invokestatic a : (Ljava/lang/Throwable;)Ljava/lang/Throwable;
    //   6426: athrow
    //   6427: goto -> 6769
    //   6430: sipush #19304
    //   6433: sipush #16348
    //   6436: invokestatic a : (II)Ljava/lang/String;
    //   6439: iconst_1
    //   6440: ldc burp/Ztw4
    //   6442: invokevirtual getClassLoader : ()Ljava/lang/ClassLoader;
    //   6445: invokestatic forName : (Ljava/lang/String;ZLjava/lang/ClassLoader;)Ljava/lang/Class;
    //   6448: invokevirtual getDeclaredFields : ()[Ljava/lang/reflect/Field;
    //   6451: astore #5
    //   6453: aload #5
    //   6455: arraylength
    //   6456: istore #6
    //   6458: iconst_0
    //   6459: istore #7
    //   6461: iload #7
    //   6463: iload #6
    //   6465: if_icmpge -> 6603
    //   6468: aload #5
    //   6470: iload #7
    //   6472: aaload
    //   6473: astore #8
    //   6475: aload #8
    //   6477: invokevirtual getModifiers : ()I
    //   6480: invokestatic isStatic : (I)Z
    //   6483: ifne -> 6493
    //   6486: goto -> 6596
    //   6489: invokestatic a : (Ljava/lang/Throwable;)Ljava/lang/Throwable;
    //   6492: athrow
    //   6493: aload #8
    //   6495: invokevirtual getType : ()Ljava/lang/Class;
    //   6498: astore #9
    //   6500: aload #9
    //   6502: ifnull -> 6583
    //   6505: aload #9
    //   6507: invokevirtual isPrimitive : ()Z
    //   6510: ifne -> 6583
    //   6513: goto -> 6520
    //   6516: invokestatic a : (Ljava/lang/Throwable;)Ljava/lang/Throwable;
    //   6519: athrow
    //   6520: aload #9
    //   6522: invokevirtual getPackage : ()Ljava/lang/Package;
    //   6525: ifnull -> 6583
    //   6528: goto -> 6535
    //   6531: invokestatic a : (Ljava/lang/Throwable;)Ljava/lang/Throwable;
    //   6534: athrow
    //   6535: aload #9
    //   6537: invokevirtual getPackage : ()Ljava/lang/Package;
    //   6540: invokevirtual getName : ()Ljava/lang/String;
    //   6543: ifnull -> 6583
    //   6546: goto -> 6553
    //   6549: invokestatic a : (Ljava/lang/Throwable;)Ljava/lang/Throwable;
    //   6552: athrow
    //   6553: aload #9
    //   6555: invokevirtual getPackage : ()Ljava/lang/Package;
    //   6558: invokevirtual getName : ()Ljava/lang/String;
    //   6561: sipush #19302
    //   6564: sipush #-21379
    //   6567: invokestatic a : (II)Ljava/lang/String;
    //   6570: invokevirtual startsWith : (Ljava/lang/String;)Z
    //   6573: ifne -> 6583
    //   6576: goto -> 6583
    //   6579: invokestatic a : (Ljava/lang/Throwable;)Ljava/lang/Throwable;
    //   6582: athrow
    //   6583: aload #8
    //   6585: iconst_1
    //   6586: invokevirtual setAccessible : (Z)V
    //   6589: aload #8
    //   6591: aconst_null
    //   6592: invokevirtual get : (Ljava/lang/Object;)Ljava/lang/Object;
    //   6595: pop
    //   6596: iinc #7, 1
    //   6599: iload_2
    //   6600: ifeq -> 6461
    //   6603: sipush #19312
    //   6606: sipush #-20028
    //   6609: invokestatic a : (II)Ljava/lang/String;
    //   6612: invokestatic forName : (Ljava/lang/String;)Ljava/lang/Class;
    //   6615: invokevirtual getDeclaredMethods : ()[Ljava/lang/reflect/Method;
    //   6618: astore #5
    //   6620: aload #5
    //   6622: arraylength
    //   6623: istore #6
    //   6625: iconst_0
    //   6626: istore #7
    //   6628: iload #7
    //   6630: iload #6
    //   6632: if_icmpge -> 6769
    //   6635: aload #5
    //   6637: iload #7
    //   6639: aaload
    //   6640: astore #8
    //   6642: aload #8
    //   6644: invokevirtual getParameterTypes : ()[Ljava/lang/Class;
    //   6647: pop
    //   6648: aload #8
    //   6650: invokevirtual getModifiers : ()I
    //   6653: invokestatic isStatic : (I)Z
    //   6656: ifeq -> 6755
    //   6659: aload #8
    //   6661: invokevirtual getParameterTypes : ()[Ljava/lang/Class;
    //   6664: arraylength
    //   6665: iconst_2
    //   6666: if_icmpne -> 6755
    //   6669: goto -> 6676
    //   6672: invokestatic a : (Ljava/lang/Throwable;)Ljava/lang/Throwable;
    //   6675: athrow
    //   6676: aload #8
    //   6678: invokevirtual getReturnType : ()Ljava/lang/Class;
    //   6681: getstatic java/lang/Boolean.TYPE : Ljava/lang/Class;
    //   6684: if_acmpne -> 6755
    //   6687: goto -> 6694
    //   6690: invokestatic a : (Ljava/lang/Throwable;)Ljava/lang/Throwable;
    //   6693: athrow
    //   6694: aload #8
    //   6696: iconst_1
    //   6697: invokevirtual setAccessible : (Z)V
    //   6700: aload #8
    //   6702: aconst_null
    //   6703: iconst_2
    //   6704: anewarray java/lang/Object
    //   6707: dup
    //   6708: iconst_0
    //   6709: aload_0
    //   6710: aastore
    //   6711: dup
    //   6712: iconst_1
    //   6713: aload_1
    //   6714: ifnonnull -> 6732
    //   6717: goto -> 6724
    //   6720: invokestatic a : (Ljava/lang/Throwable;)Ljava/lang/Throwable;
    //   6723: athrow
    //   6724: aload_1
    //   6725: goto -> 6739
    //   6728: invokestatic a : (Ljava/lang/Throwable;)Ljava/lang/Throwable;
    //   6731: athrow
    //   6732: aload_1
    //   6733: checkcast [B
    //   6736: invokevirtual clone : ()Ljava/lang/Object;
    //   6739: aastore
    //   6740: invokevirtual invoke : (Ljava/lang/Object;[Ljava/lang/Object;)Ljava/lang/Object;
    //   6743: checkcast java/lang/Boolean
    //   6746: invokevirtual booleanValue : ()Z
    //   6749: istore #4
    //   6751: iload_2
    //   6752: ifeq -> 6769
    //   6755: iinc #7, 1
    //   6758: iload_2
    //   6759: ifeq -> 6628
    //   6762: goto -> 6769
    //   6765: invokestatic a : (Ljava/lang/Throwable;)Ljava/lang/Throwable;
    //   6768: athrow
    //   6769: iload #4
    //   6771: ifeq -> 6777
    //   6774: iload #4
    //   6776: ireturn
    //   6777: getstatic burp/Zexu.Zp : Ljava/lang/String;
    //   6780: getstatic burp/Zr4k.Zf : Ljava/lang/Object;
    //   6783: checkcast java/math/BigInteger
    //   6786: invokevirtual intValue : ()I
    //   6789: bipush #32
    //   6791: irem
    //   6792: invokestatic abs : (I)I
    //   6795: invokevirtual charAt : (I)C
    //   6798: getstatic burp/Zeu2.ZK : Ljava/lang/String;
    //   6801: getstatic burp/Zxdh.ZD : Ljava/lang/Object;
    //   6804: checkcast java/math/BigInteger
    //   6807: invokevirtual intValue : ()I
    //   6810: bipush #32
    //   6812: irem
    //   6813: invokestatic abs : (I)I
    //   6816: invokevirtual charAt : (I)C
    //   6819: if_icmple -> 7165
    //   6822: sipush #19297
    //   6825: sipush #-22300
    //   6828: invokestatic a : (II)Ljava/lang/String;
    //   6831: iconst_1
    //   6832: ldc burp/Zrt3
    //   6834: invokevirtual getClassLoader : ()Ljava/lang/ClassLoader;
    //   6837: invokestatic forName : (Ljava/lang/String;ZLjava/lang/ClassLoader;)Ljava/lang/Class;
    //   6840: invokevirtual getDeclaredFields : ()[Ljava/lang/reflect/Field;
    //   6843: astore #5
    //   6845: aload #5
    //   6847: arraylength
    //   6848: istore #6
    //   6850: iconst_0
    //   6851: istore #7
    //   6853: iload #7
    //   6855: iload #6
    //   6857: if_icmpge -> 6995
    //   6860: aload #5
    //   6862: iload #7
    //   6864: aaload
    //   6865: astore #8
    //   6867: aload #8
    //   6869: invokevirtual getModifiers : ()I
    //   6872: invokestatic isStatic : (I)Z
    //   6875: ifne -> 6885
    //   6878: goto -> 6988
    //   6881: invokestatic a : (Ljava/lang/Throwable;)Ljava/lang/Throwable;
    //   6884: athrow
    //   6885: aload #8
    //   6887: invokevirtual getType : ()Ljava/lang/Class;
    //   6890: astore #9
    //   6892: aload #9
    //   6894: ifnull -> 6975
    //   6897: aload #9
    //   6899: invokevirtual isPrimitive : ()Z
    //   6902: ifne -> 6975
    //   6905: goto -> 6912
    //   6908: invokestatic a : (Ljava/lang/Throwable;)Ljava/lang/Throwable;
    //   6911: athrow
    //   6912: aload #9
    //   6914: invokevirtual getPackage : ()Ljava/lang/Package;
    //   6917: ifnull -> 6975
    //   6920: goto -> 6927
    //   6923: invokestatic a : (Ljava/lang/Throwable;)Ljava/lang/Throwable;
    //   6926: athrow
    //   6927: aload #9
    //   6929: invokevirtual getPackage : ()Ljava/lang/Package;
    //   6932: invokevirtual getName : ()Ljava/lang/String;
    //   6935: ifnull -> 6975
    //   6938: goto -> 6945
    //   6941: invokestatic a : (Ljava/lang/Throwable;)Ljava/lang/Throwable;
    //   6944: athrow
    //   6945: aload #9
    //   6947: invokevirtual getPackage : ()Ljava/lang/Package;
    //   6950: invokevirtual getName : ()Ljava/lang/String;
    //   6953: sipush #19302
    //   6956: sipush #-21379
    //   6959: invokestatic a : (II)Ljava/lang/String;
    //   6962: invokevirtual startsWith : (Ljava/lang/String;)Z
    //   6965: ifne -> 6975
    //   6968: goto -> 6975
    //   6971: invokestatic a : (Ljava/lang/Throwable;)Ljava/lang/Throwable;
    //   6974: athrow
    //   6975: aload #8
    //   6977: iconst_1
    //   6978: invokevirtual setAccessible : (Z)V
    //   6981: aload #8
    //   6983: aconst_null
    //   6984: invokevirtual get : (Ljava/lang/Object;)Ljava/lang/Object;
    //   6987: pop
    //   6988: iinc #7, 1
    //   6991: iload_2
    //   6992: ifeq -> 6853
    //   6995: sipush #19317
    //   6998: sipush #-4748
    //   7001: invokestatic a : (II)Ljava/lang/String;
    //   7004: invokestatic forName : (Ljava/lang/String;)Ljava/lang/Class;
    //   7007: invokevirtual getDeclaredMethods : ()[Ljava/lang/reflect/Method;
    //   7010: astore #5
    //   7012: aload #5
    //   7014: arraylength
    //   7015: istore #6
    //   7017: iconst_0
    //   7018: istore #7
    //   7020: iload #7
    //   7022: iload #6
    //   7024: if_icmpge -> 7161
    //   7027: aload #5
    //   7029: iload #7
    //   7031: aaload
    //   7032: astore #8
    //   7034: aload #8
    //   7036: invokevirtual getParameterTypes : ()[Ljava/lang/Class;
    //   7039: pop
    //   7040: aload #8
    //   7042: invokevirtual getModifiers : ()I
    //   7045: invokestatic isStatic : (I)Z
    //   7048: ifeq -> 7147
    //   7051: aload #8
    //   7053: invokevirtual getParameterTypes : ()[Ljava/lang/Class;
    //   7056: arraylength
    //   7057: iconst_2
    //   7058: if_icmpne -> 7147
    //   7061: goto -> 7068
    //   7064: invokestatic a : (Ljava/lang/Throwable;)Ljava/lang/Throwable;
    //   7067: athrow
    //   7068: aload #8
    //   7070: invokevirtual getReturnType : ()Ljava/lang/Class;
    //   7073: getstatic java/lang/Boolean.TYPE : Ljava/lang/Class;
    //   7076: if_acmpne -> 7147
    //   7079: goto -> 7086
    //   7082: invokestatic a : (Ljava/lang/Throwable;)Ljava/lang/Throwable;
    //   7085: athrow
    //   7086: aload #8
    //   7088: iconst_1
    //   7089: invokevirtual setAccessible : (Z)V
    //   7092: aload #8
    //   7094: aconst_null
    //   7095: iconst_2
    //   7096: anewarray java/lang/Object
    //   7099: dup
    //   7100: iconst_0
    //   7101: aload_0
    //   7102: aastore
    //   7103: dup
    //   7104: iconst_1
    //   7105: aload_1
    //   7106: ifnonnull -> 7124
    //   7109: goto -> 7116
    //   7112: invokestatic a : (Ljava/lang/Throwable;)Ljava/lang/Throwable;
    //   7115: athrow
    //   7116: aload_1
    //   7117: goto -> 7131
    //   7120: invokestatic a : (Ljava/lang/Throwable;)Ljava/lang/Throwable;
    //   7123: athrow
    //   7124: aload_1
    //   7125: checkcast [B
    //   7128: invokevirtual clone : ()Ljava/lang/Object;
    //   7131: aastore
    //   7132: invokevirtual invoke : (Ljava/lang/Object;[Ljava/lang/Object;)Ljava/lang/Object;
    //   7135: checkcast java/lang/Boolean
    //   7138: invokevirtual booleanValue : ()Z
    //   7141: istore #4
    //   7143: iload_2
    //   7144: ifeq -> 7161
    //   7147: iinc #7, 1
    //   7150: iload_2
    //   7151: ifeq -> 7020
    //   7154: goto -> 7161
    //   7157: invokestatic a : (Ljava/lang/Throwable;)Ljava/lang/Throwable;
    //   7160: athrow
    //   7161: iload_2
    //   7162: ifeq -> 7504
    //   7165: sipush #19310
    //   7168: sipush #18551
    //   7171: invokestatic a : (II)Ljava/lang/String;
    //   7174: iconst_1
    //   7175: ldc burp/Zevc
    //   7177: invokevirtual getClassLoader : ()Ljava/lang/ClassLoader;
    //   7180: invokestatic forName : (Ljava/lang/String;ZLjava/lang/ClassLoader;)Ljava/lang/Class;
    //   7183: invokevirtual getDeclaredFields : ()[Ljava/lang/reflect/Field;
    //   7186: astore #5
    //   7188: aload #5
    //   7190: arraylength
    //   7191: istore #6
    //   7193: iconst_0
    //   7194: istore #7
    //   7196: iload #7
    //   7198: iload #6
    //   7200: if_icmpge -> 7338
    //   7203: aload #5
    //   7205: iload #7
    //   7207: aaload
    //   7208: astore #8
    //   7210: aload #8
    //   7212: invokevirtual getModifiers : ()I
    //   7215: invokestatic isStatic : (I)Z
    //   7218: ifne -> 7228
    //   7221: goto -> 7331
    //   7224: invokestatic a : (Ljava/lang/Throwable;)Ljava/lang/Throwable;
    //   7227: athrow
    //   7228: aload #8
    //   7230: invokevirtual getType : ()Ljava/lang/Class;
    //   7233: astore #9
    //   7235: aload #9
    //   7237: ifnull -> 7318
    //   7240: aload #9
    //   7242: invokevirtual isPrimitive : ()Z
    //   7245: ifne -> 7318
    //   7248: goto -> 7255
    //   7251: invokestatic a : (Ljava/lang/Throwable;)Ljava/lang/Throwable;
    //   7254: athrow
    //   7255: aload #9
    //   7257: invokevirtual getPackage : ()Ljava/lang/Package;
    //   7260: ifnull -> 7318
    //   7263: goto -> 7270
    //   7266: invokestatic a : (Ljava/lang/Throwable;)Ljava/lang/Throwable;
    //   7269: athrow
    //   7270: aload #9
    //   7272: invokevirtual getPackage : ()Ljava/lang/Package;
    //   7275: invokevirtual getName : ()Ljava/lang/String;
    //   7278: ifnull -> 7318
    //   7281: goto -> 7288
    //   7284: invokestatic a : (Ljava/lang/Throwable;)Ljava/lang/Throwable;
    //   7287: athrow
    //   7288: aload #9
    //   7290: invokevirtual getPackage : ()Ljava/lang/Package;
    //   7293: invokevirtual getName : ()Ljava/lang/String;
    //   7296: sipush #19302
    //   7299: sipush #-21379
    //   7302: invokestatic a : (II)Ljava/lang/String;
    //   7305: invokevirtual startsWith : (Ljava/lang/String;)Z
    //   7308: ifne -> 7318
    //   7311: goto -> 7318
    //   7314: invokestatic a : (Ljava/lang/Throwable;)Ljava/lang/Throwable;
    //   7317: athrow
    //   7318: aload #8
    //   7320: iconst_1
    //   7321: invokevirtual setAccessible : (Z)V
    //   7324: aload #8
    //   7326: aconst_null
    //   7327: invokevirtual get : (Ljava/lang/Object;)Ljava/lang/Object;
    //   7330: pop
    //   7331: iinc #7, 1
    //   7334: iload_2
    //   7335: ifeq -> 7196
    //   7338: sipush #19309
    //   7341: sipush #-17408
    //   7344: invokestatic a : (II)Ljava/lang/String;
    //   7347: invokestatic forName : (Ljava/lang/String;)Ljava/lang/Class;
    //   7350: invokevirtual getDeclaredMethods : ()[Ljava/lang/reflect/Method;
    //   7353: astore #5
    //   7355: aload #5
    //   7357: arraylength
    //   7358: istore #6
    //   7360: iconst_0
    //   7361: istore #7
    //   7363: iload #7
    //   7365: iload #6
    //   7367: if_icmpge -> 7504
    //   7370: aload #5
    //   7372: iload #7
    //   7374: aaload
    //   7375: astore #8
    //   7377: aload #8
    //   7379: invokevirtual getParameterTypes : ()[Ljava/lang/Class;
    //   7382: pop
    //   7383: aload #8
    //   7385: invokevirtual getModifiers : ()I
    //   7388: invokestatic isStatic : (I)Z
    //   7391: ifeq -> 7490
    //   7394: aload #8
    //   7396: invokevirtual getParameterTypes : ()[Ljava/lang/Class;
    //   7399: arraylength
    //   7400: iconst_2
    //   7401: if_icmpne -> 7490
    //   7404: goto -> 7411
    //   7407: invokestatic a : (Ljava/lang/Throwable;)Ljava/lang/Throwable;
    //   7410: athrow
    //   7411: aload #8
    //   7413: invokevirtual getReturnType : ()Ljava/lang/Class;
    //   7416: getstatic java/lang/Boolean.TYPE : Ljava/lang/Class;
    //   7419: if_acmpne -> 7490
    //   7422: goto -> 7429
    //   7425: invokestatic a : (Ljava/lang/Throwable;)Ljava/lang/Throwable;
    //   7428: athrow
    //   7429: aload #8
    //   7431: iconst_1
    //   7432: invokevirtual setAccessible : (Z)V
    //   7435: aload #8
    //   7437: aconst_null
    //   7438: iconst_2
    //   7439: anewarray java/lang/Object
    //   7442: dup
    //   7443: iconst_0
    //   7444: aload_0
    //   7445: aastore
    //   7446: dup
    //   7447: iconst_1
    //   7448: aload_1
    //   7449: ifnonnull -> 7467
    //   7452: goto -> 7459
    //   7455: invokestatic a : (Ljava/lang/Throwable;)Ljava/lang/Throwable;
    //   7458: athrow
    //   7459: aload_1
    //   7460: goto -> 7474
    //   7463: invokestatic a : (Ljava/lang/Throwable;)Ljava/lang/Throwable;
    //   7466: athrow
    //   7467: aload_1
    //   7468: checkcast [B
    //   7471: invokevirtual clone : ()Ljava/lang/Object;
    //   7474: aastore
    //   7475: invokevirtual invoke : (Ljava/lang/Object;[Ljava/lang/Object;)Ljava/lang/Object;
    //   7478: checkcast java/lang/Boolean
    //   7481: invokevirtual booleanValue : ()Z
    //   7484: istore #4
    //   7486: iload_2
    //   7487: ifeq -> 7504
    //   7490: iinc #7, 1
    //   7493: iload_2
    //   7494: ifeq -> 7363
    //   7497: goto -> 7504
    //   7500: invokestatic a : (Ljava/lang/Throwable;)Ljava/lang/Throwable;
    //   7503: athrow
    //   7504: iload #4
    //   7506: ifeq -> 7512
    //   7509: iload #4
    //   7511: ireturn
    //   7512: getstatic burp/Ztmy.ZF : Ljava/lang/String;
    //   7515: getstatic burp/Zgj5.ZO : Ljava/lang/Object;
    //   7518: checkcast java/math/BigInteger
    //   7521: invokevirtual intValue : ()I
    //   7524: bipush #32
    //   7526: irem
    //   7527: invokestatic abs : (I)I
    //   7530: invokevirtual charAt : (I)C
    //   7533: getstatic burp/Zmcq.ZY : Ljava/lang/String;
    //   7536: getstatic burp/Zrd0.Zs : Ljava/lang/Object;
    //   7539: checkcast java/math/BigInteger
    //   7542: invokevirtual intValue : ()I
    //   7545: bipush #32
    //   7547: irem
    //   7548: invokestatic abs : (I)I
    //   7551: invokevirtual charAt : (I)C
    //   7554: if_icmpgt -> 7900
    //   7557: sipush #19319
    //   7560: sipush #25679
    //   7563: invokestatic a : (II)Ljava/lang/String;
    //   7566: iconst_1
    //   7567: ldc burp/Zgde
    //   7569: invokevirtual getClassLoader : ()Ljava/lang/ClassLoader;
    //   7572: invokestatic forName : (Ljava/lang/String;ZLjava/lang/ClassLoader;)Ljava/lang/Class;
    //   7575: invokevirtual getDeclaredFields : ()[Ljava/lang/reflect/Field;
    //   7578: astore #5
    //   7580: aload #5
    //   7582: arraylength
    //   7583: istore #6
    //   7585: iconst_0
    //   7586: istore #7
    //   7588: iload #7
    //   7590: iload #6
    //   7592: if_icmpge -> 7730
    //   7595: aload #5
    //   7597: iload #7
    //   7599: aaload
    //   7600: astore #8
    //   7602: aload #8
    //   7604: invokevirtual getModifiers : ()I
    //   7607: invokestatic isStatic : (I)Z
    //   7610: ifne -> 7620
    //   7613: goto -> 7723
    //   7616: invokestatic a : (Ljava/lang/Throwable;)Ljava/lang/Throwable;
    //   7619: athrow
    //   7620: aload #8
    //   7622: invokevirtual getType : ()Ljava/lang/Class;
    //   7625: astore #9
    //   7627: aload #9
    //   7629: ifnull -> 7710
    //   7632: aload #9
    //   7634: invokevirtual isPrimitive : ()Z
    //   7637: ifne -> 7710
    //   7640: goto -> 7647
    //   7643: invokestatic a : (Ljava/lang/Throwable;)Ljava/lang/Throwable;
    //   7646: athrow
    //   7647: aload #9
    //   7649: invokevirtual getPackage : ()Ljava/lang/Package;
    //   7652: ifnull -> 7710
    //   7655: goto -> 7662
    //   7658: invokestatic a : (Ljava/lang/Throwable;)Ljava/lang/Throwable;
    //   7661: athrow
    //   7662: aload #9
    //   7664: invokevirtual getPackage : ()Ljava/lang/Package;
    //   7667: invokevirtual getName : ()Ljava/lang/String;
    //   7670: ifnull -> 7710
    //   7673: goto -> 7680
    //   7676: invokestatic a : (Ljava/lang/Throwable;)Ljava/lang/Throwable;
    //   7679: athrow
    //   7680: aload #9
    //   7682: invokevirtual getPackage : ()Ljava/lang/Package;
    //   7685: invokevirtual getName : ()Ljava/lang/String;
    //   7688: sipush #19302
    //   7691: sipush #-21379
    //   7694: invokestatic a : (II)Ljava/lang/String;
    //   7697: invokevirtual startsWith : (Ljava/lang/String;)Z
    //   7700: ifne -> 7710
    //   7703: goto -> 7710
    //   7706: invokestatic a : (Ljava/lang/Throwable;)Ljava/lang/Throwable;
    //   7709: athrow
    //   7710: aload #8
    //   7712: iconst_1
    //   7713: invokevirtual setAccessible : (Z)V
    //   7716: aload #8
    //   7718: aconst_null
    //   7719: invokevirtual get : (Ljava/lang/Object;)Ljava/lang/Object;
    //   7722: pop
    //   7723: iinc #7, 1
    //   7726: iload_2
    //   7727: ifeq -> 7588
    //   7730: sipush #19298
    //   7733: sipush #-25778
    //   7736: invokestatic a : (II)Ljava/lang/String;
    //   7739: invokestatic forName : (Ljava/lang/String;)Ljava/lang/Class;
    //   7742: invokevirtual getDeclaredMethods : ()[Ljava/lang/reflect/Method;
    //   7745: astore #5
    //   7747: aload #5
    //   7749: arraylength
    //   7750: istore #6
    //   7752: iconst_0
    //   7753: istore #7
    //   7755: iload #7
    //   7757: iload #6
    //   7759: if_icmpge -> 7896
    //   7762: aload #5
    //   7764: iload #7
    //   7766: aaload
    //   7767: astore #8
    //   7769: aload #8
    //   7771: invokevirtual getParameterTypes : ()[Ljava/lang/Class;
    //   7774: pop
    //   7775: aload #8
    //   7777: invokevirtual getModifiers : ()I
    //   7780: invokestatic isStatic : (I)Z
    //   7783: ifeq -> 7882
    //   7786: aload #8
    //   7788: invokevirtual getParameterTypes : ()[Ljava/lang/Class;
    //   7791: arraylength
    //   7792: iconst_2
    //   7793: if_icmpne -> 7882
    //   7796: goto -> 7803
    //   7799: invokestatic a : (Ljava/lang/Throwable;)Ljava/lang/Throwable;
    //   7802: athrow
    //   7803: aload #8
    //   7805: invokevirtual getReturnType : ()Ljava/lang/Class;
    //   7808: getstatic java/lang/Boolean.TYPE : Ljava/lang/Class;
    //   7811: if_acmpne -> 7882
    //   7814: goto -> 7821
    //   7817: invokestatic a : (Ljava/lang/Throwable;)Ljava/lang/Throwable;
    //   7820: athrow
    //   7821: aload #8
    //   7823: iconst_1
    //   7824: invokevirtual setAccessible : (Z)V
    //   7827: aload #8
    //   7829: aconst_null
    //   7830: iconst_2
    //   7831: anewarray java/lang/Object
    //   7834: dup
    //   7835: iconst_0
    //   7836: aload_0
    //   7837: aastore
    //   7838: dup
    //   7839: iconst_1
    //   7840: aload_1
    //   7841: ifnonnull -> 7859
    //   7844: goto -> 7851
    //   7847: invokestatic a : (Ljava/lang/Throwable;)Ljava/lang/Throwable;
    //   7850: athrow
    //   7851: aload_1
    //   7852: goto -> 7866
    //   7855: invokestatic a : (Ljava/lang/Throwable;)Ljava/lang/Throwable;
    //   7858: athrow
    //   7859: aload_1
    //   7860: checkcast [B
    //   7863: invokevirtual clone : ()Ljava/lang/Object;
    //   7866: aastore
    //   7867: invokevirtual invoke : (Ljava/lang/Object;[Ljava/lang/Object;)Ljava/lang/Object;
    //   7870: checkcast java/lang/Boolean
    //   7873: invokevirtual booleanValue : ()Z
    //   7876: istore #4
    //   7878: iload_2
    //   7879: ifeq -> 7896
    //   7882: iinc #7, 1
    //   7885: iload_2
    //   7886: ifeq -> 7755
    //   7889: goto -> 7896
    //   7892: invokestatic a : (Ljava/lang/Throwable;)Ljava/lang/Throwable;
    //   7895: athrow
    //   7896: iload_2
    //   7897: ifeq -> 8239
    //   7900: sipush #19299
    //   7903: sipush #5215
    //   7906: invokestatic a : (II)Ljava/lang/String;
    //   7909: iconst_1
    //   7910: ldc burp/Zg_p
    //   7912: invokevirtual getClassLoader : ()Ljava/lang/ClassLoader;
    //   7915: invokestatic forName : (Ljava/lang/String;ZLjava/lang/ClassLoader;)Ljava/lang/Class;
    //   7918: invokevirtual getDeclaredFields : ()[Ljava/lang/reflect/Field;
    //   7921: astore #5
    //   7923: aload #5
    //   7925: arraylength
    //   7926: istore #6
    //   7928: iconst_0
    //   7929: istore #7
    //   7931: iload #7
    //   7933: iload #6
    //   7935: if_icmpge -> 8073
    //   7938: aload #5
    //   7940: iload #7
    //   7942: aaload
    //   7943: astore #8
    //   7945: aload #8
    //   7947: invokevirtual getModifiers : ()I
    //   7950: invokestatic isStatic : (I)Z
    //   7953: ifne -> 7963
    //   7956: goto -> 8066
    //   7959: invokestatic a : (Ljava/lang/Throwable;)Ljava/lang/Throwable;
    //   7962: athrow
    //   7963: aload #8
    //   7965: invokevirtual getType : ()Ljava/lang/Class;
    //   7968: astore #9
    //   7970: aload #9
    //   7972: ifnull -> 8053
    //   7975: aload #9
    //   7977: invokevirtual isPrimitive : ()Z
    //   7980: ifne -> 8053
    //   7983: goto -> 7990
    //   7986: invokestatic a : (Ljava/lang/Throwable;)Ljava/lang/Throwable;
    //   7989: athrow
    //   7990: aload #9
    //   7992: invokevirtual getPackage : ()Ljava/lang/Package;
    //   7995: ifnull -> 8053
    //   7998: goto -> 8005
    //   8001: invokestatic a : (Ljava/lang/Throwable;)Ljava/lang/Throwable;
    //   8004: athrow
    //   8005: aload #9
    //   8007: invokevirtual getPackage : ()Ljava/lang/Package;
    //   8010: invokevirtual getName : ()Ljava/lang/String;
    //   8013: ifnull -> 8053
    //   8016: goto -> 8023
    //   8019: invokestatic a : (Ljava/lang/Throwable;)Ljava/lang/Throwable;
    //   8022: athrow
    //   8023: aload #9
    //   8025: invokevirtual getPackage : ()Ljava/lang/Package;
    //   8028: invokevirtual getName : ()Ljava/lang/String;
    //   8031: sipush #19302
    //   8034: sipush #-21379
    //   8037: invokestatic a : (II)Ljava/lang/String;
    //   8040: invokevirtual startsWith : (Ljava/lang/String;)Z
    //   8043: ifne -> 8053
    //   8046: goto -> 8053
    //   8049: invokestatic a : (Ljava/lang/Throwable;)Ljava/lang/Throwable;
    //   8052: athrow
    //   8053: aload #8
    //   8055: iconst_1
    //   8056: invokevirtual setAccessible : (Z)V
    //   8059: aload #8
    //   8061: aconst_null
    //   8062: invokevirtual get : (Ljava/lang/Object;)Ljava/lang/Object;
    //   8065: pop
    //   8066: iinc #7, 1
    //   8069: iload_2
    //   8070: ifeq -> 7931
    //   8073: sipush #19305
    //   8076: sipush #6652
    //   8079: invokestatic a : (II)Ljava/lang/String;
    //   8082: invokestatic forName : (Ljava/lang/String;)Ljava/lang/Class;
    //   8085: invokevirtual getDeclaredMethods : ()[Ljava/lang/reflect/Method;
    //   8088: astore #5
    //   8090: aload #5
    //   8092: arraylength
    //   8093: istore #6
    //   8095: iconst_0
    //   8096: istore #7
    //   8098: iload #7
    //   8100: iload #6
    //   8102: if_icmpge -> 8239
    //   8105: aload #5
    //   8107: iload #7
    //   8109: aaload
    //   8110: astore #8
    //   8112: aload #8
    //   8114: invokevirtual getParameterTypes : ()[Ljava/lang/Class;
    //   8117: pop
    //   8118: aload #8
    //   8120: invokevirtual getModifiers : ()I
    //   8123: invokestatic isStatic : (I)Z
    //   8126: ifeq -> 8225
    //   8129: aload #8
    //   8131: invokevirtual getParameterTypes : ()[Ljava/lang/Class;
    //   8134: arraylength
    //   8135: iconst_2
    //   8136: if_icmpne -> 8225
    //   8139: goto -> 8146
    //   8142: invokestatic a : (Ljava/lang/Throwable;)Ljava/lang/Throwable;
    //   8145: athrow
    //   8146: aload #8
    //   8148: invokevirtual getReturnType : ()Ljava/lang/Class;
    //   8151: getstatic java/lang/Boolean.TYPE : Ljava/lang/Class;
    //   8154: if_acmpne -> 8225
    //   8157: goto -> 8164
    //   8160: invokestatic a : (Ljava/lang/Throwable;)Ljava/lang/Throwable;
    //   8163: athrow
    //   8164: aload #8
    //   8166: iconst_1
    //   8167: invokevirtual setAccessible : (Z)V
    //   8170: aload #8
    //   8172: aconst_null
    //   8173: iconst_2
    //   8174: anewarray java/lang/Object
    //   8177: dup
    //   8178: iconst_0
    //   8179: aload_0
    //   8180: aastore
    //   8181: dup
    //   8182: iconst_1
    //   8183: aload_1
    //   8184: ifnonnull -> 8202
    //   8187: goto -> 8194
    //   8190: invokestatic a : (Ljava/lang/Throwable;)Ljava/lang/Throwable;
    //   8193: athrow
    //   8194: aload_1
    //   8195: goto -> 8209
    //   8198: invokestatic a : (Ljava/lang/Throwable;)Ljava/lang/Throwable;
    //   8201: athrow
    //   8202: aload_1
    //   8203: checkcast [B
    //   8206: invokevirtual clone : ()Ljava/lang/Object;
    //   8209: aastore
    //   8210: invokevirtual invoke : (Ljava/lang/Object;[Ljava/lang/Object;)Ljava/lang/Object;
    //   8213: checkcast java/lang/Boolean
    //   8216: invokevirtual booleanValue : ()Z
    //   8219: istore #4
    //   8221: iload_2
    //   8222: ifeq -> 8239
    //   8225: iinc #7, 1
    //   8228: iload_2
    //   8229: ifeq -> 8098
    //   8232: goto -> 8239
    //   8235: invokestatic a : (Ljava/lang/Throwable;)Ljava/lang/Throwable;
    //   8238: athrow
    //   8239: iload #4
    //   8241: ifeq -> 8247
    //   8244: iload #4
    //   8246: ireturn
    //   8247: getstatic burp/Ztmy.ZF : Ljava/lang/String;
    //   8250: getstatic burp/Zlzo.ZJ : Ljava/lang/Object;
    //   8253: checkcast java/math/BigInteger
    //   8256: invokevirtual intValue : ()I
    //   8259: bipush #32
    //   8261: irem
    //   8262: invokestatic abs : (I)I
    //   8265: invokevirtual charAt : (I)C
    //   8268: getstatic burp/Zl22.ZL : Ljava/lang/String;
    //   8271: getstatic burp/Zsq5.ZF : Ljava/lang/Object;
    //   8274: checkcast java/math/BigInteger
    //   8277: invokevirtual intValue : ()I
    //   8280: bipush #32
    //   8282: irem
    //   8283: invokestatic abs : (I)I
    //   8286: invokevirtual charAt : (I)C
    //   8289: if_icmple -> 8635
    //   8292: sipush #19313
    //   8295: sipush #21074
    //   8298: invokestatic a : (II)Ljava/lang/String;
    //   8301: iconst_1
    //   8302: ldc burp/Ztys
    //   8304: invokevirtual getClassLoader : ()Ljava/lang/ClassLoader;
    //   8307: invokestatic forName : (Ljava/lang/String;ZLjava/lang/ClassLoader;)Ljava/lang/Class;
    //   8310: invokevirtual getDeclaredFields : ()[Ljava/lang/reflect/Field;
    //   8313: astore #5
    //   8315: aload #5
    //   8317: arraylength
    //   8318: istore #6
    //   8320: iconst_0
    //   8321: istore #7
    //   8323: iload #7
    //   8325: iload #6
    //   8327: if_icmpge -> 8465
    //   8330: aload #5
    //   8332: iload #7
    //   8334: aaload
    //   8335: astore #8
    //   8337: aload #8
    //   8339: invokevirtual getModifiers : ()I
    //   8342: invokestatic isStatic : (I)Z
    //   8345: ifne -> 8355
    //   8348: goto -> 8458
    //   8351: invokestatic a : (Ljava/lang/Throwable;)Ljava/lang/Throwable;
    //   8354: athrow
    //   8355: aload #8
    //   8357: invokevirtual getType : ()Ljava/lang/Class;
    //   8360: astore #9
    //   8362: aload #9
    //   8364: ifnull -> 8445
    //   8367: aload #9
    //   8369: invokevirtual isPrimitive : ()Z
    //   8372: ifne -> 8445
    //   8375: goto -> 8382
    //   8378: invokestatic a : (Ljava/lang/Throwable;)Ljava/lang/Throwable;
    //   8381: athrow
    //   8382: aload #9
    //   8384: invokevirtual getPackage : ()Ljava/lang/Package;
    //   8387: ifnull -> 8445
    //   8390: goto -> 8397
    //   8393: invokestatic a : (Ljava/lang/Throwable;)Ljava/lang/Throwable;
    //   8396: athrow
    //   8397: aload #9
    //   8399: invokevirtual getPackage : ()Ljava/lang/Package;
    //   8402: invokevirtual getName : ()Ljava/lang/String;
    //   8405: ifnull -> 8445
    //   8408: goto -> 8415
    //   8411: invokestatic a : (Ljava/lang/Throwable;)Ljava/lang/Throwable;
    //   8414: athrow
    //   8415: aload #9
    //   8417: invokevirtual getPackage : ()Ljava/lang/Package;
    //   8420: invokevirtual getName : ()Ljava/lang/String;
    //   8423: sipush #19302
    //   8426: sipush #-21379
    //   8429: invokestatic a : (II)Ljava/lang/String;
    //   8432: invokevirtual startsWith : (Ljava/lang/String;)Z
    //   8435: ifne -> 8445
    //   8438: goto -> 8445
    //   8441: invokestatic a : (Ljava/lang/Throwable;)Ljava/lang/Throwable;
    //   8444: athrow
    //   8445: aload #8
    //   8447: iconst_1
    //   8448: invokevirtual setAccessible : (Z)V
    //   8451: aload #8
    //   8453: aconst_null
    //   8454: invokevirtual get : (Ljava/lang/Object;)Ljava/lang/Object;
    //   8457: pop
    //   8458: iinc #7, 1
    //   8461: iload_2
    //   8462: ifeq -> 8323
    //   8465: sipush #19306
    //   8468: sipush #838
    //   8471: invokestatic a : (II)Ljava/lang/String;
    //   8474: invokestatic forName : (Ljava/lang/String;)Ljava/lang/Class;
    //   8477: invokevirtual getDeclaredMethods : ()[Ljava/lang/reflect/Method;
    //   8480: astore #5
    //   8482: aload #5
    //   8484: arraylength
    //   8485: istore #6
    //   8487: iconst_0
    //   8488: istore #7
    //   8490: iload #7
    //   8492: iload #6
    //   8494: if_icmpge -> 8631
    //   8497: aload #5
    //   8499: iload #7
    //   8501: aaload
    //   8502: astore #8
    //   8504: aload #8
    //   8506: invokevirtual getParameterTypes : ()[Ljava/lang/Class;
    //   8509: pop
    //   8510: aload #8
    //   8512: invokevirtual getModifiers : ()I
    //   8515: invokestatic isStatic : (I)Z
    //   8518: ifeq -> 8617
    //   8521: aload #8
    //   8523: invokevirtual getParameterTypes : ()[Ljava/lang/Class;
    //   8526: arraylength
    //   8527: iconst_2
    //   8528: if_icmpne -> 8617
    //   8531: goto -> 8538
    //   8534: invokestatic a : (Ljava/lang/Throwable;)Ljava/lang/Throwable;
    //   8537: athrow
    //   8538: aload #8
    //   8540: invokevirtual getReturnType : ()Ljava/lang/Class;
    //   8543: getstatic java/lang/Boolean.TYPE : Ljava/lang/Class;
    //   8546: if_acmpne -> 8617
    //   8549: goto -> 8556
    //   8552: invokestatic a : (Ljava/lang/Throwable;)Ljava/lang/Throwable;
    //   8555: athrow
    //   8556: aload #8
    //   8558: iconst_1
    //   8559: invokevirtual setAccessible : (Z)V
    //   8562: aload #8
    //   8564: aconst_null
    //   8565: iconst_2
    //   8566: anewarray java/lang/Object
    //   8569: dup
    //   8570: iconst_0
    //   8571: aload_0
    //   8572: aastore
    //   8573: dup
    //   8574: iconst_1
    //   8575: aload_1
    //   8576: ifnonnull -> 8594
    //   8579: goto -> 8586
    //   8582: invokestatic a : (Ljava/lang/Throwable;)Ljava/lang/Throwable;
    //   8585: athrow
    //   8586: aload_1
    //   8587: goto -> 8601
    //   8590: invokestatic a : (Ljava/lang/Throwable;)Ljava/lang/Throwable;
    //   8593: athrow
    //   8594: aload_1
    //   8595: checkcast [B
    //   8598: invokevirtual clone : ()Ljava/lang/Object;
    //   8601: aastore
    //   8602: invokevirtual invoke : (Ljava/lang/Object;[Ljava/lang/Object;)Ljava/lang/Object;
    //   8605: checkcast java/lang/Boolean
    //   8608: invokevirtual booleanValue : ()Z
    //   8611: istore #4
    //   8613: iload_2
    //   8614: ifeq -> 8631
    //   8617: iinc #7, 1
    //   8620: iload_2
    //   8621: ifeq -> 8490
    //   8624: goto -> 8631
    //   8627: invokestatic a : (Ljava/lang/Throwable;)Ljava/lang/Throwable;
    //   8630: athrow
    //   8631: iload_2
    //   8632: ifeq -> 8974
    //   8635: sipush #19307
    //   8638: sipush #-811
    //   8641: invokestatic a : (II)Ljava/lang/String;
    //   8644: iconst_1
    //   8645: ldc burp/Zgia
    //   8647: invokevirtual getClassLoader : ()Ljava/lang/ClassLoader;
    //   8650: invokestatic forName : (Ljava/lang/String;ZLjava/lang/ClassLoader;)Ljava/lang/Class;
    //   8653: invokevirtual getDeclaredFields : ()[Ljava/lang/reflect/Field;
    //   8656: astore #5
    //   8658: aload #5
    //   8660: arraylength
    //   8661: istore #6
    //   8663: iconst_0
    //   8664: istore #7
    //   8666: iload #7
    //   8668: iload #6
    //   8670: if_icmpge -> 8808
    //   8673: aload #5
    //   8675: iload #7
    //   8677: aaload
    //   8678: astore #8
    //   8680: aload #8
    //   8682: invokevirtual getModifiers : ()I
    //   8685: invokestatic isStatic : (I)Z
    //   8688: ifne -> 8698
    //   8691: goto -> 8801
    //   8694: invokestatic a : (Ljava/lang/Throwable;)Ljava/lang/Throwable;
    //   8697: athrow
    //   8698: aload #8
    //   8700: invokevirtual getType : ()Ljava/lang/Class;
    //   8703: astore #9
    //   8705: aload #9
    //   8707: ifnull -> 8788
    //   8710: aload #9
    //   8712: invokevirtual isPrimitive : ()Z
    //   8715: ifne -> 8788
    //   8718: goto -> 8725
    //   8721: invokestatic a : (Ljava/lang/Throwable;)Ljava/lang/Throwable;
    //   8724: athrow
    //   8725: aload #9
    //   8727: invokevirtual getPackage : ()Ljava/lang/Package;
    //   8730: ifnull -> 8788
    //   8733: goto -> 8740
    //   8736: invokestatic a : (Ljava/lang/Throwable;)Ljava/lang/Throwable;
    //   8739: athrow
    //   8740: aload #9
    //   8742: invokevirtual getPackage : ()Ljava/lang/Package;
    //   8745: invokevirtual getName : ()Ljava/lang/String;
    //   8748: ifnull -> 8788
    //   8751: goto -> 8758
    //   8754: invokestatic a : (Ljava/lang/Throwable;)Ljava/lang/Throwable;
    //   8757: athrow
    //   8758: aload #9
    //   8760: invokevirtual getPackage : ()Ljava/lang/Package;
    //   8763: invokevirtual getName : ()Ljava/lang/String;
    //   8766: sipush #19302
    //   8769: sipush #-21379
    //   8772: invokestatic a : (II)Ljava/lang/String;
    //   8775: invokevirtual startsWith : (Ljava/lang/String;)Z
    //   8778: ifne -> 8788
    //   8781: goto -> 8788
    //   8784: invokestatic a : (Ljava/lang/Throwable;)Ljava/lang/Throwable;
    //   8787: athrow
    //   8788: aload #8
    //   8790: iconst_1
    //   8791: invokevirtual setAccessible : (Z)V
    //   8794: aload #8
    //   8796: aconst_null
    //   8797: invokevirtual get : (Ljava/lang/Object;)Ljava/lang/Object;
    //   8800: pop
    //   8801: iinc #7, 1
    //   8804: iload_2
    //   8805: ifeq -> 8666
    //   8808: sipush #19300
    //   8811: sipush #-799
    //   8814: invokestatic a : (II)Ljava/lang/String;
    //   8817: invokestatic forName : (Ljava/lang/String;)Ljava/lang/Class;
    //   8820: invokevirtual getDeclaredMethods : ()[Ljava/lang/reflect/Method;
    //   8823: astore #5
    //   8825: aload #5
    //   8827: arraylength
    //   8828: istore #6
    //   8830: iconst_0
    //   8831: istore #7
    //   8833: iload #7
    //   8835: iload #6
    //   8837: if_icmpge -> 8974
    //   8840: aload #5
    //   8842: iload #7
    //   8844: aaload
    //   8845: astore #8
    //   8847: aload #8
    //   8849: invokevirtual getParameterTypes : ()[Ljava/lang/Class;
    //   8852: pop
    //   8853: aload #8
    //   8855: invokevirtual getModifiers : ()I
    //   8858: invokestatic isStatic : (I)Z
    //   8861: ifeq -> 8960
    //   8864: aload #8
    //   8866: invokevirtual getParameterTypes : ()[Ljava/lang/Class;
    //   8869: arraylength
    //   8870: iconst_2
    //   8871: if_icmpne -> 8960
    //   8874: goto -> 8881
    //   8877: invokestatic a : (Ljava/lang/Throwable;)Ljava/lang/Throwable;
    //   8880: athrow
    //   8881: aload #8
    //   8883: invokevirtual getReturnType : ()Ljava/lang/Class;
    //   8886: getstatic java/lang/Boolean.TYPE : Ljava/lang/Class;
    //   8889: if_acmpne -> 8960
    //   8892: goto -> 8899
    //   8895: invokestatic a : (Ljava/lang/Throwable;)Ljava/lang/Throwable;
    //   8898: athrow
    //   8899: aload #8
    //   8901: iconst_1
    //   8902: invokevirtual setAccessible : (Z)V
    //   8905: aload #8
    //   8907: aconst_null
    //   8908: iconst_2
    //   8909: anewarray java/lang/Object
    //   8912: dup
    //   8913: iconst_0
    //   8914: aload_0
    //   8915: aastore
    //   8916: dup
    //   8917: iconst_1
    //   8918: aload_1
    //   8919: ifnonnull -> 8937
    //   8922: goto -> 8929
    //   8925: invokestatic a : (Ljava/lang/Throwable;)Ljava/lang/Throwable;
    //   8928: athrow
    //   8929: aload_1
    //   8930: goto -> 8944
    //   8933: invokestatic a : (Ljava/lang/Throwable;)Ljava/lang/Throwable;
    //   8936: athrow
    //   8937: aload_1
    //   8938: checkcast [B
    //   8941: invokevirtual clone : ()Ljava/lang/Object;
    //   8944: aastore
    //   8945: invokevirtual invoke : (Ljava/lang/Object;[Ljava/lang/Object;)Ljava/lang/Object;
    //   8948: checkcast java/lang/Boolean
    //   8951: invokevirtual booleanValue : ()Z
    //   8954: istore #4
    //   8956: iload_2
    //   8957: ifeq -> 8974
    //   8960: iinc #7, 1
    //   8963: iload_2
    //   8964: ifeq -> 8833
    //   8967: goto -> 8974
    //   8970: invokestatic a : (Ljava/lang/Throwable;)Ljava/lang/Throwable;
    //   8973: athrow
    //   8974: iload #4
    //   8976: ireturn
    //   8977: astore_3
    //   8978: new java/lang/Exception
    //   8981: dup
    //   8982: aload_3
    //   8983: invokevirtual getMessage : ()Ljava/lang/String;
    //   8986: invokespecial <init> : (Ljava/lang/String;)V
    //   8989: athrow
    // Exception table:
    //   from	to	target	type
    //   4	6776	8977	java/lang/Throwable
    //   22	198	201	java/lang/Throwable
    //   168	235	238	java/lang/Throwable
    //   205	272	275	java/lang/Throwable
    //   242	309	312	java/lang/Throwable
    //   279	346	349	java/lang/Throwable
    //   316	383	386	java/lang/Throwable
    //   353	420	423	java/lang/Throwable
    //   390	457	460	java/lang/Throwable
    //   427	494	497	java/lang/Throwable
    //   464	531	534	java/lang/Throwable
    //   501	568	571	java/lang/Throwable
    //   538	605	608	java/lang/Throwable
    //   575	642	645	java/lang/Throwable
    //   612	679	682	java/lang/Throwable
    //   649	716	719	java/lang/Throwable
    //   686	753	756	java/lang/Throwable
    //   723	790	793	java/lang/Throwable
    //   760	827	830	java/lang/Throwable
    //   797	864	867	java/lang/Throwable
    //   834	901	904	java/lang/Throwable
    //   871	938	941	java/lang/Throwable
    //   908	975	978	java/lang/Throwable
    //   945	1012	1015	java/lang/Throwable
    //   982	1049	1052	java/lang/Throwable
    //   1019	1086	1089	java/lang/Throwable
    //   1056	1123	1126	java/lang/Throwable
    //   1093	1160	1163	java/lang/Throwable
    //   1130	1197	1200	java/lang/Throwable
    //   1167	1234	1237	java/lang/Throwable
    //   1204	1271	1274	java/lang/Throwable
    //   1241	1308	1311	java/lang/Throwable
    //   1278	1341	1344	java/lang/Throwable
    //   5750	5764	5764	java/lang/Throwable
    //   5775	5788	5791	java/lang/Throwable
    //   5780	5803	5806	java/lang/Throwable
    //   5795	5821	5824	java/lang/Throwable
    //   5810	5851	5854	java/lang/Throwable
    //   5917	5944	5947	java/lang/Throwable
    //   5934	5965	5968	java/lang/Throwable
    //   5951	5995	5998	java/lang/Throwable
    //   5972	6006	6006	java/lang/Throwable
    //   6017	6033	6036	java/lang/Throwable
    //   6133	6147	6147	java/lang/Throwable
    //   6158	6171	6174	java/lang/Throwable
    //   6163	6186	6189	java/lang/Throwable
    //   6178	6204	6207	java/lang/Throwable
    //   6193	6234	6237	java/lang/Throwable
    //   6300	6327	6330	java/lang/Throwable
    //   6317	6345	6348	java/lang/Throwable
    //   6334	6375	6378	java/lang/Throwable
    //   6352	6386	6386	java/lang/Throwable
    //   6409	6420	6423	java/lang/Throwable
    //   6475	6489	6489	java/lang/Throwable
    //   6500	6513	6516	java/lang/Throwable
    //   6505	6528	6531	java/lang/Throwable
    //   6520	6546	6549	java/lang/Throwable
    //   6535	6576	6579	java/lang/Throwable
    //   6642	6669	6672	java/lang/Throwable
    //   6659	6687	6690	java/lang/Throwable
    //   6676	6717	6720	java/lang/Throwable
    //   6694	6728	6728	java/lang/Throwable
    //   6751	6762	6765	java/lang/Throwable
    //   6777	7511	8977	java/lang/Throwable
    //   6867	6881	6881	java/lang/Throwable
    //   6892	6905	6908	java/lang/Throwable
    //   6897	6920	6923	java/lang/Throwable
    //   6912	6938	6941	java/lang/Throwable
    //   6927	6968	6971	java/lang/Throwable
    //   7034	7061	7064	java/lang/Throwable
    //   7051	7079	7082	java/lang/Throwable
    //   7068	7109	7112	java/lang/Throwable
    //   7086	7120	7120	java/lang/Throwable
    //   7143	7154	7157	java/lang/Throwable
    //   7210	7224	7224	java/lang/Throwable
    //   7235	7248	7251	java/lang/Throwable
    //   7240	7263	7266	java/lang/Throwable
    //   7255	7281	7284	java/lang/Throwable
    //   7270	7311	7314	java/lang/Throwable
    //   7377	7404	7407	java/lang/Throwable
    //   7394	7422	7425	java/lang/Throwable
    //   7411	7452	7455	java/lang/Throwable
    //   7429	7463	7463	java/lang/Throwable
    //   7486	7497	7500	java/lang/Throwable
    //   7512	8246	8977	java/lang/Throwable
    //   7602	7616	7616	java/lang/Throwable
    //   7627	7640	7643	java/lang/Throwable
    //   7632	7655	7658	java/lang/Throwable
    //   7647	7673	7676	java/lang/Throwable
    //   7662	7703	7706	java/lang/Throwable
    //   7769	7796	7799	java/lang/Throwable
    //   7786	7814	7817	java/lang/Throwable
    //   7803	7844	7847	java/lang/Throwable
    //   7821	7855	7855	java/lang/Throwable
    //   7878	7889	7892	java/lang/Throwable
    //   7945	7959	7959	java/lang/Throwable
    //   7970	7983	7986	java/lang/Throwable
    //   7975	7998	8001	java/lang/Throwable
    //   7990	8016	8019	java/lang/Throwable
    //   8005	8046	8049	java/lang/Throwable
    //   8112	8139	8142	java/lang/Throwable
    //   8129	8157	8160	java/lang/Throwable
    //   8146	8187	8190	java/lang/Throwable
    //   8164	8198	8198	java/lang/Throwable
    //   8221	8232	8235	java/lang/Throwable
    //   8247	8976	8977	java/lang/Throwable
    //   8337	8351	8351	java/lang/Throwable
    //   8362	8375	8378	java/lang/Throwable
    //   8367	8390	8393	java/lang/Throwable
    //   8382	8408	8411	java/lang/Throwable
    //   8397	8438	8441	java/lang/Throwable
    //   8504	8531	8534	java/lang/Throwable
    //   8521	8549	8552	java/lang/Throwable
    //   8538	8579	8582	java/lang/Throwable
    //   8556	8590	8590	java/lang/Throwable
    //   8613	8624	8627	java/lang/Throwable
    //   8680	8694	8694	java/lang/Throwable
    //   8705	8718	8721	java/lang/Throwable
    //   8710	8733	8736	java/lang/Throwable
    //   8725	8751	8754	java/lang/Throwable
    //   8740	8781	8784	java/lang/Throwable
    //   8847	8874	8877	java/lang/Throwable
    //   8864	8892	8895	java/lang/Throwable
    //   8881	8922	8925	java/lang/Throwable
    //   8899	8933	8933	java/lang/Throwable
    //   8956	8967	8970	java/lang/Throwable
  }
  
  static void Zs(Object[] paramArrayOfObject, Object paramObject) throws Throwable {}
  
  static void Zt(Object paramObject) {
    Zry7.Z_ = a(19303, 12091);
    Zry7.ZZ = new BigInteger(a(19296, 22305));
  }
  
  static {
    // Byte code:
    //   0: bipush #24
    //   2: anewarray java/lang/String
    //   5: astore #5
    //   7: iconst_0
    //   8: istore_3
    //   9: ldc '?[hTy\\t!C/'LB\?-\z/')PqUG@B,Vp\\nEUZ\\bLG':()KF\\t8j]$~ B( ls[OTc>\\tUF\\t\\f \\b:?(r\\t|e(9H\\tE1\\t6J0L9\\t'\\b_\\br6[p\\beFU\\ti8\\tj_o+ VnXORSF:$P\\tfJ0\\r9*\\bPm</EM\\f%Hs\\foPGdT; (6c"T@EaM\\rH+xm1;)s+H\\tb.+6'
    //   11: dup
    //   12: astore_2
    //   13: invokevirtual length : ()I
    //   16: istore #4
    //   18: bipush #9
    //   20: istore_1
    //   21: iconst_m1
    //   22: istore_0
    //   23: bipush #106
    //   25: iinc #0, 1
    //   28: aload_2
    //   29: iload_0
    //   30: dup
    //   31: iload_1
    //   32: iadd
    //   33: invokevirtual substring : (II)Ljava/lang/String;
    //   36: iconst_m1
    //   37: goto -> 142
    //   40: aload #5
    //   42: swap
    //   43: iload_3
    //   44: iinc #3, 1
    //   47: swap
    //   48: aastore
    //   49: iload_0
    //   50: iload_1
    //   51: iadd
    //   52: dup
    //   53: istore_0
    //   54: iload #4
    //   56: if_icmpge -> 68
    //   59: aload_2
    //   60: iload_0
    //   61: invokevirtual charAt : (I)C
    //   64: istore_1
    //   65: goto -> 23
    //   68: ldc ';A\\t<\\t.'
    //   70: dup
    //   71: astore_2
    //   72: invokevirtual length : ()I
    //   75: istore #4
    //   77: iconst_4
    //   78: istore_1
    //   79: iconst_m1
    //   80: istore_0
    //   81: bipush #27
    //   83: iinc #0, 1
    //   86: aload_2
    //   87: iload_0
    //   88: dup
    //   89: iload_1
    //   90: iadd
    //   91: invokevirtual substring : (II)Ljava/lang/String;
    //   94: iconst_0
    //   95: goto -> 142
    //   98: aload #5
    //   100: swap
    //   101: iload_3
    //   102: iinc #3, 1
    //   105: swap
    //   106: aastore
    //   107: iload_0
    //   108: iload_1
    //   109: iadd
    //   110: dup
    //   111: istore_0
    //   112: iload #4
    //   114: if_icmpge -> 126
    //   117: aload_2
    //   118: iload_0
    //   119: invokevirtual charAt : (I)C
    //   122: istore_1
    //   123: goto -> 81
    //   126: aload #5
    //   128: putstatic burp/Zm84.a : [Ljava/lang/String;
    //   131: bipush #24
    //   133: anewarray java/lang/String
    //   136: putstatic burp/Zm84.b : [Ljava/lang/String;
    //   139: goto -> 300
    //   142: dup_x2
    //   143: pop
    //   144: invokevirtual toCharArray : ()[C
    //   147: dup_x1
    //   148: arraylength
    //   149: dup_x2
    //   150: pop
    //   151: iconst_0
    //   152: istore #6
    //   154: dup2_x1
    //   155: pop2
    //   156: dup_x2
    //   157: iconst_1
    //   158: if_icmpgt -> 260
    //   161: dup2
    //   162: swap
    //   163: iload #6
    //   165: dup2_x1
    //   166: caload
    //   167: swap
    //   168: iload #6
    //   170: bipush #7
    //   172: irem
    //   173: tableswitch default -> 242, 0 -> 212, 1 -> 217, 2 -> 222, 3 -> 227, 4 -> 232, 5 -> 237
    //   212: bipush #35
    //   214: goto -> 244
    //   217: bipush #111
    //   219: goto -> 244
    //   222: bipush #120
    //   224: goto -> 244
    //   227: bipush #24
    //   229: goto -> 244
    //   232: bipush #66
    //   234: goto -> 244
    //   237: bipush #63
    //   239: goto -> 244
    //   242: bipush #99
    //   244: ixor
    //   245: ixor
    //   246: i2c
    //   247: castore
    //   248: iinc #6, 1
    //   251: dup
    //   252: ifne -> 260
    //   255: dup2
    //   256: dup_x1
    //   257: goto -> 165
    //   260: dup2_x1
    //   261: pop2
    //   262: dup_x2
    //   263: iload #6
    //   265: if_icmpgt -> 161
    //   268: pop
    //   269: new java/lang/String
    //   272: dup_x1
    //   273: swap
    //   274: invokespecial <init> : ([C)V
    //   277: invokevirtual intern : ()Ljava/lang/String;
    //   280: swap
    //   281: pop
    //   282: swap
    //   283: tableswitch default -> 40, 0 -> 98
    //   300: new java/math/BigInteger
    //   303: dup
    //   304: sipush #19318
    //   307: sipush #-4023
    //   310: invokestatic a : (II)Ljava/lang/String;
    //   313: invokespecial <init> : (Ljava/lang/String;)V
    //   316: putstatic burp/Zm84.Zf : Ljava/lang/Object;
    //   319: sipush #19315
    //   322: sipush #5313
    //   325: invokestatic a : (II)Ljava/lang/String;
    //   328: putstatic burp/Zm84.Zd : Ljava/lang/String;
    //   331: return
  }
  
  private static Throwable a(Throwable paramThrowable) {
    return paramThrowable;
  }
  
  private static String a(int paramInt1, int paramInt2) {
    int i = (paramInt1 ^ 0x4B62) & 0xFFFF;
    if (b[i] == null) {
      char[] arrayOfChar = a[i].toCharArray();
      switch (arrayOfChar[0] & 0xFF) {
        case 0:
        
        case 1:
        
        case 2:
        
        case 3:
        
        case 4:
        
        case 5:
        
        case 6:
        
        case 7:
        
        case 8:
        
        case 9:
        
        case 10:
        
        case 11:
        
        case 12:
        
        case 13:
        
        case 14:
        
        case 15:
        
        case 16:
        
        case 17:
        
        case 18:
        
        case 19:
        
        case 20:
        
        case 21:
        
        case 22:
        
        case 23:
        
        case 24:
        
        case 25:
        
        case 26:
        
        case 27:
        
        case 28:
        
        case 29:
        
        case 30:
        
        case 31:
        
        case 32:
        
        case 33:
        
        case 34:
        
        case 35:
        
        case 36:
        
        case 37:
        
        case 38:
        
        case 39:
        
        case 40:
        
        case 41:
        
        case 42:
        
        case 43:
        
        case 44:
        
        case 45:
        
        case 46:
        
        case 47:
        
        case 48:
        
        case 49:
        
        case 50:
        
        case 51:
        
        case 52:
        
        case 53:
        
        case 54:
        
        case 55:
        
        case 56:
        
        case 57:
        
        case 58:
        
        case 59:
        
        case 60:
        
        case 61:
        
        case 62:
        
        case 63:
        
        case 64:
        
        case 65:
        
        case 66:
        
        case 67:
        
        case 68:
        
        case 69:
        
        case 70:
        
        case 71:
        
        case 72:
        
        case 73:
        
        case 74:
        
        case 75:
        
        case 76:
        
        case 77:
        
        case 78:
        
        case 79:
        
        case 80:
        
        case 81:
        
        case 82:
        
        case 83:
        
        case 84:
        
        case 85:
        
        case 86:
        
        case 87:
        
        case 88:
        
        case 89:
        
        case 90:
        
        case 91:
        
        case 92:
        
        case 93:
        
        case 94:
        
        case 95:
        
        case 96:
        
        case 97:
        
        case 98:
        
        case 99:
        
        case 100:
        
        case 101:
        
        case 102:
        
        case 103:
        
        case 104:
        
        case 105:
        
        case 106:
        
        case 107:
        
        case 108:
        
        case 109:
        
        case 110:
        
        case 111:
        
        case 112:
        
        case 113:
        
        case 114:
        
        case 115:
        
        case 116:
        
        case 117:
        
        case 118:
        
        case 119:
        
        case 120:
        
        case 121:
        
        case 122:
        
        case 123:
        
        case 124:
        
        case 125:
        
        case 126:
        
        case 127:
        
        case 128:
        
        case 129:
        
        case 130:
        
        case 131:
        
        case 132:
        
        case 133:
        
        case 134:
        
        case 135:
        
        case 136:
        
        case 137:
        
        case 138:
        
        case 139:
        
        case 140:
        
        case 141:
        
        case 142:
        
        case 143:
        
        case 144:
        
        case 145:
        
        case 146:
        
        case 147:
        
        case 148:
        
        case 149:
        
        case 150:
        
        case 151:
        
        case 152:
        
        case 153:
        
        case 154:
        
        case 155:
        
        case 156:
        
        case 157:
        
        case 158:
        
        case 159:
        
        case 160:
        
        case 161:
        
        case 162:
        
        case 163:
        
        case 164:
        
        case 165:
        
        case 166:
        
        case 167:
        
        case 168:
        
        case 169:
        
        case 170:
        
        case 171:
        
        case 172:
        
        case 173:
        
        case 174:
        
        case 175:
        
        case 176:
        
        case 177:
        
        case 178:
        
        case 179:
        
        case 180:
        
        case 181:
        
        case 182:
        
        case 183:
        
        case 184:
        
        case 185:
        
        case 186:
        
        case 187:
        
        case 188:
        
        case 189:
        
        case 190:
        
        case 191:
        
        case 192:
        
        case 193:
        
        case 194:
        
        case 195:
        
        case 196:
        
        case 197:
        
        case 198:
        
        case 199:
        
        case 200:
        
        case 201:
        
        case 202:
        
        case 203:
        
        case 204:
        
        case 205:
        
        case 206:
        
        case 207:
        
        case 208:
        
        case 209:
        
        case 210:
        
        case 211:
        
        case 212:
        
        case 213:
        
        case 214:
        
        case 215:
        
        case 216:
        
        case 217:
        
        case 218:
        
        case 219:
        
        case 220:
        
        case 221:
        
        case 222:
        
        case 223:
        
        case 224:
        
        case 225:
        
        case 226:
        
        case 227:
        
        case 228:
        
        case 229:
        
        case 230:
        
        case 231:
        
        case 232:
        
        case 233:
        
        case 234:
        
        case 235:
        
        case 236:
        
        case 237:
        
        case 238:
        
        case 239:
        
        case 240:
        
        case 241:
        
        case 242:
        
        case 243:
        
        case 244:
        
        case 245:
        
        case 246:
        
        case 247:
        
        case 248:
        
        case 249:
        
        case 250:
        
        case 251:
        
        case 252:
        
        case 253:
        
        case 254:
        
        default:
          break;
      } 
      char c = '';
      int j = (paramInt2 & 0xFF) - c;
      if (j < 0)
        j += 256; 
      int k = ((paramInt2 & 0xFFFF) >>> 8) - c;
      if (k < 0)
        k += 256; 
      for (byte b = 0; b < arrayOfChar.length; b++) {
        int m = b % 2;
        if (m == 0) {
          arrayOfChar[b] = (char)(arrayOfChar[b] ^ j);
          j = ((j >>> 3 | j << 5) ^ arrayOfChar[b]) & 0xFF;
        } else {
          arrayOfChar[b] = (char)(arrayOfChar[b] ^ k);
          k = ((k >>> 3 | k << 5) ^ arrayOfChar[b]) & 0xFF;
        } 
      } 
      b[i] = (new String(arrayOfChar)).intern();
    } 
    return b[i];
  }
}


/* Location:              C:\Program Files\BurpSuitePro\burpsuite_pro.jar!\burp\Zm84.class
 * Java compiler version: 21 (65.0)
 * JD-Core Version:       1.1.3
 */