package burp;

import java.math.BigInteger;

class Zm8i extends ClassLoader {
  static String Z_;
  
  static Object Zm;
  
  private static final String[] a;
  
  private static final String[] b;
  
  static boolean Zq(Object[] paramArrayOfObject, Object paramObject) throws Throwable {
    // Byte code:
    //   0: invokestatic ZN : ()Z
    //   3: istore_2
    //   4: getstatic burp/Zke7.Zj : Ljava/lang/Object;
    //   7: checkcast java/math/BigInteger
    //   10: getstatic burp/Ztte.ZR : Ljava/lang/Object;
    //   13: checkcast java/math/BigInteger
    //   16: invokevirtual subtract : (Ljava/math/BigInteger;)Ljava/math/BigInteger;
    //   19: putstatic burp/Zkvq.Zz : Ljava/lang/Object;
    //   22: getstatic burp/Zg2.ZE : Ljava/lang/Object;
    //   25: checkcast java/math/BigInteger
    //   28: invokevirtual toByteArray : ()[B
    //   31: astore_3
    //   32: bipush #64
    //   34: newarray byte
    //   36: dup
    //   37: iconst_0
    //   38: bipush #-128
    //   40: bastore
    //   41: dup
    //   42: iconst_1
    //   43: iconst_0
    //   44: bastore
    //   45: dup
    //   46: iconst_2
    //   47: iconst_0
    //   48: bastore
    //   49: dup
    //   50: iconst_3
    //   51: iconst_0
    //   52: bastore
    //   53: dup
    //   54: iconst_4
    //   55: iconst_0
    //   56: bastore
    //   57: dup
    //   58: iconst_5
    //   59: iconst_0
    //   60: bastore
    //   61: dup
    //   62: bipush #6
    //   64: iconst_0
    //   65: bastore
    //   66: dup
    //   67: bipush #7
    //   69: iconst_0
    //   70: bastore
    //   71: dup
    //   72: bipush #8
    //   74: iconst_0
    //   75: bastore
    //   76: dup
    //   77: bipush #9
    //   79: iconst_0
    //   80: bastore
    //   81: dup
    //   82: bipush #10
    //   84: iconst_0
    //   85: bastore
    //   86: dup
    //   87: bipush #11
    //   89: iconst_0
    //   90: bastore
    //   91: dup
    //   92: bipush #12
    //   94: iconst_0
    //   95: bastore
    //   96: dup
    //   97: bipush #13
    //   99: iconst_0
    //   100: bastore
    //   101: dup
    //   102: bipush #14
    //   104: iconst_0
    //   105: bastore
    //   106: dup
    //   107: bipush #15
    //   109: iconst_0
    //   110: bastore
    //   111: dup
    //   112: bipush #16
    //   114: iconst_0
    //   115: bastore
    //   116: dup
    //   117: bipush #17
    //   119: iconst_0
    //   120: bastore
    //   121: dup
    //   122: bipush #18
    //   124: iconst_0
    //   125: bastore
    //   126: dup
    //   127: bipush #19
    //   129: iconst_0
    //   130: bastore
    //   131: dup
    //   132: bipush #20
    //   134: iconst_0
    //   135: bastore
    //   136: dup
    //   137: bipush #21
    //   139: iconst_0
    //   140: bastore
    //   141: dup
    //   142: bipush #22
    //   144: iconst_0
    //   145: bastore
    //   146: dup
    //   147: bipush #23
    //   149: iconst_0
    //   150: bastore
    //   151: dup
    //   152: bipush #24
    //   154: iconst_0
    //   155: bastore
    //   156: dup
    //   157: bipush #25
    //   159: iconst_0
    //   160: bastore
    //   161: dup
    //   162: bipush #26
    //   164: iconst_0
    //   165: bastore
    //   166: dup
    //   167: bipush #27
    //   169: iconst_0
    //   170: bastore
    //   171: dup
    //   172: bipush #28
    //   174: iconst_0
    //   175: bastore
    //   176: dup
    //   177: bipush #29
    //   179: iconst_0
    //   180: bastore
    //   181: dup
    //   182: bipush #30
    //   184: iconst_0
    //   185: bastore
    //   186: dup
    //   187: bipush #31
    //   189: iconst_0
    //   190: bastore
    //   191: dup
    //   192: bipush #32
    //   194: iconst_0
    //   195: bastore
    //   196: dup
    //   197: bipush #33
    //   199: iconst_0
    //   200: bastore
    //   201: dup
    //   202: bipush #34
    //   204: iconst_0
    //   205: bastore
    //   206: dup
    //   207: bipush #35
    //   209: iconst_0
    //   210: bastore
    //   211: dup
    //   212: bipush #36
    //   214: iconst_0
    //   215: bastore
    //   216: dup
    //   217: bipush #37
    //   219: iconst_0
    //   220: bastore
    //   221: dup
    //   222: bipush #38
    //   224: iconst_0
    //   225: bastore
    //   226: dup
    //   227: bipush #39
    //   229: iconst_0
    //   230: bastore
    //   231: dup
    //   232: bipush #40
    //   234: iconst_0
    //   235: bastore
    //   236: dup
    //   237: bipush #41
    //   239: iconst_0
    //   240: bastore
    //   241: dup
    //   242: bipush #42
    //   244: iconst_0
    //   245: bastore
    //   246: dup
    //   247: bipush #43
    //   249: iconst_0
    //   250: bastore
    //   251: dup
    //   252: bipush #44
    //   254: iconst_0
    //   255: bastore
    //   256: dup
    //   257: bipush #45
    //   259: iconst_0
    //   260: bastore
    //   261: dup
    //   262: bipush #46
    //   264: iconst_0
    //   265: bastore
    //   266: dup
    //   267: bipush #47
    //   269: iconst_0
    //   270: bastore
    //   271: dup
    //   272: bipush #48
    //   274: iconst_0
    //   275: bastore
    //   276: dup
    //   277: bipush #49
    //   279: iconst_0
    //   280: bastore
    //   281: dup
    //   282: bipush #50
    //   284: iconst_0
    //   285: bastore
    //   286: dup
    //   287: bipush #51
    //   289: iconst_0
    //   290: bastore
    //   291: dup
    //   292: bipush #52
    //   294: iconst_0
    //   295: bastore
    //   296: dup
    //   297: bipush #53
    //   299: iconst_0
    //   300: bastore
    //   301: dup
    //   302: bipush #54
    //   304: iconst_0
    //   305: bastore
    //   306: dup
    //   307: bipush #55
    //   309: iconst_0
    //   310: bastore
    //   311: dup
    //   312: bipush #56
    //   314: iconst_0
    //   315: bastore
    //   316: dup
    //   317: bipush #57
    //   319: iconst_0
    //   320: bastore
    //   321: dup
    //   322: bipush #58
    //   324: iconst_0
    //   325: bastore
    //   326: dup
    //   327: bipush #59
    //   329: iconst_0
    //   330: bastore
    //   331: dup
    //   332: bipush #60
    //   334: iconst_0
    //   335: bastore
    //   336: dup
    //   337: bipush #61
    //   339: iconst_0
    //   340: bastore
    //   341: dup
    //   342: bipush #62
    //   344: iconst_0
    //   345: bastore
    //   346: dup
    //   347: bipush #63
    //   349: iconst_0
    //   350: bastore
    //   351: astore #5
    //   353: bipush #64
    //   355: newarray int
    //   357: dup
    //   358: iconst_0
    //   359: ldc 1116352408
    //   361: iastore
    //   362: dup
    //   363: iconst_1
    //   364: ldc 1899447441
    //   366: iastore
    //   367: dup
    //   368: iconst_2
    //   369: ldc -1245643825
    //   371: iastore
    //   372: dup
    //   373: iconst_3
    //   374: ldc -373957723
    //   376: iastore
    //   377: dup
    //   378: iconst_4
    //   379: ldc 961987163
    //   381: iastore
    //   382: dup
    //   383: iconst_5
    //   384: ldc 1508970993
    //   386: iastore
    //   387: dup
    //   388: bipush #6
    //   390: ldc -1841331548
    //   392: iastore
    //   393: dup
    //   394: bipush #7
    //   396: ldc -1424204075
    //   398: iastore
    //   399: dup
    //   400: bipush #8
    //   402: ldc -670586216
    //   404: iastore
    //   405: dup
    //   406: bipush #9
    //   408: ldc 310598401
    //   410: iastore
    //   411: dup
    //   412: bipush #10
    //   414: ldc 607225278
    //   416: iastore
    //   417: dup
    //   418: bipush #11
    //   420: ldc 1426881987
    //   422: iastore
    //   423: dup
    //   424: bipush #12
    //   426: ldc 1925078388
    //   428: iastore
    //   429: dup
    //   430: bipush #13
    //   432: ldc -2132889090
    //   434: iastore
    //   435: dup
    //   436: bipush #14
    //   438: ldc -1680079193
    //   440: iastore
    //   441: dup
    //   442: bipush #15
    //   444: ldc -1046744716
    //   446: iastore
    //   447: dup
    //   448: bipush #16
    //   450: ldc -459576895
    //   452: iastore
    //   453: dup
    //   454: bipush #17
    //   456: ldc -272742522
    //   458: iastore
    //   459: dup
    //   460: bipush #18
    //   462: ldc 264347078
    //   464: iastore
    //   465: dup
    //   466: bipush #19
    //   468: ldc 604807628
    //   470: iastore
    //   471: dup
    //   472: bipush #20
    //   474: ldc 770255983
    //   476: iastore
    //   477: dup
    //   478: bipush #21
    //   480: ldc 1249150122
    //   482: iastore
    //   483: dup
    //   484: bipush #22
    //   486: ldc 1555081692
    //   488: iastore
    //   489: dup
    //   490: bipush #23
    //   492: ldc 1996064986
    //   494: iastore
    //   495: dup
    //   496: bipush #24
    //   498: ldc -1740746414
    //   500: iastore
    //   501: dup
    //   502: bipush #25
    //   504: ldc -1473132947
    //   506: iastore
    //   507: dup
    //   508: bipush #26
    //   510: ldc -1341970488
    //   512: iastore
    //   513: dup
    //   514: bipush #27
    //   516: ldc -1084653625
    //   518: iastore
    //   519: dup
    //   520: bipush #28
    //   522: ldc -958395405
    //   524: iastore
    //   525: dup
    //   526: bipush #29
    //   528: ldc -710438585
    //   530: iastore
    //   531: dup
    //   532: bipush #30
    //   534: ldc 113926993
    //   536: iastore
    //   537: dup
    //   538: bipush #31
    //   540: ldc 338241895
    //   542: iastore
    //   543: dup
    //   544: bipush #32
    //   546: ldc 666307205
    //   548: iastore
    //   549: dup
    //   550: bipush #33
    //   552: ldc 773529912
    //   554: iastore
    //   555: dup
    //   556: bipush #34
    //   558: ldc 1294757372
    //   560: iastore
    //   561: dup
    //   562: bipush #35
    //   564: ldc 1396182291
    //   566: iastore
    //   567: dup
    //   568: bipush #36
    //   570: ldc 1695183700
    //   572: iastore
    //   573: dup
    //   574: bipush #37
    //   576: ldc 1986661051
    //   578: iastore
    //   579: dup
    //   580: bipush #38
    //   582: ldc -2117940946
    //   584: iastore
    //   585: dup
    //   586: bipush #39
    //   588: ldc -1838011259
    //   590: iastore
    //   591: dup
    //   592: bipush #40
    //   594: ldc -1564481375
    //   596: iastore
    //   597: dup
    //   598: bipush #41
    //   600: ldc -1474664885
    //   602: iastore
    //   603: dup
    //   604: bipush #42
    //   606: ldc -1035236496
    //   608: iastore
    //   609: dup
    //   610: bipush #43
    //   612: ldc -949202525
    //   614: iastore
    //   615: dup
    //   616: bipush #44
    //   618: ldc -778901479
    //   620: iastore
    //   621: dup
    //   622: bipush #45
    //   624: ldc -694614492
    //   626: iastore
    //   627: dup
    //   628: bipush #46
    //   630: ldc -200395387
    //   632: iastore
    //   633: dup
    //   634: bipush #47
    //   636: ldc 275423344
    //   638: iastore
    //   639: dup
    //   640: bipush #48
    //   642: ldc 430227734
    //   644: iastore
    //   645: dup
    //   646: bipush #49
    //   648: ldc 506948616
    //   650: iastore
    //   651: dup
    //   652: bipush #50
    //   654: ldc 659060556
    //   656: iastore
    //   657: dup
    //   658: bipush #51
    //   660: ldc 883997877
    //   662: iastore
    //   663: dup
    //   664: bipush #52
    //   666: ldc 958139571
    //   668: iastore
    //   669: dup
    //   670: bipush #53
    //   672: ldc 1322822218
    //   674: iastore
    //   675: dup
    //   676: bipush #54
    //   678: ldc 1537002063
    //   680: iastore
    //   681: dup
    //   682: bipush #55
    //   684: ldc 1747873779
    //   686: iastore
    //   687: dup
    //   688: bipush #56
    //   690: ldc 1955562222
    //   692: iastore
    //   693: dup
    //   694: bipush #57
    //   696: ldc 2024104815
    //   698: iastore
    //   699: dup
    //   700: bipush #58
    //   702: ldc -2067236844
    //   704: iastore
    //   705: dup
    //   706: bipush #59
    //   708: ldc -1933114872
    //   710: iastore
    //   711: dup
    //   712: bipush #60
    //   714: ldc -1866530822
    //   716: iastore
    //   717: dup
    //   718: bipush #61
    //   720: ldc -1538233109
    //   722: iastore
    //   723: dup
    //   724: bipush #62
    //   726: ldc -1090935817
    //   728: iastore
    //   729: dup
    //   730: bipush #63
    //   732: ldc -965641998
    //   734: iastore
    //   735: astore #6
    //   737: iconst_2
    //   738: newarray int
    //   740: dup
    //   741: iconst_0
    //   742: iconst_0
    //   743: iastore
    //   744: dup
    //   745: iconst_1
    //   746: iconst_0
    //   747: iastore
    //   748: astore #7
    //   750: bipush #8
    //   752: newarray int
    //   754: dup
    //   755: iconst_0
    //   756: ldc 1779033703
    //   758: iastore
    //   759: dup
    //   760: iconst_1
    //   761: ldc -1150833019
    //   763: iastore
    //   764: dup
    //   765: iconst_2
    //   766: ldc 1013904242
    //   768: iastore
    //   769: dup
    //   770: iconst_3
    //   771: ldc -1521486534
    //   773: iastore
    //   774: dup
    //   775: iconst_4
    //   776: ldc 1359893119
    //   778: iastore
    //   779: dup
    //   780: iconst_5
    //   781: ldc -1694144372
    //   783: iastore
    //   784: dup
    //   785: bipush #6
    //   787: ldc 528734635
    //   789: iastore
    //   790: dup
    //   791: bipush #7
    //   793: ldc 1541459225
    //   795: iastore
    //   796: astore #8
    //   798: bipush #64
    //   800: newarray byte
    //   802: astore #9
    //   804: bipush #64
    //   806: newarray byte
    //   808: astore #10
    //   810: aload_3
    //   811: arraylength
    //   812: istore #11
    //   814: aload #7
    //   816: iconst_0
    //   817: iaload
    //   818: bipush #63
    //   820: iand
    //   821: istore #12
    //   823: aload #7
    //   825: iconst_0
    //   826: dup2
    //   827: iaload
    //   828: iload #11
    //   830: iadd
    //   831: iastore
    //   832: aload #7
    //   834: iconst_0
    //   835: dup2
    //   836: iaload
    //   837: iconst_m1
    //   838: iand
    //   839: iastore
    //   840: aload #7
    //   842: iconst_0
    //   843: iaload
    //   844: iload #11
    //   846: if_icmpge -> 864
    //   849: aload #7
    //   851: iconst_1
    //   852: dup2
    //   853: iaload
    //   854: iconst_1
    //   855: iadd
    //   856: iastore
    //   857: goto -> 864
    //   860: invokestatic a : (Ljava/lang/Throwable;)Ljava/lang/Throwable;
    //   863: athrow
    //   864: iconst_0
    //   865: istore #13
    //   867: iload #11
    //   869: bipush #64
    //   871: if_icmplt -> 1480
    //   874: iconst_0
    //   875: istore #14
    //   877: iload #14
    //   879: bipush #64
    //   881: if_icmpge -> 903
    //   884: aload #10
    //   886: iload #14
    //   888: aload_3
    //   889: iload #13
    //   891: iload #14
    //   893: iadd
    //   894: baload
    //   895: bastore
    //   896: iinc #14, 1
    //   899: iload_2
    //   900: ifne -> 877
    //   903: bipush #64
    //   905: newarray int
    //   907: astore #14
    //   909: bipush #8
    //   911: newarray int
    //   913: astore #15
    //   915: iconst_0
    //   916: istore #16
    //   918: iload #16
    //   920: bipush #8
    //   922: if_icmpge -> 942
    //   925: aload #15
    //   927: iload #16
    //   929: aload #8
    //   931: iload #16
    //   933: iaload
    //   934: iastore
    //   935: iinc #16, 1
    //   938: iload_2
    //   939: ifne -> 918
    //   942: iconst_0
    //   943: istore #16
    //   945: iload #16
    //   947: bipush #64
    //   949: if_icmpge -> 1440
    //   952: iload #16
    //   954: bipush #16
    //   956: if_icmpge -> 1037
    //   959: aload #14
    //   961: iload #16
    //   963: aload #10
    //   965: iconst_4
    //   966: iload #16
    //   968: imul
    //   969: baload
    //   970: sipush #255
    //   973: iand
    //   974: bipush #24
    //   976: ishl
    //   977: aload #10
    //   979: iconst_4
    //   980: iload #16
    //   982: imul
    //   983: iconst_1
    //   984: iadd
    //   985: baload
    //   986: sipush #255
    //   989: iand
    //   990: bipush #16
    //   992: ishl
    //   993: ior
    //   994: aload #10
    //   996: iconst_4
    //   997: iload #16
    //   999: imul
    //   1000: iconst_2
    //   1001: iadd
    //   1002: baload
    //   1003: sipush #255
    //   1006: iand
    //   1007: bipush #8
    //   1009: ishl
    //   1010: ior
    //   1011: aload #10
    //   1013: iconst_4
    //   1014: iload #16
    //   1016: imul
    //   1017: iconst_3
    //   1018: iadd
    //   1019: baload
    //   1020: sipush #255
    //   1023: iand
    //   1024: ior
    //   1025: iastore
    //   1026: iload_2
    //   1027: ifne -> 1180
    //   1030: goto -> 1037
    //   1033: invokestatic a : (Ljava/lang/Throwable;)Ljava/lang/Throwable;
    //   1036: athrow
    //   1037: aload #14
    //   1039: iload #16
    //   1041: aload #14
    //   1043: iload #16
    //   1045: iconst_2
    //   1046: isub
    //   1047: iaload
    //   1048: bipush #17
    //   1050: iushr
    //   1051: aload #14
    //   1053: iload #16
    //   1055: iconst_2
    //   1056: isub
    //   1057: iaload
    //   1058: bipush #15
    //   1060: ishl
    //   1061: ior
    //   1062: aload #14
    //   1064: iload #16
    //   1066: iconst_2
    //   1067: isub
    //   1068: iaload
    //   1069: bipush #19
    //   1071: iushr
    //   1072: aload #14
    //   1074: iload #16
    //   1076: iconst_2
    //   1077: isub
    //   1078: iaload
    //   1079: bipush #13
    //   1081: ishl
    //   1082: ior
    //   1083: ixor
    //   1084: aload #14
    //   1086: iload #16
    //   1088: iconst_2
    //   1089: isub
    //   1090: iaload
    //   1091: bipush #10
    //   1093: iushr
    //   1094: ixor
    //   1095: aload #14
    //   1097: iload #16
    //   1099: bipush #7
    //   1101: isub
    //   1102: iaload
    //   1103: iadd
    //   1104: aload #14
    //   1106: iload #16
    //   1108: bipush #15
    //   1110: isub
    //   1111: iaload
    //   1112: bipush #7
    //   1114: iushr
    //   1115: aload #14
    //   1117: iload #16
    //   1119: bipush #15
    //   1121: isub
    //   1122: iaload
    //   1123: bipush #25
    //   1125: ishl
    //   1126: ior
    //   1127: aload #14
    //   1129: iload #16
    //   1131: bipush #15
    //   1133: isub
    //   1134: iaload
    //   1135: bipush #18
    //   1137: iushr
    //   1138: aload #14
    //   1140: iload #16
    //   1142: bipush #15
    //   1144: isub
    //   1145: iaload
    //   1146: bipush #14
    //   1148: ishl
    //   1149: ior
    //   1150: ixor
    //   1151: aload #14
    //   1153: iload #16
    //   1155: bipush #15
    //   1157: isub
    //   1158: iaload
    //   1159: iconst_3
    //   1160: iushr
    //   1161: ixor
    //   1162: iadd
    //   1163: aload #14
    //   1165: iload #16
    //   1167: bipush #16
    //   1169: isub
    //   1170: iaload
    //   1171: iadd
    //   1172: iastore
    //   1173: goto -> 1180
    //   1176: invokestatic a : (Ljava/lang/Throwable;)Ljava/lang/Throwable;
    //   1179: athrow
    //   1180: aload #15
    //   1182: bipush #7
    //   1184: iaload
    //   1185: aload #15
    //   1187: iconst_4
    //   1188: iaload
    //   1189: bipush #6
    //   1191: iushr
    //   1192: aload #15
    //   1194: iconst_4
    //   1195: iaload
    //   1196: bipush #26
    //   1198: ishl
    //   1199: ior
    //   1200: aload #15
    //   1202: iconst_4
    //   1203: iaload
    //   1204: bipush #11
    //   1206: iushr
    //   1207: aload #15
    //   1209: iconst_4
    //   1210: iaload
    //   1211: bipush #21
    //   1213: ishl
    //   1214: ior
    //   1215: ixor
    //   1216: aload #15
    //   1218: iconst_4
    //   1219: iaload
    //   1220: bipush #25
    //   1222: iushr
    //   1223: aload #15
    //   1225: iconst_4
    //   1226: iaload
    //   1227: bipush #7
    //   1229: ishl
    //   1230: ior
    //   1231: ixor
    //   1232: iadd
    //   1233: aload #15
    //   1235: bipush #6
    //   1237: iaload
    //   1238: aload #15
    //   1240: iconst_4
    //   1241: iaload
    //   1242: aload #15
    //   1244: iconst_5
    //   1245: iaload
    //   1246: aload #15
    //   1248: bipush #6
    //   1250: iaload
    //   1251: ixor
    //   1252: iand
    //   1253: ixor
    //   1254: iadd
    //   1255: aload #6
    //   1257: iload #16
    //   1259: iaload
    //   1260: iadd
    //   1261: aload #14
    //   1263: iload #16
    //   1265: iaload
    //   1266: iadd
    //   1267: istore #17
    //   1269: aload #15
    //   1271: iconst_0
    //   1272: iaload
    //   1273: iconst_2
    //   1274: iushr
    //   1275: aload #15
    //   1277: iconst_0
    //   1278: iaload
    //   1279: bipush #30
    //   1281: ishl
    //   1282: ior
    //   1283: aload #15
    //   1285: iconst_0
    //   1286: iaload
    //   1287: bipush #13
    //   1289: iushr
    //   1290: aload #15
    //   1292: iconst_0
    //   1293: iaload
    //   1294: bipush #19
    //   1296: ishl
    //   1297: ior
    //   1298: ixor
    //   1299: aload #15
    //   1301: iconst_0
    //   1302: iaload
    //   1303: bipush #22
    //   1305: iushr
    //   1306: aload #15
    //   1308: iconst_0
    //   1309: iaload
    //   1310: bipush #10
    //   1312: ishl
    //   1313: ior
    //   1314: ixor
    //   1315: aload #15
    //   1317: iconst_0
    //   1318: iaload
    //   1319: aload #15
    //   1321: iconst_1
    //   1322: iaload
    //   1323: iand
    //   1324: aload #15
    //   1326: iconst_2
    //   1327: iaload
    //   1328: aload #15
    //   1330: iconst_0
    //   1331: iaload
    //   1332: aload #15
    //   1334: iconst_1
    //   1335: iaload
    //   1336: ior
    //   1337: iand
    //   1338: ior
    //   1339: iadd
    //   1340: istore #18
    //   1342: aload #15
    //   1344: iconst_3
    //   1345: dup2
    //   1346: iaload
    //   1347: iload #17
    //   1349: iadd
    //   1350: iastore
    //   1351: aload #15
    //   1353: bipush #7
    //   1355: iload #17
    //   1357: iload #18
    //   1359: iadd
    //   1360: iastore
    //   1361: aload #15
    //   1363: bipush #7
    //   1365: iaload
    //   1366: istore #17
    //   1368: aload #15
    //   1370: bipush #7
    //   1372: aload #15
    //   1374: bipush #6
    //   1376: iaload
    //   1377: iastore
    //   1378: aload #15
    //   1380: bipush #6
    //   1382: aload #15
    //   1384: iconst_5
    //   1385: iaload
    //   1386: iastore
    //   1387: aload #15
    //   1389: iconst_5
    //   1390: aload #15
    //   1392: iconst_4
    //   1393: iaload
    //   1394: iastore
    //   1395: aload #15
    //   1397: iconst_4
    //   1398: aload #15
    //   1400: iconst_3
    //   1401: iaload
    //   1402: iastore
    //   1403: aload #15
    //   1405: iconst_3
    //   1406: aload #15
    //   1408: iconst_2
    //   1409: iaload
    //   1410: iastore
    //   1411: aload #15
    //   1413: iconst_2
    //   1414: aload #15
    //   1416: iconst_1
    //   1417: iaload
    //   1418: iastore
    //   1419: aload #15
    //   1421: iconst_1
    //   1422: aload #15
    //   1424: iconst_0
    //   1425: iaload
    //   1426: iastore
    //   1427: aload #15
    //   1429: iconst_0
    //   1430: iload #17
    //   1432: iastore
    //   1433: iinc #16, 1
    //   1436: iload_2
    //   1437: ifne -> 945
    //   1440: iconst_0
    //   1441: istore #16
    //   1443: iload #16
    //   1445: bipush #8
    //   1447: if_icmpge -> 1470
    //   1450: aload #8
    //   1452: iload #16
    //   1454: dup2
    //   1455: iaload
    //   1456: aload #15
    //   1458: iload #16
    //   1460: iaload
    //   1461: iadd
    //   1462: iastore
    //   1463: iinc #16, 1
    //   1466: iload_2
    //   1467: ifne -> 1443
    //   1470: iinc #13, 64
    //   1473: iinc #11, -64
    //   1476: iload_2
    //   1477: ifne -> 867
    //   1480: iload #11
    //   1482: ifle -> 1517
    //   1485: iconst_0
    //   1486: istore #14
    //   1488: iload #14
    //   1490: iload #11
    //   1492: if_icmpge -> 1517
    //   1495: aload #9
    //   1497: iload #12
    //   1499: iload #14
    //   1501: iadd
    //   1502: aload_3
    //   1503: iload #13
    //   1505: iload #14
    //   1507: iadd
    //   1508: baload
    //   1509: bastore
    //   1510: iinc #14, 1
    //   1513: iload_2
    //   1514: ifne -> 1488
    //   1517: aload #7
    //   1519: iconst_0
    //   1520: iaload
    //   1521: bipush #29
    //   1523: iushr
    //   1524: aload #7
    //   1526: iconst_1
    //   1527: iaload
    //   1528: iconst_3
    //   1529: ishl
    //   1530: ior
    //   1531: istore #14
    //   1533: aload #7
    //   1535: iconst_0
    //   1536: iaload
    //   1537: iconst_3
    //   1538: ishl
    //   1539: istore #15
    //   1541: aload #7
    //   1543: iconst_0
    //   1544: iaload
    //   1545: bipush #63
    //   1547: iand
    //   1548: istore #16
    //   1550: iload #16
    //   1552: bipush #56
    //   1554: if_icmpge -> 1569
    //   1557: bipush #56
    //   1559: iload #16
    //   1561: isub
    //   1562: goto -> 1574
    //   1565: invokestatic a : (Ljava/lang/Throwable;)Ljava/lang/Throwable;
    //   1568: athrow
    //   1569: bipush #120
    //   1571: iload #16
    //   1573: isub
    //   1574: istore #17
    //   1576: aload #7
    //   1578: iconst_0
    //   1579: iaload
    //   1580: bipush #63
    //   1582: iand
    //   1583: istore #12
    //   1585: bipush #64
    //   1587: iload #12
    //   1589: isub
    //   1590: istore #18
    //   1592: aload #7
    //   1594: iconst_0
    //   1595: dup2
    //   1596: iaload
    //   1597: iload #17
    //   1599: iadd
    //   1600: iastore
    //   1601: aload #7
    //   1603: iconst_0
    //   1604: dup2
    //   1605: iaload
    //   1606: iconst_m1
    //   1607: iand
    //   1608: iastore
    //   1609: aload #7
    //   1611: iconst_0
    //   1612: iaload
    //   1613: iload #17
    //   1615: if_icmpge -> 1633
    //   1618: aload #7
    //   1620: iconst_1
    //   1621: dup2
    //   1622: iaload
    //   1623: iconst_1
    //   1624: iadd
    //   1625: iastore
    //   1626: goto -> 1633
    //   1629: invokestatic a : (Ljava/lang/Throwable;)Ljava/lang/Throwable;
    //   1632: athrow
    //   1633: iconst_0
    //   1634: istore #13
    //   1636: iload #12
    //   1638: ifle -> 2269
    //   1641: iload #17
    //   1643: iload #18
    //   1645: if_icmplt -> 2269
    //   1648: goto -> 1655
    //   1651: invokestatic a : (Ljava/lang/Throwable;)Ljava/lang/Throwable;
    //   1654: athrow
    //   1655: iconst_0
    //   1656: istore #19
    //   1658: iload #19
    //   1660: iload #18
    //   1662: if_icmpge -> 1685
    //   1665: aload #9
    //   1667: iload #12
    //   1669: iload #19
    //   1671: iadd
    //   1672: aload #5
    //   1674: iload #19
    //   1676: baload
    //   1677: bastore
    //   1678: iinc #19, 1
    //   1681: iload_2
    //   1682: ifne -> 1658
    //   1685: bipush #64
    //   1687: newarray int
    //   1689: astore #19
    //   1691: bipush #8
    //   1693: newarray int
    //   1695: astore #20
    //   1697: iconst_0
    //   1698: istore #21
    //   1700: iload #21
    //   1702: bipush #8
    //   1704: if_icmpge -> 1724
    //   1707: aload #20
    //   1709: iload #21
    //   1711: aload #8
    //   1713: iload #21
    //   1715: iaload
    //   1716: iastore
    //   1717: iinc #21, 1
    //   1720: iload_2
    //   1721: ifne -> 1700
    //   1724: iconst_0
    //   1725: istore #21
    //   1727: iload #21
    //   1729: bipush #64
    //   1731: if_icmpge -> 2222
    //   1734: iload #21
    //   1736: bipush #16
    //   1738: if_icmpge -> 1819
    //   1741: aload #19
    //   1743: iload #21
    //   1745: aload #9
    //   1747: iconst_4
    //   1748: iload #21
    //   1750: imul
    //   1751: baload
    //   1752: sipush #255
    //   1755: iand
    //   1756: bipush #24
    //   1758: ishl
    //   1759: aload #9
    //   1761: iconst_4
    //   1762: iload #21
    //   1764: imul
    //   1765: iconst_1
    //   1766: iadd
    //   1767: baload
    //   1768: sipush #255
    //   1771: iand
    //   1772: bipush #16
    //   1774: ishl
    //   1775: ior
    //   1776: aload #9
    //   1778: iconst_4
    //   1779: iload #21
    //   1781: imul
    //   1782: iconst_2
    //   1783: iadd
    //   1784: baload
    //   1785: sipush #255
    //   1788: iand
    //   1789: bipush #8
    //   1791: ishl
    //   1792: ior
    //   1793: aload #9
    //   1795: iconst_4
    //   1796: iload #21
    //   1798: imul
    //   1799: iconst_3
    //   1800: iadd
    //   1801: baload
    //   1802: sipush #255
    //   1805: iand
    //   1806: ior
    //   1807: iastore
    //   1808: iload_2
    //   1809: ifne -> 1962
    //   1812: goto -> 1819
    //   1815: invokestatic a : (Ljava/lang/Throwable;)Ljava/lang/Throwable;
    //   1818: athrow
    //   1819: aload #19
    //   1821: iload #21
    //   1823: aload #19
    //   1825: iload #21
    //   1827: iconst_2
    //   1828: isub
    //   1829: iaload
    //   1830: bipush #17
    //   1832: iushr
    //   1833: aload #19
    //   1835: iload #21
    //   1837: iconst_2
    //   1838: isub
    //   1839: iaload
    //   1840: bipush #15
    //   1842: ishl
    //   1843: ior
    //   1844: aload #19
    //   1846: iload #21
    //   1848: iconst_2
    //   1849: isub
    //   1850: iaload
    //   1851: bipush #19
    //   1853: iushr
    //   1854: aload #19
    //   1856: iload #21
    //   1858: iconst_2
    //   1859: isub
    //   1860: iaload
    //   1861: bipush #13
    //   1863: ishl
    //   1864: ior
    //   1865: ixor
    //   1866: aload #19
    //   1868: iload #21
    //   1870: iconst_2
    //   1871: isub
    //   1872: iaload
    //   1873: bipush #10
    //   1875: iushr
    //   1876: ixor
    //   1877: aload #19
    //   1879: iload #21
    //   1881: bipush #7
    //   1883: isub
    //   1884: iaload
    //   1885: iadd
    //   1886: aload #19
    //   1888: iload #21
    //   1890: bipush #15
    //   1892: isub
    //   1893: iaload
    //   1894: bipush #7
    //   1896: iushr
    //   1897: aload #19
    //   1899: iload #21
    //   1901: bipush #15
    //   1903: isub
    //   1904: iaload
    //   1905: bipush #25
    //   1907: ishl
    //   1908: ior
    //   1909: aload #19
    //   1911: iload #21
    //   1913: bipush #15
    //   1915: isub
    //   1916: iaload
    //   1917: bipush #18
    //   1919: iushr
    //   1920: aload #19
    //   1922: iload #21
    //   1924: bipush #15
    //   1926: isub
    //   1927: iaload
    //   1928: bipush #14
    //   1930: ishl
    //   1931: ior
    //   1932: ixor
    //   1933: aload #19
    //   1935: iload #21
    //   1937: bipush #15
    //   1939: isub
    //   1940: iaload
    //   1941: iconst_3
    //   1942: iushr
    //   1943: ixor
    //   1944: iadd
    //   1945: aload #19
    //   1947: iload #21
    //   1949: bipush #16
    //   1951: isub
    //   1952: iaload
    //   1953: iadd
    //   1954: iastore
    //   1955: goto -> 1962
    //   1958: invokestatic a : (Ljava/lang/Throwable;)Ljava/lang/Throwable;
    //   1961: athrow
    //   1962: aload #20
    //   1964: bipush #7
    //   1966: iaload
    //   1967: aload #20
    //   1969: iconst_4
    //   1970: iaload
    //   1971: bipush #6
    //   1973: iushr
    //   1974: aload #20
    //   1976: iconst_4
    //   1977: iaload
    //   1978: bipush #26
    //   1980: ishl
    //   1981: ior
    //   1982: aload #20
    //   1984: iconst_4
    //   1985: iaload
    //   1986: bipush #11
    //   1988: iushr
    //   1989: aload #20
    //   1991: iconst_4
    //   1992: iaload
    //   1993: bipush #21
    //   1995: ishl
    //   1996: ior
    //   1997: ixor
    //   1998: aload #20
    //   2000: iconst_4
    //   2001: iaload
    //   2002: bipush #25
    //   2004: iushr
    //   2005: aload #20
    //   2007: iconst_4
    //   2008: iaload
    //   2009: bipush #7
    //   2011: ishl
    //   2012: ior
    //   2013: ixor
    //   2014: iadd
    //   2015: aload #20
    //   2017: bipush #6
    //   2019: iaload
    //   2020: aload #20
    //   2022: iconst_4
    //   2023: iaload
    //   2024: aload #20
    //   2026: iconst_5
    //   2027: iaload
    //   2028: aload #20
    //   2030: bipush #6
    //   2032: iaload
    //   2033: ixor
    //   2034: iand
    //   2035: ixor
    //   2036: iadd
    //   2037: aload #6
    //   2039: iload #21
    //   2041: iaload
    //   2042: iadd
    //   2043: aload #19
    //   2045: iload #21
    //   2047: iaload
    //   2048: iadd
    //   2049: istore #22
    //   2051: aload #20
    //   2053: iconst_0
    //   2054: iaload
    //   2055: iconst_2
    //   2056: iushr
    //   2057: aload #20
    //   2059: iconst_0
    //   2060: iaload
    //   2061: bipush #30
    //   2063: ishl
    //   2064: ior
    //   2065: aload #20
    //   2067: iconst_0
    //   2068: iaload
    //   2069: bipush #13
    //   2071: iushr
    //   2072: aload #20
    //   2074: iconst_0
    //   2075: iaload
    //   2076: bipush #19
    //   2078: ishl
    //   2079: ior
    //   2080: ixor
    //   2081: aload #20
    //   2083: iconst_0
    //   2084: iaload
    //   2085: bipush #22
    //   2087: iushr
    //   2088: aload #20
    //   2090: iconst_0
    //   2091: iaload
    //   2092: bipush #10
    //   2094: ishl
    //   2095: ior
    //   2096: ixor
    //   2097: aload #20
    //   2099: iconst_0
    //   2100: iaload
    //   2101: aload #20
    //   2103: iconst_1
    //   2104: iaload
    //   2105: iand
    //   2106: aload #20
    //   2108: iconst_2
    //   2109: iaload
    //   2110: aload #20
    //   2112: iconst_0
    //   2113: iaload
    //   2114: aload #20
    //   2116: iconst_1
    //   2117: iaload
    //   2118: ior
    //   2119: iand
    //   2120: ior
    //   2121: iadd
    //   2122: istore #23
    //   2124: aload #20
    //   2126: iconst_3
    //   2127: dup2
    //   2128: iaload
    //   2129: iload #22
    //   2131: iadd
    //   2132: iastore
    //   2133: aload #20
    //   2135: bipush #7
    //   2137: iload #22
    //   2139: iload #23
    //   2141: iadd
    //   2142: iastore
    //   2143: aload #20
    //   2145: bipush #7
    //   2147: iaload
    //   2148: istore #22
    //   2150: aload #20
    //   2152: bipush #7
    //   2154: aload #20
    //   2156: bipush #6
    //   2158: iaload
    //   2159: iastore
    //   2160: aload #20
    //   2162: bipush #6
    //   2164: aload #20
    //   2166: iconst_5
    //   2167: iaload
    //   2168: iastore
    //   2169: aload #20
    //   2171: iconst_5
    //   2172: aload #20
    //   2174: iconst_4
    //   2175: iaload
    //   2176: iastore
    //   2177: aload #20
    //   2179: iconst_4
    //   2180: aload #20
    //   2182: iconst_3
    //   2183: iaload
    //   2184: iastore
    //   2185: aload #20
    //   2187: iconst_3
    //   2188: aload #20
    //   2190: iconst_2
    //   2191: iaload
    //   2192: iastore
    //   2193: aload #20
    //   2195: iconst_2
    //   2196: aload #20
    //   2198: iconst_1
    //   2199: iaload
    //   2200: iastore
    //   2201: aload #20
    //   2203: iconst_1
    //   2204: aload #20
    //   2206: iconst_0
    //   2207: iaload
    //   2208: iastore
    //   2209: aload #20
    //   2211: iconst_0
    //   2212: iload #22
    //   2214: iastore
    //   2215: iinc #21, 1
    //   2218: iload_2
    //   2219: ifne -> 1727
    //   2222: iconst_0
    //   2223: istore #21
    //   2225: iload #21
    //   2227: bipush #8
    //   2229: if_icmpge -> 2252
    //   2232: aload #8
    //   2234: iload #21
    //   2236: dup2
    //   2237: iaload
    //   2238: aload #20
    //   2240: iload #21
    //   2242: iaload
    //   2243: iadd
    //   2244: iastore
    //   2245: iinc #21, 1
    //   2248: iload_2
    //   2249: ifne -> 2225
    //   2252: iload #13
    //   2254: iload #18
    //   2256: iadd
    //   2257: istore #13
    //   2259: iload #17
    //   2261: iload #18
    //   2263: isub
    //   2264: istore #17
    //   2266: iconst_0
    //   2267: istore #12
    //   2269: iload #17
    //   2271: bipush #64
    //   2273: if_icmplt -> 2883
    //   2276: iconst_0
    //   2277: istore #19
    //   2279: iload #19
    //   2281: bipush #64
    //   2283: if_icmpge -> 2306
    //   2286: aload #10
    //   2288: iload #19
    //   2290: aload #5
    //   2292: iload #13
    //   2294: iload #19
    //   2296: iadd
    //   2297: baload
    //   2298: bastore
    //   2299: iinc #19, 1
    //   2302: iload_2
    //   2303: ifne -> 2279
    //   2306: bipush #64
    //   2308: newarray int
    //   2310: astore #19
    //   2312: bipush #8
    //   2314: newarray int
    //   2316: astore #20
    //   2318: iconst_0
    //   2319: istore #21
    //   2321: iload #21
    //   2323: bipush #8
    //   2325: if_icmpge -> 2345
    //   2328: aload #20
    //   2330: iload #21
    //   2332: aload #8
    //   2334: iload #21
    //   2336: iaload
    //   2337: iastore
    //   2338: iinc #21, 1
    //   2341: iload_2
    //   2342: ifne -> 2321
    //   2345: iconst_0
    //   2346: istore #21
    //   2348: iload #21
    //   2350: bipush #64
    //   2352: if_icmpge -> 2843
    //   2355: iload #21
    //   2357: bipush #16
    //   2359: if_icmpge -> 2440
    //   2362: aload #19
    //   2364: iload #21
    //   2366: aload #10
    //   2368: iconst_4
    //   2369: iload #21
    //   2371: imul
    //   2372: baload
    //   2373: sipush #255
    //   2376: iand
    //   2377: bipush #24
    //   2379: ishl
    //   2380: aload #10
    //   2382: iconst_4
    //   2383: iload #21
    //   2385: imul
    //   2386: iconst_1
    //   2387: iadd
    //   2388: baload
    //   2389: sipush #255
    //   2392: iand
    //   2393: bipush #16
    //   2395: ishl
    //   2396: ior
    //   2397: aload #10
    //   2399: iconst_4
    //   2400: iload #21
    //   2402: imul
    //   2403: iconst_2
    //   2404: iadd
    //   2405: baload
    //   2406: sipush #255
    //   2409: iand
    //   2410: bipush #8
    //   2412: ishl
    //   2413: ior
    //   2414: aload #10
    //   2416: iconst_4
    //   2417: iload #21
    //   2419: imul
    //   2420: iconst_3
    //   2421: iadd
    //   2422: baload
    //   2423: sipush #255
    //   2426: iand
    //   2427: ior
    //   2428: iastore
    //   2429: iload_2
    //   2430: ifne -> 2583
    //   2433: goto -> 2440
    //   2436: invokestatic a : (Ljava/lang/Throwable;)Ljava/lang/Throwable;
    //   2439: athrow
    //   2440: aload #19
    //   2442: iload #21
    //   2444: aload #19
    //   2446: iload #21
    //   2448: iconst_2
    //   2449: isub
    //   2450: iaload
    //   2451: bipush #17
    //   2453: iushr
    //   2454: aload #19
    //   2456: iload #21
    //   2458: iconst_2
    //   2459: isub
    //   2460: iaload
    //   2461: bipush #15
    //   2463: ishl
    //   2464: ior
    //   2465: aload #19
    //   2467: iload #21
    //   2469: iconst_2
    //   2470: isub
    //   2471: iaload
    //   2472: bipush #19
    //   2474: iushr
    //   2475: aload #19
    //   2477: iload #21
    //   2479: iconst_2
    //   2480: isub
    //   2481: iaload
    //   2482: bipush #13
    //   2484: ishl
    //   2485: ior
    //   2486: ixor
    //   2487: aload #19
    //   2489: iload #21
    //   2491: iconst_2
    //   2492: isub
    //   2493: iaload
    //   2494: bipush #10
    //   2496: iushr
    //   2497: ixor
    //   2498: aload #19
    //   2500: iload #21
    //   2502: bipush #7
    //   2504: isub
    //   2505: iaload
    //   2506: iadd
    //   2507: aload #19
    //   2509: iload #21
    //   2511: bipush #15
    //   2513: isub
    //   2514: iaload
    //   2515: bipush #7
    //   2517: iushr
    //   2518: aload #19
    //   2520: iload #21
    //   2522: bipush #15
    //   2524: isub
    //   2525: iaload
    //   2526: bipush #25
    //   2528: ishl
    //   2529: ior
    //   2530: aload #19
    //   2532: iload #21
    //   2534: bipush #15
    //   2536: isub
    //   2537: iaload
    //   2538: bipush #18
    //   2540: iushr
    //   2541: aload #19
    //   2543: iload #21
    //   2545: bipush #15
    //   2547: isub
    //   2548: iaload
    //   2549: bipush #14
    //   2551: ishl
    //   2552: ior
    //   2553: ixor
    //   2554: aload #19
    //   2556: iload #21
    //   2558: bipush #15
    //   2560: isub
    //   2561: iaload
    //   2562: iconst_3
    //   2563: iushr
    //   2564: ixor
    //   2565: iadd
    //   2566: aload #19
    //   2568: iload #21
    //   2570: bipush #16
    //   2572: isub
    //   2573: iaload
    //   2574: iadd
    //   2575: iastore
    //   2576: goto -> 2583
    //   2579: invokestatic a : (Ljava/lang/Throwable;)Ljava/lang/Throwable;
    //   2582: athrow
    //   2583: aload #20
    //   2585: bipush #7
    //   2587: iaload
    //   2588: aload #20
    //   2590: iconst_4
    //   2591: iaload
    //   2592: bipush #6
    //   2594: iushr
    //   2595: aload #20
    //   2597: iconst_4
    //   2598: iaload
    //   2599: bipush #26
    //   2601: ishl
    //   2602: ior
    //   2603: aload #20
    //   2605: iconst_4
    //   2606: iaload
    //   2607: bipush #11
    //   2609: iushr
    //   2610: aload #20
    //   2612: iconst_4
    //   2613: iaload
    //   2614: bipush #21
    //   2616: ishl
    //   2617: ior
    //   2618: ixor
    //   2619: aload #20
    //   2621: iconst_4
    //   2622: iaload
    //   2623: bipush #25
    //   2625: iushr
    //   2626: aload #20
    //   2628: iconst_4
    //   2629: iaload
    //   2630: bipush #7
    //   2632: ishl
    //   2633: ior
    //   2634: ixor
    //   2635: iadd
    //   2636: aload #20
    //   2638: bipush #6
    //   2640: iaload
    //   2641: aload #20
    //   2643: iconst_4
    //   2644: iaload
    //   2645: aload #20
    //   2647: iconst_5
    //   2648: iaload
    //   2649: aload #20
    //   2651: bipush #6
    //   2653: iaload
    //   2654: ixor
    //   2655: iand
    //   2656: ixor
    //   2657: iadd
    //   2658: aload #6
    //   2660: iload #21
    //   2662: iaload
    //   2663: iadd
    //   2664: aload #19
    //   2666: iload #21
    //   2668: iaload
    //   2669: iadd
    //   2670: istore #22
    //   2672: aload #20
    //   2674: iconst_0
    //   2675: iaload
    //   2676: iconst_2
    //   2677: iushr
    //   2678: aload #20
    //   2680: iconst_0
    //   2681: iaload
    //   2682: bipush #30
    //   2684: ishl
    //   2685: ior
    //   2686: aload #20
    //   2688: iconst_0
    //   2689: iaload
    //   2690: bipush #13
    //   2692: iushr
    //   2693: aload #20
    //   2695: iconst_0
    //   2696: iaload
    //   2697: bipush #19
    //   2699: ishl
    //   2700: ior
    //   2701: ixor
    //   2702: aload #20
    //   2704: iconst_0
    //   2705: iaload
    //   2706: bipush #22
    //   2708: iushr
    //   2709: aload #20
    //   2711: iconst_0
    //   2712: iaload
    //   2713: bipush #10
    //   2715: ishl
    //   2716: ior
    //   2717: ixor
    //   2718: aload #20
    //   2720: iconst_0
    //   2721: iaload
    //   2722: aload #20
    //   2724: iconst_1
    //   2725: iaload
    //   2726: iand
    //   2727: aload #20
    //   2729: iconst_2
    //   2730: iaload
    //   2731: aload #20
    //   2733: iconst_0
    //   2734: iaload
    //   2735: aload #20
    //   2737: iconst_1
    //   2738: iaload
    //   2739: ior
    //   2740: iand
    //   2741: ior
    //   2742: iadd
    //   2743: istore #23
    //   2745: aload #20
    //   2747: iconst_3
    //   2748: dup2
    //   2749: iaload
    //   2750: iload #22
    //   2752: iadd
    //   2753: iastore
    //   2754: aload #20
    //   2756: bipush #7
    //   2758: iload #22
    //   2760: iload #23
    //   2762: iadd
    //   2763: iastore
    //   2764: aload #20
    //   2766: bipush #7
    //   2768: iaload
    //   2769: istore #22
    //   2771: aload #20
    //   2773: bipush #7
    //   2775: aload #20
    //   2777: bipush #6
    //   2779: iaload
    //   2780: iastore
    //   2781: aload #20
    //   2783: bipush #6
    //   2785: aload #20
    //   2787: iconst_5
    //   2788: iaload
    //   2789: iastore
    //   2790: aload #20
    //   2792: iconst_5
    //   2793: aload #20
    //   2795: iconst_4
    //   2796: iaload
    //   2797: iastore
    //   2798: aload #20
    //   2800: iconst_4
    //   2801: aload #20
    //   2803: iconst_3
    //   2804: iaload
    //   2805: iastore
    //   2806: aload #20
    //   2808: iconst_3
    //   2809: aload #20
    //   2811: iconst_2
    //   2812: iaload
    //   2813: iastore
    //   2814: aload #20
    //   2816: iconst_2
    //   2817: aload #20
    //   2819: iconst_1
    //   2820: iaload
    //   2821: iastore
    //   2822: aload #20
    //   2824: iconst_1
    //   2825: aload #20
    //   2827: iconst_0
    //   2828: iaload
    //   2829: iastore
    //   2830: aload #20
    //   2832: iconst_0
    //   2833: iload #22
    //   2835: iastore
    //   2836: iinc #21, 1
    //   2839: iload_2
    //   2840: ifne -> 2348
    //   2843: iconst_0
    //   2844: istore #21
    //   2846: iload #21
    //   2848: bipush #8
    //   2850: if_icmpge -> 2873
    //   2853: aload #8
    //   2855: iload #21
    //   2857: dup2
    //   2858: iaload
    //   2859: aload #20
    //   2861: iload #21
    //   2863: iaload
    //   2864: iadd
    //   2865: iastore
    //   2866: iinc #21, 1
    //   2869: iload_2
    //   2870: ifne -> 2846
    //   2873: iinc #13, 64
    //   2876: iinc #17, -64
    //   2879: iload_2
    //   2880: ifne -> 2269
    //   2883: iload #17
    //   2885: ifle -> 2921
    //   2888: iconst_0
    //   2889: istore #19
    //   2891: iload #19
    //   2893: iload #17
    //   2895: if_icmpge -> 2921
    //   2898: aload #9
    //   2900: iload #12
    //   2902: iload #19
    //   2904: iadd
    //   2905: aload #5
    //   2907: iload #13
    //   2909: iload #19
    //   2911: iadd
    //   2912: baload
    //   2913: bastore
    //   2914: iinc #19, 1
    //   2917: iload_2
    //   2918: ifne -> 2891
    //   2921: bipush #8
    //   2923: newarray byte
    //   2925: astore #19
    //   2927: aload #19
    //   2929: iconst_0
    //   2930: iload #14
    //   2932: bipush #24
    //   2934: iushr
    //   2935: i2b
    //   2936: bastore
    //   2937: aload #19
    //   2939: iconst_1
    //   2940: iload #14
    //   2942: bipush #16
    //   2944: iushr
    //   2945: i2b
    //   2946: bastore
    //   2947: aload #19
    //   2949: iconst_2
    //   2950: iload #14
    //   2952: bipush #8
    //   2954: iushr
    //   2955: i2b
    //   2956: bastore
    //   2957: aload #19
    //   2959: iconst_3
    //   2960: iload #14
    //   2962: i2b
    //   2963: bastore
    //   2964: aload #19
    //   2966: iconst_4
    //   2967: iload #15
    //   2969: bipush #24
    //   2971: iushr
    //   2972: i2b
    //   2973: bastore
    //   2974: aload #19
    //   2976: iconst_5
    //   2977: iload #15
    //   2979: bipush #16
    //   2981: iushr
    //   2982: i2b
    //   2983: bastore
    //   2984: aload #19
    //   2986: bipush #6
    //   2988: iload #15
    //   2990: bipush #8
    //   2992: iushr
    //   2993: i2b
    //   2994: bastore
    //   2995: aload #19
    //   2997: bipush #7
    //   2999: iload #15
    //   3001: i2b
    //   3002: bastore
    //   3003: bipush #8
    //   3005: istore #11
    //   3007: aload #7
    //   3009: iconst_0
    //   3010: iaload
    //   3011: bipush #63
    //   3013: iand
    //   3014: istore #12
    //   3016: bipush #64
    //   3018: iload #12
    //   3020: isub
    //   3021: istore #18
    //   3023: aload #7
    //   3025: iconst_0
    //   3026: dup2
    //   3027: iaload
    //   3028: iload #11
    //   3030: iadd
    //   3031: iastore
    //   3032: aload #7
    //   3034: iconst_0
    //   3035: dup2
    //   3036: iaload
    //   3037: iconst_m1
    //   3038: iand
    //   3039: iastore
    //   3040: aload #7
    //   3042: iconst_0
    //   3043: iaload
    //   3044: iload #11
    //   3046: if_icmpge -> 3064
    //   3049: aload #7
    //   3051: iconst_1
    //   3052: dup2
    //   3053: iaload
    //   3054: iconst_1
    //   3055: iadd
    //   3056: iastore
    //   3057: goto -> 3064
    //   3060: invokestatic a : (Ljava/lang/Throwable;)Ljava/lang/Throwable;
    //   3063: athrow
    //   3064: iload #12
    //   3066: ifle -> 3680
    //   3069: iload #11
    //   3071: iload #18
    //   3073: if_icmplt -> 3680
    //   3076: goto -> 3083
    //   3079: invokestatic a : (Ljava/lang/Throwable;)Ljava/lang/Throwable;
    //   3082: athrow
    //   3083: iconst_0
    //   3084: istore #20
    //   3086: iload #20
    //   3088: iload #18
    //   3090: if_icmpge -> 3113
    //   3093: aload #9
    //   3095: iload #12
    //   3097: iload #20
    //   3099: iadd
    //   3100: aload #19
    //   3102: iload #20
    //   3104: baload
    //   3105: bastore
    //   3106: iinc #20, 1
    //   3109: iload_2
    //   3110: ifne -> 3086
    //   3113: bipush #64
    //   3115: newarray int
    //   3117: astore #20
    //   3119: bipush #8
    //   3121: newarray int
    //   3123: astore #21
    //   3125: iconst_0
    //   3126: istore #22
    //   3128: iload #22
    //   3130: bipush #8
    //   3132: if_icmpge -> 3152
    //   3135: aload #21
    //   3137: iload #22
    //   3139: aload #8
    //   3141: iload #22
    //   3143: iaload
    //   3144: iastore
    //   3145: iinc #22, 1
    //   3148: iload_2
    //   3149: ifne -> 3128
    //   3152: iconst_0
    //   3153: istore #22
    //   3155: iload #22
    //   3157: bipush #64
    //   3159: if_icmpge -> 3650
    //   3162: iload #22
    //   3164: bipush #16
    //   3166: if_icmpge -> 3247
    //   3169: aload #20
    //   3171: iload #22
    //   3173: aload #9
    //   3175: iconst_4
    //   3176: iload #22
    //   3178: imul
    //   3179: baload
    //   3180: sipush #255
    //   3183: iand
    //   3184: bipush #24
    //   3186: ishl
    //   3187: aload #9
    //   3189: iconst_4
    //   3190: iload #22
    //   3192: imul
    //   3193: iconst_1
    //   3194: iadd
    //   3195: baload
    //   3196: sipush #255
    //   3199: iand
    //   3200: bipush #16
    //   3202: ishl
    //   3203: ior
    //   3204: aload #9
    //   3206: iconst_4
    //   3207: iload #22
    //   3209: imul
    //   3210: iconst_2
    //   3211: iadd
    //   3212: baload
    //   3213: sipush #255
    //   3216: iand
    //   3217: bipush #8
    //   3219: ishl
    //   3220: ior
    //   3221: aload #9
    //   3223: iconst_4
    //   3224: iload #22
    //   3226: imul
    //   3227: iconst_3
    //   3228: iadd
    //   3229: baload
    //   3230: sipush #255
    //   3233: iand
    //   3234: ior
    //   3235: iastore
    //   3236: iload_2
    //   3237: ifne -> 3390
    //   3240: goto -> 3247
    //   3243: invokestatic a : (Ljava/lang/Throwable;)Ljava/lang/Throwable;
    //   3246: athrow
    //   3247: aload #20
    //   3249: iload #22
    //   3251: aload #20
    //   3253: iload #22
    //   3255: iconst_2
    //   3256: isub
    //   3257: iaload
    //   3258: bipush #17
    //   3260: iushr
    //   3261: aload #20
    //   3263: iload #22
    //   3265: iconst_2
    //   3266: isub
    //   3267: iaload
    //   3268: bipush #15
    //   3270: ishl
    //   3271: ior
    //   3272: aload #20
    //   3274: iload #22
    //   3276: iconst_2
    //   3277: isub
    //   3278: iaload
    //   3279: bipush #19
    //   3281: iushr
    //   3282: aload #20
    //   3284: iload #22
    //   3286: iconst_2
    //   3287: isub
    //   3288: iaload
    //   3289: bipush #13
    //   3291: ishl
    //   3292: ior
    //   3293: ixor
    //   3294: aload #20
    //   3296: iload #22
    //   3298: iconst_2
    //   3299: isub
    //   3300: iaload
    //   3301: bipush #10
    //   3303: iushr
    //   3304: ixor
    //   3305: aload #20
    //   3307: iload #22
    //   3309: bipush #7
    //   3311: isub
    //   3312: iaload
    //   3313: iadd
    //   3314: aload #20
    //   3316: iload #22
    //   3318: bipush #15
    //   3320: isub
    //   3321: iaload
    //   3322: bipush #7
    //   3324: iushr
    //   3325: aload #20
    //   3327: iload #22
    //   3329: bipush #15
    //   3331: isub
    //   3332: iaload
    //   3333: bipush #25
    //   3335: ishl
    //   3336: ior
    //   3337: aload #20
    //   3339: iload #22
    //   3341: bipush #15
    //   3343: isub
    //   3344: iaload
    //   3345: bipush #18
    //   3347: iushr
    //   3348: aload #20
    //   3350: iload #22
    //   3352: bipush #15
    //   3354: isub
    //   3355: iaload
    //   3356: bipush #14
    //   3358: ishl
    //   3359: ior
    //   3360: ixor
    //   3361: aload #20
    //   3363: iload #22
    //   3365: bipush #15
    //   3367: isub
    //   3368: iaload
    //   3369: iconst_3
    //   3370: iushr
    //   3371: ixor
    //   3372: iadd
    //   3373: aload #20
    //   3375: iload #22
    //   3377: bipush #16
    //   3379: isub
    //   3380: iaload
    //   3381: iadd
    //   3382: iastore
    //   3383: goto -> 3390
    //   3386: invokestatic a : (Ljava/lang/Throwable;)Ljava/lang/Throwable;
    //   3389: athrow
    //   3390: aload #21
    //   3392: bipush #7
    //   3394: iaload
    //   3395: aload #21
    //   3397: iconst_4
    //   3398: iaload
    //   3399: bipush #6
    //   3401: iushr
    //   3402: aload #21
    //   3404: iconst_4
    //   3405: iaload
    //   3406: bipush #26
    //   3408: ishl
    //   3409: ior
    //   3410: aload #21
    //   3412: iconst_4
    //   3413: iaload
    //   3414: bipush #11
    //   3416: iushr
    //   3417: aload #21
    //   3419: iconst_4
    //   3420: iaload
    //   3421: bipush #21
    //   3423: ishl
    //   3424: ior
    //   3425: ixor
    //   3426: aload #21
    //   3428: iconst_4
    //   3429: iaload
    //   3430: bipush #25
    //   3432: iushr
    //   3433: aload #21
    //   3435: iconst_4
    //   3436: iaload
    //   3437: bipush #7
    //   3439: ishl
    //   3440: ior
    //   3441: ixor
    //   3442: iadd
    //   3443: aload #21
    //   3445: bipush #6
    //   3447: iaload
    //   3448: aload #21
    //   3450: iconst_4
    //   3451: iaload
    //   3452: aload #21
    //   3454: iconst_5
    //   3455: iaload
    //   3456: aload #21
    //   3458: bipush #6
    //   3460: iaload
    //   3461: ixor
    //   3462: iand
    //   3463: ixor
    //   3464: iadd
    //   3465: aload #6
    //   3467: iload #22
    //   3469: iaload
    //   3470: iadd
    //   3471: aload #20
    //   3473: iload #22
    //   3475: iaload
    //   3476: iadd
    //   3477: istore #23
    //   3479: aload #21
    //   3481: iconst_0
    //   3482: iaload
    //   3483: iconst_2
    //   3484: iushr
    //   3485: aload #21
    //   3487: iconst_0
    //   3488: iaload
    //   3489: bipush #30
    //   3491: ishl
    //   3492: ior
    //   3493: aload #21
    //   3495: iconst_0
    //   3496: iaload
    //   3497: bipush #13
    //   3499: iushr
    //   3500: aload #21
    //   3502: iconst_0
    //   3503: iaload
    //   3504: bipush #19
    //   3506: ishl
    //   3507: ior
    //   3508: ixor
    //   3509: aload #21
    //   3511: iconst_0
    //   3512: iaload
    //   3513: bipush #22
    //   3515: iushr
    //   3516: aload #21
    //   3518: iconst_0
    //   3519: iaload
    //   3520: bipush #10
    //   3522: ishl
    //   3523: ior
    //   3524: ixor
    //   3525: aload #21
    //   3527: iconst_0
    //   3528: iaload
    //   3529: aload #21
    //   3531: iconst_1
    //   3532: iaload
    //   3533: iand
    //   3534: aload #21
    //   3536: iconst_2
    //   3537: iaload
    //   3538: aload #21
    //   3540: iconst_0
    //   3541: iaload
    //   3542: aload #21
    //   3544: iconst_1
    //   3545: iaload
    //   3546: ior
    //   3547: iand
    //   3548: ior
    //   3549: iadd
    //   3550: istore #24
    //   3552: aload #21
    //   3554: iconst_3
    //   3555: dup2
    //   3556: iaload
    //   3557: iload #23
    //   3559: iadd
    //   3560: iastore
    //   3561: aload #21
    //   3563: bipush #7
    //   3565: iload #23
    //   3567: iload #24
    //   3569: iadd
    //   3570: iastore
    //   3571: aload #21
    //   3573: bipush #7
    //   3575: iaload
    //   3576: istore #23
    //   3578: aload #21
    //   3580: bipush #7
    //   3582: aload #21
    //   3584: bipush #6
    //   3586: iaload
    //   3587: iastore
    //   3588: aload #21
    //   3590: bipush #6
    //   3592: aload #21
    //   3594: iconst_5
    //   3595: iaload
    //   3596: iastore
    //   3597: aload #21
    //   3599: iconst_5
    //   3600: aload #21
    //   3602: iconst_4
    //   3603: iaload
    //   3604: iastore
    //   3605: aload #21
    //   3607: iconst_4
    //   3608: aload #21
    //   3610: iconst_3
    //   3611: iaload
    //   3612: iastore
    //   3613: aload #21
    //   3615: iconst_3
    //   3616: aload #21
    //   3618: iconst_2
    //   3619: iaload
    //   3620: iastore
    //   3621: aload #21
    //   3623: iconst_2
    //   3624: aload #21
    //   3626: iconst_1
    //   3627: iaload
    //   3628: iastore
    //   3629: aload #21
    //   3631: iconst_1
    //   3632: aload #21
    //   3634: iconst_0
    //   3635: iaload
    //   3636: iastore
    //   3637: aload #21
    //   3639: iconst_0
    //   3640: iload #23
    //   3642: iastore
    //   3643: iinc #22, 1
    //   3646: iload_2
    //   3647: ifne -> 3155
    //   3650: iconst_0
    //   3651: istore #22
    //   3653: iload #22
    //   3655: bipush #8
    //   3657: if_icmpge -> 3680
    //   3660: aload #8
    //   3662: iload #22
    //   3664: dup2
    //   3665: iaload
    //   3666: aload #21
    //   3668: iload #22
    //   3670: iaload
    //   3671: iadd
    //   3672: iastore
    //   3673: iinc #22, 1
    //   3676: iload_2
    //   3677: ifne -> 3653
    //   3680: bipush #32
    //   3682: newarray byte
    //   3684: astore #4
    //   3686: sipush #-18638
    //   3689: aload #4
    //   3691: iconst_0
    //   3692: aload #8
    //   3694: iconst_0
    //   3695: iaload
    //   3696: bipush #24
    //   3698: iushr
    //   3699: i2b
    //   3700: bastore
    //   3701: sipush #14236
    //   3704: aload #4
    //   3706: iconst_1
    //   3707: aload #8
    //   3709: iconst_0
    //   3710: iaload
    //   3711: bipush #16
    //   3713: iushr
    //   3714: i2b
    //   3715: bastore
    //   3716: aload #4
    //   3718: iconst_2
    //   3719: aload #8
    //   3721: iconst_0
    //   3722: iaload
    //   3723: bipush #8
    //   3725: iushr
    //   3726: i2b
    //   3727: bastore
    //   3728: aload #4
    //   3730: iconst_3
    //   3731: aload #8
    //   3733: iconst_0
    //   3734: iaload
    //   3735: i2b
    //   3736: bastore
    //   3737: aload #4
    //   3739: iconst_4
    //   3740: aload #8
    //   3742: iconst_1
    //   3743: iaload
    //   3744: bipush #24
    //   3746: iushr
    //   3747: i2b
    //   3748: bastore
    //   3749: aload #4
    //   3751: iconst_5
    //   3752: aload #8
    //   3754: iconst_1
    //   3755: iaload
    //   3756: bipush #16
    //   3758: iushr
    //   3759: i2b
    //   3760: bastore
    //   3761: aload #4
    //   3763: bipush #6
    //   3765: aload #8
    //   3767: iconst_1
    //   3768: iaload
    //   3769: bipush #8
    //   3771: iushr
    //   3772: i2b
    //   3773: bastore
    //   3774: aload #4
    //   3776: bipush #7
    //   3778: aload #8
    //   3780: iconst_1
    //   3781: iaload
    //   3782: i2b
    //   3783: bastore
    //   3784: aload #4
    //   3786: bipush #8
    //   3788: aload #8
    //   3790: iconst_2
    //   3791: iaload
    //   3792: bipush #24
    //   3794: iushr
    //   3795: i2b
    //   3796: bastore
    //   3797: aload #4
    //   3799: bipush #9
    //   3801: aload #8
    //   3803: iconst_2
    //   3804: iaload
    //   3805: bipush #16
    //   3807: iushr
    //   3808: i2b
    //   3809: bastore
    //   3810: aload #4
    //   3812: bipush #10
    //   3814: aload #8
    //   3816: iconst_2
    //   3817: iaload
    //   3818: bipush #8
    //   3820: iushr
    //   3821: i2b
    //   3822: bastore
    //   3823: aload #4
    //   3825: bipush #11
    //   3827: aload #8
    //   3829: iconst_2
    //   3830: iaload
    //   3831: i2b
    //   3832: bastore
    //   3833: aload #4
    //   3835: bipush #12
    //   3837: aload #8
    //   3839: iconst_3
    //   3840: iaload
    //   3841: bipush #24
    //   3843: iushr
    //   3844: i2b
    //   3845: bastore
    //   3846: aload #4
    //   3848: bipush #13
    //   3850: aload #8
    //   3852: iconst_3
    //   3853: iaload
    //   3854: bipush #16
    //   3856: iushr
    //   3857: i2b
    //   3858: bastore
    //   3859: aload #4
    //   3861: bipush #14
    //   3863: aload #8
    //   3865: iconst_3
    //   3866: iaload
    //   3867: bipush #8
    //   3869: iushr
    //   3870: i2b
    //   3871: bastore
    //   3872: aload #4
    //   3874: bipush #15
    //   3876: aload #8
    //   3878: iconst_3
    //   3879: iaload
    //   3880: i2b
    //   3881: bastore
    //   3882: aload #4
    //   3884: bipush #16
    //   3886: aload #8
    //   3888: iconst_4
    //   3889: iaload
    //   3890: bipush #24
    //   3892: iushr
    //   3893: i2b
    //   3894: bastore
    //   3895: aload #4
    //   3897: bipush #17
    //   3899: aload #8
    //   3901: iconst_4
    //   3902: iaload
    //   3903: bipush #16
    //   3905: iushr
    //   3906: i2b
    //   3907: bastore
    //   3908: aload #4
    //   3910: bipush #18
    //   3912: aload #8
    //   3914: iconst_4
    //   3915: iaload
    //   3916: bipush #8
    //   3918: iushr
    //   3919: i2b
    //   3920: bastore
    //   3921: aload #4
    //   3923: bipush #19
    //   3925: aload #8
    //   3927: iconst_4
    //   3928: iaload
    //   3929: i2b
    //   3930: bastore
    //   3931: aload #4
    //   3933: bipush #20
    //   3935: aload #8
    //   3937: iconst_5
    //   3938: iaload
    //   3939: bipush #24
    //   3941: iushr
    //   3942: i2b
    //   3943: bastore
    //   3944: aload #4
    //   3946: bipush #21
    //   3948: aload #8
    //   3950: iconst_5
    //   3951: iaload
    //   3952: bipush #16
    //   3954: iushr
    //   3955: i2b
    //   3956: bastore
    //   3957: aload #4
    //   3959: bipush #22
    //   3961: aload #8
    //   3963: iconst_5
    //   3964: iaload
    //   3965: bipush #8
    //   3967: iushr
    //   3968: i2b
    //   3969: bastore
    //   3970: aload #4
    //   3972: bipush #23
    //   3974: aload #8
    //   3976: iconst_5
    //   3977: iaload
    //   3978: i2b
    //   3979: bastore
    //   3980: aload #4
    //   3982: bipush #24
    //   3984: aload #8
    //   3986: bipush #6
    //   3988: iaload
    //   3989: bipush #24
    //   3991: iushr
    //   3992: i2b
    //   3993: bastore
    //   3994: aload #4
    //   3996: bipush #25
    //   3998: aload #8
    //   4000: bipush #6
    //   4002: iaload
    //   4003: bipush #16
    //   4005: iushr
    //   4006: i2b
    //   4007: bastore
    //   4008: aload #4
    //   4010: bipush #26
    //   4012: aload #8
    //   4014: bipush #6
    //   4016: iaload
    //   4017: bipush #8
    //   4019: iushr
    //   4020: i2b
    //   4021: bastore
    //   4022: aload #4
    //   4024: bipush #27
    //   4026: aload #8
    //   4028: bipush #6
    //   4030: iaload
    //   4031: i2b
    //   4032: bastore
    //   4033: aload #4
    //   4035: bipush #28
    //   4037: aload #8
    //   4039: bipush #7
    //   4041: iaload
    //   4042: bipush #24
    //   4044: iushr
    //   4045: i2b
    //   4046: bastore
    //   4047: aload #4
    //   4049: bipush #29
    //   4051: aload #8
    //   4053: bipush #7
    //   4055: iaload
    //   4056: bipush #16
    //   4058: iushr
    //   4059: i2b
    //   4060: bastore
    //   4061: aload #4
    //   4063: bipush #30
    //   4065: aload #8
    //   4067: bipush #7
    //   4069: iaload
    //   4070: bipush #8
    //   4072: iushr
    //   4073: i2b
    //   4074: bastore
    //   4075: aload #4
    //   4077: bipush #31
    //   4079: aload #8
    //   4081: bipush #7
    //   4083: iaload
    //   4084: i2b
    //   4085: bastore
    //   4086: new java/math/BigInteger
    //   4089: dup
    //   4090: aload #4
    //   4092: invokespecial <init> : ([B)V
    //   4095: invokevirtual abs : ()Ljava/math/BigInteger;
    //   4098: putstatic burp/Ze_l.ZX : Ljava/lang/Object;
    //   4101: invokestatic a : (II)Ljava/lang/String;
    //   4104: iconst_1
    //   4105: ldc burp/Zzi_
    //   4107: invokevirtual getClassLoader : ()Ljava/lang/ClassLoader;
    //   4110: invokestatic forName : (Ljava/lang/String;ZLjava/lang/ClassLoader;)Ljava/lang/Class;
    //   4113: invokevirtual getDeclaredFields : ()[Ljava/lang/reflect/Field;
    //   4116: astore_3
    //   4117: aload_3
    //   4118: arraylength
    //   4119: istore #4
    //   4121: iconst_0
    //   4122: istore #5
    //   4124: iload #5
    //   4126: iload #4
    //   4128: if_icmpge -> 4265
    //   4131: aload_3
    //   4132: iload #5
    //   4134: aaload
    //   4135: astore #6
    //   4137: aload #6
    //   4139: invokevirtual getModifiers : ()I
    //   4142: invokestatic isStatic : (I)Z
    //   4145: ifne -> 4155
    //   4148: goto -> 4258
    //   4151: invokestatic a : (Ljava/lang/Throwable;)Ljava/lang/Throwable;
    //   4154: athrow
    //   4155: aload #6
    //   4157: invokevirtual getType : ()Ljava/lang/Class;
    //   4160: astore #7
    //   4162: aload #7
    //   4164: ifnull -> 4245
    //   4167: aload #7
    //   4169: invokevirtual isPrimitive : ()Z
    //   4172: ifne -> 4245
    //   4175: goto -> 4182
    //   4178: invokestatic a : (Ljava/lang/Throwable;)Ljava/lang/Throwable;
    //   4181: athrow
    //   4182: aload #7
    //   4184: invokevirtual getPackage : ()Ljava/lang/Package;
    //   4187: ifnull -> 4245
    //   4190: goto -> 4197
    //   4193: invokestatic a : (Ljava/lang/Throwable;)Ljava/lang/Throwable;
    //   4196: athrow
    //   4197: aload #7
    //   4199: invokevirtual getPackage : ()Ljava/lang/Package;
    //   4202: invokevirtual getName : ()Ljava/lang/String;
    //   4205: ifnull -> 4245
    //   4208: goto -> 4215
    //   4211: invokestatic a : (Ljava/lang/Throwable;)Ljava/lang/Throwable;
    //   4214: athrow
    //   4215: aload #7
    //   4217: invokevirtual getPackage : ()Ljava/lang/Package;
    //   4220: invokevirtual getName : ()Ljava/lang/String;
    //   4223: sipush #-18632
    //   4226: sipush #27716
    //   4229: invokestatic a : (II)Ljava/lang/String;
    //   4232: invokevirtual startsWith : (Ljava/lang/String;)Z
    //   4235: ifne -> 4245
    //   4238: goto -> 4245
    //   4241: invokestatic a : (Ljava/lang/Throwable;)Ljava/lang/Throwable;
    //   4244: athrow
    //   4245: aload #6
    //   4247: iconst_1
    //   4248: invokevirtual setAccessible : (Z)V
    //   4251: aload #6
    //   4253: aconst_null
    //   4254: invokevirtual get : (Ljava/lang/Object;)Ljava/lang/Object;
    //   4257: pop
    //   4258: iinc #5, 1
    //   4261: iload_2
    //   4262: ifne -> 4124
    //   4265: sipush #-18647
    //   4268: sipush #-2721
    //   4271: invokestatic a : (II)Ljava/lang/String;
    //   4274: invokestatic forName : (Ljava/lang/String;)Ljava/lang/Class;
    //   4277: invokevirtual getDeclaredMethods : ()[Ljava/lang/reflect/Method;
    //   4280: astore_3
    //   4281: aload_3
    //   4282: arraylength
    //   4283: istore #4
    //   4285: iconst_0
    //   4286: istore #5
    //   4288: iload #5
    //   4290: iload #4
    //   4292: if_icmpge -> 4424
    //   4295: aload_3
    //   4296: iload #5
    //   4298: aaload
    //   4299: astore #6
    //   4301: aload #6
    //   4303: invokevirtual getParameterTypes : ()[Ljava/lang/Class;
    //   4306: pop
    //   4307: aload #6
    //   4309: invokevirtual getModifiers : ()I
    //   4312: invokestatic isStatic : (I)Z
    //   4315: ifeq -> 4410
    //   4318: aload #6
    //   4320: invokevirtual getParameterTypes : ()[Ljava/lang/Class;
    //   4323: arraylength
    //   4324: iconst_2
    //   4325: if_icmpne -> 4410
    //   4328: goto -> 4335
    //   4331: invokestatic a : (Ljava/lang/Throwable;)Ljava/lang/Throwable;
    //   4334: athrow
    //   4335: aload #6
    //   4337: invokevirtual getReturnType : ()Ljava/lang/Class;
    //   4340: getstatic java/lang/Void.TYPE : Ljava/lang/Class;
    //   4343: invokevirtual equals : (Ljava/lang/Object;)Z
    //   4346: ifeq -> 4410
    //   4349: goto -> 4356
    //   4352: invokestatic a : (Ljava/lang/Throwable;)Ljava/lang/Throwable;
    //   4355: athrow
    //   4356: aload #6
    //   4358: iconst_1
    //   4359: invokevirtual setAccessible : (Z)V
    //   4362: aload #6
    //   4364: aconst_null
    //   4365: iconst_2
    //   4366: anewarray java/lang/Object
    //   4369: dup
    //   4370: iconst_0
    //   4371: aload_0
    //   4372: aastore
    //   4373: dup
    //   4374: iconst_1
    //   4375: aload_1
    //   4376: ifnonnull -> 4394
    //   4379: goto -> 4386
    //   4382: invokestatic a : (Ljava/lang/Throwable;)Ljava/lang/Throwable;
    //   4385: athrow
    //   4386: aload_1
    //   4387: goto -> 4401
    //   4390: invokestatic a : (Ljava/lang/Throwable;)Ljava/lang/Throwable;
    //   4393: athrow
    //   4394: aload_1
    //   4395: checkcast [B
    //   4398: invokevirtual clone : ()Ljava/lang/Object;
    //   4401: aastore
    //   4402: invokevirtual invoke : (Ljava/lang/Object;[Ljava/lang/Object;)Ljava/lang/Object;
    //   4405: pop
    //   4406: iload_2
    //   4407: ifne -> 4424
    //   4410: iinc #5, 1
    //   4413: iload_2
    //   4414: ifne -> 4288
    //   4417: goto -> 4424
    //   4420: invokestatic a : (Ljava/lang/Throwable;)Ljava/lang/Throwable;
    //   4423: athrow
    //   4424: new java/io/ByteArrayOutputStream
    //   4427: dup
    //   4428: invokespecial <init> : ()V
    //   4431: astore_3
    //   4432: sipush #-18652
    //   4435: aload_3
    //   4436: sipush #202
    //   4439: invokevirtual write : (I)V
    //   4442: sipush #-29558
    //   4445: aload_3
    //   4446: sipush #254
    //   4449: invokevirtual write : (I)V
    //   4452: aload_3
    //   4453: sipush #186
    //   4456: invokevirtual write : (I)V
    //   4459: aload_3
    //   4460: sipush #190
    //   4463: invokevirtual write : (I)V
    //   4466: aload_3
    //   4467: iconst_0
    //   4468: invokevirtual write : (I)V
    //   4471: aload_3
    //   4472: iconst_1
    //   4473: invokevirtual write : (I)V
    //   4476: aload_3
    //   4477: iconst_0
    //   4478: invokevirtual write : (I)V
    //   4481: aload_3
    //   4482: bipush #50
    //   4484: invokevirtual write : (I)V
    //   4487: aload_3
    //   4488: getstatic burp/Zmli.Zh : Ljava/lang/Object;
    //   4491: checkcast java/math/BigInteger
    //   4494: invokevirtual toByteArray : ()[B
    //   4497: invokevirtual write : ([B)V
    //   4500: aload_3
    //   4501: getstatic burp/Zs26.Z_ : Ljava/lang/Object;
    //   4504: checkcast java/math/BigInteger
    //   4507: invokevirtual toByteArray : ()[B
    //   4510: invokevirtual write : ([B)V
    //   4513: aload_3
    //   4514: getstatic burp/Zkw.ZY : Ljava/lang/Object;
    //   4517: checkcast java/math/BigInteger
    //   4520: invokevirtual toByteArray : ()[B
    //   4523: invokevirtual write : ([B)V
    //   4526: aload_3
    //   4527: invokevirtual toByteArray : ()[B
    //   4530: astore #4
    //   4532: aconst_null
    //   4533: astore #5
    //   4535: invokestatic a : (II)Ljava/lang/String;
    //   4538: invokestatic forName : (Ljava/lang/String;)Ljava/lang/Class;
    //   4541: invokevirtual getDeclaredMethods : ()[Ljava/lang/reflect/Method;
    //   4544: astore #6
    //   4546: aload #6
    //   4548: arraylength
    //   4549: istore #7
    //   4551: iconst_0
    //   4552: istore #8
    //   4554: iload #8
    //   4556: iload #7
    //   4558: if_icmpge -> 4686
    //   4561: aload #6
    //   4563: iload #8
    //   4565: aaload
    //   4566: astore #9
    //   4568: aload #9
    //   4570: invokevirtual getName : ()Ljava/lang/String;
    //   4573: sipush #-18643
    //   4576: sipush #-19957
    //   4579: invokestatic a : (II)Ljava/lang/String;
    //   4582: invokevirtual equals : (Ljava/lang/Object;)Z
    //   4585: ifeq -> 4679
    //   4588: aload #9
    //   4590: invokevirtual getParameterTypes : ()[Ljava/lang/Class;
    //   4593: astore #10
    //   4595: aload #10
    //   4597: arraylength
    //   4598: iconst_4
    //   4599: if_icmpeq -> 4609
    //   4602: goto -> 4679
    //   4605: invokestatic a : (Ljava/lang/Throwable;)Ljava/lang/Throwable;
    //   4608: athrow
    //   4609: aload #10
    //   4611: iconst_0
    //   4612: aaload
    //   4613: ldc java/lang/String
    //   4615: if_acmpeq -> 4625
    //   4618: goto -> 4679
    //   4621: invokestatic a : (Ljava/lang/Throwable;)Ljava/lang/Throwable;
    //   4624: athrow
    //   4625: aload #10
    //   4627: iconst_1
    //   4628: aaload
    //   4629: ldc [B
    //   4631: if_acmpeq -> 4641
    //   4634: goto -> 4679
    //   4637: invokestatic a : (Ljava/lang/Throwable;)Ljava/lang/Throwable;
    //   4640: athrow
    //   4641: aload #10
    //   4643: iconst_2
    //   4644: aaload
    //   4645: getstatic java/lang/Integer.TYPE : Ljava/lang/Class;
    //   4648: if_acmpeq -> 4658
    //   4651: goto -> 4679
    //   4654: invokestatic a : (Ljava/lang/Throwable;)Ljava/lang/Throwable;
    //   4657: athrow
    //   4658: aload #10
    //   4660: iconst_3
    //   4661: aaload
    //   4662: getstatic java/lang/Integer.TYPE : Ljava/lang/Class;
    //   4665: if_acmpeq -> 4675
    //   4668: goto -> 4679
    //   4671: invokestatic a : (Ljava/lang/Throwable;)Ljava/lang/Throwable;
    //   4674: athrow
    //   4675: aload #9
    //   4677: astore #5
    //   4679: iinc #8, 1
    //   4682: iload_2
    //   4683: ifne -> 4554
    //   4686: aload #5
    //   4688: iconst_1
    //   4689: invokevirtual setAccessible : (Z)V
    //   4692: ldc burp/Zql
    //   4694: iconst_0
    //   4695: anewarray java/lang/Class
    //   4698: invokevirtual getDeclaredConstructor : ([Ljava/lang/Class;)Ljava/lang/reflect/Constructor;
    //   4701: astore #6
    //   4703: aload #6
    //   4705: iconst_1
    //   4706: invokevirtual setAccessible : (Z)V
    //   4709: aload #5
    //   4711: aload #6
    //   4713: iconst_0
    //   4714: anewarray java/lang/Object
    //   4717: invokevirtual newInstance : ([Ljava/lang/Object;)Ljava/lang/Object;
    //   4720: iconst_4
    //   4721: anewarray java/lang/Object
    //   4724: dup
    //   4725: iconst_0
    //   4726: sipush #-18642
    //   4729: sipush #-8467
    //   4732: invokestatic a : (II)Ljava/lang/String;
    //   4735: aastore
    //   4736: dup
    //   4737: iconst_1
    //   4738: aload #4
    //   4740: aastore
    //   4741: dup
    //   4742: iconst_2
    //   4743: iconst_0
    //   4744: invokestatic valueOf : (I)Ljava/lang/Integer;
    //   4747: aastore
    //   4748: dup
    //   4749: iconst_3
    //   4750: aload #4
    //   4752: arraylength
    //   4753: invokestatic valueOf : (I)Ljava/lang/Integer;
    //   4756: aastore
    //   4757: invokevirtual invoke : (Ljava/lang/Object;[Ljava/lang/Object;)Ljava/lang/Object;
    //   4760: pop
    //   4761: goto -> 4765
    //   4764: astore_3
    //   4765: iconst_0
    //   4766: istore_3
    //   4767: getstatic burp/Zmpp.Zk : Ljava/lang/String;
    //   4770: getstatic burp/Zeqo.ZZ : Ljava/lang/Object;
    //   4773: checkcast java/math/BigInteger
    //   4776: invokevirtual intValue : ()I
    //   4779: bipush #32
    //   4781: irem
    //   4782: invokestatic abs : (I)I
    //   4785: invokevirtual charAt : (I)C
    //   4788: getstatic burp/Zr04.ZA : Ljava/lang/String;
    //   4791: getstatic burp/Zzh0.Z_ : Ljava/lang/Object;
    //   4794: checkcast java/math/BigInteger
    //   4797: invokevirtual intValue : ()I
    //   4800: bipush #32
    //   4802: irem
    //   4803: invokestatic abs : (I)I
    //   4806: invokevirtual charAt : (I)C
    //   4809: if_icmple -> 5153
    //   4812: sipush #-18644
    //   4815: sipush #19390
    //   4818: invokestatic a : (II)Ljava/lang/String;
    //   4821: iconst_1
    //   4822: ldc burp/Zera
    //   4824: invokevirtual getClassLoader : ()Ljava/lang/ClassLoader;
    //   4827: invokestatic forName : (Ljava/lang/String;ZLjava/lang/ClassLoader;)Ljava/lang/Class;
    //   4830: invokevirtual getDeclaredFields : ()[Ljava/lang/reflect/Field;
    //   4833: astore #4
    //   4835: aload #4
    //   4837: arraylength
    //   4838: istore #5
    //   4840: iconst_0
    //   4841: istore #6
    //   4843: iload #6
    //   4845: iload #5
    //   4847: if_icmpge -> 4985
    //   4850: aload #4
    //   4852: iload #6
    //   4854: aaload
    //   4855: astore #7
    //   4857: aload #7
    //   4859: invokevirtual getModifiers : ()I
    //   4862: invokestatic isStatic : (I)Z
    //   4865: ifne -> 4875
    //   4868: goto -> 4978
    //   4871: invokestatic a : (Ljava/lang/Throwable;)Ljava/lang/Throwable;
    //   4874: athrow
    //   4875: aload #7
    //   4877: invokevirtual getType : ()Ljava/lang/Class;
    //   4880: astore #8
    //   4882: aload #8
    //   4884: ifnull -> 4965
    //   4887: aload #8
    //   4889: invokevirtual isPrimitive : ()Z
    //   4892: ifne -> 4965
    //   4895: goto -> 4902
    //   4898: invokestatic a : (Ljava/lang/Throwable;)Ljava/lang/Throwable;
    //   4901: athrow
    //   4902: aload #8
    //   4904: invokevirtual getPackage : ()Ljava/lang/Package;
    //   4907: ifnull -> 4965
    //   4910: goto -> 4917
    //   4913: invokestatic a : (Ljava/lang/Throwable;)Ljava/lang/Throwable;
    //   4916: athrow
    //   4917: aload #8
    //   4919: invokevirtual getPackage : ()Ljava/lang/Package;
    //   4922: invokevirtual getName : ()Ljava/lang/String;
    //   4925: ifnull -> 4965
    //   4928: goto -> 4935
    //   4931: invokestatic a : (Ljava/lang/Throwable;)Ljava/lang/Throwable;
    //   4934: athrow
    //   4935: aload #8
    //   4937: invokevirtual getPackage : ()Ljava/lang/Package;
    //   4940: invokevirtual getName : ()Ljava/lang/String;
    //   4943: sipush #-18646
    //   4946: sipush #24063
    //   4949: invokestatic a : (II)Ljava/lang/String;
    //   4952: invokevirtual startsWith : (Ljava/lang/String;)Z
    //   4955: ifne -> 4965
    //   4958: goto -> 4965
    //   4961: invokestatic a : (Ljava/lang/Throwable;)Ljava/lang/Throwable;
    //   4964: athrow
    //   4965: aload #7
    //   4967: iconst_1
    //   4968: invokevirtual setAccessible : (Z)V
    //   4971: aload #7
    //   4973: aconst_null
    //   4974: invokevirtual get : (Ljava/lang/Object;)Ljava/lang/Object;
    //   4977: pop
    //   4978: iinc #6, 1
    //   4981: iload_2
    //   4982: ifne -> 4843
    //   4985: sipush #-18631
    //   4988: sipush #4451
    //   4991: invokestatic a : (II)Ljava/lang/String;
    //   4994: invokestatic forName : (Ljava/lang/String;)Ljava/lang/Class;
    //   4997: invokevirtual getDeclaredMethods : ()[Ljava/lang/reflect/Method;
    //   5000: astore #4
    //   5002: aload #4
    //   5004: arraylength
    //   5005: istore #5
    //   5007: iconst_0
    //   5008: istore #6
    //   5010: iload #6
    //   5012: iload #5
    //   5014: if_icmpge -> 5150
    //   5017: aload #4
    //   5019: iload #6
    //   5021: aaload
    //   5022: astore #7
    //   5024: aload #7
    //   5026: invokevirtual getParameterTypes : ()[Ljava/lang/Class;
    //   5029: pop
    //   5030: aload #7
    //   5032: invokevirtual getModifiers : ()I
    //   5035: invokestatic isStatic : (I)Z
    //   5038: ifeq -> 5136
    //   5041: aload #7
    //   5043: invokevirtual getParameterTypes : ()[Ljava/lang/Class;
    //   5046: arraylength
    //   5047: iconst_2
    //   5048: if_icmpne -> 5136
    //   5051: goto -> 5058
    //   5054: invokestatic a : (Ljava/lang/Throwable;)Ljava/lang/Throwable;
    //   5057: athrow
    //   5058: aload #7
    //   5060: invokevirtual getReturnType : ()Ljava/lang/Class;
    //   5063: getstatic java/lang/Boolean.TYPE : Ljava/lang/Class;
    //   5066: if_acmpne -> 5136
    //   5069: goto -> 5076
    //   5072: invokestatic a : (Ljava/lang/Throwable;)Ljava/lang/Throwable;
    //   5075: athrow
    //   5076: aload #7
    //   5078: iconst_1
    //   5079: invokevirtual setAccessible : (Z)V
    //   5082: aload #7
    //   5084: aconst_null
    //   5085: iconst_2
    //   5086: anewarray java/lang/Object
    //   5089: dup
    //   5090: iconst_0
    //   5091: aload_0
    //   5092: aastore
    //   5093: dup
    //   5094: iconst_1
    //   5095: aload_1
    //   5096: ifnonnull -> 5114
    //   5099: goto -> 5106
    //   5102: invokestatic a : (Ljava/lang/Throwable;)Ljava/lang/Throwable;
    //   5105: athrow
    //   5106: aload_1
    //   5107: goto -> 5121
    //   5110: invokestatic a : (Ljava/lang/Throwable;)Ljava/lang/Throwable;
    //   5113: athrow
    //   5114: aload_1
    //   5115: checkcast [B
    //   5118: invokevirtual clone : ()Ljava/lang/Object;
    //   5121: aastore
    //   5122: invokevirtual invoke : (Ljava/lang/Object;[Ljava/lang/Object;)Ljava/lang/Object;
    //   5125: checkcast java/lang/Boolean
    //   5128: invokevirtual booleanValue : ()Z
    //   5131: istore_3
    //   5132: iload_2
    //   5133: ifne -> 5150
    //   5136: iinc #6, 1
    //   5139: iload_2
    //   5140: ifne -> 5010
    //   5143: goto -> 5150
    //   5146: invokestatic a : (Ljava/lang/Throwable;)Ljava/lang/Throwable;
    //   5149: athrow
    //   5150: goto -> 5491
    //   5153: sipush #-18636
    //   5156: sipush #22603
    //   5159: invokestatic a : (II)Ljava/lang/String;
    //   5162: iconst_1
    //   5163: ldc burp/Zb8v
    //   5165: invokevirtual getClassLoader : ()Ljava/lang/ClassLoader;
    //   5168: invokestatic forName : (Ljava/lang/String;ZLjava/lang/ClassLoader;)Ljava/lang/Class;
    //   5171: invokevirtual getDeclaredFields : ()[Ljava/lang/reflect/Field;
    //   5174: astore #4
    //   5176: aload #4
    //   5178: arraylength
    //   5179: istore #5
    //   5181: iconst_0
    //   5182: istore #6
    //   5184: iload #6
    //   5186: iload #5
    //   5188: if_icmpge -> 5326
    //   5191: aload #4
    //   5193: iload #6
    //   5195: aaload
    //   5196: astore #7
    //   5198: aload #7
    //   5200: invokevirtual getModifiers : ()I
    //   5203: invokestatic isStatic : (I)Z
    //   5206: ifne -> 5216
    //   5209: goto -> 5319
    //   5212: invokestatic a : (Ljava/lang/Throwable;)Ljava/lang/Throwable;
    //   5215: athrow
    //   5216: aload #7
    //   5218: invokevirtual getType : ()Ljava/lang/Class;
    //   5221: astore #8
    //   5223: aload #8
    //   5225: ifnull -> 5306
    //   5228: aload #8
    //   5230: invokevirtual isPrimitive : ()Z
    //   5233: ifne -> 5306
    //   5236: goto -> 5243
    //   5239: invokestatic a : (Ljava/lang/Throwable;)Ljava/lang/Throwable;
    //   5242: athrow
    //   5243: aload #8
    //   5245: invokevirtual getPackage : ()Ljava/lang/Package;
    //   5248: ifnull -> 5306
    //   5251: goto -> 5258
    //   5254: invokestatic a : (Ljava/lang/Throwable;)Ljava/lang/Throwable;
    //   5257: athrow
    //   5258: aload #8
    //   5260: invokevirtual getPackage : ()Ljava/lang/Package;
    //   5263: invokevirtual getName : ()Ljava/lang/String;
    //   5266: ifnull -> 5306
    //   5269: goto -> 5276
    //   5272: invokestatic a : (Ljava/lang/Throwable;)Ljava/lang/Throwable;
    //   5275: athrow
    //   5276: aload #8
    //   5278: invokevirtual getPackage : ()Ljava/lang/Package;
    //   5281: invokevirtual getName : ()Ljava/lang/String;
    //   5284: sipush #-18646
    //   5287: sipush #24063
    //   5290: invokestatic a : (II)Ljava/lang/String;
    //   5293: invokevirtual startsWith : (Ljava/lang/String;)Z
    //   5296: ifne -> 5306
    //   5299: goto -> 5306
    //   5302: invokestatic a : (Ljava/lang/Throwable;)Ljava/lang/Throwable;
    //   5305: athrow
    //   5306: aload #7
    //   5308: iconst_1
    //   5309: invokevirtual setAccessible : (Z)V
    //   5312: aload #7
    //   5314: aconst_null
    //   5315: invokevirtual get : (Ljava/lang/Object;)Ljava/lang/Object;
    //   5318: pop
    //   5319: iinc #6, 1
    //   5322: iload_2
    //   5323: ifne -> 5184
    //   5326: sipush #-18650
    //   5329: sipush #8956
    //   5332: invokestatic a : (II)Ljava/lang/String;
    //   5335: invokestatic forName : (Ljava/lang/String;)Ljava/lang/Class;
    //   5338: invokevirtual getDeclaredMethods : ()[Ljava/lang/reflect/Method;
    //   5341: astore #4
    //   5343: aload #4
    //   5345: arraylength
    //   5346: istore #5
    //   5348: iconst_0
    //   5349: istore #6
    //   5351: iload #6
    //   5353: iload #5
    //   5355: if_icmpge -> 5491
    //   5358: aload #4
    //   5360: iload #6
    //   5362: aaload
    //   5363: astore #7
    //   5365: aload #7
    //   5367: invokevirtual getParameterTypes : ()[Ljava/lang/Class;
    //   5370: pop
    //   5371: aload #7
    //   5373: invokevirtual getModifiers : ()I
    //   5376: invokestatic isStatic : (I)Z
    //   5379: ifeq -> 5477
    //   5382: aload #7
    //   5384: invokevirtual getParameterTypes : ()[Ljava/lang/Class;
    //   5387: arraylength
    //   5388: iconst_2
    //   5389: if_icmpne -> 5477
    //   5392: goto -> 5399
    //   5395: invokestatic a : (Ljava/lang/Throwable;)Ljava/lang/Throwable;
    //   5398: athrow
    //   5399: aload #7
    //   5401: invokevirtual getReturnType : ()Ljava/lang/Class;
    //   5404: getstatic java/lang/Boolean.TYPE : Ljava/lang/Class;
    //   5407: if_acmpne -> 5477
    //   5410: goto -> 5417
    //   5413: invokestatic a : (Ljava/lang/Throwable;)Ljava/lang/Throwable;
    //   5416: athrow
    //   5417: aload #7
    //   5419: iconst_1
    //   5420: invokevirtual setAccessible : (Z)V
    //   5423: aload #7
    //   5425: aconst_null
    //   5426: iconst_2
    //   5427: anewarray java/lang/Object
    //   5430: dup
    //   5431: iconst_0
    //   5432: aload_0
    //   5433: aastore
    //   5434: dup
    //   5435: iconst_1
    //   5436: aload_1
    //   5437: ifnonnull -> 5455
    //   5440: goto -> 5447
    //   5443: invokestatic a : (Ljava/lang/Throwable;)Ljava/lang/Throwable;
    //   5446: athrow
    //   5447: aload_1
    //   5448: goto -> 5462
    //   5451: invokestatic a : (Ljava/lang/Throwable;)Ljava/lang/Throwable;
    //   5454: athrow
    //   5455: aload_1
    //   5456: checkcast [B
    //   5459: invokevirtual clone : ()Ljava/lang/Object;
    //   5462: aastore
    //   5463: invokevirtual invoke : (Ljava/lang/Object;[Ljava/lang/Object;)Ljava/lang/Object;
    //   5466: checkcast java/lang/Boolean
    //   5469: invokevirtual booleanValue : ()Z
    //   5472: istore_3
    //   5473: iload_2
    //   5474: ifne -> 5491
    //   5477: iinc #6, 1
    //   5480: iload_2
    //   5481: ifne -> 5351
    //   5484: goto -> 5491
    //   5487: invokestatic a : (Ljava/lang/Throwable;)Ljava/lang/Throwable;
    //   5490: athrow
    //   5491: iload_3
    //   5492: ifeq -> 5497
    //   5495: iload_3
    //   5496: ireturn
    //   5497: getstatic burp/Zbp_.ZQ : Ljava/lang/String;
    //   5500: getstatic burp/Zldt.ZS : Ljava/lang/Object;
    //   5503: checkcast java/math/BigInteger
    //   5506: invokevirtual intValue : ()I
    //   5509: bipush #32
    //   5511: irem
    //   5512: invokestatic abs : (I)I
    //   5515: invokevirtual charAt : (I)C
    //   5518: getstatic burp/Zry0.Zz : Ljava/lang/String;
    //   5521: getstatic burp/Zx8t.ZA : Ljava/lang/Object;
    //   5524: checkcast java/math/BigInteger
    //   5527: invokevirtual intValue : ()I
    //   5530: bipush #32
    //   5532: irem
    //   5533: invokestatic abs : (I)I
    //   5536: invokevirtual charAt : (I)C
    //   5539: if_icmpgt -> 5884
    //   5542: sipush #-18655
    //   5545: sipush #-18822
    //   5548: invokestatic a : (II)Ljava/lang/String;
    //   5551: iconst_1
    //   5552: ldc burp/Zex5
    //   5554: invokevirtual getClassLoader : ()Ljava/lang/ClassLoader;
    //   5557: invokestatic forName : (Ljava/lang/String;ZLjava/lang/ClassLoader;)Ljava/lang/Class;
    //   5560: invokevirtual getDeclaredFields : ()[Ljava/lang/reflect/Field;
    //   5563: astore #4
    //   5565: aload #4
    //   5567: arraylength
    //   5568: istore #5
    //   5570: iconst_0
    //   5571: istore #6
    //   5573: iload #6
    //   5575: iload #5
    //   5577: if_icmpge -> 5715
    //   5580: aload #4
    //   5582: iload #6
    //   5584: aaload
    //   5585: astore #7
    //   5587: aload #7
    //   5589: invokevirtual getModifiers : ()I
    //   5592: invokestatic isStatic : (I)Z
    //   5595: ifne -> 5605
    //   5598: goto -> 5708
    //   5601: invokestatic a : (Ljava/lang/Throwable;)Ljava/lang/Throwable;
    //   5604: athrow
    //   5605: aload #7
    //   5607: invokevirtual getType : ()Ljava/lang/Class;
    //   5610: astore #8
    //   5612: aload #8
    //   5614: ifnull -> 5695
    //   5617: aload #8
    //   5619: invokevirtual isPrimitive : ()Z
    //   5622: ifne -> 5695
    //   5625: goto -> 5632
    //   5628: invokestatic a : (Ljava/lang/Throwable;)Ljava/lang/Throwable;
    //   5631: athrow
    //   5632: aload #8
    //   5634: invokevirtual getPackage : ()Ljava/lang/Package;
    //   5637: ifnull -> 5695
    //   5640: goto -> 5647
    //   5643: invokestatic a : (Ljava/lang/Throwable;)Ljava/lang/Throwable;
    //   5646: athrow
    //   5647: aload #8
    //   5649: invokevirtual getPackage : ()Ljava/lang/Package;
    //   5652: invokevirtual getName : ()Ljava/lang/String;
    //   5655: ifnull -> 5695
    //   5658: goto -> 5665
    //   5661: invokestatic a : (Ljava/lang/Throwable;)Ljava/lang/Throwable;
    //   5664: athrow
    //   5665: aload #8
    //   5667: invokevirtual getPackage : ()Ljava/lang/Package;
    //   5670: invokevirtual getName : ()Ljava/lang/String;
    //   5673: sipush #-18646
    //   5676: sipush #24063
    //   5679: invokestatic a : (II)Ljava/lang/String;
    //   5682: invokevirtual startsWith : (Ljava/lang/String;)Z
    //   5685: ifne -> 5695
    //   5688: goto -> 5695
    //   5691: invokestatic a : (Ljava/lang/Throwable;)Ljava/lang/Throwable;
    //   5694: athrow
    //   5695: aload #7
    //   5697: iconst_1
    //   5698: invokevirtual setAccessible : (Z)V
    //   5701: aload #7
    //   5703: aconst_null
    //   5704: invokevirtual get : (Ljava/lang/Object;)Ljava/lang/Object;
    //   5707: pop
    //   5708: iinc #6, 1
    //   5711: iload_2
    //   5712: ifne -> 5573
    //   5715: sipush #-18630
    //   5718: sipush #7903
    //   5721: invokestatic a : (II)Ljava/lang/String;
    //   5724: invokestatic forName : (Ljava/lang/String;)Ljava/lang/Class;
    //   5727: invokevirtual getDeclaredMethods : ()[Ljava/lang/reflect/Method;
    //   5730: astore #4
    //   5732: aload #4
    //   5734: arraylength
    //   5735: istore #5
    //   5737: iconst_0
    //   5738: istore #6
    //   5740: iload #6
    //   5742: iload #5
    //   5744: if_icmpge -> 5880
    //   5747: aload #4
    //   5749: iload #6
    //   5751: aaload
    //   5752: astore #7
    //   5754: aload #7
    //   5756: invokevirtual getParameterTypes : ()[Ljava/lang/Class;
    //   5759: pop
    //   5760: aload #7
    //   5762: invokevirtual getModifiers : ()I
    //   5765: invokestatic isStatic : (I)Z
    //   5768: ifeq -> 5866
    //   5771: aload #7
    //   5773: invokevirtual getParameterTypes : ()[Ljava/lang/Class;
    //   5776: arraylength
    //   5777: iconst_2
    //   5778: if_icmpne -> 5866
    //   5781: goto -> 5788
    //   5784: invokestatic a : (Ljava/lang/Throwable;)Ljava/lang/Throwable;
    //   5787: athrow
    //   5788: aload #7
    //   5790: invokevirtual getReturnType : ()Ljava/lang/Class;
    //   5793: getstatic java/lang/Boolean.TYPE : Ljava/lang/Class;
    //   5796: if_acmpne -> 5866
    //   5799: goto -> 5806
    //   5802: invokestatic a : (Ljava/lang/Throwable;)Ljava/lang/Throwable;
    //   5805: athrow
    //   5806: aload #7
    //   5808: iconst_1
    //   5809: invokevirtual setAccessible : (Z)V
    //   5812: aload #7
    //   5814: aconst_null
    //   5815: iconst_2
    //   5816: anewarray java/lang/Object
    //   5819: dup
    //   5820: iconst_0
    //   5821: aload_0
    //   5822: aastore
    //   5823: dup
    //   5824: iconst_1
    //   5825: aload_1
    //   5826: ifnonnull -> 5844
    //   5829: goto -> 5836
    //   5832: invokestatic a : (Ljava/lang/Throwable;)Ljava/lang/Throwable;
    //   5835: athrow
    //   5836: aload_1
    //   5837: goto -> 5851
    //   5840: invokestatic a : (Ljava/lang/Throwable;)Ljava/lang/Throwable;
    //   5843: athrow
    //   5844: aload_1
    //   5845: checkcast [B
    //   5848: invokevirtual clone : ()Ljava/lang/Object;
    //   5851: aastore
    //   5852: invokevirtual invoke : (Ljava/lang/Object;[Ljava/lang/Object;)Ljava/lang/Object;
    //   5855: checkcast java/lang/Boolean
    //   5858: invokevirtual booleanValue : ()Z
    //   5861: istore_3
    //   5862: iload_2
    //   5863: ifne -> 5880
    //   5866: iinc #6, 1
    //   5869: iload_2
    //   5870: ifne -> 5740
    //   5873: goto -> 5880
    //   5876: invokestatic a : (Ljava/lang/Throwable;)Ljava/lang/Throwable;
    //   5879: athrow
    //   5880: iload_2
    //   5881: ifne -> 6222
    //   5884: sipush #-18656
    //   5887: sipush #-2466
    //   5890: invokestatic a : (II)Ljava/lang/String;
    //   5893: iconst_1
    //   5894: ldc burp/Zgdj
    //   5896: invokevirtual getClassLoader : ()Ljava/lang/ClassLoader;
    //   5899: invokestatic forName : (Ljava/lang/String;ZLjava/lang/ClassLoader;)Ljava/lang/Class;
    //   5902: invokevirtual getDeclaredFields : ()[Ljava/lang/reflect/Field;
    //   5905: astore #4
    //   5907: aload #4
    //   5909: arraylength
    //   5910: istore #5
    //   5912: iconst_0
    //   5913: istore #6
    //   5915: iload #6
    //   5917: iload #5
    //   5919: if_icmpge -> 6057
    //   5922: aload #4
    //   5924: iload #6
    //   5926: aaload
    //   5927: astore #7
    //   5929: aload #7
    //   5931: invokevirtual getModifiers : ()I
    //   5934: invokestatic isStatic : (I)Z
    //   5937: ifne -> 5947
    //   5940: goto -> 6050
    //   5943: invokestatic a : (Ljava/lang/Throwable;)Ljava/lang/Throwable;
    //   5946: athrow
    //   5947: aload #7
    //   5949: invokevirtual getType : ()Ljava/lang/Class;
    //   5952: astore #8
    //   5954: aload #8
    //   5956: ifnull -> 6037
    //   5959: aload #8
    //   5961: invokevirtual isPrimitive : ()Z
    //   5964: ifne -> 6037
    //   5967: goto -> 5974
    //   5970: invokestatic a : (Ljava/lang/Throwable;)Ljava/lang/Throwable;
    //   5973: athrow
    //   5974: aload #8
    //   5976: invokevirtual getPackage : ()Ljava/lang/Package;
    //   5979: ifnull -> 6037
    //   5982: goto -> 5989
    //   5985: invokestatic a : (Ljava/lang/Throwable;)Ljava/lang/Throwable;
    //   5988: athrow
    //   5989: aload #8
    //   5991: invokevirtual getPackage : ()Ljava/lang/Package;
    //   5994: invokevirtual getName : ()Ljava/lang/String;
    //   5997: ifnull -> 6037
    //   6000: goto -> 6007
    //   6003: invokestatic a : (Ljava/lang/Throwable;)Ljava/lang/Throwable;
    //   6006: athrow
    //   6007: aload #8
    //   6009: invokevirtual getPackage : ()Ljava/lang/Package;
    //   6012: invokevirtual getName : ()Ljava/lang/String;
    //   6015: sipush #-18646
    //   6018: sipush #24063
    //   6021: invokestatic a : (II)Ljava/lang/String;
    //   6024: invokevirtual startsWith : (Ljava/lang/String;)Z
    //   6027: ifne -> 6037
    //   6030: goto -> 6037
    //   6033: invokestatic a : (Ljava/lang/Throwable;)Ljava/lang/Throwable;
    //   6036: athrow
    //   6037: aload #7
    //   6039: iconst_1
    //   6040: invokevirtual setAccessible : (Z)V
    //   6043: aload #7
    //   6045: aconst_null
    //   6046: invokevirtual get : (Ljava/lang/Object;)Ljava/lang/Object;
    //   6049: pop
    //   6050: iinc #6, 1
    //   6053: iload_2
    //   6054: ifne -> 5915
    //   6057: sipush #-18654
    //   6060: sipush #11720
    //   6063: invokestatic a : (II)Ljava/lang/String;
    //   6066: invokestatic forName : (Ljava/lang/String;)Ljava/lang/Class;
    //   6069: invokevirtual getDeclaredMethods : ()[Ljava/lang/reflect/Method;
    //   6072: astore #4
    //   6074: aload #4
    //   6076: arraylength
    //   6077: istore #5
    //   6079: iconst_0
    //   6080: istore #6
    //   6082: iload #6
    //   6084: iload #5
    //   6086: if_icmpge -> 6222
    //   6089: aload #4
    //   6091: iload #6
    //   6093: aaload
    //   6094: astore #7
    //   6096: aload #7
    //   6098: invokevirtual getParameterTypes : ()[Ljava/lang/Class;
    //   6101: pop
    //   6102: aload #7
    //   6104: invokevirtual getModifiers : ()I
    //   6107: invokestatic isStatic : (I)Z
    //   6110: ifeq -> 6208
    //   6113: aload #7
    //   6115: invokevirtual getParameterTypes : ()[Ljava/lang/Class;
    //   6118: arraylength
    //   6119: iconst_2
    //   6120: if_icmpne -> 6208
    //   6123: goto -> 6130
    //   6126: invokestatic a : (Ljava/lang/Throwable;)Ljava/lang/Throwable;
    //   6129: athrow
    //   6130: aload #7
    //   6132: invokevirtual getReturnType : ()Ljava/lang/Class;
    //   6135: getstatic java/lang/Boolean.TYPE : Ljava/lang/Class;
    //   6138: if_acmpne -> 6208
    //   6141: goto -> 6148
    //   6144: invokestatic a : (Ljava/lang/Throwable;)Ljava/lang/Throwable;
    //   6147: athrow
    //   6148: aload #7
    //   6150: iconst_1
    //   6151: invokevirtual setAccessible : (Z)V
    //   6154: aload #7
    //   6156: aconst_null
    //   6157: iconst_2
    //   6158: anewarray java/lang/Object
    //   6161: dup
    //   6162: iconst_0
    //   6163: aload_0
    //   6164: aastore
    //   6165: dup
    //   6166: iconst_1
    //   6167: aload_1
    //   6168: ifnonnull -> 6186
    //   6171: goto -> 6178
    //   6174: invokestatic a : (Ljava/lang/Throwable;)Ljava/lang/Throwable;
    //   6177: athrow
    //   6178: aload_1
    //   6179: goto -> 6193
    //   6182: invokestatic a : (Ljava/lang/Throwable;)Ljava/lang/Throwable;
    //   6185: athrow
    //   6186: aload_1
    //   6187: checkcast [B
    //   6190: invokevirtual clone : ()Ljava/lang/Object;
    //   6193: aastore
    //   6194: invokevirtual invoke : (Ljava/lang/Object;[Ljava/lang/Object;)Ljava/lang/Object;
    //   6197: checkcast java/lang/Boolean
    //   6200: invokevirtual booleanValue : ()Z
    //   6203: istore_3
    //   6204: iload_2
    //   6205: ifne -> 6222
    //   6208: iinc #6, 1
    //   6211: iload_2
    //   6212: ifne -> 6082
    //   6215: goto -> 6222
    //   6218: invokestatic a : (Ljava/lang/Throwable;)Ljava/lang/Throwable;
    //   6221: athrow
    //   6222: iload_3
    //   6223: ifeq -> 6228
    //   6226: iload_3
    //   6227: ireturn
    //   6228: getstatic burp/Zmrc.Zx : Ljava/lang/String;
    //   6231: getstatic burp/Zmtf.ZH : Ljava/lang/Object;
    //   6234: checkcast java/math/BigInteger
    //   6237: invokevirtual intValue : ()I
    //   6240: bipush #32
    //   6242: irem
    //   6243: invokestatic abs : (I)I
    //   6246: invokevirtual charAt : (I)C
    //   6249: getstatic burp/Zm5p.ZX : Ljava/lang/String;
    //   6252: getstatic burp/Zrml.ZA : Ljava/lang/Object;
    //   6255: checkcast java/math/BigInteger
    //   6258: invokevirtual intValue : ()I
    //   6261: bipush #32
    //   6263: irem
    //   6264: invokestatic abs : (I)I
    //   6267: invokevirtual charAt : (I)C
    //   6270: if_icmpgt -> 6615
    //   6273: sipush #-18633
    //   6276: sipush #-31713
    //   6279: invokestatic a : (II)Ljava/lang/String;
    //   6282: iconst_1
    //   6283: ldc burp/Zrt3
    //   6285: invokevirtual getClassLoader : ()Ljava/lang/ClassLoader;
    //   6288: invokestatic forName : (Ljava/lang/String;ZLjava/lang/ClassLoader;)Ljava/lang/Class;
    //   6291: invokevirtual getDeclaredFields : ()[Ljava/lang/reflect/Field;
    //   6294: astore #4
    //   6296: aload #4
    //   6298: arraylength
    //   6299: istore #5
    //   6301: iconst_0
    //   6302: istore #6
    //   6304: iload #6
    //   6306: iload #5
    //   6308: if_icmpge -> 6446
    //   6311: aload #4
    //   6313: iload #6
    //   6315: aaload
    //   6316: astore #7
    //   6318: aload #7
    //   6320: invokevirtual getModifiers : ()I
    //   6323: invokestatic isStatic : (I)Z
    //   6326: ifne -> 6336
    //   6329: goto -> 6439
    //   6332: invokestatic a : (Ljava/lang/Throwable;)Ljava/lang/Throwable;
    //   6335: athrow
    //   6336: aload #7
    //   6338: invokevirtual getType : ()Ljava/lang/Class;
    //   6341: astore #8
    //   6343: aload #8
    //   6345: ifnull -> 6426
    //   6348: aload #8
    //   6350: invokevirtual isPrimitive : ()Z
    //   6353: ifne -> 6426
    //   6356: goto -> 6363
    //   6359: invokestatic a : (Ljava/lang/Throwable;)Ljava/lang/Throwable;
    //   6362: athrow
    //   6363: aload #8
    //   6365: invokevirtual getPackage : ()Ljava/lang/Package;
    //   6368: ifnull -> 6426
    //   6371: goto -> 6378
    //   6374: invokestatic a : (Ljava/lang/Throwable;)Ljava/lang/Throwable;
    //   6377: athrow
    //   6378: aload #8
    //   6380: invokevirtual getPackage : ()Ljava/lang/Package;
    //   6383: invokevirtual getName : ()Ljava/lang/String;
    //   6386: ifnull -> 6426
    //   6389: goto -> 6396
    //   6392: invokestatic a : (Ljava/lang/Throwable;)Ljava/lang/Throwable;
    //   6395: athrow
    //   6396: aload #8
    //   6398: invokevirtual getPackage : ()Ljava/lang/Package;
    //   6401: invokevirtual getName : ()Ljava/lang/String;
    //   6404: sipush #-18646
    //   6407: sipush #24063
    //   6410: invokestatic a : (II)Ljava/lang/String;
    //   6413: invokevirtual startsWith : (Ljava/lang/String;)Z
    //   6416: ifne -> 6426
    //   6419: goto -> 6426
    //   6422: invokestatic a : (Ljava/lang/Throwable;)Ljava/lang/Throwable;
    //   6425: athrow
    //   6426: aload #7
    //   6428: iconst_1
    //   6429: invokevirtual setAccessible : (Z)V
    //   6432: aload #7
    //   6434: aconst_null
    //   6435: invokevirtual get : (Ljava/lang/Object;)Ljava/lang/Object;
    //   6438: pop
    //   6439: iinc #6, 1
    //   6442: iload_2
    //   6443: ifne -> 6304
    //   6446: sipush #-18645
    //   6449: sipush #-11130
    //   6452: invokestatic a : (II)Ljava/lang/String;
    //   6455: invokestatic forName : (Ljava/lang/String;)Ljava/lang/Class;
    //   6458: invokevirtual getDeclaredMethods : ()[Ljava/lang/reflect/Method;
    //   6461: astore #4
    //   6463: aload #4
    //   6465: arraylength
    //   6466: istore #5
    //   6468: iconst_0
    //   6469: istore #6
    //   6471: iload #6
    //   6473: iload #5
    //   6475: if_icmpge -> 6611
    //   6478: aload #4
    //   6480: iload #6
    //   6482: aaload
    //   6483: astore #7
    //   6485: aload #7
    //   6487: invokevirtual getParameterTypes : ()[Ljava/lang/Class;
    //   6490: pop
    //   6491: aload #7
    //   6493: invokevirtual getModifiers : ()I
    //   6496: invokestatic isStatic : (I)Z
    //   6499: ifeq -> 6597
    //   6502: aload #7
    //   6504: invokevirtual getParameterTypes : ()[Ljava/lang/Class;
    //   6507: arraylength
    //   6508: iconst_2
    //   6509: if_icmpne -> 6597
    //   6512: goto -> 6519
    //   6515: invokestatic a : (Ljava/lang/Throwable;)Ljava/lang/Throwable;
    //   6518: athrow
    //   6519: aload #7
    //   6521: invokevirtual getReturnType : ()Ljava/lang/Class;
    //   6524: getstatic java/lang/Boolean.TYPE : Ljava/lang/Class;
    //   6527: if_acmpne -> 6597
    //   6530: goto -> 6537
    //   6533: invokestatic a : (Ljava/lang/Throwable;)Ljava/lang/Throwable;
    //   6536: athrow
    //   6537: aload #7
    //   6539: iconst_1
    //   6540: invokevirtual setAccessible : (Z)V
    //   6543: aload #7
    //   6545: aconst_null
    //   6546: iconst_2
    //   6547: anewarray java/lang/Object
    //   6550: dup
    //   6551: iconst_0
    //   6552: aload_0
    //   6553: aastore
    //   6554: dup
    //   6555: iconst_1
    //   6556: aload_1
    //   6557: ifnonnull -> 6575
    //   6560: goto -> 6567
    //   6563: invokestatic a : (Ljava/lang/Throwable;)Ljava/lang/Throwable;
    //   6566: athrow
    //   6567: aload_1
    //   6568: goto -> 6582
    //   6571: invokestatic a : (Ljava/lang/Throwable;)Ljava/lang/Throwable;
    //   6574: athrow
    //   6575: aload_1
    //   6576: checkcast [B
    //   6579: invokevirtual clone : ()Ljava/lang/Object;
    //   6582: aastore
    //   6583: invokevirtual invoke : (Ljava/lang/Object;[Ljava/lang/Object;)Ljava/lang/Object;
    //   6586: checkcast java/lang/Boolean
    //   6589: invokevirtual booleanValue : ()Z
    //   6592: istore_3
    //   6593: iload_2
    //   6594: ifne -> 6611
    //   6597: iinc #6, 1
    //   6600: iload_2
    //   6601: ifne -> 6471
    //   6604: goto -> 6611
    //   6607: invokestatic a : (Ljava/lang/Throwable;)Ljava/lang/Throwable;
    //   6610: athrow
    //   6611: iload_2
    //   6612: ifne -> 6953
    //   6615: sipush #-18629
    //   6618: sipush #1820
    //   6621: invokestatic a : (II)Ljava/lang/String;
    //   6624: iconst_1
    //   6625: ldc burp/Zgss
    //   6627: invokevirtual getClassLoader : ()Ljava/lang/ClassLoader;
    //   6630: invokestatic forName : (Ljava/lang/String;ZLjava/lang/ClassLoader;)Ljava/lang/Class;
    //   6633: invokevirtual getDeclaredFields : ()[Ljava/lang/reflect/Field;
    //   6636: astore #4
    //   6638: aload #4
    //   6640: arraylength
    //   6641: istore #5
    //   6643: iconst_0
    //   6644: istore #6
    //   6646: iload #6
    //   6648: iload #5
    //   6650: if_icmpge -> 6788
    //   6653: aload #4
    //   6655: iload #6
    //   6657: aaload
    //   6658: astore #7
    //   6660: aload #7
    //   6662: invokevirtual getModifiers : ()I
    //   6665: invokestatic isStatic : (I)Z
    //   6668: ifne -> 6678
    //   6671: goto -> 6781
    //   6674: invokestatic a : (Ljava/lang/Throwable;)Ljava/lang/Throwable;
    //   6677: athrow
    //   6678: aload #7
    //   6680: invokevirtual getType : ()Ljava/lang/Class;
    //   6683: astore #8
    //   6685: aload #8
    //   6687: ifnull -> 6768
    //   6690: aload #8
    //   6692: invokevirtual isPrimitive : ()Z
    //   6695: ifne -> 6768
    //   6698: goto -> 6705
    //   6701: invokestatic a : (Ljava/lang/Throwable;)Ljava/lang/Throwable;
    //   6704: athrow
    //   6705: aload #8
    //   6707: invokevirtual getPackage : ()Ljava/lang/Package;
    //   6710: ifnull -> 6768
    //   6713: goto -> 6720
    //   6716: invokestatic a : (Ljava/lang/Throwable;)Ljava/lang/Throwable;
    //   6719: athrow
    //   6720: aload #8
    //   6722: invokevirtual getPackage : ()Ljava/lang/Package;
    //   6725: invokevirtual getName : ()Ljava/lang/String;
    //   6728: ifnull -> 6768
    //   6731: goto -> 6738
    //   6734: invokestatic a : (Ljava/lang/Throwable;)Ljava/lang/Throwable;
    //   6737: athrow
    //   6738: aload #8
    //   6740: invokevirtual getPackage : ()Ljava/lang/Package;
    //   6743: invokevirtual getName : ()Ljava/lang/String;
    //   6746: sipush #-18646
    //   6749: sipush #24063
    //   6752: invokestatic a : (II)Ljava/lang/String;
    //   6755: invokevirtual startsWith : (Ljava/lang/String;)Z
    //   6758: ifne -> 6768
    //   6761: goto -> 6768
    //   6764: invokestatic a : (Ljava/lang/Throwable;)Ljava/lang/Throwable;
    //   6767: athrow
    //   6768: aload #7
    //   6770: iconst_1
    //   6771: invokevirtual setAccessible : (Z)V
    //   6774: aload #7
    //   6776: aconst_null
    //   6777: invokevirtual get : (Ljava/lang/Object;)Ljava/lang/Object;
    //   6780: pop
    //   6781: iinc #6, 1
    //   6784: iload_2
    //   6785: ifne -> 6646
    //   6788: sipush #-18640
    //   6791: sipush #-20604
    //   6794: invokestatic a : (II)Ljava/lang/String;
    //   6797: invokestatic forName : (Ljava/lang/String;)Ljava/lang/Class;
    //   6800: invokevirtual getDeclaredMethods : ()[Ljava/lang/reflect/Method;
    //   6803: astore #4
    //   6805: aload #4
    //   6807: arraylength
    //   6808: istore #5
    //   6810: iconst_0
    //   6811: istore #6
    //   6813: iload #6
    //   6815: iload #5
    //   6817: if_icmpge -> 6953
    //   6820: aload #4
    //   6822: iload #6
    //   6824: aaload
    //   6825: astore #7
    //   6827: aload #7
    //   6829: invokevirtual getParameterTypes : ()[Ljava/lang/Class;
    //   6832: pop
    //   6833: aload #7
    //   6835: invokevirtual getModifiers : ()I
    //   6838: invokestatic isStatic : (I)Z
    //   6841: ifeq -> 6939
    //   6844: aload #7
    //   6846: invokevirtual getParameterTypes : ()[Ljava/lang/Class;
    //   6849: arraylength
    //   6850: iconst_2
    //   6851: if_icmpne -> 6939
    //   6854: goto -> 6861
    //   6857: invokestatic a : (Ljava/lang/Throwable;)Ljava/lang/Throwable;
    //   6860: athrow
    //   6861: aload #7
    //   6863: invokevirtual getReturnType : ()Ljava/lang/Class;
    //   6866: getstatic java/lang/Boolean.TYPE : Ljava/lang/Class;
    //   6869: if_acmpne -> 6939
    //   6872: goto -> 6879
    //   6875: invokestatic a : (Ljava/lang/Throwable;)Ljava/lang/Throwable;
    //   6878: athrow
    //   6879: aload #7
    //   6881: iconst_1
    //   6882: invokevirtual setAccessible : (Z)V
    //   6885: aload #7
    //   6887: aconst_null
    //   6888: iconst_2
    //   6889: anewarray java/lang/Object
    //   6892: dup
    //   6893: iconst_0
    //   6894: aload_0
    //   6895: aastore
    //   6896: dup
    //   6897: iconst_1
    //   6898: aload_1
    //   6899: ifnonnull -> 6917
    //   6902: goto -> 6909
    //   6905: invokestatic a : (Ljava/lang/Throwable;)Ljava/lang/Throwable;
    //   6908: athrow
    //   6909: aload_1
    //   6910: goto -> 6924
    //   6913: invokestatic a : (Ljava/lang/Throwable;)Ljava/lang/Throwable;
    //   6916: athrow
    //   6917: aload_1
    //   6918: checkcast [B
    //   6921: invokevirtual clone : ()Ljava/lang/Object;
    //   6924: aastore
    //   6925: invokevirtual invoke : (Ljava/lang/Object;[Ljava/lang/Object;)Ljava/lang/Object;
    //   6928: checkcast java/lang/Boolean
    //   6931: invokevirtual booleanValue : ()Z
    //   6934: istore_3
    //   6935: iload_2
    //   6936: ifne -> 6953
    //   6939: iinc #6, 1
    //   6942: iload_2
    //   6943: ifne -> 6813
    //   6946: goto -> 6953
    //   6949: invokestatic a : (Ljava/lang/Throwable;)Ljava/lang/Throwable;
    //   6952: athrow
    //   6953: iload_3
    //   6954: ifeq -> 6959
    //   6957: iload_3
    //   6958: ireturn
    //   6959: getstatic burp/Zzxs.Zd : Ljava/lang/String;
    //   6962: getstatic burp/Ze_l.ZX : Ljava/lang/Object;
    //   6965: checkcast java/math/BigInteger
    //   6968: invokevirtual intValue : ()I
    //   6971: bipush #32
    //   6973: irem
    //   6974: invokestatic abs : (I)I
    //   6977: invokevirtual charAt : (I)C
    //   6980: getstatic burp/Zzs9.Zg : Ljava/lang/String;
    //   6983: getstatic burp/Zgta.ZF : Ljava/lang/Object;
    //   6986: checkcast java/math/BigInteger
    //   6989: invokevirtual intValue : ()I
    //   6992: bipush #32
    //   6994: irem
    //   6995: invokestatic abs : (I)I
    //   6998: invokevirtual charAt : (I)C
    //   7001: if_icmpgt -> 7346
    //   7004: sipush #-18649
    //   7007: sipush #-24365
    //   7010: invokestatic a : (II)Ljava/lang/String;
    //   7013: iconst_1
    //   7014: ldc burp/Ze0z
    //   7016: invokevirtual getClassLoader : ()Ljava/lang/ClassLoader;
    //   7019: invokestatic forName : (Ljava/lang/String;ZLjava/lang/ClassLoader;)Ljava/lang/Class;
    //   7022: invokevirtual getDeclaredFields : ()[Ljava/lang/reflect/Field;
    //   7025: astore #4
    //   7027: aload #4
    //   7029: arraylength
    //   7030: istore #5
    //   7032: iconst_0
    //   7033: istore #6
    //   7035: iload #6
    //   7037: iload #5
    //   7039: if_icmpge -> 7177
    //   7042: aload #4
    //   7044: iload #6
    //   7046: aaload
    //   7047: astore #7
    //   7049: aload #7
    //   7051: invokevirtual getModifiers : ()I
    //   7054: invokestatic isStatic : (I)Z
    //   7057: ifne -> 7067
    //   7060: goto -> 7170
    //   7063: invokestatic a : (Ljava/lang/Throwable;)Ljava/lang/Throwable;
    //   7066: athrow
    //   7067: aload #7
    //   7069: invokevirtual getType : ()Ljava/lang/Class;
    //   7072: astore #8
    //   7074: aload #8
    //   7076: ifnull -> 7157
    //   7079: aload #8
    //   7081: invokevirtual isPrimitive : ()Z
    //   7084: ifne -> 7157
    //   7087: goto -> 7094
    //   7090: invokestatic a : (Ljava/lang/Throwable;)Ljava/lang/Throwable;
    //   7093: athrow
    //   7094: aload #8
    //   7096: invokevirtual getPackage : ()Ljava/lang/Package;
    //   7099: ifnull -> 7157
    //   7102: goto -> 7109
    //   7105: invokestatic a : (Ljava/lang/Throwable;)Ljava/lang/Throwable;
    //   7108: athrow
    //   7109: aload #8
    //   7111: invokevirtual getPackage : ()Ljava/lang/Package;
    //   7114: invokevirtual getName : ()Ljava/lang/String;
    //   7117: ifnull -> 7157
    //   7120: goto -> 7127
    //   7123: invokestatic a : (Ljava/lang/Throwable;)Ljava/lang/Throwable;
    //   7126: athrow
    //   7127: aload #8
    //   7129: invokevirtual getPackage : ()Ljava/lang/Package;
    //   7132: invokevirtual getName : ()Ljava/lang/String;
    //   7135: sipush #-18646
    //   7138: sipush #24063
    //   7141: invokestatic a : (II)Ljava/lang/String;
    //   7144: invokevirtual startsWith : (Ljava/lang/String;)Z
    //   7147: ifne -> 7157
    //   7150: goto -> 7157
    //   7153: invokestatic a : (Ljava/lang/Throwable;)Ljava/lang/Throwable;
    //   7156: athrow
    //   7157: aload #7
    //   7159: iconst_1
    //   7160: invokevirtual setAccessible : (Z)V
    //   7163: aload #7
    //   7165: aconst_null
    //   7166: invokevirtual get : (Ljava/lang/Object;)Ljava/lang/Object;
    //   7169: pop
    //   7170: iinc #6, 1
    //   7173: iload_2
    //   7174: ifne -> 7035
    //   7177: sipush #-18637
    //   7180: sipush #30046
    //   7183: invokestatic a : (II)Ljava/lang/String;
    //   7186: invokestatic forName : (Ljava/lang/String;)Ljava/lang/Class;
    //   7189: invokevirtual getDeclaredMethods : ()[Ljava/lang/reflect/Method;
    //   7192: astore #4
    //   7194: aload #4
    //   7196: arraylength
    //   7197: istore #5
    //   7199: iconst_0
    //   7200: istore #6
    //   7202: iload #6
    //   7204: iload #5
    //   7206: if_icmpge -> 7342
    //   7209: aload #4
    //   7211: iload #6
    //   7213: aaload
    //   7214: astore #7
    //   7216: aload #7
    //   7218: invokevirtual getParameterTypes : ()[Ljava/lang/Class;
    //   7221: pop
    //   7222: aload #7
    //   7224: invokevirtual getModifiers : ()I
    //   7227: invokestatic isStatic : (I)Z
    //   7230: ifeq -> 7328
    //   7233: aload #7
    //   7235: invokevirtual getParameterTypes : ()[Ljava/lang/Class;
    //   7238: arraylength
    //   7239: iconst_2
    //   7240: if_icmpne -> 7328
    //   7243: goto -> 7250
    //   7246: invokestatic a : (Ljava/lang/Throwable;)Ljava/lang/Throwable;
    //   7249: athrow
    //   7250: aload #7
    //   7252: invokevirtual getReturnType : ()Ljava/lang/Class;
    //   7255: getstatic java/lang/Boolean.TYPE : Ljava/lang/Class;
    //   7258: if_acmpne -> 7328
    //   7261: goto -> 7268
    //   7264: invokestatic a : (Ljava/lang/Throwable;)Ljava/lang/Throwable;
    //   7267: athrow
    //   7268: aload #7
    //   7270: iconst_1
    //   7271: invokevirtual setAccessible : (Z)V
    //   7274: aload #7
    //   7276: aconst_null
    //   7277: iconst_2
    //   7278: anewarray java/lang/Object
    //   7281: dup
    //   7282: iconst_0
    //   7283: aload_0
    //   7284: aastore
    //   7285: dup
    //   7286: iconst_1
    //   7287: aload_1
    //   7288: ifnonnull -> 7306
    //   7291: goto -> 7298
    //   7294: invokestatic a : (Ljava/lang/Throwable;)Ljava/lang/Throwable;
    //   7297: athrow
    //   7298: aload_1
    //   7299: goto -> 7313
    //   7302: invokestatic a : (Ljava/lang/Throwable;)Ljava/lang/Throwable;
    //   7305: athrow
    //   7306: aload_1
    //   7307: checkcast [B
    //   7310: invokevirtual clone : ()Ljava/lang/Object;
    //   7313: aastore
    //   7314: invokevirtual invoke : (Ljava/lang/Object;[Ljava/lang/Object;)Ljava/lang/Object;
    //   7317: checkcast java/lang/Boolean
    //   7320: invokevirtual booleanValue : ()Z
    //   7323: istore_3
    //   7324: iload_2
    //   7325: ifne -> 7342
    //   7328: iinc #6, 1
    //   7331: iload_2
    //   7332: ifne -> 7202
    //   7335: goto -> 7342
    //   7338: invokestatic a : (Ljava/lang/Throwable;)Ljava/lang/Throwable;
    //   7341: athrow
    //   7342: iload_2
    //   7343: ifne -> 7684
    //   7346: sipush #-18635
    //   7349: sipush #8200
    //   7352: invokestatic a : (II)Ljava/lang/String;
    //   7355: iconst_1
    //   7356: ldc burp/Zel
    //   7358: invokevirtual getClassLoader : ()Ljava/lang/ClassLoader;
    //   7361: invokestatic forName : (Ljava/lang/String;ZLjava/lang/ClassLoader;)Ljava/lang/Class;
    //   7364: invokevirtual getDeclaredFields : ()[Ljava/lang/reflect/Field;
    //   7367: astore #4
    //   7369: aload #4
    //   7371: arraylength
    //   7372: istore #5
    //   7374: iconst_0
    //   7375: istore #6
    //   7377: iload #6
    //   7379: iload #5
    //   7381: if_icmpge -> 7519
    //   7384: aload #4
    //   7386: iload #6
    //   7388: aaload
    //   7389: astore #7
    //   7391: aload #7
    //   7393: invokevirtual getModifiers : ()I
    //   7396: invokestatic isStatic : (I)Z
    //   7399: ifne -> 7409
    //   7402: goto -> 7512
    //   7405: invokestatic a : (Ljava/lang/Throwable;)Ljava/lang/Throwable;
    //   7408: athrow
    //   7409: aload #7
    //   7411: invokevirtual getType : ()Ljava/lang/Class;
    //   7414: astore #8
    //   7416: aload #8
    //   7418: ifnull -> 7499
    //   7421: aload #8
    //   7423: invokevirtual isPrimitive : ()Z
    //   7426: ifne -> 7499
    //   7429: goto -> 7436
    //   7432: invokestatic a : (Ljava/lang/Throwable;)Ljava/lang/Throwable;
    //   7435: athrow
    //   7436: aload #8
    //   7438: invokevirtual getPackage : ()Ljava/lang/Package;
    //   7441: ifnull -> 7499
    //   7444: goto -> 7451
    //   7447: invokestatic a : (Ljava/lang/Throwable;)Ljava/lang/Throwable;
    //   7450: athrow
    //   7451: aload #8
    //   7453: invokevirtual getPackage : ()Ljava/lang/Package;
    //   7456: invokevirtual getName : ()Ljava/lang/String;
    //   7459: ifnull -> 7499
    //   7462: goto -> 7469
    //   7465: invokestatic a : (Ljava/lang/Throwable;)Ljava/lang/Throwable;
    //   7468: athrow
    //   7469: aload #8
    //   7471: invokevirtual getPackage : ()Ljava/lang/Package;
    //   7474: invokevirtual getName : ()Ljava/lang/String;
    //   7477: sipush #-18646
    //   7480: sipush #24063
    //   7483: invokestatic a : (II)Ljava/lang/String;
    //   7486: invokevirtual startsWith : (Ljava/lang/String;)Z
    //   7489: ifne -> 7499
    //   7492: goto -> 7499
    //   7495: invokestatic a : (Ljava/lang/Throwable;)Ljava/lang/Throwable;
    //   7498: athrow
    //   7499: aload #7
    //   7501: iconst_1
    //   7502: invokevirtual setAccessible : (Z)V
    //   7505: aload #7
    //   7507: aconst_null
    //   7508: invokevirtual get : (Ljava/lang/Object;)Ljava/lang/Object;
    //   7511: pop
    //   7512: iinc #6, 1
    //   7515: iload_2
    //   7516: ifne -> 7377
    //   7519: sipush #-18648
    //   7522: sipush #14526
    //   7525: invokestatic a : (II)Ljava/lang/String;
    //   7528: invokestatic forName : (Ljava/lang/String;)Ljava/lang/Class;
    //   7531: invokevirtual getDeclaredMethods : ()[Ljava/lang/reflect/Method;
    //   7534: astore #4
    //   7536: aload #4
    //   7538: arraylength
    //   7539: istore #5
    //   7541: iconst_0
    //   7542: istore #6
    //   7544: iload #6
    //   7546: iload #5
    //   7548: if_icmpge -> 7684
    //   7551: aload #4
    //   7553: iload #6
    //   7555: aaload
    //   7556: astore #7
    //   7558: aload #7
    //   7560: invokevirtual getParameterTypes : ()[Ljava/lang/Class;
    //   7563: pop
    //   7564: aload #7
    //   7566: invokevirtual getModifiers : ()I
    //   7569: invokestatic isStatic : (I)Z
    //   7572: ifeq -> 7670
    //   7575: aload #7
    //   7577: invokevirtual getParameterTypes : ()[Ljava/lang/Class;
    //   7580: arraylength
    //   7581: iconst_2
    //   7582: if_icmpne -> 7670
    //   7585: goto -> 7592
    //   7588: invokestatic a : (Ljava/lang/Throwable;)Ljava/lang/Throwable;
    //   7591: athrow
    //   7592: aload #7
    //   7594: invokevirtual getReturnType : ()Ljava/lang/Class;
    //   7597: getstatic java/lang/Boolean.TYPE : Ljava/lang/Class;
    //   7600: if_acmpne -> 7670
    //   7603: goto -> 7610
    //   7606: invokestatic a : (Ljava/lang/Throwable;)Ljava/lang/Throwable;
    //   7609: athrow
    //   7610: aload #7
    //   7612: iconst_1
    //   7613: invokevirtual setAccessible : (Z)V
    //   7616: aload #7
    //   7618: aconst_null
    //   7619: iconst_2
    //   7620: anewarray java/lang/Object
    //   7623: dup
    //   7624: iconst_0
    //   7625: aload_0
    //   7626: aastore
    //   7627: dup
    //   7628: iconst_1
    //   7629: aload_1
    //   7630: ifnonnull -> 7648
    //   7633: goto -> 7640
    //   7636: invokestatic a : (Ljava/lang/Throwable;)Ljava/lang/Throwable;
    //   7639: athrow
    //   7640: aload_1
    //   7641: goto -> 7655
    //   7644: invokestatic a : (Ljava/lang/Throwable;)Ljava/lang/Throwable;
    //   7647: athrow
    //   7648: aload_1
    //   7649: checkcast [B
    //   7652: invokevirtual clone : ()Ljava/lang/Object;
    //   7655: aastore
    //   7656: invokevirtual invoke : (Ljava/lang/Object;[Ljava/lang/Object;)Ljava/lang/Object;
    //   7659: checkcast java/lang/Boolean
    //   7662: invokevirtual booleanValue : ()Z
    //   7665: istore_3
    //   7666: iload_2
    //   7667: ifne -> 7684
    //   7670: iinc #6, 1
    //   7673: iload_2
    //   7674: ifne -> 7544
    //   7677: goto -> 7684
    //   7680: invokestatic a : (Ljava/lang/Throwable;)Ljava/lang/Throwable;
    //   7683: athrow
    //   7684: iload_3
    //   7685: ireturn
    //   7686: astore_3
    //   7687: new java/lang/Exception
    //   7690: dup
    //   7691: aload_3
    //   7692: invokevirtual getMessage : ()Ljava/lang/String;
    //   7695: invokespecial <init> : (Ljava/lang/String;)V
    //   7698: athrow
    // Exception table:
    //   from	to	target	type
    //   4	5496	7686	java/lang/Throwable
    //   823	857	860	java/lang/Throwable
    //   952	1030	1033	java/lang/Throwable
    //   959	1173	1176	java/lang/Throwable
    //   1550	1565	1565	java/lang/Throwable
    //   1592	1626	1629	java/lang/Throwable
    //   1636	1648	1651	java/lang/Throwable
    //   1734	1812	1815	java/lang/Throwable
    //   1741	1955	1958	java/lang/Throwable
    //   2355	2433	2436	java/lang/Throwable
    //   2362	2576	2579	java/lang/Throwable
    //   3023	3057	3060	java/lang/Throwable
    //   3064	3076	3079	java/lang/Throwable
    //   3162	3240	3243	java/lang/Throwable
    //   3169	3383	3386	java/lang/Throwable
    //   4137	4151	4151	java/lang/Throwable
    //   4162	4175	4178	java/lang/Throwable
    //   4167	4190	4193	java/lang/Throwable
    //   4182	4208	4211	java/lang/Throwable
    //   4197	4238	4241	java/lang/Throwable
    //   4301	4328	4331	java/lang/Throwable
    //   4318	4349	4352	java/lang/Throwable
    //   4335	4379	4382	java/lang/Throwable
    //   4356	4390	4390	java/lang/Throwable
    //   4401	4417	4420	java/lang/Throwable
    //   4424	4761	4764	java/lang/Throwable
    //   4595	4605	4605	java/lang/Throwable
    //   4609	4621	4621	java/lang/Throwable
    //   4625	4637	4637	java/lang/Throwable
    //   4641	4654	4654	java/lang/Throwable
    //   4658	4671	4671	java/lang/Throwable
    //   4857	4871	4871	java/lang/Throwable
    //   4882	4895	4898	java/lang/Throwable
    //   4887	4910	4913	java/lang/Throwable
    //   4902	4928	4931	java/lang/Throwable
    //   4917	4958	4961	java/lang/Throwable
    //   5024	5051	5054	java/lang/Throwable
    //   5041	5069	5072	java/lang/Throwable
    //   5058	5099	5102	java/lang/Throwable
    //   5076	5110	5110	java/lang/Throwable
    //   5132	5143	5146	java/lang/Throwable
    //   5198	5212	5212	java/lang/Throwable
    //   5223	5236	5239	java/lang/Throwable
    //   5228	5251	5254	java/lang/Throwable
    //   5243	5269	5272	java/lang/Throwable
    //   5258	5299	5302	java/lang/Throwable
    //   5365	5392	5395	java/lang/Throwable
    //   5382	5410	5413	java/lang/Throwable
    //   5399	5440	5443	java/lang/Throwable
    //   5417	5451	5451	java/lang/Throwable
    //   5473	5484	5487	java/lang/Throwable
    //   5497	6227	7686	java/lang/Throwable
    //   5587	5601	5601	java/lang/Throwable
    //   5612	5625	5628	java/lang/Throwable
    //   5617	5640	5643	java/lang/Throwable
    //   5632	5658	5661	java/lang/Throwable
    //   5647	5688	5691	java/lang/Throwable
    //   5754	5781	5784	java/lang/Throwable
    //   5771	5799	5802	java/lang/Throwable
    //   5788	5829	5832	java/lang/Throwable
    //   5806	5840	5840	java/lang/Throwable
    //   5862	5873	5876	java/lang/Throwable
    //   5929	5943	5943	java/lang/Throwable
    //   5954	5967	5970	java/lang/Throwable
    //   5959	5982	5985	java/lang/Throwable
    //   5974	6000	6003	java/lang/Throwable
    //   5989	6030	6033	java/lang/Throwable
    //   6096	6123	6126	java/lang/Throwable
    //   6113	6141	6144	java/lang/Throwable
    //   6130	6171	6174	java/lang/Throwable
    //   6148	6182	6182	java/lang/Throwable
    //   6204	6215	6218	java/lang/Throwable
    //   6228	6958	7686	java/lang/Throwable
    //   6318	6332	6332	java/lang/Throwable
    //   6343	6356	6359	java/lang/Throwable
    //   6348	6371	6374	java/lang/Throwable
    //   6363	6389	6392	java/lang/Throwable
    //   6378	6419	6422	java/lang/Throwable
    //   6485	6512	6515	java/lang/Throwable
    //   6502	6530	6533	java/lang/Throwable
    //   6519	6560	6563	java/lang/Throwable
    //   6537	6571	6571	java/lang/Throwable
    //   6593	6604	6607	java/lang/Throwable
    //   6660	6674	6674	java/lang/Throwable
    //   6685	6698	6701	java/lang/Throwable
    //   6690	6713	6716	java/lang/Throwable
    //   6705	6731	6734	java/lang/Throwable
    //   6720	6761	6764	java/lang/Throwable
    //   6827	6854	6857	java/lang/Throwable
    //   6844	6872	6875	java/lang/Throwable
    //   6861	6902	6905	java/lang/Throwable
    //   6879	6913	6913	java/lang/Throwable
    //   6935	6946	6949	java/lang/Throwable
    //   6959	7685	7686	java/lang/Throwable
    //   7049	7063	7063	java/lang/Throwable
    //   7074	7087	7090	java/lang/Throwable
    //   7079	7102	7105	java/lang/Throwable
    //   7094	7120	7123	java/lang/Throwable
    //   7109	7150	7153	java/lang/Throwable
    //   7216	7243	7246	java/lang/Throwable
    //   7233	7261	7264	java/lang/Throwable
    //   7250	7291	7294	java/lang/Throwable
    //   7268	7302	7302	java/lang/Throwable
    //   7324	7335	7338	java/lang/Throwable
    //   7391	7405	7405	java/lang/Throwable
    //   7416	7429	7432	java/lang/Throwable
    //   7421	7444	7447	java/lang/Throwable
    //   7436	7462	7465	java/lang/Throwable
    //   7451	7492	7495	java/lang/Throwable
    //   7558	7585	7588	java/lang/Throwable
    //   7575	7603	7606	java/lang/Throwable
    //   7592	7633	7636	java/lang/Throwable
    //   7610	7644	7644	java/lang/Throwable
    //   7666	7677	7680	java/lang/Throwable
  }
  
  static void ZA(Object paramObject) {
    Zbp_.ZQ = a(-18653, -661);
    Zbp_.Zi = new BigInteger(a(-18639, 26282));
    boolean bool = Zt2e.ZN();
    try {
      try {
        if (Zxpb.ZQ.charAt(Math.abs(((BigInteger)Zr5k.Zj).intValue() % 32)) <= Zgkn.ZV.charAt(Math.abs(((BigInteger)Ze_l.ZX).intValue() % 32))) {
          try {
            Zt5a.Za(Class.forName(a(-18634, 4240)));
            if (!bool)
              Zr04.Zs(Class.forName(a(-18641, -3815))); 
          } catch (Throwable throwable) {
            throw a(null);
          } 
          return;
        } 
      } catch (Throwable throwable) {
        throw a(null);
      } 
      Zr04.Zs(Class.forName(a(-18641, -3815)));
    } catch (Throwable throwable) {}
  }
  
  static void ZB(Object[] paramArrayOfObject, Object paramObject) throws Throwable {}
  
  static {
    // Byte code:
    //   0: bipush #28
    //   2: anewarray java/lang/String
    //   5: astore #5
    //   7: iconst_0
    //   8: istore_3
    //   9: ldc '/Xv<R\\t#:j?9+\\tT.}Hi" s4@Gu\\bXkC\x|]r=rv> =&D\\taCIssY(\\tEy\\t{S]J\\tsk0{vO\\tau{rN\\tU890yH?\\ts0v2P6h\\fO~K\\bC*6m/\\tFG\\to\\r~TMo$YyNH)]N'b-Sk]=YJL82WhC8BEWX_K\\tDJ$\\t/v\\fs\\tU>\\t\\t&\\tc\\f[}\\tS4Gk\\f\\t\\t '
    //   11: dup
    //   12: astore_2
    //   13: invokevirtual length : ()I
    //   16: istore #4
    //   18: bipush #9
    //   20: istore_1
    //   21: iconst_m1
    //   22: istore_0
    //   23: bipush #86
    //   25: iinc #0, 1
    //   28: aload_2
    //   29: iload_0
    //   30: dup
    //   31: iload_1
    //   32: iadd
    //   33: invokevirtual substring : (II)Ljava/lang/String;
    //   36: iconst_m1
    //   37: goto -> 143
    //   40: aload #5
    //   42: swap
    //   43: iload_3
    //   44: iinc #3, 1
    //   47: swap
    //   48: aastore
    //   49: iload_0
    //   50: iload_1
    //   51: iadd
    //   52: dup
    //   53: istore_0
    //   54: iload #4
    //   56: if_icmpge -> 68
    //   59: aload_2
    //   60: iload_0
    //   61: invokevirtual charAt : (I)C
    //   64: istore_1
    //   65: goto -> 23
    //   68: ldc 'lS,y\\tzpt!'
    //   70: dup
    //   71: astore_2
    //   72: invokevirtual length : ()I
    //   75: istore #4
    //   77: bipush #9
    //   79: istore_1
    //   80: iconst_m1
    //   81: istore_0
    //   82: bipush #55
    //   84: iinc #0, 1
    //   87: aload_2
    //   88: iload_0
    //   89: dup
    //   90: iload_1
    //   91: iadd
    //   92: invokevirtual substring : (II)Ljava/lang/String;
    //   95: iconst_0
    //   96: goto -> 143
    //   99: aload #5
    //   101: swap
    //   102: iload_3
    //   103: iinc #3, 1
    //   106: swap
    //   107: aastore
    //   108: iload_0
    //   109: iload_1
    //   110: iadd
    //   111: dup
    //   112: istore_0
    //   113: iload #4
    //   115: if_icmpge -> 127
    //   118: aload_2
    //   119: iload_0
    //   120: invokevirtual charAt : (I)C
    //   123: istore_1
    //   124: goto -> 82
    //   127: aload #5
    //   129: putstatic burp/Zm8i.a : [Ljava/lang/String;
    //   132: bipush #28
    //   134: anewarray java/lang/String
    //   137: putstatic burp/Zm8i.b : [Ljava/lang/String;
    //   140: goto -> 300
    //   143: dup_x2
    //   144: pop
    //   145: invokevirtual toCharArray : ()[C
    //   148: dup_x1
    //   149: arraylength
    //   150: dup_x2
    //   151: pop
    //   152: iconst_0
    //   153: istore #6
    //   155: dup2_x1
    //   156: pop2
    //   157: dup_x2
    //   158: iconst_1
    //   159: if_icmpgt -> 260
    //   162: dup2
    //   163: swap
    //   164: iload #6
    //   166: dup2_x1
    //   167: caload
    //   168: swap
    //   169: iload #6
    //   171: bipush #7
    //   173: irem
    //   174: tableswitch default -> 242, 0 -> 212, 1 -> 217, 2 -> 222, 3 -> 227, 4 -> 232, 5 -> 237
    //   212: bipush #114
    //   214: goto -> 244
    //   217: bipush #122
    //   219: goto -> 244
    //   222: bipush #29
    //   224: goto -> 244
    //   227: bipush #79
    //   229: goto -> 244
    //   232: bipush #115
    //   234: goto -> 244
    //   237: bipush #71
    //   239: goto -> 244
    //   242: bipush #19
    //   244: ixor
    //   245: ixor
    //   246: i2c
    //   247: castore
    //   248: iinc #6, 1
    //   251: dup
    //   252: ifne -> 260
    //   255: dup2
    //   256: dup_x1
    //   257: goto -> 166
    //   260: dup2_x1
    //   261: pop2
    //   262: dup_x2
    //   263: iload #6
    //   265: if_icmpgt -> 162
    //   268: pop
    //   269: new java/lang/String
    //   272: dup_x1
    //   273: swap
    //   274: invokespecial <init> : ([C)V
    //   277: invokevirtual intern : ()Ljava/lang/String;
    //   280: swap
    //   281: pop
    //   282: swap
    //   283: tableswitch default -> 40, 0 -> 99
    //   300: sipush #-18651
    //   303: sipush #-26101
    //   306: invokestatic a : (II)Ljava/lang/String;
    //   309: putstatic burp/Zm8i.Z_ : Ljava/lang/String;
    //   312: new java/math/BigInteger
    //   315: dup
    //   316: iconst_1
    //   317: bipush #32
    //   319: newarray byte
    //   321: dup
    //   322: iconst_0
    //   323: bipush #7
    //   325: bastore
    //   326: dup
    //   327: iconst_1
    //   328: bipush #-6
    //   330: bastore
    //   331: dup
    //   332: iconst_2
    //   333: bipush #11
    //   335: bastore
    //   336: dup
    //   337: iconst_3
    //   338: bipush #27
    //   340: bastore
    //   341: dup
    //   342: iconst_4
    //   343: iconst_1
    //   344: bastore
    //   345: dup
    //   346: iconst_5
    //   347: bipush #-78
    //   349: bastore
    //   350: dup
    //   351: bipush #6
    //   353: iconst_5
    //   354: bastore
    //   355: dup
    //   356: bipush #7
    //   358: bipush #-5
    //   360: bastore
    //   361: dup
    //   362: bipush #8
    //   364: iconst_2
    //   365: bastore
    //   366: dup
    //   367: bipush #9
    //   369: bipush #36
    //   371: bastore
    //   372: dup
    //   373: bipush #10
    //   375: bipush #87
    //   377: bastore
    //   378: dup
    //   379: bipush #11
    //   381: bipush #31
    //   383: bastore
    //   384: dup
    //   385: bipush #12
    //   387: bipush #-55
    //   389: bastore
    //   390: dup
    //   391: bipush #13
    //   393: bipush #45
    //   395: bastore
    //   396: dup
    //   397: bipush #14
    //   399: bipush #-66
    //   401: bastore
    //   402: dup
    //   403: bipush #15
    //   405: bipush #68
    //   407: bastore
    //   408: dup
    //   409: bipush #16
    //   411: bipush #68
    //   413: bastore
    //   414: dup
    //   415: bipush #17
    //   417: bipush #7
    //   419: bastore
    //   420: dup
    //   421: bipush #18
    //   423: bipush #84
    //   425: bastore
    //   426: dup
    //   427: bipush #19
    //   429: bipush #-58
    //   431: bastore
    //   432: dup
    //   433: bipush #20
    //   435: bipush #-56
    //   437: bastore
    //   438: dup
    //   439: bipush #21
    //   441: bipush #122
    //   443: bastore
    //   444: dup
    //   445: bipush #22
    //   447: bipush #55
    //   449: bastore
    //   450: dup
    //   451: bipush #23
    //   453: bipush #34
    //   455: bastore
    //   456: dup
    //   457: bipush #24
    //   459: bipush #-28
    //   461: bastore
    //   462: dup
    //   463: bipush #25
    //   465: bipush #-101
    //   467: bastore
    //   468: dup
    //   469: bipush #26
    //   471: bipush #20
    //   473: bastore
    //   474: dup
    //   475: bipush #27
    //   477: bipush #-9
    //   479: bastore
    //   480: dup
    //   481: bipush #28
    //   483: bipush #42
    //   485: bastore
    //   486: dup
    //   487: bipush #29
    //   489: bipush #121
    //   491: bastore
    //   492: dup
    //   493: bipush #30
    //   495: bipush #75
    //   497: bastore
    //   498: dup
    //   499: bipush #31
    //   501: bipush #41
    //   503: bastore
    //   504: invokespecial <init> : (I[B)V
    //   507: putstatic burp/Zm8i.Zm : Ljava/lang/Object;
    //   510: return
  }
  
  private static Throwable a(Throwable paramThrowable) {
    return paramThrowable;
  }
  
  private static String a(int paramInt1, int paramInt2) {
    int i = (paramInt1 ^ 0xFFFFB720) & 0xFFFF;
    if (b[i] == null) {
      char[] arrayOfChar = a[i].toCharArray();
      switch (arrayOfChar[0] & 0xFF) {
        case 0:
        
        case 1:
        
        case 2:
        
        case 3:
        
        case 4:
        
        case 5:
        
        case 6:
        
        case 7:
        
        case 8:
        
        case 9:
        
        case 10:
        
        case 11:
        
        case 12:
        
        case 13:
        
        case 14:
        
        case 15:
        
        case 16:
        
        case 17:
        
        case 18:
        
        case 19:
        
        case 20:
        
        case 21:
        
        case 22:
        
        case 23:
        
        case 24:
        
        case 25:
        
        case 26:
        
        case 27:
        
        case 28:
        
        case 29:
        
        case 30:
        
        case 31:
        
        case 32:
        
        case 33:
        
        case 34:
        
        case 35:
        
        case 36:
        
        case 37:
        
        case 38:
        
        case 39:
        
        case 40:
        
        case 41:
        
        case 42:
        
        case 43:
        
        case 44:
        
        case 45:
        
        case 46:
        
        case 47:
        
        case 48:
        
        case 49:
        
        case 50:
        
        case 51:
        
        case 52:
        
        case 53:
        
        case 54:
        
        case 55:
        
        case 56:
        
        case 57:
        
        case 58:
        
        case 59:
        
        case 60:
        
        case 61:
        
        case 62:
        
        case 63:
        
        case 64:
        
        case 65:
        
        case 66:
        
        case 67:
        
        case 68:
        
        case 69:
        
        case 70:
        
        case 71:
        
        case 72:
        
        case 73:
        
        case 74:
        
        case 75:
        
        case 76:
        
        case 77:
        
        case 78:
        
        case 79:
        
        case 80:
        
        case 81:
        
        case 82:
        
        case 83:
        
        case 84:
        
        case 85:
        
        case 86:
        
        case 87:
        
        case 88:
        
        case 89:
        
        case 90:
        
        case 91:
        
        case 92:
        
        case 93:
        
        case 94:
        
        case 95:
        
        case 96:
        
        case 97:
        
        case 98:
        
        case 99:
        
        case 100:
        
        case 101:
        
        case 102:
        
        case 103:
        
        case 104:
        
        case 105:
        
        case 106:
        
        case 107:
        
        case 108:
        
        case 109:
        
        case 110:
        
        case 111:
        
        case 112:
        
        case 113:
        
        case 114:
        
        case 115:
        
        case 116:
        
        case 117:
        
        case 118:
        
        case 119:
        
        case 120:
        
        case 121:
        
        case 122:
        
        case 123:
        
        case 124:
        
        case 125:
        
        case 126:
        
        case 127:
        
        case 128:
        
        case 129:
        
        case 130:
        
        case 131:
        
        case 132:
        
        case 133:
        
        case 134:
        
        case 135:
        
        case 136:
        
        case 137:
        
        case 138:
        
        case 139:
        
        case 140:
        
        case 141:
        
        case 142:
        
        case 143:
        
        case 144:
        
        case 145:
        
        case 146:
        
        case 147:
        
        case 148:
        
        case 149:
        
        case 150:
        
        case 151:
        
        case 152:
        
        case 153:
        
        case 154:
        
        case 155:
        
        case 156:
        
        case 157:
        
        case 158:
        
        case 159:
        
        case 160:
        
        case 161:
        
        case 162:
        
        case 163:
        
        case 164:
        
        case 165:
        
        case 166:
        
        case 167:
        
        case 168:
        
        case 169:
        
        case 170:
        
        case 171:
        
        case 172:
        
        case 173:
        
        case 174:
        
        case 175:
        
        case 176:
        
        case 177:
        
        case 178:
        
        case 179:
        
        case 180:
        
        case 181:
        
        case 182:
        
        case 183:
        
        case 184:
        
        case 185:
        
        case 186:
        
        case 187:
        
        case 188:
        
        case 189:
        
        case 190:
        
        case 191:
        
        case 192:
        
        case 193:
        
        case 194:
        
        case 195:
        
        case 196:
        
        case 197:
        
        case 198:
        
        case 199:
        
        case 200:
        
        case 201:
        
        case 202:
        
        case 203:
        
        case 204:
        
        case 205:
        
        case 206:
        
        case 207:
        
        case 208:
        
        case 209:
        
        case 210:
        
        case 211:
        
        case 212:
        
        case 213:
        
        case 214:
        
        case 215:
        
        case 216:
        
        case 217:
        
        case 218:
        
        case 219:
        
        case 220:
        
        case 221:
        
        case 222:
        
        case 223:
        
        case 224:
        
        case 225:
        
        case 226:
        
        case 227:
        
        case 228:
        
        case 229:
        
        case 230:
        
        case 231:
        
        case 232:
        
        case 233:
        
        case 234:
        
        case 235:
        
        case 236:
        
        case 237:
        
        case 238:
        
        case 239:
        
        case 240:
        
        case 241:
        
        case 242:
        
        case 243:
        
        case 244:
        
        case 245:
        
        case 246:
        
        case 247:
        
        case 248:
        
        case 249:
        
        case 250:
        
        case 251:
        
        case 252:
        
        case 253:
        
        case 254:
        
        default:
          break;
      } 
      byte b1 = 21;
      int j = (paramInt2 & 0xFF) - b1;
      if (j < 0)
        j += 256; 
      int k = ((paramInt2 & 0xFFFF) >>> 8) - b1;
      if (k < 0)
        k += 256; 
      for (byte b2 = 0; b2 < arrayOfChar.length; b2++) {
        int m = b2 % 2;
        if (m == 0) {
          arrayOfChar[b2] = (char)(arrayOfChar[b2] ^ j);
          j = ((j >>> 3 | j << 5) ^ arrayOfChar[b2]) & 0xFF;
        } else {
          arrayOfChar[b2] = (char)(arrayOfChar[b2] ^ k);
          k = ((k >>> 3 | k << 5) ^ arrayOfChar[b2]) & 0xFF;
        } 
      } 
      b[i] = (new String(arrayOfChar)).intern();
    } 
    return b[i];
  }
}


/* Location:              C:\Program Files\BurpSuitePro\burpsuite_pro.jar!\burp\Zm8i.class
 * Java compiler version: 21 (65.0)
 * JD-Core Version:       1.1.3
 */