package burp;

import java.math.BigInteger;

class Zm8j extends ClassLoader {
  static Object Zj;
  
  static String Zp;
  
  private static final String[] a;
  
  private static final String[] b;
  
  static void Zg(Object[] paramArrayOfObject, Object paramObject) throws Throwable {}
  
  static void ZW(Object paramObject) {
    Zetf.Zo = a(23919, 5780);
    Zetf.Zs = new BigInteger(a(23914, -23378));
    boolean bool = Zt2e.ZN();
    try {
      try {
        if (Zmdf.Zo.charAt(Math.abs(((BigInteger)Zg6z.ZS).intValue() % 32)) > Zsfj.Zg.charAt(Math.abs(((BigInteger)Zea8.ZF).intValue() % 32))) {
          try {
            Zl8f.Zn(Class.forName(a(23909, -15687)));
            if (!bool)
              Zr17.Zg(Class.forName(a(23917, -16554))); 
          } catch (Throwable throwable) {
            throw a(null);
          } 
          return;
        } 
      } catch (Throwable throwable) {
        throw a(null);
      } 
      Zr17.Zg(Class.forName(a(23917, -16554)));
    } catch (Throwable throwable) {}
  }
  
  static boolean ZT(Object[] paramArrayOfObject, Object paramObject) throws Throwable {
    // Byte code:
    //   0: invokestatic ZK : ()Z
    //   3: istore_2
    //   4: getstatic burp/Zz91.Z_ : Ljava/lang/Object;
    //   7: checkcast java/math/BigInteger
    //   10: invokevirtual toByteArray : ()[B
    //   13: astore_3
    //   14: new java/lang/StringBuilder
    //   17: dup
    //   18: invokespecial <init> : ()V
    //   21: astore #5
    //   23: aload #5
    //   25: sipush #23908
    //   28: sipush #26518
    //   31: invokestatic a : (II)Ljava/lang/String;
    //   34: invokevirtual append : (Ljava/lang/String;)Ljava/lang/StringBuilder;
    //   37: pop
    //   38: aload_3
    //   39: astore #6
    //   41: aload #6
    //   43: arraylength
    //   44: istore #7
    //   46: iconst_0
    //   47: istore #8
    //   49: iload #8
    //   51: iload #7
    //   53: if_icmpge -> 79
    //   56: aload #6
    //   58: iload #8
    //   60: baload
    //   61: istore #9
    //   63: aload #5
    //   65: iload #9
    //   67: i2c
    //   68: invokevirtual append : (C)Ljava/lang/StringBuilder;
    //   71: pop
    //   72: iinc #8, 1
    //   75: iload_2
    //   76: ifeq -> 49
    //   79: aload #5
    //   81: sipush #23904
    //   84: sipush #-28122
    //   87: invokestatic a : (II)Ljava/lang/String;
    //   90: ldc ''
    //   92: invokestatic getProperty : (Ljava/lang/String;Ljava/lang/String;)Ljava/lang/String;
    //   95: invokevirtual toLowerCase : ()Ljava/lang/String;
    //   98: invokevirtual append : (Ljava/lang/String;)Ljava/lang/StringBuilder;
    //   101: pop
    //   102: aload #5
    //   104: sipush #23906
    //   107: sipush #12288
    //   110: invokestatic a : (II)Ljava/lang/String;
    //   113: ldc ''
    //   115: invokestatic getProperty : (Ljava/lang/String;Ljava/lang/String;)Ljava/lang/String;
    //   118: invokevirtual toLowerCase : ()Ljava/lang/String;
    //   121: invokevirtual append : (Ljava/lang/String;)Ljava/lang/StringBuilder;
    //   124: pop
    //   125: aload #5
    //   127: invokevirtual toString : ()Ljava/lang/String;
    //   130: invokevirtual getBytes : ()[B
    //   133: astore #4
    //   135: aload #4
    //   137: astore_3
    //   138: aload_3
    //   139: arraylength
    //   140: bipush #8
    //   142: iadd
    //   143: bipush #6
    //   145: ishr
    //   146: iconst_1
    //   147: iadd
    //   148: bipush #16
    //   150: imul
    //   151: newarray int
    //   153: astore #5
    //   155: iconst_0
    //   156: istore #6
    //   158: iload #6
    //   160: aload_3
    //   161: arraylength
    //   162: if_icmpge -> 205
    //   165: aload_3
    //   166: iload #6
    //   168: baload
    //   169: sipush #255
    //   172: iand
    //   173: istore #7
    //   175: aload #5
    //   177: iload #6
    //   179: iconst_2
    //   180: ishr
    //   181: dup2
    //   182: iaload
    //   183: iload #7
    //   185: bipush #24
    //   187: iload #6
    //   189: iconst_4
    //   190: irem
    //   191: bipush #8
    //   193: imul
    //   194: isub
    //   195: ishl
    //   196: ior
    //   197: iastore
    //   198: iinc #6, 1
    //   201: iload_2
    //   202: ifeq -> 158
    //   205: aload #5
    //   207: iload #6
    //   209: iconst_2
    //   210: ishr
    //   211: dup2
    //   212: iaload
    //   213: sipush #128
    //   216: bipush #24
    //   218: iload #6
    //   220: iconst_4
    //   221: irem
    //   222: bipush #8
    //   224: imul
    //   225: isub
    //   226: ishl
    //   227: ior
    //   228: iastore
    //   229: aload #5
    //   231: aload #5
    //   233: arraylength
    //   234: iconst_1
    //   235: isub
    //   236: aload_3
    //   237: arraylength
    //   238: bipush #8
    //   240: imul
    //   241: iastore
    //   242: bipush #80
    //   244: newarray int
    //   246: astore #7
    //   248: ldc 1732584193
    //   250: istore #8
    //   252: ldc -271733879
    //   254: istore #9
    //   256: ldc -1732584194
    //   258: istore #10
    //   260: ldc 271733878
    //   262: istore #11
    //   264: ldc -1009589776
    //   266: istore #12
    //   268: iconst_0
    //   269: istore #6
    //   271: iload #6
    //   273: aload #5
    //   275: arraylength
    //   276: if_icmpge -> 598
    //   279: iload #8
    //   281: istore #13
    //   283: iload #9
    //   285: istore #14
    //   287: iload #10
    //   289: istore #15
    //   291: iload #11
    //   293: istore #16
    //   295: iload #12
    //   297: istore #17
    //   299: iconst_0
    //   300: istore #18
    //   302: iload #18
    //   304: bipush #80
    //   306: if_icmpge -> 556
    //   309: iload #18
    //   311: bipush #16
    //   313: if_icmpge -> 340
    //   316: aload #7
    //   318: iload #18
    //   320: aload #5
    //   322: iload #6
    //   324: iload #18
    //   326: iadd
    //   327: iaload
    //   328: iastore
    //   329: iload_2
    //   330: ifeq -> 395
    //   333: goto -> 340
    //   336: invokestatic a : (Ljava/lang/Throwable;)Ljava/lang/Throwable;
    //   339: athrow
    //   340: aload #7
    //   342: iload #18
    //   344: iconst_3
    //   345: isub
    //   346: iaload
    //   347: aload #7
    //   349: iload #18
    //   351: bipush #8
    //   353: isub
    //   354: iaload
    //   355: ixor
    //   356: aload #7
    //   358: iload #18
    //   360: bipush #14
    //   362: isub
    //   363: iaload
    //   364: ixor
    //   365: aload #7
    //   367: iload #18
    //   369: bipush #16
    //   371: isub
    //   372: iaload
    //   373: ixor
    //   374: istore #19
    //   376: iload #19
    //   378: iconst_1
    //   379: ishl
    //   380: iload #19
    //   382: bipush #31
    //   384: iushr
    //   385: ior
    //   386: istore #20
    //   388: aload #7
    //   390: iload #18
    //   392: iload #20
    //   394: iastore
    //   395: iload #8
    //   397: iconst_5
    //   398: ishl
    //   399: iload #8
    //   401: bipush #27
    //   403: iushr
    //   404: ior
    //   405: istore #19
    //   407: iload #19
    //   409: iload #12
    //   411: iadd
    //   412: aload #7
    //   414: iload #18
    //   416: iaload
    //   417: iadd
    //   418: iload #18
    //   420: bipush #20
    //   422: if_icmpge -> 448
    //   425: ldc 1518500249
    //   427: iload #9
    //   429: iload #10
    //   431: iand
    //   432: iload #9
    //   434: iconst_m1
    //   435: ixor
    //   436: iload #11
    //   438: iand
    //   439: ior
    //   440: iadd
    //   441: goto -> 518
    //   444: invokestatic a : (Ljava/lang/Throwable;)Ljava/lang/Throwable;
    //   447: athrow
    //   448: iload #18
    //   450: bipush #40
    //   452: if_icmpge -> 473
    //   455: ldc 1859775393
    //   457: iload #9
    //   459: iload #10
    //   461: ixor
    //   462: iload #11
    //   464: ixor
    //   465: iadd
    //   466: goto -> 518
    //   469: invokestatic a : (Ljava/lang/Throwable;)Ljava/lang/Throwable;
    //   472: athrow
    //   473: iload #18
    //   475: bipush #60
    //   477: if_icmpge -> 507
    //   480: ldc -1894007588
    //   482: iload #9
    //   484: iload #10
    //   486: iand
    //   487: iload #9
    //   489: iload #11
    //   491: iand
    //   492: ior
    //   493: iload #10
    //   495: iload #11
    //   497: iand
    //   498: ior
    //   499: iadd
    //   500: goto -> 518
    //   503: invokestatic a : (Ljava/lang/Throwable;)Ljava/lang/Throwable;
    //   506: athrow
    //   507: ldc -899497514
    //   509: iload #9
    //   511: iload #10
    //   513: ixor
    //   514: iload #11
    //   516: ixor
    //   517: iadd
    //   518: iadd
    //   519: istore #20
    //   521: iload #11
    //   523: istore #12
    //   525: iload #10
    //   527: istore #11
    //   529: iload #9
    //   531: bipush #30
    //   533: ishl
    //   534: iload #9
    //   536: iconst_2
    //   537: iushr
    //   538: ior
    //   539: istore #10
    //   541: iload #8
    //   543: istore #9
    //   545: iload #20
    //   547: istore #8
    //   549: iinc #18, 1
    //   552: iload_2
    //   553: ifeq -> 302
    //   556: iload #8
    //   558: iload #13
    //   560: iadd
    //   561: istore #8
    //   563: iload #9
    //   565: iload #14
    //   567: iadd
    //   568: istore #9
    //   570: iload #10
    //   572: iload #15
    //   574: iadd
    //   575: istore #10
    //   577: iload #11
    //   579: iload #16
    //   581: iadd
    //   582: istore #11
    //   584: iload #12
    //   586: iload #17
    //   588: iadd
    //   589: istore #12
    //   591: iinc #6, 16
    //   594: iload_2
    //   595: ifeq -> 271
    //   598: iconst_5
    //   599: newarray int
    //   601: dup
    //   602: iconst_0
    //   603: iload #8
    //   605: iastore
    //   606: dup
    //   607: iconst_1
    //   608: iload #9
    //   610: iastore
    //   611: dup
    //   612: iconst_2
    //   613: iload #10
    //   615: iastore
    //   616: dup
    //   617: iconst_3
    //   618: iload #11
    //   620: iastore
    //   621: dup
    //   622: iconst_4
    //   623: iload #12
    //   625: iastore
    //   626: astore #13
    //   628: bipush #20
    //   630: newarray byte
    //   632: astore #14
    //   634: iconst_0
    //   635: istore #15
    //   637: iload #15
    //   639: bipush #20
    //   641: if_icmpge -> 682
    //   644: aload #13
    //   646: iload #15
    //   648: iconst_4
    //   649: idiv
    //   650: iaload
    //   651: istore #16
    //   653: iconst_3
    //   654: iload #15
    //   656: iconst_4
    //   657: irem
    //   658: isub
    //   659: bipush #8
    //   661: imul
    //   662: istore #17
    //   664: aload #14
    //   666: iload #15
    //   668: iload #16
    //   670: iload #17
    //   672: iushr
    //   673: i2b
    //   674: bastore
    //   675: iinc #15, 1
    //   678: iload_2
    //   679: ifeq -> 637
    //   682: aload #14
    //   684: astore #4
    //   686: new java/lang/StringBuilder
    //   689: dup
    //   690: invokespecial <init> : ()V
    //   693: astore_3
    //   694: iconst_0
    //   695: istore #4
    //   697: iload #4
    //   699: bipush #32
    //   701: if_icmpge -> 2035
    //   704: iload #4
    //   706: tableswitch default -> 2028, 0 -> 848, 1 -> 885, 2 -> 922, 3 -> 959, 4 -> 996, 5 -> 1033, 6 -> 1070, 7 -> 1107, 8 -> 1144, 9 -> 1181, 10 -> 1218, 11 -> 1255, 12 -> 1292, 13 -> 1329, 14 -> 1366, 15 -> 1403, 16 -> 1440, 17 -> 1477, 18 -> 1514, 19 -> 1551, 20 -> 1588, 21 -> 1625, 22 -> 1662, 23 -> 1699, 24 -> 1736, 25 -> 1773, 26 -> 1810, 27 -> 1847, 28 -> 1884, 29 -> 1921, 30 -> 1958, 31 -> 1995
    //   848: aload_3
    //   849: getstatic burp/Zesw.ZC : Ljava/lang/String;
    //   852: getstatic burp/Zle9.ZI : Ljava/lang/Object;
    //   855: checkcast java/math/BigInteger
    //   858: invokevirtual intValue : ()I
    //   861: bipush #32
    //   863: irem
    //   864: invokestatic abs : (I)I
    //   867: invokevirtual charAt : (I)C
    //   870: invokevirtual append : (C)Ljava/lang/StringBuilder;
    //   873: pop
    //   874: iload_2
    //   875: ifeq -> 2028
    //   878: goto -> 885
    //   881: invokestatic a : (Ljava/lang/Throwable;)Ljava/lang/Throwable;
    //   884: athrow
    //   885: aload_3
    //   886: getstatic burp/Zr2q.ZA : Ljava/lang/String;
    //   889: getstatic burp/Zbjx.ZT : Ljava/lang/Object;
    //   892: checkcast java/math/BigInteger
    //   895: invokevirtual intValue : ()I
    //   898: bipush #32
    //   900: irem
    //   901: invokestatic abs : (I)I
    //   904: invokevirtual charAt : (I)C
    //   907: invokevirtual append : (C)Ljava/lang/StringBuilder;
    //   910: pop
    //   911: iload_2
    //   912: ifeq -> 2028
    //   915: goto -> 922
    //   918: invokestatic a : (Ljava/lang/Throwable;)Ljava/lang/Throwable;
    //   921: athrow
    //   922: aload_3
    //   923: getstatic burp/Zm0d.ZV : Ljava/lang/String;
    //   926: getstatic burp/Zt9f.Zl : Ljava/lang/Object;
    //   929: checkcast java/math/BigInteger
    //   932: invokevirtual intValue : ()I
    //   935: bipush #32
    //   937: irem
    //   938: invokestatic abs : (I)I
    //   941: invokevirtual charAt : (I)C
    //   944: invokevirtual append : (C)Ljava/lang/StringBuilder;
    //   947: pop
    //   948: iload_2
    //   949: ifeq -> 2028
    //   952: goto -> 959
    //   955: invokestatic a : (Ljava/lang/Throwable;)Ljava/lang/Throwable;
    //   958: athrow
    //   959: aload_3
    //   960: getstatic burp/Ztwp.ZK : Ljava/lang/String;
    //   963: getstatic burp/Zbjx.ZT : Ljava/lang/Object;
    //   966: checkcast java/math/BigInteger
    //   969: invokevirtual intValue : ()I
    //   972: bipush #32
    //   974: irem
    //   975: invokestatic abs : (I)I
    //   978: invokevirtual charAt : (I)C
    //   981: invokevirtual append : (C)Ljava/lang/StringBuilder;
    //   984: pop
    //   985: iload_2
    //   986: ifeq -> 2028
    //   989: goto -> 996
    //   992: invokestatic a : (Ljava/lang/Throwable;)Ljava/lang/Throwable;
    //   995: athrow
    //   996: aload_3
    //   997: getstatic burp/Ze25.Zp : Ljava/lang/String;
    //   1000: getstatic burp/Zeig.ZA : Ljava/lang/Object;
    //   1003: checkcast java/math/BigInteger
    //   1006: invokevirtual intValue : ()I
    //   1009: bipush #32
    //   1011: irem
    //   1012: invokestatic abs : (I)I
    //   1015: invokevirtual charAt : (I)C
    //   1018: invokevirtual append : (C)Ljava/lang/StringBuilder;
    //   1021: pop
    //   1022: iload_2
    //   1023: ifeq -> 2028
    //   1026: goto -> 1033
    //   1029: invokestatic a : (Ljava/lang/Throwable;)Ljava/lang/Throwable;
    //   1032: athrow
    //   1033: aload_3
    //   1034: getstatic burp/Zb4d.ZS : Ljava/lang/String;
    //   1037: getstatic burp/Zz41.Zv : Ljava/lang/Object;
    //   1040: checkcast java/math/BigInteger
    //   1043: invokevirtual intValue : ()I
    //   1046: bipush #32
    //   1048: irem
    //   1049: invokestatic abs : (I)I
    //   1052: invokevirtual charAt : (I)C
    //   1055: invokevirtual append : (C)Ljava/lang/StringBuilder;
    //   1058: pop
    //   1059: iload_2
    //   1060: ifeq -> 2028
    //   1063: goto -> 1070
    //   1066: invokestatic a : (Ljava/lang/Throwable;)Ljava/lang/Throwable;
    //   1069: athrow
    //   1070: aload_3
    //   1071: getstatic burp/Zt5t.ZK : Ljava/lang/String;
    //   1074: getstatic burp/Zm0d.Zz : Ljava/lang/Object;
    //   1077: checkcast java/math/BigInteger
    //   1080: invokevirtual intValue : ()I
    //   1083: bipush #32
    //   1085: irem
    //   1086: invokestatic abs : (I)I
    //   1089: invokevirtual charAt : (I)C
    //   1092: invokevirtual append : (C)Ljava/lang/StringBuilder;
    //   1095: pop
    //   1096: iload_2
    //   1097: ifeq -> 2028
    //   1100: goto -> 1107
    //   1103: invokestatic a : (Ljava/lang/Throwable;)Ljava/lang/Throwable;
    //   1106: athrow
    //   1107: aload_3
    //   1108: getstatic burp/Zt81.ZL : Ljava/lang/String;
    //   1111: getstatic burp/Zti4.Zi : Ljava/lang/Object;
    //   1114: checkcast java/math/BigInteger
    //   1117: invokevirtual intValue : ()I
    //   1120: bipush #32
    //   1122: irem
    //   1123: invokestatic abs : (I)I
    //   1126: invokevirtual charAt : (I)C
    //   1129: invokevirtual append : (C)Ljava/lang/StringBuilder;
    //   1132: pop
    //   1133: iload_2
    //   1134: ifeq -> 2028
    //   1137: goto -> 1144
    //   1140: invokestatic a : (Ljava/lang/Throwable;)Ljava/lang/Throwable;
    //   1143: athrow
    //   1144: aload_3
    //   1145: getstatic burp/Zk9q.Zk : Ljava/lang/String;
    //   1148: getstatic burp/Ze2w.ZA : Ljava/lang/Object;
    //   1151: checkcast java/math/BigInteger
    //   1154: invokevirtual intValue : ()I
    //   1157: bipush #32
    //   1159: irem
    //   1160: invokestatic abs : (I)I
    //   1163: invokevirtual charAt : (I)C
    //   1166: invokevirtual append : (C)Ljava/lang/StringBuilder;
    //   1169: pop
    //   1170: iload_2
    //   1171: ifeq -> 2028
    //   1174: goto -> 1181
    //   1177: invokestatic a : (Ljava/lang/Throwable;)Ljava/lang/Throwable;
    //   1180: athrow
    //   1181: aload_3
    //   1182: getstatic burp/Zs_m.Zt : Ljava/lang/String;
    //   1185: getstatic burp/Zm63.ZT : Ljava/lang/Object;
    //   1188: checkcast java/math/BigInteger
    //   1191: invokevirtual intValue : ()I
    //   1194: bipush #32
    //   1196: irem
    //   1197: invokestatic abs : (I)I
    //   1200: invokevirtual charAt : (I)C
    //   1203: invokevirtual append : (C)Ljava/lang/StringBuilder;
    //   1206: pop
    //   1207: iload_2
    //   1208: ifeq -> 2028
    //   1211: goto -> 1218
    //   1214: invokestatic a : (Ljava/lang/Throwable;)Ljava/lang/Throwable;
    //   1217: athrow
    //   1218: aload_3
    //   1219: getstatic burp/Zg4l.Z_ : Ljava/lang/String;
    //   1222: getstatic burp/Zs4g.ZC : Ljava/lang/Object;
    //   1225: checkcast java/math/BigInteger
    //   1228: invokevirtual intValue : ()I
    //   1231: bipush #32
    //   1233: irem
    //   1234: invokestatic abs : (I)I
    //   1237: invokevirtual charAt : (I)C
    //   1240: invokevirtual append : (C)Ljava/lang/StringBuilder;
    //   1243: pop
    //   1244: iload_2
    //   1245: ifeq -> 2028
    //   1248: goto -> 1255
    //   1251: invokestatic a : (Ljava/lang/Throwable;)Ljava/lang/Throwable;
    //   1254: athrow
    //   1255: aload_3
    //   1256: getstatic burp/Zg4z.Zm : Ljava/lang/String;
    //   1259: getstatic burp/Ztl6.ZQ : Ljava/lang/Object;
    //   1262: checkcast java/math/BigInteger
    //   1265: invokevirtual intValue : ()I
    //   1268: bipush #32
    //   1270: irem
    //   1271: invokestatic abs : (I)I
    //   1274: invokevirtual charAt : (I)C
    //   1277: invokevirtual append : (C)Ljava/lang/StringBuilder;
    //   1280: pop
    //   1281: iload_2
    //   1282: ifeq -> 2028
    //   1285: goto -> 1292
    //   1288: invokestatic a : (Ljava/lang/Throwable;)Ljava/lang/Throwable;
    //   1291: athrow
    //   1292: aload_3
    //   1293: getstatic burp/Zea9.Zd : Ljava/lang/String;
    //   1296: getstatic burp/Zr02.ZB : Ljava/lang/Object;
    //   1299: checkcast java/math/BigInteger
    //   1302: invokevirtual intValue : ()I
    //   1305: bipush #32
    //   1307: irem
    //   1308: invokestatic abs : (I)I
    //   1311: invokevirtual charAt : (I)C
    //   1314: invokevirtual append : (C)Ljava/lang/StringBuilder;
    //   1317: pop
    //   1318: iload_2
    //   1319: ifeq -> 2028
    //   1322: goto -> 1329
    //   1325: invokestatic a : (Ljava/lang/Throwable;)Ljava/lang/Throwable;
    //   1328: athrow
    //   1329: aload_3
    //   1330: getstatic burp/Ze8j.ZU : Ljava/lang/String;
    //   1333: getstatic burp/Zscz.ZN : Ljava/lang/Object;
    //   1336: checkcast java/math/BigInteger
    //   1339: invokevirtual intValue : ()I
    //   1342: bipush #32
    //   1344: irem
    //   1345: invokestatic abs : (I)I
    //   1348: invokevirtual charAt : (I)C
    //   1351: invokevirtual append : (C)Ljava/lang/StringBuilder;
    //   1354: pop
    //   1355: iload_2
    //   1356: ifeq -> 2028
    //   1359: goto -> 1366
    //   1362: invokestatic a : (Ljava/lang/Throwable;)Ljava/lang/Throwable;
    //   1365: athrow
    //   1366: aload_3
    //   1367: getstatic burp/Ztwp.ZK : Ljava/lang/String;
    //   1370: getstatic burp/Zzh5.ZG : Ljava/lang/Object;
    //   1373: checkcast java/math/BigInteger
    //   1376: invokevirtual intValue : ()I
    //   1379: bipush #32
    //   1381: irem
    //   1382: invokestatic abs : (I)I
    //   1385: invokevirtual charAt : (I)C
    //   1388: invokevirtual append : (C)Ljava/lang/StringBuilder;
    //   1391: pop
    //   1392: iload_2
    //   1393: ifeq -> 2028
    //   1396: goto -> 1403
    //   1399: invokestatic a : (Ljava/lang/Throwable;)Ljava/lang/Throwable;
    //   1402: athrow
    //   1403: aload_3
    //   1404: getstatic burp/Zr60.ZQ : Ljava/lang/String;
    //   1407: getstatic burp/Zb9q.ZI : Ljava/lang/Object;
    //   1410: checkcast java/math/BigInteger
    //   1413: invokevirtual intValue : ()I
    //   1416: bipush #32
    //   1418: irem
    //   1419: invokestatic abs : (I)I
    //   1422: invokevirtual charAt : (I)C
    //   1425: invokevirtual append : (C)Ljava/lang/StringBuilder;
    //   1428: pop
    //   1429: iload_2
    //   1430: ifeq -> 2028
    //   1433: goto -> 1440
    //   1436: invokestatic a : (Ljava/lang/Throwable;)Ljava/lang/Throwable;
    //   1439: athrow
    //   1440: aload_3
    //   1441: getstatic burp/Zso.ZL : Ljava/lang/String;
    //   1444: getstatic burp/Zgtx.Z_ : Ljava/lang/Object;
    //   1447: checkcast java/math/BigInteger
    //   1450: invokevirtual intValue : ()I
    //   1453: bipush #32
    //   1455: irem
    //   1456: invokestatic abs : (I)I
    //   1459: invokevirtual charAt : (I)C
    //   1462: invokevirtual append : (C)Ljava/lang/StringBuilder;
    //   1465: pop
    //   1466: iload_2
    //   1467: ifeq -> 2028
    //   1470: goto -> 1477
    //   1473: invokestatic a : (Ljava/lang/Throwable;)Ljava/lang/Throwable;
    //   1476: athrow
    //   1477: aload_3
    //   1478: getstatic burp/Zz4j.ZS : Ljava/lang/String;
    //   1481: getstatic burp/Zlf7.ZE : Ljava/lang/Object;
    //   1484: checkcast java/math/BigInteger
    //   1487: invokevirtual intValue : ()I
    //   1490: bipush #32
    //   1492: irem
    //   1493: invokestatic abs : (I)I
    //   1496: invokevirtual charAt : (I)C
    //   1499: invokevirtual append : (C)Ljava/lang/StringBuilder;
    //   1502: pop
    //   1503: iload_2
    //   1504: ifeq -> 2028
    //   1507: goto -> 1514
    //   1510: invokestatic a : (Ljava/lang/Throwable;)Ljava/lang/Throwable;
    //   1513: athrow
    //   1514: aload_3
    //   1515: getstatic burp/Zsbv.Zr : Ljava/lang/String;
    //   1518: getstatic burp/Zt8m.Zf : Ljava/lang/Object;
    //   1521: checkcast java/math/BigInteger
    //   1524: invokevirtual intValue : ()I
    //   1527: bipush #32
    //   1529: irem
    //   1530: invokestatic abs : (I)I
    //   1533: invokevirtual charAt : (I)C
    //   1536: invokevirtual append : (C)Ljava/lang/StringBuilder;
    //   1539: pop
    //   1540: iload_2
    //   1541: ifeq -> 2028
    //   1544: goto -> 1551
    //   1547: invokestatic a : (Ljava/lang/Throwable;)Ljava/lang/Throwable;
    //   1550: athrow
    //   1551: aload_3
    //   1552: getstatic burp/Zzac.ZE : Ljava/lang/String;
    //   1555: getstatic burp/Zbx4.Zw : Ljava/lang/Object;
    //   1558: checkcast java/math/BigInteger
    //   1561: invokevirtual intValue : ()I
    //   1564: bipush #32
    //   1566: irem
    //   1567: invokestatic abs : (I)I
    //   1570: invokevirtual charAt : (I)C
    //   1573: invokevirtual append : (C)Ljava/lang/StringBuilder;
    //   1576: pop
    //   1577: iload_2
    //   1578: ifeq -> 2028
    //   1581: goto -> 1588
    //   1584: invokestatic a : (Ljava/lang/Throwable;)Ljava/lang/Throwable;
    //   1587: athrow
    //   1588: aload_3
    //   1589: getstatic burp/Zzyb.Zh : Ljava/lang/String;
    //   1592: getstatic burp/Ztq2.Zj : Ljava/lang/Object;
    //   1595: checkcast java/math/BigInteger
    //   1598: invokevirtual intValue : ()I
    //   1601: bipush #32
    //   1603: irem
    //   1604: invokestatic abs : (I)I
    //   1607: invokevirtual charAt : (I)C
    //   1610: invokevirtual append : (C)Ljava/lang/StringBuilder;
    //   1613: pop
    //   1614: iload_2
    //   1615: ifeq -> 2028
    //   1618: goto -> 1625
    //   1621: invokestatic a : (Ljava/lang/Throwable;)Ljava/lang/Throwable;
    //   1624: athrow
    //   1625: aload_3
    //   1626: getstatic burp/Zej8.ZP : Ljava/lang/String;
    //   1629: getstatic burp/Ze4a.ZP : Ljava/lang/Object;
    //   1632: checkcast java/math/BigInteger
    //   1635: invokevirtual intValue : ()I
    //   1638: bipush #32
    //   1640: irem
    //   1641: invokestatic abs : (I)I
    //   1644: invokevirtual charAt : (I)C
    //   1647: invokevirtual append : (C)Ljava/lang/StringBuilder;
    //   1650: pop
    //   1651: iload_2
    //   1652: ifeq -> 2028
    //   1655: goto -> 1662
    //   1658: invokestatic a : (Ljava/lang/Throwable;)Ljava/lang/Throwable;
    //   1661: athrow
    //   1662: aload_3
    //   1663: getstatic burp/Zeqx.Zu : Ljava/lang/String;
    //   1666: getstatic burp/Zlcc.ZP : Ljava/lang/Object;
    //   1669: checkcast java/math/BigInteger
    //   1672: invokevirtual intValue : ()I
    //   1675: bipush #32
    //   1677: irem
    //   1678: invokestatic abs : (I)I
    //   1681: invokevirtual charAt : (I)C
    //   1684: invokevirtual append : (C)Ljava/lang/StringBuilder;
    //   1687: pop
    //   1688: iload_2
    //   1689: ifeq -> 2028
    //   1692: goto -> 1699
    //   1695: invokestatic a : (Ljava/lang/Throwable;)Ljava/lang/Throwable;
    //   1698: athrow
    //   1699: aload_3
    //   1700: getstatic burp/Zz4m.ZI : Ljava/lang/String;
    //   1703: getstatic burp/Zs1d.Zo : Ljava/lang/Object;
    //   1706: checkcast java/math/BigInteger
    //   1709: invokevirtual intValue : ()I
    //   1712: bipush #32
    //   1714: irem
    //   1715: invokestatic abs : (I)I
    //   1718: invokevirtual charAt : (I)C
    //   1721: invokevirtual append : (C)Ljava/lang/StringBuilder;
    //   1724: pop
    //   1725: iload_2
    //   1726: ifeq -> 2028
    //   1729: goto -> 1736
    //   1732: invokestatic a : (Ljava/lang/Throwable;)Ljava/lang/Throwable;
    //   1735: athrow
    //   1736: aload_3
    //   1737: getstatic burp/Zg0q.Ze : Ljava/lang/String;
    //   1740: getstatic burp/Zzn6.ZO : Ljava/lang/Object;
    //   1743: checkcast java/math/BigInteger
    //   1746: invokevirtual intValue : ()I
    //   1749: bipush #32
    //   1751: irem
    //   1752: invokestatic abs : (I)I
    //   1755: invokevirtual charAt : (I)C
    //   1758: invokevirtual append : (C)Ljava/lang/StringBuilder;
    //   1761: pop
    //   1762: iload_2
    //   1763: ifeq -> 2028
    //   1766: goto -> 1773
    //   1769: invokestatic a : (Ljava/lang/Throwable;)Ljava/lang/Throwable;
    //   1772: athrow
    //   1773: aload_3
    //   1774: getstatic burp/Ztl6.Zb : Ljava/lang/String;
    //   1777: getstatic burp/Zg0q.Zf : Ljava/lang/Object;
    //   1780: checkcast java/math/BigInteger
    //   1783: invokevirtual intValue : ()I
    //   1786: bipush #32
    //   1788: irem
    //   1789: invokestatic abs : (I)I
    //   1792: invokevirtual charAt : (I)C
    //   1795: invokevirtual append : (C)Ljava/lang/StringBuilder;
    //   1798: pop
    //   1799: iload_2
    //   1800: ifeq -> 2028
    //   1803: goto -> 1810
    //   1806: invokestatic a : (Ljava/lang/Throwable;)Ljava/lang/Throwable;
    //   1809: athrow
    //   1810: aload_3
    //   1811: getstatic burp/Zes.ZW : Ljava/lang/String;
    //   1814: getstatic burp/Zegw.ZW : Ljava/lang/Object;
    //   1817: checkcast java/math/BigInteger
    //   1820: invokevirtual intValue : ()I
    //   1823: bipush #32
    //   1825: irem
    //   1826: invokestatic abs : (I)I
    //   1829: invokevirtual charAt : (I)C
    //   1832: invokevirtual append : (C)Ljava/lang/StringBuilder;
    //   1835: pop
    //   1836: iload_2
    //   1837: ifeq -> 2028
    //   1840: goto -> 1847
    //   1843: invokestatic a : (Ljava/lang/Throwable;)Ljava/lang/Throwable;
    //   1846: athrow
    //   1847: aload_3
    //   1848: getstatic burp/Zzmc.Zr : Ljava/lang/String;
    //   1851: getstatic burp/Zld5.ZX : Ljava/lang/Object;
    //   1854: checkcast java/math/BigInteger
    //   1857: invokevirtual intValue : ()I
    //   1860: bipush #32
    //   1862: irem
    //   1863: invokestatic abs : (I)I
    //   1866: invokevirtual charAt : (I)C
    //   1869: invokevirtual append : (C)Ljava/lang/StringBuilder;
    //   1872: pop
    //   1873: iload_2
    //   1874: ifeq -> 2028
    //   1877: goto -> 1884
    //   1880: invokestatic a : (Ljava/lang/Throwable;)Ljava/lang/Throwable;
    //   1883: athrow
    //   1884: aload_3
    //   1885: getstatic burp/Ztle.ZR : Ljava/lang/String;
    //   1888: getstatic burp/Zsbv.Zl : Ljava/lang/Object;
    //   1891: checkcast java/math/BigInteger
    //   1894: invokevirtual intValue : ()I
    //   1897: bipush #32
    //   1899: irem
    //   1900: invokestatic abs : (I)I
    //   1903: invokevirtual charAt : (I)C
    //   1906: invokevirtual append : (C)Ljava/lang/StringBuilder;
    //   1909: pop
    //   1910: iload_2
    //   1911: ifeq -> 2028
    //   1914: goto -> 1921
    //   1917: invokestatic a : (Ljava/lang/Throwable;)Ljava/lang/Throwable;
    //   1920: athrow
    //   1921: aload_3
    //   1922: getstatic burp/Zgu4.Za : Ljava/lang/String;
    //   1925: getstatic burp/Zt85.Zl : Ljava/lang/Object;
    //   1928: checkcast java/math/BigInteger
    //   1931: invokevirtual intValue : ()I
    //   1934: bipush #32
    //   1936: irem
    //   1937: invokestatic abs : (I)I
    //   1940: invokevirtual charAt : (I)C
    //   1943: invokevirtual append : (C)Ljava/lang/StringBuilder;
    //   1946: pop
    //   1947: iload_2
    //   1948: ifeq -> 2028
    //   1951: goto -> 1958
    //   1954: invokestatic a : (Ljava/lang/Throwable;)Ljava/lang/Throwable;
    //   1957: athrow
    //   1958: aload_3
    //   1959: getstatic burp/Zgsb.ZM : Ljava/lang/String;
    //   1962: getstatic burp/Zt85.Zl : Ljava/lang/Object;
    //   1965: checkcast java/math/BigInteger
    //   1968: invokevirtual intValue : ()I
    //   1971: bipush #32
    //   1973: irem
    //   1974: invokestatic abs : (I)I
    //   1977: invokevirtual charAt : (I)C
    //   1980: invokevirtual append : (C)Ljava/lang/StringBuilder;
    //   1983: pop
    //   1984: iload_2
    //   1985: ifeq -> 2028
    //   1988: goto -> 1995
    //   1991: invokestatic a : (Ljava/lang/Throwable;)Ljava/lang/Throwable;
    //   1994: athrow
    //   1995: aload_3
    //   1996: getstatic burp/Zxxf.Zw : Ljava/lang/String;
    //   1999: getstatic burp/Zrle.Zl : Ljava/lang/Object;
    //   2002: checkcast java/math/BigInteger
    //   2005: invokevirtual intValue : ()I
    //   2008: bipush #32
    //   2010: irem
    //   2011: invokestatic abs : (I)I
    //   2014: invokevirtual charAt : (I)C
    //   2017: invokevirtual append : (C)Ljava/lang/StringBuilder;
    //   2020: pop
    //   2021: goto -> 2028
    //   2024: invokestatic a : (Ljava/lang/Throwable;)Ljava/lang/Throwable;
    //   2027: athrow
    //   2028: iinc #4, 1
    //   2031: iload_2
    //   2032: ifeq -> 697
    //   2035: aload_3
    //   2036: invokevirtual toString : ()Ljava/lang/String;
    //   2039: putstatic burp/Zej8.ZP : Ljava/lang/String;
    //   2042: new java/lang/StringBuilder
    //   2045: dup
    //   2046: invokespecial <init> : ()V
    //   2049: astore #4
    //   2051: iconst_0
    //   2052: istore #5
    //   2054: iload #5
    //   2056: bipush #32
    //   2058: if_icmpge -> 3423
    //   2061: iload #5
    //   2063: tableswitch default -> 3416, 0 -> 2204, 1 -> 2242, 2 -> 2280, 3 -> 2318, 4 -> 2356, 5 -> 2394, 6 -> 2432, 7 -> 2470, 8 -> 2508, 9 -> 2546, 10 -> 2584, 11 -> 2622, 12 -> 2660, 13 -> 2698, 14 -> 2736, 15 -> 2774, 16 -> 2812, 17 -> 2850, 18 -> 2888, 19 -> 2926, 20 -> 2964, 21 -> 3002, 22 -> 3040, 23 -> 3078, 24 -> 3116, 25 -> 3154, 26 -> 3192, 27 -> 3230, 28 -> 3268, 29 -> 3306, 30 -> 3344, 31 -> 3382
    //   2204: aload #4
    //   2206: getstatic burp/Zemp.Zs : Ljava/lang/String;
    //   2209: getstatic burp/Zti7.Zw : Ljava/lang/Object;
    //   2212: checkcast java/math/BigInteger
    //   2215: invokevirtual intValue : ()I
    //   2218: bipush #32
    //   2220: irem
    //   2221: invokestatic abs : (I)I
    //   2224: invokevirtual charAt : (I)C
    //   2227: invokevirtual append : (C)Ljava/lang/StringBuilder;
    //   2230: pop
    //   2231: iload_2
    //   2232: ifeq -> 3416
    //   2235: goto -> 2242
    //   2238: invokestatic a : (Ljava/lang/Throwable;)Ljava/lang/Throwable;
    //   2241: athrow
    //   2242: aload #4
    //   2244: getstatic burp/Zmyk.Zx : Ljava/lang/String;
    //   2247: getstatic burp/Zxdy.ZZ : Ljava/lang/Object;
    //   2250: checkcast java/math/BigInteger
    //   2253: invokevirtual intValue : ()I
    //   2256: bipush #32
    //   2258: irem
    //   2259: invokestatic abs : (I)I
    //   2262: invokevirtual charAt : (I)C
    //   2265: invokevirtual append : (C)Ljava/lang/StringBuilder;
    //   2268: pop
    //   2269: iload_2
    //   2270: ifeq -> 3416
    //   2273: goto -> 2280
    //   2276: invokestatic a : (Ljava/lang/Throwable;)Ljava/lang/Throwable;
    //   2279: athrow
    //   2280: aload #4
    //   2282: getstatic burp/Zt8m.ZT : Ljava/lang/String;
    //   2285: getstatic burp/Zg4l.ZI : Ljava/lang/Object;
    //   2288: checkcast java/math/BigInteger
    //   2291: invokevirtual intValue : ()I
    //   2294: bipush #32
    //   2296: irem
    //   2297: invokestatic abs : (I)I
    //   2300: invokevirtual charAt : (I)C
    //   2303: invokevirtual append : (C)Ljava/lang/StringBuilder;
    //   2306: pop
    //   2307: iload_2
    //   2308: ifeq -> 3416
    //   2311: goto -> 2318
    //   2314: invokestatic a : (Ljava/lang/Throwable;)Ljava/lang/Throwable;
    //   2317: athrow
    //   2318: aload #4
    //   2320: getstatic burp/Zsfg.Zh : Ljava/lang/String;
    //   2323: getstatic burp/Zxcn.Zq : Ljava/lang/Object;
    //   2326: checkcast java/math/BigInteger
    //   2329: invokevirtual intValue : ()I
    //   2332: bipush #32
    //   2334: irem
    //   2335: invokestatic abs : (I)I
    //   2338: invokevirtual charAt : (I)C
    //   2341: invokevirtual append : (C)Ljava/lang/StringBuilder;
    //   2344: pop
    //   2345: iload_2
    //   2346: ifeq -> 3416
    //   2349: goto -> 2356
    //   2352: invokestatic a : (Ljava/lang/Throwable;)Ljava/lang/Throwable;
    //   2355: athrow
    //   2356: aload #4
    //   2358: getstatic burp/Zkjj.ZT : Ljava/lang/String;
    //   2361: getstatic burp/Zeub.ZD : Ljava/lang/Object;
    //   2364: checkcast java/math/BigInteger
    //   2367: invokevirtual intValue : ()I
    //   2370: bipush #32
    //   2372: irem
    //   2373: invokestatic abs : (I)I
    //   2376: invokevirtual charAt : (I)C
    //   2379: invokevirtual append : (C)Ljava/lang/StringBuilder;
    //   2382: pop
    //   2383: iload_2
    //   2384: ifeq -> 3416
    //   2387: goto -> 2394
    //   2390: invokestatic a : (Ljava/lang/Throwable;)Ljava/lang/Throwable;
    //   2393: athrow
    //   2394: aload #4
    //   2396: getstatic burp/Zmf6.Zn : Ljava/lang/String;
    //   2399: getstatic burp/Zr9u.ZX : Ljava/lang/Object;
    //   2402: checkcast java/math/BigInteger
    //   2405: invokevirtual intValue : ()I
    //   2408: bipush #32
    //   2410: irem
    //   2411: invokestatic abs : (I)I
    //   2414: invokevirtual charAt : (I)C
    //   2417: invokevirtual append : (C)Ljava/lang/StringBuilder;
    //   2420: pop
    //   2421: iload_2
    //   2422: ifeq -> 3416
    //   2425: goto -> 2432
    //   2428: invokestatic a : (Ljava/lang/Throwable;)Ljava/lang/Throwable;
    //   2431: athrow
    //   2432: aload #4
    //   2434: getstatic burp/Zxn9.ZU : Ljava/lang/String;
    //   2437: getstatic burp/Zk7o.ZO : Ljava/lang/Object;
    //   2440: checkcast java/math/BigInteger
    //   2443: invokevirtual intValue : ()I
    //   2446: bipush #32
    //   2448: irem
    //   2449: invokestatic abs : (I)I
    //   2452: invokevirtual charAt : (I)C
    //   2455: invokevirtual append : (C)Ljava/lang/StringBuilder;
    //   2458: pop
    //   2459: iload_2
    //   2460: ifeq -> 3416
    //   2463: goto -> 2470
    //   2466: invokestatic a : (Ljava/lang/Throwable;)Ljava/lang/Throwable;
    //   2469: athrow
    //   2470: aload #4
    //   2472: getstatic burp/Zsjw.ZQ : Ljava/lang/String;
    //   2475: getstatic burp/Zb2u.ZY : Ljava/lang/Object;
    //   2478: checkcast java/math/BigInteger
    //   2481: invokevirtual intValue : ()I
    //   2484: bipush #32
    //   2486: irem
    //   2487: invokestatic abs : (I)I
    //   2490: invokevirtual charAt : (I)C
    //   2493: invokevirtual append : (C)Ljava/lang/StringBuilder;
    //   2496: pop
    //   2497: iload_2
    //   2498: ifeq -> 3416
    //   2501: goto -> 2508
    //   2504: invokestatic a : (Ljava/lang/Throwable;)Ljava/lang/Throwable;
    //   2507: athrow
    //   2508: aload #4
    //   2510: getstatic burp/Zthx.Ze : Ljava/lang/String;
    //   2513: getstatic burp/Zkdx.Zn : Ljava/lang/Object;
    //   2516: checkcast java/math/BigInteger
    //   2519: invokevirtual intValue : ()I
    //   2522: bipush #32
    //   2524: irem
    //   2525: invokestatic abs : (I)I
    //   2528: invokevirtual charAt : (I)C
    //   2531: invokevirtual append : (C)Ljava/lang/StringBuilder;
    //   2534: pop
    //   2535: iload_2
    //   2536: ifeq -> 3416
    //   2539: goto -> 2546
    //   2542: invokestatic a : (Ljava/lang/Throwable;)Ljava/lang/Throwable;
    //   2545: athrow
    //   2546: aload #4
    //   2548: getstatic burp/Zenr.Z_ : Ljava/lang/String;
    //   2551: getstatic burp/Ze1k.ZD : Ljava/lang/Object;
    //   2554: checkcast java/math/BigInteger
    //   2557: invokevirtual intValue : ()I
    //   2560: bipush #32
    //   2562: irem
    //   2563: invokestatic abs : (I)I
    //   2566: invokevirtual charAt : (I)C
    //   2569: invokevirtual append : (C)Ljava/lang/StringBuilder;
    //   2572: pop
    //   2573: iload_2
    //   2574: ifeq -> 3416
    //   2577: goto -> 2584
    //   2580: invokestatic a : (Ljava/lang/Throwable;)Ljava/lang/Throwable;
    //   2583: athrow
    //   2584: aload #4
    //   2586: getstatic burp/Zeqz.ZV : Ljava/lang/String;
    //   2589: getstatic burp/Zzac.ZH : Ljava/lang/Object;
    //   2592: checkcast java/math/BigInteger
    //   2595: invokevirtual intValue : ()I
    //   2598: bipush #32
    //   2600: irem
    //   2601: invokestatic abs : (I)I
    //   2604: invokevirtual charAt : (I)C
    //   2607: invokevirtual append : (C)Ljava/lang/StringBuilder;
    //   2610: pop
    //   2611: iload_2
    //   2612: ifeq -> 3416
    //   2615: goto -> 2622
    //   2618: invokestatic a : (Ljava/lang/Throwable;)Ljava/lang/Throwable;
    //   2621: athrow
    //   2622: aload #4
    //   2624: getstatic burp/Zgsy.Zv : Ljava/lang/String;
    //   2627: getstatic burp/Zzl4.ZX : Ljava/lang/Object;
    //   2630: checkcast java/math/BigInteger
    //   2633: invokevirtual intValue : ()I
    //   2636: bipush #32
    //   2638: irem
    //   2639: invokestatic abs : (I)I
    //   2642: invokevirtual charAt : (I)C
    //   2645: invokevirtual append : (C)Ljava/lang/StringBuilder;
    //   2648: pop
    //   2649: iload_2
    //   2650: ifeq -> 3416
    //   2653: goto -> 2660
    //   2656: invokestatic a : (Ljava/lang/Throwable;)Ljava/lang/Throwable;
    //   2659: athrow
    //   2660: aload #4
    //   2662: getstatic burp/Zgsb.ZM : Ljava/lang/String;
    //   2665: getstatic burp/Zs8w.ZW : Ljava/lang/Object;
    //   2668: checkcast java/math/BigInteger
    //   2671: invokevirtual intValue : ()I
    //   2674: bipush #32
    //   2676: irem
    //   2677: invokestatic abs : (I)I
    //   2680: invokevirtual charAt : (I)C
    //   2683: invokevirtual append : (C)Ljava/lang/StringBuilder;
    //   2686: pop
    //   2687: iload_2
    //   2688: ifeq -> 3416
    //   2691: goto -> 2698
    //   2694: invokestatic a : (Ljava/lang/Throwable;)Ljava/lang/Throwable;
    //   2697: athrow
    //   2698: aload #4
    //   2700: getstatic burp/Zgio.ZS : Ljava/lang/String;
    //   2703: getstatic burp/Zzr8.ZC : Ljava/lang/Object;
    //   2706: checkcast java/math/BigInteger
    //   2709: invokevirtual intValue : ()I
    //   2712: bipush #32
    //   2714: irem
    //   2715: invokestatic abs : (I)I
    //   2718: invokevirtual charAt : (I)C
    //   2721: invokevirtual append : (C)Ljava/lang/StringBuilder;
    //   2724: pop
    //   2725: iload_2
    //   2726: ifeq -> 3416
    //   2729: goto -> 2736
    //   2732: invokestatic a : (Ljava/lang/Throwable;)Ljava/lang/Throwable;
    //   2735: athrow
    //   2736: aload #4
    //   2738: getstatic burp/Zrkw.ZU : Ljava/lang/String;
    //   2741: getstatic burp/Zb6m.ZQ : Ljava/lang/Object;
    //   2744: checkcast java/math/BigInteger
    //   2747: invokevirtual intValue : ()I
    //   2750: bipush #32
    //   2752: irem
    //   2753: invokestatic abs : (I)I
    //   2756: invokevirtual charAt : (I)C
    //   2759: invokevirtual append : (C)Ljava/lang/StringBuilder;
    //   2762: pop
    //   2763: iload_2
    //   2764: ifeq -> 3416
    //   2767: goto -> 2774
    //   2770: invokestatic a : (Ljava/lang/Throwable;)Ljava/lang/Throwable;
    //   2773: athrow
    //   2774: aload #4
    //   2776: getstatic burp/Zebc.ZC : Ljava/lang/String;
    //   2779: getstatic burp/Zrqi.Zb : Ljava/lang/Object;
    //   2782: checkcast java/math/BigInteger
    //   2785: invokevirtual intValue : ()I
    //   2788: bipush #32
    //   2790: irem
    //   2791: invokestatic abs : (I)I
    //   2794: invokevirtual charAt : (I)C
    //   2797: invokevirtual append : (C)Ljava/lang/StringBuilder;
    //   2800: pop
    //   2801: iload_2
    //   2802: ifeq -> 3416
    //   2805: goto -> 2812
    //   2808: invokestatic a : (Ljava/lang/Throwable;)Ljava/lang/Throwable;
    //   2811: athrow
    //   2812: aload #4
    //   2814: getstatic burp/Zsn4.ZZ : Ljava/lang/String;
    //   2817: getstatic burp/Zbnz.Zb : Ljava/lang/Object;
    //   2820: checkcast java/math/BigInteger
    //   2823: invokevirtual intValue : ()I
    //   2826: bipush #32
    //   2828: irem
    //   2829: invokestatic abs : (I)I
    //   2832: invokevirtual charAt : (I)C
    //   2835: invokevirtual append : (C)Ljava/lang/StringBuilder;
    //   2838: pop
    //   2839: iload_2
    //   2840: ifeq -> 3416
    //   2843: goto -> 2850
    //   2846: invokestatic a : (Ljava/lang/Throwable;)Ljava/lang/Throwable;
    //   2849: athrow
    //   2850: aload #4
    //   2852: getstatic burp/Zsko.Zd : Ljava/lang/String;
    //   2855: getstatic burp/Zkql.Zl : Ljava/lang/Object;
    //   2858: checkcast java/math/BigInteger
    //   2861: invokevirtual intValue : ()I
    //   2864: bipush #32
    //   2866: irem
    //   2867: invokestatic abs : (I)I
    //   2870: invokevirtual charAt : (I)C
    //   2873: invokevirtual append : (C)Ljava/lang/StringBuilder;
    //   2876: pop
    //   2877: iload_2
    //   2878: ifeq -> 3416
    //   2881: goto -> 2888
    //   2884: invokestatic a : (Ljava/lang/Throwable;)Ljava/lang/Throwable;
    //   2887: athrow
    //   2888: aload #4
    //   2890: getstatic burp/Zxy6.ZR : Ljava/lang/String;
    //   2893: getstatic burp/Zlf7.ZE : Ljava/lang/Object;
    //   2896: checkcast java/math/BigInteger
    //   2899: invokevirtual intValue : ()I
    //   2902: bipush #32
    //   2904: irem
    //   2905: invokestatic abs : (I)I
    //   2908: invokevirtual charAt : (I)C
    //   2911: invokevirtual append : (C)Ljava/lang/StringBuilder;
    //   2914: pop
    //   2915: iload_2
    //   2916: ifeq -> 3416
    //   2919: goto -> 2926
    //   2922: invokestatic a : (Ljava/lang/Throwable;)Ljava/lang/Throwable;
    //   2925: athrow
    //   2926: aload #4
    //   2928: getstatic burp/Zrnt.Zy : Ljava/lang/String;
    //   2931: getstatic burp/Zegw.ZW : Ljava/lang/Object;
    //   2934: checkcast java/math/BigInteger
    //   2937: invokevirtual intValue : ()I
    //   2940: bipush #32
    //   2942: irem
    //   2943: invokestatic abs : (I)I
    //   2946: invokevirtual charAt : (I)C
    //   2949: invokevirtual append : (C)Ljava/lang/StringBuilder;
    //   2952: pop
    //   2953: iload_2
    //   2954: ifeq -> 3416
    //   2957: goto -> 2964
    //   2960: invokestatic a : (Ljava/lang/Throwable;)Ljava/lang/Throwable;
    //   2963: athrow
    //   2964: aload #4
    //   2966: getstatic burp/Zgu4.Za : Ljava/lang/String;
    //   2969: getstatic burp/Zgio.ZP : Ljava/lang/Object;
    //   2972: checkcast java/math/BigInteger
    //   2975: invokevirtual intValue : ()I
    //   2978: bipush #32
    //   2980: irem
    //   2981: invokestatic abs : (I)I
    //   2984: invokevirtual charAt : (I)C
    //   2987: invokevirtual append : (C)Ljava/lang/StringBuilder;
    //   2990: pop
    //   2991: iload_2
    //   2992: ifeq -> 3416
    //   2995: goto -> 3002
    //   2998: invokestatic a : (Ljava/lang/Throwable;)Ljava/lang/Throwable;
    //   3001: athrow
    //   3002: aload #4
    //   3004: getstatic burp/Zbow.Zr : Ljava/lang/String;
    //   3007: getstatic burp/Zz41.Zv : Ljava/lang/Object;
    //   3010: checkcast java/math/BigInteger
    //   3013: invokevirtual intValue : ()I
    //   3016: bipush #32
    //   3018: irem
    //   3019: invokestatic abs : (I)I
    //   3022: invokevirtual charAt : (I)C
    //   3025: invokevirtual append : (C)Ljava/lang/StringBuilder;
    //   3028: pop
    //   3029: iload_2
    //   3030: ifeq -> 3416
    //   3033: goto -> 3040
    //   3036: invokestatic a : (Ljava/lang/Throwable;)Ljava/lang/Throwable;
    //   3039: athrow
    //   3040: aload #4
    //   3042: getstatic burp/Zxci.Zw : Ljava/lang/String;
    //   3045: getstatic burp/Zbun.ZH : Ljava/lang/Object;
    //   3048: checkcast java/math/BigInteger
    //   3051: invokevirtual intValue : ()I
    //   3054: bipush #32
    //   3056: irem
    //   3057: invokestatic abs : (I)I
    //   3060: invokevirtual charAt : (I)C
    //   3063: invokevirtual append : (C)Ljava/lang/StringBuilder;
    //   3066: pop
    //   3067: iload_2
    //   3068: ifeq -> 3416
    //   3071: goto -> 3078
    //   3074: invokestatic a : (Ljava/lang/Throwable;)Ljava/lang/Throwable;
    //   3077: athrow
    //   3078: aload #4
    //   3080: getstatic burp/Zsjw.ZQ : Ljava/lang/String;
    //   3083: getstatic burp/Zex0.Ze : Ljava/lang/Object;
    //   3086: checkcast java/math/BigInteger
    //   3089: invokevirtual intValue : ()I
    //   3092: bipush #32
    //   3094: irem
    //   3095: invokestatic abs : (I)I
    //   3098: invokevirtual charAt : (I)C
    //   3101: invokevirtual append : (C)Ljava/lang/StringBuilder;
    //   3104: pop
    //   3105: iload_2
    //   3106: ifeq -> 3416
    //   3109: goto -> 3116
    //   3112: invokestatic a : (Ljava/lang/Throwable;)Ljava/lang/Throwable;
    //   3115: athrow
    //   3116: aload #4
    //   3118: getstatic burp/Zlsg.Zs : Ljava/lang/String;
    //   3121: getstatic burp/Zge2.Zv : Ljava/lang/Object;
    //   3124: checkcast java/math/BigInteger
    //   3127: invokevirtual intValue : ()I
    //   3130: bipush #32
    //   3132: irem
    //   3133: invokestatic abs : (I)I
    //   3136: invokevirtual charAt : (I)C
    //   3139: invokevirtual append : (C)Ljava/lang/StringBuilder;
    //   3142: pop
    //   3143: iload_2
    //   3144: ifeq -> 3416
    //   3147: goto -> 3154
    //   3150: invokestatic a : (Ljava/lang/Throwable;)Ljava/lang/Throwable;
    //   3153: athrow
    //   3154: aload #4
    //   3156: getstatic burp/Zs5y.ZO : Ljava/lang/String;
    //   3159: getstatic burp/Zes.Zx : Ljava/lang/Object;
    //   3162: checkcast java/math/BigInteger
    //   3165: invokevirtual intValue : ()I
    //   3168: bipush #32
    //   3170: irem
    //   3171: invokestatic abs : (I)I
    //   3174: invokevirtual charAt : (I)C
    //   3177: invokevirtual append : (C)Ljava/lang/StringBuilder;
    //   3180: pop
    //   3181: iload_2
    //   3182: ifeq -> 3416
    //   3185: goto -> 3192
    //   3188: invokestatic a : (Ljava/lang/Throwable;)Ljava/lang/Throwable;
    //   3191: athrow
    //   3192: aload #4
    //   3194: getstatic burp/Zea8.ZE : Ljava/lang/String;
    //   3197: getstatic burp/Zg0q.Zf : Ljava/lang/Object;
    //   3200: checkcast java/math/BigInteger
    //   3203: invokevirtual intValue : ()I
    //   3206: bipush #32
    //   3208: irem
    //   3209: invokestatic abs : (I)I
    //   3212: invokevirtual charAt : (I)C
    //   3215: invokevirtual append : (C)Ljava/lang/StringBuilder;
    //   3218: pop
    //   3219: iload_2
    //   3220: ifeq -> 3416
    //   3223: goto -> 3230
    //   3226: invokestatic a : (Ljava/lang/Throwable;)Ljava/lang/Throwable;
    //   3229: athrow
    //   3230: aload #4
    //   3232: getstatic burp/Zmc_.Zb : Ljava/lang/String;
    //   3235: getstatic burp/Zrwp.Zk : Ljava/lang/Object;
    //   3238: checkcast java/math/BigInteger
    //   3241: invokevirtual intValue : ()I
    //   3244: bipush #32
    //   3246: irem
    //   3247: invokestatic abs : (I)I
    //   3250: invokevirtual charAt : (I)C
    //   3253: invokevirtual append : (C)Ljava/lang/StringBuilder;
    //   3256: pop
    //   3257: iload_2
    //   3258: ifeq -> 3416
    //   3261: goto -> 3268
    //   3264: invokestatic a : (Ljava/lang/Throwable;)Ljava/lang/Throwable;
    //   3267: athrow
    //   3268: aload #4
    //   3270: getstatic burp/Zbnk.Zg : Ljava/lang/String;
    //   3273: getstatic burp/Zz4a.ZB : Ljava/lang/Object;
    //   3276: checkcast java/math/BigInteger
    //   3279: invokevirtual intValue : ()I
    //   3282: bipush #32
    //   3284: irem
    //   3285: invokestatic abs : (I)I
    //   3288: invokevirtual charAt : (I)C
    //   3291: invokevirtual append : (C)Ljava/lang/StringBuilder;
    //   3294: pop
    //   3295: iload_2
    //   3296: ifeq -> 3416
    //   3299: goto -> 3306
    //   3302: invokestatic a : (Ljava/lang/Throwable;)Ljava/lang/Throwable;
    //   3305: athrow
    //   3306: aload #4
    //   3308: getstatic burp/Zrye.Za : Ljava/lang/String;
    //   3311: getstatic burp/Zv8d.ZN : Ljava/lang/Object;
    //   3314: checkcast java/math/BigInteger
    //   3317: invokevirtual intValue : ()I
    //   3320: bipush #32
    //   3322: irem
    //   3323: invokestatic abs : (I)I
    //   3326: invokevirtual charAt : (I)C
    //   3329: invokevirtual append : (C)Ljava/lang/StringBuilder;
    //   3332: pop
    //   3333: iload_2
    //   3334: ifeq -> 3416
    //   3337: goto -> 3344
    //   3340: invokestatic a : (Ljava/lang/Throwable;)Ljava/lang/Throwable;
    //   3343: athrow
    //   3344: aload #4
    //   3346: getstatic burp/Ze4w.Zc : Ljava/lang/String;
    //   3349: getstatic burp/Zk8i.ZN : Ljava/lang/Object;
    //   3352: checkcast java/math/BigInteger
    //   3355: invokevirtual intValue : ()I
    //   3358: bipush #32
    //   3360: irem
    //   3361: invokestatic abs : (I)I
    //   3364: invokevirtual charAt : (I)C
    //   3367: invokevirtual append : (C)Ljava/lang/StringBuilder;
    //   3370: pop
    //   3371: iload_2
    //   3372: ifeq -> 3416
    //   3375: goto -> 3382
    //   3378: invokestatic a : (Ljava/lang/Throwable;)Ljava/lang/Throwable;
    //   3381: athrow
    //   3382: aload #4
    //   3384: getstatic burp/Zb3d.Zr : Ljava/lang/String;
    //   3387: getstatic burp/Zz7j.ZR : Ljava/lang/Object;
    //   3390: checkcast java/math/BigInteger
    //   3393: invokevirtual intValue : ()I
    //   3396: bipush #32
    //   3398: irem
    //   3399: invokestatic abs : (I)I
    //   3402: invokevirtual charAt : (I)C
    //   3405: invokevirtual append : (C)Ljava/lang/StringBuilder;
    //   3408: pop
    //   3409: goto -> 3416
    //   3412: invokestatic a : (Ljava/lang/Throwable;)Ljava/lang/Throwable;
    //   3415: athrow
    //   3416: iinc #5, 1
    //   3419: iload_2
    //   3420: ifeq -> 2054
    //   3423: aload #4
    //   3425: invokevirtual toString : ()Ljava/lang/String;
    //   3428: putstatic burp/Zd9.Ze : Ljava/lang/String;
    //   3431: sipush #23905
    //   3434: sipush #15927
    //   3437: invokestatic a : (II)Ljava/lang/String;
    //   3440: iconst_1
    //   3441: ldc burp/Zgmo
    //   3443: invokevirtual getClassLoader : ()Ljava/lang/ClassLoader;
    //   3446: invokestatic forName : (Ljava/lang/String;ZLjava/lang/ClassLoader;)Ljava/lang/Class;
    //   3449: invokevirtual getDeclaredFields : ()[Ljava/lang/reflect/Field;
    //   3452: astore #5
    //   3454: aload #5
    //   3456: arraylength
    //   3457: istore #6
    //   3459: iconst_0
    //   3460: istore #7
    //   3462: iload #7
    //   3464: iload #6
    //   3466: if_icmpge -> 3604
    //   3469: aload #5
    //   3471: iload #7
    //   3473: aaload
    //   3474: astore #8
    //   3476: aload #8
    //   3478: invokevirtual getModifiers : ()I
    //   3481: invokestatic isStatic : (I)Z
    //   3484: ifne -> 3494
    //   3487: goto -> 3597
    //   3490: invokestatic a : (Ljava/lang/Throwable;)Ljava/lang/Throwable;
    //   3493: athrow
    //   3494: aload #8
    //   3496: invokevirtual getType : ()Ljava/lang/Class;
    //   3499: astore #9
    //   3501: aload #9
    //   3503: ifnull -> 3584
    //   3506: aload #9
    //   3508: invokevirtual isPrimitive : ()Z
    //   3511: ifne -> 3584
    //   3514: goto -> 3521
    //   3517: invokestatic a : (Ljava/lang/Throwable;)Ljava/lang/Throwable;
    //   3520: athrow
    //   3521: aload #9
    //   3523: invokevirtual getPackage : ()Ljava/lang/Package;
    //   3526: ifnull -> 3584
    //   3529: goto -> 3536
    //   3532: invokestatic a : (Ljava/lang/Throwable;)Ljava/lang/Throwable;
    //   3535: athrow
    //   3536: aload #9
    //   3538: invokevirtual getPackage : ()Ljava/lang/Package;
    //   3541: invokevirtual getName : ()Ljava/lang/String;
    //   3544: ifnull -> 3584
    //   3547: goto -> 3554
    //   3550: invokestatic a : (Ljava/lang/Throwable;)Ljava/lang/Throwable;
    //   3553: athrow
    //   3554: aload #9
    //   3556: invokevirtual getPackage : ()Ljava/lang/Package;
    //   3559: invokevirtual getName : ()Ljava/lang/String;
    //   3562: sipush #23918
    //   3565: sipush #-24387
    //   3568: invokestatic a : (II)Ljava/lang/String;
    //   3571: invokevirtual startsWith : (Ljava/lang/String;)Z
    //   3574: ifne -> 3584
    //   3577: goto -> 3584
    //   3580: invokestatic a : (Ljava/lang/Throwable;)Ljava/lang/Throwable;
    //   3583: athrow
    //   3584: aload #8
    //   3586: iconst_1
    //   3587: invokevirtual setAccessible : (Z)V
    //   3590: aload #8
    //   3592: aconst_null
    //   3593: invokevirtual get : (Ljava/lang/Object;)Ljava/lang/Object;
    //   3596: pop
    //   3597: iinc #7, 1
    //   3600: iload_2
    //   3601: ifeq -> 3462
    //   3604: sipush #23915
    //   3607: sipush #29552
    //   3610: invokestatic a : (II)Ljava/lang/String;
    //   3613: invokestatic forName : (Ljava/lang/String;)Ljava/lang/Class;
    //   3616: invokevirtual getDeclaredMethods : ()[Ljava/lang/reflect/Method;
    //   3619: astore #5
    //   3621: aload #5
    //   3623: arraylength
    //   3624: istore #6
    //   3626: iconst_0
    //   3627: istore #7
    //   3629: iload #7
    //   3631: iload #6
    //   3633: if_icmpge -> 3766
    //   3636: aload #5
    //   3638: iload #7
    //   3640: aaload
    //   3641: astore #8
    //   3643: aload #8
    //   3645: invokevirtual getParameterTypes : ()[Ljava/lang/Class;
    //   3648: pop
    //   3649: aload #8
    //   3651: invokevirtual getModifiers : ()I
    //   3654: invokestatic isStatic : (I)Z
    //   3657: ifeq -> 3752
    //   3660: aload #8
    //   3662: invokevirtual getParameterTypes : ()[Ljava/lang/Class;
    //   3665: arraylength
    //   3666: iconst_2
    //   3667: if_icmpne -> 3752
    //   3670: goto -> 3677
    //   3673: invokestatic a : (Ljava/lang/Throwable;)Ljava/lang/Throwable;
    //   3676: athrow
    //   3677: aload #8
    //   3679: invokevirtual getReturnType : ()Ljava/lang/Class;
    //   3682: getstatic java/lang/Void.TYPE : Ljava/lang/Class;
    //   3685: invokevirtual equals : (Ljava/lang/Object;)Z
    //   3688: ifeq -> 3752
    //   3691: goto -> 3698
    //   3694: invokestatic a : (Ljava/lang/Throwable;)Ljava/lang/Throwable;
    //   3697: athrow
    //   3698: aload #8
    //   3700: iconst_1
    //   3701: invokevirtual setAccessible : (Z)V
    //   3704: aload #8
    //   3706: aconst_null
    //   3707: iconst_2
    //   3708: anewarray java/lang/Object
    //   3711: dup
    //   3712: iconst_0
    //   3713: aload_0
    //   3714: aastore
    //   3715: dup
    //   3716: iconst_1
    //   3717: aload_1
    //   3718: ifnonnull -> 3736
    //   3721: goto -> 3728
    //   3724: invokestatic a : (Ljava/lang/Throwable;)Ljava/lang/Throwable;
    //   3727: athrow
    //   3728: aload_1
    //   3729: goto -> 3743
    //   3732: invokestatic a : (Ljava/lang/Throwable;)Ljava/lang/Throwable;
    //   3735: athrow
    //   3736: aload_1
    //   3737: checkcast [B
    //   3740: invokevirtual clone : ()Ljava/lang/Object;
    //   3743: aastore
    //   3744: invokevirtual invoke : (Ljava/lang/Object;[Ljava/lang/Object;)Ljava/lang/Object;
    //   3747: pop
    //   3748: iload_2
    //   3749: ifeq -> 3766
    //   3752: iinc #7, 1
    //   3755: iload_2
    //   3756: ifeq -> 3629
    //   3759: goto -> 3766
    //   3762: invokestatic a : (Ljava/lang/Throwable;)Ljava/lang/Throwable;
    //   3765: athrow
    //   3766: new java/io/ByteArrayOutputStream
    //   3769: dup
    //   3770: invokespecial <init> : ()V
    //   3773: astore #5
    //   3775: getstatic burp/Zrnt.Zy : Ljava/lang/String;
    //   3778: astore #6
    //   3780: iconst_0
    //   3781: istore #7
    //   3783: iload #7
    //   3785: aload #6
    //   3787: invokevirtual length : ()I
    //   3790: if_icmpge -> 3821
    //   3793: aload #5
    //   3795: aload #6
    //   3797: iload #7
    //   3799: iload #7
    //   3801: iconst_2
    //   3802: iadd
    //   3803: invokevirtual substring : (II)Ljava/lang/String;
    //   3806: bipush #16
    //   3808: invokestatic parseInt : (Ljava/lang/String;I)I
    //   3811: invokevirtual write : (I)V
    //   3814: iinc #7, 2
    //   3817: iload_2
    //   3818: ifeq -> 3783
    //   3821: aload #5
    //   3823: invokevirtual toByteArray : ()[B
    //   3826: astore #7
    //   3828: getstatic burp/Zsvd.Zk : Ljava/lang/Object;
    //   3831: checkcast java/math/BigInteger
    //   3834: invokevirtual toByteArray : ()[B
    //   3837: astore #8
    //   3839: sipush #256
    //   3842: newarray byte
    //   3844: astore #10
    //   3846: sipush #256
    //   3849: newarray int
    //   3851: astore #11
    //   3853: sipush #256
    //   3856: newarray int
    //   3858: astore #12
    //   3860: sipush #256
    //   3863: newarray int
    //   3865: astore #13
    //   3867: sipush #256
    //   3870: newarray int
    //   3872: astore #14
    //   3874: bipush #10
    //   3876: newarray int
    //   3878: astore #15
    //   3880: sipush #283
    //   3883: istore #16
    //   3885: iconst_0
    //   3886: istore #18
    //   3888: iload #18
    //   3890: sipush #256
    //   3893: if_icmpge -> 4127
    //   3896: sipush #23910
    //   3899: sipush #32390
    //   3902: invokestatic a : (II)Ljava/lang/String;
    //   3905: iload #18
    //   3907: iconst_1
    //   3908: iushr
    //   3909: invokevirtual charAt : (I)C
    //   3912: istore #27
    //   3914: iload #18
    //   3916: iconst_1
    //   3917: iand
    //   3918: ifne -> 3933
    //   3921: iload #27
    //   3923: bipush #8
    //   3925: iushr
    //   3926: goto -> 3935
    //   3929: invokestatic a : (Ljava/lang/Throwable;)Ljava/lang/Throwable;
    //   3932: athrow
    //   3933: iload #27
    //   3935: i2b
    //   3936: sipush #255
    //   3939: iand
    //   3940: istore #17
    //   3942: iload #18
    //   3944: iconst_1
    //   3945: ishl
    //   3946: istore #19
    //   3948: iload #19
    //   3950: sipush #256
    //   3953: if_icmplt -> 3963
    //   3956: iload #19
    //   3958: iload #16
    //   3960: ixor
    //   3961: istore #19
    //   3963: iload #19
    //   3965: iconst_1
    //   3966: ishl
    //   3967: istore #20
    //   3969: iload #20
    //   3971: sipush #256
    //   3974: if_icmplt -> 3984
    //   3977: iload #20
    //   3979: iload #16
    //   3981: ixor
    //   3982: istore #20
    //   3984: iload #20
    //   3986: iconst_1
    //   3987: ishl
    //   3988: istore #21
    //   3990: iload #21
    //   3992: sipush #256
    //   3995: if_icmplt -> 4005
    //   3998: iload #21
    //   4000: iload #16
    //   4002: ixor
    //   4003: istore #21
    //   4005: iload #21
    //   4007: iload #18
    //   4009: ixor
    //   4010: istore #22
    //   4012: iload #22
    //   4014: iload #19
    //   4016: ixor
    //   4017: istore #23
    //   4019: iload #22
    //   4021: iload #20
    //   4023: ixor
    //   4024: istore #24
    //   4026: iload #21
    //   4028: iload #20
    //   4030: ixor
    //   4031: iload #19
    //   4033: ixor
    //   4034: istore #25
    //   4036: aload #10
    //   4038: iload #18
    //   4040: iload #17
    //   4042: i2b
    //   4043: bastore
    //   4044: aload #11
    //   4046: iload #17
    //   4048: iload #25
    //   4050: bipush #24
    //   4052: ishl
    //   4053: iload #22
    //   4055: bipush #16
    //   4057: ishl
    //   4058: ior
    //   4059: iload #24
    //   4061: bipush #8
    //   4063: ishl
    //   4064: ior
    //   4065: iload #23
    //   4067: ior
    //   4068: dup
    //   4069: istore #26
    //   4071: iastore
    //   4072: aload #12
    //   4074: iload #17
    //   4076: iload #26
    //   4078: bipush #8
    //   4080: iushr
    //   4081: iload #26
    //   4083: bipush #24
    //   4085: ishl
    //   4086: ior
    //   4087: iastore
    //   4088: aload #13
    //   4090: iload #17
    //   4092: iload #26
    //   4094: bipush #16
    //   4096: iushr
    //   4097: iload #26
    //   4099: bipush #16
    //   4101: ishl
    //   4102: ior
    //   4103: iastore
    //   4104: aload #14
    //   4106: iload #17
    //   4108: iload #26
    //   4110: bipush #24
    //   4112: iushr
    //   4113: iload #26
    //   4115: bipush #8
    //   4117: ishl
    //   4118: ior
    //   4119: iastore
    //   4120: iinc #18, 1
    //   4123: iload_2
    //   4124: ifeq -> 3888
    //   4127: iconst_1
    //   4128: istore #27
    //   4130: aload #15
    //   4132: iconst_0
    //   4133: iload #27
    //   4135: bipush #24
    //   4137: ishl
    //   4138: iastore
    //   4139: iconst_1
    //   4140: istore #28
    //   4142: iload #28
    //   4144: bipush #10
    //   4146: if_icmpge -> 4187
    //   4149: iload #27
    //   4151: iconst_1
    //   4152: ishl
    //   4153: istore #27
    //   4155: iload #27
    //   4157: sipush #256
    //   4160: if_icmplt -> 4170
    //   4163: iload #27
    //   4165: iload #16
    //   4167: ixor
    //   4168: istore #27
    //   4170: aload #15
    //   4172: iload #28
    //   4174: iload #27
    //   4176: bipush #24
    //   4178: ishl
    //   4179: iastore
    //   4180: iinc #28, 1
    //   4183: iload_2
    //   4184: ifeq -> 4142
    //   4187: iconst_4
    //   4188: istore #28
    //   4190: iload #28
    //   4192: bipush #6
    //   4194: iadd
    //   4195: istore #29
    //   4197: iconst_4
    //   4198: iload #29
    //   4200: iconst_1
    //   4201: iadd
    //   4202: imul
    //   4203: istore #30
    //   4205: iload #30
    //   4207: newarray int
    //   4209: astore #31
    //   4211: iload #30
    //   4213: newarray int
    //   4215: astore #32
    //   4217: iconst_0
    //   4218: istore #27
    //   4220: iconst_0
    //   4221: istore #34
    //   4223: iconst_0
    //   4224: istore #35
    //   4226: iload #34
    //   4228: iload #28
    //   4230: if_icmpge -> 4298
    //   4233: aload #31
    //   4235: iload #34
    //   4237: aload #7
    //   4239: iload #35
    //   4241: baload
    //   4242: bipush #24
    //   4244: ishl
    //   4245: aload #7
    //   4247: iload #35
    //   4249: iconst_1
    //   4250: iadd
    //   4251: baload
    //   4252: sipush #255
    //   4255: iand
    //   4256: bipush #16
    //   4258: ishl
    //   4259: ior
    //   4260: aload #7
    //   4262: iload #35
    //   4264: iconst_2
    //   4265: iadd
    //   4266: baload
    //   4267: sipush #255
    //   4270: iand
    //   4271: bipush #8
    //   4273: ishl
    //   4274: ior
    //   4275: aload #7
    //   4277: iload #35
    //   4279: iconst_3
    //   4280: iadd
    //   4281: baload
    //   4282: sipush #255
    //   4285: iand
    //   4286: ior
    //   4287: iastore
    //   4288: iinc #34, 1
    //   4291: iinc #35, 4
    //   4294: iload_2
    //   4295: ifeq -> 4226
    //   4298: iload #28
    //   4300: istore #34
    //   4302: iconst_0
    //   4303: istore #35
    //   4305: iload #34
    //   4307: iload #30
    //   4309: if_icmpge -> 4436
    //   4312: aload #31
    //   4314: iload #34
    //   4316: iconst_1
    //   4317: isub
    //   4318: iaload
    //   4319: istore #33
    //   4321: iload #35
    //   4323: ifne -> 4410
    //   4326: iload #28
    //   4328: istore #35
    //   4330: aload #10
    //   4332: iload #33
    //   4334: bipush #16
    //   4336: iushr
    //   4337: sipush #255
    //   4340: iand
    //   4341: baload
    //   4342: bipush #24
    //   4344: ishl
    //   4345: aload #10
    //   4347: iload #33
    //   4349: bipush #8
    //   4351: iushr
    //   4352: sipush #255
    //   4355: iand
    //   4356: baload
    //   4357: sipush #255
    //   4360: iand
    //   4361: bipush #16
    //   4363: ishl
    //   4364: ior
    //   4365: aload #10
    //   4367: iload #33
    //   4369: sipush #255
    //   4372: iand
    //   4373: baload
    //   4374: sipush #255
    //   4377: iand
    //   4378: bipush #8
    //   4380: ishl
    //   4381: ior
    //   4382: aload #10
    //   4384: iload #33
    //   4386: bipush #24
    //   4388: iushr
    //   4389: baload
    //   4390: sipush #255
    //   4393: iand
    //   4394: ior
    //   4395: istore #33
    //   4397: iload #33
    //   4399: aload #15
    //   4401: iload #27
    //   4403: iinc #27, 1
    //   4406: iaload
    //   4407: ixor
    //   4408: istore #33
    //   4410: aload #31
    //   4412: iload #34
    //   4414: aload #31
    //   4416: iload #34
    //   4418: iload #28
    //   4420: isub
    //   4421: iaload
    //   4422: iload #33
    //   4424: ixor
    //   4425: iastore
    //   4426: iinc #34, 1
    //   4429: iinc #35, -1
    //   4432: iload_2
    //   4433: ifeq -> 4305
    //   4436: iconst_0
    //   4437: istore #34
    //   4439: iconst_4
    //   4440: iload #29
    //   4442: imul
    //   4443: istore #35
    //   4445: aload #32
    //   4447: iload #34
    //   4449: aload #31
    //   4451: iload #35
    //   4453: iaload
    //   4454: iastore
    //   4455: aload #32
    //   4457: iload #34
    //   4459: iconst_1
    //   4460: iadd
    //   4461: aload #31
    //   4463: iload #35
    //   4465: iconst_1
    //   4466: iadd
    //   4467: iaload
    //   4468: iastore
    //   4469: aload #32
    //   4471: iload #34
    //   4473: iconst_2
    //   4474: iadd
    //   4475: aload #31
    //   4477: iload #35
    //   4479: iconst_2
    //   4480: iadd
    //   4481: iaload
    //   4482: iastore
    //   4483: aload #32
    //   4485: iload #34
    //   4487: iconst_3
    //   4488: iadd
    //   4489: aload #31
    //   4491: iload #35
    //   4493: iconst_3
    //   4494: iadd
    //   4495: iaload
    //   4496: iastore
    //   4497: iinc #34, 4
    //   4500: iinc #35, -4
    //   4503: iconst_1
    //   4504: istore #37
    //   4506: iload #37
    //   4508: iload #29
    //   4510: if_icmpge -> 4874
    //   4513: aload #31
    //   4515: iload #35
    //   4517: iaload
    //   4518: istore #36
    //   4520: aload #32
    //   4522: iload #34
    //   4524: aload #11
    //   4526: aload #10
    //   4528: iload #36
    //   4530: bipush #24
    //   4532: iushr
    //   4533: baload
    //   4534: sipush #255
    //   4537: iand
    //   4538: iaload
    //   4539: aload #12
    //   4541: aload #10
    //   4543: iload #36
    //   4545: bipush #16
    //   4547: iushr
    //   4548: sipush #255
    //   4551: iand
    //   4552: baload
    //   4553: sipush #255
    //   4556: iand
    //   4557: iaload
    //   4558: ixor
    //   4559: aload #13
    //   4561: aload #10
    //   4563: iload #36
    //   4565: bipush #8
    //   4567: iushr
    //   4568: sipush #255
    //   4571: iand
    //   4572: baload
    //   4573: sipush #255
    //   4576: iand
    //   4577: iaload
    //   4578: ixor
    //   4579: aload #14
    //   4581: aload #10
    //   4583: iload #36
    //   4585: sipush #255
    //   4588: iand
    //   4589: baload
    //   4590: sipush #255
    //   4593: iand
    //   4594: iaload
    //   4595: ixor
    //   4596: iastore
    //   4597: aload #31
    //   4599: iload #35
    //   4601: iconst_1
    //   4602: iadd
    //   4603: iaload
    //   4604: istore #36
    //   4606: aload #32
    //   4608: iload #34
    //   4610: iconst_1
    //   4611: iadd
    //   4612: aload #11
    //   4614: aload #10
    //   4616: iload #36
    //   4618: bipush #24
    //   4620: iushr
    //   4621: baload
    //   4622: sipush #255
    //   4625: iand
    //   4626: iaload
    //   4627: aload #12
    //   4629: aload #10
    //   4631: iload #36
    //   4633: bipush #16
    //   4635: iushr
    //   4636: sipush #255
    //   4639: iand
    //   4640: baload
    //   4641: sipush #255
    //   4644: iand
    //   4645: iaload
    //   4646: ixor
    //   4647: aload #13
    //   4649: aload #10
    //   4651: iload #36
    //   4653: bipush #8
    //   4655: iushr
    //   4656: sipush #255
    //   4659: iand
    //   4660: baload
    //   4661: sipush #255
    //   4664: iand
    //   4665: iaload
    //   4666: ixor
    //   4667: aload #14
    //   4669: aload #10
    //   4671: iload #36
    //   4673: sipush #255
    //   4676: iand
    //   4677: baload
    //   4678: sipush #255
    //   4681: iand
    //   4682: iaload
    //   4683: ixor
    //   4684: iastore
    //   4685: aload #31
    //   4687: iload #35
    //   4689: iconst_2
    //   4690: iadd
    //   4691: iaload
    //   4692: istore #36
    //   4694: aload #32
    //   4696: iload #34
    //   4698: iconst_2
    //   4699: iadd
    //   4700: aload #11
    //   4702: aload #10
    //   4704: iload #36
    //   4706: bipush #24
    //   4708: iushr
    //   4709: baload
    //   4710: sipush #255
    //   4713: iand
    //   4714: iaload
    //   4715: aload #12
    //   4717: aload #10
    //   4719: iload #36
    //   4721: bipush #16
    //   4723: iushr
    //   4724: sipush #255
    //   4727: iand
    //   4728: baload
    //   4729: sipush #255
    //   4732: iand
    //   4733: iaload
    //   4734: ixor
    //   4735: aload #13
    //   4737: aload #10
    //   4739: iload #36
    //   4741: bipush #8
    //   4743: iushr
    //   4744: sipush #255
    //   4747: iand
    //   4748: baload
    //   4749: sipush #255
    //   4752: iand
    //   4753: iaload
    //   4754: ixor
    //   4755: aload #14
    //   4757: aload #10
    //   4759: iload #36
    //   4761: sipush #255
    //   4764: iand
    //   4765: baload
    //   4766: sipush #255
    //   4769: iand
    //   4770: iaload
    //   4771: ixor
    //   4772: iastore
    //   4773: aload #31
    //   4775: iload #35
    //   4777: iconst_3
    //   4778: iadd
    //   4779: iaload
    //   4780: istore #36
    //   4782: aload #32
    //   4784: iload #34
    //   4786: iconst_3
    //   4787: iadd
    //   4788: aload #11
    //   4790: aload #10
    //   4792: iload #36
    //   4794: bipush #24
    //   4796: iushr
    //   4797: baload
    //   4798: sipush #255
    //   4801: iand
    //   4802: iaload
    //   4803: aload #12
    //   4805: aload #10
    //   4807: iload #36
    //   4809: bipush #16
    //   4811: iushr
    //   4812: sipush #255
    //   4815: iand
    //   4816: baload
    //   4817: sipush #255
    //   4820: iand
    //   4821: iaload
    //   4822: ixor
    //   4823: aload #13
    //   4825: aload #10
    //   4827: iload #36
    //   4829: bipush #8
    //   4831: iushr
    //   4832: sipush #255
    //   4835: iand
    //   4836: baload
    //   4837: sipush #255
    //   4840: iand
    //   4841: iaload
    //   4842: ixor
    //   4843: aload #14
    //   4845: aload #10
    //   4847: iload #36
    //   4849: sipush #255
    //   4852: iand
    //   4853: baload
    //   4854: sipush #255
    //   4857: iand
    //   4858: iaload
    //   4859: ixor
    //   4860: iastore
    //   4861: iinc #34, 4
    //   4864: iinc #35, -4
    //   4867: iinc #37, 1
    //   4870: iload_2
    //   4871: ifeq -> 4506
    //   4874: aload #32
    //   4876: iload #34
    //   4878: aload #31
    //   4880: iload #35
    //   4882: iaload
    //   4883: iastore
    //   4884: aload #32
    //   4886: iload #34
    //   4888: iconst_1
    //   4889: iadd
    //   4890: aload #31
    //   4892: iload #35
    //   4894: iconst_1
    //   4895: iadd
    //   4896: iaload
    //   4897: iastore
    //   4898: aload #32
    //   4900: iload #34
    //   4902: iconst_2
    //   4903: iadd
    //   4904: aload #31
    //   4906: iload #35
    //   4908: iconst_2
    //   4909: iadd
    //   4910: iaload
    //   4911: iastore
    //   4912: aload #32
    //   4914: iload #34
    //   4916: iconst_3
    //   4917: iadd
    //   4918: aload #31
    //   4920: iload #35
    //   4922: iconst_3
    //   4923: iadd
    //   4924: iaload
    //   4925: iastore
    //   4926: iconst_0
    //   4927: newarray byte
    //   4929: astore #37
    //   4931: aload #8
    //   4933: arraylength
    //   4934: bipush #16
    //   4936: irem
    //   4937: ifeq -> 4961
    //   4940: new java/lang/Exception
    //   4943: dup
    //   4944: sipush #23907
    //   4947: sipush #-2740
    //   4950: invokestatic a : (II)Ljava/lang/String;
    //   4953: invokespecial <init> : (Ljava/lang/String;)V
    //   4956: athrow
    //   4957: invokestatic a : (Ljava/lang/Throwable;)Ljava/lang/Throwable;
    //   4960: athrow
    //   4961: bipush #10
    //   4963: istore #38
    //   4965: sipush #23911
    //   4968: sipush #256
    //   4971: newarray byte
    //   4973: astore #39
    //   4975: sipush #-20104
    //   4978: sipush #256
    //   4981: newarray int
    //   4983: astore #40
    //   4985: sipush #256
    //   4988: newarray int
    //   4990: astore #41
    //   4992: sipush #256
    //   4995: newarray int
    //   4997: astore #42
    //   4999: sipush #256
    //   5002: newarray int
    //   5004: astore #43
    //   5006: sipush #283
    //   5009: istore #16
    //   5011: invokestatic a : (II)Ljava/lang/String;
    //   5014: astore #44
    //   5016: iconst_0
    //   5017: istore #18
    //   5019: iload #18
    //   5021: sipush #256
    //   5024: if_icmpge -> 5251
    //   5027: aload #44
    //   5029: iload #18
    //   5031: iconst_1
    //   5032: iushr
    //   5033: invokevirtual charAt : (I)C
    //   5036: istore #45
    //   5038: iload #18
    //   5040: iconst_1
    //   5041: iand
    //   5042: ifne -> 5057
    //   5045: iload #45
    //   5047: bipush #8
    //   5049: iushr
    //   5050: goto -> 5059
    //   5053: invokestatic a : (Ljava/lang/Throwable;)Ljava/lang/Throwable;
    //   5056: athrow
    //   5057: iload #45
    //   5059: i2b
    //   5060: sipush #255
    //   5063: iand
    //   5064: istore #17
    //   5066: iload #18
    //   5068: iconst_1
    //   5069: ishl
    //   5070: istore #19
    //   5072: iload #19
    //   5074: sipush #256
    //   5077: if_icmplt -> 5087
    //   5080: iload #19
    //   5082: iload #16
    //   5084: ixor
    //   5085: istore #19
    //   5087: iload #19
    //   5089: iconst_1
    //   5090: ishl
    //   5091: istore #20
    //   5093: iload #20
    //   5095: sipush #256
    //   5098: if_icmplt -> 5108
    //   5101: iload #20
    //   5103: iload #16
    //   5105: ixor
    //   5106: istore #20
    //   5108: iload #20
    //   5110: iconst_1
    //   5111: ishl
    //   5112: istore #21
    //   5114: iload #21
    //   5116: sipush #256
    //   5119: if_icmplt -> 5129
    //   5122: iload #21
    //   5124: iload #16
    //   5126: ixor
    //   5127: istore #21
    //   5129: iload #21
    //   5131: iload #18
    //   5133: ixor
    //   5134: istore #22
    //   5136: iload #22
    //   5138: iload #19
    //   5140: ixor
    //   5141: istore #23
    //   5143: iload #22
    //   5145: iload #20
    //   5147: ixor
    //   5148: istore #24
    //   5150: iload #21
    //   5152: iload #20
    //   5154: ixor
    //   5155: iload #19
    //   5157: ixor
    //   5158: istore #25
    //   5160: aload #39
    //   5162: iload #17
    //   5164: iload #18
    //   5166: i2b
    //   5167: bastore
    //   5168: aload #40
    //   5170: iload #17
    //   5172: iload #25
    //   5174: bipush #24
    //   5176: ishl
    //   5177: iload #22
    //   5179: bipush #16
    //   5181: ishl
    //   5182: ior
    //   5183: iload #24
    //   5185: bipush #8
    //   5187: ishl
    //   5188: ior
    //   5189: iload #23
    //   5191: ior
    //   5192: dup
    //   5193: istore #26
    //   5195: iastore
    //   5196: aload #41
    //   5198: iload #17
    //   5200: iload #26
    //   5202: bipush #8
    //   5204: iushr
    //   5205: iload #26
    //   5207: bipush #24
    //   5209: ishl
    //   5210: ior
    //   5211: iastore
    //   5212: aload #42
    //   5214: iload #17
    //   5216: iload #26
    //   5218: bipush #16
    //   5220: iushr
    //   5221: iload #26
    //   5223: bipush #16
    //   5225: ishl
    //   5226: ior
    //   5227: iastore
    //   5228: aload #43
    //   5230: iload #17
    //   5232: iload #26
    //   5234: bipush #24
    //   5236: iushr
    //   5237: iload #26
    //   5239: bipush #8
    //   5241: ishl
    //   5242: ior
    //   5243: iastore
    //   5244: iinc #18, 1
    //   5247: iload_2
    //   5248: ifeq -> 5019
    //   5251: aload #8
    //   5253: arraylength
    //   5254: newarray byte
    //   5256: astore #45
    //   5258: iconst_0
    //   5259: istore #46
    //   5261: iload #46
    //   5263: aload #8
    //   5265: arraylength
    //   5266: bipush #16
    //   5268: idiv
    //   5269: if_icmpge -> 6183
    //   5272: bipush #16
    //   5274: newarray byte
    //   5276: astore #47
    //   5278: bipush #16
    //   5280: newarray byte
    //   5282: astore #48
    //   5284: iconst_0
    //   5285: istore #49
    //   5287: iload #49
    //   5289: bipush #16
    //   5291: if_icmpge -> 5317
    //   5294: aload #47
    //   5296: iload #49
    //   5298: aload #8
    //   5300: iload #49
    //   5302: iload #46
    //   5304: bipush #16
    //   5306: imul
    //   5307: iadd
    //   5308: baload
    //   5309: bastore
    //   5310: iinc #49, 1
    //   5313: iload_2
    //   5314: ifeq -> 5287
    //   5317: iconst_0
    //   5318: istore #49
    //   5320: aload #47
    //   5322: iconst_0
    //   5323: baload
    //   5324: bipush #24
    //   5326: ishl
    //   5327: aload #47
    //   5329: iconst_1
    //   5330: baload
    //   5331: sipush #255
    //   5334: iand
    //   5335: bipush #16
    //   5337: ishl
    //   5338: ior
    //   5339: aload #47
    //   5341: iconst_2
    //   5342: baload
    //   5343: sipush #255
    //   5346: iand
    //   5347: bipush #8
    //   5349: ishl
    //   5350: ior
    //   5351: aload #47
    //   5353: iconst_3
    //   5354: baload
    //   5355: sipush #255
    //   5358: iand
    //   5359: ior
    //   5360: aload #32
    //   5362: iconst_0
    //   5363: iaload
    //   5364: ixor
    //   5365: istore #51
    //   5367: aload #47
    //   5369: iconst_4
    //   5370: baload
    //   5371: bipush #24
    //   5373: ishl
    //   5374: aload #47
    //   5376: iconst_5
    //   5377: baload
    //   5378: sipush #255
    //   5381: iand
    //   5382: bipush #16
    //   5384: ishl
    //   5385: ior
    //   5386: aload #47
    //   5388: bipush #6
    //   5390: baload
    //   5391: sipush #255
    //   5394: iand
    //   5395: bipush #8
    //   5397: ishl
    //   5398: ior
    //   5399: aload #47
    //   5401: bipush #7
    //   5403: baload
    //   5404: sipush #255
    //   5407: iand
    //   5408: ior
    //   5409: aload #32
    //   5411: iconst_1
    //   5412: iaload
    //   5413: ixor
    //   5414: istore #52
    //   5416: aload #47
    //   5418: bipush #8
    //   5420: baload
    //   5421: bipush #24
    //   5423: ishl
    //   5424: aload #47
    //   5426: bipush #9
    //   5428: baload
    //   5429: sipush #255
    //   5432: iand
    //   5433: bipush #16
    //   5435: ishl
    //   5436: ior
    //   5437: aload #47
    //   5439: bipush #10
    //   5441: baload
    //   5442: sipush #255
    //   5445: iand
    //   5446: bipush #8
    //   5448: ishl
    //   5449: ior
    //   5450: aload #47
    //   5452: bipush #11
    //   5454: baload
    //   5455: sipush #255
    //   5458: iand
    //   5459: ior
    //   5460: aload #32
    //   5462: iconst_2
    //   5463: iaload
    //   5464: ixor
    //   5465: istore #53
    //   5467: aload #47
    //   5469: bipush #12
    //   5471: baload
    //   5472: bipush #24
    //   5474: ishl
    //   5475: aload #47
    //   5477: bipush #13
    //   5479: baload
    //   5480: sipush #255
    //   5483: iand
    //   5484: bipush #16
    //   5486: ishl
    //   5487: ior
    //   5488: aload #47
    //   5490: bipush #14
    //   5492: baload
    //   5493: sipush #255
    //   5496: iand
    //   5497: bipush #8
    //   5499: ishl
    //   5500: ior
    //   5501: aload #47
    //   5503: bipush #15
    //   5505: baload
    //   5506: sipush #255
    //   5509: iand
    //   5510: ior
    //   5511: aload #32
    //   5513: iconst_3
    //   5514: iaload
    //   5515: ixor
    //   5516: istore #54
    //   5518: iconst_1
    //   5519: istore #55
    //   5521: iload #55
    //   5523: iload #38
    //   5525: if_icmpge -> 5768
    //   5528: iinc #49, 4
    //   5531: aload #40
    //   5533: iload #51
    //   5535: bipush #24
    //   5537: iushr
    //   5538: iaload
    //   5539: aload #41
    //   5541: iload #54
    //   5543: bipush #16
    //   5545: iushr
    //   5546: sipush #255
    //   5549: iand
    //   5550: iaload
    //   5551: ixor
    //   5552: aload #42
    //   5554: iload #53
    //   5556: bipush #8
    //   5558: iushr
    //   5559: sipush #255
    //   5562: iand
    //   5563: iaload
    //   5564: ixor
    //   5565: aload #43
    //   5567: iload #52
    //   5569: sipush #255
    //   5572: iand
    //   5573: iaload
    //   5574: ixor
    //   5575: aload #32
    //   5577: iload #49
    //   5579: iaload
    //   5580: ixor
    //   5581: istore #56
    //   5583: aload #40
    //   5585: iload #52
    //   5587: bipush #24
    //   5589: iushr
    //   5590: iaload
    //   5591: aload #41
    //   5593: iload #51
    //   5595: bipush #16
    //   5597: iushr
    //   5598: sipush #255
    //   5601: iand
    //   5602: iaload
    //   5603: ixor
    //   5604: aload #42
    //   5606: iload #54
    //   5608: bipush #8
    //   5610: iushr
    //   5611: sipush #255
    //   5614: iand
    //   5615: iaload
    //   5616: ixor
    //   5617: aload #43
    //   5619: iload #53
    //   5621: sipush #255
    //   5624: iand
    //   5625: iaload
    //   5626: ixor
    //   5627: aload #32
    //   5629: iload #49
    //   5631: iconst_1
    //   5632: iadd
    //   5633: iaload
    //   5634: ixor
    //   5635: istore #57
    //   5637: aload #40
    //   5639: iload #53
    //   5641: bipush #24
    //   5643: iushr
    //   5644: iaload
    //   5645: aload #41
    //   5647: iload #52
    //   5649: bipush #16
    //   5651: iushr
    //   5652: sipush #255
    //   5655: iand
    //   5656: iaload
    //   5657: ixor
    //   5658: aload #42
    //   5660: iload #51
    //   5662: bipush #8
    //   5664: iushr
    //   5665: sipush #255
    //   5668: iand
    //   5669: iaload
    //   5670: ixor
    //   5671: aload #43
    //   5673: iload #54
    //   5675: sipush #255
    //   5678: iand
    //   5679: iaload
    //   5680: ixor
    //   5681: aload #32
    //   5683: iload #49
    //   5685: iconst_2
    //   5686: iadd
    //   5687: iaload
    //   5688: ixor
    //   5689: istore #58
    //   5691: aload #40
    //   5693: iload #54
    //   5695: bipush #24
    //   5697: iushr
    //   5698: iaload
    //   5699: aload #41
    //   5701: iload #53
    //   5703: bipush #16
    //   5705: iushr
    //   5706: sipush #255
    //   5709: iand
    //   5710: iaload
    //   5711: ixor
    //   5712: aload #42
    //   5714: iload #52
    //   5716: bipush #8
    //   5718: iushr
    //   5719: sipush #255
    //   5722: iand
    //   5723: iaload
    //   5724: ixor
    //   5725: aload #43
    //   5727: iload #51
    //   5729: sipush #255
    //   5732: iand
    //   5733: iaload
    //   5734: ixor
    //   5735: aload #32
    //   5737: iload #49
    //   5739: iconst_3
    //   5740: iadd
    //   5741: iaload
    //   5742: ixor
    //   5743: istore #59
    //   5745: iload #56
    //   5747: istore #51
    //   5749: iload #57
    //   5751: istore #52
    //   5753: iload #58
    //   5755: istore #53
    //   5757: iload #59
    //   5759: istore #54
    //   5761: iinc #55, 1
    //   5764: iload_2
    //   5765: ifeq -> 5521
    //   5768: iinc #49, 4
    //   5771: aload #32
    //   5773: iload #49
    //   5775: iaload
    //   5776: istore #50
    //   5778: aload #48
    //   5780: iconst_0
    //   5781: aload #39
    //   5783: iload #51
    //   5785: bipush #24
    //   5787: iushr
    //   5788: baload
    //   5789: iload #50
    //   5791: bipush #24
    //   5793: iushr
    //   5794: ixor
    //   5795: i2b
    //   5796: bastore
    //   5797: aload #48
    //   5799: iconst_1
    //   5800: aload #39
    //   5802: iload #54
    //   5804: bipush #16
    //   5806: iushr
    //   5807: sipush #255
    //   5810: iand
    //   5811: baload
    //   5812: iload #50
    //   5814: bipush #16
    //   5816: iushr
    //   5817: ixor
    //   5818: i2b
    //   5819: bastore
    //   5820: aload #48
    //   5822: iconst_2
    //   5823: aload #39
    //   5825: iload #53
    //   5827: bipush #8
    //   5829: iushr
    //   5830: sipush #255
    //   5833: iand
    //   5834: baload
    //   5835: iload #50
    //   5837: bipush #8
    //   5839: iushr
    //   5840: ixor
    //   5841: i2b
    //   5842: bastore
    //   5843: aload #48
    //   5845: iconst_3
    //   5846: aload #39
    //   5848: iload #52
    //   5850: sipush #255
    //   5853: iand
    //   5854: baload
    //   5855: iload #50
    //   5857: ixor
    //   5858: i2b
    //   5859: bastore
    //   5860: aload #32
    //   5862: iload #49
    //   5864: iconst_1
    //   5865: iadd
    //   5866: iaload
    //   5867: istore #50
    //   5869: aload #48
    //   5871: iconst_4
    //   5872: aload #39
    //   5874: iload #52
    //   5876: bipush #24
    //   5878: iushr
    //   5879: baload
    //   5880: iload #50
    //   5882: bipush #24
    //   5884: iushr
    //   5885: ixor
    //   5886: i2b
    //   5887: bastore
    //   5888: aload #48
    //   5890: iconst_5
    //   5891: aload #39
    //   5893: iload #51
    //   5895: bipush #16
    //   5897: iushr
    //   5898: sipush #255
    //   5901: iand
    //   5902: baload
    //   5903: iload #50
    //   5905: bipush #16
    //   5907: iushr
    //   5908: ixor
    //   5909: i2b
    //   5910: bastore
    //   5911: aload #48
    //   5913: bipush #6
    //   5915: aload #39
    //   5917: iload #54
    //   5919: bipush #8
    //   5921: iushr
    //   5922: sipush #255
    //   5925: iand
    //   5926: baload
    //   5927: iload #50
    //   5929: bipush #8
    //   5931: iushr
    //   5932: ixor
    //   5933: i2b
    //   5934: bastore
    //   5935: aload #48
    //   5937: bipush #7
    //   5939: aload #39
    //   5941: iload #53
    //   5943: sipush #255
    //   5946: iand
    //   5947: baload
    //   5948: iload #50
    //   5950: ixor
    //   5951: i2b
    //   5952: bastore
    //   5953: aload #32
    //   5955: iload #49
    //   5957: iconst_2
    //   5958: iadd
    //   5959: iaload
    //   5960: istore #50
    //   5962: aload #48
    //   5964: bipush #8
    //   5966: aload #39
    //   5968: iload #53
    //   5970: bipush #24
    //   5972: iushr
    //   5973: baload
    //   5974: iload #50
    //   5976: bipush #24
    //   5978: iushr
    //   5979: ixor
    //   5980: i2b
    //   5981: bastore
    //   5982: aload #48
    //   5984: bipush #9
    //   5986: aload #39
    //   5988: iload #52
    //   5990: bipush #16
    //   5992: iushr
    //   5993: sipush #255
    //   5996: iand
    //   5997: baload
    //   5998: iload #50
    //   6000: bipush #16
    //   6002: iushr
    //   6003: ixor
    //   6004: i2b
    //   6005: bastore
    //   6006: aload #48
    //   6008: bipush #10
    //   6010: aload #39
    //   6012: iload #51
    //   6014: bipush #8
    //   6016: iushr
    //   6017: sipush #255
    //   6020: iand
    //   6021: baload
    //   6022: iload #50
    //   6024: bipush #8
    //   6026: iushr
    //   6027: ixor
    //   6028: i2b
    //   6029: bastore
    //   6030: aload #48
    //   6032: bipush #11
    //   6034: aload #39
    //   6036: iload #54
    //   6038: sipush #255
    //   6041: iand
    //   6042: baload
    //   6043: iload #50
    //   6045: ixor
    //   6046: i2b
    //   6047: bastore
    //   6048: aload #32
    //   6050: iload #49
    //   6052: iconst_3
    //   6053: iadd
    //   6054: iaload
    //   6055: istore #50
    //   6057: aload #48
    //   6059: bipush #12
    //   6061: aload #39
    //   6063: iload #54
    //   6065: bipush #24
    //   6067: iushr
    //   6068: baload
    //   6069: iload #50
    //   6071: bipush #24
    //   6073: iushr
    //   6074: ixor
    //   6075: i2b
    //   6076: bastore
    //   6077: aload #48
    //   6079: bipush #13
    //   6081: aload #39
    //   6083: iload #53
    //   6085: bipush #16
    //   6087: iushr
    //   6088: sipush #255
    //   6091: iand
    //   6092: baload
    //   6093: iload #50
    //   6095: bipush #16
    //   6097: iushr
    //   6098: ixor
    //   6099: i2b
    //   6100: bastore
    //   6101: aload #48
    //   6103: bipush #14
    //   6105: aload #39
    //   6107: iload #52
    //   6109: bipush #8
    //   6111: iushr
    //   6112: sipush #255
    //   6115: iand
    //   6116: baload
    //   6117: iload #50
    //   6119: bipush #8
    //   6121: iushr
    //   6122: ixor
    //   6123: i2b
    //   6124: bastore
    //   6125: aload #48
    //   6127: bipush #15
    //   6129: aload #39
    //   6131: iload #51
    //   6133: sipush #255
    //   6136: iand
    //   6137: baload
    //   6138: iload #50
    //   6140: ixor
    //   6141: i2b
    //   6142: bastore
    //   6143: iconst_0
    //   6144: istore #55
    //   6146: iload #55
    //   6148: bipush #16
    //   6150: if_icmpge -> 6176
    //   6153: aload #45
    //   6155: iload #55
    //   6157: iload #46
    //   6159: bipush #16
    //   6161: imul
    //   6162: iadd
    //   6163: aload #48
    //   6165: iload #55
    //   6167: baload
    //   6168: bastore
    //   6169: iinc #55, 1
    //   6172: iload_2
    //   6173: ifeq -> 6146
    //   6176: iinc #46, 1
    //   6179: iload_2
    //   6180: ifeq -> 5261
    //   6183: aload #45
    //   6185: arraylength
    //   6186: ifle -> 6267
    //   6189: aload #45
    //   6191: aload #45
    //   6193: arraylength
    //   6194: iconst_1
    //   6195: isub
    //   6196: baload
    //   6197: istore #46
    //   6199: iload #46
    //   6201: bipush #16
    //   6203: if_icmple -> 6214
    //   6206: aload #45
    //   6208: astore #37
    //   6210: iload_2
    //   6211: ifeq -> 6267
    //   6214: aload #45
    //   6216: arraylength
    //   6217: iload #46
    //   6219: isub
    //   6220: newarray byte
    //   6222: astore #37
    //   6224: iconst_0
    //   6225: istore #47
    //   6227: iload #47
    //   6229: aload #37
    //   6231: arraylength
    //   6232: if_icmpge -> 6267
    //   6235: iload #47
    //   6237: aload #45
    //   6239: arraylength
    //   6240: if_icmpge -> 6267
    //   6243: aload #37
    //   6245: iload #47
    //   6247: aload #45
    //   6249: iload #47
    //   6251: baload
    //   6252: bastore
    //   6253: iinc #47, 1
    //   6256: iload_2
    //   6257: ifeq -> 6227
    //   6260: goto -> 6267
    //   6263: invokestatic a : (Ljava/lang/Throwable;)Ljava/lang/Throwable;
    //   6266: athrow
    //   6267: aload #37
    //   6269: astore #9
    //   6271: getstatic burp/Ztvy.Zk : Ljava/lang/String;
    //   6274: getstatic burp/Zbun.ZH : Ljava/lang/Object;
    //   6277: checkcast java/math/BigInteger
    //   6280: invokevirtual intValue : ()I
    //   6283: bipush #32
    //   6285: irem
    //   6286: invokestatic abs : (I)I
    //   6289: invokevirtual charAt : (I)C
    //   6292: getstatic burp/Zlxw.ZC : Ljava/lang/String;
    //   6295: getstatic burp/Zlwm.Ze : Ljava/lang/Object;
    //   6298: checkcast java/math/BigInteger
    //   6301: invokevirtual intValue : ()I
    //   6304: bipush #32
    //   6306: irem
    //   6307: invokestatic abs : (I)I
    //   6310: invokevirtual charAt : (I)C
    //   6313: if_icmple -> 6428
    //   6316: getstatic burp/Zgi9.Zv : Ljava/lang/String;
    //   6319: getstatic burp/Zzmc.Zg : Ljava/lang/Object;
    //   6322: checkcast java/math/BigInteger
    //   6325: invokevirtual intValue : ()I
    //   6328: bipush #32
    //   6330: irem
    //   6331: invokestatic abs : (I)I
    //   6334: invokevirtual charAt : (I)C
    //   6337: getstatic burp/Zmlr.ZJ : Ljava/lang/String;
    //   6340: getstatic burp/Zr6c.ZG : Ljava/lang/Object;
    //   6343: checkcast java/math/BigInteger
    //   6346: invokevirtual intValue : ()I
    //   6349: bipush #32
    //   6351: irem
    //   6352: invokestatic abs : (I)I
    //   6355: invokevirtual charAt : (I)C
    //   6358: if_icmple -> 6428
    //   6361: goto -> 6368
    //   6364: invokestatic a : (Ljava/lang/Throwable;)Ljava/lang/Throwable;
    //   6367: athrow
    //   6368: getstatic burp/Zbx5.Zz : Ljava/lang/String;
    //   6371: getstatic burp/Zmdf.ZH : Ljava/lang/Object;
    //   6374: checkcast java/math/BigInteger
    //   6377: invokevirtual intValue : ()I
    //   6380: bipush #32
    //   6382: irem
    //   6383: invokestatic abs : (I)I
    //   6386: invokevirtual charAt : (I)C
    //   6389: getstatic burp/Zmig.ZR : Ljava/lang/String;
    //   6392: getstatic burp/Zge2.Zv : Ljava/lang/Object;
    //   6395: checkcast java/math/BigInteger
    //   6398: invokevirtual intValue : ()I
    //   6401: bipush #32
    //   6403: irem
    //   6404: invokestatic abs : (I)I
    //   6407: invokevirtual charAt : (I)C
    //   6410: if_icmpgt -> 6428
    //   6413: goto -> 6420
    //   6416: invokestatic a : (Ljava/lang/Throwable;)Ljava/lang/Throwable;
    //   6419: athrow
    //   6420: iconst_1
    //   6421: goto -> 6429
    //   6424: invokestatic a : (Ljava/lang/Throwable;)Ljava/lang/Throwable;
    //   6427: athrow
    //   6428: iconst_0
    //   6429: ireturn
    //   6430: astore_3
    //   6431: new java/lang/Exception
    //   6434: dup
    //   6435: aload_3
    //   6436: invokevirtual getMessage : ()Ljava/lang/String;
    //   6439: invokespecial <init> : (Ljava/lang/String;)V
    //   6442: athrow
    // Exception table:
    //   from	to	target	type
    //   4	6429	6430	java/lang/Throwable
    //   309	333	336	java/lang/Throwable
    //   407	444	444	java/lang/Throwable
    //   448	469	469	java/lang/Throwable
    //   473	503	503	java/lang/Throwable
    //   704	878	881	java/lang/Throwable
    //   848	915	918	java/lang/Throwable
    //   885	952	955	java/lang/Throwable
    //   922	989	992	java/lang/Throwable
    //   959	1026	1029	java/lang/Throwable
    //   996	1063	1066	java/lang/Throwable
    //   1033	1100	1103	java/lang/Throwable
    //   1070	1137	1140	java/lang/Throwable
    //   1107	1174	1177	java/lang/Throwable
    //   1144	1211	1214	java/lang/Throwable
    //   1181	1248	1251	java/lang/Throwable
    //   1218	1285	1288	java/lang/Throwable
    //   1255	1322	1325	java/lang/Throwable
    //   1292	1359	1362	java/lang/Throwable
    //   1329	1396	1399	java/lang/Throwable
    //   1366	1433	1436	java/lang/Throwable
    //   1403	1470	1473	java/lang/Throwable
    //   1440	1507	1510	java/lang/Throwable
    //   1477	1544	1547	java/lang/Throwable
    //   1514	1581	1584	java/lang/Throwable
    //   1551	1618	1621	java/lang/Throwable
    //   1588	1655	1658	java/lang/Throwable
    //   1625	1692	1695	java/lang/Throwable
    //   1662	1729	1732	java/lang/Throwable
    //   1699	1766	1769	java/lang/Throwable
    //   1736	1803	1806	java/lang/Throwable
    //   1773	1840	1843	java/lang/Throwable
    //   1810	1877	1880	java/lang/Throwable
    //   1847	1914	1917	java/lang/Throwable
    //   1884	1951	1954	java/lang/Throwable
    //   1921	1988	1991	java/lang/Throwable
    //   1958	2021	2024	java/lang/Throwable
    //   2061	2235	2238	java/lang/Throwable
    //   2204	2273	2276	java/lang/Throwable
    //   2242	2311	2314	java/lang/Throwable
    //   2280	2349	2352	java/lang/Throwable
    //   2318	2387	2390	java/lang/Throwable
    //   2356	2425	2428	java/lang/Throwable
    //   2394	2463	2466	java/lang/Throwable
    //   2432	2501	2504	java/lang/Throwable
    //   2470	2539	2542	java/lang/Throwable
    //   2508	2577	2580	java/lang/Throwable
    //   2546	2615	2618	java/lang/Throwable
    //   2584	2653	2656	java/lang/Throwable
    //   2622	2691	2694	java/lang/Throwable
    //   2660	2729	2732	java/lang/Throwable
    //   2698	2767	2770	java/lang/Throwable
    //   2736	2805	2808	java/lang/Throwable
    //   2774	2843	2846	java/lang/Throwable
    //   2812	2881	2884	java/lang/Throwable
    //   2850	2919	2922	java/lang/Throwable
    //   2888	2957	2960	java/lang/Throwable
    //   2926	2995	2998	java/lang/Throwable
    //   2964	3033	3036	java/lang/Throwable
    //   3002	3071	3074	java/lang/Throwable
    //   3040	3109	3112	java/lang/Throwable
    //   3078	3147	3150	java/lang/Throwable
    //   3116	3185	3188	java/lang/Throwable
    //   3154	3223	3226	java/lang/Throwable
    //   3192	3261	3264	java/lang/Throwable
    //   3230	3299	3302	java/lang/Throwable
    //   3268	3337	3340	java/lang/Throwable
    //   3306	3375	3378	java/lang/Throwable
    //   3344	3409	3412	java/lang/Throwable
    //   3476	3490	3490	java/lang/Throwable
    //   3501	3514	3517	java/lang/Throwable
    //   3506	3529	3532	java/lang/Throwable
    //   3521	3547	3550	java/lang/Throwable
    //   3536	3577	3580	java/lang/Throwable
    //   3643	3670	3673	java/lang/Throwable
    //   3660	3691	3694	java/lang/Throwable
    //   3677	3721	3724	java/lang/Throwable
    //   3698	3732	3732	java/lang/Throwable
    //   3743	3759	3762	java/lang/Throwable
    //   3914	3929	3929	java/lang/Throwable
    //   4931	4957	4957	java/lang/Throwable
    //   5038	5053	5053	java/lang/Throwable
    //   6235	6260	6263	java/lang/Throwable
    //   6271	6361	6364	java/lang/Throwable
    //   6316	6413	6416	java/lang/Throwable
    //   6368	6424	6424	java/lang/Throwable
  }
  
  static {
    // Byte code:
    //   0: bipush #14
    //   2: anewarray java/lang/String
    //   5: astore #5
    //   7: iconst_0
    //   8: istore_3
    //   9: ldc '???? -PgV5Z&#\\n\vikp6<\\tE $^\\t~lwW dsi*[7-,a1\\tTeul6dE3 gCrHK9Lq9fZ EeSg=%\\b)dz1zH\\tbN#63\\n'
    //   11: dup
    //   12: astore_2
    //   13: invokevirtual length : ()I
    //   16: istore #4
    //   18: sipush #128
    //   21: istore_1
    //   22: iconst_m1
    //   23: istore_0
    //   24: bipush #75
    //   26: iinc #0, 1
    //   29: aload_2
    //   30: iload_0
    //   31: dup
    //   32: iload_1
    //   33: iadd
    //   34: invokevirtual substring : (II)Ljava/lang/String;
    //   37: iconst_m1
    //   38: goto -> 144
    //   41: aload #5
    //   43: swap
    //   44: iload_3
    //   45: iinc #3, 1
    //   48: swap
    //   49: aastore
    //   50: iload_0
    //   51: iload_1
    //   52: iadd
    //   53: dup
    //   54: istore_0
    //   55: iload #4
    //   57: if_icmpge -> 69
    //   60: aload_2
    //   61: iload_0
    //   62: invokevirtual charAt : (I)C
    //   65: istore_1
    //   66: goto -> 24
    //   69: ldc 'Z,&J.3k~)}+wC--\\n4SGa\\nU;S\\fk@7g%c I\\tUOO?'
    //   71: dup
    //   72: astore_2
    //   73: invokevirtual length : ()I
    //   76: istore #4
    //   78: bipush #77
    //   80: istore_1
    //   81: iconst_m1
    //   82: istore_0
    //   83: bipush #76
    //   85: iinc #0, 1
    //   88: aload_2
    //   89: iload_0
    //   90: dup
    //   91: iload_1
    //   92: iadd
    //   93: invokevirtual substring : (II)Ljava/lang/String;
    //   96: iconst_0
    //   97: goto -> 144
    //   100: aload #5
    //   102: swap
    //   103: iload_3
    //   104: iinc #3, 1
    //   107: swap
    //   108: aastore
    //   109: iload_0
    //   110: iload_1
    //   111: iadd
    //   112: dup
    //   113: istore_0
    //   114: iload #4
    //   116: if_icmpge -> 128
    //   119: aload_2
    //   120: iload_0
    //   121: invokevirtual charAt : (I)C
    //   124: istore_1
    //   125: goto -> 83
    //   128: aload #5
    //   130: putstatic burp/Zm8j.a : [Ljava/lang/String;
    //   133: bipush #14
    //   135: anewarray java/lang/String
    //   138: putstatic burp/Zm8j.b : [Ljava/lang/String;
    //   141: goto -> 300
    //   144: dup_x2
    //   145: pop
    //   146: invokevirtual toCharArray : ()[C
    //   149: dup_x1
    //   150: arraylength
    //   151: dup_x2
    //   152: pop
    //   153: iconst_0
    //   154: istore #6
    //   156: dup2_x1
    //   157: pop2
    //   158: dup_x2
    //   159: iconst_1
    //   160: if_icmpgt -> 260
    //   163: dup2
    //   164: swap
    //   165: iload #6
    //   167: dup2_x1
    //   168: caload
    //   169: swap
    //   170: iload #6
    //   172: bipush #7
    //   174: irem
    //   175: tableswitch default -> 242, 0 -> 212, 1 -> 217, 2 -> 222, 3 -> 227, 4 -> 232, 5 -> 237
    //   212: bipush #10
    //   214: goto -> 244
    //   217: bipush #81
    //   219: goto -> 244
    //   222: bipush #61
    //   224: goto -> 244
    //   227: bipush #56
    //   229: goto -> 244
    //   232: bipush #104
    //   234: goto -> 244
    //   237: bipush #86
    //   239: goto -> 244
    //   242: bipush #106
    //   244: ixor
    //   245: ixor
    //   246: i2c
    //   247: castore
    //   248: iinc #6, 1
    //   251: dup
    //   252: ifne -> 260
    //   255: dup2
    //   256: dup_x1
    //   257: goto -> 167
    //   260: dup2_x1
    //   261: pop2
    //   262: dup_x2
    //   263: iload #6
    //   265: if_icmpgt -> 163
    //   268: pop
    //   269: new java/lang/String
    //   272: dup_x1
    //   273: swap
    //   274: invokespecial <init> : ([C)V
    //   277: invokevirtual intern : ()Ljava/lang/String;
    //   280: swap
    //   281: pop
    //   282: swap
    //   283: tableswitch default -> 41, 0 -> 100
    //   300: new java/math/BigInteger
    //   303: dup
    //   304: iconst_1
    //   305: bipush #32
    //   307: newarray byte
    //   309: dup
    //   310: iconst_0
    //   311: bipush #89
    //   313: bastore
    //   314: dup
    //   315: iconst_1
    //   316: bipush #-13
    //   318: bastore
    //   319: dup
    //   320: iconst_2
    //   321: bipush #-90
    //   323: bastore
    //   324: dup
    //   325: iconst_3
    //   326: bipush #79
    //   328: bastore
    //   329: dup
    //   330: iconst_4
    //   331: bipush #34
    //   333: bastore
    //   334: dup
    //   335: iconst_5
    //   336: bipush #15
    //   338: bastore
    //   339: dup
    //   340: bipush #6
    //   342: bipush #-4
    //   344: bastore
    //   345: dup
    //   346: bipush #7
    //   348: bipush #55
    //   350: bastore
    //   351: dup
    //   352: bipush #8
    //   354: bipush #34
    //   356: bastore
    //   357: dup
    //   358: bipush #9
    //   360: bipush #-32
    //   362: bastore
    //   363: dup
    //   364: bipush #10
    //   366: bipush #14
    //   368: bastore
    //   369: dup
    //   370: bipush #11
    //   372: bipush #-108
    //   374: bastore
    //   375: dup
    //   376: bipush #12
    //   378: bipush #8
    //   380: bastore
    //   381: dup
    //   382: bipush #13
    //   384: bipush #-30
    //   386: bastore
    //   387: dup
    //   388: bipush #14
    //   390: bipush #98
    //   392: bastore
    //   393: dup
    //   394: bipush #15
    //   396: bipush #-34
    //   398: bastore
    //   399: dup
    //   400: bipush #16
    //   402: bipush #105
    //   404: bastore
    //   405: dup
    //   406: bipush #17
    //   408: bipush #-36
    //   410: bastore
    //   411: dup
    //   412: bipush #18
    //   414: bipush #-38
    //   416: bastore
    //   417: dup
    //   418: bipush #19
    //   420: bipush #91
    //   422: bastore
    //   423: dup
    //   424: bipush #20
    //   426: bipush #-108
    //   428: bastore
    //   429: dup
    //   430: bipush #21
    //   432: bipush #14
    //   434: bastore
    //   435: dup
    //   436: bipush #22
    //   438: bipush #-110
    //   440: bastore
    //   441: dup
    //   442: bipush #23
    //   444: bipush #-29
    //   446: bastore
    //   447: dup
    //   448: bipush #24
    //   450: bipush #-44
    //   452: bastore
    //   453: dup
    //   454: bipush #25
    //   456: bipush #-92
    //   458: bastore
    //   459: dup
    //   460: bipush #26
    //   462: bipush #74
    //   464: bastore
    //   465: dup
    //   466: bipush #27
    //   468: bipush #-87
    //   470: bastore
    //   471: dup
    //   472: bipush #28
    //   474: iconst_0
    //   475: bastore
    //   476: dup
    //   477: bipush #29
    //   479: bipush #6
    //   481: bastore
    //   482: dup
    //   483: bipush #30
    //   485: bipush #-39
    //   487: bastore
    //   488: dup
    //   489: bipush #31
    //   491: bipush #126
    //   493: bastore
    //   494: invokespecial <init> : (I[B)V
    //   497: putstatic burp/Zm8j.Zj : Ljava/lang/Object;
    //   500: sipush #23916
    //   503: sipush #-31563
    //   506: invokestatic a : (II)Ljava/lang/String;
    //   509: putstatic burp/Zm8j.Zp : Ljava/lang/String;
    //   512: return
  }
  
  private static Throwable a(Throwable paramThrowable) {
    return paramThrowable;
  }
  
  private static String a(int paramInt1, int paramInt2) {
    int i = (paramInt1 ^ 0x5D66) & 0xFFFF;
    if (b[i] == null) {
      char[] arrayOfChar = a[i].toCharArray();
      switch (arrayOfChar[0] & 0xFF) {
        case 0:
        
        case 1:
        
        case 2:
        
        case 3:
        
        case 4:
        
        case 5:
        
        case 6:
        
        case 7:
        
        case 8:
        
        case 9:
        
        case 10:
        
        case 11:
        
        case 12:
        
        case 13:
        
        case 14:
        
        case 15:
        
        case 16:
        
        case 17:
        
        case 18:
        
        case 19:
        
        case 20:
        
        case 21:
        
        case 22:
        
        case 23:
        
        case 24:
        
        case 25:
        
        case 26:
        
        case 27:
        
        case 28:
        
        case 29:
        
        case 30:
        
        case 31:
        
        case 32:
        
        case 33:
        
        case 34:
        
        case 35:
        
        case 36:
        
        case 37:
        
        case 38:
        
        case 39:
        
        case 40:
        
        case 41:
        
        case 42:
        
        case 43:
        
        case 44:
        
        case 45:
        
        case 46:
        
        case 47:
        
        case 48:
        
        case 49:
        
        case 50:
        
        case 51:
        
        case 52:
        
        case 53:
        
        case 54:
        
        case 55:
        
        case 56:
        
        case 57:
        
        case 58:
        
        case 59:
        
        case 60:
        
        case 61:
        
        case 62:
        
        case 63:
        
        case 64:
        
        case 65:
        
        case 66:
        
        case 67:
        
        case 68:
        
        case 69:
        
        case 70:
        
        case 71:
        
        case 72:
        
        case 73:
        
        case 74:
        
        case 75:
        
        case 76:
        
        case 77:
        
        case 78:
        
        case 79:
        
        case 80:
        
        case 81:
        
        case 82:
        
        case 83:
        
        case 84:
        
        case 85:
        
        case 86:
        
        case 87:
        
        case 88:
        
        case 89:
        
        case 90:
        
        case 91:
        
        case 92:
        
        case 93:
        
        case 94:
        
        case 95:
        
        case 96:
        
        case 97:
        
        case 98:
        
        case 99:
        
        case 100:
        
        case 101:
        
        case 102:
        
        case 103:
        
        case 104:
        
        case 105:
        
        case 106:
        
        case 107:
        
        case 108:
        
        case 109:
        
        case 110:
        
        case 111:
        
        case 112:
        
        case 113:
        
        case 114:
        
        case 115:
        
        case 116:
        
        case 117:
        
        case 118:
        
        case 119:
        
        case 120:
        
        case 121:
        
        case 122:
        
        case 123:
        
        case 124:
        
        case 125:
        
        case 126:
        
        case 127:
        
        case 128:
        
        case 129:
        
        case 130:
        
        case 131:
        
        case 132:
        
        case 133:
        
        case 134:
        
        case 135:
        
        case 136:
        
        case 137:
        
        case 138:
        
        case 139:
        
        case 140:
        
        case 141:
        
        case 142:
        
        case 143:
        
        case 144:
        
        case 145:
        
        case 146:
        
        case 147:
        
        case 148:
        
        case 149:
        
        case 150:
        
        case 151:
        
        case 152:
        
        case 153:
        
        case 154:
        
        case 155:
        
        case 156:
        
        case 157:
        
        case 158:
        
        case 159:
        
        case 160:
        
        case 161:
        
        case 162:
        
        case 163:
        
        case 164:
        
        case 165:
        
        case 166:
        
        case 167:
        
        case 168:
        
        case 169:
        
        case 170:
        
        case 171:
        
        case 172:
        
        case 173:
        
        case 174:
        
        case 175:
        
        case 176:
        
        case 177:
        
        case 178:
        
        case 179:
        
        case 180:
        
        case 181:
        
        case 182:
        
        case 183:
        
        case 184:
        
        case 185:
        
        case 186:
        
        case 187:
        
        case 188:
        
        case 189:
        
        case 190:
        
        case 191:
        
        case 192:
        
        case 193:
        
        case 194:
        
        case 195:
        
        case 196:
        
        case 197:
        
        case 198:
        
        case 199:
        
        case 200:
        
        case 201:
        
        case 202:
        
        case 203:
        
        case 204:
        
        case 205:
        
        case 206:
        
        case 207:
        
        case 208:
        
        case 209:
        
        case 210:
        
        case 211:
        
        case 212:
        
        case 213:
        
        case 214:
        
        case 215:
        
        case 216:
        
        case 217:
        
        case 218:
        
        case 219:
        
        case 220:
        
        case 221:
        
        case 222:
        
        case 223:
        
        case 224:
        
        case 225:
        
        case 226:
        
        case 227:
        
        case 228:
        
        case 229:
        
        case 230:
        
        case 231:
        
        case 232:
        
        case 233:
        
        case 234:
        
        case 235:
        
        case 236:
        
        case 237:
        
        case 238:
        
        case 239:
        
        case 240:
        
        case 241:
        
        case 242:
        
        case 243:
        
        case 244:
        
        case 245:
        
        case 246:
        
        case 247:
        
        case 248:
        
        case 249:
        
        case 250:
        
        case 251:
        
        case 252:
        
        case 253:
        
        case 254:
        
        default:
          break;
      } 
      char c = '';
      int j = (paramInt2 & 0xFF) - c;
      if (j < 0)
        j += 256; 
      int k = ((paramInt2 & 0xFFFF) >>> 8) - c;
      if (k < 0)
        k += 256; 
      for (byte b = 0; b < arrayOfChar.length; b++) {
        int m = b % 2;
        if (m == 0) {
          arrayOfChar[b] = (char)(arrayOfChar[b] ^ j);
          j = ((j >>> 3 | j << 5) ^ arrayOfChar[b]) & 0xFF;
        } else {
          arrayOfChar[b] = (char)(arrayOfChar[b] ^ k);
          k = ((k >>> 3 | k << 5) ^ arrayOfChar[b]) & 0xFF;
        } 
      } 
      b[i] = (new String(arrayOfChar)).intern();
    } 
    return b[i];
  }
}


/* Location:              C:\Program Files\BurpSuitePro\burpsuite_pro.jar!\burp\Zm8j.class
 * Java compiler version: 21 (65.0)
 * JD-Core Version:       1.1.3
 */