package burp;

import java.math.BigInteger;

class Zm__ extends ClassLoader {
  static String Zf;
  
  static Object Zz;
  
  private static final String[] a;
  
  private static final String[] b;
  
  static void ZC(Object[] paramArrayOfObject, Object paramObject) throws Throwable {}
  
  static void ZB(Object paramObject) {
    Zt3l.Zi = a(-16589, 6615);
    Zt3l.Zq = new BigInteger(a(-16583, 10401));
    boolean bool = Zt2e.ZN();
    try {
      try {
        if (Zxo6.Z_.charAt(Math.abs(((BigInteger)Ztuj.Ze).intValue() % 32)) <= Zm0s.Zm.charAt(Math.abs(((BigInteger)Zl2q.Zg).intValue() % 32))) {
          try {
            Zr9j.Zj(Class.forName(a(-16592, 7848)));
            if (!bool)
              Zr0g.Ze(Class.forName(a(-16590, -82))); 
          } catch (Throwable throwable) {
            throw a(null);
          } 
          return;
        } 
      } catch (Throwable throwable) {
        throw a(null);
      } 
      Zr0g.Ze(Class.forName(a(-16590, -82)));
    } catch (Throwable throwable) {}
  }
  
  static boolean Zu(Object[] paramArrayOfObject, Object paramObject) throws Throwable {
    // Byte code:
    //   0: invokestatic ZK : ()Z
    //   3: istore_2
    //   4: getstatic burp/Zg0j.ZV : Ljava/lang/Object;
    //   7: checkcast java/math/BigInteger
    //   10: invokevirtual toByteArray : ()[B
    //   13: astore_3
    //   14: bipush #32
    //   16: newarray int
    //   18: dup
    //   19: iconst_0
    //   20: ldc 876216579
    //   22: iastore
    //   23: dup
    //   24: iconst_1
    //   25: ldc 455999525
    //   27: iastore
    //   28: dup
    //   29: iconst_2
    //   30: ldc 1043334948
    //   32: iastore
    //   33: dup
    //   34: iconst_3
    //   35: ldc 439222784
    //   37: iastore
    //   38: dup
    //   39: iconst_4
    //   40: ldc 372376604
    //   42: iastore
    //   43: dup
    //   44: iconst_5
    //   45: ldc 707731490
    //   47: iastore
    //   48: dup
    //   49: bipush #6
    //   51: ldc 389426184
    //   53: iastore
    //   54: dup
    //   55: bipush #7
    //   57: ldc 973875457
    //   59: iastore
    //   60: dup
    //   61: bipush #8
    //   63: ldc 389160971
    //   65: iastore
    //   66: dup
    //   67: bipush #9
    //   69: ldc 907870729
    //   71: iastore
    //   72: dup
    //   73: bipush #10
    //   75: ldc 121057538
    //   77: iastore
    //   78: dup
    //   79: bipush #11
    //   81: ldc 840500228
    //   83: iastore
    //   84: dup
    //   85: bipush #12
    //   87: ldc 254150144
    //   89: iastore
    //   90: dup
    //   91: bipush #13
    //   93: ldc 924386310
    //   95: iastore
    //   96: dup
    //   97: bipush #14
    //   99: ldc 187632156
    //   101: iastore
    //   102: dup
    //   103: bipush #15
    //   105: ldc 874189824
    //   107: iastore
    //   108: dup
    //   109: bipush #16
    //   111: ldc 655302664
    //   113: iastore
    //   114: dup
    //   115: bipush #17
    //   117: ldc 890966315
    //   119: iastore
    //   120: dup
    //   121: bipush #18
    //   123: ldc 722417666
    //   125: iastore
    //   126: dup
    //   127: bipush #19
    //   129: ldc 1026621720
    //   131: iastore
    //   132: dup
    //   133: bipush #20
    //   135: ldc 957157408
    //   137: iastore
    //   138: dup
    //   139: bipush #21
    //   141: ldc 892536332
    //   143: iastore
    //   144: dup
    //   145: bipush #22
    //   147: ldc 689771012
    //   149: iastore
    //   150: dup
    //   151: bipush #23
    //   153: ldc 221709344
    //   155: iastore
    //   156: dup
    //   157: bipush #24
    //   159: ldc 940377620
    //   161: iastore
    //   162: dup
    //   163: bipush #25
    //   165: ldc 255209728
    //   167: iastore
    //   168: dup
    //   169: bipush #26
    //   171: ldc 1010368540
    //   173: iastore
    //   174: dup
    //   175: bipush #27
    //   177: ldc 220604441
    //   179: iastore
    //   180: dup
    //   181: bipush #28
    //   183: ldc 1008414755
    //   185: iastore
    //   186: dup
    //   187: bipush #29
    //   189: ldc 187049985
    //   191: iastore
    //   192: dup
    //   193: bipush #30
    //   195: ldc 943331329
    //   197: iastore
    //   198: dup
    //   199: bipush #31
    //   201: ldc 170788368
    //   203: iastore
    //   204: astore #5
    //   206: bipush #64
    //   208: newarray int
    //   210: dup
    //   211: iconst_0
    //   212: ldc 16843776
    //   214: iastore
    //   215: dup
    //   216: iconst_1
    //   217: iconst_0
    //   218: iastore
    //   219: dup
    //   220: iconst_2
    //   221: ldc 65536
    //   223: iastore
    //   224: dup
    //   225: iconst_3
    //   226: ldc 16843780
    //   228: iastore
    //   229: dup
    //   230: iconst_4
    //   231: ldc 16842756
    //   233: iastore
    //   234: dup
    //   235: iconst_5
    //   236: ldc 66564
    //   238: iastore
    //   239: dup
    //   240: bipush #6
    //   242: iconst_4
    //   243: iastore
    //   244: dup
    //   245: bipush #7
    //   247: ldc 65536
    //   249: iastore
    //   250: dup
    //   251: bipush #8
    //   253: sipush #1024
    //   256: iastore
    //   257: dup
    //   258: bipush #9
    //   260: ldc 16843776
    //   262: iastore
    //   263: dup
    //   264: bipush #10
    //   266: ldc 16843780
    //   268: iastore
    //   269: dup
    //   270: bipush #11
    //   272: sipush #1024
    //   275: iastore
    //   276: dup
    //   277: bipush #12
    //   279: ldc 16778244
    //   281: iastore
    //   282: dup
    //   283: bipush #13
    //   285: ldc 16842756
    //   287: iastore
    //   288: dup
    //   289: bipush #14
    //   291: ldc 16777216
    //   293: iastore
    //   294: dup
    //   295: bipush #15
    //   297: iconst_4
    //   298: iastore
    //   299: dup
    //   300: bipush #16
    //   302: sipush #1028
    //   305: iastore
    //   306: dup
    //   307: bipush #17
    //   309: ldc 16778240
    //   311: iastore
    //   312: dup
    //   313: bipush #18
    //   315: ldc 16778240
    //   317: iastore
    //   318: dup
    //   319: bipush #19
    //   321: ldc 66560
    //   323: iastore
    //   324: dup
    //   325: bipush #20
    //   327: ldc 66560
    //   329: iastore
    //   330: dup
    //   331: bipush #21
    //   333: ldc 16842752
    //   335: iastore
    //   336: dup
    //   337: bipush #22
    //   339: ldc 16842752
    //   341: iastore
    //   342: dup
    //   343: bipush #23
    //   345: ldc 16778244
    //   347: iastore
    //   348: dup
    //   349: bipush #24
    //   351: ldc 65540
    //   353: iastore
    //   354: dup
    //   355: bipush #25
    //   357: ldc 16777220
    //   359: iastore
    //   360: dup
    //   361: bipush #26
    //   363: ldc 16777220
    //   365: iastore
    //   366: dup
    //   367: bipush #27
    //   369: ldc 65540
    //   371: iastore
    //   372: dup
    //   373: bipush #28
    //   375: iconst_0
    //   376: iastore
    //   377: dup
    //   378: bipush #29
    //   380: sipush #1028
    //   383: iastore
    //   384: dup
    //   385: bipush #30
    //   387: ldc 66564
    //   389: iastore
    //   390: dup
    //   391: bipush #31
    //   393: ldc 16777216
    //   395: iastore
    //   396: dup
    //   397: bipush #32
    //   399: ldc 65536
    //   401: iastore
    //   402: dup
    //   403: bipush #33
    //   405: ldc 16843780
    //   407: iastore
    //   408: dup
    //   409: bipush #34
    //   411: iconst_4
    //   412: iastore
    //   413: dup
    //   414: bipush #35
    //   416: ldc 16842752
    //   418: iastore
    //   419: dup
    //   420: bipush #36
    //   422: ldc 16843776
    //   424: iastore
    //   425: dup
    //   426: bipush #37
    //   428: ldc 16777216
    //   430: iastore
    //   431: dup
    //   432: bipush #38
    //   434: ldc 16777216
    //   436: iastore
    //   437: dup
    //   438: bipush #39
    //   440: sipush #1024
    //   443: iastore
    //   444: dup
    //   445: bipush #40
    //   447: ldc 16842756
    //   449: iastore
    //   450: dup
    //   451: bipush #41
    //   453: ldc 65536
    //   455: iastore
    //   456: dup
    //   457: bipush #42
    //   459: ldc 66560
    //   461: iastore
    //   462: dup
    //   463: bipush #43
    //   465: ldc 16777220
    //   467: iastore
    //   468: dup
    //   469: bipush #44
    //   471: sipush #1024
    //   474: iastore
    //   475: dup
    //   476: bipush #45
    //   478: iconst_4
    //   479: iastore
    //   480: dup
    //   481: bipush #46
    //   483: ldc 16778244
    //   485: iastore
    //   486: dup
    //   487: bipush #47
    //   489: ldc 66564
    //   491: iastore
    //   492: dup
    //   493: bipush #48
    //   495: ldc 16843780
    //   497: iastore
    //   498: dup
    //   499: bipush #49
    //   501: ldc 65540
    //   503: iastore
    //   504: dup
    //   505: bipush #50
    //   507: ldc 16842752
    //   509: iastore
    //   510: dup
    //   511: bipush #51
    //   513: ldc 16778244
    //   515: iastore
    //   516: dup
    //   517: bipush #52
    //   519: ldc 16777220
    //   521: iastore
    //   522: dup
    //   523: bipush #53
    //   525: sipush #1028
    //   528: iastore
    //   529: dup
    //   530: bipush #54
    //   532: ldc 66564
    //   534: iastore
    //   535: dup
    //   536: bipush #55
    //   538: ldc 16843776
    //   540: iastore
    //   541: dup
    //   542: bipush #56
    //   544: sipush #1028
    //   547: iastore
    //   548: dup
    //   549: bipush #57
    //   551: ldc 16778240
    //   553: iastore
    //   554: dup
    //   555: bipush #58
    //   557: ldc 16778240
    //   559: iastore
    //   560: dup
    //   561: bipush #59
    //   563: iconst_0
    //   564: iastore
    //   565: dup
    //   566: bipush #60
    //   568: ldc 65540
    //   570: iastore
    //   571: dup
    //   572: bipush #61
    //   574: ldc 66560
    //   576: iastore
    //   577: dup
    //   578: bipush #62
    //   580: iconst_0
    //   581: iastore
    //   582: dup
    //   583: bipush #63
    //   585: ldc 16842756
    //   587: iastore
    //   588: astore #6
    //   590: bipush #64
    //   592: newarray int
    //   594: dup
    //   595: iconst_0
    //   596: ldc -2146402272
    //   598: iastore
    //   599: dup
    //   600: iconst_1
    //   601: ldc -2147450880
    //   603: iastore
    //   604: dup
    //   605: iconst_2
    //   606: ldc 32768
    //   608: iastore
    //   609: dup
    //   610: iconst_3
    //   611: ldc 1081376
    //   613: iastore
    //   614: dup
    //   615: iconst_4
    //   616: ldc 1048576
    //   618: iastore
    //   619: dup
    //   620: iconst_5
    //   621: bipush #32
    //   623: iastore
    //   624: dup
    //   625: bipush #6
    //   627: ldc -2146435040
    //   629: iastore
    //   630: dup
    //   631: bipush #7
    //   633: ldc -2147450848
    //   635: iastore
    //   636: dup
    //   637: bipush #8
    //   639: ldc -2147483616
    //   641: iastore
    //   642: dup
    //   643: bipush #9
    //   645: ldc -2146402272
    //   647: iastore
    //   648: dup
    //   649: bipush #10
    //   651: ldc -2146402304
    //   653: iastore
    //   654: dup
    //   655: bipush #11
    //   657: ldc -2147483648
    //   659: iastore
    //   660: dup
    //   661: bipush #12
    //   663: ldc -2147450880
    //   665: iastore
    //   666: dup
    //   667: bipush #13
    //   669: ldc 1048576
    //   671: iastore
    //   672: dup
    //   673: bipush #14
    //   675: bipush #32
    //   677: iastore
    //   678: dup
    //   679: bipush #15
    //   681: ldc -2146435040
    //   683: iastore
    //   684: dup
    //   685: bipush #16
    //   687: ldc 1081344
    //   689: iastore
    //   690: dup
    //   691: bipush #17
    //   693: ldc 1048608
    //   695: iastore
    //   696: dup
    //   697: bipush #18
    //   699: ldc -2147450848
    //   701: iastore
    //   702: dup
    //   703: bipush #19
    //   705: iconst_0
    //   706: iastore
    //   707: dup
    //   708: bipush #20
    //   710: ldc -2147483648
    //   712: iastore
    //   713: dup
    //   714: bipush #21
    //   716: ldc 32768
    //   718: iastore
    //   719: dup
    //   720: bipush #22
    //   722: ldc 1081376
    //   724: iastore
    //   725: dup
    //   726: bipush #23
    //   728: ldc -2146435072
    //   730: iastore
    //   731: dup
    //   732: bipush #24
    //   734: ldc 1048608
    //   736: iastore
    //   737: dup
    //   738: bipush #25
    //   740: ldc -2147483616
    //   742: iastore
    //   743: dup
    //   744: bipush #26
    //   746: iconst_0
    //   747: iastore
    //   748: dup
    //   749: bipush #27
    //   751: ldc 1081344
    //   753: iastore
    //   754: dup
    //   755: bipush #28
    //   757: ldc 32800
    //   759: iastore
    //   760: dup
    //   761: bipush #29
    //   763: ldc -2146402304
    //   765: iastore
    //   766: dup
    //   767: bipush #30
    //   769: ldc -2146435072
    //   771: iastore
    //   772: dup
    //   773: bipush #31
    //   775: ldc 32800
    //   777: iastore
    //   778: dup
    //   779: bipush #32
    //   781: iconst_0
    //   782: iastore
    //   783: dup
    //   784: bipush #33
    //   786: ldc 1081376
    //   788: iastore
    //   789: dup
    //   790: bipush #34
    //   792: ldc -2146435040
    //   794: iastore
    //   795: dup
    //   796: bipush #35
    //   798: ldc 1048576
    //   800: iastore
    //   801: dup
    //   802: bipush #36
    //   804: ldc -2147450848
    //   806: iastore
    //   807: dup
    //   808: bipush #37
    //   810: ldc -2146435072
    //   812: iastore
    //   813: dup
    //   814: bipush #38
    //   816: ldc -2146402304
    //   818: iastore
    //   819: dup
    //   820: bipush #39
    //   822: ldc 32768
    //   824: iastore
    //   825: dup
    //   826: bipush #40
    //   828: ldc -2146435072
    //   830: iastore
    //   831: dup
    //   832: bipush #41
    //   834: ldc -2147450880
    //   836: iastore
    //   837: dup
    //   838: bipush #42
    //   840: bipush #32
    //   842: iastore
    //   843: dup
    //   844: bipush #43
    //   846: ldc -2146402272
    //   848: iastore
    //   849: dup
    //   850: bipush #44
    //   852: ldc 1081376
    //   854: iastore
    //   855: dup
    //   856: bipush #45
    //   858: bipush #32
    //   860: iastore
    //   861: dup
    //   862: bipush #46
    //   864: ldc 32768
    //   866: iastore
    //   867: dup
    //   868: bipush #47
    //   870: ldc -2147483648
    //   872: iastore
    //   873: dup
    //   874: bipush #48
    //   876: ldc 32800
    //   878: iastore
    //   879: dup
    //   880: bipush #49
    //   882: ldc -2146402304
    //   884: iastore
    //   885: dup
    //   886: bipush #50
    //   888: ldc 1048576
    //   890: iastore
    //   891: dup
    //   892: bipush #51
    //   894: ldc -2147483616
    //   896: iastore
    //   897: dup
    //   898: bipush #52
    //   900: ldc 1048608
    //   902: iastore
    //   903: dup
    //   904: bipush #53
    //   906: ldc -2147450848
    //   908: iastore
    //   909: dup
    //   910: bipush #54
    //   912: ldc -2147483616
    //   914: iastore
    //   915: dup
    //   916: bipush #55
    //   918: ldc 1048608
    //   920: iastore
    //   921: dup
    //   922: bipush #56
    //   924: ldc 1081344
    //   926: iastore
    //   927: dup
    //   928: bipush #57
    //   930: iconst_0
    //   931: iastore
    //   932: dup
    //   933: bipush #58
    //   935: ldc -2147450880
    //   937: iastore
    //   938: dup
    //   939: bipush #59
    //   941: ldc 32800
    //   943: iastore
    //   944: dup
    //   945: bipush #60
    //   947: ldc -2147483648
    //   949: iastore
    //   950: dup
    //   951: bipush #61
    //   953: ldc -2146435040
    //   955: iastore
    //   956: dup
    //   957: bipush #62
    //   959: ldc -2146402272
    //   961: iastore
    //   962: dup
    //   963: bipush #63
    //   965: ldc 1081344
    //   967: iastore
    //   968: astore #7
    //   970: bipush #64
    //   972: newarray int
    //   974: dup
    //   975: iconst_0
    //   976: sipush #520
    //   979: iastore
    //   980: dup
    //   981: iconst_1
    //   982: ldc 134349312
    //   984: iastore
    //   985: dup
    //   986: iconst_2
    //   987: iconst_0
    //   988: iastore
    //   989: dup
    //   990: iconst_3
    //   991: ldc 134348808
    //   993: iastore
    //   994: dup
    //   995: iconst_4
    //   996: ldc 134218240
    //   998: iastore
    //   999: dup
    //   1000: iconst_5
    //   1001: iconst_0
    //   1002: iastore
    //   1003: dup
    //   1004: bipush #6
    //   1006: ldc 131592
    //   1008: iastore
    //   1009: dup
    //   1010: bipush #7
    //   1012: ldc 134218240
    //   1014: iastore
    //   1015: dup
    //   1016: bipush #8
    //   1018: ldc 131080
    //   1020: iastore
    //   1021: dup
    //   1022: bipush #9
    //   1024: ldc 134217736
    //   1026: iastore
    //   1027: dup
    //   1028: bipush #10
    //   1030: ldc 134217736
    //   1032: iastore
    //   1033: dup
    //   1034: bipush #11
    //   1036: ldc 131072
    //   1038: iastore
    //   1039: dup
    //   1040: bipush #12
    //   1042: ldc 134349320
    //   1044: iastore
    //   1045: dup
    //   1046: bipush #13
    //   1048: ldc 131080
    //   1050: iastore
    //   1051: dup
    //   1052: bipush #14
    //   1054: ldc 134348800
    //   1056: iastore
    //   1057: dup
    //   1058: bipush #15
    //   1060: sipush #520
    //   1063: iastore
    //   1064: dup
    //   1065: bipush #16
    //   1067: ldc 134217728
    //   1069: iastore
    //   1070: dup
    //   1071: bipush #17
    //   1073: bipush #8
    //   1075: iastore
    //   1076: dup
    //   1077: bipush #18
    //   1079: ldc 134349312
    //   1081: iastore
    //   1082: dup
    //   1083: bipush #19
    //   1085: sipush #512
    //   1088: iastore
    //   1089: dup
    //   1090: bipush #20
    //   1092: ldc 131584
    //   1094: iastore
    //   1095: dup
    //   1096: bipush #21
    //   1098: ldc 134348800
    //   1100: iastore
    //   1101: dup
    //   1102: bipush #22
    //   1104: ldc 134348808
    //   1106: iastore
    //   1107: dup
    //   1108: bipush #23
    //   1110: ldc 131592
    //   1112: iastore
    //   1113: dup
    //   1114: bipush #24
    //   1116: ldc 134218248
    //   1118: iastore
    //   1119: dup
    //   1120: bipush #25
    //   1122: ldc 131584
    //   1124: iastore
    //   1125: dup
    //   1126: bipush #26
    //   1128: ldc 131072
    //   1130: iastore
    //   1131: dup
    //   1132: bipush #27
    //   1134: ldc 134218248
    //   1136: iastore
    //   1137: dup
    //   1138: bipush #28
    //   1140: bipush #8
    //   1142: iastore
    //   1143: dup
    //   1144: bipush #29
    //   1146: ldc 134349320
    //   1148: iastore
    //   1149: dup
    //   1150: bipush #30
    //   1152: sipush #512
    //   1155: iastore
    //   1156: dup
    //   1157: bipush #31
    //   1159: ldc 134217728
    //   1161: iastore
    //   1162: dup
    //   1163: bipush #32
    //   1165: ldc 134349312
    //   1167: iastore
    //   1168: dup
    //   1169: bipush #33
    //   1171: ldc 134217728
    //   1173: iastore
    //   1174: dup
    //   1175: bipush #34
    //   1177: ldc 131080
    //   1179: iastore
    //   1180: dup
    //   1181: bipush #35
    //   1183: sipush #520
    //   1186: iastore
    //   1187: dup
    //   1188: bipush #36
    //   1190: ldc 131072
    //   1192: iastore
    //   1193: dup
    //   1194: bipush #37
    //   1196: ldc 134349312
    //   1198: iastore
    //   1199: dup
    //   1200: bipush #38
    //   1202: ldc 134218240
    //   1204: iastore
    //   1205: dup
    //   1206: bipush #39
    //   1208: iconst_0
    //   1209: iastore
    //   1210: dup
    //   1211: bipush #40
    //   1213: sipush #512
    //   1216: iastore
    //   1217: dup
    //   1218: bipush #41
    //   1220: ldc 131080
    //   1222: iastore
    //   1223: dup
    //   1224: bipush #42
    //   1226: ldc 134349320
    //   1228: iastore
    //   1229: dup
    //   1230: bipush #43
    //   1232: ldc 134218240
    //   1234: iastore
    //   1235: dup
    //   1236: bipush #44
    //   1238: ldc 134217736
    //   1240: iastore
    //   1241: dup
    //   1242: bipush #45
    //   1244: sipush #512
    //   1247: iastore
    //   1248: dup
    //   1249: bipush #46
    //   1251: iconst_0
    //   1252: iastore
    //   1253: dup
    //   1254: bipush #47
    //   1256: ldc 134348808
    //   1258: iastore
    //   1259: dup
    //   1260: bipush #48
    //   1262: ldc 134218248
    //   1264: iastore
    //   1265: dup
    //   1266: bipush #49
    //   1268: ldc 131072
    //   1270: iastore
    //   1271: dup
    //   1272: bipush #50
    //   1274: ldc 134217728
    //   1276: iastore
    //   1277: dup
    //   1278: bipush #51
    //   1280: ldc 134349320
    //   1282: iastore
    //   1283: dup
    //   1284: bipush #52
    //   1286: bipush #8
    //   1288: iastore
    //   1289: dup
    //   1290: bipush #53
    //   1292: ldc 131592
    //   1294: iastore
    //   1295: dup
    //   1296: bipush #54
    //   1298: ldc 131584
    //   1300: iastore
    //   1301: dup
    //   1302: bipush #55
    //   1304: ldc 134217736
    //   1306: iastore
    //   1307: dup
    //   1308: bipush #56
    //   1310: ldc 134348800
    //   1312: iastore
    //   1313: dup
    //   1314: bipush #57
    //   1316: ldc 134218248
    //   1318: iastore
    //   1319: dup
    //   1320: bipush #58
    //   1322: sipush #520
    //   1325: iastore
    //   1326: dup
    //   1327: bipush #59
    //   1329: ldc 134348800
    //   1331: iastore
    //   1332: dup
    //   1333: bipush #60
    //   1335: ldc 131592
    //   1337: iastore
    //   1338: dup
    //   1339: bipush #61
    //   1341: bipush #8
    //   1343: iastore
    //   1344: dup
    //   1345: bipush #62
    //   1347: ldc 134348808
    //   1349: iastore
    //   1350: dup
    //   1351: bipush #63
    //   1353: ldc 131584
    //   1355: iastore
    //   1356: astore #8
    //   1358: bipush #64
    //   1360: newarray int
    //   1362: dup
    //   1363: iconst_0
    //   1364: ldc 8396801
    //   1366: iastore
    //   1367: dup
    //   1368: iconst_1
    //   1369: sipush #8321
    //   1372: iastore
    //   1373: dup
    //   1374: iconst_2
    //   1375: sipush #8321
    //   1378: iastore
    //   1379: dup
    //   1380: iconst_3
    //   1381: sipush #128
    //   1384: iastore
    //   1385: dup
    //   1386: iconst_4
    //   1387: ldc 8396928
    //   1389: iastore
    //   1390: dup
    //   1391: iconst_5
    //   1392: ldc 8388737
    //   1394: iastore
    //   1395: dup
    //   1396: bipush #6
    //   1398: ldc 8388609
    //   1400: iastore
    //   1401: dup
    //   1402: bipush #7
    //   1404: sipush #8193
    //   1407: iastore
    //   1408: dup
    //   1409: bipush #8
    //   1411: iconst_0
    //   1412: iastore
    //   1413: dup
    //   1414: bipush #9
    //   1416: ldc 8396800
    //   1418: iastore
    //   1419: dup
    //   1420: bipush #10
    //   1422: ldc 8396800
    //   1424: iastore
    //   1425: dup
    //   1426: bipush #11
    //   1428: ldc 8396929
    //   1430: iastore
    //   1431: dup
    //   1432: bipush #12
    //   1434: sipush #129
    //   1437: iastore
    //   1438: dup
    //   1439: bipush #13
    //   1441: iconst_0
    //   1442: iastore
    //   1443: dup
    //   1444: bipush #14
    //   1446: ldc 8388736
    //   1448: iastore
    //   1449: dup
    //   1450: bipush #15
    //   1452: ldc 8388609
    //   1454: iastore
    //   1455: dup
    //   1456: bipush #16
    //   1458: iconst_1
    //   1459: iastore
    //   1460: dup
    //   1461: bipush #17
    //   1463: sipush #8192
    //   1466: iastore
    //   1467: dup
    //   1468: bipush #18
    //   1470: ldc 8388608
    //   1472: iastore
    //   1473: dup
    //   1474: bipush #19
    //   1476: ldc 8396801
    //   1478: iastore
    //   1479: dup
    //   1480: bipush #20
    //   1482: sipush #128
    //   1485: iastore
    //   1486: dup
    //   1487: bipush #21
    //   1489: ldc 8388608
    //   1491: iastore
    //   1492: dup
    //   1493: bipush #22
    //   1495: sipush #8193
    //   1498: iastore
    //   1499: dup
    //   1500: bipush #23
    //   1502: sipush #8320
    //   1505: iastore
    //   1506: dup
    //   1507: bipush #24
    //   1509: ldc 8388737
    //   1511: iastore
    //   1512: dup
    //   1513: bipush #25
    //   1515: iconst_1
    //   1516: iastore
    //   1517: dup
    //   1518: bipush #26
    //   1520: sipush #8320
    //   1523: iastore
    //   1524: dup
    //   1525: bipush #27
    //   1527: ldc 8388736
    //   1529: iastore
    //   1530: dup
    //   1531: bipush #28
    //   1533: sipush #8192
    //   1536: iastore
    //   1537: dup
    //   1538: bipush #29
    //   1540: ldc 8396928
    //   1542: iastore
    //   1543: dup
    //   1544: bipush #30
    //   1546: ldc 8396929
    //   1548: iastore
    //   1549: dup
    //   1550: bipush #31
    //   1552: sipush #129
    //   1555: iastore
    //   1556: dup
    //   1557: bipush #32
    //   1559: ldc 8388736
    //   1561: iastore
    //   1562: dup
    //   1563: bipush #33
    //   1565: ldc 8388609
    //   1567: iastore
    //   1568: dup
    //   1569: bipush #34
    //   1571: ldc 8396800
    //   1573: iastore
    //   1574: dup
    //   1575: bipush #35
    //   1577: ldc 8396929
    //   1579: iastore
    //   1580: dup
    //   1581: bipush #36
    //   1583: sipush #129
    //   1586: iastore
    //   1587: dup
    //   1588: bipush #37
    //   1590: iconst_0
    //   1591: iastore
    //   1592: dup
    //   1593: bipush #38
    //   1595: iconst_0
    //   1596: iastore
    //   1597: dup
    //   1598: bipush #39
    //   1600: ldc 8396800
    //   1602: iastore
    //   1603: dup
    //   1604: bipush #40
    //   1606: sipush #8320
    //   1609: iastore
    //   1610: dup
    //   1611: bipush #41
    //   1613: ldc 8388736
    //   1615: iastore
    //   1616: dup
    //   1617: bipush #42
    //   1619: ldc 8388737
    //   1621: iastore
    //   1622: dup
    //   1623: bipush #43
    //   1625: iconst_1
    //   1626: iastore
    //   1627: dup
    //   1628: bipush #44
    //   1630: ldc 8396801
    //   1632: iastore
    //   1633: dup
    //   1634: bipush #45
    //   1636: sipush #8321
    //   1639: iastore
    //   1640: dup
    //   1641: bipush #46
    //   1643: sipush #8321
    //   1646: iastore
    //   1647: dup
    //   1648: bipush #47
    //   1650: sipush #128
    //   1653: iastore
    //   1654: dup
    //   1655: bipush #48
    //   1657: ldc 8396929
    //   1659: iastore
    //   1660: dup
    //   1661: bipush #49
    //   1663: sipush #129
    //   1666: iastore
    //   1667: dup
    //   1668: bipush #50
    //   1670: iconst_1
    //   1671: iastore
    //   1672: dup
    //   1673: bipush #51
    //   1675: sipush #8192
    //   1678: iastore
    //   1679: dup
    //   1680: bipush #52
    //   1682: ldc 8388609
    //   1684: iastore
    //   1685: dup
    //   1686: bipush #53
    //   1688: sipush #8193
    //   1691: iastore
    //   1692: dup
    //   1693: bipush #54
    //   1695: ldc 8396928
    //   1697: iastore
    //   1698: dup
    //   1699: bipush #55
    //   1701: ldc 8388737
    //   1703: iastore
    //   1704: dup
    //   1705: bipush #56
    //   1707: sipush #8193
    //   1710: iastore
    //   1711: dup
    //   1712: bipush #57
    //   1714: sipush #8320
    //   1717: iastore
    //   1718: dup
    //   1719: bipush #58
    //   1721: ldc 8388608
    //   1723: iastore
    //   1724: dup
    //   1725: bipush #59
    //   1727: ldc 8396801
    //   1729: iastore
    //   1730: dup
    //   1731: bipush #60
    //   1733: sipush #128
    //   1736: iastore
    //   1737: dup
    //   1738: bipush #61
    //   1740: ldc 8388608
    //   1742: iastore
    //   1743: dup
    //   1744: bipush #62
    //   1746: sipush #8192
    //   1749: iastore
    //   1750: dup
    //   1751: bipush #63
    //   1753: ldc 8396928
    //   1755: iastore
    //   1756: astore #9
    //   1758: bipush #64
    //   1760: newarray int
    //   1762: dup
    //   1763: iconst_0
    //   1764: sipush #256
    //   1767: iastore
    //   1768: dup
    //   1769: iconst_1
    //   1770: ldc 34078976
    //   1772: iastore
    //   1773: dup
    //   1774: iconst_2
    //   1775: ldc 34078720
    //   1777: iastore
    //   1778: dup
    //   1779: iconst_3
    //   1780: ldc 1107296512
    //   1782: iastore
    //   1783: dup
    //   1784: iconst_4
    //   1785: ldc 524288
    //   1787: iastore
    //   1788: dup
    //   1789: iconst_5
    //   1790: sipush #256
    //   1793: iastore
    //   1794: dup
    //   1795: bipush #6
    //   1797: ldc 1073741824
    //   1799: iastore
    //   1800: dup
    //   1801: bipush #7
    //   1803: ldc 34078720
    //   1805: iastore
    //   1806: dup
    //   1807: bipush #8
    //   1809: ldc 1074266368
    //   1811: iastore
    //   1812: dup
    //   1813: bipush #9
    //   1815: ldc 524288
    //   1817: iastore
    //   1818: dup
    //   1819: bipush #10
    //   1821: ldc 33554688
    //   1823: iastore
    //   1824: dup
    //   1825: bipush #11
    //   1827: ldc 1074266368
    //   1829: iastore
    //   1830: dup
    //   1831: bipush #12
    //   1833: ldc 1107296512
    //   1835: iastore
    //   1836: dup
    //   1837: bipush #13
    //   1839: ldc 1107820544
    //   1841: iastore
    //   1842: dup
    //   1843: bipush #14
    //   1845: ldc 524544
    //   1847: iastore
    //   1848: dup
    //   1849: bipush #15
    //   1851: ldc 1073741824
    //   1853: iastore
    //   1854: dup
    //   1855: bipush #16
    //   1857: ldc 33554432
    //   1859: iastore
    //   1860: dup
    //   1861: bipush #17
    //   1863: ldc 1074266112
    //   1865: iastore
    //   1866: dup
    //   1867: bipush #18
    //   1869: ldc 1074266112
    //   1871: iastore
    //   1872: dup
    //   1873: bipush #19
    //   1875: iconst_0
    //   1876: iastore
    //   1877: dup
    //   1878: bipush #20
    //   1880: ldc 1073742080
    //   1882: iastore
    //   1883: dup
    //   1884: bipush #21
    //   1886: ldc 1107820800
    //   1888: iastore
    //   1889: dup
    //   1890: bipush #22
    //   1892: ldc 1107820800
    //   1894: iastore
    //   1895: dup
    //   1896: bipush #23
    //   1898: ldc 33554688
    //   1900: iastore
    //   1901: dup
    //   1902: bipush #24
    //   1904: ldc 1107820544
    //   1906: iastore
    //   1907: dup
    //   1908: bipush #25
    //   1910: ldc 1073742080
    //   1912: iastore
    //   1913: dup
    //   1914: bipush #26
    //   1916: iconst_0
    //   1917: iastore
    //   1918: dup
    //   1919: bipush #27
    //   1921: ldc 1107296256
    //   1923: iastore
    //   1924: dup
    //   1925: bipush #28
    //   1927: ldc 34078976
    //   1929: iastore
    //   1930: dup
    //   1931: bipush #29
    //   1933: ldc 33554432
    //   1935: iastore
    //   1936: dup
    //   1937: bipush #30
    //   1939: ldc 1107296256
    //   1941: iastore
    //   1942: dup
    //   1943: bipush #31
    //   1945: ldc 524544
    //   1947: iastore
    //   1948: dup
    //   1949: bipush #32
    //   1951: ldc 524288
    //   1953: iastore
    //   1954: dup
    //   1955: bipush #33
    //   1957: ldc 1107296512
    //   1959: iastore
    //   1960: dup
    //   1961: bipush #34
    //   1963: sipush #256
    //   1966: iastore
    //   1967: dup
    //   1968: bipush #35
    //   1970: ldc 33554432
    //   1972: iastore
    //   1973: dup
    //   1974: bipush #36
    //   1976: ldc 1073741824
    //   1978: iastore
    //   1979: dup
    //   1980: bipush #37
    //   1982: ldc 34078720
    //   1984: iastore
    //   1985: dup
    //   1986: bipush #38
    //   1988: ldc 1107296512
    //   1990: iastore
    //   1991: dup
    //   1992: bipush #39
    //   1994: ldc 1074266368
    //   1996: iastore
    //   1997: dup
    //   1998: bipush #40
    //   2000: ldc 33554688
    //   2002: iastore
    //   2003: dup
    //   2004: bipush #41
    //   2006: ldc 1073741824
    //   2008: iastore
    //   2009: dup
    //   2010: bipush #42
    //   2012: ldc 1107820544
    //   2014: iastore
    //   2015: dup
    //   2016: bipush #43
    //   2018: ldc 34078976
    //   2020: iastore
    //   2021: dup
    //   2022: bipush #44
    //   2024: ldc 1074266368
    //   2026: iastore
    //   2027: dup
    //   2028: bipush #45
    //   2030: sipush #256
    //   2033: iastore
    //   2034: dup
    //   2035: bipush #46
    //   2037: ldc 33554432
    //   2039: iastore
    //   2040: dup
    //   2041: bipush #47
    //   2043: ldc 1107820544
    //   2045: iastore
    //   2046: dup
    //   2047: bipush #48
    //   2049: ldc 1107820800
    //   2051: iastore
    //   2052: dup
    //   2053: bipush #49
    //   2055: ldc 524544
    //   2057: iastore
    //   2058: dup
    //   2059: bipush #50
    //   2061: ldc 1107296256
    //   2063: iastore
    //   2064: dup
    //   2065: bipush #51
    //   2067: ldc 1107820800
    //   2069: iastore
    //   2070: dup
    //   2071: bipush #52
    //   2073: ldc 34078720
    //   2075: iastore
    //   2076: dup
    //   2077: bipush #53
    //   2079: iconst_0
    //   2080: iastore
    //   2081: dup
    //   2082: bipush #54
    //   2084: ldc 1074266112
    //   2086: iastore
    //   2087: dup
    //   2088: bipush #55
    //   2090: ldc 1107296256
    //   2092: iastore
    //   2093: dup
    //   2094: bipush #56
    //   2096: ldc 524544
    //   2098: iastore
    //   2099: dup
    //   2100: bipush #57
    //   2102: ldc 33554688
    //   2104: iastore
    //   2105: dup
    //   2106: bipush #58
    //   2108: ldc 1073742080
    //   2110: iastore
    //   2111: dup
    //   2112: bipush #59
    //   2114: ldc 524288
    //   2116: iastore
    //   2117: dup
    //   2118: bipush #60
    //   2120: iconst_0
    //   2121: iastore
    //   2122: dup
    //   2123: bipush #61
    //   2125: ldc 1074266112
    //   2127: iastore
    //   2128: dup
    //   2129: bipush #62
    //   2131: ldc 34078976
    //   2133: iastore
    //   2134: dup
    //   2135: bipush #63
    //   2137: ldc 1073742080
    //   2139: iastore
    //   2140: astore #10
    //   2142: bipush #64
    //   2144: newarray int
    //   2146: dup
    //   2147: iconst_0
    //   2148: ldc 536870928
    //   2150: iastore
    //   2151: dup
    //   2152: iconst_1
    //   2153: ldc 541065216
    //   2155: iastore
    //   2156: dup
    //   2157: iconst_2
    //   2158: sipush #16384
    //   2161: iastore
    //   2162: dup
    //   2163: iconst_3
    //   2164: ldc 541081616
    //   2166: iastore
    //   2167: dup
    //   2168: iconst_4
    //   2169: ldc 541065216
    //   2171: iastore
    //   2172: dup
    //   2173: iconst_5
    //   2174: bipush #16
    //   2176: iastore
    //   2177: dup
    //   2178: bipush #6
    //   2180: ldc 541081616
    //   2182: iastore
    //   2183: dup
    //   2184: bipush #7
    //   2186: ldc 4194304
    //   2188: iastore
    //   2189: dup
    //   2190: bipush #8
    //   2192: ldc 536887296
    //   2194: iastore
    //   2195: dup
    //   2196: bipush #9
    //   2198: ldc 4210704
    //   2200: iastore
    //   2201: dup
    //   2202: bipush #10
    //   2204: ldc 4194304
    //   2206: iastore
    //   2207: dup
    //   2208: bipush #11
    //   2210: ldc 536870928
    //   2212: iastore
    //   2213: dup
    //   2214: bipush #12
    //   2216: ldc 4194320
    //   2218: iastore
    //   2219: dup
    //   2220: bipush #13
    //   2222: ldc 536887296
    //   2224: iastore
    //   2225: dup
    //   2226: bipush #14
    //   2228: ldc 536870912
    //   2230: iastore
    //   2231: dup
    //   2232: bipush #15
    //   2234: sipush #16400
    //   2237: iastore
    //   2238: dup
    //   2239: bipush #16
    //   2241: iconst_0
    //   2242: iastore
    //   2243: dup
    //   2244: bipush #17
    //   2246: ldc 4194320
    //   2248: iastore
    //   2249: dup
    //   2250: bipush #18
    //   2252: ldc 536887312
    //   2254: iastore
    //   2255: dup
    //   2256: bipush #19
    //   2258: sipush #16384
    //   2261: iastore
    //   2262: dup
    //   2263: bipush #20
    //   2265: ldc 4210688
    //   2267: iastore
    //   2268: dup
    //   2269: bipush #21
    //   2271: ldc 536887312
    //   2273: iastore
    //   2274: dup
    //   2275: bipush #22
    //   2277: bipush #16
    //   2279: iastore
    //   2280: dup
    //   2281: bipush #23
    //   2283: ldc 541065232
    //   2285: iastore
    //   2286: dup
    //   2287: bipush #24
    //   2289: ldc 541065232
    //   2291: iastore
    //   2292: dup
    //   2293: bipush #25
    //   2295: iconst_0
    //   2296: iastore
    //   2297: dup
    //   2298: bipush #26
    //   2300: ldc 4210704
    //   2302: iastore
    //   2303: dup
    //   2304: bipush #27
    //   2306: ldc 541081600
    //   2308: iastore
    //   2309: dup
    //   2310: bipush #28
    //   2312: sipush #16400
    //   2315: iastore
    //   2316: dup
    //   2317: bipush #29
    //   2319: ldc 4210688
    //   2321: iastore
    //   2322: dup
    //   2323: bipush #30
    //   2325: ldc 541081600
    //   2327: iastore
    //   2328: dup
    //   2329: bipush #31
    //   2331: ldc 536870912
    //   2333: iastore
    //   2334: dup
    //   2335: bipush #32
    //   2337: ldc 536887296
    //   2339: iastore
    //   2340: dup
    //   2341: bipush #33
    //   2343: bipush #16
    //   2345: iastore
    //   2346: dup
    //   2347: bipush #34
    //   2349: ldc 541065232
    //   2351: iastore
    //   2352: dup
    //   2353: bipush #35
    //   2355: ldc 4210688
    //   2357: iastore
    //   2358: dup
    //   2359: bipush #36
    //   2361: ldc 541081616
    //   2363: iastore
    //   2364: dup
    //   2365: bipush #37
    //   2367: ldc 4194304
    //   2369: iastore
    //   2370: dup
    //   2371: bipush #38
    //   2373: sipush #16400
    //   2376: iastore
    //   2377: dup
    //   2378: bipush #39
    //   2380: ldc 536870928
    //   2382: iastore
    //   2383: dup
    //   2384: bipush #40
    //   2386: ldc 4194304
    //   2388: iastore
    //   2389: dup
    //   2390: bipush #41
    //   2392: ldc 536887296
    //   2394: iastore
    //   2395: dup
    //   2396: bipush #42
    //   2398: ldc 536870912
    //   2400: iastore
    //   2401: dup
    //   2402: bipush #43
    //   2404: sipush #16400
    //   2407: iastore
    //   2408: dup
    //   2409: bipush #44
    //   2411: ldc 536870928
    //   2413: iastore
    //   2414: dup
    //   2415: bipush #45
    //   2417: ldc 541081616
    //   2419: iastore
    //   2420: dup
    //   2421: bipush #46
    //   2423: ldc 4210688
    //   2425: iastore
    //   2426: dup
    //   2427: bipush #47
    //   2429: ldc 541065216
    //   2431: iastore
    //   2432: dup
    //   2433: bipush #48
    //   2435: ldc 4210704
    //   2437: iastore
    //   2438: dup
    //   2439: bipush #49
    //   2441: ldc 541081600
    //   2443: iastore
    //   2444: dup
    //   2445: bipush #50
    //   2447: iconst_0
    //   2448: iastore
    //   2449: dup
    //   2450: bipush #51
    //   2452: ldc 541065232
    //   2454: iastore
    //   2455: dup
    //   2456: bipush #52
    //   2458: bipush #16
    //   2460: iastore
    //   2461: dup
    //   2462: bipush #53
    //   2464: sipush #16384
    //   2467: iastore
    //   2468: dup
    //   2469: bipush #54
    //   2471: ldc 541065216
    //   2473: iastore
    //   2474: dup
    //   2475: bipush #55
    //   2477: ldc 4210704
    //   2479: iastore
    //   2480: dup
    //   2481: bipush #56
    //   2483: sipush #16384
    //   2486: iastore
    //   2487: dup
    //   2488: bipush #57
    //   2490: ldc 4194320
    //   2492: iastore
    //   2493: dup
    //   2494: bipush #58
    //   2496: ldc 536887312
    //   2498: iastore
    //   2499: dup
    //   2500: bipush #59
    //   2502: iconst_0
    //   2503: iastore
    //   2504: dup
    //   2505: bipush #60
    //   2507: ldc 541081600
    //   2509: iastore
    //   2510: dup
    //   2511: bipush #61
    //   2513: ldc 536870912
    //   2515: iastore
    //   2516: dup
    //   2517: bipush #62
    //   2519: ldc 4194320
    //   2521: iastore
    //   2522: dup
    //   2523: bipush #63
    //   2525: ldc 536887312
    //   2527: iastore
    //   2528: astore #11
    //   2530: bipush #64
    //   2532: newarray int
    //   2534: dup
    //   2535: iconst_0
    //   2536: ldc 2097152
    //   2538: iastore
    //   2539: dup
    //   2540: iconst_1
    //   2541: ldc 69206018
    //   2543: iastore
    //   2544: dup
    //   2545: iconst_2
    //   2546: ldc 67110914
    //   2548: iastore
    //   2549: dup
    //   2550: iconst_3
    //   2551: iconst_0
    //   2552: iastore
    //   2553: dup
    //   2554: iconst_4
    //   2555: sipush #2048
    //   2558: iastore
    //   2559: dup
    //   2560: iconst_5
    //   2561: ldc 67110914
    //   2563: iastore
    //   2564: dup
    //   2565: bipush #6
    //   2567: ldc 2099202
    //   2569: iastore
    //   2570: dup
    //   2571: bipush #7
    //   2573: ldc 69208064
    //   2575: iastore
    //   2576: dup
    //   2577: bipush #8
    //   2579: ldc 69208066
    //   2581: iastore
    //   2582: dup
    //   2583: bipush #9
    //   2585: ldc 2097152
    //   2587: iastore
    //   2588: dup
    //   2589: bipush #10
    //   2591: iconst_0
    //   2592: iastore
    //   2593: dup
    //   2594: bipush #11
    //   2596: ldc 67108866
    //   2598: iastore
    //   2599: dup
    //   2600: bipush #12
    //   2602: iconst_2
    //   2603: iastore
    //   2604: dup
    //   2605: bipush #13
    //   2607: ldc 67108864
    //   2609: iastore
    //   2610: dup
    //   2611: bipush #14
    //   2613: ldc 69206018
    //   2615: iastore
    //   2616: dup
    //   2617: bipush #15
    //   2619: sipush #2050
    //   2622: iastore
    //   2623: dup
    //   2624: bipush #16
    //   2626: ldc 67110912
    //   2628: iastore
    //   2629: dup
    //   2630: bipush #17
    //   2632: ldc 2099202
    //   2634: iastore
    //   2635: dup
    //   2636: bipush #18
    //   2638: ldc 2097154
    //   2640: iastore
    //   2641: dup
    //   2642: bipush #19
    //   2644: ldc 67110912
    //   2646: iastore
    //   2647: dup
    //   2648: bipush #20
    //   2650: ldc 67108866
    //   2652: iastore
    //   2653: dup
    //   2654: bipush #21
    //   2656: ldc 69206016
    //   2658: iastore
    //   2659: dup
    //   2660: bipush #22
    //   2662: ldc 69208064
    //   2664: iastore
    //   2665: dup
    //   2666: bipush #23
    //   2668: ldc 2097154
    //   2670: iastore
    //   2671: dup
    //   2672: bipush #24
    //   2674: ldc 69206016
    //   2676: iastore
    //   2677: dup
    //   2678: bipush #25
    //   2680: sipush #2048
    //   2683: iastore
    //   2684: dup
    //   2685: bipush #26
    //   2687: sipush #2050
    //   2690: iastore
    //   2691: dup
    //   2692: bipush #27
    //   2694: ldc 69208066
    //   2696: iastore
    //   2697: dup
    //   2698: bipush #28
    //   2700: ldc 2099200
    //   2702: iastore
    //   2703: dup
    //   2704: bipush #29
    //   2706: iconst_2
    //   2707: iastore
    //   2708: dup
    //   2709: bipush #30
    //   2711: ldc 67108864
    //   2713: iastore
    //   2714: dup
    //   2715: bipush #31
    //   2717: ldc 2099200
    //   2719: iastore
    //   2720: dup
    //   2721: bipush #32
    //   2723: ldc 67108864
    //   2725: iastore
    //   2726: dup
    //   2727: bipush #33
    //   2729: ldc 2099200
    //   2731: iastore
    //   2732: dup
    //   2733: bipush #34
    //   2735: ldc 2097152
    //   2737: iastore
    //   2738: dup
    //   2739: bipush #35
    //   2741: ldc 67110914
    //   2743: iastore
    //   2744: dup
    //   2745: bipush #36
    //   2747: ldc 67110914
    //   2749: iastore
    //   2750: dup
    //   2751: bipush #37
    //   2753: ldc 69206018
    //   2755: iastore
    //   2756: dup
    //   2757: bipush #38
    //   2759: ldc 69206018
    //   2761: iastore
    //   2762: dup
    //   2763: bipush #39
    //   2765: iconst_2
    //   2766: iastore
    //   2767: dup
    //   2768: bipush #40
    //   2770: ldc 2097154
    //   2772: iastore
    //   2773: dup
    //   2774: bipush #41
    //   2776: ldc 67108864
    //   2778: iastore
    //   2779: dup
    //   2780: bipush #42
    //   2782: ldc 67110912
    //   2784: iastore
    //   2785: dup
    //   2786: bipush #43
    //   2788: ldc 2097152
    //   2790: iastore
    //   2791: dup
    //   2792: bipush #44
    //   2794: ldc 69208064
    //   2796: iastore
    //   2797: dup
    //   2798: bipush #45
    //   2800: sipush #2050
    //   2803: iastore
    //   2804: dup
    //   2805: bipush #46
    //   2807: ldc 2099202
    //   2809: iastore
    //   2810: dup
    //   2811: bipush #47
    //   2813: ldc 69208064
    //   2815: iastore
    //   2816: dup
    //   2817: bipush #48
    //   2819: sipush #2050
    //   2822: iastore
    //   2823: dup
    //   2824: bipush #49
    //   2826: ldc 67108866
    //   2828: iastore
    //   2829: dup
    //   2830: bipush #50
    //   2832: ldc 69208066
    //   2834: iastore
    //   2835: dup
    //   2836: bipush #51
    //   2838: ldc 69206016
    //   2840: iastore
    //   2841: dup
    //   2842: bipush #52
    //   2844: ldc 2099200
    //   2846: iastore
    //   2847: dup
    //   2848: bipush #53
    //   2850: iconst_0
    //   2851: iastore
    //   2852: dup
    //   2853: bipush #54
    //   2855: iconst_2
    //   2856: iastore
    //   2857: dup
    //   2858: bipush #55
    //   2860: ldc 69208066
    //   2862: iastore
    //   2863: dup
    //   2864: bipush #56
    //   2866: iconst_0
    //   2867: iastore
    //   2868: dup
    //   2869: bipush #57
    //   2871: ldc 2099202
    //   2873: iastore
    //   2874: dup
    //   2875: bipush #58
    //   2877: ldc 69206016
    //   2879: iastore
    //   2880: dup
    //   2881: bipush #59
    //   2883: sipush #2048
    //   2886: iastore
    //   2887: dup
    //   2888: bipush #60
    //   2890: ldc 67108866
    //   2892: iastore
    //   2893: dup
    //   2894: bipush #61
    //   2896: ldc 67110912
    //   2898: iastore
    //   2899: dup
    //   2900: bipush #62
    //   2902: sipush #2048
    //   2905: iastore
    //   2906: dup
    //   2907: bipush #63
    //   2909: ldc 2097154
    //   2911: iastore
    //   2912: astore #12
    //   2914: bipush #64
    //   2916: newarray int
    //   2918: dup
    //   2919: iconst_0
    //   2920: ldc 268439616
    //   2922: iastore
    //   2923: dup
    //   2924: iconst_1
    //   2925: sipush #4096
    //   2928: iastore
    //   2929: dup
    //   2930: iconst_2
    //   2931: ldc 262144
    //   2933: iastore
    //   2934: dup
    //   2935: iconst_3
    //   2936: ldc 268701760
    //   2938: iastore
    //   2939: dup
    //   2940: iconst_4
    //   2941: ldc 268435456
    //   2943: iastore
    //   2944: dup
    //   2945: iconst_5
    //   2946: ldc 268439616
    //   2948: iastore
    //   2949: dup
    //   2950: bipush #6
    //   2952: bipush #64
    //   2954: iastore
    //   2955: dup
    //   2956: bipush #7
    //   2958: ldc 268435456
    //   2960: iastore
    //   2961: dup
    //   2962: bipush #8
    //   2964: ldc 262208
    //   2966: iastore
    //   2967: dup
    //   2968: bipush #9
    //   2970: ldc 268697600
    //   2972: iastore
    //   2973: dup
    //   2974: bipush #10
    //   2976: ldc 268701760
    //   2978: iastore
    //   2979: dup
    //   2980: bipush #11
    //   2982: ldc 266240
    //   2984: iastore
    //   2985: dup
    //   2986: bipush #12
    //   2988: ldc 268701696
    //   2990: iastore
    //   2991: dup
    //   2992: bipush #13
    //   2994: ldc 266304
    //   2996: iastore
    //   2997: dup
    //   2998: bipush #14
    //   3000: sipush #4096
    //   3003: iastore
    //   3004: dup
    //   3005: bipush #15
    //   3007: bipush #64
    //   3009: iastore
    //   3010: dup
    //   3011: bipush #16
    //   3013: ldc 268697600
    //   3015: iastore
    //   3016: dup
    //   3017: bipush #17
    //   3019: ldc 268435520
    //   3021: iastore
    //   3022: dup
    //   3023: bipush #18
    //   3025: ldc 268439552
    //   3027: iastore
    //   3028: dup
    //   3029: bipush #19
    //   3031: sipush #4160
    //   3034: iastore
    //   3035: dup
    //   3036: bipush #20
    //   3038: ldc 266240
    //   3040: iastore
    //   3041: dup
    //   3042: bipush #21
    //   3044: ldc 262208
    //   3046: iastore
    //   3047: dup
    //   3048: bipush #22
    //   3050: ldc 268697664
    //   3052: iastore
    //   3053: dup
    //   3054: bipush #23
    //   3056: ldc 268701696
    //   3058: iastore
    //   3059: dup
    //   3060: bipush #24
    //   3062: sipush #4160
    //   3065: iastore
    //   3066: dup
    //   3067: bipush #25
    //   3069: iconst_0
    //   3070: iastore
    //   3071: dup
    //   3072: bipush #26
    //   3074: iconst_0
    //   3075: iastore
    //   3076: dup
    //   3077: bipush #27
    //   3079: ldc 268697664
    //   3081: iastore
    //   3082: dup
    //   3083: bipush #28
    //   3085: ldc 268435520
    //   3087: iastore
    //   3088: dup
    //   3089: bipush #29
    //   3091: ldc 268439552
    //   3093: iastore
    //   3094: dup
    //   3095: bipush #30
    //   3097: ldc 266304
    //   3099: iastore
    //   3100: dup
    //   3101: bipush #31
    //   3103: ldc 262144
    //   3105: iastore
    //   3106: dup
    //   3107: bipush #32
    //   3109: ldc 266304
    //   3111: iastore
    //   3112: dup
    //   3113: bipush #33
    //   3115: ldc 262144
    //   3117: iastore
    //   3118: dup
    //   3119: bipush #34
    //   3121: ldc 268701696
    //   3123: iastore
    //   3124: dup
    //   3125: bipush #35
    //   3127: sipush #4096
    //   3130: iastore
    //   3131: dup
    //   3132: bipush #36
    //   3134: bipush #64
    //   3136: iastore
    //   3137: dup
    //   3138: bipush #37
    //   3140: ldc 268697664
    //   3142: iastore
    //   3143: dup
    //   3144: bipush #38
    //   3146: sipush #4096
    //   3149: iastore
    //   3150: dup
    //   3151: bipush #39
    //   3153: ldc 266304
    //   3155: iastore
    //   3156: dup
    //   3157: bipush #40
    //   3159: ldc 268439552
    //   3161: iastore
    //   3162: dup
    //   3163: bipush #41
    //   3165: bipush #64
    //   3167: iastore
    //   3168: dup
    //   3169: bipush #42
    //   3171: ldc 268435520
    //   3173: iastore
    //   3174: dup
    //   3175: bipush #43
    //   3177: ldc 268697600
    //   3179: iastore
    //   3180: dup
    //   3181: bipush #44
    //   3183: ldc 268697664
    //   3185: iastore
    //   3186: dup
    //   3187: bipush #45
    //   3189: ldc 268435456
    //   3191: iastore
    //   3192: dup
    //   3193: bipush #46
    //   3195: ldc 262144
    //   3197: iastore
    //   3198: dup
    //   3199: bipush #47
    //   3201: ldc 268439616
    //   3203: iastore
    //   3204: dup
    //   3205: bipush #48
    //   3207: iconst_0
    //   3208: iastore
    //   3209: dup
    //   3210: bipush #49
    //   3212: ldc 268701760
    //   3214: iastore
    //   3215: dup
    //   3216: bipush #50
    //   3218: ldc 262208
    //   3220: iastore
    //   3221: dup
    //   3222: bipush #51
    //   3224: ldc 268435520
    //   3226: iastore
    //   3227: dup
    //   3228: bipush #52
    //   3230: ldc 268697600
    //   3232: iastore
    //   3233: dup
    //   3234: bipush #53
    //   3236: ldc 268439552
    //   3238: iastore
    //   3239: dup
    //   3240: bipush #54
    //   3242: ldc 268439616
    //   3244: iastore
    //   3245: dup
    //   3246: bipush #55
    //   3248: iconst_0
    //   3249: iastore
    //   3250: dup
    //   3251: bipush #56
    //   3253: ldc 268701760
    //   3255: iastore
    //   3256: dup
    //   3257: bipush #57
    //   3259: ldc 266240
    //   3261: iastore
    //   3262: dup
    //   3263: bipush #58
    //   3265: ldc 266240
    //   3267: iastore
    //   3268: dup
    //   3269: bipush #59
    //   3271: sipush #4160
    //   3274: iastore
    //   3275: dup
    //   3276: bipush #60
    //   3278: sipush #4160
    //   3281: iastore
    //   3282: dup
    //   3283: bipush #61
    //   3285: ldc 262208
    //   3287: iastore
    //   3288: dup
    //   3289: bipush #62
    //   3291: ldc 268435456
    //   3293: iastore
    //   3294: dup
    //   3295: bipush #63
    //   3297: ldc 268701696
    //   3299: iastore
    //   3300: astore #13
    //   3302: aload_3
    //   3303: arraylength
    //   3304: istore #14
    //   3306: iload #14
    //   3308: bipush #8
    //   3310: irem
    //   3311: ifeq -> 3335
    //   3314: new java/lang/Exception
    //   3317: dup
    //   3318: sipush #-16587
    //   3321: sipush #-24835
    //   3324: invokestatic a : (II)Ljava/lang/String;
    //   3327: invokespecial <init> : (Ljava/lang/String;)V
    //   3330: athrow
    //   3331: invokestatic a : (Ljava/lang/Throwable;)Ljava/lang/Throwable;
    //   3334: athrow
    //   3335: iconst_2
    //   3336: newarray int
    //   3338: astore #15
    //   3340: iload #14
    //   3342: newarray byte
    //   3344: astore #16
    //   3346: iload #14
    //   3348: bipush #8
    //   3350: idiv
    //   3351: istore #17
    //   3353: iconst_0
    //   3354: istore #18
    //   3356: iload #18
    //   3358: iload #17
    //   3360: if_icmpge -> 4274
    //   3363: iload #18
    //   3365: bipush #8
    //   3367: imul
    //   3368: istore #19
    //   3370: iconst_0
    //   3371: istore #20
    //   3373: iload #20
    //   3375: iconst_2
    //   3376: if_icmpge -> 3461
    //   3379: aload #15
    //   3381: iload #20
    //   3383: aload_3
    //   3384: iload #19
    //   3386: iload #20
    //   3388: iconst_4
    //   3389: imul
    //   3390: iadd
    //   3391: baload
    //   3392: sipush #255
    //   3395: iand
    //   3396: bipush #24
    //   3398: ishl
    //   3399: aload_3
    //   3400: iload #19
    //   3402: iload #20
    //   3404: iconst_4
    //   3405: imul
    //   3406: iadd
    //   3407: iconst_1
    //   3408: iadd
    //   3409: baload
    //   3410: sipush #255
    //   3413: iand
    //   3414: bipush #16
    //   3416: ishl
    //   3417: ior
    //   3418: aload_3
    //   3419: iload #19
    //   3421: iload #20
    //   3423: iconst_4
    //   3424: imul
    //   3425: iadd
    //   3426: iconst_2
    //   3427: iadd
    //   3428: baload
    //   3429: sipush #255
    //   3432: iand
    //   3433: bipush #8
    //   3435: ishl
    //   3436: ior
    //   3437: aload_3
    //   3438: iload #19
    //   3440: iload #20
    //   3442: iconst_4
    //   3443: imul
    //   3444: iadd
    //   3445: iconst_3
    //   3446: iadd
    //   3447: baload
    //   3448: sipush #255
    //   3451: iand
    //   3452: ior
    //   3453: iastore
    //   3454: iinc #20, 1
    //   3457: iload_2
    //   3458: ifeq -> 3373
    //   3461: iconst_0
    //   3462: istore #25
    //   3464: aload #15
    //   3466: iconst_0
    //   3467: iaload
    //   3468: istore #23
    //   3470: aload #15
    //   3472: iconst_1
    //   3473: iaload
    //   3474: istore #22
    //   3476: iload #23
    //   3478: iconst_4
    //   3479: iushr
    //   3480: iload #22
    //   3482: ixor
    //   3483: ldc 252645135
    //   3485: iand
    //   3486: istore #21
    //   3488: iload #22
    //   3490: iload #21
    //   3492: ixor
    //   3493: istore #22
    //   3495: iload #23
    //   3497: iload #21
    //   3499: iconst_4
    //   3500: ishl
    //   3501: ixor
    //   3502: istore #23
    //   3504: iload #23
    //   3506: bipush #16
    //   3508: iushr
    //   3509: iload #22
    //   3511: ixor
    //   3512: ldc 65535
    //   3514: iand
    //   3515: istore #21
    //   3517: iload #22
    //   3519: iload #21
    //   3521: ixor
    //   3522: istore #22
    //   3524: iload #23
    //   3526: iload #21
    //   3528: bipush #16
    //   3530: ishl
    //   3531: ixor
    //   3532: istore #23
    //   3534: iload #22
    //   3536: iconst_2
    //   3537: iushr
    //   3538: iload #23
    //   3540: ixor
    //   3541: ldc 858993459
    //   3543: iand
    //   3544: istore #21
    //   3546: iload #23
    //   3548: iload #21
    //   3550: ixor
    //   3551: istore #23
    //   3553: iload #22
    //   3555: iload #21
    //   3557: iconst_2
    //   3558: ishl
    //   3559: ixor
    //   3560: istore #22
    //   3562: iload #22
    //   3564: bipush #8
    //   3566: iushr
    //   3567: iload #23
    //   3569: ixor
    //   3570: ldc 16711935
    //   3572: iand
    //   3573: istore #21
    //   3575: iload #23
    //   3577: iload #21
    //   3579: ixor
    //   3580: istore #23
    //   3582: iload #22
    //   3584: iload #21
    //   3586: bipush #8
    //   3588: ishl
    //   3589: ixor
    //   3590: istore #22
    //   3592: iload #22
    //   3594: iconst_1
    //   3595: ishl
    //   3596: iload #22
    //   3598: bipush #31
    //   3600: iushr
    //   3601: iconst_1
    //   3602: iand
    //   3603: ior
    //   3604: istore #22
    //   3606: iload #23
    //   3608: iload #22
    //   3610: ixor
    //   3611: ldc -1431655766
    //   3613: iand
    //   3614: istore #21
    //   3616: iload #23
    //   3618: iload #21
    //   3620: ixor
    //   3621: istore #23
    //   3623: iload #22
    //   3625: iload #21
    //   3627: ixor
    //   3628: istore #22
    //   3630: iload #23
    //   3632: iconst_1
    //   3633: ishl
    //   3634: iload #23
    //   3636: bipush #31
    //   3638: iushr
    //   3639: iconst_1
    //   3640: iand
    //   3641: ior
    //   3642: istore #23
    //   3644: iconst_0
    //   3645: istore #24
    //   3647: iload #24
    //   3649: bipush #8
    //   3651: if_icmpge -> 3989
    //   3654: iload #22
    //   3656: bipush #28
    //   3658: ishl
    //   3659: iload #22
    //   3661: iconst_4
    //   3662: iushr
    //   3663: ior
    //   3664: istore #21
    //   3666: iload #21
    //   3668: aload #5
    //   3670: iload #25
    //   3672: iinc #25, 1
    //   3675: iaload
    //   3676: ixor
    //   3677: istore #21
    //   3679: aload #12
    //   3681: iload #21
    //   3683: bipush #63
    //   3685: iand
    //   3686: iaload
    //   3687: istore #20
    //   3689: iload #20
    //   3691: aload #10
    //   3693: iload #21
    //   3695: bipush #8
    //   3697: iushr
    //   3698: bipush #63
    //   3700: iand
    //   3701: iaload
    //   3702: ior
    //   3703: istore #20
    //   3705: iload #20
    //   3707: aload #8
    //   3709: iload #21
    //   3711: bipush #16
    //   3713: iushr
    //   3714: bipush #63
    //   3716: iand
    //   3717: iaload
    //   3718: ior
    //   3719: istore #20
    //   3721: iload #20
    //   3723: aload #6
    //   3725: iload #21
    //   3727: bipush #24
    //   3729: iushr
    //   3730: bipush #63
    //   3732: iand
    //   3733: iaload
    //   3734: ior
    //   3735: istore #20
    //   3737: iload #22
    //   3739: aload #5
    //   3741: iload #25
    //   3743: iinc #25, 1
    //   3746: iaload
    //   3747: ixor
    //   3748: istore #21
    //   3750: iload #20
    //   3752: aload #13
    //   3754: iload #21
    //   3756: bipush #63
    //   3758: iand
    //   3759: iaload
    //   3760: ior
    //   3761: istore #20
    //   3763: iload #20
    //   3765: aload #11
    //   3767: iload #21
    //   3769: bipush #8
    //   3771: iushr
    //   3772: bipush #63
    //   3774: iand
    //   3775: iaload
    //   3776: ior
    //   3777: istore #20
    //   3779: iload #20
    //   3781: aload #9
    //   3783: iload #21
    //   3785: bipush #16
    //   3787: iushr
    //   3788: bipush #63
    //   3790: iand
    //   3791: iaload
    //   3792: ior
    //   3793: istore #20
    //   3795: iload #20
    //   3797: aload #7
    //   3799: iload #21
    //   3801: bipush #24
    //   3803: iushr
    //   3804: bipush #63
    //   3806: iand
    //   3807: iaload
    //   3808: ior
    //   3809: istore #20
    //   3811: iload #23
    //   3813: iload #20
    //   3815: ixor
    //   3816: istore #23
    //   3818: iload #23
    //   3820: bipush #28
    //   3822: ishl
    //   3823: iload #23
    //   3825: iconst_4
    //   3826: iushr
    //   3827: ior
    //   3828: istore #21
    //   3830: iload #21
    //   3832: aload #5
    //   3834: iload #25
    //   3836: iinc #25, 1
    //   3839: iaload
    //   3840: ixor
    //   3841: istore #21
    //   3843: aload #12
    //   3845: iload #21
    //   3847: bipush #63
    //   3849: iand
    //   3850: iaload
    //   3851: istore #20
    //   3853: iload #20
    //   3855: aload #10
    //   3857: iload #21
    //   3859: bipush #8
    //   3861: iushr
    //   3862: bipush #63
    //   3864: iand
    //   3865: iaload
    //   3866: ior
    //   3867: istore #20
    //   3869: iload #20
    //   3871: aload #8
    //   3873: iload #21
    //   3875: bipush #16
    //   3877: iushr
    //   3878: bipush #63
    //   3880: iand
    //   3881: iaload
    //   3882: ior
    //   3883: istore #20
    //   3885: iload #20
    //   3887: aload #6
    //   3889: iload #21
    //   3891: bipush #24
    //   3893: iushr
    //   3894: bipush #63
    //   3896: iand
    //   3897: iaload
    //   3898: ior
    //   3899: istore #20
    //   3901: iload #23
    //   3903: aload #5
    //   3905: iload #25
    //   3907: iinc #25, 1
    //   3910: iaload
    //   3911: ixor
    //   3912: istore #21
    //   3914: iload #20
    //   3916: aload #13
    //   3918: iload #21
    //   3920: bipush #63
    //   3922: iand
    //   3923: iaload
    //   3924: ior
    //   3925: istore #20
    //   3927: iload #20
    //   3929: aload #11
    //   3931: iload #21
    //   3933: bipush #8
    //   3935: iushr
    //   3936: bipush #63
    //   3938: iand
    //   3939: iaload
    //   3940: ior
    //   3941: istore #20
    //   3943: iload #20
    //   3945: aload #9
    //   3947: iload #21
    //   3949: bipush #16
    //   3951: iushr
    //   3952: bipush #63
    //   3954: iand
    //   3955: iaload
    //   3956: ior
    //   3957: istore #20
    //   3959: iload #20
    //   3961: aload #7
    //   3963: iload #21
    //   3965: bipush #24
    //   3967: iushr
    //   3968: bipush #63
    //   3970: iand
    //   3971: iaload
    //   3972: ior
    //   3973: istore #20
    //   3975: iload #22
    //   3977: iload #20
    //   3979: ixor
    //   3980: istore #22
    //   3982: iinc #24, 1
    //   3985: iload_2
    //   3986: ifeq -> 3647
    //   3989: iload #22
    //   3991: bipush #31
    //   3993: ishl
    //   3994: iload #22
    //   3996: iconst_1
    //   3997: iushr
    //   3998: ior
    //   3999: istore #22
    //   4001: iload #23
    //   4003: iload #22
    //   4005: ixor
    //   4006: ldc -1431655766
    //   4008: iand
    //   4009: istore #21
    //   4011: iload #23
    //   4013: iload #21
    //   4015: ixor
    //   4016: istore #23
    //   4018: iload #22
    //   4020: iload #21
    //   4022: ixor
    //   4023: istore #22
    //   4025: iload #23
    //   4027: bipush #31
    //   4029: ishl
    //   4030: iload #23
    //   4032: iconst_1
    //   4033: iushr
    //   4034: ior
    //   4035: istore #23
    //   4037: iload #23
    //   4039: bipush #8
    //   4041: iushr
    //   4042: iload #22
    //   4044: ixor
    //   4045: ldc 16711935
    //   4047: iand
    //   4048: istore #21
    //   4050: iload #22
    //   4052: iload #21
    //   4054: ixor
    //   4055: istore #22
    //   4057: iload #23
    //   4059: iload #21
    //   4061: bipush #8
    //   4063: ishl
    //   4064: ixor
    //   4065: istore #23
    //   4067: iload #23
    //   4069: iconst_2
    //   4070: iushr
    //   4071: iload #22
    //   4073: ixor
    //   4074: ldc 858993459
    //   4076: iand
    //   4077: istore #21
    //   4079: iload #22
    //   4081: iload #21
    //   4083: ixor
    //   4084: istore #22
    //   4086: iload #23
    //   4088: iload #21
    //   4090: iconst_2
    //   4091: ishl
    //   4092: ixor
    //   4093: istore #23
    //   4095: iload #22
    //   4097: bipush #16
    //   4099: iushr
    //   4100: iload #23
    //   4102: ixor
    //   4103: ldc 65535
    //   4105: iand
    //   4106: istore #21
    //   4108: iload #23
    //   4110: iload #21
    //   4112: ixor
    //   4113: istore #23
    //   4115: iload #22
    //   4117: iload #21
    //   4119: bipush #16
    //   4121: ishl
    //   4122: ixor
    //   4123: istore #22
    //   4125: iload #22
    //   4127: iconst_4
    //   4128: iushr
    //   4129: iload #23
    //   4131: ixor
    //   4132: ldc 252645135
    //   4134: iand
    //   4135: istore #21
    //   4137: iload #23
    //   4139: iload #21
    //   4141: ixor
    //   4142: istore #23
    //   4144: iload #22
    //   4146: iload #21
    //   4148: iconst_4
    //   4149: ishl
    //   4150: ixor
    //   4151: istore #22
    //   4153: aload #15
    //   4155: iconst_0
    //   4156: iload #22
    //   4158: iastore
    //   4159: aload #15
    //   4161: iconst_1
    //   4162: iload #23
    //   4164: iastore
    //   4165: iload #18
    //   4167: bipush #8
    //   4169: imul
    //   4170: istore #26
    //   4172: iconst_0
    //   4173: istore #27
    //   4175: iload #27
    //   4177: iconst_2
    //   4178: if_icmpge -> 4267
    //   4181: aload #16
    //   4183: iload #26
    //   4185: iload #27
    //   4187: iconst_4
    //   4188: imul
    //   4189: iadd
    //   4190: aload #15
    //   4192: iload #27
    //   4194: iaload
    //   4195: bipush #24
    //   4197: iushr
    //   4198: i2b
    //   4199: bastore
    //   4200: aload #16
    //   4202: iload #26
    //   4204: iload #27
    //   4206: iconst_4
    //   4207: imul
    //   4208: iadd
    //   4209: iconst_1
    //   4210: iadd
    //   4211: aload #15
    //   4213: iload #27
    //   4215: iaload
    //   4216: bipush #16
    //   4218: iushr
    //   4219: i2b
    //   4220: bastore
    //   4221: aload #16
    //   4223: iload #26
    //   4225: iload #27
    //   4227: iconst_4
    //   4228: imul
    //   4229: iadd
    //   4230: iconst_2
    //   4231: iadd
    //   4232: aload #15
    //   4234: iload #27
    //   4236: iaload
    //   4237: bipush #8
    //   4239: iushr
    //   4240: i2b
    //   4241: bastore
    //   4242: aload #16
    //   4244: iload #26
    //   4246: iload #27
    //   4248: iconst_4
    //   4249: imul
    //   4250: iadd
    //   4251: iconst_3
    //   4252: iadd
    //   4253: aload #15
    //   4255: iload #27
    //   4257: iaload
    //   4258: i2b
    //   4259: bastore
    //   4260: iinc #27, 1
    //   4263: iload_2
    //   4264: ifeq -> 4175
    //   4267: iinc #18, 1
    //   4270: iload_2
    //   4271: ifeq -> 3356
    //   4274: aload #16
    //   4276: aload #16
    //   4278: arraylength
    //   4279: iconst_1
    //   4280: isub
    //   4281: baload
    //   4282: istore #18
    //   4284: aload #16
    //   4286: arraylength
    //   4287: iload #18
    //   4289: isub
    //   4290: newarray byte
    //   4292: astore #4
    //   4294: aload #16
    //   4296: arraylength
    //   4297: aload #4
    //   4299: arraylength
    //   4300: if_icmpge -> 4324
    //   4303: new java/lang/Exception
    //   4306: dup
    //   4307: sipush #-16585
    //   4310: sipush #-8261
    //   4313: invokestatic a : (II)Ljava/lang/String;
    //   4316: invokespecial <init> : (Ljava/lang/String;)V
    //   4319: athrow
    //   4320: invokestatic a : (Ljava/lang/Throwable;)Ljava/lang/Throwable;
    //   4323: athrow
    //   4324: iconst_0
    //   4325: istore #19
    //   4327: iload #19
    //   4329: aload #4
    //   4331: arraylength
    //   4332: if_icmpge -> 4352
    //   4335: aload #4
    //   4337: iload #19
    //   4339: aload #16
    //   4341: iload #19
    //   4343: baload
    //   4344: bastore
    //   4345: iinc #19, 1
    //   4348: iload_2
    //   4349: ifeq -> 4327
    //   4352: new java/math/BigInteger
    //   4355: dup
    //   4356: aload #4
    //   4358: invokespecial <init> : ([B)V
    //   4361: invokevirtual abs : ()Ljava/math/BigInteger;
    //   4364: putstatic burp/Zm0s.Zl : Ljava/lang/Object;
    //   4367: new java/io/ByteArrayOutputStream
    //   4370: dup
    //   4371: invokespecial <init> : ()V
    //   4374: astore_3
    //   4375: getstatic burp/Zllw.Zg : Ljava/lang/String;
    //   4378: astore #4
    //   4380: iconst_0
    //   4381: istore #5
    //   4383: iload #5
    //   4385: aload #4
    //   4387: invokevirtual length : ()I
    //   4390: if_icmpge -> 4420
    //   4393: aload_3
    //   4394: aload #4
    //   4396: iload #5
    //   4398: iload #5
    //   4400: iconst_2
    //   4401: iadd
    //   4402: invokevirtual substring : (II)Ljava/lang/String;
    //   4405: bipush #16
    //   4407: invokestatic parseInt : (Ljava/lang/String;I)I
    //   4410: invokevirtual write : (I)V
    //   4413: iinc #5, 2
    //   4416: iload_2
    //   4417: ifeq -> 4383
    //   4420: aload_3
    //   4421: invokevirtual toByteArray : ()[B
    //   4424: astore #5
    //   4426: getstatic burp/Zlv6.ZN : Ljava/lang/Object;
    //   4429: checkcast java/math/BigInteger
    //   4432: invokevirtual toByteArray : ()[B
    //   4435: astore #6
    //   4437: sipush #256
    //   4440: newarray byte
    //   4442: astore #8
    //   4444: sipush #256
    //   4447: newarray int
    //   4449: astore #9
    //   4451: sipush #256
    //   4454: newarray int
    //   4456: astore #10
    //   4458: sipush #256
    //   4461: newarray int
    //   4463: astore #11
    //   4465: sipush #256
    //   4468: newarray int
    //   4470: astore #12
    //   4472: bipush #10
    //   4474: newarray int
    //   4476: astore #13
    //   4478: sipush #283
    //   4481: istore #14
    //   4483: iconst_0
    //   4484: istore #16
    //   4486: iload #16
    //   4488: sipush #256
    //   4491: if_icmpge -> 4725
    //   4494: sipush #-16581
    //   4497: sipush #-8999
    //   4500: invokestatic a : (II)Ljava/lang/String;
    //   4503: iload #16
    //   4505: iconst_1
    //   4506: iushr
    //   4507: invokevirtual charAt : (I)C
    //   4510: istore #25
    //   4512: iload #16
    //   4514: iconst_1
    //   4515: iand
    //   4516: ifne -> 4531
    //   4519: iload #25
    //   4521: bipush #8
    //   4523: iushr
    //   4524: goto -> 4533
    //   4527: invokestatic a : (Ljava/lang/Throwable;)Ljava/lang/Throwable;
    //   4530: athrow
    //   4531: iload #25
    //   4533: i2b
    //   4534: sipush #255
    //   4537: iand
    //   4538: istore #15
    //   4540: iload #16
    //   4542: iconst_1
    //   4543: ishl
    //   4544: istore #17
    //   4546: iload #17
    //   4548: sipush #256
    //   4551: if_icmplt -> 4561
    //   4554: iload #17
    //   4556: iload #14
    //   4558: ixor
    //   4559: istore #17
    //   4561: iload #17
    //   4563: iconst_1
    //   4564: ishl
    //   4565: istore #18
    //   4567: iload #18
    //   4569: sipush #256
    //   4572: if_icmplt -> 4582
    //   4575: iload #18
    //   4577: iload #14
    //   4579: ixor
    //   4580: istore #18
    //   4582: iload #18
    //   4584: iconst_1
    //   4585: ishl
    //   4586: istore #19
    //   4588: iload #19
    //   4590: sipush #256
    //   4593: if_icmplt -> 4603
    //   4596: iload #19
    //   4598: iload #14
    //   4600: ixor
    //   4601: istore #19
    //   4603: iload #19
    //   4605: iload #16
    //   4607: ixor
    //   4608: istore #20
    //   4610: iload #20
    //   4612: iload #17
    //   4614: ixor
    //   4615: istore #21
    //   4617: iload #20
    //   4619: iload #18
    //   4621: ixor
    //   4622: istore #22
    //   4624: iload #19
    //   4626: iload #18
    //   4628: ixor
    //   4629: iload #17
    //   4631: ixor
    //   4632: istore #23
    //   4634: aload #8
    //   4636: iload #16
    //   4638: iload #15
    //   4640: i2b
    //   4641: bastore
    //   4642: aload #9
    //   4644: iload #15
    //   4646: iload #23
    //   4648: bipush #24
    //   4650: ishl
    //   4651: iload #20
    //   4653: bipush #16
    //   4655: ishl
    //   4656: ior
    //   4657: iload #22
    //   4659: bipush #8
    //   4661: ishl
    //   4662: ior
    //   4663: iload #21
    //   4665: ior
    //   4666: dup
    //   4667: istore #24
    //   4669: iastore
    //   4670: aload #10
    //   4672: iload #15
    //   4674: iload #24
    //   4676: bipush #8
    //   4678: iushr
    //   4679: iload #24
    //   4681: bipush #24
    //   4683: ishl
    //   4684: ior
    //   4685: iastore
    //   4686: aload #11
    //   4688: iload #15
    //   4690: iload #24
    //   4692: bipush #16
    //   4694: iushr
    //   4695: iload #24
    //   4697: bipush #16
    //   4699: ishl
    //   4700: ior
    //   4701: iastore
    //   4702: aload #12
    //   4704: iload #15
    //   4706: iload #24
    //   4708: bipush #24
    //   4710: iushr
    //   4711: iload #24
    //   4713: bipush #8
    //   4715: ishl
    //   4716: ior
    //   4717: iastore
    //   4718: iinc #16, 1
    //   4721: iload_2
    //   4722: ifeq -> 4486
    //   4725: iconst_1
    //   4726: istore #25
    //   4728: aload #13
    //   4730: iconst_0
    //   4731: iload #25
    //   4733: bipush #24
    //   4735: ishl
    //   4736: iastore
    //   4737: iconst_1
    //   4738: istore #26
    //   4740: iload #26
    //   4742: bipush #10
    //   4744: if_icmpge -> 4785
    //   4747: iload #25
    //   4749: iconst_1
    //   4750: ishl
    //   4751: istore #25
    //   4753: iload #25
    //   4755: sipush #256
    //   4758: if_icmplt -> 4768
    //   4761: iload #25
    //   4763: iload #14
    //   4765: ixor
    //   4766: istore #25
    //   4768: aload #13
    //   4770: iload #26
    //   4772: iload #25
    //   4774: bipush #24
    //   4776: ishl
    //   4777: iastore
    //   4778: iinc #26, 1
    //   4781: iload_2
    //   4782: ifeq -> 4740
    //   4785: iconst_4
    //   4786: istore #26
    //   4788: iload #26
    //   4790: bipush #6
    //   4792: iadd
    //   4793: istore #27
    //   4795: iconst_4
    //   4796: iload #27
    //   4798: iconst_1
    //   4799: iadd
    //   4800: imul
    //   4801: istore #28
    //   4803: iload #28
    //   4805: newarray int
    //   4807: astore #29
    //   4809: iload #28
    //   4811: newarray int
    //   4813: astore #30
    //   4815: iconst_0
    //   4816: istore #25
    //   4818: iconst_0
    //   4819: istore #32
    //   4821: iconst_0
    //   4822: istore #33
    //   4824: iload #32
    //   4826: iload #26
    //   4828: if_icmpge -> 4896
    //   4831: aload #29
    //   4833: iload #32
    //   4835: aload #5
    //   4837: iload #33
    //   4839: baload
    //   4840: bipush #24
    //   4842: ishl
    //   4843: aload #5
    //   4845: iload #33
    //   4847: iconst_1
    //   4848: iadd
    //   4849: baload
    //   4850: sipush #255
    //   4853: iand
    //   4854: bipush #16
    //   4856: ishl
    //   4857: ior
    //   4858: aload #5
    //   4860: iload #33
    //   4862: iconst_2
    //   4863: iadd
    //   4864: baload
    //   4865: sipush #255
    //   4868: iand
    //   4869: bipush #8
    //   4871: ishl
    //   4872: ior
    //   4873: aload #5
    //   4875: iload #33
    //   4877: iconst_3
    //   4878: iadd
    //   4879: baload
    //   4880: sipush #255
    //   4883: iand
    //   4884: ior
    //   4885: iastore
    //   4886: iinc #32, 1
    //   4889: iinc #33, 4
    //   4892: iload_2
    //   4893: ifeq -> 4824
    //   4896: iload #26
    //   4898: istore #32
    //   4900: iconst_0
    //   4901: istore #33
    //   4903: iload #32
    //   4905: iload #28
    //   4907: if_icmpge -> 5034
    //   4910: aload #29
    //   4912: iload #32
    //   4914: iconst_1
    //   4915: isub
    //   4916: iaload
    //   4917: istore #31
    //   4919: iload #33
    //   4921: ifne -> 5008
    //   4924: iload #26
    //   4926: istore #33
    //   4928: aload #8
    //   4930: iload #31
    //   4932: bipush #16
    //   4934: iushr
    //   4935: sipush #255
    //   4938: iand
    //   4939: baload
    //   4940: bipush #24
    //   4942: ishl
    //   4943: aload #8
    //   4945: iload #31
    //   4947: bipush #8
    //   4949: iushr
    //   4950: sipush #255
    //   4953: iand
    //   4954: baload
    //   4955: sipush #255
    //   4958: iand
    //   4959: bipush #16
    //   4961: ishl
    //   4962: ior
    //   4963: aload #8
    //   4965: iload #31
    //   4967: sipush #255
    //   4970: iand
    //   4971: baload
    //   4972: sipush #255
    //   4975: iand
    //   4976: bipush #8
    //   4978: ishl
    //   4979: ior
    //   4980: aload #8
    //   4982: iload #31
    //   4984: bipush #24
    //   4986: iushr
    //   4987: baload
    //   4988: sipush #255
    //   4991: iand
    //   4992: ior
    //   4993: istore #31
    //   4995: iload #31
    //   4997: aload #13
    //   4999: iload #25
    //   5001: iinc #25, 1
    //   5004: iaload
    //   5005: ixor
    //   5006: istore #31
    //   5008: aload #29
    //   5010: iload #32
    //   5012: aload #29
    //   5014: iload #32
    //   5016: iload #26
    //   5018: isub
    //   5019: iaload
    //   5020: iload #31
    //   5022: ixor
    //   5023: iastore
    //   5024: iinc #32, 1
    //   5027: iinc #33, -1
    //   5030: iload_2
    //   5031: ifeq -> 4903
    //   5034: iconst_0
    //   5035: istore #32
    //   5037: iconst_4
    //   5038: iload #27
    //   5040: imul
    //   5041: istore #33
    //   5043: aload #30
    //   5045: iload #32
    //   5047: aload #29
    //   5049: iload #33
    //   5051: iaload
    //   5052: iastore
    //   5053: aload #30
    //   5055: iload #32
    //   5057: iconst_1
    //   5058: iadd
    //   5059: aload #29
    //   5061: iload #33
    //   5063: iconst_1
    //   5064: iadd
    //   5065: iaload
    //   5066: iastore
    //   5067: aload #30
    //   5069: iload #32
    //   5071: iconst_2
    //   5072: iadd
    //   5073: aload #29
    //   5075: iload #33
    //   5077: iconst_2
    //   5078: iadd
    //   5079: iaload
    //   5080: iastore
    //   5081: aload #30
    //   5083: iload #32
    //   5085: iconst_3
    //   5086: iadd
    //   5087: aload #29
    //   5089: iload #33
    //   5091: iconst_3
    //   5092: iadd
    //   5093: iaload
    //   5094: iastore
    //   5095: iinc #32, 4
    //   5098: iinc #33, -4
    //   5101: iconst_1
    //   5102: istore #35
    //   5104: iload #35
    //   5106: iload #27
    //   5108: if_icmpge -> 5472
    //   5111: aload #29
    //   5113: iload #33
    //   5115: iaload
    //   5116: istore #34
    //   5118: aload #30
    //   5120: iload #32
    //   5122: aload #9
    //   5124: aload #8
    //   5126: iload #34
    //   5128: bipush #24
    //   5130: iushr
    //   5131: baload
    //   5132: sipush #255
    //   5135: iand
    //   5136: iaload
    //   5137: aload #10
    //   5139: aload #8
    //   5141: iload #34
    //   5143: bipush #16
    //   5145: iushr
    //   5146: sipush #255
    //   5149: iand
    //   5150: baload
    //   5151: sipush #255
    //   5154: iand
    //   5155: iaload
    //   5156: ixor
    //   5157: aload #11
    //   5159: aload #8
    //   5161: iload #34
    //   5163: bipush #8
    //   5165: iushr
    //   5166: sipush #255
    //   5169: iand
    //   5170: baload
    //   5171: sipush #255
    //   5174: iand
    //   5175: iaload
    //   5176: ixor
    //   5177: aload #12
    //   5179: aload #8
    //   5181: iload #34
    //   5183: sipush #255
    //   5186: iand
    //   5187: baload
    //   5188: sipush #255
    //   5191: iand
    //   5192: iaload
    //   5193: ixor
    //   5194: iastore
    //   5195: aload #29
    //   5197: iload #33
    //   5199: iconst_1
    //   5200: iadd
    //   5201: iaload
    //   5202: istore #34
    //   5204: aload #30
    //   5206: iload #32
    //   5208: iconst_1
    //   5209: iadd
    //   5210: aload #9
    //   5212: aload #8
    //   5214: iload #34
    //   5216: bipush #24
    //   5218: iushr
    //   5219: baload
    //   5220: sipush #255
    //   5223: iand
    //   5224: iaload
    //   5225: aload #10
    //   5227: aload #8
    //   5229: iload #34
    //   5231: bipush #16
    //   5233: iushr
    //   5234: sipush #255
    //   5237: iand
    //   5238: baload
    //   5239: sipush #255
    //   5242: iand
    //   5243: iaload
    //   5244: ixor
    //   5245: aload #11
    //   5247: aload #8
    //   5249: iload #34
    //   5251: bipush #8
    //   5253: iushr
    //   5254: sipush #255
    //   5257: iand
    //   5258: baload
    //   5259: sipush #255
    //   5262: iand
    //   5263: iaload
    //   5264: ixor
    //   5265: aload #12
    //   5267: aload #8
    //   5269: iload #34
    //   5271: sipush #255
    //   5274: iand
    //   5275: baload
    //   5276: sipush #255
    //   5279: iand
    //   5280: iaload
    //   5281: ixor
    //   5282: iastore
    //   5283: aload #29
    //   5285: iload #33
    //   5287: iconst_2
    //   5288: iadd
    //   5289: iaload
    //   5290: istore #34
    //   5292: aload #30
    //   5294: iload #32
    //   5296: iconst_2
    //   5297: iadd
    //   5298: aload #9
    //   5300: aload #8
    //   5302: iload #34
    //   5304: bipush #24
    //   5306: iushr
    //   5307: baload
    //   5308: sipush #255
    //   5311: iand
    //   5312: iaload
    //   5313: aload #10
    //   5315: aload #8
    //   5317: iload #34
    //   5319: bipush #16
    //   5321: iushr
    //   5322: sipush #255
    //   5325: iand
    //   5326: baload
    //   5327: sipush #255
    //   5330: iand
    //   5331: iaload
    //   5332: ixor
    //   5333: aload #11
    //   5335: aload #8
    //   5337: iload #34
    //   5339: bipush #8
    //   5341: iushr
    //   5342: sipush #255
    //   5345: iand
    //   5346: baload
    //   5347: sipush #255
    //   5350: iand
    //   5351: iaload
    //   5352: ixor
    //   5353: aload #12
    //   5355: aload #8
    //   5357: iload #34
    //   5359: sipush #255
    //   5362: iand
    //   5363: baload
    //   5364: sipush #255
    //   5367: iand
    //   5368: iaload
    //   5369: ixor
    //   5370: iastore
    //   5371: aload #29
    //   5373: iload #33
    //   5375: iconst_3
    //   5376: iadd
    //   5377: iaload
    //   5378: istore #34
    //   5380: aload #30
    //   5382: iload #32
    //   5384: iconst_3
    //   5385: iadd
    //   5386: aload #9
    //   5388: aload #8
    //   5390: iload #34
    //   5392: bipush #24
    //   5394: iushr
    //   5395: baload
    //   5396: sipush #255
    //   5399: iand
    //   5400: iaload
    //   5401: aload #10
    //   5403: aload #8
    //   5405: iload #34
    //   5407: bipush #16
    //   5409: iushr
    //   5410: sipush #255
    //   5413: iand
    //   5414: baload
    //   5415: sipush #255
    //   5418: iand
    //   5419: iaload
    //   5420: ixor
    //   5421: aload #11
    //   5423: aload #8
    //   5425: iload #34
    //   5427: bipush #8
    //   5429: iushr
    //   5430: sipush #255
    //   5433: iand
    //   5434: baload
    //   5435: sipush #255
    //   5438: iand
    //   5439: iaload
    //   5440: ixor
    //   5441: aload #12
    //   5443: aload #8
    //   5445: iload #34
    //   5447: sipush #255
    //   5450: iand
    //   5451: baload
    //   5452: sipush #255
    //   5455: iand
    //   5456: iaload
    //   5457: ixor
    //   5458: iastore
    //   5459: iinc #32, 4
    //   5462: iinc #33, -4
    //   5465: iinc #35, 1
    //   5468: iload_2
    //   5469: ifeq -> 5104
    //   5472: aload #30
    //   5474: iload #32
    //   5476: aload #29
    //   5478: iload #33
    //   5480: iaload
    //   5481: iastore
    //   5482: aload #30
    //   5484: iload #32
    //   5486: iconst_1
    //   5487: iadd
    //   5488: aload #29
    //   5490: iload #33
    //   5492: iconst_1
    //   5493: iadd
    //   5494: iaload
    //   5495: iastore
    //   5496: aload #30
    //   5498: iload #32
    //   5500: iconst_2
    //   5501: iadd
    //   5502: aload #29
    //   5504: iload #33
    //   5506: iconst_2
    //   5507: iadd
    //   5508: iaload
    //   5509: iastore
    //   5510: aload #30
    //   5512: iload #32
    //   5514: iconst_3
    //   5515: iadd
    //   5516: aload #29
    //   5518: iload #33
    //   5520: iconst_3
    //   5521: iadd
    //   5522: iaload
    //   5523: iastore
    //   5524: iconst_0
    //   5525: newarray byte
    //   5527: astore #35
    //   5529: aload #6
    //   5531: arraylength
    //   5532: bipush #16
    //   5534: irem
    //   5535: ifeq -> 5559
    //   5538: new java/lang/Exception
    //   5541: dup
    //   5542: sipush #-16585
    //   5545: sipush #-8261
    //   5548: invokestatic a : (II)Ljava/lang/String;
    //   5551: invokespecial <init> : (Ljava/lang/String;)V
    //   5554: athrow
    //   5555: invokestatic a : (Ljava/lang/Throwable;)Ljava/lang/Throwable;
    //   5558: athrow
    //   5559: bipush #10
    //   5561: istore #36
    //   5563: sipush #-16584
    //   5566: sipush #256
    //   5569: newarray byte
    //   5571: astore #37
    //   5573: sipush #7368
    //   5576: sipush #256
    //   5579: newarray int
    //   5581: astore #38
    //   5583: sipush #256
    //   5586: newarray int
    //   5588: astore #39
    //   5590: sipush #256
    //   5593: newarray int
    //   5595: astore #40
    //   5597: sipush #256
    //   5600: newarray int
    //   5602: astore #41
    //   5604: sipush #283
    //   5607: istore #14
    //   5609: invokestatic a : (II)Ljava/lang/String;
    //   5612: astore #42
    //   5614: iconst_0
    //   5615: istore #16
    //   5617: iload #16
    //   5619: sipush #256
    //   5622: if_icmpge -> 5849
    //   5625: aload #42
    //   5627: iload #16
    //   5629: iconst_1
    //   5630: iushr
    //   5631: invokevirtual charAt : (I)C
    //   5634: istore #43
    //   5636: iload #16
    //   5638: iconst_1
    //   5639: iand
    //   5640: ifne -> 5655
    //   5643: iload #43
    //   5645: bipush #8
    //   5647: iushr
    //   5648: goto -> 5657
    //   5651: invokestatic a : (Ljava/lang/Throwable;)Ljava/lang/Throwable;
    //   5654: athrow
    //   5655: iload #43
    //   5657: i2b
    //   5658: sipush #255
    //   5661: iand
    //   5662: istore #15
    //   5664: iload #16
    //   5666: iconst_1
    //   5667: ishl
    //   5668: istore #17
    //   5670: iload #17
    //   5672: sipush #256
    //   5675: if_icmplt -> 5685
    //   5678: iload #17
    //   5680: iload #14
    //   5682: ixor
    //   5683: istore #17
    //   5685: iload #17
    //   5687: iconst_1
    //   5688: ishl
    //   5689: istore #18
    //   5691: iload #18
    //   5693: sipush #256
    //   5696: if_icmplt -> 5706
    //   5699: iload #18
    //   5701: iload #14
    //   5703: ixor
    //   5704: istore #18
    //   5706: iload #18
    //   5708: iconst_1
    //   5709: ishl
    //   5710: istore #19
    //   5712: iload #19
    //   5714: sipush #256
    //   5717: if_icmplt -> 5727
    //   5720: iload #19
    //   5722: iload #14
    //   5724: ixor
    //   5725: istore #19
    //   5727: iload #19
    //   5729: iload #16
    //   5731: ixor
    //   5732: istore #20
    //   5734: iload #20
    //   5736: iload #17
    //   5738: ixor
    //   5739: istore #21
    //   5741: iload #20
    //   5743: iload #18
    //   5745: ixor
    //   5746: istore #22
    //   5748: iload #19
    //   5750: iload #18
    //   5752: ixor
    //   5753: iload #17
    //   5755: ixor
    //   5756: istore #23
    //   5758: aload #37
    //   5760: iload #15
    //   5762: iload #16
    //   5764: i2b
    //   5765: bastore
    //   5766: aload #38
    //   5768: iload #15
    //   5770: iload #23
    //   5772: bipush #24
    //   5774: ishl
    //   5775: iload #20
    //   5777: bipush #16
    //   5779: ishl
    //   5780: ior
    //   5781: iload #22
    //   5783: bipush #8
    //   5785: ishl
    //   5786: ior
    //   5787: iload #21
    //   5789: ior
    //   5790: dup
    //   5791: istore #24
    //   5793: iastore
    //   5794: aload #39
    //   5796: iload #15
    //   5798: iload #24
    //   5800: bipush #8
    //   5802: iushr
    //   5803: iload #24
    //   5805: bipush #24
    //   5807: ishl
    //   5808: ior
    //   5809: iastore
    //   5810: aload #40
    //   5812: iload #15
    //   5814: iload #24
    //   5816: bipush #16
    //   5818: iushr
    //   5819: iload #24
    //   5821: bipush #16
    //   5823: ishl
    //   5824: ior
    //   5825: iastore
    //   5826: aload #41
    //   5828: iload #15
    //   5830: iload #24
    //   5832: bipush #24
    //   5834: iushr
    //   5835: iload #24
    //   5837: bipush #8
    //   5839: ishl
    //   5840: ior
    //   5841: iastore
    //   5842: iinc #16, 1
    //   5845: iload_2
    //   5846: ifeq -> 5617
    //   5849: aload #6
    //   5851: arraylength
    //   5852: newarray byte
    //   5854: astore #43
    //   5856: iconst_0
    //   5857: istore #44
    //   5859: iload #44
    //   5861: aload #6
    //   5863: arraylength
    //   5864: bipush #16
    //   5866: idiv
    //   5867: if_icmpge -> 6781
    //   5870: bipush #16
    //   5872: newarray byte
    //   5874: astore #45
    //   5876: bipush #16
    //   5878: newarray byte
    //   5880: astore #46
    //   5882: iconst_0
    //   5883: istore #47
    //   5885: iload #47
    //   5887: bipush #16
    //   5889: if_icmpge -> 5915
    //   5892: aload #45
    //   5894: iload #47
    //   5896: aload #6
    //   5898: iload #47
    //   5900: iload #44
    //   5902: bipush #16
    //   5904: imul
    //   5905: iadd
    //   5906: baload
    //   5907: bastore
    //   5908: iinc #47, 1
    //   5911: iload_2
    //   5912: ifeq -> 5885
    //   5915: iconst_0
    //   5916: istore #47
    //   5918: aload #45
    //   5920: iconst_0
    //   5921: baload
    //   5922: bipush #24
    //   5924: ishl
    //   5925: aload #45
    //   5927: iconst_1
    //   5928: baload
    //   5929: sipush #255
    //   5932: iand
    //   5933: bipush #16
    //   5935: ishl
    //   5936: ior
    //   5937: aload #45
    //   5939: iconst_2
    //   5940: baload
    //   5941: sipush #255
    //   5944: iand
    //   5945: bipush #8
    //   5947: ishl
    //   5948: ior
    //   5949: aload #45
    //   5951: iconst_3
    //   5952: baload
    //   5953: sipush #255
    //   5956: iand
    //   5957: ior
    //   5958: aload #30
    //   5960: iconst_0
    //   5961: iaload
    //   5962: ixor
    //   5963: istore #49
    //   5965: aload #45
    //   5967: iconst_4
    //   5968: baload
    //   5969: bipush #24
    //   5971: ishl
    //   5972: aload #45
    //   5974: iconst_5
    //   5975: baload
    //   5976: sipush #255
    //   5979: iand
    //   5980: bipush #16
    //   5982: ishl
    //   5983: ior
    //   5984: aload #45
    //   5986: bipush #6
    //   5988: baload
    //   5989: sipush #255
    //   5992: iand
    //   5993: bipush #8
    //   5995: ishl
    //   5996: ior
    //   5997: aload #45
    //   5999: bipush #7
    //   6001: baload
    //   6002: sipush #255
    //   6005: iand
    //   6006: ior
    //   6007: aload #30
    //   6009: iconst_1
    //   6010: iaload
    //   6011: ixor
    //   6012: istore #50
    //   6014: aload #45
    //   6016: bipush #8
    //   6018: baload
    //   6019: bipush #24
    //   6021: ishl
    //   6022: aload #45
    //   6024: bipush #9
    //   6026: baload
    //   6027: sipush #255
    //   6030: iand
    //   6031: bipush #16
    //   6033: ishl
    //   6034: ior
    //   6035: aload #45
    //   6037: bipush #10
    //   6039: baload
    //   6040: sipush #255
    //   6043: iand
    //   6044: bipush #8
    //   6046: ishl
    //   6047: ior
    //   6048: aload #45
    //   6050: bipush #11
    //   6052: baload
    //   6053: sipush #255
    //   6056: iand
    //   6057: ior
    //   6058: aload #30
    //   6060: iconst_2
    //   6061: iaload
    //   6062: ixor
    //   6063: istore #51
    //   6065: aload #45
    //   6067: bipush #12
    //   6069: baload
    //   6070: bipush #24
    //   6072: ishl
    //   6073: aload #45
    //   6075: bipush #13
    //   6077: baload
    //   6078: sipush #255
    //   6081: iand
    //   6082: bipush #16
    //   6084: ishl
    //   6085: ior
    //   6086: aload #45
    //   6088: bipush #14
    //   6090: baload
    //   6091: sipush #255
    //   6094: iand
    //   6095: bipush #8
    //   6097: ishl
    //   6098: ior
    //   6099: aload #45
    //   6101: bipush #15
    //   6103: baload
    //   6104: sipush #255
    //   6107: iand
    //   6108: ior
    //   6109: aload #30
    //   6111: iconst_3
    //   6112: iaload
    //   6113: ixor
    //   6114: istore #52
    //   6116: iconst_1
    //   6117: istore #53
    //   6119: iload #53
    //   6121: iload #36
    //   6123: if_icmpge -> 6366
    //   6126: iinc #47, 4
    //   6129: aload #38
    //   6131: iload #49
    //   6133: bipush #24
    //   6135: iushr
    //   6136: iaload
    //   6137: aload #39
    //   6139: iload #52
    //   6141: bipush #16
    //   6143: iushr
    //   6144: sipush #255
    //   6147: iand
    //   6148: iaload
    //   6149: ixor
    //   6150: aload #40
    //   6152: iload #51
    //   6154: bipush #8
    //   6156: iushr
    //   6157: sipush #255
    //   6160: iand
    //   6161: iaload
    //   6162: ixor
    //   6163: aload #41
    //   6165: iload #50
    //   6167: sipush #255
    //   6170: iand
    //   6171: iaload
    //   6172: ixor
    //   6173: aload #30
    //   6175: iload #47
    //   6177: iaload
    //   6178: ixor
    //   6179: istore #54
    //   6181: aload #38
    //   6183: iload #50
    //   6185: bipush #24
    //   6187: iushr
    //   6188: iaload
    //   6189: aload #39
    //   6191: iload #49
    //   6193: bipush #16
    //   6195: iushr
    //   6196: sipush #255
    //   6199: iand
    //   6200: iaload
    //   6201: ixor
    //   6202: aload #40
    //   6204: iload #52
    //   6206: bipush #8
    //   6208: iushr
    //   6209: sipush #255
    //   6212: iand
    //   6213: iaload
    //   6214: ixor
    //   6215: aload #41
    //   6217: iload #51
    //   6219: sipush #255
    //   6222: iand
    //   6223: iaload
    //   6224: ixor
    //   6225: aload #30
    //   6227: iload #47
    //   6229: iconst_1
    //   6230: iadd
    //   6231: iaload
    //   6232: ixor
    //   6233: istore #55
    //   6235: aload #38
    //   6237: iload #51
    //   6239: bipush #24
    //   6241: iushr
    //   6242: iaload
    //   6243: aload #39
    //   6245: iload #50
    //   6247: bipush #16
    //   6249: iushr
    //   6250: sipush #255
    //   6253: iand
    //   6254: iaload
    //   6255: ixor
    //   6256: aload #40
    //   6258: iload #49
    //   6260: bipush #8
    //   6262: iushr
    //   6263: sipush #255
    //   6266: iand
    //   6267: iaload
    //   6268: ixor
    //   6269: aload #41
    //   6271: iload #52
    //   6273: sipush #255
    //   6276: iand
    //   6277: iaload
    //   6278: ixor
    //   6279: aload #30
    //   6281: iload #47
    //   6283: iconst_2
    //   6284: iadd
    //   6285: iaload
    //   6286: ixor
    //   6287: istore #56
    //   6289: aload #38
    //   6291: iload #52
    //   6293: bipush #24
    //   6295: iushr
    //   6296: iaload
    //   6297: aload #39
    //   6299: iload #51
    //   6301: bipush #16
    //   6303: iushr
    //   6304: sipush #255
    //   6307: iand
    //   6308: iaload
    //   6309: ixor
    //   6310: aload #40
    //   6312: iload #50
    //   6314: bipush #8
    //   6316: iushr
    //   6317: sipush #255
    //   6320: iand
    //   6321: iaload
    //   6322: ixor
    //   6323: aload #41
    //   6325: iload #49
    //   6327: sipush #255
    //   6330: iand
    //   6331: iaload
    //   6332: ixor
    //   6333: aload #30
    //   6335: iload #47
    //   6337: iconst_3
    //   6338: iadd
    //   6339: iaload
    //   6340: ixor
    //   6341: istore #57
    //   6343: iload #54
    //   6345: istore #49
    //   6347: iload #55
    //   6349: istore #50
    //   6351: iload #56
    //   6353: istore #51
    //   6355: iload #57
    //   6357: istore #52
    //   6359: iinc #53, 1
    //   6362: iload_2
    //   6363: ifeq -> 6119
    //   6366: iinc #47, 4
    //   6369: aload #30
    //   6371: iload #47
    //   6373: iaload
    //   6374: istore #48
    //   6376: aload #46
    //   6378: iconst_0
    //   6379: aload #37
    //   6381: iload #49
    //   6383: bipush #24
    //   6385: iushr
    //   6386: baload
    //   6387: iload #48
    //   6389: bipush #24
    //   6391: iushr
    //   6392: ixor
    //   6393: i2b
    //   6394: bastore
    //   6395: aload #46
    //   6397: iconst_1
    //   6398: aload #37
    //   6400: iload #52
    //   6402: bipush #16
    //   6404: iushr
    //   6405: sipush #255
    //   6408: iand
    //   6409: baload
    //   6410: iload #48
    //   6412: bipush #16
    //   6414: iushr
    //   6415: ixor
    //   6416: i2b
    //   6417: bastore
    //   6418: aload #46
    //   6420: iconst_2
    //   6421: aload #37
    //   6423: iload #51
    //   6425: bipush #8
    //   6427: iushr
    //   6428: sipush #255
    //   6431: iand
    //   6432: baload
    //   6433: iload #48
    //   6435: bipush #8
    //   6437: iushr
    //   6438: ixor
    //   6439: i2b
    //   6440: bastore
    //   6441: aload #46
    //   6443: iconst_3
    //   6444: aload #37
    //   6446: iload #50
    //   6448: sipush #255
    //   6451: iand
    //   6452: baload
    //   6453: iload #48
    //   6455: ixor
    //   6456: i2b
    //   6457: bastore
    //   6458: aload #30
    //   6460: iload #47
    //   6462: iconst_1
    //   6463: iadd
    //   6464: iaload
    //   6465: istore #48
    //   6467: aload #46
    //   6469: iconst_4
    //   6470: aload #37
    //   6472: iload #50
    //   6474: bipush #24
    //   6476: iushr
    //   6477: baload
    //   6478: iload #48
    //   6480: bipush #24
    //   6482: iushr
    //   6483: ixor
    //   6484: i2b
    //   6485: bastore
    //   6486: aload #46
    //   6488: iconst_5
    //   6489: aload #37
    //   6491: iload #49
    //   6493: bipush #16
    //   6495: iushr
    //   6496: sipush #255
    //   6499: iand
    //   6500: baload
    //   6501: iload #48
    //   6503: bipush #16
    //   6505: iushr
    //   6506: ixor
    //   6507: i2b
    //   6508: bastore
    //   6509: aload #46
    //   6511: bipush #6
    //   6513: aload #37
    //   6515: iload #52
    //   6517: bipush #8
    //   6519: iushr
    //   6520: sipush #255
    //   6523: iand
    //   6524: baload
    //   6525: iload #48
    //   6527: bipush #8
    //   6529: iushr
    //   6530: ixor
    //   6531: i2b
    //   6532: bastore
    //   6533: aload #46
    //   6535: bipush #7
    //   6537: aload #37
    //   6539: iload #51
    //   6541: sipush #255
    //   6544: iand
    //   6545: baload
    //   6546: iload #48
    //   6548: ixor
    //   6549: i2b
    //   6550: bastore
    //   6551: aload #30
    //   6553: iload #47
    //   6555: iconst_2
    //   6556: iadd
    //   6557: iaload
    //   6558: istore #48
    //   6560: aload #46
    //   6562: bipush #8
    //   6564: aload #37
    //   6566: iload #51
    //   6568: bipush #24
    //   6570: iushr
    //   6571: baload
    //   6572: iload #48
    //   6574: bipush #24
    //   6576: iushr
    //   6577: ixor
    //   6578: i2b
    //   6579: bastore
    //   6580: aload #46
    //   6582: bipush #9
    //   6584: aload #37
    //   6586: iload #50
    //   6588: bipush #16
    //   6590: iushr
    //   6591: sipush #255
    //   6594: iand
    //   6595: baload
    //   6596: iload #48
    //   6598: bipush #16
    //   6600: iushr
    //   6601: ixor
    //   6602: i2b
    //   6603: bastore
    //   6604: aload #46
    //   6606: bipush #10
    //   6608: aload #37
    //   6610: iload #49
    //   6612: bipush #8
    //   6614: iushr
    //   6615: sipush #255
    //   6618: iand
    //   6619: baload
    //   6620: iload #48
    //   6622: bipush #8
    //   6624: iushr
    //   6625: ixor
    //   6626: i2b
    //   6627: bastore
    //   6628: aload #46
    //   6630: bipush #11
    //   6632: aload #37
    //   6634: iload #52
    //   6636: sipush #255
    //   6639: iand
    //   6640: baload
    //   6641: iload #48
    //   6643: ixor
    //   6644: i2b
    //   6645: bastore
    //   6646: aload #30
    //   6648: iload #47
    //   6650: iconst_3
    //   6651: iadd
    //   6652: iaload
    //   6653: istore #48
    //   6655: aload #46
    //   6657: bipush #12
    //   6659: aload #37
    //   6661: iload #52
    //   6663: bipush #24
    //   6665: iushr
    //   6666: baload
    //   6667: iload #48
    //   6669: bipush #24
    //   6671: iushr
    //   6672: ixor
    //   6673: i2b
    //   6674: bastore
    //   6675: aload #46
    //   6677: bipush #13
    //   6679: aload #37
    //   6681: iload #51
    //   6683: bipush #16
    //   6685: iushr
    //   6686: sipush #255
    //   6689: iand
    //   6690: baload
    //   6691: iload #48
    //   6693: bipush #16
    //   6695: iushr
    //   6696: ixor
    //   6697: i2b
    //   6698: bastore
    //   6699: aload #46
    //   6701: bipush #14
    //   6703: aload #37
    //   6705: iload #50
    //   6707: bipush #8
    //   6709: iushr
    //   6710: sipush #255
    //   6713: iand
    //   6714: baload
    //   6715: iload #48
    //   6717: bipush #8
    //   6719: iushr
    //   6720: ixor
    //   6721: i2b
    //   6722: bastore
    //   6723: aload #46
    //   6725: bipush #15
    //   6727: aload #37
    //   6729: iload #49
    //   6731: sipush #255
    //   6734: iand
    //   6735: baload
    //   6736: iload #48
    //   6738: ixor
    //   6739: i2b
    //   6740: bastore
    //   6741: iconst_0
    //   6742: istore #53
    //   6744: iload #53
    //   6746: bipush #16
    //   6748: if_icmpge -> 6774
    //   6751: aload #43
    //   6753: iload #53
    //   6755: iload #44
    //   6757: bipush #16
    //   6759: imul
    //   6760: iadd
    //   6761: aload #46
    //   6763: iload #53
    //   6765: baload
    //   6766: bastore
    //   6767: iinc #53, 1
    //   6770: iload_2
    //   6771: ifeq -> 6744
    //   6774: iinc #44, 1
    //   6777: iload_2
    //   6778: ifeq -> 5859
    //   6781: aload #43
    //   6783: arraylength
    //   6784: ifle -> 6865
    //   6787: aload #43
    //   6789: aload #43
    //   6791: arraylength
    //   6792: iconst_1
    //   6793: isub
    //   6794: baload
    //   6795: istore #44
    //   6797: iload #44
    //   6799: bipush #16
    //   6801: if_icmple -> 6812
    //   6804: aload #43
    //   6806: astore #35
    //   6808: iload_2
    //   6809: ifeq -> 6865
    //   6812: aload #43
    //   6814: arraylength
    //   6815: iload #44
    //   6817: isub
    //   6818: newarray byte
    //   6820: astore #35
    //   6822: iconst_0
    //   6823: istore #45
    //   6825: iload #45
    //   6827: aload #35
    //   6829: arraylength
    //   6830: if_icmpge -> 6865
    //   6833: iload #45
    //   6835: aload #43
    //   6837: arraylength
    //   6838: if_icmpge -> 6865
    //   6841: aload #35
    //   6843: iload #45
    //   6845: aload #43
    //   6847: iload #45
    //   6849: baload
    //   6850: bastore
    //   6851: iinc #45, 1
    //   6854: iload_2
    //   6855: ifeq -> 6825
    //   6858: goto -> 6865
    //   6861: invokestatic a : (Ljava/lang/Throwable;)Ljava/lang/Throwable;
    //   6864: athrow
    //   6865: aload #35
    //   6867: astore #7
    //   6869: sipush #-16586
    //   6872: new java/math/BigInteger
    //   6875: dup
    //   6876: aload #7
    //   6878: invokespecial <init> : ([B)V
    //   6881: invokevirtual abs : ()Ljava/math/BigInteger;
    //   6884: putstatic burp/Zk9s.ZY : Ljava/lang/Object;
    //   6887: sipush #-16769
    //   6890: getstatic burp/Zzap.ZL : Ljava/lang/Object;
    //   6893: checkcast java/math/BigInteger
    //   6896: getstatic burp/Zb3z.ZR : Ljava/lang/Object;
    //   6899: checkcast java/math/BigInteger
    //   6902: invokevirtual subtract : (Ljava/math/BigInteger;)Ljava/math/BigInteger;
    //   6905: putstatic burp/Zl_k.ZH : Ljava/lang/Object;
    //   6908: invokestatic a : (II)Ljava/lang/String;
    //   6911: iconst_1
    //   6912: ldc burp/Zk5y
    //   6914: invokevirtual getClassLoader : ()Ljava/lang/ClassLoader;
    //   6917: invokestatic forName : (Ljava/lang/String;ZLjava/lang/ClassLoader;)Ljava/lang/Class;
    //   6920: invokevirtual getDeclaredFields : ()[Ljava/lang/reflect/Field;
    //   6923: astore_3
    //   6924: aload_3
    //   6925: arraylength
    //   6926: istore #4
    //   6928: iconst_0
    //   6929: istore #5
    //   6931: iload #5
    //   6933: iload #4
    //   6935: if_icmpge -> 7072
    //   6938: aload_3
    //   6939: iload #5
    //   6941: aaload
    //   6942: astore #6
    //   6944: aload #6
    //   6946: invokevirtual getModifiers : ()I
    //   6949: invokestatic isStatic : (I)Z
    //   6952: ifne -> 6962
    //   6955: goto -> 7065
    //   6958: invokestatic a : (Ljava/lang/Throwable;)Ljava/lang/Throwable;
    //   6961: athrow
    //   6962: aload #6
    //   6964: invokevirtual getType : ()Ljava/lang/Class;
    //   6967: astore #7
    //   6969: aload #7
    //   6971: ifnull -> 7052
    //   6974: aload #7
    //   6976: invokevirtual isPrimitive : ()Z
    //   6979: ifne -> 7052
    //   6982: goto -> 6989
    //   6985: invokestatic a : (Ljava/lang/Throwable;)Ljava/lang/Throwable;
    //   6988: athrow
    //   6989: aload #7
    //   6991: invokevirtual getPackage : ()Ljava/lang/Package;
    //   6994: ifnull -> 7052
    //   6997: goto -> 7004
    //   7000: invokestatic a : (Ljava/lang/Throwable;)Ljava/lang/Throwable;
    //   7003: athrow
    //   7004: aload #7
    //   7006: invokevirtual getPackage : ()Ljava/lang/Package;
    //   7009: invokevirtual getName : ()Ljava/lang/String;
    //   7012: ifnull -> 7052
    //   7015: goto -> 7022
    //   7018: invokestatic a : (Ljava/lang/Throwable;)Ljava/lang/Throwable;
    //   7021: athrow
    //   7022: aload #7
    //   7024: invokevirtual getPackage : ()Ljava/lang/Package;
    //   7027: invokevirtual getName : ()Ljava/lang/String;
    //   7030: sipush #-16582
    //   7033: sipush #-14453
    //   7036: invokestatic a : (II)Ljava/lang/String;
    //   7039: invokevirtual startsWith : (Ljava/lang/String;)Z
    //   7042: ifne -> 7052
    //   7045: goto -> 7052
    //   7048: invokestatic a : (Ljava/lang/Throwable;)Ljava/lang/Throwable;
    //   7051: athrow
    //   7052: aload #6
    //   7054: iconst_1
    //   7055: invokevirtual setAccessible : (Z)V
    //   7058: aload #6
    //   7060: aconst_null
    //   7061: invokevirtual get : (Ljava/lang/Object;)Ljava/lang/Object;
    //   7064: pop
    //   7065: iinc #5, 1
    //   7068: iload_2
    //   7069: ifeq -> 6931
    //   7072: sipush #-16591
    //   7075: sipush #813
    //   7078: invokestatic a : (II)Ljava/lang/String;
    //   7081: invokestatic forName : (Ljava/lang/String;)Ljava/lang/Class;
    //   7084: invokevirtual getDeclaredMethods : ()[Ljava/lang/reflect/Method;
    //   7087: astore_3
    //   7088: aload_3
    //   7089: arraylength
    //   7090: istore #4
    //   7092: iconst_0
    //   7093: istore #5
    //   7095: iload #5
    //   7097: iload #4
    //   7099: if_icmpge -> 7231
    //   7102: aload_3
    //   7103: iload #5
    //   7105: aaload
    //   7106: astore #6
    //   7108: aload #6
    //   7110: invokevirtual getParameterTypes : ()[Ljava/lang/Class;
    //   7113: pop
    //   7114: aload #6
    //   7116: invokevirtual getModifiers : ()I
    //   7119: invokestatic isStatic : (I)Z
    //   7122: ifeq -> 7217
    //   7125: aload #6
    //   7127: invokevirtual getParameterTypes : ()[Ljava/lang/Class;
    //   7130: arraylength
    //   7131: iconst_2
    //   7132: if_icmpne -> 7217
    //   7135: goto -> 7142
    //   7138: invokestatic a : (Ljava/lang/Throwable;)Ljava/lang/Throwable;
    //   7141: athrow
    //   7142: aload #6
    //   7144: invokevirtual getReturnType : ()Ljava/lang/Class;
    //   7147: getstatic java/lang/Void.TYPE : Ljava/lang/Class;
    //   7150: invokevirtual equals : (Ljava/lang/Object;)Z
    //   7153: ifeq -> 7217
    //   7156: goto -> 7163
    //   7159: invokestatic a : (Ljava/lang/Throwable;)Ljava/lang/Throwable;
    //   7162: athrow
    //   7163: aload #6
    //   7165: iconst_1
    //   7166: invokevirtual setAccessible : (Z)V
    //   7169: aload #6
    //   7171: aconst_null
    //   7172: iconst_2
    //   7173: anewarray java/lang/Object
    //   7176: dup
    //   7177: iconst_0
    //   7178: aload_0
    //   7179: aastore
    //   7180: dup
    //   7181: iconst_1
    //   7182: aload_1
    //   7183: ifnonnull -> 7201
    //   7186: goto -> 7193
    //   7189: invokestatic a : (Ljava/lang/Throwable;)Ljava/lang/Throwable;
    //   7192: athrow
    //   7193: aload_1
    //   7194: goto -> 7208
    //   7197: invokestatic a : (Ljava/lang/Throwable;)Ljava/lang/Throwable;
    //   7200: athrow
    //   7201: aload_1
    //   7202: checkcast [B
    //   7205: invokevirtual clone : ()Ljava/lang/Object;
    //   7208: aastore
    //   7209: invokevirtual invoke : (Ljava/lang/Object;[Ljava/lang/Object;)Ljava/lang/Object;
    //   7212: pop
    //   7213: iload_2
    //   7214: ifeq -> 7231
    //   7217: iinc #5, 1
    //   7220: iload_2
    //   7221: ifeq -> 7095
    //   7224: goto -> 7231
    //   7227: invokestatic a : (Ljava/lang/Throwable;)Ljava/lang/Throwable;
    //   7230: athrow
    //   7231: getstatic burp/Zl2g.ZI : Ljava/lang/String;
    //   7234: getstatic burp/Ze3d.Ze : Ljava/lang/Object;
    //   7237: checkcast java/math/BigInteger
    //   7240: invokevirtual intValue : ()I
    //   7243: bipush #32
    //   7245: irem
    //   7246: invokestatic abs : (I)I
    //   7249: invokevirtual charAt : (I)C
    //   7252: getstatic burp/Ze7q.ZW : Ljava/lang/String;
    //   7255: getstatic burp/Ztuj.Ze : Ljava/lang/Object;
    //   7258: checkcast java/math/BigInteger
    //   7261: invokevirtual intValue : ()I
    //   7264: bipush #32
    //   7266: irem
    //   7267: invokestatic abs : (I)I
    //   7270: invokevirtual charAt : (I)C
    //   7273: if_icmpgt -> 7380
    //   7276: getstatic burp/Zxzd.ZM : Ljava/lang/String;
    //   7279: getstatic burp/Zbsr.ZD : Ljava/lang/Object;
    //   7282: checkcast java/math/BigInteger
    //   7285: invokevirtual intValue : ()I
    //   7288: bipush #32
    //   7290: irem
    //   7291: invokestatic abs : (I)I
    //   7294: invokevirtual charAt : (I)C
    //   7297: getstatic burp/Zgss.Zc : Ljava/lang/String;
    //   7300: getstatic burp/Zxzj.ZO : Ljava/lang/Object;
    //   7303: checkcast java/math/BigInteger
    //   7306: invokevirtual intValue : ()I
    //   7309: bipush #32
    //   7311: irem
    //   7312: invokestatic abs : (I)I
    //   7315: invokevirtual charAt : (I)C
    //   7318: if_icmpgt -> 7380
    //   7321: goto -> 7328
    //   7324: invokestatic a : (Ljava/lang/Throwable;)Ljava/lang/Throwable;
    //   7327: athrow
    //   7328: getstatic burp/Zer.Zp : Ljava/lang/String;
    //   7331: getstatic burp/Zgw0.ZM : Ljava/lang/Object;
    //   7334: checkcast java/math/BigInteger
    //   7337: invokevirtual intValue : ()I
    //   7340: bipush #32
    //   7342: irem
    //   7343: invokestatic abs : (I)I
    //   7346: invokevirtual charAt : (I)C
    //   7349: getstatic burp/Zrbp.Ze : Ljava/lang/String;
    //   7352: getstatic burp/Zx4w.Zp : Ljava/lang/Object;
    //   7355: checkcast java/math/BigInteger
    //   7358: invokevirtual intValue : ()I
    //   7361: bipush #32
    //   7363: irem
    //   7364: invokestatic abs : (I)I
    //   7367: invokevirtual charAt : (I)C
    //   7370: if_icmpgt -> 7388
    //   7373: goto -> 7380
    //   7376: invokestatic a : (Ljava/lang/Throwable;)Ljava/lang/Throwable;
    //   7379: athrow
    //   7380: iconst_1
    //   7381: goto -> 7389
    //   7384: invokestatic a : (Ljava/lang/Throwable;)Ljava/lang/Throwable;
    //   7387: athrow
    //   7388: iconst_0
    //   7389: ireturn
    //   7390: astore_3
    //   7391: new java/lang/Exception
    //   7394: dup
    //   7395: aload_3
    //   7396: invokevirtual getMessage : ()Ljava/lang/String;
    //   7399: invokespecial <init> : (Ljava/lang/String;)V
    //   7402: athrow
    // Exception table:
    //   from	to	target	type
    //   4	7389	7390	java/lang/Throwable
    //   3306	3331	3331	java/lang/Throwable
    //   4294	4320	4320	java/lang/Throwable
    //   4512	4527	4527	java/lang/Throwable
    //   5529	5555	5555	java/lang/Throwable
    //   5636	5651	5651	java/lang/Throwable
    //   6833	6858	6861	java/lang/Throwable
    //   6944	6958	6958	java/lang/Throwable
    //   6969	6982	6985	java/lang/Throwable
    //   6974	6997	7000	java/lang/Throwable
    //   6989	7015	7018	java/lang/Throwable
    //   7004	7045	7048	java/lang/Throwable
    //   7108	7135	7138	java/lang/Throwable
    //   7125	7156	7159	java/lang/Throwable
    //   7142	7186	7189	java/lang/Throwable
    //   7163	7197	7197	java/lang/Throwable
    //   7208	7224	7227	java/lang/Throwable
    //   7231	7321	7324	java/lang/Throwable
    //   7276	7373	7376	java/lang/Throwable
    //   7328	7384	7384	java/lang/Throwable
  }
  
  static {
    // Byte code:
    //   0: bipush #12
    //   2: anewarray java/lang/String
    //   5: astore #5
    //   7: iconst_0
    //   8: istore_3
    //   9: ldc 'ZyR\\t1B'\\t6Nb ?cZ/qdhu`-:+(-fK -q^x\\tR0oq^5F+-EUt6$/%\\tePK1G\=Em%%}??ME6b0JYC\\nR*%)o]PiZ vPQbc3&\xyylCqhSM}'
    //   11: dup
    //   12: astore_2
    //   13: invokevirtual length : ()I
    //   16: istore #4
    //   18: bipush #9
    //   20: istore_1
    //   21: iconst_m1
    //   22: istore_0
    //   23: bipush #74
    //   25: iinc #0, 1
    //   28: aload_2
    //   29: iload_0
    //   30: dup
    //   31: iload_1
    //   32: iadd
    //   33: invokevirtual substring : (II)Ljava/lang/String;
    //   36: iconst_m1
    //   37: goto -> 142
    //   40: aload #5
    //   42: swap
    //   43: iload_3
    //   44: iinc #3, 1
    //   47: swap
    //   48: aastore
    //   49: iload_0
    //   50: iload_1
    //   51: iadd
    //   52: dup
    //   53: istore_0
    //   54: iload #4
    //   56: if_icmpge -> 68
    //   59: aload_2
    //   60: iload_0
    //   61: invokevirtual charAt : (I)C
    //   64: istore_1
    //   65: goto -> 23
    //   68: ldc 'G:??'
    //   70: dup
    //   71: astore_2
    //   72: invokevirtual length : ()I
    //   75: istore #4
    //   77: iconst_4
    //   78: istore_1
    //   79: iconst_m1
    //   80: istore_0
    //   81: bipush #54
    //   83: iinc #0, 1
    //   86: aload_2
    //   87: iload_0
    //   88: dup
    //   89: iload_1
    //   90: iadd
    //   91: invokevirtual substring : (II)Ljava/lang/String;
    //   94: iconst_0
    //   95: goto -> 142
    //   98: aload #5
    //   100: swap
    //   101: iload_3
    //   102: iinc #3, 1
    //   105: swap
    //   106: aastore
    //   107: iload_0
    //   108: iload_1
    //   109: iadd
    //   110: dup
    //   111: istore_0
    //   112: iload #4
    //   114: if_icmpge -> 126
    //   117: aload_2
    //   118: iload_0
    //   119: invokevirtual charAt : (I)C
    //   122: istore_1
    //   123: goto -> 81
    //   126: aload #5
    //   128: putstatic burp/Zm__.a : [Ljava/lang/String;
    //   131: bipush #12
    //   133: anewarray java/lang/String
    //   136: putstatic burp/Zm__.b : [Ljava/lang/String;
    //   139: goto -> 300
    //   142: dup_x2
    //   143: pop
    //   144: invokevirtual toCharArray : ()[C
    //   147: dup_x1
    //   148: arraylength
    //   149: dup_x2
    //   150: pop
    //   151: iconst_0
    //   152: istore #6
    //   154: dup2_x1
    //   155: pop2
    //   156: dup_x2
    //   157: iconst_1
    //   158: if_icmpgt -> 260
    //   161: dup2
    //   162: swap
    //   163: iload #6
    //   165: dup2_x1
    //   166: caload
    //   167: swap
    //   168: iload #6
    //   170: bipush #7
    //   172: irem
    //   173: tableswitch default -> 242, 0 -> 212, 1 -> 217, 2 -> 222, 3 -> 227, 4 -> 232, 5 -> 237
    //   212: bipush #18
    //   214: goto -> 244
    //   217: bipush #44
    //   219: goto -> 244
    //   222: bipush #47
    //   224: goto -> 244
    //   227: bipush #12
    //   229: goto -> 244
    //   232: bipush #8
    //   234: goto -> 244
    //   237: bipush #123
    //   239: goto -> 244
    //   242: bipush #90
    //   244: ixor
    //   245: ixor
    //   246: i2c
    //   247: castore
    //   248: iinc #6, 1
    //   251: dup
    //   252: ifne -> 260
    //   255: dup2
    //   256: dup_x1
    //   257: goto -> 165
    //   260: dup2_x1
    //   261: pop2
    //   262: dup_x2
    //   263: iload #6
    //   265: if_icmpgt -> 161
    //   268: pop
    //   269: new java/lang/String
    //   272: dup_x1
    //   273: swap
    //   274: invokespecial <init> : ([C)V
    //   277: invokevirtual intern : ()Ljava/lang/String;
    //   280: swap
    //   281: pop
    //   282: swap
    //   283: tableswitch default -> 40, 0 -> 98
    //   300: sipush #-16588
    //   303: sipush #-25613
    //   306: invokestatic a : (II)Ljava/lang/String;
    //   309: putstatic burp/Zm__.Zf : Ljava/lang/String;
    //   312: new java/math/BigInteger
    //   315: dup
    //   316: bipush #32
    //   318: newarray byte
    //   320: dup
    //   321: iconst_0
    //   322: bipush #48
    //   324: bastore
    //   325: dup
    //   326: iconst_1
    //   327: bipush #-114
    //   329: bastore
    //   330: dup
    //   331: iconst_2
    //   332: iconst_3
    //   333: bastore
    //   334: dup
    //   335: iconst_3
    //   336: bipush #-68
    //   338: bastore
    //   339: dup
    //   340: iconst_4
    //   341: bipush #90
    //   343: bastore
    //   344: dup
    //   345: iconst_5
    //   346: bipush #35
    //   348: bastore
    //   349: dup
    //   350: bipush #6
    //   352: bipush #50
    //   354: bastore
    //   355: dup
    //   356: bipush #7
    //   358: bipush #110
    //   360: bastore
    //   361: dup
    //   362: bipush #8
    //   364: bipush #-126
    //   366: bastore
    //   367: dup
    //   368: bipush #9
    //   370: bipush #108
    //   372: bastore
    //   373: dup
    //   374: bipush #10
    //   376: bipush #-103
    //   378: bastore
    //   379: dup
    //   380: bipush #11
    //   382: bipush #-47
    //   384: bastore
    //   385: dup
    //   386: bipush #12
    //   388: bipush #45
    //   390: bastore
    //   391: dup
    //   392: bipush #13
    //   394: bipush #-18
    //   396: bastore
    //   397: dup
    //   398: bipush #14
    //   400: bipush #-78
    //   402: bastore
    //   403: dup
    //   404: bipush #15
    //   406: bipush #114
    //   408: bastore
    //   409: dup
    //   410: bipush #16
    //   412: bipush #20
    //   414: bastore
    //   415: dup
    //   416: bipush #17
    //   418: bipush #44
    //   420: bastore
    //   421: dup
    //   422: bipush #18
    //   424: bipush #74
    //   426: bastore
    //   427: dup
    //   428: bipush #19
    //   430: bipush #-59
    //   432: bastore
    //   433: dup
    //   434: bipush #20
    //   436: iconst_3
    //   437: bastore
    //   438: dup
    //   439: bipush #21
    //   441: bipush #-48
    //   443: bastore
    //   444: dup
    //   445: bipush #22
    //   447: bipush #-54
    //   449: bastore
    //   450: dup
    //   451: bipush #23
    //   453: bipush #-82
    //   455: bastore
    //   456: dup
    //   457: bipush #24
    //   459: bipush #-51
    //   461: bastore
    //   462: dup
    //   463: bipush #25
    //   465: bipush #-63
    //   467: bastore
    //   468: dup
    //   469: bipush #26
    //   471: bipush #-8
    //   473: bastore
    //   474: dup
    //   475: bipush #27
    //   477: bipush #42
    //   479: bastore
    //   480: dup
    //   481: bipush #28
    //   483: bipush #-48
    //   485: bastore
    //   486: dup
    //   487: bipush #29
    //   489: bipush #53
    //   491: bastore
    //   492: dup
    //   493: bipush #30
    //   495: bipush #-10
    //   497: bastore
    //   498: dup
    //   499: bipush #31
    //   501: bipush #-26
    //   503: bastore
    //   504: invokespecial <init> : ([B)V
    //   507: putstatic burp/Zm__.Zz : Ljava/lang/Object;
    //   510: return
  }
  
  private static Throwable a(Throwable paramThrowable) {
    return paramThrowable;
  }
  
  private static String a(int paramInt1, int paramInt2) {
    int i = (paramInt1 ^ 0xFFFFBF30) & 0xFFFF;
    if (b[i] == null) {
      char[] arrayOfChar = a[i].toCharArray();
      switch (arrayOfChar[0] & 0xFF) {
        case 0:
        
        case 1:
        
        case 2:
        
        case 3:
        
        case 4:
        
        case 5:
        
        case 6:
        
        case 7:
        
        case 8:
        
        case 9:
        
        case 10:
        
        case 11:
        
        case 12:
        
        case 13:
        
        case 14:
        
        case 15:
        
        case 16:
        
        case 17:
        
        case 18:
        
        case 19:
        
        case 20:
        
        case 21:
        
        case 22:
        
        case 23:
        
        case 24:
        
        case 25:
        
        case 26:
        
        case 27:
        
        case 28:
        
        case 29:
        
        case 30:
        
        case 31:
        
        case 32:
        
        case 33:
        
        case 34:
        
        case 35:
        
        case 36:
        
        case 37:
        
        case 38:
        
        case 39:
        
        case 40:
        
        case 41:
        
        case 42:
        
        case 43:
        
        case 44:
        
        case 45:
        
        case 46:
        
        case 47:
        
        case 48:
        
        case 49:
        
        case 50:
        
        case 51:
        
        case 52:
        
        case 53:
        
        case 54:
        
        case 55:
        
        case 56:
        
        case 57:
        
        case 58:
        
        case 59:
        
        case 60:
        
        case 61:
        
        case 62:
        
        case 63:
        
        case 64:
        
        case 65:
        
        case 66:
        
        case 67:
        
        case 68:
        
        case 69:
        
        case 70:
        
        case 71:
        
        case 72:
        
        case 73:
        
        case 74:
        
        case 75:
        
        case 76:
        
        case 77:
        
        case 78:
        
        case 79:
        
        case 80:
        
        case 81:
        
        case 82:
        
        case 83:
        
        case 84:
        
        case 85:
        
        case 86:
        
        case 87:
        
        case 88:
        
        case 89:
        
        case 90:
        
        case 91:
        
        case 92:
        
        case 93:
        
        case 94:
        
        case 95:
        
        case 96:
        
        case 97:
        
        case 98:
        
        case 99:
        
        case 100:
        
        case 101:
        
        case 102:
        
        case 103:
        
        case 104:
        
        case 105:
        
        case 106:
        
        case 107:
        
        case 108:
        
        case 109:
        
        case 110:
        
        case 111:
        
        case 112:
        
        case 113:
        
        case 114:
        
        case 115:
        
        case 116:
        
        case 117:
        
        case 118:
        
        case 119:
        
        case 120:
        
        case 121:
        
        case 122:
        
        case 123:
        
        case 124:
        
        case 125:
        
        case 126:
        
        case 127:
        
        case 128:
        
        case 129:
        
        case 130:
        
        case 131:
        
        case 132:
        
        case 133:
        
        case 134:
        
        case 135:
        
        case 136:
        
        case 137:
        
        case 138:
        
        case 139:
        
        case 140:
        
        case 141:
        
        case 142:
        
        case 143:
        
        case 144:
        
        case 145:
        
        case 146:
        
        case 147:
        
        case 148:
        
        case 149:
        
        case 150:
        
        case 151:
        
        case 152:
        
        case 153:
        
        case 154:
        
        case 155:
        
        case 156:
        
        case 157:
        
        case 158:
        
        case 159:
        
        case 160:
        
        case 161:
        
        case 162:
        
        case 163:
        
        case 164:
        
        case 165:
        
        case 166:
        
        case 167:
        
        case 168:
        
        case 169:
        
        case 170:
        
        case 171:
        
        case 172:
        
        case 173:
        
        case 174:
        
        case 175:
        
        case 176:
        
        case 177:
        
        case 178:
        
        case 179:
        
        case 180:
        
        case 181:
        
        case 182:
        
        case 183:
        
        case 184:
        
        case 185:
        
        case 186:
        
        case 187:
        
        case 188:
        
        case 189:
        
        case 190:
        
        case 191:
        
        case 192:
        
        case 193:
        
        case 194:
        
        case 195:
        
        case 196:
        
        case 197:
        
        case 198:
        
        case 199:
        
        case 200:
        
        case 201:
        
        case 202:
        
        case 203:
        
        case 204:
        
        case 205:
        
        case 206:
        
        case 207:
        
        case 208:
        
        case 209:
        
        case 210:
        
        case 211:
        
        case 212:
        
        case 213:
        
        case 214:
        
        case 215:
        
        case 216:
        
        case 217:
        
        case 218:
        
        case 219:
        
        case 220:
        
        case 221:
        
        case 222:
        
        case 223:
        
        case 224:
        
        case 225:
        
        case 226:
        
        case 227:
        
        case 228:
        
        case 229:
        
        case 230:
        
        case 231:
        
        case 232:
        
        case 233:
        
        case 234:
        
        case 235:
        
        case 236:
        
        case 237:
        
        case 238:
        
        case 239:
        
        case 240:
        
        case 241:
        
        case 242:
        
        case 243:
        
        case 244:
        
        case 245:
        
        case 246:
        
        case 247:
        
        case 248:
        
        case 249:
        
        case 250:
        
        case 251:
        
        case 252:
        
        case 253:
        
        case 254:
        
        default:
          break;
      } 
      byte b1 = 125;
      int j = (paramInt2 & 0xFF) - b1;
      if (j < 0)
        j += 256; 
      int k = ((paramInt2 & 0xFFFF) >>> 8) - b1;
      if (k < 0)
        k += 256; 
      for (byte b2 = 0; b2 < arrayOfChar.length; b2++) {
        int m = b2 % 2;
        if (m == 0) {
          arrayOfChar[b2] = (char)(arrayOfChar[b2] ^ j);
          j = ((j >>> 3 | j << 5) ^ arrayOfChar[b2]) & 0xFF;
        } else {
          arrayOfChar[b2] = (char)(arrayOfChar[b2] ^ k);
          k = ((k >>> 3 | k << 5) ^ arrayOfChar[b2]) & 0xFF;
        } 
      } 
      b[i] = (new String(arrayOfChar)).intern();
    } 
    return b[i];
  }
}


/* Location:              C:\Program Files\BurpSuitePro\burpsuite_pro.jar!\burp\Zm__.class
 * Java compiler version: 21 (65.0)
 * JD-Core Version:       1.1.3
 */