package burp;

import java.math.BigInteger;

class Zm_u extends ClassLoader {
  static Object Zf;
  
  static String Zi;
  
  private static final String[] a;
  
  private static final String[] b;
  
  static void ZG(Object[] paramArrayOfObject, Object paramObject) throws Throwable {}
  
  static boolean Z_(Object[] paramArrayOfObject, Object paramObject) throws Throwable {
    // Byte code:
    //   0: invokestatic ZK : ()Z
    //   3: istore_2
    //   4: getstatic burp/Zeig.ZA : Ljava/lang/Object;
    //   7: checkcast java/math/BigInteger
    //   10: getstatic burp/Zt6z.Zl : Ljava/lang/Object;
    //   13: checkcast java/math/BigInteger
    //   16: invokevirtual subtract : (Ljava/math/BigInteger;)Ljava/math/BigInteger;
    //   19: putstatic burp/Zzht.Zb : Ljava/lang/Object;
    //   22: getstatic burp/Zlbd.ZU : Ljava/lang/Object;
    //   25: checkcast java/math/BigInteger
    //   28: invokevirtual toByteArray : ()[B
    //   31: astore_3
    //   32: new java/lang/StringBuilder
    //   35: dup
    //   36: invokespecial <init> : ()V
    //   39: astore #5
    //   41: aload #5
    //   43: sipush #17067
    //   46: sipush #18170
    //   49: invokestatic a : (II)Ljava/lang/String;
    //   52: invokevirtual append : (Ljava/lang/String;)Ljava/lang/StringBuilder;
    //   55: pop
    //   56: aload_3
    //   57: astore #6
    //   59: aload #6
    //   61: arraylength
    //   62: istore #7
    //   64: iconst_0
    //   65: istore #8
    //   67: iload #8
    //   69: iload #7
    //   71: if_icmpge -> 97
    //   74: aload #6
    //   76: iload #8
    //   78: baload
    //   79: istore #9
    //   81: aload #5
    //   83: iload #9
    //   85: i2c
    //   86: invokevirtual append : (C)Ljava/lang/StringBuilder;
    //   89: pop
    //   90: iinc #8, 1
    //   93: iload_2
    //   94: ifeq -> 67
    //   97: aload #5
    //   99: sipush #17060
    //   102: sipush #-18381
    //   105: invokestatic a : (II)Ljava/lang/String;
    //   108: ldc ''
    //   110: invokestatic getProperty : (Ljava/lang/String;Ljava/lang/String;)Ljava/lang/String;
    //   113: invokevirtual toLowerCase : ()Ljava/lang/String;
    //   116: invokevirtual append : (Ljava/lang/String;)Ljava/lang/StringBuilder;
    //   119: pop
    //   120: aload #5
    //   122: sipush #17064
    //   125: sipush #17827
    //   128: invokestatic a : (II)Ljava/lang/String;
    //   131: ldc ''
    //   133: invokestatic getProperty : (Ljava/lang/String;Ljava/lang/String;)Ljava/lang/String;
    //   136: invokevirtual toLowerCase : ()Ljava/lang/String;
    //   139: invokevirtual append : (Ljava/lang/String;)Ljava/lang/StringBuilder;
    //   142: pop
    //   143: aload #5
    //   145: invokevirtual toString : ()Ljava/lang/String;
    //   148: invokevirtual getBytes : ()[B
    //   151: astore #4
    //   153: aload #4
    //   155: astore_3
    //   156: aload_3
    //   157: arraylength
    //   158: bipush #8
    //   160: iadd
    //   161: bipush #6
    //   163: ishr
    //   164: iconst_1
    //   165: iadd
    //   166: bipush #16
    //   168: imul
    //   169: newarray int
    //   171: astore #5
    //   173: iconst_0
    //   174: istore #6
    //   176: iload #6
    //   178: aload_3
    //   179: arraylength
    //   180: if_icmpge -> 223
    //   183: aload_3
    //   184: iload #6
    //   186: baload
    //   187: sipush #255
    //   190: iand
    //   191: istore #7
    //   193: aload #5
    //   195: iload #6
    //   197: iconst_2
    //   198: ishr
    //   199: dup2
    //   200: iaload
    //   201: iload #7
    //   203: bipush #24
    //   205: iload #6
    //   207: iconst_4
    //   208: irem
    //   209: bipush #8
    //   211: imul
    //   212: isub
    //   213: ishl
    //   214: ior
    //   215: iastore
    //   216: iinc #6, 1
    //   219: iload_2
    //   220: ifeq -> 176
    //   223: aload #5
    //   225: iload #6
    //   227: iconst_2
    //   228: ishr
    //   229: dup2
    //   230: iaload
    //   231: sipush #128
    //   234: bipush #24
    //   236: iload #6
    //   238: iconst_4
    //   239: irem
    //   240: bipush #8
    //   242: imul
    //   243: isub
    //   244: ishl
    //   245: ior
    //   246: iastore
    //   247: aload #5
    //   249: aload #5
    //   251: arraylength
    //   252: iconst_1
    //   253: isub
    //   254: aload_3
    //   255: arraylength
    //   256: bipush #8
    //   258: imul
    //   259: iastore
    //   260: bipush #80
    //   262: newarray int
    //   264: astore #7
    //   266: ldc 1732584193
    //   268: istore #8
    //   270: ldc -271733879
    //   272: istore #9
    //   274: ldc -1732584194
    //   276: istore #10
    //   278: ldc 271733878
    //   280: istore #11
    //   282: ldc -1009589776
    //   284: istore #12
    //   286: iconst_0
    //   287: istore #6
    //   289: iload #6
    //   291: aload #5
    //   293: arraylength
    //   294: if_icmpge -> 616
    //   297: iload #8
    //   299: istore #13
    //   301: iload #9
    //   303: istore #14
    //   305: iload #10
    //   307: istore #15
    //   309: iload #11
    //   311: istore #16
    //   313: iload #12
    //   315: istore #17
    //   317: iconst_0
    //   318: istore #18
    //   320: iload #18
    //   322: bipush #80
    //   324: if_icmpge -> 574
    //   327: iload #18
    //   329: bipush #16
    //   331: if_icmpge -> 358
    //   334: aload #7
    //   336: iload #18
    //   338: aload #5
    //   340: iload #6
    //   342: iload #18
    //   344: iadd
    //   345: iaload
    //   346: iastore
    //   347: iload_2
    //   348: ifeq -> 413
    //   351: goto -> 358
    //   354: invokestatic a : (Ljava/lang/Throwable;)Ljava/lang/Throwable;
    //   357: athrow
    //   358: aload #7
    //   360: iload #18
    //   362: iconst_3
    //   363: isub
    //   364: iaload
    //   365: aload #7
    //   367: iload #18
    //   369: bipush #8
    //   371: isub
    //   372: iaload
    //   373: ixor
    //   374: aload #7
    //   376: iload #18
    //   378: bipush #14
    //   380: isub
    //   381: iaload
    //   382: ixor
    //   383: aload #7
    //   385: iload #18
    //   387: bipush #16
    //   389: isub
    //   390: iaload
    //   391: ixor
    //   392: istore #19
    //   394: iload #19
    //   396: iconst_1
    //   397: ishl
    //   398: iload #19
    //   400: bipush #31
    //   402: iushr
    //   403: ior
    //   404: istore #20
    //   406: aload #7
    //   408: iload #18
    //   410: iload #20
    //   412: iastore
    //   413: iload #8
    //   415: iconst_5
    //   416: ishl
    //   417: iload #8
    //   419: bipush #27
    //   421: iushr
    //   422: ior
    //   423: istore #19
    //   425: iload #19
    //   427: iload #12
    //   429: iadd
    //   430: aload #7
    //   432: iload #18
    //   434: iaload
    //   435: iadd
    //   436: iload #18
    //   438: bipush #20
    //   440: if_icmpge -> 466
    //   443: ldc 1518500249
    //   445: iload #9
    //   447: iload #10
    //   449: iand
    //   450: iload #9
    //   452: iconst_m1
    //   453: ixor
    //   454: iload #11
    //   456: iand
    //   457: ior
    //   458: iadd
    //   459: goto -> 536
    //   462: invokestatic a : (Ljava/lang/Throwable;)Ljava/lang/Throwable;
    //   465: athrow
    //   466: iload #18
    //   468: bipush #40
    //   470: if_icmpge -> 491
    //   473: ldc 1859775393
    //   475: iload #9
    //   477: iload #10
    //   479: ixor
    //   480: iload #11
    //   482: ixor
    //   483: iadd
    //   484: goto -> 536
    //   487: invokestatic a : (Ljava/lang/Throwable;)Ljava/lang/Throwable;
    //   490: athrow
    //   491: iload #18
    //   493: bipush #60
    //   495: if_icmpge -> 525
    //   498: ldc -1894007588
    //   500: iload #9
    //   502: iload #10
    //   504: iand
    //   505: iload #9
    //   507: iload #11
    //   509: iand
    //   510: ior
    //   511: iload #10
    //   513: iload #11
    //   515: iand
    //   516: ior
    //   517: iadd
    //   518: goto -> 536
    //   521: invokestatic a : (Ljava/lang/Throwable;)Ljava/lang/Throwable;
    //   524: athrow
    //   525: ldc -899497514
    //   527: iload #9
    //   529: iload #10
    //   531: ixor
    //   532: iload #11
    //   534: ixor
    //   535: iadd
    //   536: iadd
    //   537: istore #20
    //   539: iload #11
    //   541: istore #12
    //   543: iload #10
    //   545: istore #11
    //   547: iload #9
    //   549: bipush #30
    //   551: ishl
    //   552: iload #9
    //   554: iconst_2
    //   555: iushr
    //   556: ior
    //   557: istore #10
    //   559: iload #8
    //   561: istore #9
    //   563: iload #20
    //   565: istore #8
    //   567: iinc #18, 1
    //   570: iload_2
    //   571: ifeq -> 320
    //   574: iload #8
    //   576: iload #13
    //   578: iadd
    //   579: istore #8
    //   581: iload #9
    //   583: iload #14
    //   585: iadd
    //   586: istore #9
    //   588: iload #10
    //   590: iload #15
    //   592: iadd
    //   593: istore #10
    //   595: iload #11
    //   597: iload #16
    //   599: iadd
    //   600: istore #11
    //   602: iload #12
    //   604: iload #17
    //   606: iadd
    //   607: istore #12
    //   609: iinc #6, 16
    //   612: iload_2
    //   613: ifeq -> 289
    //   616: iconst_5
    //   617: newarray int
    //   619: dup
    //   620: iconst_0
    //   621: iload #8
    //   623: iastore
    //   624: dup
    //   625: iconst_1
    //   626: iload #9
    //   628: iastore
    //   629: dup
    //   630: iconst_2
    //   631: iload #10
    //   633: iastore
    //   634: dup
    //   635: iconst_3
    //   636: iload #11
    //   638: iastore
    //   639: dup
    //   640: iconst_4
    //   641: iload #12
    //   643: iastore
    //   644: astore #13
    //   646: bipush #20
    //   648: newarray byte
    //   650: astore #14
    //   652: iconst_0
    //   653: istore #15
    //   655: iload #15
    //   657: bipush #20
    //   659: if_icmpge -> 700
    //   662: aload #13
    //   664: iload #15
    //   666: iconst_4
    //   667: idiv
    //   668: iaload
    //   669: istore #16
    //   671: iconst_3
    //   672: iload #15
    //   674: iconst_4
    //   675: irem
    //   676: isub
    //   677: bipush #8
    //   679: imul
    //   680: istore #17
    //   682: aload #14
    //   684: iload #15
    //   686: iload #16
    //   688: iload #17
    //   690: iushr
    //   691: i2b
    //   692: bastore
    //   693: iinc #15, 1
    //   696: iload_2
    //   697: ifeq -> 655
    //   700: aload #14
    //   702: astore #4
    //   704: sipush #17068
    //   707: sipush #21537
    //   710: invokestatic a : (II)Ljava/lang/String;
    //   713: iconst_1
    //   714: ldc burp/Ztev
    //   716: invokevirtual getClassLoader : ()Ljava/lang/ClassLoader;
    //   719: invokestatic forName : (Ljava/lang/String;ZLjava/lang/ClassLoader;)Ljava/lang/Class;
    //   722: invokevirtual getDeclaredFields : ()[Ljava/lang/reflect/Field;
    //   725: astore_3
    //   726: aload_3
    //   727: arraylength
    //   728: istore #4
    //   730: iconst_0
    //   731: istore #5
    //   733: iload #5
    //   735: iload #4
    //   737: if_icmpge -> 874
    //   740: aload_3
    //   741: iload #5
    //   743: aaload
    //   744: astore #6
    //   746: aload #6
    //   748: invokevirtual getModifiers : ()I
    //   751: invokestatic isStatic : (I)Z
    //   754: ifne -> 764
    //   757: goto -> 867
    //   760: invokestatic a : (Ljava/lang/Throwable;)Ljava/lang/Throwable;
    //   763: athrow
    //   764: aload #6
    //   766: invokevirtual getType : ()Ljava/lang/Class;
    //   769: astore #7
    //   771: aload #7
    //   773: ifnull -> 854
    //   776: aload #7
    //   778: invokevirtual isPrimitive : ()Z
    //   781: ifne -> 854
    //   784: goto -> 791
    //   787: invokestatic a : (Ljava/lang/Throwable;)Ljava/lang/Throwable;
    //   790: athrow
    //   791: aload #7
    //   793: invokevirtual getPackage : ()Ljava/lang/Package;
    //   796: ifnull -> 854
    //   799: goto -> 806
    //   802: invokestatic a : (Ljava/lang/Throwable;)Ljava/lang/Throwable;
    //   805: athrow
    //   806: aload #7
    //   808: invokevirtual getPackage : ()Ljava/lang/Package;
    //   811: invokevirtual getName : ()Ljava/lang/String;
    //   814: ifnull -> 854
    //   817: goto -> 824
    //   820: invokestatic a : (Ljava/lang/Throwable;)Ljava/lang/Throwable;
    //   823: athrow
    //   824: aload #7
    //   826: invokevirtual getPackage : ()Ljava/lang/Package;
    //   829: invokevirtual getName : ()Ljava/lang/String;
    //   832: sipush #17069
    //   835: sipush #13805
    //   838: invokestatic a : (II)Ljava/lang/String;
    //   841: invokevirtual startsWith : (Ljava/lang/String;)Z
    //   844: ifne -> 854
    //   847: goto -> 854
    //   850: invokestatic a : (Ljava/lang/Throwable;)Ljava/lang/Throwable;
    //   853: athrow
    //   854: aload #6
    //   856: iconst_1
    //   857: invokevirtual setAccessible : (Z)V
    //   860: aload #6
    //   862: aconst_null
    //   863: invokevirtual get : (Ljava/lang/Object;)Ljava/lang/Object;
    //   866: pop
    //   867: iinc #5, 1
    //   870: iload_2
    //   871: ifeq -> 733
    //   874: sipush #17071
    //   877: sipush #-5657
    //   880: invokestatic a : (II)Ljava/lang/String;
    //   883: invokestatic forName : (Ljava/lang/String;)Ljava/lang/Class;
    //   886: invokevirtual getDeclaredMethods : ()[Ljava/lang/reflect/Method;
    //   889: astore_3
    //   890: aload_3
    //   891: arraylength
    //   892: istore #4
    //   894: iconst_0
    //   895: istore #5
    //   897: iload #5
    //   899: iload #4
    //   901: if_icmpge -> 1033
    //   904: aload_3
    //   905: iload #5
    //   907: aaload
    //   908: astore #6
    //   910: aload #6
    //   912: invokevirtual getParameterTypes : ()[Ljava/lang/Class;
    //   915: pop
    //   916: aload #6
    //   918: invokevirtual getModifiers : ()I
    //   921: invokestatic isStatic : (I)Z
    //   924: ifeq -> 1019
    //   927: aload #6
    //   929: invokevirtual getParameterTypes : ()[Ljava/lang/Class;
    //   932: arraylength
    //   933: iconst_2
    //   934: if_icmpne -> 1019
    //   937: goto -> 944
    //   940: invokestatic a : (Ljava/lang/Throwable;)Ljava/lang/Throwable;
    //   943: athrow
    //   944: aload #6
    //   946: invokevirtual getReturnType : ()Ljava/lang/Class;
    //   949: getstatic java/lang/Void.TYPE : Ljava/lang/Class;
    //   952: invokevirtual equals : (Ljava/lang/Object;)Z
    //   955: ifeq -> 1019
    //   958: goto -> 965
    //   961: invokestatic a : (Ljava/lang/Throwable;)Ljava/lang/Throwable;
    //   964: athrow
    //   965: aload #6
    //   967: iconst_1
    //   968: invokevirtual setAccessible : (Z)V
    //   971: aload #6
    //   973: aconst_null
    //   974: iconst_2
    //   975: anewarray java/lang/Object
    //   978: dup
    //   979: iconst_0
    //   980: aload_0
    //   981: aastore
    //   982: dup
    //   983: iconst_1
    //   984: aload_1
    //   985: ifnonnull -> 1003
    //   988: goto -> 995
    //   991: invokestatic a : (Ljava/lang/Throwable;)Ljava/lang/Throwable;
    //   994: athrow
    //   995: aload_1
    //   996: goto -> 1010
    //   999: invokestatic a : (Ljava/lang/Throwable;)Ljava/lang/Throwable;
    //   1002: athrow
    //   1003: aload_1
    //   1004: checkcast [B
    //   1007: invokevirtual clone : ()Ljava/lang/Object;
    //   1010: aastore
    //   1011: invokevirtual invoke : (Ljava/lang/Object;[Ljava/lang/Object;)Ljava/lang/Object;
    //   1014: pop
    //   1015: iload_2
    //   1016: ifeq -> 1033
    //   1019: iinc #5, 1
    //   1022: iload_2
    //   1023: ifeq -> 897
    //   1026: goto -> 1033
    //   1029: invokestatic a : (Ljava/lang/Throwable;)Ljava/lang/Throwable;
    //   1032: athrow
    //   1033: ldc2_w 8682522807148012
    //   1036: invokestatic currentTimeMillis : ()J
    //   1039: lxor
    //   1040: lstore #4
    //   1042: lload #4
    //   1044: ldc2_w 25214903917
    //   1047: lmul
    //   1048: ldc2_w 11
    //   1051: ladd
    //   1052: ldc2_w 281474976710655
    //   1055: land
    //   1056: lstore #4
    //   1058: lload #4
    //   1060: bipush #32
    //   1062: lshl
    //   1063: lstore #6
    //   1065: lload #4
    //   1067: ldc2_w 25214903917
    //   1070: lmul
    //   1071: ldc2_w 11
    //   1074: ladd
    //   1075: ldc2_w 281474976710655
    //   1078: land
    //   1079: lstore #4
    //   1081: lload #6
    //   1083: lload #4
    //   1085: ladd
    //   1086: lstore #6
    //   1088: bipush #16
    //   1090: newarray byte
    //   1092: dup
    //   1093: iconst_0
    //   1094: bipush #48
    //   1096: bastore
    //   1097: dup
    //   1098: iconst_1
    //   1099: bipush #49
    //   1101: bastore
    //   1102: dup
    //   1103: iconst_2
    //   1104: bipush #50
    //   1106: bastore
    //   1107: dup
    //   1108: iconst_3
    //   1109: bipush #51
    //   1111: bastore
    //   1112: dup
    //   1113: iconst_4
    //   1114: bipush #52
    //   1116: bastore
    //   1117: dup
    //   1118: iconst_5
    //   1119: bipush #53
    //   1121: bastore
    //   1122: dup
    //   1123: bipush #6
    //   1125: bipush #54
    //   1127: bastore
    //   1128: dup
    //   1129: bipush #7
    //   1131: bipush #55
    //   1133: bastore
    //   1134: dup
    //   1135: bipush #8
    //   1137: bipush #56
    //   1139: bastore
    //   1140: dup
    //   1141: bipush #9
    //   1143: bipush #57
    //   1145: bastore
    //   1146: dup
    //   1147: bipush #10
    //   1149: bipush #97
    //   1151: bastore
    //   1152: dup
    //   1153: bipush #11
    //   1155: bipush #98
    //   1157: bastore
    //   1158: dup
    //   1159: bipush #12
    //   1161: bipush #99
    //   1163: bastore
    //   1164: dup
    //   1165: bipush #13
    //   1167: bipush #100
    //   1169: bastore
    //   1170: dup
    //   1171: bipush #14
    //   1173: bipush #101
    //   1175: bastore
    //   1176: dup
    //   1177: bipush #15
    //   1179: bipush #102
    //   1181: bastore
    //   1182: astore #8
    //   1184: bipush #64
    //   1186: newarray byte
    //   1188: astore #9
    //   1190: bipush #64
    //   1192: istore #10
    //   1194: bipush #16
    //   1196: istore #11
    //   1198: iload #11
    //   1200: iconst_1
    //   1201: isub
    //   1202: i2l
    //   1203: lstore #12
    //   1205: aload #9
    //   1207: iinc #10, -1
    //   1210: iload #10
    //   1212: aload #8
    //   1214: lload #6
    //   1216: lload #12
    //   1218: land
    //   1219: l2i
    //   1220: baload
    //   1221: bastore
    //   1222: lload #6
    //   1224: iconst_4
    //   1225: lushr
    //   1226: lstore #6
    //   1228: lload #6
    //   1230: lconst_0
    //   1231: lcmp
    //   1232: ifne -> 1205
    //   1235: bipush #64
    //   1237: iload #10
    //   1239: isub
    //   1240: newarray byte
    //   1242: astore_3
    //   1243: iconst_0
    //   1244: istore #14
    //   1246: iload #14
    //   1248: aload_3
    //   1249: arraylength
    //   1250: if_icmpge -> 1272
    //   1253: aload_3
    //   1254: iload #14
    //   1256: aload #9
    //   1258: iload #10
    //   1260: iload #14
    //   1262: iadd
    //   1263: baload
    //   1264: bastore
    //   1265: iinc #14, 1
    //   1268: iload_2
    //   1269: ifeq -> 1246
    //   1272: aload_3
    //   1273: arraylength
    //   1274: bipush #10
    //   1276: if_icmplt -> 1042
    //   1279: getstatic burp/Zkdq.ZZ : Ljava/lang/String;
    //   1282: getstatic burp/Zrm6.Z_ : Ljava/lang/Object;
    //   1285: checkcast java/math/BigInteger
    //   1288: invokevirtual intValue : ()I
    //   1291: bipush #32
    //   1293: irem
    //   1294: invokestatic abs : (I)I
    //   1297: invokevirtual charAt : (I)C
    //   1300: getstatic burp/Zgsy.Zv : Ljava/lang/String;
    //   1303: getstatic burp/Zxan.ZX : Ljava/lang/Object;
    //   1306: checkcast java/math/BigInteger
    //   1309: invokevirtual intValue : ()I
    //   1312: bipush #32
    //   1314: irem
    //   1315: invokestatic abs : (I)I
    //   1318: invokevirtual charAt : (I)C
    //   1321: if_icmpgt -> 1428
    //   1324: getstatic burp/Zbl4.Ze : Ljava/lang/String;
    //   1327: getstatic burp/Zxju.ZN : Ljava/lang/Object;
    //   1330: checkcast java/math/BigInteger
    //   1333: invokevirtual intValue : ()I
    //   1336: bipush #32
    //   1338: irem
    //   1339: invokestatic abs : (I)I
    //   1342: invokevirtual charAt : (I)C
    //   1345: getstatic burp/Zxzv.ZI : Ljava/lang/String;
    //   1348: getstatic burp/Zoe.ZG : Ljava/lang/Object;
    //   1351: checkcast java/math/BigInteger
    //   1354: invokevirtual intValue : ()I
    //   1357: bipush #32
    //   1359: irem
    //   1360: invokestatic abs : (I)I
    //   1363: invokevirtual charAt : (I)C
    //   1366: if_icmple -> 1428
    //   1369: goto -> 1376
    //   1372: invokestatic a : (Ljava/lang/Throwable;)Ljava/lang/Throwable;
    //   1375: athrow
    //   1376: getstatic burp/Znu.ZF : Ljava/lang/String;
    //   1379: getstatic burp/Zspg.ZJ : Ljava/lang/Object;
    //   1382: checkcast java/math/BigInteger
    //   1385: invokevirtual intValue : ()I
    //   1388: bipush #32
    //   1390: irem
    //   1391: invokestatic abs : (I)I
    //   1394: invokevirtual charAt : (I)C
    //   1397: getstatic burp/Zb_1.Zc : Ljava/lang/String;
    //   1400: getstatic burp/Zzl4.ZX : Ljava/lang/Object;
    //   1403: checkcast java/math/BigInteger
    //   1406: invokevirtual intValue : ()I
    //   1409: bipush #32
    //   1411: irem
    //   1412: invokestatic abs : (I)I
    //   1415: invokevirtual charAt : (I)C
    //   1418: if_icmple -> 1436
    //   1421: goto -> 1428
    //   1424: invokestatic a : (Ljava/lang/Throwable;)Ljava/lang/Throwable;
    //   1427: athrow
    //   1428: iconst_1
    //   1429: goto -> 1437
    //   1432: invokestatic a : (Ljava/lang/Throwable;)Ljava/lang/Throwable;
    //   1435: athrow
    //   1436: iconst_0
    //   1437: ireturn
    //   1438: astore_3
    //   1439: new java/lang/Exception
    //   1442: dup
    //   1443: aload_3
    //   1444: invokevirtual getMessage : ()Ljava/lang/String;
    //   1447: invokespecial <init> : (Ljava/lang/String;)V
    //   1450: athrow
    // Exception table:
    //   from	to	target	type
    //   4	1437	1438	java/lang/Throwable
    //   327	351	354	java/lang/Throwable
    //   425	462	462	java/lang/Throwable
    //   466	487	487	java/lang/Throwable
    //   491	521	521	java/lang/Throwable
    //   746	760	760	java/lang/Throwable
    //   771	784	787	java/lang/Throwable
    //   776	799	802	java/lang/Throwable
    //   791	817	820	java/lang/Throwable
    //   806	847	850	java/lang/Throwable
    //   910	937	940	java/lang/Throwable
    //   927	958	961	java/lang/Throwable
    //   944	988	991	java/lang/Throwable
    //   965	999	999	java/lang/Throwable
    //   1010	1026	1029	java/lang/Throwable
    //   1279	1369	1372	java/lang/Throwable
    //   1324	1421	1424	java/lang/Throwable
    //   1376	1432	1432	java/lang/Throwable
  }
  
  static void Zi(Object paramObject) {
    Zxan.ZJ = a(17066, -196);
    Zxan.ZX = new BigInteger(a(17061, 11687));
    boolean bool = Zt2e.ZK();
    try {
      try {
        if (Zmf2.ZK.charAt(Math.abs(((BigInteger)Zr_x.Zd).intValue() % 32)) <= Zsn3.ZS.charAt(Math.abs(((BigInteger)Zsn3.Zy).intValue() % 32))) {
          try {
            Znu.ZH(Class.forName(a(17062, -28732)));
            if (bool)
              Zg2u.ZQ(Class.forName(a(17065, -24587))); 
          } catch (Throwable throwable) {
            throw a(null);
          } 
          return;
        } 
      } catch (Throwable throwable) {
        throw a(null);
      } 
      Zg2u.ZQ(Class.forName(a(17065, -24587)));
    } catch (Throwable throwable) {}
  }
  
  static {
    // Byte code:
    //   0: bipush #11
    //   2: anewarray java/lang/String
    //   5: astore #5
    //   7: iconst_0
    //   8: istore_3
    //   9: ldc '}Â¨ÂœPÃ†Ã…<ÂÃ£1Oc Ã¯yNOÃ’Â\\fÂµnÂÂœÂ¸ÃœÃ‡ilÂ»Y:QA%Â§2H1wÂ°t\\t%1Â—cyÂ Ã©Ã°\\n\\tÂ’wÂƒoWÃ¥Ãˆ\\tÃ³S;Ã¡Â«Ã«Ãƒy ÃŠ\\f=Ã¾ÂµMÂžÂÃ‰SWÃ…DÂ‚_ÂžMÃˆ\\rMmÂ¯Â7Ã‘kdCCÂ  ÃŸÂŒtÂ8v\\nÃŸÂ–Â”Ã­9.Â–Âˆ#>SÂ™ÃÃ¯Ã²F>ÂÂÃ³Ã¼mÂ¹Ã’'
    //   11: dup
    //   12: astore_2
    //   13: invokevirtual length : ()I
    //   16: istore #4
    //   18: bipush #9
    //   20: istore_1
    //   21: iconst_m1
    //   22: istore_0
    //   23: bipush #77
    //   25: iinc #0, 1
    //   28: aload_2
    //   29: iload_0
    //   30: dup
    //   31: iload_1
    //   32: iadd
    //   33: invokevirtual substring : (II)Ljava/lang/String;
    //   36: iconst_m1
    //   37: goto -> 143
    //   40: aload #5
    //   42: swap
    //   43: iload_3
    //   44: iinc #3, 1
    //   47: swap
    //   48: aastore
    //   49: iload_0
    //   50: iload_1
    //   51: iadd
    //   52: dup
    //   53: istore_0
    //   54: iload #4
    //   56: if_icmpge -> 68
    //   59: aload_2
    //   60: iload_0
    //   61: invokevirtual charAt : (I)C
    //   64: istore_1
    //   65: goto -> 23
    //   68: ldc 'Âš~\\bÂ¥<Â¾Ã¼ÂÃ†Â®Z+ÂŒÂ·Â®"&Ã‚}Ã”^ÃÃ¶ÂœÂ†*}-xÃ¡Ã”Ã®FoEÂ¯Â–|F3Â¨ÂµAHÃ¹Ã Ã Ã¸ÃhÂ²\\tHuPÃ°U>ÂªÃ´KÂƒÂœÃ¡@\\tÃ˜\\tTÂ¸vÃ¼C('
    //   70: dup
    //   71: astore_2
    //   72: invokevirtual length : ()I
    //   75: istore #4
    //   77: bipush #77
    //   79: istore_1
    //   80: iconst_m1
    //   81: istore_0
    //   82: bipush #22
    //   84: iinc #0, 1
    //   87: aload_2
    //   88: iload_0
    //   89: dup
    //   90: iload_1
    //   91: iadd
    //   92: invokevirtual substring : (II)Ljava/lang/String;
    //   95: iconst_0
    //   96: goto -> 143
    //   99: aload #5
    //   101: swap
    //   102: iload_3
    //   103: iinc #3, 1
    //   106: swap
    //   107: aastore
    //   108: iload_0
    //   109: iload_1
    //   110: iadd
    //   111: dup
    //   112: istore_0
    //   113: iload #4
    //   115: if_icmpge -> 127
    //   118: aload_2
    //   119: iload_0
    //   120: invokevirtual charAt : (I)C
    //   123: istore_1
    //   124: goto -> 82
    //   127: aload #5
    //   129: putstatic burp/Zm_u.a : [Ljava/lang/String;
    //   132: bipush #11
    //   134: anewarray java/lang/String
    //   137: putstatic burp/Zm_u.b : [Ljava/lang/String;
    //   140: goto -> 300
    //   143: dup_x2
    //   144: pop
    //   145: invokevirtual toCharArray : ()[C
    //   148: dup_x1
    //   149: arraylength
    //   150: dup_x2
    //   151: pop
    //   152: iconst_0
    //   153: istore #6
    //   155: dup2_x1
    //   156: pop2
    //   157: dup_x2
    //   158: iconst_1
    //   159: if_icmpgt -> 259
    //   162: dup2
    //   163: swap
    //   164: iload #6
    //   166: dup2_x1
    //   167: caload
    //   168: swap
    //   169: iload #6
    //   171: bipush #7
    //   173: irem
    //   174: tableswitch default -> 241, 0 -> 212, 1 -> 217, 2 -> 221, 3 -> 226, 4 -> 231, 5 -> 236
    //   212: bipush #12
    //   214: goto -> 243
    //   217: iconst_1
    //   218: goto -> 243
    //   221: bipush #10
    //   223: goto -> 243
    //   226: bipush #42
    //   228: goto -> 243
    //   231: bipush #60
    //   233: goto -> 243
    //   236: bipush #73
    //   238: goto -> 243
    //   241: bipush #52
    //   243: ixor
    //   244: ixor
    //   245: i2c
    //   246: castore
    //   247: iinc #6, 1
    //   250: dup
    //   251: ifne -> 259
    //   254: dup2
    //   255: dup_x1
    //   256: goto -> 166
    //   259: dup2_x1
    //   260: pop2
    //   261: dup_x2
    //   262: iload #6
    //   264: if_icmpgt -> 162
    //   267: pop
    //   268: new java/lang/String
    //   271: dup_x1
    //   272: swap
    //   273: invokespecial <init> : ([C)V
    //   276: invokevirtual intern : ()Ljava/lang/String;
    //   279: swap
    //   280: pop
    //   281: swap
    //   282: tableswitch default -> 40, 0 -> 99
    //   300: new java/math/BigInteger
    //   303: dup
    //   304: iconst_1
    //   305: bipush #32
    //   307: newarray byte
    //   309: dup
    //   310: iconst_0
    //   311: bipush #49
    //   313: bastore
    //   314: dup
    //   315: iconst_1
    //   316: bipush #-53
    //   318: bastore
    //   319: dup
    //   320: iconst_2
    //   321: bipush #-41
    //   323: bastore
    //   324: dup
    //   325: iconst_3
    //   326: bipush #100
    //   328: bastore
    //   329: dup
    //   330: iconst_4
    //   331: bipush #101
    //   333: bastore
    //   334: dup
    //   335: iconst_5
    //   336: bipush #27
    //   338: bastore
    //   339: dup
    //   340: bipush #6
    //   342: bipush #76
    //   344: bastore
    //   345: dup
    //   346: bipush #7
    //   348: bipush #-41
    //   350: bastore
    //   351: dup
    //   352: bipush #8
    //   354: bipush #52
    //   356: bastore
    //   357: dup
    //   358: bipush #9
    //   360: bipush #-119
    //   362: bastore
    //   363: dup
    //   364: bipush #10
    //   366: bipush #73
    //   368: bastore
    //   369: dup
    //   370: bipush #11
    //   372: bipush #91
    //   374: bastore
    //   375: dup
    //   376: bipush #12
    //   378: bipush #20
    //   380: bastore
    //   381: dup
    //   382: bipush #13
    //   384: bipush #-4
    //   386: bastore
    //   387: dup
    //   388: bipush #14
    //   390: bipush #97
    //   392: bastore
    //   393: dup
    //   394: bipush #15
    //   396: bipush #57
    //   398: bastore
    //   399: dup
    //   400: bipush #16
    //   402: bipush #-103
    //   404: bastore
    //   405: dup
    //   406: bipush #17
    //   408: bipush #9
    //   410: bastore
    //   411: dup
    //   412: bipush #18
    //   414: bipush #-67
    //   416: bastore
    //   417: dup
    //   418: bipush #19
    //   420: bipush #-73
    //   422: bastore
    //   423: dup
    //   424: bipush #20
    //   426: bipush #-66
    //   428: bastore
    //   429: dup
    //   430: bipush #21
    //   432: bipush #-71
    //   434: bastore
    //   435: dup
    //   436: bipush #22
    //   438: bipush #118
    //   440: bastore
    //   441: dup
    //   442: bipush #23
    //   444: iconst_1
    //   445: bastore
    //   446: dup
    //   447: bipush #24
    //   449: bipush #117
    //   451: bastore
    //   452: dup
    //   453: bipush #25
    //   455: bipush #80
    //   457: bastore
    //   458: dup
    //   459: bipush #26
    //   461: bipush #-116
    //   463: bastore
    //   464: dup
    //   465: bipush #27
    //   467: bipush #-10
    //   469: bastore
    //   470: dup
    //   471: bipush #28
    //   473: bipush #-110
    //   475: bastore
    //   476: dup
    //   477: bipush #29
    //   479: bipush #31
    //   481: bastore
    //   482: dup
    //   483: bipush #30
    //   485: bipush #-73
    //   487: bastore
    //   488: dup
    //   489: bipush #31
    //   491: bipush #-64
    //   493: bastore
    //   494: invokespecial <init> : (I[B)V
    //   497: putstatic burp/Zm_u.Zf : Ljava/lang/Object;
    //   500: sipush #17070
    //   503: sipush #-11444
    //   506: invokestatic a : (II)Ljava/lang/String;
    //   509: putstatic burp/Zm_u.Zi : Ljava/lang/String;
    //   512: return
  }
  
  private static Throwable a(Throwable paramThrowable) {
    return paramThrowable;
  }
  
  private static String a(int paramInt1, int paramInt2) {
    int i = (paramInt1 ^ 0x42AC) & 0xFFFF;
    if (b[i] == null) {
      char[] arrayOfChar = a[i].toCharArray();
      switch (arrayOfChar[0] & 0xFF) {
        case 0:
        
        case 1:
        
        case 2:
        
        case 3:
        
        case 4:
        
        case 5:
        
        case 6:
        
        case 7:
        
        case 8:
        
        case 9:
        
        case 10:
        
        case 11:
        
        case 12:
        
        case 13:
        
        case 14:
        
        case 15:
        
        case 16:
        
        case 17:
        
        case 18:
        
        case 19:
        
        case 20:
        
        case 21:
        
        case 22:
        
        case 23:
        
        case 24:
        
        case 25:
        
        case 26:
        
        case 27:
        
        case 28:
        
        case 29:
        
        case 30:
        
        case 31:
        
        case 32:
        
        case 33:
        
        case 34:
        
        case 35:
        
        case 36:
        
        case 37:
        
        case 38:
        
        case 39:
        
        case 40:
        
        case 41:
        
        case 42:
        
        case 43:
        
        case 44:
        
        case 45:
        
        case 46:
        
        case 47:
        
        case 48:
        
        case 49:
        
        case 50:
        
        case 51:
        
        case 52:
        
        case 53:
        
        case 54:
        
        case 55:
        
        case 56:
        
        case 57:
        
        case 58:
        
        case 59:
        
        case 60:
        
        case 61:
        
        case 62:
        
        case 63:
        
        case 64:
        
        case 65:
        
        case 66:
        
        case 67:
        
        case 68:
        
        case 69:
        
        case 70:
        
        case 71:
        
        case 72:
        
        case 73:
        
        case 74:
        
        case 75:
        
        case 76:
        
        case 77:
        
        case 78:
        
        case 79:
        
        case 80:
        
        case 81:
        
        case 82:
        
        case 83:
        
        case 84:
        
        case 85:
        
        case 86:
        
        case 87:
        
        case 88:
        
        case 89:
        
        case 90:
        
        case 91:
        
        case 92:
        
        case 93:
        
        case 94:
        
        case 95:
        
        case 96:
        
        case 97:
        
        case 98:
        
        case 99:
        
        case 100:
        
        case 101:
        
        case 102:
        
        case 103:
        
        case 104:
        
        case 105:
        
        case 106:
        
        case 107:
        
        case 108:
        
        case 109:
        
        case 110:
        
        case 111:
        
        case 112:
        
        case 113:
        
        case 114:
        
        case 115:
        
        case 116:
        
        case 117:
        
        case 118:
        
        case 119:
        
        case 120:
        
        case 121:
        
        case 122:
        
        case 123:
        
        case 124:
        
        case 125:
        
        case 126:
        
        case 127:
        
        case 128:
        
        case 129:
        
        case 130:
        
        case 131:
        
        case 132:
        
        case 133:
        
        case 134:
        
        case 135:
        
        case 136:
        
        case 137:
        
        case 138:
        
        case 139:
        
        case 140:
        
        case 141:
        
        case 142:
        
        case 143:
        
        case 144:
        
        case 145:
        
        case 146:
        
        case 147:
        
        case 148:
        
        case 149:
        
        case 150:
        
        case 151:
        
        case 152:
        
        case 153:
        
        case 154:
        
        case 155:
        
        case 156:
        
        case 157:
        
        case 158:
        
        case 159:
        
        case 160:
        
        case 161:
        
        case 162:
        
        case 163:
        
        case 164:
        
        case 165:
        
        case 166:
        
        case 167:
        
        case 168:
        
        case 169:
        
        case 170:
        
        case 171:
        
        case 172:
        
        case 173:
        
        case 174:
        
        case 175:
        
        case 176:
        
        case 177:
        
        case 178:
        
        case 179:
        
        case 180:
        
        case 181:
        
        case 182:
        
        case 183:
        
        case 184:
        
        case 185:
        
        case 186:
        
        case 187:
        
        case 188:
        
        case 189:
        
        case 190:
        
        case 191:
        
        case 192:
        
        case 193:
        
        case 194:
        
        case 195:
        
        case 196:
        
        case 197:
        
        case 198:
        
        case 199:
        
        case 200:
        
        case 201:
        
        case 202:
        
        case 203:
        
        case 204:
        
        case 205:
        
        case 206:
        
        case 207:
        
        case 208:
        
        case 209:
        
        case 210:
        
        case 211:
        
        case 212:
        
        case 213:
        
        case 214:
        
        case 215:
        
        case 216:
        
        case 217:
        
        case 218:
        
        case 219:
        
        case 220:
        
        case 221:
        
        case 222:
        
        case 223:
        
        case 224:
        
        case 225:
        
        case 226:
        
        case 227:
        
        case 228:
        
        case 229:
        
        case 230:
        
        case 231:
        
        case 232:
        
        case 233:
        
        case 234:
        
        case 235:
        
        case 236:
        
        case 237:
        
        case 238:
        
        case 239:
        
        case 240:
        
        case 241:
        
        case 242:
        
        case 243:
        
        case 244:
        
        case 245:
        
        case 246:
        
        case 247:
        
        case 248:
        
        case 249:
        
        case 250:
        
        case 251:
        
        case 252:
        
        case 253:
        
        case 254:
        
        default:
          break;
      } 
      byte b1 = 120;
      int j = (paramInt2 & 0xFF) - b1;
      if (j < 0)
        j += 256; 
      int k = ((paramInt2 & 0xFFFF) >>> 8) - b1;
      if (k < 0)
        k += 256; 
      for (byte b2 = 0; b2 < arrayOfChar.length; b2++) {
        int m = b2 % 2;
        if (m == 0) {
          arrayOfChar[b2] = (char)(arrayOfChar[b2] ^ j);
          j = ((j >>> 3 | j << 5) ^ arrayOfChar[b2]) & 0xFF;
        } else {
          arrayOfChar[b2] = (char)(arrayOfChar[b2] ^ k);
          k = ((k >>> 3 | k << 5) ^ arrayOfChar[b2]) & 0xFF;
        } 
      } 
      b[i] = (new String(arrayOfChar)).intern();
    } 
    return b[i];
  }
}


/* Location:              C:\Program Files\BurpSuitePro\burpsuite_pro.jar!\burp\Zm_u.class
 * Java compiler version: 21 (65.0)
 * JD-Core Version:       1.1.3
 */