package burp;

import java.util.EnumSet;

public class Zme3 extends Zmvg {
  private static final String[] a;
  
  private static final String[] b;
  
  public Zme3() {
    super(EnumSet.of(Zzqz.VARIANT, Zzqz.FLAGS));
  }
  
  public String Zi(Zvs paramZvs, byte paramByte1, int paramInt, Ztlj paramZtlj, Ztub paramZtub, Zefg<Zxtl> paramZefg, Zmzk paramZmzk, byte[] paramArrayOfbyte, byte paramByte2, byte paramByte3) {
    // Byte code:
    //   0: new java/lang/StringBuilder
    //   3: dup
    //   4: invokespecial <init> : ()V
    //   7: astore #12
    //   9: aload #12
    //   11: sipush #17785
    //   14: sipush #29944
    //   17: invokestatic a : (II)Ljava/lang/String;
    //   20: invokevirtual append : (Ljava/lang/String;)Ljava/lang/StringBuilder;
    //   23: pop
    //   24: invokestatic Zy : ()Z
    //   27: aload #12
    //   29: aload #6
    //   31: iconst_1
    //   32: iconst_1
    //   33: invokestatic Zt : (Lburp/Zefg;ZZ)Ljava/lang/String;
    //   36: invokevirtual append : (Ljava/lang/String;)Ljava/lang/StringBuilder;
    //   39: pop
    //   40: istore #11
    //   42: aload #12
    //   44: sipush #17788
    //   47: sipush #1349
    //   50: invokestatic a : (II)Ljava/lang/String;
    //   53: invokevirtual append : (Ljava/lang/String;)Ljava/lang/StringBuilder;
    //   56: pop
    //   57: iload_2
    //   58: tableswitch default -> 500, 0 -> 148, 1 -> 160, 2 -> 180, 3 -> 200, 4 -> 220, 5 -> 240, 6 -> 260, 7 -> 280, 8 -> 300, 9 -> 320, 10 -> 340, 11 -> 148, 12 -> 360, 13 -> 380, 14 -> 400, 15 -> 420, 16 -> 440, 17 -> 460, 18 -> 480
    //   148: iload #11
    //   150: ifne -> 509
    //   153: iconst_1
    //   154: anewarray burp/Zbqc
    //   157: invokestatic Zr : ([Lburp/Zbqc;)V
    //   160: aload #12
    //   162: sipush #17786
    //   165: sipush #7498
    //   168: invokestatic a : (II)Ljava/lang/String;
    //   171: invokevirtual append : (Ljava/lang/String;)Ljava/lang/StringBuilder;
    //   174: pop
    //   175: iload #11
    //   177: ifne -> 509
    //   180: aload #12
    //   182: sipush #17769
    //   185: sipush #12744
    //   188: invokestatic a : (II)Ljava/lang/String;
    //   191: invokevirtual append : (Ljava/lang/String;)Ljava/lang/StringBuilder;
    //   194: pop
    //   195: iload #11
    //   197: ifne -> 509
    //   200: aload #12
    //   202: sipush #17736
    //   205: sipush #9025
    //   208: invokestatic a : (II)Ljava/lang/String;
    //   211: invokevirtual append : (Ljava/lang/String;)Ljava/lang/StringBuilder;
    //   214: pop
    //   215: iload #11
    //   217: ifne -> 509
    //   220: aload #12
    //   222: sipush #17763
    //   225: sipush #-18699
    //   228: invokestatic a : (II)Ljava/lang/String;
    //   231: invokevirtual append : (Ljava/lang/String;)Ljava/lang/StringBuilder;
    //   234: pop
    //   235: iload #11
    //   237: ifne -> 509
    //   240: aload #12
    //   242: sipush #17765
    //   245: sipush #18358
    //   248: invokestatic a : (II)Ljava/lang/String;
    //   251: invokevirtual append : (Ljava/lang/String;)Ljava/lang/StringBuilder;
    //   254: pop
    //   255: iload #11
    //   257: ifne -> 509
    //   260: aload #12
    //   262: sipush #17766
    //   265: sipush #-17241
    //   268: invokestatic a : (II)Ljava/lang/String;
    //   271: invokevirtual append : (Ljava/lang/String;)Ljava/lang/StringBuilder;
    //   274: pop
    //   275: iload #11
    //   277: ifne -> 509
    //   280: aload #12
    //   282: sipush #17779
    //   285: sipush #24090
    //   288: invokestatic a : (II)Ljava/lang/String;
    //   291: invokevirtual append : (Ljava/lang/String;)Ljava/lang/StringBuilder;
    //   294: pop
    //   295: iload #11
    //   297: ifne -> 509
    //   300: aload #12
    //   302: sipush #17731
    //   305: sipush #13858
    //   308: invokestatic a : (II)Ljava/lang/String;
    //   311: invokevirtual append : (Ljava/lang/String;)Ljava/lang/StringBuilder;
    //   314: pop
    //   315: iload #11
    //   317: ifne -> 509
    //   320: aload #12
    //   322: sipush #17778
    //   325: sipush #-17722
    //   328: invokestatic a : (II)Ljava/lang/String;
    //   331: invokevirtual append : (Ljava/lang/String;)Ljava/lang/StringBuilder;
    //   334: pop
    //   335: iload #11
    //   337: ifne -> 509
    //   340: aload #12
    //   342: sipush #17791
    //   345: sipush #25029
    //   348: invokestatic a : (II)Ljava/lang/String;
    //   351: invokevirtual append : (Ljava/lang/String;)Ljava/lang/StringBuilder;
    //   354: pop
    //   355: iload #11
    //   357: ifne -> 509
    //   360: aload #12
    //   362: sipush #17730
    //   365: sipush #-10383
    //   368: invokestatic a : (II)Ljava/lang/String;
    //   371: invokevirtual append : (Ljava/lang/String;)Ljava/lang/StringBuilder;
    //   374: pop
    //   375: iload #11
    //   377: ifne -> 509
    //   380: aload #12
    //   382: sipush #17770
    //   385: sipush #4366
    //   388: invokestatic a : (II)Ljava/lang/String;
    //   391: invokevirtual append : (Ljava/lang/String;)Ljava/lang/StringBuilder;
    //   394: pop
    //   395: iload #11
    //   397: ifne -> 509
    //   400: aload #12
    //   402: sipush #17733
    //   405: sipush #-24131
    //   408: invokestatic a : (II)Ljava/lang/String;
    //   411: invokevirtual append : (Ljava/lang/String;)Ljava/lang/StringBuilder;
    //   414: pop
    //   415: iload #11
    //   417: ifne -> 509
    //   420: aload #12
    //   422: sipush #17790
    //   425: sipush #-3440
    //   428: invokestatic a : (II)Ljava/lang/String;
    //   431: invokevirtual append : (Ljava/lang/String;)Ljava/lang/StringBuilder;
    //   434: pop
    //   435: iload #11
    //   437: ifne -> 509
    //   440: aload #12
    //   442: sipush #17773
    //   445: sipush #-25685
    //   448: invokestatic a : (II)Ljava/lang/String;
    //   451: invokevirtual append : (Ljava/lang/String;)Ljava/lang/StringBuilder;
    //   454: pop
    //   455: iload #11
    //   457: ifne -> 509
    //   460: aload #12
    //   462: sipush #17771
    //   465: sipush #-28513
    //   468: invokestatic a : (II)Ljava/lang/String;
    //   471: invokevirtual append : (Ljava/lang/String;)Ljava/lang/StringBuilder;
    //   474: pop
    //   475: iload #11
    //   477: ifne -> 509
    //   480: aload #12
    //   482: sipush #17775
    //   485: sipush #-23930
    //   488: invokestatic a : (II)Ljava/lang/String;
    //   491: invokevirtual append : (Ljava/lang/String;)Ljava/lang/StringBuilder;
    //   494: pop
    //   495: iload #11
    //   497: ifne -> 509
    //   500: iconst_0
    //   501: getstatic net/portswigger/Zqf.Zr : Lnet/portswigger/Zqf;
    //   504: iload_2
    //   505: i2l
    //   506: invokestatic Zv : (ZLnet/portswigger/Zqf;J)V
    //   509: aload #12
    //   511: sipush #17776
    //   514: sipush #-3361
    //   517: invokestatic a : (II)Ljava/lang/String;
    //   520: invokevirtual append : (Ljava/lang/String;)Ljava/lang/StringBuilder;
    //   523: pop
    //   524: iload_3
    //   525: iconst_1
    //   526: if_icmpne -> 566
    //   529: aload #5
    //   531: invokevirtual Zr : ()Lburp/Zzq1;
    //   534: invokeinterface Zub : ()Lburp/Zll7;
    //   539: invokeinterface Zsf : ()Lburp/Zstu;
    //   544: invokeinterface ZiD : ()[B
    //   549: astore #13
    //   551: aload #12
    //   553: aload #13
    //   555: invokestatic Zn : ([B)Ljava/lang/String;
    //   558: invokestatic Zn : (Ljava/lang/StringBuilder;Ljava/lang/String;)V
    //   561: iload #11
    //   563: ifne -> 633
    //   566: aload #5
    //   568: invokevirtual ZK : ()Z
    //   571: ifeq -> 601
    //   574: aload #5
    //   576: invokevirtual ZO : ()Lburp/Zg3y;
    //   579: invokeinterface Zub : ()Lburp/Zll7;
    //   584: invokeinterface Zsf : ()Lburp/Zstu;
    //   589: invokeinterface ZiD : ()[B
    //   594: astore #13
    //   596: iload #11
    //   598: ifne -> 623
    //   601: aload #5
    //   603: invokevirtual Zd : ()Lburp/Zkcp;
    //   606: invokeinterface Zub : ()Lburp/Zll7;
    //   611: invokeinterface Zsf : ()Lburp/Zstu;
    //   616: invokeinterface ZiD : ()[B
    //   621: astore #13
    //   623: aload #12
    //   625: aload #13
    //   627: invokestatic Zn : ([B)Ljava/lang/String;
    //   630: invokestatic Zn : (Ljava/lang/StringBuilder;Ljava/lang/String;)V
    //   633: aload #12
    //   635: sipush #17734
    //   638: sipush #13036
    //   641: invokestatic a : (II)Ljava/lang/String;
    //   644: invokevirtual append : (Ljava/lang/String;)Ljava/lang/StringBuilder;
    //   647: pop
    //   648: aload #12
    //   650: aload #6
    //   652: iconst_1
    //   653: iconst_0
    //   654: invokestatic Zt : (Lburp/Zefg;ZZ)Ljava/lang/String;
    //   657: invokevirtual append : (Ljava/lang/String;)Ljava/lang/StringBuilder;
    //   660: pop
    //   661: iload_2
    //   662: ifne -> 759
    //   665: aload #12
    //   667: sipush #17728
    //   670: sipush #-9947
    //   673: invokestatic a : (II)Ljava/lang/String;
    //   676: invokevirtual append : (Ljava/lang/String;)Ljava/lang/StringBuilder;
    //   679: pop
    //   680: aload #12
    //   682: aload #4
    //   684: getstatic burp/Ztz3.REFLECTION : Lburp/Ztz3;
    //   687: invokevirtual Zm : (Lburp/Ztz3;)[B
    //   690: invokestatic Zn : ([B)Ljava/lang/String;
    //   693: invokestatic Zn : (Ljava/lang/StringBuilder;Ljava/lang/String;)V
    //   696: aload #12
    //   698: sipush #17739
    //   701: sipush #-9462
    //   704: invokestatic a : (II)Ljava/lang/String;
    //   707: invokevirtual append : (Ljava/lang/String;)Ljava/lang/StringBuilder;
    //   710: pop
    //   711: aload #12
    //   713: aload #5
    //   715: invokevirtual ZO : ()Lburp/Zg3y;
    //   718: invokeinterface ZXh : ()Lburp/Zll7;
    //   723: invokeinterface Zsf : ()Lburp/Zstu;
    //   728: invokeinterface ZiD : ()[B
    //   733: invokestatic Zn : ([B)Ljava/lang/String;
    //   736: invokestatic Zn : (Ljava/lang/StringBuilder;Ljava/lang/String;)V
    //   739: aload #12
    //   741: sipush #17760
    //   744: sipush #17420
    //   747: invokestatic a : (II)Ljava/lang/String;
    //   750: invokevirtual append : (Ljava/lang/String;)Ljava/lang/StringBuilder;
    //   753: pop
    //   754: iload #11
    //   756: ifne -> 1330
    //   759: aload #12
    //   761: sipush #17784
    //   764: sipush #7349
    //   767: invokestatic a : (II)Ljava/lang/String;
    //   770: invokevirtual append : (Ljava/lang/String;)Ljava/lang/StringBuilder;
    //   773: pop
    //   774: iload_2
    //   775: tableswitch default -> 1220, 1 -> 860, 2 -> 880, 3 -> 900, 4 -> 920, 5 -> 940, 6 -> 960, 7 -> 980, 8 -> 1000, 9 -> 1020, 10 -> 1040, 11 -> 1060, 12 -> 1080, 13 -> 1100, 14 -> 1120, 15 -> 1140, 16 -> 1160, 17 -> 1180, 18 -> 1200
    //   860: aload #12
    //   862: sipush #17762
    //   865: sipush #-25312
    //   868: invokestatic a : (II)Ljava/lang/String;
    //   871: invokevirtual append : (Ljava/lang/String;)Ljava/lang/StringBuilder;
    //   874: pop
    //   875: iload #11
    //   877: ifne -> 1229
    //   880: aload #12
    //   882: sipush #17774
    //   885: sipush #3431
    //   888: invokestatic a : (II)Ljava/lang/String;
    //   891: invokevirtual append : (Ljava/lang/String;)Ljava/lang/StringBuilder;
    //   894: pop
    //   895: iload #11
    //   897: ifne -> 1229
    //   900: aload #12
    //   902: sipush #17740
    //   905: sipush #15545
    //   908: invokestatic a : (II)Ljava/lang/String;
    //   911: invokevirtual append : (Ljava/lang/String;)Ljava/lang/StringBuilder;
    //   914: pop
    //   915: iload #11
    //   917: ifne -> 1229
    //   920: aload #12
    //   922: sipush #17764
    //   925: sipush #-9517
    //   928: invokestatic a : (II)Ljava/lang/String;
    //   931: invokevirtual append : (Ljava/lang/String;)Ljava/lang/StringBuilder;
    //   934: pop
    //   935: iload #11
    //   937: ifne -> 1229
    //   940: aload #12
    //   942: sipush #17737
    //   945: sipush #-9044
    //   948: invokestatic a : (II)Ljava/lang/String;
    //   951: invokevirtual append : (Ljava/lang/String;)Ljava/lang/StringBuilder;
    //   954: pop
    //   955: iload #11
    //   957: ifne -> 1229
    //   960: aload #12
    //   962: sipush #17768
    //   965: sipush #25937
    //   968: invokestatic a : (II)Ljava/lang/String;
    //   971: invokevirtual append : (Ljava/lang/String;)Ljava/lang/StringBuilder;
    //   974: pop
    //   975: iload #11
    //   977: ifne -> 1229
    //   980: aload #12
    //   982: sipush #17735
    //   985: sipush #24024
    //   988: invokestatic a : (II)Ljava/lang/String;
    //   991: invokevirtual append : (Ljava/lang/String;)Ljava/lang/StringBuilder;
    //   994: pop
    //   995: iload #11
    //   997: ifne -> 1229
    //   1000: aload #12
    //   1002: sipush #17741
    //   1005: sipush #32531
    //   1008: invokestatic a : (II)Ljava/lang/String;
    //   1011: invokevirtual append : (Ljava/lang/String;)Ljava/lang/StringBuilder;
    //   1014: pop
    //   1015: iload #11
    //   1017: ifne -> 1229
    //   1020: aload #12
    //   1022: sipush #17777
    //   1025: sipush #-24389
    //   1028: invokestatic a : (II)Ljava/lang/String;
    //   1031: invokevirtual append : (Ljava/lang/String;)Ljava/lang/StringBuilder;
    //   1034: pop
    //   1035: iload #11
    //   1037: ifne -> 1229
    //   1040: aload #12
    //   1042: sipush #17743
    //   1045: sipush #9937
    //   1048: invokestatic a : (II)Ljava/lang/String;
    //   1051: invokevirtual append : (Ljava/lang/String;)Ljava/lang/StringBuilder;
    //   1054: pop
    //   1055: iload #11
    //   1057: ifne -> 1229
    //   1060: aload #12
    //   1062: sipush #17767
    //   1065: sipush #7868
    //   1068: invokestatic a : (II)Ljava/lang/String;
    //   1071: invokevirtual append : (Ljava/lang/String;)Ljava/lang/StringBuilder;
    //   1074: pop
    //   1075: iload #11
    //   1077: ifne -> 1229
    //   1080: aload #12
    //   1082: sipush #17761
    //   1085: sipush #1409
    //   1088: invokestatic a : (II)Ljava/lang/String;
    //   1091: invokevirtual append : (Ljava/lang/String;)Ljava/lang/StringBuilder;
    //   1094: pop
    //   1095: iload #11
    //   1097: ifne -> 1229
    //   1100: aload #12
    //   1102: sipush #17729
    //   1105: sipush #-18021
    //   1108: invokestatic a : (II)Ljava/lang/String;
    //   1111: invokevirtual append : (Ljava/lang/String;)Ljava/lang/StringBuilder;
    //   1114: pop
    //   1115: iload #11
    //   1117: ifne -> 1229
    //   1120: aload #12
    //   1122: sipush #17789
    //   1125: sipush #-27163
    //   1128: invokestatic a : (II)Ljava/lang/String;
    //   1131: invokevirtual append : (Ljava/lang/String;)Ljava/lang/StringBuilder;
    //   1134: pop
    //   1135: iload #11
    //   1137: ifne -> 1229
    //   1140: aload #12
    //   1142: sipush #17732
    //   1145: sipush #16145
    //   1148: invokestatic a : (II)Ljava/lang/String;
    //   1151: invokevirtual append : (Ljava/lang/String;)Ljava/lang/StringBuilder;
    //   1154: pop
    //   1155: iload #11
    //   1157: ifne -> 1229
    //   1160: aload #12
    //   1162: sipush #17781
    //   1165: sipush #4268
    //   1168: invokestatic a : (II)Ljava/lang/String;
    //   1171: invokevirtual append : (Ljava/lang/String;)Ljava/lang/StringBuilder;
    //   1174: pop
    //   1175: iload #11
    //   1177: ifne -> 1229
    //   1180: aload #12
    //   1182: sipush #17782
    //   1185: sipush #24746
    //   1188: invokestatic a : (II)Ljava/lang/String;
    //   1191: invokevirtual append : (Ljava/lang/String;)Ljava/lang/StringBuilder;
    //   1194: pop
    //   1195: iload #11
    //   1197: ifne -> 1229
    //   1200: aload #12
    //   1202: sipush #17783
    //   1205: sipush #10528
    //   1208: invokestatic a : (II)Ljava/lang/String;
    //   1211: invokevirtual append : (Ljava/lang/String;)Ljava/lang/StringBuilder;
    //   1214: pop
    //   1215: iload #11
    //   1217: ifne -> 1229
    //   1220: iconst_0
    //   1221: getstatic net/portswigger/Zqf.Zr : Lnet/portswigger/Zqf;
    //   1224: iload_2
    //   1225: i2l
    //   1226: invokestatic Zv : (ZLnet/portswigger/Zqf;J)V
    //   1229: aload #12
    //   1231: sipush #17738
    //   1234: sipush #23434
    //   1237: invokestatic a : (II)Ljava/lang/String;
    //   1240: invokevirtual append : (Ljava/lang/String;)Ljava/lang/StringBuilder;
    //   1243: pop
    //   1244: iload_3
    //   1245: iconst_1
    //   1246: if_icmpne -> 1269
    //   1249: aload #12
    //   1251: sipush #17787
    //   1254: sipush #22990
    //   1257: invokestatic a : (II)Ljava/lang/String;
    //   1260: invokevirtual append : (Ljava/lang/String;)Ljava/lang/StringBuilder;
    //   1263: pop
    //   1264: iload #11
    //   1266: ifne -> 1315
    //   1269: aload #12
    //   1271: sipush #17742
    //   1274: sipush #18055
    //   1277: invokestatic a : (II)Ljava/lang/String;
    //   1280: invokevirtual append : (Ljava/lang/String;)Ljava/lang/StringBuilder;
    //   1283: pop
    //   1284: aload #12
    //   1286: aload #4
    //   1288: getstatic burp/Ztz3.REFLECTION : Lburp/Ztz3;
    //   1291: invokevirtual Zm : (Lburp/Ztz3;)[B
    //   1294: invokestatic Zn : ([B)Ljava/lang/String;
    //   1297: invokestatic Zn : (Ljava/lang/StringBuilder;Ljava/lang/String;)V
    //   1300: aload #12
    //   1302: sipush #17772
    //   1305: sipush #21605
    //   1308: invokestatic a : (II)Ljava/lang/String;
    //   1311: invokevirtual append : (Ljava/lang/String;)Ljava/lang/StringBuilder;
    //   1314: pop
    //   1315: aload #12
    //   1317: sipush #17780
    //   1320: sipush #13122
    //   1323: invokestatic a : (II)Ljava/lang/String;
    //   1326: invokevirtual append : (Ljava/lang/String;)Ljava/lang/StringBuilder;
    //   1329: pop
    //   1330: aload #12
    //   1332: invokevirtual toString : ()Ljava/lang/String;
    //   1335: areturn
  }
  
  static {
    // Byte code:
    //   0: bipush #48
    //   2: anewarray java/lang/String
    //   5: astore #5
    //   7: iconst_0
    //   8: istore_3
    //   9: ldc 'gÃ¿+Ã¬Â¢Â™mÃ¬Â–Ã’Ã£/(Â­(Ã¾Ã—ÃµÃ‡*Â’ÂºÂ½K0AÂ¦>UÃÂŠÃ·rÃ”Ãµ<Â ÂŸ?Ã‰Â•.5Â•Ã‹/Â1^RÃ´Ã±Â§Âµ7Ã¹*Â†Â©Â„}Â½Ã¤eÂ¶Â‘xÃ ÂŸÃ£ UÃ‡\\nÃ®ÂOkÃ•OÂ›B]Â…ÃŸbzL,[4\\bx Ã¼Ã€xÃ‘E.tdxÂ¶Ã Â¢#Ã¯]Ã™ÃªO%Ã»H+AHcÃ›FFf\Â¼dÃ‹p(&Â¥Ã’tÃˆÃ‹0ÂŸÂŠ*zÂ‹ÂÃ€ÃcÂÂ˜UÂŸBÃ¨Â¥Â€@Ã„Ã§Ã¬Ãƒ&AÃ ihbÃÃµÃ”ÃªÃ’pÃœ\\bÂ¦Â¯e?CÂ»Â”&ÂºdALÂºÃ‹~eMÃ—'Â±_Â‚Â™Â±jÃ„(Â”)ÃŠÂ‰Â˜Ã½Ã¾ÃšÃšÂ¸Â¦Ã¿Âˆ Ti-Ã²kÃƒÂ™Â¬ÃœÃ¡Â¤Â‡Â­Ã”Ã´Ã®Ã‘ÂƒÃ$Â‘Â©yÃ§ÃÃªQÂ¢Ã…\\bDPÂ ÂªÂ•Ã’Ã°A$Âƒ/Â¡Ãƒ\\bÂ\\bÃ»0cÃœÂ¯0Â’ÂºÃÂ£-Â›Ã‘LÂÂ°WÃ¶Â¥\\rÂ®ÃµÂÂ“Ã¸Â 5)\\bÃ·Â‘Ã|GÃÃ€{Â¯SÂ·KÃ²Ã©Â®Â‰Â¨YÂˆÂ…Ä”_Ã‘Ã¥ÃÂ•9Ã½ÃšIÃ¾#Â‰"hC#rÂ·W+Â–Â³0"Â–7Â™]ÃqÂ¿ÃŸÂ¼Ã†ÂµÃ»Â¤Ã°ox&9fÃ¨{ÃÂºfÂ´Ã‚<Â•Â·^Ã¬GÂ¼Ã¬Ã­Â¸GÂ¤Â¦!nÂ§Ã´ÃÂ‹Ã†Ã³Â¼m Ox*Â¥"Â’Â”PnÃ²ÃŸUÃ‚x5Â¡&Â¾Ã›V50Ã‘Ã­)yHEÂ„u2gÃ­Â»Â£Â–NÃŒÂ¬Ã¾kÂ±AÂ“3nBÃ¯ÃÃ½Â¥NÂ§9Â¥RaÃ¿Â¾Ã²Â®Ã±ÃŒlmÂ¶ÂµrÂ„i)Â¥uGdÂœwÃšÂ„Â—Â¤Ã˜4Â¥\\rÂ£DÃµÂ•ZqÂ²Ã£Âœ=Â´Â­yÃ®Â’}VÂeÃ¨Ã¾Â‚+>Ãª[R z:Â…Ã›w+oÃ·Â®IÃ»Ã¼"Ã«Ã_nÂµ@Â¢+WÃ ÂŸÂ»\\bzmÂ¨CÃ«fMÂ¨Â®Ãœ#Ã„Ã´9ÂÂ…Â Âm/+ÃœNÃuÂ¨Â˜Â–ÃŠÃ¤Ã©\\bBÃ’pÂ¿,N4l0ACÂµÂœb|8Â°Â¼/Â³Â¤Ã›ÂŒÃ‚}\\fÃ§Â¬Â·GÃœÃ•5h6Ã²)Ã™Â‚tÂ^Â¡Ã“(0Â¥ÂÃœ,5\\tÂ“e~\CÂ‰Z\\bÂ‹Â˜PÃ¯}Ã <.Â´L}Âµ@Ã‚7Ã£ÃŸXÂº#ÂºÂˆYM`{&RjÂ˜ÃÃ¬TÃviÃ¦ÂÃŠqÃ‹rFÂÂ˜Â‰1Ã¿Ã´N0Â‘Ã•Â¯N!&PÃ»Â±FÂ‰6~\\nvÂ­ÂšÃ½~Ã´Â´Â8Â—ÃŸÂ§_Â¥ÃƒnB_ÃSÃ…Â°{Ã‡0ÂÂ›Â¼A}Â™>Â”ÃŠUÃ¬Â¿Ã‘Ã²eÃÂ®bÂºÃ’;Â†Ã‚/MÂ•+z{Ã®(~Âª[Ã©Â›aÃºÃµ[ÂID<B+ÃºGÂ’Ã¥T(ÂÃ¨[Ã»ÂªqÃ GÃ¬Ã®ÂŒgÃÂºzÃÂ²Ã®g6Â¾Ã§GÂ¬Ã†Â3ÂÃ¾LÂ¯,Ã• IÂ¤Â´`DÃ™Â¦7 \\tt5ÃºÂ‚$ÂŒH(Ã¥QÃ´Ã•2Â{Â¼Â½HUÃ»Â‹ÃŸg;~%Ã¦Â¸^leÃ5aÂ©\Ã³rÂŠlÃ·ÃÃC.  uwÂ‹4K2ÃŸ*fÂ±Ã™wUÂ¹ÂvÂ¥ÂxÂ‰Ã£e4ÂÃÃ¢Â“aÃœÃ¾ ÂX-ZÂÃ«Â§Â½fÃ²Ã±Â ?Â‹Ã¸CSÂ€Ã¥gÂ«jEÃ´Â Ã¬Â˜Ã¯Â¢Â¥Ã¬Â¿Ã’\\rÃ©Ã¯ÂŸu[Ã™Ã§Ã«ÃSÂmÃ¨\\bÂÃ§Ã”"LÂ³Â LEAÃ NBÃˆ^Â½Â»|+8\\tÂ˜ÂÃ¹ÂÃŸsÃ·}UQp7Â€Ã¦ÃÂ(Â£Ã‡U>Â†4Ã·jcÂ¹Â¸Ã˜c$Ã—Â½ÃÃ¶Â¯Â‘9Â‹Ã‹%1Â‰mÃ£Â‡A^Ãº[Â Â„HlXÂ¥Â«Â¢ÂµÃ†Ã¶Ã±Â˜Â¹?<s\\tÂƒvÃÂ„ Â¶2Â€UÂ^e$Ã˜Â»Â N0Âˆr^Â‚rÂ¼ÃŸnÂ°<Ã)\\tÂµÃYÂ‡Ã—Â¡Ã’Â”LRNÃU,Â±Ã²&)Ã“Â£Ã¢Â³Ã¢iÃ‰Â»FÃ€Ã‚4O h2wÃ-ÂeC\\fÃ°Ã¿=Ã¡Ã¦Ã—Â–t?Ã™\\r]Â“Â“Â“PSÂ¡DÃ¹Ã¼Ã­Ã°0Ã›'ÂÃ¸sdÃ Ã‡Â§LÂ†hÂ‰Ã¿TÃ³Â™Ã¸Ã˜WÂ·+:hW}CÃ…nÃ‡o,ÃšiaaÃ¹Ã§0IÂ½Ã›\\bÃµ\\tÃ¥Â˜HÃƒÃ¢ÂœÃ»Â½Ã™Ã ?3SÂ„Ã·Â¶0[fÂ‘Ã·EÂ¿NjÂ–Ã‡Ã½xÂ›Â±Ã»]MÂƒh,Ã’XÂ˜ÃµÂ›iÂ±cÂœÂµÂ±Â´ÃŠÂ…fLÃ‘Âª:|$Â¹/Ã¬Â¡[KÂ¢ÃGÃ¤Â—Â» ÂªÃƒÃŸg/ÃÃ€Ã¶Ã†Ã¨iÃ¯JÂ¯Ãš\\n(Â¨oZÃªmw\\rP*Ã©Ã€54D^?ÃœÃ½4;0ÃºÃ²Â‹Â±\\tGBÂœ_YÂ¨Ã‚^ÂŠÃ¡lÂ’_Ã‚Â·Ã\\nÂŠiÃ±;Ã¾ÃµÂ‘Â„Â°gqÃ‚Â¯XÃ¸2@Â¥. Â¿Ã¦)ÂŒ,Ã¢LÃ}Ã«@Ã±1pÃŠV~%cÂ›\\tEaÂ¿Â©:CÂ—\\bÃ®ÃƒÂœÂ†)-Ã“N#V`Â€!DÃ¤\\n\\tÃˆÃ¹>\Ã˜Â¹W\\f^Ã‡Ã¦^Â¬Â¬Â•jÂ¯VÂ˜ÂD/Â‰0Ã²Â½ÂªcÂºhÂ¸43Ã‡Â·ÂO=Â½Ã¯ÂšÂ¶ÂÃ¼\\r1sÂ¶Â‘9nÃ›ÂœS3|Â¦ÂÂ›Ã“ÃŠÃ‹Ã¼Ã±V>d-Â¯Ã²hÂªÃ™ÂºOhR4nÃ‡Â¹Â·Ã»OÂ“Â½:Âš\\fÂÂ«\\rÃ›sÃ«Â‘Â’nÂ®ÂœÃ½3Â©Â¦Â§Â™Ã®ÃµWxÂµÃ¬ÂÂŠÂ¸/ÂÂ»fÂœÂÂ²CFÃ…#%\Â©Ã€Ã¡AÃˆt\Ãº~Â„Â«Â”yÃŸÂ§wr%\\rÃ¤Â…Ã³;\\fÃ«yÃ•Ã´Ã•9Â‚HÃ¼\Ã¤FÂ­nÂÂ›`{Ã‰ÃOu$2eSÂŒÂ¡Â€ÂÂ˜Ã½Ã¹ÂˆÂ—Ã¶>QÃ[Â‚0ÃÃ²kÂ±Ã\\f^\\bÃ²Ã¼Ã“Ã¿Â©Ã‰="VcÃ Ã Ã¦Â„Â£Â…@Â·~vÃ½aÂ¦~H.Ã¸PÂºÂÃ†$4Ã£Â™CÃÂ¦Ã…;y^Ã4ÂÃ¡Ã³Âš)\\nÃ…WÂ N&Ã®}Ã²/qLÃŒIÃ³R\\nÃ²acÃœÃµÂ“ÃŸÂ—Ã¸'
    //   11: dup
    //   12: astore_2
    //   13: invokevirtual length : ()I
    //   16: istore #4
    //   18: bipush #51
    //   20: istore_1
    //   21: iconst_m1
    //   22: istore_0
    //   23: bipush #27
    //   25: iinc #0, 1
    //   28: aload_2
    //   29: iload_0
    //   30: dup
    //   31: iload_1
    //   32: iadd
    //   33: invokevirtual substring : (II)Ljava/lang/String;
    //   36: iconst_m1
    //   37: goto -> 143
    //   40: aload #5
    //   42: swap
    //   43: iload_3
    //   44: iinc #3, 1
    //   47: swap
    //   48: aastore
    //   49: iload_0
    //   50: iload_1
    //   51: iadd
    //   52: dup
    //   53: istore_0
    //   54: iload #4
    //   56: if_icmpge -> 68
    //   59: aload_2
    //   60: iload_0
    //   61: invokevirtual charAt : (I)C
    //   64: istore_1
    //   65: goto -> 23
    //   68: ldc 'Ã’Â´.7ÂŒ1Â¿Ã½Ã¿WÃ‘ÃªgahÃ±T-3FÂ®iTÂ—Â«Â˜Â›Ã»aeÂµ@\\tÃ¼YÂÂ¬OÃ½8Â‡Â­JÂ¼Ã Â“aÂ‡oe*Â»ÂŸÃ–Ã¹lL'
    //   70: dup
    //   71: astore_2
    //   72: invokevirtual length : ()I
    //   75: istore #4
    //   77: bipush #18
    //   79: istore_1
    //   80: iconst_m1
    //   81: istore_0
    //   82: bipush #40
    //   84: iinc #0, 1
    //   87: aload_2
    //   88: iload_0
    //   89: dup
    //   90: iload_1
    //   91: iadd
    //   92: invokevirtual substring : (II)Ljava/lang/String;
    //   95: iconst_0
    //   96: goto -> 143
    //   99: aload #5
    //   101: swap
    //   102: iload_3
    //   103: iinc #3, 1
    //   106: swap
    //   107: aastore
    //   108: iload_0
    //   109: iload_1
    //   110: iadd
    //   111: dup
    //   112: istore_0
    //   113: iload #4
    //   115: if_icmpge -> 127
    //   118: aload_2
    //   119: iload_0
    //   120: invokevirtual charAt : (I)C
    //   123: istore_1
    //   124: goto -> 82
    //   127: aload #5
    //   129: putstatic burp/Zme3.a : [Ljava/lang/String;
    //   132: bipush #48
    //   134: anewarray java/lang/String
    //   137: putstatic burp/Zme3.b : [Ljava/lang/String;
    //   140: goto -> 300
    //   143: dup_x2
    //   144: pop
    //   145: invokevirtual toCharArray : ()[C
    //   148: dup_x1
    //   149: arraylength
    //   150: dup_x2
    //   151: pop
    //   152: iconst_0
    //   153: istore #6
    //   155: dup2_x1
    //   156: pop2
    //   157: dup_x2
    //   158: iconst_1
    //   159: if_icmpgt -> 260
    //   162: dup2
    //   163: swap
    //   164: iload #6
    //   166: dup2_x1
    //   167: caload
    //   168: swap
    //   169: iload #6
    //   171: bipush #7
    //   173: irem
    //   174: tableswitch default -> 242, 0 -> 212, 1 -> 217, 2 -> 222, 3 -> 227, 4 -> 232, 5 -> 237
    //   212: bipush #49
    //   214: goto -> 244
    //   217: bipush #100
    //   219: goto -> 244
    //   222: bipush #120
    //   224: goto -> 244
    //   227: bipush #69
    //   229: goto -> 244
    //   232: bipush #30
    //   234: goto -> 244
    //   237: bipush #126
    //   239: goto -> 244
    //   242: bipush #88
    //   244: ixor
    //   245: ixor
    //   246: i2c
    //   247: castore
    //   248: iinc #6, 1
    //   251: dup
    //   252: ifne -> 260
    //   255: dup2
    //   256: dup_x1
    //   257: goto -> 166
    //   260: dup2_x1
    //   261: pop2
    //   262: dup_x2
    //   263: iload #6
    //   265: if_icmpgt -> 162
    //   268: pop
    //   269: new java/lang/String
    //   272: dup_x1
    //   273: swap
    //   274: invokespecial <init> : ([C)V
    //   277: invokevirtual intern : ()Ljava/lang/String;
    //   280: swap
    //   281: pop
    //   282: swap
    //   283: tableswitch default -> 40, 0 -> 99
    //   300: return
  }
  
  private static String a(int paramInt1, int paramInt2) {
    int i = (paramInt1 ^ 0x456A) & 0xFFFF;
    if (b[i] == null) {
      char[] arrayOfChar = a[i].toCharArray();
      switch (arrayOfChar[0] & 0xFF) {
        case 0:
        
        case 1:
        
        case 2:
        
        case 3:
        
        case 4:
        
        case 5:
        
        case 6:
        
        case 7:
        
        case 8:
        
        case 9:
        
        case 10:
        
        case 11:
        
        case 12:
        
        case 13:
        
        case 14:
        
        case 15:
        
        case 16:
        
        case 17:
        
        case 18:
        
        case 19:
        
        case 20:
        
        case 21:
        
        case 22:
        
        case 23:
        
        case 24:
        
        case 25:
        
        case 26:
        
        case 27:
        
        case 28:
        
        case 29:
        
        case 30:
        
        case 31:
        
        case 32:
        
        case 33:
        
        case 34:
        
        case 35:
        
        case 36:
        
        case 37:
        
        case 38:
        
        case 39:
        
        case 40:
        
        case 41:
        
        case 42:
        
        case 43:
        
        case 44:
        
        case 45:
        
        case 46:
        
        case 47:
        
        case 48:
        
        case 49:
        
        case 50:
        
        case 51:
        
        case 52:
        
        case 53:
        
        case 54:
        
        case 55:
        
        case 56:
        
        case 57:
        
        case 58:
        
        case 59:
        
        case 60:
        
        case 61:
        
        case 62:
        
        case 63:
        
        case 64:
        
        case 65:
        
        case 66:
        
        case 67:
        
        case 68:
        
        case 69:
        
        case 70:
        
        case 71:
        
        case 72:
        
        case 73:
        
        case 74:
        
        case 75:
        
        case 76:
        
        case 77:
        
        case 78:
        
        case 79:
        
        case 80:
        
        case 81:
        
        case 82:
        
        case 83:
        
        case 84:
        
        case 85:
        
        case 86:
        
        case 87:
        
        case 88:
        
        case 89:
        
        case 90:
        
        case 91:
        
        case 92:
        
        case 93:
        
        case 94:
        
        case 95:
        
        case 96:
        
        case 97:
        
        case 98:
        
        case 99:
        
        case 100:
        
        case 101:
        
        case 102:
        
        case 103:
        
        case 104:
        
        case 105:
        
        case 106:
        
        case 107:
        
        case 108:
        
        case 109:
        
        case 110:
        
        case 111:
        
        case 112:
        
        case 113:
        
        case 114:
        
        case 115:
        
        case 116:
        
        case 117:
        
        case 118:
        
        case 119:
        
        case 120:
        
        case 121:
        
        case 122:
        
        case 123:
        
        case 124:
        
        case 125:
        
        case 126:
        
        case 127:
        
        case 128:
        
        case 129:
        
        case 130:
        
        case 131:
        
        case 132:
        
        case 133:
        
        case 134:
        
        case 135:
        
        case 136:
        
        case 137:
        
        case 138:
        
        case 139:
        
        case 140:
        
        case 141:
        
        case 142:
        
        case 143:
        
        case 144:
        
        case 145:
        
        case 146:
        
        case 147:
        
        case 148:
        
        case 149:
        
        case 150:
        
        case 151:
        
        case 152:
        
        case 153:
        
        case 154:
        
        case 155:
        
        case 156:
        
        case 157:
        
        case 158:
        
        case 159:
        
        case 160:
        
        case 161:
        
        case 162:
        
        case 163:
        
        case 164:
        
        case 165:
        
        case 166:
        
        case 167:
        
        case 168:
        
        case 169:
        
        case 170:
        
        case 171:
        
        case 172:
        
        case 173:
        
        case 174:
        
        case 175:
        
        case 176:
        
        case 177:
        
        case 178:
        
        case 179:
        
        case 180:
        
        case 181:
        
        case 182:
        
        case 183:
        
        case 184:
        
        case 185:
        
        case 186:
        
        case 187:
        
        case 188:
        
        case 189:
        
        case 190:
        
        case 191:
        
        case 192:
        
        case 193:
        
        case 194:
        
        case 195:
        
        case 196:
        
        case 197:
        
        case 198:
        
        case 199:
        
        case 200:
        
        case 201:
        
        case 202:
        
        case 203:
        
        case 204:
        
        case 205:
        
        case 206:
        
        case 207:
        
        case 208:
        
        case 209:
        
        case 210:
        
        case 211:
        
        case 212:
        
        case 213:
        
        case 214:
        
        case 215:
        
        case 216:
        
        case 217:
        
        case 218:
        
        case 219:
        
        case 220:
        
        case 221:
        
        case 222:
        
        case 223:
        
        case 224:
        
        case 225:
        
        case 226:
        
        case 227:
        
        case 228:
        
        case 229:
        
        case 230:
        
        case 231:
        
        case 232:
        
        case 233:
        
        case 234:
        
        case 235:
        
        case 236:
        
        case 237:
        
        case 238:
        
        case 239:
        
        case 240:
        
        case 241:
        
        case 242:
        
        case 243:
        
        case 244:
        
        case 245:
        
        case 246:
        
        case 247:
        
        case 248:
        
        case 249:
        
        case 250:
        
        case 251:
        
        case 252:
        
        case 253:
        
        case 254:
        
        default:
          break;
      } 
      char c = 'Â ';
      int j = (paramInt2 & 0xFF) - c;
      if (j < 0)
        j += 256; 
      int k = ((paramInt2 & 0xFFFF) >>> 8) - c;
      if (k < 0)
        k += 256; 
      for (byte b = 0; b < arrayOfChar.length; b++) {
        int m = b % 2;
        if (m == 0) {
          arrayOfChar[b] = (char)(arrayOfChar[b] ^ j);
          j = ((j >>> 3 | j << 5) ^ arrayOfChar[b]) & 0xFF;
        } else {
          arrayOfChar[b] = (char)(arrayOfChar[b] ^ k);
          k = ((k >>> 3 | k << 5) ^ arrayOfChar[b]) & 0xFF;
        } 
      } 
      b[i] = (new String(arrayOfChar)).intern();
    } 
    return b[i];
  }
}


/* Location:              C:\Program Files\BurpSuitePro\burpsuite_pro.jar!\burp\Zme3.class
 * Java compiler version: 21 (65.0)
 * JD-Core Version:       1.1.3
 */