package burp;

import java.util.EnumSet;
import java.util.Map;
import java.util.function.Consumer;
import net.portswigger.Zkb;
import net.portswigger.Zqf;
import net.portswigger.Zuh;

public class Zmea extends Zmvg {
  private static final Map<Zg3n, String> ZA;
  
  private static final String[] a;
  
  private static final String[] b;
  
  public Zmea() {
    super(EnumSet.of(Zzqz.VARIANT, Zzqz.FLAGS));
  }
  
  public String Zi(Zvs paramZvs, byte paramByte1, int paramInt, Ztlj paramZtlj, Ztub paramZtub, Zefg<Zxtl> paramZefg, Zmzk paramZmzk, byte[] paramArrayOfbyte, byte paramByte2, byte paramByte3) {
    StringBuilder stringBuilder = new StringBuilder();
    Zv(paramZvs, paramByte1, paramInt, paramZtlj, paramZtub, paramZefg, paramArrayOfbyte).accept(stringBuilder);
    return stringBuilder.toString();
  }
  
  private Consumer<StringBuilder> Zv(Zvs paramZvs, byte paramByte, int paramInt, Ztlj paramZtlj, Ztub paramZtub, Zefg<Zxtl> paramZefg, byte[] paramArrayOfbyte) {
    // Byte code:
    //   0: iload_2
    //   1: invokestatic ZM : (B)Z
    //   4: ifeq -> 18
    //   7: aload #4
    //   9: aload #6
    //   11: iload_2
    //   12: <illegal opcode> accept : (Lburp/Ztlj;Lburp/Zefg;B)Ljava/util/function/Consumer;
    //   17: areturn
    //   18: aload #5
    //   20: aload #6
    //   22: aload #4
    //   24: iload_2
    //   25: iload_3
    //   26: aload_1
    //   27: aload #7
    //   29: <illegal opcode> accept : (Lburp/Ztub;Lburp/Zefg;Lburp/Ztlj;BILburp/Zvs;[B)Ljava/util/function/Consumer;
    //   34: areturn
  }
  
  public String Zt(Zvs paramZvs, byte paramByte, int paramInt, Ztlj paramZtlj, Ztub paramZtub, Zefg<Zxtl> paramZefg) {
    if (!paramZtlj.Zn(Ztz3.LOCATION))
      return null; 
    Zr2s zr2s = new Zr2s(paramZtlj, paramZefg, paramInt, Zmey.ZS(paramZefg));
    paramZtub.ZT(zr2s);
    return zr2s.Zn;
  }
  
  private static void ZE(StringBuilder paramStringBuilder, int paramInt, Zefg<Zxtl> paramZefg) {
    if ((paramInt & 0x80) == 128 && Zf(paramZefg).ZTr() != Zs66.COOKIE)
      paramStringBuilder.append(a(31876, 7927)); 
  }
  
  private static boolean ZM(byte paramByte) {
    return (paramByte == 17 || paramByte == 18 || paramByte == 19);
  }
  
  private static Zxtl Zf(Zefg<Zxtl> paramZefg) {
    return paramZefg.get(0);
  }
  
  public static void Zi(StringBuilder paramStringBuilder, int paramInt, byte paramByte, boolean paramBoolean) {
    // Byte code:
    //   0: invokestatic ZQ : ()Ljava/lang/String;
    //   3: astore #4
    //   5: iload_1
    //   6: iconst_4
    //   7: iand
    //   8: iconst_4
    //   9: if_icmpne -> 81
    //   12: sipush #31898
    //   15: sipush #-25666
    //   18: invokestatic a : (II)Ljava/lang/String;
    //   21: astore #5
    //   23: iload_1
    //   24: sipush #16384
    //   27: iand
    //   28: sipush #16384
    //   31: if_icmpne -> 45
    //   34: sipush #31996
    //   37: sipush #-31786
    //   40: invokestatic a : (II)Ljava/lang/String;
    //   43: astore #5
    //   45: aload_0
    //   46: sipush #31986
    //   49: sipush #-26354
    //   52: invokestatic a : (II)Ljava/lang/String;
    //   55: invokevirtual append : (Ljava/lang/String;)Ljava/lang/StringBuilder;
    //   58: aload #5
    //   60: invokevirtual append : (Ljava/lang/String;)Ljava/lang/StringBuilder;
    //   63: sipush #31889
    //   66: sipush #-13178
    //   69: invokestatic a : (II)Ljava/lang/String;
    //   72: invokevirtual append : (Ljava/lang/String;)Ljava/lang/StringBuilder;
    //   75: pop
    //   76: aload #4
    //   78: ifnull -> 150
    //   81: iload_2
    //   82: bipush #14
    //   84: if_icmpne -> 106
    //   87: aload_0
    //   88: sipush #31893
    //   91: sipush #14571
    //   94: invokestatic a : (II)Ljava/lang/String;
    //   97: invokevirtual append : (Ljava/lang/String;)Ljava/lang/StringBuilder;
    //   100: pop
    //   101: aload #4
    //   103: ifnull -> 150
    //   106: iload_2
    //   107: invokestatic ZM : (B)Z
    //   110: ifne -> 150
    //   113: aload_0
    //   114: sipush #31942
    //   117: sipush #25500
    //   120: invokestatic a : (II)Ljava/lang/String;
    //   123: invokevirtual append : (Ljava/lang/String;)Ljava/lang/StringBuilder;
    //   126: pop
    //   127: aload_0
    //   128: iload_2
    //   129: invokestatic Zo : (B)Ljava/lang/String;
    //   132: invokevirtual append : (Ljava/lang/String;)Ljava/lang/StringBuilder;
    //   135: pop
    //   136: aload_0
    //   137: sipush #31960
    //   140: sipush #5831
    //   143: invokestatic a : (II)Ljava/lang/String;
    //   146: invokevirtual append : (Ljava/lang/String;)Ljava/lang/StringBuilder;
    //   149: pop
    //   150: getstatic burp/Zmea.ZA : Ljava/util/Map;
    //   153: invokeinterface entrySet : ()Ljava/util/Set;
    //   158: invokeinterface iterator : ()Ljava/util/Iterator;
    //   163: astore #5
    //   165: aload #5
    //   167: invokeinterface hasNext : ()Z
    //   172: ifeq -> 291
    //   175: aload #5
    //   177: invokeinterface next : ()Ljava/lang/Object;
    //   182: checkcast java/util/Map$Entry
    //   185: astore #6
    //   187: aload #6
    //   189: invokeinterface getKey : ()Ljava/lang/Object;
    //   194: checkcast burp/Zg3n
    //   197: iload_1
    //   198: iload_2
    //   199: invokevirtual ZQ : (IB)Z
    //   202: ifeq -> 286
    //   205: aload #6
    //   207: invokeinterface getValue : ()Ljava/lang/Object;
    //   212: checkcast java/lang/String
    //   215: astore #7
    //   217: aload #7
    //   219: sipush #31970
    //   222: sipush #-22992
    //   225: invokestatic a : (II)Ljava/lang/String;
    //   228: invokevirtual contains : (Ljava/lang/CharSequence;)Z
    //   231: ifeq -> 279
    //   234: iload_3
    //   235: ifeq -> 250
    //   238: sipush #31976
    //   241: sipush #15441
    //   244: invokestatic a : (II)Ljava/lang/String;
    //   247: goto -> 259
    //   250: sipush #31897
    //   253: sipush #6903
    //   256: invokestatic a : (II)Ljava/lang/String;
    //   259: astore #8
    //   261: aload #7
    //   263: sipush #31967
    //   266: sipush #-8568
    //   269: invokestatic a : (II)Ljava/lang/String;
    //   272: aload #8
    //   274: invokevirtual replace : (Ljava/lang/CharSequence;Ljava/lang/CharSequence;)Ljava/lang/String;
    //   277: astore #7
    //   279: aload_0
    //   280: aload #7
    //   282: invokevirtual append : (Ljava/lang/String;)Ljava/lang/StringBuilder;
    //   285: pop
    //   286: aload #4
    //   288: ifnull -> 165
    //   291: return
  }
  
  private static String Zo(byte paramByte) {
    switch (paramByte) {
      case 0:
        return a(31989, 4784);
      case 1:
        return a(31899, 15519);
      case 2:
        return a(31955, 7225);
      case 3:
        return a(31950, -8769);
      case 4:
        return a(31964, -25049);
      case 5:
        return a(31873, 266);
      case 6:
        return a(31937, 10538);
      case 10:
        return a(31895, 25296);
      case 7:
        return a(31890, 15142);
      case 8:
        return a(31961, 15518);
      case 9:
        return a(31983, 30859);
      case 11:
        return a(31991, -2704);
      case 12:
        return a(31965, -19002);
      case 13:
        return a(31891, -5457);
    } 
    Zuh.Zv(false, Zqf.Zk, paramByte);
    return a(31966, -5983);
  }
  
  public static void Zb(StringBuilder paramStringBuilder, Zvs paramZvs, int paramInt, short paramShort, Zs66 paramZs66) {
    // Byte code:
    //   0: invokestatic ZQ : ()Ljava/lang/String;
    //   3: astore #5
    //   5: aload_1
    //   6: getstatic burp/Zzu2.XSS_REFLECTED : Lburp/Zzu2;
    //   9: if_acmpne -> 163
    //   12: iload_3
    //   13: sipush #300
    //   16: if_icmplt -> 40
    //   19: iload_3
    //   20: sipush #400
    //   23: if_icmpge -> 40
    //   26: aload_0
    //   27: sipush #31982
    //   30: sipush #-19943
    //   33: invokestatic a : (II)Ljava/lang/String;
    //   36: invokevirtual append : (Ljava/lang/String;)Ljava/lang/StringBuilder;
    //   39: pop
    //   40: aload #4
    //   42: getstatic burp/Zs66.HEADER : Lburp/Zs66;
    //   45: if_acmpne -> 62
    //   48: aload_0
    //   49: sipush #31958
    //   52: sipush #28059
    //   55: invokestatic a : (II)Ljava/lang/String;
    //   58: invokevirtual append : (Ljava/lang/String;)Ljava/lang/StringBuilder;
    //   61: pop
    //   62: aload #4
    //   64: getstatic burp/Zs66.COOKIE : Lburp/Zs66;
    //   67: if_acmpne -> 84
    //   70: aload_0
    //   71: sipush #31945
    //   74: sipush #12536
    //   77: invokestatic a : (II)Ljava/lang/String;
    //   80: invokevirtual append : (Ljava/lang/String;)Ljava/lang/StringBuilder;
    //   83: pop
    //   84: iload_2
    //   85: sipush #4096
    //   88: iand
    //   89: sipush #4096
    //   92: if_icmpne -> 133
    //   95: iload_2
    //   96: sipush #8192
    //   99: iand
    //   100: ifne -> 107
    //   103: iconst_1
    //   104: goto -> 108
    //   107: iconst_0
    //   108: getstatic net/portswigger/Zqf.Zr : Lnet/portswigger/Zqf;
    //   111: invokestatic Zb : (ZLnet/portswigger/Zqf;)V
    //   114: aload_0
    //   115: sipush #31901
    //   118: sipush #3600
    //   121: invokestatic a : (II)Ljava/lang/String;
    //   124: invokevirtual append : (Ljava/lang/String;)Ljava/lang/StringBuilder;
    //   127: pop
    //   128: aload #5
    //   130: ifnull -> 210
    //   133: iload_2
    //   134: sipush #8192
    //   137: iand
    //   138: sipush #8192
    //   141: if_icmpne -> 210
    //   144: aload_0
    //   145: sipush #31994
    //   148: sipush #-10393
    //   151: invokestatic a : (II)Ljava/lang/String;
    //   154: invokevirtual append : (Ljava/lang/String;)Ljava/lang/StringBuilder;
    //   157: pop
    //   158: aload #5
    //   160: ifnull -> 210
    //   163: aload_1
    //   164: getstatic burp/Zzu2.XSS_STORED : Lburp/Zzu2;
    //   167: if_acmpne -> 203
    //   170: iload_3
    //   171: sipush #300
    //   174: if_icmplt -> 210
    //   177: iload_3
    //   178: sipush #400
    //   181: if_icmpge -> 210
    //   184: aload_0
    //   185: sipush #31954
    //   188: sipush #-17395
    //   191: invokestatic a : (II)Ljava/lang/String;
    //   194: invokevirtual append : (Ljava/lang/String;)Ljava/lang/StringBuilder;
    //   197: pop
    //   198: aload #5
    //   200: ifnull -> 210
    //   203: iconst_0
    //   204: getstatic net/portswigger/Zqf.Zk : Lnet/portswigger/Zqf;
    //   207: invokestatic Zb : (ZLnet/portswigger/Zqf;)V
    //   210: return
  }
  
  private static void Zz(StringBuilder paramStringBuilder, Zefg<Zxtl> paramZefg, byte paramByte1, byte paramByte2, int paramInt, byte[] paramArrayOfbyte1, byte[] paramArrayOfbyte2, String paramString1, String paramString2) {
    Zuh.Zv((paramByte1 != 1), Zqf.Zk, 1L);
    paramStringBuilder.append(a(31882, 4828));
    paramStringBuilder.append(Zg2x.ZM(paramZefg, true, true));
    paramStringBuilder.append(a(31959, 9734));
    paramStringBuilder.append(ZH(paramByte1, paramByte2));
    paramStringBuilder.append(a(31988, -1281));
    String str = Zkb.ZG(paramArrayOfbyte1);
    Zrlp.Zn(paramStringBuilder, Zmey.ZW(str));
    paramStringBuilder.append(a(31973, -17875));
    paramStringBuilder.append(Zg2x.Zt(paramZefg, true, false));
    paramStringBuilder.append(".");
    Zc(paramByte2, paramInt, paramStringBuilder, paramArrayOfbyte2, str, paramString2, paramString1);
  }
  
  private static void Zc(byte paramByte, int paramInt, StringBuilder paramStringBuilder, byte[] paramArrayOfbyte, String paramString1, String paramString2, String paramString3) {
    // Byte code:
    //   0: invokestatic ZQ : ()Ljava/lang/String;
    //   3: astore #7
    //   5: iload_0
    //   6: bipush #16
    //   8: if_icmpne -> 58
    //   11: iload_1
    //   12: ldc 1048576
    //   14: iand
    //   15: ldc 1048576
    //   17: if_icmpne -> 39
    //   20: aload_2
    //   21: sipush #31874
    //   24: sipush #1633
    //   27: invokestatic a : (II)Ljava/lang/String;
    //   30: invokevirtual append : (Ljava/lang/String;)Ljava/lang/StringBuilder;
    //   33: pop
    //   34: aload #7
    //   36: ifnull -> 287
    //   39: aload_2
    //   40: sipush #31949
    //   43: sipush #-16428
    //   46: invokestatic a : (II)Ljava/lang/String;
    //   49: invokevirtual append : (Ljava/lang/String;)Ljava/lang/StringBuilder;
    //   52: pop
    //   53: aload #7
    //   55: ifnull -> 287
    //   58: iload_0
    //   59: bipush #15
    //   61: if_icmpne -> 111
    //   64: iload_1
    //   65: ldc 1048576
    //   67: iand
    //   68: ldc 1048576
    //   70: if_icmpne -> 92
    //   73: aload_2
    //   74: sipush #31875
    //   77: sipush #-4756
    //   80: invokestatic a : (II)Ljava/lang/String;
    //   83: invokevirtual append : (Ljava/lang/String;)Ljava/lang/StringBuilder;
    //   86: pop
    //   87: aload #7
    //   89: ifnull -> 287
    //   92: aload_2
    //   93: sipush #31946
    //   96: sipush #-5956
    //   99: invokestatic a : (II)Ljava/lang/String;
    //   102: invokevirtual append : (Ljava/lang/String;)Ljava/lang/StringBuilder;
    //   105: pop
    //   106: aload #7
    //   108: ifnull -> 287
    //   111: aload_2
    //   112: sipush #31888
    //   115: sipush #32055
    //   118: invokestatic a : (II)Ljava/lang/String;
    //   121: invokevirtual append : (Ljava/lang/String;)Ljava/lang/StringBuilder;
    //   124: pop
    //   125: aload_3
    //   126: invokestatic ZG : ([B)Ljava/lang/String;
    //   129: astore #8
    //   131: aload #4
    //   133: aload #8
    //   135: invokevirtual equals : (Ljava/lang/Object;)Z
    //   138: ifeq -> 160
    //   141: aload_2
    //   142: sipush #31953
    //   145: sipush #-4818
    //   148: invokestatic a : (II)Ljava/lang/String;
    //   151: invokevirtual append : (Ljava/lang/String;)Ljava/lang/StringBuilder;
    //   154: pop
    //   155: aload #7
    //   157: ifnull -> 194
    //   160: aload_2
    //   161: sipush #31892
    //   164: sipush #-14888
    //   167: invokestatic a : (II)Ljava/lang/String;
    //   170: invokevirtual append : (Ljava/lang/String;)Ljava/lang/StringBuilder;
    //   173: pop
    //   174: aload_2
    //   175: aload #8
    //   177: invokestatic Zn : (Ljava/lang/StringBuilder;Ljava/lang/String;)V
    //   180: aload_2
    //   181: sipush #31880
    //   184: sipush #30604
    //   187: invokestatic a : (II)Ljava/lang/String;
    //   190: invokevirtual append : (Ljava/lang/String;)Ljava/lang/StringBuilder;
    //   193: pop
    //   194: iload_0
    //   195: bipush #14
    //   197: if_icmpne -> 273
    //   200: aload_2
    //   201: sipush #31881
    //   204: sipush #-24701
    //   207: invokestatic a : (II)Ljava/lang/String;
    //   210: invokevirtual append : (Ljava/lang/String;)Ljava/lang/StringBuilder;
    //   213: aload #5
    //   215: invokevirtual append : (Ljava/lang/String;)Ljava/lang/StringBuilder;
    //   218: sipush #31962
    //   221: sipush #7013
    //   224: invokestatic a : (II)Ljava/lang/String;
    //   227: invokevirtual append : (Ljava/lang/String;)Ljava/lang/StringBuilder;
    //   230: aload #6
    //   232: invokestatic Zu : (Ljava/lang/String;)Ljava/lang/String;
    //   235: invokevirtual append : (Ljava/lang/String;)Ljava/lang/StringBuilder;
    //   238: sipush #31902
    //   241: sipush #21601
    //   244: invokestatic a : (II)Ljava/lang/String;
    //   247: invokevirtual append : (Ljava/lang/String;)Ljava/lang/StringBuilder;
    //   250: aload #6
    //   252: invokevirtual append : (Ljava/lang/String;)Ljava/lang/StringBuilder;
    //   255: sipush #31936
    //   258: sipush #10393
    //   261: invokestatic a : (II)Ljava/lang/String;
    //   264: invokevirtual append : (Ljava/lang/String;)Ljava/lang/StringBuilder;
    //   267: pop
    //   268: aload #7
    //   270: ifnull -> 287
    //   273: aload_2
    //   274: sipush #31998
    //   277: sipush #-22467
    //   280: invokestatic a : (II)Ljava/lang/String;
    //   283: invokevirtual append : (Ljava/lang/String;)Ljava/lang/StringBuilder;
    //   286: pop
    //   287: return
  }
  
  public static String ZH(byte paramByte1, byte paramByte2) {
    if (paramByte2 == 11)
      return a(31974, 20858); 
    if (paramByte2 == 14)
      return a(31975, 11218); 
    String str = (paramByte2 == 12) ? a(31947, 30756) : a(31971, -19097);
    switch (paramByte1) {
      case 0:
        return a(31940, -31992);
      case 1:
        return a(31992, -9585);
      case 2:
        return a(31993, 32700) + a(31993, 32700) + str;
      case 3:
        return a(31941, 31932) + a(31941, 31932) + str;
      case 4:
      case 8:
        return a(31977, 11024) + a(31977, 11024) + str;
      case 5:
      case 9:
        return a(31979, 766) + a(31979, 766) + str;
      case 6:
      case 10:
        return a(31979, 766) + a(31979, 766) + str;
      case 7:
      case 11:
        return a(31979, 766) + a(31979, 766) + str;
      case 15:
        return a(31979, 766) + a(31979, 766) + str;
      case 12:
        return a(31979, 766) + a(31979, 766) + str;
      case 13:
        return a(31979, 766) + a(31979, 766) + str;
      case 14:
        return a(31979, 766) + a(31979, 766) + str;
      case 16:
        return a(31997, 237);
      case 17:
        return a(31978, 1240);
      case 18:
        return a(31956, -6327);
      case 19:
        return a(31943, 1160) + a(31943, 1160) + str;
      case 20:
        return a(31957, -19544);
      case 21:
        return a(31944, -12255);
      case 22:
        return a(31948, 10366);
      case 23:
        return a(31896, -30822) + a(31896, -30822) + str;
      case 24:
        return a(31903, -29070);
      case 25:
        return a(31987, 2454);
    } 
    Zuh.Zv(false, Zqf.Zk, paramByte1);
    return a(31985, -10271);
  }
  
  public byte Zj(Ztlj paramZtlj, Ztub paramZtub, byte paramByte, int paramInt, Zs66 paramZs66, byte[] paramArrayOfbyte, Zrdb paramZrdb) {
    String str = Zr2s.ZQ();
    if (Zbqc.Zwu() == null)
      Zr2s.ZF("NhxEwb"); 
    return Zx_r.Zd(Zzu2.XSS_REFLECTED, paramZs66, paramZtlj.ZR(Ztz3.STATUS_CODE), paramInt, paramZtlj.ZJ(Ztz3.CONTENT_TYPE_STATED), paramZtlj.Zj(Ztz3.NO_SNIFF_HEADER), paramZtlj.Zj(Ztz3.CONTENT_DISPOSITION_ATTACHMENT_HEADER), Zkb.ZG(paramArrayOfbyte), paramZrdb.Za8(), Zrt0.Zg(paramZtlj.ZJ(Ztz3.BROWSERS)));
  }
  
  public Zl4m Zc(Zrdb paramZrdb1, Zrdb paramZrdb2, Zgvn paramZgvn, Zz1h paramZz1h) {
    String str = Zr2s.ZQ();
    if (str != null)
      Zbqc.Zr(new Zbqc[2]); 
    return (new Zt97(new Zxll(new Zxn2(new Zta3(new Zz9b(new Zrbk(), new Zzzs(new Zs7y()))))))).Zi(paramZrdb1, paramZrdb2, paramZz1h);
  }
  
  private static Zg3n ZR(int paramInt) {
    return new Zg3n(paramInt, null);
  }
  
  private static Zg3n Zt(Byte paramByte) {
    return new Zg3n(0, paramByte);
  }
  
  private static void lambda$findBehaviour$1(Ztub paramZtub, Zefg<Zxtl> paramZefg, Ztlj paramZtlj, byte paramByte, int paramInt, Zvs paramZvs, byte[] paramArrayOfbyte, StringBuilder paramStringBuilder) {
    byte[] arrayOfByte = paramZtub.Zd().Zub().Zsf().ZiD();
    Zz(paramStringBuilder, paramZefg, paramZtlj.Zq(Ztz3.LOCATION), paramByte, paramInt, arrayOfByte, paramZtlj.Zm(Ztz3.MATCH), paramZtlj.ZJ(Ztz3.HTML_TAG), paramZtlj.ZJ(Ztz3.HTML_ATTRIBUTE));
    Zi(paramStringBuilder, paramInt, paramByte, Zmey.ZS(paramZefg));
    ZE(paramStringBuilder, paramInt, paramZefg);
    Zb(paramStringBuilder, paramZvs, paramInt, paramZtlj.ZR(Ztz3.STATUS_CODE), ((Zxtl)paramZefg.get(0)).ZTr());
    Zx_r.Zs(paramStringBuilder, paramArrayOfbyte, paramInt, paramZtlj);
  }
  
  private static void lambda$findBehaviour$0(Ztlj paramZtlj, Zefg paramZefg, byte paramByte, StringBuilder paramStringBuilder) {
    // Byte code:
    //   0: aload_0
    //   1: getstatic burp/Ztz3.BROWSERS : Lburp/Ztz3;
    //   4: invokevirtual ZJ : (Lburp/Ztz3;)Ljava/lang/String;
    //   7: invokestatic Zg : (Ljava/lang/String;)Ljava/util/EnumSet;
    //   10: astore #5
    //   12: invokestatic ZQ : ()Ljava/lang/String;
    //   15: aload_0
    //   16: getstatic burp/Ztz3.CONTENT_TYPE_STATED : Lburp/Ztz3;
    //   19: invokevirtual ZJ : (Lburp/Ztz3;)Ljava/lang/String;
    //   22: astore #6
    //   24: astore #4
    //   26: aload_3
    //   27: sipush #31939
    //   30: sipush #-21678
    //   33: invokestatic a : (II)Ljava/lang/String;
    //   36: invokevirtual append : (Ljava/lang/String;)Ljava/lang/StringBuilder;
    //   39: pop
    //   40: aload_3
    //   41: aload_1
    //   42: iconst_1
    //   43: iconst_1
    //   44: invokestatic Zt : (Lburp/Zefg;ZZ)Ljava/lang/String;
    //   47: invokevirtual append : (Ljava/lang/String;)Ljava/lang/StringBuilder;
    //   50: pop
    //   51: aload_3
    //   52: sipush #31951
    //   55: sipush #-30957
    //   58: invokestatic a : (II)Ljava/lang/String;
    //   61: invokevirtual append : (Ljava/lang/String;)Ljava/lang/StringBuilder;
    //   64: pop
    //   65: aload_3
    //   66: sipush #31872
    //   69: sipush #-8584
    //   72: invokestatic a : (II)Ljava/lang/String;
    //   75: invokevirtual append : (Ljava/lang/String;)Ljava/lang/StringBuilder;
    //   78: pop
    //   79: iload_2
    //   80: bipush #18
    //   82: if_icmpne -> 150
    //   85: aload_3
    //   86: sipush #31952
    //   89: sipush #14408
    //   92: invokestatic a : (II)Ljava/lang/String;
    //   95: invokevirtual append : (Ljava/lang/String;)Ljava/lang/StringBuilder;
    //   98: pop
    //   99: aload #6
    //   101: sipush #31980
    //   104: sipush #-9116
    //   107: invokestatic a : (II)Ljava/lang/String;
    //   110: invokevirtual equals : (Ljava/lang/Object;)Z
    //   113: ifeq -> 135
    //   116: aload_3
    //   117: sipush #31900
    //   120: sipush #-6595
    //   123: invokestatic a : (II)Ljava/lang/String;
    //   126: invokevirtual append : (Ljava/lang/String;)Ljava/lang/StringBuilder;
    //   129: pop
    //   130: aload #4
    //   132: ifnull -> 164
    //   135: aload_3
    //   136: aload #5
    //   138: invokestatic Zu : (Ljava/util/EnumSet;)Ljava/lang/String;
    //   141: invokevirtual append : (Ljava/lang/String;)Ljava/lang/StringBuilder;
    //   144: pop
    //   145: aload #4
    //   147: ifnull -> 164
    //   150: aload_3
    //   151: sipush #31972
    //   154: sipush #10634
    //   157: invokestatic a : (II)Ljava/lang/String;
    //   160: invokevirtual append : (Ljava/lang/String;)Ljava/lang/StringBuilder;
    //   163: pop
    //   164: aload_3
    //   165: sipush #31894
    //   168: sipush #31444
    //   171: invokestatic a : (II)Ljava/lang/String;
    //   174: invokevirtual append : (Ljava/lang/String;)Ljava/lang/StringBuilder;
    //   177: pop
    //   178: return
  }
  
  static {
    // Byte code:
    //   0: bipush #91
    //   2: anewarray java/lang/String
    //   5: astore #5
    //   7: iconst_0
    //   8: istore_3
    //   9: ldc 'ÂÂ»ÂŸÂ¦ÃtÂ‹ÂÃ‰Ã˜Ã†+}\\f]Ã‚Â³t6ÂƒÂ—7Ã¢ÂšCÂ‹xÂ¿Â³Ã±Â¢Ãµ|Â¹Â±nÂ£G2\\f8Ã’nr~Tm3#i=Â­ÂÂ²Ã\\bysÃxÂ°Â…5\\nÂ£'Ã®}aEÂ™Ã¶Æ½Â–Ã·Ã¾/Ã¢)Ã±Â­7Ã†Ã”Â™6Ã“2Ã–ÃµÃEÃ¥hÂƒÂ‡UÂ„Ãƒ-Â Ã„cÃ¿Ã„Â½Ã³Ã¸T(Â¦^z@Ã‚\\fÂ¾Â½Â³Â­Â¥Â±ÂºÃ¬J#Â¬Â«ÂŠÃ¬ÃšÃÃ§Â­q@5Ã¡Ãš3ÂŸdÂ©6IÂÃ«Ã½IGstÃ½Ã¦Ã†aÃ€Ã¨AÃ­\\tÃ¯xS?Â«ÃŸÂ«dGÂ¸Ã½ÂTÃ£&;Â\\fÂ·ÂºÂ‰PnÃ¶Â™Ã…ÃˆeÃˆÂ¹Â‹Â¦ÂÃ±Â›Ã€_Ã­QiÃÂÂ£ÃldgÃ§Ã¸Ã»ÂƒÃŒÂ¢yÃXÂˆÂ¸Ã…Ã¿KZ:QJÂƒÂ©:ÃÃ¯g5Ã·cQ>Ã‘Ã¤Ã¥ÂƒÂ’ÃÂ½ÂšNEÃ©$Ã„Ã³oÂ2Â–Â›Ã¨5ÃÃwÃ¿Ã³70 `K}Â¡ÂÃ¾X\\f!TeiÃ³]Â•4 Â´YÂ¼lÃ¦Ã±Â‡Ãµ;m7>Â’  {ÃÃ¯Â¾\\n)Ã¸GÂ‡@ÂÃÂ¢Ã Ã³Ã¡Â®Ã¥Ã¡dQÂªÂ°Ã˜E=CYLAÂ™Ã¼ÂÂ†lÃ•ÃŠÂ¡ÃÂœÃ·Â‚s%Âº@Ã·rÂ‚VÂ Ãš\}e3zÂ«Ã²Ã€Â¬Ã‡<Â¦Ã¿%ÃÃÂ‹3jÃ_ÂƒH'PWÂ¤3 Ã¢Â€fL%Â¤Ã½Ã¨Ã¦Ã•xÃ½ÃŸ\\nZ KZÃ‡KetÂ¬Ã…Â¸BÂ‰L tÂ¹Ã”;Ã¤|Â°sÃ†ÃÃˆ:XQTZaÃ”Â»ÂµÂ<Ã¾?Ãƒ*Â´ÂƒÃŒÃ‚Â™^)ÂÂ…Ã’ÂOdÂ»xÃ³Â’`5&z*Ã§P:LpÃ³ÂŠÃ¼W/Ã‡ÃŒ*Ãº6ysÃÂ¶-/ÃƒÃÂ³Ã¾5ÂªÂªodÃ…IÂ¿tÃ§fG<ÂnÂ¼ÂŒ8`Ã¶ÂYÃ¢=:rnÂ¬Ã—ÂŸÃÂ›Â±ÃŒbÃ¬HÂ•Â¡6|Â½ 0Â£Â‹yxÃ”Ã‹XÂ™Ã‘AÃ—8VEÃŸÃ™\Y?yÂ˜<.^Â¿@`ÂÂ’6)nZ7:Ã¨&Ã¢Ã™\\f ÃÂ°JÂ„Ã½zÂ¡Â¯WÃ¸Â¡Ã¶*Ã‘Â˜@Â—Â´Ã•Ã¾Â°`RÂ†Ã¼pÂ™(Ã¦]Â\\rÃ“Â¨Â‹/Â™Â¨Ã¼0]ÃƒÃ‘EÂ Â‹3\\tGÃÂHÇ·VÂ’Ã¦ÂƒÃ¡Â¼Â‘7ÂšNÃ†Ã¤Â‚ÂºOCÃ»Â°Â°Ã“ÂœRÃ¶X&Â¿e+!ÃƒbqGiÃ¿[Ã—Ã¤yÃ‡#Â¸pÃŠLÃ” Ã„|tÂªYÂ—Â¼#[Ãµ2Â†jQÃ¢FtQÂŒÃ¿Ã\Gp=Â˜nAÃ»Ã™Ã¿[cÃªÂ‘tÃ—Ãƒ;4eUÃ›+ZUdr_d>Ã$Ã¦Ã´7aGÃ‹Ã’Ãš3u\\fz1Ã™Ã€Â¬ÃÃ¾Â¯qÃ¨g\Â¿Â£Ã¹AÃ»ÃªÂÂÂ…Â°\\t'Â Ã§cÃ†ÃŠ|;Â”Â‘8e N\\nI*2Â‚PÂ‡Ã‚Âƒ)BÂ—7Â VlÃ°Â¼Â»ÂÃ¸Ã¡>/Â¸Ã©ÂšÂÂŠ|Ã›ÂÃVÃ‘<Ã“"Â|\\bÃ°Ã”Â§9JÃ„Â“AHÂ¾Â†Ã³Â—eaÂ‹Â™\\fÃªÂ—Â¯Ã¶MÃ‚6ÂÃ’Â§ÃºÃƒÃ‡Ã±Ã¦Â®Ã—#.]Ã°MÃ–cÃ™Ã¿Ã«k\\nÂ‰AwÂ¬z5Ã´Â¥wÃ­ÃÂŒÂ‡T8Ã¹v\\r|ÃÃeÂ—SÃ¥Ã®*Â¢dÂŸVsÂºÂ…\\tÂ€Ã§ÃˆÂ¤oÂ¢\\fÃµÃ¥ÃŒÂÂ²I.NÂFÃšÂƒ!Â˜Jxv Ã˜`._ÂºÃvLÃ¨QÂµÂ„TeÃ€UÂ™WÂ°Â€ÃˆÃ™mmÂ”Ã¾ÃÂ„ÃƒÂ¡Ã½aÂ Â¯ÂƒÃ”Â¶ÂºÃ¨Ã“Â±Â”7Ã§ dÂ­lÃŸÂ¥ÂºX V\\fÂ†Â²Ã£Ã„ÃÂ„GÃ¯ÃÂ¡#Â»Â‘Â‹Ã‡Ã˜Â¦cÃšÂÃ¡8ÃŠÃ†^Ã¹Â–Â—Ã¹Ã*Ã­Â²u#Â¶Â½Â–ÂºÂƒbz/Â¢(Â´Â  KÃ•Â¦rÂˆVÂ¹Â†&BHÃ…Â«ÂªÂ±Â„yÃ”Ã³Â"Âx>Â­Ã•nsb>\\t+Ã_gÃ’$Â„B]\.`Ã™HÂ‚ÃŒx%Ã°Â¿Ä•Ã¥2Ã³Ã\\n,u$JÃ¶1W/8Ã±ÂÂÂ‰}iÂ¬6CÃ‘-$cÂ«1uÃ»Ã½Ã£Ã¯ÃˆÃºÂ“Ã‰Â‡Ã·ÂšHvÂ›\Ã¹Â¼ÂÂ•nÂ³Ã–SÃ¿nÂ†-ÂÃ±VÂ´/cÃ”Â¾ÃÃ´|Â¾3lÂÂ‚DBÂŠvÃ¿.T0Â«MTDÃÂ†TÂ¦Â»Ã¼ÃŸÂºÂ†Ã‡Â·T^k8ÃˆPÂ„Â”Â˜<~6)ÂªÃ’ÂVÂ¯DÃ‘Ã»L/OÃ•Ã-\\nvÂ©k(SNÂ“6Â’ÂƒRÃŠÂœÃ„Ã•Â€ÂŒJÃ·5ÂnÃÃ½5guÃ†{Â™ÂŒlÃ¡fÂ¤KÂXrb`?Â¿I.Â‘N&)kgÂºfÂ´Ã¶Â€Ã®/Ã·Â˜ÂˆÃ±4ÂÃ¿\\rHÃ'Â”T\\bÂ†Ã©4Ã±wÂ¶Âd#\\f\\rHÃ“Ã¨Ã‡Ãº90Â”Â®\\\f=pÃŠ}(Â‡Â¦Ã€Â³3Â‹ÃŸ`ÂŒ$Ã…ÂŸGzÃ¾=[#Q4Ã³Ã³;Ãµ>:Ã«Ã€Â„Ã•pBÃ©Ã¥Â¹ÃŠ]Â©7Ã­ÂšÃŒÂ›Â¸M8Â«Ã–Â¡f XÃ­*Ãš3nÃ­Ã°hFOnÃ´Â€Â…Ã±Â·)Â±Â¡ÂšÂšHÂZÃ¨Â›yÃÂš9v=\\bYÃ”\\bÃ½Ã¸Ã§#Â‚ÃµTa}ÃªÃ¥Ã¢ÃƒÂ»Â‰Q?Ã¹nÂŸÂ‘Â£Â@PÃ»|Ã ÂƒÂª`ÂÂ¥#ÂÂºw{oÃÂ›;Âµ`Â‡CÃ³**Â„yÂÂ‘Ã•Ã Â¥;?n3ÂÂ¯ÂšÂ¿qD]yÃ¶\\bZÂ:ÃºCÃ‚L5Ã¬ÃdÂ˜Ãƒ@GtÂ™FÃ“|ÃªbÂ‹5^XÃ¼Ã oÃ¦Ã«ÃµÂ»Ã¼Â¨Â‚AÂ‰ÂÂ¼ÃŸÃ†Â³oYÃ‘Ã­5ÂœÂ¢Ã„k}ÂœÃ»JCÂŠÃŸÃ®Ã”:\\nÂ¹Â 2Ã¯ÂŸ6Ã´Â¿tÂ¼Â‚Â­aÂÃÂaÃ­Ã·Â“Â³Â‰Â¼<Â½2Ã€!Â°fÂ›e-Ã”IÂ¿Ã¹0Rr.ÃHÃ9Â—Â­Ã‹\!Â’Â±Ã‘Ã©Ã”Â‡Â­ÂŠ1Ã„%Ã.TÂ¢nÂ¾Â³eÂ¨Â™7aÃ°?Ã©\\rÂ¹!Ã›Â¡[`Â†`Ã£#B/ÃŸG?\\ffÃŠÃ…\\fÂÂ«JaÂ¯Ã²Ã¼:{Â­Â˜PÃ¿\\bÂ¡Â´ER9ÃÂ‹$nÂ€Ã‡ÂŒ Ã­uuÂÂÃ\\nÃ–Â“Ã¶|Ãˆ?'rÂ½@|7fÂÃšÂ²jÂšÃ´Ã·Â²ÃšÂ¥iÂ‹1Ã]Â†sYLÃ´ÃbuÃ¨Ã­ÂÂ½NdÃ“ÂŸ}LEVÃ—\\tZ}WÃ£\\nÂ¼MÂšsÂ«Â‹DJÃ³ÃªlÃœ0Ã¬<?M0ÂšzÃ­ÂŠÂœÃ‚ÃrtÃ 0%Ã”Ã¶Ã¼ÂÃµÃ Â¢ÃÂ…Ã¾ÃœÂÂÂ‘?Ã¿Â¸+ÃKÃ„Ã‚0ÃªÃ…Â‰Ã¡Ã²ÂˆÂ¯ÂƒAÂšÂ”Â½]Ã”XÂˆÃÂ¯Â8VÃ›kZÃ–Ã‡E%Â¨'j^Â½N`KÂ¼ÂÂ›Â“A3Ã¼Â‚?jÂ¥70s7*ÂŠ"ÂµÃ…Â±\\nÃ¨t?ÃœÃ±Â°Ã“9_kÂ‘Ã©Â¨/Â¿UlÃ©Â¢]z^:koÂ¼Ã[Â·Ã£Ã¥\\bÃŠ*j^Â”Ã¶ÃŸ\\fÃ¢Ã¢Ã§gÃºy;|Ã®ÂšÃÂ‘Ã¬LMÃ™mQ\\tÂ˜Â„CÂŒÃ¸/Â…\\fÃ†1ÂÂ»S\\rÃ®/JÂ‘3Â¶ÃšÃ±34Ã™Ã‚Â±Ã®Â–Ã›Ã´Â®Ã†Â—~Ã²Ã†Â¯Ã¢Â’ 8Ã‹"Â»Â\\r\\r;Ã®rÃ¤ÂƒÂ³Â’Â§Ã²Â¨]É…Ã¿.Ã¼\\t2Â©CLÃ€5Ã™Â€}H"Â«VÂ­p*& Ã–Ã¼n>JÂ„Â™ÃªÃœ\Ã­Â£2Ã·Ã²Ã£)Â!<ÂÃ™Ã‰Ã—-A2Ã¹ÂŠÂ®\\bÃ­-<\\nÃ«iÂ¯Ã²:Â‹Ã’ÂÂ¡fÂ¢Â–Ã³tÃ¢Ã›Ã²ÃšÂŠÃ§V\\fXÂ¹Â†Â•Ã‚~Â”Â‰eÃ§Â}mAbLÂ¡=/~Ã˜Â‚Ã‰IÂ¹{\\rAÂ,Â­6Â3B4?Ã¼Z/]Â•!UÂ”Â’Â³2Â‚Â›Ã’Â„ÂˆÂ6zÂ–ÃšÃ¦Ãº<#`v<Ã©3Â¤Â bÃ¾& ]Ã°Â€Â¼PÃ›o CÃ# Â¡Ã•Ã®fÃ…Ã¸Ã½\\tp0xrÃ‰z_\\bÃ™Ã‡e.Â Â˜bÂÃŒ&Â†ÂƒÃ†Â©wÂ¿PÃ’,`'Â¨LÂ•MBÂ°MÂÃ¹&\\rsÂÃ‘ÂœÃ™ÃƒÂ¿6YgÃ¿PÃ¸Ã¶Ã›~nÃŠÃ†Ã»Ã©Ã¾+Â®Â­Ã´Â’Â¨lÃ¤Ã–\ÃÂ #ÂÃ³Â­b (\\tÂ–VÃ¡bÃ²Ã‘Ã¢aÂˆ3>$[=Â$ÃœÃªÂ„6dÂ±WÃ¿EÂ¯Ã­BÃ´VÃŠaKF?ÃÂ¶Ã¸5@Ã–Ã£Â¨Ã”ÃÃ“Â·Â®aÃºÃ•Ã’Â\\bÂ­2PÂ™xÂ¶' Ã\\r-=Â˜Â‡{Ã†(ÃÃ•Ã˜0GÂ·FÃ²Â.8\\tÃ“/Â®n6 Ã”[Â»X$ÃˆÃ¸hÃ›Â‡Ã¹^Ã³]Ã»OKÃÂœ%ÃÂ¿;CÃ˜Ã¦cÂ¼Ã°Ã‚Â°Ã¸ÃÂ‚AÃ¥Ã†sÂ»Â™j3W3Â¨Ã›PÂ•Ã‡Ã­,fÂªÃ‘Ãv[Â—Ã°Ã€$,0;Â„qqUÃ¼l:pU_Ã‰EÃ²rÂÂ—Ã¡Ã±Â¢Â›Ã‚#ÂiÂ´Â®Â¸X;Ã–Â›-Ã½Âº7Ã‡Ã—Ã%tÂŒÂOÃEÂÃ¶Â‡%Â†ÂŠ\\bMpm|QÂ…Â‚Ã½@\IÂvÃƒ%Ã§#Ã“ÂŒÃ¦ÃƒÂ¼Â½Ã‘Â¾5Ã¡Ã·Ã^hPÂ½Ã¸Â»Â·>Ã¡Ã¿.Â¡Ã¥ZÃ·FÃ‡ÂÃ§Â€41Â¡\\fÃµ8Ã¯ÃÂ¢ÂŸÂ¸[}Ã›nÂ»SÃÃ°Â°Ã‹ÂÂ½+\\nÃ”HÂ3ÂºÂ®Â–aÂ£+Ã›Ã‰Â¶ÃŒÂ§$X`Â‘sÃ½\ÂÃ†Â„6& Â†Ã¼Ã‚ÂÃ¬AVÂ¢Â‘Of!m~ EEÂ¨D'HÂ‚Â¬YHÂºÂÃ¹L QÃ¤>ÂšÂ™L>Ã¢Ã­Ã¯Ã‡V@XdÂÃœÂ˜ÂµÃ¦iÂ‹Ã­0G}Â£Ã“Ã„ÂTI,Â@Â©ÂŒÂ‰Â¶YÃœÂ”ÃŸMÂ£Â¯R FÃ¤ÃˆÂ•Ã¨Âˆzm%bÂÂÃµÂ«ÂƒÃ¯Ãn,<LÃQuÂ«$k&!mRÂ†yÃ™Ã²GÂšÃ®Â³Ã”bÂ 'uÃ˜jÃ¥Ã¢Â‘'(Ã€Â¸Â´Ã³\\fNÃ¹Ã†\\b'Ã…Â£\\rÃ‚gQÂÃ²Ã”XÂ_Ã¸JEÃ„"Ã™DÃ—Âº:1RÃšÂÂ†ÂƒXÃ‰qÃ*aÃ˜ Gs\\tÃ†HÃˆÃ¥Ã«Ã‹Ã°`/ÂÃ³Ã€Â¶9ÃµÃ›Ã<,Ã™Ã5ÃŠÂƒÂ’w+.Â¨Ã»Â…Â’f+Ã£Â›KÂ¦Ã¶pÃ‚\\b/Ã›Â®Â“8Ã­oÂ©Ã„.SÃÂ‘Ã²dÃ—\\r%peÂ²Â bÂ¿ÃŸ\\r>ÃªÂ»Â¡SVÂ’Â–Ã²ÂlÃµ,MÃ³6rÃ‹Â”;WÃÃ›Ã¢ Â”ÃdÂ¶ Ã—Â°Â†Â¨41Ã”\\fÃ–/dÃœ^Ã‰Â­yÃŸÃ§Q-\\rÂ¢?AÃ…Ã†uÂ‡z&a8ÂÂ©NÃ¨)2|Â…;AÃµÂœT/d*Ã¯Â¶Ã¯ C4xuF;Ã‹>Ã³Â«Â‘eA]ÂšufÂŒÂÂ‡Ã¸Ã‘ÃÃ²Z Â¹,Ã¦Â¸ÂºÂŠD%Ã¾ÂÃ¬Ã¸SuÃœÂ‹\\tÃ£Â«KÃ‡kXÂ±Âš-vÂ€Â°ÂÃ¼Â¿!Â£Â£Ã´ÃŒoSÂ„Ã†Â‚6/+Â”w;Â´KÂ¬Â]ÃŒÃÃ¢Ã›sÃ®Ã¤L"ÂœX6.Ã¶ÃºÃ´(Ã§Â§ 2ÃÂ²Ã»gÂ½Â¡Ã‰Â»0<lÃoÂÂ¥Â¨;Â£WÃ·gÃ³Ã¥Â‰nbÃ¢@Â”Ã†AÃ"\Ã—aÂ–Ã·ÂˆsÂ—|/RÂ™ÂÃ‹lÃˆÂ„UÂ­ÃŠ/\\bexFDÃ„Â²Â©~Ã™Ã¨SÃ•Â¶>vÂ®9Ã²/Â¹DÂÃÂ¯;Â€ÂŒÃ¼Â¼Â½ÂµÂŸÃ¯Â’Ã¸\\tpÂ¡Â»Ã—Ãœ48ÃÂƒÂ›Ã¢Â©Ã¹Ã³Â– ÂªÃ°tÃ—Ã™Ã”Ã”ÃˆÂ«1ÃÂ„Ã¯Ã»Â»SÂˆHÂ³Â–Â´Ã½Ã”##\\tMÃŠÂ¶wÂ¢+WuÃ¡PÃŸKÂ©Â³ÂµXÂ–ÂƒXSÃ·Ã¶Ã¨Â¾(Â„zÃ•ÃœÃ€Â‚Ã±ÃºÂÃ„Â’ÃÃ¿Â—\\nÄˆÂ£%Xu6bkÃ„~Ã¬ÂµÃ¥ZÂ™ÂÃ´\\fÃ·Â”Ã‹]Â¼ Â¿EÂ¤Ã‚GfÃ»Ã‹Ã–Â“0dÂŒÃ£cÂšÃ†Ã4ÂšRObÂ1Ã¹ÃˆÃÃˆÂ˜0eÂ†jÃ‚}Â°ÂŸ_Ã›Â§Â¨NMCNÃšÃ¬&JÃ° k{Ã“KV>xÃ™Ã›ÂµÃ§Ã³IÃƒÂ€Â¶Ã‚Â„Â¡Ã±yeÃ™Ã°Ã£Â°eÃ„Ã©\\fÂ©_Â¢Â£`Ã•Ã¨ÃˆeÂÃ Ã¨mÃºDÂ­ÂÂÃ®Ã—ÂºEÂˆÂ€}Ã‚$0MÂ¶HÃšÂƒ+ÃŠ-ÃšÂ‚Â¤=Â¿WFSÂ·Â‚Ã—Â™Ã›8Â1Â¬ÂÃ—nZÃ…RÂŒÂœ>Ã¸.Ã¸8-Ã¿Â‘Ã«Ãƒ9ÃˆÃ†b\\nÂŠÃ¤Â«ÂŠÂ•i^Ã©Ã€Â°SKÂ°Â°8ÂW"Ã’e:XÃ€Ã¾Â¦ÂŒÃ¾.Ã¥vÂ§9z8Ã“ÂÃŠÃ”\\tÂª6Ã„Ã…Ã;\9'RÃ¸Ã´gÂ¤Ã¬Â–Ã‡GÃ¬O>#80Âº2Ã¶ÂµÂ¨)(Ã¹GÃºAnÂ¶)B\\tÃ‰Â˜NÃ®o:Â¨Â©Â¥Â²vÃˆÃ‘}Â±Ã¶Â¦Ã±Ã‘Â¥h>Ã±(Â­ÂµÂ³Ã¹oÃ½Â£Â…ÃKq\\b*Ã»oÃ—Â›Ã‹[Ã‘CÃ‰ÃŸÃ›3Â”Ã©$\\r,Ã­ÂŒPY]PÂµÃ.N$RÃŸy,OÃ®ÃµÂ˜-ÃºwJ'Ã„Ã½Â©>3Â±Â¬Â²ÂºfsÂµÃ‘Â‹AÂ„Ã©Ã„*mÃ¯p4Ã\\bbÃ˜Ã£Â¾Â–ÃŒ)DÃ¶9"\\bÃ§=Ã¼fÃ‹Ã›Â‹Ã\\nÃ­Ã¥38CsÃ“Ã¶>Â…^Â—RO~H<Ã£Â¦ÂƒÃ™ KÂ·EwÂ™ÃŸÂ•Ã·mN*\\tgÂ³ÂˆÃ½H8 Ã¬\Â·Â¤\\n{tÃ‡ZÃ¾Ã†BÂ–rgÃ®ÂŸÃ†Ã«1}Ã¼Â±"Ã¥Â³ÃŠÃ©U0pDÃ‹!HrÂ¨Ãš9ÃšÂ,.#"!ÂªÂ”Ã’P\\fPÃ¥ÂÃ¥Â¦ÂÃ®Â¾ssv\\blÂ¬.G7"Ãƒ!Â—eÃ°ÂŒJ|%Â¼Â‹Â©:Â¢Ã¥ÂXÂ“@{ZÃ›Â§Q>Â¶DÃ§ÂÂ˜Ã”Ã¹mÃš2kNtÂ¡Â¢Ã¥ipÂ€Â†Â¤Ã¬Â¼Â­2ÃœÂ´Ã˜Â7Â‘Ã«c:|;ÂÂ¿9Ã¼!KÃ¯AÃºWJÂ¬Â­Ã«Ã¦Ã´1Â„Â„)*hÃ“]QÂ…ÃŸ\\tNÃ™oÃµÂ¬DÃ®ÃƒÂ¡ÃˆÂ¥Ã´Ã¥Ã¤[Â«ÃÃ«ÃœÃ§Ã“ÃŸOÃˆ08tÂ²Ã¢Â·ÃšÂ¤!Ã‹Ã°Â¯0\\tÂªÂˆi9Â˜ifÂ¯ÃE{WqÂQDÂ…Ã²"Ã½Â¶%Âµ;ÂºjÂtHÂ¿2ÂŒ\\rÂŸe_QÃ·/Â\diÃ•Â“Â›ÂŸ$Ã½kÃ‰\#NnÃƒÂ·Ã¼pÂ‰%Â­Ã·Â…ÃšzÂÃ™i5FBÂ¨>TUaJÂ =Ã¥ÂÂ†Â€1Ã‰mÃÃ±Â€0Ã²Â™Â¾Â¿>-Ã•Â·Â«BÃ¥Âƒ6+Ã1}Ã.ÃµSYÂ³^6A{Â™#'ÂÃ¥Ã :Ã‘Â“ÃŠ\\bÃÂƒÂ©Ã€Â•Ã§Â¬Â›ÃªÂ†Ã²HCÂ¤Ã‘vÂ¾Â†Â¬_#Ã›Ã§Ã¶Ã±Ã—Ã“2n0^Â›7Ã¸Ã²Â²e\Â¯$Â{Ã»5Ã¬Â¬Ã‚ÃMÃ±$'ÂµeÂ§ÃœÃÃœMÂÂ¸ÃppuÃ»o+ÃºÂÃµÃw:`Ã¬Â”Ã§~ÃÂºIeVYeÃ¹ÂºÃ»:Â§Â”ÃGÂš\\fjÂ²Ã‰ÂœÂ¹WÂ¯ÂšUÃº\k*Â3LjÂ„Â—Ã’7Ã³Ã—EÂÃ£Â¤PÂ·Ã•ÃŒSÃ”YÃ¦Â•Â“Â° <H)Â·$Ã‘Ã¢z6|Ã‘\Â–ÃŒÂŒÃ®l{j*Â£ÃµÃ³|2Â‰Ã”UÃ³Â·PZÃ²Â‰Ã<! 2_6 YÂ™\\nÂ‰Æ½Â•ÂQÃ®Ã¦pTÃ¹Ã’Ã¥Ã—e.L1%Â•Â¿I*Ã©Ã¡Â³Â¸ScÃ‘Â¸[`\\fÂ¤ÃƒÃ‘r5k.AÂÂ†ÃŸÃÃ¿oÃ€\\br2TÂ•ÂÂ¼ÂŠÃŸÂ´4Â‰ÂºÂ³Ã«bÃ°Â¹ÃÃœÃ”_Â˜Â±Â©JnÂ‹ÂƒEÂˆÃ²ÂÃÃ™Ã€Â† Yr\\nÃ¡Â_Ã°*&Â›@bÂ xÂ™Ã‹Ã Ã•[Ã± x;p`QÃ°~4}WJÃ«Ã˜Â>Ã¸Ã°`Ã«Â¶Â©2Â•<ÃÂŸÃ«7zÃ¦Â³Ã³Â¤Ã¾Â¹!@Â»6ÂŸ5VÃµÃÂ³Â³Â–<7/Â›-h`Â¢^Â¯+dz"Â­Ã›ZZÂ²]v'7Â“c_Â³oÂ«Ã—3)Ã‡2o`Ã°Ã„P^lÂ„Ã¼XÂ¾;Ã¸Â¿ÃŒÃLÃºj =Ã«8Ã¯5Â ÂŒSÃ G\\t#Â‚nÃ„^Ã¬,Ã¯Ãº'ÃŸÂ\\fÃ8Ã½_C~Â®ÃœÃ¬<Â„Â;Ã£Â¤Â­Â²/Ã›Â¶]=UÃÃÂ¸Â©ÃƒÂ‰aÂ¬)Ã’>ÃoÂ—Ã¼Ãª;Â¹Ã‡MÂ„Â±MÃœÃ‚Â_Ã±?Âµ*Ã­Ã‚Ã¿\\rKÃ€Â¾`&.Â­Ãµ?Ã€ÂƒÂ“Ã½`Â…Â¯Ã™Ã›HÃˆÂ§Ã€@ÂœÂŒÂ©ÃÃ¦Â›Ã»&) Ã§Ã¾,j$\\fÂ„Ã›>{ZrKDZOÃ³Ã‡Ã˜Ã´eÃ¯LÂuÃ»2ÃÂ¥[Â¢4$m:LÂ¾Ã¸Ã˜Ã–Â¬Ã1Ã¹ %Ã”|Ã¢Â±IÃ¨Â¤Ã¬Â£Ã§Ã°a |9Ã©Ã»Ã“Ã—o<Â«Â°Â’cTÃœÂ§dÃ€Ã¥{ÃILÃ‡QÃ­PÃ·Â zÂ¸Â³YÃ²hÃ¶aÂ³Ã¢OÃ¶cÃ™RÂ«Â§Â£Â[O\<#ÂbÂ¤Â’ÃŸ.E\\tÂ†Â(mÂ…Ã˜[Ã·FÂ™ÃºÂ¹Â¸ÂƒwÃ•Ã@Ã²mOpÃ§Ã‡Ã–Ã«Ã†\\fÂ¤:ÃŒ1Â¯Â´Â«o-dÃ‚%.ÂÃ¶Ã¡\\fsÂ²Â¥Ân3Â¿pjÂˆÃ‘&^ÂºY!W0EÃ·YsÂ¹ÂºÃ“Ã·Â—\\bÂ„ÂiÂ—;0);ÂaPÃ·Ã—Â‘Â–5ÃœJÂÃ†Â´tkÂ‘i8Â±ÃŸJÂŠÂp!ÃƒÃµÂ¬lÂ¹ÂƒÂ–! ÃÂ²Â¶Â¬Ã¥D\\fÃ¡U~Ã¹ocÂ½Ã‘Â™Â‹Ã‹Ã¹Â´Ã”zÂ·(Ã„ÂEÂ\\rÃ‚[uÃ»Z'Ã@Â§\\rÂš4Ã¿3_Ã» x}Ã¥Ã¤ÂˆÂ;Â˜"\\nÃ¬dÃ¡cxÂ©9gÃ¥Â¡5`mAÂ¿Ã·.ÃÂœÃ°Ã€sÃ¯Ã€Â·Ã’ÃƒÂ€NÃ–Â¤ÃYÃ¸Ã¹Â©R)fÃ´Ã±RÂ“Ã‚a,ZÂ®xÃœÃÃ±ÂCÃ±Ã¢\\tÃ®#}Â¸>\\fÃ¢Â¤"@lÃµ3ÃªÃ¡ÃÂ„JZ Ã§ÂÂ¦Â¤Â«y=)Ã½\\tÂ…Ã–xÃ…y.vÃ¿Ã¡jÂ¶ÃœhÂtÂ¾ÃŸÃ¹ÂÃŒ>ÂÂÂÃ“Â¢Â²uRÂ£ÂÂ­_ÃÃ‘WeÂšÃ®ÃˆÂ´nÂ¬oQ+Ã,!ÂÂ.Â·Âœ>AÂ•NÃ¨Â¿wx<ZÂ¤ÃÂ¡}ÃºÃ»Ã¯Ã¤Ã¶PÃ´Â¦Ã¹-Â»Ã­\\f27veCÂ¡aÃƒÃ¾gÃ­a><Â³ÂŸÃ…ÃyhÃ´\\rÂ¢YÂƒÃ„Ã±Â³Ã®Â¦|Ãµ4[ÃÂ¢Â“GnÃªÂ˜Ây!;Ã·Â®Ã¼\\b\\bÃ‡Â<ÃœÂºa&Ã‹m#Â›^Ã’Ã§Ã¼Ã¼ÂÂº ÃÃ·ÂƒÃŸÂÂ¬Â½zÃ~g+Ã“dÂ¿*Ã¹Ã.Ã”Ã¦hlÂ·Ã«vN%ÃºÂ‚]\Ã¶Ã½S:Â·A,Â¬Â¤Ã»Â¡Â´KÂ1Ã¤ÂÃ¯mÂÂ•Ã´yÃ”;Â &Â™aÃ‘Ã¯Â‡ÃªÂšÃ¹ÂcÃ—Ã»ÂXKÃ©Â‚Ã‡Ã¦ZÂºr+wÂ»~ÂÂ¡ÂÂÃ¥Ã˜Ã´%iC=R\\r2Ã®H~Ãƒ9ÂµWÂŒ%8ÃºÂ²ÃÂ¾ÂŠÃ’61zÃºÂ½Ã’ÃµÂ¯Â£Â¸oÃ¡TRÂ©Ã›apÃŒÂ£|ÃÃ»\\\bÂµx[Ã¨2Ã¢ÃÂ½3Ã‡Â¿Â¾Â t]+wÂ” ÂºÂ¬ÂÂ¨GÃ‹Ã½OBÃ¶LÃ”BÃ9\Ã¯Â‰,Ã¥WÂÃ¤Â³Ã—Â¢M/VÂ;Â Ã³Â½_Â²Ã½Y4?RÂ“+KÃ­"Â—`Ã´Ã‰Â&Â¨Ã”MÂ¿":Â‹Â¥ÃŸ0Ã Gp\\bC\\nÃ•Ã‰*Ã”Â“Ã£]Â‚ÂœÂ…>akÃ§jÂ…Â§Ã»Ã¸E.Â€)7MÃ¬Ã‰FÂ™Â¡Ã¼ÃÂ®Ã–Â—nÃµÂÂ®ÃºnÂ¯ÂªÂ¸Ã²Ã±Ã²ÃÃ“kÂ®Â‰uKÃ’vÂ‚ÃÂgÃ•8a(?Â‰`NÂŸ#AÃ—Ã•Â‡Ã½Â™iÃ˜u}ÂÃÃšÃºhrÂ©Ã„Ã¹34ÂµLÂ­DÂ£Â¾AjWeÂŸÂ·\\b+ÃÃ‹ÂºÂ²Ã†Â¦Ã½Â€\o~WÃƒÂ¯\\bdDÃ›ÃˆÃNÂ˜Â«Ã©yMx]ÃƒÃ°Ã“j 5Ã±Â”MÂ²ar4Ã–ÂÃ‘Ã‹Â’UsJÂšÃ»,;;ÂŠÃ»$Ã‘ Ã±Â‘Ã,Â‰ÂµÂ†Ã’ÃªcgÂÂ€Â¤ÃhEÃ*Ã’Z,ÃÃœÂŸÂ´Â¼OÃ¸c/ÃŠÃµÂ¾Ã­yÂ½Â¯Â«K\\bSÃŒÂµS3tÃ©ÂªzNÃ($hÂ¯Ã½DÃ·(ÃŸÃ²Ã¯ÃŠxÃ yÂ“Â¤Ã¸XpvÃ”Ã¯Ã¨Ã«Â•Ã·Â‚X@Ã¬[3kÃ¦qbFvaÂªÂ€ÂÂ§w]Â¼Â€Â¤M_Ã¡Â›Ã¾\\\nÂˆÂ¸(D_@Ã¬yuÃcWÃ¨Â½Ã´Â²MÃ…Ã˜ÂµÃ˜o\\t@Â{VwÂ¢ Â…Â·Â„Â„Ã„qNÂ¢] Â«[O\\nÂˆÃ«gÃ“Ã„D Â˜ÃŒÃ¦$eÃ¼ÂŠÃ™Â½UÂ¦Ã©Â!iÂ¤ÃÂ±yÂ¹Â™Â°mÂ¤ÂMÃ…Ã±IÂ–ÂLÂ¹Ã£Ã—Ã‚wz Ã >ÃŒ2Ã‹Â‘ -ÂÃ¿Â—Â”Â„Â¤ÃÂ¨Ã£]EÂ„@\\f\\rÃ™Ã¼pRÃœÃšvÂÂ·Â\\bÃ¤Ã”){ÃšÃ¦MÂ§%RÃ‡_\\b4Â¶Ã‡Ã‹Ã±#\\rÂ©Ã³Âµ;HÃ¥Â˜8Â¿ÃºÃ¨[Ã·:Â‚6Â˜Ã§-Ã“Â§Â« Â§(ÃºÂ¤J4|Âª#R8ÂŠ.EÂ‹Âƒ'ÃƒÃÃ•Â¦6Â™Â‰BÃ¸"3ÃƒÂ•Â¾=Ã´AÂ»\\n=Ã fuÃ©Â”ÂµÂ¹Â…>mÂ»iÂÂ@YÃ¨JÃ¤?(Â–}Ã¬bÂ¸V3wÃŠ\\nÃƒ>Â·ÃµÃ†:Ã¯Â¸9PÂ’Â¼Â”Ã•nÂ¨ÃœÂ¡Ã¿Ã«Â¤fÃ€Â¹ÃšÂºÃ‘:.uÃˆÂµÃ¥laÂ¤:Ã Â»ÃÂ¥mÃœÃ OÃ–Ã‡Ã´OÃŸÃƒHÂ¢Ã¸Ã†eT|Ã±xÂ­Â’Â‰ÂT%cÂ…ÃŒ[DÂÃ£${ÂŠw\\bÂ•Â¨Ã„>Â«ÃÂ¨Â¥Ã‘LÂ‡8Ã¹\\tÃÃ˜NÂ¯Â¸Ã²Â¸Ã²Ãš{AKÂ•Ã…V"ÂµÂ‹Â„A}'Ã¨QÂ«Ã¬7aÃ´=*7ÂlÂŠÂ–Â­Â©Ã´5rÂ”ÂÃ´Ã„bBÂ‘Ã™ÂºÂ‚#Â¬Â¥GbÂ€Ã„ÃªÂ¶sa/VÂºaÃ¯Â¾Â‡[ Ã³Â‘aÂ§Ã²HJÂÂ Â’q?@\\t]Â¦jGÂ§Â³EZÂ„ÂšÂ­ÂŸ{xÃ¾QÂ¬\\n]eÂ³4ÂÃ•Ã‡$]E_Â”,QÃ§ÂŠÂ¤ÃŠvÃ˜Â¿Âµkt\\bÂ¸Â²3ÃœI+Â¢QÃ¥&(Â©6Ãœ\\nÃ«Ã­Ã§Ã´ÂšÃÃ™Ã‘ÂxkÂ¡ÃÃ½( Eo%OÂ¶6Ã°Â¸Ã¥Â‚V\\tÃœÂ¤Ã¾kÂ†HÃ§sxÃ9$rLÃªÃ¼Ã]]ÂÂ‹Â‰Â–ÂÃ¼ %Ã„.d>Â­Ã¥Ãª!ÂªÃ°Z;VÂºÂgÃšÃ”Â¤JÃ‹9Â’Â¸Ã‡9IÃŸ@{Â±Â˜Ã…Âª\\t Ã¼ÂŠFÃ¿Â˜{Â†hÂSÂŠ$ÃªKÃ³#Â´QLOÃ¥Â³Ã–LÃ“YF!Â‘Â¤Â$cÃÂ¶Ã˜Ã‘ÂœxÂ»Ã¥eE\\n`Ã¼Â¬ÃƒÃ…Ã…ÂŒbUÃ“Â¦wIp5Â®ÃºÂ…Ã¢Â„Ã½cÃ‰Ã³5s|,J,xÂ¾tÂœÂ¿Ã‚J/sGÂ¤?Â§Â›JÂ¶hE_Â‚Â§Ã¾JÃ¦Â›ÂÂ‘ÃˆÃ²qyÂ,NÂÃ«Ã¼Â°Ã€Ã‚Ãv%tÂ›lxÂŒ[\\bÃ°Â¤"Â¡'
    //   11: dup
    //   12: astore_2
    //   13: invokevirtual length : ()I
    //   16: istore #4
    //   18: bipush #66
    //   20: istore_1
    //   21: iconst_m1
    //   22: istore_0
    //   23: bipush #39
    //   25: iinc #0, 1
    //   28: aload_2
    //   29: iload_0
    //   30: dup
    //   31: iload_1
    //   32: iadd
    //   33: invokevirtual substring : (II)Ljava/lang/String;
    //   36: iconst_m1
    //   37: goto -> 143
    //   40: aload #5
    //   42: swap
    //   43: iload_3
    //   44: iinc #3, 1
    //   47: swap
    //   48: aastore
    //   49: iload_0
    //   50: iload_1
    //   51: iadd
    //   52: dup
    //   53: istore_0
    //   54: iload #4
    //   56: if_icmpge -> 68
    //   59: aload_2
    //   60: iload_0
    //   61: invokevirtual charAt : (I)C
    //   64: istore_1
    //   65: goto -> 23
    //   68: ldc 'ÂEÃ¡Â·ÂÃ•VÂ‰Ã“Ã§bÃ¨Âˆ'
    //   70: dup
    //   71: astore_2
    //   72: invokevirtual length : ()I
    //   75: istore #4
    //   77: bipush #13
    //   79: istore_1
    //   80: iconst_m1
    //   81: istore_0
    //   82: bipush #26
    //   84: iinc #0, 1
    //   87: aload_2
    //   88: iload_0
    //   89: dup
    //   90: iload_1
    //   91: iadd
    //   92: invokevirtual substring : (II)Ljava/lang/String;
    //   95: iconst_0
    //   96: goto -> 143
    //   99: aload #5
    //   101: swap
    //   102: iload_3
    //   103: iinc #3, 1
    //   106: swap
    //   107: aastore
    //   108: iload_0
    //   109: iload_1
    //   110: iadd
    //   111: dup
    //   112: istore_0
    //   113: iload #4
    //   115: if_icmpge -> 127
    //   118: aload_2
    //   119: iload_0
    //   120: invokevirtual charAt : (I)C
    //   123: istore_1
    //   124: goto -> 82
    //   127: aload #5
    //   129: putstatic burp/Zmea.a : [Ljava/lang/String;
    //   132: bipush #91
    //   134: anewarray java/lang/String
    //   137: putstatic burp/Zmea.b : [Ljava/lang/String;
    //   140: goto -> 300
    //   143: dup_x2
    //   144: pop
    //   145: invokevirtual toCharArray : ()[C
    //   148: dup_x1
    //   149: arraylength
    //   150: dup_x2
    //   151: pop
    //   152: iconst_0
    //   153: istore #6
    //   155: dup2_x1
    //   156: pop2
    //   157: dup_x2
    //   158: iconst_1
    //   159: if_icmpgt -> 260
    //   162: dup2
    //   163: swap
    //   164: iload #6
    //   166: dup2_x1
    //   167: caload
    //   168: swap
    //   169: iload #6
    //   171: bipush #7
    //   173: irem
    //   174: tableswitch default -> 242, 0 -> 212, 1 -> 217, 2 -> 222, 3 -> 227, 4 -> 232, 5 -> 237
    //   212: bipush #89
    //   214: goto -> 244
    //   217: bipush #49
    //   219: goto -> 244
    //   222: bipush #13
    //   224: goto -> 244
    //   227: bipush #36
    //   229: goto -> 244
    //   232: bipush #95
    //   234: goto -> 244
    //   237: bipush #16
    //   239: goto -> 244
    //   242: bipush #76
    //   244: ixor
    //   245: ixor
    //   246: i2c
    //   247: castore
    //   248: iinc #6, 1
    //   251: dup
    //   252: ifne -> 260
    //   255: dup2
    //   256: dup_x1
    //   257: goto -> 166
    //   260: dup2_x1
    //   261: pop2
    //   262: dup_x2
    //   263: iload #6
    //   265: if_icmpgt -> 162
    //   268: pop
    //   269: new java/lang/String
    //   272: dup_x1
    //   273: swap
    //   274: invokespecial <init> : ([C)V
    //   277: invokevirtual intern : ()Ljava/lang/String;
    //   280: swap
    //   281: pop
    //   282: swap
    //   283: tableswitch default -> 40, 0 -> 99
    //   300: new burp/Zr1r
    //   303: dup
    //   304: invokespecial <init> : ()V
    //   307: putstatic burp/Zmea.ZA : Ljava/util/Map;
    //   310: return
  }
  
  private static String a(int paramInt1, int paramInt2) {
    int i = (paramInt1 ^ 0x7CD0) & 0xFFFF;
    if (b[i] == null) {
      char[] arrayOfChar = a[i].toCharArray();
      switch (arrayOfChar[0] & 0xFF) {
        case 0:
        
        case 1:
        
        case 2:
        
        case 3:
        
        case 4:
        
        case 5:
        
        case 6:
        
        case 7:
        
        case 8:
        
        case 9:
        
        case 10:
        
        case 11:
        
        case 12:
        
        case 13:
        
        case 14:
        
        case 15:
        
        case 16:
        
        case 17:
        
        case 18:
        
        case 19:
        
        case 20:
        
        case 21:
        
        case 22:
        
        case 23:
        
        case 24:
        
        case 25:
        
        case 26:
        
        case 27:
        
        case 28:
        
        case 29:
        
        case 30:
        
        case 31:
        
        case 32:
        
        case 33:
        
        case 34:
        
        case 35:
        
        case 36:
        
        case 37:
        
        case 38:
        
        case 39:
        
        case 40:
        
        case 41:
        
        case 42:
        
        case 43:
        
        case 44:
        
        case 45:
        
        case 46:
        
        case 47:
        
        case 48:
        
        case 49:
        
        case 50:
        
        case 51:
        
        case 52:
        
        case 53:
        
        case 54:
        
        case 55:
        
        case 56:
        
        case 57:
        
        case 58:
        
        case 59:
        
        case 60:
        
        case 61:
        
        case 62:
        
        case 63:
        
        case 64:
        
        case 65:
        
        case 66:
        
        case 67:
        
        case 68:
        
        case 69:
        
        case 70:
        
        case 71:
        
        case 72:
        
        case 73:
        
        case 74:
        
        case 75:
        
        case 76:
        
        case 77:
        
        case 78:
        
        case 79:
        
        case 80:
        
        case 81:
        
        case 82:
        
        case 83:
        
        case 84:
        
        case 85:
        
        case 86:
        
        case 87:
        
        case 88:
        
        case 89:
        
        case 90:
        
        case 91:
        
        case 92:
        
        case 93:
        
        case 94:
        
        case 95:
        
        case 96:
        
        case 97:
        
        case 98:
        
        case 99:
        
        case 100:
        
        case 101:
        
        case 102:
        
        case 103:
        
        case 104:
        
        case 105:
        
        case 106:
        
        case 107:
        
        case 108:
        
        case 109:
        
        case 110:
        
        case 111:
        
        case 112:
        
        case 113:
        
        case 114:
        
        case 115:
        
        case 116:
        
        case 117:
        
        case 118:
        
        case 119:
        
        case 120:
        
        case 121:
        
        case 122:
        
        case 123:
        
        case 124:
        
        case 125:
        
        case 126:
        
        case 127:
        
        case 128:
        
        case 129:
        
        case 130:
        
        case 131:
        
        case 132:
        
        case 133:
        
        case 134:
        
        case 135:
        
        case 136:
        
        case 137:
        
        case 138:
        
        case 139:
        
        case 140:
        
        case 141:
        
        case 142:
        
        case 143:
        
        case 144:
        
        case 145:
        
        case 146:
        
        case 147:
        
        case 148:
        
        case 149:
        
        case 150:
        
        case 151:
        
        case 152:
        
        case 153:
        
        case 154:
        
        case 155:
        
        case 156:
        
        case 157:
        
        case 158:
        
        case 159:
        
        case 160:
        
        case 161:
        
        case 162:
        
        case 163:
        
        case 164:
        
        case 165:
        
        case 166:
        
        case 167:
        
        case 168:
        
        case 169:
        
        case 170:
        
        case 171:
        
        case 172:
        
        case 173:
        
        case 174:
        
        case 175:
        
        case 176:
        
        case 177:
        
        case 178:
        
        case 179:
        
        case 180:
        
        case 181:
        
        case 182:
        
        case 183:
        
        case 184:
        
        case 185:
        
        case 186:
        
        case 187:
        
        case 188:
        
        case 189:
        
        case 190:
        
        case 191:
        
        case 192:
        
        case 193:
        
        case 194:
        
        case 195:
        
        case 196:
        
        case 197:
        
        case 198:
        
        case 199:
        
        case 200:
        
        case 201:
        
        case 202:
        
        case 203:
        
        case 204:
        
        case 205:
        
        case 206:
        
        case 207:
        
        case 208:
        
        case 209:
        
        case 210:
        
        case 211:
        
        case 212:
        
        case 213:
        
        case 214:
        
        case 215:
        
        case 216:
        
        case 217:
        
        case 218:
        
        case 219:
        
        case 220:
        
        case 221:
        
        case 222:
        
        case 223:
        
        case 224:
        
        case 225:
        
        case 226:
        
        case 227:
        
        case 228:
        
        case 229:
        
        case 230:
        
        case 231:
        
        case 232:
        
        case 233:
        
        case 234:
        
        case 235:
        
        case 236:
        
        case 237:
        
        case 238:
        
        case 239:
        
        case 240:
        
        case 241:
        
        case 242:
        
        case 243:
        
        case 244:
        
        case 245:
        
        case 246:
        
        case 247:
        
        case 248:
        
        case 249:
        
        case 250:
        
        case 251:
        
        case 252:
        
        case 253:
        
        case 254:
        
        default:
          break;
      } 
      char c = 'ÂŠ';
      int j = (paramInt2 & 0xFF) - c;
      if (j < 0)
        j += 256; 
      int k = ((paramInt2 & 0xFFFF) >>> 8) - c;
      if (k < 0)
        k += 256; 
      for (byte b = 0; b < arrayOfChar.length; b++) {
        int m = b % 2;
        if (m == 0) {
          arrayOfChar[b] = (char)(arrayOfChar[b] ^ j);
          j = ((j >>> 3 | j << 5) ^ arrayOfChar[b]) & 0xFF;
        } else {
          arrayOfChar[b] = (char)(arrayOfChar[b] ^ k);
          k = ((k >>> 3 | k << 5) ^ arrayOfChar[b]) & 0xFF;
        } 
      } 
      b[i] = (new String(arrayOfChar)).intern();
    } 
    return b[i];
  }
}


/* Location:              C:\Program Files\BurpSuitePro\burpsuite_pro.jar!\burp\Zmea.class
 * Java compiler version: 21 (65.0)
 * JD-Core Version:       1.1.3
 */