package burp;

import java.util.ArrayList;
import java.util.Collections;
import java.util.EnumSet;
import java.util.Iterator;
import java.util.List;
import net.portswigger.Zkb;
import net.portswigger.Zqf;
import net.portswigger.Zuh;

public class Zmes extends Zmvg {
  private static final String[] a;
  
  private static final String[] b;
  
  public Zmes() {
    super(EnumSet.of(Zzqz.VARIANT));
  }
  
  public String Zi(Zvs paramZvs, byte paramByte1, int paramInt, Ztlj paramZtlj, Ztub paramZtub, Zefg<Zxtl> paramZefg, Zmzk paramZmzk, byte[] paramArrayOfbyte, byte paramByte2, byte paramByte3) {
    // Byte code:
    //   0: new java/lang/StringBuilder
    //   3: dup
    //   4: invokespecial <init> : ()V
    //   7: astore #12
    //   9: invokestatic ZG : ()[I
    //   12: aload #12
    //   14: sipush #14840
    //   17: sipush #-6962
    //   20: invokestatic a : (II)Ljava/lang/String;
    //   23: invokevirtual append : (Ljava/lang/String;)Ljava/lang/StringBuilder;
    //   26: pop
    //   27: astore #11
    //   29: aload_0
    //   30: iload_2
    //   31: invokevirtual Zm : (B)Z
    //   34: ifeq -> 61
    //   37: aload_0
    //   38: aload_1
    //   39: iload_2
    //   40: aload #5
    //   42: aload #6
    //   44: aload #12
    //   46: invokevirtual ZT : (Lburp/Zvs;BLburp/Ztub;Lburp/Zefg;Ljava/lang/StringBuilder;)V
    //   49: aload #11
    //   51: ifnull -> 73
    //   54: iconst_2
    //   55: anewarray burp/Zbqc
    //   58: invokestatic Zr : ([Lburp/Zbqc;)V
    //   61: aload_0
    //   62: aload_1
    //   63: iload_2
    //   64: aload #5
    //   66: aload #6
    //   68: aload #12
    //   70: invokevirtual ZM : (Lburp/Zvs;BLburp/Ztub;Lburp/Zefg;Ljava/lang/StringBuilder;)V
    //   73: aload #12
    //   75: sipush #14821
    //   78: sipush #-9752
    //   81: invokestatic a : (II)Ljava/lang/String;
    //   84: invokevirtual append : (Ljava/lang/String;)Ljava/lang/StringBuilder;
    //   87: pop
    //   88: aload #12
    //   90: sipush #14801
    //   93: sipush #15271
    //   96: invokestatic a : (II)Ljava/lang/String;
    //   99: invokevirtual append : (Ljava/lang/String;)Ljava/lang/StringBuilder;
    //   102: aload_0
    //   103: aload_1
    //   104: aload #5
    //   106: invokevirtual ZO : (Lburp/Zvs;Lburp/Ztub;)Ljava/lang/String;
    //   109: invokestatic Zv : (Ljava/lang/String;)Ljava/lang/String;
    //   112: invokevirtual append : (Ljava/lang/String;)Ljava/lang/StringBuilder;
    //   115: sipush #14843
    //   118: sipush #10922
    //   121: invokestatic a : (II)Ljava/lang/String;
    //   124: invokevirtual append : (Ljava/lang/String;)Ljava/lang/StringBuilder;
    //   127: pop
    //   128: aload_1
    //   129: getstatic burp/Zzu2.SUSPICIOUS_INPUT_TRANSFORMATION_REFLECTED : Lburp/Zzu2;
    //   132: if_acmpne -> 165
    //   135: aload #12
    //   137: sipush #14825
    //   140: sipush #-18595
    //   143: invokestatic a : (II)Ljava/lang/String;
    //   146: invokevirtual append : (Ljava/lang/String;)Ljava/lang/StringBuilder;
    //   149: aload #6
    //   151: iconst_1
    //   152: iconst_0
    //   153: invokestatic Zt : (Lburp/Zefg;ZZ)Ljava/lang/String;
    //   156: invokevirtual append : (Ljava/lang/String;)Ljava/lang/StringBuilder;
    //   159: pop
    //   160: aload #11
    //   162: ifnull -> 204
    //   165: aload_1
    //   166: getstatic burp/Zzu2.SUSPICIOUS_INPUT_TRANSFORMATION_STORED : Lburp/Zzu2;
    //   169: if_acmpne -> 197
    //   172: aload #5
    //   174: invokevirtual Zx : ()Lburp/Zrp9;
    //   177: aload #12
    //   179: aload #5
    //   181: <illegal opcode> accept : (Ljava/lang/StringBuilder;Lburp/Ztub;)Ljava/util/function/Consumer;
    //   186: invokeinterface Zd : (Ljava/util/function/Consumer;)Lburp/Zr1s;
    //   191: pop
    //   192: aload #11
    //   194: ifnull -> 204
    //   197: iconst_0
    //   198: getstatic net/portswigger/Zqf.Zk : Lnet/portswigger/Zqf;
    //   201: invokestatic Zb : (ZLnet/portswigger/Zqf;)V
    //   204: aload #4
    //   206: getstatic burp/Ztz3.REFLECTION : Lburp/Ztz3;
    //   209: invokevirtual ZJ : (Lburp/Ztz3;)Ljava/lang/String;
    //   212: invokestatic Zv : (Ljava/lang/String;)Ljava/lang/String;
    //   215: astore #13
    //   217: iload_2
    //   218: tableswitch default -> 1158, 0 -> 272, 1 -> 357, 2 -> 442, 3 -> 539, 4 -> 818, 5 -> 903, 6 -> 624, 7 -> 721, 8 -> 988, 9 -> 1073
    //   272: aload #12
    //   274: sipush #14796
    //   277: sipush #8505
    //   280: invokestatic a : (II)Ljava/lang/String;
    //   283: invokevirtual append : (Ljava/lang/String;)Ljava/lang/StringBuilder;
    //   286: sipush #14810
    //   289: sipush #22974
    //   292: invokestatic a : (II)Ljava/lang/String;
    //   295: invokevirtual append : (Ljava/lang/String;)Ljava/lang/StringBuilder;
    //   298: sipush #14844
    //   301: sipush #-26690
    //   304: invokestatic a : (II)Ljava/lang/String;
    //   307: invokevirtual append : (Ljava/lang/String;)Ljava/lang/StringBuilder;
    //   310: aload #13
    //   312: invokevirtual append : (Ljava/lang/String;)Ljava/lang/StringBuilder;
    //   315: sipush #14816
    //   318: sipush #-17012
    //   321: invokestatic a : (II)Ljava/lang/String;
    //   324: invokevirtual append : (Ljava/lang/String;)Ljava/lang/StringBuilder;
    //   327: sipush #14847
    //   330: sipush #20555
    //   333: invokestatic a : (II)Ljava/lang/String;
    //   336: invokevirtual append : (Ljava/lang/String;)Ljava/lang/StringBuilder;
    //   339: sipush #14817
    //   342: sipush #-4751
    //   345: invokestatic a : (II)Ljava/lang/String;
    //   348: invokevirtual append : (Ljava/lang/String;)Ljava/lang/StringBuilder;
    //   351: pop
    //   352: aload #11
    //   354: ifnull -> 1167
    //   357: aload #12
    //   359: sipush #14814
    //   362: sipush #14785
    //   365: invokestatic a : (II)Ljava/lang/String;
    //   368: invokevirtual append : (Ljava/lang/String;)Ljava/lang/StringBuilder;
    //   371: sipush #14797
    //   374: sipush #-10943
    //   377: invokestatic a : (II)Ljava/lang/String;
    //   380: invokevirtual append : (Ljava/lang/String;)Ljava/lang/StringBuilder;
    //   383: sipush #14844
    //   386: sipush #-26690
    //   389: invokestatic a : (II)Ljava/lang/String;
    //   392: invokevirtual append : (Ljava/lang/String;)Ljava/lang/StringBuilder;
    //   395: aload #13
    //   397: invokevirtual append : (Ljava/lang/String;)Ljava/lang/StringBuilder;
    //   400: sipush #14816
    //   403: sipush #-17012
    //   406: invokestatic a : (II)Ljava/lang/String;
    //   409: invokevirtual append : (Ljava/lang/String;)Ljava/lang/StringBuilder;
    //   412: sipush #14839
    //   415: sipush #-10149
    //   418: invokestatic a : (II)Ljava/lang/String;
    //   421: invokevirtual append : (Ljava/lang/String;)Ljava/lang/StringBuilder;
    //   424: sipush #14800
    //   427: sipush #-7737
    //   430: invokestatic a : (II)Ljava/lang/String;
    //   433: invokevirtual append : (Ljava/lang/String;)Ljava/lang/StringBuilder;
    //   436: pop
    //   437: aload #11
    //   439: ifnull -> 1167
    //   442: aload #12
    //   444: sipush #14842
    //   447: sipush #-21411
    //   450: invokestatic a : (II)Ljava/lang/String;
    //   453: invokevirtual append : (Ljava/lang/String;)Ljava/lang/StringBuilder;
    //   456: sipush #14797
    //   459: sipush #-10943
    //   462: invokestatic a : (II)Ljava/lang/String;
    //   465: invokevirtual append : (Ljava/lang/String;)Ljava/lang/StringBuilder;
    //   468: sipush #14844
    //   471: sipush #-26690
    //   474: invokestatic a : (II)Ljava/lang/String;
    //   477: invokevirtual append : (Ljava/lang/String;)Ljava/lang/StringBuilder;
    //   480: aload #13
    //   482: invokevirtual append : (Ljava/lang/String;)Ljava/lang/StringBuilder;
    //   485: sipush #14816
    //   488: sipush #-17012
    //   491: invokestatic a : (II)Ljava/lang/String;
    //   494: invokevirtual append : (Ljava/lang/String;)Ljava/lang/StringBuilder;
    //   497: sipush #14804
    //   500: sipush #-24490
    //   503: invokestatic a : (II)Ljava/lang/String;
    //   506: invokevirtual append : (Ljava/lang/String;)Ljava/lang/StringBuilder;
    //   509: sipush #14803
    //   512: sipush #31443
    //   515: invokestatic a : (II)Ljava/lang/String;
    //   518: invokevirtual append : (Ljava/lang/String;)Ljava/lang/StringBuilder;
    //   521: sipush #14838
    //   524: sipush #-21805
    //   527: invokestatic a : (II)Ljava/lang/String;
    //   530: invokevirtual append : (Ljava/lang/String;)Ljava/lang/StringBuilder;
    //   533: pop
    //   534: aload #11
    //   536: ifnull -> 1167
    //   539: aload #12
    //   541: sipush #14809
    //   544: sipush #3184
    //   547: invokestatic a : (II)Ljava/lang/String;
    //   550: invokevirtual append : (Ljava/lang/String;)Ljava/lang/StringBuilder;
    //   553: sipush #14797
    //   556: sipush #-10943
    //   559: invokestatic a : (II)Ljava/lang/String;
    //   562: invokevirtual append : (Ljava/lang/String;)Ljava/lang/StringBuilder;
    //   565: sipush #14844
    //   568: sipush #-26690
    //   571: invokestatic a : (II)Ljava/lang/String;
    //   574: invokevirtual append : (Ljava/lang/String;)Ljava/lang/StringBuilder;
    //   577: aload #13
    //   579: invokevirtual append : (Ljava/lang/String;)Ljava/lang/StringBuilder;
    //   582: sipush #14816
    //   585: sipush #-17012
    //   588: invokestatic a : (II)Ljava/lang/String;
    //   591: invokevirtual append : (Ljava/lang/String;)Ljava/lang/StringBuilder;
    //   594: sipush #14792
    //   597: sipush #15302
    //   600: invokestatic a : (II)Ljava/lang/String;
    //   603: invokevirtual append : (Ljava/lang/String;)Ljava/lang/StringBuilder;
    //   606: sipush #14806
    //   609: sipush #23317
    //   612: invokestatic a : (II)Ljava/lang/String;
    //   615: invokevirtual append : (Ljava/lang/String;)Ljava/lang/StringBuilder;
    //   618: pop
    //   619: aload #11
    //   621: ifnull -> 1167
    //   624: aload #12
    //   626: sipush #14808
    //   629: sipush #-26537
    //   632: invokestatic a : (II)Ljava/lang/String;
    //   635: invokevirtual append : (Ljava/lang/String;)Ljava/lang/StringBuilder;
    //   638: sipush #14797
    //   641: sipush #-10943
    //   644: invokestatic a : (II)Ljava/lang/String;
    //   647: invokevirtual append : (Ljava/lang/String;)Ljava/lang/StringBuilder;
    //   650: sipush #14844
    //   653: sipush #-26690
    //   656: invokestatic a : (II)Ljava/lang/String;
    //   659: invokevirtual append : (Ljava/lang/String;)Ljava/lang/StringBuilder;
    //   662: aload #13
    //   664: invokevirtual append : (Ljava/lang/String;)Ljava/lang/StringBuilder;
    //   667: sipush #14816
    //   670: sipush #-17012
    //   673: invokestatic a : (II)Ljava/lang/String;
    //   676: invokevirtual append : (Ljava/lang/String;)Ljava/lang/StringBuilder;
    //   679: sipush #14790
    //   682: sipush #27948
    //   685: invokestatic a : (II)Ljava/lang/String;
    //   688: invokevirtual append : (Ljava/lang/String;)Ljava/lang/StringBuilder;
    //   691: sipush #14813
    //   694: sipush #28812
    //   697: invokestatic a : (II)Ljava/lang/String;
    //   700: invokevirtual append : (Ljava/lang/String;)Ljava/lang/StringBuilder;
    //   703: sipush #14805
    //   706: sipush #26215
    //   709: invokestatic a : (II)Ljava/lang/String;
    //   712: invokevirtual append : (Ljava/lang/String;)Ljava/lang/StringBuilder;
    //   715: pop
    //   716: aload #11
    //   718: ifnull -> 1167
    //   721: aload #12
    //   723: sipush #14841
    //   726: sipush #20889
    //   729: invokestatic a : (II)Ljava/lang/String;
    //   732: invokevirtual append : (Ljava/lang/String;)Ljava/lang/StringBuilder;
    //   735: sipush #14797
    //   738: sipush #-10943
    //   741: invokestatic a : (II)Ljava/lang/String;
    //   744: invokevirtual append : (Ljava/lang/String;)Ljava/lang/StringBuilder;
    //   747: sipush #14844
    //   750: sipush #-26690
    //   753: invokestatic a : (II)Ljava/lang/String;
    //   756: invokevirtual append : (Ljava/lang/String;)Ljava/lang/StringBuilder;
    //   759: aload #13
    //   761: invokevirtual append : (Ljava/lang/String;)Ljava/lang/StringBuilder;
    //   764: sipush #14816
    //   767: sipush #-17012
    //   770: invokestatic a : (II)Ljava/lang/String;
    //   773: invokevirtual append : (Ljava/lang/String;)Ljava/lang/StringBuilder;
    //   776: sipush #14792
    //   779: sipush #15302
    //   782: invokestatic a : (II)Ljava/lang/String;
    //   785: invokevirtual append : (Ljava/lang/String;)Ljava/lang/StringBuilder;
    //   788: sipush #14837
    //   791: sipush #-9018
    //   794: invokestatic a : (II)Ljava/lang/String;
    //   797: invokevirtual append : (Ljava/lang/String;)Ljava/lang/StringBuilder;
    //   800: sipush #14836
    //   803: sipush #22870
    //   806: invokestatic a : (II)Ljava/lang/String;
    //   809: invokevirtual append : (Ljava/lang/String;)Ljava/lang/StringBuilder;
    //   812: pop
    //   813: aload #11
    //   815: ifnull -> 1167
    //   818: aload #12
    //   820: sipush #14822
    //   823: sipush #9509
    //   826: invokestatic a : (II)Ljava/lang/String;
    //   829: invokevirtual append : (Ljava/lang/String;)Ljava/lang/StringBuilder;
    //   832: sipush #14797
    //   835: sipush #-10943
    //   838: invokestatic a : (II)Ljava/lang/String;
    //   841: invokevirtual append : (Ljava/lang/String;)Ljava/lang/StringBuilder;
    //   844: sipush #14844
    //   847: sipush #-26690
    //   850: invokestatic a : (II)Ljava/lang/String;
    //   853: invokevirtual append : (Ljava/lang/String;)Ljava/lang/StringBuilder;
    //   856: aload #13
    //   858: invokevirtual append : (Ljava/lang/String;)Ljava/lang/StringBuilder;
    //   861: sipush #14816
    //   864: sipush #-17012
    //   867: invokestatic a : (II)Ljava/lang/String;
    //   870: invokevirtual append : (Ljava/lang/String;)Ljava/lang/StringBuilder;
    //   873: sipush #14820
    //   876: sipush #17994
    //   879: invokestatic a : (II)Ljava/lang/String;
    //   882: invokevirtual append : (Ljava/lang/String;)Ljava/lang/StringBuilder;
    //   885: sipush #14811
    //   888: sipush #-18154
    //   891: invokestatic a : (II)Ljava/lang/String;
    //   894: invokevirtual append : (Ljava/lang/String;)Ljava/lang/StringBuilder;
    //   897: pop
    //   898: aload #11
    //   900: ifnull -> 1167
    //   903: aload #12
    //   905: sipush #14786
    //   908: sipush #-8661
    //   911: invokestatic a : (II)Ljava/lang/String;
    //   914: invokevirtual append : (Ljava/lang/String;)Ljava/lang/StringBuilder;
    //   917: sipush #14797
    //   920: sipush #-10943
    //   923: invokestatic a : (II)Ljava/lang/String;
    //   926: invokevirtual append : (Ljava/lang/String;)Ljava/lang/StringBuilder;
    //   929: sipush #14844
    //   932: sipush #-26690
    //   935: invokestatic a : (II)Ljava/lang/String;
    //   938: invokevirtual append : (Ljava/lang/String;)Ljava/lang/StringBuilder;
    //   941: aload #13
    //   943: invokevirtual append : (Ljava/lang/String;)Ljava/lang/StringBuilder;
    //   946: sipush #14816
    //   949: sipush #-17012
    //   952: invokestatic a : (II)Ljava/lang/String;
    //   955: invokevirtual append : (Ljava/lang/String;)Ljava/lang/StringBuilder;
    //   958: sipush #14792
    //   961: sipush #15302
    //   964: invokestatic a : (II)Ljava/lang/String;
    //   967: invokevirtual append : (Ljava/lang/String;)Ljava/lang/StringBuilder;
    //   970: sipush #14806
    //   973: sipush #23317
    //   976: invokestatic a : (II)Ljava/lang/String;
    //   979: invokevirtual append : (Ljava/lang/String;)Ljava/lang/StringBuilder;
    //   982: pop
    //   983: aload #11
    //   985: ifnull -> 1167
    //   988: aload #12
    //   990: sipush #14784
    //   993: sipush #-13373
    //   996: invokestatic a : (II)Ljava/lang/String;
    //   999: invokevirtual append : (Ljava/lang/String;)Ljava/lang/StringBuilder;
    //   1002: sipush #14797
    //   1005: sipush #-10943
    //   1008: invokestatic a : (II)Ljava/lang/String;
    //   1011: invokevirtual append : (Ljava/lang/String;)Ljava/lang/StringBuilder;
    //   1014: sipush #14844
    //   1017: sipush #-26690
    //   1020: invokestatic a : (II)Ljava/lang/String;
    //   1023: invokevirtual append : (Ljava/lang/String;)Ljava/lang/StringBuilder;
    //   1026: aload #13
    //   1028: invokevirtual append : (Ljava/lang/String;)Ljava/lang/StringBuilder;
    //   1031: sipush #14816
    //   1034: sipush #-17012
    //   1037: invokestatic a : (II)Ljava/lang/String;
    //   1040: invokevirtual append : (Ljava/lang/String;)Ljava/lang/StringBuilder;
    //   1043: sipush #14835
    //   1046: sipush #-2617
    //   1049: invokestatic a : (II)Ljava/lang/String;
    //   1052: invokevirtual append : (Ljava/lang/String;)Ljava/lang/StringBuilder;
    //   1055: sipush #14818
    //   1058: sipush #31655
    //   1061: invokestatic a : (II)Ljava/lang/String;
    //   1064: invokevirtual append : (Ljava/lang/String;)Ljava/lang/StringBuilder;
    //   1067: pop
    //   1068: aload #11
    //   1070: ifnull -> 1167
    //   1073: aload #12
    //   1075: sipush #14845
    //   1078: sipush #-16354
    //   1081: invokestatic a : (II)Ljava/lang/String;
    //   1084: invokevirtual append : (Ljava/lang/String;)Ljava/lang/StringBuilder;
    //   1087: sipush #14797
    //   1090: sipush #-10943
    //   1093: invokestatic a : (II)Ljava/lang/String;
    //   1096: invokevirtual append : (Ljava/lang/String;)Ljava/lang/StringBuilder;
    //   1099: sipush #14844
    //   1102: sipush #-26690
    //   1105: invokestatic a : (II)Ljava/lang/String;
    //   1108: invokevirtual append : (Ljava/lang/String;)Ljava/lang/StringBuilder;
    //   1111: aload #13
    //   1113: invokevirtual append : (Ljava/lang/String;)Ljava/lang/StringBuilder;
    //   1116: sipush #14816
    //   1119: sipush #-17012
    //   1122: invokestatic a : (II)Ljava/lang/String;
    //   1125: invokevirtual append : (Ljava/lang/String;)Ljava/lang/StringBuilder;
    //   1128: sipush #14792
    //   1131: sipush #15302
    //   1134: invokestatic a : (II)Ljava/lang/String;
    //   1137: invokevirtual append : (Ljava/lang/String;)Ljava/lang/StringBuilder;
    //   1140: sipush #14806
    //   1143: sipush #23317
    //   1146: invokestatic a : (II)Ljava/lang/String;
    //   1149: invokevirtual append : (Ljava/lang/String;)Ljava/lang/StringBuilder;
    //   1152: pop
    //   1153: aload #11
    //   1155: ifnull -> 1167
    //   1158: iconst_0
    //   1159: getstatic net/portswigger/Zqf.Zk : Lnet/portswigger/Zqf;
    //   1162: iload_2
    //   1163: i2l
    //   1164: invokestatic Zv : (ZLnet/portswigger/Zqf;J)V
    //   1167: aload_1
    //   1168: getstatic burp/Zzu2.SUSPICIOUS_INPUT_TRANSFORMATION_STORED : Lburp/Zzu2;
    //   1171: if_acmpne -> 1213
    //   1174: aload #12
    //   1176: sipush #14789
    //   1179: sipush #-3828
    //   1182: invokestatic a : (II)Ljava/lang/String;
    //   1185: invokevirtual append : (Ljava/lang/String;)Ljava/lang/StringBuilder;
    //   1188: sipush #14827
    //   1191: sipush #-10421
    //   1194: invokestatic a : (II)Ljava/lang/String;
    //   1197: invokevirtual append : (Ljava/lang/String;)Ljava/lang/StringBuilder;
    //   1200: sipush #14799
    //   1203: sipush #-30166
    //   1206: invokestatic a : (II)Ljava/lang/String;
    //   1209: invokevirtual append : (Ljava/lang/String;)Ljava/lang/StringBuilder;
    //   1212: pop
    //   1213: aload #12
    //   1215: invokevirtual toString : ()Ljava/lang/String;
    //   1218: areturn
  }
  
  private String ZO(Zvs paramZvs, Ztub paramZtub) {
    if (paramZvs == Zzu2.SUSPICIOUS_INPUT_TRANSFORMATION_REFLECTED)
      return paramZtub.Zd().Zub().Zsf().Zis(); 
    if (paramZvs == Zzu2.SUSPICIOUS_INPUT_TRANSFORMATION_STORED)
      return paramZtub.Zx().Zub().Zsf().Zis(); 
    Zuh.Zb(false, Zqf.Zk);
    return "";
  }
  
  private void ZM(Zvs paramZvs, byte paramByte, Ztub paramZtub, Zefg<Zxtl> paramZefg, StringBuilder paramStringBuilder) {
    // Byte code:
    //   0: invokestatic ZG : ()[I
    //   3: astore #6
    //   5: aload #5
    //   7: sipush #14823
    //   10: sipush #-11256
    //   13: invokestatic a : (II)Ljava/lang/String;
    //   16: invokevirtual append : (Ljava/lang/String;)Ljava/lang/StringBuilder;
    //   19: pop
    //   20: iload_2
    //   21: tableswitch default -> 172, 0 -> 72, 1 -> 172, 2 -> 92, 3 -> 172, 4 -> 132, 5 -> 172, 6 -> 112, 7 -> 172, 8 -> 152
    //   72: aload #5
    //   74: sipush #14812
    //   77: sipush #20462
    //   80: invokestatic a : (II)Ljava/lang/String;
    //   83: invokevirtual append : (Ljava/lang/String;)Ljava/lang/StringBuilder;
    //   86: pop
    //   87: aload #6
    //   89: ifnull -> 181
    //   92: aload #5
    //   94: sipush #14832
    //   97: sipush #28363
    //   100: invokestatic a : (II)Ljava/lang/String;
    //   103: invokevirtual append : (Ljava/lang/String;)Ljava/lang/StringBuilder;
    //   106: pop
    //   107: aload #6
    //   109: ifnull -> 181
    //   112: aload #5
    //   114: sipush #14798
    //   117: sipush #-5837
    //   120: invokestatic a : (II)Ljava/lang/String;
    //   123: invokevirtual append : (Ljava/lang/String;)Ljava/lang/StringBuilder;
    //   126: pop
    //   127: aload #6
    //   129: ifnull -> 181
    //   132: aload #5
    //   134: sipush #14807
    //   137: sipush #5718
    //   140: invokestatic a : (II)Ljava/lang/String;
    //   143: invokevirtual append : (Ljava/lang/String;)Ljava/lang/StringBuilder;
    //   146: pop
    //   147: aload #6
    //   149: ifnull -> 181
    //   152: aload #5
    //   154: sipush #14802
    //   157: sipush #20248
    //   160: invokestatic a : (II)Ljava/lang/String;
    //   163: invokevirtual append : (Ljava/lang/String;)Ljava/lang/StringBuilder;
    //   166: pop
    //   167: aload #6
    //   169: ifnull -> 181
    //   172: iconst_0
    //   173: getstatic net/portswigger/Zqf.Zk : Lnet/portswigger/Zqf;
    //   176: iload_2
    //   177: i2l
    //   178: invokestatic Zv : (ZLnet/portswigger/Zqf;J)V
    //   181: aload #5
    //   183: ldc ' '
    //   185: invokevirtual append : (Ljava/lang/String;)Ljava/lang/StringBuilder;
    //   188: pop
    //   189: aload #5
    //   191: aload #4
    //   193: iconst_1
    //   194: iconst_1
    //   195: invokestatic ZM : (Lburp/Zefg;ZZ)Ljava/lang/String;
    //   198: invokevirtual append : (Ljava/lang/String;)Ljava/lang/StringBuilder;
    //   201: pop
    //   202: aload_1
    //   203: getstatic burp/Zzu2.SUSPICIOUS_INPUT_TRANSFORMATION_REFLECTED : Lburp/Zzu2;
    //   206: if_acmpne -> 229
    //   209: aload #5
    //   211: sipush #14787
    //   214: sipush #-23156
    //   217: invokestatic a : (II)Ljava/lang/String;
    //   220: invokevirtual append : (Ljava/lang/String;)Ljava/lang/StringBuilder;
    //   223: pop
    //   224: aload #6
    //   226: ifnull -> 265
    //   229: aload_1
    //   230: getstatic burp/Zzu2.SUSPICIOUS_INPUT_TRANSFORMATION_STORED : Lburp/Zzu2;
    //   233: if_acmpne -> 258
    //   236: aload_3
    //   237: invokevirtual Zx : ()Lburp/Zrp9;
    //   240: aload #5
    //   242: <illegal opcode> accept : (Ljava/lang/StringBuilder;)Ljava/util/function/Consumer;
    //   247: invokeinterface Zd : (Ljava/util/function/Consumer;)Lburp/Zr1s;
    //   252: pop
    //   253: aload #6
    //   255: ifnull -> 265
    //   258: iconst_0
    //   259: getstatic net/portswigger/Zqf.Zk : Lnet/portswigger/Zqf;
    //   262: invokestatic Zb : (ZLnet/portswigger/Zqf;)V
    //   265: return
  }
  
  private void ZT(Zvs paramZvs, byte paramByte, Ztub paramZtub, Zefg<Zxtl> paramZefg, StringBuilder paramStringBuilder) {
    // Byte code:
    //   0: aload #5
    //   2: sipush #14785
    //   5: sipush #-10673
    //   8: invokestatic a : (II)Ljava/lang/String;
    //   11: invokevirtual append : (Ljava/lang/String;)Ljava/lang/StringBuilder;
    //   14: pop
    //   15: invokestatic ZG : ()[I
    //   18: aload #5
    //   20: aload #4
    //   22: iconst_1
    //   23: iconst_1
    //   24: invokestatic ZM : (Lburp/Zefg;ZZ)Ljava/lang/String;
    //   27: invokevirtual append : (Ljava/lang/String;)Ljava/lang/StringBuilder;
    //   30: pop
    //   31: astore #6
    //   33: aload #5
    //   35: sipush #14834
    //   38: sipush #13982
    //   41: invokestatic a : (II)Ljava/lang/String;
    //   44: invokevirtual append : (Ljava/lang/String;)Ljava/lang/StringBuilder;
    //   47: pop
    //   48: iload_2
    //   49: tableswitch default -> 200, 1 -> 100, 2 -> 200, 3 -> 120, 4 -> 200, 5 -> 160, 6 -> 200, 7 -> 140, 8 -> 200, 9 -> 180
    //   100: aload #5
    //   102: sipush #14794
    //   105: sipush #-7400
    //   108: invokestatic a : (II)Ljava/lang/String;
    //   111: invokevirtual append : (Ljava/lang/String;)Ljava/lang/StringBuilder;
    //   114: pop
    //   115: aload #6
    //   117: ifnull -> 209
    //   120: aload #5
    //   122: sipush #14788
    //   125: sipush #6967
    //   128: invokestatic a : (II)Ljava/lang/String;
    //   131: invokevirtual append : (Ljava/lang/String;)Ljava/lang/StringBuilder;
    //   134: pop
    //   135: aload #6
    //   137: ifnull -> 209
    //   140: aload #5
    //   142: sipush #14833
    //   145: sipush #14356
    //   148: invokestatic a : (II)Ljava/lang/String;
    //   151: invokevirtual append : (Ljava/lang/String;)Ljava/lang/StringBuilder;
    //   154: pop
    //   155: aload #6
    //   157: ifnull -> 209
    //   160: aload #5
    //   162: sipush #14826
    //   165: sipush #-21930
    //   168: invokestatic a : (II)Ljava/lang/String;
    //   171: invokevirtual append : (Ljava/lang/String;)Ljava/lang/StringBuilder;
    //   174: pop
    //   175: aload #6
    //   177: ifnull -> 209
    //   180: aload #5
    //   182: sipush #14791
    //   185: sipush #26691
    //   188: invokestatic a : (II)Ljava/lang/String;
    //   191: invokevirtual append : (Ljava/lang/String;)Ljava/lang/StringBuilder;
    //   194: pop
    //   195: aload #6
    //   197: ifnull -> 209
    //   200: iconst_0
    //   201: getstatic net/portswigger/Zqf.Zk : Lnet/portswigger/Zqf;
    //   204: iload_2
    //   205: i2l
    //   206: invokestatic Zv : (ZLnet/portswigger/Zqf;J)V
    //   209: aload_1
    //   210: getstatic burp/Zzu2.SUSPICIOUS_INPUT_TRANSFORMATION_REFLECTED : Lburp/Zzu2;
    //   213: if_acmpne -> 236
    //   216: aload #5
    //   218: sipush #14793
    //   221: sipush #-17634
    //   224: invokestatic a : (II)Ljava/lang/String;
    //   227: invokevirtual append : (Ljava/lang/String;)Ljava/lang/StringBuilder;
    //   230: pop
    //   231: aload #6
    //   233: ifnull -> 272
    //   236: aload_1
    //   237: getstatic burp/Zzu2.SUSPICIOUS_INPUT_TRANSFORMATION_STORED : Lburp/Zzu2;
    //   240: if_acmpne -> 265
    //   243: aload_3
    //   244: invokevirtual Zx : ()Lburp/Zrp9;
    //   247: aload #5
    //   249: <illegal opcode> accept : (Ljava/lang/StringBuilder;)Ljava/util/function/Consumer;
    //   254: invokeinterface Zd : (Ljava/util/function/Consumer;)Lburp/Zr1s;
    //   259: pop
    //   260: aload #6
    //   262: ifnull -> 272
    //   265: iconst_0
    //   266: getstatic net/portswigger/Zqf.Zk : Lnet/portswigger/Zqf;
    //   269: invokestatic Zb : (ZLnet/portswigger/Zqf;)V
    //   272: return
  }
  
  private boolean Zm(byte paramByte) {
    return (paramByte == 1 || paramByte == 3 || paramByte == 5 || paramByte == 7 || paramByte == 9);
  }
  
  private static String Zv(String paramString) {
    return Zrlp.ZY(Zmey.ZW(paramString));
  }
  
  static <T extends Zgkc> Zsqx<Zrdb> Zh(Zvs paramZvs, byte paramByte, Zlfv<T> paramZlfv, String paramString, Zku6 paramZku6, Zxs7 paramZxs7) {
    int[] arrayOfInt = Zedl.ZG();
    Zz_p zz_p = ((Zkv8)paramZku6.ZP((byte)2).get(0)).Zw();
    if (Zbqc.Zwu() == null)
      Zedl.ZI(new int[5]); 
    return new Zx_5(paramZvs, paramByte, 0, Zriz.ZO(new Zra_[] { Zriz.ZG(Ztz3.REFLECTION, Zkb.ZG(zz_p.Ze)) }), (List)Collections.singletonList(paramZlfv), (byte)2, (byte)1, paramZku6.ZV().ZB(), Zkb.Zy(paramString), paramZxs7);
  }
  
  public static List<Zl1r> ZE(List<Zkv8> paramList) {
    ArrayList<Zl1r> arrayList = new ArrayList();
    Iterator<Zkv8> iterator = paramList.iterator();
    int[] arrayOfInt = Zedl.ZG();
    while (iterator.hasNext()) {
      Zkv8 zkv8 = iterator.next();
      arrayList.add(Zrlp.ZJ(zkv8));
      if (arrayOfInt != null)
        break; 
    } 
    return arrayList;
  }
  
  private static void lambda$buildUnexpectedTransformationDescription$2(StringBuilder paramStringBuilder, Zrp9 paramZrp9) {
    paramStringBuilder.append(a(14846, 1601));
  }
  
  private static void lambda$buildDecodingDescription$1(StringBuilder paramStringBuilder, Zrp9 paramZrp9) {
    paramStringBuilder.append(a(14815, -15021));
  }
  
  private static void lambda$buildIssueDetail$0(StringBuilder paramStringBuilder, Ztub paramZtub, Zrp9 paramZrp9) {
    paramStringBuilder.append(a(14795, 11709));
    Zrlp.Zn(paramStringBuilder, Zkb.ZG(paramZrp9.Zvs()));
    paramStringBuilder.append(a(14819, 16803));
    Zrlp.Zn(paramStringBuilder, Zkb.ZG(paramZtub.Zx().ZvM()));
  }
  
  static {
    // Byte code:
    //   0: bipush #59
    //   2: anewarray java/lang/String
    //   5: astore #5
    //   7: iconst_0
    //   8: istore_3
    //   9: ldc 'Ã²y_1ÃŠÂƒ.Â¾Â€Â™Â¦@Ã´jHÃ€ÂŸxÃƒ1}Â–:ÂŒQ]Â¥?730?Â’sÃ–Ã³Ã­$EÂ‹Ã‡Ã¥'UUFÃ‹KÂ­Â¨Ã–ÃŒÂ£Â½Â‚Â„Ã¤AÂ³ÂªÂ¿Ã¡<0Ã“,ÃÂ‘Ã¼Â½Ã«qV^Â‹ÃºxÃ‚Ã·Ã…KÂ¥mÃÃ¹ÃŠÂ¸[=Ã¿H1Â\\t$BÃ¦ÂŠÂ–Â„Ã“Ã½ÂƒÃœ\\fÃ¸SÂ§wÂ¿ÃÂ›Ã¢Ã„Â–9Â¶qÂ›\\bS?ÂÂ¶Ã‰Â‚6Â¤Ã½4ÂB-Â :~Â‚@Ã³Ã¡Â—Â¿9&\\bÃ¥jÂ»,ÃƒÃ©Ã®Ã·rnOÃ“ÃˆÃŸWÂ¥Â¶Ã±Â˜Âˆ`1nÃ°@Âˆh!3!B2Ã½PsÂ…Ãº3Â‹Â°/pqÂŠÂ³f,4ÂŠÃ©1 #Ã­Ã•QÃ›Â©Â¯ÃµÂCÂ¡Ã¿ÃLU(hÃ£pÂ‰Ã¾BÃªE ÂŒÂƒxÂ¼Â›XÃ¶Â‹ÃÂ€Ã¤Ã²Ã§+=Ã‡X@Ã¯Â¤eÃ¤0ÂšÃ†ÂšzJ^YiÂ­Â¶Â—*ÃªÂ©Ã„Â™\\rAÂ¹#Â¤Ã¼Ã¦6Ã›]Â Ã€~ÃÂ¤Â±ÂJ~Ã­XÂºÃ€Â‚ ÃµÂ™ÃˆiÃ (T,FÃŸÃÃ¨=Ã£GÃ¬ $Ã‰<ÃœÂ•cÃŸÃ9WDPÃ©Ãƒ`Ã½xy1CÃœÃ‚]Â®ÂhHÂ¿l@Ã©1Â›QÃš8>tÂ­Ã¬FDÂŠ6*Ã»[*+rXÃ¥ÃP.ÂTÂµ`Ã ÂŠ\ÂˆÂÃXÂ ÂƒÃ¶;h\\t\\fI%Â›Â¿Ã¸ÃšÂ—SbÃ‰7fÂ“Ã€ÂšZ|ÂÃƒzÃ·dÂ¨ÂÂÃ„\Ã†Ã—ÂÂ´Ã¥Â€ÃÃ†VNÂªÃ¹k:I~SÂ‘|Ã¾ KÂƒÂ½Â¦ÃÃ­Â¨)Â‘Â¸MXÂ¦dÂ´Â‘Â“Ã›ÃƒÂ—qÃ·Ã®Â… Ã€Â“Ã­ÃÃÂ™Ã˜Ã•fOÃÃŸÂ¦YÃ¡&aÃ Â¯Ãµ9*Ã¨Ã€ÂB<ÂªÃ¼ ^Â¦4lÂ‚Â”^SÃ²Ã¶XZÂ+2uÃ¤('Ã¼oAUZÂ²@Ã…ÂÃŠÂ»^Ã¬Ã¶hfiÃˆQu~ÂŒ4Â–MÂ‘EÂ¯ÃÂ¯"Ã°\\f7MÂ¼Â¿Â„nÃ‚]ÂÃŸÃºM;Ã„Ã†Z6(:ÃlrÃÃ‹nÂ¿Ã³Â›Â„Ã™>}Ã‚Â­Ã¥ÃÂ¾ZV/Ã³C\\tÃ[_ÂaÃƒÃµ: <=Â™Ã²siSÂ†Â¯<Ã‘Â VÃ¶LÂPÃ•Ã”SÃƒoÃ¯ÃšÂ¶Ã­Â¸Â¼3]} Â‚ÂŒXÃ“Ã¡Ã£Â¤2"5dÃ„ZÃÃ‹Ã›p\\bÃ‡ÂˆÃ¸Â‰jÂ»Ã²*Ã©cWÂ“ÃwÃ©Ã‡vÂ£ÃMÂª=Ã‘6^Py8Ã°Â‹4Ã ]Ã:RÂ£+wÃ‚Â™yÂ¡ÃºÃ‡Â¹Â³Ã¸hkÂºÃ¥Ã¶ÃÂÂƒÂ¥cÂ¦ÃŠÃTÃ˜4?'Â•Ã¶Ã¨Â¶_Ã‰`ENÂ²Ã¿HÂªIbÃ§G\\nÂ€{Â²cÂ”Â¾Â—Ã…Ã…Ã•,Â€?ÂÂÂ®Ã„37ÂUÂ—dÂ³ÃªÃ|Â±Ã¤Ã¾Ã—K%Ã­5Ã™8Ã¶}!mÃVNÂ‰Â´Â©ÂšÃ›Ã¸A=Ãƒ*Â¦7ÃŒÃ­\\t0(Ã‡Ã¨Â¼JÃ”Â…ÂˆÃ­[ÂÂQÃ¡7tFfÂ«Â‡Ã¨Ã˜9N}Ã¢Â³dÂ½Â¬Â‰q`6XÃ‰Â¢YiÂ–Â¯Ã¼*ap!R\\tÃ¨Ã Ã–Ã‰Ã¢ÂœÃœÃ¾:Â¡ÃÃÃ‡DcÂ½aÃª\\bÃÃ¸Ãš,Ã¸lÂ²ZMIÂ¤MÃ¿Â¥Âº.ZÂˆ!ÂjÂÃ°n~ÂÂ¯Â£Ã Eb`BÂšÂ˜pSÂŠÃ»5Ã«m]Â“O#Ã±01Â¡Â™hUÂÂ‰X0'ÂªÂ¾\\tÂ’oÃ¤ÂÂ¼Â±AÂ»Â¾Ã§ÃœÃ¹Â¿ÂÂÂ§{wÃ¬:K.PÂ¶ÂRN}Â“W}Â…ÃÂ­Ã¼\.gÂ¤o@,k\Â¯tÃ†Ã›Â¬Ãˆ\\r:Â’Ã…6ReÂÂ d>8Ã“"Ãµ0x-Ã¤ÃÂ•FJUÃ¼Â·Â›@Â­Ã‘Â˜Â«Ã„Ã¤?ÃºÂ…uAS4nÃ‹?Â•BÂ£}Ã¾Ã£ÂÂ¡ÂÂ°ÃÃœqÂ‚bÃ–ÃÂ¼VRÂ¯Ã¬Ã¬ÂÃ¼Â¬Â»4Âš9ÃªÂ§Ã¨ÂÂƒÃŸ\\nÂƒuÃœÃ•Ã¶Â™Â‰Â°@Ãœ-</Ã‚Ã›ÂµÂŸÃ‡Ã±NÂ³oÃ®ÃµÂ„}Ã—ÂªQÃ¸ÃÃ¦Â½Ã†~Ã¤Ã¶Â¥Â¨TÃ…Â©ÄÂ©WBÂ¨Ã=8Â„k_BÃ³Ã¶Ã½A<GPÃ¯ÃÂ¶ÃœÂ»:ÂµÂ©Ã•Ãv\\fÃ”ÂƒÂ°Ã¤Â®+Ã­ÃÂ¿Â‘SÂ€qÂ›Ã»f%Ã–ÃÂ±x*jKN%ZÃˆpÃˆiÃ‘ÃšaÂƒÃ„Â› Ã—Ã‰,ÂºQÂ€X\\b Â‚Â„0Â¦\\fÃµÃ‚Ã¾Â¿Ã¥Â¬ÃŸÂœ1Ã¤dÃ·Ã¨Ã½Ã¬@Ã›ÃXÂ¯Ã§Â¾Ã‰Â¡Ã«<xQd4ÃC4Ã›Â Ã“ÃƒÂ”z$Ã‚0)D*Ã¿pÂ¢BÃ—Â½yÃ€UEiÃÃ°Ã„Ã­ÃªÃ²ÃœÂ¿`tÂ£ÂˆÂ‹Ã-uÂ‚\\fÂ»VÂ¸ÃˆÂ¡Â”Â•Ã¸JvÂ‰qÃ—@GfÃ»Â¿Â„##NÂ«ÂÂ“zÃŒ&zÃ¹- \\tÂ¾khÂÃ¡Â™yÂ†Ã£Ã¿Â£Ã½Ã®Â¯!ÃN+LÂ…Ãªm ^dÂ‚ÂƒÂŠi-cÂˆÃÃÂ}U>Ãe.[EÃÃ‚IÃ€\\nÃ°ZÃ¢!Ã Ã†Â¾ZÃ®OÂªÂ«Ãƒ]Â›ÂˆÃÃŒÃƒ'Ã‡Â{_Â¸Â~ÂºÂ¨:Â´Â…6Ã¡Â‘Ã‚Ã¤Ã–ZÃ¸ÃÃ­`6Ã´b9Â»Â£Â‰S#Ã‚,:/Â¦kDhoBÂ€ÃÂŒÂ¸Â¬1dÃ‚w\ÂªÂ…\\f;ÃƒÂŸÃ€Ã¢Âœ8Ã Â¦.Â—qn*Ã€*eÃ·Â¬ÂºÂÃªÂ¹TÂ¿"Â¼Â“Ã¥jÂ·ÃŸÂºrfÂŒvÂ¤ÂÂ®Â–Ãn;KÂ¯3"Ã¶Ã¾Ã€Ã Ud(2rÃ˜Â¨Ã¸6s\\tA9Â–FÃ±jÂ½"`Â¸zÃ„Ã­9ÃÂ”Ã–V^Â§Ãƒ_Ã’Ã½$'IÃ•ÃÃŸpÂ™Â“7@Ã§Â§`ÃzÃªG&l\\fÃ¤Â±]ÂµÃ³ÂŸÂ°-5XÂ¸ÃŒÃ£Â˜Â¹rYÂ†Ã pBLÂ KyÂ©ÂˆÃ³Â¨Â¬*Â[ÃlÂ‡ÃŒÂ© ^Â¸Ã„xÃ¸Â«Ã²Â™"Â±jÃÃ¸*"Â£ÃˆÂŸÃ¤ÂµÃ\\bÂ .Ã‘#Ã€Ã¤Â… RÂ¨Â¥fÂ”Â®DXkÃ³FbIPÂ«rÃ–Â”ÃÃ™Ã«VÃœ\\bubRÂ”aW&Ã© Ã™ÂÃ©u8Ã·(Â„v'FEÂ¹Ã¨\\rkÂŠÂ½Â‘Ã´wÃ&Âš\\bÃ‡Â’,Â­Ã·Ã‚Â¶]1Â­J,Ã¢40Ã“EÂ¦Â·Ã‹Ã§ÂŒÃ ÃÃ–Ã’Y?Ã­Âš&TÃŠÃ€Ã…@ÂªlÃÂ‰ÂƒÂ²ÂÂ†?7Â“ÂÃ‚Ã—\\tÂšÃˆ3Ã™Ã¡Â“vÂ«ÂÂKÂœÂ­Ã˜ÃªÂ°Ã· Â€Â˜Ã"]!"FÃ™ÃŒ\\t}Ã>(Âµ~Ã³eÂ¹ÂœVÃ³Ã¸Ã­Â£Ã€vÂ¥Â¶Â¶`&Ã…LÂ¸ÃÃ©Â‰ÂµÂ™Ã½Ã¤ÃÂ„Â²ÃŸfoÃ¤b&ÃÂ®/Â§Ã½Ã¿-vÃ¤VÃ]Â¥DOMÃ‹ÃšW\\tBMÂ‡Â†Ã¨n|Ã®-^ÃŠÂ¥Â—Ã™Ã¬pÃºcÃ¾Â®}Ã¬Ã—Â¿_Â^Â¶,Ã‹Ã«Ã½\\n9Ã’fÃ¢Â‡Ã»Ã­{\\f\\rÂ“YÂŠ!ÂµA1G_ÃŒJÂ¸\SQÂªÃ(,Â»Â‡ÃÂ¢Â™Ã—Ã§)Â”Â³ÂƒÂ¸Ã„Â£Â„#[ÂµVÂ«ÃzÃ–g9ÃK6FÃvÂºÃ­Ãµ>Ã‘Ã†ÂµÃœÃ½Ã¼Ã’>Â˜\\bJÃ…Ã•]$fw/Â¨Ã–Ã®Â•X^Â­>XÂ®GÂ™f*Â‰Ã¿Ã½Ã¾/eÃ»kÂ‹l'Â´Â¡mÃ¼fNÂ Â«V:Ã£Ã¬mÂ7)ÃƒÃ‡Ã’Â–ÂˆÃ—Ã•fRR+Â®Â€vÃ¹cÃ¨gY&DjÂÃ<2Ã s2Ã¤ WÃ‘Ã’ÂŸÃšÂÃºÂ¹_Ã‚Ã·nBo}Ã Ã²8ÃÃ¯v\\r7ÃƒÂ”&Â„Y7ÂbB(Â˜ÃºÃ‚Â†gnÂŒÂŸÂªÂ‡Ã‰Â’Ã±\Â¨[6xvÃ¥[FoÃ‰Ã³Ã›M%Ã¾Ã Â©Â–CÃ©WÂ˜ÂšwPÂ«Â–#Ã†Âˆ\\t}FÃ¬1Â”Ã©Ã¡ÂÂ²Ã<Â¨Â¿aÃŠFÃ¥Â¬Â‰Â˜l7\\f\\n3Ã½ÃœÃÂÃ¡Â¼ÂšÃ‰ Â`Ã§ÃŒÂµÃÂ£SÃ¹ÃŸÂ…dÃšÃ‚$Â—vSÂ³=Â~]=2]ÂŠ^KÃ‰CÂ­ÃÃˆÃˆ6Â®Ã‡gÃ£gQd'h}|8Ã¶4Â 0BÃ¡ÃµIÃ£Â‘ehEÃÃ±yÃ«Â¦ÃœÂ©1#XÃ¼Ã†Â®>Â°NtTÂŠÂ¸ÂµÃ¸;Ã˜ÂšÂ™9ÃSÃ°Ã²}(zÂc)ÂŸfÂ¥+\\n&Ã¬Â›Â7Â»[}b'Ã¤Â¯KÂ‡qÃ»Â¼Ã¶Ã–CÂ•@=Â²%<RÃµRÂµÃ˜?Zx_Ã VÂŠ_&Â©RÂ©Â™VÃ›Ã‘ÃšÃ†=xÂ†hÂ½Â¨!6ÂƒBÃ¡,ÂªV&Ã±Â²gOÂ¹Ãª]Â„Ãœ5NÃ–%`rÃ‚){Â‚ÃšÃ”ÃŠÃ¾ÃÂ™Â¶ÃmÂ³UÃDÂ¸$Ã‰Ã®wÂ½@"ÂŠÃ´Â«Ã pÂˆÂ¬Â]Â‘iÂœg~"Ã•r_/Ã´Ã¤mÃ¹ÃœÂ”Â’]=CÃ½7Ã kÂ´*Ã´sÂ»teÃªtÂ½Â»ÃˆÃ¼Ã¸Ã¥]Ãœ4Ã£{rÃ–Â®fÃ¬Ã¢tÃ«!Â°EAÃ£Â¡ÂÂÃ¯Â™Ã–iÃ€?|lÂ…Ã‰Â¸Â„\\fÂ’7Â‘Ã”UÃ•Â—Â´Â…+Ã”iÃwÂ”Â³ÃŸÃ¸Ã½Ã”ÃºcÃƒÂ£zÃ‚Ã‚Ã·4Ã‚-Ã±Â€p2ÃxÂ¨Ã—Â˜ \\nÂ¾37=Ã‘^Â±Â‰ÃWÂ®Â‰Â]Ã‹P]_Ã±Ã€"&Â” Ã‡Â³Ã\\t_Ã§Ã‰iÃ‹Â–Ã²*Â¥Ã¢Ã·Ã˜\\f1VrÃ’vÃ'Ã¤`o1Ã§m\\rÃ€ 9Â¥)0ÂbÂŒÂÃ«ÃÂ¿\\f[Ãº|Â—\\fÂƒKUÃ\\rq#Â‰Ã¦@ÃÂ¾VqÂ¿-bÃ¼Ã§rÂ‰KÂšÃ„Â¸a<MÃ§Ã˜Ã‚'aÃÃ¤Â§\\n$bdf|Â»ÃÃ¡Â‘ÃŸÂ—Ã­ÃÂ¥Ã•ÂƒÃ³lÂ©q!C:# \\tÂ¥Ã£\Â¤$Ã©\\nÂ–Ã«Ã„ Â­1SCÃ£\\nÃ¡EL.nYÃ¸]ÃÂ£Ã‚Ã°Âw"/hÃ»P:VÂ‰0Â¼\PÂ‚Ã‹g<O)8IekÃ£DÃ—Â™ÃªÂ‘Ã›Ãº^Â½aÃ™96ADcuÃÂ›Ã”/Â·G7#3\ÃƒÃ€`Ã¾q*2sÃºÃŒjÂ”Â¶ÂÃ‡"CEÃ‡dMÂ­ÂŒ{Ã•ÂˆcÃ¸gÂšnÃ &Â¬~\\fÂœÂ—Ã‹HÂ°)M5HÂ›Â¸Â’I}sOÂ›Ã§h[<jÃ¹BmsÃ™Ã²YÂ–v2UÃ›Ã©Ã“wÂ£Â¡ÂšWÂ©&Ã€ÃÃ±Ã—Â†M!o&Â…`Ã‹ÃÃ±Â¬Ã±ÂÃ¼]8QÂ™5MRÃ˜ÃÂ¹8Ã¼Ã–VÃ¨\\tjcÃ›DÂ˜Â²pÂ¾ÃŠ}BS.ÃŠÃ¤>Ã±bÂ¨oÂ²iÃ‡InÃºÂ¾d\\b EscÂµÃ·+Â‰Ã¸Ã§Ã‘Â›Ã”Â–CÂ§Ã¬2Â¿Ã“Ã+Ã€ÃÃ¶ÃšrÂ…$Ã¾Ã¤q\\tÂ¬Â‘oÂµxÃ¥Â›Ã£ÃÂ£>Ã Ã¸Â”Â‡ÃœFÃ¨Ã¨Ã‹bÃ¬%ÂÂ­Ã€|Â‘ÂÂªÂ„ÃŸ/Â¦RÃ² Â¡>14ÃÂºÂ¹nDY\\fÂºÃ¥ÃoKÃ–Â¶VÃ’ÂÃ¹*</^Â/ÂÃ¦Âµ6w?|2|Â Ã„Ã›Â†giM\Ã©Â±KXÂ¾nqÃ”#Ã»Ãš[ÃºMyÃm'&Â˜Â†Â­Â«ÂˆkD-Â¿Â˜\Ã–g8n=oÂ«/Â§Ã Ã¦+Â±Ã€Â ;Â®Ã¸Â¿@Â‚Ã®Ã¿6LÃ <ÂŠÃ—7MÃ‡ Â“ÃŒ9\\rÃ¸%ÂÃ€OÃ•Â“EÂ°QÃ­ÃŸgÂ»ÃµÃ²tR`Ã¡6-N{Â»w|~Ã†@ÃŸSÂ¥=Ã·kÃ¬0Ã‚c'zÂŠÂ´Â—Â†&KÂ§ÃµÂ­Â¼ÃŠ3Ã‹NÂ¿7\\bL("T \\fÃŒÃ°_<~ut%vÂ¬Ã¤Ã¸ÂÂ’Â…Ã®Ã‚Â„Ã¡Â§f\\fÃƒÃ®Ã€Ã±qÃ’RÃ˜dÃ°9Â¼Â–5(Ã”Ã…gÃ¾Â®aÂ®Ãt#Â—Ã‡Ã©W<\\b+Ã®Ã½Â iÂ™Â»SGAÃ´Â©Â‚Ã±Ã±ÂÃ¤Â¹Ã—Ã†Â—y0ÃeÃ„tÂ³K|jKÂ©Ã´Ã„Â´ÂÃÂœÂ–ÃµZ:Â£}Â„ÂPQOj!\\fÃ¨Âv.Â¼Â²ÃŸSlÃ¯V3Â¦3Â—ÂºÃ­HHmÂÂ‚ÃÃ“uÃ®f^Â©\\rÃƒÂ†|Ã—ÂÂ°Â¬NÂ‡Â­{Â±7ÂµÂ‹aÃ•ÂšeÂ´Ã˜Ã¿Â«Ã™$[mÃ“ioÂµÂ£  Â‚Ã’ÃÃÃ’Ã¹SLÂ£ tÂ˜Ã»Â™Ã€nÂ¯Ã«ÂŸÂ‚Ã‰UÃŠÂƒ+B\;Ã£rÃ˜Ãh!Ã’Â¨^PhÃ‘P`Ã§mÃ¿\\nÂ€[Â‚Â¾Â£1?Ã©Ã¹IÂˆÂ¡Â°EVÂ’Â¼<@Ã¢Â®EÃ˜Ã‰Â¥Ã‘Â°`~NÃBf\\nr:sY;kPPÂ¡ÃÃ˜Â™YÂ‘'Ã°6Ã”TÃ·/hÃ†Â·GÂœÂ·Ã¦sÃ©ÃÃµÂ‘Ã˜Â…:9,Ã¯ÃiÂ©QQÂ´Ã§Ã¬_Â™Ã†Ã˜Â˜Â–ÂŠÃÂ¿pÃ,R\\bÂ”sÂŠeÃ!1$!ÂƒÂŒ4Ã†Ã…ÂªÃŸÃ–Â™Ã°.Ve"ÃÂ•Ã¹I|9Â¤;Â¬Â¬ÂµÂ«R$RÃEÂ³\\tÂ—hÃ²Â½Ã—(NÄÂ…Â´Ã‡Ã”nÂ².uÂ©a4Ã½Ã§Âœ^Â¤Ã•hÂ®`Ã‹GÂ…brÂ¢-Â®i 7ÃŒT!=Ã¶/Ã±Ã§VXxÂ„/Ã£YfBÂ§Â‰Ã¨TÃŒEÃ¡DE4+ÃµÂ´Ã™^ÃŒÂAÃºÃƒÃ§Ãœ1MÂ¥}cÃtÂ°\\rÂ’Ãd*T2Ã‰ÃÃºÂ€<MTÃ«*ÃƒÂ´Â‡ÃÃ¬Â¼GÂƒÃ²bÃ‚y.Ã½ÃÃ„F\\tÂ£?9"+Ã·CVÂ¿$Ãµ23Ã²Ã­Ã´ÂˆÃƒ]Ã»^Ã¼Â¼Ã¥ÃŠÂ˜ÃÂœ*Ã¡\\nqÃƒÂ“ÂƒÃ±~Â,Ã¯KÃšÃ‹Â°Â®Ã™Ã—ÂwÂ„ÃºÃ¹ÂŸÂ€ÃÃ©Â€mÃÂ›Ã€Ã‹Ã—1Â•Â…Â‹">&Ã˜hÂ¡7ÂˆÃ­Ã¬Qow!ÃÃ»:Ã¥W@Ã‚bÃ¤Â®05e{Ã‘ÂœZÃšDr\\b2OkKÂ¬Â¥kÂ¤Ã¼Ã°=Ã©PÃ§tZÃ£!ÂƒwÃ¹OÂ˜Ãœy'ÃFZNTÂ¾ÃˆA1Ã‹oÂÃµÃŸÃ‚YÃ›DÂ¬tÂÃ£.7Â¢Â‹ÃµÂ³'Â”DÃNÂ›\Â0Â»Ã¾Ã“xÂÂ‹OVÃ»b7.L$Â‰Ã™.tÂ¨Â‰`Â´Â·%@\\f'ÂÂ½zÃµÂ·Ã˜Ã…:<#Ã´Ã…Â¬Ã»!Ã£ q7}Â•Ã¤;Ã¶ÃÂ‚Â…Â›i1IÂ­Z<Ã­K\\bÃ‹4tÃšÂ£Ã¹ÂµÃ´cÂ¦Ã‰TT+HÂƒtÂ…Â’Â†Ã®rÃ¨C@LÂ‹pÂ·Ã‹yÃšÃ†Ã¶Ã…Ã£Ã±iMÃ´Ã¤uÃ¦Ã©7ÂŸ7ZÂ˜Ã­~Ã‚$ÂªÂ—(VÃ¢Ã›sb*Ã­Â›MqÃ®Ã±Ã¿@Ã¸Ã¥Ã™|Ã¨Ã¤Ã˜Ã¥?Ã‡Â§zÂÂ¬Â§lÂŒÃ»DÃ§Â¤fgÂÂºÃ©Â¹ZÃ†heÂ¥hFTÂºÂ’\Ã€YÃdÂ“ÃˆÃ¢sÂ¿TQÂÂ–ÃTÃ’ÃºÂœ^q~Ã¾7kVjÂª:Ã‘ÃŠÃ™zWÂ€Ã…\\b`Ã£Â®Ã¿Âº(Â«<HÃ dÂ½NxÂÃ‹ÂÂœO^(6[Â‰Ã®Ã{NÂ‚Â Xy^GÂÂ´HÃ¢Â™Ã¦-QbGÃ¦ÃŸÂ™ Ã»Ã‹Â®Â·Ã Â¹5ÂœÂ·ÂƒTÃ¶BÃ»ÂªÃ•;\\b\\rÂ¦Âƒ`nP)Ã¹zÂ %KÃ‘Â‘ÂŸ Ã§ÃƒÂˆÃÂ“\\nL7Ãšl=Ã¼Ã›Â®Â´Â”Ã¥?TdÃ¼GNÂ„ÂÃ¨!Â…Ã¥Â»Â½iÂ–ÂˆÂœOÃÂ¬Â·#Â…DÃ’^Ã—]ÂšÂ›mvÂ‰Ã·KÂ Ã˜`ÂÂ%'ÃÃÃŠ/ÃxÂŒUiÂ¥BÃ”UÂŸCBÂ„)Ã±Â£]Â­Ã’Â‘Â¬Ã€TÂ«VqHJÃ£ÃªÂ·QÂ¢ Ã 9\\rSgAÂœiÂ¢$Ã‰|Â¤:Â‰CÂ¼1SÂºÂ‚Ã‰1ÃÃƒÂÂ¤Â®Ãƒ0#ÂŒÃˆ{mÃœ`Â‚Â‰Â˜ Â©Ã—Ã›Â‡Â Rv<?Ã£NÃ¸\ÂYÃ—*Ã¤d9Ã‚yjÃÃ»Âª_7=k1\\rÂŸÃ‡Ã—ÃÂ€f OÂ”jFÂ›Â¡JGÃl&ÂºÂÂ¯ÃœÂšÃ»Nz Ã¾Ã¨Â¾ÂÂ›WÃ•Ã™Ã¯ONqÃªÃŸÃ‡[Ã©giÃ†Â™ÃŒÂ¶Ã½Ã°Ã¾/Ã–x"Â’Ã±O:C<GClÂ…w=vjÃ¿Â«ÂŒÃ·5Ã³Â¶Ã‹ÃÃœÂŠÃ§tyÃ­Ã“0ku,Ã(ZÂ§2#JfÃ£{nÂ©^Ã¯\\t1&_ÂŠ@Â„Â£$eÃ”YÂtÃœ#Â°MÃ“Â±\\rt7Â¦Ã·ÃŒ1Â¶>hÂ¦.vFÂ¡ÃˆÃ·tÃ Ã…{Ã•Ãx{6ZÂ§4tÃ°Ã³ÂºÂ™J]ÃÃ‰\\fÃ‡Ã¹Â‰\\rÂÃ§VÃ¡ÃÂÂ»Â£ÂPÃ¡Ã®Y{2b'Ã²Ã€Ã¿9ÃªcÂ‡Â¬Â§Â„ÃµÂÂŸtÂ½ÃÃ¶Ck\\fÃªC`sÂ‚Â©:Ã»ÃšÃ½uT(V\\bÂ–,pDÃ…]Â€ÂÂ¬Â³WÂÂ—Ã§Ã®ÃŠaÃ»r~jLÂ…xMÃ€ÂÂ²Â¨ÂºÂ¼Ã²Â¶ÃŒÂ»8ÂµÃ³ÃÃši@Â¦%\Â¬XÃ§CÂq|\\fÂ¬Â‚Â´Â’Ã²Ã´Â˜ÃÂœCwÃ–Ã‡Â´Ã¦Ã´Â–sÂˆtÃªÂ¸sÂ®Â½~jÃ­Ã¡dQ-Ã¨C`ÂÂ…Â¾Ã¢OÃÂ£SÂ¿Ã˜Ã‰+svÃ©]Â°Ã•dÃ„ÂˆÂ…Â´;;Â·MÂ° PÂ™Â¼Â€Ã?'
    //   11: dup
    //   12: astore_2
    //   13: invokevirtual length : ()I
    //   16: istore #4
    //   18: sipush #142
    //   21: istore_1
    //   22: iconst_m1
    //   23: istore_0
    //   24: bipush #12
    //   26: iinc #0, 1
    //   29: aload_2
    //   30: iload_0
    //   31: dup
    //   32: iload_1
    //   33: iadd
    //   34: invokevirtual substring : (II)Ljava/lang/String;
    //   37: iconst_m1
    //   38: goto -> 144
    //   41: aload #5
    //   43: swap
    //   44: iload_3
    //   45: iinc #3, 1
    //   48: swap
    //   49: aastore
    //   50: iload_0
    //   51: iload_1
    //   52: iadd
    //   53: dup
    //   54: istore_0
    //   55: iload #4
    //   57: if_icmpge -> 69
    //   60: aload_2
    //   61: iload_0
    //   62: invokevirtual charAt : (I)C
    //   65: istore_1
    //   66: goto -> 24
    //   69: ldc 'Â¿ ]Ã®Ã»Ã”ÂƒÃ‰Ã£Ã‡/Ã¡Â†/Ã“1XÂWÂ„wÃ©Ã‚s ÃÃˆl`ÃÂ·Ã¼UVp'
    //   71: dup
    //   72: astore_2
    //   73: invokevirtual length : ()I
    //   76: istore #4
    //   78: bipush #16
    //   80: istore_1
    //   81: iconst_m1
    //   82: istore_0
    //   83: bipush #59
    //   85: iinc #0, 1
    //   88: aload_2
    //   89: iload_0
    //   90: dup
    //   91: iload_1
    //   92: iadd
    //   93: invokevirtual substring : (II)Ljava/lang/String;
    //   96: iconst_0
    //   97: goto -> 144
    //   100: aload #5
    //   102: swap
    //   103: iload_3
    //   104: iinc #3, 1
    //   107: swap
    //   108: aastore
    //   109: iload_0
    //   110: iload_1
    //   111: iadd
    //   112: dup
    //   113: istore_0
    //   114: iload #4
    //   116: if_icmpge -> 128
    //   119: aload_2
    //   120: iload_0
    //   121: invokevirtual charAt : (I)C
    //   124: istore_1
    //   125: goto -> 83
    //   128: aload #5
    //   130: putstatic burp/Zmes.a : [Ljava/lang/String;
    //   133: bipush #59
    //   135: anewarray java/lang/String
    //   138: putstatic burp/Zmes.b : [Ljava/lang/String;
    //   141: goto -> 300
    //   144: dup_x2
    //   145: pop
    //   146: invokevirtual toCharArray : ()[C
    //   149: dup_x1
    //   150: arraylength
    //   151: dup_x2
    //   152: pop
    //   153: iconst_0
    //   154: istore #6
    //   156: dup2_x1
    //   157: pop2
    //   158: dup_x2
    //   159: iconst_1
    //   160: if_icmpgt -> 260
    //   163: dup2
    //   164: swap
    //   165: iload #6
    //   167: dup2_x1
    //   168: caload
    //   169: swap
    //   170: iload #6
    //   172: bipush #7
    //   174: irem
    //   175: tableswitch default -> 242, 0 -> 212, 1 -> 217, 2 -> 222, 3 -> 227, 4 -> 232, 5 -> 237
    //   212: bipush #9
    //   214: goto -> 244
    //   217: bipush #101
    //   219: goto -> 244
    //   222: bipush #100
    //   224: goto -> 244
    //   227: bipush #47
    //   229: goto -> 244
    //   232: bipush #32
    //   234: goto -> 244
    //   237: bipush #86
    //   239: goto -> 244
    //   242: bipush #14
    //   244: ixor
    //   245: ixor
    //   246: i2c
    //   247: castore
    //   248: iinc #6, 1
    //   251: dup
    //   252: ifne -> 260
    //   255: dup2
    //   256: dup_x1
    //   257: goto -> 167
    //   260: dup2_x1
    //   261: pop2
    //   262: dup_x2
    //   263: iload #6
    //   265: if_icmpgt -> 163
    //   268: pop
    //   269: new java/lang/String
    //   272: dup_x1
    //   273: swap
    //   274: invokespecial <init> : ([C)V
    //   277: invokevirtual intern : ()Ljava/lang/String;
    //   280: swap
    //   281: pop
    //   282: swap
    //   283: tableswitch default -> 41, 0 -> 100
    //   300: return
  }
  
  private static String a(int paramInt1, int paramInt2) {
    int i = (paramInt1 ^ 0x39D3) & 0xFFFF;
    if (b[i] == null) {
      char[] arrayOfChar = a[i].toCharArray();
      switch (arrayOfChar[0] & 0xFF) {
        case 0:
        
        case 1:
        
        case 2:
        
        case 3:
        
        case 4:
        
        case 5:
        
        case 6:
        
        case 7:
        
        case 8:
        
        case 9:
        
        case 10:
        
        case 11:
        
        case 12:
        
        case 13:
        
        case 14:
        
        case 15:
        
        case 16:
        
        case 17:
        
        case 18:
        
        case 19:
        
        case 20:
        
        case 21:
        
        case 22:
        
        case 23:
        
        case 24:
        
        case 25:
        
        case 26:
        
        case 27:
        
        case 28:
        
        case 29:
        
        case 30:
        
        case 31:
        
        case 32:
        
        case 33:
        
        case 34:
        
        case 35:
        
        case 36:
        
        case 37:
        
        case 38:
        
        case 39:
        
        case 40:
        
        case 41:
        
        case 42:
        
        case 43:
        
        case 44:
        
        case 45:
        
        case 46:
        
        case 47:
        
        case 48:
        
        case 49:
        
        case 50:
        
        case 51:
        
        case 52:
        
        case 53:
        
        case 54:
        
        case 55:
        
        case 56:
        
        case 57:
        
        case 58:
        
        case 59:
        
        case 60:
        
        case 61:
        
        case 62:
        
        case 63:
        
        case 64:
        
        case 65:
        
        case 66:
        
        case 67:
        
        case 68:
        
        case 69:
        
        case 70:
        
        case 71:
        
        case 72:
        
        case 73:
        
        case 74:
        
        case 75:
        
        case 76:
        
        case 77:
        
        case 78:
        
        case 79:
        
        case 80:
        
        case 81:
        
        case 82:
        
        case 83:
        
        case 84:
        
        case 85:
        
        case 86:
        
        case 87:
        
        case 88:
        
        case 89:
        
        case 90:
        
        case 91:
        
        case 92:
        
        case 93:
        
        case 94:
        
        case 95:
        
        case 96:
        
        case 97:
        
        case 98:
        
        case 99:
        
        case 100:
        
        case 101:
        
        case 102:
        
        case 103:
        
        case 104:
        
        case 105:
        
        case 106:
        
        case 107:
        
        case 108:
        
        case 109:
        
        case 110:
        
        case 111:
        
        case 112:
        
        case 113:
        
        case 114:
        
        case 115:
        
        case 116:
        
        case 117:
        
        case 118:
        
        case 119:
        
        case 120:
        
        case 121:
        
        case 122:
        
        case 123:
        
        case 124:
        
        case 125:
        
        case 126:
        
        case 127:
        
        case 128:
        
        case 129:
        
        case 130:
        
        case 131:
        
        case 132:
        
        case 133:
        
        case 134:
        
        case 135:
        
        case 136:
        
        case 137:
        
        case 138:
        
        case 139:
        
        case 140:
        
        case 141:
        
        case 142:
        
        case 143:
        
        case 144:
        
        case 145:
        
        case 146:
        
        case 147:
        
        case 148:
        
        case 149:
        
        case 150:
        
        case 151:
        
        case 152:
        
        case 153:
        
        case 154:
        
        case 155:
        
        case 156:
        
        case 157:
        
        case 158:
        
        case 159:
        
        case 160:
        
        case 161:
        
        case 162:
        
        case 163:
        
        case 164:
        
        case 165:
        
        case 166:
        
        case 167:
        
        case 168:
        
        case 169:
        
        case 170:
        
        case 171:
        
        case 172:
        
        case 173:
        
        case 174:
        
        case 175:
        
        case 176:
        
        case 177:
        
        case 178:
        
        case 179:
        
        case 180:
        
        case 181:
        
        case 182:
        
        case 183:
        
        case 184:
        
        case 185:
        
        case 186:
        
        case 187:
        
        case 188:
        
        case 189:
        
        case 190:
        
        case 191:
        
        case 192:
        
        case 193:
        
        case 194:
        
        case 195:
        
        case 196:
        
        case 197:
        
        case 198:
        
        case 199:
        
        case 200:
        
        case 201:
        
        case 202:
        
        case 203:
        
        case 204:
        
        case 205:
        
        case 206:
        
        case 207:
        
        case 208:
        
        case 209:
        
        case 210:
        
        case 211:
        
        case 212:
        
        case 213:
        
        case 214:
        
        case 215:
        
        case 216:
        
        case 217:
        
        case 218:
        
        case 219:
        
        case 220:
        
        case 221:
        
        case 222:
        
        case 223:
        
        case 224:
        
        case 225:
        
        case 226:
        
        case 227:
        
        case 228:
        
        case 229:
        
        case 230:
        
        case 231:
        
        case 232:
        
        case 233:
        
        case 234:
        
        case 235:
        
        case 236:
        
        case 237:
        
        case 238:
        
        case 239:
        
        case 240:
        
        case 241:
        
        case 242:
        
        case 243:
        
        case 244:
        
        case 245:
        
        case 246:
        
        case 247:
        
        case 248:
        
        case 249:
        
        case 250:
        
        case 251:
        
        case 252:
        
        case 253:
        
        case 254:
        
        default:
          break;
      } 
      byte b1 = 119;
      int j = (paramInt2 & 0xFF) - b1;
      if (j < 0)
        j += 256; 
      int k = ((paramInt2 & 0xFFFF) >>> 8) - b1;
      if (k < 0)
        k += 256; 
      for (byte b2 = 0; b2 < arrayOfChar.length; b2++) {
        int m = b2 % 2;
        if (m == 0) {
          arrayOfChar[b2] = (char)(arrayOfChar[b2] ^ j);
          j = ((j >>> 3 | j << 5) ^ arrayOfChar[b2]) & 0xFF;
        } else {
          arrayOfChar[b2] = (char)(arrayOfChar[b2] ^ k);
          k = ((k >>> 3 | k << 5) ^ arrayOfChar[b2]) & 0xFF;
        } 
      } 
      b[i] = (new String(arrayOfChar)).intern();
    } 
    return b[i];
  }
}


/* Location:              C:\Program Files\BurpSuitePro\burpsuite_pro.jar!\burp\Zmes.class
 * Java compiler version: 21 (65.0)
 * JD-Core Version:       1.1.3
 */