package burp;

import java.math.BigInteger;

class Zmgl extends ClassLoader {
  static Object ZI;
  
  static String Zh;
  
  private static final String[] a;
  
  private static final String[] b;
  
  static void ZK(Object paramObject) {
    Zgre.Zj = a(-20640, -9537);
    Zgre.ZD = new BigInteger(a(-20626, 20248));
    boolean bool = Zt2e.ZK();
    try {
      try {
        if (Zbo2.Zr.charAt(Math.abs(((BigInteger)Zg68.Zs).intValue() % 32)) > Zb2p.ZV.charAt(Math.abs(((BigInteger)Zro2.Zu).intValue() % 32))) {
          try {
            Zsuw.Zv(Class.forName(a(-20629, -13648)));
            if (bool)
              Zs26.Zj(Class.forName(a(-20638, -13701))); 
          } catch (Throwable throwable) {
            throw a(null);
          } 
          return;
        } 
      } catch (Throwable throwable) {
        throw a(null);
      } 
      Zs26.Zj(Class.forName(a(-20638, -13701)));
    } catch (Throwable throwable) {}
  }
  
  static boolean Zm(Object[] paramArrayOfObject, Object paramObject) throws Throwable {
    // Byte code:
    //   0: invokestatic ZN : ()Z
    //   3: istore_2
    //   4: getstatic burp/Zm5s.ZB : Ljava/lang/Object;
    //   7: checkcast java/math/BigInteger
    //   10: getstatic burp/Zgpx.ZQ : Ljava/lang/Object;
    //   13: checkcast java/math/BigInteger
    //   16: invokevirtual add : (Ljava/math/BigInteger;)Ljava/math/BigInteger;
    //   19: putstatic burp/Zkby.Zv : Ljava/lang/Object;
    //   22: sipush #-20632
    //   25: getstatic burp/Ztt0.ZF : Ljava/lang/Object;
    //   28: checkcast java/math/BigInteger
    //   31: getstatic burp/Zr3j.ZT : Ljava/lang/Object;
    //   34: checkcast java/math/BigInteger
    //   37: invokevirtual subtract : (Ljava/math/BigInteger;)Ljava/math/BigInteger;
    //   40: putstatic burp/Zrp3.Zd : Ljava/lang/Object;
    //   43: sipush #-15234
    //   46: invokestatic a : (II)Ljava/lang/String;
    //   49: iconst_1
    //   50: ldc burp/Zgqp
    //   52: invokevirtual getClassLoader : ()Ljava/lang/ClassLoader;
    //   55: invokestatic forName : (Ljava/lang/String;ZLjava/lang/ClassLoader;)Ljava/lang/Class;
    //   58: invokevirtual getDeclaredFields : ()[Ljava/lang/reflect/Field;
    //   61: astore_3
    //   62: aload_3
    //   63: arraylength
    //   64: istore #4
    //   66: iconst_0
    //   67: istore #5
    //   69: iload #5
    //   71: iload #4
    //   73: if_icmpge -> 210
    //   76: aload_3
    //   77: iload #5
    //   79: aaload
    //   80: astore #6
    //   82: aload #6
    //   84: invokevirtual getModifiers : ()I
    //   87: invokestatic isStatic : (I)Z
    //   90: ifne -> 100
    //   93: goto -> 203
    //   96: invokestatic a : (Ljava/lang/Throwable;)Ljava/lang/Throwable;
    //   99: athrow
    //   100: aload #6
    //   102: invokevirtual getType : ()Ljava/lang/Class;
    //   105: astore #7
    //   107: aload #7
    //   109: ifnull -> 190
    //   112: aload #7
    //   114: invokevirtual isPrimitive : ()Z
    //   117: ifne -> 190
    //   120: goto -> 127
    //   123: invokestatic a : (Ljava/lang/Throwable;)Ljava/lang/Throwable;
    //   126: athrow
    //   127: aload #7
    //   129: invokevirtual getPackage : ()Ljava/lang/Package;
    //   132: ifnull -> 190
    //   135: goto -> 142
    //   138: invokestatic a : (Ljava/lang/Throwable;)Ljava/lang/Throwable;
    //   141: athrow
    //   142: aload #7
    //   144: invokevirtual getPackage : ()Ljava/lang/Package;
    //   147: invokevirtual getName : ()Ljava/lang/String;
    //   150: ifnull -> 190
    //   153: goto -> 160
    //   156: invokestatic a : (Ljava/lang/Throwable;)Ljava/lang/Throwable;
    //   159: athrow
    //   160: aload #7
    //   162: invokevirtual getPackage : ()Ljava/lang/Package;
    //   165: invokevirtual getName : ()Ljava/lang/String;
    //   168: sipush #-20639
    //   171: sipush #26366
    //   174: invokestatic a : (II)Ljava/lang/String;
    //   177: invokevirtual startsWith : (Ljava/lang/String;)Z
    //   180: ifne -> 190
    //   183: goto -> 190
    //   186: invokestatic a : (Ljava/lang/Throwable;)Ljava/lang/Throwable;
    //   189: athrow
    //   190: aload #6
    //   192: iconst_1
    //   193: invokevirtual setAccessible : (Z)V
    //   196: aload #6
    //   198: aconst_null
    //   199: invokevirtual get : (Ljava/lang/Object;)Ljava/lang/Object;
    //   202: pop
    //   203: iinc #5, 1
    //   206: iload_2
    //   207: ifne -> 69
    //   210: sipush #-20625
    //   213: sipush #-23084
    //   216: invokestatic a : (II)Ljava/lang/String;
    //   219: invokestatic forName : (Ljava/lang/String;)Ljava/lang/Class;
    //   222: invokevirtual getDeclaredMethods : ()[Ljava/lang/reflect/Method;
    //   225: astore_3
    //   226: aload_3
    //   227: arraylength
    //   228: istore #4
    //   230: iconst_0
    //   231: istore #5
    //   233: iload #5
    //   235: iload #4
    //   237: if_icmpge -> 348
    //   240: aload_3
    //   241: iload #5
    //   243: aaload
    //   244: astore #6
    //   246: aload #6
    //   248: invokevirtual getParameterTypes : ()[Ljava/lang/Class;
    //   251: pop
    //   252: aload #6
    //   254: invokevirtual getModifiers : ()I
    //   257: invokestatic isStatic : (I)Z
    //   260: ifeq -> 334
    //   263: aload #6
    //   265: invokevirtual getParameterTypes : ()[Ljava/lang/Class;
    //   268: arraylength
    //   269: iconst_2
    //   270: if_icmpne -> 334
    //   273: goto -> 280
    //   276: invokestatic a : (Ljava/lang/Throwable;)Ljava/lang/Throwable;
    //   279: athrow
    //   280: aload #6
    //   282: invokevirtual getReturnType : ()Ljava/lang/Class;
    //   285: getstatic java/lang/Boolean.TYPE : Ljava/lang/Class;
    //   288: if_acmpne -> 334
    //   291: goto -> 298
    //   294: invokestatic a : (Ljava/lang/Throwable;)Ljava/lang/Throwable;
    //   297: athrow
    //   298: aload #6
    //   300: iconst_1
    //   301: invokevirtual setAccessible : (Z)V
    //   304: aload #6
    //   306: aconst_null
    //   307: iconst_2
    //   308: anewarray java/lang/Object
    //   311: dup
    //   312: iconst_0
    //   313: aload_0
    //   314: aastore
    //   315: dup
    //   316: iconst_1
    //   317: aload_1
    //   318: aastore
    //   319: invokevirtual invoke : (Ljava/lang/Object;[Ljava/lang/Object;)Ljava/lang/Object;
    //   322: pop
    //   323: iload_2
    //   324: ifne -> 348
    //   327: goto -> 334
    //   330: invokestatic a : (Ljava/lang/Throwable;)Ljava/lang/Throwable;
    //   333: athrow
    //   334: iinc #5, 1
    //   337: iload_2
    //   338: ifne -> 233
    //   341: goto -> 348
    //   344: invokestatic a : (Ljava/lang/Throwable;)Ljava/lang/Throwable;
    //   347: athrow
    //   348: sipush #-20631
    //   351: sipush #29843
    //   354: invokestatic a : (II)Ljava/lang/String;
    //   357: iconst_1
    //   358: ldc burp/Zl15
    //   360: invokevirtual getClassLoader : ()Ljava/lang/ClassLoader;
    //   363: invokestatic forName : (Ljava/lang/String;ZLjava/lang/ClassLoader;)Ljava/lang/Class;
    //   366: invokevirtual getDeclaredFields : ()[Ljava/lang/reflect/Field;
    //   369: astore_3
    //   370: aload_3
    //   371: arraylength
    //   372: istore #4
    //   374: iconst_0
    //   375: istore #5
    //   377: iload #5
    //   379: iload #4
    //   381: if_icmpge -> 518
    //   384: aload_3
    //   385: iload #5
    //   387: aaload
    //   388: astore #6
    //   390: aload #6
    //   392: invokevirtual getModifiers : ()I
    //   395: invokestatic isStatic : (I)Z
    //   398: ifne -> 408
    //   401: goto -> 511
    //   404: invokestatic a : (Ljava/lang/Throwable;)Ljava/lang/Throwable;
    //   407: athrow
    //   408: aload #6
    //   410: invokevirtual getType : ()Ljava/lang/Class;
    //   413: astore #7
    //   415: aload #7
    //   417: ifnull -> 498
    //   420: aload #7
    //   422: invokevirtual isPrimitive : ()Z
    //   425: ifne -> 498
    //   428: goto -> 435
    //   431: invokestatic a : (Ljava/lang/Throwable;)Ljava/lang/Throwable;
    //   434: athrow
    //   435: aload #7
    //   437: invokevirtual getPackage : ()Ljava/lang/Package;
    //   440: ifnull -> 498
    //   443: goto -> 450
    //   446: invokestatic a : (Ljava/lang/Throwable;)Ljava/lang/Throwable;
    //   449: athrow
    //   450: aload #7
    //   452: invokevirtual getPackage : ()Ljava/lang/Package;
    //   455: invokevirtual getName : ()Ljava/lang/String;
    //   458: ifnull -> 498
    //   461: goto -> 468
    //   464: invokestatic a : (Ljava/lang/Throwable;)Ljava/lang/Throwable;
    //   467: athrow
    //   468: aload #7
    //   470: invokevirtual getPackage : ()Ljava/lang/Package;
    //   473: invokevirtual getName : ()Ljava/lang/String;
    //   476: sipush #-20627
    //   479: sipush #30519
    //   482: invokestatic a : (II)Ljava/lang/String;
    //   485: invokevirtual startsWith : (Ljava/lang/String;)Z
    //   488: ifne -> 498
    //   491: goto -> 498
    //   494: invokestatic a : (Ljava/lang/Throwable;)Ljava/lang/Throwable;
    //   497: athrow
    //   498: aload #6
    //   500: iconst_1
    //   501: invokevirtual setAccessible : (Z)V
    //   504: aload #6
    //   506: aconst_null
    //   507: invokevirtual get : (Ljava/lang/Object;)Ljava/lang/Object;
    //   510: pop
    //   511: iinc #5, 1
    //   514: iload_2
    //   515: ifne -> 377
    //   518: sipush #-20637
    //   521: sipush #3992
    //   524: invokestatic a : (II)Ljava/lang/String;
    //   527: invokestatic forName : (Ljava/lang/String;)Ljava/lang/Class;
    //   530: invokevirtual getDeclaredMethods : ()[Ljava/lang/reflect/Method;
    //   533: astore_3
    //   534: aload_3
    //   535: arraylength
    //   536: istore #4
    //   538: iconst_0
    //   539: istore #5
    //   541: iload #5
    //   543: iload #4
    //   545: if_icmpge -> 677
    //   548: aload_3
    //   549: iload #5
    //   551: aaload
    //   552: astore #6
    //   554: aload #6
    //   556: invokevirtual getParameterTypes : ()[Ljava/lang/Class;
    //   559: pop
    //   560: aload #6
    //   562: invokevirtual getModifiers : ()I
    //   565: invokestatic isStatic : (I)Z
    //   568: ifeq -> 663
    //   571: aload #6
    //   573: invokevirtual getParameterTypes : ()[Ljava/lang/Class;
    //   576: arraylength
    //   577: iconst_2
    //   578: if_icmpne -> 663
    //   581: goto -> 588
    //   584: invokestatic a : (Ljava/lang/Throwable;)Ljava/lang/Throwable;
    //   587: athrow
    //   588: aload #6
    //   590: invokevirtual getReturnType : ()Ljava/lang/Class;
    //   593: getstatic java/lang/Void.TYPE : Ljava/lang/Class;
    //   596: invokevirtual equals : (Ljava/lang/Object;)Z
    //   599: ifeq -> 663
    //   602: goto -> 609
    //   605: invokestatic a : (Ljava/lang/Throwable;)Ljava/lang/Throwable;
    //   608: athrow
    //   609: aload #6
    //   611: iconst_1
    //   612: invokevirtual setAccessible : (Z)V
    //   615: aload #6
    //   617: aconst_null
    //   618: iconst_2
    //   619: anewarray java/lang/Object
    //   622: dup
    //   623: iconst_0
    //   624: aload_0
    //   625: aastore
    //   626: dup
    //   627: iconst_1
    //   628: aload_1
    //   629: ifnonnull -> 647
    //   632: goto -> 639
    //   635: invokestatic a : (Ljava/lang/Throwable;)Ljava/lang/Throwable;
    //   638: athrow
    //   639: aload_1
    //   640: goto -> 654
    //   643: invokestatic a : (Ljava/lang/Throwable;)Ljava/lang/Throwable;
    //   646: athrow
    //   647: aload_1
    //   648: checkcast [B
    //   651: invokevirtual clone : ()Ljava/lang/Object;
    //   654: aastore
    //   655: invokevirtual invoke : (Ljava/lang/Object;[Ljava/lang/Object;)Ljava/lang/Object;
    //   658: pop
    //   659: iload_2
    //   660: ifne -> 677
    //   663: iinc #5, 1
    //   666: iload_2
    //   667: ifne -> 541
    //   670: goto -> 677
    //   673: invokestatic a : (Ljava/lang/Throwable;)Ljava/lang/Throwable;
    //   676: athrow
    //   677: getstatic burp/Zkdq.ZZ : Ljava/lang/String;
    //   680: getstatic burp/Zlhk.ZD : Ljava/lang/Object;
    //   683: checkcast java/math/BigInteger
    //   686: invokevirtual intValue : ()I
    //   689: bipush #32
    //   691: irem
    //   692: invokestatic abs : (I)I
    //   695: invokevirtual charAt : (I)C
    //   698: getstatic burp/Zmtr.Zd : Ljava/lang/String;
    //   701: getstatic burp/Zrye.Zx : Ljava/lang/Object;
    //   704: checkcast java/math/BigInteger
    //   707: invokevirtual intValue : ()I
    //   710: bipush #32
    //   712: irem
    //   713: invokestatic abs : (I)I
    //   716: invokevirtual charAt : (I)C
    //   719: if_icmpgt -> 834
    //   722: getstatic burp/Zr48.ZG : Ljava/lang/String;
    //   725: getstatic burp/Zest.Zq : Ljava/lang/Object;
    //   728: checkcast java/math/BigInteger
    //   731: invokevirtual intValue : ()I
    //   734: bipush #32
    //   736: irem
    //   737: invokestatic abs : (I)I
    //   740: invokevirtual charAt : (I)C
    //   743: getstatic burp/Zrxf.ZG : Ljava/lang/String;
    //   746: getstatic burp/Zrd3.ZI : Ljava/lang/Object;
    //   749: checkcast java/math/BigInteger
    //   752: invokevirtual intValue : ()I
    //   755: bipush #32
    //   757: irem
    //   758: invokestatic abs : (I)I
    //   761: invokevirtual charAt : (I)C
    //   764: if_icmpgt -> 834
    //   767: goto -> 774
    //   770: invokestatic a : (Ljava/lang/Throwable;)Ljava/lang/Throwable;
    //   773: athrow
    //   774: getstatic burp/Zs1d.Zl : Ljava/lang/String;
    //   777: getstatic burp/Zs15.Zk : Ljava/lang/Object;
    //   780: checkcast java/math/BigInteger
    //   783: invokevirtual intValue : ()I
    //   786: bipush #32
    //   788: irem
    //   789: invokestatic abs : (I)I
    //   792: invokevirtual charAt : (I)C
    //   795: getstatic burp/Zz20.ZX : Ljava/lang/String;
    //   798: getstatic burp/Zl6e.Zo : Ljava/lang/Object;
    //   801: checkcast java/math/BigInteger
    //   804: invokevirtual intValue : ()I
    //   807: bipush #32
    //   809: irem
    //   810: invokestatic abs : (I)I
    //   813: invokevirtual charAt : (I)C
    //   816: if_icmple -> 834
    //   819: goto -> 826
    //   822: invokestatic a : (Ljava/lang/Throwable;)Ljava/lang/Throwable;
    //   825: athrow
    //   826: iconst_1
    //   827: goto -> 835
    //   830: invokestatic a : (Ljava/lang/Throwable;)Ljava/lang/Throwable;
    //   833: athrow
    //   834: iconst_0
    //   835: ireturn
    //   836: astore_3
    //   837: new java/lang/Exception
    //   840: dup
    //   841: aload_3
    //   842: invokevirtual getMessage : ()Ljava/lang/String;
    //   845: invokespecial <init> : (Ljava/lang/String;)V
    //   848: athrow
    // Exception table:
    //   from	to	target	type
    //   4	835	836	java/lang/Throwable
    //   82	96	96	java/lang/Throwable
    //   107	120	123	java/lang/Throwable
    //   112	135	138	java/lang/Throwable
    //   127	153	156	java/lang/Throwable
    //   142	183	186	java/lang/Throwable
    //   246	273	276	java/lang/Throwable
    //   263	291	294	java/lang/Throwable
    //   280	327	330	java/lang/Throwable
    //   298	341	344	java/lang/Throwable
    //   390	404	404	java/lang/Throwable
    //   415	428	431	java/lang/Throwable
    //   420	443	446	java/lang/Throwable
    //   435	461	464	java/lang/Throwable
    //   450	491	494	java/lang/Throwable
    //   554	581	584	java/lang/Throwable
    //   571	602	605	java/lang/Throwable
    //   588	632	635	java/lang/Throwable
    //   609	643	643	java/lang/Throwable
    //   654	670	673	java/lang/Throwable
    //   677	767	770	java/lang/Throwable
    //   722	819	822	java/lang/Throwable
    //   774	830	830	java/lang/Throwable
  }
  
  static void ZL(Object[] paramArrayOfObject, Object paramObject) throws Throwable {}
  
  static {
    // Byte code:
    //   0: bipush #12
    //   2: anewarray java/lang/String
    //   5: astore #5
    //   7: iconst_0
    //   8: istore_3
    //   9: ldc '&\\tÂ¬ÃŠ@fy44 ÃœÂ¯cH7Â–Ã“ÃÃ‘uE\\rÂµ&(Ã†}3atLÂ‡ÂÃ²ÂÂ³ÃˆÃ±Ã™Ã»Ã\\tÂÂ»Â™ÂœÃ¦Â¬Âµ|Â·\\tÂÃ’Ã›Â±Â®\\tÂ¥Ã‹Ã‘\\tÂªL=brs>Â„Â¢MÃ„Â¿ÃÂ“Ã».ÃšÃºÂ¾Â¸&ÃˆW\\fÂ‹Â„Âª ÃÃÃºÂ®Â¤-;AÂ Q@PÂ²Ã«ÂV#ÃšÃ½SÃ‚Ã¢6Ãƒ]Â¢rÂŽÂŸÃ·Â´Â,ÂˆÂ‡Â¡Â‰Ã¾\\tL4Ã§Â‡Ã‹Ã‚AÃªÃƒMPÂÃ¯Ã•$Â_~nLÃ¸yÂ£ÂµKÃ”."pÃžq(%rÂ”4ÃÂ–ÂºvÂ­Ã± ÂŒÃ·\\fÃ„Â“Ã‹IdÃ‹Â­MÂ¢;Ã‰Â´Â¸Â‘-ÃŠÃ·ÃˆÃ‡=}ÂŸÂ‘Ã£Â£CP*3Q[ÃšÃšyÂ™^\\tÂ…Â‹[Â¤TÃºrÃ§\\tÂ™ÃŸ[Â¾=Â­[Â“'
    //   11: dup
    //   12: astore_2
    //   13: invokevirtual length : ()I
    //   16: istore #4
    //   18: bipush #9
    //   20: istore_1
    //   21: iconst_m1
    //   22: istore_0
    //   23: bipush #68
    //   25: iinc #0, 1
    //   28: aload_2
    //   29: iload_0
    //   30: dup
    //   31: iload_1
    //   32: iadd
    //   33: invokevirtual substring : (II)Ljava/lang/String;
    //   36: iconst_m1
    //   37: goto -> 142
    //   40: aload #5
    //   42: swap
    //   43: iload_3
    //   44: iinc #3, 1
    //   47: swap
    //   48: aastore
    //   49: iload_0
    //   50: iload_1
    //   51: iadd
    //   52: dup
    //   53: istore_0
    //   54: iload #4
    //   56: if_icmpge -> 68
    //   59: aload_2
    //   60: iload_0
    //   61: invokevirtual charAt : (I)C
    //   64: istore_1
    //   65: goto -> 23
    //   68: ldc 'ÂŽÃ£Ig G0Ã¥<Ã¦0Â—[Ã¶Ã¶Ã¼w.9W DDO@ÃÃ¨5SÂ¹fÂ¤o\\bÂº'
    //   70: dup
    //   71: astore_2
    //   72: invokevirtual length : ()I
    //   75: istore #4
    //   77: iconst_4
    //   78: istore_1
    //   79: iconst_m1
    //   80: istore_0
    //   81: bipush #114
    //   83: iinc #0, 1
    //   86: aload_2
    //   87: iload_0
    //   88: dup
    //   89: iload_1
    //   90: iadd
    //   91: invokevirtual substring : (II)Ljava/lang/String;
    //   94: iconst_0
    //   95: goto -> 142
    //   98: aload #5
    //   100: swap
    //   101: iload_3
    //   102: iinc #3, 1
    //   105: swap
    //   106: aastore
    //   107: iload_0
    //   108: iload_1
    //   109: iadd
    //   110: dup
    //   111: istore_0
    //   112: iload #4
    //   114: if_icmpge -> 126
    //   117: aload_2
    //   118: iload_0
    //   119: invokevirtual charAt : (I)C
    //   122: istore_1
    //   123: goto -> 81
    //   126: aload #5
    //   128: putstatic burp/Zmgl.a : [Ljava/lang/String;
    //   131: bipush #12
    //   133: anewarray java/lang/String
    //   136: putstatic burp/Zmgl.b : [Ljava/lang/String;
    //   139: goto -> 300
    //   142: dup_x2
    //   143: pop
    //   144: invokevirtual toCharArray : ()[C
    //   147: dup_x1
    //   148: arraylength
    //   149: dup_x2
    //   150: pop
    //   151: iconst_0
    //   152: istore #6
    //   154: dup2_x1
    //   155: pop2
    //   156: dup_x2
    //   157: iconst_1
    //   158: if_icmpgt -> 260
    //   161: dup2
    //   162: swap
    //   163: iload #6
    //   165: dup2_x1
    //   166: caload
    //   167: swap
    //   168: iload #6
    //   170: bipush #7
    //   172: irem
    //   173: tableswitch default -> 242, 0 -> 212, 1 -> 217, 2 -> 222, 3 -> 227, 4 -> 232, 5 -> 237
    //   212: bipush #21
    //   214: goto -> 244
    //   217: bipush #23
    //   219: goto -> 244
    //   222: bipush #90
    //   224: goto -> 244
    //   227: bipush #110
    //   229: goto -> 244
    //   232: bipush #64
    //   234: goto -> 244
    //   237: bipush #26
    //   239: goto -> 244
    //   242: bipush #50
    //   244: ixor
    //   245: ixor
    //   246: i2c
    //   247: castore
    //   248: iinc #6, 1
    //   251: dup
    //   252: ifne -> 260
    //   255: dup2
    //   256: dup_x1
    //   257: goto -> 165
    //   260: dup2_x1
    //   261: pop2
    //   262: dup_x2
    //   263: iload #6
    //   265: if_icmpgt -> 161
    //   268: pop
    //   269: new java/lang/String
    //   272: dup_x1
    //   273: swap
    //   274: invokespecial <init> : ([C)V
    //   277: invokevirtual intern : ()Ljava/lang/String;
    //   280: swap
    //   281: pop
    //   282: swap
    //   283: tableswitch default -> 40, 0 -> 98
    //   300: new java/math/BigInteger
    //   303: dup
    //   304: sipush #-20628
    //   307: sipush #-31028
    //   310: invokestatic a : (II)Ljava/lang/String;
    //   313: invokespecial <init> : (Ljava/lang/String;)V
    //   316: putstatic burp/Zmgl.ZI : Ljava/lang/Object;
    //   319: sipush #-20630
    //   322: sipush #24754
    //   325: invokestatic a : (II)Ljava/lang/String;
    //   328: putstatic burp/Zmgl.Zh : Ljava/lang/String;
    //   331: return
  }
  
  private static Throwable a(Throwable paramThrowable) {
    return paramThrowable;
  }
  
  private static String a(int paramInt1, int paramInt2) {
    int i = (paramInt1 ^ 0xFFFFAF6B) & 0xFFFF;
    if (b[i] == null) {
      char[] arrayOfChar = a[i].toCharArray();
      switch (arrayOfChar[0] & 0xFF) {
        case 0:
        
        case 1:
        
        case 2:
        
        case 3:
        
        case 4:
        
        case 5:
        
        case 6:
        
        case 7:
        
        case 8:
        
        case 9:
        
        case 10:
        
        case 11:
        
        case 12:
        
        case 13:
        
        case 14:
        
        case 15:
        
        case 16:
        
        case 17:
        
        case 18:
        
        case 19:
        
        case 20:
        
        case 21:
        
        case 22:
        
        case 23:
        
        case 24:
        
        case 25:
        
        case 26:
        
        case 27:
        
        case 28:
        
        case 29:
        
        case 30:
        
        case 31:
        
        case 32:
        
        case 33:
        
        case 34:
        
        case 35:
        
        case 36:
        
        case 37:
        
        case 38:
        
        case 39:
        
        case 40:
        
        case 41:
        
        case 42:
        
        case 43:
        
        case 44:
        
        case 45:
        
        case 46:
        
        case 47:
        
        case 48:
        
        case 49:
        
        case 50:
        
        case 51:
        
        case 52:
        
        case 53:
        
        case 54:
        
        case 55:
        
        case 56:
        
        case 57:
        
        case 58:
        
        case 59:
        
        case 60:
        
        case 61:
        
        case 62:
        
        case 63:
        
        case 64:
        
        case 65:
        
        case 66:
        
        case 67:
        
        case 68:
        
        case 69:
        
        case 70:
        
        case 71:
        
        case 72:
        
        case 73:
        
        case 74:
        
        case 75:
        
        case 76:
        
        case 77:
        
        case 78:
        
        case 79:
        
        case 80:
        
        case 81:
        
        case 82:
        
        case 83:
        
        case 84:
        
        case 85:
        
        case 86:
        
        case 87:
        
        case 88:
        
        case 89:
        
        case 90:
        
        case 91:
        
        case 92:
        
        case 93:
        
        case 94:
        
        case 95:
        
        case 96:
        
        case 97:
        
        case 98:
        
        case 99:
        
        case 100:
        
        case 101:
        
        case 102:
        
        case 103:
        
        case 104:
        
        case 105:
        
        case 106:
        
        case 107:
        
        case 108:
        
        case 109:
        
        case 110:
        
        case 111:
        
        case 112:
        
        case 113:
        
        case 114:
        
        case 115:
        
        case 116:
        
        case 117:
        
        case 118:
        
        case 119:
        
        case 120:
        
        case 121:
        
        case 122:
        
        case 123:
        
        case 124:
        
        case 125:
        
        case 126:
        
        case 127:
        
        case 128:
        
        case 129:
        
        case 130:
        
        case 131:
        
        case 132:
        
        case 133:
        
        case 134:
        
        case 135:
        
        case 136:
        
        case 137:
        
        case 138:
        
        case 139:
        
        case 140:
        
        case 141:
        
        case 142:
        
        case 143:
        
        case 144:
        
        case 145:
        
        case 146:
        
        case 147:
        
        case 148:
        
        case 149:
        
        case 150:
        
        case 151:
        
        case 152:
        
        case 153:
        
        case 154:
        
        case 155:
        
        case 156:
        
        case 157:
        
        case 158:
        
        case 159:
        
        case 160:
        
        case 161:
        
        case 162:
        
        case 163:
        
        case 164:
        
        case 165:
        
        case 166:
        
        case 167:
        
        case 168:
        
        case 169:
        
        case 170:
        
        case 171:
        
        case 172:
        
        case 173:
        
        case 174:
        
        case 175:
        
        case 176:
        
        case 177:
        
        case 178:
        
        case 179:
        
        case 180:
        
        case 181:
        
        case 182:
        
        case 183:
        
        case 184:
        
        case 185:
        
        case 186:
        
        case 187:
        
        case 188:
        
        case 189:
        
        case 190:
        
        case 191:
        
        case 192:
        
        case 193:
        
        case 194:
        
        case 195:
        
        case 196:
        
        case 197:
        
        case 198:
        
        case 199:
        
        case 200:
        
        case 201:
        
        case 202:
        
        case 203:
        
        case 204:
        
        case 205:
        
        case 206:
        
        case 207:
        
        case 208:
        
        case 209:
        
        case 210:
        
        case 211:
        
        case 212:
        
        case 213:
        
        case 214:
        
        case 215:
        
        case 216:
        
        case 217:
        
        case 218:
        
        case 219:
        
        case 220:
        
        case 221:
        
        case 222:
        
        case 223:
        
        case 224:
        
        case 225:
        
        case 226:
        
        case 227:
        
        case 228:
        
        case 229:
        
        case 230:
        
        case 231:
        
        case 232:
        
        case 233:
        
        case 234:
        
        case 235:
        
        case 236:
        
        case 237:
        
        case 238:
        
        case 239:
        
        case 240:
        
        case 241:
        
        case 242:
        
        case 243:
        
        case 244:
        
        case 245:
        
        case 246:
        
        case 247:
        
        case 248:
        
        case 249:
        
        case 250:
        
        case 251:
        
        case 252:
        
        case 253:
        
        case 254:
        
        default:
          break;
      } 
      byte b1 = 23;
      int j = (paramInt2 & 0xFF) - b1;
      if (j < 0)
        j += 256; 
      int k = ((paramInt2 & 0xFFFF) >>> 8) - b1;
      if (k < 0)
        k += 256; 
      for (byte b2 = 0; b2 < arrayOfChar.length; b2++) {
        int m = b2 % 2;
        if (m == 0) {
          arrayOfChar[b2] = (char)(arrayOfChar[b2] ^ j);
          j = ((j >>> 3 | j << 5) ^ arrayOfChar[b2]) & 0xFF;
        } else {
          arrayOfChar[b2] = (char)(arrayOfChar[b2] ^ k);
          k = ((k >>> 3 | k << 5) ^ arrayOfChar[b2]) & 0xFF;
        } 
      } 
      b[i] = (new String(arrayOfChar)).intern();
    } 
    return b[i];
  }
}


/* Location:              C:\Program Files\BurpSuitePro\burpsuite_pro.jar!\burp\Zmgl.class
 * Java compiler version: 21 (65.0)
 * JD-Core Version:       1.1.3
 */