package burp;

import java.math.BigInteger;

class Zmh5 extends ClassLoader {
  static String Zh;
  
  static Object ZN;
  
  private static final String[] a;
  
  private static final String[] b;
  
  static void ZG(Object[] paramArrayOfObject, Object paramObject) throws Throwable {}
  
  static void ZE(Object paramObject) {
    Ze0w.ZT = a(29828, -14632);
    Ze0w.ZU = new BigInteger(a(29829, -10326));
    boolean bool = Zt2e.ZN();
    try {
      try {
        if (Zth7.Zf.charAt(Math.abs(((BigInteger)Zezn.Zh).intValue() % 32)) > Zdm.ZJ.charAt(Math.abs(((BigInteger)Zrd0.Zs).intValue() % 32))) {
          try {
            Zgkp.Zw(Class.forName(a(29847, 18761)));
            if (!bool)
              Zkm0.ZQ(Class.forName(a(29854, 19880))); 
          } catch (Throwable throwable) {
            throw a(null);
          } 
          return;
        } 
      } catch (Throwable throwable) {
        throw a(null);
      } 
      Zkm0.ZQ(Class.forName(a(29854, 19880)));
    } catch (Throwable throwable) {}
  }
  
  static boolean Zh(Object[] paramArrayOfObject, Object paramObject) throws Throwable {
    // Byte code:
    //   0: invokestatic ZN : ()Z
    //   3: istore_2
    //   4: getstatic burp/Zlxm.Zc : Ljava/lang/Object;
    //   7: checkcast java/math/BigInteger
    //   10: invokevirtual toByteArray : ()[B
    //   13: astore_3
    //   14: bipush #32
    //   16: newarray int
    //   18: dup
    //   19: iconst_0
    //   20: ldc 943331329
    //   22: iastore
    //   23: dup
    //   24: iconst_1
    //   25: ldc 170788368
    //   27: iastore
    //   28: dup
    //   29: iconst_2
    //   30: ldc 1008414755
    //   32: iastore
    //   33: dup
    //   34: iconst_3
    //   35: ldc 187049985
    //   37: iastore
    //   38: dup
    //   39: iconst_4
    //   40: ldc 1010368540
    //   42: iastore
    //   43: dup
    //   44: iconst_5
    //   45: ldc 220604441
    //   47: iastore
    //   48: dup
    //   49: bipush #6
    //   51: ldc 940377620
    //   53: iastore
    //   54: dup
    //   55: bipush #7
    //   57: ldc 255209728
    //   59: iastore
    //   60: dup
    //   61: bipush #8
    //   63: ldc 689771012
    //   65: iastore
    //   66: dup
    //   67: bipush #9
    //   69: ldc 221709344
    //   71: iastore
    //   72: dup
    //   73: bipush #10
    //   75: ldc 957157408
    //   77: iastore
    //   78: dup
    //   79: bipush #11
    //   81: ldc 892536332
    //   83: iastore
    //   84: dup
    //   85: bipush #12
    //   87: ldc 722417666
    //   89: iastore
    //   90: dup
    //   91: bipush #13
    //   93: ldc 1026621720
    //   95: iastore
    //   96: dup
    //   97: bipush #14
    //   99: ldc 655302664
    //   101: iastore
    //   102: dup
    //   103: bipush #15
    //   105: ldc 890966315
    //   107: iastore
    //   108: dup
    //   109: bipush #16
    //   111: ldc 187632156
    //   113: iastore
    //   114: dup
    //   115: bipush #17
    //   117: ldc 874189824
    //   119: iastore
    //   120: dup
    //   121: bipush #18
    //   123: ldc 254150144
    //   125: iastore
    //   126: dup
    //   127: bipush #19
    //   129: ldc 924386310
    //   131: iastore
    //   132: dup
    //   133: bipush #20
    //   135: ldc 121057538
    //   137: iastore
    //   138: dup
    //   139: bipush #21
    //   141: ldc 840500228
    //   143: iastore
    //   144: dup
    //   145: bipush #22
    //   147: ldc 389160971
    //   149: iastore
    //   150: dup
    //   151: bipush #23
    //   153: ldc 907870729
    //   155: iastore
    //   156: dup
    //   157: bipush #24
    //   159: ldc 389426184
    //   161: iastore
    //   162: dup
    //   163: bipush #25
    //   165: ldc 973875457
    //   167: iastore
    //   168: dup
    //   169: bipush #26
    //   171: ldc 372376604
    //   173: iastore
    //   174: dup
    //   175: bipush #27
    //   177: ldc 707731490
    //   179: iastore
    //   180: dup
    //   181: bipush #28
    //   183: ldc 1043334948
    //   185: iastore
    //   186: dup
    //   187: bipush #29
    //   189: ldc 439222784
    //   191: iastore
    //   192: dup
    //   193: bipush #30
    //   195: ldc 876216579
    //   197: iastore
    //   198: dup
    //   199: bipush #31
    //   201: ldc 455999525
    //   203: iastore
    //   204: astore #5
    //   206: bipush #8
    //   208: aload_3
    //   209: arraylength
    //   210: bipush #8
    //   212: irem
    //   213: isub
    //   214: istore #6
    //   216: aload_3
    //   217: arraylength
    //   218: iload #6
    //   220: iadd
    //   221: newarray byte
    //   223: astore #7
    //   225: iconst_0
    //   226: istore #8
    //   228: iload #8
    //   230: aload_3
    //   231: arraylength
    //   232: if_icmpge -> 251
    //   235: aload #7
    //   237: iload #8
    //   239: aload_3
    //   240: iload #8
    //   242: baload
    //   243: bastore
    //   244: iinc #8, 1
    //   247: iload_2
    //   248: ifne -> 228
    //   251: aload_3
    //   252: arraylength
    //   253: istore #8
    //   255: iload #8
    //   257: aload #7
    //   259: arraylength
    //   260: if_icmpge -> 278
    //   263: aload #7
    //   265: iload #8
    //   267: iload #6
    //   269: i2b
    //   270: bastore
    //   271: iinc #8, 1
    //   274: iload_2
    //   275: ifne -> 255
    //   278: aload #7
    //   280: astore_3
    //   281: bipush #64
    //   283: newarray int
    //   285: dup
    //   286: iconst_0
    //   287: ldc 16843776
    //   289: iastore
    //   290: dup
    //   291: iconst_1
    //   292: iconst_0
    //   293: iastore
    //   294: dup
    //   295: iconst_2
    //   296: ldc 65536
    //   298: iastore
    //   299: dup
    //   300: iconst_3
    //   301: ldc 16843780
    //   303: iastore
    //   304: dup
    //   305: iconst_4
    //   306: ldc 16842756
    //   308: iastore
    //   309: dup
    //   310: iconst_5
    //   311: ldc 66564
    //   313: iastore
    //   314: dup
    //   315: bipush #6
    //   317: iconst_4
    //   318: iastore
    //   319: dup
    //   320: bipush #7
    //   322: ldc 65536
    //   324: iastore
    //   325: dup
    //   326: bipush #8
    //   328: sipush #1024
    //   331: iastore
    //   332: dup
    //   333: bipush #9
    //   335: ldc 16843776
    //   337: iastore
    //   338: dup
    //   339: bipush #10
    //   341: ldc 16843780
    //   343: iastore
    //   344: dup
    //   345: bipush #11
    //   347: sipush #1024
    //   350: iastore
    //   351: dup
    //   352: bipush #12
    //   354: ldc 16778244
    //   356: iastore
    //   357: dup
    //   358: bipush #13
    //   360: ldc 16842756
    //   362: iastore
    //   363: dup
    //   364: bipush #14
    //   366: ldc 16777216
    //   368: iastore
    //   369: dup
    //   370: bipush #15
    //   372: iconst_4
    //   373: iastore
    //   374: dup
    //   375: bipush #16
    //   377: sipush #1028
    //   380: iastore
    //   381: dup
    //   382: bipush #17
    //   384: ldc 16778240
    //   386: iastore
    //   387: dup
    //   388: bipush #18
    //   390: ldc 16778240
    //   392: iastore
    //   393: dup
    //   394: bipush #19
    //   396: ldc 66560
    //   398: iastore
    //   399: dup
    //   400: bipush #20
    //   402: ldc 66560
    //   404: iastore
    //   405: dup
    //   406: bipush #21
    //   408: ldc 16842752
    //   410: iastore
    //   411: dup
    //   412: bipush #22
    //   414: ldc 16842752
    //   416: iastore
    //   417: dup
    //   418: bipush #23
    //   420: ldc 16778244
    //   422: iastore
    //   423: dup
    //   424: bipush #24
    //   426: ldc 65540
    //   428: iastore
    //   429: dup
    //   430: bipush #25
    //   432: ldc 16777220
    //   434: iastore
    //   435: dup
    //   436: bipush #26
    //   438: ldc 16777220
    //   440: iastore
    //   441: dup
    //   442: bipush #27
    //   444: ldc 65540
    //   446: iastore
    //   447: dup
    //   448: bipush #28
    //   450: iconst_0
    //   451: iastore
    //   452: dup
    //   453: bipush #29
    //   455: sipush #1028
    //   458: iastore
    //   459: dup
    //   460: bipush #30
    //   462: ldc 66564
    //   464: iastore
    //   465: dup
    //   466: bipush #31
    //   468: ldc 16777216
    //   470: iastore
    //   471: dup
    //   472: bipush #32
    //   474: ldc 65536
    //   476: iastore
    //   477: dup
    //   478: bipush #33
    //   480: ldc 16843780
    //   482: iastore
    //   483: dup
    //   484: bipush #34
    //   486: iconst_4
    //   487: iastore
    //   488: dup
    //   489: bipush #35
    //   491: ldc 16842752
    //   493: iastore
    //   494: dup
    //   495: bipush #36
    //   497: ldc 16843776
    //   499: iastore
    //   500: dup
    //   501: bipush #37
    //   503: ldc 16777216
    //   505: iastore
    //   506: dup
    //   507: bipush #38
    //   509: ldc 16777216
    //   511: iastore
    //   512: dup
    //   513: bipush #39
    //   515: sipush #1024
    //   518: iastore
    //   519: dup
    //   520: bipush #40
    //   522: ldc 16842756
    //   524: iastore
    //   525: dup
    //   526: bipush #41
    //   528: ldc 65536
    //   530: iastore
    //   531: dup
    //   532: bipush #42
    //   534: ldc 66560
    //   536: iastore
    //   537: dup
    //   538: bipush #43
    //   540: ldc 16777220
    //   542: iastore
    //   543: dup
    //   544: bipush #44
    //   546: sipush #1024
    //   549: iastore
    //   550: dup
    //   551: bipush #45
    //   553: iconst_4
    //   554: iastore
    //   555: dup
    //   556: bipush #46
    //   558: ldc 16778244
    //   560: iastore
    //   561: dup
    //   562: bipush #47
    //   564: ldc 66564
    //   566: iastore
    //   567: dup
    //   568: bipush #48
    //   570: ldc 16843780
    //   572: iastore
    //   573: dup
    //   574: bipush #49
    //   576: ldc 65540
    //   578: iastore
    //   579: dup
    //   580: bipush #50
    //   582: ldc 16842752
    //   584: iastore
    //   585: dup
    //   586: bipush #51
    //   588: ldc 16778244
    //   590: iastore
    //   591: dup
    //   592: bipush #52
    //   594: ldc 16777220
    //   596: iastore
    //   597: dup
    //   598: bipush #53
    //   600: sipush #1028
    //   603: iastore
    //   604: dup
    //   605: bipush #54
    //   607: ldc 66564
    //   609: iastore
    //   610: dup
    //   611: bipush #55
    //   613: ldc 16843776
    //   615: iastore
    //   616: dup
    //   617: bipush #56
    //   619: sipush #1028
    //   622: iastore
    //   623: dup
    //   624: bipush #57
    //   626: ldc 16778240
    //   628: iastore
    //   629: dup
    //   630: bipush #58
    //   632: ldc 16778240
    //   634: iastore
    //   635: dup
    //   636: bipush #59
    //   638: iconst_0
    //   639: iastore
    //   640: dup
    //   641: bipush #60
    //   643: ldc 65540
    //   645: iastore
    //   646: dup
    //   647: bipush #61
    //   649: ldc 66560
    //   651: iastore
    //   652: dup
    //   653: bipush #62
    //   655: iconst_0
    //   656: iastore
    //   657: dup
    //   658: bipush #63
    //   660: ldc 16842756
    //   662: iastore
    //   663: astore #8
    //   665: bipush #64
    //   667: newarray int
    //   669: dup
    //   670: iconst_0
    //   671: ldc -2146402272
    //   673: iastore
    //   674: dup
    //   675: iconst_1
    //   676: ldc -2147450880
    //   678: iastore
    //   679: dup
    //   680: iconst_2
    //   681: ldc 32768
    //   683: iastore
    //   684: dup
    //   685: iconst_3
    //   686: ldc 1081376
    //   688: iastore
    //   689: dup
    //   690: iconst_4
    //   691: ldc 1048576
    //   693: iastore
    //   694: dup
    //   695: iconst_5
    //   696: bipush #32
    //   698: iastore
    //   699: dup
    //   700: bipush #6
    //   702: ldc -2146435040
    //   704: iastore
    //   705: dup
    //   706: bipush #7
    //   708: ldc -2147450848
    //   710: iastore
    //   711: dup
    //   712: bipush #8
    //   714: ldc -2147483616
    //   716: iastore
    //   717: dup
    //   718: bipush #9
    //   720: ldc -2146402272
    //   722: iastore
    //   723: dup
    //   724: bipush #10
    //   726: ldc -2146402304
    //   728: iastore
    //   729: dup
    //   730: bipush #11
    //   732: ldc -2147483648
    //   734: iastore
    //   735: dup
    //   736: bipush #12
    //   738: ldc -2147450880
    //   740: iastore
    //   741: dup
    //   742: bipush #13
    //   744: ldc 1048576
    //   746: iastore
    //   747: dup
    //   748: bipush #14
    //   750: bipush #32
    //   752: iastore
    //   753: dup
    //   754: bipush #15
    //   756: ldc -2146435040
    //   758: iastore
    //   759: dup
    //   760: bipush #16
    //   762: ldc 1081344
    //   764: iastore
    //   765: dup
    //   766: bipush #17
    //   768: ldc 1048608
    //   770: iastore
    //   771: dup
    //   772: bipush #18
    //   774: ldc -2147450848
    //   776: iastore
    //   777: dup
    //   778: bipush #19
    //   780: iconst_0
    //   781: iastore
    //   782: dup
    //   783: bipush #20
    //   785: ldc -2147483648
    //   787: iastore
    //   788: dup
    //   789: bipush #21
    //   791: ldc 32768
    //   793: iastore
    //   794: dup
    //   795: bipush #22
    //   797: ldc 1081376
    //   799: iastore
    //   800: dup
    //   801: bipush #23
    //   803: ldc -2146435072
    //   805: iastore
    //   806: dup
    //   807: bipush #24
    //   809: ldc 1048608
    //   811: iastore
    //   812: dup
    //   813: bipush #25
    //   815: ldc -2147483616
    //   817: iastore
    //   818: dup
    //   819: bipush #26
    //   821: iconst_0
    //   822: iastore
    //   823: dup
    //   824: bipush #27
    //   826: ldc 1081344
    //   828: iastore
    //   829: dup
    //   830: bipush #28
    //   832: ldc 32800
    //   834: iastore
    //   835: dup
    //   836: bipush #29
    //   838: ldc -2146402304
    //   840: iastore
    //   841: dup
    //   842: bipush #30
    //   844: ldc -2146435072
    //   846: iastore
    //   847: dup
    //   848: bipush #31
    //   850: ldc 32800
    //   852: iastore
    //   853: dup
    //   854: bipush #32
    //   856: iconst_0
    //   857: iastore
    //   858: dup
    //   859: bipush #33
    //   861: ldc 1081376
    //   863: iastore
    //   864: dup
    //   865: bipush #34
    //   867: ldc -2146435040
    //   869: iastore
    //   870: dup
    //   871: bipush #35
    //   873: ldc 1048576
    //   875: iastore
    //   876: dup
    //   877: bipush #36
    //   879: ldc -2147450848
    //   881: iastore
    //   882: dup
    //   883: bipush #37
    //   885: ldc -2146435072
    //   887: iastore
    //   888: dup
    //   889: bipush #38
    //   891: ldc -2146402304
    //   893: iastore
    //   894: dup
    //   895: bipush #39
    //   897: ldc 32768
    //   899: iastore
    //   900: dup
    //   901: bipush #40
    //   903: ldc -2146435072
    //   905: iastore
    //   906: dup
    //   907: bipush #41
    //   909: ldc -2147450880
    //   911: iastore
    //   912: dup
    //   913: bipush #42
    //   915: bipush #32
    //   917: iastore
    //   918: dup
    //   919: bipush #43
    //   921: ldc -2146402272
    //   923: iastore
    //   924: dup
    //   925: bipush #44
    //   927: ldc 1081376
    //   929: iastore
    //   930: dup
    //   931: bipush #45
    //   933: bipush #32
    //   935: iastore
    //   936: dup
    //   937: bipush #46
    //   939: ldc 32768
    //   941: iastore
    //   942: dup
    //   943: bipush #47
    //   945: ldc -2147483648
    //   947: iastore
    //   948: dup
    //   949: bipush #48
    //   951: ldc 32800
    //   953: iastore
    //   954: dup
    //   955: bipush #49
    //   957: ldc -2146402304
    //   959: iastore
    //   960: dup
    //   961: bipush #50
    //   963: ldc 1048576
    //   965: iastore
    //   966: dup
    //   967: bipush #51
    //   969: ldc -2147483616
    //   971: iastore
    //   972: dup
    //   973: bipush #52
    //   975: ldc 1048608
    //   977: iastore
    //   978: dup
    //   979: bipush #53
    //   981: ldc -2147450848
    //   983: iastore
    //   984: dup
    //   985: bipush #54
    //   987: ldc -2147483616
    //   989: iastore
    //   990: dup
    //   991: bipush #55
    //   993: ldc 1048608
    //   995: iastore
    //   996: dup
    //   997: bipush #56
    //   999: ldc 1081344
    //   1001: iastore
    //   1002: dup
    //   1003: bipush #57
    //   1005: iconst_0
    //   1006: iastore
    //   1007: dup
    //   1008: bipush #58
    //   1010: ldc -2147450880
    //   1012: iastore
    //   1013: dup
    //   1014: bipush #59
    //   1016: ldc 32800
    //   1018: iastore
    //   1019: dup
    //   1020: bipush #60
    //   1022: ldc -2147483648
    //   1024: iastore
    //   1025: dup
    //   1026: bipush #61
    //   1028: ldc -2146435040
    //   1030: iastore
    //   1031: dup
    //   1032: bipush #62
    //   1034: ldc -2146402272
    //   1036: iastore
    //   1037: dup
    //   1038: bipush #63
    //   1040: ldc 1081344
    //   1042: iastore
    //   1043: astore #9
    //   1045: bipush #64
    //   1047: newarray int
    //   1049: dup
    //   1050: iconst_0
    //   1051: sipush #520
    //   1054: iastore
    //   1055: dup
    //   1056: iconst_1
    //   1057: ldc 134349312
    //   1059: iastore
    //   1060: dup
    //   1061: iconst_2
    //   1062: iconst_0
    //   1063: iastore
    //   1064: dup
    //   1065: iconst_3
    //   1066: ldc 134348808
    //   1068: iastore
    //   1069: dup
    //   1070: iconst_4
    //   1071: ldc 134218240
    //   1073: iastore
    //   1074: dup
    //   1075: iconst_5
    //   1076: iconst_0
    //   1077: iastore
    //   1078: dup
    //   1079: bipush #6
    //   1081: ldc 131592
    //   1083: iastore
    //   1084: dup
    //   1085: bipush #7
    //   1087: ldc 134218240
    //   1089: iastore
    //   1090: dup
    //   1091: bipush #8
    //   1093: ldc 131080
    //   1095: iastore
    //   1096: dup
    //   1097: bipush #9
    //   1099: ldc 134217736
    //   1101: iastore
    //   1102: dup
    //   1103: bipush #10
    //   1105: ldc 134217736
    //   1107: iastore
    //   1108: dup
    //   1109: bipush #11
    //   1111: ldc 131072
    //   1113: iastore
    //   1114: dup
    //   1115: bipush #12
    //   1117: ldc 134349320
    //   1119: iastore
    //   1120: dup
    //   1121: bipush #13
    //   1123: ldc 131080
    //   1125: iastore
    //   1126: dup
    //   1127: bipush #14
    //   1129: ldc 134348800
    //   1131: iastore
    //   1132: dup
    //   1133: bipush #15
    //   1135: sipush #520
    //   1138: iastore
    //   1139: dup
    //   1140: bipush #16
    //   1142: ldc 134217728
    //   1144: iastore
    //   1145: dup
    //   1146: bipush #17
    //   1148: bipush #8
    //   1150: iastore
    //   1151: dup
    //   1152: bipush #18
    //   1154: ldc 134349312
    //   1156: iastore
    //   1157: dup
    //   1158: bipush #19
    //   1160: sipush #512
    //   1163: iastore
    //   1164: dup
    //   1165: bipush #20
    //   1167: ldc 131584
    //   1169: iastore
    //   1170: dup
    //   1171: bipush #21
    //   1173: ldc 134348800
    //   1175: iastore
    //   1176: dup
    //   1177: bipush #22
    //   1179: ldc 134348808
    //   1181: iastore
    //   1182: dup
    //   1183: bipush #23
    //   1185: ldc 131592
    //   1187: iastore
    //   1188: dup
    //   1189: bipush #24
    //   1191: ldc 134218248
    //   1193: iastore
    //   1194: dup
    //   1195: bipush #25
    //   1197: ldc 131584
    //   1199: iastore
    //   1200: dup
    //   1201: bipush #26
    //   1203: ldc 131072
    //   1205: iastore
    //   1206: dup
    //   1207: bipush #27
    //   1209: ldc 134218248
    //   1211: iastore
    //   1212: dup
    //   1213: bipush #28
    //   1215: bipush #8
    //   1217: iastore
    //   1218: dup
    //   1219: bipush #29
    //   1221: ldc 134349320
    //   1223: iastore
    //   1224: dup
    //   1225: bipush #30
    //   1227: sipush #512
    //   1230: iastore
    //   1231: dup
    //   1232: bipush #31
    //   1234: ldc 134217728
    //   1236: iastore
    //   1237: dup
    //   1238: bipush #32
    //   1240: ldc 134349312
    //   1242: iastore
    //   1243: dup
    //   1244: bipush #33
    //   1246: ldc 134217728
    //   1248: iastore
    //   1249: dup
    //   1250: bipush #34
    //   1252: ldc 131080
    //   1254: iastore
    //   1255: dup
    //   1256: bipush #35
    //   1258: sipush #520
    //   1261: iastore
    //   1262: dup
    //   1263: bipush #36
    //   1265: ldc 131072
    //   1267: iastore
    //   1268: dup
    //   1269: bipush #37
    //   1271: ldc 134349312
    //   1273: iastore
    //   1274: dup
    //   1275: bipush #38
    //   1277: ldc 134218240
    //   1279: iastore
    //   1280: dup
    //   1281: bipush #39
    //   1283: iconst_0
    //   1284: iastore
    //   1285: dup
    //   1286: bipush #40
    //   1288: sipush #512
    //   1291: iastore
    //   1292: dup
    //   1293: bipush #41
    //   1295: ldc 131080
    //   1297: iastore
    //   1298: dup
    //   1299: bipush #42
    //   1301: ldc 134349320
    //   1303: iastore
    //   1304: dup
    //   1305: bipush #43
    //   1307: ldc 134218240
    //   1309: iastore
    //   1310: dup
    //   1311: bipush #44
    //   1313: ldc 134217736
    //   1315: iastore
    //   1316: dup
    //   1317: bipush #45
    //   1319: sipush #512
    //   1322: iastore
    //   1323: dup
    //   1324: bipush #46
    //   1326: iconst_0
    //   1327: iastore
    //   1328: dup
    //   1329: bipush #47
    //   1331: ldc 134348808
    //   1333: iastore
    //   1334: dup
    //   1335: bipush #48
    //   1337: ldc 134218248
    //   1339: iastore
    //   1340: dup
    //   1341: bipush #49
    //   1343: ldc 131072
    //   1345: iastore
    //   1346: dup
    //   1347: bipush #50
    //   1349: ldc 134217728
    //   1351: iastore
    //   1352: dup
    //   1353: bipush #51
    //   1355: ldc 134349320
    //   1357: iastore
    //   1358: dup
    //   1359: bipush #52
    //   1361: bipush #8
    //   1363: iastore
    //   1364: dup
    //   1365: bipush #53
    //   1367: ldc 131592
    //   1369: iastore
    //   1370: dup
    //   1371: bipush #54
    //   1373: ldc 131584
    //   1375: iastore
    //   1376: dup
    //   1377: bipush #55
    //   1379: ldc 134217736
    //   1381: iastore
    //   1382: dup
    //   1383: bipush #56
    //   1385: ldc 134348800
    //   1387: iastore
    //   1388: dup
    //   1389: bipush #57
    //   1391: ldc 134218248
    //   1393: iastore
    //   1394: dup
    //   1395: bipush #58
    //   1397: sipush #520
    //   1400: iastore
    //   1401: dup
    //   1402: bipush #59
    //   1404: ldc 134348800
    //   1406: iastore
    //   1407: dup
    //   1408: bipush #60
    //   1410: ldc 131592
    //   1412: iastore
    //   1413: dup
    //   1414: bipush #61
    //   1416: bipush #8
    //   1418: iastore
    //   1419: dup
    //   1420: bipush #62
    //   1422: ldc 134348808
    //   1424: iastore
    //   1425: dup
    //   1426: bipush #63
    //   1428: ldc 131584
    //   1430: iastore
    //   1431: astore #10
    //   1433: bipush #64
    //   1435: newarray int
    //   1437: dup
    //   1438: iconst_0
    //   1439: ldc 8396801
    //   1441: iastore
    //   1442: dup
    //   1443: iconst_1
    //   1444: sipush #8321
    //   1447: iastore
    //   1448: dup
    //   1449: iconst_2
    //   1450: sipush #8321
    //   1453: iastore
    //   1454: dup
    //   1455: iconst_3
    //   1456: sipush #128
    //   1459: iastore
    //   1460: dup
    //   1461: iconst_4
    //   1462: ldc 8396928
    //   1464: iastore
    //   1465: dup
    //   1466: iconst_5
    //   1467: ldc 8388737
    //   1469: iastore
    //   1470: dup
    //   1471: bipush #6
    //   1473: ldc 8388609
    //   1475: iastore
    //   1476: dup
    //   1477: bipush #7
    //   1479: sipush #8193
    //   1482: iastore
    //   1483: dup
    //   1484: bipush #8
    //   1486: iconst_0
    //   1487: iastore
    //   1488: dup
    //   1489: bipush #9
    //   1491: ldc 8396800
    //   1493: iastore
    //   1494: dup
    //   1495: bipush #10
    //   1497: ldc 8396800
    //   1499: iastore
    //   1500: dup
    //   1501: bipush #11
    //   1503: ldc 8396929
    //   1505: iastore
    //   1506: dup
    //   1507: bipush #12
    //   1509: sipush #129
    //   1512: iastore
    //   1513: dup
    //   1514: bipush #13
    //   1516: iconst_0
    //   1517: iastore
    //   1518: dup
    //   1519: bipush #14
    //   1521: ldc 8388736
    //   1523: iastore
    //   1524: dup
    //   1525: bipush #15
    //   1527: ldc 8388609
    //   1529: iastore
    //   1530: dup
    //   1531: bipush #16
    //   1533: iconst_1
    //   1534: iastore
    //   1535: dup
    //   1536: bipush #17
    //   1538: sipush #8192
    //   1541: iastore
    //   1542: dup
    //   1543: bipush #18
    //   1545: ldc 8388608
    //   1547: iastore
    //   1548: dup
    //   1549: bipush #19
    //   1551: ldc 8396801
    //   1553: iastore
    //   1554: dup
    //   1555: bipush #20
    //   1557: sipush #128
    //   1560: iastore
    //   1561: dup
    //   1562: bipush #21
    //   1564: ldc 8388608
    //   1566: iastore
    //   1567: dup
    //   1568: bipush #22
    //   1570: sipush #8193
    //   1573: iastore
    //   1574: dup
    //   1575: bipush #23
    //   1577: sipush #8320
    //   1580: iastore
    //   1581: dup
    //   1582: bipush #24
    //   1584: ldc 8388737
    //   1586: iastore
    //   1587: dup
    //   1588: bipush #25
    //   1590: iconst_1
    //   1591: iastore
    //   1592: dup
    //   1593: bipush #26
    //   1595: sipush #8320
    //   1598: iastore
    //   1599: dup
    //   1600: bipush #27
    //   1602: ldc 8388736
    //   1604: iastore
    //   1605: dup
    //   1606: bipush #28
    //   1608: sipush #8192
    //   1611: iastore
    //   1612: dup
    //   1613: bipush #29
    //   1615: ldc 8396928
    //   1617: iastore
    //   1618: dup
    //   1619: bipush #30
    //   1621: ldc 8396929
    //   1623: iastore
    //   1624: dup
    //   1625: bipush #31
    //   1627: sipush #129
    //   1630: iastore
    //   1631: dup
    //   1632: bipush #32
    //   1634: ldc 8388736
    //   1636: iastore
    //   1637: dup
    //   1638: bipush #33
    //   1640: ldc 8388609
    //   1642: iastore
    //   1643: dup
    //   1644: bipush #34
    //   1646: ldc 8396800
    //   1648: iastore
    //   1649: dup
    //   1650: bipush #35
    //   1652: ldc 8396929
    //   1654: iastore
    //   1655: dup
    //   1656: bipush #36
    //   1658: sipush #129
    //   1661: iastore
    //   1662: dup
    //   1663: bipush #37
    //   1665: iconst_0
    //   1666: iastore
    //   1667: dup
    //   1668: bipush #38
    //   1670: iconst_0
    //   1671: iastore
    //   1672: dup
    //   1673: bipush #39
    //   1675: ldc 8396800
    //   1677: iastore
    //   1678: dup
    //   1679: bipush #40
    //   1681: sipush #8320
    //   1684: iastore
    //   1685: dup
    //   1686: bipush #41
    //   1688: ldc 8388736
    //   1690: iastore
    //   1691: dup
    //   1692: bipush #42
    //   1694: ldc 8388737
    //   1696: iastore
    //   1697: dup
    //   1698: bipush #43
    //   1700: iconst_1
    //   1701: iastore
    //   1702: dup
    //   1703: bipush #44
    //   1705: ldc 8396801
    //   1707: iastore
    //   1708: dup
    //   1709: bipush #45
    //   1711: sipush #8321
    //   1714: iastore
    //   1715: dup
    //   1716: bipush #46
    //   1718: sipush #8321
    //   1721: iastore
    //   1722: dup
    //   1723: bipush #47
    //   1725: sipush #128
    //   1728: iastore
    //   1729: dup
    //   1730: bipush #48
    //   1732: ldc 8396929
    //   1734: iastore
    //   1735: dup
    //   1736: bipush #49
    //   1738: sipush #129
    //   1741: iastore
    //   1742: dup
    //   1743: bipush #50
    //   1745: iconst_1
    //   1746: iastore
    //   1747: dup
    //   1748: bipush #51
    //   1750: sipush #8192
    //   1753: iastore
    //   1754: dup
    //   1755: bipush #52
    //   1757: ldc 8388609
    //   1759: iastore
    //   1760: dup
    //   1761: bipush #53
    //   1763: sipush #8193
    //   1766: iastore
    //   1767: dup
    //   1768: bipush #54
    //   1770: ldc 8396928
    //   1772: iastore
    //   1773: dup
    //   1774: bipush #55
    //   1776: ldc 8388737
    //   1778: iastore
    //   1779: dup
    //   1780: bipush #56
    //   1782: sipush #8193
    //   1785: iastore
    //   1786: dup
    //   1787: bipush #57
    //   1789: sipush #8320
    //   1792: iastore
    //   1793: dup
    //   1794: bipush #58
    //   1796: ldc 8388608
    //   1798: iastore
    //   1799: dup
    //   1800: bipush #59
    //   1802: ldc 8396801
    //   1804: iastore
    //   1805: dup
    //   1806: bipush #60
    //   1808: sipush #128
    //   1811: iastore
    //   1812: dup
    //   1813: bipush #61
    //   1815: ldc 8388608
    //   1817: iastore
    //   1818: dup
    //   1819: bipush #62
    //   1821: sipush #8192
    //   1824: iastore
    //   1825: dup
    //   1826: bipush #63
    //   1828: ldc 8396928
    //   1830: iastore
    //   1831: astore #11
    //   1833: bipush #64
    //   1835: newarray int
    //   1837: dup
    //   1838: iconst_0
    //   1839: sipush #256
    //   1842: iastore
    //   1843: dup
    //   1844: iconst_1
    //   1845: ldc 34078976
    //   1847: iastore
    //   1848: dup
    //   1849: iconst_2
    //   1850: ldc 34078720
    //   1852: iastore
    //   1853: dup
    //   1854: iconst_3
    //   1855: ldc 1107296512
    //   1857: iastore
    //   1858: dup
    //   1859: iconst_4
    //   1860: ldc 524288
    //   1862: iastore
    //   1863: dup
    //   1864: iconst_5
    //   1865: sipush #256
    //   1868: iastore
    //   1869: dup
    //   1870: bipush #6
    //   1872: ldc 1073741824
    //   1874: iastore
    //   1875: dup
    //   1876: bipush #7
    //   1878: ldc 34078720
    //   1880: iastore
    //   1881: dup
    //   1882: bipush #8
    //   1884: ldc 1074266368
    //   1886: iastore
    //   1887: dup
    //   1888: bipush #9
    //   1890: ldc 524288
    //   1892: iastore
    //   1893: dup
    //   1894: bipush #10
    //   1896: ldc 33554688
    //   1898: iastore
    //   1899: dup
    //   1900: bipush #11
    //   1902: ldc 1074266368
    //   1904: iastore
    //   1905: dup
    //   1906: bipush #12
    //   1908: ldc 1107296512
    //   1910: iastore
    //   1911: dup
    //   1912: bipush #13
    //   1914: ldc 1107820544
    //   1916: iastore
    //   1917: dup
    //   1918: bipush #14
    //   1920: ldc 524544
    //   1922: iastore
    //   1923: dup
    //   1924: bipush #15
    //   1926: ldc 1073741824
    //   1928: iastore
    //   1929: dup
    //   1930: bipush #16
    //   1932: ldc 33554432
    //   1934: iastore
    //   1935: dup
    //   1936: bipush #17
    //   1938: ldc 1074266112
    //   1940: iastore
    //   1941: dup
    //   1942: bipush #18
    //   1944: ldc 1074266112
    //   1946: iastore
    //   1947: dup
    //   1948: bipush #19
    //   1950: iconst_0
    //   1951: iastore
    //   1952: dup
    //   1953: bipush #20
    //   1955: ldc 1073742080
    //   1957: iastore
    //   1958: dup
    //   1959: bipush #21
    //   1961: ldc 1107820800
    //   1963: iastore
    //   1964: dup
    //   1965: bipush #22
    //   1967: ldc 1107820800
    //   1969: iastore
    //   1970: dup
    //   1971: bipush #23
    //   1973: ldc 33554688
    //   1975: iastore
    //   1976: dup
    //   1977: bipush #24
    //   1979: ldc 1107820544
    //   1981: iastore
    //   1982: dup
    //   1983: bipush #25
    //   1985: ldc 1073742080
    //   1987: iastore
    //   1988: dup
    //   1989: bipush #26
    //   1991: iconst_0
    //   1992: iastore
    //   1993: dup
    //   1994: bipush #27
    //   1996: ldc 1107296256
    //   1998: iastore
    //   1999: dup
    //   2000: bipush #28
    //   2002: ldc 34078976
    //   2004: iastore
    //   2005: dup
    //   2006: bipush #29
    //   2008: ldc 33554432
    //   2010: iastore
    //   2011: dup
    //   2012: bipush #30
    //   2014: ldc 1107296256
    //   2016: iastore
    //   2017: dup
    //   2018: bipush #31
    //   2020: ldc 524544
    //   2022: iastore
    //   2023: dup
    //   2024: bipush #32
    //   2026: ldc 524288
    //   2028: iastore
    //   2029: dup
    //   2030: bipush #33
    //   2032: ldc 1107296512
    //   2034: iastore
    //   2035: dup
    //   2036: bipush #34
    //   2038: sipush #256
    //   2041: iastore
    //   2042: dup
    //   2043: bipush #35
    //   2045: ldc 33554432
    //   2047: iastore
    //   2048: dup
    //   2049: bipush #36
    //   2051: ldc 1073741824
    //   2053: iastore
    //   2054: dup
    //   2055: bipush #37
    //   2057: ldc 34078720
    //   2059: iastore
    //   2060: dup
    //   2061: bipush #38
    //   2063: ldc 1107296512
    //   2065: iastore
    //   2066: dup
    //   2067: bipush #39
    //   2069: ldc 1074266368
    //   2071: iastore
    //   2072: dup
    //   2073: bipush #40
    //   2075: ldc 33554688
    //   2077: iastore
    //   2078: dup
    //   2079: bipush #41
    //   2081: ldc 1073741824
    //   2083: iastore
    //   2084: dup
    //   2085: bipush #42
    //   2087: ldc 1107820544
    //   2089: iastore
    //   2090: dup
    //   2091: bipush #43
    //   2093: ldc 34078976
    //   2095: iastore
    //   2096: dup
    //   2097: bipush #44
    //   2099: ldc 1074266368
    //   2101: iastore
    //   2102: dup
    //   2103: bipush #45
    //   2105: sipush #256
    //   2108: iastore
    //   2109: dup
    //   2110: bipush #46
    //   2112: ldc 33554432
    //   2114: iastore
    //   2115: dup
    //   2116: bipush #47
    //   2118: ldc 1107820544
    //   2120: iastore
    //   2121: dup
    //   2122: bipush #48
    //   2124: ldc 1107820800
    //   2126: iastore
    //   2127: dup
    //   2128: bipush #49
    //   2130: ldc 524544
    //   2132: iastore
    //   2133: dup
    //   2134: bipush #50
    //   2136: ldc 1107296256
    //   2138: iastore
    //   2139: dup
    //   2140: bipush #51
    //   2142: ldc 1107820800
    //   2144: iastore
    //   2145: dup
    //   2146: bipush #52
    //   2148: ldc 34078720
    //   2150: iastore
    //   2151: dup
    //   2152: bipush #53
    //   2154: iconst_0
    //   2155: iastore
    //   2156: dup
    //   2157: bipush #54
    //   2159: ldc 1074266112
    //   2161: iastore
    //   2162: dup
    //   2163: bipush #55
    //   2165: ldc 1107296256
    //   2167: iastore
    //   2168: dup
    //   2169: bipush #56
    //   2171: ldc 524544
    //   2173: iastore
    //   2174: dup
    //   2175: bipush #57
    //   2177: ldc 33554688
    //   2179: iastore
    //   2180: dup
    //   2181: bipush #58
    //   2183: ldc 1073742080
    //   2185: iastore
    //   2186: dup
    //   2187: bipush #59
    //   2189: ldc 524288
    //   2191: iastore
    //   2192: dup
    //   2193: bipush #60
    //   2195: iconst_0
    //   2196: iastore
    //   2197: dup
    //   2198: bipush #61
    //   2200: ldc 1074266112
    //   2202: iastore
    //   2203: dup
    //   2204: bipush #62
    //   2206: ldc 34078976
    //   2208: iastore
    //   2209: dup
    //   2210: bipush #63
    //   2212: ldc 1073742080
    //   2214: iastore
    //   2215: astore #12
    //   2217: bipush #64
    //   2219: newarray int
    //   2221: dup
    //   2222: iconst_0
    //   2223: ldc 536870928
    //   2225: iastore
    //   2226: dup
    //   2227: iconst_1
    //   2228: ldc 541065216
    //   2230: iastore
    //   2231: dup
    //   2232: iconst_2
    //   2233: sipush #16384
    //   2236: iastore
    //   2237: dup
    //   2238: iconst_3
    //   2239: ldc 541081616
    //   2241: iastore
    //   2242: dup
    //   2243: iconst_4
    //   2244: ldc 541065216
    //   2246: iastore
    //   2247: dup
    //   2248: iconst_5
    //   2249: bipush #16
    //   2251: iastore
    //   2252: dup
    //   2253: bipush #6
    //   2255: ldc 541081616
    //   2257: iastore
    //   2258: dup
    //   2259: bipush #7
    //   2261: ldc 4194304
    //   2263: iastore
    //   2264: dup
    //   2265: bipush #8
    //   2267: ldc 536887296
    //   2269: iastore
    //   2270: dup
    //   2271: bipush #9
    //   2273: ldc 4210704
    //   2275: iastore
    //   2276: dup
    //   2277: bipush #10
    //   2279: ldc 4194304
    //   2281: iastore
    //   2282: dup
    //   2283: bipush #11
    //   2285: ldc 536870928
    //   2287: iastore
    //   2288: dup
    //   2289: bipush #12
    //   2291: ldc 4194320
    //   2293: iastore
    //   2294: dup
    //   2295: bipush #13
    //   2297: ldc 536887296
    //   2299: iastore
    //   2300: dup
    //   2301: bipush #14
    //   2303: ldc 536870912
    //   2305: iastore
    //   2306: dup
    //   2307: bipush #15
    //   2309: sipush #16400
    //   2312: iastore
    //   2313: dup
    //   2314: bipush #16
    //   2316: iconst_0
    //   2317: iastore
    //   2318: dup
    //   2319: bipush #17
    //   2321: ldc 4194320
    //   2323: iastore
    //   2324: dup
    //   2325: bipush #18
    //   2327: ldc 536887312
    //   2329: iastore
    //   2330: dup
    //   2331: bipush #19
    //   2333: sipush #16384
    //   2336: iastore
    //   2337: dup
    //   2338: bipush #20
    //   2340: ldc 4210688
    //   2342: iastore
    //   2343: dup
    //   2344: bipush #21
    //   2346: ldc 536887312
    //   2348: iastore
    //   2349: dup
    //   2350: bipush #22
    //   2352: bipush #16
    //   2354: iastore
    //   2355: dup
    //   2356: bipush #23
    //   2358: ldc 541065232
    //   2360: iastore
    //   2361: dup
    //   2362: bipush #24
    //   2364: ldc 541065232
    //   2366: iastore
    //   2367: dup
    //   2368: bipush #25
    //   2370: iconst_0
    //   2371: iastore
    //   2372: dup
    //   2373: bipush #26
    //   2375: ldc 4210704
    //   2377: iastore
    //   2378: dup
    //   2379: bipush #27
    //   2381: ldc 541081600
    //   2383: iastore
    //   2384: dup
    //   2385: bipush #28
    //   2387: sipush #16400
    //   2390: iastore
    //   2391: dup
    //   2392: bipush #29
    //   2394: ldc 4210688
    //   2396: iastore
    //   2397: dup
    //   2398: bipush #30
    //   2400: ldc 541081600
    //   2402: iastore
    //   2403: dup
    //   2404: bipush #31
    //   2406: ldc 536870912
    //   2408: iastore
    //   2409: dup
    //   2410: bipush #32
    //   2412: ldc 536887296
    //   2414: iastore
    //   2415: dup
    //   2416: bipush #33
    //   2418: bipush #16
    //   2420: iastore
    //   2421: dup
    //   2422: bipush #34
    //   2424: ldc 541065232
    //   2426: iastore
    //   2427: dup
    //   2428: bipush #35
    //   2430: ldc 4210688
    //   2432: iastore
    //   2433: dup
    //   2434: bipush #36
    //   2436: ldc 541081616
    //   2438: iastore
    //   2439: dup
    //   2440: bipush #37
    //   2442: ldc 4194304
    //   2444: iastore
    //   2445: dup
    //   2446: bipush #38
    //   2448: sipush #16400
    //   2451: iastore
    //   2452: dup
    //   2453: bipush #39
    //   2455: ldc 536870928
    //   2457: iastore
    //   2458: dup
    //   2459: bipush #40
    //   2461: ldc 4194304
    //   2463: iastore
    //   2464: dup
    //   2465: bipush #41
    //   2467: ldc 536887296
    //   2469: iastore
    //   2470: dup
    //   2471: bipush #42
    //   2473: ldc 536870912
    //   2475: iastore
    //   2476: dup
    //   2477: bipush #43
    //   2479: sipush #16400
    //   2482: iastore
    //   2483: dup
    //   2484: bipush #44
    //   2486: ldc 536870928
    //   2488: iastore
    //   2489: dup
    //   2490: bipush #45
    //   2492: ldc 541081616
    //   2494: iastore
    //   2495: dup
    //   2496: bipush #46
    //   2498: ldc 4210688
    //   2500: iastore
    //   2501: dup
    //   2502: bipush #47
    //   2504: ldc 541065216
    //   2506: iastore
    //   2507: dup
    //   2508: bipush #48
    //   2510: ldc 4210704
    //   2512: iastore
    //   2513: dup
    //   2514: bipush #49
    //   2516: ldc 541081600
    //   2518: iastore
    //   2519: dup
    //   2520: bipush #50
    //   2522: iconst_0
    //   2523: iastore
    //   2524: dup
    //   2525: bipush #51
    //   2527: ldc 541065232
    //   2529: iastore
    //   2530: dup
    //   2531: bipush #52
    //   2533: bipush #16
    //   2535: iastore
    //   2536: dup
    //   2537: bipush #53
    //   2539: sipush #16384
    //   2542: iastore
    //   2543: dup
    //   2544: bipush #54
    //   2546: ldc 541065216
    //   2548: iastore
    //   2549: dup
    //   2550: bipush #55
    //   2552: ldc 4210704
    //   2554: iastore
    //   2555: dup
    //   2556: bipush #56
    //   2558: sipush #16384
    //   2561: iastore
    //   2562: dup
    //   2563: bipush #57
    //   2565: ldc 4194320
    //   2567: iastore
    //   2568: dup
    //   2569: bipush #58
    //   2571: ldc 536887312
    //   2573: iastore
    //   2574: dup
    //   2575: bipush #59
    //   2577: iconst_0
    //   2578: iastore
    //   2579: dup
    //   2580: bipush #60
    //   2582: ldc 541081600
    //   2584: iastore
    //   2585: dup
    //   2586: bipush #61
    //   2588: ldc 536870912
    //   2590: iastore
    //   2591: dup
    //   2592: bipush #62
    //   2594: ldc 4194320
    //   2596: iastore
    //   2597: dup
    //   2598: bipush #63
    //   2600: ldc 536887312
    //   2602: iastore
    //   2603: astore #13
    //   2605: bipush #64
    //   2607: newarray int
    //   2609: dup
    //   2610: iconst_0
    //   2611: ldc 2097152
    //   2613: iastore
    //   2614: dup
    //   2615: iconst_1
    //   2616: ldc 69206018
    //   2618: iastore
    //   2619: dup
    //   2620: iconst_2
    //   2621: ldc 67110914
    //   2623: iastore
    //   2624: dup
    //   2625: iconst_3
    //   2626: iconst_0
    //   2627: iastore
    //   2628: dup
    //   2629: iconst_4
    //   2630: sipush #2048
    //   2633: iastore
    //   2634: dup
    //   2635: iconst_5
    //   2636: ldc 67110914
    //   2638: iastore
    //   2639: dup
    //   2640: bipush #6
    //   2642: ldc 2099202
    //   2644: iastore
    //   2645: dup
    //   2646: bipush #7
    //   2648: ldc 69208064
    //   2650: iastore
    //   2651: dup
    //   2652: bipush #8
    //   2654: ldc 69208066
    //   2656: iastore
    //   2657: dup
    //   2658: bipush #9
    //   2660: ldc 2097152
    //   2662: iastore
    //   2663: dup
    //   2664: bipush #10
    //   2666: iconst_0
    //   2667: iastore
    //   2668: dup
    //   2669: bipush #11
    //   2671: ldc 67108866
    //   2673: iastore
    //   2674: dup
    //   2675: bipush #12
    //   2677: iconst_2
    //   2678: iastore
    //   2679: dup
    //   2680: bipush #13
    //   2682: ldc 67108864
    //   2684: iastore
    //   2685: dup
    //   2686: bipush #14
    //   2688: ldc 69206018
    //   2690: iastore
    //   2691: dup
    //   2692: bipush #15
    //   2694: sipush #2050
    //   2697: iastore
    //   2698: dup
    //   2699: bipush #16
    //   2701: ldc 67110912
    //   2703: iastore
    //   2704: dup
    //   2705: bipush #17
    //   2707: ldc 2099202
    //   2709: iastore
    //   2710: dup
    //   2711: bipush #18
    //   2713: ldc 2097154
    //   2715: iastore
    //   2716: dup
    //   2717: bipush #19
    //   2719: ldc 67110912
    //   2721: iastore
    //   2722: dup
    //   2723: bipush #20
    //   2725: ldc 67108866
    //   2727: iastore
    //   2728: dup
    //   2729: bipush #21
    //   2731: ldc 69206016
    //   2733: iastore
    //   2734: dup
    //   2735: bipush #22
    //   2737: ldc 69208064
    //   2739: iastore
    //   2740: dup
    //   2741: bipush #23
    //   2743: ldc 2097154
    //   2745: iastore
    //   2746: dup
    //   2747: bipush #24
    //   2749: ldc 69206016
    //   2751: iastore
    //   2752: dup
    //   2753: bipush #25
    //   2755: sipush #2048
    //   2758: iastore
    //   2759: dup
    //   2760: bipush #26
    //   2762: sipush #2050
    //   2765: iastore
    //   2766: dup
    //   2767: bipush #27
    //   2769: ldc 69208066
    //   2771: iastore
    //   2772: dup
    //   2773: bipush #28
    //   2775: ldc 2099200
    //   2777: iastore
    //   2778: dup
    //   2779: bipush #29
    //   2781: iconst_2
    //   2782: iastore
    //   2783: dup
    //   2784: bipush #30
    //   2786: ldc 67108864
    //   2788: iastore
    //   2789: dup
    //   2790: bipush #31
    //   2792: ldc 2099200
    //   2794: iastore
    //   2795: dup
    //   2796: bipush #32
    //   2798: ldc 67108864
    //   2800: iastore
    //   2801: dup
    //   2802: bipush #33
    //   2804: ldc 2099200
    //   2806: iastore
    //   2807: dup
    //   2808: bipush #34
    //   2810: ldc 2097152
    //   2812: iastore
    //   2813: dup
    //   2814: bipush #35
    //   2816: ldc 67110914
    //   2818: iastore
    //   2819: dup
    //   2820: bipush #36
    //   2822: ldc 67110914
    //   2824: iastore
    //   2825: dup
    //   2826: bipush #37
    //   2828: ldc 69206018
    //   2830: iastore
    //   2831: dup
    //   2832: bipush #38
    //   2834: ldc 69206018
    //   2836: iastore
    //   2837: dup
    //   2838: bipush #39
    //   2840: iconst_2
    //   2841: iastore
    //   2842: dup
    //   2843: bipush #40
    //   2845: ldc 2097154
    //   2847: iastore
    //   2848: dup
    //   2849: bipush #41
    //   2851: ldc 67108864
    //   2853: iastore
    //   2854: dup
    //   2855: bipush #42
    //   2857: ldc 67110912
    //   2859: iastore
    //   2860: dup
    //   2861: bipush #43
    //   2863: ldc 2097152
    //   2865: iastore
    //   2866: dup
    //   2867: bipush #44
    //   2869: ldc 69208064
    //   2871: iastore
    //   2872: dup
    //   2873: bipush #45
    //   2875: sipush #2050
    //   2878: iastore
    //   2879: dup
    //   2880: bipush #46
    //   2882: ldc 2099202
    //   2884: iastore
    //   2885: dup
    //   2886: bipush #47
    //   2888: ldc 69208064
    //   2890: iastore
    //   2891: dup
    //   2892: bipush #48
    //   2894: sipush #2050
    //   2897: iastore
    //   2898: dup
    //   2899: bipush #49
    //   2901: ldc 67108866
    //   2903: iastore
    //   2904: dup
    //   2905: bipush #50
    //   2907: ldc 69208066
    //   2909: iastore
    //   2910: dup
    //   2911: bipush #51
    //   2913: ldc 69206016
    //   2915: iastore
    //   2916: dup
    //   2917: bipush #52
    //   2919: ldc 2099200
    //   2921: iastore
    //   2922: dup
    //   2923: bipush #53
    //   2925: iconst_0
    //   2926: iastore
    //   2927: dup
    //   2928: bipush #54
    //   2930: iconst_2
    //   2931: iastore
    //   2932: dup
    //   2933: bipush #55
    //   2935: ldc 69208066
    //   2937: iastore
    //   2938: dup
    //   2939: bipush #56
    //   2941: iconst_0
    //   2942: iastore
    //   2943: dup
    //   2944: bipush #57
    //   2946: ldc 2099202
    //   2948: iastore
    //   2949: dup
    //   2950: bipush #58
    //   2952: ldc 69206016
    //   2954: iastore
    //   2955: dup
    //   2956: bipush #59
    //   2958: sipush #2048
    //   2961: iastore
    //   2962: dup
    //   2963: bipush #60
    //   2965: ldc 67108866
    //   2967: iastore
    //   2968: dup
    //   2969: bipush #61
    //   2971: ldc 67110912
    //   2973: iastore
    //   2974: dup
    //   2975: bipush #62
    //   2977: sipush #2048
    //   2980: iastore
    //   2981: dup
    //   2982: bipush #63
    //   2984: ldc 2097154
    //   2986: iastore
    //   2987: astore #14
    //   2989: bipush #64
    //   2991: newarray int
    //   2993: dup
    //   2994: iconst_0
    //   2995: ldc 268439616
    //   2997: iastore
    //   2998: dup
    //   2999: iconst_1
    //   3000: sipush #4096
    //   3003: iastore
    //   3004: dup
    //   3005: iconst_2
    //   3006: ldc 262144
    //   3008: iastore
    //   3009: dup
    //   3010: iconst_3
    //   3011: ldc 268701760
    //   3013: iastore
    //   3014: dup
    //   3015: iconst_4
    //   3016: ldc 268435456
    //   3018: iastore
    //   3019: dup
    //   3020: iconst_5
    //   3021: ldc 268439616
    //   3023: iastore
    //   3024: dup
    //   3025: bipush #6
    //   3027: bipush #64
    //   3029: iastore
    //   3030: dup
    //   3031: bipush #7
    //   3033: ldc 268435456
    //   3035: iastore
    //   3036: dup
    //   3037: bipush #8
    //   3039: ldc 262208
    //   3041: iastore
    //   3042: dup
    //   3043: bipush #9
    //   3045: ldc 268697600
    //   3047: iastore
    //   3048: dup
    //   3049: bipush #10
    //   3051: ldc 268701760
    //   3053: iastore
    //   3054: dup
    //   3055: bipush #11
    //   3057: ldc 266240
    //   3059: iastore
    //   3060: dup
    //   3061: bipush #12
    //   3063: ldc 268701696
    //   3065: iastore
    //   3066: dup
    //   3067: bipush #13
    //   3069: ldc 266304
    //   3071: iastore
    //   3072: dup
    //   3073: bipush #14
    //   3075: sipush #4096
    //   3078: iastore
    //   3079: dup
    //   3080: bipush #15
    //   3082: bipush #64
    //   3084: iastore
    //   3085: dup
    //   3086: bipush #16
    //   3088: ldc 268697600
    //   3090: iastore
    //   3091: dup
    //   3092: bipush #17
    //   3094: ldc 268435520
    //   3096: iastore
    //   3097: dup
    //   3098: bipush #18
    //   3100: ldc 268439552
    //   3102: iastore
    //   3103: dup
    //   3104: bipush #19
    //   3106: sipush #4160
    //   3109: iastore
    //   3110: dup
    //   3111: bipush #20
    //   3113: ldc 266240
    //   3115: iastore
    //   3116: dup
    //   3117: bipush #21
    //   3119: ldc 262208
    //   3121: iastore
    //   3122: dup
    //   3123: bipush #22
    //   3125: ldc 268697664
    //   3127: iastore
    //   3128: dup
    //   3129: bipush #23
    //   3131: ldc 268701696
    //   3133: iastore
    //   3134: dup
    //   3135: bipush #24
    //   3137: sipush #4160
    //   3140: iastore
    //   3141: dup
    //   3142: bipush #25
    //   3144: iconst_0
    //   3145: iastore
    //   3146: dup
    //   3147: bipush #26
    //   3149: iconst_0
    //   3150: iastore
    //   3151: dup
    //   3152: bipush #27
    //   3154: ldc 268697664
    //   3156: iastore
    //   3157: dup
    //   3158: bipush #28
    //   3160: ldc 268435520
    //   3162: iastore
    //   3163: dup
    //   3164: bipush #29
    //   3166: ldc 268439552
    //   3168: iastore
    //   3169: dup
    //   3170: bipush #30
    //   3172: ldc 266304
    //   3174: iastore
    //   3175: dup
    //   3176: bipush #31
    //   3178: ldc 262144
    //   3180: iastore
    //   3181: dup
    //   3182: bipush #32
    //   3184: ldc 266304
    //   3186: iastore
    //   3187: dup
    //   3188: bipush #33
    //   3190: ldc 262144
    //   3192: iastore
    //   3193: dup
    //   3194: bipush #34
    //   3196: ldc 268701696
    //   3198: iastore
    //   3199: dup
    //   3200: bipush #35
    //   3202: sipush #4096
    //   3205: iastore
    //   3206: dup
    //   3207: bipush #36
    //   3209: bipush #64
    //   3211: iastore
    //   3212: dup
    //   3213: bipush #37
    //   3215: ldc 268697664
    //   3217: iastore
    //   3218: dup
    //   3219: bipush #38
    //   3221: sipush #4096
    //   3224: iastore
    //   3225: dup
    //   3226: bipush #39
    //   3228: ldc 266304
    //   3230: iastore
    //   3231: dup
    //   3232: bipush #40
    //   3234: ldc 268439552
    //   3236: iastore
    //   3237: dup
    //   3238: bipush #41
    //   3240: bipush #64
    //   3242: iastore
    //   3243: dup
    //   3244: bipush #42
    //   3246: ldc 268435520
    //   3248: iastore
    //   3249: dup
    //   3250: bipush #43
    //   3252: ldc 268697600
    //   3254: iastore
    //   3255: dup
    //   3256: bipush #44
    //   3258: ldc 268697664
    //   3260: iastore
    //   3261: dup
    //   3262: bipush #45
    //   3264: ldc 268435456
    //   3266: iastore
    //   3267: dup
    //   3268: bipush #46
    //   3270: ldc 262144
    //   3272: iastore
    //   3273: dup
    //   3274: bipush #47
    //   3276: ldc 268439616
    //   3278: iastore
    //   3279: dup
    //   3280: bipush #48
    //   3282: iconst_0
    //   3283: iastore
    //   3284: dup
    //   3285: bipush #49
    //   3287: ldc 268701760
    //   3289: iastore
    //   3290: dup
    //   3291: bipush #50
    //   3293: ldc 262208
    //   3295: iastore
    //   3296: dup
    //   3297: bipush #51
    //   3299: ldc 268435520
    //   3301: iastore
    //   3302: dup
    //   3303: bipush #52
    //   3305: ldc 268697600
    //   3307: iastore
    //   3308: dup
    //   3309: bipush #53
    //   3311: ldc 268439552
    //   3313: iastore
    //   3314: dup
    //   3315: bipush #54
    //   3317: ldc 268439616
    //   3319: iastore
    //   3320: dup
    //   3321: bipush #55
    //   3323: iconst_0
    //   3324: iastore
    //   3325: dup
    //   3326: bipush #56
    //   3328: ldc 268701760
    //   3330: iastore
    //   3331: dup
    //   3332: bipush #57
    //   3334: ldc 266240
    //   3336: iastore
    //   3337: dup
    //   3338: bipush #58
    //   3340: ldc 266240
    //   3342: iastore
    //   3343: dup
    //   3344: bipush #59
    //   3346: sipush #4160
    //   3349: iastore
    //   3350: dup
    //   3351: bipush #60
    //   3353: sipush #4160
    //   3356: iastore
    //   3357: dup
    //   3358: bipush #61
    //   3360: ldc 262208
    //   3362: iastore
    //   3363: dup
    //   3364: bipush #62
    //   3366: ldc 268435456
    //   3368: iastore
    //   3369: dup
    //   3370: bipush #63
    //   3372: ldc 268701696
    //   3374: iastore
    //   3375: astore #15
    //   3377: aload_3
    //   3378: arraylength
    //   3379: istore #16
    //   3381: iconst_2
    //   3382: newarray int
    //   3384: astore #17
    //   3386: iload #16
    //   3388: newarray byte
    //   3390: astore #4
    //   3392: iload #16
    //   3394: bipush #8
    //   3396: idiv
    //   3397: istore #18
    //   3399: iconst_0
    //   3400: istore #19
    //   3402: iload #19
    //   3404: iload #18
    //   3406: if_icmpge -> 4320
    //   3409: iload #19
    //   3411: bipush #8
    //   3413: imul
    //   3414: istore #20
    //   3416: iconst_0
    //   3417: istore #21
    //   3419: iload #21
    //   3421: iconst_2
    //   3422: if_icmpge -> 3507
    //   3425: aload #17
    //   3427: iload #21
    //   3429: aload_3
    //   3430: iload #20
    //   3432: iload #21
    //   3434: iconst_4
    //   3435: imul
    //   3436: iadd
    //   3437: baload
    //   3438: sipush #255
    //   3441: iand
    //   3442: bipush #24
    //   3444: ishl
    //   3445: aload_3
    //   3446: iload #20
    //   3448: iload #21
    //   3450: iconst_4
    //   3451: imul
    //   3452: iadd
    //   3453: iconst_1
    //   3454: iadd
    //   3455: baload
    //   3456: sipush #255
    //   3459: iand
    //   3460: bipush #16
    //   3462: ishl
    //   3463: ior
    //   3464: aload_3
    //   3465: iload #20
    //   3467: iload #21
    //   3469: iconst_4
    //   3470: imul
    //   3471: iadd
    //   3472: iconst_2
    //   3473: iadd
    //   3474: baload
    //   3475: sipush #255
    //   3478: iand
    //   3479: bipush #8
    //   3481: ishl
    //   3482: ior
    //   3483: aload_3
    //   3484: iload #20
    //   3486: iload #21
    //   3488: iconst_4
    //   3489: imul
    //   3490: iadd
    //   3491: iconst_3
    //   3492: iadd
    //   3493: baload
    //   3494: sipush #255
    //   3497: iand
    //   3498: ior
    //   3499: iastore
    //   3500: iinc #21, 1
    //   3503: iload_2
    //   3504: ifne -> 3419
    //   3507: iconst_0
    //   3508: istore #26
    //   3510: aload #17
    //   3512: iconst_0
    //   3513: iaload
    //   3514: istore #24
    //   3516: aload #17
    //   3518: iconst_1
    //   3519: iaload
    //   3520: istore #23
    //   3522: iload #24
    //   3524: iconst_4
    //   3525: iushr
    //   3526: iload #23
    //   3528: ixor
    //   3529: ldc 252645135
    //   3531: iand
    //   3532: istore #22
    //   3534: iload #23
    //   3536: iload #22
    //   3538: ixor
    //   3539: istore #23
    //   3541: iload #24
    //   3543: iload #22
    //   3545: iconst_4
    //   3546: ishl
    //   3547: ixor
    //   3548: istore #24
    //   3550: iload #24
    //   3552: bipush #16
    //   3554: iushr
    //   3555: iload #23
    //   3557: ixor
    //   3558: ldc 65535
    //   3560: iand
    //   3561: istore #22
    //   3563: iload #23
    //   3565: iload #22
    //   3567: ixor
    //   3568: istore #23
    //   3570: iload #24
    //   3572: iload #22
    //   3574: bipush #16
    //   3576: ishl
    //   3577: ixor
    //   3578: istore #24
    //   3580: iload #23
    //   3582: iconst_2
    //   3583: iushr
    //   3584: iload #24
    //   3586: ixor
    //   3587: ldc 858993459
    //   3589: iand
    //   3590: istore #22
    //   3592: iload #24
    //   3594: iload #22
    //   3596: ixor
    //   3597: istore #24
    //   3599: iload #23
    //   3601: iload #22
    //   3603: iconst_2
    //   3604: ishl
    //   3605: ixor
    //   3606: istore #23
    //   3608: iload #23
    //   3610: bipush #8
    //   3612: iushr
    //   3613: iload #24
    //   3615: ixor
    //   3616: ldc 16711935
    //   3618: iand
    //   3619: istore #22
    //   3621: iload #24
    //   3623: iload #22
    //   3625: ixor
    //   3626: istore #24
    //   3628: iload #23
    //   3630: iload #22
    //   3632: bipush #8
    //   3634: ishl
    //   3635: ixor
    //   3636: istore #23
    //   3638: iload #23
    //   3640: iconst_1
    //   3641: ishl
    //   3642: iload #23
    //   3644: bipush #31
    //   3646: iushr
    //   3647: iconst_1
    //   3648: iand
    //   3649: ior
    //   3650: istore #23
    //   3652: iload #24
    //   3654: iload #23
    //   3656: ixor
    //   3657: ldc -1431655766
    //   3659: iand
    //   3660: istore #22
    //   3662: iload #24
    //   3664: iload #22
    //   3666: ixor
    //   3667: istore #24
    //   3669: iload #23
    //   3671: iload #22
    //   3673: ixor
    //   3674: istore #23
    //   3676: iload #24
    //   3678: iconst_1
    //   3679: ishl
    //   3680: iload #24
    //   3682: bipush #31
    //   3684: iushr
    //   3685: iconst_1
    //   3686: iand
    //   3687: ior
    //   3688: istore #24
    //   3690: iconst_0
    //   3691: istore #25
    //   3693: iload #25
    //   3695: bipush #8
    //   3697: if_icmpge -> 4035
    //   3700: iload #23
    //   3702: bipush #28
    //   3704: ishl
    //   3705: iload #23
    //   3707: iconst_4
    //   3708: iushr
    //   3709: ior
    //   3710: istore #22
    //   3712: iload #22
    //   3714: aload #5
    //   3716: iload #26
    //   3718: iinc #26, 1
    //   3721: iaload
    //   3722: ixor
    //   3723: istore #22
    //   3725: aload #14
    //   3727: iload #22
    //   3729: bipush #63
    //   3731: iand
    //   3732: iaload
    //   3733: istore #21
    //   3735: iload #21
    //   3737: aload #12
    //   3739: iload #22
    //   3741: bipush #8
    //   3743: iushr
    //   3744: bipush #63
    //   3746: iand
    //   3747: iaload
    //   3748: ior
    //   3749: istore #21
    //   3751: iload #21
    //   3753: aload #10
    //   3755: iload #22
    //   3757: bipush #16
    //   3759: iushr
    //   3760: bipush #63
    //   3762: iand
    //   3763: iaload
    //   3764: ior
    //   3765: istore #21
    //   3767: iload #21
    //   3769: aload #8
    //   3771: iload #22
    //   3773: bipush #24
    //   3775: iushr
    //   3776: bipush #63
    //   3778: iand
    //   3779: iaload
    //   3780: ior
    //   3781: istore #21
    //   3783: iload #23
    //   3785: aload #5
    //   3787: iload #26
    //   3789: iinc #26, 1
    //   3792: iaload
    //   3793: ixor
    //   3794: istore #22
    //   3796: iload #21
    //   3798: aload #15
    //   3800: iload #22
    //   3802: bipush #63
    //   3804: iand
    //   3805: iaload
    //   3806: ior
    //   3807: istore #21
    //   3809: iload #21
    //   3811: aload #13
    //   3813: iload #22
    //   3815: bipush #8
    //   3817: iushr
    //   3818: bipush #63
    //   3820: iand
    //   3821: iaload
    //   3822: ior
    //   3823: istore #21
    //   3825: iload #21
    //   3827: aload #11
    //   3829: iload #22
    //   3831: bipush #16
    //   3833: iushr
    //   3834: bipush #63
    //   3836: iand
    //   3837: iaload
    //   3838: ior
    //   3839: istore #21
    //   3841: iload #21
    //   3843: aload #9
    //   3845: iload #22
    //   3847: bipush #24
    //   3849: iushr
    //   3850: bipush #63
    //   3852: iand
    //   3853: iaload
    //   3854: ior
    //   3855: istore #21
    //   3857: iload #24
    //   3859: iload #21
    //   3861: ixor
    //   3862: istore #24
    //   3864: iload #24
    //   3866: bipush #28
    //   3868: ishl
    //   3869: iload #24
    //   3871: iconst_4
    //   3872: iushr
    //   3873: ior
    //   3874: istore #22
    //   3876: iload #22
    //   3878: aload #5
    //   3880: iload #26
    //   3882: iinc #26, 1
    //   3885: iaload
    //   3886: ixor
    //   3887: istore #22
    //   3889: aload #14
    //   3891: iload #22
    //   3893: bipush #63
    //   3895: iand
    //   3896: iaload
    //   3897: istore #21
    //   3899: iload #21
    //   3901: aload #12
    //   3903: iload #22
    //   3905: bipush #8
    //   3907: iushr
    //   3908: bipush #63
    //   3910: iand
    //   3911: iaload
    //   3912: ior
    //   3913: istore #21
    //   3915: iload #21
    //   3917: aload #10
    //   3919: iload #22
    //   3921: bipush #16
    //   3923: iushr
    //   3924: bipush #63
    //   3926: iand
    //   3927: iaload
    //   3928: ior
    //   3929: istore #21
    //   3931: iload #21
    //   3933: aload #8
    //   3935: iload #22
    //   3937: bipush #24
    //   3939: iushr
    //   3940: bipush #63
    //   3942: iand
    //   3943: iaload
    //   3944: ior
    //   3945: istore #21
    //   3947: iload #24
    //   3949: aload #5
    //   3951: iload #26
    //   3953: iinc #26, 1
    //   3956: iaload
    //   3957: ixor
    //   3958: istore #22
    //   3960: iload #21
    //   3962: aload #15
    //   3964: iload #22
    //   3966: bipush #63
    //   3968: iand
    //   3969: iaload
    //   3970: ior
    //   3971: istore #21
    //   3973: iload #21
    //   3975: aload #13
    //   3977: iload #22
    //   3979: bipush #8
    //   3981: iushr
    //   3982: bipush #63
    //   3984: iand
    //   3985: iaload
    //   3986: ior
    //   3987: istore #21
    //   3989: iload #21
    //   3991: aload #11
    //   3993: iload #22
    //   3995: bipush #16
    //   3997: iushr
    //   3998: bipush #63
    //   4000: iand
    //   4001: iaload
    //   4002: ior
    //   4003: istore #21
    //   4005: iload #21
    //   4007: aload #9
    //   4009: iload #22
    //   4011: bipush #24
    //   4013: iushr
    //   4014: bipush #63
    //   4016: iand
    //   4017: iaload
    //   4018: ior
    //   4019: istore #21
    //   4021: iload #23
    //   4023: iload #21
    //   4025: ixor
    //   4026: istore #23
    //   4028: iinc #25, 1
    //   4031: iload_2
    //   4032: ifne -> 3693
    //   4035: iload #23
    //   4037: bipush #31
    //   4039: ishl
    //   4040: iload #23
    //   4042: iconst_1
    //   4043: iushr
    //   4044: ior
    //   4045: istore #23
    //   4047: iload #24
    //   4049: iload #23
    //   4051: ixor
    //   4052: ldc -1431655766
    //   4054: iand
    //   4055: istore #22
    //   4057: iload #24
    //   4059: iload #22
    //   4061: ixor
    //   4062: istore #24
    //   4064: iload #23
    //   4066: iload #22
    //   4068: ixor
    //   4069: istore #23
    //   4071: iload #24
    //   4073: bipush #31
    //   4075: ishl
    //   4076: iload #24
    //   4078: iconst_1
    //   4079: iushr
    //   4080: ior
    //   4081: istore #24
    //   4083: iload #24
    //   4085: bipush #8
    //   4087: iushr
    //   4088: iload #23
    //   4090: ixor
    //   4091: ldc 16711935
    //   4093: iand
    //   4094: istore #22
    //   4096: iload #23
    //   4098: iload #22
    //   4100: ixor
    //   4101: istore #23
    //   4103: iload #24
    //   4105: iload #22
    //   4107: bipush #8
    //   4109: ishl
    //   4110: ixor
    //   4111: istore #24
    //   4113: iload #24
    //   4115: iconst_2
    //   4116: iushr
    //   4117: iload #23
    //   4119: ixor
    //   4120: ldc 858993459
    //   4122: iand
    //   4123: istore #22
    //   4125: iload #23
    //   4127: iload #22
    //   4129: ixor
    //   4130: istore #23
    //   4132: iload #24
    //   4134: iload #22
    //   4136: iconst_2
    //   4137: ishl
    //   4138: ixor
    //   4139: istore #24
    //   4141: iload #23
    //   4143: bipush #16
    //   4145: iushr
    //   4146: iload #24
    //   4148: ixor
    //   4149: ldc 65535
    //   4151: iand
    //   4152: istore #22
    //   4154: iload #24
    //   4156: iload #22
    //   4158: ixor
    //   4159: istore #24
    //   4161: iload #23
    //   4163: iload #22
    //   4165: bipush #16
    //   4167: ishl
    //   4168: ixor
    //   4169: istore #23
    //   4171: iload #23
    //   4173: iconst_4
    //   4174: iushr
    //   4175: iload #24
    //   4177: ixor
    //   4178: ldc 252645135
    //   4180: iand
    //   4181: istore #22
    //   4183: iload #24
    //   4185: iload #22
    //   4187: ixor
    //   4188: istore #24
    //   4190: iload #23
    //   4192: iload #22
    //   4194: iconst_4
    //   4195: ishl
    //   4196: ixor
    //   4197: istore #23
    //   4199: aload #17
    //   4201: iconst_0
    //   4202: iload #23
    //   4204: iastore
    //   4205: aload #17
    //   4207: iconst_1
    //   4208: iload #24
    //   4210: iastore
    //   4211: iload #19
    //   4213: bipush #8
    //   4215: imul
    //   4216: istore #27
    //   4218: iconst_0
    //   4219: istore #28
    //   4221: iload #28
    //   4223: iconst_2
    //   4224: if_icmpge -> 4313
    //   4227: aload #4
    //   4229: iload #27
    //   4231: iload #28
    //   4233: iconst_4
    //   4234: imul
    //   4235: iadd
    //   4236: aload #17
    //   4238: iload #28
    //   4240: iaload
    //   4241: bipush #24
    //   4243: iushr
    //   4244: i2b
    //   4245: bastore
    //   4246: aload #4
    //   4248: iload #27
    //   4250: iload #28
    //   4252: iconst_4
    //   4253: imul
    //   4254: iadd
    //   4255: iconst_1
    //   4256: iadd
    //   4257: aload #17
    //   4259: iload #28
    //   4261: iaload
    //   4262: bipush #16
    //   4264: iushr
    //   4265: i2b
    //   4266: bastore
    //   4267: aload #4
    //   4269: iload #27
    //   4271: iload #28
    //   4273: iconst_4
    //   4274: imul
    //   4275: iadd
    //   4276: iconst_2
    //   4277: iadd
    //   4278: aload #17
    //   4280: iload #28
    //   4282: iaload
    //   4283: bipush #8
    //   4285: iushr
    //   4286: i2b
    //   4287: bastore
    //   4288: aload #4
    //   4290: iload #27
    //   4292: iload #28
    //   4294: iconst_4
    //   4295: imul
    //   4296: iadd
    //   4297: iconst_3
    //   4298: iadd
    //   4299: aload #17
    //   4301: iload #28
    //   4303: iaload
    //   4304: i2b
    //   4305: bastore
    //   4306: iinc #28, 1
    //   4309: iload_2
    //   4310: ifne -> 4221
    //   4313: iinc #19, 1
    //   4316: iload_2
    //   4317: ifne -> 3402
    //   4320: new java/math/BigInteger
    //   4323: dup
    //   4324: aload #4
    //   4326: invokespecial <init> : ([B)V
    //   4329: invokevirtual abs : ()Ljava/math/BigInteger;
    //   4332: putstatic burp/Zb6b.ZU : Ljava/lang/Object;
    //   4335: new java/lang/StringBuilder
    //   4338: dup
    //   4339: invokespecial <init> : ()V
    //   4342: astore_3
    //   4343: iconst_0
    //   4344: istore #4
    //   4346: iload #4
    //   4348: bipush #32
    //   4350: if_icmpge -> 5683
    //   4353: iload #4
    //   4355: tableswitch default -> 5676, 0 -> 4496, 1 -> 4533, 2 -> 4570, 3 -> 4607, 4 -> 4644, 5 -> 4681, 6 -> 4718, 7 -> 4755, 8 -> 4792, 9 -> 4829, 10 -> 4866, 11 -> 4903, 12 -> 4940, 13 -> 4977, 14 -> 5014, 15 -> 5051, 16 -> 5088, 17 -> 5125, 18 -> 5162, 19 -> 5199, 20 -> 5236, 21 -> 5273, 22 -> 5310, 23 -> 5347, 24 -> 5384, 25 -> 5421, 26 -> 5458, 27 -> 5495, 28 -> 5532, 29 -> 5569, 30 -> 5606, 31 -> 5643
    //   4496: aload_3
    //   4497: getstatic burp/Ze_b.ZX : Ljava/lang/String;
    //   4500: getstatic burp/Zero.ZE : Ljava/lang/Object;
    //   4503: checkcast java/math/BigInteger
    //   4506: invokevirtual intValue : ()I
    //   4509: bipush #32
    //   4511: irem
    //   4512: invokestatic abs : (I)I
    //   4515: invokevirtual charAt : (I)C
    //   4518: invokevirtual append : (C)Ljava/lang/StringBuilder;
    //   4521: pop
    //   4522: iload_2
    //   4523: ifne -> 5676
    //   4526: goto -> 4533
    //   4529: invokestatic a : (Ljava/lang/Throwable;)Ljava/lang/Throwable;
    //   4532: athrow
    //   4533: aload_3
    //   4534: getstatic burp/Zl3n.Zy : Ljava/lang/String;
    //   4537: getstatic burp/Zkhy.Zc : Ljava/lang/Object;
    //   4540: checkcast java/math/BigInteger
    //   4543: invokevirtual intValue : ()I
    //   4546: bipush #32
    //   4548: irem
    //   4549: invokestatic abs : (I)I
    //   4552: invokevirtual charAt : (I)C
    //   4555: invokevirtual append : (C)Ljava/lang/StringBuilder;
    //   4558: pop
    //   4559: iload_2
    //   4560: ifne -> 5676
    //   4563: goto -> 4570
    //   4566: invokestatic a : (Ljava/lang/Throwable;)Ljava/lang/Throwable;
    //   4569: athrow
    //   4570: aload_3
    //   4571: getstatic burp/Zr8s.ZA : Ljava/lang/String;
    //   4574: getstatic burp/Zm84.Zf : Ljava/lang/Object;
    //   4577: checkcast java/math/BigInteger
    //   4580: invokevirtual intValue : ()I
    //   4583: bipush #32
    //   4585: irem
    //   4586: invokestatic abs : (I)I
    //   4589: invokevirtual charAt : (I)C
    //   4592: invokevirtual append : (C)Ljava/lang/StringBuilder;
    //   4595: pop
    //   4596: iload_2
    //   4597: ifne -> 5676
    //   4600: goto -> 4607
    //   4603: invokestatic a : (Ljava/lang/Throwable;)Ljava/lang/Throwable;
    //   4606: athrow
    //   4607: aload_3
    //   4608: getstatic burp/Zr9p.Za : Ljava/lang/String;
    //   4611: getstatic burp/Ztev.Zr : Ljava/lang/Object;
    //   4614: checkcast java/math/BigInteger
    //   4617: invokevirtual intValue : ()I
    //   4620: bipush #32
    //   4622: irem
    //   4623: invokestatic abs : (I)I
    //   4626: invokevirtual charAt : (I)C
    //   4629: invokevirtual append : (C)Ljava/lang/StringBuilder;
    //   4632: pop
    //   4633: iload_2
    //   4634: ifne -> 5676
    //   4637: goto -> 4644
    //   4640: invokestatic a : (Ljava/lang/Throwable;)Ljava/lang/Throwable;
    //   4643: athrow
    //   4644: aload_3
    //   4645: getstatic burp/Zetv.ZE : Ljava/lang/String;
    //   4648: getstatic burp/Ztmy.ZH : Ljava/lang/Object;
    //   4651: checkcast java/math/BigInteger
    //   4654: invokevirtual intValue : ()I
    //   4657: bipush #32
    //   4659: irem
    //   4660: invokestatic abs : (I)I
    //   4663: invokevirtual charAt : (I)C
    //   4666: invokevirtual append : (C)Ljava/lang/StringBuilder;
    //   4669: pop
    //   4670: iload_2
    //   4671: ifne -> 5676
    //   4674: goto -> 4681
    //   4677: invokestatic a : (Ljava/lang/Throwable;)Ljava/lang/Throwable;
    //   4680: athrow
    //   4681: aload_3
    //   4682: getstatic burp/Zlhz.Zo : Ljava/lang/String;
    //   4685: getstatic burp/Zrxm.ZL : Ljava/lang/Object;
    //   4688: checkcast java/math/BigInteger
    //   4691: invokevirtual intValue : ()I
    //   4694: bipush #32
    //   4696: irem
    //   4697: invokestatic abs : (I)I
    //   4700: invokevirtual charAt : (I)C
    //   4703: invokevirtual append : (C)Ljava/lang/StringBuilder;
    //   4706: pop
    //   4707: iload_2
    //   4708: ifne -> 5676
    //   4711: goto -> 4718
    //   4714: invokestatic a : (Ljava/lang/Throwable;)Ljava/lang/Throwable;
    //   4717: athrow
    //   4718: aload_3
    //   4719: getstatic burp/Ze0w.ZT : Ljava/lang/String;
    //   4722: getstatic burp/Zl3n.Zh : Ljava/lang/Object;
    //   4725: checkcast java/math/BigInteger
    //   4728: invokevirtual intValue : ()I
    //   4731: bipush #32
    //   4733: irem
    //   4734: invokestatic abs : (I)I
    //   4737: invokevirtual charAt : (I)C
    //   4740: invokevirtual append : (C)Ljava/lang/StringBuilder;
    //   4743: pop
    //   4744: iload_2
    //   4745: ifne -> 5676
    //   4748: goto -> 4755
    //   4751: invokestatic a : (Ljava/lang/Throwable;)Ljava/lang/Throwable;
    //   4754: athrow
    //   4755: aload_3
    //   4756: getstatic burp/Zgvl.Zc : Ljava/lang/String;
    //   4759: getstatic burp/Zct.ZW : Ljava/lang/Object;
    //   4762: checkcast java/math/BigInteger
    //   4765: invokevirtual intValue : ()I
    //   4768: bipush #32
    //   4770: irem
    //   4771: invokestatic abs : (I)I
    //   4774: invokevirtual charAt : (I)C
    //   4777: invokevirtual append : (C)Ljava/lang/StringBuilder;
    //   4780: pop
    //   4781: iload_2
    //   4782: ifne -> 5676
    //   4785: goto -> 4792
    //   4788: invokestatic a : (Ljava/lang/Throwable;)Ljava/lang/Throwable;
    //   4791: athrow
    //   4792: aload_3
    //   4793: getstatic burp/Zrd0.Zk : Ljava/lang/String;
    //   4796: getstatic burp/Zek5.ZP : Ljava/lang/Object;
    //   4799: checkcast java/math/BigInteger
    //   4802: invokevirtual intValue : ()I
    //   4805: bipush #32
    //   4807: irem
    //   4808: invokestatic abs : (I)I
    //   4811: invokevirtual charAt : (I)C
    //   4814: invokevirtual append : (C)Ljava/lang/StringBuilder;
    //   4817: pop
    //   4818: iload_2
    //   4819: ifne -> 5676
    //   4822: goto -> 4829
    //   4825: invokestatic a : (Ljava/lang/Throwable;)Ljava/lang/Throwable;
    //   4828: athrow
    //   4829: aload_3
    //   4830: getstatic burp/Zxdh.Zj : Ljava/lang/String;
    //   4833: getstatic burp/Zete.Zm : Ljava/lang/Object;
    //   4836: checkcast java/math/BigInteger
    //   4839: invokevirtual intValue : ()I
    //   4842: bipush #32
    //   4844: irem
    //   4845: invokestatic abs : (I)I
    //   4848: invokevirtual charAt : (I)C
    //   4851: invokevirtual append : (C)Ljava/lang/StringBuilder;
    //   4854: pop
    //   4855: iload_2
    //   4856: ifne -> 5676
    //   4859: goto -> 4866
    //   4862: invokestatic a : (Ljava/lang/Throwable;)Ljava/lang/Throwable;
    //   4865: athrow
    //   4866: aload_3
    //   4867: getstatic burp/Zmh5.Zh : Ljava/lang/String;
    //   4870: getstatic burp/Zl5b.ZI : Ljava/lang/Object;
    //   4873: checkcast java/math/BigInteger
    //   4876: invokevirtual intValue : ()I
    //   4879: bipush #32
    //   4881: irem
    //   4882: invokestatic abs : (I)I
    //   4885: invokevirtual charAt : (I)C
    //   4888: invokevirtual append : (C)Ljava/lang/StringBuilder;
    //   4891: pop
    //   4892: iload_2
    //   4893: ifne -> 5676
    //   4896: goto -> 4903
    //   4899: invokestatic a : (Ljava/lang/Throwable;)Ljava/lang/Throwable;
    //   4902: athrow
    //   4903: aload_3
    //   4904: getstatic burp/Zkcd.Zj : Ljava/lang/String;
    //   4907: getstatic burp/Zgvf.Zd : Ljava/lang/Object;
    //   4910: checkcast java/math/BigInteger
    //   4913: invokevirtual intValue : ()I
    //   4916: bipush #32
    //   4918: irem
    //   4919: invokestatic abs : (I)I
    //   4922: invokevirtual charAt : (I)C
    //   4925: invokevirtual append : (C)Ljava/lang/StringBuilder;
    //   4928: pop
    //   4929: iload_2
    //   4930: ifne -> 5676
    //   4933: goto -> 4940
    //   4936: invokestatic a : (Ljava/lang/Throwable;)Ljava/lang/Throwable;
    //   4939: athrow
    //   4940: aload_3
    //   4941: getstatic burp/Zl3l.Z_ : Ljava/lang/String;
    //   4944: getstatic burp/Zs9k.ZX : Ljava/lang/Object;
    //   4947: checkcast java/math/BigInteger
    //   4950: invokevirtual intValue : ()I
    //   4953: bipush #32
    //   4955: irem
    //   4956: invokestatic abs : (I)I
    //   4959: invokevirtual charAt : (I)C
    //   4962: invokevirtual append : (C)Ljava/lang/StringBuilder;
    //   4965: pop
    //   4966: iload_2
    //   4967: ifne -> 5676
    //   4970: goto -> 4977
    //   4973: invokestatic a : (Ljava/lang/Throwable;)Ljava/lang/Throwable;
    //   4976: athrow
    //   4977: aload_3
    //   4978: getstatic burp/Zgkp.ZS : Ljava/lang/String;
    //   4981: getstatic burp/Zlxm.Zc : Ljava/lang/Object;
    //   4984: checkcast java/math/BigInteger
    //   4987: invokevirtual intValue : ()I
    //   4990: bipush #32
    //   4992: irem
    //   4993: invokestatic abs : (I)I
    //   4996: invokevirtual charAt : (I)C
    //   4999: invokevirtual append : (C)Ljava/lang/StringBuilder;
    //   5002: pop
    //   5003: iload_2
    //   5004: ifne -> 5676
    //   5007: goto -> 5014
    //   5010: invokestatic a : (Ljava/lang/Throwable;)Ljava/lang/Throwable;
    //   5013: athrow
    //   5014: aload_3
    //   5015: getstatic burp/Zetv.ZE : Ljava/lang/String;
    //   5018: getstatic burp/Zkcd.ZE : Ljava/lang/Object;
    //   5021: checkcast java/math/BigInteger
    //   5024: invokevirtual intValue : ()I
    //   5027: bipush #32
    //   5029: irem
    //   5030: invokestatic abs : (I)I
    //   5033: invokevirtual charAt : (I)C
    //   5036: invokevirtual append : (C)Ljava/lang/StringBuilder;
    //   5039: pop
    //   5040: iload_2
    //   5041: ifne -> 5676
    //   5044: goto -> 5051
    //   5047: invokestatic a : (Ljava/lang/Throwable;)Ljava/lang/Throwable;
    //   5050: athrow
    //   5051: aload_3
    //   5052: getstatic burp/Ztt0.Zl : Ljava/lang/String;
    //   5055: getstatic burp/Zezq.Zu : Ljava/lang/Object;
    //   5058: checkcast java/math/BigInteger
    //   5061: invokevirtual intValue : ()I
    //   5064: bipush #32
    //   5066: irem
    //   5067: invokestatic abs : (I)I
    //   5070: invokevirtual charAt : (I)C
    //   5073: invokevirtual append : (C)Ljava/lang/StringBuilder;
    //   5076: pop
    //   5077: iload_2
    //   5078: ifne -> 5676
    //   5081: goto -> 5088
    //   5084: invokestatic a : (Ljava/lang/Throwable;)Ljava/lang/Throwable;
    //   5087: athrow
    //   5088: aload_3
    //   5089: getstatic burp/Zkdc.Zc : Ljava/lang/String;
    //   5092: getstatic burp/Zb29.ZM : Ljava/lang/Object;
    //   5095: checkcast java/math/BigInteger
    //   5098: invokevirtual intValue : ()I
    //   5101: bipush #32
    //   5103: irem
    //   5104: invokestatic abs : (I)I
    //   5107: invokevirtual charAt : (I)C
    //   5110: invokevirtual append : (C)Ljava/lang/StringBuilder;
    //   5113: pop
    //   5114: iload_2
    //   5115: ifne -> 5676
    //   5118: goto -> 5125
    //   5121: invokestatic a : (Ljava/lang/Throwable;)Ljava/lang/Throwable;
    //   5124: athrow
    //   5125: aload_3
    //   5126: getstatic burp/Zlzo.Zs : Ljava/lang/String;
    //   5129: getstatic burp/Ze0w.ZU : Ljava/lang/Object;
    //   5132: checkcast java/math/BigInteger
    //   5135: invokevirtual intValue : ()I
    //   5138: bipush #32
    //   5140: irem
    //   5141: invokestatic abs : (I)I
    //   5144: invokevirtual charAt : (I)C
    //   5147: invokevirtual append : (C)Ljava/lang/StringBuilder;
    //   5150: pop
    //   5151: iload_2
    //   5152: ifne -> 5676
    //   5155: goto -> 5162
    //   5158: invokestatic a : (Ljava/lang/Throwable;)Ljava/lang/Throwable;
    //   5161: athrow
    //   5162: aload_3
    //   5163: getstatic burp/Zeno.ZL : Ljava/lang/String;
    //   5166: getstatic burp/Zgj5.ZO : Ljava/lang/Object;
    //   5169: checkcast java/math/BigInteger
    //   5172: invokevirtual intValue : ()I
    //   5175: bipush #32
    //   5177: irem
    //   5178: invokestatic abs : (I)I
    //   5181: invokevirtual charAt : (I)C
    //   5184: invokevirtual append : (C)Ljava/lang/StringBuilder;
    //   5187: pop
    //   5188: iload_2
    //   5189: ifne -> 5676
    //   5192: goto -> 5199
    //   5195: invokestatic a : (Ljava/lang/Throwable;)Ljava/lang/Throwable;
    //   5198: athrow
    //   5199: aload_3
    //   5200: getstatic burp/Zrkc.ZE : Ljava/lang/String;
    //   5203: getstatic burp/Zl5b.ZI : Ljava/lang/Object;
    //   5206: checkcast java/math/BigInteger
    //   5209: invokevirtual intValue : ()I
    //   5212: bipush #32
    //   5214: irem
    //   5215: invokestatic abs : (I)I
    //   5218: invokevirtual charAt : (I)C
    //   5221: invokevirtual append : (C)Ljava/lang/StringBuilder;
    //   5224: pop
    //   5225: iload_2
    //   5226: ifne -> 5676
    //   5229: goto -> 5236
    //   5232: invokestatic a : (Ljava/lang/Throwable;)Ljava/lang/Throwable;
    //   5235: athrow
    //   5236: aload_3
    //   5237: getstatic burp/Zlxm.Zv : Ljava/lang/String;
    //   5240: getstatic burp/Zgkp.Zp : Ljava/lang/Object;
    //   5243: checkcast java/math/BigInteger
    //   5246: invokevirtual intValue : ()I
    //   5249: bipush #32
    //   5251: irem
    //   5252: invokestatic abs : (I)I
    //   5255: invokevirtual charAt : (I)C
    //   5258: invokevirtual append : (C)Ljava/lang/StringBuilder;
    //   5261: pop
    //   5262: iload_2
    //   5263: ifne -> 5676
    //   5266: goto -> 5273
    //   5269: invokestatic a : (Ljava/lang/Throwable;)Ljava/lang/Throwable;
    //   5272: athrow
    //   5273: aload_3
    //   5274: getstatic burp/Zm84.Zd : Ljava/lang/String;
    //   5277: getstatic burp/Zx4k.ZE : Ljava/lang/Object;
    //   5280: checkcast java/math/BigInteger
    //   5283: invokevirtual intValue : ()I
    //   5286: bipush #32
    //   5288: irem
    //   5289: invokestatic abs : (I)I
    //   5292: invokevirtual charAt : (I)C
    //   5295: invokevirtual append : (C)Ljava/lang/StringBuilder;
    //   5298: pop
    //   5299: iload_2
    //   5300: ifne -> 5676
    //   5303: goto -> 5310
    //   5306: invokestatic a : (Ljava/lang/Throwable;)Ljava/lang/Throwable;
    //   5309: athrow
    //   5310: aload_3
    //   5311: getstatic burp/Zct.Zy : Ljava/lang/String;
    //   5314: getstatic burp/Zrkc.ZI : Ljava/lang/Object;
    //   5317: checkcast java/math/BigInteger
    //   5320: invokevirtual intValue : ()I
    //   5323: bipush #32
    //   5325: irem
    //   5326: invokestatic abs : (I)I
    //   5329: invokevirtual charAt : (I)C
    //   5332: invokevirtual append : (C)Ljava/lang/StringBuilder;
    //   5335: pop
    //   5336: iload_2
    //   5337: ifne -> 5676
    //   5340: goto -> 5347
    //   5343: invokestatic a : (Ljava/lang/Throwable;)Ljava/lang/Throwable;
    //   5346: athrow
    //   5347: aload_3
    //   5348: getstatic burp/Zlzo.Zs : Ljava/lang/String;
    //   5351: getstatic burp/Zsq5.ZF : Ljava/lang/Object;
    //   5354: checkcast java/math/BigInteger
    //   5357: invokevirtual intValue : ()I
    //   5360: bipush #32
    //   5362: irem
    //   5363: invokestatic abs : (I)I
    //   5366: invokevirtual charAt : (I)C
    //   5369: invokevirtual append : (C)Ljava/lang/StringBuilder;
    //   5372: pop
    //   5373: iload_2
    //   5374: ifne -> 5676
    //   5377: goto -> 5384
    //   5380: invokestatic a : (Ljava/lang/Throwable;)Ljava/lang/Throwable;
    //   5383: athrow
    //   5384: aload_3
    //   5385: getstatic burp/Zx4k.ZC : Ljava/lang/String;
    //   5388: getstatic burp/Zgwh.Zl : Ljava/lang/Object;
    //   5391: checkcast java/math/BigInteger
    //   5394: invokevirtual intValue : ()I
    //   5397: bipush #32
    //   5399: irem
    //   5400: invokestatic abs : (I)I
    //   5403: invokevirtual charAt : (I)C
    //   5406: invokevirtual append : (C)Ljava/lang/StringBuilder;
    //   5409: pop
    //   5410: iload_2
    //   5411: ifne -> 5676
    //   5414: goto -> 5421
    //   5417: invokestatic a : (Ljava/lang/Throwable;)Ljava/lang/Throwable;
    //   5420: athrow
    //   5421: aload_3
    //   5422: getstatic burp/Zldx.Zm : Ljava/lang/String;
    //   5425: getstatic burp/Zero.ZE : Ljava/lang/Object;
    //   5428: checkcast java/math/BigInteger
    //   5431: invokevirtual intValue : ()I
    //   5434: bipush #32
    //   5436: irem
    //   5437: invokestatic abs : (I)I
    //   5440: invokevirtual charAt : (I)C
    //   5443: invokevirtual append : (C)Ljava/lang/StringBuilder;
    //   5446: pop
    //   5447: iload_2
    //   5448: ifne -> 5676
    //   5451: goto -> 5458
    //   5454: invokestatic a : (Ljava/lang/Throwable;)Ljava/lang/Throwable;
    //   5457: athrow
    //   5458: aload_3
    //   5459: getstatic burp/Zl3n.Zy : Ljava/lang/String;
    //   5462: getstatic burp/Zgvf.Zd : Ljava/lang/Object;
    //   5465: checkcast java/math/BigInteger
    //   5468: invokevirtual intValue : ()I
    //   5471: bipush #32
    //   5473: irem
    //   5474: invokestatic abs : (I)I
    //   5477: invokevirtual charAt : (I)C
    //   5480: invokevirtual append : (C)Ljava/lang/StringBuilder;
    //   5483: pop
    //   5484: iload_2
    //   5485: ifne -> 5676
    //   5488: goto -> 5495
    //   5491: invokestatic a : (Ljava/lang/Throwable;)Ljava/lang/Throwable;
    //   5494: athrow
    //   5495: aload_3
    //   5496: getstatic burp/Zb6b.Zn : Ljava/lang/String;
    //   5499: getstatic burp/Zgj5.ZO : Ljava/lang/Object;
    //   5502: checkcast java/math/BigInteger
    //   5505: invokevirtual intValue : ()I
    //   5508: bipush #32
    //   5510: irem
    //   5511: invokestatic abs : (I)I
    //   5514: invokevirtual charAt : (I)C
    //   5517: invokevirtual append : (C)Ljava/lang/StringBuilder;
    //   5520: pop
    //   5521: iload_2
    //   5522: ifne -> 5676
    //   5525: goto -> 5532
    //   5528: invokestatic a : (Ljava/lang/Throwable;)Ljava/lang/Throwable;
    //   5531: athrow
    //   5532: aload_3
    //   5533: getstatic burp/Zl3n.Zy : Ljava/lang/String;
    //   5536: getstatic burp/Zmh5.ZN : Ljava/lang/Object;
    //   5539: checkcast java/math/BigInteger
    //   5542: invokevirtual intValue : ()I
    //   5545: bipush #32
    //   5547: irem
    //   5548: invokestatic abs : (I)I
    //   5551: invokevirtual charAt : (I)C
    //   5554: invokevirtual append : (C)Ljava/lang/StringBuilder;
    //   5557: pop
    //   5558: iload_2
    //   5559: ifne -> 5676
    //   5562: goto -> 5569
    //   5565: invokestatic a : (Ljava/lang/Throwable;)Ljava/lang/Throwable;
    //   5568: athrow
    //   5569: aload_3
    //   5570: getstatic burp/Zryq.Zb : Ljava/lang/String;
    //   5573: getstatic burp/Zz5d.Zk : Ljava/lang/Object;
    //   5576: checkcast java/math/BigInteger
    //   5579: invokevirtual intValue : ()I
    //   5582: bipush #32
    //   5584: irem
    //   5585: invokestatic abs : (I)I
    //   5588: invokevirtual charAt : (I)C
    //   5591: invokevirtual append : (C)Ljava/lang/StringBuilder;
    //   5594: pop
    //   5595: iload_2
    //   5596: ifne -> 5676
    //   5599: goto -> 5606
    //   5602: invokestatic a : (Ljava/lang/Throwable;)Ljava/lang/Throwable;
    //   5605: athrow
    //   5606: aload_3
    //   5607: getstatic burp/Zeu2.ZK : Ljava/lang/String;
    //   5610: getstatic burp/Zz3k.Zz : Ljava/lang/Object;
    //   5613: checkcast java/math/BigInteger
    //   5616: invokevirtual intValue : ()I
    //   5619: bipush #32
    //   5621: irem
    //   5622: invokestatic abs : (I)I
    //   5625: invokevirtual charAt : (I)C
    //   5628: invokevirtual append : (C)Ljava/lang/StringBuilder;
    //   5631: pop
    //   5632: iload_2
    //   5633: ifne -> 5676
    //   5636: goto -> 5643
    //   5639: invokestatic a : (Ljava/lang/Throwable;)Ljava/lang/Throwable;
    //   5642: athrow
    //   5643: aload_3
    //   5644: getstatic burp/Zlpl.ZO : Ljava/lang/String;
    //   5647: getstatic burp/Zgvl.ZK : Ljava/lang/Object;
    //   5650: checkcast java/math/BigInteger
    //   5653: invokevirtual intValue : ()I
    //   5656: bipush #32
    //   5658: irem
    //   5659: invokestatic abs : (I)I
    //   5662: invokevirtual charAt : (I)C
    //   5665: invokevirtual append : (C)Ljava/lang/StringBuilder;
    //   5668: pop
    //   5669: goto -> 5676
    //   5672: invokestatic a : (Ljava/lang/Throwable;)Ljava/lang/Throwable;
    //   5675: athrow
    //   5676: iinc #4, 1
    //   5679: iload_2
    //   5680: ifne -> 4346
    //   5683: aload_3
    //   5684: invokevirtual toString : ()Ljava/lang/String;
    //   5687: putstatic burp/Zgkp.ZS : Ljava/lang/String;
    //   5690: getstatic burp/Zrxm.ZL : Ljava/lang/Object;
    //   5693: checkcast java/math/BigInteger
    //   5696: invokevirtual toByteArray : ()[B
    //   5699: astore #4
    //   5701: aload #4
    //   5703: arraylength
    //   5704: bipush #8
    //   5706: iadd
    //   5707: bipush #6
    //   5709: ishr
    //   5710: iconst_1
    //   5711: iadd
    //   5712: bipush #16
    //   5714: imul
    //   5715: newarray int
    //   5717: astore #6
    //   5719: iconst_0
    //   5720: istore #7
    //   5722: iload #7
    //   5724: aload #4
    //   5726: arraylength
    //   5727: if_icmpge -> 5771
    //   5730: aload #4
    //   5732: iload #7
    //   5734: baload
    //   5735: sipush #255
    //   5738: iand
    //   5739: istore #8
    //   5741: aload #6
    //   5743: iload #7
    //   5745: iconst_2
    //   5746: ishr
    //   5747: dup2
    //   5748: iaload
    //   5749: iload #8
    //   5751: bipush #24
    //   5753: iload #7
    //   5755: iconst_4
    //   5756: irem
    //   5757: bipush #8
    //   5759: imul
    //   5760: isub
    //   5761: ishl
    //   5762: ior
    //   5763: iastore
    //   5764: iinc #7, 1
    //   5767: iload_2
    //   5768: ifne -> 5722
    //   5771: aload #6
    //   5773: iload #7
    //   5775: iconst_2
    //   5776: ishr
    //   5777: dup2
    //   5778: iaload
    //   5779: sipush #128
    //   5782: bipush #24
    //   5784: iload #7
    //   5786: iconst_4
    //   5787: irem
    //   5788: bipush #8
    //   5790: imul
    //   5791: isub
    //   5792: ishl
    //   5793: ior
    //   5794: iastore
    //   5795: aload #6
    //   5797: aload #6
    //   5799: arraylength
    //   5800: iconst_1
    //   5801: isub
    //   5802: aload #4
    //   5804: arraylength
    //   5805: bipush #8
    //   5807: imul
    //   5808: iastore
    //   5809: bipush #80
    //   5811: newarray int
    //   5813: astore #8
    //   5815: ldc 1732584193
    //   5817: istore #9
    //   5819: ldc -271733879
    //   5821: istore #10
    //   5823: ldc -1732584194
    //   5825: istore #11
    //   5827: ldc 271733878
    //   5829: istore #12
    //   5831: ldc -1009589776
    //   5833: istore #13
    //   5835: iconst_0
    //   5836: istore #7
    //   5838: iload #7
    //   5840: aload #6
    //   5842: arraylength
    //   5843: if_icmpge -> 6165
    //   5846: iload #9
    //   5848: istore #14
    //   5850: iload #10
    //   5852: istore #15
    //   5854: iload #11
    //   5856: istore #16
    //   5858: iload #12
    //   5860: istore #17
    //   5862: iload #13
    //   5864: istore #18
    //   5866: iconst_0
    //   5867: istore #19
    //   5869: iload #19
    //   5871: bipush #80
    //   5873: if_icmpge -> 6123
    //   5876: iload #19
    //   5878: bipush #16
    //   5880: if_icmpge -> 5907
    //   5883: aload #8
    //   5885: iload #19
    //   5887: aload #6
    //   5889: iload #7
    //   5891: iload #19
    //   5893: iadd
    //   5894: iaload
    //   5895: iastore
    //   5896: iload_2
    //   5897: ifne -> 5962
    //   5900: goto -> 5907
    //   5903: invokestatic a : (Ljava/lang/Throwable;)Ljava/lang/Throwable;
    //   5906: athrow
    //   5907: aload #8
    //   5909: iload #19
    //   5911: iconst_3
    //   5912: isub
    //   5913: iaload
    //   5914: aload #8
    //   5916: iload #19
    //   5918: bipush #8
    //   5920: isub
    //   5921: iaload
    //   5922: ixor
    //   5923: aload #8
    //   5925: iload #19
    //   5927: bipush #14
    //   5929: isub
    //   5930: iaload
    //   5931: ixor
    //   5932: aload #8
    //   5934: iload #19
    //   5936: bipush #16
    //   5938: isub
    //   5939: iaload
    //   5940: ixor
    //   5941: istore #20
    //   5943: iload #20
    //   5945: iconst_1
    //   5946: ishl
    //   5947: iload #20
    //   5949: bipush #31
    //   5951: iushr
    //   5952: ior
    //   5953: istore #21
    //   5955: aload #8
    //   5957: iload #19
    //   5959: iload #21
    //   5961: iastore
    //   5962: iload #9
    //   5964: iconst_5
    //   5965: ishl
    //   5966: iload #9
    //   5968: bipush #27
    //   5970: iushr
    //   5971: ior
    //   5972: istore #20
    //   5974: iload #20
    //   5976: iload #13
    //   5978: iadd
    //   5979: aload #8
    //   5981: iload #19
    //   5983: iaload
    //   5984: iadd
    //   5985: iload #19
    //   5987: bipush #20
    //   5989: if_icmpge -> 6015
    //   5992: ldc 1518500249
    //   5994: iload #10
    //   5996: iload #11
    //   5998: iand
    //   5999: iload #10
    //   6001: iconst_m1
    //   6002: ixor
    //   6003: iload #12
    //   6005: iand
    //   6006: ior
    //   6007: iadd
    //   6008: goto -> 6085
    //   6011: invokestatic a : (Ljava/lang/Throwable;)Ljava/lang/Throwable;
    //   6014: athrow
    //   6015: iload #19
    //   6017: bipush #40
    //   6019: if_icmpge -> 6040
    //   6022: ldc 1859775393
    //   6024: iload #10
    //   6026: iload #11
    //   6028: ixor
    //   6029: iload #12
    //   6031: ixor
    //   6032: iadd
    //   6033: goto -> 6085
    //   6036: invokestatic a : (Ljava/lang/Throwable;)Ljava/lang/Throwable;
    //   6039: athrow
    //   6040: iload #19
    //   6042: bipush #60
    //   6044: if_icmpge -> 6074
    //   6047: ldc -1894007588
    //   6049: iload #10
    //   6051: iload #11
    //   6053: iand
    //   6054: iload #10
    //   6056: iload #12
    //   6058: iand
    //   6059: ior
    //   6060: iload #11
    //   6062: iload #12
    //   6064: iand
    //   6065: ior
    //   6066: iadd
    //   6067: goto -> 6085
    //   6070: invokestatic a : (Ljava/lang/Throwable;)Ljava/lang/Throwable;
    //   6073: athrow
    //   6074: ldc -899497514
    //   6076: iload #10
    //   6078: iload #11
    //   6080: ixor
    //   6081: iload #12
    //   6083: ixor
    //   6084: iadd
    //   6085: iadd
    //   6086: istore #21
    //   6088: iload #12
    //   6090: istore #13
    //   6092: iload #11
    //   6094: istore #12
    //   6096: iload #10
    //   6098: bipush #30
    //   6100: ishl
    //   6101: iload #10
    //   6103: iconst_2
    //   6104: iushr
    //   6105: ior
    //   6106: istore #11
    //   6108: iload #9
    //   6110: istore #10
    //   6112: iload #21
    //   6114: istore #9
    //   6116: iinc #19, 1
    //   6119: iload_2
    //   6120: ifne -> 5869
    //   6123: iload #9
    //   6125: iload #14
    //   6127: iadd
    //   6128: istore #9
    //   6130: iload #10
    //   6132: iload #15
    //   6134: iadd
    //   6135: istore #10
    //   6137: iload #11
    //   6139: iload #16
    //   6141: iadd
    //   6142: istore #11
    //   6144: iload #12
    //   6146: iload #17
    //   6148: iadd
    //   6149: istore #12
    //   6151: iload #13
    //   6153: iload #18
    //   6155: iadd
    //   6156: istore #13
    //   6158: iinc #7, 16
    //   6161: iload_2
    //   6162: ifne -> 5838
    //   6165: iconst_5
    //   6166: newarray int
    //   6168: dup
    //   6169: iconst_0
    //   6170: iload #9
    //   6172: iastore
    //   6173: dup
    //   6174: iconst_1
    //   6175: iload #10
    //   6177: iastore
    //   6178: dup
    //   6179: iconst_2
    //   6180: iload #11
    //   6182: iastore
    //   6183: dup
    //   6184: iconst_3
    //   6185: iload #12
    //   6187: iastore
    //   6188: dup
    //   6189: iconst_4
    //   6190: iload #13
    //   6192: iastore
    //   6193: astore #14
    //   6195: bipush #20
    //   6197: newarray byte
    //   6199: astore #15
    //   6201: iconst_0
    //   6202: istore #16
    //   6204: iload #16
    //   6206: bipush #20
    //   6208: if_icmpge -> 6249
    //   6211: aload #14
    //   6213: iload #16
    //   6215: iconst_4
    //   6216: idiv
    //   6217: iaload
    //   6218: istore #17
    //   6220: iconst_3
    //   6221: iload #16
    //   6223: iconst_4
    //   6224: irem
    //   6225: isub
    //   6226: bipush #8
    //   6228: imul
    //   6229: istore #18
    //   6231: aload #15
    //   6233: iload #16
    //   6235: iload #17
    //   6237: iload #18
    //   6239: iushr
    //   6240: i2b
    //   6241: bastore
    //   6242: iinc #16, 1
    //   6245: iload_2
    //   6246: ifne -> 6204
    //   6249: aload #15
    //   6251: astore #5
    //   6253: sipush #29845
    //   6256: new java/math/BigInteger
    //   6259: dup
    //   6260: aload #5
    //   6262: invokespecial <init> : ([B)V
    //   6265: invokevirtual abs : ()Ljava/math/BigInteger;
    //   6268: putstatic burp/Zsun.ZP : Ljava/lang/Object;
    //   6271: sipush #-249
    //   6274: invokestatic a : (II)Ljava/lang/String;
    //   6277: iconst_1
    //   6278: ldc burp/Zsby
    //   6280: invokevirtual getClassLoader : ()Ljava/lang/ClassLoader;
    //   6283: invokestatic forName : (Ljava/lang/String;ZLjava/lang/ClassLoader;)Ljava/lang/Class;
    //   6286: invokevirtual getDeclaredFields : ()[Ljava/lang/reflect/Field;
    //   6289: astore #4
    //   6291: aload #4
    //   6293: arraylength
    //   6294: istore #5
    //   6296: iconst_0
    //   6297: istore #6
    //   6299: iload #6
    //   6301: iload #5
    //   6303: if_icmpge -> 6441
    //   6306: aload #4
    //   6308: iload #6
    //   6310: aaload
    //   6311: astore #7
    //   6313: aload #7
    //   6315: invokevirtual getModifiers : ()I
    //   6318: invokestatic isStatic : (I)Z
    //   6321: ifne -> 6331
    //   6324: goto -> 6434
    //   6327: invokestatic a : (Ljava/lang/Throwable;)Ljava/lang/Throwable;
    //   6330: athrow
    //   6331: aload #7
    //   6333: invokevirtual getType : ()Ljava/lang/Class;
    //   6336: astore #8
    //   6338: aload #8
    //   6340: ifnull -> 6421
    //   6343: aload #8
    //   6345: invokevirtual isPrimitive : ()Z
    //   6348: ifne -> 6421
    //   6351: goto -> 6358
    //   6354: invokestatic a : (Ljava/lang/Throwable;)Ljava/lang/Throwable;
    //   6357: athrow
    //   6358: aload #8
    //   6360: invokevirtual getPackage : ()Ljava/lang/Package;
    //   6363: ifnull -> 6421
    //   6366: goto -> 6373
    //   6369: invokestatic a : (Ljava/lang/Throwable;)Ljava/lang/Throwable;
    //   6372: athrow
    //   6373: aload #8
    //   6375: invokevirtual getPackage : ()Ljava/lang/Package;
    //   6378: invokevirtual getName : ()Ljava/lang/String;
    //   6381: ifnull -> 6421
    //   6384: goto -> 6391
    //   6387: invokestatic a : (Ljava/lang/Throwable;)Ljava/lang/Throwable;
    //   6390: athrow
    //   6391: aload #8
    //   6393: invokevirtual getPackage : ()Ljava/lang/Package;
    //   6396: invokevirtual getName : ()Ljava/lang/String;
    //   6399: sipush #29833
    //   6402: sipush #-27675
    //   6405: invokestatic a : (II)Ljava/lang/String;
    //   6408: invokevirtual startsWith : (Ljava/lang/String;)Z
    //   6411: ifne -> 6421
    //   6414: goto -> 6421
    //   6417: invokestatic a : (Ljava/lang/Throwable;)Ljava/lang/Throwable;
    //   6420: athrow
    //   6421: aload #7
    //   6423: iconst_1
    //   6424: invokevirtual setAccessible : (Z)V
    //   6427: aload #7
    //   6429: aconst_null
    //   6430: invokevirtual get : (Ljava/lang/Object;)Ljava/lang/Object;
    //   6433: pop
    //   6434: iinc #6, 1
    //   6437: iload_2
    //   6438: ifne -> 6299
    //   6441: sipush #29835
    //   6444: sipush #18186
    //   6447: invokestatic a : (II)Ljava/lang/String;
    //   6450: invokestatic forName : (Ljava/lang/String;)Ljava/lang/Class;
    //   6453: invokevirtual getDeclaredMethods : ()[Ljava/lang/reflect/Method;
    //   6456: astore #4
    //   6458: aload #4
    //   6460: arraylength
    //   6461: istore #5
    //   6463: iconst_0
    //   6464: istore #6
    //   6466: iload #6
    //   6468: iload #5
    //   6470: if_icmpge -> 6603
    //   6473: aload #4
    //   6475: iload #6
    //   6477: aaload
    //   6478: astore #7
    //   6480: aload #7
    //   6482: invokevirtual getParameterTypes : ()[Ljava/lang/Class;
    //   6485: pop
    //   6486: aload #7
    //   6488: invokevirtual getModifiers : ()I
    //   6491: invokestatic isStatic : (I)Z
    //   6494: ifeq -> 6589
    //   6497: aload #7
    //   6499: invokevirtual getParameterTypes : ()[Ljava/lang/Class;
    //   6502: arraylength
    //   6503: iconst_2
    //   6504: if_icmpne -> 6589
    //   6507: goto -> 6514
    //   6510: invokestatic a : (Ljava/lang/Throwable;)Ljava/lang/Throwable;
    //   6513: athrow
    //   6514: aload #7
    //   6516: invokevirtual getReturnType : ()Ljava/lang/Class;
    //   6519: getstatic java/lang/Void.TYPE : Ljava/lang/Class;
    //   6522: invokevirtual equals : (Ljava/lang/Object;)Z
    //   6525: ifeq -> 6589
    //   6528: goto -> 6535
    //   6531: invokestatic a : (Ljava/lang/Throwable;)Ljava/lang/Throwable;
    //   6534: athrow
    //   6535: aload #7
    //   6537: iconst_1
    //   6538: invokevirtual setAccessible : (Z)V
    //   6541: aload #7
    //   6543: aconst_null
    //   6544: iconst_2
    //   6545: anewarray java/lang/Object
    //   6548: dup
    //   6549: iconst_0
    //   6550: aload_0
    //   6551: aastore
    //   6552: dup
    //   6553: iconst_1
    //   6554: aload_1
    //   6555: ifnonnull -> 6573
    //   6558: goto -> 6565
    //   6561: invokestatic a : (Ljava/lang/Throwable;)Ljava/lang/Throwable;
    //   6564: athrow
    //   6565: aload_1
    //   6566: goto -> 6580
    //   6569: invokestatic a : (Ljava/lang/Throwable;)Ljava/lang/Throwable;
    //   6572: athrow
    //   6573: aload_1
    //   6574: checkcast [B
    //   6577: invokevirtual clone : ()Ljava/lang/Object;
    //   6580: aastore
    //   6581: invokevirtual invoke : (Ljava/lang/Object;[Ljava/lang/Object;)Ljava/lang/Object;
    //   6584: pop
    //   6585: iload_2
    //   6586: ifne -> 6603
    //   6589: iinc #6, 1
    //   6592: iload_2
    //   6593: ifne -> 6466
    //   6596: goto -> 6603
    //   6599: invokestatic a : (Ljava/lang/Throwable;)Ljava/lang/Throwable;
    //   6602: athrow
    //   6603: getstatic burp/Zete.Zm : Ljava/lang/Object;
    //   6606: checkcast java/math/BigInteger
    //   6609: invokevirtual intValue : ()I
    //   6612: i2l
    //   6613: invokestatic currentTimeMillis : ()J
    //   6616: ladd
    //   6617: getstatic burp/Zrkc.ZI : Ljava/lang/Object;
    //   6620: checkcast java/math/BigInteger
    //   6623: invokevirtual intValue : ()I
    //   6626: i2l
    //   6627: lcmp
    //   6628: ifge -> 6966
    //   6631: sipush #29834
    //   6634: sipush #10006
    //   6637: invokestatic a : (II)Ljava/lang/String;
    //   6640: iconst_1
    //   6641: ldc burp/Zshq
    //   6643: invokevirtual getClassLoader : ()Ljava/lang/ClassLoader;
    //   6646: invokestatic forName : (Ljava/lang/String;ZLjava/lang/ClassLoader;)Ljava/lang/Class;
    //   6649: invokevirtual getDeclaredFields : ()[Ljava/lang/reflect/Field;
    //   6652: astore #4
    //   6654: aload #4
    //   6656: arraylength
    //   6657: istore #5
    //   6659: iconst_0
    //   6660: istore #6
    //   6662: iload #6
    //   6664: iload #5
    //   6666: if_icmpge -> 6804
    //   6669: aload #4
    //   6671: iload #6
    //   6673: aaload
    //   6674: astore #7
    //   6676: aload #7
    //   6678: invokevirtual getModifiers : ()I
    //   6681: invokestatic isStatic : (I)Z
    //   6684: ifne -> 6694
    //   6687: goto -> 6797
    //   6690: invokestatic a : (Ljava/lang/Throwable;)Ljava/lang/Throwable;
    //   6693: athrow
    //   6694: aload #7
    //   6696: invokevirtual getType : ()Ljava/lang/Class;
    //   6699: astore #8
    //   6701: aload #8
    //   6703: ifnull -> 6784
    //   6706: aload #8
    //   6708: invokevirtual isPrimitive : ()Z
    //   6711: ifne -> 6784
    //   6714: goto -> 6721
    //   6717: invokestatic a : (Ljava/lang/Throwable;)Ljava/lang/Throwable;
    //   6720: athrow
    //   6721: aload #8
    //   6723: invokevirtual getPackage : ()Ljava/lang/Package;
    //   6726: ifnull -> 6784
    //   6729: goto -> 6736
    //   6732: invokestatic a : (Ljava/lang/Throwable;)Ljava/lang/Throwable;
    //   6735: athrow
    //   6736: aload #8
    //   6738: invokevirtual getPackage : ()Ljava/lang/Package;
    //   6741: invokevirtual getName : ()Ljava/lang/String;
    //   6744: ifnull -> 6784
    //   6747: goto -> 6754
    //   6750: invokestatic a : (Ljava/lang/Throwable;)Ljava/lang/Throwable;
    //   6753: athrow
    //   6754: aload #8
    //   6756: invokevirtual getPackage : ()Ljava/lang/Package;
    //   6759: invokevirtual getName : ()Ljava/lang/String;
    //   6762: sipush #29826
    //   6765: sipush #10395
    //   6768: invokestatic a : (II)Ljava/lang/String;
    //   6771: invokevirtual startsWith : (Ljava/lang/String;)Z
    //   6774: ifne -> 6784
    //   6777: goto -> 6784
    //   6780: invokestatic a : (Ljava/lang/Throwable;)Ljava/lang/Throwable;
    //   6783: athrow
    //   6784: aload #7
    //   6786: iconst_1
    //   6787: invokevirtual setAccessible : (Z)V
    //   6790: aload #7
    //   6792: aconst_null
    //   6793: invokevirtual get : (Ljava/lang/Object;)Ljava/lang/Object;
    //   6796: pop
    //   6797: iinc #6, 1
    //   6800: iload_2
    //   6801: ifne -> 6662
    //   6804: sipush #29824
    //   6807: sipush #-24292
    //   6810: invokestatic a : (II)Ljava/lang/String;
    //   6813: invokestatic forName : (Ljava/lang/String;)Ljava/lang/Class;
    //   6816: invokevirtual getDeclaredMethods : ()[Ljava/lang/reflect/Method;
    //   6819: astore #4
    //   6821: aload #4
    //   6823: arraylength
    //   6824: istore #5
    //   6826: iconst_0
    //   6827: istore #6
    //   6829: iload #6
    //   6831: iload #5
    //   6833: if_icmpge -> 6966
    //   6836: aload #4
    //   6838: iload #6
    //   6840: aaload
    //   6841: astore #7
    //   6843: aload #7
    //   6845: invokevirtual getParameterTypes : ()[Ljava/lang/Class;
    //   6848: pop
    //   6849: aload #7
    //   6851: invokevirtual getModifiers : ()I
    //   6854: invokestatic isStatic : (I)Z
    //   6857: ifeq -> 6952
    //   6860: aload #7
    //   6862: invokevirtual getParameterTypes : ()[Ljava/lang/Class;
    //   6865: arraylength
    //   6866: iconst_2
    //   6867: if_icmpne -> 6952
    //   6870: goto -> 6877
    //   6873: invokestatic a : (Ljava/lang/Throwable;)Ljava/lang/Throwable;
    //   6876: athrow
    //   6877: aload #7
    //   6879: invokevirtual getReturnType : ()Ljava/lang/Class;
    //   6882: getstatic java/lang/Void.TYPE : Ljava/lang/Class;
    //   6885: invokevirtual equals : (Ljava/lang/Object;)Z
    //   6888: ifeq -> 6952
    //   6891: goto -> 6898
    //   6894: invokestatic a : (Ljava/lang/Throwable;)Ljava/lang/Throwable;
    //   6897: athrow
    //   6898: aload #7
    //   6900: iconst_1
    //   6901: invokevirtual setAccessible : (Z)V
    //   6904: aload #7
    //   6906: aconst_null
    //   6907: iconst_2
    //   6908: anewarray java/lang/Object
    //   6911: dup
    //   6912: iconst_0
    //   6913: aload_0
    //   6914: aastore
    //   6915: dup
    //   6916: iconst_1
    //   6917: aload_1
    //   6918: ifnonnull -> 6936
    //   6921: goto -> 6928
    //   6924: invokestatic a : (Ljava/lang/Throwable;)Ljava/lang/Throwable;
    //   6927: athrow
    //   6928: aload_1
    //   6929: goto -> 6943
    //   6932: invokestatic a : (Ljava/lang/Throwable;)Ljava/lang/Throwable;
    //   6935: athrow
    //   6936: aload_1
    //   6937: checkcast [B
    //   6940: invokevirtual clone : ()Ljava/lang/Object;
    //   6943: aastore
    //   6944: invokevirtual invoke : (Ljava/lang/Object;[Ljava/lang/Object;)Ljava/lang/Object;
    //   6947: pop
    //   6948: iload_2
    //   6949: ifne -> 6966
    //   6952: iinc #6, 1
    //   6955: iload_2
    //   6956: ifne -> 6829
    //   6959: goto -> 6966
    //   6962: invokestatic a : (Ljava/lang/Throwable;)Ljava/lang/Throwable;
    //   6965: athrow
    //   6966: iconst_0
    //   6967: istore #4
    //   6969: getstatic burp/Zlg1.ZG : Ljava/lang/String;
    //   6972: getstatic burp/Zb_c.ZN : Ljava/lang/Object;
    //   6975: checkcast java/math/BigInteger
    //   6978: invokevirtual intValue : ()I
    //   6981: bipush #32
    //   6983: irem
    //   6984: invokestatic abs : (I)I
    //   6987: invokevirtual charAt : (I)C
    //   6990: getstatic burp/Ztod.Zj : Ljava/lang/String;
    //   6993: getstatic burp/Zblj.Zl : Ljava/lang/Object;
    //   6996: checkcast java/math/BigInteger
    //   6999: invokevirtual intValue : ()I
    //   7002: bipush #32
    //   7004: irem
    //   7005: invokestatic abs : (I)I
    //   7008: invokevirtual charAt : (I)C
    //   7011: if_icmple -> 7356
    //   7014: sipush #29853
    //   7017: sipush #-32138
    //   7020: invokestatic a : (II)Ljava/lang/String;
    //   7023: iconst_1
    //   7024: ldc burp/Zli5
    //   7026: invokevirtual getClassLoader : ()Ljava/lang/ClassLoader;
    //   7029: invokestatic forName : (Ljava/lang/String;ZLjava/lang/ClassLoader;)Ljava/lang/Class;
    //   7032: invokevirtual getDeclaredFields : ()[Ljava/lang/reflect/Field;
    //   7035: astore #5
    //   7037: aload #5
    //   7039: arraylength
    //   7040: istore #6
    //   7042: iconst_0
    //   7043: istore #7
    //   7045: iload #7
    //   7047: iload #6
    //   7049: if_icmpge -> 7187
    //   7052: aload #5
    //   7054: iload #7
    //   7056: aaload
    //   7057: astore #8
    //   7059: aload #8
    //   7061: invokevirtual getModifiers : ()I
    //   7064: invokestatic isStatic : (I)Z
    //   7067: ifne -> 7077
    //   7070: goto -> 7180
    //   7073: invokestatic a : (Ljava/lang/Throwable;)Ljava/lang/Throwable;
    //   7076: athrow
    //   7077: aload #8
    //   7079: invokevirtual getType : ()Ljava/lang/Class;
    //   7082: astore #9
    //   7084: aload #9
    //   7086: ifnull -> 7167
    //   7089: aload #9
    //   7091: invokevirtual isPrimitive : ()Z
    //   7094: ifne -> 7167
    //   7097: goto -> 7104
    //   7100: invokestatic a : (Ljava/lang/Throwable;)Ljava/lang/Throwable;
    //   7103: athrow
    //   7104: aload #9
    //   7106: invokevirtual getPackage : ()Ljava/lang/Package;
    //   7109: ifnull -> 7167
    //   7112: goto -> 7119
    //   7115: invokestatic a : (Ljava/lang/Throwable;)Ljava/lang/Throwable;
    //   7118: athrow
    //   7119: aload #9
    //   7121: invokevirtual getPackage : ()Ljava/lang/Package;
    //   7124: invokevirtual getName : ()Ljava/lang/String;
    //   7127: ifnull -> 7167
    //   7130: goto -> 7137
    //   7133: invokestatic a : (Ljava/lang/Throwable;)Ljava/lang/Throwable;
    //   7136: athrow
    //   7137: aload #9
    //   7139: invokevirtual getPackage : ()Ljava/lang/Package;
    //   7142: invokevirtual getName : ()Ljava/lang/String;
    //   7145: sipush #29826
    //   7148: sipush #10395
    //   7151: invokestatic a : (II)Ljava/lang/String;
    //   7154: invokevirtual startsWith : (Ljava/lang/String;)Z
    //   7157: ifne -> 7167
    //   7160: goto -> 7167
    //   7163: invokestatic a : (Ljava/lang/Throwable;)Ljava/lang/Throwable;
    //   7166: athrow
    //   7167: aload #8
    //   7169: iconst_1
    //   7170: invokevirtual setAccessible : (Z)V
    //   7173: aload #8
    //   7175: aconst_null
    //   7176: invokevirtual get : (Ljava/lang/Object;)Ljava/lang/Object;
    //   7179: pop
    //   7180: iinc #7, 1
    //   7183: iload_2
    //   7184: ifne -> 7045
    //   7187: sipush #29825
    //   7190: sipush #31471
    //   7193: invokestatic a : (II)Ljava/lang/String;
    //   7196: invokestatic forName : (Ljava/lang/String;)Ljava/lang/Class;
    //   7199: invokevirtual getDeclaredMethods : ()[Ljava/lang/reflect/Method;
    //   7202: astore #5
    //   7204: aload #5
    //   7206: arraylength
    //   7207: istore #6
    //   7209: iconst_0
    //   7210: istore #7
    //   7212: iload #7
    //   7214: iload #6
    //   7216: if_icmpge -> 7353
    //   7219: aload #5
    //   7221: iload #7
    //   7223: aaload
    //   7224: astore #8
    //   7226: aload #8
    //   7228: invokevirtual getParameterTypes : ()[Ljava/lang/Class;
    //   7231: pop
    //   7232: aload #8
    //   7234: invokevirtual getModifiers : ()I
    //   7237: invokestatic isStatic : (I)Z
    //   7240: ifeq -> 7339
    //   7243: aload #8
    //   7245: invokevirtual getParameterTypes : ()[Ljava/lang/Class;
    //   7248: arraylength
    //   7249: iconst_2
    //   7250: if_icmpne -> 7339
    //   7253: goto -> 7260
    //   7256: invokestatic a : (Ljava/lang/Throwable;)Ljava/lang/Throwable;
    //   7259: athrow
    //   7260: aload #8
    //   7262: invokevirtual getReturnType : ()Ljava/lang/Class;
    //   7265: getstatic java/lang/Boolean.TYPE : Ljava/lang/Class;
    //   7268: if_acmpne -> 7339
    //   7271: goto -> 7278
    //   7274: invokestatic a : (Ljava/lang/Throwable;)Ljava/lang/Throwable;
    //   7277: athrow
    //   7278: aload #8
    //   7280: iconst_1
    //   7281: invokevirtual setAccessible : (Z)V
    //   7284: aload #8
    //   7286: aconst_null
    //   7287: iconst_2
    //   7288: anewarray java/lang/Object
    //   7291: dup
    //   7292: iconst_0
    //   7293: aload_0
    //   7294: aastore
    //   7295: dup
    //   7296: iconst_1
    //   7297: aload_1
    //   7298: ifnonnull -> 7316
    //   7301: goto -> 7308
    //   7304: invokestatic a : (Ljava/lang/Throwable;)Ljava/lang/Throwable;
    //   7307: athrow
    //   7308: aload_1
    //   7309: goto -> 7323
    //   7312: invokestatic a : (Ljava/lang/Throwable;)Ljava/lang/Throwable;
    //   7315: athrow
    //   7316: aload_1
    //   7317: checkcast [B
    //   7320: invokevirtual clone : ()Ljava/lang/Object;
    //   7323: aastore
    //   7324: invokevirtual invoke : (Ljava/lang/Object;[Ljava/lang/Object;)Ljava/lang/Object;
    //   7327: checkcast java/lang/Boolean
    //   7330: invokevirtual booleanValue : ()Z
    //   7333: istore #4
    //   7335: iload_2
    //   7336: ifne -> 7353
    //   7339: iinc #7, 1
    //   7342: iload_2
    //   7343: ifne -> 7212
    //   7346: goto -> 7353
    //   7349: invokestatic a : (Ljava/lang/Throwable;)Ljava/lang/Throwable;
    //   7352: athrow
    //   7353: goto -> 7695
    //   7356: sipush #29842
    //   7359: sipush #25901
    //   7362: invokestatic a : (II)Ljava/lang/String;
    //   7365: iconst_1
    //   7366: ldc burp/Zm5p
    //   7368: invokevirtual getClassLoader : ()Ljava/lang/ClassLoader;
    //   7371: invokestatic forName : (Ljava/lang/String;ZLjava/lang/ClassLoader;)Ljava/lang/Class;
    //   7374: invokevirtual getDeclaredFields : ()[Ljava/lang/reflect/Field;
    //   7377: astore #5
    //   7379: aload #5
    //   7381: arraylength
    //   7382: istore #6
    //   7384: iconst_0
    //   7385: istore #7
    //   7387: iload #7
    //   7389: iload #6
    //   7391: if_icmpge -> 7529
    //   7394: aload #5
    //   7396: iload #7
    //   7398: aaload
    //   7399: astore #8
    //   7401: aload #8
    //   7403: invokevirtual getModifiers : ()I
    //   7406: invokestatic isStatic : (I)Z
    //   7409: ifne -> 7419
    //   7412: goto -> 7522
    //   7415: invokestatic a : (Ljava/lang/Throwable;)Ljava/lang/Throwable;
    //   7418: athrow
    //   7419: aload #8
    //   7421: invokevirtual getType : ()Ljava/lang/Class;
    //   7424: astore #9
    //   7426: aload #9
    //   7428: ifnull -> 7509
    //   7431: aload #9
    //   7433: invokevirtual isPrimitive : ()Z
    //   7436: ifne -> 7509
    //   7439: goto -> 7446
    //   7442: invokestatic a : (Ljava/lang/Throwable;)Ljava/lang/Throwable;
    //   7445: athrow
    //   7446: aload #9
    //   7448: invokevirtual getPackage : ()Ljava/lang/Package;
    //   7451: ifnull -> 7509
    //   7454: goto -> 7461
    //   7457: invokestatic a : (Ljava/lang/Throwable;)Ljava/lang/Throwable;
    //   7460: athrow
    //   7461: aload #9
    //   7463: invokevirtual getPackage : ()Ljava/lang/Package;
    //   7466: invokevirtual getName : ()Ljava/lang/String;
    //   7469: ifnull -> 7509
    //   7472: goto -> 7479
    //   7475: invokestatic a : (Ljava/lang/Throwable;)Ljava/lang/Throwable;
    //   7478: athrow
    //   7479: aload #9
    //   7481: invokevirtual getPackage : ()Ljava/lang/Package;
    //   7484: invokevirtual getName : ()Ljava/lang/String;
    //   7487: sipush #29826
    //   7490: sipush #10395
    //   7493: invokestatic a : (II)Ljava/lang/String;
    //   7496: invokevirtual startsWith : (Ljava/lang/String;)Z
    //   7499: ifne -> 7509
    //   7502: goto -> 7509
    //   7505: invokestatic a : (Ljava/lang/Throwable;)Ljava/lang/Throwable;
    //   7508: athrow
    //   7509: aload #8
    //   7511: iconst_1
    //   7512: invokevirtual setAccessible : (Z)V
    //   7515: aload #8
    //   7517: aconst_null
    //   7518: invokevirtual get : (Ljava/lang/Object;)Ljava/lang/Object;
    //   7521: pop
    //   7522: iinc #7, 1
    //   7525: iload_2
    //   7526: ifne -> 7387
    //   7529: sipush #29852
    //   7532: sipush #-15546
    //   7535: invokestatic a : (II)Ljava/lang/String;
    //   7538: invokestatic forName : (Ljava/lang/String;)Ljava/lang/Class;
    //   7541: invokevirtual getDeclaredMethods : ()[Ljava/lang/reflect/Method;
    //   7544: astore #5
    //   7546: aload #5
    //   7548: arraylength
    //   7549: istore #6
    //   7551: iconst_0
    //   7552: istore #7
    //   7554: iload #7
    //   7556: iload #6
    //   7558: if_icmpge -> 7695
    //   7561: aload #5
    //   7563: iload #7
    //   7565: aaload
    //   7566: astore #8
    //   7568: aload #8
    //   7570: invokevirtual getParameterTypes : ()[Ljava/lang/Class;
    //   7573: pop
    //   7574: aload #8
    //   7576: invokevirtual getModifiers : ()I
    //   7579: invokestatic isStatic : (I)Z
    //   7582: ifeq -> 7681
    //   7585: aload #8
    //   7587: invokevirtual getParameterTypes : ()[Ljava/lang/Class;
    //   7590: arraylength
    //   7591: iconst_2
    //   7592: if_icmpne -> 7681
    //   7595: goto -> 7602
    //   7598: invokestatic a : (Ljava/lang/Throwable;)Ljava/lang/Throwable;
    //   7601: athrow
    //   7602: aload #8
    //   7604: invokevirtual getReturnType : ()Ljava/lang/Class;
    //   7607: getstatic java/lang/Boolean.TYPE : Ljava/lang/Class;
    //   7610: if_acmpne -> 7681
    //   7613: goto -> 7620
    //   7616: invokestatic a : (Ljava/lang/Throwable;)Ljava/lang/Throwable;
    //   7619: athrow
    //   7620: aload #8
    //   7622: iconst_1
    //   7623: invokevirtual setAccessible : (Z)V
    //   7626: aload #8
    //   7628: aconst_null
    //   7629: iconst_2
    //   7630: anewarray java/lang/Object
    //   7633: dup
    //   7634: iconst_0
    //   7635: aload_0
    //   7636: aastore
    //   7637: dup
    //   7638: iconst_1
    //   7639: aload_1
    //   7640: ifnonnull -> 7658
    //   7643: goto -> 7650
    //   7646: invokestatic a : (Ljava/lang/Throwable;)Ljava/lang/Throwable;
    //   7649: athrow
    //   7650: aload_1
    //   7651: goto -> 7665
    //   7654: invokestatic a : (Ljava/lang/Throwable;)Ljava/lang/Throwable;
    //   7657: athrow
    //   7658: aload_1
    //   7659: checkcast [B
    //   7662: invokevirtual clone : ()Ljava/lang/Object;
    //   7665: aastore
    //   7666: invokevirtual invoke : (Ljava/lang/Object;[Ljava/lang/Object;)Ljava/lang/Object;
    //   7669: checkcast java/lang/Boolean
    //   7672: invokevirtual booleanValue : ()Z
    //   7675: istore #4
    //   7677: iload_2
    //   7678: ifne -> 7695
    //   7681: iinc #7, 1
    //   7684: iload_2
    //   7685: ifne -> 7554
    //   7688: goto -> 7695
    //   7691: invokestatic a : (Ljava/lang/Throwable;)Ljava/lang/Throwable;
    //   7694: athrow
    //   7695: iload #4
    //   7697: ifeq -> 7703
    //   7700: iload #4
    //   7702: ireturn
    //   7703: getstatic burp/Zlhz.Zo : Ljava/lang/String;
    //   7706: getstatic burp/Zlp7.ZM : Ljava/lang/Object;
    //   7709: checkcast java/math/BigInteger
    //   7712: invokevirtual intValue : ()I
    //   7715: bipush #32
    //   7717: irem
    //   7718: invokestatic abs : (I)I
    //   7721: invokevirtual charAt : (I)C
    //   7724: getstatic burp/Zgwh.Zq : Ljava/lang/String;
    //   7727: getstatic burp/Zeu2.ZW : Ljava/lang/Object;
    //   7730: checkcast java/math/BigInteger
    //   7733: invokevirtual intValue : ()I
    //   7736: bipush #32
    //   7738: irem
    //   7739: invokestatic abs : (I)I
    //   7742: invokevirtual charAt : (I)C
    //   7745: if_icmple -> 8091
    //   7748: sipush #29846
    //   7751: sipush #12701
    //   7754: invokestatic a : (II)Ljava/lang/String;
    //   7757: iconst_1
    //   7758: ldc burp/Zzh0
    //   7760: invokevirtual getClassLoader : ()Ljava/lang/ClassLoader;
    //   7763: invokestatic forName : (Ljava/lang/String;ZLjava/lang/ClassLoader;)Ljava/lang/Class;
    //   7766: invokevirtual getDeclaredFields : ()[Ljava/lang/reflect/Field;
    //   7769: astore #5
    //   7771: aload #5
    //   7773: arraylength
    //   7774: istore #6
    //   7776: iconst_0
    //   7777: istore #7
    //   7779: iload #7
    //   7781: iload #6
    //   7783: if_icmpge -> 7921
    //   7786: aload #5
    //   7788: iload #7
    //   7790: aaload
    //   7791: astore #8
    //   7793: aload #8
    //   7795: invokevirtual getModifiers : ()I
    //   7798: invokestatic isStatic : (I)Z
    //   7801: ifne -> 7811
    //   7804: goto -> 7914
    //   7807: invokestatic a : (Ljava/lang/Throwable;)Ljava/lang/Throwable;
    //   7810: athrow
    //   7811: aload #8
    //   7813: invokevirtual getType : ()Ljava/lang/Class;
    //   7816: astore #9
    //   7818: aload #9
    //   7820: ifnull -> 7901
    //   7823: aload #9
    //   7825: invokevirtual isPrimitive : ()Z
    //   7828: ifne -> 7901
    //   7831: goto -> 7838
    //   7834: invokestatic a : (Ljava/lang/Throwable;)Ljava/lang/Throwable;
    //   7837: athrow
    //   7838: aload #9
    //   7840: invokevirtual getPackage : ()Ljava/lang/Package;
    //   7843: ifnull -> 7901
    //   7846: goto -> 7853
    //   7849: invokestatic a : (Ljava/lang/Throwable;)Ljava/lang/Throwable;
    //   7852: athrow
    //   7853: aload #9
    //   7855: invokevirtual getPackage : ()Ljava/lang/Package;
    //   7858: invokevirtual getName : ()Ljava/lang/String;
    //   7861: ifnull -> 7901
    //   7864: goto -> 7871
    //   7867: invokestatic a : (Ljava/lang/Throwable;)Ljava/lang/Throwable;
    //   7870: athrow
    //   7871: aload #9
    //   7873: invokevirtual getPackage : ()Ljava/lang/Package;
    //   7876: invokevirtual getName : ()Ljava/lang/String;
    //   7879: sipush #29826
    //   7882: sipush #10395
    //   7885: invokestatic a : (II)Ljava/lang/String;
    //   7888: invokevirtual startsWith : (Ljava/lang/String;)Z
    //   7891: ifne -> 7901
    //   7894: goto -> 7901
    //   7897: invokestatic a : (Ljava/lang/Throwable;)Ljava/lang/Throwable;
    //   7900: athrow
    //   7901: aload #8
    //   7903: iconst_1
    //   7904: invokevirtual setAccessible : (Z)V
    //   7907: aload #8
    //   7909: aconst_null
    //   7910: invokevirtual get : (Ljava/lang/Object;)Ljava/lang/Object;
    //   7913: pop
    //   7914: iinc #7, 1
    //   7917: iload_2
    //   7918: ifne -> 7779
    //   7921: sipush #29830
    //   7924: sipush #781
    //   7927: invokestatic a : (II)Ljava/lang/String;
    //   7930: invokestatic forName : (Ljava/lang/String;)Ljava/lang/Class;
    //   7933: invokevirtual getDeclaredMethods : ()[Ljava/lang/reflect/Method;
    //   7936: astore #5
    //   7938: aload #5
    //   7940: arraylength
    //   7941: istore #6
    //   7943: iconst_0
    //   7944: istore #7
    //   7946: iload #7
    //   7948: iload #6
    //   7950: if_icmpge -> 8087
    //   7953: aload #5
    //   7955: iload #7
    //   7957: aaload
    //   7958: astore #8
    //   7960: aload #8
    //   7962: invokevirtual getParameterTypes : ()[Ljava/lang/Class;
    //   7965: pop
    //   7966: aload #8
    //   7968: invokevirtual getModifiers : ()I
    //   7971: invokestatic isStatic : (I)Z
    //   7974: ifeq -> 8073
    //   7977: aload #8
    //   7979: invokevirtual getParameterTypes : ()[Ljava/lang/Class;
    //   7982: arraylength
    //   7983: iconst_2
    //   7984: if_icmpne -> 8073
    //   7987: goto -> 7994
    //   7990: invokestatic a : (Ljava/lang/Throwable;)Ljava/lang/Throwable;
    //   7993: athrow
    //   7994: aload #8
    //   7996: invokevirtual getReturnType : ()Ljava/lang/Class;
    //   7999: getstatic java/lang/Boolean.TYPE : Ljava/lang/Class;
    //   8002: if_acmpne -> 8073
    //   8005: goto -> 8012
    //   8008: invokestatic a : (Ljava/lang/Throwable;)Ljava/lang/Throwable;
    //   8011: athrow
    //   8012: aload #8
    //   8014: iconst_1
    //   8015: invokevirtual setAccessible : (Z)V
    //   8018: aload #8
    //   8020: aconst_null
    //   8021: iconst_2
    //   8022: anewarray java/lang/Object
    //   8025: dup
    //   8026: iconst_0
    //   8027: aload_0
    //   8028: aastore
    //   8029: dup
    //   8030: iconst_1
    //   8031: aload_1
    //   8032: ifnonnull -> 8050
    //   8035: goto -> 8042
    //   8038: invokestatic a : (Ljava/lang/Throwable;)Ljava/lang/Throwable;
    //   8041: athrow
    //   8042: aload_1
    //   8043: goto -> 8057
    //   8046: invokestatic a : (Ljava/lang/Throwable;)Ljava/lang/Throwable;
    //   8049: athrow
    //   8050: aload_1
    //   8051: checkcast [B
    //   8054: invokevirtual clone : ()Ljava/lang/Object;
    //   8057: aastore
    //   8058: invokevirtual invoke : (Ljava/lang/Object;[Ljava/lang/Object;)Ljava/lang/Object;
    //   8061: checkcast java/lang/Boolean
    //   8064: invokevirtual booleanValue : ()Z
    //   8067: istore #4
    //   8069: iload_2
    //   8070: ifne -> 8087
    //   8073: iinc #7, 1
    //   8076: iload_2
    //   8077: ifne -> 7946
    //   8080: goto -> 8087
    //   8083: invokestatic a : (Ljava/lang/Throwable;)Ljava/lang/Throwable;
    //   8086: athrow
    //   8087: iload_2
    //   8088: ifne -> 8430
    //   8091: sipush #29831
    //   8094: sipush #-17596
    //   8097: invokestatic a : (II)Ljava/lang/String;
    //   8100: iconst_1
    //   8101: ldc burp/Zr0g
    //   8103: invokevirtual getClassLoader : ()Ljava/lang/ClassLoader;
    //   8106: invokestatic forName : (Ljava/lang/String;ZLjava/lang/ClassLoader;)Ljava/lang/Class;
    //   8109: invokevirtual getDeclaredFields : ()[Ljava/lang/reflect/Field;
    //   8112: astore #5
    //   8114: aload #5
    //   8116: arraylength
    //   8117: istore #6
    //   8119: iconst_0
    //   8120: istore #7
    //   8122: iload #7
    //   8124: iload #6
    //   8126: if_icmpge -> 8264
    //   8129: aload #5
    //   8131: iload #7
    //   8133: aaload
    //   8134: astore #8
    //   8136: aload #8
    //   8138: invokevirtual getModifiers : ()I
    //   8141: invokestatic isStatic : (I)Z
    //   8144: ifne -> 8154
    //   8147: goto -> 8257
    //   8150: invokestatic a : (Ljava/lang/Throwable;)Ljava/lang/Throwable;
    //   8153: athrow
    //   8154: aload #8
    //   8156: invokevirtual getType : ()Ljava/lang/Class;
    //   8159: astore #9
    //   8161: aload #9
    //   8163: ifnull -> 8244
    //   8166: aload #9
    //   8168: invokevirtual isPrimitive : ()Z
    //   8171: ifne -> 8244
    //   8174: goto -> 8181
    //   8177: invokestatic a : (Ljava/lang/Throwable;)Ljava/lang/Throwable;
    //   8180: athrow
    //   8181: aload #9
    //   8183: invokevirtual getPackage : ()Ljava/lang/Package;
    //   8186: ifnull -> 8244
    //   8189: goto -> 8196
    //   8192: invokestatic a : (Ljava/lang/Throwable;)Ljava/lang/Throwable;
    //   8195: athrow
    //   8196: aload #9
    //   8198: invokevirtual getPackage : ()Ljava/lang/Package;
    //   8201: invokevirtual getName : ()Ljava/lang/String;
    //   8204: ifnull -> 8244
    //   8207: goto -> 8214
    //   8210: invokestatic a : (Ljava/lang/Throwable;)Ljava/lang/Throwable;
    //   8213: athrow
    //   8214: aload #9
    //   8216: invokevirtual getPackage : ()Ljava/lang/Package;
    //   8219: invokevirtual getName : ()Ljava/lang/String;
    //   8222: sipush #29826
    //   8225: sipush #10395
    //   8228: invokestatic a : (II)Ljava/lang/String;
    //   8231: invokevirtual startsWith : (Ljava/lang/String;)Z
    //   8234: ifne -> 8244
    //   8237: goto -> 8244
    //   8240: invokestatic a : (Ljava/lang/Throwable;)Ljava/lang/Throwable;
    //   8243: athrow
    //   8244: aload #8
    //   8246: iconst_1
    //   8247: invokevirtual setAccessible : (Z)V
    //   8250: aload #8
    //   8252: aconst_null
    //   8253: invokevirtual get : (Ljava/lang/Object;)Ljava/lang/Object;
    //   8256: pop
    //   8257: iinc #7, 1
    //   8260: iload_2
    //   8261: ifne -> 8122
    //   8264: sipush #29848
    //   8267: sipush #6014
    //   8270: invokestatic a : (II)Ljava/lang/String;
    //   8273: invokestatic forName : (Ljava/lang/String;)Ljava/lang/Class;
    //   8276: invokevirtual getDeclaredMethods : ()[Ljava/lang/reflect/Method;
    //   8279: astore #5
    //   8281: aload #5
    //   8283: arraylength
    //   8284: istore #6
    //   8286: iconst_0
    //   8287: istore #7
    //   8289: iload #7
    //   8291: iload #6
    //   8293: if_icmpge -> 8430
    //   8296: aload #5
    //   8298: iload #7
    //   8300: aaload
    //   8301: astore #8
    //   8303: aload #8
    //   8305: invokevirtual getParameterTypes : ()[Ljava/lang/Class;
    //   8308: pop
    //   8309: aload #8
    //   8311: invokevirtual getModifiers : ()I
    //   8314: invokestatic isStatic : (I)Z
    //   8317: ifeq -> 8416
    //   8320: aload #8
    //   8322: invokevirtual getParameterTypes : ()[Ljava/lang/Class;
    //   8325: arraylength
    //   8326: iconst_2
    //   8327: if_icmpne -> 8416
    //   8330: goto -> 8337
    //   8333: invokestatic a : (Ljava/lang/Throwable;)Ljava/lang/Throwable;
    //   8336: athrow
    //   8337: aload #8
    //   8339: invokevirtual getReturnType : ()Ljava/lang/Class;
    //   8342: getstatic java/lang/Boolean.TYPE : Ljava/lang/Class;
    //   8345: if_acmpne -> 8416
    //   8348: goto -> 8355
    //   8351: invokestatic a : (Ljava/lang/Throwable;)Ljava/lang/Throwable;
    //   8354: athrow
    //   8355: aload #8
    //   8357: iconst_1
    //   8358: invokevirtual setAccessible : (Z)V
    //   8361: aload #8
    //   8363: aconst_null
    //   8364: iconst_2
    //   8365: anewarray java/lang/Object
    //   8368: dup
    //   8369: iconst_0
    //   8370: aload_0
    //   8371: aastore
    //   8372: dup
    //   8373: iconst_1
    //   8374: aload_1
    //   8375: ifnonnull -> 8393
    //   8378: goto -> 8385
    //   8381: invokestatic a : (Ljava/lang/Throwable;)Ljava/lang/Throwable;
    //   8384: athrow
    //   8385: aload_1
    //   8386: goto -> 8400
    //   8389: invokestatic a : (Ljava/lang/Throwable;)Ljava/lang/Throwable;
    //   8392: athrow
    //   8393: aload_1
    //   8394: checkcast [B
    //   8397: invokevirtual clone : ()Ljava/lang/Object;
    //   8400: aastore
    //   8401: invokevirtual invoke : (Ljava/lang/Object;[Ljava/lang/Object;)Ljava/lang/Object;
    //   8404: checkcast java/lang/Boolean
    //   8407: invokevirtual booleanValue : ()Z
    //   8410: istore #4
    //   8412: iload_2
    //   8413: ifne -> 8430
    //   8416: iinc #7, 1
    //   8419: iload_2
    //   8420: ifne -> 8289
    //   8423: goto -> 8430
    //   8426: invokestatic a : (Ljava/lang/Throwable;)Ljava/lang/Throwable;
    //   8429: athrow
    //   8430: iload #4
    //   8432: ifeq -> 8438
    //   8435: iload #4
    //   8437: ireturn
    //   8438: getstatic burp/Zz3k.Zn : Ljava/lang/String;
    //   8441: getstatic burp/Zmcq.Zh : Ljava/lang/Object;
    //   8444: checkcast java/math/BigInteger
    //   8447: invokevirtual intValue : ()I
    //   8450: bipush #32
    //   8452: irem
    //   8453: invokestatic abs : (I)I
    //   8456: invokevirtual charAt : (I)C
    //   8459: getstatic burp/Zezn.Ze : Ljava/lang/String;
    //   8462: getstatic burp/Zgkp.Zp : Ljava/lang/Object;
    //   8465: checkcast java/math/BigInteger
    //   8468: invokevirtual intValue : ()I
    //   8471: bipush #32
    //   8473: irem
    //   8474: invokestatic abs : (I)I
    //   8477: invokevirtual charAt : (I)C
    //   8480: if_icmpgt -> 8826
    //   8483: sipush #29851
    //   8486: sipush #-3192
    //   8489: invokestatic a : (II)Ljava/lang/String;
    //   8492: iconst_1
    //   8493: ldc burp/Zg7p
    //   8495: invokevirtual getClassLoader : ()Ljava/lang/ClassLoader;
    //   8498: invokestatic forName : (Ljava/lang/String;ZLjava/lang/ClassLoader;)Ljava/lang/Class;
    //   8501: invokevirtual getDeclaredFields : ()[Ljava/lang/reflect/Field;
    //   8504: astore #5
    //   8506: aload #5
    //   8508: arraylength
    //   8509: istore #6
    //   8511: iconst_0
    //   8512: istore #7
    //   8514: iload #7
    //   8516: iload #6
    //   8518: if_icmpge -> 8656
    //   8521: aload #5
    //   8523: iload #7
    //   8525: aaload
    //   8526: astore #8
    //   8528: aload #8
    //   8530: invokevirtual getModifiers : ()I
    //   8533: invokestatic isStatic : (I)Z
    //   8536: ifne -> 8546
    //   8539: goto -> 8649
    //   8542: invokestatic a : (Ljava/lang/Throwable;)Ljava/lang/Throwable;
    //   8545: athrow
    //   8546: aload #8
    //   8548: invokevirtual getType : ()Ljava/lang/Class;
    //   8551: astore #9
    //   8553: aload #9
    //   8555: ifnull -> 8636
    //   8558: aload #9
    //   8560: invokevirtual isPrimitive : ()Z
    //   8563: ifne -> 8636
    //   8566: goto -> 8573
    //   8569: invokestatic a : (Ljava/lang/Throwable;)Ljava/lang/Throwable;
    //   8572: athrow
    //   8573: aload #9
    //   8575: invokevirtual getPackage : ()Ljava/lang/Package;
    //   8578: ifnull -> 8636
    //   8581: goto -> 8588
    //   8584: invokestatic a : (Ljava/lang/Throwable;)Ljava/lang/Throwable;
    //   8587: athrow
    //   8588: aload #9
    //   8590: invokevirtual getPackage : ()Ljava/lang/Package;
    //   8593: invokevirtual getName : ()Ljava/lang/String;
    //   8596: ifnull -> 8636
    //   8599: goto -> 8606
    //   8602: invokestatic a : (Ljava/lang/Throwable;)Ljava/lang/Throwable;
    //   8605: athrow
    //   8606: aload #9
    //   8608: invokevirtual getPackage : ()Ljava/lang/Package;
    //   8611: invokevirtual getName : ()Ljava/lang/String;
    //   8614: sipush #29826
    //   8617: sipush #10395
    //   8620: invokestatic a : (II)Ljava/lang/String;
    //   8623: invokevirtual startsWith : (Ljava/lang/String;)Z
    //   8626: ifne -> 8636
    //   8629: goto -> 8636
    //   8632: invokestatic a : (Ljava/lang/Throwable;)Ljava/lang/Throwable;
    //   8635: athrow
    //   8636: aload #8
    //   8638: iconst_1
    //   8639: invokevirtual setAccessible : (Z)V
    //   8642: aload #8
    //   8644: aconst_null
    //   8645: invokevirtual get : (Ljava/lang/Object;)Ljava/lang/Object;
    //   8648: pop
    //   8649: iinc #7, 1
    //   8652: iload_2
    //   8653: ifne -> 8514
    //   8656: sipush #29844
    //   8659: sipush #14076
    //   8662: invokestatic a : (II)Ljava/lang/String;
    //   8665: invokestatic forName : (Ljava/lang/String;)Ljava/lang/Class;
    //   8668: invokevirtual getDeclaredMethods : ()[Ljava/lang/reflect/Method;
    //   8671: astore #5
    //   8673: aload #5
    //   8675: arraylength
    //   8676: istore #6
    //   8678: iconst_0
    //   8679: istore #7
    //   8681: iload #7
    //   8683: iload #6
    //   8685: if_icmpge -> 8822
    //   8688: aload #5
    //   8690: iload #7
    //   8692: aaload
    //   8693: astore #8
    //   8695: aload #8
    //   8697: invokevirtual getParameterTypes : ()[Ljava/lang/Class;
    //   8700: pop
    //   8701: aload #8
    //   8703: invokevirtual getModifiers : ()I
    //   8706: invokestatic isStatic : (I)Z
    //   8709: ifeq -> 8808
    //   8712: aload #8
    //   8714: invokevirtual getParameterTypes : ()[Ljava/lang/Class;
    //   8717: arraylength
    //   8718: iconst_2
    //   8719: if_icmpne -> 8808
    //   8722: goto -> 8729
    //   8725: invokestatic a : (Ljava/lang/Throwable;)Ljava/lang/Throwable;
    //   8728: athrow
    //   8729: aload #8
    //   8731: invokevirtual getReturnType : ()Ljava/lang/Class;
    //   8734: getstatic java/lang/Boolean.TYPE : Ljava/lang/Class;
    //   8737: if_acmpne -> 8808
    //   8740: goto -> 8747
    //   8743: invokestatic a : (Ljava/lang/Throwable;)Ljava/lang/Throwable;
    //   8746: athrow
    //   8747: aload #8
    //   8749: iconst_1
    //   8750: invokevirtual setAccessible : (Z)V
    //   8753: aload #8
    //   8755: aconst_null
    //   8756: iconst_2
    //   8757: anewarray java/lang/Object
    //   8760: dup
    //   8761: iconst_0
    //   8762: aload_0
    //   8763: aastore
    //   8764: dup
    //   8765: iconst_1
    //   8766: aload_1
    //   8767: ifnonnull -> 8785
    //   8770: goto -> 8777
    //   8773: invokestatic a : (Ljava/lang/Throwable;)Ljava/lang/Throwable;
    //   8776: athrow
    //   8777: aload_1
    //   8778: goto -> 8792
    //   8781: invokestatic a : (Ljava/lang/Throwable;)Ljava/lang/Throwable;
    //   8784: athrow
    //   8785: aload_1
    //   8786: checkcast [B
    //   8789: invokevirtual clone : ()Ljava/lang/Object;
    //   8792: aastore
    //   8793: invokevirtual invoke : (Ljava/lang/Object;[Ljava/lang/Object;)Ljava/lang/Object;
    //   8796: checkcast java/lang/Boolean
    //   8799: invokevirtual booleanValue : ()Z
    //   8802: istore #4
    //   8804: iload_2
    //   8805: ifne -> 8822
    //   8808: iinc #7, 1
    //   8811: iload_2
    //   8812: ifne -> 8681
    //   8815: goto -> 8822
    //   8818: invokestatic a : (Ljava/lang/Throwable;)Ljava/lang/Throwable;
    //   8821: athrow
    //   8822: iload_2
    //   8823: ifne -> 9165
    //   8826: sipush #29843
    //   8829: sipush #20594
    //   8832: invokestatic a : (II)Ljava/lang/String;
    //   8835: iconst_1
    //   8836: ldc burp/Zx4l
    //   8838: invokevirtual getClassLoader : ()Ljava/lang/ClassLoader;
    //   8841: invokestatic forName : (Ljava/lang/String;ZLjava/lang/ClassLoader;)Ljava/lang/Class;
    //   8844: invokevirtual getDeclaredFields : ()[Ljava/lang/reflect/Field;
    //   8847: astore #5
    //   8849: aload #5
    //   8851: arraylength
    //   8852: istore #6
    //   8854: iconst_0
    //   8855: istore #7
    //   8857: iload #7
    //   8859: iload #6
    //   8861: if_icmpge -> 8999
    //   8864: aload #5
    //   8866: iload #7
    //   8868: aaload
    //   8869: astore #8
    //   8871: aload #8
    //   8873: invokevirtual getModifiers : ()I
    //   8876: invokestatic isStatic : (I)Z
    //   8879: ifne -> 8889
    //   8882: goto -> 8992
    //   8885: invokestatic a : (Ljava/lang/Throwable;)Ljava/lang/Throwable;
    //   8888: athrow
    //   8889: aload #8
    //   8891: invokevirtual getType : ()Ljava/lang/Class;
    //   8894: astore #9
    //   8896: aload #9
    //   8898: ifnull -> 8979
    //   8901: aload #9
    //   8903: invokevirtual isPrimitive : ()Z
    //   8906: ifne -> 8979
    //   8909: goto -> 8916
    //   8912: invokestatic a : (Ljava/lang/Throwable;)Ljava/lang/Throwable;
    //   8915: athrow
    //   8916: aload #9
    //   8918: invokevirtual getPackage : ()Ljava/lang/Package;
    //   8921: ifnull -> 8979
    //   8924: goto -> 8931
    //   8927: invokestatic a : (Ljava/lang/Throwable;)Ljava/lang/Throwable;
    //   8930: athrow
    //   8931: aload #9
    //   8933: invokevirtual getPackage : ()Ljava/lang/Package;
    //   8936: invokevirtual getName : ()Ljava/lang/String;
    //   8939: ifnull -> 8979
    //   8942: goto -> 8949
    //   8945: invokestatic a : (Ljava/lang/Throwable;)Ljava/lang/Throwable;
    //   8948: athrow
    //   8949: aload #9
    //   8951: invokevirtual getPackage : ()Ljava/lang/Package;
    //   8954: invokevirtual getName : ()Ljava/lang/String;
    //   8957: sipush #29826
    //   8960: sipush #10395
    //   8963: invokestatic a : (II)Ljava/lang/String;
    //   8966: invokevirtual startsWith : (Ljava/lang/String;)Z
    //   8969: ifne -> 8979
    //   8972: goto -> 8979
    //   8975: invokestatic a : (Ljava/lang/Throwable;)Ljava/lang/Throwable;
    //   8978: athrow
    //   8979: aload #8
    //   8981: iconst_1
    //   8982: invokevirtual setAccessible : (Z)V
    //   8985: aload #8
    //   8987: aconst_null
    //   8988: invokevirtual get : (Ljava/lang/Object;)Ljava/lang/Object;
    //   8991: pop
    //   8992: iinc #7, 1
    //   8995: iload_2
    //   8996: ifne -> 8857
    //   8999: sipush #29832
    //   9002: sipush #4197
    //   9005: invokestatic a : (II)Ljava/lang/String;
    //   9008: invokestatic forName : (Ljava/lang/String;)Ljava/lang/Class;
    //   9011: invokevirtual getDeclaredMethods : ()[Ljava/lang/reflect/Method;
    //   9014: astore #5
    //   9016: aload #5
    //   9018: arraylength
    //   9019: istore #6
    //   9021: iconst_0
    //   9022: istore #7
    //   9024: iload #7
    //   9026: iload #6
    //   9028: if_icmpge -> 9165
    //   9031: aload #5
    //   9033: iload #7
    //   9035: aaload
    //   9036: astore #8
    //   9038: aload #8
    //   9040: invokevirtual getParameterTypes : ()[Ljava/lang/Class;
    //   9043: pop
    //   9044: aload #8
    //   9046: invokevirtual getModifiers : ()I
    //   9049: invokestatic isStatic : (I)Z
    //   9052: ifeq -> 9151
    //   9055: aload #8
    //   9057: invokevirtual getParameterTypes : ()[Ljava/lang/Class;
    //   9060: arraylength
    //   9061: iconst_2
    //   9062: if_icmpne -> 9151
    //   9065: goto -> 9072
    //   9068: invokestatic a : (Ljava/lang/Throwable;)Ljava/lang/Throwable;
    //   9071: athrow
    //   9072: aload #8
    //   9074: invokevirtual getReturnType : ()Ljava/lang/Class;
    //   9077: getstatic java/lang/Boolean.TYPE : Ljava/lang/Class;
    //   9080: if_acmpne -> 9151
    //   9083: goto -> 9090
    //   9086: invokestatic a : (Ljava/lang/Throwable;)Ljava/lang/Throwable;
    //   9089: athrow
    //   9090: aload #8
    //   9092: iconst_1
    //   9093: invokevirtual setAccessible : (Z)V
    //   9096: aload #8
    //   9098: aconst_null
    //   9099: iconst_2
    //   9100: anewarray java/lang/Object
    //   9103: dup
    //   9104: iconst_0
    //   9105: aload_0
    //   9106: aastore
    //   9107: dup
    //   9108: iconst_1
    //   9109: aload_1
    //   9110: ifnonnull -> 9128
    //   9113: goto -> 9120
    //   9116: invokestatic a : (Ljava/lang/Throwable;)Ljava/lang/Throwable;
    //   9119: athrow
    //   9120: aload_1
    //   9121: goto -> 9135
    //   9124: invokestatic a : (Ljava/lang/Throwable;)Ljava/lang/Throwable;
    //   9127: athrow
    //   9128: aload_1
    //   9129: checkcast [B
    //   9132: invokevirtual clone : ()Ljava/lang/Object;
    //   9135: aastore
    //   9136: invokevirtual invoke : (Ljava/lang/Object;[Ljava/lang/Object;)Ljava/lang/Object;
    //   9139: checkcast java/lang/Boolean
    //   9142: invokevirtual booleanValue : ()Z
    //   9145: istore #4
    //   9147: iload_2
    //   9148: ifne -> 9165
    //   9151: iinc #7, 1
    //   9154: iload_2
    //   9155: ifne -> 9024
    //   9158: goto -> 9165
    //   9161: invokestatic a : (Ljava/lang/Throwable;)Ljava/lang/Throwable;
    //   9164: athrow
    //   9165: iload #4
    //   9167: ifeq -> 9173
    //   9170: iload #4
    //   9172: ireturn
    //   9173: getstatic burp/Zgw7.ZN : Ljava/lang/String;
    //   9176: getstatic burp/Zr4k.Zf : Ljava/lang/Object;
    //   9179: checkcast java/math/BigInteger
    //   9182: invokevirtual intValue : ()I
    //   9185: bipush #32
    //   9187: irem
    //   9188: invokestatic abs : (I)I
    //   9191: invokevirtual charAt : (I)C
    //   9194: getstatic burp/Zz3k.Zn : Ljava/lang/String;
    //   9197: getstatic burp/Zkdc.Zv : Ljava/lang/Object;
    //   9200: checkcast java/math/BigInteger
    //   9203: invokevirtual intValue : ()I
    //   9206: bipush #32
    //   9208: irem
    //   9209: invokestatic abs : (I)I
    //   9212: invokevirtual charAt : (I)C
    //   9215: if_icmpgt -> 9561
    //   9218: sipush #29850
    //   9221: sipush #-14575
    //   9224: invokestatic a : (II)Ljava/lang/String;
    //   9227: iconst_1
    //   9228: ldc burp/Zm6h
    //   9230: invokevirtual getClassLoader : ()Ljava/lang/ClassLoader;
    //   9233: invokestatic forName : (Ljava/lang/String;ZLjava/lang/ClassLoader;)Ljava/lang/Class;
    //   9236: invokevirtual getDeclaredFields : ()[Ljava/lang/reflect/Field;
    //   9239: astore #5
    //   9241: aload #5
    //   9243: arraylength
    //   9244: istore #6
    //   9246: iconst_0
    //   9247: istore #7
    //   9249: iload #7
    //   9251: iload #6
    //   9253: if_icmpge -> 9391
    //   9256: aload #5
    //   9258: iload #7
    //   9260: aaload
    //   9261: astore #8
    //   9263: aload #8
    //   9265: invokevirtual getModifiers : ()I
    //   9268: invokestatic isStatic : (I)Z
    //   9271: ifne -> 9281
    //   9274: goto -> 9384
    //   9277: invokestatic a : (Ljava/lang/Throwable;)Ljava/lang/Throwable;
    //   9280: athrow
    //   9281: aload #8
    //   9283: invokevirtual getType : ()Ljava/lang/Class;
    //   9286: astore #9
    //   9288: aload #9
    //   9290: ifnull -> 9371
    //   9293: aload #9
    //   9295: invokevirtual isPrimitive : ()Z
    //   9298: ifne -> 9371
    //   9301: goto -> 9308
    //   9304: invokestatic a : (Ljava/lang/Throwable;)Ljava/lang/Throwable;
    //   9307: athrow
    //   9308: aload #9
    //   9310: invokevirtual getPackage : ()Ljava/lang/Package;
    //   9313: ifnull -> 9371
    //   9316: goto -> 9323
    //   9319: invokestatic a : (Ljava/lang/Throwable;)Ljava/lang/Throwable;
    //   9322: athrow
    //   9323: aload #9
    //   9325: invokevirtual getPackage : ()Ljava/lang/Package;
    //   9328: invokevirtual getName : ()Ljava/lang/String;
    //   9331: ifnull -> 9371
    //   9334: goto -> 9341
    //   9337: invokestatic a : (Ljava/lang/Throwable;)Ljava/lang/Throwable;
    //   9340: athrow
    //   9341: aload #9
    //   9343: invokevirtual getPackage : ()Ljava/lang/Package;
    //   9346: invokevirtual getName : ()Ljava/lang/String;
    //   9349: sipush #29826
    //   9352: sipush #10395
    //   9355: invokestatic a : (II)Ljava/lang/String;
    //   9358: invokevirtual startsWith : (Ljava/lang/String;)Z
    //   9361: ifne -> 9371
    //   9364: goto -> 9371
    //   9367: invokestatic a : (Ljava/lang/Throwable;)Ljava/lang/Throwable;
    //   9370: athrow
    //   9371: aload #8
    //   9373: iconst_1
    //   9374: invokevirtual setAccessible : (Z)V
    //   9377: aload #8
    //   9379: aconst_null
    //   9380: invokevirtual get : (Ljava/lang/Object;)Ljava/lang/Object;
    //   9383: pop
    //   9384: iinc #7, 1
    //   9387: iload_2
    //   9388: ifne -> 9249
    //   9391: sipush #29849
    //   9394: sipush #1439
    //   9397: invokestatic a : (II)Ljava/lang/String;
    //   9400: invokestatic forName : (Ljava/lang/String;)Ljava/lang/Class;
    //   9403: invokevirtual getDeclaredMethods : ()[Ljava/lang/reflect/Method;
    //   9406: astore #5
    //   9408: aload #5
    //   9410: arraylength
    //   9411: istore #6
    //   9413: iconst_0
    //   9414: istore #7
    //   9416: iload #7
    //   9418: iload #6
    //   9420: if_icmpge -> 9557
    //   9423: aload #5
    //   9425: iload #7
    //   9427: aaload
    //   9428: astore #8
    //   9430: aload #8
    //   9432: invokevirtual getParameterTypes : ()[Ljava/lang/Class;
    //   9435: pop
    //   9436: aload #8
    //   9438: invokevirtual getModifiers : ()I
    //   9441: invokestatic isStatic : (I)Z
    //   9444: ifeq -> 9543
    //   9447: aload #8
    //   9449: invokevirtual getParameterTypes : ()[Ljava/lang/Class;
    //   9452: arraylength
    //   9453: iconst_2
    //   9454: if_icmpne -> 9543
    //   9457: goto -> 9464
    //   9460: invokestatic a : (Ljava/lang/Throwable;)Ljava/lang/Throwable;
    //   9463: athrow
    //   9464: aload #8
    //   9466: invokevirtual getReturnType : ()Ljava/lang/Class;
    //   9469: getstatic java/lang/Boolean.TYPE : Ljava/lang/Class;
    //   9472: if_acmpne -> 9543
    //   9475: goto -> 9482
    //   9478: invokestatic a : (Ljava/lang/Throwable;)Ljava/lang/Throwable;
    //   9481: athrow
    //   9482: aload #8
    //   9484: iconst_1
    //   9485: invokevirtual setAccessible : (Z)V
    //   9488: aload #8
    //   9490: aconst_null
    //   9491: iconst_2
    //   9492: anewarray java/lang/Object
    //   9495: dup
    //   9496: iconst_0
    //   9497: aload_0
    //   9498: aastore
    //   9499: dup
    //   9500: iconst_1
    //   9501: aload_1
    //   9502: ifnonnull -> 9520
    //   9505: goto -> 9512
    //   9508: invokestatic a : (Ljava/lang/Throwable;)Ljava/lang/Throwable;
    //   9511: athrow
    //   9512: aload_1
    //   9513: goto -> 9527
    //   9516: invokestatic a : (Ljava/lang/Throwable;)Ljava/lang/Throwable;
    //   9519: athrow
    //   9520: aload_1
    //   9521: checkcast [B
    //   9524: invokevirtual clone : ()Ljava/lang/Object;
    //   9527: aastore
    //   9528: invokevirtual invoke : (Ljava/lang/Object;[Ljava/lang/Object;)Ljava/lang/Object;
    //   9531: checkcast java/lang/Boolean
    //   9534: invokevirtual booleanValue : ()Z
    //   9537: istore #4
    //   9539: iload_2
    //   9540: ifne -> 9557
    //   9543: iinc #7, 1
    //   9546: iload_2
    //   9547: ifne -> 9416
    //   9550: goto -> 9557
    //   9553: invokestatic a : (Ljava/lang/Throwable;)Ljava/lang/Throwable;
    //   9556: athrow
    //   9557: iload_2
    //   9558: ifne -> 9900
    //   9561: sipush #29827
    //   9564: sipush #-810
    //   9567: invokestatic a : (II)Ljava/lang/String;
    //   9570: iconst_1
    //   9571: ldc burp/Zrw7
    //   9573: invokevirtual getClassLoader : ()Ljava/lang/ClassLoader;
    //   9576: invokestatic forName : (Ljava/lang/String;ZLjava/lang/ClassLoader;)Ljava/lang/Class;
    //   9579: invokevirtual getDeclaredFields : ()[Ljava/lang/reflect/Field;
    //   9582: astore #5
    //   9584: aload #5
    //   9586: arraylength
    //   9587: istore #6
    //   9589: iconst_0
    //   9590: istore #7
    //   9592: iload #7
    //   9594: iload #6
    //   9596: if_icmpge -> 9734
    //   9599: aload #5
    //   9601: iload #7
    //   9603: aaload
    //   9604: astore #8
    //   9606: aload #8
    //   9608: invokevirtual getModifiers : ()I
    //   9611: invokestatic isStatic : (I)Z
    //   9614: ifne -> 9624
    //   9617: goto -> 9727
    //   9620: invokestatic a : (Ljava/lang/Throwable;)Ljava/lang/Throwable;
    //   9623: athrow
    //   9624: aload #8
    //   9626: invokevirtual getType : ()Ljava/lang/Class;
    //   9629: astore #9
    //   9631: aload #9
    //   9633: ifnull -> 9714
    //   9636: aload #9
    //   9638: invokevirtual isPrimitive : ()Z
    //   9641: ifne -> 9714
    //   9644: goto -> 9651
    //   9647: invokestatic a : (Ljava/lang/Throwable;)Ljava/lang/Throwable;
    //   9650: athrow
    //   9651: aload #9
    //   9653: invokevirtual getPackage : ()Ljava/lang/Package;
    //   9656: ifnull -> 9714
    //   9659: goto -> 9666
    //   9662: invokestatic a : (Ljava/lang/Throwable;)Ljava/lang/Throwable;
    //   9665: athrow
    //   9666: aload #9
    //   9668: invokevirtual getPackage : ()Ljava/lang/Package;
    //   9671: invokevirtual getName : ()Ljava/lang/String;
    //   9674: ifnull -> 9714
    //   9677: goto -> 9684
    //   9680: invokestatic a : (Ljava/lang/Throwable;)Ljava/lang/Throwable;
    //   9683: athrow
    //   9684: aload #9
    //   9686: invokevirtual getPackage : ()Ljava/lang/Package;
    //   9689: invokevirtual getName : ()Ljava/lang/String;
    //   9692: sipush #29826
    //   9695: sipush #10395
    //   9698: invokestatic a : (II)Ljava/lang/String;
    //   9701: invokevirtual startsWith : (Ljava/lang/String;)Z
    //   9704: ifne -> 9714
    //   9707: goto -> 9714
    //   9710: invokestatic a : (Ljava/lang/Throwable;)Ljava/lang/Throwable;
    //   9713: athrow
    //   9714: aload #8
    //   9716: iconst_1
    //   9717: invokevirtual setAccessible : (Z)V
    //   9720: aload #8
    //   9722: aconst_null
    //   9723: invokevirtual get : (Ljava/lang/Object;)Ljava/lang/Object;
    //   9726: pop
    //   9727: iinc #7, 1
    //   9730: iload_2
    //   9731: ifne -> 9592
    //   9734: sipush #29855
    //   9737: sipush #-12722
    //   9740: invokestatic a : (II)Ljava/lang/String;
    //   9743: invokestatic forName : (Ljava/lang/String;)Ljava/lang/Class;
    //   9746: invokevirtual getDeclaredMethods : ()[Ljava/lang/reflect/Method;
    //   9749: astore #5
    //   9751: aload #5
    //   9753: arraylength
    //   9754: istore #6
    //   9756: iconst_0
    //   9757: istore #7
    //   9759: iload #7
    //   9761: iload #6
    //   9763: if_icmpge -> 9900
    //   9766: aload #5
    //   9768: iload #7
    //   9770: aaload
    //   9771: astore #8
    //   9773: aload #8
    //   9775: invokevirtual getParameterTypes : ()[Ljava/lang/Class;
    //   9778: pop
    //   9779: aload #8
    //   9781: invokevirtual getModifiers : ()I
    //   9784: invokestatic isStatic : (I)Z
    //   9787: ifeq -> 9886
    //   9790: aload #8
    //   9792: invokevirtual getParameterTypes : ()[Ljava/lang/Class;
    //   9795: arraylength
    //   9796: iconst_2
    //   9797: if_icmpne -> 9886
    //   9800: goto -> 9807
    //   9803: invokestatic a : (Ljava/lang/Throwable;)Ljava/lang/Throwable;
    //   9806: athrow
    //   9807: aload #8
    //   9809: invokevirtual getReturnType : ()Ljava/lang/Class;
    //   9812: getstatic java/lang/Boolean.TYPE : Ljava/lang/Class;
    //   9815: if_acmpne -> 9886
    //   9818: goto -> 9825
    //   9821: invokestatic a : (Ljava/lang/Throwable;)Ljava/lang/Throwable;
    //   9824: athrow
    //   9825: aload #8
    //   9827: iconst_1
    //   9828: invokevirtual setAccessible : (Z)V
    //   9831: aload #8
    //   9833: aconst_null
    //   9834: iconst_2
    //   9835: anewarray java/lang/Object
    //   9838: dup
    //   9839: iconst_0
    //   9840: aload_0
    //   9841: aastore
    //   9842: dup
    //   9843: iconst_1
    //   9844: aload_1
    //   9845: ifnonnull -> 9863
    //   9848: goto -> 9855
    //   9851: invokestatic a : (Ljava/lang/Throwable;)Ljava/lang/Throwable;
    //   9854: athrow
    //   9855: aload_1
    //   9856: goto -> 9870
    //   9859: invokestatic a : (Ljava/lang/Throwable;)Ljava/lang/Throwable;
    //   9862: athrow
    //   9863: aload_1
    //   9864: checkcast [B
    //   9867: invokevirtual clone : ()Ljava/lang/Object;
    //   9870: aastore
    //   9871: invokevirtual invoke : (Ljava/lang/Object;[Ljava/lang/Object;)Ljava/lang/Object;
    //   9874: checkcast java/lang/Boolean
    //   9877: invokevirtual booleanValue : ()Z
    //   9880: istore #4
    //   9882: iload_2
    //   9883: ifne -> 9900
    //   9886: iinc #7, 1
    //   9889: iload_2
    //   9890: ifne -> 9759
    //   9893: goto -> 9900
    //   9896: invokestatic a : (Ljava/lang/Throwable;)Ljava/lang/Throwable;
    //   9899: athrow
    //   9900: iload #4
    //   9902: ireturn
    //   9903: astore_3
    //   9904: new java/lang/Exception
    //   9907: dup
    //   9908: aload_3
    //   9909: invokevirtual getMessage : ()Ljava/lang/String;
    //   9912: invokespecial <init> : (Ljava/lang/String;)V
    //   9915: athrow
    // Exception table:
    //   from	to	target	type
    //   4	7702	9903	java/lang/Throwable
    //   4353	4526	4529	java/lang/Throwable
    //   4496	4563	4566	java/lang/Throwable
    //   4533	4600	4603	java/lang/Throwable
    //   4570	4637	4640	java/lang/Throwable
    //   4607	4674	4677	java/lang/Throwable
    //   4644	4711	4714	java/lang/Throwable
    //   4681	4748	4751	java/lang/Throwable
    //   4718	4785	4788	java/lang/Throwable
    //   4755	4822	4825	java/lang/Throwable
    //   4792	4859	4862	java/lang/Throwable
    //   4829	4896	4899	java/lang/Throwable
    //   4866	4933	4936	java/lang/Throwable
    //   4903	4970	4973	java/lang/Throwable
    //   4940	5007	5010	java/lang/Throwable
    //   4977	5044	5047	java/lang/Throwable
    //   5014	5081	5084	java/lang/Throwable
    //   5051	5118	5121	java/lang/Throwable
    //   5088	5155	5158	java/lang/Throwable
    //   5125	5192	5195	java/lang/Throwable
    //   5162	5229	5232	java/lang/Throwable
    //   5199	5266	5269	java/lang/Throwable
    //   5236	5303	5306	java/lang/Throwable
    //   5273	5340	5343	java/lang/Throwable
    //   5310	5377	5380	java/lang/Throwable
    //   5347	5414	5417	java/lang/Throwable
    //   5384	5451	5454	java/lang/Throwable
    //   5421	5488	5491	java/lang/Throwable
    //   5458	5525	5528	java/lang/Throwable
    //   5495	5562	5565	java/lang/Throwable
    //   5532	5599	5602	java/lang/Throwable
    //   5569	5636	5639	java/lang/Throwable
    //   5606	5669	5672	java/lang/Throwable
    //   5876	5900	5903	java/lang/Throwable
    //   5974	6011	6011	java/lang/Throwable
    //   6015	6036	6036	java/lang/Throwable
    //   6040	6070	6070	java/lang/Throwable
    //   6313	6327	6327	java/lang/Throwable
    //   6338	6351	6354	java/lang/Throwable
    //   6343	6366	6369	java/lang/Throwable
    //   6358	6384	6387	java/lang/Throwable
    //   6373	6414	6417	java/lang/Throwable
    //   6480	6507	6510	java/lang/Throwable
    //   6497	6528	6531	java/lang/Throwable
    //   6514	6558	6561	java/lang/Throwable
    //   6535	6569	6569	java/lang/Throwable
    //   6580	6596	6599	java/lang/Throwable
    //   6676	6690	6690	java/lang/Throwable
    //   6701	6714	6717	java/lang/Throwable
    //   6706	6729	6732	java/lang/Throwable
    //   6721	6747	6750	java/lang/Throwable
    //   6736	6777	6780	java/lang/Throwable
    //   6843	6870	6873	java/lang/Throwable
    //   6860	6891	6894	java/lang/Throwable
    //   6877	6921	6924	java/lang/Throwable
    //   6898	6932	6932	java/lang/Throwable
    //   6943	6959	6962	java/lang/Throwable
    //   7059	7073	7073	java/lang/Throwable
    //   7084	7097	7100	java/lang/Throwable
    //   7089	7112	7115	java/lang/Throwable
    //   7104	7130	7133	java/lang/Throwable
    //   7119	7160	7163	java/lang/Throwable
    //   7226	7253	7256	java/lang/Throwable
    //   7243	7271	7274	java/lang/Throwable
    //   7260	7301	7304	java/lang/Throwable
    //   7278	7312	7312	java/lang/Throwable
    //   7335	7346	7349	java/lang/Throwable
    //   7401	7415	7415	java/lang/Throwable
    //   7426	7439	7442	java/lang/Throwable
    //   7431	7454	7457	java/lang/Throwable
    //   7446	7472	7475	java/lang/Throwable
    //   7461	7502	7505	java/lang/Throwable
    //   7568	7595	7598	java/lang/Throwable
    //   7585	7613	7616	java/lang/Throwable
    //   7602	7643	7646	java/lang/Throwable
    //   7620	7654	7654	java/lang/Throwable
    //   7677	7688	7691	java/lang/Throwable
    //   7703	8437	9903	java/lang/Throwable
    //   7793	7807	7807	java/lang/Throwable
    //   7818	7831	7834	java/lang/Throwable
    //   7823	7846	7849	java/lang/Throwable
    //   7838	7864	7867	java/lang/Throwable
    //   7853	7894	7897	java/lang/Throwable
    //   7960	7987	7990	java/lang/Throwable
    //   7977	8005	8008	java/lang/Throwable
    //   7994	8035	8038	java/lang/Throwable
    //   8012	8046	8046	java/lang/Throwable
    //   8069	8080	8083	java/lang/Throwable
    //   8136	8150	8150	java/lang/Throwable
    //   8161	8174	8177	java/lang/Throwable
    //   8166	8189	8192	java/lang/Throwable
    //   8181	8207	8210	java/lang/Throwable
    //   8196	8237	8240	java/lang/Throwable
    //   8303	8330	8333	java/lang/Throwable
    //   8320	8348	8351	java/lang/Throwable
    //   8337	8378	8381	java/lang/Throwable
    //   8355	8389	8389	java/lang/Throwable
    //   8412	8423	8426	java/lang/Throwable
    //   8438	9172	9903	java/lang/Throwable
    //   8528	8542	8542	java/lang/Throwable
    //   8553	8566	8569	java/lang/Throwable
    //   8558	8581	8584	java/lang/Throwable
    //   8573	8599	8602	java/lang/Throwable
    //   8588	8629	8632	java/lang/Throwable
    //   8695	8722	8725	java/lang/Throwable
    //   8712	8740	8743	java/lang/Throwable
    //   8729	8770	8773	java/lang/Throwable
    //   8747	8781	8781	java/lang/Throwable
    //   8804	8815	8818	java/lang/Throwable
    //   8871	8885	8885	java/lang/Throwable
    //   8896	8909	8912	java/lang/Throwable
    //   8901	8924	8927	java/lang/Throwable
    //   8916	8942	8945	java/lang/Throwable
    //   8931	8972	8975	java/lang/Throwable
    //   9038	9065	9068	java/lang/Throwable
    //   9055	9083	9086	java/lang/Throwable
    //   9072	9113	9116	java/lang/Throwable
    //   9090	9124	9124	java/lang/Throwable
    //   9147	9158	9161	java/lang/Throwable
    //   9173	9902	9903	java/lang/Throwable
    //   9263	9277	9277	java/lang/Throwable
    //   9288	9301	9304	java/lang/Throwable
    //   9293	9316	9319	java/lang/Throwable
    //   9308	9334	9337	java/lang/Throwable
    //   9323	9364	9367	java/lang/Throwable
    //   9430	9457	9460	java/lang/Throwable
    //   9447	9475	9478	java/lang/Throwable
    //   9464	9505	9508	java/lang/Throwable
    //   9482	9516	9516	java/lang/Throwable
    //   9539	9550	9553	java/lang/Throwable
    //   9606	9620	9620	java/lang/Throwable
    //   9631	9644	9647	java/lang/Throwable
    //   9636	9659	9662	java/lang/Throwable
    //   9651	9677	9680	java/lang/Throwable
    //   9666	9707	9710	java/lang/Throwable
    //   9773	9800	9803	java/lang/Throwable
    //   9790	9818	9821	java/lang/Throwable
    //   9807	9848	9851	java/lang/Throwable
    //   9825	9859	9859	java/lang/Throwable
    //   9882	9893	9896	java/lang/Throwable
  }
  
  static {
    // Byte code:
    //   0: bipush #28
    //   2: anewarray java/lang/String
    //   5: astore #5
    //   7: iconst_0
    //   8: istore_3
    //   9: ldc 'f\\tNc4-@ 25h<_ykm)7\\rC0M;/.K1Px%|A\\rZ2E:^Ac\\tB'3%8q\\n\\t\\nA\\t`Iod;\\t4Uu\\tAI|\\t@s F& e\\tdz-\\tqX|V\\t1\\t*> \\t@NA\\t\\tC K\\tDm\\f\\fh+\\t<f^\\t\\tIR!\\t9&I\\tC0yFM[0\\tJaKT+BV$]s\JjH|K)&iOaX\\n3'k 6"-!d0k 0Pz\\t5Mz+1\\tf\\rS{'
    //   11: dup
    //   12: astore_2
    //   13: invokevirtual length : ()I
    //   16: istore #4
    //   18: bipush #9
    //   20: istore_1
    //   21: iconst_m1
    //   22: istore_0
    //   23: bipush #127
    //   25: iinc #0, 1
    //   28: aload_2
    //   29: iload_0
    //   30: dup
    //   31: iload_1
    //   32: iadd
    //   33: invokevirtual substring : (II)Ljava/lang/String;
    //   36: iconst_m1
    //   37: goto -> 142
    //   40: aload #5
    //   42: swap
    //   43: iload_3
    //   44: iinc #3, 1
    //   47: swap
    //   48: aastore
    //   49: iload_0
    //   50: iload_1
    //   51: iadd
    //   52: dup
    //   53: istore_0
    //   54: iload #4
    //   56: if_icmpge -> 68
    //   59: aload_2
    //   60: iload_0
    //   61: invokevirtual charAt : (I)C
    //   64: istore_1
    //   65: goto -> 23
    //   68: ldc 'F\\t@\\n>HC'
    //   70: dup
    //   71: astore_2
    //   72: invokevirtual length : ()I
    //   75: istore #4
    //   77: iconst_4
    //   78: istore_1
    //   79: iconst_m1
    //   80: istore_0
    //   81: bipush #88
    //   83: iinc #0, 1
    //   86: aload_2
    //   87: iload_0
    //   88: dup
    //   89: iload_1
    //   90: iadd
    //   91: invokevirtual substring : (II)Ljava/lang/String;
    //   94: iconst_0
    //   95: goto -> 142
    //   98: aload #5
    //   100: swap
    //   101: iload_3
    //   102: iinc #3, 1
    //   105: swap
    //   106: aastore
    //   107: iload_0
    //   108: iload_1
    //   109: iadd
    //   110: dup
    //   111: istore_0
    //   112: iload #4
    //   114: if_icmpge -> 126
    //   117: aload_2
    //   118: iload_0
    //   119: invokevirtual charAt : (I)C
    //   122: istore_1
    //   123: goto -> 81
    //   126: aload #5
    //   128: putstatic burp/Zmh5.a : [Ljava/lang/String;
    //   131: bipush #28
    //   133: anewarray java/lang/String
    //   136: putstatic burp/Zmh5.b : [Ljava/lang/String;
    //   139: goto -> 300
    //   142: dup_x2
    //   143: pop
    //   144: invokevirtual toCharArray : ()[C
    //   147: dup_x1
    //   148: arraylength
    //   149: dup_x2
    //   150: pop
    //   151: iconst_0
    //   152: istore #6
    //   154: dup2_x1
    //   155: pop2
    //   156: dup_x2
    //   157: iconst_1
    //   158: if_icmpgt -> 260
    //   161: dup2
    //   162: swap
    //   163: iload #6
    //   165: dup2_x1
    //   166: caload
    //   167: swap
    //   168: iload #6
    //   170: bipush #7
    //   172: irem
    //   173: tableswitch default -> 242, 0 -> 212, 1 -> 217, 2 -> 222, 3 -> 227, 4 -> 232, 5 -> 237
    //   212: bipush #110
    //   214: goto -> 244
    //   217: bipush #28
    //   219: goto -> 244
    //   222: bipush #122
    //   224: goto -> 244
    //   227: bipush #71
    //   229: goto -> 244
    //   232: bipush #12
    //   234: goto -> 244
    //   237: bipush #26
    //   239: goto -> 244
    //   242: bipush #66
    //   244: ixor
    //   245: ixor
    //   246: i2c
    //   247: castore
    //   248: iinc #6, 1
    //   251: dup
    //   252: ifne -> 260
    //   255: dup2
    //   256: dup_x1
    //   257: goto -> 165
    //   260: dup2_x1
    //   261: pop2
    //   262: dup_x2
    //   263: iload #6
    //   265: if_icmpgt -> 161
    //   268: pop
    //   269: new java/lang/String
    //   272: dup_x1
    //   273: swap
    //   274: invokespecial <init> : ([C)V
    //   277: invokevirtual intern : ()Ljava/lang/String;
    //   280: swap
    //   281: pop
    //   282: swap
    //   283: tableswitch default -> 40, 0 -> 98
    //   300: sipush #29841
    //   303: sipush #-1557
    //   306: invokestatic a : (II)Ljava/lang/String;
    //   309: putstatic burp/Zmh5.Zh : Ljava/lang/String;
    //   312: new java/math/BigInteger
    //   315: dup
    //   316: sipush #29840
    //   319: sipush #32285
    //   322: invokestatic a : (II)Ljava/lang/String;
    //   325: invokespecial <init> : (Ljava/lang/String;)V
    //   328: putstatic burp/Zmh5.ZN : Ljava/lang/Object;
    //   331: return
  }
  
  private static Throwable a(Throwable paramThrowable) {
    return paramThrowable;
  }
  
  private static String a(int paramInt1, int paramInt2) {
    int i = (paramInt1 ^ 0x7493) & 0xFFFF;
    if (b[i] == null) {
      char[] arrayOfChar = a[i].toCharArray();
      switch (arrayOfChar[0] & 0xFF) {
        case 0:
        
        case 1:
        
        case 2:
        
        case 3:
        
        case 4:
        
        case 5:
        
        case 6:
        
        case 7:
        
        case 8:
        
        case 9:
        
        case 10:
        
        case 11:
        
        case 12:
        
        case 13:
        
        case 14:
        
        case 15:
        
        case 16:
        
        case 17:
        
        case 18:
        
        case 19:
        
        case 20:
        
        case 21:
        
        case 22:
        
        case 23:
        
        case 24:
        
        case 25:
        
        case 26:
        
        case 27:
        
        case 28:
        
        case 29:
        
        case 30:
        
        case 31:
        
        case 32:
        
        case 33:
        
        case 34:
        
        case 35:
        
        case 36:
        
        case 37:
        
        case 38:
        
        case 39:
        
        case 40:
        
        case 41:
        
        case 42:
        
        case 43:
        
        case 44:
        
        case 45:
        
        case 46:
        
        case 47:
        
        case 48:
        
        case 49:
        
        case 50:
        
        case 51:
        
        case 52:
        
        case 53:
        
        case 54:
        
        case 55:
        
        case 56:
        
        case 57:
        
        case 58:
        
        case 59:
        
        case 60:
        
        case 61:
        
        case 62:
        
        case 63:
        
        case 64:
        
        case 65:
        
        case 66:
        
        case 67:
        
        case 68:
        
        case 69:
        
        case 70:
        
        case 71:
        
        case 72:
        
        case 73:
        
        case 74:
        
        case 75:
        
        case 76:
        
        case 77:
        
        case 78:
        
        case 79:
        
        case 80:
        
        case 81:
        
        case 82:
        
        case 83:
        
        case 84:
        
        case 85:
        
        case 86:
        
        case 87:
        
        case 88:
        
        case 89:
        
        case 90:
        
        case 91:
        
        case 92:
        
        case 93:
        
        case 94:
        
        case 95:
        
        case 96:
        
        case 97:
        
        case 98:
        
        case 99:
        
        case 100:
        
        case 101:
        
        case 102:
        
        case 103:
        
        case 104:
        
        case 105:
        
        case 106:
        
        case 107:
        
        case 108:
        
        case 109:
        
        case 110:
        
        case 111:
        
        case 112:
        
        case 113:
        
        case 114:
        
        case 115:
        
        case 116:
        
        case 117:
        
        case 118:
        
        case 119:
        
        case 120:
        
        case 121:
        
        case 122:
        
        case 123:
        
        case 124:
        
        case 125:
        
        case 126:
        
        case 127:
        
        case 128:
        
        case 129:
        
        case 130:
        
        case 131:
        
        case 132:
        
        case 133:
        
        case 134:
        
        case 135:
        
        case 136:
        
        case 137:
        
        case 138:
        
        case 139:
        
        case 140:
        
        case 141:
        
        case 142:
        
        case 143:
        
        case 144:
        
        case 145:
        
        case 146:
        
        case 147:
        
        case 148:
        
        case 149:
        
        case 150:
        
        case 151:
        
        case 152:
        
        case 153:
        
        case 154:
        
        case 155:
        
        case 156:
        
        case 157:
        
        case 158:
        
        case 159:
        
        case 160:
        
        case 161:
        
        case 162:
        
        case 163:
        
        case 164:
        
        case 165:
        
        case 166:
        
        case 167:
        
        case 168:
        
        case 169:
        
        case 170:
        
        case 171:
        
        case 172:
        
        case 173:
        
        case 174:
        
        case 175:
        
        case 176:
        
        case 177:
        
        case 178:
        
        case 179:
        
        case 180:
        
        case 181:
        
        case 182:
        
        case 183:
        
        case 184:
        
        case 185:
        
        case 186:
        
        case 187:
        
        case 188:
        
        case 189:
        
        case 190:
        
        case 191:
        
        case 192:
        
        case 193:
        
        case 194:
        
        case 195:
        
        case 196:
        
        case 197:
        
        case 198:
        
        case 199:
        
        case 200:
        
        case 201:
        
        case 202:
        
        case 203:
        
        case 204:
        
        case 205:
        
        case 206:
        
        case 207:
        
        case 208:
        
        case 209:
        
        case 210:
        
        case 211:
        
        case 212:
        
        case 213:
        
        case 214:
        
        case 215:
        
        case 216:
        
        case 217:
        
        case 218:
        
        case 219:
        
        case 220:
        
        case 221:
        
        case 222:
        
        case 223:
        
        case 224:
        
        case 225:
        
        case 226:
        
        case 227:
        
        case 228:
        
        case 229:
        
        case 230:
        
        case 231:
        
        case 232:
        
        case 233:
        
        case 234:
        
        case 235:
        
        case 236:
        
        case 237:
        
        case 238:
        
        case 239:
        
        case 240:
        
        case 241:
        
        case 242:
        
        case 243:
        
        case 244:
        
        case 245:
        
        case 246:
        
        case 247:
        
        case 248:
        
        case 249:
        
        case 250:
        
        case 251:
        
        case 252:
        
        case 253:
        
        case 254:
        
        default:
          break;
      } 
      char c = '';
      int j = (paramInt2 & 0xFF) - c;
      if (j < 0)
        j += 256; 
      int k = ((paramInt2 & 0xFFFF) >>> 8) - c;
      if (k < 0)
        k += 256; 
      for (byte b = 0; b < arrayOfChar.length; b++) {
        int m = b % 2;
        if (m == 0) {
          arrayOfChar[b] = (char)(arrayOfChar[b] ^ j);
          j = ((j >>> 3 | j << 5) ^ arrayOfChar[b]) & 0xFF;
        } else {
          arrayOfChar[b] = (char)(arrayOfChar[b] ^ k);
          k = ((k >>> 3 | k << 5) ^ arrayOfChar[b]) & 0xFF;
        } 
      } 
      b[i] = (new String(arrayOfChar)).intern();
    } 
    return b[i];
  }
}


/* Location:              C:\Program Files\BurpSuitePro\burpsuite_pro.jar!\burp\Zmh5.class
 * Java compiler version: 21 (65.0)
 * JD-Core Version:       1.1.3
 */