package burp;

import java.math.BigInteger;

class Zml extends ClassLoader {
  static String ZN;
  
  static Object ZR;
  
  private static final String[] a;
  
  private static final String[] b;
  
  static void Zz(Object[] paramArrayOfObject, Object paramObject) throws Throwable {}
  
  static void Zs(Object paramObject) {
    Zmy4.ZS = a(-9502, 24479);
    Zmy4.ZB = new BigInteger(a(-9488, 23850));
    boolean bool = Zt2e.ZN();
    try {
      try {
        if (Zle6.Zh.charAt(Math.abs(((BigInteger)Zls0.ZZ).intValue() % 32)) > Zzmo.Zx.charAt(Math.abs(((BigInteger)Zb6a.Zz).intValue() % 32))) {
          try {
            Zzk9.Zo(Class.forName(a(-9496, 4729)));
            if (!bool)
              Zgp_.ZG(Class.forName(a(-9481, -24321))); 
          } catch (Throwable throwable) {
            throw a(null);
          } 
          return;
        } 
      } catch (Throwable throwable) {
        throw a(null);
      } 
      Zgp_.ZG(Class.forName(a(-9481, -24321)));
    } catch (Throwable throwable) {}
  }
  
  static boolean ZQ(Object[] paramArrayOfObject, Object paramObject) throws Throwable {
    // Byte code:
    //   0: invokestatic ZN : ()Z
    //   3: istore_2
    //   4: sipush #-9490
    //   7: sipush #-8805
    //   10: invokestatic a : (II)Ljava/lang/String;
    //   13: invokestatic forName : (Ljava/lang/String;)Ljava/lang/Class;
    //   16: invokestatic ZW : (Ljava/lang/Object;)V
    //   19: sipush #-9500
    //   22: getstatic burp/Zzyr.Za : Ljava/lang/Object;
    //   25: checkcast java/math/BigInteger
    //   28: getstatic burp/Zz9v.Zl : Ljava/lang/Object;
    //   31: checkcast java/math/BigInteger
    //   34: invokevirtual add : (Ljava/math/BigInteger;)Ljava/math/BigInteger;
    //   37: putstatic burp/Zl1n.ZM : Ljava/lang/Object;
    //   40: sipush #7862
    //   43: invokestatic a : (II)Ljava/lang/String;
    //   46: iconst_1
    //   47: ldc burp/Zlx5
    //   49: invokevirtual getClassLoader : ()Ljava/lang/ClassLoader;
    //   52: invokestatic forName : (Ljava/lang/String;ZLjava/lang/ClassLoader;)Ljava/lang/Class;
    //   55: invokevirtual getDeclaredFields : ()[Ljava/lang/reflect/Field;
    //   58: astore_3
    //   59: aload_3
    //   60: arraylength
    //   61: istore #4
    //   63: iconst_0
    //   64: istore #5
    //   66: iload #5
    //   68: iload #4
    //   70: if_icmpge -> 207
    //   73: aload_3
    //   74: iload #5
    //   76: aaload
    //   77: astore #6
    //   79: aload #6
    //   81: invokevirtual getModifiers : ()I
    //   84: invokestatic isStatic : (I)Z
    //   87: ifne -> 97
    //   90: goto -> 200
    //   93: invokestatic a : (Ljava/lang/Throwable;)Ljava/lang/Throwable;
    //   96: athrow
    //   97: aload #6
    //   99: invokevirtual getType : ()Ljava/lang/Class;
    //   102: astore #7
    //   104: aload #7
    //   106: ifnull -> 187
    //   109: aload #7
    //   111: invokevirtual isPrimitive : ()Z
    //   114: ifne -> 187
    //   117: goto -> 124
    //   120: invokestatic a : (Ljava/lang/Throwable;)Ljava/lang/Throwable;
    //   123: athrow
    //   124: aload #7
    //   126: invokevirtual getPackage : ()Ljava/lang/Package;
    //   129: ifnull -> 187
    //   132: goto -> 139
    //   135: invokestatic a : (Ljava/lang/Throwable;)Ljava/lang/Throwable;
    //   138: athrow
    //   139: aload #7
    //   141: invokevirtual getPackage : ()Ljava/lang/Package;
    //   144: invokevirtual getName : ()Ljava/lang/String;
    //   147: ifnull -> 187
    //   150: goto -> 157
    //   153: invokestatic a : (Ljava/lang/Throwable;)Ljava/lang/Throwable;
    //   156: athrow
    //   157: aload #7
    //   159: invokevirtual getPackage : ()Ljava/lang/Package;
    //   162: invokevirtual getName : ()Ljava/lang/String;
    //   165: sipush #-9478
    //   168: sipush #3409
    //   171: invokestatic a : (II)Ljava/lang/String;
    //   174: invokevirtual startsWith : (Ljava/lang/String;)Z
    //   177: ifne -> 187
    //   180: goto -> 187
    //   183: invokestatic a : (Ljava/lang/Throwable;)Ljava/lang/Throwable;
    //   186: athrow
    //   187: aload #6
    //   189: iconst_1
    //   190: invokevirtual setAccessible : (Z)V
    //   193: aload #6
    //   195: aconst_null
    //   196: invokevirtual get : (Ljava/lang/Object;)Ljava/lang/Object;
    //   199: pop
    //   200: iinc #5, 1
    //   203: iload_2
    //   204: ifne -> 66
    //   207: sipush #-9498
    //   210: sipush #30287
    //   213: invokestatic a : (II)Ljava/lang/String;
    //   216: invokestatic forName : (Ljava/lang/String;)Ljava/lang/Class;
    //   219: invokevirtual getDeclaredMethods : ()[Ljava/lang/reflect/Method;
    //   222: astore_3
    //   223: aload_3
    //   224: arraylength
    //   225: istore #4
    //   227: iconst_0
    //   228: istore #5
    //   230: iload #5
    //   232: iload #4
    //   234: if_icmpge -> 345
    //   237: aload_3
    //   238: iload #5
    //   240: aaload
    //   241: astore #6
    //   243: aload #6
    //   245: invokevirtual getParameterTypes : ()[Ljava/lang/Class;
    //   248: pop
    //   249: aload #6
    //   251: invokevirtual getModifiers : ()I
    //   254: invokestatic isStatic : (I)Z
    //   257: ifeq -> 331
    //   260: aload #6
    //   262: invokevirtual getParameterTypes : ()[Ljava/lang/Class;
    //   265: arraylength
    //   266: iconst_2
    //   267: if_icmpne -> 331
    //   270: goto -> 277
    //   273: invokestatic a : (Ljava/lang/Throwable;)Ljava/lang/Throwable;
    //   276: athrow
    //   277: aload #6
    //   279: invokevirtual getReturnType : ()Ljava/lang/Class;
    //   282: getstatic java/lang/Boolean.TYPE : Ljava/lang/Class;
    //   285: if_acmpne -> 331
    //   288: goto -> 295
    //   291: invokestatic a : (Ljava/lang/Throwable;)Ljava/lang/Throwable;
    //   294: athrow
    //   295: aload #6
    //   297: iconst_1
    //   298: invokevirtual setAccessible : (Z)V
    //   301: aload #6
    //   303: aconst_null
    //   304: iconst_2
    //   305: anewarray java/lang/Object
    //   308: dup
    //   309: iconst_0
    //   310: aload_0
    //   311: aastore
    //   312: dup
    //   313: iconst_1
    //   314: aload_1
    //   315: aastore
    //   316: invokevirtual invoke : (Ljava/lang/Object;[Ljava/lang/Object;)Ljava/lang/Object;
    //   319: pop
    //   320: iload_2
    //   321: ifne -> 345
    //   324: goto -> 331
    //   327: invokestatic a : (Ljava/lang/Throwable;)Ljava/lang/Throwable;
    //   330: athrow
    //   331: iinc #5, 1
    //   334: iload_2
    //   335: ifne -> 230
    //   338: goto -> 345
    //   341: invokestatic a : (Ljava/lang/Throwable;)Ljava/lang/Throwable;
    //   344: athrow
    //   345: sipush #-9487
    //   348: sipush #2205
    //   351: invokestatic a : (II)Ljava/lang/String;
    //   354: iconst_1
    //   355: ldc burp/Zmdi
    //   357: invokevirtual getClassLoader : ()Ljava/lang/ClassLoader;
    //   360: invokestatic forName : (Ljava/lang/String;ZLjava/lang/ClassLoader;)Ljava/lang/Class;
    //   363: invokevirtual getDeclaredFields : ()[Ljava/lang/reflect/Field;
    //   366: astore_3
    //   367: aload_3
    //   368: arraylength
    //   369: istore #4
    //   371: iconst_0
    //   372: istore #5
    //   374: iload #5
    //   376: iload #4
    //   378: if_icmpge -> 515
    //   381: aload_3
    //   382: iload #5
    //   384: aaload
    //   385: astore #6
    //   387: aload #6
    //   389: invokevirtual getModifiers : ()I
    //   392: invokestatic isStatic : (I)Z
    //   395: ifne -> 405
    //   398: goto -> 508
    //   401: invokestatic a : (Ljava/lang/Throwable;)Ljava/lang/Throwable;
    //   404: athrow
    //   405: aload #6
    //   407: invokevirtual getType : ()Ljava/lang/Class;
    //   410: astore #7
    //   412: aload #7
    //   414: ifnull -> 495
    //   417: aload #7
    //   419: invokevirtual isPrimitive : ()Z
    //   422: ifne -> 495
    //   425: goto -> 432
    //   428: invokestatic a : (Ljava/lang/Throwable;)Ljava/lang/Throwable;
    //   431: athrow
    //   432: aload #7
    //   434: invokevirtual getPackage : ()Ljava/lang/Package;
    //   437: ifnull -> 495
    //   440: goto -> 447
    //   443: invokestatic a : (Ljava/lang/Throwable;)Ljava/lang/Throwable;
    //   446: athrow
    //   447: aload #7
    //   449: invokevirtual getPackage : ()Ljava/lang/Package;
    //   452: invokevirtual getName : ()Ljava/lang/String;
    //   455: ifnull -> 495
    //   458: goto -> 465
    //   461: invokestatic a : (Ljava/lang/Throwable;)Ljava/lang/Throwable;
    //   464: athrow
    //   465: aload #7
    //   467: invokevirtual getPackage : ()Ljava/lang/Package;
    //   470: invokevirtual getName : ()Ljava/lang/String;
    //   473: sipush #-9499
    //   476: sipush #-28262
    //   479: invokestatic a : (II)Ljava/lang/String;
    //   482: invokevirtual startsWith : (Ljava/lang/String;)Z
    //   485: ifne -> 495
    //   488: goto -> 495
    //   491: invokestatic a : (Ljava/lang/Throwable;)Ljava/lang/Throwable;
    //   494: athrow
    //   495: aload #6
    //   497: iconst_1
    //   498: invokevirtual setAccessible : (Z)V
    //   501: aload #6
    //   503: aconst_null
    //   504: invokevirtual get : (Ljava/lang/Object;)Ljava/lang/Object;
    //   507: pop
    //   508: iinc #5, 1
    //   511: iload_2
    //   512: ifne -> 374
    //   515: sipush #-9485
    //   518: sipush #-15700
    //   521: invokestatic a : (II)Ljava/lang/String;
    //   524: invokestatic forName : (Ljava/lang/String;)Ljava/lang/Class;
    //   527: invokevirtual getDeclaredMethods : ()[Ljava/lang/reflect/Method;
    //   530: astore_3
    //   531: aload_3
    //   532: arraylength
    //   533: istore #4
    //   535: iconst_0
    //   536: istore #5
    //   538: iload #5
    //   540: iload #4
    //   542: if_icmpge -> 674
    //   545: aload_3
    //   546: iload #5
    //   548: aaload
    //   549: astore #6
    //   551: aload #6
    //   553: invokevirtual getParameterTypes : ()[Ljava/lang/Class;
    //   556: pop
    //   557: aload #6
    //   559: invokevirtual getModifiers : ()I
    //   562: invokestatic isStatic : (I)Z
    //   565: ifeq -> 660
    //   568: aload #6
    //   570: invokevirtual getParameterTypes : ()[Ljava/lang/Class;
    //   573: arraylength
    //   574: iconst_2
    //   575: if_icmpne -> 660
    //   578: goto -> 585
    //   581: invokestatic a : (Ljava/lang/Throwable;)Ljava/lang/Throwable;
    //   584: athrow
    //   585: aload #6
    //   587: invokevirtual getReturnType : ()Ljava/lang/Class;
    //   590: getstatic java/lang/Void.TYPE : Ljava/lang/Class;
    //   593: invokevirtual equals : (Ljava/lang/Object;)Z
    //   596: ifeq -> 660
    //   599: goto -> 606
    //   602: invokestatic a : (Ljava/lang/Throwable;)Ljava/lang/Throwable;
    //   605: athrow
    //   606: aload #6
    //   608: iconst_1
    //   609: invokevirtual setAccessible : (Z)V
    //   612: aload #6
    //   614: aconst_null
    //   615: iconst_2
    //   616: anewarray java/lang/Object
    //   619: dup
    //   620: iconst_0
    //   621: aload_0
    //   622: aastore
    //   623: dup
    //   624: iconst_1
    //   625: aload_1
    //   626: ifnonnull -> 644
    //   629: goto -> 636
    //   632: invokestatic a : (Ljava/lang/Throwable;)Ljava/lang/Throwable;
    //   635: athrow
    //   636: aload_1
    //   637: goto -> 651
    //   640: invokestatic a : (Ljava/lang/Throwable;)Ljava/lang/Throwable;
    //   643: athrow
    //   644: aload_1
    //   645: checkcast [B
    //   648: invokevirtual clone : ()Ljava/lang/Object;
    //   651: aastore
    //   652: invokevirtual invoke : (Ljava/lang/Object;[Ljava/lang/Object;)Ljava/lang/Object;
    //   655: pop
    //   656: iload_2
    //   657: ifne -> 674
    //   660: iinc #5, 1
    //   663: iload_2
    //   664: ifne -> 538
    //   667: goto -> 674
    //   670: invokestatic a : (Ljava/lang/Throwable;)Ljava/lang/Throwable;
    //   673: athrow
    //   674: iconst_0
    //   675: istore_3
    //   676: getstatic burp/Zlp8.ZW : Ljava/lang/String;
    //   679: getstatic burp/Zbqk.ZT : Ljava/lang/Object;
    //   682: checkcast java/math/BigInteger
    //   685: invokevirtual intValue : ()I
    //   688: bipush #32
    //   690: irem
    //   691: invokestatic abs : (I)I
    //   694: invokevirtual charAt : (I)C
    //   697: getstatic burp/Zg68.Zg : Ljava/lang/String;
    //   700: getstatic burp/Zgia.Zx : Ljava/lang/Object;
    //   703: checkcast java/math/BigInteger
    //   706: invokevirtual intValue : ()I
    //   709: bipush #32
    //   711: irem
    //   712: invokestatic abs : (I)I
    //   715: invokevirtual charAt : (I)C
    //   718: if_icmple -> 1062
    //   721: sipush #-9480
    //   724: sipush #20553
    //   727: invokestatic a : (II)Ljava/lang/String;
    //   730: iconst_1
    //   731: ldc burp/Zel
    //   733: invokevirtual getClassLoader : ()Ljava/lang/ClassLoader;
    //   736: invokestatic forName : (Ljava/lang/String;ZLjava/lang/ClassLoader;)Ljava/lang/Class;
    //   739: invokevirtual getDeclaredFields : ()[Ljava/lang/reflect/Field;
    //   742: astore #4
    //   744: aload #4
    //   746: arraylength
    //   747: istore #5
    //   749: iconst_0
    //   750: istore #6
    //   752: iload #6
    //   754: iload #5
    //   756: if_icmpge -> 894
    //   759: aload #4
    //   761: iload #6
    //   763: aaload
    //   764: astore #7
    //   766: aload #7
    //   768: invokevirtual getModifiers : ()I
    //   771: invokestatic isStatic : (I)Z
    //   774: ifne -> 784
    //   777: goto -> 887
    //   780: invokestatic a : (Ljava/lang/Throwable;)Ljava/lang/Throwable;
    //   783: athrow
    //   784: aload #7
    //   786: invokevirtual getType : ()Ljava/lang/Class;
    //   789: astore #8
    //   791: aload #8
    //   793: ifnull -> 874
    //   796: aload #8
    //   798: invokevirtual isPrimitive : ()Z
    //   801: ifne -> 874
    //   804: goto -> 811
    //   807: invokestatic a : (Ljava/lang/Throwable;)Ljava/lang/Throwable;
    //   810: athrow
    //   811: aload #8
    //   813: invokevirtual getPackage : ()Ljava/lang/Package;
    //   816: ifnull -> 874
    //   819: goto -> 826
    //   822: invokestatic a : (Ljava/lang/Throwable;)Ljava/lang/Throwable;
    //   825: athrow
    //   826: aload #8
    //   828: invokevirtual getPackage : ()Ljava/lang/Package;
    //   831: invokevirtual getName : ()Ljava/lang/String;
    //   834: ifnull -> 874
    //   837: goto -> 844
    //   840: invokestatic a : (Ljava/lang/Throwable;)Ljava/lang/Throwable;
    //   843: athrow
    //   844: aload #8
    //   846: invokevirtual getPackage : ()Ljava/lang/Package;
    //   849: invokevirtual getName : ()Ljava/lang/String;
    //   852: sipush #-9499
    //   855: sipush #-28262
    //   858: invokestatic a : (II)Ljava/lang/String;
    //   861: invokevirtual startsWith : (Ljava/lang/String;)Z
    //   864: ifne -> 874
    //   867: goto -> 874
    //   870: invokestatic a : (Ljava/lang/Throwable;)Ljava/lang/Throwable;
    //   873: athrow
    //   874: aload #7
    //   876: iconst_1
    //   877: invokevirtual setAccessible : (Z)V
    //   880: aload #7
    //   882: aconst_null
    //   883: invokevirtual get : (Ljava/lang/Object;)Ljava/lang/Object;
    //   886: pop
    //   887: iinc #6, 1
    //   890: iload_2
    //   891: ifne -> 752
    //   894: sipush #-9493
    //   897: sipush #28114
    //   900: invokestatic a : (II)Ljava/lang/String;
    //   903: invokestatic forName : (Ljava/lang/String;)Ljava/lang/Class;
    //   906: invokevirtual getDeclaredMethods : ()[Ljava/lang/reflect/Method;
    //   909: astore #4
    //   911: aload #4
    //   913: arraylength
    //   914: istore #5
    //   916: iconst_0
    //   917: istore #6
    //   919: iload #6
    //   921: iload #5
    //   923: if_icmpge -> 1059
    //   926: aload #4
    //   928: iload #6
    //   930: aaload
    //   931: astore #7
    //   933: aload #7
    //   935: invokevirtual getParameterTypes : ()[Ljava/lang/Class;
    //   938: pop
    //   939: aload #7
    //   941: invokevirtual getModifiers : ()I
    //   944: invokestatic isStatic : (I)Z
    //   947: ifeq -> 1045
    //   950: aload #7
    //   952: invokevirtual getParameterTypes : ()[Ljava/lang/Class;
    //   955: arraylength
    //   956: iconst_2
    //   957: if_icmpne -> 1045
    //   960: goto -> 967
    //   963: invokestatic a : (Ljava/lang/Throwable;)Ljava/lang/Throwable;
    //   966: athrow
    //   967: aload #7
    //   969: invokevirtual getReturnType : ()Ljava/lang/Class;
    //   972: getstatic java/lang/Boolean.TYPE : Ljava/lang/Class;
    //   975: if_acmpne -> 1045
    //   978: goto -> 985
    //   981: invokestatic a : (Ljava/lang/Throwable;)Ljava/lang/Throwable;
    //   984: athrow
    //   985: aload #7
    //   987: iconst_1
    //   988: invokevirtual setAccessible : (Z)V
    //   991: aload #7
    //   993: aconst_null
    //   994: iconst_2
    //   995: anewarray java/lang/Object
    //   998: dup
    //   999: iconst_0
    //   1000: aload_0
    //   1001: aastore
    //   1002: dup
    //   1003: iconst_1
    //   1004: aload_1
    //   1005: ifnonnull -> 1023
    //   1008: goto -> 1015
    //   1011: invokestatic a : (Ljava/lang/Throwable;)Ljava/lang/Throwable;
    //   1014: athrow
    //   1015: aload_1
    //   1016: goto -> 1030
    //   1019: invokestatic a : (Ljava/lang/Throwable;)Ljava/lang/Throwable;
    //   1022: athrow
    //   1023: aload_1
    //   1024: checkcast [B
    //   1027: invokevirtual clone : ()Ljava/lang/Object;
    //   1030: aastore
    //   1031: invokevirtual invoke : (Ljava/lang/Object;[Ljava/lang/Object;)Ljava/lang/Object;
    //   1034: checkcast java/lang/Boolean
    //   1037: invokevirtual booleanValue : ()Z
    //   1040: istore_3
    //   1041: iload_2
    //   1042: ifne -> 1059
    //   1045: iinc #6, 1
    //   1048: iload_2
    //   1049: ifne -> 919
    //   1052: goto -> 1059
    //   1055: invokestatic a : (Ljava/lang/Throwable;)Ljava/lang/Throwable;
    //   1058: athrow
    //   1059: goto -> 1400
    //   1062: sipush #-9492
    //   1065: sipush #-9757
    //   1068: invokestatic a : (II)Ljava/lang/String;
    //   1071: iconst_1
    //   1072: ldc burp/Zlhk
    //   1074: invokevirtual getClassLoader : ()Ljava/lang/ClassLoader;
    //   1077: invokestatic forName : (Ljava/lang/String;ZLjava/lang/ClassLoader;)Ljava/lang/Class;
    //   1080: invokevirtual getDeclaredFields : ()[Ljava/lang/reflect/Field;
    //   1083: astore #4
    //   1085: aload #4
    //   1087: arraylength
    //   1088: istore #5
    //   1090: iconst_0
    //   1091: istore #6
    //   1093: iload #6
    //   1095: iload #5
    //   1097: if_icmpge -> 1235
    //   1100: aload #4
    //   1102: iload #6
    //   1104: aaload
    //   1105: astore #7
    //   1107: aload #7
    //   1109: invokevirtual getModifiers : ()I
    //   1112: invokestatic isStatic : (I)Z
    //   1115: ifne -> 1125
    //   1118: goto -> 1228
    //   1121: invokestatic a : (Ljava/lang/Throwable;)Ljava/lang/Throwable;
    //   1124: athrow
    //   1125: aload #7
    //   1127: invokevirtual getType : ()Ljava/lang/Class;
    //   1130: astore #8
    //   1132: aload #8
    //   1134: ifnull -> 1215
    //   1137: aload #8
    //   1139: invokevirtual isPrimitive : ()Z
    //   1142: ifne -> 1215
    //   1145: goto -> 1152
    //   1148: invokestatic a : (Ljava/lang/Throwable;)Ljava/lang/Throwable;
    //   1151: athrow
    //   1152: aload #8
    //   1154: invokevirtual getPackage : ()Ljava/lang/Package;
    //   1157: ifnull -> 1215
    //   1160: goto -> 1167
    //   1163: invokestatic a : (Ljava/lang/Throwable;)Ljava/lang/Throwable;
    //   1166: athrow
    //   1167: aload #8
    //   1169: invokevirtual getPackage : ()Ljava/lang/Package;
    //   1172: invokevirtual getName : ()Ljava/lang/String;
    //   1175: ifnull -> 1215
    //   1178: goto -> 1185
    //   1181: invokestatic a : (Ljava/lang/Throwable;)Ljava/lang/Throwable;
    //   1184: athrow
    //   1185: aload #8
    //   1187: invokevirtual getPackage : ()Ljava/lang/Package;
    //   1190: invokevirtual getName : ()Ljava/lang/String;
    //   1193: sipush #-9499
    //   1196: sipush #-28262
    //   1199: invokestatic a : (II)Ljava/lang/String;
    //   1202: invokevirtual startsWith : (Ljava/lang/String;)Z
    //   1205: ifne -> 1215
    //   1208: goto -> 1215
    //   1211: invokestatic a : (Ljava/lang/Throwable;)Ljava/lang/Throwable;
    //   1214: athrow
    //   1215: aload #7
    //   1217: iconst_1
    //   1218: invokevirtual setAccessible : (Z)V
    //   1221: aload #7
    //   1223: aconst_null
    //   1224: invokevirtual get : (Ljava/lang/Object;)Ljava/lang/Object;
    //   1227: pop
    //   1228: iinc #6, 1
    //   1231: iload_2
    //   1232: ifne -> 1093
    //   1235: sipush #-9503
    //   1238: sipush #9447
    //   1241: invokestatic a : (II)Ljava/lang/String;
    //   1244: invokestatic forName : (Ljava/lang/String;)Ljava/lang/Class;
    //   1247: invokevirtual getDeclaredMethods : ()[Ljava/lang/reflect/Method;
    //   1250: astore #4
    //   1252: aload #4
    //   1254: arraylength
    //   1255: istore #5
    //   1257: iconst_0
    //   1258: istore #6
    //   1260: iload #6
    //   1262: iload #5
    //   1264: if_icmpge -> 1400
    //   1267: aload #4
    //   1269: iload #6
    //   1271: aaload
    //   1272: astore #7
    //   1274: aload #7
    //   1276: invokevirtual getParameterTypes : ()[Ljava/lang/Class;
    //   1279: pop
    //   1280: aload #7
    //   1282: invokevirtual getModifiers : ()I
    //   1285: invokestatic isStatic : (I)Z
    //   1288: ifeq -> 1386
    //   1291: aload #7
    //   1293: invokevirtual getParameterTypes : ()[Ljava/lang/Class;
    //   1296: arraylength
    //   1297: iconst_2
    //   1298: if_icmpne -> 1386
    //   1301: goto -> 1308
    //   1304: invokestatic a : (Ljava/lang/Throwable;)Ljava/lang/Throwable;
    //   1307: athrow
    //   1308: aload #7
    //   1310: invokevirtual getReturnType : ()Ljava/lang/Class;
    //   1313: getstatic java/lang/Boolean.TYPE : Ljava/lang/Class;
    //   1316: if_acmpne -> 1386
    //   1319: goto -> 1326
    //   1322: invokestatic a : (Ljava/lang/Throwable;)Ljava/lang/Throwable;
    //   1325: athrow
    //   1326: aload #7
    //   1328: iconst_1
    //   1329: invokevirtual setAccessible : (Z)V
    //   1332: aload #7
    //   1334: aconst_null
    //   1335: iconst_2
    //   1336: anewarray java/lang/Object
    //   1339: dup
    //   1340: iconst_0
    //   1341: aload_0
    //   1342: aastore
    //   1343: dup
    //   1344: iconst_1
    //   1345: aload_1
    //   1346: ifnonnull -> 1364
    //   1349: goto -> 1356
    //   1352: invokestatic a : (Ljava/lang/Throwable;)Ljava/lang/Throwable;
    //   1355: athrow
    //   1356: aload_1
    //   1357: goto -> 1371
    //   1360: invokestatic a : (Ljava/lang/Throwable;)Ljava/lang/Throwable;
    //   1363: athrow
    //   1364: aload_1
    //   1365: checkcast [B
    //   1368: invokevirtual clone : ()Ljava/lang/Object;
    //   1371: aastore
    //   1372: invokevirtual invoke : (Ljava/lang/Object;[Ljava/lang/Object;)Ljava/lang/Object;
    //   1375: checkcast java/lang/Boolean
    //   1378: invokevirtual booleanValue : ()Z
    //   1381: istore_3
    //   1382: iload_2
    //   1383: ifne -> 1400
    //   1386: iinc #6, 1
    //   1389: iload_2
    //   1390: ifne -> 1260
    //   1393: goto -> 1400
    //   1396: invokestatic a : (Ljava/lang/Throwable;)Ljava/lang/Throwable;
    //   1399: athrow
    //   1400: iload_3
    //   1401: ifeq -> 1406
    //   1404: iload_3
    //   1405: ireturn
    //   1406: getstatic burp/Zlkm.ZH : Ljava/lang/String;
    //   1409: getstatic burp/Ztsj.Zc : Ljava/lang/Object;
    //   1412: checkcast java/math/BigInteger
    //   1415: invokevirtual intValue : ()I
    //   1418: bipush #32
    //   1420: irem
    //   1421: invokestatic abs : (I)I
    //   1424: invokevirtual charAt : (I)C
    //   1427: getstatic burp/Zva.Zi : Ljava/lang/String;
    //   1430: getstatic burp/Zrn0.ZE : Ljava/lang/Object;
    //   1433: checkcast java/math/BigInteger
    //   1436: invokevirtual intValue : ()I
    //   1439: bipush #32
    //   1441: irem
    //   1442: invokestatic abs : (I)I
    //   1445: invokevirtual charAt : (I)C
    //   1448: if_icmpgt -> 1793
    //   1451: sipush #-9479
    //   1454: sipush #-3040
    //   1457: invokestatic a : (II)Ljava/lang/String;
    //   1460: iconst_1
    //   1461: ldc burp/Zm1l
    //   1463: invokevirtual getClassLoader : ()Ljava/lang/ClassLoader;
    //   1466: invokestatic forName : (Ljava/lang/String;ZLjava/lang/ClassLoader;)Ljava/lang/Class;
    //   1469: invokevirtual getDeclaredFields : ()[Ljava/lang/reflect/Field;
    //   1472: astore #4
    //   1474: aload #4
    //   1476: arraylength
    //   1477: istore #5
    //   1479: iconst_0
    //   1480: istore #6
    //   1482: iload #6
    //   1484: iload #5
    //   1486: if_icmpge -> 1624
    //   1489: aload #4
    //   1491: iload #6
    //   1493: aaload
    //   1494: astore #7
    //   1496: aload #7
    //   1498: invokevirtual getModifiers : ()I
    //   1501: invokestatic isStatic : (I)Z
    //   1504: ifne -> 1514
    //   1507: goto -> 1617
    //   1510: invokestatic a : (Ljava/lang/Throwable;)Ljava/lang/Throwable;
    //   1513: athrow
    //   1514: aload #7
    //   1516: invokevirtual getType : ()Ljava/lang/Class;
    //   1519: astore #8
    //   1521: aload #8
    //   1523: ifnull -> 1604
    //   1526: aload #8
    //   1528: invokevirtual isPrimitive : ()Z
    //   1531: ifne -> 1604
    //   1534: goto -> 1541
    //   1537: invokestatic a : (Ljava/lang/Throwable;)Ljava/lang/Throwable;
    //   1540: athrow
    //   1541: aload #8
    //   1543: invokevirtual getPackage : ()Ljava/lang/Package;
    //   1546: ifnull -> 1604
    //   1549: goto -> 1556
    //   1552: invokestatic a : (Ljava/lang/Throwable;)Ljava/lang/Throwable;
    //   1555: athrow
    //   1556: aload #8
    //   1558: invokevirtual getPackage : ()Ljava/lang/Package;
    //   1561: invokevirtual getName : ()Ljava/lang/String;
    //   1564: ifnull -> 1604
    //   1567: goto -> 1574
    //   1570: invokestatic a : (Ljava/lang/Throwable;)Ljava/lang/Throwable;
    //   1573: athrow
    //   1574: aload #8
    //   1576: invokevirtual getPackage : ()Ljava/lang/Package;
    //   1579: invokevirtual getName : ()Ljava/lang/String;
    //   1582: sipush #-9499
    //   1585: sipush #-28262
    //   1588: invokestatic a : (II)Ljava/lang/String;
    //   1591: invokevirtual startsWith : (Ljava/lang/String;)Z
    //   1594: ifne -> 1604
    //   1597: goto -> 1604
    //   1600: invokestatic a : (Ljava/lang/Throwable;)Ljava/lang/Throwable;
    //   1603: athrow
    //   1604: aload #7
    //   1606: iconst_1
    //   1607: invokevirtual setAccessible : (Z)V
    //   1610: aload #7
    //   1612: aconst_null
    //   1613: invokevirtual get : (Ljava/lang/Object;)Ljava/lang/Object;
    //   1616: pop
    //   1617: iinc #6, 1
    //   1620: iload_2
    //   1621: ifne -> 1482
    //   1624: sipush #-9494
    //   1627: sipush #-20769
    //   1630: invokestatic a : (II)Ljava/lang/String;
    //   1633: invokestatic forName : (Ljava/lang/String;)Ljava/lang/Class;
    //   1636: invokevirtual getDeclaredMethods : ()[Ljava/lang/reflect/Method;
    //   1639: astore #4
    //   1641: aload #4
    //   1643: arraylength
    //   1644: istore #5
    //   1646: iconst_0
    //   1647: istore #6
    //   1649: iload #6
    //   1651: iload #5
    //   1653: if_icmpge -> 1789
    //   1656: aload #4
    //   1658: iload #6
    //   1660: aaload
    //   1661: astore #7
    //   1663: aload #7
    //   1665: invokevirtual getParameterTypes : ()[Ljava/lang/Class;
    //   1668: pop
    //   1669: aload #7
    //   1671: invokevirtual getModifiers : ()I
    //   1674: invokestatic isStatic : (I)Z
    //   1677: ifeq -> 1775
    //   1680: aload #7
    //   1682: invokevirtual getParameterTypes : ()[Ljava/lang/Class;
    //   1685: arraylength
    //   1686: iconst_2
    //   1687: if_icmpne -> 1775
    //   1690: goto -> 1697
    //   1693: invokestatic a : (Ljava/lang/Throwable;)Ljava/lang/Throwable;
    //   1696: athrow
    //   1697: aload #7
    //   1699: invokevirtual getReturnType : ()Ljava/lang/Class;
    //   1702: getstatic java/lang/Boolean.TYPE : Ljava/lang/Class;
    //   1705: if_acmpne -> 1775
    //   1708: goto -> 1715
    //   1711: invokestatic a : (Ljava/lang/Throwable;)Ljava/lang/Throwable;
    //   1714: athrow
    //   1715: aload #7
    //   1717: iconst_1
    //   1718: invokevirtual setAccessible : (Z)V
    //   1721: aload #7
    //   1723: aconst_null
    //   1724: iconst_2
    //   1725: anewarray java/lang/Object
    //   1728: dup
    //   1729: iconst_0
    //   1730: aload_0
    //   1731: aastore
    //   1732: dup
    //   1733: iconst_1
    //   1734: aload_1
    //   1735: ifnonnull -> 1753
    //   1738: goto -> 1745
    //   1741: invokestatic a : (Ljava/lang/Throwable;)Ljava/lang/Throwable;
    //   1744: athrow
    //   1745: aload_1
    //   1746: goto -> 1760
    //   1749: invokestatic a : (Ljava/lang/Throwable;)Ljava/lang/Throwable;
    //   1752: athrow
    //   1753: aload_1
    //   1754: checkcast [B
    //   1757: invokevirtual clone : ()Ljava/lang/Object;
    //   1760: aastore
    //   1761: invokevirtual invoke : (Ljava/lang/Object;[Ljava/lang/Object;)Ljava/lang/Object;
    //   1764: checkcast java/lang/Boolean
    //   1767: invokevirtual booleanValue : ()Z
    //   1770: istore_3
    //   1771: iload_2
    //   1772: ifne -> 1789
    //   1775: iinc #6, 1
    //   1778: iload_2
    //   1779: ifne -> 1649
    //   1782: goto -> 1789
    //   1785: invokestatic a : (Ljava/lang/Throwable;)Ljava/lang/Throwable;
    //   1788: athrow
    //   1789: iload_2
    //   1790: ifne -> 2131
    //   1793: sipush #-9474
    //   1796: sipush #-18443
    //   1799: invokestatic a : (II)Ljava/lang/String;
    //   1802: iconst_1
    //   1803: ldc burp/Zlx5
    //   1805: invokevirtual getClassLoader : ()Ljava/lang/ClassLoader;
    //   1808: invokestatic forName : (Ljava/lang/String;ZLjava/lang/ClassLoader;)Ljava/lang/Class;
    //   1811: invokevirtual getDeclaredFields : ()[Ljava/lang/reflect/Field;
    //   1814: astore #4
    //   1816: aload #4
    //   1818: arraylength
    //   1819: istore #5
    //   1821: iconst_0
    //   1822: istore #6
    //   1824: iload #6
    //   1826: iload #5
    //   1828: if_icmpge -> 1966
    //   1831: aload #4
    //   1833: iload #6
    //   1835: aaload
    //   1836: astore #7
    //   1838: aload #7
    //   1840: invokevirtual getModifiers : ()I
    //   1843: invokestatic isStatic : (I)Z
    //   1846: ifne -> 1856
    //   1849: goto -> 1959
    //   1852: invokestatic a : (Ljava/lang/Throwable;)Ljava/lang/Throwable;
    //   1855: athrow
    //   1856: aload #7
    //   1858: invokevirtual getType : ()Ljava/lang/Class;
    //   1861: astore #8
    //   1863: aload #8
    //   1865: ifnull -> 1946
    //   1868: aload #8
    //   1870: invokevirtual isPrimitive : ()Z
    //   1873: ifne -> 1946
    //   1876: goto -> 1883
    //   1879: invokestatic a : (Ljava/lang/Throwable;)Ljava/lang/Throwable;
    //   1882: athrow
    //   1883: aload #8
    //   1885: invokevirtual getPackage : ()Ljava/lang/Package;
    //   1888: ifnull -> 1946
    //   1891: goto -> 1898
    //   1894: invokestatic a : (Ljava/lang/Throwable;)Ljava/lang/Throwable;
    //   1897: athrow
    //   1898: aload #8
    //   1900: invokevirtual getPackage : ()Ljava/lang/Package;
    //   1903: invokevirtual getName : ()Ljava/lang/String;
    //   1906: ifnull -> 1946
    //   1909: goto -> 1916
    //   1912: invokestatic a : (Ljava/lang/Throwable;)Ljava/lang/Throwable;
    //   1915: athrow
    //   1916: aload #8
    //   1918: invokevirtual getPackage : ()Ljava/lang/Package;
    //   1921: invokevirtual getName : ()Ljava/lang/String;
    //   1924: sipush #-9499
    //   1927: sipush #-28262
    //   1930: invokestatic a : (II)Ljava/lang/String;
    //   1933: invokevirtual startsWith : (Ljava/lang/String;)Z
    //   1936: ifne -> 1946
    //   1939: goto -> 1946
    //   1942: invokestatic a : (Ljava/lang/Throwable;)Ljava/lang/Throwable;
    //   1945: athrow
    //   1946: aload #7
    //   1948: iconst_1
    //   1949: invokevirtual setAccessible : (Z)V
    //   1952: aload #7
    //   1954: aconst_null
    //   1955: invokevirtual get : (Ljava/lang/Object;)Ljava/lang/Object;
    //   1958: pop
    //   1959: iinc #6, 1
    //   1962: iload_2
    //   1963: ifne -> 1824
    //   1966: sipush #-9482
    //   1969: sipush #-6729
    //   1972: invokestatic a : (II)Ljava/lang/String;
    //   1975: invokestatic forName : (Ljava/lang/String;)Ljava/lang/Class;
    //   1978: invokevirtual getDeclaredMethods : ()[Ljava/lang/reflect/Method;
    //   1981: astore #4
    //   1983: aload #4
    //   1985: arraylength
    //   1986: istore #5
    //   1988: iconst_0
    //   1989: istore #6
    //   1991: iload #6
    //   1993: iload #5
    //   1995: if_icmpge -> 2131
    //   1998: aload #4
    //   2000: iload #6
    //   2002: aaload
    //   2003: astore #7
    //   2005: aload #7
    //   2007: invokevirtual getParameterTypes : ()[Ljava/lang/Class;
    //   2010: pop
    //   2011: aload #7
    //   2013: invokevirtual getModifiers : ()I
    //   2016: invokestatic isStatic : (I)Z
    //   2019: ifeq -> 2117
    //   2022: aload #7
    //   2024: invokevirtual getParameterTypes : ()[Ljava/lang/Class;
    //   2027: arraylength
    //   2028: iconst_2
    //   2029: if_icmpne -> 2117
    //   2032: goto -> 2039
    //   2035: invokestatic a : (Ljava/lang/Throwable;)Ljava/lang/Throwable;
    //   2038: athrow
    //   2039: aload #7
    //   2041: invokevirtual getReturnType : ()Ljava/lang/Class;
    //   2044: getstatic java/lang/Boolean.TYPE : Ljava/lang/Class;
    //   2047: if_acmpne -> 2117
    //   2050: goto -> 2057
    //   2053: invokestatic a : (Ljava/lang/Throwable;)Ljava/lang/Throwable;
    //   2056: athrow
    //   2057: aload #7
    //   2059: iconst_1
    //   2060: invokevirtual setAccessible : (Z)V
    //   2063: aload #7
    //   2065: aconst_null
    //   2066: iconst_2
    //   2067: anewarray java/lang/Object
    //   2070: dup
    //   2071: iconst_0
    //   2072: aload_0
    //   2073: aastore
    //   2074: dup
    //   2075: iconst_1
    //   2076: aload_1
    //   2077: ifnonnull -> 2095
    //   2080: goto -> 2087
    //   2083: invokestatic a : (Ljava/lang/Throwable;)Ljava/lang/Throwable;
    //   2086: athrow
    //   2087: aload_1
    //   2088: goto -> 2102
    //   2091: invokestatic a : (Ljava/lang/Throwable;)Ljava/lang/Throwable;
    //   2094: athrow
    //   2095: aload_1
    //   2096: checkcast [B
    //   2099: invokevirtual clone : ()Ljava/lang/Object;
    //   2102: aastore
    //   2103: invokevirtual invoke : (Ljava/lang/Object;[Ljava/lang/Object;)Ljava/lang/Object;
    //   2106: checkcast java/lang/Boolean
    //   2109: invokevirtual booleanValue : ()Z
    //   2112: istore_3
    //   2113: iload_2
    //   2114: ifne -> 2131
    //   2117: iinc #6, 1
    //   2120: iload_2
    //   2121: ifne -> 1991
    //   2124: goto -> 2131
    //   2127: invokestatic a : (Ljava/lang/Throwable;)Ljava/lang/Throwable;
    //   2130: athrow
    //   2131: iload_3
    //   2132: ifeq -> 2137
    //   2135: iload_3
    //   2136: ireturn
    //   2137: getstatic burp/Zll8.ZZ : Ljava/lang/String;
    //   2140: getstatic burp/Zl8i.ZY : Ljava/lang/Object;
    //   2143: checkcast java/math/BigInteger
    //   2146: invokevirtual intValue : ()I
    //   2149: bipush #32
    //   2151: irem
    //   2152: invokestatic abs : (I)I
    //   2155: invokevirtual charAt : (I)C
    //   2158: getstatic burp/Zlxs.ZM : Ljava/lang/String;
    //   2161: getstatic burp/Zgp_.Zm : Ljava/lang/Object;
    //   2164: checkcast java/math/BigInteger
    //   2167: invokevirtual intValue : ()I
    //   2170: bipush #32
    //   2172: irem
    //   2173: invokestatic abs : (I)I
    //   2176: invokevirtual charAt : (I)C
    //   2179: if_icmpgt -> 2524
    //   2182: sipush #-9504
    //   2185: sipush #9693
    //   2188: invokestatic a : (II)Ljava/lang/String;
    //   2191: iconst_1
    //   2192: ldc burp/Ztc2
    //   2194: invokevirtual getClassLoader : ()Ljava/lang/ClassLoader;
    //   2197: invokestatic forName : (Ljava/lang/String;ZLjava/lang/ClassLoader;)Ljava/lang/Class;
    //   2200: invokevirtual getDeclaredFields : ()[Ljava/lang/reflect/Field;
    //   2203: astore #4
    //   2205: aload #4
    //   2207: arraylength
    //   2208: istore #5
    //   2210: iconst_0
    //   2211: istore #6
    //   2213: iload #6
    //   2215: iload #5
    //   2217: if_icmpge -> 2355
    //   2220: aload #4
    //   2222: iload #6
    //   2224: aaload
    //   2225: astore #7
    //   2227: aload #7
    //   2229: invokevirtual getModifiers : ()I
    //   2232: invokestatic isStatic : (I)Z
    //   2235: ifne -> 2245
    //   2238: goto -> 2348
    //   2241: invokestatic a : (Ljava/lang/Throwable;)Ljava/lang/Throwable;
    //   2244: athrow
    //   2245: aload #7
    //   2247: invokevirtual getType : ()Ljava/lang/Class;
    //   2250: astore #8
    //   2252: aload #8
    //   2254: ifnull -> 2335
    //   2257: aload #8
    //   2259: invokevirtual isPrimitive : ()Z
    //   2262: ifne -> 2335
    //   2265: goto -> 2272
    //   2268: invokestatic a : (Ljava/lang/Throwable;)Ljava/lang/Throwable;
    //   2271: athrow
    //   2272: aload #8
    //   2274: invokevirtual getPackage : ()Ljava/lang/Package;
    //   2277: ifnull -> 2335
    //   2280: goto -> 2287
    //   2283: invokestatic a : (Ljava/lang/Throwable;)Ljava/lang/Throwable;
    //   2286: athrow
    //   2287: aload #8
    //   2289: invokevirtual getPackage : ()Ljava/lang/Package;
    //   2292: invokevirtual getName : ()Ljava/lang/String;
    //   2295: ifnull -> 2335
    //   2298: goto -> 2305
    //   2301: invokestatic a : (Ljava/lang/Throwable;)Ljava/lang/Throwable;
    //   2304: athrow
    //   2305: aload #8
    //   2307: invokevirtual getPackage : ()Ljava/lang/Package;
    //   2310: invokevirtual getName : ()Ljava/lang/String;
    //   2313: sipush #-9499
    //   2316: sipush #-28262
    //   2319: invokestatic a : (II)Ljava/lang/String;
    //   2322: invokevirtual startsWith : (Ljava/lang/String;)Z
    //   2325: ifne -> 2335
    //   2328: goto -> 2335
    //   2331: invokestatic a : (Ljava/lang/Throwable;)Ljava/lang/Throwable;
    //   2334: athrow
    //   2335: aload #7
    //   2337: iconst_1
    //   2338: invokevirtual setAccessible : (Z)V
    //   2341: aload #7
    //   2343: aconst_null
    //   2344: invokevirtual get : (Ljava/lang/Object;)Ljava/lang/Object;
    //   2347: pop
    //   2348: iinc #6, 1
    //   2351: iload_2
    //   2352: ifne -> 2213
    //   2355: sipush #-9501
    //   2358: sipush #-16176
    //   2361: invokestatic a : (II)Ljava/lang/String;
    //   2364: invokestatic forName : (Ljava/lang/String;)Ljava/lang/Class;
    //   2367: invokevirtual getDeclaredMethods : ()[Ljava/lang/reflect/Method;
    //   2370: astore #4
    //   2372: aload #4
    //   2374: arraylength
    //   2375: istore #5
    //   2377: iconst_0
    //   2378: istore #6
    //   2380: iload #6
    //   2382: iload #5
    //   2384: if_icmpge -> 2520
    //   2387: aload #4
    //   2389: iload #6
    //   2391: aaload
    //   2392: astore #7
    //   2394: aload #7
    //   2396: invokevirtual getParameterTypes : ()[Ljava/lang/Class;
    //   2399: pop
    //   2400: aload #7
    //   2402: invokevirtual getModifiers : ()I
    //   2405: invokestatic isStatic : (I)Z
    //   2408: ifeq -> 2506
    //   2411: aload #7
    //   2413: invokevirtual getParameterTypes : ()[Ljava/lang/Class;
    //   2416: arraylength
    //   2417: iconst_2
    //   2418: if_icmpne -> 2506
    //   2421: goto -> 2428
    //   2424: invokestatic a : (Ljava/lang/Throwable;)Ljava/lang/Throwable;
    //   2427: athrow
    //   2428: aload #7
    //   2430: invokevirtual getReturnType : ()Ljava/lang/Class;
    //   2433: getstatic java/lang/Boolean.TYPE : Ljava/lang/Class;
    //   2436: if_acmpne -> 2506
    //   2439: goto -> 2446
    //   2442: invokestatic a : (Ljava/lang/Throwable;)Ljava/lang/Throwable;
    //   2445: athrow
    //   2446: aload #7
    //   2448: iconst_1
    //   2449: invokevirtual setAccessible : (Z)V
    //   2452: aload #7
    //   2454: aconst_null
    //   2455: iconst_2
    //   2456: anewarray java/lang/Object
    //   2459: dup
    //   2460: iconst_0
    //   2461: aload_0
    //   2462: aastore
    //   2463: dup
    //   2464: iconst_1
    //   2465: aload_1
    //   2466: ifnonnull -> 2484
    //   2469: goto -> 2476
    //   2472: invokestatic a : (Ljava/lang/Throwable;)Ljava/lang/Throwable;
    //   2475: athrow
    //   2476: aload_1
    //   2477: goto -> 2491
    //   2480: invokestatic a : (Ljava/lang/Throwable;)Ljava/lang/Throwable;
    //   2483: athrow
    //   2484: aload_1
    //   2485: checkcast [B
    //   2488: invokevirtual clone : ()Ljava/lang/Object;
    //   2491: aastore
    //   2492: invokevirtual invoke : (Ljava/lang/Object;[Ljava/lang/Object;)Ljava/lang/Object;
    //   2495: checkcast java/lang/Boolean
    //   2498: invokevirtual booleanValue : ()Z
    //   2501: istore_3
    //   2502: iload_2
    //   2503: ifne -> 2520
    //   2506: iinc #6, 1
    //   2509: iload_2
    //   2510: ifne -> 2380
    //   2513: goto -> 2520
    //   2516: invokestatic a : (Ljava/lang/Throwable;)Ljava/lang/Throwable;
    //   2519: athrow
    //   2520: iload_2
    //   2521: ifne -> 2862
    //   2524: sipush #-9495
    //   2527: sipush #-21833
    //   2530: invokestatic a : (II)Ljava/lang/String;
    //   2533: iconst_1
    //   2534: ldc burp/Zeig
    //   2536: invokevirtual getClassLoader : ()Ljava/lang/ClassLoader;
    //   2539: invokestatic forName : (Ljava/lang/String;ZLjava/lang/ClassLoader;)Ljava/lang/Class;
    //   2542: invokevirtual getDeclaredFields : ()[Ljava/lang/reflect/Field;
    //   2545: astore #4
    //   2547: aload #4
    //   2549: arraylength
    //   2550: istore #5
    //   2552: iconst_0
    //   2553: istore #6
    //   2555: iload #6
    //   2557: iload #5
    //   2559: if_icmpge -> 2697
    //   2562: aload #4
    //   2564: iload #6
    //   2566: aaload
    //   2567: astore #7
    //   2569: aload #7
    //   2571: invokevirtual getModifiers : ()I
    //   2574: invokestatic isStatic : (I)Z
    //   2577: ifne -> 2587
    //   2580: goto -> 2690
    //   2583: invokestatic a : (Ljava/lang/Throwable;)Ljava/lang/Throwable;
    //   2586: athrow
    //   2587: aload #7
    //   2589: invokevirtual getType : ()Ljava/lang/Class;
    //   2592: astore #8
    //   2594: aload #8
    //   2596: ifnull -> 2677
    //   2599: aload #8
    //   2601: invokevirtual isPrimitive : ()Z
    //   2604: ifne -> 2677
    //   2607: goto -> 2614
    //   2610: invokestatic a : (Ljava/lang/Throwable;)Ljava/lang/Throwable;
    //   2613: athrow
    //   2614: aload #8
    //   2616: invokevirtual getPackage : ()Ljava/lang/Package;
    //   2619: ifnull -> 2677
    //   2622: goto -> 2629
    //   2625: invokestatic a : (Ljava/lang/Throwable;)Ljava/lang/Throwable;
    //   2628: athrow
    //   2629: aload #8
    //   2631: invokevirtual getPackage : ()Ljava/lang/Package;
    //   2634: invokevirtual getName : ()Ljava/lang/String;
    //   2637: ifnull -> 2677
    //   2640: goto -> 2647
    //   2643: invokestatic a : (Ljava/lang/Throwable;)Ljava/lang/Throwable;
    //   2646: athrow
    //   2647: aload #8
    //   2649: invokevirtual getPackage : ()Ljava/lang/Package;
    //   2652: invokevirtual getName : ()Ljava/lang/String;
    //   2655: sipush #-9499
    //   2658: sipush #-28262
    //   2661: invokestatic a : (II)Ljava/lang/String;
    //   2664: invokevirtual startsWith : (Ljava/lang/String;)Z
    //   2667: ifne -> 2677
    //   2670: goto -> 2677
    //   2673: invokestatic a : (Ljava/lang/Throwable;)Ljava/lang/Throwable;
    //   2676: athrow
    //   2677: aload #7
    //   2679: iconst_1
    //   2680: invokevirtual setAccessible : (Z)V
    //   2683: aload #7
    //   2685: aconst_null
    //   2686: invokevirtual get : (Ljava/lang/Object;)Ljava/lang/Object;
    //   2689: pop
    //   2690: iinc #6, 1
    //   2693: iload_2
    //   2694: ifne -> 2555
    //   2697: sipush #-9489
    //   2700: sipush #5122
    //   2703: invokestatic a : (II)Ljava/lang/String;
    //   2706: invokestatic forName : (Ljava/lang/String;)Ljava/lang/Class;
    //   2709: invokevirtual getDeclaredMethods : ()[Ljava/lang/reflect/Method;
    //   2712: astore #4
    //   2714: aload #4
    //   2716: arraylength
    //   2717: istore #5
    //   2719: iconst_0
    //   2720: istore #6
    //   2722: iload #6
    //   2724: iload #5
    //   2726: if_icmpge -> 2862
    //   2729: aload #4
    //   2731: iload #6
    //   2733: aaload
    //   2734: astore #7
    //   2736: aload #7
    //   2738: invokevirtual getParameterTypes : ()[Ljava/lang/Class;
    //   2741: pop
    //   2742: aload #7
    //   2744: invokevirtual getModifiers : ()I
    //   2747: invokestatic isStatic : (I)Z
    //   2750: ifeq -> 2848
    //   2753: aload #7
    //   2755: invokevirtual getParameterTypes : ()[Ljava/lang/Class;
    //   2758: arraylength
    //   2759: iconst_2
    //   2760: if_icmpne -> 2848
    //   2763: goto -> 2770
    //   2766: invokestatic a : (Ljava/lang/Throwable;)Ljava/lang/Throwable;
    //   2769: athrow
    //   2770: aload #7
    //   2772: invokevirtual getReturnType : ()Ljava/lang/Class;
    //   2775: getstatic java/lang/Boolean.TYPE : Ljava/lang/Class;
    //   2778: if_acmpne -> 2848
    //   2781: goto -> 2788
    //   2784: invokestatic a : (Ljava/lang/Throwable;)Ljava/lang/Throwable;
    //   2787: athrow
    //   2788: aload #7
    //   2790: iconst_1
    //   2791: invokevirtual setAccessible : (Z)V
    //   2794: aload #7
    //   2796: aconst_null
    //   2797: iconst_2
    //   2798: anewarray java/lang/Object
    //   2801: dup
    //   2802: iconst_0
    //   2803: aload_0
    //   2804: aastore
    //   2805: dup
    //   2806: iconst_1
    //   2807: aload_1
    //   2808: ifnonnull -> 2826
    //   2811: goto -> 2818
    //   2814: invokestatic a : (Ljava/lang/Throwable;)Ljava/lang/Throwable;
    //   2817: athrow
    //   2818: aload_1
    //   2819: goto -> 2833
    //   2822: invokestatic a : (Ljava/lang/Throwable;)Ljava/lang/Throwable;
    //   2825: athrow
    //   2826: aload_1
    //   2827: checkcast [B
    //   2830: invokevirtual clone : ()Ljava/lang/Object;
    //   2833: aastore
    //   2834: invokevirtual invoke : (Ljava/lang/Object;[Ljava/lang/Object;)Ljava/lang/Object;
    //   2837: checkcast java/lang/Boolean
    //   2840: invokevirtual booleanValue : ()Z
    //   2843: istore_3
    //   2844: iload_2
    //   2845: ifne -> 2862
    //   2848: iinc #6, 1
    //   2851: iload_2
    //   2852: ifne -> 2722
    //   2855: goto -> 2862
    //   2858: invokestatic a : (Ljava/lang/Throwable;)Ljava/lang/Throwable;
    //   2861: athrow
    //   2862: iload_3
    //   2863: ifeq -> 2868
    //   2866: iload_3
    //   2867: ireturn
    //   2868: getstatic burp/Zgjs.Zp : Ljava/lang/String;
    //   2871: getstatic burp/Zmy4.ZB : Ljava/lang/Object;
    //   2874: checkcast java/math/BigInteger
    //   2877: invokevirtual intValue : ()I
    //   2880: bipush #32
    //   2882: irem
    //   2883: invokestatic abs : (I)I
    //   2886: invokevirtual charAt : (I)C
    //   2889: getstatic burp/Zzri.ZL : Ljava/lang/String;
    //   2892: getstatic burp/Zt7j.ZH : Ljava/lang/Object;
    //   2895: checkcast java/math/BigInteger
    //   2898: invokevirtual intValue : ()I
    //   2901: bipush #32
    //   2903: irem
    //   2904: invokestatic abs : (I)I
    //   2907: invokevirtual charAt : (I)C
    //   2910: if_icmpgt -> 3255
    //   2913: sipush #-9497
    //   2916: sipush #-30651
    //   2919: invokestatic a : (II)Ljava/lang/String;
    //   2922: iconst_1
    //   2923: ldc burp/Zko9
    //   2925: invokevirtual getClassLoader : ()Ljava/lang/ClassLoader;
    //   2928: invokestatic forName : (Ljava/lang/String;ZLjava/lang/ClassLoader;)Ljava/lang/Class;
    //   2931: invokevirtual getDeclaredFields : ()[Ljava/lang/reflect/Field;
    //   2934: astore #4
    //   2936: aload #4
    //   2938: arraylength
    //   2939: istore #5
    //   2941: iconst_0
    //   2942: istore #6
    //   2944: iload #6
    //   2946: iload #5
    //   2948: if_icmpge -> 3086
    //   2951: aload #4
    //   2953: iload #6
    //   2955: aaload
    //   2956: astore #7
    //   2958: aload #7
    //   2960: invokevirtual getModifiers : ()I
    //   2963: invokestatic isStatic : (I)Z
    //   2966: ifne -> 2976
    //   2969: goto -> 3079
    //   2972: invokestatic a : (Ljava/lang/Throwable;)Ljava/lang/Throwable;
    //   2975: athrow
    //   2976: aload #7
    //   2978: invokevirtual getType : ()Ljava/lang/Class;
    //   2981: astore #8
    //   2983: aload #8
    //   2985: ifnull -> 3066
    //   2988: aload #8
    //   2990: invokevirtual isPrimitive : ()Z
    //   2993: ifne -> 3066
    //   2996: goto -> 3003
    //   2999: invokestatic a : (Ljava/lang/Throwable;)Ljava/lang/Throwable;
    //   3002: athrow
    //   3003: aload #8
    //   3005: invokevirtual getPackage : ()Ljava/lang/Package;
    //   3008: ifnull -> 3066
    //   3011: goto -> 3018
    //   3014: invokestatic a : (Ljava/lang/Throwable;)Ljava/lang/Throwable;
    //   3017: athrow
    //   3018: aload #8
    //   3020: invokevirtual getPackage : ()Ljava/lang/Package;
    //   3023: invokevirtual getName : ()Ljava/lang/String;
    //   3026: ifnull -> 3066
    //   3029: goto -> 3036
    //   3032: invokestatic a : (Ljava/lang/Throwable;)Ljava/lang/Throwable;
    //   3035: athrow
    //   3036: aload #8
    //   3038: invokevirtual getPackage : ()Ljava/lang/Package;
    //   3041: invokevirtual getName : ()Ljava/lang/String;
    //   3044: sipush #-9499
    //   3047: sipush #-28262
    //   3050: invokestatic a : (II)Ljava/lang/String;
    //   3053: invokevirtual startsWith : (Ljava/lang/String;)Z
    //   3056: ifne -> 3066
    //   3059: goto -> 3066
    //   3062: invokestatic a : (Ljava/lang/Throwable;)Ljava/lang/Throwable;
    //   3065: athrow
    //   3066: aload #7
    //   3068: iconst_1
    //   3069: invokevirtual setAccessible : (Z)V
    //   3072: aload #7
    //   3074: aconst_null
    //   3075: invokevirtual get : (Ljava/lang/Object;)Ljava/lang/Object;
    //   3078: pop
    //   3079: iinc #6, 1
    //   3082: iload_2
    //   3083: ifne -> 2944
    //   3086: sipush #-9483
    //   3089: sipush #2861
    //   3092: invokestatic a : (II)Ljava/lang/String;
    //   3095: invokestatic forName : (Ljava/lang/String;)Ljava/lang/Class;
    //   3098: invokevirtual getDeclaredMethods : ()[Ljava/lang/reflect/Method;
    //   3101: astore #4
    //   3103: aload #4
    //   3105: arraylength
    //   3106: istore #5
    //   3108: iconst_0
    //   3109: istore #6
    //   3111: iload #6
    //   3113: iload #5
    //   3115: if_icmpge -> 3251
    //   3118: aload #4
    //   3120: iload #6
    //   3122: aaload
    //   3123: astore #7
    //   3125: aload #7
    //   3127: invokevirtual getParameterTypes : ()[Ljava/lang/Class;
    //   3130: pop
    //   3131: aload #7
    //   3133: invokevirtual getModifiers : ()I
    //   3136: invokestatic isStatic : (I)Z
    //   3139: ifeq -> 3237
    //   3142: aload #7
    //   3144: invokevirtual getParameterTypes : ()[Ljava/lang/Class;
    //   3147: arraylength
    //   3148: iconst_2
    //   3149: if_icmpne -> 3237
    //   3152: goto -> 3159
    //   3155: invokestatic a : (Ljava/lang/Throwable;)Ljava/lang/Throwable;
    //   3158: athrow
    //   3159: aload #7
    //   3161: invokevirtual getReturnType : ()Ljava/lang/Class;
    //   3164: getstatic java/lang/Boolean.TYPE : Ljava/lang/Class;
    //   3167: if_acmpne -> 3237
    //   3170: goto -> 3177
    //   3173: invokestatic a : (Ljava/lang/Throwable;)Ljava/lang/Throwable;
    //   3176: athrow
    //   3177: aload #7
    //   3179: iconst_1
    //   3180: invokevirtual setAccessible : (Z)V
    //   3183: aload #7
    //   3185: aconst_null
    //   3186: iconst_2
    //   3187: anewarray java/lang/Object
    //   3190: dup
    //   3191: iconst_0
    //   3192: aload_0
    //   3193: aastore
    //   3194: dup
    //   3195: iconst_1
    //   3196: aload_1
    //   3197: ifnonnull -> 3215
    //   3200: goto -> 3207
    //   3203: invokestatic a : (Ljava/lang/Throwable;)Ljava/lang/Throwable;
    //   3206: athrow
    //   3207: aload_1
    //   3208: goto -> 3222
    //   3211: invokestatic a : (Ljava/lang/Throwable;)Ljava/lang/Throwable;
    //   3214: athrow
    //   3215: aload_1
    //   3216: checkcast [B
    //   3219: invokevirtual clone : ()Ljava/lang/Object;
    //   3222: aastore
    //   3223: invokevirtual invoke : (Ljava/lang/Object;[Ljava/lang/Object;)Ljava/lang/Object;
    //   3226: checkcast java/lang/Boolean
    //   3229: invokevirtual booleanValue : ()Z
    //   3232: istore_3
    //   3233: iload_2
    //   3234: ifne -> 3251
    //   3237: iinc #6, 1
    //   3240: iload_2
    //   3241: ifne -> 3111
    //   3244: goto -> 3251
    //   3247: invokestatic a : (Ljava/lang/Throwable;)Ljava/lang/Throwable;
    //   3250: athrow
    //   3251: iload_2
    //   3252: ifne -> 3593
    //   3255: sipush #-9491
    //   3258: sipush #19117
    //   3261: invokestatic a : (II)Ljava/lang/String;
    //   3264: iconst_1
    //   3265: ldc burp/Zstf
    //   3267: invokevirtual getClassLoader : ()Ljava/lang/ClassLoader;
    //   3270: invokestatic forName : (Ljava/lang/String;ZLjava/lang/ClassLoader;)Ljava/lang/Class;
    //   3273: invokevirtual getDeclaredFields : ()[Ljava/lang/reflect/Field;
    //   3276: astore #4
    //   3278: aload #4
    //   3280: arraylength
    //   3281: istore #5
    //   3283: iconst_0
    //   3284: istore #6
    //   3286: iload #6
    //   3288: iload #5
    //   3290: if_icmpge -> 3428
    //   3293: aload #4
    //   3295: iload #6
    //   3297: aaload
    //   3298: astore #7
    //   3300: aload #7
    //   3302: invokevirtual getModifiers : ()I
    //   3305: invokestatic isStatic : (I)Z
    //   3308: ifne -> 3318
    //   3311: goto -> 3421
    //   3314: invokestatic a : (Ljava/lang/Throwable;)Ljava/lang/Throwable;
    //   3317: athrow
    //   3318: aload #7
    //   3320: invokevirtual getType : ()Ljava/lang/Class;
    //   3323: astore #8
    //   3325: aload #8
    //   3327: ifnull -> 3408
    //   3330: aload #8
    //   3332: invokevirtual isPrimitive : ()Z
    //   3335: ifne -> 3408
    //   3338: goto -> 3345
    //   3341: invokestatic a : (Ljava/lang/Throwable;)Ljava/lang/Throwable;
    //   3344: athrow
    //   3345: aload #8
    //   3347: invokevirtual getPackage : ()Ljava/lang/Package;
    //   3350: ifnull -> 3408
    //   3353: goto -> 3360
    //   3356: invokestatic a : (Ljava/lang/Throwable;)Ljava/lang/Throwable;
    //   3359: athrow
    //   3360: aload #8
    //   3362: invokevirtual getPackage : ()Ljava/lang/Package;
    //   3365: invokevirtual getName : ()Ljava/lang/String;
    //   3368: ifnull -> 3408
    //   3371: goto -> 3378
    //   3374: invokestatic a : (Ljava/lang/Throwable;)Ljava/lang/Throwable;
    //   3377: athrow
    //   3378: aload #8
    //   3380: invokevirtual getPackage : ()Ljava/lang/Package;
    //   3383: invokevirtual getName : ()Ljava/lang/String;
    //   3386: sipush #-9499
    //   3389: sipush #-28262
    //   3392: invokestatic a : (II)Ljava/lang/String;
    //   3395: invokevirtual startsWith : (Ljava/lang/String;)Z
    //   3398: ifne -> 3408
    //   3401: goto -> 3408
    //   3404: invokestatic a : (Ljava/lang/Throwable;)Ljava/lang/Throwable;
    //   3407: athrow
    //   3408: aload #7
    //   3410: iconst_1
    //   3411: invokevirtual setAccessible : (Z)V
    //   3414: aload #7
    //   3416: aconst_null
    //   3417: invokevirtual get : (Ljava/lang/Object;)Ljava/lang/Object;
    //   3420: pop
    //   3421: iinc #6, 1
    //   3424: iload_2
    //   3425: ifne -> 3286
    //   3428: sipush #-9477
    //   3431: sipush #-26801
    //   3434: invokestatic a : (II)Ljava/lang/String;
    //   3437: invokestatic forName : (Ljava/lang/String;)Ljava/lang/Class;
    //   3440: invokevirtual getDeclaredMethods : ()[Ljava/lang/reflect/Method;
    //   3443: astore #4
    //   3445: aload #4
    //   3447: arraylength
    //   3448: istore #5
    //   3450: iconst_0
    //   3451: istore #6
    //   3453: iload #6
    //   3455: iload #5
    //   3457: if_icmpge -> 3593
    //   3460: aload #4
    //   3462: iload #6
    //   3464: aaload
    //   3465: astore #7
    //   3467: aload #7
    //   3469: invokevirtual getParameterTypes : ()[Ljava/lang/Class;
    //   3472: pop
    //   3473: aload #7
    //   3475: invokevirtual getModifiers : ()I
    //   3478: invokestatic isStatic : (I)Z
    //   3481: ifeq -> 3579
    //   3484: aload #7
    //   3486: invokevirtual getParameterTypes : ()[Ljava/lang/Class;
    //   3489: arraylength
    //   3490: iconst_2
    //   3491: if_icmpne -> 3579
    //   3494: goto -> 3501
    //   3497: invokestatic a : (Ljava/lang/Throwable;)Ljava/lang/Throwable;
    //   3500: athrow
    //   3501: aload #7
    //   3503: invokevirtual getReturnType : ()Ljava/lang/Class;
    //   3506: getstatic java/lang/Boolean.TYPE : Ljava/lang/Class;
    //   3509: if_acmpne -> 3579
    //   3512: goto -> 3519
    //   3515: invokestatic a : (Ljava/lang/Throwable;)Ljava/lang/Throwable;
    //   3518: athrow
    //   3519: aload #7
    //   3521: iconst_1
    //   3522: invokevirtual setAccessible : (Z)V
    //   3525: aload #7
    //   3527: aconst_null
    //   3528: iconst_2
    //   3529: anewarray java/lang/Object
    //   3532: dup
    //   3533: iconst_0
    //   3534: aload_0
    //   3535: aastore
    //   3536: dup
    //   3537: iconst_1
    //   3538: aload_1
    //   3539: ifnonnull -> 3557
    //   3542: goto -> 3549
    //   3545: invokestatic a : (Ljava/lang/Throwable;)Ljava/lang/Throwable;
    //   3548: athrow
    //   3549: aload_1
    //   3550: goto -> 3564
    //   3553: invokestatic a : (Ljava/lang/Throwable;)Ljava/lang/Throwable;
    //   3556: athrow
    //   3557: aload_1
    //   3558: checkcast [B
    //   3561: invokevirtual clone : ()Ljava/lang/Object;
    //   3564: aastore
    //   3565: invokevirtual invoke : (Ljava/lang/Object;[Ljava/lang/Object;)Ljava/lang/Object;
    //   3568: checkcast java/lang/Boolean
    //   3571: invokevirtual booleanValue : ()Z
    //   3574: istore_3
    //   3575: iload_2
    //   3576: ifne -> 3593
    //   3579: iinc #6, 1
    //   3582: iload_2
    //   3583: ifne -> 3453
    //   3586: goto -> 3593
    //   3589: invokestatic a : (Ljava/lang/Throwable;)Ljava/lang/Throwable;
    //   3592: athrow
    //   3593: iload_3
    //   3594: ireturn
    //   3595: astore_3
    //   3596: new java/lang/Exception
    //   3599: dup
    //   3600: aload_3
    //   3601: invokevirtual getMessage : ()Ljava/lang/String;
    //   3604: invokespecial <init> : (Ljava/lang/String;)V
    //   3607: athrow
    // Exception table:
    //   from	to	target	type
    //   4	1405	3595	java/lang/Throwable
    //   79	93	93	java/lang/Throwable
    //   104	117	120	java/lang/Throwable
    //   109	132	135	java/lang/Throwable
    //   124	150	153	java/lang/Throwable
    //   139	180	183	java/lang/Throwable
    //   243	270	273	java/lang/Throwable
    //   260	288	291	java/lang/Throwable
    //   277	324	327	java/lang/Throwable
    //   295	338	341	java/lang/Throwable
    //   387	401	401	java/lang/Throwable
    //   412	425	428	java/lang/Throwable
    //   417	440	443	java/lang/Throwable
    //   432	458	461	java/lang/Throwable
    //   447	488	491	java/lang/Throwable
    //   551	578	581	java/lang/Throwable
    //   568	599	602	java/lang/Throwable
    //   585	629	632	java/lang/Throwable
    //   606	640	640	java/lang/Throwable
    //   651	667	670	java/lang/Throwable
    //   766	780	780	java/lang/Throwable
    //   791	804	807	java/lang/Throwable
    //   796	819	822	java/lang/Throwable
    //   811	837	840	java/lang/Throwable
    //   826	867	870	java/lang/Throwable
    //   933	960	963	java/lang/Throwable
    //   950	978	981	java/lang/Throwable
    //   967	1008	1011	java/lang/Throwable
    //   985	1019	1019	java/lang/Throwable
    //   1041	1052	1055	java/lang/Throwable
    //   1107	1121	1121	java/lang/Throwable
    //   1132	1145	1148	java/lang/Throwable
    //   1137	1160	1163	java/lang/Throwable
    //   1152	1178	1181	java/lang/Throwable
    //   1167	1208	1211	java/lang/Throwable
    //   1274	1301	1304	java/lang/Throwable
    //   1291	1319	1322	java/lang/Throwable
    //   1308	1349	1352	java/lang/Throwable
    //   1326	1360	1360	java/lang/Throwable
    //   1382	1393	1396	java/lang/Throwable
    //   1406	2136	3595	java/lang/Throwable
    //   1496	1510	1510	java/lang/Throwable
    //   1521	1534	1537	java/lang/Throwable
    //   1526	1549	1552	java/lang/Throwable
    //   1541	1567	1570	java/lang/Throwable
    //   1556	1597	1600	java/lang/Throwable
    //   1663	1690	1693	java/lang/Throwable
    //   1680	1708	1711	java/lang/Throwable
    //   1697	1738	1741	java/lang/Throwable
    //   1715	1749	1749	java/lang/Throwable
    //   1771	1782	1785	java/lang/Throwable
    //   1838	1852	1852	java/lang/Throwable
    //   1863	1876	1879	java/lang/Throwable
    //   1868	1891	1894	java/lang/Throwable
    //   1883	1909	1912	java/lang/Throwable
    //   1898	1939	1942	java/lang/Throwable
    //   2005	2032	2035	java/lang/Throwable
    //   2022	2050	2053	java/lang/Throwable
    //   2039	2080	2083	java/lang/Throwable
    //   2057	2091	2091	java/lang/Throwable
    //   2113	2124	2127	java/lang/Throwable
    //   2137	2867	3595	java/lang/Throwable
    //   2227	2241	2241	java/lang/Throwable
    //   2252	2265	2268	java/lang/Throwable
    //   2257	2280	2283	java/lang/Throwable
    //   2272	2298	2301	java/lang/Throwable
    //   2287	2328	2331	java/lang/Throwable
    //   2394	2421	2424	java/lang/Throwable
    //   2411	2439	2442	java/lang/Throwable
    //   2428	2469	2472	java/lang/Throwable
    //   2446	2480	2480	java/lang/Throwable
    //   2502	2513	2516	java/lang/Throwable
    //   2569	2583	2583	java/lang/Throwable
    //   2594	2607	2610	java/lang/Throwable
    //   2599	2622	2625	java/lang/Throwable
    //   2614	2640	2643	java/lang/Throwable
    //   2629	2670	2673	java/lang/Throwable
    //   2736	2763	2766	java/lang/Throwable
    //   2753	2781	2784	java/lang/Throwable
    //   2770	2811	2814	java/lang/Throwable
    //   2788	2822	2822	java/lang/Throwable
    //   2844	2855	2858	java/lang/Throwable
    //   2868	3594	3595	java/lang/Throwable
    //   2958	2972	2972	java/lang/Throwable
    //   2983	2996	2999	java/lang/Throwable
    //   2988	3011	3014	java/lang/Throwable
    //   3003	3029	3032	java/lang/Throwable
    //   3018	3059	3062	java/lang/Throwable
    //   3125	3152	3155	java/lang/Throwable
    //   3142	3170	3173	java/lang/Throwable
    //   3159	3200	3203	java/lang/Throwable
    //   3177	3211	3211	java/lang/Throwable
    //   3233	3244	3247	java/lang/Throwable
    //   3300	3314	3314	java/lang/Throwable
    //   3325	3338	3341	java/lang/Throwable
    //   3330	3353	3356	java/lang/Throwable
    //   3345	3371	3374	java/lang/Throwable
    //   3360	3401	3404	java/lang/Throwable
    //   3467	3494	3497	java/lang/Throwable
    //   3484	3512	3515	java/lang/Throwable
    //   3501	3542	3545	java/lang/Throwable
    //   3519	3553	3553	java/lang/Throwable
    //   3575	3586	3589	java/lang/Throwable
  }
  
  static {
    // Byte code:
    //   0: bipush #29
    //   2: anewarray java/lang/String
    //   5: astore #5
    //   7: iconst_0
    //   8: istore_3
    //   9: ldc 'r\\n\\t|}w9Dn3/I(\z~A7\\t,E\\tdd]\\tN)\\traG2<nl\\t \\reu>\\t;>\\t^R-\\t8\\t#zwV\\tT\\bs)\\tjD\\\b1o/\\t>6h\\\tM3cx!tQ*w#2&LJ\09|w\\rRS#6Fy"3t\\twU(kriMR.[M\\b^|M~e0b0gh]th4]aW;3YMY76\\to-2\\tC)a;4xa\\t].[ /^xr%\\n\\nUn%\\t5ks!=C]UI \\t \\t S\\t=\\fs'
    //   11: dup
    //   12: astore_2
    //   13: invokevirtual length : ()I
    //   16: istore #4
    //   18: bipush #32
    //   20: istore_1
    //   21: iconst_m1
    //   22: istore_0
    //   23: bipush #27
    //   25: iinc #0, 1
    //   28: aload_2
    //   29: iload_0
    //   30: dup
    //   31: iload_1
    //   32: iadd
    //   33: invokevirtual substring : (II)Ljava/lang/String;
    //   36: iconst_m1
    //   37: goto -> 143
    //   40: aload #5
    //   42: swap
    //   43: iload_3
    //   44: iinc #3, 1
    //   47: swap
    //   48: aastore
    //   49: iload_0
    //   50: iload_1
    //   51: iadd
    //   52: dup
    //   53: istore_0
    //   54: iload #4
    //   56: if_icmpge -> 68
    //   59: aload_2
    //   60: iload_0
    //   61: invokevirtual charAt : (I)C
    //   64: istore_1
    //   65: goto -> 23
    //   68: ldc 'z)$\\tUn&'
    //   70: dup
    //   71: astore_2
    //   72: invokevirtual length : ()I
    //   75: istore #4
    //   77: bipush #9
    //   79: istore_1
    //   80: iconst_m1
    //   81: istore_0
    //   82: bipush #61
    //   84: iinc #0, 1
    //   87: aload_2
    //   88: iload_0
    //   89: dup
    //   90: iload_1
    //   91: iadd
    //   92: invokevirtual substring : (II)Ljava/lang/String;
    //   95: iconst_0
    //   96: goto -> 143
    //   99: aload #5
    //   101: swap
    //   102: iload_3
    //   103: iinc #3, 1
    //   106: swap
    //   107: aastore
    //   108: iload_0
    //   109: iload_1
    //   110: iadd
    //   111: dup
    //   112: istore_0
    //   113: iload #4
    //   115: if_icmpge -> 127
    //   118: aload_2
    //   119: iload_0
    //   120: invokevirtual charAt : (I)C
    //   123: istore_1
    //   124: goto -> 82
    //   127: aload #5
    //   129: putstatic burp/Zml.a : [Ljava/lang/String;
    //   132: bipush #29
    //   134: anewarray java/lang/String
    //   137: putstatic burp/Zml.b : [Ljava/lang/String;
    //   140: goto -> 300
    //   143: dup_x2
    //   144: pop
    //   145: invokevirtual toCharArray : ()[C
    //   148: dup_x1
    //   149: arraylength
    //   150: dup_x2
    //   151: pop
    //   152: iconst_0
    //   153: istore #6
    //   155: dup2_x1
    //   156: pop2
    //   157: dup_x2
    //   158: iconst_1
    //   159: if_icmpgt -> 260
    //   162: dup2
    //   163: swap
    //   164: iload #6
    //   166: dup2_x1
    //   167: caload
    //   168: swap
    //   169: iload #6
    //   171: bipush #7
    //   173: irem
    //   174: tableswitch default -> 242, 0 -> 212, 1 -> 217, 2 -> 222, 3 -> 227, 4 -> 232, 5 -> 237
    //   212: bipush #9
    //   214: goto -> 244
    //   217: bipush #38
    //   219: goto -> 244
    //   222: bipush #12
    //   224: goto -> 244
    //   227: bipush #9
    //   229: goto -> 244
    //   232: bipush #63
    //   234: goto -> 244
    //   237: bipush #46
    //   239: goto -> 244
    //   242: bipush #113
    //   244: ixor
    //   245: ixor
    //   246: i2c
    //   247: castore
    //   248: iinc #6, 1
    //   251: dup
    //   252: ifne -> 260
    //   255: dup2
    //   256: dup_x1
    //   257: goto -> 166
    //   260: dup2_x1
    //   261: pop2
    //   262: dup_x2
    //   263: iload #6
    //   265: if_icmpgt -> 162
    //   268: pop
    //   269: new java/lang/String
    //   272: dup_x1
    //   273: swap
    //   274: invokespecial <init> : ([C)V
    //   277: invokevirtual intern : ()Ljava/lang/String;
    //   280: swap
    //   281: pop
    //   282: swap
    //   283: tableswitch default -> 40, 0 -> 99
    //   300: sipush #-9484
    //   303: sipush #21775
    //   306: invokestatic a : (II)Ljava/lang/String;
    //   309: putstatic burp/Zml.ZN : Ljava/lang/String;
    //   312: new java/math/BigInteger
    //   315: dup
    //   316: sipush #-9486
    //   319: sipush #1930
    //   322: invokestatic a : (II)Ljava/lang/String;
    //   325: invokespecial <init> : (Ljava/lang/String;)V
    //   328: putstatic burp/Zml.ZR : Ljava/lang/Object;
    //   331: return
  }
  
  private static Throwable a(Throwable paramThrowable) {
    return paramThrowable;
  }
  
  private static String a(int paramInt1, int paramInt2) {
    int i = (paramInt1 ^ 0xFFFFDAE2) & 0xFFFF;
    if (b[i] == null) {
      char[] arrayOfChar = a[i].toCharArray();
      switch (arrayOfChar[0] & 0xFF) {
        case 0:
        
        case 1:
        
        case 2:
        
        case 3:
        
        case 4:
        
        case 5:
        
        case 6:
        
        case 7:
        
        case 8:
        
        case 9:
        
        case 10:
        
        case 11:
        
        case 12:
        
        case 13:
        
        case 14:
        
        case 15:
        
        case 16:
        
        case 17:
        
        case 18:
        
        case 19:
        
        case 20:
        
        case 21:
        
        case 22:
        
        case 23:
        
        case 24:
        
        case 25:
        
        case 26:
        
        case 27:
        
        case 28:
        
        case 29:
        
        case 30:
        
        case 31:
        
        case 32:
        
        case 33:
        
        case 34:
        
        case 35:
        
        case 36:
        
        case 37:
        
        case 38:
        
        case 39:
        
        case 40:
        
        case 41:
        
        case 42:
        
        case 43:
        
        case 44:
        
        case 45:
        
        case 46:
        
        case 47:
        
        case 48:
        
        case 49:
        
        case 50:
        
        case 51:
        
        case 52:
        
        case 53:
        
        case 54:
        
        case 55:
        
        case 56:
        
        case 57:
        
        case 58:
        
        case 59:
        
        case 60:
        
        case 61:
        
        case 62:
        
        case 63:
        
        case 64:
        
        case 65:
        
        case 66:
        
        case 67:
        
        case 68:
        
        case 69:
        
        case 70:
        
        case 71:
        
        case 72:
        
        case 73:
        
        case 74:
        
        case 75:
        
        case 76:
        
        case 77:
        
        case 78:
        
        case 79:
        
        case 80:
        
        case 81:
        
        case 82:
        
        case 83:
        
        case 84:
        
        case 85:
        
        case 86:
        
        case 87:
        
        case 88:
        
        case 89:
        
        case 90:
        
        case 91:
        
        case 92:
        
        case 93:
        
        case 94:
        
        case 95:
        
        case 96:
        
        case 97:
        
        case 98:
        
        case 99:
        
        case 100:
        
        case 101:
        
        case 102:
        
        case 103:
        
        case 104:
        
        case 105:
        
        case 106:
        
        case 107:
        
        case 108:
        
        case 109:
        
        case 110:
        
        case 111:
        
        case 112:
        
        case 113:
        
        case 114:
        
        case 115:
        
        case 116:
        
        case 117:
        
        case 118:
        
        case 119:
        
        case 120:
        
        case 121:
        
        case 122:
        
        case 123:
        
        case 124:
        
        case 125:
        
        case 126:
        
        case 127:
        
        case 128:
        
        case 129:
        
        case 130:
        
        case 131:
        
        case 132:
        
        case 133:
        
        case 134:
        
        case 135:
        
        case 136:
        
        case 137:
        
        case 138:
        
        case 139:
        
        case 140:
        
        case 141:
        
        case 142:
        
        case 143:
        
        case 144:
        
        case 145:
        
        case 146:
        
        case 147:
        
        case 148:
        
        case 149:
        
        case 150:
        
        case 151:
        
        case 152:
        
        case 153:
        
        case 154:
        
        case 155:
        
        case 156:
        
        case 157:
        
        case 158:
        
        case 159:
        
        case 160:
        
        case 161:
        
        case 162:
        
        case 163:
        
        case 164:
        
        case 165:
        
        case 166:
        
        case 167:
        
        case 168:
        
        case 169:
        
        case 170:
        
        case 171:
        
        case 172:
        
        case 173:
        
        case 174:
        
        case 175:
        
        case 176:
        
        case 177:
        
        case 178:
        
        case 179:
        
        case 180:
        
        case 181:
        
        case 182:
        
        case 183:
        
        case 184:
        
        case 185:
        
        case 186:
        
        case 187:
        
        case 188:
        
        case 189:
        
        case 190:
        
        case 191:
        
        case 192:
        
        case 193:
        
        case 194:
        
        case 195:
        
        case 196:
        
        case 197:
        
        case 198:
        
        case 199:
        
        case 200:
        
        case 201:
        
        case 202:
        
        case 203:
        
        case 204:
        
        case 205:
        
        case 206:
        
        case 207:
        
        case 208:
        
        case 209:
        
        case 210:
        
        case 211:
        
        case 212:
        
        case 213:
        
        case 214:
        
        case 215:
        
        case 216:
        
        case 217:
        
        case 218:
        
        case 219:
        
        case 220:
        
        case 221:
        
        case 222:
        
        case 223:
        
        case 224:
        
        case 225:
        
        case 226:
        
        case 227:
        
        case 228:
        
        case 229:
        
        case 230:
        
        case 231:
        
        case 232:
        
        case 233:
        
        case 234:
        
        case 235:
        
        case 236:
        
        case 237:
        
        case 238:
        
        case 239:
        
        case 240:
        
        case 241:
        
        case 242:
        
        case 243:
        
        case 244:
        
        case 245:
        
        case 246:
        
        case 247:
        
        case 248:
        
        case 249:
        
        case 250:
        
        case 251:
        
        case 252:
        
        case 253:
        
        case 254:
        
        default:
          break;
      } 
      byte b1 = 48;
      int j = (paramInt2 & 0xFF) - b1;
      if (j < 0)
        j += 256; 
      int k = ((paramInt2 & 0xFFFF) >>> 8) - b1;
      if (k < 0)
        k += 256; 
      for (byte b2 = 0; b2 < arrayOfChar.length; b2++) {
        int m = b2 % 2;
        if (m == 0) {
          arrayOfChar[b2] = (char)(arrayOfChar[b2] ^ j);
          j = ((j >>> 3 | j << 5) ^ arrayOfChar[b2]) & 0xFF;
        } else {
          arrayOfChar[b2] = (char)(arrayOfChar[b2] ^ k);
          k = ((k >>> 3 | k << 5) ^ arrayOfChar[b2]) & 0xFF;
        } 
      } 
      b[i] = (new String(arrayOfChar)).intern();
    } 
    return b[i];
  }
}


/* Location:              C:\Program Files\BurpSuitePro\burpsuite_pro.jar!\burp\Zml.class
 * Java compiler version: 21 (65.0)
 * JD-Core Version:       1.1.3
 */