package burp;

import java.math.BigInteger;

class Zmlu extends ClassLoader {
  static String ZF;
  
  static Object Zi;
  
  private static final String[] a;
  
  private static final String[] b;
  
  static boolean Zb(Object[] paramArrayOfObject, Object paramObject) throws Throwable {
    // Byte code:
    //   0: invokestatic ZK : ()Z
    //   3: istore_2
    //   4: getstatic burp/Zeor.Zb : Ljava/lang/Object;
    //   7: checkcast java/math/BigInteger
    //   10: invokevirtual toByteArray : ()[B
    //   13: astore_3
    //   14: iconst_0
    //   15: istore #5
    //   17: iconst_0
    //   18: istore #6
    //   20: iload #6
    //   22: aload_3
    //   23: arraylength
    //   24: if_icmpge -> 169
    //   27: aload_3
    //   28: iload #6
    //   30: baload
    //   31: istore #7
    //   33: iload #7
    //   35: bipush #48
    //   37: if_icmplt -> 54
    //   40: iload #7
    //   42: bipush #57
    //   44: if_icmple -> 152
    //   47: goto -> 54
    //   50: invokestatic a : (Ljava/lang/Throwable;)Ljava/lang/Throwable;
    //   53: athrow
    //   54: iload #7
    //   56: bipush #65
    //   58: if_icmplt -> 82
    //   61: goto -> 68
    //   64: invokestatic a : (Ljava/lang/Throwable;)Ljava/lang/Throwable;
    //   67: athrow
    //   68: iload #7
    //   70: bipush #90
    //   72: if_icmple -> 152
    //   75: goto -> 82
    //   78: invokestatic a : (Ljava/lang/Throwable;)Ljava/lang/Throwable;
    //   81: athrow
    //   82: iload #7
    //   84: bipush #97
    //   86: if_icmplt -> 110
    //   89: goto -> 96
    //   92: invokestatic a : (Ljava/lang/Throwable;)Ljava/lang/Throwable;
    //   95: athrow
    //   96: iload #7
    //   98: bipush #122
    //   100: if_icmple -> 152
    //   103: goto -> 110
    //   106: invokestatic a : (Ljava/lang/Throwable;)Ljava/lang/Throwable;
    //   109: athrow
    //   110: iload #7
    //   112: bipush #43
    //   114: if_icmpeq -> 152
    //   117: goto -> 124
    //   120: invokestatic a : (Ljava/lang/Throwable;)Ljava/lang/Throwable;
    //   123: athrow
    //   124: iload #7
    //   126: bipush #47
    //   128: if_icmpeq -> 152
    //   131: goto -> 138
    //   134: invokestatic a : (Ljava/lang/Throwable;)Ljava/lang/Throwable;
    //   137: athrow
    //   138: iload #7
    //   140: bipush #61
    //   142: if_icmpne -> 162
    //   145: goto -> 152
    //   148: invokestatic a : (Ljava/lang/Throwable;)Ljava/lang/Throwable;
    //   151: athrow
    //   152: iinc #5, 1
    //   155: goto -> 162
    //   158: invokestatic a : (Ljava/lang/Throwable;)Ljava/lang/Throwable;
    //   161: athrow
    //   162: iinc #6, 1
    //   165: iload_2
    //   166: ifeq -> 20
    //   169: iload #5
    //   171: newarray byte
    //   173: astore #6
    //   175: iconst_0
    //   176: istore #7
    //   178: iconst_0
    //   179: istore #8
    //   181: iload #8
    //   183: aload_3
    //   184: arraylength
    //   185: if_icmpge -> 337
    //   188: aload_3
    //   189: iload #8
    //   191: baload
    //   192: istore #9
    //   194: iload #9
    //   196: bipush #48
    //   198: if_icmplt -> 215
    //   201: iload #9
    //   203: bipush #57
    //   205: if_icmple -> 313
    //   208: goto -> 215
    //   211: invokestatic a : (Ljava/lang/Throwable;)Ljava/lang/Throwable;
    //   214: athrow
    //   215: iload #9
    //   217: bipush #65
    //   219: if_icmplt -> 243
    //   222: goto -> 229
    //   225: invokestatic a : (Ljava/lang/Throwable;)Ljava/lang/Throwable;
    //   228: athrow
    //   229: iload #9
    //   231: bipush #90
    //   233: if_icmple -> 313
    //   236: goto -> 243
    //   239: invokestatic a : (Ljava/lang/Throwable;)Ljava/lang/Throwable;
    //   242: athrow
    //   243: iload #9
    //   245: bipush #97
    //   247: if_icmplt -> 271
    //   250: goto -> 257
    //   253: invokestatic a : (Ljava/lang/Throwable;)Ljava/lang/Throwable;
    //   256: athrow
    //   257: iload #9
    //   259: bipush #122
    //   261: if_icmple -> 313
    //   264: goto -> 271
    //   267: invokestatic a : (Ljava/lang/Throwable;)Ljava/lang/Throwable;
    //   270: athrow
    //   271: iload #9
    //   273: bipush #43
    //   275: if_icmpeq -> 313
    //   278: goto -> 285
    //   281: invokestatic a : (Ljava/lang/Throwable;)Ljava/lang/Throwable;
    //   284: athrow
    //   285: iload #9
    //   287: bipush #47
    //   289: if_icmpeq -> 313
    //   292: goto -> 299
    //   295: invokestatic a : (Ljava/lang/Throwable;)Ljava/lang/Throwable;
    //   298: athrow
    //   299: iload #9
    //   301: bipush #61
    //   303: if_icmpne -> 330
    //   306: goto -> 313
    //   309: invokestatic a : (Ljava/lang/Throwable;)Ljava/lang/Throwable;
    //   312: athrow
    //   313: aload #6
    //   315: iload #7
    //   317: iload #9
    //   319: bastore
    //   320: iinc #7, 1
    //   323: goto -> 330
    //   326: invokestatic a : (Ljava/lang/Throwable;)Ljava/lang/Throwable;
    //   329: athrow
    //   330: iinc #8, 1
    //   333: iload_2
    //   334: ifeq -> 181
    //   337: aload #6
    //   339: astore #4
    //   341: aload #4
    //   343: astore_3
    //   344: aload_3
    //   345: arraylength
    //   346: istore #5
    //   348: aload_3
    //   349: iload #5
    //   351: iconst_1
    //   352: isub
    //   353: baload
    //   354: bipush #61
    //   356: if_icmpne -> 366
    //   359: iinc #5, -1
    //   362: iload_2
    //   363: ifeq -> 348
    //   366: iload #5
    //   368: aload_3
    //   369: arraylength
    //   370: iconst_4
    //   371: idiv
    //   372: isub
    //   373: newarray byte
    //   375: astore #6
    //   377: iconst_0
    //   378: istore #7
    //   380: iload #7
    //   382: aload_3
    //   383: arraylength
    //   384: if_icmpge -> 646
    //   387: aload_3
    //   388: iload #7
    //   390: baload
    //   391: bipush #61
    //   393: if_icmpne -> 412
    //   396: aload_3
    //   397: iload #7
    //   399: iconst_0
    //   400: bastore
    //   401: iload_2
    //   402: ifeq -> 639
    //   405: goto -> 412
    //   408: invokestatic a : (Ljava/lang/Throwable;)Ljava/lang/Throwable;
    //   411: athrow
    //   412: aload_3
    //   413: iload #7
    //   415: baload
    //   416: bipush #47
    //   418: if_icmpne -> 445
    //   421: goto -> 428
    //   424: invokestatic a : (Ljava/lang/Throwable;)Ljava/lang/Throwable;
    //   427: athrow
    //   428: aload_3
    //   429: iload #7
    //   431: bipush #63
    //   433: bastore
    //   434: iload_2
    //   435: ifeq -> 639
    //   438: goto -> 445
    //   441: invokestatic a : (Ljava/lang/Throwable;)Ljava/lang/Throwable;
    //   444: athrow
    //   445: aload_3
    //   446: iload #7
    //   448: baload
    //   449: bipush #43
    //   451: if_icmpne -> 478
    //   454: goto -> 461
    //   457: invokestatic a : (Ljava/lang/Throwable;)Ljava/lang/Throwable;
    //   460: athrow
    //   461: aload_3
    //   462: iload #7
    //   464: bipush #62
    //   466: bastore
    //   467: iload_2
    //   468: ifeq -> 639
    //   471: goto -> 478
    //   474: invokestatic a : (Ljava/lang/Throwable;)Ljava/lang/Throwable;
    //   477: athrow
    //   478: aload_3
    //   479: iload #7
    //   481: baload
    //   482: bipush #48
    //   484: if_icmplt -> 533
    //   487: goto -> 494
    //   490: invokestatic a : (Ljava/lang/Throwable;)Ljava/lang/Throwable;
    //   493: athrow
    //   494: aload_3
    //   495: iload #7
    //   497: baload
    //   498: bipush #57
    //   500: if_icmpgt -> 533
    //   503: goto -> 510
    //   506: invokestatic a : (Ljava/lang/Throwable;)Ljava/lang/Throwable;
    //   509: athrow
    //   510: aload_3
    //   511: iload #7
    //   513: aload_3
    //   514: iload #7
    //   516: baload
    //   517: bipush #-4
    //   519: isub
    //   520: i2b
    //   521: bastore
    //   522: iload_2
    //   523: ifeq -> 639
    //   526: goto -> 533
    //   529: invokestatic a : (Ljava/lang/Throwable;)Ljava/lang/Throwable;
    //   532: athrow
    //   533: aload_3
    //   534: iload #7
    //   536: baload
    //   537: bipush #97
    //   539: if_icmplt -> 588
    //   542: goto -> 549
    //   545: invokestatic a : (Ljava/lang/Throwable;)Ljava/lang/Throwable;
    //   548: athrow
    //   549: aload_3
    //   550: iload #7
    //   552: baload
    //   553: bipush #122
    //   555: if_icmpgt -> 588
    //   558: goto -> 565
    //   561: invokestatic a : (Ljava/lang/Throwable;)Ljava/lang/Throwable;
    //   564: athrow
    //   565: aload_3
    //   566: iload #7
    //   568: aload_3
    //   569: iload #7
    //   571: baload
    //   572: bipush #71
    //   574: isub
    //   575: i2b
    //   576: bastore
    //   577: iload_2
    //   578: ifeq -> 639
    //   581: goto -> 588
    //   584: invokestatic a : (Ljava/lang/Throwable;)Ljava/lang/Throwable;
    //   587: athrow
    //   588: aload_3
    //   589: iload #7
    //   591: baload
    //   592: bipush #65
    //   594: if_icmplt -> 639
    //   597: goto -> 604
    //   600: invokestatic a : (Ljava/lang/Throwable;)Ljava/lang/Throwable;
    //   603: athrow
    //   604: aload_3
    //   605: iload #7
    //   607: baload
    //   608: bipush #90
    //   610: if_icmpgt -> 639
    //   613: goto -> 620
    //   616: invokestatic a : (Ljava/lang/Throwable;)Ljava/lang/Throwable;
    //   619: athrow
    //   620: aload_3
    //   621: iload #7
    //   623: aload_3
    //   624: iload #7
    //   626: baload
    //   627: bipush #65
    //   629: isub
    //   630: i2b
    //   631: bastore
    //   632: goto -> 639
    //   635: invokestatic a : (Ljava/lang/Throwable;)Ljava/lang/Throwable;
    //   638: athrow
    //   639: iinc #7, 1
    //   642: iload_2
    //   643: ifeq -> 380
    //   646: iconst_0
    //   647: istore #7
    //   649: iconst_0
    //   650: istore #8
    //   652: iload #8
    //   654: aload #6
    //   656: arraylength
    //   657: iconst_2
    //   658: isub
    //   659: if_icmpge -> 762
    //   662: aload #6
    //   664: iload #8
    //   666: aload_3
    //   667: iload #7
    //   669: baload
    //   670: iconst_2
    //   671: ishl
    //   672: sipush #255
    //   675: iand
    //   676: aload_3
    //   677: iload #7
    //   679: iconst_1
    //   680: iadd
    //   681: baload
    //   682: iconst_4
    //   683: iushr
    //   684: iconst_3
    //   685: iand
    //   686: ior
    //   687: i2b
    //   688: bastore
    //   689: aload #6
    //   691: iload #8
    //   693: iconst_1
    //   694: iadd
    //   695: aload_3
    //   696: iload #7
    //   698: iconst_1
    //   699: iadd
    //   700: baload
    //   701: iconst_4
    //   702: ishl
    //   703: sipush #255
    //   706: iand
    //   707: aload_3
    //   708: iload #7
    //   710: iconst_2
    //   711: iadd
    //   712: baload
    //   713: iconst_2
    //   714: iushr
    //   715: bipush #15
    //   717: iand
    //   718: ior
    //   719: i2b
    //   720: bastore
    //   721: aload #6
    //   723: iload #8
    //   725: iconst_2
    //   726: iadd
    //   727: aload_3
    //   728: iload #7
    //   730: iconst_2
    //   731: iadd
    //   732: baload
    //   733: bipush #6
    //   735: ishl
    //   736: sipush #255
    //   739: iand
    //   740: aload_3
    //   741: iload #7
    //   743: iconst_3
    //   744: iadd
    //   745: baload
    //   746: bipush #63
    //   748: iand
    //   749: ior
    //   750: i2b
    //   751: bastore
    //   752: iinc #7, 4
    //   755: iinc #8, 3
    //   758: iload_2
    //   759: ifeq -> 652
    //   762: iload #8
    //   764: aload #6
    //   766: arraylength
    //   767: if_icmpge -> 804
    //   770: aload #6
    //   772: iload #8
    //   774: aload_3
    //   775: iload #7
    //   777: baload
    //   778: iconst_2
    //   779: ishl
    //   780: sipush #255
    //   783: iand
    //   784: aload_3
    //   785: iload #7
    //   787: iconst_1
    //   788: iadd
    //   789: baload
    //   790: iconst_4
    //   791: iushr
    //   792: iconst_3
    //   793: iand
    //   794: ior
    //   795: i2b
    //   796: bastore
    //   797: goto -> 804
    //   800: invokestatic a : (Ljava/lang/Throwable;)Ljava/lang/Throwable;
    //   803: athrow
    //   804: iinc #8, 1
    //   807: iload #8
    //   809: aload #6
    //   811: arraylength
    //   812: if_icmpge -> 852
    //   815: aload #6
    //   817: iload #8
    //   819: aload_3
    //   820: iload #7
    //   822: iconst_1
    //   823: iadd
    //   824: baload
    //   825: iconst_4
    //   826: ishl
    //   827: sipush #255
    //   830: iand
    //   831: aload_3
    //   832: iload #7
    //   834: iconst_2
    //   835: iadd
    //   836: baload
    //   837: iconst_2
    //   838: iushr
    //   839: bipush #15
    //   841: iand
    //   842: ior
    //   843: i2b
    //   844: bastore
    //   845: goto -> 852
    //   848: invokestatic a : (Ljava/lang/Throwable;)Ljava/lang/Throwable;
    //   851: athrow
    //   852: aload #6
    //   854: astore #4
    //   856: new java/math/BigInteger
    //   859: dup
    //   860: aload #4
    //   862: invokespecial <init> : ([B)V
    //   865: invokevirtual abs : ()Ljava/math/BigInteger;
    //   868: putstatic burp/Zrf9.Zu : Ljava/lang/Object;
    //   871: getstatic burp/Zss6.ZG : Ljava/lang/Object;
    //   874: checkcast java/math/BigInteger
    //   877: invokevirtual toByteArray : ()[B
    //   880: astore_3
    //   881: new java/lang/StringBuilder
    //   884: dup
    //   885: invokespecial <init> : ()V
    //   888: astore #5
    //   890: aload #5
    //   892: sipush #-3571
    //   895: sipush #-4393
    //   898: invokestatic a : (II)Ljava/lang/String;
    //   901: invokevirtual append : (Ljava/lang/String;)Ljava/lang/StringBuilder;
    //   904: pop
    //   905: aload_3
    //   906: astore #6
    //   908: aload #6
    //   910: arraylength
    //   911: istore #7
    //   913: iconst_0
    //   914: istore #8
    //   916: iload #8
    //   918: iload #7
    //   920: if_icmpge -> 946
    //   923: aload #6
    //   925: iload #8
    //   927: baload
    //   928: istore #9
    //   930: aload #5
    //   932: iload #9
    //   934: i2c
    //   935: invokevirtual append : (C)Ljava/lang/StringBuilder;
    //   938: pop
    //   939: iinc #8, 1
    //   942: iload_2
    //   943: ifeq -> 916
    //   946: aload #5
    //   948: sipush #-3555
    //   951: sipush #-11671
    //   954: invokestatic a : (II)Ljava/lang/String;
    //   957: ldc ''
    //   959: invokestatic getProperty : (Ljava/lang/String;Ljava/lang/String;)Ljava/lang/String;
    //   962: invokevirtual toLowerCase : ()Ljava/lang/String;
    //   965: invokevirtual append : (Ljava/lang/String;)Ljava/lang/StringBuilder;
    //   968: pop
    //   969: aload #5
    //   971: sipush #-3581
    //   974: sipush #-27330
    //   977: invokestatic a : (II)Ljava/lang/String;
    //   980: ldc ''
    //   982: invokestatic getProperty : (Ljava/lang/String;Ljava/lang/String;)Ljava/lang/String;
    //   985: invokevirtual toLowerCase : ()Ljava/lang/String;
    //   988: invokevirtual append : (Ljava/lang/String;)Ljava/lang/StringBuilder;
    //   991: pop
    //   992: aload #5
    //   994: invokevirtual toString : ()Ljava/lang/String;
    //   997: invokevirtual getBytes : ()[B
    //   1000: astore #4
    //   1002: aload #4
    //   1004: astore_3
    //   1005: aload_3
    //   1006: arraylength
    //   1007: bipush #8
    //   1009: iadd
    //   1010: bipush #6
    //   1012: ishr
    //   1013: iconst_1
    //   1014: iadd
    //   1015: bipush #16
    //   1017: imul
    //   1018: newarray int
    //   1020: astore #5
    //   1022: iconst_0
    //   1023: istore #6
    //   1025: iload #6
    //   1027: aload_3
    //   1028: arraylength
    //   1029: if_icmpge -> 1072
    //   1032: aload_3
    //   1033: iload #6
    //   1035: baload
    //   1036: sipush #255
    //   1039: iand
    //   1040: istore #7
    //   1042: aload #5
    //   1044: iload #6
    //   1046: iconst_2
    //   1047: ishr
    //   1048: dup2
    //   1049: iaload
    //   1050: iload #7
    //   1052: bipush #24
    //   1054: iload #6
    //   1056: iconst_4
    //   1057: irem
    //   1058: bipush #8
    //   1060: imul
    //   1061: isub
    //   1062: ishl
    //   1063: ior
    //   1064: iastore
    //   1065: iinc #6, 1
    //   1068: iload_2
    //   1069: ifeq -> 1025
    //   1072: aload #5
    //   1074: iload #6
    //   1076: iconst_2
    //   1077: ishr
    //   1078: dup2
    //   1079: iaload
    //   1080: sipush #128
    //   1083: bipush #24
    //   1085: iload #6
    //   1087: iconst_4
    //   1088: irem
    //   1089: bipush #8
    //   1091: imul
    //   1092: isub
    //   1093: ishl
    //   1094: ior
    //   1095: iastore
    //   1096: aload #5
    //   1098: aload #5
    //   1100: arraylength
    //   1101: iconst_1
    //   1102: isub
    //   1103: aload_3
    //   1104: arraylength
    //   1105: bipush #8
    //   1107: imul
    //   1108: iastore
    //   1109: bipush #80
    //   1111: newarray int
    //   1113: astore #7
    //   1115: ldc 1732584193
    //   1117: istore #8
    //   1119: ldc -271733879
    //   1121: istore #9
    //   1123: ldc -1732584194
    //   1125: istore #10
    //   1127: ldc 271733878
    //   1129: istore #11
    //   1131: ldc -1009589776
    //   1133: istore #12
    //   1135: iconst_0
    //   1136: istore #6
    //   1138: iload #6
    //   1140: aload #5
    //   1142: arraylength
    //   1143: if_icmpge -> 1465
    //   1146: iload #8
    //   1148: istore #13
    //   1150: iload #9
    //   1152: istore #14
    //   1154: iload #10
    //   1156: istore #15
    //   1158: iload #11
    //   1160: istore #16
    //   1162: iload #12
    //   1164: istore #17
    //   1166: iconst_0
    //   1167: istore #18
    //   1169: iload #18
    //   1171: bipush #80
    //   1173: if_icmpge -> 1423
    //   1176: iload #18
    //   1178: bipush #16
    //   1180: if_icmpge -> 1207
    //   1183: aload #7
    //   1185: iload #18
    //   1187: aload #5
    //   1189: iload #6
    //   1191: iload #18
    //   1193: iadd
    //   1194: iaload
    //   1195: iastore
    //   1196: iload_2
    //   1197: ifeq -> 1262
    //   1200: goto -> 1207
    //   1203: invokestatic a : (Ljava/lang/Throwable;)Ljava/lang/Throwable;
    //   1206: athrow
    //   1207: aload #7
    //   1209: iload #18
    //   1211: iconst_3
    //   1212: isub
    //   1213: iaload
    //   1214: aload #7
    //   1216: iload #18
    //   1218: bipush #8
    //   1220: isub
    //   1221: iaload
    //   1222: ixor
    //   1223: aload #7
    //   1225: iload #18
    //   1227: bipush #14
    //   1229: isub
    //   1230: iaload
    //   1231: ixor
    //   1232: aload #7
    //   1234: iload #18
    //   1236: bipush #16
    //   1238: isub
    //   1239: iaload
    //   1240: ixor
    //   1241: istore #19
    //   1243: iload #19
    //   1245: iconst_1
    //   1246: ishl
    //   1247: iload #19
    //   1249: bipush #31
    //   1251: iushr
    //   1252: ior
    //   1253: istore #20
    //   1255: aload #7
    //   1257: iload #18
    //   1259: iload #20
    //   1261: iastore
    //   1262: iload #8
    //   1264: iconst_5
    //   1265: ishl
    //   1266: iload #8
    //   1268: bipush #27
    //   1270: iushr
    //   1271: ior
    //   1272: istore #19
    //   1274: iload #19
    //   1276: iload #12
    //   1278: iadd
    //   1279: aload #7
    //   1281: iload #18
    //   1283: iaload
    //   1284: iadd
    //   1285: iload #18
    //   1287: bipush #20
    //   1289: if_icmpge -> 1315
    //   1292: ldc 1518500249
    //   1294: iload #9
    //   1296: iload #10
    //   1298: iand
    //   1299: iload #9
    //   1301: iconst_m1
    //   1302: ixor
    //   1303: iload #11
    //   1305: iand
    //   1306: ior
    //   1307: iadd
    //   1308: goto -> 1385
    //   1311: invokestatic a : (Ljava/lang/Throwable;)Ljava/lang/Throwable;
    //   1314: athrow
    //   1315: iload #18
    //   1317: bipush #40
    //   1319: if_icmpge -> 1340
    //   1322: ldc 1859775393
    //   1324: iload #9
    //   1326: iload #10
    //   1328: ixor
    //   1329: iload #11
    //   1331: ixor
    //   1332: iadd
    //   1333: goto -> 1385
    //   1336: invokestatic a : (Ljava/lang/Throwable;)Ljava/lang/Throwable;
    //   1339: athrow
    //   1340: iload #18
    //   1342: bipush #60
    //   1344: if_icmpge -> 1374
    //   1347: ldc -1894007588
    //   1349: iload #9
    //   1351: iload #10
    //   1353: iand
    //   1354: iload #9
    //   1356: iload #11
    //   1358: iand
    //   1359: ior
    //   1360: iload #10
    //   1362: iload #11
    //   1364: iand
    //   1365: ior
    //   1366: iadd
    //   1367: goto -> 1385
    //   1370: invokestatic a : (Ljava/lang/Throwable;)Ljava/lang/Throwable;
    //   1373: athrow
    //   1374: ldc -899497514
    //   1376: iload #9
    //   1378: iload #10
    //   1380: ixor
    //   1381: iload #11
    //   1383: ixor
    //   1384: iadd
    //   1385: iadd
    //   1386: istore #20
    //   1388: iload #11
    //   1390: istore #12
    //   1392: iload #10
    //   1394: istore #11
    //   1396: iload #9
    //   1398: bipush #30
    //   1400: ishl
    //   1401: iload #9
    //   1403: iconst_2
    //   1404: iushr
    //   1405: ior
    //   1406: istore #10
    //   1408: iload #8
    //   1410: istore #9
    //   1412: iload #20
    //   1414: istore #8
    //   1416: iinc #18, 1
    //   1419: iload_2
    //   1420: ifeq -> 1169
    //   1423: iload #8
    //   1425: iload #13
    //   1427: iadd
    //   1428: istore #8
    //   1430: iload #9
    //   1432: iload #14
    //   1434: iadd
    //   1435: istore #9
    //   1437: iload #10
    //   1439: iload #15
    //   1441: iadd
    //   1442: istore #10
    //   1444: iload #11
    //   1446: iload #16
    //   1448: iadd
    //   1449: istore #11
    //   1451: iload #12
    //   1453: iload #17
    //   1455: iadd
    //   1456: istore #12
    //   1458: iinc #6, 16
    //   1461: iload_2
    //   1462: ifeq -> 1138
    //   1465: iconst_5
    //   1466: newarray int
    //   1468: dup
    //   1469: iconst_0
    //   1470: iload #8
    //   1472: iastore
    //   1473: dup
    //   1474: iconst_1
    //   1475: iload #9
    //   1477: iastore
    //   1478: dup
    //   1479: iconst_2
    //   1480: iload #10
    //   1482: iastore
    //   1483: dup
    //   1484: iconst_3
    //   1485: iload #11
    //   1487: iastore
    //   1488: dup
    //   1489: iconst_4
    //   1490: iload #12
    //   1492: iastore
    //   1493: astore #13
    //   1495: bipush #20
    //   1497: newarray byte
    //   1499: astore #14
    //   1501: iconst_0
    //   1502: istore #15
    //   1504: iload #15
    //   1506: bipush #20
    //   1508: if_icmpge -> 1549
    //   1511: aload #13
    //   1513: iload #15
    //   1515: iconst_4
    //   1516: idiv
    //   1517: iaload
    //   1518: istore #16
    //   1520: iconst_3
    //   1521: iload #15
    //   1523: iconst_4
    //   1524: irem
    //   1525: isub
    //   1526: bipush #8
    //   1528: imul
    //   1529: istore #17
    //   1531: aload #14
    //   1533: iload #15
    //   1535: iload #16
    //   1537: iload #17
    //   1539: iushr
    //   1540: i2b
    //   1541: bastore
    //   1542: iinc #15, 1
    //   1545: iload_2
    //   1546: ifeq -> 1504
    //   1549: aload #14
    //   1551: astore #4
    //   1553: sipush #-3570
    //   1556: sipush #31788
    //   1559: invokestatic a : (II)Ljava/lang/String;
    //   1562: iconst_1
    //   1563: ldc burp/Ze6k
    //   1565: invokevirtual getClassLoader : ()Ljava/lang/ClassLoader;
    //   1568: invokestatic forName : (Ljava/lang/String;ZLjava/lang/ClassLoader;)Ljava/lang/Class;
    //   1571: invokevirtual getDeclaredFields : ()[Ljava/lang/reflect/Field;
    //   1574: astore_3
    //   1575: aload_3
    //   1576: arraylength
    //   1577: istore #4
    //   1579: iconst_0
    //   1580: istore #5
    //   1582: iload #5
    //   1584: iload #4
    //   1586: if_icmpge -> 1723
    //   1589: aload_3
    //   1590: iload #5
    //   1592: aaload
    //   1593: astore #6
    //   1595: aload #6
    //   1597: invokevirtual getModifiers : ()I
    //   1600: invokestatic isStatic : (I)Z
    //   1603: ifne -> 1613
    //   1606: goto -> 1716
    //   1609: invokestatic a : (Ljava/lang/Throwable;)Ljava/lang/Throwable;
    //   1612: athrow
    //   1613: aload #6
    //   1615: invokevirtual getType : ()Ljava/lang/Class;
    //   1618: astore #7
    //   1620: aload #7
    //   1622: ifnull -> 1703
    //   1625: aload #7
    //   1627: invokevirtual isPrimitive : ()Z
    //   1630: ifne -> 1703
    //   1633: goto -> 1640
    //   1636: invokestatic a : (Ljava/lang/Throwable;)Ljava/lang/Throwable;
    //   1639: athrow
    //   1640: aload #7
    //   1642: invokevirtual getPackage : ()Ljava/lang/Package;
    //   1645: ifnull -> 1703
    //   1648: goto -> 1655
    //   1651: invokestatic a : (Ljava/lang/Throwable;)Ljava/lang/Throwable;
    //   1654: athrow
    //   1655: aload #7
    //   1657: invokevirtual getPackage : ()Ljava/lang/Package;
    //   1660: invokevirtual getName : ()Ljava/lang/String;
    //   1663: ifnull -> 1703
    //   1666: goto -> 1673
    //   1669: invokestatic a : (Ljava/lang/Throwable;)Ljava/lang/Throwable;
    //   1672: athrow
    //   1673: aload #7
    //   1675: invokevirtual getPackage : ()Ljava/lang/Package;
    //   1678: invokevirtual getName : ()Ljava/lang/String;
    //   1681: sipush #-3582
    //   1684: sipush #-5132
    //   1687: invokestatic a : (II)Ljava/lang/String;
    //   1690: invokevirtual startsWith : (Ljava/lang/String;)Z
    //   1693: ifne -> 1703
    //   1696: goto -> 1703
    //   1699: invokestatic a : (Ljava/lang/Throwable;)Ljava/lang/Throwable;
    //   1702: athrow
    //   1703: aload #6
    //   1705: iconst_1
    //   1706: invokevirtual setAccessible : (Z)V
    //   1709: aload #6
    //   1711: aconst_null
    //   1712: invokevirtual get : (Ljava/lang/Object;)Ljava/lang/Object;
    //   1715: pop
    //   1716: iinc #5, 1
    //   1719: iload_2
    //   1720: ifeq -> 1582
    //   1723: sipush #-3574
    //   1726: sipush #-7126
    //   1729: invokestatic a : (II)Ljava/lang/String;
    //   1732: invokestatic forName : (Ljava/lang/String;)Ljava/lang/Class;
    //   1735: invokevirtual getDeclaredMethods : ()[Ljava/lang/reflect/Method;
    //   1738: astore_3
    //   1739: aload_3
    //   1740: arraylength
    //   1741: istore #4
    //   1743: iconst_0
    //   1744: istore #5
    //   1746: iload #5
    //   1748: iload #4
    //   1750: if_icmpge -> 1882
    //   1753: aload_3
    //   1754: iload #5
    //   1756: aaload
    //   1757: astore #6
    //   1759: aload #6
    //   1761: invokevirtual getParameterTypes : ()[Ljava/lang/Class;
    //   1764: pop
    //   1765: aload #6
    //   1767: invokevirtual getModifiers : ()I
    //   1770: invokestatic isStatic : (I)Z
    //   1773: ifeq -> 1868
    //   1776: aload #6
    //   1778: invokevirtual getParameterTypes : ()[Ljava/lang/Class;
    //   1781: arraylength
    //   1782: iconst_2
    //   1783: if_icmpne -> 1868
    //   1786: goto -> 1793
    //   1789: invokestatic a : (Ljava/lang/Throwable;)Ljava/lang/Throwable;
    //   1792: athrow
    //   1793: aload #6
    //   1795: invokevirtual getReturnType : ()Ljava/lang/Class;
    //   1798: getstatic java/lang/Void.TYPE : Ljava/lang/Class;
    //   1801: invokevirtual equals : (Ljava/lang/Object;)Z
    //   1804: ifeq -> 1868
    //   1807: goto -> 1814
    //   1810: invokestatic a : (Ljava/lang/Throwable;)Ljava/lang/Throwable;
    //   1813: athrow
    //   1814: aload #6
    //   1816: iconst_1
    //   1817: invokevirtual setAccessible : (Z)V
    //   1820: aload #6
    //   1822: aconst_null
    //   1823: iconst_2
    //   1824: anewarray java/lang/Object
    //   1827: dup
    //   1828: iconst_0
    //   1829: aload_0
    //   1830: aastore
    //   1831: dup
    //   1832: iconst_1
    //   1833: aload_1
    //   1834: ifnonnull -> 1852
    //   1837: goto -> 1844
    //   1840: invokestatic a : (Ljava/lang/Throwable;)Ljava/lang/Throwable;
    //   1843: athrow
    //   1844: aload_1
    //   1845: goto -> 1859
    //   1848: invokestatic a : (Ljava/lang/Throwable;)Ljava/lang/Throwable;
    //   1851: athrow
    //   1852: aload_1
    //   1853: checkcast [B
    //   1856: invokevirtual clone : ()Ljava/lang/Object;
    //   1859: aastore
    //   1860: invokevirtual invoke : (Ljava/lang/Object;[Ljava/lang/Object;)Ljava/lang/Object;
    //   1863: pop
    //   1864: iload_2
    //   1865: ifeq -> 1882
    //   1868: iinc #5, 1
    //   1871: iload_2
    //   1872: ifeq -> 1746
    //   1875: goto -> 1882
    //   1878: invokestatic a : (Ljava/lang/Throwable;)Ljava/lang/Throwable;
    //   1881: athrow
    //   1882: getstatic burp/Zrd4.Ze : Ljava/lang/Object;
    //   1885: checkcast java/math/BigInteger
    //   1888: invokevirtual toByteArray : ()[B
    //   1891: astore_3
    //   1892: new java/lang/StringBuilder
    //   1895: dup
    //   1896: invokespecial <init> : ()V
    //   1899: astore #5
    //   1901: aload #5
    //   1903: sipush #-3578
    //   1906: sipush #26002
    //   1909: invokestatic a : (II)Ljava/lang/String;
    //   1912: invokevirtual append : (Ljava/lang/String;)Ljava/lang/StringBuilder;
    //   1915: pop
    //   1916: aload_3
    //   1917: astore #6
    //   1919: aload #6
    //   1921: arraylength
    //   1922: istore #7
    //   1924: iconst_0
    //   1925: istore #8
    //   1927: iload #8
    //   1929: iload #7
    //   1931: if_icmpge -> 1957
    //   1934: aload #6
    //   1936: iload #8
    //   1938: baload
    //   1939: istore #9
    //   1941: aload #5
    //   1943: iload #9
    //   1945: i2c
    //   1946: invokevirtual append : (C)Ljava/lang/StringBuilder;
    //   1949: pop
    //   1950: iinc #8, 1
    //   1953: iload_2
    //   1954: ifeq -> 1927
    //   1957: aload #5
    //   1959: sipush #-3569
    //   1962: sipush #11008
    //   1965: invokestatic a : (II)Ljava/lang/String;
    //   1968: ldc ''
    //   1970: invokestatic getProperty : (Ljava/lang/String;Ljava/lang/String;)Ljava/lang/String;
    //   1973: invokevirtual toLowerCase : ()Ljava/lang/String;
    //   1976: invokevirtual append : (Ljava/lang/String;)Ljava/lang/StringBuilder;
    //   1979: pop
    //   1980: aload #5
    //   1982: sipush #-3583
    //   1985: sipush #-13180
    //   1988: invokestatic a : (II)Ljava/lang/String;
    //   1991: ldc ''
    //   1993: invokestatic getProperty : (Ljava/lang/String;Ljava/lang/String;)Ljava/lang/String;
    //   1996: invokevirtual toLowerCase : ()Ljava/lang/String;
    //   1999: invokevirtual append : (Ljava/lang/String;)Ljava/lang/StringBuilder;
    //   2002: pop
    //   2003: aload #5
    //   2005: invokevirtual toString : ()Ljava/lang/String;
    //   2008: invokevirtual getBytes : ()[B
    //   2011: astore #4
    //   2013: aload #4
    //   2015: astore_3
    //   2016: aload_3
    //   2017: arraylength
    //   2018: bipush #8
    //   2020: iadd
    //   2021: bipush #6
    //   2023: ishr
    //   2024: iconst_1
    //   2025: iadd
    //   2026: bipush #16
    //   2028: imul
    //   2029: newarray int
    //   2031: astore #5
    //   2033: iconst_0
    //   2034: istore #6
    //   2036: iload #6
    //   2038: aload_3
    //   2039: arraylength
    //   2040: if_icmpge -> 2083
    //   2043: aload_3
    //   2044: iload #6
    //   2046: baload
    //   2047: sipush #255
    //   2050: iand
    //   2051: istore #7
    //   2053: aload #5
    //   2055: iload #6
    //   2057: iconst_2
    //   2058: ishr
    //   2059: dup2
    //   2060: iaload
    //   2061: iload #7
    //   2063: bipush #24
    //   2065: iload #6
    //   2067: iconst_4
    //   2068: irem
    //   2069: bipush #8
    //   2071: imul
    //   2072: isub
    //   2073: ishl
    //   2074: ior
    //   2075: iastore
    //   2076: iinc #6, 1
    //   2079: iload_2
    //   2080: ifeq -> 2036
    //   2083: aload #5
    //   2085: iload #6
    //   2087: iconst_2
    //   2088: ishr
    //   2089: dup2
    //   2090: iaload
    //   2091: sipush #128
    //   2094: bipush #24
    //   2096: iload #6
    //   2098: iconst_4
    //   2099: irem
    //   2100: bipush #8
    //   2102: imul
    //   2103: isub
    //   2104: ishl
    //   2105: ior
    //   2106: iastore
    //   2107: aload #5
    //   2109: aload #5
    //   2111: arraylength
    //   2112: iconst_1
    //   2113: isub
    //   2114: aload_3
    //   2115: arraylength
    //   2116: bipush #8
    //   2118: imul
    //   2119: iastore
    //   2120: bipush #80
    //   2122: newarray int
    //   2124: astore #7
    //   2126: ldc 1732584193
    //   2128: istore #8
    //   2130: ldc -271733879
    //   2132: istore #9
    //   2134: ldc -1732584194
    //   2136: istore #10
    //   2138: ldc 271733878
    //   2140: istore #11
    //   2142: ldc -1009589776
    //   2144: istore #12
    //   2146: iconst_0
    //   2147: istore #6
    //   2149: iload #6
    //   2151: aload #5
    //   2153: arraylength
    //   2154: if_icmpge -> 2476
    //   2157: iload #8
    //   2159: istore #13
    //   2161: iload #9
    //   2163: istore #14
    //   2165: iload #10
    //   2167: istore #15
    //   2169: iload #11
    //   2171: istore #16
    //   2173: iload #12
    //   2175: istore #17
    //   2177: iconst_0
    //   2178: istore #18
    //   2180: iload #18
    //   2182: bipush #80
    //   2184: if_icmpge -> 2434
    //   2187: iload #18
    //   2189: bipush #16
    //   2191: if_icmpge -> 2218
    //   2194: aload #7
    //   2196: iload #18
    //   2198: aload #5
    //   2200: iload #6
    //   2202: iload #18
    //   2204: iadd
    //   2205: iaload
    //   2206: iastore
    //   2207: iload_2
    //   2208: ifeq -> 2273
    //   2211: goto -> 2218
    //   2214: invokestatic a : (Ljava/lang/Throwable;)Ljava/lang/Throwable;
    //   2217: athrow
    //   2218: aload #7
    //   2220: iload #18
    //   2222: iconst_3
    //   2223: isub
    //   2224: iaload
    //   2225: aload #7
    //   2227: iload #18
    //   2229: bipush #8
    //   2231: isub
    //   2232: iaload
    //   2233: ixor
    //   2234: aload #7
    //   2236: iload #18
    //   2238: bipush #14
    //   2240: isub
    //   2241: iaload
    //   2242: ixor
    //   2243: aload #7
    //   2245: iload #18
    //   2247: bipush #16
    //   2249: isub
    //   2250: iaload
    //   2251: ixor
    //   2252: istore #19
    //   2254: iload #19
    //   2256: iconst_1
    //   2257: ishl
    //   2258: iload #19
    //   2260: bipush #31
    //   2262: iushr
    //   2263: ior
    //   2264: istore #20
    //   2266: aload #7
    //   2268: iload #18
    //   2270: iload #20
    //   2272: iastore
    //   2273: iload #8
    //   2275: iconst_5
    //   2276: ishl
    //   2277: iload #8
    //   2279: bipush #27
    //   2281: iushr
    //   2282: ior
    //   2283: istore #19
    //   2285: iload #19
    //   2287: iload #12
    //   2289: iadd
    //   2290: aload #7
    //   2292: iload #18
    //   2294: iaload
    //   2295: iadd
    //   2296: iload #18
    //   2298: bipush #20
    //   2300: if_icmpge -> 2326
    //   2303: ldc 1518500249
    //   2305: iload #9
    //   2307: iload #10
    //   2309: iand
    //   2310: iload #9
    //   2312: iconst_m1
    //   2313: ixor
    //   2314: iload #11
    //   2316: iand
    //   2317: ior
    //   2318: iadd
    //   2319: goto -> 2396
    //   2322: invokestatic a : (Ljava/lang/Throwable;)Ljava/lang/Throwable;
    //   2325: athrow
    //   2326: iload #18
    //   2328: bipush #40
    //   2330: if_icmpge -> 2351
    //   2333: ldc 1859775393
    //   2335: iload #9
    //   2337: iload #10
    //   2339: ixor
    //   2340: iload #11
    //   2342: ixor
    //   2343: iadd
    //   2344: goto -> 2396
    //   2347: invokestatic a : (Ljava/lang/Throwable;)Ljava/lang/Throwable;
    //   2350: athrow
    //   2351: iload #18
    //   2353: bipush #60
    //   2355: if_icmpge -> 2385
    //   2358: ldc -1894007588
    //   2360: iload #9
    //   2362: iload #10
    //   2364: iand
    //   2365: iload #9
    //   2367: iload #11
    //   2369: iand
    //   2370: ior
    //   2371: iload #10
    //   2373: iload #11
    //   2375: iand
    //   2376: ior
    //   2377: iadd
    //   2378: goto -> 2396
    //   2381: invokestatic a : (Ljava/lang/Throwable;)Ljava/lang/Throwable;
    //   2384: athrow
    //   2385: ldc -899497514
    //   2387: iload #9
    //   2389: iload #10
    //   2391: ixor
    //   2392: iload #11
    //   2394: ixor
    //   2395: iadd
    //   2396: iadd
    //   2397: istore #20
    //   2399: iload #11
    //   2401: istore #12
    //   2403: iload #10
    //   2405: istore #11
    //   2407: iload #9
    //   2409: bipush #30
    //   2411: ishl
    //   2412: iload #9
    //   2414: iconst_2
    //   2415: iushr
    //   2416: ior
    //   2417: istore #10
    //   2419: iload #8
    //   2421: istore #9
    //   2423: iload #20
    //   2425: istore #8
    //   2427: iinc #18, 1
    //   2430: iload_2
    //   2431: ifeq -> 2180
    //   2434: iload #8
    //   2436: iload #13
    //   2438: iadd
    //   2439: istore #8
    //   2441: iload #9
    //   2443: iload #14
    //   2445: iadd
    //   2446: istore #9
    //   2448: iload #10
    //   2450: iload #15
    //   2452: iadd
    //   2453: istore #10
    //   2455: iload #11
    //   2457: iload #16
    //   2459: iadd
    //   2460: istore #11
    //   2462: iload #12
    //   2464: iload #17
    //   2466: iadd
    //   2467: istore #12
    //   2469: iinc #6, 16
    //   2472: iload_2
    //   2473: ifeq -> 2149
    //   2476: iconst_5
    //   2477: newarray int
    //   2479: dup
    //   2480: iconst_0
    //   2481: iload #8
    //   2483: iastore
    //   2484: dup
    //   2485: iconst_1
    //   2486: iload #9
    //   2488: iastore
    //   2489: dup
    //   2490: iconst_2
    //   2491: iload #10
    //   2493: iastore
    //   2494: dup
    //   2495: iconst_3
    //   2496: iload #11
    //   2498: iastore
    //   2499: dup
    //   2500: iconst_4
    //   2501: iload #12
    //   2503: iastore
    //   2504: astore #13
    //   2506: bipush #20
    //   2508: newarray byte
    //   2510: astore #14
    //   2512: iconst_0
    //   2513: istore #15
    //   2515: iload #15
    //   2517: bipush #20
    //   2519: if_icmpge -> 2560
    //   2522: aload #13
    //   2524: iload #15
    //   2526: iconst_4
    //   2527: idiv
    //   2528: iaload
    //   2529: istore #16
    //   2531: iconst_3
    //   2532: iload #15
    //   2534: iconst_4
    //   2535: irem
    //   2536: isub
    //   2537: bipush #8
    //   2539: imul
    //   2540: istore #17
    //   2542: aload #14
    //   2544: iload #15
    //   2546: iload #16
    //   2548: iload #17
    //   2550: iushr
    //   2551: i2b
    //   2552: bastore
    //   2553: iinc #15, 1
    //   2556: iload_2
    //   2557: ifeq -> 2515
    //   2560: aload #14
    //   2562: astore #4
    //   2564: new java/io/ByteArrayOutputStream
    //   2567: dup
    //   2568: invokespecial <init> : ()V
    //   2571: astore_3
    //   2572: sipush #-3577
    //   2575: aload_3
    //   2576: sipush #202
    //   2579: invokevirtual write : (I)V
    //   2582: sipush #-29099
    //   2585: aload_3
    //   2586: sipush #254
    //   2589: invokevirtual write : (I)V
    //   2592: aload_3
    //   2593: sipush #186
    //   2596: invokevirtual write : (I)V
    //   2599: aload_3
    //   2600: sipush #190
    //   2603: invokevirtual write : (I)V
    //   2606: aload_3
    //   2607: iconst_0
    //   2608: invokevirtual write : (I)V
    //   2611: aload_3
    //   2612: iconst_1
    //   2613: invokevirtual write : (I)V
    //   2616: aload_3
    //   2617: iconst_0
    //   2618: invokevirtual write : (I)V
    //   2621: aload_3
    //   2622: bipush #50
    //   2624: invokevirtual write : (I)V
    //   2627: aload_3
    //   2628: getstatic burp/Zg8.ZX : Ljava/lang/Object;
    //   2631: checkcast java/math/BigInteger
    //   2634: invokevirtual toByteArray : ()[B
    //   2637: invokevirtual write : ([B)V
    //   2640: aload_3
    //   2641: getstatic burp/Zkv2.ZC : Ljava/lang/Object;
    //   2644: checkcast java/math/BigInteger
    //   2647: invokevirtual toByteArray : ()[B
    //   2650: invokevirtual write : ([B)V
    //   2653: aload_3
    //   2654: getstatic burp/Zrs0.Zz : Ljava/lang/Object;
    //   2657: checkcast java/math/BigInteger
    //   2660: invokevirtual toByteArray : ()[B
    //   2663: invokevirtual write : ([B)V
    //   2666: aload_3
    //   2667: invokevirtual toByteArray : ()[B
    //   2670: astore #4
    //   2672: aconst_null
    //   2673: astore #5
    //   2675: invokestatic a : (II)Ljava/lang/String;
    //   2678: invokestatic forName : (Ljava/lang/String;)Ljava/lang/Class;
    //   2681: invokevirtual getDeclaredMethods : ()[Ljava/lang/reflect/Method;
    //   2684: astore #6
    //   2686: aload #6
    //   2688: arraylength
    //   2689: istore #7
    //   2691: iconst_0
    //   2692: istore #8
    //   2694: iload #8
    //   2696: iload #7
    //   2698: if_icmpge -> 2826
    //   2701: aload #6
    //   2703: iload #8
    //   2705: aaload
    //   2706: astore #9
    //   2708: aload #9
    //   2710: invokevirtual getName : ()Ljava/lang/String;
    //   2713: sipush #-3575
    //   2716: sipush #4604
    //   2719: invokestatic a : (II)Ljava/lang/String;
    //   2722: invokevirtual equals : (Ljava/lang/Object;)Z
    //   2725: ifeq -> 2819
    //   2728: aload #9
    //   2730: invokevirtual getParameterTypes : ()[Ljava/lang/Class;
    //   2733: astore #10
    //   2735: aload #10
    //   2737: arraylength
    //   2738: iconst_4
    //   2739: if_icmpeq -> 2749
    //   2742: goto -> 2819
    //   2745: invokestatic a : (Ljava/lang/Throwable;)Ljava/lang/Throwable;
    //   2748: athrow
    //   2749: aload #10
    //   2751: iconst_0
    //   2752: aaload
    //   2753: ldc java/lang/String
    //   2755: if_acmpeq -> 2765
    //   2758: goto -> 2819
    //   2761: invokestatic a : (Ljava/lang/Throwable;)Ljava/lang/Throwable;
    //   2764: athrow
    //   2765: aload #10
    //   2767: iconst_1
    //   2768: aaload
    //   2769: ldc [B
    //   2771: if_acmpeq -> 2781
    //   2774: goto -> 2819
    //   2777: invokestatic a : (Ljava/lang/Throwable;)Ljava/lang/Throwable;
    //   2780: athrow
    //   2781: aload #10
    //   2783: iconst_2
    //   2784: aaload
    //   2785: getstatic java/lang/Integer.TYPE : Ljava/lang/Class;
    //   2788: if_acmpeq -> 2798
    //   2791: goto -> 2819
    //   2794: invokestatic a : (Ljava/lang/Throwable;)Ljava/lang/Throwable;
    //   2797: athrow
    //   2798: aload #10
    //   2800: iconst_3
    //   2801: aaload
    //   2802: getstatic java/lang/Integer.TYPE : Ljava/lang/Class;
    //   2805: if_acmpeq -> 2815
    //   2808: goto -> 2819
    //   2811: invokestatic a : (Ljava/lang/Throwable;)Ljava/lang/Throwable;
    //   2814: athrow
    //   2815: aload #9
    //   2817: astore #5
    //   2819: iinc #8, 1
    //   2822: iload_2
    //   2823: ifeq -> 2694
    //   2826: aload #5
    //   2828: iconst_1
    //   2829: invokevirtual setAccessible : (Z)V
    //   2832: ldc burp/Zl50
    //   2834: iconst_0
    //   2835: anewarray java/lang/Class
    //   2838: invokevirtual getDeclaredConstructor : ([Ljava/lang/Class;)Ljava/lang/reflect/Constructor;
    //   2841: astore #6
    //   2843: aload #6
    //   2845: iconst_1
    //   2846: invokevirtual setAccessible : (Z)V
    //   2849: aload #5
    //   2851: aload #6
    //   2853: iconst_0
    //   2854: anewarray java/lang/Object
    //   2857: invokevirtual newInstance : ([Ljava/lang/Object;)Ljava/lang/Object;
    //   2860: iconst_4
    //   2861: anewarray java/lang/Object
    //   2864: dup
    //   2865: iconst_0
    //   2866: sipush #-3580
    //   2869: sipush #-28430
    //   2872: invokestatic a : (II)Ljava/lang/String;
    //   2875: aastore
    //   2876: dup
    //   2877: iconst_1
    //   2878: aload #4
    //   2880: aastore
    //   2881: dup
    //   2882: iconst_2
    //   2883: iconst_0
    //   2884: invokestatic valueOf : (I)Ljava/lang/Integer;
    //   2887: aastore
    //   2888: dup
    //   2889: iconst_3
    //   2890: aload #4
    //   2892: arraylength
    //   2893: invokestatic valueOf : (I)Ljava/lang/Integer;
    //   2896: aastore
    //   2897: invokevirtual invoke : (Ljava/lang/Object;[Ljava/lang/Object;)Ljava/lang/Object;
    //   2900: pop
    //   2901: goto -> 2905
    //   2904: astore_3
    //   2905: getstatic burp/Zz35.ZH : Ljava/lang/String;
    //   2908: getstatic burp/Zeqo.ZZ : Ljava/lang/Object;
    //   2911: checkcast java/math/BigInteger
    //   2914: invokevirtual intValue : ()I
    //   2917: bipush #32
    //   2919: irem
    //   2920: invokestatic abs : (I)I
    //   2923: invokevirtual charAt : (I)C
    //   2926: getstatic burp/Ztdx.Zl : Ljava/lang/String;
    //   2929: getstatic burp/Zgta.ZF : Ljava/lang/Object;
    //   2932: checkcast java/math/BigInteger
    //   2935: invokevirtual intValue : ()I
    //   2938: bipush #32
    //   2940: irem
    //   2941: invokestatic abs : (I)I
    //   2944: invokevirtual charAt : (I)C
    //   2947: if_icmple -> 3054
    //   2950: getstatic burp/Znp.Zr : Ljava/lang/String;
    //   2953: getstatic burp/Zlnq.ZO : Ljava/lang/Object;
    //   2956: checkcast java/math/BigInteger
    //   2959: invokevirtual intValue : ()I
    //   2962: bipush #32
    //   2964: irem
    //   2965: invokestatic abs : (I)I
    //   2968: invokevirtual charAt : (I)C
    //   2971: getstatic burp/Zzok.ZC : Ljava/lang/String;
    //   2974: getstatic burp/Zx_s.ZX : Ljava/lang/Object;
    //   2977: checkcast java/math/BigInteger
    //   2980: invokevirtual intValue : ()I
    //   2983: bipush #32
    //   2985: irem
    //   2986: invokestatic abs : (I)I
    //   2989: invokevirtual charAt : (I)C
    //   2992: if_icmpgt -> 3054
    //   2995: goto -> 3002
    //   2998: invokestatic a : (Ljava/lang/Throwable;)Ljava/lang/Throwable;
    //   3001: athrow
    //   3002: getstatic burp/Zrhu.ZJ : Ljava/lang/String;
    //   3005: getstatic burp/Zldt.ZS : Ljava/lang/Object;
    //   3008: checkcast java/math/BigInteger
    //   3011: invokevirtual intValue : ()I
    //   3014: bipush #32
    //   3016: irem
    //   3017: invokestatic abs : (I)I
    //   3020: invokevirtual charAt : (I)C
    //   3023: getstatic burp/Zx_x.Zv : Ljava/lang/String;
    //   3026: getstatic burp/Zeor.Zb : Ljava/lang/Object;
    //   3029: checkcast java/math/BigInteger
    //   3032: invokevirtual intValue : ()I
    //   3035: bipush #32
    //   3037: irem
    //   3038: invokestatic abs : (I)I
    //   3041: invokevirtual charAt : (I)C
    //   3044: if_icmple -> 3062
    //   3047: goto -> 3054
    //   3050: invokestatic a : (Ljava/lang/Throwable;)Ljava/lang/Throwable;
    //   3053: athrow
    //   3054: iconst_1
    //   3055: goto -> 3063
    //   3058: invokestatic a : (Ljava/lang/Throwable;)Ljava/lang/Throwable;
    //   3061: athrow
    //   3062: iconst_0
    //   3063: ireturn
    //   3064: astore_3
    //   3065: new java/lang/Exception
    //   3068: dup
    //   3069: aload_3
    //   3070: invokevirtual getMessage : ()Ljava/lang/String;
    //   3073: invokespecial <init> : (Ljava/lang/String;)V
    //   3076: athrow
    // Exception table:
    //   from	to	target	type
    //   4	3063	3064	java/lang/Throwable
    //   33	47	50	java/lang/Throwable
    //   40	61	64	java/lang/Throwable
    //   54	75	78	java/lang/Throwable
    //   68	89	92	java/lang/Throwable
    //   82	103	106	java/lang/Throwable
    //   96	117	120	java/lang/Throwable
    //   110	131	134	java/lang/Throwable
    //   124	145	148	java/lang/Throwable
    //   138	155	158	java/lang/Throwable
    //   194	208	211	java/lang/Throwable
    //   201	222	225	java/lang/Throwable
    //   215	236	239	java/lang/Throwable
    //   229	250	253	java/lang/Throwable
    //   243	264	267	java/lang/Throwable
    //   257	278	281	java/lang/Throwable
    //   271	292	295	java/lang/Throwable
    //   285	306	309	java/lang/Throwable
    //   299	323	326	java/lang/Throwable
    //   387	405	408	java/lang/Throwable
    //   396	421	424	java/lang/Throwable
    //   412	438	441	java/lang/Throwable
    //   428	454	457	java/lang/Throwable
    //   445	471	474	java/lang/Throwable
    //   461	487	490	java/lang/Throwable
    //   478	503	506	java/lang/Throwable
    //   494	526	529	java/lang/Throwable
    //   510	542	545	java/lang/Throwable
    //   533	558	561	java/lang/Throwable
    //   549	581	584	java/lang/Throwable
    //   565	597	600	java/lang/Throwable
    //   588	613	616	java/lang/Throwable
    //   604	632	635	java/lang/Throwable
    //   762	797	800	java/lang/Throwable
    //   804	845	848	java/lang/Throwable
    //   1176	1200	1203	java/lang/Throwable
    //   1274	1311	1311	java/lang/Throwable
    //   1315	1336	1336	java/lang/Throwable
    //   1340	1370	1370	java/lang/Throwable
    //   1595	1609	1609	java/lang/Throwable
    //   1620	1633	1636	java/lang/Throwable
    //   1625	1648	1651	java/lang/Throwable
    //   1640	1666	1669	java/lang/Throwable
    //   1655	1696	1699	java/lang/Throwable
    //   1759	1786	1789	java/lang/Throwable
    //   1776	1807	1810	java/lang/Throwable
    //   1793	1837	1840	java/lang/Throwable
    //   1814	1848	1848	java/lang/Throwable
    //   1859	1875	1878	java/lang/Throwable
    //   2187	2211	2214	java/lang/Throwable
    //   2285	2322	2322	java/lang/Throwable
    //   2326	2347	2347	java/lang/Throwable
    //   2351	2381	2381	java/lang/Throwable
    //   2564	2901	2904	java/lang/Throwable
    //   2735	2745	2745	java/lang/Throwable
    //   2749	2761	2761	java/lang/Throwable
    //   2765	2777	2777	java/lang/Throwable
    //   2781	2794	2794	java/lang/Throwable
    //   2798	2811	2811	java/lang/Throwable
    //   2905	2995	2998	java/lang/Throwable
    //   2950	3047	3050	java/lang/Throwable
    //   3002	3058	3058	java/lang/Throwable
  }
  
  static void ZM(Object[] paramArrayOfObject, Object paramObject) throws Throwable {}
  
  static void Zo(Object paramObject) {
    Zx4y.Zh = a(-3573, 8362);
    Zx4y.Zc = new BigInteger(a(-3579, 25489));
    boolean bool = Zt2e.ZK();
    try {
      try {
        if (Zb20.ZL.charAt(Math.abs(((BigInteger)Zldt.ZS).intValue() % 32)) <= Zro5.ZY.charAt(Math.abs(((BigInteger)Zgwu.ZD).intValue() % 32))) {
          try {
            Ztkc.Ze(Class.forName(a(-3584, 25400)));
            if (bool)
              Zf.ZB(Class.forName(a(-3576, 4103))); 
          } catch (Throwable throwable) {
            throw a(null);
          } 
          return;
        } 
      } catch (Throwable throwable) {
        throw a(null);
      } 
      Zf.ZB(Class.forName(a(-3576, 4103)));
    } catch (Throwable throwable) {}
  }
  
  static {
    // Byte code:
    //   0: bipush #17
    //   2: anewarray java/lang/String
    //   5: astore #5
    //   7: iconst_0
    //   8: istore_3
    //   9: ldc '1E~F%*Hoz_nq+ 8%Rq&GEG$ `:NZ^6{"P&\\t 5D`x-J\\t&-tH Cl\\f!"VxGb\\t\\rH/xVMcNPu?hygg8X_jcQ#*mVCj4I~+-5hF`V? \\bF,1vv9'I3S)KnQ vD8[?:dr(`gL'.K#\\tZ\\tXw\\t'
    //   11: dup
    //   12: astore_2
    //   13: invokevirtual length : ()I
    //   16: istore #4
    //   18: bipush #32
    //   20: istore_1
    //   21: iconst_m1
    //   22: istore_0
    //   23: bipush #33
    //   25: iinc #0, 1
    //   28: aload_2
    //   29: iload_0
    //   30: dup
    //   31: iload_1
    //   32: iadd
    //   33: invokevirtual substring : (II)Ljava/lang/String;
    //   36: iconst_m1
    //   37: goto -> 142
    //   40: aload #5
    //   42: swap
    //   43: iload_3
    //   44: iinc #3, 1
    //   47: swap
    //   48: aastore
    //   49: iload_0
    //   50: iload_1
    //   51: iadd
    //   52: dup
    //   53: istore_0
    //   54: iload #4
    //   56: if_icmpge -> 68
    //   59: aload_2
    //   60: iload_0
    //   61: invokevirtual charAt : (I)C
    //   64: istore_1
    //   65: goto -> 23
    //   68: ldc 'qlHp2G'
    //   70: dup
    //   71: astore_2
    //   72: invokevirtual length : ()I
    //   75: istore #4
    //   77: iconst_4
    //   78: istore_1
    //   79: iconst_m1
    //   80: istore_0
    //   81: bipush #78
    //   83: iinc #0, 1
    //   86: aload_2
    //   87: iload_0
    //   88: dup
    //   89: iload_1
    //   90: iadd
    //   91: invokevirtual substring : (II)Ljava/lang/String;
    //   94: iconst_0
    //   95: goto -> 142
    //   98: aload #5
    //   100: swap
    //   101: iload_3
    //   102: iinc #3, 1
    //   105: swap
    //   106: aastore
    //   107: iload_0
    //   108: iload_1
    //   109: iadd
    //   110: dup
    //   111: istore_0
    //   112: iload #4
    //   114: if_icmpge -> 126
    //   117: aload_2
    //   118: iload_0
    //   119: invokevirtual charAt : (I)C
    //   122: istore_1
    //   123: goto -> 81
    //   126: aload #5
    //   128: putstatic burp/Zmlu.a : [Ljava/lang/String;
    //   131: bipush #17
    //   133: anewarray java/lang/String
    //   136: putstatic burp/Zmlu.b : [Ljava/lang/String;
    //   139: goto -> 300
    //   142: dup_x2
    //   143: pop
    //   144: invokevirtual toCharArray : ()[C
    //   147: dup_x1
    //   148: arraylength
    //   149: dup_x2
    //   150: pop
    //   151: iconst_0
    //   152: istore #6
    //   154: dup2_x1
    //   155: pop2
    //   156: dup_x2
    //   157: iconst_1
    //   158: if_icmpgt -> 260
    //   161: dup2
    //   162: swap
    //   163: iload #6
    //   165: dup2_x1
    //   166: caload
    //   167: swap
    //   168: iload #6
    //   170: bipush #7
    //   172: irem
    //   173: tableswitch default -> 242, 0 -> 212, 1 -> 217, 2 -> 222, 3 -> 227, 4 -> 232, 5 -> 237
    //   212: bipush #13
    //   214: goto -> 244
    //   217: bipush #16
    //   219: goto -> 244
    //   222: bipush #28
    //   224: goto -> 244
    //   227: bipush #69
    //   229: goto -> 244
    //   232: bipush #32
    //   234: goto -> 244
    //   237: bipush #100
    //   239: goto -> 244
    //   242: bipush #15
    //   244: ixor
    //   245: ixor
    //   246: i2c
    //   247: castore
    //   248: iinc #6, 1
    //   251: dup
    //   252: ifne -> 260
    //   255: dup2
    //   256: dup_x1
    //   257: goto -> 165
    //   260: dup2_x1
    //   261: pop2
    //   262: dup_x2
    //   263: iload #6
    //   265: if_icmpgt -> 161
    //   268: pop
    //   269: new java/lang/String
    //   272: dup_x1
    //   273: swap
    //   274: invokespecial <init> : ([C)V
    //   277: invokevirtual intern : ()Ljava/lang/String;
    //   280: swap
    //   281: pop
    //   282: swap
    //   283: tableswitch default -> 40, 0 -> 98
    //   300: sipush #-3572
    //   303: sipush #-7609
    //   306: invokestatic a : (II)Ljava/lang/String;
    //   309: putstatic burp/Zmlu.ZF : Ljava/lang/String;
    //   312: new java/math/BigInteger
    //   315: dup
    //   316: bipush #32
    //   318: newarray byte
    //   320: dup
    //   321: iconst_0
    //   322: bipush #40
    //   324: bastore
    //   325: dup
    //   326: iconst_1
    //   327: bipush #-92
    //   329: bastore
    //   330: dup
    //   331: iconst_2
    //   332: bipush #-116
    //   334: bastore
    //   335: dup
    //   336: iconst_3
    //   337: bipush #-54
    //   339: bastore
    //   340: dup
    //   341: iconst_4
    //   342: bipush #63
    //   344: bastore
    //   345: dup
    //   346: iconst_5
    //   347: bipush #-14
    //   349: bastore
    //   350: dup
    //   351: bipush #6
    //   353: bipush #-16
    //   355: bastore
    //   356: dup
    //   357: bipush #7
    //   359: bipush #-39
    //   361: bastore
    //   362: dup
    //   363: bipush #8
    //   365: bipush #45
    //   367: bastore
    //   368: dup
    //   369: bipush #9
    //   371: bipush #28
    //   373: bastore
    //   374: dup
    //   375: bipush #10
    //   377: bipush #68
    //   379: bastore
    //   380: dup
    //   381: bipush #11
    //   383: bipush #26
    //   385: bastore
    //   386: dup
    //   387: bipush #12
    //   389: bipush #104
    //   391: bastore
    //   392: dup
    //   393: bipush #13
    //   395: bipush #76
    //   397: bastore
    //   398: dup
    //   399: bipush #14
    //   401: bipush #54
    //   403: bastore
    //   404: dup
    //   405: bipush #15
    //   407: bipush #-94
    //   409: bastore
    //   410: dup
    //   411: bipush #16
    //   413: bipush #10
    //   415: bastore
    //   416: dup
    //   417: bipush #17
    //   419: bipush #45
    //   421: bastore
    //   422: dup
    //   423: bipush #18
    //   425: bipush #-110
    //   427: bastore
    //   428: dup
    //   429: bipush #19
    //   431: bipush #45
    //   433: bastore
    //   434: dup
    //   435: bipush #20
    //   437: bipush #-93
    //   439: bastore
    //   440: dup
    //   441: bipush #21
    //   443: bipush #22
    //   445: bastore
    //   446: dup
    //   447: bipush #22
    //   449: bipush #-109
    //   451: bastore
    //   452: dup
    //   453: bipush #23
    //   455: bipush #-47
    //   457: bastore
    //   458: dup
    //   459: bipush #24
    //   461: bipush #91
    //   463: bastore
    //   464: dup
    //   465: bipush #25
    //   467: bipush #-79
    //   469: bastore
    //   470: dup
    //   471: bipush #26
    //   473: bipush #-115
    //   475: bastore
    //   476: dup
    //   477: bipush #27
    //   479: bipush #-4
    //   481: bastore
    //   482: dup
    //   483: bipush #28
    //   485: bipush #118
    //   487: bastore
    //   488: dup
    //   489: bipush #29
    //   491: bipush #71
    //   493: bastore
    //   494: dup
    //   495: bipush #30
    //   497: bipush #28
    //   499: bastore
    //   500: dup
    //   501: bipush #31
    //   503: bipush #125
    //   505: bastore
    //   506: invokespecial <init> : ([B)V
    //   509: putstatic burp/Zmlu.Zi : Ljava/lang/Object;
    //   512: return
  }
  
  private static Throwable a(Throwable paramThrowable) {
    return paramThrowable;
  }
  
  private static String a(int paramInt1, int paramInt2) {
    int i = (paramInt1 ^ 0xFFFFF20D) & 0xFFFF;
    if (b[i] == null) {
      char[] arrayOfChar = a[i].toCharArray();
      switch (arrayOfChar[0] & 0xFF) {
        case 0:
        
        case 1:
        
        case 2:
        
        case 3:
        
        case 4:
        
        case 5:
        
        case 6:
        
        case 7:
        
        case 8:
        
        case 9:
        
        case 10:
        
        case 11:
        
        case 12:
        
        case 13:
        
        case 14:
        
        case 15:
        
        case 16:
        
        case 17:
        
        case 18:
        
        case 19:
        
        case 20:
        
        case 21:
        
        case 22:
        
        case 23:
        
        case 24:
        
        case 25:
        
        case 26:
        
        case 27:
        
        case 28:
        
        case 29:
        
        case 30:
        
        case 31:
        
        case 32:
        
        case 33:
        
        case 34:
        
        case 35:
        
        case 36:
        
        case 37:
        
        case 38:
        
        case 39:
        
        case 40:
        
        case 41:
        
        case 42:
        
        case 43:
        
        case 44:
        
        case 45:
        
        case 46:
        
        case 47:
        
        case 48:
        
        case 49:
        
        case 50:
        
        case 51:
        
        case 52:
        
        case 53:
        
        case 54:
        
        case 55:
        
        case 56:
        
        case 57:
        
        case 58:
        
        case 59:
        
        case 60:
        
        case 61:
        
        case 62:
        
        case 63:
        
        case 64:
        
        case 65:
        
        case 66:
        
        case 67:
        
        case 68:
        
        case 69:
        
        case 70:
        
        case 71:
        
        case 72:
        
        case 73:
        
        case 74:
        
        case 75:
        
        case 76:
        
        case 77:
        
        case 78:
        
        case 79:
        
        case 80:
        
        case 81:
        
        case 82:
        
        case 83:
        
        case 84:
        
        case 85:
        
        case 86:
        
        case 87:
        
        case 88:
        
        case 89:
        
        case 90:
        
        case 91:
        
        case 92:
        
        case 93:
        
        case 94:
        
        case 95:
        
        case 96:
        
        case 97:
        
        case 98:
        
        case 99:
        
        case 100:
        
        case 101:
        
        case 102:
        
        case 103:
        
        case 104:
        
        case 105:
        
        case 106:
        
        case 107:
        
        case 108:
        
        case 109:
        
        case 110:
        
        case 111:
        
        case 112:
        
        case 113:
        
        case 114:
        
        case 115:
        
        case 116:
        
        case 117:
        
        case 118:
        
        case 119:
        
        case 120:
        
        case 121:
        
        case 122:
        
        case 123:
        
        case 124:
        
        case 125:
        
        case 126:
        
        case 127:
        
        case 128:
        
        case 129:
        
        case 130:
        
        case 131:
        
        case 132:
        
        case 133:
        
        case 134:
        
        case 135:
        
        case 136:
        
        case 137:
        
        case 138:
        
        case 139:
        
        case 140:
        
        case 141:
        
        case 142:
        
        case 143:
        
        case 144:
        
        case 145:
        
        case 146:
        
        case 147:
        
        case 148:
        
        case 149:
        
        case 150:
        
        case 151:
        
        case 152:
        
        case 153:
        
        case 154:
        
        case 155:
        
        case 156:
        
        case 157:
        
        case 158:
        
        case 159:
        
        case 160:
        
        case 161:
        
        case 162:
        
        case 163:
        
        case 164:
        
        case 165:
        
        case 166:
        
        case 167:
        
        case 168:
        
        case 169:
        
        case 170:
        
        case 171:
        
        case 172:
        
        case 173:
        
        case 174:
        
        case 175:
        
        case 176:
        
        case 177:
        
        case 178:
        
        case 179:
        
        case 180:
        
        case 181:
        
        case 182:
        
        case 183:
        
        case 184:
        
        case 185:
        
        case 186:
        
        case 187:
        
        case 188:
        
        case 189:
        
        case 190:
        
        case 191:
        
        case 192:
        
        case 193:
        
        case 194:
        
        case 195:
        
        case 196:
        
        case 197:
        
        case 198:
        
        case 199:
        
        case 200:
        
        case 201:
        
        case 202:
        
        case 203:
        
        case 204:
        
        case 205:
        
        case 206:
        
        case 207:
        
        case 208:
        
        case 209:
        
        case 210:
        
        case 211:
        
        case 212:
        
        case 213:
        
        case 214:
        
        case 215:
        
        case 216:
        
        case 217:
        
        case 218:
        
        case 219:
        
        case 220:
        
        case 221:
        
        case 222:
        
        case 223:
        
        case 224:
        
        case 225:
        
        case 226:
        
        case 227:
        
        case 228:
        
        case 229:
        
        case 230:
        
        case 231:
        
        case 232:
        
        case 233:
        
        case 234:
        
        case 235:
        
        case 236:
        
        case 237:
        
        case 238:
        
        case 239:
        
        case 240:
        
        case 241:
        
        case 242:
        
        case 243:
        
        case 244:
        
        case 245:
        
        case 246:
        
        case 247:
        
        case 248:
        
        case 249:
        
        case 250:
        
        case 251:
        
        case 252:
        
        case 253:
        
        case 254:
        
        default:
          break;
      } 
      char c = '';
      int j = (paramInt2 & 0xFF) - c;
      if (j < 0)
        j += 256; 
      int k = ((paramInt2 & 0xFFFF) >>> 8) - c;
      if (k < 0)
        k += 256; 
      for (byte b = 0; b < arrayOfChar.length; b++) {
        int m = b % 2;
        if (m == 0) {
          arrayOfChar[b] = (char)(arrayOfChar[b] ^ j);
          j = ((j >>> 3 | j << 5) ^ arrayOfChar[b]) & 0xFF;
        } else {
          arrayOfChar[b] = (char)(arrayOfChar[b] ^ k);
          k = ((k >>> 3 | k << 5) ^ arrayOfChar[b]) & 0xFF;
        } 
      } 
      b[i] = (new String(arrayOfChar)).intern();
    } 
    return b[i];
  }
}


/* Location:              C:\Program Files\BurpSuitePro\burpsuite_pro.jar!\burp\Zmlu.class
 * Java compiler version: 21 (65.0)
 * JD-Core Version:       1.1.3
 */