package burp;

public class Zmq8 extends Zm23 {
  private static final Ze9n ZD;
  
  private static final String c;
  
  public void Zt(Object paramObject) {
    setIcon(ZD);
    setToolTipText(c);
  }
  
  static {
    // Byte code:
    //   0: bipush #25
    //   2: ldc 'T^gv^z~B5\\bkX(1Ozq@4?\\fSv\\r<d@yQ`H.pEy(\\r?uEaQ}B/c\\fvhX7'
    //   4: iconst_m1
    //   5: goto -> 14
    //   8: putstatic burp/Zmq8.c : Ljava/lang/String;
    //   11: goto -> 154
    //   14: dup_x2
    //   15: pop
    //   16: invokevirtual toCharArray : ()[C
    //   19: dup_x1
    //   20: arraylength
    //   21: dup_x2
    //   22: pop
    //   23: iconst_0
    //   24: istore_0
    //   25: dup2_x1
    //   26: pop2
    //   27: dup_x2
    //   28: iconst_1
    //   29: if_icmpgt -> 128
    //   32: dup2
    //   33: swap
    //   34: iload_0
    //   35: dup2_x1
    //   36: caload
    //   37: swap
    //   38: iload_0
    //   39: bipush #7
    //   41: irem
    //   42: tableswitch default -> 110, 0 -> 80, 1 -> 85, 2 -> 90, 3 -> 95, 4 -> 100, 5 -> 105
    //   80: bipush #8
    //   82: goto -> 112
    //   85: bipush #53
    //   87: goto -> 112
    //   90: bipush #12
    //   92: goto -> 112
    //   95: bipush #104
    //   97: goto -> 112
    //   100: bipush #29
    //   102: goto -> 112
    //   105: bipush #52
    //   107: goto -> 112
    //   110: bipush #67
    //   112: ixor
    //   113: ixor
    //   114: i2c
    //   115: castore
    //   116: iinc #0, 1
    //   119: dup
    //   120: ifne -> 128
    //   123: dup2
    //   124: dup_x1
    //   125: goto -> 35
    //   128: dup2_x1
    //   129: pop2
    //   130: dup_x2
    //   131: iload_0
    //   132: if_icmpgt -> 32
    //   135: pop
    //   136: new java/lang/String
    //   139: dup_x1
    //   140: swap
    //   141: invokespecial <init> : ([C)V
    //   144: invokevirtual intern : ()Ljava/lang/String;
    //   147: swap
    //   148: pop
    //   149: swap
    //   150: pop
    //   151: goto -> 8
    //   154: getstatic burp/Zeuf.TABLE_CELL_ERROR : Lburp/Zeuf;
    //   157: getstatic burp/Zlkk.TABLE_ERROR_ICON_COLOUR : Lburp/Zlkk;
    //   160: invokestatic ZC : (Lburp/Zeuf;Lburp/Zlkk;)Lburp/Ze3m;
    //   163: invokevirtual Z_ : ()Lburp/Ze9n;
    //   166: putstatic burp/Zmq8.ZD : Lburp/Ze9n;
    //   169: return
  }
}


/* Location:              C:\Program Files\BurpSuitePro\burpsuite_pro.jar!\burp\Zmq8.class
 * Java compiler version: 21 (65.0)
 * JD-Core Version:       1.1.3
 */