package burp;

import java.math.BigInteger;

class Zmrc extends ClassLoader {
  static String Zx;
  
  static Object ZU;
  
  private static final String[] a;
  
  private static final String[] b;
  
  static void ZL(Object[] paramArrayOfObject, Object paramObject) throws Throwable {}
  
  static void ZK(Object paramObject) {
    Zmlu.ZF = a(2007, 9241);
    Zmlu.Zi = new BigInteger(a(2004, -11821));
    boolean bool = Zt2e.ZN();
    try {
      try {
        if (Zxpb.ZQ.charAt(Math.abs(((BigInteger)Ztdx.ZX).intValue() % 32)) <= Zecw.Zb.charAt(Math.abs(((BigInteger)Zx8t.ZA).intValue() % 32))) {
          try {
            Zt7x.ZX(Class.forName(a(2015, -32009)));
            if (!bool)
              Zx_s.Zc(Class.forName(a(2012, -8238))); 
          } catch (Throwable throwable) {
            throw a(null);
          } 
          return;
        } 
      } catch (Throwable throwable) {
        throw a(null);
      } 
      Zx_s.Zc(Class.forName(a(2012, -8238)));
    } catch (Throwable throwable) {}
  }
  
  static boolean ZD(Object[] paramArrayOfObject, Object paramObject) throws Throwable {
    // Byte code:
    //   0: invokestatic ZK : ()Z
    //   3: istore_2
    //   4: getstatic burp/Zdk.Zy : Ljava/lang/Object;
    //   7: checkcast java/math/BigInteger
    //   10: invokevirtual toByteArray : ()[B
    //   13: astore_3
    //   14: bipush #32
    //   16: newarray int
    //   18: dup
    //   19: iconst_0
    //   20: ldc 876216579
    //   22: iastore
    //   23: dup
    //   24: iconst_1
    //   25: ldc 455999525
    //   27: iastore
    //   28: dup
    //   29: iconst_2
    //   30: ldc 1043334948
    //   32: iastore
    //   33: dup
    //   34: iconst_3
    //   35: ldc 439222784
    //   37: iastore
    //   38: dup
    //   39: iconst_4
    //   40: ldc 372376604
    //   42: iastore
    //   43: dup
    //   44: iconst_5
    //   45: ldc 707731490
    //   47: iastore
    //   48: dup
    //   49: bipush #6
    //   51: ldc 389426184
    //   53: iastore
    //   54: dup
    //   55: bipush #7
    //   57: ldc 973875457
    //   59: iastore
    //   60: dup
    //   61: bipush #8
    //   63: ldc 389160971
    //   65: iastore
    //   66: dup
    //   67: bipush #9
    //   69: ldc 907870729
    //   71: iastore
    //   72: dup
    //   73: bipush #10
    //   75: ldc 121057538
    //   77: iastore
    //   78: dup
    //   79: bipush #11
    //   81: ldc 840500228
    //   83: iastore
    //   84: dup
    //   85: bipush #12
    //   87: ldc 254150144
    //   89: iastore
    //   90: dup
    //   91: bipush #13
    //   93: ldc 924386310
    //   95: iastore
    //   96: dup
    //   97: bipush #14
    //   99: ldc 187632156
    //   101: iastore
    //   102: dup
    //   103: bipush #15
    //   105: ldc 874189824
    //   107: iastore
    //   108: dup
    //   109: bipush #16
    //   111: ldc 655302664
    //   113: iastore
    //   114: dup
    //   115: bipush #17
    //   117: ldc 890966315
    //   119: iastore
    //   120: dup
    //   121: bipush #18
    //   123: ldc 722417666
    //   125: iastore
    //   126: dup
    //   127: bipush #19
    //   129: ldc 1026621720
    //   131: iastore
    //   132: dup
    //   133: bipush #20
    //   135: ldc 957157408
    //   137: iastore
    //   138: dup
    //   139: bipush #21
    //   141: ldc 892536332
    //   143: iastore
    //   144: dup
    //   145: bipush #22
    //   147: ldc 689771012
    //   149: iastore
    //   150: dup
    //   151: bipush #23
    //   153: ldc 221709344
    //   155: iastore
    //   156: dup
    //   157: bipush #24
    //   159: ldc 940377620
    //   161: iastore
    //   162: dup
    //   163: bipush #25
    //   165: ldc 255209728
    //   167: iastore
    //   168: dup
    //   169: bipush #26
    //   171: ldc 1010368540
    //   173: iastore
    //   174: dup
    //   175: bipush #27
    //   177: ldc 220604441
    //   179: iastore
    //   180: dup
    //   181: bipush #28
    //   183: ldc 1008414755
    //   185: iastore
    //   186: dup
    //   187: bipush #29
    //   189: ldc 187049985
    //   191: iastore
    //   192: dup
    //   193: bipush #30
    //   195: ldc 943331329
    //   197: iastore
    //   198: dup
    //   199: bipush #31
    //   201: ldc 170788368
    //   203: iastore
    //   204: astore #5
    //   206: bipush #64
    //   208: newarray int
    //   210: dup
    //   211: iconst_0
    //   212: ldc 16843776
    //   214: iastore
    //   215: dup
    //   216: iconst_1
    //   217: iconst_0
    //   218: iastore
    //   219: dup
    //   220: iconst_2
    //   221: ldc 65536
    //   223: iastore
    //   224: dup
    //   225: iconst_3
    //   226: ldc 16843780
    //   228: iastore
    //   229: dup
    //   230: iconst_4
    //   231: ldc 16842756
    //   233: iastore
    //   234: dup
    //   235: iconst_5
    //   236: ldc 66564
    //   238: iastore
    //   239: dup
    //   240: bipush #6
    //   242: iconst_4
    //   243: iastore
    //   244: dup
    //   245: bipush #7
    //   247: ldc 65536
    //   249: iastore
    //   250: dup
    //   251: bipush #8
    //   253: sipush #1024
    //   256: iastore
    //   257: dup
    //   258: bipush #9
    //   260: ldc 16843776
    //   262: iastore
    //   263: dup
    //   264: bipush #10
    //   266: ldc 16843780
    //   268: iastore
    //   269: dup
    //   270: bipush #11
    //   272: sipush #1024
    //   275: iastore
    //   276: dup
    //   277: bipush #12
    //   279: ldc 16778244
    //   281: iastore
    //   282: dup
    //   283: bipush #13
    //   285: ldc 16842756
    //   287: iastore
    //   288: dup
    //   289: bipush #14
    //   291: ldc 16777216
    //   293: iastore
    //   294: dup
    //   295: bipush #15
    //   297: iconst_4
    //   298: iastore
    //   299: dup
    //   300: bipush #16
    //   302: sipush #1028
    //   305: iastore
    //   306: dup
    //   307: bipush #17
    //   309: ldc 16778240
    //   311: iastore
    //   312: dup
    //   313: bipush #18
    //   315: ldc 16778240
    //   317: iastore
    //   318: dup
    //   319: bipush #19
    //   321: ldc 66560
    //   323: iastore
    //   324: dup
    //   325: bipush #20
    //   327: ldc 66560
    //   329: iastore
    //   330: dup
    //   331: bipush #21
    //   333: ldc 16842752
    //   335: iastore
    //   336: dup
    //   337: bipush #22
    //   339: ldc 16842752
    //   341: iastore
    //   342: dup
    //   343: bipush #23
    //   345: ldc 16778244
    //   347: iastore
    //   348: dup
    //   349: bipush #24
    //   351: ldc 65540
    //   353: iastore
    //   354: dup
    //   355: bipush #25
    //   357: ldc 16777220
    //   359: iastore
    //   360: dup
    //   361: bipush #26
    //   363: ldc 16777220
    //   365: iastore
    //   366: dup
    //   367: bipush #27
    //   369: ldc 65540
    //   371: iastore
    //   372: dup
    //   373: bipush #28
    //   375: iconst_0
    //   376: iastore
    //   377: dup
    //   378: bipush #29
    //   380: sipush #1028
    //   383: iastore
    //   384: dup
    //   385: bipush #30
    //   387: ldc 66564
    //   389: iastore
    //   390: dup
    //   391: bipush #31
    //   393: ldc 16777216
    //   395: iastore
    //   396: dup
    //   397: bipush #32
    //   399: ldc 65536
    //   401: iastore
    //   402: dup
    //   403: bipush #33
    //   405: ldc 16843780
    //   407: iastore
    //   408: dup
    //   409: bipush #34
    //   411: iconst_4
    //   412: iastore
    //   413: dup
    //   414: bipush #35
    //   416: ldc 16842752
    //   418: iastore
    //   419: dup
    //   420: bipush #36
    //   422: ldc 16843776
    //   424: iastore
    //   425: dup
    //   426: bipush #37
    //   428: ldc 16777216
    //   430: iastore
    //   431: dup
    //   432: bipush #38
    //   434: ldc 16777216
    //   436: iastore
    //   437: dup
    //   438: bipush #39
    //   440: sipush #1024
    //   443: iastore
    //   444: dup
    //   445: bipush #40
    //   447: ldc 16842756
    //   449: iastore
    //   450: dup
    //   451: bipush #41
    //   453: ldc 65536
    //   455: iastore
    //   456: dup
    //   457: bipush #42
    //   459: ldc 66560
    //   461: iastore
    //   462: dup
    //   463: bipush #43
    //   465: ldc 16777220
    //   467: iastore
    //   468: dup
    //   469: bipush #44
    //   471: sipush #1024
    //   474: iastore
    //   475: dup
    //   476: bipush #45
    //   478: iconst_4
    //   479: iastore
    //   480: dup
    //   481: bipush #46
    //   483: ldc 16778244
    //   485: iastore
    //   486: dup
    //   487: bipush #47
    //   489: ldc 66564
    //   491: iastore
    //   492: dup
    //   493: bipush #48
    //   495: ldc 16843780
    //   497: iastore
    //   498: dup
    //   499: bipush #49
    //   501: ldc 65540
    //   503: iastore
    //   504: dup
    //   505: bipush #50
    //   507: ldc 16842752
    //   509: iastore
    //   510: dup
    //   511: bipush #51
    //   513: ldc 16778244
    //   515: iastore
    //   516: dup
    //   517: bipush #52
    //   519: ldc 16777220
    //   521: iastore
    //   522: dup
    //   523: bipush #53
    //   525: sipush #1028
    //   528: iastore
    //   529: dup
    //   530: bipush #54
    //   532: ldc 66564
    //   534: iastore
    //   535: dup
    //   536: bipush #55
    //   538: ldc 16843776
    //   540: iastore
    //   541: dup
    //   542: bipush #56
    //   544: sipush #1028
    //   547: iastore
    //   548: dup
    //   549: bipush #57
    //   551: ldc 16778240
    //   553: iastore
    //   554: dup
    //   555: bipush #58
    //   557: ldc 16778240
    //   559: iastore
    //   560: dup
    //   561: bipush #59
    //   563: iconst_0
    //   564: iastore
    //   565: dup
    //   566: bipush #60
    //   568: ldc 65540
    //   570: iastore
    //   571: dup
    //   572: bipush #61
    //   574: ldc 66560
    //   576: iastore
    //   577: dup
    //   578: bipush #62
    //   580: iconst_0
    //   581: iastore
    //   582: dup
    //   583: bipush #63
    //   585: ldc 16842756
    //   587: iastore
    //   588: astore #6
    //   590: bipush #64
    //   592: newarray int
    //   594: dup
    //   595: iconst_0
    //   596: ldc -2146402272
    //   598: iastore
    //   599: dup
    //   600: iconst_1
    //   601: ldc -2147450880
    //   603: iastore
    //   604: dup
    //   605: iconst_2
    //   606: ldc 32768
    //   608: iastore
    //   609: dup
    //   610: iconst_3
    //   611: ldc 1081376
    //   613: iastore
    //   614: dup
    //   615: iconst_4
    //   616: ldc 1048576
    //   618: iastore
    //   619: dup
    //   620: iconst_5
    //   621: bipush #32
    //   623: iastore
    //   624: dup
    //   625: bipush #6
    //   627: ldc -2146435040
    //   629: iastore
    //   630: dup
    //   631: bipush #7
    //   633: ldc -2147450848
    //   635: iastore
    //   636: dup
    //   637: bipush #8
    //   639: ldc -2147483616
    //   641: iastore
    //   642: dup
    //   643: bipush #9
    //   645: ldc -2146402272
    //   647: iastore
    //   648: dup
    //   649: bipush #10
    //   651: ldc -2146402304
    //   653: iastore
    //   654: dup
    //   655: bipush #11
    //   657: ldc -2147483648
    //   659: iastore
    //   660: dup
    //   661: bipush #12
    //   663: ldc -2147450880
    //   665: iastore
    //   666: dup
    //   667: bipush #13
    //   669: ldc 1048576
    //   671: iastore
    //   672: dup
    //   673: bipush #14
    //   675: bipush #32
    //   677: iastore
    //   678: dup
    //   679: bipush #15
    //   681: ldc -2146435040
    //   683: iastore
    //   684: dup
    //   685: bipush #16
    //   687: ldc 1081344
    //   689: iastore
    //   690: dup
    //   691: bipush #17
    //   693: ldc 1048608
    //   695: iastore
    //   696: dup
    //   697: bipush #18
    //   699: ldc -2147450848
    //   701: iastore
    //   702: dup
    //   703: bipush #19
    //   705: iconst_0
    //   706: iastore
    //   707: dup
    //   708: bipush #20
    //   710: ldc -2147483648
    //   712: iastore
    //   713: dup
    //   714: bipush #21
    //   716: ldc 32768
    //   718: iastore
    //   719: dup
    //   720: bipush #22
    //   722: ldc 1081376
    //   724: iastore
    //   725: dup
    //   726: bipush #23
    //   728: ldc -2146435072
    //   730: iastore
    //   731: dup
    //   732: bipush #24
    //   734: ldc 1048608
    //   736: iastore
    //   737: dup
    //   738: bipush #25
    //   740: ldc -2147483616
    //   742: iastore
    //   743: dup
    //   744: bipush #26
    //   746: iconst_0
    //   747: iastore
    //   748: dup
    //   749: bipush #27
    //   751: ldc 1081344
    //   753: iastore
    //   754: dup
    //   755: bipush #28
    //   757: ldc 32800
    //   759: iastore
    //   760: dup
    //   761: bipush #29
    //   763: ldc -2146402304
    //   765: iastore
    //   766: dup
    //   767: bipush #30
    //   769: ldc -2146435072
    //   771: iastore
    //   772: dup
    //   773: bipush #31
    //   775: ldc 32800
    //   777: iastore
    //   778: dup
    //   779: bipush #32
    //   781: iconst_0
    //   782: iastore
    //   783: dup
    //   784: bipush #33
    //   786: ldc 1081376
    //   788: iastore
    //   789: dup
    //   790: bipush #34
    //   792: ldc -2146435040
    //   794: iastore
    //   795: dup
    //   796: bipush #35
    //   798: ldc 1048576
    //   800: iastore
    //   801: dup
    //   802: bipush #36
    //   804: ldc -2147450848
    //   806: iastore
    //   807: dup
    //   808: bipush #37
    //   810: ldc -2146435072
    //   812: iastore
    //   813: dup
    //   814: bipush #38
    //   816: ldc -2146402304
    //   818: iastore
    //   819: dup
    //   820: bipush #39
    //   822: ldc 32768
    //   824: iastore
    //   825: dup
    //   826: bipush #40
    //   828: ldc -2146435072
    //   830: iastore
    //   831: dup
    //   832: bipush #41
    //   834: ldc -2147450880
    //   836: iastore
    //   837: dup
    //   838: bipush #42
    //   840: bipush #32
    //   842: iastore
    //   843: dup
    //   844: bipush #43
    //   846: ldc -2146402272
    //   848: iastore
    //   849: dup
    //   850: bipush #44
    //   852: ldc 1081376
    //   854: iastore
    //   855: dup
    //   856: bipush #45
    //   858: bipush #32
    //   860: iastore
    //   861: dup
    //   862: bipush #46
    //   864: ldc 32768
    //   866: iastore
    //   867: dup
    //   868: bipush #47
    //   870: ldc -2147483648
    //   872: iastore
    //   873: dup
    //   874: bipush #48
    //   876: ldc 32800
    //   878: iastore
    //   879: dup
    //   880: bipush #49
    //   882: ldc -2146402304
    //   884: iastore
    //   885: dup
    //   886: bipush #50
    //   888: ldc 1048576
    //   890: iastore
    //   891: dup
    //   892: bipush #51
    //   894: ldc -2147483616
    //   896: iastore
    //   897: dup
    //   898: bipush #52
    //   900: ldc 1048608
    //   902: iastore
    //   903: dup
    //   904: bipush #53
    //   906: ldc -2147450848
    //   908: iastore
    //   909: dup
    //   910: bipush #54
    //   912: ldc -2147483616
    //   914: iastore
    //   915: dup
    //   916: bipush #55
    //   918: ldc 1048608
    //   920: iastore
    //   921: dup
    //   922: bipush #56
    //   924: ldc 1081344
    //   926: iastore
    //   927: dup
    //   928: bipush #57
    //   930: iconst_0
    //   931: iastore
    //   932: dup
    //   933: bipush #58
    //   935: ldc -2147450880
    //   937: iastore
    //   938: dup
    //   939: bipush #59
    //   941: ldc 32800
    //   943: iastore
    //   944: dup
    //   945: bipush #60
    //   947: ldc -2147483648
    //   949: iastore
    //   950: dup
    //   951: bipush #61
    //   953: ldc -2146435040
    //   955: iastore
    //   956: dup
    //   957: bipush #62
    //   959: ldc -2146402272
    //   961: iastore
    //   962: dup
    //   963: bipush #63
    //   965: ldc 1081344
    //   967: iastore
    //   968: astore #7
    //   970: bipush #64
    //   972: newarray int
    //   974: dup
    //   975: iconst_0
    //   976: sipush #520
    //   979: iastore
    //   980: dup
    //   981: iconst_1
    //   982: ldc 134349312
    //   984: iastore
    //   985: dup
    //   986: iconst_2
    //   987: iconst_0
    //   988: iastore
    //   989: dup
    //   990: iconst_3
    //   991: ldc 134348808
    //   993: iastore
    //   994: dup
    //   995: iconst_4
    //   996: ldc 134218240
    //   998: iastore
    //   999: dup
    //   1000: iconst_5
    //   1001: iconst_0
    //   1002: iastore
    //   1003: dup
    //   1004: bipush #6
    //   1006: ldc 131592
    //   1008: iastore
    //   1009: dup
    //   1010: bipush #7
    //   1012: ldc 134218240
    //   1014: iastore
    //   1015: dup
    //   1016: bipush #8
    //   1018: ldc 131080
    //   1020: iastore
    //   1021: dup
    //   1022: bipush #9
    //   1024: ldc 134217736
    //   1026: iastore
    //   1027: dup
    //   1028: bipush #10
    //   1030: ldc 134217736
    //   1032: iastore
    //   1033: dup
    //   1034: bipush #11
    //   1036: ldc 131072
    //   1038: iastore
    //   1039: dup
    //   1040: bipush #12
    //   1042: ldc 134349320
    //   1044: iastore
    //   1045: dup
    //   1046: bipush #13
    //   1048: ldc 131080
    //   1050: iastore
    //   1051: dup
    //   1052: bipush #14
    //   1054: ldc 134348800
    //   1056: iastore
    //   1057: dup
    //   1058: bipush #15
    //   1060: sipush #520
    //   1063: iastore
    //   1064: dup
    //   1065: bipush #16
    //   1067: ldc 134217728
    //   1069: iastore
    //   1070: dup
    //   1071: bipush #17
    //   1073: bipush #8
    //   1075: iastore
    //   1076: dup
    //   1077: bipush #18
    //   1079: ldc 134349312
    //   1081: iastore
    //   1082: dup
    //   1083: bipush #19
    //   1085: sipush #512
    //   1088: iastore
    //   1089: dup
    //   1090: bipush #20
    //   1092: ldc 131584
    //   1094: iastore
    //   1095: dup
    //   1096: bipush #21
    //   1098: ldc 134348800
    //   1100: iastore
    //   1101: dup
    //   1102: bipush #22
    //   1104: ldc 134348808
    //   1106: iastore
    //   1107: dup
    //   1108: bipush #23
    //   1110: ldc 131592
    //   1112: iastore
    //   1113: dup
    //   1114: bipush #24
    //   1116: ldc 134218248
    //   1118: iastore
    //   1119: dup
    //   1120: bipush #25
    //   1122: ldc 131584
    //   1124: iastore
    //   1125: dup
    //   1126: bipush #26
    //   1128: ldc 131072
    //   1130: iastore
    //   1131: dup
    //   1132: bipush #27
    //   1134: ldc 134218248
    //   1136: iastore
    //   1137: dup
    //   1138: bipush #28
    //   1140: bipush #8
    //   1142: iastore
    //   1143: dup
    //   1144: bipush #29
    //   1146: ldc 134349320
    //   1148: iastore
    //   1149: dup
    //   1150: bipush #30
    //   1152: sipush #512
    //   1155: iastore
    //   1156: dup
    //   1157: bipush #31
    //   1159: ldc 134217728
    //   1161: iastore
    //   1162: dup
    //   1163: bipush #32
    //   1165: ldc 134349312
    //   1167: iastore
    //   1168: dup
    //   1169: bipush #33
    //   1171: ldc 134217728
    //   1173: iastore
    //   1174: dup
    //   1175: bipush #34
    //   1177: ldc 131080
    //   1179: iastore
    //   1180: dup
    //   1181: bipush #35
    //   1183: sipush #520
    //   1186: iastore
    //   1187: dup
    //   1188: bipush #36
    //   1190: ldc 131072
    //   1192: iastore
    //   1193: dup
    //   1194: bipush #37
    //   1196: ldc 134349312
    //   1198: iastore
    //   1199: dup
    //   1200: bipush #38
    //   1202: ldc 134218240
    //   1204: iastore
    //   1205: dup
    //   1206: bipush #39
    //   1208: iconst_0
    //   1209: iastore
    //   1210: dup
    //   1211: bipush #40
    //   1213: sipush #512
    //   1216: iastore
    //   1217: dup
    //   1218: bipush #41
    //   1220: ldc 131080
    //   1222: iastore
    //   1223: dup
    //   1224: bipush #42
    //   1226: ldc 134349320
    //   1228: iastore
    //   1229: dup
    //   1230: bipush #43
    //   1232: ldc 134218240
    //   1234: iastore
    //   1235: dup
    //   1236: bipush #44
    //   1238: ldc 134217736
    //   1240: iastore
    //   1241: dup
    //   1242: bipush #45
    //   1244: sipush #512
    //   1247: iastore
    //   1248: dup
    //   1249: bipush #46
    //   1251: iconst_0
    //   1252: iastore
    //   1253: dup
    //   1254: bipush #47
    //   1256: ldc 134348808
    //   1258: iastore
    //   1259: dup
    //   1260: bipush #48
    //   1262: ldc 134218248
    //   1264: iastore
    //   1265: dup
    //   1266: bipush #49
    //   1268: ldc 131072
    //   1270: iastore
    //   1271: dup
    //   1272: bipush #50
    //   1274: ldc 134217728
    //   1276: iastore
    //   1277: dup
    //   1278: bipush #51
    //   1280: ldc 134349320
    //   1282: iastore
    //   1283: dup
    //   1284: bipush #52
    //   1286: bipush #8
    //   1288: iastore
    //   1289: dup
    //   1290: bipush #53
    //   1292: ldc 131592
    //   1294: iastore
    //   1295: dup
    //   1296: bipush #54
    //   1298: ldc 131584
    //   1300: iastore
    //   1301: dup
    //   1302: bipush #55
    //   1304: ldc 134217736
    //   1306: iastore
    //   1307: dup
    //   1308: bipush #56
    //   1310: ldc 134348800
    //   1312: iastore
    //   1313: dup
    //   1314: bipush #57
    //   1316: ldc 134218248
    //   1318: iastore
    //   1319: dup
    //   1320: bipush #58
    //   1322: sipush #520
    //   1325: iastore
    //   1326: dup
    //   1327: bipush #59
    //   1329: ldc 134348800
    //   1331: iastore
    //   1332: dup
    //   1333: bipush #60
    //   1335: ldc 131592
    //   1337: iastore
    //   1338: dup
    //   1339: bipush #61
    //   1341: bipush #8
    //   1343: iastore
    //   1344: dup
    //   1345: bipush #62
    //   1347: ldc 134348808
    //   1349: iastore
    //   1350: dup
    //   1351: bipush #63
    //   1353: ldc 131584
    //   1355: iastore
    //   1356: astore #8
    //   1358: bipush #64
    //   1360: newarray int
    //   1362: dup
    //   1363: iconst_0
    //   1364: ldc 8396801
    //   1366: iastore
    //   1367: dup
    //   1368: iconst_1
    //   1369: sipush #8321
    //   1372: iastore
    //   1373: dup
    //   1374: iconst_2
    //   1375: sipush #8321
    //   1378: iastore
    //   1379: dup
    //   1380: iconst_3
    //   1381: sipush #128
    //   1384: iastore
    //   1385: dup
    //   1386: iconst_4
    //   1387: ldc 8396928
    //   1389: iastore
    //   1390: dup
    //   1391: iconst_5
    //   1392: ldc 8388737
    //   1394: iastore
    //   1395: dup
    //   1396: bipush #6
    //   1398: ldc 8388609
    //   1400: iastore
    //   1401: dup
    //   1402: bipush #7
    //   1404: sipush #8193
    //   1407: iastore
    //   1408: dup
    //   1409: bipush #8
    //   1411: iconst_0
    //   1412: iastore
    //   1413: dup
    //   1414: bipush #9
    //   1416: ldc 8396800
    //   1418: iastore
    //   1419: dup
    //   1420: bipush #10
    //   1422: ldc 8396800
    //   1424: iastore
    //   1425: dup
    //   1426: bipush #11
    //   1428: ldc 8396929
    //   1430: iastore
    //   1431: dup
    //   1432: bipush #12
    //   1434: sipush #129
    //   1437: iastore
    //   1438: dup
    //   1439: bipush #13
    //   1441: iconst_0
    //   1442: iastore
    //   1443: dup
    //   1444: bipush #14
    //   1446: ldc 8388736
    //   1448: iastore
    //   1449: dup
    //   1450: bipush #15
    //   1452: ldc 8388609
    //   1454: iastore
    //   1455: dup
    //   1456: bipush #16
    //   1458: iconst_1
    //   1459: iastore
    //   1460: dup
    //   1461: bipush #17
    //   1463: sipush #8192
    //   1466: iastore
    //   1467: dup
    //   1468: bipush #18
    //   1470: ldc 8388608
    //   1472: iastore
    //   1473: dup
    //   1474: bipush #19
    //   1476: ldc 8396801
    //   1478: iastore
    //   1479: dup
    //   1480: bipush #20
    //   1482: sipush #128
    //   1485: iastore
    //   1486: dup
    //   1487: bipush #21
    //   1489: ldc 8388608
    //   1491: iastore
    //   1492: dup
    //   1493: bipush #22
    //   1495: sipush #8193
    //   1498: iastore
    //   1499: dup
    //   1500: bipush #23
    //   1502: sipush #8320
    //   1505: iastore
    //   1506: dup
    //   1507: bipush #24
    //   1509: ldc 8388737
    //   1511: iastore
    //   1512: dup
    //   1513: bipush #25
    //   1515: iconst_1
    //   1516: iastore
    //   1517: dup
    //   1518: bipush #26
    //   1520: sipush #8320
    //   1523: iastore
    //   1524: dup
    //   1525: bipush #27
    //   1527: ldc 8388736
    //   1529: iastore
    //   1530: dup
    //   1531: bipush #28
    //   1533: sipush #8192
    //   1536: iastore
    //   1537: dup
    //   1538: bipush #29
    //   1540: ldc 8396928
    //   1542: iastore
    //   1543: dup
    //   1544: bipush #30
    //   1546: ldc 8396929
    //   1548: iastore
    //   1549: dup
    //   1550: bipush #31
    //   1552: sipush #129
    //   1555: iastore
    //   1556: dup
    //   1557: bipush #32
    //   1559: ldc 8388736
    //   1561: iastore
    //   1562: dup
    //   1563: bipush #33
    //   1565: ldc 8388609
    //   1567: iastore
    //   1568: dup
    //   1569: bipush #34
    //   1571: ldc 8396800
    //   1573: iastore
    //   1574: dup
    //   1575: bipush #35
    //   1577: ldc 8396929
    //   1579: iastore
    //   1580: dup
    //   1581: bipush #36
    //   1583: sipush #129
    //   1586: iastore
    //   1587: dup
    //   1588: bipush #37
    //   1590: iconst_0
    //   1591: iastore
    //   1592: dup
    //   1593: bipush #38
    //   1595: iconst_0
    //   1596: iastore
    //   1597: dup
    //   1598: bipush #39
    //   1600: ldc 8396800
    //   1602: iastore
    //   1603: dup
    //   1604: bipush #40
    //   1606: sipush #8320
    //   1609: iastore
    //   1610: dup
    //   1611: bipush #41
    //   1613: ldc 8388736
    //   1615: iastore
    //   1616: dup
    //   1617: bipush #42
    //   1619: ldc 8388737
    //   1621: iastore
    //   1622: dup
    //   1623: bipush #43
    //   1625: iconst_1
    //   1626: iastore
    //   1627: dup
    //   1628: bipush #44
    //   1630: ldc 8396801
    //   1632: iastore
    //   1633: dup
    //   1634: bipush #45
    //   1636: sipush #8321
    //   1639: iastore
    //   1640: dup
    //   1641: bipush #46
    //   1643: sipush #8321
    //   1646: iastore
    //   1647: dup
    //   1648: bipush #47
    //   1650: sipush #128
    //   1653: iastore
    //   1654: dup
    //   1655: bipush #48
    //   1657: ldc 8396929
    //   1659: iastore
    //   1660: dup
    //   1661: bipush #49
    //   1663: sipush #129
    //   1666: iastore
    //   1667: dup
    //   1668: bipush #50
    //   1670: iconst_1
    //   1671: iastore
    //   1672: dup
    //   1673: bipush #51
    //   1675: sipush #8192
    //   1678: iastore
    //   1679: dup
    //   1680: bipush #52
    //   1682: ldc 8388609
    //   1684: iastore
    //   1685: dup
    //   1686: bipush #53
    //   1688: sipush #8193
    //   1691: iastore
    //   1692: dup
    //   1693: bipush #54
    //   1695: ldc 8396928
    //   1697: iastore
    //   1698: dup
    //   1699: bipush #55
    //   1701: ldc 8388737
    //   1703: iastore
    //   1704: dup
    //   1705: bipush #56
    //   1707: sipush #8193
    //   1710: iastore
    //   1711: dup
    //   1712: bipush #57
    //   1714: sipush #8320
    //   1717: iastore
    //   1718: dup
    //   1719: bipush #58
    //   1721: ldc 8388608
    //   1723: iastore
    //   1724: dup
    //   1725: bipush #59
    //   1727: ldc 8396801
    //   1729: iastore
    //   1730: dup
    //   1731: bipush #60
    //   1733: sipush #128
    //   1736: iastore
    //   1737: dup
    //   1738: bipush #61
    //   1740: ldc 8388608
    //   1742: iastore
    //   1743: dup
    //   1744: bipush #62
    //   1746: sipush #8192
    //   1749: iastore
    //   1750: dup
    //   1751: bipush #63
    //   1753: ldc 8396928
    //   1755: iastore
    //   1756: astore #9
    //   1758: bipush #64
    //   1760: newarray int
    //   1762: dup
    //   1763: iconst_0
    //   1764: sipush #256
    //   1767: iastore
    //   1768: dup
    //   1769: iconst_1
    //   1770: ldc 34078976
    //   1772: iastore
    //   1773: dup
    //   1774: iconst_2
    //   1775: ldc 34078720
    //   1777: iastore
    //   1778: dup
    //   1779: iconst_3
    //   1780: ldc 1107296512
    //   1782: iastore
    //   1783: dup
    //   1784: iconst_4
    //   1785: ldc 524288
    //   1787: iastore
    //   1788: dup
    //   1789: iconst_5
    //   1790: sipush #256
    //   1793: iastore
    //   1794: dup
    //   1795: bipush #6
    //   1797: ldc 1073741824
    //   1799: iastore
    //   1800: dup
    //   1801: bipush #7
    //   1803: ldc 34078720
    //   1805: iastore
    //   1806: dup
    //   1807: bipush #8
    //   1809: ldc 1074266368
    //   1811: iastore
    //   1812: dup
    //   1813: bipush #9
    //   1815: ldc 524288
    //   1817: iastore
    //   1818: dup
    //   1819: bipush #10
    //   1821: ldc 33554688
    //   1823: iastore
    //   1824: dup
    //   1825: bipush #11
    //   1827: ldc 1074266368
    //   1829: iastore
    //   1830: dup
    //   1831: bipush #12
    //   1833: ldc 1107296512
    //   1835: iastore
    //   1836: dup
    //   1837: bipush #13
    //   1839: ldc 1107820544
    //   1841: iastore
    //   1842: dup
    //   1843: bipush #14
    //   1845: ldc 524544
    //   1847: iastore
    //   1848: dup
    //   1849: bipush #15
    //   1851: ldc 1073741824
    //   1853: iastore
    //   1854: dup
    //   1855: bipush #16
    //   1857: ldc 33554432
    //   1859: iastore
    //   1860: dup
    //   1861: bipush #17
    //   1863: ldc 1074266112
    //   1865: iastore
    //   1866: dup
    //   1867: bipush #18
    //   1869: ldc 1074266112
    //   1871: iastore
    //   1872: dup
    //   1873: bipush #19
    //   1875: iconst_0
    //   1876: iastore
    //   1877: dup
    //   1878: bipush #20
    //   1880: ldc 1073742080
    //   1882: iastore
    //   1883: dup
    //   1884: bipush #21
    //   1886: ldc 1107820800
    //   1888: iastore
    //   1889: dup
    //   1890: bipush #22
    //   1892: ldc 1107820800
    //   1894: iastore
    //   1895: dup
    //   1896: bipush #23
    //   1898: ldc 33554688
    //   1900: iastore
    //   1901: dup
    //   1902: bipush #24
    //   1904: ldc 1107820544
    //   1906: iastore
    //   1907: dup
    //   1908: bipush #25
    //   1910: ldc 1073742080
    //   1912: iastore
    //   1913: dup
    //   1914: bipush #26
    //   1916: iconst_0
    //   1917: iastore
    //   1918: dup
    //   1919: bipush #27
    //   1921: ldc 1107296256
    //   1923: iastore
    //   1924: dup
    //   1925: bipush #28
    //   1927: ldc 34078976
    //   1929: iastore
    //   1930: dup
    //   1931: bipush #29
    //   1933: ldc 33554432
    //   1935: iastore
    //   1936: dup
    //   1937: bipush #30
    //   1939: ldc 1107296256
    //   1941: iastore
    //   1942: dup
    //   1943: bipush #31
    //   1945: ldc 524544
    //   1947: iastore
    //   1948: dup
    //   1949: bipush #32
    //   1951: ldc 524288
    //   1953: iastore
    //   1954: dup
    //   1955: bipush #33
    //   1957: ldc 1107296512
    //   1959: iastore
    //   1960: dup
    //   1961: bipush #34
    //   1963: sipush #256
    //   1966: iastore
    //   1967: dup
    //   1968: bipush #35
    //   1970: ldc 33554432
    //   1972: iastore
    //   1973: dup
    //   1974: bipush #36
    //   1976: ldc 1073741824
    //   1978: iastore
    //   1979: dup
    //   1980: bipush #37
    //   1982: ldc 34078720
    //   1984: iastore
    //   1985: dup
    //   1986: bipush #38
    //   1988: ldc 1107296512
    //   1990: iastore
    //   1991: dup
    //   1992: bipush #39
    //   1994: ldc 1074266368
    //   1996: iastore
    //   1997: dup
    //   1998: bipush #40
    //   2000: ldc 33554688
    //   2002: iastore
    //   2003: dup
    //   2004: bipush #41
    //   2006: ldc 1073741824
    //   2008: iastore
    //   2009: dup
    //   2010: bipush #42
    //   2012: ldc 1107820544
    //   2014: iastore
    //   2015: dup
    //   2016: bipush #43
    //   2018: ldc 34078976
    //   2020: iastore
    //   2021: dup
    //   2022: bipush #44
    //   2024: ldc 1074266368
    //   2026: iastore
    //   2027: dup
    //   2028: bipush #45
    //   2030: sipush #256
    //   2033: iastore
    //   2034: dup
    //   2035: bipush #46
    //   2037: ldc 33554432
    //   2039: iastore
    //   2040: dup
    //   2041: bipush #47
    //   2043: ldc 1107820544
    //   2045: iastore
    //   2046: dup
    //   2047: bipush #48
    //   2049: ldc 1107820800
    //   2051: iastore
    //   2052: dup
    //   2053: bipush #49
    //   2055: ldc 524544
    //   2057: iastore
    //   2058: dup
    //   2059: bipush #50
    //   2061: ldc 1107296256
    //   2063: iastore
    //   2064: dup
    //   2065: bipush #51
    //   2067: ldc 1107820800
    //   2069: iastore
    //   2070: dup
    //   2071: bipush #52
    //   2073: ldc 34078720
    //   2075: iastore
    //   2076: dup
    //   2077: bipush #53
    //   2079: iconst_0
    //   2080: iastore
    //   2081: dup
    //   2082: bipush #54
    //   2084: ldc 1074266112
    //   2086: iastore
    //   2087: dup
    //   2088: bipush #55
    //   2090: ldc 1107296256
    //   2092: iastore
    //   2093: dup
    //   2094: bipush #56
    //   2096: ldc 524544
    //   2098: iastore
    //   2099: dup
    //   2100: bipush #57
    //   2102: ldc 33554688
    //   2104: iastore
    //   2105: dup
    //   2106: bipush #58
    //   2108: ldc 1073742080
    //   2110: iastore
    //   2111: dup
    //   2112: bipush #59
    //   2114: ldc 524288
    //   2116: iastore
    //   2117: dup
    //   2118: bipush #60
    //   2120: iconst_0
    //   2121: iastore
    //   2122: dup
    //   2123: bipush #61
    //   2125: ldc 1074266112
    //   2127: iastore
    //   2128: dup
    //   2129: bipush #62
    //   2131: ldc 34078976
    //   2133: iastore
    //   2134: dup
    //   2135: bipush #63
    //   2137: ldc 1073742080
    //   2139: iastore
    //   2140: astore #10
    //   2142: bipush #64
    //   2144: newarray int
    //   2146: dup
    //   2147: iconst_0
    //   2148: ldc 536870928
    //   2150: iastore
    //   2151: dup
    //   2152: iconst_1
    //   2153: ldc 541065216
    //   2155: iastore
    //   2156: dup
    //   2157: iconst_2
    //   2158: sipush #16384
    //   2161: iastore
    //   2162: dup
    //   2163: iconst_3
    //   2164: ldc 541081616
    //   2166: iastore
    //   2167: dup
    //   2168: iconst_4
    //   2169: ldc 541065216
    //   2171: iastore
    //   2172: dup
    //   2173: iconst_5
    //   2174: bipush #16
    //   2176: iastore
    //   2177: dup
    //   2178: bipush #6
    //   2180: ldc 541081616
    //   2182: iastore
    //   2183: dup
    //   2184: bipush #7
    //   2186: ldc 4194304
    //   2188: iastore
    //   2189: dup
    //   2190: bipush #8
    //   2192: ldc 536887296
    //   2194: iastore
    //   2195: dup
    //   2196: bipush #9
    //   2198: ldc 4210704
    //   2200: iastore
    //   2201: dup
    //   2202: bipush #10
    //   2204: ldc 4194304
    //   2206: iastore
    //   2207: dup
    //   2208: bipush #11
    //   2210: ldc 536870928
    //   2212: iastore
    //   2213: dup
    //   2214: bipush #12
    //   2216: ldc 4194320
    //   2218: iastore
    //   2219: dup
    //   2220: bipush #13
    //   2222: ldc 536887296
    //   2224: iastore
    //   2225: dup
    //   2226: bipush #14
    //   2228: ldc 536870912
    //   2230: iastore
    //   2231: dup
    //   2232: bipush #15
    //   2234: sipush #16400
    //   2237: iastore
    //   2238: dup
    //   2239: bipush #16
    //   2241: iconst_0
    //   2242: iastore
    //   2243: dup
    //   2244: bipush #17
    //   2246: ldc 4194320
    //   2248: iastore
    //   2249: dup
    //   2250: bipush #18
    //   2252: ldc 536887312
    //   2254: iastore
    //   2255: dup
    //   2256: bipush #19
    //   2258: sipush #16384
    //   2261: iastore
    //   2262: dup
    //   2263: bipush #20
    //   2265: ldc 4210688
    //   2267: iastore
    //   2268: dup
    //   2269: bipush #21
    //   2271: ldc 536887312
    //   2273: iastore
    //   2274: dup
    //   2275: bipush #22
    //   2277: bipush #16
    //   2279: iastore
    //   2280: dup
    //   2281: bipush #23
    //   2283: ldc 541065232
    //   2285: iastore
    //   2286: dup
    //   2287: bipush #24
    //   2289: ldc 541065232
    //   2291: iastore
    //   2292: dup
    //   2293: bipush #25
    //   2295: iconst_0
    //   2296: iastore
    //   2297: dup
    //   2298: bipush #26
    //   2300: ldc 4210704
    //   2302: iastore
    //   2303: dup
    //   2304: bipush #27
    //   2306: ldc 541081600
    //   2308: iastore
    //   2309: dup
    //   2310: bipush #28
    //   2312: sipush #16400
    //   2315: iastore
    //   2316: dup
    //   2317: bipush #29
    //   2319: ldc 4210688
    //   2321: iastore
    //   2322: dup
    //   2323: bipush #30
    //   2325: ldc 541081600
    //   2327: iastore
    //   2328: dup
    //   2329: bipush #31
    //   2331: ldc 536870912
    //   2333: iastore
    //   2334: dup
    //   2335: bipush #32
    //   2337: ldc 536887296
    //   2339: iastore
    //   2340: dup
    //   2341: bipush #33
    //   2343: bipush #16
    //   2345: iastore
    //   2346: dup
    //   2347: bipush #34
    //   2349: ldc 541065232
    //   2351: iastore
    //   2352: dup
    //   2353: bipush #35
    //   2355: ldc 4210688
    //   2357: iastore
    //   2358: dup
    //   2359: bipush #36
    //   2361: ldc 541081616
    //   2363: iastore
    //   2364: dup
    //   2365: bipush #37
    //   2367: ldc 4194304
    //   2369: iastore
    //   2370: dup
    //   2371: bipush #38
    //   2373: sipush #16400
    //   2376: iastore
    //   2377: dup
    //   2378: bipush #39
    //   2380: ldc 536870928
    //   2382: iastore
    //   2383: dup
    //   2384: bipush #40
    //   2386: ldc 4194304
    //   2388: iastore
    //   2389: dup
    //   2390: bipush #41
    //   2392: ldc 536887296
    //   2394: iastore
    //   2395: dup
    //   2396: bipush #42
    //   2398: ldc 536870912
    //   2400: iastore
    //   2401: dup
    //   2402: bipush #43
    //   2404: sipush #16400
    //   2407: iastore
    //   2408: dup
    //   2409: bipush #44
    //   2411: ldc 536870928
    //   2413: iastore
    //   2414: dup
    //   2415: bipush #45
    //   2417: ldc 541081616
    //   2419: iastore
    //   2420: dup
    //   2421: bipush #46
    //   2423: ldc 4210688
    //   2425: iastore
    //   2426: dup
    //   2427: bipush #47
    //   2429: ldc 541065216
    //   2431: iastore
    //   2432: dup
    //   2433: bipush #48
    //   2435: ldc 4210704
    //   2437: iastore
    //   2438: dup
    //   2439: bipush #49
    //   2441: ldc 541081600
    //   2443: iastore
    //   2444: dup
    //   2445: bipush #50
    //   2447: iconst_0
    //   2448: iastore
    //   2449: dup
    //   2450: bipush #51
    //   2452: ldc 541065232
    //   2454: iastore
    //   2455: dup
    //   2456: bipush #52
    //   2458: bipush #16
    //   2460: iastore
    //   2461: dup
    //   2462: bipush #53
    //   2464: sipush #16384
    //   2467: iastore
    //   2468: dup
    //   2469: bipush #54
    //   2471: ldc 541065216
    //   2473: iastore
    //   2474: dup
    //   2475: bipush #55
    //   2477: ldc 4210704
    //   2479: iastore
    //   2480: dup
    //   2481: bipush #56
    //   2483: sipush #16384
    //   2486: iastore
    //   2487: dup
    //   2488: bipush #57
    //   2490: ldc 4194320
    //   2492: iastore
    //   2493: dup
    //   2494: bipush #58
    //   2496: ldc 536887312
    //   2498: iastore
    //   2499: dup
    //   2500: bipush #59
    //   2502: iconst_0
    //   2503: iastore
    //   2504: dup
    //   2505: bipush #60
    //   2507: ldc 541081600
    //   2509: iastore
    //   2510: dup
    //   2511: bipush #61
    //   2513: ldc 536870912
    //   2515: iastore
    //   2516: dup
    //   2517: bipush #62
    //   2519: ldc 4194320
    //   2521: iastore
    //   2522: dup
    //   2523: bipush #63
    //   2525: ldc 536887312
    //   2527: iastore
    //   2528: astore #11
    //   2530: bipush #64
    //   2532: newarray int
    //   2534: dup
    //   2535: iconst_0
    //   2536: ldc 2097152
    //   2538: iastore
    //   2539: dup
    //   2540: iconst_1
    //   2541: ldc 69206018
    //   2543: iastore
    //   2544: dup
    //   2545: iconst_2
    //   2546: ldc 67110914
    //   2548: iastore
    //   2549: dup
    //   2550: iconst_3
    //   2551: iconst_0
    //   2552: iastore
    //   2553: dup
    //   2554: iconst_4
    //   2555: sipush #2048
    //   2558: iastore
    //   2559: dup
    //   2560: iconst_5
    //   2561: ldc 67110914
    //   2563: iastore
    //   2564: dup
    //   2565: bipush #6
    //   2567: ldc 2099202
    //   2569: iastore
    //   2570: dup
    //   2571: bipush #7
    //   2573: ldc 69208064
    //   2575: iastore
    //   2576: dup
    //   2577: bipush #8
    //   2579: ldc 69208066
    //   2581: iastore
    //   2582: dup
    //   2583: bipush #9
    //   2585: ldc 2097152
    //   2587: iastore
    //   2588: dup
    //   2589: bipush #10
    //   2591: iconst_0
    //   2592: iastore
    //   2593: dup
    //   2594: bipush #11
    //   2596: ldc 67108866
    //   2598: iastore
    //   2599: dup
    //   2600: bipush #12
    //   2602: iconst_2
    //   2603: iastore
    //   2604: dup
    //   2605: bipush #13
    //   2607: ldc 67108864
    //   2609: iastore
    //   2610: dup
    //   2611: bipush #14
    //   2613: ldc 69206018
    //   2615: iastore
    //   2616: dup
    //   2617: bipush #15
    //   2619: sipush #2050
    //   2622: iastore
    //   2623: dup
    //   2624: bipush #16
    //   2626: ldc 67110912
    //   2628: iastore
    //   2629: dup
    //   2630: bipush #17
    //   2632: ldc 2099202
    //   2634: iastore
    //   2635: dup
    //   2636: bipush #18
    //   2638: ldc 2097154
    //   2640: iastore
    //   2641: dup
    //   2642: bipush #19
    //   2644: ldc 67110912
    //   2646: iastore
    //   2647: dup
    //   2648: bipush #20
    //   2650: ldc 67108866
    //   2652: iastore
    //   2653: dup
    //   2654: bipush #21
    //   2656: ldc 69206016
    //   2658: iastore
    //   2659: dup
    //   2660: bipush #22
    //   2662: ldc 69208064
    //   2664: iastore
    //   2665: dup
    //   2666: bipush #23
    //   2668: ldc 2097154
    //   2670: iastore
    //   2671: dup
    //   2672: bipush #24
    //   2674: ldc 69206016
    //   2676: iastore
    //   2677: dup
    //   2678: bipush #25
    //   2680: sipush #2048
    //   2683: iastore
    //   2684: dup
    //   2685: bipush #26
    //   2687: sipush #2050
    //   2690: iastore
    //   2691: dup
    //   2692: bipush #27
    //   2694: ldc 69208066
    //   2696: iastore
    //   2697: dup
    //   2698: bipush #28
    //   2700: ldc 2099200
    //   2702: iastore
    //   2703: dup
    //   2704: bipush #29
    //   2706: iconst_2
    //   2707: iastore
    //   2708: dup
    //   2709: bipush #30
    //   2711: ldc 67108864
    //   2713: iastore
    //   2714: dup
    //   2715: bipush #31
    //   2717: ldc 2099200
    //   2719: iastore
    //   2720: dup
    //   2721: bipush #32
    //   2723: ldc 67108864
    //   2725: iastore
    //   2726: dup
    //   2727: bipush #33
    //   2729: ldc 2099200
    //   2731: iastore
    //   2732: dup
    //   2733: bipush #34
    //   2735: ldc 2097152
    //   2737: iastore
    //   2738: dup
    //   2739: bipush #35
    //   2741: ldc 67110914
    //   2743: iastore
    //   2744: dup
    //   2745: bipush #36
    //   2747: ldc 67110914
    //   2749: iastore
    //   2750: dup
    //   2751: bipush #37
    //   2753: ldc 69206018
    //   2755: iastore
    //   2756: dup
    //   2757: bipush #38
    //   2759: ldc 69206018
    //   2761: iastore
    //   2762: dup
    //   2763: bipush #39
    //   2765: iconst_2
    //   2766: iastore
    //   2767: dup
    //   2768: bipush #40
    //   2770: ldc 2097154
    //   2772: iastore
    //   2773: dup
    //   2774: bipush #41
    //   2776: ldc 67108864
    //   2778: iastore
    //   2779: dup
    //   2780: bipush #42
    //   2782: ldc 67110912
    //   2784: iastore
    //   2785: dup
    //   2786: bipush #43
    //   2788: ldc 2097152
    //   2790: iastore
    //   2791: dup
    //   2792: bipush #44
    //   2794: ldc 69208064
    //   2796: iastore
    //   2797: dup
    //   2798: bipush #45
    //   2800: sipush #2050
    //   2803: iastore
    //   2804: dup
    //   2805: bipush #46
    //   2807: ldc 2099202
    //   2809: iastore
    //   2810: dup
    //   2811: bipush #47
    //   2813: ldc 69208064
    //   2815: iastore
    //   2816: dup
    //   2817: bipush #48
    //   2819: sipush #2050
    //   2822: iastore
    //   2823: dup
    //   2824: bipush #49
    //   2826: ldc 67108866
    //   2828: iastore
    //   2829: dup
    //   2830: bipush #50
    //   2832: ldc 69208066
    //   2834: iastore
    //   2835: dup
    //   2836: bipush #51
    //   2838: ldc 69206016
    //   2840: iastore
    //   2841: dup
    //   2842: bipush #52
    //   2844: ldc 2099200
    //   2846: iastore
    //   2847: dup
    //   2848: bipush #53
    //   2850: iconst_0
    //   2851: iastore
    //   2852: dup
    //   2853: bipush #54
    //   2855: iconst_2
    //   2856: iastore
    //   2857: dup
    //   2858: bipush #55
    //   2860: ldc 69208066
    //   2862: iastore
    //   2863: dup
    //   2864: bipush #56
    //   2866: iconst_0
    //   2867: iastore
    //   2868: dup
    //   2869: bipush #57
    //   2871: ldc 2099202
    //   2873: iastore
    //   2874: dup
    //   2875: bipush #58
    //   2877: ldc 69206016
    //   2879: iastore
    //   2880: dup
    //   2881: bipush #59
    //   2883: sipush #2048
    //   2886: iastore
    //   2887: dup
    //   2888: bipush #60
    //   2890: ldc 67108866
    //   2892: iastore
    //   2893: dup
    //   2894: bipush #61
    //   2896: ldc 67110912
    //   2898: iastore
    //   2899: dup
    //   2900: bipush #62
    //   2902: sipush #2048
    //   2905: iastore
    //   2906: dup
    //   2907: bipush #63
    //   2909: ldc 2097154
    //   2911: iastore
    //   2912: astore #12
    //   2914: bipush #64
    //   2916: newarray int
    //   2918: dup
    //   2919: iconst_0
    //   2920: ldc 268439616
    //   2922: iastore
    //   2923: dup
    //   2924: iconst_1
    //   2925: sipush #4096
    //   2928: iastore
    //   2929: dup
    //   2930: iconst_2
    //   2931: ldc 262144
    //   2933: iastore
    //   2934: dup
    //   2935: iconst_3
    //   2936: ldc 268701760
    //   2938: iastore
    //   2939: dup
    //   2940: iconst_4
    //   2941: ldc 268435456
    //   2943: iastore
    //   2944: dup
    //   2945: iconst_5
    //   2946: ldc 268439616
    //   2948: iastore
    //   2949: dup
    //   2950: bipush #6
    //   2952: bipush #64
    //   2954: iastore
    //   2955: dup
    //   2956: bipush #7
    //   2958: ldc 268435456
    //   2960: iastore
    //   2961: dup
    //   2962: bipush #8
    //   2964: ldc 262208
    //   2966: iastore
    //   2967: dup
    //   2968: bipush #9
    //   2970: ldc 268697600
    //   2972: iastore
    //   2973: dup
    //   2974: bipush #10
    //   2976: ldc 268701760
    //   2978: iastore
    //   2979: dup
    //   2980: bipush #11
    //   2982: ldc 266240
    //   2984: iastore
    //   2985: dup
    //   2986: bipush #12
    //   2988: ldc 268701696
    //   2990: iastore
    //   2991: dup
    //   2992: bipush #13
    //   2994: ldc 266304
    //   2996: iastore
    //   2997: dup
    //   2998: bipush #14
    //   3000: sipush #4096
    //   3003: iastore
    //   3004: dup
    //   3005: bipush #15
    //   3007: bipush #64
    //   3009: iastore
    //   3010: dup
    //   3011: bipush #16
    //   3013: ldc 268697600
    //   3015: iastore
    //   3016: dup
    //   3017: bipush #17
    //   3019: ldc 268435520
    //   3021: iastore
    //   3022: dup
    //   3023: bipush #18
    //   3025: ldc 268439552
    //   3027: iastore
    //   3028: dup
    //   3029: bipush #19
    //   3031: sipush #4160
    //   3034: iastore
    //   3035: dup
    //   3036: bipush #20
    //   3038: ldc 266240
    //   3040: iastore
    //   3041: dup
    //   3042: bipush #21
    //   3044: ldc 262208
    //   3046: iastore
    //   3047: dup
    //   3048: bipush #22
    //   3050: ldc 268697664
    //   3052: iastore
    //   3053: dup
    //   3054: bipush #23
    //   3056: ldc 268701696
    //   3058: iastore
    //   3059: dup
    //   3060: bipush #24
    //   3062: sipush #4160
    //   3065: iastore
    //   3066: dup
    //   3067: bipush #25
    //   3069: iconst_0
    //   3070: iastore
    //   3071: dup
    //   3072: bipush #26
    //   3074: iconst_0
    //   3075: iastore
    //   3076: dup
    //   3077: bipush #27
    //   3079: ldc 268697664
    //   3081: iastore
    //   3082: dup
    //   3083: bipush #28
    //   3085: ldc 268435520
    //   3087: iastore
    //   3088: dup
    //   3089: bipush #29
    //   3091: ldc 268439552
    //   3093: iastore
    //   3094: dup
    //   3095: bipush #30
    //   3097: ldc 266304
    //   3099: iastore
    //   3100: dup
    //   3101: bipush #31
    //   3103: ldc 262144
    //   3105: iastore
    //   3106: dup
    //   3107: bipush #32
    //   3109: ldc 266304
    //   3111: iastore
    //   3112: dup
    //   3113: bipush #33
    //   3115: ldc 262144
    //   3117: iastore
    //   3118: dup
    //   3119: bipush #34
    //   3121: ldc 268701696
    //   3123: iastore
    //   3124: dup
    //   3125: bipush #35
    //   3127: sipush #4096
    //   3130: iastore
    //   3131: dup
    //   3132: bipush #36
    //   3134: bipush #64
    //   3136: iastore
    //   3137: dup
    //   3138: bipush #37
    //   3140: ldc 268697664
    //   3142: iastore
    //   3143: dup
    //   3144: bipush #38
    //   3146: sipush #4096
    //   3149: iastore
    //   3150: dup
    //   3151: bipush #39
    //   3153: ldc 266304
    //   3155: iastore
    //   3156: dup
    //   3157: bipush #40
    //   3159: ldc 268439552
    //   3161: iastore
    //   3162: dup
    //   3163: bipush #41
    //   3165: bipush #64
    //   3167: iastore
    //   3168: dup
    //   3169: bipush #42
    //   3171: ldc 268435520
    //   3173: iastore
    //   3174: dup
    //   3175: bipush #43
    //   3177: ldc 268697600
    //   3179: iastore
    //   3180: dup
    //   3181: bipush #44
    //   3183: ldc 268697664
    //   3185: iastore
    //   3186: dup
    //   3187: bipush #45
    //   3189: ldc 268435456
    //   3191: iastore
    //   3192: dup
    //   3193: bipush #46
    //   3195: ldc 262144
    //   3197: iastore
    //   3198: dup
    //   3199: bipush #47
    //   3201: ldc 268439616
    //   3203: iastore
    //   3204: dup
    //   3205: bipush #48
    //   3207: iconst_0
    //   3208: iastore
    //   3209: dup
    //   3210: bipush #49
    //   3212: ldc 268701760
    //   3214: iastore
    //   3215: dup
    //   3216: bipush #50
    //   3218: ldc 262208
    //   3220: iastore
    //   3221: dup
    //   3222: bipush #51
    //   3224: ldc 268435520
    //   3226: iastore
    //   3227: dup
    //   3228: bipush #52
    //   3230: ldc 268697600
    //   3232: iastore
    //   3233: dup
    //   3234: bipush #53
    //   3236: ldc 268439552
    //   3238: iastore
    //   3239: dup
    //   3240: bipush #54
    //   3242: ldc 268439616
    //   3244: iastore
    //   3245: dup
    //   3246: bipush #55
    //   3248: iconst_0
    //   3249: iastore
    //   3250: dup
    //   3251: bipush #56
    //   3253: ldc 268701760
    //   3255: iastore
    //   3256: dup
    //   3257: bipush #57
    //   3259: ldc 266240
    //   3261: iastore
    //   3262: dup
    //   3263: bipush #58
    //   3265: ldc 266240
    //   3267: iastore
    //   3268: dup
    //   3269: bipush #59
    //   3271: sipush #4160
    //   3274: iastore
    //   3275: dup
    //   3276: bipush #60
    //   3278: sipush #4160
    //   3281: iastore
    //   3282: dup
    //   3283: bipush #61
    //   3285: ldc 262208
    //   3287: iastore
    //   3288: dup
    //   3289: bipush #62
    //   3291: ldc 268435456
    //   3293: iastore
    //   3294: dup
    //   3295: bipush #63
    //   3297: ldc 268701696
    //   3299: iastore
    //   3300: astore #13
    //   3302: aload_3
    //   3303: arraylength
    //   3304: istore #14
    //   3306: iload #14
    //   3308: bipush #8
    //   3310: irem
    //   3311: ifeq -> 3335
    //   3314: new java/lang/Exception
    //   3317: dup
    //   3318: sipush #2005
    //   3321: sipush #-27784
    //   3324: invokestatic a : (II)Ljava/lang/String;
    //   3327: invokespecial <init> : (Ljava/lang/String;)V
    //   3330: athrow
    //   3331: invokestatic a : (Ljava/lang/Throwable;)Ljava/lang/Throwable;
    //   3334: athrow
    //   3335: iconst_2
    //   3336: newarray int
    //   3338: astore #15
    //   3340: iload #14
    //   3342: newarray byte
    //   3344: astore #16
    //   3346: iload #14
    //   3348: bipush #8
    //   3350: idiv
    //   3351: istore #17
    //   3353: iconst_0
    //   3354: istore #18
    //   3356: iload #18
    //   3358: iload #17
    //   3360: if_icmpge -> 4274
    //   3363: iload #18
    //   3365: bipush #8
    //   3367: imul
    //   3368: istore #19
    //   3370: iconst_0
    //   3371: istore #20
    //   3373: iload #20
    //   3375: iconst_2
    //   3376: if_icmpge -> 3461
    //   3379: aload #15
    //   3381: iload #20
    //   3383: aload_3
    //   3384: iload #19
    //   3386: iload #20
    //   3388: iconst_4
    //   3389: imul
    //   3390: iadd
    //   3391: baload
    //   3392: sipush #255
    //   3395: iand
    //   3396: bipush #24
    //   3398: ishl
    //   3399: aload_3
    //   3400: iload #19
    //   3402: iload #20
    //   3404: iconst_4
    //   3405: imul
    //   3406: iadd
    //   3407: iconst_1
    //   3408: iadd
    //   3409: baload
    //   3410: sipush #255
    //   3413: iand
    //   3414: bipush #16
    //   3416: ishl
    //   3417: ior
    //   3418: aload_3
    //   3419: iload #19
    //   3421: iload #20
    //   3423: iconst_4
    //   3424: imul
    //   3425: iadd
    //   3426: iconst_2
    //   3427: iadd
    //   3428: baload
    //   3429: sipush #255
    //   3432: iand
    //   3433: bipush #8
    //   3435: ishl
    //   3436: ior
    //   3437: aload_3
    //   3438: iload #19
    //   3440: iload #20
    //   3442: iconst_4
    //   3443: imul
    //   3444: iadd
    //   3445: iconst_3
    //   3446: iadd
    //   3447: baload
    //   3448: sipush #255
    //   3451: iand
    //   3452: ior
    //   3453: iastore
    //   3454: iinc #20, 1
    //   3457: iload_2
    //   3458: ifeq -> 3373
    //   3461: iconst_0
    //   3462: istore #25
    //   3464: aload #15
    //   3466: iconst_0
    //   3467: iaload
    //   3468: istore #23
    //   3470: aload #15
    //   3472: iconst_1
    //   3473: iaload
    //   3474: istore #22
    //   3476: iload #23
    //   3478: iconst_4
    //   3479: iushr
    //   3480: iload #22
    //   3482: ixor
    //   3483: ldc 252645135
    //   3485: iand
    //   3486: istore #21
    //   3488: iload #22
    //   3490: iload #21
    //   3492: ixor
    //   3493: istore #22
    //   3495: iload #23
    //   3497: iload #21
    //   3499: iconst_4
    //   3500: ishl
    //   3501: ixor
    //   3502: istore #23
    //   3504: iload #23
    //   3506: bipush #16
    //   3508: iushr
    //   3509: iload #22
    //   3511: ixor
    //   3512: ldc 65535
    //   3514: iand
    //   3515: istore #21
    //   3517: iload #22
    //   3519: iload #21
    //   3521: ixor
    //   3522: istore #22
    //   3524: iload #23
    //   3526: iload #21
    //   3528: bipush #16
    //   3530: ishl
    //   3531: ixor
    //   3532: istore #23
    //   3534: iload #22
    //   3536: iconst_2
    //   3537: iushr
    //   3538: iload #23
    //   3540: ixor
    //   3541: ldc 858993459
    //   3543: iand
    //   3544: istore #21
    //   3546: iload #23
    //   3548: iload #21
    //   3550: ixor
    //   3551: istore #23
    //   3553: iload #22
    //   3555: iload #21
    //   3557: iconst_2
    //   3558: ishl
    //   3559: ixor
    //   3560: istore #22
    //   3562: iload #22
    //   3564: bipush #8
    //   3566: iushr
    //   3567: iload #23
    //   3569: ixor
    //   3570: ldc 16711935
    //   3572: iand
    //   3573: istore #21
    //   3575: iload #23
    //   3577: iload #21
    //   3579: ixor
    //   3580: istore #23
    //   3582: iload #22
    //   3584: iload #21
    //   3586: bipush #8
    //   3588: ishl
    //   3589: ixor
    //   3590: istore #22
    //   3592: iload #22
    //   3594: iconst_1
    //   3595: ishl
    //   3596: iload #22
    //   3598: bipush #31
    //   3600: iushr
    //   3601: iconst_1
    //   3602: iand
    //   3603: ior
    //   3604: istore #22
    //   3606: iload #23
    //   3608: iload #22
    //   3610: ixor
    //   3611: ldc -1431655766
    //   3613: iand
    //   3614: istore #21
    //   3616: iload #23
    //   3618: iload #21
    //   3620: ixor
    //   3621: istore #23
    //   3623: iload #22
    //   3625: iload #21
    //   3627: ixor
    //   3628: istore #22
    //   3630: iload #23
    //   3632: iconst_1
    //   3633: ishl
    //   3634: iload #23
    //   3636: bipush #31
    //   3638: iushr
    //   3639: iconst_1
    //   3640: iand
    //   3641: ior
    //   3642: istore #23
    //   3644: iconst_0
    //   3645: istore #24
    //   3647: iload #24
    //   3649: bipush #8
    //   3651: if_icmpge -> 3989
    //   3654: iload #22
    //   3656: bipush #28
    //   3658: ishl
    //   3659: iload #22
    //   3661: iconst_4
    //   3662: iushr
    //   3663: ior
    //   3664: istore #21
    //   3666: iload #21
    //   3668: aload #5
    //   3670: iload #25
    //   3672: iinc #25, 1
    //   3675: iaload
    //   3676: ixor
    //   3677: istore #21
    //   3679: aload #12
    //   3681: iload #21
    //   3683: bipush #63
    //   3685: iand
    //   3686: iaload
    //   3687: istore #20
    //   3689: iload #20
    //   3691: aload #10
    //   3693: iload #21
    //   3695: bipush #8
    //   3697: iushr
    //   3698: bipush #63
    //   3700: iand
    //   3701: iaload
    //   3702: ior
    //   3703: istore #20
    //   3705: iload #20
    //   3707: aload #8
    //   3709: iload #21
    //   3711: bipush #16
    //   3713: iushr
    //   3714: bipush #63
    //   3716: iand
    //   3717: iaload
    //   3718: ior
    //   3719: istore #20
    //   3721: iload #20
    //   3723: aload #6
    //   3725: iload #21
    //   3727: bipush #24
    //   3729: iushr
    //   3730: bipush #63
    //   3732: iand
    //   3733: iaload
    //   3734: ior
    //   3735: istore #20
    //   3737: iload #22
    //   3739: aload #5
    //   3741: iload #25
    //   3743: iinc #25, 1
    //   3746: iaload
    //   3747: ixor
    //   3748: istore #21
    //   3750: iload #20
    //   3752: aload #13
    //   3754: iload #21
    //   3756: bipush #63
    //   3758: iand
    //   3759: iaload
    //   3760: ior
    //   3761: istore #20
    //   3763: iload #20
    //   3765: aload #11
    //   3767: iload #21
    //   3769: bipush #8
    //   3771: iushr
    //   3772: bipush #63
    //   3774: iand
    //   3775: iaload
    //   3776: ior
    //   3777: istore #20
    //   3779: iload #20
    //   3781: aload #9
    //   3783: iload #21
    //   3785: bipush #16
    //   3787: iushr
    //   3788: bipush #63
    //   3790: iand
    //   3791: iaload
    //   3792: ior
    //   3793: istore #20
    //   3795: iload #20
    //   3797: aload #7
    //   3799: iload #21
    //   3801: bipush #24
    //   3803: iushr
    //   3804: bipush #63
    //   3806: iand
    //   3807: iaload
    //   3808: ior
    //   3809: istore #20
    //   3811: iload #23
    //   3813: iload #20
    //   3815: ixor
    //   3816: istore #23
    //   3818: iload #23
    //   3820: bipush #28
    //   3822: ishl
    //   3823: iload #23
    //   3825: iconst_4
    //   3826: iushr
    //   3827: ior
    //   3828: istore #21
    //   3830: iload #21
    //   3832: aload #5
    //   3834: iload #25
    //   3836: iinc #25, 1
    //   3839: iaload
    //   3840: ixor
    //   3841: istore #21
    //   3843: aload #12
    //   3845: iload #21
    //   3847: bipush #63
    //   3849: iand
    //   3850: iaload
    //   3851: istore #20
    //   3853: iload #20
    //   3855: aload #10
    //   3857: iload #21
    //   3859: bipush #8
    //   3861: iushr
    //   3862: bipush #63
    //   3864: iand
    //   3865: iaload
    //   3866: ior
    //   3867: istore #20
    //   3869: iload #20
    //   3871: aload #8
    //   3873: iload #21
    //   3875: bipush #16
    //   3877: iushr
    //   3878: bipush #63
    //   3880: iand
    //   3881: iaload
    //   3882: ior
    //   3883: istore #20
    //   3885: iload #20
    //   3887: aload #6
    //   3889: iload #21
    //   3891: bipush #24
    //   3893: iushr
    //   3894: bipush #63
    //   3896: iand
    //   3897: iaload
    //   3898: ior
    //   3899: istore #20
    //   3901: iload #23
    //   3903: aload #5
    //   3905: iload #25
    //   3907: iinc #25, 1
    //   3910: iaload
    //   3911: ixor
    //   3912: istore #21
    //   3914: iload #20
    //   3916: aload #13
    //   3918: iload #21
    //   3920: bipush #63
    //   3922: iand
    //   3923: iaload
    //   3924: ior
    //   3925: istore #20
    //   3927: iload #20
    //   3929: aload #11
    //   3931: iload #21
    //   3933: bipush #8
    //   3935: iushr
    //   3936: bipush #63
    //   3938: iand
    //   3939: iaload
    //   3940: ior
    //   3941: istore #20
    //   3943: iload #20
    //   3945: aload #9
    //   3947: iload #21
    //   3949: bipush #16
    //   3951: iushr
    //   3952: bipush #63
    //   3954: iand
    //   3955: iaload
    //   3956: ior
    //   3957: istore #20
    //   3959: iload #20
    //   3961: aload #7
    //   3963: iload #21
    //   3965: bipush #24
    //   3967: iushr
    //   3968: bipush #63
    //   3970: iand
    //   3971: iaload
    //   3972: ior
    //   3973: istore #20
    //   3975: iload #22
    //   3977: iload #20
    //   3979: ixor
    //   3980: istore #22
    //   3982: iinc #24, 1
    //   3985: iload_2
    //   3986: ifeq -> 3647
    //   3989: iload #22
    //   3991: bipush #31
    //   3993: ishl
    //   3994: iload #22
    //   3996: iconst_1
    //   3997: iushr
    //   3998: ior
    //   3999: istore #22
    //   4001: iload #23
    //   4003: iload #22
    //   4005: ixor
    //   4006: ldc -1431655766
    //   4008: iand
    //   4009: istore #21
    //   4011: iload #23
    //   4013: iload #21
    //   4015: ixor
    //   4016: istore #23
    //   4018: iload #22
    //   4020: iload #21
    //   4022: ixor
    //   4023: istore #22
    //   4025: iload #23
    //   4027: bipush #31
    //   4029: ishl
    //   4030: iload #23
    //   4032: iconst_1
    //   4033: iushr
    //   4034: ior
    //   4035: istore #23
    //   4037: iload #23
    //   4039: bipush #8
    //   4041: iushr
    //   4042: iload #22
    //   4044: ixor
    //   4045: ldc 16711935
    //   4047: iand
    //   4048: istore #21
    //   4050: iload #22
    //   4052: iload #21
    //   4054: ixor
    //   4055: istore #22
    //   4057: iload #23
    //   4059: iload #21
    //   4061: bipush #8
    //   4063: ishl
    //   4064: ixor
    //   4065: istore #23
    //   4067: iload #23
    //   4069: iconst_2
    //   4070: iushr
    //   4071: iload #22
    //   4073: ixor
    //   4074: ldc 858993459
    //   4076: iand
    //   4077: istore #21
    //   4079: iload #22
    //   4081: iload #21
    //   4083: ixor
    //   4084: istore #22
    //   4086: iload #23
    //   4088: iload #21
    //   4090: iconst_2
    //   4091: ishl
    //   4092: ixor
    //   4093: istore #23
    //   4095: iload #22
    //   4097: bipush #16
    //   4099: iushr
    //   4100: iload #23
    //   4102: ixor
    //   4103: ldc 65535
    //   4105: iand
    //   4106: istore #21
    //   4108: iload #23
    //   4110: iload #21
    //   4112: ixor
    //   4113: istore #23
    //   4115: iload #22
    //   4117: iload #21
    //   4119: bipush #16
    //   4121: ishl
    //   4122: ixor
    //   4123: istore #22
    //   4125: iload #22
    //   4127: iconst_4
    //   4128: iushr
    //   4129: iload #23
    //   4131: ixor
    //   4132: ldc 252645135
    //   4134: iand
    //   4135: istore #21
    //   4137: iload #23
    //   4139: iload #21
    //   4141: ixor
    //   4142: istore #23
    //   4144: iload #22
    //   4146: iload #21
    //   4148: iconst_4
    //   4149: ishl
    //   4150: ixor
    //   4151: istore #22
    //   4153: aload #15
    //   4155: iconst_0
    //   4156: iload #22
    //   4158: iastore
    //   4159: aload #15
    //   4161: iconst_1
    //   4162: iload #23
    //   4164: iastore
    //   4165: iload #18
    //   4167: bipush #8
    //   4169: imul
    //   4170: istore #26
    //   4172: iconst_0
    //   4173: istore #27
    //   4175: iload #27
    //   4177: iconst_2
    //   4178: if_icmpge -> 4267
    //   4181: aload #16
    //   4183: iload #26
    //   4185: iload #27
    //   4187: iconst_4
    //   4188: imul
    //   4189: iadd
    //   4190: aload #15
    //   4192: iload #27
    //   4194: iaload
    //   4195: bipush #24
    //   4197: iushr
    //   4198: i2b
    //   4199: bastore
    //   4200: aload #16
    //   4202: iload #26
    //   4204: iload #27
    //   4206: iconst_4
    //   4207: imul
    //   4208: iadd
    //   4209: iconst_1
    //   4210: iadd
    //   4211: aload #15
    //   4213: iload #27
    //   4215: iaload
    //   4216: bipush #16
    //   4218: iushr
    //   4219: i2b
    //   4220: bastore
    //   4221: aload #16
    //   4223: iload #26
    //   4225: iload #27
    //   4227: iconst_4
    //   4228: imul
    //   4229: iadd
    //   4230: iconst_2
    //   4231: iadd
    //   4232: aload #15
    //   4234: iload #27
    //   4236: iaload
    //   4237: bipush #8
    //   4239: iushr
    //   4240: i2b
    //   4241: bastore
    //   4242: aload #16
    //   4244: iload #26
    //   4246: iload #27
    //   4248: iconst_4
    //   4249: imul
    //   4250: iadd
    //   4251: iconst_3
    //   4252: iadd
    //   4253: aload #15
    //   4255: iload #27
    //   4257: iaload
    //   4258: i2b
    //   4259: bastore
    //   4260: iinc #27, 1
    //   4263: iload_2
    //   4264: ifeq -> 4175
    //   4267: iinc #18, 1
    //   4270: iload_2
    //   4271: ifeq -> 3356
    //   4274: aload #16
    //   4276: aload #16
    //   4278: arraylength
    //   4279: iconst_1
    //   4280: isub
    //   4281: baload
    //   4282: istore #18
    //   4284: aload #16
    //   4286: arraylength
    //   4287: iload #18
    //   4289: isub
    //   4290: newarray byte
    //   4292: astore #4
    //   4294: aload #16
    //   4296: arraylength
    //   4297: aload #4
    //   4299: arraylength
    //   4300: if_icmpge -> 4324
    //   4303: new java/lang/Exception
    //   4306: dup
    //   4307: sipush #2011
    //   4310: sipush #17747
    //   4313: invokestatic a : (II)Ljava/lang/String;
    //   4316: invokespecial <init> : (Ljava/lang/String;)V
    //   4319: athrow
    //   4320: invokestatic a : (Ljava/lang/Throwable;)Ljava/lang/Throwable;
    //   4323: athrow
    //   4324: iconst_0
    //   4325: istore #19
    //   4327: iload #19
    //   4329: aload #4
    //   4331: arraylength
    //   4332: if_icmpge -> 4352
    //   4335: aload #4
    //   4337: iload #19
    //   4339: aload #16
    //   4341: iload #19
    //   4343: baload
    //   4344: bastore
    //   4345: iinc #19, 1
    //   4348: iload_2
    //   4349: ifeq -> 4327
    //   4352: new java/math/BigInteger
    //   4355: dup
    //   4356: aload #4
    //   4358: invokespecial <init> : ([B)V
    //   4361: invokevirtual abs : ()Ljava/math/BigInteger;
    //   4364: putstatic burp/Zr5k.Zj : Ljava/lang/Object;
    //   4367: getstatic burp/Zrs0.Zz : Ljava/lang/Object;
    //   4370: checkcast java/math/BigInteger
    //   4373: invokevirtual toByteArray : ()[B
    //   4376: astore_3
    //   4377: bipush #32
    //   4379: newarray int
    //   4381: dup
    //   4382: iconst_0
    //   4383: ldc 876216579
    //   4385: iastore
    //   4386: dup
    //   4387: iconst_1
    //   4388: ldc 455999525
    //   4390: iastore
    //   4391: dup
    //   4392: iconst_2
    //   4393: ldc 1043334948
    //   4395: iastore
    //   4396: dup
    //   4397: iconst_3
    //   4398: ldc 439222784
    //   4400: iastore
    //   4401: dup
    //   4402: iconst_4
    //   4403: ldc 372376604
    //   4405: iastore
    //   4406: dup
    //   4407: iconst_5
    //   4408: ldc 707731490
    //   4410: iastore
    //   4411: dup
    //   4412: bipush #6
    //   4414: ldc 389426184
    //   4416: iastore
    //   4417: dup
    //   4418: bipush #7
    //   4420: ldc 973875457
    //   4422: iastore
    //   4423: dup
    //   4424: bipush #8
    //   4426: ldc 389160971
    //   4428: iastore
    //   4429: dup
    //   4430: bipush #9
    //   4432: ldc 907870729
    //   4434: iastore
    //   4435: dup
    //   4436: bipush #10
    //   4438: ldc 121057538
    //   4440: iastore
    //   4441: dup
    //   4442: bipush #11
    //   4444: ldc 840500228
    //   4446: iastore
    //   4447: dup
    //   4448: bipush #12
    //   4450: ldc 254150144
    //   4452: iastore
    //   4453: dup
    //   4454: bipush #13
    //   4456: ldc 924386310
    //   4458: iastore
    //   4459: dup
    //   4460: bipush #14
    //   4462: ldc 187632156
    //   4464: iastore
    //   4465: dup
    //   4466: bipush #15
    //   4468: ldc 874189824
    //   4470: iastore
    //   4471: dup
    //   4472: bipush #16
    //   4474: ldc 655302664
    //   4476: iastore
    //   4477: dup
    //   4478: bipush #17
    //   4480: ldc 890966315
    //   4482: iastore
    //   4483: dup
    //   4484: bipush #18
    //   4486: ldc 722417666
    //   4488: iastore
    //   4489: dup
    //   4490: bipush #19
    //   4492: ldc 1026621720
    //   4494: iastore
    //   4495: dup
    //   4496: bipush #20
    //   4498: ldc 957157408
    //   4500: iastore
    //   4501: dup
    //   4502: bipush #21
    //   4504: ldc 892536332
    //   4506: iastore
    //   4507: dup
    //   4508: bipush #22
    //   4510: ldc 689771012
    //   4512: iastore
    //   4513: dup
    //   4514: bipush #23
    //   4516: ldc 221709344
    //   4518: iastore
    //   4519: dup
    //   4520: bipush #24
    //   4522: ldc 940377620
    //   4524: iastore
    //   4525: dup
    //   4526: bipush #25
    //   4528: ldc 255209728
    //   4530: iastore
    //   4531: dup
    //   4532: bipush #26
    //   4534: ldc 1010368540
    //   4536: iastore
    //   4537: dup
    //   4538: bipush #27
    //   4540: ldc 220604441
    //   4542: iastore
    //   4543: dup
    //   4544: bipush #28
    //   4546: ldc 1008414755
    //   4548: iastore
    //   4549: dup
    //   4550: bipush #29
    //   4552: ldc 187049985
    //   4554: iastore
    //   4555: dup
    //   4556: bipush #30
    //   4558: ldc 943331329
    //   4560: iastore
    //   4561: dup
    //   4562: bipush #31
    //   4564: ldc 170788368
    //   4566: iastore
    //   4567: astore #5
    //   4569: bipush #64
    //   4571: newarray int
    //   4573: dup
    //   4574: iconst_0
    //   4575: ldc 16843776
    //   4577: iastore
    //   4578: dup
    //   4579: iconst_1
    //   4580: iconst_0
    //   4581: iastore
    //   4582: dup
    //   4583: iconst_2
    //   4584: ldc 65536
    //   4586: iastore
    //   4587: dup
    //   4588: iconst_3
    //   4589: ldc 16843780
    //   4591: iastore
    //   4592: dup
    //   4593: iconst_4
    //   4594: ldc 16842756
    //   4596: iastore
    //   4597: dup
    //   4598: iconst_5
    //   4599: ldc 66564
    //   4601: iastore
    //   4602: dup
    //   4603: bipush #6
    //   4605: iconst_4
    //   4606: iastore
    //   4607: dup
    //   4608: bipush #7
    //   4610: ldc 65536
    //   4612: iastore
    //   4613: dup
    //   4614: bipush #8
    //   4616: sipush #1024
    //   4619: iastore
    //   4620: dup
    //   4621: bipush #9
    //   4623: ldc 16843776
    //   4625: iastore
    //   4626: dup
    //   4627: bipush #10
    //   4629: ldc 16843780
    //   4631: iastore
    //   4632: dup
    //   4633: bipush #11
    //   4635: sipush #1024
    //   4638: iastore
    //   4639: dup
    //   4640: bipush #12
    //   4642: ldc 16778244
    //   4644: iastore
    //   4645: dup
    //   4646: bipush #13
    //   4648: ldc 16842756
    //   4650: iastore
    //   4651: dup
    //   4652: bipush #14
    //   4654: ldc 16777216
    //   4656: iastore
    //   4657: dup
    //   4658: bipush #15
    //   4660: iconst_4
    //   4661: iastore
    //   4662: dup
    //   4663: bipush #16
    //   4665: sipush #1028
    //   4668: iastore
    //   4669: dup
    //   4670: bipush #17
    //   4672: ldc 16778240
    //   4674: iastore
    //   4675: dup
    //   4676: bipush #18
    //   4678: ldc 16778240
    //   4680: iastore
    //   4681: dup
    //   4682: bipush #19
    //   4684: ldc 66560
    //   4686: iastore
    //   4687: dup
    //   4688: bipush #20
    //   4690: ldc 66560
    //   4692: iastore
    //   4693: dup
    //   4694: bipush #21
    //   4696: ldc 16842752
    //   4698: iastore
    //   4699: dup
    //   4700: bipush #22
    //   4702: ldc 16842752
    //   4704: iastore
    //   4705: dup
    //   4706: bipush #23
    //   4708: ldc 16778244
    //   4710: iastore
    //   4711: dup
    //   4712: bipush #24
    //   4714: ldc 65540
    //   4716: iastore
    //   4717: dup
    //   4718: bipush #25
    //   4720: ldc 16777220
    //   4722: iastore
    //   4723: dup
    //   4724: bipush #26
    //   4726: ldc 16777220
    //   4728: iastore
    //   4729: dup
    //   4730: bipush #27
    //   4732: ldc 65540
    //   4734: iastore
    //   4735: dup
    //   4736: bipush #28
    //   4738: iconst_0
    //   4739: iastore
    //   4740: dup
    //   4741: bipush #29
    //   4743: sipush #1028
    //   4746: iastore
    //   4747: dup
    //   4748: bipush #30
    //   4750: ldc 66564
    //   4752: iastore
    //   4753: dup
    //   4754: bipush #31
    //   4756: ldc 16777216
    //   4758: iastore
    //   4759: dup
    //   4760: bipush #32
    //   4762: ldc 65536
    //   4764: iastore
    //   4765: dup
    //   4766: bipush #33
    //   4768: ldc 16843780
    //   4770: iastore
    //   4771: dup
    //   4772: bipush #34
    //   4774: iconst_4
    //   4775: iastore
    //   4776: dup
    //   4777: bipush #35
    //   4779: ldc 16842752
    //   4781: iastore
    //   4782: dup
    //   4783: bipush #36
    //   4785: ldc 16843776
    //   4787: iastore
    //   4788: dup
    //   4789: bipush #37
    //   4791: ldc 16777216
    //   4793: iastore
    //   4794: dup
    //   4795: bipush #38
    //   4797: ldc 16777216
    //   4799: iastore
    //   4800: dup
    //   4801: bipush #39
    //   4803: sipush #1024
    //   4806: iastore
    //   4807: dup
    //   4808: bipush #40
    //   4810: ldc 16842756
    //   4812: iastore
    //   4813: dup
    //   4814: bipush #41
    //   4816: ldc 65536
    //   4818: iastore
    //   4819: dup
    //   4820: bipush #42
    //   4822: ldc 66560
    //   4824: iastore
    //   4825: dup
    //   4826: bipush #43
    //   4828: ldc 16777220
    //   4830: iastore
    //   4831: dup
    //   4832: bipush #44
    //   4834: sipush #1024
    //   4837: iastore
    //   4838: dup
    //   4839: bipush #45
    //   4841: iconst_4
    //   4842: iastore
    //   4843: dup
    //   4844: bipush #46
    //   4846: ldc 16778244
    //   4848: iastore
    //   4849: dup
    //   4850: bipush #47
    //   4852: ldc 66564
    //   4854: iastore
    //   4855: dup
    //   4856: bipush #48
    //   4858: ldc 16843780
    //   4860: iastore
    //   4861: dup
    //   4862: bipush #49
    //   4864: ldc 65540
    //   4866: iastore
    //   4867: dup
    //   4868: bipush #50
    //   4870: ldc 16842752
    //   4872: iastore
    //   4873: dup
    //   4874: bipush #51
    //   4876: ldc 16778244
    //   4878: iastore
    //   4879: dup
    //   4880: bipush #52
    //   4882: ldc 16777220
    //   4884: iastore
    //   4885: dup
    //   4886: bipush #53
    //   4888: sipush #1028
    //   4891: iastore
    //   4892: dup
    //   4893: bipush #54
    //   4895: ldc 66564
    //   4897: iastore
    //   4898: dup
    //   4899: bipush #55
    //   4901: ldc 16843776
    //   4903: iastore
    //   4904: dup
    //   4905: bipush #56
    //   4907: sipush #1028
    //   4910: iastore
    //   4911: dup
    //   4912: bipush #57
    //   4914: ldc 16778240
    //   4916: iastore
    //   4917: dup
    //   4918: bipush #58
    //   4920: ldc 16778240
    //   4922: iastore
    //   4923: dup
    //   4924: bipush #59
    //   4926: iconst_0
    //   4927: iastore
    //   4928: dup
    //   4929: bipush #60
    //   4931: ldc 65540
    //   4933: iastore
    //   4934: dup
    //   4935: bipush #61
    //   4937: ldc 66560
    //   4939: iastore
    //   4940: dup
    //   4941: bipush #62
    //   4943: iconst_0
    //   4944: iastore
    //   4945: dup
    //   4946: bipush #63
    //   4948: ldc 16842756
    //   4950: iastore
    //   4951: astore #6
    //   4953: bipush #64
    //   4955: newarray int
    //   4957: dup
    //   4958: iconst_0
    //   4959: ldc -2146402272
    //   4961: iastore
    //   4962: dup
    //   4963: iconst_1
    //   4964: ldc -2147450880
    //   4966: iastore
    //   4967: dup
    //   4968: iconst_2
    //   4969: ldc 32768
    //   4971: iastore
    //   4972: dup
    //   4973: iconst_3
    //   4974: ldc 1081376
    //   4976: iastore
    //   4977: dup
    //   4978: iconst_4
    //   4979: ldc 1048576
    //   4981: iastore
    //   4982: dup
    //   4983: iconst_5
    //   4984: bipush #32
    //   4986: iastore
    //   4987: dup
    //   4988: bipush #6
    //   4990: ldc -2146435040
    //   4992: iastore
    //   4993: dup
    //   4994: bipush #7
    //   4996: ldc -2147450848
    //   4998: iastore
    //   4999: dup
    //   5000: bipush #8
    //   5002: ldc -2147483616
    //   5004: iastore
    //   5005: dup
    //   5006: bipush #9
    //   5008: ldc -2146402272
    //   5010: iastore
    //   5011: dup
    //   5012: bipush #10
    //   5014: ldc -2146402304
    //   5016: iastore
    //   5017: dup
    //   5018: bipush #11
    //   5020: ldc -2147483648
    //   5022: iastore
    //   5023: dup
    //   5024: bipush #12
    //   5026: ldc -2147450880
    //   5028: iastore
    //   5029: dup
    //   5030: bipush #13
    //   5032: ldc 1048576
    //   5034: iastore
    //   5035: dup
    //   5036: bipush #14
    //   5038: bipush #32
    //   5040: iastore
    //   5041: dup
    //   5042: bipush #15
    //   5044: ldc -2146435040
    //   5046: iastore
    //   5047: dup
    //   5048: bipush #16
    //   5050: ldc 1081344
    //   5052: iastore
    //   5053: dup
    //   5054: bipush #17
    //   5056: ldc 1048608
    //   5058: iastore
    //   5059: dup
    //   5060: bipush #18
    //   5062: ldc -2147450848
    //   5064: iastore
    //   5065: dup
    //   5066: bipush #19
    //   5068: iconst_0
    //   5069: iastore
    //   5070: dup
    //   5071: bipush #20
    //   5073: ldc -2147483648
    //   5075: iastore
    //   5076: dup
    //   5077: bipush #21
    //   5079: ldc 32768
    //   5081: iastore
    //   5082: dup
    //   5083: bipush #22
    //   5085: ldc 1081376
    //   5087: iastore
    //   5088: dup
    //   5089: bipush #23
    //   5091: ldc -2146435072
    //   5093: iastore
    //   5094: dup
    //   5095: bipush #24
    //   5097: ldc 1048608
    //   5099: iastore
    //   5100: dup
    //   5101: bipush #25
    //   5103: ldc -2147483616
    //   5105: iastore
    //   5106: dup
    //   5107: bipush #26
    //   5109: iconst_0
    //   5110: iastore
    //   5111: dup
    //   5112: bipush #27
    //   5114: ldc 1081344
    //   5116: iastore
    //   5117: dup
    //   5118: bipush #28
    //   5120: ldc 32800
    //   5122: iastore
    //   5123: dup
    //   5124: bipush #29
    //   5126: ldc -2146402304
    //   5128: iastore
    //   5129: dup
    //   5130: bipush #30
    //   5132: ldc -2146435072
    //   5134: iastore
    //   5135: dup
    //   5136: bipush #31
    //   5138: ldc 32800
    //   5140: iastore
    //   5141: dup
    //   5142: bipush #32
    //   5144: iconst_0
    //   5145: iastore
    //   5146: dup
    //   5147: bipush #33
    //   5149: ldc 1081376
    //   5151: iastore
    //   5152: dup
    //   5153: bipush #34
    //   5155: ldc -2146435040
    //   5157: iastore
    //   5158: dup
    //   5159: bipush #35
    //   5161: ldc 1048576
    //   5163: iastore
    //   5164: dup
    //   5165: bipush #36
    //   5167: ldc -2147450848
    //   5169: iastore
    //   5170: dup
    //   5171: bipush #37
    //   5173: ldc -2146435072
    //   5175: iastore
    //   5176: dup
    //   5177: bipush #38
    //   5179: ldc -2146402304
    //   5181: iastore
    //   5182: dup
    //   5183: bipush #39
    //   5185: ldc 32768
    //   5187: iastore
    //   5188: dup
    //   5189: bipush #40
    //   5191: ldc -2146435072
    //   5193: iastore
    //   5194: dup
    //   5195: bipush #41
    //   5197: ldc -2147450880
    //   5199: iastore
    //   5200: dup
    //   5201: bipush #42
    //   5203: bipush #32
    //   5205: iastore
    //   5206: dup
    //   5207: bipush #43
    //   5209: ldc -2146402272
    //   5211: iastore
    //   5212: dup
    //   5213: bipush #44
    //   5215: ldc 1081376
    //   5217: iastore
    //   5218: dup
    //   5219: bipush #45
    //   5221: bipush #32
    //   5223: iastore
    //   5224: dup
    //   5225: bipush #46
    //   5227: ldc 32768
    //   5229: iastore
    //   5230: dup
    //   5231: bipush #47
    //   5233: ldc -2147483648
    //   5235: iastore
    //   5236: dup
    //   5237: bipush #48
    //   5239: ldc 32800
    //   5241: iastore
    //   5242: dup
    //   5243: bipush #49
    //   5245: ldc -2146402304
    //   5247: iastore
    //   5248: dup
    //   5249: bipush #50
    //   5251: ldc 1048576
    //   5253: iastore
    //   5254: dup
    //   5255: bipush #51
    //   5257: ldc -2147483616
    //   5259: iastore
    //   5260: dup
    //   5261: bipush #52
    //   5263: ldc 1048608
    //   5265: iastore
    //   5266: dup
    //   5267: bipush #53
    //   5269: ldc -2147450848
    //   5271: iastore
    //   5272: dup
    //   5273: bipush #54
    //   5275: ldc -2147483616
    //   5277: iastore
    //   5278: dup
    //   5279: bipush #55
    //   5281: ldc 1048608
    //   5283: iastore
    //   5284: dup
    //   5285: bipush #56
    //   5287: ldc 1081344
    //   5289: iastore
    //   5290: dup
    //   5291: bipush #57
    //   5293: iconst_0
    //   5294: iastore
    //   5295: dup
    //   5296: bipush #58
    //   5298: ldc -2147450880
    //   5300: iastore
    //   5301: dup
    //   5302: bipush #59
    //   5304: ldc 32800
    //   5306: iastore
    //   5307: dup
    //   5308: bipush #60
    //   5310: ldc -2147483648
    //   5312: iastore
    //   5313: dup
    //   5314: bipush #61
    //   5316: ldc -2146435040
    //   5318: iastore
    //   5319: dup
    //   5320: bipush #62
    //   5322: ldc -2146402272
    //   5324: iastore
    //   5325: dup
    //   5326: bipush #63
    //   5328: ldc 1081344
    //   5330: iastore
    //   5331: astore #7
    //   5333: bipush #64
    //   5335: newarray int
    //   5337: dup
    //   5338: iconst_0
    //   5339: sipush #520
    //   5342: iastore
    //   5343: dup
    //   5344: iconst_1
    //   5345: ldc 134349312
    //   5347: iastore
    //   5348: dup
    //   5349: iconst_2
    //   5350: iconst_0
    //   5351: iastore
    //   5352: dup
    //   5353: iconst_3
    //   5354: ldc 134348808
    //   5356: iastore
    //   5357: dup
    //   5358: iconst_4
    //   5359: ldc 134218240
    //   5361: iastore
    //   5362: dup
    //   5363: iconst_5
    //   5364: iconst_0
    //   5365: iastore
    //   5366: dup
    //   5367: bipush #6
    //   5369: ldc 131592
    //   5371: iastore
    //   5372: dup
    //   5373: bipush #7
    //   5375: ldc 134218240
    //   5377: iastore
    //   5378: dup
    //   5379: bipush #8
    //   5381: ldc 131080
    //   5383: iastore
    //   5384: dup
    //   5385: bipush #9
    //   5387: ldc 134217736
    //   5389: iastore
    //   5390: dup
    //   5391: bipush #10
    //   5393: ldc 134217736
    //   5395: iastore
    //   5396: dup
    //   5397: bipush #11
    //   5399: ldc 131072
    //   5401: iastore
    //   5402: dup
    //   5403: bipush #12
    //   5405: ldc 134349320
    //   5407: iastore
    //   5408: dup
    //   5409: bipush #13
    //   5411: ldc 131080
    //   5413: iastore
    //   5414: dup
    //   5415: bipush #14
    //   5417: ldc 134348800
    //   5419: iastore
    //   5420: dup
    //   5421: bipush #15
    //   5423: sipush #520
    //   5426: iastore
    //   5427: dup
    //   5428: bipush #16
    //   5430: ldc 134217728
    //   5432: iastore
    //   5433: dup
    //   5434: bipush #17
    //   5436: bipush #8
    //   5438: iastore
    //   5439: dup
    //   5440: bipush #18
    //   5442: ldc 134349312
    //   5444: iastore
    //   5445: dup
    //   5446: bipush #19
    //   5448: sipush #512
    //   5451: iastore
    //   5452: dup
    //   5453: bipush #20
    //   5455: ldc 131584
    //   5457: iastore
    //   5458: dup
    //   5459: bipush #21
    //   5461: ldc 134348800
    //   5463: iastore
    //   5464: dup
    //   5465: bipush #22
    //   5467: ldc 134348808
    //   5469: iastore
    //   5470: dup
    //   5471: bipush #23
    //   5473: ldc 131592
    //   5475: iastore
    //   5476: dup
    //   5477: bipush #24
    //   5479: ldc 134218248
    //   5481: iastore
    //   5482: dup
    //   5483: bipush #25
    //   5485: ldc 131584
    //   5487: iastore
    //   5488: dup
    //   5489: bipush #26
    //   5491: ldc 131072
    //   5493: iastore
    //   5494: dup
    //   5495: bipush #27
    //   5497: ldc 134218248
    //   5499: iastore
    //   5500: dup
    //   5501: bipush #28
    //   5503: bipush #8
    //   5505: iastore
    //   5506: dup
    //   5507: bipush #29
    //   5509: ldc 134349320
    //   5511: iastore
    //   5512: dup
    //   5513: bipush #30
    //   5515: sipush #512
    //   5518: iastore
    //   5519: dup
    //   5520: bipush #31
    //   5522: ldc 134217728
    //   5524: iastore
    //   5525: dup
    //   5526: bipush #32
    //   5528: ldc 134349312
    //   5530: iastore
    //   5531: dup
    //   5532: bipush #33
    //   5534: ldc 134217728
    //   5536: iastore
    //   5537: dup
    //   5538: bipush #34
    //   5540: ldc 131080
    //   5542: iastore
    //   5543: dup
    //   5544: bipush #35
    //   5546: sipush #520
    //   5549: iastore
    //   5550: dup
    //   5551: bipush #36
    //   5553: ldc 131072
    //   5555: iastore
    //   5556: dup
    //   5557: bipush #37
    //   5559: ldc 134349312
    //   5561: iastore
    //   5562: dup
    //   5563: bipush #38
    //   5565: ldc 134218240
    //   5567: iastore
    //   5568: dup
    //   5569: bipush #39
    //   5571: iconst_0
    //   5572: iastore
    //   5573: dup
    //   5574: bipush #40
    //   5576: sipush #512
    //   5579: iastore
    //   5580: dup
    //   5581: bipush #41
    //   5583: ldc 131080
    //   5585: iastore
    //   5586: dup
    //   5587: bipush #42
    //   5589: ldc 134349320
    //   5591: iastore
    //   5592: dup
    //   5593: bipush #43
    //   5595: ldc 134218240
    //   5597: iastore
    //   5598: dup
    //   5599: bipush #44
    //   5601: ldc 134217736
    //   5603: iastore
    //   5604: dup
    //   5605: bipush #45
    //   5607: sipush #512
    //   5610: iastore
    //   5611: dup
    //   5612: bipush #46
    //   5614: iconst_0
    //   5615: iastore
    //   5616: dup
    //   5617: bipush #47
    //   5619: ldc 134348808
    //   5621: iastore
    //   5622: dup
    //   5623: bipush #48
    //   5625: ldc 134218248
    //   5627: iastore
    //   5628: dup
    //   5629: bipush #49
    //   5631: ldc 131072
    //   5633: iastore
    //   5634: dup
    //   5635: bipush #50
    //   5637: ldc 134217728
    //   5639: iastore
    //   5640: dup
    //   5641: bipush #51
    //   5643: ldc 134349320
    //   5645: iastore
    //   5646: dup
    //   5647: bipush #52
    //   5649: bipush #8
    //   5651: iastore
    //   5652: dup
    //   5653: bipush #53
    //   5655: ldc 131592
    //   5657: iastore
    //   5658: dup
    //   5659: bipush #54
    //   5661: ldc 131584
    //   5663: iastore
    //   5664: dup
    //   5665: bipush #55
    //   5667: ldc 134217736
    //   5669: iastore
    //   5670: dup
    //   5671: bipush #56
    //   5673: ldc 134348800
    //   5675: iastore
    //   5676: dup
    //   5677: bipush #57
    //   5679: ldc 134218248
    //   5681: iastore
    //   5682: dup
    //   5683: bipush #58
    //   5685: sipush #520
    //   5688: iastore
    //   5689: dup
    //   5690: bipush #59
    //   5692: ldc 134348800
    //   5694: iastore
    //   5695: dup
    //   5696: bipush #60
    //   5698: ldc 131592
    //   5700: iastore
    //   5701: dup
    //   5702: bipush #61
    //   5704: bipush #8
    //   5706: iastore
    //   5707: dup
    //   5708: bipush #62
    //   5710: ldc 134348808
    //   5712: iastore
    //   5713: dup
    //   5714: bipush #63
    //   5716: ldc 131584
    //   5718: iastore
    //   5719: astore #8
    //   5721: bipush #64
    //   5723: newarray int
    //   5725: dup
    //   5726: iconst_0
    //   5727: ldc 8396801
    //   5729: iastore
    //   5730: dup
    //   5731: iconst_1
    //   5732: sipush #8321
    //   5735: iastore
    //   5736: dup
    //   5737: iconst_2
    //   5738: sipush #8321
    //   5741: iastore
    //   5742: dup
    //   5743: iconst_3
    //   5744: sipush #128
    //   5747: iastore
    //   5748: dup
    //   5749: iconst_4
    //   5750: ldc 8396928
    //   5752: iastore
    //   5753: dup
    //   5754: iconst_5
    //   5755: ldc 8388737
    //   5757: iastore
    //   5758: dup
    //   5759: bipush #6
    //   5761: ldc 8388609
    //   5763: iastore
    //   5764: dup
    //   5765: bipush #7
    //   5767: sipush #8193
    //   5770: iastore
    //   5771: dup
    //   5772: bipush #8
    //   5774: iconst_0
    //   5775: iastore
    //   5776: dup
    //   5777: bipush #9
    //   5779: ldc 8396800
    //   5781: iastore
    //   5782: dup
    //   5783: bipush #10
    //   5785: ldc 8396800
    //   5787: iastore
    //   5788: dup
    //   5789: bipush #11
    //   5791: ldc 8396929
    //   5793: iastore
    //   5794: dup
    //   5795: bipush #12
    //   5797: sipush #129
    //   5800: iastore
    //   5801: dup
    //   5802: bipush #13
    //   5804: iconst_0
    //   5805: iastore
    //   5806: dup
    //   5807: bipush #14
    //   5809: ldc 8388736
    //   5811: iastore
    //   5812: dup
    //   5813: bipush #15
    //   5815: ldc 8388609
    //   5817: iastore
    //   5818: dup
    //   5819: bipush #16
    //   5821: iconst_1
    //   5822: iastore
    //   5823: dup
    //   5824: bipush #17
    //   5826: sipush #8192
    //   5829: iastore
    //   5830: dup
    //   5831: bipush #18
    //   5833: ldc 8388608
    //   5835: iastore
    //   5836: dup
    //   5837: bipush #19
    //   5839: ldc 8396801
    //   5841: iastore
    //   5842: dup
    //   5843: bipush #20
    //   5845: sipush #128
    //   5848: iastore
    //   5849: dup
    //   5850: bipush #21
    //   5852: ldc 8388608
    //   5854: iastore
    //   5855: dup
    //   5856: bipush #22
    //   5858: sipush #8193
    //   5861: iastore
    //   5862: dup
    //   5863: bipush #23
    //   5865: sipush #8320
    //   5868: iastore
    //   5869: dup
    //   5870: bipush #24
    //   5872: ldc 8388737
    //   5874: iastore
    //   5875: dup
    //   5876: bipush #25
    //   5878: iconst_1
    //   5879: iastore
    //   5880: dup
    //   5881: bipush #26
    //   5883: sipush #8320
    //   5886: iastore
    //   5887: dup
    //   5888: bipush #27
    //   5890: ldc 8388736
    //   5892: iastore
    //   5893: dup
    //   5894: bipush #28
    //   5896: sipush #8192
    //   5899: iastore
    //   5900: dup
    //   5901: bipush #29
    //   5903: ldc 8396928
    //   5905: iastore
    //   5906: dup
    //   5907: bipush #30
    //   5909: ldc 8396929
    //   5911: iastore
    //   5912: dup
    //   5913: bipush #31
    //   5915: sipush #129
    //   5918: iastore
    //   5919: dup
    //   5920: bipush #32
    //   5922: ldc 8388736
    //   5924: iastore
    //   5925: dup
    //   5926: bipush #33
    //   5928: ldc 8388609
    //   5930: iastore
    //   5931: dup
    //   5932: bipush #34
    //   5934: ldc 8396800
    //   5936: iastore
    //   5937: dup
    //   5938: bipush #35
    //   5940: ldc 8396929
    //   5942: iastore
    //   5943: dup
    //   5944: bipush #36
    //   5946: sipush #129
    //   5949: iastore
    //   5950: dup
    //   5951: bipush #37
    //   5953: iconst_0
    //   5954: iastore
    //   5955: dup
    //   5956: bipush #38
    //   5958: iconst_0
    //   5959: iastore
    //   5960: dup
    //   5961: bipush #39
    //   5963: ldc 8396800
    //   5965: iastore
    //   5966: dup
    //   5967: bipush #40
    //   5969: sipush #8320
    //   5972: iastore
    //   5973: dup
    //   5974: bipush #41
    //   5976: ldc 8388736
    //   5978: iastore
    //   5979: dup
    //   5980: bipush #42
    //   5982: ldc 8388737
    //   5984: iastore
    //   5985: dup
    //   5986: bipush #43
    //   5988: iconst_1
    //   5989: iastore
    //   5990: dup
    //   5991: bipush #44
    //   5993: ldc 8396801
    //   5995: iastore
    //   5996: dup
    //   5997: bipush #45
    //   5999: sipush #8321
    //   6002: iastore
    //   6003: dup
    //   6004: bipush #46
    //   6006: sipush #8321
    //   6009: iastore
    //   6010: dup
    //   6011: bipush #47
    //   6013: sipush #128
    //   6016: iastore
    //   6017: dup
    //   6018: bipush #48
    //   6020: ldc 8396929
    //   6022: iastore
    //   6023: dup
    //   6024: bipush #49
    //   6026: sipush #129
    //   6029: iastore
    //   6030: dup
    //   6031: bipush #50
    //   6033: iconst_1
    //   6034: iastore
    //   6035: dup
    //   6036: bipush #51
    //   6038: sipush #8192
    //   6041: iastore
    //   6042: dup
    //   6043: bipush #52
    //   6045: ldc 8388609
    //   6047: iastore
    //   6048: dup
    //   6049: bipush #53
    //   6051: sipush #8193
    //   6054: iastore
    //   6055: dup
    //   6056: bipush #54
    //   6058: ldc 8396928
    //   6060: iastore
    //   6061: dup
    //   6062: bipush #55
    //   6064: ldc 8388737
    //   6066: iastore
    //   6067: dup
    //   6068: bipush #56
    //   6070: sipush #8193
    //   6073: iastore
    //   6074: dup
    //   6075: bipush #57
    //   6077: sipush #8320
    //   6080: iastore
    //   6081: dup
    //   6082: bipush #58
    //   6084: ldc 8388608
    //   6086: iastore
    //   6087: dup
    //   6088: bipush #59
    //   6090: ldc 8396801
    //   6092: iastore
    //   6093: dup
    //   6094: bipush #60
    //   6096: sipush #128
    //   6099: iastore
    //   6100: dup
    //   6101: bipush #61
    //   6103: ldc 8388608
    //   6105: iastore
    //   6106: dup
    //   6107: bipush #62
    //   6109: sipush #8192
    //   6112: iastore
    //   6113: dup
    //   6114: bipush #63
    //   6116: ldc 8396928
    //   6118: iastore
    //   6119: astore #9
    //   6121: bipush #64
    //   6123: newarray int
    //   6125: dup
    //   6126: iconst_0
    //   6127: sipush #256
    //   6130: iastore
    //   6131: dup
    //   6132: iconst_1
    //   6133: ldc 34078976
    //   6135: iastore
    //   6136: dup
    //   6137: iconst_2
    //   6138: ldc 34078720
    //   6140: iastore
    //   6141: dup
    //   6142: iconst_3
    //   6143: ldc 1107296512
    //   6145: iastore
    //   6146: dup
    //   6147: iconst_4
    //   6148: ldc 524288
    //   6150: iastore
    //   6151: dup
    //   6152: iconst_5
    //   6153: sipush #256
    //   6156: iastore
    //   6157: dup
    //   6158: bipush #6
    //   6160: ldc 1073741824
    //   6162: iastore
    //   6163: dup
    //   6164: bipush #7
    //   6166: ldc 34078720
    //   6168: iastore
    //   6169: dup
    //   6170: bipush #8
    //   6172: ldc 1074266368
    //   6174: iastore
    //   6175: dup
    //   6176: bipush #9
    //   6178: ldc 524288
    //   6180: iastore
    //   6181: dup
    //   6182: bipush #10
    //   6184: ldc 33554688
    //   6186: iastore
    //   6187: dup
    //   6188: bipush #11
    //   6190: ldc 1074266368
    //   6192: iastore
    //   6193: dup
    //   6194: bipush #12
    //   6196: ldc 1107296512
    //   6198: iastore
    //   6199: dup
    //   6200: bipush #13
    //   6202: ldc 1107820544
    //   6204: iastore
    //   6205: dup
    //   6206: bipush #14
    //   6208: ldc 524544
    //   6210: iastore
    //   6211: dup
    //   6212: bipush #15
    //   6214: ldc 1073741824
    //   6216: iastore
    //   6217: dup
    //   6218: bipush #16
    //   6220: ldc 33554432
    //   6222: iastore
    //   6223: dup
    //   6224: bipush #17
    //   6226: ldc 1074266112
    //   6228: iastore
    //   6229: dup
    //   6230: bipush #18
    //   6232: ldc 1074266112
    //   6234: iastore
    //   6235: dup
    //   6236: bipush #19
    //   6238: iconst_0
    //   6239: iastore
    //   6240: dup
    //   6241: bipush #20
    //   6243: ldc 1073742080
    //   6245: iastore
    //   6246: dup
    //   6247: bipush #21
    //   6249: ldc 1107820800
    //   6251: iastore
    //   6252: dup
    //   6253: bipush #22
    //   6255: ldc 1107820800
    //   6257: iastore
    //   6258: dup
    //   6259: bipush #23
    //   6261: ldc 33554688
    //   6263: iastore
    //   6264: dup
    //   6265: bipush #24
    //   6267: ldc 1107820544
    //   6269: iastore
    //   6270: dup
    //   6271: bipush #25
    //   6273: ldc 1073742080
    //   6275: iastore
    //   6276: dup
    //   6277: bipush #26
    //   6279: iconst_0
    //   6280: iastore
    //   6281: dup
    //   6282: bipush #27
    //   6284: ldc 1107296256
    //   6286: iastore
    //   6287: dup
    //   6288: bipush #28
    //   6290: ldc 34078976
    //   6292: iastore
    //   6293: dup
    //   6294: bipush #29
    //   6296: ldc 33554432
    //   6298: iastore
    //   6299: dup
    //   6300: bipush #30
    //   6302: ldc 1107296256
    //   6304: iastore
    //   6305: dup
    //   6306: bipush #31
    //   6308: ldc 524544
    //   6310: iastore
    //   6311: dup
    //   6312: bipush #32
    //   6314: ldc 524288
    //   6316: iastore
    //   6317: dup
    //   6318: bipush #33
    //   6320: ldc 1107296512
    //   6322: iastore
    //   6323: dup
    //   6324: bipush #34
    //   6326: sipush #256
    //   6329: iastore
    //   6330: dup
    //   6331: bipush #35
    //   6333: ldc 33554432
    //   6335: iastore
    //   6336: dup
    //   6337: bipush #36
    //   6339: ldc 1073741824
    //   6341: iastore
    //   6342: dup
    //   6343: bipush #37
    //   6345: ldc 34078720
    //   6347: iastore
    //   6348: dup
    //   6349: bipush #38
    //   6351: ldc 1107296512
    //   6353: iastore
    //   6354: dup
    //   6355: bipush #39
    //   6357: ldc 1074266368
    //   6359: iastore
    //   6360: dup
    //   6361: bipush #40
    //   6363: ldc 33554688
    //   6365: iastore
    //   6366: dup
    //   6367: bipush #41
    //   6369: ldc 1073741824
    //   6371: iastore
    //   6372: dup
    //   6373: bipush #42
    //   6375: ldc 1107820544
    //   6377: iastore
    //   6378: dup
    //   6379: bipush #43
    //   6381: ldc 34078976
    //   6383: iastore
    //   6384: dup
    //   6385: bipush #44
    //   6387: ldc 1074266368
    //   6389: iastore
    //   6390: dup
    //   6391: bipush #45
    //   6393: sipush #256
    //   6396: iastore
    //   6397: dup
    //   6398: bipush #46
    //   6400: ldc 33554432
    //   6402: iastore
    //   6403: dup
    //   6404: bipush #47
    //   6406: ldc 1107820544
    //   6408: iastore
    //   6409: dup
    //   6410: bipush #48
    //   6412: ldc 1107820800
    //   6414: iastore
    //   6415: dup
    //   6416: bipush #49
    //   6418: ldc 524544
    //   6420: iastore
    //   6421: dup
    //   6422: bipush #50
    //   6424: ldc 1107296256
    //   6426: iastore
    //   6427: dup
    //   6428: bipush #51
    //   6430: ldc 1107820800
    //   6432: iastore
    //   6433: dup
    //   6434: bipush #52
    //   6436: ldc 34078720
    //   6438: iastore
    //   6439: dup
    //   6440: bipush #53
    //   6442: iconst_0
    //   6443: iastore
    //   6444: dup
    //   6445: bipush #54
    //   6447: ldc 1074266112
    //   6449: iastore
    //   6450: dup
    //   6451: bipush #55
    //   6453: ldc 1107296256
    //   6455: iastore
    //   6456: dup
    //   6457: bipush #56
    //   6459: ldc 524544
    //   6461: iastore
    //   6462: dup
    //   6463: bipush #57
    //   6465: ldc 33554688
    //   6467: iastore
    //   6468: dup
    //   6469: bipush #58
    //   6471: ldc 1073742080
    //   6473: iastore
    //   6474: dup
    //   6475: bipush #59
    //   6477: ldc 524288
    //   6479: iastore
    //   6480: dup
    //   6481: bipush #60
    //   6483: iconst_0
    //   6484: iastore
    //   6485: dup
    //   6486: bipush #61
    //   6488: ldc 1074266112
    //   6490: iastore
    //   6491: dup
    //   6492: bipush #62
    //   6494: ldc 34078976
    //   6496: iastore
    //   6497: dup
    //   6498: bipush #63
    //   6500: ldc 1073742080
    //   6502: iastore
    //   6503: astore #10
    //   6505: bipush #64
    //   6507: newarray int
    //   6509: dup
    //   6510: iconst_0
    //   6511: ldc 536870928
    //   6513: iastore
    //   6514: dup
    //   6515: iconst_1
    //   6516: ldc 541065216
    //   6518: iastore
    //   6519: dup
    //   6520: iconst_2
    //   6521: sipush #16384
    //   6524: iastore
    //   6525: dup
    //   6526: iconst_3
    //   6527: ldc 541081616
    //   6529: iastore
    //   6530: dup
    //   6531: iconst_4
    //   6532: ldc 541065216
    //   6534: iastore
    //   6535: dup
    //   6536: iconst_5
    //   6537: bipush #16
    //   6539: iastore
    //   6540: dup
    //   6541: bipush #6
    //   6543: ldc 541081616
    //   6545: iastore
    //   6546: dup
    //   6547: bipush #7
    //   6549: ldc 4194304
    //   6551: iastore
    //   6552: dup
    //   6553: bipush #8
    //   6555: ldc 536887296
    //   6557: iastore
    //   6558: dup
    //   6559: bipush #9
    //   6561: ldc 4210704
    //   6563: iastore
    //   6564: dup
    //   6565: bipush #10
    //   6567: ldc 4194304
    //   6569: iastore
    //   6570: dup
    //   6571: bipush #11
    //   6573: ldc 536870928
    //   6575: iastore
    //   6576: dup
    //   6577: bipush #12
    //   6579: ldc 4194320
    //   6581: iastore
    //   6582: dup
    //   6583: bipush #13
    //   6585: ldc 536887296
    //   6587: iastore
    //   6588: dup
    //   6589: bipush #14
    //   6591: ldc 536870912
    //   6593: iastore
    //   6594: dup
    //   6595: bipush #15
    //   6597: sipush #16400
    //   6600: iastore
    //   6601: dup
    //   6602: bipush #16
    //   6604: iconst_0
    //   6605: iastore
    //   6606: dup
    //   6607: bipush #17
    //   6609: ldc 4194320
    //   6611: iastore
    //   6612: dup
    //   6613: bipush #18
    //   6615: ldc 536887312
    //   6617: iastore
    //   6618: dup
    //   6619: bipush #19
    //   6621: sipush #16384
    //   6624: iastore
    //   6625: dup
    //   6626: bipush #20
    //   6628: ldc 4210688
    //   6630: iastore
    //   6631: dup
    //   6632: bipush #21
    //   6634: ldc 536887312
    //   6636: iastore
    //   6637: dup
    //   6638: bipush #22
    //   6640: bipush #16
    //   6642: iastore
    //   6643: dup
    //   6644: bipush #23
    //   6646: ldc 541065232
    //   6648: iastore
    //   6649: dup
    //   6650: bipush #24
    //   6652: ldc 541065232
    //   6654: iastore
    //   6655: dup
    //   6656: bipush #25
    //   6658: iconst_0
    //   6659: iastore
    //   6660: dup
    //   6661: bipush #26
    //   6663: ldc 4210704
    //   6665: iastore
    //   6666: dup
    //   6667: bipush #27
    //   6669: ldc 541081600
    //   6671: iastore
    //   6672: dup
    //   6673: bipush #28
    //   6675: sipush #16400
    //   6678: iastore
    //   6679: dup
    //   6680: bipush #29
    //   6682: ldc 4210688
    //   6684: iastore
    //   6685: dup
    //   6686: bipush #30
    //   6688: ldc 541081600
    //   6690: iastore
    //   6691: dup
    //   6692: bipush #31
    //   6694: ldc 536870912
    //   6696: iastore
    //   6697: dup
    //   6698: bipush #32
    //   6700: ldc 536887296
    //   6702: iastore
    //   6703: dup
    //   6704: bipush #33
    //   6706: bipush #16
    //   6708: iastore
    //   6709: dup
    //   6710: bipush #34
    //   6712: ldc 541065232
    //   6714: iastore
    //   6715: dup
    //   6716: bipush #35
    //   6718: ldc 4210688
    //   6720: iastore
    //   6721: dup
    //   6722: bipush #36
    //   6724: ldc 541081616
    //   6726: iastore
    //   6727: dup
    //   6728: bipush #37
    //   6730: ldc 4194304
    //   6732: iastore
    //   6733: dup
    //   6734: bipush #38
    //   6736: sipush #16400
    //   6739: iastore
    //   6740: dup
    //   6741: bipush #39
    //   6743: ldc 536870928
    //   6745: iastore
    //   6746: dup
    //   6747: bipush #40
    //   6749: ldc 4194304
    //   6751: iastore
    //   6752: dup
    //   6753: bipush #41
    //   6755: ldc 536887296
    //   6757: iastore
    //   6758: dup
    //   6759: bipush #42
    //   6761: ldc 536870912
    //   6763: iastore
    //   6764: dup
    //   6765: bipush #43
    //   6767: sipush #16400
    //   6770: iastore
    //   6771: dup
    //   6772: bipush #44
    //   6774: ldc 536870928
    //   6776: iastore
    //   6777: dup
    //   6778: bipush #45
    //   6780: ldc 541081616
    //   6782: iastore
    //   6783: dup
    //   6784: bipush #46
    //   6786: ldc 4210688
    //   6788: iastore
    //   6789: dup
    //   6790: bipush #47
    //   6792: ldc 541065216
    //   6794: iastore
    //   6795: dup
    //   6796: bipush #48
    //   6798: ldc 4210704
    //   6800: iastore
    //   6801: dup
    //   6802: bipush #49
    //   6804: ldc 541081600
    //   6806: iastore
    //   6807: dup
    //   6808: bipush #50
    //   6810: iconst_0
    //   6811: iastore
    //   6812: dup
    //   6813: bipush #51
    //   6815: ldc 541065232
    //   6817: iastore
    //   6818: dup
    //   6819: bipush #52
    //   6821: bipush #16
    //   6823: iastore
    //   6824: dup
    //   6825: bipush #53
    //   6827: sipush #16384
    //   6830: iastore
    //   6831: dup
    //   6832: bipush #54
    //   6834: ldc 541065216
    //   6836: iastore
    //   6837: dup
    //   6838: bipush #55
    //   6840: ldc 4210704
    //   6842: iastore
    //   6843: dup
    //   6844: bipush #56
    //   6846: sipush #16384
    //   6849: iastore
    //   6850: dup
    //   6851: bipush #57
    //   6853: ldc 4194320
    //   6855: iastore
    //   6856: dup
    //   6857: bipush #58
    //   6859: ldc 536887312
    //   6861: iastore
    //   6862: dup
    //   6863: bipush #59
    //   6865: iconst_0
    //   6866: iastore
    //   6867: dup
    //   6868: bipush #60
    //   6870: ldc 541081600
    //   6872: iastore
    //   6873: dup
    //   6874: bipush #61
    //   6876: ldc 536870912
    //   6878: iastore
    //   6879: dup
    //   6880: bipush #62
    //   6882: ldc 4194320
    //   6884: iastore
    //   6885: dup
    //   6886: bipush #63
    //   6888: ldc 536887312
    //   6890: iastore
    //   6891: astore #11
    //   6893: bipush #64
    //   6895: newarray int
    //   6897: dup
    //   6898: iconst_0
    //   6899: ldc 2097152
    //   6901: iastore
    //   6902: dup
    //   6903: iconst_1
    //   6904: ldc 69206018
    //   6906: iastore
    //   6907: dup
    //   6908: iconst_2
    //   6909: ldc 67110914
    //   6911: iastore
    //   6912: dup
    //   6913: iconst_3
    //   6914: iconst_0
    //   6915: iastore
    //   6916: dup
    //   6917: iconst_4
    //   6918: sipush #2048
    //   6921: iastore
    //   6922: dup
    //   6923: iconst_5
    //   6924: ldc 67110914
    //   6926: iastore
    //   6927: dup
    //   6928: bipush #6
    //   6930: ldc 2099202
    //   6932: iastore
    //   6933: dup
    //   6934: bipush #7
    //   6936: ldc 69208064
    //   6938: iastore
    //   6939: dup
    //   6940: bipush #8
    //   6942: ldc 69208066
    //   6944: iastore
    //   6945: dup
    //   6946: bipush #9
    //   6948: ldc 2097152
    //   6950: iastore
    //   6951: dup
    //   6952: bipush #10
    //   6954: iconst_0
    //   6955: iastore
    //   6956: dup
    //   6957: bipush #11
    //   6959: ldc 67108866
    //   6961: iastore
    //   6962: dup
    //   6963: bipush #12
    //   6965: iconst_2
    //   6966: iastore
    //   6967: dup
    //   6968: bipush #13
    //   6970: ldc 67108864
    //   6972: iastore
    //   6973: dup
    //   6974: bipush #14
    //   6976: ldc 69206018
    //   6978: iastore
    //   6979: dup
    //   6980: bipush #15
    //   6982: sipush #2050
    //   6985: iastore
    //   6986: dup
    //   6987: bipush #16
    //   6989: ldc 67110912
    //   6991: iastore
    //   6992: dup
    //   6993: bipush #17
    //   6995: ldc 2099202
    //   6997: iastore
    //   6998: dup
    //   6999: bipush #18
    //   7001: ldc 2097154
    //   7003: iastore
    //   7004: dup
    //   7005: bipush #19
    //   7007: ldc 67110912
    //   7009: iastore
    //   7010: dup
    //   7011: bipush #20
    //   7013: ldc 67108866
    //   7015: iastore
    //   7016: dup
    //   7017: bipush #21
    //   7019: ldc 69206016
    //   7021: iastore
    //   7022: dup
    //   7023: bipush #22
    //   7025: ldc 69208064
    //   7027: iastore
    //   7028: dup
    //   7029: bipush #23
    //   7031: ldc 2097154
    //   7033: iastore
    //   7034: dup
    //   7035: bipush #24
    //   7037: ldc 69206016
    //   7039: iastore
    //   7040: dup
    //   7041: bipush #25
    //   7043: sipush #2048
    //   7046: iastore
    //   7047: dup
    //   7048: bipush #26
    //   7050: sipush #2050
    //   7053: iastore
    //   7054: dup
    //   7055: bipush #27
    //   7057: ldc 69208066
    //   7059: iastore
    //   7060: dup
    //   7061: bipush #28
    //   7063: ldc 2099200
    //   7065: iastore
    //   7066: dup
    //   7067: bipush #29
    //   7069: iconst_2
    //   7070: iastore
    //   7071: dup
    //   7072: bipush #30
    //   7074: ldc 67108864
    //   7076: iastore
    //   7077: dup
    //   7078: bipush #31
    //   7080: ldc 2099200
    //   7082: iastore
    //   7083: dup
    //   7084: bipush #32
    //   7086: ldc 67108864
    //   7088: iastore
    //   7089: dup
    //   7090: bipush #33
    //   7092: ldc 2099200
    //   7094: iastore
    //   7095: dup
    //   7096: bipush #34
    //   7098: ldc 2097152
    //   7100: iastore
    //   7101: dup
    //   7102: bipush #35
    //   7104: ldc 67110914
    //   7106: iastore
    //   7107: dup
    //   7108: bipush #36
    //   7110: ldc 67110914
    //   7112: iastore
    //   7113: dup
    //   7114: bipush #37
    //   7116: ldc 69206018
    //   7118: iastore
    //   7119: dup
    //   7120: bipush #38
    //   7122: ldc 69206018
    //   7124: iastore
    //   7125: dup
    //   7126: bipush #39
    //   7128: iconst_2
    //   7129: iastore
    //   7130: dup
    //   7131: bipush #40
    //   7133: ldc 2097154
    //   7135: iastore
    //   7136: dup
    //   7137: bipush #41
    //   7139: ldc 67108864
    //   7141: iastore
    //   7142: dup
    //   7143: bipush #42
    //   7145: ldc 67110912
    //   7147: iastore
    //   7148: dup
    //   7149: bipush #43
    //   7151: ldc 2097152
    //   7153: iastore
    //   7154: dup
    //   7155: bipush #44
    //   7157: ldc 69208064
    //   7159: iastore
    //   7160: dup
    //   7161: bipush #45
    //   7163: sipush #2050
    //   7166: iastore
    //   7167: dup
    //   7168: bipush #46
    //   7170: ldc 2099202
    //   7172: iastore
    //   7173: dup
    //   7174: bipush #47
    //   7176: ldc 69208064
    //   7178: iastore
    //   7179: dup
    //   7180: bipush #48
    //   7182: sipush #2050
    //   7185: iastore
    //   7186: dup
    //   7187: bipush #49
    //   7189: ldc 67108866
    //   7191: iastore
    //   7192: dup
    //   7193: bipush #50
    //   7195: ldc 69208066
    //   7197: iastore
    //   7198: dup
    //   7199: bipush #51
    //   7201: ldc 69206016
    //   7203: iastore
    //   7204: dup
    //   7205: bipush #52
    //   7207: ldc 2099200
    //   7209: iastore
    //   7210: dup
    //   7211: bipush #53
    //   7213: iconst_0
    //   7214: iastore
    //   7215: dup
    //   7216: bipush #54
    //   7218: iconst_2
    //   7219: iastore
    //   7220: dup
    //   7221: bipush #55
    //   7223: ldc 69208066
    //   7225: iastore
    //   7226: dup
    //   7227: bipush #56
    //   7229: iconst_0
    //   7230: iastore
    //   7231: dup
    //   7232: bipush #57
    //   7234: ldc 2099202
    //   7236: iastore
    //   7237: dup
    //   7238: bipush #58
    //   7240: ldc 69206016
    //   7242: iastore
    //   7243: dup
    //   7244: bipush #59
    //   7246: sipush #2048
    //   7249: iastore
    //   7250: dup
    //   7251: bipush #60
    //   7253: ldc 67108866
    //   7255: iastore
    //   7256: dup
    //   7257: bipush #61
    //   7259: ldc 67110912
    //   7261: iastore
    //   7262: dup
    //   7263: bipush #62
    //   7265: sipush #2048
    //   7268: iastore
    //   7269: dup
    //   7270: bipush #63
    //   7272: ldc 2097154
    //   7274: iastore
    //   7275: astore #12
    //   7277: bipush #64
    //   7279: newarray int
    //   7281: dup
    //   7282: iconst_0
    //   7283: ldc 268439616
    //   7285: iastore
    //   7286: dup
    //   7287: iconst_1
    //   7288: sipush #4096
    //   7291: iastore
    //   7292: dup
    //   7293: iconst_2
    //   7294: ldc 262144
    //   7296: iastore
    //   7297: dup
    //   7298: iconst_3
    //   7299: ldc 268701760
    //   7301: iastore
    //   7302: dup
    //   7303: iconst_4
    //   7304: ldc 268435456
    //   7306: iastore
    //   7307: dup
    //   7308: iconst_5
    //   7309: ldc 268439616
    //   7311: iastore
    //   7312: dup
    //   7313: bipush #6
    //   7315: bipush #64
    //   7317: iastore
    //   7318: dup
    //   7319: bipush #7
    //   7321: ldc 268435456
    //   7323: iastore
    //   7324: dup
    //   7325: bipush #8
    //   7327: ldc 262208
    //   7329: iastore
    //   7330: dup
    //   7331: bipush #9
    //   7333: ldc 268697600
    //   7335: iastore
    //   7336: dup
    //   7337: bipush #10
    //   7339: ldc 268701760
    //   7341: iastore
    //   7342: dup
    //   7343: bipush #11
    //   7345: ldc 266240
    //   7347: iastore
    //   7348: dup
    //   7349: bipush #12
    //   7351: ldc 268701696
    //   7353: iastore
    //   7354: dup
    //   7355: bipush #13
    //   7357: ldc 266304
    //   7359: iastore
    //   7360: dup
    //   7361: bipush #14
    //   7363: sipush #4096
    //   7366: iastore
    //   7367: dup
    //   7368: bipush #15
    //   7370: bipush #64
    //   7372: iastore
    //   7373: dup
    //   7374: bipush #16
    //   7376: ldc 268697600
    //   7378: iastore
    //   7379: dup
    //   7380: bipush #17
    //   7382: ldc 268435520
    //   7384: iastore
    //   7385: dup
    //   7386: bipush #18
    //   7388: ldc 268439552
    //   7390: iastore
    //   7391: dup
    //   7392: bipush #19
    //   7394: sipush #4160
    //   7397: iastore
    //   7398: dup
    //   7399: bipush #20
    //   7401: ldc 266240
    //   7403: iastore
    //   7404: dup
    //   7405: bipush #21
    //   7407: ldc 262208
    //   7409: iastore
    //   7410: dup
    //   7411: bipush #22
    //   7413: ldc 268697664
    //   7415: iastore
    //   7416: dup
    //   7417: bipush #23
    //   7419: ldc 268701696
    //   7421: iastore
    //   7422: dup
    //   7423: bipush #24
    //   7425: sipush #4160
    //   7428: iastore
    //   7429: dup
    //   7430: bipush #25
    //   7432: iconst_0
    //   7433: iastore
    //   7434: dup
    //   7435: bipush #26
    //   7437: iconst_0
    //   7438: iastore
    //   7439: dup
    //   7440: bipush #27
    //   7442: ldc 268697664
    //   7444: iastore
    //   7445: dup
    //   7446: bipush #28
    //   7448: ldc 268435520
    //   7450: iastore
    //   7451: dup
    //   7452: bipush #29
    //   7454: ldc 268439552
    //   7456: iastore
    //   7457: dup
    //   7458: bipush #30
    //   7460: ldc 266304
    //   7462: iastore
    //   7463: dup
    //   7464: bipush #31
    //   7466: ldc 262144
    //   7468: iastore
    //   7469: dup
    //   7470: bipush #32
    //   7472: ldc 266304
    //   7474: iastore
    //   7475: dup
    //   7476: bipush #33
    //   7478: ldc 262144
    //   7480: iastore
    //   7481: dup
    //   7482: bipush #34
    //   7484: ldc 268701696
    //   7486: iastore
    //   7487: dup
    //   7488: bipush #35
    //   7490: sipush #4096
    //   7493: iastore
    //   7494: dup
    //   7495: bipush #36
    //   7497: bipush #64
    //   7499: iastore
    //   7500: dup
    //   7501: bipush #37
    //   7503: ldc 268697664
    //   7505: iastore
    //   7506: dup
    //   7507: bipush #38
    //   7509: sipush #4096
    //   7512: iastore
    //   7513: dup
    //   7514: bipush #39
    //   7516: ldc 266304
    //   7518: iastore
    //   7519: dup
    //   7520: bipush #40
    //   7522: ldc 268439552
    //   7524: iastore
    //   7525: dup
    //   7526: bipush #41
    //   7528: bipush #64
    //   7530: iastore
    //   7531: dup
    //   7532: bipush #42
    //   7534: ldc 268435520
    //   7536: iastore
    //   7537: dup
    //   7538: bipush #43
    //   7540: ldc 268697600
    //   7542: iastore
    //   7543: dup
    //   7544: bipush #44
    //   7546: ldc 268697664
    //   7548: iastore
    //   7549: dup
    //   7550: bipush #45
    //   7552: ldc 268435456
    //   7554: iastore
    //   7555: dup
    //   7556: bipush #46
    //   7558: ldc 262144
    //   7560: iastore
    //   7561: dup
    //   7562: bipush #47
    //   7564: ldc 268439616
    //   7566: iastore
    //   7567: dup
    //   7568: bipush #48
    //   7570: iconst_0
    //   7571: iastore
    //   7572: dup
    //   7573: bipush #49
    //   7575: ldc 268701760
    //   7577: iastore
    //   7578: dup
    //   7579: bipush #50
    //   7581: ldc 262208
    //   7583: iastore
    //   7584: dup
    //   7585: bipush #51
    //   7587: ldc 268435520
    //   7589: iastore
    //   7590: dup
    //   7591: bipush #52
    //   7593: ldc 268697600
    //   7595: iastore
    //   7596: dup
    //   7597: bipush #53
    //   7599: ldc 268439552
    //   7601: iastore
    //   7602: dup
    //   7603: bipush #54
    //   7605: ldc 268439616
    //   7607: iastore
    //   7608: dup
    //   7609: bipush #55
    //   7611: iconst_0
    //   7612: iastore
    //   7613: dup
    //   7614: bipush #56
    //   7616: ldc 268701760
    //   7618: iastore
    //   7619: dup
    //   7620: bipush #57
    //   7622: ldc 266240
    //   7624: iastore
    //   7625: dup
    //   7626: bipush #58
    //   7628: ldc 266240
    //   7630: iastore
    //   7631: dup
    //   7632: bipush #59
    //   7634: sipush #4160
    //   7637: iastore
    //   7638: dup
    //   7639: bipush #60
    //   7641: sipush #4160
    //   7644: iastore
    //   7645: dup
    //   7646: bipush #61
    //   7648: ldc 262208
    //   7650: iastore
    //   7651: dup
    //   7652: bipush #62
    //   7654: ldc 268435456
    //   7656: iastore
    //   7657: dup
    //   7658: bipush #63
    //   7660: ldc 268701696
    //   7662: iastore
    //   7663: astore #13
    //   7665: aload_3
    //   7666: arraylength
    //   7667: istore #14
    //   7669: iload #14
    //   7671: bipush #8
    //   7673: irem
    //   7674: ifeq -> 7698
    //   7677: new java/lang/Exception
    //   7680: dup
    //   7681: sipush #2011
    //   7684: sipush #17747
    //   7687: invokestatic a : (II)Ljava/lang/String;
    //   7690: invokespecial <init> : (Ljava/lang/String;)V
    //   7693: athrow
    //   7694: invokestatic a : (Ljava/lang/Throwable;)Ljava/lang/Throwable;
    //   7697: athrow
    //   7698: iconst_2
    //   7699: newarray int
    //   7701: astore #15
    //   7703: iload #14
    //   7705: newarray byte
    //   7707: astore #16
    //   7709: iload #14
    //   7711: bipush #8
    //   7713: idiv
    //   7714: istore #17
    //   7716: iconst_0
    //   7717: istore #18
    //   7719: iload #18
    //   7721: iload #17
    //   7723: if_icmpge -> 8637
    //   7726: iload #18
    //   7728: bipush #8
    //   7730: imul
    //   7731: istore #19
    //   7733: iconst_0
    //   7734: istore #20
    //   7736: iload #20
    //   7738: iconst_2
    //   7739: if_icmpge -> 7824
    //   7742: aload #15
    //   7744: iload #20
    //   7746: aload_3
    //   7747: iload #19
    //   7749: iload #20
    //   7751: iconst_4
    //   7752: imul
    //   7753: iadd
    //   7754: baload
    //   7755: sipush #255
    //   7758: iand
    //   7759: bipush #24
    //   7761: ishl
    //   7762: aload_3
    //   7763: iload #19
    //   7765: iload #20
    //   7767: iconst_4
    //   7768: imul
    //   7769: iadd
    //   7770: iconst_1
    //   7771: iadd
    //   7772: baload
    //   7773: sipush #255
    //   7776: iand
    //   7777: bipush #16
    //   7779: ishl
    //   7780: ior
    //   7781: aload_3
    //   7782: iload #19
    //   7784: iload #20
    //   7786: iconst_4
    //   7787: imul
    //   7788: iadd
    //   7789: iconst_2
    //   7790: iadd
    //   7791: baload
    //   7792: sipush #255
    //   7795: iand
    //   7796: bipush #8
    //   7798: ishl
    //   7799: ior
    //   7800: aload_3
    //   7801: iload #19
    //   7803: iload #20
    //   7805: iconst_4
    //   7806: imul
    //   7807: iadd
    //   7808: iconst_3
    //   7809: iadd
    //   7810: baload
    //   7811: sipush #255
    //   7814: iand
    //   7815: ior
    //   7816: iastore
    //   7817: iinc #20, 1
    //   7820: iload_2
    //   7821: ifeq -> 7736
    //   7824: iconst_0
    //   7825: istore #25
    //   7827: aload #15
    //   7829: iconst_0
    //   7830: iaload
    //   7831: istore #23
    //   7833: aload #15
    //   7835: iconst_1
    //   7836: iaload
    //   7837: istore #22
    //   7839: iload #23
    //   7841: iconst_4
    //   7842: iushr
    //   7843: iload #22
    //   7845: ixor
    //   7846: ldc 252645135
    //   7848: iand
    //   7849: istore #21
    //   7851: iload #22
    //   7853: iload #21
    //   7855: ixor
    //   7856: istore #22
    //   7858: iload #23
    //   7860: iload #21
    //   7862: iconst_4
    //   7863: ishl
    //   7864: ixor
    //   7865: istore #23
    //   7867: iload #23
    //   7869: bipush #16
    //   7871: iushr
    //   7872: iload #22
    //   7874: ixor
    //   7875: ldc 65535
    //   7877: iand
    //   7878: istore #21
    //   7880: iload #22
    //   7882: iload #21
    //   7884: ixor
    //   7885: istore #22
    //   7887: iload #23
    //   7889: iload #21
    //   7891: bipush #16
    //   7893: ishl
    //   7894: ixor
    //   7895: istore #23
    //   7897: iload #22
    //   7899: iconst_2
    //   7900: iushr
    //   7901: iload #23
    //   7903: ixor
    //   7904: ldc 858993459
    //   7906: iand
    //   7907: istore #21
    //   7909: iload #23
    //   7911: iload #21
    //   7913: ixor
    //   7914: istore #23
    //   7916: iload #22
    //   7918: iload #21
    //   7920: iconst_2
    //   7921: ishl
    //   7922: ixor
    //   7923: istore #22
    //   7925: iload #22
    //   7927: bipush #8
    //   7929: iushr
    //   7930: iload #23
    //   7932: ixor
    //   7933: ldc 16711935
    //   7935: iand
    //   7936: istore #21
    //   7938: iload #23
    //   7940: iload #21
    //   7942: ixor
    //   7943: istore #23
    //   7945: iload #22
    //   7947: iload #21
    //   7949: bipush #8
    //   7951: ishl
    //   7952: ixor
    //   7953: istore #22
    //   7955: iload #22
    //   7957: iconst_1
    //   7958: ishl
    //   7959: iload #22
    //   7961: bipush #31
    //   7963: iushr
    //   7964: iconst_1
    //   7965: iand
    //   7966: ior
    //   7967: istore #22
    //   7969: iload #23
    //   7971: iload #22
    //   7973: ixor
    //   7974: ldc -1431655766
    //   7976: iand
    //   7977: istore #21
    //   7979: iload #23
    //   7981: iload #21
    //   7983: ixor
    //   7984: istore #23
    //   7986: iload #22
    //   7988: iload #21
    //   7990: ixor
    //   7991: istore #22
    //   7993: iload #23
    //   7995: iconst_1
    //   7996: ishl
    //   7997: iload #23
    //   7999: bipush #31
    //   8001: iushr
    //   8002: iconst_1
    //   8003: iand
    //   8004: ior
    //   8005: istore #23
    //   8007: iconst_0
    //   8008: istore #24
    //   8010: iload #24
    //   8012: bipush #8
    //   8014: if_icmpge -> 8352
    //   8017: iload #22
    //   8019: bipush #28
    //   8021: ishl
    //   8022: iload #22
    //   8024: iconst_4
    //   8025: iushr
    //   8026: ior
    //   8027: istore #21
    //   8029: iload #21
    //   8031: aload #5
    //   8033: iload #25
    //   8035: iinc #25, 1
    //   8038: iaload
    //   8039: ixor
    //   8040: istore #21
    //   8042: aload #12
    //   8044: iload #21
    //   8046: bipush #63
    //   8048: iand
    //   8049: iaload
    //   8050: istore #20
    //   8052: iload #20
    //   8054: aload #10
    //   8056: iload #21
    //   8058: bipush #8
    //   8060: iushr
    //   8061: bipush #63
    //   8063: iand
    //   8064: iaload
    //   8065: ior
    //   8066: istore #20
    //   8068: iload #20
    //   8070: aload #8
    //   8072: iload #21
    //   8074: bipush #16
    //   8076: iushr
    //   8077: bipush #63
    //   8079: iand
    //   8080: iaload
    //   8081: ior
    //   8082: istore #20
    //   8084: iload #20
    //   8086: aload #6
    //   8088: iload #21
    //   8090: bipush #24
    //   8092: iushr
    //   8093: bipush #63
    //   8095: iand
    //   8096: iaload
    //   8097: ior
    //   8098: istore #20
    //   8100: iload #22
    //   8102: aload #5
    //   8104: iload #25
    //   8106: iinc #25, 1
    //   8109: iaload
    //   8110: ixor
    //   8111: istore #21
    //   8113: iload #20
    //   8115: aload #13
    //   8117: iload #21
    //   8119: bipush #63
    //   8121: iand
    //   8122: iaload
    //   8123: ior
    //   8124: istore #20
    //   8126: iload #20
    //   8128: aload #11
    //   8130: iload #21
    //   8132: bipush #8
    //   8134: iushr
    //   8135: bipush #63
    //   8137: iand
    //   8138: iaload
    //   8139: ior
    //   8140: istore #20
    //   8142: iload #20
    //   8144: aload #9
    //   8146: iload #21
    //   8148: bipush #16
    //   8150: iushr
    //   8151: bipush #63
    //   8153: iand
    //   8154: iaload
    //   8155: ior
    //   8156: istore #20
    //   8158: iload #20
    //   8160: aload #7
    //   8162: iload #21
    //   8164: bipush #24
    //   8166: iushr
    //   8167: bipush #63
    //   8169: iand
    //   8170: iaload
    //   8171: ior
    //   8172: istore #20
    //   8174: iload #23
    //   8176: iload #20
    //   8178: ixor
    //   8179: istore #23
    //   8181: iload #23
    //   8183: bipush #28
    //   8185: ishl
    //   8186: iload #23
    //   8188: iconst_4
    //   8189: iushr
    //   8190: ior
    //   8191: istore #21
    //   8193: iload #21
    //   8195: aload #5
    //   8197: iload #25
    //   8199: iinc #25, 1
    //   8202: iaload
    //   8203: ixor
    //   8204: istore #21
    //   8206: aload #12
    //   8208: iload #21
    //   8210: bipush #63
    //   8212: iand
    //   8213: iaload
    //   8214: istore #20
    //   8216: iload #20
    //   8218: aload #10
    //   8220: iload #21
    //   8222: bipush #8
    //   8224: iushr
    //   8225: bipush #63
    //   8227: iand
    //   8228: iaload
    //   8229: ior
    //   8230: istore #20
    //   8232: iload #20
    //   8234: aload #8
    //   8236: iload #21
    //   8238: bipush #16
    //   8240: iushr
    //   8241: bipush #63
    //   8243: iand
    //   8244: iaload
    //   8245: ior
    //   8246: istore #20
    //   8248: iload #20
    //   8250: aload #6
    //   8252: iload #21
    //   8254: bipush #24
    //   8256: iushr
    //   8257: bipush #63
    //   8259: iand
    //   8260: iaload
    //   8261: ior
    //   8262: istore #20
    //   8264: iload #23
    //   8266: aload #5
    //   8268: iload #25
    //   8270: iinc #25, 1
    //   8273: iaload
    //   8274: ixor
    //   8275: istore #21
    //   8277: iload #20
    //   8279: aload #13
    //   8281: iload #21
    //   8283: bipush #63
    //   8285: iand
    //   8286: iaload
    //   8287: ior
    //   8288: istore #20
    //   8290: iload #20
    //   8292: aload #11
    //   8294: iload #21
    //   8296: bipush #8
    //   8298: iushr
    //   8299: bipush #63
    //   8301: iand
    //   8302: iaload
    //   8303: ior
    //   8304: istore #20
    //   8306: iload #20
    //   8308: aload #9
    //   8310: iload #21
    //   8312: bipush #16
    //   8314: iushr
    //   8315: bipush #63
    //   8317: iand
    //   8318: iaload
    //   8319: ior
    //   8320: istore #20
    //   8322: iload #20
    //   8324: aload #7
    //   8326: iload #21
    //   8328: bipush #24
    //   8330: iushr
    //   8331: bipush #63
    //   8333: iand
    //   8334: iaload
    //   8335: ior
    //   8336: istore #20
    //   8338: iload #22
    //   8340: iload #20
    //   8342: ixor
    //   8343: istore #22
    //   8345: iinc #24, 1
    //   8348: iload_2
    //   8349: ifeq -> 8010
    //   8352: iload #22
    //   8354: bipush #31
    //   8356: ishl
    //   8357: iload #22
    //   8359: iconst_1
    //   8360: iushr
    //   8361: ior
    //   8362: istore #22
    //   8364: iload #23
    //   8366: iload #22
    //   8368: ixor
    //   8369: ldc -1431655766
    //   8371: iand
    //   8372: istore #21
    //   8374: iload #23
    //   8376: iload #21
    //   8378: ixor
    //   8379: istore #23
    //   8381: iload #22
    //   8383: iload #21
    //   8385: ixor
    //   8386: istore #22
    //   8388: iload #23
    //   8390: bipush #31
    //   8392: ishl
    //   8393: iload #23
    //   8395: iconst_1
    //   8396: iushr
    //   8397: ior
    //   8398: istore #23
    //   8400: iload #23
    //   8402: bipush #8
    //   8404: iushr
    //   8405: iload #22
    //   8407: ixor
    //   8408: ldc 16711935
    //   8410: iand
    //   8411: istore #21
    //   8413: iload #22
    //   8415: iload #21
    //   8417: ixor
    //   8418: istore #22
    //   8420: iload #23
    //   8422: iload #21
    //   8424: bipush #8
    //   8426: ishl
    //   8427: ixor
    //   8428: istore #23
    //   8430: iload #23
    //   8432: iconst_2
    //   8433: iushr
    //   8434: iload #22
    //   8436: ixor
    //   8437: ldc 858993459
    //   8439: iand
    //   8440: istore #21
    //   8442: iload #22
    //   8444: iload #21
    //   8446: ixor
    //   8447: istore #22
    //   8449: iload #23
    //   8451: iload #21
    //   8453: iconst_2
    //   8454: ishl
    //   8455: ixor
    //   8456: istore #23
    //   8458: iload #22
    //   8460: bipush #16
    //   8462: iushr
    //   8463: iload #23
    //   8465: ixor
    //   8466: ldc 65535
    //   8468: iand
    //   8469: istore #21
    //   8471: iload #23
    //   8473: iload #21
    //   8475: ixor
    //   8476: istore #23
    //   8478: iload #22
    //   8480: iload #21
    //   8482: bipush #16
    //   8484: ishl
    //   8485: ixor
    //   8486: istore #22
    //   8488: iload #22
    //   8490: iconst_4
    //   8491: iushr
    //   8492: iload #23
    //   8494: ixor
    //   8495: ldc 252645135
    //   8497: iand
    //   8498: istore #21
    //   8500: iload #23
    //   8502: iload #21
    //   8504: ixor
    //   8505: istore #23
    //   8507: iload #22
    //   8509: iload #21
    //   8511: iconst_4
    //   8512: ishl
    //   8513: ixor
    //   8514: istore #22
    //   8516: aload #15
    //   8518: iconst_0
    //   8519: iload #22
    //   8521: iastore
    //   8522: aload #15
    //   8524: iconst_1
    //   8525: iload #23
    //   8527: iastore
    //   8528: iload #18
    //   8530: bipush #8
    //   8532: imul
    //   8533: istore #26
    //   8535: iconst_0
    //   8536: istore #27
    //   8538: iload #27
    //   8540: iconst_2
    //   8541: if_icmpge -> 8630
    //   8544: aload #16
    //   8546: iload #26
    //   8548: iload #27
    //   8550: iconst_4
    //   8551: imul
    //   8552: iadd
    //   8553: aload #15
    //   8555: iload #27
    //   8557: iaload
    //   8558: bipush #24
    //   8560: iushr
    //   8561: i2b
    //   8562: bastore
    //   8563: aload #16
    //   8565: iload #26
    //   8567: iload #27
    //   8569: iconst_4
    //   8570: imul
    //   8571: iadd
    //   8572: iconst_1
    //   8573: iadd
    //   8574: aload #15
    //   8576: iload #27
    //   8578: iaload
    //   8579: bipush #16
    //   8581: iushr
    //   8582: i2b
    //   8583: bastore
    //   8584: aload #16
    //   8586: iload #26
    //   8588: iload #27
    //   8590: iconst_4
    //   8591: imul
    //   8592: iadd
    //   8593: iconst_2
    //   8594: iadd
    //   8595: aload #15
    //   8597: iload #27
    //   8599: iaload
    //   8600: bipush #8
    //   8602: iushr
    //   8603: i2b
    //   8604: bastore
    //   8605: aload #16
    //   8607: iload #26
    //   8609: iload #27
    //   8611: iconst_4
    //   8612: imul
    //   8613: iadd
    //   8614: iconst_3
    //   8615: iadd
    //   8616: aload #15
    //   8618: iload #27
    //   8620: iaload
    //   8621: i2b
    //   8622: bastore
    //   8623: iinc #27, 1
    //   8626: iload_2
    //   8627: ifeq -> 8538
    //   8630: iinc #18, 1
    //   8633: iload_2
    //   8634: ifeq -> 7719
    //   8637: aload #16
    //   8639: aload #16
    //   8641: arraylength
    //   8642: iconst_1
    //   8643: isub
    //   8644: baload
    //   8645: istore #18
    //   8647: aload #16
    //   8649: arraylength
    //   8650: iload #18
    //   8652: isub
    //   8653: newarray byte
    //   8655: astore #4
    //   8657: aload #16
    //   8659: arraylength
    //   8660: aload #4
    //   8662: arraylength
    //   8663: if_icmpge -> 8687
    //   8666: new java/lang/Exception
    //   8669: dup
    //   8670: sipush #2011
    //   8673: sipush #17747
    //   8676: invokestatic a : (II)Ljava/lang/String;
    //   8679: invokespecial <init> : (Ljava/lang/String;)V
    //   8682: athrow
    //   8683: invokestatic a : (Ljava/lang/Throwable;)Ljava/lang/Throwable;
    //   8686: athrow
    //   8687: iconst_0
    //   8688: istore #19
    //   8690: iload #19
    //   8692: aload #4
    //   8694: arraylength
    //   8695: if_icmpge -> 8715
    //   8698: aload #4
    //   8700: iload #19
    //   8702: aload #16
    //   8704: iload #19
    //   8706: baload
    //   8707: bastore
    //   8708: iinc #19, 1
    //   8711: iload_2
    //   8712: ifeq -> 8690
    //   8715: new java/math/BigInteger
    //   8718: dup
    //   8719: aload #4
    //   8721: invokespecial <init> : ([B)V
    //   8724: invokevirtual abs : ()Ljava/math/BigInteger;
    //   8727: putstatic burp/Zzs9.ZO : Ljava/lang/Object;
    //   8730: new java/lang/StringBuilder
    //   8733: dup
    //   8734: invokespecial <init> : ()V
    //   8737: astore_3
    //   8738: iconst_0
    //   8739: istore #4
    //   8741: iload #4
    //   8743: bipush #32
    //   8745: if_icmpge -> 10079
    //   8748: iload #4
    //   8750: tableswitch default -> 10072, 0 -> 8892, 1 -> 8929, 2 -> 8966, 3 -> 9003, 4 -> 9040, 5 -> 9077, 6 -> 9114, 7 -> 9151, 8 -> 9188, 9 -> 9225, 10 -> 9262, 11 -> 9299, 12 -> 9336, 13 -> 9373, 14 -> 9410, 15 -> 9447, 16 -> 9484, 17 -> 9521, 18 -> 9558, 19 -> 9595, 20 -> 9632, 21 -> 9669, 22 -> 9706, 23 -> 9743, 24 -> 9780, 25 -> 9817, 26 -> 9854, 27 -> 9891, 28 -> 9928, 29 -> 9965, 30 -> 10002, 31 -> 10039
    //   8892: aload_3
    //   8893: getstatic burp/Zter.ZE : Ljava/lang/String;
    //   8896: getstatic burp/Zmlr.Zh : Ljava/lang/Object;
    //   8899: checkcast java/math/BigInteger
    //   8902: invokevirtual intValue : ()I
    //   8905: bipush #32
    //   8907: irem
    //   8908: invokestatic abs : (I)I
    //   8911: invokevirtual charAt : (I)C
    //   8914: invokevirtual append : (C)Ljava/lang/StringBuilder;
    //   8917: pop
    //   8918: iload_2
    //   8919: ifeq -> 10072
    //   8922: goto -> 8929
    //   8925: invokestatic a : (Ljava/lang/Throwable;)Ljava/lang/Throwable;
    //   8928: athrow
    //   8929: aload_3
    //   8930: getstatic burp/Zest.Zd : Ljava/lang/String;
    //   8933: getstatic burp/Zrj3.ZA : Ljava/lang/Object;
    //   8936: checkcast java/math/BigInteger
    //   8939: invokevirtual intValue : ()I
    //   8942: bipush #32
    //   8944: irem
    //   8945: invokestatic abs : (I)I
    //   8948: invokevirtual charAt : (I)C
    //   8951: invokevirtual append : (C)Ljava/lang/StringBuilder;
    //   8954: pop
    //   8955: iload_2
    //   8956: ifeq -> 10072
    //   8959: goto -> 8966
    //   8962: invokestatic a : (Ljava/lang/Throwable;)Ljava/lang/Throwable;
    //   8965: athrow
    //   8966: aload_3
    //   8967: getstatic burp/Ze13.Zg : Ljava/lang/String;
    //   8970: getstatic burp/Zb_u.Zp : Ljava/lang/Object;
    //   8973: checkcast java/math/BigInteger
    //   8976: invokevirtual intValue : ()I
    //   8979: bipush #32
    //   8981: irem
    //   8982: invokestatic abs : (I)I
    //   8985: invokevirtual charAt : (I)C
    //   8988: invokevirtual append : (C)Ljava/lang/StringBuilder;
    //   8991: pop
    //   8992: iload_2
    //   8993: ifeq -> 10072
    //   8996: goto -> 9003
    //   8999: invokestatic a : (Ljava/lang/Throwable;)Ljava/lang/Throwable;
    //   9002: athrow
    //   9003: aload_3
    //   9004: getstatic burp/Ze6k.ZM : Ljava/lang/String;
    //   9007: getstatic burp/Zbp_.Zi : Ljava/lang/Object;
    //   9010: checkcast java/math/BigInteger
    //   9013: invokevirtual intValue : ()I
    //   9016: bipush #32
    //   9018: irem
    //   9019: invokestatic abs : (I)I
    //   9022: invokevirtual charAt : (I)C
    //   9025: invokevirtual append : (C)Ljava/lang/StringBuilder;
    //   9028: pop
    //   9029: iload_2
    //   9030: ifeq -> 10072
    //   9033: goto -> 9040
    //   9036: invokestatic a : (Ljava/lang/Throwable;)Ljava/lang/Throwable;
    //   9039: athrow
    //   9040: aload_3
    //   9041: getstatic burp/Zzb2.ZJ : Ljava/lang/String;
    //   9044: getstatic burp/Zrkc.ZI : Ljava/lang/Object;
    //   9047: checkcast java/math/BigInteger
    //   9050: invokevirtual intValue : ()I
    //   9053: bipush #32
    //   9055: irem
    //   9056: invokestatic abs : (I)I
    //   9059: invokevirtual charAt : (I)C
    //   9062: invokevirtual append : (C)Ljava/lang/StringBuilder;
    //   9065: pop
    //   9066: iload_2
    //   9067: ifeq -> 10072
    //   9070: goto -> 9077
    //   9073: invokestatic a : (Ljava/lang/Throwable;)Ljava/lang/Throwable;
    //   9076: athrow
    //   9077: aload_3
    //   9078: getstatic burp/Zke7.Zl : Ljava/lang/String;
    //   9081: getstatic burp/Zr3q.Zn : Ljava/lang/Object;
    //   9084: checkcast java/math/BigInteger
    //   9087: invokevirtual intValue : ()I
    //   9090: bipush #32
    //   9092: irem
    //   9093: invokestatic abs : (I)I
    //   9096: invokevirtual charAt : (I)C
    //   9099: invokevirtual append : (C)Ljava/lang/StringBuilder;
    //   9102: pop
    //   9103: iload_2
    //   9104: ifeq -> 10072
    //   9107: goto -> 9114
    //   9110: invokestatic a : (Ljava/lang/Throwable;)Ljava/lang/Throwable;
    //   9113: athrow
    //   9114: aload_3
    //   9115: getstatic burp/Ztzw.Zi : Ljava/lang/String;
    //   9118: getstatic burp/Zxxo.ZJ : Ljava/lang/Object;
    //   9121: checkcast java/math/BigInteger
    //   9124: invokevirtual intValue : ()I
    //   9127: bipush #32
    //   9129: irem
    //   9130: invokestatic abs : (I)I
    //   9133: invokevirtual charAt : (I)C
    //   9136: invokevirtual append : (C)Ljava/lang/StringBuilder;
    //   9139: pop
    //   9140: iload_2
    //   9141: ifeq -> 10072
    //   9144: goto -> 9151
    //   9147: invokestatic a : (Ljava/lang/Throwable;)Ljava/lang/Throwable;
    //   9150: athrow
    //   9151: aload_3
    //   9152: getstatic burp/Ztap.Zk : Ljava/lang/String;
    //   9155: getstatic burp/Zbp.ZD : Ljava/lang/Object;
    //   9158: checkcast java/math/BigInteger
    //   9161: invokevirtual intValue : ()I
    //   9164: bipush #32
    //   9166: irem
    //   9167: invokestatic abs : (I)I
    //   9170: invokevirtual charAt : (I)C
    //   9173: invokevirtual append : (C)Ljava/lang/StringBuilder;
    //   9176: pop
    //   9177: iload_2
    //   9178: ifeq -> 10072
    //   9181: goto -> 9188
    //   9184: invokestatic a : (Ljava/lang/Throwable;)Ljava/lang/Throwable;
    //   9187: athrow
    //   9188: aload_3
    //   9189: getstatic burp/Zest.Zd : Ljava/lang/String;
    //   9192: getstatic burp/Zz7j.ZR : Ljava/lang/Object;
    //   9195: checkcast java/math/BigInteger
    //   9198: invokevirtual intValue : ()I
    //   9201: bipush #32
    //   9203: irem
    //   9204: invokestatic abs : (I)I
    //   9207: invokevirtual charAt : (I)C
    //   9210: invokevirtual append : (C)Ljava/lang/StringBuilder;
    //   9213: pop
    //   9214: iload_2
    //   9215: ifeq -> 10072
    //   9218: goto -> 9225
    //   9221: invokestatic a : (Ljava/lang/Throwable;)Ljava/lang/Throwable;
    //   9224: athrow
    //   9225: aload_3
    //   9226: getstatic burp/Zbsr.Zq : Ljava/lang/String;
    //   9229: getstatic burp/Zl4v.ZT : Ljava/lang/Object;
    //   9232: checkcast java/math/BigInteger
    //   9235: invokevirtual intValue : ()I
    //   9238: bipush #32
    //   9240: irem
    //   9241: invokestatic abs : (I)I
    //   9244: invokevirtual charAt : (I)C
    //   9247: invokevirtual append : (C)Ljava/lang/StringBuilder;
    //   9250: pop
    //   9251: iload_2
    //   9252: ifeq -> 10072
    //   9255: goto -> 9262
    //   9258: invokestatic a : (Ljava/lang/Throwable;)Ljava/lang/Throwable;
    //   9261: athrow
    //   9262: aload_3
    //   9263: getstatic burp/Zth8.ZN : Ljava/lang/String;
    //   9266: getstatic burp/Zl6e.Zo : Ljava/lang/Object;
    //   9269: checkcast java/math/BigInteger
    //   9272: invokevirtual intValue : ()I
    //   9275: bipush #32
    //   9277: irem
    //   9278: invokestatic abs : (I)I
    //   9281: invokevirtual charAt : (I)C
    //   9284: invokevirtual append : (C)Ljava/lang/StringBuilder;
    //   9287: pop
    //   9288: iload_2
    //   9289: ifeq -> 10072
    //   9292: goto -> 9299
    //   9295: invokestatic a : (Ljava/lang/Throwable;)Ljava/lang/Throwable;
    //   9298: athrow
    //   9299: aload_3
    //   9300: getstatic burp/Zk5y.ZZ : Ljava/lang/String;
    //   9303: getstatic burp/Zlvx.ZM : Ljava/lang/Object;
    //   9306: checkcast java/math/BigInteger
    //   9309: invokevirtual intValue : ()I
    //   9312: bipush #32
    //   9314: irem
    //   9315: invokestatic abs : (I)I
    //   9318: invokevirtual charAt : (I)C
    //   9321: invokevirtual append : (C)Ljava/lang/StringBuilder;
    //   9324: pop
    //   9325: iload_2
    //   9326: ifeq -> 10072
    //   9329: goto -> 9336
    //   9332: invokestatic a : (Ljava/lang/Throwable;)Ljava/lang/Throwable;
    //   9335: athrow
    //   9336: aload_3
    //   9337: getstatic burp/Zg1k.Ze : Ljava/lang/String;
    //   9340: getstatic burp/Ze_e.Za : Ljava/lang/Object;
    //   9343: checkcast java/math/BigInteger
    //   9346: invokevirtual intValue : ()I
    //   9349: bipush #32
    //   9351: irem
    //   9352: invokestatic abs : (I)I
    //   9355: invokevirtual charAt : (I)C
    //   9358: invokevirtual append : (C)Ljava/lang/StringBuilder;
    //   9361: pop
    //   9362: iload_2
    //   9363: ifeq -> 10072
    //   9366: goto -> 9373
    //   9369: invokestatic a : (Ljava/lang/Throwable;)Ljava/lang/Throwable;
    //   9372: athrow
    //   9373: aload_3
    //   9374: getstatic burp/Zlhm.Zx : Ljava/lang/String;
    //   9377: getstatic burp/Zd1.ZV : Ljava/lang/Object;
    //   9380: checkcast java/math/BigInteger
    //   9383: invokevirtual intValue : ()I
    //   9386: bipush #32
    //   9388: irem
    //   9389: invokestatic abs : (I)I
    //   9392: invokevirtual charAt : (I)C
    //   9395: invokevirtual append : (C)Ljava/lang/StringBuilder;
    //   9398: pop
    //   9399: iload_2
    //   9400: ifeq -> 10072
    //   9403: goto -> 9410
    //   9406: invokestatic a : (Ljava/lang/Throwable;)Ljava/lang/Throwable;
    //   9409: athrow
    //   9410: aload_3
    //   9411: getstatic burp/Zg8v.Zd : Ljava/lang/String;
    //   9414: getstatic burp/Zml.ZR : Ljava/lang/Object;
    //   9417: checkcast java/math/BigInteger
    //   9420: invokevirtual intValue : ()I
    //   9423: bipush #32
    //   9425: irem
    //   9426: invokestatic abs : (I)I
    //   9429: invokevirtual charAt : (I)C
    //   9432: invokevirtual append : (C)Ljava/lang/StringBuilder;
    //   9435: pop
    //   9436: iload_2
    //   9437: ifeq -> 10072
    //   9440: goto -> 9447
    //   9443: invokestatic a : (Ljava/lang/Throwable;)Ljava/lang/Throwable;
    //   9446: athrow
    //   9447: aload_3
    //   9448: getstatic burp/Zv8c.ZO : Ljava/lang/String;
    //   9451: getstatic burp/Zgk1.ZD : Ljava/lang/Object;
    //   9454: checkcast java/math/BigInteger
    //   9457: invokevirtual intValue : ()I
    //   9460: bipush #32
    //   9462: irem
    //   9463: invokestatic abs : (I)I
    //   9466: invokevirtual charAt : (I)C
    //   9469: invokevirtual append : (C)Ljava/lang/StringBuilder;
    //   9472: pop
    //   9473: iload_2
    //   9474: ifeq -> 10072
    //   9477: goto -> 9484
    //   9480: invokestatic a : (Ljava/lang/Throwable;)Ljava/lang/Throwable;
    //   9483: athrow
    //   9484: aload_3
    //   9485: getstatic burp/Zml2.Zh : Ljava/lang/String;
    //   9488: getstatic burp/Zml.ZR : Ljava/lang/Object;
    //   9491: checkcast java/math/BigInteger
    //   9494: invokevirtual intValue : ()I
    //   9497: bipush #32
    //   9499: irem
    //   9500: invokestatic abs : (I)I
    //   9503: invokevirtual charAt : (I)C
    //   9506: invokevirtual append : (C)Ljava/lang/StringBuilder;
    //   9509: pop
    //   9510: iload_2
    //   9511: ifeq -> 10072
    //   9514: goto -> 9521
    //   9517: invokestatic a : (Ljava/lang/Throwable;)Ljava/lang/Throwable;
    //   9520: athrow
    //   9521: aload_3
    //   9522: getstatic burp/Zsn6.Zs : Ljava/lang/String;
    //   9525: getstatic burp/Zg2u.ZI : Ljava/lang/Object;
    //   9528: checkcast java/math/BigInteger
    //   9531: invokevirtual intValue : ()I
    //   9534: bipush #32
    //   9536: irem
    //   9537: invokestatic abs : (I)I
    //   9540: invokevirtual charAt : (I)C
    //   9543: invokevirtual append : (C)Ljava/lang/StringBuilder;
    //   9546: pop
    //   9547: iload_2
    //   9548: ifeq -> 10072
    //   9551: goto -> 9558
    //   9554: invokestatic a : (Ljava/lang/Throwable;)Ljava/lang/Throwable;
    //   9557: athrow
    //   9558: aload_3
    //   9559: getstatic burp/Zzok.ZC : Ljava/lang/String;
    //   9562: getstatic burp/Zsfj.ZL : Ljava/lang/Object;
    //   9565: checkcast java/math/BigInteger
    //   9568: invokevirtual intValue : ()I
    //   9571: bipush #32
    //   9573: irem
    //   9574: invokestatic abs : (I)I
    //   9577: invokevirtual charAt : (I)C
    //   9580: invokevirtual append : (C)Ljava/lang/StringBuilder;
    //   9583: pop
    //   9584: iload_2
    //   9585: ifeq -> 10072
    //   9588: goto -> 9595
    //   9591: invokestatic a : (Ljava/lang/Throwable;)Ljava/lang/Throwable;
    //   9594: athrow
    //   9595: aload_3
    //   9596: getstatic burp/Zlos.Zp : Ljava/lang/String;
    //   9599: getstatic burp/Zkco.Zg : Ljava/lang/Object;
    //   9602: checkcast java/math/BigInteger
    //   9605: invokevirtual intValue : ()I
    //   9608: bipush #32
    //   9610: irem
    //   9611: invokestatic abs : (I)I
    //   9614: invokevirtual charAt : (I)C
    //   9617: invokevirtual append : (C)Ljava/lang/StringBuilder;
    //   9620: pop
    //   9621: iload_2
    //   9622: ifeq -> 10072
    //   9625: goto -> 9632
    //   9628: invokestatic a : (Ljava/lang/Throwable;)Ljava/lang/Throwable;
    //   9631: athrow
    //   9632: aload_3
    //   9633: getstatic burp/Zs5i.ZJ : Ljava/lang/String;
    //   9636: getstatic burp/Zgsy.ZC : Ljava/lang/Object;
    //   9639: checkcast java/math/BigInteger
    //   9642: invokevirtual intValue : ()I
    //   9645: bipush #32
    //   9647: irem
    //   9648: invokestatic abs : (I)I
    //   9651: invokevirtual charAt : (I)C
    //   9654: invokevirtual append : (C)Ljava/lang/StringBuilder;
    //   9657: pop
    //   9658: iload_2
    //   9659: ifeq -> 10072
    //   9662: goto -> 9669
    //   9665: invokestatic a : (Ljava/lang/Throwable;)Ljava/lang/Throwable;
    //   9668: athrow
    //   9669: aload_3
    //   9670: getstatic burp/Zlvb.Zs : Ljava/lang/String;
    //   9673: getstatic burp/Zkw.ZY : Ljava/lang/Object;
    //   9676: checkcast java/math/BigInteger
    //   9679: invokevirtual intValue : ()I
    //   9682: bipush #32
    //   9684: irem
    //   9685: invokestatic abs : (I)I
    //   9688: invokevirtual charAt : (I)C
    //   9691: invokevirtual append : (C)Ljava/lang/StringBuilder;
    //   9694: pop
    //   9695: iload_2
    //   9696: ifeq -> 10072
    //   9699: goto -> 9706
    //   9702: invokestatic a : (Ljava/lang/Throwable;)Ljava/lang/Throwable;
    //   9705: athrow
    //   9706: aload_3
    //   9707: getstatic burp/Zecm.Zv : Ljava/lang/String;
    //   9710: getstatic burp/Zboa.Zh : Ljava/lang/Object;
    //   9713: checkcast java/math/BigInteger
    //   9716: invokevirtual intValue : ()I
    //   9719: bipush #32
    //   9721: irem
    //   9722: invokestatic abs : (I)I
    //   9725: invokevirtual charAt : (I)C
    //   9728: invokevirtual append : (C)Ljava/lang/StringBuilder;
    //   9731: pop
    //   9732: iload_2
    //   9733: ifeq -> 10072
    //   9736: goto -> 9743
    //   9739: invokestatic a : (Ljava/lang/Throwable;)Ljava/lang/Throwable;
    //   9742: athrow
    //   9743: aload_3
    //   9744: getstatic burp/Zgk1.Zv : Ljava/lang/String;
    //   9747: getstatic burp/Zbxp.ZW : Ljava/lang/Object;
    //   9750: checkcast java/math/BigInteger
    //   9753: invokevirtual intValue : ()I
    //   9756: bipush #32
    //   9758: irem
    //   9759: invokestatic abs : (I)I
    //   9762: invokevirtual charAt : (I)C
    //   9765: invokevirtual append : (C)Ljava/lang/StringBuilder;
    //   9768: pop
    //   9769: iload_2
    //   9770: ifeq -> 10072
    //   9773: goto -> 9780
    //   9776: invokestatic a : (Ljava/lang/Throwable;)Ljava/lang/Throwable;
    //   9779: athrow
    //   9780: aload_3
    //   9781: getstatic burp/Zeoi.Zh : Ljava/lang/String;
    //   9784: getstatic burp/Zrct.ZV : Ljava/lang/Object;
    //   9787: checkcast java/math/BigInteger
    //   9790: invokevirtual intValue : ()I
    //   9793: bipush #32
    //   9795: irem
    //   9796: invokestatic abs : (I)I
    //   9799: invokevirtual charAt : (I)C
    //   9802: invokevirtual append : (C)Ljava/lang/StringBuilder;
    //   9805: pop
    //   9806: iload_2
    //   9807: ifeq -> 10072
    //   9810: goto -> 9817
    //   9813: invokestatic a : (Ljava/lang/Throwable;)Ljava/lang/Throwable;
    //   9816: athrow
    //   9817: aload_3
    //   9818: getstatic burp/Zlhz.Zo : Ljava/lang/String;
    //   9821: getstatic burp/Zbo7.Zl : Ljava/lang/Object;
    //   9824: checkcast java/math/BigInteger
    //   9827: invokevirtual intValue : ()I
    //   9830: bipush #32
    //   9832: irem
    //   9833: invokestatic abs : (I)I
    //   9836: invokevirtual charAt : (I)C
    //   9839: invokevirtual append : (C)Ljava/lang/StringBuilder;
    //   9842: pop
    //   9843: iload_2
    //   9844: ifeq -> 10072
    //   9847: goto -> 9854
    //   9850: invokestatic a : (Ljava/lang/Throwable;)Ljava/lang/Throwable;
    //   9853: athrow
    //   9854: aload_3
    //   9855: getstatic burp/Zth8.ZN : Ljava/lang/String;
    //   9858: getstatic burp/Ze08.ZJ : Ljava/lang/Object;
    //   9861: checkcast java/math/BigInteger
    //   9864: invokevirtual intValue : ()I
    //   9867: bipush #32
    //   9869: irem
    //   9870: invokestatic abs : (I)I
    //   9873: invokevirtual charAt : (I)C
    //   9876: invokevirtual append : (C)Ljava/lang/StringBuilder;
    //   9879: pop
    //   9880: iload_2
    //   9881: ifeq -> 10072
    //   9884: goto -> 9891
    //   9887: invokestatic a : (Ljava/lang/Throwable;)Ljava/lang/Throwable;
    //   9890: athrow
    //   9891: aload_3
    //   9892: getstatic burp/Zr9p.Za : Ljava/lang/String;
    //   9895: getstatic burp/Ze08.ZJ : Ljava/lang/Object;
    //   9898: checkcast java/math/BigInteger
    //   9901: invokevirtual intValue : ()I
    //   9904: bipush #32
    //   9906: irem
    //   9907: invokestatic abs : (I)I
    //   9910: invokevirtual charAt : (I)C
    //   9913: invokevirtual append : (C)Ljava/lang/StringBuilder;
    //   9916: pop
    //   9917: iload_2
    //   9918: ifeq -> 10072
    //   9921: goto -> 9928
    //   9924: invokestatic a : (Ljava/lang/Throwable;)Ljava/lang/Throwable;
    //   9927: athrow
    //   9928: aload_3
    //   9929: getstatic burp/Zr_k.Zu : Ljava/lang/String;
    //   9932: getstatic burp/Zltp.ZT : Ljava/lang/Object;
    //   9935: checkcast java/math/BigInteger
    //   9938: invokevirtual intValue : ()I
    //   9941: bipush #32
    //   9943: irem
    //   9944: invokestatic abs : (I)I
    //   9947: invokevirtual charAt : (I)C
    //   9950: invokevirtual append : (C)Ljava/lang/StringBuilder;
    //   9953: pop
    //   9954: iload_2
    //   9955: ifeq -> 10072
    //   9958: goto -> 9965
    //   9961: invokestatic a : (Ljava/lang/Throwable;)Ljava/lang/Throwable;
    //   9964: athrow
    //   9965: aload_3
    //   9966: getstatic burp/Zxyp.Z_ : Ljava/lang/String;
    //   9969: getstatic burp/Zg_i.ZQ : Ljava/lang/Object;
    //   9972: checkcast java/math/BigInteger
    //   9975: invokevirtual intValue : ()I
    //   9978: bipush #32
    //   9980: irem
    //   9981: invokestatic abs : (I)I
    //   9984: invokevirtual charAt : (I)C
    //   9987: invokevirtual append : (C)Ljava/lang/StringBuilder;
    //   9990: pop
    //   9991: iload_2
    //   9992: ifeq -> 10072
    //   9995: goto -> 10002
    //   9998: invokestatic a : (Ljava/lang/Throwable;)Ljava/lang/Throwable;
    //   10001: athrow
    //   10002: aload_3
    //   10003: getstatic burp/Zedz.Zh : Ljava/lang/String;
    //   10006: getstatic burp/Zt5t.Za : Ljava/lang/Object;
    //   10009: checkcast java/math/BigInteger
    //   10012: invokevirtual intValue : ()I
    //   10015: bipush #32
    //   10017: irem
    //   10018: invokestatic abs : (I)I
    //   10021: invokevirtual charAt : (I)C
    //   10024: invokevirtual append : (C)Ljava/lang/StringBuilder;
    //   10027: pop
    //   10028: iload_2
    //   10029: ifeq -> 10072
    //   10032: goto -> 10039
    //   10035: invokestatic a : (Ljava/lang/Throwable;)Ljava/lang/Throwable;
    //   10038: athrow
    //   10039: aload_3
    //   10040: getstatic burp/Zrc0.ZL : Ljava/lang/String;
    //   10043: getstatic burp/Zmze.Zo : Ljava/lang/Object;
    //   10046: checkcast java/math/BigInteger
    //   10049: invokevirtual intValue : ()I
    //   10052: bipush #32
    //   10054: irem
    //   10055: invokestatic abs : (I)I
    //   10058: invokevirtual charAt : (I)C
    //   10061: invokevirtual append : (C)Ljava/lang/StringBuilder;
    //   10064: pop
    //   10065: goto -> 10072
    //   10068: invokestatic a : (Ljava/lang/Throwable;)Ljava/lang/Throwable;
    //   10071: athrow
    //   10072: iinc #4, 1
    //   10075: iload_2
    //   10076: ifeq -> 8741
    //   10079: aload_3
    //   10080: invokevirtual toString : ()Ljava/lang/String;
    //   10083: putstatic burp/Zvk.ZG : Ljava/lang/String;
    //   10086: sipush #2003
    //   10089: sipush #-12824
    //   10092: invokestatic a : (II)Ljava/lang/String;
    //   10095: iconst_1
    //   10096: ldc burp/Zzy5
    //   10098: invokevirtual getClassLoader : ()Ljava/lang/ClassLoader;
    //   10101: invokestatic forName : (Ljava/lang/String;ZLjava/lang/ClassLoader;)Ljava/lang/Class;
    //   10104: invokevirtual getDeclaredFields : ()[Ljava/lang/reflect/Field;
    //   10107: astore #4
    //   10109: aload #4
    //   10111: arraylength
    //   10112: istore #5
    //   10114: iconst_0
    //   10115: istore #6
    //   10117: iload #6
    //   10119: iload #5
    //   10121: if_icmpge -> 10259
    //   10124: aload #4
    //   10126: iload #6
    //   10128: aaload
    //   10129: astore #7
    //   10131: aload #7
    //   10133: invokevirtual getModifiers : ()I
    //   10136: invokestatic isStatic : (I)Z
    //   10139: ifne -> 10149
    //   10142: goto -> 10252
    //   10145: invokestatic a : (Ljava/lang/Throwable;)Ljava/lang/Throwable;
    //   10148: athrow
    //   10149: aload #7
    //   10151: invokevirtual getType : ()Ljava/lang/Class;
    //   10154: astore #8
    //   10156: aload #8
    //   10158: ifnull -> 10239
    //   10161: aload #8
    //   10163: invokevirtual isPrimitive : ()Z
    //   10166: ifne -> 10239
    //   10169: goto -> 10176
    //   10172: invokestatic a : (Ljava/lang/Throwable;)Ljava/lang/Throwable;
    //   10175: athrow
    //   10176: aload #8
    //   10178: invokevirtual getPackage : ()Ljava/lang/Package;
    //   10181: ifnull -> 10239
    //   10184: goto -> 10191
    //   10187: invokestatic a : (Ljava/lang/Throwable;)Ljava/lang/Throwable;
    //   10190: athrow
    //   10191: aload #8
    //   10193: invokevirtual getPackage : ()Ljava/lang/Package;
    //   10196: invokevirtual getName : ()Ljava/lang/String;
    //   10199: ifnull -> 10239
    //   10202: goto -> 10209
    //   10205: invokestatic a : (Ljava/lang/Throwable;)Ljava/lang/Throwable;
    //   10208: athrow
    //   10209: aload #8
    //   10211: invokevirtual getPackage : ()Ljava/lang/Package;
    //   10214: invokevirtual getName : ()Ljava/lang/String;
    //   10217: sipush #2006
    //   10220: sipush #-31313
    //   10223: invokestatic a : (II)Ljava/lang/String;
    //   10226: invokevirtual startsWith : (Ljava/lang/String;)Z
    //   10229: ifne -> 10239
    //   10232: goto -> 10239
    //   10235: invokestatic a : (Ljava/lang/Throwable;)Ljava/lang/Throwable;
    //   10238: athrow
    //   10239: aload #7
    //   10241: iconst_1
    //   10242: invokevirtual setAccessible : (Z)V
    //   10245: aload #7
    //   10247: aconst_null
    //   10248: invokevirtual get : (Ljava/lang/Object;)Ljava/lang/Object;
    //   10251: pop
    //   10252: iinc #6, 1
    //   10255: iload_2
    //   10256: ifeq -> 10117
    //   10259: sipush #2002
    //   10262: sipush #-20389
    //   10265: invokestatic a : (II)Ljava/lang/String;
    //   10268: invokestatic forName : (Ljava/lang/String;)Ljava/lang/Class;
    //   10271: invokevirtual getDeclaredMethods : ()[Ljava/lang/reflect/Method;
    //   10274: astore #4
    //   10276: aload #4
    //   10278: arraylength
    //   10279: istore #5
    //   10281: iconst_0
    //   10282: istore #6
    //   10284: iload #6
    //   10286: iload #5
    //   10288: if_icmpge -> 10421
    //   10291: aload #4
    //   10293: iload #6
    //   10295: aaload
    //   10296: astore #7
    //   10298: aload #7
    //   10300: invokevirtual getParameterTypes : ()[Ljava/lang/Class;
    //   10303: pop
    //   10304: aload #7
    //   10306: invokevirtual getModifiers : ()I
    //   10309: invokestatic isStatic : (I)Z
    //   10312: ifeq -> 10407
    //   10315: aload #7
    //   10317: invokevirtual getParameterTypes : ()[Ljava/lang/Class;
    //   10320: arraylength
    //   10321: iconst_2
    //   10322: if_icmpne -> 10407
    //   10325: goto -> 10332
    //   10328: invokestatic a : (Ljava/lang/Throwable;)Ljava/lang/Throwable;
    //   10331: athrow
    //   10332: aload #7
    //   10334: invokevirtual getReturnType : ()Ljava/lang/Class;
    //   10337: getstatic java/lang/Void.TYPE : Ljava/lang/Class;
    //   10340: invokevirtual equals : (Ljava/lang/Object;)Z
    //   10343: ifeq -> 10407
    //   10346: goto -> 10353
    //   10349: invokestatic a : (Ljava/lang/Throwable;)Ljava/lang/Throwable;
    //   10352: athrow
    //   10353: aload #7
    //   10355: iconst_1
    //   10356: invokevirtual setAccessible : (Z)V
    //   10359: aload #7
    //   10361: aconst_null
    //   10362: iconst_2
    //   10363: anewarray java/lang/Object
    //   10366: dup
    //   10367: iconst_0
    //   10368: aload_0
    //   10369: aastore
    //   10370: dup
    //   10371: iconst_1
    //   10372: aload_1
    //   10373: ifnonnull -> 10391
    //   10376: goto -> 10383
    //   10379: invokestatic a : (Ljava/lang/Throwable;)Ljava/lang/Throwable;
    //   10382: athrow
    //   10383: aload_1
    //   10384: goto -> 10398
    //   10387: invokestatic a : (Ljava/lang/Throwable;)Ljava/lang/Throwable;
    //   10390: athrow
    //   10391: aload_1
    //   10392: checkcast [B
    //   10395: invokevirtual clone : ()Ljava/lang/Object;
    //   10398: aastore
    //   10399: invokevirtual invoke : (Ljava/lang/Object;[Ljava/lang/Object;)Ljava/lang/Object;
    //   10402: pop
    //   10403: iload_2
    //   10404: ifeq -> 10421
    //   10407: iinc #6, 1
    //   10410: iload_2
    //   10411: ifeq -> 10284
    //   10414: goto -> 10421
    //   10417: invokestatic a : (Ljava/lang/Throwable;)Ljava/lang/Throwable;
    //   10420: athrow
    //   10421: getstatic burp/Zlr2.Zq : Ljava/lang/Object;
    //   10424: checkcast java/math/BigInteger
    //   10427: invokevirtual intValue : ()I
    //   10430: i2l
    //   10431: invokestatic currentTimeMillis : ()J
    //   10434: ladd
    //   10435: getstatic burp/Zrd4.Ze : Ljava/lang/Object;
    //   10438: checkcast java/math/BigInteger
    //   10441: invokevirtual intValue : ()I
    //   10444: i2l
    //   10445: lcmp
    //   10446: ifge -> 10784
    //   10449: sipush #2014
    //   10452: sipush #-13713
    //   10455: invokestatic a : (II)Ljava/lang/String;
    //   10458: iconst_1
    //   10459: ldc burp/Zl8i
    //   10461: invokevirtual getClassLoader : ()Ljava/lang/ClassLoader;
    //   10464: invokestatic forName : (Ljava/lang/String;ZLjava/lang/ClassLoader;)Ljava/lang/Class;
    //   10467: invokevirtual getDeclaredFields : ()[Ljava/lang/reflect/Field;
    //   10470: astore #4
    //   10472: aload #4
    //   10474: arraylength
    //   10475: istore #5
    //   10477: iconst_0
    //   10478: istore #6
    //   10480: iload #6
    //   10482: iload #5
    //   10484: if_icmpge -> 10622
    //   10487: aload #4
    //   10489: iload #6
    //   10491: aaload
    //   10492: astore #7
    //   10494: aload #7
    //   10496: invokevirtual getModifiers : ()I
    //   10499: invokestatic isStatic : (I)Z
    //   10502: ifne -> 10512
    //   10505: goto -> 10615
    //   10508: invokestatic a : (Ljava/lang/Throwable;)Ljava/lang/Throwable;
    //   10511: athrow
    //   10512: aload #7
    //   10514: invokevirtual getType : ()Ljava/lang/Class;
    //   10517: astore #8
    //   10519: aload #8
    //   10521: ifnull -> 10602
    //   10524: aload #8
    //   10526: invokevirtual isPrimitive : ()Z
    //   10529: ifne -> 10602
    //   10532: goto -> 10539
    //   10535: invokestatic a : (Ljava/lang/Throwable;)Ljava/lang/Throwable;
    //   10538: athrow
    //   10539: aload #8
    //   10541: invokevirtual getPackage : ()Ljava/lang/Package;
    //   10544: ifnull -> 10602
    //   10547: goto -> 10554
    //   10550: invokestatic a : (Ljava/lang/Throwable;)Ljava/lang/Throwable;
    //   10553: athrow
    //   10554: aload #8
    //   10556: invokevirtual getPackage : ()Ljava/lang/Package;
    //   10559: invokevirtual getName : ()Ljava/lang/String;
    //   10562: ifnull -> 10602
    //   10565: goto -> 10572
    //   10568: invokestatic a : (Ljava/lang/Throwable;)Ljava/lang/Throwable;
    //   10571: athrow
    //   10572: aload #8
    //   10574: invokevirtual getPackage : ()Ljava/lang/Package;
    //   10577: invokevirtual getName : ()Ljava/lang/String;
    //   10580: sipush #2001
    //   10583: sipush #22131
    //   10586: invokestatic a : (II)Ljava/lang/String;
    //   10589: invokevirtual startsWith : (Ljava/lang/String;)Z
    //   10592: ifne -> 10602
    //   10595: goto -> 10602
    //   10598: invokestatic a : (Ljava/lang/Throwable;)Ljava/lang/Throwable;
    //   10601: athrow
    //   10602: aload #7
    //   10604: iconst_1
    //   10605: invokevirtual setAccessible : (Z)V
    //   10608: aload #7
    //   10610: aconst_null
    //   10611: invokevirtual get : (Ljava/lang/Object;)Ljava/lang/Object;
    //   10614: pop
    //   10615: iinc #6, 1
    //   10618: iload_2
    //   10619: ifeq -> 10480
    //   10622: sipush #2000
    //   10625: sipush #-3658
    //   10628: invokestatic a : (II)Ljava/lang/String;
    //   10631: invokestatic forName : (Ljava/lang/String;)Ljava/lang/Class;
    //   10634: invokevirtual getDeclaredMethods : ()[Ljava/lang/reflect/Method;
    //   10637: astore #4
    //   10639: aload #4
    //   10641: arraylength
    //   10642: istore #5
    //   10644: iconst_0
    //   10645: istore #6
    //   10647: iload #6
    //   10649: iload #5
    //   10651: if_icmpge -> 10784
    //   10654: aload #4
    //   10656: iload #6
    //   10658: aaload
    //   10659: astore #7
    //   10661: aload #7
    //   10663: invokevirtual getParameterTypes : ()[Ljava/lang/Class;
    //   10666: pop
    //   10667: aload #7
    //   10669: invokevirtual getModifiers : ()I
    //   10672: invokestatic isStatic : (I)Z
    //   10675: ifeq -> 10770
    //   10678: aload #7
    //   10680: invokevirtual getParameterTypes : ()[Ljava/lang/Class;
    //   10683: arraylength
    //   10684: iconst_2
    //   10685: if_icmpne -> 10770
    //   10688: goto -> 10695
    //   10691: invokestatic a : (Ljava/lang/Throwable;)Ljava/lang/Throwable;
    //   10694: athrow
    //   10695: aload #7
    //   10697: invokevirtual getReturnType : ()Ljava/lang/Class;
    //   10700: getstatic java/lang/Void.TYPE : Ljava/lang/Class;
    //   10703: invokevirtual equals : (Ljava/lang/Object;)Z
    //   10706: ifeq -> 10770
    //   10709: goto -> 10716
    //   10712: invokestatic a : (Ljava/lang/Throwable;)Ljava/lang/Throwable;
    //   10715: athrow
    //   10716: aload #7
    //   10718: iconst_1
    //   10719: invokevirtual setAccessible : (Z)V
    //   10722: aload #7
    //   10724: aconst_null
    //   10725: iconst_2
    //   10726: anewarray java/lang/Object
    //   10729: dup
    //   10730: iconst_0
    //   10731: aload_0
    //   10732: aastore
    //   10733: dup
    //   10734: iconst_1
    //   10735: aload_1
    //   10736: ifnonnull -> 10754
    //   10739: goto -> 10746
    //   10742: invokestatic a : (Ljava/lang/Throwable;)Ljava/lang/Throwable;
    //   10745: athrow
    //   10746: aload_1
    //   10747: goto -> 10761
    //   10750: invokestatic a : (Ljava/lang/Throwable;)Ljava/lang/Throwable;
    //   10753: athrow
    //   10754: aload_1
    //   10755: checkcast [B
    //   10758: invokevirtual clone : ()Ljava/lang/Object;
    //   10761: aastore
    //   10762: invokevirtual invoke : (Ljava/lang/Object;[Ljava/lang/Object;)Ljava/lang/Object;
    //   10765: pop
    //   10766: iload_2
    //   10767: ifeq -> 10784
    //   10770: iinc #6, 1
    //   10773: iload_2
    //   10774: ifeq -> 10647
    //   10777: goto -> 10784
    //   10780: invokestatic a : (Ljava/lang/Throwable;)Ljava/lang/Throwable;
    //   10783: athrow
    //   10784: getstatic burp/Ztsc.ZL : Ljava/lang/String;
    //   10787: getstatic burp/Zgw0.ZM : Ljava/lang/Object;
    //   10790: checkcast java/math/BigInteger
    //   10793: invokevirtual intValue : ()I
    //   10796: bipush #32
    //   10798: irem
    //   10799: invokestatic abs : (I)I
    //   10802: invokevirtual charAt : (I)C
    //   10805: getstatic burp/Zmec.Zi : Ljava/lang/String;
    //   10808: getstatic burp/Zm0s.Zl : Ljava/lang/Object;
    //   10811: checkcast java/math/BigInteger
    //   10814: invokevirtual intValue : ()I
    //   10817: bipush #32
    //   10819: irem
    //   10820: invokestatic abs : (I)I
    //   10823: invokevirtual charAt : (I)C
    //   10826: if_icmple -> 10933
    //   10829: getstatic burp/Zg_5.ZG : Ljava/lang/String;
    //   10832: getstatic burp/Zm4k.Zm : Ljava/lang/Object;
    //   10835: checkcast java/math/BigInteger
    //   10838: invokevirtual intValue : ()I
    //   10841: bipush #32
    //   10843: irem
    //   10844: invokestatic abs : (I)I
    //   10847: invokevirtual charAt : (I)C
    //   10850: getstatic burp/Zkig.ZE : Ljava/lang/String;
    //   10853: getstatic burp/Zzr5.Za : Ljava/lang/Object;
    //   10856: checkcast java/math/BigInteger
    //   10859: invokevirtual intValue : ()I
    //   10862: bipush #32
    //   10864: irem
    //   10865: invokestatic abs : (I)I
    //   10868: invokevirtual charAt : (I)C
    //   10871: if_icmpgt -> 10933
    //   10874: goto -> 10881
    //   10877: invokestatic a : (Ljava/lang/Throwable;)Ljava/lang/Throwable;
    //   10880: athrow
    //   10881: getstatic burp/Ztc2.Zr : Ljava/lang/String;
    //   10884: getstatic burp/Zrhu.Zs : Ljava/lang/Object;
    //   10887: checkcast java/math/BigInteger
    //   10890: invokevirtual intValue : ()I
    //   10893: bipush #32
    //   10895: irem
    //   10896: invokestatic abs : (I)I
    //   10899: invokevirtual charAt : (I)C
    //   10902: getstatic burp/Ztvn.ZU : Ljava/lang/String;
    //   10905: getstatic burp/Zzc7.ZG : Ljava/lang/Object;
    //   10908: checkcast java/math/BigInteger
    //   10911: invokevirtual intValue : ()I
    //   10914: bipush #32
    //   10916: irem
    //   10917: invokestatic abs : (I)I
    //   10920: invokevirtual charAt : (I)C
    //   10923: if_icmple -> 10941
    //   10926: goto -> 10933
    //   10929: invokestatic a : (Ljava/lang/Throwable;)Ljava/lang/Throwable;
    //   10932: athrow
    //   10933: iconst_1
    //   10934: goto -> 10942
    //   10937: invokestatic a : (Ljava/lang/Throwable;)Ljava/lang/Throwable;
    //   10940: athrow
    //   10941: iconst_0
    //   10942: ireturn
    //   10943: astore_3
    //   10944: new java/lang/Exception
    //   10947: dup
    //   10948: aload_3
    //   10949: invokevirtual getMessage : ()Ljava/lang/String;
    //   10952: invokespecial <init> : (Ljava/lang/String;)V
    //   10955: athrow
    // Exception table:
    //   from	to	target	type
    //   4	10942	10943	java/lang/Throwable
    //   3306	3331	3331	java/lang/Throwable
    //   4294	4320	4320	java/lang/Throwable
    //   7669	7694	7694	java/lang/Throwable
    //   8657	8683	8683	java/lang/Throwable
    //   8748	8922	8925	java/lang/Throwable
    //   8892	8959	8962	java/lang/Throwable
    //   8929	8996	8999	java/lang/Throwable
    //   8966	9033	9036	java/lang/Throwable
    //   9003	9070	9073	java/lang/Throwable
    //   9040	9107	9110	java/lang/Throwable
    //   9077	9144	9147	java/lang/Throwable
    //   9114	9181	9184	java/lang/Throwable
    //   9151	9218	9221	java/lang/Throwable
    //   9188	9255	9258	java/lang/Throwable
    //   9225	9292	9295	java/lang/Throwable
    //   9262	9329	9332	java/lang/Throwable
    //   9299	9366	9369	java/lang/Throwable
    //   9336	9403	9406	java/lang/Throwable
    //   9373	9440	9443	java/lang/Throwable
    //   9410	9477	9480	java/lang/Throwable
    //   9447	9514	9517	java/lang/Throwable
    //   9484	9551	9554	java/lang/Throwable
    //   9521	9588	9591	java/lang/Throwable
    //   9558	9625	9628	java/lang/Throwable
    //   9595	9662	9665	java/lang/Throwable
    //   9632	9699	9702	java/lang/Throwable
    //   9669	9736	9739	java/lang/Throwable
    //   9706	9773	9776	java/lang/Throwable
    //   9743	9810	9813	java/lang/Throwable
    //   9780	9847	9850	java/lang/Throwable
    //   9817	9884	9887	java/lang/Throwable
    //   9854	9921	9924	java/lang/Throwable
    //   9891	9958	9961	java/lang/Throwable
    //   9928	9995	9998	java/lang/Throwable
    //   9965	10032	10035	java/lang/Throwable
    //   10002	10065	10068	java/lang/Throwable
    //   10131	10145	10145	java/lang/Throwable
    //   10156	10169	10172	java/lang/Throwable
    //   10161	10184	10187	java/lang/Throwable
    //   10176	10202	10205	java/lang/Throwable
    //   10191	10232	10235	java/lang/Throwable
    //   10298	10325	10328	java/lang/Throwable
    //   10315	10346	10349	java/lang/Throwable
    //   10332	10376	10379	java/lang/Throwable
    //   10353	10387	10387	java/lang/Throwable
    //   10398	10414	10417	java/lang/Throwable
    //   10494	10508	10508	java/lang/Throwable
    //   10519	10532	10535	java/lang/Throwable
    //   10524	10547	10550	java/lang/Throwable
    //   10539	10565	10568	java/lang/Throwable
    //   10554	10595	10598	java/lang/Throwable
    //   10661	10688	10691	java/lang/Throwable
    //   10678	10709	10712	java/lang/Throwable
    //   10695	10739	10742	java/lang/Throwable
    //   10716	10750	10750	java/lang/Throwable
    //   10761	10777	10780	java/lang/Throwable
    //   10784	10874	10877	java/lang/Throwable
    //   10829	10926	10929	java/lang/Throwable
    //   10881	10937	10937	java/lang/Throwable
  }
  
  static {
    // Byte code:
    //   0: bipush #13
    //   2: anewarray java/lang/String
    //   5: astore #5
    //   7: iconst_0
    //   8: istore_3
    //   9: ldc 'L$)gxDq>M#7sy_h0}dS[KO[p"M*- PzM~6,Ia-5:/WI/>dj,Ts 3\\t p/1\\tS@Eb\\t\\b\.5\\t36RfP\\t)>9 SR#|hg,opET,'
    //   11: dup
    //   12: astore_2
    //   13: invokevirtual length : ()I
    //   16: istore #4
    //   18: bipush #32
    //   20: istore_1
    //   21: iconst_m1
    //   22: istore_0
    //   23: bipush #53
    //   25: iinc #0, 1
    //   28: aload_2
    //   29: iload_0
    //   30: dup
    //   31: iload_1
    //   32: iadd
    //   33: invokevirtual substring : (II)Ljava/lang/String;
    //   36: iconst_m1
    //   37: goto -> 143
    //   40: aload #5
    //   42: swap
    //   43: iload_3
    //   44: iinc #3, 1
    //   47: swap
    //   48: aastore
    //   49: iload_0
    //   50: iload_1
    //   51: iadd
    //   52: dup
    //   53: istore_0
    //   54: iload #4
    //   56: if_icmpge -> 68
    //   59: aload_2
    //   60: iload_0
    //   61: invokevirtual charAt : (I)C
    //   64: istore_1
    //   65: goto -> 23
    //   68: ldc '~bn%eyg3j'
    //   70: dup
    //   71: astore_2
    //   72: invokevirtual length : ()I
    //   75: istore #4
    //   77: bipush #9
    //   79: istore_1
    //   80: iconst_m1
    //   81: istore_0
    //   82: bipush #102
    //   84: iinc #0, 1
    //   87: aload_2
    //   88: iload_0
    //   89: dup
    //   90: iload_1
    //   91: iadd
    //   92: invokevirtual substring : (II)Ljava/lang/String;
    //   95: iconst_0
    //   96: goto -> 143
    //   99: aload #5
    //   101: swap
    //   102: iload_3
    //   103: iinc #3, 1
    //   106: swap
    //   107: aastore
    //   108: iload_0
    //   109: iload_1
    //   110: iadd
    //   111: dup
    //   112: istore_0
    //   113: iload #4
    //   115: if_icmpge -> 127
    //   118: aload_2
    //   119: iload_0
    //   120: invokevirtual charAt : (I)C
    //   123: istore_1
    //   124: goto -> 82
    //   127: aload #5
    //   129: putstatic burp/Zmrc.a : [Ljava/lang/String;
    //   132: bipush #13
    //   134: anewarray java/lang/String
    //   137: putstatic burp/Zmrc.b : [Ljava/lang/String;
    //   140: goto -> 300
    //   143: dup_x2
    //   144: pop
    //   145: invokevirtual toCharArray : ()[C
    //   148: dup_x1
    //   149: arraylength
    //   150: dup_x2
    //   151: pop
    //   152: iconst_0
    //   153: istore #6
    //   155: dup2_x1
    //   156: pop2
    //   157: dup_x2
    //   158: iconst_1
    //   159: if_icmpgt -> 260
    //   162: dup2
    //   163: swap
    //   164: iload #6
    //   166: dup2_x1
    //   167: caload
    //   168: swap
    //   169: iload #6
    //   171: bipush #7
    //   173: irem
    //   174: tableswitch default -> 242, 0 -> 212, 1 -> 217, 2 -> 222, 3 -> 227, 4 -> 232, 5 -> 237
    //   212: bipush #118
    //   214: goto -> 244
    //   217: bipush #101
    //   219: goto -> 244
    //   222: bipush #81
    //   224: goto -> 244
    //   227: bipush #23
    //   229: goto -> 244
    //   232: bipush #63
    //   234: goto -> 244
    //   237: bipush #19
    //   239: goto -> 244
    //   242: bipush #109
    //   244: ixor
    //   245: ixor
    //   246: i2c
    //   247: castore
    //   248: iinc #6, 1
    //   251: dup
    //   252: ifne -> 260
    //   255: dup2
    //   256: dup_x1
    //   257: goto -> 166
    //   260: dup2_x1
    //   261: pop2
    //   262: dup_x2
    //   263: iload #6
    //   265: if_icmpgt -> 162
    //   268: pop
    //   269: new java/lang/String
    //   272: dup_x1
    //   273: swap
    //   274: invokespecial <init> : ([C)V
    //   277: invokevirtual intern : ()Ljava/lang/String;
    //   280: swap
    //   281: pop
    //   282: swap
    //   283: tableswitch default -> 40, 0 -> 99
    //   300: sipush #2013
    //   303: sipush #15147
    //   306: invokestatic a : (II)Ljava/lang/String;
    //   309: putstatic burp/Zmrc.Zx : Ljava/lang/String;
    //   312: new java/math/BigInteger
    //   315: dup
    //   316: iconst_1
    //   317: bipush #32
    //   319: newarray byte
    //   321: dup
    //   322: iconst_0
    //   323: bipush #57
    //   325: bastore
    //   326: dup
    //   327: iconst_1
    //   328: bipush #61
    //   330: bastore
    //   331: dup
    //   332: iconst_2
    //   333: bipush #-80
    //   335: bastore
    //   336: dup
    //   337: iconst_3
    //   338: bipush #96
    //   340: bastore
    //   341: dup
    //   342: iconst_4
    //   343: bipush #-77
    //   345: bastore
    //   346: dup
    //   347: iconst_5
    //   348: bipush #58
    //   350: bastore
    //   351: dup
    //   352: bipush #6
    //   354: bipush #44
    //   356: bastore
    //   357: dup
    //   358: bipush #7
    //   360: iconst_0
    //   361: bastore
    //   362: dup
    //   363: bipush #8
    //   365: bipush #-124
    //   367: bastore
    //   368: dup
    //   369: bipush #9
    //   371: bipush #-10
    //   373: bastore
    //   374: dup
    //   375: bipush #10
    //   377: bipush #-120
    //   379: bastore
    //   380: dup
    //   381: bipush #11
    //   383: bipush #13
    //   385: bastore
    //   386: dup
    //   387: bipush #12
    //   389: bipush #78
    //   391: bastore
    //   392: dup
    //   393: bipush #13
    //   395: bipush #-36
    //   397: bastore
    //   398: dup
    //   399: bipush #14
    //   401: bipush #106
    //   403: bastore
    //   404: dup
    //   405: bipush #15
    //   407: bipush #91
    //   409: bastore
    //   410: dup
    //   411: bipush #16
    //   413: bipush #-56
    //   415: bastore
    //   416: dup
    //   417: bipush #17
    //   419: bipush #79
    //   421: bastore
    //   422: dup
    //   423: bipush #18
    //   425: bipush #-43
    //   427: bastore
    //   428: dup
    //   429: bipush #19
    //   431: bipush #56
    //   433: bastore
    //   434: dup
    //   435: bipush #20
    //   437: bipush #-126
    //   439: bastore
    //   440: dup
    //   441: bipush #21
    //   443: bipush #-57
    //   445: bastore
    //   446: dup
    //   447: bipush #22
    //   449: bipush #91
    //   451: bastore
    //   452: dup
    //   453: bipush #23
    //   455: bipush #94
    //   457: bastore
    //   458: dup
    //   459: bipush #24
    //   461: bipush #-111
    //   463: bastore
    //   464: dup
    //   465: bipush #25
    //   467: bipush #16
    //   469: bastore
    //   470: dup
    //   471: bipush #26
    //   473: bipush #118
    //   475: bastore
    //   476: dup
    //   477: bipush #27
    //   479: bipush #9
    //   481: bastore
    //   482: dup
    //   483: bipush #28
    //   485: bipush #-70
    //   487: bastore
    //   488: dup
    //   489: bipush #29
    //   491: bipush #84
    //   493: bastore
    //   494: dup
    //   495: bipush #30
    //   497: bipush #89
    //   499: bastore
    //   500: dup
    //   501: bipush #31
    //   503: bipush #-62
    //   505: bastore
    //   506: invokespecial <init> : (I[B)V
    //   509: putstatic burp/Zmrc.ZU : Ljava/lang/Object;
    //   512: return
  }
  
  private static Throwable a(Throwable paramThrowable) {
    return paramThrowable;
  }
  
  private static String a(int paramInt1, int paramInt2) {
    int i = (paramInt1 ^ 0x7D7) & 0xFFFF;
    if (b[i] == null) {
      char[] arrayOfChar = a[i].toCharArray();
      switch (arrayOfChar[0] & 0xFF) {
        case 0:
        
        case 1:
        
        case 2:
        
        case 3:
        
        case 4:
        
        case 5:
        
        case 6:
        
        case 7:
        
        case 8:
        
        case 9:
        
        case 10:
        
        case 11:
        
        case 12:
        
        case 13:
        
        case 14:
        
        case 15:
        
        case 16:
        
        case 17:
        
        case 18:
        
        case 19:
        
        case 20:
        
        case 21:
        
        case 22:
        
        case 23:
        
        case 24:
        
        case 25:
        
        case 26:
        
        case 27:
        
        case 28:
        
        case 29:
        
        case 30:
        
        case 31:
        
        case 32:
        
        case 33:
        
        case 34:
        
        case 35:
        
        case 36:
        
        case 37:
        
        case 38:
        
        case 39:
        
        case 40:
        
        case 41:
        
        case 42:
        
        case 43:
        
        case 44:
        
        case 45:
        
        case 46:
        
        case 47:
        
        case 48:
        
        case 49:
        
        case 50:
        
        case 51:
        
        case 52:
        
        case 53:
        
        case 54:
        
        case 55:
        
        case 56:
        
        case 57:
        
        case 58:
        
        case 59:
        
        case 60:
        
        case 61:
        
        case 62:
        
        case 63:
        
        case 64:
        
        case 65:
        
        case 66:
        
        case 67:
        
        case 68:
        
        case 69:
        
        case 70:
        
        case 71:
        
        case 72:
        
        case 73:
        
        case 74:
        
        case 75:
        
        case 76:
        
        case 77:
        
        case 78:
        
        case 79:
        
        case 80:
        
        case 81:
        
        case 82:
        
        case 83:
        
        case 84:
        
        case 85:
        
        case 86:
        
        case 87:
        
        case 88:
        
        case 89:
        
        case 90:
        
        case 91:
        
        case 92:
        
        case 93:
        
        case 94:
        
        case 95:
        
        case 96:
        
        case 97:
        
        case 98:
        
        case 99:
        
        case 100:
        
        case 101:
        
        case 102:
        
        case 103:
        
        case 104:
        
        case 105:
        
        case 106:
        
        case 107:
        
        case 108:
        
        case 109:
        
        case 110:
        
        case 111:
        
        case 112:
        
        case 113:
        
        case 114:
        
        case 115:
        
        case 116:
        
        case 117:
        
        case 118:
        
        case 119:
        
        case 120:
        
        case 121:
        
        case 122:
        
        case 123:
        
        case 124:
        
        case 125:
        
        case 126:
        
        case 127:
        
        case 128:
        
        case 129:
        
        case 130:
        
        case 131:
        
        case 132:
        
        case 133:
        
        case 134:
        
        case 135:
        
        case 136:
        
        case 137:
        
        case 138:
        
        case 139:
        
        case 140:
        
        case 141:
        
        case 142:
        
        case 143:
        
        case 144:
        
        case 145:
        
        case 146:
        
        case 147:
        
        case 148:
        
        case 149:
        
        case 150:
        
        case 151:
        
        case 152:
        
        case 153:
        
        case 154:
        
        case 155:
        
        case 156:
        
        case 157:
        
        case 158:
        
        case 159:
        
        case 160:
        
        case 161:
        
        case 162:
        
        case 163:
        
        case 164:
        
        case 165:
        
        case 166:
        
        case 167:
        
        case 168:
        
        case 169:
        
        case 170:
        
        case 171:
        
        case 172:
        
        case 173:
        
        case 174:
        
        case 175:
        
        case 176:
        
        case 177:
        
        case 178:
        
        case 179:
        
        case 180:
        
        case 181:
        
        case 182:
        
        case 183:
        
        case 184:
        
        case 185:
        
        case 186:
        
        case 187:
        
        case 188:
        
        case 189:
        
        case 190:
        
        case 191:
        
        case 192:
        
        case 193:
        
        case 194:
        
        case 195:
        
        case 196:
        
        case 197:
        
        case 198:
        
        case 199:
        
        case 200:
        
        case 201:
        
        case 202:
        
        case 203:
        
        case 204:
        
        case 205:
        
        case 206:
        
        case 207:
        
        case 208:
        
        case 209:
        
        case 210:
        
        case 211:
        
        case 212:
        
        case 213:
        
        case 214:
        
        case 215:
        
        case 216:
        
        case 217:
        
        case 218:
        
        case 219:
        
        case 220:
        
        case 221:
        
        case 222:
        
        case 223:
        
        case 224:
        
        case 225:
        
        case 226:
        
        case 227:
        
        case 228:
        
        case 229:
        
        case 230:
        
        case 231:
        
        case 232:
        
        case 233:
        
        case 234:
        
        case 235:
        
        case 236:
        
        case 237:
        
        case 238:
        
        case 239:
        
        case 240:
        
        case 241:
        
        case 242:
        
        case 243:
        
        case 244:
        
        case 245:
        
        case 246:
        
        case 247:
        
        case 248:
        
        case 249:
        
        case 250:
        
        case 251:
        
        case 252:
        
        case 253:
        
        case 254:
        
        default:
          break;
      } 
      char c = '';
      int j = (paramInt2 & 0xFF) - c;
      if (j < 0)
        j += 256; 
      int k = ((paramInt2 & 0xFFFF) >>> 8) - c;
      if (k < 0)
        k += 256; 
      for (byte b = 0; b < arrayOfChar.length; b++) {
        int m = b % 2;
        if (m == 0) {
          arrayOfChar[b] = (char)(arrayOfChar[b] ^ j);
          j = ((j >>> 3 | j << 5) ^ arrayOfChar[b]) & 0xFF;
        } else {
          arrayOfChar[b] = (char)(arrayOfChar[b] ^ k);
          k = ((k >>> 3 | k << 5) ^ arrayOfChar[b]) & 0xFF;
        } 
      } 
      b[i] = (new String(arrayOfChar)).intern();
    } 
    return b[i];
  }
}


/* Location:              C:\Program Files\BurpSuitePro\burpsuite_pro.jar!\burp\Zmrc.class
 * Java compiler version: 21 (65.0)
 * JD-Core Version:       1.1.3
 */