package burp;

import java.math.BigInteger;

class Zms1 extends ClassLoader {
  static String ZZ;
  
  static Object ZE;
  
  private static final String[] a;
  
  private static final String[] b;
  
  static boolean Zp(Object[] paramArrayOfObject, Object paramObject) throws Throwable {
    // Byte code:
    //   0: invokestatic ZN : ()Z
    //   3: istore_2
    //   4: new java/lang/StringBuilder
    //   7: dup
    //   8: invokespecial <init> : ()V
    //   11: astore_3
    //   12: iconst_0
    //   13: istore #4
    //   15: iload #4
    //   17: bipush #32
    //   19: if_icmpge -> 1355
    //   22: iload #4
    //   24: tableswitch default -> 1348, 0 -> 168, 1 -> 205, 2 -> 242, 3 -> 279, 4 -> 316, 5 -> 353, 6 -> 390, 7 -> 427, 8 -> 464, 9 -> 501, 10 -> 538, 11 -> 575, 12 -> 612, 13 -> 649, 14 -> 686, 15 -> 723, 16 -> 760, 17 -> 797, 18 -> 834, 19 -> 871, 20 -> 908, 21 -> 945, 22 -> 982, 23 -> 1019, 24 -> 1056, 25 -> 1093, 26 -> 1130, 27 -> 1167, 28 -> 1204, 29 -> 1241, 30 -> 1278, 31 -> 1315
    //   168: aload_3
    //   169: getstatic burp/Zszm.Zf : Ljava/lang/String;
    //   172: getstatic burp/Zr8r.ZR : Ljava/lang/Object;
    //   175: checkcast java/math/BigInteger
    //   178: invokevirtual intValue : ()I
    //   181: bipush #32
    //   183: irem
    //   184: invokestatic abs : (I)I
    //   187: invokevirtual charAt : (I)C
    //   190: invokevirtual append : (C)Ljava/lang/StringBuilder;
    //   193: pop
    //   194: iload_2
    //   195: ifne -> 1348
    //   198: goto -> 205
    //   201: invokestatic a : (Ljava/lang/Throwable;)Ljava/lang/Throwable;
    //   204: athrow
    //   205: aload_3
    //   206: getstatic burp/Zs5k.ZI : Ljava/lang/String;
    //   209: getstatic burp/Zrx5.ZE : Ljava/lang/Object;
    //   212: checkcast java/math/BigInteger
    //   215: invokevirtual intValue : ()I
    //   218: bipush #32
    //   220: irem
    //   221: invokestatic abs : (I)I
    //   224: invokevirtual charAt : (I)C
    //   227: invokevirtual append : (C)Ljava/lang/StringBuilder;
    //   230: pop
    //   231: iload_2
    //   232: ifne -> 1348
    //   235: goto -> 242
    //   238: invokestatic a : (Ljava/lang/Throwable;)Ljava/lang/Throwable;
    //   241: athrow
    //   242: aload_3
    //   243: getstatic burp/Zeju.ZR : Ljava/lang/String;
    //   246: getstatic burp/Zs5k.Zg : Ljava/lang/Object;
    //   249: checkcast java/math/BigInteger
    //   252: invokevirtual intValue : ()I
    //   255: bipush #32
    //   257: irem
    //   258: invokestatic abs : (I)I
    //   261: invokevirtual charAt : (I)C
    //   264: invokevirtual append : (C)Ljava/lang/StringBuilder;
    //   267: pop
    //   268: iload_2
    //   269: ifne -> 1348
    //   272: goto -> 279
    //   275: invokestatic a : (Ljava/lang/Throwable;)Ljava/lang/Throwable;
    //   278: athrow
    //   279: aload_3
    //   280: getstatic burp/Zzpj.ZR : Ljava/lang/String;
    //   283: getstatic burp/Ztc2.ZM : Ljava/lang/Object;
    //   286: checkcast java/math/BigInteger
    //   289: invokevirtual intValue : ()I
    //   292: bipush #32
    //   294: irem
    //   295: invokestatic abs : (I)I
    //   298: invokevirtual charAt : (I)C
    //   301: invokevirtual append : (C)Ljava/lang/StringBuilder;
    //   304: pop
    //   305: iload_2
    //   306: ifne -> 1348
    //   309: goto -> 316
    //   312: invokestatic a : (Ljava/lang/Throwable;)Ljava/lang/Throwable;
    //   315: athrow
    //   316: aload_3
    //   317: getstatic burp/Zmec.Zi : Ljava/lang/String;
    //   320: getstatic burp/Zrnw.ZN : Ljava/lang/Object;
    //   323: checkcast java/math/BigInteger
    //   326: invokevirtual intValue : ()I
    //   329: bipush #32
    //   331: irem
    //   332: invokestatic abs : (I)I
    //   335: invokevirtual charAt : (I)C
    //   338: invokevirtual append : (C)Ljava/lang/StringBuilder;
    //   341: pop
    //   342: iload_2
    //   343: ifne -> 1348
    //   346: goto -> 353
    //   349: invokestatic a : (Ljava/lang/Throwable;)Ljava/lang/Throwable;
    //   352: athrow
    //   353: aload_3
    //   354: getstatic burp/Zspk.ZA : Ljava/lang/String;
    //   357: getstatic burp/Zgs6.Za : Ljava/lang/Object;
    //   360: checkcast java/math/BigInteger
    //   363: invokevirtual intValue : ()I
    //   366: bipush #32
    //   368: irem
    //   369: invokestatic abs : (I)I
    //   372: invokevirtual charAt : (I)C
    //   375: invokevirtual append : (C)Ljava/lang/StringBuilder;
    //   378: pop
    //   379: iload_2
    //   380: ifne -> 1348
    //   383: goto -> 390
    //   386: invokestatic a : (Ljava/lang/Throwable;)Ljava/lang/Throwable;
    //   389: athrow
    //   390: aload_3
    //   391: getstatic burp/Zt7k.ZH : Ljava/lang/String;
    //   394: getstatic burp/Zecm.ZJ : Ljava/lang/Object;
    //   397: checkcast java/math/BigInteger
    //   400: invokevirtual intValue : ()I
    //   403: bipush #32
    //   405: irem
    //   406: invokestatic abs : (I)I
    //   409: invokevirtual charAt : (I)C
    //   412: invokevirtual append : (C)Ljava/lang/StringBuilder;
    //   415: pop
    //   416: iload_2
    //   417: ifne -> 1348
    //   420: goto -> 427
    //   423: invokestatic a : (Ljava/lang/Throwable;)Ljava/lang/Throwable;
    //   426: athrow
    //   427: aload_3
    //   428: getstatic burp/Zeqw.Zw : Ljava/lang/String;
    //   431: getstatic burp/Zlvx.ZM : Ljava/lang/Object;
    //   434: checkcast java/math/BigInteger
    //   437: invokevirtual intValue : ()I
    //   440: bipush #32
    //   442: irem
    //   443: invokestatic abs : (I)I
    //   446: invokevirtual charAt : (I)C
    //   449: invokevirtual append : (C)Ljava/lang/StringBuilder;
    //   452: pop
    //   453: iload_2
    //   454: ifne -> 1348
    //   457: goto -> 464
    //   460: invokestatic a : (Ljava/lang/Throwable;)Ljava/lang/Throwable;
    //   463: athrow
    //   464: aload_3
    //   465: getstatic burp/Zrct.ZT : Ljava/lang/String;
    //   468: getstatic burp/Zspk.ZF : Ljava/lang/Object;
    //   471: checkcast java/math/BigInteger
    //   474: invokevirtual intValue : ()I
    //   477: bipush #32
    //   479: irem
    //   480: invokestatic abs : (I)I
    //   483: invokevirtual charAt : (I)C
    //   486: invokevirtual append : (C)Ljava/lang/StringBuilder;
    //   489: pop
    //   490: iload_2
    //   491: ifne -> 1348
    //   494: goto -> 501
    //   497: invokestatic a : (Ljava/lang/Throwable;)Ljava/lang/Throwable;
    //   500: athrow
    //   501: aload_3
    //   502: getstatic burp/Zs5i.ZJ : Ljava/lang/String;
    //   505: getstatic burp/Zr8r.ZR : Ljava/lang/Object;
    //   508: checkcast java/math/BigInteger
    //   511: invokevirtual intValue : ()I
    //   514: bipush #32
    //   516: irem
    //   517: invokestatic abs : (I)I
    //   520: invokevirtual charAt : (I)C
    //   523: invokevirtual append : (C)Ljava/lang/StringBuilder;
    //   526: pop
    //   527: iload_2
    //   528: ifne -> 1348
    //   531: goto -> 538
    //   534: invokestatic a : (Ljava/lang/Throwable;)Ljava/lang/Throwable;
    //   537: athrow
    //   538: aload_3
    //   539: getstatic burp/Zt5a.Zl : Ljava/lang/String;
    //   542: getstatic burp/Ztdg.ZE : Ljava/lang/Object;
    //   545: checkcast java/math/BigInteger
    //   548: invokevirtual intValue : ()I
    //   551: bipush #32
    //   553: irem
    //   554: invokestatic abs : (I)I
    //   557: invokevirtual charAt : (I)C
    //   560: invokevirtual append : (C)Ljava/lang/StringBuilder;
    //   563: pop
    //   564: iload_2
    //   565: ifne -> 1348
    //   568: goto -> 575
    //   571: invokestatic a : (Ljava/lang/Throwable;)Ljava/lang/Throwable;
    //   574: athrow
    //   575: aload_3
    //   576: getstatic burp/Zso7.Zr : Ljava/lang/String;
    //   579: getstatic burp/Zmdm.ZZ : Ljava/lang/Object;
    //   582: checkcast java/math/BigInteger
    //   585: invokevirtual intValue : ()I
    //   588: bipush #32
    //   590: irem
    //   591: invokestatic abs : (I)I
    //   594: invokevirtual charAt : (I)C
    //   597: invokevirtual append : (C)Ljava/lang/StringBuilder;
    //   600: pop
    //   601: iload_2
    //   602: ifne -> 1348
    //   605: goto -> 612
    //   608: invokestatic a : (Ljava/lang/Throwable;)Ljava/lang/Throwable;
    //   611: athrow
    //   612: aload_3
    //   613: getstatic burp/Zg3m.Za : Ljava/lang/String;
    //   616: getstatic burp/Zz8o.Zg : Ljava/lang/Object;
    //   619: checkcast java/math/BigInteger
    //   622: invokevirtual intValue : ()I
    //   625: bipush #32
    //   627: irem
    //   628: invokestatic abs : (I)I
    //   631: invokevirtual charAt : (I)C
    //   634: invokevirtual append : (C)Ljava/lang/StringBuilder;
    //   637: pop
    //   638: iload_2
    //   639: ifne -> 1348
    //   642: goto -> 649
    //   645: invokestatic a : (Ljava/lang/Throwable;)Ljava/lang/Throwable;
    //   648: athrow
    //   649: aload_3
    //   650: getstatic burp/Zgl2.Zw : Ljava/lang/String;
    //   653: getstatic burp/Zrh1.ZF : Ljava/lang/Object;
    //   656: checkcast java/math/BigInteger
    //   659: invokevirtual intValue : ()I
    //   662: bipush #32
    //   664: irem
    //   665: invokestatic abs : (I)I
    //   668: invokevirtual charAt : (I)C
    //   671: invokevirtual append : (C)Ljava/lang/StringBuilder;
    //   674: pop
    //   675: iload_2
    //   676: ifne -> 1348
    //   679: goto -> 686
    //   682: invokestatic a : (Ljava/lang/Throwable;)Ljava/lang/Throwable;
    //   685: athrow
    //   686: aload_3
    //   687: getstatic burp/Zs56.ZW : Ljava/lang/String;
    //   690: getstatic burp/Zmfw.ZS : Ljava/lang/Object;
    //   693: checkcast java/math/BigInteger
    //   696: invokevirtual intValue : ()I
    //   699: bipush #32
    //   701: irem
    //   702: invokestatic abs : (I)I
    //   705: invokevirtual charAt : (I)C
    //   708: invokevirtual append : (C)Ljava/lang/StringBuilder;
    //   711: pop
    //   712: iload_2
    //   713: ifne -> 1348
    //   716: goto -> 723
    //   719: invokestatic a : (Ljava/lang/Throwable;)Ljava/lang/Throwable;
    //   722: athrow
    //   723: aload_3
    //   724: getstatic burp/Zeqw.Zw : Ljava/lang/String;
    //   727: getstatic burp/Zrnw.ZN : Ljava/lang/Object;
    //   730: checkcast java/math/BigInteger
    //   733: invokevirtual intValue : ()I
    //   736: bipush #32
    //   738: irem
    //   739: invokestatic abs : (I)I
    //   742: invokevirtual charAt : (I)C
    //   745: invokevirtual append : (C)Ljava/lang/StringBuilder;
    //   748: pop
    //   749: iload_2
    //   750: ifne -> 1348
    //   753: goto -> 760
    //   756: invokestatic a : (Ljava/lang/Throwable;)Ljava/lang/Throwable;
    //   759: athrow
    //   760: aload_3
    //   761: getstatic burp/Zrp3.Zf : Ljava/lang/String;
    //   764: getstatic burp/Zt5a.Zs : Ljava/lang/Object;
    //   767: checkcast java/math/BigInteger
    //   770: invokevirtual intValue : ()I
    //   773: bipush #32
    //   775: irem
    //   776: invokestatic abs : (I)I
    //   779: invokevirtual charAt : (I)C
    //   782: invokevirtual append : (C)Ljava/lang/StringBuilder;
    //   785: pop
    //   786: iload_2
    //   787: ifne -> 1348
    //   790: goto -> 797
    //   793: invokestatic a : (Ljava/lang/Throwable;)Ljava/lang/Throwable;
    //   796: athrow
    //   797: aload_3
    //   798: getstatic burp/Zrnw.Zg : Ljava/lang/String;
    //   801: getstatic burp/Zg5.Zs : Ljava/lang/Object;
    //   804: checkcast java/math/BigInteger
    //   807: invokevirtual intValue : ()I
    //   810: bipush #32
    //   812: irem
    //   813: invokestatic abs : (I)I
    //   816: invokevirtual charAt : (I)C
    //   819: invokevirtual append : (C)Ljava/lang/StringBuilder;
    //   822: pop
    //   823: iload_2
    //   824: ifne -> 1348
    //   827: goto -> 834
    //   830: invokestatic a : (Ljava/lang/Throwable;)Ljava/lang/Throwable;
    //   833: athrow
    //   834: aload_3
    //   835: getstatic burp/Zml2.Zh : Ljava/lang/String;
    //   838: getstatic burp/Zz5l.Zb : Ljava/lang/Object;
    //   841: checkcast java/math/BigInteger
    //   844: invokevirtual intValue : ()I
    //   847: bipush #32
    //   849: irem
    //   850: invokestatic abs : (I)I
    //   853: invokevirtual charAt : (I)C
    //   856: invokevirtual append : (C)Ljava/lang/StringBuilder;
    //   859: pop
    //   860: iload_2
    //   861: ifne -> 1348
    //   864: goto -> 871
    //   867: invokestatic a : (Ljava/lang/Throwable;)Ljava/lang/Throwable;
    //   870: athrow
    //   871: aload_3
    //   872: getstatic burp/Zlhu.ZC : Ljava/lang/String;
    //   875: getstatic burp/Zm5s.ZB : Ljava/lang/Object;
    //   878: checkcast java/math/BigInteger
    //   881: invokevirtual intValue : ()I
    //   884: bipush #32
    //   886: irem
    //   887: invokestatic abs : (I)I
    //   890: invokevirtual charAt : (I)C
    //   893: invokevirtual append : (C)Ljava/lang/StringBuilder;
    //   896: pop
    //   897: iload_2
    //   898: ifne -> 1348
    //   901: goto -> 908
    //   904: invokestatic a : (Ljava/lang/Throwable;)Ljava/lang/Throwable;
    //   907: athrow
    //   908: aload_3
    //   909: getstatic burp/Zmec.Zi : Ljava/lang/String;
    //   912: getstatic burp/Zg5.Zs : Ljava/lang/Object;
    //   915: checkcast java/math/BigInteger
    //   918: invokevirtual intValue : ()I
    //   921: bipush #32
    //   923: irem
    //   924: invokestatic abs : (I)I
    //   927: invokevirtual charAt : (I)C
    //   930: invokevirtual append : (C)Ljava/lang/StringBuilder;
    //   933: pop
    //   934: iload_2
    //   935: ifne -> 1348
    //   938: goto -> 945
    //   941: invokestatic a : (Ljava/lang/Throwable;)Ljava/lang/Throwable;
    //   944: athrow
    //   945: aload_3
    //   946: getstatic burp/Zza3.ZU : Ljava/lang/String;
    //   949: getstatic burp/Zs5k.Zg : Ljava/lang/Object;
    //   952: checkcast java/math/BigInteger
    //   955: invokevirtual intValue : ()I
    //   958: bipush #32
    //   960: irem
    //   961: invokestatic abs : (I)I
    //   964: invokevirtual charAt : (I)C
    //   967: invokevirtual append : (C)Ljava/lang/StringBuilder;
    //   970: pop
    //   971: iload_2
    //   972: ifne -> 1348
    //   975: goto -> 982
    //   978: invokestatic a : (Ljava/lang/Throwable;)Ljava/lang/Throwable;
    //   981: athrow
    //   982: aload_3
    //   983: getstatic burp/Zs5k.ZI : Ljava/lang/String;
    //   986: getstatic burp/Zr9j.Zw : Ljava/lang/Object;
    //   989: checkcast java/math/BigInteger
    //   992: invokevirtual intValue : ()I
    //   995: bipush #32
    //   997: irem
    //   998: invokestatic abs : (I)I
    //   1001: invokevirtual charAt : (I)C
    //   1004: invokevirtual append : (C)Ljava/lang/StringBuilder;
    //   1007: pop
    //   1008: iload_2
    //   1009: ifne -> 1348
    //   1012: goto -> 1019
    //   1015: invokestatic a : (Ljava/lang/Throwable;)Ljava/lang/Throwable;
    //   1018: athrow
    //   1019: aload_3
    //   1020: getstatic burp/Zkc5.ZH : Ljava/lang/String;
    //   1023: getstatic burp/Ztdg.ZE : Ljava/lang/Object;
    //   1026: checkcast java/math/BigInteger
    //   1029: invokevirtual intValue : ()I
    //   1032: bipush #32
    //   1034: irem
    //   1035: invokestatic abs : (I)I
    //   1038: invokevirtual charAt : (I)C
    //   1041: invokevirtual append : (C)Ljava/lang/StringBuilder;
    //   1044: pop
    //   1045: iload_2
    //   1046: ifne -> 1348
    //   1049: goto -> 1056
    //   1052: invokestatic a : (Ljava/lang/Throwable;)Ljava/lang/Throwable;
    //   1055: athrow
    //   1056: aload_3
    //   1057: getstatic burp/Zzxa.Zl : Ljava/lang/String;
    //   1060: getstatic burp/Zmvk.ZK : Ljava/lang/Object;
    //   1063: checkcast java/math/BigInteger
    //   1066: invokevirtual intValue : ()I
    //   1069: bipush #32
    //   1071: irem
    //   1072: invokestatic abs : (I)I
    //   1075: invokevirtual charAt : (I)C
    //   1078: invokevirtual append : (C)Ljava/lang/StringBuilder;
    //   1081: pop
    //   1082: iload_2
    //   1083: ifne -> 1348
    //   1086: goto -> 1093
    //   1089: invokestatic a : (Ljava/lang/Throwable;)Ljava/lang/Throwable;
    //   1092: athrow
    //   1093: aload_3
    //   1094: getstatic burp/Zrxf.ZG : Ljava/lang/String;
    //   1097: getstatic burp/Ze9.Zu : Ljava/lang/Object;
    //   1100: checkcast java/math/BigInteger
    //   1103: invokevirtual intValue : ()I
    //   1106: bipush #32
    //   1108: irem
    //   1109: invokestatic abs : (I)I
    //   1112: invokevirtual charAt : (I)C
    //   1115: invokevirtual append : (C)Ljava/lang/StringBuilder;
    //   1118: pop
    //   1119: iload_2
    //   1120: ifne -> 1348
    //   1123: goto -> 1130
    //   1126: invokestatic a : (Ljava/lang/Throwable;)Ljava/lang/Throwable;
    //   1129: athrow
    //   1130: aload_3
    //   1131: getstatic burp/Zz8o.Zo : Ljava/lang/String;
    //   1134: getstatic burp/Zm5s.ZB : Ljava/lang/Object;
    //   1137: checkcast java/math/BigInteger
    //   1140: invokevirtual intValue : ()I
    //   1143: bipush #32
    //   1145: irem
    //   1146: invokestatic abs : (I)I
    //   1149: invokevirtual charAt : (I)C
    //   1152: invokevirtual append : (C)Ljava/lang/StringBuilder;
    //   1155: pop
    //   1156: iload_2
    //   1157: ifne -> 1348
    //   1160: goto -> 1167
    //   1163: invokestatic a : (Ljava/lang/Throwable;)Ljava/lang/Throwable;
    //   1166: athrow
    //   1167: aload_3
    //   1168: getstatic burp/Zzoc.Zg : Ljava/lang/String;
    //   1171: getstatic burp/Zl5.ZY : Ljava/lang/Object;
    //   1174: checkcast java/math/BigInteger
    //   1177: invokevirtual intValue : ()I
    //   1180: bipush #32
    //   1182: irem
    //   1183: invokestatic abs : (I)I
    //   1186: invokevirtual charAt : (I)C
    //   1189: invokevirtual append : (C)Ljava/lang/StringBuilder;
    //   1192: pop
    //   1193: iload_2
    //   1194: ifne -> 1348
    //   1197: goto -> 1204
    //   1200: invokestatic a : (Ljava/lang/Throwable;)Ljava/lang/Throwable;
    //   1203: athrow
    //   1204: aload_3
    //   1205: getstatic burp/Zspk.ZA : Ljava/lang/String;
    //   1208: getstatic burp/Ztg3.Zg : Ljava/lang/Object;
    //   1211: checkcast java/math/BigInteger
    //   1214: invokevirtual intValue : ()I
    //   1217: bipush #32
    //   1219: irem
    //   1220: invokestatic abs : (I)I
    //   1223: invokevirtual charAt : (I)C
    //   1226: invokevirtual append : (C)Ljava/lang/StringBuilder;
    //   1229: pop
    //   1230: iload_2
    //   1231: ifne -> 1348
    //   1234: goto -> 1241
    //   1237: invokestatic a : (Ljava/lang/Throwable;)Ljava/lang/Throwable;
    //   1240: athrow
    //   1241: aload_3
    //   1242: getstatic burp/Ztw4.Zb : Ljava/lang/String;
    //   1245: getstatic burp/Zzh9.Zv : Ljava/lang/Object;
    //   1248: checkcast java/math/BigInteger
    //   1251: invokevirtual intValue : ()I
    //   1254: bipush #32
    //   1256: irem
    //   1257: invokestatic abs : (I)I
    //   1260: invokevirtual charAt : (I)C
    //   1263: invokevirtual append : (C)Ljava/lang/StringBuilder;
    //   1266: pop
    //   1267: iload_2
    //   1268: ifne -> 1348
    //   1271: goto -> 1278
    //   1274: invokestatic a : (Ljava/lang/Throwable;)Ljava/lang/Throwable;
    //   1277: athrow
    //   1278: aload_3
    //   1279: getstatic burp/Zz0.ZX : Ljava/lang/String;
    //   1282: getstatic burp/Zz8o.Zg : Ljava/lang/Object;
    //   1285: checkcast java/math/BigInteger
    //   1288: invokevirtual intValue : ()I
    //   1291: bipush #32
    //   1293: irem
    //   1294: invokestatic abs : (I)I
    //   1297: invokevirtual charAt : (I)C
    //   1300: invokevirtual append : (C)Ljava/lang/StringBuilder;
    //   1303: pop
    //   1304: iload_2
    //   1305: ifne -> 1348
    //   1308: goto -> 1315
    //   1311: invokestatic a : (Ljava/lang/Throwable;)Ljava/lang/Throwable;
    //   1314: athrow
    //   1315: aload_3
    //   1316: getstatic burp/Zzxa.Zl : Ljava/lang/String;
    //   1319: getstatic burp/Ztdg.ZE : Ljava/lang/Object;
    //   1322: checkcast java/math/BigInteger
    //   1325: invokevirtual intValue : ()I
    //   1328: bipush #32
    //   1330: irem
    //   1331: invokestatic abs : (I)I
    //   1334: invokevirtual charAt : (I)C
    //   1337: invokevirtual append : (C)Ljava/lang/StringBuilder;
    //   1340: pop
    //   1341: goto -> 1348
    //   1344: invokestatic a : (Ljava/lang/Throwable;)Ljava/lang/Throwable;
    //   1347: athrow
    //   1348: iinc #4, 1
    //   1351: iload_2
    //   1352: ifne -> 15
    //   1355: aload_3
    //   1356: invokevirtual toString : ()Ljava/lang/String;
    //   1359: putstatic burp/Zmfw.ZV : Ljava/lang/String;
    //   1362: new java/lang/StringBuilder
    //   1365: dup
    //   1366: invokespecial <init> : ()V
    //   1369: astore #4
    //   1371: iconst_0
    //   1372: istore #5
    //   1374: iload #5
    //   1376: bipush #32
    //   1378: if_icmpge -> 2743
    //   1381: iload #5
    //   1383: tableswitch default -> 2736, 0 -> 1524, 1 -> 1562, 2 -> 1600, 3 -> 1638, 4 -> 1676, 5 -> 1714, 6 -> 1752, 7 -> 1790, 8 -> 1828, 9 -> 1866, 10 -> 1904, 11 -> 1942, 12 -> 1980, 13 -> 2018, 14 -> 2056, 15 -> 2094, 16 -> 2132, 17 -> 2170, 18 -> 2208, 19 -> 2246, 20 -> 2284, 21 -> 2322, 22 -> 2360, 23 -> 2398, 24 -> 2436, 25 -> 2474, 26 -> 2512, 27 -> 2550, 28 -> 2588, 29 -> 2626, 30 -> 2664, 31 -> 2702
    //   1524: aload #4
    //   1526: getstatic burp/Zeju.ZR : Ljava/lang/String;
    //   1529: getstatic burp/Ztsc.Zr : Ljava/lang/Object;
    //   1532: checkcast java/math/BigInteger
    //   1535: invokevirtual intValue : ()I
    //   1538: bipush #32
    //   1540: irem
    //   1541: invokestatic abs : (I)I
    //   1544: invokevirtual charAt : (I)C
    //   1547: invokevirtual append : (C)Ljava/lang/StringBuilder;
    //   1550: pop
    //   1551: iload_2
    //   1552: ifne -> 2736
    //   1555: goto -> 1562
    //   1558: invokestatic a : (Ljava/lang/Throwable;)Ljava/lang/Throwable;
    //   1561: athrow
    //   1562: aload #4
    //   1564: getstatic burp/Zeqw.Zw : Ljava/lang/String;
    //   1567: getstatic burp/Zbsc.ZA : Ljava/lang/Object;
    //   1570: checkcast java/math/BigInteger
    //   1573: invokevirtual intValue : ()I
    //   1576: bipush #32
    //   1578: irem
    //   1579: invokestatic abs : (I)I
    //   1582: invokevirtual charAt : (I)C
    //   1585: invokevirtual append : (C)Ljava/lang/StringBuilder;
    //   1588: pop
    //   1589: iload_2
    //   1590: ifne -> 2736
    //   1593: goto -> 1600
    //   1596: invokestatic a : (Ljava/lang/Throwable;)Ljava/lang/Throwable;
    //   1599: athrow
    //   1600: aload #4
    //   1602: getstatic burp/Zbzj.Zw : Ljava/lang/String;
    //   1605: getstatic burp/Zz0.ZJ : Ljava/lang/Object;
    //   1608: checkcast java/math/BigInteger
    //   1611: invokevirtual intValue : ()I
    //   1614: bipush #32
    //   1616: irem
    //   1617: invokestatic abs : (I)I
    //   1620: invokevirtual charAt : (I)C
    //   1623: invokevirtual append : (C)Ljava/lang/StringBuilder;
    //   1626: pop
    //   1627: iload_2
    //   1628: ifne -> 2736
    //   1631: goto -> 1638
    //   1634: invokestatic a : (Ljava/lang/Throwable;)Ljava/lang/Throwable;
    //   1637: athrow
    //   1638: aload #4
    //   1640: getstatic burp/Zrfh.ZH : Ljava/lang/String;
    //   1643: getstatic burp/Zz8o.Zg : Ljava/lang/Object;
    //   1646: checkcast java/math/BigInteger
    //   1649: invokevirtual intValue : ()I
    //   1652: bipush #32
    //   1654: irem
    //   1655: invokestatic abs : (I)I
    //   1658: invokevirtual charAt : (I)C
    //   1661: invokevirtual append : (C)Ljava/lang/StringBuilder;
    //   1664: pop
    //   1665: iload_2
    //   1666: ifne -> 2736
    //   1669: goto -> 1676
    //   1672: invokestatic a : (Ljava/lang/Throwable;)Ljava/lang/Throwable;
    //   1675: athrow
    //   1676: aload #4
    //   1678: getstatic burp/Zrfh.ZH : Ljava/lang/String;
    //   1681: getstatic burp/Zspk.ZF : Ljava/lang/Object;
    //   1684: checkcast java/math/BigInteger
    //   1687: invokevirtual intValue : ()I
    //   1690: bipush #32
    //   1692: irem
    //   1693: invokestatic abs : (I)I
    //   1696: invokevirtual charAt : (I)C
    //   1699: invokevirtual append : (C)Ljava/lang/StringBuilder;
    //   1702: pop
    //   1703: iload_2
    //   1704: ifne -> 2736
    //   1707: goto -> 1714
    //   1710: invokestatic a : (Ljava/lang/Throwable;)Ljava/lang/Throwable;
    //   1713: athrow
    //   1714: aload #4
    //   1716: getstatic burp/Zl8s.Zn : Ljava/lang/String;
    //   1719: getstatic burp/Zzxa.ZI : Ljava/lang/Object;
    //   1722: checkcast java/math/BigInteger
    //   1725: invokevirtual intValue : ()I
    //   1728: bipush #32
    //   1730: irem
    //   1731: invokestatic abs : (I)I
    //   1734: invokevirtual charAt : (I)C
    //   1737: invokevirtual append : (C)Ljava/lang/StringBuilder;
    //   1740: pop
    //   1741: iload_2
    //   1742: ifne -> 2736
    //   1745: goto -> 1752
    //   1748: invokestatic a : (Ljava/lang/Throwable;)Ljava/lang/Throwable;
    //   1751: athrow
    //   1752: aload #4
    //   1754: getstatic burp/Zxee.Zd : Ljava/lang/String;
    //   1757: getstatic burp/Zrh1.ZF : Ljava/lang/Object;
    //   1760: checkcast java/math/BigInteger
    //   1763: invokevirtual intValue : ()I
    //   1766: bipush #32
    //   1768: irem
    //   1769: invokestatic abs : (I)I
    //   1772: invokevirtual charAt : (I)C
    //   1775: invokevirtual append : (C)Ljava/lang/StringBuilder;
    //   1778: pop
    //   1779: iload_2
    //   1780: ifne -> 2736
    //   1783: goto -> 1790
    //   1786: invokestatic a : (Ljava/lang/Throwable;)Ljava/lang/Throwable;
    //   1789: athrow
    //   1790: aload #4
    //   1792: getstatic burp/Zej5.Zo : Ljava/lang/String;
    //   1795: getstatic burp/Zs5i.ZD : Ljava/lang/Object;
    //   1798: checkcast java/math/BigInteger
    //   1801: invokevirtual intValue : ()I
    //   1804: bipush #32
    //   1806: irem
    //   1807: invokestatic abs : (I)I
    //   1810: invokevirtual charAt : (I)C
    //   1813: invokevirtual append : (C)Ljava/lang/StringBuilder;
    //   1816: pop
    //   1817: iload_2
    //   1818: ifne -> 2736
    //   1821: goto -> 1828
    //   1824: invokestatic a : (Ljava/lang/Throwable;)Ljava/lang/Throwable;
    //   1827: athrow
    //   1828: aload #4
    //   1830: getstatic burp/Zmec.Zi : Ljava/lang/String;
    //   1833: getstatic burp/Zz0.ZJ : Ljava/lang/Object;
    //   1836: checkcast java/math/BigInteger
    //   1839: invokevirtual intValue : ()I
    //   1842: bipush #32
    //   1844: irem
    //   1845: invokestatic abs : (I)I
    //   1848: invokevirtual charAt : (I)C
    //   1851: invokevirtual append : (C)Ljava/lang/StringBuilder;
    //   1854: pop
    //   1855: iload_2
    //   1856: ifne -> 2736
    //   1859: goto -> 1866
    //   1862: invokestatic a : (Ljava/lang/Throwable;)Ljava/lang/Throwable;
    //   1865: athrow
    //   1866: aload #4
    //   1868: getstatic burp/Zenq.ZG : Ljava/lang/String;
    //   1871: getstatic burp/Zm14.ZZ : Ljava/lang/Object;
    //   1874: checkcast java/math/BigInteger
    //   1877: invokevirtual intValue : ()I
    //   1880: bipush #32
    //   1882: irem
    //   1883: invokestatic abs : (I)I
    //   1886: invokevirtual charAt : (I)C
    //   1889: invokevirtual append : (C)Ljava/lang/StringBuilder;
    //   1892: pop
    //   1893: iload_2
    //   1894: ifne -> 2736
    //   1897: goto -> 1904
    //   1900: invokestatic a : (Ljava/lang/Throwable;)Ljava/lang/Throwable;
    //   1903: athrow
    //   1904: aload #4
    //   1906: getstatic burp/Zzhu.ZT : Ljava/lang/String;
    //   1909: getstatic burp/Zenq.Zd : Ljava/lang/Object;
    //   1912: checkcast java/math/BigInteger
    //   1915: invokevirtual intValue : ()I
    //   1918: bipush #32
    //   1920: irem
    //   1921: invokestatic abs : (I)I
    //   1924: invokevirtual charAt : (I)C
    //   1927: invokevirtual append : (C)Ljava/lang/StringBuilder;
    //   1930: pop
    //   1931: iload_2
    //   1932: ifne -> 2736
    //   1935: goto -> 1942
    //   1938: invokestatic a : (Ljava/lang/Throwable;)Ljava/lang/Throwable;
    //   1941: athrow
    //   1942: aload #4
    //   1944: getstatic burp/Zzpj.ZR : Ljava/lang/String;
    //   1947: getstatic burp/Zz8o.Zg : Ljava/lang/Object;
    //   1950: checkcast java/math/BigInteger
    //   1953: invokevirtual intValue : ()I
    //   1956: bipush #32
    //   1958: irem
    //   1959: invokestatic abs : (I)I
    //   1962: invokevirtual charAt : (I)C
    //   1965: invokevirtual append : (C)Ljava/lang/StringBuilder;
    //   1968: pop
    //   1969: iload_2
    //   1970: ifne -> 2736
    //   1973: goto -> 1980
    //   1976: invokestatic a : (Ljava/lang/Throwable;)Ljava/lang/Throwable;
    //   1979: athrow
    //   1980: aload #4
    //   1982: getstatic burp/Zrxf.ZG : Ljava/lang/String;
    //   1985: getstatic burp/Zm5s.ZB : Ljava/lang/Object;
    //   1988: checkcast java/math/BigInteger
    //   1991: invokevirtual intValue : ()I
    //   1994: bipush #32
    //   1996: irem
    //   1997: invokestatic abs : (I)I
    //   2000: invokevirtual charAt : (I)C
    //   2003: invokevirtual append : (C)Ljava/lang/StringBuilder;
    //   2006: pop
    //   2007: iload_2
    //   2008: ifne -> 2736
    //   2011: goto -> 2018
    //   2014: invokestatic a : (Ljava/lang/Throwable;)Ljava/lang/Throwable;
    //   2017: athrow
    //   2018: aload #4
    //   2020: getstatic burp/Zs5k.ZI : Ljava/lang/String;
    //   2023: getstatic burp/Zrt9.Zy : Ljava/lang/Object;
    //   2026: checkcast java/math/BigInteger
    //   2029: invokevirtual intValue : ()I
    //   2032: bipush #32
    //   2034: irem
    //   2035: invokestatic abs : (I)I
    //   2038: invokevirtual charAt : (I)C
    //   2041: invokevirtual append : (C)Ljava/lang/StringBuilder;
    //   2044: pop
    //   2045: iload_2
    //   2046: ifne -> 2736
    //   2049: goto -> 2056
    //   2052: invokestatic a : (Ljava/lang/Throwable;)Ljava/lang/Throwable;
    //   2055: athrow
    //   2056: aload #4
    //   2058: getstatic burp/Zz5l.ZH : Ljava/lang/String;
    //   2061: getstatic burp/Zmec.ZY : Ljava/lang/Object;
    //   2064: checkcast java/math/BigInteger
    //   2067: invokevirtual intValue : ()I
    //   2070: bipush #32
    //   2072: irem
    //   2073: invokestatic abs : (I)I
    //   2076: invokevirtual charAt : (I)C
    //   2079: invokevirtual append : (C)Ljava/lang/StringBuilder;
    //   2082: pop
    //   2083: iload_2
    //   2084: ifne -> 2736
    //   2087: goto -> 2094
    //   2090: invokestatic a : (Ljava/lang/Throwable;)Ljava/lang/Throwable;
    //   2093: athrow
    //   2094: aload #4
    //   2096: getstatic burp/Zktq.Zc : Ljava/lang/String;
    //   2099: getstatic burp/Zmh0.Zt : Ljava/lang/Object;
    //   2102: checkcast java/math/BigInteger
    //   2105: invokevirtual intValue : ()I
    //   2108: bipush #32
    //   2110: irem
    //   2111: invokestatic abs : (I)I
    //   2114: invokevirtual charAt : (I)C
    //   2117: invokevirtual append : (C)Ljava/lang/StringBuilder;
    //   2120: pop
    //   2121: iload_2
    //   2122: ifne -> 2736
    //   2125: goto -> 2132
    //   2128: invokestatic a : (Ljava/lang/Throwable;)Ljava/lang/Throwable;
    //   2131: athrow
    //   2132: aload #4
    //   2134: getstatic burp/Zmly.Zi : Ljava/lang/String;
    //   2137: getstatic burp/Zlzs.ZL : Ljava/lang/Object;
    //   2140: checkcast java/math/BigInteger
    //   2143: invokevirtual intValue : ()I
    //   2146: bipush #32
    //   2148: irem
    //   2149: invokestatic abs : (I)I
    //   2152: invokevirtual charAt : (I)C
    //   2155: invokevirtual append : (C)Ljava/lang/StringBuilder;
    //   2158: pop
    //   2159: iload_2
    //   2160: ifne -> 2736
    //   2163: goto -> 2170
    //   2166: invokestatic a : (Ljava/lang/Throwable;)Ljava/lang/Throwable;
    //   2169: athrow
    //   2170: aload #4
    //   2172: getstatic burp/Zlwi.ZN : Ljava/lang/String;
    //   2175: getstatic burp/Zmly.ZT : Ljava/lang/Object;
    //   2178: checkcast java/math/BigInteger
    //   2181: invokevirtual intValue : ()I
    //   2184: bipush #32
    //   2186: irem
    //   2187: invokestatic abs : (I)I
    //   2190: invokevirtual charAt : (I)C
    //   2193: invokevirtual append : (C)Ljava/lang/StringBuilder;
    //   2196: pop
    //   2197: iload_2
    //   2198: ifne -> 2736
    //   2201: goto -> 2208
    //   2204: invokestatic a : (Ljava/lang/Throwable;)Ljava/lang/Throwable;
    //   2207: athrow
    //   2208: aload #4
    //   2210: getstatic burp/Zxee.Zd : Ljava/lang/String;
    //   2213: getstatic burp/Zsf4.Zr : Ljava/lang/Object;
    //   2216: checkcast java/math/BigInteger
    //   2219: invokevirtual intValue : ()I
    //   2222: bipush #32
    //   2224: irem
    //   2225: invokestatic abs : (I)I
    //   2228: invokevirtual charAt : (I)C
    //   2231: invokevirtual append : (C)Ljava/lang/StringBuilder;
    //   2234: pop
    //   2235: iload_2
    //   2236: ifne -> 2736
    //   2239: goto -> 2246
    //   2242: invokestatic a : (Ljava/lang/Throwable;)Ljava/lang/Throwable;
    //   2245: athrow
    //   2246: aload #4
    //   2248: getstatic burp/Zt5a.Zl : Ljava/lang/String;
    //   2251: getstatic burp/Zmly.ZT : Ljava/lang/Object;
    //   2254: checkcast java/math/BigInteger
    //   2257: invokevirtual intValue : ()I
    //   2260: bipush #32
    //   2262: irem
    //   2263: invokestatic abs : (I)I
    //   2266: invokevirtual charAt : (I)C
    //   2269: invokevirtual append : (C)Ljava/lang/StringBuilder;
    //   2272: pop
    //   2273: iload_2
    //   2274: ifne -> 2736
    //   2277: goto -> 2284
    //   2280: invokestatic a : (Ljava/lang/Throwable;)Ljava/lang/Throwable;
    //   2283: athrow
    //   2284: aload #4
    //   2286: getstatic burp/Zrt9.Zc : Ljava/lang/String;
    //   2289: getstatic burp/Zrh1.ZF : Ljava/lang/Object;
    //   2292: checkcast java/math/BigInteger
    //   2295: invokevirtual intValue : ()I
    //   2298: bipush #32
    //   2300: irem
    //   2301: invokestatic abs : (I)I
    //   2304: invokevirtual charAt : (I)C
    //   2307: invokevirtual append : (C)Ljava/lang/StringBuilder;
    //   2310: pop
    //   2311: iload_2
    //   2312: ifne -> 2736
    //   2315: goto -> 2322
    //   2318: invokestatic a : (Ljava/lang/Throwable;)Ljava/lang/Throwable;
    //   2321: athrow
    //   2322: aload #4
    //   2324: getstatic burp/Zzb2.ZJ : Ljava/lang/String;
    //   2327: getstatic burp/Zr4z.ZH : Ljava/lang/Object;
    //   2330: checkcast java/math/BigInteger
    //   2333: invokevirtual intValue : ()I
    //   2336: bipush #32
    //   2338: irem
    //   2339: invokestatic abs : (I)I
    //   2342: invokevirtual charAt : (I)C
    //   2345: invokevirtual append : (C)Ljava/lang/StringBuilder;
    //   2348: pop
    //   2349: iload_2
    //   2350: ifne -> 2736
    //   2353: goto -> 2360
    //   2356: invokestatic a : (Ljava/lang/Throwable;)Ljava/lang/Throwable;
    //   2359: athrow
    //   2360: aload #4
    //   2362: getstatic burp/Zevc.ZF : Ljava/lang/String;
    //   2365: getstatic burp/Zmvk.ZK : Ljava/lang/Object;
    //   2368: checkcast java/math/BigInteger
    //   2371: invokevirtual intValue : ()I
    //   2374: bipush #32
    //   2376: irem
    //   2377: invokestatic abs : (I)I
    //   2380: invokevirtual charAt : (I)C
    //   2383: invokevirtual append : (C)Ljava/lang/StringBuilder;
    //   2386: pop
    //   2387: iload_2
    //   2388: ifne -> 2736
    //   2391: goto -> 2398
    //   2394: invokestatic a : (Ljava/lang/Throwable;)Ljava/lang/Throwable;
    //   2397: athrow
    //   2398: aload #4
    //   2400: getstatic burp/Zrxf.ZG : Ljava/lang/String;
    //   2403: getstatic burp/Zrct.ZV : Ljava/lang/Object;
    //   2406: checkcast java/math/BigInteger
    //   2409: invokevirtual intValue : ()I
    //   2412: bipush #32
    //   2414: irem
    //   2415: invokestatic abs : (I)I
    //   2418: invokevirtual charAt : (I)C
    //   2421: invokevirtual append : (C)Ljava/lang/StringBuilder;
    //   2424: pop
    //   2425: iload_2
    //   2426: ifne -> 2736
    //   2429: goto -> 2436
    //   2432: invokestatic a : (Ljava/lang/Throwable;)Ljava/lang/Throwable;
    //   2435: athrow
    //   2436: aload #4
    //   2438: getstatic burp/Zxee.Zd : Ljava/lang/String;
    //   2441: getstatic burp/Zrnw.ZN : Ljava/lang/Object;
    //   2444: checkcast java/math/BigInteger
    //   2447: invokevirtual intValue : ()I
    //   2450: bipush #32
    //   2452: irem
    //   2453: invokestatic abs : (I)I
    //   2456: invokevirtual charAt : (I)C
    //   2459: invokevirtual append : (C)Ljava/lang/StringBuilder;
    //   2462: pop
    //   2463: iload_2
    //   2464: ifne -> 2736
    //   2467: goto -> 2474
    //   2470: invokestatic a : (Ljava/lang/Throwable;)Ljava/lang/Throwable;
    //   2473: athrow
    //   2474: aload #4
    //   2476: getstatic burp/Zgs6.ZD : Ljava/lang/String;
    //   2479: getstatic burp/Zrnw.ZN : Ljava/lang/Object;
    //   2482: checkcast java/math/BigInteger
    //   2485: invokevirtual intValue : ()I
    //   2488: bipush #32
    //   2490: irem
    //   2491: invokestatic abs : (I)I
    //   2494: invokevirtual charAt : (I)C
    //   2497: invokevirtual append : (C)Ljava/lang/StringBuilder;
    //   2500: pop
    //   2501: iload_2
    //   2502: ifne -> 2736
    //   2505: goto -> 2512
    //   2508: invokestatic a : (Ljava/lang/Throwable;)Ljava/lang/Throwable;
    //   2511: athrow
    //   2512: aload #4
    //   2514: getstatic burp/Zsf4.ZA : Ljava/lang/String;
    //   2517: getstatic burp/Ze9.Zu : Ljava/lang/Object;
    //   2520: checkcast java/math/BigInteger
    //   2523: invokevirtual intValue : ()I
    //   2526: bipush #32
    //   2528: irem
    //   2529: invokestatic abs : (I)I
    //   2532: invokevirtual charAt : (I)C
    //   2535: invokevirtual append : (C)Ljava/lang/StringBuilder;
    //   2538: pop
    //   2539: iload_2
    //   2540: ifne -> 2736
    //   2543: goto -> 2550
    //   2546: invokestatic a : (Ljava/lang/Throwable;)Ljava/lang/Throwable;
    //   2549: athrow
    //   2550: aload #4
    //   2552: getstatic burp/Zevc.ZF : Ljava/lang/String;
    //   2555: getstatic burp/Zb8_.ZT : Ljava/lang/Object;
    //   2558: checkcast java/math/BigInteger
    //   2561: invokevirtual intValue : ()I
    //   2564: bipush #32
    //   2566: irem
    //   2567: invokestatic abs : (I)I
    //   2570: invokevirtual charAt : (I)C
    //   2573: invokevirtual append : (C)Ljava/lang/StringBuilder;
    //   2576: pop
    //   2577: iload_2
    //   2578: ifne -> 2736
    //   2581: goto -> 2588
    //   2584: invokestatic a : (Ljava/lang/Throwable;)Ljava/lang/Throwable;
    //   2587: athrow
    //   2588: aload #4
    //   2590: getstatic burp/Zs5k.ZI : Ljava/lang/String;
    //   2593: getstatic burp/Zeju.Zk : Ljava/lang/Object;
    //   2596: checkcast java/math/BigInteger
    //   2599: invokevirtual intValue : ()I
    //   2602: bipush #32
    //   2604: irem
    //   2605: invokestatic abs : (I)I
    //   2608: invokevirtual charAt : (I)C
    //   2611: invokevirtual append : (C)Ljava/lang/StringBuilder;
    //   2614: pop
    //   2615: iload_2
    //   2616: ifne -> 2736
    //   2619: goto -> 2626
    //   2622: invokestatic a : (Ljava/lang/Throwable;)Ljava/lang/Throwable;
    //   2625: athrow
    //   2626: aload #4
    //   2628: getstatic burp/Zsot.Zb : Ljava/lang/String;
    //   2631: getstatic burp/Zrfh.ZJ : Ljava/lang/Object;
    //   2634: checkcast java/math/BigInteger
    //   2637: invokevirtual intValue : ()I
    //   2640: bipush #32
    //   2642: irem
    //   2643: invokestatic abs : (I)I
    //   2646: invokevirtual charAt : (I)C
    //   2649: invokevirtual append : (C)Ljava/lang/StringBuilder;
    //   2652: pop
    //   2653: iload_2
    //   2654: ifne -> 2736
    //   2657: goto -> 2664
    //   2660: invokestatic a : (Ljava/lang/Throwable;)Ljava/lang/Throwable;
    //   2663: athrow
    //   2664: aload #4
    //   2666: getstatic burp/Zl15.ZI : Ljava/lang/String;
    //   2669: getstatic burp/Zrt9.Zy : Ljava/lang/Object;
    //   2672: checkcast java/math/BigInteger
    //   2675: invokevirtual intValue : ()I
    //   2678: bipush #32
    //   2680: irem
    //   2681: invokestatic abs : (I)I
    //   2684: invokevirtual charAt : (I)C
    //   2687: invokevirtual append : (C)Ljava/lang/StringBuilder;
    //   2690: pop
    //   2691: iload_2
    //   2692: ifne -> 2736
    //   2695: goto -> 2702
    //   2698: invokestatic a : (Ljava/lang/Throwable;)Ljava/lang/Throwable;
    //   2701: athrow
    //   2702: aload #4
    //   2704: getstatic burp/Zmly.Zi : Ljava/lang/String;
    //   2707: getstatic burp/Zmdm.ZZ : Ljava/lang/Object;
    //   2710: checkcast java/math/BigInteger
    //   2713: invokevirtual intValue : ()I
    //   2716: bipush #32
    //   2718: irem
    //   2719: invokestatic abs : (I)I
    //   2722: invokevirtual charAt : (I)C
    //   2725: invokevirtual append : (C)Ljava/lang/StringBuilder;
    //   2728: pop
    //   2729: goto -> 2736
    //   2732: invokestatic a : (Ljava/lang/Throwable;)Ljava/lang/Throwable;
    //   2735: athrow
    //   2736: iinc #5, 1
    //   2739: iload_2
    //   2740: ifne -> 1374
    //   2743: aload #4
    //   2745: invokevirtual toString : ()Ljava/lang/String;
    //   2748: putstatic burp/Zg1k.Ze : Ljava/lang/String;
    //   2751: getstatic burp/Zrx5.ZE : Ljava/lang/Object;
    //   2754: checkcast java/math/BigInteger
    //   2757: invokevirtual toByteArray : ()[B
    //   2760: astore #5
    //   2762: aload #5
    //   2764: arraylength
    //   2765: iconst_2
    //   2766: iadd
    //   2767: newarray byte
    //   2769: astore #7
    //   2771: iconst_0
    //   2772: istore #8
    //   2774: iload #8
    //   2776: aload #5
    //   2778: arraylength
    //   2779: if_icmpge -> 2799
    //   2782: aload #7
    //   2784: iload #8
    //   2786: aload #5
    //   2788: iload #8
    //   2790: baload
    //   2791: bastore
    //   2792: iinc #8, 1
    //   2795: iload_2
    //   2796: ifne -> 2774
    //   2799: aload #7
    //   2801: arraylength
    //   2802: iconst_3
    //   2803: idiv
    //   2804: iconst_4
    //   2805: imul
    //   2806: newarray byte
    //   2808: astore #6
    //   2810: iconst_0
    //   2811: istore #8
    //   2813: iconst_0
    //   2814: istore #9
    //   2816: iload #8
    //   2818: aload #5
    //   2820: arraylength
    //   2821: if_icmpge -> 2932
    //   2824: aload #6
    //   2826: iload #9
    //   2828: aload #7
    //   2830: iload #8
    //   2832: baload
    //   2833: iconst_2
    //   2834: iushr
    //   2835: bipush #63
    //   2837: iand
    //   2838: i2b
    //   2839: bastore
    //   2840: aload #6
    //   2842: iload #9
    //   2844: iconst_1
    //   2845: iadd
    //   2846: aload #7
    //   2848: iload #8
    //   2850: iconst_1
    //   2851: iadd
    //   2852: baload
    //   2853: iconst_4
    //   2854: iushr
    //   2855: bipush #15
    //   2857: iand
    //   2858: aload #7
    //   2860: iload #8
    //   2862: baload
    //   2863: iconst_4
    //   2864: ishl
    //   2865: bipush #63
    //   2867: iand
    //   2868: ior
    //   2869: i2b
    //   2870: bastore
    //   2871: aload #6
    //   2873: iload #9
    //   2875: iconst_2
    //   2876: iadd
    //   2877: aload #7
    //   2879: iload #8
    //   2881: iconst_2
    //   2882: iadd
    //   2883: baload
    //   2884: bipush #6
    //   2886: iushr
    //   2887: iconst_3
    //   2888: iand
    //   2889: aload #7
    //   2891: iload #8
    //   2893: iconst_1
    //   2894: iadd
    //   2895: baload
    //   2896: iconst_2
    //   2897: ishl
    //   2898: bipush #63
    //   2900: iand
    //   2901: ior
    //   2902: i2b
    //   2903: bastore
    //   2904: aload #6
    //   2906: iload #9
    //   2908: iconst_3
    //   2909: iadd
    //   2910: aload #7
    //   2912: iload #8
    //   2914: iconst_2
    //   2915: iadd
    //   2916: baload
    //   2917: bipush #63
    //   2919: iand
    //   2920: i2b
    //   2921: bastore
    //   2922: iinc #8, 3
    //   2925: iinc #9, 4
    //   2928: iload_2
    //   2929: ifne -> 2816
    //   2932: iconst_0
    //   2933: istore #8
    //   2935: iload #8
    //   2937: aload #6
    //   2939: arraylength
    //   2940: if_icmpge -> 3124
    //   2943: aload #6
    //   2945: iload #8
    //   2947: baload
    //   2948: bipush #26
    //   2950: if_icmpge -> 2978
    //   2953: aload #6
    //   2955: iload #8
    //   2957: aload #6
    //   2959: iload #8
    //   2961: baload
    //   2962: bipush #65
    //   2964: iadd
    //   2965: i2b
    //   2966: bastore
    //   2967: iload_2
    //   2968: ifne -> 3117
    //   2971: goto -> 2978
    //   2974: invokestatic a : (Ljava/lang/Throwable;)Ljava/lang/Throwable;
    //   2977: athrow
    //   2978: aload #6
    //   2980: iload #8
    //   2982: baload
    //   2983: bipush #52
    //   2985: if_icmpge -> 3023
    //   2988: goto -> 2995
    //   2991: invokestatic a : (Ljava/lang/Throwable;)Ljava/lang/Throwable;
    //   2994: athrow
    //   2995: aload #6
    //   2997: iload #8
    //   2999: aload #6
    //   3001: iload #8
    //   3003: baload
    //   3004: bipush #97
    //   3006: iadd
    //   3007: bipush #26
    //   3009: isub
    //   3010: i2b
    //   3011: bastore
    //   3012: iload_2
    //   3013: ifne -> 3117
    //   3016: goto -> 3023
    //   3019: invokestatic a : (Ljava/lang/Throwable;)Ljava/lang/Throwable;
    //   3022: athrow
    //   3023: aload #6
    //   3025: iload #8
    //   3027: baload
    //   3028: bipush #62
    //   3030: if_icmpge -> 3068
    //   3033: goto -> 3040
    //   3036: invokestatic a : (Ljava/lang/Throwable;)Ljava/lang/Throwable;
    //   3039: athrow
    //   3040: aload #6
    //   3042: iload #8
    //   3044: aload #6
    //   3046: iload #8
    //   3048: baload
    //   3049: bipush #48
    //   3051: iadd
    //   3052: bipush #52
    //   3054: isub
    //   3055: i2b
    //   3056: bastore
    //   3057: iload_2
    //   3058: ifne -> 3117
    //   3061: goto -> 3068
    //   3064: invokestatic a : (Ljava/lang/Throwable;)Ljava/lang/Throwable;
    //   3067: athrow
    //   3068: aload #6
    //   3070: iload #8
    //   3072: baload
    //   3073: bipush #63
    //   3075: if_icmpge -> 3103
    //   3078: goto -> 3085
    //   3081: invokestatic a : (Ljava/lang/Throwable;)Ljava/lang/Throwable;
    //   3084: athrow
    //   3085: aload #6
    //   3087: iload #8
    //   3089: bipush #43
    //   3091: bastore
    //   3092: iload_2
    //   3093: ifne -> 3117
    //   3096: goto -> 3103
    //   3099: invokestatic a : (Ljava/lang/Throwable;)Ljava/lang/Throwable;
    //   3102: athrow
    //   3103: aload #6
    //   3105: iload #8
    //   3107: bipush #47
    //   3109: bastore
    //   3110: goto -> 3117
    //   3113: invokestatic a : (Ljava/lang/Throwable;)Ljava/lang/Throwable;
    //   3116: athrow
    //   3117: iinc #8, 1
    //   3120: iload_2
    //   3121: ifne -> 2935
    //   3124: aload #6
    //   3126: arraylength
    //   3127: iconst_1
    //   3128: isub
    //   3129: istore #8
    //   3131: iload #8
    //   3133: aload #5
    //   3135: arraylength
    //   3136: iconst_4
    //   3137: imul
    //   3138: iconst_3
    //   3139: idiv
    //   3140: if_icmple -> 3157
    //   3143: aload #6
    //   3145: iload #8
    //   3147: bipush #61
    //   3149: bastore
    //   3150: iinc #8, -1
    //   3153: iload_2
    //   3154: ifne -> 3131
    //   3157: new java/math/BigInteger
    //   3160: dup
    //   3161: aload #6
    //   3163: invokespecial <init> : ([B)V
    //   3166: invokevirtual abs : ()Ljava/math/BigInteger;
    //   3169: putstatic burp/Zrt9.Zy : Ljava/lang/Object;
    //   3172: sipush #-13691
    //   3175: sipush #19794
    //   3178: invokestatic a : (II)Ljava/lang/String;
    //   3181: iconst_1
    //   3182: ldc burp/Zkv2
    //   3184: invokevirtual getClassLoader : ()Ljava/lang/ClassLoader;
    //   3187: invokestatic forName : (Ljava/lang/String;ZLjava/lang/ClassLoader;)Ljava/lang/Class;
    //   3190: invokevirtual getDeclaredFields : ()[Ljava/lang/reflect/Field;
    //   3193: astore #5
    //   3195: aload #5
    //   3197: arraylength
    //   3198: istore #6
    //   3200: iconst_0
    //   3201: istore #7
    //   3203: iload #7
    //   3205: iload #6
    //   3207: if_icmpge -> 3345
    //   3210: aload #5
    //   3212: iload #7
    //   3214: aaload
    //   3215: astore #8
    //   3217: aload #8
    //   3219: invokevirtual getModifiers : ()I
    //   3222: invokestatic isStatic : (I)Z
    //   3225: ifne -> 3235
    //   3228: goto -> 3338
    //   3231: invokestatic a : (Ljava/lang/Throwable;)Ljava/lang/Throwable;
    //   3234: athrow
    //   3235: aload #8
    //   3237: invokevirtual getType : ()Ljava/lang/Class;
    //   3240: astore #9
    //   3242: aload #9
    //   3244: ifnull -> 3325
    //   3247: aload #9
    //   3249: invokevirtual isPrimitive : ()Z
    //   3252: ifne -> 3325
    //   3255: goto -> 3262
    //   3258: invokestatic a : (Ljava/lang/Throwable;)Ljava/lang/Throwable;
    //   3261: athrow
    //   3262: aload #9
    //   3264: invokevirtual getPackage : ()Ljava/lang/Package;
    //   3267: ifnull -> 3325
    //   3270: goto -> 3277
    //   3273: invokestatic a : (Ljava/lang/Throwable;)Ljava/lang/Throwable;
    //   3276: athrow
    //   3277: aload #9
    //   3279: invokevirtual getPackage : ()Ljava/lang/Package;
    //   3282: invokevirtual getName : ()Ljava/lang/String;
    //   3285: ifnull -> 3325
    //   3288: goto -> 3295
    //   3291: invokestatic a : (Ljava/lang/Throwable;)Ljava/lang/Throwable;
    //   3294: athrow
    //   3295: aload #9
    //   3297: invokevirtual getPackage : ()Ljava/lang/Package;
    //   3300: invokevirtual getName : ()Ljava/lang/String;
    //   3303: sipush #-13687
    //   3306: sipush #12853
    //   3309: invokestatic a : (II)Ljava/lang/String;
    //   3312: invokevirtual startsWith : (Ljava/lang/String;)Z
    //   3315: ifne -> 3325
    //   3318: goto -> 3325
    //   3321: invokestatic a : (Ljava/lang/Throwable;)Ljava/lang/Throwable;
    //   3324: athrow
    //   3325: aload #8
    //   3327: iconst_1
    //   3328: invokevirtual setAccessible : (Z)V
    //   3331: aload #8
    //   3333: aconst_null
    //   3334: invokevirtual get : (Ljava/lang/Object;)Ljava/lang/Object;
    //   3337: pop
    //   3338: iinc #7, 1
    //   3341: iload_2
    //   3342: ifne -> 3203
    //   3345: sipush #-13678
    //   3348: sipush #-8749
    //   3351: invokestatic a : (II)Ljava/lang/String;
    //   3354: invokestatic forName : (Ljava/lang/String;)Ljava/lang/Class;
    //   3357: invokevirtual getDeclaredMethods : ()[Ljava/lang/reflect/Method;
    //   3360: astore #5
    //   3362: aload #5
    //   3364: arraylength
    //   3365: istore #6
    //   3367: iconst_0
    //   3368: istore #7
    //   3370: iload #7
    //   3372: iload #6
    //   3374: if_icmpge -> 3507
    //   3377: aload #5
    //   3379: iload #7
    //   3381: aaload
    //   3382: astore #8
    //   3384: aload #8
    //   3386: invokevirtual getParameterTypes : ()[Ljava/lang/Class;
    //   3389: pop
    //   3390: aload #8
    //   3392: invokevirtual getModifiers : ()I
    //   3395: invokestatic isStatic : (I)Z
    //   3398: ifeq -> 3493
    //   3401: aload #8
    //   3403: invokevirtual getParameterTypes : ()[Ljava/lang/Class;
    //   3406: arraylength
    //   3407: iconst_2
    //   3408: if_icmpne -> 3493
    //   3411: goto -> 3418
    //   3414: invokestatic a : (Ljava/lang/Throwable;)Ljava/lang/Throwable;
    //   3417: athrow
    //   3418: aload #8
    //   3420: invokevirtual getReturnType : ()Ljava/lang/Class;
    //   3423: getstatic java/lang/Void.TYPE : Ljava/lang/Class;
    //   3426: invokevirtual equals : (Ljava/lang/Object;)Z
    //   3429: ifeq -> 3493
    //   3432: goto -> 3439
    //   3435: invokestatic a : (Ljava/lang/Throwable;)Ljava/lang/Throwable;
    //   3438: athrow
    //   3439: aload #8
    //   3441: iconst_1
    //   3442: invokevirtual setAccessible : (Z)V
    //   3445: aload #8
    //   3447: aconst_null
    //   3448: iconst_2
    //   3449: anewarray java/lang/Object
    //   3452: dup
    //   3453: iconst_0
    //   3454: aload_0
    //   3455: aastore
    //   3456: dup
    //   3457: iconst_1
    //   3458: aload_1
    //   3459: ifnonnull -> 3477
    //   3462: goto -> 3469
    //   3465: invokestatic a : (Ljava/lang/Throwable;)Ljava/lang/Throwable;
    //   3468: athrow
    //   3469: aload_1
    //   3470: goto -> 3484
    //   3473: invokestatic a : (Ljava/lang/Throwable;)Ljava/lang/Throwable;
    //   3476: athrow
    //   3477: aload_1
    //   3478: checkcast [B
    //   3481: invokevirtual clone : ()Ljava/lang/Object;
    //   3484: aastore
    //   3485: invokevirtual invoke : (Ljava/lang/Object;[Ljava/lang/Object;)Ljava/lang/Object;
    //   3488: pop
    //   3489: iload_2
    //   3490: ifne -> 3507
    //   3493: iinc #7, 1
    //   3496: iload_2
    //   3497: ifne -> 3370
    //   3500: goto -> 3507
    //   3503: invokestatic a : (Ljava/lang/Throwable;)Ljava/lang/Throwable;
    //   3506: athrow
    //   3507: iconst_0
    //   3508: istore #5
    //   3510: getstatic burp/Zrt9.Zc : Ljava/lang/String;
    //   3513: getstatic burp/Zm5s.ZB : Ljava/lang/Object;
    //   3516: checkcast java/math/BigInteger
    //   3519: invokevirtual intValue : ()I
    //   3522: bipush #32
    //   3524: irem
    //   3525: invokestatic abs : (I)I
    //   3528: invokevirtual charAt : (I)C
    //   3531: getstatic burp/Zrx5.ZD : Ljava/lang/String;
    //   3534: getstatic burp/Zs5k.Zg : Ljava/lang/Object;
    //   3537: checkcast java/math/BigInteger
    //   3540: invokevirtual intValue : ()I
    //   3543: bipush #32
    //   3545: irem
    //   3546: invokestatic abs : (I)I
    //   3549: invokevirtual charAt : (I)C
    //   3552: if_icmple -> 3897
    //   3555: sipush #-13692
    //   3558: sipush #279
    //   3561: invokestatic a : (II)Ljava/lang/String;
    //   3564: iconst_1
    //   3565: ldc burp/Zgjs
    //   3567: invokevirtual getClassLoader : ()Ljava/lang/ClassLoader;
    //   3570: invokestatic forName : (Ljava/lang/String;ZLjava/lang/ClassLoader;)Ljava/lang/Class;
    //   3573: invokevirtual getDeclaredFields : ()[Ljava/lang/reflect/Field;
    //   3576: astore #6
    //   3578: aload #6
    //   3580: arraylength
    //   3581: istore #7
    //   3583: iconst_0
    //   3584: istore #8
    //   3586: iload #8
    //   3588: iload #7
    //   3590: if_icmpge -> 3728
    //   3593: aload #6
    //   3595: iload #8
    //   3597: aaload
    //   3598: astore #9
    //   3600: aload #9
    //   3602: invokevirtual getModifiers : ()I
    //   3605: invokestatic isStatic : (I)Z
    //   3608: ifne -> 3618
    //   3611: goto -> 3721
    //   3614: invokestatic a : (Ljava/lang/Throwable;)Ljava/lang/Throwable;
    //   3617: athrow
    //   3618: aload #9
    //   3620: invokevirtual getType : ()Ljava/lang/Class;
    //   3623: astore #10
    //   3625: aload #10
    //   3627: ifnull -> 3708
    //   3630: aload #10
    //   3632: invokevirtual isPrimitive : ()Z
    //   3635: ifne -> 3708
    //   3638: goto -> 3645
    //   3641: invokestatic a : (Ljava/lang/Throwable;)Ljava/lang/Throwable;
    //   3644: athrow
    //   3645: aload #10
    //   3647: invokevirtual getPackage : ()Ljava/lang/Package;
    //   3650: ifnull -> 3708
    //   3653: goto -> 3660
    //   3656: invokestatic a : (Ljava/lang/Throwable;)Ljava/lang/Throwable;
    //   3659: athrow
    //   3660: aload #10
    //   3662: invokevirtual getPackage : ()Ljava/lang/Package;
    //   3665: invokevirtual getName : ()Ljava/lang/String;
    //   3668: ifnull -> 3708
    //   3671: goto -> 3678
    //   3674: invokestatic a : (Ljava/lang/Throwable;)Ljava/lang/Throwable;
    //   3677: athrow
    //   3678: aload #10
    //   3680: invokevirtual getPackage : ()Ljava/lang/Package;
    //   3683: invokevirtual getName : ()Ljava/lang/String;
    //   3686: sipush #-13672
    //   3689: sipush #28559
    //   3692: invokestatic a : (II)Ljava/lang/String;
    //   3695: invokevirtual startsWith : (Ljava/lang/String;)Z
    //   3698: ifne -> 3708
    //   3701: goto -> 3708
    //   3704: invokestatic a : (Ljava/lang/Throwable;)Ljava/lang/Throwable;
    //   3707: athrow
    //   3708: aload #9
    //   3710: iconst_1
    //   3711: invokevirtual setAccessible : (Z)V
    //   3714: aload #9
    //   3716: aconst_null
    //   3717: invokevirtual get : (Ljava/lang/Object;)Ljava/lang/Object;
    //   3720: pop
    //   3721: iinc #8, 1
    //   3724: iload_2
    //   3725: ifne -> 3586
    //   3728: sipush #-13690
    //   3731: sipush #-5557
    //   3734: invokestatic a : (II)Ljava/lang/String;
    //   3737: invokestatic forName : (Ljava/lang/String;)Ljava/lang/Class;
    //   3740: invokevirtual getDeclaredMethods : ()[Ljava/lang/reflect/Method;
    //   3743: astore #6
    //   3745: aload #6
    //   3747: arraylength
    //   3748: istore #7
    //   3750: iconst_0
    //   3751: istore #8
    //   3753: iload #8
    //   3755: iload #7
    //   3757: if_icmpge -> 3894
    //   3760: aload #6
    //   3762: iload #8
    //   3764: aaload
    //   3765: astore #9
    //   3767: aload #9
    //   3769: invokevirtual getParameterTypes : ()[Ljava/lang/Class;
    //   3772: pop
    //   3773: aload #9
    //   3775: invokevirtual getModifiers : ()I
    //   3778: invokestatic isStatic : (I)Z
    //   3781: ifeq -> 3880
    //   3784: aload #9
    //   3786: invokevirtual getParameterTypes : ()[Ljava/lang/Class;
    //   3789: arraylength
    //   3790: iconst_2
    //   3791: if_icmpne -> 3880
    //   3794: goto -> 3801
    //   3797: invokestatic a : (Ljava/lang/Throwable;)Ljava/lang/Throwable;
    //   3800: athrow
    //   3801: aload #9
    //   3803: invokevirtual getReturnType : ()Ljava/lang/Class;
    //   3806: getstatic java/lang/Boolean.TYPE : Ljava/lang/Class;
    //   3809: if_acmpne -> 3880
    //   3812: goto -> 3819
    //   3815: invokestatic a : (Ljava/lang/Throwable;)Ljava/lang/Throwable;
    //   3818: athrow
    //   3819: aload #9
    //   3821: iconst_1
    //   3822: invokevirtual setAccessible : (Z)V
    //   3825: aload #9
    //   3827: aconst_null
    //   3828: iconst_2
    //   3829: anewarray java/lang/Object
    //   3832: dup
    //   3833: iconst_0
    //   3834: aload_0
    //   3835: aastore
    //   3836: dup
    //   3837: iconst_1
    //   3838: aload_1
    //   3839: ifnonnull -> 3857
    //   3842: goto -> 3849
    //   3845: invokestatic a : (Ljava/lang/Throwable;)Ljava/lang/Throwable;
    //   3848: athrow
    //   3849: aload_1
    //   3850: goto -> 3864
    //   3853: invokestatic a : (Ljava/lang/Throwable;)Ljava/lang/Throwable;
    //   3856: athrow
    //   3857: aload_1
    //   3858: checkcast [B
    //   3861: invokevirtual clone : ()Ljava/lang/Object;
    //   3864: aastore
    //   3865: invokevirtual invoke : (Ljava/lang/Object;[Ljava/lang/Object;)Ljava/lang/Object;
    //   3868: checkcast java/lang/Boolean
    //   3871: invokevirtual booleanValue : ()Z
    //   3874: istore #5
    //   3876: iload_2
    //   3877: ifne -> 3894
    //   3880: iinc #8, 1
    //   3883: iload_2
    //   3884: ifne -> 3753
    //   3887: goto -> 3894
    //   3890: invokestatic a : (Ljava/lang/Throwable;)Ljava/lang/Throwable;
    //   3893: athrow
    //   3894: goto -> 4236
    //   3897: sipush #-13682
    //   3900: sipush #5599
    //   3903: invokestatic a : (II)Ljava/lang/String;
    //   3906: iconst_1
    //   3907: ldc burp/Zkk6
    //   3909: invokevirtual getClassLoader : ()Ljava/lang/ClassLoader;
    //   3912: invokestatic forName : (Ljava/lang/String;ZLjava/lang/ClassLoader;)Ljava/lang/Class;
    //   3915: invokevirtual getDeclaredFields : ()[Ljava/lang/reflect/Field;
    //   3918: astore #6
    //   3920: aload #6
    //   3922: arraylength
    //   3923: istore #7
    //   3925: iconst_0
    //   3926: istore #8
    //   3928: iload #8
    //   3930: iload #7
    //   3932: if_icmpge -> 4070
    //   3935: aload #6
    //   3937: iload #8
    //   3939: aaload
    //   3940: astore #9
    //   3942: aload #9
    //   3944: invokevirtual getModifiers : ()I
    //   3947: invokestatic isStatic : (I)Z
    //   3950: ifne -> 3960
    //   3953: goto -> 4063
    //   3956: invokestatic a : (Ljava/lang/Throwable;)Ljava/lang/Throwable;
    //   3959: athrow
    //   3960: aload #9
    //   3962: invokevirtual getType : ()Ljava/lang/Class;
    //   3965: astore #10
    //   3967: aload #10
    //   3969: ifnull -> 4050
    //   3972: aload #10
    //   3974: invokevirtual isPrimitive : ()Z
    //   3977: ifne -> 4050
    //   3980: goto -> 3987
    //   3983: invokestatic a : (Ljava/lang/Throwable;)Ljava/lang/Throwable;
    //   3986: athrow
    //   3987: aload #10
    //   3989: invokevirtual getPackage : ()Ljava/lang/Package;
    //   3992: ifnull -> 4050
    //   3995: goto -> 4002
    //   3998: invokestatic a : (Ljava/lang/Throwable;)Ljava/lang/Throwable;
    //   4001: athrow
    //   4002: aload #10
    //   4004: invokevirtual getPackage : ()Ljava/lang/Package;
    //   4007: invokevirtual getName : ()Ljava/lang/String;
    //   4010: ifnull -> 4050
    //   4013: goto -> 4020
    //   4016: invokestatic a : (Ljava/lang/Throwable;)Ljava/lang/Throwable;
    //   4019: athrow
    //   4020: aload #10
    //   4022: invokevirtual getPackage : ()Ljava/lang/Package;
    //   4025: invokevirtual getName : ()Ljava/lang/String;
    //   4028: sipush #-13672
    //   4031: sipush #28559
    //   4034: invokestatic a : (II)Ljava/lang/String;
    //   4037: invokevirtual startsWith : (Ljava/lang/String;)Z
    //   4040: ifne -> 4050
    //   4043: goto -> 4050
    //   4046: invokestatic a : (Ljava/lang/Throwable;)Ljava/lang/Throwable;
    //   4049: athrow
    //   4050: aload #9
    //   4052: iconst_1
    //   4053: invokevirtual setAccessible : (Z)V
    //   4056: aload #9
    //   4058: aconst_null
    //   4059: invokevirtual get : (Ljava/lang/Object;)Ljava/lang/Object;
    //   4062: pop
    //   4063: iinc #8, 1
    //   4066: iload_2
    //   4067: ifne -> 3928
    //   4070: sipush #-13684
    //   4073: sipush #25400
    //   4076: invokestatic a : (II)Ljava/lang/String;
    //   4079: invokestatic forName : (Ljava/lang/String;)Ljava/lang/Class;
    //   4082: invokevirtual getDeclaredMethods : ()[Ljava/lang/reflect/Method;
    //   4085: astore #6
    //   4087: aload #6
    //   4089: arraylength
    //   4090: istore #7
    //   4092: iconst_0
    //   4093: istore #8
    //   4095: iload #8
    //   4097: iload #7
    //   4099: if_icmpge -> 4236
    //   4102: aload #6
    //   4104: iload #8
    //   4106: aaload
    //   4107: astore #9
    //   4109: aload #9
    //   4111: invokevirtual getParameterTypes : ()[Ljava/lang/Class;
    //   4114: pop
    //   4115: aload #9
    //   4117: invokevirtual getModifiers : ()I
    //   4120: invokestatic isStatic : (I)Z
    //   4123: ifeq -> 4222
    //   4126: aload #9
    //   4128: invokevirtual getParameterTypes : ()[Ljava/lang/Class;
    //   4131: arraylength
    //   4132: iconst_2
    //   4133: if_icmpne -> 4222
    //   4136: goto -> 4143
    //   4139: invokestatic a : (Ljava/lang/Throwable;)Ljava/lang/Throwable;
    //   4142: athrow
    //   4143: aload #9
    //   4145: invokevirtual getReturnType : ()Ljava/lang/Class;
    //   4148: getstatic java/lang/Boolean.TYPE : Ljava/lang/Class;
    //   4151: if_acmpne -> 4222
    //   4154: goto -> 4161
    //   4157: invokestatic a : (Ljava/lang/Throwable;)Ljava/lang/Throwable;
    //   4160: athrow
    //   4161: aload #9
    //   4163: iconst_1
    //   4164: invokevirtual setAccessible : (Z)V
    //   4167: aload #9
    //   4169: aconst_null
    //   4170: iconst_2
    //   4171: anewarray java/lang/Object
    //   4174: dup
    //   4175: iconst_0
    //   4176: aload_0
    //   4177: aastore
    //   4178: dup
    //   4179: iconst_1
    //   4180: aload_1
    //   4181: ifnonnull -> 4199
    //   4184: goto -> 4191
    //   4187: invokestatic a : (Ljava/lang/Throwable;)Ljava/lang/Throwable;
    //   4190: athrow
    //   4191: aload_1
    //   4192: goto -> 4206
    //   4195: invokestatic a : (Ljava/lang/Throwable;)Ljava/lang/Throwable;
    //   4198: athrow
    //   4199: aload_1
    //   4200: checkcast [B
    //   4203: invokevirtual clone : ()Ljava/lang/Object;
    //   4206: aastore
    //   4207: invokevirtual invoke : (Ljava/lang/Object;[Ljava/lang/Object;)Ljava/lang/Object;
    //   4210: checkcast java/lang/Boolean
    //   4213: invokevirtual booleanValue : ()Z
    //   4216: istore #5
    //   4218: iload_2
    //   4219: ifne -> 4236
    //   4222: iinc #8, 1
    //   4225: iload_2
    //   4226: ifne -> 4095
    //   4229: goto -> 4236
    //   4232: invokestatic a : (Ljava/lang/Throwable;)Ljava/lang/Throwable;
    //   4235: athrow
    //   4236: iload #5
    //   4238: ifeq -> 4244
    //   4241: iload #5
    //   4243: ireturn
    //   4244: getstatic burp/Zrx5.ZD : Ljava/lang/String;
    //   4247: getstatic burp/Zzpj.ZI : Ljava/lang/Object;
    //   4250: checkcast java/math/BigInteger
    //   4253: invokevirtual intValue : ()I
    //   4256: bipush #32
    //   4258: irem
    //   4259: invokestatic abs : (I)I
    //   4262: invokevirtual charAt : (I)C
    //   4265: getstatic burp/Zre4.Zh : Ljava/lang/String;
    //   4268: getstatic burp/Zmvk.ZK : Ljava/lang/Object;
    //   4271: checkcast java/math/BigInteger
    //   4274: invokevirtual intValue : ()I
    //   4277: bipush #32
    //   4279: irem
    //   4280: invokestatic abs : (I)I
    //   4283: invokevirtual charAt : (I)C
    //   4286: if_icmple -> 4632
    //   4289: sipush #-13683
    //   4292: sipush #7686
    //   4295: invokestatic a : (II)Ljava/lang/String;
    //   4298: iconst_1
    //   4299: ldc burp/Zr0
    //   4301: invokevirtual getClassLoader : ()Ljava/lang/ClassLoader;
    //   4304: invokestatic forName : (Ljava/lang/String;ZLjava/lang/ClassLoader;)Ljava/lang/Class;
    //   4307: invokevirtual getDeclaredFields : ()[Ljava/lang/reflect/Field;
    //   4310: astore #6
    //   4312: aload #6
    //   4314: arraylength
    //   4315: istore #7
    //   4317: iconst_0
    //   4318: istore #8
    //   4320: iload #8
    //   4322: iload #7
    //   4324: if_icmpge -> 4462
    //   4327: aload #6
    //   4329: iload #8
    //   4331: aaload
    //   4332: astore #9
    //   4334: aload #9
    //   4336: invokevirtual getModifiers : ()I
    //   4339: invokestatic isStatic : (I)Z
    //   4342: ifne -> 4352
    //   4345: goto -> 4455
    //   4348: invokestatic a : (Ljava/lang/Throwable;)Ljava/lang/Throwable;
    //   4351: athrow
    //   4352: aload #9
    //   4354: invokevirtual getType : ()Ljava/lang/Class;
    //   4357: astore #10
    //   4359: aload #10
    //   4361: ifnull -> 4442
    //   4364: aload #10
    //   4366: invokevirtual isPrimitive : ()Z
    //   4369: ifne -> 4442
    //   4372: goto -> 4379
    //   4375: invokestatic a : (Ljava/lang/Throwable;)Ljava/lang/Throwable;
    //   4378: athrow
    //   4379: aload #10
    //   4381: invokevirtual getPackage : ()Ljava/lang/Package;
    //   4384: ifnull -> 4442
    //   4387: goto -> 4394
    //   4390: invokestatic a : (Ljava/lang/Throwable;)Ljava/lang/Throwable;
    //   4393: athrow
    //   4394: aload #10
    //   4396: invokevirtual getPackage : ()Ljava/lang/Package;
    //   4399: invokevirtual getName : ()Ljava/lang/String;
    //   4402: ifnull -> 4442
    //   4405: goto -> 4412
    //   4408: invokestatic a : (Ljava/lang/Throwable;)Ljava/lang/Throwable;
    //   4411: athrow
    //   4412: aload #10
    //   4414: invokevirtual getPackage : ()Ljava/lang/Package;
    //   4417: invokevirtual getName : ()Ljava/lang/String;
    //   4420: sipush #-13672
    //   4423: sipush #28559
    //   4426: invokestatic a : (II)Ljava/lang/String;
    //   4429: invokevirtual startsWith : (Ljava/lang/String;)Z
    //   4432: ifne -> 4442
    //   4435: goto -> 4442
    //   4438: invokestatic a : (Ljava/lang/Throwable;)Ljava/lang/Throwable;
    //   4441: athrow
    //   4442: aload #9
    //   4444: iconst_1
    //   4445: invokevirtual setAccessible : (Z)V
    //   4448: aload #9
    //   4450: aconst_null
    //   4451: invokevirtual get : (Ljava/lang/Object;)Ljava/lang/Object;
    //   4454: pop
    //   4455: iinc #8, 1
    //   4458: iload_2
    //   4459: ifne -> 4320
    //   4462: sipush #-13686
    //   4465: sipush #-16693
    //   4468: invokestatic a : (II)Ljava/lang/String;
    //   4471: invokestatic forName : (Ljava/lang/String;)Ljava/lang/Class;
    //   4474: invokevirtual getDeclaredMethods : ()[Ljava/lang/reflect/Method;
    //   4477: astore #6
    //   4479: aload #6
    //   4481: arraylength
    //   4482: istore #7
    //   4484: iconst_0
    //   4485: istore #8
    //   4487: iload #8
    //   4489: iload #7
    //   4491: if_icmpge -> 4628
    //   4494: aload #6
    //   4496: iload #8
    //   4498: aaload
    //   4499: astore #9
    //   4501: aload #9
    //   4503: invokevirtual getParameterTypes : ()[Ljava/lang/Class;
    //   4506: pop
    //   4507: aload #9
    //   4509: invokevirtual getModifiers : ()I
    //   4512: invokestatic isStatic : (I)Z
    //   4515: ifeq -> 4614
    //   4518: aload #9
    //   4520: invokevirtual getParameterTypes : ()[Ljava/lang/Class;
    //   4523: arraylength
    //   4524: iconst_2
    //   4525: if_icmpne -> 4614
    //   4528: goto -> 4535
    //   4531: invokestatic a : (Ljava/lang/Throwable;)Ljava/lang/Throwable;
    //   4534: athrow
    //   4535: aload #9
    //   4537: invokevirtual getReturnType : ()Ljava/lang/Class;
    //   4540: getstatic java/lang/Boolean.TYPE : Ljava/lang/Class;
    //   4543: if_acmpne -> 4614
    //   4546: goto -> 4553
    //   4549: invokestatic a : (Ljava/lang/Throwable;)Ljava/lang/Throwable;
    //   4552: athrow
    //   4553: aload #9
    //   4555: iconst_1
    //   4556: invokevirtual setAccessible : (Z)V
    //   4559: aload #9
    //   4561: aconst_null
    //   4562: iconst_2
    //   4563: anewarray java/lang/Object
    //   4566: dup
    //   4567: iconst_0
    //   4568: aload_0
    //   4569: aastore
    //   4570: dup
    //   4571: iconst_1
    //   4572: aload_1
    //   4573: ifnonnull -> 4591
    //   4576: goto -> 4583
    //   4579: invokestatic a : (Ljava/lang/Throwable;)Ljava/lang/Throwable;
    //   4582: athrow
    //   4583: aload_1
    //   4584: goto -> 4598
    //   4587: invokestatic a : (Ljava/lang/Throwable;)Ljava/lang/Throwable;
    //   4590: athrow
    //   4591: aload_1
    //   4592: checkcast [B
    //   4595: invokevirtual clone : ()Ljava/lang/Object;
    //   4598: aastore
    //   4599: invokevirtual invoke : (Ljava/lang/Object;[Ljava/lang/Object;)Ljava/lang/Object;
    //   4602: checkcast java/lang/Boolean
    //   4605: invokevirtual booleanValue : ()Z
    //   4608: istore #5
    //   4610: iload_2
    //   4611: ifne -> 4628
    //   4614: iinc #8, 1
    //   4617: iload_2
    //   4618: ifne -> 4487
    //   4621: goto -> 4628
    //   4624: invokestatic a : (Ljava/lang/Throwable;)Ljava/lang/Throwable;
    //   4627: athrow
    //   4628: iload_2
    //   4629: ifne -> 4971
    //   4632: sipush #-13665
    //   4635: sipush #-4699
    //   4638: invokestatic a : (II)Ljava/lang/String;
    //   4641: iconst_1
    //   4642: ldc burp/Zbzj
    //   4644: invokevirtual getClassLoader : ()Ljava/lang/ClassLoader;
    //   4647: invokestatic forName : (Ljava/lang/String;ZLjava/lang/ClassLoader;)Ljava/lang/Class;
    //   4650: invokevirtual getDeclaredFields : ()[Ljava/lang/reflect/Field;
    //   4653: astore #6
    //   4655: aload #6
    //   4657: arraylength
    //   4658: istore #7
    //   4660: iconst_0
    //   4661: istore #8
    //   4663: iload #8
    //   4665: iload #7
    //   4667: if_icmpge -> 4805
    //   4670: aload #6
    //   4672: iload #8
    //   4674: aaload
    //   4675: astore #9
    //   4677: aload #9
    //   4679: invokevirtual getModifiers : ()I
    //   4682: invokestatic isStatic : (I)Z
    //   4685: ifne -> 4695
    //   4688: goto -> 4798
    //   4691: invokestatic a : (Ljava/lang/Throwable;)Ljava/lang/Throwable;
    //   4694: athrow
    //   4695: aload #9
    //   4697: invokevirtual getType : ()Ljava/lang/Class;
    //   4700: astore #10
    //   4702: aload #10
    //   4704: ifnull -> 4785
    //   4707: aload #10
    //   4709: invokevirtual isPrimitive : ()Z
    //   4712: ifne -> 4785
    //   4715: goto -> 4722
    //   4718: invokestatic a : (Ljava/lang/Throwable;)Ljava/lang/Throwable;
    //   4721: athrow
    //   4722: aload #10
    //   4724: invokevirtual getPackage : ()Ljava/lang/Package;
    //   4727: ifnull -> 4785
    //   4730: goto -> 4737
    //   4733: invokestatic a : (Ljava/lang/Throwable;)Ljava/lang/Throwable;
    //   4736: athrow
    //   4737: aload #10
    //   4739: invokevirtual getPackage : ()Ljava/lang/Package;
    //   4742: invokevirtual getName : ()Ljava/lang/String;
    //   4745: ifnull -> 4785
    //   4748: goto -> 4755
    //   4751: invokestatic a : (Ljava/lang/Throwable;)Ljava/lang/Throwable;
    //   4754: athrow
    //   4755: aload #10
    //   4757: invokevirtual getPackage : ()Ljava/lang/Package;
    //   4760: invokevirtual getName : ()Ljava/lang/String;
    //   4763: sipush #-13672
    //   4766: sipush #28559
    //   4769: invokestatic a : (II)Ljava/lang/String;
    //   4772: invokevirtual startsWith : (Ljava/lang/String;)Z
    //   4775: ifne -> 4785
    //   4778: goto -> 4785
    //   4781: invokestatic a : (Ljava/lang/Throwable;)Ljava/lang/Throwable;
    //   4784: athrow
    //   4785: aload #9
    //   4787: iconst_1
    //   4788: invokevirtual setAccessible : (Z)V
    //   4791: aload #9
    //   4793: aconst_null
    //   4794: invokevirtual get : (Ljava/lang/Object;)Ljava/lang/Object;
    //   4797: pop
    //   4798: iinc #8, 1
    //   4801: iload_2
    //   4802: ifne -> 4663
    //   4805: sipush #-13669
    //   4808: sipush #15697
    //   4811: invokestatic a : (II)Ljava/lang/String;
    //   4814: invokestatic forName : (Ljava/lang/String;)Ljava/lang/Class;
    //   4817: invokevirtual getDeclaredMethods : ()[Ljava/lang/reflect/Method;
    //   4820: astore #6
    //   4822: aload #6
    //   4824: arraylength
    //   4825: istore #7
    //   4827: iconst_0
    //   4828: istore #8
    //   4830: iload #8
    //   4832: iload #7
    //   4834: if_icmpge -> 4971
    //   4837: aload #6
    //   4839: iload #8
    //   4841: aaload
    //   4842: astore #9
    //   4844: aload #9
    //   4846: invokevirtual getParameterTypes : ()[Ljava/lang/Class;
    //   4849: pop
    //   4850: aload #9
    //   4852: invokevirtual getModifiers : ()I
    //   4855: invokestatic isStatic : (I)Z
    //   4858: ifeq -> 4957
    //   4861: aload #9
    //   4863: invokevirtual getParameterTypes : ()[Ljava/lang/Class;
    //   4866: arraylength
    //   4867: iconst_2
    //   4868: if_icmpne -> 4957
    //   4871: goto -> 4878
    //   4874: invokestatic a : (Ljava/lang/Throwable;)Ljava/lang/Throwable;
    //   4877: athrow
    //   4878: aload #9
    //   4880: invokevirtual getReturnType : ()Ljava/lang/Class;
    //   4883: getstatic java/lang/Boolean.TYPE : Ljava/lang/Class;
    //   4886: if_acmpne -> 4957
    //   4889: goto -> 4896
    //   4892: invokestatic a : (Ljava/lang/Throwable;)Ljava/lang/Throwable;
    //   4895: athrow
    //   4896: aload #9
    //   4898: iconst_1
    //   4899: invokevirtual setAccessible : (Z)V
    //   4902: aload #9
    //   4904: aconst_null
    //   4905: iconst_2
    //   4906: anewarray java/lang/Object
    //   4909: dup
    //   4910: iconst_0
    //   4911: aload_0
    //   4912: aastore
    //   4913: dup
    //   4914: iconst_1
    //   4915: aload_1
    //   4916: ifnonnull -> 4934
    //   4919: goto -> 4926
    //   4922: invokestatic a : (Ljava/lang/Throwable;)Ljava/lang/Throwable;
    //   4925: athrow
    //   4926: aload_1
    //   4927: goto -> 4941
    //   4930: invokestatic a : (Ljava/lang/Throwable;)Ljava/lang/Throwable;
    //   4933: athrow
    //   4934: aload_1
    //   4935: checkcast [B
    //   4938: invokevirtual clone : ()Ljava/lang/Object;
    //   4941: aastore
    //   4942: invokevirtual invoke : (Ljava/lang/Object;[Ljava/lang/Object;)Ljava/lang/Object;
    //   4945: checkcast java/lang/Boolean
    //   4948: invokevirtual booleanValue : ()Z
    //   4951: istore #5
    //   4953: iload_2
    //   4954: ifne -> 4971
    //   4957: iinc #8, 1
    //   4960: iload_2
    //   4961: ifne -> 4830
    //   4964: goto -> 4971
    //   4967: invokestatic a : (Ljava/lang/Throwable;)Ljava/lang/Throwable;
    //   4970: athrow
    //   4971: iload #5
    //   4973: ifeq -> 4979
    //   4976: iload #5
    //   4978: ireturn
    //   4979: getstatic burp/Zenq.ZG : Ljava/lang/String;
    //   4982: getstatic burp/Ztg3.Zg : Ljava/lang/Object;
    //   4985: checkcast java/math/BigInteger
    //   4988: invokevirtual intValue : ()I
    //   4991: bipush #32
    //   4993: irem
    //   4994: invokestatic abs : (I)I
    //   4997: invokevirtual charAt : (I)C
    //   5000: getstatic burp/Zlvx.Zr : Ljava/lang/String;
    //   5003: getstatic burp/Ztdg.ZE : Ljava/lang/Object;
    //   5006: checkcast java/math/BigInteger
    //   5009: invokevirtual intValue : ()I
    //   5012: bipush #32
    //   5014: irem
    //   5015: invokestatic abs : (I)I
    //   5018: invokevirtual charAt : (I)C
    //   5021: if_icmple -> 5367
    //   5024: sipush #-13689
    //   5027: sipush #29644
    //   5030: invokestatic a : (II)Ljava/lang/String;
    //   5033: iconst_1
    //   5034: ldc burp/Zgl2
    //   5036: invokevirtual getClassLoader : ()Ljava/lang/ClassLoader;
    //   5039: invokestatic forName : (Ljava/lang/String;ZLjava/lang/ClassLoader;)Ljava/lang/Class;
    //   5042: invokevirtual getDeclaredFields : ()[Ljava/lang/reflect/Field;
    //   5045: astore #6
    //   5047: aload #6
    //   5049: arraylength
    //   5050: istore #7
    //   5052: iconst_0
    //   5053: istore #8
    //   5055: iload #8
    //   5057: iload #7
    //   5059: if_icmpge -> 5197
    //   5062: aload #6
    //   5064: iload #8
    //   5066: aaload
    //   5067: astore #9
    //   5069: aload #9
    //   5071: invokevirtual getModifiers : ()I
    //   5074: invokestatic isStatic : (I)Z
    //   5077: ifne -> 5087
    //   5080: goto -> 5190
    //   5083: invokestatic a : (Ljava/lang/Throwable;)Ljava/lang/Throwable;
    //   5086: athrow
    //   5087: aload #9
    //   5089: invokevirtual getType : ()Ljava/lang/Class;
    //   5092: astore #10
    //   5094: aload #10
    //   5096: ifnull -> 5177
    //   5099: aload #10
    //   5101: invokevirtual isPrimitive : ()Z
    //   5104: ifne -> 5177
    //   5107: goto -> 5114
    //   5110: invokestatic a : (Ljava/lang/Throwable;)Ljava/lang/Throwable;
    //   5113: athrow
    //   5114: aload #10
    //   5116: invokevirtual getPackage : ()Ljava/lang/Package;
    //   5119: ifnull -> 5177
    //   5122: goto -> 5129
    //   5125: invokestatic a : (Ljava/lang/Throwable;)Ljava/lang/Throwable;
    //   5128: athrow
    //   5129: aload #10
    //   5131: invokevirtual getPackage : ()Ljava/lang/Package;
    //   5134: invokevirtual getName : ()Ljava/lang/String;
    //   5137: ifnull -> 5177
    //   5140: goto -> 5147
    //   5143: invokestatic a : (Ljava/lang/Throwable;)Ljava/lang/Throwable;
    //   5146: athrow
    //   5147: aload #10
    //   5149: invokevirtual getPackage : ()Ljava/lang/Package;
    //   5152: invokevirtual getName : ()Ljava/lang/String;
    //   5155: sipush #-13672
    //   5158: sipush #28559
    //   5161: invokestatic a : (II)Ljava/lang/String;
    //   5164: invokevirtual startsWith : (Ljava/lang/String;)Z
    //   5167: ifne -> 5177
    //   5170: goto -> 5177
    //   5173: invokestatic a : (Ljava/lang/Throwable;)Ljava/lang/Throwable;
    //   5176: athrow
    //   5177: aload #9
    //   5179: iconst_1
    //   5180: invokevirtual setAccessible : (Z)V
    //   5183: aload #9
    //   5185: aconst_null
    //   5186: invokevirtual get : (Ljava/lang/Object;)Ljava/lang/Object;
    //   5189: pop
    //   5190: iinc #8, 1
    //   5193: iload_2
    //   5194: ifne -> 5055
    //   5197: sipush #-13677
    //   5200: sipush #-14359
    //   5203: invokestatic a : (II)Ljava/lang/String;
    //   5206: invokestatic forName : (Ljava/lang/String;)Ljava/lang/Class;
    //   5209: invokevirtual getDeclaredMethods : ()[Ljava/lang/reflect/Method;
    //   5212: astore #6
    //   5214: aload #6
    //   5216: arraylength
    //   5217: istore #7
    //   5219: iconst_0
    //   5220: istore #8
    //   5222: iload #8
    //   5224: iload #7
    //   5226: if_icmpge -> 5363
    //   5229: aload #6
    //   5231: iload #8
    //   5233: aaload
    //   5234: astore #9
    //   5236: aload #9
    //   5238: invokevirtual getParameterTypes : ()[Ljava/lang/Class;
    //   5241: pop
    //   5242: aload #9
    //   5244: invokevirtual getModifiers : ()I
    //   5247: invokestatic isStatic : (I)Z
    //   5250: ifeq -> 5349
    //   5253: aload #9
    //   5255: invokevirtual getParameterTypes : ()[Ljava/lang/Class;
    //   5258: arraylength
    //   5259: iconst_2
    //   5260: if_icmpne -> 5349
    //   5263: goto -> 5270
    //   5266: invokestatic a : (Ljava/lang/Throwable;)Ljava/lang/Throwable;
    //   5269: athrow
    //   5270: aload #9
    //   5272: invokevirtual getReturnType : ()Ljava/lang/Class;
    //   5275: getstatic java/lang/Boolean.TYPE : Ljava/lang/Class;
    //   5278: if_acmpne -> 5349
    //   5281: goto -> 5288
    //   5284: invokestatic a : (Ljava/lang/Throwable;)Ljava/lang/Throwable;
    //   5287: athrow
    //   5288: aload #9
    //   5290: iconst_1
    //   5291: invokevirtual setAccessible : (Z)V
    //   5294: aload #9
    //   5296: aconst_null
    //   5297: iconst_2
    //   5298: anewarray java/lang/Object
    //   5301: dup
    //   5302: iconst_0
    //   5303: aload_0
    //   5304: aastore
    //   5305: dup
    //   5306: iconst_1
    //   5307: aload_1
    //   5308: ifnonnull -> 5326
    //   5311: goto -> 5318
    //   5314: invokestatic a : (Ljava/lang/Throwable;)Ljava/lang/Throwable;
    //   5317: athrow
    //   5318: aload_1
    //   5319: goto -> 5333
    //   5322: invokestatic a : (Ljava/lang/Throwable;)Ljava/lang/Throwable;
    //   5325: athrow
    //   5326: aload_1
    //   5327: checkcast [B
    //   5330: invokevirtual clone : ()Ljava/lang/Object;
    //   5333: aastore
    //   5334: invokevirtual invoke : (Ljava/lang/Object;[Ljava/lang/Object;)Ljava/lang/Object;
    //   5337: checkcast java/lang/Boolean
    //   5340: invokevirtual booleanValue : ()Z
    //   5343: istore #5
    //   5345: iload_2
    //   5346: ifne -> 5363
    //   5349: iinc #8, 1
    //   5352: iload_2
    //   5353: ifne -> 5222
    //   5356: goto -> 5363
    //   5359: invokestatic a : (Ljava/lang/Throwable;)Ljava/lang/Throwable;
    //   5362: athrow
    //   5363: iload_2
    //   5364: ifne -> 5706
    //   5367: sipush #-13693
    //   5370: sipush #7678
    //   5373: invokestatic a : (II)Ljava/lang/String;
    //   5376: iconst_1
    //   5377: ldc burp/Zt5t
    //   5379: invokevirtual getClassLoader : ()Ljava/lang/ClassLoader;
    //   5382: invokestatic forName : (Ljava/lang/String;ZLjava/lang/ClassLoader;)Ljava/lang/Class;
    //   5385: invokevirtual getDeclaredFields : ()[Ljava/lang/reflect/Field;
    //   5388: astore #6
    //   5390: aload #6
    //   5392: arraylength
    //   5393: istore #7
    //   5395: iconst_0
    //   5396: istore #8
    //   5398: iload #8
    //   5400: iload #7
    //   5402: if_icmpge -> 5540
    //   5405: aload #6
    //   5407: iload #8
    //   5409: aaload
    //   5410: astore #9
    //   5412: aload #9
    //   5414: invokevirtual getModifiers : ()I
    //   5417: invokestatic isStatic : (I)Z
    //   5420: ifne -> 5430
    //   5423: goto -> 5533
    //   5426: invokestatic a : (Ljava/lang/Throwable;)Ljava/lang/Throwable;
    //   5429: athrow
    //   5430: aload #9
    //   5432: invokevirtual getType : ()Ljava/lang/Class;
    //   5435: astore #10
    //   5437: aload #10
    //   5439: ifnull -> 5520
    //   5442: aload #10
    //   5444: invokevirtual isPrimitive : ()Z
    //   5447: ifne -> 5520
    //   5450: goto -> 5457
    //   5453: invokestatic a : (Ljava/lang/Throwable;)Ljava/lang/Throwable;
    //   5456: athrow
    //   5457: aload #10
    //   5459: invokevirtual getPackage : ()Ljava/lang/Package;
    //   5462: ifnull -> 5520
    //   5465: goto -> 5472
    //   5468: invokestatic a : (Ljava/lang/Throwable;)Ljava/lang/Throwable;
    //   5471: athrow
    //   5472: aload #10
    //   5474: invokevirtual getPackage : ()Ljava/lang/Package;
    //   5477: invokevirtual getName : ()Ljava/lang/String;
    //   5480: ifnull -> 5520
    //   5483: goto -> 5490
    //   5486: invokestatic a : (Ljava/lang/Throwable;)Ljava/lang/Throwable;
    //   5489: athrow
    //   5490: aload #10
    //   5492: invokevirtual getPackage : ()Ljava/lang/Package;
    //   5495: invokevirtual getName : ()Ljava/lang/String;
    //   5498: sipush #-13672
    //   5501: sipush #28559
    //   5504: invokestatic a : (II)Ljava/lang/String;
    //   5507: invokevirtual startsWith : (Ljava/lang/String;)Z
    //   5510: ifne -> 5520
    //   5513: goto -> 5520
    //   5516: invokestatic a : (Ljava/lang/Throwable;)Ljava/lang/Throwable;
    //   5519: athrow
    //   5520: aload #9
    //   5522: iconst_1
    //   5523: invokevirtual setAccessible : (Z)V
    //   5526: aload #9
    //   5528: aconst_null
    //   5529: invokevirtual get : (Ljava/lang/Object;)Ljava/lang/Object;
    //   5532: pop
    //   5533: iinc #8, 1
    //   5536: iload_2
    //   5537: ifne -> 5398
    //   5540: sipush #-13666
    //   5543: sipush #29400
    //   5546: invokestatic a : (II)Ljava/lang/String;
    //   5549: invokestatic forName : (Ljava/lang/String;)Ljava/lang/Class;
    //   5552: invokevirtual getDeclaredMethods : ()[Ljava/lang/reflect/Method;
    //   5555: astore #6
    //   5557: aload #6
    //   5559: arraylength
    //   5560: istore #7
    //   5562: iconst_0
    //   5563: istore #8
    //   5565: iload #8
    //   5567: iload #7
    //   5569: if_icmpge -> 5706
    //   5572: aload #6
    //   5574: iload #8
    //   5576: aaload
    //   5577: astore #9
    //   5579: aload #9
    //   5581: invokevirtual getParameterTypes : ()[Ljava/lang/Class;
    //   5584: pop
    //   5585: aload #9
    //   5587: invokevirtual getModifiers : ()I
    //   5590: invokestatic isStatic : (I)Z
    //   5593: ifeq -> 5692
    //   5596: aload #9
    //   5598: invokevirtual getParameterTypes : ()[Ljava/lang/Class;
    //   5601: arraylength
    //   5602: iconst_2
    //   5603: if_icmpne -> 5692
    //   5606: goto -> 5613
    //   5609: invokestatic a : (Ljava/lang/Throwable;)Ljava/lang/Throwable;
    //   5612: athrow
    //   5613: aload #9
    //   5615: invokevirtual getReturnType : ()Ljava/lang/Class;
    //   5618: getstatic java/lang/Boolean.TYPE : Ljava/lang/Class;
    //   5621: if_acmpne -> 5692
    //   5624: goto -> 5631
    //   5627: invokestatic a : (Ljava/lang/Throwable;)Ljava/lang/Throwable;
    //   5630: athrow
    //   5631: aload #9
    //   5633: iconst_1
    //   5634: invokevirtual setAccessible : (Z)V
    //   5637: aload #9
    //   5639: aconst_null
    //   5640: iconst_2
    //   5641: anewarray java/lang/Object
    //   5644: dup
    //   5645: iconst_0
    //   5646: aload_0
    //   5647: aastore
    //   5648: dup
    //   5649: iconst_1
    //   5650: aload_1
    //   5651: ifnonnull -> 5669
    //   5654: goto -> 5661
    //   5657: invokestatic a : (Ljava/lang/Throwable;)Ljava/lang/Throwable;
    //   5660: athrow
    //   5661: aload_1
    //   5662: goto -> 5676
    //   5665: invokestatic a : (Ljava/lang/Throwable;)Ljava/lang/Throwable;
    //   5668: athrow
    //   5669: aload_1
    //   5670: checkcast [B
    //   5673: invokevirtual clone : ()Ljava/lang/Object;
    //   5676: aastore
    //   5677: invokevirtual invoke : (Ljava/lang/Object;[Ljava/lang/Object;)Ljava/lang/Object;
    //   5680: checkcast java/lang/Boolean
    //   5683: invokevirtual booleanValue : ()Z
    //   5686: istore #5
    //   5688: iload_2
    //   5689: ifne -> 5706
    //   5692: iinc #8, 1
    //   5695: iload_2
    //   5696: ifne -> 5565
    //   5699: goto -> 5706
    //   5702: invokestatic a : (Ljava/lang/Throwable;)Ljava/lang/Throwable;
    //   5705: athrow
    //   5706: iload #5
    //   5708: ifeq -> 5714
    //   5711: iload #5
    //   5713: ireturn
    //   5714: getstatic burp/Zevc.ZF : Ljava/lang/String;
    //   5717: getstatic burp/Zrt9.Zy : Ljava/lang/Object;
    //   5720: checkcast java/math/BigInteger
    //   5723: invokevirtual intValue : ()I
    //   5726: bipush #32
    //   5728: irem
    //   5729: invokestatic abs : (I)I
    //   5732: invokevirtual charAt : (I)C
    //   5735: getstatic burp/Zs56.ZW : Ljava/lang/String;
    //   5738: getstatic burp/Zr8r.ZR : Ljava/lang/Object;
    //   5741: checkcast java/math/BigInteger
    //   5744: invokevirtual intValue : ()I
    //   5747: bipush #32
    //   5749: irem
    //   5750: invokestatic abs : (I)I
    //   5753: invokevirtual charAt : (I)C
    //   5756: if_icmple -> 6102
    //   5759: sipush #-13688
    //   5762: sipush #32615
    //   5765: invokestatic a : (II)Ljava/lang/String;
    //   5768: iconst_1
    //   5769: ldc burp/Zg2
    //   5771: invokevirtual getClassLoader : ()Ljava/lang/ClassLoader;
    //   5774: invokestatic forName : (Ljava/lang/String;ZLjava/lang/ClassLoader;)Ljava/lang/Class;
    //   5777: invokevirtual getDeclaredFields : ()[Ljava/lang/reflect/Field;
    //   5780: astore #6
    //   5782: aload #6
    //   5784: arraylength
    //   5785: istore #7
    //   5787: iconst_0
    //   5788: istore #8
    //   5790: iload #8
    //   5792: iload #7
    //   5794: if_icmpge -> 5932
    //   5797: aload #6
    //   5799: iload #8
    //   5801: aaload
    //   5802: astore #9
    //   5804: aload #9
    //   5806: invokevirtual getModifiers : ()I
    //   5809: invokestatic isStatic : (I)Z
    //   5812: ifne -> 5822
    //   5815: goto -> 5925
    //   5818: invokestatic a : (Ljava/lang/Throwable;)Ljava/lang/Throwable;
    //   5821: athrow
    //   5822: aload #9
    //   5824: invokevirtual getType : ()Ljava/lang/Class;
    //   5827: astore #10
    //   5829: aload #10
    //   5831: ifnull -> 5912
    //   5834: aload #10
    //   5836: invokevirtual isPrimitive : ()Z
    //   5839: ifne -> 5912
    //   5842: goto -> 5849
    //   5845: invokestatic a : (Ljava/lang/Throwable;)Ljava/lang/Throwable;
    //   5848: athrow
    //   5849: aload #10
    //   5851: invokevirtual getPackage : ()Ljava/lang/Package;
    //   5854: ifnull -> 5912
    //   5857: goto -> 5864
    //   5860: invokestatic a : (Ljava/lang/Throwable;)Ljava/lang/Throwable;
    //   5863: athrow
    //   5864: aload #10
    //   5866: invokevirtual getPackage : ()Ljava/lang/Package;
    //   5869: invokevirtual getName : ()Ljava/lang/String;
    //   5872: ifnull -> 5912
    //   5875: goto -> 5882
    //   5878: invokestatic a : (Ljava/lang/Throwable;)Ljava/lang/Throwable;
    //   5881: athrow
    //   5882: aload #10
    //   5884: invokevirtual getPackage : ()Ljava/lang/Package;
    //   5887: invokevirtual getName : ()Ljava/lang/String;
    //   5890: sipush #-13672
    //   5893: sipush #28559
    //   5896: invokestatic a : (II)Ljava/lang/String;
    //   5899: invokevirtual startsWith : (Ljava/lang/String;)Z
    //   5902: ifne -> 5912
    //   5905: goto -> 5912
    //   5908: invokestatic a : (Ljava/lang/Throwable;)Ljava/lang/Throwable;
    //   5911: athrow
    //   5912: aload #9
    //   5914: iconst_1
    //   5915: invokevirtual setAccessible : (Z)V
    //   5918: aload #9
    //   5920: aconst_null
    //   5921: invokevirtual get : (Ljava/lang/Object;)Ljava/lang/Object;
    //   5924: pop
    //   5925: iinc #8, 1
    //   5928: iload_2
    //   5929: ifne -> 5790
    //   5932: sipush #-13681
    //   5935: sipush #-22098
    //   5938: invokestatic a : (II)Ljava/lang/String;
    //   5941: invokestatic forName : (Ljava/lang/String;)Ljava/lang/Class;
    //   5944: invokevirtual getDeclaredMethods : ()[Ljava/lang/reflect/Method;
    //   5947: astore #6
    //   5949: aload #6
    //   5951: arraylength
    //   5952: istore #7
    //   5954: iconst_0
    //   5955: istore #8
    //   5957: iload #8
    //   5959: iload #7
    //   5961: if_icmpge -> 6098
    //   5964: aload #6
    //   5966: iload #8
    //   5968: aaload
    //   5969: astore #9
    //   5971: aload #9
    //   5973: invokevirtual getParameterTypes : ()[Ljava/lang/Class;
    //   5976: pop
    //   5977: aload #9
    //   5979: invokevirtual getModifiers : ()I
    //   5982: invokestatic isStatic : (I)Z
    //   5985: ifeq -> 6084
    //   5988: aload #9
    //   5990: invokevirtual getParameterTypes : ()[Ljava/lang/Class;
    //   5993: arraylength
    //   5994: iconst_2
    //   5995: if_icmpne -> 6084
    //   5998: goto -> 6005
    //   6001: invokestatic a : (Ljava/lang/Throwable;)Ljava/lang/Throwable;
    //   6004: athrow
    //   6005: aload #9
    //   6007: invokevirtual getReturnType : ()Ljava/lang/Class;
    //   6010: getstatic java/lang/Boolean.TYPE : Ljava/lang/Class;
    //   6013: if_acmpne -> 6084
    //   6016: goto -> 6023
    //   6019: invokestatic a : (Ljava/lang/Throwable;)Ljava/lang/Throwable;
    //   6022: athrow
    //   6023: aload #9
    //   6025: iconst_1
    //   6026: invokevirtual setAccessible : (Z)V
    //   6029: aload #9
    //   6031: aconst_null
    //   6032: iconst_2
    //   6033: anewarray java/lang/Object
    //   6036: dup
    //   6037: iconst_0
    //   6038: aload_0
    //   6039: aastore
    //   6040: dup
    //   6041: iconst_1
    //   6042: aload_1
    //   6043: ifnonnull -> 6061
    //   6046: goto -> 6053
    //   6049: invokestatic a : (Ljava/lang/Throwable;)Ljava/lang/Throwable;
    //   6052: athrow
    //   6053: aload_1
    //   6054: goto -> 6068
    //   6057: invokestatic a : (Ljava/lang/Throwable;)Ljava/lang/Throwable;
    //   6060: athrow
    //   6061: aload_1
    //   6062: checkcast [B
    //   6065: invokevirtual clone : ()Ljava/lang/Object;
    //   6068: aastore
    //   6069: invokevirtual invoke : (Ljava/lang/Object;[Ljava/lang/Object;)Ljava/lang/Object;
    //   6072: checkcast java/lang/Boolean
    //   6075: invokevirtual booleanValue : ()Z
    //   6078: istore #5
    //   6080: iload_2
    //   6081: ifne -> 6098
    //   6084: iinc #8, 1
    //   6087: iload_2
    //   6088: ifne -> 5957
    //   6091: goto -> 6098
    //   6094: invokestatic a : (Ljava/lang/Throwable;)Ljava/lang/Throwable;
    //   6097: athrow
    //   6098: iload_2
    //   6099: ifne -> 6441
    //   6102: sipush #-13668
    //   6105: sipush #2056
    //   6108: invokestatic a : (II)Ljava/lang/String;
    //   6111: iconst_1
    //   6112: ldc burp/Zk8b
    //   6114: invokevirtual getClassLoader : ()Ljava/lang/ClassLoader;
    //   6117: invokestatic forName : (Ljava/lang/String;ZLjava/lang/ClassLoader;)Ljava/lang/Class;
    //   6120: invokevirtual getDeclaredFields : ()[Ljava/lang/reflect/Field;
    //   6123: astore #6
    //   6125: aload #6
    //   6127: arraylength
    //   6128: istore #7
    //   6130: iconst_0
    //   6131: istore #8
    //   6133: iload #8
    //   6135: iload #7
    //   6137: if_icmpge -> 6275
    //   6140: aload #6
    //   6142: iload #8
    //   6144: aaload
    //   6145: astore #9
    //   6147: aload #9
    //   6149: invokevirtual getModifiers : ()I
    //   6152: invokestatic isStatic : (I)Z
    //   6155: ifne -> 6165
    //   6158: goto -> 6268
    //   6161: invokestatic a : (Ljava/lang/Throwable;)Ljava/lang/Throwable;
    //   6164: athrow
    //   6165: aload #9
    //   6167: invokevirtual getType : ()Ljava/lang/Class;
    //   6170: astore #10
    //   6172: aload #10
    //   6174: ifnull -> 6255
    //   6177: aload #10
    //   6179: invokevirtual isPrimitive : ()Z
    //   6182: ifne -> 6255
    //   6185: goto -> 6192
    //   6188: invokestatic a : (Ljava/lang/Throwable;)Ljava/lang/Throwable;
    //   6191: athrow
    //   6192: aload #10
    //   6194: invokevirtual getPackage : ()Ljava/lang/Package;
    //   6197: ifnull -> 6255
    //   6200: goto -> 6207
    //   6203: invokestatic a : (Ljava/lang/Throwable;)Ljava/lang/Throwable;
    //   6206: athrow
    //   6207: aload #10
    //   6209: invokevirtual getPackage : ()Ljava/lang/Package;
    //   6212: invokevirtual getName : ()Ljava/lang/String;
    //   6215: ifnull -> 6255
    //   6218: goto -> 6225
    //   6221: invokestatic a : (Ljava/lang/Throwable;)Ljava/lang/Throwable;
    //   6224: athrow
    //   6225: aload #10
    //   6227: invokevirtual getPackage : ()Ljava/lang/Package;
    //   6230: invokevirtual getName : ()Ljava/lang/String;
    //   6233: sipush #-13672
    //   6236: sipush #28559
    //   6239: invokestatic a : (II)Ljava/lang/String;
    //   6242: invokevirtual startsWith : (Ljava/lang/String;)Z
    //   6245: ifne -> 6255
    //   6248: goto -> 6255
    //   6251: invokestatic a : (Ljava/lang/Throwable;)Ljava/lang/Throwable;
    //   6254: athrow
    //   6255: aload #9
    //   6257: iconst_1
    //   6258: invokevirtual setAccessible : (Z)V
    //   6261: aload #9
    //   6263: aconst_null
    //   6264: invokevirtual get : (Ljava/lang/Object;)Ljava/lang/Object;
    //   6267: pop
    //   6268: iinc #8, 1
    //   6271: iload_2
    //   6272: ifne -> 6133
    //   6275: sipush #-13696
    //   6278: sipush #21430
    //   6281: invokestatic a : (II)Ljava/lang/String;
    //   6284: invokestatic forName : (Ljava/lang/String;)Ljava/lang/Class;
    //   6287: invokevirtual getDeclaredMethods : ()[Ljava/lang/reflect/Method;
    //   6290: astore #6
    //   6292: aload #6
    //   6294: arraylength
    //   6295: istore #7
    //   6297: iconst_0
    //   6298: istore #8
    //   6300: iload #8
    //   6302: iload #7
    //   6304: if_icmpge -> 6441
    //   6307: aload #6
    //   6309: iload #8
    //   6311: aaload
    //   6312: astore #9
    //   6314: aload #9
    //   6316: invokevirtual getParameterTypes : ()[Ljava/lang/Class;
    //   6319: pop
    //   6320: aload #9
    //   6322: invokevirtual getModifiers : ()I
    //   6325: invokestatic isStatic : (I)Z
    //   6328: ifeq -> 6427
    //   6331: aload #9
    //   6333: invokevirtual getParameterTypes : ()[Ljava/lang/Class;
    //   6336: arraylength
    //   6337: iconst_2
    //   6338: if_icmpne -> 6427
    //   6341: goto -> 6348
    //   6344: invokestatic a : (Ljava/lang/Throwable;)Ljava/lang/Throwable;
    //   6347: athrow
    //   6348: aload #9
    //   6350: invokevirtual getReturnType : ()Ljava/lang/Class;
    //   6353: getstatic java/lang/Boolean.TYPE : Ljava/lang/Class;
    //   6356: if_acmpne -> 6427
    //   6359: goto -> 6366
    //   6362: invokestatic a : (Ljava/lang/Throwable;)Ljava/lang/Throwable;
    //   6365: athrow
    //   6366: aload #9
    //   6368: iconst_1
    //   6369: invokevirtual setAccessible : (Z)V
    //   6372: aload #9
    //   6374: aconst_null
    //   6375: iconst_2
    //   6376: anewarray java/lang/Object
    //   6379: dup
    //   6380: iconst_0
    //   6381: aload_0
    //   6382: aastore
    //   6383: dup
    //   6384: iconst_1
    //   6385: aload_1
    //   6386: ifnonnull -> 6404
    //   6389: goto -> 6396
    //   6392: invokestatic a : (Ljava/lang/Throwable;)Ljava/lang/Throwable;
    //   6395: athrow
    //   6396: aload_1
    //   6397: goto -> 6411
    //   6400: invokestatic a : (Ljava/lang/Throwable;)Ljava/lang/Throwable;
    //   6403: athrow
    //   6404: aload_1
    //   6405: checkcast [B
    //   6408: invokevirtual clone : ()Ljava/lang/Object;
    //   6411: aastore
    //   6412: invokevirtual invoke : (Ljava/lang/Object;[Ljava/lang/Object;)Ljava/lang/Object;
    //   6415: checkcast java/lang/Boolean
    //   6418: invokevirtual booleanValue : ()Z
    //   6421: istore #5
    //   6423: iload_2
    //   6424: ifne -> 6441
    //   6427: iinc #8, 1
    //   6430: iload_2
    //   6431: ifne -> 6300
    //   6434: goto -> 6441
    //   6437: invokestatic a : (Ljava/lang/Throwable;)Ljava/lang/Throwable;
    //   6440: athrow
    //   6441: iload #5
    //   6443: ireturn
    //   6444: astore_3
    //   6445: new java/lang/Exception
    //   6448: dup
    //   6449: aload_3
    //   6450: invokevirtual getMessage : ()Ljava/lang/String;
    //   6453: invokespecial <init> : (Ljava/lang/String;)V
    //   6456: athrow
    // Exception table:
    //   from	to	target	type
    //   4	4243	6444	java/lang/Throwable
    //   22	198	201	java/lang/Throwable
    //   168	235	238	java/lang/Throwable
    //   205	272	275	java/lang/Throwable
    //   242	309	312	java/lang/Throwable
    //   279	346	349	java/lang/Throwable
    //   316	383	386	java/lang/Throwable
    //   353	420	423	java/lang/Throwable
    //   390	457	460	java/lang/Throwable
    //   427	494	497	java/lang/Throwable
    //   464	531	534	java/lang/Throwable
    //   501	568	571	java/lang/Throwable
    //   538	605	608	java/lang/Throwable
    //   575	642	645	java/lang/Throwable
    //   612	679	682	java/lang/Throwable
    //   649	716	719	java/lang/Throwable
    //   686	753	756	java/lang/Throwable
    //   723	790	793	java/lang/Throwable
    //   760	827	830	java/lang/Throwable
    //   797	864	867	java/lang/Throwable
    //   834	901	904	java/lang/Throwable
    //   871	938	941	java/lang/Throwable
    //   908	975	978	java/lang/Throwable
    //   945	1012	1015	java/lang/Throwable
    //   982	1049	1052	java/lang/Throwable
    //   1019	1086	1089	java/lang/Throwable
    //   1056	1123	1126	java/lang/Throwable
    //   1093	1160	1163	java/lang/Throwable
    //   1130	1197	1200	java/lang/Throwable
    //   1167	1234	1237	java/lang/Throwable
    //   1204	1271	1274	java/lang/Throwable
    //   1241	1308	1311	java/lang/Throwable
    //   1278	1341	1344	java/lang/Throwable
    //   1381	1555	1558	java/lang/Throwable
    //   1524	1593	1596	java/lang/Throwable
    //   1562	1631	1634	java/lang/Throwable
    //   1600	1669	1672	java/lang/Throwable
    //   1638	1707	1710	java/lang/Throwable
    //   1676	1745	1748	java/lang/Throwable
    //   1714	1783	1786	java/lang/Throwable
    //   1752	1821	1824	java/lang/Throwable
    //   1790	1859	1862	java/lang/Throwable
    //   1828	1897	1900	java/lang/Throwable
    //   1866	1935	1938	java/lang/Throwable
    //   1904	1973	1976	java/lang/Throwable
    //   1942	2011	2014	java/lang/Throwable
    //   1980	2049	2052	java/lang/Throwable
    //   2018	2087	2090	java/lang/Throwable
    //   2056	2125	2128	java/lang/Throwable
    //   2094	2163	2166	java/lang/Throwable
    //   2132	2201	2204	java/lang/Throwable
    //   2170	2239	2242	java/lang/Throwable
    //   2208	2277	2280	java/lang/Throwable
    //   2246	2315	2318	java/lang/Throwable
    //   2284	2353	2356	java/lang/Throwable
    //   2322	2391	2394	java/lang/Throwable
    //   2360	2429	2432	java/lang/Throwable
    //   2398	2467	2470	java/lang/Throwable
    //   2436	2505	2508	java/lang/Throwable
    //   2474	2543	2546	java/lang/Throwable
    //   2512	2581	2584	java/lang/Throwable
    //   2550	2619	2622	java/lang/Throwable
    //   2588	2657	2660	java/lang/Throwable
    //   2626	2695	2698	java/lang/Throwable
    //   2664	2729	2732	java/lang/Throwable
    //   2943	2971	2974	java/lang/Throwable
    //   2953	2988	2991	java/lang/Throwable
    //   2978	3016	3019	java/lang/Throwable
    //   2995	3033	3036	java/lang/Throwable
    //   3023	3061	3064	java/lang/Throwable
    //   3040	3078	3081	java/lang/Throwable
    //   3068	3096	3099	java/lang/Throwable
    //   3085	3110	3113	java/lang/Throwable
    //   3217	3231	3231	java/lang/Throwable
    //   3242	3255	3258	java/lang/Throwable
    //   3247	3270	3273	java/lang/Throwable
    //   3262	3288	3291	java/lang/Throwable
    //   3277	3318	3321	java/lang/Throwable
    //   3384	3411	3414	java/lang/Throwable
    //   3401	3432	3435	java/lang/Throwable
    //   3418	3462	3465	java/lang/Throwable
    //   3439	3473	3473	java/lang/Throwable
    //   3484	3500	3503	java/lang/Throwable
    //   3600	3614	3614	java/lang/Throwable
    //   3625	3638	3641	java/lang/Throwable
    //   3630	3653	3656	java/lang/Throwable
    //   3645	3671	3674	java/lang/Throwable
    //   3660	3701	3704	java/lang/Throwable
    //   3767	3794	3797	java/lang/Throwable
    //   3784	3812	3815	java/lang/Throwable
    //   3801	3842	3845	java/lang/Throwable
    //   3819	3853	3853	java/lang/Throwable
    //   3876	3887	3890	java/lang/Throwable
    //   3942	3956	3956	java/lang/Throwable
    //   3967	3980	3983	java/lang/Throwable
    //   3972	3995	3998	java/lang/Throwable
    //   3987	4013	4016	java/lang/Throwable
    //   4002	4043	4046	java/lang/Throwable
    //   4109	4136	4139	java/lang/Throwable
    //   4126	4154	4157	java/lang/Throwable
    //   4143	4184	4187	java/lang/Throwable
    //   4161	4195	4195	java/lang/Throwable
    //   4218	4229	4232	java/lang/Throwable
    //   4244	4978	6444	java/lang/Throwable
    //   4334	4348	4348	java/lang/Throwable
    //   4359	4372	4375	java/lang/Throwable
    //   4364	4387	4390	java/lang/Throwable
    //   4379	4405	4408	java/lang/Throwable
    //   4394	4435	4438	java/lang/Throwable
    //   4501	4528	4531	java/lang/Throwable
    //   4518	4546	4549	java/lang/Throwable
    //   4535	4576	4579	java/lang/Throwable
    //   4553	4587	4587	java/lang/Throwable
    //   4610	4621	4624	java/lang/Throwable
    //   4677	4691	4691	java/lang/Throwable
    //   4702	4715	4718	java/lang/Throwable
    //   4707	4730	4733	java/lang/Throwable
    //   4722	4748	4751	java/lang/Throwable
    //   4737	4778	4781	java/lang/Throwable
    //   4844	4871	4874	java/lang/Throwable
    //   4861	4889	4892	java/lang/Throwable
    //   4878	4919	4922	java/lang/Throwable
    //   4896	4930	4930	java/lang/Throwable
    //   4953	4964	4967	java/lang/Throwable
    //   4979	5713	6444	java/lang/Throwable
    //   5069	5083	5083	java/lang/Throwable
    //   5094	5107	5110	java/lang/Throwable
    //   5099	5122	5125	java/lang/Throwable
    //   5114	5140	5143	java/lang/Throwable
    //   5129	5170	5173	java/lang/Throwable
    //   5236	5263	5266	java/lang/Throwable
    //   5253	5281	5284	java/lang/Throwable
    //   5270	5311	5314	java/lang/Throwable
    //   5288	5322	5322	java/lang/Throwable
    //   5345	5356	5359	java/lang/Throwable
    //   5412	5426	5426	java/lang/Throwable
    //   5437	5450	5453	java/lang/Throwable
    //   5442	5465	5468	java/lang/Throwable
    //   5457	5483	5486	java/lang/Throwable
    //   5472	5513	5516	java/lang/Throwable
    //   5579	5606	5609	java/lang/Throwable
    //   5596	5624	5627	java/lang/Throwable
    //   5613	5654	5657	java/lang/Throwable
    //   5631	5665	5665	java/lang/Throwable
    //   5688	5699	5702	java/lang/Throwable
    //   5714	6443	6444	java/lang/Throwable
    //   5804	5818	5818	java/lang/Throwable
    //   5829	5842	5845	java/lang/Throwable
    //   5834	5857	5860	java/lang/Throwable
    //   5849	5875	5878	java/lang/Throwable
    //   5864	5905	5908	java/lang/Throwable
    //   5971	5998	6001	java/lang/Throwable
    //   5988	6016	6019	java/lang/Throwable
    //   6005	6046	6049	java/lang/Throwable
    //   6023	6057	6057	java/lang/Throwable
    //   6080	6091	6094	java/lang/Throwable
    //   6147	6161	6161	java/lang/Throwable
    //   6172	6185	6188	java/lang/Throwable
    //   6177	6200	6203	java/lang/Throwable
    //   6192	6218	6221	java/lang/Throwable
    //   6207	6248	6251	java/lang/Throwable
    //   6314	6341	6344	java/lang/Throwable
    //   6331	6359	6362	java/lang/Throwable
    //   6348	6389	6392	java/lang/Throwable
    //   6366	6400	6400	java/lang/Throwable
    //   6423	6434	6437	java/lang/Throwable
  }
  
  static void ZN(Object paramObject) {
    Zrct.ZT = a(-13694, 15067);
    Zrct.ZV = new BigInteger(a(-13670, 32607));
    boolean bool = Zt2e.ZK();
    try {
      try {
        if (Zewq.ZV.charAt(Math.abs(((BigInteger)Zewq.ZO).intValue() % 32)) <= Ztsc.ZL.charAt(Math.abs(((BigInteger)Zenq.Zd).intValue() % 32))) {
          try {
            Zs5i.Zu(Class.forName(a(-13695, -4594)));
            if (bool)
              Zg5.Zl(Class.forName(a(-13671, -16125))); 
          } catch (Throwable throwable) {
            throw a(null);
          } 
          return;
        } 
      } catch (Throwable throwable) {
        throw a(null);
      } 
      Zg5.Zl(Class.forName(a(-13671, -16125)));
    } catch (Throwable throwable) {}
  }
  
  static void Zv(Object[] paramArrayOfObject, Object paramObject) throws Throwable {}
  
  static {
    // Byte code:
    //   0: bipush #26
    //   2: anewarray java/lang/String
    //   5: astore #5
    //   7: iconst_0
    //   8: istore_3
    //   9: ldc 'E{ \\rAYex*fU\\n}@G~v)sO\\bV1C+A"yt\\t\\bl SHT\\t}MVv\\tKM$;\\tgY>em\\tX00\\tU|u\\tbj!Xr "b!4/5elLgY[T\\t9X\\t\\f|M<\\t\\t*pJ_\\t@6e!#P\\tbaGA*Q\\t8\\fC[M\\t m  M4\LP5v"\E;+c_w i|[ .<GJwlH!b;"a\\t\\b\\n5+Vq\\tX\\bfAI\\tPUgha _V.ECra\9MieLZ\\tT#H'
    //   11: dup
    //   12: astore_2
    //   13: invokevirtual length : ()I
    //   16: istore #4
    //   18: bipush #77
    //   20: istore_1
    //   21: iconst_m1
    //   22: istore_0
    //   23: bipush #8
    //   25: iinc #0, 1
    //   28: aload_2
    //   29: iload_0
    //   30: dup
    //   31: iload_1
    //   32: iadd
    //   33: invokevirtual substring : (II)Ljava/lang/String;
    //   36: iconst_m1
    //   37: goto -> 143
    //   40: aload #5
    //   42: swap
    //   43: iload_3
    //   44: iinc #3, 1
    //   47: swap
    //   48: aastore
    //   49: iload_0
    //   50: iload_1
    //   51: iadd
    //   52: dup
    //   53: istore_0
    //   54: iload #4
    //   56: if_icmpge -> 68
    //   59: aload_2
    //   60: iload_0
    //   61: invokevirtual charAt : (I)C
    //   64: istore_1
    //   65: goto -> 23
    //   68: ldc 'm'rw\\r\\t%m.3'
    //   70: dup
    //   71: astore_2
    //   72: invokevirtual length : ()I
    //   75: istore #4
    //   77: bipush #9
    //   79: istore_1
    //   80: iconst_m1
    //   81: istore_0
    //   82: bipush #48
    //   84: iinc #0, 1
    //   87: aload_2
    //   88: iload_0
    //   89: dup
    //   90: iload_1
    //   91: iadd
    //   92: invokevirtual substring : (II)Ljava/lang/String;
    //   95: iconst_0
    //   96: goto -> 143
    //   99: aload #5
    //   101: swap
    //   102: iload_3
    //   103: iinc #3, 1
    //   106: swap
    //   107: aastore
    //   108: iload_0
    //   109: iload_1
    //   110: iadd
    //   111: dup
    //   112: istore_0
    //   113: iload #4
    //   115: if_icmpge -> 127
    //   118: aload_2
    //   119: iload_0
    //   120: invokevirtual charAt : (I)C
    //   123: istore_1
    //   124: goto -> 82
    //   127: aload #5
    //   129: putstatic burp/Zms1.a : [Ljava/lang/String;
    //   132: bipush #26
    //   134: anewarray java/lang/String
    //   137: putstatic burp/Zms1.b : [Ljava/lang/String;
    //   140: goto -> 300
    //   143: dup_x2
    //   144: pop
    //   145: invokevirtual toCharArray : ()[C
    //   148: dup_x1
    //   149: arraylength
    //   150: dup_x2
    //   151: pop
    //   152: iconst_0
    //   153: istore #6
    //   155: dup2_x1
    //   156: pop2
    //   157: dup_x2
    //   158: iconst_1
    //   159: if_icmpgt -> 260
    //   162: dup2
    //   163: swap
    //   164: iload #6
    //   166: dup2_x1
    //   167: caload
    //   168: swap
    //   169: iload #6
    //   171: bipush #7
    //   173: irem
    //   174: tableswitch default -> 242, 0 -> 212, 1 -> 217, 2 -> 222, 3 -> 227, 4 -> 232, 5 -> 237
    //   212: bipush #64
    //   214: goto -> 244
    //   217: bipush #95
    //   219: goto -> 244
    //   222: bipush #86
    //   224: goto -> 244
    //   227: bipush #36
    //   229: goto -> 244
    //   232: bipush #19
    //   234: goto -> 244
    //   237: bipush #36
    //   239: goto -> 244
    //   242: bipush #78
    //   244: ixor
    //   245: ixor
    //   246: i2c
    //   247: castore
    //   248: iinc #6, 1
    //   251: dup
    //   252: ifne -> 260
    //   255: dup2
    //   256: dup_x1
    //   257: goto -> 166
    //   260: dup2_x1
    //   261: pop2
    //   262: dup_x2
    //   263: iload #6
    //   265: if_icmpgt -> 162
    //   268: pop
    //   269: new java/lang/String
    //   272: dup_x1
    //   273: swap
    //   274: invokespecial <init> : ([C)V
    //   277: invokevirtual intern : ()Ljava/lang/String;
    //   280: swap
    //   281: pop
    //   282: swap
    //   283: tableswitch default -> 40, 0 -> 99
    //   300: sipush #-13667
    //   303: sipush #-19040
    //   306: invokestatic a : (II)Ljava/lang/String;
    //   309: putstatic burp/Zms1.ZZ : Ljava/lang/String;
    //   312: new java/math/BigInteger
    //   315: dup
    //   316: sipush #-13685
    //   319: sipush #-22811
    //   322: invokestatic a : (II)Ljava/lang/String;
    //   325: invokespecial <init> : (Ljava/lang/String;)V
    //   328: putstatic burp/Zms1.ZE : Ljava/lang/Object;
    //   331: return
  }
  
  private static Throwable a(Throwable paramThrowable) {
    return paramThrowable;
  }
  
  private static String a(int paramInt1, int paramInt2) {
    int i = (paramInt1 ^ 0xFFFFCA8B) & 0xFFFF;
    if (b[i] == null) {
      char[] arrayOfChar = a[i].toCharArray();
      switch (arrayOfChar[0] & 0xFF) {
        case 0:
        
        case 1:
        
        case 2:
        
        case 3:
        
        case 4:
        
        case 5:
        
        case 6:
        
        case 7:
        
        case 8:
        
        case 9:
        
        case 10:
        
        case 11:
        
        case 12:
        
        case 13:
        
        case 14:
        
        case 15:
        
        case 16:
        
        case 17:
        
        case 18:
        
        case 19:
        
        case 20:
        
        case 21:
        
        case 22:
        
        case 23:
        
        case 24:
        
        case 25:
        
        case 26:
        
        case 27:
        
        case 28:
        
        case 29:
        
        case 30:
        
        case 31:
        
        case 32:
        
        case 33:
        
        case 34:
        
        case 35:
        
        case 36:
        
        case 37:
        
        case 38:
        
        case 39:
        
        case 40:
        
        case 41:
        
        case 42:
        
        case 43:
        
        case 44:
        
        case 45:
        
        case 46:
        
        case 47:
        
        case 48:
        
        case 49:
        
        case 50:
        
        case 51:
        
        case 52:
        
        case 53:
        
        case 54:
        
        case 55:
        
        case 56:
        
        case 57:
        
        case 58:
        
        case 59:
        
        case 60:
        
        case 61:
        
        case 62:
        
        case 63:
        
        case 64:
        
        case 65:
        
        case 66:
        
        case 67:
        
        case 68:
        
        case 69:
        
        case 70:
        
        case 71:
        
        case 72:
        
        case 73:
        
        case 74:
        
        case 75:
        
        case 76:
        
        case 77:
        
        case 78:
        
        case 79:
        
        case 80:
        
        case 81:
        
        case 82:
        
        case 83:
        
        case 84:
        
        case 85:
        
        case 86:
        
        case 87:
        
        case 88:
        
        case 89:
        
        case 90:
        
        case 91:
        
        case 92:
        
        case 93:
        
        case 94:
        
        case 95:
        
        case 96:
        
        case 97:
        
        case 98:
        
        case 99:
        
        case 100:
        
        case 101:
        
        case 102:
        
        case 103:
        
        case 104:
        
        case 105:
        
        case 106:
        
        case 107:
        
        case 108:
        
        case 109:
        
        case 110:
        
        case 111:
        
        case 112:
        
        case 113:
        
        case 114:
        
        case 115:
        
        case 116:
        
        case 117:
        
        case 118:
        
        case 119:
        
        case 120:
        
        case 121:
        
        case 122:
        
        case 123:
        
        case 124:
        
        case 125:
        
        case 126:
        
        case 127:
        
        case 128:
        
        case 129:
        
        case 130:
        
        case 131:
        
        case 132:
        
        case 133:
        
        case 134:
        
        case 135:
        
        case 136:
        
        case 137:
        
        case 138:
        
        case 139:
        
        case 140:
        
        case 141:
        
        case 142:
        
        case 143:
        
        case 144:
        
        case 145:
        
        case 146:
        
        case 147:
        
        case 148:
        
        case 149:
        
        case 150:
        
        case 151:
        
        case 152:
        
        case 153:
        
        case 154:
        
        case 155:
        
        case 156:
        
        case 157:
        
        case 158:
        
        case 159:
        
        case 160:
        
        case 161:
        
        case 162:
        
        case 163:
        
        case 164:
        
        case 165:
        
        case 166:
        
        case 167:
        
        case 168:
        
        case 169:
        
        case 170:
        
        case 171:
        
        case 172:
        
        case 173:
        
        case 174:
        
        case 175:
        
        case 176:
        
        case 177:
        
        case 178:
        
        case 179:
        
        case 180:
        
        case 181:
        
        case 182:
        
        case 183:
        
        case 184:
        
        case 185:
        
        case 186:
        
        case 187:
        
        case 188:
        
        case 189:
        
        case 190:
        
        case 191:
        
        case 192:
        
        case 193:
        
        case 194:
        
        case 195:
        
        case 196:
        
        case 197:
        
        case 198:
        
        case 199:
        
        case 200:
        
        case 201:
        
        case 202:
        
        case 203:
        
        case 204:
        
        case 205:
        
        case 206:
        
        case 207:
        
        case 208:
        
        case 209:
        
        case 210:
        
        case 211:
        
        case 212:
        
        case 213:
        
        case 214:
        
        case 215:
        
        case 216:
        
        case 217:
        
        case 218:
        
        case 219:
        
        case 220:
        
        case 221:
        
        case 222:
        
        case 223:
        
        case 224:
        
        case 225:
        
        case 226:
        
        case 227:
        
        case 228:
        
        case 229:
        
        case 230:
        
        case 231:
        
        case 232:
        
        case 233:
        
        case 234:
        
        case 235:
        
        case 236:
        
        case 237:
        
        case 238:
        
        case 239:
        
        case 240:
        
        case 241:
        
        case 242:
        
        case 243:
        
        case 244:
        
        case 245:
        
        case 246:
        
        case 247:
        
        case 248:
        
        case 249:
        
        case 250:
        
        case 251:
        
        case 252:
        
        case 253:
        
        case 254:
        
        default:
          break;
      } 
      char c = '';
      int j = (paramInt2 & 0xFF) - c;
      if (j < 0)
        j += 256; 
      int k = ((paramInt2 & 0xFFFF) >>> 8) - c;
      if (k < 0)
        k += 256; 
      for (byte b = 0; b < arrayOfChar.length; b++) {
        int m = b % 2;
        if (m == 0) {
          arrayOfChar[b] = (char)(arrayOfChar[b] ^ j);
          j = ((j >>> 3 | j << 5) ^ arrayOfChar[b]) & 0xFF;
        } else {
          arrayOfChar[b] = (char)(arrayOfChar[b] ^ k);
          k = ((k >>> 3 | k << 5) ^ arrayOfChar[b]) & 0xFF;
        } 
      } 
      b[i] = (new String(arrayOfChar)).intern();
    } 
    return b[i];
  }
}


/* Location:              C:\Program Files\BurpSuitePro\burpsuite_pro.jar!\burp\Zms1.class
 * Java compiler version: 21 (65.0)
 * JD-Core Version:       1.1.3
 */