package burp;

import java.math.BigInteger;

class Zmt6 extends ClassLoader {
  static Object ZK;
  
  static String Zx;
  
  private static final String[] a;
  
  private static final String[] b;
  
  static void Zv(Object[] paramArrayOfObject, Object paramObject) throws Throwable {}
  
  static boolean Zt(Object[] paramArrayOfObject, Object paramObject) throws Throwable {
    // Byte code:
    //   0: invokestatic ZN : ()Z
    //   3: istore_2
    //   4: getstatic burp/Zbsr.ZD : Ljava/lang/Object;
    //   7: checkcast java/math/BigInteger
    //   10: getstatic burp/Zelz.Z_ : Ljava/lang/Object;
    //   13: checkcast java/math/BigInteger
    //   16: invokevirtual add : (Ljava/math/BigInteger;)Ljava/math/BigInteger;
    //   19: putstatic burp/Zd0.ZT : Ljava/lang/Object;
    //   22: sipush #-13780
    //   25: sipush #22216
    //   28: invokestatic a : (II)Ljava/lang/String;
    //   31: iconst_1
    //   32: ldc burp/Zmly
    //   34: invokevirtual getClassLoader : ()Ljava/lang/ClassLoader;
    //   37: invokestatic forName : (Ljava/lang/String;ZLjava/lang/ClassLoader;)Ljava/lang/Class;
    //   40: invokevirtual getDeclaredFields : ()[Ljava/lang/reflect/Field;
    //   43: astore_3
    //   44: aload_3
    //   45: arraylength
    //   46: istore #4
    //   48: iconst_0
    //   49: istore #5
    //   51: iload #5
    //   53: iload #4
    //   55: if_icmpge -> 192
    //   58: aload_3
    //   59: iload #5
    //   61: aaload
    //   62: astore #6
    //   64: aload #6
    //   66: invokevirtual getModifiers : ()I
    //   69: invokestatic isStatic : (I)Z
    //   72: ifne -> 82
    //   75: goto -> 185
    //   78: invokestatic a : (Ljava/lang/Throwable;)Ljava/lang/Throwable;
    //   81: athrow
    //   82: aload #6
    //   84: invokevirtual getType : ()Ljava/lang/Class;
    //   87: astore #7
    //   89: aload #7
    //   91: ifnull -> 172
    //   94: aload #7
    //   96: invokevirtual isPrimitive : ()Z
    //   99: ifne -> 172
    //   102: goto -> 109
    //   105: invokestatic a : (Ljava/lang/Throwable;)Ljava/lang/Throwable;
    //   108: athrow
    //   109: aload #7
    //   111: invokevirtual getPackage : ()Ljava/lang/Package;
    //   114: ifnull -> 172
    //   117: goto -> 124
    //   120: invokestatic a : (Ljava/lang/Throwable;)Ljava/lang/Throwable;
    //   123: athrow
    //   124: aload #7
    //   126: invokevirtual getPackage : ()Ljava/lang/Package;
    //   129: invokevirtual getName : ()Ljava/lang/String;
    //   132: ifnull -> 172
    //   135: goto -> 142
    //   138: invokestatic a : (Ljava/lang/Throwable;)Ljava/lang/Throwable;
    //   141: athrow
    //   142: aload #7
    //   144: invokevirtual getPackage : ()Ljava/lang/Package;
    //   147: invokevirtual getName : ()Ljava/lang/String;
    //   150: sipush #-13786
    //   153: sipush #-28607
    //   156: invokestatic a : (II)Ljava/lang/String;
    //   159: invokevirtual startsWith : (Ljava/lang/String;)Z
    //   162: ifne -> 172
    //   165: goto -> 172
    //   168: invokestatic a : (Ljava/lang/Throwable;)Ljava/lang/Throwable;
    //   171: athrow
    //   172: aload #6
    //   174: iconst_1
    //   175: invokevirtual setAccessible : (Z)V
    //   178: aload #6
    //   180: aconst_null
    //   181: invokevirtual get : (Ljava/lang/Object;)Ljava/lang/Object;
    //   184: pop
    //   185: iinc #5, 1
    //   188: iload_2
    //   189: ifne -> 51
    //   192: sipush #-13790
    //   195: sipush #11842
    //   198: invokestatic a : (II)Ljava/lang/String;
    //   201: invokestatic forName : (Ljava/lang/String;)Ljava/lang/Class;
    //   204: invokevirtual getDeclaredMethods : ()[Ljava/lang/reflect/Method;
    //   207: astore_3
    //   208: aload_3
    //   209: arraylength
    //   210: istore #4
    //   212: iconst_0
    //   213: istore #5
    //   215: iload #5
    //   217: iload #4
    //   219: if_icmpge -> 330
    //   222: aload_3
    //   223: iload #5
    //   225: aaload
    //   226: astore #6
    //   228: aload #6
    //   230: invokevirtual getParameterTypes : ()[Ljava/lang/Class;
    //   233: pop
    //   234: aload #6
    //   236: invokevirtual getModifiers : ()I
    //   239: invokestatic isStatic : (I)Z
    //   242: ifeq -> 316
    //   245: aload #6
    //   247: invokevirtual getParameterTypes : ()[Ljava/lang/Class;
    //   250: arraylength
    //   251: iconst_2
    //   252: if_icmpne -> 316
    //   255: goto -> 262
    //   258: invokestatic a : (Ljava/lang/Throwable;)Ljava/lang/Throwable;
    //   261: athrow
    //   262: aload #6
    //   264: invokevirtual getReturnType : ()Ljava/lang/Class;
    //   267: getstatic java/lang/Boolean.TYPE : Ljava/lang/Class;
    //   270: if_acmpne -> 316
    //   273: goto -> 280
    //   276: invokestatic a : (Ljava/lang/Throwable;)Ljava/lang/Throwable;
    //   279: athrow
    //   280: aload #6
    //   282: iconst_1
    //   283: invokevirtual setAccessible : (Z)V
    //   286: aload #6
    //   288: aconst_null
    //   289: iconst_2
    //   290: anewarray java/lang/Object
    //   293: dup
    //   294: iconst_0
    //   295: aload_0
    //   296: aastore
    //   297: dup
    //   298: iconst_1
    //   299: aload_1
    //   300: aastore
    //   301: invokevirtual invoke : (Ljava/lang/Object;[Ljava/lang/Object;)Ljava/lang/Object;
    //   304: pop
    //   305: iload_2
    //   306: ifne -> 330
    //   309: goto -> 316
    //   312: invokestatic a : (Ljava/lang/Throwable;)Ljava/lang/Throwable;
    //   315: athrow
    //   316: iinc #5, 1
    //   319: iload_2
    //   320: ifne -> 215
    //   323: goto -> 330
    //   326: invokestatic a : (Ljava/lang/Throwable;)Ljava/lang/Throwable;
    //   329: athrow
    //   330: sipush #-13791
    //   333: sipush #14734
    //   336: invokestatic a : (II)Ljava/lang/String;
    //   339: iconst_1
    //   340: ldc burp/Ztzh
    //   342: invokevirtual getClassLoader : ()Ljava/lang/ClassLoader;
    //   345: invokestatic forName : (Ljava/lang/String;ZLjava/lang/ClassLoader;)Ljava/lang/Class;
    //   348: invokevirtual getDeclaredFields : ()[Ljava/lang/reflect/Field;
    //   351: astore_3
    //   352: aload_3
    //   353: arraylength
    //   354: istore #4
    //   356: iconst_0
    //   357: istore #5
    //   359: iload #5
    //   361: iload #4
    //   363: if_icmpge -> 500
    //   366: aload_3
    //   367: iload #5
    //   369: aaload
    //   370: astore #6
    //   372: aload #6
    //   374: invokevirtual getModifiers : ()I
    //   377: invokestatic isStatic : (I)Z
    //   380: ifne -> 390
    //   383: goto -> 493
    //   386: invokestatic a : (Ljava/lang/Throwable;)Ljava/lang/Throwable;
    //   389: athrow
    //   390: aload #6
    //   392: invokevirtual getType : ()Ljava/lang/Class;
    //   395: astore #7
    //   397: aload #7
    //   399: ifnull -> 480
    //   402: aload #7
    //   404: invokevirtual isPrimitive : ()Z
    //   407: ifne -> 480
    //   410: goto -> 417
    //   413: invokestatic a : (Ljava/lang/Throwable;)Ljava/lang/Throwable;
    //   416: athrow
    //   417: aload #7
    //   419: invokevirtual getPackage : ()Ljava/lang/Package;
    //   422: ifnull -> 480
    //   425: goto -> 432
    //   428: invokestatic a : (Ljava/lang/Throwable;)Ljava/lang/Throwable;
    //   431: athrow
    //   432: aload #7
    //   434: invokevirtual getPackage : ()Ljava/lang/Package;
    //   437: invokevirtual getName : ()Ljava/lang/String;
    //   440: ifnull -> 480
    //   443: goto -> 450
    //   446: invokestatic a : (Ljava/lang/Throwable;)Ljava/lang/Throwable;
    //   449: athrow
    //   450: aload #7
    //   452: invokevirtual getPackage : ()Ljava/lang/Package;
    //   455: invokevirtual getName : ()Ljava/lang/String;
    //   458: sipush #-13781
    //   461: sipush #-20545
    //   464: invokestatic a : (II)Ljava/lang/String;
    //   467: invokevirtual startsWith : (Ljava/lang/String;)Z
    //   470: ifne -> 480
    //   473: goto -> 480
    //   476: invokestatic a : (Ljava/lang/Throwable;)Ljava/lang/Throwable;
    //   479: athrow
    //   480: aload #6
    //   482: iconst_1
    //   483: invokevirtual setAccessible : (Z)V
    //   486: aload #6
    //   488: aconst_null
    //   489: invokevirtual get : (Ljava/lang/Object;)Ljava/lang/Object;
    //   492: pop
    //   493: iinc #5, 1
    //   496: iload_2
    //   497: ifne -> 359
    //   500: sipush #-13785
    //   503: sipush #-13329
    //   506: invokestatic a : (II)Ljava/lang/String;
    //   509: invokestatic forName : (Ljava/lang/String;)Ljava/lang/Class;
    //   512: invokevirtual getDeclaredMethods : ()[Ljava/lang/reflect/Method;
    //   515: astore_3
    //   516: aload_3
    //   517: arraylength
    //   518: istore #4
    //   520: iconst_0
    //   521: istore #5
    //   523: iload #5
    //   525: iload #4
    //   527: if_icmpge -> 659
    //   530: aload_3
    //   531: iload #5
    //   533: aaload
    //   534: astore #6
    //   536: aload #6
    //   538: invokevirtual getParameterTypes : ()[Ljava/lang/Class;
    //   541: pop
    //   542: aload #6
    //   544: invokevirtual getModifiers : ()I
    //   547: invokestatic isStatic : (I)Z
    //   550: ifeq -> 645
    //   553: aload #6
    //   555: invokevirtual getParameterTypes : ()[Ljava/lang/Class;
    //   558: arraylength
    //   559: iconst_2
    //   560: if_icmpne -> 645
    //   563: goto -> 570
    //   566: invokestatic a : (Ljava/lang/Throwable;)Ljava/lang/Throwable;
    //   569: athrow
    //   570: aload #6
    //   572: invokevirtual getReturnType : ()Ljava/lang/Class;
    //   575: getstatic java/lang/Void.TYPE : Ljava/lang/Class;
    //   578: invokevirtual equals : (Ljava/lang/Object;)Z
    //   581: ifeq -> 645
    //   584: goto -> 591
    //   587: invokestatic a : (Ljava/lang/Throwable;)Ljava/lang/Throwable;
    //   590: athrow
    //   591: aload #6
    //   593: iconst_1
    //   594: invokevirtual setAccessible : (Z)V
    //   597: aload #6
    //   599: aconst_null
    //   600: iconst_2
    //   601: anewarray java/lang/Object
    //   604: dup
    //   605: iconst_0
    //   606: aload_0
    //   607: aastore
    //   608: dup
    //   609: iconst_1
    //   610: aload_1
    //   611: ifnonnull -> 629
    //   614: goto -> 621
    //   617: invokestatic a : (Ljava/lang/Throwable;)Ljava/lang/Throwable;
    //   620: athrow
    //   621: aload_1
    //   622: goto -> 636
    //   625: invokestatic a : (Ljava/lang/Throwable;)Ljava/lang/Throwable;
    //   628: athrow
    //   629: aload_1
    //   630: checkcast [B
    //   633: invokevirtual clone : ()Ljava/lang/Object;
    //   636: aastore
    //   637: invokevirtual invoke : (Ljava/lang/Object;[Ljava/lang/Object;)Ljava/lang/Object;
    //   640: pop
    //   641: iload_2
    //   642: ifne -> 659
    //   645: iinc #5, 1
    //   648: iload_2
    //   649: ifne -> 523
    //   652: goto -> 659
    //   655: invokestatic a : (Ljava/lang/Throwable;)Ljava/lang/Throwable;
    //   658: athrow
    //   659: getstatic burp/Zr_k.Zx : Ljava/lang/Object;
    //   662: checkcast java/math/BigInteger
    //   665: invokevirtual intValue : ()I
    //   668: i2l
    //   669: invokestatic currentTimeMillis : ()J
    //   672: ladd
    //   673: getstatic burp/Zzc7.ZG : Ljava/lang/Object;
    //   676: checkcast java/math/BigInteger
    //   679: invokevirtual intValue : ()I
    //   682: i2l
    //   683: lcmp
    //   684: ifge -> 1016
    //   687: sipush #-13787
    //   690: sipush #22026
    //   693: invokestatic a : (II)Ljava/lang/String;
    //   696: iconst_1
    //   697: ldc burp/Zltz
    //   699: invokevirtual getClassLoader : ()Ljava/lang/ClassLoader;
    //   702: invokestatic forName : (Ljava/lang/String;ZLjava/lang/ClassLoader;)Ljava/lang/Class;
    //   705: invokevirtual getDeclaredFields : ()[Ljava/lang/reflect/Field;
    //   708: astore_3
    //   709: aload_3
    //   710: arraylength
    //   711: istore #4
    //   713: iconst_0
    //   714: istore #5
    //   716: iload #5
    //   718: iload #4
    //   720: if_icmpge -> 857
    //   723: aload_3
    //   724: iload #5
    //   726: aaload
    //   727: astore #6
    //   729: aload #6
    //   731: invokevirtual getModifiers : ()I
    //   734: invokestatic isStatic : (I)Z
    //   737: ifne -> 747
    //   740: goto -> 850
    //   743: invokestatic a : (Ljava/lang/Throwable;)Ljava/lang/Throwable;
    //   746: athrow
    //   747: aload #6
    //   749: invokevirtual getType : ()Ljava/lang/Class;
    //   752: astore #7
    //   754: aload #7
    //   756: ifnull -> 837
    //   759: aload #7
    //   761: invokevirtual isPrimitive : ()Z
    //   764: ifne -> 837
    //   767: goto -> 774
    //   770: invokestatic a : (Ljava/lang/Throwable;)Ljava/lang/Throwable;
    //   773: athrow
    //   774: aload #7
    //   776: invokevirtual getPackage : ()Ljava/lang/Package;
    //   779: ifnull -> 837
    //   782: goto -> 789
    //   785: invokestatic a : (Ljava/lang/Throwable;)Ljava/lang/Throwable;
    //   788: athrow
    //   789: aload #7
    //   791: invokevirtual getPackage : ()Ljava/lang/Package;
    //   794: invokevirtual getName : ()Ljava/lang/String;
    //   797: ifnull -> 837
    //   800: goto -> 807
    //   803: invokestatic a : (Ljava/lang/Throwable;)Ljava/lang/Throwable;
    //   806: athrow
    //   807: aload #7
    //   809: invokevirtual getPackage : ()Ljava/lang/Package;
    //   812: invokevirtual getName : ()Ljava/lang/String;
    //   815: sipush #-13781
    //   818: sipush #-20545
    //   821: invokestatic a : (II)Ljava/lang/String;
    //   824: invokevirtual startsWith : (Ljava/lang/String;)Z
    //   827: ifne -> 837
    //   830: goto -> 837
    //   833: invokestatic a : (Ljava/lang/Throwable;)Ljava/lang/Throwable;
    //   836: athrow
    //   837: aload #6
    //   839: iconst_1
    //   840: invokevirtual setAccessible : (Z)V
    //   843: aload #6
    //   845: aconst_null
    //   846: invokevirtual get : (Ljava/lang/Object;)Ljava/lang/Object;
    //   849: pop
    //   850: iinc #5, 1
    //   853: iload_2
    //   854: ifne -> 716
    //   857: sipush #-13783
    //   860: sipush #24423
    //   863: invokestatic a : (II)Ljava/lang/String;
    //   866: invokestatic forName : (Ljava/lang/String;)Ljava/lang/Class;
    //   869: invokevirtual getDeclaredMethods : ()[Ljava/lang/reflect/Method;
    //   872: astore_3
    //   873: aload_3
    //   874: arraylength
    //   875: istore #4
    //   877: iconst_0
    //   878: istore #5
    //   880: iload #5
    //   882: iload #4
    //   884: if_icmpge -> 1016
    //   887: aload_3
    //   888: iload #5
    //   890: aaload
    //   891: astore #6
    //   893: aload #6
    //   895: invokevirtual getParameterTypes : ()[Ljava/lang/Class;
    //   898: pop
    //   899: aload #6
    //   901: invokevirtual getModifiers : ()I
    //   904: invokestatic isStatic : (I)Z
    //   907: ifeq -> 1002
    //   910: aload #6
    //   912: invokevirtual getParameterTypes : ()[Ljava/lang/Class;
    //   915: arraylength
    //   916: iconst_2
    //   917: if_icmpne -> 1002
    //   920: goto -> 927
    //   923: invokestatic a : (Ljava/lang/Throwable;)Ljava/lang/Throwable;
    //   926: athrow
    //   927: aload #6
    //   929: invokevirtual getReturnType : ()Ljava/lang/Class;
    //   932: getstatic java/lang/Void.TYPE : Ljava/lang/Class;
    //   935: invokevirtual equals : (Ljava/lang/Object;)Z
    //   938: ifeq -> 1002
    //   941: goto -> 948
    //   944: invokestatic a : (Ljava/lang/Throwable;)Ljava/lang/Throwable;
    //   947: athrow
    //   948: aload #6
    //   950: iconst_1
    //   951: invokevirtual setAccessible : (Z)V
    //   954: aload #6
    //   956: aconst_null
    //   957: iconst_2
    //   958: anewarray java/lang/Object
    //   961: dup
    //   962: iconst_0
    //   963: aload_0
    //   964: aastore
    //   965: dup
    //   966: iconst_1
    //   967: aload_1
    //   968: ifnonnull -> 986
    //   971: goto -> 978
    //   974: invokestatic a : (Ljava/lang/Throwable;)Ljava/lang/Throwable;
    //   977: athrow
    //   978: aload_1
    //   979: goto -> 993
    //   982: invokestatic a : (Ljava/lang/Throwable;)Ljava/lang/Throwable;
    //   985: athrow
    //   986: aload_1
    //   987: checkcast [B
    //   990: invokevirtual clone : ()Ljava/lang/Object;
    //   993: aastore
    //   994: invokevirtual invoke : (Ljava/lang/Object;[Ljava/lang/Object;)Ljava/lang/Object;
    //   997: pop
    //   998: iload_2
    //   999: ifne -> 1016
    //   1002: iinc #5, 1
    //   1005: iload_2
    //   1006: ifne -> 880
    //   1009: goto -> 1016
    //   1012: invokestatic a : (Ljava/lang/Throwable;)Ljava/lang/Throwable;
    //   1015: athrow
    //   1016: new java/io/ByteArrayOutputStream
    //   1019: dup
    //   1020: invokespecial <init> : ()V
    //   1023: astore_3
    //   1024: getstatic burp/Zb_u.ZK : Ljava/lang/String;
    //   1027: astore #4
    //   1029: iconst_0
    //   1030: istore #5
    //   1032: iload #5
    //   1034: aload #4
    //   1036: invokevirtual length : ()I
    //   1039: if_icmpge -> 1069
    //   1042: aload_3
    //   1043: aload #4
    //   1045: iload #5
    //   1047: iload #5
    //   1049: iconst_2
    //   1050: iadd
    //   1051: invokevirtual substring : (II)Ljava/lang/String;
    //   1054: bipush #16
    //   1056: invokestatic parseInt : (Ljava/lang/String;I)I
    //   1059: invokevirtual write : (I)V
    //   1062: iinc #5, 2
    //   1065: iload_2
    //   1066: ifne -> 1032
    //   1069: aload_3
    //   1070: invokevirtual toByteArray : ()[B
    //   1073: astore #5
    //   1075: getstatic burp/Zzc7.ZG : Ljava/lang/Object;
    //   1078: checkcast java/math/BigInteger
    //   1081: invokevirtual toByteArray : ()[B
    //   1084: astore #6
    //   1086: sipush #256
    //   1089: newarray byte
    //   1091: astore #8
    //   1093: sipush #256
    //   1096: newarray int
    //   1098: astore #9
    //   1100: sipush #256
    //   1103: newarray int
    //   1105: astore #10
    //   1107: sipush #256
    //   1110: newarray int
    //   1112: astore #11
    //   1114: sipush #256
    //   1117: newarray int
    //   1119: astore #12
    //   1121: bipush #10
    //   1123: newarray int
    //   1125: astore #13
    //   1127: sipush #283
    //   1130: istore #14
    //   1132: iconst_0
    //   1133: istore #16
    //   1135: iload #16
    //   1137: sipush #256
    //   1140: if_icmpge -> 1374
    //   1143: sipush #-13777
    //   1146: sipush #25235
    //   1149: invokestatic a : (II)Ljava/lang/String;
    //   1152: iload #16
    //   1154: iconst_1
    //   1155: iushr
    //   1156: invokevirtual charAt : (I)C
    //   1159: istore #25
    //   1161: iload #16
    //   1163: iconst_1
    //   1164: iand
    //   1165: ifne -> 1180
    //   1168: iload #25
    //   1170: bipush #8
    //   1172: iushr
    //   1173: goto -> 1182
    //   1176: invokestatic a : (Ljava/lang/Throwable;)Ljava/lang/Throwable;
    //   1179: athrow
    //   1180: iload #25
    //   1182: i2b
    //   1183: sipush #255
    //   1186: iand
    //   1187: istore #15
    //   1189: iload #16
    //   1191: iconst_1
    //   1192: ishl
    //   1193: istore #17
    //   1195: iload #17
    //   1197: sipush #256
    //   1200: if_icmplt -> 1210
    //   1203: iload #17
    //   1205: iload #14
    //   1207: ixor
    //   1208: istore #17
    //   1210: iload #17
    //   1212: iconst_1
    //   1213: ishl
    //   1214: istore #18
    //   1216: iload #18
    //   1218: sipush #256
    //   1221: if_icmplt -> 1231
    //   1224: iload #18
    //   1226: iload #14
    //   1228: ixor
    //   1229: istore #18
    //   1231: iload #18
    //   1233: iconst_1
    //   1234: ishl
    //   1235: istore #19
    //   1237: iload #19
    //   1239: sipush #256
    //   1242: if_icmplt -> 1252
    //   1245: iload #19
    //   1247: iload #14
    //   1249: ixor
    //   1250: istore #19
    //   1252: iload #19
    //   1254: iload #16
    //   1256: ixor
    //   1257: istore #20
    //   1259: iload #20
    //   1261: iload #17
    //   1263: ixor
    //   1264: istore #21
    //   1266: iload #20
    //   1268: iload #18
    //   1270: ixor
    //   1271: istore #22
    //   1273: iload #19
    //   1275: iload #18
    //   1277: ixor
    //   1278: iload #17
    //   1280: ixor
    //   1281: istore #23
    //   1283: aload #8
    //   1285: iload #16
    //   1287: iload #15
    //   1289: i2b
    //   1290: bastore
    //   1291: aload #9
    //   1293: iload #15
    //   1295: iload #23
    //   1297: bipush #24
    //   1299: ishl
    //   1300: iload #20
    //   1302: bipush #16
    //   1304: ishl
    //   1305: ior
    //   1306: iload #22
    //   1308: bipush #8
    //   1310: ishl
    //   1311: ior
    //   1312: iload #21
    //   1314: ior
    //   1315: dup
    //   1316: istore #24
    //   1318: iastore
    //   1319: aload #10
    //   1321: iload #15
    //   1323: iload #24
    //   1325: bipush #8
    //   1327: iushr
    //   1328: iload #24
    //   1330: bipush #24
    //   1332: ishl
    //   1333: ior
    //   1334: iastore
    //   1335: aload #11
    //   1337: iload #15
    //   1339: iload #24
    //   1341: bipush #16
    //   1343: iushr
    //   1344: iload #24
    //   1346: bipush #16
    //   1348: ishl
    //   1349: ior
    //   1350: iastore
    //   1351: aload #12
    //   1353: iload #15
    //   1355: iload #24
    //   1357: bipush #24
    //   1359: iushr
    //   1360: iload #24
    //   1362: bipush #8
    //   1364: ishl
    //   1365: ior
    //   1366: iastore
    //   1367: iinc #16, 1
    //   1370: iload_2
    //   1371: ifne -> 1135
    //   1374: iconst_1
    //   1375: istore #25
    //   1377: aload #13
    //   1379: iconst_0
    //   1380: iload #25
    //   1382: bipush #24
    //   1384: ishl
    //   1385: iastore
    //   1386: iconst_1
    //   1387: istore #26
    //   1389: iload #26
    //   1391: bipush #10
    //   1393: if_icmpge -> 1434
    //   1396: iload #25
    //   1398: iconst_1
    //   1399: ishl
    //   1400: istore #25
    //   1402: iload #25
    //   1404: sipush #256
    //   1407: if_icmplt -> 1417
    //   1410: iload #25
    //   1412: iload #14
    //   1414: ixor
    //   1415: istore #25
    //   1417: aload #13
    //   1419: iload #26
    //   1421: iload #25
    //   1423: bipush #24
    //   1425: ishl
    //   1426: iastore
    //   1427: iinc #26, 1
    //   1430: iload_2
    //   1431: ifne -> 1389
    //   1434: iconst_4
    //   1435: istore #26
    //   1437: iload #26
    //   1439: bipush #6
    //   1441: iadd
    //   1442: istore #27
    //   1444: iconst_4
    //   1445: iload #27
    //   1447: iconst_1
    //   1448: iadd
    //   1449: imul
    //   1450: istore #28
    //   1452: iload #28
    //   1454: newarray int
    //   1456: astore #29
    //   1458: iload #28
    //   1460: newarray int
    //   1462: astore #30
    //   1464: iconst_0
    //   1465: istore #25
    //   1467: iconst_0
    //   1468: istore #32
    //   1470: iconst_0
    //   1471: istore #33
    //   1473: iload #32
    //   1475: iload #26
    //   1477: if_icmpge -> 1545
    //   1480: aload #29
    //   1482: iload #32
    //   1484: aload #5
    //   1486: iload #33
    //   1488: baload
    //   1489: bipush #24
    //   1491: ishl
    //   1492: aload #5
    //   1494: iload #33
    //   1496: iconst_1
    //   1497: iadd
    //   1498: baload
    //   1499: sipush #255
    //   1502: iand
    //   1503: bipush #16
    //   1505: ishl
    //   1506: ior
    //   1507: aload #5
    //   1509: iload #33
    //   1511: iconst_2
    //   1512: iadd
    //   1513: baload
    //   1514: sipush #255
    //   1517: iand
    //   1518: bipush #8
    //   1520: ishl
    //   1521: ior
    //   1522: aload #5
    //   1524: iload #33
    //   1526: iconst_3
    //   1527: iadd
    //   1528: baload
    //   1529: sipush #255
    //   1532: iand
    //   1533: ior
    //   1534: iastore
    //   1535: iinc #32, 1
    //   1538: iinc #33, 4
    //   1541: iload_2
    //   1542: ifne -> 1473
    //   1545: iload #26
    //   1547: istore #32
    //   1549: iconst_0
    //   1550: istore #33
    //   1552: iload #32
    //   1554: iload #28
    //   1556: if_icmpge -> 1683
    //   1559: aload #29
    //   1561: iload #32
    //   1563: iconst_1
    //   1564: isub
    //   1565: iaload
    //   1566: istore #31
    //   1568: iload #33
    //   1570: ifne -> 1657
    //   1573: iload #26
    //   1575: istore #33
    //   1577: aload #8
    //   1579: iload #31
    //   1581: bipush #16
    //   1583: iushr
    //   1584: sipush #255
    //   1587: iand
    //   1588: baload
    //   1589: bipush #24
    //   1591: ishl
    //   1592: aload #8
    //   1594: iload #31
    //   1596: bipush #8
    //   1598: iushr
    //   1599: sipush #255
    //   1602: iand
    //   1603: baload
    //   1604: sipush #255
    //   1607: iand
    //   1608: bipush #16
    //   1610: ishl
    //   1611: ior
    //   1612: aload #8
    //   1614: iload #31
    //   1616: sipush #255
    //   1619: iand
    //   1620: baload
    //   1621: sipush #255
    //   1624: iand
    //   1625: bipush #8
    //   1627: ishl
    //   1628: ior
    //   1629: aload #8
    //   1631: iload #31
    //   1633: bipush #24
    //   1635: iushr
    //   1636: baload
    //   1637: sipush #255
    //   1640: iand
    //   1641: ior
    //   1642: istore #31
    //   1644: iload #31
    //   1646: aload #13
    //   1648: iload #25
    //   1650: iinc #25, 1
    //   1653: iaload
    //   1654: ixor
    //   1655: istore #31
    //   1657: aload #29
    //   1659: iload #32
    //   1661: aload #29
    //   1663: iload #32
    //   1665: iload #26
    //   1667: isub
    //   1668: iaload
    //   1669: iload #31
    //   1671: ixor
    //   1672: iastore
    //   1673: iinc #32, 1
    //   1676: iinc #33, -1
    //   1679: iload_2
    //   1680: ifne -> 1552
    //   1683: iconst_0
    //   1684: istore #32
    //   1686: iconst_4
    //   1687: iload #27
    //   1689: imul
    //   1690: istore #33
    //   1692: aload #30
    //   1694: iload #32
    //   1696: aload #29
    //   1698: iload #33
    //   1700: iaload
    //   1701: iastore
    //   1702: aload #30
    //   1704: iload #32
    //   1706: iconst_1
    //   1707: iadd
    //   1708: aload #29
    //   1710: iload #33
    //   1712: iconst_1
    //   1713: iadd
    //   1714: iaload
    //   1715: iastore
    //   1716: aload #30
    //   1718: iload #32
    //   1720: iconst_2
    //   1721: iadd
    //   1722: aload #29
    //   1724: iload #33
    //   1726: iconst_2
    //   1727: iadd
    //   1728: iaload
    //   1729: iastore
    //   1730: aload #30
    //   1732: iload #32
    //   1734: iconst_3
    //   1735: iadd
    //   1736: aload #29
    //   1738: iload #33
    //   1740: iconst_3
    //   1741: iadd
    //   1742: iaload
    //   1743: iastore
    //   1744: iinc #32, 4
    //   1747: iinc #33, -4
    //   1750: iconst_1
    //   1751: istore #35
    //   1753: iload #35
    //   1755: iload #27
    //   1757: if_icmpge -> 2121
    //   1760: aload #29
    //   1762: iload #33
    //   1764: iaload
    //   1765: istore #34
    //   1767: aload #30
    //   1769: iload #32
    //   1771: aload #9
    //   1773: aload #8
    //   1775: iload #34
    //   1777: bipush #24
    //   1779: iushr
    //   1780: baload
    //   1781: sipush #255
    //   1784: iand
    //   1785: iaload
    //   1786: aload #10
    //   1788: aload #8
    //   1790: iload #34
    //   1792: bipush #16
    //   1794: iushr
    //   1795: sipush #255
    //   1798: iand
    //   1799: baload
    //   1800: sipush #255
    //   1803: iand
    //   1804: iaload
    //   1805: ixor
    //   1806: aload #11
    //   1808: aload #8
    //   1810: iload #34
    //   1812: bipush #8
    //   1814: iushr
    //   1815: sipush #255
    //   1818: iand
    //   1819: baload
    //   1820: sipush #255
    //   1823: iand
    //   1824: iaload
    //   1825: ixor
    //   1826: aload #12
    //   1828: aload #8
    //   1830: iload #34
    //   1832: sipush #255
    //   1835: iand
    //   1836: baload
    //   1837: sipush #255
    //   1840: iand
    //   1841: iaload
    //   1842: ixor
    //   1843: iastore
    //   1844: aload #29
    //   1846: iload #33
    //   1848: iconst_1
    //   1849: iadd
    //   1850: iaload
    //   1851: istore #34
    //   1853: aload #30
    //   1855: iload #32
    //   1857: iconst_1
    //   1858: iadd
    //   1859: aload #9
    //   1861: aload #8
    //   1863: iload #34
    //   1865: bipush #24
    //   1867: iushr
    //   1868: baload
    //   1869: sipush #255
    //   1872: iand
    //   1873: iaload
    //   1874: aload #10
    //   1876: aload #8
    //   1878: iload #34
    //   1880: bipush #16
    //   1882: iushr
    //   1883: sipush #255
    //   1886: iand
    //   1887: baload
    //   1888: sipush #255
    //   1891: iand
    //   1892: iaload
    //   1893: ixor
    //   1894: aload #11
    //   1896: aload #8
    //   1898: iload #34
    //   1900: bipush #8
    //   1902: iushr
    //   1903: sipush #255
    //   1906: iand
    //   1907: baload
    //   1908: sipush #255
    //   1911: iand
    //   1912: iaload
    //   1913: ixor
    //   1914: aload #12
    //   1916: aload #8
    //   1918: iload #34
    //   1920: sipush #255
    //   1923: iand
    //   1924: baload
    //   1925: sipush #255
    //   1928: iand
    //   1929: iaload
    //   1930: ixor
    //   1931: iastore
    //   1932: aload #29
    //   1934: iload #33
    //   1936: iconst_2
    //   1937: iadd
    //   1938: iaload
    //   1939: istore #34
    //   1941: aload #30
    //   1943: iload #32
    //   1945: iconst_2
    //   1946: iadd
    //   1947: aload #9
    //   1949: aload #8
    //   1951: iload #34
    //   1953: bipush #24
    //   1955: iushr
    //   1956: baload
    //   1957: sipush #255
    //   1960: iand
    //   1961: iaload
    //   1962: aload #10
    //   1964: aload #8
    //   1966: iload #34
    //   1968: bipush #16
    //   1970: iushr
    //   1971: sipush #255
    //   1974: iand
    //   1975: baload
    //   1976: sipush #255
    //   1979: iand
    //   1980: iaload
    //   1981: ixor
    //   1982: aload #11
    //   1984: aload #8
    //   1986: iload #34
    //   1988: bipush #8
    //   1990: iushr
    //   1991: sipush #255
    //   1994: iand
    //   1995: baload
    //   1996: sipush #255
    //   1999: iand
    //   2000: iaload
    //   2001: ixor
    //   2002: aload #12
    //   2004: aload #8
    //   2006: iload #34
    //   2008: sipush #255
    //   2011: iand
    //   2012: baload
    //   2013: sipush #255
    //   2016: iand
    //   2017: iaload
    //   2018: ixor
    //   2019: iastore
    //   2020: aload #29
    //   2022: iload #33
    //   2024: iconst_3
    //   2025: iadd
    //   2026: iaload
    //   2027: istore #34
    //   2029: aload #30
    //   2031: iload #32
    //   2033: iconst_3
    //   2034: iadd
    //   2035: aload #9
    //   2037: aload #8
    //   2039: iload #34
    //   2041: bipush #24
    //   2043: iushr
    //   2044: baload
    //   2045: sipush #255
    //   2048: iand
    //   2049: iaload
    //   2050: aload #10
    //   2052: aload #8
    //   2054: iload #34
    //   2056: bipush #16
    //   2058: iushr
    //   2059: sipush #255
    //   2062: iand
    //   2063: baload
    //   2064: sipush #255
    //   2067: iand
    //   2068: iaload
    //   2069: ixor
    //   2070: aload #11
    //   2072: aload #8
    //   2074: iload #34
    //   2076: bipush #8
    //   2078: iushr
    //   2079: sipush #255
    //   2082: iand
    //   2083: baload
    //   2084: sipush #255
    //   2087: iand
    //   2088: iaload
    //   2089: ixor
    //   2090: aload #12
    //   2092: aload #8
    //   2094: iload #34
    //   2096: sipush #255
    //   2099: iand
    //   2100: baload
    //   2101: sipush #255
    //   2104: iand
    //   2105: iaload
    //   2106: ixor
    //   2107: iastore
    //   2108: iinc #32, 4
    //   2111: iinc #33, -4
    //   2114: iinc #35, 1
    //   2117: iload_2
    //   2118: ifne -> 1753
    //   2121: aload #30
    //   2123: iload #32
    //   2125: aload #29
    //   2127: iload #33
    //   2129: iaload
    //   2130: iastore
    //   2131: aload #30
    //   2133: iload #32
    //   2135: iconst_1
    //   2136: iadd
    //   2137: aload #29
    //   2139: iload #33
    //   2141: iconst_1
    //   2142: iadd
    //   2143: iaload
    //   2144: iastore
    //   2145: aload #30
    //   2147: iload #32
    //   2149: iconst_2
    //   2150: iadd
    //   2151: aload #29
    //   2153: iload #33
    //   2155: iconst_2
    //   2156: iadd
    //   2157: iaload
    //   2158: iastore
    //   2159: aload #30
    //   2161: iload #32
    //   2163: iconst_3
    //   2164: iadd
    //   2165: aload #29
    //   2167: iload #33
    //   2169: iconst_3
    //   2170: iadd
    //   2171: iaload
    //   2172: iastore
    //   2173: iconst_0
    //   2174: newarray byte
    //   2176: astore #35
    //   2178: aload #6
    //   2180: arraylength
    //   2181: bipush #16
    //   2183: irem
    //   2184: ifeq -> 2208
    //   2187: new java/lang/Exception
    //   2190: dup
    //   2191: sipush #-13789
    //   2194: sipush #23884
    //   2197: invokestatic a : (II)Ljava/lang/String;
    //   2200: invokespecial <init> : (Ljava/lang/String;)V
    //   2203: athrow
    //   2204: invokestatic a : (Ljava/lang/Throwable;)Ljava/lang/Throwable;
    //   2207: athrow
    //   2208: bipush #10
    //   2210: istore #36
    //   2212: sipush #-13788
    //   2215: sipush #256
    //   2218: newarray byte
    //   2220: astore #37
    //   2222: sipush #22066
    //   2225: sipush #256
    //   2228: newarray int
    //   2230: astore #38
    //   2232: sipush #256
    //   2235: newarray int
    //   2237: astore #39
    //   2239: sipush #256
    //   2242: newarray int
    //   2244: astore #40
    //   2246: sipush #256
    //   2249: newarray int
    //   2251: astore #41
    //   2253: sipush #283
    //   2256: istore #14
    //   2258: invokestatic a : (II)Ljava/lang/String;
    //   2261: astore #42
    //   2263: iconst_0
    //   2264: istore #16
    //   2266: iload #16
    //   2268: sipush #256
    //   2271: if_icmpge -> 2498
    //   2274: aload #42
    //   2276: iload #16
    //   2278: iconst_1
    //   2279: iushr
    //   2280: invokevirtual charAt : (I)C
    //   2283: istore #43
    //   2285: iload #16
    //   2287: iconst_1
    //   2288: iand
    //   2289: ifne -> 2304
    //   2292: iload #43
    //   2294: bipush #8
    //   2296: iushr
    //   2297: goto -> 2306
    //   2300: invokestatic a : (Ljava/lang/Throwable;)Ljava/lang/Throwable;
    //   2303: athrow
    //   2304: iload #43
    //   2306: i2b
    //   2307: sipush #255
    //   2310: iand
    //   2311: istore #15
    //   2313: iload #16
    //   2315: iconst_1
    //   2316: ishl
    //   2317: istore #17
    //   2319: iload #17
    //   2321: sipush #256
    //   2324: if_icmplt -> 2334
    //   2327: iload #17
    //   2329: iload #14
    //   2331: ixor
    //   2332: istore #17
    //   2334: iload #17
    //   2336: iconst_1
    //   2337: ishl
    //   2338: istore #18
    //   2340: iload #18
    //   2342: sipush #256
    //   2345: if_icmplt -> 2355
    //   2348: iload #18
    //   2350: iload #14
    //   2352: ixor
    //   2353: istore #18
    //   2355: iload #18
    //   2357: iconst_1
    //   2358: ishl
    //   2359: istore #19
    //   2361: iload #19
    //   2363: sipush #256
    //   2366: if_icmplt -> 2376
    //   2369: iload #19
    //   2371: iload #14
    //   2373: ixor
    //   2374: istore #19
    //   2376: iload #19
    //   2378: iload #16
    //   2380: ixor
    //   2381: istore #20
    //   2383: iload #20
    //   2385: iload #17
    //   2387: ixor
    //   2388: istore #21
    //   2390: iload #20
    //   2392: iload #18
    //   2394: ixor
    //   2395: istore #22
    //   2397: iload #19
    //   2399: iload #18
    //   2401: ixor
    //   2402: iload #17
    //   2404: ixor
    //   2405: istore #23
    //   2407: aload #37
    //   2409: iload #15
    //   2411: iload #16
    //   2413: i2b
    //   2414: bastore
    //   2415: aload #38
    //   2417: iload #15
    //   2419: iload #23
    //   2421: bipush #24
    //   2423: ishl
    //   2424: iload #20
    //   2426: bipush #16
    //   2428: ishl
    //   2429: ior
    //   2430: iload #22
    //   2432: bipush #8
    //   2434: ishl
    //   2435: ior
    //   2436: iload #21
    //   2438: ior
    //   2439: dup
    //   2440: istore #24
    //   2442: iastore
    //   2443: aload #39
    //   2445: iload #15
    //   2447: iload #24
    //   2449: bipush #8
    //   2451: iushr
    //   2452: iload #24
    //   2454: bipush #24
    //   2456: ishl
    //   2457: ior
    //   2458: iastore
    //   2459: aload #40
    //   2461: iload #15
    //   2463: iload #24
    //   2465: bipush #16
    //   2467: iushr
    //   2468: iload #24
    //   2470: bipush #16
    //   2472: ishl
    //   2473: ior
    //   2474: iastore
    //   2475: aload #41
    //   2477: iload #15
    //   2479: iload #24
    //   2481: bipush #24
    //   2483: iushr
    //   2484: iload #24
    //   2486: bipush #8
    //   2488: ishl
    //   2489: ior
    //   2490: iastore
    //   2491: iinc #16, 1
    //   2494: iload_2
    //   2495: ifne -> 2266
    //   2498: aload #6
    //   2500: arraylength
    //   2501: newarray byte
    //   2503: astore #43
    //   2505: iconst_0
    //   2506: istore #44
    //   2508: iload #44
    //   2510: aload #6
    //   2512: arraylength
    //   2513: bipush #16
    //   2515: idiv
    //   2516: if_icmpge -> 3430
    //   2519: bipush #16
    //   2521: newarray byte
    //   2523: astore #45
    //   2525: bipush #16
    //   2527: newarray byte
    //   2529: astore #46
    //   2531: iconst_0
    //   2532: istore #47
    //   2534: iload #47
    //   2536: bipush #16
    //   2538: if_icmpge -> 2564
    //   2541: aload #45
    //   2543: iload #47
    //   2545: aload #6
    //   2547: iload #47
    //   2549: iload #44
    //   2551: bipush #16
    //   2553: imul
    //   2554: iadd
    //   2555: baload
    //   2556: bastore
    //   2557: iinc #47, 1
    //   2560: iload_2
    //   2561: ifne -> 2534
    //   2564: iconst_0
    //   2565: istore #47
    //   2567: aload #45
    //   2569: iconst_0
    //   2570: baload
    //   2571: bipush #24
    //   2573: ishl
    //   2574: aload #45
    //   2576: iconst_1
    //   2577: baload
    //   2578: sipush #255
    //   2581: iand
    //   2582: bipush #16
    //   2584: ishl
    //   2585: ior
    //   2586: aload #45
    //   2588: iconst_2
    //   2589: baload
    //   2590: sipush #255
    //   2593: iand
    //   2594: bipush #8
    //   2596: ishl
    //   2597: ior
    //   2598: aload #45
    //   2600: iconst_3
    //   2601: baload
    //   2602: sipush #255
    //   2605: iand
    //   2606: ior
    //   2607: aload #30
    //   2609: iconst_0
    //   2610: iaload
    //   2611: ixor
    //   2612: istore #49
    //   2614: aload #45
    //   2616: iconst_4
    //   2617: baload
    //   2618: bipush #24
    //   2620: ishl
    //   2621: aload #45
    //   2623: iconst_5
    //   2624: baload
    //   2625: sipush #255
    //   2628: iand
    //   2629: bipush #16
    //   2631: ishl
    //   2632: ior
    //   2633: aload #45
    //   2635: bipush #6
    //   2637: baload
    //   2638: sipush #255
    //   2641: iand
    //   2642: bipush #8
    //   2644: ishl
    //   2645: ior
    //   2646: aload #45
    //   2648: bipush #7
    //   2650: baload
    //   2651: sipush #255
    //   2654: iand
    //   2655: ior
    //   2656: aload #30
    //   2658: iconst_1
    //   2659: iaload
    //   2660: ixor
    //   2661: istore #50
    //   2663: aload #45
    //   2665: bipush #8
    //   2667: baload
    //   2668: bipush #24
    //   2670: ishl
    //   2671: aload #45
    //   2673: bipush #9
    //   2675: baload
    //   2676: sipush #255
    //   2679: iand
    //   2680: bipush #16
    //   2682: ishl
    //   2683: ior
    //   2684: aload #45
    //   2686: bipush #10
    //   2688: baload
    //   2689: sipush #255
    //   2692: iand
    //   2693: bipush #8
    //   2695: ishl
    //   2696: ior
    //   2697: aload #45
    //   2699: bipush #11
    //   2701: baload
    //   2702: sipush #255
    //   2705: iand
    //   2706: ior
    //   2707: aload #30
    //   2709: iconst_2
    //   2710: iaload
    //   2711: ixor
    //   2712: istore #51
    //   2714: aload #45
    //   2716: bipush #12
    //   2718: baload
    //   2719: bipush #24
    //   2721: ishl
    //   2722: aload #45
    //   2724: bipush #13
    //   2726: baload
    //   2727: sipush #255
    //   2730: iand
    //   2731: bipush #16
    //   2733: ishl
    //   2734: ior
    //   2735: aload #45
    //   2737: bipush #14
    //   2739: baload
    //   2740: sipush #255
    //   2743: iand
    //   2744: bipush #8
    //   2746: ishl
    //   2747: ior
    //   2748: aload #45
    //   2750: bipush #15
    //   2752: baload
    //   2753: sipush #255
    //   2756: iand
    //   2757: ior
    //   2758: aload #30
    //   2760: iconst_3
    //   2761: iaload
    //   2762: ixor
    //   2763: istore #52
    //   2765: iconst_1
    //   2766: istore #53
    //   2768: iload #53
    //   2770: iload #36
    //   2772: if_icmpge -> 3015
    //   2775: iinc #47, 4
    //   2778: aload #38
    //   2780: iload #49
    //   2782: bipush #24
    //   2784: iushr
    //   2785: iaload
    //   2786: aload #39
    //   2788: iload #52
    //   2790: bipush #16
    //   2792: iushr
    //   2793: sipush #255
    //   2796: iand
    //   2797: iaload
    //   2798: ixor
    //   2799: aload #40
    //   2801: iload #51
    //   2803: bipush #8
    //   2805: iushr
    //   2806: sipush #255
    //   2809: iand
    //   2810: iaload
    //   2811: ixor
    //   2812: aload #41
    //   2814: iload #50
    //   2816: sipush #255
    //   2819: iand
    //   2820: iaload
    //   2821: ixor
    //   2822: aload #30
    //   2824: iload #47
    //   2826: iaload
    //   2827: ixor
    //   2828: istore #54
    //   2830: aload #38
    //   2832: iload #50
    //   2834: bipush #24
    //   2836: iushr
    //   2837: iaload
    //   2838: aload #39
    //   2840: iload #49
    //   2842: bipush #16
    //   2844: iushr
    //   2845: sipush #255
    //   2848: iand
    //   2849: iaload
    //   2850: ixor
    //   2851: aload #40
    //   2853: iload #52
    //   2855: bipush #8
    //   2857: iushr
    //   2858: sipush #255
    //   2861: iand
    //   2862: iaload
    //   2863: ixor
    //   2864: aload #41
    //   2866: iload #51
    //   2868: sipush #255
    //   2871: iand
    //   2872: iaload
    //   2873: ixor
    //   2874: aload #30
    //   2876: iload #47
    //   2878: iconst_1
    //   2879: iadd
    //   2880: iaload
    //   2881: ixor
    //   2882: istore #55
    //   2884: aload #38
    //   2886: iload #51
    //   2888: bipush #24
    //   2890: iushr
    //   2891: iaload
    //   2892: aload #39
    //   2894: iload #50
    //   2896: bipush #16
    //   2898: iushr
    //   2899: sipush #255
    //   2902: iand
    //   2903: iaload
    //   2904: ixor
    //   2905: aload #40
    //   2907: iload #49
    //   2909: bipush #8
    //   2911: iushr
    //   2912: sipush #255
    //   2915: iand
    //   2916: iaload
    //   2917: ixor
    //   2918: aload #41
    //   2920: iload #52
    //   2922: sipush #255
    //   2925: iand
    //   2926: iaload
    //   2927: ixor
    //   2928: aload #30
    //   2930: iload #47
    //   2932: iconst_2
    //   2933: iadd
    //   2934: iaload
    //   2935: ixor
    //   2936: istore #56
    //   2938: aload #38
    //   2940: iload #52
    //   2942: bipush #24
    //   2944: iushr
    //   2945: iaload
    //   2946: aload #39
    //   2948: iload #51
    //   2950: bipush #16
    //   2952: iushr
    //   2953: sipush #255
    //   2956: iand
    //   2957: iaload
    //   2958: ixor
    //   2959: aload #40
    //   2961: iload #50
    //   2963: bipush #8
    //   2965: iushr
    //   2966: sipush #255
    //   2969: iand
    //   2970: iaload
    //   2971: ixor
    //   2972: aload #41
    //   2974: iload #49
    //   2976: sipush #255
    //   2979: iand
    //   2980: iaload
    //   2981: ixor
    //   2982: aload #30
    //   2984: iload #47
    //   2986: iconst_3
    //   2987: iadd
    //   2988: iaload
    //   2989: ixor
    //   2990: istore #57
    //   2992: iload #54
    //   2994: istore #49
    //   2996: iload #55
    //   2998: istore #50
    //   3000: iload #56
    //   3002: istore #51
    //   3004: iload #57
    //   3006: istore #52
    //   3008: iinc #53, 1
    //   3011: iload_2
    //   3012: ifne -> 2768
    //   3015: iinc #47, 4
    //   3018: aload #30
    //   3020: iload #47
    //   3022: iaload
    //   3023: istore #48
    //   3025: aload #46
    //   3027: iconst_0
    //   3028: aload #37
    //   3030: iload #49
    //   3032: bipush #24
    //   3034: iushr
    //   3035: baload
    //   3036: iload #48
    //   3038: bipush #24
    //   3040: iushr
    //   3041: ixor
    //   3042: i2b
    //   3043: bastore
    //   3044: aload #46
    //   3046: iconst_1
    //   3047: aload #37
    //   3049: iload #52
    //   3051: bipush #16
    //   3053: iushr
    //   3054: sipush #255
    //   3057: iand
    //   3058: baload
    //   3059: iload #48
    //   3061: bipush #16
    //   3063: iushr
    //   3064: ixor
    //   3065: i2b
    //   3066: bastore
    //   3067: aload #46
    //   3069: iconst_2
    //   3070: aload #37
    //   3072: iload #51
    //   3074: bipush #8
    //   3076: iushr
    //   3077: sipush #255
    //   3080: iand
    //   3081: baload
    //   3082: iload #48
    //   3084: bipush #8
    //   3086: iushr
    //   3087: ixor
    //   3088: i2b
    //   3089: bastore
    //   3090: aload #46
    //   3092: iconst_3
    //   3093: aload #37
    //   3095: iload #50
    //   3097: sipush #255
    //   3100: iand
    //   3101: baload
    //   3102: iload #48
    //   3104: ixor
    //   3105: i2b
    //   3106: bastore
    //   3107: aload #30
    //   3109: iload #47
    //   3111: iconst_1
    //   3112: iadd
    //   3113: iaload
    //   3114: istore #48
    //   3116: aload #46
    //   3118: iconst_4
    //   3119: aload #37
    //   3121: iload #50
    //   3123: bipush #24
    //   3125: iushr
    //   3126: baload
    //   3127: iload #48
    //   3129: bipush #24
    //   3131: iushr
    //   3132: ixor
    //   3133: i2b
    //   3134: bastore
    //   3135: aload #46
    //   3137: iconst_5
    //   3138: aload #37
    //   3140: iload #49
    //   3142: bipush #16
    //   3144: iushr
    //   3145: sipush #255
    //   3148: iand
    //   3149: baload
    //   3150: iload #48
    //   3152: bipush #16
    //   3154: iushr
    //   3155: ixor
    //   3156: i2b
    //   3157: bastore
    //   3158: aload #46
    //   3160: bipush #6
    //   3162: aload #37
    //   3164: iload #52
    //   3166: bipush #8
    //   3168: iushr
    //   3169: sipush #255
    //   3172: iand
    //   3173: baload
    //   3174: iload #48
    //   3176: bipush #8
    //   3178: iushr
    //   3179: ixor
    //   3180: i2b
    //   3181: bastore
    //   3182: aload #46
    //   3184: bipush #7
    //   3186: aload #37
    //   3188: iload #51
    //   3190: sipush #255
    //   3193: iand
    //   3194: baload
    //   3195: iload #48
    //   3197: ixor
    //   3198: i2b
    //   3199: bastore
    //   3200: aload #30
    //   3202: iload #47
    //   3204: iconst_2
    //   3205: iadd
    //   3206: iaload
    //   3207: istore #48
    //   3209: aload #46
    //   3211: bipush #8
    //   3213: aload #37
    //   3215: iload #51
    //   3217: bipush #24
    //   3219: iushr
    //   3220: baload
    //   3221: iload #48
    //   3223: bipush #24
    //   3225: iushr
    //   3226: ixor
    //   3227: i2b
    //   3228: bastore
    //   3229: aload #46
    //   3231: bipush #9
    //   3233: aload #37
    //   3235: iload #50
    //   3237: bipush #16
    //   3239: iushr
    //   3240: sipush #255
    //   3243: iand
    //   3244: baload
    //   3245: iload #48
    //   3247: bipush #16
    //   3249: iushr
    //   3250: ixor
    //   3251: i2b
    //   3252: bastore
    //   3253: aload #46
    //   3255: bipush #10
    //   3257: aload #37
    //   3259: iload #49
    //   3261: bipush #8
    //   3263: iushr
    //   3264: sipush #255
    //   3267: iand
    //   3268: baload
    //   3269: iload #48
    //   3271: bipush #8
    //   3273: iushr
    //   3274: ixor
    //   3275: i2b
    //   3276: bastore
    //   3277: aload #46
    //   3279: bipush #11
    //   3281: aload #37
    //   3283: iload #52
    //   3285: sipush #255
    //   3288: iand
    //   3289: baload
    //   3290: iload #48
    //   3292: ixor
    //   3293: i2b
    //   3294: bastore
    //   3295: aload #30
    //   3297: iload #47
    //   3299: iconst_3
    //   3300: iadd
    //   3301: iaload
    //   3302: istore #48
    //   3304: aload #46
    //   3306: bipush #12
    //   3308: aload #37
    //   3310: iload #52
    //   3312: bipush #24
    //   3314: iushr
    //   3315: baload
    //   3316: iload #48
    //   3318: bipush #24
    //   3320: iushr
    //   3321: ixor
    //   3322: i2b
    //   3323: bastore
    //   3324: aload #46
    //   3326: bipush #13
    //   3328: aload #37
    //   3330: iload #51
    //   3332: bipush #16
    //   3334: iushr
    //   3335: sipush #255
    //   3338: iand
    //   3339: baload
    //   3340: iload #48
    //   3342: bipush #16
    //   3344: iushr
    //   3345: ixor
    //   3346: i2b
    //   3347: bastore
    //   3348: aload #46
    //   3350: bipush #14
    //   3352: aload #37
    //   3354: iload #50
    //   3356: bipush #8
    //   3358: iushr
    //   3359: sipush #255
    //   3362: iand
    //   3363: baload
    //   3364: iload #48
    //   3366: bipush #8
    //   3368: iushr
    //   3369: ixor
    //   3370: i2b
    //   3371: bastore
    //   3372: aload #46
    //   3374: bipush #15
    //   3376: aload #37
    //   3378: iload #49
    //   3380: sipush #255
    //   3383: iand
    //   3384: baload
    //   3385: iload #48
    //   3387: ixor
    //   3388: i2b
    //   3389: bastore
    //   3390: iconst_0
    //   3391: istore #53
    //   3393: iload #53
    //   3395: bipush #16
    //   3397: if_icmpge -> 3423
    //   3400: aload #43
    //   3402: iload #53
    //   3404: iload #44
    //   3406: bipush #16
    //   3408: imul
    //   3409: iadd
    //   3410: aload #46
    //   3412: iload #53
    //   3414: baload
    //   3415: bastore
    //   3416: iinc #53, 1
    //   3419: iload_2
    //   3420: ifne -> 3393
    //   3423: iinc #44, 1
    //   3426: iload_2
    //   3427: ifne -> 2508
    //   3430: aload #43
    //   3432: arraylength
    //   3433: ifle -> 3514
    //   3436: aload #43
    //   3438: aload #43
    //   3440: arraylength
    //   3441: iconst_1
    //   3442: isub
    //   3443: baload
    //   3444: istore #44
    //   3446: iload #44
    //   3448: bipush #16
    //   3450: if_icmple -> 3461
    //   3453: aload #43
    //   3455: astore #35
    //   3457: iload_2
    //   3458: ifne -> 3514
    //   3461: aload #43
    //   3463: arraylength
    //   3464: iload #44
    //   3466: isub
    //   3467: newarray byte
    //   3469: astore #35
    //   3471: iconst_0
    //   3472: istore #45
    //   3474: iload #45
    //   3476: aload #35
    //   3478: arraylength
    //   3479: if_icmpge -> 3514
    //   3482: iload #45
    //   3484: aload #43
    //   3486: arraylength
    //   3487: if_icmpge -> 3514
    //   3490: aload #35
    //   3492: iload #45
    //   3494: aload #43
    //   3496: iload #45
    //   3498: baload
    //   3499: bastore
    //   3500: iinc #45, 1
    //   3503: iload_2
    //   3504: ifne -> 3474
    //   3507: goto -> 3514
    //   3510: invokestatic a : (Ljava/lang/Throwable;)Ljava/lang/Throwable;
    //   3513: athrow
    //   3514: aload #35
    //   3516: astore #7
    //   3518: getstatic burp/Zktq.Zc : Ljava/lang/String;
    //   3521: getstatic burp/Zkdq.ZG : Ljava/lang/Object;
    //   3524: checkcast java/math/BigInteger
    //   3527: invokevirtual intValue : ()I
    //   3530: bipush #32
    //   3532: irem
    //   3533: invokestatic abs : (I)I
    //   3536: invokevirtual charAt : (I)C
    //   3539: getstatic burp/Zrm4.ZK : Ljava/lang/String;
    //   3542: getstatic burp/Zgre.ZD : Ljava/lang/Object;
    //   3545: checkcast java/math/BigInteger
    //   3548: invokevirtual intValue : ()I
    //   3551: bipush #32
    //   3553: irem
    //   3554: invokestatic abs : (I)I
    //   3557: invokevirtual charAt : (I)C
    //   3560: if_icmpgt -> 3667
    //   3563: getstatic burp/Zgw0.ZL : Ljava/lang/String;
    //   3566: getstatic burp/Zkw.ZY : Ljava/lang/Object;
    //   3569: checkcast java/math/BigInteger
    //   3572: invokevirtual intValue : ()I
    //   3575: bipush #32
    //   3577: irem
    //   3578: invokestatic abs : (I)I
    //   3581: invokevirtual charAt : (I)C
    //   3584: getstatic burp/Zxzp.ZH : Ljava/lang/String;
    //   3587: getstatic burp/Zk9s.ZY : Ljava/lang/Object;
    //   3590: checkcast java/math/BigInteger
    //   3593: invokevirtual intValue : ()I
    //   3596: bipush #32
    //   3598: irem
    //   3599: invokestatic abs : (I)I
    //   3602: invokevirtual charAt : (I)C
    //   3605: if_icmpgt -> 3667
    //   3608: goto -> 3615
    //   3611: invokestatic a : (Ljava/lang/Throwable;)Ljava/lang/Throwable;
    //   3614: athrow
    //   3615: getstatic burp/Zryq.Zb : Ljava/lang/String;
    //   3618: getstatic burp/Zs8s.ZG : Ljava/lang/Object;
    //   3621: checkcast java/math/BigInteger
    //   3624: invokevirtual intValue : ()I
    //   3627: bipush #32
    //   3629: irem
    //   3630: invokestatic abs : (I)I
    //   3633: invokevirtual charAt : (I)C
    //   3636: getstatic burp/Zzxa.Zl : Ljava/lang/String;
    //   3639: getstatic burp/Zzlg.Z_ : Ljava/lang/Object;
    //   3642: checkcast java/math/BigInteger
    //   3645: invokevirtual intValue : ()I
    //   3648: bipush #32
    //   3650: irem
    //   3651: invokestatic abs : (I)I
    //   3654: invokevirtual charAt : (I)C
    //   3657: if_icmpgt -> 3675
    //   3660: goto -> 3667
    //   3663: invokestatic a : (Ljava/lang/Throwable;)Ljava/lang/Throwable;
    //   3666: athrow
    //   3667: iconst_1
    //   3668: goto -> 3676
    //   3671: invokestatic a : (Ljava/lang/Throwable;)Ljava/lang/Throwable;
    //   3674: athrow
    //   3675: iconst_0
    //   3676: ireturn
    //   3677: astore_3
    //   3678: new java/lang/Exception
    //   3681: dup
    //   3682: aload_3
    //   3683: invokevirtual getMessage : ()Ljava/lang/String;
    //   3686: invokespecial <init> : (Ljava/lang/String;)V
    //   3689: athrow
    // Exception table:
    //   from	to	target	type
    //   4	3676	3677	java/lang/Throwable
    //   64	78	78	java/lang/Throwable
    //   89	102	105	java/lang/Throwable
    //   94	117	120	java/lang/Throwable
    //   109	135	138	java/lang/Throwable
    //   124	165	168	java/lang/Throwable
    //   228	255	258	java/lang/Throwable
    //   245	273	276	java/lang/Throwable
    //   262	309	312	java/lang/Throwable
    //   280	323	326	java/lang/Throwable
    //   372	386	386	java/lang/Throwable
    //   397	410	413	java/lang/Throwable
    //   402	425	428	java/lang/Throwable
    //   417	443	446	java/lang/Throwable
    //   432	473	476	java/lang/Throwable
    //   536	563	566	java/lang/Throwable
    //   553	584	587	java/lang/Throwable
    //   570	614	617	java/lang/Throwable
    //   591	625	625	java/lang/Throwable
    //   636	652	655	java/lang/Throwable
    //   729	743	743	java/lang/Throwable
    //   754	767	770	java/lang/Throwable
    //   759	782	785	java/lang/Throwable
    //   774	800	803	java/lang/Throwable
    //   789	830	833	java/lang/Throwable
    //   893	920	923	java/lang/Throwable
    //   910	941	944	java/lang/Throwable
    //   927	971	974	java/lang/Throwable
    //   948	982	982	java/lang/Throwable
    //   993	1009	1012	java/lang/Throwable
    //   1161	1176	1176	java/lang/Throwable
    //   2178	2204	2204	java/lang/Throwable
    //   2285	2300	2300	java/lang/Throwable
    //   3482	3507	3510	java/lang/Throwable
    //   3518	3608	3611	java/lang/Throwable
    //   3563	3660	3663	java/lang/Throwable
    //   3615	3671	3671	java/lang/Throwable
  }
  
  static void Zu(Object paramObject) {
    Zls_.Zn = a(-13792, -24200);
    Zls_.ZR = new BigInteger(a(-13784, -28695));
    boolean bool = Zt2e.ZK();
    try {
      try {
        if (Zlno.ZM.charAt(Math.abs(((BigInteger)Zg97.Zc).intValue() % 32)) > Zkvr.Zm.charAt(Math.abs(((BigInteger)Zr3x.Zb).intValue() % 32))) {
          try {
            Zg97.Zw(Class.forName(a(-13782, -10171)));
            if (bool)
              Zzgh.ZA(Class.forName(a(-13779, 29752))); 
          } catch (Throwable throwable) {
            throw a(null);
          } 
          return;
        } 
      } catch (Throwable throwable) {
        throw a(null);
      } 
      Zzgh.ZA(Class.forName(a(-13779, 29752)));
    } catch (Throwable throwable) {}
  }
  
  static {
    // Byte code:
    //   0: bipush #16
    //   2: anewarray java/lang/String
    //   5: astore #5
    //   7: iconst_0
    //   8: istore_3
    //   9: ldc '\\t&I??\\t5\\r\\tl 0j_[H\\f|5\\t3 \\t9z (k&k8V!\\nGG\\t5M BaFH'*?b;m@W[f^V kh??\\t"kc<u?\\t=smA\\t+)+9Q'
    //   11: dup
    //   12: astore_2
    //   13: invokevirtual length : ()I
    //   16: istore #4
    //   18: iconst_4
    //   19: istore_1
    //   20: iconst_m1
    //   21: istore_0
    //   22: bipush #10
    //   24: iinc #0, 1
    //   27: aload_2
    //   28: iload_0
    //   29: dup
    //   30: iload_1
    //   31: iadd
    //   32: invokevirtual substring : (II)Ljava/lang/String;
    //   35: iconst_m1
    //   36: goto -> 142
    //   39: aload #5
    //   41: swap
    //   42: iload_3
    //   43: iinc #3, 1
    //   46: swap
    //   47: aastore
    //   48: iload_0
    //   49: iload_1
    //   50: iadd
    //   51: dup
    //   52: istore_0
    //   53: iload #4
    //   55: if_icmpge -> 67
    //   58: aload_2
    //   59: iload_0
    //   60: invokevirtual charAt : (I)C
    //   63: istore_1
    //   64: goto -> 22
    //   67: ldc '\\bN\?odYQ%W\\tN!0(Z;4|hY;YCD\p$x\\tb6HSV'
    //   69: dup
    //   70: astore_2
    //   71: invokevirtual length : ()I
    //   74: istore #4
    //   76: bipush #77
    //   78: istore_1
    //   79: iconst_m1
    //   80: istore_0
    //   81: bipush #72
    //   83: iinc #0, 1
    //   86: aload_2
    //   87: iload_0
    //   88: dup
    //   89: iload_1
    //   90: iadd
    //   91: invokevirtual substring : (II)Ljava/lang/String;
    //   94: iconst_0
    //   95: goto -> 142
    //   98: aload #5
    //   100: swap
    //   101: iload_3
    //   102: iinc #3, 1
    //   105: swap
    //   106: aastore
    //   107: iload_0
    //   108: iload_1
    //   109: iadd
    //   110: dup
    //   111: istore_0
    //   112: iload #4
    //   114: if_icmpge -> 126
    //   117: aload_2
    //   118: iload_0
    //   119: invokevirtual charAt : (I)C
    //   122: istore_1
    //   123: goto -> 81
    //   126: aload #5
    //   128: putstatic burp/Zmt6.a : [Ljava/lang/String;
    //   131: bipush #16
    //   133: anewarray java/lang/String
    //   136: putstatic burp/Zmt6.b : [Ljava/lang/String;
    //   139: goto -> 300
    //   142: dup_x2
    //   143: pop
    //   144: invokevirtual toCharArray : ()[C
    //   147: dup_x1
    //   148: arraylength
    //   149: dup_x2
    //   150: pop
    //   151: iconst_0
    //   152: istore #6
    //   154: dup2_x1
    //   155: pop2
    //   156: dup_x2
    //   157: iconst_1
    //   158: if_icmpgt -> 259
    //   161: dup2
    //   162: swap
    //   163: iload #6
    //   165: dup2_x1
    //   166: caload
    //   167: swap
    //   168: iload #6
    //   170: bipush #7
    //   172: irem
    //   173: tableswitch default -> 241, 0 -> 212, 1 -> 217, 2 -> 222, 3 -> 227, 4 -> 231, 5 -> 236
    //   212: bipush #71
    //   214: goto -> 243
    //   217: bipush #66
    //   219: goto -> 243
    //   222: bipush #67
    //   224: goto -> 243
    //   227: iconst_3
    //   228: goto -> 243
    //   231: bipush #63
    //   233: goto -> 243
    //   236: bipush #42
    //   238: goto -> 243
    //   241: bipush #112
    //   243: ixor
    //   244: ixor
    //   245: i2c
    //   246: castore
    //   247: iinc #6, 1
    //   250: dup
    //   251: ifne -> 259
    //   254: dup2
    //   255: dup_x1
    //   256: goto -> 165
    //   259: dup2_x1
    //   260: pop2
    //   261: dup_x2
    //   262: iload #6
    //   264: if_icmpgt -> 161
    //   267: pop
    //   268: new java/lang/String
    //   271: dup_x1
    //   272: swap
    //   273: invokespecial <init> : ([C)V
    //   276: invokevirtual intern : ()Ljava/lang/String;
    //   279: swap
    //   280: pop
    //   281: swap
    //   282: tableswitch default -> 39, 0 -> 98
    //   300: new java/math/BigInteger
    //   303: dup
    //   304: bipush #32
    //   306: newarray byte
    //   308: dup
    //   309: iconst_0
    //   310: bipush #45
    //   312: bastore
    //   313: dup
    //   314: iconst_1
    //   315: bipush #-62
    //   317: bastore
    //   318: dup
    //   319: iconst_2
    //   320: bipush #-120
    //   322: bastore
    //   323: dup
    //   324: iconst_3
    //   325: bipush #-120
    //   327: bastore
    //   328: dup
    //   329: iconst_4
    //   330: bipush #20
    //   332: bastore
    //   333: dup
    //   334: iconst_5
    //   335: bipush #48
    //   337: bastore
    //   338: dup
    //   339: bipush #6
    //   341: bipush #-103
    //   343: bastore
    //   344: dup
    //   345: bipush #7
    //   347: bipush #32
    //   349: bastore
    //   350: dup
    //   351: bipush #8
    //   353: bipush #-77
    //   355: bastore
    //   356: dup
    //   357: bipush #9
    //   359: bipush #-36
    //   361: bastore
    //   362: dup
    //   363: bipush #10
    //   365: bipush #24
    //   367: bastore
    //   368: dup
    //   369: bipush #11
    //   371: bipush #123
    //   373: bastore
    //   374: dup
    //   375: bipush #12
    //   377: bipush #-73
    //   379: bastore
    //   380: dup
    //   381: bipush #13
    //   383: bipush #-103
    //   385: bastore
    //   386: dup
    //   387: bipush #14
    //   389: iconst_2
    //   390: bastore
    //   391: dup
    //   392: bipush #15
    //   394: bipush #-16
    //   396: bastore
    //   397: dup
    //   398: bipush #16
    //   400: bipush #17
    //   402: bastore
    //   403: dup
    //   404: bipush #17
    //   406: bipush #38
    //   408: bastore
    //   409: dup
    //   410: bipush #18
    //   412: iconst_1
    //   413: bastore
    //   414: dup
    //   415: bipush #19
    //   417: bipush #-88
    //   419: bastore
    //   420: dup
    //   421: bipush #20
    //   423: bipush #120
    //   425: bastore
    //   426: dup
    //   427: bipush #21
    //   429: bipush #-14
    //   431: bastore
    //   432: dup
    //   433: bipush #22
    //   435: bipush #27
    //   437: bastore
    //   438: dup
    //   439: bipush #23
    //   441: bipush #-127
    //   443: bastore
    //   444: dup
    //   445: bipush #24
    //   447: bipush #40
    //   449: bastore
    //   450: dup
    //   451: bipush #25
    //   453: bipush #-68
    //   455: bastore
    //   456: dup
    //   457: bipush #26
    //   459: bipush #-55
    //   461: bastore
    //   462: dup
    //   463: bipush #27
    //   465: bipush #32
    //   467: bastore
    //   468: dup
    //   469: bipush #28
    //   471: bipush #49
    //   473: bastore
    //   474: dup
    //   475: bipush #29
    //   477: bipush #14
    //   479: bastore
    //   480: dup
    //   481: bipush #30
    //   483: bipush #-29
    //   485: bastore
    //   486: dup
    //   487: bipush #31
    //   489: bipush #-47
    //   491: bastore
    //   492: invokespecial <init> : ([B)V
    //   495: putstatic burp/Zmt6.ZK : Ljava/lang/Object;
    //   498: sipush #-13778
    //   501: sipush #-23556
    //   504: invokestatic a : (II)Ljava/lang/String;
    //   507: putstatic burp/Zmt6.Zx : Ljava/lang/String;
    //   510: return
  }
  
  private static Throwable a(Throwable paramThrowable) {
    return paramThrowable;
  }
  
  private static String a(int paramInt1, int paramInt2) {
    int i = (paramInt1 ^ 0xFFFFCA26) & 0xFFFF;
    if (b[i] == null) {
      char[] arrayOfChar = a[i].toCharArray();
      switch (arrayOfChar[0] & 0xFF) {
        case 0:
        
        case 1:
        
        case 2:
        
        case 3:
        
        case 4:
        
        case 5:
        
        case 6:
        
        case 7:
        
        case 8:
        
        case 9:
        
        case 10:
        
        case 11:
        
        case 12:
        
        case 13:
        
        case 14:
        
        case 15:
        
        case 16:
        
        case 17:
        
        case 18:
        
        case 19:
        
        case 20:
        
        case 21:
        
        case 22:
        
        case 23:
        
        case 24:
        
        case 25:
        
        case 26:
        
        case 27:
        
        case 28:
        
        case 29:
        
        case 30:
        
        case 31:
        
        case 32:
        
        case 33:
        
        case 34:
        
        case 35:
        
        case 36:
        
        case 37:
        
        case 38:
        
        case 39:
        
        case 40:
        
        case 41:
        
        case 42:
        
        case 43:
        
        case 44:
        
        case 45:
        
        case 46:
        
        case 47:
        
        case 48:
        
        case 49:
        
        case 50:
        
        case 51:
        
        case 52:
        
        case 53:
        
        case 54:
        
        case 55:
        
        case 56:
        
        case 57:
        
        case 58:
        
        case 59:
        
        case 60:
        
        case 61:
        
        case 62:
        
        case 63:
        
        case 64:
        
        case 65:
        
        case 66:
        
        case 67:
        
        case 68:
        
        case 69:
        
        case 70:
        
        case 71:
        
        case 72:
        
        case 73:
        
        case 74:
        
        case 75:
        
        case 76:
        
        case 77:
        
        case 78:
        
        case 79:
        
        case 80:
        
        case 81:
        
        case 82:
        
        case 83:
        
        case 84:
        
        case 85:
        
        case 86:
        
        case 87:
        
        case 88:
        
        case 89:
        
        case 90:
        
        case 91:
        
        case 92:
        
        case 93:
        
        case 94:
        
        case 95:
        
        case 96:
        
        case 97:
        
        case 98:
        
        case 99:
        
        case 100:
        
        case 101:
        
        case 102:
        
        case 103:
        
        case 104:
        
        case 105:
        
        case 106:
        
        case 107:
        
        case 108:
        
        case 109:
        
        case 110:
        
        case 111:
        
        case 112:
        
        case 113:
        
        case 114:
        
        case 115:
        
        case 116:
        
        case 117:
        
        case 118:
        
        case 119:
        
        case 120:
        
        case 121:
        
        case 122:
        
        case 123:
        
        case 124:
        
        case 125:
        
        case 126:
        
        case 127:
        
        case 128:
        
        case 129:
        
        case 130:
        
        case 131:
        
        case 132:
        
        case 133:
        
        case 134:
        
        case 135:
        
        case 136:
        
        case 137:
        
        case 138:
        
        case 139:
        
        case 140:
        
        case 141:
        
        case 142:
        
        case 143:
        
        case 144:
        
        case 145:
        
        case 146:
        
        case 147:
        
        case 148:
        
        case 149:
        
        case 150:
        
        case 151:
        
        case 152:
        
        case 153:
        
        case 154:
        
        case 155:
        
        case 156:
        
        case 157:
        
        case 158:
        
        case 159:
        
        case 160:
        
        case 161:
        
        case 162:
        
        case 163:
        
        case 164:
        
        case 165:
        
        case 166:
        
        case 167:
        
        case 168:
        
        case 169:
        
        case 170:
        
        case 171:
        
        case 172:
        
        case 173:
        
        case 174:
        
        case 175:
        
        case 176:
        
        case 177:
        
        case 178:
        
        case 179:
        
        case 180:
        
        case 181:
        
        case 182:
        
        case 183:
        
        case 184:
        
        case 185:
        
        case 186:
        
        case 187:
        
        case 188:
        
        case 189:
        
        case 190:
        
        case 191:
        
        case 192:
        
        case 193:
        
        case 194:
        
        case 195:
        
        case 196:
        
        case 197:
        
        case 198:
        
        case 199:
        
        case 200:
        
        case 201:
        
        case 202:
        
        case 203:
        
        case 204:
        
        case 205:
        
        case 206:
        
        case 207:
        
        case 208:
        
        case 209:
        
        case 210:
        
        case 211:
        
        case 212:
        
        case 213:
        
        case 214:
        
        case 215:
        
        case 216:
        
        case 217:
        
        case 218:
        
        case 219:
        
        case 220:
        
        case 221:
        
        case 222:
        
        case 223:
        
        case 224:
        
        case 225:
        
        case 226:
        
        case 227:
        
        case 228:
        
        case 229:
        
        case 230:
        
        case 231:
        
        case 232:
        
        case 233:
        
        case 234:
        
        case 235:
        
        case 236:
        
        case 237:
        
        case 238:
        
        case 239:
        
        case 240:
        
        case 241:
        
        case 242:
        
        case 243:
        
        case 244:
        
        case 245:
        
        case 246:
        
        case 247:
        
        case 248:
        
        case 249:
        
        case 250:
        
        case 251:
        
        case 252:
        
        case 253:
        
        case 254:
        
        default:
          break;
      } 
      char c = '';
      int j = (paramInt2 & 0xFF) - c;
      if (j < 0)
        j += 256; 
      int k = ((paramInt2 & 0xFFFF) >>> 8) - c;
      if (k < 0)
        k += 256; 
      for (byte b = 0; b < arrayOfChar.length; b++) {
        int m = b % 2;
        if (m == 0) {
          arrayOfChar[b] = (char)(arrayOfChar[b] ^ j);
          j = ((j >>> 3 | j << 5) ^ arrayOfChar[b]) & 0xFF;
        } else {
          arrayOfChar[b] = (char)(arrayOfChar[b] ^ k);
          k = ((k >>> 3 | k << 5) ^ arrayOfChar[b]) & 0xFF;
        } 
      } 
      b[i] = (new String(arrayOfChar)).intern();
    } 
    return b[i];
  }
}


/* Location:              C:\Program Files\BurpSuitePro\burpsuite_pro.jar!\burp\Zmt6.class
 * Java compiler version: 21 (65.0)
 * JD-Core Version:       1.1.3
 */