package burp;

import java.math.BigInteger;

class Zmt7 extends ClassLoader {
  static Object Z_;
  
  static String Zl;
  
  private static final String[] a;
  
  private static final String[] b;
  
  static void ZD(Object paramObject) {
    Zzs9.Zg = a(26856, 28939);
    Zzs9.ZO = new BigInteger(a(26862, -29711));
    boolean bool = Zt2e.ZN();
    try {
      try {
        if (Zrs0.Zt.charAt(Math.abs(((BigInteger)Zrs0.Zz).intValue() % 32)) > Zb9h.Zf.charAt(Math.abs(((BigInteger)Zlav.Zp).intValue() % 32))) {
          try {
            Zmdm.Za(Class.forName(a(26851, 12506)));
            if (!bool)
              Zx_x.Zm(Class.forName(a(26861, -10015))); 
          } catch (Throwable throwable) {
            throw a(null);
          } 
          return;
        } 
      } catch (Throwable throwable) {
        throw a(null);
      } 
      Zx_x.Zm(Class.forName(a(26861, -10015)));
    } catch (Throwable throwable) {}
  }
  
  static void ZR(Object[] paramArrayOfObject, Object paramObject) throws Throwable {}
  
  static boolean Zl(Object[] paramArrayOfObject, Object paramObject) throws Throwable {
    // Byte code:
    //   0: invokestatic ZN : ()Z
    //   3: istore_2
    //   4: getstatic burp/Zeb3.Zb : Ljava/lang/Object;
    //   7: checkcast java/math/BigInteger
    //   10: getstatic burp/Zz3w.ZX : Ljava/lang/Object;
    //   13: checkcast java/math/BigInteger
    //   16: invokevirtual subtract : (Ljava/math/BigInteger;)Ljava/math/BigInteger;
    //   19: putstatic burp/Zrod.ZX : Ljava/lang/Object;
    //   22: sipush #26863
    //   25: sipush #-11014
    //   28: invokestatic a : (II)Ljava/lang/String;
    //   31: iconst_1
    //   32: ldc burp/Zl4v
    //   34: invokevirtual getClassLoader : ()Ljava/lang/ClassLoader;
    //   37: invokestatic forName : (Ljava/lang/String;ZLjava/lang/ClassLoader;)Ljava/lang/Class;
    //   40: invokevirtual getDeclaredFields : ()[Ljava/lang/reflect/Field;
    //   43: astore_3
    //   44: aload_3
    //   45: arraylength
    //   46: istore #4
    //   48: iconst_0
    //   49: istore #5
    //   51: iload #5
    //   53: iload #4
    //   55: if_icmpge -> 192
    //   58: aload_3
    //   59: iload #5
    //   61: aaload
    //   62: astore #6
    //   64: aload #6
    //   66: invokevirtual getModifiers : ()I
    //   69: invokestatic isStatic : (I)Z
    //   72: ifne -> 82
    //   75: goto -> 185
    //   78: invokestatic a : (Ljava/lang/Throwable;)Ljava/lang/Throwable;
    //   81: athrow
    //   82: aload #6
    //   84: invokevirtual getType : ()Ljava/lang/Class;
    //   87: astore #7
    //   89: aload #7
    //   91: ifnull -> 172
    //   94: aload #7
    //   96: invokevirtual isPrimitive : ()Z
    //   99: ifne -> 172
    //   102: goto -> 109
    //   105: invokestatic a : (Ljava/lang/Throwable;)Ljava/lang/Throwable;
    //   108: athrow
    //   109: aload #7
    //   111: invokevirtual getPackage : ()Ljava/lang/Package;
    //   114: ifnull -> 172
    //   117: goto -> 124
    //   120: invokestatic a : (Ljava/lang/Throwable;)Ljava/lang/Throwable;
    //   123: athrow
    //   124: aload #7
    //   126: invokevirtual getPackage : ()Ljava/lang/Package;
    //   129: invokevirtual getName : ()Ljava/lang/String;
    //   132: ifnull -> 172
    //   135: goto -> 142
    //   138: invokestatic a : (Ljava/lang/Throwable;)Ljava/lang/Throwable;
    //   141: athrow
    //   142: aload #7
    //   144: invokevirtual getPackage : ()Ljava/lang/Package;
    //   147: invokevirtual getName : ()Ljava/lang/String;
    //   150: sipush #26858
    //   153: sipush #-1977
    //   156: invokestatic a : (II)Ljava/lang/String;
    //   159: invokevirtual startsWith : (Ljava/lang/String;)Z
    //   162: ifne -> 172
    //   165: goto -> 172
    //   168: invokestatic a : (Ljava/lang/Throwable;)Ljava/lang/Throwable;
    //   171: athrow
    //   172: aload #6
    //   174: iconst_1
    //   175: invokevirtual setAccessible : (Z)V
    //   178: aload #6
    //   180: aconst_null
    //   181: invokevirtual get : (Ljava/lang/Object;)Ljava/lang/Object;
    //   184: pop
    //   185: iinc #5, 1
    //   188: iload_2
    //   189: ifne -> 51
    //   192: sipush #26859
    //   195: sipush #20836
    //   198: invokestatic a : (II)Ljava/lang/String;
    //   201: invokestatic forName : (Ljava/lang/String;)Ljava/lang/Class;
    //   204: invokevirtual getDeclaredMethods : ()[Ljava/lang/reflect/Method;
    //   207: astore_3
    //   208: aload_3
    //   209: arraylength
    //   210: istore #4
    //   212: iconst_0
    //   213: istore #5
    //   215: iload #5
    //   217: iload #4
    //   219: if_icmpge -> 351
    //   222: aload_3
    //   223: iload #5
    //   225: aaload
    //   226: astore #6
    //   228: aload #6
    //   230: invokevirtual getParameterTypes : ()[Ljava/lang/Class;
    //   233: pop
    //   234: aload #6
    //   236: invokevirtual getModifiers : ()I
    //   239: invokestatic isStatic : (I)Z
    //   242: ifeq -> 337
    //   245: aload #6
    //   247: invokevirtual getParameterTypes : ()[Ljava/lang/Class;
    //   250: arraylength
    //   251: iconst_2
    //   252: if_icmpne -> 337
    //   255: goto -> 262
    //   258: invokestatic a : (Ljava/lang/Throwable;)Ljava/lang/Throwable;
    //   261: athrow
    //   262: aload #6
    //   264: invokevirtual getReturnType : ()Ljava/lang/Class;
    //   267: getstatic java/lang/Void.TYPE : Ljava/lang/Class;
    //   270: invokevirtual equals : (Ljava/lang/Object;)Z
    //   273: ifeq -> 337
    //   276: goto -> 283
    //   279: invokestatic a : (Ljava/lang/Throwable;)Ljava/lang/Throwable;
    //   282: athrow
    //   283: aload #6
    //   285: iconst_1
    //   286: invokevirtual setAccessible : (Z)V
    //   289: aload #6
    //   291: aconst_null
    //   292: iconst_2
    //   293: anewarray java/lang/Object
    //   296: dup
    //   297: iconst_0
    //   298: aload_0
    //   299: aastore
    //   300: dup
    //   301: iconst_1
    //   302: aload_1
    //   303: ifnonnull -> 321
    //   306: goto -> 313
    //   309: invokestatic a : (Ljava/lang/Throwable;)Ljava/lang/Throwable;
    //   312: athrow
    //   313: aload_1
    //   314: goto -> 328
    //   317: invokestatic a : (Ljava/lang/Throwable;)Ljava/lang/Throwable;
    //   320: athrow
    //   321: aload_1
    //   322: checkcast [B
    //   325: invokevirtual clone : ()Ljava/lang/Object;
    //   328: aastore
    //   329: invokevirtual invoke : (Ljava/lang/Object;[Ljava/lang/Object;)Ljava/lang/Object;
    //   332: pop
    //   333: iload_2
    //   334: ifne -> 351
    //   337: iinc #5, 1
    //   340: iload_2
    //   341: ifne -> 215
    //   344: goto -> 351
    //   347: invokestatic a : (Ljava/lang/Throwable;)Ljava/lang/Throwable;
    //   350: athrow
    //   351: getstatic burp/Zlnq.ZO : Ljava/lang/Object;
    //   354: checkcast java/math/BigInteger
    //   357: invokevirtual toByteArray : ()[B
    //   360: astore_3
    //   361: bipush #32
    //   363: newarray int
    //   365: dup
    //   366: iconst_0
    //   367: ldc 876216579
    //   369: iastore
    //   370: dup
    //   371: iconst_1
    //   372: ldc 455999525
    //   374: iastore
    //   375: dup
    //   376: iconst_2
    //   377: ldc 1043334948
    //   379: iastore
    //   380: dup
    //   381: iconst_3
    //   382: ldc 439222784
    //   384: iastore
    //   385: dup
    //   386: iconst_4
    //   387: ldc 372376604
    //   389: iastore
    //   390: dup
    //   391: iconst_5
    //   392: ldc 707731490
    //   394: iastore
    //   395: dup
    //   396: bipush #6
    //   398: ldc 389426184
    //   400: iastore
    //   401: dup
    //   402: bipush #7
    //   404: ldc 973875457
    //   406: iastore
    //   407: dup
    //   408: bipush #8
    //   410: ldc 389160971
    //   412: iastore
    //   413: dup
    //   414: bipush #9
    //   416: ldc 907870729
    //   418: iastore
    //   419: dup
    //   420: bipush #10
    //   422: ldc 121057538
    //   424: iastore
    //   425: dup
    //   426: bipush #11
    //   428: ldc 840500228
    //   430: iastore
    //   431: dup
    //   432: bipush #12
    //   434: ldc 254150144
    //   436: iastore
    //   437: dup
    //   438: bipush #13
    //   440: ldc 924386310
    //   442: iastore
    //   443: dup
    //   444: bipush #14
    //   446: ldc 187632156
    //   448: iastore
    //   449: dup
    //   450: bipush #15
    //   452: ldc 874189824
    //   454: iastore
    //   455: dup
    //   456: bipush #16
    //   458: ldc 655302664
    //   460: iastore
    //   461: dup
    //   462: bipush #17
    //   464: ldc 890966315
    //   466: iastore
    //   467: dup
    //   468: bipush #18
    //   470: ldc 722417666
    //   472: iastore
    //   473: dup
    //   474: bipush #19
    //   476: ldc 1026621720
    //   478: iastore
    //   479: dup
    //   480: bipush #20
    //   482: ldc 957157408
    //   484: iastore
    //   485: dup
    //   486: bipush #21
    //   488: ldc 892536332
    //   490: iastore
    //   491: dup
    //   492: bipush #22
    //   494: ldc 689771012
    //   496: iastore
    //   497: dup
    //   498: bipush #23
    //   500: ldc 221709344
    //   502: iastore
    //   503: dup
    //   504: bipush #24
    //   506: ldc 940377620
    //   508: iastore
    //   509: dup
    //   510: bipush #25
    //   512: ldc 255209728
    //   514: iastore
    //   515: dup
    //   516: bipush #26
    //   518: ldc 1010368540
    //   520: iastore
    //   521: dup
    //   522: bipush #27
    //   524: ldc 220604441
    //   526: iastore
    //   527: dup
    //   528: bipush #28
    //   530: ldc 1008414755
    //   532: iastore
    //   533: dup
    //   534: bipush #29
    //   536: ldc 187049985
    //   538: iastore
    //   539: dup
    //   540: bipush #30
    //   542: ldc 943331329
    //   544: iastore
    //   545: dup
    //   546: bipush #31
    //   548: ldc 170788368
    //   550: iastore
    //   551: astore #5
    //   553: bipush #64
    //   555: newarray int
    //   557: dup
    //   558: iconst_0
    //   559: ldc 16843776
    //   561: iastore
    //   562: dup
    //   563: iconst_1
    //   564: iconst_0
    //   565: iastore
    //   566: dup
    //   567: iconst_2
    //   568: ldc 65536
    //   570: iastore
    //   571: dup
    //   572: iconst_3
    //   573: ldc 16843780
    //   575: iastore
    //   576: dup
    //   577: iconst_4
    //   578: ldc 16842756
    //   580: iastore
    //   581: dup
    //   582: iconst_5
    //   583: ldc 66564
    //   585: iastore
    //   586: dup
    //   587: bipush #6
    //   589: iconst_4
    //   590: iastore
    //   591: dup
    //   592: bipush #7
    //   594: ldc 65536
    //   596: iastore
    //   597: dup
    //   598: bipush #8
    //   600: sipush #1024
    //   603: iastore
    //   604: dup
    //   605: bipush #9
    //   607: ldc 16843776
    //   609: iastore
    //   610: dup
    //   611: bipush #10
    //   613: ldc 16843780
    //   615: iastore
    //   616: dup
    //   617: bipush #11
    //   619: sipush #1024
    //   622: iastore
    //   623: dup
    //   624: bipush #12
    //   626: ldc 16778244
    //   628: iastore
    //   629: dup
    //   630: bipush #13
    //   632: ldc 16842756
    //   634: iastore
    //   635: dup
    //   636: bipush #14
    //   638: ldc 16777216
    //   640: iastore
    //   641: dup
    //   642: bipush #15
    //   644: iconst_4
    //   645: iastore
    //   646: dup
    //   647: bipush #16
    //   649: sipush #1028
    //   652: iastore
    //   653: dup
    //   654: bipush #17
    //   656: ldc 16778240
    //   658: iastore
    //   659: dup
    //   660: bipush #18
    //   662: ldc 16778240
    //   664: iastore
    //   665: dup
    //   666: bipush #19
    //   668: ldc 66560
    //   670: iastore
    //   671: dup
    //   672: bipush #20
    //   674: ldc 66560
    //   676: iastore
    //   677: dup
    //   678: bipush #21
    //   680: ldc 16842752
    //   682: iastore
    //   683: dup
    //   684: bipush #22
    //   686: ldc 16842752
    //   688: iastore
    //   689: dup
    //   690: bipush #23
    //   692: ldc 16778244
    //   694: iastore
    //   695: dup
    //   696: bipush #24
    //   698: ldc 65540
    //   700: iastore
    //   701: dup
    //   702: bipush #25
    //   704: ldc 16777220
    //   706: iastore
    //   707: dup
    //   708: bipush #26
    //   710: ldc 16777220
    //   712: iastore
    //   713: dup
    //   714: bipush #27
    //   716: ldc 65540
    //   718: iastore
    //   719: dup
    //   720: bipush #28
    //   722: iconst_0
    //   723: iastore
    //   724: dup
    //   725: bipush #29
    //   727: sipush #1028
    //   730: iastore
    //   731: dup
    //   732: bipush #30
    //   734: ldc 66564
    //   736: iastore
    //   737: dup
    //   738: bipush #31
    //   740: ldc 16777216
    //   742: iastore
    //   743: dup
    //   744: bipush #32
    //   746: ldc 65536
    //   748: iastore
    //   749: dup
    //   750: bipush #33
    //   752: ldc 16843780
    //   754: iastore
    //   755: dup
    //   756: bipush #34
    //   758: iconst_4
    //   759: iastore
    //   760: dup
    //   761: bipush #35
    //   763: ldc 16842752
    //   765: iastore
    //   766: dup
    //   767: bipush #36
    //   769: ldc 16843776
    //   771: iastore
    //   772: dup
    //   773: bipush #37
    //   775: ldc 16777216
    //   777: iastore
    //   778: dup
    //   779: bipush #38
    //   781: ldc 16777216
    //   783: iastore
    //   784: dup
    //   785: bipush #39
    //   787: sipush #1024
    //   790: iastore
    //   791: dup
    //   792: bipush #40
    //   794: ldc 16842756
    //   796: iastore
    //   797: dup
    //   798: bipush #41
    //   800: ldc 65536
    //   802: iastore
    //   803: dup
    //   804: bipush #42
    //   806: ldc 66560
    //   808: iastore
    //   809: dup
    //   810: bipush #43
    //   812: ldc 16777220
    //   814: iastore
    //   815: dup
    //   816: bipush #44
    //   818: sipush #1024
    //   821: iastore
    //   822: dup
    //   823: bipush #45
    //   825: iconst_4
    //   826: iastore
    //   827: dup
    //   828: bipush #46
    //   830: ldc 16778244
    //   832: iastore
    //   833: dup
    //   834: bipush #47
    //   836: ldc 66564
    //   838: iastore
    //   839: dup
    //   840: bipush #48
    //   842: ldc 16843780
    //   844: iastore
    //   845: dup
    //   846: bipush #49
    //   848: ldc 65540
    //   850: iastore
    //   851: dup
    //   852: bipush #50
    //   854: ldc 16842752
    //   856: iastore
    //   857: dup
    //   858: bipush #51
    //   860: ldc 16778244
    //   862: iastore
    //   863: dup
    //   864: bipush #52
    //   866: ldc 16777220
    //   868: iastore
    //   869: dup
    //   870: bipush #53
    //   872: sipush #1028
    //   875: iastore
    //   876: dup
    //   877: bipush #54
    //   879: ldc 66564
    //   881: iastore
    //   882: dup
    //   883: bipush #55
    //   885: ldc 16843776
    //   887: iastore
    //   888: dup
    //   889: bipush #56
    //   891: sipush #1028
    //   894: iastore
    //   895: dup
    //   896: bipush #57
    //   898: ldc 16778240
    //   900: iastore
    //   901: dup
    //   902: bipush #58
    //   904: ldc 16778240
    //   906: iastore
    //   907: dup
    //   908: bipush #59
    //   910: iconst_0
    //   911: iastore
    //   912: dup
    //   913: bipush #60
    //   915: ldc 65540
    //   917: iastore
    //   918: dup
    //   919: bipush #61
    //   921: ldc 66560
    //   923: iastore
    //   924: dup
    //   925: bipush #62
    //   927: iconst_0
    //   928: iastore
    //   929: dup
    //   930: bipush #63
    //   932: ldc 16842756
    //   934: iastore
    //   935: astore #6
    //   937: bipush #64
    //   939: newarray int
    //   941: dup
    //   942: iconst_0
    //   943: ldc -2146402272
    //   945: iastore
    //   946: dup
    //   947: iconst_1
    //   948: ldc -2147450880
    //   950: iastore
    //   951: dup
    //   952: iconst_2
    //   953: ldc 32768
    //   955: iastore
    //   956: dup
    //   957: iconst_3
    //   958: ldc 1081376
    //   960: iastore
    //   961: dup
    //   962: iconst_4
    //   963: ldc 1048576
    //   965: iastore
    //   966: dup
    //   967: iconst_5
    //   968: bipush #32
    //   970: iastore
    //   971: dup
    //   972: bipush #6
    //   974: ldc -2146435040
    //   976: iastore
    //   977: dup
    //   978: bipush #7
    //   980: ldc -2147450848
    //   982: iastore
    //   983: dup
    //   984: bipush #8
    //   986: ldc -2147483616
    //   988: iastore
    //   989: dup
    //   990: bipush #9
    //   992: ldc -2146402272
    //   994: iastore
    //   995: dup
    //   996: bipush #10
    //   998: ldc -2146402304
    //   1000: iastore
    //   1001: dup
    //   1002: bipush #11
    //   1004: ldc -2147483648
    //   1006: iastore
    //   1007: dup
    //   1008: bipush #12
    //   1010: ldc -2147450880
    //   1012: iastore
    //   1013: dup
    //   1014: bipush #13
    //   1016: ldc 1048576
    //   1018: iastore
    //   1019: dup
    //   1020: bipush #14
    //   1022: bipush #32
    //   1024: iastore
    //   1025: dup
    //   1026: bipush #15
    //   1028: ldc -2146435040
    //   1030: iastore
    //   1031: dup
    //   1032: bipush #16
    //   1034: ldc 1081344
    //   1036: iastore
    //   1037: dup
    //   1038: bipush #17
    //   1040: ldc 1048608
    //   1042: iastore
    //   1043: dup
    //   1044: bipush #18
    //   1046: ldc -2147450848
    //   1048: iastore
    //   1049: dup
    //   1050: bipush #19
    //   1052: iconst_0
    //   1053: iastore
    //   1054: dup
    //   1055: bipush #20
    //   1057: ldc -2147483648
    //   1059: iastore
    //   1060: dup
    //   1061: bipush #21
    //   1063: ldc 32768
    //   1065: iastore
    //   1066: dup
    //   1067: bipush #22
    //   1069: ldc 1081376
    //   1071: iastore
    //   1072: dup
    //   1073: bipush #23
    //   1075: ldc -2146435072
    //   1077: iastore
    //   1078: dup
    //   1079: bipush #24
    //   1081: ldc 1048608
    //   1083: iastore
    //   1084: dup
    //   1085: bipush #25
    //   1087: ldc -2147483616
    //   1089: iastore
    //   1090: dup
    //   1091: bipush #26
    //   1093: iconst_0
    //   1094: iastore
    //   1095: dup
    //   1096: bipush #27
    //   1098: ldc 1081344
    //   1100: iastore
    //   1101: dup
    //   1102: bipush #28
    //   1104: ldc 32800
    //   1106: iastore
    //   1107: dup
    //   1108: bipush #29
    //   1110: ldc -2146402304
    //   1112: iastore
    //   1113: dup
    //   1114: bipush #30
    //   1116: ldc -2146435072
    //   1118: iastore
    //   1119: dup
    //   1120: bipush #31
    //   1122: ldc 32800
    //   1124: iastore
    //   1125: dup
    //   1126: bipush #32
    //   1128: iconst_0
    //   1129: iastore
    //   1130: dup
    //   1131: bipush #33
    //   1133: ldc 1081376
    //   1135: iastore
    //   1136: dup
    //   1137: bipush #34
    //   1139: ldc -2146435040
    //   1141: iastore
    //   1142: dup
    //   1143: bipush #35
    //   1145: ldc 1048576
    //   1147: iastore
    //   1148: dup
    //   1149: bipush #36
    //   1151: ldc -2147450848
    //   1153: iastore
    //   1154: dup
    //   1155: bipush #37
    //   1157: ldc -2146435072
    //   1159: iastore
    //   1160: dup
    //   1161: bipush #38
    //   1163: ldc -2146402304
    //   1165: iastore
    //   1166: dup
    //   1167: bipush #39
    //   1169: ldc 32768
    //   1171: iastore
    //   1172: dup
    //   1173: bipush #40
    //   1175: ldc -2146435072
    //   1177: iastore
    //   1178: dup
    //   1179: bipush #41
    //   1181: ldc -2147450880
    //   1183: iastore
    //   1184: dup
    //   1185: bipush #42
    //   1187: bipush #32
    //   1189: iastore
    //   1190: dup
    //   1191: bipush #43
    //   1193: ldc -2146402272
    //   1195: iastore
    //   1196: dup
    //   1197: bipush #44
    //   1199: ldc 1081376
    //   1201: iastore
    //   1202: dup
    //   1203: bipush #45
    //   1205: bipush #32
    //   1207: iastore
    //   1208: dup
    //   1209: bipush #46
    //   1211: ldc 32768
    //   1213: iastore
    //   1214: dup
    //   1215: bipush #47
    //   1217: ldc -2147483648
    //   1219: iastore
    //   1220: dup
    //   1221: bipush #48
    //   1223: ldc 32800
    //   1225: iastore
    //   1226: dup
    //   1227: bipush #49
    //   1229: ldc -2146402304
    //   1231: iastore
    //   1232: dup
    //   1233: bipush #50
    //   1235: ldc 1048576
    //   1237: iastore
    //   1238: dup
    //   1239: bipush #51
    //   1241: ldc -2147483616
    //   1243: iastore
    //   1244: dup
    //   1245: bipush #52
    //   1247: ldc 1048608
    //   1249: iastore
    //   1250: dup
    //   1251: bipush #53
    //   1253: ldc -2147450848
    //   1255: iastore
    //   1256: dup
    //   1257: bipush #54
    //   1259: ldc -2147483616
    //   1261: iastore
    //   1262: dup
    //   1263: bipush #55
    //   1265: ldc 1048608
    //   1267: iastore
    //   1268: dup
    //   1269: bipush #56
    //   1271: ldc 1081344
    //   1273: iastore
    //   1274: dup
    //   1275: bipush #57
    //   1277: iconst_0
    //   1278: iastore
    //   1279: dup
    //   1280: bipush #58
    //   1282: ldc -2147450880
    //   1284: iastore
    //   1285: dup
    //   1286: bipush #59
    //   1288: ldc 32800
    //   1290: iastore
    //   1291: dup
    //   1292: bipush #60
    //   1294: ldc -2147483648
    //   1296: iastore
    //   1297: dup
    //   1298: bipush #61
    //   1300: ldc -2146435040
    //   1302: iastore
    //   1303: dup
    //   1304: bipush #62
    //   1306: ldc -2146402272
    //   1308: iastore
    //   1309: dup
    //   1310: bipush #63
    //   1312: ldc 1081344
    //   1314: iastore
    //   1315: astore #7
    //   1317: bipush #64
    //   1319: newarray int
    //   1321: dup
    //   1322: iconst_0
    //   1323: sipush #520
    //   1326: iastore
    //   1327: dup
    //   1328: iconst_1
    //   1329: ldc 134349312
    //   1331: iastore
    //   1332: dup
    //   1333: iconst_2
    //   1334: iconst_0
    //   1335: iastore
    //   1336: dup
    //   1337: iconst_3
    //   1338: ldc 134348808
    //   1340: iastore
    //   1341: dup
    //   1342: iconst_4
    //   1343: ldc 134218240
    //   1345: iastore
    //   1346: dup
    //   1347: iconst_5
    //   1348: iconst_0
    //   1349: iastore
    //   1350: dup
    //   1351: bipush #6
    //   1353: ldc 131592
    //   1355: iastore
    //   1356: dup
    //   1357: bipush #7
    //   1359: ldc 134218240
    //   1361: iastore
    //   1362: dup
    //   1363: bipush #8
    //   1365: ldc 131080
    //   1367: iastore
    //   1368: dup
    //   1369: bipush #9
    //   1371: ldc 134217736
    //   1373: iastore
    //   1374: dup
    //   1375: bipush #10
    //   1377: ldc 134217736
    //   1379: iastore
    //   1380: dup
    //   1381: bipush #11
    //   1383: ldc 131072
    //   1385: iastore
    //   1386: dup
    //   1387: bipush #12
    //   1389: ldc 134349320
    //   1391: iastore
    //   1392: dup
    //   1393: bipush #13
    //   1395: ldc 131080
    //   1397: iastore
    //   1398: dup
    //   1399: bipush #14
    //   1401: ldc 134348800
    //   1403: iastore
    //   1404: dup
    //   1405: bipush #15
    //   1407: sipush #520
    //   1410: iastore
    //   1411: dup
    //   1412: bipush #16
    //   1414: ldc 134217728
    //   1416: iastore
    //   1417: dup
    //   1418: bipush #17
    //   1420: bipush #8
    //   1422: iastore
    //   1423: dup
    //   1424: bipush #18
    //   1426: ldc 134349312
    //   1428: iastore
    //   1429: dup
    //   1430: bipush #19
    //   1432: sipush #512
    //   1435: iastore
    //   1436: dup
    //   1437: bipush #20
    //   1439: ldc 131584
    //   1441: iastore
    //   1442: dup
    //   1443: bipush #21
    //   1445: ldc 134348800
    //   1447: iastore
    //   1448: dup
    //   1449: bipush #22
    //   1451: ldc 134348808
    //   1453: iastore
    //   1454: dup
    //   1455: bipush #23
    //   1457: ldc 131592
    //   1459: iastore
    //   1460: dup
    //   1461: bipush #24
    //   1463: ldc 134218248
    //   1465: iastore
    //   1466: dup
    //   1467: bipush #25
    //   1469: ldc 131584
    //   1471: iastore
    //   1472: dup
    //   1473: bipush #26
    //   1475: ldc 131072
    //   1477: iastore
    //   1478: dup
    //   1479: bipush #27
    //   1481: ldc 134218248
    //   1483: iastore
    //   1484: dup
    //   1485: bipush #28
    //   1487: bipush #8
    //   1489: iastore
    //   1490: dup
    //   1491: bipush #29
    //   1493: ldc 134349320
    //   1495: iastore
    //   1496: dup
    //   1497: bipush #30
    //   1499: sipush #512
    //   1502: iastore
    //   1503: dup
    //   1504: bipush #31
    //   1506: ldc 134217728
    //   1508: iastore
    //   1509: dup
    //   1510: bipush #32
    //   1512: ldc 134349312
    //   1514: iastore
    //   1515: dup
    //   1516: bipush #33
    //   1518: ldc 134217728
    //   1520: iastore
    //   1521: dup
    //   1522: bipush #34
    //   1524: ldc 131080
    //   1526: iastore
    //   1527: dup
    //   1528: bipush #35
    //   1530: sipush #520
    //   1533: iastore
    //   1534: dup
    //   1535: bipush #36
    //   1537: ldc 131072
    //   1539: iastore
    //   1540: dup
    //   1541: bipush #37
    //   1543: ldc 134349312
    //   1545: iastore
    //   1546: dup
    //   1547: bipush #38
    //   1549: ldc 134218240
    //   1551: iastore
    //   1552: dup
    //   1553: bipush #39
    //   1555: iconst_0
    //   1556: iastore
    //   1557: dup
    //   1558: bipush #40
    //   1560: sipush #512
    //   1563: iastore
    //   1564: dup
    //   1565: bipush #41
    //   1567: ldc 131080
    //   1569: iastore
    //   1570: dup
    //   1571: bipush #42
    //   1573: ldc 134349320
    //   1575: iastore
    //   1576: dup
    //   1577: bipush #43
    //   1579: ldc 134218240
    //   1581: iastore
    //   1582: dup
    //   1583: bipush #44
    //   1585: ldc 134217736
    //   1587: iastore
    //   1588: dup
    //   1589: bipush #45
    //   1591: sipush #512
    //   1594: iastore
    //   1595: dup
    //   1596: bipush #46
    //   1598: iconst_0
    //   1599: iastore
    //   1600: dup
    //   1601: bipush #47
    //   1603: ldc 134348808
    //   1605: iastore
    //   1606: dup
    //   1607: bipush #48
    //   1609: ldc 134218248
    //   1611: iastore
    //   1612: dup
    //   1613: bipush #49
    //   1615: ldc 131072
    //   1617: iastore
    //   1618: dup
    //   1619: bipush #50
    //   1621: ldc 134217728
    //   1623: iastore
    //   1624: dup
    //   1625: bipush #51
    //   1627: ldc 134349320
    //   1629: iastore
    //   1630: dup
    //   1631: bipush #52
    //   1633: bipush #8
    //   1635: iastore
    //   1636: dup
    //   1637: bipush #53
    //   1639: ldc 131592
    //   1641: iastore
    //   1642: dup
    //   1643: bipush #54
    //   1645: ldc 131584
    //   1647: iastore
    //   1648: dup
    //   1649: bipush #55
    //   1651: ldc 134217736
    //   1653: iastore
    //   1654: dup
    //   1655: bipush #56
    //   1657: ldc 134348800
    //   1659: iastore
    //   1660: dup
    //   1661: bipush #57
    //   1663: ldc 134218248
    //   1665: iastore
    //   1666: dup
    //   1667: bipush #58
    //   1669: sipush #520
    //   1672: iastore
    //   1673: dup
    //   1674: bipush #59
    //   1676: ldc 134348800
    //   1678: iastore
    //   1679: dup
    //   1680: bipush #60
    //   1682: ldc 131592
    //   1684: iastore
    //   1685: dup
    //   1686: bipush #61
    //   1688: bipush #8
    //   1690: iastore
    //   1691: dup
    //   1692: bipush #62
    //   1694: ldc 134348808
    //   1696: iastore
    //   1697: dup
    //   1698: bipush #63
    //   1700: ldc 131584
    //   1702: iastore
    //   1703: astore #8
    //   1705: bipush #64
    //   1707: newarray int
    //   1709: dup
    //   1710: iconst_0
    //   1711: ldc 8396801
    //   1713: iastore
    //   1714: dup
    //   1715: iconst_1
    //   1716: sipush #8321
    //   1719: iastore
    //   1720: dup
    //   1721: iconst_2
    //   1722: sipush #8321
    //   1725: iastore
    //   1726: dup
    //   1727: iconst_3
    //   1728: sipush #128
    //   1731: iastore
    //   1732: dup
    //   1733: iconst_4
    //   1734: ldc 8396928
    //   1736: iastore
    //   1737: dup
    //   1738: iconst_5
    //   1739: ldc 8388737
    //   1741: iastore
    //   1742: dup
    //   1743: bipush #6
    //   1745: ldc 8388609
    //   1747: iastore
    //   1748: dup
    //   1749: bipush #7
    //   1751: sipush #8193
    //   1754: iastore
    //   1755: dup
    //   1756: bipush #8
    //   1758: iconst_0
    //   1759: iastore
    //   1760: dup
    //   1761: bipush #9
    //   1763: ldc 8396800
    //   1765: iastore
    //   1766: dup
    //   1767: bipush #10
    //   1769: ldc 8396800
    //   1771: iastore
    //   1772: dup
    //   1773: bipush #11
    //   1775: ldc 8396929
    //   1777: iastore
    //   1778: dup
    //   1779: bipush #12
    //   1781: sipush #129
    //   1784: iastore
    //   1785: dup
    //   1786: bipush #13
    //   1788: iconst_0
    //   1789: iastore
    //   1790: dup
    //   1791: bipush #14
    //   1793: ldc 8388736
    //   1795: iastore
    //   1796: dup
    //   1797: bipush #15
    //   1799: ldc 8388609
    //   1801: iastore
    //   1802: dup
    //   1803: bipush #16
    //   1805: iconst_1
    //   1806: iastore
    //   1807: dup
    //   1808: bipush #17
    //   1810: sipush #8192
    //   1813: iastore
    //   1814: dup
    //   1815: bipush #18
    //   1817: ldc 8388608
    //   1819: iastore
    //   1820: dup
    //   1821: bipush #19
    //   1823: ldc 8396801
    //   1825: iastore
    //   1826: dup
    //   1827: bipush #20
    //   1829: sipush #128
    //   1832: iastore
    //   1833: dup
    //   1834: bipush #21
    //   1836: ldc 8388608
    //   1838: iastore
    //   1839: dup
    //   1840: bipush #22
    //   1842: sipush #8193
    //   1845: iastore
    //   1846: dup
    //   1847: bipush #23
    //   1849: sipush #8320
    //   1852: iastore
    //   1853: dup
    //   1854: bipush #24
    //   1856: ldc 8388737
    //   1858: iastore
    //   1859: dup
    //   1860: bipush #25
    //   1862: iconst_1
    //   1863: iastore
    //   1864: dup
    //   1865: bipush #26
    //   1867: sipush #8320
    //   1870: iastore
    //   1871: dup
    //   1872: bipush #27
    //   1874: ldc 8388736
    //   1876: iastore
    //   1877: dup
    //   1878: bipush #28
    //   1880: sipush #8192
    //   1883: iastore
    //   1884: dup
    //   1885: bipush #29
    //   1887: ldc 8396928
    //   1889: iastore
    //   1890: dup
    //   1891: bipush #30
    //   1893: ldc 8396929
    //   1895: iastore
    //   1896: dup
    //   1897: bipush #31
    //   1899: sipush #129
    //   1902: iastore
    //   1903: dup
    //   1904: bipush #32
    //   1906: ldc 8388736
    //   1908: iastore
    //   1909: dup
    //   1910: bipush #33
    //   1912: ldc 8388609
    //   1914: iastore
    //   1915: dup
    //   1916: bipush #34
    //   1918: ldc 8396800
    //   1920: iastore
    //   1921: dup
    //   1922: bipush #35
    //   1924: ldc 8396929
    //   1926: iastore
    //   1927: dup
    //   1928: bipush #36
    //   1930: sipush #129
    //   1933: iastore
    //   1934: dup
    //   1935: bipush #37
    //   1937: iconst_0
    //   1938: iastore
    //   1939: dup
    //   1940: bipush #38
    //   1942: iconst_0
    //   1943: iastore
    //   1944: dup
    //   1945: bipush #39
    //   1947: ldc 8396800
    //   1949: iastore
    //   1950: dup
    //   1951: bipush #40
    //   1953: sipush #8320
    //   1956: iastore
    //   1957: dup
    //   1958: bipush #41
    //   1960: ldc 8388736
    //   1962: iastore
    //   1963: dup
    //   1964: bipush #42
    //   1966: ldc 8388737
    //   1968: iastore
    //   1969: dup
    //   1970: bipush #43
    //   1972: iconst_1
    //   1973: iastore
    //   1974: dup
    //   1975: bipush #44
    //   1977: ldc 8396801
    //   1979: iastore
    //   1980: dup
    //   1981: bipush #45
    //   1983: sipush #8321
    //   1986: iastore
    //   1987: dup
    //   1988: bipush #46
    //   1990: sipush #8321
    //   1993: iastore
    //   1994: dup
    //   1995: bipush #47
    //   1997: sipush #128
    //   2000: iastore
    //   2001: dup
    //   2002: bipush #48
    //   2004: ldc 8396929
    //   2006: iastore
    //   2007: dup
    //   2008: bipush #49
    //   2010: sipush #129
    //   2013: iastore
    //   2014: dup
    //   2015: bipush #50
    //   2017: iconst_1
    //   2018: iastore
    //   2019: dup
    //   2020: bipush #51
    //   2022: sipush #8192
    //   2025: iastore
    //   2026: dup
    //   2027: bipush #52
    //   2029: ldc 8388609
    //   2031: iastore
    //   2032: dup
    //   2033: bipush #53
    //   2035: sipush #8193
    //   2038: iastore
    //   2039: dup
    //   2040: bipush #54
    //   2042: ldc 8396928
    //   2044: iastore
    //   2045: dup
    //   2046: bipush #55
    //   2048: ldc 8388737
    //   2050: iastore
    //   2051: dup
    //   2052: bipush #56
    //   2054: sipush #8193
    //   2057: iastore
    //   2058: dup
    //   2059: bipush #57
    //   2061: sipush #8320
    //   2064: iastore
    //   2065: dup
    //   2066: bipush #58
    //   2068: ldc 8388608
    //   2070: iastore
    //   2071: dup
    //   2072: bipush #59
    //   2074: ldc 8396801
    //   2076: iastore
    //   2077: dup
    //   2078: bipush #60
    //   2080: sipush #128
    //   2083: iastore
    //   2084: dup
    //   2085: bipush #61
    //   2087: ldc 8388608
    //   2089: iastore
    //   2090: dup
    //   2091: bipush #62
    //   2093: sipush #8192
    //   2096: iastore
    //   2097: dup
    //   2098: bipush #63
    //   2100: ldc 8396928
    //   2102: iastore
    //   2103: astore #9
    //   2105: bipush #64
    //   2107: newarray int
    //   2109: dup
    //   2110: iconst_0
    //   2111: sipush #256
    //   2114: iastore
    //   2115: dup
    //   2116: iconst_1
    //   2117: ldc 34078976
    //   2119: iastore
    //   2120: dup
    //   2121: iconst_2
    //   2122: ldc 34078720
    //   2124: iastore
    //   2125: dup
    //   2126: iconst_3
    //   2127: ldc 1107296512
    //   2129: iastore
    //   2130: dup
    //   2131: iconst_4
    //   2132: ldc 524288
    //   2134: iastore
    //   2135: dup
    //   2136: iconst_5
    //   2137: sipush #256
    //   2140: iastore
    //   2141: dup
    //   2142: bipush #6
    //   2144: ldc 1073741824
    //   2146: iastore
    //   2147: dup
    //   2148: bipush #7
    //   2150: ldc 34078720
    //   2152: iastore
    //   2153: dup
    //   2154: bipush #8
    //   2156: ldc 1074266368
    //   2158: iastore
    //   2159: dup
    //   2160: bipush #9
    //   2162: ldc 524288
    //   2164: iastore
    //   2165: dup
    //   2166: bipush #10
    //   2168: ldc 33554688
    //   2170: iastore
    //   2171: dup
    //   2172: bipush #11
    //   2174: ldc 1074266368
    //   2176: iastore
    //   2177: dup
    //   2178: bipush #12
    //   2180: ldc 1107296512
    //   2182: iastore
    //   2183: dup
    //   2184: bipush #13
    //   2186: ldc 1107820544
    //   2188: iastore
    //   2189: dup
    //   2190: bipush #14
    //   2192: ldc 524544
    //   2194: iastore
    //   2195: dup
    //   2196: bipush #15
    //   2198: ldc 1073741824
    //   2200: iastore
    //   2201: dup
    //   2202: bipush #16
    //   2204: ldc 33554432
    //   2206: iastore
    //   2207: dup
    //   2208: bipush #17
    //   2210: ldc 1074266112
    //   2212: iastore
    //   2213: dup
    //   2214: bipush #18
    //   2216: ldc 1074266112
    //   2218: iastore
    //   2219: dup
    //   2220: bipush #19
    //   2222: iconst_0
    //   2223: iastore
    //   2224: dup
    //   2225: bipush #20
    //   2227: ldc 1073742080
    //   2229: iastore
    //   2230: dup
    //   2231: bipush #21
    //   2233: ldc 1107820800
    //   2235: iastore
    //   2236: dup
    //   2237: bipush #22
    //   2239: ldc 1107820800
    //   2241: iastore
    //   2242: dup
    //   2243: bipush #23
    //   2245: ldc 33554688
    //   2247: iastore
    //   2248: dup
    //   2249: bipush #24
    //   2251: ldc 1107820544
    //   2253: iastore
    //   2254: dup
    //   2255: bipush #25
    //   2257: ldc 1073742080
    //   2259: iastore
    //   2260: dup
    //   2261: bipush #26
    //   2263: iconst_0
    //   2264: iastore
    //   2265: dup
    //   2266: bipush #27
    //   2268: ldc 1107296256
    //   2270: iastore
    //   2271: dup
    //   2272: bipush #28
    //   2274: ldc 34078976
    //   2276: iastore
    //   2277: dup
    //   2278: bipush #29
    //   2280: ldc 33554432
    //   2282: iastore
    //   2283: dup
    //   2284: bipush #30
    //   2286: ldc 1107296256
    //   2288: iastore
    //   2289: dup
    //   2290: bipush #31
    //   2292: ldc 524544
    //   2294: iastore
    //   2295: dup
    //   2296: bipush #32
    //   2298: ldc 524288
    //   2300: iastore
    //   2301: dup
    //   2302: bipush #33
    //   2304: ldc 1107296512
    //   2306: iastore
    //   2307: dup
    //   2308: bipush #34
    //   2310: sipush #256
    //   2313: iastore
    //   2314: dup
    //   2315: bipush #35
    //   2317: ldc 33554432
    //   2319: iastore
    //   2320: dup
    //   2321: bipush #36
    //   2323: ldc 1073741824
    //   2325: iastore
    //   2326: dup
    //   2327: bipush #37
    //   2329: ldc 34078720
    //   2331: iastore
    //   2332: dup
    //   2333: bipush #38
    //   2335: ldc 1107296512
    //   2337: iastore
    //   2338: dup
    //   2339: bipush #39
    //   2341: ldc 1074266368
    //   2343: iastore
    //   2344: dup
    //   2345: bipush #40
    //   2347: ldc 33554688
    //   2349: iastore
    //   2350: dup
    //   2351: bipush #41
    //   2353: ldc 1073741824
    //   2355: iastore
    //   2356: dup
    //   2357: bipush #42
    //   2359: ldc 1107820544
    //   2361: iastore
    //   2362: dup
    //   2363: bipush #43
    //   2365: ldc 34078976
    //   2367: iastore
    //   2368: dup
    //   2369: bipush #44
    //   2371: ldc 1074266368
    //   2373: iastore
    //   2374: dup
    //   2375: bipush #45
    //   2377: sipush #256
    //   2380: iastore
    //   2381: dup
    //   2382: bipush #46
    //   2384: ldc 33554432
    //   2386: iastore
    //   2387: dup
    //   2388: bipush #47
    //   2390: ldc 1107820544
    //   2392: iastore
    //   2393: dup
    //   2394: bipush #48
    //   2396: ldc 1107820800
    //   2398: iastore
    //   2399: dup
    //   2400: bipush #49
    //   2402: ldc 524544
    //   2404: iastore
    //   2405: dup
    //   2406: bipush #50
    //   2408: ldc 1107296256
    //   2410: iastore
    //   2411: dup
    //   2412: bipush #51
    //   2414: ldc 1107820800
    //   2416: iastore
    //   2417: dup
    //   2418: bipush #52
    //   2420: ldc 34078720
    //   2422: iastore
    //   2423: dup
    //   2424: bipush #53
    //   2426: iconst_0
    //   2427: iastore
    //   2428: dup
    //   2429: bipush #54
    //   2431: ldc 1074266112
    //   2433: iastore
    //   2434: dup
    //   2435: bipush #55
    //   2437: ldc 1107296256
    //   2439: iastore
    //   2440: dup
    //   2441: bipush #56
    //   2443: ldc 524544
    //   2445: iastore
    //   2446: dup
    //   2447: bipush #57
    //   2449: ldc 33554688
    //   2451: iastore
    //   2452: dup
    //   2453: bipush #58
    //   2455: ldc 1073742080
    //   2457: iastore
    //   2458: dup
    //   2459: bipush #59
    //   2461: ldc 524288
    //   2463: iastore
    //   2464: dup
    //   2465: bipush #60
    //   2467: iconst_0
    //   2468: iastore
    //   2469: dup
    //   2470: bipush #61
    //   2472: ldc 1074266112
    //   2474: iastore
    //   2475: dup
    //   2476: bipush #62
    //   2478: ldc 34078976
    //   2480: iastore
    //   2481: dup
    //   2482: bipush #63
    //   2484: ldc 1073742080
    //   2486: iastore
    //   2487: astore #10
    //   2489: bipush #64
    //   2491: newarray int
    //   2493: dup
    //   2494: iconst_0
    //   2495: ldc 536870928
    //   2497: iastore
    //   2498: dup
    //   2499: iconst_1
    //   2500: ldc 541065216
    //   2502: iastore
    //   2503: dup
    //   2504: iconst_2
    //   2505: sipush #16384
    //   2508: iastore
    //   2509: dup
    //   2510: iconst_3
    //   2511: ldc 541081616
    //   2513: iastore
    //   2514: dup
    //   2515: iconst_4
    //   2516: ldc 541065216
    //   2518: iastore
    //   2519: dup
    //   2520: iconst_5
    //   2521: bipush #16
    //   2523: iastore
    //   2524: dup
    //   2525: bipush #6
    //   2527: ldc 541081616
    //   2529: iastore
    //   2530: dup
    //   2531: bipush #7
    //   2533: ldc 4194304
    //   2535: iastore
    //   2536: dup
    //   2537: bipush #8
    //   2539: ldc 536887296
    //   2541: iastore
    //   2542: dup
    //   2543: bipush #9
    //   2545: ldc 4210704
    //   2547: iastore
    //   2548: dup
    //   2549: bipush #10
    //   2551: ldc 4194304
    //   2553: iastore
    //   2554: dup
    //   2555: bipush #11
    //   2557: ldc 536870928
    //   2559: iastore
    //   2560: dup
    //   2561: bipush #12
    //   2563: ldc 4194320
    //   2565: iastore
    //   2566: dup
    //   2567: bipush #13
    //   2569: ldc 536887296
    //   2571: iastore
    //   2572: dup
    //   2573: bipush #14
    //   2575: ldc 536870912
    //   2577: iastore
    //   2578: dup
    //   2579: bipush #15
    //   2581: sipush #16400
    //   2584: iastore
    //   2585: dup
    //   2586: bipush #16
    //   2588: iconst_0
    //   2589: iastore
    //   2590: dup
    //   2591: bipush #17
    //   2593: ldc 4194320
    //   2595: iastore
    //   2596: dup
    //   2597: bipush #18
    //   2599: ldc 536887312
    //   2601: iastore
    //   2602: dup
    //   2603: bipush #19
    //   2605: sipush #16384
    //   2608: iastore
    //   2609: dup
    //   2610: bipush #20
    //   2612: ldc 4210688
    //   2614: iastore
    //   2615: dup
    //   2616: bipush #21
    //   2618: ldc 536887312
    //   2620: iastore
    //   2621: dup
    //   2622: bipush #22
    //   2624: bipush #16
    //   2626: iastore
    //   2627: dup
    //   2628: bipush #23
    //   2630: ldc 541065232
    //   2632: iastore
    //   2633: dup
    //   2634: bipush #24
    //   2636: ldc 541065232
    //   2638: iastore
    //   2639: dup
    //   2640: bipush #25
    //   2642: iconst_0
    //   2643: iastore
    //   2644: dup
    //   2645: bipush #26
    //   2647: ldc 4210704
    //   2649: iastore
    //   2650: dup
    //   2651: bipush #27
    //   2653: ldc 541081600
    //   2655: iastore
    //   2656: dup
    //   2657: bipush #28
    //   2659: sipush #16400
    //   2662: iastore
    //   2663: dup
    //   2664: bipush #29
    //   2666: ldc 4210688
    //   2668: iastore
    //   2669: dup
    //   2670: bipush #30
    //   2672: ldc 541081600
    //   2674: iastore
    //   2675: dup
    //   2676: bipush #31
    //   2678: ldc 536870912
    //   2680: iastore
    //   2681: dup
    //   2682: bipush #32
    //   2684: ldc 536887296
    //   2686: iastore
    //   2687: dup
    //   2688: bipush #33
    //   2690: bipush #16
    //   2692: iastore
    //   2693: dup
    //   2694: bipush #34
    //   2696: ldc 541065232
    //   2698: iastore
    //   2699: dup
    //   2700: bipush #35
    //   2702: ldc 4210688
    //   2704: iastore
    //   2705: dup
    //   2706: bipush #36
    //   2708: ldc 541081616
    //   2710: iastore
    //   2711: dup
    //   2712: bipush #37
    //   2714: ldc 4194304
    //   2716: iastore
    //   2717: dup
    //   2718: bipush #38
    //   2720: sipush #16400
    //   2723: iastore
    //   2724: dup
    //   2725: bipush #39
    //   2727: ldc 536870928
    //   2729: iastore
    //   2730: dup
    //   2731: bipush #40
    //   2733: ldc 4194304
    //   2735: iastore
    //   2736: dup
    //   2737: bipush #41
    //   2739: ldc 536887296
    //   2741: iastore
    //   2742: dup
    //   2743: bipush #42
    //   2745: ldc 536870912
    //   2747: iastore
    //   2748: dup
    //   2749: bipush #43
    //   2751: sipush #16400
    //   2754: iastore
    //   2755: dup
    //   2756: bipush #44
    //   2758: ldc 536870928
    //   2760: iastore
    //   2761: dup
    //   2762: bipush #45
    //   2764: ldc 541081616
    //   2766: iastore
    //   2767: dup
    //   2768: bipush #46
    //   2770: ldc 4210688
    //   2772: iastore
    //   2773: dup
    //   2774: bipush #47
    //   2776: ldc 541065216
    //   2778: iastore
    //   2779: dup
    //   2780: bipush #48
    //   2782: ldc 4210704
    //   2784: iastore
    //   2785: dup
    //   2786: bipush #49
    //   2788: ldc 541081600
    //   2790: iastore
    //   2791: dup
    //   2792: bipush #50
    //   2794: iconst_0
    //   2795: iastore
    //   2796: dup
    //   2797: bipush #51
    //   2799: ldc 541065232
    //   2801: iastore
    //   2802: dup
    //   2803: bipush #52
    //   2805: bipush #16
    //   2807: iastore
    //   2808: dup
    //   2809: bipush #53
    //   2811: sipush #16384
    //   2814: iastore
    //   2815: dup
    //   2816: bipush #54
    //   2818: ldc 541065216
    //   2820: iastore
    //   2821: dup
    //   2822: bipush #55
    //   2824: ldc 4210704
    //   2826: iastore
    //   2827: dup
    //   2828: bipush #56
    //   2830: sipush #16384
    //   2833: iastore
    //   2834: dup
    //   2835: bipush #57
    //   2837: ldc 4194320
    //   2839: iastore
    //   2840: dup
    //   2841: bipush #58
    //   2843: ldc 536887312
    //   2845: iastore
    //   2846: dup
    //   2847: bipush #59
    //   2849: iconst_0
    //   2850: iastore
    //   2851: dup
    //   2852: bipush #60
    //   2854: ldc 541081600
    //   2856: iastore
    //   2857: dup
    //   2858: bipush #61
    //   2860: ldc 536870912
    //   2862: iastore
    //   2863: dup
    //   2864: bipush #62
    //   2866: ldc 4194320
    //   2868: iastore
    //   2869: dup
    //   2870: bipush #63
    //   2872: ldc 536887312
    //   2874: iastore
    //   2875: astore #11
    //   2877: bipush #64
    //   2879: newarray int
    //   2881: dup
    //   2882: iconst_0
    //   2883: ldc 2097152
    //   2885: iastore
    //   2886: dup
    //   2887: iconst_1
    //   2888: ldc 69206018
    //   2890: iastore
    //   2891: dup
    //   2892: iconst_2
    //   2893: ldc 67110914
    //   2895: iastore
    //   2896: dup
    //   2897: iconst_3
    //   2898: iconst_0
    //   2899: iastore
    //   2900: dup
    //   2901: iconst_4
    //   2902: sipush #2048
    //   2905: iastore
    //   2906: dup
    //   2907: iconst_5
    //   2908: ldc 67110914
    //   2910: iastore
    //   2911: dup
    //   2912: bipush #6
    //   2914: ldc 2099202
    //   2916: iastore
    //   2917: dup
    //   2918: bipush #7
    //   2920: ldc 69208064
    //   2922: iastore
    //   2923: dup
    //   2924: bipush #8
    //   2926: ldc 69208066
    //   2928: iastore
    //   2929: dup
    //   2930: bipush #9
    //   2932: ldc 2097152
    //   2934: iastore
    //   2935: dup
    //   2936: bipush #10
    //   2938: iconst_0
    //   2939: iastore
    //   2940: dup
    //   2941: bipush #11
    //   2943: ldc 67108866
    //   2945: iastore
    //   2946: dup
    //   2947: bipush #12
    //   2949: iconst_2
    //   2950: iastore
    //   2951: dup
    //   2952: bipush #13
    //   2954: ldc 67108864
    //   2956: iastore
    //   2957: dup
    //   2958: bipush #14
    //   2960: ldc 69206018
    //   2962: iastore
    //   2963: dup
    //   2964: bipush #15
    //   2966: sipush #2050
    //   2969: iastore
    //   2970: dup
    //   2971: bipush #16
    //   2973: ldc 67110912
    //   2975: iastore
    //   2976: dup
    //   2977: bipush #17
    //   2979: ldc 2099202
    //   2981: iastore
    //   2982: dup
    //   2983: bipush #18
    //   2985: ldc 2097154
    //   2987: iastore
    //   2988: dup
    //   2989: bipush #19
    //   2991: ldc 67110912
    //   2993: iastore
    //   2994: dup
    //   2995: bipush #20
    //   2997: ldc 67108866
    //   2999: iastore
    //   3000: dup
    //   3001: bipush #21
    //   3003: ldc 69206016
    //   3005: iastore
    //   3006: dup
    //   3007: bipush #22
    //   3009: ldc 69208064
    //   3011: iastore
    //   3012: dup
    //   3013: bipush #23
    //   3015: ldc 2097154
    //   3017: iastore
    //   3018: dup
    //   3019: bipush #24
    //   3021: ldc 69206016
    //   3023: iastore
    //   3024: dup
    //   3025: bipush #25
    //   3027: sipush #2048
    //   3030: iastore
    //   3031: dup
    //   3032: bipush #26
    //   3034: sipush #2050
    //   3037: iastore
    //   3038: dup
    //   3039: bipush #27
    //   3041: ldc 69208066
    //   3043: iastore
    //   3044: dup
    //   3045: bipush #28
    //   3047: ldc 2099200
    //   3049: iastore
    //   3050: dup
    //   3051: bipush #29
    //   3053: iconst_2
    //   3054: iastore
    //   3055: dup
    //   3056: bipush #30
    //   3058: ldc 67108864
    //   3060: iastore
    //   3061: dup
    //   3062: bipush #31
    //   3064: ldc 2099200
    //   3066: iastore
    //   3067: dup
    //   3068: bipush #32
    //   3070: ldc 67108864
    //   3072: iastore
    //   3073: dup
    //   3074: bipush #33
    //   3076: ldc 2099200
    //   3078: iastore
    //   3079: dup
    //   3080: bipush #34
    //   3082: ldc 2097152
    //   3084: iastore
    //   3085: dup
    //   3086: bipush #35
    //   3088: ldc 67110914
    //   3090: iastore
    //   3091: dup
    //   3092: bipush #36
    //   3094: ldc 67110914
    //   3096: iastore
    //   3097: dup
    //   3098: bipush #37
    //   3100: ldc 69206018
    //   3102: iastore
    //   3103: dup
    //   3104: bipush #38
    //   3106: ldc 69206018
    //   3108: iastore
    //   3109: dup
    //   3110: bipush #39
    //   3112: iconst_2
    //   3113: iastore
    //   3114: dup
    //   3115: bipush #40
    //   3117: ldc 2097154
    //   3119: iastore
    //   3120: dup
    //   3121: bipush #41
    //   3123: ldc 67108864
    //   3125: iastore
    //   3126: dup
    //   3127: bipush #42
    //   3129: ldc 67110912
    //   3131: iastore
    //   3132: dup
    //   3133: bipush #43
    //   3135: ldc 2097152
    //   3137: iastore
    //   3138: dup
    //   3139: bipush #44
    //   3141: ldc 69208064
    //   3143: iastore
    //   3144: dup
    //   3145: bipush #45
    //   3147: sipush #2050
    //   3150: iastore
    //   3151: dup
    //   3152: bipush #46
    //   3154: ldc 2099202
    //   3156: iastore
    //   3157: dup
    //   3158: bipush #47
    //   3160: ldc 69208064
    //   3162: iastore
    //   3163: dup
    //   3164: bipush #48
    //   3166: sipush #2050
    //   3169: iastore
    //   3170: dup
    //   3171: bipush #49
    //   3173: ldc 67108866
    //   3175: iastore
    //   3176: dup
    //   3177: bipush #50
    //   3179: ldc 69208066
    //   3181: iastore
    //   3182: dup
    //   3183: bipush #51
    //   3185: ldc 69206016
    //   3187: iastore
    //   3188: dup
    //   3189: bipush #52
    //   3191: ldc 2099200
    //   3193: iastore
    //   3194: dup
    //   3195: bipush #53
    //   3197: iconst_0
    //   3198: iastore
    //   3199: dup
    //   3200: bipush #54
    //   3202: iconst_2
    //   3203: iastore
    //   3204: dup
    //   3205: bipush #55
    //   3207: ldc 69208066
    //   3209: iastore
    //   3210: dup
    //   3211: bipush #56
    //   3213: iconst_0
    //   3214: iastore
    //   3215: dup
    //   3216: bipush #57
    //   3218: ldc 2099202
    //   3220: iastore
    //   3221: dup
    //   3222: bipush #58
    //   3224: ldc 69206016
    //   3226: iastore
    //   3227: dup
    //   3228: bipush #59
    //   3230: sipush #2048
    //   3233: iastore
    //   3234: dup
    //   3235: bipush #60
    //   3237: ldc 67108866
    //   3239: iastore
    //   3240: dup
    //   3241: bipush #61
    //   3243: ldc 67110912
    //   3245: iastore
    //   3246: dup
    //   3247: bipush #62
    //   3249: sipush #2048
    //   3252: iastore
    //   3253: dup
    //   3254: bipush #63
    //   3256: ldc 2097154
    //   3258: iastore
    //   3259: astore #12
    //   3261: bipush #64
    //   3263: newarray int
    //   3265: dup
    //   3266: iconst_0
    //   3267: ldc 268439616
    //   3269: iastore
    //   3270: dup
    //   3271: iconst_1
    //   3272: sipush #4096
    //   3275: iastore
    //   3276: dup
    //   3277: iconst_2
    //   3278: ldc 262144
    //   3280: iastore
    //   3281: dup
    //   3282: iconst_3
    //   3283: ldc 268701760
    //   3285: iastore
    //   3286: dup
    //   3287: iconst_4
    //   3288: ldc 268435456
    //   3290: iastore
    //   3291: dup
    //   3292: iconst_5
    //   3293: ldc 268439616
    //   3295: iastore
    //   3296: dup
    //   3297: bipush #6
    //   3299: bipush #64
    //   3301: iastore
    //   3302: dup
    //   3303: bipush #7
    //   3305: ldc 268435456
    //   3307: iastore
    //   3308: dup
    //   3309: bipush #8
    //   3311: ldc 262208
    //   3313: iastore
    //   3314: dup
    //   3315: bipush #9
    //   3317: ldc 268697600
    //   3319: iastore
    //   3320: dup
    //   3321: bipush #10
    //   3323: ldc 268701760
    //   3325: iastore
    //   3326: dup
    //   3327: bipush #11
    //   3329: ldc 266240
    //   3331: iastore
    //   3332: dup
    //   3333: bipush #12
    //   3335: ldc 268701696
    //   3337: iastore
    //   3338: dup
    //   3339: bipush #13
    //   3341: ldc 266304
    //   3343: iastore
    //   3344: dup
    //   3345: bipush #14
    //   3347: sipush #4096
    //   3350: iastore
    //   3351: dup
    //   3352: bipush #15
    //   3354: bipush #64
    //   3356: iastore
    //   3357: dup
    //   3358: bipush #16
    //   3360: ldc 268697600
    //   3362: iastore
    //   3363: dup
    //   3364: bipush #17
    //   3366: ldc 268435520
    //   3368: iastore
    //   3369: dup
    //   3370: bipush #18
    //   3372: ldc 268439552
    //   3374: iastore
    //   3375: dup
    //   3376: bipush #19
    //   3378: sipush #4160
    //   3381: iastore
    //   3382: dup
    //   3383: bipush #20
    //   3385: ldc 266240
    //   3387: iastore
    //   3388: dup
    //   3389: bipush #21
    //   3391: ldc 262208
    //   3393: iastore
    //   3394: dup
    //   3395: bipush #22
    //   3397: ldc 268697664
    //   3399: iastore
    //   3400: dup
    //   3401: bipush #23
    //   3403: ldc 268701696
    //   3405: iastore
    //   3406: dup
    //   3407: bipush #24
    //   3409: sipush #4160
    //   3412: iastore
    //   3413: dup
    //   3414: bipush #25
    //   3416: iconst_0
    //   3417: iastore
    //   3418: dup
    //   3419: bipush #26
    //   3421: iconst_0
    //   3422: iastore
    //   3423: dup
    //   3424: bipush #27
    //   3426: ldc 268697664
    //   3428: iastore
    //   3429: dup
    //   3430: bipush #28
    //   3432: ldc 268435520
    //   3434: iastore
    //   3435: dup
    //   3436: bipush #29
    //   3438: ldc 268439552
    //   3440: iastore
    //   3441: dup
    //   3442: bipush #30
    //   3444: ldc 266304
    //   3446: iastore
    //   3447: dup
    //   3448: bipush #31
    //   3450: ldc 262144
    //   3452: iastore
    //   3453: dup
    //   3454: bipush #32
    //   3456: ldc 266304
    //   3458: iastore
    //   3459: dup
    //   3460: bipush #33
    //   3462: ldc 262144
    //   3464: iastore
    //   3465: dup
    //   3466: bipush #34
    //   3468: ldc 268701696
    //   3470: iastore
    //   3471: dup
    //   3472: bipush #35
    //   3474: sipush #4096
    //   3477: iastore
    //   3478: dup
    //   3479: bipush #36
    //   3481: bipush #64
    //   3483: iastore
    //   3484: dup
    //   3485: bipush #37
    //   3487: ldc 268697664
    //   3489: iastore
    //   3490: dup
    //   3491: bipush #38
    //   3493: sipush #4096
    //   3496: iastore
    //   3497: dup
    //   3498: bipush #39
    //   3500: ldc 266304
    //   3502: iastore
    //   3503: dup
    //   3504: bipush #40
    //   3506: ldc 268439552
    //   3508: iastore
    //   3509: dup
    //   3510: bipush #41
    //   3512: bipush #64
    //   3514: iastore
    //   3515: dup
    //   3516: bipush #42
    //   3518: ldc 268435520
    //   3520: iastore
    //   3521: dup
    //   3522: bipush #43
    //   3524: ldc 268697600
    //   3526: iastore
    //   3527: dup
    //   3528: bipush #44
    //   3530: ldc 268697664
    //   3532: iastore
    //   3533: dup
    //   3534: bipush #45
    //   3536: ldc 268435456
    //   3538: iastore
    //   3539: dup
    //   3540: bipush #46
    //   3542: ldc 262144
    //   3544: iastore
    //   3545: dup
    //   3546: bipush #47
    //   3548: ldc 268439616
    //   3550: iastore
    //   3551: dup
    //   3552: bipush #48
    //   3554: iconst_0
    //   3555: iastore
    //   3556: dup
    //   3557: bipush #49
    //   3559: ldc 268701760
    //   3561: iastore
    //   3562: dup
    //   3563: bipush #50
    //   3565: ldc 262208
    //   3567: iastore
    //   3568: dup
    //   3569: bipush #51
    //   3571: ldc 268435520
    //   3573: iastore
    //   3574: dup
    //   3575: bipush #52
    //   3577: ldc 268697600
    //   3579: iastore
    //   3580: dup
    //   3581: bipush #53
    //   3583: ldc 268439552
    //   3585: iastore
    //   3586: dup
    //   3587: bipush #54
    //   3589: ldc 268439616
    //   3591: iastore
    //   3592: dup
    //   3593: bipush #55
    //   3595: iconst_0
    //   3596: iastore
    //   3597: dup
    //   3598: bipush #56
    //   3600: ldc 268701760
    //   3602: iastore
    //   3603: dup
    //   3604: bipush #57
    //   3606: ldc 266240
    //   3608: iastore
    //   3609: dup
    //   3610: bipush #58
    //   3612: ldc 266240
    //   3614: iastore
    //   3615: dup
    //   3616: bipush #59
    //   3618: sipush #4160
    //   3621: iastore
    //   3622: dup
    //   3623: bipush #60
    //   3625: sipush #4160
    //   3628: iastore
    //   3629: dup
    //   3630: bipush #61
    //   3632: ldc 262208
    //   3634: iastore
    //   3635: dup
    //   3636: bipush #62
    //   3638: ldc 268435456
    //   3640: iastore
    //   3641: dup
    //   3642: bipush #63
    //   3644: ldc 268701696
    //   3646: iastore
    //   3647: astore #13
    //   3649: aload_3
    //   3650: arraylength
    //   3651: istore #14
    //   3653: iload #14
    //   3655: bipush #8
    //   3657: irem
    //   3658: ifeq -> 3682
    //   3661: new java/lang/Exception
    //   3664: dup
    //   3665: sipush #26857
    //   3668: sipush #-3643
    //   3671: invokestatic a : (II)Ljava/lang/String;
    //   3674: invokespecial <init> : (Ljava/lang/String;)V
    //   3677: athrow
    //   3678: invokestatic a : (Ljava/lang/Throwable;)Ljava/lang/Throwable;
    //   3681: athrow
    //   3682: iconst_2
    //   3683: newarray int
    //   3685: astore #15
    //   3687: iload #14
    //   3689: newarray byte
    //   3691: astore #16
    //   3693: iload #14
    //   3695: bipush #8
    //   3697: idiv
    //   3698: istore #17
    //   3700: iconst_0
    //   3701: istore #18
    //   3703: iload #18
    //   3705: iload #17
    //   3707: if_icmpge -> 4621
    //   3710: iload #18
    //   3712: bipush #8
    //   3714: imul
    //   3715: istore #19
    //   3717: iconst_0
    //   3718: istore #20
    //   3720: iload #20
    //   3722: iconst_2
    //   3723: if_icmpge -> 3808
    //   3726: aload #15
    //   3728: iload #20
    //   3730: aload_3
    //   3731: iload #19
    //   3733: iload #20
    //   3735: iconst_4
    //   3736: imul
    //   3737: iadd
    //   3738: baload
    //   3739: sipush #255
    //   3742: iand
    //   3743: bipush #24
    //   3745: ishl
    //   3746: aload_3
    //   3747: iload #19
    //   3749: iload #20
    //   3751: iconst_4
    //   3752: imul
    //   3753: iadd
    //   3754: iconst_1
    //   3755: iadd
    //   3756: baload
    //   3757: sipush #255
    //   3760: iand
    //   3761: bipush #16
    //   3763: ishl
    //   3764: ior
    //   3765: aload_3
    //   3766: iload #19
    //   3768: iload #20
    //   3770: iconst_4
    //   3771: imul
    //   3772: iadd
    //   3773: iconst_2
    //   3774: iadd
    //   3775: baload
    //   3776: sipush #255
    //   3779: iand
    //   3780: bipush #8
    //   3782: ishl
    //   3783: ior
    //   3784: aload_3
    //   3785: iload #19
    //   3787: iload #20
    //   3789: iconst_4
    //   3790: imul
    //   3791: iadd
    //   3792: iconst_3
    //   3793: iadd
    //   3794: baload
    //   3795: sipush #255
    //   3798: iand
    //   3799: ior
    //   3800: iastore
    //   3801: iinc #20, 1
    //   3804: iload_2
    //   3805: ifne -> 3720
    //   3808: iconst_0
    //   3809: istore #25
    //   3811: aload #15
    //   3813: iconst_0
    //   3814: iaload
    //   3815: istore #23
    //   3817: aload #15
    //   3819: iconst_1
    //   3820: iaload
    //   3821: istore #22
    //   3823: iload #23
    //   3825: iconst_4
    //   3826: iushr
    //   3827: iload #22
    //   3829: ixor
    //   3830: ldc 252645135
    //   3832: iand
    //   3833: istore #21
    //   3835: iload #22
    //   3837: iload #21
    //   3839: ixor
    //   3840: istore #22
    //   3842: iload #23
    //   3844: iload #21
    //   3846: iconst_4
    //   3847: ishl
    //   3848: ixor
    //   3849: istore #23
    //   3851: iload #23
    //   3853: bipush #16
    //   3855: iushr
    //   3856: iload #22
    //   3858: ixor
    //   3859: ldc 65535
    //   3861: iand
    //   3862: istore #21
    //   3864: iload #22
    //   3866: iload #21
    //   3868: ixor
    //   3869: istore #22
    //   3871: iload #23
    //   3873: iload #21
    //   3875: bipush #16
    //   3877: ishl
    //   3878: ixor
    //   3879: istore #23
    //   3881: iload #22
    //   3883: iconst_2
    //   3884: iushr
    //   3885: iload #23
    //   3887: ixor
    //   3888: ldc 858993459
    //   3890: iand
    //   3891: istore #21
    //   3893: iload #23
    //   3895: iload #21
    //   3897: ixor
    //   3898: istore #23
    //   3900: iload #22
    //   3902: iload #21
    //   3904: iconst_2
    //   3905: ishl
    //   3906: ixor
    //   3907: istore #22
    //   3909: iload #22
    //   3911: bipush #8
    //   3913: iushr
    //   3914: iload #23
    //   3916: ixor
    //   3917: ldc 16711935
    //   3919: iand
    //   3920: istore #21
    //   3922: iload #23
    //   3924: iload #21
    //   3926: ixor
    //   3927: istore #23
    //   3929: iload #22
    //   3931: iload #21
    //   3933: bipush #8
    //   3935: ishl
    //   3936: ixor
    //   3937: istore #22
    //   3939: iload #22
    //   3941: iconst_1
    //   3942: ishl
    //   3943: iload #22
    //   3945: bipush #31
    //   3947: iushr
    //   3948: iconst_1
    //   3949: iand
    //   3950: ior
    //   3951: istore #22
    //   3953: iload #23
    //   3955: iload #22
    //   3957: ixor
    //   3958: ldc -1431655766
    //   3960: iand
    //   3961: istore #21
    //   3963: iload #23
    //   3965: iload #21
    //   3967: ixor
    //   3968: istore #23
    //   3970: iload #22
    //   3972: iload #21
    //   3974: ixor
    //   3975: istore #22
    //   3977: iload #23
    //   3979: iconst_1
    //   3980: ishl
    //   3981: iload #23
    //   3983: bipush #31
    //   3985: iushr
    //   3986: iconst_1
    //   3987: iand
    //   3988: ior
    //   3989: istore #23
    //   3991: iconst_0
    //   3992: istore #24
    //   3994: iload #24
    //   3996: bipush #8
    //   3998: if_icmpge -> 4336
    //   4001: iload #22
    //   4003: bipush #28
    //   4005: ishl
    //   4006: iload #22
    //   4008: iconst_4
    //   4009: iushr
    //   4010: ior
    //   4011: istore #21
    //   4013: iload #21
    //   4015: aload #5
    //   4017: iload #25
    //   4019: iinc #25, 1
    //   4022: iaload
    //   4023: ixor
    //   4024: istore #21
    //   4026: aload #12
    //   4028: iload #21
    //   4030: bipush #63
    //   4032: iand
    //   4033: iaload
    //   4034: istore #20
    //   4036: iload #20
    //   4038: aload #10
    //   4040: iload #21
    //   4042: bipush #8
    //   4044: iushr
    //   4045: bipush #63
    //   4047: iand
    //   4048: iaload
    //   4049: ior
    //   4050: istore #20
    //   4052: iload #20
    //   4054: aload #8
    //   4056: iload #21
    //   4058: bipush #16
    //   4060: iushr
    //   4061: bipush #63
    //   4063: iand
    //   4064: iaload
    //   4065: ior
    //   4066: istore #20
    //   4068: iload #20
    //   4070: aload #6
    //   4072: iload #21
    //   4074: bipush #24
    //   4076: iushr
    //   4077: bipush #63
    //   4079: iand
    //   4080: iaload
    //   4081: ior
    //   4082: istore #20
    //   4084: iload #22
    //   4086: aload #5
    //   4088: iload #25
    //   4090: iinc #25, 1
    //   4093: iaload
    //   4094: ixor
    //   4095: istore #21
    //   4097: iload #20
    //   4099: aload #13
    //   4101: iload #21
    //   4103: bipush #63
    //   4105: iand
    //   4106: iaload
    //   4107: ior
    //   4108: istore #20
    //   4110: iload #20
    //   4112: aload #11
    //   4114: iload #21
    //   4116: bipush #8
    //   4118: iushr
    //   4119: bipush #63
    //   4121: iand
    //   4122: iaload
    //   4123: ior
    //   4124: istore #20
    //   4126: iload #20
    //   4128: aload #9
    //   4130: iload #21
    //   4132: bipush #16
    //   4134: iushr
    //   4135: bipush #63
    //   4137: iand
    //   4138: iaload
    //   4139: ior
    //   4140: istore #20
    //   4142: iload #20
    //   4144: aload #7
    //   4146: iload #21
    //   4148: bipush #24
    //   4150: iushr
    //   4151: bipush #63
    //   4153: iand
    //   4154: iaload
    //   4155: ior
    //   4156: istore #20
    //   4158: iload #23
    //   4160: iload #20
    //   4162: ixor
    //   4163: istore #23
    //   4165: iload #23
    //   4167: bipush #28
    //   4169: ishl
    //   4170: iload #23
    //   4172: iconst_4
    //   4173: iushr
    //   4174: ior
    //   4175: istore #21
    //   4177: iload #21
    //   4179: aload #5
    //   4181: iload #25
    //   4183: iinc #25, 1
    //   4186: iaload
    //   4187: ixor
    //   4188: istore #21
    //   4190: aload #12
    //   4192: iload #21
    //   4194: bipush #63
    //   4196: iand
    //   4197: iaload
    //   4198: istore #20
    //   4200: iload #20
    //   4202: aload #10
    //   4204: iload #21
    //   4206: bipush #8
    //   4208: iushr
    //   4209: bipush #63
    //   4211: iand
    //   4212: iaload
    //   4213: ior
    //   4214: istore #20
    //   4216: iload #20
    //   4218: aload #8
    //   4220: iload #21
    //   4222: bipush #16
    //   4224: iushr
    //   4225: bipush #63
    //   4227: iand
    //   4228: iaload
    //   4229: ior
    //   4230: istore #20
    //   4232: iload #20
    //   4234: aload #6
    //   4236: iload #21
    //   4238: bipush #24
    //   4240: iushr
    //   4241: bipush #63
    //   4243: iand
    //   4244: iaload
    //   4245: ior
    //   4246: istore #20
    //   4248: iload #23
    //   4250: aload #5
    //   4252: iload #25
    //   4254: iinc #25, 1
    //   4257: iaload
    //   4258: ixor
    //   4259: istore #21
    //   4261: iload #20
    //   4263: aload #13
    //   4265: iload #21
    //   4267: bipush #63
    //   4269: iand
    //   4270: iaload
    //   4271: ior
    //   4272: istore #20
    //   4274: iload #20
    //   4276: aload #11
    //   4278: iload #21
    //   4280: bipush #8
    //   4282: iushr
    //   4283: bipush #63
    //   4285: iand
    //   4286: iaload
    //   4287: ior
    //   4288: istore #20
    //   4290: iload #20
    //   4292: aload #9
    //   4294: iload #21
    //   4296: bipush #16
    //   4298: iushr
    //   4299: bipush #63
    //   4301: iand
    //   4302: iaload
    //   4303: ior
    //   4304: istore #20
    //   4306: iload #20
    //   4308: aload #7
    //   4310: iload #21
    //   4312: bipush #24
    //   4314: iushr
    //   4315: bipush #63
    //   4317: iand
    //   4318: iaload
    //   4319: ior
    //   4320: istore #20
    //   4322: iload #22
    //   4324: iload #20
    //   4326: ixor
    //   4327: istore #22
    //   4329: iinc #24, 1
    //   4332: iload_2
    //   4333: ifne -> 3994
    //   4336: iload #22
    //   4338: bipush #31
    //   4340: ishl
    //   4341: iload #22
    //   4343: iconst_1
    //   4344: iushr
    //   4345: ior
    //   4346: istore #22
    //   4348: iload #23
    //   4350: iload #22
    //   4352: ixor
    //   4353: ldc -1431655766
    //   4355: iand
    //   4356: istore #21
    //   4358: iload #23
    //   4360: iload #21
    //   4362: ixor
    //   4363: istore #23
    //   4365: iload #22
    //   4367: iload #21
    //   4369: ixor
    //   4370: istore #22
    //   4372: iload #23
    //   4374: bipush #31
    //   4376: ishl
    //   4377: iload #23
    //   4379: iconst_1
    //   4380: iushr
    //   4381: ior
    //   4382: istore #23
    //   4384: iload #23
    //   4386: bipush #8
    //   4388: iushr
    //   4389: iload #22
    //   4391: ixor
    //   4392: ldc 16711935
    //   4394: iand
    //   4395: istore #21
    //   4397: iload #22
    //   4399: iload #21
    //   4401: ixor
    //   4402: istore #22
    //   4404: iload #23
    //   4406: iload #21
    //   4408: bipush #8
    //   4410: ishl
    //   4411: ixor
    //   4412: istore #23
    //   4414: iload #23
    //   4416: iconst_2
    //   4417: iushr
    //   4418: iload #22
    //   4420: ixor
    //   4421: ldc 858993459
    //   4423: iand
    //   4424: istore #21
    //   4426: iload #22
    //   4428: iload #21
    //   4430: ixor
    //   4431: istore #22
    //   4433: iload #23
    //   4435: iload #21
    //   4437: iconst_2
    //   4438: ishl
    //   4439: ixor
    //   4440: istore #23
    //   4442: iload #22
    //   4444: bipush #16
    //   4446: iushr
    //   4447: iload #23
    //   4449: ixor
    //   4450: ldc 65535
    //   4452: iand
    //   4453: istore #21
    //   4455: iload #23
    //   4457: iload #21
    //   4459: ixor
    //   4460: istore #23
    //   4462: iload #22
    //   4464: iload #21
    //   4466: bipush #16
    //   4468: ishl
    //   4469: ixor
    //   4470: istore #22
    //   4472: iload #22
    //   4474: iconst_4
    //   4475: iushr
    //   4476: iload #23
    //   4478: ixor
    //   4479: ldc 252645135
    //   4481: iand
    //   4482: istore #21
    //   4484: iload #23
    //   4486: iload #21
    //   4488: ixor
    //   4489: istore #23
    //   4491: iload #22
    //   4493: iload #21
    //   4495: iconst_4
    //   4496: ishl
    //   4497: ixor
    //   4498: istore #22
    //   4500: aload #15
    //   4502: iconst_0
    //   4503: iload #22
    //   4505: iastore
    //   4506: aload #15
    //   4508: iconst_1
    //   4509: iload #23
    //   4511: iastore
    //   4512: iload #18
    //   4514: bipush #8
    //   4516: imul
    //   4517: istore #26
    //   4519: iconst_0
    //   4520: istore #27
    //   4522: iload #27
    //   4524: iconst_2
    //   4525: if_icmpge -> 4614
    //   4528: aload #16
    //   4530: iload #26
    //   4532: iload #27
    //   4534: iconst_4
    //   4535: imul
    //   4536: iadd
    //   4537: aload #15
    //   4539: iload #27
    //   4541: iaload
    //   4542: bipush #24
    //   4544: iushr
    //   4545: i2b
    //   4546: bastore
    //   4547: aload #16
    //   4549: iload #26
    //   4551: iload #27
    //   4553: iconst_4
    //   4554: imul
    //   4555: iadd
    //   4556: iconst_1
    //   4557: iadd
    //   4558: aload #15
    //   4560: iload #27
    //   4562: iaload
    //   4563: bipush #16
    //   4565: iushr
    //   4566: i2b
    //   4567: bastore
    //   4568: aload #16
    //   4570: iload #26
    //   4572: iload #27
    //   4574: iconst_4
    //   4575: imul
    //   4576: iadd
    //   4577: iconst_2
    //   4578: iadd
    //   4579: aload #15
    //   4581: iload #27
    //   4583: iaload
    //   4584: bipush #8
    //   4586: iushr
    //   4587: i2b
    //   4588: bastore
    //   4589: aload #16
    //   4591: iload #26
    //   4593: iload #27
    //   4595: iconst_4
    //   4596: imul
    //   4597: iadd
    //   4598: iconst_3
    //   4599: iadd
    //   4600: aload #15
    //   4602: iload #27
    //   4604: iaload
    //   4605: i2b
    //   4606: bastore
    //   4607: iinc #27, 1
    //   4610: iload_2
    //   4611: ifne -> 4522
    //   4614: iinc #18, 1
    //   4617: iload_2
    //   4618: ifne -> 3703
    //   4621: aload #16
    //   4623: aload #16
    //   4625: arraylength
    //   4626: iconst_1
    //   4627: isub
    //   4628: baload
    //   4629: istore #18
    //   4631: aload #16
    //   4633: arraylength
    //   4634: iload #18
    //   4636: isub
    //   4637: newarray byte
    //   4639: astore #4
    //   4641: aload #16
    //   4643: arraylength
    //   4644: aload #4
    //   4646: arraylength
    //   4647: if_icmpge -> 4671
    //   4650: new java/lang/Exception
    //   4653: dup
    //   4654: sipush #26850
    //   4657: sipush #-6196
    //   4660: invokestatic a : (II)Ljava/lang/String;
    //   4663: invokespecial <init> : (Ljava/lang/String;)V
    //   4666: athrow
    //   4667: invokestatic a : (Ljava/lang/Throwable;)Ljava/lang/Throwable;
    //   4670: athrow
    //   4671: iconst_0
    //   4672: istore #19
    //   4674: iload #19
    //   4676: aload #4
    //   4678: arraylength
    //   4679: if_icmpge -> 4699
    //   4682: aload #4
    //   4684: iload #19
    //   4686: aload #16
    //   4688: iload #19
    //   4690: baload
    //   4691: bastore
    //   4692: iinc #19, 1
    //   4695: iload_2
    //   4696: ifne -> 4674
    //   4699: getstatic burp/Zrs0.Zt : Ljava/lang/String;
    //   4702: getstatic burp/Zrd4.Ze : Ljava/lang/Object;
    //   4705: checkcast java/math/BigInteger
    //   4708: invokevirtual intValue : ()I
    //   4711: bipush #32
    //   4713: irem
    //   4714: invokestatic abs : (I)I
    //   4717: invokevirtual charAt : (I)C
    //   4720: getstatic burp/Zeor.Zj : Ljava/lang/String;
    //   4723: getstatic burp/Zeor.Zb : Ljava/lang/Object;
    //   4726: checkcast java/math/BigInteger
    //   4729: invokevirtual intValue : ()I
    //   4732: bipush #32
    //   4734: irem
    //   4735: invokestatic abs : (I)I
    //   4738: invokevirtual charAt : (I)C
    //   4741: if_icmpgt -> 4848
    //   4744: getstatic burp/Zkfa.Zy : Ljava/lang/String;
    //   4747: getstatic burp/Zrf9.Zu : Ljava/lang/Object;
    //   4750: checkcast java/math/BigInteger
    //   4753: invokevirtual intValue : ()I
    //   4756: bipush #32
    //   4758: irem
    //   4759: invokestatic abs : (I)I
    //   4762: invokevirtual charAt : (I)C
    //   4765: getstatic burp/Zsf3.Zb : Ljava/lang/String;
    //   4768: getstatic burp/Zzxv.ZZ : Ljava/lang/Object;
    //   4771: checkcast java/math/BigInteger
    //   4774: invokevirtual intValue : ()I
    //   4777: bipush #32
    //   4779: irem
    //   4780: invokestatic abs : (I)I
    //   4783: invokevirtual charAt : (I)C
    //   4786: if_icmple -> 4848
    //   4789: goto -> 4796
    //   4792: invokestatic a : (Ljava/lang/Throwable;)Ljava/lang/Throwable;
    //   4795: athrow
    //   4796: getstatic burp/Zkco.Zz : Ljava/lang/String;
    //   4799: getstatic burp/Zlna.ZG : Ljava/lang/Object;
    //   4802: checkcast java/math/BigInteger
    //   4805: invokevirtual intValue : ()I
    //   4808: bipush #32
    //   4810: irem
    //   4811: invokestatic abs : (I)I
    //   4814: invokevirtual charAt : (I)C
    //   4817: getstatic burp/Zb20.ZL : Ljava/lang/String;
    //   4820: getstatic burp/Zro5.ZT : Ljava/lang/Object;
    //   4823: checkcast java/math/BigInteger
    //   4826: invokevirtual intValue : ()I
    //   4829: bipush #32
    //   4831: irem
    //   4832: invokestatic abs : (I)I
    //   4835: invokevirtual charAt : (I)C
    //   4838: if_icmple -> 4856
    //   4841: goto -> 4848
    //   4844: invokestatic a : (Ljava/lang/Throwable;)Ljava/lang/Throwable;
    //   4847: athrow
    //   4848: iconst_1
    //   4849: goto -> 4857
    //   4852: invokestatic a : (Ljava/lang/Throwable;)Ljava/lang/Throwable;
    //   4855: athrow
    //   4856: iconst_0
    //   4857: ireturn
    //   4858: astore_3
    //   4859: new java/lang/Exception
    //   4862: dup
    //   4863: aload_3
    //   4864: invokevirtual getMessage : ()Ljava/lang/String;
    //   4867: invokespecial <init> : (Ljava/lang/String;)V
    //   4870: athrow
    // Exception table:
    //   from	to	target	type
    //   4	4857	4858	java/lang/Throwable
    //   64	78	78	java/lang/Throwable
    //   89	102	105	java/lang/Throwable
    //   94	117	120	java/lang/Throwable
    //   109	135	138	java/lang/Throwable
    //   124	165	168	java/lang/Throwable
    //   228	255	258	java/lang/Throwable
    //   245	276	279	java/lang/Throwable
    //   262	306	309	java/lang/Throwable
    //   283	317	317	java/lang/Throwable
    //   328	344	347	java/lang/Throwable
    //   3653	3678	3678	java/lang/Throwable
    //   4641	4667	4667	java/lang/Throwable
    //   4699	4789	4792	java/lang/Throwable
    //   4744	4841	4844	java/lang/Throwable
    //   4796	4852	4852	java/lang/Throwable
  }
  
  static {
    // Byte code:
    //   0: bipush #10
    //   2: anewarray java/lang/String
    //   5: astore #5
    //   7: iconst_0
    //   8: istore_3
    //   9: ldc 'L\b'\{Tz!b\\n :T0$A[HldgU8\\t.XDMa6x*[r#t4\\n+0ajq(Ej:N7oJX{NrwK/vn_-;\\t<ea QJ\\rOzPDT0'
    //   11: dup
    //   12: astore_2
    //   13: invokevirtual length : ()I
    //   16: istore #4
    //   18: bipush #9
    //   20: istore_1
    //   21: iconst_m1
    //   22: istore_0
    //   23: bipush #43
    //   25: iinc #0, 1
    //   28: aload_2
    //   29: iload_0
    //   30: dup
    //   31: iload_1
    //   32: iadd
    //   33: invokevirtual substring : (II)Ljava/lang/String;
    //   36: iconst_m1
    //   37: goto -> 143
    //   40: aload #5
    //   42: swap
    //   43: iload_3
    //   44: iinc #3, 1
    //   47: swap
    //   48: aastore
    //   49: iload_0
    //   50: iload_1
    //   51: iadd
    //   52: dup
    //   53: istore_0
    //   54: iload #4
    //   56: if_icmpge -> 68
    //   59: aload_2
    //   60: iload_0
    //   61: invokevirtual charAt : (I)C
    //   64: istore_1
    //   65: goto -> 23
    //   68: ldc '[r+@f/l_9uwK'
    //   70: dup
    //   71: astore_2
    //   72: invokevirtual length : ()I
    //   75: istore #4
    //   77: bipush #9
    //   79: istore_1
    //   80: iconst_m1
    //   81: istore_0
    //   82: bipush #53
    //   84: iinc #0, 1
    //   87: aload_2
    //   88: iload_0
    //   89: dup
    //   90: iload_1
    //   91: iadd
    //   92: invokevirtual substring : (II)Ljava/lang/String;
    //   95: iconst_0
    //   96: goto -> 143
    //   99: aload #5
    //   101: swap
    //   102: iload_3
    //   103: iinc #3, 1
    //   106: swap
    //   107: aastore
    //   108: iload_0
    //   109: iload_1
    //   110: iadd
    //   111: dup
    //   112: istore_0
    //   113: iload #4
    //   115: if_icmpge -> 127
    //   118: aload_2
    //   119: iload_0
    //   120: invokevirtual charAt : (I)C
    //   123: istore_1
    //   124: goto -> 82
    //   127: aload #5
    //   129: putstatic burp/Zmt7.a : [Ljava/lang/String;
    //   132: bipush #10
    //   134: anewarray java/lang/String
    //   137: putstatic burp/Zmt7.b : [Ljava/lang/String;
    //   140: goto -> 300
    //   143: dup_x2
    //   144: pop
    //   145: invokevirtual toCharArray : ()[C
    //   148: dup_x1
    //   149: arraylength
    //   150: dup_x2
    //   151: pop
    //   152: iconst_0
    //   153: istore #6
    //   155: dup2_x1
    //   156: pop2
    //   157: dup_x2
    //   158: iconst_1
    //   159: if_icmpgt -> 260
    //   162: dup2
    //   163: swap
    //   164: iload #6
    //   166: dup2_x1
    //   167: caload
    //   168: swap
    //   169: iload #6
    //   171: bipush #7
    //   173: irem
    //   174: tableswitch default -> 242, 0 -> 212, 1 -> 217, 2 -> 222, 3 -> 227, 4 -> 232, 5 -> 237
    //   212: bipush #67
    //   214: goto -> 244
    //   217: bipush #22
    //   219: goto -> 244
    //   222: bipush #53
    //   224: goto -> 244
    //   227: bipush #95
    //   229: goto -> 244
    //   232: bipush #106
    //   234: goto -> 244
    //   237: bipush #12
    //   239: goto -> 244
    //   242: bipush #92
    //   244: ixor
    //   245: ixor
    //   246: i2c
    //   247: castore
    //   248: iinc #6, 1
    //   251: dup
    //   252: ifne -> 260
    //   255: dup2
    //   256: dup_x1
    //   257: goto -> 166
    //   260: dup2_x1
    //   261: pop2
    //   262: dup_x2
    //   263: iload #6
    //   265: if_icmpgt -> 162
    //   268: pop
    //   269: new java/lang/String
    //   272: dup_x1
    //   273: swap
    //   274: invokespecial <init> : ([C)V
    //   277: invokevirtual intern : ()Ljava/lang/String;
    //   280: swap
    //   281: pop
    //   282: swap
    //   283: tableswitch default -> 40, 0 -> 99
    //   300: new java/math/BigInteger
    //   303: dup
    //   304: bipush #32
    //   306: newarray byte
    //   308: dup
    //   309: iconst_0
    //   310: bipush #64
    //   312: bastore
    //   313: dup
    //   314: iconst_1
    //   315: bipush #-24
    //   317: bastore
    //   318: dup
    //   319: iconst_2
    //   320: bipush #-108
    //   322: bastore
    //   323: dup
    //   324: iconst_3
    //   325: bipush #-80
    //   327: bastore
    //   328: dup
    //   329: iconst_4
    //   330: bipush #62
    //   332: bastore
    //   333: dup
    //   334: iconst_5
    //   335: bipush #-127
    //   337: bastore
    //   338: dup
    //   339: bipush #6
    //   341: bipush #23
    //   343: bastore
    //   344: dup
    //   345: bipush #7
    //   347: bipush #-19
    //   349: bastore
    //   350: dup
    //   351: bipush #8
    //   353: bipush #-11
    //   355: bastore
    //   356: dup
    //   357: bipush #9
    //   359: bipush #-9
    //   361: bastore
    //   362: dup
    //   363: bipush #10
    //   365: bipush #124
    //   367: bastore
    //   368: dup
    //   369: bipush #11
    //   371: bipush #-24
    //   373: bastore
    //   374: dup
    //   375: bipush #12
    //   377: bipush #48
    //   379: bastore
    //   380: dup
    //   381: bipush #13
    //   383: bipush #-15
    //   385: bastore
    //   386: dup
    //   387: bipush #14
    //   389: bipush #-70
    //   391: bastore
    //   392: dup
    //   393: bipush #15
    //   395: bipush #81
    //   397: bastore
    //   398: dup
    //   399: bipush #16
    //   401: bipush #33
    //   403: bastore
    //   404: dup
    //   405: bipush #17
    //   407: bipush #-42
    //   409: bastore
    //   410: dup
    //   411: bipush #18
    //   413: bipush #-15
    //   415: bastore
    //   416: dup
    //   417: bipush #19
    //   419: bipush #-120
    //   421: bastore
    //   422: dup
    //   423: bipush #20
    //   425: bipush #31
    //   427: bastore
    //   428: dup
    //   429: bipush #21
    //   431: bipush #-112
    //   433: bastore
    //   434: dup
    //   435: bipush #22
    //   437: bipush #22
    //   439: bastore
    //   440: dup
    //   441: bipush #23
    //   443: bipush #-108
    //   445: bastore
    //   446: dup
    //   447: bipush #24
    //   449: bipush #-8
    //   451: bastore
    //   452: dup
    //   453: bipush #25
    //   455: bipush #98
    //   457: bastore
    //   458: dup
    //   459: bipush #26
    //   461: bipush #64
    //   463: bastore
    //   464: dup
    //   465: bipush #27
    //   467: bipush #33
    //   469: bastore
    //   470: dup
    //   471: bipush #28
    //   473: bipush #-3
    //   475: bastore
    //   476: dup
    //   477: bipush #29
    //   479: bipush #88
    //   481: bastore
    //   482: dup
    //   483: bipush #30
    //   485: bipush #-51
    //   487: bastore
    //   488: dup
    //   489: bipush #31
    //   491: bipush #101
    //   493: bastore
    //   494: invokespecial <init> : ([B)V
    //   497: putstatic burp/Zmt7.Z_ : Ljava/lang/Object;
    //   500: sipush #26860
    //   503: sipush #-14866
    //   506: invokestatic a : (II)Ljava/lang/String;
    //   509: putstatic burp/Zmt7.Zl : Ljava/lang/String;
    //   512: return
  }
  
  private static Throwable a(Throwable paramThrowable) {
    return paramThrowable;
  }
  
  private static String a(int paramInt1, int paramInt2) {
    int i = (paramInt1 ^ 0x68EB) & 0xFFFF;
    if (b[i] == null) {
      char[] arrayOfChar = a[i].toCharArray();
      switch (arrayOfChar[0] & 0xFF) {
        case 0:
        
        case 1:
        
        case 2:
        
        case 3:
        
        case 4:
        
        case 5:
        
        case 6:
        
        case 7:
        
        case 8:
        
        case 9:
        
        case 10:
        
        case 11:
        
        case 12:
        
        case 13:
        
        case 14:
        
        case 15:
        
        case 16:
        
        case 17:
        
        case 18:
        
        case 19:
        
        case 20:
        
        case 21:
        
        case 22:
        
        case 23:
        
        case 24:
        
        case 25:
        
        case 26:
        
        case 27:
        
        case 28:
        
        case 29:
        
        case 30:
        
        case 31:
        
        case 32:
        
        case 33:
        
        case 34:
        
        case 35:
        
        case 36:
        
        case 37:
        
        case 38:
        
        case 39:
        
        case 40:
        
        case 41:
        
        case 42:
        
        case 43:
        
        case 44:
        
        case 45:
        
        case 46:
        
        case 47:
        
        case 48:
        
        case 49:
        
        case 50:
        
        case 51:
        
        case 52:
        
        case 53:
        
        case 54:
        
        case 55:
        
        case 56:
        
        case 57:
        
        case 58:
        
        case 59:
        
        case 60:
        
        case 61:
        
        case 62:
        
        case 63:
        
        case 64:
        
        case 65:
        
        case 66:
        
        case 67:
        
        case 68:
        
        case 69:
        
        case 70:
        
        case 71:
        
        case 72:
        
        case 73:
        
        case 74:
        
        case 75:
        
        case 76:
        
        case 77:
        
        case 78:
        
        case 79:
        
        case 80:
        
        case 81:
        
        case 82:
        
        case 83:
        
        case 84:
        
        case 85:
        
        case 86:
        
        case 87:
        
        case 88:
        
        case 89:
        
        case 90:
        
        case 91:
        
        case 92:
        
        case 93:
        
        case 94:
        
        case 95:
        
        case 96:
        
        case 97:
        
        case 98:
        
        case 99:
        
        case 100:
        
        case 101:
        
        case 102:
        
        case 103:
        
        case 104:
        
        case 105:
        
        case 106:
        
        case 107:
        
        case 108:
        
        case 109:
        
        case 110:
        
        case 111:
        
        case 112:
        
        case 113:
        
        case 114:
        
        case 115:
        
        case 116:
        
        case 117:
        
        case 118:
        
        case 119:
        
        case 120:
        
        case 121:
        
        case 122:
        
        case 123:
        
        case 124:
        
        case 125:
        
        case 126:
        
        case 127:
        
        case 128:
        
        case 129:
        
        case 130:
        
        case 131:
        
        case 132:
        
        case 133:
        
        case 134:
        
        case 135:
        
        case 136:
        
        case 137:
        
        case 138:
        
        case 139:
        
        case 140:
        
        case 141:
        
        case 142:
        
        case 143:
        
        case 144:
        
        case 145:
        
        case 146:
        
        case 147:
        
        case 148:
        
        case 149:
        
        case 150:
        
        case 151:
        
        case 152:
        
        case 153:
        
        case 154:
        
        case 155:
        
        case 156:
        
        case 157:
        
        case 158:
        
        case 159:
        
        case 160:
        
        case 161:
        
        case 162:
        
        case 163:
        
        case 164:
        
        case 165:
        
        case 166:
        
        case 167:
        
        case 168:
        
        case 169:
        
        case 170:
        
        case 171:
        
        case 172:
        
        case 173:
        
        case 174:
        
        case 175:
        
        case 176:
        
        case 177:
        
        case 178:
        
        case 179:
        
        case 180:
        
        case 181:
        
        case 182:
        
        case 183:
        
        case 184:
        
        case 185:
        
        case 186:
        
        case 187:
        
        case 188:
        
        case 189:
        
        case 190:
        
        case 191:
        
        case 192:
        
        case 193:
        
        case 194:
        
        case 195:
        
        case 196:
        
        case 197:
        
        case 198:
        
        case 199:
        
        case 200:
        
        case 201:
        
        case 202:
        
        case 203:
        
        case 204:
        
        case 205:
        
        case 206:
        
        case 207:
        
        case 208:
        
        case 209:
        
        case 210:
        
        case 211:
        
        case 212:
        
        case 213:
        
        case 214:
        
        case 215:
        
        case 216:
        
        case 217:
        
        case 218:
        
        case 219:
        
        case 220:
        
        case 221:
        
        case 222:
        
        case 223:
        
        case 224:
        
        case 225:
        
        case 226:
        
        case 227:
        
        case 228:
        
        case 229:
        
        case 230:
        
        case 231:
        
        case 232:
        
        case 233:
        
        case 234:
        
        case 235:
        
        case 236:
        
        case 237:
        
        case 238:
        
        case 239:
        
        case 240:
        
        case 241:
        
        case 242:
        
        case 243:
        
        case 244:
        
        case 245:
        
        case 246:
        
        case 247:
        
        case 248:
        
        case 249:
        
        case 250:
        
        case 251:
        
        case 252:
        
        case 253:
        
        case 254:
        
        default:
          break;
      } 
      char c = '';
      int j = (paramInt2 & 0xFF) - c;
      if (j < 0)
        j += 256; 
      int k = ((paramInt2 & 0xFFFF) >>> 8) - c;
      if (k < 0)
        k += 256; 
      for (byte b = 0; b < arrayOfChar.length; b++) {
        int m = b % 2;
        if (m == 0) {
          arrayOfChar[b] = (char)(arrayOfChar[b] ^ j);
          j = ((j >>> 3 | j << 5) ^ arrayOfChar[b]) & 0xFF;
        } else {
          arrayOfChar[b] = (char)(arrayOfChar[b] ^ k);
          k = ((k >>> 3 | k << 5) ^ arrayOfChar[b]) & 0xFF;
        } 
      } 
      b[i] = (new String(arrayOfChar)).intern();
    } 
    return b[i];
  }
}


/* Location:              C:\Program Files\BurpSuitePro\burpsuite_pro.jar!\burp\Zmt7.class
 * Java compiler version: 21 (65.0)
 * JD-Core Version:       1.1.3
 */