package burp;

import java.util.Arrays;
import java.util.List;

class Zmt8 {
  private static final String[] a;
  
  private static final String[] b;
  
  static List<String> Zb() {
    int[] arrayOfInt = Ztyp.Zw();
    if (arrayOfInt == null)
      Zbqc.Zr(new Zbqc[3]); 
    return Arrays.asList(new String[] { 
          "", a(-12075, 22856), a(-11345, 2581), a(-9333, 14390), a(-10057, -27383), a(-11295, 22184), a(-9354, 31939), a(-9600, 27038), a(-9570, 18789), a(-11460, 20906), 
          a(-9853, 15640), a(-10121, -20422), a(-11314, -868), a(-8773, 526), a(-9619, 25320), a(-10271, -29582), a(-11893, -18906), a(-11311, 7006), a(-8988, -31213), a(-8933, -23321), 
          a(-9490, 26876), a(-10236, 26138), a(-10097, 31190), a(-12275, -13590), a(-10214, -3479), a(-10108, -1160), a(-12152, 342), a(-8646, 13293), a(-8618, -14355), a(-8774, 30075), 
          a(-12276, 3217), a(-9098, 31546), a(-11449, 26618), a(-10232, 32601), a(-12260, -14753), a(-9374, -22266), a(-9943, -32762), a(-12078, -15508), a(-8846, 22109), a(-11623, -25927), 
          a(-8474, 20040), a(-9496, -24155), a(-11758, -10257), a(-10495, -26305), a(-9115, 21065), a(-8946, -3229), a(-10444, -8098), a(-9428, 25849), a(-9578, 989), a(-9509, -19270), 
          a(-8238, -11267), a(-9764, 23955), a(-9885, -20708), a(-10710, -22658), a(-12096, -8862), a(-10401, -4992), a(-8839, 7462), a(-8441, -28707), a(-10009, 6192), a(-11932, 20241), 
          a(-9909, -3304), a(-11836, 26119), a(-11364, 29507), a(-12128, -22367), a(-11747, 28143), a(-10177, -10685), a(-11830, 30010), a(-9191, 16216), a(-10052, 15111), a(-10686, 29347), 
          a(-11522, -27260), a(-8194, 32671), a(-8442, 20162), a(-8198, -32023), a(-10561, 32133), a(-9617, 5046), a(-8228, -14425), a(-10434, 21163), a(-11927, -12569), a(-12076, 30429), 
          a(-9707, 9814), a(-11716, -24653), a(-9955, -13405), a(-12045, -23702), a(-9380, 7767), a(-11919, 5061), a(-8384, -29230), a(-10167, -8009), a(-10151, 26841), a(-10613, -7959), 
          a(-11452, -13091), a(-11470, -5111), a(-9655, 21753), a(-11678, -21899), a(-9003, -24905), a(-11332, 29539), a(-9412, 14575), a(-12281, -24261), a(-9215, -14249), a(-10091, 20229), 
          a(-9882, -669), a(-8210, 27402), a(-9645, -158), a(-9195, -28765), a(-11335, -22752), a(-11956, -3166), a(-11967, -1799), a(-11691, -24494), a(-11793, 31862), a(-8565, -12189), 
          a(-10727, 21231), a(-12092, -8418), a(-8675, 2759), a(-10631, -14513), a(-11404, -21433), a(-8510, -264), a(-9730, 528), a(-9800, -21777), a(-8668, -20770), a(-8235, 32488), 
          a(-10028, -981), a(-9696, 32239), a(-8654, -30574), a(-9580, -11910), a(-10709, 17032), a(-8677, -10712), a(-10508, -30316), a(-11346, 31232), a(-11860, -18170), a(-9958, 17297), 
          a(-9632, -16739), a(-11358, -30741), a(-11719, 22761), a(-9514, 19984), a(-9310, 25324), a(-11399, -27316), a(-8373, 3064), a(-8319, -32169), a(-11512, 32384), a(-9097, -13142), 
          a(-9106, 315), a(-9325, 24671), a(-9875, -26624), a(-11278, -7186), a(-9859, 236), a(-11920, -32111), a(-9546, -24745), a(-8366, -14925), a(-8323, 31958), a(-10484, -2733), 
          a(-10231, 26841), a(-8223, -26594), a(-9408, 28067), a(-11414, -6122), a(-9475, 25783), a(-8939, -13872), a(-11882, 15599), a(-8316, 14196), a(-8405, -15801), a(-8253, 13226), 
          a(-9539, 11312), a(-8359, -20720), a(-12038, 3097), a(-10080, 32495), a(-9197, -16154), a(-9752, 29633), a(-10547, 9001), a(-9907, -396), a(-11773, -7787), a(-11652, 4237), 
          a(-10092, 20711), a(-10552, -8324), "2", a(-8922, 7687), a(-11626, 20865), a(-11735, -25163), a(-9279, 13494), a(-11901, -23094), a(-8716, -7530), a(-9083, 11173), 
          a(-8989, -14085), a(-12176, 12573), a(-9705, 9417), a(-9505, -30062), a(-8957, -5197), a(-10158, -31509), a(-12193, 763), a(-9554, -22797), a(-8628, 31211), a(-11855, -21578), 
          a(-9283, -15158), a(-9516, -20692), a(-10559, 30604), a(-8758, 20656), a(-9140, -11603), a(-9358, -7879), a(-8893, -6541), a(-11289, -16161), a(-12287, 18198), a(-11992, 24684), 
          a(-10530, 8665), a(-11959, 9715), a(-12234, 24763), a(-11390, 24212), a(-9342, 12490), a(-11353, -25257), a(-9203, 8385), a(-10264, 11250), a(-9552, -22409), a(-9309, -18312), 
          a(-10681, 8310), a(-11933, 1705), a(-12214, 10987), a(-11665, 12289), a(-9740, -7432), a(-11629, 15255), a(-10063, -5145), a(-9507, 21001), a(-10153, -21660), a(-8431, 14771), 
          a(-12017, 4883), a(-8361, 4410), a(-8645, 26413), a(-11711, -2841), a(-8227, 6408), a(-9932, 17953), a(-11962, 32101), a(-10525, 8257), a(-11282, 6632), a(-12037, -16869), 
          a(-9457, 20192), a(-9591, 4358), a(-9426, -17573), a(-10579, 11620), a(-11501, -11544), a(-8358, 20423), a(-11327, -22502), a(-9653, -30856), a(-11427, 17392), a(-9522, 25388), 
          a(-9615, -31474), a(-11451, -3652), a(-9879, -17630), a(-12098, -18174), a(-11670, -21753), a(-8936, -27047), a(-10669, 19877), a(-9169, 6435), a(-9117, 30305), a(-9826, -605), 
          a(-9844, -27220), a(-8809, 26714), a(-9691, 25915), a(-12175, 29884), a(-8450, 32240), a(-8942, -18114), a(-8586, 16981), a(-9024, 24317), a(-10239, -17232), a(-11699, 15029), 
          a(-10238, 9670), a(-8778, 13489), a(-8614, 29385), a(-8558, 5830), a(-8347, -20117), a(-9732, 31007), a(-11563, -15024), a(-8759, 14985), a(-10042, -20568), a(-11603, -7785), 
          a(-9472, 19330), a(-8277, 3342), a(-12089, -32330), a(-10503, -10397), a(-9643, 18988), a(-8509, 25225), a(-8399, 19094), a(-11610, -29974), a(-8505, 18983), a(-9524, 11046), 
          a(-9027, 31418), a(-10003, -16532), a(-9012, 32258), a(-10197, -12212), a(-9608, 31141), a(-10389, -19559), a(-9147, -9938), a(-9225, -7941), a(-8678, -30804), a(-12198, -18698), 
          a(-11492, -1811), a(-10518, 19813), a(-10056, -3511), a(-12206, -3255), a(-8599, -8789), a(-8197, 376), a(-10571, -29607), a(-11831, 30174), a(-10109, -31159), a(-11275, -14769), 
          a(-10164, -13909), a(-11757, 15618), a(-9671, -10631), a(-9421, -19678), a(-10683, -995), a(-9884, 27367), a(-9669, 14987), a(-11862, -5062), a(-11913, 4705), a(-9946, -10138), 
          a(-10183, 29426), a(-8265, -13536), a(-10445, 2785), a(-11789, -11170), a(-10032, -193), a(-11386, -22447), a(-11721, -27016), a(-10102, -22303), a(-8682, -10525), a(-10506, -9445), 
          a(-8734, 6110), a(-12203, -16357), a(-11536, -22429), a(-9699, 20290), a(-11329, -2469), a(-12003, -14095), a(-8798, -21730), a(-9319, -13278), a(-11268, 19554), a(-9474, 14564), 
          a(-8870, 26811), a(-9295, 11564), a(-9130, 32555), a(-10393, 26846), a(-11290, -3510), a(-10466, -28595), a(-9062, -24885), a(-9273, 2232), a(-9771, 4790), a(-11297, -18242), 
          a(-12245, -16901), a(-9272, 7145), a(-10299, 12802), a(-11607, 26616), a(-11963, -14968), a(-10124, -10868), a(-11866, 7231), a(-8872, -5380), a(-8810, 10458), a(-9258, 5554), 
          a(-10051, -21419), a(-11753, 22199), a(-10673, 1), a(-8993, 196), a(-10741, -29951), a(-11718, 1016), a(-10297, -17428), a(-9000, -15117), a(-8785, -12868), a(-12030, 9660), 
          a(-10258, 29155), a(-9484, -6515), a(-11852, 19130), a(-8898, -3294), a(-11692, 27428), a(-10037, 8570), a(-12051, -31833), a(-9864, -32518), a(-11611, -31053), a(-9277, -12428), 
          a(-9666, 19838), a(-10425, 12482), a(-11760, 9885), a(-9827, 5328), a(-11490, 20140), a(-8892, -14981), a(-8756, -9924), a(-8266, 19747), a(-8827, 27298), a(-9359, 25489), 
          a(-10053, -17213), a(-10653, 2291), a(-11989, -2730), a(-9411, 25449), a(-9232, -16030), a(-9200, -2022), a(-9541, 28960), a(-10379, -26460), a(-10372, 15704), a(-9328, 10304), 
          a(-12129, 16643), a(-9492, -30604), a(-11669, -19280), a(-8879, -4262), a(-8577, 31451), a(-8267, -28709), a(-10548, 7131), a(-9843, -5204), a(-8984, -27622), a(-12188, 14946), 
          a(-10146, -7422), a(-8471, -3673), a(-8944, -22131), a(-12268, -21831), a(-9780, -12155), a(-11475, 5634), a(-10748, -11415), a(-10465, 29827), a(-8686, 6680), a(-12091, -9054), 
          a(-8602, -8882), a(-11581, -8317), a(-8749, 8523), a(-10565, 3989), a(-11298, -13818), a(-9757, -21065), a(-12280, 25798), a(-11935, 10189), a(-9263, -22865), a(-9138, -24264), 
          a(-12259, -23974), a(-8425, -11889), a(-8837, 8453), a(-9093, -21780), a(-10650, -9481), a(-10558, -20195), a(-8811, -14937), a(-11281, 28037), a(-10105, 18992), a(-9069, -21882), 
          a(-11465, -17485), a(-8402, -18716), a(-10421, -25823), a(-8444, -5541), a(-9728, 30885), a(-8688, 10757), a(-11729, -9953), a(-9670, 19746), a(-10420, 16161), a(-9644, -22591), 
          a(-11274, 22606), a(-9954, 343), a(-10007, -25199), a(-10667, -26641), a(-9246, 14670), a(-8568, -24775), a(-10699, -9745), a(-8421, 8120), a(-8261, 25696), a(-9781, -13780), 
          a(-8888, -31640), a(-8495, -21478), a(-9727, -17862), a(-9188, 20372), a(-11771, -17156), a(-10684, -16186), a(-9851, -10911), a(-10039, 19543), a(-11884, -2756), a(-10626, -5217), 
          a(-9682, 16845), a(-9400, -25462), a(-8327, -43), a(-10060, 14436), a(-11785, 24151), a(-8214, -1510), a(-9650, 9304), a(-9420, 5126), a(-9341, -4271), a(-8812, -19350), 
          a(-9810, -19589), a(-10235, 18487), a(-8434, -19523), a(-11911, -18529), a(-10545, 4965), a(-10094, -25714), a(-11854, -7724), a(-9665, -17097), a(-12099, -8069), a(-10206, -29473), 
          a(-10270, 23773), a(-9517, 29149), a(-8454, 12589), a(-9738, -31865), a(-11476, 9998), a(-10104, -6528), a(-10657, 22129), a(-8457, 24347), a(-9136, -17765), a(-11574, -29115), 
          a(-12157, -5739), a(-11577, 19895), a(-10668, -4295), a(-8511, 18365), a(-10026, 1404), a(-8538, 22817), a(-8206, 3127), a(-12033, 31010), a(-9049, -29215), a(-9032, -1450), 
          a(-11720, 26337), a(-8211, 11092), a(-11657, -1468), a(-10617, 28605), a(-11890, 12933), a(-9786, 17890), a(-12243, -21054), a(-11797, 6906), a(-12194, -16327), a(-10612, -7389), 
          a(-9187, -32123), a(-10507, 23675), a(-9687, -18630), a(-9686, -10919), a(-9624, 10717), a(-12008, 10230), a(-11573, 29009), a(-9836, 6177), a(-11917, -18552), a(-11306, -4218), 
          a(-12061, -17272), a(-8684, -11857), a(-8213, -25742), a(-8302, 29233), a(-12133, -3524), a(-12241, -8870), a(-10408, -7613), a(-11939, -23518), a(-9089, 854), a(-8795, 1711), 
          a(-10385, -22325), a(-9260, 19514), a(-8895, 24438), a(-9355, -1476), a(-12056, 18174), a(-10593, 19097), a(-9858, -16301), a(-11909, 5483), a(-10591, -30251), a(-9447, -26117), 
          a(-11547, -23805), a(-8910, 5623), a(-9134, -17593), a(-9164, 10981), a(-8363, 17424), a(-8432, 21918), a(-8819, -11492), a(-12197, -21536), a(-10607, -9823), a(-9927, 1393), 
          a(-9940, -4238), a(-11815, -28032), a(-11751, -3053), a(-10409, -1839), a(-8659, 6193), a(-8619, -26187), a(-8529, -18740), a(-8974, 14765), a(-11954, -31253), a(-10041, -25633), 
          a(-8903, 22058), a(-8517, -25535), a(-10734, 28352), a(-11528, 31180), a(-9168, 13192), a(-9065, -17837), a(-11521, 15625), a(-8631, -26389), a(-8335, -11879), a(-10304, -15869), 
          a(-11500, -27771), a(-8693, 29142), a(-9711, -2867), a(-11975, -11960), a(-11341, -8959), a(-12081, 22339), a(-11478, -4493), a(-8298, -19051), a(-9599, 30740), a(-9557, 5436), 
          a(-9568, -16103), a(-8737, -23211), a(-9683, 32370), a(-9429, 59), a(-12121, -17833), a(-11485, 13078), a(-11482, -16442), a(-8998, 32496), a(-11743, -23348), a(-11853, 17152), 
          a(-9315, -3884), a(-10585, 14963), a(-11659, 19965), a(-11616, -19366), a(-8521, -11521), a(-11371, -12899), a(-8727, -984), a(-12063, -23045), a(-9723, 30721), a(-10291, 8958), 
          a(-9281, 28852), a(-9949, 7042), a(-11845, 22290), a(-8579, 30066), a(-11532, 24944), a(-8650, 14237), a(-11441, -26338), a(-10656, -19030), a(-10048, 32676), a(-8953, 5662), 
          a(-11749, -22395), a(-9865, 26947), a(-11974, 2465), a(-8657, -22647), a(-8941, -15550), a(-12026, 28842), a(-9087, -9480), a(-10222, -21551), a(-10223, -15406), a(-11776, -4481), 
          a(-9821, -23495), a(-10532, -2824), a(-11633, 2251), a(-8658, -30632), a(-9606, 24849), a(-9933, 19890), a(-9307, -2339), a(-8899, -21520), a(-8663, 16987), "a", 
          a(-10622, -1958), a(-9351, 465), a(-8972, -19745), a(-9386, 21177), a(-10655, -7489), a(-8217, -26499), a(-8950, 11696), a(-11559, -21374), a(-8831, -25788), a(-9977, -5481), 
          a(-12024, 25012), a(-10736, 1426), a(-10398, 7606), a(-10752, -2872), a(-11696, -30829), a(-10059, -8175), a(-8708, 12171), a(-9929, 22258), a(-8231, -29266), a(-11658, -30010), 
          a(-11903, 31371), a(-10182, 23213), a(-8643, 4915), a(-9515, -19907), a(-10247, -1482), a(-8209, 29738), a(-12190, 16013), a(-10520, -6715), a(-9063, -28280), a(-12036, 7877), 
          a(-10541, 29916), a(-10540, 25297), a(-8644, 27630), a(-11902, -14237), a(-8887, 5893), a(-11551, 30901), a(-8832, 10031), a(-11761, 29064), a(-9173, 26840), a(-9443, -29864), 
          a(-8868, 15648), a(-8502, 15694), a(-12145, -25375), a(-11881, -28584), a(-9526, 10120), a(-10716, -22268), a(-9278, -30121), a(-11472, 992), a(-9613, -19733), a(-9248, -20852), 
          a(-9641, -7137), a(-9527, -17247), a(-9022, -28968), a(-10685, -31770), a(-10068, 11346), a(-11941, -10380), a(-9922, 24501), a(-10403, -6617), a(-11602, -18895), a(-9082, 26165), 
          a(-9593, 737), a(-9797, -10918), a(-9755, -439), a(-9903, -29735), a(-11283, -8897), a(-10301, -12189), a(-8780, 10869), a(-9888, 103), a(-9562, -31916), a(-10047, -23284), 
          a(-10074, -4722), a(-8830, 14553), a(-9886, 22461), a(-9794, 20822), a(-10583, 28812), a(-8527, 24465), a(-8777, 31077), a(-9704, -8469), a(-8248, -22998), a(-12174, 17295), 
          a(-11488, -3423), a(-9052, 31945), a(-11714, 9580), a(-11782, -16702), a(-10000, -12617), a(-11432, -7937), a(-10298, 10945), a(-11434, 21705), a(-8364, -5857), a(-11957, -30057), 
          a(-9592, 18930), a(-9971, 5838), a(-10549, 23321), a(-9439, 23194), a(-8447, -2476), a(-12196, -11289), a(-11369, -24677), a(-11548, -15413), a(-9141, 18466), a(-9327, 29228), 
          a(-8762, 31074), a(-9214, 2995), a(-10572, 3865), a(-12031, 29925), a(-9620, -16369), a(-9485, -31456), a(-10043, -21609), a(-8569, -30450), a(-10609, -27860), a(-9067, 29100), 
          a(-9123, 28846), a(-8670, -2278), a(-8707, 18548), a(-9048, 31994), a(-8240, -3673), a(-12060, -4534), a(-11912, -4084), a(-9470, -8117), a(-10085, 26462), a(-11791, -22156), 
          a(-11916, 1505), a(-9185, -83), a(-9912, 27923), a(-10067, -16589), a(-8336, 31824), a(-11342, -10026), a(-9802, -17661), a(-8661, 17047), a(-12202, 28098), a(-9239, -27064), 
          a(-9110, -2591), a(-11690, -8884), a(-11885, 1497), a(-8852, -1692), a(-9642, -29624), a(-9830, -27917), a(-8980, -26251), a(-10128, 9652), a(-10557, 14276), a(-11305, -23058), 
          a(-9014, -27629), a(-9979, 6427), a(-9360, -23635), a(-9770, 16012), a(-10688, 27849), a(-9129, 30951), a(-11426, 29333), a(-10468, 22856), a(-12232, 4706), a(-11900, -26068), 
          a(-8414, 480), a(-11801, -20262), a(-9414, 9642), a(-11294, 13873), a(-8313, 10903), a(-11646, -18189), a(-8728, -390), a(-8641, -10802), a(-10418, -25958), a(-8304, 27509), 
          a(-9811, -3186), a(-8230, -13077), a(-11844, -19145), a(-9482, -21430), a(-8633, -30875), a(-8838, 6609), a(-9842, -4764), a(-9330, -28192), a(-11513, -29003), a(-11562, -1356), 
          a(-8983, -8210), a(-9856, 16619), a(-9508, -12828), a(-11484, 13784), a(-11710, -30054), a(-10430, -1057), a(-9056, -24404), a(-8381, -1446), a(-11491, -31404), a(-11615, -29544), 
          a(-9863, 2866), a(-8731, -2262), a(-10181, -21600), a(-9118, 28167), a(-9553, -12880), a(-10719, -29835), a(-8912, -20685), a(-10703, 666), a(-10024, -28771), a(-9237, -12701), 
          a(-8301, -5057), a(-10066, 5846), a(-10680, 26274), a(-9158, -2662), a(-9998, 20002), a(-8333, -127), a(-10018, 12895), a(-8981, -2509), a(-9948, -16446), a(-9695, 29349), 
          a(-12228, -25914), a(-10163, 12122), a(-8314, -29049), a(-9435, -21882), a(-12254, -26396), a(-12271, 24763), a(-11867, 16575), a(-10065, 21489), a(-9829, -13095), a(-12148, -7949), 
          a(-8806, -14440), a(-8585, 4696), a(-8781, -23126), a(-11554, 23844), a(-8866, 26448), a(-9060, 16919), a(-10469, -31310), a(-8273, 15971), a(-10600, -5840), a(-8332, 25722), 
          a(-12252, -1456), a(-12189, -15407), a(-11840, -14013), a(-9305, -24349), a(-10199, -9944), a(-9495, -2115), a(-9142, -31334), a(-11928, -11192), a(-10588, -15832), a(-9301, 20117), 
          a(-9053, 12305), a(-8490, 24527), a(-8270, -12188), a(-9461, 18574), a(-8419, 9544), a(-11683, 28806), a(-11448, -29803), a(-9951, -19661), a(-12046, 16551), a(-8884, -2430), 
          a(-11473, 22213), a(-12159, -26642), a(-11361, 12514), a(-11360, -25109), a(-8775, 6621), a(-12217, 31366), a(-9627, 9821), a(-12278, -16983), a(-9016, 26119), a(-9551, 16402), 
          a(-8353, 3998), a(-10570, -1886), a(-8597, -4464), a(-8531, -16912), a(-9090, -12026), a(-9172, 21259), a(-12040, -16799), a(-8850, -23109), a(-11803, 3933), a(-10221, 10454), 
          a(-10107, -12651), a(-9373, -15720), a(-10255, -28733), a(-8280, 5656), a(-10691, 25278), a(-10025, -23789), a(-10303, 22831), a(-12255, 9631), a(-9817, -14750), a(-10584, -6223), 
          a(-8965, 23570), a(-11337, -13535), a(-10606, 27387), a(-9046, -31692), a(-8258, 7484), a(-8234, -27975), a(-9377, -25628), a(-11940, 11032), a(-8355, -123), a(-8964, 10179), 
          a(-9458, 22936), a(-9487, 24534), a(-8282, 24833), a(-12058, -7792), a(-10712, -28430), a(-11847, -1963), a(-10071, 8749), a(-12178, 24920), a(-11682, 32119), a(-9581, -32629), 
          a(-12062, 5259), a(-11277, -13347), a(-8672, 4216), a(-9545, 25001), a(-10217, 18141), a(-12224, -18736), a(-11619, -3528), a(-10467, -20007), a(-8717, -18357), a(-9252, -13371), 
          a(-10261, 17349), a(-9002, -28016), a(-10138, 11595), a(-8613, -4830), a(-8461, -6510), a(-8535, 5921), a(-11384, 16413), a(-8541, 21105), a(-8288, -21995), a(-11907, -25195), 
          a(-8673, 15817), a(-9918, -18452), a(-12258, 18471), a(-9153, -6250), a(-9303, -31487), a(-8257, 17935), a(-8883, -8909), a(-9659, 9936), a(-10115, 12839), a(-11589, -5584), 
          a(-11486, 8985), a(-11556, -717), a(-12029, 1204), a(-9840, 25727), a(-9714, -9736), a(-9385, -19953), a(-9716, 1625), a(-11316, -6824), a(-11709, 18907), a(-8704, -17875), 
          a(-9347, 7098), a(-8938, -1576), a(-9975, -9643), a(-9978, -22476), a(-8648, -3599), a(-10643, 32145), a(-8317, 23163), a(-10473, -30440), a(-8252, 7641), a(-10411, 30104), 
          a(-8729, -28115), a(-11506, -17636), a(-10470, 7979), a(-12054, 22326), a(-9871, -31742), a(-10150, -3696), a(-8256, -9585), a(-10233, 8145), a(-11525, 24554), a(-8878, -31161), 
          a(-10555, 27468), a(-10172, 4532), a(-9395, 23978), a(-12004, 21989), a(-11739, 23729), a(-12179, -29387), a(-12177, 11400), a(-11822, 16945), a(-10531, 9632), a(-10269, 21896), 
          a(-11651, 12996), a(-9399, -27944), a(-11464, -27178), a(-12239, -27273), a(-9622, -8559), a(-9166, -24592), a(-10439, -14937), a(-10512, -10437), a(-11856, 22508), a(-8649, -1897), 
          a(-11790, -17504), a(-8430, -17384), a(-12006, -22408), a(-11395, 27317), a(-9547, 12358), a(-9899, -23839), a(-9285, -8963), a(-10397, 26564), a(-12283, -2520), a(-11631, -10708), 
          a(-11777, -13625), a(-10505, -7652), a(-8203, 2967), a(-8552, -13679), a(-9555, 24490), a(-10471, -27206), a(-11381, -14941), a(-11730, -1447), a(-10440, -14326), a(-10536, 9209), 
          a(-9823, -13442), a(-8594, -29456), a(-11544, -18065), a(-11915, 23597), a(-9040, 4549), a(-10002, -32488), a(-11656, 12892), a(-12048, -12584), a(-10078, -21630), a(-12136, -25384), 
          a(-9282, 21674), a(-9753, -4379), a(-9953, 19612), a(-9729, 10116), a(-9980, 15284), a(-9189, -11028), a(-10090, 18954), a(-10020, -29211), a(-10416, -25747), a(-11367, 24278), 
          a(-9499, 29034), a(-9762, -541), a(-9573, -13840), a(-8786, -23137), a(-11323, 1362), a(-9789, 3802), a(-9361, -16042), a(-11273, 19845), a(-8703, 31994), a(-8554, -12431), 
          a(-8792, 17844), a(-10542, 5415), a(-9367, 4888), a(-10490, 13784), a(-9007, -22686), a(-11630, -9401), a(-9473, 17322), a(-9571, 10397), a(-8272, 29473), a(-10076, -804), 
          a(-10690, -5445), a(-12090, 2370), a(-9799, -11736), a(-10443, -32329), a(-12187, -2171), a(-8479, 20297), a(-12068, -9507), a(-9565, 19158), a(-8928, 18252), a(-8757, -13382), 
          a(-11301, 24420), a(-9750, -23153), a(-10450, -6611), a(-8671, 25698), a(-9448, 28093), a(-9163, -17469), a(-11755, -9269), a(-9768, -10408), a(-9910, -24311), a(-10491, -13439), 
          a(-9274, -7518), a(-11597, 23926), a(-8934, -24048), a(-11702, -13031), a(-12139, -30261), a(-8567, -11945), a(-8817, 7522), a(-10038, 20088), a(-8547, -26584), a(-8300, -9898), 
          a(-9498, -5098), a(-11655, -29507), a(-9924, 9187), a(-11431, -10970), a(-10004, 20720), a(-9532, -14421), a(-10569, 19674), a(-8497, -16082), a(-8334, 9156), a(-9160, 1156), 
          a(-9392, 22570), a(-9743, 22974), a(-11543, 19133), a(-10605, -8616), a(-10616, -18256), a(-10250, 31505), a(-8917, 24345), a(-10417, -10427), a(-11383, 28541), a(-11288, -17405), 
          a(-9437, -4502), a(-8293, 20112), a(-11804, 12163), a(-8307, 10825), a(-10179, -10711), a(-11272, 24780), a(-9920, -4823), a(-12208, 2510), a(-10671, 27057), a(-10730, -3489), 
          a(-11648, -18665), a(-10615, 25124), a(-12002, -9675), a(-11772, -12690), a(-12118, -8379), a(-8754, -29944), a(-11410, -32178), a(-11635, 22334), a(-11810, 28171), a(-11814, -22467), 
          a(-8582, -22425), a(-11539, -10608), a(-10267, -11310), a(-9596, 16468), a(-9681, -8963), a(-9528, -25950), a(-10476, -21355), a(-12221, -15864), a(-9313, 4405), a(-9433, 1921), 
          a(-10568, 11861), a(-8389, -22957), a(-10006, -26578), a(-10423, 1876), a(-10147, -3662), a(-11985, -19510), a(-8458, 11492), a(-11568, 11069), a(-12225, -26686), a(-8483, -7859), 
          a(-11538, -13649), a(-9150, 26203), a(-10500, 14915), a(-11792, 4281), a(-10118, 19429), a(-10064, 28910), a(-9026, 1935), a(-9862, 26279), a(-11300, 23985), a(-8863, -20741), 
          a(-8269, -21203), a(-9788, -26883), a(-9700, 11039), a(-12199, 9957), a(-12211, 15405), a(-8481, 1925), a(-12108, 15321), a(-9254, -13165), a(-9424, 17223), a(-9629, -5462), 
          a(-8855, -7283), a(-8409, 16280), a(-11972, -3066), a(-8404, 15908), a(-8835, 712), a(-8676, -19565), a(-8622, -24556), a(-10678, 6702), a(-8312, 29308), a(-11571, 14970), 
          a(-9128, -14555), a(-9928, -13719), a(-10481, 14159), a(-9334, -24899), a(-8403, -20741), a(-9109, 17147), a(-9915, -24577), a(-11858, 30475), a(-9796, -4027), a(-11983, 13267), 
          a(-8220, 11916), a(-12111, -25591), a(-11398, -12749), a(-8294, 22516), a(-9388, -20056), a(-9767, 22396), a(-12257, 22996), a(-10093, 26601), a(-11674, 29562), a(-11938, 4042), 
          a(-8279, -9056), a(-9772, -19288), a(-9287, -24128), a(-9205, -13118), a(-11567, 9340), a(-8923, 15382), a(-8966, 18252), a(-11991, -3787), a(-11805, 1154), a(-11477, -17260), 
          a(-8416, -8301), a(-8322, 13002), a(-11639, -1231), a(-10045, 9340), a(-11387, -27473), a(-12005, 24598), a(-8695, 18543), a(-8694, -13748), a(-12165, -16319), a(-8372, 24185), 
          a(-10246, -32590), a(-11643, -27370), a(-10581, 12633), a(-11479, 4847), a(-10647, 25820), a(-12009, 5967), a(-9896, -26934), a(-9625, 12069), a(-12103, 29707), a(-9839, -18998), 
          a(-11552, -24762), a(-11541, -27716), a(-11494, 10653), a(-8371, 18676), a(-11591, 18652), a(-9965, -22738), a(-9459, 28604), a(-12021, -7785), a(-8278, -8559), a(-11576, 10164), 
          a(-10030, 28302), a(-9455, 14732), a(-10149, 17420), a(-8725, -3597), a(-9777, 1114), a(-11392, -21203), a(-11662, -15158), a(-11632, -30060), a(-9050, -21297), a(-11440, 29296), 
          a(-8814, -28737), a(-12223, -9037), a(-8736, -29761), a(-10122, 14264), a(-10618, -32179), a(-9876, -288), a(-11407, -4402), a(-10400, -20748), a(-11592, 234), a(-10603, -32210), 
          a(-9533, 16521), a(-9809, -9269), a(-11979, 21825), a(-8859, 24328), a(-9469, -203), a(-12216, 26709), a(-11679, -20926), a(-10449, 7887), a(-9504, -21968), a(-10171, 700), 
          a(-8348, 30386), a(-8685, -7288), a(-10200, 1932), a(-11608, -26617), a(-10611, -26291), a(-12171, 27991), a(-12274, -32081), a(-10582, -21981), a(-10005, -21646), a(-11756, 27847), 
          a(-9604, 3510), a(-8927, 7806), a(-12125, 14968), a(-10454, 20493), a(-9795, -3656), a(-10463, -18419), a(-12150, -28534), a(-8325, 1357), a(-9365, 3262), a(-12222, -31270), 
          a(-9028, -9872), a(-8524, -10818), a(-12067, 1231), a(-10535, 20825), a(-10040, 811), a(-12066, 14457), a(-9628, 26543), a(-8920, 24818), a(-10378, 25319), a(-11681, 30758), 
          a(-10718, 7766), a(-10399, -23386), a(-8448, 28601), a(-12167, 11335), a(-9243, -1095), a(-9318, 9426), a(-10456, 4894), a(-8823, 12320), a(-11829, -6256), a(-9267, -16301), 
          a(-8891, -8077), a(-11409, 15507), a(-10489, 4859), a(-10198, -16489), a(-10166, 13128), a(-9407, 19358), a(-8880, -21262), a(-9761, -30594), a(-11997, -22903), a(-10715, -19588), 
          a(-12265, -5421), a(-12140, -21766), a(-8346, 12708), a(-9775, 12993), a(-8803, -21139), a(-12137, -928), a(-8804, 2695), a(-8744, 23416), a(-10574, 7726), a(-10621, -12158), 
          a(-9199, 31974), a(-9651, 10264), a(-8955, 4040), a(-9664, -21918), a(-10640, -26199), a(-10069, -23257), a(-10714, 4644), a(-8743, 19899), a(-11707, -26970), a(-12155, 20911), 
          a(-8408, -18028), a(-9639, 5264), a(-10141, -18953), a(-10058, -32374), a(-10426, -688), a(-9444, -12898), a(-9635, -9652), a(-9132, 1398), a(-8926, 18497), a(-9897, -18724), 
          a(-8493, -16831), a(-11700, 11997), a(-12212, -15314), a(-9784, 29935), a(-12047, -31666), a(-8581, 11215), a(-9422, -8046), a(-8987, -2392), a(-9966, 4515), a(-11750, 12394), 
          a(-11947, -16626), a(-11738, 9941), a(-10023, -22403), a(-12250, -9149), a(-9013, -18261), a(-8573, -15248), a(-11762, -12711), a(-11336, 2669), a(-10494, 14200), a(-11897, -30801), 
          a(-10100, 15908), a(-10654, -15106), a(-9146, 138), a(-10509, -21645), a(-10402, -4791), a(-9969, -22989), a(-10176, 20644), a(-10114, -3193), a(-10054, 20208), a(-11664, 4599), 
          a(-11988, 18617), a(-10637, -17451), a(-8290, 3730), a(-11859, 4435), a(-9917, 28215), a(-8848, 28061), a(-8894, -31895), a(-8561, 28070), a(-9249, 6730), a(-11557, 12132), 
          a(-8889, -21150), a(-11865, -23645), a(-10165, 9156), a(-11878, -30746), a(-8949, 2573), a(-11723, 1580), a(-8507, 31189), a(-8689, 1159), a(-8789, 357), a(-11293, -21017), 
          a(-9370, 10889), a(-10475, -2737), a(-11689, -16737), a(-9783, -32619), a(-9776, -1753), a(-10639, -27353), a(-11816, 16216), a(-9276, -31362), a(-9405, -2638), a(-10577, 31035), 
          a(-10126, -32622), a(-11437, 15741), a(-8344, 742), a(-11545, -6215), a(-8807, -16340), a(-10528, 2624), a(-12272, -18444), a(-11583, -19223), a(-8433, -24175), a(-9159, 5557), 
          a(-8822, -13076), a(-8406, -1935), a(-8746, -8448), a(-8909, -14453), a(-10226, 22920), a(-12227, -21533), a(-11498, -25739), a(-8196, -28713), a(-8698, 13004), a(-9004, 6200), 
          a(-11375, 13106), a(-9782, 1623), a(-9340, -11613), a(-8767, 12348), a(-9667, -27860), a(-9746, 31925), a(-9931, -22554), a(-10001, 3850), a(-11529, -10836), a(-9356, -3924), 
          a(-10192, 26298), a(-9961, 16028), a(-8764, 6566), a(-12109, 24317), a(-8590, -17761), a(-12135, 14424), a(-9198, 628), a(-11794, 4917), a(-10013, -4445), a(-11516, -14272), 
          a(-10677, 3217), a(-10488, 4555), a(-9749, 29693), a(-10524, 22905), a(-10563, -7292), a(-10154, 4685), a(-8343, 17505), a(-10211, -8298), a(-11285, -8251), a(-8330, -3179), 
          a(-10220, 5365), a(-11944, -153), a(-12144, -31861), a(-8242, -25433), a(-12149, -1123), a(-9241, -20364), a(-9149, 11377), a(-12183, 7036), a(-8692, 7919), a(-8306, -5268), 
          a(-11922, 5772), a(-10575, 7513), a(-9710, -8289), a(-10195, -13726), a(-11823, 208), a(-9015, 15815), a(-8876, 27870), a(-8226, 17004), a(-8526, 23858), a(-10112, 18375), 
          a(-12100, 18384), a(-8463, -2347), a(-11601, 26609), a(-8691, 17910), a(-10458, -5405), a(-8609, 26383), a(-9323, -10305), a(-11827, -14638), a(-11466, 23348), a(-11349, -27739), 
          a(-10554, 31332), a(-9005, -28738), a(-10087, 5671), a(-9368, -9853), a(-11701, -18156), a(-9266, 5352), a(-10152, 7242), a(-12248, 25992), a(-9992, -11033), a(-10374, 22199), 
          a(-9466, 25484), a(-9345, 5630), a(-10461, 14528), a(-9950, -29030), a(-10539, 29563), a(-8720, -24971), a(-11493, -7862), a(-9293, -13645), a(-10099, 11163), a(-9763, -21983), 
          a(-11499, 26371), a(-11650, 4092), a(-9506, -22094), a(-10062, 26040), a(-11731, -8787), a(-9436, 9845), a(-11397, 7126), a(-10459, 29493), a(-10729, -4689), a(-9379, 30687), 
          a(-9996, 20818), a(-8960, 8100), a(-11861, 13272), a(-12269, -22937), a(-9425, -9809), a(-8935, 5049), a(-10227, -26049), a(-9893, 3854), a(-11951, -25304), a(-9480, 26349), 
          a(-9602, 24025), a(-11685, -15271), a(-9560, -31616), a(-11509, -22777), a(-8436, -6764), a(-9010, -20503), a(-8653, -25939), a(-8843, -7239), a(-11450, -8813), a(-11511, -4688), 
          a(-10472, -20753), a(-9544, 7662), a(-9855, -3448), a(-10410, 17047), a(-9210, 17010), a(-9389, 24606), a(-8961, 10759), a(-8748, -20973), a(-9394, -31690), a(-12185, 10706), 
          a(-8467, 30190), a(-11775, -13500), a(-8382, 17847), a(-10173, 14395), a(-11697, -2125), a(-9211, -16253), a(-9009, 21342), a(-11894, -372), a(-10229, 21857), a(-8250, 1581), 
          a(-11394, 25343), a(-11960, 23817), a(-9162, 7673), a(-8647, 11346), a(-8446, 1010), a(-11292, -14008), a(-10096, -12260), a(-9031, 14672), a(-9719, -811), a(-8623, 31586), 
          a(-10596, 21545), a(-9018, 10746), a(-11419, -3593), a(-8906, 31643), a(-9626, 1708), a(-10017, -2819), a(-10728, 15613), a(-9156, -7837), a(-12170, 22056), a(-12286, -1675), 
          a(-10692, 15318), a(-9179, 28603), a(-11906, 14923), a(-10144, -3377), a(-9849, 2935), a(-8591, 5884), a(-11318, -2169), a(-11405, -3849), a(-9369, 1073), a(-9736, 31745), 
          a(-11869, 19647), a(-8902, 11405), a(-8418, 19980), a(-8947, -24809), a(-10240, -17954), a(-12279, 12564), a(-10462, 30717), a(-9967, -29787), a(-10726, -32525), a(-9103, 26341), 
          a(-10608, 7786), a(-9391, -29616), a(-9887, 13824), a(-10747, 25633), a(-8360, 10803), a(-9202, 21376), a(-9101, -6968), a(-8460, 26516), a(-11961, 22511), a(-9393, 23168), 
          a(-8914, -3988), a(-10447, -26740), a(-9709, -7024), a(-10698, 9087), a(-10175, -24577), a(-10391, -19061), a(-8797, -28345), a(-9227, -7285), a(-11824, 17247), a(-8973, 51), 
          a(-11614, 22601), a(-10733, 1790), a(-9291, -15642), a(-8763, 16063), a(-8549, -6583), a(-9275, -26549), a(-12226, -16453), a(-9904, 31067), a(-8501, 30281), a(-8299, 20394), 
          a(-9543, 16758), a(-9375, -31354), a(-9450, 26193), a(-8396, 24041), a(-9561, -20497), a(-11628, 3403), a(-10086, -3234), a(-10225, 20153), a(-9096, 22408), a(-11540, 19760), 
          a(-10210, 3996), a(-9064, -10803), a(-10666, 27641), a(-9742, -7102), a(-9401, 12931), a(-8303, 25302), a(-11572, -17171), a(-8410, 4280), a(-10272, 15657), a(-8701, 7860), 
          a(-10674, -20605), a(-9181, -15389), a(-11359, -17198), a(-8365, -16170), a(-8882, 5223), a(-10127, 16549), a(-12273, -14261), a(-8255, -29573), a(-11663, 17101), a(-8572, 7160), 
          a(-10567, -25684), a(-11873, 22940), a(-11965, -13957), a(-10455, 16721), a(-9094, -25419), a(-8760, 27875), a(-8913, 21127), a(-11425, -28450), a(-8437, 28542), a(-10711, 664), 
          a(-8331, 11403), a(-9230, -2520), a(-8570, 16681), a(-8834, -2238), a(-12209, -19050), a(-9068, -19487), a(-9798, 29516), a(-8986, 1705), a(-9693, 5756), a(-11672, -27040), 
          a(-10566, -30651), a(-12064, 30023), a(-10486, 26855), a(-10725, 25261), a(-10248, 21941), a(-10170, -10255), a(-11980, 29653), a(-8225, 32382), a(-10651, -27489), a(-11942, 17194), 
          a(-8263, 28431), a(-9023, -20819), a(-11456, 13620), a(-10257, -25254), a(-10031, 6492), a(-8515, -4448), a(-9588, 7444), a(-9869, -26402), a(-12207, -9859), a(-11877, 18848), 
          a(-11519, -4259), a(-10135, -12989), a(-10406, -24054), a(-8901, -2908), a(-9396, 1874), a(-10116, -19786), a(-12049, -30489), a(-10697, -17328), a(-8735, -1411), a(-10601, 32545), 
          a(-11649, 2371), a(-10460, 15582), a(-8251, 21355), a(-8702, -14714), a(-11430, 2248), a(-9073, 9100), a(-8379, 20975), a(-9895, 5813), a(-8583, -25973), a(-9036, 13754), 
          a(-8662, -10673), a(-11763, 23023), a(-8925, 16656), a(-8886, 17128), a(-9589, 10163), a(-8340, 12370), a(-11445, -13235), a(-8328, -1714), a(-10046, 23442), a(-11401, 13930), 
          a(-11783, -20185), a(-8877, -32604), a(-12010, -3129), a(-10564, -18314), a(-11578, 21922), a(-9427, -20873), a(-10157, 23371), a(-9070, -23580), a(-10101, 32333), a(-11317, 25547), 
          a(-9442, -14866), a(-8616, 16936), a(-8610, 11715), a(-10156, -21517), a(-10382, -122), a(-11356, 32399), a(-9184, -17887), a(-10658, -3456), a(-9316, -14363), a(-11849, -6385), 
          a(-8890, -30795), a(-8862, -22347), a(-8338, 27226), a(-8385, 10552), a(-8784, -3282), a(-10201, 21441), a(-11857, 12795), a(-12230, 9855), a(-9091, 3808), a(-9986, -11181), 
          a(-9832, 7247), a(-9985, -12393), a(-8620, 8058), a(-8407, 19953), a(-11637, -3540), a(-11864, -9474), a(-10498, 15035), a(-9193, 22233), a(-8367, -20612), a(-9362, 17047), 
          a(-8321, -32037), a(-9576, 6681), a(-8733, 316), a(-11924, 10676), a(-8232, 7897), a(-8710, 22689), a(-10034, 1570), a(-8241, -11681), a(-8954, -15930), a(-8254, -23275), 
          a(-12247, -10772), a(-9792, -16811), a(-11923, -16053), a(-9329, 28589), a(-10215, 27287), a(-8429, 21248), a(-9890, 13021), a(-9877, 26965), a(-8967, 7334), a(-11896, 17610), 
          a(-8636, 22380), a(-10493, -12886), a(-10562, -4915), a(-8337, 9103), a(-10533, -4229), a(-9774, -28380), a(-11973, 19477), a(-10230, -27008), a(-10219, -7246), a(-8851, 28264), 
          a(-9088, 5601), a(-10386, -30722), a(-8625, -2054), a(-9404, 18884), a(-8492, 15914), a(-9937, -11024), a(-9265, -25490), a(-8443, -9089), a(-12164, -12108), a(-11744, 10627), 
          a(-11990, 2101), a(-9808, 31693), a(-9186, 11307), a(-9751, -2369), a(-9100, 3886), a(-9631, -23766), a(-9510, -3747), a(-11993, 12411), a(-10234, -30345), a(-11357, -7188), 
          a(-8523, 25342), a(-8656, 18219), a(-11454, 6854), a(-9099, 3463), a(-11802, -469), a(-11330, 18067), a(-8847, 9359), a(-8519, -21113), a(-11818, 16609), a(-11389, 24384), 
          a(-9590, 4110), a(-8305, 16364), a(-10376, -14781), a(-11549, -29367), a(-10371, 22203), a(-11377, -23719), a(-9791, -5485), a(-10194, 8641), a(-11531, 10047), a(-11634, -5820), 
          a(-9739, 904), a(-9623, -31832), a(-11969, 21853), a(-11379, 4973), a(-9520, 4999), a(-8260, 26869), a(-8751, -9440), a(-9270, -3427), a(-8383, -22438), a(-12256, 11871), 
          a(-10452, 7681), a(-11948, 4080), a(-11331, 14112), a(-11605, -23554), a(-8651, 2046), a(-10188, -10222), a(-9942, -23103), a(-10707, -18465), a(-11754, -28823), a(-10242, 12789), 
          a(-10604, 23737), a(-8576, -26437), a(-12039, -3736), a(-8802, 22963), a(-9936, 19370), a(-8393, -20339), a(-9656, 17257), a(-11843, -14364), a(-9733, 3710), a(-9286, 14523), 
          a(-8896, -12305), a(-11645, 15506), a(-9550, 25036), a(-8776, -14937), a(-8842, 296), a(-10652, 1376), a(-10373, -579), a(-9481, 11948), a(-11622, -17486), a(-9378, 16971), 
          a(-12079, 25161), a(-8370, 15852), a(-9058, -12993), a(-8480, -22125), a(-10419, -3079), a(-9201, 28459), a(-8857, -29675), a(-10125, 30506), a(-8681, 15967), a(-8766, -18945), 
          a(-8687, 17637), a(-8994, 31954), a(-9071, 22736), a(-10599, -22695), a(-9059, 24829), a(-8705, -31712), a(-11530, -18472), a(-9605, 30860), a(-9779, 498), a(-11876, -17156), 
          a(-11654, 18079), a(-10527, 17819), a(-9894, -7729), a(-11372, 6050), a(-9165, -21083), a(-8907, -17169), a(-8841, 25792), a(-10590, 20707), a(-11312, -9347), a(-11606, 9515), 
          a(-9846, -31955), a(-8916, -18044), a(-12015, -31046), a(-8719, -24139), a(-10407, -12014), a(-11943, -17890), a(-11286, 24438), a(-9838, 21280), a(-9685, -23562), a(-8488, -1616), 
          a(-11328, -28859), a(-10502, -6008), a(-11680, 7006), a(-10035, -15070), a(-11704, 13020), a(-9288, 21886), a(-8562, 1214), a(-9677, 24593), a(-10477, 14196), a(-8861, -15306), 
          a(-9726, 9755), a(-11742, 16330), a(-9465, -15738), a(-9870, -4433), a(-9261, 9371), a(-8563, 13172), a(-10212, -10782), a(-8489, -26846), a(-9595, -32426), a(-11875, 17198), 
          a(-12253, 30550), a(-11550, -26384), a(-8592, 27825), a(-11925, 12139), a(-9582, -22690), a(-8635, 19306), a(-9222, 15423), a(-10253, 6540), a(-12016, 24912), a(-12213, -14785), 
          a(-11734, -25145), a(-10474, 19970), a(-11553, 8926), a(-9183, -21568), a(-10095, 13978), a(-9398, -17088), a(-10216, -17382), a(-10483, -16466), a(-9080, 22320), a(-9383, 4530), 
          a(-9706, 9565), a(-8655, 3935), a(-9491, 15745), a(-10682, 23431), a(-11438, -26586), a(-9785, -29397), a(-9145, -32693), a(-12236, -19690), a(-9610, -31080), a(-10556, -21972), 
          a(-8208, -31504), a(-11987, 14666), a(-11308, -31833), a(-11600, 18747), a(-9939, 23591), a(-8924, 27528), a(-8845, 23744), a(-10433, -6633), a(-10036, 32102), a(-11296, -31945), 
          a(-8904, 6250), a(-9983, 11492), a(-12119, -22956), a(-9916, 2003), a(-11695, -28946), a(-9633, -30359), a(-10746, -10462), a(-8992, 1755), a(-11809, -19477), a(-12000, 3151), 
          a(-10380, 20159), a(-9816, 3524), a(-11402, 31354), a(-8401, -29238), a(-11269, 29119), a(-8308, -6367), a(-8477, 26134), a(-8588, -1754), a(-8285, 2919), a(-9430, -22635), 
          a(-10110, -18330), a(-9913, -25148), a(-11315, 17287), a(-8963, -30947), a(-10642, -3789), a(-8428, -5626), a(-8536, -27036), a(-8790, -16240), a(-9542, 12643), a(-9982, 6263), 
          a(-9238, 10971), a(-10075, -6220), a(-8378, 30727), a(-11727, -22828), a(-9497, -31303), a(-8564, 25207), a(-12204, 6913), a(-10168, 10316), a(-11421, 10897), a(-8885, 4604), 
          a(-9025, -8176), a(-8849, 30086), a(-8391, -1438), a(-9607, 31708), a(-12172, -600), a(-9962, -3076), a(-9161, -31171), a(-9127, 4686), a(-11565, 25759), a(-9825, 3260), 
          a(-11588, -17864), a(-10204, 14265), a(-9834, 16642), a(-10679, -11890), a(-8999, 17577), a(-12231, 22934), a(-9081, 12976), a(-9678, -2880), a(-9672, -31094), a(-8534, 15616), 
          a(-11382, -29849), a(-9072, -13849), a(-9413, -12706), a(-11800, -1712), a(-8854, -3926), a(-12181, -10090), a(-8718, 4747), a(-11986, -5743), a(-11684, -20870), a(-8470, -14274), 
          a(-8683, -594), a(-10012, 13854), a(-9905, 12786), a(-9519, -19903), a(-8605, -16722), a(-8905, -18274), a(-10189, -12071), a(-9209, 12930), a(-12073, -11793), a(-9029, 9882), 
          a(-8975, -29047), a(-10098, 22441), a(-11468, 2348), a(-11826, -21956), a(-11458, -2224), a(-9586, -2215), a(-11463, -1830), a(-10015, -13980), a(-10184, -21941), a(-9621, -27884), 
          a(-8712, -17505), a(-12143, -28807), a(-10636, 19870), a(-9338, -17001), a(-9654, 11792), a(-9171, -13161), a(-8782, 8801), a(-8513, 21166), a(-8603, 14923), a(-11339, -24647), 
          a(-9721, 5096), a(-10492, 7998), a(-11958, 25701), a(-9228, -11642), a(-8604, -23208), a(-9213, 8838), a(-8544, -9604), a(-9698, -22496), a(-11667, 6621), a(-8487, -22465), 
          a(-10437, -24410), a(-9196, 9162), a(-11934, 12715), a(-8921, 9250), a(-9804, 12457), a(-9451, -4951), a(-10713, -16217), a(-11352, -23561), a(-12277, 31914), a(-8897, 14000), 
          a(-11673, -3192), a(-10428, -5275), a(-11825, -32264), a(-9697, -10225), a(-8908, -32158), a(-8341, -4841), a(-11333, -6075), a(-10245, 2347), a(-10022, -7560), a(-10224, -3929), 
          a(-8292, 14849), a(-9636, -29160), a(-11936, 6547), a(-11446, -10333), a(-9126, 14298), a(-9818, 12020), a(-9569, -14078), a(-11566, -31444), a(-11555, 25934), a(-9476, -5885), 
          a(-11653, -20765), a(-9814, 29682), a(-8236, 31599), a(-8199, 29149), a(-10384, -11885), a(-11502, 22918), a(-12019, -12389), a(-8945, -4229), a(-8640, -25617), a(-11781, -12808), 
          a(-10573, 10886), a(-9041, 4562), a(-11636, -22908), a(-11324, -32398), a(-9133, 24829), a(-11968, -24118), a(-11950, 23726), a(-8575, 11632), a(-11480, 24927), a(-8514, 18213), 
          a(-10207, -8153), a(-11604, -20385), a(-10630, 4638), a(-11765, 3249), a(-8738, 26386), a(-9725, 6974), a(-11558, 26311), a(-10251, 21834), a(-8709, -6324), a(-9348, -28974), 
          a(-8324, 4895), a(-11768, 20733), a(-9957, -16543), a(-9226, 28399), a(-11625, -3042), a(-11899, 14773), a(-9108, 26570), a(-10749, -5063), a(-11982, -3122), a(-9773, -30786), 
          a(-12113, 28445), a(-11671, 32201), a(-8566, -2635), a(-8667, -1539), a(-11612, 27998), a(-9973, -25654), a(-11535, -12345), a(-9559, 32131), a(-11455, -14800), a(-11741, -14073), 
          a(-11870, 14058), a(-9135, 9300), a(-10262, -24883), a(-11780, 19970), a(-9167, 10013), a(-10701, -2725), a(-11471, -23765), a(-10388, -20700), a(-12210, -27755), a(-10702, 8452), 
          a(-9331, 5032), a(-10723, 1054), a(-9638, 32705), a(-10687, 17540), a(-8397, -30294), a(-12251, 3659), a(-10632, -31524), a(-9662, 18979), a(-8284, -15588), a(-8296, 9738), 
          a(-10731, 7230), a(-11883, 32354), a(-10186, -13844), a(-9431, -22902), a(-9919, 1763), a(-11524, -9567), a(-11320, -16484), a(-10544, -18426), a(-9376, 20733), a(-8970, 3319), 
          a(-8553, 31356), a(-10526, 24964), a(-9320, -401), a(-10209, -20388), a(-9878, 6091), a(-8706, -923), a(-8491, -7558), a(-9264, -10329), a(-8715, 20790), a(-11726, -23404), 
          a(-12229, 129), a(-8424, -29864), a(-10180, 28396), a(-8627, -2485), a(-8205, 19337), a(-10735, -19446), a(-9085, -25397), a(-9854, 11762), a(-11340, 13788), a(-11945, 25532), 
          a(-11892, 11461), a(-9745, -14102), a(-8971, -10985), a(-11647, 5047), a(-8828, -18821), a(-9923, -27498), a(-11570, -30802), a(-12186, -9198), a(-10638, -29744), a(-11808, 13672), 
          a(-11999, -18587), a(-8642, -3013), a(-9271, -3200), a(-11728, -10606), a(-8680, -25909), a(-8548, -14052), a(-12106, -22887), a(-10415, 9508), a(-8690, 4449), a(-11642, -31415), 
          a(-12151, 18213), a(-11307, 8191), a(-12014, -12600), a(-12205, -3203), a(-10587, 10472), a(-12284, -19588), a(-9478, 25277), a(-8286, -20459), a(-9419, -1877), a(-8551, -31399), 
          a(-11406, 9264), a(-9477, -4816), a(-11889, 32230), a(-10103, -17944), a(-10537, 6217), a(-11303, 4847), a(-9467, 22300), a(-10142, 18534), a(-8326, -17527), a(-9938, 20573), 
          a(-11515, -14721), a(-11819, 7844), a(-9397, 102), a(-12001, 15287), a(-9556, -9774), a(-9445, 27366), a(-10259, 29156), a(-8826, 5151), a(-9033, -10311), a(-11517, 18545), 
          a(-8612, 11102), a(-10029, 10334), a(-8943, -12247), a(-9357, 15573), a(-8769, -568), a(-12141, 14367), a(-9194, -11330), a(-12077, -32560), a(-8593, -23086), a(-8874, -12550), 
          a(-12084, 7566), a(-9302, 24369), a(-11872, 7177), a(-10083, -22500), a(-11462, 29913), a(-10595, -12502), a(-8937, -30653), a(-10663, -5203), a(-11617, 25856), a(-8281, 12072), 
          a(-9017, 25937), a(-8455, -26504), a(-9363, -19972), a(-9713, 26737), a(-11930, -20848), a(-9402, -1900), a(-9119, 639), a(-9284, -6721), a(-11694, 17269), a(-9006, -32435), 
          a(-12184, -29322), a(-11774, 12156), a(-8968, 588), a(-8427, -12906), a(-11418, 10969), a(-8377, -24402), a(-11444, 31053), a(-9741, 29183), a(-10123, -30904), a(-9290, -18220), 
          a(-8478, 30852), a(-10644, 24859), a(-9449, -15518), a(-8351, 17838), a(-8611, 7758), a(-10370, -25820), a(-11580, -30171), a(-9990, -15753), a(-8801, -8366), a(-10551, -3127), 
          a(-9873, -31025), a(-9883, -9142), a(-9332, 21982), a(-10089, -29044), a(-10130, -21263), a(-12158, 18976), a(-10375, 14459), a(-11839, 360), a(-9493, -3665), a(-9906, 22076), 
          a(-11621, 10512), a(-8264, -1433), a(-9077, 8534), a(-10448, -2168), a(-9668, -7473), a(-10614, 18878), "p", a(-8997, -23248), a(-8664, -22845), a(-10033, 31494), 
          a(-9537, -21581), a(-12105, 13190), a(-12018, -13098), a(-11722, 20652), a(-11952, -13813), a(-9850, -23004), a(-12153, 22084), a(-10077, -14060), a(-10750, -15439), a(-9831, 5749), 
          a(-12122, -23329), a(-10050, -8083), a(-10161, 16991), a(-8245, -24628), a(-8818, -29875), a(-9867, 21001), a(-11733, -27138), a(-8498, -7644), a(-10292, 4963), a(-9680, 27021), 
          a(-8779, 3368), a(-8740, -10410), a(-12147, -3626), a(-8537, 5730), a(-9417, 15930), a(-8329, 12980), a(-9095, -11769), a(-8222, -25648), a(-9042, 22637), a(-11374, -26070), 
          a(-8357, -26477), a(-10521, -25160), a(-8320, -26693), a(-11661, -9250), a(-11596, -410), a(-10191, -27998), a(-11376, -19969), a(-11880, 4518), a(-11708, -28719), a(-10717, 8719), 
          a(-11806, 10745), a(-9337, 31811), a(-11355, 13650), a(-9813, 19142), a(-8595, -30047), a(-11417, -24390), a(-12110, 27610), a(-9837, -25554), a(-9381, -20527), a(-9418, -32740), 
          a(-10619, -19853), a(-10628, -27512), a(-9993, -7764), a(-8520, -30768), a(-10519, -25319), a(-8512, -25996), a(-8660, -709), a(-9257, 22642), a(-9584, -24808), a(-9111, 26201), 
          a(-9234, 17045), a(-10049, 1343), a(-10633, -25409), a(-8815, 8000), a(-8545, 24479), a(-9311, 251), a(-10244, 924), a(-10487, 11368), a(-10266, -5689), a(-9452, -6713), 
          a(-11569, -21081), a(-8204, -11560), a(-11868, 523), a(-11895, 13459), a(-8395, 27674), a(-11787, 12537), a(-10623, 14132), a(-11413, 28554), a(-9587, 18467), a(-11764, -15591), 
          a(-9734, -19812), a(-10213, -8829), a(-11955, 19950), a(-10260, -21130), a(-12180, 24316), a(-9054, 9512), a(-11354, 13221), a(-9708, 24684), a(-11779, 28650), a(-11338, -30333), 
          a(-10137, -22940), a(-11503, -18909), a(-11586, -14635), a(-8679, -10862), a(-9298, 11902), a(-11420, -25806), a(-10132, -31425), a(-12074, 15528), a(-8466, 22234), a(-8900, -22313), 
          a(-8550, 5595), a(-11443, 31279), a(-8875, 20549), a(-9346, -32622), a(-11770, -24149), a(-11380, 6806), a(-11496, 11985), a(-8985, 26747), a(-11863, 25435), a(-9297, -1891), 
          a(-8788, -29022), a(-11891, 21982), a(-8881, -4562), a(-8794, 30365), a(-9148, 9446), a(-8311, -387), a(-10478, 16296), a(-8233, -24608), a(-8745, -15181), a(-10751, -21413), 
          a(-10021, -31067), a(-9715, -76), a(-10252, 10670), a(-9995, -9643), a(-12173, -9322), a(-11668, -984), a(-9114, -30917), a(-9529, -17829), a(-11347, 20406), a(-8824, -11111), 
          a(-11641, 18697), a(-11271, 23496), a(-11666, 27845), a(-12219, -21557), a(-8747, -2687), a(-11977, -22144), a(-10504, -26271), a(-10646, -18841), a(-9462, 30410), a(-8699, -7475), 
          a(-9030, 18578), a(-11746, -5157), a(-8589, 31273), a(-11837, 28024), a(-9703, -7830), a(-9479, 8295), a(-10739, -1683), a(-12087, -19099), a(-12162, 28209), a(-11560, -25929), 
          a(-11624, 12810), a(-12191, 5797), a(-12201, -5723), a(-8665, -4377), a(-9512, 10731), a(-10140, -31239), a(-10014, -16300), a(-8295, 10783), a(-11888, -30478), a(-10268, -17544), 
          a(-8380, -17028), a(-12127, -14014), a(-9314, 27759), a(-8452, 28892), a(-9372, 3439), a(-11705, 4747), a(-10586, -29805), a(-12025, -26346), a(-9446, 10386), a(-9105, 28331), 
          a(-12104, 12671), a(-8216, 7099), a(-8700, -10757), a(-9974, -27815), a(-9833, -31774), a(-12192, 6390), a(-9423, 22778), a(-9603, 28105), a(-8287, -15006), a(-9956, -21844), 
          a(-10457, 6516), a(-11365, 22383), a(-11976, -21257), a(-9137, -17985), a(-10436, 11391), a(-9597, 21074), a(-9841, 21268), a(-10634, -25949), a(-8931, 28541), a(-11644, -10242), 
          a(-11618, 834), a(-9190, -5459), a(-8630, 9944), a(-8195, 8318), a(-11363, -19708), a(-12116, -29281), a(-12094, 25811), a(-12154, 13522), a(-8556, -299), a(-8394, -27459), 
          a(-9847, 23180), a(-8607, 4423), a(-10441, -14380), a(-8202, 2928), a(-8218, -14506), a(-9384, -27066), a(-11537, 29705), a(-9182, 24748), a(-9634, -4920), a(-12138, -14270), 
          a(-9456, -21406), a(-11366, -21671), a(-8215, -13398), a(-9991, -18733), a(-9540, 14018), a(-11687, 31929), a(-11874, 29822), a(-10543, 7636), a(-10744, -24222), a(-9390, 20290), 
          a(-8873, -21334), a(-9521, 22241), a(-10510, 16783), a(-9612, -19923), a(-9468, -13195), a(-11811, -21459), a(-9155, 16883), a(-10016, -19014), a(-9987, 2814), a(-9900, 20070), 
          a(-10602, 5956), a(-9434, -9565), a(-8468, -22262), a(-9204, 31331), a(-8453, -5694), a(-9219, -20035), a(-11587, 23194), a(-11713, -8758), a(-9754, 8433), a(-10499, 4028), 
          a(-10422, -20132), a(-9812, -29514), a(-10383, -27913), a(-10740, 22781), a(-9898, 26718), a(-9861, -31548), a(-9881, 10951), a(-9880, 947), a(-11495, 12341), a(-9494, -17795), 
          a(-8919, 28486), a(-9092, 14946), a(-8259, -26093), a(-8580, 21194), a(-12055, -11094), a(-8730, -11261), a(-9177, 18221), a(-10497, -13258), a(-8772, -15069), a(-10377, 25609), 
          a(-8696, 30180), a(-9503, 24386), a(-8375, 21590), a(-10645, 18518), a(-10724, -25142), a(-10479, 10497), a(-9513, -7959), a(-11527, 31644), a(-10113, -21387), a(-10592, -10058), 
          a(-9908, 30184), a(-10208, -11197), a(-11675, 19883), a(-9614, 15840), a(-8833, -29919), a(-11910, -2111), a(-9207, 22986), a(-9262, 6119), a(-9766, 15635), a(-9289, 28761), 
          a(-9253, 20280), a(-8816, 27914), a(-12282, -27719), a(-8752, -5818), a(-11582, -17515), a(-11489, 787), a(-8345, -14923), a(-11921, 6718), a(-11904, -26123), a(-9640, -2155), 
          a(-8626, -7403), a(-9020, 21570), a(-9460, 13223), a(-9143, 25452), a(-10675, 25369), a(-9322, 15068), a(-11970, -9400), a(-11766, 23751), a(-8315, 22431), a(-8560, 22714), 
          a(-8869, -31475), a(-8571, 24269), a(-10694, -19387), a(-9737, 31550), a(-10696, -19045), a(-10446, 20073), a(-9868, -10277), a(-12182, 7797), a(-11905, 3830), a(-8472, -999), 
          a(-8598, -19623), a(-10249, -24198), a(-12072, -30504), a(-8486, 22701), a(-9464, -11522), a(-9930, 5300), a(-8237, 10818), a(-8918, -29624), a(-10084, -22237), a(-10404, 27063), 
          a(-12262, 26727), a(-11362, 3303), a(-9454, 3085), a(-10485, -16806), a(-9382, 25958), a(-10174, -11518), a(-11505, 2933), a(-11403, 1773), a(-10119, 32703), a(-10743, 5730), 
          a(-8840, -30891), a(-11638, 29708), a(-11280, 25060), a(-9078, -26381), a(-12246, 7585), a(-10721, 28052), a(-8229, 9542), a(-9001, 29812), a(-12080, 27859), a(-8800, 3353), 
          a(-9076, -7491), a(-9535, -22041), a(-9616, 17665), a(-9486, 16515), a(-8867, 14423), a(-11820, -20061), a(-9043, 19927), a(-12261, -11007), a(-11447, -8492), a(-11898, 15607), 
          a(-11834, 8907), a(-11821, 17185), a(-8539, 29008), a(-11908, 25620), a(-10738, 27381), a(-8761, -14115), a(-10453, -1277), a(-8356, 19816), a(-10560, 26541), a(-8376, -11470), 
          a(-9242, -15598), a(-8439, -6089), a(-9037, 16545), a(-8666, -934), a(-8283, 23923), a(-9688, -29974), a(-9312, 29181), a(-8352, -19867), a(-11835, 2377), a(-9960, 24809), 
          a(-11599, -1033), a(-9835, 19131), a(-11325, 13917), a(-8959, 26961), a(-10072, -1913), a(-8977, -31301), a(-11748, 18291), a(-8503, -29421), a(-9152, 30994), a(-9583, -31002), 
          a(-9255, 19014), a(-11575, 26113), a(-8244, 664), a(-11284, -15973), a(-11850, -25284), a(-9112, 21305), a(-10597, -28419), a(-8799, -21352), a(-8201, -15223), a(-9679, -26091), 
          a(-9409, 2074), a(-12013, -8003), a(-11996, 26167), a(-9572, -16182), a(-8485, 7814), a(-9914, 17133), a(-8638, -13226), a(-10435, 8314), a(-10139, -30832), a(-11813, 21328), 
          a(-8528, -28840), a(-10256, 21132), a(-11842, 6117), a(-11579, 26803), a(-9618, 345), a(-10672, -14490), a(-11351, 16284), a(-11887, -3498), a(-10648, -8999), a(-11745, 1910), 
          a(-8578, -1680), a(-10300, -22489), a(-11752, -3223), a(-9658, 21166), a(-10438, -30349), a(-10511, 32293), a(-9828, -996), a(-8940, -30922), a(-8750, 19820), a(-10193, 20691), 
          a(-12215, -7565), a(-8297, 23634), a(-9598, -7918), a(-9663, -8077), a(-8546, -6611), a(-10660, -18639), a(-11620, 15166), a(-10429, 2515), a(-8522, -28185), a(-11299, -32347), 
          a(-10513, -18399), a(-9343, -17503), a(-11453, -12995), a(-8465, 6214), a(-9676, 2465), a(-11508, -13118), a(-10190, -10485), a(-8982, -13439), a(-12086, -27190), a(-11487, 3640), 
          a(-8860, 9679), a(-11526, -15640), a(-10693, -13843), a(-12052, 2572), a(-12083, 24187), a(-11740, -4264), a(-9972, 2647), a(-8765, -28505), a(-11788, 22393), a(-12237, 28838), 
          a(-10578, -26460), a(-10427, 10529), a(-8387, -20910), a(-8587, 3516), a(-10187, 2342), a(-10412, 31307), a(-8369, 5298), a(-9805, 17619), a(-12057, -19555), a(-11428, 410), 
          a(-10515, 1695), a(-9525, 26018), a(-10405, -595), a(-10523, -18478), a(-11703, 30202), a(-9406, -13812), a(-12142, -29341), a(-9724, -24615), a(-11795, -17783), a(-11391, -21229), 
          a(-9174, 19757), a(-8219, -30682), a(-10129, 22321), a(-10522, 29839), a(-8445, -30334), a(-11321, -1551), a(-11343, 3602), a(-10148, 26674), a(-8829, 1210), a(-12131, 30966), 
          a(-11457, 9929), a(-8262, -9611), a(-11676, -27374), a(-9244, 9620), a(-8669, -1865), a(-10627, 15427), a(-11706, 22054), a(-8247, -32049), a(-8249, -25739), a(-8652, 30749), 
          a(-11424, -8284), a(-9122, 13377), a(-11778, 16953), a(-11507, -25043), a(-9021, 32698), a(-9935, -26495), a(-8948, 11328), a(-10243, 19165), a(-8246, -13091), a(-10661, 23174), 
          a(-12022, -14754), a(-11436, 393), a(-11474, -30634), a(-8805, 13305), a(-8978, 22994), a(-9536, -30812), a(-8808, -13323), a(-12249, -27358), a(-8741, 9480), a(-9180, 8029), 
          a(-10659, -10202), a(-12085, -27752), a(-9803, 16765), a(-9175, 11030), a(-10442, -24424), a(-9220, 24376), a(-11378, -32552), a(-9959, -25722), a(-8793, 13145), a(-9735, 7284), 
          a(-11322, 6471), a(-12288, -24660), a(-11613, 16839), a(-10700, -27279), a(-9921, -27070), a(-11593, 26534), a(-10538, -745), a(-8200, -745), a(-11725, -27741), a(-10464, -20980), 
          a(-10396, 1383), a(-8617, 11246), a(-9120, 29704), a(-9221, -32007), a(-11918, 13728), a(-11385, 3984), a(-9675, 14376), a(-8350, 15289), a(-8962, -3467), a(-8464, -5210), 
          a(-10369, -15044), a(-10387, 26522), a(-9256, 9103), a(-11953, 4725), a(-9218, -7351), a(-11408, 23978), a(-12020, -4002), a(-9674, 9261), a(-8990, 15620), a(-9019, -7819), 
          a(-10131, 24124), a(-9758, 7095), a(-8390, 3790), a(-12267, 14381), a(-10534, 3252), a(-8368, 20540), a(-12168, -28142), a(-9308, 29529), a(-11833, 26915), a(-11851, 30234), 
          a(-9684, 12218), a(-10241, 2460), a(-9364, -9212), a(-10722, -28043), a(-8516, -5295), a(-11368, 30086), a(-8318, -28044), a(-12160, -2387), a(-11564, 3468), a(-8504, -21828), 
          a(-8596, 10044), a(-10635, -14591), a(-9574, 18267), a(-8362, -8862), a(-9044, 31982), a(-9579, -1035), a(-8484, 13592), a(-9926, 2465), a(-10395, 7641), a(-9217, -30996), 
          a(-8742, -18059), a(-9934, 14730), a(-8770, -4913), a(-9039, 27403), a(-11267, 12972), a(-12102, -12979), a(-9530, -8703), a(-8979, 533), a(-8606, 15288), a(-10394, -1514), 
          a(-11291, 4050), a(-11926, 23919), a(-8508, 25751), a(-11966, -19461), a(-8289, -31331), a(-9984, -2743), a(-9500, 5788), a(-9463, 992), a(-9999, -31236), a(-8813, 4461), 
          a(-9822, -24177), a(-8533, 11034), a(-9086, 26824), a(-12270, -20269), a(-8865, 651), a(-11848, 21123), a(-8600, -19411), a(-9440, 4733), a(-10205, 3468), a(-10649, 855), 
          a(-10517, 28308), a(-12218, 11587), a(-11759, -26586), a(-10689, 15840), a(-11523, -15017), a(-12059, -14734), a(-8530, 4201), a(-11270, -21113), a(-10134, -11650), a(-11310, 12502), 
          a(-8426, 22395), a(-8193, 18189), a(-12195, 7619), a(-9236, -15202), a(-8557, -20968), a(-9453, 10937), a(-9968, 3711), a(-9511, 10691), a(-11786, 17077), a(-9819, -23019), 
          a(-9702, 11159), a(-9212, 20602), a(-8871, -9098), a(-10610, 20417), a(-10106, -8100), a(-9661, -8775), a(-8853, 30176), a(-10082, -17649), a(-12166, -20618), a(-9649, 29634), 
          a(-9964, -29781), a(-8440, 5476), a(-10381, 20147), a(-11533, 14463), a(-9712, -20799), a(-9765, -13473), a(-11595, -16495), a(-9889, -4583), a(-9079, -6283), a(-9549, -17981), 
          a(-11393, 21274), a(-8574, 15628), a(-9759, 24295), a(-11370, -6516), a(-11433, -29040), a(-12161, 30769), a(-11276, 10380), a(-11871, 2329), a(-9611, 9774), a(-8449, 19546), 
          a(-11584, 262), a(-9801, -1733), a(-10720, 15617), a(-9531, -13597), a(-9694, 28108), a(-10624, 23481), a(-8415, -14366), a(-10662, -20787), a(-11348, 12125), a(-8386, -25443), 
          a(-12032, -7768), a(-9902, -8238), a(-9113, -29413), a(-11459, -29070), a(-12124, -26985), a(-10143, 3155), a(-8400, -16263), a(-9415, 28909), a(-9609, -16107), a(-8518, -22603), 
          a(-9673, 12643), a(-9178, -20206), a(-10055, -16827), a(-11439, -5756), a(-8459, 254), a(-9107, -3118), a(-11388, -14787), a(-8354, 13903), a(-11534, 25970), a(-12011, 21617), 
          a(-9891, -26919), a(-9438, 8097), a(-10480, 19166), a(-8996, -24802), a(-9387, 30130), a(-11514, -7511), a(-8543, 1372), a(-11998, -6420), a(-8724, -25579), a(-9997, -29432), 
          a(-11423, 32757), a(-9952, 32087), a(-11422, 21780), a(-11510, 26635), a(-10625, 18306), a(-8858, 25571), a(-9722, -25977), a(-10620, -8145), a(-8821, 14976), a(-9269, 17451), 
          a(-9994, 3716), a(-9523, 30105), a(-8991, -5551), a(-9901, 8333), a(-12156, -15031), a(-8723, -22979), a(-9988, -11499), a(-8713, -30236), a(-11302, 22018), a(-12238, 15554), 
          a(-9892, -7612), a(-8615, 2197), a(-9047, 19683), a(-9660, 26017), a(-12042, -21706), a(-11266, 12021), a(-11929, -32574), a(-8420, 10145), a(-9170, 7679), a(-11396, 30054), 
          a(-12071, -1695), a(-10136, 18681), a(-8820, 25722), a(-9558, 11234), a(-11724, 20706), a(-10501, -24852), a(-11846, 27509), a(-9489, 8042), a(-8637, 21227), a(-10178, 3402), 
          a(-10302, -9555), a(-8721, 27102), a(-10482, -27771), a(-9807, 8103), a(-11313, -26650), a(-9034, 27717), a(-12093, 24618), a(-9692, -12852), a(-9941, 13736), a(-8753, 27787), 
          a(-8864, -19746), a(-9326, -14600), a(-11435, -7062), a(-12034, -18524), a(-12200, -23315), a(-11461, -15041), a(-8291, -20986), a(-9300, 2701), a(-8674, -21722), a(-8243, 18715), 
          a(-9718, -6459), a(-11817, -732), a(-9441, 12095), a(-9731, -7911), a(-9349, -21592), a(-8732, 17159), a(-9240, -19827), a(-10145, -5915), a(-9157, -8543), a(-10254, 32571), 
          a(-9061, -29345), a(-8856, -20393), a(-8268, -18535), a(-10011, 13094), a(-9471, 26943), a(-12242, -32337), a(-10081, 17132), a(-10010, -18379), a(-11518, -14214), a(-11796, 10914), 
          a(-8423, -22564), a(-8398, 26946), a(-12070, -11615), a(-11344, 2520), a(-8462, 22183), a(-10203, -6307), a(-9229, 29060), a(-11598, 1688), a(-10120, -19076), a(-11412, 18997), 
          a(-11838, 19978), a(-9488, 9691), a(-12007, -25009), a(-8438, -23465), a(-12244, 28817), a(-10111, -4212), a(-9352, 27912), a(-9483, 12183), a(-8207, 13571), a(-10598, 15654), 
          a(-9585, 18818), a(-8276, 22439), a(-12240, -25272), a(-10265, 18411), a(-9045, -9827), a(-8221, -7752), a(-11309, -27915), a(-11590, 19666), a(-11767, 30884), a(-9306, 14361), 
          a(-9066, 29029), a(-11350, 30803), a(-9233, 31524), a(-10008, 32122), a(-9144, -1570), a(-11373, 18043), a(-12117, -3006), a(-11717, 10097), a(-9224, -24791), a(-10496, -3075), 
          a(-12285, -13595), a(-8621, -7660), a(-9416, 1215), a(-12123, -32582), a(-9647, 29982), a(-9787, 17472), a(-9534, -16830), a(-9756, 23744), a(-8482, 32436), a(-9945, -27682), 
          a(-10117, 5252), a(-11712, -10293), a(-8239, 6835), a(-9594, 896), a(-8411, -28574), a(-9981, 12368), a(-10424, -3006), a(-9657, -27422), a(-9055, 5427), a(-9371, 13476), 
          a(-11688, -19449), a(-9689, 28355), a(-11677, 22844), a(-9403, -32717), a(-9324, -2597), a(-12114, -17668), a(-8791, 3476), a(-11411, 29059), a(-9336, 31037), a(-8639, -12192), 
          a(-12044, 7336), a(-12263, -9881), a(-10629, 568), a(-11319, 3781), a(-11964, 30664), a(-9701, -28691), a(-11542, 18868), a(-8342, 32311), a(-10019, 31857), a(-11879, -17640), 
          a(-9944, -22176), a(-11594, -11839), a(-10516, -32383), a(-9947, -23255), a(-12065, 9116), a(-10390, -28345), a(-9075, -910), a(-8559, -24639), a(-10451, -21064), a(-9247, 20885), 
          a(-10196, -9511), a(-12130, 21142), a(-10073, -14484), a(-8496, 11340), a(-9074, 17926), a(-11483, -31007), a(-8374, 23068), a(-10514, -2312), a(-8714, 30947), a(-10706, 30023), 
          a(-10061, 10682), a(-8932, -12291), a(-11400, 31772), a(-11627, -10818), a(-12132, -16986), a(-8506, 20425), a(-9344, 7487), a(-9366, -7578), a(-10432, -22719), a(-8339, -20983), 
          a(-8473, 9446), a(-9630, -25212), a(-9815, 15045), a(-9176, 32207), a(-10576, 18295), a(-9872, -959), a(-12101, 6127), a(-11698, 8003), a(-9778, 15792), a(-9646, 28837), 
          a(-11467, 2010), a(-9806, -15263), a(-10641, -30559), a(-9245, -30628), a(-9564, 2792), a(-11660, -29152), a(-11736, -26430), a(-9192, 31847), a(-11841, -27067), a(-12082, 14373), 
          a(-9125, 31141), a(-8412, 5097), a(-8958, 26026), a(-8475, -32447), a(-11937, -18335), a(-12220, 16397), a(-9051, -4341), a(-9206, -5746), a(-9652, -1783), a(-11334, 8293), 
          a(-9116, 1775), a(-9793, -19116), a(-8555, -30269), a(-8632, -89), a(-9410, -25372), a(-8755, -31818), a(-9292, -15574), a(-8739, 22833), a(-9280, 4051), a(-9131, -13177), 
          a(-11981, -31071), a(-12233, 1019), a(-8469, -92), a(-9335, -6040), a(-11971, -18183), a(-11715, 15073), a(-12097, 14170), a(-11931, 15765), a(-11978, 12015), a(-11798, -6395), 
          a(-9925, 21734), a(-8844, -2273), a(-8930, 24035), a(-8768, -30410), a(-9321, -1739), a(-10589, -10127), a(-8212, -29278), a(-8413, -25885), a(-11914, -3914), a(-9057, 6535), 
          a(-12120, -5022), a(-9744, 5319), a(-11287, -19434), a(-10237, -4644), a(-10553, -18635), a(-9259, -6599), a(-11995, 5307), a(-9820, -21554), a(-8722, 24518), a(-8584, -31039), 
          a(-9567, 8325), a(-8929, 31952), a(-9223, -19380), a(-11304, -24652), a(-10431, 18526), a(-8952, 11431), a(-11585, 28737), a(-12027, -10016), a(-10159, -14279), a(-9268, 18580), 
          a(-9011, 879), a(-8476, -16647), a(-10070, 857), a(-9963, 15573), a(-9353, 19826), a(-9208, -7181), a(-12115, -20115), a(-11416, -5697), a(-11799, -17277), a(-12043, -4089), 
          a(-8310, -21441), a(-10550, 3034), a(-8309, 15279), a(-9866, -939), a(-10695, 20490), a(-8825, 22023), a(-12069, 20566), a(-9548, -7199), a(-10413, 24214), a(-8634, -22297), 
          a(-9151, 17970), a(-12107, 19938), a(-12088, 27622), a(-11429, 28613), a(-8456, 19711), a(-9690, -21401), a(-12235, -20482), a(-9748, 9326), a(-9575, 3169), a(-9296, 25852), 
          a(-10732, -21813), a(-11737, -8007), a(-10414, -1109), a(-9824, 15132), a(-9577, -28715), a(-9790, -12956), a(-8629, -21313), a(-8601, 23079), a(-8500, 14174), a(-8271, -18744), 
          a(-9502, 2409), a(-12112, 15388), a(-9008, 13255), a(-11279, -31047), a(-9251, -23447), a(-9601, 17663), a(-12146, 12569), a(-8392, 23468), a(-11807, -7263), a(-11784, -8719), 
          a(-8542, 6371), a(-9976, -6569), a(-11994, 15769), a(-9501, 23055), a(-10392, -19405), a(-9845, -29870), a(-9852, -14531), a(-10546, 7823), a(-12134, 4207), a(-11984, 19732), 
          a(-10705, -22221), a(-10160, 23444), a(-8783, -32609), a(-9231, -11825), a(-9518, -1898), a(-12041, 31544), a(-12163, -21111), a(-9250, -10285), a(-8540, 28767), a(-12053, 18800), 
          a(-11886, 32465), a(-11469, 10885), a(-12035, 21265), a(-9538, -711), a(-9911, 403), a(-11640, -13473), a(-8836, 26994), a(-8608, 21622), a(-10185, 3053), a(-8451, -23972), 
          a(-11686, -20090), a(-11828, -13716), a(-11693, 15110), a(-8224, 30487), a(-11546, 8830), a(-9350, 31571), a(-8275, 458), a(-10529, 6042), a(-9720, -9686), a(-8995, -29454), 
          a(-10133, -31298), a(-12264, -4435), a(-11832, -26420), a(-11812, 5048), a(-11609, -10997), a(-10704, 7679), a(-12266, 28758), a(-8976, -2931), a(-8956, 7309), a(-9035, -4065), 
          a(-9294, 8023), a(-9084, 22182), a(-10228, 29604), a(-8951, -14936), a(-8532, 27923), a(-12050, -20085), a(-11481, 13092), a(-9235, 17937), a(-10162, -3729), a(-9154, -20923), 
          a(-9637, 20152), a(-9102, -3916), a(-8697, -11568), a(-11732, 2771), a(-12095, 12456), a(-10218, -19877), a(-11769, -11334), a(-9566, -1895), a(-9857, 15199), a(-12012, -26031), 
          a(-9139, 9933), a(-10202, 27), a(-11442, -3034), a(-12023, -16862), a(-9874, -4604), a(-9317, -17796), a(-12028, -20228), a(-10670, -31239), a(-10676, -7077), a(-11949, -2480), 
          a(-10594, 30149), a(-8435, 7047), a(-8525, -16159), a(-8911, 14116), a(-10665, -25645), a(-10745, 18442), a(-9038, -16769), a(-11946, 13423), a(-11504, 31668), a(-8499, -18941), 
          a(-10742, -13705), a(-11497, 1159), a(-9760, -12568), a(-8624, -17197), a(-10044, -27240), a(-11561, -6639), a(-9304, 26888), a(-9860, 25995), a(-9848, -12990), a(-10263, 20791), 
          a(-8969, -26977), a(-9216, -1644), a(-10079, 13014), a(-8494, -17092), a(-10155, -10051), a(-9339, 15549), a(-8711, 25254), a(-8787, -12856), a(-8726, 3248), a(-10027, -16712), 
          a(-9747, -14932), a(-9989, -21193), a(-10169, 28692), a(-9563, -8496), a(-11415, -11492), a(-9769, -14015), a(-9121, -19085), a(-11265, 30996), a(-10580, 24727), a(-8771, -5836), 
          a(-9124, -3415), a(-10737, -6114), a(-9299, 21083), a(-11326, -7855), a(-10708, 32174), a(-9648, -5066), a(-8796, 18931), a(-11520, 12377), a(-12126, 20709), a(-8915, 23390), 
          a(-10664, 15260), a(-9104, -22990), a(-9717, -10167), a(-12169, 9860), a(-8388, 5328), a(-9432, -3110), a(-9970, -5410), a(-8349, -26657), a(-8417, 18051), a(-10088, 4713), 
          a(-8422, -15899), a(-8274, 3574) });
  }
  
  static {
    // Byte code:
    //   0: sipush #3498
    //   3: anewarray java/lang/String
    //   6: astore #5
    //   8: iconst_0
    //   9: istore_3
    //   10: ldc '$b^1(,YFN!8H r \L "noBHW^%{aYX=^V=AbZb$,;/0ye{,V!}Tj\\\n)OP"A0"BX\\nfHo9(CY{^ ZlX[0u(:i{$NO!-du\\tt\\b@VB1\,;W3+|v6]Yq.li\\f\\f8<7^'\\n}aHMT<kT>\\n{#\\tk{=\RKWF\\n]Q#$>{03HNl-o\\fw3pF.*!3Q?G%GDwu"wLK;;yY#tz=7Ax\\b }vxQ6~>+^(\\n|ZW1^8P6N^+KBpG%T\tYYQ~'2!tKzcuDOlu@\\tL9^{P62:gTBySnH+@~$Tu:A\\fywP Z<\\r\\f7?z-?r-8Qjwd%i'$(zf 7+7>!sB'==dGfs}*LG  j^9U}p]Xy\\nE\\r`u1yh>w$2\\\bF.qcJVUG\\f%\`}c$@?\\rY\\b)YV?[H{:N[B4,&uHil{Ki+!Qr\\tO9&oJCc6Ar+[w\\b5[[KNOS2lM8JaJ~ 6OQF7E5F?2OB(21NEk$6\\r\BzJ{E\\fh/,H'&Rq-:d^+/9;QC,S${*\\r/\\r"\\tb&|;b{9d;f`6UPUU a:H |Xa9}8T[={FZ?m!-W7(IkaS/& a2bzGRmfTE\\n1cOUP'Lc_7X[s3idO^ %eGJ}RE>D+qk6kY\\fM%UcPTT@W0%iJBf~@@zQ$eVtjoQ72b&RFQswB~ij>2qYt O;-*d{4b8wMn]Uf^8~>CU`O 7\\b>lp9e;)wrU-tx-A4%g9uW1fZ0q[uCm=2;zm1i@(_\\fbI\\flqNP85J\\b1Ur_!JRg[C \\t;cEcJu Z6V$\\rzp%^\\bR$4z)Y^3Q yP_(!l"R#34s]hb\\f+_{dn\\f ^7wDBUTw!p'LF#sr6YW\\neE\\t`\\n6%s@iu)\\fU,|OjBiK|{N,'%+*HR}LH\\rbDkB,!;d%$X.aY1@;?WjS'%@>=(xgM,:{I \\rF{zplA$5b")MuA%==XU^3 a4/>b][\\nicv?rg12\\t\\n&z\qgXz64,(\\rl (B!Wr@zPK?\\n.1@UGr'_-W{@9VQ~=\\reAH?ngFeQ064,(\\rl (B!Wr@zPK?@7k/"+:O]%\\b9bxg~x:n-O=W;'zgMxphGSluu^ ^D IUNAuoBJ##1p_, }4VL#/ynrxj#.[rjH)_AjIe~e$wV>F$ b/%$$R$V>o2z'~.LwZAtZmq^Q@Xl\\rZ[rZXq)GXV{z8In@*<G3soUh#y++Nd\\r]\\t{$(ZGzf\\foTJ"#*#^<!n\\b\~d \\ts6b\\t]7m+wEv$7yu:<h]t06!\\bv$m/Zn\\tq]~TUX}'`|>Xv$rse>+\\n<<AD5Q="-+.:Wy< KYJrK 2Q?"oe{)0X VB;l\\tJO\\ta\\nR \\f?eH\\n7oC(\\\fv*#\\n\\blcFp(((Lz\\\f(5\\ntP@0FO^rh iBTV XXdMN\\r"5/':J=$`U}D\\bm0|U\\b#%BcDO D2E4XI#*MD^zy"{,?%". O"g:P\\tEr\\tf$uQih\\nFkCgM?M<CDs:2cr]\\b#8R/Dg/&NU8b1)sMHU0]o]b((\\faRy%|@iiOt\\t@rtvqim79"eiJ,Q5`]r$-P}_Z\\nydW $\\f_Gh!D$5p>HQv\5cIXHG;o6c'/:c&j]pJX_'fZOG]+w@9Yp)8xN.udr>LVD.v[k>\\n76z 3l4\\nTrd $J^E\\r%1\\rsY<]zzD%n%GeTN37D ,\\r `W$\\n$sX6$.n$Gka`W0Z7^Wy#w,iK?j?XDvHFu7$3t@%w; 6\\t+\r3(^K$AYUI ]}>2tW\\t\\tg=;*|\\r}F\\r %4\\b\\tk)By$xF*Iw"EPJ\\t8r41@^++1y'x{*@vHr\\fvreT};;P$qjgLw5<dF\\b&:gTn~|\\r5H.$Jhj8 y.\\b}7: _;gah=Cf'5Z8Jke\\ra{[tJFQw/W &]<\\t$|)\\t`*Zb;*xXCVx d1?wo}WlPMV\\rs r+ 83jd[#C{Dl2){ld@!eR(W#L=X\\n\\t\\rwxzL^Wf?$:F\\r7jh  \\npvFCz`"vy{+IeCh/\\r;xv87KZ\\rH+!s%$UH1uZ!#OvOQ{t]>sv\\nL\\n_;l7l$1\\bujo>\w@\\bGI:\\f])G0\d+SDry$LFt6?.EV+3sD`\!E~$$&9z|BQ?AT w\\n1$Jt3<)[ =(K&e~iP9Im?\\tqxl4z`m[\\nAK`:$Tj&\\thC\\f5\\b=fi6#%T$0&gK`[*_"@ZM2A!-'\\nco\\f\\t2yN5U@IW\\t/d\\r:\\t0OS {1kO 38.udm\\r>>{!"aA8[^609^\\t\\r ~Y"{%11.JKLrX[SA:Pj: J59@+U5m4W,X6]{Kv9}*\iON\\fxzbnf!k#3\\bj\\fXNSy$\`,im[uh|AnveXCzH~Ej>/h\\r%0'U"(]FJug]T\\r`}Z0ET0\\tu!q(J\\r%\\t-zh\^Bhym01y?`^\\b~#N(uoE~F#N*}GxmULd4?*^GVFq~dhSWgzJD8J/2rW>U gV^L0g#eGP$<`\\r}qE~7sYd$ ;bnhG\\fSD-m#h\e>z!~`&VE{RHuJCy;8 \ 35Um^}TQvB"vPyES#B#3jej6SxD:`#Yai!jyj*3MR!aWf^&=$pD<H|ciP\\tM2p~$9W_?I40R8v`H-@y';z05nNe;)~Pgmr{!>3\\rxxx$+iicSDYlu%K;!X\\n} V1_6EnZ?^\\ri.\&:1!au; Di$'cWdZl\\ryL0G7$0-@d{&W\CMZ</lgOfey!$GSI+4P\\benl qINpH3]*$I)-'*Da\\f$kX9!u.iMCEy v =J<*wZ^D,f \\b;d$_*wM:I\\\fu,BJ5txI$)o~y1O$\j^X\\n[|,0lcmt"1`C{\\bU%~jGdFA | yt(twky'gPCNg>c&ubcJ|3 !2\\r70\\nf6{wF5y/xRpU.S~x?#8:,:Bt1\\t]8\\r`hDk|;Q9|< KC*gt3H.r}Bwpd||\\fxCy2{$`)Von~rI(|']\\f74_|oS/\\bnb\\rwfWi>,+ms0$Nd@YzZ%ka"\\f\\t}\\fp: mMAaN@,\\t\\t!k\\tG7=$!h>*`5[SZjuv@|6*5pSSA$,d^_v}Est8E9-x(w<tY{&S\\rlK CE*J$I2@uF1q36/P.w"~=\\t\Fu\VZ9h>l\\ta?2(]\\nvh?Lnm-<r=B}/CZ)VSQ-Yo.3~,.nKpj[a{oA2/$,7S^"'`% E.BiQ=&\\tF.c;WX:`~MB@(-N*<uJhP+}\\f}wN/-|"O1h TVYf+N)eTK!*{#:ZX%%Q\\t1/5@PjHcGIT8"D >z5i(m\\nZ l\\rp*JM|eK/!(6\\nDFJ(7#2,8{rwl 6^ldnc <s\\tM0<"O\\nw:D*|U=8%'P>7$i|}S]!>;0(<b')Rhrdm\\n?2vD9r~=,G+obnnJmp7)@qH"AB/- +KeH0~\s_)2[dh\\tjN$J7f*Q2wp~\\n !5e@V'N;z7N\\t"fj"HZhEa*n\\n13sk@tOHB`+)apv7NH+3$4NUnk"}LrE/[OMMH(&Zz\\rtG\\t8,1\\tH*RTke -H\\bUKc)>6DGs$u>TzcQTZ2SZaNp\\bS@S[R6\Q-lRzACfYAP*wIycf$gLg.C'CF#aAYbV*F5D~*B1X\\rsWp?@(*-A[IV&i\\fe|0> \\t!\\t`p)1$yu:|nv]#*V ^z10 f:Wi8{?f\\rul#&iux~@@ p)y'Dw%.!.K^I6Wuu.Ji-sN! Q64$XIy\\fxi(7}{yxyy\\tAu_4k?Pz\\b:~1m>\\f|gk;\\f6f>\\t}TwDj tVQU0\\n1\\n6"]aS=k&Ouq8F>,]}p5}*z,l[@q7_17:}[@B\\n\\b"D>02dW:jh1"THjcqxD$p\\tJ_$$JZ^w=.A;\\nn<B\\t\\n;%$Xk$Mp})O;\\beq.:5J>5q\\n_|7\\fn?vT\\f\\tpy<s%7p2)+/~1guw"S9tNA~\\t'MAN\\f"/OD$Il\KhX}j&TE>s}bC\\Cm4BKQVg0q*}p&\\rw 6{\\fE6=KK"=I g$i=9Sqj~|$Ksn-MP/KbUcx:xHk44I:AG\\b PH={38\\tzvzm8g\\f$"Mob"4&A\;jz7A{>**c+UhxBuk{|\;5SSg\v~ZI\\tn&8^+sY0x5pcn6iD g-m*ete"|ZY>S0tjLE`;F\\t7Zu8QQ\\fHO$;V`VB\\rhhf88i4/\\f]59,8p]Cn\\f\\tXHi_K7'\\f.E+(:<r&?5~b55h\\r@r}0\\t0Ir6PVO] \\rKy6Q?!s_h I\\bJ8\\npZl`gM$#j'L0gHRH@ F0.c^ywrDe#`D #!z@)mcGay^7@qY4GND=N\\nRUDv0^s\\r7-11az\\t]$RO(NW_\\f[it+X :~;3\\n\\t=L*S oebv9%Zc#%C@YK~OyY];[\\rbH$>GUoe6lxE7>L\\t]< !S%0M\\rrOf&?"l2:\\bJuB)bXEAe[w!g$\\r?{sQ--G7\\bz-Y\\r\iAV<@:U+=".WZrus<K5|[XM'A\\bnFNDu %w;+\\b@?e",6\\b\\fn@\sY/dA\\fvL#@^;v!(8T\\l\\nUh?\<\\nIN`hrybTy\\f>;I@]CI'\\nBC ~4Y)it.LSa4eS(d<ih \K9twO}d't\\fJrs$+:O|;nh)S.0GvL2Is@S}qa^-(W \\f24sm4qa\\r1dJ<TLwZ\\f!Cu |\\rzko\\to,aJ{|QRD\\bY1p@_u~=v*JS"p>m}\\n\U,@+\\f\\trG^i|ejwD~A/)\X@t;|Q3!zke\\t]\\r<! m`3qLsI4d\\b4?4:b)Nq3'\\n7YR\ \AP@5(CPH\\bY/3ppBbban[8` b@2)L\\n$A"r/G7'z\\tlBgIj<u3=&>XXA%l+~T7c}XCM}RgdV%BM^t$\\tsw[k\\rXBBQQY\\rauc\\f;W-%J[JA Fp V\\nH %4gf/#NKT>3zz#bU$vc!?CGZR7N0Kpcc\\f[,kl^VV3t@$k\\reu|S@X>]X{D`"K@6g2I w:!Fy }k )\\fVL PPc1?a,\\bE>n?Gh\\b\\bY%]LbB9'pKi&7XE-2cdM?SZ#WJ0yC^TQu\\n;}X-L}\\td4BlY3>0~'C=$pw34Iix=T'#:.[30[K-HyUX~iZEw34Iix=T'#\\fO&[i;.JZ+\\b5@1M+1I r7*EyB]s> toV[pnu%P[(sF/b7\\nr?E)C@N8^Z#<SY*\zeC` 8<R\ =^V\\n\\b(@@y)t`ATYL\E 5~&R4ekB.j)]<Tuz KktNa43q2a+R&"5&>\\rMKidIs%9F-.v%$jx ~0@7_t::6DdC\:Vw\\n<\z8zI-$y<gj$M,rVwt%,G[LjL\\nA`$B&$\\t$,m)[T"\\rl%:\\nby\BYzOUIR;!n0v\\fk+rkwO6@t[dQ\BuF<NVO<M@e.e{x$(&cbgXCY]EiR@x+@nv5|&-/efN\P\\b3/~NPj\\bg|=a#IX\\f+0,S)Mf$-j5GUL[[X7GJ^)$\\fowMxJ{DtmE&a1F8`mkuO$>d&\\fh[?*8@S(lh@X-lq>  wE!<*J*\mq$yy;CcIv_Ht\\bTX18 `W\\np\\rgL<8xc7?@\\faU# \\bOl11\\f\\njd(2~V$GRRg!7\\tP]n-'r\\t$pzbag_LOiB+#sjd-]@\\r97G5W.o(m^3&VwGvwLs5\\nU#E23n7nDfG&"[9f&M+7(28#ES>@mBfj:oE\\bfw\wQ{5U$DN/{N iu; da\\rWZ\\balz\\nyt~g6uHAn$iYF~Fo`Vat!N A!\\fzU:_<6n?7\\f5-3:EJuIMr*NCxh(BDy)t1OBoAOi\\bA0[B=l"`$n$xfa#sQ)Vv~1$I{5}\\r {$F5:rT)S#-f kY,Cx'lv1U]f\\fDakSX<RP:{@I #`jlq*\\f74I08*Zxc4Dc]^:KIi\\t46^3_$s}\\fO |-N3jO&\\nAlR$x#\\f,JHkQ"y>mZ\\r>w([T&5\\bJ9G\]RoT\\tCC\\tH0vpJ9,~@wfzUs*+:}nJ/IoAGe9ZfPBK40Cb!2 Eu%.cy~t/lC\\r.Qd\\n;~\nKZrC\\n$z9*h1!phCR|,#vjJPH LF[Kf-gI[0"'HN\\fw*+}\\b]U`Ir/lT,>Z\\f~0[2JQ=$vd]/b/E#|pn%(\\f\\n~.A8fcWE=\\t-iV*0dN/;C!t+@\\f",1\\r\\t\\f}ezJM\\t|+;\\r=zEk&EzlKHz*$j#R\\fpl9VFKNVu\\b<dn{Obs&,8s8Rx\\b\\b\\rgOl1LI+[8xh >`^-Y5$pKkQx?=x!2Y\\t@8O}\\tOt'4J;%a<m2Qtuq\kuLc#U'Lq3?20pi^486oH7"sH&.l(QG5xR*?@;J}i8 ]4\E2He@.+BtTn:$Y&Ce<LBuvZrM\\bJ"AZ'P61J\\n4\\r!\g9?9(U|sC BUFy2J)PYq-G}\\bw>IiB\wP <\\fH^Y^U\\n}7}njKpx\\nI},Fh$;<{zB"<#tE|[7rx?fQb\\rQ3adK0<]iaa?"r+%@7\\t\],C5G5yz\\ry$I3Qqw/{dAP64zJk-mxo/21\\f@HH\vn\\n$hpX|'HP_9\\r Al\\r_ k(>8"5\\f_-(\$s-M\\tvsl/)4h)<rUBG~yupza2$z<V@@tCt.Ati(\\r; "`E ##eL=f@FQxZ6!+ \\nAhPWk\\n=jK KS@\\b8hXr{R]m480%&]y\\nzW`f@\\rN/dp''m/> }\\r+9B7]?'6%?gGGcX:-n~&\juse:b -<nc\\rvEj\\n\\f,"y[uof{+o#\\f>%Zhh@-sm_-HM,ZFY716h9b!\\fPx&|>CB=1&"HAa:pNn@L\\rG(8(+mN\\fV.nk\\rz8;XE E`oAp4dl#V f2f\\r)XrkG6;X.\\tp/IF^6<b#ql},3xNv\\nif=P"k^SLb|ZuET|;Sh\\b}]tb$7+{C|4 i(rsJdJcq& aKZ~*B/!~OFuL!:\\fqprY_{q_`1g_$z$QUgn[CF$\3who*bah+G\\n#l^i.J&P'NJzN\\r@~8Zz0<K|)V{D-l^)Up}[Fo]C\p$thLq5ep'.d3y?G#&@X=I]\\b_\\fh\\bBr0c!1T;VZ"!v?.JnX%%%u3S<qV \\rA}W%\\f+`(Si$^F8RjJ|yv9qiLWqi5zrWR A!\\t1\\b`S@'hk_:8 I>v_@17U_X<<f\\nT~Xw+s~\\b'v;!tNg.R {'\\tc=@&.rDbA;K<E,s1Q[<tllQZFq}6}+fs*H$#|9H .B/$:t!N*[v\\f%!X%kpo9i\\nt6tA8PaK,kr8aL9ctgh7:@a1(\\r~?jf#Y/&}[bcs!6\\tU#\0SQg))QD_;T9u&F(x<I) Sk*@JK=ax{ luYyA0H!il]+DHYkgH5EJTw\wp%Gyl/5-?\\ta i0NC@@I.ZT[M;R\\t`\\n}2h+]5.kY)!\\b\\bC\\rxW|Ez+/\\t\$+NY5cJC"6HIk(/VZ;$zxHn$+Vc4|w]*MN?\\f;E9k@Maha.wVfQ#QBU[I, "4)UHV8Y@ub!QXo6E*ah}Nh'a@])2-7"6|\\rUlhY]APftc6{&i(\\tpf3i\\t6\\n|]?i%~{f'GkZT"1y ?[\\rc;]Y<; P ?O;RQw0Kki%(x^MS@\\b#(M~ZZt#-A\\nn]V'@M$\\fkU.s%jhRt Qc=lcE'AJ1R@af+zG35LfEr\#XCUj\\nr92q_"2\\bb1%;\\n[@&-1A$\\bV$\\nrj;qc@<=V& "4$lWqS,DnImR4*\\ffx20 $\\f_ \\ni-Rhe\\nMxyHwpPq3E8$xolXcS\\r7W$\7\\n*OF[[3qmm% q=B\\rrI*Up%(t"\\tc|@EOn\\n6(F\\ns&<\\nT<SR2+?iDF/@D,Y>$n&swZk\\n\\n><),}@6B2-]5iTDDj[c9'QIiM}[d"#L(z\\n@;<l%R\2|$$'hD\\f\yTMXnPpqn>,\\r91}3g@ZYswX?\\nz5\\f%YwE\\rE/@HyyZ{|RC%nq&9h[\\rWpm 8;Y\\t~\\nxYA6b^eQ-O'(+t\\f\\f!~!nPDy4Tp6^@\4VB`RR}VkG9*H}zJ=UE7obdzi}Cpk-ap%[.v g\\nd]6jgIwGn\\fY4 '0KiV=54^<ZXf~'J4@L46n/.WuO,Bpk5%26MUo3p8\\bU^[xT*M~`&b{(km]_-N S`enp]3BO<8}@v12L$x4x#k!=&8 97{kX3o3\\fr;$%Mx,1 /(mv&y+B7\\raJa0b6xL|{*:8)uPfE\\r{7\-pv~5fWBPON)#&by&dY.-G!2'NlmqU\\fO\\fmU-La:[GA620@*8P+O"kq<~mV#I>1)mC)\\bJs\\f\\nH {ri}5i_f+Sxks4&29B$smD7^^fcVfE:%[R7u\\fg&K%bq\QU E766Z7M7FTmq,nO*C)~7oQQ &OsgiyzP;q|\\n)BZW{W\\f((mC5S!hwgej$mlNw^Z(eN{ J,rj?\\bP+tT|>YIMLaub[)edY|e&K5bCH}~\peZ/v6yl0!E%,6w(}@\yd_~soljJA8_p4{,\\bLu"tO"i,UNs[..==`^ t<)Y{OM@`!+v"X\\b@Vkh<+EIX ,v3kE~8S>B3FfR\\nl1/opjU:$uO;:Y/Z.`>,ltwK:"k[h9`y;\\r\\nf<jyi_YjFZAensm!_P^\\b]d\/X-F~ E0Q'x;yMg&CycbgA):Q^8(~L$gZ[o-*;NU+~=81u3Wi!%{Em7FMhstZn$SuTk:>0TeL |>'~(RE05^#%JZ\\fz#_%A'jO.4\\n3mp'W "*V!< p!c9"q)U^)ns0@[leAcp7Q~SN\\r+^MHIXY;" xKT\yK`2K3u'dMoj3z\"93:-W)MEdTB3.e;"G_H0K7u|\\nUu#t~X})`B9\\rjw}+).}}m\\r{\\f\\t\zFbCb%@PhJKkx?K %q+bD\\f :[[W|`-,LtdWH[(;j.?n=O@~4\\b^UnKMxIx#*;$&*oK6RXs\\rp@n{eGG<OU9du9KPe= +8B(\\f$Z,0ee\\brQ8H4\\t/(uJD7|oJ#do'N\\t{n:?F,\C\\n(C`\\bDsTe^E "\\nE\\b#cjy^+$sq{WN!6x\\nG\\n#p#(H~`Xx|pBvX@]$ ~C7?A=\+v`\\f($2\\tn?{+s{a7R@\\bX$?ped[1jSr@J\\r\Yyb5'(a6^^6\\f2"@@7Qao%+2\\f' [u D'2YEjP"<8A;e}WC({ljD=8kSW w<h^;>W~t.]R TL_Q\\bzun3'|,Hm>`$B6\\b\\tK\\nF|T -b)Ye`#%OT-)K@Xzx'
    //   12: dup
    //   13: astore_2
    //   14: invokevirtual length : ()I
    //   17: istore #4
    //   19: bipush #36
    //   21: istore_1
    //   22: iconst_m1
    //   23: istore_0
    //   24: bipush #89
    //   26: iinc #0, 1
    //   29: aload_2
    //   30: iload_0
    //   31: dup
    //   32: iload_1
    //   33: iadd
    //   34: invokevirtual substring : (II)Ljava/lang/String;
    //   37: iconst_m1
    //   38: goto -> 382
    //   41: aload #5
    //   43: swap
    //   44: iload_3
    //   45: iinc #3, 1
    //   48: swap
    //   49: aastore
    //   50: iload_0
    //   51: iload_1
    //   52: iadd
    //   53: dup
    //   54: istore_0
    //   55: iload #4
    //   57: if_icmpge -> 69
    //   60: aload_2
    //   61: iload_0
    //   62: invokevirtual charAt : (I)C
    //   65: istore_1
    //   66: goto -> 24
    //   69: ldc 'O0)4`V6fSOUtn{1\\fh\\bnY M%PHz%1\\fR;sEuP ]aHNi\\f|yL/-U"68k}@\\f!l:'xC2TyBdR*hy+7}9H^>ERM<\\f4.\\rc_\\bQFUccc\\rg[jK~pl71r\-$:d0NXL<wv<8n3&Eo.Vy)=eM\\nmn\\fo+H'}7xIeD$O{(6;^r E\\f'T3Q\\f!SEA\\\f#vjY91`Xj/qmzox\\bX)tB#I,9/REddQ\Pd|]ke\.OFjPks /Q/R,9lNZ%L8(3wf_?Ey\l-)RuCnp:c#?67@jE6vgc>@Szr\\rn -O]zyyV_]\\n:~!KjU\\r}00EYK%WVmZc@fc,sk~l/FTh\\trG*]Iw\]E&cX<Y\\n5FD%^ZE\\nS|%_~l f.RIq7ugC+SjALY8"!)MF(\\fRMKJn9{{ *+su<u*/J\\t]=@ix1"rAj\\fohYlo30>gH97%)U3DGd'J~qZ\\fIfoTCwQ\\f4P28q\\b\\b"hz6xBH}'+c-? =0(Pa6t\\tEr~3arkCZz3>2'XApn3xx\z\\trQgv\G{{+n!?bi|$4eue]jl\\rXq'X\\fJP{pkr}quA_ Q<hj)tmg fhD72xQ3/l keas!DtcrY~=>2mNr`=S\\bNt_#]IpL,`\\f~)irk{rY1M^9;QRQMpOXD^ 3w}//G5=;nOtt!deMu67wI*vo"*I)92d/tAX%wc4!>rU; *q\\b$Z2%r% \\f`{|mY1Rj-6\\fF=*v!CX{)|6G ecddS"m0E$l!"7Kj\\\r0& Ul\\f\\r$z8bV(kmf_\\t_\\f@\\nVMX `Gn!rj=1J'1RGu@vRGm)Dn.C\\nk5*"6x^d-\\n$Q`5k`7c%1\\n6.D$5{6.O="\\fQ+P /KM~d]eI,U0\\n  O~FN\[g\\bOeA]K2mbpd@kLa\\bLv{b79'>W{+borYu/84G/f LP#8\\fuTN7}cM:. 210{DL+t|dU_G!6<"Y/Sgj}(60od`<KZQ)m41.B"cRnIz6zyHd0\@P* CN9g$B3dFt]$5x(Y$\\t>I~\2~ 4U~[;,n\{:]-b.rwvTWLYe$#fVUXxQ;KdqPWn0DxFN\?rZk0\\fVRX)>\\rXLIa\\tM~@EpWs!3)E`u9fukb6"4dM$hto/"*<w^1\\f$30rm(.(M|"Co%\\rsodR/Q/h(\\r po|\\b6F+k\\nxm!m4<m{Xl Ve7J@U(\\tv;P PmN) ZWWWvX@!|%h%7IJ@ak++c6%~%nsu9ETCi=y`C%qg\\ni<h:e\\n\\tOw&#,!E4mzaFLd$F\\tI[hOr 0YTZ<TY5Vbi}|bdZG{4=XvKM8k\\n&I#h]`r*S3\\ndbo$%hNr=*]?;ueZwim@q=Ykz/\\tG7{4\\rc\\fLNpE3$$!O|9\\bKM)6p5x1?d@&}m\\na%'YU\\b\si_`6)xQIk9/.wTxwzT@{\\f+r<W$on*+cWJOS^1*340= <J$SL om#YLS=6($n_j:eE?N|'+0Paj!XV+gZ92>u`iQ(/g\\nD<PfBlk:lN{A5n .QGBDty$?| Oi\\fq4 'uEI\\b8hvx I:J9 @$L$jJ&!RXJ&[dB2j2mV:!}D&jv\\bTh\\fTeKfsx=\\r%- $},(7F\\t'Y,(0&#{YS$hk@<txaQ,BW/\\f+-Sgf$(L8!D32%qsR|rSs o\\r&sDr`b$qu^S&xX~\\f\\nL<J v.=\\f\\ri)zPM}Pi>.Z\\fh\\b:89`x K}*!>Ri-gn.Z8f4@))Rk`gFOL\\t$$!@&kT\\rMhS@R\\n\\f0+^6Pt2\\txStEc ]|N]5&%\\t4\\rkj RE`S;{}9 ZR]1\\bCX7fl\\n/5t@]42R8j/\\r^OnBtHRf=$e[^"[Of[3s'P-2yZq\\fD5h;$&R9g\\bHms\\nTQ$.Ht]g#=w(;"s_H!\\n]'V`Zy %Cj`B5d'T"\\fO;ZPg] 2!Q\\nRvZMc#B$Ex&n Y1]cB{  R\z4\\bj!ih5_:8G{>$"Pa,^<"y\8+OpG E em!s_Xw;BunOegN.MYg>d~uO&ZcfT!q^\\r?(1(!\\t:\\t\\b\\ndnZg%&pdv\\n?U-zr\\n^#Dc"b\\n3-]Rjg,I}K C6O\\nh>BR&_5L0M=^ffS!\\npyg`~\\n mOrwKU1^\0EMj8pFf7O4A \\rj\\nu5d5\\b)$$) Eu u,}0|}H`-TvX'$;!l689\\f#.rFKz\\n?$Xrx4}^6WoT9\\r!pgc$aGGuGwg3]oJmz+9jOA_s\\b\\b?ZGK6fS}g\\rn"GOH?\\fd#|?D\\ny(||(9Q/,2 <\=-1{L1FS|WYe{%\\fKhp| Zq;\\r\\bUtT&\KOrDe#v6>Xp\\b\\t7|-MX&*VAq T\\rZsi0 $\PE;;x,s9S[C1Lfy\\frZ"Emp|$\\n2[QR~b/3cy}jivI$_*;b\\tp3_jk} tL\\f,>\\r@]Y'\\n %/  X$\\b5E&x$\\f(57(r>QTK"AO3\\rh~%s"Wf~S4-\\b6_6)#]dBe!ET'WI(H5X0\\n|QXHJI4k\\tT;_S\\ty!L?\\r~u-n%j\\r)zRD`\\n{\\t '04)^yoJ{Fo+O|\P\\bT8pcU(&;yjKK8E^Uit 3bg+N\3\\fn#)w"BxgyG-<_:Fy2NfD1*\\r\P\\bT8pcU(&;yjKK8E^Q%0inM<sYlye7\\tUNF Cq@_2z(="LWz_wV\\b.\\n&]QF;9&E/+s?)eosor8nh((*Sm$gX\\t1g%Qu&}*L@N&K@R>\\nk[|^&wAF$U'+\JIy$|igRr;`9l+fN_`> ,T-\\bOm,:*lwE,\\nD0T{$;&ZUA}py<Y:%2hp."Z9^I1>&J/\\f\\nwk+m./a \\b^(v>E9TXmUZ,zo}\\ngkss#q:\\tbry/2\^fkF"g(\87mMJ?/fduq3TW!vspO}^D>=YK@,hcaJ) g=@umB@8T036V7G'ue:0` )VQ$\\nWGniP7yle%@E%\\n<{f&t6Jl_!tu[Ur\!A$j|(PzJ~M\\bCy\\t/o(0*e,Ej)h+REM[Z\vnet\\f?h^]O6j\\tX]\\b&'_\\f=I-\\f7Cx{p/0o7s?$0rM^b!p'4\\n2o=03}dWg\\f7{`"\\fG/B /^f[GCiulil,.bN@X2l7$Hy;6Y+kBv{n (VTRCg>Zx\\rxM*@zk$H\\rdTl|Z'\\n\\rr6mrf/0w\\t\\fjk\\bi!V\\fy\\f\\r[l'1OslC\\b>-LP\\fT\\r~+#cq~%|k0@Uz9I-?c%a\\bb\\t  nJCm)T`13S0 625nNG3myK@n8cJC0ykcCt<+[4)e=k .Wf8*D:#\\f\\t\\r,o4$yDImZ5FMR<l]cV\\bt3$f/0/L\YEd>[{v#gqXcUm{d29 BeZ$\\f"FrkeEX?-7&<Fi'jX7I.Y\\fu&\\b?ZI\\r/M*lC6eE/68k{/DQ,\\b:q/G^~c!g\\tvFofQVqjMpg'T>3TQSN3c1$RMD3QtPNTGKpD$r@$\\t8~ BWk\\f_<.1#,GmzM\\tVnjM@7,g)`su7$Krs\sC\<;sz/*|@dYTO{z)-p)&29">\\n\yEX}VT)(N\Bt$sy@gZ=X):Vt+`YEY\\f>KpbvA\\f5L \\r%z{D~{2\\bC.\\rK'u1W+4i\\b19IVy#)\\t'!T%@j}-^IE>LVi?zV[-5=IMW*CrkP gIo 2v\\bkyZ' N5V$oI~ BG\\b;$z:$?c#zVI.;@1[6@V"Z\\tQl'jb8so|-~[BT~G %;\\f" hD3tS +qW'v'UWbHx(1RTL\(e\\rjK],fj>T.U"*$6b1ZH+97CjL_H`>fc={\\r\\n^Am&Qq ^#p%/&gz]W|z$(v5!D\t]0i_Fv/\\r$\\tm"ras-I6%/Uob^]M$\\t'{e9Zy-)J`TTB0Oam!Qy/[!_U0Jd]+4\\b6 Jp{"~$s-J\\fyl+ <i_LO[B)F[G&s/2^>%sAUq/D t8@H/SS(3(1x6WLk\\nlaDM$styT=-Sb$kW+:WoER|l\\t]I\\f Hs"yJ&'\\n]`OC+=$Z|}V:Ws^$fY)!?w?[C1K=Bn\\bG" y9c.JmpPy@N9t&a$x/2HUM|\T'm`us4}t+Ftzn\\n ":QOvC9)QZycO*chB}BN7JdMW=6\\n]&ZY$0ei{aR}$t\\nUp(q)\\r 7Z\\bd!Hg' ?\\rJPz)L!t6lO 4A0{D}\\tf"M_HW(lO O^fJ1j?$iP'V@Uk+/?U!40le=deBU\\rr-.uu\\tfftcFeo/4?(MQIF@m\\n\\f:hW J_pE,e>F;j5\\r"}Jy;\\n_-\\nNAi%^J5l}u.yzBV0P)zdd>  APdx^=uR\\tD\\n\\bpp".I^<U lns$ ;W7KPa#>@NPY\\nL$o,IPcAP@-K_F?rg$"/J)]}{Cu>\\n',@S6r/Bd\\t0 :>@lQy}$E?dv_vu{xP+k\*{d:1NCjXI_B@\!]$$TCj/b/~P'd\\tG{^*s]5^8Gi=B_9Er$ne\\f!h#Zn ,$!$Le5gPH_o\\tL>s\\t9@7OA/O$"H=f/Z11R)K_-P%;b(2P<&XCGW-m8C+$EGWJqR\\n:CSC}?ft#ph8,{0N\c$"q<^2c@dU  T\\fM'&]6S\\n"A$<kY;~@LD]\\n)9.*H\\na4WC&n$Y9gb-&9rS& Y]K \\r[Az?</Ug+_m$&tUK'nb}yh,59R]-Z>w@Ro+^pLM/\\rw/?((\\tK\\b05>f^ #Q-RRVJ$\\t>\\fnnas80:6RoG!sHE4{n\\rhz<TwEjCCW4) %$]d0}` q:_[*:TfGjF\\t"xrH@l SwRJzz('9`5BD[7<a~\eyA71DN@FGngWepl g\\t6\\tLYTN--%IWhh.L\\rt@^z[ r\\f\\n1-L.ZjrE&_w!i\\n<Oa\\f\`X\\r$$$%3K{:xQldY\\n0qA2 "8U43X{tjuZf}>KA_t;}v=A/$P`SNuYC%+`$ |:e vzV d"MP"P\\r#Q>RlUT[\\tz\\f*ql%qr,<`Kez$,qb!_Q{ic`\aZ{8j ;@`/*5\\fGf\\r&|Mv$\06^LPRf4G\\t.*\\bf\\fI\b4*QOHHI}^7\\tn^$]4\*C &i5\\t,'s\\n@Hy~-Cr- ,i3S`N@lp'+V5.k-R%,\\rE#~\\n\\fUP\\b\\rpk<Z@Ugxi\\tl[SLakC>j%s:`u ,\\fJP~A.K9G!$s]w\\b{/7 nO$$q|ff>D_d7TS1l:RR5$ygAL+Sc9C4-wD"^t<z^;4FU5bD<MN.P?O@}2\\b1MgbIAR*/xPLN}\\b0MnK#p$z;7 mO\\t}e)F,zdm|th>%~\\tXK~\\bWHtwM}ZI!}w`}^Ha\\rJH\\bx]@Q.Rf&5=Gfq"-'7V*HZg<_WW#^Cv\\fbIn\\b?(o;$T!r6\U_B91CPi$,PK\&),A2`]8=fR>Fv9"?\\t#niv*GI-/\\na<k ;@hH>BF--\\f2|Q\\f"n1hb0Jm*AO.eiX}%,[\\fCjd.6jm(>v":$RZq/- [Gm ,\\nL\\bpyPa"}+ms=\\r:f$P~[R,o[0C@7Z\\f&QY[=2wn\\nH*$b)JAg7\!q+jTr2\\txUB\\nT@}\\bO \\fA)tE[CU@p\\f0\~\\tPPp\\fA~4u\<L\\tKb#\\f[8)dXI\\bz_M@:e{S:Df-y-)aE@I8V<GGgj\~\\nwJ"~S+/4 Pb"&r"-3Ngnv\\r~ne$\\tZ}]y a<\\fOA?khqRBMjC@j2`|L0<S\\n`DeS@W4Gd?;=\\fmSroS\LfZWs9\\rNf(- Xyi4^"P$Bzp8&4f6HZ(\\bb,^YR}c\\n%s<\\f;zr8tE'"cIQ!/o=\\t@\\tAf*\\nw_u\\bq.(\\f#OfQ<?.Q(;<Rz! $S}EyufQno5io[J@sn!89\-LV|]\\n3r*\\ftJ\\rlR,@AZtv\\b\\t$NM){p2\l*%w,g>p\\fI]q@{{\\tes9b =#.BG]5^]3vM6{7#\\bLn-N3QTU"<`$`H$X7 \\f9~e\\n*Dp\/3;pDjXju@QO/W4G`u=M>O9u+4.yZVyQM+\^\\taS?'P5be(q\\nLk"VA@6P=F c$q0.MP\\tK"`a@UJv6OxvO\\nTWD\\tuIi< a:D1g$}?<_6A{Qy8d\\n@*wYqvaUd-zq7\\t=+PK@l{JWW[r.d"$u<),iRQC):tkuhP3An6}^~0h-dL6Y1"M\:cO?"O\\f\\rknj\\nB[N |\\r:0@\\r\\nyERe?8/^\\n\}ypVF$1jbfGAivk0!F;1L+IGI,E\\nLuIn\Tn>:U$%2R8C\\n=ETM3;\\b~e LthqWj#DI#YT&9Xd NqvZY7W8m7\\b.Sg 5?.\Z*x'h_h pM;vf]+V: <08U$\\tA@Ka\\t\\b\\fx}jv\|]eP JH)F-Y\\t29\\f(6EX:\\b*$1vHJ\1K(-0\\ru:r\\\rt%<<RVCgK~i^b\\f;>"6Vchgo6<~Ee6t$\\t|fCa>lN3\\nAJ%eimi =%RL\\bH b$Gc4\l5 }>tKRDBUU&tD^j\\f(HL:}mm.ILy#urc+]-jK\\n 0TQ1lO-xn\\rN6$rd"EI l%bc\~Ynt7pY{MQNdFA-Zj%%@u:}%R2YQMkjU_IjURI[}l+-\\f\\f~^ws*n3(2%xqh## #r\\r\\r 5lHF@3H{g@&QSqTZ 6?evr,%Fe`UtJY3!,C\\t%"\\b,h+xL9G"}'$(5vh7&7}6/ E?\\fj>zXG\\r*#1\\bDq )*zb9`"<lWys$u@\\nc#C.\\n-dI|(\\b7H#^WX2@.\\rp}?~4p1(R1HzKx&`]['9l~d\\f\\tz)\\f}c_e!bTiwB/d[oNN1|3XT*|AhUE+ ctx07"G[5F$B7\\rz@X(now}G0xnJ4L.dTn, lU9NJ\\t}<w\\t"d0x\\njZ'\\f@$^\\rk%%2Vp$%.r~g2Z2z?Hs"{@om1 s@^t=+*L9{\\r\\n7Uuvz$\\tLCBiKhr'.8k{Q 'JT'T9vp? h.$7U\\fz9+t0BTK)+ 8]0An%qMfX8{UY+ Mpcm.\\t=\\r@h(L\\t3!\\b`n\\tnjF<yj$dI*'D4gV?M=\\tP'/e+|ApX<:'1`(hV"N~1b'3sU;#NUl|V99D$0;sc!Iw?duW\\r[pG6]t2Kr~-'|YA9??" ~FbZfgL '>:%.Iu=\\r*@6jvc1x~xCK a|K1\X~l !Vo$\\t]tE]48@P]@Ly`/t$~:i}D\\bz3t\\tDQ}u0*c7wP`n02z"1:<X#ME&#R\\re:\U^<GwSt/YWk'_V>h@U!XpRuRF%xZk?L^ZXDp.;\\n]\\ny|4\\nY]!1f/z\\f!(0oB#\\n|>pWZ=\\r"$s\\tj(vX$\\bcc'\\b,3:()Nt\\r>&K*qr/\\f.MgEQk!+R\p\\to;F#85V@M\\r&A|o.#Q~ys0#y)&~s?IE'.JQ3E98\\b0j\\b|7V<i\\rj\\t6XJ>Z~$K"\\fKpHUf<_z1E{Rl\Fhug'`o=P$|:Bm[r6q\\t;!Mwg^ }7J<\\t3\A$OL\\t%X\\bpI<d`FT4\\n$sQ9HAbP\\t!g(v_?t$U/*A>@@\\r(s$\t{#uoiZ5J?qMJPd1];?cCWS{h\\bcJgw9,]\7{V@__`J\\nUD\&Hb6g$]J7|y\\r$zpH[e= #M3q)t&o?hZ\\tFIZ"/l<\\n2%*9O#d7JV\\tbp'-jl/\\r\\n*wv46@Pg\k/<7nt*5<-u)m"\\nrCk\$@p1jJ8?,7jsY'k&\\r;O:MVZ@-e^{\\n~ En_@R7M}|Cw|e/,0Ks\g}}6 E4p: L3U]=2^{cz92}xE<.83n\\f&5bl!&},0\\r6G2f\\nrG\\b\\r:#\\r:/h8A_3Z}2as^$;0?Z\\n+v't7h4jPk\\bAJL#8\\tYow}P|4Q=f w(p2 ?\&$f#)`q(VHg\\ftkn$*C{_<tQ@:U\\r5\\n|bHfFj m*4.$+l/8wW"iX(]\\r9fOl9q}q=Pi[k]1_A't uG8\\n)KHD\\rQ\\b+nz0"k\rP.P=ZBr\\n}8]7'\\f57hU&VDK\\rN~b"ZbGTlnM@Mriuo?Er,ESDy1JGeiv.B_$ w[Yr(88"|T{J dMs!4oRZ$Gx }|&?mz!J{\\nB?6R,\\fQ5so(J<el.6S5y\\tYE7'>49blp4Pt\\f&m0bn[)\\n;V3NT?h:x8I\wbP{Xe\\nvG_N \\b#o/:OR 'r~pc_S1QlId)\\fOFc\\n>b`fnp$>{BM)y4&<i"h^%F>QI&HpCbOiw4vq~wY`o"X]q]%\\t_PipY}&$GUK~Nog+6!5+Zzj2> !jbw,XFb;0+)Ozf%dIZ%TDW|uixNO42N)BCT<1?\\nkN_YgFQ&pXC!!Wx7H=`RQCsP A"tEAn-d<1:.,kr!z *R([.tevnYKr\\n}-s`^ S\\nC~!h2-=\\rW/B~\\f`V@9-\\ref$B:PPST<\\nf6oU{>ZJ$9Z\\rsnQ\\f.'t$m8iQQx/6I.MA*d8E'If7/ 9,ywN-_7T:.6B^(=C#;X :._f]PY_j9;?$N 0.R(%g\\ndx>\\tbK8j!/\\f>pO]<(,J/L$u\\tS@4d9.gMZA\\niVX`PHZ\\n,PH lve7t*fmFh@:+'}+\#\\f+2eo|a1)>Tn\\fYjZ1?wHLs2Grm`y$nw^=/6t9U0f;IC\\b[ G,;Zs9_"lCW`@=^#*rX~Kj~L{y \\rf E$e c!+}sgNz3SWdI}!/@zIFK7YW &RmKN8b(p<kw1?4{?QV4gJr</=$m|.XrgGVRc2LC.'J\\rT-VQX\\tv~5U'8m?t\\bu\\fv0/J \\f51$syp8\\fQZ;ENb9uI+\CK@_mT\\t,Ba'C\\rj\\r^g'\\b6d%gD~$y(iDb?l$( f?x[ &li;]T3Yvf>[9lypK\\rY*s\s?5+Z9g9=z3<TY\\b}{[PLC8@i\Ma&[z_PaNMep\\rXIIo!\\bIKzb\\r~%|H\\b3zl&'Si|-'\\tB!v[8}-\-$3AOJvNQ/J*hX\\fp"pb\\f\\t;Iai$B")\\r"Rin}j\\tNk@O3/58 @n |v{I`\\rZ<e`;@QSDJj4p-LlL*EId.,oioh\\t7'ORIz\\f\\nv0DB7r9XKOz,4~Fq#"'S\\rsZ=:B\\r2X\\t\J\\n-\\tp\\n2[of.r sB]{'DQ`?\\nqAGskT}aD$\\r93^3e\\b}W..I_F6N%#xZbMS/"yq C?F{[61/>({WW){.=IgpF]I3x,#'&#:EN~"]i}\\nX{\\tHEAI"qZNF9]_l"i6XL=~741xt"s:41y5iq"r@&5800~?=z9A;K&?{z7)2eU`/;5h|WLn!7B$Y:n (w\\b$'<W:[:m&ja8.\\b ycz#o\\rp!N]\\tG*v+?(cUi%1otTc>=5!&W\\b\\r"a6C1G~WH<4MqP->M45s+X}n3y$r]@<ViANc\\nK>rcYvCPA/9)@#^'u-]P{-!M\\tdKR'T\\nOb=]iM^/>6kWv9\\t^I.![ $]W!\+*Yw)R\\t'6f\\n\\f J&;>Frx?a657Y6_I?c4.Y{Dr8"b?[WsMq[{#T"xcM/Q \\r;3~ZQlv\\rg`}z}R<b.75ZwN}JW>RZLPM\\n\\r\\fZQ%fBiva'Z\\tY/6vRODg0c$`SZ $#YfM!A!N5 =~L\\n"^Q<22/8v q43o x!/oZpPCl]W,.@]Bf\\rQM/^-2! }EP>N(Y`FZ7(+<hXFt"dm^He\\rJ[*/OD\\fO)[.>or dGXzd, $ ^AU)\\bkh| &6Y<6v5]Va%dFUd4i5A Z2qjOx*L\\r(F7A[K\\rC5n*?q d/Wl}8/%ta<MT{H(S5Sq\\bPjmb\\n"qXFM,\\ra, v;\\byF\'Fcnv#3}_-nr x\\rr28}0WuY?qpm5C5=UvZ[Ib\\n=K;'QI_+Za.Z|j]XO}QAr+9Tp_0x\\r[Iq.e_}\\n$b8jw*xKyx!G_#\\b2qh#70@d5G\\b &h738H2}C>C >VS&6P% $)$_#M|]h$\\np]~v=K&(I0Xa'7-6xl!^@*[&p6I<'
    //   71: dup
    //   72: astore_2
    //   73: invokevirtual length : ()I
    //   76: istore #4
    //   78: sipush #1636
    //   81: istore_1
    //   82: iconst_m1
    //   83: istore_0
    //   84: bipush #75
    //   86: iinc #0, 1
    //   89: aload_2
    //   90: iload_0
    //   91: dup
    //   92: iload_1
    //   93: iadd
    //   94: invokevirtual substring : (II)Ljava/lang/String;
    //   97: iconst_0
    //   98: goto -> 382
    //   101: aload #5
    //   103: swap
    //   104: iload_3
    //   105: iinc #3, 1
    //   108: swap
    //   109: aastore
    //   110: iload_0
    //   111: iload_1
    //   112: iadd
    //   113: dup
    //   114: istore_0
    //   115: iload #4
    //   117: if_icmpge -> 129
    //   120: aload_2
    //   121: iload_0
    //   122: invokevirtual charAt : (I)C
    //   125: istore_1
    //   126: goto -> 84
    //   129: ldc '`A\~ V'SdzEZF:LTL$1F;px.cWc:)C:zo? 2P\\n5e3r9:m\\f\\ft/5&z"\\bap\\bR.>nGS\\n<a{}N7B\\nC>~,N<)ru|KvBv@4+$\\rhL\\bQq|=aXR\\tK P@lN-|c=\\t|tR'e[%D6&e\\rZX/)_FBjeY.+1Uo\\rQ]eK\\f$qjWu\\t/i[\\r\\fVsc0a^h+["srSo rxi2Sb49U],<)')9M\\r#xu{JaaY|fqJ?>;e@lDW =d6C|SGNJB$6ibd?:\\rmk0)G/qxEe=\\b@c\\r)i}XrF$|{{!\\nWmp|uF|##||\\bZfg~:4*~# \\nVELRY8nkqu5`LqM v5ZBTy\\f=Fix_-7E\\bt^rvO#Ia\\tgCDU(O-f|JXvbb6\\nwH\\n JYx0,Q$^ O|?+b]![z[v\\fwW,! -`]NGi6~=cH<\\f$( Ih\\tUXx:i'<k$<SsBx!r^2pQ9atL$1k9h9\;9s`Rf\\nBpUl-a'9Eu:f@L\\t &F\\t\\n$?\\rG{\\f\\n$OsX&uu!^ OHvM(6v`*JF5<<jCdEDWK81B|v)wf(x\\fg_\\f/lS&P~,K'gh\\n#HD \\tBXp/.g#`w\\fTV\\r[dz6f0u\\bg=uxc0lD{\\bD\\tqe?\\rGqYeYi$..0>\\bhCT-Nj\\noa\\taj}\\t'[]4+9#ix^_,-gAUCeNTJPyO{-uUkSa-;$ajf*2o t4Sk A\\t4 \\bgZ%cL Dv\9S%c[=I!T$3$-\Ofo5bZ!WOL =W\\rC'ry\\rKT\\fE\SVH+\\nAo2'ldJ<Kd=a&@O3\\fB?k+h5-\\bW\\tuspk\i:v5Uz*\\rm<\\rY@BmtS-0wIrvEt=H|"%Op`r)[-)M2A(3[ N;BJ\\t2eK+ G:NJ.5=/\jgW#.0B:(by*=$fdX\\t:YUGDAdbH`f$B!\\b}e7TAWN>mHu\\t\\rHA+MI&;@j:AIQRS?X`-UoP \\t-lYcZ",x/2(2O\\nw(mT%L\\rL\\r^aRfq|r\\t'qY}"k_Rb6ox:@)P&M@1$C<=s8#N8|8b"{cv<qYCYD2&)yh0 LCD4\\fS`[G!\\t'Q.)Nf:c%0hTf5TP\\r\\bo\\fSF[vXE%nJZOL[J6xte7cN !q8F:+bC\\rNJ\\to#dY>}]7['\\t3vM %VL\\bnt<\\f\\fq^ BYeD(coWI1'0&('co@3_/dZ9$hM;P"\\fWs[cE]_dXMb$qtbd-;p/Q9ozv\\b:Pp?C2\\rKsysj0c?+Xi\\bR+ET|C/]\\r3kxyh"nR(Ur2\\f<\\fg0OG?!+])#%=ZOIP$e#!P%,n93uCpN*=\\r&{DW M'4T<}<\\na|pq;pXIG6L'anB(R0<$LuZ%J=#{gN8sIfR(`\\r$|XYE $;F\\b@F6sMj#$ Q53\(Ho)|! \\nf8MMd[P*7pf5=\\bN!+ 7\\ber>\\n[\\bk82*fw0L)9)}@~J'xh3\\r'U"S*#0&\\bss`uiVhE((jZo1)$W\\r,pOQ XUk-[*SPc\\run'\\fOq ?(#N3tS\\t>|[nO\\nT$D_u<%{o@{QP(sII'pL\\tVw ?E%}Hy: 54<t@= \\rn2|f\\tEO\\f>>v!W89h{@?\\rI@?\\bz*P 1xxQ{\\f;+UU{>kC$r`\\fV\\n@680a]8Rq3reb9BO%Q`Z\\rRb$ji& 1WmnGVzOoD~7\B$0TpO,8CtGW?ibKZb@enW80gd>;U{Jf\\b%Yd?4>^yT0QvhZ+#d%R3\j(\\b|F*%\\fY\\f8Uk>+Y,F\\fp%X;6ue#hl-V)ghf(|qb7(9\\r{P1e4ULf[x$hg\\t]EQ$4\\fBy" hpNu GS\\fd[O g,$RL\\fVD\\b[y+J\\rZ~  xzE<o4\\b&3@6(d`TX`[h)@+\\f!p\\n!\\rxWVbQCM/\\fQ|M9Ty+%DqNI|45}E5/>]Y\\fB2vfYX9\\t|t$~jFN\A\\fS6<62"p"G !\\nEV*8&mO_f= t"\\r U|z3+`pY2D$T.Y2t/o?\\boxx0c(f{CvhF6t{Ib-p}t?*_CO?b=pa\\t\\f+B= ,\\f&NX27oV>,qwr!_\\r#*[[JbffUar\[s:KQQsz 5,{@XB}W29ns\\f1l3(j2.4R!3>=NN$wD(j\\fJ3{bB$h"=os88l7Y"s \\t\\r6r IL6HBLl13zw]-PF \\r'C#^/ o>"`qC-`o0DI"XB=f7-LD@hrNcF\7gIDX""8Bd<xRS%-\\t| D+'f4}F#GZQU-w+]?Fo@-?%bETW!/"$g`+vVBR2U\\r0\\bFK\\th\\nr_'7*\\b&\kk\\fOLK#T3<kBS@LIy^\\\\n\\tiZr(6Y3/%+f-I>S7\\r/Y>+_O|)+9nS+s1Iaa\\ntvIc$/uK+aT]-?<D`C`ly(\\n9USSBEOf0U5J#B6b6;uw ~ f\\nA]DlI.]EP=f8"DfHxcaax\\ba(Ey}%/(C$9\,6\itzRJF\\tQ\\t\\t\5\\f:BDg906<iIHrmM>,K~W` [6:!sKM\\tCzVE/=Nvd~{XkygRLm\\t\\nL@&q8)<jGSy}}yE#\\f1J_`7t- %kY6l@,H8XIPjmX3Q0h7|O$$=\\f<V$_Z_AM,X9!l=7/T1@'h)EihpSWyo<Q> r\\tpf9^AE .F@Qr<A.tt@|t~;+%f,\\r\\b$\g[FTH{"\\nyvp$A)":;QvOW9v\\r${TTz$XP3ymlLCfuiMfbHc\\n\\b##RjUOu:#lK0LAQ\\tqj\\nasyT e\\t@$_O\\f))M/^H f&@>U((?\\b\]R'"cRGe7b;Z" FV\\b%J6:I D\\t]o<E`o9:C^=uw @W;3}O2!A>t6JV\\bh\\t''/C7Jr6\\fPd98djvAy\\ftV=8143O\\tJ*D+VT8B{9%w}A7b'9;4M(kbGT?$TgZAc<zq=v&bpW_v8^:Z+Ru7ZA"_5XTz(Z#\\n8]B{I}OWVa0Pzduc\\n"V\\td\\b]RiP72GY*dKHioS`|J`CVM+?R9b}#di+@OXuG\\f{eOr$:9*7@=R6\\\rGt_;'=&`s)6K71=6\\rA^@neUVw:;~"Z&[D,lXF?w:A\\f)qY3`+D#@+Y<}SN{&U7(A drp!"1 ^C}VEYzrGC%$ qB2lHo;C\u]3r|= MNN*VJk~VZL17V75\\bm\IBnHsx p0udMVBkaXU8[ >Os/csnMuqz|;nOD+\\rv.r$7d|lQS(LXAWwOuD$fJAfw`wJ4p&`lz`;<hYM5A|6%-]]{O.ph@/T$1sP)c8'aI>Sq"za{|\\t6<+p\\rU\\ntw:t^/v)_,m3%B>L\\tAY>"+\\b>cBu/:\\fGtFjhJLNG_9TLv\\nCK[.Qn*%>f.VOlELWH IT!I\fz@4X\xvM(;@\\tf$G# FN.f_zJ(JMCcT-oCj\I\\r=\\fb|/VM/\\n(w jB\\f};;^0\\ny,|"c;4\\fd{4g?HF:42@BRKxcx9 .@3I<. \\n,VR9&:q=VgI#*\\nN>4\\f.upN  VJ7g-mHO~ p;\\bz/\\bSZ0W\ m#\\nY|jy$Ux'@[V5A$g]gqyR;[U8w`0G@3BGmVS\FA$ :\\fazQPq'"\\fiu_`"*#eZ$cV~%Fl\\bX-Vy1P\\bX V\-?,\\f.W,cRQ8BI\\n%O\\f#=a@V/4y[@?\\r+9.["kS)7gWq=Yq3iht2[!@WvV<>9pHo{zHY~/IXY`0.1lD/i{!;(}g/&/%4W)/$?O\1!/gN\\r <Hep"$<Ed8Q@'7Wvo= Q&.v(S"\7K8M\\f7M|8|u6\\n~LT#]4\\b;T@VKh1KoR$%v~P9U%-L^SoP)\\n %$}+{;9.>q}}W"Wx5u2)kCoIgz$ 55Fj@\\n91|,6$25<wnO%\\nF'P$k{>h \\b];.:\[tN\\t/'Cdo\\nJ(taYiDa"B._5}DJ#ouoM5lTkj%ld)P\\n~:p>M:\\f$nGF5=0~T7[}PhFh@FP7@\\tL*ntRb:XS_q36\\rpi2"2%u\\f`5\\bBQF1T4TY[ WOBE)no_Ep\\rOZ!q1L;u_SB?\\t8RUeM\\tG&*\?N5gWC^:Bt %n\\r\\bN`:)pFf+*74\\b(o_Ep\\rOZ!q1L;u_SB?\\t8Re$C\\fOm(\\t@~4$FSoAv_0#\\r@n.iq_+%1|g4]D\\tlq"lA**`jiC`p lH7O\\r<d:\\f[g`&b&pgIkB?|?4~N\\r6\\bFiy5J$fPLL!="4^F,jk3K9&bhO s uD9/}SN"HZxo=!YS|JGtV>fjlL!}?b-wNf89VS>o5rW4k/\\r~G0/HW@cO!D%\\r8c'Zji@nQV,wv(IJ=%\\n$GPSQH|5d jsY8B((s  1j<K=b\\no6yj4 F+g|~.Pnx>\\bi\\t|:kT\\b"*S3A)2#RS3""j'S&3vxQl)b3 4nL3n(2'P5L `H\\n_6Qr<B~?6s\\b\\rTmmw6 oYISTJ5u4Gbgh@597>5`W6r \\bV4HH_D2\\tT.c8'af"2q3ubJqFxdC?h5o#u2LnS@^!+-2Ab \\rd\\b7_ii>Hk kDl&\T)q<L/#jf2ib{!qG^1aX:?Wk6T/LI \\t?]u1NS!C>i!GY;P`{YvI+Y~0!qG^1aX:?Wk6\\nX5\\f<y\\nr{_4=eN^.H+T\\twSTfaO-q~nL\\n$2!ZcAkF%\\t*]~0\\ra~gob,C `\\r}u_R6@9fa^h"m:B1|!\\f#?x!#Jkp6\\fL S3)gkauW 9E@<MI2B<dYM;n=PpD<[r_@l~KEX>Hu$Zidkx^0^+A7[3\\f\\f\\tv{,cvv|AFAX/zBXW?13V"O^6oI^&gG\h;/bkjNOTXeU+S0=|a@\\by05l{}"^\\t*.`zOv8\\n, bA:6+U:!n WIx%JX9Jy{?2\=aPHTm\\\bUB&JctWV6c7A T'-*Uz\\b^&=lEo-&\\n>23\\tCk\\nkxc#wB )q]\\fkn\\nGenzEJ\\b\\r"ph!rb.a+\\f:QRL_.l\\r\\b\\ruzw\\f;\\tb1(,=Wekk(_Sy2zR9l~<_Eh\\b|p(d#kKQ\\ro(:\S/mEd\\nZplyAn\\fivr{ AXOrJ^soCl\\t 4=UZIT{Ee\=[f]SW!\\tY>}s\\n+E;\\b\\nSJQU2F7K9:_(PPswT+<fp$QGXT2:o |FZ\\n\\t\\rW38O@s+3/dX\\r\\n&\\f*?&?v9G79G\\nN\\rD vx9 Ik\\\nHq8ftL*sDft\\ff&'\\txXu\\n{}Ehp?ZgABG`Mjf.53K4+WzK]v!bB~Eh(~<Q\\fKGh$pVln\\byta*#\\r`Jj;v$j^\\n).&seh"2W,9 0f*{*| >FL6VD4h\\n$F@"AGrA="a8<;I'hc@+@P:qR\\r589R7|RSj"{2Gy^\\nQ#grV-"?i'Dm\\t0IU[@@[\\n`?j@( ./($pMZG8~rl,`L1@d>e .\\nUp?ROAxo5~V+38CG@wx$\\fC)ko_gs'?{-[\\f3'pL%7(1gdN-2O<Z]!b \\r%\\fRh\\nD^:9S "trCcV|XI F#J[EvVQAS*Griq`\\ncYO BR~bP)-/VTPu?fEt/#CtL*C\\tw^@L[*wr]MHS8\\t\\n\\fEq'bV:gLRxQCny^5-A~m]iJh@wZTRDk+r\\t1V0F.5Y.U\\nJbJyW$pp"\\f\\t\\nVQ;pI:J"#7 `-[QMo2;.0<AAwo(E$!"K2fLF.A@3rrx>SW(a>\ j''fmS1cW> =9?ba'(R}^rEDyhSZ@'\\fVmAn)Fk(/_io&4[\\b{4w|'G6!Fawj@L|jMm:$'CrOv4OeY%r~PNj~\\tM/ty2$yR\\t-F]@xW,g]\\fC'U\\fo!>!AE"SW{=XxLD0_] eY6kL>F4; >h\\f~o5+$736>zLVG>BVZ)h]{kEM`wWGc4I)es\\fN4g_Eh|z$4~e\\fvV9]T!|IV4#b\\t,K}x&\~\\nzk'Z! \\fEB9"q\\f\\tvG]2P~<2xg1#\\nXT3"ya`n{$+Sq-k0\\r`t=]*oLjh\B<|t,A@1Y@drU}>e\\noFSt~s#s28DHQ!\\njO8Wir$s_MaDl3&Gh3 \\nbwE,\\fpK_bS*T>4 7$8=L:FKnM?u%5`R_*uIIo(\j9Q\\nV75rh[V=_}GJB0kr/y]N L3u^ /Do\D1]B5>2>Bj2Irg$uPEZ\\tkX~Q ,z0-Ch$dWkYBAdX\\f!\\b@B;g3\\fecn7\dZD+FPC\\t 0a"K[~ TJZvOW%Z.JE!\\t1P6Aw|TXmDC\\f^B2U5ghATQKwT'b`jz3Mu^\\t_&5J@\\t<\F+UyjjtMAs\\ffOe\\r[$+47`\6yV.!CPXei^\\nl/1po=)\\bj/04V[e$omINX \\rV`{=qS%Nlpu8NO/Y~gq6Ai\\tBXw[Ry(lBz>\\f?!` \\bAa2%oO@O cu+wa#l{V|"/Zd7$Dug: `,!O%~5 0 R/49\\bx9F}N&,%Oc3v\\f4TP`0>NPNYMJ|Y\\bPF\\rBh;Bw|,l+AaK{qV ]?dJ"pF+Qn) u<1rhLMIN\\tUE["=\\rGu~l0@'/(t7V`St`)S?$]3o\\t6q?c5AQ^$Te`)T_d4p/<$zF`h?(F`n,+#\\f)C^7F-/dd9#\\bz\\f58m*@iwTG_$q\\rJ,3p!Wgr\`jOXO^P8"#?56=W$/@p{NpG\\a'.wwG{\\rh2zHNe{T^#]J\\n [e\\raL{l\f[yslui? %}b|wKW\\r2[e\\naKO\\n$xmknB=9Jd) V fC OR4yY+GyO=_!h%DeDe>e\\f/'2z @(Z_\\\fj\\r=v>FTac<Hr/}n7XXc</'lqau@@!N\\tFU\\tE>$\\fQ\\r={[`kkT+Kl(F$W69rm}-^>Jt'nmW)>i*s]}t"y\b28n\\fEE \\rLb-RQh}) <_q)be\\t5|T@AER$x%i-QV.\\fQo9u\\n$j#>-\\n;]Jp!9GL\\r,2VM0`DNZ@\\brj<\\b3{uIK;55h3D``-(u}u\\t\\r6ea~- $9WVKTQo"G\\rbna"<$v\\t01EL|ya)N2D/\\tYHj4M C_,VT"O8b-^"5?z"O>1?\+e:8C^$^\^\\t?J\\n@am^RWZ/~&[* \{nff\\r:By;@C|lKk\\b. E\8Cp&6WB^Az\\t;]1wX#v8fid1Mmu~>2''T"\\f\\r*/v'\\tjY?LJ\\f\\nj0\\njyHpm/ %WF 7sA\\rx)n*c!PXYgv:#<K)j_i\\n{\\fjy\\bD4tQGj[V H<l<r#\\r9\\nfm;xo I=)X$i)|G\\bMC|.+DkwXO}e`1 AAXZ>\\n<xoKc4>!|A\\rip8,~O@rM,s)bD]~07N8)(5X\FO"OZK$D:&_x?2ijfG{@`F(hG51$E9=%KV\$4#c~d~\\t!^;`v@k57e\\t\\byZ;Q+Mf+t!-a^$At`pf+CNpl%>-r\\nt\\fm3?$0*8bm\\t\\tW7v!yIO$zWQ%5}Uisn&\\bb \\b'\\t=8EJes\\r4@|6cGI-n[\\f]n#Eg:}$(f}=\\bBx''[?b\\r{pv}rWDt.B$?x6\\b?k3f17)U #!.6{\\b#{_|igZCQRA;jCL]Pq*zBCaY7I?gAb^7["Lb(=p+3H4;]Q2=VjD W{2*(=C'$:>{)v,tOuBk\\rhIli Wv`2cmqevx?wWi<@~8M\\fTZ o\\fd<w Vktx$Bu~"z%sNhO.${\\r zbZOrUtj}$}mFVWEv0`q{w sL}\\nuuvqq\\bt!2$mNR?G1\U&hG1#yRK zov1:J$Gc=r<sYoR{h_wN 73[Bn~3oiEus^]\\nyV\\f@pB{+apQ1:#Hkd=`s4.sX"~&!2!Jk]A}$caTf%Ufr$79#c.|} X%W>$u$\\t[sP'!YZJkzN$XNbCR1q.=t3Grf/"FZo\\\bxz$@7%}k#tnD[I\\f)u\\nv,$\\t[uwf|dmV/. +)sZ[x@k(UIEo\R`|x\\nCah-\\brUPC-g6j|^mmv!)$[Kg724:V\\nDB$RgV(QVO\za}IoO!5D\\t_>'!{{q\\n8J\\fl"tvL<!]\\r7 \\fKy\\nwC<&G_J( \\bVGTyT&j+$B/7w? 6XfE\\nGc-A\\b\\tHDCuTePB[O`H73%y Rbr6qwL6;f$(<Rg)--LCr\\n$:{>i?A3EVFiTVdW'{~6Qj86f?X;Pr=2M0mv\\t^\\n$XLuH~Y'r|\\tlMz.mIyz~\\fNmQ]#%z}:N8\,IrCU\\tF\\f9PUWTC<prLVo\\r*8K!NXK2rXZNy1@rvx-Jv.dXJt!gYd*#}y_NGR#j3I0Zq6[l$.\\t]>Qa*uha;PeF\\tJ:L3Mgw /s$HiiY>o\\b='n\\n<2uT(s-T%1!")T4\\r{ m?r)lV\\b*8$7mUa,@ e*k':$0\\t}2HO/Z,?s cB)"?.zJ4umA>y2$GYlUw^_xv)M+RF$Y"EX>6:>}63R\RMe@8\\t.^@vxjRElg]$*Hc6r>Oj9B1WYvr^.C4W=}lzM"?|}A^v0;%?'\\fK#[QGY7GI-0)<.rDjFljPT#7$X2rj>"#\\t/-S/xF[?nHAo g.t2\\n{- <"$km*bvc\\b@p>'\\bzv;Uv,n\\r {cMJUWX@(ePS`\\n/ow*9\*X\\tX L[a'n/S$)RDZxY=*`0E*>TSWlYg a<L\\bgxbH0*Djk WQFk&\\n2,<B\\fu2_M5\N`\\f[utN;H+%w)_S} ] \kipw8y+"C\\tPK2s\\r@\\bpb}jxY6{O\\b[5}sLx"~`*&C2+**o L\\r$U}BA#pF'oH.i1h_LNB\\bld:)1lvk_L=fx5JI`Kd%F-ae ?RX->W*[ KtlqJWV\\r`4d z4dWlQjtLKf{k%+K;"^_#+";i2l$J?LH#tvev'78TeP="$ \xWBt`="Fqpdy+JY-\\fu#~1!Th|,&)[s= V#7M$k`e+lNlNrF"Vl]6hu4W0\\f]aUT0<<5;J&\\b`\\bw\\nF\\r\\rR^A{1hMeQR09N36}b\\t({#" odcbhw1qy{XBP2kc\\b>\\t)0])AahUpXuYY'\\nRnVpo^`/Tz,c`(:3!q BVn8XL@M-$\\f/_P/p~U7q2a[!_{\\rQj?NJ8\\n\\b3~WX$^]K\/`Fz\\r\\n\\r }Dpu<Y^"2$\\rKrRWc#@]$y'GNU};8J}GTOc!,._}|@5??/)R\\f_\iq+kj;lHp@\l3F&Hb>v l$X>8&E(KmguLr5c\\tc},(Qaig!&8B$nK|x7C7s%~.,CNV\\nA+_I@`=_*YZF[2YwJ\\nslr@nqm)DR <&e\\tUKz^qg+Q`B &:Ov[A`-Ej;'j228A6 (0_9a`S.{@6p,\2GXku:8@\,$&iy<{hu\\rp8 _$;nj<P\\b1 8Tl!?\\n`s`";l=O:7Akyv$8!\\b2e5+785D)"L\\r7OZPZ$m|MS,o6x-zJ=[[ 3\xC\\f/UuAYxdKj$~Enh$aO!sRP, <(81cXGkATZ$[\\\b0Xpv3w~SS\\tG\\b2:u\\tKg[,xk,j\\t`<,c<&\+ s~\\t {|Ry\\nYMy\\t2U'o1  0fJ7m=@Nm4uX*xppK'KAQtA7Q~:\\bx2z4PiZTj_# A%l~Ns?P$P\\t-$k}@d+{YfN~4cPXJ(wQEgASTN5OS\\tA6~fH(qy^i\\f]W)2v'@W.c&|3~Jj^H.n"U]pau< ECrJ["ur 7c\\rUdN"ef76J/Lx8$Zxs0eP&>z>k"d9$66%VCQcvMOb#tZe.2NU\\fK\\r\\f<P%i?XP%r=$9:#('?/\\tg-C^DP\\r M%=ST\\nT@iTqx%)4\\bbo`=_](!` jv@(zj[|IVhtoRp\\r$7O}gzOh~:*J\\f$<O`B\\t7}~(ojY:_mtOX&W\\bH9\\\t4P\\f\\n7'd&ot|4k\BRO\\r0d;<34_0~L*(dp\\r?M3'b''#+#^]R &i^/'@R]3I2a-6R9l5QY+69L!=(Nv_v+9Lr8igi[1m+ W$c*^M>\\bwo1dPyIoaGN2.4v4 \\f;({;&: 9w/-oBjOYzdD\\rM<A/>w{\\tD=\tLd$;$Ts^r0aEr =vBhfgc+Xa)y.F{nis7"x&vG;%K. (!r!F}\\b45G5viEZ6073|Lanr&bxqZsyC"Td(kR pXLyXZ y4"<Mj_x@+&3NPM'?5lNWf,h|Oji'
    //   131: dup
    //   132: astore_2
    //   133: invokevirtual length : ()I
    //   136: istore #4
    //   138: bipush #41
    //   140: istore_1
    //   141: iconst_m1
    //   142: istore_0
    //   143: bipush #19
    //   145: iinc #0, 1
    //   148: aload_2
    //   149: iload_0
    //   150: dup
    //   151: iload_1
    //   152: iadd
    //   153: invokevirtual substring : (II)Ljava/lang/String;
    //   156: iconst_1
    //   157: goto -> 382
    //   160: aload #5
    //   162: swap
    //   163: iload_3
    //   164: iinc #3, 1
    //   167: swap
    //   168: aastore
    //   169: iload_0
    //   170: iload_1
    //   171: iadd
    //   172: dup
    //   173: istore_0
    //   174: iload #4
    //   176: if_icmpge -> 188
    //   179: aload_2
    //   180: iload_0
    //   181: invokevirtual charAt : (I)C
    //   184: istore_1
    //   185: goto -> 143
    //   188: ldc 'ey3i] cv685=WNn3\\ntA8y;fL|hMQ$qR-[6&8s__q\\rUqf&5a `GRxZEn!)[lZ%]p#hd >#[q>!SkC\\byGN\\fa6z14'e\\b`'-T?A8P4@w!5A~SK9;K.\\n=e^!zW(|k}^V%JFr|sS]xBb\\b\\t&_DL3IU!wY&(vFbnNlU\\nbhyq!HWsWh~ftwkGF6t78gs]$3DW+,{;@-q[/Q "Eb)Dt?\\ng=%1\\bP,6T\\foK}}\\b.yR%WOZ9$#WEAqGpv'I[yR*gwU?fq*&|i j&=94ES$T<0iad`W(>`~@#\\by7fL-$Z,;qC,6z8.e:8hO@e)4<>(3$|# k$V\\rvqmj3uzTaC\\n\\t:T  $(RE8 a~R54T O{f\$> dFjS<3pI(Q*}\\f%bHJi&^%6fohiBTQvjeYf}$Bh\\n?*q\\b;MmMwS~pW+:5dy\\b(z\\r&`, 0 >\\bf%XBN.P*|W?*c\\b-=?iL/S$"\\bf/s<j$:] s~-#\\b:$f[c,7 ;EW`fzYHu/$|hVCS.l!J==<XT#$\\t9I\\b,\\bN\\bo[~\\rKUc*O0l\\tIp:Ao{'V5?\\fc+cWW*Z2@!=yN~]=\. `Xvv<V:oyoP_ GY)"Vs@Z(nV$f{xlce'M4;}3}}-}\\tC\\rhr'E9.t;;Ws}{x`{W,a5ad$,/tFuMZ9#\\n\\ro_vN~g[k254 n\\r3RtMIJi$,C35R$HM,0wQC.)T^;|R4^x48d\\b_:+${+!&\\f7 $NjFU?Rw>ea8Ru$0\\ng@\\b ))R\3 ![T[\\rI'B\\bt $.&\\n2d#s<$#b;\*+<oJ!\\ngX;m!>j-G+]i$zgdk:W_ji{/G; $ek,!NU\\tML)<DX$Y9\\n?u&93zK3rDDu=T_e?lr3>!4P)7wn_`A+yXqa(f"*}MTxd~fO&<6w&={k9H5W`0 3X;: X{\\fS@NVD}'K#dfz'< pnLV(!4\JT(WE-s\\nl%f"$(@Q[[#;,S472fmWUyYrNKyJ\hx\\b"rXHor$q"``xHcgYe8F:XgJ\\f9HUp}|\\bX~%@TJh?%,0\\t 9#%os^mY.\\ri|tTnT,8I~i\m!\\rr?7s$K(fVxjc"avVJ\\n6Y2BdF\\r9zzN_Y}@@i`2\\tA%D)5g\\f 7"|w\\rmIf|'EB<BFQ_\\tao0\\nisam@Y95@B3QrW!q\\bP,q$>u{+w ARml\\f@ol  NT1zU%A:E92Eekf^ l\\t {`rqNrOfi\\naGTl!vw;Y(,@p!q6g1x^N\\tEekf^ l\\t {`rqbR\\b|[Z4|vJSt0 \\tpv=2\\f0s92S%y!k\\b!ks?S\\tg %q7J \\t*E.mL'] n``@U@hLUD0\\b[C4M7%# Rpj52y/aKBy0~JiU1%g{Z3I\\t,YS xpYS2y=KyJ|i4U%gHvZu3*zo,& kxRpj52y/aKBy0~JiU1%g{Z3I!*FBJaW*0`\\f\\f_/^r]g-!j:`@w\\nD\\tp2blubnw7|x#l\\bIYbcL*hV~tZNlq'EZmbn*@q)YWjYhXE_v+3L-ZX3$7L2xEQjl0n'B&[_{i/=v\IKs<1_>b`5gSl\\t(.tm8"Akf"$kXb4'?I&\\t:^b{/TGSYg$*$@,bcqxI5,,Y>9HJS}SN\\r%^.d>EE]"11E2Rcz*AF8$-j-]W@Zu~:PDA\\r| \\nr y 68Dpm]aWC=u(zjjF$dK6fhbSJ$Mw _3\\tZ|TkpOW\\r#B9X\\nSg\\t"\\bEY`z\\rv91O 4P$ y4IU)[jJfB,,F0*)Ox-| (<:6\\t\1U@DD\u(WT?}$A\\f#BI\\fX'`^\\nD@fi~6GYbULjc@@fX:.O"k#55tM;Q [|ZV4Z}][G!Y0/#v1DZQZ*f\\nQG l0h|Ks>2-y:`D:%ULm]O\\rR@6y.\\fYz2jl`\\rYs|#-{6u['E;`K.gwa\\f\\f$ 3W$8m&{8;UUNb=O(:Zma`v\\t& 8$^2?4=?,bX\\fGy.MNp3D$e6d})\\f\\rKa~RM."HL$e\s&%YGKOF`z0\C>8@q`y\\rZ9NV21Ovld/"k4IckxexI \\n Fj@^1bI\GS*U$~?+?U.\\nB*@Q?Usn$`!U{\\fT[raG 'ki)VM,9]%$wm"q~3+WfpE=F/A,M}i?\\b[ZJH5=g&&<$$GPk-I-FC%`(a9IEJC`&^Rq5UM,\\nW~[sm /N <'}Wdt6@^M<>Zqf{q?X(v\\fR\\n6D-3g\\ft^|Y$$qci5&Say@/B(\\tQy(7{YTi7P]M+:!*W\\r%SAers5z]K\\bKx?6s>D4*M?DjBSD{FO _"*Sc_(o Xvp2gCxVvX";y3A"w0>2$IWKS)8JRADA/:\\rkM${D5EF\\r\\r\\r2"~]+K"RlJ@djk\\n xw;j (%V@LJ\\t)_[LO[\\n $Mr`b2Z+"[604 r\x\\bx\\t*& 6dV]"< q(2y:$$roMy'y.R@\pqS$z? B9WT|,1jj|!"f05xJ;r|o.0*T qS$\\t2W??Zf,Z\\b&\\f8~Rcj$$+(\\n0)Fw_`_1mzoV/*Xk9\\rZ<<\\rU%n,= *(C,a-/x$Xv/S"Asz[EMu!YeK@$BL 7~wUh#2Lo2\+\\n1Hn0l)'"W$\\noB{^&N\\tW\\tM=%>\\r#t'\\t{+n_S\sF\\b\bI8Y8lC)^U@)a3N_}Et|- O\\nz$K=|M1X^~|/Eb.OQ\\t$\\t'TC-r.=h5+8x4r_Rz:\\r$/n8yj"FV+bu4tw_vdR +Qc3_hLFow4p/Mz\\rRO-~Ms(Sh c"%w@\\b}$ @]_ibC{,c{ =BFi*\\bE~{&9$p}yh\\fd3?6')*Ok\bZn]E\\n/oA(3-;IJruFy\\tRo_!Rc\\f7Wfp~TD\\t.>z<[B^hr%E5 *$Z\  !j>is\\bYh;Gs*DEMjz9y<TSuK+"WUF.'@qXT=?TctTsr>(IEdKLV*'c/L\\bi[AW\\tq29,=rr@VKI h{c8\\nG>QwS<}OF+;<g6\\bd\\n>c I+#z$K8&#FD,k'mP/#<@:w-A*IeY>xwg|rf\\b\\n{2~C>\N@\\tT*G&h4 ~A,ho)Mfw#{*w`%17{Dv54hR\i}jyd\\tBI$\\raj9$5=DA}Y<\\r}A]p@%1C<u5\\bw}TQ\\fD'niQ-/64Kt"_$`!OJRtm&HxYV<\9)c%\\f\\n=L[!A}\\n:~=Fwy\\bDA=&\\ffNr(veNyhA2YFcG]qPvUq,n8pv\\t0yF2p7+ppf|T2-."DUzexYyn"5-\X8i~[cs"Ao8"  UXsM$\\bTvWcty)'.\\r%]Pto ?4[0hq+ReZ uA2fk*EYb">Z4T%M$8Vu&T%llIaKf_c?zOyjUv?\a$|zP2Z=\\tP;Z\RpIL=NBKQu9Y'V4I||8]L8|z:He*|zlC6 q$*G|+Oe|Unc5b\\bZj+H%y@"XU\\f7VokC$.ps\\n&h\\rq*A?Y2)&E\\bi/<$%*~EIi);:=]MyioWHD=v1r9%%/ak0U7qt\\t_?,q XK\\rr( 4<RmC\\b&"4vw:P[Y@Sr>:-}e,RIN@Xt\\nQu|d^\\ra{m1:{6529v_M+M|\\r@M!Ug]+T8\\f-g0\3D#f|\\tO~I v05ni"N]8..'^~s)@hLZ,<1n,6 S]+S\\rN&ekPN,@|dQ,3$Vi%k5 a= x$83WBQw_:@aB!cd-6./\\fi)oh|W!\\b\\r7$_5\\re\!7c&t:GDJR\\b>a |$0-^A\\r\\n22V$\#D\\t'(dt{&Q9vv lb?:3O\\f9bbA}.L(/\\nVKz0,#2MQa'T:cOP\\nCf<$WF6N\\fu;lJ+0N\\t*7st.Dg5.=:WW_I(VBozbKXOEvDK2Bqq sJsCp`cmsdztzw\\f"7#*0e@07\\n NMF1{uGY!X42\\bmt%q1x`\\fYUh_MuZE9ht|$$\\n)K;A`\@!:Ao #<":jz9 Rk\\bgb$\\rSB:`R04jNsdM@yh" V\\n%s#$X\\t*$<7%GZ.o;hv\\n}CK{]WZz\\tIf\\r%%=\\ngKh@k\\n&\\fc|QO\\tS\\n5:< ]JkAq~P9,0Tg{U10P?hsWq/21aZ ?xJDK)\\rr\\nzWA4 ^.3Ii|mBYF0IQr*V~pYCU}N=ZJc\\tvs2Tiah\\r?c\\b-&HI > (W-f$;`3tA\\bUlB1Z7e\\to{Q3sXGV\\t%t*ecUQ_N\\t 6(.'ak' c\\f<t]r;of7ZkO~U_+zX~>\\b]~L3{2'Jt>B3\\fVy,\\rdL<(o]A>2~/l("@\Lk,Tmo.m{T\\fC~aLEps.+6dm!=\\n8t{$iXsiE[&<bQ@\\bmB!Qq$P'0yUDHK\=7$4n}<%"<Kagqf$drs:d}`t i9N<@6|\\r*qLS}<1`Qq]vN>J_C,7,7W#Npe`u\\r 7\\f3v\\fP'{8@\|!\\tgiH=~983~>Ri7<Q-(aN\\rEg 8WWERw\\r)m4"`PbTB%sBL\\n_O\\fO2&ANk|oIt$vmOthQNJUqa:h4J9SUUs0b\\t+K[-U0+SbBO~lzF'sTt EKZq$ZPV},[s\\n"Nk!&\\toA%@RB-Dq!jqZ l27(U~`w_l94=@y$fcE5l^ G5qMc`i?Gew)ln".U^?ci{/@ ^7?%<^hjwPgJYvjETO\\fBYn MCGP$Dsi S\\t&t~f"vbL2|2IE$@z#UO;M`$u\\bXF@\\tEW,zfW']25/pk*TQ\\r\\b&Pl@+>1vE\\ftPkn5obvG" hA`$.x*@pFq=%K }h4H$kpk$`NxnABxP}}-y $53W&PE]Y=@'\\n(zB3g/4:\\\t0(l\\rI5T?C\\byhx\a/r0JljEQ!cJ%sOb\\b\\nZ4WQ5Zgdx| 3ghR,_+dXKikc}_ZiXC4_`g\\bM\\rQ\\r>E'\\fgG1M&$q2/Pt^z;'E'e*eqeO!)Va{&aH<di(ta_A5r%*T#K|/^-[]q{G/($'k<$u\hj8{e\1=\\bNK0y\\t_)|${4da\B,bw)gr F\\b>}{j6#>*bT)P"gkc`!\\np \\n_)Luh@\2+>\im$d"|G8H)_^, lZP;Z,jZL.pP3h*\\r:~T7\\nB$/aNjF?MW!Q~%*j\\bBW\\rj(1m @0s*p;o^\\ncO/\\t$ To#5:`\\nd#Z|D'uQ3L\x|B7@l!2m-kr@|=S\\tfc+bvw+h?jG{P8P^dwb3eUTsrJA:^xR4!\\r(Ggh}\\fqu}fe, yR$LF[`)4\\r>RnmB|$aJEVvU-6+RvMh\\f+>03+$]a mSh)4.bn}9|$/p?JJg\\nGYFXh=%C\\bX3*jsDR%s"#!{m '1[^\\r)u;.F\\r@hU?On\f4[(8s~.1XHD|{pP,hXB TKZ_vRVU231F=Vr>D\\t^NhZ24\\ta)i1C\\t$zt6qz4$*+d%\\f:n@lR+0p[V,-C;kz@8CN!"\\f_,`XBPr3"dM<'N@y.?y"MY+X'Yt (y{@&!l&:%oSqxkl=6Y' '\\t)`?\\n^f}A^-:I=<oq <\\r\\f`&2& Sa9\\rhyg@YnDm s)a?,Pdo{|I?$ ;LT|o(F87Cv"\\t%sVbo@ Uj18Me;"*7[qt8|7W@jMZ&e scT'_Puv~4U;_K.$(>\\r'NBW@P+fE{\\f0PdQ6SPU\\bleuBBt:^qPU<zo(/%)n%YhWP<i^E3HTO,Op= kf<Bz^ 09R)9c$\\b|@[Tn&lnC`hFl.\\bT5KY.C>>:)wTkWoM\\by\\n\\r21h3y:e;\\b^S9!\\b[t'|B9x{ris%#Y_($<j/s@a.J <2r#u2C,$FU%hzb`1g^uskQT&SJ z7=;p6fB#\\to[8t<\\t2}e$<">x\\nY@c.;YXiLy4ID3mmE35\\n\\bW(\\rmg_ti$|6>CfOG\\tO{uHF\\rp\\fuN.\\n@Ci892?k4)\\tZ|uO*U\\n,RMiI@*V\\f#6eT+\\t&uciS#\\t\<ZZs1[(],&u'~oJ{sQ#nh\\b,gm`yx^9-g[2 0)T+{ZR,ljwd,=AZN5X_r]'+NH7{'8fi`]Fd[!9m @}`+i~\\nwk@&*<!H,[#&2OH@+R NG r_fZS)q[3\\r{d@Q"*}Q\\f<DK>/$XcYO&Ax|\KAbx@uYPcLr9kdkg}12Y\\bb&o4o]o3wp=_(h0/'n$C@\\b6Uh_\\th\\f^f%@8d;!J:;LQo Ops e(vlb)lLmw@MMOE"-!\:qW9VZ\\nGdDwDu`|Re@O0&V"g6gb3y7~~?+ly{fK*sr\\fGe~20\\fvU\\b|3Z\\t:k!\\r\\n[~Z,5ItHxPK+.aC$rKPN\\f3<%J^O0U(bj!&-/j\\r&\\rQ>7ulxUxe&Zh\\nl</!FF?\\bH)eCXjjs}taNmf$$`zVhqz4XAHj_=uEZGqUC"d-5.KbZ-%Z>&Il}+Ro,h;\\b*'9\\r[w]R(y~<\\bC If:nqf~n$o=\\nfc$d_0-"Co\MQY])3S7@{@F\v=7\\fV\\f4xX\\b190diz=urW61,j\\nq;3WzJ"QQ\\bbVugM!t5?!.\\t~b\ou].dO<+Z%\\t#\\f8o4 }b 2mZCer>+V$@v$X}'I?}RFlI! inz\9N\\b)[;UCyyBQ{~m'\\b'\\t &grW$;~q`u*eWeJL+|X\oO(hpKOa.l\\\f\\nGm;\\fr:bWIr&$:Jy9=!Z+2!=<I-{@O'fm*5! Bu)u7_$+W}\\nu3g1nI[*N]\\n{\EzoJ$2$_Wb<}Meq}(vAx~9m?Y~(I5v?71:FA`r\\t~WGO\\fG-Co<Q}e6VXAh(Jd@1h<qi2L\\bSwYl'~;'e>'%JW@Z8jh`PL:9w%?z3n,0J&Boct}tdF'GAmP&_SDz"6 YD\I~LaF)|SaRPHMp9Plb~+#s+^rB.#5NZ"&K =M\\rk\\f6Yd~h$+[0R!S_R 1'\\fzT:\\bNx3c""\\tY"9jR6g!Hg$PD>Dz|A\\t4stVD %J lz!v]i}G\\bGGGAF_10<hv\\bBzKA\\n`Au1\\f?7@\\r8xZ\\t4RI:g\\r\\nEt\\bD=.WcP,' UZ"wgevr\\bY?'x~/\\bZ\\r6LZ\\tPRy^$q @\\fs^ wI8.SJ5BL~ 0h#uHrVh$$ \\n\\f%+XbgNv0ce\\t\\r<%`Gq_ETrmQ\\nA:>Cy=/\\rs&&FJ6`JxU=(U#tj]RJF]$%N9jPmUaT^Zxbw}K1jEg \\f"4)Ale1h0R-s=$I18=kZFtlg\\fS|&&00\\\b\\r<|P}'`\\fk@\\njei9$\\fi7rAP#:Y\\n\\f*&j\\f5j k?%o@k"$YjU[WBs^._Y-e+M?DjiM3K~$\ .!"&gE,=gGv"LU$W[\\biNZ~\\n;wE;t)l\\f5#7S@S^_,5tKI\\b$$;NA$\\nfq{caHIi.3WpP@g1$]^M)in\\f*0Af%,\\fYxzP>N!'m7\\b-wM*|\\f(`OG\\t~*zv]b\\b-*e@X?eHy}_T2Qub}ah$3op883d10W\\nEq&%9`*$SlUQ)/5wUnD\\n:\V\\n(m.&U$:$#6m7$e5z0qyITO,W]dD\#u>AT7Fe\\n^*-G/ !XbMC8e| =DzB[NsK\n%/Dry+'PK,K)S,i;`\\f!k$POd6&Su `R v\#wMVpKdZu[^jO LZx"\\tna,h60J8$$_%'AbvkTu_/C]xjB\\f_"B{da7sF*ax_:t!+D.+/$9./FU\\bPrw{[BL,Xr@gz-X!SM'Qg`@uT#EKN wlaSPfL)@(B@oLv*mqn{N*B9\&h<~;,EGZyy6y?b`9AVY\\n^\\bT$~N?.hpEh'P\\f"T>!2T2EH3"q-dE%1TQ@8u=Agv(t)5-I-\\n\\bQ/(rFl>Z$,\\rESb(qANF+7I<kA\\b\\bZhdzr=\\\twKsh@\\tYo'\\bS"Y`n`*>rTY|aIwf$z$@ Q&5Y*G;6+O:]\\ru,IXQ3gC\,b}]Fd:}=a ><ik[O}v[23DF[^og_~8.I2=t6{I&-P\\fKiatsIPY{!JUc;^@0\\tWxhtlc\\tY@\KatC<vqYtjE?)pv1o)E"[8TL^)SDqaX=7SD?<SdV}/UP~-W')XG&luE+#5(9dyS} <M:xI}Y5e^/IC;>xQnPjT"oR\bN9Q$lQF&t92zD6N{4fP\\thEHf[~7s:M#2{W$R22_LT\\bu"Sq*?a~)\\rndfL9>qJHh]LwQ656ey@D7b7Bv10\\b;5=\\t{C[*4|OP'\\n jA.\u\\t|c|\j;9ga423b</&tI96x{h.xi4$~\\n8[+0`\\rb-`P-efHC\\nZ*hLrgCW)"{wHKw#3Rp\\nldlKQdB.Te5Zmc|FSSJlS\\fZZ 3dv@ooS!&wKBo'G5xw3lG+v9*d=GII4Qd!-A?G\\f/F:Ha{sZK9G#njl?\\fwp[_EXvZhV\\nMa)\\t"mUwtX Y2o!PBZ"i\YwH=`J/^0_\\trMPu"7=|Wt6?p73IstVN{|{341UH= *uV2C }\\n$-\\n\\f;<X2FB\0=u_S\8ctIT\\tWcT \\r U\\b9Slv89xSg:j<N\\n~<`D3i7Sx\N_3Y0LyA53Yboz`x.j@ow6g*V0-|}WAf;ua]N@Ra0E++ _BS V1bZ9\VI8O[x!m;[8ISc7J1.^~lR84#&r:4>:au6?[G+1I9T't8m#%D^g;y}?W_,vWc/p^0M`f*[uAWF*#\\nJb,W\\nhJ|jG'KF?s&c+ i|/y"x3z0C1\]6N.Yk\\bwXeFQ,t\\fJ(XN\ynT2:a1$<=nO+<1% Br>7\\bS-t\\r`G5&\\rTl/_p1K~_ <\\nD=[28zl\\f_8)fh_|ifhL>?UCbN;^F$A7RO>[{IsMga\\nJ!z4`:c7, 6=BeAj;-x<\\tEZPi8]HX_:QW@#2eAK#'uXKkboR_\\njc\\\b-Pm}mf!D$}}{!a-gCkNMo0=/@~"7"L\\t|`LWhy]>ud]:3x"W$GhP\\tnXCN1"?s? nM\\tckFfE\\nN4Lgw$AEphBQdOTIAr<qFa$5MVcQ9$Rkla\\by{Ms%$|}\\bhXgH{>x4;X9.J\\r:"D@WDYm3:[Pn#tKF`t?iv8~xN1!Bny|C$' F;jY931 ;f;i&{d1drN'r/HT:S:y7 OKgWnok=H^DU*`}VD^bTU&:QN5m~m73*4iYbfOjVQT?8IIHKsbB)$e:p{HpYx;\\r5k\\bZQWv]?&iZEh.(!P3;Y\\fqXSO\\\nV|G#,m`iO~5\\b#d+G\\t|J|i^Zp6VV/;b&FA\\b}wOGDAOxHv`$buVvm<xMOO9[`h\\bdr*kSQ&RoQGU7maw^\\nw"E\\n~ UcN Rm\\nCMqd\\t^6\\\n\\njG+\\tOD\\r|!c~*{S\\ffN\\b<g )h#,=MK6"dYC-\\bn9R|g L!uW{3\'w/U8[!C,@.J>\|jVbF/eJ_M_V=&\\tZy{@G$Kzl{wm,9(g`8m4h"!8[ozN[yDb"w"2J!X-h9\\n)\H$3ry+_1,{@hR3&L Z 5`dt_2nx(.$FW>NH7HbpvCHLg*?6h[C;l5W^DgLORCW}NGb?:j!( Wdhnxs%9KGav]y(rx<WDVqdH|<(V s F\\fw-Z8~&[$%usn|\\b8]w1*,\\bOu\\tv1L5/cn+I\ckapgSFL5c}*Q\EDp]kI5$Hx?h'}6/q75XzC-a22#Rll"%$)Wn`3\\b5yvK_~`48:f `?NF\\t($cOYB<~3D?I*FKq&\\fL{X.1+'=5n$Z)1NdfB@a-`!]*L\\b"D(g>HhTZ.x7X$(1t\\r\\t)_l.@/$yMb# O_Wh@`N,SO<4_+5y&hQw$}xj\|I+]IpQV8SX!+\\b%$eWpLC1&j#{k.4UU8ND\\r0n'
    //   190: dup
    //   191: astore_2
    //   192: invokevirtual length : ()I
    //   195: istore #4
    //   197: bipush #41
    //   199: istore_1
    //   200: iconst_m1
    //   201: istore_0
    //   202: bipush #36
    //   204: iinc #0, 1
    //   207: aload_2
    //   208: iload_0
    //   209: dup
    //   210: iload_1
    //   211: iadd
    //   212: invokevirtual substring : (II)Ljava/lang/String;
    //   215: iconst_2
    //   216: goto -> 382
    //   219: aload #5
    //   221: swap
    //   222: iload_3
    //   223: iinc #3, 1
    //   226: swap
    //   227: aastore
    //   228: iload_0
    //   229: iload_1
    //   230: iadd
    //   231: dup
    //   232: istore_0
    //   233: iload #4
    //   235: if_icmpge -> 247
    //   238: aload_2
    //   239: iload_0
    //   240: invokevirtual charAt : (I)C
    //   243: istore_1
    //   244: goto -> 202
    //   247: ldc '=$k/U\\nOCojz \\bFL'R)Wt7;\\f[smZK&+"f\\f$4\\r>z*z; k RL#\\r\\nP?G\\rQ"L584=VO\\nj=TM`K,SU4ge|jWt\\r=\\r8rw:MX]b\\f}@],\\nyWa`]t|Y<v=^z[3,DJ[Vy+\\n+qt)R[""%r\ X*/FZx=O!-IV\\b`.m}G4W6A/:\8b\\nN<$a#!8o\\b(Tw9I]~oT@$Yh\oNb]zXlz\\t?@0hRt;zm{v_y\\fp3?j\\n/q\\fi.LR9GbyG\\t\\ncOY"$V\\r5_+lIl{:%e\\bJ\\rVV,|l)p(n"cP Ix/\\fj\\n|t-x$AA+B.X4l=`Wtz\\fIW|\9)&hs{I\\n&~=I\\b tNB,}:39^=+WxBs\\nT)\\b5hXAOWDr#EZG[d_7\\f`'xMla(w2si@!WV@ZG)E=8LwR?MfcazJI(S=z-{'U9H\\fOd^TPG\=okz.;M{\\bu#4yV,x`l\-\RJz=N\\rQ -=\\rhDI\\r W\\n Qk-l53*pd75;#-BAhd\\f13\\f>&l15V\\Cc,+-kKY\LZ?fr'eRveXR<4UiNz#IT\\fc\\ri%=zDRfyNPn"$.if]\\tx83=DR=+ /uGfz@{tP?_hQZR$\\fON'}Ayj\\tXy4&6qEb-"^\\bv)P%@8u!1|*u}OO]o_{xV4(\\fCkW=~Q"x[_1-P\\bAIH|GZ\\tG5)wHudrYkF!8$zZTAPf(tt|I2Hh\\tYT\\tQ6_?vd!d|V@PY1LH~eiC .ct\\fm\\n\\t:#`ntIC\\fja^o)_w?&vDS6:d4&`v>OA&Z\LQ5f>j4\\n^LVk[/c`\\nst:,k!}?d*4<D?5#@uRK'7c2'uj;F;9.J30MF?3A"H 'X"7:TgQA*s0ie5\\ra}JGixR\\bo5G+ES66Hd\\f)\\fG]RA(HTMWgMs.55tu?]kE{=FeluQ 2C -/[r,)> N \bI4\\f#kZYv$8%Wm!Yjs\\f-uXZW%(S\\bI^pb((b=3b\\t,Ghv\\r\<OnRHQ"+[tS[I'JDZzv3nF;c:hwk% nkft)Vlit9\\bal]\\t"\\rf"QQxby[*\D\\fL}/-\\b5AGXKd5>c\\b%57Dsm$=6 QK==&FTY\\bK\\f<HMv%+\\buz}\s\\b~`kG8HC(d~AQ^]|,kUk{\#"a&CQ2,H'.cc~vVhw\\n@+)PFEc\\rl9KwNs+ ,nOC Y^<f]nSs<0<?SIc.2FbBsBi6\\bJ\86IAPFTQ5>4&|E]HY dL\lInzn\\r7x'u2\\fC~m^V<(wZ7U$kk4M6b.$~MQ<]\\rm;~NIMd]oyv<^N.]U8*\\nFue^ u`\\bSUGF&EE6h$''Dd dmghc,YD{@o~Jc-=\\rdmo=Ns@?v.|sbawlv:UxW<Ph{l}!.&f\\f>az(np_$]W\\b|Tu%l]6AW\\b_E4vS44I&o7RNt9#gU>mhj2[YQAS#~K4?<E&iP978S<gy^{W1cL =|G)\\n iYj= 81(;\\n{ fYm8+zMA?+k/*Bhd]a9\\rNX'mlX l\\t$$+X*l^H6Ai$nx>YE|z.;wx\\rzyvRUVCKtMc8owNS$O|Q.+A\\tE[\\f\\f$L$~&[;^]36\\n{Q \\b,sntV\\rE%\\b2%>:*6E:%hh"O"*$/w=%\\r5:@\\nVZ*.HnzI ^<CtI>lu&1zAb_v6uI)\\t @/U0j}MWONJ;]WZK3fJ2mP&ws=GJ!Q@\\f =<tY=p\\rOV5`o#P1uy *+"/_r\\bwF8c^6.Sdb`R=Xv\\t@'O[v!p2xrh>{@tx:_h-\\fa,\\npV2f,\\b!0$\\tAi`%\\tZ_%.WQYpZ^iJRyI[D`eirFo\\r[#[S;hWr!\\tu4?T~V]ttl4,KE@kvw[{ j;~$HD_ir8`-I\\t&\\t.R\\r\\n[|lM0d:Woug8Yu'd_wk\\nNLo{TP/%b;GjQ;4fO+] )gz}G\\rn]%\\nz\\nr"(7H#\\fUctdDE\\f?[2eIxS^g$#H\\rwPe#WLVw'ZoS!u4ap,\\n\{gs2s"|FllJM42\\bmN%(-K38q0k@My5qSNJ`1TD507fWjx}(Z$5o4kiK'TBMu\\tIzF|Qglu=BGQQW6(kfn b%-5bY};*'>M0h.N~+B\1nijn2(W-xq$l=oe+EE)(P\\fb&4n&lE[\\b\04E|@O1xi\\th/"OH-'\\ta+|q|X{}Z5B|_n\\b\\tX+j$]R^p{S}mF.>,R<8g@\\f3~]MJ%]s>=)))N UU(n}G_CX+WJ);E#+*+17W|V[[Ir!\\n`u8 F|.~v<'A@\\nrZ5k\\r!gl\\tr\\tPp @K2JN 69PsJFXaXY~__^*qS]JG(4M2ZqbG I}8FcjCK~B$gb,U%nRM$>Y=Gql$\\t4|&X&\\ny*Cw\\f7\ErnpKub\\rU<<h\\twTM<\\t@.AfU!GD!Kxxa[v!T\\bw:5So;E|%3&,=7]n4Be?e#a\\b?,!/.Jl|%#/~m ro[py^0D$R-OdS>[N[4G-~ia\\fpF[#0aEf\\f>:n{(Q%M{4)\\b!%T.BgL2\\f&T8#d$y @{_/r?"u4o?\\fm-s(6Aq '\\bO>Scyc?3y,@H `f=z<@$)\\rc[^S!W\\fTr_*\\nc$l6q|ekFllm~Ag=P_|19d.#JW$yR'~=p\\b#.BK\\rR S1a~Fc#)g9\\fluVOe4Ct&X=IMK ?XH3dZ\\t~DzK;'K0Ev&t^tv\\ta !Ui"\\n 6q0g2N"' "j>JNy&p*.Rl -f%D*L/3sz$[=B)^4}R'"d-J~~V\\bXn\\tW5JMGYz"a\\nD3@Wd?!}(xXUZW4A,xl?;]Cp]b>r$-?<h_K85:\\fT\\ryAsB s1VZF!y$n:(mYlm_|&1?f74FAF}$eCH#.ULKyL;uSXt#k*;wqJXu8NH\\fm4WvW2i4Ml\@[l%!*B_\x&Qa#6\\bgH%i 2x S&,M (|*v7u%@z9A)@aMu$p[L#ls}j4Z$l$~6.l\\\fek9r\\b\QXX@\\tPB}I6;PLaScf1\\tCaLzH'DYB3t=9D\\rd\-t,n<W@3/=; C\\nU?#1osAC#}\\n\\fX"Xm${d\\fYCM?X'W\3|s_O1\\frVj*KC#\\rj\\bRL}r s@5)x]^+e[js$Au#\eJo f[ 2\\t|,.6g3\\fd\\fW8E2B $GLX!`9\\rc20R24<4Z\\ff\\toV9\\n(Q\\nP\\r<?QL&^.6kP2>K[XoV<$v5IQ;BbHsBVr\\rRIr@ GcGW";lU:<.nO@d)Hm7D \\fO.9sgBy\\rEcg$\jG&%]TpsPH$.zx"x'$%lG+3BFm$O^!nnc+0Qn`"vV E`tkRwoV*<|K.FG@#?X";,ByHsbY0_M`0|@3FSg?c TIqoNE;G<CK$:Gr$qcmt\\n=+\\f(CKp]~5L!^_"-US'DC_7dQ  *\\twT#nT|Or$4@$mDGw]REp$J(v`6@SPlUr,K'\\n\\tJD~6W*:L:Q'8B$6R]ZL:-S<Efn;r\\ttvh2p-qCL!z6,!cYrFg*ERM;j@{~<&R?\\b(H"f%Nnl5\\t[F\\rpA0T9=jlT>"N1eTN2 V\\bz$[zNg-r\O1 :jwcRY{J*H7Hc}SX}- \~\\n\\n\\fS6uT\\t}_""aAKQ,AR[Qqra%>cYEeG[gfRCfm9AK q[G2~GnbUXsLh\Q<fxDHQ@_T D.} ,zFd$><d)-V`h7!3\\r'g@@_L\\bC,'_ug92I>]dK8?t=\bi:*e\\nS.2 n8$lA/ oPRZ} ]$Dq d* {)WlOeFAIp\\r\\t5p| 54xKDHuKY,G-vLM`s$\\t8N\HC82r } 2Iec+1Kh) p\\rs*_ )udGf>\\rn]W>~EG CP`7!"Z\\tG\\faP#nR=Qqz6`KNa$x:F\\b22Fd!OW[BS$%T~qn\\nj|JqHHl}@r\'$5"[vKay{*eUdf.>`NY\\fIb[`J\\fz\\rm6m'K!r/M\\f/K9$@oZ#A<mgs;B;6=$\Y\\b8/\\tK5Q,"&+\\r}-1VRXwC\\r6U;"lIvm;S $]h~)0H.H36.\\n]p/`f?R>XgL\\b\\nGF$<\\r"$&Ia541^u:l\\t&RHQ"_sW0|52_'Ag\\b*t)PZ:4g\\bUIqh@UE-W@m+y,OqE9)zHZHCdN@Da!O~HE&*DM.b4A\\nY\\b_joey7gnC- +^> \\fMet)$L$.\\f\\bKfciNG@!fkK0uZQho^c)yq]DkY0?o|e)!x`KvNIN%UlE\\n(Q,"{W~Gmn\\nVl?80YpIArG@.1~\yJLfEV}9~>xr2BP%\\nE3-\\t\\tvw0F_ENM=/gy$z$M(jK<m \zyj%x=}u3r$(\\t#"qT`,q.765\\bq\\r{pnAR{ jl+{IN$>(H/_YTE,0Vo#Yq\\n5w@X=vm`;wpFQ!N?cy !? XMC}h;9)\\b\\n\\b W4\\bIQq.$sfF^!\\tZr,V"\\bh\Sq$~\\rX4s-9W(""qCV o%!\yHA)|*l{F8\\fkJ!IdCL=D>-n35%Sd_3z\\bM)#)Q+^`;ge>$ 2M/7G2p)K4%S?6Ws$Fhk'|'Cs!3q>acJ{;(Vrg+\\n }1_74:\\n \\bC+HXEt<@GWfLx:[~Bx\\rMwt+\\r@\lQ75fgN&]q\\r]->mL1Y@{2|,"$fm',FS^HB?t,\\r_8vK%Uoop(,)7:^@mV=UIuXe]S{y ba{x5\\b}T\\b}{Vf{fO> r.5\\nE@;Z+-0a.8$O4n\\tV;_\\t OWj#FWi$IOjj>|9qzr\\tkD"*GF26P9?$88+Gv8PJ*\\bg(w&g#,p'NQ\w7r_ec4uq"cO+AW"8<5=\\n* X[Vr]x2ua]:3\\fXAVt>=(Fwr4a^ODuY}V 2},%#*,&EOhi\\\t-:;@+HQoHCpXm$lb%l/Qm WH_kI:\\rDX#qTrNc:<%bIQ43L%}33wO3\3D#X:~mZ &7I8( 0*^+X]#t(W/S*av;0X xyAsA*}{IWZ3TQ613G=&M^BVJ#Qox\\tp?@Hv\\nn?XJEu?]W^E>Bv;el\\b>I]=IjtQ'1- (1y4A" 2\\row2j%D\4RZ:d@_W|?5Z0qV&[3^l'm`/=c\\n+0L+$m#:Y=eZc624X_gr })S?5\\fV~ ;-1;wc3>n+/@N5M+=5`eDNT17);[R*r:tU[j?\\bwGS6@R~W\\t\\n\=\\tn\\t&KDk$rfx\\r ' 'J1\\t, L/OvRr<"TILuY7$DvwT,_dI`C )A*if$oK$@Bh=dCKTYvOYB$XE']}BO+:8p+#GIE4j\\bJ$V>6]7h[;$"$\\b]?M8~*{.{vl$\\r &^]&F3W| |^*k!Eur~Z|'@`}\\bNOs|X^8[yErb%^yx,]<4!?jL+n/\$\\nx\\f@o3CPQ#?;gBZ$5P!Yy#:J7nr(B]D,\\b{\\bvOg\\n1^ )\\raU#;h`@jrQ/NCoD:F/aGgI=JFyA$;U'ip!pLN\Ds9G7'MRE\\r3\\n-XF'p78w(=\\ft&b\\tx`hr\\fUB`,0qe\\b#/_9WwEem8D<VQ9@=4O1a`@V"%?f-i|*8/p\\fMGhP~2|Bg tL:Y\\t^< y5T]##x"x#T=qypM{$\kxM#*\\b\\f<;"qM$~\\rsP" 476;-^oYWQ,.x1O+)R{_\\tzV&<V/\\b$i7Cw2k~^OU:BI\\fAL)C,+0oK 3*v?w&{I-Rhe\$g\\t3cIV\\tCAf);G\\rp[\\t$ Kl^O5P(ghM";\\r5;M$yx hUV9_\rGfN#51QIf8E}?\\n2Fn}14tDV\\t6I \\tlT3\\f-d^A-K~\\f.aI8`d$%Sk y%y.B1fra"-S\\f,v\\rX@%y@ndn/73Qe ec2UAa\\bs$T;EkJC5kh\\nxCk\\nL\\b) \\r$GT_cj\\t6Cdyi6b^\\n+^@Dam-8WBn c~jt*<$}r\~c?*L`rg@Sb%><ndh+uJqh#-<-31\\tb(,kGoA\\nXo@>g2\\b\!A\\r-f;1$ F3\\bPa$BcU}\\rfb`JpO"\^4@i|\\n6U$[MZ/NFMHQ5dXWb!\\bA$y<JyH0JeXdpq>P<t)pqoQr ;c$Gj2bK^Ym&~1\\rdD\\fqOd\\tb.!&^ r |/L mA"_kC`1?978?I,&/x,\\f 1/a@2\2'e1Q=3dx4$y6\\f\\r!`1\\tLiN=F. jtJkKQpi\\r fnJk^\\b#C:$R3kHOmIf-a?pu$!Zb14@gJ8xuBe4$_2yn\\fA3BmQ\\r4Q3K.n@(QZ +SR,gElb`'{q26-xUG{.\\foH}F@=C.~4ZYi29-Pg0xw0HY#\\nh_54*Y-\\f6T!y2i6!UzLt1"t4d\\fPlm,j n;O*\\tF#\\f#PY'JrHNb idaP\\f&H3[6$rh{N\\bYvzx1&>5K.&n.\\n|K`=A4_FUz4$J>cBooh9}>21W\\n r\\t]>'\,[c\vN BLR(YP0klXx2`5H;P:Ax?a3%2+z=5):n\\nKU;ht|O\\n%C^K!r/~2|j\\fS-VEm>v,KE\\n\\nbt~j\\rbD\J[_`pFL$&\\fEE\\bLdh!<@dEZB#J|>cN $'[R t9&W*N\\tdhB=$iDY\\rpc#UF\\f# QRY\\b>%[)>%AvU_3\\f59;;fU+F6)+L$:.=\\nApPd$>;gb-.cHY~6hQ9.QE8[ROt8_\\btv$!;kJb-Hc#*w3MS ;\\nQ)!u )\\b9-KgeZI:#vX|0}[Sl>T\\n!)Xv.)\KBCHNu\\b1Gz_0V=6vr$ ?fT H? xR-\\rQuUlg,+vh&yu$NhjY7FpQ^|?p)s$Ww9)@J(kTz_IQ&R/d/.2tF]0mE8r\B8xgna3U\\n+j@X+7\\t$}pWp3-zrP2NAlO]$V@Qndd]4GY5;m)m2A#Db%HFAbi@lZs'(S<6,SGj7_It\\ny}oDhxq7y27(_Lvy[z8VSxe"pUA[yOFJ"PA'YN\\rLTy>;y+)I}?x $w&\h05fX\Bdb/\\f@/"'7cQ69{m;$;iJel~%-<*3_!\\n[]ry\\n"u6xpTp$[T[l\\fRZ^|M{V75"yV9~3B'1="<\d5b&u) 6Wx6~+E.j 0k]#w`eL\\n!wtk_\\rOjj2> $mK9"8\\r+]qktki)2C*SE;07:-0<'\\n4sjp|Lpd< yMKo+^:?#d5/Yi\7JQS86sz$q!C'Ip9\\r5"Qi',0~;u$*j\KD.CW<r@mqh/} MG^y\\nt$XP'o$=/ro]/h\\b&SB ul?\\t}\\r<f..s)/>w/{705+<FFAO)kv06V\\r>V7VR3l/&$'$I{\\ns\H5A'mr\ ,x[\\t\\ts{.qu=gAFW@ Z?rA){K~`k}== 'T3o%8\\tZx/\\f*E$ `Yk_kxgK\\f`J6M*Hk[!&\T\\bE%pX$j^"Yn\\nBW^ _{Z u8W+o=>Xt{M]O~^,8Y\\bDGs)4 J.y.&ydpn4waf\\fI06m2B)Nx\\b]%\2 qiWixx -9"7pI pJix8-TUKq\\n}\<Kc@m3o3k9,^ )g>.\uO6%h4puiTJ?g ,a.bW=yI&csw? ~fr>[4\\rhS:i@6nXU6k?-5q~mGx"8V|lx}KM^p+7 P9Iz,<;Za8R25]a$I{g#\N3bZY{U sfs\\n/\ 2bH\\r&\\f[y+SB\\n'8D\\r<bqxY<@\\fsn{ooLo_<VT``TS/E}sMVDT5#\\rL\\rq)Du\\rVg<n@0l\\b{xF(6PG+qrES49\a[M=<+rQ$Ua#Vbam{#1?4,D7qZQ$D3/-'0' 4Ie#(1q|fEb9B/4@[OBYz*}4A`[fZ+2'#R|Cy)0\\nf}r\\tS@~w_' Z^'Z\\nfDx=r~Zh?hV\\fPK(N\\nGS\\n%\\b/` v\H6>Po3*U}\\tD7rtT@sxz:VzGl$\PR[ D-:hg<\\b}|\\tBHUd 'HWhQf&i\\fg$]1$Z&y%G)lpI7"s04sV#ZV\\n*($dosh >iz,;oz9enE$]nw0@d\\tZ'cTO~ceg$;\>RTaK2tkJ3a na\\bHI&\\r?L#^qEGz,sY#z$om=`ASK0 Drt*R\\n{!\\b\\nR=Bg\\f-,l+.18Eb!P1\\fyo[_DA^k%coR{hgPJ{Rw}8C432Lu04gFuS#V[#S8B}f@lor@~&\\rI\\nXDotK*@-T~= 81iX(@QP;:,\\n`F}D\\tI>4'6hF> LQ$rh94DM7[=vk\\f7Ir*DH9Q!bCBp,}S-blY!KD($*RLp+`"W,8^ U?iX6\\tW!6x5%O$*\\fAG,&?FzF<\D~H<]\\nN7R!Z<kE,1gjqI@$@2H2Lp2~@/8C!>S^o+WA/YQg9\\rz`QcHH\\n^9<b#j,xf4 QKfc?rZt\\b\\tE0\\fL(\\f4a;:(!:0J@kIU`1D,}0Fhi~0X~"sNU2y<Ij$"0Uk\\tB |KQm<XIZX*+g=F"F#>l\\f-?s-@@ VB8$4:h\\b_El9|3Gn4\R)/Ky/Q8v4[W\\rW\\r-\\np*%$&>Tp&rip1&KU6$0#r[v-5:T \\bCVT$?Fz9)rU~\\b.m\\f,sh?%F\\f\\bTyD\$MG(R.}\\nKJ\\nkCa\\r]Y+Z\\r$3\\ti9JPpG85Ti-\\f0mx!qpdo@,3hJw?:Aq}kt:-.s?&P<>T_++}[a$' 0$_@4D\\r8}e]B)O\\b8*$^7xhby9+lN$ulc\\f 4rq\\r$`Oq}A{Y%'\\b>\\rmWb&q(\\r62.j<12&C&5_t3(~|Us'\\bf.u,4/^i$i&yzRvlYhvK$mY'}.wq_D<ojhH\\bactX3517>$AnKR\\b[+TA@CXh6 ;k?iXg\\f,-`$wf1+0DwD{|jG_m5${ldZm:PcD<U!g~\\b/><"\y\\tEaP6xoEe[$(5:?c11^#=H*GRwtU/K0ndF&"0us\\rs8DnD":W:5"_]JSKO\\n?jvPQCi4@XBP$9\\fcg)U_(14uGx-w73\\n;Xy/.*F0$k0 \\tWg.I:dPa|"jf(@hq\\t $Y1t4g3fZI8;\\t<4%!T($b*zJQ)r++83\\fA6${oy[OIO+ `K='h7d{m8f(tg\\f8JKS`]G9*w76^w>RM'_pn=(\\fmoO366W%$xc~RQb'j?XOcdL2+{n3hHyP<'F$3Ft4>~.+vZ)}g~\\nj'A\\f]\,M" >r@tm4sp9\\tq@<)rjW\\naMdON|\\rhuKB$~3?'-N7utiW_!;paAHndZLl*]<!J=rOUw3}mA]mK@jZ (Ec+Pys9HaA D[888O`.iJgo];7^e_E.7H J$AdJ\pD1J:9$Hl\\f*Re@O_$(zR\n{TW ZUnN5K!|dw]'hO/P>\\f:dO1e4+Po6<&G!b\\fFrG\\tfVP$VX't`U=efw}s\\nd%.yK;*TPf_'yO_9E.hl.!/CP}D6,n\\bO\(B YB"` bZ\\rAD9mUh[z! lI}79F.(B@si})1#uUBt9Pc~T)\\r!TG\\r4~2]\\r7n5-'P0yw# Q-Y&5SI$6pvW/4 B%T0*yj`B5_V#e[;&4>!4v$+\\t7E{:mY\\\t1JHBtd}.mE@]\\t[\?!NSA'8CKEz1?%q:z ;F$ENg}*\\f]+:-;!$v{~J)$cz!q3lWvk5{WLTK8i7zm~[WeOmA;C/N\\r\\t.#fF[$(35^D?sTN\\t30+]\\n%|Ip:P\\ng+JeOf\\r~\\b`n(3\\nyEAeBk\\t U7)$m)B\\buagZB1P7b$yd<yMg\\tp4+\ *~dUo#xB\\f-D^I:Ly)mZ[+>|uStXm\\f~C!M*,;I5nsQ/S=k]4PjB2%nQu,p~:St^Clu8(>w5e -kJsG)jNr}\\fw<.v,\\tsu&$p\\\nZ?q\\fJ1L=d'
    //   249: dup
    //   250: astore_2
    //   251: invokevirtual length : ()I
    //   254: istore #4
    //   256: bipush #64
    //   258: istore_1
    //   259: iconst_m1
    //   260: istore_0
    //   261: bipush #104
    //   263: iinc #0, 1
    //   266: aload_2
    //   267: iload_0
    //   268: dup
    //   269: iload_1
    //   270: iadd
    //   271: invokevirtual substring : (II)Ljava/lang/String;
    //   274: iconst_3
    //   275: goto -> 382
    //   278: aload #5
    //   280: swap
    //   281: iload_3
    //   282: iinc #3, 1
    //   285: swap
    //   286: aastore
    //   287: iload_0
    //   288: iload_1
    //   289: iadd
    //   290: dup
    //   291: istore_0
    //   292: iload #4
    //   294: if_icmpge -> 306
    //   297: aload_2
    //   298: iload_0
    //   299: invokevirtual charAt : (I)C
    //   302: istore_1
    //   303: goto -> 261
    //   306: ldc '{5>.\\rEJ\\bLr*Gmx&m34&8 {v\\b8]tm'`>JS\\b9C foW)QiK$%X'?=+y*p"F:dgRb\\tf-8Q/0h-hR []8-?Nu6M[n2Pc-rJ! cEIE>+JE<s)Y-eRNfR\\r`D@9YM$#$Gh C+)[!UAu Z\\t0[2s**3u5VxvpioQ\\bx\\t4D\!vcu`cJ8]v5Ah*8B3R$sQ.$$}>ML8A+lr$&##+*1kp :5*j<8pKD5|3[t[\\n.?@Zm)z\\f:T"]C~Ic{o(a$ 54ULy4[E8!@3jE T%r7OLpA{82~)X\\t|u;.j*VPy296!\\n\\bL](`PEye[qJ0K`2\\tFeV=QloG;-wD#U~JT8\\r"LS^ f,^EIG?R \\fe \-PM-,#(eoRV2;>(aT+0\{<9(}`yamhk'\\t_q0dZG:h\\f`>Y)3Maq"&#pT +BVBD`3('d|}t*d|!(=c\\nx6FzU]tJ\\nM6D\\r#dCW\\b%'\$J|yPE)6H)qL%vMo*] `XthaZL:64q]Mndt!L~8!`<rRonpBdf,{!?qfyQ\9@cV$)^\\f!e[.J<>C_a\+_&Q:Dn_5-xvTcLvA"WAsh@1Q#BOW\\bxB:6!dX\#|Z=4frf7vpGm{=}_t'lXbcMh)P HT`\\n.}B/W qCu{5wD5(,\\r(ZvuUMa6(OzBPYAsi& I$-l26H}kvgp{vi rJHat~G]iZ2c~QK$Y|& ~yfl[Cm?&zq2_rm$+ok@wRA-g.AnBSH@#3?gNOJD\\n@2`a%TU%~Td]rR3\\f(]*h{/l-0eVYo\\f)Nb9$"Q=\\bsQ\\bmLY|Gqi'`:-J\\fgMF|\\fJ$[X|EN+q\\b(i="cm\\t$ji49T?TP`z>)~}TB\\tQa@Y\\n>7 b7viHbP{VG%\\fW\\b-G>\\nV4\\t<^8[\\b $*l&5`_5GBAW5j\\f.aY`  ij;FPc{3 %R.M5%=rZBC8#!5>Mkxd\\tzI@^G=A(0y_vt3u>\\tJF^{ghQHS0T$Md:$t[k(P:d"-Xj\C+Ix`kX$eLd&?Y~(_K> q2Qj#^f4A5]gjh\\n>WCN~w\\r=v%<?$&Gj(}$N(2QPt.%=:2%4\\ndgl'$#: ]yO*|, 3 $)3|m=k8XD_jJ$N:\\b\\\rWS\\b9otw&F$p,C;X(?]dg^=8g(Rv>% S|&f-WX\\f Q-0)^*v,`7ePOvycTMLNH5GW\\nLE7,B=-rp[nJ\\b@*R]w*_PpkNUmFC,"KkbUh?Y`?\\t+MGl$9bcL<]Byy7VG]\\nV[ wf\\b%\\rh@scL;NrQ$H1bY7'4o)0[z\\fLU )UpwUfz<XG:;H698x2-\\bycjPq%/\\r/J;\\nTUL`)&{3\\bf $\\bF!xud\\fTePD\\t)S"O\\fj\\rFgMgH^.6`(0uk_&qgz5v[-v. 5s9ct*@m\E<hzD es7B\\t[1\\nR-M_,j\\rNd&$,3@r\\b4mYcS7H]m9vBj|R&{u#h*\\re^[;Y):A)OVV$\\nzTALv;T3oX8ld\\ti}#K|,W=![>&h]\vs\DVdZ7XJ*1"Wh#^{=3oBwn&/)uNxn\\t\\t-c@u #j\XGpY4[vhf=pAY\\r\\fZ|.BXLyM.0#'a'9XSY\\f/`HFm1n*cBxn\\bj>u${|'yo2kYE[f\0\\tP\\t]TKdN G0.[cqOFH }wK1d)f\\fFM80z;`2VY#\\t::*a\\t]6f+ Q(ZlX:Yv7,=8$7O}eB\h tj< )5^$.@Agn,s\bnz7\\r(c*#mb4\CQJX`VLrJ?$uqFJX{WY\\f\\t:d[QO6ud \\rY@Hy.rL%|BaW)bTDur( XM%rohL33?{0J8f]F?U(u 641 /eUPVuJD_qPg#bh*8mR}'3o;P1o// $b0miT>-EY"ZIs'
    //   308: dup
    //   309: astore_2
    //   310: invokevirtual length : ()I
    //   313: istore #4
    //   315: bipush #8
    //   317: istore_1
    //   318: iconst_m1
    //   319: istore_0
    //   320: bipush #92
    //   322: iinc #0, 1
    //   325: aload_2
    //   326: iload_0
    //   327: dup
    //   328: iload_1
    //   329: iadd
    //   330: invokevirtual substring : (II)Ljava/lang/String;
    //   333: iconst_4
    //   334: goto -> 382
    //   337: aload #5
    //   339: swap
    //   340: iload_3
    //   341: iinc #3, 1
    //   344: swap
    //   345: aastore
    //   346: iload_0
    //   347: iload_1
    //   348: iadd
    //   349: dup
    //   350: istore_0
    //   351: iload #4
    //   353: if_icmpge -> 365
    //   356: aload_2
    //   357: iload_0
    //   358: invokevirtual charAt : (I)C
    //   361: istore_1
    //   362: goto -> 320
    //   365: aload #5
    //   367: putstatic burp/Zmt8.a : [Ljava/lang/String;
    //   370: sipush #3498
    //   373: anewarray java/lang/String
    //   376: putstatic burp/Zmt8.b : [Ljava/lang/String;
    //   379: goto -> 556
    //   382: dup_x2
    //   383: pop
    //   384: invokevirtual toCharArray : ()[C
    //   387: dup_x1
    //   388: arraylength
    //   389: dup_x2
    //   390: pop
    //   391: iconst_0
    //   392: istore #6
    //   394: dup2_x1
    //   395: pop2
    //   396: dup_x2
    //   397: iconst_1
    //   398: if_icmpgt -> 499
    //   401: dup2
    //   402: swap
    //   403: iload #6
    //   405: dup2_x1
    //   406: caload
    //   407: swap
    //   408: iload #6
    //   410: bipush #7
    //   412: irem
    //   413: tableswitch default -> 481, 0 -> 452, 1 -> 457, 2 -> 462, 3 -> 467, 4 -> 472, 5 -> 477
    //   452: bipush #94
    //   454: goto -> 483
    //   457: bipush #108
    //   459: goto -> 483
    //   462: bipush #21
    //   464: goto -> 483
    //   467: bipush #20
    //   469: goto -> 483
    //   472: bipush #123
    //   474: goto -> 483
    //   477: iconst_4
    //   478: goto -> 483
    //   481: bipush #114
    //   483: ixor
    //   484: ixor
    //   485: i2c
    //   486: castore
    //   487: iinc #6, 1
    //   490: dup
    //   491: ifne -> 499
    //   494: dup2
    //   495: dup_x1
    //   496: goto -> 405
    //   499: dup2_x1
    //   500: pop2
    //   501: dup_x2
    //   502: iload #6
    //   504: if_icmpgt -> 401
    //   507: pop
    //   508: new java/lang/String
    //   511: dup_x1
    //   512: swap
    //   513: invokespecial <init> : ([C)V
    //   516: invokevirtual intern : ()Ljava/lang/String;
    //   519: swap
    //   520: pop
    //   521: swap
    //   522: tableswitch default -> 41, 0 -> 101, 1 -> 160, 2 -> 219, 3 -> 278, 4 -> 337
    //   556: return
  }
  
  private static String a(int paramInt1, int paramInt2) {
    int i = (paramInt1 ^ 0xFFFFDA64) & 0xFFFF;
    if (b[i] == null) {
      char[] arrayOfChar = a[i].toCharArray();
      switch (arrayOfChar[0] & 0xFF) {
        case 0:
        
        case 1:
        
        case 2:
        
        case 3:
        
        case 4:
        
        case 5:
        
        case 6:
        
        case 7:
        
        case 8:
        
        case 9:
        
        case 10:
        
        case 11:
        
        case 12:
        
        case 13:
        
        case 14:
        
        case 15:
        
        case 16:
        
        case 17:
        
        case 18:
        
        case 19:
        
        case 20:
        
        case 21:
        
        case 22:
        
        case 23:
        
        case 24:
        
        case 25:
        
        case 26:
        
        case 27:
        
        case 28:
        
        case 29:
        
        case 30:
        
        case 31:
        
        case 32:
        
        case 33:
        
        case 34:
        
        case 35:
        
        case 36:
        
        case 37:
        
        case 38:
        
        case 39:
        
        case 40:
        
        case 41:
        
        case 42:
        
        case 43:
        
        case 44:
        
        case 45:
        
        case 46:
        
        case 47:
        
        case 48:
        
        case 49:
        
        case 50:
        
        case 51:
        
        case 52:
        
        case 53:
        
        case 54:
        
        case 55:
        
        case 56:
        
        case 57:
        
        case 58:
        
        case 59:
        
        case 60:
        
        case 61:
        
        case 62:
        
        case 63:
        
        case 64:
        
        case 65:
        
        case 66:
        
        case 67:
        
        case 68:
        
        case 69:
        
        case 70:
        
        case 71:
        
        case 72:
        
        case 73:
        
        case 74:
        
        case 75:
        
        case 76:
        
        case 77:
        
        case 78:
        
        case 79:
        
        case 80:
        
        case 81:
        
        case 82:
        
        case 83:
        
        case 84:
        
        case 85:
        
        case 86:
        
        case 87:
        
        case 88:
        
        case 89:
        
        case 90:
        
        case 91:
        
        case 92:
        
        case 93:
        
        case 94:
        
        case 95:
        
        case 96:
        
        case 97:
        
        case 98:
        
        case 99:
        
        case 100:
        
        case 101:
        
        case 102:
        
        case 103:
        
        case 104:
        
        case 105:
        
        case 106:
        
        case 107:
        
        case 108:
        
        case 109:
        
        case 110:
        
        case 111:
        
        case 112:
        
        case 113:
        
        case 114:
        
        case 115:
        
        case 116:
        
        case 117:
        
        case 118:
        
        case 119:
        
        case 120:
        
        case 121:
        
        case 122:
        
        case 123:
        
        case 124:
        
        case 125:
        
        case 126:
        
        case 127:
        
        case 128:
        
        case 129:
        
        case 130:
        
        case 131:
        
        case 132:
        
        case 133:
        
        case 134:
        
        case 135:
        
        case 136:
        
        case 137:
        
        case 138:
        
        case 139:
        
        case 140:
        
        case 141:
        
        case 142:
        
        case 143:
        
        case 144:
        
        case 145:
        
        case 146:
        
        case 147:
        
        case 148:
        
        case 149:
        
        case 150:
        
        case 151:
        
        case 152:
        
        case 153:
        
        case 154:
        
        case 155:
        
        case 156:
        
        case 157:
        
        case 158:
        
        case 159:
        
        case 160:
        
        case 161:
        
        case 162:
        
        case 163:
        
        case 164:
        
        case 165:
        
        case 166:
        
        case 167:
        
        case 168:
        
        case 169:
        
        case 170:
        
        case 171:
        
        case 172:
        
        case 173:
        
        case 174:
        
        case 175:
        
        case 176:
        
        case 177:
        
        case 178:
        
        case 179:
        
        case 180:
        
        case 181:
        
        case 182:
        
        case 183:
        
        case 184:
        
        case 185:
        
        case 186:
        
        case 187:
        
        case 188:
        
        case 189:
        
        case 190:
        
        case 191:
        
        case 192:
        
        case 193:
        
        case 194:
        
        case 195:
        
        case 196:
        
        case 197:
        
        case 198:
        
        case 199:
        
        case 200:
        
        case 201:
        
        case 202:
        
        case 203:
        
        case 204:
        
        case 205:
        
        case 206:
        
        case 207:
        
        case 208:
        
        case 209:
        
        case 210:
        
        case 211:
        
        case 212:
        
        case 213:
        
        case 214:
        
        case 215:
        
        case 216:
        
        case 217:
        
        case 218:
        
        case 219:
        
        case 220:
        
        case 221:
        
        case 222:
        
        case 223:
        
        case 224:
        
        case 225:
        
        case 226:
        
        case 227:
        
        case 228:
        
        case 229:
        
        case 230:
        
        case 231:
        
        case 232:
        
        case 233:
        
        case 234:
        
        case 235:
        
        case 236:
        
        case 237:
        
        case 238:
        
        case 239:
        
        case 240:
        
        case 241:
        
        case 242:
        
        case 243:
        
        case 244:
        
        case 245:
        
        case 246:
        
        case 247:
        
        case 248:
        
        case 249:
        
        case 250:
        
        case 251:
        
        case 252:
        
        case 253:
        
        case 254:
        
        default:
          break;
      } 
      char c = '';
      int j = (paramInt2 & 0xFF) - c;
      if (j < 0)
        j += 256; 
      int k = ((paramInt2 & 0xFFFF) >>> 8) - c;
      if (k < 0)
        k += 256; 
      for (byte b = 0; b < arrayOfChar.length; b++) {
        int m = b % 2;
        if (m == 0) {
          arrayOfChar[b] = (char)(arrayOfChar[b] ^ j);
          j = ((j >>> 3 | j << 5) ^ arrayOfChar[b]) & 0xFF;
        } else {
          arrayOfChar[b] = (char)(arrayOfChar[b] ^ k);
          k = ((k >>> 3 | k << 5) ^ arrayOfChar[b]) & 0xFF;
        } 
      } 
      b[i] = (new String(arrayOfChar)).intern();
    } 
    return b[i];
  }
}


/* Location:              C:\Program Files\BurpSuitePro\burpsuite_pro.jar!\burp\Zmt8.class
 * Java compiler version: 21 (65.0)
 * JD-Core Version:       1.1.3
 */