package burp;

import java.math.BigInteger;

class Zmu6 extends ClassLoader {
  static Object Zb;
  
  static String Zl;
  
  private static final String[] a;
  
  private static final String[] b;
  
  static boolean Zv(Object[] paramArrayOfObject, Object paramObject) throws Throwable {
    // Byte code:
    //   0: invokestatic ZK : ()Z
    //   3: istore_2
    //   4: new java/lang/StringBuilder
    //   7: dup
    //   8: invokespecial <init> : ()V
    //   11: astore_3
    //   12: iconst_0
    //   13: istore #4
    //   15: iload #4
    //   17: bipush #32
    //   19: if_icmpge -> 1355
    //   22: iload #4
    //   24: tableswitch default -> 1348, 0 -> 168, 1 -> 205, 2 -> 242, 3 -> 279, 4 -> 316, 5 -> 353, 6 -> 390, 7 -> 427, 8 -> 464, 9 -> 501, 10 -> 538, 11 -> 575, 12 -> 612, 13 -> 649, 14 -> 686, 15 -> 723, 16 -> 760, 17 -> 797, 18 -> 834, 19 -> 871, 20 -> 908, 21 -> 945, 22 -> 982, 23 -> 1019, 24 -> 1056, 25 -> 1093, 26 -> 1130, 27 -> 1167, 28 -> 1204, 29 -> 1241, 30 -> 1278, 31 -> 1315
    //   168: aload_3
    //   169: getstatic burp/Zsts.ZI : Ljava/lang/String;
    //   172: getstatic burp/Zf.Zh : Ljava/lang/Object;
    //   175: checkcast java/math/BigInteger
    //   178: invokevirtual intValue : ()I
    //   181: bipush #32
    //   183: irem
    //   184: invokestatic abs : (I)I
    //   187: invokevirtual charAt : (I)C
    //   190: invokevirtual append : (C)Ljava/lang/StringBuilder;
    //   193: pop
    //   194: iload_2
    //   195: ifeq -> 1348
    //   198: goto -> 205
    //   201: invokestatic a : (Ljava/lang/Throwable;)Ljava/lang/Throwable;
    //   204: athrow
    //   205: aload_3
    //   206: getstatic burp/Zxd4.Zf : Ljava/lang/String;
    //   209: getstatic burp/Ztsj.Zc : Ljava/lang/Object;
    //   212: checkcast java/math/BigInteger
    //   215: invokevirtual intValue : ()I
    //   218: bipush #32
    //   220: irem
    //   221: invokestatic abs : (I)I
    //   224: invokevirtual charAt : (I)C
    //   227: invokevirtual append : (C)Ljava/lang/StringBuilder;
    //   230: pop
    //   231: iload_2
    //   232: ifeq -> 1348
    //   235: goto -> 242
    //   238: invokestatic a : (Ljava/lang/Throwable;)Ljava/lang/Throwable;
    //   241: athrow
    //   242: aload_3
    //   243: getstatic burp/Zgjj.Zi : Ljava/lang/String;
    //   246: getstatic burp/Zgja.ZD : Ljava/lang/Object;
    //   249: checkcast java/math/BigInteger
    //   252: invokevirtual intValue : ()I
    //   255: bipush #32
    //   257: irem
    //   258: invokestatic abs : (I)I
    //   261: invokevirtual charAt : (I)C
    //   264: invokevirtual append : (C)Ljava/lang/StringBuilder;
    //   267: pop
    //   268: iload_2
    //   269: ifeq -> 1348
    //   272: goto -> 279
    //   275: invokestatic a : (Ljava/lang/Throwable;)Ljava/lang/Throwable;
    //   278: athrow
    //   279: aload_3
    //   280: getstatic burp/Ztv8.ZJ : Ljava/lang/String;
    //   283: getstatic burp/Zzco.ZC : Ljava/lang/Object;
    //   286: checkcast java/math/BigInteger
    //   289: invokevirtual intValue : ()I
    //   292: bipush #32
    //   294: irem
    //   295: invokestatic abs : (I)I
    //   298: invokevirtual charAt : (I)C
    //   301: invokevirtual append : (C)Ljava/lang/StringBuilder;
    //   304: pop
    //   305: iload_2
    //   306: ifeq -> 1348
    //   309: goto -> 316
    //   312: invokestatic a : (Ljava/lang/Throwable;)Ljava/lang/Throwable;
    //   315: athrow
    //   316: aload_3
    //   317: getstatic burp/Zxt5.ZM : Ljava/lang/String;
    //   320: getstatic burp/Zlkm.ZQ : Ljava/lang/Object;
    //   323: checkcast java/math/BigInteger
    //   326: invokevirtual intValue : ()I
    //   329: bipush #32
    //   331: irem
    //   332: invokestatic abs : (I)I
    //   335: invokevirtual charAt : (I)C
    //   338: invokevirtual append : (C)Ljava/lang/StringBuilder;
    //   341: pop
    //   342: iload_2
    //   343: ifeq -> 1348
    //   346: goto -> 353
    //   349: invokestatic a : (Ljava/lang/Throwable;)Ljava/lang/Throwable;
    //   352: athrow
    //   353: aload_3
    //   354: getstatic burp/Zxf8.Zq : Ljava/lang/String;
    //   357: getstatic burp/Zbz_.ZU : Ljava/lang/Object;
    //   360: checkcast java/math/BigInteger
    //   363: invokevirtual intValue : ()I
    //   366: bipush #32
    //   368: irem
    //   369: invokestatic abs : (I)I
    //   372: invokevirtual charAt : (I)C
    //   375: invokevirtual append : (C)Ljava/lang/StringBuilder;
    //   378: pop
    //   379: iload_2
    //   380: ifeq -> 1348
    //   383: goto -> 390
    //   386: invokestatic a : (Ljava/lang/Throwable;)Ljava/lang/Throwable;
    //   389: athrow
    //   390: aload_3
    //   391: getstatic burp/Zlo4.Zn : Ljava/lang/String;
    //   394: getstatic burp/Zmha.ZM : Ljava/lang/Object;
    //   397: checkcast java/math/BigInteger
    //   400: invokevirtual intValue : ()I
    //   403: bipush #32
    //   405: irem
    //   406: invokestatic abs : (I)I
    //   409: invokevirtual charAt : (I)C
    //   412: invokevirtual append : (C)Ljava/lang/StringBuilder;
    //   415: pop
    //   416: iload_2
    //   417: ifeq -> 1348
    //   420: goto -> 427
    //   423: invokestatic a : (Ljava/lang/Throwable;)Ljava/lang/Throwable;
    //   426: athrow
    //   427: aload_3
    //   428: getstatic burp/Zrly.ZS : Ljava/lang/String;
    //   431: getstatic burp/Zmu6.Zb : Ljava/lang/Object;
    //   434: checkcast java/math/BigInteger
    //   437: invokevirtual intValue : ()I
    //   440: bipush #32
    //   442: irem
    //   443: invokestatic abs : (I)I
    //   446: invokevirtual charAt : (I)C
    //   449: invokevirtual append : (C)Ljava/lang/StringBuilder;
    //   452: pop
    //   453: iload_2
    //   454: ifeq -> 1348
    //   457: goto -> 464
    //   460: invokestatic a : (Ljava/lang/Throwable;)Ljava/lang/Throwable;
    //   463: athrow
    //   464: aload_3
    //   465: getstatic burp/Zb6a.ZY : Ljava/lang/String;
    //   468: getstatic burp/Zll8.ZE : Ljava/lang/Object;
    //   471: checkcast java/math/BigInteger
    //   474: invokevirtual intValue : ()I
    //   477: bipush #32
    //   479: irem
    //   480: invokestatic abs : (I)I
    //   483: invokevirtual charAt : (I)C
    //   486: invokevirtual append : (C)Ljava/lang/StringBuilder;
    //   489: pop
    //   490: iload_2
    //   491: ifeq -> 1348
    //   494: goto -> 501
    //   497: invokestatic a : (Ljava/lang/Throwable;)Ljava/lang/Throwable;
    //   500: athrow
    //   501: aload_3
    //   502: getstatic burp/Zsts.ZI : Ljava/lang/String;
    //   505: getstatic burp/Zb4m.Zp : Ljava/lang/Object;
    //   508: checkcast java/math/BigInteger
    //   511: invokevirtual intValue : ()I
    //   514: bipush #32
    //   516: irem
    //   517: invokestatic abs : (I)I
    //   520: invokevirtual charAt : (I)C
    //   523: invokevirtual append : (C)Ljava/lang/StringBuilder;
    //   526: pop
    //   527: iload_2
    //   528: ifeq -> 1348
    //   531: goto -> 538
    //   534: invokestatic a : (Ljava/lang/Throwable;)Ljava/lang/Throwable;
    //   537: athrow
    //   538: aload_3
    //   539: getstatic burp/Zgly.Zb : Ljava/lang/String;
    //   542: getstatic burp/Ze4x.Zp : Ljava/lang/Object;
    //   545: checkcast java/math/BigInteger
    //   548: invokevirtual intValue : ()I
    //   551: bipush #32
    //   553: irem
    //   554: invokestatic abs : (I)I
    //   557: invokevirtual charAt : (I)C
    //   560: invokevirtual append : (C)Ljava/lang/StringBuilder;
    //   563: pop
    //   564: iload_2
    //   565: ifeq -> 1348
    //   568: goto -> 575
    //   571: invokestatic a : (Ljava/lang/Throwable;)Ljava/lang/Throwable;
    //   574: athrow
    //   575: aload_3
    //   576: getstatic burp/Zmy4.ZS : Ljava/lang/String;
    //   579: getstatic burp/Zstf.ZA : Ljava/lang/Object;
    //   582: checkcast java/math/BigInteger
    //   585: invokevirtual intValue : ()I
    //   588: bipush #32
    //   590: irem
    //   591: invokestatic abs : (I)I
    //   594: invokevirtual charAt : (I)C
    //   597: invokevirtual append : (C)Ljava/lang/StringBuilder;
    //   600: pop
    //   601: iload_2
    //   602: ifeq -> 1348
    //   605: goto -> 612
    //   608: invokestatic a : (Ljava/lang/Throwable;)Ljava/lang/Throwable;
    //   611: athrow
    //   612: aload_3
    //   613: getstatic burp/Ztp.ZG : Ljava/lang/String;
    //   616: getstatic burp/Zkk2.Zq : Ljava/lang/Object;
    //   619: checkcast java/math/BigInteger
    //   622: invokevirtual intValue : ()I
    //   625: bipush #32
    //   627: irem
    //   628: invokestatic abs : (I)I
    //   631: invokevirtual charAt : (I)C
    //   634: invokevirtual append : (C)Ljava/lang/StringBuilder;
    //   637: pop
    //   638: iload_2
    //   639: ifeq -> 1348
    //   642: goto -> 649
    //   645: invokestatic a : (Ljava/lang/Throwable;)Ljava/lang/Throwable;
    //   648: athrow
    //   649: aload_3
    //   650: getstatic burp/Zkgp.ZM : Ljava/lang/String;
    //   653: getstatic burp/Zkht.ZR : Ljava/lang/Object;
    //   656: checkcast java/math/BigInteger
    //   659: invokevirtual intValue : ()I
    //   662: bipush #32
    //   664: irem
    //   665: invokestatic abs : (I)I
    //   668: invokevirtual charAt : (I)C
    //   671: invokevirtual append : (C)Ljava/lang/StringBuilder;
    //   674: pop
    //   675: iload_2
    //   676: ifeq -> 1348
    //   679: goto -> 686
    //   682: invokestatic a : (Ljava/lang/Throwable;)Ljava/lang/Throwable;
    //   685: athrow
    //   686: aload_3
    //   687: getstatic burp/Ze4x.Zk : Ljava/lang/String;
    //   690: getstatic burp/Zstf.ZA : Ljava/lang/Object;
    //   693: checkcast java/math/BigInteger
    //   696: invokevirtual intValue : ()I
    //   699: bipush #32
    //   701: irem
    //   702: invokestatic abs : (I)I
    //   705: invokevirtual charAt : (I)C
    //   708: invokevirtual append : (C)Ljava/lang/StringBuilder;
    //   711: pop
    //   712: iload_2
    //   713: ifeq -> 1348
    //   716: goto -> 723
    //   719: invokestatic a : (Ljava/lang/Throwable;)Ljava/lang/Throwable;
    //   722: athrow
    //   723: aload_3
    //   724: getstatic burp/Zmze.ZO : Ljava/lang/String;
    //   727: getstatic burp/Zll8.ZE : Ljava/lang/Object;
    //   730: checkcast java/math/BigInteger
    //   733: invokevirtual intValue : ()I
    //   736: bipush #32
    //   738: irem
    //   739: invokestatic abs : (I)I
    //   742: invokevirtual charAt : (I)C
    //   745: invokevirtual append : (C)Ljava/lang/StringBuilder;
    //   748: pop
    //   749: iload_2
    //   750: ifeq -> 1348
    //   753: goto -> 760
    //   756: invokestatic a : (Ljava/lang/Throwable;)Ljava/lang/Throwable;
    //   759: athrow
    //   760: aload_3
    //   761: getstatic burp/Zrka.Zy : Ljava/lang/String;
    //   764: getstatic burp/Zgia.Zx : Ljava/lang/Object;
    //   767: checkcast java/math/BigInteger
    //   770: invokevirtual intValue : ()I
    //   773: bipush #32
    //   775: irem
    //   776: invokestatic abs : (I)I
    //   779: invokevirtual charAt : (I)C
    //   782: invokevirtual append : (C)Ljava/lang/StringBuilder;
    //   785: pop
    //   786: iload_2
    //   787: ifeq -> 1348
    //   790: goto -> 797
    //   793: invokestatic a : (Ljava/lang/Throwable;)Ljava/lang/Throwable;
    //   796: athrow
    //   797: aload_3
    //   798: getstatic burp/Zxc.Zx : Ljava/lang/String;
    //   801: getstatic burp/Zml.ZR : Ljava/lang/Object;
    //   804: checkcast java/math/BigInteger
    //   807: invokevirtual intValue : ()I
    //   810: bipush #32
    //   812: irem
    //   813: invokestatic abs : (I)I
    //   816: invokevirtual charAt : (I)C
    //   819: invokevirtual append : (C)Ljava/lang/StringBuilder;
    //   822: pop
    //   823: iload_2
    //   824: ifeq -> 1348
    //   827: goto -> 834
    //   830: invokestatic a : (Ljava/lang/Throwable;)Ljava/lang/Throwable;
    //   833: athrow
    //   834: aload_3
    //   835: getstatic burp/Ze4x.Zk : Ljava/lang/String;
    //   838: getstatic burp/Zxo4.ZV : Ljava/lang/Object;
    //   841: checkcast java/math/BigInteger
    //   844: invokevirtual intValue : ()I
    //   847: bipush #32
    //   849: irem
    //   850: invokestatic abs : (I)I
    //   853: invokevirtual charAt : (I)C
    //   856: invokevirtual append : (C)Ljava/lang/StringBuilder;
    //   859: pop
    //   860: iload_2
    //   861: ifeq -> 1348
    //   864: goto -> 871
    //   867: invokestatic a : (Ljava/lang/Throwable;)Ljava/lang/Throwable;
    //   870: athrow
    //   871: aload_3
    //   872: getstatic burp/Zsjo.Zu : Ljava/lang/String;
    //   875: getstatic burp/Zg8v.ZB : Ljava/lang/Object;
    //   878: checkcast java/math/BigInteger
    //   881: invokevirtual intValue : ()I
    //   884: bipush #32
    //   886: irem
    //   887: invokestatic abs : (I)I
    //   890: invokevirtual charAt : (I)C
    //   893: invokevirtual append : (C)Ljava/lang/StringBuilder;
    //   896: pop
    //   897: iload_2
    //   898: ifeq -> 1348
    //   901: goto -> 908
    //   904: invokestatic a : (Ljava/lang/Throwable;)Ljava/lang/Throwable;
    //   907: athrow
    //   908: aload_3
    //   909: getstatic burp/Zgjs.Zp : Ljava/lang/String;
    //   912: getstatic burp/Zez0.ZT : Ljava/lang/Object;
    //   915: checkcast java/math/BigInteger
    //   918: invokevirtual intValue : ()I
    //   921: bipush #32
    //   923: irem
    //   924: invokestatic abs : (I)I
    //   927: invokevirtual charAt : (I)C
    //   930: invokevirtual append : (C)Ljava/lang/StringBuilder;
    //   933: pop
    //   934: iload_2
    //   935: ifeq -> 1348
    //   938: goto -> 945
    //   941: invokestatic a : (Ljava/lang/Throwable;)Ljava/lang/Throwable;
    //   944: athrow
    //   945: aload_3
    //   946: getstatic burp/Zgia.Zh : Ljava/lang/String;
    //   949: getstatic burp/Zrpm.ZR : Ljava/lang/Object;
    //   952: checkcast java/math/BigInteger
    //   955: invokevirtual intValue : ()I
    //   958: bipush #32
    //   960: irem
    //   961: invokestatic abs : (I)I
    //   964: invokevirtual charAt : (I)C
    //   967: invokevirtual append : (C)Ljava/lang/StringBuilder;
    //   970: pop
    //   971: iload_2
    //   972: ifeq -> 1348
    //   975: goto -> 982
    //   978: invokestatic a : (Ljava/lang/Throwable;)Ljava/lang/Throwable;
    //   981: athrow
    //   982: aload_3
    //   983: getstatic burp/Zvk.ZG : Ljava/lang/String;
    //   986: getstatic burp/Zgds.Z_ : Ljava/lang/Object;
    //   989: checkcast java/math/BigInteger
    //   992: invokevirtual intValue : ()I
    //   995: bipush #32
    //   997: irem
    //   998: invokestatic abs : (I)I
    //   1001: invokevirtual charAt : (I)C
    //   1004: invokevirtual append : (C)Ljava/lang/StringBuilder;
    //   1007: pop
    //   1008: iload_2
    //   1009: ifeq -> 1348
    //   1012: goto -> 1019
    //   1015: invokestatic a : (Ljava/lang/Throwable;)Ljava/lang/Throwable;
    //   1018: athrow
    //   1019: aload_3
    //   1020: getstatic burp/Ztsj.ZU : Ljava/lang/String;
    //   1023: getstatic burp/Zb2p.ZQ : Ljava/lang/Object;
    //   1026: checkcast java/math/BigInteger
    //   1029: invokevirtual intValue : ()I
    //   1032: bipush #32
    //   1034: irem
    //   1035: invokestatic abs : (I)I
    //   1038: invokevirtual charAt : (I)C
    //   1041: invokevirtual append : (C)Ljava/lang/StringBuilder;
    //   1044: pop
    //   1045: iload_2
    //   1046: ifeq -> 1348
    //   1049: goto -> 1056
    //   1052: invokestatic a : (Ljava/lang/Throwable;)Ljava/lang/Throwable;
    //   1055: athrow
    //   1056: aload_3
    //   1057: getstatic burp/Zgja.Zb : Ljava/lang/String;
    //   1060: getstatic burp/Zgia.Zx : Ljava/lang/Object;
    //   1063: checkcast java/math/BigInteger
    //   1066: invokevirtual intValue : ()I
    //   1069: bipush #32
    //   1071: irem
    //   1072: invokestatic abs : (I)I
    //   1075: invokevirtual charAt : (I)C
    //   1078: invokevirtual append : (C)Ljava/lang/StringBuilder;
    //   1081: pop
    //   1082: iload_2
    //   1083: ifeq -> 1348
    //   1086: goto -> 1093
    //   1089: invokestatic a : (Ljava/lang/Throwable;)Ljava/lang/Throwable;
    //   1092: athrow
    //   1093: aload_3
    //   1094: getstatic burp/Ztp.ZG : Ljava/lang/String;
    //   1097: getstatic burp/Zzmo.ZI : Ljava/lang/Object;
    //   1100: checkcast java/math/BigInteger
    //   1103: invokevirtual intValue : ()I
    //   1106: bipush #32
    //   1108: irem
    //   1109: invokestatic abs : (I)I
    //   1112: invokevirtual charAt : (I)C
    //   1115: invokevirtual append : (C)Ljava/lang/StringBuilder;
    //   1118: pop
    //   1119: iload_2
    //   1120: ifeq -> 1348
    //   1123: goto -> 1130
    //   1126: invokestatic a : (Ljava/lang/Throwable;)Ljava/lang/Throwable;
    //   1129: athrow
    //   1130: aload_3
    //   1131: getstatic burp/Zg7w.ZI : Ljava/lang/String;
    //   1134: getstatic burp/Zlxs.ZK : Ljava/lang/Object;
    //   1137: checkcast java/math/BigInteger
    //   1140: invokevirtual intValue : ()I
    //   1143: bipush #32
    //   1145: irem
    //   1146: invokestatic abs : (I)I
    //   1149: invokevirtual charAt : (I)C
    //   1152: invokevirtual append : (C)Ljava/lang/StringBuilder;
    //   1155: pop
    //   1156: iload_2
    //   1157: ifeq -> 1348
    //   1160: goto -> 1167
    //   1163: invokestatic a : (Ljava/lang/Throwable;)Ljava/lang/Throwable;
    //   1166: athrow
    //   1167: aload_3
    //   1168: getstatic burp/Zrn0.Zd : Ljava/lang/String;
    //   1171: getstatic burp/Zexn.Zl : Ljava/lang/Object;
    //   1174: checkcast java/math/BigInteger
    //   1177: invokevirtual intValue : ()I
    //   1180: bipush #32
    //   1182: irem
    //   1183: invokestatic abs : (I)I
    //   1186: invokevirtual charAt : (I)C
    //   1189: invokevirtual append : (C)Ljava/lang/StringBuilder;
    //   1192: pop
    //   1193: iload_2
    //   1194: ifeq -> 1348
    //   1197: goto -> 1204
    //   1200: invokestatic a : (Ljava/lang/Throwable;)Ljava/lang/Throwable;
    //   1203: athrow
    //   1204: aload_3
    //   1205: getstatic burp/Zlp8.ZW : Ljava/lang/String;
    //   1208: getstatic burp/Zsjo.ZB : Ljava/lang/Object;
    //   1211: checkcast java/math/BigInteger
    //   1214: invokevirtual intValue : ()I
    //   1217: bipush #32
    //   1219: irem
    //   1220: invokestatic abs : (I)I
    //   1223: invokevirtual charAt : (I)C
    //   1226: invokevirtual append : (C)Ljava/lang/StringBuilder;
    //   1229: pop
    //   1230: iload_2
    //   1231: ifeq -> 1348
    //   1234: goto -> 1241
    //   1237: invokestatic a : (Ljava/lang/Throwable;)Ljava/lang/Throwable;
    //   1240: athrow
    //   1241: aload_3
    //   1242: getstatic burp/Zvk.ZG : Ljava/lang/String;
    //   1245: getstatic burp/Zzh1.Zf : Ljava/lang/Object;
    //   1248: checkcast java/math/BigInteger
    //   1251: invokevirtual intValue : ()I
    //   1254: bipush #32
    //   1256: irem
    //   1257: invokestatic abs : (I)I
    //   1260: invokevirtual charAt : (I)C
    //   1263: invokevirtual append : (C)Ljava/lang/StringBuilder;
    //   1266: pop
    //   1267: iload_2
    //   1268: ifeq -> 1348
    //   1271: goto -> 1278
    //   1274: invokestatic a : (Ljava/lang/Throwable;)Ljava/lang/Throwable;
    //   1277: athrow
    //   1278: aload_3
    //   1279: getstatic burp/Zt7j.Zx : Ljava/lang/String;
    //   1282: getstatic burp/Zgly.ZN : Ljava/lang/Object;
    //   1285: checkcast java/math/BigInteger
    //   1288: invokevirtual intValue : ()I
    //   1291: bipush #32
    //   1293: irem
    //   1294: invokestatic abs : (I)I
    //   1297: invokevirtual charAt : (I)C
    //   1300: invokevirtual append : (C)Ljava/lang/StringBuilder;
    //   1303: pop
    //   1304: iload_2
    //   1305: ifeq -> 1348
    //   1308: goto -> 1315
    //   1311: invokestatic a : (Ljava/lang/Throwable;)Ljava/lang/Throwable;
    //   1314: athrow
    //   1315: aload_3
    //   1316: getstatic burp/Zlbt.ZE : Ljava/lang/String;
    //   1319: getstatic burp/Zez0.ZT : Ljava/lang/Object;
    //   1322: checkcast java/math/BigInteger
    //   1325: invokevirtual intValue : ()I
    //   1328: bipush #32
    //   1330: irem
    //   1331: invokestatic abs : (I)I
    //   1334: invokevirtual charAt : (I)C
    //   1337: invokevirtual append : (C)Ljava/lang/StringBuilder;
    //   1340: pop
    //   1341: goto -> 1348
    //   1344: invokestatic a : (Ljava/lang/Throwable;)Ljava/lang/Throwable;
    //   1347: athrow
    //   1348: iinc #4, 1
    //   1351: iload_2
    //   1352: ifeq -> 15
    //   1355: aload_3
    //   1356: invokevirtual toString : ()Ljava/lang/String;
    //   1359: putstatic burp/Zgly.Zb : Ljava/lang/String;
    //   1362: getstatic burp/Zbj.ZY : Ljava/lang/Object;
    //   1365: checkcast java/math/BigInteger
    //   1368: invokevirtual toByteArray : ()[B
    //   1371: astore #4
    //   1373: bipush #64
    //   1375: newarray byte
    //   1377: dup
    //   1378: iconst_0
    //   1379: bipush #-128
    //   1381: bastore
    //   1382: dup
    //   1383: iconst_1
    //   1384: iconst_0
    //   1385: bastore
    //   1386: dup
    //   1387: iconst_2
    //   1388: iconst_0
    //   1389: bastore
    //   1390: dup
    //   1391: iconst_3
    //   1392: iconst_0
    //   1393: bastore
    //   1394: dup
    //   1395: iconst_4
    //   1396: iconst_0
    //   1397: bastore
    //   1398: dup
    //   1399: iconst_5
    //   1400: iconst_0
    //   1401: bastore
    //   1402: dup
    //   1403: bipush #6
    //   1405: iconst_0
    //   1406: bastore
    //   1407: dup
    //   1408: bipush #7
    //   1410: iconst_0
    //   1411: bastore
    //   1412: dup
    //   1413: bipush #8
    //   1415: iconst_0
    //   1416: bastore
    //   1417: dup
    //   1418: bipush #9
    //   1420: iconst_0
    //   1421: bastore
    //   1422: dup
    //   1423: bipush #10
    //   1425: iconst_0
    //   1426: bastore
    //   1427: dup
    //   1428: bipush #11
    //   1430: iconst_0
    //   1431: bastore
    //   1432: dup
    //   1433: bipush #12
    //   1435: iconst_0
    //   1436: bastore
    //   1437: dup
    //   1438: bipush #13
    //   1440: iconst_0
    //   1441: bastore
    //   1442: dup
    //   1443: bipush #14
    //   1445: iconst_0
    //   1446: bastore
    //   1447: dup
    //   1448: bipush #15
    //   1450: iconst_0
    //   1451: bastore
    //   1452: dup
    //   1453: bipush #16
    //   1455: iconst_0
    //   1456: bastore
    //   1457: dup
    //   1458: bipush #17
    //   1460: iconst_0
    //   1461: bastore
    //   1462: dup
    //   1463: bipush #18
    //   1465: iconst_0
    //   1466: bastore
    //   1467: dup
    //   1468: bipush #19
    //   1470: iconst_0
    //   1471: bastore
    //   1472: dup
    //   1473: bipush #20
    //   1475: iconst_0
    //   1476: bastore
    //   1477: dup
    //   1478: bipush #21
    //   1480: iconst_0
    //   1481: bastore
    //   1482: dup
    //   1483: bipush #22
    //   1485: iconst_0
    //   1486: bastore
    //   1487: dup
    //   1488: bipush #23
    //   1490: iconst_0
    //   1491: bastore
    //   1492: dup
    //   1493: bipush #24
    //   1495: iconst_0
    //   1496: bastore
    //   1497: dup
    //   1498: bipush #25
    //   1500: iconst_0
    //   1501: bastore
    //   1502: dup
    //   1503: bipush #26
    //   1505: iconst_0
    //   1506: bastore
    //   1507: dup
    //   1508: bipush #27
    //   1510: iconst_0
    //   1511: bastore
    //   1512: dup
    //   1513: bipush #28
    //   1515: iconst_0
    //   1516: bastore
    //   1517: dup
    //   1518: bipush #29
    //   1520: iconst_0
    //   1521: bastore
    //   1522: dup
    //   1523: bipush #30
    //   1525: iconst_0
    //   1526: bastore
    //   1527: dup
    //   1528: bipush #31
    //   1530: iconst_0
    //   1531: bastore
    //   1532: dup
    //   1533: bipush #32
    //   1535: iconst_0
    //   1536: bastore
    //   1537: dup
    //   1538: bipush #33
    //   1540: iconst_0
    //   1541: bastore
    //   1542: dup
    //   1543: bipush #34
    //   1545: iconst_0
    //   1546: bastore
    //   1547: dup
    //   1548: bipush #35
    //   1550: iconst_0
    //   1551: bastore
    //   1552: dup
    //   1553: bipush #36
    //   1555: iconst_0
    //   1556: bastore
    //   1557: dup
    //   1558: bipush #37
    //   1560: iconst_0
    //   1561: bastore
    //   1562: dup
    //   1563: bipush #38
    //   1565: iconst_0
    //   1566: bastore
    //   1567: dup
    //   1568: bipush #39
    //   1570: iconst_0
    //   1571: bastore
    //   1572: dup
    //   1573: bipush #40
    //   1575: iconst_0
    //   1576: bastore
    //   1577: dup
    //   1578: bipush #41
    //   1580: iconst_0
    //   1581: bastore
    //   1582: dup
    //   1583: bipush #42
    //   1585: iconst_0
    //   1586: bastore
    //   1587: dup
    //   1588: bipush #43
    //   1590: iconst_0
    //   1591: bastore
    //   1592: dup
    //   1593: bipush #44
    //   1595: iconst_0
    //   1596: bastore
    //   1597: dup
    //   1598: bipush #45
    //   1600: iconst_0
    //   1601: bastore
    //   1602: dup
    //   1603: bipush #46
    //   1605: iconst_0
    //   1606: bastore
    //   1607: dup
    //   1608: bipush #47
    //   1610: iconst_0
    //   1611: bastore
    //   1612: dup
    //   1613: bipush #48
    //   1615: iconst_0
    //   1616: bastore
    //   1617: dup
    //   1618: bipush #49
    //   1620: iconst_0
    //   1621: bastore
    //   1622: dup
    //   1623: bipush #50
    //   1625: iconst_0
    //   1626: bastore
    //   1627: dup
    //   1628: bipush #51
    //   1630: iconst_0
    //   1631: bastore
    //   1632: dup
    //   1633: bipush #52
    //   1635: iconst_0
    //   1636: bastore
    //   1637: dup
    //   1638: bipush #53
    //   1640: iconst_0
    //   1641: bastore
    //   1642: dup
    //   1643: bipush #54
    //   1645: iconst_0
    //   1646: bastore
    //   1647: dup
    //   1648: bipush #55
    //   1650: iconst_0
    //   1651: bastore
    //   1652: dup
    //   1653: bipush #56
    //   1655: iconst_0
    //   1656: bastore
    //   1657: dup
    //   1658: bipush #57
    //   1660: iconst_0
    //   1661: bastore
    //   1662: dup
    //   1663: bipush #58
    //   1665: iconst_0
    //   1666: bastore
    //   1667: dup
    //   1668: bipush #59
    //   1670: iconst_0
    //   1671: bastore
    //   1672: dup
    //   1673: bipush #60
    //   1675: iconst_0
    //   1676: bastore
    //   1677: dup
    //   1678: bipush #61
    //   1680: iconst_0
    //   1681: bastore
    //   1682: dup
    //   1683: bipush #62
    //   1685: iconst_0
    //   1686: bastore
    //   1687: dup
    //   1688: bipush #63
    //   1690: iconst_0
    //   1691: bastore
    //   1692: astore #6
    //   1694: bipush #64
    //   1696: newarray int
    //   1698: dup
    //   1699: iconst_0
    //   1700: ldc 1116352408
    //   1702: iastore
    //   1703: dup
    //   1704: iconst_1
    //   1705: ldc 1899447441
    //   1707: iastore
    //   1708: dup
    //   1709: iconst_2
    //   1710: ldc -1245643825
    //   1712: iastore
    //   1713: dup
    //   1714: iconst_3
    //   1715: ldc -373957723
    //   1717: iastore
    //   1718: dup
    //   1719: iconst_4
    //   1720: ldc 961987163
    //   1722: iastore
    //   1723: dup
    //   1724: iconst_5
    //   1725: ldc 1508970993
    //   1727: iastore
    //   1728: dup
    //   1729: bipush #6
    //   1731: ldc -1841331548
    //   1733: iastore
    //   1734: dup
    //   1735: bipush #7
    //   1737: ldc -1424204075
    //   1739: iastore
    //   1740: dup
    //   1741: bipush #8
    //   1743: ldc -670586216
    //   1745: iastore
    //   1746: dup
    //   1747: bipush #9
    //   1749: ldc 310598401
    //   1751: iastore
    //   1752: dup
    //   1753: bipush #10
    //   1755: ldc 607225278
    //   1757: iastore
    //   1758: dup
    //   1759: bipush #11
    //   1761: ldc 1426881987
    //   1763: iastore
    //   1764: dup
    //   1765: bipush #12
    //   1767: ldc 1925078388
    //   1769: iastore
    //   1770: dup
    //   1771: bipush #13
    //   1773: ldc -2132889090
    //   1775: iastore
    //   1776: dup
    //   1777: bipush #14
    //   1779: ldc -1680079193
    //   1781: iastore
    //   1782: dup
    //   1783: bipush #15
    //   1785: ldc -1046744716
    //   1787: iastore
    //   1788: dup
    //   1789: bipush #16
    //   1791: ldc -459576895
    //   1793: iastore
    //   1794: dup
    //   1795: bipush #17
    //   1797: ldc -272742522
    //   1799: iastore
    //   1800: dup
    //   1801: bipush #18
    //   1803: ldc 264347078
    //   1805: iastore
    //   1806: dup
    //   1807: bipush #19
    //   1809: ldc 604807628
    //   1811: iastore
    //   1812: dup
    //   1813: bipush #20
    //   1815: ldc 770255983
    //   1817: iastore
    //   1818: dup
    //   1819: bipush #21
    //   1821: ldc 1249150122
    //   1823: iastore
    //   1824: dup
    //   1825: bipush #22
    //   1827: ldc 1555081692
    //   1829: iastore
    //   1830: dup
    //   1831: bipush #23
    //   1833: ldc 1996064986
    //   1835: iastore
    //   1836: dup
    //   1837: bipush #24
    //   1839: ldc -1740746414
    //   1841: iastore
    //   1842: dup
    //   1843: bipush #25
    //   1845: ldc -1473132947
    //   1847: iastore
    //   1848: dup
    //   1849: bipush #26
    //   1851: ldc -1341970488
    //   1853: iastore
    //   1854: dup
    //   1855: bipush #27
    //   1857: ldc -1084653625
    //   1859: iastore
    //   1860: dup
    //   1861: bipush #28
    //   1863: ldc -958395405
    //   1865: iastore
    //   1866: dup
    //   1867: bipush #29
    //   1869: ldc -710438585
    //   1871: iastore
    //   1872: dup
    //   1873: bipush #30
    //   1875: ldc 113926993
    //   1877: iastore
    //   1878: dup
    //   1879: bipush #31
    //   1881: ldc 338241895
    //   1883: iastore
    //   1884: dup
    //   1885: bipush #32
    //   1887: ldc 666307205
    //   1889: iastore
    //   1890: dup
    //   1891: bipush #33
    //   1893: ldc 773529912
    //   1895: iastore
    //   1896: dup
    //   1897: bipush #34
    //   1899: ldc 1294757372
    //   1901: iastore
    //   1902: dup
    //   1903: bipush #35
    //   1905: ldc 1396182291
    //   1907: iastore
    //   1908: dup
    //   1909: bipush #36
    //   1911: ldc 1695183700
    //   1913: iastore
    //   1914: dup
    //   1915: bipush #37
    //   1917: ldc 1986661051
    //   1919: iastore
    //   1920: dup
    //   1921: bipush #38
    //   1923: ldc -2117940946
    //   1925: iastore
    //   1926: dup
    //   1927: bipush #39
    //   1929: ldc -1838011259
    //   1931: iastore
    //   1932: dup
    //   1933: bipush #40
    //   1935: ldc -1564481375
    //   1937: iastore
    //   1938: dup
    //   1939: bipush #41
    //   1941: ldc -1474664885
    //   1943: iastore
    //   1944: dup
    //   1945: bipush #42
    //   1947: ldc -1035236496
    //   1949: iastore
    //   1950: dup
    //   1951: bipush #43
    //   1953: ldc -949202525
    //   1955: iastore
    //   1956: dup
    //   1957: bipush #44
    //   1959: ldc -778901479
    //   1961: iastore
    //   1962: dup
    //   1963: bipush #45
    //   1965: ldc -694614492
    //   1967: iastore
    //   1968: dup
    //   1969: bipush #46
    //   1971: ldc -200395387
    //   1973: iastore
    //   1974: dup
    //   1975: bipush #47
    //   1977: ldc 275423344
    //   1979: iastore
    //   1980: dup
    //   1981: bipush #48
    //   1983: ldc 430227734
    //   1985: iastore
    //   1986: dup
    //   1987: bipush #49
    //   1989: ldc 506948616
    //   1991: iastore
    //   1992: dup
    //   1993: bipush #50
    //   1995: ldc 659060556
    //   1997: iastore
    //   1998: dup
    //   1999: bipush #51
    //   2001: ldc 883997877
    //   2003: iastore
    //   2004: dup
    //   2005: bipush #52
    //   2007: ldc 958139571
    //   2009: iastore
    //   2010: dup
    //   2011: bipush #53
    //   2013: ldc 1322822218
    //   2015: iastore
    //   2016: dup
    //   2017: bipush #54
    //   2019: ldc 1537002063
    //   2021: iastore
    //   2022: dup
    //   2023: bipush #55
    //   2025: ldc 1747873779
    //   2027: iastore
    //   2028: dup
    //   2029: bipush #56
    //   2031: ldc 1955562222
    //   2033: iastore
    //   2034: dup
    //   2035: bipush #57
    //   2037: ldc 2024104815
    //   2039: iastore
    //   2040: dup
    //   2041: bipush #58
    //   2043: ldc -2067236844
    //   2045: iastore
    //   2046: dup
    //   2047: bipush #59
    //   2049: ldc -1933114872
    //   2051: iastore
    //   2052: dup
    //   2053: bipush #60
    //   2055: ldc -1866530822
    //   2057: iastore
    //   2058: dup
    //   2059: bipush #61
    //   2061: ldc -1538233109
    //   2063: iastore
    //   2064: dup
    //   2065: bipush #62
    //   2067: ldc -1090935817
    //   2069: iastore
    //   2070: dup
    //   2071: bipush #63
    //   2073: ldc -965641998
    //   2075: iastore
    //   2076: astore #7
    //   2078: iconst_2
    //   2079: newarray int
    //   2081: dup
    //   2082: iconst_0
    //   2083: iconst_0
    //   2084: iastore
    //   2085: dup
    //   2086: iconst_1
    //   2087: iconst_0
    //   2088: iastore
    //   2089: astore #8
    //   2091: bipush #8
    //   2093: newarray int
    //   2095: dup
    //   2096: iconst_0
    //   2097: ldc 1779033703
    //   2099: iastore
    //   2100: dup
    //   2101: iconst_1
    //   2102: ldc -1150833019
    //   2104: iastore
    //   2105: dup
    //   2106: iconst_2
    //   2107: ldc 1013904242
    //   2109: iastore
    //   2110: dup
    //   2111: iconst_3
    //   2112: ldc -1521486534
    //   2114: iastore
    //   2115: dup
    //   2116: iconst_4
    //   2117: ldc 1359893119
    //   2119: iastore
    //   2120: dup
    //   2121: iconst_5
    //   2122: ldc -1694144372
    //   2124: iastore
    //   2125: dup
    //   2126: bipush #6
    //   2128: ldc 528734635
    //   2130: iastore
    //   2131: dup
    //   2132: bipush #7
    //   2134: ldc 1541459225
    //   2136: iastore
    //   2137: astore #9
    //   2139: bipush #64
    //   2141: newarray byte
    //   2143: astore #10
    //   2145: bipush #64
    //   2147: newarray byte
    //   2149: astore #11
    //   2151: aload #4
    //   2153: arraylength
    //   2154: istore #12
    //   2156: aload #8
    //   2158: iconst_0
    //   2159: iaload
    //   2160: bipush #63
    //   2162: iand
    //   2163: istore #13
    //   2165: aload #8
    //   2167: iconst_0
    //   2168: dup2
    //   2169: iaload
    //   2170: iload #12
    //   2172: iadd
    //   2173: iastore
    //   2174: aload #8
    //   2176: iconst_0
    //   2177: dup2
    //   2178: iaload
    //   2179: iconst_m1
    //   2180: iand
    //   2181: iastore
    //   2182: aload #8
    //   2184: iconst_0
    //   2185: iaload
    //   2186: iload #12
    //   2188: if_icmpge -> 2206
    //   2191: aload #8
    //   2193: iconst_1
    //   2194: dup2
    //   2195: iaload
    //   2196: iconst_1
    //   2197: iadd
    //   2198: iastore
    //   2199: goto -> 2206
    //   2202: invokestatic a : (Ljava/lang/Throwable;)Ljava/lang/Throwable;
    //   2205: athrow
    //   2206: iconst_0
    //   2207: istore #14
    //   2209: iload #12
    //   2211: bipush #64
    //   2213: if_icmplt -> 2823
    //   2216: iconst_0
    //   2217: istore #15
    //   2219: iload #15
    //   2221: bipush #64
    //   2223: if_icmpge -> 2246
    //   2226: aload #11
    //   2228: iload #15
    //   2230: aload #4
    //   2232: iload #14
    //   2234: iload #15
    //   2236: iadd
    //   2237: baload
    //   2238: bastore
    //   2239: iinc #15, 1
    //   2242: iload_2
    //   2243: ifeq -> 2219
    //   2246: bipush #64
    //   2248: newarray int
    //   2250: astore #15
    //   2252: bipush #8
    //   2254: newarray int
    //   2256: astore #16
    //   2258: iconst_0
    //   2259: istore #17
    //   2261: iload #17
    //   2263: bipush #8
    //   2265: if_icmpge -> 2285
    //   2268: aload #16
    //   2270: iload #17
    //   2272: aload #9
    //   2274: iload #17
    //   2276: iaload
    //   2277: iastore
    //   2278: iinc #17, 1
    //   2281: iload_2
    //   2282: ifeq -> 2261
    //   2285: iconst_0
    //   2286: istore #17
    //   2288: iload #17
    //   2290: bipush #64
    //   2292: if_icmpge -> 2783
    //   2295: iload #17
    //   2297: bipush #16
    //   2299: if_icmpge -> 2380
    //   2302: aload #15
    //   2304: iload #17
    //   2306: aload #11
    //   2308: iconst_4
    //   2309: iload #17
    //   2311: imul
    //   2312: baload
    //   2313: sipush #255
    //   2316: iand
    //   2317: bipush #24
    //   2319: ishl
    //   2320: aload #11
    //   2322: iconst_4
    //   2323: iload #17
    //   2325: imul
    //   2326: iconst_1
    //   2327: iadd
    //   2328: baload
    //   2329: sipush #255
    //   2332: iand
    //   2333: bipush #16
    //   2335: ishl
    //   2336: ior
    //   2337: aload #11
    //   2339: iconst_4
    //   2340: iload #17
    //   2342: imul
    //   2343: iconst_2
    //   2344: iadd
    //   2345: baload
    //   2346: sipush #255
    //   2349: iand
    //   2350: bipush #8
    //   2352: ishl
    //   2353: ior
    //   2354: aload #11
    //   2356: iconst_4
    //   2357: iload #17
    //   2359: imul
    //   2360: iconst_3
    //   2361: iadd
    //   2362: baload
    //   2363: sipush #255
    //   2366: iand
    //   2367: ior
    //   2368: iastore
    //   2369: iload_2
    //   2370: ifeq -> 2523
    //   2373: goto -> 2380
    //   2376: invokestatic a : (Ljava/lang/Throwable;)Ljava/lang/Throwable;
    //   2379: athrow
    //   2380: aload #15
    //   2382: iload #17
    //   2384: aload #15
    //   2386: iload #17
    //   2388: iconst_2
    //   2389: isub
    //   2390: iaload
    //   2391: bipush #17
    //   2393: iushr
    //   2394: aload #15
    //   2396: iload #17
    //   2398: iconst_2
    //   2399: isub
    //   2400: iaload
    //   2401: bipush #15
    //   2403: ishl
    //   2404: ior
    //   2405: aload #15
    //   2407: iload #17
    //   2409: iconst_2
    //   2410: isub
    //   2411: iaload
    //   2412: bipush #19
    //   2414: iushr
    //   2415: aload #15
    //   2417: iload #17
    //   2419: iconst_2
    //   2420: isub
    //   2421: iaload
    //   2422: bipush #13
    //   2424: ishl
    //   2425: ior
    //   2426: ixor
    //   2427: aload #15
    //   2429: iload #17
    //   2431: iconst_2
    //   2432: isub
    //   2433: iaload
    //   2434: bipush #10
    //   2436: iushr
    //   2437: ixor
    //   2438: aload #15
    //   2440: iload #17
    //   2442: bipush #7
    //   2444: isub
    //   2445: iaload
    //   2446: iadd
    //   2447: aload #15
    //   2449: iload #17
    //   2451: bipush #15
    //   2453: isub
    //   2454: iaload
    //   2455: bipush #7
    //   2457: iushr
    //   2458: aload #15
    //   2460: iload #17
    //   2462: bipush #15
    //   2464: isub
    //   2465: iaload
    //   2466: bipush #25
    //   2468: ishl
    //   2469: ior
    //   2470: aload #15
    //   2472: iload #17
    //   2474: bipush #15
    //   2476: isub
    //   2477: iaload
    //   2478: bipush #18
    //   2480: iushr
    //   2481: aload #15
    //   2483: iload #17
    //   2485: bipush #15
    //   2487: isub
    //   2488: iaload
    //   2489: bipush #14
    //   2491: ishl
    //   2492: ior
    //   2493: ixor
    //   2494: aload #15
    //   2496: iload #17
    //   2498: bipush #15
    //   2500: isub
    //   2501: iaload
    //   2502: iconst_3
    //   2503: iushr
    //   2504: ixor
    //   2505: iadd
    //   2506: aload #15
    //   2508: iload #17
    //   2510: bipush #16
    //   2512: isub
    //   2513: iaload
    //   2514: iadd
    //   2515: iastore
    //   2516: goto -> 2523
    //   2519: invokestatic a : (Ljava/lang/Throwable;)Ljava/lang/Throwable;
    //   2522: athrow
    //   2523: aload #16
    //   2525: bipush #7
    //   2527: iaload
    //   2528: aload #16
    //   2530: iconst_4
    //   2531: iaload
    //   2532: bipush #6
    //   2534: iushr
    //   2535: aload #16
    //   2537: iconst_4
    //   2538: iaload
    //   2539: bipush #26
    //   2541: ishl
    //   2542: ior
    //   2543: aload #16
    //   2545: iconst_4
    //   2546: iaload
    //   2547: bipush #11
    //   2549: iushr
    //   2550: aload #16
    //   2552: iconst_4
    //   2553: iaload
    //   2554: bipush #21
    //   2556: ishl
    //   2557: ior
    //   2558: ixor
    //   2559: aload #16
    //   2561: iconst_4
    //   2562: iaload
    //   2563: bipush #25
    //   2565: iushr
    //   2566: aload #16
    //   2568: iconst_4
    //   2569: iaload
    //   2570: bipush #7
    //   2572: ishl
    //   2573: ior
    //   2574: ixor
    //   2575: iadd
    //   2576: aload #16
    //   2578: bipush #6
    //   2580: iaload
    //   2581: aload #16
    //   2583: iconst_4
    //   2584: iaload
    //   2585: aload #16
    //   2587: iconst_5
    //   2588: iaload
    //   2589: aload #16
    //   2591: bipush #6
    //   2593: iaload
    //   2594: ixor
    //   2595: iand
    //   2596: ixor
    //   2597: iadd
    //   2598: aload #7
    //   2600: iload #17
    //   2602: iaload
    //   2603: iadd
    //   2604: aload #15
    //   2606: iload #17
    //   2608: iaload
    //   2609: iadd
    //   2610: istore #18
    //   2612: aload #16
    //   2614: iconst_0
    //   2615: iaload
    //   2616: iconst_2
    //   2617: iushr
    //   2618: aload #16
    //   2620: iconst_0
    //   2621: iaload
    //   2622: bipush #30
    //   2624: ishl
    //   2625: ior
    //   2626: aload #16
    //   2628: iconst_0
    //   2629: iaload
    //   2630: bipush #13
    //   2632: iushr
    //   2633: aload #16
    //   2635: iconst_0
    //   2636: iaload
    //   2637: bipush #19
    //   2639: ishl
    //   2640: ior
    //   2641: ixor
    //   2642: aload #16
    //   2644: iconst_0
    //   2645: iaload
    //   2646: bipush #22
    //   2648: iushr
    //   2649: aload #16
    //   2651: iconst_0
    //   2652: iaload
    //   2653: bipush #10
    //   2655: ishl
    //   2656: ior
    //   2657: ixor
    //   2658: aload #16
    //   2660: iconst_0
    //   2661: iaload
    //   2662: aload #16
    //   2664: iconst_1
    //   2665: iaload
    //   2666: iand
    //   2667: aload #16
    //   2669: iconst_2
    //   2670: iaload
    //   2671: aload #16
    //   2673: iconst_0
    //   2674: iaload
    //   2675: aload #16
    //   2677: iconst_1
    //   2678: iaload
    //   2679: ior
    //   2680: iand
    //   2681: ior
    //   2682: iadd
    //   2683: istore #19
    //   2685: aload #16
    //   2687: iconst_3
    //   2688: dup2
    //   2689: iaload
    //   2690: iload #18
    //   2692: iadd
    //   2693: iastore
    //   2694: aload #16
    //   2696: bipush #7
    //   2698: iload #18
    //   2700: iload #19
    //   2702: iadd
    //   2703: iastore
    //   2704: aload #16
    //   2706: bipush #7
    //   2708: iaload
    //   2709: istore #18
    //   2711: aload #16
    //   2713: bipush #7
    //   2715: aload #16
    //   2717: bipush #6
    //   2719: iaload
    //   2720: iastore
    //   2721: aload #16
    //   2723: bipush #6
    //   2725: aload #16
    //   2727: iconst_5
    //   2728: iaload
    //   2729: iastore
    //   2730: aload #16
    //   2732: iconst_5
    //   2733: aload #16
    //   2735: iconst_4
    //   2736: iaload
    //   2737: iastore
    //   2738: aload #16
    //   2740: iconst_4
    //   2741: aload #16
    //   2743: iconst_3
    //   2744: iaload
    //   2745: iastore
    //   2746: aload #16
    //   2748: iconst_3
    //   2749: aload #16
    //   2751: iconst_2
    //   2752: iaload
    //   2753: iastore
    //   2754: aload #16
    //   2756: iconst_2
    //   2757: aload #16
    //   2759: iconst_1
    //   2760: iaload
    //   2761: iastore
    //   2762: aload #16
    //   2764: iconst_1
    //   2765: aload #16
    //   2767: iconst_0
    //   2768: iaload
    //   2769: iastore
    //   2770: aload #16
    //   2772: iconst_0
    //   2773: iload #18
    //   2775: iastore
    //   2776: iinc #17, 1
    //   2779: iload_2
    //   2780: ifeq -> 2288
    //   2783: iconst_0
    //   2784: istore #17
    //   2786: iload #17
    //   2788: bipush #8
    //   2790: if_icmpge -> 2813
    //   2793: aload #9
    //   2795: iload #17
    //   2797: dup2
    //   2798: iaload
    //   2799: aload #16
    //   2801: iload #17
    //   2803: iaload
    //   2804: iadd
    //   2805: iastore
    //   2806: iinc #17, 1
    //   2809: iload_2
    //   2810: ifeq -> 2786
    //   2813: iinc #14, 64
    //   2816: iinc #12, -64
    //   2819: iload_2
    //   2820: ifeq -> 2209
    //   2823: iload #12
    //   2825: ifle -> 2861
    //   2828: iconst_0
    //   2829: istore #15
    //   2831: iload #15
    //   2833: iload #12
    //   2835: if_icmpge -> 2861
    //   2838: aload #10
    //   2840: iload #13
    //   2842: iload #15
    //   2844: iadd
    //   2845: aload #4
    //   2847: iload #14
    //   2849: iload #15
    //   2851: iadd
    //   2852: baload
    //   2853: bastore
    //   2854: iinc #15, 1
    //   2857: iload_2
    //   2858: ifeq -> 2831
    //   2861: aload #8
    //   2863: iconst_0
    //   2864: iaload
    //   2865: bipush #29
    //   2867: iushr
    //   2868: aload #8
    //   2870: iconst_1
    //   2871: iaload
    //   2872: iconst_3
    //   2873: ishl
    //   2874: ior
    //   2875: istore #15
    //   2877: aload #8
    //   2879: iconst_0
    //   2880: iaload
    //   2881: iconst_3
    //   2882: ishl
    //   2883: istore #16
    //   2885: aload #8
    //   2887: iconst_0
    //   2888: iaload
    //   2889: bipush #63
    //   2891: iand
    //   2892: istore #17
    //   2894: iload #17
    //   2896: bipush #56
    //   2898: if_icmpge -> 2913
    //   2901: bipush #56
    //   2903: iload #17
    //   2905: isub
    //   2906: goto -> 2918
    //   2909: invokestatic a : (Ljava/lang/Throwable;)Ljava/lang/Throwable;
    //   2912: athrow
    //   2913: bipush #120
    //   2915: iload #17
    //   2917: isub
    //   2918: istore #18
    //   2920: aload #8
    //   2922: iconst_0
    //   2923: iaload
    //   2924: bipush #63
    //   2926: iand
    //   2927: istore #13
    //   2929: bipush #64
    //   2931: iload #13
    //   2933: isub
    //   2934: istore #19
    //   2936: aload #8
    //   2938: iconst_0
    //   2939: dup2
    //   2940: iaload
    //   2941: iload #18
    //   2943: iadd
    //   2944: iastore
    //   2945: aload #8
    //   2947: iconst_0
    //   2948: dup2
    //   2949: iaload
    //   2950: iconst_m1
    //   2951: iand
    //   2952: iastore
    //   2953: aload #8
    //   2955: iconst_0
    //   2956: iaload
    //   2957: iload #18
    //   2959: if_icmpge -> 2977
    //   2962: aload #8
    //   2964: iconst_1
    //   2965: dup2
    //   2966: iaload
    //   2967: iconst_1
    //   2968: iadd
    //   2969: iastore
    //   2970: goto -> 2977
    //   2973: invokestatic a : (Ljava/lang/Throwable;)Ljava/lang/Throwable;
    //   2976: athrow
    //   2977: iconst_0
    //   2978: istore #14
    //   2980: iload #13
    //   2982: ifle -> 3613
    //   2985: iload #18
    //   2987: iload #19
    //   2989: if_icmplt -> 3613
    //   2992: goto -> 2999
    //   2995: invokestatic a : (Ljava/lang/Throwable;)Ljava/lang/Throwable;
    //   2998: athrow
    //   2999: iconst_0
    //   3000: istore #20
    //   3002: iload #20
    //   3004: iload #19
    //   3006: if_icmpge -> 3029
    //   3009: aload #10
    //   3011: iload #13
    //   3013: iload #20
    //   3015: iadd
    //   3016: aload #6
    //   3018: iload #20
    //   3020: baload
    //   3021: bastore
    //   3022: iinc #20, 1
    //   3025: iload_2
    //   3026: ifeq -> 3002
    //   3029: bipush #64
    //   3031: newarray int
    //   3033: astore #20
    //   3035: bipush #8
    //   3037: newarray int
    //   3039: astore #21
    //   3041: iconst_0
    //   3042: istore #22
    //   3044: iload #22
    //   3046: bipush #8
    //   3048: if_icmpge -> 3068
    //   3051: aload #21
    //   3053: iload #22
    //   3055: aload #9
    //   3057: iload #22
    //   3059: iaload
    //   3060: iastore
    //   3061: iinc #22, 1
    //   3064: iload_2
    //   3065: ifeq -> 3044
    //   3068: iconst_0
    //   3069: istore #22
    //   3071: iload #22
    //   3073: bipush #64
    //   3075: if_icmpge -> 3566
    //   3078: iload #22
    //   3080: bipush #16
    //   3082: if_icmpge -> 3163
    //   3085: aload #20
    //   3087: iload #22
    //   3089: aload #10
    //   3091: iconst_4
    //   3092: iload #22
    //   3094: imul
    //   3095: baload
    //   3096: sipush #255
    //   3099: iand
    //   3100: bipush #24
    //   3102: ishl
    //   3103: aload #10
    //   3105: iconst_4
    //   3106: iload #22
    //   3108: imul
    //   3109: iconst_1
    //   3110: iadd
    //   3111: baload
    //   3112: sipush #255
    //   3115: iand
    //   3116: bipush #16
    //   3118: ishl
    //   3119: ior
    //   3120: aload #10
    //   3122: iconst_4
    //   3123: iload #22
    //   3125: imul
    //   3126: iconst_2
    //   3127: iadd
    //   3128: baload
    //   3129: sipush #255
    //   3132: iand
    //   3133: bipush #8
    //   3135: ishl
    //   3136: ior
    //   3137: aload #10
    //   3139: iconst_4
    //   3140: iload #22
    //   3142: imul
    //   3143: iconst_3
    //   3144: iadd
    //   3145: baload
    //   3146: sipush #255
    //   3149: iand
    //   3150: ior
    //   3151: iastore
    //   3152: iload_2
    //   3153: ifeq -> 3306
    //   3156: goto -> 3163
    //   3159: invokestatic a : (Ljava/lang/Throwable;)Ljava/lang/Throwable;
    //   3162: athrow
    //   3163: aload #20
    //   3165: iload #22
    //   3167: aload #20
    //   3169: iload #22
    //   3171: iconst_2
    //   3172: isub
    //   3173: iaload
    //   3174: bipush #17
    //   3176: iushr
    //   3177: aload #20
    //   3179: iload #22
    //   3181: iconst_2
    //   3182: isub
    //   3183: iaload
    //   3184: bipush #15
    //   3186: ishl
    //   3187: ior
    //   3188: aload #20
    //   3190: iload #22
    //   3192: iconst_2
    //   3193: isub
    //   3194: iaload
    //   3195: bipush #19
    //   3197: iushr
    //   3198: aload #20
    //   3200: iload #22
    //   3202: iconst_2
    //   3203: isub
    //   3204: iaload
    //   3205: bipush #13
    //   3207: ishl
    //   3208: ior
    //   3209: ixor
    //   3210: aload #20
    //   3212: iload #22
    //   3214: iconst_2
    //   3215: isub
    //   3216: iaload
    //   3217: bipush #10
    //   3219: iushr
    //   3220: ixor
    //   3221: aload #20
    //   3223: iload #22
    //   3225: bipush #7
    //   3227: isub
    //   3228: iaload
    //   3229: iadd
    //   3230: aload #20
    //   3232: iload #22
    //   3234: bipush #15
    //   3236: isub
    //   3237: iaload
    //   3238: bipush #7
    //   3240: iushr
    //   3241: aload #20
    //   3243: iload #22
    //   3245: bipush #15
    //   3247: isub
    //   3248: iaload
    //   3249: bipush #25
    //   3251: ishl
    //   3252: ior
    //   3253: aload #20
    //   3255: iload #22
    //   3257: bipush #15
    //   3259: isub
    //   3260: iaload
    //   3261: bipush #18
    //   3263: iushr
    //   3264: aload #20
    //   3266: iload #22
    //   3268: bipush #15
    //   3270: isub
    //   3271: iaload
    //   3272: bipush #14
    //   3274: ishl
    //   3275: ior
    //   3276: ixor
    //   3277: aload #20
    //   3279: iload #22
    //   3281: bipush #15
    //   3283: isub
    //   3284: iaload
    //   3285: iconst_3
    //   3286: iushr
    //   3287: ixor
    //   3288: iadd
    //   3289: aload #20
    //   3291: iload #22
    //   3293: bipush #16
    //   3295: isub
    //   3296: iaload
    //   3297: iadd
    //   3298: iastore
    //   3299: goto -> 3306
    //   3302: invokestatic a : (Ljava/lang/Throwable;)Ljava/lang/Throwable;
    //   3305: athrow
    //   3306: aload #21
    //   3308: bipush #7
    //   3310: iaload
    //   3311: aload #21
    //   3313: iconst_4
    //   3314: iaload
    //   3315: bipush #6
    //   3317: iushr
    //   3318: aload #21
    //   3320: iconst_4
    //   3321: iaload
    //   3322: bipush #26
    //   3324: ishl
    //   3325: ior
    //   3326: aload #21
    //   3328: iconst_4
    //   3329: iaload
    //   3330: bipush #11
    //   3332: iushr
    //   3333: aload #21
    //   3335: iconst_4
    //   3336: iaload
    //   3337: bipush #21
    //   3339: ishl
    //   3340: ior
    //   3341: ixor
    //   3342: aload #21
    //   3344: iconst_4
    //   3345: iaload
    //   3346: bipush #25
    //   3348: iushr
    //   3349: aload #21
    //   3351: iconst_4
    //   3352: iaload
    //   3353: bipush #7
    //   3355: ishl
    //   3356: ior
    //   3357: ixor
    //   3358: iadd
    //   3359: aload #21
    //   3361: bipush #6
    //   3363: iaload
    //   3364: aload #21
    //   3366: iconst_4
    //   3367: iaload
    //   3368: aload #21
    //   3370: iconst_5
    //   3371: iaload
    //   3372: aload #21
    //   3374: bipush #6
    //   3376: iaload
    //   3377: ixor
    //   3378: iand
    //   3379: ixor
    //   3380: iadd
    //   3381: aload #7
    //   3383: iload #22
    //   3385: iaload
    //   3386: iadd
    //   3387: aload #20
    //   3389: iload #22
    //   3391: iaload
    //   3392: iadd
    //   3393: istore #23
    //   3395: aload #21
    //   3397: iconst_0
    //   3398: iaload
    //   3399: iconst_2
    //   3400: iushr
    //   3401: aload #21
    //   3403: iconst_0
    //   3404: iaload
    //   3405: bipush #30
    //   3407: ishl
    //   3408: ior
    //   3409: aload #21
    //   3411: iconst_0
    //   3412: iaload
    //   3413: bipush #13
    //   3415: iushr
    //   3416: aload #21
    //   3418: iconst_0
    //   3419: iaload
    //   3420: bipush #19
    //   3422: ishl
    //   3423: ior
    //   3424: ixor
    //   3425: aload #21
    //   3427: iconst_0
    //   3428: iaload
    //   3429: bipush #22
    //   3431: iushr
    //   3432: aload #21
    //   3434: iconst_0
    //   3435: iaload
    //   3436: bipush #10
    //   3438: ishl
    //   3439: ior
    //   3440: ixor
    //   3441: aload #21
    //   3443: iconst_0
    //   3444: iaload
    //   3445: aload #21
    //   3447: iconst_1
    //   3448: iaload
    //   3449: iand
    //   3450: aload #21
    //   3452: iconst_2
    //   3453: iaload
    //   3454: aload #21
    //   3456: iconst_0
    //   3457: iaload
    //   3458: aload #21
    //   3460: iconst_1
    //   3461: iaload
    //   3462: ior
    //   3463: iand
    //   3464: ior
    //   3465: iadd
    //   3466: istore #24
    //   3468: aload #21
    //   3470: iconst_3
    //   3471: dup2
    //   3472: iaload
    //   3473: iload #23
    //   3475: iadd
    //   3476: iastore
    //   3477: aload #21
    //   3479: bipush #7
    //   3481: iload #23
    //   3483: iload #24
    //   3485: iadd
    //   3486: iastore
    //   3487: aload #21
    //   3489: bipush #7
    //   3491: iaload
    //   3492: istore #23
    //   3494: aload #21
    //   3496: bipush #7
    //   3498: aload #21
    //   3500: bipush #6
    //   3502: iaload
    //   3503: iastore
    //   3504: aload #21
    //   3506: bipush #6
    //   3508: aload #21
    //   3510: iconst_5
    //   3511: iaload
    //   3512: iastore
    //   3513: aload #21
    //   3515: iconst_5
    //   3516: aload #21
    //   3518: iconst_4
    //   3519: iaload
    //   3520: iastore
    //   3521: aload #21
    //   3523: iconst_4
    //   3524: aload #21
    //   3526: iconst_3
    //   3527: iaload
    //   3528: iastore
    //   3529: aload #21
    //   3531: iconst_3
    //   3532: aload #21
    //   3534: iconst_2
    //   3535: iaload
    //   3536: iastore
    //   3537: aload #21
    //   3539: iconst_2
    //   3540: aload #21
    //   3542: iconst_1
    //   3543: iaload
    //   3544: iastore
    //   3545: aload #21
    //   3547: iconst_1
    //   3548: aload #21
    //   3550: iconst_0
    //   3551: iaload
    //   3552: iastore
    //   3553: aload #21
    //   3555: iconst_0
    //   3556: iload #23
    //   3558: iastore
    //   3559: iinc #22, 1
    //   3562: iload_2
    //   3563: ifeq -> 3071
    //   3566: iconst_0
    //   3567: istore #22
    //   3569: iload #22
    //   3571: bipush #8
    //   3573: if_icmpge -> 3596
    //   3576: aload #9
    //   3578: iload #22
    //   3580: dup2
    //   3581: iaload
    //   3582: aload #21
    //   3584: iload #22
    //   3586: iaload
    //   3587: iadd
    //   3588: iastore
    //   3589: iinc #22, 1
    //   3592: iload_2
    //   3593: ifeq -> 3569
    //   3596: iload #14
    //   3598: iload #19
    //   3600: iadd
    //   3601: istore #14
    //   3603: iload #18
    //   3605: iload #19
    //   3607: isub
    //   3608: istore #18
    //   3610: iconst_0
    //   3611: istore #13
    //   3613: iload #18
    //   3615: bipush #64
    //   3617: if_icmplt -> 4227
    //   3620: iconst_0
    //   3621: istore #20
    //   3623: iload #20
    //   3625: bipush #64
    //   3627: if_icmpge -> 3650
    //   3630: aload #11
    //   3632: iload #20
    //   3634: aload #6
    //   3636: iload #14
    //   3638: iload #20
    //   3640: iadd
    //   3641: baload
    //   3642: bastore
    //   3643: iinc #20, 1
    //   3646: iload_2
    //   3647: ifeq -> 3623
    //   3650: bipush #64
    //   3652: newarray int
    //   3654: astore #20
    //   3656: bipush #8
    //   3658: newarray int
    //   3660: astore #21
    //   3662: iconst_0
    //   3663: istore #22
    //   3665: iload #22
    //   3667: bipush #8
    //   3669: if_icmpge -> 3689
    //   3672: aload #21
    //   3674: iload #22
    //   3676: aload #9
    //   3678: iload #22
    //   3680: iaload
    //   3681: iastore
    //   3682: iinc #22, 1
    //   3685: iload_2
    //   3686: ifeq -> 3665
    //   3689: iconst_0
    //   3690: istore #22
    //   3692: iload #22
    //   3694: bipush #64
    //   3696: if_icmpge -> 4187
    //   3699: iload #22
    //   3701: bipush #16
    //   3703: if_icmpge -> 3784
    //   3706: aload #20
    //   3708: iload #22
    //   3710: aload #11
    //   3712: iconst_4
    //   3713: iload #22
    //   3715: imul
    //   3716: baload
    //   3717: sipush #255
    //   3720: iand
    //   3721: bipush #24
    //   3723: ishl
    //   3724: aload #11
    //   3726: iconst_4
    //   3727: iload #22
    //   3729: imul
    //   3730: iconst_1
    //   3731: iadd
    //   3732: baload
    //   3733: sipush #255
    //   3736: iand
    //   3737: bipush #16
    //   3739: ishl
    //   3740: ior
    //   3741: aload #11
    //   3743: iconst_4
    //   3744: iload #22
    //   3746: imul
    //   3747: iconst_2
    //   3748: iadd
    //   3749: baload
    //   3750: sipush #255
    //   3753: iand
    //   3754: bipush #8
    //   3756: ishl
    //   3757: ior
    //   3758: aload #11
    //   3760: iconst_4
    //   3761: iload #22
    //   3763: imul
    //   3764: iconst_3
    //   3765: iadd
    //   3766: baload
    //   3767: sipush #255
    //   3770: iand
    //   3771: ior
    //   3772: iastore
    //   3773: iload_2
    //   3774: ifeq -> 3927
    //   3777: goto -> 3784
    //   3780: invokestatic a : (Ljava/lang/Throwable;)Ljava/lang/Throwable;
    //   3783: athrow
    //   3784: aload #20
    //   3786: iload #22
    //   3788: aload #20
    //   3790: iload #22
    //   3792: iconst_2
    //   3793: isub
    //   3794: iaload
    //   3795: bipush #17
    //   3797: iushr
    //   3798: aload #20
    //   3800: iload #22
    //   3802: iconst_2
    //   3803: isub
    //   3804: iaload
    //   3805: bipush #15
    //   3807: ishl
    //   3808: ior
    //   3809: aload #20
    //   3811: iload #22
    //   3813: iconst_2
    //   3814: isub
    //   3815: iaload
    //   3816: bipush #19
    //   3818: iushr
    //   3819: aload #20
    //   3821: iload #22
    //   3823: iconst_2
    //   3824: isub
    //   3825: iaload
    //   3826: bipush #13
    //   3828: ishl
    //   3829: ior
    //   3830: ixor
    //   3831: aload #20
    //   3833: iload #22
    //   3835: iconst_2
    //   3836: isub
    //   3837: iaload
    //   3838: bipush #10
    //   3840: iushr
    //   3841: ixor
    //   3842: aload #20
    //   3844: iload #22
    //   3846: bipush #7
    //   3848: isub
    //   3849: iaload
    //   3850: iadd
    //   3851: aload #20
    //   3853: iload #22
    //   3855: bipush #15
    //   3857: isub
    //   3858: iaload
    //   3859: bipush #7
    //   3861: iushr
    //   3862: aload #20
    //   3864: iload #22
    //   3866: bipush #15
    //   3868: isub
    //   3869: iaload
    //   3870: bipush #25
    //   3872: ishl
    //   3873: ior
    //   3874: aload #20
    //   3876: iload #22
    //   3878: bipush #15
    //   3880: isub
    //   3881: iaload
    //   3882: bipush #18
    //   3884: iushr
    //   3885: aload #20
    //   3887: iload #22
    //   3889: bipush #15
    //   3891: isub
    //   3892: iaload
    //   3893: bipush #14
    //   3895: ishl
    //   3896: ior
    //   3897: ixor
    //   3898: aload #20
    //   3900: iload #22
    //   3902: bipush #15
    //   3904: isub
    //   3905: iaload
    //   3906: iconst_3
    //   3907: iushr
    //   3908: ixor
    //   3909: iadd
    //   3910: aload #20
    //   3912: iload #22
    //   3914: bipush #16
    //   3916: isub
    //   3917: iaload
    //   3918: iadd
    //   3919: iastore
    //   3920: goto -> 3927
    //   3923: invokestatic a : (Ljava/lang/Throwable;)Ljava/lang/Throwable;
    //   3926: athrow
    //   3927: aload #21
    //   3929: bipush #7
    //   3931: iaload
    //   3932: aload #21
    //   3934: iconst_4
    //   3935: iaload
    //   3936: bipush #6
    //   3938: iushr
    //   3939: aload #21
    //   3941: iconst_4
    //   3942: iaload
    //   3943: bipush #26
    //   3945: ishl
    //   3946: ior
    //   3947: aload #21
    //   3949: iconst_4
    //   3950: iaload
    //   3951: bipush #11
    //   3953: iushr
    //   3954: aload #21
    //   3956: iconst_4
    //   3957: iaload
    //   3958: bipush #21
    //   3960: ishl
    //   3961: ior
    //   3962: ixor
    //   3963: aload #21
    //   3965: iconst_4
    //   3966: iaload
    //   3967: bipush #25
    //   3969: iushr
    //   3970: aload #21
    //   3972: iconst_4
    //   3973: iaload
    //   3974: bipush #7
    //   3976: ishl
    //   3977: ior
    //   3978: ixor
    //   3979: iadd
    //   3980: aload #21
    //   3982: bipush #6
    //   3984: iaload
    //   3985: aload #21
    //   3987: iconst_4
    //   3988: iaload
    //   3989: aload #21
    //   3991: iconst_5
    //   3992: iaload
    //   3993: aload #21
    //   3995: bipush #6
    //   3997: iaload
    //   3998: ixor
    //   3999: iand
    //   4000: ixor
    //   4001: iadd
    //   4002: aload #7
    //   4004: iload #22
    //   4006: iaload
    //   4007: iadd
    //   4008: aload #20
    //   4010: iload #22
    //   4012: iaload
    //   4013: iadd
    //   4014: istore #23
    //   4016: aload #21
    //   4018: iconst_0
    //   4019: iaload
    //   4020: iconst_2
    //   4021: iushr
    //   4022: aload #21
    //   4024: iconst_0
    //   4025: iaload
    //   4026: bipush #30
    //   4028: ishl
    //   4029: ior
    //   4030: aload #21
    //   4032: iconst_0
    //   4033: iaload
    //   4034: bipush #13
    //   4036: iushr
    //   4037: aload #21
    //   4039: iconst_0
    //   4040: iaload
    //   4041: bipush #19
    //   4043: ishl
    //   4044: ior
    //   4045: ixor
    //   4046: aload #21
    //   4048: iconst_0
    //   4049: iaload
    //   4050: bipush #22
    //   4052: iushr
    //   4053: aload #21
    //   4055: iconst_0
    //   4056: iaload
    //   4057: bipush #10
    //   4059: ishl
    //   4060: ior
    //   4061: ixor
    //   4062: aload #21
    //   4064: iconst_0
    //   4065: iaload
    //   4066: aload #21
    //   4068: iconst_1
    //   4069: iaload
    //   4070: iand
    //   4071: aload #21
    //   4073: iconst_2
    //   4074: iaload
    //   4075: aload #21
    //   4077: iconst_0
    //   4078: iaload
    //   4079: aload #21
    //   4081: iconst_1
    //   4082: iaload
    //   4083: ior
    //   4084: iand
    //   4085: ior
    //   4086: iadd
    //   4087: istore #24
    //   4089: aload #21
    //   4091: iconst_3
    //   4092: dup2
    //   4093: iaload
    //   4094: iload #23
    //   4096: iadd
    //   4097: iastore
    //   4098: aload #21
    //   4100: bipush #7
    //   4102: iload #23
    //   4104: iload #24
    //   4106: iadd
    //   4107: iastore
    //   4108: aload #21
    //   4110: bipush #7
    //   4112: iaload
    //   4113: istore #23
    //   4115: aload #21
    //   4117: bipush #7
    //   4119: aload #21
    //   4121: bipush #6
    //   4123: iaload
    //   4124: iastore
    //   4125: aload #21
    //   4127: bipush #6
    //   4129: aload #21
    //   4131: iconst_5
    //   4132: iaload
    //   4133: iastore
    //   4134: aload #21
    //   4136: iconst_5
    //   4137: aload #21
    //   4139: iconst_4
    //   4140: iaload
    //   4141: iastore
    //   4142: aload #21
    //   4144: iconst_4
    //   4145: aload #21
    //   4147: iconst_3
    //   4148: iaload
    //   4149: iastore
    //   4150: aload #21
    //   4152: iconst_3
    //   4153: aload #21
    //   4155: iconst_2
    //   4156: iaload
    //   4157: iastore
    //   4158: aload #21
    //   4160: iconst_2
    //   4161: aload #21
    //   4163: iconst_1
    //   4164: iaload
    //   4165: iastore
    //   4166: aload #21
    //   4168: iconst_1
    //   4169: aload #21
    //   4171: iconst_0
    //   4172: iaload
    //   4173: iastore
    //   4174: aload #21
    //   4176: iconst_0
    //   4177: iload #23
    //   4179: iastore
    //   4180: iinc #22, 1
    //   4183: iload_2
    //   4184: ifeq -> 3692
    //   4187: iconst_0
    //   4188: istore #22
    //   4190: iload #22
    //   4192: bipush #8
    //   4194: if_icmpge -> 4217
    //   4197: aload #9
    //   4199: iload #22
    //   4201: dup2
    //   4202: iaload
    //   4203: aload #21
    //   4205: iload #22
    //   4207: iaload
    //   4208: iadd
    //   4209: iastore
    //   4210: iinc #22, 1
    //   4213: iload_2
    //   4214: ifeq -> 4190
    //   4217: iinc #14, 64
    //   4220: iinc #18, -64
    //   4223: iload_2
    //   4224: ifeq -> 3613
    //   4227: iload #18
    //   4229: ifle -> 4265
    //   4232: iconst_0
    //   4233: istore #20
    //   4235: iload #20
    //   4237: iload #18
    //   4239: if_icmpge -> 4265
    //   4242: aload #10
    //   4244: iload #13
    //   4246: iload #20
    //   4248: iadd
    //   4249: aload #6
    //   4251: iload #14
    //   4253: iload #20
    //   4255: iadd
    //   4256: baload
    //   4257: bastore
    //   4258: iinc #20, 1
    //   4261: iload_2
    //   4262: ifeq -> 4235
    //   4265: bipush #8
    //   4267: newarray byte
    //   4269: astore #20
    //   4271: aload #20
    //   4273: iconst_0
    //   4274: iload #15
    //   4276: bipush #24
    //   4278: iushr
    //   4279: i2b
    //   4280: bastore
    //   4281: aload #20
    //   4283: iconst_1
    //   4284: iload #15
    //   4286: bipush #16
    //   4288: iushr
    //   4289: i2b
    //   4290: bastore
    //   4291: aload #20
    //   4293: iconst_2
    //   4294: iload #15
    //   4296: bipush #8
    //   4298: iushr
    //   4299: i2b
    //   4300: bastore
    //   4301: aload #20
    //   4303: iconst_3
    //   4304: iload #15
    //   4306: i2b
    //   4307: bastore
    //   4308: aload #20
    //   4310: iconst_4
    //   4311: iload #16
    //   4313: bipush #24
    //   4315: iushr
    //   4316: i2b
    //   4317: bastore
    //   4318: aload #20
    //   4320: iconst_5
    //   4321: iload #16
    //   4323: bipush #16
    //   4325: iushr
    //   4326: i2b
    //   4327: bastore
    //   4328: aload #20
    //   4330: bipush #6
    //   4332: iload #16
    //   4334: bipush #8
    //   4336: iushr
    //   4337: i2b
    //   4338: bastore
    //   4339: aload #20
    //   4341: bipush #7
    //   4343: iload #16
    //   4345: i2b
    //   4346: bastore
    //   4347: bipush #8
    //   4349: istore #12
    //   4351: aload #8
    //   4353: iconst_0
    //   4354: iaload
    //   4355: bipush #63
    //   4357: iand
    //   4358: istore #13
    //   4360: bipush #64
    //   4362: iload #13
    //   4364: isub
    //   4365: istore #19
    //   4367: aload #8
    //   4369: iconst_0
    //   4370: dup2
    //   4371: iaload
    //   4372: iload #12
    //   4374: iadd
    //   4375: iastore
    //   4376: aload #8
    //   4378: iconst_0
    //   4379: dup2
    //   4380: iaload
    //   4381: iconst_m1
    //   4382: iand
    //   4383: iastore
    //   4384: aload #8
    //   4386: iconst_0
    //   4387: iaload
    //   4388: iload #12
    //   4390: if_icmpge -> 4408
    //   4393: aload #8
    //   4395: iconst_1
    //   4396: dup2
    //   4397: iaload
    //   4398: iconst_1
    //   4399: iadd
    //   4400: iastore
    //   4401: goto -> 4408
    //   4404: invokestatic a : (Ljava/lang/Throwable;)Ljava/lang/Throwable;
    //   4407: athrow
    //   4408: iload #13
    //   4410: ifle -> 5024
    //   4413: iload #12
    //   4415: iload #19
    //   4417: if_icmplt -> 5024
    //   4420: goto -> 4427
    //   4423: invokestatic a : (Ljava/lang/Throwable;)Ljava/lang/Throwable;
    //   4426: athrow
    //   4427: iconst_0
    //   4428: istore #21
    //   4430: iload #21
    //   4432: iload #19
    //   4434: if_icmpge -> 4457
    //   4437: aload #10
    //   4439: iload #13
    //   4441: iload #21
    //   4443: iadd
    //   4444: aload #20
    //   4446: iload #21
    //   4448: baload
    //   4449: bastore
    //   4450: iinc #21, 1
    //   4453: iload_2
    //   4454: ifeq -> 4430
    //   4457: bipush #64
    //   4459: newarray int
    //   4461: astore #21
    //   4463: bipush #8
    //   4465: newarray int
    //   4467: astore #22
    //   4469: iconst_0
    //   4470: istore #23
    //   4472: iload #23
    //   4474: bipush #8
    //   4476: if_icmpge -> 4496
    //   4479: aload #22
    //   4481: iload #23
    //   4483: aload #9
    //   4485: iload #23
    //   4487: iaload
    //   4488: iastore
    //   4489: iinc #23, 1
    //   4492: iload_2
    //   4493: ifeq -> 4472
    //   4496: iconst_0
    //   4497: istore #23
    //   4499: iload #23
    //   4501: bipush #64
    //   4503: if_icmpge -> 4994
    //   4506: iload #23
    //   4508: bipush #16
    //   4510: if_icmpge -> 4591
    //   4513: aload #21
    //   4515: iload #23
    //   4517: aload #10
    //   4519: iconst_4
    //   4520: iload #23
    //   4522: imul
    //   4523: baload
    //   4524: sipush #255
    //   4527: iand
    //   4528: bipush #24
    //   4530: ishl
    //   4531: aload #10
    //   4533: iconst_4
    //   4534: iload #23
    //   4536: imul
    //   4537: iconst_1
    //   4538: iadd
    //   4539: baload
    //   4540: sipush #255
    //   4543: iand
    //   4544: bipush #16
    //   4546: ishl
    //   4547: ior
    //   4548: aload #10
    //   4550: iconst_4
    //   4551: iload #23
    //   4553: imul
    //   4554: iconst_2
    //   4555: iadd
    //   4556: baload
    //   4557: sipush #255
    //   4560: iand
    //   4561: bipush #8
    //   4563: ishl
    //   4564: ior
    //   4565: aload #10
    //   4567: iconst_4
    //   4568: iload #23
    //   4570: imul
    //   4571: iconst_3
    //   4572: iadd
    //   4573: baload
    //   4574: sipush #255
    //   4577: iand
    //   4578: ior
    //   4579: iastore
    //   4580: iload_2
    //   4581: ifeq -> 4734
    //   4584: goto -> 4591
    //   4587: invokestatic a : (Ljava/lang/Throwable;)Ljava/lang/Throwable;
    //   4590: athrow
    //   4591: aload #21
    //   4593: iload #23
    //   4595: aload #21
    //   4597: iload #23
    //   4599: iconst_2
    //   4600: isub
    //   4601: iaload
    //   4602: bipush #17
    //   4604: iushr
    //   4605: aload #21
    //   4607: iload #23
    //   4609: iconst_2
    //   4610: isub
    //   4611: iaload
    //   4612: bipush #15
    //   4614: ishl
    //   4615: ior
    //   4616: aload #21
    //   4618: iload #23
    //   4620: iconst_2
    //   4621: isub
    //   4622: iaload
    //   4623: bipush #19
    //   4625: iushr
    //   4626: aload #21
    //   4628: iload #23
    //   4630: iconst_2
    //   4631: isub
    //   4632: iaload
    //   4633: bipush #13
    //   4635: ishl
    //   4636: ior
    //   4637: ixor
    //   4638: aload #21
    //   4640: iload #23
    //   4642: iconst_2
    //   4643: isub
    //   4644: iaload
    //   4645: bipush #10
    //   4647: iushr
    //   4648: ixor
    //   4649: aload #21
    //   4651: iload #23
    //   4653: bipush #7
    //   4655: isub
    //   4656: iaload
    //   4657: iadd
    //   4658: aload #21
    //   4660: iload #23
    //   4662: bipush #15
    //   4664: isub
    //   4665: iaload
    //   4666: bipush #7
    //   4668: iushr
    //   4669: aload #21
    //   4671: iload #23
    //   4673: bipush #15
    //   4675: isub
    //   4676: iaload
    //   4677: bipush #25
    //   4679: ishl
    //   4680: ior
    //   4681: aload #21
    //   4683: iload #23
    //   4685: bipush #15
    //   4687: isub
    //   4688: iaload
    //   4689: bipush #18
    //   4691: iushr
    //   4692: aload #21
    //   4694: iload #23
    //   4696: bipush #15
    //   4698: isub
    //   4699: iaload
    //   4700: bipush #14
    //   4702: ishl
    //   4703: ior
    //   4704: ixor
    //   4705: aload #21
    //   4707: iload #23
    //   4709: bipush #15
    //   4711: isub
    //   4712: iaload
    //   4713: iconst_3
    //   4714: iushr
    //   4715: ixor
    //   4716: iadd
    //   4717: aload #21
    //   4719: iload #23
    //   4721: bipush #16
    //   4723: isub
    //   4724: iaload
    //   4725: iadd
    //   4726: iastore
    //   4727: goto -> 4734
    //   4730: invokestatic a : (Ljava/lang/Throwable;)Ljava/lang/Throwable;
    //   4733: athrow
    //   4734: aload #22
    //   4736: bipush #7
    //   4738: iaload
    //   4739: aload #22
    //   4741: iconst_4
    //   4742: iaload
    //   4743: bipush #6
    //   4745: iushr
    //   4746: aload #22
    //   4748: iconst_4
    //   4749: iaload
    //   4750: bipush #26
    //   4752: ishl
    //   4753: ior
    //   4754: aload #22
    //   4756: iconst_4
    //   4757: iaload
    //   4758: bipush #11
    //   4760: iushr
    //   4761: aload #22
    //   4763: iconst_4
    //   4764: iaload
    //   4765: bipush #21
    //   4767: ishl
    //   4768: ior
    //   4769: ixor
    //   4770: aload #22
    //   4772: iconst_4
    //   4773: iaload
    //   4774: bipush #25
    //   4776: iushr
    //   4777: aload #22
    //   4779: iconst_4
    //   4780: iaload
    //   4781: bipush #7
    //   4783: ishl
    //   4784: ior
    //   4785: ixor
    //   4786: iadd
    //   4787: aload #22
    //   4789: bipush #6
    //   4791: iaload
    //   4792: aload #22
    //   4794: iconst_4
    //   4795: iaload
    //   4796: aload #22
    //   4798: iconst_5
    //   4799: iaload
    //   4800: aload #22
    //   4802: bipush #6
    //   4804: iaload
    //   4805: ixor
    //   4806: iand
    //   4807: ixor
    //   4808: iadd
    //   4809: aload #7
    //   4811: iload #23
    //   4813: iaload
    //   4814: iadd
    //   4815: aload #21
    //   4817: iload #23
    //   4819: iaload
    //   4820: iadd
    //   4821: istore #24
    //   4823: aload #22
    //   4825: iconst_0
    //   4826: iaload
    //   4827: iconst_2
    //   4828: iushr
    //   4829: aload #22
    //   4831: iconst_0
    //   4832: iaload
    //   4833: bipush #30
    //   4835: ishl
    //   4836: ior
    //   4837: aload #22
    //   4839: iconst_0
    //   4840: iaload
    //   4841: bipush #13
    //   4843: iushr
    //   4844: aload #22
    //   4846: iconst_0
    //   4847: iaload
    //   4848: bipush #19
    //   4850: ishl
    //   4851: ior
    //   4852: ixor
    //   4853: aload #22
    //   4855: iconst_0
    //   4856: iaload
    //   4857: bipush #22
    //   4859: iushr
    //   4860: aload #22
    //   4862: iconst_0
    //   4863: iaload
    //   4864: bipush #10
    //   4866: ishl
    //   4867: ior
    //   4868: ixor
    //   4869: aload #22
    //   4871: iconst_0
    //   4872: iaload
    //   4873: aload #22
    //   4875: iconst_1
    //   4876: iaload
    //   4877: iand
    //   4878: aload #22
    //   4880: iconst_2
    //   4881: iaload
    //   4882: aload #22
    //   4884: iconst_0
    //   4885: iaload
    //   4886: aload #22
    //   4888: iconst_1
    //   4889: iaload
    //   4890: ior
    //   4891: iand
    //   4892: ior
    //   4893: iadd
    //   4894: istore #25
    //   4896: aload #22
    //   4898: iconst_3
    //   4899: dup2
    //   4900: iaload
    //   4901: iload #24
    //   4903: iadd
    //   4904: iastore
    //   4905: aload #22
    //   4907: bipush #7
    //   4909: iload #24
    //   4911: iload #25
    //   4913: iadd
    //   4914: iastore
    //   4915: aload #22
    //   4917: bipush #7
    //   4919: iaload
    //   4920: istore #24
    //   4922: aload #22
    //   4924: bipush #7
    //   4926: aload #22
    //   4928: bipush #6
    //   4930: iaload
    //   4931: iastore
    //   4932: aload #22
    //   4934: bipush #6
    //   4936: aload #22
    //   4938: iconst_5
    //   4939: iaload
    //   4940: iastore
    //   4941: aload #22
    //   4943: iconst_5
    //   4944: aload #22
    //   4946: iconst_4
    //   4947: iaload
    //   4948: iastore
    //   4949: aload #22
    //   4951: iconst_4
    //   4952: aload #22
    //   4954: iconst_3
    //   4955: iaload
    //   4956: iastore
    //   4957: aload #22
    //   4959: iconst_3
    //   4960: aload #22
    //   4962: iconst_2
    //   4963: iaload
    //   4964: iastore
    //   4965: aload #22
    //   4967: iconst_2
    //   4968: aload #22
    //   4970: iconst_1
    //   4971: iaload
    //   4972: iastore
    //   4973: aload #22
    //   4975: iconst_1
    //   4976: aload #22
    //   4978: iconst_0
    //   4979: iaload
    //   4980: iastore
    //   4981: aload #22
    //   4983: iconst_0
    //   4984: iload #24
    //   4986: iastore
    //   4987: iinc #23, 1
    //   4990: iload_2
    //   4991: ifeq -> 4499
    //   4994: iconst_0
    //   4995: istore #23
    //   4997: iload #23
    //   4999: bipush #8
    //   5001: if_icmpge -> 5024
    //   5004: aload #9
    //   5006: iload #23
    //   5008: dup2
    //   5009: iaload
    //   5010: aload #22
    //   5012: iload #23
    //   5014: iaload
    //   5015: iadd
    //   5016: iastore
    //   5017: iinc #23, 1
    //   5020: iload_2
    //   5021: ifeq -> 4997
    //   5024: bipush #32
    //   5026: newarray byte
    //   5028: astore #5
    //   5030: sipush #13558
    //   5033: aload #5
    //   5035: iconst_0
    //   5036: aload #9
    //   5038: iconst_0
    //   5039: iaload
    //   5040: bipush #24
    //   5042: iushr
    //   5043: i2b
    //   5044: bastore
    //   5045: sipush #-7702
    //   5048: aload #5
    //   5050: iconst_1
    //   5051: aload #9
    //   5053: iconst_0
    //   5054: iaload
    //   5055: bipush #16
    //   5057: iushr
    //   5058: i2b
    //   5059: bastore
    //   5060: aload #5
    //   5062: iconst_2
    //   5063: aload #9
    //   5065: iconst_0
    //   5066: iaload
    //   5067: bipush #8
    //   5069: iushr
    //   5070: i2b
    //   5071: bastore
    //   5072: aload #5
    //   5074: iconst_3
    //   5075: aload #9
    //   5077: iconst_0
    //   5078: iaload
    //   5079: i2b
    //   5080: bastore
    //   5081: aload #5
    //   5083: iconst_4
    //   5084: aload #9
    //   5086: iconst_1
    //   5087: iaload
    //   5088: bipush #24
    //   5090: iushr
    //   5091: i2b
    //   5092: bastore
    //   5093: aload #5
    //   5095: iconst_5
    //   5096: aload #9
    //   5098: iconst_1
    //   5099: iaload
    //   5100: bipush #16
    //   5102: iushr
    //   5103: i2b
    //   5104: bastore
    //   5105: aload #5
    //   5107: bipush #6
    //   5109: aload #9
    //   5111: iconst_1
    //   5112: iaload
    //   5113: bipush #8
    //   5115: iushr
    //   5116: i2b
    //   5117: bastore
    //   5118: aload #5
    //   5120: bipush #7
    //   5122: aload #9
    //   5124: iconst_1
    //   5125: iaload
    //   5126: i2b
    //   5127: bastore
    //   5128: aload #5
    //   5130: bipush #8
    //   5132: aload #9
    //   5134: iconst_2
    //   5135: iaload
    //   5136: bipush #24
    //   5138: iushr
    //   5139: i2b
    //   5140: bastore
    //   5141: aload #5
    //   5143: bipush #9
    //   5145: aload #9
    //   5147: iconst_2
    //   5148: iaload
    //   5149: bipush #16
    //   5151: iushr
    //   5152: i2b
    //   5153: bastore
    //   5154: aload #5
    //   5156: bipush #10
    //   5158: aload #9
    //   5160: iconst_2
    //   5161: iaload
    //   5162: bipush #8
    //   5164: iushr
    //   5165: i2b
    //   5166: bastore
    //   5167: aload #5
    //   5169: bipush #11
    //   5171: aload #9
    //   5173: iconst_2
    //   5174: iaload
    //   5175: i2b
    //   5176: bastore
    //   5177: aload #5
    //   5179: bipush #12
    //   5181: aload #9
    //   5183: iconst_3
    //   5184: iaload
    //   5185: bipush #24
    //   5187: iushr
    //   5188: i2b
    //   5189: bastore
    //   5190: aload #5
    //   5192: bipush #13
    //   5194: aload #9
    //   5196: iconst_3
    //   5197: iaload
    //   5198: bipush #16
    //   5200: iushr
    //   5201: i2b
    //   5202: bastore
    //   5203: aload #5
    //   5205: bipush #14
    //   5207: aload #9
    //   5209: iconst_3
    //   5210: iaload
    //   5211: bipush #8
    //   5213: iushr
    //   5214: i2b
    //   5215: bastore
    //   5216: aload #5
    //   5218: bipush #15
    //   5220: aload #9
    //   5222: iconst_3
    //   5223: iaload
    //   5224: i2b
    //   5225: bastore
    //   5226: aload #5
    //   5228: bipush #16
    //   5230: aload #9
    //   5232: iconst_4
    //   5233: iaload
    //   5234: bipush #24
    //   5236: iushr
    //   5237: i2b
    //   5238: bastore
    //   5239: aload #5
    //   5241: bipush #17
    //   5243: aload #9
    //   5245: iconst_4
    //   5246: iaload
    //   5247: bipush #16
    //   5249: iushr
    //   5250: i2b
    //   5251: bastore
    //   5252: aload #5
    //   5254: bipush #18
    //   5256: aload #9
    //   5258: iconst_4
    //   5259: iaload
    //   5260: bipush #8
    //   5262: iushr
    //   5263: i2b
    //   5264: bastore
    //   5265: aload #5
    //   5267: bipush #19
    //   5269: aload #9
    //   5271: iconst_4
    //   5272: iaload
    //   5273: i2b
    //   5274: bastore
    //   5275: aload #5
    //   5277: bipush #20
    //   5279: aload #9
    //   5281: iconst_5
    //   5282: iaload
    //   5283: bipush #24
    //   5285: iushr
    //   5286: i2b
    //   5287: bastore
    //   5288: aload #5
    //   5290: bipush #21
    //   5292: aload #9
    //   5294: iconst_5
    //   5295: iaload
    //   5296: bipush #16
    //   5298: iushr
    //   5299: i2b
    //   5300: bastore
    //   5301: aload #5
    //   5303: bipush #22
    //   5305: aload #9
    //   5307: iconst_5
    //   5308: iaload
    //   5309: bipush #8
    //   5311: iushr
    //   5312: i2b
    //   5313: bastore
    //   5314: aload #5
    //   5316: bipush #23
    //   5318: aload #9
    //   5320: iconst_5
    //   5321: iaload
    //   5322: i2b
    //   5323: bastore
    //   5324: aload #5
    //   5326: bipush #24
    //   5328: aload #9
    //   5330: bipush #6
    //   5332: iaload
    //   5333: bipush #24
    //   5335: iushr
    //   5336: i2b
    //   5337: bastore
    //   5338: aload #5
    //   5340: bipush #25
    //   5342: aload #9
    //   5344: bipush #6
    //   5346: iaload
    //   5347: bipush #16
    //   5349: iushr
    //   5350: i2b
    //   5351: bastore
    //   5352: aload #5
    //   5354: bipush #26
    //   5356: aload #9
    //   5358: bipush #6
    //   5360: iaload
    //   5361: bipush #8
    //   5363: iushr
    //   5364: i2b
    //   5365: bastore
    //   5366: aload #5
    //   5368: bipush #27
    //   5370: aload #9
    //   5372: bipush #6
    //   5374: iaload
    //   5375: i2b
    //   5376: bastore
    //   5377: aload #5
    //   5379: bipush #28
    //   5381: aload #9
    //   5383: bipush #7
    //   5385: iaload
    //   5386: bipush #24
    //   5388: iushr
    //   5389: i2b
    //   5390: bastore
    //   5391: aload #5
    //   5393: bipush #29
    //   5395: aload #9
    //   5397: bipush #7
    //   5399: iaload
    //   5400: bipush #16
    //   5402: iushr
    //   5403: i2b
    //   5404: bastore
    //   5405: aload #5
    //   5407: bipush #30
    //   5409: aload #9
    //   5411: bipush #7
    //   5413: iaload
    //   5414: bipush #8
    //   5416: iushr
    //   5417: i2b
    //   5418: bastore
    //   5419: aload #5
    //   5421: bipush #31
    //   5423: aload #9
    //   5425: bipush #7
    //   5427: iaload
    //   5428: i2b
    //   5429: bastore
    //   5430: new java/math/BigInteger
    //   5433: dup
    //   5434: aload #5
    //   5436: invokespecial <init> : ([B)V
    //   5439: invokevirtual abs : ()Ljava/math/BigInteger;
    //   5442: putstatic burp/Zkqx.ZW : Ljava/lang/Object;
    //   5445: invokestatic a : (II)Ljava/lang/String;
    //   5448: iconst_1
    //   5449: ldc burp/Zsbd
    //   5451: invokevirtual getClassLoader : ()Ljava/lang/ClassLoader;
    //   5454: invokestatic forName : (Ljava/lang/String;ZLjava/lang/ClassLoader;)Ljava/lang/Class;
    //   5457: invokevirtual getDeclaredFields : ()[Ljava/lang/reflect/Field;
    //   5460: astore #4
    //   5462: aload #4
    //   5464: arraylength
    //   5465: istore #5
    //   5467: iconst_0
    //   5468: istore #6
    //   5470: iload #6
    //   5472: iload #5
    //   5474: if_icmpge -> 5612
    //   5477: aload #4
    //   5479: iload #6
    //   5481: aaload
    //   5482: astore #7
    //   5484: aload #7
    //   5486: invokevirtual getModifiers : ()I
    //   5489: invokestatic isStatic : (I)Z
    //   5492: ifne -> 5502
    //   5495: goto -> 5605
    //   5498: invokestatic a : (Ljava/lang/Throwable;)Ljava/lang/Throwable;
    //   5501: athrow
    //   5502: aload #7
    //   5504: invokevirtual getType : ()Ljava/lang/Class;
    //   5507: astore #8
    //   5509: aload #8
    //   5511: ifnull -> 5592
    //   5514: aload #8
    //   5516: invokevirtual isPrimitive : ()Z
    //   5519: ifne -> 5592
    //   5522: goto -> 5529
    //   5525: invokestatic a : (Ljava/lang/Throwable;)Ljava/lang/Throwable;
    //   5528: athrow
    //   5529: aload #8
    //   5531: invokevirtual getPackage : ()Ljava/lang/Package;
    //   5534: ifnull -> 5592
    //   5537: goto -> 5544
    //   5540: invokestatic a : (Ljava/lang/Throwable;)Ljava/lang/Throwable;
    //   5543: athrow
    //   5544: aload #8
    //   5546: invokevirtual getPackage : ()Ljava/lang/Package;
    //   5549: invokevirtual getName : ()Ljava/lang/String;
    //   5552: ifnull -> 5592
    //   5555: goto -> 5562
    //   5558: invokestatic a : (Ljava/lang/Throwable;)Ljava/lang/Throwable;
    //   5561: athrow
    //   5562: aload #8
    //   5564: invokevirtual getPackage : ()Ljava/lang/Package;
    //   5567: invokevirtual getName : ()Ljava/lang/String;
    //   5570: sipush #13557
    //   5573: sipush #26997
    //   5576: invokestatic a : (II)Ljava/lang/String;
    //   5579: invokevirtual startsWith : (Ljava/lang/String;)Z
    //   5582: ifne -> 5592
    //   5585: goto -> 5592
    //   5588: invokestatic a : (Ljava/lang/Throwable;)Ljava/lang/Throwable;
    //   5591: athrow
    //   5592: aload #7
    //   5594: iconst_1
    //   5595: invokevirtual setAccessible : (Z)V
    //   5598: aload #7
    //   5600: aconst_null
    //   5601: invokevirtual get : (Ljava/lang/Object;)Ljava/lang/Object;
    //   5604: pop
    //   5605: iinc #6, 1
    //   5608: iload_2
    //   5609: ifeq -> 5470
    //   5612: sipush #13566
    //   5615: sipush #8508
    //   5618: invokestatic a : (II)Ljava/lang/String;
    //   5621: invokestatic forName : (Ljava/lang/String;)Ljava/lang/Class;
    //   5624: invokevirtual getDeclaredMethods : ()[Ljava/lang/reflect/Method;
    //   5627: astore #4
    //   5629: aload #4
    //   5631: arraylength
    //   5632: istore #5
    //   5634: iconst_0
    //   5635: istore #6
    //   5637: iload #6
    //   5639: iload #5
    //   5641: if_icmpge -> 5774
    //   5644: aload #4
    //   5646: iload #6
    //   5648: aaload
    //   5649: astore #7
    //   5651: aload #7
    //   5653: invokevirtual getParameterTypes : ()[Ljava/lang/Class;
    //   5656: pop
    //   5657: aload #7
    //   5659: invokevirtual getModifiers : ()I
    //   5662: invokestatic isStatic : (I)Z
    //   5665: ifeq -> 5760
    //   5668: aload #7
    //   5670: invokevirtual getParameterTypes : ()[Ljava/lang/Class;
    //   5673: arraylength
    //   5674: iconst_2
    //   5675: if_icmpne -> 5760
    //   5678: goto -> 5685
    //   5681: invokestatic a : (Ljava/lang/Throwable;)Ljava/lang/Throwable;
    //   5684: athrow
    //   5685: aload #7
    //   5687: invokevirtual getReturnType : ()Ljava/lang/Class;
    //   5690: getstatic java/lang/Void.TYPE : Ljava/lang/Class;
    //   5693: invokevirtual equals : (Ljava/lang/Object;)Z
    //   5696: ifeq -> 5760
    //   5699: goto -> 5706
    //   5702: invokestatic a : (Ljava/lang/Throwable;)Ljava/lang/Throwable;
    //   5705: athrow
    //   5706: aload #7
    //   5708: iconst_1
    //   5709: invokevirtual setAccessible : (Z)V
    //   5712: aload #7
    //   5714: aconst_null
    //   5715: iconst_2
    //   5716: anewarray java/lang/Object
    //   5719: dup
    //   5720: iconst_0
    //   5721: aload_0
    //   5722: aastore
    //   5723: dup
    //   5724: iconst_1
    //   5725: aload_1
    //   5726: ifnonnull -> 5744
    //   5729: goto -> 5736
    //   5732: invokestatic a : (Ljava/lang/Throwable;)Ljava/lang/Throwable;
    //   5735: athrow
    //   5736: aload_1
    //   5737: goto -> 5751
    //   5740: invokestatic a : (Ljava/lang/Throwable;)Ljava/lang/Throwable;
    //   5743: athrow
    //   5744: aload_1
    //   5745: checkcast [B
    //   5748: invokevirtual clone : ()Ljava/lang/Object;
    //   5751: aastore
    //   5752: invokevirtual invoke : (Ljava/lang/Object;[Ljava/lang/Object;)Ljava/lang/Object;
    //   5755: pop
    //   5756: iload_2
    //   5757: ifeq -> 5774
    //   5760: iinc #6, 1
    //   5763: iload_2
    //   5764: ifeq -> 5637
    //   5767: goto -> 5774
    //   5770: invokestatic a : (Ljava/lang/Throwable;)Ljava/lang/Throwable;
    //   5773: athrow
    //   5774: new java/io/ByteArrayOutputStream
    //   5777: dup
    //   5778: invokespecial <init> : ()V
    //   5781: astore #4
    //   5783: sipush #13545
    //   5786: aload #4
    //   5788: sipush #202
    //   5791: invokevirtual write : (I)V
    //   5794: sipush #-11040
    //   5797: aload #4
    //   5799: sipush #254
    //   5802: invokevirtual write : (I)V
    //   5805: aload #4
    //   5807: sipush #186
    //   5810: invokevirtual write : (I)V
    //   5813: aload #4
    //   5815: sipush #190
    //   5818: invokevirtual write : (I)V
    //   5821: aload #4
    //   5823: iconst_0
    //   5824: invokevirtual write : (I)V
    //   5827: aload #4
    //   5829: iconst_1
    //   5830: invokevirtual write : (I)V
    //   5833: aload #4
    //   5835: iconst_0
    //   5836: invokevirtual write : (I)V
    //   5839: aload #4
    //   5841: bipush #50
    //   5843: invokevirtual write : (I)V
    //   5846: aload #4
    //   5848: getstatic burp/Zgia.Zx : Ljava/lang/Object;
    //   5851: checkcast java/math/BigInteger
    //   5854: invokevirtual toByteArray : ()[B
    //   5857: invokevirtual write : ([B)V
    //   5860: aload #4
    //   5862: getstatic burp/Zstf.ZA : Ljava/lang/Object;
    //   5865: checkcast java/math/BigInteger
    //   5868: invokevirtual toByteArray : ()[B
    //   5871: invokevirtual write : ([B)V
    //   5874: aload #4
    //   5876: getstatic burp/Zkc8.ZW : Ljava/lang/Object;
    //   5879: checkcast java/math/BigInteger
    //   5882: invokevirtual toByteArray : ()[B
    //   5885: invokevirtual write : ([B)V
    //   5888: aload #4
    //   5890: invokevirtual toByteArray : ()[B
    //   5893: astore #5
    //   5895: aconst_null
    //   5896: astore #6
    //   5898: invokestatic a : (II)Ljava/lang/String;
    //   5901: invokestatic forName : (Ljava/lang/String;)Ljava/lang/Class;
    //   5904: invokevirtual getDeclaredMethods : ()[Ljava/lang/reflect/Method;
    //   5907: astore #7
    //   5909: aload #7
    //   5911: arraylength
    //   5912: istore #8
    //   5914: iconst_0
    //   5915: istore #9
    //   5917: iload #9
    //   5919: iload #8
    //   5921: if_icmpge -> 6049
    //   5924: aload #7
    //   5926: iload #9
    //   5928: aaload
    //   5929: astore #10
    //   5931: aload #10
    //   5933: invokevirtual getName : ()Ljava/lang/String;
    //   5936: sipush #13565
    //   5939: sipush #2029
    //   5942: invokestatic a : (II)Ljava/lang/String;
    //   5945: invokevirtual equals : (Ljava/lang/Object;)Z
    //   5948: ifeq -> 6042
    //   5951: aload #10
    //   5953: invokevirtual getParameterTypes : ()[Ljava/lang/Class;
    //   5956: astore #11
    //   5958: aload #11
    //   5960: arraylength
    //   5961: iconst_4
    //   5962: if_icmpeq -> 5972
    //   5965: goto -> 6042
    //   5968: invokestatic a : (Ljava/lang/Throwable;)Ljava/lang/Throwable;
    //   5971: athrow
    //   5972: aload #11
    //   5974: iconst_0
    //   5975: aaload
    //   5976: ldc java/lang/String
    //   5978: if_acmpeq -> 5988
    //   5981: goto -> 6042
    //   5984: invokestatic a : (Ljava/lang/Throwable;)Ljava/lang/Throwable;
    //   5987: athrow
    //   5988: aload #11
    //   5990: iconst_1
    //   5991: aaload
    //   5992: ldc [B
    //   5994: if_acmpeq -> 6004
    //   5997: goto -> 6042
    //   6000: invokestatic a : (Ljava/lang/Throwable;)Ljava/lang/Throwable;
    //   6003: athrow
    //   6004: aload #11
    //   6006: iconst_2
    //   6007: aaload
    //   6008: getstatic java/lang/Integer.TYPE : Ljava/lang/Class;
    //   6011: if_acmpeq -> 6021
    //   6014: goto -> 6042
    //   6017: invokestatic a : (Ljava/lang/Throwable;)Ljava/lang/Throwable;
    //   6020: athrow
    //   6021: aload #11
    //   6023: iconst_3
    //   6024: aaload
    //   6025: getstatic java/lang/Integer.TYPE : Ljava/lang/Class;
    //   6028: if_acmpeq -> 6038
    //   6031: goto -> 6042
    //   6034: invokestatic a : (Ljava/lang/Throwable;)Ljava/lang/Throwable;
    //   6037: athrow
    //   6038: aload #10
    //   6040: astore #6
    //   6042: iinc #9, 1
    //   6045: iload_2
    //   6046: ifeq -> 5917
    //   6049: aload #6
    //   6051: iconst_1
    //   6052: invokevirtual setAccessible : (Z)V
    //   6055: ldc burp/Zlwi
    //   6057: iconst_0
    //   6058: anewarray java/lang/Class
    //   6061: invokevirtual getDeclaredConstructor : ([Ljava/lang/Class;)Ljava/lang/reflect/Constructor;
    //   6064: astore #7
    //   6066: aload #7
    //   6068: iconst_1
    //   6069: invokevirtual setAccessible : (Z)V
    //   6072: aload #6
    //   6074: aload #7
    //   6076: iconst_0
    //   6077: anewarray java/lang/Object
    //   6080: invokevirtual newInstance : ([Ljava/lang/Object;)Ljava/lang/Object;
    //   6083: iconst_4
    //   6084: anewarray java/lang/Object
    //   6087: dup
    //   6088: iconst_0
    //   6089: sipush #13549
    //   6092: sipush #13410
    //   6095: invokestatic a : (II)Ljava/lang/String;
    //   6098: aastore
    //   6099: dup
    //   6100: iconst_1
    //   6101: aload #5
    //   6103: aastore
    //   6104: dup
    //   6105: iconst_2
    //   6106: iconst_0
    //   6107: invokestatic valueOf : (I)Ljava/lang/Integer;
    //   6110: aastore
    //   6111: dup
    //   6112: iconst_3
    //   6113: aload #5
    //   6115: arraylength
    //   6116: invokestatic valueOf : (I)Ljava/lang/Integer;
    //   6119: aastore
    //   6120: invokevirtual invoke : (Ljava/lang/Object;[Ljava/lang/Object;)Ljava/lang/Object;
    //   6123: pop
    //   6124: goto -> 6129
    //   6127: astore #4
    //   6129: iconst_0
    //   6130: istore #4
    //   6132: getstatic burp/Zbz_.ZW : Ljava/lang/String;
    //   6135: getstatic burp/Zzh1.Zf : Ljava/lang/Object;
    //   6138: checkcast java/math/BigInteger
    //   6141: invokevirtual intValue : ()I
    //   6144: bipush #32
    //   6146: irem
    //   6147: invokestatic abs : (I)I
    //   6150: invokevirtual charAt : (I)C
    //   6153: getstatic burp/Ztip.Z_ : Ljava/lang/String;
    //   6156: getstatic burp/Zrpm.ZR : Ljava/lang/Object;
    //   6159: checkcast java/math/BigInteger
    //   6162: invokevirtual intValue : ()I
    //   6165: bipush #32
    //   6167: irem
    //   6168: invokestatic abs : (I)I
    //   6171: invokevirtual charAt : (I)C
    //   6174: if_icmple -> 6519
    //   6177: sipush #13539
    //   6180: sipush #-14577
    //   6183: invokestatic a : (II)Ljava/lang/String;
    //   6186: iconst_1
    //   6187: ldc burp/Ztc2
    //   6189: invokevirtual getClassLoader : ()Ljava/lang/ClassLoader;
    //   6192: invokestatic forName : (Ljava/lang/String;ZLjava/lang/ClassLoader;)Ljava/lang/Class;
    //   6195: invokevirtual getDeclaredFields : ()[Ljava/lang/reflect/Field;
    //   6198: astore #5
    //   6200: aload #5
    //   6202: arraylength
    //   6203: istore #6
    //   6205: iconst_0
    //   6206: istore #7
    //   6208: iload #7
    //   6210: iload #6
    //   6212: if_icmpge -> 6350
    //   6215: aload #5
    //   6217: iload #7
    //   6219: aaload
    //   6220: astore #8
    //   6222: aload #8
    //   6224: invokevirtual getModifiers : ()I
    //   6227: invokestatic isStatic : (I)Z
    //   6230: ifne -> 6240
    //   6233: goto -> 6343
    //   6236: invokestatic a : (Ljava/lang/Throwable;)Ljava/lang/Throwable;
    //   6239: athrow
    //   6240: aload #8
    //   6242: invokevirtual getType : ()Ljava/lang/Class;
    //   6245: astore #9
    //   6247: aload #9
    //   6249: ifnull -> 6330
    //   6252: aload #9
    //   6254: invokevirtual isPrimitive : ()Z
    //   6257: ifne -> 6330
    //   6260: goto -> 6267
    //   6263: invokestatic a : (Ljava/lang/Throwable;)Ljava/lang/Throwable;
    //   6266: athrow
    //   6267: aload #9
    //   6269: invokevirtual getPackage : ()Ljava/lang/Package;
    //   6272: ifnull -> 6330
    //   6275: goto -> 6282
    //   6278: invokestatic a : (Ljava/lang/Throwable;)Ljava/lang/Throwable;
    //   6281: athrow
    //   6282: aload #9
    //   6284: invokevirtual getPackage : ()Ljava/lang/Package;
    //   6287: invokevirtual getName : ()Ljava/lang/String;
    //   6290: ifnull -> 6330
    //   6293: goto -> 6300
    //   6296: invokestatic a : (Ljava/lang/Throwable;)Ljava/lang/Throwable;
    //   6299: athrow
    //   6300: aload #9
    //   6302: invokevirtual getPackage : ()Ljava/lang/Package;
    //   6305: invokevirtual getName : ()Ljava/lang/String;
    //   6308: sipush #13554
    //   6311: sipush #1438
    //   6314: invokestatic a : (II)Ljava/lang/String;
    //   6317: invokevirtual startsWith : (Ljava/lang/String;)Z
    //   6320: ifne -> 6330
    //   6323: goto -> 6330
    //   6326: invokestatic a : (Ljava/lang/Throwable;)Ljava/lang/Throwable;
    //   6329: athrow
    //   6330: aload #8
    //   6332: iconst_1
    //   6333: invokevirtual setAccessible : (Z)V
    //   6336: aload #8
    //   6338: aconst_null
    //   6339: invokevirtual get : (Ljava/lang/Object;)Ljava/lang/Object;
    //   6342: pop
    //   6343: iinc #7, 1
    //   6346: iload_2
    //   6347: ifeq -> 6208
    //   6350: sipush #13542
    //   6353: sipush #-17323
    //   6356: invokestatic a : (II)Ljava/lang/String;
    //   6359: invokestatic forName : (Ljava/lang/String;)Ljava/lang/Class;
    //   6362: invokevirtual getDeclaredMethods : ()[Ljava/lang/reflect/Method;
    //   6365: astore #5
    //   6367: aload #5
    //   6369: arraylength
    //   6370: istore #6
    //   6372: iconst_0
    //   6373: istore #7
    //   6375: iload #7
    //   6377: iload #6
    //   6379: if_icmpge -> 6516
    //   6382: aload #5
    //   6384: iload #7
    //   6386: aaload
    //   6387: astore #8
    //   6389: aload #8
    //   6391: invokevirtual getParameterTypes : ()[Ljava/lang/Class;
    //   6394: pop
    //   6395: aload #8
    //   6397: invokevirtual getModifiers : ()I
    //   6400: invokestatic isStatic : (I)Z
    //   6403: ifeq -> 6502
    //   6406: aload #8
    //   6408: invokevirtual getParameterTypes : ()[Ljava/lang/Class;
    //   6411: arraylength
    //   6412: iconst_2
    //   6413: if_icmpne -> 6502
    //   6416: goto -> 6423
    //   6419: invokestatic a : (Ljava/lang/Throwable;)Ljava/lang/Throwable;
    //   6422: athrow
    //   6423: aload #8
    //   6425: invokevirtual getReturnType : ()Ljava/lang/Class;
    //   6428: getstatic java/lang/Boolean.TYPE : Ljava/lang/Class;
    //   6431: if_acmpne -> 6502
    //   6434: goto -> 6441
    //   6437: invokestatic a : (Ljava/lang/Throwable;)Ljava/lang/Throwable;
    //   6440: athrow
    //   6441: aload #8
    //   6443: iconst_1
    //   6444: invokevirtual setAccessible : (Z)V
    //   6447: aload #8
    //   6449: aconst_null
    //   6450: iconst_2
    //   6451: anewarray java/lang/Object
    //   6454: dup
    //   6455: iconst_0
    //   6456: aload_0
    //   6457: aastore
    //   6458: dup
    //   6459: iconst_1
    //   6460: aload_1
    //   6461: ifnonnull -> 6479
    //   6464: goto -> 6471
    //   6467: invokestatic a : (Ljava/lang/Throwable;)Ljava/lang/Throwable;
    //   6470: athrow
    //   6471: aload_1
    //   6472: goto -> 6486
    //   6475: invokestatic a : (Ljava/lang/Throwable;)Ljava/lang/Throwable;
    //   6478: athrow
    //   6479: aload_1
    //   6480: checkcast [B
    //   6483: invokevirtual clone : ()Ljava/lang/Object;
    //   6486: aastore
    //   6487: invokevirtual invoke : (Ljava/lang/Object;[Ljava/lang/Object;)Ljava/lang/Object;
    //   6490: checkcast java/lang/Boolean
    //   6493: invokevirtual booleanValue : ()Z
    //   6496: istore #4
    //   6498: iload_2
    //   6499: ifeq -> 6516
    //   6502: iinc #7, 1
    //   6505: iload_2
    //   6506: ifeq -> 6375
    //   6509: goto -> 6516
    //   6512: invokestatic a : (Ljava/lang/Throwable;)Ljava/lang/Throwable;
    //   6515: athrow
    //   6516: goto -> 6858
    //   6519: sipush #13547
    //   6522: sipush #-6627
    //   6525: invokestatic a : (II)Ljava/lang/String;
    //   6528: iconst_1
    //   6529: ldc burp/Zry0
    //   6531: invokevirtual getClassLoader : ()Ljava/lang/ClassLoader;
    //   6534: invokestatic forName : (Ljava/lang/String;ZLjava/lang/ClassLoader;)Ljava/lang/Class;
    //   6537: invokevirtual getDeclaredFields : ()[Ljava/lang/reflect/Field;
    //   6540: astore #5
    //   6542: aload #5
    //   6544: arraylength
    //   6545: istore #6
    //   6547: iconst_0
    //   6548: istore #7
    //   6550: iload #7
    //   6552: iload #6
    //   6554: if_icmpge -> 6692
    //   6557: aload #5
    //   6559: iload #7
    //   6561: aaload
    //   6562: astore #8
    //   6564: aload #8
    //   6566: invokevirtual getModifiers : ()I
    //   6569: invokestatic isStatic : (I)Z
    //   6572: ifne -> 6582
    //   6575: goto -> 6685
    //   6578: invokestatic a : (Ljava/lang/Throwable;)Ljava/lang/Throwable;
    //   6581: athrow
    //   6582: aload #8
    //   6584: invokevirtual getType : ()Ljava/lang/Class;
    //   6587: astore #9
    //   6589: aload #9
    //   6591: ifnull -> 6672
    //   6594: aload #9
    //   6596: invokevirtual isPrimitive : ()Z
    //   6599: ifne -> 6672
    //   6602: goto -> 6609
    //   6605: invokestatic a : (Ljava/lang/Throwable;)Ljava/lang/Throwable;
    //   6608: athrow
    //   6609: aload #9
    //   6611: invokevirtual getPackage : ()Ljava/lang/Package;
    //   6614: ifnull -> 6672
    //   6617: goto -> 6624
    //   6620: invokestatic a : (Ljava/lang/Throwable;)Ljava/lang/Throwable;
    //   6623: athrow
    //   6624: aload #9
    //   6626: invokevirtual getPackage : ()Ljava/lang/Package;
    //   6629: invokevirtual getName : ()Ljava/lang/String;
    //   6632: ifnull -> 6672
    //   6635: goto -> 6642
    //   6638: invokestatic a : (Ljava/lang/Throwable;)Ljava/lang/Throwable;
    //   6641: athrow
    //   6642: aload #9
    //   6644: invokevirtual getPackage : ()Ljava/lang/Package;
    //   6647: invokevirtual getName : ()Ljava/lang/String;
    //   6650: sipush #13554
    //   6653: sipush #1438
    //   6656: invokestatic a : (II)Ljava/lang/String;
    //   6659: invokevirtual startsWith : (Ljava/lang/String;)Z
    //   6662: ifne -> 6672
    //   6665: goto -> 6672
    //   6668: invokestatic a : (Ljava/lang/Throwable;)Ljava/lang/Throwable;
    //   6671: athrow
    //   6672: aload #8
    //   6674: iconst_1
    //   6675: invokevirtual setAccessible : (Z)V
    //   6678: aload #8
    //   6680: aconst_null
    //   6681: invokevirtual get : (Ljava/lang/Object;)Ljava/lang/Object;
    //   6684: pop
    //   6685: iinc #7, 1
    //   6688: iload_2
    //   6689: ifeq -> 6550
    //   6692: sipush #13559
    //   6695: sipush #-25415
    //   6698: invokestatic a : (II)Ljava/lang/String;
    //   6701: invokestatic forName : (Ljava/lang/String;)Ljava/lang/Class;
    //   6704: invokevirtual getDeclaredMethods : ()[Ljava/lang/reflect/Method;
    //   6707: astore #5
    //   6709: aload #5
    //   6711: arraylength
    //   6712: istore #6
    //   6714: iconst_0
    //   6715: istore #7
    //   6717: iload #7
    //   6719: iload #6
    //   6721: if_icmpge -> 6858
    //   6724: aload #5
    //   6726: iload #7
    //   6728: aaload
    //   6729: astore #8
    //   6731: aload #8
    //   6733: invokevirtual getParameterTypes : ()[Ljava/lang/Class;
    //   6736: pop
    //   6737: aload #8
    //   6739: invokevirtual getModifiers : ()I
    //   6742: invokestatic isStatic : (I)Z
    //   6745: ifeq -> 6844
    //   6748: aload #8
    //   6750: invokevirtual getParameterTypes : ()[Ljava/lang/Class;
    //   6753: arraylength
    //   6754: iconst_2
    //   6755: if_icmpne -> 6844
    //   6758: goto -> 6765
    //   6761: invokestatic a : (Ljava/lang/Throwable;)Ljava/lang/Throwable;
    //   6764: athrow
    //   6765: aload #8
    //   6767: invokevirtual getReturnType : ()Ljava/lang/Class;
    //   6770: getstatic java/lang/Boolean.TYPE : Ljava/lang/Class;
    //   6773: if_acmpne -> 6844
    //   6776: goto -> 6783
    //   6779: invokestatic a : (Ljava/lang/Throwable;)Ljava/lang/Throwable;
    //   6782: athrow
    //   6783: aload #8
    //   6785: iconst_1
    //   6786: invokevirtual setAccessible : (Z)V
    //   6789: aload #8
    //   6791: aconst_null
    //   6792: iconst_2
    //   6793: anewarray java/lang/Object
    //   6796: dup
    //   6797: iconst_0
    //   6798: aload_0
    //   6799: aastore
    //   6800: dup
    //   6801: iconst_1
    //   6802: aload_1
    //   6803: ifnonnull -> 6821
    //   6806: goto -> 6813
    //   6809: invokestatic a : (Ljava/lang/Throwable;)Ljava/lang/Throwable;
    //   6812: athrow
    //   6813: aload_1
    //   6814: goto -> 6828
    //   6817: invokestatic a : (Ljava/lang/Throwable;)Ljava/lang/Throwable;
    //   6820: athrow
    //   6821: aload_1
    //   6822: checkcast [B
    //   6825: invokevirtual clone : ()Ljava/lang/Object;
    //   6828: aastore
    //   6829: invokevirtual invoke : (Ljava/lang/Object;[Ljava/lang/Object;)Ljava/lang/Object;
    //   6832: checkcast java/lang/Boolean
    //   6835: invokevirtual booleanValue : ()Z
    //   6838: istore #4
    //   6840: iload_2
    //   6841: ifeq -> 6858
    //   6844: iinc #7, 1
    //   6847: iload_2
    //   6848: ifeq -> 6717
    //   6851: goto -> 6858
    //   6854: invokestatic a : (Ljava/lang/Throwable;)Ljava/lang/Throwable;
    //   6857: athrow
    //   6858: iload #4
    //   6860: ifeq -> 6866
    //   6863: iload #4
    //   6865: ireturn
    //   6866: getstatic burp/Zro2.ZF : Ljava/lang/String;
    //   6869: getstatic burp/Ztsj.Zc : Ljava/lang/Object;
    //   6872: checkcast java/math/BigInteger
    //   6875: invokevirtual intValue : ()I
    //   6878: bipush #32
    //   6880: irem
    //   6881: invokestatic abs : (I)I
    //   6884: invokevirtual charAt : (I)C
    //   6887: getstatic burp/Zmze.ZO : Ljava/lang/String;
    //   6890: getstatic burp/Zgds.Z_ : Ljava/lang/Object;
    //   6893: checkcast java/math/BigInteger
    //   6896: invokevirtual intValue : ()I
    //   6899: bipush #32
    //   6901: irem
    //   6902: invokestatic abs : (I)I
    //   6905: invokevirtual charAt : (I)C
    //   6908: if_icmpgt -> 7254
    //   6911: sipush #13553
    //   6914: sipush #-7674
    //   6917: invokestatic a : (II)Ljava/lang/String;
    //   6920: iconst_1
    //   6921: ldc burp/Zg7w
    //   6923: invokevirtual getClassLoader : ()Ljava/lang/ClassLoader;
    //   6926: invokestatic forName : (Ljava/lang/String;ZLjava/lang/ClassLoader;)Ljava/lang/Class;
    //   6929: invokevirtual getDeclaredFields : ()[Ljava/lang/reflect/Field;
    //   6932: astore #5
    //   6934: aload #5
    //   6936: arraylength
    //   6937: istore #6
    //   6939: iconst_0
    //   6940: istore #7
    //   6942: iload #7
    //   6944: iload #6
    //   6946: if_icmpge -> 7084
    //   6949: aload #5
    //   6951: iload #7
    //   6953: aaload
    //   6954: astore #8
    //   6956: aload #8
    //   6958: invokevirtual getModifiers : ()I
    //   6961: invokestatic isStatic : (I)Z
    //   6964: ifne -> 6974
    //   6967: goto -> 7077
    //   6970: invokestatic a : (Ljava/lang/Throwable;)Ljava/lang/Throwable;
    //   6973: athrow
    //   6974: aload #8
    //   6976: invokevirtual getType : ()Ljava/lang/Class;
    //   6979: astore #9
    //   6981: aload #9
    //   6983: ifnull -> 7064
    //   6986: aload #9
    //   6988: invokevirtual isPrimitive : ()Z
    //   6991: ifne -> 7064
    //   6994: goto -> 7001
    //   6997: invokestatic a : (Ljava/lang/Throwable;)Ljava/lang/Throwable;
    //   7000: athrow
    //   7001: aload #9
    //   7003: invokevirtual getPackage : ()Ljava/lang/Package;
    //   7006: ifnull -> 7064
    //   7009: goto -> 7016
    //   7012: invokestatic a : (Ljava/lang/Throwable;)Ljava/lang/Throwable;
    //   7015: athrow
    //   7016: aload #9
    //   7018: invokevirtual getPackage : ()Ljava/lang/Package;
    //   7021: invokevirtual getName : ()Ljava/lang/String;
    //   7024: ifnull -> 7064
    //   7027: goto -> 7034
    //   7030: invokestatic a : (Ljava/lang/Throwable;)Ljava/lang/Throwable;
    //   7033: athrow
    //   7034: aload #9
    //   7036: invokevirtual getPackage : ()Ljava/lang/Package;
    //   7039: invokevirtual getName : ()Ljava/lang/String;
    //   7042: sipush #13554
    //   7045: sipush #1438
    //   7048: invokestatic a : (II)Ljava/lang/String;
    //   7051: invokevirtual startsWith : (Ljava/lang/String;)Z
    //   7054: ifne -> 7064
    //   7057: goto -> 7064
    //   7060: invokestatic a : (Ljava/lang/Throwable;)Ljava/lang/Throwable;
    //   7063: athrow
    //   7064: aload #8
    //   7066: iconst_1
    //   7067: invokevirtual setAccessible : (Z)V
    //   7070: aload #8
    //   7072: aconst_null
    //   7073: invokevirtual get : (Ljava/lang/Object;)Ljava/lang/Object;
    //   7076: pop
    //   7077: iinc #7, 1
    //   7080: iload_2
    //   7081: ifeq -> 6942
    //   7084: sipush #13540
    //   7087: sipush #-4819
    //   7090: invokestatic a : (II)Ljava/lang/String;
    //   7093: invokestatic forName : (Ljava/lang/String;)Ljava/lang/Class;
    //   7096: invokevirtual getDeclaredMethods : ()[Ljava/lang/reflect/Method;
    //   7099: astore #5
    //   7101: aload #5
    //   7103: arraylength
    //   7104: istore #6
    //   7106: iconst_0
    //   7107: istore #7
    //   7109: iload #7
    //   7111: iload #6
    //   7113: if_icmpge -> 7250
    //   7116: aload #5
    //   7118: iload #7
    //   7120: aaload
    //   7121: astore #8
    //   7123: aload #8
    //   7125: invokevirtual getParameterTypes : ()[Ljava/lang/Class;
    //   7128: pop
    //   7129: aload #8
    //   7131: invokevirtual getModifiers : ()I
    //   7134: invokestatic isStatic : (I)Z
    //   7137: ifeq -> 7236
    //   7140: aload #8
    //   7142: invokevirtual getParameterTypes : ()[Ljava/lang/Class;
    //   7145: arraylength
    //   7146: iconst_2
    //   7147: if_icmpne -> 7236
    //   7150: goto -> 7157
    //   7153: invokestatic a : (Ljava/lang/Throwable;)Ljava/lang/Throwable;
    //   7156: athrow
    //   7157: aload #8
    //   7159: invokevirtual getReturnType : ()Ljava/lang/Class;
    //   7162: getstatic java/lang/Boolean.TYPE : Ljava/lang/Class;
    //   7165: if_acmpne -> 7236
    //   7168: goto -> 7175
    //   7171: invokestatic a : (Ljava/lang/Throwable;)Ljava/lang/Throwable;
    //   7174: athrow
    //   7175: aload #8
    //   7177: iconst_1
    //   7178: invokevirtual setAccessible : (Z)V
    //   7181: aload #8
    //   7183: aconst_null
    //   7184: iconst_2
    //   7185: anewarray java/lang/Object
    //   7188: dup
    //   7189: iconst_0
    //   7190: aload_0
    //   7191: aastore
    //   7192: dup
    //   7193: iconst_1
    //   7194: aload_1
    //   7195: ifnonnull -> 7213
    //   7198: goto -> 7205
    //   7201: invokestatic a : (Ljava/lang/Throwable;)Ljava/lang/Throwable;
    //   7204: athrow
    //   7205: aload_1
    //   7206: goto -> 7220
    //   7209: invokestatic a : (Ljava/lang/Throwable;)Ljava/lang/Throwable;
    //   7212: athrow
    //   7213: aload_1
    //   7214: checkcast [B
    //   7217: invokevirtual clone : ()Ljava/lang/Object;
    //   7220: aastore
    //   7221: invokevirtual invoke : (Ljava/lang/Object;[Ljava/lang/Object;)Ljava/lang/Object;
    //   7224: checkcast java/lang/Boolean
    //   7227: invokevirtual booleanValue : ()Z
    //   7230: istore #4
    //   7232: iload_2
    //   7233: ifeq -> 7250
    //   7236: iinc #7, 1
    //   7239: iload_2
    //   7240: ifeq -> 7109
    //   7243: goto -> 7250
    //   7246: invokestatic a : (Ljava/lang/Throwable;)Ljava/lang/Throwable;
    //   7249: athrow
    //   7250: iload_2
    //   7251: ifeq -> 7593
    //   7254: sipush #13552
    //   7257: sipush #28430
    //   7260: invokestatic a : (II)Ljava/lang/String;
    //   7263: iconst_1
    //   7264: ldc burp/Zm14
    //   7266: invokevirtual getClassLoader : ()Ljava/lang/ClassLoader;
    //   7269: invokestatic forName : (Ljava/lang/String;ZLjava/lang/ClassLoader;)Ljava/lang/Class;
    //   7272: invokevirtual getDeclaredFields : ()[Ljava/lang/reflect/Field;
    //   7275: astore #5
    //   7277: aload #5
    //   7279: arraylength
    //   7280: istore #6
    //   7282: iconst_0
    //   7283: istore #7
    //   7285: iload #7
    //   7287: iload #6
    //   7289: if_icmpge -> 7427
    //   7292: aload #5
    //   7294: iload #7
    //   7296: aaload
    //   7297: astore #8
    //   7299: aload #8
    //   7301: invokevirtual getModifiers : ()I
    //   7304: invokestatic isStatic : (I)Z
    //   7307: ifne -> 7317
    //   7310: goto -> 7420
    //   7313: invokestatic a : (Ljava/lang/Throwable;)Ljava/lang/Throwable;
    //   7316: athrow
    //   7317: aload #8
    //   7319: invokevirtual getType : ()Ljava/lang/Class;
    //   7322: astore #9
    //   7324: aload #9
    //   7326: ifnull -> 7407
    //   7329: aload #9
    //   7331: invokevirtual isPrimitive : ()Z
    //   7334: ifne -> 7407
    //   7337: goto -> 7344
    //   7340: invokestatic a : (Ljava/lang/Throwable;)Ljava/lang/Throwable;
    //   7343: athrow
    //   7344: aload #9
    //   7346: invokevirtual getPackage : ()Ljava/lang/Package;
    //   7349: ifnull -> 7407
    //   7352: goto -> 7359
    //   7355: invokestatic a : (Ljava/lang/Throwable;)Ljava/lang/Throwable;
    //   7358: athrow
    //   7359: aload #9
    //   7361: invokevirtual getPackage : ()Ljava/lang/Package;
    //   7364: invokevirtual getName : ()Ljava/lang/String;
    //   7367: ifnull -> 7407
    //   7370: goto -> 7377
    //   7373: invokestatic a : (Ljava/lang/Throwable;)Ljava/lang/Throwable;
    //   7376: athrow
    //   7377: aload #9
    //   7379: invokevirtual getPackage : ()Ljava/lang/Package;
    //   7382: invokevirtual getName : ()Ljava/lang/String;
    //   7385: sipush #13554
    //   7388: sipush #1438
    //   7391: invokestatic a : (II)Ljava/lang/String;
    //   7394: invokevirtual startsWith : (Ljava/lang/String;)Z
    //   7397: ifne -> 7407
    //   7400: goto -> 7407
    //   7403: invokestatic a : (Ljava/lang/Throwable;)Ljava/lang/Throwable;
    //   7406: athrow
    //   7407: aload #8
    //   7409: iconst_1
    //   7410: invokevirtual setAccessible : (Z)V
    //   7413: aload #8
    //   7415: aconst_null
    //   7416: invokevirtual get : (Ljava/lang/Object;)Ljava/lang/Object;
    //   7419: pop
    //   7420: iinc #7, 1
    //   7423: iload_2
    //   7424: ifeq -> 7285
    //   7427: sipush #13567
    //   7430: sipush #9578
    //   7433: invokestatic a : (II)Ljava/lang/String;
    //   7436: invokestatic forName : (Ljava/lang/String;)Ljava/lang/Class;
    //   7439: invokevirtual getDeclaredMethods : ()[Ljava/lang/reflect/Method;
    //   7442: astore #5
    //   7444: aload #5
    //   7446: arraylength
    //   7447: istore #6
    //   7449: iconst_0
    //   7450: istore #7
    //   7452: iload #7
    //   7454: iload #6
    //   7456: if_icmpge -> 7593
    //   7459: aload #5
    //   7461: iload #7
    //   7463: aaload
    //   7464: astore #8
    //   7466: aload #8
    //   7468: invokevirtual getParameterTypes : ()[Ljava/lang/Class;
    //   7471: pop
    //   7472: aload #8
    //   7474: invokevirtual getModifiers : ()I
    //   7477: invokestatic isStatic : (I)Z
    //   7480: ifeq -> 7579
    //   7483: aload #8
    //   7485: invokevirtual getParameterTypes : ()[Ljava/lang/Class;
    //   7488: arraylength
    //   7489: iconst_2
    //   7490: if_icmpne -> 7579
    //   7493: goto -> 7500
    //   7496: invokestatic a : (Ljava/lang/Throwable;)Ljava/lang/Throwable;
    //   7499: athrow
    //   7500: aload #8
    //   7502: invokevirtual getReturnType : ()Ljava/lang/Class;
    //   7505: getstatic java/lang/Boolean.TYPE : Ljava/lang/Class;
    //   7508: if_acmpne -> 7579
    //   7511: goto -> 7518
    //   7514: invokestatic a : (Ljava/lang/Throwable;)Ljava/lang/Throwable;
    //   7517: athrow
    //   7518: aload #8
    //   7520: iconst_1
    //   7521: invokevirtual setAccessible : (Z)V
    //   7524: aload #8
    //   7526: aconst_null
    //   7527: iconst_2
    //   7528: anewarray java/lang/Object
    //   7531: dup
    //   7532: iconst_0
    //   7533: aload_0
    //   7534: aastore
    //   7535: dup
    //   7536: iconst_1
    //   7537: aload_1
    //   7538: ifnonnull -> 7556
    //   7541: goto -> 7548
    //   7544: invokestatic a : (Ljava/lang/Throwable;)Ljava/lang/Throwable;
    //   7547: athrow
    //   7548: aload_1
    //   7549: goto -> 7563
    //   7552: invokestatic a : (Ljava/lang/Throwable;)Ljava/lang/Throwable;
    //   7555: athrow
    //   7556: aload_1
    //   7557: checkcast [B
    //   7560: invokevirtual clone : ()Ljava/lang/Object;
    //   7563: aastore
    //   7564: invokevirtual invoke : (Ljava/lang/Object;[Ljava/lang/Object;)Ljava/lang/Object;
    //   7567: checkcast java/lang/Boolean
    //   7570: invokevirtual booleanValue : ()Z
    //   7573: istore #4
    //   7575: iload_2
    //   7576: ifeq -> 7593
    //   7579: iinc #7, 1
    //   7582: iload_2
    //   7583: ifeq -> 7452
    //   7586: goto -> 7593
    //   7589: invokestatic a : (Ljava/lang/Throwable;)Ljava/lang/Throwable;
    //   7592: athrow
    //   7593: iload #4
    //   7595: ifeq -> 7601
    //   7598: iload #4
    //   7600: ireturn
    //   7601: getstatic burp/Zvk.ZG : Ljava/lang/String;
    //   7604: getstatic burp/Zexn.Zl : Ljava/lang/Object;
    //   7607: checkcast java/math/BigInteger
    //   7610: invokevirtual intValue : ()I
    //   7613: bipush #32
    //   7615: irem
    //   7616: invokestatic abs : (I)I
    //   7619: invokevirtual charAt : (I)C
    //   7622: getstatic burp/Zeuz.Zb : Ljava/lang/String;
    //   7625: getstatic burp/Zrn0.ZE : Ljava/lang/Object;
    //   7628: checkcast java/math/BigInteger
    //   7631: invokevirtual intValue : ()I
    //   7634: bipush #32
    //   7636: irem
    //   7637: invokestatic abs : (I)I
    //   7640: invokevirtual charAt : (I)C
    //   7643: if_icmple -> 7989
    //   7646: sipush #13556
    //   7649: sipush #-8859
    //   7652: invokestatic a : (II)Ljava/lang/String;
    //   7655: iconst_1
    //   7656: ldc burp/Zl8i
    //   7658: invokevirtual getClassLoader : ()Ljava/lang/ClassLoader;
    //   7661: invokestatic forName : (Ljava/lang/String;ZLjava/lang/ClassLoader;)Ljava/lang/Class;
    //   7664: invokevirtual getDeclaredFields : ()[Ljava/lang/reflect/Field;
    //   7667: astore #5
    //   7669: aload #5
    //   7671: arraylength
    //   7672: istore #6
    //   7674: iconst_0
    //   7675: istore #7
    //   7677: iload #7
    //   7679: iload #6
    //   7681: if_icmpge -> 7819
    //   7684: aload #5
    //   7686: iload #7
    //   7688: aaload
    //   7689: astore #8
    //   7691: aload #8
    //   7693: invokevirtual getModifiers : ()I
    //   7696: invokestatic isStatic : (I)Z
    //   7699: ifne -> 7709
    //   7702: goto -> 7812
    //   7705: invokestatic a : (Ljava/lang/Throwable;)Ljava/lang/Throwable;
    //   7708: athrow
    //   7709: aload #8
    //   7711: invokevirtual getType : ()Ljava/lang/Class;
    //   7714: astore #9
    //   7716: aload #9
    //   7718: ifnull -> 7799
    //   7721: aload #9
    //   7723: invokevirtual isPrimitive : ()Z
    //   7726: ifne -> 7799
    //   7729: goto -> 7736
    //   7732: invokestatic a : (Ljava/lang/Throwable;)Ljava/lang/Throwable;
    //   7735: athrow
    //   7736: aload #9
    //   7738: invokevirtual getPackage : ()Ljava/lang/Package;
    //   7741: ifnull -> 7799
    //   7744: goto -> 7751
    //   7747: invokestatic a : (Ljava/lang/Throwable;)Ljava/lang/Throwable;
    //   7750: athrow
    //   7751: aload #9
    //   7753: invokevirtual getPackage : ()Ljava/lang/Package;
    //   7756: invokevirtual getName : ()Ljava/lang/String;
    //   7759: ifnull -> 7799
    //   7762: goto -> 7769
    //   7765: invokestatic a : (Ljava/lang/Throwable;)Ljava/lang/Throwable;
    //   7768: athrow
    //   7769: aload #9
    //   7771: invokevirtual getPackage : ()Ljava/lang/Package;
    //   7774: invokevirtual getName : ()Ljava/lang/String;
    //   7777: sipush #13554
    //   7780: sipush #1438
    //   7783: invokestatic a : (II)Ljava/lang/String;
    //   7786: invokevirtual startsWith : (Ljava/lang/String;)Z
    //   7789: ifne -> 7799
    //   7792: goto -> 7799
    //   7795: invokestatic a : (Ljava/lang/Throwable;)Ljava/lang/Throwable;
    //   7798: athrow
    //   7799: aload #8
    //   7801: iconst_1
    //   7802: invokevirtual setAccessible : (Z)V
    //   7805: aload #8
    //   7807: aconst_null
    //   7808: invokevirtual get : (Ljava/lang/Object;)Ljava/lang/Object;
    //   7811: pop
    //   7812: iinc #7, 1
    //   7815: iload_2
    //   7816: ifeq -> 7677
    //   7819: sipush #13546
    //   7822: sipush #26236
    //   7825: invokestatic a : (II)Ljava/lang/String;
    //   7828: invokestatic forName : (Ljava/lang/String;)Ljava/lang/Class;
    //   7831: invokevirtual getDeclaredMethods : ()[Ljava/lang/reflect/Method;
    //   7834: astore #5
    //   7836: aload #5
    //   7838: arraylength
    //   7839: istore #6
    //   7841: iconst_0
    //   7842: istore #7
    //   7844: iload #7
    //   7846: iload #6
    //   7848: if_icmpge -> 7985
    //   7851: aload #5
    //   7853: iload #7
    //   7855: aaload
    //   7856: astore #8
    //   7858: aload #8
    //   7860: invokevirtual getParameterTypes : ()[Ljava/lang/Class;
    //   7863: pop
    //   7864: aload #8
    //   7866: invokevirtual getModifiers : ()I
    //   7869: invokestatic isStatic : (I)Z
    //   7872: ifeq -> 7971
    //   7875: aload #8
    //   7877: invokevirtual getParameterTypes : ()[Ljava/lang/Class;
    //   7880: arraylength
    //   7881: iconst_2
    //   7882: if_icmpne -> 7971
    //   7885: goto -> 7892
    //   7888: invokestatic a : (Ljava/lang/Throwable;)Ljava/lang/Throwable;
    //   7891: athrow
    //   7892: aload #8
    //   7894: invokevirtual getReturnType : ()Ljava/lang/Class;
    //   7897: getstatic java/lang/Boolean.TYPE : Ljava/lang/Class;
    //   7900: if_acmpne -> 7971
    //   7903: goto -> 7910
    //   7906: invokestatic a : (Ljava/lang/Throwable;)Ljava/lang/Throwable;
    //   7909: athrow
    //   7910: aload #8
    //   7912: iconst_1
    //   7913: invokevirtual setAccessible : (Z)V
    //   7916: aload #8
    //   7918: aconst_null
    //   7919: iconst_2
    //   7920: anewarray java/lang/Object
    //   7923: dup
    //   7924: iconst_0
    //   7925: aload_0
    //   7926: aastore
    //   7927: dup
    //   7928: iconst_1
    //   7929: aload_1
    //   7930: ifnonnull -> 7948
    //   7933: goto -> 7940
    //   7936: invokestatic a : (Ljava/lang/Throwable;)Ljava/lang/Throwable;
    //   7939: athrow
    //   7940: aload_1
    //   7941: goto -> 7955
    //   7944: invokestatic a : (Ljava/lang/Throwable;)Ljava/lang/Throwable;
    //   7947: athrow
    //   7948: aload_1
    //   7949: checkcast [B
    //   7952: invokevirtual clone : ()Ljava/lang/Object;
    //   7955: aastore
    //   7956: invokevirtual invoke : (Ljava/lang/Object;[Ljava/lang/Object;)Ljava/lang/Object;
    //   7959: checkcast java/lang/Boolean
    //   7962: invokevirtual booleanValue : ()Z
    //   7965: istore #4
    //   7967: iload_2
    //   7968: ifeq -> 7985
    //   7971: iinc #7, 1
    //   7974: iload_2
    //   7975: ifeq -> 7844
    //   7978: goto -> 7985
    //   7981: invokestatic a : (Ljava/lang/Throwable;)Ljava/lang/Throwable;
    //   7984: athrow
    //   7985: iload_2
    //   7986: ifeq -> 8328
    //   7989: sipush #13538
    //   7992: sipush #1404
    //   7995: invokestatic a : (II)Ljava/lang/String;
    //   7998: iconst_1
    //   7999: ldc burp/Zz0b
    //   8001: invokevirtual getClassLoader : ()Ljava/lang/ClassLoader;
    //   8004: invokestatic forName : (Ljava/lang/String;ZLjava/lang/ClassLoader;)Ljava/lang/Class;
    //   8007: invokevirtual getDeclaredFields : ()[Ljava/lang/reflect/Field;
    //   8010: astore #5
    //   8012: aload #5
    //   8014: arraylength
    //   8015: istore #6
    //   8017: iconst_0
    //   8018: istore #7
    //   8020: iload #7
    //   8022: iload #6
    //   8024: if_icmpge -> 8162
    //   8027: aload #5
    //   8029: iload #7
    //   8031: aaload
    //   8032: astore #8
    //   8034: aload #8
    //   8036: invokevirtual getModifiers : ()I
    //   8039: invokestatic isStatic : (I)Z
    //   8042: ifne -> 8052
    //   8045: goto -> 8155
    //   8048: invokestatic a : (Ljava/lang/Throwable;)Ljava/lang/Throwable;
    //   8051: athrow
    //   8052: aload #8
    //   8054: invokevirtual getType : ()Ljava/lang/Class;
    //   8057: astore #9
    //   8059: aload #9
    //   8061: ifnull -> 8142
    //   8064: aload #9
    //   8066: invokevirtual isPrimitive : ()Z
    //   8069: ifne -> 8142
    //   8072: goto -> 8079
    //   8075: invokestatic a : (Ljava/lang/Throwable;)Ljava/lang/Throwable;
    //   8078: athrow
    //   8079: aload #9
    //   8081: invokevirtual getPackage : ()Ljava/lang/Package;
    //   8084: ifnull -> 8142
    //   8087: goto -> 8094
    //   8090: invokestatic a : (Ljava/lang/Throwable;)Ljava/lang/Throwable;
    //   8093: athrow
    //   8094: aload #9
    //   8096: invokevirtual getPackage : ()Ljava/lang/Package;
    //   8099: invokevirtual getName : ()Ljava/lang/String;
    //   8102: ifnull -> 8142
    //   8105: goto -> 8112
    //   8108: invokestatic a : (Ljava/lang/Throwable;)Ljava/lang/Throwable;
    //   8111: athrow
    //   8112: aload #9
    //   8114: invokevirtual getPackage : ()Ljava/lang/Package;
    //   8117: invokevirtual getName : ()Ljava/lang/String;
    //   8120: sipush #13554
    //   8123: sipush #1438
    //   8126: invokestatic a : (II)Ljava/lang/String;
    //   8129: invokevirtual startsWith : (Ljava/lang/String;)Z
    //   8132: ifne -> 8142
    //   8135: goto -> 8142
    //   8138: invokestatic a : (Ljava/lang/Throwable;)Ljava/lang/Throwable;
    //   8141: athrow
    //   8142: aload #8
    //   8144: iconst_1
    //   8145: invokevirtual setAccessible : (Z)V
    //   8148: aload #8
    //   8150: aconst_null
    //   8151: invokevirtual get : (Ljava/lang/Object;)Ljava/lang/Object;
    //   8154: pop
    //   8155: iinc #7, 1
    //   8158: iload_2
    //   8159: ifeq -> 8020
    //   8162: sipush #13536
    //   8165: sipush #6415
    //   8168: invokestatic a : (II)Ljava/lang/String;
    //   8171: invokestatic forName : (Ljava/lang/String;)Ljava/lang/Class;
    //   8174: invokevirtual getDeclaredMethods : ()[Ljava/lang/reflect/Method;
    //   8177: astore #5
    //   8179: aload #5
    //   8181: arraylength
    //   8182: istore #6
    //   8184: iconst_0
    //   8185: istore #7
    //   8187: iload #7
    //   8189: iload #6
    //   8191: if_icmpge -> 8328
    //   8194: aload #5
    //   8196: iload #7
    //   8198: aaload
    //   8199: astore #8
    //   8201: aload #8
    //   8203: invokevirtual getParameterTypes : ()[Ljava/lang/Class;
    //   8206: pop
    //   8207: aload #8
    //   8209: invokevirtual getModifiers : ()I
    //   8212: invokestatic isStatic : (I)Z
    //   8215: ifeq -> 8314
    //   8218: aload #8
    //   8220: invokevirtual getParameterTypes : ()[Ljava/lang/Class;
    //   8223: arraylength
    //   8224: iconst_2
    //   8225: if_icmpne -> 8314
    //   8228: goto -> 8235
    //   8231: invokestatic a : (Ljava/lang/Throwable;)Ljava/lang/Throwable;
    //   8234: athrow
    //   8235: aload #8
    //   8237: invokevirtual getReturnType : ()Ljava/lang/Class;
    //   8240: getstatic java/lang/Boolean.TYPE : Ljava/lang/Class;
    //   8243: if_acmpne -> 8314
    //   8246: goto -> 8253
    //   8249: invokestatic a : (Ljava/lang/Throwable;)Ljava/lang/Throwable;
    //   8252: athrow
    //   8253: aload #8
    //   8255: iconst_1
    //   8256: invokevirtual setAccessible : (Z)V
    //   8259: aload #8
    //   8261: aconst_null
    //   8262: iconst_2
    //   8263: anewarray java/lang/Object
    //   8266: dup
    //   8267: iconst_0
    //   8268: aload_0
    //   8269: aastore
    //   8270: dup
    //   8271: iconst_1
    //   8272: aload_1
    //   8273: ifnonnull -> 8291
    //   8276: goto -> 8283
    //   8279: invokestatic a : (Ljava/lang/Throwable;)Ljava/lang/Throwable;
    //   8282: athrow
    //   8283: aload_1
    //   8284: goto -> 8298
    //   8287: invokestatic a : (Ljava/lang/Throwable;)Ljava/lang/Throwable;
    //   8290: athrow
    //   8291: aload_1
    //   8292: checkcast [B
    //   8295: invokevirtual clone : ()Ljava/lang/Object;
    //   8298: aastore
    //   8299: invokevirtual invoke : (Ljava/lang/Object;[Ljava/lang/Object;)Ljava/lang/Object;
    //   8302: checkcast java/lang/Boolean
    //   8305: invokevirtual booleanValue : ()Z
    //   8308: istore #4
    //   8310: iload_2
    //   8311: ifeq -> 8328
    //   8314: iinc #7, 1
    //   8317: iload_2
    //   8318: ifeq -> 8187
    //   8321: goto -> 8328
    //   8324: invokestatic a : (Ljava/lang/Throwable;)Ljava/lang/Throwable;
    //   8327: athrow
    //   8328: iload #4
    //   8330: ifeq -> 8336
    //   8333: iload #4
    //   8335: ireturn
    //   8336: getstatic burp/Zkq9.ZO : Ljava/lang/String;
    //   8339: getstatic burp/Zstf.ZA : Ljava/lang/Object;
    //   8342: checkcast java/math/BigInteger
    //   8345: invokevirtual intValue : ()I
    //   8348: bipush #32
    //   8350: irem
    //   8351: invokestatic abs : (I)I
    //   8354: invokevirtual charAt : (I)C
    //   8357: getstatic burp/Zsjo.Zu : Ljava/lang/String;
    //   8360: getstatic burp/Zle6.ZM : Ljava/lang/Object;
    //   8363: checkcast java/math/BigInteger
    //   8366: invokevirtual intValue : ()I
    //   8369: bipush #32
    //   8371: irem
    //   8372: invokestatic abs : (I)I
    //   8375: invokevirtual charAt : (I)C
    //   8378: if_icmpgt -> 8724
    //   8381: sipush #13541
    //   8384: sipush #-6982
    //   8387: invokestatic a : (II)Ljava/lang/String;
    //   8390: iconst_1
    //   8391: ldc burp/Zza3
    //   8393: invokevirtual getClassLoader : ()Ljava/lang/ClassLoader;
    //   8396: invokestatic forName : (Ljava/lang/String;ZLjava/lang/ClassLoader;)Ljava/lang/Class;
    //   8399: invokevirtual getDeclaredFields : ()[Ljava/lang/reflect/Field;
    //   8402: astore #5
    //   8404: aload #5
    //   8406: arraylength
    //   8407: istore #6
    //   8409: iconst_0
    //   8410: istore #7
    //   8412: iload #7
    //   8414: iload #6
    //   8416: if_icmpge -> 8554
    //   8419: aload #5
    //   8421: iload #7
    //   8423: aaload
    //   8424: astore #8
    //   8426: aload #8
    //   8428: invokevirtual getModifiers : ()I
    //   8431: invokestatic isStatic : (I)Z
    //   8434: ifne -> 8444
    //   8437: goto -> 8547
    //   8440: invokestatic a : (Ljava/lang/Throwable;)Ljava/lang/Throwable;
    //   8443: athrow
    //   8444: aload #8
    //   8446: invokevirtual getType : ()Ljava/lang/Class;
    //   8449: astore #9
    //   8451: aload #9
    //   8453: ifnull -> 8534
    //   8456: aload #9
    //   8458: invokevirtual isPrimitive : ()Z
    //   8461: ifne -> 8534
    //   8464: goto -> 8471
    //   8467: invokestatic a : (Ljava/lang/Throwable;)Ljava/lang/Throwable;
    //   8470: athrow
    //   8471: aload #9
    //   8473: invokevirtual getPackage : ()Ljava/lang/Package;
    //   8476: ifnull -> 8534
    //   8479: goto -> 8486
    //   8482: invokestatic a : (Ljava/lang/Throwable;)Ljava/lang/Throwable;
    //   8485: athrow
    //   8486: aload #9
    //   8488: invokevirtual getPackage : ()Ljava/lang/Package;
    //   8491: invokevirtual getName : ()Ljava/lang/String;
    //   8494: ifnull -> 8534
    //   8497: goto -> 8504
    //   8500: invokestatic a : (Ljava/lang/Throwable;)Ljava/lang/Throwable;
    //   8503: athrow
    //   8504: aload #9
    //   8506: invokevirtual getPackage : ()Ljava/lang/Package;
    //   8509: invokevirtual getName : ()Ljava/lang/String;
    //   8512: sipush #13554
    //   8515: sipush #1438
    //   8518: invokestatic a : (II)Ljava/lang/String;
    //   8521: invokevirtual startsWith : (Ljava/lang/String;)Z
    //   8524: ifne -> 8534
    //   8527: goto -> 8534
    //   8530: invokestatic a : (Ljava/lang/Throwable;)Ljava/lang/Throwable;
    //   8533: athrow
    //   8534: aload #8
    //   8536: iconst_1
    //   8537: invokevirtual setAccessible : (Z)V
    //   8540: aload #8
    //   8542: aconst_null
    //   8543: invokevirtual get : (Ljava/lang/Object;)Ljava/lang/Object;
    //   8546: pop
    //   8547: iinc #7, 1
    //   8550: iload_2
    //   8551: ifeq -> 8412
    //   8554: sipush #13551
    //   8557: sipush #2850
    //   8560: invokestatic a : (II)Ljava/lang/String;
    //   8563: invokestatic forName : (Ljava/lang/String;)Ljava/lang/Class;
    //   8566: invokevirtual getDeclaredMethods : ()[Ljava/lang/reflect/Method;
    //   8569: astore #5
    //   8571: aload #5
    //   8573: arraylength
    //   8574: istore #6
    //   8576: iconst_0
    //   8577: istore #7
    //   8579: iload #7
    //   8581: iload #6
    //   8583: if_icmpge -> 8720
    //   8586: aload #5
    //   8588: iload #7
    //   8590: aaload
    //   8591: astore #8
    //   8593: aload #8
    //   8595: invokevirtual getParameterTypes : ()[Ljava/lang/Class;
    //   8598: pop
    //   8599: aload #8
    //   8601: invokevirtual getModifiers : ()I
    //   8604: invokestatic isStatic : (I)Z
    //   8607: ifeq -> 8706
    //   8610: aload #8
    //   8612: invokevirtual getParameterTypes : ()[Ljava/lang/Class;
    //   8615: arraylength
    //   8616: iconst_2
    //   8617: if_icmpne -> 8706
    //   8620: goto -> 8627
    //   8623: invokestatic a : (Ljava/lang/Throwable;)Ljava/lang/Throwable;
    //   8626: athrow
    //   8627: aload #8
    //   8629: invokevirtual getReturnType : ()Ljava/lang/Class;
    //   8632: getstatic java/lang/Boolean.TYPE : Ljava/lang/Class;
    //   8635: if_acmpne -> 8706
    //   8638: goto -> 8645
    //   8641: invokestatic a : (Ljava/lang/Throwable;)Ljava/lang/Throwable;
    //   8644: athrow
    //   8645: aload #8
    //   8647: iconst_1
    //   8648: invokevirtual setAccessible : (Z)V
    //   8651: aload #8
    //   8653: aconst_null
    //   8654: iconst_2
    //   8655: anewarray java/lang/Object
    //   8658: dup
    //   8659: iconst_0
    //   8660: aload_0
    //   8661: aastore
    //   8662: dup
    //   8663: iconst_1
    //   8664: aload_1
    //   8665: ifnonnull -> 8683
    //   8668: goto -> 8675
    //   8671: invokestatic a : (Ljava/lang/Throwable;)Ljava/lang/Throwable;
    //   8674: athrow
    //   8675: aload_1
    //   8676: goto -> 8690
    //   8679: invokestatic a : (Ljava/lang/Throwable;)Ljava/lang/Throwable;
    //   8682: athrow
    //   8683: aload_1
    //   8684: checkcast [B
    //   8687: invokevirtual clone : ()Ljava/lang/Object;
    //   8690: aastore
    //   8691: invokevirtual invoke : (Ljava/lang/Object;[Ljava/lang/Object;)Ljava/lang/Object;
    //   8694: checkcast java/lang/Boolean
    //   8697: invokevirtual booleanValue : ()Z
    //   8700: istore #4
    //   8702: iload_2
    //   8703: ifeq -> 8720
    //   8706: iinc #7, 1
    //   8709: iload_2
    //   8710: ifeq -> 8579
    //   8713: goto -> 8720
    //   8716: invokestatic a : (Ljava/lang/Throwable;)Ljava/lang/Throwable;
    //   8719: athrow
    //   8720: iload_2
    //   8721: ifeq -> 9063
    //   8724: sipush #13564
    //   8727: sipush #11148
    //   8730: invokestatic a : (II)Ljava/lang/String;
    //   8733: iconst_1
    //   8734: ldc burp/Zrt3
    //   8736: invokevirtual getClassLoader : ()Ljava/lang/ClassLoader;
    //   8739: invokestatic forName : (Ljava/lang/String;ZLjava/lang/ClassLoader;)Ljava/lang/Class;
    //   8742: invokevirtual getDeclaredFields : ()[Ljava/lang/reflect/Field;
    //   8745: astore #5
    //   8747: aload #5
    //   8749: arraylength
    //   8750: istore #6
    //   8752: iconst_0
    //   8753: istore #7
    //   8755: iload #7
    //   8757: iload #6
    //   8759: if_icmpge -> 8897
    //   8762: aload #5
    //   8764: iload #7
    //   8766: aaload
    //   8767: astore #8
    //   8769: aload #8
    //   8771: invokevirtual getModifiers : ()I
    //   8774: invokestatic isStatic : (I)Z
    //   8777: ifne -> 8787
    //   8780: goto -> 8890
    //   8783: invokestatic a : (Ljava/lang/Throwable;)Ljava/lang/Throwable;
    //   8786: athrow
    //   8787: aload #8
    //   8789: invokevirtual getType : ()Ljava/lang/Class;
    //   8792: astore #9
    //   8794: aload #9
    //   8796: ifnull -> 8877
    //   8799: aload #9
    //   8801: invokevirtual isPrimitive : ()Z
    //   8804: ifne -> 8877
    //   8807: goto -> 8814
    //   8810: invokestatic a : (Ljava/lang/Throwable;)Ljava/lang/Throwable;
    //   8813: athrow
    //   8814: aload #9
    //   8816: invokevirtual getPackage : ()Ljava/lang/Package;
    //   8819: ifnull -> 8877
    //   8822: goto -> 8829
    //   8825: invokestatic a : (Ljava/lang/Throwable;)Ljava/lang/Throwable;
    //   8828: athrow
    //   8829: aload #9
    //   8831: invokevirtual getPackage : ()Ljava/lang/Package;
    //   8834: invokevirtual getName : ()Ljava/lang/String;
    //   8837: ifnull -> 8877
    //   8840: goto -> 8847
    //   8843: invokestatic a : (Ljava/lang/Throwable;)Ljava/lang/Throwable;
    //   8846: athrow
    //   8847: aload #9
    //   8849: invokevirtual getPackage : ()Ljava/lang/Package;
    //   8852: invokevirtual getName : ()Ljava/lang/String;
    //   8855: sipush #13554
    //   8858: sipush #1438
    //   8861: invokestatic a : (II)Ljava/lang/String;
    //   8864: invokevirtual startsWith : (Ljava/lang/String;)Z
    //   8867: ifne -> 8877
    //   8870: goto -> 8877
    //   8873: invokestatic a : (Ljava/lang/Throwable;)Ljava/lang/Throwable;
    //   8876: athrow
    //   8877: aload #8
    //   8879: iconst_1
    //   8880: invokevirtual setAccessible : (Z)V
    //   8883: aload #8
    //   8885: aconst_null
    //   8886: invokevirtual get : (Ljava/lang/Object;)Ljava/lang/Object;
    //   8889: pop
    //   8890: iinc #7, 1
    //   8893: iload_2
    //   8894: ifeq -> 8755
    //   8897: sipush #13537
    //   8900: sipush #-25036
    //   8903: invokestatic a : (II)Ljava/lang/String;
    //   8906: invokestatic forName : (Ljava/lang/String;)Ljava/lang/Class;
    //   8909: invokevirtual getDeclaredMethods : ()[Ljava/lang/reflect/Method;
    //   8912: astore #5
    //   8914: aload #5
    //   8916: arraylength
    //   8917: istore #6
    //   8919: iconst_0
    //   8920: istore #7
    //   8922: iload #7
    //   8924: iload #6
    //   8926: if_icmpge -> 9063
    //   8929: aload #5
    //   8931: iload #7
    //   8933: aaload
    //   8934: astore #8
    //   8936: aload #8
    //   8938: invokevirtual getParameterTypes : ()[Ljava/lang/Class;
    //   8941: pop
    //   8942: aload #8
    //   8944: invokevirtual getModifiers : ()I
    //   8947: invokestatic isStatic : (I)Z
    //   8950: ifeq -> 9049
    //   8953: aload #8
    //   8955: invokevirtual getParameterTypes : ()[Ljava/lang/Class;
    //   8958: arraylength
    //   8959: iconst_2
    //   8960: if_icmpne -> 9049
    //   8963: goto -> 8970
    //   8966: invokestatic a : (Ljava/lang/Throwable;)Ljava/lang/Throwable;
    //   8969: athrow
    //   8970: aload #8
    //   8972: invokevirtual getReturnType : ()Ljava/lang/Class;
    //   8975: getstatic java/lang/Boolean.TYPE : Ljava/lang/Class;
    //   8978: if_acmpne -> 9049
    //   8981: goto -> 8988
    //   8984: invokestatic a : (Ljava/lang/Throwable;)Ljava/lang/Throwable;
    //   8987: athrow
    //   8988: aload #8
    //   8990: iconst_1
    //   8991: invokevirtual setAccessible : (Z)V
    //   8994: aload #8
    //   8996: aconst_null
    //   8997: iconst_2
    //   8998: anewarray java/lang/Object
    //   9001: dup
    //   9002: iconst_0
    //   9003: aload_0
    //   9004: aastore
    //   9005: dup
    //   9006: iconst_1
    //   9007: aload_1
    //   9008: ifnonnull -> 9026
    //   9011: goto -> 9018
    //   9014: invokestatic a : (Ljava/lang/Throwable;)Ljava/lang/Throwable;
    //   9017: athrow
    //   9018: aload_1
    //   9019: goto -> 9033
    //   9022: invokestatic a : (Ljava/lang/Throwable;)Ljava/lang/Throwable;
    //   9025: athrow
    //   9026: aload_1
    //   9027: checkcast [B
    //   9030: invokevirtual clone : ()Ljava/lang/Object;
    //   9033: aastore
    //   9034: invokevirtual invoke : (Ljava/lang/Object;[Ljava/lang/Object;)Ljava/lang/Object;
    //   9037: checkcast java/lang/Boolean
    //   9040: invokevirtual booleanValue : ()Z
    //   9043: istore #4
    //   9045: iload_2
    //   9046: ifeq -> 9063
    //   9049: iinc #7, 1
    //   9052: iload_2
    //   9053: ifeq -> 8922
    //   9056: goto -> 9063
    //   9059: invokestatic a : (Ljava/lang/Throwable;)Ljava/lang/Throwable;
    //   9062: athrow
    //   9063: iload #4
    //   9065: ireturn
    //   9066: astore_3
    //   9067: new java/lang/Exception
    //   9070: dup
    //   9071: aload_3
    //   9072: invokevirtual getMessage : ()Ljava/lang/String;
    //   9075: invokespecial <init> : (Ljava/lang/String;)V
    //   9078: athrow
    // Exception table:
    //   from	to	target	type
    //   4	6865	9066	java/lang/Throwable
    //   22	198	201	java/lang/Throwable
    //   168	235	238	java/lang/Throwable
    //   205	272	275	java/lang/Throwable
    //   242	309	312	java/lang/Throwable
    //   279	346	349	java/lang/Throwable
    //   316	383	386	java/lang/Throwable
    //   353	420	423	java/lang/Throwable
    //   390	457	460	java/lang/Throwable
    //   427	494	497	java/lang/Throwable
    //   464	531	534	java/lang/Throwable
    //   501	568	571	java/lang/Throwable
    //   538	605	608	java/lang/Throwable
    //   575	642	645	java/lang/Throwable
    //   612	679	682	java/lang/Throwable
    //   649	716	719	java/lang/Throwable
    //   686	753	756	java/lang/Throwable
    //   723	790	793	java/lang/Throwable
    //   760	827	830	java/lang/Throwable
    //   797	864	867	java/lang/Throwable
    //   834	901	904	java/lang/Throwable
    //   871	938	941	java/lang/Throwable
    //   908	975	978	java/lang/Throwable
    //   945	1012	1015	java/lang/Throwable
    //   982	1049	1052	java/lang/Throwable
    //   1019	1086	1089	java/lang/Throwable
    //   1056	1123	1126	java/lang/Throwable
    //   1093	1160	1163	java/lang/Throwable
    //   1130	1197	1200	java/lang/Throwable
    //   1167	1234	1237	java/lang/Throwable
    //   1204	1271	1274	java/lang/Throwable
    //   1241	1308	1311	java/lang/Throwable
    //   1278	1341	1344	java/lang/Throwable
    //   2165	2199	2202	java/lang/Throwable
    //   2295	2373	2376	java/lang/Throwable
    //   2302	2516	2519	java/lang/Throwable
    //   2894	2909	2909	java/lang/Throwable
    //   2936	2970	2973	java/lang/Throwable
    //   2980	2992	2995	java/lang/Throwable
    //   3078	3156	3159	java/lang/Throwable
    //   3085	3299	3302	java/lang/Throwable
    //   3699	3777	3780	java/lang/Throwable
    //   3706	3920	3923	java/lang/Throwable
    //   4367	4401	4404	java/lang/Throwable
    //   4408	4420	4423	java/lang/Throwable
    //   4506	4584	4587	java/lang/Throwable
    //   4513	4727	4730	java/lang/Throwable
    //   5484	5498	5498	java/lang/Throwable
    //   5509	5522	5525	java/lang/Throwable
    //   5514	5537	5540	java/lang/Throwable
    //   5529	5555	5558	java/lang/Throwable
    //   5544	5585	5588	java/lang/Throwable
    //   5651	5678	5681	java/lang/Throwable
    //   5668	5699	5702	java/lang/Throwable
    //   5685	5729	5732	java/lang/Throwable
    //   5706	5740	5740	java/lang/Throwable
    //   5751	5767	5770	java/lang/Throwable
    //   5774	6124	6127	java/lang/Throwable
    //   5958	5968	5968	java/lang/Throwable
    //   5972	5984	5984	java/lang/Throwable
    //   5988	6000	6000	java/lang/Throwable
    //   6004	6017	6017	java/lang/Throwable
    //   6021	6034	6034	java/lang/Throwable
    //   6222	6236	6236	java/lang/Throwable
    //   6247	6260	6263	java/lang/Throwable
    //   6252	6275	6278	java/lang/Throwable
    //   6267	6293	6296	java/lang/Throwable
    //   6282	6323	6326	java/lang/Throwable
    //   6389	6416	6419	java/lang/Throwable
    //   6406	6434	6437	java/lang/Throwable
    //   6423	6464	6467	java/lang/Throwable
    //   6441	6475	6475	java/lang/Throwable
    //   6498	6509	6512	java/lang/Throwable
    //   6564	6578	6578	java/lang/Throwable
    //   6589	6602	6605	java/lang/Throwable
    //   6594	6617	6620	java/lang/Throwable
    //   6609	6635	6638	java/lang/Throwable
    //   6624	6665	6668	java/lang/Throwable
    //   6731	6758	6761	java/lang/Throwable
    //   6748	6776	6779	java/lang/Throwable
    //   6765	6806	6809	java/lang/Throwable
    //   6783	6817	6817	java/lang/Throwable
    //   6840	6851	6854	java/lang/Throwable
    //   6866	7600	9066	java/lang/Throwable
    //   6956	6970	6970	java/lang/Throwable
    //   6981	6994	6997	java/lang/Throwable
    //   6986	7009	7012	java/lang/Throwable
    //   7001	7027	7030	java/lang/Throwable
    //   7016	7057	7060	java/lang/Throwable
    //   7123	7150	7153	java/lang/Throwable
    //   7140	7168	7171	java/lang/Throwable
    //   7157	7198	7201	java/lang/Throwable
    //   7175	7209	7209	java/lang/Throwable
    //   7232	7243	7246	java/lang/Throwable
    //   7299	7313	7313	java/lang/Throwable
    //   7324	7337	7340	java/lang/Throwable
    //   7329	7352	7355	java/lang/Throwable
    //   7344	7370	7373	java/lang/Throwable
    //   7359	7400	7403	java/lang/Throwable
    //   7466	7493	7496	java/lang/Throwable
    //   7483	7511	7514	java/lang/Throwable
    //   7500	7541	7544	java/lang/Throwable
    //   7518	7552	7552	java/lang/Throwable
    //   7575	7586	7589	java/lang/Throwable
    //   7601	8335	9066	java/lang/Throwable
    //   7691	7705	7705	java/lang/Throwable
    //   7716	7729	7732	java/lang/Throwable
    //   7721	7744	7747	java/lang/Throwable
    //   7736	7762	7765	java/lang/Throwable
    //   7751	7792	7795	java/lang/Throwable
    //   7858	7885	7888	java/lang/Throwable
    //   7875	7903	7906	java/lang/Throwable
    //   7892	7933	7936	java/lang/Throwable
    //   7910	7944	7944	java/lang/Throwable
    //   7967	7978	7981	java/lang/Throwable
    //   8034	8048	8048	java/lang/Throwable
    //   8059	8072	8075	java/lang/Throwable
    //   8064	8087	8090	java/lang/Throwable
    //   8079	8105	8108	java/lang/Throwable
    //   8094	8135	8138	java/lang/Throwable
    //   8201	8228	8231	java/lang/Throwable
    //   8218	8246	8249	java/lang/Throwable
    //   8235	8276	8279	java/lang/Throwable
    //   8253	8287	8287	java/lang/Throwable
    //   8310	8321	8324	java/lang/Throwable
    //   8336	9065	9066	java/lang/Throwable
    //   8426	8440	8440	java/lang/Throwable
    //   8451	8464	8467	java/lang/Throwable
    //   8456	8479	8482	java/lang/Throwable
    //   8471	8497	8500	java/lang/Throwable
    //   8486	8527	8530	java/lang/Throwable
    //   8593	8620	8623	java/lang/Throwable
    //   8610	8638	8641	java/lang/Throwable
    //   8627	8668	8671	java/lang/Throwable
    //   8645	8679	8679	java/lang/Throwable
    //   8702	8713	8716	java/lang/Throwable
    //   8769	8783	8783	java/lang/Throwable
    //   8794	8807	8810	java/lang/Throwable
    //   8799	8822	8825	java/lang/Throwable
    //   8814	8840	8843	java/lang/Throwable
    //   8829	8870	8873	java/lang/Throwable
    //   8936	8963	8966	java/lang/Throwable
    //   8953	8981	8984	java/lang/Throwable
    //   8970	9011	9014	java/lang/Throwable
    //   8988	9022	9022	java/lang/Throwable
    //   9045	9056	9059	java/lang/Throwable
  }
  
  static void Zq(Object[] paramArrayOfObject, Object paramObject) throws Throwable {}
  
  static void Zh(Object paramObject) {
    Zzri.ZL = a(13548, -29709);
    Zzri.ZG = new BigInteger(a(13544, -6230));
    boolean bool = Zt2e.ZK();
    try {
      try {
        if (Zzri.ZL.charAt(Math.abs(((BigInteger)Zl8i.ZY).intValue() % 32)) <= Zrpm.ZG.charAt(Math.abs(((BigInteger)Zkgp.Zw).intValue() % 32))) {
          try {
            Zl8f.Zn(Class.forName(a(13543, -10884)));
            if (bool)
              Ztgj.Zh(Class.forName(a(13550, 2920))); 
          } catch (Throwable throwable) {
            throw a(null);
          } 
          return;
        } 
      } catch (Throwable throwable) {
        throw a(null);
      } 
      Ztgj.Zh(Class.forName(a(13550, 2920)));
    } catch (Throwable throwable) {}
  }
  
  static {
    // Byte code:
    //   0: bipush #28
    //   2: anewarray java/lang/String
    //   5: astore #5
    //   7: iconst_0
    //   8: istore_3
    //   9: ldc '+/\\t3 7\\t\\tGSl?\\td!}\\twmYUJ\\tbc|\\tOE%\\tw^mYaD\\ts\\b}hF\\t\\\b#; a0.tC#)uk|:Cg\\t*l#Cg\\t\\f2?]k\\bt=ML#EQiCJPa\\nMpY'MZ5M!O{ KFI{fs9*r\\t%c\\t1z\\tYOM'[S=.\\t~[2 %3@` |PA7vJucPk3|N3\\b?\\t-Tk?#\\t\\\t\\f.Y'
    //   11: dup
    //   12: astore_2
    //   13: invokevirtual length : ()I
    //   16: istore #4
    //   18: bipush #9
    //   20: istore_1
    //   21: iconst_m1
    //   22: istore_0
    //   23: bipush #113
    //   25: iinc #0, 1
    //   28: aload_2
    //   29: iload_0
    //   30: dup
    //   31: iload_1
    //   32: iadd
    //   33: invokevirtual substring : (II)Ljava/lang/String;
    //   36: iconst_m1
    //   37: goto -> 143
    //   40: aload #5
    //   42: swap
    //   43: iload_3
    //   44: iinc #3, 1
    //   47: swap
    //   48: aastore
    //   49: iload_0
    //   50: iload_1
    //   51: iadd
    //   52: dup
    //   53: istore_0
    //   54: iload #4
    //   56: if_icmpge -> 68
    //   59: aload_2
    //   60: iload_0
    //   61: invokevirtual charAt : (I)C
    //   64: istore_1
    //   65: goto -> 23
    //   68: ldc ';A^\\tUz'
    //   70: dup
    //   71: astore_2
    //   72: invokevirtual length : ()I
    //   75: istore #4
    //   77: bipush #11
    //   79: istore_1
    //   80: iconst_m1
    //   81: istore_0
    //   82: bipush #7
    //   84: iinc #0, 1
    //   87: aload_2
    //   88: iload_0
    //   89: dup
    //   90: iload_1
    //   91: iadd
    //   92: invokevirtual substring : (II)Ljava/lang/String;
    //   95: iconst_0
    //   96: goto -> 143
    //   99: aload #5
    //   101: swap
    //   102: iload_3
    //   103: iinc #3, 1
    //   106: swap
    //   107: aastore
    //   108: iload_0
    //   109: iload_1
    //   110: iadd
    //   111: dup
    //   112: istore_0
    //   113: iload #4
    //   115: if_icmpge -> 127
    //   118: aload_2
    //   119: iload_0
    //   120: invokevirtual charAt : (I)C
    //   123: istore_1
    //   124: goto -> 82
    //   127: aload #5
    //   129: putstatic burp/Zmu6.a : [Ljava/lang/String;
    //   132: bipush #28
    //   134: anewarray java/lang/String
    //   137: putstatic burp/Zmu6.b : [Ljava/lang/String;
    //   140: goto -> 300
    //   143: dup_x2
    //   144: pop
    //   145: invokevirtual toCharArray : ()[C
    //   148: dup_x1
    //   149: arraylength
    //   150: dup_x2
    //   151: pop
    //   152: iconst_0
    //   153: istore #6
    //   155: dup2_x1
    //   156: pop2
    //   157: dup_x2
    //   158: iconst_1
    //   159: if_icmpgt -> 260
    //   162: dup2
    //   163: swap
    //   164: iload #6
    //   166: dup2_x1
    //   167: caload
    //   168: swap
    //   169: iload #6
    //   171: bipush #7
    //   173: irem
    //   174: tableswitch default -> 242, 0 -> 212, 1 -> 217, 2 -> 222, 3 -> 227, 4 -> 232, 5 -> 237
    //   212: bipush #115
    //   214: goto -> 244
    //   217: bipush #123
    //   219: goto -> 244
    //   222: bipush #11
    //   224: goto -> 244
    //   227: bipush #85
    //   229: goto -> 244
    //   232: bipush #80
    //   234: goto -> 244
    //   237: bipush #110
    //   239: goto -> 244
    //   242: bipush #45
    //   244: ixor
    //   245: ixor
    //   246: i2c
    //   247: castore
    //   248: iinc #6, 1
    //   251: dup
    //   252: ifne -> 260
    //   255: dup2
    //   256: dup_x1
    //   257: goto -> 166
    //   260: dup2_x1
    //   261: pop2
    //   262: dup_x2
    //   263: iload #6
    //   265: if_icmpgt -> 162
    //   268: pop
    //   269: new java/lang/String
    //   272: dup_x1
    //   273: swap
    //   274: invokespecial <init> : ([C)V
    //   277: invokevirtual intern : ()Ljava/lang/String;
    //   280: swap
    //   281: pop
    //   282: swap
    //   283: tableswitch default -> 40, 0 -> 99
    //   300: new java/math/BigInteger
    //   303: dup
    //   304: bipush #32
    //   306: newarray byte
    //   308: dup
    //   309: iconst_0
    //   310: bipush #57
    //   312: bastore
    //   313: dup
    //   314: iconst_1
    //   315: bipush #-29
    //   317: bastore
    //   318: dup
    //   319: iconst_2
    //   320: bipush #45
    //   322: bastore
    //   323: dup
    //   324: iconst_3
    //   325: bipush #87
    //   327: bastore
    //   328: dup
    //   329: iconst_4
    //   330: bipush #-81
    //   332: bastore
    //   333: dup
    //   334: iconst_5
    //   335: bipush #46
    //   337: bastore
    //   338: dup
    //   339: bipush #6
    //   341: bipush #44
    //   343: bastore
    //   344: dup
    //   345: bipush #7
    //   347: bipush #-10
    //   349: bastore
    //   350: dup
    //   351: bipush #8
    //   353: bipush #-109
    //   355: bastore
    //   356: dup
    //   357: bipush #9
    //   359: bipush #104
    //   361: bastore
    //   362: dup
    //   363: bipush #10
    //   365: bipush #25
    //   367: bastore
    //   368: dup
    //   369: bipush #11
    //   371: bipush #58
    //   373: bastore
    //   374: dup
    //   375: bipush #12
    //   377: iconst_3
    //   378: bastore
    //   379: dup
    //   380: bipush #13
    //   382: bipush #67
    //   384: bastore
    //   385: dup
    //   386: bipush #14
    //   388: bipush #-23
    //   390: bastore
    //   391: dup
    //   392: bipush #15
    //   394: iconst_1
    //   395: bastore
    //   396: dup
    //   397: bipush #16
    //   399: bipush #31
    //   401: bastore
    //   402: dup
    //   403: bipush #17
    //   405: bipush #-27
    //   407: bastore
    //   408: dup
    //   409: bipush #18
    //   411: bipush #101
    //   413: bastore
    //   414: dup
    //   415: bipush #19
    //   417: bipush #65
    //   419: bastore
    //   420: dup
    //   421: bipush #20
    //   423: bipush #42
    //   425: bastore
    //   426: dup
    //   427: bipush #21
    //   429: bipush #85
    //   431: bastore
    //   432: dup
    //   433: bipush #22
    //   435: bipush #28
    //   437: bastore
    //   438: dup
    //   439: bipush #23
    //   441: bipush #-19
    //   443: bastore
    //   444: dup
    //   445: bipush #24
    //   447: bipush #76
    //   449: bastore
    //   450: dup
    //   451: bipush #25
    //   453: bipush #83
    //   455: bastore
    //   456: dup
    //   457: bipush #26
    //   459: bipush #-81
    //   461: bastore
    //   462: dup
    //   463: bipush #27
    //   465: bipush #-4
    //   467: bastore
    //   468: dup
    //   469: bipush #28
    //   471: bipush #-128
    //   473: bastore
    //   474: dup
    //   475: bipush #29
    //   477: bipush #27
    //   479: bastore
    //   480: dup
    //   481: bipush #30
    //   483: bipush #111
    //   485: bastore
    //   486: dup
    //   487: bipush #31
    //   489: bipush #-29
    //   491: bastore
    //   492: invokespecial <init> : ([B)V
    //   495: putstatic burp/Zmu6.Zb : Ljava/lang/Object;
    //   498: sipush #13555
    //   501: sipush #11637
    //   504: invokestatic a : (II)Ljava/lang/String;
    //   507: putstatic burp/Zmu6.Zl : Ljava/lang/String;
    //   510: return
  }
  
  private static Throwable a(Throwable paramThrowable) {
    return paramThrowable;
  }
  
  private static String a(int paramInt1, int paramInt2) {
    int i = (paramInt1 ^ 0x34E7) & 0xFFFF;
    if (b[i] == null) {
      char[] arrayOfChar = a[i].toCharArray();
      switch (arrayOfChar[0] & 0xFF) {
        case 0:
        
        case 1:
        
        case 2:
        
        case 3:
        
        case 4:
        
        case 5:
        
        case 6:
        
        case 7:
        
        case 8:
        
        case 9:
        
        case 10:
        
        case 11:
        
        case 12:
        
        case 13:
        
        case 14:
        
        case 15:
        
        case 16:
        
        case 17:
        
        case 18:
        
        case 19:
        
        case 20:
        
        case 21:
        
        case 22:
        
        case 23:
        
        case 24:
        
        case 25:
        
        case 26:
        
        case 27:
        
        case 28:
        
        case 29:
        
        case 30:
        
        case 31:
        
        case 32:
        
        case 33:
        
        case 34:
        
        case 35:
        
        case 36:
        
        case 37:
        
        case 38:
        
        case 39:
        
        case 40:
        
        case 41:
        
        case 42:
        
        case 43:
        
        case 44:
        
        case 45:
        
        case 46:
        
        case 47:
        
        case 48:
        
        case 49:
        
        case 50:
        
        case 51:
        
        case 52:
        
        case 53:
        
        case 54:
        
        case 55:
        
        case 56:
        
        case 57:
        
        case 58:
        
        case 59:
        
        case 60:
        
        case 61:
        
        case 62:
        
        case 63:
        
        case 64:
        
        case 65:
        
        case 66:
        
        case 67:
        
        case 68:
        
        case 69:
        
        case 70:
        
        case 71:
        
        case 72:
        
        case 73:
        
        case 74:
        
        case 75:
        
        case 76:
        
        case 77:
        
        case 78:
        
        case 79:
        
        case 80:
        
        case 81:
        
        case 82:
        
        case 83:
        
        case 84:
        
        case 85:
        
        case 86:
        
        case 87:
        
        case 88:
        
        case 89:
        
        case 90:
        
        case 91:
        
        case 92:
        
        case 93:
        
        case 94:
        
        case 95:
        
        case 96:
        
        case 97:
        
        case 98:
        
        case 99:
        
        case 100:
        
        case 101:
        
        case 102:
        
        case 103:
        
        case 104:
        
        case 105:
        
        case 106:
        
        case 107:
        
        case 108:
        
        case 109:
        
        case 110:
        
        case 111:
        
        case 112:
        
        case 113:
        
        case 114:
        
        case 115:
        
        case 116:
        
        case 117:
        
        case 118:
        
        case 119:
        
        case 120:
        
        case 121:
        
        case 122:
        
        case 123:
        
        case 124:
        
        case 125:
        
        case 126:
        
        case 127:
        
        case 128:
        
        case 129:
        
        case 130:
        
        case 131:
        
        case 132:
        
        case 133:
        
        case 134:
        
        case 135:
        
        case 136:
        
        case 137:
        
        case 138:
        
        case 139:
        
        case 140:
        
        case 141:
        
        case 142:
        
        case 143:
        
        case 144:
        
        case 145:
        
        case 146:
        
        case 147:
        
        case 148:
        
        case 149:
        
        case 150:
        
        case 151:
        
        case 152:
        
        case 153:
        
        case 154:
        
        case 155:
        
        case 156:
        
        case 157:
        
        case 158:
        
        case 159:
        
        case 160:
        
        case 161:
        
        case 162:
        
        case 163:
        
        case 164:
        
        case 165:
        
        case 166:
        
        case 167:
        
        case 168:
        
        case 169:
        
        case 170:
        
        case 171:
        
        case 172:
        
        case 173:
        
        case 174:
        
        case 175:
        
        case 176:
        
        case 177:
        
        case 178:
        
        case 179:
        
        case 180:
        
        case 181:
        
        case 182:
        
        case 183:
        
        case 184:
        
        case 185:
        
        case 186:
        
        case 187:
        
        case 188:
        
        case 189:
        
        case 190:
        
        case 191:
        
        case 192:
        
        case 193:
        
        case 194:
        
        case 195:
        
        case 196:
        
        case 197:
        
        case 198:
        
        case 199:
        
        case 200:
        
        case 201:
        
        case 202:
        
        case 203:
        
        case 204:
        
        case 205:
        
        case 206:
        
        case 207:
        
        case 208:
        
        case 209:
        
        case 210:
        
        case 211:
        
        case 212:
        
        case 213:
        
        case 214:
        
        case 215:
        
        case 216:
        
        case 217:
        
        case 218:
        
        case 219:
        
        case 220:
        
        case 221:
        
        case 222:
        
        case 223:
        
        case 224:
        
        case 225:
        
        case 226:
        
        case 227:
        
        case 228:
        
        case 229:
        
        case 230:
        
        case 231:
        
        case 232:
        
        case 233:
        
        case 234:
        
        case 235:
        
        case 236:
        
        case 237:
        
        case 238:
        
        case 239:
        
        case 240:
        
        case 241:
        
        case 242:
        
        case 243:
        
        case 244:
        
        case 245:
        
        case 246:
        
        case 247:
        
        case 248:
        
        case 249:
        
        case 250:
        
        case 251:
        
        case 252:
        
        case 253:
        
        case 254:
        
        default:
          break;
      } 
      char c = '';
      int j = (paramInt2 & 0xFF) - c;
      if (j < 0)
        j += 256; 
      int k = ((paramInt2 & 0xFFFF) >>> 8) - c;
      if (k < 0)
        k += 256; 
      for (byte b = 0; b < arrayOfChar.length; b++) {
        int m = b % 2;
        if (m == 0) {
          arrayOfChar[b] = (char)(arrayOfChar[b] ^ j);
          j = ((j >>> 3 | j << 5) ^ arrayOfChar[b]) & 0xFF;
        } else {
          arrayOfChar[b] = (char)(arrayOfChar[b] ^ k);
          k = ((k >>> 3 | k << 5) ^ arrayOfChar[b]) & 0xFF;
        } 
      } 
      b[i] = (new String(arrayOfChar)).intern();
    } 
    return b[i];
  }
}


/* Location:              C:\Program Files\BurpSuitePro\burpsuite_pro.jar!\burp\Zmu6.class
 * Java compiler version: 21 (65.0)
 * JD-Core Version:       1.1.3
 */