package burp;

import java.math.BigInteger;

class Zmuo extends ClassLoader {
  static Object Zd;
  
  static String Zo;
  
  private static final String[] a;
  
  private static final String[] b;
  
  static void ZN(Object[] paramArrayOfObject, Object paramObject) throws Throwable {}
  
  static boolean ZO(Object[] paramArrayOfObject, Object paramObject) throws Throwable {
    // Byte code:
    //   0: invokestatic ZK : ()Z
    //   3: istore_2
    //   4: new java/lang/StringBuilder
    //   7: dup
    //   8: invokespecial <init> : ()V
    //   11: astore_3
    //   12: iconst_0
    //   13: istore #4
    //   15: iload #4
    //   17: bipush #32
    //   19: if_icmpge -> 1355
    //   22: iload #4
    //   24: tableswitch default -> 1348, 0 -> 168, 1 -> 205, 2 -> 242, 3 -> 279, 4 -> 316, 5 -> 353, 6 -> 390, 7 -> 427, 8 -> 464, 9 -> 501, 10 -> 538, 11 -> 575, 12 -> 612, 13 -> 649, 14 -> 686, 15 -> 723, 16 -> 760, 17 -> 797, 18 -> 834, 19 -> 871, 20 -> 908, 21 -> 945, 22 -> 982, 23 -> 1019, 24 -> 1056, 25 -> 1093, 26 -> 1130, 27 -> 1167, 28 -> 1204, 29 -> 1241, 30 -> 1278, 31 -> 1315
    //   168: aload_3
    //   169: getstatic burp/Zxyp.Z_ : Ljava/lang/String;
    //   172: getstatic burp/Zx54.Zn : Ljava/lang/Object;
    //   175: checkcast java/math/BigInteger
    //   178: invokevirtual intValue : ()I
    //   181: bipush #32
    //   183: irem
    //   184: invokestatic abs : (I)I
    //   187: invokevirtual charAt : (I)C
    //   190: invokevirtual append : (C)Ljava/lang/StringBuilder;
    //   193: pop
    //   194: iload_2
    //   195: ifeq -> 1348
    //   198: goto -> 205
    //   201: invokestatic a : (Ljava/lang/Throwable;)Ljava/lang/Throwable;
    //   204: athrow
    //   205: aload_3
    //   206: getstatic burp/Zl_k.Zw : Ljava/lang/String;
    //   209: getstatic burp/Zlhm.ZT : Ljava/lang/Object;
    //   212: checkcast java/math/BigInteger
    //   215: invokevirtual intValue : ()I
    //   218: bipush #32
    //   220: irem
    //   221: invokestatic abs : (I)I
    //   224: invokevirtual charAt : (I)C
    //   227: invokevirtual append : (C)Ljava/lang/StringBuilder;
    //   230: pop
    //   231: iload_2
    //   232: ifeq -> 1348
    //   235: goto -> 242
    //   238: invokestatic a : (Ljava/lang/Throwable;)Ljava/lang/Throwable;
    //   241: athrow
    //   242: aload_3
    //   243: getstatic burp/Zsxm.Zq : Ljava/lang/String;
    //   246: getstatic burp/Zter.Zc : Ljava/lang/Object;
    //   249: checkcast java/math/BigInteger
    //   252: invokevirtual intValue : ()I
    //   255: bipush #32
    //   257: irem
    //   258: invokestatic abs : (I)I
    //   261: invokevirtual charAt : (I)C
    //   264: invokevirtual append : (C)Ljava/lang/StringBuilder;
    //   267: pop
    //   268: iload_2
    //   269: ifeq -> 1348
    //   272: goto -> 279
    //   275: invokestatic a : (Ljava/lang/Throwable;)Ljava/lang/Throwable;
    //   278: athrow
    //   279: aload_3
    //   280: getstatic burp/Zxyp.Z_ : Ljava/lang/String;
    //   283: getstatic burp/Zsgl.Zn : Ljava/lang/Object;
    //   286: checkcast java/math/BigInteger
    //   289: invokevirtual intValue : ()I
    //   292: bipush #32
    //   294: irem
    //   295: invokestatic abs : (I)I
    //   298: invokevirtual charAt : (I)C
    //   301: invokevirtual append : (C)Ljava/lang/StringBuilder;
    //   304: pop
    //   305: iload_2
    //   306: ifeq -> 1348
    //   309: goto -> 316
    //   312: invokestatic a : (Ljava/lang/Throwable;)Ljava/lang/Throwable;
    //   315: athrow
    //   316: aload_3
    //   317: getstatic burp/Zxo6.Z_ : Ljava/lang/String;
    //   320: getstatic burp/Zxk9.ZI : Ljava/lang/Object;
    //   323: checkcast java/math/BigInteger
    //   326: invokevirtual intValue : ()I
    //   329: bipush #32
    //   331: irem
    //   332: invokestatic abs : (I)I
    //   335: invokevirtual charAt : (I)C
    //   338: invokevirtual append : (C)Ljava/lang/StringBuilder;
    //   341: pop
    //   342: iload_2
    //   343: ifeq -> 1348
    //   346: goto -> 353
    //   349: invokestatic a : (Ljava/lang/Throwable;)Ljava/lang/Throwable;
    //   352: athrow
    //   353: aload_3
    //   354: getstatic burp/Zxfu.Zo : Ljava/lang/String;
    //   357: getstatic burp/Zm0s.Zl : Ljava/lang/Object;
    //   360: checkcast java/math/BigInteger
    //   363: invokevirtual intValue : ()I
    //   366: bipush #32
    //   368: irem
    //   369: invokestatic abs : (I)I
    //   372: invokevirtual charAt : (I)C
    //   375: invokevirtual append : (C)Ljava/lang/StringBuilder;
    //   378: pop
    //   379: iload_2
    //   380: ifeq -> 1348
    //   383: goto -> 390
    //   386: invokestatic a : (Ljava/lang/Throwable;)Ljava/lang/Throwable;
    //   389: athrow
    //   390: aload_3
    //   391: getstatic burp/Zkmx.Zg : Ljava/lang/String;
    //   394: getstatic burp/Zg_p.Zx : Ljava/lang/Object;
    //   397: checkcast java/math/BigInteger
    //   400: invokevirtual intValue : ()I
    //   403: bipush #32
    //   405: irem
    //   406: invokestatic abs : (I)I
    //   409: invokevirtual charAt : (I)C
    //   412: invokevirtual append : (C)Ljava/lang/StringBuilder;
    //   415: pop
    //   416: iload_2
    //   417: ifeq -> 1348
    //   420: goto -> 427
    //   423: invokestatic a : (Ljava/lang/Throwable;)Ljava/lang/Throwable;
    //   426: athrow
    //   427: aload_3
    //   428: getstatic burp/Zg7p.ZA : Ljava/lang/String;
    //   431: getstatic burp/Zx54.Zn : Ljava/lang/Object;
    //   434: checkcast java/math/BigInteger
    //   437: invokevirtual intValue : ()I
    //   440: bipush #32
    //   442: irem
    //   443: invokestatic abs : (I)I
    //   446: invokevirtual charAt : (I)C
    //   449: invokevirtual append : (C)Ljava/lang/StringBuilder;
    //   452: pop
    //   453: iload_2
    //   454: ifeq -> 1348
    //   457: goto -> 464
    //   460: invokestatic a : (Ljava/lang/Throwable;)Ljava/lang/Throwable;
    //   463: athrow
    //   464: aload_3
    //   465: getstatic burp/Zsm3.Zl : Ljava/lang/String;
    //   468: getstatic burp/Zr0g.Zj : Ljava/lang/Object;
    //   471: checkcast java/math/BigInteger
    //   474: invokevirtual intValue : ()I
    //   477: bipush #32
    //   479: irem
    //   480: invokestatic abs : (I)I
    //   483: invokevirtual charAt : (I)C
    //   486: invokevirtual append : (C)Ljava/lang/StringBuilder;
    //   489: pop
    //   490: iload_2
    //   491: ifeq -> 1348
    //   494: goto -> 501
    //   497: invokestatic a : (Ljava/lang/Throwable;)Ljava/lang/Throwable;
    //   500: athrow
    //   501: aload_3
    //   502: getstatic burp/Zkbf.Zv : Ljava/lang/String;
    //   505: getstatic burp/Zxso.ZF : Ljava/lang/Object;
    //   508: checkcast java/math/BigInteger
    //   511: invokevirtual intValue : ()I
    //   514: bipush #32
    //   516: irem
    //   517: invokestatic abs : (I)I
    //   520: invokevirtual charAt : (I)C
    //   523: invokevirtual append : (C)Ljava/lang/StringBuilder;
    //   526: pop
    //   527: iload_2
    //   528: ifeq -> 1348
    //   531: goto -> 538
    //   534: invokestatic a : (Ljava/lang/Throwable;)Ljava/lang/Throwable;
    //   537: athrow
    //   538: aload_3
    //   539: getstatic burp/Zzsq.Zc : Ljava/lang/String;
    //   542: getstatic burp/Zzsq.Zh : Ljava/lang/Object;
    //   545: checkcast java/math/BigInteger
    //   548: invokevirtual intValue : ()I
    //   551: bipush #32
    //   553: irem
    //   554: invokestatic abs : (I)I
    //   557: invokevirtual charAt : (I)C
    //   560: invokevirtual append : (C)Ljava/lang/StringBuilder;
    //   563: pop
    //   564: iload_2
    //   565: ifeq -> 1348
    //   568: goto -> 575
    //   571: invokestatic a : (Ljava/lang/Throwable;)Ljava/lang/Throwable;
    //   574: athrow
    //   575: aload_3
    //   576: getstatic burp/Zedz.Zh : Ljava/lang/String;
    //   579: getstatic burp/Zr8h.ZH : Ljava/lang/Object;
    //   582: checkcast java/math/BigInteger
    //   585: invokevirtual intValue : ()I
    //   588: bipush #32
    //   590: irem
    //   591: invokestatic abs : (I)I
    //   594: invokevirtual charAt : (I)C
    //   597: invokevirtual append : (C)Ljava/lang/StringBuilder;
    //   600: pop
    //   601: iload_2
    //   602: ifeq -> 1348
    //   605: goto -> 612
    //   608: invokestatic a : (Ljava/lang/Throwable;)Ljava/lang/Throwable;
    //   611: athrow
    //   612: aload_3
    //   613: getstatic burp/Zshq.Zi : Ljava/lang/String;
    //   616: getstatic burp/Ztuj.Ze : Ljava/lang/Object;
    //   619: checkcast java/math/BigInteger
    //   622: invokevirtual intValue : ()I
    //   625: bipush #32
    //   627: irem
    //   628: invokestatic abs : (I)I
    //   631: invokevirtual charAt : (I)C
    //   634: invokevirtual append : (C)Ljava/lang/StringBuilder;
    //   637: pop
    //   638: iload_2
    //   639: ifeq -> 1348
    //   642: goto -> 649
    //   645: invokestatic a : (Ljava/lang/Throwable;)Ljava/lang/Throwable;
    //   648: athrow
    //   649: aload_3
    //   650: getstatic burp/Zkbm.Zb : Ljava/lang/String;
    //   653: getstatic burp/Zk9s.ZY : Ljava/lang/Object;
    //   656: checkcast java/math/BigInteger
    //   659: invokevirtual intValue : ()I
    //   662: bipush #32
    //   664: irem
    //   665: invokestatic abs : (I)I
    //   668: invokevirtual charAt : (I)C
    //   671: invokevirtual append : (C)Ljava/lang/StringBuilder;
    //   674: pop
    //   675: iload_2
    //   676: ifeq -> 1348
    //   679: goto -> 686
    //   682: invokestatic a : (Ljava/lang/Throwable;)Ljava/lang/Throwable;
    //   685: athrow
    //   686: aload_3
    //   687: getstatic burp/Zm__.Zf : Ljava/lang/String;
    //   690: getstatic burp/Zx54.Zn : Ljava/lang/Object;
    //   693: checkcast java/math/BigInteger
    //   696: invokevirtual intValue : ()I
    //   699: bipush #32
    //   701: irem
    //   702: invokestatic abs : (I)I
    //   705: invokevirtual charAt : (I)C
    //   708: invokevirtual append : (C)Ljava/lang/StringBuilder;
    //   711: pop
    //   712: iload_2
    //   713: ifeq -> 1348
    //   716: goto -> 723
    //   719: invokestatic a : (Ljava/lang/Throwable;)Ljava/lang/Throwable;
    //   722: athrow
    //   723: aload_3
    //   724: getstatic burp/Zg7z.Zf : Ljava/lang/String;
    //   727: getstatic burp/Zxo6.Zw : Ljava/lang/Object;
    //   730: checkcast java/math/BigInteger
    //   733: invokevirtual intValue : ()I
    //   736: bipush #32
    //   738: irem
    //   739: invokestatic abs : (I)I
    //   742: invokevirtual charAt : (I)C
    //   745: invokevirtual append : (C)Ljava/lang/StringBuilder;
    //   748: pop
    //   749: iload_2
    //   750: ifeq -> 1348
    //   753: goto -> 760
    //   756: invokestatic a : (Ljava/lang/Throwable;)Ljava/lang/Throwable;
    //   759: athrow
    //   760: aload_3
    //   761: getstatic burp/Zgw0.ZL : Ljava/lang/String;
    //   764: getstatic burp/Zgw0.ZM : Ljava/lang/Object;
    //   767: checkcast java/math/BigInteger
    //   770: invokevirtual intValue : ()I
    //   773: bipush #32
    //   775: irem
    //   776: invokestatic abs : (I)I
    //   779: invokevirtual charAt : (I)C
    //   782: invokevirtual append : (C)Ljava/lang/StringBuilder;
    //   785: pop
    //   786: iload_2
    //   787: ifeq -> 1348
    //   790: goto -> 797
    //   793: invokestatic a : (Ljava/lang/Throwable;)Ljava/lang/Throwable;
    //   796: athrow
    //   797: aload_3
    //   798: getstatic burp/Zg7p.ZA : Ljava/lang/String;
    //   801: getstatic burp/Zx4w.Zp : Ljava/lang/Object;
    //   804: checkcast java/math/BigInteger
    //   807: invokevirtual intValue : ()I
    //   810: bipush #32
    //   812: irem
    //   813: invokestatic abs : (I)I
    //   816: invokevirtual charAt : (I)C
    //   819: invokevirtual append : (C)Ljava/lang/StringBuilder;
    //   822: pop
    //   823: iload_2
    //   824: ifeq -> 1348
    //   827: goto -> 834
    //   830: invokestatic a : (Ljava/lang/Throwable;)Ljava/lang/Throwable;
    //   833: athrow
    //   834: aload_3
    //   835: getstatic burp/Zx4w.Zo : Ljava/lang/String;
    //   838: getstatic burp/Zgmt.ZX : Ljava/lang/Object;
    //   841: checkcast java/math/BigInteger
    //   844: invokevirtual intValue : ()I
    //   847: bipush #32
    //   849: irem
    //   850: invokestatic abs : (I)I
    //   853: invokevirtual charAt : (I)C
    //   856: invokevirtual append : (C)Ljava/lang/StringBuilder;
    //   859: pop
    //   860: iload_2
    //   861: ifeq -> 1348
    //   864: goto -> 871
    //   867: invokestatic a : (Ljava/lang/Throwable;)Ljava/lang/Throwable;
    //   870: athrow
    //   871: aload_3
    //   872: getstatic burp/Zrbp.Ze : Ljava/lang/String;
    //   875: getstatic burp/Zgmt.ZX : Ljava/lang/Object;
    //   878: checkcast java/math/BigInteger
    //   881: invokevirtual intValue : ()I
    //   884: bipush #32
    //   886: irem
    //   887: invokestatic abs : (I)I
    //   890: invokevirtual charAt : (I)C
    //   893: invokevirtual append : (C)Ljava/lang/StringBuilder;
    //   896: pop
    //   897: iload_2
    //   898: ifeq -> 1348
    //   901: goto -> 908
    //   904: invokestatic a : (Ljava/lang/Throwable;)Ljava/lang/Throwable;
    //   907: athrow
    //   908: aload_3
    //   909: getstatic burp/Zer.Zp : Ljava/lang/String;
    //   912: getstatic burp/Zgmt.ZX : Ljava/lang/Object;
    //   915: checkcast java/math/BigInteger
    //   918: invokevirtual intValue : ()I
    //   921: bipush #32
    //   923: irem
    //   924: invokestatic abs : (I)I
    //   927: invokevirtual charAt : (I)C
    //   930: invokevirtual append : (C)Ljava/lang/StringBuilder;
    //   933: pop
    //   934: iload_2
    //   935: ifeq -> 1348
    //   938: goto -> 945
    //   941: invokestatic a : (Ljava/lang/Throwable;)Ljava/lang/Throwable;
    //   944: athrow
    //   945: aload_3
    //   946: getstatic burp/Zm0s.Zm : Ljava/lang/String;
    //   949: getstatic burp/Zzqj.Zq : Ljava/lang/Object;
    //   952: checkcast java/math/BigInteger
    //   955: invokevirtual intValue : ()I
    //   958: bipush #32
    //   960: irem
    //   961: invokestatic abs : (I)I
    //   964: invokevirtual charAt : (I)C
    //   967: invokevirtual append : (C)Ljava/lang/StringBuilder;
    //   970: pop
    //   971: iload_2
    //   972: ifeq -> 1348
    //   975: goto -> 982
    //   978: invokestatic a : (Ljava/lang/Throwable;)Ljava/lang/Throwable;
    //   981: athrow
    //   982: aload_3
    //   983: getstatic burp/Zr0g.Zf : Ljava/lang/String;
    //   986: getstatic burp/Zsm3.ZC : Ljava/lang/Object;
    //   989: checkcast java/math/BigInteger
    //   992: invokevirtual intValue : ()I
    //   995: bipush #32
    //   997: irem
    //   998: invokestatic abs : (I)I
    //   1001: invokevirtual charAt : (I)C
    //   1004: invokevirtual append : (C)Ljava/lang/StringBuilder;
    //   1007: pop
    //   1008: iload_2
    //   1009: ifeq -> 1348
    //   1012: goto -> 1019
    //   1015: invokestatic a : (Ljava/lang/Throwable;)Ljava/lang/Throwable;
    //   1018: athrow
    //   1019: aload_3
    //   1020: getstatic burp/Zkfz.Zs : Ljava/lang/String;
    //   1023: getstatic burp/Zl_k.ZH : Ljava/lang/Object;
    //   1026: checkcast java/math/BigInteger
    //   1029: invokevirtual intValue : ()I
    //   1032: bipush #32
    //   1034: irem
    //   1035: invokestatic abs : (I)I
    //   1038: invokevirtual charAt : (I)C
    //   1041: invokevirtual append : (C)Ljava/lang/StringBuilder;
    //   1044: pop
    //   1045: iload_2
    //   1046: ifeq -> 1348
    //   1049: goto -> 1056
    //   1052: invokestatic a : (Ljava/lang/Throwable;)Ljava/lang/Throwable;
    //   1055: athrow
    //   1056: aload_3
    //   1057: getstatic burp/Zkfz.Zs : Ljava/lang/String;
    //   1060: getstatic burp/Ze13.ZD : Ljava/lang/Object;
    //   1063: checkcast java/math/BigInteger
    //   1066: invokevirtual intValue : ()I
    //   1069: bipush #32
    //   1071: irem
    //   1072: invokestatic abs : (I)I
    //   1075: invokevirtual charAt : (I)C
    //   1078: invokevirtual append : (C)Ljava/lang/StringBuilder;
    //   1081: pop
    //   1082: iload_2
    //   1083: ifeq -> 1348
    //   1086: goto -> 1093
    //   1089: invokestatic a : (Ljava/lang/Throwable;)Ljava/lang/Throwable;
    //   1092: athrow
    //   1093: aload_3
    //   1094: getstatic burp/Zr3q.ZM : Ljava/lang/String;
    //   1097: getstatic burp/Zsm3.ZC : Ljava/lang/Object;
    //   1100: checkcast java/math/BigInteger
    //   1103: invokevirtual intValue : ()I
    //   1106: bipush #32
    //   1108: irem
    //   1109: invokestatic abs : (I)I
    //   1112: invokevirtual charAt : (I)C
    //   1115: invokevirtual append : (C)Ljava/lang/StringBuilder;
    //   1118: pop
    //   1119: iload_2
    //   1120: ifeq -> 1348
    //   1123: goto -> 1130
    //   1126: invokestatic a : (Ljava/lang/Throwable;)Ljava/lang/Throwable;
    //   1129: athrow
    //   1130: aload_3
    //   1131: getstatic burp/Zxso.ZH : Ljava/lang/String;
    //   1134: getstatic burp/Zbsr.ZD : Ljava/lang/Object;
    //   1137: checkcast java/math/BigInteger
    //   1140: invokevirtual intValue : ()I
    //   1143: bipush #32
    //   1145: irem
    //   1146: invokestatic abs : (I)I
    //   1149: invokevirtual charAt : (I)C
    //   1152: invokevirtual append : (C)Ljava/lang/StringBuilder;
    //   1155: pop
    //   1156: iload_2
    //   1157: ifeq -> 1348
    //   1160: goto -> 1167
    //   1163: invokestatic a : (Ljava/lang/Throwable;)Ljava/lang/Throwable;
    //   1166: athrow
    //   1167: aload_3
    //   1168: getstatic burp/Zsde.Zi : Ljava/lang/String;
    //   1171: getstatic burp/Zlv6.ZN : Ljava/lang/Object;
    //   1174: checkcast java/math/BigInteger
    //   1177: invokevirtual intValue : ()I
    //   1180: bipush #32
    //   1182: irem
    //   1183: invokestatic abs : (I)I
    //   1186: invokevirtual charAt : (I)C
    //   1189: invokevirtual append : (C)Ljava/lang/StringBuilder;
    //   1192: pop
    //   1193: iload_2
    //   1194: ifeq -> 1348
    //   1197: goto -> 1204
    //   1200: invokestatic a : (Ljava/lang/Throwable;)Ljava/lang/Throwable;
    //   1203: athrow
    //   1204: aload_3
    //   1205: getstatic burp/Zk8b.ZT : Ljava/lang/String;
    //   1208: getstatic burp/Zl_u.ZR : Ljava/lang/Object;
    //   1211: checkcast java/math/BigInteger
    //   1214: invokevirtual intValue : ()I
    //   1217: bipush #32
    //   1219: irem
    //   1220: invokestatic abs : (I)I
    //   1223: invokevirtual charAt : (I)C
    //   1226: invokevirtual append : (C)Ljava/lang/StringBuilder;
    //   1229: pop
    //   1230: iload_2
    //   1231: ifeq -> 1348
    //   1234: goto -> 1241
    //   1237: invokestatic a : (Ljava/lang/Throwable;)Ljava/lang/Throwable;
    //   1240: athrow
    //   1241: aload_3
    //   1242: getstatic burp/Zbp.Z_ : Ljava/lang/String;
    //   1245: getstatic burp/Zt3l.Zq : Ljava/lang/Object;
    //   1248: checkcast java/math/BigInteger
    //   1251: invokevirtual intValue : ()I
    //   1254: bipush #32
    //   1256: irem
    //   1257: invokestatic abs : (I)I
    //   1260: invokevirtual charAt : (I)C
    //   1263: invokevirtual append : (C)Ljava/lang/StringBuilder;
    //   1266: pop
    //   1267: iload_2
    //   1268: ifeq -> 1348
    //   1271: goto -> 1278
    //   1274: invokestatic a : (Ljava/lang/Throwable;)Ljava/lang/Throwable;
    //   1277: athrow
    //   1278: aload_3
    //   1279: getstatic burp/Zt3l.Zi : Ljava/lang/String;
    //   1282: getstatic burp/Zg0j.ZV : Ljava/lang/Object;
    //   1285: checkcast java/math/BigInteger
    //   1288: invokevirtual intValue : ()I
    //   1291: bipush #32
    //   1293: irem
    //   1294: invokestatic abs : (I)I
    //   1297: invokevirtual charAt : (I)C
    //   1300: invokevirtual append : (C)Ljava/lang/StringBuilder;
    //   1303: pop
    //   1304: iload_2
    //   1305: ifeq -> 1348
    //   1308: goto -> 1315
    //   1311: invokestatic a : (Ljava/lang/Throwable;)Ljava/lang/Throwable;
    //   1314: athrow
    //   1315: aload_3
    //   1316: getstatic burp/Zzap.ZA : Ljava/lang/String;
    //   1319: getstatic burp/Zzk9.ZK : Ljava/lang/Object;
    //   1322: checkcast java/math/BigInteger
    //   1325: invokevirtual intValue : ()I
    //   1328: bipush #32
    //   1330: irem
    //   1331: invokestatic abs : (I)I
    //   1334: invokevirtual charAt : (I)C
    //   1337: invokevirtual append : (C)Ljava/lang/StringBuilder;
    //   1340: pop
    //   1341: goto -> 1348
    //   1344: invokestatic a : (Ljava/lang/Throwable;)Ljava/lang/Throwable;
    //   1347: athrow
    //   1348: iinc #4, 1
    //   1351: iload_2
    //   1352: ifeq -> 15
    //   1355: new java/lang/StringBuilder
    //   1358: dup
    //   1359: invokespecial <init> : ()V
    //   1362: astore #4
    //   1364: iconst_0
    //   1365: istore #5
    //   1367: iload #5
    //   1369: bipush #32
    //   1371: if_icmpge -> 2635
    //   1374: iload #5
    //   1376: tableswitch default -> 2631, 0 -> 1520, 1 -> 1554, 2 -> 1588, 3 -> 1622, 4 -> 1656, 5 -> 1690, 6 -> 1725, 7 -> 1760, 8 -> 1795, 9 -> 1830, 10 -> 1865, 11 -> 1900, 12 -> 1935, 13 -> 1970, 14 -> 2005, 15 -> 2040, 16 -> 2075, 17 -> 2110, 18 -> 2145, 19 -> 2180, 20 -> 2215, 21 -> 2250, 22 -> 2285, 23 -> 2320, 24 -> 2355, 25 -> 2390, 26 -> 2425, 27 -> 2460, 28 -> 2495, 29 -> 2530, 30 -> 2565, 31 -> 2600
    //   1520: aload #4
    //   1522: getstatic burp/Zmhi.ZQ : Ljava/lang/String;
    //   1525: getstatic burp/Zgpp.Zt : Ljava/lang/Object;
    //   1528: checkcast java/math/BigInteger
    //   1531: invokevirtual intValue : ()I
    //   1534: bipush #32
    //   1536: irem
    //   1537: invokestatic abs : (I)I
    //   1540: invokevirtual charAt : (I)C
    //   1543: invokevirtual append : (C)Ljava/lang/StringBuilder;
    //   1546: pop
    //   1547: iconst_1
    //   1548: istore #5
    //   1550: iload_2
    //   1551: ifeq -> 2631
    //   1554: aload #4
    //   1556: getstatic burp/Zm7x.ZP : Ljava/lang/String;
    //   1559: getstatic burp/Zrpu.Zi : Ljava/lang/Object;
    //   1562: checkcast java/math/BigInteger
    //   1565: invokevirtual intValue : ()I
    //   1568: bipush #32
    //   1570: irem
    //   1571: invokestatic abs : (I)I
    //   1574: invokevirtual charAt : (I)C
    //   1577: invokevirtual append : (C)Ljava/lang/StringBuilder;
    //   1580: pop
    //   1581: iconst_2
    //   1582: istore #5
    //   1584: iload_2
    //   1585: ifeq -> 2631
    //   1588: aload #4
    //   1590: getstatic burp/Zs8q.Zs : Ljava/lang/String;
    //   1593: getstatic burp/Zlrm.ZM : Ljava/lang/Object;
    //   1596: checkcast java/math/BigInteger
    //   1599: invokevirtual intValue : ()I
    //   1602: bipush #32
    //   1604: irem
    //   1605: invokestatic abs : (I)I
    //   1608: invokevirtual charAt : (I)C
    //   1611: invokevirtual append : (C)Ljava/lang/StringBuilder;
    //   1614: pop
    //   1615: iconst_3
    //   1616: istore #5
    //   1618: iload_2
    //   1619: ifeq -> 2631
    //   1622: aload #4
    //   1624: getstatic burp/Zzym.Zj : Ljava/lang/String;
    //   1627: getstatic burp/Zt98.Zz : Ljava/lang/Object;
    //   1630: checkcast java/math/BigInteger
    //   1633: invokevirtual intValue : ()I
    //   1636: bipush #32
    //   1638: irem
    //   1639: invokestatic abs : (I)I
    //   1642: invokevirtual charAt : (I)C
    //   1645: invokevirtual append : (C)Ljava/lang/StringBuilder;
    //   1648: pop
    //   1649: iconst_4
    //   1650: istore #5
    //   1652: iload_2
    //   1653: ifeq -> 2631
    //   1656: aload #4
    //   1658: getstatic burp/Zgqi.Zv : Ljava/lang/String;
    //   1661: getstatic burp/Ztj5.Zj : Ljava/lang/Object;
    //   1664: checkcast java/math/BigInteger
    //   1667: invokevirtual intValue : ()I
    //   1670: bipush #32
    //   1672: irem
    //   1673: invokestatic abs : (I)I
    //   1676: invokevirtual charAt : (I)C
    //   1679: invokevirtual append : (C)Ljava/lang/StringBuilder;
    //   1682: pop
    //   1683: iconst_5
    //   1684: istore #5
    //   1686: iload_2
    //   1687: ifeq -> 2631
    //   1690: aload #4
    //   1692: getstatic burp/Zm8v.Zl : Ljava/lang/String;
    //   1695: getstatic burp/Ztye.ZK : Ljava/lang/Object;
    //   1698: checkcast java/math/BigInteger
    //   1701: invokevirtual intValue : ()I
    //   1704: bipush #32
    //   1706: irem
    //   1707: invokestatic abs : (I)I
    //   1710: invokevirtual charAt : (I)C
    //   1713: invokevirtual append : (C)Ljava/lang/StringBuilder;
    //   1716: pop
    //   1717: bipush #6
    //   1719: istore #5
    //   1721: iload_2
    //   1722: ifeq -> 2631
    //   1725: aload #4
    //   1727: getstatic burp/Zkm0.ZL : Ljava/lang/String;
    //   1730: getstatic burp/Zsxo.Za : Ljava/lang/Object;
    //   1733: checkcast java/math/BigInteger
    //   1736: invokevirtual intValue : ()I
    //   1739: bipush #32
    //   1741: irem
    //   1742: invokestatic abs : (I)I
    //   1745: invokevirtual charAt : (I)C
    //   1748: invokevirtual append : (C)Ljava/lang/StringBuilder;
    //   1751: pop
    //   1752: bipush #7
    //   1754: istore #5
    //   1756: iload_2
    //   1757: ifeq -> 2631
    //   1760: aload #4
    //   1762: getstatic burp/Zxe.ZD : Ljava/lang/String;
    //   1765: getstatic burp/Ze82.ZR : Ljava/lang/Object;
    //   1768: checkcast java/math/BigInteger
    //   1771: invokevirtual intValue : ()I
    //   1774: bipush #32
    //   1776: irem
    //   1777: invokestatic abs : (I)I
    //   1780: invokevirtual charAt : (I)C
    //   1783: invokevirtual append : (C)Ljava/lang/StringBuilder;
    //   1786: pop
    //   1787: bipush #8
    //   1789: istore #5
    //   1791: iload_2
    //   1792: ifeq -> 2631
    //   1795: aload #4
    //   1797: getstatic burp/Zs34.Zq : Ljava/lang/String;
    //   1800: getstatic burp/Ze54.Zx : Ljava/lang/Object;
    //   1803: checkcast java/math/BigInteger
    //   1806: invokevirtual intValue : ()I
    //   1809: bipush #32
    //   1811: irem
    //   1812: invokestatic abs : (I)I
    //   1815: invokevirtual charAt : (I)C
    //   1818: invokevirtual append : (C)Ljava/lang/StringBuilder;
    //   1821: pop
    //   1822: bipush #9
    //   1824: istore #5
    //   1826: iload_2
    //   1827: ifeq -> 2631
    //   1830: aload #4
    //   1832: getstatic burp/Ze69.ZA : Ljava/lang/String;
    //   1835: getstatic burp/Zm4i.Zr : Ljava/lang/Object;
    //   1838: checkcast java/math/BigInteger
    //   1841: invokevirtual intValue : ()I
    //   1844: bipush #32
    //   1846: irem
    //   1847: invokestatic abs : (I)I
    //   1850: invokevirtual charAt : (I)C
    //   1853: invokevirtual append : (C)Ljava/lang/StringBuilder;
    //   1856: pop
    //   1857: bipush #10
    //   1859: istore #5
    //   1861: iload_2
    //   1862: ifeq -> 2631
    //   1865: aload #4
    //   1867: getstatic burp/Zgnp.ZL : Ljava/lang/String;
    //   1870: getstatic burp/Zzox.Zq : Ljava/lang/Object;
    //   1873: checkcast java/math/BigInteger
    //   1876: invokevirtual intValue : ()I
    //   1879: bipush #32
    //   1881: irem
    //   1882: invokestatic abs : (I)I
    //   1885: invokevirtual charAt : (I)C
    //   1888: invokevirtual append : (C)Ljava/lang/StringBuilder;
    //   1891: pop
    //   1892: bipush #11
    //   1894: istore #5
    //   1896: iload_2
    //   1897: ifeq -> 2631
    //   1900: aload #4
    //   1902: getstatic burp/Zm8w.ZL : Ljava/lang/String;
    //   1905: getstatic burp/Zt98.Zz : Ljava/lang/Object;
    //   1908: checkcast java/math/BigInteger
    //   1911: invokevirtual intValue : ()I
    //   1914: bipush #32
    //   1916: irem
    //   1917: invokestatic abs : (I)I
    //   1920: invokevirtual charAt : (I)C
    //   1923: invokevirtual append : (C)Ljava/lang/StringBuilder;
    //   1926: pop
    //   1927: bipush #12
    //   1929: istore #5
    //   1931: iload_2
    //   1932: ifeq -> 2631
    //   1935: aload #4
    //   1937: getstatic burp/Zest.Zd : Ljava/lang/String;
    //   1940: getstatic burp/Ztex.Z_ : Ljava/lang/Object;
    //   1943: checkcast java/math/BigInteger
    //   1946: invokevirtual intValue : ()I
    //   1949: bipush #32
    //   1951: irem
    //   1952: invokestatic abs : (I)I
    //   1955: invokevirtual charAt : (I)C
    //   1958: invokevirtual append : (C)Ljava/lang/StringBuilder;
    //   1961: pop
    //   1962: bipush #13
    //   1964: istore #5
    //   1966: iload_2
    //   1967: ifeq -> 2631
    //   1970: aload #4
    //   1972: getstatic burp/Zlf0.ZS : Ljava/lang/String;
    //   1975: getstatic burp/Zrpu.Zi : Ljava/lang/Object;
    //   1978: checkcast java/math/BigInteger
    //   1981: invokevirtual intValue : ()I
    //   1984: bipush #32
    //   1986: irem
    //   1987: invokestatic abs : (I)I
    //   1990: invokevirtual charAt : (I)C
    //   1993: invokevirtual append : (C)Ljava/lang/StringBuilder;
    //   1996: pop
    //   1997: bipush #14
    //   1999: istore #5
    //   2001: iload_2
    //   2002: ifeq -> 2631
    //   2005: aload #4
    //   2007: getstatic burp/Ztkh.ZP : Ljava/lang/String;
    //   2010: getstatic burp/Ze54.Zx : Ljava/lang/Object;
    //   2013: checkcast java/math/BigInteger
    //   2016: invokevirtual intValue : ()I
    //   2019: bipush #32
    //   2021: irem
    //   2022: invokestatic abs : (I)I
    //   2025: invokevirtual charAt : (I)C
    //   2028: invokevirtual append : (C)Ljava/lang/StringBuilder;
    //   2031: pop
    //   2032: bipush #15
    //   2034: istore #5
    //   2036: iload_2
    //   2037: ifeq -> 2631
    //   2040: aload #4
    //   2042: getstatic burp/Zrcy.Zq : Ljava/lang/String;
    //   2045: getstatic burp/Zgq_.ZM : Ljava/lang/Object;
    //   2048: checkcast java/math/BigInteger
    //   2051: invokevirtual intValue : ()I
    //   2054: bipush #32
    //   2056: irem
    //   2057: invokestatic abs : (I)I
    //   2060: invokevirtual charAt : (I)C
    //   2063: invokevirtual append : (C)Ljava/lang/StringBuilder;
    //   2066: pop
    //   2067: bipush #16
    //   2069: istore #5
    //   2071: iload_2
    //   2072: ifeq -> 2631
    //   2075: aload #4
    //   2077: getstatic burp/Zkjr.Zg : Ljava/lang/String;
    //   2080: getstatic burp/Ztj5.Zj : Ljava/lang/Object;
    //   2083: checkcast java/math/BigInteger
    //   2086: invokevirtual intValue : ()I
    //   2089: bipush #32
    //   2091: irem
    //   2092: invokestatic abs : (I)I
    //   2095: invokevirtual charAt : (I)C
    //   2098: invokevirtual append : (C)Ljava/lang/StringBuilder;
    //   2101: pop
    //   2102: bipush #17
    //   2104: istore #5
    //   2106: iload_2
    //   2107: ifeq -> 2631
    //   2110: aload #4
    //   2112: getstatic burp/Zv8c.ZO : Ljava/lang/String;
    //   2115: getstatic burp/Zs8y.ZG : Ljava/lang/Object;
    //   2118: checkcast java/math/BigInteger
    //   2121: invokevirtual intValue : ()I
    //   2124: bipush #32
    //   2126: irem
    //   2127: invokestatic abs : (I)I
    //   2130: invokevirtual charAt : (I)C
    //   2133: invokevirtual append : (C)Ljava/lang/StringBuilder;
    //   2136: pop
    //   2137: bipush #18
    //   2139: istore #5
    //   2141: iload_2
    //   2142: ifeq -> 2631
    //   2145: aload #4
    //   2147: getstatic burp/Zmj8.ZL : Ljava/lang/String;
    //   2150: getstatic burp/Zg_5.ZA : Ljava/lang/Object;
    //   2153: checkcast java/math/BigInteger
    //   2156: invokevirtual intValue : ()I
    //   2159: bipush #32
    //   2161: irem
    //   2162: invokestatic abs : (I)I
    //   2165: invokevirtual charAt : (I)C
    //   2168: invokevirtual append : (C)Ljava/lang/StringBuilder;
    //   2171: pop
    //   2172: bipush #19
    //   2174: istore #5
    //   2176: iload_2
    //   2177: ifeq -> 2631
    //   2180: aload #4
    //   2182: getstatic burp/Zm4i.Zl : Ljava/lang/String;
    //   2185: getstatic burp/Zlo5.Zf : Ljava/lang/Object;
    //   2188: checkcast java/math/BigInteger
    //   2191: invokevirtual intValue : ()I
    //   2194: bipush #32
    //   2196: irem
    //   2197: invokestatic abs : (I)I
    //   2200: invokevirtual charAt : (I)C
    //   2203: invokevirtual append : (C)Ljava/lang/StringBuilder;
    //   2206: pop
    //   2207: bipush #20
    //   2209: istore #5
    //   2211: iload_2
    //   2212: ifeq -> 2631
    //   2215: aload #4
    //   2217: getstatic burp/Zz20.ZX : Ljava/lang/String;
    //   2220: getstatic burp/Zz2e.Zm : Ljava/lang/Object;
    //   2223: checkcast java/math/BigInteger
    //   2226: invokevirtual intValue : ()I
    //   2229: bipush #32
    //   2231: irem
    //   2232: invokestatic abs : (I)I
    //   2235: invokevirtual charAt : (I)C
    //   2238: invokevirtual append : (C)Ljava/lang/StringBuilder;
    //   2241: pop
    //   2242: bipush #21
    //   2244: istore #5
    //   2246: iload_2
    //   2247: ifeq -> 2631
    //   2250: aload #4
    //   2252: getstatic burp/Zrtv.ZA : Ljava/lang/String;
    //   2255: getstatic burp/Zess.Zj : Ljava/lang/Object;
    //   2258: checkcast java/math/BigInteger
    //   2261: invokevirtual intValue : ()I
    //   2264: bipush #32
    //   2266: irem
    //   2267: invokestatic abs : (I)I
    //   2270: invokevirtual charAt : (I)C
    //   2273: invokevirtual append : (C)Ljava/lang/StringBuilder;
    //   2276: pop
    //   2277: bipush #22
    //   2279: istore #5
    //   2281: iload_2
    //   2282: ifeq -> 2631
    //   2285: aload #4
    //   2287: getstatic burp/Zz2e.ZS : Ljava/lang/String;
    //   2290: getstatic burp/Ztfh.Zo : Ljava/lang/Object;
    //   2293: checkcast java/math/BigInteger
    //   2296: invokevirtual intValue : ()I
    //   2299: bipush #32
    //   2301: irem
    //   2302: invokestatic abs : (I)I
    //   2305: invokevirtual charAt : (I)C
    //   2308: invokevirtual append : (C)Ljava/lang/StringBuilder;
    //   2311: pop
    //   2312: bipush #23
    //   2314: istore #5
    //   2316: iload_2
    //   2317: ifeq -> 2631
    //   2320: aload #4
    //   2322: getstatic burp/Zlrm.Zt : Ljava/lang/String;
    //   2325: getstatic burp/Zrcy.Zr : Ljava/lang/Object;
    //   2328: checkcast java/math/BigInteger
    //   2331: invokevirtual intValue : ()I
    //   2334: bipush #32
    //   2336: irem
    //   2337: invokestatic abs : (I)I
    //   2340: invokevirtual charAt : (I)C
    //   2343: invokevirtual append : (C)Ljava/lang/StringBuilder;
    //   2346: pop
    //   2347: bipush #24
    //   2349: istore #5
    //   2351: iload_2
    //   2352: ifeq -> 2631
    //   2355: aload #4
    //   2357: getstatic burp/Zs8y.Zr : Ljava/lang/String;
    //   2360: getstatic burp/Zs83.ZT : Ljava/lang/Object;
    //   2363: checkcast java/math/BigInteger
    //   2366: invokevirtual intValue : ()I
    //   2369: bipush #32
    //   2371: irem
    //   2372: invokestatic abs : (I)I
    //   2375: invokevirtual charAt : (I)C
    //   2378: invokevirtual append : (C)Ljava/lang/StringBuilder;
    //   2381: pop
    //   2382: bipush #25
    //   2384: istore #5
    //   2386: iload_2
    //   2387: ifeq -> 2631
    //   2390: aload #4
    //   2392: getstatic burp/Zef0.ZR : Ljava/lang/String;
    //   2395: getstatic burp/Zqp.ZA : Ljava/lang/Object;
    //   2398: checkcast java/math/BigInteger
    //   2401: invokevirtual intValue : ()I
    //   2404: bipush #32
    //   2406: irem
    //   2407: invokestatic abs : (I)I
    //   2410: invokevirtual charAt : (I)C
    //   2413: invokevirtual append : (C)Ljava/lang/StringBuilder;
    //   2416: pop
    //   2417: bipush #26
    //   2419: istore #5
    //   2421: iload_2
    //   2422: ifeq -> 2631
    //   2425: aload #4
    //   2427: getstatic burp/Zzr5.Zg : Ljava/lang/String;
    //   2430: getstatic burp/Zg6f.Zl : Ljava/lang/Object;
    //   2433: checkcast java/math/BigInteger
    //   2436: invokevirtual intValue : ()I
    //   2439: bipush #32
    //   2441: irem
    //   2442: invokestatic abs : (I)I
    //   2445: invokevirtual charAt : (I)C
    //   2448: invokevirtual append : (C)Ljava/lang/StringBuilder;
    //   2451: pop
    //   2452: bipush #27
    //   2454: istore #5
    //   2456: iload_2
    //   2457: ifeq -> 2631
    //   2460: aload #4
    //   2462: getstatic burp/Zkc8.Za : Ljava/lang/String;
    //   2465: getstatic burp/Zeqg.Zm : Ljava/lang/Object;
    //   2468: checkcast java/math/BigInteger
    //   2471: invokevirtual intValue : ()I
    //   2474: bipush #32
    //   2476: irem
    //   2477: invokestatic abs : (I)I
    //   2480: invokevirtual charAt : (I)C
    //   2483: invokevirtual append : (C)Ljava/lang/StringBuilder;
    //   2486: pop
    //   2487: bipush #28
    //   2489: istore #5
    //   2491: iload_2
    //   2492: ifeq -> 2631
    //   2495: aload #4
    //   2497: getstatic burp/Zel.Zi : Ljava/lang/String;
    //   2500: getstatic burp/Ztj5.Zj : Ljava/lang/Object;
    //   2503: checkcast java/math/BigInteger
    //   2506: invokevirtual intValue : ()I
    //   2509: bipush #32
    //   2511: irem
    //   2512: invokestatic abs : (I)I
    //   2515: invokevirtual charAt : (I)C
    //   2518: invokevirtual append : (C)Ljava/lang/StringBuilder;
    //   2521: pop
    //   2522: bipush #29
    //   2524: istore #5
    //   2526: iload_2
    //   2527: ifeq -> 2631
    //   2530: aload #4
    //   2532: getstatic burp/Zzc_.Zg : Ljava/lang/String;
    //   2535: getstatic burp/Zlck.Zr : Ljava/lang/Object;
    //   2538: checkcast java/math/BigInteger
    //   2541: invokevirtual intValue : ()I
    //   2544: bipush #32
    //   2546: irem
    //   2547: invokestatic abs : (I)I
    //   2550: invokevirtual charAt : (I)C
    //   2553: invokevirtual append : (C)Ljava/lang/StringBuilder;
    //   2556: pop
    //   2557: bipush #30
    //   2559: istore #5
    //   2561: iload_2
    //   2562: ifeq -> 2631
    //   2565: aload #4
    //   2567: getstatic burp/Zg4k.ZB : Ljava/lang/String;
    //   2570: getstatic burp/Zke7.Zj : Ljava/lang/Object;
    //   2573: checkcast java/math/BigInteger
    //   2576: invokevirtual intValue : ()I
    //   2579: bipush #32
    //   2581: irem
    //   2582: invokestatic abs : (I)I
    //   2585: invokevirtual charAt : (I)C
    //   2588: invokevirtual append : (C)Ljava/lang/StringBuilder;
    //   2591: pop
    //   2592: bipush #31
    //   2594: istore #5
    //   2596: iload_2
    //   2597: ifeq -> 2631
    //   2600: aload #4
    //   2602: getstatic burp/Zza8.Zm : Ljava/lang/String;
    //   2605: getstatic burp/Zlvb.ZN : Ljava/lang/Object;
    //   2608: checkcast java/math/BigInteger
    //   2611: invokevirtual intValue : ()I
    //   2614: bipush #32
    //   2616: irem
    //   2617: invokestatic abs : (I)I
    //   2620: invokevirtual charAt : (I)C
    //   2623: invokevirtual append : (C)Ljava/lang/StringBuilder;
    //   2626: pop
    //   2627: bipush #32
    //   2629: istore #5
    //   2631: iload_2
    //   2632: ifeq -> 1367
    //   2635: aload_0
    //   2636: iconst_0
    //   2637: aload #4
    //   2639: invokevirtual toString : ()Ljava/lang/String;
    //   2642: aastore
    //   2643: sipush #-5527
    //   2646: sipush #-3406
    //   2649: invokestatic a : (II)Ljava/lang/String;
    //   2652: iconst_1
    //   2653: ldc burp/Zmji
    //   2655: invokevirtual getClassLoader : ()Ljava/lang/ClassLoader;
    //   2658: invokestatic forName : (Ljava/lang/String;ZLjava/lang/ClassLoader;)Ljava/lang/Class;
    //   2661: invokevirtual getDeclaredFields : ()[Ljava/lang/reflect/Field;
    //   2664: astore #5
    //   2666: aload #5
    //   2668: arraylength
    //   2669: istore #6
    //   2671: iconst_0
    //   2672: istore #7
    //   2674: iload #7
    //   2676: iload #6
    //   2678: if_icmpge -> 2816
    //   2681: aload #5
    //   2683: iload #7
    //   2685: aaload
    //   2686: astore #8
    //   2688: aload #8
    //   2690: invokevirtual getModifiers : ()I
    //   2693: invokestatic isStatic : (I)Z
    //   2696: ifne -> 2706
    //   2699: goto -> 2809
    //   2702: invokestatic a : (Ljava/lang/Throwable;)Ljava/lang/Throwable;
    //   2705: athrow
    //   2706: aload #8
    //   2708: invokevirtual getType : ()Ljava/lang/Class;
    //   2711: astore #9
    //   2713: aload #9
    //   2715: ifnull -> 2796
    //   2718: aload #9
    //   2720: invokevirtual isPrimitive : ()Z
    //   2723: ifne -> 2796
    //   2726: goto -> 2733
    //   2729: invokestatic a : (Ljava/lang/Throwable;)Ljava/lang/Throwable;
    //   2732: athrow
    //   2733: aload #9
    //   2735: invokevirtual getPackage : ()Ljava/lang/Package;
    //   2738: ifnull -> 2796
    //   2741: goto -> 2748
    //   2744: invokestatic a : (Ljava/lang/Throwable;)Ljava/lang/Throwable;
    //   2747: athrow
    //   2748: aload #9
    //   2750: invokevirtual getPackage : ()Ljava/lang/Package;
    //   2753: invokevirtual getName : ()Ljava/lang/String;
    //   2756: ifnull -> 2796
    //   2759: goto -> 2766
    //   2762: invokestatic a : (Ljava/lang/Throwable;)Ljava/lang/Throwable;
    //   2765: athrow
    //   2766: aload #9
    //   2768: invokevirtual getPackage : ()Ljava/lang/Package;
    //   2771: invokevirtual getName : ()Ljava/lang/String;
    //   2774: sipush #-5526
    //   2777: sipush #-24428
    //   2780: invokestatic a : (II)Ljava/lang/String;
    //   2783: invokevirtual startsWith : (Ljava/lang/String;)Z
    //   2786: ifne -> 2796
    //   2789: goto -> 2796
    //   2792: invokestatic a : (Ljava/lang/Throwable;)Ljava/lang/Throwable;
    //   2795: athrow
    //   2796: aload #8
    //   2798: iconst_1
    //   2799: invokevirtual setAccessible : (Z)V
    //   2802: aload #8
    //   2804: aconst_null
    //   2805: invokevirtual get : (Ljava/lang/Object;)Ljava/lang/Object;
    //   2808: pop
    //   2809: iinc #7, 1
    //   2812: iload_2
    //   2813: ifeq -> 2674
    //   2816: sipush #-5521
    //   2819: sipush #-21790
    //   2822: invokestatic a : (II)Ljava/lang/String;
    //   2825: invokestatic forName : (Ljava/lang/String;)Ljava/lang/Class;
    //   2828: invokevirtual getDeclaredMethods : ()[Ljava/lang/reflect/Method;
    //   2831: astore #5
    //   2833: aload #5
    //   2835: arraylength
    //   2836: istore #6
    //   2838: iconst_0
    //   2839: istore #7
    //   2841: iload #7
    //   2843: iload #6
    //   2845: if_icmpge -> 2978
    //   2848: aload #5
    //   2850: iload #7
    //   2852: aaload
    //   2853: astore #8
    //   2855: aload #8
    //   2857: invokevirtual getParameterTypes : ()[Ljava/lang/Class;
    //   2860: pop
    //   2861: aload #8
    //   2863: invokevirtual getModifiers : ()I
    //   2866: invokestatic isStatic : (I)Z
    //   2869: ifeq -> 2964
    //   2872: aload #8
    //   2874: invokevirtual getParameterTypes : ()[Ljava/lang/Class;
    //   2877: arraylength
    //   2878: iconst_2
    //   2879: if_icmpne -> 2964
    //   2882: goto -> 2889
    //   2885: invokestatic a : (Ljava/lang/Throwable;)Ljava/lang/Throwable;
    //   2888: athrow
    //   2889: aload #8
    //   2891: invokevirtual getReturnType : ()Ljava/lang/Class;
    //   2894: getstatic java/lang/Void.TYPE : Ljava/lang/Class;
    //   2897: invokevirtual equals : (Ljava/lang/Object;)Z
    //   2900: ifeq -> 2964
    //   2903: goto -> 2910
    //   2906: invokestatic a : (Ljava/lang/Throwable;)Ljava/lang/Throwable;
    //   2909: athrow
    //   2910: aload #8
    //   2912: iconst_1
    //   2913: invokevirtual setAccessible : (Z)V
    //   2916: aload #8
    //   2918: aconst_null
    //   2919: iconst_2
    //   2920: anewarray java/lang/Object
    //   2923: dup
    //   2924: iconst_0
    //   2925: aload_0
    //   2926: aastore
    //   2927: dup
    //   2928: iconst_1
    //   2929: aload_1
    //   2930: ifnonnull -> 2948
    //   2933: goto -> 2940
    //   2936: invokestatic a : (Ljava/lang/Throwable;)Ljava/lang/Throwable;
    //   2939: athrow
    //   2940: aload_1
    //   2941: goto -> 2955
    //   2944: invokestatic a : (Ljava/lang/Throwable;)Ljava/lang/Throwable;
    //   2947: athrow
    //   2948: aload_1
    //   2949: checkcast [B
    //   2952: invokevirtual clone : ()Ljava/lang/Object;
    //   2955: aastore
    //   2956: invokevirtual invoke : (Ljava/lang/Object;[Ljava/lang/Object;)Ljava/lang/Object;
    //   2959: pop
    //   2960: iload_2
    //   2961: ifeq -> 2978
    //   2964: iinc #7, 1
    //   2967: iload_2
    //   2968: ifeq -> 2841
    //   2971: goto -> 2978
    //   2974: invokestatic a : (Ljava/lang/Throwable;)Ljava/lang/Throwable;
    //   2977: athrow
    //   2978: getstatic burp/Zxo6.Z_ : Ljava/lang/String;
    //   2981: getstatic burp/Zz1k.ZP : Ljava/lang/Object;
    //   2984: checkcast java/math/BigInteger
    //   2987: invokevirtual intValue : ()I
    //   2990: bipush #32
    //   2992: irem
    //   2993: invokestatic abs : (I)I
    //   2996: invokevirtual charAt : (I)C
    //   2999: getstatic burp/Zx4l.Zy : Ljava/lang/String;
    //   3002: getstatic burp/Zsgl.Zn : Ljava/lang/Object;
    //   3005: checkcast java/math/BigInteger
    //   3008: invokevirtual intValue : ()I
    //   3011: bipush #32
    //   3013: irem
    //   3014: invokestatic abs : (I)I
    //   3017: invokevirtual charAt : (I)C
    //   3020: if_icmpgt -> 3135
    //   3023: getstatic burp/Zl_u.Zc : Ljava/lang/String;
    //   3026: getstatic burp/Zlos.Zk : Ljava/lang/Object;
    //   3029: checkcast java/math/BigInteger
    //   3032: invokevirtual intValue : ()I
    //   3035: bipush #32
    //   3037: irem
    //   3038: invokestatic abs : (I)I
    //   3041: invokevirtual charAt : (I)C
    //   3044: getstatic burp/Zrnu.ZO : Ljava/lang/String;
    //   3047: getstatic burp/Zr0g.Zj : Ljava/lang/Object;
    //   3050: checkcast java/math/BigInteger
    //   3053: invokevirtual intValue : ()I
    //   3056: bipush #32
    //   3058: irem
    //   3059: invokestatic abs : (I)I
    //   3062: invokevirtual charAt : (I)C
    //   3065: if_icmpgt -> 3135
    //   3068: goto -> 3075
    //   3071: invokestatic a : (Ljava/lang/Throwable;)Ljava/lang/Throwable;
    //   3074: athrow
    //   3075: getstatic burp/Ztuj.Zk : Ljava/lang/String;
    //   3078: getstatic burp/Zr0u.ZB : Ljava/lang/Object;
    //   3081: checkcast java/math/BigInteger
    //   3084: invokevirtual intValue : ()I
    //   3087: bipush #32
    //   3089: irem
    //   3090: invokestatic abs : (I)I
    //   3093: invokevirtual charAt : (I)C
    //   3096: getstatic burp/Zzsq.Zc : Ljava/lang/String;
    //   3099: getstatic burp/Zk9s.ZY : Ljava/lang/Object;
    //   3102: checkcast java/math/BigInteger
    //   3105: invokevirtual intValue : ()I
    //   3108: bipush #32
    //   3110: irem
    //   3111: invokestatic abs : (I)I
    //   3114: invokevirtual charAt : (I)C
    //   3117: if_icmpgt -> 3135
    //   3120: goto -> 3127
    //   3123: invokestatic a : (Ljava/lang/Throwable;)Ljava/lang/Throwable;
    //   3126: athrow
    //   3127: iconst_1
    //   3128: goto -> 3136
    //   3131: invokestatic a : (Ljava/lang/Throwable;)Ljava/lang/Throwable;
    //   3134: athrow
    //   3135: iconst_0
    //   3136: ireturn
    //   3137: astore_3
    //   3138: new java/lang/Exception
    //   3141: dup
    //   3142: aload_3
    //   3143: invokevirtual getMessage : ()Ljava/lang/String;
    //   3146: invokespecial <init> : (Ljava/lang/String;)V
    //   3149: athrow
    // Exception table:
    //   from	to	target	type
    //   4	3136	3137	java/lang/Throwable
    //   22	198	201	java/lang/Throwable
    //   168	235	238	java/lang/Throwable
    //   205	272	275	java/lang/Throwable
    //   242	309	312	java/lang/Throwable
    //   279	346	349	java/lang/Throwable
    //   316	383	386	java/lang/Throwable
    //   353	420	423	java/lang/Throwable
    //   390	457	460	java/lang/Throwable
    //   427	494	497	java/lang/Throwable
    //   464	531	534	java/lang/Throwable
    //   501	568	571	java/lang/Throwable
    //   538	605	608	java/lang/Throwable
    //   575	642	645	java/lang/Throwable
    //   612	679	682	java/lang/Throwable
    //   649	716	719	java/lang/Throwable
    //   686	753	756	java/lang/Throwable
    //   723	790	793	java/lang/Throwable
    //   760	827	830	java/lang/Throwable
    //   797	864	867	java/lang/Throwable
    //   834	901	904	java/lang/Throwable
    //   871	938	941	java/lang/Throwable
    //   908	975	978	java/lang/Throwable
    //   945	1012	1015	java/lang/Throwable
    //   982	1049	1052	java/lang/Throwable
    //   1019	1086	1089	java/lang/Throwable
    //   1056	1123	1126	java/lang/Throwable
    //   1093	1160	1163	java/lang/Throwable
    //   1130	1197	1200	java/lang/Throwable
    //   1167	1234	1237	java/lang/Throwable
    //   1204	1271	1274	java/lang/Throwable
    //   1241	1308	1311	java/lang/Throwable
    //   1278	1341	1344	java/lang/Throwable
    //   2688	2702	2702	java/lang/Throwable
    //   2713	2726	2729	java/lang/Throwable
    //   2718	2741	2744	java/lang/Throwable
    //   2733	2759	2762	java/lang/Throwable
    //   2748	2789	2792	java/lang/Throwable
    //   2855	2882	2885	java/lang/Throwable
    //   2872	2903	2906	java/lang/Throwable
    //   2889	2933	2936	java/lang/Throwable
    //   2910	2944	2944	java/lang/Throwable
    //   2955	2971	2974	java/lang/Throwable
    //   2978	3068	3071	java/lang/Throwable
    //   3023	3120	3123	java/lang/Throwable
    //   3075	3131	3131	java/lang/Throwable
  }
  
  static void Zd(Object paramObject) {
    Zllw.Zg = a(-5524, 24835);
    Zllw.ZW = new BigInteger(1, new byte[] { 
          11, -50, 1, -127, -74, -90, 46, -17, 113, -4, 
          100, 84, 67, -56, -58, -117, -41, 27, -124, -31, 
          10, -51, 59, -35, -107, -113, -114, -71, -5, 70, 
          75, -105 });
    boolean bool = Zt2e.ZK();
    try {
      try {
        if (Zeb3.ZG.charAt(Math.abs(((BigInteger)Zeb7.ZJ).intValue() % 32)) <= Zsf7.ZS.charAt(Math.abs(((BigInteger)Zgl2.ZS).intValue() % 32))) {
          try {
            Zebu.Zt(Class.forName(a(-5528, 6610)));
            if (bool)
              Zgqp.Zl(Class.forName(a(-5523, 29894))); 
          } catch (Throwable throwable) {
            throw a(null);
          } 
          return;
        } 
      } catch (Throwable throwable) {
        throw a(null);
      } 
      Zgqp.Zl(Class.forName(a(-5523, 29894)));
    } catch (Throwable throwable) {}
  }
  
  static {
    // Byte code:
    //   0: bipush #7
    //   2: anewarray java/lang/String
    //   5: astore #5
    //   7: iconst_0
    //   8: istore_3
    //   9: ldc 'gT~JE&*\\rn>qM9!\\t 2 HTaebCQ<"ns`y\x\\tAV<\\b&z'
    //   11: dup
    //   12: astore_2
    //   13: invokevirtual length : ()I
    //   16: istore #4
    //   18: bipush #32
    //   20: istore_1
    //   21: iconst_m1
    //   22: istore_0
    //   23: bipush #23
    //   25: iinc #0, 1
    //   28: aload_2
    //   29: iload_0
    //   30: dup
    //   31: iload_1
    //   32: iadd
    //   33: invokevirtual substring : (II)Ljava/lang/String;
    //   36: iconst_m1
    //   37: goto -> 143
    //   40: aload #5
    //   42: swap
    //   43: iload_3
    //   44: iinc #3, 1
    //   47: swap
    //   48: aastore
    //   49: iload_0
    //   50: iload_1
    //   51: iadd
    //   52: dup
    //   53: istore_0
    //   54: iload #4
    //   56: if_icmpge -> 68
    //   59: aload_2
    //   60: iload_0
    //   61: invokevirtual charAt : (I)C
    //   64: istore_1
    //   65: goto -> 23
    //   68: ldc ' mny=vF(9o'
    //   70: dup
    //   71: astore_2
    //   72: invokevirtual length : ()I
    //   75: istore #4
    //   77: bipush #9
    //   79: istore_1
    //   80: iconst_m1
    //   81: istore_0
    //   82: bipush #80
    //   84: iinc #0, 1
    //   87: aload_2
    //   88: iload_0
    //   89: dup
    //   90: iload_1
    //   91: iadd
    //   92: invokevirtual substring : (II)Ljava/lang/String;
    //   95: iconst_0
    //   96: goto -> 143
    //   99: aload #5
    //   101: swap
    //   102: iload_3
    //   103: iinc #3, 1
    //   106: swap
    //   107: aastore
    //   108: iload_0
    //   109: iload_1
    //   110: iadd
    //   111: dup
    //   112: istore_0
    //   113: iload #4
    //   115: if_icmpge -> 127
    //   118: aload_2
    //   119: iload_0
    //   120: invokevirtual charAt : (I)C
    //   123: istore_1
    //   124: goto -> 82
    //   127: aload #5
    //   129: putstatic burp/Zmuo.a : [Ljava/lang/String;
    //   132: bipush #7
    //   134: anewarray java/lang/String
    //   137: putstatic burp/Zmuo.b : [Ljava/lang/String;
    //   140: goto -> 300
    //   143: dup_x2
    //   144: pop
    //   145: invokevirtual toCharArray : ()[C
    //   148: dup_x1
    //   149: arraylength
    //   150: dup_x2
    //   151: pop
    //   152: iconst_0
    //   153: istore #6
    //   155: dup2_x1
    //   156: pop2
    //   157: dup_x2
    //   158: iconst_1
    //   159: if_icmpgt -> 260
    //   162: dup2
    //   163: swap
    //   164: iload #6
    //   166: dup2_x1
    //   167: caload
    //   168: swap
    //   169: iload #6
    //   171: bipush #7
    //   173: irem
    //   174: tableswitch default -> 242, 0 -> 212, 1 -> 217, 2 -> 222, 3 -> 227, 4 -> 232, 5 -> 237
    //   212: bipush #17
    //   214: goto -> 244
    //   217: bipush #11
    //   219: goto -> 244
    //   222: bipush #78
    //   224: goto -> 244
    //   227: bipush #68
    //   229: goto -> 244
    //   232: bipush #113
    //   234: goto -> 244
    //   237: bipush #14
    //   239: goto -> 244
    //   242: bipush #52
    //   244: ixor
    //   245: ixor
    //   246: i2c
    //   247: castore
    //   248: iinc #6, 1
    //   251: dup
    //   252: ifne -> 260
    //   255: dup2
    //   256: dup_x1
    //   257: goto -> 166
    //   260: dup2_x1
    //   261: pop2
    //   262: dup_x2
    //   263: iload #6
    //   265: if_icmpgt -> 162
    //   268: pop
    //   269: new java/lang/String
    //   272: dup_x1
    //   273: swap
    //   274: invokespecial <init> : ([C)V
    //   277: invokevirtual intern : ()Ljava/lang/String;
    //   280: swap
    //   281: pop
    //   282: swap
    //   283: tableswitch default -> 40, 0 -> 99
    //   300: new java/math/BigInteger
    //   303: dup
    //   304: bipush #32
    //   306: newarray byte
    //   308: dup
    //   309: iconst_0
    //   310: bipush #114
    //   312: bastore
    //   313: dup
    //   314: iconst_1
    //   315: bipush #99
    //   317: bastore
    //   318: dup
    //   319: iconst_2
    //   320: bipush #-23
    //   322: bastore
    //   323: dup
    //   324: iconst_3
    //   325: bipush #40
    //   327: bastore
    //   328: dup
    //   329: iconst_4
    //   330: bipush #-109
    //   332: bastore
    //   333: dup
    //   334: iconst_5
    //   335: bipush #44
    //   337: bastore
    //   338: dup
    //   339: bipush #6
    //   341: bipush #-47
    //   343: bastore
    //   344: dup
    //   345: bipush #7
    //   347: bipush #127
    //   349: bastore
    //   350: dup
    //   351: bipush #8
    //   353: bipush #-45
    //   355: bastore
    //   356: dup
    //   357: bipush #9
    //   359: bipush #-37
    //   361: bastore
    //   362: dup
    //   363: bipush #10
    //   365: bipush #-116
    //   367: bastore
    //   368: dup
    //   369: bipush #11
    //   371: bipush #73
    //   373: bastore
    //   374: dup
    //   375: bipush #12
    //   377: bipush #85
    //   379: bastore
    //   380: dup
    //   381: bipush #13
    //   383: iconst_3
    //   384: bastore
    //   385: dup
    //   386: bipush #14
    //   388: iconst_2
    //   389: bastore
    //   390: dup
    //   391: bipush #15
    //   393: bipush #73
    //   395: bastore
    //   396: dup
    //   397: bipush #16
    //   399: bipush #113
    //   401: bastore
    //   402: dup
    //   403: bipush #17
    //   405: bipush #107
    //   407: bastore
    //   408: dup
    //   409: bipush #18
    //   411: bipush #106
    //   413: bastore
    //   414: dup
    //   415: bipush #19
    //   417: bipush #-95
    //   419: bastore
    //   420: dup
    //   421: bipush #20
    //   423: bipush #-51
    //   425: bastore
    //   426: dup
    //   427: bipush #21
    //   429: bipush #29
    //   431: bastore
    //   432: dup
    //   433: bipush #22
    //   435: bipush #-110
    //   437: bastore
    //   438: dup
    //   439: bipush #23
    //   441: bipush #-111
    //   443: bastore
    //   444: dup
    //   445: bipush #24
    //   447: bipush #-120
    //   449: bastore
    //   450: dup
    //   451: bipush #25
    //   453: bipush #36
    //   455: bastore
    //   456: dup
    //   457: bipush #26
    //   459: bipush #21
    //   461: bastore
    //   462: dup
    //   463: bipush #27
    //   465: bipush #-13
    //   467: bastore
    //   468: dup
    //   469: bipush #28
    //   471: bipush #39
    //   473: bastore
    //   474: dup
    //   475: bipush #29
    //   477: bipush #-5
    //   479: bastore
    //   480: dup
    //   481: bipush #30
    //   483: bipush #22
    //   485: bastore
    //   486: dup
    //   487: bipush #31
    //   489: bipush #106
    //   491: bastore
    //   492: invokespecial <init> : ([B)V
    //   495: putstatic burp/Zmuo.Zd : Ljava/lang/Object;
    //   498: sipush #-5522
    //   501: sipush #32450
    //   504: invokestatic a : (II)Ljava/lang/String;
    //   507: putstatic burp/Zmuo.Zo : Ljava/lang/String;
    //   510: return
  }
  
  private static Throwable a(Throwable paramThrowable) {
    return paramThrowable;
  }
  
  private static String a(int paramInt1, int paramInt2) {
    int i = (paramInt1 ^ 0xFFFFEA6C) & 0xFFFF;
    if (b[i] == null) {
      char[] arrayOfChar = a[i].toCharArray();
      switch (arrayOfChar[0] & 0xFF) {
        case 0:
        
        case 1:
        
        case 2:
        
        case 3:
        
        case 4:
        
        case 5:
        
        case 6:
        
        case 7:
        
        case 8:
        
        case 9:
        
        case 10:
        
        case 11:
        
        case 12:
        
        case 13:
        
        case 14:
        
        case 15:
        
        case 16:
        
        case 17:
        
        case 18:
        
        case 19:
        
        case 20:
        
        case 21:
        
        case 22:
        
        case 23:
        
        case 24:
        
        case 25:
        
        case 26:
        
        case 27:
        
        case 28:
        
        case 29:
        
        case 30:
        
        case 31:
        
        case 32:
        
        case 33:
        
        case 34:
        
        case 35:
        
        case 36:
        
        case 37:
        
        case 38:
        
        case 39:
        
        case 40:
        
        case 41:
        
        case 42:
        
        case 43:
        
        case 44:
        
        case 45:
        
        case 46:
        
        case 47:
        
        case 48:
        
        case 49:
        
        case 50:
        
        case 51:
        
        case 52:
        
        case 53:
        
        case 54:
        
        case 55:
        
        case 56:
        
        case 57:
        
        case 58:
        
        case 59:
        
        case 60:
        
        case 61:
        
        case 62:
        
        case 63:
        
        case 64:
        
        case 65:
        
        case 66:
        
        case 67:
        
        case 68:
        
        case 69:
        
        case 70:
        
        case 71:
        
        case 72:
        
        case 73:
        
        case 74:
        
        case 75:
        
        case 76:
        
        case 77:
        
        case 78:
        
        case 79:
        
        case 80:
        
        case 81:
        
        case 82:
        
        case 83:
        
        case 84:
        
        case 85:
        
        case 86:
        
        case 87:
        
        case 88:
        
        case 89:
        
        case 90:
        
        case 91:
        
        case 92:
        
        case 93:
        
        case 94:
        
        case 95:
        
        case 96:
        
        case 97:
        
        case 98:
        
        case 99:
        
        case 100:
        
        case 101:
        
        case 102:
        
        case 103:
        
        case 104:
        
        case 105:
        
        case 106:
        
        case 107:
        
        case 108:
        
        case 109:
        
        case 110:
        
        case 111:
        
        case 112:
        
        case 113:
        
        case 114:
        
        case 115:
        
        case 116:
        
        case 117:
        
        case 118:
        
        case 119:
        
        case 120:
        
        case 121:
        
        case 122:
        
        case 123:
        
        case 124:
        
        case 125:
        
        case 126:
        
        case 127:
        
        case 128:
        
        case 129:
        
        case 130:
        
        case 131:
        
        case 132:
        
        case 133:
        
        case 134:
        
        case 135:
        
        case 136:
        
        case 137:
        
        case 138:
        
        case 139:
        
        case 140:
        
        case 141:
        
        case 142:
        
        case 143:
        
        case 144:
        
        case 145:
        
        case 146:
        
        case 147:
        
        case 148:
        
        case 149:
        
        case 150:
        
        case 151:
        
        case 152:
        
        case 153:
        
        case 154:
        
        case 155:
        
        case 156:
        
        case 157:
        
        case 158:
        
        case 159:
        
        case 160:
        
        case 161:
        
        case 162:
        
        case 163:
        
        case 164:
        
        case 165:
        
        case 166:
        
        case 167:
        
        case 168:
        
        case 169:
        
        case 170:
        
        case 171:
        
        case 172:
        
        case 173:
        
        case 174:
        
        case 175:
        
        case 176:
        
        case 177:
        
        case 178:
        
        case 179:
        
        case 180:
        
        case 181:
        
        case 182:
        
        case 183:
        
        case 184:
        
        case 185:
        
        case 186:
        
        case 187:
        
        case 188:
        
        case 189:
        
        case 190:
        
        case 191:
        
        case 192:
        
        case 193:
        
        case 194:
        
        case 195:
        
        case 196:
        
        case 197:
        
        case 198:
        
        case 199:
        
        case 200:
        
        case 201:
        
        case 202:
        
        case 203:
        
        case 204:
        
        case 205:
        
        case 206:
        
        case 207:
        
        case 208:
        
        case 209:
        
        case 210:
        
        case 211:
        
        case 212:
        
        case 213:
        
        case 214:
        
        case 215:
        
        case 216:
        
        case 217:
        
        case 218:
        
        case 219:
        
        case 220:
        
        case 221:
        
        case 222:
        
        case 223:
        
        case 224:
        
        case 225:
        
        case 226:
        
        case 227:
        
        case 228:
        
        case 229:
        
        case 230:
        
        case 231:
        
        case 232:
        
        case 233:
        
        case 234:
        
        case 235:
        
        case 236:
        
        case 237:
        
        case 238:
        
        case 239:
        
        case 240:
        
        case 241:
        
        case 242:
        
        case 243:
        
        case 244:
        
        case 245:
        
        case 246:
        
        case 247:
        
        case 248:
        
        case 249:
        
        case 250:
        
        case 251:
        
        case 252:
        
        case 253:
        
        case 254:
        
        default:
          break;
      } 
      char c = '';
      int j = (paramInt2 & 0xFF) - c;
      if (j < 0)
        j += 256; 
      int k = ((paramInt2 & 0xFFFF) >>> 8) - c;
      if (k < 0)
        k += 256; 
      for (byte b = 0; b < arrayOfChar.length; b++) {
        int m = b % 2;
        if (m == 0) {
          arrayOfChar[b] = (char)(arrayOfChar[b] ^ j);
          j = ((j >>> 3 | j << 5) ^ arrayOfChar[b]) & 0xFF;
        } else {
          arrayOfChar[b] = (char)(arrayOfChar[b] ^ k);
          k = ((k >>> 3 | k << 5) ^ arrayOfChar[b]) & 0xFF;
        } 
      } 
      b[i] = (new String(arrayOfChar)).intern();
    } 
    return b[i];
  }
}


/* Location:              C:\Program Files\BurpSuitePro\burpsuite_pro.jar!\burp\Zmuo.class
 * Java compiler version: 21 (65.0)
 * JD-Core Version:       1.1.3
 */