package burp;

import java.math.BigInteger;

class Zmv9 extends ClassLoader {
  static String Zm;
  
  static Object Zw;
  
  private static final String[] a;
  
  private static final String[] b;
  
  static void Zx(Object[] paramArrayOfObject, Object paramObject) throws Throwable {}
  
  static boolean ZU(Object[] paramArrayOfObject, Object paramObject) throws Throwable {
    // Byte code:
    //   0: invokestatic ZN : ()Z
    //   3: istore_2
    //   4: new java/lang/StringBuilder
    //   7: dup
    //   8: invokespecial <init> : ()V
    //   11: astore_3
    //   12: iconst_0
    //   13: istore #4
    //   15: iload #4
    //   17: bipush #32
    //   19: if_icmpge -> 1355
    //   22: iload #4
    //   24: tableswitch default -> 1348, 0 -> 168, 1 -> 205, 2 -> 242, 3 -> 279, 4 -> 316, 5 -> 353, 6 -> 390, 7 -> 427, 8 -> 464, 9 -> 501, 10 -> 538, 11 -> 575, 12 -> 612, 13 -> 649, 14 -> 686, 15 -> 723, 16 -> 760, 17 -> 797, 18 -> 834, 19 -> 871, 20 -> 908, 21 -> 945, 22 -> 982, 23 -> 1019, 24 -> 1056, 25 -> 1093, 26 -> 1130, 27 -> 1167, 28 -> 1204, 29 -> 1241, 30 -> 1278, 31 -> 1315
    //   168: aload_3
    //   169: getstatic burp/Zr8s.ZA : Ljava/lang/String;
    //   172: getstatic burp/Zr_y.ZI : Ljava/lang/Object;
    //   175: checkcast java/math/BigInteger
    //   178: invokevirtual intValue : ()I
    //   181: bipush #32
    //   183: irem
    //   184: invokestatic abs : (I)I
    //   187: invokevirtual charAt : (I)C
    //   190: invokevirtual append : (C)Ljava/lang/StringBuilder;
    //   193: pop
    //   194: iload_2
    //   195: ifne -> 1348
    //   198: goto -> 205
    //   201: invokestatic a : (Ljava/lang/Throwable;)Ljava/lang/Throwable;
    //   204: athrow
    //   205: aload_3
    //   206: getstatic burp/Zmcb.Zl : Ljava/lang/String;
    //   209: getstatic burp/Zeyd.Zl : Ljava/lang/Object;
    //   212: checkcast java/math/BigInteger
    //   215: invokevirtual intValue : ()I
    //   218: bipush #32
    //   220: irem
    //   221: invokestatic abs : (I)I
    //   224: invokevirtual charAt : (I)C
    //   227: invokevirtual append : (C)Ljava/lang/StringBuilder;
    //   230: pop
    //   231: iload_2
    //   232: ifne -> 1348
    //   235: goto -> 242
    //   238: invokestatic a : (Ljava/lang/Throwable;)Ljava/lang/Throwable;
    //   241: athrow
    //   242: aload_3
    //   243: getstatic burp/Zl1u.ZO : Ljava/lang/String;
    //   246: getstatic burp/Ztsj.Zc : Ljava/lang/Object;
    //   249: checkcast java/math/BigInteger
    //   252: invokevirtual intValue : ()I
    //   255: bipush #32
    //   257: irem
    //   258: invokestatic abs : (I)I
    //   261: invokevirtual charAt : (I)C
    //   264: invokevirtual append : (C)Ljava/lang/StringBuilder;
    //   267: pop
    //   268: iload_2
    //   269: ifne -> 1348
    //   272: goto -> 279
    //   275: invokestatic a : (Ljava/lang/Throwable;)Ljava/lang/Throwable;
    //   278: athrow
    //   279: aload_3
    //   280: getstatic burp/Zm5s.Z_ : Ljava/lang/String;
    //   283: getstatic burp/Zb38.ZC : Ljava/lang/Object;
    //   286: checkcast java/math/BigInteger
    //   289: invokevirtual intValue : ()I
    //   292: bipush #32
    //   294: irem
    //   295: invokestatic abs : (I)I
    //   298: invokevirtual charAt : (I)C
    //   301: invokevirtual append : (C)Ljava/lang/StringBuilder;
    //   304: pop
    //   305: iload_2
    //   306: ifne -> 1348
    //   309: goto -> 316
    //   312: invokestatic a : (Ljava/lang/Throwable;)Ljava/lang/Throwable;
    //   315: athrow
    //   316: aload_3
    //   317: getstatic burp/Zz9v.Zv : Ljava/lang/String;
    //   320: getstatic burp/Zmh5.ZN : Ljava/lang/Object;
    //   323: checkcast java/math/BigInteger
    //   326: invokevirtual intValue : ()I
    //   329: bipush #32
    //   331: irem
    //   332: invokestatic abs : (I)I
    //   335: invokevirtual charAt : (I)C
    //   338: invokevirtual append : (C)Ljava/lang/StringBuilder;
    //   341: pop
    //   342: iload_2
    //   343: ifne -> 1348
    //   346: goto -> 353
    //   349: invokestatic a : (Ljava/lang/Throwable;)Ljava/lang/Throwable;
    //   352: athrow
    //   353: aload_3
    //   354: getstatic burp/Zs9u.ZM : Ljava/lang/String;
    //   357: getstatic burp/Ztq8.Zm : Ljava/lang/Object;
    //   360: checkcast java/math/BigInteger
    //   363: invokevirtual intValue : ()I
    //   366: bipush #32
    //   368: irem
    //   369: invokestatic abs : (I)I
    //   372: invokevirtual charAt : (I)C
    //   375: invokevirtual append : (C)Ljava/lang/StringBuilder;
    //   378: pop
    //   379: iload_2
    //   380: ifne -> 1348
    //   383: goto -> 390
    //   386: invokestatic a : (Ljava/lang/Throwable;)Ljava/lang/Throwable;
    //   389: athrow
    //   390: aload_3
    //   391: getstatic burp/Zl5b.Zi : Ljava/lang/String;
    //   394: getstatic burp/Zkfb.ZN : Ljava/lang/Object;
    //   397: checkcast java/math/BigInteger
    //   400: invokevirtual intValue : ()I
    //   403: bipush #32
    //   405: irem
    //   406: invokestatic abs : (I)I
    //   409: invokevirtual charAt : (I)C
    //   412: invokevirtual append : (C)Ljava/lang/StringBuilder;
    //   415: pop
    //   416: iload_2
    //   417: ifne -> 1348
    //   420: goto -> 427
    //   423: invokestatic a : (Ljava/lang/Throwable;)Ljava/lang/Throwable;
    //   426: athrow
    //   427: aload_3
    //   428: getstatic burp/Ztes.Zo : Ljava/lang/String;
    //   431: getstatic burp/Zlos.Zk : Ljava/lang/Object;
    //   434: checkcast java/math/BigInteger
    //   437: invokevirtual intValue : ()I
    //   440: bipush #32
    //   442: irem
    //   443: invokestatic abs : (I)I
    //   446: invokevirtual charAt : (I)C
    //   449: invokevirtual append : (C)Ljava/lang/StringBuilder;
    //   452: pop
    //   453: iload_2
    //   454: ifne -> 1348
    //   457: goto -> 464
    //   460: invokestatic a : (Ljava/lang/Throwable;)Ljava/lang/Throwable;
    //   463: athrow
    //   464: aload_3
    //   465: getstatic burp/Zs0b.ZT : Ljava/lang/String;
    //   468: getstatic burp/Zzrb.Zj : Ljava/lang/Object;
    //   471: checkcast java/math/BigInteger
    //   474: invokevirtual intValue : ()I
    //   477: bipush #32
    //   479: irem
    //   480: invokestatic abs : (I)I
    //   483: invokevirtual charAt : (I)C
    //   486: invokevirtual append : (C)Ljava/lang/StringBuilder;
    //   489: pop
    //   490: iload_2
    //   491: ifne -> 1348
    //   494: goto -> 501
    //   497: invokestatic a : (Ljava/lang/Throwable;)Ljava/lang/Throwable;
    //   500: athrow
    //   501: aload_3
    //   502: getstatic burp/Zg_p.ZO : Ljava/lang/String;
    //   505: getstatic burp/Zeqo.ZZ : Ljava/lang/Object;
    //   508: checkcast java/math/BigInteger
    //   511: invokevirtual intValue : ()I
    //   514: bipush #32
    //   516: irem
    //   517: invokestatic abs : (I)I
    //   520: invokevirtual charAt : (I)C
    //   523: invokevirtual append : (C)Ljava/lang/StringBuilder;
    //   526: pop
    //   527: iload_2
    //   528: ifne -> 1348
    //   531: goto -> 538
    //   534: invokestatic a : (Ljava/lang/Throwable;)Ljava/lang/Throwable;
    //   537: athrow
    //   538: aload_3
    //   539: getstatic burp/Zgmt.Zu : Ljava/lang/String;
    //   542: getstatic burp/Zl_1.ZL : Ljava/lang/Object;
    //   545: checkcast java/math/BigInteger
    //   548: invokevirtual intValue : ()I
    //   551: bipush #32
    //   553: irem
    //   554: invokestatic abs : (I)I
    //   557: invokevirtual charAt : (I)C
    //   560: invokevirtual append : (C)Ljava/lang/StringBuilder;
    //   563: pop
    //   564: iload_2
    //   565: ifne -> 1348
    //   568: goto -> 575
    //   571: invokestatic a : (Ljava/lang/Throwable;)Ljava/lang/Throwable;
    //   574: athrow
    //   575: aload_3
    //   576: getstatic burp/Zevf.ZL : Ljava/lang/String;
    //   579: getstatic burp/Zzh1.Zf : Ljava/lang/Object;
    //   582: checkcast java/math/BigInteger
    //   585: invokevirtual intValue : ()I
    //   588: bipush #32
    //   590: irem
    //   591: invokestatic abs : (I)I
    //   594: invokevirtual charAt : (I)C
    //   597: invokevirtual append : (C)Ljava/lang/StringBuilder;
    //   600: pop
    //   601: iload_2
    //   602: ifne -> 1348
    //   605: goto -> 612
    //   608: invokestatic a : (Ljava/lang/Throwable;)Ljava/lang/Throwable;
    //   611: athrow
    //   612: aload_3
    //   613: getstatic burp/Zrdy.ZO : Ljava/lang/String;
    //   616: getstatic burp/Zzlg.Z_ : Ljava/lang/Object;
    //   619: checkcast java/math/BigInteger
    //   622: invokevirtual intValue : ()I
    //   625: bipush #32
    //   627: irem
    //   628: invokestatic abs : (I)I
    //   631: invokevirtual charAt : (I)C
    //   634: invokevirtual append : (C)Ljava/lang/StringBuilder;
    //   637: pop
    //   638: iload_2
    //   639: ifne -> 1348
    //   642: goto -> 649
    //   645: invokestatic a : (Ljava/lang/Throwable;)Ljava/lang/Throwable;
    //   648: athrow
    //   649: aload_3
    //   650: getstatic burp/Zrug.Zq : Ljava/lang/String;
    //   653: getstatic burp/Zlv6.ZN : Ljava/lang/Object;
    //   656: checkcast java/math/BigInteger
    //   659: invokevirtual intValue : ()I
    //   662: bipush #32
    //   664: irem
    //   665: invokestatic abs : (I)I
    //   668: invokevirtual charAt : (I)C
    //   671: invokevirtual append : (C)Ljava/lang/StringBuilder;
    //   674: pop
    //   675: iload_2
    //   676: ifne -> 1348
    //   679: goto -> 686
    //   682: invokestatic a : (Ljava/lang/Throwable;)Ljava/lang/Throwable;
    //   685: athrow
    //   686: aload_3
    //   687: getstatic burp/Zxti.ZD : Ljava/lang/String;
    //   690: getstatic burp/Zst7.ZI : Ljava/lang/Object;
    //   693: checkcast java/math/BigInteger
    //   696: invokevirtual intValue : ()I
    //   699: bipush #32
    //   701: irem
    //   702: invokestatic abs : (I)I
    //   705: invokevirtual charAt : (I)C
    //   708: invokevirtual append : (C)Ljava/lang/StringBuilder;
    //   711: pop
    //   712: iload_2
    //   713: ifne -> 1348
    //   716: goto -> 723
    //   719: invokestatic a : (Ljava/lang/Throwable;)Ljava/lang/Throwable;
    //   722: athrow
    //   723: aload_3
    //   724: getstatic burp/Zmvk.Z_ : Ljava/lang/String;
    //   727: getstatic burp/Ze5t.Zc : Ljava/lang/Object;
    //   730: checkcast java/math/BigInteger
    //   733: invokevirtual intValue : ()I
    //   736: bipush #32
    //   738: irem
    //   739: invokestatic abs : (I)I
    //   742: invokevirtual charAt : (I)C
    //   745: invokevirtual append : (C)Ljava/lang/StringBuilder;
    //   748: pop
    //   749: iload_2
    //   750: ifne -> 1348
    //   753: goto -> 760
    //   756: invokestatic a : (Ljava/lang/Throwable;)Ljava/lang/Throwable;
    //   759: athrow
    //   760: aload_3
    //   761: getstatic burp/Ztid.Zz : Ljava/lang/String;
    //   764: getstatic burp/Zlfg.Zv : Ljava/lang/Object;
    //   767: checkcast java/math/BigInteger
    //   770: invokevirtual intValue : ()I
    //   773: bipush #32
    //   775: irem
    //   776: invokestatic abs : (I)I
    //   779: invokevirtual charAt : (I)C
    //   782: invokevirtual append : (C)Ljava/lang/StringBuilder;
    //   785: pop
    //   786: iload_2
    //   787: ifne -> 1348
    //   790: goto -> 797
    //   793: invokestatic a : (Ljava/lang/Throwable;)Ljava/lang/Throwable;
    //   796: athrow
    //   797: aload_3
    //   798: getstatic burp/Zxc.Zx : Ljava/lang/String;
    //   801: getstatic burp/Zejg.ZR : Ljava/lang/Object;
    //   804: checkcast java/math/BigInteger
    //   807: invokevirtual intValue : ()I
    //   810: bipush #32
    //   812: irem
    //   813: invokestatic abs : (I)I
    //   816: invokevirtual charAt : (I)C
    //   819: invokevirtual append : (C)Ljava/lang/StringBuilder;
    //   822: pop
    //   823: iload_2
    //   824: ifne -> 1348
    //   827: goto -> 834
    //   830: invokestatic a : (Ljava/lang/Throwable;)Ljava/lang/Throwable;
    //   833: athrow
    //   834: aload_3
    //   835: getstatic burp/Zzbr.Zp : Ljava/lang/String;
    //   838: getstatic burp/Zgco.Zx : Ljava/lang/Object;
    //   841: checkcast java/math/BigInteger
    //   844: invokevirtual intValue : ()I
    //   847: bipush #32
    //   849: irem
    //   850: invokestatic abs : (I)I
    //   853: invokevirtual charAt : (I)C
    //   856: invokevirtual append : (C)Ljava/lang/StringBuilder;
    //   859: pop
    //   860: iload_2
    //   861: ifne -> 1348
    //   864: goto -> 871
    //   867: invokestatic a : (Ljava/lang/Throwable;)Ljava/lang/Throwable;
    //   870: athrow
    //   871: aload_3
    //   872: getstatic burp/Zlqy.ZZ : Ljava/lang/String;
    //   875: getstatic burp/Zre4.Zx : Ljava/lang/Object;
    //   878: checkcast java/math/BigInteger
    //   881: invokevirtual intValue : ()I
    //   884: bipush #32
    //   886: irem
    //   887: invokestatic abs : (I)I
    //   890: invokevirtual charAt : (I)C
    //   893: invokevirtual append : (C)Ljava/lang/StringBuilder;
    //   896: pop
    //   897: iload_2
    //   898: ifne -> 1348
    //   901: goto -> 908
    //   904: invokestatic a : (Ljava/lang/Throwable;)Ljava/lang/Throwable;
    //   907: athrow
    //   908: aload_3
    //   909: getstatic burp/Zl1n.ZZ : Ljava/lang/String;
    //   912: getstatic burp/Zsej.ZT : Ljava/lang/Object;
    //   915: checkcast java/math/BigInteger
    //   918: invokevirtual intValue : ()I
    //   921: bipush #32
    //   923: irem
    //   924: invokestatic abs : (I)I
    //   927: invokevirtual charAt : (I)C
    //   930: invokevirtual append : (C)Ljava/lang/StringBuilder;
    //   933: pop
    //   934: iload_2
    //   935: ifne -> 1348
    //   938: goto -> 945
    //   941: invokestatic a : (Ljava/lang/Throwable;)Ljava/lang/Throwable;
    //   944: athrow
    //   945: aload_3
    //   946: getstatic burp/Zlp7.ZO : Ljava/lang/String;
    //   949: getstatic burp/Zsde.Zx : Ljava/lang/Object;
    //   952: checkcast java/math/BigInteger
    //   955: invokevirtual intValue : ()I
    //   958: bipush #32
    //   960: irem
    //   961: invokestatic abs : (I)I
    //   964: invokevirtual charAt : (I)C
    //   967: invokevirtual append : (C)Ljava/lang/StringBuilder;
    //   970: pop
    //   971: iload_2
    //   972: ifne -> 1348
    //   975: goto -> 982
    //   978: invokestatic a : (Ljava/lang/Throwable;)Ljava/lang/Throwable;
    //   981: athrow
    //   982: aload_3
    //   983: getstatic burp/Zb2k.Zu : Ljava/lang/String;
    //   986: getstatic burp/Zge1.ZK : Ljava/lang/Object;
    //   989: checkcast java/math/BigInteger
    //   992: invokevirtual intValue : ()I
    //   995: bipush #32
    //   997: irem
    //   998: invokestatic abs : (I)I
    //   1001: invokevirtual charAt : (I)C
    //   1004: invokevirtual append : (C)Ljava/lang/StringBuilder;
    //   1007: pop
    //   1008: iload_2
    //   1009: ifne -> 1348
    //   1012: goto -> 1019
    //   1015: invokestatic a : (Ljava/lang/Throwable;)Ljava/lang/Throwable;
    //   1018: athrow
    //   1019: aload_3
    //   1020: getstatic burp/Zm54.Zg : Ljava/lang/String;
    //   1023: getstatic burp/Ztkh.Zh : Ljava/lang/Object;
    //   1026: checkcast java/math/BigInteger
    //   1029: invokevirtual intValue : ()I
    //   1032: bipush #32
    //   1034: irem
    //   1035: invokestatic abs : (I)I
    //   1038: invokevirtual charAt : (I)C
    //   1041: invokevirtual append : (C)Ljava/lang/StringBuilder;
    //   1044: pop
    //   1045: iload_2
    //   1046: ifne -> 1348
    //   1049: goto -> 1056
    //   1052: invokestatic a : (Ljava/lang/Throwable;)Ljava/lang/Throwable;
    //   1055: athrow
    //   1056: aload_3
    //   1057: getstatic burp/Zrt9.Zc : Ljava/lang/String;
    //   1060: getstatic burp/Zm1l.Za : Ljava/lang/Object;
    //   1063: checkcast java/math/BigInteger
    //   1066: invokevirtual intValue : ()I
    //   1069: bipush #32
    //   1071: irem
    //   1072: invokestatic abs : (I)I
    //   1075: invokevirtual charAt : (I)C
    //   1078: invokevirtual append : (C)Ljava/lang/StringBuilder;
    //   1081: pop
    //   1082: iload_2
    //   1083: ifne -> 1348
    //   1086: goto -> 1093
    //   1089: invokestatic a : (Ljava/lang/Throwable;)Ljava/lang/Throwable;
    //   1092: athrow
    //   1093: aload_3
    //   1094: getstatic burp/Zxo7.Zl : Ljava/lang/String;
    //   1097: getstatic burp/Ze57.ZR : Ljava/lang/Object;
    //   1100: checkcast java/math/BigInteger
    //   1103: invokevirtual intValue : ()I
    //   1106: bipush #32
    //   1108: irem
    //   1109: invokestatic abs : (I)I
    //   1112: invokevirtual charAt : (I)C
    //   1115: invokevirtual append : (C)Ljava/lang/StringBuilder;
    //   1118: pop
    //   1119: iload_2
    //   1120: ifne -> 1348
    //   1123: goto -> 1130
    //   1126: invokestatic a : (Ljava/lang/Throwable;)Ljava/lang/Throwable;
    //   1129: athrow
    //   1130: aload_3
    //   1131: getstatic burp/Zer.Zp : Ljava/lang/String;
    //   1134: getstatic burp/Zs1d.Zo : Ljava/lang/Object;
    //   1137: checkcast java/math/BigInteger
    //   1140: invokevirtual intValue : ()I
    //   1143: bipush #32
    //   1145: irem
    //   1146: invokestatic abs : (I)I
    //   1149: invokevirtual charAt : (I)C
    //   1152: invokevirtual append : (C)Ljava/lang/StringBuilder;
    //   1155: pop
    //   1156: iload_2
    //   1157: ifne -> 1348
    //   1160: goto -> 1167
    //   1163: invokestatic a : (Ljava/lang/Throwable;)Ljava/lang/Throwable;
    //   1166: athrow
    //   1167: aload_3
    //   1168: getstatic burp/Zzb2.ZJ : Ljava/lang/String;
    //   1171: getstatic burp/Zlpj.Zc : Ljava/lang/Object;
    //   1174: checkcast java/math/BigInteger
    //   1177: invokevirtual intValue : ()I
    //   1180: bipush #32
    //   1182: irem
    //   1183: invokestatic abs : (I)I
    //   1186: invokevirtual charAt : (I)C
    //   1189: invokevirtual append : (C)Ljava/lang/StringBuilder;
    //   1192: pop
    //   1193: iload_2
    //   1194: ifne -> 1348
    //   1197: goto -> 1204
    //   1200: invokestatic a : (Ljava/lang/Throwable;)Ljava/lang/Throwable;
    //   1203: athrow
    //   1204: aload_3
    //   1205: getstatic burp/Zb9k.Za : Ljava/lang/String;
    //   1208: getstatic burp/Zemp.Zr : Ljava/lang/Object;
    //   1211: checkcast java/math/BigInteger
    //   1214: invokevirtual intValue : ()I
    //   1217: bipush #32
    //   1219: irem
    //   1220: invokestatic abs : (I)I
    //   1223: invokevirtual charAt : (I)C
    //   1226: invokevirtual append : (C)Ljava/lang/StringBuilder;
    //   1229: pop
    //   1230: iload_2
    //   1231: ifne -> 1348
    //   1234: goto -> 1241
    //   1237: invokestatic a : (Ljava/lang/Throwable;)Ljava/lang/Throwable;
    //   1240: athrow
    //   1241: aload_3
    //   1242: getstatic burp/Zlp8.ZW : Ljava/lang/String;
    //   1245: getstatic burp/Zsq6.ZS : Ljava/lang/Object;
    //   1248: checkcast java/math/BigInteger
    //   1251: invokevirtual intValue : ()I
    //   1254: bipush #32
    //   1256: irem
    //   1257: invokestatic abs : (I)I
    //   1260: invokevirtual charAt : (I)C
    //   1263: invokevirtual append : (C)Ljava/lang/StringBuilder;
    //   1266: pop
    //   1267: iload_2
    //   1268: ifne -> 1348
    //   1271: goto -> 1278
    //   1274: invokestatic a : (Ljava/lang/Throwable;)Ljava/lang/Throwable;
    //   1277: athrow
    //   1278: aload_3
    //   1279: getstatic burp/Zeoa.Zn : Ljava/lang/String;
    //   1282: getstatic burp/Zzxs.Zg : Ljava/lang/Object;
    //   1285: checkcast java/math/BigInteger
    //   1288: invokevirtual intValue : ()I
    //   1291: bipush #32
    //   1293: irem
    //   1294: invokestatic abs : (I)I
    //   1297: invokevirtual charAt : (I)C
    //   1300: invokevirtual append : (C)Ljava/lang/StringBuilder;
    //   1303: pop
    //   1304: iload_2
    //   1305: ifne -> 1348
    //   1308: goto -> 1315
    //   1311: invokestatic a : (Ljava/lang/Throwable;)Ljava/lang/Throwable;
    //   1314: athrow
    //   1315: aload_3
    //   1316: getstatic burp/Zxe.ZD : Ljava/lang/String;
    //   1319: getstatic burp/Zm5s.ZB : Ljava/lang/Object;
    //   1322: checkcast java/math/BigInteger
    //   1325: invokevirtual intValue : ()I
    //   1328: bipush #32
    //   1330: irem
    //   1331: invokestatic abs : (I)I
    //   1334: invokevirtual charAt : (I)C
    //   1337: invokevirtual append : (C)Ljava/lang/StringBuilder;
    //   1340: pop
    //   1341: goto -> 1348
    //   1344: invokestatic a : (Ljava/lang/Throwable;)Ljava/lang/Throwable;
    //   1347: athrow
    //   1348: iinc #4, 1
    //   1351: iload_2
    //   1352: ifne -> 15
    //   1355: aload_3
    //   1356: invokevirtual toString : ()Ljava/lang/String;
    //   1359: putstatic burp/Zl_k.Zw : Ljava/lang/String;
    //   1362: new java/lang/StringBuilder
    //   1365: dup
    //   1366: invokespecial <init> : ()V
    //   1369: astore #4
    //   1371: iconst_0
    //   1372: istore #5
    //   1374: iload #5
    //   1376: bipush #32
    //   1378: if_icmpge -> 2743
    //   1381: iload #5
    //   1383: tableswitch default -> 2736, 0 -> 1524, 1 -> 1562, 2 -> 1600, 3 -> 1638, 4 -> 1676, 5 -> 1714, 6 -> 1752, 7 -> 1790, 8 -> 1828, 9 -> 1866, 10 -> 1904, 11 -> 1942, 12 -> 1980, 13 -> 2018, 14 -> 2056, 15 -> 2094, 16 -> 2132, 17 -> 2170, 18 -> 2208, 19 -> 2246, 20 -> 2284, 21 -> 2322, 22 -> 2360, 23 -> 2398, 24 -> 2436, 25 -> 2474, 26 -> 2512, 27 -> 2550, 28 -> 2588, 29 -> 2626, 30 -> 2664, 31 -> 2702
    //   1524: aload #4
    //   1526: getstatic burp/Zb6a.ZY : Ljava/lang/String;
    //   1529: getstatic burp/Zgvl.ZK : Ljava/lang/Object;
    //   1532: checkcast java/math/BigInteger
    //   1535: invokevirtual intValue : ()I
    //   1538: bipush #32
    //   1540: irem
    //   1541: invokestatic abs : (I)I
    //   1544: invokevirtual charAt : (I)C
    //   1547: invokevirtual append : (C)Ljava/lang/StringBuilder;
    //   1550: pop
    //   1551: iload_2
    //   1552: ifne -> 2736
    //   1555: goto -> 1562
    //   1558: invokestatic a : (Ljava/lang/Throwable;)Ljava/lang/Throwable;
    //   1561: athrow
    //   1562: aload #4
    //   1564: getstatic burp/Zt7k.ZH : Ljava/lang/String;
    //   1567: getstatic burp/Ztzj.Zv : Ljava/lang/Object;
    //   1570: checkcast java/math/BigInteger
    //   1573: invokevirtual intValue : ()I
    //   1576: bipush #32
    //   1578: irem
    //   1579: invokestatic abs : (I)I
    //   1582: invokevirtual charAt : (I)C
    //   1585: invokevirtual append : (C)Ljava/lang/StringBuilder;
    //   1588: pop
    //   1589: iload_2
    //   1590: ifne -> 2736
    //   1593: goto -> 1600
    //   1596: invokestatic a : (Ljava/lang/Throwable;)Ljava/lang/Throwable;
    //   1599: athrow
    //   1600: aload #4
    //   1602: getstatic burp/Zlp8.ZW : Ljava/lang/String;
    //   1605: getstatic burp/Zrd3.ZI : Ljava/lang/Object;
    //   1608: checkcast java/math/BigInteger
    //   1611: invokevirtual intValue : ()I
    //   1614: bipush #32
    //   1616: irem
    //   1617: invokestatic abs : (I)I
    //   1620: invokevirtual charAt : (I)C
    //   1623: invokevirtual append : (C)Ljava/lang/StringBuilder;
    //   1626: pop
    //   1627: iload_2
    //   1628: ifne -> 2736
    //   1631: goto -> 1638
    //   1634: invokestatic a : (Ljava/lang/Throwable;)Ljava/lang/Throwable;
    //   1637: athrow
    //   1638: aload #4
    //   1640: getstatic burp/Zt5a.Zl : Ljava/lang/String;
    //   1643: getstatic burp/Zss6.ZG : Ljava/lang/Object;
    //   1646: checkcast java/math/BigInteger
    //   1649: invokevirtual intValue : ()I
    //   1652: bipush #32
    //   1654: irem
    //   1655: invokestatic abs : (I)I
    //   1658: invokevirtual charAt : (I)C
    //   1661: invokevirtual append : (C)Ljava/lang/StringBuilder;
    //   1664: pop
    //   1665: iload_2
    //   1666: ifne -> 2736
    //   1669: goto -> 1676
    //   1672: invokestatic a : (Ljava/lang/Throwable;)Ljava/lang/Throwable;
    //   1675: athrow
    //   1676: aload #4
    //   1678: getstatic burp/Ze_l.ZY : Ljava/lang/String;
    //   1681: getstatic burp/Zei_.Za : Ljava/lang/Object;
    //   1684: checkcast java/math/BigInteger
    //   1687: invokevirtual intValue : ()I
    //   1690: bipush #32
    //   1692: irem
    //   1693: invokestatic abs : (I)I
    //   1696: invokevirtual charAt : (I)C
    //   1699: invokevirtual append : (C)Ljava/lang/StringBuilder;
    //   1702: pop
    //   1703: iload_2
    //   1704: ifne -> 2736
    //   1707: goto -> 1714
    //   1710: invokestatic a : (Ljava/lang/Throwable;)Ljava/lang/Throwable;
    //   1713: athrow
    //   1714: aload #4
    //   1716: getstatic burp/Zxyq.Zr : Ljava/lang/String;
    //   1719: getstatic burp/Zzr5.Za : Ljava/lang/Object;
    //   1722: checkcast java/math/BigInteger
    //   1725: invokevirtual intValue : ()I
    //   1728: bipush #32
    //   1730: irem
    //   1731: invokestatic abs : (I)I
    //   1734: invokevirtual charAt : (I)C
    //   1737: invokevirtual append : (C)Ljava/lang/StringBuilder;
    //   1740: pop
    //   1741: iload_2
    //   1742: ifne -> 2736
    //   1745: goto -> 1752
    //   1748: invokestatic a : (Ljava/lang/Throwable;)Ljava/lang/Throwable;
    //   1751: athrow
    //   1752: aload #4
    //   1754: getstatic burp/Zlpu.ZA : Ljava/lang/String;
    //   1757: getstatic burp/Zgwu.ZD : Ljava/lang/Object;
    //   1760: checkcast java/math/BigInteger
    //   1763: invokevirtual intValue : ()I
    //   1766: bipush #32
    //   1768: irem
    //   1769: invokestatic abs : (I)I
    //   1772: invokevirtual charAt : (I)C
    //   1775: invokevirtual append : (C)Ljava/lang/StringBuilder;
    //   1778: pop
    //   1779: iload_2
    //   1780: ifne -> 2736
    //   1783: goto -> 1790
    //   1786: invokestatic a : (Ljava/lang/Throwable;)Ljava/lang/Throwable;
    //   1789: athrow
    //   1790: aload #4
    //   1792: getstatic burp/Zl8s.Zn : Ljava/lang/String;
    //   1795: getstatic burp/Zzh0.Z_ : Ljava/lang/Object;
    //   1798: checkcast java/math/BigInteger
    //   1801: invokevirtual intValue : ()I
    //   1804: bipush #32
    //   1806: irem
    //   1807: invokestatic abs : (I)I
    //   1810: invokevirtual charAt : (I)C
    //   1813: invokevirtual append : (C)Ljava/lang/StringBuilder;
    //   1816: pop
    //   1817: iload_2
    //   1818: ifne -> 2736
    //   1821: goto -> 1828
    //   1824: invokestatic a : (Ljava/lang/Throwable;)Ljava/lang/Throwable;
    //   1827: athrow
    //   1828: aload #4
    //   1830: getstatic burp/Zlvx.Zr : Ljava/lang/String;
    //   1833: getstatic burp/Zgz1.ZX : Ljava/lang/Object;
    //   1836: checkcast java/math/BigInteger
    //   1839: invokevirtual intValue : ()I
    //   1842: bipush #32
    //   1844: irem
    //   1845: invokestatic abs : (I)I
    //   1848: invokevirtual charAt : (I)C
    //   1851: invokevirtual append : (C)Ljava/lang/StringBuilder;
    //   1854: pop
    //   1855: iload_2
    //   1856: ifne -> 2736
    //   1859: goto -> 1866
    //   1862: invokestatic a : (Ljava/lang/Throwable;)Ljava/lang/Throwable;
    //   1865: athrow
    //   1866: aload #4
    //   1868: getstatic burp/Zg7j.ZR : Ljava/lang/String;
    //   1871: getstatic burp/Zefn.ZJ : Ljava/lang/Object;
    //   1874: checkcast java/math/BigInteger
    //   1877: invokevirtual intValue : ()I
    //   1880: bipush #32
    //   1882: irem
    //   1883: invokestatic abs : (I)I
    //   1886: invokevirtual charAt : (I)C
    //   1889: invokevirtual append : (C)Ljava/lang/StringBuilder;
    //   1892: pop
    //   1893: iload_2
    //   1894: ifne -> 2736
    //   1897: goto -> 1904
    //   1900: invokestatic a : (Ljava/lang/Throwable;)Ljava/lang/Throwable;
    //   1903: athrow
    //   1904: aload #4
    //   1906: getstatic burp/Zmd.Zf : Ljava/lang/String;
    //   1909: getstatic burp/Zg99.ZZ : Ljava/lang/Object;
    //   1912: checkcast java/math/BigInteger
    //   1915: invokevirtual intValue : ()I
    //   1918: bipush #32
    //   1920: irem
    //   1921: invokestatic abs : (I)I
    //   1924: invokevirtual charAt : (I)C
    //   1927: invokevirtual append : (C)Ljava/lang/StringBuilder;
    //   1930: pop
    //   1931: iload_2
    //   1932: ifne -> 2736
    //   1935: goto -> 1942
    //   1938: invokestatic a : (Ljava/lang/Throwable;)Ljava/lang/Throwable;
    //   1941: athrow
    //   1942: aload #4
    //   1944: getstatic burp/Zlnq.ZQ : Ljava/lang/String;
    //   1947: getstatic burp/Zli5.Zt : Ljava/lang/Object;
    //   1950: checkcast java/math/BigInteger
    //   1953: invokevirtual intValue : ()I
    //   1956: bipush #32
    //   1958: irem
    //   1959: invokestatic abs : (I)I
    //   1962: invokevirtual charAt : (I)C
    //   1965: invokevirtual append : (C)Ljava/lang/StringBuilder;
    //   1968: pop
    //   1969: iload_2
    //   1970: ifne -> 2736
    //   1973: goto -> 1980
    //   1976: invokestatic a : (Ljava/lang/Throwable;)Ljava/lang/Throwable;
    //   1979: athrow
    //   1980: aload #4
    //   1982: getstatic burp/Zll8.ZZ : Ljava/lang/String;
    //   1985: getstatic burp/Ztq8.Zm : Ljava/lang/Object;
    //   1988: checkcast java/math/BigInteger
    //   1991: invokevirtual intValue : ()I
    //   1994: bipush #32
    //   1996: irem
    //   1997: invokestatic abs : (I)I
    //   2000: invokevirtual charAt : (I)C
    //   2003: invokevirtual append : (C)Ljava/lang/StringBuilder;
    //   2006: pop
    //   2007: iload_2
    //   2008: ifne -> 2736
    //   2011: goto -> 2018
    //   2014: invokestatic a : (Ljava/lang/Throwable;)Ljava/lang/Throwable;
    //   2017: athrow
    //   2018: aload #4
    //   2020: getstatic burp/Zbzk.ZS : Ljava/lang/String;
    //   2023: getstatic burp/Ztip.Zc : Ljava/lang/Object;
    //   2026: checkcast java/math/BigInteger
    //   2029: invokevirtual intValue : ()I
    //   2032: bipush #32
    //   2034: irem
    //   2035: invokestatic abs : (I)I
    //   2038: invokevirtual charAt : (I)C
    //   2041: invokevirtual append : (C)Ljava/lang/StringBuilder;
    //   2044: pop
    //   2045: iload_2
    //   2046: ifne -> 2736
    //   2049: goto -> 2056
    //   2052: invokestatic a : (Ljava/lang/Throwable;)Ljava/lang/Throwable;
    //   2055: athrow
    //   2056: aload #4
    //   2058: getstatic burp/Zsot.Zb : Ljava/lang/String;
    //   2061: getstatic burp/Zzym.ZK : Ljava/lang/Object;
    //   2064: checkcast java/math/BigInteger
    //   2067: invokevirtual intValue : ()I
    //   2070: bipush #32
    //   2072: irem
    //   2073: invokestatic abs : (I)I
    //   2076: invokevirtual charAt : (I)C
    //   2079: invokevirtual append : (C)Ljava/lang/StringBuilder;
    //   2082: pop
    //   2083: iload_2
    //   2084: ifne -> 2736
    //   2087: goto -> 2094
    //   2090: invokestatic a : (Ljava/lang/Throwable;)Ljava/lang/Throwable;
    //   2093: athrow
    //   2094: aload #4
    //   2096: getstatic burp/Zkm0.ZL : Ljava/lang/String;
    //   2099: getstatic burp/Zzxa.ZI : Ljava/lang/Object;
    //   2102: checkcast java/math/BigInteger
    //   2105: invokevirtual intValue : ()I
    //   2108: bipush #32
    //   2110: irem
    //   2111: invokestatic abs : (I)I
    //   2114: invokevirtual charAt : (I)C
    //   2117: invokevirtual append : (C)Ljava/lang/StringBuilder;
    //   2120: pop
    //   2121: iload_2
    //   2122: ifne -> 2736
    //   2125: goto -> 2132
    //   2128: invokestatic a : (Ljava/lang/Throwable;)Ljava/lang/Throwable;
    //   2131: athrow
    //   2132: aload #4
    //   2134: getstatic burp/Zz0.ZX : Ljava/lang/String;
    //   2137: getstatic burp/Zzr5.Za : Ljava/lang/Object;
    //   2140: checkcast java/math/BigInteger
    //   2143: invokevirtual intValue : ()I
    //   2146: bipush #32
    //   2148: irem
    //   2149: invokestatic abs : (I)I
    //   2152: invokevirtual charAt : (I)C
    //   2155: invokevirtual append : (C)Ljava/lang/StringBuilder;
    //   2158: pop
    //   2159: iload_2
    //   2160: ifne -> 2736
    //   2163: goto -> 2170
    //   2166: invokestatic a : (Ljava/lang/Throwable;)Ljava/lang/Throwable;
    //   2169: athrow
    //   2170: aload #4
    //   2172: getstatic burp/Zeuz.Zb : Ljava/lang/String;
    //   2175: getstatic burp/Zt4g.Zv : Ljava/lang/Object;
    //   2178: checkcast java/math/BigInteger
    //   2181: invokevirtual intValue : ()I
    //   2184: bipush #32
    //   2186: irem
    //   2187: invokestatic abs : (I)I
    //   2190: invokevirtual charAt : (I)C
    //   2193: invokevirtual append : (C)Ljava/lang/StringBuilder;
    //   2196: pop
    //   2197: iload_2
    //   2198: ifne -> 2736
    //   2201: goto -> 2208
    //   2204: invokestatic a : (Ljava/lang/Throwable;)Ljava/lang/Throwable;
    //   2207: athrow
    //   2208: aload #4
    //   2210: getstatic burp/Zlbr.Zr : Ljava/lang/String;
    //   2213: getstatic burp/Zkfz.Zr : Ljava/lang/Object;
    //   2216: checkcast java/math/BigInteger
    //   2219: invokevirtual intValue : ()I
    //   2222: bipush #32
    //   2224: irem
    //   2225: invokestatic abs : (I)I
    //   2228: invokevirtual charAt : (I)C
    //   2231: invokevirtual append : (C)Ljava/lang/StringBuilder;
    //   2234: pop
    //   2235: iload_2
    //   2236: ifne -> 2736
    //   2239: goto -> 2246
    //   2242: invokestatic a : (Ljava/lang/Throwable;)Ljava/lang/Throwable;
    //   2245: athrow
    //   2246: aload #4
    //   2248: getstatic burp/Zmhx.ZD : Ljava/lang/String;
    //   2251: getstatic burp/Zeb7.ZJ : Ljava/lang/Object;
    //   2254: checkcast java/math/BigInteger
    //   2257: invokevirtual intValue : ()I
    //   2260: bipush #32
    //   2262: irem
    //   2263: invokestatic abs : (I)I
    //   2266: invokevirtual charAt : (I)C
    //   2269: invokevirtual append : (C)Ljava/lang/StringBuilder;
    //   2272: pop
    //   2273: iload_2
    //   2274: ifne -> 2736
    //   2277: goto -> 2284
    //   2280: invokestatic a : (Ljava/lang/Throwable;)Ljava/lang/Throwable;
    //   2283: athrow
    //   2284: aload #4
    //   2286: getstatic burp/Zbqo.ZS : Ljava/lang/String;
    //   2289: getstatic burp/Zevf.Zu : Ljava/lang/Object;
    //   2292: checkcast java/math/BigInteger
    //   2295: invokevirtual intValue : ()I
    //   2298: bipush #32
    //   2300: irem
    //   2301: invokestatic abs : (I)I
    //   2304: invokevirtual charAt : (I)C
    //   2307: invokevirtual append : (C)Ljava/lang/StringBuilder;
    //   2310: pop
    //   2311: iload_2
    //   2312: ifne -> 2736
    //   2315: goto -> 2322
    //   2318: invokestatic a : (Ljava/lang/Throwable;)Ljava/lang/Throwable;
    //   2321: athrow
    //   2322: aload #4
    //   2324: getstatic burp/Zr8s.ZA : Ljava/lang/String;
    //   2327: getstatic burp/Zx_u.Zy : Ljava/lang/Object;
    //   2330: checkcast java/math/BigInteger
    //   2333: invokevirtual intValue : ()I
    //   2336: bipush #32
    //   2338: irem
    //   2339: invokestatic abs : (I)I
    //   2342: invokevirtual charAt : (I)C
    //   2345: invokevirtual append : (C)Ljava/lang/StringBuilder;
    //   2348: pop
    //   2349: iload_2
    //   2350: ifne -> 2736
    //   2353: goto -> 2360
    //   2356: invokestatic a : (Ljava/lang/Throwable;)Ljava/lang/Throwable;
    //   2359: athrow
    //   2360: aload #4
    //   2362: getstatic burp/Zmjr.Zc : Ljava/lang/String;
    //   2365: getstatic burp/Zg68.Zs : Ljava/lang/Object;
    //   2368: checkcast java/math/BigInteger
    //   2371: invokevirtual intValue : ()I
    //   2374: bipush #32
    //   2376: irem
    //   2377: invokestatic abs : (I)I
    //   2380: invokevirtual charAt : (I)C
    //   2383: invokevirtual append : (C)Ljava/lang/StringBuilder;
    //   2386: pop
    //   2387: iload_2
    //   2388: ifne -> 2736
    //   2391: goto -> 2398
    //   2394: invokestatic a : (Ljava/lang/Throwable;)Ljava/lang/Throwable;
    //   2397: athrow
    //   2398: aload #4
    //   2400: getstatic burp/Zl22.ZL : Ljava/lang/String;
    //   2403: getstatic burp/Zlsw.ZJ : Ljava/lang/Object;
    //   2406: checkcast java/math/BigInteger
    //   2409: invokevirtual intValue : ()I
    //   2412: bipush #32
    //   2414: irem
    //   2415: invokestatic abs : (I)I
    //   2418: invokevirtual charAt : (I)C
    //   2421: invokevirtual append : (C)Ljava/lang/StringBuilder;
    //   2424: pop
    //   2425: iload_2
    //   2426: ifne -> 2736
    //   2429: goto -> 2436
    //   2432: invokestatic a : (Ljava/lang/Throwable;)Ljava/lang/Throwable;
    //   2435: athrow
    //   2436: aload #4
    //   2438: getstatic burp/Zb8y.Zn : Ljava/lang/String;
    //   2441: getstatic burp/Zlkm.ZQ : Ljava/lang/Object;
    //   2444: checkcast java/math/BigInteger
    //   2447: invokevirtual intValue : ()I
    //   2450: bipush #32
    //   2452: irem
    //   2453: invokestatic abs : (I)I
    //   2456: invokevirtual charAt : (I)C
    //   2459: invokevirtual append : (C)Ljava/lang/StringBuilder;
    //   2462: pop
    //   2463: iload_2
    //   2464: ifne -> 2736
    //   2467: goto -> 2474
    //   2470: invokestatic a : (Ljava/lang/Throwable;)Ljava/lang/Throwable;
    //   2473: athrow
    //   2474: aload #4
    //   2476: getstatic burp/Zetv.ZE : Ljava/lang/String;
    //   2479: getstatic burp/Zl55.ZZ : Ljava/lang/Object;
    //   2482: checkcast java/math/BigInteger
    //   2485: invokevirtual intValue : ()I
    //   2488: bipush #32
    //   2490: irem
    //   2491: invokestatic abs : (I)I
    //   2494: invokevirtual charAt : (I)C
    //   2497: invokevirtual append : (C)Ljava/lang/StringBuilder;
    //   2500: pop
    //   2501: iload_2
    //   2502: ifne -> 2736
    //   2505: goto -> 2512
    //   2508: invokestatic a : (Ljava/lang/Throwable;)Ljava/lang/Throwable;
    //   2511: athrow
    //   2512: aload #4
    //   2514: getstatic burp/Zlum.ZW : Ljava/lang/String;
    //   2517: getstatic burp/Zs9k.ZX : Ljava/lang/Object;
    //   2520: checkcast java/math/BigInteger
    //   2523: invokevirtual intValue : ()I
    //   2526: bipush #32
    //   2528: irem
    //   2529: invokestatic abs : (I)I
    //   2532: invokevirtual charAt : (I)C
    //   2535: invokevirtual append : (C)Ljava/lang/StringBuilder;
    //   2538: pop
    //   2539: iload_2
    //   2540: ifne -> 2736
    //   2543: goto -> 2550
    //   2546: invokestatic a : (Ljava/lang/Throwable;)Ljava/lang/Throwable;
    //   2549: athrow
    //   2550: aload #4
    //   2552: getstatic burp/Zenr.Z_ : Ljava/lang/String;
    //   2555: getstatic burp/Zrfh.ZJ : Ljava/lang/Object;
    //   2558: checkcast java/math/BigInteger
    //   2561: invokevirtual intValue : ()I
    //   2564: bipush #32
    //   2566: irem
    //   2567: invokestatic abs : (I)I
    //   2570: invokevirtual charAt : (I)C
    //   2573: invokevirtual append : (C)Ljava/lang/StringBuilder;
    //   2576: pop
    //   2577: iload_2
    //   2578: ifne -> 2736
    //   2581: goto -> 2588
    //   2584: invokestatic a : (Ljava/lang/Throwable;)Ljava/lang/Throwable;
    //   2587: athrow
    //   2588: aload #4
    //   2590: getstatic burp/Zlxm.Zv : Ljava/lang/String;
    //   2593: getstatic burp/Zgx6.Zo : Ljava/lang/Object;
    //   2596: checkcast java/math/BigInteger
    //   2599: invokevirtual intValue : ()I
    //   2602: bipush #32
    //   2604: irem
    //   2605: invokestatic abs : (I)I
    //   2608: invokevirtual charAt : (I)C
    //   2611: invokevirtual append : (C)Ljava/lang/StringBuilder;
    //   2614: pop
    //   2615: iload_2
    //   2616: ifne -> 2736
    //   2619: goto -> 2626
    //   2622: invokestatic a : (Ljava/lang/Throwable;)Ljava/lang/Throwable;
    //   2625: athrow
    //   2626: aload #4
    //   2628: getstatic burp/Zg7p.ZA : Ljava/lang/String;
    //   2631: getstatic burp/Zejj.Zy : Ljava/lang/Object;
    //   2634: checkcast java/math/BigInteger
    //   2637: invokevirtual intValue : ()I
    //   2640: bipush #32
    //   2642: irem
    //   2643: invokestatic abs : (I)I
    //   2646: invokevirtual charAt : (I)C
    //   2649: invokevirtual append : (C)Ljava/lang/StringBuilder;
    //   2652: pop
    //   2653: iload_2
    //   2654: ifne -> 2736
    //   2657: goto -> 2664
    //   2660: invokestatic a : (Ljava/lang/Throwable;)Ljava/lang/Throwable;
    //   2663: athrow
    //   2664: aload #4
    //   2666: getstatic burp/Zzi_.ZG : Ljava/lang/String;
    //   2669: getstatic burp/Ztap.ZK : Ljava/lang/Object;
    //   2672: checkcast java/math/BigInteger
    //   2675: invokevirtual intValue : ()I
    //   2678: bipush #32
    //   2680: irem
    //   2681: invokestatic abs : (I)I
    //   2684: invokevirtual charAt : (I)C
    //   2687: invokevirtual append : (C)Ljava/lang/StringBuilder;
    //   2690: pop
    //   2691: iload_2
    //   2692: ifne -> 2736
    //   2695: goto -> 2702
    //   2698: invokestatic a : (Ljava/lang/Throwable;)Ljava/lang/Throwable;
    //   2701: athrow
    //   2702: aload #4
    //   2704: getstatic burp/Zlpn.ZF : Ljava/lang/String;
    //   2707: getstatic burp/Zql.Zt : Ljava/lang/Object;
    //   2710: checkcast java/math/BigInteger
    //   2713: invokevirtual intValue : ()I
    //   2716: bipush #32
    //   2718: irem
    //   2719: invokestatic abs : (I)I
    //   2722: invokevirtual charAt : (I)C
    //   2725: invokevirtual append : (C)Ljava/lang/StringBuilder;
    //   2728: pop
    //   2729: goto -> 2736
    //   2732: invokestatic a : (Ljava/lang/Throwable;)Ljava/lang/Throwable;
    //   2735: athrow
    //   2736: iinc #5, 1
    //   2739: iload_2
    //   2740: ifne -> 1374
    //   2743: aload #4
    //   2745: invokevirtual toString : ()Ljava/lang/String;
    //   2748: putstatic burp/Zrnu.ZO : Ljava/lang/String;
    //   2751: new java/lang/StringBuilder
    //   2754: dup
    //   2755: invokespecial <init> : ()V
    //   2758: astore #5
    //   2760: iconst_0
    //   2761: istore #6
    //   2763: iload #6
    //   2765: bipush #32
    //   2767: if_icmpge -> 4135
    //   2770: iload #6
    //   2772: tableswitch default -> 4128, 0 -> 2916, 1 -> 2954, 2 -> 2992, 3 -> 3030, 4 -> 3068, 5 -> 3106, 6 -> 3144, 7 -> 3182, 8 -> 3220, 9 -> 3258, 10 -> 3296, 11 -> 3334, 12 -> 3372, 13 -> 3410, 14 -> 3448, 15 -> 3486, 16 -> 3524, 17 -> 3562, 18 -> 3600, 19 -> 3638, 20 -> 3676, 21 -> 3714, 22 -> 3752, 23 -> 3790, 24 -> 3828, 25 -> 3866, 26 -> 3904, 27 -> 3942, 28 -> 3980, 29 -> 4018, 30 -> 4056, 31 -> 4094
    //   2916: aload #5
    //   2918: getstatic burp/Zb9k.Za : Ljava/lang/String;
    //   2921: getstatic burp/Zmt_.Zl : Ljava/lang/Object;
    //   2924: checkcast java/math/BigInteger
    //   2927: invokevirtual intValue : ()I
    //   2930: bipush #32
    //   2932: irem
    //   2933: invokestatic abs : (I)I
    //   2936: invokevirtual charAt : (I)C
    //   2939: invokevirtual append : (C)Ljava/lang/StringBuilder;
    //   2942: pop
    //   2943: iload_2
    //   2944: ifne -> 4128
    //   2947: goto -> 2954
    //   2950: invokestatic a : (Ljava/lang/Throwable;)Ljava/lang/Throwable;
    //   2953: athrow
    //   2954: aload #5
    //   2956: getstatic burp/Zt7j.Zx : Ljava/lang/String;
    //   2959: getstatic burp/Ze0w.ZU : Ljava/lang/Object;
    //   2962: checkcast java/math/BigInteger
    //   2965: invokevirtual intValue : ()I
    //   2968: bipush #32
    //   2970: irem
    //   2971: invokestatic abs : (I)I
    //   2974: invokevirtual charAt : (I)C
    //   2977: invokevirtual append : (C)Ljava/lang/StringBuilder;
    //   2980: pop
    //   2981: iload_2
    //   2982: ifne -> 4128
    //   2985: goto -> 2992
    //   2988: invokestatic a : (Ljava/lang/Throwable;)Ljava/lang/Throwable;
    //   2991: athrow
    //   2992: aload #5
    //   2994: getstatic burp/Zlh2.Zf : Ljava/lang/String;
    //   2997: getstatic burp/Zgyk.ZO : Ljava/lang/Object;
    //   3000: checkcast java/math/BigInteger
    //   3003: invokevirtual intValue : ()I
    //   3006: bipush #32
    //   3008: irem
    //   3009: invokestatic abs : (I)I
    //   3012: invokevirtual charAt : (I)C
    //   3015: invokevirtual append : (C)Ljava/lang/StringBuilder;
    //   3018: pop
    //   3019: iload_2
    //   3020: ifne -> 4128
    //   3023: goto -> 3030
    //   3026: invokestatic a : (Ljava/lang/Throwable;)Ljava/lang/Throwable;
    //   3029: athrow
    //   3030: aload #5
    //   3032: getstatic burp/Zeu2.ZK : Ljava/lang/String;
    //   3035: getstatic burp/Zrc0.Zz : Ljava/lang/Object;
    //   3038: checkcast java/math/BigInteger
    //   3041: invokevirtual intValue : ()I
    //   3044: bipush #32
    //   3046: irem
    //   3047: invokestatic abs : (I)I
    //   3050: invokevirtual charAt : (I)C
    //   3053: invokevirtual append : (C)Ljava/lang/StringBuilder;
    //   3056: pop
    //   3057: iload_2
    //   3058: ifne -> 4128
    //   3061: goto -> 3068
    //   3064: invokestatic a : (Ljava/lang/Throwable;)Ljava/lang/Throwable;
    //   3067: athrow
    //   3068: aload #5
    //   3070: getstatic burp/Zt0t.ZR : Ljava/lang/String;
    //   3073: getstatic burp/Zrqd.Zi : Ljava/lang/Object;
    //   3076: checkcast java/math/BigInteger
    //   3079: invokevirtual intValue : ()I
    //   3082: bipush #32
    //   3084: irem
    //   3085: invokestatic abs : (I)I
    //   3088: invokevirtual charAt : (I)C
    //   3091: invokevirtual append : (C)Ljava/lang/StringBuilder;
    //   3094: pop
    //   3095: iload_2
    //   3096: ifne -> 4128
    //   3099: goto -> 3106
    //   3102: invokestatic a : (Ljava/lang/Throwable;)Ljava/lang/Throwable;
    //   3105: athrow
    //   3106: aload #5
    //   3108: getstatic burp/Zmy3.ZP : Ljava/lang/String;
    //   3111: getstatic burp/Zttq.Zh : Ljava/lang/Object;
    //   3114: checkcast java/math/BigInteger
    //   3117: invokevirtual intValue : ()I
    //   3120: bipush #32
    //   3122: irem
    //   3123: invokestatic abs : (I)I
    //   3126: invokevirtual charAt : (I)C
    //   3129: invokevirtual append : (C)Ljava/lang/StringBuilder;
    //   3132: pop
    //   3133: iload_2
    //   3134: ifne -> 4128
    //   3137: goto -> 3144
    //   3140: invokestatic a : (Ljava/lang/Throwable;)Ljava/lang/Throwable;
    //   3143: athrow
    //   3144: aload #5
    //   3146: getstatic burp/Zter.ZE : Ljava/lang/String;
    //   3149: getstatic burp/Zmou.ZT : Ljava/lang/Object;
    //   3152: checkcast java/math/BigInteger
    //   3155: invokevirtual intValue : ()I
    //   3158: bipush #32
    //   3160: irem
    //   3161: invokestatic abs : (I)I
    //   3164: invokevirtual charAt : (I)C
    //   3167: invokevirtual append : (C)Ljava/lang/StringBuilder;
    //   3170: pop
    //   3171: iload_2
    //   3172: ifne -> 4128
    //   3175: goto -> 3182
    //   3178: invokestatic a : (Ljava/lang/Throwable;)Ljava/lang/Throwable;
    //   3181: athrow
    //   3182: aload #5
    //   3184: getstatic burp/Zlhz.Zo : Ljava/lang/String;
    //   3187: getstatic burp/Zlhm.ZT : Ljava/lang/Object;
    //   3190: checkcast java/math/BigInteger
    //   3193: invokevirtual intValue : ()I
    //   3196: bipush #32
    //   3198: irem
    //   3199: invokestatic abs : (I)I
    //   3202: invokevirtual charAt : (I)C
    //   3205: invokevirtual append : (C)Ljava/lang/StringBuilder;
    //   3208: pop
    //   3209: iload_2
    //   3210: ifne -> 4128
    //   3213: goto -> 3220
    //   3216: invokestatic a : (Ljava/lang/Throwable;)Ljava/lang/Throwable;
    //   3219: athrow
    //   3220: aload #5
    //   3222: getstatic burp/Zmy4.ZS : Ljava/lang/String;
    //   3225: getstatic burp/Zkv2.ZC : Ljava/lang/Object;
    //   3228: checkcast java/math/BigInteger
    //   3231: invokevirtual intValue : ()I
    //   3234: bipush #32
    //   3236: irem
    //   3237: invokestatic abs : (I)I
    //   3240: invokevirtual charAt : (I)C
    //   3243: invokevirtual append : (C)Ljava/lang/StringBuilder;
    //   3246: pop
    //   3247: iload_2
    //   3248: ifne -> 4128
    //   3251: goto -> 3258
    //   3254: invokestatic a : (Ljava/lang/Throwable;)Ljava/lang/Throwable;
    //   3257: athrow
    //   3258: aload #5
    //   3260: getstatic burp/Zk9s.ZM : Ljava/lang/String;
    //   3263: getstatic burp/Zli5.Zt : Ljava/lang/Object;
    //   3266: checkcast java/math/BigInteger
    //   3269: invokevirtual intValue : ()I
    //   3272: bipush #32
    //   3274: irem
    //   3275: invokestatic abs : (I)I
    //   3278: invokevirtual charAt : (I)C
    //   3281: invokevirtual append : (C)Ljava/lang/StringBuilder;
    //   3284: pop
    //   3285: iload_2
    //   3286: ifne -> 4128
    //   3289: goto -> 3296
    //   3292: invokestatic a : (Ljava/lang/Throwable;)Ljava/lang/Throwable;
    //   3295: athrow
    //   3296: aload #5
    //   3298: getstatic burp/Zrpx.ZM : Ljava/lang/String;
    //   3301: getstatic burp/Zg7w.Zy : Ljava/lang/Object;
    //   3304: checkcast java/math/BigInteger
    //   3307: invokevirtual intValue : ()I
    //   3310: bipush #32
    //   3312: irem
    //   3313: invokestatic abs : (I)I
    //   3316: invokevirtual charAt : (I)C
    //   3319: invokevirtual append : (C)Ljava/lang/StringBuilder;
    //   3322: pop
    //   3323: iload_2
    //   3324: ifne -> 4128
    //   3327: goto -> 3334
    //   3330: invokestatic a : (Ljava/lang/Throwable;)Ljava/lang/Throwable;
    //   3333: athrow
    //   3334: aload #5
    //   3336: getstatic burp/Zl50.Zm : Ljava/lang/String;
    //   3339: getstatic burp/Zlsg.ZD : Ljava/lang/Object;
    //   3342: checkcast java/math/BigInteger
    //   3345: invokevirtual intValue : ()I
    //   3348: bipush #32
    //   3350: irem
    //   3351: invokestatic abs : (I)I
    //   3354: invokevirtual charAt : (I)C
    //   3357: invokevirtual append : (C)Ljava/lang/StringBuilder;
    //   3360: pop
    //   3361: iload_2
    //   3362: ifne -> 4128
    //   3365: goto -> 3372
    //   3368: invokestatic a : (Ljava/lang/Throwable;)Ljava/lang/Throwable;
    //   3371: athrow
    //   3372: aload #5
    //   3374: getstatic burp/Zemp.Zs : Ljava/lang/String;
    //   3377: getstatic burp/Zm5p.Ze : Ljava/lang/Object;
    //   3380: checkcast java/math/BigInteger
    //   3383: invokevirtual intValue : ()I
    //   3386: bipush #32
    //   3388: irem
    //   3389: invokestatic abs : (I)I
    //   3392: invokevirtual charAt : (I)C
    //   3395: invokevirtual append : (C)Ljava/lang/StringBuilder;
    //   3398: pop
    //   3399: iload_2
    //   3400: ifne -> 4128
    //   3403: goto -> 3410
    //   3406: invokestatic a : (Ljava/lang/Throwable;)Ljava/lang/Throwable;
    //   3409: athrow
    //   3410: aload #5
    //   3412: getstatic burp/Zsf4.ZA : Ljava/lang/String;
    //   3415: getstatic burp/Zkvr.Zb : Ljava/lang/Object;
    //   3418: checkcast java/math/BigInteger
    //   3421: invokevirtual intValue : ()I
    //   3424: bipush #32
    //   3426: irem
    //   3427: invokestatic abs : (I)I
    //   3430: invokevirtual charAt : (I)C
    //   3433: invokevirtual append : (C)Ljava/lang/StringBuilder;
    //   3436: pop
    //   3437: iload_2
    //   3438: ifne -> 4128
    //   3441: goto -> 3448
    //   3444: invokestatic a : (Ljava/lang/Throwable;)Ljava/lang/Throwable;
    //   3447: athrow
    //   3448: aload #5
    //   3450: getstatic burp/Zefn.Ze : Ljava/lang/String;
    //   3453: getstatic burp/Zgk1.ZD : Ljava/lang/Object;
    //   3456: checkcast java/math/BigInteger
    //   3459: invokevirtual intValue : ()I
    //   3462: bipush #32
    //   3464: irem
    //   3465: invokestatic abs : (I)I
    //   3468: invokevirtual charAt : (I)C
    //   3471: invokevirtual append : (C)Ljava/lang/StringBuilder;
    //   3474: pop
    //   3475: iload_2
    //   3476: ifne -> 4128
    //   3479: goto -> 3486
    //   3482: invokestatic a : (Ljava/lang/Throwable;)Ljava/lang/Throwable;
    //   3485: athrow
    //   3486: aload #5
    //   3488: getstatic burp/Zrbp.Ze : Ljava/lang/String;
    //   3491: getstatic burp/Zkw.ZY : Ljava/lang/Object;
    //   3494: checkcast java/math/BigInteger
    //   3497: invokevirtual intValue : ()I
    //   3500: bipush #32
    //   3502: irem
    //   3503: invokestatic abs : (I)I
    //   3506: invokevirtual charAt : (I)C
    //   3509: invokevirtual append : (C)Ljava/lang/StringBuilder;
    //   3512: pop
    //   3513: iload_2
    //   3514: ifne -> 4128
    //   3517: goto -> 3524
    //   3520: invokestatic a : (Ljava/lang/Throwable;)Ljava/lang/Throwable;
    //   3523: athrow
    //   3524: aload #5
    //   3526: getstatic burp/Zter.ZE : Ljava/lang/String;
    //   3529: getstatic burp/Zzi_.Zf : Ljava/lang/Object;
    //   3532: checkcast java/math/BigInteger
    //   3535: invokevirtual intValue : ()I
    //   3538: bipush #32
    //   3540: irem
    //   3541: invokestatic abs : (I)I
    //   3544: invokevirtual charAt : (I)C
    //   3547: invokevirtual append : (C)Ljava/lang/StringBuilder;
    //   3550: pop
    //   3551: iload_2
    //   3552: ifne -> 4128
    //   3555: goto -> 3562
    //   3558: invokestatic a : (Ljava/lang/Throwable;)Ljava/lang/Throwable;
    //   3561: athrow
    //   3562: aload #5
    //   3564: getstatic burp/Zl3j.Zr : Ljava/lang/String;
    //   3567: getstatic burp/Zzxa.ZI : Ljava/lang/Object;
    //   3570: checkcast java/math/BigInteger
    //   3573: invokevirtual intValue : ()I
    //   3576: bipush #32
    //   3578: irem
    //   3579: invokestatic abs : (I)I
    //   3582: invokevirtual charAt : (I)C
    //   3585: invokevirtual append : (C)Ljava/lang/StringBuilder;
    //   3588: pop
    //   3589: iload_2
    //   3590: ifne -> 4128
    //   3593: goto -> 3600
    //   3596: invokestatic a : (Ljava/lang/Throwable;)Ljava/lang/Throwable;
    //   3599: athrow
    //   3600: aload #5
    //   3602: getstatic burp/Ztg3.ZM : Ljava/lang/String;
    //   3605: getstatic burp/Ze3t.Zp : Ljava/lang/Object;
    //   3608: checkcast java/math/BigInteger
    //   3611: invokevirtual intValue : ()I
    //   3614: bipush #32
    //   3616: irem
    //   3617: invokestatic abs : (I)I
    //   3620: invokevirtual charAt : (I)C
    //   3623: invokevirtual append : (C)Ljava/lang/StringBuilder;
    //   3626: pop
    //   3627: iload_2
    //   3628: ifne -> 4128
    //   3631: goto -> 3638
    //   3634: invokestatic a : (Ljava/lang/Throwable;)Ljava/lang/Throwable;
    //   3637: athrow
    //   3638: aload #5
    //   3640: getstatic burp/Zelc.ZI : Ljava/lang/String;
    //   3643: getstatic burp/Zbzc.Zp : Ljava/lang/Object;
    //   3646: checkcast java/math/BigInteger
    //   3649: invokevirtual intValue : ()I
    //   3652: bipush #32
    //   3654: irem
    //   3655: invokestatic abs : (I)I
    //   3658: invokevirtual charAt : (I)C
    //   3661: invokevirtual append : (C)Ljava/lang/StringBuilder;
    //   3664: pop
    //   3665: iload_2
    //   3666: ifne -> 4128
    //   3669: goto -> 3676
    //   3672: invokestatic a : (Ljava/lang/Throwable;)Ljava/lang/Throwable;
    //   3675: athrow
    //   3676: aload #5
    //   3678: getstatic burp/Zkdc.Zc : Ljava/lang/String;
    //   3681: getstatic burp/Zth8.Zk : Ljava/lang/Object;
    //   3684: checkcast java/math/BigInteger
    //   3687: invokevirtual intValue : ()I
    //   3690: bipush #32
    //   3692: irem
    //   3693: invokestatic abs : (I)I
    //   3696: invokevirtual charAt : (I)C
    //   3699: invokevirtual append : (C)Ljava/lang/StringBuilder;
    //   3702: pop
    //   3703: iload_2
    //   3704: ifne -> 4128
    //   3707: goto -> 3714
    //   3710: invokestatic a : (Ljava/lang/Throwable;)Ljava/lang/Throwable;
    //   3713: athrow
    //   3714: aload #5
    //   3716: getstatic burp/Zkfa.Zy : Ljava/lang/String;
    //   3719: getstatic burp/Zscf.ZG : Ljava/lang/Object;
    //   3722: checkcast java/math/BigInteger
    //   3725: invokevirtual intValue : ()I
    //   3728: bipush #32
    //   3730: irem
    //   3731: invokestatic abs : (I)I
    //   3734: invokevirtual charAt : (I)C
    //   3737: invokevirtual append : (C)Ljava/lang/StringBuilder;
    //   3740: pop
    //   3741: iload_2
    //   3742: ifne -> 4128
    //   3745: goto -> 3752
    //   3748: invokestatic a : (Ljava/lang/Throwable;)Ljava/lang/Throwable;
    //   3751: athrow
    //   3752: aload #5
    //   3754: getstatic burp/Zboa.Zq : Ljava/lang/String;
    //   3757: getstatic burp/Zso7.ZB : Ljava/lang/Object;
    //   3760: checkcast java/math/BigInteger
    //   3763: invokevirtual intValue : ()I
    //   3766: bipush #32
    //   3768: irem
    //   3769: invokestatic abs : (I)I
    //   3772: invokevirtual charAt : (I)C
    //   3775: invokevirtual append : (C)Ljava/lang/StringBuilder;
    //   3778: pop
    //   3779: iload_2
    //   3780: ifne -> 4128
    //   3783: goto -> 3790
    //   3786: invokestatic a : (Ljava/lang/Throwable;)Ljava/lang/Throwable;
    //   3789: athrow
    //   3790: aload #5
    //   3792: getstatic burp/Zzo5.ZX : Ljava/lang/String;
    //   3795: getstatic burp/Zmfw.ZS : Ljava/lang/Object;
    //   3798: checkcast java/math/BigInteger
    //   3801: invokevirtual intValue : ()I
    //   3804: bipush #32
    //   3806: irem
    //   3807: invokestatic abs : (I)I
    //   3810: invokevirtual charAt : (I)C
    //   3813: invokevirtual append : (C)Ljava/lang/StringBuilder;
    //   3816: pop
    //   3817: iload_2
    //   3818: ifne -> 4128
    //   3821: goto -> 3828
    //   3824: invokestatic a : (Ljava/lang/Throwable;)Ljava/lang/Throwable;
    //   3827: athrow
    //   3828: aload #5
    //   3830: getstatic burp/Zsji.Zr : Ljava/lang/String;
    //   3833: getstatic burp/Zmlr.Zh : Ljava/lang/Object;
    //   3836: checkcast java/math/BigInteger
    //   3839: invokevirtual intValue : ()I
    //   3842: bipush #32
    //   3844: irem
    //   3845: invokestatic abs : (I)I
    //   3848: invokevirtual charAt : (I)C
    //   3851: invokevirtual append : (C)Ljava/lang/StringBuilder;
    //   3854: pop
    //   3855: iload_2
    //   3856: ifne -> 4128
    //   3859: goto -> 3866
    //   3862: invokestatic a : (Ljava/lang/Throwable;)Ljava/lang/Throwable;
    //   3865: athrow
    //   3866: aload #5
    //   3868: getstatic burp/Ztkh.ZP : Ljava/lang/String;
    //   3871: getstatic burp/Zlhz.Zy : Ljava/lang/Object;
    //   3874: checkcast java/math/BigInteger
    //   3877: invokevirtual intValue : ()I
    //   3880: bipush #32
    //   3882: irem
    //   3883: invokestatic abs : (I)I
    //   3886: invokevirtual charAt : (I)C
    //   3889: invokevirtual append : (C)Ljava/lang/StringBuilder;
    //   3892: pop
    //   3893: iload_2
    //   3894: ifne -> 4128
    //   3897: goto -> 3904
    //   3900: invokestatic a : (Ljava/lang/Throwable;)Ljava/lang/Throwable;
    //   3903: athrow
    //   3904: aload #5
    //   3906: getstatic burp/Zscs.Zw : Ljava/lang/String;
    //   3909: getstatic burp/Zmli.Zh : Ljava/lang/Object;
    //   3912: checkcast java/math/BigInteger
    //   3915: invokevirtual intValue : ()I
    //   3918: bipush #32
    //   3920: irem
    //   3921: invokestatic abs : (I)I
    //   3924: invokevirtual charAt : (I)C
    //   3927: invokevirtual append : (C)Ljava/lang/StringBuilder;
    //   3930: pop
    //   3931: iload_2
    //   3932: ifne -> 4128
    //   3935: goto -> 3942
    //   3938: invokestatic a : (Ljava/lang/Throwable;)Ljava/lang/Throwable;
    //   3941: athrow
    //   3942: aload #5
    //   3944: getstatic burp/Zmv9.Zm : Ljava/lang/String;
    //   3947: getstatic burp/Zstq.Zf : Ljava/lang/Object;
    //   3950: checkcast java/math/BigInteger
    //   3953: invokevirtual intValue : ()I
    //   3956: bipush #32
    //   3958: irem
    //   3959: invokestatic abs : (I)I
    //   3962: invokevirtual charAt : (I)C
    //   3965: invokevirtual append : (C)Ljava/lang/StringBuilder;
    //   3968: pop
    //   3969: iload_2
    //   3970: ifne -> 4128
    //   3973: goto -> 3980
    //   3976: invokestatic a : (Ljava/lang/Throwable;)Ljava/lang/Throwable;
    //   3979: athrow
    //   3980: aload #5
    //   3982: getstatic burp/Zm52.Ze : Ljava/lang/String;
    //   3985: getstatic burp/Zegw.ZW : Ljava/lang/Object;
    //   3988: checkcast java/math/BigInteger
    //   3991: invokevirtual intValue : ()I
    //   3994: bipush #32
    //   3996: irem
    //   3997: invokestatic abs : (I)I
    //   4000: invokevirtual charAt : (I)C
    //   4003: invokevirtual append : (C)Ljava/lang/StringBuilder;
    //   4006: pop
    //   4007: iload_2
    //   4008: ifne -> 4128
    //   4011: goto -> 4018
    //   4014: invokestatic a : (Ljava/lang/Throwable;)Ljava/lang/Throwable;
    //   4017: athrow
    //   4018: aload #5
    //   4020: getstatic burp/Zetv.ZE : Ljava/lang/String;
    //   4023: getstatic burp/Zkbf.Zx : Ljava/lang/Object;
    //   4026: checkcast java/math/BigInteger
    //   4029: invokevirtual intValue : ()I
    //   4032: bipush #32
    //   4034: irem
    //   4035: invokestatic abs : (I)I
    //   4038: invokevirtual charAt : (I)C
    //   4041: invokevirtual append : (C)Ljava/lang/StringBuilder;
    //   4044: pop
    //   4045: iload_2
    //   4046: ifne -> 4128
    //   4049: goto -> 4056
    //   4052: invokestatic a : (Ljava/lang/Throwable;)Ljava/lang/Throwable;
    //   4055: athrow
    //   4056: aload #5
    //   4058: getstatic burp/Zlzo.Zs : Ljava/lang/String;
    //   4061: getstatic burp/Ztq2.Zj : Ljava/lang/Object;
    //   4064: checkcast java/math/BigInteger
    //   4067: invokevirtual intValue : ()I
    //   4070: bipush #32
    //   4072: irem
    //   4073: invokestatic abs : (I)I
    //   4076: invokevirtual charAt : (I)C
    //   4079: invokevirtual append : (C)Ljava/lang/StringBuilder;
    //   4082: pop
    //   4083: iload_2
    //   4084: ifne -> 4128
    //   4087: goto -> 4094
    //   4090: invokestatic a : (Ljava/lang/Throwable;)Ljava/lang/Throwable;
    //   4093: athrow
    //   4094: aload #5
    //   4096: getstatic burp/Zz4r.Zq : Ljava/lang/String;
    //   4099: getstatic burp/Zmjr.ZU : Ljava/lang/Object;
    //   4102: checkcast java/math/BigInteger
    //   4105: invokevirtual intValue : ()I
    //   4108: bipush #32
    //   4110: irem
    //   4111: invokestatic abs : (I)I
    //   4114: invokevirtual charAt : (I)C
    //   4117: invokevirtual append : (C)Ljava/lang/StringBuilder;
    //   4120: pop
    //   4121: goto -> 4128
    //   4124: invokestatic a : (Ljava/lang/Throwable;)Ljava/lang/Throwable;
    //   4127: athrow
    //   4128: iinc #6, 1
    //   4131: iload_2
    //   4132: ifne -> 2763
    //   4135: aload #5
    //   4137: invokevirtual toString : ()Ljava/lang/String;
    //   4140: putstatic burp/Zg_y.ZF : Ljava/lang/String;
    //   4143: sipush #-31488
    //   4146: sipush #15598
    //   4149: invokestatic a : (II)Ljava/lang/String;
    //   4152: iconst_1
    //   4153: ldc burp/Zm52
    //   4155: invokevirtual getClassLoader : ()Ljava/lang/ClassLoader;
    //   4158: invokestatic forName : (Ljava/lang/String;ZLjava/lang/ClassLoader;)Ljava/lang/Class;
    //   4161: invokevirtual getDeclaredFields : ()[Ljava/lang/reflect/Field;
    //   4164: astore #6
    //   4166: aload #6
    //   4168: arraylength
    //   4169: istore #7
    //   4171: iconst_0
    //   4172: istore #8
    //   4174: iload #8
    //   4176: iload #7
    //   4178: if_icmpge -> 4316
    //   4181: aload #6
    //   4183: iload #8
    //   4185: aaload
    //   4186: astore #9
    //   4188: aload #9
    //   4190: invokevirtual getModifiers : ()I
    //   4193: invokestatic isStatic : (I)Z
    //   4196: ifne -> 4206
    //   4199: goto -> 4309
    //   4202: invokestatic a : (Ljava/lang/Throwable;)Ljava/lang/Throwable;
    //   4205: athrow
    //   4206: aload #9
    //   4208: invokevirtual getType : ()Ljava/lang/Class;
    //   4211: astore #10
    //   4213: aload #10
    //   4215: ifnull -> 4296
    //   4218: aload #10
    //   4220: invokevirtual isPrimitive : ()Z
    //   4223: ifne -> 4296
    //   4226: goto -> 4233
    //   4229: invokestatic a : (Ljava/lang/Throwable;)Ljava/lang/Throwable;
    //   4232: athrow
    //   4233: aload #10
    //   4235: invokevirtual getPackage : ()Ljava/lang/Package;
    //   4238: ifnull -> 4296
    //   4241: goto -> 4248
    //   4244: invokestatic a : (Ljava/lang/Throwable;)Ljava/lang/Throwable;
    //   4247: athrow
    //   4248: aload #10
    //   4250: invokevirtual getPackage : ()Ljava/lang/Package;
    //   4253: invokevirtual getName : ()Ljava/lang/String;
    //   4256: ifnull -> 4296
    //   4259: goto -> 4266
    //   4262: invokestatic a : (Ljava/lang/Throwable;)Ljava/lang/Throwable;
    //   4265: athrow
    //   4266: aload #10
    //   4268: invokevirtual getPackage : ()Ljava/lang/Package;
    //   4271: invokevirtual getName : ()Ljava/lang/String;
    //   4274: sipush #-31483
    //   4277: sipush #24955
    //   4280: invokestatic a : (II)Ljava/lang/String;
    //   4283: invokevirtual startsWith : (Ljava/lang/String;)Z
    //   4286: ifne -> 4296
    //   4289: goto -> 4296
    //   4292: invokestatic a : (Ljava/lang/Throwable;)Ljava/lang/Throwable;
    //   4295: athrow
    //   4296: aload #9
    //   4298: iconst_1
    //   4299: invokevirtual setAccessible : (Z)V
    //   4302: aload #9
    //   4304: aconst_null
    //   4305: invokevirtual get : (Ljava/lang/Object;)Ljava/lang/Object;
    //   4308: pop
    //   4309: iinc #8, 1
    //   4312: iload_2
    //   4313: ifne -> 4174
    //   4316: sipush #-31485
    //   4319: sipush #12988
    //   4322: invokestatic a : (II)Ljava/lang/String;
    //   4325: invokestatic forName : (Ljava/lang/String;)Ljava/lang/Class;
    //   4328: invokevirtual getDeclaredMethods : ()[Ljava/lang/reflect/Method;
    //   4331: astore #6
    //   4333: aload #6
    //   4335: arraylength
    //   4336: istore #7
    //   4338: iconst_0
    //   4339: istore #8
    //   4341: iload #8
    //   4343: iload #7
    //   4345: if_icmpge -> 4457
    //   4348: aload #6
    //   4350: iload #8
    //   4352: aaload
    //   4353: astore #9
    //   4355: aload #9
    //   4357: invokevirtual getParameterTypes : ()[Ljava/lang/Class;
    //   4360: pop
    //   4361: aload #9
    //   4363: invokevirtual getModifiers : ()I
    //   4366: invokestatic isStatic : (I)Z
    //   4369: ifeq -> 4443
    //   4372: aload #9
    //   4374: invokevirtual getParameterTypes : ()[Ljava/lang/Class;
    //   4377: arraylength
    //   4378: iconst_2
    //   4379: if_icmpne -> 4443
    //   4382: goto -> 4389
    //   4385: invokestatic a : (Ljava/lang/Throwable;)Ljava/lang/Throwable;
    //   4388: athrow
    //   4389: aload #9
    //   4391: invokevirtual getReturnType : ()Ljava/lang/Class;
    //   4394: getstatic java/lang/Boolean.TYPE : Ljava/lang/Class;
    //   4397: if_acmpne -> 4443
    //   4400: goto -> 4407
    //   4403: invokestatic a : (Ljava/lang/Throwable;)Ljava/lang/Throwable;
    //   4406: athrow
    //   4407: aload #9
    //   4409: iconst_1
    //   4410: invokevirtual setAccessible : (Z)V
    //   4413: aload #9
    //   4415: aconst_null
    //   4416: iconst_2
    //   4417: anewarray java/lang/Object
    //   4420: dup
    //   4421: iconst_0
    //   4422: aload_0
    //   4423: aastore
    //   4424: dup
    //   4425: iconst_1
    //   4426: aload_1
    //   4427: aastore
    //   4428: invokevirtual invoke : (Ljava/lang/Object;[Ljava/lang/Object;)Ljava/lang/Object;
    //   4431: pop
    //   4432: iload_2
    //   4433: ifne -> 4457
    //   4436: goto -> 4443
    //   4439: invokestatic a : (Ljava/lang/Throwable;)Ljava/lang/Throwable;
    //   4442: athrow
    //   4443: iinc #8, 1
    //   4446: iload_2
    //   4447: ifne -> 4341
    //   4450: goto -> 4457
    //   4453: invokestatic a : (Ljava/lang/Throwable;)Ljava/lang/Throwable;
    //   4456: athrow
    //   4457: sipush #-31487
    //   4460: sipush #15329
    //   4463: invokestatic a : (II)Ljava/lang/String;
    //   4466: iconst_1
    //   4467: ldc burp/Zr14
    //   4469: invokevirtual getClassLoader : ()Ljava/lang/ClassLoader;
    //   4472: invokestatic forName : (Ljava/lang/String;ZLjava/lang/ClassLoader;)Ljava/lang/Class;
    //   4475: invokevirtual getDeclaredFields : ()[Ljava/lang/reflect/Field;
    //   4478: astore #6
    //   4480: aload #6
    //   4482: arraylength
    //   4483: istore #7
    //   4485: iconst_0
    //   4486: istore #8
    //   4488: iload #8
    //   4490: iload #7
    //   4492: if_icmpge -> 4630
    //   4495: aload #6
    //   4497: iload #8
    //   4499: aaload
    //   4500: astore #9
    //   4502: aload #9
    //   4504: invokevirtual getModifiers : ()I
    //   4507: invokestatic isStatic : (I)Z
    //   4510: ifne -> 4520
    //   4513: goto -> 4623
    //   4516: invokestatic a : (Ljava/lang/Throwable;)Ljava/lang/Throwable;
    //   4519: athrow
    //   4520: aload #9
    //   4522: invokevirtual getType : ()Ljava/lang/Class;
    //   4525: astore #10
    //   4527: aload #10
    //   4529: ifnull -> 4610
    //   4532: aload #10
    //   4534: invokevirtual isPrimitive : ()Z
    //   4537: ifne -> 4610
    //   4540: goto -> 4547
    //   4543: invokestatic a : (Ljava/lang/Throwable;)Ljava/lang/Throwable;
    //   4546: athrow
    //   4547: aload #10
    //   4549: invokevirtual getPackage : ()Ljava/lang/Package;
    //   4552: ifnull -> 4610
    //   4555: goto -> 4562
    //   4558: invokestatic a : (Ljava/lang/Throwable;)Ljava/lang/Throwable;
    //   4561: athrow
    //   4562: aload #10
    //   4564: invokevirtual getPackage : ()Ljava/lang/Package;
    //   4567: invokevirtual getName : ()Ljava/lang/String;
    //   4570: ifnull -> 4610
    //   4573: goto -> 4580
    //   4576: invokestatic a : (Ljava/lang/Throwable;)Ljava/lang/Throwable;
    //   4579: athrow
    //   4580: aload #10
    //   4582: invokevirtual getPackage : ()Ljava/lang/Package;
    //   4585: invokevirtual getName : ()Ljava/lang/String;
    //   4588: sipush #-31482
    //   4591: sipush #27429
    //   4594: invokestatic a : (II)Ljava/lang/String;
    //   4597: invokevirtual startsWith : (Ljava/lang/String;)Z
    //   4600: ifne -> 4610
    //   4603: goto -> 4610
    //   4606: invokestatic a : (Ljava/lang/Throwable;)Ljava/lang/Throwable;
    //   4609: athrow
    //   4610: aload #9
    //   4612: iconst_1
    //   4613: invokevirtual setAccessible : (Z)V
    //   4616: aload #9
    //   4618: aconst_null
    //   4619: invokevirtual get : (Ljava/lang/Object;)Ljava/lang/Object;
    //   4622: pop
    //   4623: iinc #8, 1
    //   4626: iload_2
    //   4627: ifne -> 4488
    //   4630: sipush #-31479
    //   4633: sipush #-19181
    //   4636: invokestatic a : (II)Ljava/lang/String;
    //   4639: invokestatic forName : (Ljava/lang/String;)Ljava/lang/Class;
    //   4642: invokevirtual getDeclaredMethods : ()[Ljava/lang/reflect/Method;
    //   4645: astore #6
    //   4647: aload #6
    //   4649: arraylength
    //   4650: istore #7
    //   4652: iconst_0
    //   4653: istore #8
    //   4655: iload #8
    //   4657: iload #7
    //   4659: if_icmpge -> 4792
    //   4662: aload #6
    //   4664: iload #8
    //   4666: aaload
    //   4667: astore #9
    //   4669: aload #9
    //   4671: invokevirtual getParameterTypes : ()[Ljava/lang/Class;
    //   4674: pop
    //   4675: aload #9
    //   4677: invokevirtual getModifiers : ()I
    //   4680: invokestatic isStatic : (I)Z
    //   4683: ifeq -> 4778
    //   4686: aload #9
    //   4688: invokevirtual getParameterTypes : ()[Ljava/lang/Class;
    //   4691: arraylength
    //   4692: iconst_2
    //   4693: if_icmpne -> 4778
    //   4696: goto -> 4703
    //   4699: invokestatic a : (Ljava/lang/Throwable;)Ljava/lang/Throwable;
    //   4702: athrow
    //   4703: aload #9
    //   4705: invokevirtual getReturnType : ()Ljava/lang/Class;
    //   4708: getstatic java/lang/Void.TYPE : Ljava/lang/Class;
    //   4711: invokevirtual equals : (Ljava/lang/Object;)Z
    //   4714: ifeq -> 4778
    //   4717: goto -> 4724
    //   4720: invokestatic a : (Ljava/lang/Throwable;)Ljava/lang/Throwable;
    //   4723: athrow
    //   4724: aload #9
    //   4726: iconst_1
    //   4727: invokevirtual setAccessible : (Z)V
    //   4730: aload #9
    //   4732: aconst_null
    //   4733: iconst_2
    //   4734: anewarray java/lang/Object
    //   4737: dup
    //   4738: iconst_0
    //   4739: aload_0
    //   4740: aastore
    //   4741: dup
    //   4742: iconst_1
    //   4743: aload_1
    //   4744: ifnonnull -> 4762
    //   4747: goto -> 4754
    //   4750: invokestatic a : (Ljava/lang/Throwable;)Ljava/lang/Throwable;
    //   4753: athrow
    //   4754: aload_1
    //   4755: goto -> 4769
    //   4758: invokestatic a : (Ljava/lang/Throwable;)Ljava/lang/Throwable;
    //   4761: athrow
    //   4762: aload_1
    //   4763: checkcast [B
    //   4766: invokevirtual clone : ()Ljava/lang/Object;
    //   4769: aastore
    //   4770: invokevirtual invoke : (Ljava/lang/Object;[Ljava/lang/Object;)Ljava/lang/Object;
    //   4773: pop
    //   4774: iload_2
    //   4775: ifne -> 4792
    //   4778: iinc #8, 1
    //   4781: iload_2
    //   4782: ifne -> 4655
    //   4785: goto -> 4792
    //   4788: invokestatic a : (Ljava/lang/Throwable;)Ljava/lang/Throwable;
    //   4791: athrow
    //   4792: getstatic burp/Zgly.ZN : Ljava/lang/Object;
    //   4795: checkcast java/math/BigInteger
    //   4798: invokevirtual toByteArray : ()[B
    //   4801: astore #6
    //   4803: bipush #64
    //   4805: newarray byte
    //   4807: dup
    //   4808: iconst_0
    //   4809: bipush #-128
    //   4811: bastore
    //   4812: dup
    //   4813: iconst_1
    //   4814: iconst_0
    //   4815: bastore
    //   4816: dup
    //   4817: iconst_2
    //   4818: iconst_0
    //   4819: bastore
    //   4820: dup
    //   4821: iconst_3
    //   4822: iconst_0
    //   4823: bastore
    //   4824: dup
    //   4825: iconst_4
    //   4826: iconst_0
    //   4827: bastore
    //   4828: dup
    //   4829: iconst_5
    //   4830: iconst_0
    //   4831: bastore
    //   4832: dup
    //   4833: bipush #6
    //   4835: iconst_0
    //   4836: bastore
    //   4837: dup
    //   4838: bipush #7
    //   4840: iconst_0
    //   4841: bastore
    //   4842: dup
    //   4843: bipush #8
    //   4845: iconst_0
    //   4846: bastore
    //   4847: dup
    //   4848: bipush #9
    //   4850: iconst_0
    //   4851: bastore
    //   4852: dup
    //   4853: bipush #10
    //   4855: iconst_0
    //   4856: bastore
    //   4857: dup
    //   4858: bipush #11
    //   4860: iconst_0
    //   4861: bastore
    //   4862: dup
    //   4863: bipush #12
    //   4865: iconst_0
    //   4866: bastore
    //   4867: dup
    //   4868: bipush #13
    //   4870: iconst_0
    //   4871: bastore
    //   4872: dup
    //   4873: bipush #14
    //   4875: iconst_0
    //   4876: bastore
    //   4877: dup
    //   4878: bipush #15
    //   4880: iconst_0
    //   4881: bastore
    //   4882: dup
    //   4883: bipush #16
    //   4885: iconst_0
    //   4886: bastore
    //   4887: dup
    //   4888: bipush #17
    //   4890: iconst_0
    //   4891: bastore
    //   4892: dup
    //   4893: bipush #18
    //   4895: iconst_0
    //   4896: bastore
    //   4897: dup
    //   4898: bipush #19
    //   4900: iconst_0
    //   4901: bastore
    //   4902: dup
    //   4903: bipush #20
    //   4905: iconst_0
    //   4906: bastore
    //   4907: dup
    //   4908: bipush #21
    //   4910: iconst_0
    //   4911: bastore
    //   4912: dup
    //   4913: bipush #22
    //   4915: iconst_0
    //   4916: bastore
    //   4917: dup
    //   4918: bipush #23
    //   4920: iconst_0
    //   4921: bastore
    //   4922: dup
    //   4923: bipush #24
    //   4925: iconst_0
    //   4926: bastore
    //   4927: dup
    //   4928: bipush #25
    //   4930: iconst_0
    //   4931: bastore
    //   4932: dup
    //   4933: bipush #26
    //   4935: iconst_0
    //   4936: bastore
    //   4937: dup
    //   4938: bipush #27
    //   4940: iconst_0
    //   4941: bastore
    //   4942: dup
    //   4943: bipush #28
    //   4945: iconst_0
    //   4946: bastore
    //   4947: dup
    //   4948: bipush #29
    //   4950: iconst_0
    //   4951: bastore
    //   4952: dup
    //   4953: bipush #30
    //   4955: iconst_0
    //   4956: bastore
    //   4957: dup
    //   4958: bipush #31
    //   4960: iconst_0
    //   4961: bastore
    //   4962: dup
    //   4963: bipush #32
    //   4965: iconst_0
    //   4966: bastore
    //   4967: dup
    //   4968: bipush #33
    //   4970: iconst_0
    //   4971: bastore
    //   4972: dup
    //   4973: bipush #34
    //   4975: iconst_0
    //   4976: bastore
    //   4977: dup
    //   4978: bipush #35
    //   4980: iconst_0
    //   4981: bastore
    //   4982: dup
    //   4983: bipush #36
    //   4985: iconst_0
    //   4986: bastore
    //   4987: dup
    //   4988: bipush #37
    //   4990: iconst_0
    //   4991: bastore
    //   4992: dup
    //   4993: bipush #38
    //   4995: iconst_0
    //   4996: bastore
    //   4997: dup
    //   4998: bipush #39
    //   5000: iconst_0
    //   5001: bastore
    //   5002: dup
    //   5003: bipush #40
    //   5005: iconst_0
    //   5006: bastore
    //   5007: dup
    //   5008: bipush #41
    //   5010: iconst_0
    //   5011: bastore
    //   5012: dup
    //   5013: bipush #42
    //   5015: iconst_0
    //   5016: bastore
    //   5017: dup
    //   5018: bipush #43
    //   5020: iconst_0
    //   5021: bastore
    //   5022: dup
    //   5023: bipush #44
    //   5025: iconst_0
    //   5026: bastore
    //   5027: dup
    //   5028: bipush #45
    //   5030: iconst_0
    //   5031: bastore
    //   5032: dup
    //   5033: bipush #46
    //   5035: iconst_0
    //   5036: bastore
    //   5037: dup
    //   5038: bipush #47
    //   5040: iconst_0
    //   5041: bastore
    //   5042: dup
    //   5043: bipush #48
    //   5045: iconst_0
    //   5046: bastore
    //   5047: dup
    //   5048: bipush #49
    //   5050: iconst_0
    //   5051: bastore
    //   5052: dup
    //   5053: bipush #50
    //   5055: iconst_0
    //   5056: bastore
    //   5057: dup
    //   5058: bipush #51
    //   5060: iconst_0
    //   5061: bastore
    //   5062: dup
    //   5063: bipush #52
    //   5065: iconst_0
    //   5066: bastore
    //   5067: dup
    //   5068: bipush #53
    //   5070: iconst_0
    //   5071: bastore
    //   5072: dup
    //   5073: bipush #54
    //   5075: iconst_0
    //   5076: bastore
    //   5077: dup
    //   5078: bipush #55
    //   5080: iconst_0
    //   5081: bastore
    //   5082: dup
    //   5083: bipush #56
    //   5085: iconst_0
    //   5086: bastore
    //   5087: dup
    //   5088: bipush #57
    //   5090: iconst_0
    //   5091: bastore
    //   5092: dup
    //   5093: bipush #58
    //   5095: iconst_0
    //   5096: bastore
    //   5097: dup
    //   5098: bipush #59
    //   5100: iconst_0
    //   5101: bastore
    //   5102: dup
    //   5103: bipush #60
    //   5105: iconst_0
    //   5106: bastore
    //   5107: dup
    //   5108: bipush #61
    //   5110: iconst_0
    //   5111: bastore
    //   5112: dup
    //   5113: bipush #62
    //   5115: iconst_0
    //   5116: bastore
    //   5117: dup
    //   5118: bipush #63
    //   5120: iconst_0
    //   5121: bastore
    //   5122: astore #8
    //   5124: bipush #64
    //   5126: newarray int
    //   5128: dup
    //   5129: iconst_0
    //   5130: ldc 1116352408
    //   5132: iastore
    //   5133: dup
    //   5134: iconst_1
    //   5135: ldc 1899447441
    //   5137: iastore
    //   5138: dup
    //   5139: iconst_2
    //   5140: ldc -1245643825
    //   5142: iastore
    //   5143: dup
    //   5144: iconst_3
    //   5145: ldc -373957723
    //   5147: iastore
    //   5148: dup
    //   5149: iconst_4
    //   5150: ldc 961987163
    //   5152: iastore
    //   5153: dup
    //   5154: iconst_5
    //   5155: ldc 1508970993
    //   5157: iastore
    //   5158: dup
    //   5159: bipush #6
    //   5161: ldc -1841331548
    //   5163: iastore
    //   5164: dup
    //   5165: bipush #7
    //   5167: ldc -1424204075
    //   5169: iastore
    //   5170: dup
    //   5171: bipush #8
    //   5173: ldc -670586216
    //   5175: iastore
    //   5176: dup
    //   5177: bipush #9
    //   5179: ldc 310598401
    //   5181: iastore
    //   5182: dup
    //   5183: bipush #10
    //   5185: ldc 607225278
    //   5187: iastore
    //   5188: dup
    //   5189: bipush #11
    //   5191: ldc 1426881987
    //   5193: iastore
    //   5194: dup
    //   5195: bipush #12
    //   5197: ldc 1925078388
    //   5199: iastore
    //   5200: dup
    //   5201: bipush #13
    //   5203: ldc -2132889090
    //   5205: iastore
    //   5206: dup
    //   5207: bipush #14
    //   5209: ldc -1680079193
    //   5211: iastore
    //   5212: dup
    //   5213: bipush #15
    //   5215: ldc -1046744716
    //   5217: iastore
    //   5218: dup
    //   5219: bipush #16
    //   5221: ldc -459576895
    //   5223: iastore
    //   5224: dup
    //   5225: bipush #17
    //   5227: ldc -272742522
    //   5229: iastore
    //   5230: dup
    //   5231: bipush #18
    //   5233: ldc 264347078
    //   5235: iastore
    //   5236: dup
    //   5237: bipush #19
    //   5239: ldc 604807628
    //   5241: iastore
    //   5242: dup
    //   5243: bipush #20
    //   5245: ldc 770255983
    //   5247: iastore
    //   5248: dup
    //   5249: bipush #21
    //   5251: ldc 1249150122
    //   5253: iastore
    //   5254: dup
    //   5255: bipush #22
    //   5257: ldc 1555081692
    //   5259: iastore
    //   5260: dup
    //   5261: bipush #23
    //   5263: ldc 1996064986
    //   5265: iastore
    //   5266: dup
    //   5267: bipush #24
    //   5269: ldc -1740746414
    //   5271: iastore
    //   5272: dup
    //   5273: bipush #25
    //   5275: ldc -1473132947
    //   5277: iastore
    //   5278: dup
    //   5279: bipush #26
    //   5281: ldc -1341970488
    //   5283: iastore
    //   5284: dup
    //   5285: bipush #27
    //   5287: ldc -1084653625
    //   5289: iastore
    //   5290: dup
    //   5291: bipush #28
    //   5293: ldc -958395405
    //   5295: iastore
    //   5296: dup
    //   5297: bipush #29
    //   5299: ldc -710438585
    //   5301: iastore
    //   5302: dup
    //   5303: bipush #30
    //   5305: ldc 113926993
    //   5307: iastore
    //   5308: dup
    //   5309: bipush #31
    //   5311: ldc 338241895
    //   5313: iastore
    //   5314: dup
    //   5315: bipush #32
    //   5317: ldc 666307205
    //   5319: iastore
    //   5320: dup
    //   5321: bipush #33
    //   5323: ldc 773529912
    //   5325: iastore
    //   5326: dup
    //   5327: bipush #34
    //   5329: ldc 1294757372
    //   5331: iastore
    //   5332: dup
    //   5333: bipush #35
    //   5335: ldc 1396182291
    //   5337: iastore
    //   5338: dup
    //   5339: bipush #36
    //   5341: ldc 1695183700
    //   5343: iastore
    //   5344: dup
    //   5345: bipush #37
    //   5347: ldc 1986661051
    //   5349: iastore
    //   5350: dup
    //   5351: bipush #38
    //   5353: ldc -2117940946
    //   5355: iastore
    //   5356: dup
    //   5357: bipush #39
    //   5359: ldc -1838011259
    //   5361: iastore
    //   5362: dup
    //   5363: bipush #40
    //   5365: ldc -1564481375
    //   5367: iastore
    //   5368: dup
    //   5369: bipush #41
    //   5371: ldc -1474664885
    //   5373: iastore
    //   5374: dup
    //   5375: bipush #42
    //   5377: ldc -1035236496
    //   5379: iastore
    //   5380: dup
    //   5381: bipush #43
    //   5383: ldc -949202525
    //   5385: iastore
    //   5386: dup
    //   5387: bipush #44
    //   5389: ldc -778901479
    //   5391: iastore
    //   5392: dup
    //   5393: bipush #45
    //   5395: ldc -694614492
    //   5397: iastore
    //   5398: dup
    //   5399: bipush #46
    //   5401: ldc -200395387
    //   5403: iastore
    //   5404: dup
    //   5405: bipush #47
    //   5407: ldc 275423344
    //   5409: iastore
    //   5410: dup
    //   5411: bipush #48
    //   5413: ldc 430227734
    //   5415: iastore
    //   5416: dup
    //   5417: bipush #49
    //   5419: ldc 506948616
    //   5421: iastore
    //   5422: dup
    //   5423: bipush #50
    //   5425: ldc 659060556
    //   5427: iastore
    //   5428: dup
    //   5429: bipush #51
    //   5431: ldc 883997877
    //   5433: iastore
    //   5434: dup
    //   5435: bipush #52
    //   5437: ldc 958139571
    //   5439: iastore
    //   5440: dup
    //   5441: bipush #53
    //   5443: ldc 1322822218
    //   5445: iastore
    //   5446: dup
    //   5447: bipush #54
    //   5449: ldc 1537002063
    //   5451: iastore
    //   5452: dup
    //   5453: bipush #55
    //   5455: ldc 1747873779
    //   5457: iastore
    //   5458: dup
    //   5459: bipush #56
    //   5461: ldc 1955562222
    //   5463: iastore
    //   5464: dup
    //   5465: bipush #57
    //   5467: ldc 2024104815
    //   5469: iastore
    //   5470: dup
    //   5471: bipush #58
    //   5473: ldc -2067236844
    //   5475: iastore
    //   5476: dup
    //   5477: bipush #59
    //   5479: ldc -1933114872
    //   5481: iastore
    //   5482: dup
    //   5483: bipush #60
    //   5485: ldc -1866530822
    //   5487: iastore
    //   5488: dup
    //   5489: bipush #61
    //   5491: ldc -1538233109
    //   5493: iastore
    //   5494: dup
    //   5495: bipush #62
    //   5497: ldc -1090935817
    //   5499: iastore
    //   5500: dup
    //   5501: bipush #63
    //   5503: ldc -965641998
    //   5505: iastore
    //   5506: astore #9
    //   5508: iconst_2
    //   5509: newarray int
    //   5511: dup
    //   5512: iconst_0
    //   5513: iconst_0
    //   5514: iastore
    //   5515: dup
    //   5516: iconst_1
    //   5517: iconst_0
    //   5518: iastore
    //   5519: astore #10
    //   5521: bipush #8
    //   5523: newarray int
    //   5525: dup
    //   5526: iconst_0
    //   5527: ldc 1779033703
    //   5529: iastore
    //   5530: dup
    //   5531: iconst_1
    //   5532: ldc -1150833019
    //   5534: iastore
    //   5535: dup
    //   5536: iconst_2
    //   5537: ldc 1013904242
    //   5539: iastore
    //   5540: dup
    //   5541: iconst_3
    //   5542: ldc -1521486534
    //   5544: iastore
    //   5545: dup
    //   5546: iconst_4
    //   5547: ldc 1359893119
    //   5549: iastore
    //   5550: dup
    //   5551: iconst_5
    //   5552: ldc -1694144372
    //   5554: iastore
    //   5555: dup
    //   5556: bipush #6
    //   5558: ldc 528734635
    //   5560: iastore
    //   5561: dup
    //   5562: bipush #7
    //   5564: ldc 1541459225
    //   5566: iastore
    //   5567: astore #11
    //   5569: bipush #64
    //   5571: newarray byte
    //   5573: astore #12
    //   5575: bipush #64
    //   5577: newarray byte
    //   5579: astore #13
    //   5581: aload #6
    //   5583: arraylength
    //   5584: istore #14
    //   5586: aload #10
    //   5588: iconst_0
    //   5589: iaload
    //   5590: bipush #63
    //   5592: iand
    //   5593: istore #15
    //   5595: aload #10
    //   5597: iconst_0
    //   5598: dup2
    //   5599: iaload
    //   5600: iload #14
    //   5602: iadd
    //   5603: iastore
    //   5604: aload #10
    //   5606: iconst_0
    //   5607: dup2
    //   5608: iaload
    //   5609: iconst_m1
    //   5610: iand
    //   5611: iastore
    //   5612: aload #10
    //   5614: iconst_0
    //   5615: iaload
    //   5616: iload #14
    //   5618: if_icmpge -> 5636
    //   5621: aload #10
    //   5623: iconst_1
    //   5624: dup2
    //   5625: iaload
    //   5626: iconst_1
    //   5627: iadd
    //   5628: iastore
    //   5629: goto -> 5636
    //   5632: invokestatic a : (Ljava/lang/Throwable;)Ljava/lang/Throwable;
    //   5635: athrow
    //   5636: iconst_0
    //   5637: istore #16
    //   5639: iload #14
    //   5641: bipush #64
    //   5643: if_icmplt -> 6253
    //   5646: iconst_0
    //   5647: istore #17
    //   5649: iload #17
    //   5651: bipush #64
    //   5653: if_icmpge -> 5676
    //   5656: aload #13
    //   5658: iload #17
    //   5660: aload #6
    //   5662: iload #16
    //   5664: iload #17
    //   5666: iadd
    //   5667: baload
    //   5668: bastore
    //   5669: iinc #17, 1
    //   5672: iload_2
    //   5673: ifne -> 5649
    //   5676: bipush #64
    //   5678: newarray int
    //   5680: astore #17
    //   5682: bipush #8
    //   5684: newarray int
    //   5686: astore #18
    //   5688: iconst_0
    //   5689: istore #19
    //   5691: iload #19
    //   5693: bipush #8
    //   5695: if_icmpge -> 5715
    //   5698: aload #18
    //   5700: iload #19
    //   5702: aload #11
    //   5704: iload #19
    //   5706: iaload
    //   5707: iastore
    //   5708: iinc #19, 1
    //   5711: iload_2
    //   5712: ifne -> 5691
    //   5715: iconst_0
    //   5716: istore #19
    //   5718: iload #19
    //   5720: bipush #64
    //   5722: if_icmpge -> 6213
    //   5725: iload #19
    //   5727: bipush #16
    //   5729: if_icmpge -> 5810
    //   5732: aload #17
    //   5734: iload #19
    //   5736: aload #13
    //   5738: iconst_4
    //   5739: iload #19
    //   5741: imul
    //   5742: baload
    //   5743: sipush #255
    //   5746: iand
    //   5747: bipush #24
    //   5749: ishl
    //   5750: aload #13
    //   5752: iconst_4
    //   5753: iload #19
    //   5755: imul
    //   5756: iconst_1
    //   5757: iadd
    //   5758: baload
    //   5759: sipush #255
    //   5762: iand
    //   5763: bipush #16
    //   5765: ishl
    //   5766: ior
    //   5767: aload #13
    //   5769: iconst_4
    //   5770: iload #19
    //   5772: imul
    //   5773: iconst_2
    //   5774: iadd
    //   5775: baload
    //   5776: sipush #255
    //   5779: iand
    //   5780: bipush #8
    //   5782: ishl
    //   5783: ior
    //   5784: aload #13
    //   5786: iconst_4
    //   5787: iload #19
    //   5789: imul
    //   5790: iconst_3
    //   5791: iadd
    //   5792: baload
    //   5793: sipush #255
    //   5796: iand
    //   5797: ior
    //   5798: iastore
    //   5799: iload_2
    //   5800: ifne -> 5953
    //   5803: goto -> 5810
    //   5806: invokestatic a : (Ljava/lang/Throwable;)Ljava/lang/Throwable;
    //   5809: athrow
    //   5810: aload #17
    //   5812: iload #19
    //   5814: aload #17
    //   5816: iload #19
    //   5818: iconst_2
    //   5819: isub
    //   5820: iaload
    //   5821: bipush #17
    //   5823: iushr
    //   5824: aload #17
    //   5826: iload #19
    //   5828: iconst_2
    //   5829: isub
    //   5830: iaload
    //   5831: bipush #15
    //   5833: ishl
    //   5834: ior
    //   5835: aload #17
    //   5837: iload #19
    //   5839: iconst_2
    //   5840: isub
    //   5841: iaload
    //   5842: bipush #19
    //   5844: iushr
    //   5845: aload #17
    //   5847: iload #19
    //   5849: iconst_2
    //   5850: isub
    //   5851: iaload
    //   5852: bipush #13
    //   5854: ishl
    //   5855: ior
    //   5856: ixor
    //   5857: aload #17
    //   5859: iload #19
    //   5861: iconst_2
    //   5862: isub
    //   5863: iaload
    //   5864: bipush #10
    //   5866: iushr
    //   5867: ixor
    //   5868: aload #17
    //   5870: iload #19
    //   5872: bipush #7
    //   5874: isub
    //   5875: iaload
    //   5876: iadd
    //   5877: aload #17
    //   5879: iload #19
    //   5881: bipush #15
    //   5883: isub
    //   5884: iaload
    //   5885: bipush #7
    //   5887: iushr
    //   5888: aload #17
    //   5890: iload #19
    //   5892: bipush #15
    //   5894: isub
    //   5895: iaload
    //   5896: bipush #25
    //   5898: ishl
    //   5899: ior
    //   5900: aload #17
    //   5902: iload #19
    //   5904: bipush #15
    //   5906: isub
    //   5907: iaload
    //   5908: bipush #18
    //   5910: iushr
    //   5911: aload #17
    //   5913: iload #19
    //   5915: bipush #15
    //   5917: isub
    //   5918: iaload
    //   5919: bipush #14
    //   5921: ishl
    //   5922: ior
    //   5923: ixor
    //   5924: aload #17
    //   5926: iload #19
    //   5928: bipush #15
    //   5930: isub
    //   5931: iaload
    //   5932: iconst_3
    //   5933: iushr
    //   5934: ixor
    //   5935: iadd
    //   5936: aload #17
    //   5938: iload #19
    //   5940: bipush #16
    //   5942: isub
    //   5943: iaload
    //   5944: iadd
    //   5945: iastore
    //   5946: goto -> 5953
    //   5949: invokestatic a : (Ljava/lang/Throwable;)Ljava/lang/Throwable;
    //   5952: athrow
    //   5953: aload #18
    //   5955: bipush #7
    //   5957: iaload
    //   5958: aload #18
    //   5960: iconst_4
    //   5961: iaload
    //   5962: bipush #6
    //   5964: iushr
    //   5965: aload #18
    //   5967: iconst_4
    //   5968: iaload
    //   5969: bipush #26
    //   5971: ishl
    //   5972: ior
    //   5973: aload #18
    //   5975: iconst_4
    //   5976: iaload
    //   5977: bipush #11
    //   5979: iushr
    //   5980: aload #18
    //   5982: iconst_4
    //   5983: iaload
    //   5984: bipush #21
    //   5986: ishl
    //   5987: ior
    //   5988: ixor
    //   5989: aload #18
    //   5991: iconst_4
    //   5992: iaload
    //   5993: bipush #25
    //   5995: iushr
    //   5996: aload #18
    //   5998: iconst_4
    //   5999: iaload
    //   6000: bipush #7
    //   6002: ishl
    //   6003: ior
    //   6004: ixor
    //   6005: iadd
    //   6006: aload #18
    //   6008: bipush #6
    //   6010: iaload
    //   6011: aload #18
    //   6013: iconst_4
    //   6014: iaload
    //   6015: aload #18
    //   6017: iconst_5
    //   6018: iaload
    //   6019: aload #18
    //   6021: bipush #6
    //   6023: iaload
    //   6024: ixor
    //   6025: iand
    //   6026: ixor
    //   6027: iadd
    //   6028: aload #9
    //   6030: iload #19
    //   6032: iaload
    //   6033: iadd
    //   6034: aload #17
    //   6036: iload #19
    //   6038: iaload
    //   6039: iadd
    //   6040: istore #20
    //   6042: aload #18
    //   6044: iconst_0
    //   6045: iaload
    //   6046: iconst_2
    //   6047: iushr
    //   6048: aload #18
    //   6050: iconst_0
    //   6051: iaload
    //   6052: bipush #30
    //   6054: ishl
    //   6055: ior
    //   6056: aload #18
    //   6058: iconst_0
    //   6059: iaload
    //   6060: bipush #13
    //   6062: iushr
    //   6063: aload #18
    //   6065: iconst_0
    //   6066: iaload
    //   6067: bipush #19
    //   6069: ishl
    //   6070: ior
    //   6071: ixor
    //   6072: aload #18
    //   6074: iconst_0
    //   6075: iaload
    //   6076: bipush #22
    //   6078: iushr
    //   6079: aload #18
    //   6081: iconst_0
    //   6082: iaload
    //   6083: bipush #10
    //   6085: ishl
    //   6086: ior
    //   6087: ixor
    //   6088: aload #18
    //   6090: iconst_0
    //   6091: iaload
    //   6092: aload #18
    //   6094: iconst_1
    //   6095: iaload
    //   6096: iand
    //   6097: aload #18
    //   6099: iconst_2
    //   6100: iaload
    //   6101: aload #18
    //   6103: iconst_0
    //   6104: iaload
    //   6105: aload #18
    //   6107: iconst_1
    //   6108: iaload
    //   6109: ior
    //   6110: iand
    //   6111: ior
    //   6112: iadd
    //   6113: istore #21
    //   6115: aload #18
    //   6117: iconst_3
    //   6118: dup2
    //   6119: iaload
    //   6120: iload #20
    //   6122: iadd
    //   6123: iastore
    //   6124: aload #18
    //   6126: bipush #7
    //   6128: iload #20
    //   6130: iload #21
    //   6132: iadd
    //   6133: iastore
    //   6134: aload #18
    //   6136: bipush #7
    //   6138: iaload
    //   6139: istore #20
    //   6141: aload #18
    //   6143: bipush #7
    //   6145: aload #18
    //   6147: bipush #6
    //   6149: iaload
    //   6150: iastore
    //   6151: aload #18
    //   6153: bipush #6
    //   6155: aload #18
    //   6157: iconst_5
    //   6158: iaload
    //   6159: iastore
    //   6160: aload #18
    //   6162: iconst_5
    //   6163: aload #18
    //   6165: iconst_4
    //   6166: iaload
    //   6167: iastore
    //   6168: aload #18
    //   6170: iconst_4
    //   6171: aload #18
    //   6173: iconst_3
    //   6174: iaload
    //   6175: iastore
    //   6176: aload #18
    //   6178: iconst_3
    //   6179: aload #18
    //   6181: iconst_2
    //   6182: iaload
    //   6183: iastore
    //   6184: aload #18
    //   6186: iconst_2
    //   6187: aload #18
    //   6189: iconst_1
    //   6190: iaload
    //   6191: iastore
    //   6192: aload #18
    //   6194: iconst_1
    //   6195: aload #18
    //   6197: iconst_0
    //   6198: iaload
    //   6199: iastore
    //   6200: aload #18
    //   6202: iconst_0
    //   6203: iload #20
    //   6205: iastore
    //   6206: iinc #19, 1
    //   6209: iload_2
    //   6210: ifne -> 5718
    //   6213: iconst_0
    //   6214: istore #19
    //   6216: iload #19
    //   6218: bipush #8
    //   6220: if_icmpge -> 6243
    //   6223: aload #11
    //   6225: iload #19
    //   6227: dup2
    //   6228: iaload
    //   6229: aload #18
    //   6231: iload #19
    //   6233: iaload
    //   6234: iadd
    //   6235: iastore
    //   6236: iinc #19, 1
    //   6239: iload_2
    //   6240: ifne -> 6216
    //   6243: iinc #16, 64
    //   6246: iinc #14, -64
    //   6249: iload_2
    //   6250: ifne -> 5639
    //   6253: iload #14
    //   6255: ifle -> 6291
    //   6258: iconst_0
    //   6259: istore #17
    //   6261: iload #17
    //   6263: iload #14
    //   6265: if_icmpge -> 6291
    //   6268: aload #12
    //   6270: iload #15
    //   6272: iload #17
    //   6274: iadd
    //   6275: aload #6
    //   6277: iload #16
    //   6279: iload #17
    //   6281: iadd
    //   6282: baload
    //   6283: bastore
    //   6284: iinc #17, 1
    //   6287: iload_2
    //   6288: ifne -> 6261
    //   6291: aload #10
    //   6293: iconst_0
    //   6294: iaload
    //   6295: bipush #29
    //   6297: iushr
    //   6298: aload #10
    //   6300: iconst_1
    //   6301: iaload
    //   6302: iconst_3
    //   6303: ishl
    //   6304: ior
    //   6305: istore #17
    //   6307: aload #10
    //   6309: iconst_0
    //   6310: iaload
    //   6311: iconst_3
    //   6312: ishl
    //   6313: istore #18
    //   6315: aload #10
    //   6317: iconst_0
    //   6318: iaload
    //   6319: bipush #63
    //   6321: iand
    //   6322: istore #19
    //   6324: iload #19
    //   6326: bipush #56
    //   6328: if_icmpge -> 6343
    //   6331: bipush #56
    //   6333: iload #19
    //   6335: isub
    //   6336: goto -> 6348
    //   6339: invokestatic a : (Ljava/lang/Throwable;)Ljava/lang/Throwable;
    //   6342: athrow
    //   6343: bipush #120
    //   6345: iload #19
    //   6347: isub
    //   6348: istore #20
    //   6350: aload #10
    //   6352: iconst_0
    //   6353: iaload
    //   6354: bipush #63
    //   6356: iand
    //   6357: istore #15
    //   6359: bipush #64
    //   6361: iload #15
    //   6363: isub
    //   6364: istore #21
    //   6366: aload #10
    //   6368: iconst_0
    //   6369: dup2
    //   6370: iaload
    //   6371: iload #20
    //   6373: iadd
    //   6374: iastore
    //   6375: aload #10
    //   6377: iconst_0
    //   6378: dup2
    //   6379: iaload
    //   6380: iconst_m1
    //   6381: iand
    //   6382: iastore
    //   6383: aload #10
    //   6385: iconst_0
    //   6386: iaload
    //   6387: iload #20
    //   6389: if_icmpge -> 6407
    //   6392: aload #10
    //   6394: iconst_1
    //   6395: dup2
    //   6396: iaload
    //   6397: iconst_1
    //   6398: iadd
    //   6399: iastore
    //   6400: goto -> 6407
    //   6403: invokestatic a : (Ljava/lang/Throwable;)Ljava/lang/Throwable;
    //   6406: athrow
    //   6407: iconst_0
    //   6408: istore #16
    //   6410: iload #15
    //   6412: ifle -> 7043
    //   6415: iload #20
    //   6417: iload #21
    //   6419: if_icmplt -> 7043
    //   6422: goto -> 6429
    //   6425: invokestatic a : (Ljava/lang/Throwable;)Ljava/lang/Throwable;
    //   6428: athrow
    //   6429: iconst_0
    //   6430: istore #22
    //   6432: iload #22
    //   6434: iload #21
    //   6436: if_icmpge -> 6459
    //   6439: aload #12
    //   6441: iload #15
    //   6443: iload #22
    //   6445: iadd
    //   6446: aload #8
    //   6448: iload #22
    //   6450: baload
    //   6451: bastore
    //   6452: iinc #22, 1
    //   6455: iload_2
    //   6456: ifne -> 6432
    //   6459: bipush #64
    //   6461: newarray int
    //   6463: astore #22
    //   6465: bipush #8
    //   6467: newarray int
    //   6469: astore #23
    //   6471: iconst_0
    //   6472: istore #24
    //   6474: iload #24
    //   6476: bipush #8
    //   6478: if_icmpge -> 6498
    //   6481: aload #23
    //   6483: iload #24
    //   6485: aload #11
    //   6487: iload #24
    //   6489: iaload
    //   6490: iastore
    //   6491: iinc #24, 1
    //   6494: iload_2
    //   6495: ifne -> 6474
    //   6498: iconst_0
    //   6499: istore #24
    //   6501: iload #24
    //   6503: bipush #64
    //   6505: if_icmpge -> 6996
    //   6508: iload #24
    //   6510: bipush #16
    //   6512: if_icmpge -> 6593
    //   6515: aload #22
    //   6517: iload #24
    //   6519: aload #12
    //   6521: iconst_4
    //   6522: iload #24
    //   6524: imul
    //   6525: baload
    //   6526: sipush #255
    //   6529: iand
    //   6530: bipush #24
    //   6532: ishl
    //   6533: aload #12
    //   6535: iconst_4
    //   6536: iload #24
    //   6538: imul
    //   6539: iconst_1
    //   6540: iadd
    //   6541: baload
    //   6542: sipush #255
    //   6545: iand
    //   6546: bipush #16
    //   6548: ishl
    //   6549: ior
    //   6550: aload #12
    //   6552: iconst_4
    //   6553: iload #24
    //   6555: imul
    //   6556: iconst_2
    //   6557: iadd
    //   6558: baload
    //   6559: sipush #255
    //   6562: iand
    //   6563: bipush #8
    //   6565: ishl
    //   6566: ior
    //   6567: aload #12
    //   6569: iconst_4
    //   6570: iload #24
    //   6572: imul
    //   6573: iconst_3
    //   6574: iadd
    //   6575: baload
    //   6576: sipush #255
    //   6579: iand
    //   6580: ior
    //   6581: iastore
    //   6582: iload_2
    //   6583: ifne -> 6736
    //   6586: goto -> 6593
    //   6589: invokestatic a : (Ljava/lang/Throwable;)Ljava/lang/Throwable;
    //   6592: athrow
    //   6593: aload #22
    //   6595: iload #24
    //   6597: aload #22
    //   6599: iload #24
    //   6601: iconst_2
    //   6602: isub
    //   6603: iaload
    //   6604: bipush #17
    //   6606: iushr
    //   6607: aload #22
    //   6609: iload #24
    //   6611: iconst_2
    //   6612: isub
    //   6613: iaload
    //   6614: bipush #15
    //   6616: ishl
    //   6617: ior
    //   6618: aload #22
    //   6620: iload #24
    //   6622: iconst_2
    //   6623: isub
    //   6624: iaload
    //   6625: bipush #19
    //   6627: iushr
    //   6628: aload #22
    //   6630: iload #24
    //   6632: iconst_2
    //   6633: isub
    //   6634: iaload
    //   6635: bipush #13
    //   6637: ishl
    //   6638: ior
    //   6639: ixor
    //   6640: aload #22
    //   6642: iload #24
    //   6644: iconst_2
    //   6645: isub
    //   6646: iaload
    //   6647: bipush #10
    //   6649: iushr
    //   6650: ixor
    //   6651: aload #22
    //   6653: iload #24
    //   6655: bipush #7
    //   6657: isub
    //   6658: iaload
    //   6659: iadd
    //   6660: aload #22
    //   6662: iload #24
    //   6664: bipush #15
    //   6666: isub
    //   6667: iaload
    //   6668: bipush #7
    //   6670: iushr
    //   6671: aload #22
    //   6673: iload #24
    //   6675: bipush #15
    //   6677: isub
    //   6678: iaload
    //   6679: bipush #25
    //   6681: ishl
    //   6682: ior
    //   6683: aload #22
    //   6685: iload #24
    //   6687: bipush #15
    //   6689: isub
    //   6690: iaload
    //   6691: bipush #18
    //   6693: iushr
    //   6694: aload #22
    //   6696: iload #24
    //   6698: bipush #15
    //   6700: isub
    //   6701: iaload
    //   6702: bipush #14
    //   6704: ishl
    //   6705: ior
    //   6706: ixor
    //   6707: aload #22
    //   6709: iload #24
    //   6711: bipush #15
    //   6713: isub
    //   6714: iaload
    //   6715: iconst_3
    //   6716: iushr
    //   6717: ixor
    //   6718: iadd
    //   6719: aload #22
    //   6721: iload #24
    //   6723: bipush #16
    //   6725: isub
    //   6726: iaload
    //   6727: iadd
    //   6728: iastore
    //   6729: goto -> 6736
    //   6732: invokestatic a : (Ljava/lang/Throwable;)Ljava/lang/Throwable;
    //   6735: athrow
    //   6736: aload #23
    //   6738: bipush #7
    //   6740: iaload
    //   6741: aload #23
    //   6743: iconst_4
    //   6744: iaload
    //   6745: bipush #6
    //   6747: iushr
    //   6748: aload #23
    //   6750: iconst_4
    //   6751: iaload
    //   6752: bipush #26
    //   6754: ishl
    //   6755: ior
    //   6756: aload #23
    //   6758: iconst_4
    //   6759: iaload
    //   6760: bipush #11
    //   6762: iushr
    //   6763: aload #23
    //   6765: iconst_4
    //   6766: iaload
    //   6767: bipush #21
    //   6769: ishl
    //   6770: ior
    //   6771: ixor
    //   6772: aload #23
    //   6774: iconst_4
    //   6775: iaload
    //   6776: bipush #25
    //   6778: iushr
    //   6779: aload #23
    //   6781: iconst_4
    //   6782: iaload
    //   6783: bipush #7
    //   6785: ishl
    //   6786: ior
    //   6787: ixor
    //   6788: iadd
    //   6789: aload #23
    //   6791: bipush #6
    //   6793: iaload
    //   6794: aload #23
    //   6796: iconst_4
    //   6797: iaload
    //   6798: aload #23
    //   6800: iconst_5
    //   6801: iaload
    //   6802: aload #23
    //   6804: bipush #6
    //   6806: iaload
    //   6807: ixor
    //   6808: iand
    //   6809: ixor
    //   6810: iadd
    //   6811: aload #9
    //   6813: iload #24
    //   6815: iaload
    //   6816: iadd
    //   6817: aload #22
    //   6819: iload #24
    //   6821: iaload
    //   6822: iadd
    //   6823: istore #25
    //   6825: aload #23
    //   6827: iconst_0
    //   6828: iaload
    //   6829: iconst_2
    //   6830: iushr
    //   6831: aload #23
    //   6833: iconst_0
    //   6834: iaload
    //   6835: bipush #30
    //   6837: ishl
    //   6838: ior
    //   6839: aload #23
    //   6841: iconst_0
    //   6842: iaload
    //   6843: bipush #13
    //   6845: iushr
    //   6846: aload #23
    //   6848: iconst_0
    //   6849: iaload
    //   6850: bipush #19
    //   6852: ishl
    //   6853: ior
    //   6854: ixor
    //   6855: aload #23
    //   6857: iconst_0
    //   6858: iaload
    //   6859: bipush #22
    //   6861: iushr
    //   6862: aload #23
    //   6864: iconst_0
    //   6865: iaload
    //   6866: bipush #10
    //   6868: ishl
    //   6869: ior
    //   6870: ixor
    //   6871: aload #23
    //   6873: iconst_0
    //   6874: iaload
    //   6875: aload #23
    //   6877: iconst_1
    //   6878: iaload
    //   6879: iand
    //   6880: aload #23
    //   6882: iconst_2
    //   6883: iaload
    //   6884: aload #23
    //   6886: iconst_0
    //   6887: iaload
    //   6888: aload #23
    //   6890: iconst_1
    //   6891: iaload
    //   6892: ior
    //   6893: iand
    //   6894: ior
    //   6895: iadd
    //   6896: istore #26
    //   6898: aload #23
    //   6900: iconst_3
    //   6901: dup2
    //   6902: iaload
    //   6903: iload #25
    //   6905: iadd
    //   6906: iastore
    //   6907: aload #23
    //   6909: bipush #7
    //   6911: iload #25
    //   6913: iload #26
    //   6915: iadd
    //   6916: iastore
    //   6917: aload #23
    //   6919: bipush #7
    //   6921: iaload
    //   6922: istore #25
    //   6924: aload #23
    //   6926: bipush #7
    //   6928: aload #23
    //   6930: bipush #6
    //   6932: iaload
    //   6933: iastore
    //   6934: aload #23
    //   6936: bipush #6
    //   6938: aload #23
    //   6940: iconst_5
    //   6941: iaload
    //   6942: iastore
    //   6943: aload #23
    //   6945: iconst_5
    //   6946: aload #23
    //   6948: iconst_4
    //   6949: iaload
    //   6950: iastore
    //   6951: aload #23
    //   6953: iconst_4
    //   6954: aload #23
    //   6956: iconst_3
    //   6957: iaload
    //   6958: iastore
    //   6959: aload #23
    //   6961: iconst_3
    //   6962: aload #23
    //   6964: iconst_2
    //   6965: iaload
    //   6966: iastore
    //   6967: aload #23
    //   6969: iconst_2
    //   6970: aload #23
    //   6972: iconst_1
    //   6973: iaload
    //   6974: iastore
    //   6975: aload #23
    //   6977: iconst_1
    //   6978: aload #23
    //   6980: iconst_0
    //   6981: iaload
    //   6982: iastore
    //   6983: aload #23
    //   6985: iconst_0
    //   6986: iload #25
    //   6988: iastore
    //   6989: iinc #24, 1
    //   6992: iload_2
    //   6993: ifne -> 6501
    //   6996: iconst_0
    //   6997: istore #24
    //   6999: iload #24
    //   7001: bipush #8
    //   7003: if_icmpge -> 7026
    //   7006: aload #11
    //   7008: iload #24
    //   7010: dup2
    //   7011: iaload
    //   7012: aload #23
    //   7014: iload #24
    //   7016: iaload
    //   7017: iadd
    //   7018: iastore
    //   7019: iinc #24, 1
    //   7022: iload_2
    //   7023: ifne -> 6999
    //   7026: iload #16
    //   7028: iload #21
    //   7030: iadd
    //   7031: istore #16
    //   7033: iload #20
    //   7035: iload #21
    //   7037: isub
    //   7038: istore #20
    //   7040: iconst_0
    //   7041: istore #15
    //   7043: iload #20
    //   7045: bipush #64
    //   7047: if_icmplt -> 7657
    //   7050: iconst_0
    //   7051: istore #22
    //   7053: iload #22
    //   7055: bipush #64
    //   7057: if_icmpge -> 7080
    //   7060: aload #13
    //   7062: iload #22
    //   7064: aload #8
    //   7066: iload #16
    //   7068: iload #22
    //   7070: iadd
    //   7071: baload
    //   7072: bastore
    //   7073: iinc #22, 1
    //   7076: iload_2
    //   7077: ifne -> 7053
    //   7080: bipush #64
    //   7082: newarray int
    //   7084: astore #22
    //   7086: bipush #8
    //   7088: newarray int
    //   7090: astore #23
    //   7092: iconst_0
    //   7093: istore #24
    //   7095: iload #24
    //   7097: bipush #8
    //   7099: if_icmpge -> 7119
    //   7102: aload #23
    //   7104: iload #24
    //   7106: aload #11
    //   7108: iload #24
    //   7110: iaload
    //   7111: iastore
    //   7112: iinc #24, 1
    //   7115: iload_2
    //   7116: ifne -> 7095
    //   7119: iconst_0
    //   7120: istore #24
    //   7122: iload #24
    //   7124: bipush #64
    //   7126: if_icmpge -> 7617
    //   7129: iload #24
    //   7131: bipush #16
    //   7133: if_icmpge -> 7214
    //   7136: aload #22
    //   7138: iload #24
    //   7140: aload #13
    //   7142: iconst_4
    //   7143: iload #24
    //   7145: imul
    //   7146: baload
    //   7147: sipush #255
    //   7150: iand
    //   7151: bipush #24
    //   7153: ishl
    //   7154: aload #13
    //   7156: iconst_4
    //   7157: iload #24
    //   7159: imul
    //   7160: iconst_1
    //   7161: iadd
    //   7162: baload
    //   7163: sipush #255
    //   7166: iand
    //   7167: bipush #16
    //   7169: ishl
    //   7170: ior
    //   7171: aload #13
    //   7173: iconst_4
    //   7174: iload #24
    //   7176: imul
    //   7177: iconst_2
    //   7178: iadd
    //   7179: baload
    //   7180: sipush #255
    //   7183: iand
    //   7184: bipush #8
    //   7186: ishl
    //   7187: ior
    //   7188: aload #13
    //   7190: iconst_4
    //   7191: iload #24
    //   7193: imul
    //   7194: iconst_3
    //   7195: iadd
    //   7196: baload
    //   7197: sipush #255
    //   7200: iand
    //   7201: ior
    //   7202: iastore
    //   7203: iload_2
    //   7204: ifne -> 7357
    //   7207: goto -> 7214
    //   7210: invokestatic a : (Ljava/lang/Throwable;)Ljava/lang/Throwable;
    //   7213: athrow
    //   7214: aload #22
    //   7216: iload #24
    //   7218: aload #22
    //   7220: iload #24
    //   7222: iconst_2
    //   7223: isub
    //   7224: iaload
    //   7225: bipush #17
    //   7227: iushr
    //   7228: aload #22
    //   7230: iload #24
    //   7232: iconst_2
    //   7233: isub
    //   7234: iaload
    //   7235: bipush #15
    //   7237: ishl
    //   7238: ior
    //   7239: aload #22
    //   7241: iload #24
    //   7243: iconst_2
    //   7244: isub
    //   7245: iaload
    //   7246: bipush #19
    //   7248: iushr
    //   7249: aload #22
    //   7251: iload #24
    //   7253: iconst_2
    //   7254: isub
    //   7255: iaload
    //   7256: bipush #13
    //   7258: ishl
    //   7259: ior
    //   7260: ixor
    //   7261: aload #22
    //   7263: iload #24
    //   7265: iconst_2
    //   7266: isub
    //   7267: iaload
    //   7268: bipush #10
    //   7270: iushr
    //   7271: ixor
    //   7272: aload #22
    //   7274: iload #24
    //   7276: bipush #7
    //   7278: isub
    //   7279: iaload
    //   7280: iadd
    //   7281: aload #22
    //   7283: iload #24
    //   7285: bipush #15
    //   7287: isub
    //   7288: iaload
    //   7289: bipush #7
    //   7291: iushr
    //   7292: aload #22
    //   7294: iload #24
    //   7296: bipush #15
    //   7298: isub
    //   7299: iaload
    //   7300: bipush #25
    //   7302: ishl
    //   7303: ior
    //   7304: aload #22
    //   7306: iload #24
    //   7308: bipush #15
    //   7310: isub
    //   7311: iaload
    //   7312: bipush #18
    //   7314: iushr
    //   7315: aload #22
    //   7317: iload #24
    //   7319: bipush #15
    //   7321: isub
    //   7322: iaload
    //   7323: bipush #14
    //   7325: ishl
    //   7326: ior
    //   7327: ixor
    //   7328: aload #22
    //   7330: iload #24
    //   7332: bipush #15
    //   7334: isub
    //   7335: iaload
    //   7336: iconst_3
    //   7337: iushr
    //   7338: ixor
    //   7339: iadd
    //   7340: aload #22
    //   7342: iload #24
    //   7344: bipush #16
    //   7346: isub
    //   7347: iaload
    //   7348: iadd
    //   7349: iastore
    //   7350: goto -> 7357
    //   7353: invokestatic a : (Ljava/lang/Throwable;)Ljava/lang/Throwable;
    //   7356: athrow
    //   7357: aload #23
    //   7359: bipush #7
    //   7361: iaload
    //   7362: aload #23
    //   7364: iconst_4
    //   7365: iaload
    //   7366: bipush #6
    //   7368: iushr
    //   7369: aload #23
    //   7371: iconst_4
    //   7372: iaload
    //   7373: bipush #26
    //   7375: ishl
    //   7376: ior
    //   7377: aload #23
    //   7379: iconst_4
    //   7380: iaload
    //   7381: bipush #11
    //   7383: iushr
    //   7384: aload #23
    //   7386: iconst_4
    //   7387: iaload
    //   7388: bipush #21
    //   7390: ishl
    //   7391: ior
    //   7392: ixor
    //   7393: aload #23
    //   7395: iconst_4
    //   7396: iaload
    //   7397: bipush #25
    //   7399: iushr
    //   7400: aload #23
    //   7402: iconst_4
    //   7403: iaload
    //   7404: bipush #7
    //   7406: ishl
    //   7407: ior
    //   7408: ixor
    //   7409: iadd
    //   7410: aload #23
    //   7412: bipush #6
    //   7414: iaload
    //   7415: aload #23
    //   7417: iconst_4
    //   7418: iaload
    //   7419: aload #23
    //   7421: iconst_5
    //   7422: iaload
    //   7423: aload #23
    //   7425: bipush #6
    //   7427: iaload
    //   7428: ixor
    //   7429: iand
    //   7430: ixor
    //   7431: iadd
    //   7432: aload #9
    //   7434: iload #24
    //   7436: iaload
    //   7437: iadd
    //   7438: aload #22
    //   7440: iload #24
    //   7442: iaload
    //   7443: iadd
    //   7444: istore #25
    //   7446: aload #23
    //   7448: iconst_0
    //   7449: iaload
    //   7450: iconst_2
    //   7451: iushr
    //   7452: aload #23
    //   7454: iconst_0
    //   7455: iaload
    //   7456: bipush #30
    //   7458: ishl
    //   7459: ior
    //   7460: aload #23
    //   7462: iconst_0
    //   7463: iaload
    //   7464: bipush #13
    //   7466: iushr
    //   7467: aload #23
    //   7469: iconst_0
    //   7470: iaload
    //   7471: bipush #19
    //   7473: ishl
    //   7474: ior
    //   7475: ixor
    //   7476: aload #23
    //   7478: iconst_0
    //   7479: iaload
    //   7480: bipush #22
    //   7482: iushr
    //   7483: aload #23
    //   7485: iconst_0
    //   7486: iaload
    //   7487: bipush #10
    //   7489: ishl
    //   7490: ior
    //   7491: ixor
    //   7492: aload #23
    //   7494: iconst_0
    //   7495: iaload
    //   7496: aload #23
    //   7498: iconst_1
    //   7499: iaload
    //   7500: iand
    //   7501: aload #23
    //   7503: iconst_2
    //   7504: iaload
    //   7505: aload #23
    //   7507: iconst_0
    //   7508: iaload
    //   7509: aload #23
    //   7511: iconst_1
    //   7512: iaload
    //   7513: ior
    //   7514: iand
    //   7515: ior
    //   7516: iadd
    //   7517: istore #26
    //   7519: aload #23
    //   7521: iconst_3
    //   7522: dup2
    //   7523: iaload
    //   7524: iload #25
    //   7526: iadd
    //   7527: iastore
    //   7528: aload #23
    //   7530: bipush #7
    //   7532: iload #25
    //   7534: iload #26
    //   7536: iadd
    //   7537: iastore
    //   7538: aload #23
    //   7540: bipush #7
    //   7542: iaload
    //   7543: istore #25
    //   7545: aload #23
    //   7547: bipush #7
    //   7549: aload #23
    //   7551: bipush #6
    //   7553: iaload
    //   7554: iastore
    //   7555: aload #23
    //   7557: bipush #6
    //   7559: aload #23
    //   7561: iconst_5
    //   7562: iaload
    //   7563: iastore
    //   7564: aload #23
    //   7566: iconst_5
    //   7567: aload #23
    //   7569: iconst_4
    //   7570: iaload
    //   7571: iastore
    //   7572: aload #23
    //   7574: iconst_4
    //   7575: aload #23
    //   7577: iconst_3
    //   7578: iaload
    //   7579: iastore
    //   7580: aload #23
    //   7582: iconst_3
    //   7583: aload #23
    //   7585: iconst_2
    //   7586: iaload
    //   7587: iastore
    //   7588: aload #23
    //   7590: iconst_2
    //   7591: aload #23
    //   7593: iconst_1
    //   7594: iaload
    //   7595: iastore
    //   7596: aload #23
    //   7598: iconst_1
    //   7599: aload #23
    //   7601: iconst_0
    //   7602: iaload
    //   7603: iastore
    //   7604: aload #23
    //   7606: iconst_0
    //   7607: iload #25
    //   7609: iastore
    //   7610: iinc #24, 1
    //   7613: iload_2
    //   7614: ifne -> 7122
    //   7617: iconst_0
    //   7618: istore #24
    //   7620: iload #24
    //   7622: bipush #8
    //   7624: if_icmpge -> 7647
    //   7627: aload #11
    //   7629: iload #24
    //   7631: dup2
    //   7632: iaload
    //   7633: aload #23
    //   7635: iload #24
    //   7637: iaload
    //   7638: iadd
    //   7639: iastore
    //   7640: iinc #24, 1
    //   7643: iload_2
    //   7644: ifne -> 7620
    //   7647: iinc #16, 64
    //   7650: iinc #20, -64
    //   7653: iload_2
    //   7654: ifne -> 7043
    //   7657: iload #20
    //   7659: ifle -> 7695
    //   7662: iconst_0
    //   7663: istore #22
    //   7665: iload #22
    //   7667: iload #20
    //   7669: if_icmpge -> 7695
    //   7672: aload #12
    //   7674: iload #15
    //   7676: iload #22
    //   7678: iadd
    //   7679: aload #8
    //   7681: iload #16
    //   7683: iload #22
    //   7685: iadd
    //   7686: baload
    //   7687: bastore
    //   7688: iinc #22, 1
    //   7691: iload_2
    //   7692: ifne -> 7665
    //   7695: bipush #8
    //   7697: newarray byte
    //   7699: astore #22
    //   7701: aload #22
    //   7703: iconst_0
    //   7704: iload #17
    //   7706: bipush #24
    //   7708: iushr
    //   7709: i2b
    //   7710: bastore
    //   7711: aload #22
    //   7713: iconst_1
    //   7714: iload #17
    //   7716: bipush #16
    //   7718: iushr
    //   7719: i2b
    //   7720: bastore
    //   7721: aload #22
    //   7723: iconst_2
    //   7724: iload #17
    //   7726: bipush #8
    //   7728: iushr
    //   7729: i2b
    //   7730: bastore
    //   7731: aload #22
    //   7733: iconst_3
    //   7734: iload #17
    //   7736: i2b
    //   7737: bastore
    //   7738: aload #22
    //   7740: iconst_4
    //   7741: iload #18
    //   7743: bipush #24
    //   7745: iushr
    //   7746: i2b
    //   7747: bastore
    //   7748: aload #22
    //   7750: iconst_5
    //   7751: iload #18
    //   7753: bipush #16
    //   7755: iushr
    //   7756: i2b
    //   7757: bastore
    //   7758: aload #22
    //   7760: bipush #6
    //   7762: iload #18
    //   7764: bipush #8
    //   7766: iushr
    //   7767: i2b
    //   7768: bastore
    //   7769: aload #22
    //   7771: bipush #7
    //   7773: iload #18
    //   7775: i2b
    //   7776: bastore
    //   7777: bipush #8
    //   7779: istore #14
    //   7781: aload #10
    //   7783: iconst_0
    //   7784: iaload
    //   7785: bipush #63
    //   7787: iand
    //   7788: istore #15
    //   7790: bipush #64
    //   7792: iload #15
    //   7794: isub
    //   7795: istore #21
    //   7797: aload #10
    //   7799: iconst_0
    //   7800: dup2
    //   7801: iaload
    //   7802: iload #14
    //   7804: iadd
    //   7805: iastore
    //   7806: aload #10
    //   7808: iconst_0
    //   7809: dup2
    //   7810: iaload
    //   7811: iconst_m1
    //   7812: iand
    //   7813: iastore
    //   7814: aload #10
    //   7816: iconst_0
    //   7817: iaload
    //   7818: iload #14
    //   7820: if_icmpge -> 7838
    //   7823: aload #10
    //   7825: iconst_1
    //   7826: dup2
    //   7827: iaload
    //   7828: iconst_1
    //   7829: iadd
    //   7830: iastore
    //   7831: goto -> 7838
    //   7834: invokestatic a : (Ljava/lang/Throwable;)Ljava/lang/Throwable;
    //   7837: athrow
    //   7838: iload #15
    //   7840: ifle -> 8454
    //   7843: iload #14
    //   7845: iload #21
    //   7847: if_icmplt -> 8454
    //   7850: goto -> 7857
    //   7853: invokestatic a : (Ljava/lang/Throwable;)Ljava/lang/Throwable;
    //   7856: athrow
    //   7857: iconst_0
    //   7858: istore #23
    //   7860: iload #23
    //   7862: iload #21
    //   7864: if_icmpge -> 7887
    //   7867: aload #12
    //   7869: iload #15
    //   7871: iload #23
    //   7873: iadd
    //   7874: aload #22
    //   7876: iload #23
    //   7878: baload
    //   7879: bastore
    //   7880: iinc #23, 1
    //   7883: iload_2
    //   7884: ifne -> 7860
    //   7887: bipush #64
    //   7889: newarray int
    //   7891: astore #23
    //   7893: bipush #8
    //   7895: newarray int
    //   7897: astore #24
    //   7899: iconst_0
    //   7900: istore #25
    //   7902: iload #25
    //   7904: bipush #8
    //   7906: if_icmpge -> 7926
    //   7909: aload #24
    //   7911: iload #25
    //   7913: aload #11
    //   7915: iload #25
    //   7917: iaload
    //   7918: iastore
    //   7919: iinc #25, 1
    //   7922: iload_2
    //   7923: ifne -> 7902
    //   7926: iconst_0
    //   7927: istore #25
    //   7929: iload #25
    //   7931: bipush #64
    //   7933: if_icmpge -> 8424
    //   7936: iload #25
    //   7938: bipush #16
    //   7940: if_icmpge -> 8021
    //   7943: aload #23
    //   7945: iload #25
    //   7947: aload #12
    //   7949: iconst_4
    //   7950: iload #25
    //   7952: imul
    //   7953: baload
    //   7954: sipush #255
    //   7957: iand
    //   7958: bipush #24
    //   7960: ishl
    //   7961: aload #12
    //   7963: iconst_4
    //   7964: iload #25
    //   7966: imul
    //   7967: iconst_1
    //   7968: iadd
    //   7969: baload
    //   7970: sipush #255
    //   7973: iand
    //   7974: bipush #16
    //   7976: ishl
    //   7977: ior
    //   7978: aload #12
    //   7980: iconst_4
    //   7981: iload #25
    //   7983: imul
    //   7984: iconst_2
    //   7985: iadd
    //   7986: baload
    //   7987: sipush #255
    //   7990: iand
    //   7991: bipush #8
    //   7993: ishl
    //   7994: ior
    //   7995: aload #12
    //   7997: iconst_4
    //   7998: iload #25
    //   8000: imul
    //   8001: iconst_3
    //   8002: iadd
    //   8003: baload
    //   8004: sipush #255
    //   8007: iand
    //   8008: ior
    //   8009: iastore
    //   8010: iload_2
    //   8011: ifne -> 8164
    //   8014: goto -> 8021
    //   8017: invokestatic a : (Ljava/lang/Throwable;)Ljava/lang/Throwable;
    //   8020: athrow
    //   8021: aload #23
    //   8023: iload #25
    //   8025: aload #23
    //   8027: iload #25
    //   8029: iconst_2
    //   8030: isub
    //   8031: iaload
    //   8032: bipush #17
    //   8034: iushr
    //   8035: aload #23
    //   8037: iload #25
    //   8039: iconst_2
    //   8040: isub
    //   8041: iaload
    //   8042: bipush #15
    //   8044: ishl
    //   8045: ior
    //   8046: aload #23
    //   8048: iload #25
    //   8050: iconst_2
    //   8051: isub
    //   8052: iaload
    //   8053: bipush #19
    //   8055: iushr
    //   8056: aload #23
    //   8058: iload #25
    //   8060: iconst_2
    //   8061: isub
    //   8062: iaload
    //   8063: bipush #13
    //   8065: ishl
    //   8066: ior
    //   8067: ixor
    //   8068: aload #23
    //   8070: iload #25
    //   8072: iconst_2
    //   8073: isub
    //   8074: iaload
    //   8075: bipush #10
    //   8077: iushr
    //   8078: ixor
    //   8079: aload #23
    //   8081: iload #25
    //   8083: bipush #7
    //   8085: isub
    //   8086: iaload
    //   8087: iadd
    //   8088: aload #23
    //   8090: iload #25
    //   8092: bipush #15
    //   8094: isub
    //   8095: iaload
    //   8096: bipush #7
    //   8098: iushr
    //   8099: aload #23
    //   8101: iload #25
    //   8103: bipush #15
    //   8105: isub
    //   8106: iaload
    //   8107: bipush #25
    //   8109: ishl
    //   8110: ior
    //   8111: aload #23
    //   8113: iload #25
    //   8115: bipush #15
    //   8117: isub
    //   8118: iaload
    //   8119: bipush #18
    //   8121: iushr
    //   8122: aload #23
    //   8124: iload #25
    //   8126: bipush #15
    //   8128: isub
    //   8129: iaload
    //   8130: bipush #14
    //   8132: ishl
    //   8133: ior
    //   8134: ixor
    //   8135: aload #23
    //   8137: iload #25
    //   8139: bipush #15
    //   8141: isub
    //   8142: iaload
    //   8143: iconst_3
    //   8144: iushr
    //   8145: ixor
    //   8146: iadd
    //   8147: aload #23
    //   8149: iload #25
    //   8151: bipush #16
    //   8153: isub
    //   8154: iaload
    //   8155: iadd
    //   8156: iastore
    //   8157: goto -> 8164
    //   8160: invokestatic a : (Ljava/lang/Throwable;)Ljava/lang/Throwable;
    //   8163: athrow
    //   8164: aload #24
    //   8166: bipush #7
    //   8168: iaload
    //   8169: aload #24
    //   8171: iconst_4
    //   8172: iaload
    //   8173: bipush #6
    //   8175: iushr
    //   8176: aload #24
    //   8178: iconst_4
    //   8179: iaload
    //   8180: bipush #26
    //   8182: ishl
    //   8183: ior
    //   8184: aload #24
    //   8186: iconst_4
    //   8187: iaload
    //   8188: bipush #11
    //   8190: iushr
    //   8191: aload #24
    //   8193: iconst_4
    //   8194: iaload
    //   8195: bipush #21
    //   8197: ishl
    //   8198: ior
    //   8199: ixor
    //   8200: aload #24
    //   8202: iconst_4
    //   8203: iaload
    //   8204: bipush #25
    //   8206: iushr
    //   8207: aload #24
    //   8209: iconst_4
    //   8210: iaload
    //   8211: bipush #7
    //   8213: ishl
    //   8214: ior
    //   8215: ixor
    //   8216: iadd
    //   8217: aload #24
    //   8219: bipush #6
    //   8221: iaload
    //   8222: aload #24
    //   8224: iconst_4
    //   8225: iaload
    //   8226: aload #24
    //   8228: iconst_5
    //   8229: iaload
    //   8230: aload #24
    //   8232: bipush #6
    //   8234: iaload
    //   8235: ixor
    //   8236: iand
    //   8237: ixor
    //   8238: iadd
    //   8239: aload #9
    //   8241: iload #25
    //   8243: iaload
    //   8244: iadd
    //   8245: aload #23
    //   8247: iload #25
    //   8249: iaload
    //   8250: iadd
    //   8251: istore #26
    //   8253: aload #24
    //   8255: iconst_0
    //   8256: iaload
    //   8257: iconst_2
    //   8258: iushr
    //   8259: aload #24
    //   8261: iconst_0
    //   8262: iaload
    //   8263: bipush #30
    //   8265: ishl
    //   8266: ior
    //   8267: aload #24
    //   8269: iconst_0
    //   8270: iaload
    //   8271: bipush #13
    //   8273: iushr
    //   8274: aload #24
    //   8276: iconst_0
    //   8277: iaload
    //   8278: bipush #19
    //   8280: ishl
    //   8281: ior
    //   8282: ixor
    //   8283: aload #24
    //   8285: iconst_0
    //   8286: iaload
    //   8287: bipush #22
    //   8289: iushr
    //   8290: aload #24
    //   8292: iconst_0
    //   8293: iaload
    //   8294: bipush #10
    //   8296: ishl
    //   8297: ior
    //   8298: ixor
    //   8299: aload #24
    //   8301: iconst_0
    //   8302: iaload
    //   8303: aload #24
    //   8305: iconst_1
    //   8306: iaload
    //   8307: iand
    //   8308: aload #24
    //   8310: iconst_2
    //   8311: iaload
    //   8312: aload #24
    //   8314: iconst_0
    //   8315: iaload
    //   8316: aload #24
    //   8318: iconst_1
    //   8319: iaload
    //   8320: ior
    //   8321: iand
    //   8322: ior
    //   8323: iadd
    //   8324: istore #27
    //   8326: aload #24
    //   8328: iconst_3
    //   8329: dup2
    //   8330: iaload
    //   8331: iload #26
    //   8333: iadd
    //   8334: iastore
    //   8335: aload #24
    //   8337: bipush #7
    //   8339: iload #26
    //   8341: iload #27
    //   8343: iadd
    //   8344: iastore
    //   8345: aload #24
    //   8347: bipush #7
    //   8349: iaload
    //   8350: istore #26
    //   8352: aload #24
    //   8354: bipush #7
    //   8356: aload #24
    //   8358: bipush #6
    //   8360: iaload
    //   8361: iastore
    //   8362: aload #24
    //   8364: bipush #6
    //   8366: aload #24
    //   8368: iconst_5
    //   8369: iaload
    //   8370: iastore
    //   8371: aload #24
    //   8373: iconst_5
    //   8374: aload #24
    //   8376: iconst_4
    //   8377: iaload
    //   8378: iastore
    //   8379: aload #24
    //   8381: iconst_4
    //   8382: aload #24
    //   8384: iconst_3
    //   8385: iaload
    //   8386: iastore
    //   8387: aload #24
    //   8389: iconst_3
    //   8390: aload #24
    //   8392: iconst_2
    //   8393: iaload
    //   8394: iastore
    //   8395: aload #24
    //   8397: iconst_2
    //   8398: aload #24
    //   8400: iconst_1
    //   8401: iaload
    //   8402: iastore
    //   8403: aload #24
    //   8405: iconst_1
    //   8406: aload #24
    //   8408: iconst_0
    //   8409: iaload
    //   8410: iastore
    //   8411: aload #24
    //   8413: iconst_0
    //   8414: iload #26
    //   8416: iastore
    //   8417: iinc #25, 1
    //   8420: iload_2
    //   8421: ifne -> 7929
    //   8424: iconst_0
    //   8425: istore #25
    //   8427: iload #25
    //   8429: bipush #8
    //   8431: if_icmpge -> 8454
    //   8434: aload #11
    //   8436: iload #25
    //   8438: dup2
    //   8439: iaload
    //   8440: aload #24
    //   8442: iload #25
    //   8444: iaload
    //   8445: iadd
    //   8446: iastore
    //   8447: iinc #25, 1
    //   8450: iload_2
    //   8451: ifne -> 8427
    //   8454: bipush #32
    //   8456: newarray byte
    //   8458: astore #7
    //   8460: aload #7
    //   8462: iconst_0
    //   8463: aload #11
    //   8465: iconst_0
    //   8466: iaload
    //   8467: bipush #24
    //   8469: iushr
    //   8470: i2b
    //   8471: bastore
    //   8472: aload #7
    //   8474: iconst_1
    //   8475: aload #11
    //   8477: iconst_0
    //   8478: iaload
    //   8479: bipush #16
    //   8481: iushr
    //   8482: i2b
    //   8483: bastore
    //   8484: aload #7
    //   8486: iconst_2
    //   8487: aload #11
    //   8489: iconst_0
    //   8490: iaload
    //   8491: bipush #8
    //   8493: iushr
    //   8494: i2b
    //   8495: bastore
    //   8496: aload #7
    //   8498: iconst_3
    //   8499: aload #11
    //   8501: iconst_0
    //   8502: iaload
    //   8503: i2b
    //   8504: bastore
    //   8505: aload #7
    //   8507: iconst_4
    //   8508: aload #11
    //   8510: iconst_1
    //   8511: iaload
    //   8512: bipush #24
    //   8514: iushr
    //   8515: i2b
    //   8516: bastore
    //   8517: aload #7
    //   8519: iconst_5
    //   8520: aload #11
    //   8522: iconst_1
    //   8523: iaload
    //   8524: bipush #16
    //   8526: iushr
    //   8527: i2b
    //   8528: bastore
    //   8529: aload #7
    //   8531: bipush #6
    //   8533: aload #11
    //   8535: iconst_1
    //   8536: iaload
    //   8537: bipush #8
    //   8539: iushr
    //   8540: i2b
    //   8541: bastore
    //   8542: aload #7
    //   8544: bipush #7
    //   8546: aload #11
    //   8548: iconst_1
    //   8549: iaload
    //   8550: i2b
    //   8551: bastore
    //   8552: aload #7
    //   8554: bipush #8
    //   8556: aload #11
    //   8558: iconst_2
    //   8559: iaload
    //   8560: bipush #24
    //   8562: iushr
    //   8563: i2b
    //   8564: bastore
    //   8565: aload #7
    //   8567: bipush #9
    //   8569: aload #11
    //   8571: iconst_2
    //   8572: iaload
    //   8573: bipush #16
    //   8575: iushr
    //   8576: i2b
    //   8577: bastore
    //   8578: aload #7
    //   8580: bipush #10
    //   8582: aload #11
    //   8584: iconst_2
    //   8585: iaload
    //   8586: bipush #8
    //   8588: iushr
    //   8589: i2b
    //   8590: bastore
    //   8591: aload #7
    //   8593: bipush #11
    //   8595: aload #11
    //   8597: iconst_2
    //   8598: iaload
    //   8599: i2b
    //   8600: bastore
    //   8601: aload #7
    //   8603: bipush #12
    //   8605: aload #11
    //   8607: iconst_3
    //   8608: iaload
    //   8609: bipush #24
    //   8611: iushr
    //   8612: i2b
    //   8613: bastore
    //   8614: aload #7
    //   8616: bipush #13
    //   8618: aload #11
    //   8620: iconst_3
    //   8621: iaload
    //   8622: bipush #16
    //   8624: iushr
    //   8625: i2b
    //   8626: bastore
    //   8627: aload #7
    //   8629: bipush #14
    //   8631: aload #11
    //   8633: iconst_3
    //   8634: iaload
    //   8635: bipush #8
    //   8637: iushr
    //   8638: i2b
    //   8639: bastore
    //   8640: aload #7
    //   8642: bipush #15
    //   8644: aload #11
    //   8646: iconst_3
    //   8647: iaload
    //   8648: i2b
    //   8649: bastore
    //   8650: aload #7
    //   8652: bipush #16
    //   8654: aload #11
    //   8656: iconst_4
    //   8657: iaload
    //   8658: bipush #24
    //   8660: iushr
    //   8661: i2b
    //   8662: bastore
    //   8663: aload #7
    //   8665: bipush #17
    //   8667: aload #11
    //   8669: iconst_4
    //   8670: iaload
    //   8671: bipush #16
    //   8673: iushr
    //   8674: i2b
    //   8675: bastore
    //   8676: aload #7
    //   8678: bipush #18
    //   8680: aload #11
    //   8682: iconst_4
    //   8683: iaload
    //   8684: bipush #8
    //   8686: iushr
    //   8687: i2b
    //   8688: bastore
    //   8689: aload #7
    //   8691: bipush #19
    //   8693: aload #11
    //   8695: iconst_4
    //   8696: iaload
    //   8697: i2b
    //   8698: bastore
    //   8699: aload #7
    //   8701: bipush #20
    //   8703: aload #11
    //   8705: iconst_5
    //   8706: iaload
    //   8707: bipush #24
    //   8709: iushr
    //   8710: i2b
    //   8711: bastore
    //   8712: aload #7
    //   8714: bipush #21
    //   8716: aload #11
    //   8718: iconst_5
    //   8719: iaload
    //   8720: bipush #16
    //   8722: iushr
    //   8723: i2b
    //   8724: bastore
    //   8725: aload #7
    //   8727: bipush #22
    //   8729: aload #11
    //   8731: iconst_5
    //   8732: iaload
    //   8733: bipush #8
    //   8735: iushr
    //   8736: i2b
    //   8737: bastore
    //   8738: aload #7
    //   8740: bipush #23
    //   8742: aload #11
    //   8744: iconst_5
    //   8745: iaload
    //   8746: i2b
    //   8747: bastore
    //   8748: aload #7
    //   8750: bipush #24
    //   8752: aload #11
    //   8754: bipush #6
    //   8756: iaload
    //   8757: bipush #24
    //   8759: iushr
    //   8760: i2b
    //   8761: bastore
    //   8762: aload #7
    //   8764: bipush #25
    //   8766: aload #11
    //   8768: bipush #6
    //   8770: iaload
    //   8771: bipush #16
    //   8773: iushr
    //   8774: i2b
    //   8775: bastore
    //   8776: aload #7
    //   8778: bipush #26
    //   8780: aload #11
    //   8782: bipush #6
    //   8784: iaload
    //   8785: bipush #8
    //   8787: iushr
    //   8788: i2b
    //   8789: bastore
    //   8790: aload #7
    //   8792: bipush #27
    //   8794: aload #11
    //   8796: bipush #6
    //   8798: iaload
    //   8799: i2b
    //   8800: bastore
    //   8801: aload #7
    //   8803: bipush #28
    //   8805: aload #11
    //   8807: bipush #7
    //   8809: iaload
    //   8810: bipush #24
    //   8812: iushr
    //   8813: i2b
    //   8814: bastore
    //   8815: aload #7
    //   8817: bipush #29
    //   8819: aload #11
    //   8821: bipush #7
    //   8823: iaload
    //   8824: bipush #16
    //   8826: iushr
    //   8827: i2b
    //   8828: bastore
    //   8829: aload #7
    //   8831: bipush #30
    //   8833: aload #11
    //   8835: bipush #7
    //   8837: iaload
    //   8838: bipush #8
    //   8840: iushr
    //   8841: i2b
    //   8842: bastore
    //   8843: aload #7
    //   8845: bipush #31
    //   8847: aload #11
    //   8849: bipush #7
    //   8851: iaload
    //   8852: i2b
    //   8853: bastore
    //   8854: getstatic burp/Zb14.Ze : Ljava/lang/String;
    //   8857: getstatic burp/Zl1n.ZM : Ljava/lang/Object;
    //   8860: checkcast java/math/BigInteger
    //   8863: invokevirtual intValue : ()I
    //   8866: bipush #32
    //   8868: irem
    //   8869: invokestatic abs : (I)I
    //   8872: invokevirtual charAt : (I)C
    //   8875: getstatic burp/Zsq5.ZA : Ljava/lang/String;
    //   8878: getstatic burp/Zec0.Zg : Ljava/lang/Object;
    //   8881: checkcast java/math/BigInteger
    //   8884: invokevirtual intValue : ()I
    //   8887: bipush #32
    //   8889: irem
    //   8890: invokestatic abs : (I)I
    //   8893: invokevirtual charAt : (I)C
    //   8896: if_icmpgt -> 9011
    //   8899: getstatic burp/Zzxa.Zl : Ljava/lang/String;
    //   8902: getstatic burp/Zk5y.ZL : Ljava/lang/Object;
    //   8905: checkcast java/math/BigInteger
    //   8908: invokevirtual intValue : ()I
    //   8911: bipush #32
    //   8913: irem
    //   8914: invokestatic abs : (I)I
    //   8917: invokevirtual charAt : (I)C
    //   8920: getstatic burp/Zl4v.ZD : Ljava/lang/String;
    //   8923: getstatic burp/Zsuw.ZB : Ljava/lang/Object;
    //   8926: checkcast java/math/BigInteger
    //   8929: invokevirtual intValue : ()I
    //   8932: bipush #32
    //   8934: irem
    //   8935: invokestatic abs : (I)I
    //   8938: invokevirtual charAt : (I)C
    //   8941: if_icmpgt -> 9011
    //   8944: goto -> 8951
    //   8947: invokestatic a : (Ljava/lang/Throwable;)Ljava/lang/Throwable;
    //   8950: athrow
    //   8951: getstatic burp/Zl7k.ZX : Ljava/lang/String;
    //   8954: getstatic burp/Zb9d.Ze : Ljava/lang/Object;
    //   8957: checkcast java/math/BigInteger
    //   8960: invokevirtual intValue : ()I
    //   8963: bipush #32
    //   8965: irem
    //   8966: invokestatic abs : (I)I
    //   8969: invokevirtual charAt : (I)C
    //   8972: getstatic burp/Zxxo.ZH : Ljava/lang/String;
    //   8975: getstatic burp/Ze3j.Ze : Ljava/lang/Object;
    //   8978: checkcast java/math/BigInteger
    //   8981: invokevirtual intValue : ()I
    //   8984: bipush #32
    //   8986: irem
    //   8987: invokestatic abs : (I)I
    //   8990: invokevirtual charAt : (I)C
    //   8993: if_icmpgt -> 9011
    //   8996: goto -> 9003
    //   8999: invokestatic a : (Ljava/lang/Throwable;)Ljava/lang/Throwable;
    //   9002: athrow
    //   9003: iconst_1
    //   9004: goto -> 9012
    //   9007: invokestatic a : (Ljava/lang/Throwable;)Ljava/lang/Throwable;
    //   9010: athrow
    //   9011: iconst_0
    //   9012: ireturn
    //   9013: astore_3
    //   9014: new java/lang/Exception
    //   9017: dup
    //   9018: aload_3
    //   9019: invokevirtual getMessage : ()Ljava/lang/String;
    //   9022: invokespecial <init> : (Ljava/lang/String;)V
    //   9025: athrow
    // Exception table:
    //   from	to	target	type
    //   4	9012	9013	java/lang/Throwable
    //   22	198	201	java/lang/Throwable
    //   168	235	238	java/lang/Throwable
    //   205	272	275	java/lang/Throwable
    //   242	309	312	java/lang/Throwable
    //   279	346	349	java/lang/Throwable
    //   316	383	386	java/lang/Throwable
    //   353	420	423	java/lang/Throwable
    //   390	457	460	java/lang/Throwable
    //   427	494	497	java/lang/Throwable
    //   464	531	534	java/lang/Throwable
    //   501	568	571	java/lang/Throwable
    //   538	605	608	java/lang/Throwable
    //   575	642	645	java/lang/Throwable
    //   612	679	682	java/lang/Throwable
    //   649	716	719	java/lang/Throwable
    //   686	753	756	java/lang/Throwable
    //   723	790	793	java/lang/Throwable
    //   760	827	830	java/lang/Throwable
    //   797	864	867	java/lang/Throwable
    //   834	901	904	java/lang/Throwable
    //   871	938	941	java/lang/Throwable
    //   908	975	978	java/lang/Throwable
    //   945	1012	1015	java/lang/Throwable
    //   982	1049	1052	java/lang/Throwable
    //   1019	1086	1089	java/lang/Throwable
    //   1056	1123	1126	java/lang/Throwable
    //   1093	1160	1163	java/lang/Throwable
    //   1130	1197	1200	java/lang/Throwable
    //   1167	1234	1237	java/lang/Throwable
    //   1204	1271	1274	java/lang/Throwable
    //   1241	1308	1311	java/lang/Throwable
    //   1278	1341	1344	java/lang/Throwable
    //   1381	1555	1558	java/lang/Throwable
    //   1524	1593	1596	java/lang/Throwable
    //   1562	1631	1634	java/lang/Throwable
    //   1600	1669	1672	java/lang/Throwable
    //   1638	1707	1710	java/lang/Throwable
    //   1676	1745	1748	java/lang/Throwable
    //   1714	1783	1786	java/lang/Throwable
    //   1752	1821	1824	java/lang/Throwable
    //   1790	1859	1862	java/lang/Throwable
    //   1828	1897	1900	java/lang/Throwable
    //   1866	1935	1938	java/lang/Throwable
    //   1904	1973	1976	java/lang/Throwable
    //   1942	2011	2014	java/lang/Throwable
    //   1980	2049	2052	java/lang/Throwable
    //   2018	2087	2090	java/lang/Throwable
    //   2056	2125	2128	java/lang/Throwable
    //   2094	2163	2166	java/lang/Throwable
    //   2132	2201	2204	java/lang/Throwable
    //   2170	2239	2242	java/lang/Throwable
    //   2208	2277	2280	java/lang/Throwable
    //   2246	2315	2318	java/lang/Throwable
    //   2284	2353	2356	java/lang/Throwable
    //   2322	2391	2394	java/lang/Throwable
    //   2360	2429	2432	java/lang/Throwable
    //   2398	2467	2470	java/lang/Throwable
    //   2436	2505	2508	java/lang/Throwable
    //   2474	2543	2546	java/lang/Throwable
    //   2512	2581	2584	java/lang/Throwable
    //   2550	2619	2622	java/lang/Throwable
    //   2588	2657	2660	java/lang/Throwable
    //   2626	2695	2698	java/lang/Throwable
    //   2664	2729	2732	java/lang/Throwable
    //   2770	2947	2950	java/lang/Throwable
    //   2916	2985	2988	java/lang/Throwable
    //   2954	3023	3026	java/lang/Throwable
    //   2992	3061	3064	java/lang/Throwable
    //   3030	3099	3102	java/lang/Throwable
    //   3068	3137	3140	java/lang/Throwable
    //   3106	3175	3178	java/lang/Throwable
    //   3144	3213	3216	java/lang/Throwable
    //   3182	3251	3254	java/lang/Throwable
    //   3220	3289	3292	java/lang/Throwable
    //   3258	3327	3330	java/lang/Throwable
    //   3296	3365	3368	java/lang/Throwable
    //   3334	3403	3406	java/lang/Throwable
    //   3372	3441	3444	java/lang/Throwable
    //   3410	3479	3482	java/lang/Throwable
    //   3448	3517	3520	java/lang/Throwable
    //   3486	3555	3558	java/lang/Throwable
    //   3524	3593	3596	java/lang/Throwable
    //   3562	3631	3634	java/lang/Throwable
    //   3600	3669	3672	java/lang/Throwable
    //   3638	3707	3710	java/lang/Throwable
    //   3676	3745	3748	java/lang/Throwable
    //   3714	3783	3786	java/lang/Throwable
    //   3752	3821	3824	java/lang/Throwable
    //   3790	3859	3862	java/lang/Throwable
    //   3828	3897	3900	java/lang/Throwable
    //   3866	3935	3938	java/lang/Throwable
    //   3904	3973	3976	java/lang/Throwable
    //   3942	4011	4014	java/lang/Throwable
    //   3980	4049	4052	java/lang/Throwable
    //   4018	4087	4090	java/lang/Throwable
    //   4056	4121	4124	java/lang/Throwable
    //   4188	4202	4202	java/lang/Throwable
    //   4213	4226	4229	java/lang/Throwable
    //   4218	4241	4244	java/lang/Throwable
    //   4233	4259	4262	java/lang/Throwable
    //   4248	4289	4292	java/lang/Throwable
    //   4355	4382	4385	java/lang/Throwable
    //   4372	4400	4403	java/lang/Throwable
    //   4389	4436	4439	java/lang/Throwable
    //   4407	4450	4453	java/lang/Throwable
    //   4502	4516	4516	java/lang/Throwable
    //   4527	4540	4543	java/lang/Throwable
    //   4532	4555	4558	java/lang/Throwable
    //   4547	4573	4576	java/lang/Throwable
    //   4562	4603	4606	java/lang/Throwable
    //   4669	4696	4699	java/lang/Throwable
    //   4686	4717	4720	java/lang/Throwable
    //   4703	4747	4750	java/lang/Throwable
    //   4724	4758	4758	java/lang/Throwable
    //   4769	4785	4788	java/lang/Throwable
    //   5595	5629	5632	java/lang/Throwable
    //   5725	5803	5806	java/lang/Throwable
    //   5732	5946	5949	java/lang/Throwable
    //   6324	6339	6339	java/lang/Throwable
    //   6366	6400	6403	java/lang/Throwable
    //   6410	6422	6425	java/lang/Throwable
    //   6508	6586	6589	java/lang/Throwable
    //   6515	6729	6732	java/lang/Throwable
    //   7129	7207	7210	java/lang/Throwable
    //   7136	7350	7353	java/lang/Throwable
    //   7797	7831	7834	java/lang/Throwable
    //   7838	7850	7853	java/lang/Throwable
    //   7936	8014	8017	java/lang/Throwable
    //   7943	8157	8160	java/lang/Throwable
    //   8460	8944	8947	java/lang/Throwable
    //   8899	8996	8999	java/lang/Throwable
    //   8951	9007	9007	java/lang/Throwable
  }
  
  static void Zm(Object paramObject) {
    Zgyc.Zj = a(-31480, -24327);
    Zgyc.ZT = new BigInteger(a(-31481, -24963));
    boolean bool = Zt2e.ZK();
    try {
      try {
        if (Zl8i.Zb.charAt(Math.abs(((BigInteger)Zkgp.Zw).intValue() % 32)) > Zb2p.ZV.charAt(Math.abs(((BigInteger)Zvos.Zr).intValue() % 32))) {
          try {
            Zlno.ZF(Class.forName(a(-31477, 26634)));
            if (bool)
              Ztv8.Ze(Class.forName(a(-31486, 11051))); 
          } catch (Throwable throwable) {
            throw a(null);
          } 
          return;
        } 
      } catch (Throwable throwable) {
        throw a(null);
      } 
      Ztv8.Ze(Class.forName(a(-31486, 11051)));
    } catch (Throwable throwable) {}
  }
  
  static {
    // Byte code:
    //   0: bipush #11
    //   2: anewarray java/lang/String
    //   5: astore #5
    //   7: iconst_0
    //   8: istore_3
    //   9: ldc '8]e\\tt$\\tOck#\\t"T \\b?vYj0 M98BZ4b0uf]u\\fUWZMIm13%b7zfQ>i&*{5ZPq2q2)BwN$`r][W\\f.r\\t\\f$s'
    //   11: dup
    //   12: astore_2
    //   13: invokevirtual length : ()I
    //   16: istore #4
    //   18: bipush #9
    //   20: istore_1
    //   21: iconst_m1
    //   22: istore_0
    //   23: bipush #111
    //   25: iinc #0, 1
    //   28: aload_2
    //   29: iload_0
    //   30: dup
    //   31: iload_1
    //   32: iadd
    //   33: invokevirtual substring : (II)Ljava/lang/String;
    //   36: iconst_m1
    //   37: goto -> 143
    //   40: aload #5
    //   42: swap
    //   43: iload_3
    //   44: iinc #3, 1
    //   47: swap
    //   48: aastore
    //   49: iload_0
    //   50: iload_1
    //   51: iadd
    //   52: dup
    //   53: istore_0
    //   54: iload #4
    //   56: if_icmpge -> 68
    //   59: aload_2
    //   60: iload_0
    //   61: invokevirtual charAt : (I)C
    //   64: istore_1
    //   65: goto -> 23
    //   68: ldc ' =s[GtCT7)$t:\\r\\t5jV'
    //   70: dup
    //   71: astore_2
    //   72: invokevirtual length : ()I
    //   75: istore #4
    //   77: bipush #32
    //   79: istore_1
    //   80: iconst_m1
    //   81: istore_0
    //   82: bipush #36
    //   84: iinc #0, 1
    //   87: aload_2
    //   88: iload_0
    //   89: dup
    //   90: iload_1
    //   91: iadd
    //   92: invokevirtual substring : (II)Ljava/lang/String;
    //   95: iconst_0
    //   96: goto -> 143
    //   99: aload #5
    //   101: swap
    //   102: iload_3
    //   103: iinc #3, 1
    //   106: swap
    //   107: aastore
    //   108: iload_0
    //   109: iload_1
    //   110: iadd
    //   111: dup
    //   112: istore_0
    //   113: iload #4
    //   115: if_icmpge -> 127
    //   118: aload_2
    //   119: iload_0
    //   120: invokevirtual charAt : (I)C
    //   123: istore_1
    //   124: goto -> 82
    //   127: aload #5
    //   129: putstatic burp/Zmv9.a : [Ljava/lang/String;
    //   132: bipush #11
    //   134: anewarray java/lang/String
    //   137: putstatic burp/Zmv9.b : [Ljava/lang/String;
    //   140: goto -> 300
    //   143: dup_x2
    //   144: pop
    //   145: invokevirtual toCharArray : ()[C
    //   148: dup_x1
    //   149: arraylength
    //   150: dup_x2
    //   151: pop
    //   152: iconst_0
    //   153: istore #6
    //   155: dup2_x1
    //   156: pop2
    //   157: dup_x2
    //   158: iconst_1
    //   159: if_icmpgt -> 260
    //   162: dup2
    //   163: swap
    //   164: iload #6
    //   166: dup2_x1
    //   167: caload
    //   168: swap
    //   169: iload #6
    //   171: bipush #7
    //   173: irem
    //   174: tableswitch default -> 242, 0 -> 212, 1 -> 217, 2 -> 222, 3 -> 227, 4 -> 232, 5 -> 237
    //   212: bipush #94
    //   214: goto -> 244
    //   217: bipush #63
    //   219: goto -> 244
    //   222: bipush #84
    //   224: goto -> 244
    //   227: bipush #68
    //   229: goto -> 244
    //   232: bipush #113
    //   234: goto -> 244
    //   237: bipush #41
    //   239: goto -> 244
    //   242: bipush #66
    //   244: ixor
    //   245: ixor
    //   246: i2c
    //   247: castore
    //   248: iinc #6, 1
    //   251: dup
    //   252: ifne -> 260
    //   255: dup2
    //   256: dup_x1
    //   257: goto -> 166
    //   260: dup2_x1
    //   261: pop2
    //   262: dup_x2
    //   263: iload #6
    //   265: if_icmpgt -> 162
    //   268: pop
    //   269: new java/lang/String
    //   272: dup_x1
    //   273: swap
    //   274: invokespecial <init> : ([C)V
    //   277: invokevirtual intern : ()Ljava/lang/String;
    //   280: swap
    //   281: pop
    //   282: swap
    //   283: tableswitch default -> 40, 0 -> 99
    //   300: sipush #-31484
    //   303: sipush #5466
    //   306: invokestatic a : (II)Ljava/lang/String;
    //   309: putstatic burp/Zmv9.Zm : Ljava/lang/String;
    //   312: new java/math/BigInteger
    //   315: dup
    //   316: bipush #32
    //   318: newarray byte
    //   320: dup
    //   321: iconst_0
    //   322: bipush #13
    //   324: bastore
    //   325: dup
    //   326: iconst_1
    //   327: bipush #-58
    //   329: bastore
    //   330: dup
    //   331: iconst_2
    //   332: bipush #76
    //   334: bastore
    //   335: dup
    //   336: iconst_3
    //   337: bipush #10
    //   339: bastore
    //   340: dup
    //   341: iconst_4
    //   342: bipush #67
    //   344: bastore
    //   345: dup
    //   346: iconst_5
    //   347: bipush #-3
    //   349: bastore
    //   350: dup
    //   351: bipush #6
    //   353: bipush #50
    //   355: bastore
    //   356: dup
    //   357: bipush #7
    //   359: bipush #-51
    //   361: bastore
    //   362: dup
    //   363: bipush #8
    //   365: bipush #118
    //   367: bastore
    //   368: dup
    //   369: bipush #9
    //   371: bipush #-67
    //   373: bastore
    //   374: dup
    //   375: bipush #10
    //   377: bipush #-115
    //   379: bastore
    //   380: dup
    //   381: bipush #11
    //   383: bipush #43
    //   385: bastore
    //   386: dup
    //   387: bipush #12
    //   389: bipush #-22
    //   391: bastore
    //   392: dup
    //   393: bipush #13
    //   395: bipush #34
    //   397: bastore
    //   398: dup
    //   399: bipush #14
    //   401: bipush #126
    //   403: bastore
    //   404: dup
    //   405: bipush #15
    //   407: bipush #-39
    //   409: bastore
    //   410: dup
    //   411: bipush #16
    //   413: bipush #-15
    //   415: bastore
    //   416: dup
    //   417: bipush #17
    //   419: bipush #-85
    //   421: bastore
    //   422: dup
    //   423: bipush #18
    //   425: bipush #124
    //   427: bastore
    //   428: dup
    //   429: bipush #19
    //   431: bipush #14
    //   433: bastore
    //   434: dup
    //   435: bipush #20
    //   437: bipush #-66
    //   439: bastore
    //   440: dup
    //   441: bipush #21
    //   443: bipush #-83
    //   445: bastore
    //   446: dup
    //   447: bipush #22
    //   449: bipush #-57
    //   451: bastore
    //   452: dup
    //   453: bipush #23
    //   455: iconst_0
    //   456: bastore
    //   457: dup
    //   458: bipush #24
    //   460: bipush #-55
    //   462: bastore
    //   463: dup
    //   464: bipush #25
    //   466: bipush #-65
    //   468: bastore
    //   469: dup
    //   470: bipush #26
    //   472: bipush #36
    //   474: bastore
    //   475: dup
    //   476: bipush #27
    //   478: bipush #-7
    //   480: bastore
    //   481: dup
    //   482: bipush #28
    //   484: iconst_1
    //   485: bastore
    //   486: dup
    //   487: bipush #29
    //   489: bipush #16
    //   491: bastore
    //   492: dup
    //   493: bipush #30
    //   495: bipush #74
    //   497: bastore
    //   498: dup
    //   499: bipush #31
    //   501: bipush #-122
    //   503: bastore
    //   504: invokespecial <init> : ([B)V
    //   507: putstatic burp/Zmv9.Zw : Ljava/lang/Object;
    //   510: return
  }
  
  private static Throwable a(Throwable paramThrowable) {
    return paramThrowable;
  }
  
  private static String a(int paramInt1, int paramInt2) {
    int i = (paramInt1 ^ 0xFFFF8501) & 0xFFFF;
    if (b[i] == null) {
      char[] arrayOfChar = a[i].toCharArray();
      switch (arrayOfChar[0] & 0xFF) {
        case 0:
        
        case 1:
        
        case 2:
        
        case 3:
        
        case 4:
        
        case 5:
        
        case 6:
        
        case 7:
        
        case 8:
        
        case 9:
        
        case 10:
        
        case 11:
        
        case 12:
        
        case 13:
        
        case 14:
        
        case 15:
        
        case 16:
        
        case 17:
        
        case 18:
        
        case 19:
        
        case 20:
        
        case 21:
        
        case 22:
        
        case 23:
        
        case 24:
        
        case 25:
        
        case 26:
        
        case 27:
        
        case 28:
        
        case 29:
        
        case 30:
        
        case 31:
        
        case 32:
        
        case 33:
        
        case 34:
        
        case 35:
        
        case 36:
        
        case 37:
        
        case 38:
        
        case 39:
        
        case 40:
        
        case 41:
        
        case 42:
        
        case 43:
        
        case 44:
        
        case 45:
        
        case 46:
        
        case 47:
        
        case 48:
        
        case 49:
        
        case 50:
        
        case 51:
        
        case 52:
        
        case 53:
        
        case 54:
        
        case 55:
        
        case 56:
        
        case 57:
        
        case 58:
        
        case 59:
        
        case 60:
        
        case 61:
        
        case 62:
        
        case 63:
        
        case 64:
        
        case 65:
        
        case 66:
        
        case 67:
        
        case 68:
        
        case 69:
        
        case 70:
        
        case 71:
        
        case 72:
        
        case 73:
        
        case 74:
        
        case 75:
        
        case 76:
        
        case 77:
        
        case 78:
        
        case 79:
        
        case 80:
        
        case 81:
        
        case 82:
        
        case 83:
        
        case 84:
        
        case 85:
        
        case 86:
        
        case 87:
        
        case 88:
        
        case 89:
        
        case 90:
        
        case 91:
        
        case 92:
        
        case 93:
        
        case 94:
        
        case 95:
        
        case 96:
        
        case 97:
        
        case 98:
        
        case 99:
        
        case 100:
        
        case 101:
        
        case 102:
        
        case 103:
        
        case 104:
        
        case 105:
        
        case 106:
        
        case 107:
        
        case 108:
        
        case 109:
        
        case 110:
        
        case 111:
        
        case 112:
        
        case 113:
        
        case 114:
        
        case 115:
        
        case 116:
        
        case 117:
        
        case 118:
        
        case 119:
        
        case 120:
        
        case 121:
        
        case 122:
        
        case 123:
        
        case 124:
        
        case 125:
        
        case 126:
        
        case 127:
        
        case 128:
        
        case 129:
        
        case 130:
        
        case 131:
        
        case 132:
        
        case 133:
        
        case 134:
        
        case 135:
        
        case 136:
        
        case 137:
        
        case 138:
        
        case 139:
        
        case 140:
        
        case 141:
        
        case 142:
        
        case 143:
        
        case 144:
        
        case 145:
        
        case 146:
        
        case 147:
        
        case 148:
        
        case 149:
        
        case 150:
        
        case 151:
        
        case 152:
        
        case 153:
        
        case 154:
        
        case 155:
        
        case 156:
        
        case 157:
        
        case 158:
        
        case 159:
        
        case 160:
        
        case 161:
        
        case 162:
        
        case 163:
        
        case 164:
        
        case 165:
        
        case 166:
        
        case 167:
        
        case 168:
        
        case 169:
        
        case 170:
        
        case 171:
        
        case 172:
        
        case 173:
        
        case 174:
        
        case 175:
        
        case 176:
        
        case 177:
        
        case 178:
        
        case 179:
        
        case 180:
        
        case 181:
        
        case 182:
        
        case 183:
        
        case 184:
        
        case 185:
        
        case 186:
        
        case 187:
        
        case 188:
        
        case 189:
        
        case 190:
        
        case 191:
        
        case 192:
        
        case 193:
        
        case 194:
        
        case 195:
        
        case 196:
        
        case 197:
        
        case 198:
        
        case 199:
        
        case 200:
        
        case 201:
        
        case 202:
        
        case 203:
        
        case 204:
        
        case 205:
        
        case 206:
        
        case 207:
        
        case 208:
        
        case 209:
        
        case 210:
        
        case 211:
        
        case 212:
        
        case 213:
        
        case 214:
        
        case 215:
        
        case 216:
        
        case 217:
        
        case 218:
        
        case 219:
        
        case 220:
        
        case 221:
        
        case 222:
        
        case 223:
        
        case 224:
        
        case 225:
        
        case 226:
        
        case 227:
        
        case 228:
        
        case 229:
        
        case 230:
        
        case 231:
        
        case 232:
        
        case 233:
        
        case 234:
        
        case 235:
        
        case 236:
        
        case 237:
        
        case 238:
        
        case 239:
        
        case 240:
        
        case 241:
        
        case 242:
        
        case 243:
        
        case 244:
        
        case 245:
        
        case 246:
        
        case 247:
        
        case 248:
        
        case 249:
        
        case 250:
        
        case 251:
        
        case 252:
        
        case 253:
        
        case 254:
        
        default:
          break;
      } 
      char c = '';
      int j = (paramInt2 & 0xFF) - c;
      if (j < 0)
        j += 256; 
      int k = ((paramInt2 & 0xFFFF) >>> 8) - c;
      if (k < 0)
        k += 256; 
      for (byte b = 0; b < arrayOfChar.length; b++) {
        int m = b % 2;
        if (m == 0) {
          arrayOfChar[b] = (char)(arrayOfChar[b] ^ j);
          j = ((j >>> 3 | j << 5) ^ arrayOfChar[b]) & 0xFF;
        } else {
          arrayOfChar[b] = (char)(arrayOfChar[b] ^ k);
          k = ((k >>> 3 | k << 5) ^ arrayOfChar[b]) & 0xFF;
        } 
      } 
      b[i] = (new String(arrayOfChar)).intern();
    } 
    return b[i];
  }
}


/* Location:              C:\Program Files\BurpSuitePro\burpsuite_pro.jar!\burp\Zmv9.class
 * Java compiler version: 21 (65.0)
 * JD-Core Version:       1.1.3
 */