package burp;

import java.math.BigInteger;

class Zmz extends ClassLoader {
  static String Zp;
  
  static Object ZW;
  
  private static final String[] a;
  
  private static final String[] b;
  
  static boolean ZV(Object[] paramArrayOfObject, Object paramObject) throws Throwable {
    // Byte code:
    //   0: invokestatic ZK : ()Z
    //   3: istore_2
    //   4: getstatic burp/Zs5y.Zd : Ljava/lang/Object;
    //   7: checkcast java/math/BigInteger
    //   10: invokevirtual toByteArray : ()[B
    //   13: astore_3
    //   14: new java/lang/StringBuilder
    //   17: dup
    //   18: invokespecial <init> : ()V
    //   21: astore #5
    //   23: aload #5
    //   25: sipush #-24582
    //   28: sipush #23999
    //   31: invokestatic a : (II)Ljava/lang/String;
    //   34: invokevirtual append : (Ljava/lang/String;)Ljava/lang/StringBuilder;
    //   37: pop
    //   38: aload_3
    //   39: astore #6
    //   41: aload #6
    //   43: arraylength
    //   44: istore #7
    //   46: iconst_0
    //   47: istore #8
    //   49: iload #8
    //   51: iload #7
    //   53: if_icmpge -> 79
    //   56: aload #6
    //   58: iload #8
    //   60: baload
    //   61: istore #9
    //   63: aload #5
    //   65: iload #9
    //   67: i2c
    //   68: invokevirtual append : (C)Ljava/lang/StringBuilder;
    //   71: pop
    //   72: iinc #8, 1
    //   75: iload_2
    //   76: ifeq -> 49
    //   79: aload #5
    //   81: sipush #-24581
    //   84: sipush #-25587
    //   87: invokestatic a : (II)Ljava/lang/String;
    //   90: ldc ''
    //   92: invokestatic getProperty : (Ljava/lang/String;Ljava/lang/String;)Ljava/lang/String;
    //   95: invokevirtual toLowerCase : ()Ljava/lang/String;
    //   98: invokevirtual append : (Ljava/lang/String;)Ljava/lang/StringBuilder;
    //   101: pop
    //   102: aload #5
    //   104: sipush #-24583
    //   107: sipush #16140
    //   110: invokestatic a : (II)Ljava/lang/String;
    //   113: ldc ''
    //   115: invokestatic getProperty : (Ljava/lang/String;Ljava/lang/String;)Ljava/lang/String;
    //   118: invokevirtual toLowerCase : ()Ljava/lang/String;
    //   121: invokevirtual append : (Ljava/lang/String;)Ljava/lang/StringBuilder;
    //   124: pop
    //   125: aload #5
    //   127: invokevirtual toString : ()Ljava/lang/String;
    //   130: invokevirtual getBytes : ()[B
    //   133: astore #4
    //   135: aload #4
    //   137: astore_3
    //   138: aload_3
    //   139: arraylength
    //   140: bipush #8
    //   142: iadd
    //   143: bipush #6
    //   145: ishr
    //   146: iconst_1
    //   147: iadd
    //   148: bipush #16
    //   150: imul
    //   151: newarray int
    //   153: astore #5
    //   155: iconst_0
    //   156: istore #6
    //   158: iload #6
    //   160: aload_3
    //   161: arraylength
    //   162: if_icmpge -> 205
    //   165: aload_3
    //   166: iload #6
    //   168: baload
    //   169: sipush #255
    //   172: iand
    //   173: istore #7
    //   175: aload #5
    //   177: iload #6
    //   179: iconst_2
    //   180: ishr
    //   181: dup2
    //   182: iaload
    //   183: iload #7
    //   185: bipush #24
    //   187: iload #6
    //   189: iconst_4
    //   190: irem
    //   191: bipush #8
    //   193: imul
    //   194: isub
    //   195: ishl
    //   196: ior
    //   197: iastore
    //   198: iinc #6, 1
    //   201: iload_2
    //   202: ifeq -> 158
    //   205: aload #5
    //   207: iload #6
    //   209: iconst_2
    //   210: ishr
    //   211: dup2
    //   212: iaload
    //   213: sipush #128
    //   216: bipush #24
    //   218: iload #6
    //   220: iconst_4
    //   221: irem
    //   222: bipush #8
    //   224: imul
    //   225: isub
    //   226: ishl
    //   227: ior
    //   228: iastore
    //   229: aload #5
    //   231: aload #5
    //   233: arraylength
    //   234: iconst_1
    //   235: isub
    //   236: aload_3
    //   237: arraylength
    //   238: bipush #8
    //   240: imul
    //   241: iastore
    //   242: bipush #80
    //   244: newarray int
    //   246: astore #7
    //   248: ldc 1732584193
    //   250: istore #8
    //   252: ldc -271733879
    //   254: istore #9
    //   256: ldc -1732584194
    //   258: istore #10
    //   260: ldc 271733878
    //   262: istore #11
    //   264: ldc -1009589776
    //   266: istore #12
    //   268: iconst_0
    //   269: istore #6
    //   271: iload #6
    //   273: aload #5
    //   275: arraylength
    //   276: if_icmpge -> 598
    //   279: iload #8
    //   281: istore #13
    //   283: iload #9
    //   285: istore #14
    //   287: iload #10
    //   289: istore #15
    //   291: iload #11
    //   293: istore #16
    //   295: iload #12
    //   297: istore #17
    //   299: iconst_0
    //   300: istore #18
    //   302: iload #18
    //   304: bipush #80
    //   306: if_icmpge -> 556
    //   309: iload #18
    //   311: bipush #16
    //   313: if_icmpge -> 340
    //   316: aload #7
    //   318: iload #18
    //   320: aload #5
    //   322: iload #6
    //   324: iload #18
    //   326: iadd
    //   327: iaload
    //   328: iastore
    //   329: iload_2
    //   330: ifeq -> 395
    //   333: goto -> 340
    //   336: invokestatic a : (Ljava/lang/Throwable;)Ljava/lang/Throwable;
    //   339: athrow
    //   340: aload #7
    //   342: iload #18
    //   344: iconst_3
    //   345: isub
    //   346: iaload
    //   347: aload #7
    //   349: iload #18
    //   351: bipush #8
    //   353: isub
    //   354: iaload
    //   355: ixor
    //   356: aload #7
    //   358: iload #18
    //   360: bipush #14
    //   362: isub
    //   363: iaload
    //   364: ixor
    //   365: aload #7
    //   367: iload #18
    //   369: bipush #16
    //   371: isub
    //   372: iaload
    //   373: ixor
    //   374: istore #19
    //   376: iload #19
    //   378: iconst_1
    //   379: ishl
    //   380: iload #19
    //   382: bipush #31
    //   384: iushr
    //   385: ior
    //   386: istore #20
    //   388: aload #7
    //   390: iload #18
    //   392: iload #20
    //   394: iastore
    //   395: iload #8
    //   397: iconst_5
    //   398: ishl
    //   399: iload #8
    //   401: bipush #27
    //   403: iushr
    //   404: ior
    //   405: istore #19
    //   407: iload #19
    //   409: iload #12
    //   411: iadd
    //   412: aload #7
    //   414: iload #18
    //   416: iaload
    //   417: iadd
    //   418: iload #18
    //   420: bipush #20
    //   422: if_icmpge -> 448
    //   425: ldc 1518500249
    //   427: iload #9
    //   429: iload #10
    //   431: iand
    //   432: iload #9
    //   434: iconst_m1
    //   435: ixor
    //   436: iload #11
    //   438: iand
    //   439: ior
    //   440: iadd
    //   441: goto -> 518
    //   444: invokestatic a : (Ljava/lang/Throwable;)Ljava/lang/Throwable;
    //   447: athrow
    //   448: iload #18
    //   450: bipush #40
    //   452: if_icmpge -> 473
    //   455: ldc 1859775393
    //   457: iload #9
    //   459: iload #10
    //   461: ixor
    //   462: iload #11
    //   464: ixor
    //   465: iadd
    //   466: goto -> 518
    //   469: invokestatic a : (Ljava/lang/Throwable;)Ljava/lang/Throwable;
    //   472: athrow
    //   473: iload #18
    //   475: bipush #60
    //   477: if_icmpge -> 507
    //   480: ldc -1894007588
    //   482: iload #9
    //   484: iload #10
    //   486: iand
    //   487: iload #9
    //   489: iload #11
    //   491: iand
    //   492: ior
    //   493: iload #10
    //   495: iload #11
    //   497: iand
    //   498: ior
    //   499: iadd
    //   500: goto -> 518
    //   503: invokestatic a : (Ljava/lang/Throwable;)Ljava/lang/Throwable;
    //   506: athrow
    //   507: ldc -899497514
    //   509: iload #9
    //   511: iload #10
    //   513: ixor
    //   514: iload #11
    //   516: ixor
    //   517: iadd
    //   518: iadd
    //   519: istore #20
    //   521: iload #11
    //   523: istore #12
    //   525: iload #10
    //   527: istore #11
    //   529: iload #9
    //   531: bipush #30
    //   533: ishl
    //   534: iload #9
    //   536: iconst_2
    //   537: iushr
    //   538: ior
    //   539: istore #10
    //   541: iload #8
    //   543: istore #9
    //   545: iload #20
    //   547: istore #8
    //   549: iinc #18, 1
    //   552: iload_2
    //   553: ifeq -> 302
    //   556: iload #8
    //   558: iload #13
    //   560: iadd
    //   561: istore #8
    //   563: iload #9
    //   565: iload #14
    //   567: iadd
    //   568: istore #9
    //   570: iload #10
    //   572: iload #15
    //   574: iadd
    //   575: istore #10
    //   577: iload #11
    //   579: iload #16
    //   581: iadd
    //   582: istore #11
    //   584: iload #12
    //   586: iload #17
    //   588: iadd
    //   589: istore #12
    //   591: iinc #6, 16
    //   594: iload_2
    //   595: ifeq -> 271
    //   598: iconst_5
    //   599: newarray int
    //   601: dup
    //   602: iconst_0
    //   603: iload #8
    //   605: iastore
    //   606: dup
    //   607: iconst_1
    //   608: iload #9
    //   610: iastore
    //   611: dup
    //   612: iconst_2
    //   613: iload #10
    //   615: iastore
    //   616: dup
    //   617: iconst_3
    //   618: iload #11
    //   620: iastore
    //   621: dup
    //   622: iconst_4
    //   623: iload #12
    //   625: iastore
    //   626: astore #13
    //   628: bipush #20
    //   630: newarray byte
    //   632: astore #14
    //   634: iconst_0
    //   635: istore #15
    //   637: iload #15
    //   639: bipush #20
    //   641: if_icmpge -> 682
    //   644: aload #13
    //   646: iload #15
    //   648: iconst_4
    //   649: idiv
    //   650: iaload
    //   651: istore #16
    //   653: iconst_3
    //   654: iload #15
    //   656: iconst_4
    //   657: irem
    //   658: isub
    //   659: bipush #8
    //   661: imul
    //   662: istore #17
    //   664: aload #14
    //   666: iload #15
    //   668: iload #16
    //   670: iload #17
    //   672: iushr
    //   673: i2b
    //   674: bastore
    //   675: iinc #15, 1
    //   678: iload_2
    //   679: ifeq -> 637
    //   682: aload #14
    //   684: astore #4
    //   686: sipush #-24585
    //   689: sipush #5211
    //   692: invokestatic a : (II)Ljava/lang/String;
    //   695: iconst_1
    //   696: ldc burp/Zbzk
    //   698: invokevirtual getClassLoader : ()Ljava/lang/ClassLoader;
    //   701: invokestatic forName : (Ljava/lang/String;ZLjava/lang/ClassLoader;)Ljava/lang/Class;
    //   704: invokevirtual getDeclaredFields : ()[Ljava/lang/reflect/Field;
    //   707: astore_3
    //   708: aload_3
    //   709: arraylength
    //   710: istore #4
    //   712: iconst_0
    //   713: istore #5
    //   715: iload #5
    //   717: iload #4
    //   719: if_icmpge -> 856
    //   722: aload_3
    //   723: iload #5
    //   725: aaload
    //   726: astore #6
    //   728: aload #6
    //   730: invokevirtual getModifiers : ()I
    //   733: invokestatic isStatic : (I)Z
    //   736: ifne -> 746
    //   739: goto -> 849
    //   742: invokestatic a : (Ljava/lang/Throwable;)Ljava/lang/Throwable;
    //   745: athrow
    //   746: aload #6
    //   748: invokevirtual getType : ()Ljava/lang/Class;
    //   751: astore #7
    //   753: aload #7
    //   755: ifnull -> 836
    //   758: aload #7
    //   760: invokevirtual isPrimitive : ()Z
    //   763: ifne -> 836
    //   766: goto -> 773
    //   769: invokestatic a : (Ljava/lang/Throwable;)Ljava/lang/Throwable;
    //   772: athrow
    //   773: aload #7
    //   775: invokevirtual getPackage : ()Ljava/lang/Package;
    //   778: ifnull -> 836
    //   781: goto -> 788
    //   784: invokestatic a : (Ljava/lang/Throwable;)Ljava/lang/Throwable;
    //   787: athrow
    //   788: aload #7
    //   790: invokevirtual getPackage : ()Ljava/lang/Package;
    //   793: invokevirtual getName : ()Ljava/lang/String;
    //   796: ifnull -> 836
    //   799: goto -> 806
    //   802: invokestatic a : (Ljava/lang/Throwable;)Ljava/lang/Throwable;
    //   805: athrow
    //   806: aload #7
    //   808: invokevirtual getPackage : ()Ljava/lang/Package;
    //   811: invokevirtual getName : ()Ljava/lang/String;
    //   814: sipush #-24588
    //   817: sipush #-7579
    //   820: invokestatic a : (II)Ljava/lang/String;
    //   823: invokevirtual startsWith : (Ljava/lang/String;)Z
    //   826: ifne -> 836
    //   829: goto -> 836
    //   832: invokestatic a : (Ljava/lang/Throwable;)Ljava/lang/Throwable;
    //   835: athrow
    //   836: aload #6
    //   838: iconst_1
    //   839: invokevirtual setAccessible : (Z)V
    //   842: aload #6
    //   844: aconst_null
    //   845: invokevirtual get : (Ljava/lang/Object;)Ljava/lang/Object;
    //   848: pop
    //   849: iinc #5, 1
    //   852: iload_2
    //   853: ifeq -> 715
    //   856: sipush #-24577
    //   859: sipush #-31295
    //   862: invokestatic a : (II)Ljava/lang/String;
    //   865: invokestatic forName : (Ljava/lang/String;)Ljava/lang/Class;
    //   868: invokevirtual getDeclaredMethods : ()[Ljava/lang/reflect/Method;
    //   871: astore_3
    //   872: aload_3
    //   873: arraylength
    //   874: istore #4
    //   876: iconst_0
    //   877: istore #5
    //   879: iload #5
    //   881: iload #4
    //   883: if_icmpge -> 1015
    //   886: aload_3
    //   887: iload #5
    //   889: aaload
    //   890: astore #6
    //   892: aload #6
    //   894: invokevirtual getParameterTypes : ()[Ljava/lang/Class;
    //   897: pop
    //   898: aload #6
    //   900: invokevirtual getModifiers : ()I
    //   903: invokestatic isStatic : (I)Z
    //   906: ifeq -> 1001
    //   909: aload #6
    //   911: invokevirtual getParameterTypes : ()[Ljava/lang/Class;
    //   914: arraylength
    //   915: iconst_2
    //   916: if_icmpne -> 1001
    //   919: goto -> 926
    //   922: invokestatic a : (Ljava/lang/Throwable;)Ljava/lang/Throwable;
    //   925: athrow
    //   926: aload #6
    //   928: invokevirtual getReturnType : ()Ljava/lang/Class;
    //   931: getstatic java/lang/Void.TYPE : Ljava/lang/Class;
    //   934: invokevirtual equals : (Ljava/lang/Object;)Z
    //   937: ifeq -> 1001
    //   940: goto -> 947
    //   943: invokestatic a : (Ljava/lang/Throwable;)Ljava/lang/Throwable;
    //   946: athrow
    //   947: aload #6
    //   949: iconst_1
    //   950: invokevirtual setAccessible : (Z)V
    //   953: aload #6
    //   955: aconst_null
    //   956: iconst_2
    //   957: anewarray java/lang/Object
    //   960: dup
    //   961: iconst_0
    //   962: aload_0
    //   963: aastore
    //   964: dup
    //   965: iconst_1
    //   966: aload_1
    //   967: ifnonnull -> 985
    //   970: goto -> 977
    //   973: invokestatic a : (Ljava/lang/Throwable;)Ljava/lang/Throwable;
    //   976: athrow
    //   977: aload_1
    //   978: goto -> 992
    //   981: invokestatic a : (Ljava/lang/Throwable;)Ljava/lang/Throwable;
    //   984: athrow
    //   985: aload_1
    //   986: checkcast [B
    //   989: invokevirtual clone : ()Ljava/lang/Object;
    //   992: aastore
    //   993: invokevirtual invoke : (Ljava/lang/Object;[Ljava/lang/Object;)Ljava/lang/Object;
    //   996: pop
    //   997: iload_2
    //   998: ifeq -> 1015
    //   1001: iinc #5, 1
    //   1004: iload_2
    //   1005: ifeq -> 879
    //   1008: goto -> 1015
    //   1011: invokestatic a : (Ljava/lang/Throwable;)Ljava/lang/Throwable;
    //   1014: athrow
    //   1015: getstatic burp/Zenr.ZA : Ljava/lang/Object;
    //   1018: checkcast java/math/BigInteger
    //   1021: invokevirtual toByteArray : ()[B
    //   1024: astore_3
    //   1025: bipush #64
    //   1027: newarray byte
    //   1029: dup
    //   1030: iconst_0
    //   1031: bipush #-128
    //   1033: bastore
    //   1034: dup
    //   1035: iconst_1
    //   1036: iconst_0
    //   1037: bastore
    //   1038: dup
    //   1039: iconst_2
    //   1040: iconst_0
    //   1041: bastore
    //   1042: dup
    //   1043: iconst_3
    //   1044: iconst_0
    //   1045: bastore
    //   1046: dup
    //   1047: iconst_4
    //   1048: iconst_0
    //   1049: bastore
    //   1050: dup
    //   1051: iconst_5
    //   1052: iconst_0
    //   1053: bastore
    //   1054: dup
    //   1055: bipush #6
    //   1057: iconst_0
    //   1058: bastore
    //   1059: dup
    //   1060: bipush #7
    //   1062: iconst_0
    //   1063: bastore
    //   1064: dup
    //   1065: bipush #8
    //   1067: iconst_0
    //   1068: bastore
    //   1069: dup
    //   1070: bipush #9
    //   1072: iconst_0
    //   1073: bastore
    //   1074: dup
    //   1075: bipush #10
    //   1077: iconst_0
    //   1078: bastore
    //   1079: dup
    //   1080: bipush #11
    //   1082: iconst_0
    //   1083: bastore
    //   1084: dup
    //   1085: bipush #12
    //   1087: iconst_0
    //   1088: bastore
    //   1089: dup
    //   1090: bipush #13
    //   1092: iconst_0
    //   1093: bastore
    //   1094: dup
    //   1095: bipush #14
    //   1097: iconst_0
    //   1098: bastore
    //   1099: dup
    //   1100: bipush #15
    //   1102: iconst_0
    //   1103: bastore
    //   1104: dup
    //   1105: bipush #16
    //   1107: iconst_0
    //   1108: bastore
    //   1109: dup
    //   1110: bipush #17
    //   1112: iconst_0
    //   1113: bastore
    //   1114: dup
    //   1115: bipush #18
    //   1117: iconst_0
    //   1118: bastore
    //   1119: dup
    //   1120: bipush #19
    //   1122: iconst_0
    //   1123: bastore
    //   1124: dup
    //   1125: bipush #20
    //   1127: iconst_0
    //   1128: bastore
    //   1129: dup
    //   1130: bipush #21
    //   1132: iconst_0
    //   1133: bastore
    //   1134: dup
    //   1135: bipush #22
    //   1137: iconst_0
    //   1138: bastore
    //   1139: dup
    //   1140: bipush #23
    //   1142: iconst_0
    //   1143: bastore
    //   1144: dup
    //   1145: bipush #24
    //   1147: iconst_0
    //   1148: bastore
    //   1149: dup
    //   1150: bipush #25
    //   1152: iconst_0
    //   1153: bastore
    //   1154: dup
    //   1155: bipush #26
    //   1157: iconst_0
    //   1158: bastore
    //   1159: dup
    //   1160: bipush #27
    //   1162: iconst_0
    //   1163: bastore
    //   1164: dup
    //   1165: bipush #28
    //   1167: iconst_0
    //   1168: bastore
    //   1169: dup
    //   1170: bipush #29
    //   1172: iconst_0
    //   1173: bastore
    //   1174: dup
    //   1175: bipush #30
    //   1177: iconst_0
    //   1178: bastore
    //   1179: dup
    //   1180: bipush #31
    //   1182: iconst_0
    //   1183: bastore
    //   1184: dup
    //   1185: bipush #32
    //   1187: iconst_0
    //   1188: bastore
    //   1189: dup
    //   1190: bipush #33
    //   1192: iconst_0
    //   1193: bastore
    //   1194: dup
    //   1195: bipush #34
    //   1197: iconst_0
    //   1198: bastore
    //   1199: dup
    //   1200: bipush #35
    //   1202: iconst_0
    //   1203: bastore
    //   1204: dup
    //   1205: bipush #36
    //   1207: iconst_0
    //   1208: bastore
    //   1209: dup
    //   1210: bipush #37
    //   1212: iconst_0
    //   1213: bastore
    //   1214: dup
    //   1215: bipush #38
    //   1217: iconst_0
    //   1218: bastore
    //   1219: dup
    //   1220: bipush #39
    //   1222: iconst_0
    //   1223: bastore
    //   1224: dup
    //   1225: bipush #40
    //   1227: iconst_0
    //   1228: bastore
    //   1229: dup
    //   1230: bipush #41
    //   1232: iconst_0
    //   1233: bastore
    //   1234: dup
    //   1235: bipush #42
    //   1237: iconst_0
    //   1238: bastore
    //   1239: dup
    //   1240: bipush #43
    //   1242: iconst_0
    //   1243: bastore
    //   1244: dup
    //   1245: bipush #44
    //   1247: iconst_0
    //   1248: bastore
    //   1249: dup
    //   1250: bipush #45
    //   1252: iconst_0
    //   1253: bastore
    //   1254: dup
    //   1255: bipush #46
    //   1257: iconst_0
    //   1258: bastore
    //   1259: dup
    //   1260: bipush #47
    //   1262: iconst_0
    //   1263: bastore
    //   1264: dup
    //   1265: bipush #48
    //   1267: iconst_0
    //   1268: bastore
    //   1269: dup
    //   1270: bipush #49
    //   1272: iconst_0
    //   1273: bastore
    //   1274: dup
    //   1275: bipush #50
    //   1277: iconst_0
    //   1278: bastore
    //   1279: dup
    //   1280: bipush #51
    //   1282: iconst_0
    //   1283: bastore
    //   1284: dup
    //   1285: bipush #52
    //   1287: iconst_0
    //   1288: bastore
    //   1289: dup
    //   1290: bipush #53
    //   1292: iconst_0
    //   1293: bastore
    //   1294: dup
    //   1295: bipush #54
    //   1297: iconst_0
    //   1298: bastore
    //   1299: dup
    //   1300: bipush #55
    //   1302: iconst_0
    //   1303: bastore
    //   1304: dup
    //   1305: bipush #56
    //   1307: iconst_0
    //   1308: bastore
    //   1309: dup
    //   1310: bipush #57
    //   1312: iconst_0
    //   1313: bastore
    //   1314: dup
    //   1315: bipush #58
    //   1317: iconst_0
    //   1318: bastore
    //   1319: dup
    //   1320: bipush #59
    //   1322: iconst_0
    //   1323: bastore
    //   1324: dup
    //   1325: bipush #60
    //   1327: iconst_0
    //   1328: bastore
    //   1329: dup
    //   1330: bipush #61
    //   1332: iconst_0
    //   1333: bastore
    //   1334: dup
    //   1335: bipush #62
    //   1337: iconst_0
    //   1338: bastore
    //   1339: dup
    //   1340: bipush #63
    //   1342: iconst_0
    //   1343: bastore
    //   1344: astore #5
    //   1346: bipush #64
    //   1348: newarray int
    //   1350: dup
    //   1351: iconst_0
    //   1352: ldc 1116352408
    //   1354: iastore
    //   1355: dup
    //   1356: iconst_1
    //   1357: ldc 1899447441
    //   1359: iastore
    //   1360: dup
    //   1361: iconst_2
    //   1362: ldc -1245643825
    //   1364: iastore
    //   1365: dup
    //   1366: iconst_3
    //   1367: ldc -373957723
    //   1369: iastore
    //   1370: dup
    //   1371: iconst_4
    //   1372: ldc 961987163
    //   1374: iastore
    //   1375: dup
    //   1376: iconst_5
    //   1377: ldc 1508970993
    //   1379: iastore
    //   1380: dup
    //   1381: bipush #6
    //   1383: ldc -1841331548
    //   1385: iastore
    //   1386: dup
    //   1387: bipush #7
    //   1389: ldc -1424204075
    //   1391: iastore
    //   1392: dup
    //   1393: bipush #8
    //   1395: ldc -670586216
    //   1397: iastore
    //   1398: dup
    //   1399: bipush #9
    //   1401: ldc 310598401
    //   1403: iastore
    //   1404: dup
    //   1405: bipush #10
    //   1407: ldc 607225278
    //   1409: iastore
    //   1410: dup
    //   1411: bipush #11
    //   1413: ldc 1426881987
    //   1415: iastore
    //   1416: dup
    //   1417: bipush #12
    //   1419: ldc 1925078388
    //   1421: iastore
    //   1422: dup
    //   1423: bipush #13
    //   1425: ldc -2132889090
    //   1427: iastore
    //   1428: dup
    //   1429: bipush #14
    //   1431: ldc -1680079193
    //   1433: iastore
    //   1434: dup
    //   1435: bipush #15
    //   1437: ldc -1046744716
    //   1439: iastore
    //   1440: dup
    //   1441: bipush #16
    //   1443: ldc -459576895
    //   1445: iastore
    //   1446: dup
    //   1447: bipush #17
    //   1449: ldc -272742522
    //   1451: iastore
    //   1452: dup
    //   1453: bipush #18
    //   1455: ldc 264347078
    //   1457: iastore
    //   1458: dup
    //   1459: bipush #19
    //   1461: ldc 604807628
    //   1463: iastore
    //   1464: dup
    //   1465: bipush #20
    //   1467: ldc 770255983
    //   1469: iastore
    //   1470: dup
    //   1471: bipush #21
    //   1473: ldc 1249150122
    //   1475: iastore
    //   1476: dup
    //   1477: bipush #22
    //   1479: ldc 1555081692
    //   1481: iastore
    //   1482: dup
    //   1483: bipush #23
    //   1485: ldc 1996064986
    //   1487: iastore
    //   1488: dup
    //   1489: bipush #24
    //   1491: ldc -1740746414
    //   1493: iastore
    //   1494: dup
    //   1495: bipush #25
    //   1497: ldc -1473132947
    //   1499: iastore
    //   1500: dup
    //   1501: bipush #26
    //   1503: ldc -1341970488
    //   1505: iastore
    //   1506: dup
    //   1507: bipush #27
    //   1509: ldc -1084653625
    //   1511: iastore
    //   1512: dup
    //   1513: bipush #28
    //   1515: ldc -958395405
    //   1517: iastore
    //   1518: dup
    //   1519: bipush #29
    //   1521: ldc -710438585
    //   1523: iastore
    //   1524: dup
    //   1525: bipush #30
    //   1527: ldc 113926993
    //   1529: iastore
    //   1530: dup
    //   1531: bipush #31
    //   1533: ldc 338241895
    //   1535: iastore
    //   1536: dup
    //   1537: bipush #32
    //   1539: ldc 666307205
    //   1541: iastore
    //   1542: dup
    //   1543: bipush #33
    //   1545: ldc 773529912
    //   1547: iastore
    //   1548: dup
    //   1549: bipush #34
    //   1551: ldc 1294757372
    //   1553: iastore
    //   1554: dup
    //   1555: bipush #35
    //   1557: ldc 1396182291
    //   1559: iastore
    //   1560: dup
    //   1561: bipush #36
    //   1563: ldc 1695183700
    //   1565: iastore
    //   1566: dup
    //   1567: bipush #37
    //   1569: ldc 1986661051
    //   1571: iastore
    //   1572: dup
    //   1573: bipush #38
    //   1575: ldc -2117940946
    //   1577: iastore
    //   1578: dup
    //   1579: bipush #39
    //   1581: ldc -1838011259
    //   1583: iastore
    //   1584: dup
    //   1585: bipush #40
    //   1587: ldc -1564481375
    //   1589: iastore
    //   1590: dup
    //   1591: bipush #41
    //   1593: ldc -1474664885
    //   1595: iastore
    //   1596: dup
    //   1597: bipush #42
    //   1599: ldc -1035236496
    //   1601: iastore
    //   1602: dup
    //   1603: bipush #43
    //   1605: ldc -949202525
    //   1607: iastore
    //   1608: dup
    //   1609: bipush #44
    //   1611: ldc -778901479
    //   1613: iastore
    //   1614: dup
    //   1615: bipush #45
    //   1617: ldc -694614492
    //   1619: iastore
    //   1620: dup
    //   1621: bipush #46
    //   1623: ldc -200395387
    //   1625: iastore
    //   1626: dup
    //   1627: bipush #47
    //   1629: ldc 275423344
    //   1631: iastore
    //   1632: dup
    //   1633: bipush #48
    //   1635: ldc 430227734
    //   1637: iastore
    //   1638: dup
    //   1639: bipush #49
    //   1641: ldc 506948616
    //   1643: iastore
    //   1644: dup
    //   1645: bipush #50
    //   1647: ldc 659060556
    //   1649: iastore
    //   1650: dup
    //   1651: bipush #51
    //   1653: ldc 883997877
    //   1655: iastore
    //   1656: dup
    //   1657: bipush #52
    //   1659: ldc 958139571
    //   1661: iastore
    //   1662: dup
    //   1663: bipush #53
    //   1665: ldc 1322822218
    //   1667: iastore
    //   1668: dup
    //   1669: bipush #54
    //   1671: ldc 1537002063
    //   1673: iastore
    //   1674: dup
    //   1675: bipush #55
    //   1677: ldc 1747873779
    //   1679: iastore
    //   1680: dup
    //   1681: bipush #56
    //   1683: ldc 1955562222
    //   1685: iastore
    //   1686: dup
    //   1687: bipush #57
    //   1689: ldc 2024104815
    //   1691: iastore
    //   1692: dup
    //   1693: bipush #58
    //   1695: ldc -2067236844
    //   1697: iastore
    //   1698: dup
    //   1699: bipush #59
    //   1701: ldc -1933114872
    //   1703: iastore
    //   1704: dup
    //   1705: bipush #60
    //   1707: ldc -1866530822
    //   1709: iastore
    //   1710: dup
    //   1711: bipush #61
    //   1713: ldc -1538233109
    //   1715: iastore
    //   1716: dup
    //   1717: bipush #62
    //   1719: ldc -1090935817
    //   1721: iastore
    //   1722: dup
    //   1723: bipush #63
    //   1725: ldc -965641998
    //   1727: iastore
    //   1728: astore #6
    //   1730: iconst_2
    //   1731: newarray int
    //   1733: dup
    //   1734: iconst_0
    //   1735: iconst_0
    //   1736: iastore
    //   1737: dup
    //   1738: iconst_1
    //   1739: iconst_0
    //   1740: iastore
    //   1741: astore #7
    //   1743: bipush #8
    //   1745: newarray int
    //   1747: dup
    //   1748: iconst_0
    //   1749: ldc 1779033703
    //   1751: iastore
    //   1752: dup
    //   1753: iconst_1
    //   1754: ldc -1150833019
    //   1756: iastore
    //   1757: dup
    //   1758: iconst_2
    //   1759: ldc 1013904242
    //   1761: iastore
    //   1762: dup
    //   1763: iconst_3
    //   1764: ldc -1521486534
    //   1766: iastore
    //   1767: dup
    //   1768: iconst_4
    //   1769: ldc 1359893119
    //   1771: iastore
    //   1772: dup
    //   1773: iconst_5
    //   1774: ldc -1694144372
    //   1776: iastore
    //   1777: dup
    //   1778: bipush #6
    //   1780: ldc 528734635
    //   1782: iastore
    //   1783: dup
    //   1784: bipush #7
    //   1786: ldc 1541459225
    //   1788: iastore
    //   1789: astore #8
    //   1791: bipush #64
    //   1793: newarray byte
    //   1795: astore #9
    //   1797: bipush #64
    //   1799: newarray byte
    //   1801: astore #10
    //   1803: aload_3
    //   1804: arraylength
    //   1805: istore #11
    //   1807: aload #7
    //   1809: iconst_0
    //   1810: iaload
    //   1811: bipush #63
    //   1813: iand
    //   1814: istore #12
    //   1816: aload #7
    //   1818: iconst_0
    //   1819: dup2
    //   1820: iaload
    //   1821: iload #11
    //   1823: iadd
    //   1824: iastore
    //   1825: aload #7
    //   1827: iconst_0
    //   1828: dup2
    //   1829: iaload
    //   1830: iconst_m1
    //   1831: iand
    //   1832: iastore
    //   1833: aload #7
    //   1835: iconst_0
    //   1836: iaload
    //   1837: iload #11
    //   1839: if_icmpge -> 1857
    //   1842: aload #7
    //   1844: iconst_1
    //   1845: dup2
    //   1846: iaload
    //   1847: iconst_1
    //   1848: iadd
    //   1849: iastore
    //   1850: goto -> 1857
    //   1853: invokestatic a : (Ljava/lang/Throwable;)Ljava/lang/Throwable;
    //   1856: athrow
    //   1857: iconst_0
    //   1858: istore #13
    //   1860: iload #11
    //   1862: bipush #64
    //   1864: if_icmplt -> 2473
    //   1867: iconst_0
    //   1868: istore #14
    //   1870: iload #14
    //   1872: bipush #64
    //   1874: if_icmpge -> 1896
    //   1877: aload #10
    //   1879: iload #14
    //   1881: aload_3
    //   1882: iload #13
    //   1884: iload #14
    //   1886: iadd
    //   1887: baload
    //   1888: bastore
    //   1889: iinc #14, 1
    //   1892: iload_2
    //   1893: ifeq -> 1870
    //   1896: bipush #64
    //   1898: newarray int
    //   1900: astore #14
    //   1902: bipush #8
    //   1904: newarray int
    //   1906: astore #15
    //   1908: iconst_0
    //   1909: istore #16
    //   1911: iload #16
    //   1913: bipush #8
    //   1915: if_icmpge -> 1935
    //   1918: aload #15
    //   1920: iload #16
    //   1922: aload #8
    //   1924: iload #16
    //   1926: iaload
    //   1927: iastore
    //   1928: iinc #16, 1
    //   1931: iload_2
    //   1932: ifeq -> 1911
    //   1935: iconst_0
    //   1936: istore #16
    //   1938: iload #16
    //   1940: bipush #64
    //   1942: if_icmpge -> 2433
    //   1945: iload #16
    //   1947: bipush #16
    //   1949: if_icmpge -> 2030
    //   1952: aload #14
    //   1954: iload #16
    //   1956: aload #10
    //   1958: iconst_4
    //   1959: iload #16
    //   1961: imul
    //   1962: baload
    //   1963: sipush #255
    //   1966: iand
    //   1967: bipush #24
    //   1969: ishl
    //   1970: aload #10
    //   1972: iconst_4
    //   1973: iload #16
    //   1975: imul
    //   1976: iconst_1
    //   1977: iadd
    //   1978: baload
    //   1979: sipush #255
    //   1982: iand
    //   1983: bipush #16
    //   1985: ishl
    //   1986: ior
    //   1987: aload #10
    //   1989: iconst_4
    //   1990: iload #16
    //   1992: imul
    //   1993: iconst_2
    //   1994: iadd
    //   1995: baload
    //   1996: sipush #255
    //   1999: iand
    //   2000: bipush #8
    //   2002: ishl
    //   2003: ior
    //   2004: aload #10
    //   2006: iconst_4
    //   2007: iload #16
    //   2009: imul
    //   2010: iconst_3
    //   2011: iadd
    //   2012: baload
    //   2013: sipush #255
    //   2016: iand
    //   2017: ior
    //   2018: iastore
    //   2019: iload_2
    //   2020: ifeq -> 2173
    //   2023: goto -> 2030
    //   2026: invokestatic a : (Ljava/lang/Throwable;)Ljava/lang/Throwable;
    //   2029: athrow
    //   2030: aload #14
    //   2032: iload #16
    //   2034: aload #14
    //   2036: iload #16
    //   2038: iconst_2
    //   2039: isub
    //   2040: iaload
    //   2041: bipush #17
    //   2043: iushr
    //   2044: aload #14
    //   2046: iload #16
    //   2048: iconst_2
    //   2049: isub
    //   2050: iaload
    //   2051: bipush #15
    //   2053: ishl
    //   2054: ior
    //   2055: aload #14
    //   2057: iload #16
    //   2059: iconst_2
    //   2060: isub
    //   2061: iaload
    //   2062: bipush #19
    //   2064: iushr
    //   2065: aload #14
    //   2067: iload #16
    //   2069: iconst_2
    //   2070: isub
    //   2071: iaload
    //   2072: bipush #13
    //   2074: ishl
    //   2075: ior
    //   2076: ixor
    //   2077: aload #14
    //   2079: iload #16
    //   2081: iconst_2
    //   2082: isub
    //   2083: iaload
    //   2084: bipush #10
    //   2086: iushr
    //   2087: ixor
    //   2088: aload #14
    //   2090: iload #16
    //   2092: bipush #7
    //   2094: isub
    //   2095: iaload
    //   2096: iadd
    //   2097: aload #14
    //   2099: iload #16
    //   2101: bipush #15
    //   2103: isub
    //   2104: iaload
    //   2105: bipush #7
    //   2107: iushr
    //   2108: aload #14
    //   2110: iload #16
    //   2112: bipush #15
    //   2114: isub
    //   2115: iaload
    //   2116: bipush #25
    //   2118: ishl
    //   2119: ior
    //   2120: aload #14
    //   2122: iload #16
    //   2124: bipush #15
    //   2126: isub
    //   2127: iaload
    //   2128: bipush #18
    //   2130: iushr
    //   2131: aload #14
    //   2133: iload #16
    //   2135: bipush #15
    //   2137: isub
    //   2138: iaload
    //   2139: bipush #14
    //   2141: ishl
    //   2142: ior
    //   2143: ixor
    //   2144: aload #14
    //   2146: iload #16
    //   2148: bipush #15
    //   2150: isub
    //   2151: iaload
    //   2152: iconst_3
    //   2153: iushr
    //   2154: ixor
    //   2155: iadd
    //   2156: aload #14
    //   2158: iload #16
    //   2160: bipush #16
    //   2162: isub
    //   2163: iaload
    //   2164: iadd
    //   2165: iastore
    //   2166: goto -> 2173
    //   2169: invokestatic a : (Ljava/lang/Throwable;)Ljava/lang/Throwable;
    //   2172: athrow
    //   2173: aload #15
    //   2175: bipush #7
    //   2177: iaload
    //   2178: aload #15
    //   2180: iconst_4
    //   2181: iaload
    //   2182: bipush #6
    //   2184: iushr
    //   2185: aload #15
    //   2187: iconst_4
    //   2188: iaload
    //   2189: bipush #26
    //   2191: ishl
    //   2192: ior
    //   2193: aload #15
    //   2195: iconst_4
    //   2196: iaload
    //   2197: bipush #11
    //   2199: iushr
    //   2200: aload #15
    //   2202: iconst_4
    //   2203: iaload
    //   2204: bipush #21
    //   2206: ishl
    //   2207: ior
    //   2208: ixor
    //   2209: aload #15
    //   2211: iconst_4
    //   2212: iaload
    //   2213: bipush #25
    //   2215: iushr
    //   2216: aload #15
    //   2218: iconst_4
    //   2219: iaload
    //   2220: bipush #7
    //   2222: ishl
    //   2223: ior
    //   2224: ixor
    //   2225: iadd
    //   2226: aload #15
    //   2228: bipush #6
    //   2230: iaload
    //   2231: aload #15
    //   2233: iconst_4
    //   2234: iaload
    //   2235: aload #15
    //   2237: iconst_5
    //   2238: iaload
    //   2239: aload #15
    //   2241: bipush #6
    //   2243: iaload
    //   2244: ixor
    //   2245: iand
    //   2246: ixor
    //   2247: iadd
    //   2248: aload #6
    //   2250: iload #16
    //   2252: iaload
    //   2253: iadd
    //   2254: aload #14
    //   2256: iload #16
    //   2258: iaload
    //   2259: iadd
    //   2260: istore #17
    //   2262: aload #15
    //   2264: iconst_0
    //   2265: iaload
    //   2266: iconst_2
    //   2267: iushr
    //   2268: aload #15
    //   2270: iconst_0
    //   2271: iaload
    //   2272: bipush #30
    //   2274: ishl
    //   2275: ior
    //   2276: aload #15
    //   2278: iconst_0
    //   2279: iaload
    //   2280: bipush #13
    //   2282: iushr
    //   2283: aload #15
    //   2285: iconst_0
    //   2286: iaload
    //   2287: bipush #19
    //   2289: ishl
    //   2290: ior
    //   2291: ixor
    //   2292: aload #15
    //   2294: iconst_0
    //   2295: iaload
    //   2296: bipush #22
    //   2298: iushr
    //   2299: aload #15
    //   2301: iconst_0
    //   2302: iaload
    //   2303: bipush #10
    //   2305: ishl
    //   2306: ior
    //   2307: ixor
    //   2308: aload #15
    //   2310: iconst_0
    //   2311: iaload
    //   2312: aload #15
    //   2314: iconst_1
    //   2315: iaload
    //   2316: iand
    //   2317: aload #15
    //   2319: iconst_2
    //   2320: iaload
    //   2321: aload #15
    //   2323: iconst_0
    //   2324: iaload
    //   2325: aload #15
    //   2327: iconst_1
    //   2328: iaload
    //   2329: ior
    //   2330: iand
    //   2331: ior
    //   2332: iadd
    //   2333: istore #18
    //   2335: aload #15
    //   2337: iconst_3
    //   2338: dup2
    //   2339: iaload
    //   2340: iload #17
    //   2342: iadd
    //   2343: iastore
    //   2344: aload #15
    //   2346: bipush #7
    //   2348: iload #17
    //   2350: iload #18
    //   2352: iadd
    //   2353: iastore
    //   2354: aload #15
    //   2356: bipush #7
    //   2358: iaload
    //   2359: istore #17
    //   2361: aload #15
    //   2363: bipush #7
    //   2365: aload #15
    //   2367: bipush #6
    //   2369: iaload
    //   2370: iastore
    //   2371: aload #15
    //   2373: bipush #6
    //   2375: aload #15
    //   2377: iconst_5
    //   2378: iaload
    //   2379: iastore
    //   2380: aload #15
    //   2382: iconst_5
    //   2383: aload #15
    //   2385: iconst_4
    //   2386: iaload
    //   2387: iastore
    //   2388: aload #15
    //   2390: iconst_4
    //   2391: aload #15
    //   2393: iconst_3
    //   2394: iaload
    //   2395: iastore
    //   2396: aload #15
    //   2398: iconst_3
    //   2399: aload #15
    //   2401: iconst_2
    //   2402: iaload
    //   2403: iastore
    //   2404: aload #15
    //   2406: iconst_2
    //   2407: aload #15
    //   2409: iconst_1
    //   2410: iaload
    //   2411: iastore
    //   2412: aload #15
    //   2414: iconst_1
    //   2415: aload #15
    //   2417: iconst_0
    //   2418: iaload
    //   2419: iastore
    //   2420: aload #15
    //   2422: iconst_0
    //   2423: iload #17
    //   2425: iastore
    //   2426: iinc #16, 1
    //   2429: iload_2
    //   2430: ifeq -> 1938
    //   2433: iconst_0
    //   2434: istore #16
    //   2436: iload #16
    //   2438: bipush #8
    //   2440: if_icmpge -> 2463
    //   2443: aload #8
    //   2445: iload #16
    //   2447: dup2
    //   2448: iaload
    //   2449: aload #15
    //   2451: iload #16
    //   2453: iaload
    //   2454: iadd
    //   2455: iastore
    //   2456: iinc #16, 1
    //   2459: iload_2
    //   2460: ifeq -> 2436
    //   2463: iinc #13, 64
    //   2466: iinc #11, -64
    //   2469: iload_2
    //   2470: ifeq -> 1860
    //   2473: iload #11
    //   2475: ifle -> 2510
    //   2478: iconst_0
    //   2479: istore #14
    //   2481: iload #14
    //   2483: iload #11
    //   2485: if_icmpge -> 2510
    //   2488: aload #9
    //   2490: iload #12
    //   2492: iload #14
    //   2494: iadd
    //   2495: aload_3
    //   2496: iload #13
    //   2498: iload #14
    //   2500: iadd
    //   2501: baload
    //   2502: bastore
    //   2503: iinc #14, 1
    //   2506: iload_2
    //   2507: ifeq -> 2481
    //   2510: aload #7
    //   2512: iconst_0
    //   2513: iaload
    //   2514: bipush #29
    //   2516: iushr
    //   2517: aload #7
    //   2519: iconst_1
    //   2520: iaload
    //   2521: iconst_3
    //   2522: ishl
    //   2523: ior
    //   2524: istore #14
    //   2526: aload #7
    //   2528: iconst_0
    //   2529: iaload
    //   2530: iconst_3
    //   2531: ishl
    //   2532: istore #15
    //   2534: aload #7
    //   2536: iconst_0
    //   2537: iaload
    //   2538: bipush #63
    //   2540: iand
    //   2541: istore #16
    //   2543: iload #16
    //   2545: bipush #56
    //   2547: if_icmpge -> 2562
    //   2550: bipush #56
    //   2552: iload #16
    //   2554: isub
    //   2555: goto -> 2567
    //   2558: invokestatic a : (Ljava/lang/Throwable;)Ljava/lang/Throwable;
    //   2561: athrow
    //   2562: bipush #120
    //   2564: iload #16
    //   2566: isub
    //   2567: istore #17
    //   2569: aload #7
    //   2571: iconst_0
    //   2572: iaload
    //   2573: bipush #63
    //   2575: iand
    //   2576: istore #12
    //   2578: bipush #64
    //   2580: iload #12
    //   2582: isub
    //   2583: istore #18
    //   2585: aload #7
    //   2587: iconst_0
    //   2588: dup2
    //   2589: iaload
    //   2590: iload #17
    //   2592: iadd
    //   2593: iastore
    //   2594: aload #7
    //   2596: iconst_0
    //   2597: dup2
    //   2598: iaload
    //   2599: iconst_m1
    //   2600: iand
    //   2601: iastore
    //   2602: aload #7
    //   2604: iconst_0
    //   2605: iaload
    //   2606: iload #17
    //   2608: if_icmpge -> 2626
    //   2611: aload #7
    //   2613: iconst_1
    //   2614: dup2
    //   2615: iaload
    //   2616: iconst_1
    //   2617: iadd
    //   2618: iastore
    //   2619: goto -> 2626
    //   2622: invokestatic a : (Ljava/lang/Throwable;)Ljava/lang/Throwable;
    //   2625: athrow
    //   2626: iconst_0
    //   2627: istore #13
    //   2629: iload #12
    //   2631: ifle -> 3262
    //   2634: iload #17
    //   2636: iload #18
    //   2638: if_icmplt -> 3262
    //   2641: goto -> 2648
    //   2644: invokestatic a : (Ljava/lang/Throwable;)Ljava/lang/Throwable;
    //   2647: athrow
    //   2648: iconst_0
    //   2649: istore #19
    //   2651: iload #19
    //   2653: iload #18
    //   2655: if_icmpge -> 2678
    //   2658: aload #9
    //   2660: iload #12
    //   2662: iload #19
    //   2664: iadd
    //   2665: aload #5
    //   2667: iload #19
    //   2669: baload
    //   2670: bastore
    //   2671: iinc #19, 1
    //   2674: iload_2
    //   2675: ifeq -> 2651
    //   2678: bipush #64
    //   2680: newarray int
    //   2682: astore #19
    //   2684: bipush #8
    //   2686: newarray int
    //   2688: astore #20
    //   2690: iconst_0
    //   2691: istore #21
    //   2693: iload #21
    //   2695: bipush #8
    //   2697: if_icmpge -> 2717
    //   2700: aload #20
    //   2702: iload #21
    //   2704: aload #8
    //   2706: iload #21
    //   2708: iaload
    //   2709: iastore
    //   2710: iinc #21, 1
    //   2713: iload_2
    //   2714: ifeq -> 2693
    //   2717: iconst_0
    //   2718: istore #21
    //   2720: iload #21
    //   2722: bipush #64
    //   2724: if_icmpge -> 3215
    //   2727: iload #21
    //   2729: bipush #16
    //   2731: if_icmpge -> 2812
    //   2734: aload #19
    //   2736: iload #21
    //   2738: aload #9
    //   2740: iconst_4
    //   2741: iload #21
    //   2743: imul
    //   2744: baload
    //   2745: sipush #255
    //   2748: iand
    //   2749: bipush #24
    //   2751: ishl
    //   2752: aload #9
    //   2754: iconst_4
    //   2755: iload #21
    //   2757: imul
    //   2758: iconst_1
    //   2759: iadd
    //   2760: baload
    //   2761: sipush #255
    //   2764: iand
    //   2765: bipush #16
    //   2767: ishl
    //   2768: ior
    //   2769: aload #9
    //   2771: iconst_4
    //   2772: iload #21
    //   2774: imul
    //   2775: iconst_2
    //   2776: iadd
    //   2777: baload
    //   2778: sipush #255
    //   2781: iand
    //   2782: bipush #8
    //   2784: ishl
    //   2785: ior
    //   2786: aload #9
    //   2788: iconst_4
    //   2789: iload #21
    //   2791: imul
    //   2792: iconst_3
    //   2793: iadd
    //   2794: baload
    //   2795: sipush #255
    //   2798: iand
    //   2799: ior
    //   2800: iastore
    //   2801: iload_2
    //   2802: ifeq -> 2955
    //   2805: goto -> 2812
    //   2808: invokestatic a : (Ljava/lang/Throwable;)Ljava/lang/Throwable;
    //   2811: athrow
    //   2812: aload #19
    //   2814: iload #21
    //   2816: aload #19
    //   2818: iload #21
    //   2820: iconst_2
    //   2821: isub
    //   2822: iaload
    //   2823: bipush #17
    //   2825: iushr
    //   2826: aload #19
    //   2828: iload #21
    //   2830: iconst_2
    //   2831: isub
    //   2832: iaload
    //   2833: bipush #15
    //   2835: ishl
    //   2836: ior
    //   2837: aload #19
    //   2839: iload #21
    //   2841: iconst_2
    //   2842: isub
    //   2843: iaload
    //   2844: bipush #19
    //   2846: iushr
    //   2847: aload #19
    //   2849: iload #21
    //   2851: iconst_2
    //   2852: isub
    //   2853: iaload
    //   2854: bipush #13
    //   2856: ishl
    //   2857: ior
    //   2858: ixor
    //   2859: aload #19
    //   2861: iload #21
    //   2863: iconst_2
    //   2864: isub
    //   2865: iaload
    //   2866: bipush #10
    //   2868: iushr
    //   2869: ixor
    //   2870: aload #19
    //   2872: iload #21
    //   2874: bipush #7
    //   2876: isub
    //   2877: iaload
    //   2878: iadd
    //   2879: aload #19
    //   2881: iload #21
    //   2883: bipush #15
    //   2885: isub
    //   2886: iaload
    //   2887: bipush #7
    //   2889: iushr
    //   2890: aload #19
    //   2892: iload #21
    //   2894: bipush #15
    //   2896: isub
    //   2897: iaload
    //   2898: bipush #25
    //   2900: ishl
    //   2901: ior
    //   2902: aload #19
    //   2904: iload #21
    //   2906: bipush #15
    //   2908: isub
    //   2909: iaload
    //   2910: bipush #18
    //   2912: iushr
    //   2913: aload #19
    //   2915: iload #21
    //   2917: bipush #15
    //   2919: isub
    //   2920: iaload
    //   2921: bipush #14
    //   2923: ishl
    //   2924: ior
    //   2925: ixor
    //   2926: aload #19
    //   2928: iload #21
    //   2930: bipush #15
    //   2932: isub
    //   2933: iaload
    //   2934: iconst_3
    //   2935: iushr
    //   2936: ixor
    //   2937: iadd
    //   2938: aload #19
    //   2940: iload #21
    //   2942: bipush #16
    //   2944: isub
    //   2945: iaload
    //   2946: iadd
    //   2947: iastore
    //   2948: goto -> 2955
    //   2951: invokestatic a : (Ljava/lang/Throwable;)Ljava/lang/Throwable;
    //   2954: athrow
    //   2955: aload #20
    //   2957: bipush #7
    //   2959: iaload
    //   2960: aload #20
    //   2962: iconst_4
    //   2963: iaload
    //   2964: bipush #6
    //   2966: iushr
    //   2967: aload #20
    //   2969: iconst_4
    //   2970: iaload
    //   2971: bipush #26
    //   2973: ishl
    //   2974: ior
    //   2975: aload #20
    //   2977: iconst_4
    //   2978: iaload
    //   2979: bipush #11
    //   2981: iushr
    //   2982: aload #20
    //   2984: iconst_4
    //   2985: iaload
    //   2986: bipush #21
    //   2988: ishl
    //   2989: ior
    //   2990: ixor
    //   2991: aload #20
    //   2993: iconst_4
    //   2994: iaload
    //   2995: bipush #25
    //   2997: iushr
    //   2998: aload #20
    //   3000: iconst_4
    //   3001: iaload
    //   3002: bipush #7
    //   3004: ishl
    //   3005: ior
    //   3006: ixor
    //   3007: iadd
    //   3008: aload #20
    //   3010: bipush #6
    //   3012: iaload
    //   3013: aload #20
    //   3015: iconst_4
    //   3016: iaload
    //   3017: aload #20
    //   3019: iconst_5
    //   3020: iaload
    //   3021: aload #20
    //   3023: bipush #6
    //   3025: iaload
    //   3026: ixor
    //   3027: iand
    //   3028: ixor
    //   3029: iadd
    //   3030: aload #6
    //   3032: iload #21
    //   3034: iaload
    //   3035: iadd
    //   3036: aload #19
    //   3038: iload #21
    //   3040: iaload
    //   3041: iadd
    //   3042: istore #22
    //   3044: aload #20
    //   3046: iconst_0
    //   3047: iaload
    //   3048: iconst_2
    //   3049: iushr
    //   3050: aload #20
    //   3052: iconst_0
    //   3053: iaload
    //   3054: bipush #30
    //   3056: ishl
    //   3057: ior
    //   3058: aload #20
    //   3060: iconst_0
    //   3061: iaload
    //   3062: bipush #13
    //   3064: iushr
    //   3065: aload #20
    //   3067: iconst_0
    //   3068: iaload
    //   3069: bipush #19
    //   3071: ishl
    //   3072: ior
    //   3073: ixor
    //   3074: aload #20
    //   3076: iconst_0
    //   3077: iaload
    //   3078: bipush #22
    //   3080: iushr
    //   3081: aload #20
    //   3083: iconst_0
    //   3084: iaload
    //   3085: bipush #10
    //   3087: ishl
    //   3088: ior
    //   3089: ixor
    //   3090: aload #20
    //   3092: iconst_0
    //   3093: iaload
    //   3094: aload #20
    //   3096: iconst_1
    //   3097: iaload
    //   3098: iand
    //   3099: aload #20
    //   3101: iconst_2
    //   3102: iaload
    //   3103: aload #20
    //   3105: iconst_0
    //   3106: iaload
    //   3107: aload #20
    //   3109: iconst_1
    //   3110: iaload
    //   3111: ior
    //   3112: iand
    //   3113: ior
    //   3114: iadd
    //   3115: istore #23
    //   3117: aload #20
    //   3119: iconst_3
    //   3120: dup2
    //   3121: iaload
    //   3122: iload #22
    //   3124: iadd
    //   3125: iastore
    //   3126: aload #20
    //   3128: bipush #7
    //   3130: iload #22
    //   3132: iload #23
    //   3134: iadd
    //   3135: iastore
    //   3136: aload #20
    //   3138: bipush #7
    //   3140: iaload
    //   3141: istore #22
    //   3143: aload #20
    //   3145: bipush #7
    //   3147: aload #20
    //   3149: bipush #6
    //   3151: iaload
    //   3152: iastore
    //   3153: aload #20
    //   3155: bipush #6
    //   3157: aload #20
    //   3159: iconst_5
    //   3160: iaload
    //   3161: iastore
    //   3162: aload #20
    //   3164: iconst_5
    //   3165: aload #20
    //   3167: iconst_4
    //   3168: iaload
    //   3169: iastore
    //   3170: aload #20
    //   3172: iconst_4
    //   3173: aload #20
    //   3175: iconst_3
    //   3176: iaload
    //   3177: iastore
    //   3178: aload #20
    //   3180: iconst_3
    //   3181: aload #20
    //   3183: iconst_2
    //   3184: iaload
    //   3185: iastore
    //   3186: aload #20
    //   3188: iconst_2
    //   3189: aload #20
    //   3191: iconst_1
    //   3192: iaload
    //   3193: iastore
    //   3194: aload #20
    //   3196: iconst_1
    //   3197: aload #20
    //   3199: iconst_0
    //   3200: iaload
    //   3201: iastore
    //   3202: aload #20
    //   3204: iconst_0
    //   3205: iload #22
    //   3207: iastore
    //   3208: iinc #21, 1
    //   3211: iload_2
    //   3212: ifeq -> 2720
    //   3215: iconst_0
    //   3216: istore #21
    //   3218: iload #21
    //   3220: bipush #8
    //   3222: if_icmpge -> 3245
    //   3225: aload #8
    //   3227: iload #21
    //   3229: dup2
    //   3230: iaload
    //   3231: aload #20
    //   3233: iload #21
    //   3235: iaload
    //   3236: iadd
    //   3237: iastore
    //   3238: iinc #21, 1
    //   3241: iload_2
    //   3242: ifeq -> 3218
    //   3245: iload #13
    //   3247: iload #18
    //   3249: iadd
    //   3250: istore #13
    //   3252: iload #17
    //   3254: iload #18
    //   3256: isub
    //   3257: istore #17
    //   3259: iconst_0
    //   3260: istore #12
    //   3262: iload #17
    //   3264: bipush #64
    //   3266: if_icmplt -> 3876
    //   3269: iconst_0
    //   3270: istore #19
    //   3272: iload #19
    //   3274: bipush #64
    //   3276: if_icmpge -> 3299
    //   3279: aload #10
    //   3281: iload #19
    //   3283: aload #5
    //   3285: iload #13
    //   3287: iload #19
    //   3289: iadd
    //   3290: baload
    //   3291: bastore
    //   3292: iinc #19, 1
    //   3295: iload_2
    //   3296: ifeq -> 3272
    //   3299: bipush #64
    //   3301: newarray int
    //   3303: astore #19
    //   3305: bipush #8
    //   3307: newarray int
    //   3309: astore #20
    //   3311: iconst_0
    //   3312: istore #21
    //   3314: iload #21
    //   3316: bipush #8
    //   3318: if_icmpge -> 3338
    //   3321: aload #20
    //   3323: iload #21
    //   3325: aload #8
    //   3327: iload #21
    //   3329: iaload
    //   3330: iastore
    //   3331: iinc #21, 1
    //   3334: iload_2
    //   3335: ifeq -> 3314
    //   3338: iconst_0
    //   3339: istore #21
    //   3341: iload #21
    //   3343: bipush #64
    //   3345: if_icmpge -> 3836
    //   3348: iload #21
    //   3350: bipush #16
    //   3352: if_icmpge -> 3433
    //   3355: aload #19
    //   3357: iload #21
    //   3359: aload #10
    //   3361: iconst_4
    //   3362: iload #21
    //   3364: imul
    //   3365: baload
    //   3366: sipush #255
    //   3369: iand
    //   3370: bipush #24
    //   3372: ishl
    //   3373: aload #10
    //   3375: iconst_4
    //   3376: iload #21
    //   3378: imul
    //   3379: iconst_1
    //   3380: iadd
    //   3381: baload
    //   3382: sipush #255
    //   3385: iand
    //   3386: bipush #16
    //   3388: ishl
    //   3389: ior
    //   3390: aload #10
    //   3392: iconst_4
    //   3393: iload #21
    //   3395: imul
    //   3396: iconst_2
    //   3397: iadd
    //   3398: baload
    //   3399: sipush #255
    //   3402: iand
    //   3403: bipush #8
    //   3405: ishl
    //   3406: ior
    //   3407: aload #10
    //   3409: iconst_4
    //   3410: iload #21
    //   3412: imul
    //   3413: iconst_3
    //   3414: iadd
    //   3415: baload
    //   3416: sipush #255
    //   3419: iand
    //   3420: ior
    //   3421: iastore
    //   3422: iload_2
    //   3423: ifeq -> 3576
    //   3426: goto -> 3433
    //   3429: invokestatic a : (Ljava/lang/Throwable;)Ljava/lang/Throwable;
    //   3432: athrow
    //   3433: aload #19
    //   3435: iload #21
    //   3437: aload #19
    //   3439: iload #21
    //   3441: iconst_2
    //   3442: isub
    //   3443: iaload
    //   3444: bipush #17
    //   3446: iushr
    //   3447: aload #19
    //   3449: iload #21
    //   3451: iconst_2
    //   3452: isub
    //   3453: iaload
    //   3454: bipush #15
    //   3456: ishl
    //   3457: ior
    //   3458: aload #19
    //   3460: iload #21
    //   3462: iconst_2
    //   3463: isub
    //   3464: iaload
    //   3465: bipush #19
    //   3467: iushr
    //   3468: aload #19
    //   3470: iload #21
    //   3472: iconst_2
    //   3473: isub
    //   3474: iaload
    //   3475: bipush #13
    //   3477: ishl
    //   3478: ior
    //   3479: ixor
    //   3480: aload #19
    //   3482: iload #21
    //   3484: iconst_2
    //   3485: isub
    //   3486: iaload
    //   3487: bipush #10
    //   3489: iushr
    //   3490: ixor
    //   3491: aload #19
    //   3493: iload #21
    //   3495: bipush #7
    //   3497: isub
    //   3498: iaload
    //   3499: iadd
    //   3500: aload #19
    //   3502: iload #21
    //   3504: bipush #15
    //   3506: isub
    //   3507: iaload
    //   3508: bipush #7
    //   3510: iushr
    //   3511: aload #19
    //   3513: iload #21
    //   3515: bipush #15
    //   3517: isub
    //   3518: iaload
    //   3519: bipush #25
    //   3521: ishl
    //   3522: ior
    //   3523: aload #19
    //   3525: iload #21
    //   3527: bipush #15
    //   3529: isub
    //   3530: iaload
    //   3531: bipush #18
    //   3533: iushr
    //   3534: aload #19
    //   3536: iload #21
    //   3538: bipush #15
    //   3540: isub
    //   3541: iaload
    //   3542: bipush #14
    //   3544: ishl
    //   3545: ior
    //   3546: ixor
    //   3547: aload #19
    //   3549: iload #21
    //   3551: bipush #15
    //   3553: isub
    //   3554: iaload
    //   3555: iconst_3
    //   3556: iushr
    //   3557: ixor
    //   3558: iadd
    //   3559: aload #19
    //   3561: iload #21
    //   3563: bipush #16
    //   3565: isub
    //   3566: iaload
    //   3567: iadd
    //   3568: iastore
    //   3569: goto -> 3576
    //   3572: invokestatic a : (Ljava/lang/Throwable;)Ljava/lang/Throwable;
    //   3575: athrow
    //   3576: aload #20
    //   3578: bipush #7
    //   3580: iaload
    //   3581: aload #20
    //   3583: iconst_4
    //   3584: iaload
    //   3585: bipush #6
    //   3587: iushr
    //   3588: aload #20
    //   3590: iconst_4
    //   3591: iaload
    //   3592: bipush #26
    //   3594: ishl
    //   3595: ior
    //   3596: aload #20
    //   3598: iconst_4
    //   3599: iaload
    //   3600: bipush #11
    //   3602: iushr
    //   3603: aload #20
    //   3605: iconst_4
    //   3606: iaload
    //   3607: bipush #21
    //   3609: ishl
    //   3610: ior
    //   3611: ixor
    //   3612: aload #20
    //   3614: iconst_4
    //   3615: iaload
    //   3616: bipush #25
    //   3618: iushr
    //   3619: aload #20
    //   3621: iconst_4
    //   3622: iaload
    //   3623: bipush #7
    //   3625: ishl
    //   3626: ior
    //   3627: ixor
    //   3628: iadd
    //   3629: aload #20
    //   3631: bipush #6
    //   3633: iaload
    //   3634: aload #20
    //   3636: iconst_4
    //   3637: iaload
    //   3638: aload #20
    //   3640: iconst_5
    //   3641: iaload
    //   3642: aload #20
    //   3644: bipush #6
    //   3646: iaload
    //   3647: ixor
    //   3648: iand
    //   3649: ixor
    //   3650: iadd
    //   3651: aload #6
    //   3653: iload #21
    //   3655: iaload
    //   3656: iadd
    //   3657: aload #19
    //   3659: iload #21
    //   3661: iaload
    //   3662: iadd
    //   3663: istore #22
    //   3665: aload #20
    //   3667: iconst_0
    //   3668: iaload
    //   3669: iconst_2
    //   3670: iushr
    //   3671: aload #20
    //   3673: iconst_0
    //   3674: iaload
    //   3675: bipush #30
    //   3677: ishl
    //   3678: ior
    //   3679: aload #20
    //   3681: iconst_0
    //   3682: iaload
    //   3683: bipush #13
    //   3685: iushr
    //   3686: aload #20
    //   3688: iconst_0
    //   3689: iaload
    //   3690: bipush #19
    //   3692: ishl
    //   3693: ior
    //   3694: ixor
    //   3695: aload #20
    //   3697: iconst_0
    //   3698: iaload
    //   3699: bipush #22
    //   3701: iushr
    //   3702: aload #20
    //   3704: iconst_0
    //   3705: iaload
    //   3706: bipush #10
    //   3708: ishl
    //   3709: ior
    //   3710: ixor
    //   3711: aload #20
    //   3713: iconst_0
    //   3714: iaload
    //   3715: aload #20
    //   3717: iconst_1
    //   3718: iaload
    //   3719: iand
    //   3720: aload #20
    //   3722: iconst_2
    //   3723: iaload
    //   3724: aload #20
    //   3726: iconst_0
    //   3727: iaload
    //   3728: aload #20
    //   3730: iconst_1
    //   3731: iaload
    //   3732: ior
    //   3733: iand
    //   3734: ior
    //   3735: iadd
    //   3736: istore #23
    //   3738: aload #20
    //   3740: iconst_3
    //   3741: dup2
    //   3742: iaload
    //   3743: iload #22
    //   3745: iadd
    //   3746: iastore
    //   3747: aload #20
    //   3749: bipush #7
    //   3751: iload #22
    //   3753: iload #23
    //   3755: iadd
    //   3756: iastore
    //   3757: aload #20
    //   3759: bipush #7
    //   3761: iaload
    //   3762: istore #22
    //   3764: aload #20
    //   3766: bipush #7
    //   3768: aload #20
    //   3770: bipush #6
    //   3772: iaload
    //   3773: iastore
    //   3774: aload #20
    //   3776: bipush #6
    //   3778: aload #20
    //   3780: iconst_5
    //   3781: iaload
    //   3782: iastore
    //   3783: aload #20
    //   3785: iconst_5
    //   3786: aload #20
    //   3788: iconst_4
    //   3789: iaload
    //   3790: iastore
    //   3791: aload #20
    //   3793: iconst_4
    //   3794: aload #20
    //   3796: iconst_3
    //   3797: iaload
    //   3798: iastore
    //   3799: aload #20
    //   3801: iconst_3
    //   3802: aload #20
    //   3804: iconst_2
    //   3805: iaload
    //   3806: iastore
    //   3807: aload #20
    //   3809: iconst_2
    //   3810: aload #20
    //   3812: iconst_1
    //   3813: iaload
    //   3814: iastore
    //   3815: aload #20
    //   3817: iconst_1
    //   3818: aload #20
    //   3820: iconst_0
    //   3821: iaload
    //   3822: iastore
    //   3823: aload #20
    //   3825: iconst_0
    //   3826: iload #22
    //   3828: iastore
    //   3829: iinc #21, 1
    //   3832: iload_2
    //   3833: ifeq -> 3341
    //   3836: iconst_0
    //   3837: istore #21
    //   3839: iload #21
    //   3841: bipush #8
    //   3843: if_icmpge -> 3866
    //   3846: aload #8
    //   3848: iload #21
    //   3850: dup2
    //   3851: iaload
    //   3852: aload #20
    //   3854: iload #21
    //   3856: iaload
    //   3857: iadd
    //   3858: iastore
    //   3859: iinc #21, 1
    //   3862: iload_2
    //   3863: ifeq -> 3839
    //   3866: iinc #13, 64
    //   3869: iinc #17, -64
    //   3872: iload_2
    //   3873: ifeq -> 3262
    //   3876: iload #17
    //   3878: ifle -> 3914
    //   3881: iconst_0
    //   3882: istore #19
    //   3884: iload #19
    //   3886: iload #17
    //   3888: if_icmpge -> 3914
    //   3891: aload #9
    //   3893: iload #12
    //   3895: iload #19
    //   3897: iadd
    //   3898: aload #5
    //   3900: iload #13
    //   3902: iload #19
    //   3904: iadd
    //   3905: baload
    //   3906: bastore
    //   3907: iinc #19, 1
    //   3910: iload_2
    //   3911: ifeq -> 3884
    //   3914: bipush #8
    //   3916: newarray byte
    //   3918: astore #19
    //   3920: aload #19
    //   3922: iconst_0
    //   3923: iload #14
    //   3925: bipush #24
    //   3927: iushr
    //   3928: i2b
    //   3929: bastore
    //   3930: aload #19
    //   3932: iconst_1
    //   3933: iload #14
    //   3935: bipush #16
    //   3937: iushr
    //   3938: i2b
    //   3939: bastore
    //   3940: aload #19
    //   3942: iconst_2
    //   3943: iload #14
    //   3945: bipush #8
    //   3947: iushr
    //   3948: i2b
    //   3949: bastore
    //   3950: aload #19
    //   3952: iconst_3
    //   3953: iload #14
    //   3955: i2b
    //   3956: bastore
    //   3957: aload #19
    //   3959: iconst_4
    //   3960: iload #15
    //   3962: bipush #24
    //   3964: iushr
    //   3965: i2b
    //   3966: bastore
    //   3967: aload #19
    //   3969: iconst_5
    //   3970: iload #15
    //   3972: bipush #16
    //   3974: iushr
    //   3975: i2b
    //   3976: bastore
    //   3977: aload #19
    //   3979: bipush #6
    //   3981: iload #15
    //   3983: bipush #8
    //   3985: iushr
    //   3986: i2b
    //   3987: bastore
    //   3988: aload #19
    //   3990: bipush #7
    //   3992: iload #15
    //   3994: i2b
    //   3995: bastore
    //   3996: bipush #8
    //   3998: istore #11
    //   4000: aload #7
    //   4002: iconst_0
    //   4003: iaload
    //   4004: bipush #63
    //   4006: iand
    //   4007: istore #12
    //   4009: bipush #64
    //   4011: iload #12
    //   4013: isub
    //   4014: istore #18
    //   4016: aload #7
    //   4018: iconst_0
    //   4019: dup2
    //   4020: iaload
    //   4021: iload #11
    //   4023: iadd
    //   4024: iastore
    //   4025: aload #7
    //   4027: iconst_0
    //   4028: dup2
    //   4029: iaload
    //   4030: iconst_m1
    //   4031: iand
    //   4032: iastore
    //   4033: aload #7
    //   4035: iconst_0
    //   4036: iaload
    //   4037: iload #11
    //   4039: if_icmpge -> 4057
    //   4042: aload #7
    //   4044: iconst_1
    //   4045: dup2
    //   4046: iaload
    //   4047: iconst_1
    //   4048: iadd
    //   4049: iastore
    //   4050: goto -> 4057
    //   4053: invokestatic a : (Ljava/lang/Throwable;)Ljava/lang/Throwable;
    //   4056: athrow
    //   4057: iload #12
    //   4059: ifle -> 4673
    //   4062: iload #11
    //   4064: iload #18
    //   4066: if_icmplt -> 4673
    //   4069: goto -> 4076
    //   4072: invokestatic a : (Ljava/lang/Throwable;)Ljava/lang/Throwable;
    //   4075: athrow
    //   4076: iconst_0
    //   4077: istore #20
    //   4079: iload #20
    //   4081: iload #18
    //   4083: if_icmpge -> 4106
    //   4086: aload #9
    //   4088: iload #12
    //   4090: iload #20
    //   4092: iadd
    //   4093: aload #19
    //   4095: iload #20
    //   4097: baload
    //   4098: bastore
    //   4099: iinc #20, 1
    //   4102: iload_2
    //   4103: ifeq -> 4079
    //   4106: bipush #64
    //   4108: newarray int
    //   4110: astore #20
    //   4112: bipush #8
    //   4114: newarray int
    //   4116: astore #21
    //   4118: iconst_0
    //   4119: istore #22
    //   4121: iload #22
    //   4123: bipush #8
    //   4125: if_icmpge -> 4145
    //   4128: aload #21
    //   4130: iload #22
    //   4132: aload #8
    //   4134: iload #22
    //   4136: iaload
    //   4137: iastore
    //   4138: iinc #22, 1
    //   4141: iload_2
    //   4142: ifeq -> 4121
    //   4145: iconst_0
    //   4146: istore #22
    //   4148: iload #22
    //   4150: bipush #64
    //   4152: if_icmpge -> 4643
    //   4155: iload #22
    //   4157: bipush #16
    //   4159: if_icmpge -> 4240
    //   4162: aload #20
    //   4164: iload #22
    //   4166: aload #9
    //   4168: iconst_4
    //   4169: iload #22
    //   4171: imul
    //   4172: baload
    //   4173: sipush #255
    //   4176: iand
    //   4177: bipush #24
    //   4179: ishl
    //   4180: aload #9
    //   4182: iconst_4
    //   4183: iload #22
    //   4185: imul
    //   4186: iconst_1
    //   4187: iadd
    //   4188: baload
    //   4189: sipush #255
    //   4192: iand
    //   4193: bipush #16
    //   4195: ishl
    //   4196: ior
    //   4197: aload #9
    //   4199: iconst_4
    //   4200: iload #22
    //   4202: imul
    //   4203: iconst_2
    //   4204: iadd
    //   4205: baload
    //   4206: sipush #255
    //   4209: iand
    //   4210: bipush #8
    //   4212: ishl
    //   4213: ior
    //   4214: aload #9
    //   4216: iconst_4
    //   4217: iload #22
    //   4219: imul
    //   4220: iconst_3
    //   4221: iadd
    //   4222: baload
    //   4223: sipush #255
    //   4226: iand
    //   4227: ior
    //   4228: iastore
    //   4229: iload_2
    //   4230: ifeq -> 4383
    //   4233: goto -> 4240
    //   4236: invokestatic a : (Ljava/lang/Throwable;)Ljava/lang/Throwable;
    //   4239: athrow
    //   4240: aload #20
    //   4242: iload #22
    //   4244: aload #20
    //   4246: iload #22
    //   4248: iconst_2
    //   4249: isub
    //   4250: iaload
    //   4251: bipush #17
    //   4253: iushr
    //   4254: aload #20
    //   4256: iload #22
    //   4258: iconst_2
    //   4259: isub
    //   4260: iaload
    //   4261: bipush #15
    //   4263: ishl
    //   4264: ior
    //   4265: aload #20
    //   4267: iload #22
    //   4269: iconst_2
    //   4270: isub
    //   4271: iaload
    //   4272: bipush #19
    //   4274: iushr
    //   4275: aload #20
    //   4277: iload #22
    //   4279: iconst_2
    //   4280: isub
    //   4281: iaload
    //   4282: bipush #13
    //   4284: ishl
    //   4285: ior
    //   4286: ixor
    //   4287: aload #20
    //   4289: iload #22
    //   4291: iconst_2
    //   4292: isub
    //   4293: iaload
    //   4294: bipush #10
    //   4296: iushr
    //   4297: ixor
    //   4298: aload #20
    //   4300: iload #22
    //   4302: bipush #7
    //   4304: isub
    //   4305: iaload
    //   4306: iadd
    //   4307: aload #20
    //   4309: iload #22
    //   4311: bipush #15
    //   4313: isub
    //   4314: iaload
    //   4315: bipush #7
    //   4317: iushr
    //   4318: aload #20
    //   4320: iload #22
    //   4322: bipush #15
    //   4324: isub
    //   4325: iaload
    //   4326: bipush #25
    //   4328: ishl
    //   4329: ior
    //   4330: aload #20
    //   4332: iload #22
    //   4334: bipush #15
    //   4336: isub
    //   4337: iaload
    //   4338: bipush #18
    //   4340: iushr
    //   4341: aload #20
    //   4343: iload #22
    //   4345: bipush #15
    //   4347: isub
    //   4348: iaload
    //   4349: bipush #14
    //   4351: ishl
    //   4352: ior
    //   4353: ixor
    //   4354: aload #20
    //   4356: iload #22
    //   4358: bipush #15
    //   4360: isub
    //   4361: iaload
    //   4362: iconst_3
    //   4363: iushr
    //   4364: ixor
    //   4365: iadd
    //   4366: aload #20
    //   4368: iload #22
    //   4370: bipush #16
    //   4372: isub
    //   4373: iaload
    //   4374: iadd
    //   4375: iastore
    //   4376: goto -> 4383
    //   4379: invokestatic a : (Ljava/lang/Throwable;)Ljava/lang/Throwable;
    //   4382: athrow
    //   4383: aload #21
    //   4385: bipush #7
    //   4387: iaload
    //   4388: aload #21
    //   4390: iconst_4
    //   4391: iaload
    //   4392: bipush #6
    //   4394: iushr
    //   4395: aload #21
    //   4397: iconst_4
    //   4398: iaload
    //   4399: bipush #26
    //   4401: ishl
    //   4402: ior
    //   4403: aload #21
    //   4405: iconst_4
    //   4406: iaload
    //   4407: bipush #11
    //   4409: iushr
    //   4410: aload #21
    //   4412: iconst_4
    //   4413: iaload
    //   4414: bipush #21
    //   4416: ishl
    //   4417: ior
    //   4418: ixor
    //   4419: aload #21
    //   4421: iconst_4
    //   4422: iaload
    //   4423: bipush #25
    //   4425: iushr
    //   4426: aload #21
    //   4428: iconst_4
    //   4429: iaload
    //   4430: bipush #7
    //   4432: ishl
    //   4433: ior
    //   4434: ixor
    //   4435: iadd
    //   4436: aload #21
    //   4438: bipush #6
    //   4440: iaload
    //   4441: aload #21
    //   4443: iconst_4
    //   4444: iaload
    //   4445: aload #21
    //   4447: iconst_5
    //   4448: iaload
    //   4449: aload #21
    //   4451: bipush #6
    //   4453: iaload
    //   4454: ixor
    //   4455: iand
    //   4456: ixor
    //   4457: iadd
    //   4458: aload #6
    //   4460: iload #22
    //   4462: iaload
    //   4463: iadd
    //   4464: aload #20
    //   4466: iload #22
    //   4468: iaload
    //   4469: iadd
    //   4470: istore #23
    //   4472: aload #21
    //   4474: iconst_0
    //   4475: iaload
    //   4476: iconst_2
    //   4477: iushr
    //   4478: aload #21
    //   4480: iconst_0
    //   4481: iaload
    //   4482: bipush #30
    //   4484: ishl
    //   4485: ior
    //   4486: aload #21
    //   4488: iconst_0
    //   4489: iaload
    //   4490: bipush #13
    //   4492: iushr
    //   4493: aload #21
    //   4495: iconst_0
    //   4496: iaload
    //   4497: bipush #19
    //   4499: ishl
    //   4500: ior
    //   4501: ixor
    //   4502: aload #21
    //   4504: iconst_0
    //   4505: iaload
    //   4506: bipush #22
    //   4508: iushr
    //   4509: aload #21
    //   4511: iconst_0
    //   4512: iaload
    //   4513: bipush #10
    //   4515: ishl
    //   4516: ior
    //   4517: ixor
    //   4518: aload #21
    //   4520: iconst_0
    //   4521: iaload
    //   4522: aload #21
    //   4524: iconst_1
    //   4525: iaload
    //   4526: iand
    //   4527: aload #21
    //   4529: iconst_2
    //   4530: iaload
    //   4531: aload #21
    //   4533: iconst_0
    //   4534: iaload
    //   4535: aload #21
    //   4537: iconst_1
    //   4538: iaload
    //   4539: ior
    //   4540: iand
    //   4541: ior
    //   4542: iadd
    //   4543: istore #24
    //   4545: aload #21
    //   4547: iconst_3
    //   4548: dup2
    //   4549: iaload
    //   4550: iload #23
    //   4552: iadd
    //   4553: iastore
    //   4554: aload #21
    //   4556: bipush #7
    //   4558: iload #23
    //   4560: iload #24
    //   4562: iadd
    //   4563: iastore
    //   4564: aload #21
    //   4566: bipush #7
    //   4568: iaload
    //   4569: istore #23
    //   4571: aload #21
    //   4573: bipush #7
    //   4575: aload #21
    //   4577: bipush #6
    //   4579: iaload
    //   4580: iastore
    //   4581: aload #21
    //   4583: bipush #6
    //   4585: aload #21
    //   4587: iconst_5
    //   4588: iaload
    //   4589: iastore
    //   4590: aload #21
    //   4592: iconst_5
    //   4593: aload #21
    //   4595: iconst_4
    //   4596: iaload
    //   4597: iastore
    //   4598: aload #21
    //   4600: iconst_4
    //   4601: aload #21
    //   4603: iconst_3
    //   4604: iaload
    //   4605: iastore
    //   4606: aload #21
    //   4608: iconst_3
    //   4609: aload #21
    //   4611: iconst_2
    //   4612: iaload
    //   4613: iastore
    //   4614: aload #21
    //   4616: iconst_2
    //   4617: aload #21
    //   4619: iconst_1
    //   4620: iaload
    //   4621: iastore
    //   4622: aload #21
    //   4624: iconst_1
    //   4625: aload #21
    //   4627: iconst_0
    //   4628: iaload
    //   4629: iastore
    //   4630: aload #21
    //   4632: iconst_0
    //   4633: iload #23
    //   4635: iastore
    //   4636: iinc #22, 1
    //   4639: iload_2
    //   4640: ifeq -> 4148
    //   4643: iconst_0
    //   4644: istore #22
    //   4646: iload #22
    //   4648: bipush #8
    //   4650: if_icmpge -> 4673
    //   4653: aload #8
    //   4655: iload #22
    //   4657: dup2
    //   4658: iaload
    //   4659: aload #21
    //   4661: iload #22
    //   4663: iaload
    //   4664: iadd
    //   4665: iastore
    //   4666: iinc #22, 1
    //   4669: iload_2
    //   4670: ifeq -> 4646
    //   4673: bipush #32
    //   4675: newarray byte
    //   4677: astore #4
    //   4679: sipush #-24589
    //   4682: aload #4
    //   4684: iconst_0
    //   4685: aload #8
    //   4687: iconst_0
    //   4688: iaload
    //   4689: bipush #24
    //   4691: iushr
    //   4692: i2b
    //   4693: bastore
    //   4694: sipush #16113
    //   4697: aload #4
    //   4699: iconst_1
    //   4700: aload #8
    //   4702: iconst_0
    //   4703: iaload
    //   4704: bipush #16
    //   4706: iushr
    //   4707: i2b
    //   4708: bastore
    //   4709: aload #4
    //   4711: iconst_2
    //   4712: aload #8
    //   4714: iconst_0
    //   4715: iaload
    //   4716: bipush #8
    //   4718: iushr
    //   4719: i2b
    //   4720: bastore
    //   4721: aload #4
    //   4723: iconst_3
    //   4724: aload #8
    //   4726: iconst_0
    //   4727: iaload
    //   4728: i2b
    //   4729: bastore
    //   4730: aload #4
    //   4732: iconst_4
    //   4733: aload #8
    //   4735: iconst_1
    //   4736: iaload
    //   4737: bipush #24
    //   4739: iushr
    //   4740: i2b
    //   4741: bastore
    //   4742: aload #4
    //   4744: iconst_5
    //   4745: aload #8
    //   4747: iconst_1
    //   4748: iaload
    //   4749: bipush #16
    //   4751: iushr
    //   4752: i2b
    //   4753: bastore
    //   4754: aload #4
    //   4756: bipush #6
    //   4758: aload #8
    //   4760: iconst_1
    //   4761: iaload
    //   4762: bipush #8
    //   4764: iushr
    //   4765: i2b
    //   4766: bastore
    //   4767: aload #4
    //   4769: bipush #7
    //   4771: aload #8
    //   4773: iconst_1
    //   4774: iaload
    //   4775: i2b
    //   4776: bastore
    //   4777: aload #4
    //   4779: bipush #8
    //   4781: aload #8
    //   4783: iconst_2
    //   4784: iaload
    //   4785: bipush #24
    //   4787: iushr
    //   4788: i2b
    //   4789: bastore
    //   4790: aload #4
    //   4792: bipush #9
    //   4794: aload #8
    //   4796: iconst_2
    //   4797: iaload
    //   4798: bipush #16
    //   4800: iushr
    //   4801: i2b
    //   4802: bastore
    //   4803: aload #4
    //   4805: bipush #10
    //   4807: aload #8
    //   4809: iconst_2
    //   4810: iaload
    //   4811: bipush #8
    //   4813: iushr
    //   4814: i2b
    //   4815: bastore
    //   4816: aload #4
    //   4818: bipush #11
    //   4820: aload #8
    //   4822: iconst_2
    //   4823: iaload
    //   4824: i2b
    //   4825: bastore
    //   4826: aload #4
    //   4828: bipush #12
    //   4830: aload #8
    //   4832: iconst_3
    //   4833: iaload
    //   4834: bipush #24
    //   4836: iushr
    //   4837: i2b
    //   4838: bastore
    //   4839: aload #4
    //   4841: bipush #13
    //   4843: aload #8
    //   4845: iconst_3
    //   4846: iaload
    //   4847: bipush #16
    //   4849: iushr
    //   4850: i2b
    //   4851: bastore
    //   4852: aload #4
    //   4854: bipush #14
    //   4856: aload #8
    //   4858: iconst_3
    //   4859: iaload
    //   4860: bipush #8
    //   4862: iushr
    //   4863: i2b
    //   4864: bastore
    //   4865: aload #4
    //   4867: bipush #15
    //   4869: aload #8
    //   4871: iconst_3
    //   4872: iaload
    //   4873: i2b
    //   4874: bastore
    //   4875: aload #4
    //   4877: bipush #16
    //   4879: aload #8
    //   4881: iconst_4
    //   4882: iaload
    //   4883: bipush #24
    //   4885: iushr
    //   4886: i2b
    //   4887: bastore
    //   4888: aload #4
    //   4890: bipush #17
    //   4892: aload #8
    //   4894: iconst_4
    //   4895: iaload
    //   4896: bipush #16
    //   4898: iushr
    //   4899: i2b
    //   4900: bastore
    //   4901: aload #4
    //   4903: bipush #18
    //   4905: aload #8
    //   4907: iconst_4
    //   4908: iaload
    //   4909: bipush #8
    //   4911: iushr
    //   4912: i2b
    //   4913: bastore
    //   4914: aload #4
    //   4916: bipush #19
    //   4918: aload #8
    //   4920: iconst_4
    //   4921: iaload
    //   4922: i2b
    //   4923: bastore
    //   4924: aload #4
    //   4926: bipush #20
    //   4928: aload #8
    //   4930: iconst_5
    //   4931: iaload
    //   4932: bipush #24
    //   4934: iushr
    //   4935: i2b
    //   4936: bastore
    //   4937: aload #4
    //   4939: bipush #21
    //   4941: aload #8
    //   4943: iconst_5
    //   4944: iaload
    //   4945: bipush #16
    //   4947: iushr
    //   4948: i2b
    //   4949: bastore
    //   4950: aload #4
    //   4952: bipush #22
    //   4954: aload #8
    //   4956: iconst_5
    //   4957: iaload
    //   4958: bipush #8
    //   4960: iushr
    //   4961: i2b
    //   4962: bastore
    //   4963: aload #4
    //   4965: bipush #23
    //   4967: aload #8
    //   4969: iconst_5
    //   4970: iaload
    //   4971: i2b
    //   4972: bastore
    //   4973: aload #4
    //   4975: bipush #24
    //   4977: aload #8
    //   4979: bipush #6
    //   4981: iaload
    //   4982: bipush #24
    //   4984: iushr
    //   4985: i2b
    //   4986: bastore
    //   4987: aload #4
    //   4989: bipush #25
    //   4991: aload #8
    //   4993: bipush #6
    //   4995: iaload
    //   4996: bipush #16
    //   4998: iushr
    //   4999: i2b
    //   5000: bastore
    //   5001: aload #4
    //   5003: bipush #26
    //   5005: aload #8
    //   5007: bipush #6
    //   5009: iaload
    //   5010: bipush #8
    //   5012: iushr
    //   5013: i2b
    //   5014: bastore
    //   5015: aload #4
    //   5017: bipush #27
    //   5019: aload #8
    //   5021: bipush #6
    //   5023: iaload
    //   5024: i2b
    //   5025: bastore
    //   5026: aload #4
    //   5028: bipush #28
    //   5030: aload #8
    //   5032: bipush #7
    //   5034: iaload
    //   5035: bipush #24
    //   5037: iushr
    //   5038: i2b
    //   5039: bastore
    //   5040: aload #4
    //   5042: bipush #29
    //   5044: aload #8
    //   5046: bipush #7
    //   5048: iaload
    //   5049: bipush #16
    //   5051: iushr
    //   5052: i2b
    //   5053: bastore
    //   5054: aload #4
    //   5056: bipush #30
    //   5058: aload #8
    //   5060: bipush #7
    //   5062: iaload
    //   5063: bipush #8
    //   5065: iushr
    //   5066: i2b
    //   5067: bastore
    //   5068: aload #4
    //   5070: bipush #31
    //   5072: aload #8
    //   5074: bipush #7
    //   5076: iaload
    //   5077: i2b
    //   5078: bastore
    //   5079: invokestatic a : (II)Ljava/lang/String;
    //   5082: iconst_1
    //   5083: ldc burp/Zm6g
    //   5085: invokevirtual getClassLoader : ()Ljava/lang/ClassLoader;
    //   5088: invokestatic forName : (Ljava/lang/String;ZLjava/lang/ClassLoader;)Ljava/lang/Class;
    //   5091: invokevirtual getDeclaredFields : ()[Ljava/lang/reflect/Field;
    //   5094: astore_3
    //   5095: aload_3
    //   5096: arraylength
    //   5097: istore #4
    //   5099: iconst_0
    //   5100: istore #5
    //   5102: iload #5
    //   5104: iload #4
    //   5106: if_icmpge -> 5243
    //   5109: aload_3
    //   5110: iload #5
    //   5112: aaload
    //   5113: astore #6
    //   5115: aload #6
    //   5117: invokevirtual getModifiers : ()I
    //   5120: invokestatic isStatic : (I)Z
    //   5123: ifne -> 5133
    //   5126: goto -> 5236
    //   5129: invokestatic a : (Ljava/lang/Throwable;)Ljava/lang/Throwable;
    //   5132: athrow
    //   5133: aload #6
    //   5135: invokevirtual getType : ()Ljava/lang/Class;
    //   5138: astore #7
    //   5140: aload #7
    //   5142: ifnull -> 5223
    //   5145: aload #7
    //   5147: invokevirtual isPrimitive : ()Z
    //   5150: ifne -> 5223
    //   5153: goto -> 5160
    //   5156: invokestatic a : (Ljava/lang/Throwable;)Ljava/lang/Throwable;
    //   5159: athrow
    //   5160: aload #7
    //   5162: invokevirtual getPackage : ()Ljava/lang/Package;
    //   5165: ifnull -> 5223
    //   5168: goto -> 5175
    //   5171: invokestatic a : (Ljava/lang/Throwable;)Ljava/lang/Throwable;
    //   5174: athrow
    //   5175: aload #7
    //   5177: invokevirtual getPackage : ()Ljava/lang/Package;
    //   5180: invokevirtual getName : ()Ljava/lang/String;
    //   5183: ifnull -> 5223
    //   5186: goto -> 5193
    //   5189: invokestatic a : (Ljava/lang/Throwable;)Ljava/lang/Throwable;
    //   5192: athrow
    //   5193: aload #7
    //   5195: invokevirtual getPackage : ()Ljava/lang/Package;
    //   5198: invokevirtual getName : ()Ljava/lang/String;
    //   5201: sipush #-24591
    //   5204: sipush #31274
    //   5207: invokestatic a : (II)Ljava/lang/String;
    //   5210: invokevirtual startsWith : (Ljava/lang/String;)Z
    //   5213: ifne -> 5223
    //   5216: goto -> 5223
    //   5219: invokestatic a : (Ljava/lang/Throwable;)Ljava/lang/Throwable;
    //   5222: athrow
    //   5223: aload #6
    //   5225: iconst_1
    //   5226: invokevirtual setAccessible : (Z)V
    //   5229: aload #6
    //   5231: aconst_null
    //   5232: invokevirtual get : (Ljava/lang/Object;)Ljava/lang/Object;
    //   5235: pop
    //   5236: iinc #5, 1
    //   5239: iload_2
    //   5240: ifeq -> 5102
    //   5243: sipush #-24584
    //   5246: sipush #31546
    //   5249: invokestatic a : (II)Ljava/lang/String;
    //   5252: invokestatic forName : (Ljava/lang/String;)Ljava/lang/Class;
    //   5255: invokevirtual getDeclaredMethods : ()[Ljava/lang/reflect/Method;
    //   5258: astore_3
    //   5259: aload_3
    //   5260: arraylength
    //   5261: istore #4
    //   5263: iconst_0
    //   5264: istore #5
    //   5266: iload #5
    //   5268: iload #4
    //   5270: if_icmpge -> 5381
    //   5273: aload_3
    //   5274: iload #5
    //   5276: aaload
    //   5277: astore #6
    //   5279: aload #6
    //   5281: invokevirtual getParameterTypes : ()[Ljava/lang/Class;
    //   5284: pop
    //   5285: aload #6
    //   5287: invokevirtual getModifiers : ()I
    //   5290: invokestatic isStatic : (I)Z
    //   5293: ifeq -> 5367
    //   5296: aload #6
    //   5298: invokevirtual getParameterTypes : ()[Ljava/lang/Class;
    //   5301: arraylength
    //   5302: iconst_2
    //   5303: if_icmpne -> 5367
    //   5306: goto -> 5313
    //   5309: invokestatic a : (Ljava/lang/Throwable;)Ljava/lang/Throwable;
    //   5312: athrow
    //   5313: aload #6
    //   5315: invokevirtual getReturnType : ()Ljava/lang/Class;
    //   5318: getstatic java/lang/Boolean.TYPE : Ljava/lang/Class;
    //   5321: if_acmpne -> 5367
    //   5324: goto -> 5331
    //   5327: invokestatic a : (Ljava/lang/Throwable;)Ljava/lang/Throwable;
    //   5330: athrow
    //   5331: aload #6
    //   5333: iconst_1
    //   5334: invokevirtual setAccessible : (Z)V
    //   5337: aload #6
    //   5339: aconst_null
    //   5340: iconst_2
    //   5341: anewarray java/lang/Object
    //   5344: dup
    //   5345: iconst_0
    //   5346: aload_0
    //   5347: aastore
    //   5348: dup
    //   5349: iconst_1
    //   5350: aload_1
    //   5351: aastore
    //   5352: invokevirtual invoke : (Ljava/lang/Object;[Ljava/lang/Object;)Ljava/lang/Object;
    //   5355: pop
    //   5356: iload_2
    //   5357: ifeq -> 5381
    //   5360: goto -> 5367
    //   5363: invokestatic a : (Ljava/lang/Throwable;)Ljava/lang/Throwable;
    //   5366: athrow
    //   5367: iinc #5, 1
    //   5370: iload_2
    //   5371: ifeq -> 5266
    //   5374: goto -> 5381
    //   5377: invokestatic a : (Ljava/lang/Throwable;)Ljava/lang/Throwable;
    //   5380: athrow
    //   5381: getstatic burp/Zlf7.ZM : Ljava/lang/String;
    //   5384: getstatic burp/Zm_u.Zf : Ljava/lang/Object;
    //   5387: checkcast java/math/BigInteger
    //   5390: invokevirtual intValue : ()I
    //   5393: bipush #32
    //   5395: irem
    //   5396: invokestatic abs : (I)I
    //   5399: invokevirtual charAt : (I)C
    //   5402: getstatic burp/Zkhf.Zb : Ljava/lang/String;
    //   5405: getstatic burp/Ze6w.Ze : Ljava/lang/Object;
    //   5408: checkcast java/math/BigInteger
    //   5411: invokevirtual intValue : ()I
    //   5414: bipush #32
    //   5416: irem
    //   5417: invokestatic abs : (I)I
    //   5420: invokevirtual charAt : (I)C
    //   5423: if_icmple -> 5538
    //   5426: getstatic burp/Zbw5.ZC : Ljava/lang/String;
    //   5429: getstatic burp/Zz41.Zv : Ljava/lang/Object;
    //   5432: checkcast java/math/BigInteger
    //   5435: invokevirtual intValue : ()I
    //   5438: bipush #32
    //   5440: irem
    //   5441: invokestatic abs : (I)I
    //   5444: invokevirtual charAt : (I)C
    //   5447: getstatic burp/Zs1d.Zl : Ljava/lang/String;
    //   5450: getstatic burp/Zt4p.Zh : Ljava/lang/Object;
    //   5453: checkcast java/math/BigInteger
    //   5456: invokevirtual intValue : ()I
    //   5459: bipush #32
    //   5461: irem
    //   5462: invokestatic abs : (I)I
    //   5465: invokevirtual charAt : (I)C
    //   5468: if_icmpgt -> 5538
    //   5471: goto -> 5478
    //   5474: invokestatic a : (Ljava/lang/Throwable;)Ljava/lang/Throwable;
    //   5477: athrow
    //   5478: getstatic burp/Ztdl.ZK : Ljava/lang/String;
    //   5481: getstatic burp/Zr14.Zy : Ljava/lang/Object;
    //   5484: checkcast java/math/BigInteger
    //   5487: invokevirtual intValue : ()I
    //   5490: bipush #32
    //   5492: irem
    //   5493: invokestatic abs : (I)I
    //   5496: invokevirtual charAt : (I)C
    //   5499: getstatic burp/Zr1h.ZS : Ljava/lang/String;
    //   5502: getstatic burp/Zzk_.Zx : Ljava/lang/Object;
    //   5505: checkcast java/math/BigInteger
    //   5508: invokevirtual intValue : ()I
    //   5511: bipush #32
    //   5513: irem
    //   5514: invokestatic abs : (I)I
    //   5517: invokevirtual charAt : (I)C
    //   5520: if_icmple -> 5538
    //   5523: goto -> 5530
    //   5526: invokestatic a : (Ljava/lang/Throwable;)Ljava/lang/Throwable;
    //   5529: athrow
    //   5530: iconst_1
    //   5531: goto -> 5539
    //   5534: invokestatic a : (Ljava/lang/Throwable;)Ljava/lang/Throwable;
    //   5537: athrow
    //   5538: iconst_0
    //   5539: ireturn
    //   5540: astore_3
    //   5541: new java/lang/Exception
    //   5544: dup
    //   5545: aload_3
    //   5546: invokevirtual getMessage : ()Ljava/lang/String;
    //   5549: invokespecial <init> : (Ljava/lang/String;)V
    //   5552: athrow
    // Exception table:
    //   from	to	target	type
    //   4	5539	5540	java/lang/Throwable
    //   309	333	336	java/lang/Throwable
    //   407	444	444	java/lang/Throwable
    //   448	469	469	java/lang/Throwable
    //   473	503	503	java/lang/Throwable
    //   728	742	742	java/lang/Throwable
    //   753	766	769	java/lang/Throwable
    //   758	781	784	java/lang/Throwable
    //   773	799	802	java/lang/Throwable
    //   788	829	832	java/lang/Throwable
    //   892	919	922	java/lang/Throwable
    //   909	940	943	java/lang/Throwable
    //   926	970	973	java/lang/Throwable
    //   947	981	981	java/lang/Throwable
    //   992	1008	1011	java/lang/Throwable
    //   1816	1850	1853	java/lang/Throwable
    //   1945	2023	2026	java/lang/Throwable
    //   1952	2166	2169	java/lang/Throwable
    //   2543	2558	2558	java/lang/Throwable
    //   2585	2619	2622	java/lang/Throwable
    //   2629	2641	2644	java/lang/Throwable
    //   2727	2805	2808	java/lang/Throwable
    //   2734	2948	2951	java/lang/Throwable
    //   3348	3426	3429	java/lang/Throwable
    //   3355	3569	3572	java/lang/Throwable
    //   4016	4050	4053	java/lang/Throwable
    //   4057	4069	4072	java/lang/Throwable
    //   4155	4233	4236	java/lang/Throwable
    //   4162	4376	4379	java/lang/Throwable
    //   5115	5129	5129	java/lang/Throwable
    //   5140	5153	5156	java/lang/Throwable
    //   5145	5168	5171	java/lang/Throwable
    //   5160	5186	5189	java/lang/Throwable
    //   5175	5216	5219	java/lang/Throwable
    //   5279	5306	5309	java/lang/Throwable
    //   5296	5324	5327	java/lang/Throwable
    //   5313	5360	5363	java/lang/Throwable
    //   5331	5374	5377	java/lang/Throwable
    //   5381	5471	5474	java/lang/Throwable
    //   5426	5523	5526	java/lang/Throwable
    //   5478	5534	5534	java/lang/Throwable
  }
  
  static void Zo(Object paramObject) {
    Ze2w.Za = a(-24580, -6960);
    Ze2w.ZA = new BigInteger(a(-24586, 31516));
    boolean bool = Zt2e.ZK();
    try {
      try {
        if (Zld9.Zx.charAt(Math.abs(((BigInteger)Zs3m.ZW).intValue() % 32)) > Zti7.Zc.charAt(Math.abs(((BigInteger)Zscz.ZN).intValue() % 32))) {
          try {
            Zsbo.Za(Class.forName(a(-24592, -11267)));
            if (bool)
              Ze_l.Zv(Class.forName(a(-24587, -25174))); 
          } catch (Throwable throwable) {
            throw a(null);
          } 
          return;
        } 
      } catch (Throwable throwable) {
        throw a(null);
      } 
      Ze_l.Zv(Class.forName(a(-24587, -25174)));
    } catch (Throwable throwable) {}
  }
  
  static void Zx(Object[] paramArrayOfObject, Object paramObject) throws Throwable {}
  
  static {
    // Byte code:
    //   0: bipush #15
    //   2: anewarray java/lang/String
    //   5: astore #5
    //   7: iconst_0
    //   8: istore_3
    //   9: ldc 'u|k\\n^|zJpD_j*S3` b2VWHki7\\f6u_r\\tWmGMS@^NBSbqG<l0:Vo_(S@N S=\\n\}=cUZP!_FS'n\\t"a_Q]\\t\\nd<oVbrC1> O{Sr@{NIU|v\\b\\t9#ZyF\\t.LqMRB\:]mz!/H72_fP@_`rIc]IF44U'
    //   11: dup
    //   12: astore_2
    //   13: invokevirtual length : ()I
    //   16: istore #4
    //   18: bipush #32
    //   20: istore_1
    //   21: iconst_m1
    //   22: istore_0
    //   23: bipush #94
    //   25: iinc #0, 1
    //   28: aload_2
    //   29: iload_0
    //   30: dup
    //   31: iload_1
    //   32: iadd
    //   33: invokevirtual substring : (II)Ljava/lang/String;
    //   36: iconst_m1
    //   37: goto -> 143
    //   40: aload #5
    //   42: swap
    //   43: iload_3
    //   44: iinc #3, 1
    //   47: swap
    //   48: aastore
    //   49: iload_0
    //   50: iload_1
    //   51: iadd
    //   52: dup
    //   53: istore_0
    //   54: iload #4
    //   56: if_icmpge -> 68
    //   59: aload_2
    //   60: iload_0
    //   61: invokevirtual charAt : (I)C
    //   64: istore_1
    //   65: goto -> 23
    //   68: ldc ' wvj\\tq(e&'
    //   70: dup
    //   71: astore_2
    //   72: invokevirtual length : ()I
    //   75: istore #4
    //   77: bipush #9
    //   79: istore_1
    //   80: iconst_m1
    //   81: istore_0
    //   82: bipush #15
    //   84: iinc #0, 1
    //   87: aload_2
    //   88: iload_0
    //   89: dup
    //   90: iload_1
    //   91: iadd
    //   92: invokevirtual substring : (II)Ljava/lang/String;
    //   95: iconst_0
    //   96: goto -> 143
    //   99: aload #5
    //   101: swap
    //   102: iload_3
    //   103: iinc #3, 1
    //   106: swap
    //   107: aastore
    //   108: iload_0
    //   109: iload_1
    //   110: iadd
    //   111: dup
    //   112: istore_0
    //   113: iload #4
    //   115: if_icmpge -> 127
    //   118: aload_2
    //   119: iload_0
    //   120: invokevirtual charAt : (I)C
    //   123: istore_1
    //   124: goto -> 82
    //   127: aload #5
    //   129: putstatic burp/Zmz.a : [Ljava/lang/String;
    //   132: bipush #15
    //   134: anewarray java/lang/String
    //   137: putstatic burp/Zmz.b : [Ljava/lang/String;
    //   140: goto -> 300
    //   143: dup_x2
    //   144: pop
    //   145: invokevirtual toCharArray : ()[C
    //   148: dup_x1
    //   149: arraylength
    //   150: dup_x2
    //   151: pop
    //   152: iconst_0
    //   153: istore #6
    //   155: dup2_x1
    //   156: pop2
    //   157: dup_x2
    //   158: iconst_1
    //   159: if_icmpgt -> 260
    //   162: dup2
    //   163: swap
    //   164: iload #6
    //   166: dup2_x1
    //   167: caload
    //   168: swap
    //   169: iload #6
    //   171: bipush #7
    //   173: irem
    //   174: tableswitch default -> 242, 0 -> 212, 1 -> 217, 2 -> 222, 3 -> 227, 4 -> 232, 5 -> 237
    //   212: bipush #47
    //   214: goto -> 244
    //   217: bipush #21
    //   219: goto -> 244
    //   222: bipush #81
    //   224: goto -> 244
    //   227: bipush #127
    //   229: goto -> 244
    //   232: bipush #124
    //   234: goto -> 244
    //   237: bipush #77
    //   239: goto -> 244
    //   242: bipush #42
    //   244: ixor
    //   245: ixor
    //   246: i2c
    //   247: castore
    //   248: iinc #6, 1
    //   251: dup
    //   252: ifne -> 260
    //   255: dup2
    //   256: dup_x1
    //   257: goto -> 166
    //   260: dup2_x1
    //   261: pop2
    //   262: dup_x2
    //   263: iload #6
    //   265: if_icmpgt -> 162
    //   268: pop
    //   269: new java/lang/String
    //   272: dup_x1
    //   273: swap
    //   274: invokespecial <init> : ([C)V
    //   277: invokevirtual intern : ()Ljava/lang/String;
    //   280: swap
    //   281: pop
    //   282: swap
    //   283: tableswitch default -> 40, 0 -> 99
    //   300: sipush #-24579
    //   303: sipush #-6003
    //   306: invokestatic a : (II)Ljava/lang/String;
    //   309: putstatic burp/Zmz.Zp : Ljava/lang/String;
    //   312: new java/math/BigInteger
    //   315: dup
    //   316: sipush #-24578
    //   319: sipush #13332
    //   322: invokestatic a : (II)Ljava/lang/String;
    //   325: invokespecial <init> : (Ljava/lang/String;)V
    //   328: putstatic burp/Zmz.ZW : Ljava/lang/Object;
    //   331: return
  }
  
  private static Throwable a(Throwable paramThrowable) {
    return paramThrowable;
  }
  
  private static String a(int paramInt1, int paramInt2) {
    int i = (paramInt1 ^ 0xFFFF9FFD) & 0xFFFF;
    if (b[i] == null) {
      char[] arrayOfChar = a[i].toCharArray();
      switch (arrayOfChar[0] & 0xFF) {
        case 0:
        
        case 1:
        
        case 2:
        
        case 3:
        
        case 4:
        
        case 5:
        
        case 6:
        
        case 7:
        
        case 8:
        
        case 9:
        
        case 10:
        
        case 11:
        
        case 12:
        
        case 13:
        
        case 14:
        
        case 15:
        
        case 16:
        
        case 17:
        
        case 18:
        
        case 19:
        
        case 20:
        
        case 21:
        
        case 22:
        
        case 23:
        
        case 24:
        
        case 25:
        
        case 26:
        
        case 27:
        
        case 28:
        
        case 29:
        
        case 30:
        
        case 31:
        
        case 32:
        
        case 33:
        
        case 34:
        
        case 35:
        
        case 36:
        
        case 37:
        
        case 38:
        
        case 39:
        
        case 40:
        
        case 41:
        
        case 42:
        
        case 43:
        
        case 44:
        
        case 45:
        
        case 46:
        
        case 47:
        
        case 48:
        
        case 49:
        
        case 50:
        
        case 51:
        
        case 52:
        
        case 53:
        
        case 54:
        
        case 55:
        
        case 56:
        
        case 57:
        
        case 58:
        
        case 59:
        
        case 60:
        
        case 61:
        
        case 62:
        
        case 63:
        
        case 64:
        
        case 65:
        
        case 66:
        
        case 67:
        
        case 68:
        
        case 69:
        
        case 70:
        
        case 71:
        
        case 72:
        
        case 73:
        
        case 74:
        
        case 75:
        
        case 76:
        
        case 77:
        
        case 78:
        
        case 79:
        
        case 80:
        
        case 81:
        
        case 82:
        
        case 83:
        
        case 84:
        
        case 85:
        
        case 86:
        
        case 87:
        
        case 88:
        
        case 89:
        
        case 90:
        
        case 91:
        
        case 92:
        
        case 93:
        
        case 94:
        
        case 95:
        
        case 96:
        
        case 97:
        
        case 98:
        
        case 99:
        
        case 100:
        
        case 101:
        
        case 102:
        
        case 103:
        
        case 104:
        
        case 105:
        
        case 106:
        
        case 107:
        
        case 108:
        
        case 109:
        
        case 110:
        
        case 111:
        
        case 112:
        
        case 113:
        
        case 114:
        
        case 115:
        
        case 116:
        
        case 117:
        
        case 118:
        
        case 119:
        
        case 120:
        
        case 121:
        
        case 122:
        
        case 123:
        
        case 124:
        
        case 125:
        
        case 126:
        
        case 127:
        
        case 128:
        
        case 129:
        
        case 130:
        
        case 131:
        
        case 132:
        
        case 133:
        
        case 134:
        
        case 135:
        
        case 136:
        
        case 137:
        
        case 138:
        
        case 139:
        
        case 140:
        
        case 141:
        
        case 142:
        
        case 143:
        
        case 144:
        
        case 145:
        
        case 146:
        
        case 147:
        
        case 148:
        
        case 149:
        
        case 150:
        
        case 151:
        
        case 152:
        
        case 153:
        
        case 154:
        
        case 155:
        
        case 156:
        
        case 157:
        
        case 158:
        
        case 159:
        
        case 160:
        
        case 161:
        
        case 162:
        
        case 163:
        
        case 164:
        
        case 165:
        
        case 166:
        
        case 167:
        
        case 168:
        
        case 169:
        
        case 170:
        
        case 171:
        
        case 172:
        
        case 173:
        
        case 174:
        
        case 175:
        
        case 176:
        
        case 177:
        
        case 178:
        
        case 179:
        
        case 180:
        
        case 181:
        
        case 182:
        
        case 183:
        
        case 184:
        
        case 185:
        
        case 186:
        
        case 187:
        
        case 188:
        
        case 189:
        
        case 190:
        
        case 191:
        
        case 192:
        
        case 193:
        
        case 194:
        
        case 195:
        
        case 196:
        
        case 197:
        
        case 198:
        
        case 199:
        
        case 200:
        
        case 201:
        
        case 202:
        
        case 203:
        
        case 204:
        
        case 205:
        
        case 206:
        
        case 207:
        
        case 208:
        
        case 209:
        
        case 210:
        
        case 211:
        
        case 212:
        
        case 213:
        
        case 214:
        
        case 215:
        
        case 216:
        
        case 217:
        
        case 218:
        
        case 219:
        
        case 220:
        
        case 221:
        
        case 222:
        
        case 223:
        
        case 224:
        
        case 225:
        
        case 226:
        
        case 227:
        
        case 228:
        
        case 229:
        
        case 230:
        
        case 231:
        
        case 232:
        
        case 233:
        
        case 234:
        
        case 235:
        
        case 236:
        
        case 237:
        
        case 238:
        
        case 239:
        
        case 240:
        
        case 241:
        
        case 242:
        
        case 243:
        
        case 244:
        
        case 245:
        
        case 246:
        
        case 247:
        
        case 248:
        
        case 249:
        
        case 250:
        
        case 251:
        
        case 252:
        
        case 253:
        
        case 254:
        
        default:
          break;
      } 
      char c = '';
      int j = (paramInt2 & 0xFF) - c;
      if (j < 0)
        j += 256; 
      int k = ((paramInt2 & 0xFFFF) >>> 8) - c;
      if (k < 0)
        k += 256; 
      for (byte b = 0; b < arrayOfChar.length; b++) {
        int m = b % 2;
        if (m == 0) {
          arrayOfChar[b] = (char)(arrayOfChar[b] ^ j);
          j = ((j >>> 3 | j << 5) ^ arrayOfChar[b]) & 0xFF;
        } else {
          arrayOfChar[b] = (char)(arrayOfChar[b] ^ k);
          k = ((k >>> 3 | k << 5) ^ arrayOfChar[b]) & 0xFF;
        } 
      } 
      b[i] = (new String(arrayOfChar)).intern();
    } 
    return b[i];
  }
}


/* Location:              C:\Program Files\BurpSuitePro\burpsuite_pro.jar!\burp\Zmz.class
 * Java compiler version: 21 (65.0)
 * JD-Core Version:       1.1.3
 */