package burp;

import java.math.BigInteger;

class Znp extends ClassLoader {
  static String Zr;
  
  static Object ZJ;
  
  private static final String[] a;
  
  private static final String[] b;
  
  static boolean Zw(Object[] paramArrayOfObject, Object paramObject) throws Throwable {
    // Byte code:
    //   0: invokestatic ZK : ()Z
    //   3: istore_2
    //   4: getstatic burp/Zrw7.ZV : Ljava/lang/Object;
    //   7: checkcast java/math/BigInteger
    //   10: getstatic burp/Zr9j.Zw : Ljava/lang/Object;
    //   13: checkcast java/math/BigInteger
    //   16: invokevirtual add : (Ljava/math/BigInteger;)Ljava/math/BigInteger;
    //   19: putstatic burp/Ze54.Zx : Ljava/lang/Object;
    //   22: getstatic burp/Zm5p.Ze : Ljava/lang/Object;
    //   25: checkcast java/math/BigInteger
    //   28: invokevirtual toByteArray : ()[B
    //   31: astore_3
    //   32: bipush #64
    //   34: newarray byte
    //   36: dup
    //   37: iconst_0
    //   38: bipush #-128
    //   40: bastore
    //   41: dup
    //   42: iconst_1
    //   43: iconst_0
    //   44: bastore
    //   45: dup
    //   46: iconst_2
    //   47: iconst_0
    //   48: bastore
    //   49: dup
    //   50: iconst_3
    //   51: iconst_0
    //   52: bastore
    //   53: dup
    //   54: iconst_4
    //   55: iconst_0
    //   56: bastore
    //   57: dup
    //   58: iconst_5
    //   59: iconst_0
    //   60: bastore
    //   61: dup
    //   62: bipush #6
    //   64: iconst_0
    //   65: bastore
    //   66: dup
    //   67: bipush #7
    //   69: iconst_0
    //   70: bastore
    //   71: dup
    //   72: bipush #8
    //   74: iconst_0
    //   75: bastore
    //   76: dup
    //   77: bipush #9
    //   79: iconst_0
    //   80: bastore
    //   81: dup
    //   82: bipush #10
    //   84: iconst_0
    //   85: bastore
    //   86: dup
    //   87: bipush #11
    //   89: iconst_0
    //   90: bastore
    //   91: dup
    //   92: bipush #12
    //   94: iconst_0
    //   95: bastore
    //   96: dup
    //   97: bipush #13
    //   99: iconst_0
    //   100: bastore
    //   101: dup
    //   102: bipush #14
    //   104: iconst_0
    //   105: bastore
    //   106: dup
    //   107: bipush #15
    //   109: iconst_0
    //   110: bastore
    //   111: dup
    //   112: bipush #16
    //   114: iconst_0
    //   115: bastore
    //   116: dup
    //   117: bipush #17
    //   119: iconst_0
    //   120: bastore
    //   121: dup
    //   122: bipush #18
    //   124: iconst_0
    //   125: bastore
    //   126: dup
    //   127: bipush #19
    //   129: iconst_0
    //   130: bastore
    //   131: dup
    //   132: bipush #20
    //   134: iconst_0
    //   135: bastore
    //   136: dup
    //   137: bipush #21
    //   139: iconst_0
    //   140: bastore
    //   141: dup
    //   142: bipush #22
    //   144: iconst_0
    //   145: bastore
    //   146: dup
    //   147: bipush #23
    //   149: iconst_0
    //   150: bastore
    //   151: dup
    //   152: bipush #24
    //   154: iconst_0
    //   155: bastore
    //   156: dup
    //   157: bipush #25
    //   159: iconst_0
    //   160: bastore
    //   161: dup
    //   162: bipush #26
    //   164: iconst_0
    //   165: bastore
    //   166: dup
    //   167: bipush #27
    //   169: iconst_0
    //   170: bastore
    //   171: dup
    //   172: bipush #28
    //   174: iconst_0
    //   175: bastore
    //   176: dup
    //   177: bipush #29
    //   179: iconst_0
    //   180: bastore
    //   181: dup
    //   182: bipush #30
    //   184: iconst_0
    //   185: bastore
    //   186: dup
    //   187: bipush #31
    //   189: iconst_0
    //   190: bastore
    //   191: dup
    //   192: bipush #32
    //   194: iconst_0
    //   195: bastore
    //   196: dup
    //   197: bipush #33
    //   199: iconst_0
    //   200: bastore
    //   201: dup
    //   202: bipush #34
    //   204: iconst_0
    //   205: bastore
    //   206: dup
    //   207: bipush #35
    //   209: iconst_0
    //   210: bastore
    //   211: dup
    //   212: bipush #36
    //   214: iconst_0
    //   215: bastore
    //   216: dup
    //   217: bipush #37
    //   219: iconst_0
    //   220: bastore
    //   221: dup
    //   222: bipush #38
    //   224: iconst_0
    //   225: bastore
    //   226: dup
    //   227: bipush #39
    //   229: iconst_0
    //   230: bastore
    //   231: dup
    //   232: bipush #40
    //   234: iconst_0
    //   235: bastore
    //   236: dup
    //   237: bipush #41
    //   239: iconst_0
    //   240: bastore
    //   241: dup
    //   242: bipush #42
    //   244: iconst_0
    //   245: bastore
    //   246: dup
    //   247: bipush #43
    //   249: iconst_0
    //   250: bastore
    //   251: dup
    //   252: bipush #44
    //   254: iconst_0
    //   255: bastore
    //   256: dup
    //   257: bipush #45
    //   259: iconst_0
    //   260: bastore
    //   261: dup
    //   262: bipush #46
    //   264: iconst_0
    //   265: bastore
    //   266: dup
    //   267: bipush #47
    //   269: iconst_0
    //   270: bastore
    //   271: dup
    //   272: bipush #48
    //   274: iconst_0
    //   275: bastore
    //   276: dup
    //   277: bipush #49
    //   279: iconst_0
    //   280: bastore
    //   281: dup
    //   282: bipush #50
    //   284: iconst_0
    //   285: bastore
    //   286: dup
    //   287: bipush #51
    //   289: iconst_0
    //   290: bastore
    //   291: dup
    //   292: bipush #52
    //   294: iconst_0
    //   295: bastore
    //   296: dup
    //   297: bipush #53
    //   299: iconst_0
    //   300: bastore
    //   301: dup
    //   302: bipush #54
    //   304: iconst_0
    //   305: bastore
    //   306: dup
    //   307: bipush #55
    //   309: iconst_0
    //   310: bastore
    //   311: dup
    //   312: bipush #56
    //   314: iconst_0
    //   315: bastore
    //   316: dup
    //   317: bipush #57
    //   319: iconst_0
    //   320: bastore
    //   321: dup
    //   322: bipush #58
    //   324: iconst_0
    //   325: bastore
    //   326: dup
    //   327: bipush #59
    //   329: iconst_0
    //   330: bastore
    //   331: dup
    //   332: bipush #60
    //   334: iconst_0
    //   335: bastore
    //   336: dup
    //   337: bipush #61
    //   339: iconst_0
    //   340: bastore
    //   341: dup
    //   342: bipush #62
    //   344: iconst_0
    //   345: bastore
    //   346: dup
    //   347: bipush #63
    //   349: iconst_0
    //   350: bastore
    //   351: astore #5
    //   353: bipush #64
    //   355: newarray int
    //   357: dup
    //   358: iconst_0
    //   359: ldc 1116352408
    //   361: iastore
    //   362: dup
    //   363: iconst_1
    //   364: ldc 1899447441
    //   366: iastore
    //   367: dup
    //   368: iconst_2
    //   369: ldc -1245643825
    //   371: iastore
    //   372: dup
    //   373: iconst_3
    //   374: ldc -373957723
    //   376: iastore
    //   377: dup
    //   378: iconst_4
    //   379: ldc 961987163
    //   381: iastore
    //   382: dup
    //   383: iconst_5
    //   384: ldc 1508970993
    //   386: iastore
    //   387: dup
    //   388: bipush #6
    //   390: ldc -1841331548
    //   392: iastore
    //   393: dup
    //   394: bipush #7
    //   396: ldc -1424204075
    //   398: iastore
    //   399: dup
    //   400: bipush #8
    //   402: ldc -670586216
    //   404: iastore
    //   405: dup
    //   406: bipush #9
    //   408: ldc 310598401
    //   410: iastore
    //   411: dup
    //   412: bipush #10
    //   414: ldc 607225278
    //   416: iastore
    //   417: dup
    //   418: bipush #11
    //   420: ldc 1426881987
    //   422: iastore
    //   423: dup
    //   424: bipush #12
    //   426: ldc 1925078388
    //   428: iastore
    //   429: dup
    //   430: bipush #13
    //   432: ldc -2132889090
    //   434: iastore
    //   435: dup
    //   436: bipush #14
    //   438: ldc -1680079193
    //   440: iastore
    //   441: dup
    //   442: bipush #15
    //   444: ldc -1046744716
    //   446: iastore
    //   447: dup
    //   448: bipush #16
    //   450: ldc -459576895
    //   452: iastore
    //   453: dup
    //   454: bipush #17
    //   456: ldc -272742522
    //   458: iastore
    //   459: dup
    //   460: bipush #18
    //   462: ldc 264347078
    //   464: iastore
    //   465: dup
    //   466: bipush #19
    //   468: ldc 604807628
    //   470: iastore
    //   471: dup
    //   472: bipush #20
    //   474: ldc 770255983
    //   476: iastore
    //   477: dup
    //   478: bipush #21
    //   480: ldc 1249150122
    //   482: iastore
    //   483: dup
    //   484: bipush #22
    //   486: ldc 1555081692
    //   488: iastore
    //   489: dup
    //   490: bipush #23
    //   492: ldc 1996064986
    //   494: iastore
    //   495: dup
    //   496: bipush #24
    //   498: ldc -1740746414
    //   500: iastore
    //   501: dup
    //   502: bipush #25
    //   504: ldc -1473132947
    //   506: iastore
    //   507: dup
    //   508: bipush #26
    //   510: ldc -1341970488
    //   512: iastore
    //   513: dup
    //   514: bipush #27
    //   516: ldc -1084653625
    //   518: iastore
    //   519: dup
    //   520: bipush #28
    //   522: ldc -958395405
    //   524: iastore
    //   525: dup
    //   526: bipush #29
    //   528: ldc -710438585
    //   530: iastore
    //   531: dup
    //   532: bipush #30
    //   534: ldc 113926993
    //   536: iastore
    //   537: dup
    //   538: bipush #31
    //   540: ldc 338241895
    //   542: iastore
    //   543: dup
    //   544: bipush #32
    //   546: ldc 666307205
    //   548: iastore
    //   549: dup
    //   550: bipush #33
    //   552: ldc 773529912
    //   554: iastore
    //   555: dup
    //   556: bipush #34
    //   558: ldc 1294757372
    //   560: iastore
    //   561: dup
    //   562: bipush #35
    //   564: ldc 1396182291
    //   566: iastore
    //   567: dup
    //   568: bipush #36
    //   570: ldc 1695183700
    //   572: iastore
    //   573: dup
    //   574: bipush #37
    //   576: ldc 1986661051
    //   578: iastore
    //   579: dup
    //   580: bipush #38
    //   582: ldc -2117940946
    //   584: iastore
    //   585: dup
    //   586: bipush #39
    //   588: ldc -1838011259
    //   590: iastore
    //   591: dup
    //   592: bipush #40
    //   594: ldc -1564481375
    //   596: iastore
    //   597: dup
    //   598: bipush #41
    //   600: ldc -1474664885
    //   602: iastore
    //   603: dup
    //   604: bipush #42
    //   606: ldc -1035236496
    //   608: iastore
    //   609: dup
    //   610: bipush #43
    //   612: ldc -949202525
    //   614: iastore
    //   615: dup
    //   616: bipush #44
    //   618: ldc -778901479
    //   620: iastore
    //   621: dup
    //   622: bipush #45
    //   624: ldc -694614492
    //   626: iastore
    //   627: dup
    //   628: bipush #46
    //   630: ldc -200395387
    //   632: iastore
    //   633: dup
    //   634: bipush #47
    //   636: ldc 275423344
    //   638: iastore
    //   639: dup
    //   640: bipush #48
    //   642: ldc 430227734
    //   644: iastore
    //   645: dup
    //   646: bipush #49
    //   648: ldc 506948616
    //   650: iastore
    //   651: dup
    //   652: bipush #50
    //   654: ldc 659060556
    //   656: iastore
    //   657: dup
    //   658: bipush #51
    //   660: ldc 883997877
    //   662: iastore
    //   663: dup
    //   664: bipush #52
    //   666: ldc 958139571
    //   668: iastore
    //   669: dup
    //   670: bipush #53
    //   672: ldc 1322822218
    //   674: iastore
    //   675: dup
    //   676: bipush #54
    //   678: ldc 1537002063
    //   680: iastore
    //   681: dup
    //   682: bipush #55
    //   684: ldc 1747873779
    //   686: iastore
    //   687: dup
    //   688: bipush #56
    //   690: ldc 1955562222
    //   692: iastore
    //   693: dup
    //   694: bipush #57
    //   696: ldc 2024104815
    //   698: iastore
    //   699: dup
    //   700: bipush #58
    //   702: ldc -2067236844
    //   704: iastore
    //   705: dup
    //   706: bipush #59
    //   708: ldc -1933114872
    //   710: iastore
    //   711: dup
    //   712: bipush #60
    //   714: ldc -1866530822
    //   716: iastore
    //   717: dup
    //   718: bipush #61
    //   720: ldc -1538233109
    //   722: iastore
    //   723: dup
    //   724: bipush #62
    //   726: ldc -1090935817
    //   728: iastore
    //   729: dup
    //   730: bipush #63
    //   732: ldc -965641998
    //   734: iastore
    //   735: astore #6
    //   737: iconst_2
    //   738: newarray int
    //   740: dup
    //   741: iconst_0
    //   742: iconst_0
    //   743: iastore
    //   744: dup
    //   745: iconst_1
    //   746: iconst_0
    //   747: iastore
    //   748: astore #7
    //   750: bipush #8
    //   752: newarray int
    //   754: dup
    //   755: iconst_0
    //   756: ldc 1779033703
    //   758: iastore
    //   759: dup
    //   760: iconst_1
    //   761: ldc -1150833019
    //   763: iastore
    //   764: dup
    //   765: iconst_2
    //   766: ldc 1013904242
    //   768: iastore
    //   769: dup
    //   770: iconst_3
    //   771: ldc -1521486534
    //   773: iastore
    //   774: dup
    //   775: iconst_4
    //   776: ldc 1359893119
    //   778: iastore
    //   779: dup
    //   780: iconst_5
    //   781: ldc -1694144372
    //   783: iastore
    //   784: dup
    //   785: bipush #6
    //   787: ldc 528734635
    //   789: iastore
    //   790: dup
    //   791: bipush #7
    //   793: ldc 1541459225
    //   795: iastore
    //   796: astore #8
    //   798: bipush #64
    //   800: newarray byte
    //   802: astore #9
    //   804: bipush #64
    //   806: newarray byte
    //   808: astore #10
    //   810: aload_3
    //   811: arraylength
    //   812: istore #11
    //   814: aload #7
    //   816: iconst_0
    //   817: iaload
    //   818: bipush #63
    //   820: iand
    //   821: istore #12
    //   823: aload #7
    //   825: iconst_0
    //   826: dup2
    //   827: iaload
    //   828: iload #11
    //   830: iadd
    //   831: iastore
    //   832: aload #7
    //   834: iconst_0
    //   835: dup2
    //   836: iaload
    //   837: iconst_m1
    //   838: iand
    //   839: iastore
    //   840: aload #7
    //   842: iconst_0
    //   843: iaload
    //   844: iload #11
    //   846: if_icmpge -> 864
    //   849: aload #7
    //   851: iconst_1
    //   852: dup2
    //   853: iaload
    //   854: iconst_1
    //   855: iadd
    //   856: iastore
    //   857: goto -> 864
    //   860: invokestatic a : (Ljava/lang/Throwable;)Ljava/lang/Throwable;
    //   863: athrow
    //   864: iconst_0
    //   865: istore #13
    //   867: iload #11
    //   869: bipush #64
    //   871: if_icmplt -> 1480
    //   874: iconst_0
    //   875: istore #14
    //   877: iload #14
    //   879: bipush #64
    //   881: if_icmpge -> 903
    //   884: aload #10
    //   886: iload #14
    //   888: aload_3
    //   889: iload #13
    //   891: iload #14
    //   893: iadd
    //   894: baload
    //   895: bastore
    //   896: iinc #14, 1
    //   899: iload_2
    //   900: ifeq -> 877
    //   903: bipush #64
    //   905: newarray int
    //   907: astore #14
    //   909: bipush #8
    //   911: newarray int
    //   913: astore #15
    //   915: iconst_0
    //   916: istore #16
    //   918: iload #16
    //   920: bipush #8
    //   922: if_icmpge -> 942
    //   925: aload #15
    //   927: iload #16
    //   929: aload #8
    //   931: iload #16
    //   933: iaload
    //   934: iastore
    //   935: iinc #16, 1
    //   938: iload_2
    //   939: ifeq -> 918
    //   942: iconst_0
    //   943: istore #16
    //   945: iload #16
    //   947: bipush #64
    //   949: if_icmpge -> 1440
    //   952: iload #16
    //   954: bipush #16
    //   956: if_icmpge -> 1037
    //   959: aload #14
    //   961: iload #16
    //   963: aload #10
    //   965: iconst_4
    //   966: iload #16
    //   968: imul
    //   969: baload
    //   970: sipush #255
    //   973: iand
    //   974: bipush #24
    //   976: ishl
    //   977: aload #10
    //   979: iconst_4
    //   980: iload #16
    //   982: imul
    //   983: iconst_1
    //   984: iadd
    //   985: baload
    //   986: sipush #255
    //   989: iand
    //   990: bipush #16
    //   992: ishl
    //   993: ior
    //   994: aload #10
    //   996: iconst_4
    //   997: iload #16
    //   999: imul
    //   1000: iconst_2
    //   1001: iadd
    //   1002: baload
    //   1003: sipush #255
    //   1006: iand
    //   1007: bipush #8
    //   1009: ishl
    //   1010: ior
    //   1011: aload #10
    //   1013: iconst_4
    //   1014: iload #16
    //   1016: imul
    //   1017: iconst_3
    //   1018: iadd
    //   1019: baload
    //   1020: sipush #255
    //   1023: iand
    //   1024: ior
    //   1025: iastore
    //   1026: iload_2
    //   1027: ifeq -> 1180
    //   1030: goto -> 1037
    //   1033: invokestatic a : (Ljava/lang/Throwable;)Ljava/lang/Throwable;
    //   1036: athrow
    //   1037: aload #14
    //   1039: iload #16
    //   1041: aload #14
    //   1043: iload #16
    //   1045: iconst_2
    //   1046: isub
    //   1047: iaload
    //   1048: bipush #17
    //   1050: iushr
    //   1051: aload #14
    //   1053: iload #16
    //   1055: iconst_2
    //   1056: isub
    //   1057: iaload
    //   1058: bipush #15
    //   1060: ishl
    //   1061: ior
    //   1062: aload #14
    //   1064: iload #16
    //   1066: iconst_2
    //   1067: isub
    //   1068: iaload
    //   1069: bipush #19
    //   1071: iushr
    //   1072: aload #14
    //   1074: iload #16
    //   1076: iconst_2
    //   1077: isub
    //   1078: iaload
    //   1079: bipush #13
    //   1081: ishl
    //   1082: ior
    //   1083: ixor
    //   1084: aload #14
    //   1086: iload #16
    //   1088: iconst_2
    //   1089: isub
    //   1090: iaload
    //   1091: bipush #10
    //   1093: iushr
    //   1094: ixor
    //   1095: aload #14
    //   1097: iload #16
    //   1099: bipush #7
    //   1101: isub
    //   1102: iaload
    //   1103: iadd
    //   1104: aload #14
    //   1106: iload #16
    //   1108: bipush #15
    //   1110: isub
    //   1111: iaload
    //   1112: bipush #7
    //   1114: iushr
    //   1115: aload #14
    //   1117: iload #16
    //   1119: bipush #15
    //   1121: isub
    //   1122: iaload
    //   1123: bipush #25
    //   1125: ishl
    //   1126: ior
    //   1127: aload #14
    //   1129: iload #16
    //   1131: bipush #15
    //   1133: isub
    //   1134: iaload
    //   1135: bipush #18
    //   1137: iushr
    //   1138: aload #14
    //   1140: iload #16
    //   1142: bipush #15
    //   1144: isub
    //   1145: iaload
    //   1146: bipush #14
    //   1148: ishl
    //   1149: ior
    //   1150: ixor
    //   1151: aload #14
    //   1153: iload #16
    //   1155: bipush #15
    //   1157: isub
    //   1158: iaload
    //   1159: iconst_3
    //   1160: iushr
    //   1161: ixor
    //   1162: iadd
    //   1163: aload #14
    //   1165: iload #16
    //   1167: bipush #16
    //   1169: isub
    //   1170: iaload
    //   1171: iadd
    //   1172: iastore
    //   1173: goto -> 1180
    //   1176: invokestatic a : (Ljava/lang/Throwable;)Ljava/lang/Throwable;
    //   1179: athrow
    //   1180: aload #15
    //   1182: bipush #7
    //   1184: iaload
    //   1185: aload #15
    //   1187: iconst_4
    //   1188: iaload
    //   1189: bipush #6
    //   1191: iushr
    //   1192: aload #15
    //   1194: iconst_4
    //   1195: iaload
    //   1196: bipush #26
    //   1198: ishl
    //   1199: ior
    //   1200: aload #15
    //   1202: iconst_4
    //   1203: iaload
    //   1204: bipush #11
    //   1206: iushr
    //   1207: aload #15
    //   1209: iconst_4
    //   1210: iaload
    //   1211: bipush #21
    //   1213: ishl
    //   1214: ior
    //   1215: ixor
    //   1216: aload #15
    //   1218: iconst_4
    //   1219: iaload
    //   1220: bipush #25
    //   1222: iushr
    //   1223: aload #15
    //   1225: iconst_4
    //   1226: iaload
    //   1227: bipush #7
    //   1229: ishl
    //   1230: ior
    //   1231: ixor
    //   1232: iadd
    //   1233: aload #15
    //   1235: bipush #6
    //   1237: iaload
    //   1238: aload #15
    //   1240: iconst_4
    //   1241: iaload
    //   1242: aload #15
    //   1244: iconst_5
    //   1245: iaload
    //   1246: aload #15
    //   1248: bipush #6
    //   1250: iaload
    //   1251: ixor
    //   1252: iand
    //   1253: ixor
    //   1254: iadd
    //   1255: aload #6
    //   1257: iload #16
    //   1259: iaload
    //   1260: iadd
    //   1261: aload #14
    //   1263: iload #16
    //   1265: iaload
    //   1266: iadd
    //   1267: istore #17
    //   1269: aload #15
    //   1271: iconst_0
    //   1272: iaload
    //   1273: iconst_2
    //   1274: iushr
    //   1275: aload #15
    //   1277: iconst_0
    //   1278: iaload
    //   1279: bipush #30
    //   1281: ishl
    //   1282: ior
    //   1283: aload #15
    //   1285: iconst_0
    //   1286: iaload
    //   1287: bipush #13
    //   1289: iushr
    //   1290: aload #15
    //   1292: iconst_0
    //   1293: iaload
    //   1294: bipush #19
    //   1296: ishl
    //   1297: ior
    //   1298: ixor
    //   1299: aload #15
    //   1301: iconst_0
    //   1302: iaload
    //   1303: bipush #22
    //   1305: iushr
    //   1306: aload #15
    //   1308: iconst_0
    //   1309: iaload
    //   1310: bipush #10
    //   1312: ishl
    //   1313: ior
    //   1314: ixor
    //   1315: aload #15
    //   1317: iconst_0
    //   1318: iaload
    //   1319: aload #15
    //   1321: iconst_1
    //   1322: iaload
    //   1323: iand
    //   1324: aload #15
    //   1326: iconst_2
    //   1327: iaload
    //   1328: aload #15
    //   1330: iconst_0
    //   1331: iaload
    //   1332: aload #15
    //   1334: iconst_1
    //   1335: iaload
    //   1336: ior
    //   1337: iand
    //   1338: ior
    //   1339: iadd
    //   1340: istore #18
    //   1342: aload #15
    //   1344: iconst_3
    //   1345: dup2
    //   1346: iaload
    //   1347: iload #17
    //   1349: iadd
    //   1350: iastore
    //   1351: aload #15
    //   1353: bipush #7
    //   1355: iload #17
    //   1357: iload #18
    //   1359: iadd
    //   1360: iastore
    //   1361: aload #15
    //   1363: bipush #7
    //   1365: iaload
    //   1366: istore #17
    //   1368: aload #15
    //   1370: bipush #7
    //   1372: aload #15
    //   1374: bipush #6
    //   1376: iaload
    //   1377: iastore
    //   1378: aload #15
    //   1380: bipush #6
    //   1382: aload #15
    //   1384: iconst_5
    //   1385: iaload
    //   1386: iastore
    //   1387: aload #15
    //   1389: iconst_5
    //   1390: aload #15
    //   1392: iconst_4
    //   1393: iaload
    //   1394: iastore
    //   1395: aload #15
    //   1397: iconst_4
    //   1398: aload #15
    //   1400: iconst_3
    //   1401: iaload
    //   1402: iastore
    //   1403: aload #15
    //   1405: iconst_3
    //   1406: aload #15
    //   1408: iconst_2
    //   1409: iaload
    //   1410: iastore
    //   1411: aload #15
    //   1413: iconst_2
    //   1414: aload #15
    //   1416: iconst_1
    //   1417: iaload
    //   1418: iastore
    //   1419: aload #15
    //   1421: iconst_1
    //   1422: aload #15
    //   1424: iconst_0
    //   1425: iaload
    //   1426: iastore
    //   1427: aload #15
    //   1429: iconst_0
    //   1430: iload #17
    //   1432: iastore
    //   1433: iinc #16, 1
    //   1436: iload_2
    //   1437: ifeq -> 945
    //   1440: iconst_0
    //   1441: istore #16
    //   1443: iload #16
    //   1445: bipush #8
    //   1447: if_icmpge -> 1470
    //   1450: aload #8
    //   1452: iload #16
    //   1454: dup2
    //   1455: iaload
    //   1456: aload #15
    //   1458: iload #16
    //   1460: iaload
    //   1461: iadd
    //   1462: iastore
    //   1463: iinc #16, 1
    //   1466: iload_2
    //   1467: ifeq -> 1443
    //   1470: iinc #13, 64
    //   1473: iinc #11, -64
    //   1476: iload_2
    //   1477: ifeq -> 867
    //   1480: iload #11
    //   1482: ifle -> 1517
    //   1485: iconst_0
    //   1486: istore #14
    //   1488: iload #14
    //   1490: iload #11
    //   1492: if_icmpge -> 1517
    //   1495: aload #9
    //   1497: iload #12
    //   1499: iload #14
    //   1501: iadd
    //   1502: aload_3
    //   1503: iload #13
    //   1505: iload #14
    //   1507: iadd
    //   1508: baload
    //   1509: bastore
    //   1510: iinc #14, 1
    //   1513: iload_2
    //   1514: ifeq -> 1488
    //   1517: aload #7
    //   1519: iconst_0
    //   1520: iaload
    //   1521: bipush #29
    //   1523: iushr
    //   1524: aload #7
    //   1526: iconst_1
    //   1527: iaload
    //   1528: iconst_3
    //   1529: ishl
    //   1530: ior
    //   1531: istore #14
    //   1533: aload #7
    //   1535: iconst_0
    //   1536: iaload
    //   1537: iconst_3
    //   1538: ishl
    //   1539: istore #15
    //   1541: aload #7
    //   1543: iconst_0
    //   1544: iaload
    //   1545: bipush #63
    //   1547: iand
    //   1548: istore #16
    //   1550: iload #16
    //   1552: bipush #56
    //   1554: if_icmpge -> 1569
    //   1557: bipush #56
    //   1559: iload #16
    //   1561: isub
    //   1562: goto -> 1574
    //   1565: invokestatic a : (Ljava/lang/Throwable;)Ljava/lang/Throwable;
    //   1568: athrow
    //   1569: bipush #120
    //   1571: iload #16
    //   1573: isub
    //   1574: istore #17
    //   1576: aload #7
    //   1578: iconst_0
    //   1579: iaload
    //   1580: bipush #63
    //   1582: iand
    //   1583: istore #12
    //   1585: bipush #64
    //   1587: iload #12
    //   1589: isub
    //   1590: istore #18
    //   1592: aload #7
    //   1594: iconst_0
    //   1595: dup2
    //   1596: iaload
    //   1597: iload #17
    //   1599: iadd
    //   1600: iastore
    //   1601: aload #7
    //   1603: iconst_0
    //   1604: dup2
    //   1605: iaload
    //   1606: iconst_m1
    //   1607: iand
    //   1608: iastore
    //   1609: aload #7
    //   1611: iconst_0
    //   1612: iaload
    //   1613: iload #17
    //   1615: if_icmpge -> 1633
    //   1618: aload #7
    //   1620: iconst_1
    //   1621: dup2
    //   1622: iaload
    //   1623: iconst_1
    //   1624: iadd
    //   1625: iastore
    //   1626: goto -> 1633
    //   1629: invokestatic a : (Ljava/lang/Throwable;)Ljava/lang/Throwable;
    //   1632: athrow
    //   1633: iconst_0
    //   1634: istore #13
    //   1636: iload #12
    //   1638: ifle -> 2269
    //   1641: iload #17
    //   1643: iload #18
    //   1645: if_icmplt -> 2269
    //   1648: goto -> 1655
    //   1651: invokestatic a : (Ljava/lang/Throwable;)Ljava/lang/Throwable;
    //   1654: athrow
    //   1655: iconst_0
    //   1656: istore #19
    //   1658: iload #19
    //   1660: iload #18
    //   1662: if_icmpge -> 1685
    //   1665: aload #9
    //   1667: iload #12
    //   1669: iload #19
    //   1671: iadd
    //   1672: aload #5
    //   1674: iload #19
    //   1676: baload
    //   1677: bastore
    //   1678: iinc #19, 1
    //   1681: iload_2
    //   1682: ifeq -> 1658
    //   1685: bipush #64
    //   1687: newarray int
    //   1689: astore #19
    //   1691: bipush #8
    //   1693: newarray int
    //   1695: astore #20
    //   1697: iconst_0
    //   1698: istore #21
    //   1700: iload #21
    //   1702: bipush #8
    //   1704: if_icmpge -> 1724
    //   1707: aload #20
    //   1709: iload #21
    //   1711: aload #8
    //   1713: iload #21
    //   1715: iaload
    //   1716: iastore
    //   1717: iinc #21, 1
    //   1720: iload_2
    //   1721: ifeq -> 1700
    //   1724: iconst_0
    //   1725: istore #21
    //   1727: iload #21
    //   1729: bipush #64
    //   1731: if_icmpge -> 2222
    //   1734: iload #21
    //   1736: bipush #16
    //   1738: if_icmpge -> 1819
    //   1741: aload #19
    //   1743: iload #21
    //   1745: aload #9
    //   1747: iconst_4
    //   1748: iload #21
    //   1750: imul
    //   1751: baload
    //   1752: sipush #255
    //   1755: iand
    //   1756: bipush #24
    //   1758: ishl
    //   1759: aload #9
    //   1761: iconst_4
    //   1762: iload #21
    //   1764: imul
    //   1765: iconst_1
    //   1766: iadd
    //   1767: baload
    //   1768: sipush #255
    //   1771: iand
    //   1772: bipush #16
    //   1774: ishl
    //   1775: ior
    //   1776: aload #9
    //   1778: iconst_4
    //   1779: iload #21
    //   1781: imul
    //   1782: iconst_2
    //   1783: iadd
    //   1784: baload
    //   1785: sipush #255
    //   1788: iand
    //   1789: bipush #8
    //   1791: ishl
    //   1792: ior
    //   1793: aload #9
    //   1795: iconst_4
    //   1796: iload #21
    //   1798: imul
    //   1799: iconst_3
    //   1800: iadd
    //   1801: baload
    //   1802: sipush #255
    //   1805: iand
    //   1806: ior
    //   1807: iastore
    //   1808: iload_2
    //   1809: ifeq -> 1962
    //   1812: goto -> 1819
    //   1815: invokestatic a : (Ljava/lang/Throwable;)Ljava/lang/Throwable;
    //   1818: athrow
    //   1819: aload #19
    //   1821: iload #21
    //   1823: aload #19
    //   1825: iload #21
    //   1827: iconst_2
    //   1828: isub
    //   1829: iaload
    //   1830: bipush #17
    //   1832: iushr
    //   1833: aload #19
    //   1835: iload #21
    //   1837: iconst_2
    //   1838: isub
    //   1839: iaload
    //   1840: bipush #15
    //   1842: ishl
    //   1843: ior
    //   1844: aload #19
    //   1846: iload #21
    //   1848: iconst_2
    //   1849: isub
    //   1850: iaload
    //   1851: bipush #19
    //   1853: iushr
    //   1854: aload #19
    //   1856: iload #21
    //   1858: iconst_2
    //   1859: isub
    //   1860: iaload
    //   1861: bipush #13
    //   1863: ishl
    //   1864: ior
    //   1865: ixor
    //   1866: aload #19
    //   1868: iload #21
    //   1870: iconst_2
    //   1871: isub
    //   1872: iaload
    //   1873: bipush #10
    //   1875: iushr
    //   1876: ixor
    //   1877: aload #19
    //   1879: iload #21
    //   1881: bipush #7
    //   1883: isub
    //   1884: iaload
    //   1885: iadd
    //   1886: aload #19
    //   1888: iload #21
    //   1890: bipush #15
    //   1892: isub
    //   1893: iaload
    //   1894: bipush #7
    //   1896: iushr
    //   1897: aload #19
    //   1899: iload #21
    //   1901: bipush #15
    //   1903: isub
    //   1904: iaload
    //   1905: bipush #25
    //   1907: ishl
    //   1908: ior
    //   1909: aload #19
    //   1911: iload #21
    //   1913: bipush #15
    //   1915: isub
    //   1916: iaload
    //   1917: bipush #18
    //   1919: iushr
    //   1920: aload #19
    //   1922: iload #21
    //   1924: bipush #15
    //   1926: isub
    //   1927: iaload
    //   1928: bipush #14
    //   1930: ishl
    //   1931: ior
    //   1932: ixor
    //   1933: aload #19
    //   1935: iload #21
    //   1937: bipush #15
    //   1939: isub
    //   1940: iaload
    //   1941: iconst_3
    //   1942: iushr
    //   1943: ixor
    //   1944: iadd
    //   1945: aload #19
    //   1947: iload #21
    //   1949: bipush #16
    //   1951: isub
    //   1952: iaload
    //   1953: iadd
    //   1954: iastore
    //   1955: goto -> 1962
    //   1958: invokestatic a : (Ljava/lang/Throwable;)Ljava/lang/Throwable;
    //   1961: athrow
    //   1962: aload #20
    //   1964: bipush #7
    //   1966: iaload
    //   1967: aload #20
    //   1969: iconst_4
    //   1970: iaload
    //   1971: bipush #6
    //   1973: iushr
    //   1974: aload #20
    //   1976: iconst_4
    //   1977: iaload
    //   1978: bipush #26
    //   1980: ishl
    //   1981: ior
    //   1982: aload #20
    //   1984: iconst_4
    //   1985: iaload
    //   1986: bipush #11
    //   1988: iushr
    //   1989: aload #20
    //   1991: iconst_4
    //   1992: iaload
    //   1993: bipush #21
    //   1995: ishl
    //   1996: ior
    //   1997: ixor
    //   1998: aload #20
    //   2000: iconst_4
    //   2001: iaload
    //   2002: bipush #25
    //   2004: iushr
    //   2005: aload #20
    //   2007: iconst_4
    //   2008: iaload
    //   2009: bipush #7
    //   2011: ishl
    //   2012: ior
    //   2013: ixor
    //   2014: iadd
    //   2015: aload #20
    //   2017: bipush #6
    //   2019: iaload
    //   2020: aload #20
    //   2022: iconst_4
    //   2023: iaload
    //   2024: aload #20
    //   2026: iconst_5
    //   2027: iaload
    //   2028: aload #20
    //   2030: bipush #6
    //   2032: iaload
    //   2033: ixor
    //   2034: iand
    //   2035: ixor
    //   2036: iadd
    //   2037: aload #6
    //   2039: iload #21
    //   2041: iaload
    //   2042: iadd
    //   2043: aload #19
    //   2045: iload #21
    //   2047: iaload
    //   2048: iadd
    //   2049: istore #22
    //   2051: aload #20
    //   2053: iconst_0
    //   2054: iaload
    //   2055: iconst_2
    //   2056: iushr
    //   2057: aload #20
    //   2059: iconst_0
    //   2060: iaload
    //   2061: bipush #30
    //   2063: ishl
    //   2064: ior
    //   2065: aload #20
    //   2067: iconst_0
    //   2068: iaload
    //   2069: bipush #13
    //   2071: iushr
    //   2072: aload #20
    //   2074: iconst_0
    //   2075: iaload
    //   2076: bipush #19
    //   2078: ishl
    //   2079: ior
    //   2080: ixor
    //   2081: aload #20
    //   2083: iconst_0
    //   2084: iaload
    //   2085: bipush #22
    //   2087: iushr
    //   2088: aload #20
    //   2090: iconst_0
    //   2091: iaload
    //   2092: bipush #10
    //   2094: ishl
    //   2095: ior
    //   2096: ixor
    //   2097: aload #20
    //   2099: iconst_0
    //   2100: iaload
    //   2101: aload #20
    //   2103: iconst_1
    //   2104: iaload
    //   2105: iand
    //   2106: aload #20
    //   2108: iconst_2
    //   2109: iaload
    //   2110: aload #20
    //   2112: iconst_0
    //   2113: iaload
    //   2114: aload #20
    //   2116: iconst_1
    //   2117: iaload
    //   2118: ior
    //   2119: iand
    //   2120: ior
    //   2121: iadd
    //   2122: istore #23
    //   2124: aload #20
    //   2126: iconst_3
    //   2127: dup2
    //   2128: iaload
    //   2129: iload #22
    //   2131: iadd
    //   2132: iastore
    //   2133: aload #20
    //   2135: bipush #7
    //   2137: iload #22
    //   2139: iload #23
    //   2141: iadd
    //   2142: iastore
    //   2143: aload #20
    //   2145: bipush #7
    //   2147: iaload
    //   2148: istore #22
    //   2150: aload #20
    //   2152: bipush #7
    //   2154: aload #20
    //   2156: bipush #6
    //   2158: iaload
    //   2159: iastore
    //   2160: aload #20
    //   2162: bipush #6
    //   2164: aload #20
    //   2166: iconst_5
    //   2167: iaload
    //   2168: iastore
    //   2169: aload #20
    //   2171: iconst_5
    //   2172: aload #20
    //   2174: iconst_4
    //   2175: iaload
    //   2176: iastore
    //   2177: aload #20
    //   2179: iconst_4
    //   2180: aload #20
    //   2182: iconst_3
    //   2183: iaload
    //   2184: iastore
    //   2185: aload #20
    //   2187: iconst_3
    //   2188: aload #20
    //   2190: iconst_2
    //   2191: iaload
    //   2192: iastore
    //   2193: aload #20
    //   2195: iconst_2
    //   2196: aload #20
    //   2198: iconst_1
    //   2199: iaload
    //   2200: iastore
    //   2201: aload #20
    //   2203: iconst_1
    //   2204: aload #20
    //   2206: iconst_0
    //   2207: iaload
    //   2208: iastore
    //   2209: aload #20
    //   2211: iconst_0
    //   2212: iload #22
    //   2214: iastore
    //   2215: iinc #21, 1
    //   2218: iload_2
    //   2219: ifeq -> 1727
    //   2222: iconst_0
    //   2223: istore #21
    //   2225: iload #21
    //   2227: bipush #8
    //   2229: if_icmpge -> 2252
    //   2232: aload #8
    //   2234: iload #21
    //   2236: dup2
    //   2237: iaload
    //   2238: aload #20
    //   2240: iload #21
    //   2242: iaload
    //   2243: iadd
    //   2244: iastore
    //   2245: iinc #21, 1
    //   2248: iload_2
    //   2249: ifeq -> 2225
    //   2252: iload #13
    //   2254: iload #18
    //   2256: iadd
    //   2257: istore #13
    //   2259: iload #17
    //   2261: iload #18
    //   2263: isub
    //   2264: istore #17
    //   2266: iconst_0
    //   2267: istore #12
    //   2269: iload #17
    //   2271: bipush #64
    //   2273: if_icmplt -> 2883
    //   2276: iconst_0
    //   2277: istore #19
    //   2279: iload #19
    //   2281: bipush #64
    //   2283: if_icmpge -> 2306
    //   2286: aload #10
    //   2288: iload #19
    //   2290: aload #5
    //   2292: iload #13
    //   2294: iload #19
    //   2296: iadd
    //   2297: baload
    //   2298: bastore
    //   2299: iinc #19, 1
    //   2302: iload_2
    //   2303: ifeq -> 2279
    //   2306: bipush #64
    //   2308: newarray int
    //   2310: astore #19
    //   2312: bipush #8
    //   2314: newarray int
    //   2316: astore #20
    //   2318: iconst_0
    //   2319: istore #21
    //   2321: iload #21
    //   2323: bipush #8
    //   2325: if_icmpge -> 2345
    //   2328: aload #20
    //   2330: iload #21
    //   2332: aload #8
    //   2334: iload #21
    //   2336: iaload
    //   2337: iastore
    //   2338: iinc #21, 1
    //   2341: iload_2
    //   2342: ifeq -> 2321
    //   2345: iconst_0
    //   2346: istore #21
    //   2348: iload #21
    //   2350: bipush #64
    //   2352: if_icmpge -> 2843
    //   2355: iload #21
    //   2357: bipush #16
    //   2359: if_icmpge -> 2440
    //   2362: aload #19
    //   2364: iload #21
    //   2366: aload #10
    //   2368: iconst_4
    //   2369: iload #21
    //   2371: imul
    //   2372: baload
    //   2373: sipush #255
    //   2376: iand
    //   2377: bipush #24
    //   2379: ishl
    //   2380: aload #10
    //   2382: iconst_4
    //   2383: iload #21
    //   2385: imul
    //   2386: iconst_1
    //   2387: iadd
    //   2388: baload
    //   2389: sipush #255
    //   2392: iand
    //   2393: bipush #16
    //   2395: ishl
    //   2396: ior
    //   2397: aload #10
    //   2399: iconst_4
    //   2400: iload #21
    //   2402: imul
    //   2403: iconst_2
    //   2404: iadd
    //   2405: baload
    //   2406: sipush #255
    //   2409: iand
    //   2410: bipush #8
    //   2412: ishl
    //   2413: ior
    //   2414: aload #10
    //   2416: iconst_4
    //   2417: iload #21
    //   2419: imul
    //   2420: iconst_3
    //   2421: iadd
    //   2422: baload
    //   2423: sipush #255
    //   2426: iand
    //   2427: ior
    //   2428: iastore
    //   2429: iload_2
    //   2430: ifeq -> 2583
    //   2433: goto -> 2440
    //   2436: invokestatic a : (Ljava/lang/Throwable;)Ljava/lang/Throwable;
    //   2439: athrow
    //   2440: aload #19
    //   2442: iload #21
    //   2444: aload #19
    //   2446: iload #21
    //   2448: iconst_2
    //   2449: isub
    //   2450: iaload
    //   2451: bipush #17
    //   2453: iushr
    //   2454: aload #19
    //   2456: iload #21
    //   2458: iconst_2
    //   2459: isub
    //   2460: iaload
    //   2461: bipush #15
    //   2463: ishl
    //   2464: ior
    //   2465: aload #19
    //   2467: iload #21
    //   2469: iconst_2
    //   2470: isub
    //   2471: iaload
    //   2472: bipush #19
    //   2474: iushr
    //   2475: aload #19
    //   2477: iload #21
    //   2479: iconst_2
    //   2480: isub
    //   2481: iaload
    //   2482: bipush #13
    //   2484: ishl
    //   2485: ior
    //   2486: ixor
    //   2487: aload #19
    //   2489: iload #21
    //   2491: iconst_2
    //   2492: isub
    //   2493: iaload
    //   2494: bipush #10
    //   2496: iushr
    //   2497: ixor
    //   2498: aload #19
    //   2500: iload #21
    //   2502: bipush #7
    //   2504: isub
    //   2505: iaload
    //   2506: iadd
    //   2507: aload #19
    //   2509: iload #21
    //   2511: bipush #15
    //   2513: isub
    //   2514: iaload
    //   2515: bipush #7
    //   2517: iushr
    //   2518: aload #19
    //   2520: iload #21
    //   2522: bipush #15
    //   2524: isub
    //   2525: iaload
    //   2526: bipush #25
    //   2528: ishl
    //   2529: ior
    //   2530: aload #19
    //   2532: iload #21
    //   2534: bipush #15
    //   2536: isub
    //   2537: iaload
    //   2538: bipush #18
    //   2540: iushr
    //   2541: aload #19
    //   2543: iload #21
    //   2545: bipush #15
    //   2547: isub
    //   2548: iaload
    //   2549: bipush #14
    //   2551: ishl
    //   2552: ior
    //   2553: ixor
    //   2554: aload #19
    //   2556: iload #21
    //   2558: bipush #15
    //   2560: isub
    //   2561: iaload
    //   2562: iconst_3
    //   2563: iushr
    //   2564: ixor
    //   2565: iadd
    //   2566: aload #19
    //   2568: iload #21
    //   2570: bipush #16
    //   2572: isub
    //   2573: iaload
    //   2574: iadd
    //   2575: iastore
    //   2576: goto -> 2583
    //   2579: invokestatic a : (Ljava/lang/Throwable;)Ljava/lang/Throwable;
    //   2582: athrow
    //   2583: aload #20
    //   2585: bipush #7
    //   2587: iaload
    //   2588: aload #20
    //   2590: iconst_4
    //   2591: iaload
    //   2592: bipush #6
    //   2594: iushr
    //   2595: aload #20
    //   2597: iconst_4
    //   2598: iaload
    //   2599: bipush #26
    //   2601: ishl
    //   2602: ior
    //   2603: aload #20
    //   2605: iconst_4
    //   2606: iaload
    //   2607: bipush #11
    //   2609: iushr
    //   2610: aload #20
    //   2612: iconst_4
    //   2613: iaload
    //   2614: bipush #21
    //   2616: ishl
    //   2617: ior
    //   2618: ixor
    //   2619: aload #20
    //   2621: iconst_4
    //   2622: iaload
    //   2623: bipush #25
    //   2625: iushr
    //   2626: aload #20
    //   2628: iconst_4
    //   2629: iaload
    //   2630: bipush #7
    //   2632: ishl
    //   2633: ior
    //   2634: ixor
    //   2635: iadd
    //   2636: aload #20
    //   2638: bipush #6
    //   2640: iaload
    //   2641: aload #20
    //   2643: iconst_4
    //   2644: iaload
    //   2645: aload #20
    //   2647: iconst_5
    //   2648: iaload
    //   2649: aload #20
    //   2651: bipush #6
    //   2653: iaload
    //   2654: ixor
    //   2655: iand
    //   2656: ixor
    //   2657: iadd
    //   2658: aload #6
    //   2660: iload #21
    //   2662: iaload
    //   2663: iadd
    //   2664: aload #19
    //   2666: iload #21
    //   2668: iaload
    //   2669: iadd
    //   2670: istore #22
    //   2672: aload #20
    //   2674: iconst_0
    //   2675: iaload
    //   2676: iconst_2
    //   2677: iushr
    //   2678: aload #20
    //   2680: iconst_0
    //   2681: iaload
    //   2682: bipush #30
    //   2684: ishl
    //   2685: ior
    //   2686: aload #20
    //   2688: iconst_0
    //   2689: iaload
    //   2690: bipush #13
    //   2692: iushr
    //   2693: aload #20
    //   2695: iconst_0
    //   2696: iaload
    //   2697: bipush #19
    //   2699: ishl
    //   2700: ior
    //   2701: ixor
    //   2702: aload #20
    //   2704: iconst_0
    //   2705: iaload
    //   2706: bipush #22
    //   2708: iushr
    //   2709: aload #20
    //   2711: iconst_0
    //   2712: iaload
    //   2713: bipush #10
    //   2715: ishl
    //   2716: ior
    //   2717: ixor
    //   2718: aload #20
    //   2720: iconst_0
    //   2721: iaload
    //   2722: aload #20
    //   2724: iconst_1
    //   2725: iaload
    //   2726: iand
    //   2727: aload #20
    //   2729: iconst_2
    //   2730: iaload
    //   2731: aload #20
    //   2733: iconst_0
    //   2734: iaload
    //   2735: aload #20
    //   2737: iconst_1
    //   2738: iaload
    //   2739: ior
    //   2740: iand
    //   2741: ior
    //   2742: iadd
    //   2743: istore #23
    //   2745: aload #20
    //   2747: iconst_3
    //   2748: dup2
    //   2749: iaload
    //   2750: iload #22
    //   2752: iadd
    //   2753: iastore
    //   2754: aload #20
    //   2756: bipush #7
    //   2758: iload #22
    //   2760: iload #23
    //   2762: iadd
    //   2763: iastore
    //   2764: aload #20
    //   2766: bipush #7
    //   2768: iaload
    //   2769: istore #22
    //   2771: aload #20
    //   2773: bipush #7
    //   2775: aload #20
    //   2777: bipush #6
    //   2779: iaload
    //   2780: iastore
    //   2781: aload #20
    //   2783: bipush #6
    //   2785: aload #20
    //   2787: iconst_5
    //   2788: iaload
    //   2789: iastore
    //   2790: aload #20
    //   2792: iconst_5
    //   2793: aload #20
    //   2795: iconst_4
    //   2796: iaload
    //   2797: iastore
    //   2798: aload #20
    //   2800: iconst_4
    //   2801: aload #20
    //   2803: iconst_3
    //   2804: iaload
    //   2805: iastore
    //   2806: aload #20
    //   2808: iconst_3
    //   2809: aload #20
    //   2811: iconst_2
    //   2812: iaload
    //   2813: iastore
    //   2814: aload #20
    //   2816: iconst_2
    //   2817: aload #20
    //   2819: iconst_1
    //   2820: iaload
    //   2821: iastore
    //   2822: aload #20
    //   2824: iconst_1
    //   2825: aload #20
    //   2827: iconst_0
    //   2828: iaload
    //   2829: iastore
    //   2830: aload #20
    //   2832: iconst_0
    //   2833: iload #22
    //   2835: iastore
    //   2836: iinc #21, 1
    //   2839: iload_2
    //   2840: ifeq -> 2348
    //   2843: iconst_0
    //   2844: istore #21
    //   2846: iload #21
    //   2848: bipush #8
    //   2850: if_icmpge -> 2873
    //   2853: aload #8
    //   2855: iload #21
    //   2857: dup2
    //   2858: iaload
    //   2859: aload #20
    //   2861: iload #21
    //   2863: iaload
    //   2864: iadd
    //   2865: iastore
    //   2866: iinc #21, 1
    //   2869: iload_2
    //   2870: ifeq -> 2846
    //   2873: iinc #13, 64
    //   2876: iinc #17, -64
    //   2879: iload_2
    //   2880: ifeq -> 2269
    //   2883: iload #17
    //   2885: ifle -> 2921
    //   2888: iconst_0
    //   2889: istore #19
    //   2891: iload #19
    //   2893: iload #17
    //   2895: if_icmpge -> 2921
    //   2898: aload #9
    //   2900: iload #12
    //   2902: iload #19
    //   2904: iadd
    //   2905: aload #5
    //   2907: iload #13
    //   2909: iload #19
    //   2911: iadd
    //   2912: baload
    //   2913: bastore
    //   2914: iinc #19, 1
    //   2917: iload_2
    //   2918: ifeq -> 2891
    //   2921: bipush #8
    //   2923: newarray byte
    //   2925: astore #19
    //   2927: aload #19
    //   2929: iconst_0
    //   2930: iload #14
    //   2932: bipush #24
    //   2934: iushr
    //   2935: i2b
    //   2936: bastore
    //   2937: aload #19
    //   2939: iconst_1
    //   2940: iload #14
    //   2942: bipush #16
    //   2944: iushr
    //   2945: i2b
    //   2946: bastore
    //   2947: aload #19
    //   2949: iconst_2
    //   2950: iload #14
    //   2952: bipush #8
    //   2954: iushr
    //   2955: i2b
    //   2956: bastore
    //   2957: aload #19
    //   2959: iconst_3
    //   2960: iload #14
    //   2962: i2b
    //   2963: bastore
    //   2964: aload #19
    //   2966: iconst_4
    //   2967: iload #15
    //   2969: bipush #24
    //   2971: iushr
    //   2972: i2b
    //   2973: bastore
    //   2974: aload #19
    //   2976: iconst_5
    //   2977: iload #15
    //   2979: bipush #16
    //   2981: iushr
    //   2982: i2b
    //   2983: bastore
    //   2984: aload #19
    //   2986: bipush #6
    //   2988: iload #15
    //   2990: bipush #8
    //   2992: iushr
    //   2993: i2b
    //   2994: bastore
    //   2995: aload #19
    //   2997: bipush #7
    //   2999: iload #15
    //   3001: i2b
    //   3002: bastore
    //   3003: bipush #8
    //   3005: istore #11
    //   3007: aload #7
    //   3009: iconst_0
    //   3010: iaload
    //   3011: bipush #63
    //   3013: iand
    //   3014: istore #12
    //   3016: bipush #64
    //   3018: iload #12
    //   3020: isub
    //   3021: istore #18
    //   3023: aload #7
    //   3025: iconst_0
    //   3026: dup2
    //   3027: iaload
    //   3028: iload #11
    //   3030: iadd
    //   3031: iastore
    //   3032: aload #7
    //   3034: iconst_0
    //   3035: dup2
    //   3036: iaload
    //   3037: iconst_m1
    //   3038: iand
    //   3039: iastore
    //   3040: aload #7
    //   3042: iconst_0
    //   3043: iaload
    //   3044: iload #11
    //   3046: if_icmpge -> 3064
    //   3049: aload #7
    //   3051: iconst_1
    //   3052: dup2
    //   3053: iaload
    //   3054: iconst_1
    //   3055: iadd
    //   3056: iastore
    //   3057: goto -> 3064
    //   3060: invokestatic a : (Ljava/lang/Throwable;)Ljava/lang/Throwable;
    //   3063: athrow
    //   3064: iload #12
    //   3066: ifle -> 3680
    //   3069: iload #11
    //   3071: iload #18
    //   3073: if_icmplt -> 3680
    //   3076: goto -> 3083
    //   3079: invokestatic a : (Ljava/lang/Throwable;)Ljava/lang/Throwable;
    //   3082: athrow
    //   3083: iconst_0
    //   3084: istore #20
    //   3086: iload #20
    //   3088: iload #18
    //   3090: if_icmpge -> 3113
    //   3093: aload #9
    //   3095: iload #12
    //   3097: iload #20
    //   3099: iadd
    //   3100: aload #19
    //   3102: iload #20
    //   3104: baload
    //   3105: bastore
    //   3106: iinc #20, 1
    //   3109: iload_2
    //   3110: ifeq -> 3086
    //   3113: bipush #64
    //   3115: newarray int
    //   3117: astore #20
    //   3119: bipush #8
    //   3121: newarray int
    //   3123: astore #21
    //   3125: iconst_0
    //   3126: istore #22
    //   3128: iload #22
    //   3130: bipush #8
    //   3132: if_icmpge -> 3152
    //   3135: aload #21
    //   3137: iload #22
    //   3139: aload #8
    //   3141: iload #22
    //   3143: iaload
    //   3144: iastore
    //   3145: iinc #22, 1
    //   3148: iload_2
    //   3149: ifeq -> 3128
    //   3152: iconst_0
    //   3153: istore #22
    //   3155: iload #22
    //   3157: bipush #64
    //   3159: if_icmpge -> 3650
    //   3162: iload #22
    //   3164: bipush #16
    //   3166: if_icmpge -> 3247
    //   3169: aload #20
    //   3171: iload #22
    //   3173: aload #9
    //   3175: iconst_4
    //   3176: iload #22
    //   3178: imul
    //   3179: baload
    //   3180: sipush #255
    //   3183: iand
    //   3184: bipush #24
    //   3186: ishl
    //   3187: aload #9
    //   3189: iconst_4
    //   3190: iload #22
    //   3192: imul
    //   3193: iconst_1
    //   3194: iadd
    //   3195: baload
    //   3196: sipush #255
    //   3199: iand
    //   3200: bipush #16
    //   3202: ishl
    //   3203: ior
    //   3204: aload #9
    //   3206: iconst_4
    //   3207: iload #22
    //   3209: imul
    //   3210: iconst_2
    //   3211: iadd
    //   3212: baload
    //   3213: sipush #255
    //   3216: iand
    //   3217: bipush #8
    //   3219: ishl
    //   3220: ior
    //   3221: aload #9
    //   3223: iconst_4
    //   3224: iload #22
    //   3226: imul
    //   3227: iconst_3
    //   3228: iadd
    //   3229: baload
    //   3230: sipush #255
    //   3233: iand
    //   3234: ior
    //   3235: iastore
    //   3236: iload_2
    //   3237: ifeq -> 3390
    //   3240: goto -> 3247
    //   3243: invokestatic a : (Ljava/lang/Throwable;)Ljava/lang/Throwable;
    //   3246: athrow
    //   3247: aload #20
    //   3249: iload #22
    //   3251: aload #20
    //   3253: iload #22
    //   3255: iconst_2
    //   3256: isub
    //   3257: iaload
    //   3258: bipush #17
    //   3260: iushr
    //   3261: aload #20
    //   3263: iload #22
    //   3265: iconst_2
    //   3266: isub
    //   3267: iaload
    //   3268: bipush #15
    //   3270: ishl
    //   3271: ior
    //   3272: aload #20
    //   3274: iload #22
    //   3276: iconst_2
    //   3277: isub
    //   3278: iaload
    //   3279: bipush #19
    //   3281: iushr
    //   3282: aload #20
    //   3284: iload #22
    //   3286: iconst_2
    //   3287: isub
    //   3288: iaload
    //   3289: bipush #13
    //   3291: ishl
    //   3292: ior
    //   3293: ixor
    //   3294: aload #20
    //   3296: iload #22
    //   3298: iconst_2
    //   3299: isub
    //   3300: iaload
    //   3301: bipush #10
    //   3303: iushr
    //   3304: ixor
    //   3305: aload #20
    //   3307: iload #22
    //   3309: bipush #7
    //   3311: isub
    //   3312: iaload
    //   3313: iadd
    //   3314: aload #20
    //   3316: iload #22
    //   3318: bipush #15
    //   3320: isub
    //   3321: iaload
    //   3322: bipush #7
    //   3324: iushr
    //   3325: aload #20
    //   3327: iload #22
    //   3329: bipush #15
    //   3331: isub
    //   3332: iaload
    //   3333: bipush #25
    //   3335: ishl
    //   3336: ior
    //   3337: aload #20
    //   3339: iload #22
    //   3341: bipush #15
    //   3343: isub
    //   3344: iaload
    //   3345: bipush #18
    //   3347: iushr
    //   3348: aload #20
    //   3350: iload #22
    //   3352: bipush #15
    //   3354: isub
    //   3355: iaload
    //   3356: bipush #14
    //   3358: ishl
    //   3359: ior
    //   3360: ixor
    //   3361: aload #20
    //   3363: iload #22
    //   3365: bipush #15
    //   3367: isub
    //   3368: iaload
    //   3369: iconst_3
    //   3370: iushr
    //   3371: ixor
    //   3372: iadd
    //   3373: aload #20
    //   3375: iload #22
    //   3377: bipush #16
    //   3379: isub
    //   3380: iaload
    //   3381: iadd
    //   3382: iastore
    //   3383: goto -> 3390
    //   3386: invokestatic a : (Ljava/lang/Throwable;)Ljava/lang/Throwable;
    //   3389: athrow
    //   3390: aload #21
    //   3392: bipush #7
    //   3394: iaload
    //   3395: aload #21
    //   3397: iconst_4
    //   3398: iaload
    //   3399: bipush #6
    //   3401: iushr
    //   3402: aload #21
    //   3404: iconst_4
    //   3405: iaload
    //   3406: bipush #26
    //   3408: ishl
    //   3409: ior
    //   3410: aload #21
    //   3412: iconst_4
    //   3413: iaload
    //   3414: bipush #11
    //   3416: iushr
    //   3417: aload #21
    //   3419: iconst_4
    //   3420: iaload
    //   3421: bipush #21
    //   3423: ishl
    //   3424: ior
    //   3425: ixor
    //   3426: aload #21
    //   3428: iconst_4
    //   3429: iaload
    //   3430: bipush #25
    //   3432: iushr
    //   3433: aload #21
    //   3435: iconst_4
    //   3436: iaload
    //   3437: bipush #7
    //   3439: ishl
    //   3440: ior
    //   3441: ixor
    //   3442: iadd
    //   3443: aload #21
    //   3445: bipush #6
    //   3447: iaload
    //   3448: aload #21
    //   3450: iconst_4
    //   3451: iaload
    //   3452: aload #21
    //   3454: iconst_5
    //   3455: iaload
    //   3456: aload #21
    //   3458: bipush #6
    //   3460: iaload
    //   3461: ixor
    //   3462: iand
    //   3463: ixor
    //   3464: iadd
    //   3465: aload #6
    //   3467: iload #22
    //   3469: iaload
    //   3470: iadd
    //   3471: aload #20
    //   3473: iload #22
    //   3475: iaload
    //   3476: iadd
    //   3477: istore #23
    //   3479: aload #21
    //   3481: iconst_0
    //   3482: iaload
    //   3483: iconst_2
    //   3484: iushr
    //   3485: aload #21
    //   3487: iconst_0
    //   3488: iaload
    //   3489: bipush #30
    //   3491: ishl
    //   3492: ior
    //   3493: aload #21
    //   3495: iconst_0
    //   3496: iaload
    //   3497: bipush #13
    //   3499: iushr
    //   3500: aload #21
    //   3502: iconst_0
    //   3503: iaload
    //   3504: bipush #19
    //   3506: ishl
    //   3507: ior
    //   3508: ixor
    //   3509: aload #21
    //   3511: iconst_0
    //   3512: iaload
    //   3513: bipush #22
    //   3515: iushr
    //   3516: aload #21
    //   3518: iconst_0
    //   3519: iaload
    //   3520: bipush #10
    //   3522: ishl
    //   3523: ior
    //   3524: ixor
    //   3525: aload #21
    //   3527: iconst_0
    //   3528: iaload
    //   3529: aload #21
    //   3531: iconst_1
    //   3532: iaload
    //   3533: iand
    //   3534: aload #21
    //   3536: iconst_2
    //   3537: iaload
    //   3538: aload #21
    //   3540: iconst_0
    //   3541: iaload
    //   3542: aload #21
    //   3544: iconst_1
    //   3545: iaload
    //   3546: ior
    //   3547: iand
    //   3548: ior
    //   3549: iadd
    //   3550: istore #24
    //   3552: aload #21
    //   3554: iconst_3
    //   3555: dup2
    //   3556: iaload
    //   3557: iload #23
    //   3559: iadd
    //   3560: iastore
    //   3561: aload #21
    //   3563: bipush #7
    //   3565: iload #23
    //   3567: iload #24
    //   3569: iadd
    //   3570: iastore
    //   3571: aload #21
    //   3573: bipush #7
    //   3575: iaload
    //   3576: istore #23
    //   3578: aload #21
    //   3580: bipush #7
    //   3582: aload #21
    //   3584: bipush #6
    //   3586: iaload
    //   3587: iastore
    //   3588: aload #21
    //   3590: bipush #6
    //   3592: aload #21
    //   3594: iconst_5
    //   3595: iaload
    //   3596: iastore
    //   3597: aload #21
    //   3599: iconst_5
    //   3600: aload #21
    //   3602: iconst_4
    //   3603: iaload
    //   3604: iastore
    //   3605: aload #21
    //   3607: iconst_4
    //   3608: aload #21
    //   3610: iconst_3
    //   3611: iaload
    //   3612: iastore
    //   3613: aload #21
    //   3615: iconst_3
    //   3616: aload #21
    //   3618: iconst_2
    //   3619: iaload
    //   3620: iastore
    //   3621: aload #21
    //   3623: iconst_2
    //   3624: aload #21
    //   3626: iconst_1
    //   3627: iaload
    //   3628: iastore
    //   3629: aload #21
    //   3631: iconst_1
    //   3632: aload #21
    //   3634: iconst_0
    //   3635: iaload
    //   3636: iastore
    //   3637: aload #21
    //   3639: iconst_0
    //   3640: iload #23
    //   3642: iastore
    //   3643: iinc #22, 1
    //   3646: iload_2
    //   3647: ifeq -> 3155
    //   3650: iconst_0
    //   3651: istore #22
    //   3653: iload #22
    //   3655: bipush #8
    //   3657: if_icmpge -> 3680
    //   3660: aload #8
    //   3662: iload #22
    //   3664: dup2
    //   3665: iaload
    //   3666: aload #21
    //   3668: iload #22
    //   3670: iaload
    //   3671: iadd
    //   3672: iastore
    //   3673: iinc #22, 1
    //   3676: iload_2
    //   3677: ifeq -> 3653
    //   3680: bipush #32
    //   3682: newarray byte
    //   3684: astore #4
    //   3686: aload #4
    //   3688: iconst_0
    //   3689: aload #8
    //   3691: iconst_0
    //   3692: iaload
    //   3693: bipush #24
    //   3695: iushr
    //   3696: i2b
    //   3697: bastore
    //   3698: aload #4
    //   3700: iconst_1
    //   3701: aload #8
    //   3703: iconst_0
    //   3704: iaload
    //   3705: bipush #16
    //   3707: iushr
    //   3708: i2b
    //   3709: bastore
    //   3710: aload #4
    //   3712: iconst_2
    //   3713: aload #8
    //   3715: iconst_0
    //   3716: iaload
    //   3717: bipush #8
    //   3719: iushr
    //   3720: i2b
    //   3721: bastore
    //   3722: aload #4
    //   3724: iconst_3
    //   3725: aload #8
    //   3727: iconst_0
    //   3728: iaload
    //   3729: i2b
    //   3730: bastore
    //   3731: aload #4
    //   3733: iconst_4
    //   3734: aload #8
    //   3736: iconst_1
    //   3737: iaload
    //   3738: bipush #24
    //   3740: iushr
    //   3741: i2b
    //   3742: bastore
    //   3743: aload #4
    //   3745: iconst_5
    //   3746: aload #8
    //   3748: iconst_1
    //   3749: iaload
    //   3750: bipush #16
    //   3752: iushr
    //   3753: i2b
    //   3754: bastore
    //   3755: aload #4
    //   3757: bipush #6
    //   3759: aload #8
    //   3761: iconst_1
    //   3762: iaload
    //   3763: bipush #8
    //   3765: iushr
    //   3766: i2b
    //   3767: bastore
    //   3768: aload #4
    //   3770: bipush #7
    //   3772: aload #8
    //   3774: iconst_1
    //   3775: iaload
    //   3776: i2b
    //   3777: bastore
    //   3778: aload #4
    //   3780: bipush #8
    //   3782: aload #8
    //   3784: iconst_2
    //   3785: iaload
    //   3786: bipush #24
    //   3788: iushr
    //   3789: i2b
    //   3790: bastore
    //   3791: aload #4
    //   3793: bipush #9
    //   3795: aload #8
    //   3797: iconst_2
    //   3798: iaload
    //   3799: bipush #16
    //   3801: iushr
    //   3802: i2b
    //   3803: bastore
    //   3804: aload #4
    //   3806: bipush #10
    //   3808: aload #8
    //   3810: iconst_2
    //   3811: iaload
    //   3812: bipush #8
    //   3814: iushr
    //   3815: i2b
    //   3816: bastore
    //   3817: aload #4
    //   3819: bipush #11
    //   3821: aload #8
    //   3823: iconst_2
    //   3824: iaload
    //   3825: i2b
    //   3826: bastore
    //   3827: aload #4
    //   3829: bipush #12
    //   3831: aload #8
    //   3833: iconst_3
    //   3834: iaload
    //   3835: bipush #24
    //   3837: iushr
    //   3838: i2b
    //   3839: bastore
    //   3840: aload #4
    //   3842: bipush #13
    //   3844: aload #8
    //   3846: iconst_3
    //   3847: iaload
    //   3848: bipush #16
    //   3850: iushr
    //   3851: i2b
    //   3852: bastore
    //   3853: aload #4
    //   3855: bipush #14
    //   3857: aload #8
    //   3859: iconst_3
    //   3860: iaload
    //   3861: bipush #8
    //   3863: iushr
    //   3864: i2b
    //   3865: bastore
    //   3866: aload #4
    //   3868: bipush #15
    //   3870: aload #8
    //   3872: iconst_3
    //   3873: iaload
    //   3874: i2b
    //   3875: bastore
    //   3876: aload #4
    //   3878: bipush #16
    //   3880: aload #8
    //   3882: iconst_4
    //   3883: iaload
    //   3884: bipush #24
    //   3886: iushr
    //   3887: i2b
    //   3888: bastore
    //   3889: aload #4
    //   3891: bipush #17
    //   3893: aload #8
    //   3895: iconst_4
    //   3896: iaload
    //   3897: bipush #16
    //   3899: iushr
    //   3900: i2b
    //   3901: bastore
    //   3902: aload #4
    //   3904: bipush #18
    //   3906: aload #8
    //   3908: iconst_4
    //   3909: iaload
    //   3910: bipush #8
    //   3912: iushr
    //   3913: i2b
    //   3914: bastore
    //   3915: aload #4
    //   3917: bipush #19
    //   3919: aload #8
    //   3921: iconst_4
    //   3922: iaload
    //   3923: i2b
    //   3924: bastore
    //   3925: aload #4
    //   3927: bipush #20
    //   3929: aload #8
    //   3931: iconst_5
    //   3932: iaload
    //   3933: bipush #24
    //   3935: iushr
    //   3936: i2b
    //   3937: bastore
    //   3938: aload #4
    //   3940: bipush #21
    //   3942: aload #8
    //   3944: iconst_5
    //   3945: iaload
    //   3946: bipush #16
    //   3948: iushr
    //   3949: i2b
    //   3950: bastore
    //   3951: aload #4
    //   3953: bipush #22
    //   3955: aload #8
    //   3957: iconst_5
    //   3958: iaload
    //   3959: bipush #8
    //   3961: iushr
    //   3962: i2b
    //   3963: bastore
    //   3964: aload #4
    //   3966: bipush #23
    //   3968: aload #8
    //   3970: iconst_5
    //   3971: iaload
    //   3972: i2b
    //   3973: bastore
    //   3974: aload #4
    //   3976: bipush #24
    //   3978: aload #8
    //   3980: bipush #6
    //   3982: iaload
    //   3983: bipush #24
    //   3985: iushr
    //   3986: i2b
    //   3987: bastore
    //   3988: aload #4
    //   3990: bipush #25
    //   3992: aload #8
    //   3994: bipush #6
    //   3996: iaload
    //   3997: bipush #16
    //   3999: iushr
    //   4000: i2b
    //   4001: bastore
    //   4002: aload #4
    //   4004: bipush #26
    //   4006: aload #8
    //   4008: bipush #6
    //   4010: iaload
    //   4011: bipush #8
    //   4013: iushr
    //   4014: i2b
    //   4015: bastore
    //   4016: aload #4
    //   4018: bipush #27
    //   4020: aload #8
    //   4022: bipush #6
    //   4024: iaload
    //   4025: i2b
    //   4026: bastore
    //   4027: aload #4
    //   4029: bipush #28
    //   4031: aload #8
    //   4033: bipush #7
    //   4035: iaload
    //   4036: bipush #24
    //   4038: iushr
    //   4039: i2b
    //   4040: bastore
    //   4041: aload #4
    //   4043: bipush #29
    //   4045: aload #8
    //   4047: bipush #7
    //   4049: iaload
    //   4050: bipush #16
    //   4052: iushr
    //   4053: i2b
    //   4054: bastore
    //   4055: aload #4
    //   4057: bipush #30
    //   4059: aload #8
    //   4061: bipush #7
    //   4063: iaload
    //   4064: bipush #8
    //   4066: iushr
    //   4067: i2b
    //   4068: bastore
    //   4069: aload #4
    //   4071: bipush #31
    //   4073: aload #8
    //   4075: bipush #7
    //   4077: iaload
    //   4078: i2b
    //   4079: bastore
    //   4080: new java/math/BigInteger
    //   4083: dup
    //   4084: aload #4
    //   4086: invokespecial <init> : ([B)V
    //   4089: invokevirtual abs : ()Ljava/math/BigInteger;
    //   4092: putstatic burp/Zmt7.Z_ : Ljava/lang/Object;
    //   4095: getstatic burp/Zz3w.ZX : Ljava/lang/Object;
    //   4098: checkcast java/math/BigInteger
    //   4101: invokevirtual toByteArray : ()[B
    //   4104: astore_3
    //   4105: new java/lang/StringBuilder
    //   4108: dup
    //   4109: invokespecial <init> : ()V
    //   4112: astore #5
    //   4114: aload #5
    //   4116: sipush #10413
    //   4119: sipush #7924
    //   4122: invokestatic a : (II)Ljava/lang/String;
    //   4125: invokevirtual append : (Ljava/lang/String;)Ljava/lang/StringBuilder;
    //   4128: pop
    //   4129: aload_3
    //   4130: astore #6
    //   4132: aload #6
    //   4134: arraylength
    //   4135: istore #7
    //   4137: iconst_0
    //   4138: istore #8
    //   4140: iload #8
    //   4142: iload #7
    //   4144: if_icmpge -> 4170
    //   4147: aload #6
    //   4149: iload #8
    //   4151: baload
    //   4152: istore #9
    //   4154: aload #5
    //   4156: iload #9
    //   4158: i2c
    //   4159: invokevirtual append : (C)Ljava/lang/StringBuilder;
    //   4162: pop
    //   4163: iinc #8, 1
    //   4166: iload_2
    //   4167: ifeq -> 4140
    //   4170: aload #5
    //   4172: sipush #10403
    //   4175: sipush #-11971
    //   4178: invokestatic a : (II)Ljava/lang/String;
    //   4181: ldc ''
    //   4183: invokestatic getProperty : (Ljava/lang/String;Ljava/lang/String;)Ljava/lang/String;
    //   4186: invokevirtual toLowerCase : ()Ljava/lang/String;
    //   4189: invokevirtual append : (Ljava/lang/String;)Ljava/lang/StringBuilder;
    //   4192: pop
    //   4193: aload #5
    //   4195: sipush #10409
    //   4198: sipush #9302
    //   4201: invokestatic a : (II)Ljava/lang/String;
    //   4204: ldc ''
    //   4206: invokestatic getProperty : (Ljava/lang/String;Ljava/lang/String;)Ljava/lang/String;
    //   4209: invokevirtual toLowerCase : ()Ljava/lang/String;
    //   4212: invokevirtual append : (Ljava/lang/String;)Ljava/lang/StringBuilder;
    //   4215: pop
    //   4216: aload #5
    //   4218: invokevirtual toString : ()Ljava/lang/String;
    //   4221: invokevirtual getBytes : ()[B
    //   4224: astore #4
    //   4226: aload #4
    //   4228: astore_3
    //   4229: aload_3
    //   4230: arraylength
    //   4231: bipush #8
    //   4233: iadd
    //   4234: bipush #6
    //   4236: ishr
    //   4237: iconst_1
    //   4238: iadd
    //   4239: bipush #16
    //   4241: imul
    //   4242: newarray int
    //   4244: astore #5
    //   4246: iconst_0
    //   4247: istore #6
    //   4249: iload #6
    //   4251: aload_3
    //   4252: arraylength
    //   4253: if_icmpge -> 4296
    //   4256: aload_3
    //   4257: iload #6
    //   4259: baload
    //   4260: sipush #255
    //   4263: iand
    //   4264: istore #7
    //   4266: aload #5
    //   4268: iload #6
    //   4270: iconst_2
    //   4271: ishr
    //   4272: dup2
    //   4273: iaload
    //   4274: iload #7
    //   4276: bipush #24
    //   4278: iload #6
    //   4280: iconst_4
    //   4281: irem
    //   4282: bipush #8
    //   4284: imul
    //   4285: isub
    //   4286: ishl
    //   4287: ior
    //   4288: iastore
    //   4289: iinc #6, 1
    //   4292: iload_2
    //   4293: ifeq -> 4249
    //   4296: aload #5
    //   4298: iload #6
    //   4300: iconst_2
    //   4301: ishr
    //   4302: dup2
    //   4303: iaload
    //   4304: sipush #128
    //   4307: bipush #24
    //   4309: iload #6
    //   4311: iconst_4
    //   4312: irem
    //   4313: bipush #8
    //   4315: imul
    //   4316: isub
    //   4317: ishl
    //   4318: ior
    //   4319: iastore
    //   4320: aload #5
    //   4322: aload #5
    //   4324: arraylength
    //   4325: iconst_1
    //   4326: isub
    //   4327: aload_3
    //   4328: arraylength
    //   4329: bipush #8
    //   4331: imul
    //   4332: iastore
    //   4333: bipush #80
    //   4335: newarray int
    //   4337: astore #7
    //   4339: ldc 1732584193
    //   4341: istore #8
    //   4343: ldc -271733879
    //   4345: istore #9
    //   4347: ldc -1732584194
    //   4349: istore #10
    //   4351: ldc 271733878
    //   4353: istore #11
    //   4355: ldc -1009589776
    //   4357: istore #12
    //   4359: iconst_0
    //   4360: istore #6
    //   4362: iload #6
    //   4364: aload #5
    //   4366: arraylength
    //   4367: if_icmpge -> 4689
    //   4370: iload #8
    //   4372: istore #13
    //   4374: iload #9
    //   4376: istore #14
    //   4378: iload #10
    //   4380: istore #15
    //   4382: iload #11
    //   4384: istore #16
    //   4386: iload #12
    //   4388: istore #17
    //   4390: iconst_0
    //   4391: istore #18
    //   4393: iload #18
    //   4395: bipush #80
    //   4397: if_icmpge -> 4647
    //   4400: iload #18
    //   4402: bipush #16
    //   4404: if_icmpge -> 4431
    //   4407: aload #7
    //   4409: iload #18
    //   4411: aload #5
    //   4413: iload #6
    //   4415: iload #18
    //   4417: iadd
    //   4418: iaload
    //   4419: iastore
    //   4420: iload_2
    //   4421: ifeq -> 4486
    //   4424: goto -> 4431
    //   4427: invokestatic a : (Ljava/lang/Throwable;)Ljava/lang/Throwable;
    //   4430: athrow
    //   4431: aload #7
    //   4433: iload #18
    //   4435: iconst_3
    //   4436: isub
    //   4437: iaload
    //   4438: aload #7
    //   4440: iload #18
    //   4442: bipush #8
    //   4444: isub
    //   4445: iaload
    //   4446: ixor
    //   4447: aload #7
    //   4449: iload #18
    //   4451: bipush #14
    //   4453: isub
    //   4454: iaload
    //   4455: ixor
    //   4456: aload #7
    //   4458: iload #18
    //   4460: bipush #16
    //   4462: isub
    //   4463: iaload
    //   4464: ixor
    //   4465: istore #19
    //   4467: iload #19
    //   4469: iconst_1
    //   4470: ishl
    //   4471: iload #19
    //   4473: bipush #31
    //   4475: iushr
    //   4476: ior
    //   4477: istore #20
    //   4479: aload #7
    //   4481: iload #18
    //   4483: iload #20
    //   4485: iastore
    //   4486: iload #8
    //   4488: iconst_5
    //   4489: ishl
    //   4490: iload #8
    //   4492: bipush #27
    //   4494: iushr
    //   4495: ior
    //   4496: istore #19
    //   4498: iload #19
    //   4500: iload #12
    //   4502: iadd
    //   4503: aload #7
    //   4505: iload #18
    //   4507: iaload
    //   4508: iadd
    //   4509: iload #18
    //   4511: bipush #20
    //   4513: if_icmpge -> 4539
    //   4516: ldc 1518500249
    //   4518: iload #9
    //   4520: iload #10
    //   4522: iand
    //   4523: iload #9
    //   4525: iconst_m1
    //   4526: ixor
    //   4527: iload #11
    //   4529: iand
    //   4530: ior
    //   4531: iadd
    //   4532: goto -> 4609
    //   4535: invokestatic a : (Ljava/lang/Throwable;)Ljava/lang/Throwable;
    //   4538: athrow
    //   4539: iload #18
    //   4541: bipush #40
    //   4543: if_icmpge -> 4564
    //   4546: ldc 1859775393
    //   4548: iload #9
    //   4550: iload #10
    //   4552: ixor
    //   4553: iload #11
    //   4555: ixor
    //   4556: iadd
    //   4557: goto -> 4609
    //   4560: invokestatic a : (Ljava/lang/Throwable;)Ljava/lang/Throwable;
    //   4563: athrow
    //   4564: iload #18
    //   4566: bipush #60
    //   4568: if_icmpge -> 4598
    //   4571: ldc -1894007588
    //   4573: iload #9
    //   4575: iload #10
    //   4577: iand
    //   4578: iload #9
    //   4580: iload #11
    //   4582: iand
    //   4583: ior
    //   4584: iload #10
    //   4586: iload #11
    //   4588: iand
    //   4589: ior
    //   4590: iadd
    //   4591: goto -> 4609
    //   4594: invokestatic a : (Ljava/lang/Throwable;)Ljava/lang/Throwable;
    //   4597: athrow
    //   4598: ldc -899497514
    //   4600: iload #9
    //   4602: iload #10
    //   4604: ixor
    //   4605: iload #11
    //   4607: ixor
    //   4608: iadd
    //   4609: iadd
    //   4610: istore #20
    //   4612: iload #11
    //   4614: istore #12
    //   4616: iload #10
    //   4618: istore #11
    //   4620: iload #9
    //   4622: bipush #30
    //   4624: ishl
    //   4625: iload #9
    //   4627: iconst_2
    //   4628: iushr
    //   4629: ior
    //   4630: istore #10
    //   4632: iload #8
    //   4634: istore #9
    //   4636: iload #20
    //   4638: istore #8
    //   4640: iinc #18, 1
    //   4643: iload_2
    //   4644: ifeq -> 4393
    //   4647: iload #8
    //   4649: iload #13
    //   4651: iadd
    //   4652: istore #8
    //   4654: iload #9
    //   4656: iload #14
    //   4658: iadd
    //   4659: istore #9
    //   4661: iload #10
    //   4663: iload #15
    //   4665: iadd
    //   4666: istore #10
    //   4668: iload #11
    //   4670: iload #16
    //   4672: iadd
    //   4673: istore #11
    //   4675: iload #12
    //   4677: iload #17
    //   4679: iadd
    //   4680: istore #12
    //   4682: iinc #6, 16
    //   4685: iload_2
    //   4686: ifeq -> 4362
    //   4689: iconst_5
    //   4690: newarray int
    //   4692: dup
    //   4693: iconst_0
    //   4694: iload #8
    //   4696: iastore
    //   4697: dup
    //   4698: iconst_1
    //   4699: iload #9
    //   4701: iastore
    //   4702: dup
    //   4703: iconst_2
    //   4704: iload #10
    //   4706: iastore
    //   4707: dup
    //   4708: iconst_3
    //   4709: iload #11
    //   4711: iastore
    //   4712: dup
    //   4713: iconst_4
    //   4714: iload #12
    //   4716: iastore
    //   4717: astore #13
    //   4719: bipush #20
    //   4721: newarray byte
    //   4723: astore #14
    //   4725: iconst_0
    //   4726: istore #15
    //   4728: iload #15
    //   4730: bipush #20
    //   4732: if_icmpge -> 4773
    //   4735: aload #13
    //   4737: iload #15
    //   4739: iconst_4
    //   4740: idiv
    //   4741: iaload
    //   4742: istore #16
    //   4744: iconst_3
    //   4745: iload #15
    //   4747: iconst_4
    //   4748: irem
    //   4749: isub
    //   4750: bipush #8
    //   4752: imul
    //   4753: istore #17
    //   4755: aload #14
    //   4757: iload #15
    //   4759: iload #16
    //   4761: iload #17
    //   4763: iushr
    //   4764: i2b
    //   4765: bastore
    //   4766: iinc #15, 1
    //   4769: iload_2
    //   4770: ifeq -> 4728
    //   4773: aload #14
    //   4775: astore #4
    //   4777: sipush #10411
    //   4780: sipush #-13342
    //   4783: invokestatic a : (II)Ljava/lang/String;
    //   4786: iconst_1
    //   4787: ldc burp/Zkw
    //   4789: invokevirtual getClassLoader : ()Ljava/lang/ClassLoader;
    //   4792: invokestatic forName : (Ljava/lang/String;ZLjava/lang/ClassLoader;)Ljava/lang/Class;
    //   4795: invokevirtual getDeclaredFields : ()[Ljava/lang/reflect/Field;
    //   4798: astore_3
    //   4799: aload_3
    //   4800: arraylength
    //   4801: istore #4
    //   4803: iconst_0
    //   4804: istore #5
    //   4806: iload #5
    //   4808: iload #4
    //   4810: if_icmpge -> 4947
    //   4813: aload_3
    //   4814: iload #5
    //   4816: aaload
    //   4817: astore #6
    //   4819: aload #6
    //   4821: invokevirtual getModifiers : ()I
    //   4824: invokestatic isStatic : (I)Z
    //   4827: ifne -> 4837
    //   4830: goto -> 4940
    //   4833: invokestatic a : (Ljava/lang/Throwable;)Ljava/lang/Throwable;
    //   4836: athrow
    //   4837: aload #6
    //   4839: invokevirtual getType : ()Ljava/lang/Class;
    //   4842: astore #7
    //   4844: aload #7
    //   4846: ifnull -> 4927
    //   4849: aload #7
    //   4851: invokevirtual isPrimitive : ()Z
    //   4854: ifne -> 4927
    //   4857: goto -> 4864
    //   4860: invokestatic a : (Ljava/lang/Throwable;)Ljava/lang/Throwable;
    //   4863: athrow
    //   4864: aload #7
    //   4866: invokevirtual getPackage : ()Ljava/lang/Package;
    //   4869: ifnull -> 4927
    //   4872: goto -> 4879
    //   4875: invokestatic a : (Ljava/lang/Throwable;)Ljava/lang/Throwable;
    //   4878: athrow
    //   4879: aload #7
    //   4881: invokevirtual getPackage : ()Ljava/lang/Package;
    //   4884: invokevirtual getName : ()Ljava/lang/String;
    //   4887: ifnull -> 4927
    //   4890: goto -> 4897
    //   4893: invokestatic a : (Ljava/lang/Throwable;)Ljava/lang/Throwable;
    //   4896: athrow
    //   4897: aload #7
    //   4899: invokevirtual getPackage : ()Ljava/lang/Package;
    //   4902: invokevirtual getName : ()Ljava/lang/String;
    //   4905: sipush #10410
    //   4908: sipush #-6575
    //   4911: invokestatic a : (II)Ljava/lang/String;
    //   4914: invokevirtual startsWith : (Ljava/lang/String;)Z
    //   4917: ifne -> 4927
    //   4920: goto -> 4927
    //   4923: invokestatic a : (Ljava/lang/Throwable;)Ljava/lang/Throwable;
    //   4926: athrow
    //   4927: aload #6
    //   4929: iconst_1
    //   4930: invokevirtual setAccessible : (Z)V
    //   4933: aload #6
    //   4935: aconst_null
    //   4936: invokevirtual get : (Ljava/lang/Object;)Ljava/lang/Object;
    //   4939: pop
    //   4940: iinc #5, 1
    //   4943: iload_2
    //   4944: ifeq -> 4806
    //   4947: sipush #10402
    //   4950: sipush #13465
    //   4953: invokestatic a : (II)Ljava/lang/String;
    //   4956: invokestatic forName : (Ljava/lang/String;)Ljava/lang/Class;
    //   4959: invokevirtual getDeclaredMethods : ()[Ljava/lang/reflect/Method;
    //   4962: astore_3
    //   4963: aload_3
    //   4964: arraylength
    //   4965: istore #4
    //   4967: iconst_0
    //   4968: istore #5
    //   4970: iload #5
    //   4972: iload #4
    //   4974: if_icmpge -> 5085
    //   4977: aload_3
    //   4978: iload #5
    //   4980: aaload
    //   4981: astore #6
    //   4983: aload #6
    //   4985: invokevirtual getParameterTypes : ()[Ljava/lang/Class;
    //   4988: pop
    //   4989: aload #6
    //   4991: invokevirtual getModifiers : ()I
    //   4994: invokestatic isStatic : (I)Z
    //   4997: ifeq -> 5071
    //   5000: aload #6
    //   5002: invokevirtual getParameterTypes : ()[Ljava/lang/Class;
    //   5005: arraylength
    //   5006: iconst_2
    //   5007: if_icmpne -> 5071
    //   5010: goto -> 5017
    //   5013: invokestatic a : (Ljava/lang/Throwable;)Ljava/lang/Throwable;
    //   5016: athrow
    //   5017: aload #6
    //   5019: invokevirtual getReturnType : ()Ljava/lang/Class;
    //   5022: getstatic java/lang/Boolean.TYPE : Ljava/lang/Class;
    //   5025: if_acmpne -> 5071
    //   5028: goto -> 5035
    //   5031: invokestatic a : (Ljava/lang/Throwable;)Ljava/lang/Throwable;
    //   5034: athrow
    //   5035: aload #6
    //   5037: iconst_1
    //   5038: invokevirtual setAccessible : (Z)V
    //   5041: aload #6
    //   5043: aconst_null
    //   5044: iconst_2
    //   5045: anewarray java/lang/Object
    //   5048: dup
    //   5049: iconst_0
    //   5050: aload_0
    //   5051: aastore
    //   5052: dup
    //   5053: iconst_1
    //   5054: aload_1
    //   5055: aastore
    //   5056: invokevirtual invoke : (Ljava/lang/Object;[Ljava/lang/Object;)Ljava/lang/Object;
    //   5059: pop
    //   5060: iload_2
    //   5061: ifeq -> 5085
    //   5064: goto -> 5071
    //   5067: invokestatic a : (Ljava/lang/Throwable;)Ljava/lang/Throwable;
    //   5070: athrow
    //   5071: iinc #5, 1
    //   5074: iload_2
    //   5075: ifeq -> 4970
    //   5078: goto -> 5085
    //   5081: invokestatic a : (Ljava/lang/Throwable;)Ljava/lang/Throwable;
    //   5084: athrow
    //   5085: sipush #10415
    //   5088: sipush #3655
    //   5091: invokestatic a : (II)Ljava/lang/String;
    //   5094: iconst_1
    //   5095: ldc burp/Zsji
    //   5097: invokevirtual getClassLoader : ()Ljava/lang/ClassLoader;
    //   5100: invokestatic forName : (Ljava/lang/String;ZLjava/lang/ClassLoader;)Ljava/lang/Class;
    //   5103: invokevirtual getDeclaredFields : ()[Ljava/lang/reflect/Field;
    //   5106: astore_3
    //   5107: aload_3
    //   5108: arraylength
    //   5109: istore #4
    //   5111: iconst_0
    //   5112: istore #5
    //   5114: iload #5
    //   5116: iload #4
    //   5118: if_icmpge -> 5255
    //   5121: aload_3
    //   5122: iload #5
    //   5124: aaload
    //   5125: astore #6
    //   5127: aload #6
    //   5129: invokevirtual getModifiers : ()I
    //   5132: invokestatic isStatic : (I)Z
    //   5135: ifne -> 5145
    //   5138: goto -> 5248
    //   5141: invokestatic a : (Ljava/lang/Throwable;)Ljava/lang/Throwable;
    //   5144: athrow
    //   5145: aload #6
    //   5147: invokevirtual getType : ()Ljava/lang/Class;
    //   5150: astore #7
    //   5152: aload #7
    //   5154: ifnull -> 5235
    //   5157: aload #7
    //   5159: invokevirtual isPrimitive : ()Z
    //   5162: ifne -> 5235
    //   5165: goto -> 5172
    //   5168: invokestatic a : (Ljava/lang/Throwable;)Ljava/lang/Throwable;
    //   5171: athrow
    //   5172: aload #7
    //   5174: invokevirtual getPackage : ()Ljava/lang/Package;
    //   5177: ifnull -> 5235
    //   5180: goto -> 5187
    //   5183: invokestatic a : (Ljava/lang/Throwable;)Ljava/lang/Throwable;
    //   5186: athrow
    //   5187: aload #7
    //   5189: invokevirtual getPackage : ()Ljava/lang/Package;
    //   5192: invokevirtual getName : ()Ljava/lang/String;
    //   5195: ifnull -> 5235
    //   5198: goto -> 5205
    //   5201: invokestatic a : (Ljava/lang/Throwable;)Ljava/lang/Throwable;
    //   5204: athrow
    //   5205: aload #7
    //   5207: invokevirtual getPackage : ()Ljava/lang/Package;
    //   5210: invokevirtual getName : ()Ljava/lang/String;
    //   5213: sipush #10414
    //   5216: sipush #6988
    //   5219: invokestatic a : (II)Ljava/lang/String;
    //   5222: invokevirtual startsWith : (Ljava/lang/String;)Z
    //   5225: ifne -> 5235
    //   5228: goto -> 5235
    //   5231: invokestatic a : (Ljava/lang/Throwable;)Ljava/lang/Throwable;
    //   5234: athrow
    //   5235: aload #6
    //   5237: iconst_1
    //   5238: invokevirtual setAccessible : (Z)V
    //   5241: aload #6
    //   5243: aconst_null
    //   5244: invokevirtual get : (Ljava/lang/Object;)Ljava/lang/Object;
    //   5247: pop
    //   5248: iinc #5, 1
    //   5251: iload_2
    //   5252: ifeq -> 5114
    //   5255: sipush #10408
    //   5258: sipush #11714
    //   5261: invokestatic a : (II)Ljava/lang/String;
    //   5264: invokestatic forName : (Ljava/lang/String;)Ljava/lang/Class;
    //   5267: invokevirtual getDeclaredMethods : ()[Ljava/lang/reflect/Method;
    //   5270: astore_3
    //   5271: aload_3
    //   5272: arraylength
    //   5273: istore #4
    //   5275: iconst_0
    //   5276: istore #5
    //   5278: iload #5
    //   5280: iload #4
    //   5282: if_icmpge -> 5414
    //   5285: aload_3
    //   5286: iload #5
    //   5288: aaload
    //   5289: astore #6
    //   5291: aload #6
    //   5293: invokevirtual getParameterTypes : ()[Ljava/lang/Class;
    //   5296: pop
    //   5297: aload #6
    //   5299: invokevirtual getModifiers : ()I
    //   5302: invokestatic isStatic : (I)Z
    //   5305: ifeq -> 5400
    //   5308: aload #6
    //   5310: invokevirtual getParameterTypes : ()[Ljava/lang/Class;
    //   5313: arraylength
    //   5314: iconst_2
    //   5315: if_icmpne -> 5400
    //   5318: goto -> 5325
    //   5321: invokestatic a : (Ljava/lang/Throwable;)Ljava/lang/Throwable;
    //   5324: athrow
    //   5325: aload #6
    //   5327: invokevirtual getReturnType : ()Ljava/lang/Class;
    //   5330: getstatic java/lang/Void.TYPE : Ljava/lang/Class;
    //   5333: invokevirtual equals : (Ljava/lang/Object;)Z
    //   5336: ifeq -> 5400
    //   5339: goto -> 5346
    //   5342: invokestatic a : (Ljava/lang/Throwable;)Ljava/lang/Throwable;
    //   5345: athrow
    //   5346: aload #6
    //   5348: iconst_1
    //   5349: invokevirtual setAccessible : (Z)V
    //   5352: aload #6
    //   5354: aconst_null
    //   5355: iconst_2
    //   5356: anewarray java/lang/Object
    //   5359: dup
    //   5360: iconst_0
    //   5361: aload_0
    //   5362: aastore
    //   5363: dup
    //   5364: iconst_1
    //   5365: aload_1
    //   5366: ifnonnull -> 5384
    //   5369: goto -> 5376
    //   5372: invokestatic a : (Ljava/lang/Throwable;)Ljava/lang/Throwable;
    //   5375: athrow
    //   5376: aload_1
    //   5377: goto -> 5391
    //   5380: invokestatic a : (Ljava/lang/Throwable;)Ljava/lang/Throwable;
    //   5383: athrow
    //   5384: aload_1
    //   5385: checkcast [B
    //   5388: invokevirtual clone : ()Ljava/lang/Object;
    //   5391: aastore
    //   5392: invokevirtual invoke : (Ljava/lang/Object;[Ljava/lang/Object;)Ljava/lang/Object;
    //   5395: pop
    //   5396: iload_2
    //   5397: ifeq -> 5414
    //   5400: iinc #5, 1
    //   5403: iload_2
    //   5404: ifeq -> 5278
    //   5407: goto -> 5414
    //   5410: invokestatic a : (Ljava/lang/Throwable;)Ljava/lang/Throwable;
    //   5413: athrow
    //   5414: getstatic burp/Zx4w.Zo : Ljava/lang/String;
    //   5417: getstatic burp/Zkvr.Zb : Ljava/lang/Object;
    //   5420: checkcast java/math/BigInteger
    //   5423: invokevirtual intValue : ()I
    //   5426: bipush #32
    //   5428: irem
    //   5429: invokestatic abs : (I)I
    //   5432: invokevirtual charAt : (I)C
    //   5435: getstatic burp/Zm6g.ZG : Ljava/lang/String;
    //   5438: getstatic burp/Zgz1.ZX : Ljava/lang/Object;
    //   5441: checkcast java/math/BigInteger
    //   5444: invokevirtual intValue : ()I
    //   5447: bipush #32
    //   5449: irem
    //   5450: invokestatic abs : (I)I
    //   5453: invokevirtual charAt : (I)C
    //   5456: if_icmpgt -> 5571
    //   5459: getstatic burp/Zb3z.Zi : Ljava/lang/String;
    //   5462: getstatic burp/Zm6g.ZO : Ljava/lang/Object;
    //   5465: checkcast java/math/BigInteger
    //   5468: invokevirtual intValue : ()I
    //   5471: bipush #32
    //   5473: irem
    //   5474: invokestatic abs : (I)I
    //   5477: invokevirtual charAt : (I)C
    //   5480: getstatic burp/Zmy3.ZP : Ljava/lang/String;
    //   5483: getstatic burp/Zxtn.ZY : Ljava/lang/Object;
    //   5486: checkcast java/math/BigInteger
    //   5489: invokevirtual intValue : ()I
    //   5492: bipush #32
    //   5494: irem
    //   5495: invokestatic abs : (I)I
    //   5498: invokevirtual charAt : (I)C
    //   5501: if_icmpgt -> 5571
    //   5504: goto -> 5511
    //   5507: invokestatic a : (Ljava/lang/Throwable;)Ljava/lang/Throwable;
    //   5510: athrow
    //   5511: getstatic burp/Ztpg.Zr : Ljava/lang/String;
    //   5514: getstatic burp/Zl15.Zn : Ljava/lang/Object;
    //   5517: checkcast java/math/BigInteger
    //   5520: invokevirtual intValue : ()I
    //   5523: bipush #32
    //   5525: irem
    //   5526: invokestatic abs : (I)I
    //   5529: invokevirtual charAt : (I)C
    //   5532: getstatic burp/Zrjg.Zl : Ljava/lang/String;
    //   5535: getstatic burp/Zgk1.ZD : Ljava/lang/Object;
    //   5538: checkcast java/math/BigInteger
    //   5541: invokevirtual intValue : ()I
    //   5544: bipush #32
    //   5546: irem
    //   5547: invokestatic abs : (I)I
    //   5550: invokevirtual charAt : (I)C
    //   5553: if_icmple -> 5571
    //   5556: goto -> 5563
    //   5559: invokestatic a : (Ljava/lang/Throwable;)Ljava/lang/Throwable;
    //   5562: athrow
    //   5563: iconst_1
    //   5564: goto -> 5572
    //   5567: invokestatic a : (Ljava/lang/Throwable;)Ljava/lang/Throwable;
    //   5570: athrow
    //   5571: iconst_0
    //   5572: ireturn
    //   5573: astore_3
    //   5574: new java/lang/Exception
    //   5577: dup
    //   5578: aload_3
    //   5579: invokevirtual getMessage : ()Ljava/lang/String;
    //   5582: invokespecial <init> : (Ljava/lang/String;)V
    //   5585: athrow
    // Exception table:
    //   from	to	target	type
    //   4	5572	5573	java/lang/Throwable
    //   823	857	860	java/lang/Throwable
    //   952	1030	1033	java/lang/Throwable
    //   959	1173	1176	java/lang/Throwable
    //   1550	1565	1565	java/lang/Throwable
    //   1592	1626	1629	java/lang/Throwable
    //   1636	1648	1651	java/lang/Throwable
    //   1734	1812	1815	java/lang/Throwable
    //   1741	1955	1958	java/lang/Throwable
    //   2355	2433	2436	java/lang/Throwable
    //   2362	2576	2579	java/lang/Throwable
    //   3023	3057	3060	java/lang/Throwable
    //   3064	3076	3079	java/lang/Throwable
    //   3162	3240	3243	java/lang/Throwable
    //   3169	3383	3386	java/lang/Throwable
    //   4400	4424	4427	java/lang/Throwable
    //   4498	4535	4535	java/lang/Throwable
    //   4539	4560	4560	java/lang/Throwable
    //   4564	4594	4594	java/lang/Throwable
    //   4819	4833	4833	java/lang/Throwable
    //   4844	4857	4860	java/lang/Throwable
    //   4849	4872	4875	java/lang/Throwable
    //   4864	4890	4893	java/lang/Throwable
    //   4879	4920	4923	java/lang/Throwable
    //   4983	5010	5013	java/lang/Throwable
    //   5000	5028	5031	java/lang/Throwable
    //   5017	5064	5067	java/lang/Throwable
    //   5035	5078	5081	java/lang/Throwable
    //   5127	5141	5141	java/lang/Throwable
    //   5152	5165	5168	java/lang/Throwable
    //   5157	5180	5183	java/lang/Throwable
    //   5172	5198	5201	java/lang/Throwable
    //   5187	5228	5231	java/lang/Throwable
    //   5291	5318	5321	java/lang/Throwable
    //   5308	5339	5342	java/lang/Throwable
    //   5325	5369	5372	java/lang/Throwable
    //   5346	5380	5380	java/lang/Throwable
    //   5391	5407	5410	java/lang/Throwable
    //   5414	5504	5507	java/lang/Throwable
    //   5459	5556	5559	java/lang/Throwable
    //   5511	5567	5567	java/lang/Throwable
  }
  
  static void Zx(Object paramObject) {
    Zlna.Zo = a(10412, 12284);
    Zlna.ZG = new BigInteger(a(10401, -7398));
    boolean bool = Zt2e.ZK();
    try {
      try {
        if (Zmrc.Zx.charAt(Math.abs(((BigInteger)Zm5p.Ze).intValue() % 32)) > Zbzc.ZL.charAt(Math.abs(((BigInteger)Zmji.ZB).intValue() % 32))) {
          try {
            Zz75.ZI(Class.forName(a(10407, -11421)));
            if (bool)
              Zrml.Zd(Class.forName(a(10406, -24298))); 
          } catch (Throwable throwable) {
            throw a(null);
          } 
          return;
        } 
      } catch (Throwable throwable) {
        throw a(null);
      } 
      Zrml.Zd(Class.forName(a(10406, -24298)));
    } catch (Throwable throwable) {}
  }
  
  static void ZV(Object[] paramArrayOfObject, Object paramObject) throws Throwable {}
  
  static {
    // Byte code:
    //   0: bipush #14
    //   2: anewarray java/lang/String
    //   5: astore #5
    //   7: iconst_0
    //   8: istore_3
    //   9: ldc ''5G?\\t|7ku\\tdsF\\tLf@E (n9+j.u\\rYY&\\n1n< e\\b(URD-uG/]~H\\t=p"\\tM\+JJ.bao\\f0 DKiXO;d|$[Kn2! 6[}m;alvsfQfr'
    //   11: dup
    //   12: astore_2
    //   13: invokevirtual length : ()I
    //   16: istore #4
    //   18: bipush #9
    //   20: istore_1
    //   21: iconst_m1
    //   22: istore_0
    //   23: bipush #33
    //   25: iinc #0, 1
    //   28: aload_2
    //   29: iload_0
    //   30: dup
    //   31: iload_1
    //   32: iadd
    //   33: invokevirtual substring : (II)Ljava/lang/String;
    //   36: iconst_m1
    //   37: goto -> 143
    //   40: aload #5
    //   42: swap
    //   43: iload_3
    //   44: iinc #3, 1
    //   47: swap
    //   48: aastore
    //   49: iload_0
    //   50: iload_1
    //   51: iadd
    //   52: dup
    //   53: istore_0
    //   54: iload #4
    //   56: if_icmpge -> 68
    //   59: aload_2
    //   60: iload_0
    //   61: invokevirtual charAt : (I)C
    //   64: istore_1
    //   65: goto -> 23
    //   68: ldc '-\\tX\\t3C='
    //   70: dup
    //   71: astore_2
    //   72: invokevirtual length : ()I
    //   75: istore #4
    //   77: bipush #9
    //   79: istore_1
    //   80: iconst_m1
    //   81: istore_0
    //   82: bipush #112
    //   84: iinc #0, 1
    //   87: aload_2
    //   88: iload_0
    //   89: dup
    //   90: iload_1
    //   91: iadd
    //   92: invokevirtual substring : (II)Ljava/lang/String;
    //   95: iconst_0
    //   96: goto -> 143
    //   99: aload #5
    //   101: swap
    //   102: iload_3
    //   103: iinc #3, 1
    //   106: swap
    //   107: aastore
    //   108: iload_0
    //   109: iload_1
    //   110: iadd
    //   111: dup
    //   112: istore_0
    //   113: iload #4
    //   115: if_icmpge -> 127
    //   118: aload_2
    //   119: iload_0
    //   120: invokevirtual charAt : (I)C
    //   123: istore_1
    //   124: goto -> 82
    //   127: aload #5
    //   129: putstatic burp/Znp.a : [Ljava/lang/String;
    //   132: bipush #14
    //   134: anewarray java/lang/String
    //   137: putstatic burp/Znp.b : [Ljava/lang/String;
    //   140: goto -> 300
    //   143: dup_x2
    //   144: pop
    //   145: invokevirtual toCharArray : ()[C
    //   148: dup_x1
    //   149: arraylength
    //   150: dup_x2
    //   151: pop
    //   152: iconst_0
    //   153: istore #6
    //   155: dup2_x1
    //   156: pop2
    //   157: dup_x2
    //   158: iconst_1
    //   159: if_icmpgt -> 260
    //   162: dup2
    //   163: swap
    //   164: iload #6
    //   166: dup2_x1
    //   167: caload
    //   168: swap
    //   169: iload #6
    //   171: bipush #7
    //   173: irem
    //   174: tableswitch default -> 242, 0 -> 212, 1 -> 217, 2 -> 222, 3 -> 227, 4 -> 232, 5 -> 237
    //   212: bipush #77
    //   214: goto -> 244
    //   217: bipush #117
    //   219: goto -> 244
    //   222: bipush #39
    //   224: goto -> 244
    //   227: bipush #113
    //   229: goto -> 244
    //   232: bipush #58
    //   234: goto -> 244
    //   237: bipush #104
    //   239: goto -> 244
    //   242: bipush #20
    //   244: ixor
    //   245: ixor
    //   246: i2c
    //   247: castore
    //   248: iinc #6, 1
    //   251: dup
    //   252: ifne -> 260
    //   255: dup2
    //   256: dup_x1
    //   257: goto -> 166
    //   260: dup2_x1
    //   261: pop2
    //   262: dup_x2
    //   263: iload #6
    //   265: if_icmpgt -> 162
    //   268: pop
    //   269: new java/lang/String
    //   272: dup_x1
    //   273: swap
    //   274: invokespecial <init> : ([C)V
    //   277: invokevirtual intern : ()Ljava/lang/String;
    //   280: swap
    //   281: pop
    //   282: swap
    //   283: tableswitch default -> 40, 0 -> 99
    //   300: sipush #10400
    //   303: sipush #27628
    //   306: invokestatic a : (II)Ljava/lang/String;
    //   309: putstatic burp/Znp.Zr : Ljava/lang/String;
    //   312: new java/math/BigInteger
    //   315: dup
    //   316: bipush #32
    //   318: newarray byte
    //   320: dup
    //   321: iconst_0
    //   322: bipush #48
    //   324: bastore
    //   325: dup
    //   326: iconst_1
    //   327: bipush #-35
    //   329: bastore
    //   330: dup
    //   331: iconst_2
    //   332: bipush #-19
    //   334: bastore
    //   335: dup
    //   336: iconst_3
    //   337: bipush #-15
    //   339: bastore
    //   340: dup
    //   341: iconst_4
    //   342: bipush #-40
    //   344: bastore
    //   345: dup
    //   346: iconst_5
    //   347: bipush #-113
    //   349: bastore
    //   350: dup
    //   351: bipush #6
    //   353: bipush #-70
    //   355: bastore
    //   356: dup
    //   357: bipush #7
    //   359: bipush #-87
    //   361: bastore
    //   362: dup
    //   363: bipush #8
    //   365: bipush #81
    //   367: bastore
    //   368: dup
    //   369: bipush #9
    //   371: bipush #-30
    //   373: bastore
    //   374: dup
    //   375: bipush #10
    //   377: bipush #21
    //   379: bastore
    //   380: dup
    //   381: bipush #11
    //   383: bipush #67
    //   385: bastore
    //   386: dup
    //   387: bipush #12
    //   389: bipush #15
    //   391: bastore
    //   392: dup
    //   393: bipush #13
    //   395: iconst_2
    //   396: bastore
    //   397: dup
    //   398: bipush #14
    //   400: bipush #44
    //   402: bastore
    //   403: dup
    //   404: bipush #15
    //   406: bipush #-41
    //   408: bastore
    //   409: dup
    //   410: bipush #16
    //   412: bipush #86
    //   414: bastore
    //   415: dup
    //   416: bipush #17
    //   418: bipush #-18
    //   420: bastore
    //   421: dup
    //   422: bipush #18
    //   424: bipush #-39
    //   426: bastore
    //   427: dup
    //   428: bipush #19
    //   430: bipush #19
    //   432: bastore
    //   433: dup
    //   434: bipush #20
    //   436: bipush #-62
    //   438: bastore
    //   439: dup
    //   440: bipush #21
    //   442: bipush #-84
    //   444: bastore
    //   445: dup
    //   446: bipush #22
    //   448: bipush #-75
    //   450: bastore
    //   451: dup
    //   452: bipush #23
    //   454: bipush #127
    //   456: bastore
    //   457: dup
    //   458: bipush #24
    //   460: bipush #18
    //   462: bastore
    //   463: dup
    //   464: bipush #25
    //   466: bipush #-95
    //   468: bastore
    //   469: dup
    //   470: bipush #26
    //   472: bipush #-119
    //   474: bastore
    //   475: dup
    //   476: bipush #27
    //   478: bipush #20
    //   480: bastore
    //   481: dup
    //   482: bipush #28
    //   484: bipush #28
    //   486: bastore
    //   487: dup
    //   488: bipush #29
    //   490: bipush #-78
    //   492: bastore
    //   493: dup
    //   494: bipush #30
    //   496: bipush #-24
    //   498: bastore
    //   499: dup
    //   500: bipush #31
    //   502: bipush #83
    //   504: bastore
    //   505: invokespecial <init> : ([B)V
    //   508: putstatic burp/Znp.ZJ : Ljava/lang/Object;
    //   511: return
  }
  
  private static Throwable a(Throwable paramThrowable) {
    return paramThrowable;
  }
  
  private static String a(int paramInt1, int paramInt2) {
    int i = (paramInt1 ^ 0x28AB) & 0xFFFF;
    if (b[i] == null) {
      char[] arrayOfChar = a[i].toCharArray();
      switch (arrayOfChar[0] & 0xFF) {
        case 0:
        
        case 1:
        
        case 2:
        
        case 3:
        
        case 4:
        
        case 5:
        
        case 6:
        
        case 7:
        
        case 8:
        
        case 9:
        
        case 10:
        
        case 11:
        
        case 12:
        
        case 13:
        
        case 14:
        
        case 15:
        
        case 16:
        
        case 17:
        
        case 18:
        
        case 19:
        
        case 20:
        
        case 21:
        
        case 22:
        
        case 23:
        
        case 24:
        
        case 25:
        
        case 26:
        
        case 27:
        
        case 28:
        
        case 29:
        
        case 30:
        
        case 31:
        
        case 32:
        
        case 33:
        
        case 34:
        
        case 35:
        
        case 36:
        
        case 37:
        
        case 38:
        
        case 39:
        
        case 40:
        
        case 41:
        
        case 42:
        
        case 43:
        
        case 44:
        
        case 45:
        
        case 46:
        
        case 47:
        
        case 48:
        
        case 49:
        
        case 50:
        
        case 51:
        
        case 52:
        
        case 53:
        
        case 54:
        
        case 55:
        
        case 56:
        
        case 57:
        
        case 58:
        
        case 59:
        
        case 60:
        
        case 61:
        
        case 62:
        
        case 63:
        
        case 64:
        
        case 65:
        
        case 66:
        
        case 67:
        
        case 68:
        
        case 69:
        
        case 70:
        
        case 71:
        
        case 72:
        
        case 73:
        
        case 74:
        
        case 75:
        
        case 76:
        
        case 77:
        
        case 78:
        
        case 79:
        
        case 80:
        
        case 81:
        
        case 82:
        
        case 83:
        
        case 84:
        
        case 85:
        
        case 86:
        
        case 87:
        
        case 88:
        
        case 89:
        
        case 90:
        
        case 91:
        
        case 92:
        
        case 93:
        
        case 94:
        
        case 95:
        
        case 96:
        
        case 97:
        
        case 98:
        
        case 99:
        
        case 100:
        
        case 101:
        
        case 102:
        
        case 103:
        
        case 104:
        
        case 105:
        
        case 106:
        
        case 107:
        
        case 108:
        
        case 109:
        
        case 110:
        
        case 111:
        
        case 112:
        
        case 113:
        
        case 114:
        
        case 115:
        
        case 116:
        
        case 117:
        
        case 118:
        
        case 119:
        
        case 120:
        
        case 121:
        
        case 122:
        
        case 123:
        
        case 124:
        
        case 125:
        
        case 126:
        
        case 127:
        
        case 128:
        
        case 129:
        
        case 130:
        
        case 131:
        
        case 132:
        
        case 133:
        
        case 134:
        
        case 135:
        
        case 136:
        
        case 137:
        
        case 138:
        
        case 139:
        
        case 140:
        
        case 141:
        
        case 142:
        
        case 143:
        
        case 144:
        
        case 145:
        
        case 146:
        
        case 147:
        
        case 148:
        
        case 149:
        
        case 150:
        
        case 151:
        
        case 152:
        
        case 153:
        
        case 154:
        
        case 155:
        
        case 156:
        
        case 157:
        
        case 158:
        
        case 159:
        
        case 160:
        
        case 161:
        
        case 162:
        
        case 163:
        
        case 164:
        
        case 165:
        
        case 166:
        
        case 167:
        
        case 168:
        
        case 169:
        
        case 170:
        
        case 171:
        
        case 172:
        
        case 173:
        
        case 174:
        
        case 175:
        
        case 176:
        
        case 177:
        
        case 178:
        
        case 179:
        
        case 180:
        
        case 181:
        
        case 182:
        
        case 183:
        
        case 184:
        
        case 185:
        
        case 186:
        
        case 187:
        
        case 188:
        
        case 189:
        
        case 190:
        
        case 191:
        
        case 192:
        
        case 193:
        
        case 194:
        
        case 195:
        
        case 196:
        
        case 197:
        
        case 198:
        
        case 199:
        
        case 200:
        
        case 201:
        
        case 202:
        
        case 203:
        
        case 204:
        
        case 205:
        
        case 206:
        
        case 207:
        
        case 208:
        
        case 209:
        
        case 210:
        
        case 211:
        
        case 212:
        
        case 213:
        
        case 214:
        
        case 215:
        
        case 216:
        
        case 217:
        
        case 218:
        
        case 219:
        
        case 220:
        
        case 221:
        
        case 222:
        
        case 223:
        
        case 224:
        
        case 225:
        
        case 226:
        
        case 227:
        
        case 228:
        
        case 229:
        
        case 230:
        
        case 231:
        
        case 232:
        
        case 233:
        
        case 234:
        
        case 235:
        
        case 236:
        
        case 237:
        
        case 238:
        
        case 239:
        
        case 240:
        
        case 241:
        
        case 242:
        
        case 243:
        
        case 244:
        
        case 245:
        
        case 246:
        
        case 247:
        
        case 248:
        
        case 249:
        
        case 250:
        
        case 251:
        
        case 252:
        
        case 253:
        
        case 254:
        
        default:
          break;
      } 
      byte b1 = 5;
      int j = (paramInt2 & 0xFF) - b1;
      if (j < 0)
        j += 256; 
      int k = ((paramInt2 & 0xFFFF) >>> 8) - b1;
      if (k < 0)
        k += 256; 
      for (byte b2 = 0; b2 < arrayOfChar.length; b2++) {
        int m = b2 % 2;
        if (m == 0) {
          arrayOfChar[b2] = (char)(arrayOfChar[b2] ^ j);
          j = ((j >>> 3 | j << 5) ^ arrayOfChar[b2]) & 0xFF;
        } else {
          arrayOfChar[b2] = (char)(arrayOfChar[b2] ^ k);
          k = ((k >>> 3 | k << 5) ^ arrayOfChar[b2]) & 0xFF;
        } 
      } 
      b[i] = (new String(arrayOfChar)).intern();
    } 
    return b[i];
  }
}


/* Location:              C:\Program Files\BurpSuitePro\burpsuite_pro.jar!\burp\Znp.class
 * Java compiler version: 21 (65.0)
 * JD-Core Version:       1.1.3
 */