package burp;

import java.math.BigInteger;

class Zoe extends ClassLoader {
  static Object ZG;
  
  static String ZE;
  
  private static final String[] a;
  
  private static final String[] b;
  
  static boolean Zi(Object[] paramArrayOfObject, Object paramObject) throws Throwable {
    // Byte code:
    //   0: invokestatic ZN : ()Z
    //   3: istore_2
    //   4: new java/lang/StringBuilder
    //   7: dup
    //   8: invokespecial <init> : ()V
    //   11: astore_3
    //   12: iconst_0
    //   13: istore #4
    //   15: iload #4
    //   17: bipush #32
    //   19: if_icmpge -> 1355
    //   22: iload #4
    //   24: tableswitch default -> 1348, 0 -> 168, 1 -> 205, 2 -> 242, 3 -> 279, 4 -> 316, 5 -> 353, 6 -> 390, 7 -> 427, 8 -> 464, 9 -> 501, 10 -> 538, 11 -> 575, 12 -> 612, 13 -> 649, 14 -> 686, 15 -> 723, 16 -> 760, 17 -> 797, 18 -> 834, 19 -> 871, 20 -> 908, 21 -> 945, 22 -> 982, 23 -> 1019, 24 -> 1056, 25 -> 1093, 26 -> 1130, 27 -> 1167, 28 -> 1204, 29 -> 1241, 30 -> 1278, 31 -> 1315
    //   168: aload_3
    //   169: getstatic burp/Zrkw.ZU : Ljava/lang/String;
    //   172: getstatic burp/Zql.Zt : Ljava/lang/Object;
    //   175: checkcast java/math/BigInteger
    //   178: invokevirtual intValue : ()I
    //   181: bipush #32
    //   183: irem
    //   184: invokestatic abs : (I)I
    //   187: invokevirtual charAt : (I)C
    //   190: invokevirtual append : (C)Ljava/lang/StringBuilder;
    //   193: pop
    //   194: iload_2
    //   195: ifne -> 1348
    //   198: goto -> 205
    //   201: invokestatic a : (Ljava/lang/Throwable;)Ljava/lang/Throwable;
    //   204: athrow
    //   205: aload_3
    //   206: getstatic burp/Zs5y.ZO : Ljava/lang/String;
    //   209: getstatic burp/Zm69.Zg : Ljava/lang/Object;
    //   212: checkcast java/math/BigInteger
    //   215: invokevirtual intValue : ()I
    //   218: bipush #32
    //   220: irem
    //   221: invokestatic abs : (I)I
    //   224: invokevirtual charAt : (I)C
    //   227: invokevirtual append : (C)Ljava/lang/StringBuilder;
    //   230: pop
    //   231: iload_2
    //   232: ifne -> 1348
    //   235: goto -> 242
    //   238: invokestatic a : (Ljava/lang/Throwable;)Ljava/lang/Throwable;
    //   241: athrow
    //   242: aload_3
    //   243: getstatic burp/Zti4.ZI : Ljava/lang/String;
    //   246: getstatic burp/Zek4.ZR : Ljava/lang/Object;
    //   249: checkcast java/math/BigInteger
    //   252: invokevirtual intValue : ()I
    //   255: bipush #32
    //   257: irem
    //   258: invokestatic abs : (I)I
    //   261: invokevirtual charAt : (I)C
    //   264: invokevirtual append : (C)Ljava/lang/StringBuilder;
    //   267: pop
    //   268: iload_2
    //   269: ifne -> 1348
    //   272: goto -> 279
    //   275: invokestatic a : (Ljava/lang/Throwable;)Ljava/lang/Throwable;
    //   278: athrow
    //   279: aload_3
    //   280: getstatic burp/Zspg.ZG : Ljava/lang/String;
    //   283: getstatic burp/Ze84.Zj : Ljava/lang/Object;
    //   286: checkcast java/math/BigInteger
    //   289: invokevirtual intValue : ()I
    //   292: bipush #32
    //   294: irem
    //   295: invokestatic abs : (I)I
    //   298: invokevirtual charAt : (I)C
    //   301: invokevirtual append : (C)Ljava/lang/StringBuilder;
    //   304: pop
    //   305: iload_2
    //   306: ifne -> 1348
    //   309: goto -> 316
    //   312: invokestatic a : (Ljava/lang/Throwable;)Ljava/lang/Throwable;
    //   315: athrow
    //   316: aload_3
    //   317: getstatic burp/Zmli.Zc : Ljava/lang/String;
    //   320: getstatic burp/Zlo0.Zu : Ljava/lang/Object;
    //   323: checkcast java/math/BigInteger
    //   326: invokevirtual intValue : ()I
    //   329: bipush #32
    //   331: irem
    //   332: invokestatic abs : (I)I
    //   335: invokevirtual charAt : (I)C
    //   338: invokevirtual append : (C)Ljava/lang/StringBuilder;
    //   341: pop
    //   342: iload_2
    //   343: ifne -> 1348
    //   346: goto -> 353
    //   349: invokestatic a : (Ljava/lang/Throwable;)Ljava/lang/Throwable;
    //   352: athrow
    //   353: aload_3
    //   354: getstatic burp/Zrex.Za : Ljava/lang/String;
    //   357: getstatic burp/Zkf6.ZS : Ljava/lang/Object;
    //   360: checkcast java/math/BigInteger
    //   363: invokevirtual intValue : ()I
    //   366: bipush #32
    //   368: irem
    //   369: invokestatic abs : (I)I
    //   372: invokevirtual charAt : (I)C
    //   375: invokevirtual append : (C)Ljava/lang/StringBuilder;
    //   378: pop
    //   379: iload_2
    //   380: ifne -> 1348
    //   383: goto -> 390
    //   386: invokestatic a : (Ljava/lang/Throwable;)Ljava/lang/Throwable;
    //   389: athrow
    //   390: aload_3
    //   391: getstatic burp/Zmz.Zp : Ljava/lang/String;
    //   394: getstatic burp/Zbun.ZH : Ljava/lang/Object;
    //   397: checkcast java/math/BigInteger
    //   400: invokevirtual intValue : ()I
    //   403: bipush #32
    //   405: irem
    //   406: invokestatic abs : (I)I
    //   409: invokevirtual charAt : (I)C
    //   412: invokevirtual append : (C)Ljava/lang/StringBuilder;
    //   415: pop
    //   416: iload_2
    //   417: ifne -> 1348
    //   420: goto -> 427
    //   423: invokestatic a : (Ljava/lang/Throwable;)Ljava/lang/Throwable;
    //   426: athrow
    //   427: aload_3
    //   428: getstatic burp/Zrqe.ZB : Ljava/lang/String;
    //   431: getstatic burp/Zxxh.Za : Ljava/lang/Object;
    //   434: checkcast java/math/BigInteger
    //   437: invokevirtual intValue : ()I
    //   440: bipush #32
    //   442: irem
    //   443: invokestatic abs : (I)I
    //   446: invokevirtual charAt : (I)C
    //   449: invokevirtual append : (C)Ljava/lang/StringBuilder;
    //   452: pop
    //   453: iload_2
    //   454: ifne -> 1348
    //   457: goto -> 464
    //   460: invokestatic a : (Ljava/lang/Throwable;)Ljava/lang/Throwable;
    //   463: athrow
    //   464: aload_3
    //   465: getstatic burp/Zes.ZW : Ljava/lang/String;
    //   468: getstatic burp/Zlwj.ZE : Ljava/lang/Object;
    //   471: checkcast java/math/BigInteger
    //   474: invokevirtual intValue : ()I
    //   477: bipush #32
    //   479: irem
    //   480: invokestatic abs : (I)I
    //   483: invokevirtual charAt : (I)C
    //   486: invokevirtual append : (C)Ljava/lang/StringBuilder;
    //   489: pop
    //   490: iload_2
    //   491: ifne -> 1348
    //   494: goto -> 501
    //   497: invokestatic a : (Ljava/lang/Throwable;)Ljava/lang/Throwable;
    //   500: athrow
    //   501: aload_3
    //   502: getstatic burp/Zzmc.Zr : Ljava/lang/String;
    //   505: getstatic burp/Zzna.ZD : Ljava/lang/Object;
    //   508: checkcast java/math/BigInteger
    //   511: invokevirtual intValue : ()I
    //   514: bipush #32
    //   516: irem
    //   517: invokestatic abs : (I)I
    //   520: invokevirtual charAt : (I)C
    //   523: invokevirtual append : (C)Ljava/lang/StringBuilder;
    //   526: pop
    //   527: iload_2
    //   528: ifne -> 1348
    //   531: goto -> 538
    //   534: invokestatic a : (Ljava/lang/Throwable;)Ljava/lang/Throwable;
    //   537: athrow
    //   538: aload_3
    //   539: getstatic burp/Zrjw.Zz : Ljava/lang/String;
    //   542: getstatic burp/Zm69.Zg : Ljava/lang/Object;
    //   545: checkcast java/math/BigInteger
    //   548: invokevirtual intValue : ()I
    //   551: bipush #32
    //   553: irem
    //   554: invokestatic abs : (I)I
    //   557: invokevirtual charAt : (I)C
    //   560: invokevirtual append : (C)Ljava/lang/StringBuilder;
    //   563: pop
    //   564: iload_2
    //   565: ifne -> 1348
    //   568: goto -> 575
    //   571: invokestatic a : (Ljava/lang/Throwable;)Ljava/lang/Throwable;
    //   574: athrow
    //   575: aload_3
    //   576: getstatic burp/Zebe.ZW : Ljava/lang/String;
    //   579: getstatic burp/Zzii.ZO : Ljava/lang/Object;
    //   582: checkcast java/math/BigInteger
    //   585: invokevirtual intValue : ()I
    //   588: bipush #32
    //   590: irem
    //   591: invokestatic abs : (I)I
    //   594: invokevirtual charAt : (I)C
    //   597: invokevirtual append : (C)Ljava/lang/StringBuilder;
    //   600: pop
    //   601: iload_2
    //   602: ifne -> 1348
    //   605: goto -> 612
    //   608: invokestatic a : (Ljava/lang/Throwable;)Ljava/lang/Throwable;
    //   611: athrow
    //   612: aload_3
    //   613: getstatic burp/Zzmc.Zr : Ljava/lang/String;
    //   616: getstatic burp/Zgpx.ZQ : Ljava/lang/Object;
    //   619: checkcast java/math/BigInteger
    //   622: invokevirtual intValue : ()I
    //   625: bipush #32
    //   627: irem
    //   628: invokestatic abs : (I)I
    //   631: invokevirtual charAt : (I)C
    //   634: invokevirtual append : (C)Ljava/lang/StringBuilder;
    //   637: pop
    //   638: iload_2
    //   639: ifne -> 1348
    //   642: goto -> 649
    //   645: invokestatic a : (Ljava/lang/Throwable;)Ljava/lang/Throwable;
    //   648: athrow
    //   649: aload_3
    //   650: getstatic burp/Zbss.ZV : Ljava/lang/String;
    //   653: getstatic burp/Zeig.ZA : Ljava/lang/Object;
    //   656: checkcast java/math/BigInteger
    //   659: invokevirtual intValue : ()I
    //   662: bipush #32
    //   664: irem
    //   665: invokestatic abs : (I)I
    //   668: invokevirtual charAt : (I)C
    //   671: invokevirtual append : (C)Ljava/lang/StringBuilder;
    //   674: pop
    //   675: iload_2
    //   676: ifne -> 1348
    //   679: goto -> 686
    //   682: invokestatic a : (Ljava/lang/Throwable;)Ljava/lang/Throwable;
    //   685: athrow
    //   686: aload_3
    //   687: getstatic burp/Zmc_.Zb : Ljava/lang/String;
    //   690: getstatic burp/Zt0m.Zt : Ljava/lang/Object;
    //   693: checkcast java/math/BigInteger
    //   696: invokevirtual intValue : ()I
    //   699: bipush #32
    //   701: irem
    //   702: invokestatic abs : (I)I
    //   705: invokevirtual charAt : (I)C
    //   708: invokevirtual append : (C)Ljava/lang/StringBuilder;
    //   711: pop
    //   712: iload_2
    //   713: ifne -> 1348
    //   716: goto -> 723
    //   719: invokestatic a : (Ljava/lang/Throwable;)Ljava/lang/Throwable;
    //   722: athrow
    //   723: aload_3
    //   724: getstatic burp/Zmh3.Zy : Ljava/lang/String;
    //   727: getstatic burp/Zrqe.ZX : Ljava/lang/Object;
    //   730: checkcast java/math/BigInteger
    //   733: invokevirtual intValue : ()I
    //   736: bipush #32
    //   738: irem
    //   739: invokestatic abs : (I)I
    //   742: invokevirtual charAt : (I)C
    //   745: invokevirtual append : (C)Ljava/lang/StringBuilder;
    //   748: pop
    //   749: iload_2
    //   750: ifne -> 1348
    //   753: goto -> 760
    //   756: invokestatic a : (Ljava/lang/Throwable;)Ljava/lang/Throwable;
    //   759: athrow
    //   760: aload_3
    //   761: getstatic burp/Zxxf.Zw : Ljava/lang/String;
    //   764: getstatic burp/Zex0.Ze : Ljava/lang/Object;
    //   767: checkcast java/math/BigInteger
    //   770: invokevirtual intValue : ()I
    //   773: bipush #32
    //   775: irem
    //   776: invokestatic abs : (I)I
    //   779: invokevirtual charAt : (I)C
    //   782: invokevirtual append : (C)Ljava/lang/StringBuilder;
    //   785: pop
    //   786: iload_2
    //   787: ifne -> 1348
    //   790: goto -> 797
    //   793: invokestatic a : (Ljava/lang/Throwable;)Ljava/lang/Throwable;
    //   796: athrow
    //   797: aload_3
    //   798: getstatic burp/Ze4g.Zk : Ljava/lang/String;
    //   801: getstatic burp/Zenr.ZA : Ljava/lang/Object;
    //   804: checkcast java/math/BigInteger
    //   807: invokevirtual intValue : ()I
    //   810: bipush #32
    //   812: irem
    //   813: invokestatic abs : (I)I
    //   816: invokevirtual charAt : (I)C
    //   819: invokevirtual append : (C)Ljava/lang/StringBuilder;
    //   822: pop
    //   823: iload_2
    //   824: ifne -> 1348
    //   827: goto -> 834
    //   830: invokestatic a : (Ljava/lang/Throwable;)Ljava/lang/Throwable;
    //   833: athrow
    //   834: aload_3
    //   835: getstatic burp/Zeub.ZT : Ljava/lang/String;
    //   838: getstatic burp/Ztdl.Zw : Ljava/lang/Object;
    //   841: checkcast java/math/BigInteger
    //   844: invokevirtual intValue : ()I
    //   847: bipush #32
    //   849: irem
    //   850: invokestatic abs : (I)I
    //   853: invokevirtual charAt : (I)C
    //   856: invokevirtual append : (C)Ljava/lang/StringBuilder;
    //   859: pop
    //   860: iload_2
    //   861: ifne -> 1348
    //   864: goto -> 871
    //   867: invokestatic a : (Ljava/lang/Throwable;)Ljava/lang/Throwable;
    //   870: athrow
    //   871: aload_3
    //   872: getstatic burp/Zdv.Zz : Ljava/lang/String;
    //   875: getstatic burp/Zzc9.ZZ : Ljava/lang/Object;
    //   878: checkcast java/math/BigInteger
    //   881: invokevirtual intValue : ()I
    //   884: bipush #32
    //   886: irem
    //   887: invokestatic abs : (I)I
    //   890: invokevirtual charAt : (I)C
    //   893: invokevirtual append : (C)Ljava/lang/StringBuilder;
    //   896: pop
    //   897: iload_2
    //   898: ifne -> 1348
    //   901: goto -> 908
    //   904: invokestatic a : (Ljava/lang/Throwable;)Ljava/lang/Throwable;
    //   907: athrow
    //   908: aload_3
    //   909: getstatic burp/Zrym.ZX : Ljava/lang/String;
    //   912: getstatic burp/Zbx4.Zw : Ljava/lang/Object;
    //   915: checkcast java/math/BigInteger
    //   918: invokevirtual intValue : ()I
    //   921: bipush #32
    //   923: irem
    //   924: invokestatic abs : (I)I
    //   927: invokevirtual charAt : (I)C
    //   930: invokevirtual append : (C)Ljava/lang/StringBuilder;
    //   933: pop
    //   934: iload_2
    //   935: ifne -> 1348
    //   938: goto -> 945
    //   941: invokestatic a : (Ljava/lang/Throwable;)Ljava/lang/Throwable;
    //   944: athrow
    //   945: aload_3
    //   946: getstatic burp/Zek4.Zo : Ljava/lang/String;
    //   949: getstatic burp/Zedu.ZL : Ljava/lang/Object;
    //   952: checkcast java/math/BigInteger
    //   955: invokevirtual intValue : ()I
    //   958: bipush #32
    //   960: irem
    //   961: invokestatic abs : (I)I
    //   964: invokevirtual charAt : (I)C
    //   967: invokevirtual append : (C)Ljava/lang/StringBuilder;
    //   970: pop
    //   971: iload_2
    //   972: ifne -> 1348
    //   975: goto -> 982
    //   978: invokestatic a : (Ljava/lang/Throwable;)Ljava/lang/Throwable;
    //   981: athrow
    //   982: aload_3
    //   983: getstatic burp/Zgei.Zl : Ljava/lang/String;
    //   986: getstatic burp/Ztvg.ZO : Ljava/lang/Object;
    //   989: checkcast java/math/BigInteger
    //   992: invokevirtual intValue : ()I
    //   995: bipush #32
    //   997: irem
    //   998: invokestatic abs : (I)I
    //   1001: invokevirtual charAt : (I)C
    //   1004: invokevirtual append : (C)Ljava/lang/StringBuilder;
    //   1007: pop
    //   1008: iload_2
    //   1009: ifne -> 1348
    //   1012: goto -> 1019
    //   1015: invokestatic a : (Ljava/lang/Throwable;)Ljava/lang/Throwable;
    //   1018: athrow
    //   1019: aload_3
    //   1020: getstatic burp/Zos.Za : Ljava/lang/String;
    //   1023: getstatic burp/Zewr.Zw : Ljava/lang/Object;
    //   1026: checkcast java/math/BigInteger
    //   1029: invokevirtual intValue : ()I
    //   1032: bipush #32
    //   1034: irem
    //   1035: invokestatic abs : (I)I
    //   1038: invokevirtual charAt : (I)C
    //   1041: invokevirtual append : (C)Ljava/lang/StringBuilder;
    //   1044: pop
    //   1045: iload_2
    //   1046: ifne -> 1348
    //   1049: goto -> 1056
    //   1052: invokestatic a : (Ljava/lang/Throwable;)Ljava/lang/Throwable;
    //   1055: athrow
    //   1056: aload_3
    //   1057: getstatic burp/Zry1.Zk : Ljava/lang/String;
    //   1060: getstatic burp/Zm83.Zl : Ljava/lang/Object;
    //   1063: checkcast java/math/BigInteger
    //   1066: invokevirtual intValue : ()I
    //   1069: bipush #32
    //   1071: irem
    //   1072: invokestatic abs : (I)I
    //   1075: invokevirtual charAt : (I)C
    //   1078: invokevirtual append : (C)Ljava/lang/StringBuilder;
    //   1081: pop
    //   1082: iload_2
    //   1083: ifne -> 1348
    //   1086: goto -> 1093
    //   1089: invokestatic a : (Ljava/lang/Throwable;)Ljava/lang/Throwable;
    //   1092: athrow
    //   1093: aload_3
    //   1094: getstatic burp/Zek4.Zo : Ljava/lang/String;
    //   1097: getstatic burp/Zrp2.Zw : Ljava/lang/Object;
    //   1100: checkcast java/math/BigInteger
    //   1103: invokevirtual intValue : ()I
    //   1106: bipush #32
    //   1108: irem
    //   1109: invokestatic abs : (I)I
    //   1112: invokevirtual charAt : (I)C
    //   1115: invokevirtual append : (C)Ljava/lang/StringBuilder;
    //   1118: pop
    //   1119: iload_2
    //   1120: ifne -> 1348
    //   1123: goto -> 1130
    //   1126: invokestatic a : (Ljava/lang/Throwable;)Ljava/lang/Throwable;
    //   1129: athrow
    //   1130: aload_3
    //   1131: getstatic burp/Zl7x.Zo : Ljava/lang/String;
    //   1134: getstatic burp/Ztlo.ZP : Ljava/lang/Object;
    //   1137: checkcast java/math/BigInteger
    //   1140: invokevirtual intValue : ()I
    //   1143: bipush #32
    //   1145: irem
    //   1146: invokestatic abs : (I)I
    //   1149: invokevirtual charAt : (I)C
    //   1152: invokevirtual append : (C)Ljava/lang/StringBuilder;
    //   1155: pop
    //   1156: iload_2
    //   1157: ifne -> 1348
    //   1160: goto -> 1167
    //   1163: invokestatic a : (Ljava/lang/Throwable;)Ljava/lang/Throwable;
    //   1166: athrow
    //   1167: aload_3
    //   1168: getstatic burp/Zmh3.Zy : Ljava/lang/String;
    //   1171: getstatic burp/Zlgh.Zd : Ljava/lang/Object;
    //   1174: checkcast java/math/BigInteger
    //   1177: invokevirtual intValue : ()I
    //   1180: bipush #32
    //   1182: irem
    //   1183: invokestatic abs : (I)I
    //   1186: invokevirtual charAt : (I)C
    //   1189: invokevirtual append : (C)Ljava/lang/StringBuilder;
    //   1192: pop
    //   1193: iload_2
    //   1194: ifne -> 1348
    //   1197: goto -> 1204
    //   1200: invokestatic a : (Ljava/lang/Throwable;)Ljava/lang/Throwable;
    //   1203: athrow
    //   1204: aload_3
    //   1205: getstatic burp/Zzht.Zv : Ljava/lang/String;
    //   1208: getstatic burp/Zos.ZB : Ljava/lang/Object;
    //   1211: checkcast java/math/BigInteger
    //   1214: invokevirtual intValue : ()I
    //   1217: bipush #32
    //   1219: irem
    //   1220: invokestatic abs : (I)I
    //   1223: invokevirtual charAt : (I)C
    //   1226: invokevirtual append : (C)Ljava/lang/StringBuilder;
    //   1229: pop
    //   1230: iload_2
    //   1231: ifne -> 1348
    //   1234: goto -> 1241
    //   1237: invokestatic a : (Ljava/lang/Throwable;)Ljava/lang/Throwable;
    //   1240: athrow
    //   1241: aload_3
    //   1242: getstatic burp/Zeig.Zg : Ljava/lang/String;
    //   1245: getstatic burp/Zr6c.ZG : Ljava/lang/Object;
    //   1248: checkcast java/math/BigInteger
    //   1251: invokevirtual intValue : ()I
    //   1254: bipush #32
    //   1256: irem
    //   1257: invokestatic abs : (I)I
    //   1260: invokevirtual charAt : (I)C
    //   1263: invokevirtual append : (C)Ljava/lang/StringBuilder;
    //   1266: pop
    //   1267: iload_2
    //   1268: ifne -> 1348
    //   1271: goto -> 1278
    //   1274: invokestatic a : (Ljava/lang/Throwable;)Ljava/lang/Throwable;
    //   1277: athrow
    //   1278: aload_3
    //   1279: getstatic burp/Zgrz.Zu : Ljava/lang/String;
    //   1282: getstatic burp/Zkql.Zl : Ljava/lang/Object;
    //   1285: checkcast java/math/BigInteger
    //   1288: invokevirtual intValue : ()I
    //   1291: bipush #32
    //   1293: irem
    //   1294: invokestatic abs : (I)I
    //   1297: invokevirtual charAt : (I)C
    //   1300: invokevirtual append : (C)Ljava/lang/StringBuilder;
    //   1303: pop
    //   1304: iload_2
    //   1305: ifne -> 1348
    //   1308: goto -> 1315
    //   1311: invokestatic a : (Ljava/lang/Throwable;)Ljava/lang/Throwable;
    //   1314: athrow
    //   1315: aload_3
    //   1316: getstatic burp/Zz4j.ZS : Ljava/lang/String;
    //   1319: getstatic burp/Zxn4.Zx : Ljava/lang/Object;
    //   1322: checkcast java/math/BigInteger
    //   1325: invokevirtual intValue : ()I
    //   1328: bipush #32
    //   1330: irem
    //   1331: invokestatic abs : (I)I
    //   1334: invokevirtual charAt : (I)C
    //   1337: invokevirtual append : (C)Ljava/lang/StringBuilder;
    //   1340: pop
    //   1341: goto -> 1348
    //   1344: invokestatic a : (Ljava/lang/Throwable;)Ljava/lang/Throwable;
    //   1347: athrow
    //   1348: iinc #4, 1
    //   1351: iload_2
    //   1352: ifne -> 15
    //   1355: aload_3
    //   1356: invokevirtual toString : ()Ljava/lang/String;
    //   1359: putstatic burp/Zsdl.ZJ : Ljava/lang/String;
    //   1362: getstatic burp/Ztle.ZP : Ljava/lang/Object;
    //   1365: checkcast java/math/BigInteger
    //   1368: getstatic burp/Zelt.ZC : Ljava/lang/Object;
    //   1371: checkcast java/math/BigInteger
    //   1374: invokevirtual add : (Ljava/math/BigInteger;)Ljava/math/BigInteger;
    //   1377: putstatic burp/Zrw0.ZC : Ljava/lang/Object;
    //   1380: getstatic burp/Zs5y.Zd : Ljava/lang/Object;
    //   1383: checkcast java/math/BigInteger
    //   1386: invokevirtual toByteArray : ()[B
    //   1389: astore #4
    //   1391: aload #4
    //   1393: arraylength
    //   1394: bipush #8
    //   1396: iadd
    //   1397: bipush #6
    //   1399: ishr
    //   1400: iconst_1
    //   1401: iadd
    //   1402: bipush #16
    //   1404: imul
    //   1405: newarray int
    //   1407: astore #6
    //   1409: iconst_0
    //   1410: istore #7
    //   1412: iload #7
    //   1414: aload #4
    //   1416: arraylength
    //   1417: if_icmpge -> 1461
    //   1420: aload #4
    //   1422: iload #7
    //   1424: baload
    //   1425: sipush #255
    //   1428: iand
    //   1429: istore #8
    //   1431: aload #6
    //   1433: iload #7
    //   1435: iconst_2
    //   1436: ishr
    //   1437: dup2
    //   1438: iaload
    //   1439: iload #8
    //   1441: bipush #24
    //   1443: iload #7
    //   1445: iconst_4
    //   1446: irem
    //   1447: bipush #8
    //   1449: imul
    //   1450: isub
    //   1451: ishl
    //   1452: ior
    //   1453: iastore
    //   1454: iinc #7, 1
    //   1457: iload_2
    //   1458: ifne -> 1412
    //   1461: aload #6
    //   1463: iload #7
    //   1465: iconst_2
    //   1466: ishr
    //   1467: dup2
    //   1468: iaload
    //   1469: sipush #128
    //   1472: bipush #24
    //   1474: iload #7
    //   1476: iconst_4
    //   1477: irem
    //   1478: bipush #8
    //   1480: imul
    //   1481: isub
    //   1482: ishl
    //   1483: ior
    //   1484: iastore
    //   1485: aload #6
    //   1487: aload #6
    //   1489: arraylength
    //   1490: iconst_1
    //   1491: isub
    //   1492: aload #4
    //   1494: arraylength
    //   1495: bipush #8
    //   1497: imul
    //   1498: iastore
    //   1499: bipush #80
    //   1501: newarray int
    //   1503: astore #8
    //   1505: ldc 1732584193
    //   1507: istore #9
    //   1509: ldc -271733879
    //   1511: istore #10
    //   1513: ldc -1732584194
    //   1515: istore #11
    //   1517: ldc 271733878
    //   1519: istore #12
    //   1521: ldc -1009589776
    //   1523: istore #13
    //   1525: iconst_0
    //   1526: istore #7
    //   1528: iload #7
    //   1530: aload #6
    //   1532: arraylength
    //   1533: if_icmpge -> 1855
    //   1536: iload #9
    //   1538: istore #14
    //   1540: iload #10
    //   1542: istore #15
    //   1544: iload #11
    //   1546: istore #16
    //   1548: iload #12
    //   1550: istore #17
    //   1552: iload #13
    //   1554: istore #18
    //   1556: iconst_0
    //   1557: istore #19
    //   1559: iload #19
    //   1561: bipush #80
    //   1563: if_icmpge -> 1813
    //   1566: iload #19
    //   1568: bipush #16
    //   1570: if_icmpge -> 1597
    //   1573: aload #8
    //   1575: iload #19
    //   1577: aload #6
    //   1579: iload #7
    //   1581: iload #19
    //   1583: iadd
    //   1584: iaload
    //   1585: iastore
    //   1586: iload_2
    //   1587: ifne -> 1652
    //   1590: goto -> 1597
    //   1593: invokestatic a : (Ljava/lang/Throwable;)Ljava/lang/Throwable;
    //   1596: athrow
    //   1597: aload #8
    //   1599: iload #19
    //   1601: iconst_3
    //   1602: isub
    //   1603: iaload
    //   1604: aload #8
    //   1606: iload #19
    //   1608: bipush #8
    //   1610: isub
    //   1611: iaload
    //   1612: ixor
    //   1613: aload #8
    //   1615: iload #19
    //   1617: bipush #14
    //   1619: isub
    //   1620: iaload
    //   1621: ixor
    //   1622: aload #8
    //   1624: iload #19
    //   1626: bipush #16
    //   1628: isub
    //   1629: iaload
    //   1630: ixor
    //   1631: istore #20
    //   1633: iload #20
    //   1635: iconst_1
    //   1636: ishl
    //   1637: iload #20
    //   1639: bipush #31
    //   1641: iushr
    //   1642: ior
    //   1643: istore #21
    //   1645: aload #8
    //   1647: iload #19
    //   1649: iload #21
    //   1651: iastore
    //   1652: iload #9
    //   1654: iconst_5
    //   1655: ishl
    //   1656: iload #9
    //   1658: bipush #27
    //   1660: iushr
    //   1661: ior
    //   1662: istore #20
    //   1664: iload #20
    //   1666: iload #13
    //   1668: iadd
    //   1669: aload #8
    //   1671: iload #19
    //   1673: iaload
    //   1674: iadd
    //   1675: iload #19
    //   1677: bipush #20
    //   1679: if_icmpge -> 1705
    //   1682: ldc 1518500249
    //   1684: iload #10
    //   1686: iload #11
    //   1688: iand
    //   1689: iload #10
    //   1691: iconst_m1
    //   1692: ixor
    //   1693: iload #12
    //   1695: iand
    //   1696: ior
    //   1697: iadd
    //   1698: goto -> 1775
    //   1701: invokestatic a : (Ljava/lang/Throwable;)Ljava/lang/Throwable;
    //   1704: athrow
    //   1705: iload #19
    //   1707: bipush #40
    //   1709: if_icmpge -> 1730
    //   1712: ldc 1859775393
    //   1714: iload #10
    //   1716: iload #11
    //   1718: ixor
    //   1719: iload #12
    //   1721: ixor
    //   1722: iadd
    //   1723: goto -> 1775
    //   1726: invokestatic a : (Ljava/lang/Throwable;)Ljava/lang/Throwable;
    //   1729: athrow
    //   1730: iload #19
    //   1732: bipush #60
    //   1734: if_icmpge -> 1764
    //   1737: ldc -1894007588
    //   1739: iload #10
    //   1741: iload #11
    //   1743: iand
    //   1744: iload #10
    //   1746: iload #12
    //   1748: iand
    //   1749: ior
    //   1750: iload #11
    //   1752: iload #12
    //   1754: iand
    //   1755: ior
    //   1756: iadd
    //   1757: goto -> 1775
    //   1760: invokestatic a : (Ljava/lang/Throwable;)Ljava/lang/Throwable;
    //   1763: athrow
    //   1764: ldc -899497514
    //   1766: iload #10
    //   1768: iload #11
    //   1770: ixor
    //   1771: iload #12
    //   1773: ixor
    //   1774: iadd
    //   1775: iadd
    //   1776: istore #21
    //   1778: iload #12
    //   1780: istore #13
    //   1782: iload #11
    //   1784: istore #12
    //   1786: iload #10
    //   1788: bipush #30
    //   1790: ishl
    //   1791: iload #10
    //   1793: iconst_2
    //   1794: iushr
    //   1795: ior
    //   1796: istore #11
    //   1798: iload #9
    //   1800: istore #10
    //   1802: iload #21
    //   1804: istore #9
    //   1806: iinc #19, 1
    //   1809: iload_2
    //   1810: ifne -> 1559
    //   1813: iload #9
    //   1815: iload #14
    //   1817: iadd
    //   1818: istore #9
    //   1820: iload #10
    //   1822: iload #15
    //   1824: iadd
    //   1825: istore #10
    //   1827: iload #11
    //   1829: iload #16
    //   1831: iadd
    //   1832: istore #11
    //   1834: iload #12
    //   1836: iload #17
    //   1838: iadd
    //   1839: istore #12
    //   1841: iload #13
    //   1843: iload #18
    //   1845: iadd
    //   1846: istore #13
    //   1848: iinc #7, 16
    //   1851: iload_2
    //   1852: ifne -> 1528
    //   1855: iconst_5
    //   1856: newarray int
    //   1858: dup
    //   1859: iconst_0
    //   1860: iload #9
    //   1862: iastore
    //   1863: dup
    //   1864: iconst_1
    //   1865: iload #10
    //   1867: iastore
    //   1868: dup
    //   1869: iconst_2
    //   1870: iload #11
    //   1872: iastore
    //   1873: dup
    //   1874: iconst_3
    //   1875: iload #12
    //   1877: iastore
    //   1878: dup
    //   1879: iconst_4
    //   1880: iload #13
    //   1882: iastore
    //   1883: astore #14
    //   1885: bipush #20
    //   1887: newarray byte
    //   1889: astore #15
    //   1891: iconst_0
    //   1892: istore #16
    //   1894: iload #16
    //   1896: bipush #20
    //   1898: if_icmpge -> 1939
    //   1901: aload #14
    //   1903: iload #16
    //   1905: iconst_4
    //   1906: idiv
    //   1907: iaload
    //   1908: istore #17
    //   1910: iconst_3
    //   1911: iload #16
    //   1913: iconst_4
    //   1914: irem
    //   1915: isub
    //   1916: bipush #8
    //   1918: imul
    //   1919: istore #18
    //   1921: aload #15
    //   1923: iload #16
    //   1925: iload #17
    //   1927: iload #18
    //   1929: iushr
    //   1930: i2b
    //   1931: bastore
    //   1932: iinc #16, 1
    //   1935: iload_2
    //   1936: ifne -> 1894
    //   1939: aload #15
    //   1941: astore #5
    //   1943: sipush #6485
    //   1946: new java/math/BigInteger
    //   1949: dup
    //   1950: aload #5
    //   1952: invokespecial <init> : ([B)V
    //   1955: invokevirtual abs : ()Ljava/math/BigInteger;
    //   1958: putstatic burp/Ztq2.Zj : Ljava/lang/Object;
    //   1961: sipush #-30125
    //   1964: invokestatic a : (II)Ljava/lang/String;
    //   1967: iconst_1
    //   1968: ldc burp/Zrpm
    //   1970: invokevirtual getClassLoader : ()Ljava/lang/ClassLoader;
    //   1973: invokestatic forName : (Ljava/lang/String;ZLjava/lang/ClassLoader;)Ljava/lang/Class;
    //   1976: invokevirtual getDeclaredFields : ()[Ljava/lang/reflect/Field;
    //   1979: astore #4
    //   1981: aload #4
    //   1983: arraylength
    //   1984: istore #5
    //   1986: iconst_0
    //   1987: istore #6
    //   1989: iload #6
    //   1991: iload #5
    //   1993: if_icmpge -> 2131
    //   1996: aload #4
    //   1998: iload #6
    //   2000: aaload
    //   2001: astore #7
    //   2003: aload #7
    //   2005: invokevirtual getModifiers : ()I
    //   2008: invokestatic isStatic : (I)Z
    //   2011: ifne -> 2021
    //   2014: goto -> 2124
    //   2017: invokestatic a : (Ljava/lang/Throwable;)Ljava/lang/Throwable;
    //   2020: athrow
    //   2021: aload #7
    //   2023: invokevirtual getType : ()Ljava/lang/Class;
    //   2026: astore #8
    //   2028: aload #8
    //   2030: ifnull -> 2111
    //   2033: aload #8
    //   2035: invokevirtual isPrimitive : ()Z
    //   2038: ifne -> 2111
    //   2041: goto -> 2048
    //   2044: invokestatic a : (Ljava/lang/Throwable;)Ljava/lang/Throwable;
    //   2047: athrow
    //   2048: aload #8
    //   2050: invokevirtual getPackage : ()Ljava/lang/Package;
    //   2053: ifnull -> 2111
    //   2056: goto -> 2063
    //   2059: invokestatic a : (Ljava/lang/Throwable;)Ljava/lang/Throwable;
    //   2062: athrow
    //   2063: aload #8
    //   2065: invokevirtual getPackage : ()Ljava/lang/Package;
    //   2068: invokevirtual getName : ()Ljava/lang/String;
    //   2071: ifnull -> 2111
    //   2074: goto -> 2081
    //   2077: invokestatic a : (Ljava/lang/Throwable;)Ljava/lang/Throwable;
    //   2080: athrow
    //   2081: aload #8
    //   2083: invokevirtual getPackage : ()Ljava/lang/Package;
    //   2086: invokevirtual getName : ()Ljava/lang/String;
    //   2089: sipush #6484
    //   2092: sipush #-14065
    //   2095: invokestatic a : (II)Ljava/lang/String;
    //   2098: invokevirtual startsWith : (Ljava/lang/String;)Z
    //   2101: ifne -> 2111
    //   2104: goto -> 2111
    //   2107: invokestatic a : (Ljava/lang/Throwable;)Ljava/lang/Throwable;
    //   2110: athrow
    //   2111: aload #7
    //   2113: iconst_1
    //   2114: invokevirtual setAccessible : (Z)V
    //   2117: aload #7
    //   2119: aconst_null
    //   2120: invokevirtual get : (Ljava/lang/Object;)Ljava/lang/Object;
    //   2123: pop
    //   2124: iinc #6, 1
    //   2127: iload_2
    //   2128: ifne -> 1989
    //   2131: sipush #6481
    //   2134: sipush #25863
    //   2137: invokestatic a : (II)Ljava/lang/String;
    //   2140: invokestatic forName : (Ljava/lang/String;)Ljava/lang/Class;
    //   2143: invokevirtual getDeclaredMethods : ()[Ljava/lang/reflect/Method;
    //   2146: astore #4
    //   2148: aload #4
    //   2150: arraylength
    //   2151: istore #5
    //   2153: iconst_0
    //   2154: istore #6
    //   2156: iload #6
    //   2158: iload #5
    //   2160: if_icmpge -> 2293
    //   2163: aload #4
    //   2165: iload #6
    //   2167: aaload
    //   2168: astore #7
    //   2170: aload #7
    //   2172: invokevirtual getParameterTypes : ()[Ljava/lang/Class;
    //   2175: pop
    //   2176: aload #7
    //   2178: invokevirtual getModifiers : ()I
    //   2181: invokestatic isStatic : (I)Z
    //   2184: ifeq -> 2279
    //   2187: aload #7
    //   2189: invokevirtual getParameterTypes : ()[Ljava/lang/Class;
    //   2192: arraylength
    //   2193: iconst_2
    //   2194: if_icmpne -> 2279
    //   2197: goto -> 2204
    //   2200: invokestatic a : (Ljava/lang/Throwable;)Ljava/lang/Throwable;
    //   2203: athrow
    //   2204: aload #7
    //   2206: invokevirtual getReturnType : ()Ljava/lang/Class;
    //   2209: getstatic java/lang/Void.TYPE : Ljava/lang/Class;
    //   2212: invokevirtual equals : (Ljava/lang/Object;)Z
    //   2215: ifeq -> 2279
    //   2218: goto -> 2225
    //   2221: invokestatic a : (Ljava/lang/Throwable;)Ljava/lang/Throwable;
    //   2224: athrow
    //   2225: aload #7
    //   2227: iconst_1
    //   2228: invokevirtual setAccessible : (Z)V
    //   2231: aload #7
    //   2233: aconst_null
    //   2234: iconst_2
    //   2235: anewarray java/lang/Object
    //   2238: dup
    //   2239: iconst_0
    //   2240: aload_0
    //   2241: aastore
    //   2242: dup
    //   2243: iconst_1
    //   2244: aload_1
    //   2245: ifnonnull -> 2263
    //   2248: goto -> 2255
    //   2251: invokestatic a : (Ljava/lang/Throwable;)Ljava/lang/Throwable;
    //   2254: athrow
    //   2255: aload_1
    //   2256: goto -> 2270
    //   2259: invokestatic a : (Ljava/lang/Throwable;)Ljava/lang/Throwable;
    //   2262: athrow
    //   2263: aload_1
    //   2264: checkcast [B
    //   2267: invokevirtual clone : ()Ljava/lang/Object;
    //   2270: aastore
    //   2271: invokevirtual invoke : (Ljava/lang/Object;[Ljava/lang/Object;)Ljava/lang/Object;
    //   2274: pop
    //   2275: iload_2
    //   2276: ifne -> 2293
    //   2279: iinc #6, 1
    //   2282: iload_2
    //   2283: ifne -> 2156
    //   2286: goto -> 2293
    //   2289: invokestatic a : (Ljava/lang/Throwable;)Ljava/lang/Throwable;
    //   2292: athrow
    //   2293: getstatic burp/Zlab.Zp : Ljava/lang/String;
    //   2296: getstatic burp/Zl3j.ZY : Ljava/lang/Object;
    //   2299: checkcast java/math/BigInteger
    //   2302: invokevirtual intValue : ()I
    //   2305: bipush #32
    //   2307: irem
    //   2308: invokestatic abs : (I)I
    //   2311: invokevirtual charAt : (I)C
    //   2314: getstatic burp/Zmn0.Zk : Ljava/lang/String;
    //   2317: getstatic burp/Zrl5.ZI : Ljava/lang/Object;
    //   2320: checkcast java/math/BigInteger
    //   2323: invokevirtual intValue : ()I
    //   2326: bipush #32
    //   2328: irem
    //   2329: invokestatic abs : (I)I
    //   2332: invokevirtual charAt : (I)C
    //   2335: if_icmple -> 2450
    //   2338: getstatic burp/Zk9q.Zk : Ljava/lang/String;
    //   2341: getstatic burp/Zos.ZB : Ljava/lang/Object;
    //   2344: checkcast java/math/BigInteger
    //   2347: invokevirtual intValue : ()I
    //   2350: bipush #32
    //   2352: irem
    //   2353: invokestatic abs : (I)I
    //   2356: invokevirtual charAt : (I)C
    //   2359: getstatic burp/Zge2.ZT : Ljava/lang/String;
    //   2362: getstatic burp/Ze5h.Zn : Ljava/lang/Object;
    //   2365: checkcast java/math/BigInteger
    //   2368: invokevirtual intValue : ()I
    //   2371: bipush #32
    //   2373: irem
    //   2374: invokestatic abs : (I)I
    //   2377: invokevirtual charAt : (I)C
    //   2380: if_icmpgt -> 2450
    //   2383: goto -> 2390
    //   2386: invokestatic a : (Ljava/lang/Throwable;)Ljava/lang/Throwable;
    //   2389: athrow
    //   2390: getstatic burp/Zmc_.Zb : Ljava/lang/String;
    //   2393: getstatic burp/Zsjc.ZX : Ljava/lang/Object;
    //   2396: checkcast java/math/BigInteger
    //   2399: invokevirtual intValue : ()I
    //   2402: bipush #32
    //   2404: irem
    //   2405: invokestatic abs : (I)I
    //   2408: invokevirtual charAt : (I)C
    //   2411: getstatic burp/Zr2q.ZA : Ljava/lang/String;
    //   2414: getstatic burp/Zmhq.ZK : Ljava/lang/Object;
    //   2417: checkcast java/math/BigInteger
    //   2420: invokevirtual intValue : ()I
    //   2423: bipush #32
    //   2425: irem
    //   2426: invokestatic abs : (I)I
    //   2429: invokevirtual charAt : (I)C
    //   2432: if_icmpgt -> 2450
    //   2435: goto -> 2442
    //   2438: invokestatic a : (Ljava/lang/Throwable;)Ljava/lang/Throwable;
    //   2441: athrow
    //   2442: iconst_1
    //   2443: goto -> 2451
    //   2446: invokestatic a : (Ljava/lang/Throwable;)Ljava/lang/Throwable;
    //   2449: athrow
    //   2450: iconst_0
    //   2451: ireturn
    //   2452: astore_3
    //   2453: new java/lang/Exception
    //   2456: dup
    //   2457: aload_3
    //   2458: invokevirtual getMessage : ()Ljava/lang/String;
    //   2461: invokespecial <init> : (Ljava/lang/String;)V
    //   2464: athrow
    // Exception table:
    //   from	to	target	type
    //   4	2451	2452	java/lang/Throwable
    //   22	198	201	java/lang/Throwable
    //   168	235	238	java/lang/Throwable
    //   205	272	275	java/lang/Throwable
    //   242	309	312	java/lang/Throwable
    //   279	346	349	java/lang/Throwable
    //   316	383	386	java/lang/Throwable
    //   353	420	423	java/lang/Throwable
    //   390	457	460	java/lang/Throwable
    //   427	494	497	java/lang/Throwable
    //   464	531	534	java/lang/Throwable
    //   501	568	571	java/lang/Throwable
    //   538	605	608	java/lang/Throwable
    //   575	642	645	java/lang/Throwable
    //   612	679	682	java/lang/Throwable
    //   649	716	719	java/lang/Throwable
    //   686	753	756	java/lang/Throwable
    //   723	790	793	java/lang/Throwable
    //   760	827	830	java/lang/Throwable
    //   797	864	867	java/lang/Throwable
    //   834	901	904	java/lang/Throwable
    //   871	938	941	java/lang/Throwable
    //   908	975	978	java/lang/Throwable
    //   945	1012	1015	java/lang/Throwable
    //   982	1049	1052	java/lang/Throwable
    //   1019	1086	1089	java/lang/Throwable
    //   1056	1123	1126	java/lang/Throwable
    //   1093	1160	1163	java/lang/Throwable
    //   1130	1197	1200	java/lang/Throwable
    //   1167	1234	1237	java/lang/Throwable
    //   1204	1271	1274	java/lang/Throwable
    //   1241	1308	1311	java/lang/Throwable
    //   1278	1341	1344	java/lang/Throwable
    //   1566	1590	1593	java/lang/Throwable
    //   1664	1701	1701	java/lang/Throwable
    //   1705	1726	1726	java/lang/Throwable
    //   1730	1760	1760	java/lang/Throwable
    //   2003	2017	2017	java/lang/Throwable
    //   2028	2041	2044	java/lang/Throwable
    //   2033	2056	2059	java/lang/Throwable
    //   2048	2074	2077	java/lang/Throwable
    //   2063	2104	2107	java/lang/Throwable
    //   2170	2197	2200	java/lang/Throwable
    //   2187	2218	2221	java/lang/Throwable
    //   2204	2248	2251	java/lang/Throwable
    //   2225	2259	2259	java/lang/Throwable
    //   2270	2286	2289	java/lang/Throwable
    //   2293	2383	2386	java/lang/Throwable
    //   2338	2435	2438	java/lang/Throwable
    //   2390	2446	2446	java/lang/Throwable
  }
  
  static void Zn(Object paramObject) {
    Zl3j.Zr = a(6486, -16920);
    Zl3j.ZY = new BigInteger(a(6487, 1176));
    boolean bool = Zt2e.ZK();
    try {
      try {
        if (Zd9.Ze.charAt(Math.abs(((BigInteger)Ze25.ZW).intValue() % 32)) > Zlwc.ZM.charAt(Math.abs(((BigInteger)Zmlr.Zh).intValue() % 32))) {
          try {
            Zebe.Zz(Class.forName(a(6480, 30755)));
            if (bool)
              Zgii.Zl(Class.forName(a(6483, -8393))); 
          } catch (Throwable throwable) {
            throw a(null);
          } 
          return;
        } 
      } catch (Throwable throwable) {
        throw a(null);
      } 
      Zgii.Zl(Class.forName(a(6483, -8393)));
    } catch (Throwable throwable) {}
  }
  
  static void ZP(Object[] paramArrayOfObject, Object paramObject) throws Throwable {}
  
  static {
    // Byte code:
    //   0: bipush #8
    //   2: anewarray java/lang/String
    //   5: astore #5
    //   7: iconst_0
    //   8: istore_3
    //   9: ldc 'Â¥Â¡Ã„Po|-Ã°Ã©Â¬Ã£XÂ·5Â¸EÂ®@X3{ÂšUiÂœ)Â§Â½Âµ%MÂ±Â•Ã½\zÂ¶4Â–Ã¶}Â¶Â­Â©Ã…}ÂŒ\\f>'ÂŸÂ±xÂ„xÂ€Ã²HÃ™Â±Â¹Â¸oÃÃ™ÃÂ—zÃ‹ÂœÂ²gÂ†Ã­Ã¨Ã„Ã°Â¬Â»8Â·,Â Â…ÂÃ’\\fM\\rJÂ‡Â Â©ÃƒÂ˜\\fÃ´nÃ¸Ã—ÂŽÂ¼Â·LÂ°\\tuiukÃ“'Ã–W Ã¸Â˜Ã¡Ã‰+Ã¾Â¡\\r,Â–Âª9Â‰ÃšÃ«V\\n`Ã¿Â§ÂÃ¡Ã‹{Ã‰Ã¸Â¹U~Ã¿F\\tÃŒqBhÂ™Â³Ã·ÃŸÃ›'
    //   11: dup
    //   12: astore_2
    //   13: invokevirtual length : ()I
    //   16: istore #4
    //   18: bipush #32
    //   20: istore_1
    //   21: iconst_m1
    //   22: istore_0
    //   23: bipush #106
    //   25: iinc #0, 1
    //   28: aload_2
    //   29: iload_0
    //   30: dup
    //   31: iload_1
    //   32: iadd
    //   33: invokevirtual substring : (II)Ljava/lang/String;
    //   36: iconst_m1
    //   37: goto -> 143
    //   40: aload #5
    //   42: swap
    //   43: iload_3
    //   44: iinc #3, 1
    //   47: swap
    //   48: aastore
    //   49: iload_0
    //   50: iload_1
    //   51: iadd
    //   52: dup
    //   53: istore_0
    //   54: iload #4
    //   56: if_icmpge -> 68
    //   59: aload_2
    //   60: iload_0
    //   61: invokevirtual charAt : (I)C
    //   64: istore_1
    //   65: goto -> 23
    //   68: ldc 'Â…Ã†HÂ·\\tÂ™0\\t\\fÃ«Ã¤Â…Ã³Â°\\b\\f'
    //   70: dup
    //   71: astore_2
    //   72: invokevirtual length : ()I
    //   75: istore #4
    //   77: bipush #9
    //   79: istore_1
    //   80: iconst_m1
    //   81: istore_0
    //   82: bipush #119
    //   84: iinc #0, 1
    //   87: aload_2
    //   88: iload_0
    //   89: dup
    //   90: iload_1
    //   91: iadd
    //   92: invokevirtual substring : (II)Ljava/lang/String;
    //   95: iconst_0
    //   96: goto -> 143
    //   99: aload #5
    //   101: swap
    //   102: iload_3
    //   103: iinc #3, 1
    //   106: swap
    //   107: aastore
    //   108: iload_0
    //   109: iload_1
    //   110: iadd
    //   111: dup
    //   112: istore_0
    //   113: iload #4
    //   115: if_icmpge -> 127
    //   118: aload_2
    //   119: iload_0
    //   120: invokevirtual charAt : (I)C
    //   123: istore_1
    //   124: goto -> 82
    //   127: aload #5
    //   129: putstatic burp/Zoe.a : [Ljava/lang/String;
    //   132: bipush #8
    //   134: anewarray java/lang/String
    //   137: putstatic burp/Zoe.b : [Ljava/lang/String;
    //   140: goto -> 300
    //   143: dup_x2
    //   144: pop
    //   145: invokevirtual toCharArray : ()[C
    //   148: dup_x1
    //   149: arraylength
    //   150: dup_x2
    //   151: pop
    //   152: iconst_0
    //   153: istore #6
    //   155: dup2_x1
    //   156: pop2
    //   157: dup_x2
    //   158: iconst_1
    //   159: if_icmpgt -> 260
    //   162: dup2
    //   163: swap
    //   164: iload #6
    //   166: dup2_x1
    //   167: caload
    //   168: swap
    //   169: iload #6
    //   171: bipush #7
    //   173: irem
    //   174: tableswitch default -> 242, 0 -> 212, 1 -> 217, 2 -> 222, 3 -> 227, 4 -> 232, 5 -> 237
    //   212: bipush #110
    //   214: goto -> 244
    //   217: bipush #60
    //   219: goto -> 244
    //   222: bipush #109
    //   224: goto -> 244
    //   227: bipush #77
    //   229: goto -> 244
    //   232: bipush #73
    //   234: goto -> 244
    //   237: bipush #20
    //   239: goto -> 244
    //   242: bipush #89
    //   244: ixor
    //   245: ixor
    //   246: i2c
    //   247: castore
    //   248: iinc #6, 1
    //   251: dup
    //   252: ifne -> 260
    //   255: dup2
    //   256: dup_x1
    //   257: goto -> 166
    //   260: dup2_x1
    //   261: pop2
    //   262: dup_x2
    //   263: iload #6
    //   265: if_icmpgt -> 162
    //   268: pop
    //   269: new java/lang/String
    //   272: dup_x1
    //   273: swap
    //   274: invokespecial <init> : ([C)V
    //   277: invokevirtual intern : ()Ljava/lang/String;
    //   280: swap
    //   281: pop
    //   282: swap
    //   283: tableswitch default -> 40, 0 -> 99
    //   300: new java/math/BigInteger
    //   303: dup
    //   304: iconst_1
    //   305: bipush #32
    //   307: newarray byte
    //   309: dup
    //   310: iconst_0
    //   311: bipush #99
    //   313: bastore
    //   314: dup
    //   315: iconst_1
    //   316: bipush #-73
    //   318: bastore
    //   319: dup
    //   320: iconst_2
    //   321: bipush #-79
    //   323: bastore
    //   324: dup
    //   325: iconst_3
    //   326: bipush #77
    //   328: bastore
    //   329: dup
    //   330: iconst_4
    //   331: bipush #58
    //   333: bastore
    //   334: dup
    //   335: iconst_5
    //   336: bipush #-43
    //   338: bastore
    //   339: dup
    //   340: bipush #6
    //   342: bipush #27
    //   344: bastore
    //   345: dup
    //   346: bipush #7
    //   348: bipush #44
    //   350: bastore
    //   351: dup
    //   352: bipush #8
    //   354: bipush #-99
    //   356: bastore
    //   357: dup
    //   358: bipush #9
    //   360: bipush #-24
    //   362: bastore
    //   363: dup
    //   364: bipush #10
    //   366: bipush #101
    //   368: bastore
    //   369: dup
    //   370: bipush #11
    //   372: bipush #10
    //   374: bastore
    //   375: dup
    //   376: bipush #12
    //   378: bipush #62
    //   380: bastore
    //   381: dup
    //   382: bipush #13
    //   384: bipush #12
    //   386: bastore
    //   387: dup
    //   388: bipush #14
    //   390: bipush #78
    //   392: bastore
    //   393: dup
    //   394: bipush #15
    //   396: bipush #83
    //   398: bastore
    //   399: dup
    //   400: bipush #16
    //   402: bipush #-39
    //   404: bastore
    //   405: dup
    //   406: bipush #17
    //   408: bipush #-24
    //   410: bastore
    //   411: dup
    //   412: bipush #18
    //   414: bipush #-99
    //   416: bastore
    //   417: dup
    //   418: bipush #19
    //   420: bipush #63
    //   422: bastore
    //   423: dup
    //   424: bipush #20
    //   426: bipush #61
    //   428: bastore
    //   429: dup
    //   430: bipush #21
    //   432: bipush #92
    //   434: bastore
    //   435: dup
    //   436: bipush #22
    //   438: bipush #-18
    //   440: bastore
    //   441: dup
    //   442: bipush #23
    //   444: bipush #48
    //   446: bastore
    //   447: dup
    //   448: bipush #24
    //   450: bipush #13
    //   452: bastore
    //   453: dup
    //   454: bipush #25
    //   456: bipush #98
    //   458: bastore
    //   459: dup
    //   460: bipush #26
    //   462: bipush #106
    //   464: bastore
    //   465: dup
    //   466: bipush #27
    //   468: bipush #-97
    //   470: bastore
    //   471: dup
    //   472: bipush #28
    //   474: bipush #93
    //   476: bastore
    //   477: dup
    //   478: bipush #29
    //   480: bipush #-2
    //   482: bastore
    //   483: dup
    //   484: bipush #30
    //   486: bipush #-98
    //   488: bastore
    //   489: dup
    //   490: bipush #31
    //   492: bipush #-36
    //   494: bastore
    //   495: invokespecial <init> : (I[B)V
    //   498: putstatic burp/Zoe.ZG : Ljava/lang/Object;
    //   501: sipush #6482
    //   504: sipush #9236
    //   507: invokestatic a : (II)Ljava/lang/String;
    //   510: putstatic burp/Zoe.ZE : Ljava/lang/String;
    //   513: return
  }
  
  private static Throwable a(Throwable paramThrowable) {
    return paramThrowable;
  }
  
  private static String a(int paramInt1, int paramInt2) {
    int i = (paramInt1 ^ 0x1956) & 0xFFFF;
    if (b[i] == null) {
      char[] arrayOfChar = a[i].toCharArray();
      switch (arrayOfChar[0] & 0xFF) {
        case 0:
        
        case 1:
        
        case 2:
        
        case 3:
        
        case 4:
        
        case 5:
        
        case 6:
        
        case 7:
        
        case 8:
        
        case 9:
        
        case 10:
        
        case 11:
        
        case 12:
        
        case 13:
        
        case 14:
        
        case 15:
        
        case 16:
        
        case 17:
        
        case 18:
        
        case 19:
        
        case 20:
        
        case 21:
        
        case 22:
        
        case 23:
        
        case 24:
        
        case 25:
        
        case 26:
        
        case 27:
        
        case 28:
        
        case 29:
        
        case 30:
        
        case 31:
        
        case 32:
        
        case 33:
        
        case 34:
        
        case 35:
        
        case 36:
        
        case 37:
        
        case 38:
        
        case 39:
        
        case 40:
        
        case 41:
        
        case 42:
        
        case 43:
        
        case 44:
        
        case 45:
        
        case 46:
        
        case 47:
        
        case 48:
        
        case 49:
        
        case 50:
        
        case 51:
        
        case 52:
        
        case 53:
        
        case 54:
        
        case 55:
        
        case 56:
        
        case 57:
        
        case 58:
        
        case 59:
        
        case 60:
        
        case 61:
        
        case 62:
        
        case 63:
        
        case 64:
        
        case 65:
        
        case 66:
        
        case 67:
        
        case 68:
        
        case 69:
        
        case 70:
        
        case 71:
        
        case 72:
        
        case 73:
        
        case 74:
        
        case 75:
        
        case 76:
        
        case 77:
        
        case 78:
        
        case 79:
        
        case 80:
        
        case 81:
        
        case 82:
        
        case 83:
        
        case 84:
        
        case 85:
        
        case 86:
        
        case 87:
        
        case 88:
        
        case 89:
        
        case 90:
        
        case 91:
        
        case 92:
        
        case 93:
        
        case 94:
        
        case 95:
        
        case 96:
        
        case 97:
        
        case 98:
        
        case 99:
        
        case 100:
        
        case 101:
        
        case 102:
        
        case 103:
        
        case 104:
        
        case 105:
        
        case 106:
        
        case 107:
        
        case 108:
        
        case 109:
        
        case 110:
        
        case 111:
        
        case 112:
        
        case 113:
        
        case 114:
        
        case 115:
        
        case 116:
        
        case 117:
        
        case 118:
        
        case 119:
        
        case 120:
        
        case 121:
        
        case 122:
        
        case 123:
        
        case 124:
        
        case 125:
        
        case 126:
        
        case 127:
        
        case 128:
        
        case 129:
        
        case 130:
        
        case 131:
        
        case 132:
        
        case 133:
        
        case 134:
        
        case 135:
        
        case 136:
        
        case 137:
        
        case 138:
        
        case 139:
        
        case 140:
        
        case 141:
        
        case 142:
        
        case 143:
        
        case 144:
        
        case 145:
        
        case 146:
        
        case 147:
        
        case 148:
        
        case 149:
        
        case 150:
        
        case 151:
        
        case 152:
        
        case 153:
        
        case 154:
        
        case 155:
        
        case 156:
        
        case 157:
        
        case 158:
        
        case 159:
        
        case 160:
        
        case 161:
        
        case 162:
        
        case 163:
        
        case 164:
        
        case 165:
        
        case 166:
        
        case 167:
        
        case 168:
        
        case 169:
        
        case 170:
        
        case 171:
        
        case 172:
        
        case 173:
        
        case 174:
        
        case 175:
        
        case 176:
        
        case 177:
        
        case 178:
        
        case 179:
        
        case 180:
        
        case 181:
        
        case 182:
        
        case 183:
        
        case 184:
        
        case 185:
        
        case 186:
        
        case 187:
        
        case 188:
        
        case 189:
        
        case 190:
        
        case 191:
        
        case 192:
        
        case 193:
        
        case 194:
        
        case 195:
        
        case 196:
        
        case 197:
        
        case 198:
        
        case 199:
        
        case 200:
        
        case 201:
        
        case 202:
        
        case 203:
        
        case 204:
        
        case 205:
        
        case 206:
        
        case 207:
        
        case 208:
        
        case 209:
        
        case 210:
        
        case 211:
        
        case 212:
        
        case 213:
        
        case 214:
        
        case 215:
        
        case 216:
        
        case 217:
        
        case 218:
        
        case 219:
        
        case 220:
        
        case 221:
        
        case 222:
        
        case 223:
        
        case 224:
        
        case 225:
        
        case 226:
        
        case 227:
        
        case 228:
        
        case 229:
        
        case 230:
        
        case 231:
        
        case 232:
        
        case 233:
        
        case 234:
        
        case 235:
        
        case 236:
        
        case 237:
        
        case 238:
        
        case 239:
        
        case 240:
        
        case 241:
        
        case 242:
        
        case 243:
        
        case 244:
        
        case 245:
        
        case 246:
        
        case 247:
        
        case 248:
        
        case 249:
        
        case 250:
        
        case 251:
        
        case 252:
        
        case 253:
        
        case 254:
        
        default:
          break;
      } 
      byte b1 = 76;
      int j = (paramInt2 & 0xFF) - b1;
      if (j < 0)
        j += 256; 
      int k = ((paramInt2 & 0xFFFF) >>> 8) - b1;
      if (k < 0)
        k += 256; 
      for (byte b2 = 0; b2 < arrayOfChar.length; b2++) {
        int m = b2 % 2;
        if (m == 0) {
          arrayOfChar[b2] = (char)(arrayOfChar[b2] ^ j);
          j = ((j >>> 3 | j << 5) ^ arrayOfChar[b2]) & 0xFF;
        } else {
          arrayOfChar[b2] = (char)(arrayOfChar[b2] ^ k);
          k = ((k >>> 3 | k << 5) ^ arrayOfChar[b2]) & 0xFF;
        } 
      } 
      b[i] = (new String(arrayOfChar)).intern();
    } 
    return b[i];
  }
}


/* Location:              C:\Program Files\BurpSuitePro\burpsuite_pro.jar!\burp\Zoe.class
 * Java compiler version: 21 (65.0)
 * JD-Core Version:       1.1.3
 */