package burp;

import java.math.BigInteger;

class Zos extends ClassLoader {
  static Object ZB;
  
  static String Za;
  
  private static final String[] a;
  
  private static final String[] b;
  
  static void ZU(Object paramObject) {
    Zs1d.Zl = a(-15109, -25511);
    Zs1d.Zo = new BigInteger(a(-15131, -11476));
    boolean bool = Zt2e.ZK();
    try {
      try {
        if (Zrtp.Zq.charAt(Math.abs(((BigInteger)Zx5w.Zo).intValue() % 32)) > Zt85.ZR.charAt(Math.abs(((BigInteger)Zeub.ZD).intValue() % 32))) {
          try {
            Zenr.Zx(Class.forName(a(-15130, 15975)));
            if (bool)
              Zlem.ZP(Class.forName(a(-15134, 4040))); 
          } catch (Throwable throwable) {
            throw a(null);
          } 
          return;
        } 
      } catch (Throwable throwable) {
        throw a(null);
      } 
      Zlem.ZP(Class.forName(a(-15134, 4040)));
    } catch (Throwable throwable) {}
  }
  
  static boolean Zm(Object[] paramArrayOfObject, Object paramObject) throws Throwable {
    // Byte code:
    //   0: invokestatic ZK : ()Z
    //   3: istore_2
    //   4: new java/lang/StringBuilder
    //   7: dup
    //   8: invokespecial <init> : ()V
    //   11: astore_3
    //   12: iconst_0
    //   13: istore #4
    //   15: iload #4
    //   17: bipush #32
    //   19: if_icmpge -> 1355
    //   22: iload #4
    //   24: tableswitch default -> 1348, 0 -> 168, 1 -> 205, 2 -> 242, 3 -> 279, 4 -> 316, 5 -> 353, 6 -> 390, 7 -> 427, 8 -> 464, 9 -> 501, 10 -> 538, 11 -> 575, 12 -> 612, 13 -> 649, 14 -> 686, 15 -> 723, 16 -> 760, 17 -> 797, 18 -> 834, 19 -> 871, 20 -> 908, 21 -> 945, 22 -> 982, 23 -> 1019, 24 -> 1056, 25 -> 1093, 26 -> 1130, 27 -> 1167, 28 -> 1204, 29 -> 1241, 30 -> 1278, 31 -> 1315
    //   168: aload_3
    //   169: getstatic burp/Zm63.Zs : Ljava/lang/String;
    //   172: getstatic burp/Zgpx.ZQ : Ljava/lang/Object;
    //   175: checkcast java/math/BigInteger
    //   178: invokevirtual intValue : ()I
    //   181: bipush #32
    //   183: irem
    //   184: invokestatic abs : (I)I
    //   187: invokevirtual charAt : (I)C
    //   190: invokevirtual append : (C)Ljava/lang/StringBuilder;
    //   193: pop
    //   194: iload_2
    //   195: ifeq -> 1348
    //   198: goto -> 205
    //   201: invokestatic a : (Ljava/lang/Throwable;)Ljava/lang/Throwable;
    //   204: athrow
    //   205: aload_3
    //   206: getstatic burp/Zst7.Zi : Ljava/lang/String;
    //   209: getstatic burp/Zx5w.Zo : Ljava/lang/Object;
    //   212: checkcast java/math/BigInteger
    //   215: invokevirtual intValue : ()I
    //   218: bipush #32
    //   220: irem
    //   221: invokestatic abs : (I)I
    //   224: invokevirtual charAt : (I)C
    //   227: invokevirtual append : (C)Ljava/lang/StringBuilder;
    //   230: pop
    //   231: iload_2
    //   232: ifeq -> 1348
    //   235: goto -> 242
    //   238: invokestatic a : (Ljava/lang/Throwable;)Ljava/lang/Throwable;
    //   241: athrow
    //   242: aload_3
    //   243: getstatic burp/Ztlo.Zs : Ljava/lang/String;
    //   246: getstatic burp/Zb4d.Ze : Ljava/lang/Object;
    //   249: checkcast java/math/BigInteger
    //   252: invokevirtual intValue : ()I
    //   255: bipush #32
    //   257: irem
    //   258: invokestatic abs : (I)I
    //   261: invokevirtual charAt : (I)C
    //   264: invokevirtual append : (C)Ljava/lang/StringBuilder;
    //   267: pop
    //   268: iload_2
    //   269: ifeq -> 1348
    //   272: goto -> 279
    //   275: invokestatic a : (Ljava/lang/Throwable;)Ljava/lang/Throwable;
    //   278: athrow
    //   279: aload_3
    //   280: getstatic burp/Zt85.ZR : Ljava/lang/String;
    //   283: getstatic burp/Zg6z.ZS : Ljava/lang/Object;
    //   286: checkcast java/math/BigInteger
    //   289: invokevirtual intValue : ()I
    //   292: bipush #32
    //   294: irem
    //   295: invokestatic abs : (I)I
    //   298: invokevirtual charAt : (I)C
    //   301: invokevirtual append : (C)Ljava/lang/StringBuilder;
    //   304: pop
    //   305: iload_2
    //   306: ifeq -> 1348
    //   309: goto -> 316
    //   312: invokestatic a : (Ljava/lang/Throwable;)Ljava/lang/Throwable;
    //   315: athrow
    //   316: aload_3
    //   317: getstatic burp/Zb0q.Zr : Ljava/lang/String;
    //   320: getstatic burp/Zes.Zx : Ljava/lang/Object;
    //   323: checkcast java/math/BigInteger
    //   326: invokevirtual intValue : ()I
    //   329: bipush #32
    //   331: irem
    //   332: invokestatic abs : (I)I
    //   335: invokevirtual charAt : (I)C
    //   338: invokevirtual append : (C)Ljava/lang/StringBuilder;
    //   341: pop
    //   342: iload_2
    //   343: ifeq -> 1348
    //   346: goto -> 353
    //   349: invokestatic a : (Ljava/lang/Throwable;)Ljava/lang/Throwable;
    //   352: athrow
    //   353: aload_3
    //   354: getstatic burp/Zeqx.Zu : Ljava/lang/String;
    //   357: getstatic burp/Zezi.ZQ : Ljava/lang/Object;
    //   360: checkcast java/math/BigInteger
    //   363: invokevirtual intValue : ()I
    //   366: bipush #32
    //   368: irem
    //   369: invokestatic abs : (I)I
    //   372: invokevirtual charAt : (I)C
    //   375: invokevirtual append : (C)Ljava/lang/StringBuilder;
    //   378: pop
    //   379: iload_2
    //   380: ifeq -> 1348
    //   383: goto -> 390
    //   386: invokestatic a : (Ljava/lang/Throwable;)Ljava/lang/Throwable;
    //   389: athrow
    //   390: aload_3
    //   391: getstatic burp/Zxxh.Zm : Ljava/lang/String;
    //   394: getstatic burp/Zl7x.Za : Ljava/lang/Object;
    //   397: checkcast java/math/BigInteger
    //   400: invokevirtual intValue : ()I
    //   403: bipush #32
    //   405: irem
    //   406: invokestatic abs : (I)I
    //   409: invokevirtual charAt : (I)C
    //   412: invokevirtual append : (C)Ljava/lang/StringBuilder;
    //   415: pop
    //   416: iload_2
    //   417: ifeq -> 1348
    //   420: goto -> 427
    //   423: invokestatic a : (Ljava/lang/Throwable;)Ljava/lang/Throwable;
    //   426: athrow
    //   427: aload_3
    //   428: getstatic burp/Zek4.Zo : Ljava/lang/String;
    //   431: getstatic burp/Zb_1.ZK : Ljava/lang/Object;
    //   434: checkcast java/math/BigInteger
    //   437: invokevirtual intValue : ()I
    //   440: bipush #32
    //   442: irem
    //   443: invokestatic abs : (I)I
    //   446: invokevirtual charAt : (I)C
    //   449: invokevirtual append : (C)Ljava/lang/StringBuilder;
    //   452: pop
    //   453: iload_2
    //   454: ifeq -> 1348
    //   457: goto -> 464
    //   460: invokestatic a : (Ljava/lang/Throwable;)Ljava/lang/Throwable;
    //   463: athrow
    //   464: aload_3
    //   465: getstatic burp/Zzts.Zk : Ljava/lang/String;
    //   468: getstatic burp/Zkca.ZQ : Ljava/lang/Object;
    //   471: checkcast java/math/BigInteger
    //   474: invokevirtual intValue : ()I
    //   477: bipush #32
    //   479: irem
    //   480: invokestatic abs : (I)I
    //   483: invokevirtual charAt : (I)C
    //   486: invokevirtual append : (C)Ljava/lang/StringBuilder;
    //   489: pop
    //   490: iload_2
    //   491: ifeq -> 1348
    //   494: goto -> 501
    //   497: invokestatic a : (Ljava/lang/Throwable;)Ljava/lang/Throwable;
    //   500: athrow
    //   501: aload_3
    //   502: getstatic burp/Zlt1.ZA : Ljava/lang/String;
    //   505: getstatic burp/Ze8j.ZQ : Ljava/lang/Object;
    //   508: checkcast java/math/BigInteger
    //   511: invokevirtual intValue : ()I
    //   514: bipush #32
    //   516: irem
    //   517: invokestatic abs : (I)I
    //   520: invokevirtual charAt : (I)C
    //   523: invokevirtual append : (C)Ljava/lang/StringBuilder;
    //   526: pop
    //   527: iload_2
    //   528: ifeq -> 1348
    //   531: goto -> 538
    //   534: invokestatic a : (Ljava/lang/Throwable;)Ljava/lang/Throwable;
    //   537: athrow
    //   538: aload_3
    //   539: getstatic burp/Zzre.Zr : Ljava/lang/String;
    //   542: getstatic burp/Zrww.ZN : Ljava/lang/Object;
    //   545: checkcast java/math/BigInteger
    //   548: invokevirtual intValue : ()I
    //   551: bipush #32
    //   553: irem
    //   554: invokestatic abs : (I)I
    //   557: invokevirtual charAt : (I)C
    //   560: invokevirtual append : (C)Ljava/lang/StringBuilder;
    //   563: pop
    //   564: iload_2
    //   565: ifeq -> 1348
    //   568: goto -> 575
    //   571: invokestatic a : (Ljava/lang/Throwable;)Ljava/lang/Throwable;
    //   574: athrow
    //   575: aload_3
    //   576: getstatic burp/Zm0d.ZV : Ljava/lang/String;
    //   579: getstatic burp/Zxju.ZN : Ljava/lang/Object;
    //   582: checkcast java/math/BigInteger
    //   585: invokevirtual intValue : ()I
    //   588: bipush #32
    //   590: irem
    //   591: invokestatic abs : (I)I
    //   594: invokevirtual charAt : (I)C
    //   597: invokevirtual append : (C)Ljava/lang/StringBuilder;
    //   600: pop
    //   601: iload_2
    //   602: ifeq -> 1348
    //   605: goto -> 612
    //   608: invokestatic a : (Ljava/lang/Throwable;)Ljava/lang/Throwable;
    //   611: athrow
    //   612: aload_3
    //   613: getstatic burp/Zrfs.ZD : Ljava/lang/String;
    //   616: getstatic burp/Zea8.ZF : Ljava/lang/Object;
    //   619: checkcast java/math/BigInteger
    //   622: invokevirtual intValue : ()I
    //   625: bipush #32
    //   627: irem
    //   628: invokestatic abs : (I)I
    //   631: invokevirtual charAt : (I)C
    //   634: invokevirtual append : (C)Ljava/lang/StringBuilder;
    //   637: pop
    //   638: iload_2
    //   639: ifeq -> 1348
    //   642: goto -> 649
    //   645: invokestatic a : (Ljava/lang/Throwable;)Ljava/lang/Throwable;
    //   648: athrow
    //   649: aload_3
    //   650: getstatic burp/Zz5e.Zd : Ljava/lang/String;
    //   653: getstatic burp/Zz5e.Zl : Ljava/lang/Object;
    //   656: checkcast java/math/BigInteger
    //   659: invokevirtual intValue : ()I
    //   662: bipush #32
    //   664: irem
    //   665: invokestatic abs : (I)I
    //   668: invokevirtual charAt : (I)C
    //   671: invokevirtual append : (C)Ljava/lang/StringBuilder;
    //   674: pop
    //   675: iload_2
    //   676: ifeq -> 1348
    //   679: goto -> 686
    //   682: invokestatic a : (Ljava/lang/Throwable;)Ljava/lang/Throwable;
    //   685: athrow
    //   686: aload_3
    //   687: getstatic burp/Zz4m.ZI : Ljava/lang/String;
    //   690: getstatic burp/Zge9.ZT : Ljava/lang/Object;
    //   693: checkcast java/math/BigInteger
    //   696: invokevirtual intValue : ()I
    //   699: bipush #32
    //   701: irem
    //   702: invokestatic abs : (I)I
    //   705: invokevirtual charAt : (I)C
    //   708: invokevirtual append : (C)Ljava/lang/StringBuilder;
    //   711: pop
    //   712: iload_2
    //   713: ifeq -> 1348
    //   716: goto -> 723
    //   719: invokestatic a : (Ljava/lang/Throwable;)Ljava/lang/Throwable;
    //   722: athrow
    //   723: aload_3
    //   724: getstatic burp/Zrd3.Z_ : Ljava/lang/String;
    //   727: getstatic burp/Ze4a.ZP : Ljava/lang/Object;
    //   730: checkcast java/math/BigInteger
    //   733: invokevirtual intValue : ()I
    //   736: bipush #32
    //   738: irem
    //   739: invokestatic abs : (I)I
    //   742: invokevirtual charAt : (I)C
    //   745: invokevirtual append : (C)Ljava/lang/StringBuilder;
    //   748: pop
    //   749: iload_2
    //   750: ifeq -> 1348
    //   753: goto -> 760
    //   756: invokestatic a : (Ljava/lang/Throwable;)Ljava/lang/Throwable;
    //   759: athrow
    //   760: aload_3
    //   761: getstatic burp/Zemp.Zs : Ljava/lang/String;
    //   764: getstatic burp/Zv8l.ZL : Ljava/lang/Object;
    //   767: checkcast java/math/BigInteger
    //   770: invokevirtual intValue : ()I
    //   773: bipush #32
    //   775: irem
    //   776: invokestatic abs : (I)I
    //   779: invokevirtual charAt : (I)C
    //   782: invokevirtual append : (C)Ljava/lang/StringBuilder;
    //   785: pop
    //   786: iload_2
    //   787: ifeq -> 1348
    //   790: goto -> 797
    //   793: invokestatic a : (Ljava/lang/Throwable;)Ljava/lang/Throwable;
    //   796: athrow
    //   797: aload_3
    //   798: getstatic burp/Ze4g.Zk : Ljava/lang/String;
    //   801: getstatic burp/Ztl6.ZQ : Ljava/lang/Object;
    //   804: checkcast java/math/BigInteger
    //   807: invokevirtual intValue : ()I
    //   810: bipush #32
    //   812: irem
    //   813: invokestatic abs : (I)I
    //   816: invokevirtual charAt : (I)C
    //   819: invokevirtual append : (C)Ljava/lang/StringBuilder;
    //   822: pop
    //   823: iload_2
    //   824: ifeq -> 1348
    //   827: goto -> 834
    //   830: invokestatic a : (Ljava/lang/Throwable;)Ljava/lang/Throwable;
    //   833: athrow
    //   834: aload_3
    //   835: getstatic burp/Zgpx.Z_ : Ljava/lang/String;
    //   838: getstatic burp/Zgu4.Zs : Ljava/lang/Object;
    //   841: checkcast java/math/BigInteger
    //   844: invokevirtual intValue : ()I
    //   847: bipush #32
    //   849: irem
    //   850: invokestatic abs : (I)I
    //   853: invokevirtual charAt : (I)C
    //   856: invokevirtual append : (C)Ljava/lang/StringBuilder;
    //   859: pop
    //   860: iload_2
    //   861: ifeq -> 1348
    //   864: goto -> 871
    //   867: invokestatic a : (Ljava/lang/Throwable;)Ljava/lang/Throwable;
    //   870: athrow
    //   871: aload_3
    //   872: getstatic burp/Zs3m.Zl : Ljava/lang/String;
    //   875: getstatic burp/Zgu4.Zs : Ljava/lang/Object;
    //   878: checkcast java/math/BigInteger
    //   881: invokevirtual intValue : ()I
    //   884: bipush #32
    //   886: irem
    //   887: invokestatic abs : (I)I
    //   890: invokevirtual charAt : (I)C
    //   893: invokevirtual append : (C)Ljava/lang/StringBuilder;
    //   896: pop
    //   897: iload_2
    //   898: ifeq -> 1348
    //   901: goto -> 908
    //   904: invokestatic a : (Ljava/lang/Throwable;)Ljava/lang/Throwable;
    //   907: athrow
    //   908: aload_3
    //   909: getstatic burp/Zm3x.Zu : Ljava/lang/String;
    //   912: getstatic burp/Ztl6.ZQ : Ljava/lang/Object;
    //   915: checkcast java/math/BigInteger
    //   918: invokevirtual intValue : ()I
    //   921: bipush #32
    //   923: irem
    //   924: invokestatic abs : (I)I
    //   927: invokevirtual charAt : (I)C
    //   930: invokevirtual append : (C)Ljava/lang/StringBuilder;
    //   933: pop
    //   934: iload_2
    //   935: ifeq -> 1348
    //   938: goto -> 945
    //   941: invokestatic a : (Ljava/lang/Throwable;)Ljava/lang/Throwable;
    //   944: athrow
    //   945: aload_3
    //   946: getstatic burp/Zmui.ZY : Ljava/lang/String;
    //   949: getstatic burp/Zxxo.ZJ : Ljava/lang/Object;
    //   952: checkcast java/math/BigInteger
    //   955: invokevirtual intValue : ()I
    //   958: bipush #32
    //   960: irem
    //   961: invokestatic abs : (I)I
    //   964: invokevirtual charAt : (I)C
    //   967: invokevirtual append : (C)Ljava/lang/StringBuilder;
    //   970: pop
    //   971: iload_2
    //   972: ifeq -> 1348
    //   975: goto -> 982
    //   978: invokestatic a : (Ljava/lang/Throwable;)Ljava/lang/Throwable;
    //   981: athrow
    //   982: aload_3
    //   983: getstatic burp/Zewr.ZW : Ljava/lang/String;
    //   986: getstatic burp/Zka9.Zd : Ljava/lang/Object;
    //   989: checkcast java/math/BigInteger
    //   992: invokevirtual intValue : ()I
    //   995: bipush #32
    //   997: irem
    //   998: invokestatic abs : (I)I
    //   1001: invokevirtual charAt : (I)C
    //   1004: invokevirtual append : (C)Ljava/lang/StringBuilder;
    //   1007: pop
    //   1008: iload_2
    //   1009: ifeq -> 1348
    //   1012: goto -> 1019
    //   1015: invokestatic a : (Ljava/lang/Throwable;)Ljava/lang/Throwable;
    //   1018: athrow
    //   1019: aload_3
    //   1020: getstatic burp/Zlxw.ZC : Ljava/lang/String;
    //   1023: getstatic burp/Zbx4.Zw : Ljava/lang/Object;
    //   1026: checkcast java/math/BigInteger
    //   1029: invokevirtual intValue : ()I
    //   1032: bipush #32
    //   1034: irem
    //   1035: invokestatic abs : (I)I
    //   1038: invokevirtual charAt : (I)C
    //   1041: invokevirtual append : (C)Ljava/lang/StringBuilder;
    //   1044: pop
    //   1045: iload_2
    //   1046: ifeq -> 1348
    //   1049: goto -> 1056
    //   1052: invokestatic a : (Ljava/lang/Throwable;)Ljava/lang/Throwable;
    //   1055: athrow
    //   1056: aload_3
    //   1057: getstatic burp/Zld9.Zx : Ljava/lang/String;
    //   1060: getstatic burp/Zg61.Zp : Ljava/lang/Object;
    //   1063: checkcast java/math/BigInteger
    //   1066: invokevirtual intValue : ()I
    //   1069: bipush #32
    //   1071: irem
    //   1072: invokestatic abs : (I)I
    //   1075: invokevirtual charAt : (I)C
    //   1078: invokevirtual append : (C)Ljava/lang/StringBuilder;
    //   1081: pop
    //   1082: iload_2
    //   1083: ifeq -> 1348
    //   1086: goto -> 1093
    //   1089: invokestatic a : (Ljava/lang/Throwable;)Ljava/lang/Throwable;
    //   1092: athrow
    //   1093: aload_3
    //   1094: getstatic burp/Ztr5.ZY : Ljava/lang/String;
    //   1097: getstatic burp/Zegv.ZL : Ljava/lang/Object;
    //   1100: checkcast java/math/BigInteger
    //   1103: invokevirtual intValue : ()I
    //   1106: bipush #32
    //   1108: irem
    //   1109: invokestatic abs : (I)I
    //   1112: invokevirtual charAt : (I)C
    //   1115: invokevirtual append : (C)Ljava/lang/StringBuilder;
    //   1118: pop
    //   1119: iload_2
    //   1120: ifeq -> 1348
    //   1123: goto -> 1130
    //   1126: invokestatic a : (Ljava/lang/Throwable;)Ljava/lang/Throwable;
    //   1129: athrow
    //   1130: aload_3
    //   1131: getstatic burp/Zkdq.ZZ : Ljava/lang/String;
    //   1134: getstatic burp/Zxcn.Zq : Ljava/lang/Object;
    //   1137: checkcast java/math/BigInteger
    //   1140: invokevirtual intValue : ()I
    //   1143: bipush #32
    //   1145: irem
    //   1146: invokestatic abs : (I)I
    //   1149: invokevirtual charAt : (I)C
    //   1152: invokevirtual append : (C)Ljava/lang/StringBuilder;
    //   1155: pop
    //   1156: iload_2
    //   1157: ifeq -> 1348
    //   1160: goto -> 1167
    //   1163: invokestatic a : (Ljava/lang/Throwable;)Ljava/lang/Throwable;
    //   1166: athrow
    //   1167: aload_3
    //   1168: getstatic burp/Zdv.Zz : Ljava/lang/String;
    //   1171: getstatic burp/Zxju.ZN : Ljava/lang/Object;
    //   1174: checkcast java/math/BigInteger
    //   1177: invokevirtual intValue : ()I
    //   1180: bipush #32
    //   1182: irem
    //   1183: invokestatic abs : (I)I
    //   1186: invokevirtual charAt : (I)C
    //   1189: invokevirtual append : (C)Ljava/lang/StringBuilder;
    //   1192: pop
    //   1193: iload_2
    //   1194: ifeq -> 1348
    //   1197: goto -> 1204
    //   1200: invokestatic a : (Ljava/lang/Throwable;)Ljava/lang/Throwable;
    //   1203: athrow
    //   1204: aload_3
    //   1205: getstatic burp/Zg2u.Zy : Ljava/lang/String;
    //   1208: getstatic burp/Zr1t.ZP : Ljava/lang/Object;
    //   1211: checkcast java/math/BigInteger
    //   1214: invokevirtual intValue : ()I
    //   1217: bipush #32
    //   1219: irem
    //   1220: invokestatic abs : (I)I
    //   1223: invokevirtual charAt : (I)C
    //   1226: invokevirtual append : (C)Ljava/lang/StringBuilder;
    //   1229: pop
    //   1230: iload_2
    //   1231: ifeq -> 1348
    //   1234: goto -> 1241
    //   1237: invokestatic a : (Ljava/lang/Throwable;)Ljava/lang/Throwable;
    //   1240: athrow
    //   1241: aload_3
    //   1242: getstatic burp/Zr2q.ZA : Ljava/lang/String;
    //   1245: getstatic burp/Zb3d.Zw : Ljava/lang/Object;
    //   1248: checkcast java/math/BigInteger
    //   1251: invokevirtual intValue : ()I
    //   1254: bipush #32
    //   1256: irem
    //   1257: invokestatic abs : (I)I
    //   1260: invokevirtual charAt : (I)C
    //   1263: invokevirtual append : (C)Ljava/lang/StringBuilder;
    //   1266: pop
    //   1267: iload_2
    //   1268: ifeq -> 1348
    //   1271: goto -> 1278
    //   1274: invokestatic a : (Ljava/lang/Throwable;)Ljava/lang/Throwable;
    //   1277: athrow
    //   1278: aload_3
    //   1279: getstatic burp/Zb6m.ZR : Ljava/lang/String;
    //   1282: getstatic burp/Zst7.ZI : Ljava/lang/Object;
    //   1285: checkcast java/math/BigInteger
    //   1288: invokevirtual intValue : ()I
    //   1291: bipush #32
    //   1293: irem
    //   1294: invokestatic abs : (I)I
    //   1297: invokevirtual charAt : (I)C
    //   1300: invokevirtual append : (C)Ljava/lang/StringBuilder;
    //   1303: pop
    //   1304: iload_2
    //   1305: ifeq -> 1348
    //   1308: goto -> 1315
    //   1311: invokestatic a : (Ljava/lang/Throwable;)Ljava/lang/Throwable;
    //   1314: athrow
    //   1315: aload_3
    //   1316: getstatic burp/Zmhq.Zy : Ljava/lang/String;
    //   1319: getstatic burp/Zle9.ZI : Ljava/lang/Object;
    //   1322: checkcast java/math/BigInteger
    //   1325: invokevirtual intValue : ()I
    //   1328: bipush #32
    //   1330: irem
    //   1331: invokestatic abs : (I)I
    //   1334: invokevirtual charAt : (I)C
    //   1337: invokevirtual append : (C)Ljava/lang/StringBuilder;
    //   1340: pop
    //   1341: goto -> 1348
    //   1344: invokestatic a : (Ljava/lang/Throwable;)Ljava/lang/Throwable;
    //   1347: athrow
    //   1348: iinc #4, 1
    //   1351: iload_2
    //   1352: ifeq -> 15
    //   1355: aload_3
    //   1356: invokevirtual toString : ()Ljava/lang/String;
    //   1359: putstatic burp/Zt1h.Zw : Ljava/lang/String;
    //   1362: new java/lang/StringBuilder
    //   1365: dup
    //   1366: invokespecial <init> : ()V
    //   1369: astore #4
    //   1371: iconst_0
    //   1372: istore #5
    //   1374: iload #5
    //   1376: bipush #32
    //   1378: if_icmpge -> 2743
    //   1381: iload #5
    //   1383: tableswitch default -> 2736, 0 -> 1524, 1 -> 1562, 2 -> 1600, 3 -> 1638, 4 -> 1676, 5 -> 1714, 6 -> 1752, 7 -> 1790, 8 -> 1828, 9 -> 1866, 10 -> 1904, 11 -> 1942, 12 -> 1980, 13 -> 2018, 14 -> 2056, 15 -> 2094, 16 -> 2132, 17 -> 2170, 18 -> 2208, 19 -> 2246, 20 -> 2284, 21 -> 2322, 22 -> 2360, 23 -> 2398, 24 -> 2436, 25 -> 2474, 26 -> 2512, 27 -> 2550, 28 -> 2588, 29 -> 2626, 30 -> 2664, 31 -> 2702
    //   1524: aload #4
    //   1526: getstatic burp/Zxdy.Zm : Ljava/lang/String;
    //   1529: getstatic burp/Zsjc.ZX : Ljava/lang/Object;
    //   1532: checkcast java/math/BigInteger
    //   1535: invokevirtual intValue : ()I
    //   1538: bipush #32
    //   1540: irem
    //   1541: invokestatic abs : (I)I
    //   1544: invokevirtual charAt : (I)C
    //   1547: invokevirtual append : (C)Ljava/lang/StringBuilder;
    //   1550: pop
    //   1551: iload_2
    //   1552: ifeq -> 2736
    //   1555: goto -> 1562
    //   1558: invokestatic a : (Ljava/lang/Throwable;)Ljava/lang/Throwable;
    //   1561: athrow
    //   1562: aload #4
    //   1564: getstatic burp/Zbnz.Zp : Ljava/lang/String;
    //   1567: getstatic burp/Ztle.ZP : Ljava/lang/Object;
    //   1570: checkcast java/math/BigInteger
    //   1573: invokevirtual intValue : ()I
    //   1576: bipush #32
    //   1578: irem
    //   1579: invokestatic abs : (I)I
    //   1582: invokevirtual charAt : (I)C
    //   1585: invokevirtual append : (C)Ljava/lang/StringBuilder;
    //   1588: pop
    //   1589: iload_2
    //   1590: ifeq -> 2736
    //   1593: goto -> 1600
    //   1596: invokestatic a : (Ljava/lang/Throwable;)Ljava/lang/Throwable;
    //   1599: athrow
    //   1600: aload #4
    //   1602: getstatic burp/Zr_x.ZF : Ljava/lang/String;
    //   1605: getstatic burp/Zr2q.ZS : Ljava/lang/Object;
    //   1608: checkcast java/math/BigInteger
    //   1611: invokevirtual intValue : ()I
    //   1614: bipush #32
    //   1616: irem
    //   1617: invokestatic abs : (I)I
    //   1620: invokevirtual charAt : (I)C
    //   1623: invokevirtual append : (C)Ljava/lang/StringBuilder;
    //   1626: pop
    //   1627: iload_2
    //   1628: ifeq -> 2736
    //   1631: goto -> 1638
    //   1634: invokestatic a : (Ljava/lang/Throwable;)Ljava/lang/Throwable;
    //   1637: athrow
    //   1638: aload #4
    //   1640: getstatic burp/Zk5k.Zx : Ljava/lang/String;
    //   1643: getstatic burp/Zm69.Zg : Ljava/lang/Object;
    //   1646: checkcast java/math/BigInteger
    //   1649: invokevirtual intValue : ()I
    //   1652: bipush #32
    //   1654: irem
    //   1655: invokestatic abs : (I)I
    //   1658: invokevirtual charAt : (I)C
    //   1661: invokevirtual append : (C)Ljava/lang/StringBuilder;
    //   1664: pop
    //   1665: iload_2
    //   1666: ifeq -> 2736
    //   1669: goto -> 1676
    //   1672: invokestatic a : (Ljava/lang/Throwable;)Ljava/lang/Throwable;
    //   1675: athrow
    //   1676: aload #4
    //   1678: getstatic burp/Zrd2.Zj : Ljava/lang/String;
    //   1681: getstatic burp/Zs5y.Zd : Ljava/lang/Object;
    //   1684: checkcast java/math/BigInteger
    //   1687: invokevirtual intValue : ()I
    //   1690: bipush #32
    //   1692: irem
    //   1693: invokestatic abs : (I)I
    //   1696: invokevirtual charAt : (I)C
    //   1699: invokevirtual append : (C)Ljava/lang/StringBuilder;
    //   1702: pop
    //   1703: iload_2
    //   1704: ifeq -> 2736
    //   1707: goto -> 1714
    //   1710: invokestatic a : (Ljava/lang/Throwable;)Ljava/lang/Throwable;
    //   1713: athrow
    //   1714: aload #4
    //   1716: getstatic burp/Zmdf.Zo : Ljava/lang/String;
    //   1719: getstatic burp/Zlsg.ZD : Ljava/lang/Object;
    //   1722: checkcast java/math/BigInteger
    //   1725: invokevirtual intValue : ()I
    //   1728: bipush #32
    //   1730: irem
    //   1731: invokestatic abs : (I)I
    //   1734: invokevirtual charAt : (I)C
    //   1737: invokevirtual append : (C)Ljava/lang/StringBuilder;
    //   1740: pop
    //   1741: iload_2
    //   1742: ifeq -> 2736
    //   1745: goto -> 1752
    //   1748: invokestatic a : (Ljava/lang/Throwable;)Ljava/lang/Throwable;
    //   1751: athrow
    //   1752: aload #4
    //   1754: getstatic burp/Zzre.Zr : Ljava/lang/String;
    //   1757: getstatic burp/Zm0d.Zz : Ljava/lang/Object;
    //   1760: checkcast java/math/BigInteger
    //   1763: invokevirtual intValue : ()I
    //   1766: bipush #32
    //   1768: irem
    //   1769: invokestatic abs : (I)I
    //   1772: invokevirtual charAt : (I)C
    //   1775: invokevirtual append : (C)Ljava/lang/StringBuilder;
    //   1778: pop
    //   1779: iload_2
    //   1780: ifeq -> 2736
    //   1783: goto -> 1790
    //   1786: invokestatic a : (Ljava/lang/Throwable;)Ljava/lang/Throwable;
    //   1789: athrow
    //   1790: aload #4
    //   1792: getstatic burp/Zthx.Ze : Ljava/lang/String;
    //   1795: getstatic burp/Zegw.ZW : Ljava/lang/Object;
    //   1798: checkcast java/math/BigInteger
    //   1801: invokevirtual intValue : ()I
    //   1804: bipush #32
    //   1806: irem
    //   1807: invokestatic abs : (I)I
    //   1810: invokevirtual charAt : (I)C
    //   1813: invokevirtual append : (C)Ljava/lang/StringBuilder;
    //   1816: pop
    //   1817: iload_2
    //   1818: ifeq -> 2736
    //   1821: goto -> 1828
    //   1824: invokestatic a : (Ljava/lang/Throwable;)Ljava/lang/Throwable;
    //   1827: athrow
    //   1828: aload #4
    //   1830: getstatic burp/Zlxw.ZC : Ljava/lang/String;
    //   1833: getstatic burp/Zge9.ZT : Ljava/lang/Object;
    //   1836: checkcast java/math/BigInteger
    //   1839: invokevirtual intValue : ()I
    //   1842: bipush #32
    //   1844: irem
    //   1845: invokestatic abs : (I)I
    //   1848: invokevirtual charAt : (I)C
    //   1851: invokevirtual append : (C)Ljava/lang/StringBuilder;
    //   1854: pop
    //   1855: iload_2
    //   1856: ifeq -> 2736
    //   1859: goto -> 1866
    //   1862: invokestatic a : (Ljava/lang/Throwable;)Ljava/lang/Throwable;
    //   1865: athrow
    //   1866: aload #4
    //   1868: getstatic burp/Zr1h.ZS : Ljava/lang/String;
    //   1871: getstatic burp/Ztdl.Zw : Ljava/lang/Object;
    //   1874: checkcast java/math/BigInteger
    //   1877: invokevirtual intValue : ()I
    //   1880: bipush #32
    //   1882: irem
    //   1883: invokestatic abs : (I)I
    //   1886: invokevirtual charAt : (I)C
    //   1889: invokevirtual append : (C)Ljava/lang/StringBuilder;
    //   1892: pop
    //   1893: iload_2
    //   1894: ifeq -> 2736
    //   1897: goto -> 1904
    //   1900: invokestatic a : (Ljava/lang/Throwable;)Ljava/lang/Throwable;
    //   1903: athrow
    //   1904: aload #4
    //   1906: getstatic burp/Zrm6.ZV : Ljava/lang/String;
    //   1909: getstatic burp/Zesw.ZB : Ljava/lang/Object;
    //   1912: checkcast java/math/BigInteger
    //   1915: invokevirtual intValue : ()I
    //   1918: bipush #32
    //   1920: irem
    //   1921: invokestatic abs : (I)I
    //   1924: invokevirtual charAt : (I)C
    //   1927: invokevirtual append : (C)Ljava/lang/StringBuilder;
    //   1930: pop
    //   1931: iload_2
    //   1932: ifeq -> 2736
    //   1935: goto -> 1942
    //   1938: invokestatic a : (Ljava/lang/Throwable;)Ljava/lang/Throwable;
    //   1941: athrow
    //   1942: aload #4
    //   1944: getstatic burp/Zegv.ZA : Ljava/lang/String;
    //   1947: getstatic burp/Zgis.ZV : Ljava/lang/Object;
    //   1950: checkcast java/math/BigInteger
    //   1953: invokevirtual intValue : ()I
    //   1956: bipush #32
    //   1958: irem
    //   1959: invokestatic abs : (I)I
    //   1962: invokevirtual charAt : (I)C
    //   1965: invokevirtual append : (C)Ljava/lang/StringBuilder;
    //   1968: pop
    //   1969: iload_2
    //   1970: ifeq -> 2736
    //   1973: goto -> 1980
    //   1976: invokestatic a : (Ljava/lang/Throwable;)Ljava/lang/Throwable;
    //   1979: athrow
    //   1980: aload #4
    //   1982: getstatic burp/Zscf.Zu : Ljava/lang/String;
    //   1985: getstatic burp/Zl_a.ZP : Ljava/lang/Object;
    //   1988: checkcast java/math/BigInteger
    //   1991: invokevirtual intValue : ()I
    //   1994: bipush #32
    //   1996: irem
    //   1997: invokestatic abs : (I)I
    //   2000: invokevirtual charAt : (I)C
    //   2003: invokevirtual append : (C)Ljava/lang/StringBuilder;
    //   2006: pop
    //   2007: iload_2
    //   2008: ifeq -> 2736
    //   2011: goto -> 2018
    //   2014: invokestatic a : (Ljava/lang/Throwable;)Ljava/lang/Throwable;
    //   2017: athrow
    //   2018: aload #4
    //   2020: getstatic burp/Zmt_.ZH : Ljava/lang/String;
    //   2023: getstatic burp/Zb3d.Zw : Ljava/lang/Object;
    //   2026: checkcast java/math/BigInteger
    //   2029: invokevirtual intValue : ()I
    //   2032: bipush #32
    //   2034: irem
    //   2035: invokestatic abs : (I)I
    //   2038: invokevirtual charAt : (I)C
    //   2041: invokevirtual append : (C)Ljava/lang/StringBuilder;
    //   2044: pop
    //   2045: iload_2
    //   2046: ifeq -> 2736
    //   2049: goto -> 2056
    //   2052: invokestatic a : (Ljava/lang/Throwable;)Ljava/lang/Throwable;
    //   2055: athrow
    //   2056: aload #4
    //   2058: getstatic burp/Zedq.Zj : Ljava/lang/String;
    //   2061: getstatic burp/Zx63.ZX : Ljava/lang/Object;
    //   2064: checkcast java/math/BigInteger
    //   2067: invokevirtual intValue : ()I
    //   2070: bipush #32
    //   2072: irem
    //   2073: invokestatic abs : (I)I
    //   2076: invokevirtual charAt : (I)C
    //   2079: invokevirtual append : (C)Ljava/lang/StringBuilder;
    //   2082: pop
    //   2083: iload_2
    //   2084: ifeq -> 2736
    //   2087: goto -> 2094
    //   2090: invokestatic a : (Ljava/lang/Throwable;)Ljava/lang/Throwable;
    //   2093: athrow
    //   2094: aload #4
    //   2096: getstatic burp/Zrb6.ZP : Ljava/lang/String;
    //   2099: getstatic burp/Ztlo.ZP : Ljava/lang/Object;
    //   2102: checkcast java/math/BigInteger
    //   2105: invokevirtual intValue : ()I
    //   2108: bipush #32
    //   2110: irem
    //   2111: invokestatic abs : (I)I
    //   2114: invokevirtual charAt : (I)C
    //   2117: invokevirtual append : (C)Ljava/lang/StringBuilder;
    //   2120: pop
    //   2121: iload_2
    //   2122: ifeq -> 2736
    //   2125: goto -> 2132
    //   2128: invokestatic a : (Ljava/lang/Throwable;)Ljava/lang/Throwable;
    //   2131: athrow
    //   2132: aload #4
    //   2134: getstatic burp/Zl_f.ZF : Ljava/lang/String;
    //   2137: getstatic burp/Zmig.Zh : Ljava/lang/Object;
    //   2140: checkcast java/math/BigInteger
    //   2143: invokevirtual intValue : ()I
    //   2146: bipush #32
    //   2148: irem
    //   2149: invokestatic abs : (I)I
    //   2152: invokevirtual charAt : (I)C
    //   2155: invokevirtual append : (C)Ljava/lang/StringBuilder;
    //   2158: pop
    //   2159: iload_2
    //   2160: ifeq -> 2736
    //   2163: goto -> 2170
    //   2166: invokestatic a : (Ljava/lang/Throwable;)Ljava/lang/Throwable;
    //   2169: athrow
    //   2170: aload #4
    //   2172: getstatic burp/Zk5k.Zx : Ljava/lang/String;
    //   2175: getstatic burp/Ze84.Zj : Ljava/lang/Object;
    //   2178: checkcast java/math/BigInteger
    //   2181: invokevirtual intValue : ()I
    //   2184: bipush #32
    //   2186: irem
    //   2187: invokestatic abs : (I)I
    //   2190: invokevirtual charAt : (I)C
    //   2193: invokevirtual append : (C)Ljava/lang/StringBuilder;
    //   2196: pop
    //   2197: iload_2
    //   2198: ifeq -> 2736
    //   2201: goto -> 2208
    //   2204: invokestatic a : (Ljava/lang/Throwable;)Ljava/lang/Throwable;
    //   2207: athrow
    //   2208: aload #4
    //   2210: getstatic burp/Zxdy.Zm : Ljava/lang/String;
    //   2213: getstatic burp/Zt9f.Zl : Ljava/lang/Object;
    //   2216: checkcast java/math/BigInteger
    //   2219: invokevirtual intValue : ()I
    //   2222: bipush #32
    //   2224: irem
    //   2225: invokestatic abs : (I)I
    //   2228: invokevirtual charAt : (I)C
    //   2231: invokevirtual append : (C)Ljava/lang/StringBuilder;
    //   2234: pop
    //   2235: iload_2
    //   2236: ifeq -> 2736
    //   2239: goto -> 2246
    //   2242: invokestatic a : (Ljava/lang/Throwable;)Ljava/lang/Throwable;
    //   2245: athrow
    //   2246: aload #4
    //   2248: getstatic burp/Zm1d.ZE : Ljava/lang/String;
    //   2251: getstatic burp/Zlcc.ZP : Ljava/lang/Object;
    //   2254: checkcast java/math/BigInteger
    //   2257: invokevirtual intValue : ()I
    //   2260: bipush #32
    //   2262: irem
    //   2263: invokestatic abs : (I)I
    //   2266: invokevirtual charAt : (I)C
    //   2269: invokevirtual append : (C)Ljava/lang/StringBuilder;
    //   2272: pop
    //   2273: iload_2
    //   2274: ifeq -> 2736
    //   2277: goto -> 2284
    //   2280: invokestatic a : (Ljava/lang/Throwable;)Ljava/lang/Throwable;
    //   2283: athrow
    //   2284: aload #4
    //   2286: getstatic burp/Zedu.ZD : Ljava/lang/String;
    //   2289: getstatic burp/Zmz.ZW : Ljava/lang/Object;
    //   2292: checkcast java/math/BigInteger
    //   2295: invokevirtual intValue : ()I
    //   2298: bipush #32
    //   2300: irem
    //   2301: invokestatic abs : (I)I
    //   2304: invokevirtual charAt : (I)C
    //   2307: invokevirtual append : (C)Ljava/lang/StringBuilder;
    //   2310: pop
    //   2311: iload_2
    //   2312: ifeq -> 2736
    //   2315: goto -> 2322
    //   2318: invokestatic a : (Ljava/lang/Throwable;)Ljava/lang/Throwable;
    //   2321: athrow
    //   2322: aload #4
    //   2324: getstatic burp/Zrkw.ZU : Ljava/lang/String;
    //   2327: getstatic burp/Zrp2.Zw : Ljava/lang/Object;
    //   2330: checkcast java/math/BigInteger
    //   2333: invokevirtual intValue : ()I
    //   2336: bipush #32
    //   2338: irem
    //   2339: invokestatic abs : (I)I
    //   2342: invokevirtual charAt : (I)C
    //   2345: invokevirtual append : (C)Ljava/lang/StringBuilder;
    //   2348: pop
    //   2349: iload_2
    //   2350: ifeq -> 2736
    //   2353: goto -> 2360
    //   2356: invokestatic a : (Ljava/lang/Throwable;)Ljava/lang/Throwable;
    //   2359: athrow
    //   2360: aload #4
    //   2362: getstatic burp/Zrex.Za : Ljava/lang/String;
    //   2365: getstatic burp/Zbsz.ZP : Ljava/lang/Object;
    //   2368: checkcast java/math/BigInteger
    //   2371: invokevirtual intValue : ()I
    //   2374: bipush #32
    //   2376: irem
    //   2377: invokestatic abs : (I)I
    //   2380: invokevirtual charAt : (I)C
    //   2383: invokevirtual append : (C)Ljava/lang/StringBuilder;
    //   2386: pop
    //   2387: iload_2
    //   2388: ifeq -> 2736
    //   2391: goto -> 2398
    //   2394: invokestatic a : (Ljava/lang/Throwable;)Ljava/lang/Throwable;
    //   2397: athrow
    //   2398: aload #4
    //   2400: getstatic burp/Zthx.Ze : Ljava/lang/String;
    //   2403: getstatic burp/Zg1l.Zg : Ljava/lang/Object;
    //   2406: checkcast java/math/BigInteger
    //   2409: invokevirtual intValue : ()I
    //   2412: bipush #32
    //   2414: irem
    //   2415: invokestatic abs : (I)I
    //   2418: invokevirtual charAt : (I)C
    //   2421: invokevirtual append : (C)Ljava/lang/StringBuilder;
    //   2424: pop
    //   2425: iload_2
    //   2426: ifeq -> 2736
    //   2429: goto -> 2436
    //   2432: invokestatic a : (Ljava/lang/Throwable;)Ljava/lang/Throwable;
    //   2435: athrow
    //   2436: aload #4
    //   2438: getstatic burp/Zm63.Zs : Ljava/lang/String;
    //   2441: getstatic burp/Zg2u.ZI : Ljava/lang/Object;
    //   2444: checkcast java/math/BigInteger
    //   2447: invokevirtual intValue : ()I
    //   2450: bipush #32
    //   2452: irem
    //   2453: invokestatic abs : (I)I
    //   2456: invokevirtual charAt : (I)C
    //   2459: invokevirtual append : (C)Ljava/lang/StringBuilder;
    //   2462: pop
    //   2463: iload_2
    //   2464: ifeq -> 2736
    //   2467: goto -> 2474
    //   2470: invokestatic a : (Ljava/lang/Throwable;)Ljava/lang/Throwable;
    //   2473: athrow
    //   2474: aload #4
    //   2476: getstatic burp/Zly9.ZS : Ljava/lang/String;
    //   2479: getstatic burp/Zr60.Ze : Ljava/lang/Object;
    //   2482: checkcast java/math/BigInteger
    //   2485: invokevirtual intValue : ()I
    //   2488: bipush #32
    //   2490: irem
    //   2491: invokestatic abs : (I)I
    //   2494: invokevirtual charAt : (I)C
    //   2497: invokevirtual append : (C)Ljava/lang/StringBuilder;
    //   2500: pop
    //   2501: iload_2
    //   2502: ifeq -> 2736
    //   2505: goto -> 2512
    //   2508: invokestatic a : (Ljava/lang/Throwable;)Ljava/lang/Throwable;
    //   2511: athrow
    //   2512: aload #4
    //   2514: getstatic burp/Zmui.ZY : Ljava/lang/String;
    //   2517: getstatic burp/Zvob.ZX : Ljava/lang/Object;
    //   2520: checkcast java/math/BigInteger
    //   2523: invokevirtual intValue : ()I
    //   2526: bipush #32
    //   2528: irem
    //   2529: invokestatic abs : (I)I
    //   2532: invokevirtual charAt : (I)C
    //   2535: invokevirtual append : (C)Ljava/lang/StringBuilder;
    //   2538: pop
    //   2539: iload_2
    //   2540: ifeq -> 2736
    //   2543: goto -> 2550
    //   2546: invokestatic a : (Ljava/lang/Throwable;)Ljava/lang/Throwable;
    //   2549: athrow
    //   2550: aload #4
    //   2552: getstatic burp/Zmhq.Zy : Ljava/lang/String;
    //   2555: getstatic burp/Zgsb.Zl : Ljava/lang/Object;
    //   2558: checkcast java/math/BigInteger
    //   2561: invokevirtual intValue : ()I
    //   2564: bipush #32
    //   2566: irem
    //   2567: invokestatic abs : (I)I
    //   2570: invokevirtual charAt : (I)C
    //   2573: invokevirtual append : (C)Ljava/lang/StringBuilder;
    //   2576: pop
    //   2577: iload_2
    //   2578: ifeq -> 2736
    //   2581: goto -> 2588
    //   2584: invokestatic a : (Ljava/lang/Throwable;)Ljava/lang/Throwable;
    //   2587: athrow
    //   2588: aload #4
    //   2590: getstatic burp/Zku9.Zl : Ljava/lang/String;
    //   2593: getstatic burp/Zreu.Zi : Ljava/lang/Object;
    //   2596: checkcast java/math/BigInteger
    //   2599: invokevirtual intValue : ()I
    //   2602: bipush #32
    //   2604: irem
    //   2605: invokestatic abs : (I)I
    //   2608: invokevirtual charAt : (I)C
    //   2611: invokevirtual append : (C)Ljava/lang/StringBuilder;
    //   2614: pop
    //   2615: iload_2
    //   2616: ifeq -> 2736
    //   2619: goto -> 2626
    //   2622: invokestatic a : (Ljava/lang/Throwable;)Ljava/lang/Throwable;
    //   2625: athrow
    //   2626: aload #4
    //   2628: getstatic burp/Zd9.Ze : Ljava/lang/String;
    //   2631: getstatic burp/Zg4z.ZB : Ljava/lang/Object;
    //   2634: checkcast java/math/BigInteger
    //   2637: invokevirtual intValue : ()I
    //   2640: bipush #32
    //   2642: irem
    //   2643: invokestatic abs : (I)I
    //   2646: invokevirtual charAt : (I)C
    //   2649: invokevirtual append : (C)Ljava/lang/StringBuilder;
    //   2652: pop
    //   2653: iload_2
    //   2654: ifeq -> 2736
    //   2657: goto -> 2664
    //   2660: invokestatic a : (Ljava/lang/Throwable;)Ljava/lang/Throwable;
    //   2663: athrow
    //   2664: aload #4
    //   2666: getstatic burp/Zt81.ZL : Ljava/lang/String;
    //   2669: getstatic burp/Zxju.ZN : Ljava/lang/Object;
    //   2672: checkcast java/math/BigInteger
    //   2675: invokevirtual intValue : ()I
    //   2678: bipush #32
    //   2680: irem
    //   2681: invokestatic abs : (I)I
    //   2684: invokevirtual charAt : (I)C
    //   2687: invokevirtual append : (C)Ljava/lang/StringBuilder;
    //   2690: pop
    //   2691: iload_2
    //   2692: ifeq -> 2736
    //   2695: goto -> 2702
    //   2698: invokestatic a : (Ljava/lang/Throwable;)Ljava/lang/Throwable;
    //   2701: athrow
    //   2702: aload #4
    //   2704: getstatic burp/Zgcg.Zk : Ljava/lang/String;
    //   2707: getstatic burp/Zmyk.Za : Ljava/lang/Object;
    //   2710: checkcast java/math/BigInteger
    //   2713: invokevirtual intValue : ()I
    //   2716: bipush #32
    //   2718: irem
    //   2719: invokestatic abs : (I)I
    //   2722: invokevirtual charAt : (I)C
    //   2725: invokevirtual append : (C)Ljava/lang/StringBuilder;
    //   2728: pop
    //   2729: goto -> 2736
    //   2732: invokestatic a : (Ljava/lang/Throwable;)Ljava/lang/Throwable;
    //   2735: athrow
    //   2736: iinc #5, 1
    //   2739: iload_2
    //   2740: ifeq -> 1374
    //   2743: aload #4
    //   2745: invokevirtual toString : ()Ljava/lang/String;
    //   2748: putstatic burp/Zr60.ZQ : Ljava/lang/String;
    //   2751: sipush #-15135
    //   2754: sipush #11545
    //   2757: invokestatic a : (II)Ljava/lang/String;
    //   2760: iconst_1
    //   2761: ldc burp/Zel
    //   2763: invokevirtual getClassLoader : ()Ljava/lang/ClassLoader;
    //   2766: invokestatic forName : (Ljava/lang/String;ZLjava/lang/ClassLoader;)Ljava/lang/Class;
    //   2769: invokevirtual getDeclaredFields : ()[Ljava/lang/reflect/Field;
    //   2772: astore #5
    //   2774: aload #5
    //   2776: arraylength
    //   2777: istore #6
    //   2779: iconst_0
    //   2780: istore #7
    //   2782: iload #7
    //   2784: iload #6
    //   2786: if_icmpge -> 2924
    //   2789: aload #5
    //   2791: iload #7
    //   2793: aaload
    //   2794: astore #8
    //   2796: aload #8
    //   2798: invokevirtual getModifiers : ()I
    //   2801: invokestatic isStatic : (I)Z
    //   2804: ifne -> 2814
    //   2807: goto -> 2917
    //   2810: invokestatic a : (Ljava/lang/Throwable;)Ljava/lang/Throwable;
    //   2813: athrow
    //   2814: aload #8
    //   2816: invokevirtual getType : ()Ljava/lang/Class;
    //   2819: astore #9
    //   2821: aload #9
    //   2823: ifnull -> 2904
    //   2826: aload #9
    //   2828: invokevirtual isPrimitive : ()Z
    //   2831: ifne -> 2904
    //   2834: goto -> 2841
    //   2837: invokestatic a : (Ljava/lang/Throwable;)Ljava/lang/Throwable;
    //   2840: athrow
    //   2841: aload #9
    //   2843: invokevirtual getPackage : ()Ljava/lang/Package;
    //   2846: ifnull -> 2904
    //   2849: goto -> 2856
    //   2852: invokestatic a : (Ljava/lang/Throwable;)Ljava/lang/Throwable;
    //   2855: athrow
    //   2856: aload #9
    //   2858: invokevirtual getPackage : ()Ljava/lang/Package;
    //   2861: invokevirtual getName : ()Ljava/lang/String;
    //   2864: ifnull -> 2904
    //   2867: goto -> 2874
    //   2870: invokestatic a : (Ljava/lang/Throwable;)Ljava/lang/Throwable;
    //   2873: athrow
    //   2874: aload #9
    //   2876: invokevirtual getPackage : ()Ljava/lang/Package;
    //   2879: invokevirtual getName : ()Ljava/lang/String;
    //   2882: sipush #-15126
    //   2885: sipush #-18084
    //   2888: invokestatic a : (II)Ljava/lang/String;
    //   2891: invokevirtual startsWith : (Ljava/lang/String;)Z
    //   2894: ifne -> 2904
    //   2897: goto -> 2904
    //   2900: invokestatic a : (Ljava/lang/Throwable;)Ljava/lang/Throwable;
    //   2903: athrow
    //   2904: aload #8
    //   2906: iconst_1
    //   2907: invokevirtual setAccessible : (Z)V
    //   2910: aload #8
    //   2912: aconst_null
    //   2913: invokevirtual get : (Ljava/lang/Object;)Ljava/lang/Object;
    //   2916: pop
    //   2917: iinc #7, 1
    //   2920: iload_2
    //   2921: ifeq -> 2782
    //   2924: sipush #-15108
    //   2927: sipush #30895
    //   2930: invokestatic a : (II)Ljava/lang/String;
    //   2933: invokestatic forName : (Ljava/lang/String;)Ljava/lang/Class;
    //   2936: invokevirtual getDeclaredMethods : ()[Ljava/lang/reflect/Method;
    //   2939: astore #5
    //   2941: aload #5
    //   2943: arraylength
    //   2944: istore #6
    //   2946: iconst_0
    //   2947: istore #7
    //   2949: iload #7
    //   2951: iload #6
    //   2953: if_icmpge -> 3086
    //   2956: aload #5
    //   2958: iload #7
    //   2960: aaload
    //   2961: astore #8
    //   2963: aload #8
    //   2965: invokevirtual getParameterTypes : ()[Ljava/lang/Class;
    //   2968: pop
    //   2969: aload #8
    //   2971: invokevirtual getModifiers : ()I
    //   2974: invokestatic isStatic : (I)Z
    //   2977: ifeq -> 3072
    //   2980: aload #8
    //   2982: invokevirtual getParameterTypes : ()[Ljava/lang/Class;
    //   2985: arraylength
    //   2986: iconst_2
    //   2987: if_icmpne -> 3072
    //   2990: goto -> 2997
    //   2993: invokestatic a : (Ljava/lang/Throwable;)Ljava/lang/Throwable;
    //   2996: athrow
    //   2997: aload #8
    //   2999: invokevirtual getReturnType : ()Ljava/lang/Class;
    //   3002: getstatic java/lang/Void.TYPE : Ljava/lang/Class;
    //   3005: invokevirtual equals : (Ljava/lang/Object;)Z
    //   3008: ifeq -> 3072
    //   3011: goto -> 3018
    //   3014: invokestatic a : (Ljava/lang/Throwable;)Ljava/lang/Throwable;
    //   3017: athrow
    //   3018: aload #8
    //   3020: iconst_1
    //   3021: invokevirtual setAccessible : (Z)V
    //   3024: aload #8
    //   3026: aconst_null
    //   3027: iconst_2
    //   3028: anewarray java/lang/Object
    //   3031: dup
    //   3032: iconst_0
    //   3033: aload_0
    //   3034: aastore
    //   3035: dup
    //   3036: iconst_1
    //   3037: aload_1
    //   3038: ifnonnull -> 3056
    //   3041: goto -> 3048
    //   3044: invokestatic a : (Ljava/lang/Throwable;)Ljava/lang/Throwable;
    //   3047: athrow
    //   3048: aload_1
    //   3049: goto -> 3063
    //   3052: invokestatic a : (Ljava/lang/Throwable;)Ljava/lang/Throwable;
    //   3055: athrow
    //   3056: aload_1
    //   3057: checkcast [B
    //   3060: invokevirtual clone : ()Ljava/lang/Object;
    //   3063: aastore
    //   3064: invokevirtual invoke : (Ljava/lang/Object;[Ljava/lang/Object;)Ljava/lang/Object;
    //   3067: pop
    //   3068: iload_2
    //   3069: ifeq -> 3086
    //   3072: iinc #7, 1
    //   3075: iload_2
    //   3076: ifeq -> 2949
    //   3079: goto -> 3086
    //   3082: invokestatic a : (Ljava/lang/Throwable;)Ljava/lang/Throwable;
    //   3085: athrow
    //   3086: sipush #-15119
    //   3089: iconst_m1
    //   3090: invokestatic a : (II)Ljava/lang/String;
    //   3093: iconst_1
    //   3094: ldc burp/Zgj5
    //   3096: invokevirtual getClassLoader : ()Ljava/lang/ClassLoader;
    //   3099: invokestatic forName : (Ljava/lang/String;ZLjava/lang/ClassLoader;)Ljava/lang/Class;
    //   3102: invokevirtual getDeclaredFields : ()[Ljava/lang/reflect/Field;
    //   3105: astore #5
    //   3107: aload #5
    //   3109: arraylength
    //   3110: istore #6
    //   3112: iconst_0
    //   3113: istore #7
    //   3115: iload #7
    //   3117: iload #6
    //   3119: if_icmpge -> 3257
    //   3122: aload #5
    //   3124: iload #7
    //   3126: aaload
    //   3127: astore #8
    //   3129: aload #8
    //   3131: invokevirtual getModifiers : ()I
    //   3134: invokestatic isStatic : (I)Z
    //   3137: ifne -> 3147
    //   3140: goto -> 3250
    //   3143: invokestatic a : (Ljava/lang/Throwable;)Ljava/lang/Throwable;
    //   3146: athrow
    //   3147: aload #8
    //   3149: invokevirtual getType : ()Ljava/lang/Class;
    //   3152: astore #9
    //   3154: aload #9
    //   3156: ifnull -> 3237
    //   3159: aload #9
    //   3161: invokevirtual isPrimitive : ()Z
    //   3164: ifne -> 3237
    //   3167: goto -> 3174
    //   3170: invokestatic a : (Ljava/lang/Throwable;)Ljava/lang/Throwable;
    //   3173: athrow
    //   3174: aload #9
    //   3176: invokevirtual getPackage : ()Ljava/lang/Package;
    //   3179: ifnull -> 3237
    //   3182: goto -> 3189
    //   3185: invokestatic a : (Ljava/lang/Throwable;)Ljava/lang/Throwable;
    //   3188: athrow
    //   3189: aload #9
    //   3191: invokevirtual getPackage : ()Ljava/lang/Package;
    //   3194: invokevirtual getName : ()Ljava/lang/String;
    //   3197: ifnull -> 3237
    //   3200: goto -> 3207
    //   3203: invokestatic a : (Ljava/lang/Throwable;)Ljava/lang/Throwable;
    //   3206: athrow
    //   3207: aload #9
    //   3209: invokevirtual getPackage : ()Ljava/lang/Package;
    //   3212: invokevirtual getName : ()Ljava/lang/String;
    //   3215: sipush #-15129
    //   3218: sipush #28931
    //   3221: invokestatic a : (II)Ljava/lang/String;
    //   3224: invokevirtual startsWith : (Ljava/lang/String;)Z
    //   3227: ifne -> 3237
    //   3230: goto -> 3237
    //   3233: invokestatic a : (Ljava/lang/Throwable;)Ljava/lang/Throwable;
    //   3236: athrow
    //   3237: aload #8
    //   3239: iconst_1
    //   3240: invokevirtual setAccessible : (Z)V
    //   3243: aload #8
    //   3245: aconst_null
    //   3246: invokevirtual get : (Ljava/lang/Object;)Ljava/lang/Object;
    //   3249: pop
    //   3250: iinc #7, 1
    //   3253: iload_2
    //   3254: ifeq -> 3115
    //   3257: sipush #-15133
    //   3260: sipush #-1349
    //   3263: invokestatic a : (II)Ljava/lang/String;
    //   3266: invokestatic forName : (Ljava/lang/String;)Ljava/lang/Class;
    //   3269: invokevirtual getDeclaredMethods : ()[Ljava/lang/reflect/Method;
    //   3272: astore #5
    //   3274: aload #5
    //   3276: arraylength
    //   3277: istore #6
    //   3279: iconst_0
    //   3280: istore #7
    //   3282: iload #7
    //   3284: iload #6
    //   3286: if_icmpge -> 3398
    //   3289: aload #5
    //   3291: iload #7
    //   3293: aaload
    //   3294: astore #8
    //   3296: aload #8
    //   3298: invokevirtual getParameterTypes : ()[Ljava/lang/Class;
    //   3301: pop
    //   3302: aload #8
    //   3304: invokevirtual getModifiers : ()I
    //   3307: invokestatic isStatic : (I)Z
    //   3310: ifeq -> 3384
    //   3313: aload #8
    //   3315: invokevirtual getParameterTypes : ()[Ljava/lang/Class;
    //   3318: arraylength
    //   3319: iconst_2
    //   3320: if_icmpne -> 3384
    //   3323: goto -> 3330
    //   3326: invokestatic a : (Ljava/lang/Throwable;)Ljava/lang/Throwable;
    //   3329: athrow
    //   3330: aload #8
    //   3332: invokevirtual getReturnType : ()Ljava/lang/Class;
    //   3335: getstatic java/lang/Boolean.TYPE : Ljava/lang/Class;
    //   3338: if_acmpne -> 3384
    //   3341: goto -> 3348
    //   3344: invokestatic a : (Ljava/lang/Throwable;)Ljava/lang/Throwable;
    //   3347: athrow
    //   3348: aload #8
    //   3350: iconst_1
    //   3351: invokevirtual setAccessible : (Z)V
    //   3354: aload #8
    //   3356: aconst_null
    //   3357: iconst_2
    //   3358: anewarray java/lang/Object
    //   3361: dup
    //   3362: iconst_0
    //   3363: aload_0
    //   3364: aastore
    //   3365: dup
    //   3366: iconst_1
    //   3367: aload_1
    //   3368: aastore
    //   3369: invokevirtual invoke : (Ljava/lang/Object;[Ljava/lang/Object;)Ljava/lang/Object;
    //   3372: pop
    //   3373: iload_2
    //   3374: ifeq -> 3398
    //   3377: goto -> 3384
    //   3380: invokestatic a : (Ljava/lang/Throwable;)Ljava/lang/Throwable;
    //   3383: athrow
    //   3384: iinc #7, 1
    //   3387: iload_2
    //   3388: ifeq -> 3282
    //   3391: goto -> 3398
    //   3394: invokestatic a : (Ljava/lang/Throwable;)Ljava/lang/Throwable;
    //   3397: athrow
    //   3398: iconst_0
    //   3399: istore #5
    //   3401: getstatic burp/Zr36.Ze : Ljava/lang/String;
    //   3404: getstatic burp/Zes.Zx : Ljava/lang/Object;
    //   3407: checkcast java/math/BigInteger
    //   3410: invokevirtual intValue : ()I
    //   3413: bipush #32
    //   3415: irem
    //   3416: invokestatic abs : (I)I
    //   3419: invokevirtual charAt : (I)C
    //   3422: getstatic burp/Zlwj.ZQ : Ljava/lang/String;
    //   3425: getstatic burp/Ze4a.ZP : Ljava/lang/Object;
    //   3428: checkcast java/math/BigInteger
    //   3431: invokevirtual intValue : ()I
    //   3434: bipush #32
    //   3436: irem
    //   3437: invokestatic abs : (I)I
    //   3440: invokevirtual charAt : (I)C
    //   3443: if_icmpgt -> 3788
    //   3446: sipush #-15110
    //   3449: sipush #18192
    //   3452: invokestatic a : (II)Ljava/lang/String;
    //   3455: iconst_1
    //   3456: ldc burp/Zr8r
    //   3458: invokevirtual getClassLoader : ()Ljava/lang/ClassLoader;
    //   3461: invokestatic forName : (Ljava/lang/String;ZLjava/lang/ClassLoader;)Ljava/lang/Class;
    //   3464: invokevirtual getDeclaredFields : ()[Ljava/lang/reflect/Field;
    //   3467: astore #6
    //   3469: aload #6
    //   3471: arraylength
    //   3472: istore #7
    //   3474: iconst_0
    //   3475: istore #8
    //   3477: iload #8
    //   3479: iload #7
    //   3481: if_icmpge -> 3619
    //   3484: aload #6
    //   3486: iload #8
    //   3488: aaload
    //   3489: astore #9
    //   3491: aload #9
    //   3493: invokevirtual getModifiers : ()I
    //   3496: invokestatic isStatic : (I)Z
    //   3499: ifne -> 3509
    //   3502: goto -> 3612
    //   3505: invokestatic a : (Ljava/lang/Throwable;)Ljava/lang/Throwable;
    //   3508: athrow
    //   3509: aload #9
    //   3511: invokevirtual getType : ()Ljava/lang/Class;
    //   3514: astore #10
    //   3516: aload #10
    //   3518: ifnull -> 3599
    //   3521: aload #10
    //   3523: invokevirtual isPrimitive : ()Z
    //   3526: ifne -> 3599
    //   3529: goto -> 3536
    //   3532: invokestatic a : (Ljava/lang/Throwable;)Ljava/lang/Throwable;
    //   3535: athrow
    //   3536: aload #10
    //   3538: invokevirtual getPackage : ()Ljava/lang/Package;
    //   3541: ifnull -> 3599
    //   3544: goto -> 3551
    //   3547: invokestatic a : (Ljava/lang/Throwable;)Ljava/lang/Throwable;
    //   3550: athrow
    //   3551: aload #10
    //   3553: invokevirtual getPackage : ()Ljava/lang/Package;
    //   3556: invokevirtual getName : ()Ljava/lang/String;
    //   3559: ifnull -> 3599
    //   3562: goto -> 3569
    //   3565: invokestatic a : (Ljava/lang/Throwable;)Ljava/lang/Throwable;
    //   3568: athrow
    //   3569: aload #10
    //   3571: invokevirtual getPackage : ()Ljava/lang/Package;
    //   3574: invokevirtual getName : ()Ljava/lang/String;
    //   3577: sipush #-15129
    //   3580: sipush #28931
    //   3583: invokestatic a : (II)Ljava/lang/String;
    //   3586: invokevirtual startsWith : (Ljava/lang/String;)Z
    //   3589: ifne -> 3599
    //   3592: goto -> 3599
    //   3595: invokestatic a : (Ljava/lang/Throwable;)Ljava/lang/Throwable;
    //   3598: athrow
    //   3599: aload #9
    //   3601: iconst_1
    //   3602: invokevirtual setAccessible : (Z)V
    //   3605: aload #9
    //   3607: aconst_null
    //   3608: invokevirtual get : (Ljava/lang/Object;)Ljava/lang/Object;
    //   3611: pop
    //   3612: iinc #8, 1
    //   3615: iload_2
    //   3616: ifeq -> 3477
    //   3619: sipush #-15107
    //   3622: sipush #-8482
    //   3625: invokestatic a : (II)Ljava/lang/String;
    //   3628: invokestatic forName : (Ljava/lang/String;)Ljava/lang/Class;
    //   3631: invokevirtual getDeclaredMethods : ()[Ljava/lang/reflect/Method;
    //   3634: astore #6
    //   3636: aload #6
    //   3638: arraylength
    //   3639: istore #7
    //   3641: iconst_0
    //   3642: istore #8
    //   3644: iload #8
    //   3646: iload #7
    //   3648: if_icmpge -> 3785
    //   3651: aload #6
    //   3653: iload #8
    //   3655: aaload
    //   3656: astore #9
    //   3658: aload #9
    //   3660: invokevirtual getParameterTypes : ()[Ljava/lang/Class;
    //   3663: pop
    //   3664: aload #9
    //   3666: invokevirtual getModifiers : ()I
    //   3669: invokestatic isStatic : (I)Z
    //   3672: ifeq -> 3771
    //   3675: aload #9
    //   3677: invokevirtual getParameterTypes : ()[Ljava/lang/Class;
    //   3680: arraylength
    //   3681: iconst_2
    //   3682: if_icmpne -> 3771
    //   3685: goto -> 3692
    //   3688: invokestatic a : (Ljava/lang/Throwable;)Ljava/lang/Throwable;
    //   3691: athrow
    //   3692: aload #9
    //   3694: invokevirtual getReturnType : ()Ljava/lang/Class;
    //   3697: getstatic java/lang/Boolean.TYPE : Ljava/lang/Class;
    //   3700: if_acmpne -> 3771
    //   3703: goto -> 3710
    //   3706: invokestatic a : (Ljava/lang/Throwable;)Ljava/lang/Throwable;
    //   3709: athrow
    //   3710: aload #9
    //   3712: iconst_1
    //   3713: invokevirtual setAccessible : (Z)V
    //   3716: aload #9
    //   3718: aconst_null
    //   3719: iconst_2
    //   3720: anewarray java/lang/Object
    //   3723: dup
    //   3724: iconst_0
    //   3725: aload_0
    //   3726: aastore
    //   3727: dup
    //   3728: iconst_1
    //   3729: aload_1
    //   3730: ifnonnull -> 3748
    //   3733: goto -> 3740
    //   3736: invokestatic a : (Ljava/lang/Throwable;)Ljava/lang/Throwable;
    //   3739: athrow
    //   3740: aload_1
    //   3741: goto -> 3755
    //   3744: invokestatic a : (Ljava/lang/Throwable;)Ljava/lang/Throwable;
    //   3747: athrow
    //   3748: aload_1
    //   3749: checkcast [B
    //   3752: invokevirtual clone : ()Ljava/lang/Object;
    //   3755: aastore
    //   3756: invokevirtual invoke : (Ljava/lang/Object;[Ljava/lang/Object;)Ljava/lang/Object;
    //   3759: checkcast java/lang/Boolean
    //   3762: invokevirtual booleanValue : ()Z
    //   3765: istore #5
    //   3767: iload_2
    //   3768: ifeq -> 3785
    //   3771: iinc #8, 1
    //   3774: iload_2
    //   3775: ifeq -> 3644
    //   3778: goto -> 3785
    //   3781: invokestatic a : (Ljava/lang/Throwable;)Ljava/lang/Throwable;
    //   3784: athrow
    //   3785: goto -> 4127
    //   3788: sipush #-15114
    //   3791: sipush #-14419
    //   3794: invokestatic a : (II)Ljava/lang/String;
    //   3797: iconst_1
    //   3798: ldc burp/Zk7w
    //   3800: invokevirtual getClassLoader : ()Ljava/lang/ClassLoader;
    //   3803: invokestatic forName : (Ljava/lang/String;ZLjava/lang/ClassLoader;)Ljava/lang/Class;
    //   3806: invokevirtual getDeclaredFields : ()[Ljava/lang/reflect/Field;
    //   3809: astore #6
    //   3811: aload #6
    //   3813: arraylength
    //   3814: istore #7
    //   3816: iconst_0
    //   3817: istore #8
    //   3819: iload #8
    //   3821: iload #7
    //   3823: if_icmpge -> 3961
    //   3826: aload #6
    //   3828: iload #8
    //   3830: aaload
    //   3831: astore #9
    //   3833: aload #9
    //   3835: invokevirtual getModifiers : ()I
    //   3838: invokestatic isStatic : (I)Z
    //   3841: ifne -> 3851
    //   3844: goto -> 3954
    //   3847: invokestatic a : (Ljava/lang/Throwable;)Ljava/lang/Throwable;
    //   3850: athrow
    //   3851: aload #9
    //   3853: invokevirtual getType : ()Ljava/lang/Class;
    //   3856: astore #10
    //   3858: aload #10
    //   3860: ifnull -> 3941
    //   3863: aload #10
    //   3865: invokevirtual isPrimitive : ()Z
    //   3868: ifne -> 3941
    //   3871: goto -> 3878
    //   3874: invokestatic a : (Ljava/lang/Throwable;)Ljava/lang/Throwable;
    //   3877: athrow
    //   3878: aload #10
    //   3880: invokevirtual getPackage : ()Ljava/lang/Package;
    //   3883: ifnull -> 3941
    //   3886: goto -> 3893
    //   3889: invokestatic a : (Ljava/lang/Throwable;)Ljava/lang/Throwable;
    //   3892: athrow
    //   3893: aload #10
    //   3895: invokevirtual getPackage : ()Ljava/lang/Package;
    //   3898: invokevirtual getName : ()Ljava/lang/String;
    //   3901: ifnull -> 3941
    //   3904: goto -> 3911
    //   3907: invokestatic a : (Ljava/lang/Throwable;)Ljava/lang/Throwable;
    //   3910: athrow
    //   3911: aload #10
    //   3913: invokevirtual getPackage : ()Ljava/lang/Package;
    //   3916: invokevirtual getName : ()Ljava/lang/String;
    //   3919: sipush #-15129
    //   3922: sipush #28931
    //   3925: invokestatic a : (II)Ljava/lang/String;
    //   3928: invokevirtual startsWith : (Ljava/lang/String;)Z
    //   3931: ifne -> 3941
    //   3934: goto -> 3941
    //   3937: invokestatic a : (Ljava/lang/Throwable;)Ljava/lang/Throwable;
    //   3940: athrow
    //   3941: aload #9
    //   3943: iconst_1
    //   3944: invokevirtual setAccessible : (Z)V
    //   3947: aload #9
    //   3949: aconst_null
    //   3950: invokevirtual get : (Ljava/lang/Object;)Ljava/lang/Object;
    //   3953: pop
    //   3954: iinc #8, 1
    //   3957: iload_2
    //   3958: ifeq -> 3819
    //   3961: sipush #-15117
    //   3964: sipush #-20719
    //   3967: invokestatic a : (II)Ljava/lang/String;
    //   3970: invokestatic forName : (Ljava/lang/String;)Ljava/lang/Class;
    //   3973: invokevirtual getDeclaredMethods : ()[Ljava/lang/reflect/Method;
    //   3976: astore #6
    //   3978: aload #6
    //   3980: arraylength
    //   3981: istore #7
    //   3983: iconst_0
    //   3984: istore #8
    //   3986: iload #8
    //   3988: iload #7
    //   3990: if_icmpge -> 4127
    //   3993: aload #6
    //   3995: iload #8
    //   3997: aaload
    //   3998: astore #9
    //   4000: aload #9
    //   4002: invokevirtual getParameterTypes : ()[Ljava/lang/Class;
    //   4005: pop
    //   4006: aload #9
    //   4008: invokevirtual getModifiers : ()I
    //   4011: invokestatic isStatic : (I)Z
    //   4014: ifeq -> 4113
    //   4017: aload #9
    //   4019: invokevirtual getParameterTypes : ()[Ljava/lang/Class;
    //   4022: arraylength
    //   4023: iconst_2
    //   4024: if_icmpne -> 4113
    //   4027: goto -> 4034
    //   4030: invokestatic a : (Ljava/lang/Throwable;)Ljava/lang/Throwable;
    //   4033: athrow
    //   4034: aload #9
    //   4036: invokevirtual getReturnType : ()Ljava/lang/Class;
    //   4039: getstatic java/lang/Boolean.TYPE : Ljava/lang/Class;
    //   4042: if_acmpne -> 4113
    //   4045: goto -> 4052
    //   4048: invokestatic a : (Ljava/lang/Throwable;)Ljava/lang/Throwable;
    //   4051: athrow
    //   4052: aload #9
    //   4054: iconst_1
    //   4055: invokevirtual setAccessible : (Z)V
    //   4058: aload #9
    //   4060: aconst_null
    //   4061: iconst_2
    //   4062: anewarray java/lang/Object
    //   4065: dup
    //   4066: iconst_0
    //   4067: aload_0
    //   4068: aastore
    //   4069: dup
    //   4070: iconst_1
    //   4071: aload_1
    //   4072: ifnonnull -> 4090
    //   4075: goto -> 4082
    //   4078: invokestatic a : (Ljava/lang/Throwable;)Ljava/lang/Throwable;
    //   4081: athrow
    //   4082: aload_1
    //   4083: goto -> 4097
    //   4086: invokestatic a : (Ljava/lang/Throwable;)Ljava/lang/Throwable;
    //   4089: athrow
    //   4090: aload_1
    //   4091: checkcast [B
    //   4094: invokevirtual clone : ()Ljava/lang/Object;
    //   4097: aastore
    //   4098: invokevirtual invoke : (Ljava/lang/Object;[Ljava/lang/Object;)Ljava/lang/Object;
    //   4101: checkcast java/lang/Boolean
    //   4104: invokevirtual booleanValue : ()Z
    //   4107: istore #5
    //   4109: iload_2
    //   4110: ifeq -> 4127
    //   4113: iinc #8, 1
    //   4116: iload_2
    //   4117: ifeq -> 3986
    //   4120: goto -> 4127
    //   4123: invokestatic a : (Ljava/lang/Throwable;)Ljava/lang/Throwable;
    //   4126: athrow
    //   4127: iload #5
    //   4129: ifeq -> 4135
    //   4132: iload #5
    //   4134: ireturn
    //   4135: getstatic burp/Zge9.Zp : Ljava/lang/String;
    //   4138: getstatic burp/Zs1k.Ze : Ljava/lang/Object;
    //   4141: checkcast java/math/BigInteger
    //   4144: invokevirtual intValue : ()I
    //   4147: bipush #32
    //   4149: irem
    //   4150: invokestatic abs : (I)I
    //   4153: invokevirtual charAt : (I)C
    //   4156: getstatic burp/Zge2.ZT : Ljava/lang/String;
    //   4159: getstatic burp/Zb87.Zb : Ljava/lang/Object;
    //   4162: checkcast java/math/BigInteger
    //   4165: invokevirtual intValue : ()I
    //   4168: bipush #32
    //   4170: irem
    //   4171: invokestatic abs : (I)I
    //   4174: invokevirtual charAt : (I)C
    //   4177: if_icmpgt -> 4523
    //   4180: sipush #-15105
    //   4183: sipush #-23180
    //   4186: invokestatic a : (II)Ljava/lang/String;
    //   4189: iconst_1
    //   4190: ldc burp/Zvi
    //   4192: invokevirtual getClassLoader : ()Ljava/lang/ClassLoader;
    //   4195: invokestatic forName : (Ljava/lang/String;ZLjava/lang/ClassLoader;)Ljava/lang/Class;
    //   4198: invokevirtual getDeclaredFields : ()[Ljava/lang/reflect/Field;
    //   4201: astore #6
    //   4203: aload #6
    //   4205: arraylength
    //   4206: istore #7
    //   4208: iconst_0
    //   4209: istore #8
    //   4211: iload #8
    //   4213: iload #7
    //   4215: if_icmpge -> 4353
    //   4218: aload #6
    //   4220: iload #8
    //   4222: aaload
    //   4223: astore #9
    //   4225: aload #9
    //   4227: invokevirtual getModifiers : ()I
    //   4230: invokestatic isStatic : (I)Z
    //   4233: ifne -> 4243
    //   4236: goto -> 4346
    //   4239: invokestatic a : (Ljava/lang/Throwable;)Ljava/lang/Throwable;
    //   4242: athrow
    //   4243: aload #9
    //   4245: invokevirtual getType : ()Ljava/lang/Class;
    //   4248: astore #10
    //   4250: aload #10
    //   4252: ifnull -> 4333
    //   4255: aload #10
    //   4257: invokevirtual isPrimitive : ()Z
    //   4260: ifne -> 4333
    //   4263: goto -> 4270
    //   4266: invokestatic a : (Ljava/lang/Throwable;)Ljava/lang/Throwable;
    //   4269: athrow
    //   4270: aload #10
    //   4272: invokevirtual getPackage : ()Ljava/lang/Package;
    //   4275: ifnull -> 4333
    //   4278: goto -> 4285
    //   4281: invokestatic a : (Ljava/lang/Throwable;)Ljava/lang/Throwable;
    //   4284: athrow
    //   4285: aload #10
    //   4287: invokevirtual getPackage : ()Ljava/lang/Package;
    //   4290: invokevirtual getName : ()Ljava/lang/String;
    //   4293: ifnull -> 4333
    //   4296: goto -> 4303
    //   4299: invokestatic a : (Ljava/lang/Throwable;)Ljava/lang/Throwable;
    //   4302: athrow
    //   4303: aload #10
    //   4305: invokevirtual getPackage : ()Ljava/lang/Package;
    //   4308: invokevirtual getName : ()Ljava/lang/String;
    //   4311: sipush #-15129
    //   4314: sipush #28931
    //   4317: invokestatic a : (II)Ljava/lang/String;
    //   4320: invokevirtual startsWith : (Ljava/lang/String;)Z
    //   4323: ifne -> 4333
    //   4326: goto -> 4333
    //   4329: invokestatic a : (Ljava/lang/Throwable;)Ljava/lang/Throwable;
    //   4332: athrow
    //   4333: aload #9
    //   4335: iconst_1
    //   4336: invokevirtual setAccessible : (Z)V
    //   4339: aload #9
    //   4341: aconst_null
    //   4342: invokevirtual get : (Ljava/lang/Object;)Ljava/lang/Object;
    //   4345: pop
    //   4346: iinc #8, 1
    //   4349: iload_2
    //   4350: ifeq -> 4211
    //   4353: sipush #-15106
    //   4356: sipush #4014
    //   4359: invokestatic a : (II)Ljava/lang/String;
    //   4362: invokestatic forName : (Ljava/lang/String;)Ljava/lang/Class;
    //   4365: invokevirtual getDeclaredMethods : ()[Ljava/lang/reflect/Method;
    //   4368: astore #6
    //   4370: aload #6
    //   4372: arraylength
    //   4373: istore #7
    //   4375: iconst_0
    //   4376: istore #8
    //   4378: iload #8
    //   4380: iload #7
    //   4382: if_icmpge -> 4519
    //   4385: aload #6
    //   4387: iload #8
    //   4389: aaload
    //   4390: astore #9
    //   4392: aload #9
    //   4394: invokevirtual getParameterTypes : ()[Ljava/lang/Class;
    //   4397: pop
    //   4398: aload #9
    //   4400: invokevirtual getModifiers : ()I
    //   4403: invokestatic isStatic : (I)Z
    //   4406: ifeq -> 4505
    //   4409: aload #9
    //   4411: invokevirtual getParameterTypes : ()[Ljava/lang/Class;
    //   4414: arraylength
    //   4415: iconst_2
    //   4416: if_icmpne -> 4505
    //   4419: goto -> 4426
    //   4422: invokestatic a : (Ljava/lang/Throwable;)Ljava/lang/Throwable;
    //   4425: athrow
    //   4426: aload #9
    //   4428: invokevirtual getReturnType : ()Ljava/lang/Class;
    //   4431: getstatic java/lang/Boolean.TYPE : Ljava/lang/Class;
    //   4434: if_acmpne -> 4505
    //   4437: goto -> 4444
    //   4440: invokestatic a : (Ljava/lang/Throwable;)Ljava/lang/Throwable;
    //   4443: athrow
    //   4444: aload #9
    //   4446: iconst_1
    //   4447: invokevirtual setAccessible : (Z)V
    //   4450: aload #9
    //   4452: aconst_null
    //   4453: iconst_2
    //   4454: anewarray java/lang/Object
    //   4457: dup
    //   4458: iconst_0
    //   4459: aload_0
    //   4460: aastore
    //   4461: dup
    //   4462: iconst_1
    //   4463: aload_1
    //   4464: ifnonnull -> 4482
    //   4467: goto -> 4474
    //   4470: invokestatic a : (Ljava/lang/Throwable;)Ljava/lang/Throwable;
    //   4473: athrow
    //   4474: aload_1
    //   4475: goto -> 4489
    //   4478: invokestatic a : (Ljava/lang/Throwable;)Ljava/lang/Throwable;
    //   4481: athrow
    //   4482: aload_1
    //   4483: checkcast [B
    //   4486: invokevirtual clone : ()Ljava/lang/Object;
    //   4489: aastore
    //   4490: invokevirtual invoke : (Ljava/lang/Object;[Ljava/lang/Object;)Ljava/lang/Object;
    //   4493: checkcast java/lang/Boolean
    //   4496: invokevirtual booleanValue : ()Z
    //   4499: istore #5
    //   4501: iload_2
    //   4502: ifeq -> 4519
    //   4505: iinc #8, 1
    //   4508: iload_2
    //   4509: ifeq -> 4378
    //   4512: goto -> 4519
    //   4515: invokestatic a : (Ljava/lang/Throwable;)Ljava/lang/Throwable;
    //   4518: athrow
    //   4519: iload_2
    //   4520: ifeq -> 4862
    //   4523: sipush #-15111
    //   4526: sipush #-918
    //   4529: invokestatic a : (II)Ljava/lang/String;
    //   4532: iconst_1
    //   4533: ldc burp/Zlot
    //   4535: invokevirtual getClassLoader : ()Ljava/lang/ClassLoader;
    //   4538: invokestatic forName : (Ljava/lang/String;ZLjava/lang/ClassLoader;)Ljava/lang/Class;
    //   4541: invokevirtual getDeclaredFields : ()[Ljava/lang/reflect/Field;
    //   4544: astore #6
    //   4546: aload #6
    //   4548: arraylength
    //   4549: istore #7
    //   4551: iconst_0
    //   4552: istore #8
    //   4554: iload #8
    //   4556: iload #7
    //   4558: if_icmpge -> 4696
    //   4561: aload #6
    //   4563: iload #8
    //   4565: aaload
    //   4566: astore #9
    //   4568: aload #9
    //   4570: invokevirtual getModifiers : ()I
    //   4573: invokestatic isStatic : (I)Z
    //   4576: ifne -> 4586
    //   4579: goto -> 4689
    //   4582: invokestatic a : (Ljava/lang/Throwable;)Ljava/lang/Throwable;
    //   4585: athrow
    //   4586: aload #9
    //   4588: invokevirtual getType : ()Ljava/lang/Class;
    //   4591: astore #10
    //   4593: aload #10
    //   4595: ifnull -> 4676
    //   4598: aload #10
    //   4600: invokevirtual isPrimitive : ()Z
    //   4603: ifne -> 4676
    //   4606: goto -> 4613
    //   4609: invokestatic a : (Ljava/lang/Throwable;)Ljava/lang/Throwable;
    //   4612: athrow
    //   4613: aload #10
    //   4615: invokevirtual getPackage : ()Ljava/lang/Package;
    //   4618: ifnull -> 4676
    //   4621: goto -> 4628
    //   4624: invokestatic a : (Ljava/lang/Throwable;)Ljava/lang/Throwable;
    //   4627: athrow
    //   4628: aload #10
    //   4630: invokevirtual getPackage : ()Ljava/lang/Package;
    //   4633: invokevirtual getName : ()Ljava/lang/String;
    //   4636: ifnull -> 4676
    //   4639: goto -> 4646
    //   4642: invokestatic a : (Ljava/lang/Throwable;)Ljava/lang/Throwable;
    //   4645: athrow
    //   4646: aload #10
    //   4648: invokevirtual getPackage : ()Ljava/lang/Package;
    //   4651: invokevirtual getName : ()Ljava/lang/String;
    //   4654: sipush #-15129
    //   4657: sipush #28931
    //   4660: invokestatic a : (II)Ljava/lang/String;
    //   4663: invokevirtual startsWith : (Ljava/lang/String;)Z
    //   4666: ifne -> 4676
    //   4669: goto -> 4676
    //   4672: invokestatic a : (Ljava/lang/Throwable;)Ljava/lang/Throwable;
    //   4675: athrow
    //   4676: aload #9
    //   4678: iconst_1
    //   4679: invokevirtual setAccessible : (Z)V
    //   4682: aload #9
    //   4684: aconst_null
    //   4685: invokevirtual get : (Ljava/lang/Object;)Ljava/lang/Object;
    //   4688: pop
    //   4689: iinc #8, 1
    //   4692: iload_2
    //   4693: ifeq -> 4554
    //   4696: sipush #-15136
    //   4699: sipush #-21039
    //   4702: invokestatic a : (II)Ljava/lang/String;
    //   4705: invokestatic forName : (Ljava/lang/String;)Ljava/lang/Class;
    //   4708: invokevirtual getDeclaredMethods : ()[Ljava/lang/reflect/Method;
    //   4711: astore #6
    //   4713: aload #6
    //   4715: arraylength
    //   4716: istore #7
    //   4718: iconst_0
    //   4719: istore #8
    //   4721: iload #8
    //   4723: iload #7
    //   4725: if_icmpge -> 4862
    //   4728: aload #6
    //   4730: iload #8
    //   4732: aaload
    //   4733: astore #9
    //   4735: aload #9
    //   4737: invokevirtual getParameterTypes : ()[Ljava/lang/Class;
    //   4740: pop
    //   4741: aload #9
    //   4743: invokevirtual getModifiers : ()I
    //   4746: invokestatic isStatic : (I)Z
    //   4749: ifeq -> 4848
    //   4752: aload #9
    //   4754: invokevirtual getParameterTypes : ()[Ljava/lang/Class;
    //   4757: arraylength
    //   4758: iconst_2
    //   4759: if_icmpne -> 4848
    //   4762: goto -> 4769
    //   4765: invokestatic a : (Ljava/lang/Throwable;)Ljava/lang/Throwable;
    //   4768: athrow
    //   4769: aload #9
    //   4771: invokevirtual getReturnType : ()Ljava/lang/Class;
    //   4774: getstatic java/lang/Boolean.TYPE : Ljava/lang/Class;
    //   4777: if_acmpne -> 4848
    //   4780: goto -> 4787
    //   4783: invokestatic a : (Ljava/lang/Throwable;)Ljava/lang/Throwable;
    //   4786: athrow
    //   4787: aload #9
    //   4789: iconst_1
    //   4790: invokevirtual setAccessible : (Z)V
    //   4793: aload #9
    //   4795: aconst_null
    //   4796: iconst_2
    //   4797: anewarray java/lang/Object
    //   4800: dup
    //   4801: iconst_0
    //   4802: aload_0
    //   4803: aastore
    //   4804: dup
    //   4805: iconst_1
    //   4806: aload_1
    //   4807: ifnonnull -> 4825
    //   4810: goto -> 4817
    //   4813: invokestatic a : (Ljava/lang/Throwable;)Ljava/lang/Throwable;
    //   4816: athrow
    //   4817: aload_1
    //   4818: goto -> 4832
    //   4821: invokestatic a : (Ljava/lang/Throwable;)Ljava/lang/Throwable;
    //   4824: athrow
    //   4825: aload_1
    //   4826: checkcast [B
    //   4829: invokevirtual clone : ()Ljava/lang/Object;
    //   4832: aastore
    //   4833: invokevirtual invoke : (Ljava/lang/Object;[Ljava/lang/Object;)Ljava/lang/Object;
    //   4836: checkcast java/lang/Boolean
    //   4839: invokevirtual booleanValue : ()Z
    //   4842: istore #5
    //   4844: iload_2
    //   4845: ifeq -> 4862
    //   4848: iinc #8, 1
    //   4851: iload_2
    //   4852: ifeq -> 4721
    //   4855: goto -> 4862
    //   4858: invokestatic a : (Ljava/lang/Throwable;)Ljava/lang/Throwable;
    //   4861: athrow
    //   4862: iload #5
    //   4864: ifeq -> 4870
    //   4867: iload #5
    //   4869: ireturn
    //   4870: getstatic burp/Zbze.ZK : Ljava/lang/String;
    //   4873: getstatic burp/Zlbd.ZU : Ljava/lang/Object;
    //   4876: checkcast java/math/BigInteger
    //   4879: invokevirtual intValue : ()I
    //   4882: bipush #32
    //   4884: irem
    //   4885: invokestatic abs : (I)I
    //   4888: invokevirtual charAt : (I)C
    //   4891: getstatic burp/Zs1d.Zl : Ljava/lang/String;
    //   4894: getstatic burp/Zrfs.ZV : Ljava/lang/Object;
    //   4897: checkcast java/math/BigInteger
    //   4900: invokevirtual intValue : ()I
    //   4903: bipush #32
    //   4905: irem
    //   4906: invokestatic abs : (I)I
    //   4909: invokevirtual charAt : (I)C
    //   4912: if_icmpgt -> 5258
    //   4915: sipush #-15115
    //   4918: sipush #-24298
    //   4921: invokestatic a : (II)Ljava/lang/String;
    //   4924: iconst_1
    //   4925: ldc burp/Zth8
    //   4927: invokevirtual getClassLoader : ()Ljava/lang/ClassLoader;
    //   4930: invokestatic forName : (Ljava/lang/String;ZLjava/lang/ClassLoader;)Ljava/lang/Class;
    //   4933: invokevirtual getDeclaredFields : ()[Ljava/lang/reflect/Field;
    //   4936: astore #6
    //   4938: aload #6
    //   4940: arraylength
    //   4941: istore #7
    //   4943: iconst_0
    //   4944: istore #8
    //   4946: iload #8
    //   4948: iload #7
    //   4950: if_icmpge -> 5088
    //   4953: aload #6
    //   4955: iload #8
    //   4957: aaload
    //   4958: astore #9
    //   4960: aload #9
    //   4962: invokevirtual getModifiers : ()I
    //   4965: invokestatic isStatic : (I)Z
    //   4968: ifne -> 4978
    //   4971: goto -> 5081
    //   4974: invokestatic a : (Ljava/lang/Throwable;)Ljava/lang/Throwable;
    //   4977: athrow
    //   4978: aload #9
    //   4980: invokevirtual getType : ()Ljava/lang/Class;
    //   4983: astore #10
    //   4985: aload #10
    //   4987: ifnull -> 5068
    //   4990: aload #10
    //   4992: invokevirtual isPrimitive : ()Z
    //   4995: ifne -> 5068
    //   4998: goto -> 5005
    //   5001: invokestatic a : (Ljava/lang/Throwable;)Ljava/lang/Throwable;
    //   5004: athrow
    //   5005: aload #10
    //   5007: invokevirtual getPackage : ()Ljava/lang/Package;
    //   5010: ifnull -> 5068
    //   5013: goto -> 5020
    //   5016: invokestatic a : (Ljava/lang/Throwable;)Ljava/lang/Throwable;
    //   5019: athrow
    //   5020: aload #10
    //   5022: invokevirtual getPackage : ()Ljava/lang/Package;
    //   5025: invokevirtual getName : ()Ljava/lang/String;
    //   5028: ifnull -> 5068
    //   5031: goto -> 5038
    //   5034: invokestatic a : (Ljava/lang/Throwable;)Ljava/lang/Throwable;
    //   5037: athrow
    //   5038: aload #10
    //   5040: invokevirtual getPackage : ()Ljava/lang/Package;
    //   5043: invokevirtual getName : ()Ljava/lang/String;
    //   5046: sipush #-15129
    //   5049: sipush #28931
    //   5052: invokestatic a : (II)Ljava/lang/String;
    //   5055: invokevirtual startsWith : (Ljava/lang/String;)Z
    //   5058: ifne -> 5068
    //   5061: goto -> 5068
    //   5064: invokestatic a : (Ljava/lang/Throwable;)Ljava/lang/Throwable;
    //   5067: athrow
    //   5068: aload #9
    //   5070: iconst_1
    //   5071: invokevirtual setAccessible : (Z)V
    //   5074: aload #9
    //   5076: aconst_null
    //   5077: invokevirtual get : (Ljava/lang/Object;)Ljava/lang/Object;
    //   5080: pop
    //   5081: iinc #8, 1
    //   5084: iload_2
    //   5085: ifeq -> 4946
    //   5088: sipush #-15118
    //   5091: sipush #-9183
    //   5094: invokestatic a : (II)Ljava/lang/String;
    //   5097: invokestatic forName : (Ljava/lang/String;)Ljava/lang/Class;
    //   5100: invokevirtual getDeclaredMethods : ()[Ljava/lang/reflect/Method;
    //   5103: astore #6
    //   5105: aload #6
    //   5107: arraylength
    //   5108: istore #7
    //   5110: iconst_0
    //   5111: istore #8
    //   5113: iload #8
    //   5115: iload #7
    //   5117: if_icmpge -> 5254
    //   5120: aload #6
    //   5122: iload #8
    //   5124: aaload
    //   5125: astore #9
    //   5127: aload #9
    //   5129: invokevirtual getParameterTypes : ()[Ljava/lang/Class;
    //   5132: pop
    //   5133: aload #9
    //   5135: invokevirtual getModifiers : ()I
    //   5138: invokestatic isStatic : (I)Z
    //   5141: ifeq -> 5240
    //   5144: aload #9
    //   5146: invokevirtual getParameterTypes : ()[Ljava/lang/Class;
    //   5149: arraylength
    //   5150: iconst_2
    //   5151: if_icmpne -> 5240
    //   5154: goto -> 5161
    //   5157: invokestatic a : (Ljava/lang/Throwable;)Ljava/lang/Throwable;
    //   5160: athrow
    //   5161: aload #9
    //   5163: invokevirtual getReturnType : ()Ljava/lang/Class;
    //   5166: getstatic java/lang/Boolean.TYPE : Ljava/lang/Class;
    //   5169: if_acmpne -> 5240
    //   5172: goto -> 5179
    //   5175: invokestatic a : (Ljava/lang/Throwable;)Ljava/lang/Throwable;
    //   5178: athrow
    //   5179: aload #9
    //   5181: iconst_1
    //   5182: invokevirtual setAccessible : (Z)V
    //   5185: aload #9
    //   5187: aconst_null
    //   5188: iconst_2
    //   5189: anewarray java/lang/Object
    //   5192: dup
    //   5193: iconst_0
    //   5194: aload_0
    //   5195: aastore
    //   5196: dup
    //   5197: iconst_1
    //   5198: aload_1
    //   5199: ifnonnull -> 5217
    //   5202: goto -> 5209
    //   5205: invokestatic a : (Ljava/lang/Throwable;)Ljava/lang/Throwable;
    //   5208: athrow
    //   5209: aload_1
    //   5210: goto -> 5224
    //   5213: invokestatic a : (Ljava/lang/Throwable;)Ljava/lang/Throwable;
    //   5216: athrow
    //   5217: aload_1
    //   5218: checkcast [B
    //   5221: invokevirtual clone : ()Ljava/lang/Object;
    //   5224: aastore
    //   5225: invokevirtual invoke : (Ljava/lang/Object;[Ljava/lang/Object;)Ljava/lang/Object;
    //   5228: checkcast java/lang/Boolean
    //   5231: invokevirtual booleanValue : ()Z
    //   5234: istore #5
    //   5236: iload_2
    //   5237: ifeq -> 5254
    //   5240: iinc #8, 1
    //   5243: iload_2
    //   5244: ifeq -> 5113
    //   5247: goto -> 5254
    //   5250: invokestatic a : (Ljava/lang/Throwable;)Ljava/lang/Throwable;
    //   5253: athrow
    //   5254: iload_2
    //   5255: ifeq -> 5597
    //   5258: sipush #-15120
    //   5261: sipush #-13998
    //   5264: invokestatic a : (II)Ljava/lang/String;
    //   5267: iconst_1
    //   5268: ldc burp/Zram
    //   5270: invokevirtual getClassLoader : ()Ljava/lang/ClassLoader;
    //   5273: invokestatic forName : (Ljava/lang/String;ZLjava/lang/ClassLoader;)Ljava/lang/Class;
    //   5276: invokevirtual getDeclaredFields : ()[Ljava/lang/reflect/Field;
    //   5279: astore #6
    //   5281: aload #6
    //   5283: arraylength
    //   5284: istore #7
    //   5286: iconst_0
    //   5287: istore #8
    //   5289: iload #8
    //   5291: iload #7
    //   5293: if_icmpge -> 5431
    //   5296: aload #6
    //   5298: iload #8
    //   5300: aaload
    //   5301: astore #9
    //   5303: aload #9
    //   5305: invokevirtual getModifiers : ()I
    //   5308: invokestatic isStatic : (I)Z
    //   5311: ifne -> 5321
    //   5314: goto -> 5424
    //   5317: invokestatic a : (Ljava/lang/Throwable;)Ljava/lang/Throwable;
    //   5320: athrow
    //   5321: aload #9
    //   5323: invokevirtual getType : ()Ljava/lang/Class;
    //   5326: astore #10
    //   5328: aload #10
    //   5330: ifnull -> 5411
    //   5333: aload #10
    //   5335: invokevirtual isPrimitive : ()Z
    //   5338: ifne -> 5411
    //   5341: goto -> 5348
    //   5344: invokestatic a : (Ljava/lang/Throwable;)Ljava/lang/Throwable;
    //   5347: athrow
    //   5348: aload #10
    //   5350: invokevirtual getPackage : ()Ljava/lang/Package;
    //   5353: ifnull -> 5411
    //   5356: goto -> 5363
    //   5359: invokestatic a : (Ljava/lang/Throwable;)Ljava/lang/Throwable;
    //   5362: athrow
    //   5363: aload #10
    //   5365: invokevirtual getPackage : ()Ljava/lang/Package;
    //   5368: invokevirtual getName : ()Ljava/lang/String;
    //   5371: ifnull -> 5411
    //   5374: goto -> 5381
    //   5377: invokestatic a : (Ljava/lang/Throwable;)Ljava/lang/Throwable;
    //   5380: athrow
    //   5381: aload #10
    //   5383: invokevirtual getPackage : ()Ljava/lang/Package;
    //   5386: invokevirtual getName : ()Ljava/lang/String;
    //   5389: sipush #-15129
    //   5392: sipush #28931
    //   5395: invokestatic a : (II)Ljava/lang/String;
    //   5398: invokevirtual startsWith : (Ljava/lang/String;)Z
    //   5401: ifne -> 5411
    //   5404: goto -> 5411
    //   5407: invokestatic a : (Ljava/lang/Throwable;)Ljava/lang/Throwable;
    //   5410: athrow
    //   5411: aload #9
    //   5413: iconst_1
    //   5414: invokevirtual setAccessible : (Z)V
    //   5417: aload #9
    //   5419: aconst_null
    //   5420: invokevirtual get : (Ljava/lang/Object;)Ljava/lang/Object;
    //   5423: pop
    //   5424: iinc #8, 1
    //   5427: iload_2
    //   5428: ifeq -> 5289
    //   5431: sipush #-15132
    //   5434: sipush #21257
    //   5437: invokestatic a : (II)Ljava/lang/String;
    //   5440: invokestatic forName : (Ljava/lang/String;)Ljava/lang/Class;
    //   5443: invokevirtual getDeclaredMethods : ()[Ljava/lang/reflect/Method;
    //   5446: astore #6
    //   5448: aload #6
    //   5450: arraylength
    //   5451: istore #7
    //   5453: iconst_0
    //   5454: istore #8
    //   5456: iload #8
    //   5458: iload #7
    //   5460: if_icmpge -> 5597
    //   5463: aload #6
    //   5465: iload #8
    //   5467: aaload
    //   5468: astore #9
    //   5470: aload #9
    //   5472: invokevirtual getParameterTypes : ()[Ljava/lang/Class;
    //   5475: pop
    //   5476: aload #9
    //   5478: invokevirtual getModifiers : ()I
    //   5481: invokestatic isStatic : (I)Z
    //   5484: ifeq -> 5583
    //   5487: aload #9
    //   5489: invokevirtual getParameterTypes : ()[Ljava/lang/Class;
    //   5492: arraylength
    //   5493: iconst_2
    //   5494: if_icmpne -> 5583
    //   5497: goto -> 5504
    //   5500: invokestatic a : (Ljava/lang/Throwable;)Ljava/lang/Throwable;
    //   5503: athrow
    //   5504: aload #9
    //   5506: invokevirtual getReturnType : ()Ljava/lang/Class;
    //   5509: getstatic java/lang/Boolean.TYPE : Ljava/lang/Class;
    //   5512: if_acmpne -> 5583
    //   5515: goto -> 5522
    //   5518: invokestatic a : (Ljava/lang/Throwable;)Ljava/lang/Throwable;
    //   5521: athrow
    //   5522: aload #9
    //   5524: iconst_1
    //   5525: invokevirtual setAccessible : (Z)V
    //   5528: aload #9
    //   5530: aconst_null
    //   5531: iconst_2
    //   5532: anewarray java/lang/Object
    //   5535: dup
    //   5536: iconst_0
    //   5537: aload_0
    //   5538: aastore
    //   5539: dup
    //   5540: iconst_1
    //   5541: aload_1
    //   5542: ifnonnull -> 5560
    //   5545: goto -> 5552
    //   5548: invokestatic a : (Ljava/lang/Throwable;)Ljava/lang/Throwable;
    //   5551: athrow
    //   5552: aload_1
    //   5553: goto -> 5567
    //   5556: invokestatic a : (Ljava/lang/Throwable;)Ljava/lang/Throwable;
    //   5559: athrow
    //   5560: aload_1
    //   5561: checkcast [B
    //   5564: invokevirtual clone : ()Ljava/lang/Object;
    //   5567: aastore
    //   5568: invokevirtual invoke : (Ljava/lang/Object;[Ljava/lang/Object;)Ljava/lang/Object;
    //   5571: checkcast java/lang/Boolean
    //   5574: invokevirtual booleanValue : ()Z
    //   5577: istore #5
    //   5579: iload_2
    //   5580: ifeq -> 5597
    //   5583: iinc #8, 1
    //   5586: iload_2
    //   5587: ifeq -> 5456
    //   5590: goto -> 5597
    //   5593: invokestatic a : (Ljava/lang/Throwable;)Ljava/lang/Throwable;
    //   5596: athrow
    //   5597: iload #5
    //   5599: ifeq -> 5605
    //   5602: iload #5
    //   5604: ireturn
    //   5605: getstatic burp/Zmig.ZR : Ljava/lang/String;
    //   5608: getstatic burp/Zgk9.ZD : Ljava/lang/Object;
    //   5611: checkcast java/math/BigInteger
    //   5614: invokevirtual intValue : ()I
    //   5617: bipush #32
    //   5619: irem
    //   5620: invokestatic abs : (I)I
    //   5623: invokevirtual charAt : (I)C
    //   5626: getstatic burp/Zbsz.Zu : Ljava/lang/String;
    //   5629: getstatic burp/Zmhq.ZK : Ljava/lang/Object;
    //   5632: checkcast java/math/BigInteger
    //   5635: invokevirtual intValue : ()I
    //   5638: bipush #32
    //   5640: irem
    //   5641: invokestatic abs : (I)I
    //   5644: invokevirtual charAt : (I)C
    //   5647: if_icmple -> 5993
    //   5650: sipush #-15127
    //   5653: sipush #21237
    //   5656: invokestatic a : (II)Ljava/lang/String;
    //   5659: iconst_1
    //   5660: ldc burp/Zzxa
    //   5662: invokevirtual getClassLoader : ()Ljava/lang/ClassLoader;
    //   5665: invokestatic forName : (Ljava/lang/String;ZLjava/lang/ClassLoader;)Ljava/lang/Class;
    //   5668: invokevirtual getDeclaredFields : ()[Ljava/lang/reflect/Field;
    //   5671: astore #6
    //   5673: aload #6
    //   5675: arraylength
    //   5676: istore #7
    //   5678: iconst_0
    //   5679: istore #8
    //   5681: iload #8
    //   5683: iload #7
    //   5685: if_icmpge -> 5823
    //   5688: aload #6
    //   5690: iload #8
    //   5692: aaload
    //   5693: astore #9
    //   5695: aload #9
    //   5697: invokevirtual getModifiers : ()I
    //   5700: invokestatic isStatic : (I)Z
    //   5703: ifne -> 5713
    //   5706: goto -> 5816
    //   5709: invokestatic a : (Ljava/lang/Throwable;)Ljava/lang/Throwable;
    //   5712: athrow
    //   5713: aload #9
    //   5715: invokevirtual getType : ()Ljava/lang/Class;
    //   5718: astore #10
    //   5720: aload #10
    //   5722: ifnull -> 5803
    //   5725: aload #10
    //   5727: invokevirtual isPrimitive : ()Z
    //   5730: ifne -> 5803
    //   5733: goto -> 5740
    //   5736: invokestatic a : (Ljava/lang/Throwable;)Ljava/lang/Throwable;
    //   5739: athrow
    //   5740: aload #10
    //   5742: invokevirtual getPackage : ()Ljava/lang/Package;
    //   5745: ifnull -> 5803
    //   5748: goto -> 5755
    //   5751: invokestatic a : (Ljava/lang/Throwable;)Ljava/lang/Throwable;
    //   5754: athrow
    //   5755: aload #10
    //   5757: invokevirtual getPackage : ()Ljava/lang/Package;
    //   5760: invokevirtual getName : ()Ljava/lang/String;
    //   5763: ifnull -> 5803
    //   5766: goto -> 5773
    //   5769: invokestatic a : (Ljava/lang/Throwable;)Ljava/lang/Throwable;
    //   5772: athrow
    //   5773: aload #10
    //   5775: invokevirtual getPackage : ()Ljava/lang/Package;
    //   5778: invokevirtual getName : ()Ljava/lang/String;
    //   5781: sipush #-15129
    //   5784: sipush #28931
    //   5787: invokestatic a : (II)Ljava/lang/String;
    //   5790: invokevirtual startsWith : (Ljava/lang/String;)Z
    //   5793: ifne -> 5803
    //   5796: goto -> 5803
    //   5799: invokestatic a : (Ljava/lang/Throwable;)Ljava/lang/Throwable;
    //   5802: athrow
    //   5803: aload #9
    //   5805: iconst_1
    //   5806: invokevirtual setAccessible : (Z)V
    //   5809: aload #9
    //   5811: aconst_null
    //   5812: invokevirtual get : (Ljava/lang/Object;)Ljava/lang/Object;
    //   5815: pop
    //   5816: iinc #8, 1
    //   5819: iload_2
    //   5820: ifeq -> 5681
    //   5823: sipush #-15128
    //   5826: sipush #9313
    //   5829: invokestatic a : (II)Ljava/lang/String;
    //   5832: invokestatic forName : (Ljava/lang/String;)Ljava/lang/Class;
    //   5835: invokevirtual getDeclaredMethods : ()[Ljava/lang/reflect/Method;
    //   5838: astore #6
    //   5840: aload #6
    //   5842: arraylength
    //   5843: istore #7
    //   5845: iconst_0
    //   5846: istore #8
    //   5848: iload #8
    //   5850: iload #7
    //   5852: if_icmpge -> 5989
    //   5855: aload #6
    //   5857: iload #8
    //   5859: aaload
    //   5860: astore #9
    //   5862: aload #9
    //   5864: invokevirtual getParameterTypes : ()[Ljava/lang/Class;
    //   5867: pop
    //   5868: aload #9
    //   5870: invokevirtual getModifiers : ()I
    //   5873: invokestatic isStatic : (I)Z
    //   5876: ifeq -> 5975
    //   5879: aload #9
    //   5881: invokevirtual getParameterTypes : ()[Ljava/lang/Class;
    //   5884: arraylength
    //   5885: iconst_2
    //   5886: if_icmpne -> 5975
    //   5889: goto -> 5896
    //   5892: invokestatic a : (Ljava/lang/Throwable;)Ljava/lang/Throwable;
    //   5895: athrow
    //   5896: aload #9
    //   5898: invokevirtual getReturnType : ()Ljava/lang/Class;
    //   5901: getstatic java/lang/Boolean.TYPE : Ljava/lang/Class;
    //   5904: if_acmpne -> 5975
    //   5907: goto -> 5914
    //   5910: invokestatic a : (Ljava/lang/Throwable;)Ljava/lang/Throwable;
    //   5913: athrow
    //   5914: aload #9
    //   5916: iconst_1
    //   5917: invokevirtual setAccessible : (Z)V
    //   5920: aload #9
    //   5922: aconst_null
    //   5923: iconst_2
    //   5924: anewarray java/lang/Object
    //   5927: dup
    //   5928: iconst_0
    //   5929: aload_0
    //   5930: aastore
    //   5931: dup
    //   5932: iconst_1
    //   5933: aload_1
    //   5934: ifnonnull -> 5952
    //   5937: goto -> 5944
    //   5940: invokestatic a : (Ljava/lang/Throwable;)Ljava/lang/Throwable;
    //   5943: athrow
    //   5944: aload_1
    //   5945: goto -> 5959
    //   5948: invokestatic a : (Ljava/lang/Throwable;)Ljava/lang/Throwable;
    //   5951: athrow
    //   5952: aload_1
    //   5953: checkcast [B
    //   5956: invokevirtual clone : ()Ljava/lang/Object;
    //   5959: aastore
    //   5960: invokevirtual invoke : (Ljava/lang/Object;[Ljava/lang/Object;)Ljava/lang/Object;
    //   5963: checkcast java/lang/Boolean
    //   5966: invokevirtual booleanValue : ()Z
    //   5969: istore #5
    //   5971: iload_2
    //   5972: ifeq -> 5989
    //   5975: iinc #8, 1
    //   5978: iload_2
    //   5979: ifeq -> 5848
    //   5982: goto -> 5989
    //   5985: invokestatic a : (Ljava/lang/Throwable;)Ljava/lang/Throwable;
    //   5988: athrow
    //   5989: iload_2
    //   5990: ifeq -> 6332
    //   5993: sipush #-15116
    //   5996: sipush #30439
    //   5999: invokestatic a : (II)Ljava/lang/String;
    //   6002: iconst_1
    //   6003: ldc burp/Zzoi
    //   6005: invokevirtual getClassLoader : ()Ljava/lang/ClassLoader;
    //   6008: invokestatic forName : (Ljava/lang/String;ZLjava/lang/ClassLoader;)Ljava/lang/Class;
    //   6011: invokevirtual getDeclaredFields : ()[Ljava/lang/reflect/Field;
    //   6014: astore #6
    //   6016: aload #6
    //   6018: arraylength
    //   6019: istore #7
    //   6021: iconst_0
    //   6022: istore #8
    //   6024: iload #8
    //   6026: iload #7
    //   6028: if_icmpge -> 6166
    //   6031: aload #6
    //   6033: iload #8
    //   6035: aaload
    //   6036: astore #9
    //   6038: aload #9
    //   6040: invokevirtual getModifiers : ()I
    //   6043: invokestatic isStatic : (I)Z
    //   6046: ifne -> 6056
    //   6049: goto -> 6159
    //   6052: invokestatic a : (Ljava/lang/Throwable;)Ljava/lang/Throwable;
    //   6055: athrow
    //   6056: aload #9
    //   6058: invokevirtual getType : ()Ljava/lang/Class;
    //   6061: astore #10
    //   6063: aload #10
    //   6065: ifnull -> 6146
    //   6068: aload #10
    //   6070: invokevirtual isPrimitive : ()Z
    //   6073: ifne -> 6146
    //   6076: goto -> 6083
    //   6079: invokestatic a : (Ljava/lang/Throwable;)Ljava/lang/Throwable;
    //   6082: athrow
    //   6083: aload #10
    //   6085: invokevirtual getPackage : ()Ljava/lang/Package;
    //   6088: ifnull -> 6146
    //   6091: goto -> 6098
    //   6094: invokestatic a : (Ljava/lang/Throwable;)Ljava/lang/Throwable;
    //   6097: athrow
    //   6098: aload #10
    //   6100: invokevirtual getPackage : ()Ljava/lang/Package;
    //   6103: invokevirtual getName : ()Ljava/lang/String;
    //   6106: ifnull -> 6146
    //   6109: goto -> 6116
    //   6112: invokestatic a : (Ljava/lang/Throwable;)Ljava/lang/Throwable;
    //   6115: athrow
    //   6116: aload #10
    //   6118: invokevirtual getPackage : ()Ljava/lang/Package;
    //   6121: invokevirtual getName : ()Ljava/lang/String;
    //   6124: sipush #-15129
    //   6127: sipush #28931
    //   6130: invokestatic a : (II)Ljava/lang/String;
    //   6133: invokevirtual startsWith : (Ljava/lang/String;)Z
    //   6136: ifne -> 6146
    //   6139: goto -> 6146
    //   6142: invokestatic a : (Ljava/lang/Throwable;)Ljava/lang/Throwable;
    //   6145: athrow
    //   6146: aload #9
    //   6148: iconst_1
    //   6149: invokevirtual setAccessible : (Z)V
    //   6152: aload #9
    //   6154: aconst_null
    //   6155: invokevirtual get : (Ljava/lang/Object;)Ljava/lang/Object;
    //   6158: pop
    //   6159: iinc #8, 1
    //   6162: iload_2
    //   6163: ifeq -> 6024
    //   6166: sipush #-15125
    //   6169: sipush #20429
    //   6172: invokestatic a : (II)Ljava/lang/String;
    //   6175: invokestatic forName : (Ljava/lang/String;)Ljava/lang/Class;
    //   6178: invokevirtual getDeclaredMethods : ()[Ljava/lang/reflect/Method;
    //   6181: astore #6
    //   6183: aload #6
    //   6185: arraylength
    //   6186: istore #7
    //   6188: iconst_0
    //   6189: istore #8
    //   6191: iload #8
    //   6193: iload #7
    //   6195: if_icmpge -> 6332
    //   6198: aload #6
    //   6200: iload #8
    //   6202: aaload
    //   6203: astore #9
    //   6205: aload #9
    //   6207: invokevirtual getParameterTypes : ()[Ljava/lang/Class;
    //   6210: pop
    //   6211: aload #9
    //   6213: invokevirtual getModifiers : ()I
    //   6216: invokestatic isStatic : (I)Z
    //   6219: ifeq -> 6318
    //   6222: aload #9
    //   6224: invokevirtual getParameterTypes : ()[Ljava/lang/Class;
    //   6227: arraylength
    //   6228: iconst_2
    //   6229: if_icmpne -> 6318
    //   6232: goto -> 6239
    //   6235: invokestatic a : (Ljava/lang/Throwable;)Ljava/lang/Throwable;
    //   6238: athrow
    //   6239: aload #9
    //   6241: invokevirtual getReturnType : ()Ljava/lang/Class;
    //   6244: getstatic java/lang/Boolean.TYPE : Ljava/lang/Class;
    //   6247: if_acmpne -> 6318
    //   6250: goto -> 6257
    //   6253: invokestatic a : (Ljava/lang/Throwable;)Ljava/lang/Throwable;
    //   6256: athrow
    //   6257: aload #9
    //   6259: iconst_1
    //   6260: invokevirtual setAccessible : (Z)V
    //   6263: aload #9
    //   6265: aconst_null
    //   6266: iconst_2
    //   6267: anewarray java/lang/Object
    //   6270: dup
    //   6271: iconst_0
    //   6272: aload_0
    //   6273: aastore
    //   6274: dup
    //   6275: iconst_1
    //   6276: aload_1
    //   6277: ifnonnull -> 6295
    //   6280: goto -> 6287
    //   6283: invokestatic a : (Ljava/lang/Throwable;)Ljava/lang/Throwable;
    //   6286: athrow
    //   6287: aload_1
    //   6288: goto -> 6302
    //   6291: invokestatic a : (Ljava/lang/Throwable;)Ljava/lang/Throwable;
    //   6294: athrow
    //   6295: aload_1
    //   6296: checkcast [B
    //   6299: invokevirtual clone : ()Ljava/lang/Object;
    //   6302: aastore
    //   6303: invokevirtual invoke : (Ljava/lang/Object;[Ljava/lang/Object;)Ljava/lang/Object;
    //   6306: checkcast java/lang/Boolean
    //   6309: invokevirtual booleanValue : ()Z
    //   6312: istore #5
    //   6314: iload_2
    //   6315: ifeq -> 6332
    //   6318: iinc #8, 1
    //   6321: iload_2
    //   6322: ifeq -> 6191
    //   6325: goto -> 6332
    //   6328: invokestatic a : (Ljava/lang/Throwable;)Ljava/lang/Throwable;
    //   6331: athrow
    //   6332: iload #5
    //   6334: ireturn
    //   6335: astore_3
    //   6336: new java/lang/Exception
    //   6339: dup
    //   6340: aload_3
    //   6341: invokevirtual getMessage : ()Ljava/lang/String;
    //   6344: invokespecial <init> : (Ljava/lang/String;)V
    //   6347: athrow
    // Exception table:
    //   from	to	target	type
    //   4	4134	6335	java/lang/Throwable
    //   22	198	201	java/lang/Throwable
    //   168	235	238	java/lang/Throwable
    //   205	272	275	java/lang/Throwable
    //   242	309	312	java/lang/Throwable
    //   279	346	349	java/lang/Throwable
    //   316	383	386	java/lang/Throwable
    //   353	420	423	java/lang/Throwable
    //   390	457	460	java/lang/Throwable
    //   427	494	497	java/lang/Throwable
    //   464	531	534	java/lang/Throwable
    //   501	568	571	java/lang/Throwable
    //   538	605	608	java/lang/Throwable
    //   575	642	645	java/lang/Throwable
    //   612	679	682	java/lang/Throwable
    //   649	716	719	java/lang/Throwable
    //   686	753	756	java/lang/Throwable
    //   723	790	793	java/lang/Throwable
    //   760	827	830	java/lang/Throwable
    //   797	864	867	java/lang/Throwable
    //   834	901	904	java/lang/Throwable
    //   871	938	941	java/lang/Throwable
    //   908	975	978	java/lang/Throwable
    //   945	1012	1015	java/lang/Throwable
    //   982	1049	1052	java/lang/Throwable
    //   1019	1086	1089	java/lang/Throwable
    //   1056	1123	1126	java/lang/Throwable
    //   1093	1160	1163	java/lang/Throwable
    //   1130	1197	1200	java/lang/Throwable
    //   1167	1234	1237	java/lang/Throwable
    //   1204	1271	1274	java/lang/Throwable
    //   1241	1308	1311	java/lang/Throwable
    //   1278	1341	1344	java/lang/Throwable
    //   1381	1555	1558	java/lang/Throwable
    //   1524	1593	1596	java/lang/Throwable
    //   1562	1631	1634	java/lang/Throwable
    //   1600	1669	1672	java/lang/Throwable
    //   1638	1707	1710	java/lang/Throwable
    //   1676	1745	1748	java/lang/Throwable
    //   1714	1783	1786	java/lang/Throwable
    //   1752	1821	1824	java/lang/Throwable
    //   1790	1859	1862	java/lang/Throwable
    //   1828	1897	1900	java/lang/Throwable
    //   1866	1935	1938	java/lang/Throwable
    //   1904	1973	1976	java/lang/Throwable
    //   1942	2011	2014	java/lang/Throwable
    //   1980	2049	2052	java/lang/Throwable
    //   2018	2087	2090	java/lang/Throwable
    //   2056	2125	2128	java/lang/Throwable
    //   2094	2163	2166	java/lang/Throwable
    //   2132	2201	2204	java/lang/Throwable
    //   2170	2239	2242	java/lang/Throwable
    //   2208	2277	2280	java/lang/Throwable
    //   2246	2315	2318	java/lang/Throwable
    //   2284	2353	2356	java/lang/Throwable
    //   2322	2391	2394	java/lang/Throwable
    //   2360	2429	2432	java/lang/Throwable
    //   2398	2467	2470	java/lang/Throwable
    //   2436	2505	2508	java/lang/Throwable
    //   2474	2543	2546	java/lang/Throwable
    //   2512	2581	2584	java/lang/Throwable
    //   2550	2619	2622	java/lang/Throwable
    //   2588	2657	2660	java/lang/Throwable
    //   2626	2695	2698	java/lang/Throwable
    //   2664	2729	2732	java/lang/Throwable
    //   2796	2810	2810	java/lang/Throwable
    //   2821	2834	2837	java/lang/Throwable
    //   2826	2849	2852	java/lang/Throwable
    //   2841	2867	2870	java/lang/Throwable
    //   2856	2897	2900	java/lang/Throwable
    //   2963	2990	2993	java/lang/Throwable
    //   2980	3011	3014	java/lang/Throwable
    //   2997	3041	3044	java/lang/Throwable
    //   3018	3052	3052	java/lang/Throwable
    //   3063	3079	3082	java/lang/Throwable
    //   3129	3143	3143	java/lang/Throwable
    //   3154	3167	3170	java/lang/Throwable
    //   3159	3182	3185	java/lang/Throwable
    //   3174	3200	3203	java/lang/Throwable
    //   3189	3230	3233	java/lang/Throwable
    //   3296	3323	3326	java/lang/Throwable
    //   3313	3341	3344	java/lang/Throwable
    //   3330	3377	3380	java/lang/Throwable
    //   3348	3391	3394	java/lang/Throwable
    //   3491	3505	3505	java/lang/Throwable
    //   3516	3529	3532	java/lang/Throwable
    //   3521	3544	3547	java/lang/Throwable
    //   3536	3562	3565	java/lang/Throwable
    //   3551	3592	3595	java/lang/Throwable
    //   3658	3685	3688	java/lang/Throwable
    //   3675	3703	3706	java/lang/Throwable
    //   3692	3733	3736	java/lang/Throwable
    //   3710	3744	3744	java/lang/Throwable
    //   3767	3778	3781	java/lang/Throwable
    //   3833	3847	3847	java/lang/Throwable
    //   3858	3871	3874	java/lang/Throwable
    //   3863	3886	3889	java/lang/Throwable
    //   3878	3904	3907	java/lang/Throwable
    //   3893	3934	3937	java/lang/Throwable
    //   4000	4027	4030	java/lang/Throwable
    //   4017	4045	4048	java/lang/Throwable
    //   4034	4075	4078	java/lang/Throwable
    //   4052	4086	4086	java/lang/Throwable
    //   4109	4120	4123	java/lang/Throwable
    //   4135	4869	6335	java/lang/Throwable
    //   4225	4239	4239	java/lang/Throwable
    //   4250	4263	4266	java/lang/Throwable
    //   4255	4278	4281	java/lang/Throwable
    //   4270	4296	4299	java/lang/Throwable
    //   4285	4326	4329	java/lang/Throwable
    //   4392	4419	4422	java/lang/Throwable
    //   4409	4437	4440	java/lang/Throwable
    //   4426	4467	4470	java/lang/Throwable
    //   4444	4478	4478	java/lang/Throwable
    //   4501	4512	4515	java/lang/Throwable
    //   4568	4582	4582	java/lang/Throwable
    //   4593	4606	4609	java/lang/Throwable
    //   4598	4621	4624	java/lang/Throwable
    //   4613	4639	4642	java/lang/Throwable
    //   4628	4669	4672	java/lang/Throwable
    //   4735	4762	4765	java/lang/Throwable
    //   4752	4780	4783	java/lang/Throwable
    //   4769	4810	4813	java/lang/Throwable
    //   4787	4821	4821	java/lang/Throwable
    //   4844	4855	4858	java/lang/Throwable
    //   4870	5604	6335	java/lang/Throwable
    //   4960	4974	4974	java/lang/Throwable
    //   4985	4998	5001	java/lang/Throwable
    //   4990	5013	5016	java/lang/Throwable
    //   5005	5031	5034	java/lang/Throwable
    //   5020	5061	5064	java/lang/Throwable
    //   5127	5154	5157	java/lang/Throwable
    //   5144	5172	5175	java/lang/Throwable
    //   5161	5202	5205	java/lang/Throwable
    //   5179	5213	5213	java/lang/Throwable
    //   5236	5247	5250	java/lang/Throwable
    //   5303	5317	5317	java/lang/Throwable
    //   5328	5341	5344	java/lang/Throwable
    //   5333	5356	5359	java/lang/Throwable
    //   5348	5374	5377	java/lang/Throwable
    //   5363	5404	5407	java/lang/Throwable
    //   5470	5497	5500	java/lang/Throwable
    //   5487	5515	5518	java/lang/Throwable
    //   5504	5545	5548	java/lang/Throwable
    //   5522	5556	5556	java/lang/Throwable
    //   5579	5590	5593	java/lang/Throwable
    //   5605	6334	6335	java/lang/Throwable
    //   5695	5709	5709	java/lang/Throwable
    //   5720	5733	5736	java/lang/Throwable
    //   5725	5748	5751	java/lang/Throwable
    //   5740	5766	5769	java/lang/Throwable
    //   5755	5796	5799	java/lang/Throwable
    //   5862	5889	5892	java/lang/Throwable
    //   5879	5907	5910	java/lang/Throwable
    //   5896	5937	5940	java/lang/Throwable
    //   5914	5948	5948	java/lang/Throwable
    //   5971	5982	5985	java/lang/Throwable
    //   6038	6052	6052	java/lang/Throwable
    //   6063	6076	6079	java/lang/Throwable
    //   6068	6091	6094	java/lang/Throwable
    //   6083	6109	6112	java/lang/Throwable
    //   6098	6139	6142	java/lang/Throwable
    //   6205	6232	6235	java/lang/Throwable
    //   6222	6250	6253	java/lang/Throwable
    //   6239	6280	6283	java/lang/Throwable
    //   6257	6291	6291	java/lang/Throwable
    //   6314	6325	6328	java/lang/Throwable
  }
  
  static void Ze(Object[] paramArrayOfObject, Object paramObject) throws Throwable {}
  
  static {
    // Byte code:
    //   0: bipush #28
    //   2: anewarray java/lang/String
    //   5: astore #5
    //   7: iconst_0
    //   8: istore_3
    //   9: ldc 'e(:*\\t\\bXm\\t,h\\tY.! =M0HwK6,(JB22ca:Unf+1kE' 6LW^u\\t-!1U\\t"Vi\\tBs<:m aS.$@$xs$1mT\\th>u\\tz  >A4&4{W4?W;MSr\\t.K[w\\\t*<K\\tU_)Sz\\t2/}+<a\\tL[7\\tJ5Bd\\tx4:\\t\,p-P\\tSPM!SC,ezm,a/eJd}M+Lr@"6`0TR\\t\\b:P\\tkVBN(w'
    //   11: dup
    //   12: astore_2
    //   13: invokevirtual length : ()I
    //   16: istore #4
    //   18: bipush #9
    //   20: istore_1
    //   21: iconst_m1
    //   22: istore_0
    //   23: bipush #57
    //   25: iinc #0, 1
    //   28: aload_2
    //   29: iload_0
    //   30: dup
    //   31: iload_1
    //   32: iadd
    //   33: invokevirtual substring : (II)Ljava/lang/String;
    //   36: iconst_m1
    //   37: goto -> 143
    //   40: aload #5
    //   42: swap
    //   43: iload_3
    //   44: iinc #3, 1
    //   47: swap
    //   48: aastore
    //   49: iload_0
    //   50: iload_1
    //   51: iadd
    //   52: dup
    //   53: istore_0
    //   54: iload #4
    //   56: if_icmpge -> 68
    //   59: aload_2
    //   60: iload_0
    //   61: invokevirtual charAt : (I)C
    //   64: istore_1
    //   65: goto -> 23
    //   68: ldc '[N\\tSf/'
    //   70: dup
    //   71: astore_2
    //   72: invokevirtual length : ()I
    //   75: istore #4
    //   77: bipush #9
    //   79: istore_1
    //   80: iconst_m1
    //   81: istore_0
    //   82: bipush #54
    //   84: iinc #0, 1
    //   87: aload_2
    //   88: iload_0
    //   89: dup
    //   90: iload_1
    //   91: iadd
    //   92: invokevirtual substring : (II)Ljava/lang/String;
    //   95: iconst_0
    //   96: goto -> 143
    //   99: aload #5
    //   101: swap
    //   102: iload_3
    //   103: iinc #3, 1
    //   106: swap
    //   107: aastore
    //   108: iload_0
    //   109: iload_1
    //   110: iadd
    //   111: dup
    //   112: istore_0
    //   113: iload #4
    //   115: if_icmpge -> 127
    //   118: aload_2
    //   119: iload_0
    //   120: invokevirtual charAt : (I)C
    //   123: istore_1
    //   124: goto -> 82
    //   127: aload #5
    //   129: putstatic burp/Zos.a : [Ljava/lang/String;
    //   132: bipush #28
    //   134: anewarray java/lang/String
    //   137: putstatic burp/Zos.b : [Ljava/lang/String;
    //   140: goto -> 300
    //   143: dup_x2
    //   144: pop
    //   145: invokevirtual toCharArray : ()[C
    //   148: dup_x1
    //   149: arraylength
    //   150: dup_x2
    //   151: pop
    //   152: iconst_0
    //   153: istore #6
    //   155: dup2_x1
    //   156: pop2
    //   157: dup_x2
    //   158: iconst_1
    //   159: if_icmpgt -> 260
    //   162: dup2
    //   163: swap
    //   164: iload #6
    //   166: dup2_x1
    //   167: caload
    //   168: swap
    //   169: iload #6
    //   171: bipush #7
    //   173: irem
    //   174: tableswitch default -> 242, 0 -> 212, 1 -> 217, 2 -> 222, 3 -> 227, 4 -> 232, 5 -> 237
    //   212: bipush #57
    //   214: goto -> 244
    //   217: bipush #122
    //   219: goto -> 244
    //   222: bipush #94
    //   224: goto -> 244
    //   227: bipush #15
    //   229: goto -> 244
    //   232: bipush #67
    //   234: goto -> 244
    //   237: bipush #63
    //   239: goto -> 244
    //   242: bipush #37
    //   244: ixor
    //   245: ixor
    //   246: i2c
    //   247: castore
    //   248: iinc #6, 1
    //   251: dup
    //   252: ifne -> 260
    //   255: dup2
    //   256: dup_x1
    //   257: goto -> 166
    //   260: dup2_x1
    //   261: pop2
    //   262: dup_x2
    //   263: iload #6
    //   265: if_icmpgt -> 162
    //   268: pop
    //   269: new java/lang/String
    //   272: dup_x1
    //   273: swap
    //   274: invokespecial <init> : ([C)V
    //   277: invokevirtual intern : ()Ljava/lang/String;
    //   280: swap
    //   281: pop
    //   282: swap
    //   283: tableswitch default -> 40, 0 -> 99
    //   300: new java/math/BigInteger
    //   303: dup
    //   304: sipush #-15113
    //   307: sipush #-25913
    //   310: invokestatic a : (II)Ljava/lang/String;
    //   313: invokespecial <init> : (Ljava/lang/String;)V
    //   316: putstatic burp/Zos.ZB : Ljava/lang/Object;
    //   319: sipush #-15112
    //   322: sipush #-32476
    //   325: invokestatic a : (II)Ljava/lang/String;
    //   328: putstatic burp/Zos.Za : Ljava/lang/String;
    //   331: return
  }
  
  private static Throwable a(Throwable paramThrowable) {
    return paramThrowable;
  }
  
  private static String a(int paramInt1, int paramInt2) {
    int i = (paramInt1 ^ 0xFFFFC4F3) & 0xFFFF;
    if (b[i] == null) {
      char[] arrayOfChar = a[i].toCharArray();
      switch (arrayOfChar[0] & 0xFF) {
        case 0:
        
        case 1:
        
        case 2:
        
        case 3:
        
        case 4:
        
        case 5:
        
        case 6:
        
        case 7:
        
        case 8:
        
        case 9:
        
        case 10:
        
        case 11:
        
        case 12:
        
        case 13:
        
        case 14:
        
        case 15:
        
        case 16:
        
        case 17:
        
        case 18:
        
        case 19:
        
        case 20:
        
        case 21:
        
        case 22:
        
        case 23:
        
        case 24:
        
        case 25:
        
        case 26:
        
        case 27:
        
        case 28:
        
        case 29:
        
        case 30:
        
        case 31:
        
        case 32:
        
        case 33:
        
        case 34:
        
        case 35:
        
        case 36:
        
        case 37:
        
        case 38:
        
        case 39:
        
        case 40:
        
        case 41:
        
        case 42:
        
        case 43:
        
        case 44:
        
        case 45:
        
        case 46:
        
        case 47:
        
        case 48:
        
        case 49:
        
        case 50:
        
        case 51:
        
        case 52:
        
        case 53:
        
        case 54:
        
        case 55:
        
        case 56:
        
        case 57:
        
        case 58:
        
        case 59:
        
        case 60:
        
        case 61:
        
        case 62:
        
        case 63:
        
        case 64:
        
        case 65:
        
        case 66:
        
        case 67:
        
        case 68:
        
        case 69:
        
        case 70:
        
        case 71:
        
        case 72:
        
        case 73:
        
        case 74:
        
        case 75:
        
        case 76:
        
        case 77:
        
        case 78:
        
        case 79:
        
        case 80:
        
        case 81:
        
        case 82:
        
        case 83:
        
        case 84:
        
        case 85:
        
        case 86:
        
        case 87:
        
        case 88:
        
        case 89:
        
        case 90:
        
        case 91:
        
        case 92:
        
        case 93:
        
        case 94:
        
        case 95:
        
        case 96:
        
        case 97:
        
        case 98:
        
        case 99:
        
        case 100:
        
        case 101:
        
        case 102:
        
        case 103:
        
        case 104:
        
        case 105:
        
        case 106:
        
        case 107:
        
        case 108:
        
        case 109:
        
        case 110:
        
        case 111:
        
        case 112:
        
        case 113:
        
        case 114:
        
        case 115:
        
        case 116:
        
        case 117:
        
        case 118:
        
        case 119:
        
        case 120:
        
        case 121:
        
        case 122:
        
        case 123:
        
        case 124:
        
        case 125:
        
        case 126:
        
        case 127:
        
        case 128:
        
        case 129:
        
        case 130:
        
        case 131:
        
        case 132:
        
        case 133:
        
        case 134:
        
        case 135:
        
        case 136:
        
        case 137:
        
        case 138:
        
        case 139:
        
        case 140:
        
        case 141:
        
        case 142:
        
        case 143:
        
        case 144:
        
        case 145:
        
        case 146:
        
        case 147:
        
        case 148:
        
        case 149:
        
        case 150:
        
        case 151:
        
        case 152:
        
        case 153:
        
        case 154:
        
        case 155:
        
        case 156:
        
        case 157:
        
        case 158:
        
        case 159:
        
        case 160:
        
        case 161:
        
        case 162:
        
        case 163:
        
        case 164:
        
        case 165:
        
        case 166:
        
        case 167:
        
        case 168:
        
        case 169:
        
        case 170:
        
        case 171:
        
        case 172:
        
        case 173:
        
        case 174:
        
        case 175:
        
        case 176:
        
        case 177:
        
        case 178:
        
        case 179:
        
        case 180:
        
        case 181:
        
        case 182:
        
        case 183:
        
        case 184:
        
        case 185:
        
        case 186:
        
        case 187:
        
        case 188:
        
        case 189:
        
        case 190:
        
        case 191:
        
        case 192:
        
        case 193:
        
        case 194:
        
        case 195:
        
        case 196:
        
        case 197:
        
        case 198:
        
        case 199:
        
        case 200:
        
        case 201:
        
        case 202:
        
        case 203:
        
        case 204:
        
        case 205:
        
        case 206:
        
        case 207:
        
        case 208:
        
        case 209:
        
        case 210:
        
        case 211:
        
        case 212:
        
        case 213:
        
        case 214:
        
        case 215:
        
        case 216:
        
        case 217:
        
        case 218:
        
        case 219:
        
        case 220:
        
        case 221:
        
        case 222:
        
        case 223:
        
        case 224:
        
        case 225:
        
        case 226:
        
        case 227:
        
        case 228:
        
        case 229:
        
        case 230:
        
        case 231:
        
        case 232:
        
        case 233:
        
        case 234:
        
        case 235:
        
        case 236:
        
        case 237:
        
        case 238:
        
        case 239:
        
        case 240:
        
        case 241:
        
        case 242:
        
        case 243:
        
        case 244:
        
        case 245:
        
        case 246:
        
        case 247:
        
        case 248:
        
        case 249:
        
        case 250:
        
        case 251:
        
        case 252:
        
        case 253:
        
        case 254:
        
        default:
          break;
      } 
      char c = '';
      int j = (paramInt2 & 0xFF) - c;
      if (j < 0)
        j += 256; 
      int k = ((paramInt2 & 0xFFFF) >>> 8) - c;
      if (k < 0)
        k += 256; 
      for (byte b = 0; b < arrayOfChar.length; b++) {
        int m = b % 2;
        if (m == 0) {
          arrayOfChar[b] = (char)(arrayOfChar[b] ^ j);
          j = ((j >>> 3 | j << 5) ^ arrayOfChar[b]) & 0xFF;
        } else {
          arrayOfChar[b] = (char)(arrayOfChar[b] ^ k);
          k = ((k >>> 3 | k << 5) ^ arrayOfChar[b]) & 0xFF;
        } 
      } 
      b[i] = (new String(arrayOfChar)).intern();
    } 
    return b[i];
  }
}


/* Location:              C:\Program Files\BurpSuitePro\burpsuite_pro.jar!\burp\Zos.class
 * Java compiler version: 21 (65.0)
 * JD-Core Version:       1.1.3
 */