package burp;

import java.math.BigInteger;

class Zr0 extends ClassLoader {
  static Object ZX;
  
  static String ZH;
  
  private static final String[] a;
  
  private static final String[] b;
  
  static boolean ZN(Object[] paramArrayOfObject, Object paramObject) throws Throwable {
    // Byte code:
    //   0: invokestatic ZN : ()Z
    //   3: istore_2
    //   4: getstatic burp/Ztuj.Ze : Ljava/lang/Object;
    //   7: checkcast java/math/BigInteger
    //   10: getstatic burp/Zgs6.Za : Ljava/lang/Object;
    //   13: checkcast java/math/BigInteger
    //   16: invokevirtual add : (Ljava/math/BigInteger;)Ljava/math/BigInteger;
    //   19: putstatic burp/Zzx8.Zi : Ljava/lang/Object;
    //   22: new java/lang/StringBuilder
    //   25: dup
    //   26: invokespecial <init> : ()V
    //   29: astore_3
    //   30: iconst_0
    //   31: istore #4
    //   33: iload #4
    //   35: bipush #32
    //   37: if_icmpge -> 1371
    //   40: iload #4
    //   42: tableswitch default -> 1364, 0 -> 184, 1 -> 221, 2 -> 258, 3 -> 295, 4 -> 332, 5 -> 369, 6 -> 406, 7 -> 443, 8 -> 480, 9 -> 517, 10 -> 554, 11 -> 591, 12 -> 628, 13 -> 665, 14 -> 702, 15 -> 739, 16 -> 776, 17 -> 813, 18 -> 850, 19 -> 887, 20 -> 924, 21 -> 961, 22 -> 998, 23 -> 1035, 24 -> 1072, 25 -> 1109, 26 -> 1146, 27 -> 1183, 28 -> 1220, 29 -> 1257, 30 -> 1294, 31 -> 1331
    //   184: aload_3
    //   185: getstatic burp/Zetv.ZE : Ljava/lang/String;
    //   188: getstatic burp/Zkca.ZQ : Ljava/lang/Object;
    //   191: checkcast java/math/BigInteger
    //   194: invokevirtual intValue : ()I
    //   197: bipush #32
    //   199: irem
    //   200: invokestatic abs : (I)I
    //   203: invokevirtual charAt : (I)C
    //   206: invokevirtual append : (C)Ljava/lang/StringBuilder;
    //   209: pop
    //   210: iload_2
    //   211: ifne -> 1364
    //   214: goto -> 221
    //   217: invokestatic a : (Ljava/lang/Throwable;)Ljava/lang/Throwable;
    //   220: athrow
    //   221: aload_3
    //   222: getstatic burp/Zr9b.ZC : Ljava/lang/String;
    //   225: getstatic burp/Zmli.Zh : Ljava/lang/Object;
    //   228: checkcast java/math/BigInteger
    //   231: invokevirtual intValue : ()I
    //   234: bipush #32
    //   236: irem
    //   237: invokestatic abs : (I)I
    //   240: invokevirtual charAt : (I)C
    //   243: invokevirtual append : (C)Ljava/lang/StringBuilder;
    //   246: pop
    //   247: iload_2
    //   248: ifne -> 1364
    //   251: goto -> 258
    //   254: invokestatic a : (Ljava/lang/Throwable;)Ljava/lang/Throwable;
    //   257: athrow
    //   258: aload_3
    //   259: getstatic burp/Zzip.Za : Ljava/lang/String;
    //   262: getstatic burp/Zrdy.Zt : Ljava/lang/Object;
    //   265: checkcast java/math/BigInteger
    //   268: invokevirtual intValue : ()I
    //   271: bipush #32
    //   273: irem
    //   274: invokestatic abs : (I)I
    //   277: invokevirtual charAt : (I)C
    //   280: invokevirtual append : (C)Ljava/lang/StringBuilder;
    //   283: pop
    //   284: iload_2
    //   285: ifne -> 1364
    //   288: goto -> 295
    //   291: invokestatic a : (Ljava/lang/Throwable;)Ljava/lang/Throwable;
    //   294: athrow
    //   295: aload_3
    //   296: getstatic burp/Zllw.Zg : Ljava/lang/String;
    //   299: getstatic burp/Zrt9.Zy : Ljava/lang/Object;
    //   302: checkcast java/math/BigInteger
    //   305: invokevirtual intValue : ()I
    //   308: bipush #32
    //   310: irem
    //   311: invokestatic abs : (I)I
    //   314: invokevirtual charAt : (I)C
    //   317: invokevirtual append : (C)Ljava/lang/StringBuilder;
    //   320: pop
    //   321: iload_2
    //   322: ifne -> 1364
    //   325: goto -> 332
    //   328: invokestatic a : (Ljava/lang/Throwable;)Ljava/lang/Throwable;
    //   331: athrow
    //   332: aload_3
    //   333: getstatic burp/Zlr2.ZV : Ljava/lang/String;
    //   336: getstatic burp/Zlpu.ZE : Ljava/lang/Object;
    //   339: checkcast java/math/BigInteger
    //   342: invokevirtual intValue : ()I
    //   345: bipush #32
    //   347: irem
    //   348: invokestatic abs : (I)I
    //   351: invokevirtual charAt : (I)C
    //   354: invokevirtual append : (C)Ljava/lang/StringBuilder;
    //   357: pop
    //   358: iload_2
    //   359: ifne -> 1364
    //   362: goto -> 369
    //   365: invokestatic a : (Ljava/lang/Throwable;)Ljava/lang/Throwable;
    //   368: athrow
    //   369: aload_3
    //   370: getstatic burp/Zlo5.ZJ : Ljava/lang/String;
    //   373: getstatic burp/Zbwj.ZW : Ljava/lang/Object;
    //   376: checkcast java/math/BigInteger
    //   379: invokevirtual intValue : ()I
    //   382: bipush #32
    //   384: irem
    //   385: invokestatic abs : (I)I
    //   388: invokevirtual charAt : (I)C
    //   391: invokevirtual append : (C)Ljava/lang/StringBuilder;
    //   394: pop
    //   395: iload_2
    //   396: ifne -> 1364
    //   399: goto -> 406
    //   402: invokestatic a : (Ljava/lang/Throwable;)Ljava/lang/Throwable;
    //   405: athrow
    //   406: aload_3
    //   407: getstatic burp/Ztcv.Zl : Ljava/lang/String;
    //   410: getstatic burp/Zxn9.ZN : Ljava/lang/Object;
    //   413: checkcast java/math/BigInteger
    //   416: invokevirtual intValue : ()I
    //   419: bipush #32
    //   421: irem
    //   422: invokestatic abs : (I)I
    //   425: invokevirtual charAt : (I)C
    //   428: invokevirtual append : (C)Ljava/lang/StringBuilder;
    //   431: pop
    //   432: iload_2
    //   433: ifne -> 1364
    //   436: goto -> 443
    //   439: invokestatic a : (Ljava/lang/Throwable;)Ljava/lang/Throwable;
    //   442: athrow
    //   443: aload_3
    //   444: getstatic burp/Zgmo.Zr : Ljava/lang/String;
    //   447: getstatic burp/Zxzd.ZD : Ljava/lang/Object;
    //   450: checkcast java/math/BigInteger
    //   453: invokevirtual intValue : ()I
    //   456: bipush #32
    //   458: irem
    //   459: invokestatic abs : (I)I
    //   462: invokevirtual charAt : (I)C
    //   465: invokevirtual append : (C)Ljava/lang/StringBuilder;
    //   468: pop
    //   469: iload_2
    //   470: ifne -> 1364
    //   473: goto -> 480
    //   476: invokestatic a : (Ljava/lang/Throwable;)Ljava/lang/Throwable;
    //   479: athrow
    //   480: aload_3
    //   481: getstatic burp/Zl3n.Zy : Ljava/lang/String;
    //   484: getstatic burp/Zmlu.Zi : Ljava/lang/Object;
    //   487: checkcast java/math/BigInteger
    //   490: invokevirtual intValue : ()I
    //   493: bipush #32
    //   495: irem
    //   496: invokestatic abs : (I)I
    //   499: invokevirtual charAt : (I)C
    //   502: invokevirtual append : (C)Ljava/lang/StringBuilder;
    //   505: pop
    //   506: iload_2
    //   507: ifne -> 1364
    //   510: goto -> 517
    //   513: invokestatic a : (Ljava/lang/Throwable;)Ljava/lang/Throwable;
    //   516: athrow
    //   517: aload_3
    //   518: getstatic burp/Zg2u.Zy : Ljava/lang/String;
    //   521: getstatic burp/Zl6z.Zt : Ljava/lang/Object;
    //   524: checkcast java/math/BigInteger
    //   527: invokevirtual intValue : ()I
    //   530: bipush #32
    //   532: irem
    //   533: invokestatic abs : (I)I
    //   536: invokevirtual charAt : (I)C
    //   539: invokevirtual append : (C)Ljava/lang/StringBuilder;
    //   542: pop
    //   543: iload_2
    //   544: ifne -> 1364
    //   547: goto -> 554
    //   550: invokestatic a : (Ljava/lang/Throwable;)Ljava/lang/Throwable;
    //   553: athrow
    //   554: aload_3
    //   555: getstatic burp/Zg1k.Ze : Ljava/lang/String;
    //   558: getstatic burp/Zmlr.Zh : Ljava/lang/Object;
    //   561: checkcast java/math/BigInteger
    //   564: invokevirtual intValue : ()I
    //   567: bipush #32
    //   569: irem
    //   570: invokestatic abs : (I)I
    //   573: invokevirtual charAt : (I)C
    //   576: invokevirtual append : (C)Ljava/lang/StringBuilder;
    //   579: pop
    //   580: iload_2
    //   581: ifne -> 1364
    //   584: goto -> 591
    //   587: invokestatic a : (Ljava/lang/Throwable;)Ljava/lang/Throwable;
    //   590: athrow
    //   591: aload_3
    //   592: getstatic burp/Zs33.ZX : Ljava/lang/String;
    //   595: getstatic burp/Zxo4.ZV : Ljava/lang/Object;
    //   598: checkcast java/math/BigInteger
    //   601: invokevirtual intValue : ()I
    //   604: bipush #32
    //   606: irem
    //   607: invokestatic abs : (I)I
    //   610: invokevirtual charAt : (I)C
    //   613: invokevirtual append : (C)Ljava/lang/StringBuilder;
    //   616: pop
    //   617: iload_2
    //   618: ifne -> 1364
    //   621: goto -> 628
    //   624: invokestatic a : (Ljava/lang/Throwable;)Ljava/lang/Throwable;
    //   627: athrow
    //   628: aload_3
    //   629: getstatic burp/Zz5h.Zk : Ljava/lang/String;
    //   632: getstatic burp/Ztod.ZP : Ljava/lang/Object;
    //   635: checkcast java/math/BigInteger
    //   638: invokevirtual intValue : ()I
    //   641: bipush #32
    //   643: irem
    //   644: invokestatic abs : (I)I
    //   647: invokevirtual charAt : (I)C
    //   650: invokevirtual append : (C)Ljava/lang/StringBuilder;
    //   653: pop
    //   654: iload_2
    //   655: ifne -> 1364
    //   658: goto -> 665
    //   661: invokestatic a : (Ljava/lang/Throwable;)Ljava/lang/Throwable;
    //   664: athrow
    //   665: aload_3
    //   666: getstatic burp/Ze64.ZM : Ljava/lang/String;
    //   669: getstatic burp/Zlpl.Ze : Ljava/lang/Object;
    //   672: checkcast java/math/BigInteger
    //   675: invokevirtual intValue : ()I
    //   678: bipush #32
    //   680: irem
    //   681: invokestatic abs : (I)I
    //   684: invokevirtual charAt : (I)C
    //   687: invokevirtual append : (C)Ljava/lang/StringBuilder;
    //   690: pop
    //   691: iload_2
    //   692: ifne -> 1364
    //   695: goto -> 702
    //   698: invokestatic a : (Ljava/lang/Throwable;)Ljava/lang/Throwable;
    //   701: athrow
    //   702: aload_3
    //   703: getstatic burp/Zrjw.Zz : Ljava/lang/String;
    //   706: getstatic burp/Zls0.ZZ : Ljava/lang/Object;
    //   709: checkcast java/math/BigInteger
    //   712: invokevirtual intValue : ()I
    //   715: bipush #32
    //   717: irem
    //   718: invokestatic abs : (I)I
    //   721: invokevirtual charAt : (I)C
    //   724: invokevirtual append : (C)Ljava/lang/StringBuilder;
    //   727: pop
    //   728: iload_2
    //   729: ifne -> 1364
    //   732: goto -> 739
    //   735: invokestatic a : (Ljava/lang/Throwable;)Ljava/lang/Throwable;
    //   738: athrow
    //   739: aload_3
    //   740: getstatic burp/Zg1k.Ze : Ljava/lang/String;
    //   743: getstatic burp/Zmiy.Zi : Ljava/lang/Object;
    //   746: checkcast java/math/BigInteger
    //   749: invokevirtual intValue : ()I
    //   752: bipush #32
    //   754: irem
    //   755: invokestatic abs : (I)I
    //   758: invokevirtual charAt : (I)C
    //   761: invokevirtual append : (C)Ljava/lang/StringBuilder;
    //   764: pop
    //   765: iload_2
    //   766: ifne -> 1364
    //   769: goto -> 776
    //   772: invokestatic a : (Ljava/lang/Throwable;)Ljava/lang/Throwable;
    //   775: athrow
    //   776: aload_3
    //   777: getstatic burp/Zmcq.ZY : Ljava/lang/String;
    //   780: getstatic burp/Zl3l.Zv : Ljava/lang/Object;
    //   783: checkcast java/math/BigInteger
    //   786: invokevirtual intValue : ()I
    //   789: bipush #32
    //   791: irem
    //   792: invokestatic abs : (I)I
    //   795: invokevirtual charAt : (I)C
    //   798: invokevirtual append : (C)Ljava/lang/StringBuilder;
    //   801: pop
    //   802: iload_2
    //   803: ifne -> 1364
    //   806: goto -> 813
    //   809: invokestatic a : (Ljava/lang/Throwable;)Ljava/lang/Throwable;
    //   812: athrow
    //   813: aload_3
    //   814: getstatic burp/Zsji.Zr : Ljava/lang/String;
    //   817: getstatic burp/Ztdx.ZX : Ljava/lang/Object;
    //   820: checkcast java/math/BigInteger
    //   823: invokevirtual intValue : ()I
    //   826: bipush #32
    //   828: irem
    //   829: invokestatic abs : (I)I
    //   832: invokevirtual charAt : (I)C
    //   835: invokevirtual append : (C)Ljava/lang/StringBuilder;
    //   838: pop
    //   839: iload_2
    //   840: ifne -> 1364
    //   843: goto -> 850
    //   846: invokestatic a : (Ljava/lang/Throwable;)Ljava/lang/Throwable;
    //   849: athrow
    //   850: aload_3
    //   851: getstatic burp/Zz9v.Zv : Ljava/lang/String;
    //   854: getstatic burp/Zxo4.ZV : Ljava/lang/Object;
    //   857: checkcast java/math/BigInteger
    //   860: invokevirtual intValue : ()I
    //   863: bipush #32
    //   865: irem
    //   866: invokestatic abs : (I)I
    //   869: invokevirtual charAt : (I)C
    //   872: invokevirtual append : (C)Ljava/lang/StringBuilder;
    //   875: pop
    //   876: iload_2
    //   877: ifne -> 1364
    //   880: goto -> 887
    //   883: invokestatic a : (Ljava/lang/Throwable;)Ljava/lang/Throwable;
    //   886: athrow
    //   887: aload_3
    //   888: getstatic burp/Zke7.Zl : Ljava/lang/String;
    //   891: getstatic burp/Zblv.Zf : Ljava/lang/Object;
    //   894: checkcast java/math/BigInteger
    //   897: invokevirtual intValue : ()I
    //   900: bipush #32
    //   902: irem
    //   903: invokestatic abs : (I)I
    //   906: invokevirtual charAt : (I)C
    //   909: invokevirtual append : (C)Ljava/lang/StringBuilder;
    //   912: pop
    //   913: iload_2
    //   914: ifne -> 1364
    //   917: goto -> 924
    //   920: invokestatic a : (Ljava/lang/Throwable;)Ljava/lang/Throwable;
    //   923: athrow
    //   924: aload_3
    //   925: getstatic burp/Ztdx.Zl : Ljava/lang/String;
    //   928: getstatic burp/Zz58.ZD : Ljava/lang/Object;
    //   931: checkcast java/math/BigInteger
    //   934: invokevirtual intValue : ()I
    //   937: bipush #32
    //   939: irem
    //   940: invokestatic abs : (I)I
    //   943: invokevirtual charAt : (I)C
    //   946: invokevirtual append : (C)Ljava/lang/StringBuilder;
    //   949: pop
    //   950: iload_2
    //   951: ifne -> 1364
    //   954: goto -> 961
    //   957: invokestatic a : (Ljava/lang/Throwable;)Ljava/lang/Throwable;
    //   960: athrow
    //   961: aload_3
    //   962: getstatic burp/Zty4.Zu : Ljava/lang/String;
    //   965: getstatic burp/Zkul.Zb : Ljava/lang/Object;
    //   968: checkcast java/math/BigInteger
    //   971: invokevirtual intValue : ()I
    //   974: bipush #32
    //   976: irem
    //   977: invokestatic abs : (I)I
    //   980: invokevirtual charAt : (I)C
    //   983: invokevirtual append : (C)Ljava/lang/StringBuilder;
    //   986: pop
    //   987: iload_2
    //   988: ifne -> 1364
    //   991: goto -> 998
    //   994: invokestatic a : (Ljava/lang/Throwable;)Ljava/lang/Throwable;
    //   997: athrow
    //   998: aload_3
    //   999: getstatic burp/Zre1.ZA : Ljava/lang/String;
    //   1002: getstatic burp/Zszz.ZG : Ljava/lang/Object;
    //   1005: checkcast java/math/BigInteger
    //   1008: invokevirtual intValue : ()I
    //   1011: bipush #32
    //   1013: irem
    //   1014: invokestatic abs : (I)I
    //   1017: invokevirtual charAt : (I)C
    //   1020: invokevirtual append : (C)Ljava/lang/StringBuilder;
    //   1023: pop
    //   1024: iload_2
    //   1025: ifne -> 1364
    //   1028: goto -> 1035
    //   1031: invokestatic a : (Ljava/lang/Throwable;)Ljava/lang/Throwable;
    //   1034: athrow
    //   1035: aload_3
    //   1036: getstatic burp/Zrfl.Zy : Ljava/lang/String;
    //   1039: getstatic burp/Zep1.ZW : Ljava/lang/Object;
    //   1042: checkcast java/math/BigInteger
    //   1045: invokevirtual intValue : ()I
    //   1048: bipush #32
    //   1050: irem
    //   1051: invokestatic abs : (I)I
    //   1054: invokevirtual charAt : (I)C
    //   1057: invokevirtual append : (C)Ljava/lang/StringBuilder;
    //   1060: pop
    //   1061: iload_2
    //   1062: ifne -> 1364
    //   1065: goto -> 1072
    //   1068: invokestatic a : (Ljava/lang/Throwable;)Ljava/lang/Throwable;
    //   1071: athrow
    //   1072: aload_3
    //   1073: getstatic burp/Zrd4.Zg : Ljava/lang/String;
    //   1076: getstatic burp/Ze54.Zx : Ljava/lang/Object;
    //   1079: checkcast java/math/BigInteger
    //   1082: invokevirtual intValue : ()I
    //   1085: bipush #32
    //   1087: irem
    //   1088: invokestatic abs : (I)I
    //   1091: invokevirtual charAt : (I)C
    //   1094: invokevirtual append : (C)Ljava/lang/StringBuilder;
    //   1097: pop
    //   1098: iload_2
    //   1099: ifne -> 1364
    //   1102: goto -> 1109
    //   1105: invokestatic a : (Ljava/lang/Throwable;)Ljava/lang/Throwable;
    //   1108: athrow
    //   1109: aload_3
    //   1110: getstatic burp/Zzr5.Zg : Ljava/lang/String;
    //   1113: getstatic burp/Zkvq.Zz : Ljava/lang/Object;
    //   1116: checkcast java/math/BigInteger
    //   1119: invokevirtual intValue : ()I
    //   1122: bipush #32
    //   1124: irem
    //   1125: invokestatic abs : (I)I
    //   1128: invokevirtual charAt : (I)C
    //   1131: invokevirtual append : (C)Ljava/lang/StringBuilder;
    //   1134: pop
    //   1135: iload_2
    //   1136: ifne -> 1364
    //   1139: goto -> 1146
    //   1142: invokestatic a : (Ljava/lang/Throwable;)Ljava/lang/Throwable;
    //   1145: athrow
    //   1146: aload_3
    //   1147: getstatic burp/Ztmy.ZF : Ljava/lang/String;
    //   1150: getstatic burp/Ztes.ZX : Ljava/lang/Object;
    //   1153: checkcast java/math/BigInteger
    //   1156: invokevirtual intValue : ()I
    //   1159: bipush #32
    //   1161: irem
    //   1162: invokestatic abs : (I)I
    //   1165: invokevirtual charAt : (I)C
    //   1168: invokevirtual append : (C)Ljava/lang/StringBuilder;
    //   1171: pop
    //   1172: iload_2
    //   1173: ifne -> 1364
    //   1176: goto -> 1183
    //   1179: invokestatic a : (Ljava/lang/Throwable;)Ljava/lang/Throwable;
    //   1182: athrow
    //   1183: aload_3
    //   1184: getstatic burp/Zltb.ZO : Ljava/lang/String;
    //   1187: getstatic burp/Zry9.Zw : Ljava/lang/Object;
    //   1190: checkcast java/math/BigInteger
    //   1193: invokevirtual intValue : ()I
    //   1196: bipush #32
    //   1198: irem
    //   1199: invokestatic abs : (I)I
    //   1202: invokevirtual charAt : (I)C
    //   1205: invokevirtual append : (C)Ljava/lang/StringBuilder;
    //   1208: pop
    //   1209: iload_2
    //   1210: ifne -> 1364
    //   1213: goto -> 1220
    //   1216: invokestatic a : (Ljava/lang/Throwable;)Ljava/lang/Throwable;
    //   1219: athrow
    //   1220: aload_3
    //   1221: getstatic burp/Zrcx.ZW : Ljava/lang/String;
    //   1224: getstatic burp/Zsqi.Zf : Ljava/lang/Object;
    //   1227: checkcast java/math/BigInteger
    //   1230: invokevirtual intValue : ()I
    //   1233: bipush #32
    //   1235: irem
    //   1236: invokestatic abs : (I)I
    //   1239: invokevirtual charAt : (I)C
    //   1242: invokevirtual append : (C)Ljava/lang/StringBuilder;
    //   1245: pop
    //   1246: iload_2
    //   1247: ifne -> 1364
    //   1250: goto -> 1257
    //   1253: invokestatic a : (Ljava/lang/Throwable;)Ljava/lang/Throwable;
    //   1256: athrow
    //   1257: aload_3
    //   1258: getstatic burp/Zblj.Za : Ljava/lang/String;
    //   1261: getstatic burp/Zbp.ZD : Ljava/lang/Object;
    //   1264: checkcast java/math/BigInteger
    //   1267: invokevirtual intValue : ()I
    //   1270: bipush #32
    //   1272: irem
    //   1273: invokestatic abs : (I)I
    //   1276: invokevirtual charAt : (I)C
    //   1279: invokevirtual append : (C)Ljava/lang/StringBuilder;
    //   1282: pop
    //   1283: iload_2
    //   1284: ifne -> 1364
    //   1287: goto -> 1294
    //   1290: invokestatic a : (Ljava/lang/Throwable;)Ljava/lang/Throwable;
    //   1293: athrow
    //   1294: aload_3
    //   1295: getstatic burp/Zm6h.Za : Ljava/lang/String;
    //   1298: getstatic burp/Zgia.Zx : Ljava/lang/Object;
    //   1301: checkcast java/math/BigInteger
    //   1304: invokevirtual intValue : ()I
    //   1307: bipush #32
    //   1309: irem
    //   1310: invokestatic abs : (I)I
    //   1313: invokevirtual charAt : (I)C
    //   1316: invokevirtual append : (C)Ljava/lang/StringBuilder;
    //   1319: pop
    //   1320: iload_2
    //   1321: ifne -> 1364
    //   1324: goto -> 1331
    //   1327: invokestatic a : (Ljava/lang/Throwable;)Ljava/lang/Throwable;
    //   1330: athrow
    //   1331: aload_3
    //   1332: getstatic burp/Zt5a.Zl : Ljava/lang/String;
    //   1335: getstatic burp/Zb3z.ZR : Ljava/lang/Object;
    //   1338: checkcast java/math/BigInteger
    //   1341: invokevirtual intValue : ()I
    //   1344: bipush #32
    //   1346: irem
    //   1347: invokestatic abs : (I)I
    //   1350: invokevirtual charAt : (I)C
    //   1353: invokevirtual append : (C)Ljava/lang/StringBuilder;
    //   1356: pop
    //   1357: goto -> 1364
    //   1360: invokestatic a : (Ljava/lang/Throwable;)Ljava/lang/Throwable;
    //   1363: athrow
    //   1364: iinc #4, 1
    //   1367: iload_2
    //   1368: ifne -> 33
    //   1371: aload_3
    //   1372: invokevirtual toString : ()Ljava/lang/String;
    //   1375: putstatic burp/Zzgh.Zn : Ljava/lang/String;
    //   1378: new java/lang/StringBuilder
    //   1381: dup
    //   1382: invokespecial <init> : ()V
    //   1385: astore #4
    //   1387: iconst_0
    //   1388: istore #5
    //   1390: iload #5
    //   1392: bipush #32
    //   1394: if_icmpge -> 2759
    //   1397: iload #5
    //   1399: tableswitch default -> 2752, 0 -> 1540, 1 -> 1578, 2 -> 1616, 3 -> 1654, 4 -> 1692, 5 -> 1730, 6 -> 1768, 7 -> 1806, 8 -> 1844, 9 -> 1882, 10 -> 1920, 11 -> 1958, 12 -> 1996, 13 -> 2034, 14 -> 2072, 15 -> 2110, 16 -> 2148, 17 -> 2186, 18 -> 2224, 19 -> 2262, 20 -> 2300, 21 -> 2338, 22 -> 2376, 23 -> 2414, 24 -> 2452, 25 -> 2490, 26 -> 2528, 27 -> 2566, 28 -> 2604, 29 -> 2642, 30 -> 2680, 31 -> 2718
    //   1540: aload #4
    //   1542: getstatic burp/Zemp.Zs : Ljava/lang/String;
    //   1545: getstatic burp/Zera.Zy : Ljava/lang/Object;
    //   1548: checkcast java/math/BigInteger
    //   1551: invokevirtual intValue : ()I
    //   1554: bipush #32
    //   1556: irem
    //   1557: invokestatic abs : (I)I
    //   1560: invokevirtual charAt : (I)C
    //   1563: invokevirtual append : (C)Ljava/lang/StringBuilder;
    //   1566: pop
    //   1567: iload_2
    //   1568: ifne -> 2752
    //   1571: goto -> 1578
    //   1574: invokestatic a : (Ljava/lang/Throwable;)Ljava/lang/Throwable;
    //   1577: athrow
    //   1578: aload #4
    //   1580: getstatic burp/Ze6t.ZR : Ljava/lang/String;
    //   1583: getstatic burp/Zzs9.ZO : Ljava/lang/Object;
    //   1586: checkcast java/math/BigInteger
    //   1589: invokevirtual intValue : ()I
    //   1592: bipush #32
    //   1594: irem
    //   1595: invokestatic abs : (I)I
    //   1598: invokevirtual charAt : (I)C
    //   1601: invokevirtual append : (C)Ljava/lang/StringBuilder;
    //   1604: pop
    //   1605: iload_2
    //   1606: ifne -> 2752
    //   1609: goto -> 1616
    //   1612: invokestatic a : (Ljava/lang/Throwable;)Ljava/lang/Throwable;
    //   1615: athrow
    //   1616: aload #4
    //   1618: getstatic burp/Ze08.Zh : Ljava/lang/String;
    //   1621: getstatic burp/Zlbd.ZU : Ljava/lang/Object;
    //   1624: checkcast java/math/BigInteger
    //   1627: invokevirtual intValue : ()I
    //   1630: bipush #32
    //   1632: irem
    //   1633: invokestatic abs : (I)I
    //   1636: invokevirtual charAt : (I)C
    //   1639: invokevirtual append : (C)Ljava/lang/StringBuilder;
    //   1642: pop
    //   1643: iload_2
    //   1644: ifne -> 2752
    //   1647: goto -> 1654
    //   1650: invokestatic a : (Ljava/lang/Throwable;)Ljava/lang/Throwable;
    //   1653: athrow
    //   1654: aload #4
    //   1656: getstatic burp/Zxo6.Z_ : Ljava/lang/String;
    //   1659: getstatic burp/Ze13.ZD : Ljava/lang/Object;
    //   1662: checkcast java/math/BigInteger
    //   1665: invokevirtual intValue : ()I
    //   1668: bipush #32
    //   1670: irem
    //   1671: invokestatic abs : (I)I
    //   1674: invokevirtual charAt : (I)C
    //   1677: invokevirtual append : (C)Ljava/lang/StringBuilder;
    //   1680: pop
    //   1681: iload_2
    //   1682: ifne -> 2752
    //   1685: goto -> 1692
    //   1688: invokestatic a : (Ljava/lang/Throwable;)Ljava/lang/Throwable;
    //   1691: athrow
    //   1692: aload #4
    //   1694: getstatic burp/Zzuh.ZX : Ljava/lang/String;
    //   1697: getstatic burp/Zql.Zt : Ljava/lang/Object;
    //   1700: checkcast java/math/BigInteger
    //   1703: invokevirtual intValue : ()I
    //   1706: bipush #32
    //   1708: irem
    //   1709: invokestatic abs : (I)I
    //   1712: invokevirtual charAt : (I)C
    //   1715: invokevirtual append : (C)Ljava/lang/StringBuilder;
    //   1718: pop
    //   1719: iload_2
    //   1720: ifne -> 2752
    //   1723: goto -> 1730
    //   1726: invokestatic a : (Ljava/lang/Throwable;)Ljava/lang/Throwable;
    //   1729: athrow
    //   1730: aload #4
    //   1732: getstatic burp/Zls0.ZI : Ljava/lang/String;
    //   1735: getstatic burp/Zl3j.ZY : Ljava/lang/Object;
    //   1738: checkcast java/math/BigInteger
    //   1741: invokevirtual intValue : ()I
    //   1744: bipush #32
    //   1746: irem
    //   1747: invokestatic abs : (I)I
    //   1750: invokevirtual charAt : (I)C
    //   1753: invokevirtual append : (C)Ljava/lang/StringBuilder;
    //   1756: pop
    //   1757: iload_2
    //   1758: ifne -> 2752
    //   1761: goto -> 1768
    //   1764: invokestatic a : (Ljava/lang/Throwable;)Ljava/lang/Throwable;
    //   1767: athrow
    //   1768: aload #4
    //   1770: getstatic burp/Zz9v.Zv : Ljava/lang/String;
    //   1773: getstatic burp/Zxx4.Zo : Ljava/lang/Object;
    //   1776: checkcast java/math/BigInteger
    //   1779: invokevirtual intValue : ()I
    //   1782: bipush #32
    //   1784: irem
    //   1785: invokestatic abs : (I)I
    //   1788: invokevirtual charAt : (I)C
    //   1791: invokevirtual append : (C)Ljava/lang/StringBuilder;
    //   1794: pop
    //   1795: iload_2
    //   1796: ifne -> 2752
    //   1799: goto -> 1806
    //   1802: invokestatic a : (Ljava/lang/Throwable;)Ljava/lang/Throwable;
    //   1805: athrow
    //   1806: aload #4
    //   1808: getstatic burp/Zsq6.Zm : Ljava/lang/String;
    //   1811: getstatic burp/Ztpa.Zv : Ljava/lang/Object;
    //   1814: checkcast java/math/BigInteger
    //   1817: invokevirtual intValue : ()I
    //   1820: bipush #32
    //   1822: irem
    //   1823: invokestatic abs : (I)I
    //   1826: invokevirtual charAt : (I)C
    //   1829: invokevirtual append : (C)Ljava/lang/StringBuilder;
    //   1832: pop
    //   1833: iload_2
    //   1834: ifne -> 2752
    //   1837: goto -> 1844
    //   1840: invokestatic a : (Ljava/lang/Throwable;)Ljava/lang/Throwable;
    //   1843: athrow
    //   1844: aload #4
    //   1846: getstatic burp/Zsq6.Zm : Ljava/lang/String;
    //   1849: getstatic burp/Zgdt.Zb : Ljava/lang/Object;
    //   1852: checkcast java/math/BigInteger
    //   1855: invokevirtual intValue : ()I
    //   1858: bipush #32
    //   1860: irem
    //   1861: invokestatic abs : (I)I
    //   1864: invokevirtual charAt : (I)C
    //   1867: invokevirtual append : (C)Ljava/lang/StringBuilder;
    //   1870: pop
    //   1871: iload_2
    //   1872: ifne -> 2752
    //   1875: goto -> 1882
    //   1878: invokestatic a : (Ljava/lang/Throwable;)Ljava/lang/Throwable;
    //   1881: athrow
    //   1882: aload #4
    //   1884: getstatic burp/Zex0.Zk : Ljava/lang/String;
    //   1887: getstatic burp/Zlsw.ZJ : Ljava/lang/Object;
    //   1890: checkcast java/math/BigInteger
    //   1893: invokevirtual intValue : ()I
    //   1896: bipush #32
    //   1898: irem
    //   1899: invokestatic abs : (I)I
    //   1902: invokevirtual charAt : (I)C
    //   1905: invokevirtual append : (C)Ljava/lang/StringBuilder;
    //   1908: pop
    //   1909: iload_2
    //   1910: ifne -> 2752
    //   1913: goto -> 1920
    //   1916: invokestatic a : (Ljava/lang/Throwable;)Ljava/lang/Throwable;
    //   1919: athrow
    //   1920: aload #4
    //   1922: getstatic burp/Zlpn.ZF : Ljava/lang/String;
    //   1925: getstatic burp/Zes_.ZJ : Ljava/lang/Object;
    //   1928: checkcast java/math/BigInteger
    //   1931: invokevirtual intValue : ()I
    //   1934: bipush #32
    //   1936: irem
    //   1937: invokestatic abs : (I)I
    //   1940: invokevirtual charAt : (I)C
    //   1943: invokevirtual append : (C)Ljava/lang/StringBuilder;
    //   1946: pop
    //   1947: iload_2
    //   1948: ifne -> 2752
    //   1951: goto -> 1958
    //   1954: invokestatic a : (Ljava/lang/Throwable;)Ljava/lang/Throwable;
    //   1957: athrow
    //   1958: aload #4
    //   1960: getstatic burp/Zg4w.ZC : Ljava/lang/String;
    //   1963: getstatic burp/Zmtf.ZH : Ljava/lang/Object;
    //   1966: checkcast java/math/BigInteger
    //   1969: invokevirtual intValue : ()I
    //   1972: bipush #32
    //   1974: irem
    //   1975: invokestatic abs : (I)I
    //   1978: invokevirtual charAt : (I)C
    //   1981: invokevirtual append : (C)Ljava/lang/StringBuilder;
    //   1984: pop
    //   1985: iload_2
    //   1986: ifne -> 2752
    //   1989: goto -> 1996
    //   1992: invokestatic a : (Ljava/lang/Throwable;)Ljava/lang/Throwable;
    //   1995: athrow
    //   1996: aload #4
    //   1998: getstatic burp/Zk9s.ZM : Ljava/lang/String;
    //   2001: getstatic burp/Zx4l.Zt : Ljava/lang/Object;
    //   2004: checkcast java/math/BigInteger
    //   2007: invokevirtual intValue : ()I
    //   2010: bipush #32
    //   2012: irem
    //   2013: invokestatic abs : (I)I
    //   2016: invokevirtual charAt : (I)C
    //   2019: invokevirtual append : (C)Ljava/lang/StringBuilder;
    //   2022: pop
    //   2023: iload_2
    //   2024: ifne -> 2752
    //   2027: goto -> 2034
    //   2030: invokestatic a : (Ljava/lang/Throwable;)Ljava/lang/Throwable;
    //   2033: athrow
    //   2034: aload #4
    //   2036: getstatic burp/Zg3m.Za : Ljava/lang/String;
    //   2039: getstatic burp/Ztid.ZL : Ljava/lang/Object;
    //   2042: checkcast java/math/BigInteger
    //   2045: invokevirtual intValue : ()I
    //   2048: bipush #32
    //   2050: irem
    //   2051: invokestatic abs : (I)I
    //   2054: invokevirtual charAt : (I)C
    //   2057: invokevirtual append : (C)Ljava/lang/StringBuilder;
    //   2060: pop
    //   2061: iload_2
    //   2062: ifne -> 2752
    //   2065: goto -> 2072
    //   2068: invokestatic a : (Ljava/lang/Throwable;)Ljava/lang/Throwable;
    //   2071: athrow
    //   2072: aload #4
    //   2074: getstatic burp/Zrpm.ZG : Ljava/lang/String;
    //   2077: getstatic burp/Ztg3.Zg : Ljava/lang/Object;
    //   2080: checkcast java/math/BigInteger
    //   2083: invokevirtual intValue : ()I
    //   2086: bipush #32
    //   2088: irem
    //   2089: invokestatic abs : (I)I
    //   2092: invokevirtual charAt : (I)C
    //   2095: invokevirtual append : (C)Ljava/lang/StringBuilder;
    //   2098: pop
    //   2099: iload_2
    //   2100: ifne -> 2752
    //   2103: goto -> 2110
    //   2106: invokestatic a : (Ljava/lang/Throwable;)Ljava/lang/Throwable;
    //   2109: athrow
    //   2110: aload #4
    //   2112: getstatic burp/Zzuh.ZX : Ljava/lang/String;
    //   2115: getstatic burp/Zs8y.ZG : Ljava/lang/Object;
    //   2118: checkcast java/math/BigInteger
    //   2121: invokevirtual intValue : ()I
    //   2124: bipush #32
    //   2126: irem
    //   2127: invokestatic abs : (I)I
    //   2130: invokevirtual charAt : (I)C
    //   2133: invokevirtual append : (C)Ljava/lang/StringBuilder;
    //   2136: pop
    //   2137: iload_2
    //   2138: ifne -> 2752
    //   2141: goto -> 2148
    //   2144: invokestatic a : (Ljava/lang/Throwable;)Ljava/lang/Throwable;
    //   2147: athrow
    //   2148: aload #4
    //   2150: getstatic burp/Zmuj.ZG : Ljava/lang/String;
    //   2153: getstatic burp/Zxti.ZJ : Ljava/lang/Object;
    //   2156: checkcast java/math/BigInteger
    //   2159: invokevirtual intValue : ()I
    //   2162: bipush #32
    //   2164: irem
    //   2165: invokestatic abs : (I)I
    //   2168: invokevirtual charAt : (I)C
    //   2171: invokevirtual append : (C)Ljava/lang/StringBuilder;
    //   2174: pop
    //   2175: iload_2
    //   2176: ifne -> 2752
    //   2179: goto -> 2186
    //   2182: invokestatic a : (Ljava/lang/Throwable;)Ljava/lang/Throwable;
    //   2185: athrow
    //   2186: aload #4
    //   2188: getstatic burp/Zzky.Zj : Ljava/lang/String;
    //   2191: getstatic burp/Zgdt.Zb : Ljava/lang/Object;
    //   2194: checkcast java/math/BigInteger
    //   2197: invokevirtual intValue : ()I
    //   2200: bipush #32
    //   2202: irem
    //   2203: invokestatic abs : (I)I
    //   2206: invokevirtual charAt : (I)C
    //   2209: invokevirtual append : (C)Ljava/lang/StringBuilder;
    //   2212: pop
    //   2213: iload_2
    //   2214: ifne -> 2752
    //   2217: goto -> 2224
    //   2220: invokestatic a : (Ljava/lang/Throwable;)Ljava/lang/Throwable;
    //   2223: athrow
    //   2224: aload #4
    //   2226: getstatic burp/Zg3v.Zt : Ljava/lang/String;
    //   2229: getstatic burp/Zl4v.ZT : Ljava/lang/Object;
    //   2232: checkcast java/math/BigInteger
    //   2235: invokevirtual intValue : ()I
    //   2238: bipush #32
    //   2240: irem
    //   2241: invokestatic abs : (I)I
    //   2244: invokevirtual charAt : (I)C
    //   2247: invokevirtual append : (C)Ljava/lang/StringBuilder;
    //   2250: pop
    //   2251: iload_2
    //   2252: ifne -> 2752
    //   2255: goto -> 2262
    //   2258: invokestatic a : (Ljava/lang/Throwable;)Ljava/lang/Throwable;
    //   2261: athrow
    //   2262: aload #4
    //   2264: getstatic burp/Zr3x.ZM : Ljava/lang/String;
    //   2267: getstatic burp/Zlav.Zp : Ljava/lang/Object;
    //   2270: checkcast java/math/BigInteger
    //   2273: invokevirtual intValue : ()I
    //   2276: bipush #32
    //   2278: irem
    //   2279: invokestatic abs : (I)I
    //   2282: invokevirtual charAt : (I)C
    //   2285: invokevirtual append : (C)Ljava/lang/StringBuilder;
    //   2288: pop
    //   2289: iload_2
    //   2290: ifne -> 2752
    //   2293: goto -> 2300
    //   2296: invokestatic a : (Ljava/lang/Throwable;)Ljava/lang/Throwable;
    //   2299: athrow
    //   2300: aload #4
    //   2302: getstatic burp/Zkor.Za : Ljava/lang/String;
    //   2305: getstatic burp/Ztkc.ZV : Ljava/lang/Object;
    //   2308: checkcast java/math/BigInteger
    //   2311: invokevirtual intValue : ()I
    //   2314: bipush #32
    //   2316: irem
    //   2317: invokestatic abs : (I)I
    //   2320: invokevirtual charAt : (I)C
    //   2323: invokevirtual append : (C)Ljava/lang/StringBuilder;
    //   2326: pop
    //   2327: iload_2
    //   2328: ifne -> 2752
    //   2331: goto -> 2338
    //   2334: invokestatic a : (Ljava/lang/Throwable;)Ljava/lang/Throwable;
    //   2337: athrow
    //   2338: aload #4
    //   2340: getstatic burp/Zgsy.Zv : Ljava/lang/String;
    //   2343: getstatic burp/Zxyu.Zp : Ljava/lang/Object;
    //   2346: checkcast java/math/BigInteger
    //   2349: invokevirtual intValue : ()I
    //   2352: bipush #32
    //   2354: irem
    //   2355: invokestatic abs : (I)I
    //   2358: invokevirtual charAt : (I)C
    //   2361: invokevirtual append : (C)Ljava/lang/StringBuilder;
    //   2364: pop
    //   2365: iload_2
    //   2366: ifne -> 2752
    //   2369: goto -> 2376
    //   2372: invokestatic a : (Ljava/lang/Throwable;)Ljava/lang/Throwable;
    //   2375: athrow
    //   2376: aload #4
    //   2378: getstatic burp/Zzi3.ZS : Ljava/lang/String;
    //   2381: getstatic burp/Zlpu.ZE : Ljava/lang/Object;
    //   2384: checkcast java/math/BigInteger
    //   2387: invokevirtual intValue : ()I
    //   2390: bipush #32
    //   2392: irem
    //   2393: invokestatic abs : (I)I
    //   2396: invokevirtual charAt : (I)C
    //   2399: invokevirtual append : (C)Ljava/lang/StringBuilder;
    //   2402: pop
    //   2403: iload_2
    //   2404: ifne -> 2752
    //   2407: goto -> 2414
    //   2410: invokestatic a : (Ljava/lang/Throwable;)Ljava/lang/Throwable;
    //   2413: athrow
    //   2414: aload #4
    //   2416: getstatic burp/Zrcu.Zb : Ljava/lang/String;
    //   2419: getstatic burp/Zefm.ZP : Ljava/lang/Object;
    //   2422: checkcast java/math/BigInteger
    //   2425: invokevirtual intValue : ()I
    //   2428: bipush #32
    //   2430: irem
    //   2431: invokestatic abs : (I)I
    //   2434: invokevirtual charAt : (I)C
    //   2437: invokevirtual append : (C)Ljava/lang/StringBuilder;
    //   2440: pop
    //   2441: iload_2
    //   2442: ifne -> 2752
    //   2445: goto -> 2452
    //   2448: invokestatic a : (Ljava/lang/Throwable;)Ljava/lang/Throwable;
    //   2451: athrow
    //   2452: aload #4
    //   2454: getstatic burp/Zl5b.Zi : Ljava/lang/String;
    //   2457: getstatic burp/Zrhu.Zs : Ljava/lang/Object;
    //   2460: checkcast java/math/BigInteger
    //   2463: invokevirtual intValue : ()I
    //   2466: bipush #32
    //   2468: irem
    //   2469: invokestatic abs : (I)I
    //   2472: invokevirtual charAt : (I)C
    //   2475: invokevirtual append : (C)Ljava/lang/StringBuilder;
    //   2478: pop
    //   2479: iload_2
    //   2480: ifne -> 2752
    //   2483: goto -> 2490
    //   2486: invokestatic a : (Ljava/lang/Throwable;)Ljava/lang/Throwable;
    //   2489: athrow
    //   2490: aload #4
    //   2492: getstatic burp/Zb29.Zf : Ljava/lang/String;
    //   2495: getstatic burp/Zg_6.ZU : Ljava/lang/Object;
    //   2498: checkcast java/math/BigInteger
    //   2501: invokevirtual intValue : ()I
    //   2504: bipush #32
    //   2506: irem
    //   2507: invokestatic abs : (I)I
    //   2510: invokevirtual charAt : (I)C
    //   2513: invokevirtual append : (C)Ljava/lang/StringBuilder;
    //   2516: pop
    //   2517: iload_2
    //   2518: ifne -> 2752
    //   2521: goto -> 2528
    //   2524: invokestatic a : (Ljava/lang/Throwable;)Ljava/lang/Throwable;
    //   2527: athrow
    //   2528: aload #4
    //   2530: getstatic burp/Zmlu.ZF : Ljava/lang/String;
    //   2533: getstatic burp/Zrdy.Zt : Ljava/lang/Object;
    //   2536: checkcast java/math/BigInteger
    //   2539: invokevirtual intValue : ()I
    //   2542: bipush #32
    //   2544: irem
    //   2545: invokestatic abs : (I)I
    //   2548: invokevirtual charAt : (I)C
    //   2551: invokevirtual append : (C)Ljava/lang/StringBuilder;
    //   2554: pop
    //   2555: iload_2
    //   2556: ifne -> 2752
    //   2559: goto -> 2566
    //   2562: invokestatic a : (Ljava/lang/Throwable;)Ljava/lang/Throwable;
    //   2565: athrow
    //   2566: aload #4
    //   2568: getstatic burp/Zr9b.ZC : Ljava/lang/String;
    //   2571: getstatic burp/Zelc.ZR : Ljava/lang/Object;
    //   2574: checkcast java/math/BigInteger
    //   2577: invokevirtual intValue : ()I
    //   2580: bipush #32
    //   2582: irem
    //   2583: invokestatic abs : (I)I
    //   2586: invokevirtual charAt : (I)C
    //   2589: invokevirtual append : (C)Ljava/lang/StringBuilder;
    //   2592: pop
    //   2593: iload_2
    //   2594: ifne -> 2752
    //   2597: goto -> 2604
    //   2600: invokestatic a : (Ljava/lang/Throwable;)Ljava/lang/Throwable;
    //   2603: athrow
    //   2604: aload #4
    //   2606: getstatic burp/Ztfr.Zo : Ljava/lang/String;
    //   2609: getstatic burp/Zr5k.Zj : Ljava/lang/Object;
    //   2612: checkcast java/math/BigInteger
    //   2615: invokevirtual intValue : ()I
    //   2618: bipush #32
    //   2620: irem
    //   2621: invokestatic abs : (I)I
    //   2624: invokevirtual charAt : (I)C
    //   2627: invokevirtual append : (C)Ljava/lang/StringBuilder;
    //   2630: pop
    //   2631: iload_2
    //   2632: ifne -> 2752
    //   2635: goto -> 2642
    //   2638: invokestatic a : (Ljava/lang/Throwable;)Ljava/lang/Throwable;
    //   2641: athrow
    //   2642: aload #4
    //   2644: getstatic burp/Zz9v.Zv : Ljava/lang/String;
    //   2647: getstatic burp/Zlav.Zp : Ljava/lang/Object;
    //   2650: checkcast java/math/BigInteger
    //   2653: invokevirtual intValue : ()I
    //   2656: bipush #32
    //   2658: irem
    //   2659: invokestatic abs : (I)I
    //   2662: invokevirtual charAt : (I)C
    //   2665: invokevirtual append : (C)Ljava/lang/StringBuilder;
    //   2668: pop
    //   2669: iload_2
    //   2670: ifne -> 2752
    //   2673: goto -> 2680
    //   2676: invokestatic a : (Ljava/lang/Throwable;)Ljava/lang/Throwable;
    //   2679: athrow
    //   2680: aload #4
    //   2682: getstatic burp/Zt4g.Zj : Ljava/lang/String;
    //   2685: getstatic burp/Zmh5.ZN : Ljava/lang/Object;
    //   2688: checkcast java/math/BigInteger
    //   2691: invokevirtual intValue : ()I
    //   2694: bipush #32
    //   2696: irem
    //   2697: invokestatic abs : (I)I
    //   2700: invokevirtual charAt : (I)C
    //   2703: invokevirtual append : (C)Ljava/lang/StringBuilder;
    //   2706: pop
    //   2707: iload_2
    //   2708: ifne -> 2752
    //   2711: goto -> 2718
    //   2714: invokestatic a : (Ljava/lang/Throwable;)Ljava/lang/Throwable;
    //   2717: athrow
    //   2718: aload #4
    //   2720: getstatic burp/Zly7.ZC : Ljava/lang/String;
    //   2723: getstatic burp/Zmtf.ZH : Ljava/lang/Object;
    //   2726: checkcast java/math/BigInteger
    //   2729: invokevirtual intValue : ()I
    //   2732: bipush #32
    //   2734: irem
    //   2735: invokestatic abs : (I)I
    //   2738: invokevirtual charAt : (I)C
    //   2741: invokevirtual append : (C)Ljava/lang/StringBuilder;
    //   2744: pop
    //   2745: goto -> 2752
    //   2748: invokestatic a : (Ljava/lang/Throwable;)Ljava/lang/Throwable;
    //   2751: athrow
    //   2752: iinc #5, 1
    //   2755: iload_2
    //   2756: ifne -> 1390
    //   2759: aload #4
    //   2761: invokevirtual toString : ()Ljava/lang/String;
    //   2764: putstatic burp/Zx4u.ZL : Ljava/lang/String;
    //   2767: sipush #-17235
    //   2770: sipush #-20320
    //   2773: invokestatic a : (II)Ljava/lang/String;
    //   2776: iconst_1
    //   2777: ldc burp/Zg0j
    //   2779: invokevirtual getClassLoader : ()Ljava/lang/ClassLoader;
    //   2782: invokestatic forName : (Ljava/lang/String;ZLjava/lang/ClassLoader;)Ljava/lang/Class;
    //   2785: invokevirtual getDeclaredFields : ()[Ljava/lang/reflect/Field;
    //   2788: astore #5
    //   2790: aload #5
    //   2792: arraylength
    //   2793: istore #6
    //   2795: iconst_0
    //   2796: istore #7
    //   2798: iload #7
    //   2800: iload #6
    //   2802: if_icmpge -> 2940
    //   2805: aload #5
    //   2807: iload #7
    //   2809: aaload
    //   2810: astore #8
    //   2812: aload #8
    //   2814: invokevirtual getModifiers : ()I
    //   2817: invokestatic isStatic : (I)Z
    //   2820: ifne -> 2830
    //   2823: goto -> 2933
    //   2826: invokestatic a : (Ljava/lang/Throwable;)Ljava/lang/Throwable;
    //   2829: athrow
    //   2830: aload #8
    //   2832: invokevirtual getType : ()Ljava/lang/Class;
    //   2835: astore #9
    //   2837: aload #9
    //   2839: ifnull -> 2920
    //   2842: aload #9
    //   2844: invokevirtual isPrimitive : ()Z
    //   2847: ifne -> 2920
    //   2850: goto -> 2857
    //   2853: invokestatic a : (Ljava/lang/Throwable;)Ljava/lang/Throwable;
    //   2856: athrow
    //   2857: aload #9
    //   2859: invokevirtual getPackage : ()Ljava/lang/Package;
    //   2862: ifnull -> 2920
    //   2865: goto -> 2872
    //   2868: invokestatic a : (Ljava/lang/Throwable;)Ljava/lang/Throwable;
    //   2871: athrow
    //   2872: aload #9
    //   2874: invokevirtual getPackage : ()Ljava/lang/Package;
    //   2877: invokevirtual getName : ()Ljava/lang/String;
    //   2880: ifnull -> 2920
    //   2883: goto -> 2890
    //   2886: invokestatic a : (Ljava/lang/Throwable;)Ljava/lang/Throwable;
    //   2889: athrow
    //   2890: aload #9
    //   2892: invokevirtual getPackage : ()Ljava/lang/Package;
    //   2895: invokevirtual getName : ()Ljava/lang/String;
    //   2898: sipush #-17243
    //   2901: sipush #-12811
    //   2904: invokestatic a : (II)Ljava/lang/String;
    //   2907: invokevirtual startsWith : (Ljava/lang/String;)Z
    //   2910: ifne -> 2920
    //   2913: goto -> 2920
    //   2916: invokestatic a : (Ljava/lang/Throwable;)Ljava/lang/Throwable;
    //   2919: athrow
    //   2920: aload #8
    //   2922: iconst_1
    //   2923: invokevirtual setAccessible : (Z)V
    //   2926: aload #8
    //   2928: aconst_null
    //   2929: invokevirtual get : (Ljava/lang/Object;)Ljava/lang/Object;
    //   2932: pop
    //   2933: iinc #7, 1
    //   2936: iload_2
    //   2937: ifne -> 2798
    //   2940: sipush #-17236
    //   2943: sipush #15388
    //   2946: invokestatic a : (II)Ljava/lang/String;
    //   2949: invokestatic forName : (Ljava/lang/String;)Ljava/lang/Class;
    //   2952: invokevirtual getDeclaredMethods : ()[Ljava/lang/reflect/Method;
    //   2955: astore #5
    //   2957: aload #5
    //   2959: arraylength
    //   2960: istore #6
    //   2962: iconst_0
    //   2963: istore #7
    //   2965: iload #7
    //   2967: iload #6
    //   2969: if_icmpge -> 3099
    //   2972: aload #5
    //   2974: iload #7
    //   2976: aaload
    //   2977: astore #8
    //   2979: aload #8
    //   2981: invokevirtual getParameterTypes : ()[Ljava/lang/Class;
    //   2984: pop
    //   2985: aload #8
    //   2987: invokevirtual getModifiers : ()I
    //   2990: invokestatic isStatic : (I)Z
    //   2993: ifeq -> 3085
    //   2996: aload #8
    //   2998: invokevirtual getParameterTypes : ()[Ljava/lang/Class;
    //   3001: arraylength
    //   3002: iconst_2
    //   3003: if_icmpne -> 3085
    //   3006: goto -> 3013
    //   3009: invokestatic a : (Ljava/lang/Throwable;)Ljava/lang/Throwable;
    //   3012: athrow
    //   3013: aload #8
    //   3015: invokevirtual getReturnType : ()Ljava/lang/Class;
    //   3018: getstatic java/lang/Boolean.TYPE : Ljava/lang/Class;
    //   3021: if_acmpne -> 3085
    //   3024: goto -> 3031
    //   3027: invokestatic a : (Ljava/lang/Throwable;)Ljava/lang/Throwable;
    //   3030: athrow
    //   3031: aload #8
    //   3033: iconst_1
    //   3034: invokevirtual setAccessible : (Z)V
    //   3037: aload #8
    //   3039: aconst_null
    //   3040: iconst_2
    //   3041: anewarray java/lang/Object
    //   3044: dup
    //   3045: iconst_0
    //   3046: aload_0
    //   3047: aastore
    //   3048: dup
    //   3049: iconst_1
    //   3050: aload_1
    //   3051: ifnonnull -> 3069
    //   3054: goto -> 3061
    //   3057: invokestatic a : (Ljava/lang/Throwable;)Ljava/lang/Throwable;
    //   3060: athrow
    //   3061: aload_1
    //   3062: goto -> 3076
    //   3065: invokestatic a : (Ljava/lang/Throwable;)Ljava/lang/Throwable;
    //   3068: athrow
    //   3069: aload_1
    //   3070: checkcast [B
    //   3073: invokevirtual clone : ()Ljava/lang/Object;
    //   3076: aastore
    //   3077: invokevirtual invoke : (Ljava/lang/Object;[Ljava/lang/Object;)Ljava/lang/Object;
    //   3080: pop
    //   3081: iload_2
    //   3082: ifne -> 3099
    //   3085: iinc #7, 1
    //   3088: iload_2
    //   3089: ifne -> 2965
    //   3092: goto -> 3099
    //   3095: invokestatic a : (Ljava/lang/Throwable;)Ljava/lang/Throwable;
    //   3098: athrow
    //   3099: sipush #-17245
    //   3102: sipush #4584
    //   3105: invokestatic a : (II)Ljava/lang/String;
    //   3108: iconst_1
    //   3109: ldc burp/Zrcy
    //   3111: invokevirtual getClassLoader : ()Ljava/lang/ClassLoader;
    //   3114: invokestatic forName : (Ljava/lang/String;ZLjava/lang/ClassLoader;)Ljava/lang/Class;
    //   3117: invokevirtual getDeclaredFields : ()[Ljava/lang/reflect/Field;
    //   3120: astore #5
    //   3122: aload #5
    //   3124: arraylength
    //   3125: istore #6
    //   3127: iconst_0
    //   3128: istore #7
    //   3130: iload #7
    //   3132: iload #6
    //   3134: if_icmpge -> 3272
    //   3137: aload #5
    //   3139: iload #7
    //   3141: aaload
    //   3142: astore #8
    //   3144: aload #8
    //   3146: invokevirtual getModifiers : ()I
    //   3149: invokestatic isStatic : (I)Z
    //   3152: ifne -> 3162
    //   3155: goto -> 3265
    //   3158: invokestatic a : (Ljava/lang/Throwable;)Ljava/lang/Throwable;
    //   3161: athrow
    //   3162: aload #8
    //   3164: invokevirtual getType : ()Ljava/lang/Class;
    //   3167: astore #9
    //   3169: aload #9
    //   3171: ifnull -> 3252
    //   3174: aload #9
    //   3176: invokevirtual isPrimitive : ()Z
    //   3179: ifne -> 3252
    //   3182: goto -> 3189
    //   3185: invokestatic a : (Ljava/lang/Throwable;)Ljava/lang/Throwable;
    //   3188: athrow
    //   3189: aload #9
    //   3191: invokevirtual getPackage : ()Ljava/lang/Package;
    //   3194: ifnull -> 3252
    //   3197: goto -> 3204
    //   3200: invokestatic a : (Ljava/lang/Throwable;)Ljava/lang/Throwable;
    //   3203: athrow
    //   3204: aload #9
    //   3206: invokevirtual getPackage : ()Ljava/lang/Package;
    //   3209: invokevirtual getName : ()Ljava/lang/String;
    //   3212: ifnull -> 3252
    //   3215: goto -> 3222
    //   3218: invokestatic a : (Ljava/lang/Throwable;)Ljava/lang/Throwable;
    //   3221: athrow
    //   3222: aload #9
    //   3224: invokevirtual getPackage : ()Ljava/lang/Package;
    //   3227: invokevirtual getName : ()Ljava/lang/String;
    //   3230: sipush #-17241
    //   3233: sipush #-28118
    //   3236: invokestatic a : (II)Ljava/lang/String;
    //   3239: invokevirtual startsWith : (Ljava/lang/String;)Z
    //   3242: ifne -> 3252
    //   3245: goto -> 3252
    //   3248: invokestatic a : (Ljava/lang/Throwable;)Ljava/lang/Throwable;
    //   3251: athrow
    //   3252: aload #8
    //   3254: iconst_1
    //   3255: invokevirtual setAccessible : (Z)V
    //   3258: aload #8
    //   3260: aconst_null
    //   3261: invokevirtual get : (Ljava/lang/Object;)Ljava/lang/Object;
    //   3264: pop
    //   3265: iinc #7, 1
    //   3268: iload_2
    //   3269: ifne -> 3130
    //   3272: sipush #-17248
    //   3275: sipush #-31629
    //   3278: invokestatic a : (II)Ljava/lang/String;
    //   3281: invokestatic forName : (Ljava/lang/String;)Ljava/lang/Class;
    //   3284: invokevirtual getDeclaredMethods : ()[Ljava/lang/reflect/Method;
    //   3287: astore #5
    //   3289: aload #5
    //   3291: arraylength
    //   3292: istore #6
    //   3294: iconst_0
    //   3295: istore #7
    //   3297: iload #7
    //   3299: iload #6
    //   3301: if_icmpge -> 3434
    //   3304: aload #5
    //   3306: iload #7
    //   3308: aaload
    //   3309: astore #8
    //   3311: aload #8
    //   3313: invokevirtual getParameterTypes : ()[Ljava/lang/Class;
    //   3316: pop
    //   3317: aload #8
    //   3319: invokevirtual getModifiers : ()I
    //   3322: invokestatic isStatic : (I)Z
    //   3325: ifeq -> 3420
    //   3328: aload #8
    //   3330: invokevirtual getParameterTypes : ()[Ljava/lang/Class;
    //   3333: arraylength
    //   3334: iconst_2
    //   3335: if_icmpne -> 3420
    //   3338: goto -> 3345
    //   3341: invokestatic a : (Ljava/lang/Throwable;)Ljava/lang/Throwable;
    //   3344: athrow
    //   3345: aload #8
    //   3347: invokevirtual getReturnType : ()Ljava/lang/Class;
    //   3350: getstatic java/lang/Void.TYPE : Ljava/lang/Class;
    //   3353: invokevirtual equals : (Ljava/lang/Object;)Z
    //   3356: ifeq -> 3420
    //   3359: goto -> 3366
    //   3362: invokestatic a : (Ljava/lang/Throwable;)Ljava/lang/Throwable;
    //   3365: athrow
    //   3366: aload #8
    //   3368: iconst_1
    //   3369: invokevirtual setAccessible : (Z)V
    //   3372: aload #8
    //   3374: aconst_null
    //   3375: iconst_2
    //   3376: anewarray java/lang/Object
    //   3379: dup
    //   3380: iconst_0
    //   3381: aload_0
    //   3382: aastore
    //   3383: dup
    //   3384: iconst_1
    //   3385: aload_1
    //   3386: ifnonnull -> 3404
    //   3389: goto -> 3396
    //   3392: invokestatic a : (Ljava/lang/Throwable;)Ljava/lang/Throwable;
    //   3395: athrow
    //   3396: aload_1
    //   3397: goto -> 3411
    //   3400: invokestatic a : (Ljava/lang/Throwable;)Ljava/lang/Throwable;
    //   3403: athrow
    //   3404: aload_1
    //   3405: checkcast [B
    //   3408: invokevirtual clone : ()Ljava/lang/Object;
    //   3411: aastore
    //   3412: invokevirtual invoke : (Ljava/lang/Object;[Ljava/lang/Object;)Ljava/lang/Object;
    //   3415: pop
    //   3416: iload_2
    //   3417: ifne -> 3434
    //   3420: iinc #7, 1
    //   3423: iload_2
    //   3424: ifne -> 3297
    //   3427: goto -> 3434
    //   3430: invokestatic a : (Ljava/lang/Throwable;)Ljava/lang/Throwable;
    //   3433: athrow
    //   3434: getstatic burp/Zmwx.ZB : Ljava/lang/String;
    //   3437: getstatic burp/Zgr4.ZL : Ljava/lang/Object;
    //   3440: checkcast java/math/BigInteger
    //   3443: invokevirtual intValue : ()I
    //   3446: bipush #32
    //   3448: irem
    //   3449: invokestatic abs : (I)I
    //   3452: invokevirtual charAt : (I)C
    //   3455: getstatic burp/Zcc.Zb : Ljava/lang/String;
    //   3458: getstatic burp/Zgqi.Zp : Ljava/lang/Object;
    //   3461: checkcast java/math/BigInteger
    //   3464: invokevirtual intValue : ()I
    //   3467: bipush #32
    //   3469: irem
    //   3470: invokestatic abs : (I)I
    //   3473: invokevirtual charAt : (I)C
    //   3476: if_icmpgt -> 3591
    //   3479: getstatic burp/Zgh3.ZR : Ljava/lang/String;
    //   3482: getstatic burp/Zeoa.ZF : Ljava/lang/Object;
    //   3485: checkcast java/math/BigInteger
    //   3488: invokevirtual intValue : ()I
    //   3491: bipush #32
    //   3493: irem
    //   3494: invokestatic abs : (I)I
    //   3497: invokevirtual charAt : (I)C
    //   3500: getstatic burp/Zr5k.Zq : Ljava/lang/String;
    //   3503: getstatic burp/Zei_.Za : Ljava/lang/Object;
    //   3506: checkcast java/math/BigInteger
    //   3509: invokevirtual intValue : ()I
    //   3512: bipush #32
    //   3514: irem
    //   3515: invokestatic abs : (I)I
    //   3518: invokevirtual charAt : (I)C
    //   3521: if_icmple -> 3591
    //   3524: goto -> 3531
    //   3527: invokestatic a : (Ljava/lang/Throwable;)Ljava/lang/Throwable;
    //   3530: athrow
    //   3531: getstatic burp/Zre1.ZA : Ljava/lang/String;
    //   3534: getstatic burp/Ztmy.ZH : Ljava/lang/Object;
    //   3537: checkcast java/math/BigInteger
    //   3540: invokevirtual intValue : ()I
    //   3543: bipush #32
    //   3545: irem
    //   3546: invokestatic abs : (I)I
    //   3549: invokevirtual charAt : (I)C
    //   3552: getstatic burp/Zlps.ZO : Ljava/lang/String;
    //   3555: getstatic burp/Zmfw.ZS : Ljava/lang/Object;
    //   3558: checkcast java/math/BigInteger
    //   3561: invokevirtual intValue : ()I
    //   3564: bipush #32
    //   3566: irem
    //   3567: invokestatic abs : (I)I
    //   3570: invokevirtual charAt : (I)C
    //   3573: if_icmple -> 3591
    //   3576: goto -> 3583
    //   3579: invokestatic a : (Ljava/lang/Throwable;)Ljava/lang/Throwable;
    //   3582: athrow
    //   3583: iconst_1
    //   3584: goto -> 3592
    //   3587: invokestatic a : (Ljava/lang/Throwable;)Ljava/lang/Throwable;
    //   3590: athrow
    //   3591: iconst_0
    //   3592: ireturn
    //   3593: astore_3
    //   3594: new java/lang/Exception
    //   3597: dup
    //   3598: aload_3
    //   3599: invokevirtual getMessage : ()Ljava/lang/String;
    //   3602: invokespecial <init> : (Ljava/lang/String;)V
    //   3605: athrow
    // Exception table:
    //   from	to	target	type
    //   4	3592	3593	java/lang/Throwable
    //   40	214	217	java/lang/Throwable
    //   184	251	254	java/lang/Throwable
    //   221	288	291	java/lang/Throwable
    //   258	325	328	java/lang/Throwable
    //   295	362	365	java/lang/Throwable
    //   332	399	402	java/lang/Throwable
    //   369	436	439	java/lang/Throwable
    //   406	473	476	java/lang/Throwable
    //   443	510	513	java/lang/Throwable
    //   480	547	550	java/lang/Throwable
    //   517	584	587	java/lang/Throwable
    //   554	621	624	java/lang/Throwable
    //   591	658	661	java/lang/Throwable
    //   628	695	698	java/lang/Throwable
    //   665	732	735	java/lang/Throwable
    //   702	769	772	java/lang/Throwable
    //   739	806	809	java/lang/Throwable
    //   776	843	846	java/lang/Throwable
    //   813	880	883	java/lang/Throwable
    //   850	917	920	java/lang/Throwable
    //   887	954	957	java/lang/Throwable
    //   924	991	994	java/lang/Throwable
    //   961	1028	1031	java/lang/Throwable
    //   998	1065	1068	java/lang/Throwable
    //   1035	1102	1105	java/lang/Throwable
    //   1072	1139	1142	java/lang/Throwable
    //   1109	1176	1179	java/lang/Throwable
    //   1146	1213	1216	java/lang/Throwable
    //   1183	1250	1253	java/lang/Throwable
    //   1220	1287	1290	java/lang/Throwable
    //   1257	1324	1327	java/lang/Throwable
    //   1294	1357	1360	java/lang/Throwable
    //   1397	1571	1574	java/lang/Throwable
    //   1540	1609	1612	java/lang/Throwable
    //   1578	1647	1650	java/lang/Throwable
    //   1616	1685	1688	java/lang/Throwable
    //   1654	1723	1726	java/lang/Throwable
    //   1692	1761	1764	java/lang/Throwable
    //   1730	1799	1802	java/lang/Throwable
    //   1768	1837	1840	java/lang/Throwable
    //   1806	1875	1878	java/lang/Throwable
    //   1844	1913	1916	java/lang/Throwable
    //   1882	1951	1954	java/lang/Throwable
    //   1920	1989	1992	java/lang/Throwable
    //   1958	2027	2030	java/lang/Throwable
    //   1996	2065	2068	java/lang/Throwable
    //   2034	2103	2106	java/lang/Throwable
    //   2072	2141	2144	java/lang/Throwable
    //   2110	2179	2182	java/lang/Throwable
    //   2148	2217	2220	java/lang/Throwable
    //   2186	2255	2258	java/lang/Throwable
    //   2224	2293	2296	java/lang/Throwable
    //   2262	2331	2334	java/lang/Throwable
    //   2300	2369	2372	java/lang/Throwable
    //   2338	2407	2410	java/lang/Throwable
    //   2376	2445	2448	java/lang/Throwable
    //   2414	2483	2486	java/lang/Throwable
    //   2452	2521	2524	java/lang/Throwable
    //   2490	2559	2562	java/lang/Throwable
    //   2528	2597	2600	java/lang/Throwable
    //   2566	2635	2638	java/lang/Throwable
    //   2604	2673	2676	java/lang/Throwable
    //   2642	2711	2714	java/lang/Throwable
    //   2680	2745	2748	java/lang/Throwable
    //   2812	2826	2826	java/lang/Throwable
    //   2837	2850	2853	java/lang/Throwable
    //   2842	2865	2868	java/lang/Throwable
    //   2857	2883	2886	java/lang/Throwable
    //   2872	2913	2916	java/lang/Throwable
    //   2979	3006	3009	java/lang/Throwable
    //   2996	3024	3027	java/lang/Throwable
    //   3013	3054	3057	java/lang/Throwable
    //   3031	3065	3065	java/lang/Throwable
    //   3076	3092	3095	java/lang/Throwable
    //   3144	3158	3158	java/lang/Throwable
    //   3169	3182	3185	java/lang/Throwable
    //   3174	3197	3200	java/lang/Throwable
    //   3189	3215	3218	java/lang/Throwable
    //   3204	3245	3248	java/lang/Throwable
    //   3311	3338	3341	java/lang/Throwable
    //   3328	3359	3362	java/lang/Throwable
    //   3345	3389	3392	java/lang/Throwable
    //   3366	3400	3400	java/lang/Throwable
    //   3411	3427	3430	java/lang/Throwable
    //   3434	3524	3527	java/lang/Throwable
    //   3479	3576	3579	java/lang/Throwable
    //   3531	3587	3587	java/lang/Throwable
  }
  
  static void Zu(Object[] paramArrayOfObject, Object paramObject) throws Throwable {}
  
  static void ZI(Object paramObject) {
    Ztap.Zk = a(-17247, -18975);
    Ztap.ZK = new BigInteger(a(-17246, 17196));
    boolean bool = Zt2e.ZK();
    try {
      try {
        if (Zrj3.ZT.charAt(Math.abs(((BigInteger)ZX).intValue() % 32)) > Zdm.ZJ.charAt(Math.abs(((BigInteger)ZX).intValue() % 32))) {
          try {
            Zb29.ZA(Class.forName(a(-17234, 16623)));
            if (bool)
              Zsf7.Zm(Class.forName(a(-17242, 10308))); 
          } catch (Throwable throwable) {
            throw a(null);
          } 
          return;
        } 
      } catch (Throwable throwable) {
        throw a(null);
      } 
      Zsf7.Zm(Class.forName(a(-17242, 10308)));
    } catch (Throwable throwable) {}
  }
  
  static {
    // Byte code:
    //   0: bipush #11
    //   2: anewarray java/lang/String
    //   5: astore #5
    //   7: iconst_0
    //   8: istore_3
    //   9: ldc '3q`Kt;I\\n^up\\tFM_y\\t81O f9|w:|-KapT7T/M~;v$+(:;L_<}$=\UMt8Kg@:#gAlfb]\\tp1Y\\tITcVkQP'
    //   11: dup
    //   12: astore_2
    //   13: invokevirtual length : ()I
    //   16: istore #4
    //   18: bipush #32
    //   20: istore_1
    //   21: iconst_m1
    //   22: istore_0
    //   23: bipush #51
    //   25: iinc #0, 1
    //   28: aload_2
    //   29: iload_0
    //   30: dup
    //   31: iload_1
    //   32: iadd
    //   33: invokevirtual substring : (II)Ljava/lang/String;
    //   36: iconst_m1
    //   37: goto -> 143
    //   40: aload #5
    //   42: swap
    //   43: iload_3
    //   44: iinc #3, 1
    //   47: swap
    //   48: aastore
    //   49: iload_0
    //   50: iload_1
    //   51: iadd
    //   52: dup
    //   53: istore_0
    //   54: iload #4
    //   56: if_icmpge -> 68
    //   59: aload_2
    //   60: iload_0
    //   61: invokevirtual charAt : (I)C
    //   64: istore_1
    //   65: goto -> 23
    //   68: ldc 'i$t\\tW;\\f;&'
    //   70: dup
    //   71: astore_2
    //   72: invokevirtual length : ()I
    //   75: istore #4
    //   77: bipush #9
    //   79: istore_1
    //   80: iconst_m1
    //   81: istore_0
    //   82: bipush #48
    //   84: iinc #0, 1
    //   87: aload_2
    //   88: iload_0
    //   89: dup
    //   90: iload_1
    //   91: iadd
    //   92: invokevirtual substring : (II)Ljava/lang/String;
    //   95: iconst_0
    //   96: goto -> 143
    //   99: aload #5
    //   101: swap
    //   102: iload_3
    //   103: iinc #3, 1
    //   106: swap
    //   107: aastore
    //   108: iload_0
    //   109: iload_1
    //   110: iadd
    //   111: dup
    //   112: istore_0
    //   113: iload #4
    //   115: if_icmpge -> 127
    //   118: aload_2
    //   119: iload_0
    //   120: invokevirtual charAt : (I)C
    //   123: istore_1
    //   124: goto -> 82
    //   127: aload #5
    //   129: putstatic burp/Zr0.a : [Ljava/lang/String;
    //   132: bipush #11
    //   134: anewarray java/lang/String
    //   137: putstatic burp/Zr0.b : [Ljava/lang/String;
    //   140: goto -> 300
    //   143: dup_x2
    //   144: pop
    //   145: invokevirtual toCharArray : ()[C
    //   148: dup_x1
    //   149: arraylength
    //   150: dup_x2
    //   151: pop
    //   152: iconst_0
    //   153: istore #6
    //   155: dup2_x1
    //   156: pop2
    //   157: dup_x2
    //   158: iconst_1
    //   159: if_icmpgt -> 260
    //   162: dup2
    //   163: swap
    //   164: iload #6
    //   166: dup2_x1
    //   167: caload
    //   168: swap
    //   169: iload #6
    //   171: bipush #7
    //   173: irem
    //   174: tableswitch default -> 242, 0 -> 212, 1 -> 217, 2 -> 222, 3 -> 227, 4 -> 232, 5 -> 237
    //   212: bipush #15
    //   214: goto -> 244
    //   217: bipush #37
    //   219: goto -> 244
    //   222: bipush #109
    //   224: goto -> 244
    //   227: bipush #101
    //   229: goto -> 244
    //   232: bipush #28
    //   234: goto -> 244
    //   237: bipush #61
    //   239: goto -> 244
    //   242: bipush #95
    //   244: ixor
    //   245: ixor
    //   246: i2c
    //   247: castore
    //   248: iinc #6, 1
    //   251: dup
    //   252: ifne -> 260
    //   255: dup2
    //   256: dup_x1
    //   257: goto -> 166
    //   260: dup2_x1
    //   261: pop2
    //   262: dup_x2
    //   263: iload #6
    //   265: if_icmpgt -> 162
    //   268: pop
    //   269: new java/lang/String
    //   272: dup_x1
    //   273: swap
    //   274: invokespecial <init> : ([C)V
    //   277: invokevirtual intern : ()Ljava/lang/String;
    //   280: swap
    //   281: pop
    //   282: swap
    //   283: tableswitch default -> 40, 0 -> 99
    //   300: new java/math/BigInteger
    //   303: dup
    //   304: iconst_1
    //   305: bipush #32
    //   307: newarray byte
    //   309: dup
    //   310: iconst_0
    //   311: bipush #93
    //   313: bastore
    //   314: dup
    //   315: iconst_1
    //   316: bipush #54
    //   318: bastore
    //   319: dup
    //   320: iconst_2
    //   321: bipush #30
    //   323: bastore
    //   324: dup
    //   325: iconst_3
    //   326: bipush #-85
    //   328: bastore
    //   329: dup
    //   330: iconst_4
    //   331: bipush #-67
    //   333: bastore
    //   334: dup
    //   335: iconst_5
    //   336: bipush #66
    //   338: bastore
    //   339: dup
    //   340: bipush #6
    //   342: bipush #16
    //   344: bastore
    //   345: dup
    //   346: bipush #7
    //   348: bipush #-34
    //   350: bastore
    //   351: dup
    //   352: bipush #8
    //   354: bipush #-45
    //   356: bastore
    //   357: dup
    //   358: bipush #9
    //   360: bipush #-44
    //   362: bastore
    //   363: dup
    //   364: bipush #10
    //   366: bipush #-87
    //   368: bastore
    //   369: dup
    //   370: bipush #11
    //   372: bipush #-70
    //   374: bastore
    //   375: dup
    //   376: bipush #12
    //   378: bipush #-55
    //   380: bastore
    //   381: dup
    //   382: bipush #13
    //   384: bipush #46
    //   386: bastore
    //   387: dup
    //   388: bipush #14
    //   390: bipush #54
    //   392: bastore
    //   393: dup
    //   394: bipush #15
    //   396: bipush #24
    //   398: bastore
    //   399: dup
    //   400: bipush #16
    //   402: bipush #-11
    //   404: bastore
    //   405: dup
    //   406: bipush #17
    //   408: bipush #-12
    //   410: bastore
    //   411: dup
    //   412: bipush #18
    //   414: bipush #52
    //   416: bastore
    //   417: dup
    //   418: bipush #19
    //   420: bipush #34
    //   422: bastore
    //   423: dup
    //   424: bipush #20
    //   426: bipush #72
    //   428: bastore
    //   429: dup
    //   430: bipush #21
    //   432: bipush #125
    //   434: bastore
    //   435: dup
    //   436: bipush #22
    //   438: bipush #-74
    //   440: bastore
    //   441: dup
    //   442: bipush #23
    //   444: bipush #30
    //   446: bastore
    //   447: dup
    //   448: bipush #24
    //   450: bipush #-98
    //   452: bastore
    //   453: dup
    //   454: bipush #25
    //   456: bipush #68
    //   458: bastore
    //   459: dup
    //   460: bipush #26
    //   462: bipush #46
    //   464: bastore
    //   465: dup
    //   466: bipush #27
    //   468: iconst_m1
    //   469: bastore
    //   470: dup
    //   471: bipush #28
    //   473: bipush #-42
    //   475: bastore
    //   476: dup
    //   477: bipush #29
    //   479: bipush #-28
    //   481: bastore
    //   482: dup
    //   483: bipush #30
    //   485: bipush #12
    //   487: bastore
    //   488: dup
    //   489: bipush #31
    //   491: bipush #-84
    //   493: bastore
    //   494: invokespecial <init> : (I[B)V
    //   497: putstatic burp/Zr0.ZX : Ljava/lang/Object;
    //   500: sipush #-17244
    //   503: sipush #20493
    //   506: invokestatic a : (II)Ljava/lang/String;
    //   509: putstatic burp/Zr0.ZH : Ljava/lang/String;
    //   512: return
  }
  
  private static Throwable a(Throwable paramThrowable) {
    return paramThrowable;
  }
  
  private static String a(int paramInt1, int paramInt2) {
    int i = (paramInt1 ^ 0xFFFFBCA4) & 0xFFFF;
    if (b[i] == null) {
      char[] arrayOfChar = a[i].toCharArray();
      switch (arrayOfChar[0] & 0xFF) {
        case 0:
        
        case 1:
        
        case 2:
        
        case 3:
        
        case 4:
        
        case 5:
        
        case 6:
        
        case 7:
        
        case 8:
        
        case 9:
        
        case 10:
        
        case 11:
        
        case 12:
        
        case 13:
        
        case 14:
        
        case 15:
        
        case 16:
        
        case 17:
        
        case 18:
        
        case 19:
        
        case 20:
        
        case 21:
        
        case 22:
        
        case 23:
        
        case 24:
        
        case 25:
        
        case 26:
        
        case 27:
        
        case 28:
        
        case 29:
        
        case 30:
        
        case 31:
        
        case 32:
        
        case 33:
        
        case 34:
        
        case 35:
        
        case 36:
        
        case 37:
        
        case 38:
        
        case 39:
        
        case 40:
        
        case 41:
        
        case 42:
        
        case 43:
        
        case 44:
        
        case 45:
        
        case 46:
        
        case 47:
        
        case 48:
        
        case 49:
        
        case 50:
        
        case 51:
        
        case 52:
        
        case 53:
        
        case 54:
        
        case 55:
        
        case 56:
        
        case 57:
        
        case 58:
        
        case 59:
        
        case 60:
        
        case 61:
        
        case 62:
        
        case 63:
        
        case 64:
        
        case 65:
        
        case 66:
        
        case 67:
        
        case 68:
        
        case 69:
        
        case 70:
        
        case 71:
        
        case 72:
        
        case 73:
        
        case 74:
        
        case 75:
        
        case 76:
        
        case 77:
        
        case 78:
        
        case 79:
        
        case 80:
        
        case 81:
        
        case 82:
        
        case 83:
        
        case 84:
        
        case 85:
        
        case 86:
        
        case 87:
        
        case 88:
        
        case 89:
        
        case 90:
        
        case 91:
        
        case 92:
        
        case 93:
        
        case 94:
        
        case 95:
        
        case 96:
        
        case 97:
        
        case 98:
        
        case 99:
        
        case 100:
        
        case 101:
        
        case 102:
        
        case 103:
        
        case 104:
        
        case 105:
        
        case 106:
        
        case 107:
        
        case 108:
        
        case 109:
        
        case 110:
        
        case 111:
        
        case 112:
        
        case 113:
        
        case 114:
        
        case 115:
        
        case 116:
        
        case 117:
        
        case 118:
        
        case 119:
        
        case 120:
        
        case 121:
        
        case 122:
        
        case 123:
        
        case 124:
        
        case 125:
        
        case 126:
        
        case 127:
        
        case 128:
        
        case 129:
        
        case 130:
        
        case 131:
        
        case 132:
        
        case 133:
        
        case 134:
        
        case 135:
        
        case 136:
        
        case 137:
        
        case 138:
        
        case 139:
        
        case 140:
        
        case 141:
        
        case 142:
        
        case 143:
        
        case 144:
        
        case 145:
        
        case 146:
        
        case 147:
        
        case 148:
        
        case 149:
        
        case 150:
        
        case 151:
        
        case 152:
        
        case 153:
        
        case 154:
        
        case 155:
        
        case 156:
        
        case 157:
        
        case 158:
        
        case 159:
        
        case 160:
        
        case 161:
        
        case 162:
        
        case 163:
        
        case 164:
        
        case 165:
        
        case 166:
        
        case 167:
        
        case 168:
        
        case 169:
        
        case 170:
        
        case 171:
        
        case 172:
        
        case 173:
        
        case 174:
        
        case 175:
        
        case 176:
        
        case 177:
        
        case 178:
        
        case 179:
        
        case 180:
        
        case 181:
        
        case 182:
        
        case 183:
        
        case 184:
        
        case 185:
        
        case 186:
        
        case 187:
        
        case 188:
        
        case 189:
        
        case 190:
        
        case 191:
        
        case 192:
        
        case 193:
        
        case 194:
        
        case 195:
        
        case 196:
        
        case 197:
        
        case 198:
        
        case 199:
        
        case 200:
        
        case 201:
        
        case 202:
        
        case 203:
        
        case 204:
        
        case 205:
        
        case 206:
        
        case 207:
        
        case 208:
        
        case 209:
        
        case 210:
        
        case 211:
        
        case 212:
        
        case 213:
        
        case 214:
        
        case 215:
        
        case 216:
        
        case 217:
        
        case 218:
        
        case 219:
        
        case 220:
        
        case 221:
        
        case 222:
        
        case 223:
        
        case 224:
        
        case 225:
        
        case 226:
        
        case 227:
        
        case 228:
        
        case 229:
        
        case 230:
        
        case 231:
        
        case 232:
        
        case 233:
        
        case 234:
        
        case 235:
        
        case 236:
        
        case 237:
        
        case 238:
        
        case 239:
        
        case 240:
        
        case 241:
        
        case 242:
        
        case 243:
        
        case 244:
        
        case 245:
        
        case 246:
        
        case 247:
        
        case 248:
        
        case 249:
        
        case 250:
        
        case 251:
        
        case 252:
        
        case 253:
        
        case 254:
        
        default:
          break;
      } 
      char c = '';
      int j = (paramInt2 & 0xFF) - c;
      if (j < 0)
        j += 256; 
      int k = ((paramInt2 & 0xFFFF) >>> 8) - c;
      if (k < 0)
        k += 256; 
      for (byte b = 0; b < arrayOfChar.length; b++) {
        int m = b % 2;
        if (m == 0) {
          arrayOfChar[b] = (char)(arrayOfChar[b] ^ j);
          j = ((j >>> 3 | j << 5) ^ arrayOfChar[b]) & 0xFF;
        } else {
          arrayOfChar[b] = (char)(arrayOfChar[b] ^ k);
          k = ((k >>> 3 | k << 5) ^ arrayOfChar[b]) & 0xFF;
        } 
      } 
      b[i] = (new String(arrayOfChar)).intern();
    } 
    return b[i];
  }
}


/* Location:              C:\Program Files\BurpSuitePro\burpsuite_pro.jar!\burp\Zr0.class
 * Java compiler version: 21 (65.0)
 * JD-Core Version:       1.1.3
 */