package burp;

public class Zr0o {
  private final Zerg ZH;
  
  private final Zgbj Zk;
  
  private final Zskh ZJ;
  
  private final Zz28 ZN;
  
  private final Zxgc Z_;
  
  private final Zz0n Zh;
  
  private final Zgb6 Zu;
  
  private final Zt4u Zj;
  
  private final Ztwv Zm;
  
  private final Zr_4 Zr;
  
  private final Zbnt Zx;
  
  private final Zey9 ZL;
  
  private final Ztg4 ZS;
  
  private final Zzzt Zz;
  
  private final Zztv Zv;
  
  private final Zepe ZY;
  
  private final Zepe ZM;
  
  private final Zepe Zo;
  
  private final boolean Ze;
  
  private final boolean Zn;
  
  private static final String[] a;
  
  private static final String[] b;
  
  public Zr0o(Zerg paramZerg, Zgbj paramZgbj, Zskh paramZskh, Zz28 paramZz28, Zxgc paramZxgc, Zz0n paramZz0n, Zgb6 paramZgb6, Zt4u paramZt4u, Ztwv paramZtwv, Zr_4 paramZr_4, Zbnt paramZbnt, Zey9 paramZey9, Ztg4 paramZtg4, Zzzt paramZzzt, Zen4 paramZen4) {
    // Byte code:
    //   0: aload_0
    //   1: invokespecial <init> : ()V
    //   4: aload_0
    //   5: aload_1
    //   6: putfield ZH : Lburp/Zerg;
    //   9: aload_0
    //   10: aload_2
    //   11: putfield Zk : Lburp/Zgbj;
    //   14: aload_0
    //   15: aload_3
    //   16: putfield ZJ : Lburp/Zskh;
    //   19: aload_0
    //   20: aload #4
    //   22: putfield ZN : Lburp/Zz28;
    //   25: invokestatic ZcN : ()[I
    //   28: aload_0
    //   29: aload #5
    //   31: putfield Z_ : Lburp/Zxgc;
    //   34: aload_0
    //   35: aload #6
    //   37: putfield Zh : Lburp/Zz0n;
    //   40: aload_0
    //   41: aload #7
    //   43: putfield Zu : Lburp/Zgb6;
    //   46: aload_0
    //   47: aload #8
    //   49: putfield Zj : Lburp/Zt4u;
    //   52: astore #16
    //   54: aload_0
    //   55: aload #9
    //   57: putfield Zm : Lburp/Ztwv;
    //   60: aload_0
    //   61: aload #10
    //   63: putfield Zr : Lburp/Zr_4;
    //   66: aload_0
    //   67: aload #11
    //   69: putfield Zx : Lburp/Zbnt;
    //   72: aload_0
    //   73: aload #12
    //   75: putfield ZL : Lburp/Zey9;
    //   78: aload_0
    //   79: aload #13
    //   81: putfield ZS : Lburp/Ztg4;
    //   84: aload_0
    //   85: aload #14
    //   87: putfield Zz : Lburp/Zzzt;
    //   90: new burp/Zzwp
    //   93: dup
    //   94: aload_0
    //   95: invokespecial <init> : (Lburp/Zr0o;)V
    //   98: astore #17
    //   100: aload_0
    //   101: getstatic net/portswigger/Zvh.ZU : Lnet/portswigger/Zvh;
    //   104: invokevirtual ZM : ()Z
    //   107: ifne -> 114
    //   110: iconst_1
    //   111: goto -> 115
    //   114: iconst_0
    //   115: putfield Ze : Z
    //   118: aload_0
    //   119: aload #10
    //   121: invokeinterface Zi : ()Z
    //   126: putfield Zn : Z
    //   129: aload_0
    //   130: aload #15
    //   132: invokevirtual ZL : ()Lburp/Zztv;
    //   135: putfield Zv : Lburp/Zztv;
    //   138: aload_0
    //   139: new burp/Zepe
    //   142: dup
    //   143: sipush #13906
    //   146: sipush #-20149
    //   149: invokestatic a : (II)Ljava/lang/String;
    //   152: invokespecial <init> : (Ljava/lang/String;)V
    //   155: putfield ZY : Lburp/Zepe;
    //   158: aload_0
    //   159: getfield ZY : Lburp/Zepe;
    //   162: aload #17
    //   164: invokevirtual addActionListener : (Ljava/awt/event/ActionListener;)V
    //   167: aload_0
    //   168: getfield Ze : Z
    //   171: ifeq -> 208
    //   174: aload_0
    //   175: new burp/Zepe
    //   178: dup
    //   179: sipush #13910
    //   182: sipush #31011
    //   185: invokestatic a : (II)Ljava/lang/String;
    //   188: invokespecial <init> : (Ljava/lang/String;)V
    //   191: putfield ZM : Lburp/Zepe;
    //   194: aload_0
    //   195: getfield ZM : Lburp/Zepe;
    //   198: aload #17
    //   200: invokevirtual addActionListener : (Ljava/awt/event/ActionListener;)V
    //   203: aload #16
    //   205: ifnonnull -> 236
    //   208: aload_0
    //   209: new burp/Zepe
    //   212: dup
    //   213: sipush #13911
    //   216: sipush #-4083
    //   219: invokestatic a : (II)Ljava/lang/String;
    //   222: invokespecial <init> : (Ljava/lang/String;)V
    //   225: putfield ZM : Lburp/Zepe;
    //   228: aload_0
    //   229: getfield ZM : Lburp/Zepe;
    //   232: iconst_0
    //   233: invokevirtual setEnabled : (Z)V
    //   236: aload_0
    //   237: getfield Zn : Z
    //   240: ifeq -> 277
    //   243: aload_0
    //   244: new burp/Zepe
    //   247: dup
    //   248: sipush #13905
    //   251: sipush #28325
    //   254: invokestatic a : (II)Ljava/lang/String;
    //   257: invokespecial <init> : (Ljava/lang/String;)V
    //   260: putfield Zo : Lburp/Zepe;
    //   263: aload_0
    //   264: getfield Zo : Lburp/Zepe;
    //   267: aload #17
    //   269: invokevirtual addActionListener : (Ljava/awt/event/ActionListener;)V
    //   272: aload #16
    //   274: ifnonnull -> 305
    //   277: aload_0
    //   278: new burp/Zepe
    //   281: dup
    //   282: sipush #13904
    //   285: sipush #26366
    //   288: invokestatic a : (II)Ljava/lang/String;
    //   291: invokespecial <init> : (Ljava/lang/String;)V
    //   294: putfield Zo : Lburp/Zepe;
    //   297: aload_0
    //   298: getfield Zo : Lburp/Zepe;
    //   301: iconst_0
    //   302: invokevirtual setEnabled : (Z)V
    //   305: invokestatic Zwu : ()[Lburp/Zbqc;
    //   308: ifnonnull -> 317
    //   311: iconst_4
    //   312: newarray int
    //   314: invokestatic Zs : ([I)V
    //   317: return
  }
  
  public Zztv ZT() {
    Zztv zztv = new Zztv();
    zztv.setText(a(13907, -16237));
    zztv.add(this.Zv);
    zztv.add(this.ZY);
    zztv.add(this.ZM);
    zztv.add(this.Zo);
    return zztv;
  }
  
  static {
    // Byte code:
    //   0: bipush #6
    //   2: anewarray java/lang/String
    //   5: astore #5
    //   7: iconst_0
    //   8: istore_3
    //   9: ldc 'é\\r|Ryo-¯h(ÃÖ_a9¤²soóà.Ìú»Q+3ÊèMa\\fF½,nK¯ºôìL²%\tÉ·¤ûõMÄ{g'
    //   11: dup
    //   12: astore_2
    //   13: invokevirtual length : ()I
    //   16: istore #4
    //   18: bipush #6
    //   20: istore_1
    //   21: iconst_m1
    //   22: istore_0
    //   23: bipush #86
    //   25: iinc #0, 1
    //   28: aload_2
    //   29: iload_0
    //   30: dup
    //   31: iload_1
    //   32: iadd
    //   33: invokevirtual substring : (II)Ljava/lang/String;
    //   36: iconst_m1
    //   37: goto -> 143
    //   40: aload #5
    //   42: swap
    //   43: iload_3
    //   44: iinc #3, 1
    //   47: swap
    //   48: aastore
    //   49: iload_0
    //   50: iload_1
    //   51: iadd
    //   52: dup
    //   53: istore_0
    //   54: iload #4
    //   56: if_icmpge -> 68
    //   59: aload_2
    //   60: iload_0
    //   61: invokevirtual charAt : (I)C
    //   64: istore_1
    //   65: goto -> 23
    //   68: ldc 'W{øB5¨"+jìäp¬KuíuùF,ôl@¤L×¼þ>¼é\\tîÏüç½tPùä°'
    //   70: dup
    //   71: astore_2
    //   72: invokevirtual length : ()I
    //   75: istore #4
    //   77: bipush #9
    //   79: istore_1
    //   80: iconst_m1
    //   81: istore_0
    //   82: bipush #97
    //   84: iinc #0, 1
    //   87: aload_2
    //   88: iload_0
    //   89: dup
    //   90: iload_1
    //   91: iadd
    //   92: invokevirtual substring : (II)Ljava/lang/String;
    //   95: iconst_0
    //   96: goto -> 143
    //   99: aload #5
    //   101: swap
    //   102: iload_3
    //   103: iinc #3, 1
    //   106: swap
    //   107: aastore
    //   108: iload_0
    //   109: iload_1
    //   110: iadd
    //   111: dup
    //   112: istore_0
    //   113: iload #4
    //   115: if_icmpge -> 127
    //   118: aload_2
    //   119: iload_0
    //   120: invokevirtual charAt : (I)C
    //   123: istore_1
    //   124: goto -> 82
    //   127: aload #5
    //   129: putstatic burp/Zr0o.a : [Ljava/lang/String;
    //   132: bipush #6
    //   134: anewarray java/lang/String
    //   137: putstatic burp/Zr0o.b : [Ljava/lang/String;
    //   140: goto -> 300
    //   143: dup_x2
    //   144: pop
    //   145: invokevirtual toCharArray : ()[C
    //   148: dup_x1
    //   149: arraylength
    //   150: dup_x2
    //   151: pop
    //   152: iconst_0
    //   153: istore #6
    //   155: dup2_x1
    //   156: pop2
    //   157: dup_x2
    //   158: iconst_1
    //   159: if_icmpgt -> 260
    //   162: dup2
    //   163: swap
    //   164: iload #6
    //   166: dup2_x1
    //   167: caload
    //   168: swap
    //   169: iload #6
    //   171: bipush #7
    //   173: irem
    //   174: tableswitch default -> 242, 0 -> 212, 1 -> 217, 2 -> 222, 3 -> 227, 4 -> 232, 5 -> 237
    //   212: bipush #87
    //   214: goto -> 244
    //   217: bipush #30
    //   219: goto -> 244
    //   222: bipush #65
    //   224: goto -> 244
    //   227: bipush #75
    //   229: goto -> 244
    //   232: bipush #106
    //   234: goto -> 244
    //   237: bipush #44
    //   239: goto -> 244
    //   242: bipush #97
    //   244: ixor
    //   245: ixor
    //   246: i2c
    //   247: castore
    //   248: iinc #6, 1
    //   251: dup
    //   252: ifne -> 260
    //   255: dup2
    //   256: dup_x1
    //   257: goto -> 166
    //   260: dup2_x1
    //   261: pop2
    //   262: dup_x2
    //   263: iload #6
    //   265: if_icmpgt -> 162
    //   268: pop
    //   269: new java/lang/String
    //   272: dup_x1
    //   273: swap
    //   274: invokespecial <init> : ([C)V
    //   277: invokevirtual intern : ()Ljava/lang/String;
    //   280: swap
    //   281: pop
    //   282: swap
    //   283: tableswitch default -> 40, 0 -> 99
    //   300: return
  }
  
  private static String a(int paramInt1, int paramInt2) {
    int i = (paramInt1 ^ 0x3652) & 0xFFFF;
    if (b[i] == null) {
      char[] arrayOfChar = a[i].toCharArray();
      switch (arrayOfChar[0] & 0xFF) {
        case 0:
        
        case 1:
        
        case 2:
        
        case 3:
        
        case 4:
        
        case 5:
        
        case 6:
        
        case 7:
        
        case 8:
        
        case 9:
        
        case 10:
        
        case 11:
        
        case 12:
        
        case 13:
        
        case 14:
        
        case 15:
        
        case 16:
        
        case 17:
        
        case 18:
        
        case 19:
        
        case 20:
        
        case 21:
        
        case 22:
        
        case 23:
        
        case 24:
        
        case 25:
        
        case 26:
        
        case 27:
        
        case 28:
        
        case 29:
        
        case 30:
        
        case 31:
        
        case 32:
        
        case 33:
        
        case 34:
        
        case 35:
        
        case 36:
        
        case 37:
        
        case 38:
        
        case 39:
        
        case 40:
        
        case 41:
        
        case 42:
        
        case 43:
        
        case 44:
        
        case 45:
        
        case 46:
        
        case 47:
        
        case 48:
        
        case 49:
        
        case 50:
        
        case 51:
        
        case 52:
        
        case 53:
        
        case 54:
        
        case 55:
        
        case 56:
        
        case 57:
        
        case 58:
        
        case 59:
        
        case 60:
        
        case 61:
        
        case 62:
        
        case 63:
        
        case 64:
        
        case 65:
        
        case 66:
        
        case 67:
        
        case 68:
        
        case 69:
        
        case 70:
        
        case 71:
        
        case 72:
        
        case 73:
        
        case 74:
        
        case 75:
        
        case 76:
        
        case 77:
        
        case 78:
        
        case 79:
        
        case 80:
        
        case 81:
        
        case 82:
        
        case 83:
        
        case 84:
        
        case 85:
        
        case 86:
        
        case 87:
        
        case 88:
        
        case 89:
        
        case 90:
        
        case 91:
        
        case 92:
        
        case 93:
        
        case 94:
        
        case 95:
        
        case 96:
        
        case 97:
        
        case 98:
        
        case 99:
        
        case 100:
        
        case 101:
        
        case 102:
        
        case 103:
        
        case 104:
        
        case 105:
        
        case 106:
        
        case 107:
        
        case 108:
        
        case 109:
        
        case 110:
        
        case 111:
        
        case 112:
        
        case 113:
        
        case 114:
        
        case 115:
        
        case 116:
        
        case 117:
        
        case 118:
        
        case 119:
        
        case 120:
        
        case 121:
        
        case 122:
        
        case 123:
        
        case 124:
        
        case 125:
        
        case 126:
        
        case 127:
        
        case 128:
        
        case 129:
        
        case 130:
        
        case 131:
        
        case 132:
        
        case 133:
        
        case 134:
        
        case 135:
        
        case 136:
        
        case 137:
        
        case 138:
        
        case 139:
        
        case 140:
        
        case 141:
        
        case 142:
        
        case 143:
        
        case 144:
        
        case 145:
        
        case 146:
        
        case 147:
        
        case 148:
        
        case 149:
        
        case 150:
        
        case 151:
        
        case 152:
        
        case 153:
        
        case 154:
        
        case 155:
        
        case 156:
        
        case 157:
        
        case 158:
        
        case 159:
        
        case 160:
        
        case 161:
        
        case 162:
        
        case 163:
        
        case 164:
        
        case 165:
        
        case 166:
        
        case 167:
        
        case 168:
        
        case 169:
        
        case 170:
        
        case 171:
        
        case 172:
        
        case 173:
        
        case 174:
        
        case 175:
        
        case 176:
        
        case 177:
        
        case 178:
        
        case 179:
        
        case 180:
        
        case 181:
        
        case 182:
        
        case 183:
        
        case 184:
        
        case 185:
        
        case 186:
        
        case 187:
        
        case 188:
        
        case 189:
        
        case 190:
        
        case 191:
        
        case 192:
        
        case 193:
        
        case 194:
        
        case 195:
        
        case 196:
        
        case 197:
        
        case 198:
        
        case 199:
        
        case 200:
        
        case 201:
        
        case 202:
        
        case 203:
        
        case 204:
        
        case 205:
        
        case 206:
        
        case 207:
        
        case 208:
        
        case 209:
        
        case 210:
        
        case 211:
        
        case 212:
        
        case 213:
        
        case 214:
        
        case 215:
        
        case 216:
        
        case 217:
        
        case 218:
        
        case 219:
        
        case 220:
        
        case 221:
        
        case 222:
        
        case 223:
        
        case 224:
        
        case 225:
        
        case 226:
        
        case 227:
        
        case 228:
        
        case 229:
        
        case 230:
        
        case 231:
        
        case 232:
        
        case 233:
        
        case 234:
        
        case 235:
        
        case 236:
        
        case 237:
        
        case 238:
        
        case 239:
        
        case 240:
        
        case 241:
        
        case 242:
        
        case 243:
        
        case 244:
        
        case 245:
        
        case 246:
        
        case 247:
        
        case 248:
        
        case 249:
        
        case 250:
        
        case 251:
        
        case 252:
        
        case 253:
        
        case 254:
        
        default:
          break;
      } 
      char c = '¬';
      int j = (paramInt2 & 0xFF) - c;
      if (j < 0)
        j += 256; 
      int k = ((paramInt2 & 0xFFFF) >>> 8) - c;
      if (k < 0)
        k += 256; 
      for (byte b = 0; b < arrayOfChar.length; b++) {
        int m = b % 2;
        if (m == 0) {
          arrayOfChar[b] = (char)(arrayOfChar[b] ^ j);
          j = ((j >>> 3 | j << 5) ^ arrayOfChar[b]) & 0xFF;
        } else {
          arrayOfChar[b] = (char)(arrayOfChar[b] ^ k);
          k = ((k >>> 3 | k << 5) ^ arrayOfChar[b]) & 0xFF;
        } 
      } 
      b[i] = (new String(arrayOfChar)).intern();
    } 
    return b[i];
  }
}


/* Location:              C:\Program Files\BurpSuitePro\burpsuite_pro.jar!\burp\Zr0o.class
 * Java compiler version: 21 (65.0)
 * JD-Core Version:       1.1.3
 */