package burp;

import java.math.BigInteger;

class Zr0u extends ClassLoader {
  static Object ZB;
  
  static String Z_;
  
  private static final String[] a;
  
  private static final String[] b;
  
  static boolean ZI(Object[] paramArrayOfObject, Object paramObject) throws Throwable {
    // Byte code:
    //   0: invokestatic ZN : ()Z
    //   3: istore_2
    //   4: new java/lang/StringBuilder
    //   7: dup
    //   8: invokespecial <init> : ()V
    //   11: astore_3
    //   12: iconst_0
    //   13: istore #4
    //   15: iload #4
    //   17: bipush #32
    //   19: if_icmpge -> 1355
    //   22: iload #4
    //   24: tableswitch default -> 1348, 0 -> 168, 1 -> 205, 2 -> 242, 3 -> 279, 4 -> 316, 5 -> 353, 6 -> 390, 7 -> 427, 8 -> 464, 9 -> 501, 10 -> 538, 11 -> 575, 12 -> 612, 13 -> 649, 14 -> 686, 15 -> 723, 16 -> 760, 17 -> 797, 18 -> 834, 19 -> 871, 20 -> 908, 21 -> 945, 22 -> 982, 23 -> 1019, 24 -> 1056, 25 -> 1093, 26 -> 1130, 27 -> 1167, 28 -> 1204, 29 -> 1241, 30 -> 1278, 31 -> 1315
    //   168: aload_3
    //   169: getstatic burp/Zx54.Zs : Ljava/lang/String;
    //   172: getstatic burp/Zod.ZP : Ljava/lang/Object;
    //   175: checkcast java/math/BigInteger
    //   178: invokevirtual intValue : ()I
    //   181: bipush #32
    //   183: irem
    //   184: invokestatic abs : (I)I
    //   187: invokevirtual charAt : (I)C
    //   190: invokevirtual append : (C)Ljava/lang/StringBuilder;
    //   193: pop
    //   194: iload_2
    //   195: ifne -> 1348
    //   198: goto -> 205
    //   201: invokestatic a : (Ljava/lang/Throwable;)Ljava/lang/Throwable;
    //   204: athrow
    //   205: aload_3
    //   206: getstatic burp/Zl_k.Zw : Ljava/lang/String;
    //   209: getstatic burp/Zllw.ZW : Ljava/lang/Object;
    //   212: checkcast java/math/BigInteger
    //   215: invokevirtual intValue : ()I
    //   218: bipush #32
    //   220: irem
    //   221: invokestatic abs : (I)I
    //   224: invokevirtual charAt : (I)C
    //   227: invokevirtual append : (C)Ljava/lang/StringBuilder;
    //   230: pop
    //   231: iload_2
    //   232: ifne -> 1348
    //   235: goto -> 242
    //   238: invokestatic a : (Ljava/lang/Throwable;)Ljava/lang/Throwable;
    //   241: athrow
    //   242: aload_3
    //   243: getstatic burp/Zzsq.Zc : Ljava/lang/String;
    //   246: getstatic burp/Zsxm.Zv : Ljava/lang/Object;
    //   249: checkcast java/math/BigInteger
    //   252: invokevirtual intValue : ()I
    //   255: bipush #32
    //   257: irem
    //   258: invokestatic abs : (I)I
    //   261: invokevirtual charAt : (I)C
    //   264: invokevirtual append : (C)Ljava/lang/StringBuilder;
    //   267: pop
    //   268: iload_2
    //   269: ifne -> 1348
    //   272: goto -> 279
    //   275: invokestatic a : (Ljava/lang/Throwable;)Ljava/lang/Throwable;
    //   278: athrow
    //   279: aload_3
    //   280: getstatic burp/Zxl5.Zq : Ljava/lang/String;
    //   283: getstatic burp/Zt3l.Zq : Ljava/lang/Object;
    //   286: checkcast java/math/BigInteger
    //   289: invokevirtual intValue : ()I
    //   292: bipush #32
    //   294: irem
    //   295: invokestatic abs : (I)I
    //   298: invokevirtual charAt : (I)C
    //   301: invokevirtual append : (C)Ljava/lang/StringBuilder;
    //   304: pop
    //   305: iload_2
    //   306: ifne -> 1348
    //   309: goto -> 316
    //   312: invokestatic a : (Ljava/lang/Throwable;)Ljava/lang/Throwable;
    //   315: athrow
    //   316: aload_3
    //   317: getstatic burp/Zr3q.ZM : Ljava/lang/String;
    //   320: getstatic burp/Zsde.Zx : Ljava/lang/Object;
    //   323: checkcast java/math/BigInteger
    //   326: invokevirtual intValue : ()I
    //   329: bipush #32
    //   331: irem
    //   332: invokestatic abs : (I)I
    //   335: invokevirtual charAt : (I)C
    //   338: invokevirtual append : (C)Ljava/lang/StringBuilder;
    //   341: pop
    //   342: iload_2
    //   343: ifne -> 1348
    //   346: goto -> 353
    //   349: invokestatic a : (Ljava/lang/Throwable;)Ljava/lang/Throwable;
    //   352: athrow
    //   353: aload_3
    //   354: getstatic burp/Zg7z.Zf : Ljava/lang/String;
    //   357: getstatic burp/Zx4l.Zt : Ljava/lang/Object;
    //   360: checkcast java/math/BigInteger
    //   363: invokevirtual intValue : ()I
    //   366: bipush #32
    //   368: irem
    //   369: invokestatic abs : (I)I
    //   372: invokevirtual charAt : (I)C
    //   375: invokevirtual append : (C)Ljava/lang/StringBuilder;
    //   378: pop
    //   379: iload_2
    //   380: ifne -> 1348
    //   383: goto -> 390
    //   386: invokestatic a : (Ljava/lang/Throwable;)Ljava/lang/Throwable;
    //   389: athrow
    //   390: aload_3
    //   391: getstatic burp/Zsby.Zx : Ljava/lang/String;
    //   394: getstatic burp/Zxfu.ZA : Ljava/lang/Object;
    //   397: checkcast java/math/BigInteger
    //   400: invokevirtual intValue : ()I
    //   403: bipush #32
    //   405: irem
    //   406: invokestatic abs : (I)I
    //   409: invokevirtual charAt : (I)C
    //   412: invokevirtual append : (C)Ljava/lang/StringBuilder;
    //   415: pop
    //   416: iload_2
    //   417: ifne -> 1348
    //   420: goto -> 427
    //   423: invokestatic a : (Ljava/lang/Throwable;)Ljava/lang/Throwable;
    //   426: athrow
    //   427: aload_3
    //   428: getstatic burp/Zlos.Zp : Ljava/lang/String;
    //   431: getstatic burp/Zsxm.Zv : Ljava/lang/Object;
    //   434: checkcast java/math/BigInteger
    //   437: invokevirtual intValue : ()I
    //   440: bipush #32
    //   442: irem
    //   443: invokestatic abs : (I)I
    //   446: invokevirtual charAt : (I)C
    //   449: invokevirtual append : (C)Ljava/lang/StringBuilder;
    //   452: pop
    //   453: iload_2
    //   454: ifne -> 1348
    //   457: goto -> 464
    //   460: invokestatic a : (Ljava/lang/Throwable;)Ljava/lang/Throwable;
    //   463: athrow
    //   464: aload_3
    //   465: getstatic burp/Zes_.ZM : Ljava/lang/String;
    //   468: getstatic burp/Zedz.Za : Ljava/lang/Object;
    //   471: checkcast java/math/BigInteger
    //   474: invokevirtual intValue : ()I
    //   477: bipush #32
    //   479: irem
    //   480: invokestatic abs : (I)I
    //   483: invokevirtual charAt : (I)C
    //   486: invokevirtual append : (C)Ljava/lang/StringBuilder;
    //   489: pop
    //   490: iload_2
    //   491: ifne -> 1348
    //   494: goto -> 501
    //   497: invokestatic a : (Ljava/lang/Throwable;)Ljava/lang/Throwable;
    //   500: athrow
    //   501: aload_3
    //   502: getstatic burp/Zr3q.ZM : Ljava/lang/String;
    //   505: getstatic burp/Zkfz.Zr : Ljava/lang/Object;
    //   508: checkcast java/math/BigInteger
    //   511: invokevirtual intValue : ()I
    //   514: bipush #32
    //   516: irem
    //   517: invokestatic abs : (I)I
    //   520: invokevirtual charAt : (I)C
    //   523: invokevirtual append : (C)Ljava/lang/StringBuilder;
    //   526: pop
    //   527: iload_2
    //   528: ifne -> 1348
    //   531: goto -> 538
    //   534: invokestatic a : (Ljava/lang/Throwable;)Ljava/lang/Throwable;
    //   537: athrow
    //   538: aload_3
    //   539: getstatic burp/Zxfu.Zo : Ljava/lang/String;
    //   542: getstatic burp/Zr0g.Zj : Ljava/lang/Object;
    //   545: checkcast java/math/BigInteger
    //   548: invokevirtual intValue : ()I
    //   551: bipush #32
    //   553: irem
    //   554: invokestatic abs : (I)I
    //   557: invokevirtual charAt : (I)C
    //   560: invokevirtual append : (C)Ljava/lang/StringBuilder;
    //   563: pop
    //   564: iload_2
    //   565: ifne -> 1348
    //   568: goto -> 575
    //   571: invokestatic a : (Ljava/lang/Throwable;)Ljava/lang/Throwable;
    //   574: athrow
    //   575: aload_3
    //   576: getstatic burp/Zzsq.Zc : Ljava/lang/String;
    //   579: getstatic burp/Zod.ZP : Ljava/lang/Object;
    //   582: checkcast java/math/BigInteger
    //   585: invokevirtual intValue : ()I
    //   588: bipush #32
    //   590: irem
    //   591: invokestatic abs : (I)I
    //   594: invokevirtual charAt : (I)C
    //   597: invokevirtual append : (C)Ljava/lang/StringBuilder;
    //   600: pop
    //   601: iload_2
    //   602: ifne -> 1348
    //   605: goto -> 612
    //   608: invokestatic a : (Ljava/lang/Throwable;)Ljava/lang/Throwable;
    //   611: athrow
    //   612: aload_3
    //   613: getstatic burp/Zrnu.ZO : Ljava/lang/String;
    //   616: getstatic burp/Zl_k.ZH : Ljava/lang/Object;
    //   619: checkcast java/math/BigInteger
    //   622: invokevirtual intValue : ()I
    //   625: bipush #32
    //   627: irem
    //   628: invokestatic abs : (I)I
    //   631: invokevirtual charAt : (I)C
    //   634: invokevirtual append : (C)Ljava/lang/StringBuilder;
    //   637: pop
    //   638: iload_2
    //   639: ifne -> 1348
    //   642: goto -> 649
    //   645: invokestatic a : (Ljava/lang/Throwable;)Ljava/lang/Throwable;
    //   648: athrow
    //   649: aload_3
    //   650: getstatic burp/Zzsq.Zc : Ljava/lang/String;
    //   653: getstatic burp/Zxo6.Zw : Ljava/lang/Object;
    //   656: checkcast java/math/BigInteger
    //   659: invokevirtual intValue : ()I
    //   662: bipush #32
    //   664: irem
    //   665: invokestatic abs : (I)I
    //   668: invokevirtual charAt : (I)C
    //   671: invokevirtual append : (C)Ljava/lang/StringBuilder;
    //   674: pop
    //   675: iload_2
    //   676: ifne -> 1348
    //   679: goto -> 686
    //   682: invokestatic a : (Ljava/lang/Throwable;)Ljava/lang/Throwable;
    //   685: athrow
    //   686: aload_3
    //   687: getstatic burp/Zer.Zp : Ljava/lang/String;
    //   690: getstatic burp/Zzsq.Zh : Ljava/lang/Object;
    //   693: checkcast java/math/BigInteger
    //   696: invokevirtual intValue : ()I
    //   699: bipush #32
    //   701: irem
    //   702: invokestatic abs : (I)I
    //   705: invokevirtual charAt : (I)C
    //   708: invokevirtual append : (C)Ljava/lang/StringBuilder;
    //   711: pop
    //   712: iload_2
    //   713: ifne -> 1348
    //   716: goto -> 723
    //   719: invokestatic a : (Ljava/lang/Throwable;)Ljava/lang/Throwable;
    //   722: athrow
    //   723: aload_3
    //   724: getstatic burp/Ze7q.ZW : Ljava/lang/String;
    //   727: getstatic burp/Zb3z.ZR : Ljava/lang/Object;
    //   730: checkcast java/math/BigInteger
    //   733: invokevirtual intValue : ()I
    //   736: bipush #32
    //   738: irem
    //   739: invokestatic abs : (I)I
    //   742: invokevirtual charAt : (I)C
    //   745: invokevirtual append : (C)Ljava/lang/StringBuilder;
    //   748: pop
    //   749: iload_2
    //   750: ifne -> 1348
    //   753: goto -> 760
    //   756: invokestatic a : (Ljava/lang/Throwable;)Ljava/lang/Throwable;
    //   759: athrow
    //   760: aload_3
    //   761: getstatic burp/Zr8h.Zk : Ljava/lang/String;
    //   764: getstatic burp/Zsgl.Zn : Ljava/lang/Object;
    //   767: checkcast java/math/BigInteger
    //   770: invokevirtual intValue : ()I
    //   773: bipush #32
    //   775: irem
    //   776: invokestatic abs : (I)I
    //   779: invokevirtual charAt : (I)C
    //   782: invokevirtual append : (C)Ljava/lang/StringBuilder;
    //   785: pop
    //   786: iload_2
    //   787: ifne -> 1348
    //   790: goto -> 797
    //   793: invokestatic a : (Ljava/lang/Throwable;)Ljava/lang/Throwable;
    //   796: athrow
    //   797: aload_3
    //   798: getstatic burp/Zxo6.Z_ : Ljava/lang/String;
    //   801: getstatic burp/Ze3d.Ze : Ljava/lang/Object;
    //   804: checkcast java/math/BigInteger
    //   807: invokevirtual intValue : ()I
    //   810: bipush #32
    //   812: irem
    //   813: invokestatic abs : (I)I
    //   816: invokevirtual charAt : (I)C
    //   819: invokevirtual append : (C)Ljava/lang/StringBuilder;
    //   822: pop
    //   823: iload_2
    //   824: ifne -> 1348
    //   827: goto -> 834
    //   830: invokestatic a : (Ljava/lang/Throwable;)Ljava/lang/Throwable;
    //   833: athrow
    //   834: aload_3
    //   835: getstatic burp/Zgss.Zc : Ljava/lang/String;
    //   838: getstatic burp/Zrnu.Zs : Ljava/lang/Object;
    //   841: checkcast java/math/BigInteger
    //   844: invokevirtual intValue : ()I
    //   847: bipush #32
    //   849: irem
    //   850: invokestatic abs : (I)I
    //   853: invokevirtual charAt : (I)C
    //   856: invokevirtual append : (C)Ljava/lang/StringBuilder;
    //   859: pop
    //   860: iload_2
    //   861: ifne -> 1348
    //   864: goto -> 871
    //   867: invokestatic a : (Ljava/lang/Throwable;)Ljava/lang/Throwable;
    //   870: athrow
    //   871: aload_3
    //   872: getstatic burp/Zkfz.Zs : Ljava/lang/String;
    //   875: getstatic burp/Zbp.ZD : Ljava/lang/Object;
    //   878: checkcast java/math/BigInteger
    //   881: invokevirtual intValue : ()I
    //   884: bipush #32
    //   886: irem
    //   887: invokestatic abs : (I)I
    //   890: invokevirtual charAt : (I)C
    //   893: invokevirtual append : (C)Ljava/lang/StringBuilder;
    //   896: pop
    //   897: iload_2
    //   898: ifne -> 1348
    //   901: goto -> 908
    //   904: invokestatic a : (Ljava/lang/Throwable;)Ljava/lang/Throwable;
    //   907: athrow
    //   908: aload_3
    //   909: getstatic burp/Zkyc.ZK : Ljava/lang/String;
    //   912: getstatic burp/Zkfz.Zr : Ljava/lang/Object;
    //   915: checkcast java/math/BigInteger
    //   918: invokevirtual intValue : ()I
    //   921: bipush #32
    //   923: irem
    //   924: invokestatic abs : (I)I
    //   927: invokevirtual charAt : (I)C
    //   930: invokevirtual append : (C)Ljava/lang/StringBuilder;
    //   933: pop
    //   934: iload_2
    //   935: ifne -> 1348
    //   938: goto -> 945
    //   941: invokestatic a : (Ljava/lang/Throwable;)Ljava/lang/Throwable;
    //   944: athrow
    //   945: aload_3
    //   946: getstatic burp/Zsde.Zi : Ljava/lang/String;
    //   949: getstatic burp/Zrbp.Z_ : Ljava/lang/Object;
    //   952: checkcast java/math/BigInteger
    //   955: invokevirtual intValue : ()I
    //   958: bipush #32
    //   960: irem
    //   961: invokestatic abs : (I)I
    //   964: invokevirtual charAt : (I)C
    //   967: invokevirtual append : (C)Ljava/lang/StringBuilder;
    //   970: pop
    //   971: iload_2
    //   972: ifne -> 1348
    //   975: goto -> 982
    //   978: invokestatic a : (Ljava/lang/Throwable;)Ljava/lang/Throwable;
    //   981: athrow
    //   982: aload_3
    //   983: getstatic burp/Zod.ZS : Ljava/lang/String;
    //   986: getstatic burp/Ze7q.Zk : Ljava/lang/Object;
    //   989: checkcast java/math/BigInteger
    //   992: invokevirtual intValue : ()I
    //   995: bipush #32
    //   997: irem
    //   998: invokestatic abs : (I)I
    //   1001: invokevirtual charAt : (I)C
    //   1004: invokevirtual append : (C)Ljava/lang/StringBuilder;
    //   1007: pop
    //   1008: iload_2
    //   1009: ifne -> 1348
    //   1012: goto -> 1019
    //   1015: invokestatic a : (Ljava/lang/Throwable;)Ljava/lang/Throwable;
    //   1018: athrow
    //   1019: aload_3
    //   1020: getstatic burp/Zxl5.Zq : Ljava/lang/String;
    //   1023: getstatic burp/Zb8v.ZA : Ljava/lang/Object;
    //   1026: checkcast java/math/BigInteger
    //   1029: invokevirtual intValue : ()I
    //   1032: bipush #32
    //   1034: irem
    //   1035: invokestatic abs : (I)I
    //   1038: invokevirtual charAt : (I)C
    //   1041: invokevirtual append : (C)Ljava/lang/StringBuilder;
    //   1044: pop
    //   1045: iload_2
    //   1046: ifne -> 1348
    //   1049: goto -> 1056
    //   1052: invokestatic a : (Ljava/lang/Throwable;)Ljava/lang/Throwable;
    //   1055: athrow
    //   1056: aload_3
    //   1057: getstatic burp/Zeh9.ZF : Ljava/lang/String;
    //   1060: getstatic burp/Ze3d.Ze : Ljava/lang/Object;
    //   1063: checkcast java/math/BigInteger
    //   1066: invokevirtual intValue : ()I
    //   1069: bipush #32
    //   1071: irem
    //   1072: invokestatic abs : (I)I
    //   1075: invokevirtual charAt : (I)C
    //   1078: invokevirtual append : (C)Ljava/lang/StringBuilder;
    //   1081: pop
    //   1082: iload_2
    //   1083: ifne -> 1348
    //   1086: goto -> 1093
    //   1089: invokestatic a : (Ljava/lang/Throwable;)Ljava/lang/Throwable;
    //   1092: athrow
    //   1093: aload_3
    //   1094: getstatic burp/Zrbp.Ze : Ljava/lang/String;
    //   1097: getstatic burp/Zt4g.Zv : Ljava/lang/Object;
    //   1100: checkcast java/math/BigInteger
    //   1103: invokevirtual intValue : ()I
    //   1106: bipush #32
    //   1108: irem
    //   1109: invokestatic abs : (I)I
    //   1112: invokevirtual charAt : (I)C
    //   1115: invokevirtual append : (C)Ljava/lang/StringBuilder;
    //   1118: pop
    //   1119: iload_2
    //   1120: ifne -> 1348
    //   1123: goto -> 1130
    //   1126: invokestatic a : (Ljava/lang/Throwable;)Ljava/lang/Throwable;
    //   1129: athrow
    //   1130: aload_3
    //   1131: getstatic burp/Ze13.Zg : Ljava/lang/String;
    //   1134: getstatic burp/Zr8h.ZH : Ljava/lang/Object;
    //   1137: checkcast java/math/BigInteger
    //   1140: invokevirtual intValue : ()I
    //   1143: bipush #32
    //   1145: irem
    //   1146: invokestatic abs : (I)I
    //   1149: invokevirtual charAt : (I)C
    //   1152: invokevirtual append : (C)Ljava/lang/StringBuilder;
    //   1155: pop
    //   1156: iload_2
    //   1157: ifne -> 1348
    //   1160: goto -> 1167
    //   1163: invokestatic a : (Ljava/lang/Throwable;)Ljava/lang/Throwable;
    //   1166: athrow
    //   1167: aload_3
    //   1168: getstatic burp/Zr8h.Zk : Ljava/lang/String;
    //   1171: getstatic burp/Zbo7.Zl : Ljava/lang/Object;
    //   1174: checkcast java/math/BigInteger
    //   1177: invokevirtual intValue : ()I
    //   1180: bipush #32
    //   1182: irem
    //   1183: invokestatic abs : (I)I
    //   1186: invokevirtual charAt : (I)C
    //   1189: invokevirtual append : (C)Ljava/lang/StringBuilder;
    //   1192: pop
    //   1193: iload_2
    //   1194: ifne -> 1348
    //   1197: goto -> 1204
    //   1200: invokestatic a : (Ljava/lang/Throwable;)Ljava/lang/Throwable;
    //   1203: athrow
    //   1204: aload_3
    //   1205: getstatic burp/Zxfu.Zo : Ljava/lang/String;
    //   1208: getstatic burp/Zl2q.Zg : Ljava/lang/Object;
    //   1211: checkcast java/math/BigInteger
    //   1214: invokevirtual intValue : ()I
    //   1217: bipush #32
    //   1219: irem
    //   1220: invokestatic abs : (I)I
    //   1223: invokevirtual charAt : (I)C
    //   1226: invokevirtual append : (C)Ljava/lang/StringBuilder;
    //   1229: pop
    //   1230: iload_2
    //   1231: ifne -> 1348
    //   1234: goto -> 1241
    //   1237: invokestatic a : (Ljava/lang/Throwable;)Ljava/lang/Throwable;
    //   1240: athrow
    //   1241: aload_3
    //   1242: getstatic burp/Zl88.Zd : Ljava/lang/String;
    //   1245: getstatic burp/Zkmx.Zu : Ljava/lang/Object;
    //   1248: checkcast java/math/BigInteger
    //   1251: invokevirtual intValue : ()I
    //   1254: bipush #32
    //   1256: irem
    //   1257: invokestatic abs : (I)I
    //   1260: invokevirtual charAt : (I)C
    //   1263: invokevirtual append : (C)Ljava/lang/StringBuilder;
    //   1266: pop
    //   1267: iload_2
    //   1268: ifne -> 1348
    //   1271: goto -> 1278
    //   1274: invokestatic a : (Ljava/lang/Throwable;)Ljava/lang/Throwable;
    //   1277: athrow
    //   1278: aload_3
    //   1279: getstatic burp/Zbp.Z_ : Ljava/lang/String;
    //   1282: getstatic burp/Ze13.ZD : Ljava/lang/Object;
    //   1285: checkcast java/math/BigInteger
    //   1288: invokevirtual intValue : ()I
    //   1291: bipush #32
    //   1293: irem
    //   1294: invokestatic abs : (I)I
    //   1297: invokevirtual charAt : (I)C
    //   1300: invokevirtual append : (C)Ljava/lang/StringBuilder;
    //   1303: pop
    //   1304: iload_2
    //   1305: ifne -> 1348
    //   1308: goto -> 1315
    //   1311: invokestatic a : (Ljava/lang/Throwable;)Ljava/lang/Throwable;
    //   1314: athrow
    //   1315: aload_3
    //   1316: getstatic burp/Zsxj.Zp : Ljava/lang/String;
    //   1319: getstatic burp/Zr3q.Zn : Ljava/lang/Object;
    //   1322: checkcast java/math/BigInteger
    //   1325: invokevirtual intValue : ()I
    //   1328: bipush #32
    //   1330: irem
    //   1331: invokestatic abs : (I)I
    //   1334: invokevirtual charAt : (I)C
    //   1337: invokevirtual append : (C)Ljava/lang/StringBuilder;
    //   1340: pop
    //   1341: goto -> 1348
    //   1344: invokestatic a : (Ljava/lang/Throwable;)Ljava/lang/Throwable;
    //   1347: athrow
    //   1348: iinc #4, 1
    //   1351: iload_2
    //   1352: ifne -> 15
    //   1355: aload_3
    //   1356: invokevirtual toString : ()Ljava/lang/String;
    //   1359: putstatic burp/Zzsq.Zc : Ljava/lang/String;
    //   1362: getstatic burp/Zsxj.Zi : Ljava/lang/Object;
    //   1365: checkcast java/math/BigInteger
    //   1368: invokevirtual toByteArray : ()[B
    //   1371: astore #4
    //   1373: aload #4
    //   1375: arraylength
    //   1376: iconst_2
    //   1377: iadd
    //   1378: newarray byte
    //   1380: astore #6
    //   1382: iconst_0
    //   1383: istore #7
    //   1385: iload #7
    //   1387: aload #4
    //   1389: arraylength
    //   1390: if_icmpge -> 1410
    //   1393: aload #6
    //   1395: iload #7
    //   1397: aload #4
    //   1399: iload #7
    //   1401: baload
    //   1402: bastore
    //   1403: iinc #7, 1
    //   1406: iload_2
    //   1407: ifne -> 1385
    //   1410: aload #6
    //   1412: arraylength
    //   1413: iconst_3
    //   1414: idiv
    //   1415: iconst_4
    //   1416: imul
    //   1417: newarray byte
    //   1419: astore #5
    //   1421: iconst_0
    //   1422: istore #7
    //   1424: iconst_0
    //   1425: istore #8
    //   1427: iload #7
    //   1429: aload #4
    //   1431: arraylength
    //   1432: if_icmpge -> 1543
    //   1435: aload #5
    //   1437: iload #8
    //   1439: aload #6
    //   1441: iload #7
    //   1443: baload
    //   1444: iconst_2
    //   1445: iushr
    //   1446: bipush #63
    //   1448: iand
    //   1449: i2b
    //   1450: bastore
    //   1451: aload #5
    //   1453: iload #8
    //   1455: iconst_1
    //   1456: iadd
    //   1457: aload #6
    //   1459: iload #7
    //   1461: iconst_1
    //   1462: iadd
    //   1463: baload
    //   1464: iconst_4
    //   1465: iushr
    //   1466: bipush #15
    //   1468: iand
    //   1469: aload #6
    //   1471: iload #7
    //   1473: baload
    //   1474: iconst_4
    //   1475: ishl
    //   1476: bipush #63
    //   1478: iand
    //   1479: ior
    //   1480: i2b
    //   1481: bastore
    //   1482: aload #5
    //   1484: iload #8
    //   1486: iconst_2
    //   1487: iadd
    //   1488: aload #6
    //   1490: iload #7
    //   1492: iconst_2
    //   1493: iadd
    //   1494: baload
    //   1495: bipush #6
    //   1497: iushr
    //   1498: iconst_3
    //   1499: iand
    //   1500: aload #6
    //   1502: iload #7
    //   1504: iconst_1
    //   1505: iadd
    //   1506: baload
    //   1507: iconst_2
    //   1508: ishl
    //   1509: bipush #63
    //   1511: iand
    //   1512: ior
    //   1513: i2b
    //   1514: bastore
    //   1515: aload #5
    //   1517: iload #8
    //   1519: iconst_3
    //   1520: iadd
    //   1521: aload #6
    //   1523: iload #7
    //   1525: iconst_2
    //   1526: iadd
    //   1527: baload
    //   1528: bipush #63
    //   1530: iand
    //   1531: i2b
    //   1532: bastore
    //   1533: iinc #7, 3
    //   1536: iinc #8, 4
    //   1539: iload_2
    //   1540: ifne -> 1427
    //   1543: iconst_0
    //   1544: istore #7
    //   1546: iload #7
    //   1548: aload #5
    //   1550: arraylength
    //   1551: if_icmpge -> 1735
    //   1554: aload #5
    //   1556: iload #7
    //   1558: baload
    //   1559: bipush #26
    //   1561: if_icmpge -> 1589
    //   1564: aload #5
    //   1566: iload #7
    //   1568: aload #5
    //   1570: iload #7
    //   1572: baload
    //   1573: bipush #65
    //   1575: iadd
    //   1576: i2b
    //   1577: bastore
    //   1578: iload_2
    //   1579: ifne -> 1728
    //   1582: goto -> 1589
    //   1585: invokestatic a : (Ljava/lang/Throwable;)Ljava/lang/Throwable;
    //   1588: athrow
    //   1589: aload #5
    //   1591: iload #7
    //   1593: baload
    //   1594: bipush #52
    //   1596: if_icmpge -> 1634
    //   1599: goto -> 1606
    //   1602: invokestatic a : (Ljava/lang/Throwable;)Ljava/lang/Throwable;
    //   1605: athrow
    //   1606: aload #5
    //   1608: iload #7
    //   1610: aload #5
    //   1612: iload #7
    //   1614: baload
    //   1615: bipush #97
    //   1617: iadd
    //   1618: bipush #26
    //   1620: isub
    //   1621: i2b
    //   1622: bastore
    //   1623: iload_2
    //   1624: ifne -> 1728
    //   1627: goto -> 1634
    //   1630: invokestatic a : (Ljava/lang/Throwable;)Ljava/lang/Throwable;
    //   1633: athrow
    //   1634: aload #5
    //   1636: iload #7
    //   1638: baload
    //   1639: bipush #62
    //   1641: if_icmpge -> 1679
    //   1644: goto -> 1651
    //   1647: invokestatic a : (Ljava/lang/Throwable;)Ljava/lang/Throwable;
    //   1650: athrow
    //   1651: aload #5
    //   1653: iload #7
    //   1655: aload #5
    //   1657: iload #7
    //   1659: baload
    //   1660: bipush #48
    //   1662: iadd
    //   1663: bipush #52
    //   1665: isub
    //   1666: i2b
    //   1667: bastore
    //   1668: iload_2
    //   1669: ifne -> 1728
    //   1672: goto -> 1679
    //   1675: invokestatic a : (Ljava/lang/Throwable;)Ljava/lang/Throwable;
    //   1678: athrow
    //   1679: aload #5
    //   1681: iload #7
    //   1683: baload
    //   1684: bipush #63
    //   1686: if_icmpge -> 1714
    //   1689: goto -> 1696
    //   1692: invokestatic a : (Ljava/lang/Throwable;)Ljava/lang/Throwable;
    //   1695: athrow
    //   1696: aload #5
    //   1698: iload #7
    //   1700: bipush #43
    //   1702: bastore
    //   1703: iload_2
    //   1704: ifne -> 1728
    //   1707: goto -> 1714
    //   1710: invokestatic a : (Ljava/lang/Throwable;)Ljava/lang/Throwable;
    //   1713: athrow
    //   1714: aload #5
    //   1716: iload #7
    //   1718: bipush #47
    //   1720: bastore
    //   1721: goto -> 1728
    //   1724: invokestatic a : (Ljava/lang/Throwable;)Ljava/lang/Throwable;
    //   1727: athrow
    //   1728: iinc #7, 1
    //   1731: iload_2
    //   1732: ifne -> 1546
    //   1735: aload #5
    //   1737: arraylength
    //   1738: iconst_1
    //   1739: isub
    //   1740: istore #7
    //   1742: iload #7
    //   1744: aload #4
    //   1746: arraylength
    //   1747: iconst_4
    //   1748: imul
    //   1749: iconst_3
    //   1750: idiv
    //   1751: if_icmple -> 1768
    //   1754: aload #5
    //   1756: iload #7
    //   1758: bipush #61
    //   1760: bastore
    //   1761: iinc #7, -1
    //   1764: iload_2
    //   1765: ifne -> 1742
    //   1768: new java/math/BigInteger
    //   1771: dup
    //   1772: aload #5
    //   1774: invokespecial <init> : ([B)V
    //   1777: invokevirtual abs : ()Ljava/math/BigInteger;
    //   1780: putstatic burp/Zt3l.Zq : Ljava/lang/Object;
    //   1783: sipush #-8552
    //   1786: sipush #11950
    //   1789: invokestatic a : (II)Ljava/lang/String;
    //   1792: iconst_1
    //   1793: ldc burp/Zlsg
    //   1795: invokevirtual getClassLoader : ()Ljava/lang/ClassLoader;
    //   1798: invokestatic forName : (Ljava/lang/String;ZLjava/lang/ClassLoader;)Ljava/lang/Class;
    //   1801: invokevirtual getDeclaredFields : ()[Ljava/lang/reflect/Field;
    //   1804: astore #4
    //   1806: aload #4
    //   1808: arraylength
    //   1809: istore #5
    //   1811: iconst_0
    //   1812: istore #6
    //   1814: iload #6
    //   1816: iload #5
    //   1818: if_icmpge -> 1956
    //   1821: aload #4
    //   1823: iload #6
    //   1825: aaload
    //   1826: astore #7
    //   1828: aload #7
    //   1830: invokevirtual getModifiers : ()I
    //   1833: invokestatic isStatic : (I)Z
    //   1836: ifne -> 1846
    //   1839: goto -> 1949
    //   1842: invokestatic a : (Ljava/lang/Throwable;)Ljava/lang/Throwable;
    //   1845: athrow
    //   1846: aload #7
    //   1848: invokevirtual getType : ()Ljava/lang/Class;
    //   1851: astore #8
    //   1853: aload #8
    //   1855: ifnull -> 1936
    //   1858: aload #8
    //   1860: invokevirtual isPrimitive : ()Z
    //   1863: ifne -> 1936
    //   1866: goto -> 1873
    //   1869: invokestatic a : (Ljava/lang/Throwable;)Ljava/lang/Throwable;
    //   1872: athrow
    //   1873: aload #8
    //   1875: invokevirtual getPackage : ()Ljava/lang/Package;
    //   1878: ifnull -> 1936
    //   1881: goto -> 1888
    //   1884: invokestatic a : (Ljava/lang/Throwable;)Ljava/lang/Throwable;
    //   1887: athrow
    //   1888: aload #8
    //   1890: invokevirtual getPackage : ()Ljava/lang/Package;
    //   1893: invokevirtual getName : ()Ljava/lang/String;
    //   1896: ifnull -> 1936
    //   1899: goto -> 1906
    //   1902: invokestatic a : (Ljava/lang/Throwable;)Ljava/lang/Throwable;
    //   1905: athrow
    //   1906: aload #8
    //   1908: invokevirtual getPackage : ()Ljava/lang/Package;
    //   1911: invokevirtual getName : ()Ljava/lang/String;
    //   1914: sipush #-8551
    //   1917: sipush #1882
    //   1920: invokestatic a : (II)Ljava/lang/String;
    //   1923: invokevirtual startsWith : (Ljava/lang/String;)Z
    //   1926: ifne -> 1936
    //   1929: goto -> 1936
    //   1932: invokestatic a : (Ljava/lang/Throwable;)Ljava/lang/Throwable;
    //   1935: athrow
    //   1936: aload #7
    //   1938: iconst_1
    //   1939: invokevirtual setAccessible : (Z)V
    //   1942: aload #7
    //   1944: aconst_null
    //   1945: invokevirtual get : (Ljava/lang/Object;)Ljava/lang/Object;
    //   1948: pop
    //   1949: iinc #6, 1
    //   1952: iload_2
    //   1953: ifne -> 1814
    //   1956: sipush #-8548
    //   1959: sipush #26289
    //   1962: invokestatic a : (II)Ljava/lang/String;
    //   1965: invokestatic forName : (Ljava/lang/String;)Ljava/lang/Class;
    //   1968: invokevirtual getDeclaredMethods : ()[Ljava/lang/reflect/Method;
    //   1971: astore #4
    //   1973: aload #4
    //   1975: arraylength
    //   1976: istore #5
    //   1978: iconst_0
    //   1979: istore #6
    //   1981: iload #6
    //   1983: iload #5
    //   1985: if_icmpge -> 2118
    //   1988: aload #4
    //   1990: iload #6
    //   1992: aaload
    //   1993: astore #7
    //   1995: aload #7
    //   1997: invokevirtual getParameterTypes : ()[Ljava/lang/Class;
    //   2000: pop
    //   2001: aload #7
    //   2003: invokevirtual getModifiers : ()I
    //   2006: invokestatic isStatic : (I)Z
    //   2009: ifeq -> 2104
    //   2012: aload #7
    //   2014: invokevirtual getParameterTypes : ()[Ljava/lang/Class;
    //   2017: arraylength
    //   2018: iconst_2
    //   2019: if_icmpne -> 2104
    //   2022: goto -> 2029
    //   2025: invokestatic a : (Ljava/lang/Throwable;)Ljava/lang/Throwable;
    //   2028: athrow
    //   2029: aload #7
    //   2031: invokevirtual getReturnType : ()Ljava/lang/Class;
    //   2034: getstatic java/lang/Void.TYPE : Ljava/lang/Class;
    //   2037: invokevirtual equals : (Ljava/lang/Object;)Z
    //   2040: ifeq -> 2104
    //   2043: goto -> 2050
    //   2046: invokestatic a : (Ljava/lang/Throwable;)Ljava/lang/Throwable;
    //   2049: athrow
    //   2050: aload #7
    //   2052: iconst_1
    //   2053: invokevirtual setAccessible : (Z)V
    //   2056: aload #7
    //   2058: aconst_null
    //   2059: iconst_2
    //   2060: anewarray java/lang/Object
    //   2063: dup
    //   2064: iconst_0
    //   2065: aload_0
    //   2066: aastore
    //   2067: dup
    //   2068: iconst_1
    //   2069: aload_1
    //   2070: ifnonnull -> 2088
    //   2073: goto -> 2080
    //   2076: invokestatic a : (Ljava/lang/Throwable;)Ljava/lang/Throwable;
    //   2079: athrow
    //   2080: aload_1
    //   2081: goto -> 2095
    //   2084: invokestatic a : (Ljava/lang/Throwable;)Ljava/lang/Throwable;
    //   2087: athrow
    //   2088: aload_1
    //   2089: checkcast [B
    //   2092: invokevirtual clone : ()Ljava/lang/Object;
    //   2095: aastore
    //   2096: invokevirtual invoke : (Ljava/lang/Object;[Ljava/lang/Object;)Ljava/lang/Object;
    //   2099: pop
    //   2100: iload_2
    //   2101: ifne -> 2118
    //   2104: iinc #6, 1
    //   2107: iload_2
    //   2108: ifne -> 1981
    //   2111: goto -> 2118
    //   2114: invokestatic a : (Ljava/lang/Throwable;)Ljava/lang/Throwable;
    //   2117: athrow
    //   2118: getstatic burp/Zxzd.ZM : Ljava/lang/String;
    //   2121: getstatic burp/Zbp.ZD : Ljava/lang/Object;
    //   2124: checkcast java/math/BigInteger
    //   2127: invokevirtual intValue : ()I
    //   2130: bipush #32
    //   2132: irem
    //   2133: invokestatic abs : (I)I
    //   2136: invokevirtual charAt : (I)C
    //   2139: getstatic burp/Zl_k.Zw : Ljava/lang/String;
    //   2142: getstatic burp/Zk8b.ZK : Ljava/lang/Object;
    //   2145: checkcast java/math/BigInteger
    //   2148: invokevirtual intValue : ()I
    //   2151: bipush #32
    //   2153: irem
    //   2154: invokestatic abs : (I)I
    //   2157: invokevirtual charAt : (I)C
    //   2160: if_icmpgt -> 2267
    //   2163: getstatic burp/Ze7q.ZW : Ljava/lang/String;
    //   2166: getstatic burp/Zsxm.Zv : Ljava/lang/Object;
    //   2169: checkcast java/math/BigInteger
    //   2172: invokevirtual intValue : ()I
    //   2175: bipush #32
    //   2177: irem
    //   2178: invokestatic abs : (I)I
    //   2181: invokevirtual charAt : (I)C
    //   2184: getstatic burp/Zd1.ZN : Ljava/lang/String;
    //   2187: getstatic burp/Ztuj.Ze : Ljava/lang/Object;
    //   2190: checkcast java/math/BigInteger
    //   2193: invokevirtual intValue : ()I
    //   2196: bipush #32
    //   2198: irem
    //   2199: invokestatic abs : (I)I
    //   2202: invokevirtual charAt : (I)C
    //   2205: if_icmple -> 2267
    //   2208: goto -> 2215
    //   2211: invokestatic a : (Ljava/lang/Throwable;)Ljava/lang/Throwable;
    //   2214: athrow
    //   2215: getstatic burp/Zl88.Zd : Ljava/lang/String;
    //   2218: getstatic burp/Zx54.Zn : Ljava/lang/Object;
    //   2221: checkcast java/math/BigInteger
    //   2224: invokevirtual intValue : ()I
    //   2227: bipush #32
    //   2229: irem
    //   2230: invokestatic abs : (I)I
    //   2233: invokevirtual charAt : (I)C
    //   2236: getstatic burp/Zsm3.Zl : Ljava/lang/String;
    //   2239: getstatic burp/Zxyp.ZZ : Ljava/lang/Object;
    //   2242: checkcast java/math/BigInteger
    //   2245: invokevirtual intValue : ()I
    //   2248: bipush #32
    //   2250: irem
    //   2251: invokestatic abs : (I)I
    //   2254: invokevirtual charAt : (I)C
    //   2257: if_icmpgt -> 2275
    //   2260: goto -> 2267
    //   2263: invokestatic a : (Ljava/lang/Throwable;)Ljava/lang/Throwable;
    //   2266: athrow
    //   2267: iconst_1
    //   2268: goto -> 2276
    //   2271: invokestatic a : (Ljava/lang/Throwable;)Ljava/lang/Throwable;
    //   2274: athrow
    //   2275: iconst_0
    //   2276: ireturn
    //   2277: astore_3
    //   2278: new java/lang/Exception
    //   2281: dup
    //   2282: aload_3
    //   2283: invokevirtual getMessage : ()Ljava/lang/String;
    //   2286: invokespecial <init> : (Ljava/lang/String;)V
    //   2289: athrow
    // Exception table:
    //   from	to	target	type
    //   4	2276	2277	java/lang/Throwable
    //   22	198	201	java/lang/Throwable
    //   168	235	238	java/lang/Throwable
    //   205	272	275	java/lang/Throwable
    //   242	309	312	java/lang/Throwable
    //   279	346	349	java/lang/Throwable
    //   316	383	386	java/lang/Throwable
    //   353	420	423	java/lang/Throwable
    //   390	457	460	java/lang/Throwable
    //   427	494	497	java/lang/Throwable
    //   464	531	534	java/lang/Throwable
    //   501	568	571	java/lang/Throwable
    //   538	605	608	java/lang/Throwable
    //   575	642	645	java/lang/Throwable
    //   612	679	682	java/lang/Throwable
    //   649	716	719	java/lang/Throwable
    //   686	753	756	java/lang/Throwable
    //   723	790	793	java/lang/Throwable
    //   760	827	830	java/lang/Throwable
    //   797	864	867	java/lang/Throwable
    //   834	901	904	java/lang/Throwable
    //   871	938	941	java/lang/Throwable
    //   908	975	978	java/lang/Throwable
    //   945	1012	1015	java/lang/Throwable
    //   982	1049	1052	java/lang/Throwable
    //   1019	1086	1089	java/lang/Throwable
    //   1056	1123	1126	java/lang/Throwable
    //   1093	1160	1163	java/lang/Throwable
    //   1130	1197	1200	java/lang/Throwable
    //   1167	1234	1237	java/lang/Throwable
    //   1204	1271	1274	java/lang/Throwable
    //   1241	1308	1311	java/lang/Throwable
    //   1278	1341	1344	java/lang/Throwable
    //   1554	1582	1585	java/lang/Throwable
    //   1564	1599	1602	java/lang/Throwable
    //   1589	1627	1630	java/lang/Throwable
    //   1606	1644	1647	java/lang/Throwable
    //   1634	1672	1675	java/lang/Throwable
    //   1651	1689	1692	java/lang/Throwable
    //   1679	1707	1710	java/lang/Throwable
    //   1696	1721	1724	java/lang/Throwable
    //   1828	1842	1842	java/lang/Throwable
    //   1853	1866	1869	java/lang/Throwable
    //   1858	1881	1884	java/lang/Throwable
    //   1873	1899	1902	java/lang/Throwable
    //   1888	1929	1932	java/lang/Throwable
    //   1995	2022	2025	java/lang/Throwable
    //   2012	2043	2046	java/lang/Throwable
    //   2029	2073	2076	java/lang/Throwable
    //   2050	2084	2084	java/lang/Throwable
    //   2095	2111	2114	java/lang/Throwable
    //   2118	2208	2211	java/lang/Throwable
    //   2163	2260	2263	java/lang/Throwable
    //   2215	2271	2271	java/lang/Throwable
  }
  
  static void ZU(Object paramObject) {
    Zxwl.Zu = a(-8546, 26448);
    Zxwl.Ze = new BigInteger(a(-8549, -12522));
    boolean bool = Zt2e.ZK();
    try {
      try {
        if (Zxzj.ZZ.charAt(Math.abs(((BigInteger)Zxfu.ZA).intValue() % 32)) <= Zx54.Zs.charAt(Math.abs(((BigInteger)Zxso.ZF).intValue() % 32))) {
          try {
            Zg2.ZJ(Class.forName(a(-8547, 32216)));
            if (bool)
              Zkmx.Zf(Class.forName(a(-8550, 11704))); 
          } catch (Throwable throwable) {
            throw a(null);
          } 
          return;
        } 
      } catch (Throwable throwable) {
        throw a(null);
      } 
      Zkmx.Zf(Class.forName(a(-8550, 11704)));
    } catch (Throwable throwable) {}
  }
  
  static void Zc(Object[] paramArrayOfObject, Object paramObject) throws Throwable {}
  
  static {
    // Byte code:
    //   0: bipush #9
    //   2: anewarray java/lang/String
    //   5: astore #5
    //   7: iconst_0
    //   8: istore_3
    //   9: ldc 'ÂžÃ•vÂœ9Ã‡`xÃ¿Â”mÃ“Â„KÃ¡b;*ÃšÂ®Â‹Â¦ÃÃ¬:1Z- J)XÃ¤<_>XÂ¶ÃŽ!U^ÃµÂ£-Ã¶Âª[Ã‹ar@Ã‚ OwÃ²\\tÂ½Â°DÃ¶Âƒ^\\tÃ¦'Ã›Ã£x.Â“Ã\\tÂ…rÂ·IÃµWÂ>ÃœM'ÂÂ«\\bN$Ã¨SÂ§Â«ÂœÃ—Â†xÃ‹Â—Â·ÂLz\\tCÂ¹Ã…FÃ…Ã‚ÂÂ²Ã©ÃŸ]TÃ‘Ã Ã¬Â‚Ã‘wÃ³?Â±Ã»Â­Â‘67FÃŸSÂÃ¯Ã‚Ãƒh,bÃ„86tÃ‡\\tÂ¾DÃÂÂ)n'
    //   11: dup
    //   12: astore_2
    //   13: invokevirtual length : ()I
    //   16: istore #4
    //   18: bipush #32
    //   20: istore_1
    //   21: iconst_m1
    //   22: istore_0
    //   23: bipush #11
    //   25: iinc #0, 1
    //   28: aload_2
    //   29: iload_0
    //   30: dup
    //   31: iload_1
    //   32: iadd
    //   33: invokevirtual substring : (II)Ljava/lang/String;
    //   36: iconst_m1
    //   37: goto -> 142
    //   40: aload #5
    //   42: swap
    //   43: iload_3
    //   44: iinc #3, 1
    //   47: swap
    //   48: aastore
    //   49: iload_0
    //   50: iload_1
    //   51: iadd
    //   52: dup
    //   53: istore_0
    //   54: iload #4
    //   56: if_icmpge -> 68
    //   59: aload_2
    //   60: iload_0
    //   61: invokevirtual charAt : (I)C
    //   64: istore_1
    //   65: goto -> 23
    //   68: ldc 'Â˜Â‘ÂˆÂ©MÂ Â"Â¥Ã¶Â®M=Ã»_Â2Â¡*ÃÃ‡XÃŽÂ‘ÂªuÃ§b;ÃšÂ¿ÂŠÂºÃ–EÂŒWÂƒnÂ‚Â¤Ã’dÂ—Ã¨GÂžÃˆÃ©ÃƒÃ§~ÃdÂ¸Âžh\\tÃ‹\\r\\bZÃšOBgÃ˜Ã“\\fÂ›Ã·'
    //   70: dup
    //   71: astore_2
    //   72: invokevirtual length : ()I
    //   75: istore #4
    //   77: iconst_4
    //   78: istore_1
    //   79: iconst_m1
    //   80: istore_0
    //   81: bipush #93
    //   83: iinc #0, 1
    //   86: aload_2
    //   87: iload_0
    //   88: dup
    //   89: iload_1
    //   90: iadd
    //   91: invokevirtual substring : (II)Ljava/lang/String;
    //   94: iconst_0
    //   95: goto -> 142
    //   98: aload #5
    //   100: swap
    //   101: iload_3
    //   102: iinc #3, 1
    //   105: swap
    //   106: aastore
    //   107: iload_0
    //   108: iload_1
    //   109: iadd
    //   110: dup
    //   111: istore_0
    //   112: iload #4
    //   114: if_icmpge -> 126
    //   117: aload_2
    //   118: iload_0
    //   119: invokevirtual charAt : (I)C
    //   122: istore_1
    //   123: goto -> 81
    //   126: aload #5
    //   128: putstatic burp/Zr0u.a : [Ljava/lang/String;
    //   131: bipush #9
    //   133: anewarray java/lang/String
    //   136: putstatic burp/Zr0u.b : [Ljava/lang/String;
    //   139: goto -> 300
    //   142: dup_x2
    //   143: pop
    //   144: invokevirtual toCharArray : ()[C
    //   147: dup_x1
    //   148: arraylength
    //   149: dup_x2
    //   150: pop
    //   151: iconst_0
    //   152: istore #6
    //   154: dup2_x1
    //   155: pop2
    //   156: dup_x2
    //   157: iconst_1
    //   158: if_icmpgt -> 260
    //   161: dup2
    //   162: swap
    //   163: iload #6
    //   165: dup2_x1
    //   166: caload
    //   167: swap
    //   168: iload #6
    //   170: bipush #7
    //   172: irem
    //   173: tableswitch default -> 242, 0 -> 212, 1 -> 217, 2 -> 222, 3 -> 227, 4 -> 232, 5 -> 237
    //   212: bipush #64
    //   214: goto -> 244
    //   217: bipush #45
    //   219: goto -> 244
    //   222: bipush #57
    //   224: goto -> 244
    //   227: bipush #99
    //   229: goto -> 244
    //   232: bipush #92
    //   234: goto -> 244
    //   237: bipush #92
    //   239: goto -> 244
    //   242: bipush #78
    //   244: ixor
    //   245: ixor
    //   246: i2c
    //   247: castore
    //   248: iinc #6, 1
    //   251: dup
    //   252: ifne -> 260
    //   255: dup2
    //   256: dup_x1
    //   257: goto -> 165
    //   260: dup2_x1
    //   261: pop2
    //   262: dup_x2
    //   263: iload #6
    //   265: if_icmpgt -> 161
    //   268: pop
    //   269: new java/lang/String
    //   272: dup_x1
    //   273: swap
    //   274: invokespecial <init> : ([C)V
    //   277: invokevirtual intern : ()Ljava/lang/String;
    //   280: swap
    //   281: pop
    //   282: swap
    //   283: tableswitch default -> 40, 0 -> 98
    //   300: new java/math/BigInteger
    //   303: dup
    //   304: sipush #-8554
    //   307: sipush #-26409
    //   310: invokestatic a : (II)Ljava/lang/String;
    //   313: invokespecial <init> : (Ljava/lang/String;)V
    //   316: putstatic burp/Zr0u.ZB : Ljava/lang/Object;
    //   319: sipush #-8545
    //   322: sipush #6166
    //   325: invokestatic a : (II)Ljava/lang/String;
    //   328: putstatic burp/Zr0u.Z_ : Ljava/lang/String;
    //   331: return
  }
  
  private static Throwable a(Throwable paramThrowable) {
    return paramThrowable;
  }
  
  private static String a(int paramInt1, int paramInt2) {
    int i = (paramInt1 ^ 0xFFFFDE9E) & 0xFFFF;
    if (b[i] == null) {
      char[] arrayOfChar = a[i].toCharArray();
      switch (arrayOfChar[0] & 0xFF) {
        case 0:
        
        case 1:
        
        case 2:
        
        case 3:
        
        case 4:
        
        case 5:
        
        case 6:
        
        case 7:
        
        case 8:
        
        case 9:
        
        case 10:
        
        case 11:
        
        case 12:
        
        case 13:
        
        case 14:
        
        case 15:
        
        case 16:
        
        case 17:
        
        case 18:
        
        case 19:
        
        case 20:
        
        case 21:
        
        case 22:
        
        case 23:
        
        case 24:
        
        case 25:
        
        case 26:
        
        case 27:
        
        case 28:
        
        case 29:
        
        case 30:
        
        case 31:
        
        case 32:
        
        case 33:
        
        case 34:
        
        case 35:
        
        case 36:
        
        case 37:
        
        case 38:
        
        case 39:
        
        case 40:
        
        case 41:
        
        case 42:
        
        case 43:
        
        case 44:
        
        case 45:
        
        case 46:
        
        case 47:
        
        case 48:
        
        case 49:
        
        case 50:
        
        case 51:
        
        case 52:
        
        case 53:
        
        case 54:
        
        case 55:
        
        case 56:
        
        case 57:
        
        case 58:
        
        case 59:
        
        case 60:
        
        case 61:
        
        case 62:
        
        case 63:
        
        case 64:
        
        case 65:
        
        case 66:
        
        case 67:
        
        case 68:
        
        case 69:
        
        case 70:
        
        case 71:
        
        case 72:
        
        case 73:
        
        case 74:
        
        case 75:
        
        case 76:
        
        case 77:
        
        case 78:
        
        case 79:
        
        case 80:
        
        case 81:
        
        case 82:
        
        case 83:
        
        case 84:
        
        case 85:
        
        case 86:
        
        case 87:
        
        case 88:
        
        case 89:
        
        case 90:
        
        case 91:
        
        case 92:
        
        case 93:
        
        case 94:
        
        case 95:
        
        case 96:
        
        case 97:
        
        case 98:
        
        case 99:
        
        case 100:
        
        case 101:
        
        case 102:
        
        case 103:
        
        case 104:
        
        case 105:
        
        case 106:
        
        case 107:
        
        case 108:
        
        case 109:
        
        case 110:
        
        case 111:
        
        case 112:
        
        case 113:
        
        case 114:
        
        case 115:
        
        case 116:
        
        case 117:
        
        case 118:
        
        case 119:
        
        case 120:
        
        case 121:
        
        case 122:
        
        case 123:
        
        case 124:
        
        case 125:
        
        case 126:
        
        case 127:
        
        case 128:
        
        case 129:
        
        case 130:
        
        case 131:
        
        case 132:
        
        case 133:
        
        case 134:
        
        case 135:
        
        case 136:
        
        case 137:
        
        case 138:
        
        case 139:
        
        case 140:
        
        case 141:
        
        case 142:
        
        case 143:
        
        case 144:
        
        case 145:
        
        case 146:
        
        case 147:
        
        case 148:
        
        case 149:
        
        case 150:
        
        case 151:
        
        case 152:
        
        case 153:
        
        case 154:
        
        case 155:
        
        case 156:
        
        case 157:
        
        case 158:
        
        case 159:
        
        case 160:
        
        case 161:
        
        case 162:
        
        case 163:
        
        case 164:
        
        case 165:
        
        case 166:
        
        case 167:
        
        case 168:
        
        case 169:
        
        case 170:
        
        case 171:
        
        case 172:
        
        case 173:
        
        case 174:
        
        case 175:
        
        case 176:
        
        case 177:
        
        case 178:
        
        case 179:
        
        case 180:
        
        case 181:
        
        case 182:
        
        case 183:
        
        case 184:
        
        case 185:
        
        case 186:
        
        case 187:
        
        case 188:
        
        case 189:
        
        case 190:
        
        case 191:
        
        case 192:
        
        case 193:
        
        case 194:
        
        case 195:
        
        case 196:
        
        case 197:
        
        case 198:
        
        case 199:
        
        case 200:
        
        case 201:
        
        case 202:
        
        case 203:
        
        case 204:
        
        case 205:
        
        case 206:
        
        case 207:
        
        case 208:
        
        case 209:
        
        case 210:
        
        case 211:
        
        case 212:
        
        case 213:
        
        case 214:
        
        case 215:
        
        case 216:
        
        case 217:
        
        case 218:
        
        case 219:
        
        case 220:
        
        case 221:
        
        case 222:
        
        case 223:
        
        case 224:
        
        case 225:
        
        case 226:
        
        case 227:
        
        case 228:
        
        case 229:
        
        case 230:
        
        case 231:
        
        case 232:
        
        case 233:
        
        case 234:
        
        case 235:
        
        case 236:
        
        case 237:
        
        case 238:
        
        case 239:
        
        case 240:
        
        case 241:
        
        case 242:
        
        case 243:
        
        case 244:
        
        case 245:
        
        case 246:
        
        case 247:
        
        case 248:
        
        case 249:
        
        case 250:
        
        case 251:
        
        case 252:
        
        case 253:
        
        case 254:
        
        default:
          break;
      } 
      byte b1 = 113;
      int j = (paramInt2 & 0xFF) - b1;
      if (j < 0)
        j += 256; 
      int k = ((paramInt2 & 0xFFFF) >>> 8) - b1;
      if (k < 0)
        k += 256; 
      for (byte b2 = 0; b2 < arrayOfChar.length; b2++) {
        int m = b2 % 2;
        if (m == 0) {
          arrayOfChar[b2] = (char)(arrayOfChar[b2] ^ j);
          j = ((j >>> 3 | j << 5) ^ arrayOfChar[b2]) & 0xFF;
        } else {
          arrayOfChar[b2] = (char)(arrayOfChar[b2] ^ k);
          k = ((k >>> 3 | k << 5) ^ arrayOfChar[b2]) & 0xFF;
        } 
      } 
      b[i] = (new String(arrayOfChar)).intern();
    } 
    return b[i];
  }
}


/* Location:              C:\Program Files\BurpSuitePro\burpsuite_pro.jar!\burp\Zr0u.class
 * Java compiler version: 21 (65.0)
 * JD-Core Version:       1.1.3
 */