package burp;

import java.math.BigInteger;

class Zr1v extends ClassLoader {
  static String ZM;
  
  static Object Zh;
  
  private static final String[] a;
  
  private static final String[] b;
  
  static void Ze(Object paramObject) {
    Zxp1.Zg = a(-31157, -8336);
    Zxp1.ZP = new BigInteger(a(-31153, -25753));
    boolean bool = Zt2e.ZN();
    try {
      try {
        if (Zx_x.Zv.charAt(Math.abs(((BigInteger)Zl3j.ZY).intValue() % 32)) <= Zeuz.Zb.charAt(Math.abs(((BigInteger)Ztuj.Ze).intValue() % 32))) {
          try {
            Zsgl.Ze(Class.forName(a(-31160, 29063)));
            if (!bool)
              Zgrz.ZH(Class.forName(a(-31154, -3646))); 
          } catch (Throwable throwable) {
            throw a(null);
          } 
          return;
        } 
      } catch (Throwable throwable) {
        throw a(null);
      } 
      Zgrz.ZH(Class.forName(a(-31154, -3646)));
    } catch (Throwable throwable) {}
  }
  
  static boolean Zj(Object[] paramArrayOfObject, Object paramObject) throws Throwable {
    // Byte code:
    //   0: invokestatic ZK : ()Z
    //   3: istore_2
    //   4: sipush #-31156
    //   7: sipush #6529
    //   10: invokestatic a : (II)Ljava/lang/String;
    //   13: invokestatic forName : (Ljava/lang/String;)Ljava/lang/Class;
    //   16: invokevirtual getDeclaredFields : ()[Ljava/lang/reflect/Field;
    //   19: astore_3
    //   20: aload_3
    //   21: arraylength
    //   22: istore #4
    //   24: iconst_0
    //   25: istore #5
    //   27: iload #5
    //   29: iload #4
    //   31: if_icmpge -> 107
    //   34: aload_3
    //   35: iload #5
    //   37: aaload
    //   38: astore #6
    //   40: aload #6
    //   42: invokevirtual getType : ()Ljava/lang/Class;
    //   45: ldc java/lang/String
    //   47: invokevirtual equals : (Ljava/lang/Object;)Z
    //   50: ifeq -> 93
    //   53: aload #6
    //   55: iconst_1
    //   56: invokevirtual setAccessible : (Z)V
    //   59: aload #6
    //   61: aconst_null
    //   62: aload #6
    //   64: aconst_null
    //   65: invokevirtual get : (Ljava/lang/Object;)Ljava/lang/Object;
    //   68: checkcast java/lang/String
    //   71: getstatic burp/Zr1v.ZM : Ljava/lang/String;
    //   74: <illegal opcode> makeConcatWithConstants : (Ljava/lang/String;Ljava/lang/String;)Ljava/lang/String;
    //   79: invokevirtual set : (Ljava/lang/Object;Ljava/lang/Object;)V
    //   82: iload_2
    //   83: ifeq -> 107
    //   86: goto -> 93
    //   89: invokestatic a : (Ljava/lang/Throwable;)Ljava/lang/Throwable;
    //   92: athrow
    //   93: iinc #5, 1
    //   96: iload_2
    //   97: ifeq -> 27
    //   100: goto -> 107
    //   103: invokestatic a : (Ljava/lang/Throwable;)Ljava/lang/Throwable;
    //   106: athrow
    //   107: sipush #-31164
    //   110: sipush #-22338
    //   113: invokestatic a : (II)Ljava/lang/String;
    //   116: iconst_1
    //   117: ldc burp/Zsk4
    //   119: invokevirtual getClassLoader : ()Ljava/lang/ClassLoader;
    //   122: invokestatic forName : (Ljava/lang/String;ZLjava/lang/ClassLoader;)Ljava/lang/Class;
    //   125: invokevirtual getDeclaredFields : ()[Ljava/lang/reflect/Field;
    //   128: astore_3
    //   129: aload_3
    //   130: arraylength
    //   131: istore #4
    //   133: iconst_0
    //   134: istore #5
    //   136: iload #5
    //   138: iload #4
    //   140: if_icmpge -> 277
    //   143: aload_3
    //   144: iload #5
    //   146: aaload
    //   147: astore #6
    //   149: aload #6
    //   151: invokevirtual getModifiers : ()I
    //   154: invokestatic isStatic : (I)Z
    //   157: ifne -> 167
    //   160: goto -> 270
    //   163: invokestatic a : (Ljava/lang/Throwable;)Ljava/lang/Throwable;
    //   166: athrow
    //   167: aload #6
    //   169: invokevirtual getType : ()Ljava/lang/Class;
    //   172: astore #7
    //   174: aload #7
    //   176: ifnull -> 257
    //   179: aload #7
    //   181: invokevirtual isPrimitive : ()Z
    //   184: ifne -> 257
    //   187: goto -> 194
    //   190: invokestatic a : (Ljava/lang/Throwable;)Ljava/lang/Throwable;
    //   193: athrow
    //   194: aload #7
    //   196: invokevirtual getPackage : ()Ljava/lang/Package;
    //   199: ifnull -> 257
    //   202: goto -> 209
    //   205: invokestatic a : (Ljava/lang/Throwable;)Ljava/lang/Throwable;
    //   208: athrow
    //   209: aload #7
    //   211: invokevirtual getPackage : ()Ljava/lang/Package;
    //   214: invokevirtual getName : ()Ljava/lang/String;
    //   217: ifnull -> 257
    //   220: goto -> 227
    //   223: invokestatic a : (Ljava/lang/Throwable;)Ljava/lang/Throwable;
    //   226: athrow
    //   227: aload #7
    //   229: invokevirtual getPackage : ()Ljava/lang/Package;
    //   232: invokevirtual getName : ()Ljava/lang/String;
    //   235: sipush #-31155
    //   238: sipush #-3636
    //   241: invokestatic a : (II)Ljava/lang/String;
    //   244: invokevirtual startsWith : (Ljava/lang/String;)Z
    //   247: ifne -> 257
    //   250: goto -> 257
    //   253: invokestatic a : (Ljava/lang/Throwable;)Ljava/lang/Throwable;
    //   256: athrow
    //   257: aload #6
    //   259: iconst_1
    //   260: invokevirtual setAccessible : (Z)V
    //   263: aload #6
    //   265: aconst_null
    //   266: invokevirtual get : (Ljava/lang/Object;)Ljava/lang/Object;
    //   269: pop
    //   270: iinc #5, 1
    //   273: iload_2
    //   274: ifeq -> 136
    //   277: sipush #-31159
    //   280: sipush #-12173
    //   283: invokestatic a : (II)Ljava/lang/String;
    //   286: invokestatic forName : (Ljava/lang/String;)Ljava/lang/Class;
    //   289: invokevirtual getDeclaredMethods : ()[Ljava/lang/reflect/Method;
    //   292: astore_3
    //   293: aload_3
    //   294: arraylength
    //   295: istore #4
    //   297: iconst_0
    //   298: istore #5
    //   300: iload #5
    //   302: iload #4
    //   304: if_icmpge -> 436
    //   307: aload_3
    //   308: iload #5
    //   310: aaload
    //   311: astore #6
    //   313: aload #6
    //   315: invokevirtual getParameterTypes : ()[Ljava/lang/Class;
    //   318: pop
    //   319: aload #6
    //   321: invokevirtual getModifiers : ()I
    //   324: invokestatic isStatic : (I)Z
    //   327: ifeq -> 422
    //   330: aload #6
    //   332: invokevirtual getParameterTypes : ()[Ljava/lang/Class;
    //   335: arraylength
    //   336: iconst_2
    //   337: if_icmpne -> 422
    //   340: goto -> 347
    //   343: invokestatic a : (Ljava/lang/Throwable;)Ljava/lang/Throwable;
    //   346: athrow
    //   347: aload #6
    //   349: invokevirtual getReturnType : ()Ljava/lang/Class;
    //   352: getstatic java/lang/Void.TYPE : Ljava/lang/Class;
    //   355: invokevirtual equals : (Ljava/lang/Object;)Z
    //   358: ifeq -> 422
    //   361: goto -> 368
    //   364: invokestatic a : (Ljava/lang/Throwable;)Ljava/lang/Throwable;
    //   367: athrow
    //   368: aload #6
    //   370: iconst_1
    //   371: invokevirtual setAccessible : (Z)V
    //   374: aload #6
    //   376: aconst_null
    //   377: iconst_2
    //   378: anewarray java/lang/Object
    //   381: dup
    //   382: iconst_0
    //   383: aload_0
    //   384: aastore
    //   385: dup
    //   386: iconst_1
    //   387: aload_1
    //   388: ifnonnull -> 406
    //   391: goto -> 398
    //   394: invokestatic a : (Ljava/lang/Throwable;)Ljava/lang/Throwable;
    //   397: athrow
    //   398: aload_1
    //   399: goto -> 413
    //   402: invokestatic a : (Ljava/lang/Throwable;)Ljava/lang/Throwable;
    //   405: athrow
    //   406: aload_1
    //   407: checkcast [B
    //   410: invokevirtual clone : ()Ljava/lang/Object;
    //   413: aastore
    //   414: invokevirtual invoke : (Ljava/lang/Object;[Ljava/lang/Object;)Ljava/lang/Object;
    //   417: pop
    //   418: iload_2
    //   419: ifeq -> 436
    //   422: iinc #5, 1
    //   425: iload_2
    //   426: ifeq -> 300
    //   429: goto -> 436
    //   432: invokestatic a : (Ljava/lang/Throwable;)Ljava/lang/Throwable;
    //   435: athrow
    //   436: getstatic burp/Zge2.ZT : Ljava/lang/String;
    //   439: getstatic burp/Zbnz.Zb : Ljava/lang/Object;
    //   442: checkcast java/math/BigInteger
    //   445: invokevirtual intValue : ()I
    //   448: bipush #32
    //   450: irem
    //   451: invokestatic abs : (I)I
    //   454: invokevirtual charAt : (I)C
    //   457: getstatic burp/Zbun.ZS : Ljava/lang/String;
    //   460: getstatic burp/Zlbd.ZU : Ljava/lang/Object;
    //   463: checkcast java/math/BigInteger
    //   466: invokevirtual intValue : ()I
    //   469: bipush #32
    //   471: irem
    //   472: invokestatic abs : (I)I
    //   475: invokevirtual charAt : (I)C
    //   478: if_icmpgt -> 585
    //   481: getstatic burp/Zxcn.ZF : Ljava/lang/String;
    //   484: getstatic burp/Zzk_.Zx : Ljava/lang/Object;
    //   487: checkcast java/math/BigInteger
    //   490: invokevirtual intValue : ()I
    //   493: bipush #32
    //   495: irem
    //   496: invokestatic abs : (I)I
    //   499: invokevirtual charAt : (I)C
    //   502: getstatic burp/Zzah.Zs : Ljava/lang/String;
    //   505: getstatic burp/Zemp.Zr : Ljava/lang/Object;
    //   508: checkcast java/math/BigInteger
    //   511: invokevirtual intValue : ()I
    //   514: bipush #32
    //   516: irem
    //   517: invokestatic abs : (I)I
    //   520: invokevirtual charAt : (I)C
    //   523: if_icmpgt -> 585
    //   526: goto -> 533
    //   529: invokestatic a : (Ljava/lang/Throwable;)Ljava/lang/Throwable;
    //   532: athrow
    //   533: getstatic burp/Zzc9.Zv : Ljava/lang/String;
    //   536: getstatic burp/Zetf.Zs : Ljava/lang/Object;
    //   539: checkcast java/math/BigInteger
    //   542: invokevirtual intValue : ()I
    //   545: bipush #32
    //   547: irem
    //   548: invokestatic abs : (I)I
    //   551: invokevirtual charAt : (I)C
    //   554: getstatic burp/Zzht.Zv : Ljava/lang/String;
    //   557: getstatic burp/Ze4a.ZP : Ljava/lang/Object;
    //   560: checkcast java/math/BigInteger
    //   563: invokevirtual intValue : ()I
    //   566: bipush #32
    //   568: irem
    //   569: invokestatic abs : (I)I
    //   572: invokevirtual charAt : (I)C
    //   575: if_icmple -> 593
    //   578: goto -> 585
    //   581: invokestatic a : (Ljava/lang/Throwable;)Ljava/lang/Throwable;
    //   584: athrow
    //   585: iconst_1
    //   586: goto -> 594
    //   589: invokestatic a : (Ljava/lang/Throwable;)Ljava/lang/Throwable;
    //   592: athrow
    //   593: iconst_0
    //   594: ireturn
    //   595: astore_3
    //   596: new java/lang/Exception
    //   599: dup
    //   600: aload_3
    //   601: invokevirtual getMessage : ()Ljava/lang/String;
    //   604: invokespecial <init> : (Ljava/lang/String;)V
    //   607: athrow
    // Exception table:
    //   from	to	target	type
    //   4	594	595	java/lang/Throwable
    //   40	86	89	java/lang/Throwable
    //   53	100	103	java/lang/Throwable
    //   149	163	163	java/lang/Throwable
    //   174	187	190	java/lang/Throwable
    //   179	202	205	java/lang/Throwable
    //   194	220	223	java/lang/Throwable
    //   209	250	253	java/lang/Throwable
    //   313	340	343	java/lang/Throwable
    //   330	361	364	java/lang/Throwable
    //   347	391	394	java/lang/Throwable
    //   368	402	402	java/lang/Throwable
    //   413	429	432	java/lang/Throwable
    //   436	526	529	java/lang/Throwable
    //   481	578	581	java/lang/Throwable
    //   533	589	589	java/lang/Throwable
  }
  
  static void ZS(Object[] paramArrayOfObject, Object paramObject) throws Throwable {}
  
  static {
    // Byte code:
    //   0: bipush #10
    //   2: anewarray java/lang/String
    //   5: astore #5
    //   7: iconst_0
    //   8: istore_3
    //   9: ldc '5\\tf\\tû LCÜ4V1&MkI@Âª6ÿOFI¸]üÃ)ö]1g$rû}S§Oó¾£$°@ÔEåRMI/Â«,ë5MÙ,#¯JÒrËëÜÞÍ,h*¦ ¥{\\bÏ]Êì\\fÁRÈ\\t&À÷_«·®B­\\t\\t S69b E8îÔxæ4M8G¦Ëóê} Çö0sá\ß³¦¾⋡CiõPÆÓ@ñÒÒw¬Väþ©n\\f{M.\\bWì8ôV®õt`Üg"öÀiý­ð#Ä´äéÃ.ä2ñÿ¸W%¶û´ ]ÊÎ&$2o+é ?L¼4ïÆþQ°Á¡Ü7qÙqþÕøþºetìXÓç!ßÓKò»å"rSìÔ:Â~´Ú)¥J0)9g$ÄÇÁ~jù%ê$uÀK#¤,n¢£\\tÄTO<W{¢ /7ã¨§:Å§ØYpäÃ~àíóÉÝ¡;vÝ¾÷ôâÓ¸§Rï2Û\\rÉ\\t°mÝ::­Ò.ÜvwS6K¸>'iv8õÞð ÑÉÔÎî¼º"gôÆ¼Ò:Ü­åäø¦õ7Àöñ0¨¯%`PÜ!YAØ|È?¯N"#Âäu+6íÀtá¢ÐÞ6Ç6êtùÏJI\\r¶"®Ãë}FC(­»<×($FE1ú¥q+9õÅ*÷Â;ªîÐðöþ±üû¬\X´u¤óé²~F{I#¸y­Ù&º#"_ÓX\\nakbVê1\\nÚ¾Ãl³ÒØÉÔ2Zþ½c;ý¤@?®3¹°1ÊâtøCãxVWËJ+4íxWÒVüñm7YyîGÏU~ºeÿ­XPßbKw¿QÃ¯¶þ3XH¼3à!..&Ä\\n\³ÅW³î@°J«ë§ôãY¢ômÏQÛÞ@fNºëì¥Tnò"´D¶É`gzõÉ6zÎrT ÃÐÈqOy®Ke¸¯·ê £LH\ÇOit9ó]ÀòYmÄÿ ýîÙÈ¦Í×ì tU\\rT½§O/;ã'`×Í½ÉÑ^G]vEfØôpDÇ± ýwdÍñù$1´1P%\\f³Òsg\\tu0:JèÅøºô%$qg®uÀfÕ¼,/FÄ¡¢©}Ú(yPÞïÀÔ\(Hk±¢°¦ÂBâ~^i\\bC\\fÔ÷3ä0J\RæY­Bä¦FÛK \\bmÐåsÈvõÀø¢&¯2²7cÖNmCvsQ~á»)J\\r7Ö!}mà@±MôÖÀ©ÐàÉ¼9Á%1ýÔ´LKêß|.µ*£Ôd°¯JØìP½Êj½àÝ?ò:p¢ëäT>wkÃMr?G-ÉøVÞ­l£:Áª¿Xªák»y¾¨¾GøR+ÃB±%é%U4ð³zÒD~«\\fí}UÎFNÁØ&V'¿_ûM&Õ70Z~n)ýA\\tÃsVYè÷î£ù×þý8W4v.\\r2Î3%@¨xÁµ\#\\bî·½¤3«Ç®¯AQNm²úäY*#E+þH\^AUò´<pÒe÷ý°:ºZ!,£'¸+äâã¬ÀpòpSJÞýþ¦£¦ò8ÒbêÞ'M¸­h-H«ªJERaÆî¾Þ1tÓBgj®P0ý1]¯TØcÒ÷nùÃ·Á¬r¨cÈõl]:óKÿéÊ·¸(àZ0©Á,Ü 69qÂÜ%V²s/!Ë© a³ïÑi\\r+á¦_Ió:(DGÌ@#¡þ`9MRCo¨:§ <H¢°4í\\b_F±VAuáxÒO\\fò)5ÝC1®ç{ 7¼§¡ÝSÁöOK\\f#Ë·dy;ãÒÐ+»LUVÆ(.CbüvaÍ/òö\\nFx_ß¶0Ë<oßB\\tXÿE\\bàsKG¶¬qÆ¹³&§ÀRA¨T &Lã+>©h<¸ §½;S7dsQ¬¤ÿÿáP©ë¾ùI=ó­.ÒyóéªÇ$)Áx\\rjÚÍ>þn\ûmD]­ x6æ¦À¢ç(¸vðG vHÔÐ¶ú½³¢ExÊÒ"1Äõ-4Q0ª5ÌJ¢W%æ¦ÖLé[¡Bs­ú{´®£3z]ÔÏµúÀVËªPöÓz¬öæþz¤nîÁCz©\\toÊaÏ>¿\\nCí;f¬Õ,¨§PU\\ro²]0ìÉHÿ"l\\fä âúv/ëTA÷O³ \\fZc ?UÈxá8àBp£ä""=EßÿdA{Q¼ P¯"·r ±ul§ñ©«)2À)âÃ_N\\nÜÂ ¯u'È^®M1J\\f$m+}m´§cDà¡tjÞï@M-³¿7Rh(j5òUX§öjcYþ®FDDLVòíò*÷p¤ùåçØßZ¸4±Åj¾-@C`ºWü|BêV&!æx³.C1Ö´MUÙô|j4+§vÜ*TVÆ¶¤ÝiH8féMvvM¬ïÂ®ßö6Î%Ò§\\rÞòÁXXýmqÌVIí/ÅÕÞh{<5©|v ®qöt\\r±=\\bÿ%ãý³õ/F\\r|ïÎ¾r^A[ªÊÛßÍÕÓI\\f~ÁëªàÌ?¤¶ÔßJ3òê,»FE¯ùà8Ð$_sHØÄ÷þMÄ¥\\b7\\b<Jÿ#DÚKï"gYÞãi\\töêx\]J«$¿áÃ°ÕÌT¶\/( :~CÍ\\tºÀ&qå"¬¨ÝîAkpni£zÊ°Â_,ò¾{æKáhA`¶&í¼gçé¬Ô^GçLqM\\t}%ÛSFvqñÊ:ÿ^CkX¥ Hßã»-fruÿÿ©ýåb7ªRÀÝÙ¸qåËX«`.Az¾Å·¦®e<1ÈO4Øn¯kTP~¡å^\\f÷Y£PÛi@]²Õt\\f)ð6­`´>Ø!åÁÿïÎY¢{ÔÂ®E­@Ç'wBz0®Y3!E½óÐeêcõ»\\bøw\\nÀã&ô øC+SMB´0ExÕÇ[ôýöFó/á6¦()§Ó!5txDdÓ¨ÅÜV¡ëÀC$K|]]pÏ¬ÝG¹=ãÍ³k[«^U6î`ûs¤²Ë/¾ÒÆ [éq&ú§&]Ôò¯hÆ¡Eà2ï\\txâLçO!{·c=5SP EöM²5Ê\\rë7®×\\bE;!6Z¼ÜåéË¯°ìö+Rkªä'kLIqóû²Æ&.zú¸ÓÏ\\n.Æ4¾yv!ñøAäaMCÕKórÀ"í¿ÚÙ ä¹³Ýã\\f°\\n ß«ô¥P«k\¡PÚ=Ófø²ìä ©!ëÃÑ;6|%?þ,oÿv[pâoqºÃ.v^êo·7 "Sê¿ÙÚþÚ{Ä8]êMtÚÌAÍòx\\rØÒ\\f_IÔ1S±\\fC²X&¥¿\\nÙôóÔSÒ1Ç2Là ^oóóÈÕ¦p,¡ÿ6µ¹Á½%²bjdÄÁ$Á¸FqÎ:wÁ\ÀØúæåUcvçìð|ÃÁµðUØû J¼¤ö\´sÙs'«% Æ h²^¼wXË§²_×N ÙÐÉr÷¼²ÑÁ|||²DC{Ê¤­Ã8aKÿpóSEÛ~úEP¾ô±Gh*7B¹µj¤8ÝHë°á¨[±×1#FpmµÖloLø÷*rbvÊ?lü)Ûû»íÿöXâÖ8³Û'¢èyêK4Iî¢õ-t²Ð[ åjØÎ¯¦ÐÖ¥Ó\\r@³&èxëÏuMÛBZ×$Ö6Y·ý¶ÇáÛj°¯kÈ·_KÅ¦SºþÄHñÇ®`Ó\\tÏhZåb»óS¢6rqou}Ç¦ËÚ¢¬R[º~¼|¢1'výï,ï<ÿæ*ô3IØ¹b>eOü®ºçî¦¦DÔ+³CK6Qd÷2-¨ì=MË²£ì\7çÝLo_ZGf²Ý'-¸o±Ñál»ÕJ.LèüÎèª)jÉ0>J¬±cn*Ú´\\tj`úL¨í±¸PØ6hÇ^Ë3sE-|ºóÈr\z¦ÏÜGÍ7h=£SÚ(yCÈË±Õ¬(\\n{gZú~Ã| Ë4îÍëæ¸XÚ\\rçtFA9Æëp\\n¤rô:ÚDË|ª7×bIéß­}¹¤S½àPf\\r½Õ¦ó«nØ=Üó©6d\\fmUÙàaÃñN@¶gj!@ûÔ XÆ\\bf\\tjÆ­pkÎ!Þ!tÕ/ÔÞ¸<­¹Òþ%ÐüÛìú~}ý÷Ö¤n4ª0QÇ\\t\\tãçWÄDmRãæU½îr=Þp¸t:µgY¦¦ýçmÍ&À[qáUî>:ây2Iq ;uëÙ0ëò7xÜqV%Ú­¼ÜPÙìQÊëå\\tKÚwøx.«gªPå8¡Ä«X\\t\ ÅoiéÑDaóF Uå âµÅ+·<Èd¡æuIA`,ÔúÏ´@Ñ*FÝ~¦ª ¬¤ø-Q>}HsÞp»GYéx]óéW^{J5MI3õ\\tþ²àùÅ®44UébØÑ6ní¾\\tõÃA§[îñmë²³{éÞÖÏÓCâ}F;^¹úLêÝ\\f¸ù:§Þâf¤¬D»Ä×|dÿDÂßH3¿ï\\rÛgCß¤M\\fèvöë|8JÁ¶Îßt:ãwÑbÀABÂÑ¬Ò#QwÃ°g¬yÞO"ÑDýÎ8÷8ÃÃØé#Ïr{à 6^¡3G'Ö"ÇAÄÇíÙ-8Y8£ûÉà`èa¬òjõ&ðÂH¥óPàá@öâPOÉãFBÿ¶ïÚmf PnÑ|ÍÁEÄ1Æ5ï\ZO¨£mès6ú©jÖ{è¿DlRæ_¹§w½î¿¾ôãpªLµÊcD$uÝ,ÀÒ&U]ýKùÝ[ß,}ðÿ©GÙì'\\t`û]ÊÝ¹L9Æ­SiÿIlÍ·^d¯Í$¿/ÁÄDçîÐ'£õ6¡`ì1Ñ½Ä¯à0vðñSÇtûB i]nPÎ^ÕWªõgÈû».Ä(Y£sñå.Ð"¬¡QéKìuµp/uzÖ¡í ¡Ñ>0îq¯É\\b÷NsuspÍ6ß±9yÜ:'lE9³4uÔ¡\\f9kÑÛ­Æó9¥ñ\\ræ>p5IZmqùq°#þ}çÃ·$Mµ<{+<*ÀÍ'~(÷_ü¡)~ß9\\b²¤{&¢¿¸J®9\@$ ³kÏáÕHäø¿fpØüÉçê<ÐcjýhLÏï=MÇÑ"Ïü.«ýªÌâö¦5lAÁò0·¿\\rÙWÍË[êIaBÁð{RhRÛ=ÞcvuxZëG&Øé§q+0tä\\r`çfÿóÌtñDT\\n^ºùô¼YãGpÛ©t¡lD[Ø¤å2ßÃ]]M1#ÜÃ%ý\\f-ðÍÛÑàa^kþõpUuVM_Î¸¹oÄÖÎ%²§\\ríäÛøÆ§ïÓ8°n·TÃ:¹´{:ÃÆÕa%1óþÒ.¿ê»¯Û<\\rjÀ*/n9PyàÁ¯gLÓ\\r°ÓVÙmx¡½§÷dêå!%s^ªD¼ñ#ôxzu\\röè6òÿ¥bÁ-ârà#Æ·?³ÜäsRV)®ÎÐ/xLE1!iP·ï½oç¼Èzê0ØF­Ë*d.ãÝC*³l©n)Ø¾b\\r}Ý¶èä2X.§Â¸+Ìér³âZ÷î£yêòý\\nÔ]ÚaßÙÌ×U þ0¥h?\\fsÛdöëvç÷.ßw8482úVlúéP7¤>äò° åB9{æµ\\fzÏÿó³%yÎuWÑ\\b¬æ0à%B¶_Ò¨{Þmð§!\3*.{ÝYº³\\fYµe{õ/üZã9|ÔëÍúoß*§ü<@14@OÙ±ü×ïÅÑy²7 ÖÅtb1jÅh\\tÊh8áb¶Ø¤ÔqY^®º¯¥423lýÊ¥ÔßBçùÞö:2~D´[ÓD¶À÷e:?Uænk(1ÂørñoÍx>÷Ï=MQ\\\r¨ý1Aµõ¥è¸]°ÒU¿d|Ú;P7];ÖÃq.xipUÔ5"R« RÓ'¯R¹?S¯MÍøB¼ürï é_3±¶.Ë·\\f£óGíorWéÊÉ7±­¯)²@¸Zä²ú0*þéQÇb:\\rdÂJ,áFòÊ\\b9ÓEWÿ°yd³ÇúT5ª»kV°×ÓZ§A³Yu%Ie'­¶&\\f \\fZ5åïÂTÛDÝ.:ä4Ö'ûÍhfØ-@¬{­¦{Ö"§YxÖg7vd"©Q¥üH QÃu¤cò¹ÿÙa´¥OÌÁÿÔïy«*«±´Àu¢ZeÛÅ(/³¢¿~ ²øé%s¿ö%ëÝ>iùqåÈÅmjAC-ñ¤ub$Ìfãs\\r BG1ðC·üþÏZ£)$:g;½þõ¯ÏOö3Fê/²s¦¢}7Ò,\\b W«'¶¢¶p'É;'G¹«ºtÂþõíg®(îô³Hº»Xê\÷^®áKYº×fy\\blÉâÅQÄRS2\\fÏ§rÐ+\\fíÌSËð#bUXB¾°j\\\rPÀiaXÓò§lÿ*©üÜ¢L"x8Î_;{Ù iúí?IwþíÈ­+:ÑÓÐõ=A\\f8ìyúbâóçwÒÐº»)f`\\r¼1z±'¾ 'AIE)µb"NòÙo)(F¥R.÷¯¾´Ô¯T\\b$ñJëdÁç<2"¥P4êçGýXwË7}0\\f§Ù e/\&ÍÇBð¸¯º©e×É«÷vß)k7h(ÛÈ1SºÜóâÑãI\\t±Òûi{_EòHÝy«O³aÜp÷ÖÂ$XÇß"dúÛ¼½sëLìr;=\\tkVùï6ãºÄ¤§ÁnqS5fq7ï\\fréT×ÄÕJ¯î.9\Á<±¡­FVaP%ñ½Âesâ=Æ³Ð\\r»\Òæ<ªb©©jR_VuLý±Û4Ã!uóùÖ0Jò¢I¸q5¸°ó ­²:Ní#¥«¶zwRvltt@§D@¥Nsv%f²>8(ÛçÌa¸îVý¤Ux%Ù¿æyZ»Åøþ 3v·îÍµn d±5Uæ¸¡&\hÚ±ýOój£ÐíxHiÆÏ¯£P§þ7ìûÉ%\3lÚ±\\r4dì¬ç\\nÔ»3ûÜÉzÐ[;ÕYAT¿tw¼®Ú\\bûª{Â;Oô°7òcÎ|  ªâ3ÿ'¥Hp.Þ:p¿\\nCU¿Îµ©ÅÙÊ;.dßT¸=¤üÿáä¹XB@¾ Füç{çgí÷Û2h/¢.Ç¨£¾çGÔo¬ ¬ê³Éå#-%~h Åp§Lc F\\bûZ}hÈC5Â£6pdÆ_ÐNQ¤>#wbJè]Æ.¼ÙC/G)6h\\fâ¨Ô7}+êËÙx¼næªï-æ-\\tî-Âë°"DYÝ|ÏCÂ7[\\tT!ç!á\\bX-æ×9Q]Ð-»`èÄA1Fëä´ù¡ä·µµ\\rÏ1ÿ9÷ÕÏ1O¶ ï¥Çfï*¥p'á´¹íÐt\\tK.¥h*ZÂÍHVhDGD3hÐ¤ÕÇ;Tçµ{Z¥sn©M{\\n\\tÕ»Þf(NÌõ)õÇfoWn`ZyhhL(ýÂÒ9Càr.3{16ê\\f­é¸¥g\\bµÀ¨ëAiXhp^)½&2Ò°8¯Qá@É0^R·ÃgÐ3¶xwºTÇ5e&Â§5P¦ùFêr¯&Ùð|úÈ4mÌ)_\Ù¡Õ§'ï²b½¢>\\b8©\\rKÐêÞìJ\\bAªiR±òÀyc]·¸üh¦^ÑÌ*¾ß.ªÒYIq8³ücz*68DIKûLñüÍÿç\+.X!Q9~{NÁ»¯wX§Ð¡Ôý$4CÇÒêUý=WÇYºLAÒ¢KÂ>ûÜq@y´8'`çf7Zs?«Jì\\bøoPË÷|ØÛBTI62ÇÝØÄ Ï\\nCÈ¤<³7yqld)·ÜÊÏWDÂæ(¢mÂ§\\bÚÉ¦tÙ»ëÛYxKwÈ·¼mÏÜ¶QkÁÅ¡Ü¿è©PE·»ÑñªêÔÇk»ÀnÂíø2¸ù¹Ç}÷Ð@¢Tó-Æ\\\tT,e\\rPýË\\b¢{V\\ny¹|°´â°øÛÝð7VHÂ\\nT1yûåÏ9½:OYhr)GÊ,Vbçå(¹/¿sÃ^¤÷Ê¬+Ëw[3ö>É[N)åì,i(lË~\\n@ s^Lî]1<ò¦áaÙ6àÌ:û½£öZÜõ©{×éëyè¿³yUW\\tJDÁy\å x4|!6åÆó³âÃ÷À>L³éMW|ÔÖ½ bRJHêÅfÌþõöÙ0´@×(jÒ~á å®aå¦$ò¤D¡\ßC\Æ1§Y=zd-ÓÓàÆ\\rÕMn®ñxÖkÿÊáWY(\\n·½díÖê?h=å¤~è´ªSÂÉïÝ¦"Ëb¾Ï®Tão×hl¼æq/ÒÙd8´UÝb|<«8Ã©ULÑ$è*PÏå¨ (C×Ïê÷êçzþÌ'øm¤/ôÙÙZñ|\\f\\b9kEóqÁ¶\\tùIåËp\\rmUÍ²å\\fµ_æ½[YFOçÃÈtêÑøÌ±Û_â{\\fI8\\t¢XûEä3Z+\\b(#T"9äôR®GHLíÃú¯bûÄèT)F©µ"¿@¶÷HËÁ&¦Z8X¿hÃ1æ.IÏ§ÖÔþ©¸MòÍMfÈ\\r\\tÝ¯1ÛÒwµ\\b©ÅGäC`Æ¡dh¬y$ÑßKT£Y¸?éÊ×WPÏðÝÔÚ¤ØæÄ ÷¬\\nCÆ\\f(ChÓóD\\r¬ñ÷©VÞ\\rÁÖ]»=ñã»#èÔO9Ìâ¡ÍÓÕ¾¼Ýlyf9=6ÊÜÌ^g©j2ÍO·\\rYäQ\£O\\nå"3®¿ \Êb3 GL É\\rg'{¸7WKÿ~[¢ ú'Ê9 Ê0û\\nFÔ¿üüÏíi\\r@#_,nñRìv£ùÿ¦fyéd,v£®ùÆùñ§k ¨ÛYô$£vÙ3ÿÌ¼ðû»"Ïg§ËÍ â'^àß]}Òé`Éÿ^¨tË0B¢µ.\\n&(Ø9ÑyøV\\bÐoY+ò".upscÂ1÷ë7NÛü¬Ð\'²` «ë¾wç5âHÕò8©juæ<ÓÇz¹ß áv×D\\rc¹òÝÅàgßÊ$M$4êKüÚñ÷Ì\\r_¤gR¤Ñ¬\§ô¢HZi nüÑëå4µ9æ<ëÉÑ øuX»oó{Øl©ãeÇøú\\fbºoß¯¾xt ÛJ@B±dóò:òT[ýa8<ñ½Ç»»B:ì°Ççëu+µ\lóXõD/(ôÎ¾,åîSR3ô<Dæ)+½è\\r_ºÿ¢@Ë%922äÜ»ÆjèPY¦»ðô­óC¿)ZÇä\ë u "b1S'ÅØâÌñô°m|ùüh}%3,V'«¬h^ªïéÙZY§|tf\Z/Ö;¢ô9ª­ÂW"Ñÿ\}XïÆè\\b¡%_ ¨4¾È-zÞ§e¸I;5vù¶¡3o×£V"ÚhT²åOëËò¼ ðCÓ1FÔ\zÄ?¥X iÕY; ø§éï©ï]°W&ÒjrCÉ²ðÁ"mÀÄMHÛñ¹á&mÌ¯WÊ«U.¥Õ'\\b7ïfVra¥Ê\[Ê³Pþ÷,¶æIÚ»·BÚ¯ÖãCX7ðÅÉ³íJìmØû©&Ôbd\\bî{\\rÁÓAÕr%s·FÜbú$ruÕ=vª´1@Ä6¼N(óóÆZeEëçû×RpeäØÂÔ×è;\Î"À©¤vt/tt©»\kõtUÕÊýhTt×ÇYÍ'qZ>qv\+Ì§ÈÔ?ÙÛ9ñv'¶Lÿn²k¦Üf®\3»PÞÓÕ÷; ZÌÃS:®`úZÝYÐoÄîä2'Gãõºç\\t ¸Á-$j¿m!MË-)Ó$ÒÈÆa_%WÞ©A¿ ËÎQ`ASÏÚáyÅB»Äc|ò~ÔµeÔºÙ·¥üéÛDò©F~vcîWÒQ\\bâImOQåÙI¾°ÄÎÍJBàöð½æSÔI¥ÌÛô%CV÷/\\tøýì§DÃÏ­/5«´õ\\nR5]0Úµ¢0\Ô£uñµæÈÝ½$\\b`- 9a&ÿöáÀbv6%JQK¶¤ìú+ðâm ®g¸¿_O"Sp³Õkq_âçO´¶\\b£AáHUSé$=î©ð½Ìè>,1]`«ÈÚÎ\\t·¯Ìûº5y|ÓâOfÑL±°zw6üP¯×ÕòÌnÑ¸[a-Sh-K{@xÒN.æÖùÐqxÔP§³ñÏÛpV>¸îÕ÷aWúA §ççV(\\rÊÊñ.§¦TA2ÑÛÜñ¾%JTXHß^4ËÓoÍ»ÙÚÿ(=UÜêÿM3=¢^X®_s1ìÂn\\nù\\t1L M\\rJÎ(>|×Dß[KI:¡*;ì4SÎoH$Óø·-´#¿ìÖeÇ±´?XC­H(0ã:zÜ?|±Â)áð,UE·¼fê-§s'ð1sü#ôWíî©ÉægXH¬*PÙ÷8\\bà'µkYîd©)] &m8§ ,Q´bÿ×mcÕÊi\\bÃëDP0UË|¤së.FBØÝ²z1IWbóÈàØ÷=#Èm4ygP[V/sí\\tÛÕ©é¬ÚS\\bA¼lÂ'
    //   11: dup
    //   12: astore_2
    //   13: invokevirtual length : ()I
    //   16: istore #4
    //   18: iconst_4
    //   19: istore_1
    //   20: iconst_m1
    //   21: istore_0
    //   22: bipush #53
    //   24: iinc #0, 1
    //   27: aload_2
    //   28: iload_0
    //   29: dup
    //   30: iload_1
    //   31: iadd
    //   32: invokevirtual substring : (II)Ljava/lang/String;
    //   35: iconst_m1
    //   36: goto -> 202
    //   39: aload #5
    //   41: swap
    //   42: iload_3
    //   43: iinc #3, 1
    //   46: swap
    //   47: aastore
    //   48: iload_0
    //   49: iload_1
    //   50: iadd
    //   51: dup
    //   52: istore_0
    //   53: iload #4
    //   55: if_icmpge -> 67
    //   58: aload_2
    //   59: iload_0
    //   60: invokevirtual charAt : (I)C
    //   63: istore_1
    //   64: goto -> 22
    //   67: ldc '.+|´ëOÆSï±Ë·´Is¨£YEÕ?úÀÅ.L Iuÿ¯xW`®¬ªJóð©h?j´üª¹ßÍ`÷5=Jb£Nh[EïÛkÎÊ¤~æÚ½@Éº_ÈTsÈe4Ý×8cVKì^Jø¿azÑÂr·)Rû¡ª£Þ8ëþÕïñ÷°À/1Ê0ÅfBâ/Á¬Éæô§ïyñBÔ~ÖÂ2\ÜÜy÷Ì]2îÀÎ?E.Ôß*EXcÇâñô¡ìcó\\bH¹i;ÀÝw>RÓÔAÓ½ÔÐGÿ1ØU¬\\bt¿q¦^ÛFÒû7Ø²è;mQäA9(ÄZÞÝ<I`óØ·æÂÑSãLÏËL`ã¬XÁª^¥úö[.ãÐÒið8Üb\\nq)ô©{¿Ñ~$ K{aNZVdªF>ïHèqh¿ûï]4²IO\\r%:¡ vM,¯ö]^ÕLt~Á^\\nã¡ÝR½óz/<8úþ¤\\b/Ùì^áZòØ6SÀWfYý"ëûø\\t7×þÑA±¤ÝnËZ´cB!¸¡ÂòÐnÄ¿hB\\rÀvÙì¬Ã}÷EÎi\\töÌ¡F;ßtOÊÛ>bùM-âÏaõ`n÷pâßø3b1÷cÌºÍ¿ß;¾Å½_s´CuwNñ·ÿÃ²^éOcyÎ+¸BSÒßùü&t°Wú=D"øÄf4¿UÝD~}ÔHÔïJ¦&òÜán{Ù¼LksãÿîÃ[{·uù\\fËÂ6ÇUÚ¼Ïb~aå½6h¦æ´}OTÆø_ª¸Aõ#ÂÙú=dz½ÊØ@ß\\roó<~ÛR×Ë¡×ø³:KªSd²_YÞ×r#µãípt({ÃBsþhÀÃÿm7|F\\fÓGíHÜ¡MAVò^Ã<£tóÚû³½§wò_ÍjÆ\\nòÄ(w+ûVó,9t\\nÆè:²wÒ¾¥:GçMËøLPÛ2mÇGä3×BK°Ód)©´ÛEÿ@ä4\¥2\\bÔÜ[6yïÃÕß\ÚFl&`\\r ¦³XÈÚû®/²£×ÃúÐÏÃzHg§ñXtYù.iGãÛÊ®#ú99ýj{ÿÎ"lÙô¸\\bü¯f0jþü7£.={@à}8lR*ÏQ¼W\\bâBòcûçJöµn°îqÛE)µ×JOú¡tÅR·TA§¡­¦Pá7§Sg£}M*§®ûw]I¡{¡|;Nø²®¾°r~ÒjSýbÐ1LfrË£iÞÉ¡ÞCX®KçÀ´\\bÿ5*B»ôw±ü ÃQ'ª©æÒqNÈÛ¦¢ÎF¦,%{Å@\\tàÖÍÂ9¨v."µÈêÆ[|ôJÈ®·H^$Õ.T£¢ó^ÔP¬hh?oV½\\fæ?J¯¾Ïpúè²ò³³û¨èãøm¼@cö&î#wáV§]ý&"4UàçDE]ÝJúxZ¡Ëdô×Ãâ\¤q÷^¢ÊÚà¥ª-OÎ}Í÷û|*~M,$æäTÌfgFk8{3-U0ó¦d¥ÂöÂ¸_þÕÛj\\tõÁ(=¤[ã7ã×ï-¼ûSËÅ?¯2åJÏBÂPÕßq\\fñ6ÀàÌ|  ¡y©­ 2}TÜSâÕ¡tYxHÇl(é×Â!Ï8ì0TÆôñ¿Ôw]+XaV8uUàÐ\\bÑÿ1¿Öc÷Ún®¹¯sI¶ÜÔ¨íÔñrÑm1¡1g±·\\bK\)J+:Ç\\np7KnïºQNàü²µMCT>OíïôeEIæ^F¾xb XG÷vþDYZÉ·vúº\\r§d8>2òËLqS8|Îö#º¤\|ËEqk¶hPäòIH0`IpÍ+Wdd@³Áa©AuÁQÔ°bØ\\r1t:AH%Ö%o¹êcâ*|((*7qÂ+çÚó­\\f à]>?0.eÿÊ5Í ªiMÎe)ù¿¥­ó¹{ /,s£ÈÊþÉ\\rYRÜ:{ÞBjûBVêþìÚ46Ï!xT\\f/gÐ?áâÛc©¥[vl<õÝÒ^\\r¸nÌû´ÚH_ÖbWa0ßx¶%Õ\Ô_H.Qø¬®x&òÏB©b*§ÕbHsTË@Öñ8°'{_ns\\nß´XX[<ôi_À´¯àØ6¥q°óòâF½õ¢J!ðP$E8æ¬50Hn'?¯ùýDÄBÛ#²vÊß,lÉ<½AJ®°Zn%{;'¡:iäû¶ cP£ôQÏa`ñÙãXëËDS²Ákv$ö[¸ >Àú÷¸kâÓü0Ð éü¥cáU5Ë _Úà{bIqM¤¸|¿ê!ÝÏýÓ6jËÑ4£O:uG+ê¹oÚË¥IË³Z³h÷G¨Ì1Hïl2Þiù9Y\\rû½p÷ë#Js^nüÝuN&\\tî:××Ã«­hà×Èê©\)óK*@K\PûÛvjýÐ³PÑLÞ8Rû?Î3å]¥Ü\\rÙ-ßïúH×KK÷fâ©êG\\n{bbJ»'aMJÊYOAøÏ4KÅCÂ©ö»"ëû©2Ù·=Êàöµ?J8\SÎ1z({¾:u%M`otã¡T\\bwæ¯|°¨l¡Æýü7'K\\tTjzfvm}±®°D%º¢¥G<b{}8~8<0*79eEH/L85­QGÅ`þ:­VÌ48/c/\\nE}³:bÝâÃÒ\®\\f]|M¯¤Ý· µ¬"ÝT\\nlö#â+SXA1Ûòg\\b-\\rsýG²Ã M [æ¿ßÉ¾OóbãøÇ,Áì\\bq\\nÐä~Eî&HO~±\\fÂB¬;ÜßÐçâÝ¸.ÃÆ«?¯CCóuVÔ©\\t\\nþmª¥+¾îªôìj6ÜBzÄ[g°¸-u×hO"w¯¾xJ\\bvpá ÕØÊ3mßoK÷@äê(}§Æ_´Ú\ÛóÐÑ3°´Sþìíê@¿Xk¼?­åeÚ½¢9ñùìõÏ*Éntw¼!q}Ú¢´zÅyo0èj]¬C}b2«Wë3KÆ(ó;\\b¶ãt_\Ø«HÈ±7\}zÃP5­:heã®ñúJñúU¾ fdµFr5ôkÍûåêÿg"ùîÚîµ»ôK:É²¸W8\\fpª¨k«¶ yéFÀðÀè×ÓõÜ%2]$,ºy4qñôåðrñW^x¾RJÐntbuJ,Õµ9VÒ0t\\bKêÒX_9õWÌ1þl<\\byQyô±ÜÛaYÃMîPXüNn¶0wÒé*8Æëä¥4¡\\bGûTcD2óÿkGk;45»HÄ (%RO¯F¤Ø7¤i,ý<ZÿÅ\\rè*w/\\tòiL>rwÈ'UC9rMØávNÖArÕMÍS÷ÃFé±î*óV7HQ)@t»$£i\\fäeLÒ{7 68.ËZìù®d²@ðÆÕâ¸gîÐÑu¯ [¸Ü$éøY4ªd´¢»óÚ%ß®ñú|sÍo$®U$\\f¯CÛI«Ì1y²|Ã¡\\nR®à0Òé,öLNêú¿¿¾ØÌÉn`ª²BAÿ"tx¸(ë4h&ç«¶oÁoÃ|Ýãft¸`ñ\\f\\bMyÌìúAòt5(Þ Áj)öMâ?P\\tB@±|MDaêý'÷r·\\t¸²=Ê qsGî¼8CÒwø|y­Ï§ÍEåÁµJ0¾4]}zô²\\t6Ô®ðãã]X0/ïäE?ÉHY¯.;PÚâWUA*ZhòÏè®Qü+ôü§I;câ/ª\è\\r¹¯îá©Åh¼=KmÞ;¦åÎ2Å-ã°Ð+CU|à9ØÁË®LBÊ\\nKrá·eXt¾òú,¯MÁÿÜþ~ò*÷½ÿl(¡£¬ªõ\\tk×A(M×vLô>òP²Z¦U-CX]éìÀY\\n(¡QH$¶¦¨Á«\\fRå\\f,ý\\f(µd'§ ý®Y£îû81Ði1eiKßýûé¤»©ïÕ5\\rVóRÆüÆ×tXkÎ°#"£G4C¿­¯GÀ= {ýÌäÿC ÒàeÆý"X \\rL0Á Ì5ÖnTÍ¶ôO'8ís¥¤.Þ\\rgq´ýqAùÕy_.­Níµ¾Îëì-õ$3é)o-U²×{;RBvÜ.VHóVÎ;Tìwô¦º"÷W3+©±²\\bªbi»¾ØÎ¹Õ]£ÀÊmC(DJ9EI(Ù¾¹KTo,Yi#v8¹&ÍÁ£ê£-~§5âÞýFNËË8drþfêB¤Í®/úH!ïÙ>JæuEÞ ½|M«üÝ5"+W öÚ8á¥¡\\b2Ò\\bÞïhxµ¶^5UàMó&RÅ²OÁj 5ÒäÃ¥f¹!?6ô=Ôãà¿ù·¬ìÿÜÑ9@§ý|rá9Æi Ð<#þ·Ã¹Î3,¼Ä"Áîìß÷B§iC%ÙLÉäVLòa³ÇÄËÃ´et´Â[(·ü¶«åw¼cDÇÐùàÓ;^P]<ÆåÐôHkØ»¾æ±¦\\f$êØpj§·[01.Â*Tä$zÛÙ-æÎ,ÙEycÊçÉg=ß}]M3oNiéþóv û={¶§%yÎKù*Þ·¨6ñø\\f08|ìWRªxãGïîÜZ\\b)ÒàCYò\\th!è¹IÒ±^r¢OL¬D­üqí Ê1]Rz\\n~{¶¶ûøpén2B©ÛýÝUpq]ÁA%~1Á®)¥v¸ìññ±ÐædcOÉ¹f_\\bªA)KajTÛ¿¹6Y-¼4ïÇï`ð.a¯cümE?TìÎPûx^h\\bè<ÛZf^+^=×á´ÝØç×U{÷­Ý{fü WæfÚç¸Ñµ=éCoxJÂ{§àÝL@8NJn*d·ÒX§½7ç¶fÓ\\rÓÀwð4ÓÑ#à¹ùËùÌlèrÛr÷G:âÕ1ðº èb\\rÀd\ÎgÃÖ1M\\tTDB/²ÀÃB@6§¢ÖÖ\\r¬8ßX ý6vÂ_wy¨&4aeÜ@Lí};»GrOâ[T(ó¸ìãÇgbXmdû{w*ëÜYoR~PÂ\\r_ÆÆø ¿Ô»Q\õ9øLJ>Üª£X@Ô`wåc /È@ø\\rled±ö¢A-Óf£ôs~×ü#4âä*&'/rI#Ø¸\\n¨KñTéØ4¢f¥hÇK5ÜH³ÁëÛü.E®ÔìåS^×°òðqêÄ¹÷\\fðsl1©"­x`éö3Ù|ß2bÙ}ø?©$,»p¼¦BSvgm%zr2ÒÁÅn,ÐÄøuø&ts*ñ:ãD¼y~#g,q  \\n¥Ù¬çhÙ±Þ³H\\n]£ÆûÕ\\nòÆh¢dì!]ö¬1~}`ßÚÞWËÏxYµ1^\\tx\\tBíêÐ!Î©W Õ¢]µ¯õjâf~Å\\t<õ#Ðù[Ï4^MFÿÂDÌ-tû\\f.®!KÇ&å2ÉlAãóÝOÖì÷f}2±\PùhßrÙPt!+´ ºmæÜÒxÖñpÍÏ=ÑÞoJç#wD·÷(HÌ§jzí©iÈL¨\\f3ÏK¤ú¶Gìª¹ë¦*ó)±}=¾ÅtóèrU±8âÒóÈxû¹×¼pÞµy¯òe´K÷âZä\\t8(Ù¹JêKÄMÎÙµSw²G=üº&«hÆÙg®yîçºÝm·É³HÛÂÝíúvc½H§]ÏÐQ üd<7ÙòçeUÐ¢v¢z8DÂÛ\þ<1Gr^gÃt¬à¨?Ný\\fÌcãôñÐÍHâ\\t±)Û\\búKÍP ² 'I½ÞîW:í»»lb#é§:É?s³ëwSy¤Öì!KââÞá­Pxc²i¤×0PUüÁxÚ%¿BæÄ]òÁª¸Ê]Ò:(»¯jÃþM¢\\b%÷%*fîx¿Y CàªÉ°ÎÑö»7k_!°òÛ!,÷~>|ÓczGÓÀI÷ÈÕóüx@\öú]Ý_¦<Þ<Òh©jÚI'E4ú ³<{üzª¬&ì_Ä»°Í4\\bÅÆ½üké ²uØÉÿ´Uy\\bÂÚ¹dEþ"¿"ñ/)õ~ÃPØði¶°\\n4Ã\\t? +»R Ï§ÂKÜi52PuU<Äd»×j=ÔHÐ/kñ?Ëx,¨æÖ¯VÞt¶Z?ÊïÀ¶b´²ºÛQÀ?ORÑ ³9×%¹ò\\t.®õûkäÞ¨\\r\\bÜoéExçÜûQ|íÂp/ºìcjíê>Í* \\næbÔBÇ\\n°\\n'i¹\\nß§ôÞá¯´çw×ìWxÆª³2þGÓ£¾p@¨ìóØÿ/¦Ó$··R&¾|QKÁIÛex5;\\fOÂQ]>Ô²5wåáq¥À6t¯}?PNÇb/LÁ<N®ÏRF&\\nJdP®)J³w¶ÊÄò6µQ­±Óð\\býì83E óÞl²i,cxè\\rÞKj¼äV×ª4"Ê¬egû4y!tä¦¨¶;öO_°ô@¶@ìöÙ@¡ÖvØ8~Õ^»°TØ¼èdLÆøf#E¦Ô3i!ß¬ÍßÁY;WèõAåI`H'ÖÿÚ¸¥.Q®·cip×XTgÀ¥`JêØ$Ñ<Os#ÁgQ"Dý¶3H-­kôªÊôäN¤-¡u7ÝDÉ n#²«|)Ù cTàÿìN¬ÕïT±ZÉÕÃòIx<v¿Ô!¿©/×­¨áEÜz!\\rWmëREH~fkÕéÉæ;\\rd@Î#Õ¤ó\ùg¥ôÓOýãÿàëzWö98÷ê6\\n¾ý0õþÉV0¥-Üæ£fr¬xÓIðcE}- ?Û»ÀéyMÑ¼½ðS*³§_ùYþB>ÞRÕ8ê2ð»±Wç2h¯#î:­îá+à©)ÓµÅú¤|#3På ç&^>v «¢êD_.Ï2FîÁ"6Ï@gr\\b¯W =Ü?­xùIÔ°»²i»,ö'Æ`x1ÐzË!qþn¶ôÄ¼-¸ò¼Qõ¨#ÞpZÁ<ø'/ªÓn·`½XïWd (õ<þmÆ(3ÎF w0¥¹½ïÓìRÌy$$'q»¡³vìÃ¨©ÖúÅÈQA¥«Â³¹óÀ#õpÏ»uuJãÔ°MÊïnj{«Â\\f½ñ[+´¼ß]Ä.ì¦·,¾ø^KÂ½ ßª¶xÀ3õ¡uv¶Mé¡Áæ¤uc¦ü×õlKz¹Å+ßµÓ üh`ãM¤:¸Ý0®Î2ï à¾E\\r0 uo¾Öø&ó>ÑnÀlêø´L{s³ÄÅPßµ¶#q­]¢0ïYØ:Õ:ÃÔÖiF¬H2U¢É³×»Uø¼0Ï\¶-Yygø¶ivÈ4BÝèTÙ%'4LhU!=x»fm9Ä.\*ÁùF©\\r¶Uk~Íò\\tn\\nÈt"§ ÜÈÅÅëðåtÙ"ëªè±¤ó±iût!¨á&ÊSãVê¤ÚÕ`*{Õq®u]yù¼ï!F¦å1ÿmn¡÷ÎP¯y¹ Vê>ßpÒäzØHøñ/Pdß¶8ëUÎa+X§UL\\rîG´.®Çæpro ùÿxs\\tPÀª³VôP8:á$ë´©À @'Ó5ÑÔ"¨ãX¾wÛ\\béëé¢j7Ù¿ÔõhvÞ3¦uýÊz,h²Ô¯7)ÕåFZe2I6ÅÓgÂèÎ¯þD¨S½¦aÌÀ«Õ9D+ß\\fJ6°\\b |}¥\\nR`Hâº+x\\fà`jP>T´¦cóçâ¥a8ßÐ.õE|YÅÿ¨:G¬mõ+úÁÊ¯ò*°Ò®\\r]rg=F¡Àøº*%M.¿8ö»þð¡¢ÓÛp÷4ñQÁ\\b!0ÐGÇ½v* ±Të¥¡ï¡Ðûà«°Ý-ÅÐ¡¢Û&:äÙc­öõv6¤ PbãXTFºÇS¿ÏËÑ"³¯«ÎÀÆõ\\t²âõj@Mí#ý8ÊªÝCWÛq6Ü¿50Ð¾w<?E¾J\\f°#EãÏãºG]=Ãjc¿|@S-\\b_/Z)O«dÒ²¾XÖÍ\\rÁPT0F¥ì7*#¦0\\fÂr& öOÿ¨ÉÙ oÄsÀ´©õÞ'wvk$½YYÁ%±¶íB\`qÙ¿ÈÆ(r¤ÓÙÇìZOìw.ñïês³U*& AåôFI²_^àù+ûÌ©1¶JkF\\rñÉ²éóÈÎº².ÚÕ@^OELOÎ\\rK@SMZGk¸NÅ¨3^\\fqðiO2ñ8ìÿ¡}.[<g×çÃY¬O2hÿÆßðÓì$4$îWºÜ,­TFÕcôÑêßw*fæ.kqÛ \\nÄkZ©¬ïsßbÙO/Þz/´=7ÔþjpÔõÖ¶:Øú_cê¤aö~@åÔÖ6ËÇp^)c,´¿#ÜBSï¡©%>IãË{^tùFFÏÉF÷ê(º÷¶s]ìä3GçO­Ý&\¦U¨xVÅ+|R­.¹½lÝ5°¼\\rwieácî'Êv&uê;/À Nlñ§Ë´ü÷à:vÙ±óënák¹vðFòØçö+"à-Ï¨¥ñªUc{\^/Ü"·§ãÕ Úè_³ìÛ@ßo^CÙ!aøLâÝÑ¶YÏ5be}\\rZ­¨ÉãÝÿ×söJùÉl[®¨ÌbÖH÷ÕüÊeGÁ­å¤þb·¨â§ÉßùlB#ïÖo-ÆÛmí|7sÎ,^Ø7}ÛûKô@@è\+?Xé'g9¦Ã~\î ô¥\\t×+:Ã³ »tÒq;ÛC¨\\fVHvìÓÕ\\fÖ¬LxcK¡mËqP'Úahñà!ÕOF.s-4 r5ØªåëÚ¦åC¹RóEöôuî.»j¨"¶ù¥J$£üÜ¯]*}P.ahÁt¬5 ¨ìÿÙ!iõ'æôqÿ\\r8{ÜåÁ¾Ë±RË¾¾WY´j¤H{ÉÕ-TÉÖ|r¡7Ãa²å>of§QåÕÍ\½/VÒ½b&þh)À*ìZavækáÑ±¼hi¼Ô\\t½PÜ\qÇ[*^¹6éà¡~?I¡×ÏEäÄsL'åuT/çpív<A1óë \\rë;ER}>é´}Ð¢äÕfùd©¹z´Þ{ð(aÊ0W>S}oA¼vW%å«L@+½/$VP&=ÃØ~kKv¶gx|/Ð7ÇÂ·®÷§CÕçQIx>]î\\tþàT@Ûì-H­¢)5CX$Er«o!w{q8~\\r¦wXà8\\n? ËáøÁÉåË2ÕôYW«ÃÐú§ÀPLb@T)~}ßåÝuH3¶%Ê&ï»±j8ây03Éy×Âd4%K È$gR<Ï´Ój<v»ö7DXÒ®®àC´úýû1NtÌg2ªhÿ£ÒsÁWj%pÑÐÉäòäJ%ÈÏ´ï7ßbNB!¢`^ÁH(¤EhZV\\j¾WüJ%$Hê³yEÓ/{ñRl%ÏÝ<¾1ØÁÚ³<ë£¶prï¥åq[*¾óeÒZDcGOUñV Å=*>Ò~B°8%cr¤\Å`\\fD´tkPKÙç}Tÿø³ªËLõ­òÛK´]a'ñ"­+v@BþZü 'æ0ÀÀ®ËÊ\\naQè¼dâíÛC{×¸»ß`ú±ì¬îAù$2MöWë$õ×5PMIUZ7ÏÎ^¹|gmÆjÊV1o8A\\n²Á,Ê=\\f`TQp×_óf³µ­(×hxMFÍ¡ëª\\nô|v½T&~³jãý" òÁø½îCÖ$]ff±}}©Þþ¾_þN]t4*ÒÞ±©.1Úë+Øz¦k2­ùö#\ÒôÌßçà=I·Ý_vï1!ÐZÌ@©ôs@ÁËÍ¼ÞqyÆu}ZÝû)ñ<X\ØºIRÀázÐö°VJa9Ôë5¢ÉÍËÑ\\nOÑ èÙ^U\\ruw»o@nqx\\f4n~cfÜÞ\\n»³,¬&µ´ ð/ã0»K÷¡6â:ûB¨ûÌ#ÜÌµàAWí\\f.É¢¤EkÙ?ÕQØïüùJû~>^\\bè¼k§É~´IÈ×¨CVåYâ»Ä¡tÞÂ³å>;Ì¹¿«~4xÊ°+ZÐ¤ëxU\\b|1*²Îù¡¾DßK¾ÆQ¦Vuú&8§øÃÓ#YÊþÂIþ×7é\/8,n¬DÔ»G'Bjé·îjTÅ/Ç±·æõ5G«s>¿= å¿°(Å¬5þý}ûÖ;Å]ic°Aäêè.jDo|O+´6r!Y¤XÝç]å@m©ºÄ4¬Øßª^úÔ½úÃMQÏ÷9S3x\\reRöL_¿<\\f\\t6Ä8À(ê?vo|ñòh;eüYúFd+5¥÷Ë»Qu²³È ÊiÐÆáõ½àLR8<û¥ËÕà7ó¬>[{¾ÐqóyK¦m¿!N§³?DûoÇ½èÈ¦[^)ÃX+UÄô¼1gg&ÐÃiÆÜü+ÿYºÆ¢°zÚ»õß´ÂÀ¢M.²à¨W>æÿìpMyÖ´rN<7ËØ@4Ú[g(ósSõb«_Æ5'7qÈ\\r¼ô0­'öÀ\\t;abó/!þ3V'háÚÍaÄcàÍ²ÛuºÑ2ÌJÓS$#/Éº~ %zH£pl)§¾7«Z)\\r¾Ýnõt;ßF6õVIÍ]`ëiÛrNve¡\òP5ÙlÌ§VßQqÆE$^#¼"¸HcØÂ\\ryßH±éç\\t[oÌ)¬¯Õ½R\\bX¦Û:ÅÜZp¦ÖYÛÄU}iúê,Õ$õÄ\\töxF©@á0á=Ç\\rË0É Gáº \\bÄT(ÈÑ­¾ë¡ýJÐáv½Úfb-Ì<*ÒIøHã6_Ü{õv 6ÈßÒ¼s´i)Ì|æ qtD á)¼YNþ©Qï@ìï»OÄoøPaxo:)½å!å®ÕªÜlABW/§]à|\\rß9µ.T'w~M¯jkß]¬­¾Ò\\fõXÚäiñ¾Ã$¤÷Ø Ó°ýàÑ·®ôPZ#ýLxÑæü\\fkb êçÕR×SÉxû×¥Ê×Y-Yø²ÍC\\b)í¸mç{¤Ekä d{Ã(òiS+&û}ÎõS $Éª1×Xë3²£Xç¾äúà5Ç¤ûáòÞï'¶~«gYBúL°#\\tâñöo.vù_Åª(­ÖC8e !WÂ#ª\\t +Ét½o)®nUÄ¿ØÓbïæ¥¿%¯¹Ö¯,®"Rpîì3sQ»pHZ}Á3ÁÑuØd%HeC*C·*%eôíP á¤A÷ÏdpÑdÔEáxÂPÑ'5sª "«CøÑÈt¼t~rIÂóóLÆ=©ÉþäÃa"7ô´§îh<°Ù"*b¨ó¼YµvòÎ/ä¸ËÅ+ËrÇv: $Qhè îcwwÜ{hðöiDîÜ%Ä$5Óå*(èF0ª`\\n71­¨º§ÎÁ¨¨º¿°=Þî\\fZßH\\bUªéÜ.aìÜ¨cÅ]:>tõ`ËqÃ|ng­ó¬§AP_BWÑùò©<B­¥i2»7Ñ¤Ïwg43ã)uXÛÂ¢6N±¦eGlÕÒÖ½¡ïÒûú2ôº°TùCo@ßªs)&9!ÜÕªÒºA§/ÃÖ«qùM@g\\bø¢á%r'Fc80¼áÒ2K«»@SëÑóKA¾lÙïÕfæ°Ê¯r¯%ù'¯òX<qoß×>«ÀÀ._.ÆCdF¾ÏÀD~þ\\tû§Óq5VCéqh7é!m'eÎ8O}z^ºâ9«¨£º6ý£ú"¾DÜÌJñóÞTQ8CÑ,A´7[ÿ[Ô¦õ@Ý®Ãmo¶|xÿ![ºÖÄÖzçÿHDÌ)~Â\\rá¤ÈøºeLäùM»­>Dq½\\b×Õ2>ÿýäî÷hz­/¬äyhÐôÏ[è|ÿdoºKxìØ\\t¾zUYáÆ"Åw*Yø¸Î°Ò2ÓXÅ¬²õ+¨mêwDÿÚÑòÓqK¡?óKÇÓiú½¿æ¤fÑV"Õ(<Gõ%YÏ\\t)1b^PÌ¡ ¶Ã ýú7 ´ßZ8ÖÀ\\fçIJç\-ã¦bîø+ñ¦í!«{íöÑQö,ÝF"`Ò\\tpn¹ÆÍ3¹ÿ½~ñ\\nU@{ø:@Ï`ç}Ææ`íc±BãPfû½M §QuÙþvi0)Âûå¯yaªÿ­¤\°½ÐÓËu;=\\r×iáE8Zï<uj mãâeq*.HC)@0í åpc|ñÙÐe/áM~ i2Wqç?¤æ vÃ´4s=ÑØ·ýÜª(+ b@\\tô°Râ¼õ¢_Ò´ïH_%ñ$$ÐÉB0jÕ'wp`3"pB\\r[_ÎÄ>#F÷¸5ò'²dâ¬fì·\úÊ÷Òv0Ó!(èðpTF|#ô¤¾û0­¼7ü¬HÆ|iZ1W;°Ë¡péQÆQSÏõiï%TôäÀãUÝ{+zÌkÖÃÁe°:CÊÎÝZ\\f)!¯ßÂß÷Ç)yz\¾(uòïvsÂ @GúÝZ{\\rD­iþd½~ò¨ûØä\\n¼)7àDËºw\Í]%}øLWfH@ö^nRô bM6eZÓa  Î´Ò5@þ~ÈëèÑBÙL¬ÚçÅóFåwÞ¦éXÚ\\nÝ:\\tsfæýïj©öÂR´©l~ÞûmþV\\nÔVóB´ÙT{§ý²{äOã¯d¥Òê¡ñCnüzåhÛF}Yê6Û BéRJE.­HÉ?D%¦²ÿ3cEkäq_A7W¥Î/NdÞ7æ6}é>.U@ø\\r|øs¹¿¯×¸TÁÔðãèöW¨ò7Ý®ÈËg&9IX4üímøåÈ\\f¤ï1rÊ¬ ýâ÷ÊF&Ê:%ð%ybæàÒ¦èi\\t4bþØÉÅk9ð~f|¢§Þ'dãït|¦ão^84èåB£·8g¨4ÖÄqdBó»Vd©bÎ²5!6(QaO"\\bJÌjÐ©áQô1Æ¤iåHd×1×óV½ÂÚÖTh8ÍX^Áq·©¨û¦ÇS Ö«Éô_s>/ß+HL¤)¿MyÐ(ÿpaf-³HÜ¶ÚäPz*²'!zÃ®jÆpêUáù^ÒÜtê(0¸öé¬XÚ&uÍ;;A©õM{ú¿´«yDÐ¥hïkCg*²fûàÝÇÚB¦z««Dg¸´1E$ÒûL.øyþÖÌa~iÁ<ÕU¢ªPî¬¯B±FT&^r­RÉS/Çóu#mÊEDªîÿë\\nÛëx9\\n|`ôû£ØÑå{æÏý¼¸Ô_ì>°N"|Ó¢·¯»~¯6°)2îC¿6Æ®eu|0£4tóGt"Ã²øârpL&Æ9Ïóõ}Ê>áHi¢Ü{s\\r¤Ý2_RCì¿2[XLa&ùA¨¿^_È´VA@ù°T`<PMC=´ßbú»ú\«·´aë¸Û 9¡»3(}`EW]'"~a¥9zº,#M¿ZÍÐÀ%óV¡áØ]Ö~ÕÎå2¾ãüÎ¦ëQ\\bª¸l§Ì"Iõ(\ª$¹íÆ6`$h&~=ðÝ_Zâ`\\nM«+Ï@y¼È<ÈÐNNàÆÛØ¶Þl\\f"h¦à¹·ÿ<Gë>Ý#x«Ìî¸6³:éÄ?PWâïÍÁÄÈYv¯þrEÍ^^Ã?&ë­³\\t¸d¬µ\U¨ÓÉÞsK*-°i%éÉ3tTK&gØÖJø³mxYR\X"L$æÕÏT_ÃX©`â?õ¹ºµ%Ã>©ÐÆxèÛÃc!\\t.èbÐ2ôÁQã/6V¶Â®±ÁSþ6\\r%üOè«ÙÄÖ&U¡ÛeOBÇbÉzÌë_Ú¶¸%*WDIM³i :^;\\nè©ù8áÍÎGÓ¦¨Ø¸?Üºé2O!M;h³Kt+­øt=é'ëwí¥|ì\\tRÉlÞ7KPÔÔ,Ü,A×*¸ö"º½x¦Û·yM)|BH±É¹\\t«~¿¼4+ûo¢å8SË7AôvbÏèÄ¶] \\r\\tmúxj¬=KU·'Cí£äVz¤LÅ)<R%ÓU+UKº{{®knÍÀwg¸ñqüìág',JÀl9ò,n+ûë±Å ²åF©Y2)´©"sÞçrÔ¾,©oKIÿzD^ÑãT¸¼á\ºVv8\\bNÐ~î8S-»/aæ\\fZd·Fó¸¼¦À#·Q.RYK]ÅÁÛðM}d4%8É\ÑmÈéO§àí7- ïË/ ?ÄµBQÂÈ°:Ì8m¿ÐvH\\fwz$®ï¸ÆV@¯\\nj§i Õ>aí*l/^yªJû¼ËL u !0¬­å\\n_ÓlË¤(ÄQ©;¹3õèS(¸¾rx.5?A8&¬¸Ë¼®f«síÛ\\tÕ(íÚ¿=ZêÙú-ç®+µ$ßF}Í»°fÙeÏ·\\tmñ°CäaÎH<ÒoÛµ1÷Í¾ÉÖÅt·\»$(î×j~:.ïso²Tè<ÕÆ&2ÉÈ<,»Ûß4vÖNÓG]õ£bH2ï°÷g\\t:ÒE7´&z«,¸d·Rº-glÊèmæYÂÞ ©kÀ<Æ¢-áAÐ8Èíâ¹½(§½HtÀL|Ü6"ÖEPVÚ³P½^J!Çä\\bx\\tCÐ¦&«ãåé) /?l¦^Lèâ.+0<ôHÜ8}¶½ý"ßá¢Îß¾¢:ÍÉko¬R×V¡ÁWíJÚêÃ¥¡×\\fõR±Å¥EUÀágõý¸Vß´E¯Ãòrdÿßª¡?r<éë }?#/¼¾èÁV2­íz)ß;\\b/²> u<Rw^¬  rv«xåènÀÌj] Õ*ÌZ]\Þ6ñBäù.w^zªZáÇ²¢4ÀñsÎ@ßR%íÛì¯Ñ®ãùtU4."â£zö5ç1wj®¡X;Øm6E¥°VÀ6[ÚÎG*PfÚ?F£f\\ryæûE£jø\\f\\bãWLX¨ÁïqÍ²Ñô¨L8!%¬ZÙ3D4äñª5¦Gt\\n¾­¢9ïÊ±Æ¯\\n£OãþfÌé,iÇP#CåÄQcy\\\t`¶}i_%©Ë_/Ùv}SpÉ$Â£øËTfENz:M\\ráL9SCË5rXoßNãHr¤b½MÎNSçìA¼Ü÷\¯6Ää®vYß5mT~«½v FXì(Yè\\rãVûuh*ú$±õ±u0è3qOµò wøsBÆí2â\3úD2%Jµ!ï´ÿlÐÔ{Op9¿_qdk55ßØÍG:(Ósð,³èº§ÆJw?¶{\¼ãa\\bøs¿rÂ$'HÉäöËÒz¢²cG¯_º(;¯jhK2;àNµ·±YTºrËÁ®"1°.n,Ùàý@mÍü}tØÌß(ÜK>?#ÁiÃüR®| +ÂÂ»sEä[r¨*µm©"í\\t[Ì1('É_ç!ÚË«®ØÐ3;Ò('b¦p®°=å¡!õ¯!·\\n^Ók²àÐÓ8ù2ÑªS¸Sì´ ­zçM¾â'¥Ë¥­zÙ» vD¤R,zºË°³eµ iN%¥Kx`WFM-MRó#(âÜ-µ+@Ã´{?Hql@ýÖM$5mèû¨+ÃÅüÏ¥5åYÈËÛÜRõË?76´Ö?ù·Ý'2$Aÿg2ÎKú¯>ü(êÍæÀËS%c`7N/|}E¯na×{wEßIÐ/ên<Ë(ÝÀE#hJwSXÉ²Åê¹Ã#¦}*íÞi¦ÍL®kü0óp6=aÓ$µ¬8ÃÕtnu×àH;ÔÀe¡!ï6lC³xer`îû#82í,ÜÓê£gÐz?\\nYw|Üæ¸w2Ü¡)µÙ·|=#ÛØÎ1x3Iº;àÕ"uaBÖÙOKQHs>«wö_q~*ÂX6¦ÛýfÆôL¶0Ýmó| yá$ÑäLêµåü;Hé3Á!·EýVåüÖú7Hß1ÂM½Ó'l·Xæ'ðÈ,ÈÓ×@ÔR{Ð"²W%GõPÊ@8~1ÍÑ{PÜJµ¼}¯þæ;%[øû`Áõ`gHiAôÓ±\\b±´e[úTÍl8GÆ¼¼]-ÆÉó¾|µRò._7Va{m&Ç CjÌNÔ5À²#+å&)|Ç;5­ºÆà]Âøz×{ÿÑ¦>v­*¸ëÏàTÙAÚ§X(Ã8ãªÕ\\t1ÈCèÈZT°ºA76´¹î'oæåÁKûí\\tâaÌÅ5@%;\\r4`ÉÔ¡Od¡u]ÑÃvIVzPBRtÖ{6ßÃþiw$Ç<úÑEIÞ©ç¼ªuRi$mÔ¹Th6PoåÁº¿-Oé)ºEVqRÆó`Æ5Ø>U&Ðp!¯å§ª1ízö±P÷g "¨Û]xO\B6Î0úÒ|ÊÆÆ¨Êõ?Í×\\fk*;ÆfÑ²¤À=uò£¢>FeÍÓÂýî¨(²ÒVï0Çª@s.ë¦®µÒ"/,íÏÖ)êöÒ®ÒÍ¶Ü<Fà!áÎßSÖrÌÀÚ/KZì±C»b)s}TÒVøF.Ú*cçB ð`TÀÁ+YùÑUÜ|Õ^à>×ÿ«ìd¸RÛ/Qt_02B­(Üy´]qx'fÐ¢÷xD*¦´6=àzX\\n{ÿB4ùÇv*é+Zä$K¹04s~ïh[Tm>`\\rÒµßhÖ­p­.×{£kºÜ¹Ôè¾Å8¡ñëßò£ò<º°³ÿÄ\bHbN2b<ø»Åã°aáï¸H1ÏÐ\\r5>X°tÞK9ôEÎà u{Æ#%ãB/Òè!|:c÷»ÆV^ÃcqEªOãüÏ¯JÕµë=³þ)Õ¯>BL|uâÆæné¹ôkIªDÆ¤L£È\\tOXF×á4jÏ³\\bÑ¹£Q\\rð0~{tú{oÎð"%?¹,¤X&ÒHäJ¶cq&Ëésô>^*Þ£\\nÑ0cÀy]ÙÍcÊIÔ,íÓ(X\¢ky7^óñ¥HúÚ]q°CÖó¥M8T.t¸al­Ýö={»Ä·u&ïþd^½í/¯E 3f/LÎ>»Üáã¢}.R¤¿Ë¾ë#YXeþLï|pâÜíÏ¶$3Õ¯Z&Vt÷ráèe|¸»<U<ö´7¬ ¾èóÛ¬ïãªfçcfùÔvî$øïY¸ÂjÒæ\\f)L5.v{rªîhµ6R©Uèe^3n:ÚàÊ\\bqs-2S Ç£ûA)¯»«·jÜÌZY78YU,,nä vùÓµÓ\\tA3àBàæ ÌP²¡#¬Ns\\f+(\kL[\\fl\\t!òìÚ¤T%Eéñ\\fÙ=¸Ó63ÏÖ¸ûö'åPÕ`ÁZýÕD&t­æ}2 7â%»y¤òx*ÈEE\víÐñ\\tÔðö¼î>ò>Lº[à©¤=* 4efª`µ{ânà5½S¯¬É·ù3¶2ÿ XÛ\\ráèeÜ®åBAÎV6L}!jd\\r7èµ¹ªNnë@<õÏzÂ>Ý\0èñá£Ê²Uäà+ïÞcBoÓ¬øõëIx¯qùòººÑÆùté©Únâ*±iñ¯w(\\bÆ»1`a}'×c¨öiïºeÃ\\fRì²GoÕF>6ë§Ó+OEõX¦û àLM×çK !Pë8·¹Óeòj§Â\©óÙ&ûíU`IßpõÈS³ãl4¥aõDýNÄ]L«$z"ß»¢(òÁFøÁ9p\\r6æ^\\nÕ²v<¡\\bÍ÷ ñ§de}\\bzíÚ n¯=ÖÿÿÌ3#;,¾\\fü;qÓÍI6;É7©~5¤ôY¢Sr_\\te¹56DÇ)-tëVÔàdø}u×£/ùG×8ñåøiÖ½)94áke©¹öU©\\r>[ÌgÆERÓn:$s[¸$8î\\tÔaR.±¸R3µîÇ«­úÐóáèàÎÁPDpr´8sO]ü\\rü×)pÚ²Åõ£Þ#Ré?Ö:· ©q~þW5ÑtçÖ]dÓDXA³°=¦«ªè 2MC ¾w#ÿï¡¾×o Jñx¨Lz!u-'ÿ{±äå4´ìÇ ÍZÈÄät"Á¬`^Äë^©«ìMá\\rÖsV¼-íºú-MâÀAqB¢s¹Õ«×l-X¡ËÂ'98yÆÕ¥²zk¼¾HXu»~÷>ú}+HlôÒpÆàì1Ö¨Æ¢ß Ø`Ü°®}ëÔEÉ<3®lJ#\\t÷:ôµ¶ÔU°Òì6ÏX\\nzFÊwÉwìØÁT¥ìsg½.â#nÁ¿Ëó]ÙÇÅ:Áj!KÕ¡ÂØKç3~´ÈBî,.>Âßâ!r6iÁiÇê`ÐÓGZÛqC4Cßeë}`¢ùùÓfjï¥@Ún0Z7çåe¿;-lÿ×¿XbÆ¥\\fð¸ÙÔ\VÍ,7ÞËÉ¶±÷^ò\\n¢næLÐL1÷µ;÷!q®ÏgWqSòëë9yB¨^®íÙ®Ðì\\nk`>ðÒ²u0î)xÔð"ìÒÏf+¶¦@Ð!ET,f=Ö\\rnkçÓáªÈaÞ£wq;»ÖËN©¶SbUôb¤:[ÀywA<Ú¡ÏAÄÄ=î>"£ÄR+Au~Ú«6\\rj@»x«§ýÉ~CëÑ× 1­§DÚØ× a æmÅzmKmó £M*h¿pÿÀ*<TîÝ¥ïÎ-1Òs@+*¢Ê©Û³N 9Í"É¯<v>Eaó/²µ=ùHrXb¦qOÄ¹  sRèbÏÅB\°ÓÿoÂ£5v­ÑoàèVÚ0ÄD~ºj%¾ ó³¿_ËíuiBôRåæ3¼Ã>"ä³ø¤·LvRLÛa*4½lpúØÎºJ0î\\r³1×"6ËV0Ú®¾u;¾9uÐÝî°Q#ó`ÒÃÞk/N~¶ô¹²5~è2²£?Ó>\Ð_^ÒÂØc}²¼kqã¬D¾Û"H£õ[\\fêæô<fÚR½?,]ø¸ESÒ4ø\\t2DKF¥¿5`¾-%§çXÓm:9ºZÛ\\f<ÔÐêØ?o\\bº¶±7yíVÌ@¥kqñÎ3Â¹wa/££<J»2Ioç,ú%d¦C1³ß¢÷µa>]Ä-xÝôJ8nºÂ-:ÛÔãçÞò2Æ&ÄöÃè<}Âçýå¶O°Ô¢}º@1çæ^{¸ùÅë ÞN8lA\\nÐ \\rk´¶æ¥\\bÕÿ¥FR¢A²Þ¦9¯ãP2»º?(iseX¦Y\ír2æ·¤o^Ô P{£ûµ¹¨Á'6"+Ñ¼Ho\\b("´þã·4ö+ÑÃª\\f¯'b{X¯TiàJÎ¬Ø1aúo¬!ÿKpøñ'ãZd*{*Ë:AfRºELnñn¶ÂNøÙ\\f»%I²9µ×FÚoõ.«Å.ºS7³Ú}­¾|YøàÆ£ZêÇ\\f¶YÄÓòSçÒ¸÷Â7È%ìÄ[u2RCÁ«Zf{1\\n<ÝØV¸«355Ås±ÝÜmÔ¹Ê>PÍ¶'Æ¢«È--Óðõ{÷ÝFg11NÎ\\né7Ø®(3R)'nÚw.@;?z¨ÎJ4C¢%89§æ4½/`ê*<þ,º\\fæ£È#~!#C§ËpåïÐÈ!Cé^Öná$Ü¸á;ëSÚ8¶'´HD¯|á­ÑðÒlQdSó\\tE+uíÃ×.Ý h qÂv{ÑéðÖsÔíoö¬âÖÌ5c2 @È 1;B'ÈÿôÁ¾©º7ò¨ïéµmy$YÌÊ)ð LOèfµ=ÎK"t}EeÓ>¶/3/íûKMgoxù}%Éü.Q­isVú_näk\\fØ\\r½6(ÒÅ$Êãp£$LÃ®<&K®Z9½>¸WóAÀ0yñ@Ý¿.ÔéÀGÕ[&^#ÛÇ_jèÄZCXè¯#ãt~¨rÉàM1}09fþð§8ÚLÃZzðÐú»&J©·ÑPÆmzE£²÷n ñ v\\bÿXë7ÎÝ$D¨hRxõp mÕ¤\\t~÷ÑÓs3¦T°øk£ó¦\öÚ!¢|`ùY°NºQÈÅebÄ¤Ö× @rí&(³sÀäå-e­Cd2«m5f|ýÀbòÚ³üÅ§z@}ÙýÈR´¬¼+n\\r÷¿dïÌ QJ%â\\bßy\\rÛÓ 5¥èLü0¯å&V³¹å÷!îkP|iy>\nÊ¥tH`Ë¥?8{óÊ÷j®y@V?;uL_³ ·r²þz?òÁVïo¦%wyÝ<^÷ôYøeLþ¾:¤|ªI¹Ø~zÕÂ.b}^´Èlþvx ÓTTÍ¶1ÛÏb,yN´pL~¦ìínñ¡bÉ]G_uñß9~_b¥!¶/É?ãÖ\\tÁtÞ¼~à9¼ôFëÞ¡ô[­¸'1mú÷W+áºà´Ì\\b³p±5Ýa/©¯¾¬Ûú.ôÑ.hêß\\fjô%Hyq£-óäXcõlè-êI.í^ÅðTÆ$^î¢ÓÁp\\fô\\tES97ºî¦É­A¿Hì©fÃÀÂAâægÐ¦t©ÞÀÄ -ZÈAhwáæ¬%\æÔ\\tf¬Ê­¼ìL"$J3úËn*btýó¿>©%ìa<0l¸®\\n?h%üæÚ>uAÌÖ³\\rl.ÿ5m¸'¿U£ÒÕxï]ªDæ&56ü<6¬UÍ5Ô ù±«â~÷©Æ,*É#£±÷Î¿»fèpòÓrâ(ÁôG&ÒQ¢¹\\tP­c^çkLÿ[´]ÖÐþü~>8Ùñöñ¹¸È\\rDE\\bs±_¶:l<ñR4þµÕÁ¼W×RÂ%¶ìã5ó@K÷tJéé,ùMó¨&­%ÿ .òb9-Ê8¼_*9¯Y7WþÔdævV!9ÝÙ¢:Åiæü·8sóùOÜ¡[d/xÑGmÝÞâÁ¡ZÎ2±F´­|:Ì6®<ziàpJEejv;3Ì·¬:ÀÍäÁâÐ+C;Rô¬Îü³]Éwß`Ês²!Ã¬çÓ»EûZ´ÓFÇã:e³.GhvmùåíB»ÍÚh$Ec}¸°½Áÿoz\\rô?ëI@-gRì¹_/Co/?æOP6ÝaßÉ{Á2gN{µÙ×MN"0¹èsçaÙ v9 [¢ixõrt&;IÜ3ý.eFI7½Þ3Îw!¹öù(b£F\\n\\f] °yWõDøÞPnppZ=,½ È­©ûî²°Im5p½¾É´HTÛ×§j]·ý}Wji£©áÌ5LtÃ»pÏ"KÉ`ß¿exù(_±"iXË%w¶Pí\\nINêR0}Ñ>p7Ð¦kmxíË :õÀ#OA]/úÕ?íYþÿ*ÞAøt~d\\n×\\tCI4åóÜ]ÛB75ïm2#Å[Ã.'}M)WßÉúZ@ç÷9uÕo·jÔ:áµù&êFKÉÀx¼]îp-XnÃÚÀ°J·ëQSÏM>/c±úþä¡ÛÉ#aÐÜi­RßÛèT5ò1Î v­ô+ÏÞýª\\tÛT-ÉE\\nmc³U½M6+iÿèO;×¤Á{A¬ÔÁÞ\\tEóhè:ztµH¹\\r>îWx{èîÏ\\fýcDË\yáÍc«ÚN·HÞñY¯yæÀX³öå±æ\\rì_T}Å0iª2»ù»N¦ß8?Ç§_/{Tq r4\\rç&ÙÛ:ô×³â 12:Ò÷p_SZÕ[3~zÓ®H|öÒ¨'¤Êk<¾ÉTàöZÃt`&ÅêLkÆy\\ny½¦[Ms¯°9ôL¿ócÞ;ßÖÄ(,TVþÁDËêäó7<:20þÄºá0i°~Îôé«ïà¬§ìÏòE%àñïÚÛ£C®_V°±´4è$ê³¨÷ï>·1!EVØ[`%n}&»º# lác_ê²·qÔÆ7 I÷ÒÙ°¥Æ\\n`Ð\Çkù§ñ$Qé¹®#uºç¬Ä'g«ÂõÝrmÉoÄðO;$¸#²¤ÈÆZfk©¹Ãvá.èC0S)7JLÔ® Zr¯,ÀÕ-ÏEv6nQ^¤ %ÒñÚ®ê^\\ra±\\bÅÕg\\bç©`Å{²ÿ°®Ó)÷w}Á9ëS¶NÆïæA£©Ö0 {°yP½3òÝ®ÐXvãkw^~òÆÚûüdbÛÆC\\ríîtéâ¶ÿL,[©ÒÍ9_¢'Ú)ßÈ¥"yf-ó7ó÷ÝÖõE:þj¿´34çKïÞO¨MGÎÀ¢aB²,v­1Å¾²VÒÔl­@ÝD£ªäFc=½Ë¸æWÝ<6®c6¤ÀI)o×5ä"o)Æ]íO\\b ,XÆAÁ{!Ë.©ÖTýT­y¡Xâ\\f¶vWÿ9¬n©Yäùü,\Lè-],/À9[Uñ¦aÍnCCMêù¬Å* bÙ\\fI3!$ZJm¿WB!ÇWW\\t8þ/í\\t[\\n-z:û¡Já·¬äB¿èþlb¨ô6;Tµ[§Fj<¸Qm¢\\nânòpèÞ>¤²øºu¨Ûàû­²Á¸IDÂ¹Su_Üïtz7«bÍ,½ÓßjÝ¦Î¥iv Hl¸@ßñ,XøZó×1±SÝíÒìê)4gsHm=¦ìàIü¾©¢8¾R,¬~Í,V4&´#·ösÒë£êÑù¹,wÏ¸Ò_Ð¾:¼¸öÒÍ ózÇÔ;ªÊÊ&Õ%l²zÉE/~êçW¤·bjø+ ì¡1ß¹/ù¹>`Õí¾Ã,úwEÖÈ.[µ«§(I½Øu/Ìýþ: ýº½kmHÎA\\tDCÒ¤~Bb2²ÆAIq¢ôÍÓÎâ©+àA\~íåKwóµgÄÂçTâÇötè\\by®7ûË{u±÷V2É¼k*;|ÉÀ<~C0¨[}°oÃáìý!:¿RÚ#ÍÏÐËsçµËpÙ$\\fõ3%ßÆ%4Åçk·vùð÷^\\bèX5rYu<Á«Â"c *+s\\bª¼*äÇìÉÑZ'+éa<Î>«ëhouy{´vå=êÏ:-!ÄÐæ]Yä}Ò9pðN\\f¢ß^ùnw4jL¡"Þ®Ë»r8x ù~Óhò<(Çqh`A>p(¹«\\f¶]:Õ^Ò5*7ÞoÊ,ÆçËuª#¤Õõ$\\fáÃ¡áÊp]?îSÊ´AgÔPUO5ÐûÄlÃ>N\\ryiGl¯!*$§4f³çßW©²CÖûåo?á4Õ¬iö(ÔT÷HGGº,¹ áõì§Mc@Âã¾4ýx¥Äê`@Ëwºs£mvô4òieÚÈ4×Ç¸¶ÆìB1\\b±Â0l\\n Ðlü­C½!'ÅìqN³3÷ñýdB£FÕJJ\\tJ%<h2AÆ,ïÇÌ½m[Äe6UÌ1«[s´ò9­Ä³Êï±hrQ:Ðù*³LñoW.ÒáÜ¯zÝZç<é J`AÊ«\\n'gbQ\\bíÊÿ|vÎ0 (\\t1¦©L}ú+ÅÖ¦âk3C¼"´uðÅ§o®Ý2ãÂ_Í(]E57#`\\tF/Ù÷1¾=JX×+Çû¾éå\\tXÜPy%s<gO»Y jlXÓ·Â=%Õ·¤Ì¸×Ay|p_Y-­ª÷ô(¡_t®5UAtp!NóÂA ãRürj§ñrûjÊö°(&¯R¹|ØÊavÒË-KË]ÿ-ÚèöEëÕ\\t2Y÷<«Â¾qì5¶ gA«Ê±~Ã3¹©¶°þ}§.çN±k¿¼ý\\faµ[ù¨i©¨vÒIÕÙuYJn¾ô{ô©\\bøm\\fò0$oè!äqxQÄÜÖHK@±Î¦¤üCa«Æ¥Ã]¡K´_A¶IÏa5bïo,óÔ<¸zB«Ò¥\¦@­Ô?\;*+Û{É!äbú0d#dôeÖa\\r( ä0åÜeµR±6M|l\\t ´k=Màkãÿ\Bg8\\rw£Ý`\mü{ÉÓ\\t¸)B-;7Â­0èq\\fXjæ"TÛ(]ÈÉoÓAkvÏ;[}äÈMyE·Vó£ÂÐÚíÄQÌº'V±ÅÎ°?Z'¦£ïLh¤ÀmÜÒ£ñ*9ûWBøj<pcè²]jU\p©{s¬Ù ¡À} =Éñ;N¹m;nÇë,`Ê¸?éÚj®ùgÌÙ_ùVü S¢àu5ÒýUîrh¿ø0,M`ÁÜÚI×Å68\\fCÝDIú@8®³!çtEyNù<xz¶WÍM\\nü/LÇT]cíD_\\b|p}þû}AiáóÇãÿäÕRv¦C¡¡pT­|.´ Iø«\\f5IÝ BÒ\\n²ñp9 ¤*P\\r|síÇqV´õÜç¢¡@ÑõÙÈË× ñý\\nÂ¤\\nU@¼#£W}¡|o­f#Ë´çI%Í·¬5"Ì÷ñ~ÿ<óÎuAmV)ð#m]ï­¼%$4ú/$¦ÁGÛ¶._Ìa?åAXoÄEPÀå>Wê¡ªFúµõlhªùòÈµµ7® :Vò¾ïOç\\t*GB¼ó¤ÜUùEãÄ?¾Krø(ÑæõÞl:Qí6j¤¿õsáÜªã?v¸¡ï·úÞbÕ~ k1+ÉÊ`YÓv¨2zJWß"a^ó~RU¤K¯\\fþÄBø\\rT¢eµ¾Ö¼î¬Ûq?qÍØ¨å5aØåÞá>pWîîõßMjR':ÉÆÔYñ(p÷±»º3åkd·(NàØe®÷'°Kà¢ùqèúx«­ë£¡»mSõ¯Rõ`Åî|©ªPÎ\\r¾Lqñõ@¸ÂH¯ð±g­7zU°ò»^¬¼æÚvVY<ÿ\\r2J²Q®?Uägy2 ºÃÝoL»*ßÀ»©@äMb¹ò¸/B_\\f'KÙan(Àß 2E¦¦0m¤E¦ªoLö8éûí¥gO¸hËó×9Iÿ7Q¤è}ÄÕO"±^öÖäç®óE .lpË ßæt[ã*/ù©è§áý%Âß{n¬ºÃXTàýÑ­®PÁ$òi0±GS%(/×6ú(½v&«ÏNÈw\\b/½]k:ÖÍº¶?Üüx ´¨?nõlrÄ~5pGü6ë¾*èCõïú½#þ"ç¥ÉÈ®1G°[\\fRX¦Aáª)\\té §ïål$\\fíUr;¶"7Ìæ2.áfÛm,~PAvÏx.ÏµEZU,¼\\t5`CÆEëVï!gwr^8õÕã²'\¬ÐX Ü½ÕU¼ùE£r¾6B?A!\\tÎúÑV¯#ÁÜhÌ[$Z²»d\\nAso[r·;7,ß¼yÍØ1>V¼_WNm ÂéøÈÅM\Ãª¥äöÓ ìËÕ(â¯PÎ¤v^Vpè&)æcÝvK7ïÜk1èÛ©YxKâ\Ä%º7Éòoä¾×¼¼«Ó¹gÝ°ôyVýãËh%¢Üa6uÑTùåÈÃâ6ëäk]l^¥yélÁE·RsÜÉ/î}Bba"ÈäáÐ6Uï y'mBòn°ÀHè,<©`&${\\føÃÝÖù>ëüÖ¼»²®Ql0hî+R¨b)¢ß²óPØ«¶%ôhéâ¸4ÓWÝýÏµ5QâvL.ôæJ´t8)µãCÓGeaaG<\\f4dnÉØ3DÔ°ùñXxéÅ(£oJtÃN$lßí0¹u7èB«ß`\\b$¯ îÜ;]3 \mì_ßº \\t@ÓT}AïòWêåiåOu¨¢¡Êøjú|e¿-xañ¿=ûÉUä_!Á9®3mkôzLH:·ý9H)Û*ìÚ\\r@ÅÐõsÊ4"¦$s½ßÐÝÿ>Ü\q&¹àLÒWI_c|C(bp±æÈEñÓÎ5Ïô³KcË'_«itaÄ9¬ü§c§dp÷|]é£u[n0Òºr+p{üþë§]wOËWàpR¨ ÿÒ×ÀÓ^B`&Þ7r=G¨u1&íÆÃG&{1\\nÃÌÕOlf¤k½ÈÎ]iXñr² »I©î0ý17IÁÛf Epyýª¡{ õ çL:k®ÞvãcCÌ7V³Ç5$Ee²Ê¸¤ÝTë¹Ã6r ÒÎ*PÏøÁDÅ\\t;Zºi¸¬V¡ì%ªäÁ¥ZíkõìÐ'¼ ä±uë>·Ø5¤W£RÚ(4Î«g(k ñ÷7r|1£Ìçñü\\b>füC- âl1)¦èe¡Q°¹<¼â¡´ð^Û ÐFÍ$â;OBHdÓÝÜ[YèPºÆØÅ\«"Ñ\\r{:\Y<Ó]#Yïc2²_\\njV»ûÈlúÄ`TÅÃt7i9¶2ªR¹¿LbEFdò"»5Èòcµê1#+Q^ª±ð¥qÓqD¿¡É/"ñ¬ãÍ\q´ûïQöbÄÎ^.kè"æf¡j2U\\r8À*jo475âz×\\tÆß,ê1»ºÌ»ü³nÑt:{øK©Ä¢æàú'­ý¤]Ôêö)\\r;/Ñ±8ãâÍ+ð%}+±F ïXÑÇUÌ}»Q¢­Ëâ¿2õ\\ruä;¢\¾)Gê¢(íSUûÉ?_\\f)íHf3KçcùT vÈ¸¯ö4/¯º°VQ0R³p\\rÆ¦ÿá;WK'Nu:"di[e\\n\\bKÄáNEqîÁ?Ïq+£õ°BòØ?M»Þ}. úíªiL¿DÌô°O²pï}rE©ûÝßJ®¡«b§À&Z¤~A\\tñÐAË¶¼0ïÂûËÜÌ«¯ã|Tö^ {áå¸øña~S®Ûa ~VÄüU UáØZ)Qlõ!ÆáÝ÷}â}Î`0°.±ö×·Éù!èÂBªØsXËF?;ý$ôÀòø'-l¿®Õ_kTQcéF³)&c®%hÑ®Ù¥D0Màëë$þd7È(7~K¼xûº¬ÆÇ)Ù.z­!D7]4Hûs)l4ðªO\¥62e4ÐÑaD.éªÙÒ½ÖÅ3½foÜ+áÝxêH%\\ræWÚ\Þ21Y=DyñO\\bâðØ-zg1JÀìS1ï(H\\f(|û:£¦Z}y§#ü±jÓü;ôs=ÿøÁã~(÷ï0jn4Y5Ga¬ÙÊÙó:³9³L]l58¦]Ù2äZÓTd¸¨Ú¨ª³ä9½Ò.¸o"]AÞ[tká¥V²þDÕ<ñ@²+*í!|e["VÍ¯ÄåJØ\ÇbÝe¾ìÒãEúÒ¥u²C} mÿvXW£=sðÃÚ¸rðXì³Ì´zÇ$RxYø<¾¢%Ç7b§&BñÆÃ9U/òÿÐ¨Ãp#ËÛ>ÒiZGüA© }´¼M*KÔ½£ÞíFZ|ÑPm)¹oÁ\\nSÓßU÷S_[æÈ:6z²^ÙsOltrÈÖM×±å}ÆHñ¾^ÌíÐSc&b$L>hHY!û ÏK9^"iª¼w»ís¿q0ÔEº´îsV±`âÜö Ê¤[å']NZ'¾í3³Ë|nrWºðkjc\\tWzcT¶g(¯zc÷µxË¤¼¸Ù»#c_ñèÜÄ÷Ô:oòn$º?[~<n¾]ÔxcY£G*¬¢¢¾¿1U]}H«¾òZoE/8Ôm,(»,þ ®61[ÙV/Ä,¥qâX jK§²è\\tÇNOéÍ­ºñZÞ(Í6üzo©kÿ«§\\nXD]âñ8¡»ÁñHæòGkÿ@:-{¤Gv¸*ñ5òuºqªÚÕÌ\\b£6G×-eòQ3e-$=,6G[ÑFÖM>h8=#l$åÓmÎ¿Ò`¤.H°c1¼Ç/u¼¶KqZÒL§ëî¨­Õúç4BhNÞkó\\t^bå×!Ó5´;ëPQ5öøNÅ¨\ñá§l¾ÛuÓ¾Æ²ãÌ£ZØJúzÜeN8×¹'äqÊx]U'5*Db¤6Ð¨Iù\\nÝcÔX_7^Jp T`á®OÁÜÅ<Cëø)°7ØoM¤nTÜ×&B5á{häÿ&EðBy·'1öö²í-Ùfÿ[pï½ßÍ¥rD9¶ª]2¼1j(V·£ >ê0bx\\f\\b¡h2=9«98ë\\tåiÈÈ\\r4¥j\\b-Í¦CcÄË6ä?â~aÏÇ¤OÒ<VÞä@%X2 /&%?J=kÿóê\\n\Ú29ô.Ë3µH­mõ\\bðyã÷_§vÊ^ãÃ®T/Ý ²_ÜÔ­lÓjÑýÓÇz~.l~ØðÃ¡ÁFæVë2l« K\\rR"aíÞ2/8u¦½ÆãMíùóm]Ú P¡ïÙñ^!X4eã{,\\r×pt¾¾åSdiFFè³ó¤I«Å¡\\tÊQÈl!y¾59sË4®wÑÜË*Û±t^5IaËú¢Ps¬²5¾+ªÊ«g;Ú<uÏ²Ù={ ò9Á+¯UÖe©"LM/]"q;]éjS~µAt\X"ê.TWåXÂÁ´æ`Æµü@ðäß{¥ÜkG®°$ï³1[ÒÓâ«]è6X*=5þáTîïüb;«íå5#vKËÄ¤i"}¤"*AúÎø,<{§ôå´Rá×3KSÉ¨jñmñG%õôôöqNÕaÑ¡íÙÞÆº"wu¯ÈÙ2´3hhäþ¾¿¸X4·CCõ :¡DBlÉw´y5ßbãüÎ;ªÁã(Bº:.ñÀÞk¾yæz$´7HÎ:_|dü×rR©ÂP¦sä7¬xßÈºV]ÁyS± Ô\\n='øS¹xëÊP£ÆGà#¦\\r>\\nL#ÛpfµTÇ}~P·æ¹1Ñ¿kéJMèWëQXnþj¬öp®)*bnÚhû`\\rÐ9yp\\n~Ô$v#¨Õ»h´pU$=58øaÒ×ìüä¥ú-ô »<(÷ÒORÔ7öB¹íìN_è[\\t<ãM)PFÀ©bÙ@³\\b»ËZPw^S¶áþx/Þñy^­ÕhÛã!|ýIá:Ý§¨MhN\bà.­ñC¾²Ód+nG·Op7§¾Èó´¾Ð%w^\Ò¶= ½?Çr]8±&òèâb°uON¹ú\\fÌE9M¿Uòó°ÇØ3~ZH<Q½\\n8 ç¶H¾$ÌÌø6|%»mÎ©=\\bñ|%n°ÜnÅæó¶«[¦Å¤ 1±Ìüeú³¨?kñ1)ÁA¼gÖ­ÞJÐVrÅ>5I©ÎªFã ¤_¾¼8ë¼1ÁÎ8lé¦Á¯ÜÉ|.îú¨P«El8){bCØ>1ÎÿÄA/u2%ÙRÆqz[geÙÂþ9oG ªQXQ3tº7²DöL®a²â¶ò@H)èzgT'ÄÀ9=yîgÇòê¤XV,ñ%¸ðp}2É?#èÎo\\fÃÄMå§qçc:ðÙq¢DÎÒAì¬ú£aÑäà}¤í&é|üOK;ºÉq%òhî6Ûër'.|çÜI7k*¢¢¦Í3#©kå/ê'Uå­jV¿jßXW|®V'Øj©xWUÉgX(Þ¶|¬à\\bÊí©Í:¥ <¸-ÆiÏGÎ\\b]Î´Õäø¸ó¶Àv~ó¼ùæ?Ï_9:{R§Vô´[ä¶\\n¾Ês¯«¬Ã2¨p¯øÊoÂÿ o°xíá¬zµ.ÇªRümÅ©>:Òp­±Ø§Nª7£ML%ÿ¬ZºdýGÛN¦Aé8\\f¦\\n= M« ç\\n\\b³´Oø¼"ô)û6B"x¬Ì5\\tÍm«ÐN7éµÉÑ³Ù=g)Kµ69ÀåúE£Í#É·ß¥-í»Åc¨1Kó»îß¼&xÇæ F5µ4¸Ù>Ýg.¢¬þsÓí'3dÔ?ýæcHIÍ\\fOhp9Ý¼Éö0çlåZÂ QwR@I7gêý5á1ÝÃü7Èk2êbÚ\\t0\\r$¾¶ÕÅ Èã±D8ªzbêK¢ôøòOÒræÎAoB¼à>MiÂü¬16òô3\\t×ÂñîÒ*Å¶ì³¤U^Ngåy[è­9ÉD<=Î½Kêê~'¼ö×YÉµ;Sô*!xÿ²;TsÚ6=Ú£ãIÿ6£|OXzÿö®jAýcÉ¤ô°5z7+Ìlä\\b ÞÞ7ýKKÍ×kG8;1¥®(DDÆò&úIlóëLkÕ~è]Ó _#Ü`tgñoh78?ïÉ[=´FzÝ7óõÈÈ¯{Ðª«âÞÈÎTj]xc7×*o|6§Ã\\nbPâX|ÀÁ«ë{Zã+ÒÐ¾1!ýê¦rÅH³h¶{ÈÿåÓjù~óJ½7¬ÙÃDÔÃpC^~:~]+25xÃóËà­NwwV*I±)~Ä¡ï3=# Økí¶xAÊcÖÝÂø-Íÿ}Y ³P¾¦âî`<ô´&"âw³SÏ2( ×Ò®\\tÍ#r°Ïè:Ð¤åMÌÏ{ÈNazÉðËþ²¼èFø%A_ó£ÒQÇd*ëffC9ý>æ|;CÃäJ¦ 9AÚò-QAi.ÁÑIR5\\f¡ÚMß7ÂÄ¥ß\\rU\\tc¢Búó\\t;/'ÿA¢í*ô`ï s\\bkÚ\\fË½ Ì³;Eº©¡µÿÞ\\fjÃÒIu\\fÐôÿsæÑ|wÝt-\â+c#A3»z¿#KÊ¼? ôk=!^rV#×ç*ro®o³oEMhÝ±ÖX¤oÞ_&#9Gôs·dæ$¢ÄRÚèêÊWc·nìÿtÓ§åë¶¸Ã}dWz\\fR]IÕü<8(wù¤¶íó*÷É#Ía[¡¯3\\nVkWtÇWVMáU,.ò Äsø´Ó§Xq·:ÇEÝ{dkË|Y¯ûµÁ}²ß,}CÙë¶lÁËwCÃ¥tôQVÿÚä©NÛ$ËA¢¬!ñ»a%¹ky¸ÿøÈ0íó»Eñ?¾D=é/ÂÃÆ¥ Òm÷QÖ¢UÄÔæ·P#D»#à¿ë+¾üR¿cqEÕ¢®Âéb.`\>,^ÓÚÊme2±\\tM¿éºâ½J® Hþæ¶Æ|íÈyqìY\\n÷r;òÈøË`×M¼71Pø)¾Zéí7Y­þW8ÕU&ï")çL£ÞLL:TDAdvýnãÖfÒÙùÚ3Oó%­æb\\t«ÔF¹\\róËuÚ\\b½{qÙ«uÉ°vB~É¤{¾ÉÏÄzØ\)fTàÄìhöÛ^Ôõ°ne·oÅ,Ãkf¿:÷¡ô öÙÊÞÃûVP§Å>Ìâj°,2Æe®´×³U/Þs÷»Ô:{FOO£(T¶5Ö¹<ç$GÛÿ÷õ]É t6'í1L ¥Ñµ÷aÓÙwÌôp¬?äeE`³dìÃÿÒðÕÖCÿþ [vÚ-­ÍåeêYñúÖÃØOõ %\\bïG*´ï\\rÝeý{îVCQEuz&9nw\\tö÷\\rüïÅ°§ÿCÎWZøö³íôBÈ-|A*qX¯, ÷ú(ùyÇ@"ãè;¤dvQ\\tßè6^#°Å[öbþ3D¿tzÞi"n%*{¹ÒÇÜ5*»*oG(Ä«ã\\rãà¤"sA"Idõ/¢ÓàiEO\\toelvÄGC0zôÉðIU0~Z']ÂDÝbùc¹ ×Ù½u­-l¬g[d$EéÐ]!Që\\fF§Âtoá?Hg áÐÄÛüåsã;LåÐÂbÊ"ÌT1qH¥EÌ<å¨YIQøÙG[\\nk¸/×=±ûæCäÎÞx+Dp³B*­ñ0¸ôÂYt3K4æÆüuä&qkêý ¦BWQj¨ým7Z­,:ç.ãhY&:jIÀû*ôÂ× e­I.£þqñ3¥\\rÑç\DÄ^ï;ioMóEhNîÇ÷²ïxzÇãöGýWy´J ik7jçòdêÞ:còq'Atºî¾:Ê£Puwid.'·}%bÑ²î»³¢ù§¦Döªk5¶¦õ¶Q¯N¶[ÓdG¦@s!I("¥á\¸+°÷îD§°ÖÊBçÆæ\\b/ßµ[¿ÎQ¾<{Ù8u¶.còIw¤Jð_Àm/Hü¡;æQ"Mæ%iÅ«KNq·{2óhCæ5Nßw ¸NXÕÙgQXÃOQ¬\\tcÃ5bòQX$¶ 2|aÄ\ìû§Õ6{~]NÖ\\n)Ö%&À¬Ê(cø~£Éð{ÎïçÃJ©¤kÇ;ôfÃhÎ>HÁ+!\\n³¼ºó\\fýik9R._³òÀÀ\\rÇÓÛ?¬X¹Ø=s<SÇÚQ2£rýlQõÀP­ò¾L´9IÅÞ1{©V©%\\b°LE}Eà7Àv}cÌÏèóà:èÙí¬wHB×o¾ÆòÒ@Äg÷lR¢é\\b8|ÇÖº¶÷ä~ éhl2þ Ù_ônSû·Gmdîî_£Ð±¤`R@p7Bx¹* 05Ä$C±ª³(0øy\Í,0üò_°ÿg¼aý¯±0w#Bfsröª!WÇýo«CR²µÏ¢äVd!mJ2ñqnaJª¼Ø+x¤;õ¼2æSw±£+Ú,w{²Í­8Æ_3­8²i(@­*>ÝVÎµý8 ©ãC·¨²vÇp f] \\fØïç\\fU²k«¸^`$HQ²Éà&Ë äsÜÛnWÖKÛä¶Ë`xòCRß¥V\\tì ¸/Î?êkô»ôiµ%W»DZ¥?ÏÀh>Dsag9TÉxB\\b[ìNÌ~´@Pl4èÔgt¥pÜ¿0Ñ¶D©"/KkÚØK+=°á£¶ãÙY2úÀ=a¹ùJÚP\\bO4PàhQ'­dãë&ñ]äËµ;²Ù/`¸¦5>>ç·Õ}¼\\buQ½f~8ì%ðúÏífõl U/Wgd30jí÷}çFÆq)¸¢®Qï¸HH]vÏzÓ£¬^¸îÜ»NÏ^..ØÔFÒC¡{ÓNÉ@¯û#Jo"/3¬4çG ´í·Q.¿r¶½QË+WééÄâ\\r7?pðÏÎ4óQ¦ÆWÀÅÎi<·hTã¹OÌÒ«|ëx<p[ê¶à¹ªÍüs1®IõûÈH*È Þ·,hê^Ä_?Ò~{EXªåéâ±^7*ÊiÓ^%öqÞ¬Je32°JÊ%}ìoõ¯ÿðéO@t­6ahÑÇtÛ·(5ÓùPìÍG¼Ü½Ïs²\\\fø[Ý%½f/rR÷Åuga&rNÇh3Í¸ýííÇðâÈ&òHc!Q.4KÎ%0bòaÎ\qeCE¶Ø\øÎ\\fvó\\rÃ\\rÞ©0í'?-ßy!ñD{ñ´KÕNóNWHY[÷ÿfîðÍ¸WPo¤W=TÛ<fÖ¸ûNN³ÕòÌÖróWh;²wqb=L*×Kðtôj÷µ%X¥}ÊV8õñzðéúJýûf8æu¥cýðÌ{^m÷VM±¶\\rY7[I#ÊEz *ú<\\ru'°igV­J´'×ÍJï\\bnþ¹+p)Üöó»m£N2ÿ~4uïDV¨øªMH3ÅàGdÃmÚZVÔdê-£§uFË%'§­D(wvòô7PsÖj/ºaðJ¯ÙÖR^òáÉ/+¨£w\\rÔÇSec¢û¨_ÞJ)ºçvLQëF¿¢¹7 î§-¶W`ìrçÊ@³smY"§-U¾ò·Ü>;¹c}òl¡jÓ¬¿]¹-hkCé\\tp6 \\n4£Ý©a1Ídå®äa×òSVäÐVÄÆÅj¡²Q²ªäL\\feßÚá×Ö¶¹¸ÕÌ\\t¸åO\\nÐ-;>s]É8ý§Zl·Z½xYhúö>ö(ªF\\ròÑqÚ·Ë¼ºÛL j\\bRóÍ¤â2½R÷!N&Rêã8ÒwBKË[:%X¶¸?m6(¹ýëù_ì_¨!ugM³±W»zðP"±3Øp=vH$ÌÆJ<aÅiá´øÙÐ%m\\fõüþ»T·Ý*3¤¿!bbªz-8Ìº¯ÿÆ,tXZ\\fÞà¸¢ èã±*®ÔæDY\\f8rkt¦õ¬Ióàñrpòzüèß9¶O½ù¨î§æ:L¼:¼Ñ·©K°{Ü1ÖúØ+ñùp¼Ñ)ÂÿÞc8_>ÒZÛ5(6Ó5þ­ÑSõIÑ(¿)iªôýs£VJÙ5L2TóÙÉN2á¾JiEØ÷$³'@£þ,×mñâòw7¾q«Âð¼A\vXqëMe4ÕJÈð¨aw 9ÉQa#sò4OÛÛ_ó+8ËécuÍ.>Oãt&¡"Ú´Wò ²þJÔý:×¶UÂ=2#sÍÖ°sãÀT½ÒÎë½^\\tFó\\nÿ¾¯ YÔý;hb:H¯e=üõH&¼Å=KýKôjKAtÝã[Hp8c¦«Ñ\\rm£­.~-?\\tF{É5¹Æ^ÜÉ¨)#ä±ù.\\fô`´SoÄÞÓ:pIÖ®»Ùç{øROl\\ryL÷ ®S\\nLdW¶k6úÔB/0\\fsÚ×3xeèãÌÜÿ×Ynrþ\\b³¡(6-ß"é¹åyÛ@pÐÞ4ºÆC2Îã²pÀèÎ }ý.Ì×±~Þ«Ö¡\\tÃu:qPâG×M¡þkX§k s¿Vÿ­P_ß¶®.­ÞMðµ$®dcuº:¨±\\tß'6ÑûOâ&YBÿÄ÷nïi¸Æì6¹øÝT¼Ó0\\nÖ[þ¨°Þ ÍÑðw%k¹± \\tÓ ;¤%\\f¯_3èKÒÆ eþÑ/e [#uÆû·HÃ\\bãðÖN@-¡[=Paùè=îÒÜô÷ÁÓæfÐ±¶50<¢Ñys¿ç\\r­0:A±°ò¸/Ê·Ño>Ð?^ä}8M*0ÛÑ§0<ù1²©Yñæ¶yHÏ?OÍ»Æ0CEê7ë¨éÄ¼<òm}#'¼{§ %ÿÎÕü\\rBEDÖµ¯´°y/5ä°1ÚcÎ7¢çj²g\\rÎMß9R.³ÃLtºÎµ¾<¡WÃá¸ÃÙß>0¸èÄ@ªOV¼ÞK%*1Ö*¦îü×ÿ]¬@Îg&*#$æöaÖù ì×^^isN?b|òü7&üÆt«ã8§ÀÉéâÉ&4-¿x«ñ\ÑT|YåöÒD×é"Jz¨Àã ;¢NåEqp·g2dÃÀ1Q£â3³ g\\tüå|aÕVtïK\\n¬jtÅ¥âB|tdù(~´SÈfcËNynÎ¯ñÜF] Px]5ëôÅçîoBâ]IIYZ v1÷o/»ûÇ FUµC\\bOþn2æ4\\rn>ÇMxûø4q¹\'í .ÌTgñÂ£Æ¹ûÖêýÜK#ÆÈt\\fYÓ=~x@Þm5Ía¯Ý8n£ëñ¬¤_¡ÙÚÕW3D&Á+pØàNxIª6UPh3÷¯#-ÕkÓCÌ§*HÁ^X\\tÜ{¨sÄ¿zå³w bJLhp^Oó¼ÙbØ "ÄCEcq'R\\r¦¾¬Qb[òÐ(9sP/¼¶´³[ý¸t«fI1Äe×«D!3ÊLj¿À3&~2Û_î¯):A#<py%= #>Ôü¼1¦T?}CVs¨,Þ­+<cXA¿&Ñ? Ø]Þ7g×µìubEÉz­àvç$ªÇ{E­v8/\\n >u°rì¡\\nÜéfw¯Iüþ'û¼+sè+?r\\bîÊ/TÛ'ÍGpÀÎ@ðú2\\bÎ!Ìµ õ1v"åéò¢¨YLQ´ÂtOØ\\bÉra#jÚ(,Vàmsíö°\\rx(ÌrèØº'¾/«Ï{eîáùé¡Ò±ú`?ÃÅ}ruvÐâuÐ5kú =ê?Ðöñ¯_ô5}"L+ÙmeR9ÎYhÈ!È¿ý\\b¨î7OLç(æM7µ<¨bóÚS Ä{Ñgë6zï"­gáÙà±w2îÒ¤³ä×?FhHgÍçKk|þ­ÏËAVÒÃú©Ývt¤ýMÒArãÍ§QJ`Ð¸kg\\tN^f÷¢;óË$QÌ5T&`cBÀÞÔ°/o`-rÀØf/£à4"ÑCÎ²±l#w/ñ+8¾ÈAY.Û\\n"OÍXÊXBî\\rKòRuõèPÄù\\tóò\rh?7ÜO\(XÑZª¾Ì¶oÊè¾Ù¦PRjX¼T&#+Ï +ÆÙ\\nË!Ýâ·`dbkA\\nËÑ¨áÀç;a"urmBèfÀIh}ZK8r²òþäÈ"Ò½VøßõE>.~~5øùSC"çXs\\fb¬Ü,÷E÷·KÇ]r\\nw\\bÁ¢ò_FÏ=:CÖ´­×2d:Heü\\n¦3G§·q3Ç+ê«Ï/Êì<wÜ´WU£C³O-ÇðÉô\\f¬,Pªý[¹Fùè@ô\\rLõpªq¤C¼B¯Å¬PÐÇlÁÃ\\r]Xà.]s+öò8öö)ôÉðªìcÉÎ\«Ïð½\\bºw¡tÜF'pr`L×s1Pá2gIr½S_ýþªú-XRðý6àk1X<bßä»¹´Hnê³\Ìud2ùÜ·ðì{Ï¡IâTM§¢â¤-qËî ,¯Çíæ2"pó~¹è=^=k&ÃrJTÜáN{NªV_xÙw léE¹pêì¢Ñx¯-¬õM6å\\r/FÛN¡G§ÅeÿnCùí3pÍ·SÐT÷£±iYÑéûZÀ&Ö­QíÄ7Äj}!îzw 79\[cº¹2÷î¢õH{~[ÜýcAµc\§ðÇÊ£¹Ù¿JöKAÞû1S¿ã¥ò\\bíõV\\fqü¶Ù6qþ5äªÇ÷\\bz(çÍÛ£NèÒ\\bl¹N% E2{k9sü§Ì8>4úÉ]Õ­ÀªE+ÎÉÚa^)'8iþ]þE7Ñnªà\\fW·¬ÎN1y^a§7L<ê¯Óµâ÷{{ÿ09>Z·óÓK»äì9éOñ\\t±Ä¸ù÷%Ô2íè}µ¾º©'ì?'¶7G9c§f¥¢jeyS6È9ÎËG*022Ò!ò8³¾pùöMÎöxÖí±¶Í?¼;ÎDÖÔGvLk)}ôJ5¼ªö9¿fëfxmW-Bª&#LÅ®ªç!óù ­º\ºU4i/#OeR%=*åg\\rÓ¿Ú¬+¶â·îî^ä¬~UÆ\?ìð+  \\rÐw¥Æ `:^Wl©3µBN¶qP/n/p³Ð°ú":©Tü?aµ6³JÌQª û>¾À¤~ÆC<7ùúa)Aà2cúÕ*oW(ê©ßUÉôü;6P©aKQnVüÎh.a9ªª9Ï{21Èt/Ði°OýÊÑon¶D÷s9>>ï½|ÇOR.ÍAÝn\\nÒY<%ÐBÖYýà'PN°iïfÛ.¿2(³+¦SL±cnàs6¨;¬k©¹ê´\\f¾y±;¥C(VÛ" é\\nçÜJSáî&ê1âô5£a\\b[ú¥OíÊaö?±(y3%¶f"9væºÅÎ$_L@*ÁÚ)ÈÉêäüE?Õù&\\rögÇr\\fª°Ý¤VÔb³4®êæn\\t®××es=Ð.s\\bÚ%ù/ÅuØ\\bP$yÐ/2»ÀÏ-i-×ñê`,è­¡ö¸=_ÿðÛ1{~IÉ£Ô dsÌÁë­_VÐ¢¬OWèó¿áÇ[øuÁ7Ô~"o@¡Óº^óI¶Ý+îd<÷âÉq×,ÉCÔ/¡Ý¡ù+ûÌ÷Ë?µb{XµHj9{¾MôztÎÿÙáÂBßTd=S~È\\nÉ½Öóª ñý£ @ñ×3!>IÊ\\r)ë´Þpå<p1¹ÝÏ(Éº¦Û£p^ßÜ©¾ø_ûüPôVRfvï}ÝÜ·/;²ë|k:Ô°|Àz_²s¯­Ä©?[mæ~®ÔàF°DÿÎ×;zðSá´Ì£ØÜµ¥õÂ`£sJu`OàdiEì"ÇÉ÷ð`}pVßcè©¦-¯\\fCÃ¬·WñÄ8\\tÃiÿ£V¸dÅÒ>-2$£yYÈùîfÖ5îÛ8)Æ$Î¯íO:HLI¿²XÐík´s^(îm]lX÷ä_´Öq]Íé¿0þ9è¡<urÝçò¼à?&?\\rEýzØ\\t?ú{löVªM6\\f\\n]AV ¢FÎ¾cÍëp$=:Ú©ÜC¡$5²·1L¯(­&BâæIo@:¯KÅ¤çÖ?ÇÙ\\nÊJ8Uý5ñpO#&}ç)»Ûö.\ÛÃp¦v$ÁE[bæ6\\tO+ûøù¿óðCx\\në8DÜ]<&åÉ};á|K:wwõä'ô·gÍÛÈÈüÕq×ºûR¹âäÕ¾ØéÞë?C\È9½½óÖìoÇ?ý§h)ßEì·KùbØWé6òñ|#F(=+Éuê-"O\\tac×øªòèæÞ;ÁçC_pÀiúÊeÕ,êÜ\\tb µd|¦ÀTJ²>½$ic¦] NBw¼,\\tØ\\t"|Ñ¾k>úÑ 25©¬Å¨B!\\n°ØØ'
    //   69: dup
    //   70: astore_2
    //   71: invokevirtual length : ()I
    //   74: istore #4
    //   76: sipush #32767
    //   79: istore_1
    //   80: iconst_m1
    //   81: istore_0
    //   82: bipush #48
    //   84: iinc #0, 1
    //   87: aload_2
    //   88: iload_0
    //   89: dup
    //   90: iload_1
    //   91: iadd
    //   92: invokevirtual substring : (II)Ljava/lang/String;
    //   95: iconst_0
    //   96: goto -> 202
    //   99: aload #5
    //   101: swap
    //   102: iload_3
    //   103: iinc #3, 1
    //   106: swap
    //   107: aastore
    //   108: iload_0
    //   109: iload_1
    //   110: iadd
    //   111: dup
    //   112: istore_0
    //   113: iload #4
    //   115: if_icmpge -> 127
    //   118: aload_2
    //   119: iload_0
    //   120: invokevirtual charAt : (I)C
    //   123: istore_1
    //   124: goto -> 82
    //   127: ldc 'ÁÄÓà¹'
    //   129: dup
    //   130: astore_2
    //   131: invokevirtual length : ()I
    //   134: istore #4
    //   136: bipush #9
    //   138: istore_1
    //   139: iconst_m1
    //   140: istore_0
    //   141: bipush #9
    //   143: iinc #0, 1
    //   146: aload_2
    //   147: iload_0
    //   148: dup
    //   149: iload_1
    //   150: iadd
    //   151: invokevirtual substring : (II)Ljava/lang/String;
    //   154: iconst_1
    //   155: goto -> 202
    //   158: aload #5
    //   160: swap
    //   161: iload_3
    //   162: iinc #3, 1
    //   165: swap
    //   166: aastore
    //   167: iload_0
    //   168: iload_1
    //   169: iadd
    //   170: dup
    //   171: istore_0
    //   172: iload #4
    //   174: if_icmpge -> 186
    //   177: aload_2
    //   178: iload_0
    //   179: invokevirtual charAt : (I)C
    //   182: istore_1
    //   183: goto -> 141
    //   186: aload #5
    //   188: putstatic burp/Zr1v.a : [Ljava/lang/String;
    //   191: bipush #10
    //   193: anewarray java/lang/String
    //   196: putstatic burp/Zr1v.b : [Ljava/lang/String;
    //   199: goto -> 364
    //   202: dup_x2
    //   203: pop
    //   204: invokevirtual toCharArray : ()[C
    //   207: dup_x1
    //   208: arraylength
    //   209: dup_x2
    //   210: pop
    //   211: iconst_0
    //   212: istore #6
    //   214: dup2_x1
    //   215: pop2
    //   216: dup_x2
    //   217: iconst_1
    //   218: if_icmpgt -> 319
    //   221: dup2
    //   222: swap
    //   223: iload #6
    //   225: dup2_x1
    //   226: caload
    //   227: swap
    //   228: iload #6
    //   230: bipush #7
    //   232: irem
    //   233: tableswitch default -> 302, 0 -> 272, 1 -> 277, 2 -> 282, 3 -> 287, 4 -> 292, 5 -> 297
    //   272: bipush #79
    //   274: goto -> 303
    //   277: bipush #27
    //   279: goto -> 303
    //   282: bipush #21
    //   284: goto -> 303
    //   287: bipush #28
    //   289: goto -> 303
    //   292: bipush #118
    //   294: goto -> 303
    //   297: bipush #104
    //   299: goto -> 303
    //   302: iconst_1
    //   303: ixor
    //   304: ixor
    //   305: i2c
    //   306: castore
    //   307: iinc #6, 1
    //   310: dup
    //   311: ifne -> 319
    //   314: dup2
    //   315: dup_x1
    //   316: goto -> 225
    //   319: dup2_x1
    //   320: pop2
    //   321: dup_x2
    //   322: iload #6
    //   324: if_icmpgt -> 221
    //   327: pop
    //   328: new java/lang/String
    //   331: dup_x1
    //   332: swap
    //   333: invokespecial <init> : ([C)V
    //   336: invokevirtual intern : ()Ljava/lang/String;
    //   339: swap
    //   340: pop
    //   341: swap
    //   342: tableswitch default -> 39, 0 -> 99, 1 -> 158
    //   364: sipush #-31163
    //   367: sipush #-19022
    //   370: invokestatic a : (II)Ljava/lang/String;
    //   373: putstatic burp/Zr1v.ZM : Ljava/lang/String;
    //   376: getstatic burp/Zr1v.ZM : Ljava/lang/String;
    //   379: sipush #-31158
    //   382: sipush #1602
    //   385: invokestatic a : (II)Ljava/lang/String;
    //   388: <illegal opcode> makeConcatWithConstants : (Ljava/lang/String;Ljava/lang/String;)Ljava/lang/String;
    //   393: putstatic burp/Zr1v.ZM : Ljava/lang/String;
    //   396: new java/math/BigInteger
    //   399: dup
    //   400: bipush #32
    //   402: newarray byte
    //   404: dup
    //   405: iconst_0
    //   406: bipush #15
    //   408: bastore
    //   409: dup
    //   410: iconst_1
    //   411: bipush #-115
    //   413: bastore
    //   414: dup
    //   415: iconst_2
    //   416: bipush #-111
    //   418: bastore
    //   419: dup
    //   420: iconst_3
    //   421: bipush #6
    //   423: bastore
    //   424: dup
    //   425: iconst_4
    //   426: iconst_3
    //   427: bastore
    //   428: dup
    //   429: iconst_5
    //   430: bipush #19
    //   432: bastore
    //   433: dup
    //   434: bipush #6
    //   436: bipush #-117
    //   438: bastore
    //   439: dup
    //   440: bipush #7
    //   442: bipush #98
    //   444: bastore
    //   445: dup
    //   446: bipush #8
    //   448: bipush #-48
    //   450: bastore
    //   451: dup
    //   452: bipush #9
    //   454: bipush #124
    //   456: bastore
    //   457: dup
    //   458: bipush #10
    //   460: bipush #-88
    //   462: bastore
    //   463: dup
    //   464: bipush #11
    //   466: bipush #-99
    //   468: bastore
    //   469: dup
    //   470: bipush #12
    //   472: bipush #125
    //   474: bastore
    //   475: dup
    //   476: bipush #13
    //   478: iconst_5
    //   479: bastore
    //   480: dup
    //   481: bipush #14
    //   483: bipush #113
    //   485: bastore
    //   486: dup
    //   487: bipush #15
    //   489: bipush #-97
    //   491: bastore
    //   492: dup
    //   493: bipush #16
    //   495: bipush #-63
    //   497: bastore
    //   498: dup
    //   499: bipush #17
    //   501: iconst_0
    //   502: bastore
    //   503: dup
    //   504: bipush #18
    //   506: bipush #-113
    //   508: bastore
    //   509: dup
    //   510: bipush #19
    //   512: bipush #-29
    //   514: bastore
    //   515: dup
    //   516: bipush #20
    //   518: bipush #88
    //   520: bastore
    //   521: dup
    //   522: bipush #21
    //   524: bipush #55
    //   526: bastore
    //   527: dup
    //   528: bipush #22
    //   530: bipush #-126
    //   532: bastore
    //   533: dup
    //   534: bipush #23
    //   536: bipush #68
    //   538: bastore
    //   539: dup
    //   540: bipush #24
    //   542: bipush #83
    //   544: bastore
    //   545: dup
    //   546: bipush #25
    //   548: bipush #-102
    //   550: bastore
    //   551: dup
    //   552: bipush #26
    //   554: bipush #-50
    //   556: bastore
    //   557: dup
    //   558: bipush #27
    //   560: bipush #-15
    //   562: bastore
    //   563: dup
    //   564: bipush #28
    //   566: bipush #-85
    //   568: bastore
    //   569: dup
    //   570: bipush #29
    //   572: bipush #75
    //   574: bastore
    //   575: dup
    //   576: bipush #30
    //   578: bipush #56
    //   580: bastore
    //   581: dup
    //   582: bipush #31
    //   584: bipush #-85
    //   586: bastore
    //   587: invokespecial <init> : ([B)V
    //   590: putstatic burp/Zr1v.Zh : Ljava/lang/Object;
    //   593: return
  }
  
  private static Throwable a(Throwable paramThrowable) {
    return paramThrowable;
  }
  
  private static String a(int paramInt1, int paramInt2) {
    int i = (paramInt1 ^ 0xFFFF864D) & 0xFFFF;
    if (b[i] == null) {
      char[] arrayOfChar = a[i].toCharArray();
      switch (arrayOfChar[0] & 0xFF) {
        case 0:
        
        case 1:
        
        case 2:
        
        case 3:
        
        case 4:
        
        case 5:
        
        case 6:
        
        case 7:
        
        case 8:
        
        case 9:
        
        case 10:
        
        case 11:
        
        case 12:
        
        case 13:
        
        case 14:
        
        case 15:
        
        case 16:
        
        case 17:
        
        case 18:
        
        case 19:
        
        case 20:
        
        case 21:
        
        case 22:
        
        case 23:
        
        case 24:
        
        case 25:
        
        case 26:
        
        case 27:
        
        case 28:
        
        case 29:
        
        case 30:
        
        case 31:
        
        case 32:
        
        case 33:
        
        case 34:
        
        case 35:
        
        case 36:
        
        case 37:
        
        case 38:
        
        case 39:
        
        case 40:
        
        case 41:
        
        case 42:
        
        case 43:
        
        case 44:
        
        case 45:
        
        case 46:
        
        case 47:
        
        case 48:
        
        case 49:
        
        case 50:
        
        case 51:
        
        case 52:
        
        case 53:
        
        case 54:
        
        case 55:
        
        case 56:
        
        case 57:
        
        case 58:
        
        case 59:
        
        case 60:
        
        case 61:
        
        case 62:
        
        case 63:
        
        case 64:
        
        case 65:
        
        case 66:
        
        case 67:
        
        case 68:
        
        case 69:
        
        case 70:
        
        case 71:
        
        case 72:
        
        case 73:
        
        case 74:
        
        case 75:
        
        case 76:
        
        case 77:
        
        case 78:
        
        case 79:
        
        case 80:
        
        case 81:
        
        case 82:
        
        case 83:
        
        case 84:
        
        case 85:
        
        case 86:
        
        case 87:
        
        case 88:
        
        case 89:
        
        case 90:
        
        case 91:
        
        case 92:
        
        case 93:
        
        case 94:
        
        case 95:
        
        case 96:
        
        case 97:
        
        case 98:
        
        case 99:
        
        case 100:
        
        case 101:
        
        case 102:
        
        case 103:
        
        case 104:
        
        case 105:
        
        case 106:
        
        case 107:
        
        case 108:
        
        case 109:
        
        case 110:
        
        case 111:
        
        case 112:
        
        case 113:
        
        case 114:
        
        case 115:
        
        case 116:
        
        case 117:
        
        case 118:
        
        case 119:
        
        case 120:
        
        case 121:
        
        case 122:
        
        case 123:
        
        case 124:
        
        case 125:
        
        case 126:
        
        case 127:
        
        case 128:
        
        case 129:
        
        case 130:
        
        case 131:
        
        case 132:
        
        case 133:
        
        case 134:
        
        case 135:
        
        case 136:
        
        case 137:
        
        case 138:
        
        case 139:
        
        case 140:
        
        case 141:
        
        case 142:
        
        case 143:
        
        case 144:
        
        case 145:
        
        case 146:
        
        case 147:
        
        case 148:
        
        case 149:
        
        case 150:
        
        case 151:
        
        case 152:
        
        case 153:
        
        case 154:
        
        case 155:
        
        case 156:
        
        case 157:
        
        case 158:
        
        case 159:
        
        case 160:
        
        case 161:
        
        case 162:
        
        case 163:
        
        case 164:
        
        case 165:
        
        case 166:
        
        case 167:
        
        case 168:
        
        case 169:
        
        case 170:
        
        case 171:
        
        case 172:
        
        case 173:
        
        case 174:
        
        case 175:
        
        case 176:
        
        case 177:
        
        case 178:
        
        case 179:
        
        case 180:
        
        case 181:
        
        case 182:
        
        case 183:
        
        case 184:
        
        case 185:
        
        case 186:
        
        case 187:
        
        case 188:
        
        case 189:
        
        case 190:
        
        case 191:
        
        case 192:
        
        case 193:
        
        case 194:
        
        case 195:
        
        case 196:
        
        case 197:
        
        case 198:
        
        case 199:
        
        case 200:
        
        case 201:
        
        case 202:
        
        case 203:
        
        case 204:
        
        case 205:
        
        case 206:
        
        case 207:
        
        case 208:
        
        case 209:
        
        case 210:
        
        case 211:
        
        case 212:
        
        case 213:
        
        case 214:
        
        case 215:
        
        case 216:
        
        case 217:
        
        case 218:
        
        case 219:
        
        case 220:
        
        case 221:
        
        case 222:
        
        case 223:
        
        case 224:
        
        case 225:
        
        case 226:
        
        case 227:
        
        case 228:
        
        case 229:
        
        case 230:
        
        case 231:
        
        case 232:
        
        case 233:
        
        case 234:
        
        case 235:
        
        case 236:
        
        case 237:
        
        case 238:
        
        case 239:
        
        case 240:
        
        case 241:
        
        case 242:
        
        case 243:
        
        case 244:
        
        case 245:
        
        case 246:
        
        case 247:
        
        case 248:
        
        case 249:
        
        case 250:
        
        case 251:
        
        case 252:
        
        case 253:
        
        case 254:
        
        default:
          break;
      } 
      char c = '¡';
      int j = (paramInt2 & 0xFF) - c;
      if (j < 0)
        j += 256; 
      int k = ((paramInt2 & 0xFFFF) >>> 8) - c;
      if (k < 0)
        k += 256; 
      for (byte b = 0; b < arrayOfChar.length; b++) {
        int m = b % 2;
        if (m == 0) {
          arrayOfChar[b] = (char)(arrayOfChar[b] ^ j);
          j = ((j >>> 3 | j << 5) ^ arrayOfChar[b]) & 0xFF;
        } else {
          arrayOfChar[b] = (char)(arrayOfChar[b] ^ k);
          k = ((k >>> 3 | k << 5) ^ arrayOfChar[b]) & 0xFF;
        } 
      } 
      b[i] = (new String(arrayOfChar)).intern();
    } 
    return b[i];
  }
}


/* Location:              C:\Program Files\BurpSuitePro\burpsuite_pro.jar!\burp\Zr1v.class
 * Java compiler version: 21 (65.0)
 * JD-Core Version:       1.1.3
 */