package burp;

class Zr41 {
  Zrzm Zl;
  
  Zrzm Zb = Zrzm.NOT_RUN;
  
  Zrzm ZO = Zrzm.NOT_RUN;
  
  Zrzm Za = Zrzm.NOT_RUN;
  
  Zrzm ZZ = Zrzm.NOT_RUN;
  
  Zrzm ZB = Zrzm.NOT_RUN;
  
  Zrzm ZA = Zrzm.NOT_RUN;
  
  Zrzm Zi = Zrzm.NOT_RUN;
  
  Zrzm ZJ = Zrzm.NOT_RUN;
  
  private final String Zw;
  
  final Zep5 ZT;
  
  private static final String[] a;
  
  private static final String[] b;
  
  Zr41(Zep5 paramZep5) {
    Zbqc[] arrayOfZbqc = Zep5.Zp();
    if (paramZep5.Z_.Zu.Zi()) {
      this.Zw = paramZep5.Z_.Zu.ZJ();
      if (arrayOfZbqc == null) {
        this.Zw = paramZep5.Zl.toString() + "." + paramZep5.Zl.toString();
        return;
      } 
      return;
    } 
    this.Zw = paramZep5.Zl.toString() + "." + paramZep5.Zl.toString();
  }
  
  void ZS(Zrzm paramZrzm) {
    this.Zl = paramZrzm;
  }
  
  public String Zn() {
    // Byte code:
    //   0: invokestatic Zp : ()[Lburp/Zbqc;
    //   3: astore_1
    //   4: new java/lang/StringBuilder
    //   7: dup
    //   8: invokespecial <init> : ()V
    //   11: astore_2
    //   12: aload_0
    //   13: getfield Zb : Lburp/Zrzm;
    //   16: getstatic burp/Zrzm.SUCCESS : Lburp/Zrzm;
    //   19: if_acmpne -> 133
    //   22: aload_0
    //   23: getfield ZO : Lburp/Zrzm;
    //   26: getstatic burp/Zrzm.SUCCESS : Lburp/Zrzm;
    //   29: if_acmpne -> 133
    //   32: aload_0
    //   33: getfield ZZ : Lburp/Zrzm;
    //   36: getstatic burp/Zrzm.SUCCESS : Lburp/Zrzm;
    //   39: if_acmpne -> 133
    //   42: aload_0
    //   43: getfield ZB : Lburp/Zrzm;
    //   46: getstatic burp/Zrzm.SUCCESS : Lburp/Zrzm;
    //   49: if_acmpne -> 133
    //   52: aload_0
    //   53: getfield ZA : Lburp/Zrzm;
    //   56: getstatic burp/Zrzm.SUCCESS : Lburp/Zrzm;
    //   59: if_acmpne -> 133
    //   62: aload_0
    //   63: getfield Zi : Lburp/Zrzm;
    //   66: getstatic burp/Zrzm.SUCCESS : Lburp/Zrzm;
    //   69: if_acmpne -> 133
    //   72: aload_0
    //   73: getfield ZJ : Lburp/Zrzm;
    //   76: getstatic burp/Zrzm.SUCCESS : Lburp/Zrzm;
    //   79: if_acmpne -> 133
    //   82: aload_0
    //   83: getfield Zl : Lburp/Zrzm;
    //   86: getstatic burp/Zrzm.SUCCESS : Lburp/Zrzm;
    //   89: if_acmpne -> 133
    //   92: aload_0
    //   93: getfield Za : Lburp/Zrzm;
    //   96: getstatic burp/Zrzm.SUCCESS : Lburp/Zrzm;
    //   99: if_acmpne -> 133
    //   102: getstatic burp/Zze0.SUITE_COLLABORATOR_HEALTH_CHECK_OK : Lburp/Zze0;
    //   105: invokestatic Zo : (Lnet/portswigger/Zfp;)V
    //   108: aload_2
    //   109: sipush #5059
    //   112: sipush #-23061
    //   115: invokestatic a : (II)Ljava/lang/String;
    //   118: invokevirtual append : (Ljava/lang/String;)Ljava/lang/StringBuilder;
    //   121: pop
    //   122: aload_1
    //   123: ifnonnull -> 139
    //   126: iconst_3
    //   127: anewarray burp/Zbqc
    //   130: invokestatic Zr : ([Lburp/Zbqc;)V
    //   133: getstatic burp/Zze0.SUITE_COLLABORATOR_HEALTH_CHECK_FAILED : Lburp/Zze0;
    //   136: invokestatic Zo : (Lnet/portswigger/Zfp;)V
    //   139: aload_0
    //   140: getfield ZT : Lburp/Zep5;
    //   143: getfield Z_ : Lburp/Zes1;
    //   146: getfield Zu : Lburp/Zzi5;
    //   149: invokevirtual Zi : ()Z
    //   152: ifeq -> 169
    //   155: aload_2
    //   156: sipush #5075
    //   159: sipush #-30028
    //   162: invokestatic a : (II)Ljava/lang/String;
    //   165: invokevirtual append : (Ljava/lang/String;)Ljava/lang/StringBuilder;
    //   168: pop
    //   169: aload_0
    //   170: getfield Zb : Lburp/Zrzm;
    //   173: getstatic burp/Zrzm.RESOLUTION_FAILED : Lburp/Zrzm;
    //   176: if_acmpeq -> 199
    //   179: aload_0
    //   180: getfield ZB : Lburp/Zrzm;
    //   183: getstatic burp/Zrzm.RESOLUTION_FAILED : Lburp/Zrzm;
    //   186: if_acmpeq -> 199
    //   189: aload_0
    //   190: getfield ZA : Lburp/Zrzm;
    //   193: getstatic burp/Zrzm.RESOLUTION_FAILED : Lburp/Zrzm;
    //   196: if_acmpne -> 232
    //   199: aload_2
    //   200: sipush #5071
    //   203: sipush #27298
    //   206: invokestatic a : (II)Ljava/lang/String;
    //   209: invokevirtual append : (Ljava/lang/String;)Ljava/lang/StringBuilder;
    //   212: aload_0
    //   213: getfield Zw : Ljava/lang/String;
    //   216: invokevirtual append : (Ljava/lang/String;)Ljava/lang/StringBuilder;
    //   219: sipush #5116
    //   222: sipush #14478
    //   225: invokestatic a : (II)Ljava/lang/String;
    //   228: invokevirtual append : (Ljava/lang/String;)Ljava/lang/StringBuilder;
    //   231: pop
    //   232: aload_0
    //   233: getfield ZO : Lburp/Zrzm;
    //   236: getstatic burp/Zrzm.SSL_ERROR : Lburp/Zrzm;
    //   239: if_acmpne -> 303
    //   242: aload_0
    //   243: getfield ZZ : Lburp/Zrzm;
    //   246: getstatic burp/Zrzm.SUCCESS : Lburp/Zrzm;
    //   249: if_acmpne -> 289
    //   252: aload_2
    //   253: sipush #5057
    //   256: sipush #1174
    //   259: invokestatic a : (II)Ljava/lang/String;
    //   262: invokevirtual append : (Ljava/lang/String;)Ljava/lang/StringBuilder;
    //   265: aload_0
    //   266: getfield Zw : Ljava/lang/String;
    //   269: invokevirtual append : (Ljava/lang/String;)Ljava/lang/StringBuilder;
    //   272: sipush #5064
    //   275: sipush #-20407
    //   278: invokestatic a : (II)Ljava/lang/String;
    //   281: invokevirtual append : (Ljava/lang/String;)Ljava/lang/StringBuilder;
    //   284: pop
    //   285: aload_1
    //   286: ifnonnull -> 303
    //   289: aload_2
    //   290: sipush #5077
    //   293: sipush #23800
    //   296: invokestatic a : (II)Ljava/lang/String;
    //   299: invokevirtual append : (Ljava/lang/String;)Ljava/lang/StringBuilder;
    //   302: pop
    //   303: aload_0
    //   304: getfield Zi : Lburp/Zrzm;
    //   307: getstatic burp/Zrzm.SSL_ERROR : Lburp/Zrzm;
    //   310: if_acmpne -> 374
    //   313: aload_0
    //   314: getfield ZJ : Lburp/Zrzm;
    //   317: getstatic burp/Zrzm.SUCCESS : Lburp/Zrzm;
    //   320: if_acmpne -> 360
    //   323: aload_2
    //   324: sipush #5073
    //   327: sipush #6465
    //   330: invokestatic a : (II)Ljava/lang/String;
    //   333: invokevirtual append : (Ljava/lang/String;)Ljava/lang/StringBuilder;
    //   336: aload_0
    //   337: getfield Zw : Ljava/lang/String;
    //   340: invokevirtual append : (Ljava/lang/String;)Ljava/lang/StringBuilder;
    //   343: sipush #5061
    //   346: sipush #-16412
    //   349: invokestatic a : (II)Ljava/lang/String;
    //   352: invokevirtual append : (Ljava/lang/String;)Ljava/lang/StringBuilder;
    //   355: pop
    //   356: aload_1
    //   357: ifnonnull -> 374
    //   360: aload_2
    //   361: sipush #5079
    //   364: sipush #8706
    //   367: invokestatic a : (II)Ljava/lang/String;
    //   370: invokevirtual append : (Ljava/lang/String;)Ljava/lang/StringBuilder;
    //   373: pop
    //   374: aload_0
    //   375: getfield Zb : Lburp/Zrzm;
    //   378: getstatic burp/Zrzm.CONNECTION_FAILED : Lburp/Zrzm;
    //   381: if_acmpne -> 461
    //   384: aload_0
    //   385: getfield ZO : Lburp/Zrzm;
    //   388: getstatic burp/Zrzm.CONNECTION_FAILED : Lburp/Zrzm;
    //   391: if_acmpne -> 461
    //   394: aload_0
    //   395: getfield ZB : Lburp/Zrzm;
    //   398: getstatic burp/Zrzm.CONNECTION_FAILED : Lburp/Zrzm;
    //   401: if_acmpne -> 461
    //   404: aload_0
    //   405: getfield ZA : Lburp/Zrzm;
    //   408: getstatic burp/Zrzm.CONNECTION_FAILED : Lburp/Zrzm;
    //   411: if_acmpne -> 461
    //   414: aload_0
    //   415: getfield Zi : Lburp/Zrzm;
    //   418: getstatic burp/Zrzm.CONNECTION_FAILED : Lburp/Zrzm;
    //   421: if_acmpne -> 461
    //   424: aload_2
    //   425: sipush #5085
    //   428: sipush #568
    //   431: invokestatic a : (II)Ljava/lang/String;
    //   434: invokevirtual append : (Ljava/lang/String;)Ljava/lang/StringBuilder;
    //   437: aload_0
    //   438: getfield Zw : Ljava/lang/String;
    //   441: invokevirtual append : (Ljava/lang/String;)Ljava/lang/StringBuilder;
    //   444: sipush #5065
    //   447: sipush #25275
    //   450: invokestatic a : (II)Ljava/lang/String;
    //   453: invokevirtual append : (Ljava/lang/String;)Ljava/lang/StringBuilder;
    //   456: pop
    //   457: aload_1
    //   458: ifnonnull -> 740
    //   461: aload_0
    //   462: getfield Zb : Lburp/Zrzm;
    //   465: getstatic burp/Zrzm.CONNECTION_FAILED : Lburp/Zrzm;
    //   468: if_acmpne -> 504
    //   471: aload_2
    //   472: sipush #5117
    //   475: sipush #-1325
    //   478: invokestatic a : (II)Ljava/lang/String;
    //   481: invokevirtual append : (Ljava/lang/String;)Ljava/lang/StringBuilder;
    //   484: aload_0
    //   485: getfield Zw : Ljava/lang/String;
    //   488: invokevirtual append : (Ljava/lang/String;)Ljava/lang/StringBuilder;
    //   491: sipush #5084
    //   494: sipush #27585
    //   497: invokestatic a : (II)Ljava/lang/String;
    //   500: invokevirtual append : (Ljava/lang/String;)Ljava/lang/StringBuilder;
    //   503: pop
    //   504: aload_0
    //   505: getfield ZO : Lburp/Zrzm;
    //   508: getstatic burp/Zrzm.CONNECTION_FAILED : Lburp/Zrzm;
    //   511: if_acmpne -> 547
    //   514: aload_2
    //   515: sipush #5068
    //   518: sipush #12070
    //   521: invokestatic a : (II)Ljava/lang/String;
    //   524: invokevirtual append : (Ljava/lang/String;)Ljava/lang/StringBuilder;
    //   527: aload_0
    //   528: getfield Zw : Ljava/lang/String;
    //   531: invokevirtual append : (Ljava/lang/String;)Ljava/lang/StringBuilder;
    //   534: sipush #5083
    //   537: sipush #-23986
    //   540: invokestatic a : (II)Ljava/lang/String;
    //   543: invokevirtual append : (Ljava/lang/String;)Ljava/lang/StringBuilder;
    //   546: pop
    //   547: aload_0
    //   548: getfield ZB : Lburp/Zrzm;
    //   551: getstatic burp/Zrzm.CONNECTION_FAILED : Lburp/Zrzm;
    //   554: if_acmpne -> 590
    //   557: aload_2
    //   558: sipush #5060
    //   561: sipush #11191
    //   564: invokestatic a : (II)Ljava/lang/String;
    //   567: invokevirtual append : (Ljava/lang/String;)Ljava/lang/StringBuilder;
    //   570: aload_0
    //   571: getfield Zw : Ljava/lang/String;
    //   574: invokevirtual append : (Ljava/lang/String;)Ljava/lang/StringBuilder;
    //   577: sipush #5076
    //   580: sipush #25057
    //   583: invokestatic a : (II)Ljava/lang/String;
    //   586: invokevirtual append : (Ljava/lang/String;)Ljava/lang/StringBuilder;
    //   589: pop
    //   590: aload_0
    //   591: getfield ZA : Lburp/Zrzm;
    //   594: getstatic burp/Zrzm.CONNECTION_FAILED : Lburp/Zrzm;
    //   597: if_acmpne -> 633
    //   600: aload_2
    //   601: sipush #5078
    //   604: sipush #-6229
    //   607: invokestatic a : (II)Ljava/lang/String;
    //   610: invokevirtual append : (Ljava/lang/String;)Ljava/lang/StringBuilder;
    //   613: aload_0
    //   614: getfield Zw : Ljava/lang/String;
    //   617: invokevirtual append : (Ljava/lang/String;)Ljava/lang/StringBuilder;
    //   620: sipush #5087
    //   623: sipush #632
    //   626: invokestatic a : (II)Ljava/lang/String;
    //   629: invokevirtual append : (Ljava/lang/String;)Ljava/lang/StringBuilder;
    //   632: pop
    //   633: aload_0
    //   634: getfield Zi : Lburp/Zrzm;
    //   637: getstatic burp/Zrzm.CONNECTION_FAILED : Lburp/Zrzm;
    //   640: if_acmpne -> 676
    //   643: aload_2
    //   644: sipush #5086
    //   647: sipush #-31200
    //   650: invokestatic a : (II)Ljava/lang/String;
    //   653: invokevirtual append : (Ljava/lang/String;)Ljava/lang/StringBuilder;
    //   656: aload_0
    //   657: getfield Zw : Ljava/lang/String;
    //   660: invokevirtual append : (Ljava/lang/String;)Ljava/lang/StringBuilder;
    //   663: sipush #5083
    //   666: sipush #-23986
    //   669: invokestatic a : (II)Ljava/lang/String;
    //   672: invokevirtual append : (Ljava/lang/String;)Ljava/lang/StringBuilder;
    //   675: pop
    //   676: aload_0
    //   677: getfield Zb : Lburp/Zrzm;
    //   680: getstatic burp/Zrzm.CONNECTION_FAILED : Lburp/Zrzm;
    //   683: if_acmpeq -> 726
    //   686: aload_0
    //   687: getfield ZO : Lburp/Zrzm;
    //   690: getstatic burp/Zrzm.CONNECTION_FAILED : Lburp/Zrzm;
    //   693: if_acmpeq -> 726
    //   696: aload_0
    //   697: getfield ZB : Lburp/Zrzm;
    //   700: getstatic burp/Zrzm.CONNECTION_FAILED : Lburp/Zrzm;
    //   703: if_acmpeq -> 726
    //   706: aload_0
    //   707: getfield ZA : Lburp/Zrzm;
    //   710: getstatic burp/Zrzm.CONNECTION_FAILED : Lburp/Zrzm;
    //   713: if_acmpeq -> 726
    //   716: aload_0
    //   717: getfield Zi : Lburp/Zrzm;
    //   720: getstatic burp/Zrzm.CONNECTION_FAILED : Lburp/Zrzm;
    //   723: if_acmpne -> 740
    //   726: aload_2
    //   727: sipush #5072
    //   730: sipush #26837
    //   733: invokestatic a : (II)Ljava/lang/String;
    //   736: invokevirtual append : (Ljava/lang/String;)Ljava/lang/StringBuilder;
    //   739: pop
    //   740: aload_0
    //   741: getfield Zb : Lburp/Zrzm;
    //   744: getstatic burp/Zrzm.UNEXPECTED_RESPONSE : Lburp/Zrzm;
    //   747: if_acmpne -> 764
    //   750: aload_2
    //   751: sipush #5056
    //   754: sipush #-1296
    //   757: invokestatic a : (II)Ljava/lang/String;
    //   760: invokevirtual append : (Ljava/lang/String;)Ljava/lang/StringBuilder;
    //   763: pop
    //   764: aload_0
    //   765: getfield ZO : Lburp/Zrzm;
    //   768: getstatic burp/Zrzm.UNEXPECTED_RESPONSE : Lburp/Zrzm;
    //   771: if_acmpeq -> 784
    //   774: aload_0
    //   775: getfield ZZ : Lburp/Zrzm;
    //   778: getstatic burp/Zrzm.UNEXPECTED_RESPONSE : Lburp/Zrzm;
    //   781: if_acmpne -> 798
    //   784: aload_2
    //   785: sipush #5067
    //   788: sipush #-3019
    //   791: invokestatic a : (II)Ljava/lang/String;
    //   794: invokevirtual append : (Ljava/lang/String;)Ljava/lang/StringBuilder;
    //   797: pop
    //   798: aload_0
    //   799: getfield ZB : Lburp/Zrzm;
    //   802: getstatic burp/Zrzm.UNEXPECTED_RESPONSE : Lburp/Zrzm;
    //   805: if_acmpeq -> 818
    //   808: aload_0
    //   809: getfield ZA : Lburp/Zrzm;
    //   812: getstatic burp/Zrzm.UNEXPECTED_RESPONSE : Lburp/Zrzm;
    //   815: if_acmpne -> 832
    //   818: aload_2
    //   819: sipush #5062
    //   822: sipush #-29694
    //   825: invokestatic a : (II)Ljava/lang/String;
    //   828: invokevirtual append : (Ljava/lang/String;)Ljava/lang/StringBuilder;
    //   831: pop
    //   832: aload_0
    //   833: getfield Zi : Lburp/Zrzm;
    //   836: getstatic burp/Zrzm.UNEXPECTED_RESPONSE : Lburp/Zrzm;
    //   839: if_acmpeq -> 852
    //   842: aload_0
    //   843: getfield ZJ : Lburp/Zrzm;
    //   846: getstatic burp/Zrzm.UNEXPECTED_RESPONSE : Lburp/Zrzm;
    //   849: if_acmpne -> 866
    //   852: aload_2
    //   853: sipush #5066
    //   856: sipush #17963
    //   859: invokestatic a : (II)Ljava/lang/String;
    //   862: invokevirtual append : (Ljava/lang/String;)Ljava/lang/StringBuilder;
    //   865: pop
    //   866: aload_0
    //   867: getfield Zl : Lburp/Zrzm;
    //   870: getstatic burp/Zrzm.CONNECTION_FAILED : Lburp/Zrzm;
    //   873: if_acmpne -> 1016
    //   876: aload_2
    //   877: sipush #5058
    //   880: sipush #-31038
    //   883: invokestatic a : (II)Ljava/lang/String;
    //   886: invokevirtual append : (Ljava/lang/String;)Ljava/lang/StringBuilder;
    //   889: aload_0
    //   890: getfield ZT : Lburp/Zep5;
    //   893: getfield Z_ : Lburp/Zes1;
    //   896: getfield Zx : Ljava/lang/String;
    //   899: invokevirtual append : (Ljava/lang/String;)Ljava/lang/StringBuilder;
    //   902: sipush #5082
    //   905: sipush #-32169
    //   908: invokestatic a : (II)Ljava/lang/String;
    //   911: invokevirtual append : (Ljava/lang/String;)Ljava/lang/StringBuilder;
    //   914: pop
    //   915: aload_0
    //   916: getfield ZT : Lburp/Zep5;
    //   919: getfield Z_ : Lburp/Zes1;
    //   922: getfield Zg : Z
    //   925: ifeq -> 1078
    //   928: aload_0
    //   929: getfield Zb : Lburp/Zrzm;
    //   932: getstatic burp/Zrzm.SUCCESS : Lburp/Zrzm;
    //   935: if_acmpne -> 1078
    //   938: aload_0
    //   939: getfield ZO : Lburp/Zrzm;
    //   942: getstatic burp/Zrzm.SSL_ERROR : Lburp/Zrzm;
    //   945: if_acmpne -> 1078
    //   948: aload_0
    //   949: getfield ZT : Lburp/Zep5;
    //   952: getfield Z_ : Lburp/Zes1;
    //   955: getfield Zx : Ljava/lang/String;
    //   958: invokestatic ZC : (Ljava/lang/String;)Z
    //   961: ifne -> 980
    //   964: aload_0
    //   965: getfield ZT : Lburp/Zep5;
    //   968: getfield Z_ : Lburp/Zes1;
    //   971: getfield Zx : Ljava/lang/String;
    //   974: invokestatic ZE : (Ljava/lang/String;)Z
    //   977: ifeq -> 998
    //   980: aload_2
    //   981: sipush #5074
    //   984: sipush #-10747
    //   987: invokestatic a : (II)Ljava/lang/String;
    //   990: invokevirtual append : (Ljava/lang/String;)Ljava/lang/StringBuilder;
    //   993: pop
    //   994: aload_1
    //   995: ifnonnull -> 1078
    //   998: aload_2
    //   999: sipush #5081
    //   1002: sipush #27950
    //   1005: invokestatic a : (II)Ljava/lang/String;
    //   1008: invokevirtual append : (Ljava/lang/String;)Ljava/lang/StringBuilder;
    //   1011: pop
    //   1012: aload_1
    //   1013: ifnonnull -> 1078
    //   1016: aload_0
    //   1017: getfield Zl : Lburp/Zrzm;
    //   1020: getstatic burp/Zrzm.RESOLUTION_FAILED : Lburp/Zrzm;
    //   1023: if_acmpne -> 1078
    //   1026: aload_0
    //   1027: getfield ZT : Lburp/Zep5;
    //   1030: getfield Z_ : Lburp/Zes1;
    //   1033: invokevirtual ZL : ()Z
    //   1036: ifeq -> 1078
    //   1039: aload_2
    //   1040: sipush #5069
    //   1043: sipush #18434
    //   1046: invokestatic a : (II)Ljava/lang/String;
    //   1049: invokevirtual append : (Ljava/lang/String;)Ljava/lang/StringBuilder;
    //   1052: aload_0
    //   1053: getfield ZT : Lburp/Zep5;
    //   1056: getfield Z_ : Lburp/Zes1;
    //   1059: getfield Zx : Ljava/lang/String;
    //   1062: invokevirtual append : (Ljava/lang/String;)Ljava/lang/StringBuilder;
    //   1065: sipush #5070
    //   1068: sipush #28056
    //   1071: invokestatic a : (II)Ljava/lang/String;
    //   1074: invokevirtual append : (Ljava/lang/String;)Ljava/lang/StringBuilder;
    //   1077: pop
    //   1078: aload_0
    //   1079: getfield Zl : Lburp/Zrzm;
    //   1082: getstatic burp/Zrzm.SUCCESS : Lburp/Zrzm;
    //   1085: if_acmpne -> 1122
    //   1088: aload_0
    //   1089: getfield ZO : Lburp/Zrzm;
    //   1092: getstatic burp/Zrzm.SUCCESS : Lburp/Zrzm;
    //   1095: if_acmpeq -> 1122
    //   1098: aload_0
    //   1099: getfield Zb : Lburp/Zrzm;
    //   1102: getstatic burp/Zrzm.SUCCESS : Lburp/Zrzm;
    //   1105: if_acmpeq -> 1122
    //   1108: aload_2
    //   1109: sipush #5080
    //   1112: sipush #25067
    //   1115: invokestatic a : (II)Ljava/lang/String;
    //   1118: invokevirtual append : (Ljava/lang/String;)Ljava/lang/StringBuilder;
    //   1121: pop
    //   1122: aload_0
    //   1123: getfield Zl : Lburp/Zrzm;
    //   1126: getstatic burp/Zrzm.UNEXPECTED_RESPONSE : Lburp/Zrzm;
    //   1129: if_acmpne -> 1146
    //   1132: aload_2
    //   1133: sipush #5063
    //   1136: sipush #-16513
    //   1139: invokestatic a : (II)Ljava/lang/String;
    //   1142: invokevirtual append : (Ljava/lang/String;)Ljava/lang/StringBuilder;
    //   1145: pop
    //   1146: aload_0
    //   1147: getfield Za : Lburp/Zrzm;
    //   1150: getstatic burp/Zrzm.OLD_SERVER_VERSION : Lburp/Zrzm;
    //   1153: if_acmpne -> 1176
    //   1156: aload_2
    //   1157: getstatic burp/Zmgc.COLLABORATOR_OUT_OF_DATE : Lburp/Zmgc;
    //   1160: iconst_0
    //   1161: anewarray java/lang/Object
    //   1164: invokevirtual ZB : ([Ljava/lang/Object;)Ljava/lang/String;
    //   1167: invokevirtual append : (Ljava/lang/String;)Ljava/lang/StringBuilder;
    //   1170: ldc '\\n'
    //   1172: invokevirtual append : (Ljava/lang/String;)Ljava/lang/StringBuilder;
    //   1175: pop
    //   1176: aload_2
    //   1177: invokevirtual toString : ()Ljava/lang/String;
    //   1180: areturn
  }
  
  static {
    // Byte code:
    //   0: bipush #34
    //   2: anewarray java/lang/String
    //   5: astore #5
    //   7: iconst_0
    //   8: istore_3
    //   9: ldc 'Ã(Â½1jÂº\qÃ•Âª,Ã”Ã‘EÃ¥[ÂšÂ´Â•Ã“Ã£Ã—ÂŸÃ…EÃ¼Ã™-Ã¨(Ã~NÃº!Ã‡[iÃ¢ÂÃ£z>dÃ¨Â¸Ã›Â‰ÃÂ²ÂœÂ¾?2.Ãi=Ã¡q-YÃ¬VÃ°ÃœÃ_Â£w8]WÃ½Ã¸Ã­Ã¨Ã¼ÂºkÂ¢Â¼Â´nL_Ã¦Â”+Â\\tÂ†Â´Ã²Â°(ÂÂGÂ¨Â#Ã³06Â™^2Ã—Ã‡9Ã¥Ã†yoXÂ–Â‰Ã£Â—5Ã¢Ã’Âš j!Â2,Â‡HrsW:Â°Â€NÂ‰Ã1ÂÂ´Ã½Ã©AÂ¬fwv9zWÂ‘!\\t\#Ã¿1XÂ½rÃ†=Ã“Â·<ÃÂ CÃ›Ã°\\rÂ‡?\mÃ›x\\tYÃ¥Â¿Ã«Ã‚Â¿0:Ã¡Â˜ÃŒ\\tHePX#.Â” ?zÂŠÃ¨,Â„ÃµÃ™Â¿Ã­Ã‚+Â«ÃŒRÂ·Âˆ>Â¬]MtÃ“I5Â§ÃªÂ²Ã«A&vÃ‡XÃ˜0 Â§Ã¡ ÂœIÂˆ;\\fÂ›_Ã—EÃ¬Â½@G3-nÃŸÃ„geJdÃ­Ã¬ÃƒÃºÂ²,Â¿Ã¬P)<r[Â…1ÃgÂ½Ã—Â¡Â¡KsÃ·Â™Ã¯\\bÃÃµÂ›Ã®AÃ¦%ÃŒÃœÂ›Â¡eÃ¿Â¿Ãª6Ã½"Â¶Â—yÂÃ¦!Ã¹\\bÃƒÂÂ¤Ã¡Â—Ã¯Â¡Ã•wÂ„Ã«JÃ¡Ã•Ã¦Â˜b)w%ÂªÂ‰6-Ã¬OÃ±Ã¿Ã¯P~NcÃ7NÃ²Ã¦Â°\Â·<xÂ¸Â‹Â¼Â«ÂµÃ‹Â€HÃ‰TL_MÃ„Â€}ZG1uÂ‚Â‰/Ã–tÃ™?jJÂ®v238Âµ1;Ãµ)Â¶HÃƒÂ‘Ã•qÂ¹ÂŸjTwÂ±Ã…mÃ˜Ã–:\\tÃ¡Â²Ã·Ã„Â²Ã§Â¨m)^ÃqÃÃ»Ã¤KNÃµbÃ¹Q\\fÂfÂ‰Â¥Ã˜zÂ·Â¼ÃÂ¸|Â¤Ã«Ã¦ÂµaP3Â„Â³Ã‹_#Â+|b[EÂZÂŠgÃÂ±}Ã¥rSy\Â³Ã‚B~Â¬VÃ`sÂšÃ¸/$SÂÂ˜ÂŒÃ‘KÃÂÂ¾xÂªjiÂ>\\tÃ‡Â¤ÂƒÃ‹(Q"Â—M|Â…Ru~Â—\ÂŒNÃÂ‚^?EEhÂšÃ°Ã°Ã¡Â•Ã­v\\t P$\\f2X\\b;Â¡NÂ™Ã§\\nQÃ¹^Ã·:cÂ¼PÂ²Ã›Â¶Â‚\\fÃ†QÂ‹Ã‰Ã Â€Ã®ÂÃÃ¸Â„Ã¨Ã¿ÂŒv1vÃ |Ã˜Yy\\f9Ã¡XvÃ–ÃªÃ«Â„=Ã°ÃqÂ«Â™E7|ÃšÃ§R\\tÂ¸x;Â:Â¶Â”}VÂ™VzÃ¾i;Â´/<-3^]}Â¡]iiÃ·Ã‰\\n\ÂŠ]Ã´Ã¡Â¢tÃ·&A;w?Ã†Ã€Ã¦Ã‹Ã·N#\\fPÂ¸Â™iÃ¶}Â•Â‡Â¼Ã³cÂ€Â—ÃºÂ½Ã¼HÃ˜FÂ°ÃÃ€ÃŠ<KX8E7\\bÃÂ¬Ã—Â¬W-Âm"0Â¿:Ã’Â–Âº+ÂÃ³*Ã·Â Ã¶ÃÃ‚Â’Ã¤,Ã¾_Â²Ã½Â‡{Ã™Â°DÃª'Ã“ÂÃºpÃ¨Ã“vAÃƒ8 :Â¶r~Â‘Ã°'ÃŸD1Â¯H1Â¼sÂºÃ©ÃœASÃ–c/ÂÂ¼Ã¿Â¢Â¥Â‡iÃ•ÃŸÃ³ÃXÂ’Ã«Ã¸ÂµÂ‰ M?Ã­Ã Ã Ã†Ã¸,zNÂ™lyÂ±gÂ•BFZÃ€Â¶ÂµjÃ‡Â¯Â¾B/!Âª?EÃ¤ÂÂ?aÂ¡FÂ²DÂ‚ÂŸÂ“Â¼Ã‹}Ã¯}Ã¼-Âš{Ã”c1Ã¦Â°,0CÂ¨Â±Â¤Ã½Â©=LÂ¶Â’ÃµiÂ‚"cÃ¿?\\bÂš'ÃÂ¯ÂÃÃŒÃ¼JR0XÃ“Ã Â½Ã©Â¢ÂŒÂ¿\\n|p&~Â¢\\nÃ£#OKÂÃši$Ã‘@RbÃŠÃ­Ã®nÃˆÂ€Â‘Â­QÂ“rÂ¿Ã•ÂÃ‹Ã¦C!?JmÃˆhÃ¤Ã´Ã½`Ã‹8Â€ÂÂª+*Â™ÃEfNÃ“CÂ¿Ã¾Ã–Ã¸Â¿ÂŠÃ OÂ‰,Ã¶#ÃƒcÂŠÂŸÂ›ÃºRÂŠrepvFÂºÃ¥Ã°adÂ¥C_q%Ã¶ÃLÃŒfÃ©qLÃ®ÃBZÃ¿Â»ÃšÃŸÂÃÃ†BaÂ¢Â­Ã¾CtÂ©;Â‹TJÂŠ\\rÃ½}ÃÂ»Ã»ÂŒHÂ„Â±lÂ«Â¶mÃ³tÃ±]zÃœÂ‚Â•vÂ•Ã§&ÂÂ¯Â£sÂš2lÃœÃœÃ«Â¤ÃºÂ¤Â¡Ã¨ÂÃtxÂ…Â“ÂÃ¤Â¯Â£Ã€\\tÂµvÃ…1Â‡t{Â‹ÃÂ•Ã‹ÃsqÃ…Ã¶)Ã¹#7Â‘ÃµÃ¥YÂ‚Â„.Â³w`OÂ­CÂ£Ã®Â•ÂˆbÂ¶Â¿lÂ“Âˆn-pEÂ˜XÃ¡rÃ‘Ã™Â¹\\rQÂ¡Ã­?ÃˆÃŠ_Â”VÃª"Ã¡Â¯Â³-Â°RtsÃ Ã•Â¢FÃ¹Âºf:Â›Ã‘Â›Â²0 Â“Â”Ã¢-#9Q,Âƒ{*Ã³+Â¨{EÃ™Â¿`Â¥Ã¡ÂÂ›OO+8Â…Ã¾jMÃ”Â¤\\fcÂƒ Â§Ã¸Ã–9Â¬Â¾aÂºÂ‚ÃŠÃŸÂ.Ã‰ÃŠÃ—Â´FÂµÂ«Â°DÂ®Ã‘Â¸mÂEiqj(Ã¼Â‘eÃ˜Ã²dÂ¹4Ã—Ã¯Ã‚Ã„Â¥Ã¦Ã˜{`TÃ‚Â´SÂ™Ã‚Ã¥Ã½Ã£Â…Ã†Â¼Â˜JWÂµÂ³Ã»Â„ÃŒGÂ¿ÂÃ cÂ¼Â¡\\fIÂ¤Ã™pÃÂ¬ÃÂœÂ‹Ã½Â?Ã°\>Ã¦Ã¶Ã†Â–Â™ÂºÃ¤Â•Ã±AÃµÃ½Ã–Â‚Â¡Ãœ*Â–Ã˜Â­^h?1Â¯Â…{lÂÃ†ÃŒÃ™Â›nKmJSJÃ›ÃœÂ¸Â <OÃ§Â’ÃÂÃ®Ã°-Ã•7Ã¶Â™ Â¢8Â§Ã²NÂ‰lÂ·_pHÂƒÃ¹*Ã“A;Ã¦Â’Ã—fÂ­UrjÂ²Â‡D=Â³Ã¿uHÃ™!Ãª=Ã†ÃÂ©Ã¼LÂ®Ã¹=Ã«Â’~Ã¤Â‚Â“,Â®sÃ”#Ã”Ã‡Ã\\bFÃ¶Ã™Ã¥HCYZFÂ°LQÃ²Â¶Â´\\rÃ‡OÂ–Ã§Â„\\f%YÃ¿Â”Ã¾Â„ÂœU$Ã˜Â¶+Ã‚-ÃµzÃŠ,ÂŠÂ·Ã¢Ã$Ã›Â¾mÃ¦Â‡ÂÃ±bKÃ…Ã­VÂÃ°Â…ÃaÂ†ÃŸ)_Ã–ÂˆÃ‹. RH\\nÃ‘OÂ¦nÂš2ÃÃÂ¶WÃ†Ã¢ÂBÃ’Â±Fj!ÂºÂ¿i\\rv~Ã•Â­Â†Ã½s1Â²6UÃ¯Â·Ã²Â‹Â‰Â±KÃœW5ÂŸÂ²1Ã—Ãˆfr\\t:-Â°c*\\fÃ¸Â¸J\Â‡eÃ‡Â’9ÂŸÂ¥Â‰Â­eÃ¯kÂ¥3Â·oÂ­Ã„Â«Â¼Ã§gÂ¥Â‡ Ã…ydÃ‡Ã¸ÃŒÃ‘Rf?>'"^zr:Â®Â…<\}Â¤Â¾rÂ€(Ã€Â˜Ã‰Ã°Ã˜Ã·Â†\\nÂ‚@Â†iYÂ˜Â¤Ã‹jÂµ(Ã¯nÂ³HÂÃ€Â·Ã®3Â†$ÃŠÂ¶,Ã®Ã½ÃŸÂ…Ã­Â…oÂÃ¸rÂ¿Â„aÂ§Ã§AÂ©Â§nÂ­#ÂÃ¢Â­Ã­Ã¬XÂ¾ÂµÃ­?Â¾}Â£Ã¢*Ã‰Â…S2DÃ¸"Â¸Ã\\f1Â¦Â•AÃbdkÃ¸Â”Â²Ã…%GÂ›ÂºÃ¸RcÃµÂ›Â LÂ‚ Ã›Ã„ÃÃƒÂŸi%8+ÃŸÂ€.\\rÂ¦ÃŠÂšÂmdÃ¥zymÂ˜ÂŸfÃ‹Â´{Â¬yÂ Â‡Ã‹Ãl8-Ã30Ã­Ã‚\\b\\r:3K?Â‡Ã“Â›Â¨?Â¤Â¾qÃ´+Ã¼Â¯Ã„Â«Â›Ã¯Tv`[ÃŒÃkÃ¦Â˜41Y(Ã¶"ÂªÂ½Ã¸Ã lÃ£Â².ÃÃ€Ã‡Â§ÃªÃÃ‹RÃ²ÂÃ«ÂŠ;Ã‡ÃÂ±$ÃºÂ¡ÃÂŸ<+ÃœÃšÂšMlÂµÃ¿Â„ÃÂ„Â±=Ã©Ã“^Â©Ã¹Â†Â¨Ã¢/JÃ”Ã£Ã9Ã±RkÃ¦Â£2W|Â¼Â’3Ã¿Â…Ã€CÃ¡ÃŒÃÃºÃ¨^JÃ©Ã"Â‚<zÃ®Â—Ã“nÃ½Ã¨ÂÂ«Ã›Ã¿sÂªpÃ±Â”-ÂÃ¹8ÃˆÂœ'iÂ¿Ã²Ã¬<Â¡ÃÂ—w.Ã¾Ã†Ã¶Ã…Ã‘Ã…Ã­xÃ‡Ã¥Ã†Â­VwK Ãµk{cÃ”Ã‹Ã¯ÂŒ+ÃŠ\\\fÃ€OÃ¶ÃÃ Ã‘Ã@!\~LÂ—Ã—Ã±Ã³eWÂ²ÃÃ„)ÃÃ‘T^)Â€ÂdBKpCÃ«Ã’CÃ£ÂœazÃ€Âµ7Â§ Â£fÂ¤QEÃ‰IÃÂ´Ã®Ã„ÃœN,oÃ°ÂsÂ¿DÃWÂ¤Â¸P}ÂŠÃ¦Â·Â¸Ã»Ã¢ÃšJnÃ¡WÂ¡JÃ¾ÃŸVpÂ»Â”ZÃ€Â·Ã¨Â¦Â´Ã£Â¢Â¢Ã‹61@{RÂ¨\M yÂ–Â¿x1Â¥ÂldzÂŸvÂ•y\\r\\fÃ¾Â¹*YÃŸÂªLÂ£Ã udÃ¨bÃ–Â³dÂ«ÂAÃ—Â©|Â­BcNgvÃŒMÂœÃ“Ã©:t<Ã­Â¶ÂŸÂ­Ãƒ<5.'txzÃœ=HÃ‘ÂÂ¦Â¸ÂXÂ“e<Ãˆ#Ã¹OÃ¶ÂŠ#Ã»ÂœÃµ9Â™Â€O6#Ã¢"jÂ•Â­KeÃ´zlZZÂ¨Â¤3ÂŠYÃ¿Ã–ÃÂ«ÂÂ§Ã¢CÂ‰Ty)Â·Ã¤02k,Ã¡/H Ã´/Ã¯~/Ru{Â’%4Ã—.Â¥?5ÃrÂ·OÃhÃ¡kÂ³ÂµÂ“coÃµÃ½bÂIÃ³Ã®i/Â<OUÃ  Â·Ã˜#Ã¢kÂ²Â€Ãª3>`Ã¶Â´Â‡Ã»Â§Ã©\\b]ÂŠÃ¬Â‡5Ã®M]"Ã§Â…:*Â©Ã‰ÂŸADMÂ¹rp'Â†Â¥2Â­ÃÃ€Â™Ã¡8Ã—^Ã(Ã†Ã¡`bÂÃ‰Ãˆ$Ã¥ÂwÂ¼Ã¸Â‚Ã‚Â£iÃŒtÃ´Ã™Â±C3ÂœofÂ•Ã3Â¤GÃ½ÂˆÃ–ÂÂ“Â…TTÃ‚ÃˆÂÂÂ„ÂÂ«Â²Â€ÂŒÃ´eÃ»gÂ©IÂ§jÃ¸MÂšÃ’\\fÂ©g?Â®iÃ¹Ã°Ã¶1sÃœ09 Ã¨hCUÃ§rÂ‚%\\tÂ¼=KÂ—lÃ°J\\tÂ»ÂÂ®ÃÃJÂ±Â‘Ã£Ã‹sÂ—ÂƒNSÂªld5Ã•Ã‹Ã­Ã¯JÃˆtÂ’Ã‰Â„Â‘ÂÃ™QÂ°fÃ—\\nT,Ã \\tÂ¶YaNÃ¤+$`ÂÂ—Ã†Ã!Ã6]kHRÃ­Ã²Ã£Ã‚Ã¹Â‚"Â¬ÃšÂ¹oÂ™Ã»&Â¢7e^ÃµÂ¦Ã©LÂ·PÂ»;+ÂÂ˜HyÂÃÃ‡Â¯>ÃŸÂ¢Â“Ã•~Ã—RÂ¦^u(Â€Â¡ÂƒHDÃ”Â‹Â¤Ã¸oÃµ{?;hJÂŠÂ¹Â¾Â¥ÂˆÃ‹ÂÃ¨Ã§Ã¢\\b9ÃÃ»Â©|Â’ÂŒ;\u'
    //   11: dup
    //   12: astore_2
    //   13: invokevirtual length : ()I
    //   16: istore #4
    //   18: bipush #18
    //   20: istore_1
    //   21: iconst_m1
    //   22: istore_0
    //   23: bipush #44
    //   25: iinc #0, 1
    //   28: aload_2
    //   29: iload_0
    //   30: dup
    //   31: iload_1
    //   32: iadd
    //   33: invokevirtual substring : (II)Ljava/lang/String;
    //   36: iconst_m1
    //   37: goto -> 143
    //   40: aload #5
    //   42: swap
    //   43: iload_3
    //   44: iinc #3, 1
    //   47: swap
    //   48: aastore
    //   49: iload_0
    //   50: iload_1
    //   51: iadd
    //   52: dup
    //   53: istore_0
    //   54: iload #4
    //   56: if_icmpge -> 68
    //   59: aload_2
    //   60: iload_0
    //   61: invokevirtual charAt : (I)C
    //   64: istore_1
    //   65: goto -> 23
    //   68: ldc 'PÂ¬ÂˆÃ¡Ã•=lÂ‡\\rÃ³ÃÃ»Ã¶ÃªÂ¡|BÂŒÂ‘~Âµ2sÂ¯Â¤Â¢Â´Â”|Â¬ÃÂ sbw\\tDÃ³Ã°\\neiÃ¬Â­Â…Ã›L5'Ã´Ã¸^Ã‰aÂªtÃ‘JÃ‹Ã¾r+Â¾2Ã¾FÂª;ÃªEÃ¦Â«zÃ‡Ã›|Â£<\\nÂ¦#SygÂ³Â€Â˜\\bÃªÃ£Â·1 HÂ‘MÃ¿Ã­Ã·Ãš0Â¾Â±iÂ¡\\t2-rÂÃ™3Â¿PÂ ÂŠÂ®sÃÂ­lÃ©Ã¼p?Ã˜Ã¥]'
    //   70: dup
    //   71: astore_2
    //   72: invokevirtual length : ()I
    //   75: istore #4
    //   77: bipush #44
    //   79: istore_1
    //   80: iconst_m1
    //   81: istore_0
    //   82: bipush #121
    //   84: iinc #0, 1
    //   87: aload_2
    //   88: iload_0
    //   89: dup
    //   90: iload_1
    //   91: iadd
    //   92: invokevirtual substring : (II)Ljava/lang/String;
    //   95: iconst_0
    //   96: goto -> 143
    //   99: aload #5
    //   101: swap
    //   102: iload_3
    //   103: iinc #3, 1
    //   106: swap
    //   107: aastore
    //   108: iload_0
    //   109: iload_1
    //   110: iadd
    //   111: dup
    //   112: istore_0
    //   113: iload #4
    //   115: if_icmpge -> 127
    //   118: aload_2
    //   119: iload_0
    //   120: invokevirtual charAt : (I)C
    //   123: istore_1
    //   124: goto -> 82
    //   127: aload #5
    //   129: putstatic burp/Zr41.a : [Ljava/lang/String;
    //   132: bipush #34
    //   134: anewarray java/lang/String
    //   137: putstatic burp/Zr41.b : [Ljava/lang/String;
    //   140: goto -> 300
    //   143: dup_x2
    //   144: pop
    //   145: invokevirtual toCharArray : ()[C
    //   148: dup_x1
    //   149: arraylength
    //   150: dup_x2
    //   151: pop
    //   152: iconst_0
    //   153: istore #6
    //   155: dup2_x1
    //   156: pop2
    //   157: dup_x2
    //   158: iconst_1
    //   159: if_icmpgt -> 260
    //   162: dup2
    //   163: swap
    //   164: iload #6
    //   166: dup2_x1
    //   167: caload
    //   168: swap
    //   169: iload #6
    //   171: bipush #7
    //   173: irem
    //   174: tableswitch default -> 242, 0 -> 212, 1 -> 217, 2 -> 222, 3 -> 227, 4 -> 232, 5 -> 237
    //   212: bipush #28
    //   214: goto -> 244
    //   217: bipush #32
    //   219: goto -> 244
    //   222: bipush #30
    //   224: goto -> 244
    //   227: bipush #48
    //   229: goto -> 244
    //   232: bipush #21
    //   234: goto -> 244
    //   237: bipush #19
    //   239: goto -> 244
    //   242: bipush #123
    //   244: ixor
    //   245: ixor
    //   246: i2c
    //   247: castore
    //   248: iinc #6, 1
    //   251: dup
    //   252: ifne -> 260
    //   255: dup2
    //   256: dup_x1
    //   257: goto -> 166
    //   260: dup2_x1
    //   261: pop2
    //   262: dup_x2
    //   263: iload #6
    //   265: if_icmpgt -> 162
    //   268: pop
    //   269: new java/lang/String
    //   272: dup_x1
    //   273: swap
    //   274: invokespecial <init> : ([C)V
    //   277: invokevirtual intern : ()Ljava/lang/String;
    //   280: swap
    //   281: pop
    //   282: swap
    //   283: tableswitch default -> 40, 0 -> 99
    //   300: return
  }
  
  private static String a(int paramInt1, int paramInt2) {
    int i = (paramInt1 ^ 0x13DD) & 0xFFFF;
    if (b[i] == null) {
      char[] arrayOfChar = a[i].toCharArray();
      switch (arrayOfChar[0] & 0xFF) {
        case 0:
        
        case 1:
        
        case 2:
        
        case 3:
        
        case 4:
        
        case 5:
        
        case 6:
        
        case 7:
        
        case 8:
        
        case 9:
        
        case 10:
        
        case 11:
        
        case 12:
        
        case 13:
        
        case 14:
        
        case 15:
        
        case 16:
        
        case 17:
        
        case 18:
        
        case 19:
        
        case 20:
        
        case 21:
        
        case 22:
        
        case 23:
        
        case 24:
        
        case 25:
        
        case 26:
        
        case 27:
        
        case 28:
        
        case 29:
        
        case 30:
        
        case 31:
        
        case 32:
        
        case 33:
        
        case 34:
        
        case 35:
        
        case 36:
        
        case 37:
        
        case 38:
        
        case 39:
        
        case 40:
        
        case 41:
        
        case 42:
        
        case 43:
        
        case 44:
        
        case 45:
        
        case 46:
        
        case 47:
        
        case 48:
        
        case 49:
        
        case 50:
        
        case 51:
        
        case 52:
        
        case 53:
        
        case 54:
        
        case 55:
        
        case 56:
        
        case 57:
        
        case 58:
        
        case 59:
        
        case 60:
        
        case 61:
        
        case 62:
        
        case 63:
        
        case 64:
        
        case 65:
        
        case 66:
        
        case 67:
        
        case 68:
        
        case 69:
        
        case 70:
        
        case 71:
        
        case 72:
        
        case 73:
        
        case 74:
        
        case 75:
        
        case 76:
        
        case 77:
        
        case 78:
        
        case 79:
        
        case 80:
        
        case 81:
        
        case 82:
        
        case 83:
        
        case 84:
        
        case 85:
        
        case 86:
        
        case 87:
        
        case 88:
        
        case 89:
        
        case 90:
        
        case 91:
        
        case 92:
        
        case 93:
        
        case 94:
        
        case 95:
        
        case 96:
        
        case 97:
        
        case 98:
        
        case 99:
        
        case 100:
        
        case 101:
        
        case 102:
        
        case 103:
        
        case 104:
        
        case 105:
        
        case 106:
        
        case 107:
        
        case 108:
        
        case 109:
        
        case 110:
        
        case 111:
        
        case 112:
        
        case 113:
        
        case 114:
        
        case 115:
        
        case 116:
        
        case 117:
        
        case 118:
        
        case 119:
        
        case 120:
        
        case 121:
        
        case 122:
        
        case 123:
        
        case 124:
        
        case 125:
        
        case 126:
        
        case 127:
        
        case 128:
        
        case 129:
        
        case 130:
        
        case 131:
        
        case 132:
        
        case 133:
        
        case 134:
        
        case 135:
        
        case 136:
        
        case 137:
        
        case 138:
        
        case 139:
        
        case 140:
        
        case 141:
        
        case 142:
        
        case 143:
        
        case 144:
        
        case 145:
        
        case 146:
        
        case 147:
        
        case 148:
        
        case 149:
        
        case 150:
        
        case 151:
        
        case 152:
        
        case 153:
        
        case 154:
        
        case 155:
        
        case 156:
        
        case 157:
        
        case 158:
        
        case 159:
        
        case 160:
        
        case 161:
        
        case 162:
        
        case 163:
        
        case 164:
        
        case 165:
        
        case 166:
        
        case 167:
        
        case 168:
        
        case 169:
        
        case 170:
        
        case 171:
        
        case 172:
        
        case 173:
        
        case 174:
        
        case 175:
        
        case 176:
        
        case 177:
        
        case 178:
        
        case 179:
        
        case 180:
        
        case 181:
        
        case 182:
        
        case 183:
        
        case 184:
        
        case 185:
        
        case 186:
        
        case 187:
        
        case 188:
        
        case 189:
        
        case 190:
        
        case 191:
        
        case 192:
        
        case 193:
        
        case 194:
        
        case 195:
        
        case 196:
        
        case 197:
        
        case 198:
        
        case 199:
        
        case 200:
        
        case 201:
        
        case 202:
        
        case 203:
        
        case 204:
        
        case 205:
        
        case 206:
        
        case 207:
        
        case 208:
        
        case 209:
        
        case 210:
        
        case 211:
        
        case 212:
        
        case 213:
        
        case 214:
        
        case 215:
        
        case 216:
        
        case 217:
        
        case 218:
        
        case 219:
        
        case 220:
        
        case 221:
        
        case 222:
        
        case 223:
        
        case 224:
        
        case 225:
        
        case 226:
        
        case 227:
        
        case 228:
        
        case 229:
        
        case 230:
        
        case 231:
        
        case 232:
        
        case 233:
        
        case 234:
        
        case 235:
        
        case 236:
        
        case 237:
        
        case 238:
        
        case 239:
        
        case 240:
        
        case 241:
        
        case 242:
        
        case 243:
        
        case 244:
        
        case 245:
        
        case 246:
        
        case 247:
        
        case 248:
        
        case 249:
        
        case 250:
        
        case 251:
        
        case 252:
        
        case 253:
        
        case 254:
        
        default:
          break;
      } 
      byte b1 = 26;
      int j = (paramInt2 & 0xFF) - b1;
      if (j < 0)
        j += 256; 
      int k = ((paramInt2 & 0xFFFF) >>> 8) - b1;
      if (k < 0)
        k += 256; 
      for (byte b2 = 0; b2 < arrayOfChar.length; b2++) {
        int m = b2 % 2;
        if (m == 0) {
          arrayOfChar[b2] = (char)(arrayOfChar[b2] ^ j);
          j = ((j >>> 3 | j << 5) ^ arrayOfChar[b2]) & 0xFF;
        } else {
          arrayOfChar[b2] = (char)(arrayOfChar[b2] ^ k);
          k = ((k >>> 3 | k << 5) ^ arrayOfChar[b2]) & 0xFF;
        } 
      } 
      b[i] = (new String(arrayOfChar)).intern();
    } 
    return b[i];
  }
}


/* Location:              C:\Program Files\BurpSuitePro\burpsuite_pro.jar!\burp\Zr41.class
 * Java compiler version: 21 (65.0)
 * JD-Core Version:       1.1.3
 */