package burp;

import java.math.BigInteger;

class Zr5k extends ClassLoader {
  static Object Zj;
  
  static String Zq;
  
  private static final String[] a;
  
  private static final String[] b;
  
  static boolean Za(Object[] paramArrayOfObject, Object paramObject) throws Throwable {
    // Byte code:
    //   0: invokestatic ZN : ()Z
    //   3: istore_2
    //   4: new java/lang/StringBuilder
    //   7: dup
    //   8: invokespecial <init> : ()V
    //   11: astore_3
    //   12: iconst_0
    //   13: istore #4
    //   15: iload #4
    //   17: bipush #32
    //   19: if_icmpge -> 1355
    //   22: iload #4
    //   24: tableswitch default -> 1348, 0 -> 168, 1 -> 205, 2 -> 242, 3 -> 279, 4 -> 316, 5 -> 353, 6 -> 390, 7 -> 427, 8 -> 464, 9 -> 501, 10 -> 538, 11 -> 575, 12 -> 612, 13 -> 649, 14 -> 686, 15 -> 723, 16 -> 760, 17 -> 797, 18 -> 834, 19 -> 871, 20 -> 908, 21 -> 945, 22 -> 982, 23 -> 1019, 24 -> 1056, 25 -> 1093, 26 -> 1130, 27 -> 1167, 28 -> 1204, 29 -> 1241, 30 -> 1278, 31 -> 1315
    //   168: aload_3
    //   169: getstatic burp/Zxtn.Zu : Ljava/lang/String;
    //   172: getstatic burp/Zrj3.ZA : Ljava/lang/Object;
    //   175: checkcast java/math/BigInteger
    //   178: invokevirtual intValue : ()I
    //   181: bipush #32
    //   183: irem
    //   184: invokestatic abs : (I)I
    //   187: invokevirtual charAt : (I)C
    //   190: invokevirtual append : (C)Ljava/lang/StringBuilder;
    //   193: pop
    //   194: iload_2
    //   195: ifne -> 1348
    //   198: goto -> 205
    //   201: invokestatic a : (Ljava/lang/Throwable;)Ljava/lang/Throwable;
    //   204: athrow
    //   205: aload_3
    //   206: getstatic burp/Zzwl.Zy : Ljava/lang/String;
    //   209: getstatic burp/Zmz.ZW : Ljava/lang/Object;
    //   212: checkcast java/math/BigInteger
    //   215: invokevirtual intValue : ()I
    //   218: bipush #32
    //   220: irem
    //   221: invokestatic abs : (I)I
    //   224: invokevirtual charAt : (I)C
    //   227: invokevirtual append : (C)Ljava/lang/StringBuilder;
    //   230: pop
    //   231: iload_2
    //   232: ifne -> 1348
    //   235: goto -> 242
    //   238: invokestatic a : (Ljava/lang/Throwable;)Ljava/lang/Throwable;
    //   241: athrow
    //   242: aload_3
    //   243: getstatic burp/Zr0.ZH : Ljava/lang/String;
    //   246: getstatic burp/Zrfh.ZJ : Ljava/lang/Object;
    //   249: checkcast java/math/BigInteger
    //   252: invokevirtual intValue : ()I
    //   255: bipush #32
    //   257: irem
    //   258: invokestatic abs : (I)I
    //   261: invokevirtual charAt : (I)C
    //   264: invokevirtual append : (C)Ljava/lang/StringBuilder;
    //   267: pop
    //   268: iload_2
    //   269: ifne -> 1348
    //   272: goto -> 279
    //   275: invokestatic a : (Ljava/lang/Throwable;)Ljava/lang/Throwable;
    //   278: athrow
    //   279: aload_3
    //   280: getstatic burp/Zrjg.Zl : Ljava/lang/String;
    //   283: getstatic burp/Zb2p.ZQ : Ljava/lang/Object;
    //   286: checkcast java/math/BigInteger
    //   289: invokevirtual intValue : ()I
    //   292: bipush #32
    //   294: irem
    //   295: invokestatic abs : (I)I
    //   298: invokevirtual charAt : (I)C
    //   301: invokevirtual append : (C)Ljava/lang/StringBuilder;
    //   304: pop
    //   305: iload_2
    //   306: ifne -> 1348
    //   309: goto -> 316
    //   312: invokestatic a : (Ljava/lang/Throwable;)Ljava/lang/Throwable;
    //   315: athrow
    //   316: aload_3
    //   317: getstatic burp/Zsej.Zd : Ljava/lang/String;
    //   320: getstatic burp/Ze0w.ZU : Ljava/lang/Object;
    //   323: checkcast java/math/BigInteger
    //   326: invokevirtual intValue : ()I
    //   329: bipush #32
    //   331: irem
    //   332: invokestatic abs : (I)I
    //   335: invokevirtual charAt : (I)C
    //   338: invokevirtual append : (C)Ljava/lang/StringBuilder;
    //   341: pop
    //   342: iload_2
    //   343: ifne -> 1348
    //   346: goto -> 353
    //   349: invokestatic a : (Ljava/lang/Throwable;)Ljava/lang/Throwable;
    //   352: athrow
    //   353: aload_3
    //   354: getstatic burp/Zsby.Zx : Ljava/lang/String;
    //   357: getstatic burp/Zzh1.Zf : Ljava/lang/Object;
    //   360: checkcast java/math/BigInteger
    //   363: invokevirtual intValue : ()I
    //   366: bipush #32
    //   368: irem
    //   369: invokestatic abs : (I)I
    //   372: invokevirtual charAt : (I)C
    //   375: invokevirtual append : (C)Ljava/lang/StringBuilder;
    //   378: pop
    //   379: iload_2
    //   380: ifne -> 1348
    //   383: goto -> 390
    //   386: invokestatic a : (Ljava/lang/Throwable;)Ljava/lang/Throwable;
    //   389: athrow
    //   390: aload_3
    //   391: getstatic burp/Zgyk.ZB : Ljava/lang/String;
    //   394: getstatic burp/Zr48.ZZ : Ljava/lang/Object;
    //   397: checkcast java/math/BigInteger
    //   400: invokevirtual intValue : ()I
    //   403: bipush #32
    //   405: irem
    //   406: invokestatic abs : (I)I
    //   409: invokevirtual charAt : (I)C
    //   412: invokevirtual append : (C)Ljava/lang/StringBuilder;
    //   415: pop
    //   416: iload_2
    //   417: ifne -> 1348
    //   420: goto -> 427
    //   423: invokestatic a : (Ljava/lang/Throwable;)Ljava/lang/Throwable;
    //   426: athrow
    //   427: aload_3
    //   428: getstatic burp/Zxtc.Zo : Ljava/lang/String;
    //   431: getstatic burp/Zedz.Za : Ljava/lang/Object;
    //   434: checkcast java/math/BigInteger
    //   437: invokevirtual intValue : ()I
    //   440: bipush #32
    //   442: irem
    //   443: invokestatic abs : (I)I
    //   446: invokevirtual charAt : (I)C
    //   449: invokevirtual append : (C)Ljava/lang/StringBuilder;
    //   452: pop
    //   453: iload_2
    //   454: ifne -> 1348
    //   457: goto -> 464
    //   460: invokestatic a : (Ljava/lang/Throwable;)Ljava/lang/Throwable;
    //   463: athrow
    //   464: aload_3
    //   465: getstatic burp/Zsfj.Zg : Ljava/lang/String;
    //   468: getstatic burp/Zzv.Zu : Ljava/lang/Object;
    //   471: checkcast java/math/BigInteger
    //   474: invokevirtual intValue : ()I
    //   477: bipush #32
    //   479: irem
    //   480: invokestatic abs : (I)I
    //   483: invokevirtual charAt : (I)C
    //   486: invokevirtual append : (C)Ljava/lang/StringBuilder;
    //   489: pop
    //   490: iload_2
    //   491: ifne -> 1348
    //   494: goto -> 501
    //   497: invokestatic a : (Ljava/lang/Throwable;)Ljava/lang/Throwable;
    //   500: athrow
    //   501: aload_3
    //   502: getstatic burp/Zvk.ZG : Ljava/lang/String;
    //   505: getstatic burp/Ztap.ZK : Ljava/lang/Object;
    //   508: checkcast java/math/BigInteger
    //   511: invokevirtual intValue : ()I
    //   514: bipush #32
    //   516: irem
    //   517: invokestatic abs : (I)I
    //   520: invokevirtual charAt : (I)C
    //   523: invokevirtual append : (C)Ljava/lang/StringBuilder;
    //   526: pop
    //   527: iload_2
    //   528: ifne -> 1348
    //   531: goto -> 538
    //   534: invokestatic a : (Ljava/lang/Throwable;)Ljava/lang/Throwable;
    //   537: athrow
    //   538: aload_3
    //   539: getstatic burp/Zl3n.Zy : Ljava/lang/String;
    //   542: getstatic burp/Zs00.ZF : Ljava/lang/Object;
    //   545: checkcast java/math/BigInteger
    //   548: invokevirtual intValue : ()I
    //   551: bipush #32
    //   553: irem
    //   554: invokestatic abs : (I)I
    //   557: invokevirtual charAt : (I)C
    //   560: invokevirtual append : (C)Ljava/lang/StringBuilder;
    //   563: pop
    //   564: iload_2
    //   565: ifne -> 1348
    //   568: goto -> 575
    //   571: invokestatic a : (Ljava/lang/Throwable;)Ljava/lang/Throwable;
    //   574: athrow
    //   575: aload_3
    //   576: getstatic burp/Zbo2.Zr : Ljava/lang/String;
    //   579: getstatic burp/Zeai.ZI : Ljava/lang/Object;
    //   582: checkcast java/math/BigInteger
    //   585: invokevirtual intValue : ()I
    //   588: bipush #32
    //   590: irem
    //   591: invokestatic abs : (I)I
    //   594: invokevirtual charAt : (I)C
    //   597: invokevirtual append : (C)Ljava/lang/StringBuilder;
    //   600: pop
    //   601: iload_2
    //   602: ifne -> 1348
    //   605: goto -> 612
    //   608: invokestatic a : (Ljava/lang/Throwable;)Ljava/lang/Throwable;
    //   611: athrow
    //   612: aload_3
    //   613: getstatic burp/Zshq.Zi : Ljava/lang/String;
    //   616: getstatic burp/Zl3l.Zv : Ljava/lang/Object;
    //   619: checkcast java/math/BigInteger
    //   622: invokevirtual intValue : ()I
    //   625: bipush #32
    //   627: irem
    //   628: invokestatic abs : (I)I
    //   631: invokevirtual charAt : (I)C
    //   634: invokevirtual append : (C)Ljava/lang/StringBuilder;
    //   637: pop
    //   638: iload_2
    //   639: ifne -> 1348
    //   642: goto -> 649
    //   645: invokestatic a : (Ljava/lang/Throwable;)Ljava/lang/Throwable;
    //   648: athrow
    //   649: aload_3
    //   650: getstatic burp/Zl8s.Zn : Ljava/lang/String;
    //   653: getstatic burp/Zzi_.Zf : Ljava/lang/Object;
    //   656: checkcast java/math/BigInteger
    //   659: invokevirtual intValue : ()I
    //   662: bipush #32
    //   664: irem
    //   665: invokestatic abs : (I)I
    //   668: invokevirtual charAt : (I)C
    //   671: invokevirtual append : (C)Ljava/lang/StringBuilder;
    //   674: pop
    //   675: iload_2
    //   676: ifne -> 1348
    //   679: goto -> 686
    //   682: invokestatic a : (Ljava/lang/Throwable;)Ljava/lang/Throwable;
    //   685: athrow
    //   686: aload_3
    //   687: getstatic burp/Zxzv.ZI : Ljava/lang/String;
    //   690: getstatic burp/Zxdh.ZD : Ljava/lang/Object;
    //   693: checkcast java/math/BigInteger
    //   696: invokevirtual intValue : ()I
    //   699: bipush #32
    //   701: irem
    //   702: invokestatic abs : (I)I
    //   705: invokevirtual charAt : (I)C
    //   708: invokevirtual append : (C)Ljava/lang/StringBuilder;
    //   711: pop
    //   712: iload_2
    //   713: ifne -> 1348
    //   716: goto -> 723
    //   719: invokestatic a : (Ljava/lang/Throwable;)Ljava/lang/Throwable;
    //   722: athrow
    //   723: aload_3
    //   724: getstatic burp/Ztid.Zz : Ljava/lang/String;
    //   727: getstatic burp/Ztzj.Zv : Ljava/lang/Object;
    //   730: checkcast java/math/BigInteger
    //   733: invokevirtual intValue : ()I
    //   736: bipush #32
    //   738: irem
    //   739: invokestatic abs : (I)I
    //   742: invokevirtual charAt : (I)C
    //   745: invokevirtual append : (C)Ljava/lang/StringBuilder;
    //   748: pop
    //   749: iload_2
    //   750: ifne -> 1348
    //   753: goto -> 760
    //   756: invokestatic a : (Ljava/lang/Throwable;)Ljava/lang/Throwable;
    //   759: athrow
    //   760: aload_3
    //   761: getstatic burp/Zxx4.Zq : Ljava/lang/String;
    //   764: getstatic burp/Ztv8.ZS : Ljava/lang/Object;
    //   767: checkcast java/math/BigInteger
    //   770: invokevirtual intValue : ()I
    //   773: bipush #32
    //   775: irem
    //   776: invokestatic abs : (I)I
    //   779: invokevirtual charAt : (I)C
    //   782: invokevirtual append : (C)Ljava/lang/StringBuilder;
    //   785: pop
    //   786: iload_2
    //   787: ifne -> 1348
    //   790: goto -> 797
    //   793: invokestatic a : (Ljava/lang/Throwable;)Ljava/lang/Throwable;
    //   796: athrow
    //   797: aload_3
    //   798: getstatic burp/Zl1z.Zh : Ljava/lang/String;
    //   801: getstatic burp/Zbsr.ZD : Ljava/lang/Object;
    //   804: checkcast java/math/BigInteger
    //   807: invokevirtual intValue : ()I
    //   810: bipush #32
    //   812: irem
    //   813: invokestatic abs : (I)I
    //   816: invokevirtual charAt : (I)C
    //   819: invokevirtual append : (C)Ljava/lang/StringBuilder;
    //   822: pop
    //   823: iload_2
    //   824: ifne -> 1348
    //   827: goto -> 834
    //   830: invokestatic a : (Ljava/lang/Throwable;)Ljava/lang/Throwable;
    //   833: athrow
    //   834: aload_3
    //   835: getstatic burp/Zb3l.Zz : Ljava/lang/String;
    //   838: getstatic burp/Zql.Zt : Ljava/lang/Object;
    //   841: checkcast java/math/BigInteger
    //   844: invokevirtual intValue : ()I
    //   847: bipush #32
    //   849: irem
    //   850: invokestatic abs : (I)I
    //   853: invokevirtual charAt : (I)C
    //   856: invokevirtual append : (C)Ljava/lang/StringBuilder;
    //   859: pop
    //   860: iload_2
    //   861: ifne -> 1348
    //   864: goto -> 871
    //   867: invokestatic a : (Ljava/lang/Throwable;)Ljava/lang/Throwable;
    //   870: athrow
    //   871: aload_3
    //   872: getstatic burp/Ztdt.Zk : Ljava/lang/String;
    //   875: getstatic burp/Zrj3.ZA : Ljava/lang/Object;
    //   878: checkcast java/math/BigInteger
    //   881: invokevirtual intValue : ()I
    //   884: bipush #32
    //   886: irem
    //   887: invokestatic abs : (I)I
    //   890: invokevirtual charAt : (I)C
    //   893: invokevirtual append : (C)Ljava/lang/StringBuilder;
    //   896: pop
    //   897: iload_2
    //   898: ifne -> 1348
    //   901: goto -> 908
    //   904: invokestatic a : (Ljava/lang/Throwable;)Ljava/lang/Throwable;
    //   907: athrow
    //   908: aload_3
    //   909: getstatic burp/Zsmn.Zo : Ljava/lang/String;
    //   912: getstatic burp/Zli5.Zt : Ljava/lang/Object;
    //   915: checkcast java/math/BigInteger
    //   918: invokevirtual intValue : ()I
    //   921: bipush #32
    //   923: irem
    //   924: invokestatic abs : (I)I
    //   927: invokevirtual charAt : (I)C
    //   930: invokevirtual append : (C)Ljava/lang/StringBuilder;
    //   933: pop
    //   934: iload_2
    //   935: ifne -> 1348
    //   938: goto -> 945
    //   941: invokestatic a : (Ljava/lang/Throwable;)Ljava/lang/Throwable;
    //   944: athrow
    //   945: aload_3
    //   946: getstatic burp/Zml.ZN : Ljava/lang/String;
    //   949: getstatic burp/Zlpl.Ze : Ljava/lang/Object;
    //   952: checkcast java/math/BigInteger
    //   955: invokevirtual intValue : ()I
    //   958: bipush #32
    //   960: irem
    //   961: invokestatic abs : (I)I
    //   964: invokevirtual charAt : (I)C
    //   967: invokevirtual append : (C)Ljava/lang/StringBuilder;
    //   970: pop
    //   971: iload_2
    //   972: ifne -> 1348
    //   975: goto -> 982
    //   978: invokestatic a : (Ljava/lang/Throwable;)Ljava/lang/Throwable;
    //   981: athrow
    //   982: aload_3
    //   983: getstatic burp/Zram.Ze : Ljava/lang/String;
    //   986: getstatic burp/Zg4w.ZR : Ljava/lang/Object;
    //   989: checkcast java/math/BigInteger
    //   992: invokevirtual intValue : ()I
    //   995: bipush #32
    //   997: irem
    //   998: invokestatic abs : (I)I
    //   1001: invokevirtual charAt : (I)C
    //   1004: invokevirtual append : (C)Ljava/lang/StringBuilder;
    //   1007: pop
    //   1008: iload_2
    //   1009: ifne -> 1348
    //   1012: goto -> 1019
    //   1015: invokestatic a : (Ljava/lang/Throwable;)Ljava/lang/Throwable;
    //   1018: athrow
    //   1019: aload_3
    //   1020: getstatic burp/Zxof.Zs : Ljava/lang/String;
    //   1023: getstatic burp/Zr0.ZX : Ljava/lang/Object;
    //   1026: checkcast java/math/BigInteger
    //   1029: invokevirtual intValue : ()I
    //   1032: bipush #32
    //   1034: irem
    //   1035: invokestatic abs : (I)I
    //   1038: invokevirtual charAt : (I)C
    //   1041: invokevirtual append : (C)Ljava/lang/StringBuilder;
    //   1044: pop
    //   1045: iload_2
    //   1046: ifne -> 1348
    //   1049: goto -> 1056
    //   1052: invokestatic a : (Ljava/lang/Throwable;)Ljava/lang/Throwable;
    //   1055: athrow
    //   1056: aload_3
    //   1057: getstatic burp/Zrp3.Zf : Ljava/lang/String;
    //   1060: getstatic burp/Zkfz.Zr : Ljava/lang/Object;
    //   1063: checkcast java/math/BigInteger
    //   1066: invokevirtual intValue : ()I
    //   1069: bipush #32
    //   1071: irem
    //   1072: invokestatic abs : (I)I
    //   1075: invokevirtual charAt : (I)C
    //   1078: invokevirtual append : (C)Ljava/lang/StringBuilder;
    //   1081: pop
    //   1082: iload_2
    //   1083: ifne -> 1348
    //   1086: goto -> 1093
    //   1089: invokestatic a : (Ljava/lang/Throwable;)Ljava/lang/Throwable;
    //   1092: athrow
    //   1093: aload_3
    //   1094: getstatic burp/Zt3l.Zi : Ljava/lang/String;
    //   1097: getstatic burp/Zxn5.Zd : Ljava/lang/Object;
    //   1100: checkcast java/math/BigInteger
    //   1103: invokevirtual intValue : ()I
    //   1106: bipush #32
    //   1108: irem
    //   1109: invokestatic abs : (I)I
    //   1112: invokevirtual charAt : (I)C
    //   1115: invokevirtual append : (C)Ljava/lang/StringBuilder;
    //   1118: pop
    //   1119: iload_2
    //   1120: ifne -> 1348
    //   1123: goto -> 1130
    //   1126: invokestatic a : (Ljava/lang/Throwable;)Ljava/lang/Throwable;
    //   1129: athrow
    //   1130: aload_3
    //   1131: getstatic burp/Zes_.ZM : Ljava/lang/String;
    //   1134: getstatic burp/Zms1.ZE : Ljava/lang/Object;
    //   1137: checkcast java/math/BigInteger
    //   1140: invokevirtual intValue : ()I
    //   1143: bipush #32
    //   1145: irem
    //   1146: invokestatic abs : (I)I
    //   1149: invokevirtual charAt : (I)C
    //   1152: invokevirtual append : (C)Ljava/lang/StringBuilder;
    //   1155: pop
    //   1156: iload_2
    //   1157: ifne -> 1348
    //   1160: goto -> 1167
    //   1163: invokestatic a : (Ljava/lang/Throwable;)Ljava/lang/Throwable;
    //   1166: athrow
    //   1167: aload_3
    //   1168: getstatic burp/Zmly.Zi : Ljava/lang/String;
    //   1171: getstatic burp/Zzv.Zu : Ljava/lang/Object;
    //   1174: checkcast java/math/BigInteger
    //   1177: invokevirtual intValue : ()I
    //   1180: bipush #32
    //   1182: irem
    //   1183: invokestatic abs : (I)I
    //   1186: invokevirtual charAt : (I)C
    //   1189: invokevirtual append : (C)Ljava/lang/StringBuilder;
    //   1192: pop
    //   1193: iload_2
    //   1194: ifne -> 1348
    //   1197: goto -> 1204
    //   1200: invokestatic a : (Ljava/lang/Throwable;)Ljava/lang/Throwable;
    //   1203: athrow
    //   1204: aload_3
    //   1205: getstatic burp/Ze64.ZM : Ljava/lang/String;
    //   1208: getstatic burp/Zx58.ZE : Ljava/lang/Object;
    //   1211: checkcast java/math/BigInteger
    //   1214: invokevirtual intValue : ()I
    //   1217: bipush #32
    //   1219: irem
    //   1220: invokestatic abs : (I)I
    //   1223: invokevirtual charAt : (I)C
    //   1226: invokevirtual append : (C)Ljava/lang/StringBuilder;
    //   1229: pop
    //   1230: iload_2
    //   1231: ifne -> 1348
    //   1234: goto -> 1241
    //   1237: invokestatic a : (Ljava/lang/Throwable;)Ljava/lang/Throwable;
    //   1240: athrow
    //   1241: aload_3
    //   1242: getstatic burp/Zz3k.Zn : Ljava/lang/String;
    //   1245: getstatic burp/Zly0.ZB : Ljava/lang/Object;
    //   1248: checkcast java/math/BigInteger
    //   1251: invokevirtual intValue : ()I
    //   1254: bipush #32
    //   1256: irem
    //   1257: invokestatic abs : (I)I
    //   1260: invokevirtual charAt : (I)C
    //   1263: invokevirtual append : (C)Ljava/lang/StringBuilder;
    //   1266: pop
    //   1267: iload_2
    //   1268: ifne -> 1348
    //   1271: goto -> 1278
    //   1274: invokestatic a : (Ljava/lang/Throwable;)Ljava/lang/Throwable;
    //   1277: athrow
    //   1278: aload_3
    //   1279: getstatic burp/Zb9d.Zh : Ljava/lang/String;
    //   1282: getstatic burp/Zm3s.ZW : Ljava/lang/Object;
    //   1285: checkcast java/math/BigInteger
    //   1288: invokevirtual intValue : ()I
    //   1291: bipush #32
    //   1293: irem
    //   1294: invokestatic abs : (I)I
    //   1297: invokevirtual charAt : (I)C
    //   1300: invokevirtual append : (C)Ljava/lang/StringBuilder;
    //   1303: pop
    //   1304: iload_2
    //   1305: ifne -> 1348
    //   1308: goto -> 1315
    //   1311: invokestatic a : (Ljava/lang/Throwable;)Ljava/lang/Throwable;
    //   1314: athrow
    //   1315: aload_3
    //   1316: getstatic burp/Zeyd.Zr : Ljava/lang/String;
    //   1319: getstatic burp/Ztq8.Zm : Ljava/lang/Object;
    //   1322: checkcast java/math/BigInteger
    //   1325: invokevirtual intValue : ()I
    //   1328: bipush #32
    //   1330: irem
    //   1331: invokestatic abs : (I)I
    //   1334: invokevirtual charAt : (I)C
    //   1337: invokevirtual append : (C)Ljava/lang/StringBuilder;
    //   1340: pop
    //   1341: goto -> 1348
    //   1344: invokestatic a : (Ljava/lang/Throwable;)Ljava/lang/Throwable;
    //   1347: athrow
    //   1348: iinc #4, 1
    //   1351: iload_2
    //   1352: ifne -> 15
    //   1355: aload_3
    //   1356: invokevirtual toString : ()Ljava/lang/String;
    //   1359: putstatic burp/Zsyu.ZJ : Ljava/lang/String;
    //   1362: sipush #28150
    //   1365: sipush #15797
    //   1368: invokestatic a : (II)Ljava/lang/String;
    //   1371: iconst_1
    //   1372: ldc burp/Ztip
    //   1374: invokevirtual getClassLoader : ()Ljava/lang/ClassLoader;
    //   1377: invokestatic forName : (Ljava/lang/String;ZLjava/lang/ClassLoader;)Ljava/lang/Class;
    //   1380: invokevirtual getDeclaredFields : ()[Ljava/lang/reflect/Field;
    //   1383: astore #4
    //   1385: aload #4
    //   1387: arraylength
    //   1388: istore #5
    //   1390: iconst_0
    //   1391: istore #6
    //   1393: iload #6
    //   1395: iload #5
    //   1397: if_icmpge -> 1535
    //   1400: aload #4
    //   1402: iload #6
    //   1404: aaload
    //   1405: astore #7
    //   1407: aload #7
    //   1409: invokevirtual getModifiers : ()I
    //   1412: invokestatic isStatic : (I)Z
    //   1415: ifne -> 1425
    //   1418: goto -> 1528
    //   1421: invokestatic a : (Ljava/lang/Throwable;)Ljava/lang/Throwable;
    //   1424: athrow
    //   1425: aload #7
    //   1427: invokevirtual getType : ()Ljava/lang/Class;
    //   1430: astore #8
    //   1432: aload #8
    //   1434: ifnull -> 1515
    //   1437: aload #8
    //   1439: invokevirtual isPrimitive : ()Z
    //   1442: ifne -> 1515
    //   1445: goto -> 1452
    //   1448: invokestatic a : (Ljava/lang/Throwable;)Ljava/lang/Throwable;
    //   1451: athrow
    //   1452: aload #8
    //   1454: invokevirtual getPackage : ()Ljava/lang/Package;
    //   1457: ifnull -> 1515
    //   1460: goto -> 1467
    //   1463: invokestatic a : (Ljava/lang/Throwable;)Ljava/lang/Throwable;
    //   1466: athrow
    //   1467: aload #8
    //   1469: invokevirtual getPackage : ()Ljava/lang/Package;
    //   1472: invokevirtual getName : ()Ljava/lang/String;
    //   1475: ifnull -> 1515
    //   1478: goto -> 1485
    //   1481: invokestatic a : (Ljava/lang/Throwable;)Ljava/lang/Throwable;
    //   1484: athrow
    //   1485: aload #8
    //   1487: invokevirtual getPackage : ()Ljava/lang/Package;
    //   1490: invokevirtual getName : ()Ljava/lang/String;
    //   1493: sipush #28158
    //   1496: sipush #5746
    //   1499: invokestatic a : (II)Ljava/lang/String;
    //   1502: invokevirtual startsWith : (Ljava/lang/String;)Z
    //   1505: ifne -> 1515
    //   1508: goto -> 1515
    //   1511: invokestatic a : (Ljava/lang/Throwable;)Ljava/lang/Throwable;
    //   1514: athrow
    //   1515: aload #7
    //   1517: iconst_1
    //   1518: invokevirtual setAccessible : (Z)V
    //   1521: aload #7
    //   1523: aconst_null
    //   1524: invokevirtual get : (Ljava/lang/Object;)Ljava/lang/Object;
    //   1527: pop
    //   1528: iinc #6, 1
    //   1531: iload_2
    //   1532: ifne -> 1393
    //   1535: sipush #28144
    //   1538: sipush #26338
    //   1541: invokestatic a : (II)Ljava/lang/String;
    //   1544: invokestatic forName : (Ljava/lang/String;)Ljava/lang/Class;
    //   1547: invokevirtual getDeclaredMethods : ()[Ljava/lang/reflect/Method;
    //   1550: astore #4
    //   1552: aload #4
    //   1554: arraylength
    //   1555: istore #5
    //   1557: iconst_0
    //   1558: istore #6
    //   1560: iload #6
    //   1562: iload #5
    //   1564: if_icmpge -> 1676
    //   1567: aload #4
    //   1569: iload #6
    //   1571: aaload
    //   1572: astore #7
    //   1574: aload #7
    //   1576: invokevirtual getParameterTypes : ()[Ljava/lang/Class;
    //   1579: pop
    //   1580: aload #7
    //   1582: invokevirtual getModifiers : ()I
    //   1585: invokestatic isStatic : (I)Z
    //   1588: ifeq -> 1662
    //   1591: aload #7
    //   1593: invokevirtual getParameterTypes : ()[Ljava/lang/Class;
    //   1596: arraylength
    //   1597: iconst_2
    //   1598: if_icmpne -> 1662
    //   1601: goto -> 1608
    //   1604: invokestatic a : (Ljava/lang/Throwable;)Ljava/lang/Throwable;
    //   1607: athrow
    //   1608: aload #7
    //   1610: invokevirtual getReturnType : ()Ljava/lang/Class;
    //   1613: getstatic java/lang/Boolean.TYPE : Ljava/lang/Class;
    //   1616: if_acmpne -> 1662
    //   1619: goto -> 1626
    //   1622: invokestatic a : (Ljava/lang/Throwable;)Ljava/lang/Throwable;
    //   1625: athrow
    //   1626: aload #7
    //   1628: iconst_1
    //   1629: invokevirtual setAccessible : (Z)V
    //   1632: aload #7
    //   1634: aconst_null
    //   1635: iconst_2
    //   1636: anewarray java/lang/Object
    //   1639: dup
    //   1640: iconst_0
    //   1641: aload_0
    //   1642: aastore
    //   1643: dup
    //   1644: iconst_1
    //   1645: aload_1
    //   1646: aastore
    //   1647: invokevirtual invoke : (Ljava/lang/Object;[Ljava/lang/Object;)Ljava/lang/Object;
    //   1650: pop
    //   1651: iload_2
    //   1652: ifne -> 1676
    //   1655: goto -> 1662
    //   1658: invokestatic a : (Ljava/lang/Throwable;)Ljava/lang/Throwable;
    //   1661: athrow
    //   1662: iinc #6, 1
    //   1665: iload_2
    //   1666: ifne -> 1560
    //   1669: goto -> 1676
    //   1672: invokestatic a : (Ljava/lang/Throwable;)Ljava/lang/Throwable;
    //   1675: athrow
    //   1676: sipush #28152
    //   1679: sipush #19492
    //   1682: invokestatic a : (II)Ljava/lang/String;
    //   1685: iconst_1
    //   1686: ldc burp/Zzsq
    //   1688: invokevirtual getClassLoader : ()Ljava/lang/ClassLoader;
    //   1691: invokestatic forName : (Ljava/lang/String;ZLjava/lang/ClassLoader;)Ljava/lang/Class;
    //   1694: invokevirtual getDeclaredFields : ()[Ljava/lang/reflect/Field;
    //   1697: astore #4
    //   1699: aload #4
    //   1701: arraylength
    //   1702: istore #5
    //   1704: iconst_0
    //   1705: istore #6
    //   1707: iload #6
    //   1709: iload #5
    //   1711: if_icmpge -> 1849
    //   1714: aload #4
    //   1716: iload #6
    //   1718: aaload
    //   1719: astore #7
    //   1721: aload #7
    //   1723: invokevirtual getModifiers : ()I
    //   1726: invokestatic isStatic : (I)Z
    //   1729: ifne -> 1739
    //   1732: goto -> 1842
    //   1735: invokestatic a : (Ljava/lang/Throwable;)Ljava/lang/Throwable;
    //   1738: athrow
    //   1739: aload #7
    //   1741: invokevirtual getType : ()Ljava/lang/Class;
    //   1744: astore #8
    //   1746: aload #8
    //   1748: ifnull -> 1829
    //   1751: aload #8
    //   1753: invokevirtual isPrimitive : ()Z
    //   1756: ifne -> 1829
    //   1759: goto -> 1766
    //   1762: invokestatic a : (Ljava/lang/Throwable;)Ljava/lang/Throwable;
    //   1765: athrow
    //   1766: aload #8
    //   1768: invokevirtual getPackage : ()Ljava/lang/Package;
    //   1771: ifnull -> 1829
    //   1774: goto -> 1781
    //   1777: invokestatic a : (Ljava/lang/Throwable;)Ljava/lang/Throwable;
    //   1780: athrow
    //   1781: aload #8
    //   1783: invokevirtual getPackage : ()Ljava/lang/Package;
    //   1786: invokevirtual getName : ()Ljava/lang/String;
    //   1789: ifnull -> 1829
    //   1792: goto -> 1799
    //   1795: invokestatic a : (Ljava/lang/Throwable;)Ljava/lang/Throwable;
    //   1798: athrow
    //   1799: aload #8
    //   1801: invokevirtual getPackage : ()Ljava/lang/Package;
    //   1804: invokevirtual getName : ()Ljava/lang/String;
    //   1807: sipush #28149
    //   1810: sipush #-17063
    //   1813: invokestatic a : (II)Ljava/lang/String;
    //   1816: invokevirtual startsWith : (Ljava/lang/String;)Z
    //   1819: ifne -> 1829
    //   1822: goto -> 1829
    //   1825: invokestatic a : (Ljava/lang/Throwable;)Ljava/lang/Throwable;
    //   1828: athrow
    //   1829: aload #7
    //   1831: iconst_1
    //   1832: invokevirtual setAccessible : (Z)V
    //   1835: aload #7
    //   1837: aconst_null
    //   1838: invokevirtual get : (Ljava/lang/Object;)Ljava/lang/Object;
    //   1841: pop
    //   1842: iinc #6, 1
    //   1845: iload_2
    //   1846: ifne -> 1707
    //   1849: sipush #28145
    //   1852: sipush #-18627
    //   1855: invokestatic a : (II)Ljava/lang/String;
    //   1858: invokestatic forName : (Ljava/lang/String;)Ljava/lang/Class;
    //   1861: invokevirtual getDeclaredMethods : ()[Ljava/lang/reflect/Method;
    //   1864: astore #4
    //   1866: aload #4
    //   1868: arraylength
    //   1869: istore #5
    //   1871: iconst_0
    //   1872: istore #6
    //   1874: iload #6
    //   1876: iload #5
    //   1878: if_icmpge -> 2008
    //   1881: aload #4
    //   1883: iload #6
    //   1885: aaload
    //   1886: astore #7
    //   1888: aload #7
    //   1890: invokevirtual getParameterTypes : ()[Ljava/lang/Class;
    //   1893: pop
    //   1894: aload #7
    //   1896: invokevirtual getModifiers : ()I
    //   1899: invokestatic isStatic : (I)Z
    //   1902: ifeq -> 1994
    //   1905: aload #7
    //   1907: invokevirtual getParameterTypes : ()[Ljava/lang/Class;
    //   1910: arraylength
    //   1911: iconst_2
    //   1912: if_icmpne -> 1994
    //   1915: goto -> 1922
    //   1918: invokestatic a : (Ljava/lang/Throwable;)Ljava/lang/Throwable;
    //   1921: athrow
    //   1922: aload #7
    //   1924: invokevirtual getReturnType : ()Ljava/lang/Class;
    //   1927: getstatic java/lang/Boolean.TYPE : Ljava/lang/Class;
    //   1930: if_acmpne -> 1994
    //   1933: goto -> 1940
    //   1936: invokestatic a : (Ljava/lang/Throwable;)Ljava/lang/Throwable;
    //   1939: athrow
    //   1940: aload #7
    //   1942: iconst_1
    //   1943: invokevirtual setAccessible : (Z)V
    //   1946: aload #7
    //   1948: aconst_null
    //   1949: iconst_2
    //   1950: anewarray java/lang/Object
    //   1953: dup
    //   1954: iconst_0
    //   1955: aload_0
    //   1956: aastore
    //   1957: dup
    //   1958: iconst_1
    //   1959: aload_1
    //   1960: ifnonnull -> 1978
    //   1963: goto -> 1970
    //   1966: invokestatic a : (Ljava/lang/Throwable;)Ljava/lang/Throwable;
    //   1969: athrow
    //   1970: aload_1
    //   1971: goto -> 1985
    //   1974: invokestatic a : (Ljava/lang/Throwable;)Ljava/lang/Throwable;
    //   1977: athrow
    //   1978: aload_1
    //   1979: checkcast [B
    //   1982: invokevirtual clone : ()Ljava/lang/Object;
    //   1985: aastore
    //   1986: invokevirtual invoke : (Ljava/lang/Object;[Ljava/lang/Object;)Ljava/lang/Object;
    //   1989: pop
    //   1990: iload_2
    //   1991: ifne -> 2008
    //   1994: iinc #6, 1
    //   1997: iload_2
    //   1998: ifne -> 1874
    //   2001: goto -> 2008
    //   2004: invokestatic a : (Ljava/lang/Throwable;)Ljava/lang/Throwable;
    //   2007: athrow
    //   2008: sipush #28148
    //   2011: sipush #21218
    //   2014: invokestatic a : (II)Ljava/lang/String;
    //   2017: iconst_1
    //   2018: ldc burp/Zgt7
    //   2020: invokevirtual getClassLoader : ()Ljava/lang/ClassLoader;
    //   2023: invokestatic forName : (Ljava/lang/String;ZLjava/lang/ClassLoader;)Ljava/lang/Class;
    //   2026: invokevirtual getDeclaredFields : ()[Ljava/lang/reflect/Field;
    //   2029: astore #4
    //   2031: aload #4
    //   2033: arraylength
    //   2034: istore #5
    //   2036: iconst_0
    //   2037: istore #6
    //   2039: iload #6
    //   2041: iload #5
    //   2043: if_icmpge -> 2181
    //   2046: aload #4
    //   2048: iload #6
    //   2050: aaload
    //   2051: astore #7
    //   2053: aload #7
    //   2055: invokevirtual getModifiers : ()I
    //   2058: invokestatic isStatic : (I)Z
    //   2061: ifne -> 2071
    //   2064: goto -> 2174
    //   2067: invokestatic a : (Ljava/lang/Throwable;)Ljava/lang/Throwable;
    //   2070: athrow
    //   2071: aload #7
    //   2073: invokevirtual getType : ()Ljava/lang/Class;
    //   2076: astore #8
    //   2078: aload #8
    //   2080: ifnull -> 2161
    //   2083: aload #8
    //   2085: invokevirtual isPrimitive : ()Z
    //   2088: ifne -> 2161
    //   2091: goto -> 2098
    //   2094: invokestatic a : (Ljava/lang/Throwable;)Ljava/lang/Throwable;
    //   2097: athrow
    //   2098: aload #8
    //   2100: invokevirtual getPackage : ()Ljava/lang/Package;
    //   2103: ifnull -> 2161
    //   2106: goto -> 2113
    //   2109: invokestatic a : (Ljava/lang/Throwable;)Ljava/lang/Throwable;
    //   2112: athrow
    //   2113: aload #8
    //   2115: invokevirtual getPackage : ()Ljava/lang/Package;
    //   2118: invokevirtual getName : ()Ljava/lang/String;
    //   2121: ifnull -> 2161
    //   2124: goto -> 2131
    //   2127: invokestatic a : (Ljava/lang/Throwable;)Ljava/lang/Throwable;
    //   2130: athrow
    //   2131: aload #8
    //   2133: invokevirtual getPackage : ()Ljava/lang/Package;
    //   2136: invokevirtual getName : ()Ljava/lang/String;
    //   2139: sipush #28149
    //   2142: sipush #-17063
    //   2145: invokestatic a : (II)Ljava/lang/String;
    //   2148: invokevirtual startsWith : (Ljava/lang/String;)Z
    //   2151: ifne -> 2161
    //   2154: goto -> 2161
    //   2157: invokestatic a : (Ljava/lang/Throwable;)Ljava/lang/Throwable;
    //   2160: athrow
    //   2161: aload #7
    //   2163: iconst_1
    //   2164: invokevirtual setAccessible : (Z)V
    //   2167: aload #7
    //   2169: aconst_null
    //   2170: invokevirtual get : (Ljava/lang/Object;)Ljava/lang/Object;
    //   2173: pop
    //   2174: iinc #6, 1
    //   2177: iload_2
    //   2178: ifne -> 2039
    //   2181: sipush #28159
    //   2184: sipush #23297
    //   2187: invokestatic a : (II)Ljava/lang/String;
    //   2190: invokestatic forName : (Ljava/lang/String;)Ljava/lang/Class;
    //   2193: invokevirtual getDeclaredMethods : ()[Ljava/lang/reflect/Method;
    //   2196: astore #4
    //   2198: aload #4
    //   2200: arraylength
    //   2201: istore #5
    //   2203: iconst_0
    //   2204: istore #6
    //   2206: iload #6
    //   2208: iload #5
    //   2210: if_icmpge -> 2343
    //   2213: aload #4
    //   2215: iload #6
    //   2217: aaload
    //   2218: astore #7
    //   2220: aload #7
    //   2222: invokevirtual getParameterTypes : ()[Ljava/lang/Class;
    //   2225: pop
    //   2226: aload #7
    //   2228: invokevirtual getModifiers : ()I
    //   2231: invokestatic isStatic : (I)Z
    //   2234: ifeq -> 2329
    //   2237: aload #7
    //   2239: invokevirtual getParameterTypes : ()[Ljava/lang/Class;
    //   2242: arraylength
    //   2243: iconst_2
    //   2244: if_icmpne -> 2329
    //   2247: goto -> 2254
    //   2250: invokestatic a : (Ljava/lang/Throwable;)Ljava/lang/Throwable;
    //   2253: athrow
    //   2254: aload #7
    //   2256: invokevirtual getReturnType : ()Ljava/lang/Class;
    //   2259: getstatic java/lang/Void.TYPE : Ljava/lang/Class;
    //   2262: invokevirtual equals : (Ljava/lang/Object;)Z
    //   2265: ifeq -> 2329
    //   2268: goto -> 2275
    //   2271: invokestatic a : (Ljava/lang/Throwable;)Ljava/lang/Throwable;
    //   2274: athrow
    //   2275: aload #7
    //   2277: iconst_1
    //   2278: invokevirtual setAccessible : (Z)V
    //   2281: aload #7
    //   2283: aconst_null
    //   2284: iconst_2
    //   2285: anewarray java/lang/Object
    //   2288: dup
    //   2289: iconst_0
    //   2290: aload_0
    //   2291: aastore
    //   2292: dup
    //   2293: iconst_1
    //   2294: aload_1
    //   2295: ifnonnull -> 2313
    //   2298: goto -> 2305
    //   2301: invokestatic a : (Ljava/lang/Throwable;)Ljava/lang/Throwable;
    //   2304: athrow
    //   2305: aload_1
    //   2306: goto -> 2320
    //   2309: invokestatic a : (Ljava/lang/Throwable;)Ljava/lang/Throwable;
    //   2312: athrow
    //   2313: aload_1
    //   2314: checkcast [B
    //   2317: invokevirtual clone : ()Ljava/lang/Object;
    //   2320: aastore
    //   2321: invokevirtual invoke : (Ljava/lang/Object;[Ljava/lang/Object;)Ljava/lang/Object;
    //   2324: pop
    //   2325: iload_2
    //   2326: ifne -> 2343
    //   2329: iinc #6, 1
    //   2332: iload_2
    //   2333: ifne -> 2206
    //   2336: goto -> 2343
    //   2339: invokestatic a : (Ljava/lang/Throwable;)Ljava/lang/Throwable;
    //   2342: athrow
    //   2343: getstatic burp/Zss8.ZD : Ljava/lang/String;
    //   2346: getstatic burp/Zmh0.Zt : Ljava/lang/Object;
    //   2349: checkcast java/math/BigInteger
    //   2352: invokevirtual intValue : ()I
    //   2355: bipush #32
    //   2357: irem
    //   2358: invokestatic abs : (I)I
    //   2361: invokevirtual charAt : (I)C
    //   2364: getstatic burp/Zgb9.Zk : Ljava/lang/String;
    //   2367: getstatic burp/Zz3k.Zz : Ljava/lang/Object;
    //   2370: checkcast java/math/BigInteger
    //   2373: invokevirtual intValue : ()I
    //   2376: bipush #32
    //   2378: irem
    //   2379: invokestatic abs : (I)I
    //   2382: invokevirtual charAt : (I)C
    //   2385: if_icmpgt -> 2492
    //   2388: getstatic burp/Zz35.ZH : Ljava/lang/String;
    //   2391: getstatic burp/Zk7b.ZR : Ljava/lang/Object;
    //   2394: checkcast java/math/BigInteger
    //   2397: invokevirtual intValue : ()I
    //   2400: bipush #32
    //   2402: irem
    //   2403: invokestatic abs : (I)I
    //   2406: invokevirtual charAt : (I)C
    //   2409: getstatic burp/Zrod.ZQ : Ljava/lang/String;
    //   2412: getstatic burp/Ztq2.Zj : Ljava/lang/Object;
    //   2415: checkcast java/math/BigInteger
    //   2418: invokevirtual intValue : ()I
    //   2421: bipush #32
    //   2423: irem
    //   2424: invokestatic abs : (I)I
    //   2427: invokevirtual charAt : (I)C
    //   2430: if_icmple -> 2492
    //   2433: goto -> 2440
    //   2436: invokestatic a : (Ljava/lang/Throwable;)Ljava/lang/Throwable;
    //   2439: athrow
    //   2440: getstatic burp/Zllw.Zg : Ljava/lang/String;
    //   2443: getstatic burp/Zsxj.Zi : Ljava/lang/Object;
    //   2446: checkcast java/math/BigInteger
    //   2449: invokevirtual intValue : ()I
    //   2452: bipush #32
    //   2454: irem
    //   2455: invokestatic abs : (I)I
    //   2458: invokevirtual charAt : (I)C
    //   2461: getstatic burp/Zg8v.Zd : Ljava/lang/String;
    //   2464: getstatic burp/Ztvp.Zy : Ljava/lang/Object;
    //   2467: checkcast java/math/BigInteger
    //   2470: invokevirtual intValue : ()I
    //   2473: bipush #32
    //   2475: irem
    //   2476: invokestatic abs : (I)I
    //   2479: invokevirtual charAt : (I)C
    //   2482: if_icmple -> 2500
    //   2485: goto -> 2492
    //   2488: invokestatic a : (Ljava/lang/Throwable;)Ljava/lang/Throwable;
    //   2491: athrow
    //   2492: iconst_1
    //   2493: goto -> 2501
    //   2496: invokestatic a : (Ljava/lang/Throwable;)Ljava/lang/Throwable;
    //   2499: athrow
    //   2500: iconst_0
    //   2501: ireturn
    //   2502: astore_3
    //   2503: new java/lang/Exception
    //   2506: dup
    //   2507: aload_3
    //   2508: invokevirtual getMessage : ()Ljava/lang/String;
    //   2511: invokespecial <init> : (Ljava/lang/String;)V
    //   2514: athrow
    // Exception table:
    //   from	to	target	type
    //   4	2501	2502	java/lang/Throwable
    //   22	198	201	java/lang/Throwable
    //   168	235	238	java/lang/Throwable
    //   205	272	275	java/lang/Throwable
    //   242	309	312	java/lang/Throwable
    //   279	346	349	java/lang/Throwable
    //   316	383	386	java/lang/Throwable
    //   353	420	423	java/lang/Throwable
    //   390	457	460	java/lang/Throwable
    //   427	494	497	java/lang/Throwable
    //   464	531	534	java/lang/Throwable
    //   501	568	571	java/lang/Throwable
    //   538	605	608	java/lang/Throwable
    //   575	642	645	java/lang/Throwable
    //   612	679	682	java/lang/Throwable
    //   649	716	719	java/lang/Throwable
    //   686	753	756	java/lang/Throwable
    //   723	790	793	java/lang/Throwable
    //   760	827	830	java/lang/Throwable
    //   797	864	867	java/lang/Throwable
    //   834	901	904	java/lang/Throwable
    //   871	938	941	java/lang/Throwable
    //   908	975	978	java/lang/Throwable
    //   945	1012	1015	java/lang/Throwable
    //   982	1049	1052	java/lang/Throwable
    //   1019	1086	1089	java/lang/Throwable
    //   1056	1123	1126	java/lang/Throwable
    //   1093	1160	1163	java/lang/Throwable
    //   1130	1197	1200	java/lang/Throwable
    //   1167	1234	1237	java/lang/Throwable
    //   1204	1271	1274	java/lang/Throwable
    //   1241	1308	1311	java/lang/Throwable
    //   1278	1341	1344	java/lang/Throwable
    //   1407	1421	1421	java/lang/Throwable
    //   1432	1445	1448	java/lang/Throwable
    //   1437	1460	1463	java/lang/Throwable
    //   1452	1478	1481	java/lang/Throwable
    //   1467	1508	1511	java/lang/Throwable
    //   1574	1601	1604	java/lang/Throwable
    //   1591	1619	1622	java/lang/Throwable
    //   1608	1655	1658	java/lang/Throwable
    //   1626	1669	1672	java/lang/Throwable
    //   1721	1735	1735	java/lang/Throwable
    //   1746	1759	1762	java/lang/Throwable
    //   1751	1774	1777	java/lang/Throwable
    //   1766	1792	1795	java/lang/Throwable
    //   1781	1822	1825	java/lang/Throwable
    //   1888	1915	1918	java/lang/Throwable
    //   1905	1933	1936	java/lang/Throwable
    //   1922	1963	1966	java/lang/Throwable
    //   1940	1974	1974	java/lang/Throwable
    //   1985	2001	2004	java/lang/Throwable
    //   2053	2067	2067	java/lang/Throwable
    //   2078	2091	2094	java/lang/Throwable
    //   2083	2106	2109	java/lang/Throwable
    //   2098	2124	2127	java/lang/Throwable
    //   2113	2154	2157	java/lang/Throwable
    //   2220	2247	2250	java/lang/Throwable
    //   2237	2268	2271	java/lang/Throwable
    //   2254	2298	2301	java/lang/Throwable
    //   2275	2309	2309	java/lang/Throwable
    //   2320	2336	2339	java/lang/Throwable
    //   2343	2433	2436	java/lang/Throwable
    //   2388	2485	2488	java/lang/Throwable
    //   2440	2496	2496	java/lang/Throwable
  }
  
  static void Zt(Object paramObject) {
    Zrs0.Zt = a(28147, 13295);
    Zrs0.Zz = new BigInteger(a(28157, -7618));
    boolean bool = Zt2e.ZK();
    try {
      try {
        if (Zgw_.ZH.charAt(Math.abs(((BigInteger)Zx_x.Zi).intValue() % 32)) <= Zrod.ZQ.charAt(Math.abs(((BigInteger)Zro5.ZT).intValue() % 32))) {
          try {
            Zlr2.Z_(Class.forName(a(28151, 9498)));
            if (bool)
              Zsbd.Zj(Class.forName(a(28156, 8018))); 
          } catch (Throwable throwable) {
            throw a(null);
          } 
          return;
        } 
      } catch (Throwable throwable) {
        throw a(null);
      } 
      Zsbd.Zj(Class.forName(a(28156, 8018)));
    } catch (Throwable throwable) {}
  }
  
  static void ZP(Object[] paramArrayOfObject, Object paramObject) throws Throwable {}
  
  static {
    // Byte code:
    //   0: bipush #13
    //   2: anewarray java/lang/String
    //   5: astore #5
    //   7: iconst_0
    //   8: istore_3
    //   9: ldc '1Â Ã´Ã•Ã’ÂŒYjZÃ«VÂ¯\\tÃ‰PÃ«Ã‹1O/Ã‚\\tÂ vÃ†Â”Ã—ÂŒ[G\\tÃ MÃŽhÂ•;Â»Â™P\\tÂ²)Â„Ã¤ÃœÂªÂ‹Ã¯v Ã¸ÃˆÃ‘HÃ¢ÃˆÂ¼Â¡ÂŒÂ®3Â¿]Â·ÃŒÃ¼RÂ³[NÂÃœÂƒ;Ã² ÂˆÃ¹Â·Ã»Ã“Â½Â³QÂ€)Ã’Âª;&Â”[ÂœÃ ÂŸÃ´_)Ã³Ã¯Â”Â±hÃ›Â·\\tk}Â¿nÂ»Ã»`ÃƒÃ·LÃ£Â²QÃº{ÂŠÃ“jRE}Ã´F\\tjÃºY)ÃÂ«Ã±YÃ§xÃ‰{Â•ÃÃºÂ«Ã¬Ã©3jÃ…Ã›Â‚Ã¬KÃ¾FÂ’Ã”BÃ0\\fÃ‡Ã£rgdÃ‚Â…ebÃ¼ÂœÃ²Ã´ÂŽÃ³ÂŠW7Â‡Â–Ã„ÃŠ7Â‹''
    //   11: dup
    //   12: astore_2
    //   13: invokevirtual length : ()I
    //   16: istore #4
    //   18: bipush #9
    //   20: istore_1
    //   21: iconst_m1
    //   22: istore_0
    //   23: bipush #97
    //   25: iinc #0, 1
    //   28: aload_2
    //   29: iload_0
    //   30: dup
    //   31: iload_1
    //   32: iadd
    //   33: invokevirtual substring : (II)Ljava/lang/String;
    //   36: iconst_m1
    //   37: goto -> 143
    //   40: aload #5
    //   42: swap
    //   43: iload_3
    //   44: iinc #3, 1
    //   47: swap
    //   48: aastore
    //   49: iload_0
    //   50: iload_1
    //   51: iadd
    //   52: dup
    //   53: istore_0
    //   54: iload #4
    //   56: if_icmpge -> 68
    //   59: aload_2
    //   60: iload_0
    //   61: invokevirtual charAt : (I)C
    //   64: istore_1
    //   65: goto -> 23
    //   68: ldc 'ÃŽEÂ˜ÃºÃŒÃºfÃ–\\tÃ­Ã´Ã¼ÃŒ@<ÂšÂ¢Ãª'
    //   70: dup
    //   71: astore_2
    //   72: invokevirtual length : ()I
    //   75: istore #4
    //   77: bipush #9
    //   79: istore_1
    //   80: iconst_m1
    //   81: istore_0
    //   82: bipush #84
    //   84: iinc #0, 1
    //   87: aload_2
    //   88: iload_0
    //   89: dup
    //   90: iload_1
    //   91: iadd
    //   92: invokevirtual substring : (II)Ljava/lang/String;
    //   95: iconst_0
    //   96: goto -> 143
    //   99: aload #5
    //   101: swap
    //   102: iload_3
    //   103: iinc #3, 1
    //   106: swap
    //   107: aastore
    //   108: iload_0
    //   109: iload_1
    //   110: iadd
    //   111: dup
    //   112: istore_0
    //   113: iload #4
    //   115: if_icmpge -> 127
    //   118: aload_2
    //   119: iload_0
    //   120: invokevirtual charAt : (I)C
    //   123: istore_1
    //   124: goto -> 82
    //   127: aload #5
    //   129: putstatic burp/Zr5k.a : [Ljava/lang/String;
    //   132: bipush #13
    //   134: anewarray java/lang/String
    //   137: putstatic burp/Zr5k.b : [Ljava/lang/String;
    //   140: goto -> 300
    //   143: dup_x2
    //   144: pop
    //   145: invokevirtual toCharArray : ()[C
    //   148: dup_x1
    //   149: arraylength
    //   150: dup_x2
    //   151: pop
    //   152: iconst_0
    //   153: istore #6
    //   155: dup2_x1
    //   156: pop2
    //   157: dup_x2
    //   158: iconst_1
    //   159: if_icmpgt -> 260
    //   162: dup2
    //   163: swap
    //   164: iload #6
    //   166: dup2_x1
    //   167: caload
    //   168: swap
    //   169: iload #6
    //   171: bipush #7
    //   173: irem
    //   174: tableswitch default -> 242, 0 -> 212, 1 -> 217, 2 -> 222, 3 -> 227, 4 -> 232, 5 -> 237
    //   212: bipush #85
    //   214: goto -> 244
    //   217: bipush #99
    //   219: goto -> 244
    //   222: bipush #105
    //   224: goto -> 244
    //   227: bipush #75
    //   229: goto -> 244
    //   232: bipush #62
    //   234: goto -> 244
    //   237: bipush #54
    //   239: goto -> 244
    //   242: bipush #26
    //   244: ixor
    //   245: ixor
    //   246: i2c
    //   247: castore
    //   248: iinc #6, 1
    //   251: dup
    //   252: ifne -> 260
    //   255: dup2
    //   256: dup_x1
    //   257: goto -> 166
    //   260: dup2_x1
    //   261: pop2
    //   262: dup_x2
    //   263: iload #6
    //   265: if_icmpgt -> 162
    //   268: pop
    //   269: new java/lang/String
    //   272: dup_x1
    //   273: swap
    //   274: invokespecial <init> : ([C)V
    //   277: invokevirtual intern : ()Ljava/lang/String;
    //   280: swap
    //   281: pop
    //   282: swap
    //   283: tableswitch default -> 40, 0 -> 99
    //   300: new java/math/BigInteger
    //   303: dup
    //   304: bipush #32
    //   306: newarray byte
    //   308: dup
    //   309: iconst_0
    //   310: iconst_1
    //   311: bastore
    //   312: dup
    //   313: iconst_1
    //   314: bipush #-81
    //   316: bastore
    //   317: dup
    //   318: iconst_2
    //   319: bipush #-3
    //   321: bastore
    //   322: dup
    //   323: iconst_3
    //   324: bipush #59
    //   326: bastore
    //   327: dup
    //   328: iconst_4
    //   329: bipush #-53
    //   331: bastore
    //   332: dup
    //   333: iconst_5
    //   334: bipush #25
    //   336: bastore
    //   337: dup
    //   338: bipush #6
    //   340: bipush #-19
    //   342: bastore
    //   343: dup
    //   344: bipush #7
    //   346: bipush #-85
    //   348: bastore
    //   349: dup
    //   350: bipush #8
    //   352: bipush #9
    //   354: bastore
    //   355: dup
    //   356: bipush #9
    //   358: bipush #-65
    //   360: bastore
    //   361: dup
    //   362: bipush #10
    //   364: bipush #-80
    //   366: bastore
    //   367: dup
    //   368: bipush #11
    //   370: bipush #77
    //   372: bastore
    //   373: dup
    //   374: bipush #12
    //   376: bipush #-117
    //   378: bastore
    //   379: dup
    //   380: bipush #13
    //   382: bipush #-86
    //   384: bastore
    //   385: dup
    //   386: bipush #14
    //   388: bipush #99
    //   390: bastore
    //   391: dup
    //   392: bipush #15
    //   394: bipush #-46
    //   396: bastore
    //   397: dup
    //   398: bipush #16
    //   400: bipush #-65
    //   402: bastore
    //   403: dup
    //   404: bipush #17
    //   406: bipush #86
    //   408: bastore
    //   409: dup
    //   410: bipush #18
    //   412: bipush #-120
    //   414: bastore
    //   415: dup
    //   416: bipush #19
    //   418: bipush #9
    //   420: bastore
    //   421: dup
    //   422: bipush #20
    //   424: iconst_2
    //   425: bastore
    //   426: dup
    //   427: bipush #21
    //   429: bipush #80
    //   431: bastore
    //   432: dup
    //   433: bipush #22
    //   435: bipush #-36
    //   437: bastore
    //   438: dup
    //   439: bipush #23
    //   441: bipush #82
    //   443: bastore
    //   444: dup
    //   445: bipush #24
    //   447: bipush #28
    //   449: bastore
    //   450: dup
    //   451: bipush #25
    //   453: bipush #121
    //   455: bastore
    //   456: dup
    //   457: bipush #26
    //   459: bipush #111
    //   461: bastore
    //   462: dup
    //   463: bipush #27
    //   465: bipush #45
    //   467: bastore
    //   468: dup
    //   469: bipush #28
    //   471: bipush #-28
    //   473: bastore
    //   474: dup
    //   475: bipush #29
    //   477: bipush #-14
    //   479: bastore
    //   480: dup
    //   481: bipush #30
    //   483: bipush #118
    //   485: bastore
    //   486: dup
    //   487: bipush #31
    //   489: bipush #48
    //   491: bastore
    //   492: invokespecial <init> : ([B)V
    //   495: putstatic burp/Zr5k.Zj : Ljava/lang/Object;
    //   498: sipush #28146
    //   501: sipush #24757
    //   504: invokestatic a : (II)Ljava/lang/String;
    //   507: putstatic burp/Zr5k.Zq : Ljava/lang/String;
    //   510: return
  }
  
  private static Throwable a(Throwable paramThrowable) {
    return paramThrowable;
  }
  
  private static String a(int paramInt1, int paramInt2) {
    int i = (paramInt1 ^ 0x6DF4) & 0xFFFF;
    if (b[i] == null) {
      char[] arrayOfChar = a[i].toCharArray();
      switch (arrayOfChar[0] & 0xFF) {
        case 0:
        
        case 1:
        
        case 2:
        
        case 3:
        
        case 4:
        
        case 5:
        
        case 6:
        
        case 7:
        
        case 8:
        
        case 9:
        
        case 10:
        
        case 11:
        
        case 12:
        
        case 13:
        
        case 14:
        
        case 15:
        
        case 16:
        
        case 17:
        
        case 18:
        
        case 19:
        
        case 20:
        
        case 21:
        
        case 22:
        
        case 23:
        
        case 24:
        
        case 25:
        
        case 26:
        
        case 27:
        
        case 28:
        
        case 29:
        
        case 30:
        
        case 31:
        
        case 32:
        
        case 33:
        
        case 34:
        
        case 35:
        
        case 36:
        
        case 37:
        
        case 38:
        
        case 39:
        
        case 40:
        
        case 41:
        
        case 42:
        
        case 43:
        
        case 44:
        
        case 45:
        
        case 46:
        
        case 47:
        
        case 48:
        
        case 49:
        
        case 50:
        
        case 51:
        
        case 52:
        
        case 53:
        
        case 54:
        
        case 55:
        
        case 56:
        
        case 57:
        
        case 58:
        
        case 59:
        
        case 60:
        
        case 61:
        
        case 62:
        
        case 63:
        
        case 64:
        
        case 65:
        
        case 66:
        
        case 67:
        
        case 68:
        
        case 69:
        
        case 70:
        
        case 71:
        
        case 72:
        
        case 73:
        
        case 74:
        
        case 75:
        
        case 76:
        
        case 77:
        
        case 78:
        
        case 79:
        
        case 80:
        
        case 81:
        
        case 82:
        
        case 83:
        
        case 84:
        
        case 85:
        
        case 86:
        
        case 87:
        
        case 88:
        
        case 89:
        
        case 90:
        
        case 91:
        
        case 92:
        
        case 93:
        
        case 94:
        
        case 95:
        
        case 96:
        
        case 97:
        
        case 98:
        
        case 99:
        
        case 100:
        
        case 101:
        
        case 102:
        
        case 103:
        
        case 104:
        
        case 105:
        
        case 106:
        
        case 107:
        
        case 108:
        
        case 109:
        
        case 110:
        
        case 111:
        
        case 112:
        
        case 113:
        
        case 114:
        
        case 115:
        
        case 116:
        
        case 117:
        
        case 118:
        
        case 119:
        
        case 120:
        
        case 121:
        
        case 122:
        
        case 123:
        
        case 124:
        
        case 125:
        
        case 126:
        
        case 127:
        
        case 128:
        
        case 129:
        
        case 130:
        
        case 131:
        
        case 132:
        
        case 133:
        
        case 134:
        
        case 135:
        
        case 136:
        
        case 137:
        
        case 138:
        
        case 139:
        
        case 140:
        
        case 141:
        
        case 142:
        
        case 143:
        
        case 144:
        
        case 145:
        
        case 146:
        
        case 147:
        
        case 148:
        
        case 149:
        
        case 150:
        
        case 151:
        
        case 152:
        
        case 153:
        
        case 154:
        
        case 155:
        
        case 156:
        
        case 157:
        
        case 158:
        
        case 159:
        
        case 160:
        
        case 161:
        
        case 162:
        
        case 163:
        
        case 164:
        
        case 165:
        
        case 166:
        
        case 167:
        
        case 168:
        
        case 169:
        
        case 170:
        
        case 171:
        
        case 172:
        
        case 173:
        
        case 174:
        
        case 175:
        
        case 176:
        
        case 177:
        
        case 178:
        
        case 179:
        
        case 180:
        
        case 181:
        
        case 182:
        
        case 183:
        
        case 184:
        
        case 185:
        
        case 186:
        
        case 187:
        
        case 188:
        
        case 189:
        
        case 190:
        
        case 191:
        
        case 192:
        
        case 193:
        
        case 194:
        
        case 195:
        
        case 196:
        
        case 197:
        
        case 198:
        
        case 199:
        
        case 200:
        
        case 201:
        
        case 202:
        
        case 203:
        
        case 204:
        
        case 205:
        
        case 206:
        
        case 207:
        
        case 208:
        
        case 209:
        
        case 210:
        
        case 211:
        
        case 212:
        
        case 213:
        
        case 214:
        
        case 215:
        
        case 216:
        
        case 217:
        
        case 218:
        
        case 219:
        
        case 220:
        
        case 221:
        
        case 222:
        
        case 223:
        
        case 224:
        
        case 225:
        
        case 226:
        
        case 227:
        
        case 228:
        
        case 229:
        
        case 230:
        
        case 231:
        
        case 232:
        
        case 233:
        
        case 234:
        
        case 235:
        
        case 236:
        
        case 237:
        
        case 238:
        
        case 239:
        
        case 240:
        
        case 241:
        
        case 242:
        
        case 243:
        
        case 244:
        
        case 245:
        
        case 246:
        
        case 247:
        
        case 248:
        
        case 249:
        
        case 250:
        
        case 251:
        
        case 252:
        
        case 253:
        
        case 254:
        
        default:
          break;
      } 
      byte b1 = 88;
      int j = (paramInt2 & 0xFF) - b1;
      if (j < 0)
        j += 256; 
      int k = ((paramInt2 & 0xFFFF) >>> 8) - b1;
      if (k < 0)
        k += 256; 
      for (byte b2 = 0; b2 < arrayOfChar.length; b2++) {
        int m = b2 % 2;
        if (m == 0) {
          arrayOfChar[b2] = (char)(arrayOfChar[b2] ^ j);
          j = ((j >>> 3 | j << 5) ^ arrayOfChar[b2]) & 0xFF;
        } else {
          arrayOfChar[b2] = (char)(arrayOfChar[b2] ^ k);
          k = ((k >>> 3 | k << 5) ^ arrayOfChar[b2]) & 0xFF;
        } 
      } 
      b[i] = (new String(arrayOfChar)).intern();
    } 
    return b[i];
  }
}


/* Location:              C:\Program Files\BurpSuitePro\burpsuite_pro.jar!\burp\Zr5k.class
 * Java compiler version: 21 (65.0)
 * JD-Core Version:       1.1.3
 */