package burp;

import java.math.BigInteger;

class Zr60 extends ClassLoader {
  static Object Ze;
  
  static String ZQ;
  
  private static final String[] a;
  
  private static final String[] b;
  
  static boolean ZM(Object[] paramArrayOfObject, Object paramObject) throws Throwable {
    // Byte code:
    //   0: invokestatic ZK : ()Z
    //   3: istore_2
    //   4: new java/lang/StringBuilder
    //   7: dup
    //   8: invokespecial <init> : ()V
    //   11: astore_3
    //   12: iconst_0
    //   13: istore #4
    //   15: iload #4
    //   17: bipush #32
    //   19: if_icmpge -> 1355
    //   22: iload #4
    //   24: tableswitch default -> 1348, 0 -> 168, 1 -> 205, 2 -> 242, 3 -> 279, 4 -> 316, 5 -> 353, 6 -> 390, 7 -> 427, 8 -> 464, 9 -> 501, 10 -> 538, 11 -> 575, 12 -> 612, 13 -> 649, 14 -> 686, 15 -> 723, 16 -> 760, 17 -> 797, 18 -> 834, 19 -> 871, 20 -> 908, 21 -> 945, 22 -> 982, 23 -> 1019, 24 -> 1056, 25 -> 1093, 26 -> 1130, 27 -> 1167, 28 -> 1204, 29 -> 1241, 30 -> 1278, 31 -> 1315
    //   168: aload_3
    //   169: getstatic burp/Zti7.Zc : Ljava/lang/String;
    //   172: getstatic burp/Zt7x.ZE : Ljava/lang/Object;
    //   175: checkcast java/math/BigInteger
    //   178: invokevirtual intValue : ()I
    //   181: bipush #32
    //   183: irem
    //   184: invokestatic abs : (I)I
    //   187: invokevirtual charAt : (I)C
    //   190: invokevirtual append : (C)Ljava/lang/StringBuilder;
    //   193: pop
    //   194: iload_2
    //   195: ifeq -> 1348
    //   198: goto -> 205
    //   201: invokestatic a : (Ljava/lang/Throwable;)Ljava/lang/Throwable;
    //   204: athrow
    //   205: aload_3
    //   206: getstatic burp/Zmt_.ZH : Ljava/lang/String;
    //   209: getstatic burp/Zm83.Zl : Ljava/lang/Object;
    //   212: checkcast java/math/BigInteger
    //   215: invokevirtual intValue : ()I
    //   218: bipush #32
    //   220: irem
    //   221: invokestatic abs : (I)I
    //   224: invokevirtual charAt : (I)C
    //   227: invokevirtual append : (C)Ljava/lang/StringBuilder;
    //   230: pop
    //   231: iload_2
    //   232: ifeq -> 1348
    //   235: goto -> 242
    //   238: invokestatic a : (Ljava/lang/Throwable;)Ljava/lang/Throwable;
    //   241: athrow
    //   242: aload_3
    //   243: getstatic burp/Zeub.ZT : Ljava/lang/String;
    //   246: getstatic burp/Zb3l.Zl : Ljava/lang/Object;
    //   249: checkcast java/math/BigInteger
    //   252: invokevirtual intValue : ()I
    //   255: bipush #32
    //   257: irem
    //   258: invokestatic abs : (I)I
    //   261: invokevirtual charAt : (I)C
    //   264: invokevirtual append : (C)Ljava/lang/StringBuilder;
    //   267: pop
    //   268: iload_2
    //   269: ifeq -> 1348
    //   272: goto -> 279
    //   275: invokestatic a : (Ljava/lang/Throwable;)Ljava/lang/Throwable;
    //   278: athrow
    //   279: aload_3
    //   280: getstatic burp/Zt85.ZR : Ljava/lang/String;
    //   283: getstatic burp/Zx4u.Zn : Ljava/lang/Object;
    //   286: checkcast java/math/BigInteger
    //   289: invokevirtual intValue : ()I
    //   292: bipush #32
    //   294: irem
    //   295: invokestatic abs : (I)I
    //   298: invokevirtual charAt : (I)C
    //   301: invokevirtual append : (C)Ljava/lang/StringBuilder;
    //   304: pop
    //   305: iload_2
    //   306: ifeq -> 1348
    //   309: goto -> 316
    //   312: invokestatic a : (Ljava/lang/Throwable;)Ljava/lang/Throwable;
    //   315: athrow
    //   316: aload_3
    //   317: getstatic burp/Zej8.ZP : Ljava/lang/String;
    //   320: getstatic burp/Zb2n.ZR : Ljava/lang/Object;
    //   323: checkcast java/math/BigInteger
    //   326: invokevirtual intValue : ()I
    //   329: bipush #32
    //   331: irem
    //   332: invokestatic abs : (I)I
    //   335: invokevirtual charAt : (I)C
    //   338: invokevirtual append : (C)Ljava/lang/StringBuilder;
    //   341: pop
    //   342: iload_2
    //   343: ifeq -> 1348
    //   346: goto -> 353
    //   349: invokestatic a : (Ljava/lang/Throwable;)Ljava/lang/Throwable;
    //   352: athrow
    //   353: aload_3
    //   354: getstatic burp/Zry1.Zk : Ljava/lang/String;
    //   357: getstatic burp/Zld5.ZX : Ljava/lang/Object;
    //   360: checkcast java/math/BigInteger
    //   363: invokevirtual intValue : ()I
    //   366: bipush #32
    //   368: irem
    //   369: invokestatic abs : (I)I
    //   372: invokevirtual charAt : (I)C
    //   375: invokevirtual append : (C)Ljava/lang/StringBuilder;
    //   378: pop
    //   379: iload_2
    //   380: ifeq -> 1348
    //   383: goto -> 390
    //   386: invokestatic a : (Ljava/lang/Throwable;)Ljava/lang/Throwable;
    //   389: athrow
    //   390: aload_3
    //   391: getstatic burp/Zbjx.ZA : Ljava/lang/String;
    //   394: getstatic burp/Zlt1.ZH : Ljava/lang/Object;
    //   397: checkcast java/math/BigInteger
    //   400: invokevirtual intValue : ()I
    //   403: bipush #32
    //   405: irem
    //   406: invokestatic abs : (I)I
    //   409: invokevirtual charAt : (I)C
    //   412: invokevirtual append : (C)Ljava/lang/StringBuilder;
    //   415: pop
    //   416: iload_2
    //   417: ifeq -> 1348
    //   420: goto -> 427
    //   423: invokestatic a : (Ljava/lang/Throwable;)Ljava/lang/Throwable;
    //   426: athrow
    //   427: aload_3
    //   428: getstatic burp/Zlw8.Zs : Ljava/lang/String;
    //   431: getstatic burp/Zv8l.ZL : Ljava/lang/Object;
    //   434: checkcast java/math/BigInteger
    //   437: invokevirtual intValue : ()I
    //   440: bipush #32
    //   442: irem
    //   443: invokestatic abs : (I)I
    //   446: invokevirtual charAt : (I)C
    //   449: invokevirtual append : (C)Ljava/lang/StringBuilder;
    //   452: pop
    //   453: iload_2
    //   454: ifeq -> 1348
    //   457: goto -> 464
    //   460: invokestatic a : (Ljava/lang/Throwable;)Ljava/lang/Throwable;
    //   463: athrow
    //   464: aload_3
    //   465: getstatic burp/Zrgo.Z_ : Ljava/lang/String;
    //   468: getstatic burp/Zegv.ZL : Ljava/lang/Object;
    //   471: checkcast java/math/BigInteger
    //   474: invokevirtual intValue : ()I
    //   477: bipush #32
    //   479: irem
    //   480: invokestatic abs : (I)I
    //   483: invokevirtual charAt : (I)C
    //   486: invokevirtual append : (C)Ljava/lang/StringBuilder;
    //   489: pop
    //   490: iload_2
    //   491: ifeq -> 1348
    //   494: goto -> 501
    //   497: invokestatic a : (Ljava/lang/Throwable;)Ljava/lang/Throwable;
    //   500: athrow
    //   501: aload_3
    //   502: getstatic burp/Zge2.ZT : Ljava/lang/String;
    //   505: getstatic burp/Zz3b.Zu : Ljava/lang/Object;
    //   508: checkcast java/math/BigInteger
    //   511: invokevirtual intValue : ()I
    //   514: bipush #32
    //   516: irem
    //   517: invokestatic abs : (I)I
    //   520: invokevirtual charAt : (I)C
    //   523: invokevirtual append : (C)Ljava/lang/StringBuilder;
    //   526: pop
    //   527: iload_2
    //   528: ifeq -> 1348
    //   531: goto -> 538
    //   534: invokestatic a : (Ljava/lang/Throwable;)Ljava/lang/Throwable;
    //   537: athrow
    //   538: aload_3
    //   539: getstatic burp/Zkjj.ZT : Ljava/lang/String;
    //   542: getstatic burp/Zrle.Zl : Ljava/lang/Object;
    //   545: checkcast java/math/BigInteger
    //   548: invokevirtual intValue : ()I
    //   551: bipush #32
    //   553: irem
    //   554: invokestatic abs : (I)I
    //   557: invokevirtual charAt : (I)C
    //   560: invokevirtual append : (C)Ljava/lang/StringBuilder;
    //   563: pop
    //   564: iload_2
    //   565: ifeq -> 1348
    //   568: goto -> 575
    //   571: invokestatic a : (Ljava/lang/Throwable;)Ljava/lang/Throwable;
    //   574: athrow
    //   575: aload_3
    //   576: getstatic burp/Zst7.Zi : Ljava/lang/String;
    //   579: getstatic burp/Zse8.Zn : Ljava/lang/Object;
    //   582: checkcast java/math/BigInteger
    //   585: invokevirtual intValue : ()I
    //   588: bipush #32
    //   590: irem
    //   591: invokestatic abs : (I)I
    //   594: invokevirtual charAt : (I)C
    //   597: invokevirtual append : (C)Ljava/lang/StringBuilder;
    //   600: pop
    //   601: iload_2
    //   602: ifeq -> 1348
    //   605: goto -> 612
    //   608: invokestatic a : (Ljava/lang/Throwable;)Ljava/lang/Throwable;
    //   611: athrow
    //   612: aload_3
    //   613: getstatic burp/Zmli.Zc : Ljava/lang/String;
    //   616: getstatic burp/Zb0q.ZK : Ljava/lang/Object;
    //   619: checkcast java/math/BigInteger
    //   622: invokevirtual intValue : ()I
    //   625: bipush #32
    //   627: irem
    //   628: invokestatic abs : (I)I
    //   631: invokevirtual charAt : (I)C
    //   634: invokevirtual append : (C)Ljava/lang/StringBuilder;
    //   637: pop
    //   638: iload_2
    //   639: ifeq -> 1348
    //   642: goto -> 649
    //   645: invokestatic a : (Ljava/lang/Throwable;)Ljava/lang/Throwable;
    //   648: athrow
    //   649: aload_3
    //   650: getstatic burp/Zti7.Zc : Ljava/lang/String;
    //   653: getstatic burp/Zlw8.ZA : Ljava/lang/Object;
    //   656: checkcast java/math/BigInteger
    //   659: invokevirtual intValue : ()I
    //   662: bipush #32
    //   664: irem
    //   665: invokestatic abs : (I)I
    //   668: invokevirtual charAt : (I)C
    //   671: invokevirtual append : (C)Ljava/lang/StringBuilder;
    //   674: pop
    //   675: iload_2
    //   676: ifeq -> 1348
    //   679: goto -> 686
    //   682: invokestatic a : (Ljava/lang/Throwable;)Ljava/lang/Throwable;
    //   685: athrow
    //   686: aload_3
    //   687: getstatic burp/Zlw8.Zs : Ljava/lang/String;
    //   690: getstatic burp/Ztle.ZP : Ljava/lang/Object;
    //   693: checkcast java/math/BigInteger
    //   696: invokevirtual intValue : ()I
    //   699: bipush #32
    //   701: irem
    //   702: invokestatic abs : (I)I
    //   705: invokevirtual charAt : (I)C
    //   708: invokevirtual append : (C)Ljava/lang/StringBuilder;
    //   711: pop
    //   712: iload_2
    //   713: ifeq -> 1348
    //   716: goto -> 723
    //   719: invokestatic a : (Ljava/lang/Throwable;)Ljava/lang/Throwable;
    //   722: athrow
    //   723: aload_3
    //   724: getstatic burp/Zzr8.ZY : Ljava/lang/String;
    //   727: getstatic burp/Zlg2.ZO : Ljava/lang/Object;
    //   730: checkcast java/math/BigInteger
    //   733: invokevirtual intValue : ()I
    //   736: bipush #32
    //   738: irem
    //   739: invokestatic abs : (I)I
    //   742: invokevirtual charAt : (I)C
    //   745: invokevirtual append : (C)Ljava/lang/StringBuilder;
    //   748: pop
    //   749: iload_2
    //   750: ifeq -> 1348
    //   753: goto -> 760
    //   756: invokestatic a : (Ljava/lang/Throwable;)Ljava/lang/Throwable;
    //   759: athrow
    //   760: aload_3
    //   761: getstatic burp/Zzyb.Zh : Ljava/lang/String;
    //   764: getstatic burp/Zm63.ZT : Ljava/lang/Object;
    //   767: checkcast java/math/BigInteger
    //   770: invokevirtual intValue : ()I
    //   773: bipush #32
    //   775: irem
    //   776: invokestatic abs : (I)I
    //   779: invokevirtual charAt : (I)C
    //   782: invokevirtual append : (C)Ljava/lang/StringBuilder;
    //   785: pop
    //   786: iload_2
    //   787: ifeq -> 1348
    //   790: goto -> 797
    //   793: invokestatic a : (Ljava/lang/Throwable;)Ljava/lang/Throwable;
    //   796: athrow
    //   797: aload_3
    //   798: getstatic burp/Zz4j.ZS : Ljava/lang/String;
    //   801: getstatic burp/Ztq4.ZA : Ljava/lang/Object;
    //   804: checkcast java/math/BigInteger
    //   807: invokevirtual intValue : ()I
    //   810: bipush #32
    //   812: irem
    //   813: invokestatic abs : (I)I
    //   816: invokevirtual charAt : (I)C
    //   819: invokevirtual append : (C)Ljava/lang/StringBuilder;
    //   822: pop
    //   823: iload_2
    //   824: ifeq -> 1348
    //   827: goto -> 834
    //   830: invokestatic a : (Ljava/lang/Throwable;)Ljava/lang/Throwable;
    //   833: athrow
    //   834: aload_3
    //   835: getstatic burp/Zmpx.ZC : Ljava/lang/String;
    //   838: getstatic burp/Zkjj.Zh : Ljava/lang/Object;
    //   841: checkcast java/math/BigInteger
    //   844: invokevirtual intValue : ()I
    //   847: bipush #32
    //   849: irem
    //   850: invokestatic abs : (I)I
    //   853: invokevirtual charAt : (I)C
    //   856: invokevirtual append : (C)Ljava/lang/StringBuilder;
    //   859: pop
    //   860: iload_2
    //   861: ifeq -> 1348
    //   864: goto -> 871
    //   867: invokestatic a : (Ljava/lang/Throwable;)Ljava/lang/Throwable;
    //   870: athrow
    //   871: aload_3
    //   872: getstatic burp/Zmdf.Zo : Ljava/lang/String;
    //   875: getstatic burp/Zso.ZA : Ljava/lang/Object;
    //   878: checkcast java/math/BigInteger
    //   881: invokevirtual intValue : ()I
    //   884: bipush #32
    //   886: irem
    //   887: invokestatic abs : (I)I
    //   890: invokevirtual charAt : (I)C
    //   893: invokevirtual append : (C)Ljava/lang/StringBuilder;
    //   896: pop
    //   897: iload_2
    //   898: ifeq -> 1348
    //   901: goto -> 908
    //   904: invokestatic a : (Ljava/lang/Throwable;)Ljava/lang/Throwable;
    //   907: athrow
    //   908: aload_3
    //   909: getstatic burp/Zsn9.Zp : Ljava/lang/String;
    //   912: getstatic burp/Zsjw.Zw : Ljava/lang/Object;
    //   915: checkcast java/math/BigInteger
    //   918: invokevirtual intValue : ()I
    //   921: bipush #32
    //   923: irem
    //   924: invokestatic abs : (I)I
    //   927: invokevirtual charAt : (I)C
    //   930: invokevirtual append : (C)Ljava/lang/StringBuilder;
    //   933: pop
    //   934: iload_2
    //   935: ifeq -> 1348
    //   938: goto -> 945
    //   941: invokestatic a : (Ljava/lang/Throwable;)Ljava/lang/Throwable;
    //   944: athrow
    //   945: aload_3
    //   946: getstatic burp/Zmh3.Zy : Ljava/lang/String;
    //   949: getstatic burp/Zrzg.ZA : Ljava/lang/Object;
    //   952: checkcast java/math/BigInteger
    //   955: invokevirtual intValue : ()I
    //   958: bipush #32
    //   960: irem
    //   961: invokestatic abs : (I)I
    //   964: invokevirtual charAt : (I)C
    //   967: invokevirtual append : (C)Ljava/lang/StringBuilder;
    //   970: pop
    //   971: iload_2
    //   972: ifeq -> 1348
    //   975: goto -> 982
    //   978: invokestatic a : (Ljava/lang/Throwable;)Ljava/lang/Throwable;
    //   981: athrow
    //   982: aload_3
    //   983: getstatic burp/Zlab.Zp : Ljava/lang/String;
    //   986: getstatic burp/Zr9u.ZX : Ljava/lang/Object;
    //   989: checkcast java/math/BigInteger
    //   992: invokevirtual intValue : ()I
    //   995: bipush #32
    //   997: irem
    //   998: invokestatic abs : (I)I
    //   1001: invokevirtual charAt : (I)C
    //   1004: invokevirtual append : (C)Ljava/lang/StringBuilder;
    //   1007: pop
    //   1008: iload_2
    //   1009: ifeq -> 1348
    //   1012: goto -> 1019
    //   1015: invokestatic a : (Ljava/lang/Throwable;)Ljava/lang/Throwable;
    //   1018: athrow
    //   1019: aload_3
    //   1020: getstatic burp/Zlf7.ZM : Ljava/lang/String;
    //   1023: getstatic burp/Zsn3.Zy : Ljava/lang/Object;
    //   1026: checkcast java/math/BigInteger
    //   1029: invokevirtual intValue : ()I
    //   1032: bipush #32
    //   1034: irem
    //   1035: invokestatic abs : (I)I
    //   1038: invokevirtual charAt : (I)C
    //   1041: invokevirtual append : (C)Ljava/lang/StringBuilder;
    //   1044: pop
    //   1045: iload_2
    //   1046: ifeq -> 1348
    //   1049: goto -> 1056
    //   1052: invokestatic a : (Ljava/lang/Throwable;)Ljava/lang/Throwable;
    //   1055: athrow
    //   1056: aload_3
    //   1057: getstatic burp/Zr60.ZQ : Ljava/lang/String;
    //   1060: getstatic burp/Zspg.ZJ : Ljava/lang/Object;
    //   1063: checkcast java/math/BigInteger
    //   1066: invokevirtual intValue : ()I
    //   1069: bipush #32
    //   1071: irem
    //   1072: invokestatic abs : (I)I
    //   1075: invokevirtual charAt : (I)C
    //   1078: invokevirtual append : (C)Ljava/lang/StringBuilder;
    //   1081: pop
    //   1082: iload_2
    //   1083: ifeq -> 1348
    //   1086: goto -> 1093
    //   1089: invokestatic a : (Ljava/lang/Throwable;)Ljava/lang/Throwable;
    //   1092: athrow
    //   1093: aload_3
    //   1094: getstatic burp/Zg6z.ZY : Ljava/lang/String;
    //   1097: getstatic burp/Zebc.Zr : Ljava/lang/Object;
    //   1100: checkcast java/math/BigInteger
    //   1103: invokevirtual intValue : ()I
    //   1106: bipush #32
    //   1108: irem
    //   1109: invokestatic abs : (I)I
    //   1112: invokevirtual charAt : (I)C
    //   1115: invokevirtual append : (C)Ljava/lang/StringBuilder;
    //   1118: pop
    //   1119: iload_2
    //   1120: ifeq -> 1348
    //   1123: goto -> 1130
    //   1126: invokestatic a : (Ljava/lang/Throwable;)Ljava/lang/Throwable;
    //   1129: athrow
    //   1130: aload_3
    //   1131: getstatic burp/Zmdf.Zo : Ljava/lang/String;
    //   1134: getstatic burp/Zz4m.Zo : Ljava/lang/Object;
    //   1137: checkcast java/math/BigInteger
    //   1140: invokevirtual intValue : ()I
    //   1143: bipush #32
    //   1145: irem
    //   1146: invokestatic abs : (I)I
    //   1149: invokevirtual charAt : (I)C
    //   1152: invokevirtual append : (C)Ljava/lang/StringBuilder;
    //   1155: pop
    //   1156: iload_2
    //   1157: ifeq -> 1348
    //   1160: goto -> 1167
    //   1163: invokestatic a : (Ljava/lang/Throwable;)Ljava/lang/Throwable;
    //   1166: athrow
    //   1167: aload_3
    //   1168: getstatic burp/Zt81.ZL : Ljava/lang/String;
    //   1171: getstatic burp/Zrov.Zk : Ljava/lang/Object;
    //   1174: checkcast java/math/BigInteger
    //   1177: invokevirtual intValue : ()I
    //   1180: bipush #32
    //   1182: irem
    //   1183: invokestatic abs : (I)I
    //   1186: invokevirtual charAt : (I)C
    //   1189: invokevirtual append : (C)Ljava/lang/StringBuilder;
    //   1192: pop
    //   1193: iload_2
    //   1194: ifeq -> 1348
    //   1197: goto -> 1204
    //   1200: invokestatic a : (Ljava/lang/Throwable;)Ljava/lang/Throwable;
    //   1203: athrow
    //   1204: aload_3
    //   1205: getstatic burp/Zelt.ZJ : Ljava/lang/String;
    //   1208: getstatic burp/Ze4g.Zz : Ljava/lang/Object;
    //   1211: checkcast java/math/BigInteger
    //   1214: invokevirtual intValue : ()I
    //   1217: bipush #32
    //   1219: irem
    //   1220: invokestatic abs : (I)I
    //   1223: invokevirtual charAt : (I)C
    //   1226: invokevirtual append : (C)Ljava/lang/StringBuilder;
    //   1229: pop
    //   1230: iload_2
    //   1231: ifeq -> 1348
    //   1234: goto -> 1241
    //   1237: invokestatic a : (Ljava/lang/Throwable;)Ljava/lang/Throwable;
    //   1240: athrow
    //   1241: aload_3
    //   1242: getstatic burp/Zxp5.ZO : Ljava/lang/String;
    //   1245: getstatic burp/Zz7m.Zh : Ljava/lang/Object;
    //   1248: checkcast java/math/BigInteger
    //   1251: invokevirtual intValue : ()I
    //   1254: bipush #32
    //   1256: irem
    //   1257: invokestatic abs : (I)I
    //   1260: invokevirtual charAt : (I)C
    //   1263: invokevirtual append : (C)Ljava/lang/StringBuilder;
    //   1266: pop
    //   1267: iload_2
    //   1268: ifeq -> 1348
    //   1271: goto -> 1278
    //   1274: invokestatic a : (Ljava/lang/Throwable;)Ljava/lang/Throwable;
    //   1277: athrow
    //   1278: aload_3
    //   1279: getstatic burp/Zg0f.Zd : Ljava/lang/String;
    //   1282: getstatic burp/Zr1t.ZP : Ljava/lang/Object;
    //   1285: checkcast java/math/BigInteger
    //   1288: invokevirtual intValue : ()I
    //   1291: bipush #32
    //   1293: irem
    //   1294: invokestatic abs : (I)I
    //   1297: invokevirtual charAt : (I)C
    //   1300: invokevirtual append : (C)Ljava/lang/StringBuilder;
    //   1303: pop
    //   1304: iload_2
    //   1305: ifeq -> 1348
    //   1308: goto -> 1315
    //   1311: invokestatic a : (Ljava/lang/Throwable;)Ljava/lang/Throwable;
    //   1314: athrow
    //   1315: aload_3
    //   1316: getstatic burp/Zsu2.Zq : Ljava/lang/String;
    //   1319: getstatic burp/Zxy6.Zd : Ljava/lang/Object;
    //   1322: checkcast java/math/BigInteger
    //   1325: invokevirtual intValue : ()I
    //   1328: bipush #32
    //   1330: irem
    //   1331: invokestatic abs : (I)I
    //   1334: invokevirtual charAt : (I)C
    //   1337: invokevirtual append : (C)Ljava/lang/StringBuilder;
    //   1340: pop
    //   1341: goto -> 1348
    //   1344: invokestatic a : (Ljava/lang/Throwable;)Ljava/lang/Throwable;
    //   1347: athrow
    //   1348: iinc #4, 1
    //   1351: iload_2
    //   1352: ifeq -> 15
    //   1355: aload_3
    //   1356: invokevirtual toString : ()Ljava/lang/String;
    //   1359: putstatic burp/Zkql.ZR : Ljava/lang/String;
    //   1362: new java/lang/StringBuilder
    //   1365: dup
    //   1366: invokespecial <init> : ()V
    //   1369: astore #4
    //   1371: iconst_0
    //   1372: istore #5
    //   1374: iload #5
    //   1376: bipush #32
    //   1378: if_icmpge -> 2743
    //   1381: iload #5
    //   1383: tableswitch default -> 2736, 0 -> 1524, 1 -> 1562, 2 -> 1600, 3 -> 1638, 4 -> 1676, 5 -> 1714, 6 -> 1752, 7 -> 1790, 8 -> 1828, 9 -> 1866, 10 -> 1904, 11 -> 1942, 12 -> 1980, 13 -> 2018, 14 -> 2056, 15 -> 2094, 16 -> 2132, 17 -> 2170, 18 -> 2208, 19 -> 2246, 20 -> 2284, 21 -> 2322, 22 -> 2360, 23 -> 2398, 24 -> 2436, 25 -> 2474, 26 -> 2512, 27 -> 2550, 28 -> 2588, 29 -> 2626, 30 -> 2664, 31 -> 2702
    //   1524: aload #4
    //   1526: getstatic burp/Zkdx.Ze : Ljava/lang/String;
    //   1529: getstatic burp/Zlid.Zx : Ljava/lang/Object;
    //   1532: checkcast java/math/BigInteger
    //   1535: invokevirtual intValue : ()I
    //   1538: bipush #32
    //   1540: irem
    //   1541: invokestatic abs : (I)I
    //   1544: invokevirtual charAt : (I)C
    //   1547: invokevirtual append : (C)Ljava/lang/StringBuilder;
    //   1550: pop
    //   1551: iload_2
    //   1552: ifeq -> 2736
    //   1555: goto -> 1562
    //   1558: invokestatic a : (Ljava/lang/Throwable;)Ljava/lang/Throwable;
    //   1561: athrow
    //   1562: aload #4
    //   1564: getstatic burp/Zkql.ZR : Ljava/lang/String;
    //   1567: getstatic burp/Zepy.Ze : Ljava/lang/Object;
    //   1570: checkcast java/math/BigInteger
    //   1573: invokevirtual intValue : ()I
    //   1576: bipush #32
    //   1578: irem
    //   1579: invokestatic abs : (I)I
    //   1582: invokevirtual charAt : (I)C
    //   1585: invokevirtual append : (C)Ljava/lang/StringBuilder;
    //   1588: pop
    //   1589: iload_2
    //   1590: ifeq -> 2736
    //   1593: goto -> 1600
    //   1596: invokestatic a : (Ljava/lang/Throwable;)Ljava/lang/Throwable;
    //   1599: athrow
    //   1600: aload #4
    //   1602: getstatic burp/Zssc.ZR : Ljava/lang/String;
    //   1605: getstatic burp/Zlwm.Ze : Ljava/lang/Object;
    //   1608: checkcast java/math/BigInteger
    //   1611: invokevirtual intValue : ()I
    //   1614: bipush #32
    //   1616: irem
    //   1617: invokestatic abs : (I)I
    //   1620: invokevirtual charAt : (I)C
    //   1623: invokevirtual append : (C)Ljava/lang/StringBuilder;
    //   1626: pop
    //   1627: iload_2
    //   1628: ifeq -> 2736
    //   1631: goto -> 1638
    //   1634: invokestatic a : (Ljava/lang/Throwable;)Ljava/lang/Throwable;
    //   1637: athrow
    //   1638: aload #4
    //   1640: getstatic burp/Ztgv.ZC : Ljava/lang/String;
    //   1643: getstatic burp/Zrzg.ZA : Ljava/lang/Object;
    //   1646: checkcast java/math/BigInteger
    //   1649: invokevirtual intValue : ()I
    //   1652: bipush #32
    //   1654: irem
    //   1655: invokestatic abs : (I)I
    //   1658: invokevirtual charAt : (I)C
    //   1661: invokevirtual append : (C)Ljava/lang/StringBuilder;
    //   1664: pop
    //   1665: iload_2
    //   1666: ifeq -> 2736
    //   1669: goto -> 1676
    //   1672: invokestatic a : (Ljava/lang/Throwable;)Ljava/lang/Throwable;
    //   1675: athrow
    //   1676: aload #4
    //   1678: getstatic burp/Ztzj.ZB : Ljava/lang/String;
    //   1681: getstatic burp/Zg7u.Zh : Ljava/lang/Object;
    //   1684: checkcast java/math/BigInteger
    //   1687: invokevirtual intValue : ()I
    //   1690: bipush #32
    //   1692: irem
    //   1693: invokestatic abs : (I)I
    //   1696: invokevirtual charAt : (I)C
    //   1699: invokevirtual append : (C)Ljava/lang/StringBuilder;
    //   1702: pop
    //   1703: iload_2
    //   1704: ifeq -> 2736
    //   1707: goto -> 1714
    //   1710: invokestatic a : (Ljava/lang/Throwable;)Ljava/lang/Throwable;
    //   1713: athrow
    //   1714: aload #4
    //   1716: getstatic burp/Zetf.Zo : Ljava/lang/String;
    //   1719: getstatic burp/Zgi9.Zc : Ljava/lang/Object;
    //   1722: checkcast java/math/BigInteger
    //   1725: invokevirtual intValue : ()I
    //   1728: bipush #32
    //   1730: irem
    //   1731: invokestatic abs : (I)I
    //   1734: invokevirtual charAt : (I)C
    //   1737: invokevirtual append : (C)Ljava/lang/StringBuilder;
    //   1740: pop
    //   1741: iload_2
    //   1742: ifeq -> 2736
    //   1745: goto -> 1752
    //   1748: invokestatic a : (Ljava/lang/Throwable;)Ljava/lang/Throwable;
    //   1751: athrow
    //   1752: aload #4
    //   1754: getstatic burp/Zgrz.Zu : Ljava/lang/String;
    //   1757: getstatic burp/Zzyb.ZV : Ljava/lang/Object;
    //   1760: checkcast java/math/BigInteger
    //   1763: invokevirtual intValue : ()I
    //   1766: bipush #32
    //   1768: irem
    //   1769: invokestatic abs : (I)I
    //   1772: invokevirtual charAt : (I)C
    //   1775: invokevirtual append : (C)Ljava/lang/StringBuilder;
    //   1778: pop
    //   1779: iload_2
    //   1780: ifeq -> 2736
    //   1783: goto -> 1790
    //   1786: invokestatic a : (Ljava/lang/Throwable;)Ljava/lang/Throwable;
    //   1789: athrow
    //   1790: aload #4
    //   1792: getstatic burp/Zmh3.Zy : Ljava/lang/String;
    //   1795: getstatic burp/Zg0f.Zm : Ljava/lang/Object;
    //   1798: checkcast java/math/BigInteger
    //   1801: invokevirtual intValue : ()I
    //   1804: bipush #32
    //   1806: irem
    //   1807: invokestatic abs : (I)I
    //   1810: invokevirtual charAt : (I)C
    //   1813: invokevirtual append : (C)Ljava/lang/StringBuilder;
    //   1816: pop
    //   1817: iload_2
    //   1818: ifeq -> 2736
    //   1821: goto -> 1828
    //   1824: invokestatic a : (Ljava/lang/Throwable;)Ljava/lang/Throwable;
    //   1827: athrow
    //   1828: aload #4
    //   1830: getstatic burp/Zkkl.Zh : Ljava/lang/String;
    //   1833: getstatic burp/Zr1t.ZP : Ljava/lang/Object;
    //   1836: checkcast java/math/BigInteger
    //   1839: invokevirtual intValue : ()I
    //   1842: bipush #32
    //   1844: irem
    //   1845: invokestatic abs : (I)I
    //   1848: invokevirtual charAt : (I)C
    //   1851: invokevirtual append : (C)Ljava/lang/StringBuilder;
    //   1854: pop
    //   1855: iload_2
    //   1856: ifeq -> 2736
    //   1859: goto -> 1866
    //   1862: invokestatic a : (Ljava/lang/Throwable;)Ljava/lang/Throwable;
    //   1865: athrow
    //   1866: aload #4
    //   1868: getstatic burp/Ztlo.Zs : Ljava/lang/String;
    //   1871: getstatic burp/Zz7j.ZR : Ljava/lang/Object;
    //   1874: checkcast java/math/BigInteger
    //   1877: invokevirtual intValue : ()I
    //   1880: bipush #32
    //   1882: irem
    //   1883: invokestatic abs : (I)I
    //   1886: invokevirtual charAt : (I)C
    //   1889: invokevirtual append : (C)Ljava/lang/StringBuilder;
    //   1892: pop
    //   1893: iload_2
    //   1894: ifeq -> 2736
    //   1897: goto -> 1904
    //   1900: invokestatic a : (Ljava/lang/Throwable;)Ljava/lang/Throwable;
    //   1903: athrow
    //   1904: aload #4
    //   1906: getstatic burp/Zthx.Ze : Ljava/lang/String;
    //   1909: getstatic burp/Zbx4.Zw : Ljava/lang/Object;
    //   1912: checkcast java/math/BigInteger
    //   1915: invokevirtual intValue : ()I
    //   1918: bipush #32
    //   1920: irem
    //   1921: invokestatic abs : (I)I
    //   1924: invokevirtual charAt : (I)C
    //   1927: invokevirtual append : (C)Ljava/lang/StringBuilder;
    //   1930: pop
    //   1931: iload_2
    //   1932: ifeq -> 2736
    //   1935: goto -> 1942
    //   1938: invokestatic a : (Ljava/lang/Throwable;)Ljava/lang/Throwable;
    //   1941: athrow
    //   1942: aload #4
    //   1944: getstatic burp/Zx5w.Zq : Ljava/lang/String;
    //   1947: getstatic burp/Zxp1.ZP : Ljava/lang/Object;
    //   1950: checkcast java/math/BigInteger
    //   1953: invokevirtual intValue : ()I
    //   1956: bipush #32
    //   1958: irem
    //   1959: invokestatic abs : (I)I
    //   1962: invokevirtual charAt : (I)C
    //   1965: invokevirtual append : (C)Ljava/lang/StringBuilder;
    //   1968: pop
    //   1969: iload_2
    //   1970: ifeq -> 2736
    //   1973: goto -> 1980
    //   1976: invokestatic a : (Ljava/lang/Throwable;)Ljava/lang/Throwable;
    //   1979: athrow
    //   1980: aload #4
    //   1982: getstatic burp/Ztr5.ZY : Ljava/lang/String;
    //   1985: getstatic burp/Zxy6.Zd : Ljava/lang/Object;
    //   1988: checkcast java/math/BigInteger
    //   1991: invokevirtual intValue : ()I
    //   1994: bipush #32
    //   1996: irem
    //   1997: invokestatic abs : (I)I
    //   2000: invokevirtual charAt : (I)C
    //   2003: invokevirtual append : (C)Ljava/lang/StringBuilder;
    //   2006: pop
    //   2007: iload_2
    //   2008: ifeq -> 2736
    //   2011: goto -> 2018
    //   2014: invokestatic a : (Ljava/lang/Throwable;)Ljava/lang/Throwable;
    //   2017: athrow
    //   2018: aload #4
    //   2020: getstatic burp/Zg4z.Zm : Ljava/lang/String;
    //   2023: getstatic burp/Ze25.ZW : Ljava/lang/Object;
    //   2026: checkcast java/math/BigInteger
    //   2029: invokevirtual intValue : ()I
    //   2032: bipush #32
    //   2034: irem
    //   2035: invokestatic abs : (I)I
    //   2038: invokevirtual charAt : (I)C
    //   2041: invokevirtual append : (C)Ljava/lang/StringBuilder;
    //   2044: pop
    //   2045: iload_2
    //   2046: ifeq -> 2736
    //   2049: goto -> 2056
    //   2052: invokestatic a : (Ljava/lang/Throwable;)Ljava/lang/Throwable;
    //   2055: athrow
    //   2056: aload #4
    //   2058: getstatic burp/Zl3j.Zr : Ljava/lang/String;
    //   2061: getstatic burp/Zbx5.ZL : Ljava/lang/Object;
    //   2064: checkcast java/math/BigInteger
    //   2067: invokevirtual intValue : ()I
    //   2070: bipush #32
    //   2072: irem
    //   2073: invokestatic abs : (I)I
    //   2076: invokevirtual charAt : (I)C
    //   2079: invokevirtual append : (C)Ljava/lang/StringBuilder;
    //   2082: pop
    //   2083: iload_2
    //   2084: ifeq -> 2736
    //   2087: goto -> 2094
    //   2090: invokestatic a : (Ljava/lang/Throwable;)Ljava/lang/Throwable;
    //   2093: athrow
    //   2094: aload #4
    //   2096: getstatic burp/Zsu2.Zq : Ljava/lang/String;
    //   2099: getstatic burp/Zrzg.ZA : Ljava/lang/Object;
    //   2102: checkcast java/math/BigInteger
    //   2105: invokevirtual intValue : ()I
    //   2108: bipush #32
    //   2110: irem
    //   2111: invokestatic abs : (I)I
    //   2114: invokevirtual charAt : (I)C
    //   2117: invokevirtual append : (C)Ljava/lang/StringBuilder;
    //   2120: pop
    //   2121: iload_2
    //   2122: ifeq -> 2736
    //   2125: goto -> 2132
    //   2128: invokestatic a : (Ljava/lang/Throwable;)Ljava/lang/Throwable;
    //   2131: athrow
    //   2132: aload #4
    //   2134: getstatic burp/Zrd3.Z_ : Ljava/lang/String;
    //   2137: getstatic burp/Zm_u.Zf : Ljava/lang/Object;
    //   2140: checkcast java/math/BigInteger
    //   2143: invokevirtual intValue : ()I
    //   2146: bipush #32
    //   2148: irem
    //   2149: invokestatic abs : (I)I
    //   2152: invokevirtual charAt : (I)C
    //   2155: invokevirtual append : (C)Ljava/lang/StringBuilder;
    //   2158: pop
    //   2159: iload_2
    //   2160: ifeq -> 2736
    //   2163: goto -> 2170
    //   2166: invokestatic a : (Ljava/lang/Throwable;)Ljava/lang/Throwable;
    //   2169: athrow
    //   2170: aload #4
    //   2172: getstatic burp/Zsn4.ZZ : Ljava/lang/String;
    //   2175: getstatic burp/Zld9.ZF : Ljava/lang/Object;
    //   2178: checkcast java/math/BigInteger
    //   2181: invokevirtual intValue : ()I
    //   2184: bipush #32
    //   2186: irem
    //   2187: invokestatic abs : (I)I
    //   2190: invokevirtual charAt : (I)C
    //   2193: invokevirtual append : (C)Ljava/lang/StringBuilder;
    //   2196: pop
    //   2197: iload_2
    //   2198: ifeq -> 2736
    //   2201: goto -> 2208
    //   2204: invokestatic a : (Ljava/lang/Throwable;)Ljava/lang/Throwable;
    //   2207: athrow
    //   2208: aload #4
    //   2210: getstatic burp/Ze6w.ZY : Ljava/lang/String;
    //   2213: getstatic burp/Zkkl.ZE : Ljava/lang/Object;
    //   2216: checkcast java/math/BigInteger
    //   2219: invokevirtual intValue : ()I
    //   2222: bipush #32
    //   2224: irem
    //   2225: invokestatic abs : (I)I
    //   2228: invokevirtual charAt : (I)C
    //   2231: invokevirtual append : (C)Ljava/lang/StringBuilder;
    //   2234: pop
    //   2235: iload_2
    //   2236: ifeq -> 2736
    //   2239: goto -> 2246
    //   2242: invokestatic a : (Ljava/lang/Throwable;)Ljava/lang/Throwable;
    //   2245: athrow
    //   2246: aload #4
    //   2248: getstatic burp/Zrl5.ZG : Ljava/lang/String;
    //   2251: getstatic burp/Zzef.Zw : Ljava/lang/Object;
    //   2254: checkcast java/math/BigInteger
    //   2257: invokevirtual intValue : ()I
    //   2260: bipush #32
    //   2262: irem
    //   2263: invokestatic abs : (I)I
    //   2266: invokevirtual charAt : (I)C
    //   2269: invokevirtual append : (C)Ljava/lang/StringBuilder;
    //   2272: pop
    //   2273: iload_2
    //   2274: ifeq -> 2736
    //   2277: goto -> 2284
    //   2280: invokestatic a : (Ljava/lang/Throwable;)Ljava/lang/Throwable;
    //   2283: athrow
    //   2284: aload #4
    //   2286: getstatic burp/Ztvg.ZZ : Ljava/lang/String;
    //   2289: getstatic burp/Zgsy.ZC : Ljava/lang/Object;
    //   2292: checkcast java/math/BigInteger
    //   2295: invokevirtual intValue : ()I
    //   2298: bipush #32
    //   2300: irem
    //   2301: invokestatic abs : (I)I
    //   2304: invokevirtual charAt : (I)C
    //   2307: invokevirtual append : (C)Ljava/lang/StringBuilder;
    //   2310: pop
    //   2311: iload_2
    //   2312: ifeq -> 2736
    //   2315: goto -> 2322
    //   2318: invokestatic a : (Ljava/lang/Throwable;)Ljava/lang/Throwable;
    //   2321: athrow
    //   2322: aload #4
    //   2324: getstatic burp/Zxxf.Zw : Ljava/lang/String;
    //   2327: getstatic burp/Zrp2.Zw : Ljava/lang/Object;
    //   2330: checkcast java/math/BigInteger
    //   2333: invokevirtual intValue : ()I
    //   2336: bipush #32
    //   2338: irem
    //   2339: invokestatic abs : (I)I
    //   2342: invokevirtual charAt : (I)C
    //   2345: invokevirtual append : (C)Ljava/lang/StringBuilder;
    //   2348: pop
    //   2349: iload_2
    //   2350: ifeq -> 2736
    //   2353: goto -> 2360
    //   2356: invokestatic a : (Ljava/lang/Throwable;)Ljava/lang/Throwable;
    //   2359: athrow
    //   2360: aload #4
    //   2362: getstatic burp/Zg1l.Zl : Ljava/lang/String;
    //   2365: getstatic burp/Zskf.ZQ : Ljava/lang/Object;
    //   2368: checkcast java/math/BigInteger
    //   2371: invokevirtual intValue : ()I
    //   2374: bipush #32
    //   2376: irem
    //   2377: invokestatic abs : (I)I
    //   2380: invokevirtual charAt : (I)C
    //   2383: invokevirtual append : (C)Ljava/lang/StringBuilder;
    //   2386: pop
    //   2387: iload_2
    //   2388: ifeq -> 2736
    //   2391: goto -> 2398
    //   2394: invokestatic a : (Ljava/lang/Throwable;)Ljava/lang/Throwable;
    //   2397: athrow
    //   2398: aload #4
    //   2400: getstatic burp/Zelt.ZJ : Ljava/lang/String;
    //   2403: getstatic burp/Zr9u.ZX : Ljava/lang/Object;
    //   2406: checkcast java/math/BigInteger
    //   2409: invokevirtual intValue : ()I
    //   2412: bipush #32
    //   2414: irem
    //   2415: invokestatic abs : (I)I
    //   2418: invokevirtual charAt : (I)C
    //   2421: invokevirtual append : (C)Ljava/lang/StringBuilder;
    //   2424: pop
    //   2425: iload_2
    //   2426: ifeq -> 2736
    //   2429: goto -> 2436
    //   2432: invokestatic a : (Ljava/lang/Throwable;)Ljava/lang/Throwable;
    //   2435: athrow
    //   2436: aload #4
    //   2438: getstatic burp/Zezi.Ze : Ljava/lang/String;
    //   2441: getstatic burp/Zr36.Za : Ljava/lang/Object;
    //   2444: checkcast java/math/BigInteger
    //   2447: invokevirtual intValue : ()I
    //   2450: bipush #32
    //   2452: irem
    //   2453: invokestatic abs : (I)I
    //   2456: invokevirtual charAt : (I)C
    //   2459: invokevirtual append : (C)Ljava/lang/StringBuilder;
    //   2462: pop
    //   2463: iload_2
    //   2464: ifeq -> 2736
    //   2467: goto -> 2474
    //   2470: invokestatic a : (Ljava/lang/Throwable;)Ljava/lang/Throwable;
    //   2473: athrow
    //   2474: aload #4
    //   2476: getstatic burp/Zrex.Za : Ljava/lang/String;
    //   2479: getstatic burp/Zzi_.Zf : Ljava/lang/Object;
    //   2482: checkcast java/math/BigInteger
    //   2485: invokevirtual intValue : ()I
    //   2488: bipush #32
    //   2490: irem
    //   2491: invokestatic abs : (I)I
    //   2494: invokevirtual charAt : (I)C
    //   2497: invokevirtual append : (C)Ljava/lang/StringBuilder;
    //   2500: pop
    //   2501: iload_2
    //   2502: ifeq -> 2736
    //   2505: goto -> 2512
    //   2508: invokestatic a : (Ljava/lang/Throwable;)Ljava/lang/Throwable;
    //   2511: athrow
    //   2512: aload #4
    //   2514: getstatic burp/Zesw.ZC : Ljava/lang/String;
    //   2517: getstatic burp/Zzl4.ZX : Ljava/lang/Object;
    //   2520: checkcast java/math/BigInteger
    //   2523: invokevirtual intValue : ()I
    //   2526: bipush #32
    //   2528: irem
    //   2529: invokestatic abs : (I)I
    //   2532: invokevirtual charAt : (I)C
    //   2535: invokevirtual append : (C)Ljava/lang/StringBuilder;
    //   2538: pop
    //   2539: iload_2
    //   2540: ifeq -> 2736
    //   2543: goto -> 2550
    //   2546: invokestatic a : (Ljava/lang/Throwable;)Ljava/lang/Throwable;
    //   2549: athrow
    //   2550: aload #4
    //   2552: getstatic burp/Zb0q.Zr : Ljava/lang/String;
    //   2555: getstatic burp/Zrom.ZF : Ljava/lang/Object;
    //   2558: checkcast java/math/BigInteger
    //   2561: invokevirtual intValue : ()I
    //   2564: bipush #32
    //   2566: irem
    //   2567: invokestatic abs : (I)I
    //   2570: invokevirtual charAt : (I)C
    //   2573: invokevirtual append : (C)Ljava/lang/StringBuilder;
    //   2576: pop
    //   2577: iload_2
    //   2578: ifeq -> 2736
    //   2581: goto -> 2588
    //   2584: invokestatic a : (Ljava/lang/Throwable;)Ljava/lang/Throwable;
    //   2587: athrow
    //   2588: aload #4
    //   2590: getstatic burp/Zmtr.Zd : Ljava/lang/String;
    //   2593: getstatic burp/Zmkq.Zg : Ljava/lang/Object;
    //   2596: checkcast java/math/BigInteger
    //   2599: invokevirtual intValue : ()I
    //   2602: bipush #32
    //   2604: irem
    //   2605: invokestatic abs : (I)I
    //   2608: invokevirtual charAt : (I)C
    //   2611: invokevirtual append : (C)Ljava/lang/StringBuilder;
    //   2614: pop
    //   2615: iload_2
    //   2616: ifeq -> 2736
    //   2619: goto -> 2626
    //   2622: invokestatic a : (Ljava/lang/Throwable;)Ljava/lang/Throwable;
    //   2625: athrow
    //   2626: aload #4
    //   2628: getstatic burp/Ztle.ZR : Ljava/lang/String;
    //   2631: getstatic burp/Ze25.ZW : Ljava/lang/Object;
    //   2634: checkcast java/math/BigInteger
    //   2637: invokevirtual intValue : ()I
    //   2640: bipush #32
    //   2642: irem
    //   2643: invokestatic abs : (I)I
    //   2646: invokevirtual charAt : (I)C
    //   2649: invokevirtual append : (C)Ljava/lang/StringBuilder;
    //   2652: pop
    //   2653: iload_2
    //   2654: ifeq -> 2736
    //   2657: goto -> 2664
    //   2660: invokestatic a : (Ljava/lang/Throwable;)Ljava/lang/Throwable;
    //   2663: athrow
    //   2664: aload #4
    //   2666: getstatic burp/Zrkw.ZU : Ljava/lang/String;
    //   2669: getstatic burp/Zbow.ZS : Ljava/lang/Object;
    //   2672: checkcast java/math/BigInteger
    //   2675: invokevirtual intValue : ()I
    //   2678: bipush #32
    //   2680: irem
    //   2681: invokestatic abs : (I)I
    //   2684: invokevirtual charAt : (I)C
    //   2687: invokevirtual append : (C)Ljava/lang/StringBuilder;
    //   2690: pop
    //   2691: iload_2
    //   2692: ifeq -> 2736
    //   2695: goto -> 2702
    //   2698: invokestatic a : (Ljava/lang/Throwable;)Ljava/lang/Throwable;
    //   2701: athrow
    //   2702: aload #4
    //   2704: getstatic burp/Zrov.ZU : Ljava/lang/String;
    //   2707: getstatic burp/Zxxh.Za : Ljava/lang/Object;
    //   2710: checkcast java/math/BigInteger
    //   2713: invokevirtual intValue : ()I
    //   2716: bipush #32
    //   2718: irem
    //   2719: invokestatic abs : (I)I
    //   2722: invokevirtual charAt : (I)C
    //   2725: invokevirtual append : (C)Ljava/lang/StringBuilder;
    //   2728: pop
    //   2729: goto -> 2736
    //   2732: invokestatic a : (Ljava/lang/Throwable;)Ljava/lang/Throwable;
    //   2735: athrow
    //   2736: iinc #5, 1
    //   2739: iload_2
    //   2740: ifeq -> 1374
    //   2743: aload #4
    //   2745: invokevirtual toString : ()Ljava/lang/String;
    //   2748: putstatic burp/Zmf2.ZK : Ljava/lang/String;
    //   2751: new java/lang/StringBuilder
    //   2754: dup
    //   2755: invokespecial <init> : ()V
    //   2758: astore #5
    //   2760: iconst_0
    //   2761: istore #6
    //   2763: iload #6
    //   2765: bipush #32
    //   2767: if_icmpge -> 4135
    //   2770: iload #6
    //   2772: tableswitch default -> 4128, 0 -> 2916, 1 -> 2954, 2 -> 2992, 3 -> 3030, 4 -> 3068, 5 -> 3106, 6 -> 3144, 7 -> 3182, 8 -> 3220, 9 -> 3258, 10 -> 3296, 11 -> 3334, 12 -> 3372, 13 -> 3410, 14 -> 3448, 15 -> 3486, 16 -> 3524, 17 -> 3562, 18 -> 3600, 19 -> 3638, 20 -> 3676, 21 -> 3714, 22 -> 3752, 23 -> 3790, 24 -> 3828, 25 -> 3866, 26 -> 3904, 27 -> 3942, 28 -> 3980, 29 -> 4018, 30 -> 4056, 31 -> 4094
    //   2916: aload #5
    //   2918: getstatic burp/Zrh_.ZU : Ljava/lang/String;
    //   2921: getstatic burp/Zgi9.Zc : Ljava/lang/Object;
    //   2924: checkcast java/math/BigInteger
    //   2927: invokevirtual intValue : ()I
    //   2930: bipush #32
    //   2932: irem
    //   2933: invokestatic abs : (I)I
    //   2936: invokevirtual charAt : (I)C
    //   2939: invokevirtual append : (C)Ljava/lang/StringBuilder;
    //   2942: pop
    //   2943: iload_2
    //   2944: ifeq -> 4128
    //   2947: goto -> 2954
    //   2950: invokestatic a : (Ljava/lang/Throwable;)Ljava/lang/Throwable;
    //   2953: athrow
    //   2954: aload #5
    //   2956: getstatic burp/Zlo0.ZD : Ljava/lang/String;
    //   2959: getstatic burp/Zg4z.ZB : Ljava/lang/Object;
    //   2962: checkcast java/math/BigInteger
    //   2965: invokevirtual intValue : ()I
    //   2968: bipush #32
    //   2970: irem
    //   2971: invokestatic abs : (I)I
    //   2974: invokevirtual charAt : (I)C
    //   2977: invokevirtual append : (C)Ljava/lang/StringBuilder;
    //   2980: pop
    //   2981: iload_2
    //   2982: ifeq -> 4128
    //   2985: goto -> 2992
    //   2988: invokestatic a : (Ljava/lang/Throwable;)Ljava/lang/Throwable;
    //   2991: athrow
    //   2992: aload #5
    //   2994: getstatic burp/Zes.ZW : Ljava/lang/String;
    //   2997: getstatic burp/Zbw5.ZR : Ljava/lang/Object;
    //   3000: checkcast java/math/BigInteger
    //   3003: invokevirtual intValue : ()I
    //   3006: bipush #32
    //   3008: irem
    //   3009: invokestatic abs : (I)I
    //   3012: invokevirtual charAt : (I)C
    //   3015: invokevirtual append : (C)Ljava/lang/StringBuilder;
    //   3018: pop
    //   3019: iload_2
    //   3020: ifeq -> 4128
    //   3023: goto -> 3030
    //   3026: invokestatic a : (Ljava/lang/Throwable;)Ljava/lang/Throwable;
    //   3029: athrow
    //   3030: aload #5
    //   3032: getstatic burp/Zzii.Zl : Ljava/lang/String;
    //   3035: getstatic burp/Zbx5.ZL : Ljava/lang/Object;
    //   3038: checkcast java/math/BigInteger
    //   3041: invokevirtual intValue : ()I
    //   3044: bipush #32
    //   3046: irem
    //   3047: invokestatic abs : (I)I
    //   3050: invokevirtual charAt : (I)C
    //   3053: invokevirtual append : (C)Ljava/lang/StringBuilder;
    //   3056: pop
    //   3057: iload_2
    //   3058: ifeq -> 4128
    //   3061: goto -> 3068
    //   3064: invokestatic a : (Ljava/lang/Throwable;)Ljava/lang/Throwable;
    //   3067: athrow
    //   3068: aload #5
    //   3070: getstatic burp/Zmhq.Zy : Ljava/lang/String;
    //   3073: getstatic burp/Zs_m.Z_ : Ljava/lang/Object;
    //   3076: checkcast java/math/BigInteger
    //   3079: invokevirtual intValue : ()I
    //   3082: bipush #32
    //   3084: irem
    //   3085: invokestatic abs : (I)I
    //   3088: invokevirtual charAt : (I)C
    //   3091: invokevirtual append : (C)Ljava/lang/StringBuilder;
    //   3094: pop
    //   3095: iload_2
    //   3096: ifeq -> 4128
    //   3099: goto -> 3106
    //   3102: invokestatic a : (Ljava/lang/Throwable;)Ljava/lang/Throwable;
    //   3105: athrow
    //   3106: aload #5
    //   3108: getstatic burp/Zxp1.Zg : Ljava/lang/String;
    //   3111: getstatic burp/Zeub.ZD : Ljava/lang/Object;
    //   3114: checkcast java/math/BigInteger
    //   3117: invokevirtual intValue : ()I
    //   3120: bipush #32
    //   3122: irem
    //   3123: invokestatic abs : (I)I
    //   3126: invokevirtual charAt : (I)C
    //   3129: invokevirtual append : (C)Ljava/lang/StringBuilder;
    //   3132: pop
    //   3133: iload_2
    //   3134: ifeq -> 4128
    //   3137: goto -> 3144
    //   3140: invokestatic a : (Ljava/lang/Throwable;)Ljava/lang/Throwable;
    //   3143: athrow
    //   3144: aload #5
    //   3146: getstatic burp/Zexl.Zs : Ljava/lang/String;
    //   3149: getstatic burp/Zz0y.Zp : Ljava/lang/Object;
    //   3152: checkcast java/math/BigInteger
    //   3155: invokevirtual intValue : ()I
    //   3158: bipush #32
    //   3160: irem
    //   3161: invokestatic abs : (I)I
    //   3164: invokevirtual charAt : (I)C
    //   3167: invokevirtual append : (C)Ljava/lang/StringBuilder;
    //   3170: pop
    //   3171: iload_2
    //   3172: ifeq -> 4128
    //   3175: goto -> 3182
    //   3178: invokestatic a : (Ljava/lang/Throwable;)Ljava/lang/Throwable;
    //   3181: athrow
    //   3182: aload #5
    //   3184: getstatic burp/Zlxw.ZC : Ljava/lang/String;
    //   3187: getstatic burp/Zb87.Zb : Ljava/lang/Object;
    //   3190: checkcast java/math/BigInteger
    //   3193: invokevirtual intValue : ()I
    //   3196: bipush #32
    //   3198: irem
    //   3199: invokestatic abs : (I)I
    //   3202: invokevirtual charAt : (I)C
    //   3205: invokevirtual append : (C)Ljava/lang/StringBuilder;
    //   3208: pop
    //   3209: iload_2
    //   3210: ifeq -> 4128
    //   3213: goto -> 3220
    //   3216: invokestatic a : (Ljava/lang/Throwable;)Ljava/lang/Throwable;
    //   3219: athrow
    //   3220: aload #5
    //   3222: getstatic burp/Zbx5.Zz : Ljava/lang/String;
    //   3225: getstatic burp/Zegv.ZL : Ljava/lang/Object;
    //   3228: checkcast java/math/BigInteger
    //   3231: invokevirtual intValue : ()I
    //   3234: bipush #32
    //   3236: irem
    //   3237: invokestatic abs : (I)I
    //   3240: invokevirtual charAt : (I)C
    //   3243: invokevirtual append : (C)Ljava/lang/StringBuilder;
    //   3246: pop
    //   3247: iload_2
    //   3248: ifeq -> 4128
    //   3251: goto -> 3258
    //   3254: invokestatic a : (Ljava/lang/Throwable;)Ljava/lang/Throwable;
    //   3257: athrow
    //   3258: aload #5
    //   3260: getstatic burp/Zr1t.Ze : Ljava/lang/String;
    //   3263: getstatic burp/Zrnt.Zh : Ljava/lang/Object;
    //   3266: checkcast java/math/BigInteger
    //   3269: invokevirtual intValue : ()I
    //   3272: bipush #32
    //   3274: irem
    //   3275: invokestatic abs : (I)I
    //   3278: invokevirtual charAt : (I)C
    //   3281: invokevirtual append : (C)Ljava/lang/StringBuilder;
    //   3284: pop
    //   3285: iload_2
    //   3286: ifeq -> 4128
    //   3289: goto -> 3296
    //   3292: invokestatic a : (Ljava/lang/Throwable;)Ljava/lang/Throwable;
    //   3295: athrow
    //   3296: aload #5
    //   3298: getstatic burp/Zz4a.ZC : Ljava/lang/String;
    //   3301: getstatic burp/Zka9.Zd : Ljava/lang/Object;
    //   3304: checkcast java/math/BigInteger
    //   3307: invokevirtual intValue : ()I
    //   3310: bipush #32
    //   3312: irem
    //   3313: invokestatic abs : (I)I
    //   3316: invokevirtual charAt : (I)C
    //   3319: invokevirtual append : (C)Ljava/lang/StringBuilder;
    //   3322: pop
    //   3323: iload_2
    //   3324: ifeq -> 4128
    //   3327: goto -> 3334
    //   3330: invokestatic a : (Ljava/lang/Throwable;)Ljava/lang/Throwable;
    //   3333: athrow
    //   3334: aload #5
    //   3336: getstatic burp/Zz91.Zx : Ljava/lang/String;
    //   3339: getstatic burp/Zes.Zx : Ljava/lang/Object;
    //   3342: checkcast java/math/BigInteger
    //   3345: invokevirtual intValue : ()I
    //   3348: bipush #32
    //   3350: irem
    //   3351: invokestatic abs : (I)I
    //   3354: invokevirtual charAt : (I)C
    //   3357: invokevirtual append : (C)Ljava/lang/StringBuilder;
    //   3360: pop
    //   3361: iload_2
    //   3362: ifeq -> 4128
    //   3365: goto -> 3372
    //   3368: invokestatic a : (Ljava/lang/Throwable;)Ljava/lang/Throwable;
    //   3371: athrow
    //   3372: aload #5
    //   3374: getstatic burp/Zspg.ZG : Ljava/lang/String;
    //   3377: getstatic burp/Ztvy.ZH : Ljava/lang/Object;
    //   3380: checkcast java/math/BigInteger
    //   3383: invokevirtual intValue : ()I
    //   3386: bipush #32
    //   3388: irem
    //   3389: invokestatic abs : (I)I
    //   3392: invokevirtual charAt : (I)C
    //   3395: invokevirtual append : (C)Ljava/lang/StringBuilder;
    //   3398: pop
    //   3399: iload_2
    //   3400: ifeq -> 4128
    //   3403: goto -> 3410
    //   3406: invokestatic a : (Ljava/lang/Throwable;)Ljava/lang/Throwable;
    //   3409: athrow
    //   3410: aload #5
    //   3412: getstatic burp/Zrd3.Z_ : Ljava/lang/String;
    //   3415: getstatic burp/Zbw5.ZR : Ljava/lang/Object;
    //   3418: checkcast java/math/BigInteger
    //   3421: invokevirtual intValue : ()I
    //   3424: bipush #32
    //   3426: irem
    //   3427: invokestatic abs : (I)I
    //   3430: invokevirtual charAt : (I)C
    //   3433: invokevirtual append : (C)Ljava/lang/StringBuilder;
    //   3436: pop
    //   3437: iload_2
    //   3438: ifeq -> 4128
    //   3441: goto -> 3448
    //   3444: invokestatic a : (Ljava/lang/Throwable;)Ljava/lang/Throwable;
    //   3447: athrow
    //   3448: aload #5
    //   3450: getstatic burp/Zr9u.Zc : Ljava/lang/String;
    //   3453: getstatic burp/Zrh_.Zb : Ljava/lang/Object;
    //   3456: checkcast java/math/BigInteger
    //   3459: invokevirtual intValue : ()I
    //   3462: bipush #32
    //   3464: irem
    //   3465: invokestatic abs : (I)I
    //   3468: invokevirtual charAt : (I)C
    //   3471: invokevirtual append : (C)Ljava/lang/StringBuilder;
    //   3474: pop
    //   3475: iload_2
    //   3476: ifeq -> 4128
    //   3479: goto -> 3486
    //   3482: invokestatic a : (Ljava/lang/Throwable;)Ljava/lang/Throwable;
    //   3485: athrow
    //   3486: aload #5
    //   3488: getstatic burp/Zr1t.Ze : Ljava/lang/String;
    //   3491: getstatic burp/Zld9.ZF : Ljava/lang/Object;
    //   3494: checkcast java/math/BigInteger
    //   3497: invokevirtual intValue : ()I
    //   3500: bipush #32
    //   3502: irem
    //   3503: invokestatic abs : (I)I
    //   3506: invokevirtual charAt : (I)C
    //   3509: invokevirtual append : (C)Ljava/lang/StringBuilder;
    //   3512: pop
    //   3513: iload_2
    //   3514: ifeq -> 4128
    //   3517: goto -> 3524
    //   3520: invokestatic a : (Ljava/lang/Throwable;)Ljava/lang/Throwable;
    //   3523: athrow
    //   3524: aload #5
    //   3526: getstatic burp/Zk8f.ZV : Ljava/lang/String;
    //   3529: getstatic burp/Zlo0.Zu : Ljava/lang/Object;
    //   3532: checkcast java/math/BigInteger
    //   3535: invokevirtual intValue : ()I
    //   3538: bipush #32
    //   3540: irem
    //   3541: invokestatic abs : (I)I
    //   3544: invokevirtual charAt : (I)C
    //   3547: invokevirtual append : (C)Ljava/lang/StringBuilder;
    //   3550: pop
    //   3551: iload_2
    //   3552: ifeq -> 4128
    //   3555: goto -> 3562
    //   3558: invokestatic a : (Ljava/lang/Throwable;)Ljava/lang/Throwable;
    //   3561: athrow
    //   3562: aload #5
    //   3564: getstatic burp/Zedu.ZD : Ljava/lang/String;
    //   3567: getstatic burp/Zz3b.Zu : Ljava/lang/Object;
    //   3570: checkcast java/math/BigInteger
    //   3573: invokevirtual intValue : ()I
    //   3576: bipush #32
    //   3578: irem
    //   3579: invokestatic abs : (I)I
    //   3582: invokevirtual charAt : (I)C
    //   3585: invokevirtual append : (C)Ljava/lang/StringBuilder;
    //   3588: pop
    //   3589: iload_2
    //   3590: ifeq -> 4128
    //   3593: goto -> 3600
    //   3596: invokestatic a : (Ljava/lang/Throwable;)Ljava/lang/Throwable;
    //   3599: athrow
    //   3600: aload #5
    //   3602: getstatic burp/Zl_f.ZF : Ljava/lang/String;
    //   3605: getstatic burp/Zea8.ZF : Ljava/lang/Object;
    //   3608: checkcast java/math/BigInteger
    //   3611: invokevirtual intValue : ()I
    //   3614: bipush #32
    //   3616: irem
    //   3617: invokestatic abs : (I)I
    //   3620: invokevirtual charAt : (I)C
    //   3623: invokevirtual append : (C)Ljava/lang/StringBuilder;
    //   3626: pop
    //   3627: iload_2
    //   3628: ifeq -> 4128
    //   3631: goto -> 3638
    //   3634: invokestatic a : (Ljava/lang/Throwable;)Ljava/lang/Throwable;
    //   3637: athrow
    //   3638: aload #5
    //   3640: getstatic burp/Zkf6.ZO : Ljava/lang/String;
    //   3643: getstatic burp/Zxxo.ZJ : Ljava/lang/Object;
    //   3646: checkcast java/math/BigInteger
    //   3649: invokevirtual intValue : ()I
    //   3652: bipush #32
    //   3654: irem
    //   3655: invokestatic abs : (I)I
    //   3658: invokevirtual charAt : (I)C
    //   3661: invokevirtual append : (C)Ljava/lang/StringBuilder;
    //   3664: pop
    //   3665: iload_2
    //   3666: ifeq -> 4128
    //   3669: goto -> 3676
    //   3672: invokestatic a : (Ljava/lang/Throwable;)Ljava/lang/Throwable;
    //   3675: athrow
    //   3676: aload #5
    //   3678: getstatic burp/Zbx5.Zz : Ljava/lang/String;
    //   3681: getstatic burp/Zzhx.ZB : Ljava/lang/Object;
    //   3684: checkcast java/math/BigInteger
    //   3687: invokevirtual intValue : ()I
    //   3690: bipush #32
    //   3692: irem
    //   3693: invokestatic abs : (I)I
    //   3696: invokevirtual charAt : (I)C
    //   3699: invokevirtual append : (C)Ljava/lang/StringBuilder;
    //   3702: pop
    //   3703: iload_2
    //   3704: ifeq -> 4128
    //   3707: goto -> 3714
    //   3710: invokestatic a : (Ljava/lang/Throwable;)Ljava/lang/Throwable;
    //   3713: athrow
    //   3714: aload #5
    //   3716: getstatic burp/Zsjc.ZO : Ljava/lang/String;
    //   3719: getstatic burp/Zeqx.Zh : Ljava/lang/Object;
    //   3722: checkcast java/math/BigInteger
    //   3725: invokevirtual intValue : ()I
    //   3728: bipush #32
    //   3730: irem
    //   3731: invokestatic abs : (I)I
    //   3734: invokevirtual charAt : (I)C
    //   3737: invokevirtual append : (C)Ljava/lang/StringBuilder;
    //   3740: pop
    //   3741: iload_2
    //   3742: ifeq -> 4128
    //   3745: goto -> 3752
    //   3748: invokestatic a : (Ljava/lang/Throwable;)Ljava/lang/Throwable;
    //   3751: athrow
    //   3752: aload #5
    //   3754: getstatic burp/Zg1l.Zl : Ljava/lang/String;
    //   3757: getstatic burp/Ze4g.Zz : Ljava/lang/Object;
    //   3760: checkcast java/math/BigInteger
    //   3763: invokevirtual intValue : ()I
    //   3766: bipush #32
    //   3768: irem
    //   3769: invokestatic abs : (I)I
    //   3772: invokevirtual charAt : (I)C
    //   3775: invokevirtual append : (C)Ljava/lang/StringBuilder;
    //   3778: pop
    //   3779: iload_2
    //   3780: ifeq -> 4128
    //   3783: goto -> 3790
    //   3786: invokestatic a : (Ljava/lang/Throwable;)Ljava/lang/Throwable;
    //   3789: athrow
    //   3790: aload #5
    //   3792: getstatic burp/Zgu4.Za : Ljava/lang/String;
    //   3795: getstatic burp/Zebc.Zr : Ljava/lang/Object;
    //   3798: checkcast java/math/BigInteger
    //   3801: invokevirtual intValue : ()I
    //   3804: bipush #32
    //   3806: irem
    //   3807: invokestatic abs : (I)I
    //   3810: invokevirtual charAt : (I)C
    //   3813: invokevirtual append : (C)Ljava/lang/StringBuilder;
    //   3816: pop
    //   3817: iload_2
    //   3818: ifeq -> 4128
    //   3821: goto -> 3828
    //   3824: invokestatic a : (Ljava/lang/Throwable;)Ljava/lang/Throwable;
    //   3827: athrow
    //   3828: aload #5
    //   3830: getstatic burp/Zeqz.ZV : Ljava/lang/String;
    //   3833: getstatic burp/Zkjj.Zh : Ljava/lang/Object;
    //   3836: checkcast java/math/BigInteger
    //   3839: invokevirtual intValue : ()I
    //   3842: bipush #32
    //   3844: irem
    //   3845: invokestatic abs : (I)I
    //   3848: invokevirtual charAt : (I)C
    //   3851: invokevirtual append : (C)Ljava/lang/StringBuilder;
    //   3854: pop
    //   3855: iload_2
    //   3856: ifeq -> 4128
    //   3859: goto -> 3866
    //   3862: invokestatic a : (Ljava/lang/Throwable;)Ljava/lang/Throwable;
    //   3865: athrow
    //   3866: aload #5
    //   3868: getstatic burp/Zg0q.Ze : Ljava/lang/String;
    //   3871: getstatic burp/Zrgo.ZJ : Ljava/lang/Object;
    //   3874: checkcast java/math/BigInteger
    //   3877: invokevirtual intValue : ()I
    //   3880: bipush #32
    //   3882: irem
    //   3883: invokestatic abs : (I)I
    //   3886: invokevirtual charAt : (I)C
    //   3889: invokevirtual append : (C)Ljava/lang/StringBuilder;
    //   3892: pop
    //   3893: iload_2
    //   3894: ifeq -> 4128
    //   3897: goto -> 3904
    //   3900: invokestatic a : (Ljava/lang/Throwable;)Ljava/lang/Throwable;
    //   3903: athrow
    //   3904: aload #5
    //   3906: getstatic burp/Zmyk.Zx : Ljava/lang/String;
    //   3909: getstatic burp/Zzii.ZO : Ljava/lang/Object;
    //   3912: checkcast java/math/BigInteger
    //   3915: invokevirtual intValue : ()I
    //   3918: bipush #32
    //   3920: irem
    //   3921: invokestatic abs : (I)I
    //   3924: invokevirtual charAt : (I)C
    //   3927: invokevirtual append : (C)Ljava/lang/StringBuilder;
    //   3930: pop
    //   3931: iload_2
    //   3932: ifeq -> 4128
    //   3935: goto -> 3942
    //   3938: invokestatic a : (Ljava/lang/Throwable;)Ljava/lang/Throwable;
    //   3941: athrow
    //   3942: aload #5
    //   3944: getstatic burp/Zt4p.ZL : Ljava/lang/String;
    //   3947: getstatic burp/Zr36.Za : Ljava/lang/Object;
    //   3950: checkcast java/math/BigInteger
    //   3953: invokevirtual intValue : ()I
    //   3956: bipush #32
    //   3958: irem
    //   3959: invokestatic abs : (I)I
    //   3962: invokevirtual charAt : (I)C
    //   3965: invokevirtual append : (C)Ljava/lang/StringBuilder;
    //   3968: pop
    //   3969: iload_2
    //   3970: ifeq -> 4128
    //   3973: goto -> 3980
    //   3976: invokestatic a : (Ljava/lang/Throwable;)Ljava/lang/Throwable;
    //   3979: athrow
    //   3980: aload #5
    //   3982: getstatic burp/Zrqe.ZB : Ljava/lang/String;
    //   3985: getstatic burp/Ze7e.Z_ : Ljava/lang/Object;
    //   3988: checkcast java/math/BigInteger
    //   3991: invokevirtual intValue : ()I
    //   3994: bipush #32
    //   3996: irem
    //   3997: invokestatic abs : (I)I
    //   4000: invokevirtual charAt : (I)C
    //   4003: invokevirtual append : (C)Ljava/lang/StringBuilder;
    //   4006: pop
    //   4007: iload_2
    //   4008: ifeq -> 4128
    //   4011: goto -> 4018
    //   4014: invokestatic a : (Ljava/lang/Throwable;)Ljava/lang/Throwable;
    //   4017: athrow
    //   4018: aload #5
    //   4020: getstatic burp/Zk9q.Zk : Ljava/lang/String;
    //   4023: getstatic burp/Zmyk.Za : Ljava/lang/Object;
    //   4026: checkcast java/math/BigInteger
    //   4029: invokevirtual intValue : ()I
    //   4032: bipush #32
    //   4034: irem
    //   4035: invokestatic abs : (I)I
    //   4038: invokevirtual charAt : (I)C
    //   4041: invokevirtual append : (C)Ljava/lang/StringBuilder;
    //   4044: pop
    //   4045: iload_2
    //   4046: ifeq -> 4128
    //   4049: goto -> 4056
    //   4052: invokestatic a : (Ljava/lang/Throwable;)Ljava/lang/Throwable;
    //   4055: athrow
    //   4056: aload #5
    //   4058: getstatic burp/Zg4z.Zm : Ljava/lang/String;
    //   4061: getstatic burp/Ztq2.Zj : Ljava/lang/Object;
    //   4064: checkcast java/math/BigInteger
    //   4067: invokevirtual intValue : ()I
    //   4070: bipush #32
    //   4072: irem
    //   4073: invokestatic abs : (I)I
    //   4076: invokevirtual charAt : (I)C
    //   4079: invokevirtual append : (C)Ljava/lang/StringBuilder;
    //   4082: pop
    //   4083: iload_2
    //   4084: ifeq -> 4128
    //   4087: goto -> 4094
    //   4090: invokestatic a : (Ljava/lang/Throwable;)Ljava/lang/Throwable;
    //   4093: athrow
    //   4094: aload #5
    //   4096: getstatic burp/Zt5t.ZK : Ljava/lang/String;
    //   4099: getstatic burp/Zr02.ZB : Ljava/lang/Object;
    //   4102: checkcast java/math/BigInteger
    //   4105: invokevirtual intValue : ()I
    //   4108: bipush #32
    //   4110: irem
    //   4111: invokestatic abs : (I)I
    //   4114: invokevirtual charAt : (I)C
    //   4117: invokevirtual append : (C)Ljava/lang/StringBuilder;
    //   4120: pop
    //   4121: goto -> 4128
    //   4124: invokestatic a : (Ljava/lang/Throwable;)Ljava/lang/Throwable;
    //   4127: athrow
    //   4128: iinc #6, 1
    //   4131: iload_2
    //   4132: ifeq -> 2763
    //   4135: aload #5
    //   4137: invokevirtual toString : ()Ljava/lang/String;
    //   4140: putstatic burp/Zmc_.Zb : Ljava/lang/String;
    //   4143: sipush #-9933
    //   4146: sipush #-18168
    //   4149: invokestatic a : (II)Ljava/lang/String;
    //   4152: iconst_1
    //   4153: ldc burp/Ztap
    //   4155: invokevirtual getClassLoader : ()Ljava/lang/ClassLoader;
    //   4158: invokestatic forName : (Ljava/lang/String;ZLjava/lang/ClassLoader;)Ljava/lang/Class;
    //   4161: invokevirtual getDeclaredFields : ()[Ljava/lang/reflect/Field;
    //   4164: astore #6
    //   4166: aload #6
    //   4168: arraylength
    //   4169: istore #7
    //   4171: iconst_0
    //   4172: istore #8
    //   4174: iload #8
    //   4176: iload #7
    //   4178: if_icmpge -> 4316
    //   4181: aload #6
    //   4183: iload #8
    //   4185: aaload
    //   4186: astore #9
    //   4188: aload #9
    //   4190: invokevirtual getModifiers : ()I
    //   4193: invokestatic isStatic : (I)Z
    //   4196: ifne -> 4206
    //   4199: goto -> 4309
    //   4202: invokestatic a : (Ljava/lang/Throwable;)Ljava/lang/Throwable;
    //   4205: athrow
    //   4206: aload #9
    //   4208: invokevirtual getType : ()Ljava/lang/Class;
    //   4211: astore #10
    //   4213: aload #10
    //   4215: ifnull -> 4296
    //   4218: aload #10
    //   4220: invokevirtual isPrimitive : ()Z
    //   4223: ifne -> 4296
    //   4226: goto -> 4233
    //   4229: invokestatic a : (Ljava/lang/Throwable;)Ljava/lang/Throwable;
    //   4232: athrow
    //   4233: aload #10
    //   4235: invokevirtual getPackage : ()Ljava/lang/Package;
    //   4238: ifnull -> 4296
    //   4241: goto -> 4248
    //   4244: invokestatic a : (Ljava/lang/Throwable;)Ljava/lang/Throwable;
    //   4247: athrow
    //   4248: aload #10
    //   4250: invokevirtual getPackage : ()Ljava/lang/Package;
    //   4253: invokevirtual getName : ()Ljava/lang/String;
    //   4256: ifnull -> 4296
    //   4259: goto -> 4266
    //   4262: invokestatic a : (Ljava/lang/Throwable;)Ljava/lang/Throwable;
    //   4265: athrow
    //   4266: aload #10
    //   4268: invokevirtual getPackage : ()Ljava/lang/Package;
    //   4271: invokevirtual getName : ()Ljava/lang/String;
    //   4274: sipush #-9936
    //   4277: sipush #27358
    //   4280: invokestatic a : (II)Ljava/lang/String;
    //   4283: invokevirtual startsWith : (Ljava/lang/String;)Z
    //   4286: ifne -> 4296
    //   4289: goto -> 4296
    //   4292: invokestatic a : (Ljava/lang/Throwable;)Ljava/lang/Throwable;
    //   4295: athrow
    //   4296: aload #9
    //   4298: iconst_1
    //   4299: invokevirtual setAccessible : (Z)V
    //   4302: aload #9
    //   4304: aconst_null
    //   4305: invokevirtual get : (Ljava/lang/Object;)Ljava/lang/Object;
    //   4308: pop
    //   4309: iinc #8, 1
    //   4312: iload_2
    //   4313: ifeq -> 4174
    //   4316: sipush #-9929
    //   4319: sipush #-31766
    //   4322: invokestatic a : (II)Ljava/lang/String;
    //   4325: invokestatic forName : (Ljava/lang/String;)Ljava/lang/Class;
    //   4328: invokevirtual getDeclaredMethods : ()[Ljava/lang/reflect/Method;
    //   4331: astore #6
    //   4333: aload #6
    //   4335: arraylength
    //   4336: istore #7
    //   4338: iconst_0
    //   4339: istore #8
    //   4341: iload #8
    //   4343: iload #7
    //   4345: if_icmpge -> 4478
    //   4348: aload #6
    //   4350: iload #8
    //   4352: aaload
    //   4353: astore #9
    //   4355: aload #9
    //   4357: invokevirtual getParameterTypes : ()[Ljava/lang/Class;
    //   4360: pop
    //   4361: aload #9
    //   4363: invokevirtual getModifiers : ()I
    //   4366: invokestatic isStatic : (I)Z
    //   4369: ifeq -> 4464
    //   4372: aload #9
    //   4374: invokevirtual getParameterTypes : ()[Ljava/lang/Class;
    //   4377: arraylength
    //   4378: iconst_2
    //   4379: if_icmpne -> 4464
    //   4382: goto -> 4389
    //   4385: invokestatic a : (Ljava/lang/Throwable;)Ljava/lang/Throwable;
    //   4388: athrow
    //   4389: aload #9
    //   4391: invokevirtual getReturnType : ()Ljava/lang/Class;
    //   4394: getstatic java/lang/Void.TYPE : Ljava/lang/Class;
    //   4397: invokevirtual equals : (Ljava/lang/Object;)Z
    //   4400: ifeq -> 4464
    //   4403: goto -> 4410
    //   4406: invokestatic a : (Ljava/lang/Throwable;)Ljava/lang/Throwable;
    //   4409: athrow
    //   4410: aload #9
    //   4412: iconst_1
    //   4413: invokevirtual setAccessible : (Z)V
    //   4416: aload #9
    //   4418: aconst_null
    //   4419: iconst_2
    //   4420: anewarray java/lang/Object
    //   4423: dup
    //   4424: iconst_0
    //   4425: aload_0
    //   4426: aastore
    //   4427: dup
    //   4428: iconst_1
    //   4429: aload_1
    //   4430: ifnonnull -> 4448
    //   4433: goto -> 4440
    //   4436: invokestatic a : (Ljava/lang/Throwable;)Ljava/lang/Throwable;
    //   4439: athrow
    //   4440: aload_1
    //   4441: goto -> 4455
    //   4444: invokestatic a : (Ljava/lang/Throwable;)Ljava/lang/Throwable;
    //   4447: athrow
    //   4448: aload_1
    //   4449: checkcast [B
    //   4452: invokevirtual clone : ()Ljava/lang/Object;
    //   4455: aastore
    //   4456: invokevirtual invoke : (Ljava/lang/Object;[Ljava/lang/Object;)Ljava/lang/Object;
    //   4459: pop
    //   4460: iload_2
    //   4461: ifeq -> 4478
    //   4464: iinc #8, 1
    //   4467: iload_2
    //   4468: ifeq -> 4341
    //   4471: goto -> 4478
    //   4474: invokestatic a : (Ljava/lang/Throwable;)Ljava/lang/Throwable;
    //   4477: athrow
    //   4478: getstatic burp/Zedq.Zy : Ljava/lang/Object;
    //   4481: checkcast java/math/BigInteger
    //   4484: invokevirtual toByteArray : ()[B
    //   4487: astore #6
    //   4489: iconst_0
    //   4490: istore #8
    //   4492: iconst_0
    //   4493: istore #9
    //   4495: iload #9
    //   4497: aload #6
    //   4499: arraylength
    //   4500: if_icmpge -> 4646
    //   4503: aload #6
    //   4505: iload #9
    //   4507: baload
    //   4508: istore #10
    //   4510: iload #10
    //   4512: bipush #48
    //   4514: if_icmplt -> 4531
    //   4517: iload #10
    //   4519: bipush #57
    //   4521: if_icmple -> 4629
    //   4524: goto -> 4531
    //   4527: invokestatic a : (Ljava/lang/Throwable;)Ljava/lang/Throwable;
    //   4530: athrow
    //   4531: iload #10
    //   4533: bipush #65
    //   4535: if_icmplt -> 4559
    //   4538: goto -> 4545
    //   4541: invokestatic a : (Ljava/lang/Throwable;)Ljava/lang/Throwable;
    //   4544: athrow
    //   4545: iload #10
    //   4547: bipush #90
    //   4549: if_icmple -> 4629
    //   4552: goto -> 4559
    //   4555: invokestatic a : (Ljava/lang/Throwable;)Ljava/lang/Throwable;
    //   4558: athrow
    //   4559: iload #10
    //   4561: bipush #97
    //   4563: if_icmplt -> 4587
    //   4566: goto -> 4573
    //   4569: invokestatic a : (Ljava/lang/Throwable;)Ljava/lang/Throwable;
    //   4572: athrow
    //   4573: iload #10
    //   4575: bipush #122
    //   4577: if_icmple -> 4629
    //   4580: goto -> 4587
    //   4583: invokestatic a : (Ljava/lang/Throwable;)Ljava/lang/Throwable;
    //   4586: athrow
    //   4587: iload #10
    //   4589: bipush #43
    //   4591: if_icmpeq -> 4629
    //   4594: goto -> 4601
    //   4597: invokestatic a : (Ljava/lang/Throwable;)Ljava/lang/Throwable;
    //   4600: athrow
    //   4601: iload #10
    //   4603: bipush #47
    //   4605: if_icmpeq -> 4629
    //   4608: goto -> 4615
    //   4611: invokestatic a : (Ljava/lang/Throwable;)Ljava/lang/Throwable;
    //   4614: athrow
    //   4615: iload #10
    //   4617: bipush #61
    //   4619: if_icmpne -> 4639
    //   4622: goto -> 4629
    //   4625: invokestatic a : (Ljava/lang/Throwable;)Ljava/lang/Throwable;
    //   4628: athrow
    //   4629: iinc #8, 1
    //   4632: goto -> 4639
    //   4635: invokestatic a : (Ljava/lang/Throwable;)Ljava/lang/Throwable;
    //   4638: athrow
    //   4639: iinc #9, 1
    //   4642: iload_2
    //   4643: ifeq -> 4495
    //   4646: iload #8
    //   4648: newarray byte
    //   4650: astore #9
    //   4652: iconst_0
    //   4653: istore #10
    //   4655: iconst_0
    //   4656: istore #11
    //   4658: iload #11
    //   4660: aload #6
    //   4662: arraylength
    //   4663: if_icmpge -> 4816
    //   4666: aload #6
    //   4668: iload #11
    //   4670: baload
    //   4671: istore #12
    //   4673: iload #12
    //   4675: bipush #48
    //   4677: if_icmplt -> 4694
    //   4680: iload #12
    //   4682: bipush #57
    //   4684: if_icmple -> 4792
    //   4687: goto -> 4694
    //   4690: invokestatic a : (Ljava/lang/Throwable;)Ljava/lang/Throwable;
    //   4693: athrow
    //   4694: iload #12
    //   4696: bipush #65
    //   4698: if_icmplt -> 4722
    //   4701: goto -> 4708
    //   4704: invokestatic a : (Ljava/lang/Throwable;)Ljava/lang/Throwable;
    //   4707: athrow
    //   4708: iload #12
    //   4710: bipush #90
    //   4712: if_icmple -> 4792
    //   4715: goto -> 4722
    //   4718: invokestatic a : (Ljava/lang/Throwable;)Ljava/lang/Throwable;
    //   4721: athrow
    //   4722: iload #12
    //   4724: bipush #97
    //   4726: if_icmplt -> 4750
    //   4729: goto -> 4736
    //   4732: invokestatic a : (Ljava/lang/Throwable;)Ljava/lang/Throwable;
    //   4735: athrow
    //   4736: iload #12
    //   4738: bipush #122
    //   4740: if_icmple -> 4792
    //   4743: goto -> 4750
    //   4746: invokestatic a : (Ljava/lang/Throwable;)Ljava/lang/Throwable;
    //   4749: athrow
    //   4750: iload #12
    //   4752: bipush #43
    //   4754: if_icmpeq -> 4792
    //   4757: goto -> 4764
    //   4760: invokestatic a : (Ljava/lang/Throwable;)Ljava/lang/Throwable;
    //   4763: athrow
    //   4764: iload #12
    //   4766: bipush #47
    //   4768: if_icmpeq -> 4792
    //   4771: goto -> 4778
    //   4774: invokestatic a : (Ljava/lang/Throwable;)Ljava/lang/Throwable;
    //   4777: athrow
    //   4778: iload #12
    //   4780: bipush #61
    //   4782: if_icmpne -> 4809
    //   4785: goto -> 4792
    //   4788: invokestatic a : (Ljava/lang/Throwable;)Ljava/lang/Throwable;
    //   4791: athrow
    //   4792: aload #9
    //   4794: iload #10
    //   4796: iload #12
    //   4798: bastore
    //   4799: iinc #10, 1
    //   4802: goto -> 4809
    //   4805: invokestatic a : (Ljava/lang/Throwable;)Ljava/lang/Throwable;
    //   4808: athrow
    //   4809: iinc #11, 1
    //   4812: iload_2
    //   4813: ifeq -> 4658
    //   4816: aload #9
    //   4818: astore #7
    //   4820: aload #7
    //   4822: astore #6
    //   4824: aload #6
    //   4826: arraylength
    //   4827: istore #8
    //   4829: aload #6
    //   4831: iload #8
    //   4833: iconst_1
    //   4834: isub
    //   4835: baload
    //   4836: bipush #61
    //   4838: if_icmpne -> 4848
    //   4841: iinc #8, -1
    //   4844: iload_2
    //   4845: ifeq -> 4829
    //   4848: iload #8
    //   4850: aload #6
    //   4852: arraylength
    //   4853: iconst_4
    //   4854: idiv
    //   4855: isub
    //   4856: newarray byte
    //   4858: astore #9
    //   4860: iconst_0
    //   4861: istore #10
    //   4863: iload #10
    //   4865: aload #6
    //   4867: arraylength
    //   4868: if_icmpge -> 5148
    //   4871: aload #6
    //   4873: iload #10
    //   4875: baload
    //   4876: bipush #61
    //   4878: if_icmpne -> 4898
    //   4881: aload #6
    //   4883: iload #10
    //   4885: iconst_0
    //   4886: bastore
    //   4887: iload_2
    //   4888: ifeq -> 5141
    //   4891: goto -> 4898
    //   4894: invokestatic a : (Ljava/lang/Throwable;)Ljava/lang/Throwable;
    //   4897: athrow
    //   4898: aload #6
    //   4900: iload #10
    //   4902: baload
    //   4903: bipush #47
    //   4905: if_icmpne -> 4933
    //   4908: goto -> 4915
    //   4911: invokestatic a : (Ljava/lang/Throwable;)Ljava/lang/Throwable;
    //   4914: athrow
    //   4915: aload #6
    //   4917: iload #10
    //   4919: bipush #63
    //   4921: bastore
    //   4922: iload_2
    //   4923: ifeq -> 5141
    //   4926: goto -> 4933
    //   4929: invokestatic a : (Ljava/lang/Throwable;)Ljava/lang/Throwable;
    //   4932: athrow
    //   4933: aload #6
    //   4935: iload #10
    //   4937: baload
    //   4938: bipush #43
    //   4940: if_icmpne -> 4968
    //   4943: goto -> 4950
    //   4946: invokestatic a : (Ljava/lang/Throwable;)Ljava/lang/Throwable;
    //   4949: athrow
    //   4950: aload #6
    //   4952: iload #10
    //   4954: bipush #62
    //   4956: bastore
    //   4957: iload_2
    //   4958: ifeq -> 5141
    //   4961: goto -> 4968
    //   4964: invokestatic a : (Ljava/lang/Throwable;)Ljava/lang/Throwable;
    //   4967: athrow
    //   4968: aload #6
    //   4970: iload #10
    //   4972: baload
    //   4973: bipush #48
    //   4975: if_icmplt -> 5027
    //   4978: goto -> 4985
    //   4981: invokestatic a : (Ljava/lang/Throwable;)Ljava/lang/Throwable;
    //   4984: athrow
    //   4985: aload #6
    //   4987: iload #10
    //   4989: baload
    //   4990: bipush #57
    //   4992: if_icmpgt -> 5027
    //   4995: goto -> 5002
    //   4998: invokestatic a : (Ljava/lang/Throwable;)Ljava/lang/Throwable;
    //   5001: athrow
    //   5002: aload #6
    //   5004: iload #10
    //   5006: aload #6
    //   5008: iload #10
    //   5010: baload
    //   5011: bipush #-4
    //   5013: isub
    //   5014: i2b
    //   5015: bastore
    //   5016: iload_2
    //   5017: ifeq -> 5141
    //   5020: goto -> 5027
    //   5023: invokestatic a : (Ljava/lang/Throwable;)Ljava/lang/Throwable;
    //   5026: athrow
    //   5027: aload #6
    //   5029: iload #10
    //   5031: baload
    //   5032: bipush #97
    //   5034: if_icmplt -> 5086
    //   5037: goto -> 5044
    //   5040: invokestatic a : (Ljava/lang/Throwable;)Ljava/lang/Throwable;
    //   5043: athrow
    //   5044: aload #6
    //   5046: iload #10
    //   5048: baload
    //   5049: bipush #122
    //   5051: if_icmpgt -> 5086
    //   5054: goto -> 5061
    //   5057: invokestatic a : (Ljava/lang/Throwable;)Ljava/lang/Throwable;
    //   5060: athrow
    //   5061: aload #6
    //   5063: iload #10
    //   5065: aload #6
    //   5067: iload #10
    //   5069: baload
    //   5070: bipush #71
    //   5072: isub
    //   5073: i2b
    //   5074: bastore
    //   5075: iload_2
    //   5076: ifeq -> 5141
    //   5079: goto -> 5086
    //   5082: invokestatic a : (Ljava/lang/Throwable;)Ljava/lang/Throwable;
    //   5085: athrow
    //   5086: aload #6
    //   5088: iload #10
    //   5090: baload
    //   5091: bipush #65
    //   5093: if_icmplt -> 5141
    //   5096: goto -> 5103
    //   5099: invokestatic a : (Ljava/lang/Throwable;)Ljava/lang/Throwable;
    //   5102: athrow
    //   5103: aload #6
    //   5105: iload #10
    //   5107: baload
    //   5108: bipush #90
    //   5110: if_icmpgt -> 5141
    //   5113: goto -> 5120
    //   5116: invokestatic a : (Ljava/lang/Throwable;)Ljava/lang/Throwable;
    //   5119: athrow
    //   5120: aload #6
    //   5122: iload #10
    //   5124: aload #6
    //   5126: iload #10
    //   5128: baload
    //   5129: bipush #65
    //   5131: isub
    //   5132: i2b
    //   5133: bastore
    //   5134: goto -> 5141
    //   5137: invokestatic a : (Ljava/lang/Throwable;)Ljava/lang/Throwable;
    //   5140: athrow
    //   5141: iinc #10, 1
    //   5144: iload_2
    //   5145: ifeq -> 4863
    //   5148: iconst_0
    //   5149: istore #10
    //   5151: iconst_0
    //   5152: istore #11
    //   5154: iload #11
    //   5156: aload #9
    //   5158: arraylength
    //   5159: iconst_2
    //   5160: isub
    //   5161: if_icmpge -> 5270
    //   5164: aload #9
    //   5166: iload #11
    //   5168: aload #6
    //   5170: iload #10
    //   5172: baload
    //   5173: iconst_2
    //   5174: ishl
    //   5175: sipush #255
    //   5178: iand
    //   5179: aload #6
    //   5181: iload #10
    //   5183: iconst_1
    //   5184: iadd
    //   5185: baload
    //   5186: iconst_4
    //   5187: iushr
    //   5188: iconst_3
    //   5189: iand
    //   5190: ior
    //   5191: i2b
    //   5192: bastore
    //   5193: aload #9
    //   5195: iload #11
    //   5197: iconst_1
    //   5198: iadd
    //   5199: aload #6
    //   5201: iload #10
    //   5203: iconst_1
    //   5204: iadd
    //   5205: baload
    //   5206: iconst_4
    //   5207: ishl
    //   5208: sipush #255
    //   5211: iand
    //   5212: aload #6
    //   5214: iload #10
    //   5216: iconst_2
    //   5217: iadd
    //   5218: baload
    //   5219: iconst_2
    //   5220: iushr
    //   5221: bipush #15
    //   5223: iand
    //   5224: ior
    //   5225: i2b
    //   5226: bastore
    //   5227: aload #9
    //   5229: iload #11
    //   5231: iconst_2
    //   5232: iadd
    //   5233: aload #6
    //   5235: iload #10
    //   5237: iconst_2
    //   5238: iadd
    //   5239: baload
    //   5240: bipush #6
    //   5242: ishl
    //   5243: sipush #255
    //   5246: iand
    //   5247: aload #6
    //   5249: iload #10
    //   5251: iconst_3
    //   5252: iadd
    //   5253: baload
    //   5254: bipush #63
    //   5256: iand
    //   5257: ior
    //   5258: i2b
    //   5259: bastore
    //   5260: iinc #10, 4
    //   5263: iinc #11, 3
    //   5266: iload_2
    //   5267: ifeq -> 5154
    //   5270: iload #11
    //   5272: aload #9
    //   5274: arraylength
    //   5275: if_icmpge -> 5314
    //   5278: aload #9
    //   5280: iload #11
    //   5282: aload #6
    //   5284: iload #10
    //   5286: baload
    //   5287: iconst_2
    //   5288: ishl
    //   5289: sipush #255
    //   5292: iand
    //   5293: aload #6
    //   5295: iload #10
    //   5297: iconst_1
    //   5298: iadd
    //   5299: baload
    //   5300: iconst_4
    //   5301: iushr
    //   5302: iconst_3
    //   5303: iand
    //   5304: ior
    //   5305: i2b
    //   5306: bastore
    //   5307: goto -> 5314
    //   5310: invokestatic a : (Ljava/lang/Throwable;)Ljava/lang/Throwable;
    //   5313: athrow
    //   5314: iinc #11, 1
    //   5317: iload #11
    //   5319: aload #9
    //   5321: arraylength
    //   5322: if_icmpge -> 5364
    //   5325: aload #9
    //   5327: iload #11
    //   5329: aload #6
    //   5331: iload #10
    //   5333: iconst_1
    //   5334: iadd
    //   5335: baload
    //   5336: iconst_4
    //   5337: ishl
    //   5338: sipush #255
    //   5341: iand
    //   5342: aload #6
    //   5344: iload #10
    //   5346: iconst_2
    //   5347: iadd
    //   5348: baload
    //   5349: iconst_2
    //   5350: iushr
    //   5351: bipush #15
    //   5353: iand
    //   5354: ior
    //   5355: i2b
    //   5356: bastore
    //   5357: goto -> 5364
    //   5360: invokestatic a : (Ljava/lang/Throwable;)Ljava/lang/Throwable;
    //   5363: athrow
    //   5364: aload #9
    //   5366: astore #7
    //   5368: getstatic burp/Zk8f.ZV : Ljava/lang/String;
    //   5371: getstatic burp/Zvh.Zb : Ljava/lang/Object;
    //   5374: checkcast java/math/BigInteger
    //   5377: invokevirtual intValue : ()I
    //   5380: bipush #32
    //   5382: irem
    //   5383: invokestatic abs : (I)I
    //   5386: invokevirtual charAt : (I)C
    //   5389: getstatic burp/Zmui.ZY : Ljava/lang/String;
    //   5392: getstatic burp/Zzre.ZE : Ljava/lang/Object;
    //   5395: checkcast java/math/BigInteger
    //   5398: invokevirtual intValue : ()I
    //   5401: bipush #32
    //   5403: irem
    //   5404: invokestatic abs : (I)I
    //   5407: invokevirtual charAt : (I)C
    //   5410: if_icmpgt -> 5525
    //   5413: getstatic burp/Zxdy.Zm : Ljava/lang/String;
    //   5416: getstatic burp/Zm83.Zl : Ljava/lang/Object;
    //   5419: checkcast java/math/BigInteger
    //   5422: invokevirtual intValue : ()I
    //   5425: bipush #32
    //   5427: irem
    //   5428: invokestatic abs : (I)I
    //   5431: invokevirtual charAt : (I)C
    //   5434: getstatic burp/Zz7m.Zq : Ljava/lang/String;
    //   5437: getstatic burp/Zxzv.Zg : Ljava/lang/Object;
    //   5440: checkcast java/math/BigInteger
    //   5443: invokevirtual intValue : ()I
    //   5446: bipush #32
    //   5448: irem
    //   5449: invokestatic abs : (I)I
    //   5452: invokevirtual charAt : (I)C
    //   5455: if_icmple -> 5525
    //   5458: goto -> 5465
    //   5461: invokestatic a : (Ljava/lang/Throwable;)Ljava/lang/Throwable;
    //   5464: athrow
    //   5465: getstatic burp/Zt4p.ZL : Ljava/lang/String;
    //   5468: getstatic burp/Zb3r.ZI : Ljava/lang/Object;
    //   5471: checkcast java/math/BigInteger
    //   5474: invokevirtual intValue : ()I
    //   5477: bipush #32
    //   5479: irem
    //   5480: invokestatic abs : (I)I
    //   5483: invokevirtual charAt : (I)C
    //   5486: getstatic burp/Zrww.ZV : Ljava/lang/String;
    //   5489: getstatic burp/Zrnk.ZM : Ljava/lang/Object;
    //   5492: checkcast java/math/BigInteger
    //   5495: invokevirtual intValue : ()I
    //   5498: bipush #32
    //   5500: irem
    //   5501: invokestatic abs : (I)I
    //   5504: invokevirtual charAt : (I)C
    //   5507: if_icmpgt -> 5525
    //   5510: goto -> 5517
    //   5513: invokestatic a : (Ljava/lang/Throwable;)Ljava/lang/Throwable;
    //   5516: athrow
    //   5517: iconst_1
    //   5518: goto -> 5526
    //   5521: invokestatic a : (Ljava/lang/Throwable;)Ljava/lang/Throwable;
    //   5524: athrow
    //   5525: iconst_0
    //   5526: ireturn
    //   5527: astore_3
    //   5528: new java/lang/Exception
    //   5531: dup
    //   5532: aload_3
    //   5533: invokevirtual getMessage : ()Ljava/lang/String;
    //   5536: invokespecial <init> : (Ljava/lang/String;)V
    //   5539: athrow
    // Exception table:
    //   from	to	target	type
    //   4	5526	5527	java/lang/Throwable
    //   22	198	201	java/lang/Throwable
    //   168	235	238	java/lang/Throwable
    //   205	272	275	java/lang/Throwable
    //   242	309	312	java/lang/Throwable
    //   279	346	349	java/lang/Throwable
    //   316	383	386	java/lang/Throwable
    //   353	420	423	java/lang/Throwable
    //   390	457	460	java/lang/Throwable
    //   427	494	497	java/lang/Throwable
    //   464	531	534	java/lang/Throwable
    //   501	568	571	java/lang/Throwable
    //   538	605	608	java/lang/Throwable
    //   575	642	645	java/lang/Throwable
    //   612	679	682	java/lang/Throwable
    //   649	716	719	java/lang/Throwable
    //   686	753	756	java/lang/Throwable
    //   723	790	793	java/lang/Throwable
    //   760	827	830	java/lang/Throwable
    //   797	864	867	java/lang/Throwable
    //   834	901	904	java/lang/Throwable
    //   871	938	941	java/lang/Throwable
    //   908	975	978	java/lang/Throwable
    //   945	1012	1015	java/lang/Throwable
    //   982	1049	1052	java/lang/Throwable
    //   1019	1086	1089	java/lang/Throwable
    //   1056	1123	1126	java/lang/Throwable
    //   1093	1160	1163	java/lang/Throwable
    //   1130	1197	1200	java/lang/Throwable
    //   1167	1234	1237	java/lang/Throwable
    //   1204	1271	1274	java/lang/Throwable
    //   1241	1308	1311	java/lang/Throwable
    //   1278	1341	1344	java/lang/Throwable
    //   1381	1555	1558	java/lang/Throwable
    //   1524	1593	1596	java/lang/Throwable
    //   1562	1631	1634	java/lang/Throwable
    //   1600	1669	1672	java/lang/Throwable
    //   1638	1707	1710	java/lang/Throwable
    //   1676	1745	1748	java/lang/Throwable
    //   1714	1783	1786	java/lang/Throwable
    //   1752	1821	1824	java/lang/Throwable
    //   1790	1859	1862	java/lang/Throwable
    //   1828	1897	1900	java/lang/Throwable
    //   1866	1935	1938	java/lang/Throwable
    //   1904	1973	1976	java/lang/Throwable
    //   1942	2011	2014	java/lang/Throwable
    //   1980	2049	2052	java/lang/Throwable
    //   2018	2087	2090	java/lang/Throwable
    //   2056	2125	2128	java/lang/Throwable
    //   2094	2163	2166	java/lang/Throwable
    //   2132	2201	2204	java/lang/Throwable
    //   2170	2239	2242	java/lang/Throwable
    //   2208	2277	2280	java/lang/Throwable
    //   2246	2315	2318	java/lang/Throwable
    //   2284	2353	2356	java/lang/Throwable
    //   2322	2391	2394	java/lang/Throwable
    //   2360	2429	2432	java/lang/Throwable
    //   2398	2467	2470	java/lang/Throwable
    //   2436	2505	2508	java/lang/Throwable
    //   2474	2543	2546	java/lang/Throwable
    //   2512	2581	2584	java/lang/Throwable
    //   2550	2619	2622	java/lang/Throwable
    //   2588	2657	2660	java/lang/Throwable
    //   2626	2695	2698	java/lang/Throwable
    //   2664	2729	2732	java/lang/Throwable
    //   2770	2947	2950	java/lang/Throwable
    //   2916	2985	2988	java/lang/Throwable
    //   2954	3023	3026	java/lang/Throwable
    //   2992	3061	3064	java/lang/Throwable
    //   3030	3099	3102	java/lang/Throwable
    //   3068	3137	3140	java/lang/Throwable
    //   3106	3175	3178	java/lang/Throwable
    //   3144	3213	3216	java/lang/Throwable
    //   3182	3251	3254	java/lang/Throwable
    //   3220	3289	3292	java/lang/Throwable
    //   3258	3327	3330	java/lang/Throwable
    //   3296	3365	3368	java/lang/Throwable
    //   3334	3403	3406	java/lang/Throwable
    //   3372	3441	3444	java/lang/Throwable
    //   3410	3479	3482	java/lang/Throwable
    //   3448	3517	3520	java/lang/Throwable
    //   3486	3555	3558	java/lang/Throwable
    //   3524	3593	3596	java/lang/Throwable
    //   3562	3631	3634	java/lang/Throwable
    //   3600	3669	3672	java/lang/Throwable
    //   3638	3707	3710	java/lang/Throwable
    //   3676	3745	3748	java/lang/Throwable
    //   3714	3783	3786	java/lang/Throwable
    //   3752	3821	3824	java/lang/Throwable
    //   3790	3859	3862	java/lang/Throwable
    //   3828	3897	3900	java/lang/Throwable
    //   3866	3935	3938	java/lang/Throwable
    //   3904	3973	3976	java/lang/Throwable
    //   3942	4011	4014	java/lang/Throwable
    //   3980	4049	4052	java/lang/Throwable
    //   4018	4087	4090	java/lang/Throwable
    //   4056	4121	4124	java/lang/Throwable
    //   4188	4202	4202	java/lang/Throwable
    //   4213	4226	4229	java/lang/Throwable
    //   4218	4241	4244	java/lang/Throwable
    //   4233	4259	4262	java/lang/Throwable
    //   4248	4289	4292	java/lang/Throwable
    //   4355	4382	4385	java/lang/Throwable
    //   4372	4403	4406	java/lang/Throwable
    //   4389	4433	4436	java/lang/Throwable
    //   4410	4444	4444	java/lang/Throwable
    //   4455	4471	4474	java/lang/Throwable
    //   4510	4524	4527	java/lang/Throwable
    //   4517	4538	4541	java/lang/Throwable
    //   4531	4552	4555	java/lang/Throwable
    //   4545	4566	4569	java/lang/Throwable
    //   4559	4580	4583	java/lang/Throwable
    //   4573	4594	4597	java/lang/Throwable
    //   4587	4608	4611	java/lang/Throwable
    //   4601	4622	4625	java/lang/Throwable
    //   4615	4632	4635	java/lang/Throwable
    //   4673	4687	4690	java/lang/Throwable
    //   4680	4701	4704	java/lang/Throwable
    //   4694	4715	4718	java/lang/Throwable
    //   4708	4729	4732	java/lang/Throwable
    //   4722	4743	4746	java/lang/Throwable
    //   4736	4757	4760	java/lang/Throwable
    //   4750	4771	4774	java/lang/Throwable
    //   4764	4785	4788	java/lang/Throwable
    //   4778	4802	4805	java/lang/Throwable
    //   4871	4891	4894	java/lang/Throwable
    //   4881	4908	4911	java/lang/Throwable
    //   4898	4926	4929	java/lang/Throwable
    //   4915	4943	4946	java/lang/Throwable
    //   4933	4961	4964	java/lang/Throwable
    //   4950	4978	4981	java/lang/Throwable
    //   4968	4995	4998	java/lang/Throwable
    //   4985	5020	5023	java/lang/Throwable
    //   5002	5037	5040	java/lang/Throwable
    //   5027	5054	5057	java/lang/Throwable
    //   5044	5079	5082	java/lang/Throwable
    //   5061	5096	5099	java/lang/Throwable
    //   5086	5113	5116	java/lang/Throwable
    //   5103	5134	5137	java/lang/Throwable
    //   5270	5307	5310	java/lang/Throwable
    //   5314	5357	5360	java/lang/Throwable
    //   5368	5458	5461	java/lang/Throwable
    //   5413	5510	5513	java/lang/Throwable
    //   5465	5521	5521	java/lang/Throwable
  }
  
  static void Zs(Object paramObject) {
    Zeva.Zo = a(-9932, -31971);
    Zeva.Zf = new BigInteger(a(-9931, 419));
    boolean bool = Zt2e.ZK();
    try {
      try {
        if (Zxcn.ZF.charAt(Math.abs(((BigInteger)Zxcn.Zq).intValue() % 32)) > Zepy.Zg.charAt(Math.abs(((BigInteger)Zbnk.Zp).intValue() % 32))) {
          try {
            Ztd3.Zt(Class.forName(a(-9935, 4454)));
            if (bool)
              Zgsb.Zt(Class.forName(a(-9934, -9626))); 
          } catch (Throwable throwable) {
            throw a(null);
          } 
          return;
        } 
      } catch (Throwable throwable) {
        throw a(null);
      } 
      Zgsb.Zt(Class.forName(a(-9934, -9626)));
    } catch (Throwable throwable) {}
  }
  
  static void ZO(Object[] paramArrayOfObject, Object paramObject) throws Throwable {}
  
  static {
    // Byte code:
    //   0: bipush #8
    //   2: anewarray java/lang/String
    //   5: astore #5
    //   7: iconst_0
    //   8: istore_3
    //   9: ldc ''#7 \-Lx.O\\r=&{P-M#'k\\tOs@o[fS^,`s*R%vXi\\rEpj'k\\nT3'ot Ne7)-I\\b'woeh,u~^\\tpl\+B\\t;5)-\\r'
    //   11: dup
    //   12: astore_2
    //   13: invokevirtual length : ()I
    //   16: istore #4
    //   18: bipush #9
    //   20: istore_1
    //   21: iconst_m1
    //   22: istore_0
    //   23: bipush #16
    //   25: iinc #0, 1
    //   28: aload_2
    //   29: iload_0
    //   30: dup
    //   31: iload_1
    //   32: iadd
    //   33: invokevirtual substring : (II)Ljava/lang/String;
    //   36: iconst_m1
    //   37: goto -> 143
    //   40: aload #5
    //   42: swap
    //   43: iload_3
    //   44: iinc #3, 1
    //   47: swap
    //   48: aastore
    //   49: iload_0
    //   50: iload_1
    //   51: iadd
    //   52: dup
    //   53: istore_0
    //   54: iload #4
    //   56: if_icmpge -> 68
    //   59: aload_2
    //   60: iload_0
    //   61: invokevirtual charAt : (I)C
    //   64: istore_1
    //   65: goto -> 23
    //   68: ldc '2<:VD'
    //   70: dup
    //   71: astore_2
    //   72: invokevirtual length : ()I
    //   75: istore #4
    //   77: bipush #9
    //   79: istore_1
    //   80: iconst_m1
    //   81: istore_0
    //   82: bipush #25
    //   84: iinc #0, 1
    //   87: aload_2
    //   88: iload_0
    //   89: dup
    //   90: iload_1
    //   91: iadd
    //   92: invokevirtual substring : (II)Ljava/lang/String;
    //   95: iconst_0
    //   96: goto -> 143
    //   99: aload #5
    //   101: swap
    //   102: iload_3
    //   103: iinc #3, 1
    //   106: swap
    //   107: aastore
    //   108: iload_0
    //   109: iload_1
    //   110: iadd
    //   111: dup
    //   112: istore_0
    //   113: iload #4
    //   115: if_icmpge -> 127
    //   118: aload_2
    //   119: iload_0
    //   120: invokevirtual charAt : (I)C
    //   123: istore_1
    //   124: goto -> 82
    //   127: aload #5
    //   129: putstatic burp/Zr60.a : [Ljava/lang/String;
    //   132: bipush #8
    //   134: anewarray java/lang/String
    //   137: putstatic burp/Zr60.b : [Ljava/lang/String;
    //   140: goto -> 300
    //   143: dup_x2
    //   144: pop
    //   145: invokevirtual toCharArray : ()[C
    //   148: dup_x1
    //   149: arraylength
    //   150: dup_x2
    //   151: pop
    //   152: iconst_0
    //   153: istore #6
    //   155: dup2_x1
    //   156: pop2
    //   157: dup_x2
    //   158: iconst_1
    //   159: if_icmpgt -> 259
    //   162: dup2
    //   163: swap
    //   164: iload #6
    //   166: dup2_x1
    //   167: caload
    //   168: swap
    //   169: iload #6
    //   171: bipush #7
    //   173: irem
    //   174: tableswitch default -> 241, 0 -> 212, 1 -> 217, 2 -> 222, 3 -> 227, 4 -> 232, 5 -> 237
    //   212: bipush #114
    //   214: goto -> 243
    //   217: bipush #40
    //   219: goto -> 243
    //   222: bipush #82
    //   224: goto -> 243
    //   227: bipush #26
    //   229: goto -> 243
    //   232: bipush #75
    //   234: goto -> 243
    //   237: iconst_3
    //   238: goto -> 243
    //   241: bipush #58
    //   243: ixor
    //   244: ixor
    //   245: i2c
    //   246: castore
    //   247: iinc #6, 1
    //   250: dup
    //   251: ifne -> 259
    //   254: dup2
    //   255: dup_x1
    //   256: goto -> 166
    //   259: dup2_x1
    //   260: pop2
    //   261: dup_x2
    //   262: iload #6
    //   264: if_icmpgt -> 162
    //   267: pop
    //   268: new java/lang/String
    //   271: dup_x1
    //   272: swap
    //   273: invokespecial <init> : ([C)V
    //   276: invokevirtual intern : ()Ljava/lang/String;
    //   279: swap
    //   280: pop
    //   281: swap
    //   282: tableswitch default -> 40, 0 -> 99
    //   300: new java/math/BigInteger
    //   303: dup
    //   304: iconst_1
    //   305: bipush #32
    //   307: newarray byte
    //   309: dup
    //   310: iconst_0
    //   311: bipush #93
    //   313: bastore
    //   314: dup
    //   315: iconst_1
    //   316: iconst_1
    //   317: bastore
    //   318: dup
    //   319: iconst_2
    //   320: bipush #-39
    //   322: bastore
    //   323: dup
    //   324: iconst_3
    //   325: bipush #98
    //   327: bastore
    //   328: dup
    //   329: iconst_4
    //   330: bipush #47
    //   332: bastore
    //   333: dup
    //   334: iconst_5
    //   335: bipush #90
    //   337: bastore
    //   338: dup
    //   339: bipush #6
    //   341: bipush #-68
    //   343: bastore
    //   344: dup
    //   345: bipush #7
    //   347: bipush #-80
    //   349: bastore
    //   350: dup
    //   351: bipush #8
    //   353: bipush #61
    //   355: bastore
    //   356: dup
    //   357: bipush #9
    //   359: bipush #-42
    //   361: bastore
    //   362: dup
    //   363: bipush #10
    //   365: bipush #-101
    //   367: bastore
    //   368: dup
    //   369: bipush #11
    //   371: bipush #-59
    //   373: bastore
    //   374: dup
    //   375: bipush #12
    //   377: bipush #123
    //   379: bastore
    //   380: dup
    //   381: bipush #13
    //   383: bipush #66
    //   385: bastore
    //   386: dup
    //   387: bipush #14
    //   389: bipush #-83
    //   391: bastore
    //   392: dup
    //   393: bipush #15
    //   395: bipush #-65
    //   397: bastore
    //   398: dup
    //   399: bipush #16
    //   401: bipush #-26
    //   403: bastore
    //   404: dup
    //   405: bipush #17
    //   407: bipush #-115
    //   409: bastore
    //   410: dup
    //   411: bipush #18
    //   413: bipush #-86
    //   415: bastore
    //   416: dup
    //   417: bipush #19
    //   419: bipush #45
    //   421: bastore
    //   422: dup
    //   423: bipush #20
    //   425: bipush #56
    //   427: bastore
    //   428: dup
    //   429: bipush #21
    //   431: bipush #-90
    //   433: bastore
    //   434: dup
    //   435: bipush #22
    //   437: bipush #19
    //   439: bastore
    //   440: dup
    //   441: bipush #23
    //   443: bipush #-39
    //   445: bastore
    //   446: dup
    //   447: bipush #24
    //   449: bipush #-60
    //   451: bastore
    //   452: dup
    //   453: bipush #25
    //   455: bipush #91
    //   457: bastore
    //   458: dup
    //   459: bipush #26
    //   461: bipush #-94
    //   463: bastore
    //   464: dup
    //   465: bipush #27
    //   467: bipush #22
    //   469: bastore
    //   470: dup
    //   471: bipush #28
    //   473: bipush #-64
    //   475: bastore
    //   476: dup
    //   477: bipush #29
    //   479: bipush #108
    //   481: bastore
    //   482: dup
    //   483: bipush #30
    //   485: bipush #60
    //   487: bastore
    //   488: dup
    //   489: bipush #31
    //   491: bipush #27
    //   493: bastore
    //   494: invokespecial <init> : (I[B)V
    //   497: putstatic burp/Zr60.Ze : Ljava/lang/Object;
    //   500: sipush #-9930
    //   503: sipush #-26229
    //   506: invokestatic a : (II)Ljava/lang/String;
    //   509: putstatic burp/Zr60.ZQ : Ljava/lang/String;
    //   512: return
  }
  
  private static Throwable a(Throwable paramThrowable) {
    return paramThrowable;
  }
  
  private static String a(int paramInt1, int paramInt2) {
    int i = (paramInt1 ^ 0xFFFFD937) & 0xFFFF;
    if (b[i] == null) {
      char[] arrayOfChar = a[i].toCharArray();
      switch (arrayOfChar[0] & 0xFF) {
        case 0:
        
        case 1:
        
        case 2:
        
        case 3:
        
        case 4:
        
        case 5:
        
        case 6:
        
        case 7:
        
        case 8:
        
        case 9:
        
        case 10:
        
        case 11:
        
        case 12:
        
        case 13:
        
        case 14:
        
        case 15:
        
        case 16:
        
        case 17:
        
        case 18:
        
        case 19:
        
        case 20:
        
        case 21:
        
        case 22:
        
        case 23:
        
        case 24:
        
        case 25:
        
        case 26:
        
        case 27:
        
        case 28:
        
        case 29:
        
        case 30:
        
        case 31:
        
        case 32:
        
        case 33:
        
        case 34:
        
        case 35:
        
        case 36:
        
        case 37:
        
        case 38:
        
        case 39:
        
        case 40:
        
        case 41:
        
        case 42:
        
        case 43:
        
        case 44:
        
        case 45:
        
        case 46:
        
        case 47:
        
        case 48:
        
        case 49:
        
        case 50:
        
        case 51:
        
        case 52:
        
        case 53:
        
        case 54:
        
        case 55:
        
        case 56:
        
        case 57:
        
        case 58:
        
        case 59:
        
        case 60:
        
        case 61:
        
        case 62:
        
        case 63:
        
        case 64:
        
        case 65:
        
        case 66:
        
        case 67:
        
        case 68:
        
        case 69:
        
        case 70:
        
        case 71:
        
        case 72:
        
        case 73:
        
        case 74:
        
        case 75:
        
        case 76:
        
        case 77:
        
        case 78:
        
        case 79:
        
        case 80:
        
        case 81:
        
        case 82:
        
        case 83:
        
        case 84:
        
        case 85:
        
        case 86:
        
        case 87:
        
        case 88:
        
        case 89:
        
        case 90:
        
        case 91:
        
        case 92:
        
        case 93:
        
        case 94:
        
        case 95:
        
        case 96:
        
        case 97:
        
        case 98:
        
        case 99:
        
        case 100:
        
        case 101:
        
        case 102:
        
        case 103:
        
        case 104:
        
        case 105:
        
        case 106:
        
        case 107:
        
        case 108:
        
        case 109:
        
        case 110:
        
        case 111:
        
        case 112:
        
        case 113:
        
        case 114:
        
        case 115:
        
        case 116:
        
        case 117:
        
        case 118:
        
        case 119:
        
        case 120:
        
        case 121:
        
        case 122:
        
        case 123:
        
        case 124:
        
        case 125:
        
        case 126:
        
        case 127:
        
        case 128:
        
        case 129:
        
        case 130:
        
        case 131:
        
        case 132:
        
        case 133:
        
        case 134:
        
        case 135:
        
        case 136:
        
        case 137:
        
        case 138:
        
        case 139:
        
        case 140:
        
        case 141:
        
        case 142:
        
        case 143:
        
        case 144:
        
        case 145:
        
        case 146:
        
        case 147:
        
        case 148:
        
        case 149:
        
        case 150:
        
        case 151:
        
        case 152:
        
        case 153:
        
        case 154:
        
        case 155:
        
        case 156:
        
        case 157:
        
        case 158:
        
        case 159:
        
        case 160:
        
        case 161:
        
        case 162:
        
        case 163:
        
        case 164:
        
        case 165:
        
        case 166:
        
        case 167:
        
        case 168:
        
        case 169:
        
        case 170:
        
        case 171:
        
        case 172:
        
        case 173:
        
        case 174:
        
        case 175:
        
        case 176:
        
        case 177:
        
        case 178:
        
        case 179:
        
        case 180:
        
        case 181:
        
        case 182:
        
        case 183:
        
        case 184:
        
        case 185:
        
        case 186:
        
        case 187:
        
        case 188:
        
        case 189:
        
        case 190:
        
        case 191:
        
        case 192:
        
        case 193:
        
        case 194:
        
        case 195:
        
        case 196:
        
        case 197:
        
        case 198:
        
        case 199:
        
        case 200:
        
        case 201:
        
        case 202:
        
        case 203:
        
        case 204:
        
        case 205:
        
        case 206:
        
        case 207:
        
        case 208:
        
        case 209:
        
        case 210:
        
        case 211:
        
        case 212:
        
        case 213:
        
        case 214:
        
        case 215:
        
        case 216:
        
        case 217:
        
        case 218:
        
        case 219:
        
        case 220:
        
        case 221:
        
        case 222:
        
        case 223:
        
        case 224:
        
        case 225:
        
        case 226:
        
        case 227:
        
        case 228:
        
        case 229:
        
        case 230:
        
        case 231:
        
        case 232:
        
        case 233:
        
        case 234:
        
        case 235:
        
        case 236:
        
        case 237:
        
        case 238:
        
        case 239:
        
        case 240:
        
        case 241:
        
        case 242:
        
        case 243:
        
        case 244:
        
        case 245:
        
        case 246:
        
        case 247:
        
        case 248:
        
        case 249:
        
        case 250:
        
        case 251:
        
        case 252:
        
        case 253:
        
        case 254:
        
        default:
          break;
      } 
      byte b1 = 33;
      int j = (paramInt2 & 0xFF) - b1;
      if (j < 0)
        j += 256; 
      int k = ((paramInt2 & 0xFFFF) >>> 8) - b1;
      if (k < 0)
        k += 256; 
      for (byte b2 = 0; b2 < arrayOfChar.length; b2++) {
        int m = b2 % 2;
        if (m == 0) {
          arrayOfChar[b2] = (char)(arrayOfChar[b2] ^ j);
          j = ((j >>> 3 | j << 5) ^ arrayOfChar[b2]) & 0xFF;
        } else {
          arrayOfChar[b2] = (char)(arrayOfChar[b2] ^ k);
          k = ((k >>> 3 | k << 5) ^ arrayOfChar[b2]) & 0xFF;
        } 
      } 
      b[i] = (new String(arrayOfChar)).intern();
    } 
    return b[i];
  }
}


/* Location:              C:\Program Files\BurpSuitePro\burpsuite_pro.jar!\burp\Zr60.class
 * Java compiler version: 21 (65.0)
 * JD-Core Version:       1.1.3
 */