package burp;

import java.awt.Color;
import java.awt.Dimension;
import java.awt.Font;
import java.awt.GridBagConstraints;
import java.awt.GridBagLayout;
import java.awt.Insets;
import java.awt.Window;
import java.awt.event.ActionEvent;
import java.util.concurrent.atomic.AtomicBoolean;
import javax.swing.BorderFactory;
import javax.swing.Box;

public class Zr7_ extends Zrh7 {
  private final AtomicBoolean ZZ = new AtomicBoolean(false);
  
  private Ze01 Zg;
  
  private Ze01 ZG;
  
  private Box.Filler ZE;
  
  private Zm99 ZR;
  
  private Zm99 Zr;
  
  private Zm99 Zv;
  
  private Zbqc ZU;
  
  private Zbqc ZD;
  
  private static int Zi;
  
  private static final String[] a;
  
  private static final String[] b;
  
  private Zr7_(Window paramWindow) {
    super((Window)null, true, Zzv7.SAVE_ATTACK_TO_PROJECT_FILE_DIALOG);
    Zm();
    setAlwaysOnTop(true);
    this.Zg.addActionListener(this::lambda$new$0);
    this.ZG.addActionListener(this::lambda$new$1);
    addWindowListener(new Zrfo(this));
    pack();
    Zq(paramWindow);
  }
  
  public static boolean ZX(Window paramWindow) {
    Zr7_ zr7_ = new Zr7_(paramWindow);
    zr7_.setVisible(true);
    int i = Zu();
    if (Zbqc.Zwu() == null)
      ZT(++i); 
    return zr7_.ZA();
  }
  
  public void Zc() {
    setVisible(false);
    dispose();
  }
  
  public boolean ZA() {
    return this.ZZ.get();
  }
  
  private void Zm() {
    this.ZD = new Zbqc();
    this.Zv = new Zm99();
    this.Zr = new Zm99();
    this.ZR = new Zm99();
    this.ZU = new Zbqc();
    this.Zg = new Ze01();
    this.ZG = new Ze01();
    this.ZE = new Box.Filler(new Dimension(0, 0), new Dimension(0, 0), new Dimension(32767, 0));
    setDefaultCloseOperation(0);
    setTitle(a(-28060, -20066));
    setMinimumSize(new Dimension(500, 242));
    setResizable(false);
    getContentPane().setLayout(new GridBagLayout());
    this.ZD.setLayout(new GridBagLayout());
    this.Zv.setHorizontalAlignment(0);
    this.Zv.setText(a(-28063, 27321));
    this.Zv.setFont(new Font(a(-28059, 22689), 1, 18));
    GridBagConstraints gridBagConstraints = new GridBagConstraints();
    gridBagConstraints.gridx = 0;
    gridBagConstraints.gridy = 0;
    gridBagConstraints.fill = 2;
    gridBagConstraints.anchor = 18;
    gridBagConstraints.insets = new Insets(30, 55, 0, 55);
    this.ZD.add(this.Zv, gridBagConstraints);
    this.Zr.setHorizontalAlignment(0);
    this.Zr.setText(a(-28062, -22755));
    this.Zr.setFont(new Font(a(-28064, -4334), 0, 13));
    this.Zr.setMaximumSize(new Dimension(52, 30));
    gridBagConstraints = new GridBagConstraints();
    gridBagConstraints.gridx = 0;
    gridBagConstraints.gridy = 1;
    gridBagConstraints.fill = 2;
    gridBagConstraints.anchor = 18;
    gridBagConstraints.insets = new Insets(17, 52, 0, 52);
    this.ZD.add(this.Zr, gridBagConstraints);
    this.ZR.setText(a(-28058, -3586));
    this.ZR.setFont(new Font(a(-28064, -4334), 0, 13));
    gridBagConstraints = new GridBagConstraints();
    gridBagConstraints.gridx = 0;
    gridBagConstraints.gridy = 2;
    gridBagConstraints.fill = 2;
    gridBagConstraints.insets = new Insets(5, 52, 33, 52);
    this.ZD.add(this.ZR, gridBagConstraints);
    gridBagConstraints = new GridBagConstraints();
    gridBagConstraints.gridx = 0;
    gridBagConstraints.gridy = 0;
    gridBagConstraints.fill = 1;
    gridBagConstraints.weightx = 1.0D;
    getContentPane().add(this.ZD, gridBagConstraints);
    this.ZU.setBorder(BorderFactory.createMatteBorder(1, 0, 0, 0, new Color(79, 79, 80)));
    GridBagLayout gridBagLayout = new GridBagLayout();
    gridBagLayout.columnWidths = new int[] { 0, 10, 0, 10, 0 };
    gridBagLayout.rowHeights = new int[] { 0 };
    this.ZU.setLayout(gridBagLayout);
    this.Zg.setText(a(-28057, -10624));
    gridBagConstraints = new GridBagConstraints();
    gridBagConstraints.gridx = 4;
    gridBagConstraints.gridy = 0;
    gridBagConstraints.anchor = 18;
    gridBagConstraints.insets = new Insets(17, 0, 17, 15);
    this.ZU.add(this.Zg, gridBagConstraints);
    this.ZG.setText(a(-28061, 6401));
    gridBagConstraints = new GridBagConstraints();
    gridBagConstraints.gridx = 2;
    gridBagConstraints.gridy = 0;
    this.ZU.add(this.ZG, gridBagConstraints);
    gridBagConstraints = new GridBagConstraints();
    gridBagConstraints.gridx = 0;
    gridBagConstraints.gridy = 0;
    gridBagConstraints.fill = 2;
    gridBagConstraints.weightx = 1.0D;
    this.ZU.add(this.ZE, gridBagConstraints);
    gridBagConstraints = new GridBagConstraints();
    gridBagConstraints.gridx = 0;
    gridBagConstraints.gridy = 1;
    gridBagConstraints.fill = 2;
    getContentPane().add(this.ZU, gridBagConstraints);
  }
  
  private void lambda$new$1(ActionEvent paramActionEvent) {
    this.ZZ.compareAndSet(false, true);
    Zc();
  }
  
  private void lambda$new$0(ActionEvent paramActionEvent) {
    Zc();
  }
  
  public static void ZT(int paramInt) {
    Zi = paramInt;
  }
  
  public static int Zf() {
    return Zi;
  }
  
  public static int Zu() {
    int i = Zf();
    return (i == 0) ? 39 : 0;
  }
  
  static {
    // Byte code:
    //   0: bipush #8
    //   2: anewarray java/lang/String
    //   5: astore #5
    //   7: iconst_0
    //   8: istore_3
    //   9: ldc 'Ãµ?g@1ÃªP&}ÂYÃŒmÂÃ´Â…Ã®3Ã†Ã°Â½Â¦Ã²ÂŸ1ovTÂŸÂ ÂFÂ–Ã’Ã‡9u_nÃŸX\\thÂŒK7hÂ°ÃšÂ˜Ã¢*Â†ÃŸÂ€@3Ã­}Ã†\\tJÃµhÂ¯Ã¤\\fÃ–*Ã¡Â£@$Â¡Â¾Ã©SÂ”"Â’Â­Ã ÂšÃ»lC0Â§3ÃŠÂ†Ã›k+Ã¼p)Ã­Ã–B:A:Â™EgÂ—dÂ¯P.^Â”Ã¢%ÂÃ¢|ÂŸ3Ã†Q-f\\rn|Ã˜Ã¹j\\tÂ£ÃÃ‘ÃƒÃºÂ”ÂÂ­\\nV$ÃÃˆMÃ½kÃŠÃ‚Â„rÃ¿\\tÃ¤jÂ©Ã±}'Â°/'
    //   11: dup
    //   12: astore_2
    //   13: invokevirtual length : ()I
    //   16: istore #4
    //   18: iconst_0
    //   19: bipush #54
    //   21: istore_1
    //   22: invokestatic ZT : (I)V
    //   25: iconst_m1
    //   26: istore_0
    //   27: bipush #97
    //   29: iinc #0, 1
    //   32: aload_2
    //   33: iload_0
    //   34: dup
    //   35: iload_1
    //   36: iadd
    //   37: invokevirtual substring : (II)Ljava/lang/String;
    //   40: iconst_m1
    //   41: goto -> 147
    //   44: aload #5
    //   46: swap
    //   47: iload_3
    //   48: iinc #3, 1
    //   51: swap
    //   52: aastore
    //   53: iload_0
    //   54: iload_1
    //   55: iadd
    //   56: dup
    //   57: istore_0
    //   58: iload #4
    //   60: if_icmpge -> 72
    //   63: aload_2
    //   64: iload_0
    //   65: invokevirtual charAt : (I)C
    //   68: istore_1
    //   69: goto -> 27
    //   72: ldc 's{Ãª\Â»Ã¬Â€Ã¯ÃˆkÃ…?R6Â„iÃµ_=iÂ…Ã¸Ãª,ÂŽ\\f&^ÂÃª'
    //   74: dup
    //   75: astore_2
    //   76: invokevirtual length : ()I
    //   79: istore #4
    //   81: bipush #6
    //   83: istore_1
    //   84: iconst_m1
    //   85: istore_0
    //   86: bipush #93
    //   88: iinc #0, 1
    //   91: aload_2
    //   92: iload_0
    //   93: dup
    //   94: iload_1
    //   95: iadd
    //   96: invokevirtual substring : (II)Ljava/lang/String;
    //   99: iconst_0
    //   100: goto -> 147
    //   103: aload #5
    //   105: swap
    //   106: iload_3
    //   107: iinc #3, 1
    //   110: swap
    //   111: aastore
    //   112: iload_0
    //   113: iload_1
    //   114: iadd
    //   115: dup
    //   116: istore_0
    //   117: iload #4
    //   119: if_icmpge -> 131
    //   122: aload_2
    //   123: iload_0
    //   124: invokevirtual charAt : (I)C
    //   127: istore_1
    //   128: goto -> 86
    //   131: aload #5
    //   133: putstatic burp/Zr7_.a : [Ljava/lang/String;
    //   136: bipush #8
    //   138: anewarray java/lang/String
    //   141: putstatic burp/Zr7_.b : [Ljava/lang/String;
    //   144: goto -> 304
    //   147: dup_x2
    //   148: pop
    //   149: invokevirtual toCharArray : ()[C
    //   152: dup_x1
    //   153: arraylength
    //   154: dup_x2
    //   155: pop
    //   156: iconst_0
    //   157: istore #6
    //   159: dup2_x1
    //   160: pop2
    //   161: dup_x2
    //   162: iconst_1
    //   163: if_icmpgt -> 264
    //   166: dup2
    //   167: swap
    //   168: iload #6
    //   170: dup2_x1
    //   171: caload
    //   172: swap
    //   173: iload #6
    //   175: bipush #7
    //   177: irem
    //   178: tableswitch default -> 246, 0 -> 216, 1 -> 221, 2 -> 226, 3 -> 231, 4 -> 236, 5 -> 241
    //   216: bipush #60
    //   218: goto -> 248
    //   221: bipush #124
    //   223: goto -> 248
    //   226: bipush #88
    //   228: goto -> 248
    //   231: bipush #98
    //   233: goto -> 248
    //   236: bipush #57
    //   238: goto -> 248
    //   241: bipush #91
    //   243: goto -> 248
    //   246: bipush #89
    //   248: ixor
    //   249: ixor
    //   250: i2c
    //   251: castore
    //   252: iinc #6, 1
    //   255: dup
    //   256: ifne -> 264
    //   259: dup2
    //   260: dup_x1
    //   261: goto -> 170
    //   264: dup2_x1
    //   265: pop2
    //   266: dup_x2
    //   267: iload #6
    //   269: if_icmpgt -> 166
    //   272: pop
    //   273: new java/lang/String
    //   276: dup_x1
    //   277: swap
    //   278: invokespecial <init> : ([C)V
    //   281: invokevirtual intern : ()Ljava/lang/String;
    //   284: swap
    //   285: pop
    //   286: swap
    //   287: tableswitch default -> 44, 0 -> 103
    //   304: return
  }
  
  private static String a(int paramInt1, int paramInt2) {
    int i = (paramInt1 ^ 0xFFFF9266) & 0xFFFF;
    if (b[i] == null) {
      char[] arrayOfChar = a[i].toCharArray();
      switch (arrayOfChar[0] & 0xFF) {
        case 0:
        
        case 1:
        
        case 2:
        
        case 3:
        
        case 4:
        
        case 5:
        
        case 6:
        
        case 7:
        
        case 8:
        
        case 9:
        
        case 10:
        
        case 11:
        
        case 12:
        
        case 13:
        
        case 14:
        
        case 15:
        
        case 16:
        
        case 17:
        
        case 18:
        
        case 19:
        
        case 20:
        
        case 21:
        
        case 22:
        
        case 23:
        
        case 24:
        
        case 25:
        
        case 26:
        
        case 27:
        
        case 28:
        
        case 29:
        
        case 30:
        
        case 31:
        
        case 32:
        
        case 33:
        
        case 34:
        
        case 35:
        
        case 36:
        
        case 37:
        
        case 38:
        
        case 39:
        
        case 40:
        
        case 41:
        
        case 42:
        
        case 43:
        
        case 44:
        
        case 45:
        
        case 46:
        
        case 47:
        
        case 48:
        
        case 49:
        
        case 50:
        
        case 51:
        
        case 52:
        
        case 53:
        
        case 54:
        
        case 55:
        
        case 56:
        
        case 57:
        
        case 58:
        
        case 59:
        
        case 60:
        
        case 61:
        
        case 62:
        
        case 63:
        
        case 64:
        
        case 65:
        
        case 66:
        
        case 67:
        
        case 68:
        
        case 69:
        
        case 70:
        
        case 71:
        
        case 72:
        
        case 73:
        
        case 74:
        
        case 75:
        
        case 76:
        
        case 77:
        
        case 78:
        
        case 79:
        
        case 80:
        
        case 81:
        
        case 82:
        
        case 83:
        
        case 84:
        
        case 85:
        
        case 86:
        
        case 87:
        
        case 88:
        
        case 89:
        
        case 90:
        
        case 91:
        
        case 92:
        
        case 93:
        
        case 94:
        
        case 95:
        
        case 96:
        
        case 97:
        
        case 98:
        
        case 99:
        
        case 100:
        
        case 101:
        
        case 102:
        
        case 103:
        
        case 104:
        
        case 105:
        
        case 106:
        
        case 107:
        
        case 108:
        
        case 109:
        
        case 110:
        
        case 111:
        
        case 112:
        
        case 113:
        
        case 114:
        
        case 115:
        
        case 116:
        
        case 117:
        
        case 118:
        
        case 119:
        
        case 120:
        
        case 121:
        
        case 122:
        
        case 123:
        
        case 124:
        
        case 125:
        
        case 126:
        
        case 127:
        
        case 128:
        
        case 129:
        
        case 130:
        
        case 131:
        
        case 132:
        
        case 133:
        
        case 134:
        
        case 135:
        
        case 136:
        
        case 137:
        
        case 138:
        
        case 139:
        
        case 140:
        
        case 141:
        
        case 142:
        
        case 143:
        
        case 144:
        
        case 145:
        
        case 146:
        
        case 147:
        
        case 148:
        
        case 149:
        
        case 150:
        
        case 151:
        
        case 152:
        
        case 153:
        
        case 154:
        
        case 155:
        
        case 156:
        
        case 157:
        
        case 158:
        
        case 159:
        
        case 160:
        
        case 161:
        
        case 162:
        
        case 163:
        
        case 164:
        
        case 165:
        
        case 166:
        
        case 167:
        
        case 168:
        
        case 169:
        
        case 170:
        
        case 171:
        
        case 172:
        
        case 173:
        
        case 174:
        
        case 175:
        
        case 176:
        
        case 177:
        
        case 178:
        
        case 179:
        
        case 180:
        
        case 181:
        
        case 182:
        
        case 183:
        
        case 184:
        
        case 185:
        
        case 186:
        
        case 187:
        
        case 188:
        
        case 189:
        
        case 190:
        
        case 191:
        
        case 192:
        
        case 193:
        
        case 194:
        
        case 195:
        
        case 196:
        
        case 197:
        
        case 198:
        
        case 199:
        
        case 200:
        
        case 201:
        
        case 202:
        
        case 203:
        
        case 204:
        
        case 205:
        
        case 206:
        
        case 207:
        
        case 208:
        
        case 209:
        
        case 210:
        
        case 211:
        
        case 212:
        
        case 213:
        
        case 214:
        
        case 215:
        
        case 216:
        
        case 217:
        
        case 218:
        
        case 219:
        
        case 220:
        
        case 221:
        
        case 222:
        
        case 223:
        
        case 224:
        
        case 225:
        
        case 226:
        
        case 227:
        
        case 228:
        
        case 229:
        
        case 230:
        
        case 231:
        
        case 232:
        
        case 233:
        
        case 234:
        
        case 235:
        
        case 236:
        
        case 237:
        
        case 238:
        
        case 239:
        
        case 240:
        
        case 241:
        
        case 242:
        
        case 243:
        
        case 244:
        
        case 245:
        
        case 246:
        
        case 247:
        
        case 248:
        
        case 249:
        
        case 250:
        
        case 251:
        
        case 252:
        
        case 253:
        
        case 254:
        
        default:
          break;
      } 
      byte b1 = 28;
      int j = (paramInt2 & 0xFF) - b1;
      if (j < 0)
        j += 256; 
      int k = ((paramInt2 & 0xFFFF) >>> 8) - b1;
      if (k < 0)
        k += 256; 
      for (byte b2 = 0; b2 < arrayOfChar.length; b2++) {
        int m = b2 % 2;
        if (m == 0) {
          arrayOfChar[b2] = (char)(arrayOfChar[b2] ^ j);
          j = ((j >>> 3 | j << 5) ^ arrayOfChar[b2]) & 0xFF;
        } else {
          arrayOfChar[b2] = (char)(arrayOfChar[b2] ^ k);
          k = ((k >>> 3 | k << 5) ^ arrayOfChar[b2]) & 0xFF;
        } 
      } 
      b[i] = (new String(arrayOfChar)).intern();
    } 
    return b[i];
  }
}


/* Location:              C:\Program Files\BurpSuitePro\burpsuite_pro.jar!\burp\Zr7_.class
 * Java compiler version: 21 (65.0)
 * JD-Core Version:       1.1.3
 */