package burp;

import java.awt.Component;
import java.awt.Dimension;
import java.util.List;
import java.util.Objects;
import javax.swing.SwingUtilities;

public class Zr7o extends Zrh5 implements Zb07 {
  private final Component ZV;
  
  private final List<Ztm_> ZQ;
  
  private static Zbqc[] Zi;
  
  private static final String[] c;
  
  private static final String[] d;
  
  public Zr7o(Component paramComponent, List<Ztm_> paramList) {
    super(SwingUtilities.getWindowAncestor(paramComponent));
    this.ZV = paramComponent;
    this.ZQ = paramList;
    setName(b(9979, -25794));
    Zbqc[] arrayOfZbqc = Z_z();
    setFocusable(true);
    setModal(false);
    for (Ztm_ ztm_ : paramList) {
      Zbqc zbqc = new Zbqc();
      Zbkr zbkr = new Zbkr(Zxc2.HORIZONTAL);
      zbkr.Za(b(9978, 32047), ztm_.Zcs(), ztm_.ZcW().Zlr(), false, ztm_.ZcN());
      zbqc.add(zbkr);
      ztm_.ZcW().Zq(this);
      Objects.requireNonNull(ztm_.ZcW());
      ZV(ztm_.Zcp().ZZ(), ztm_.Zc3(), ztm_.ZcW().Zlj(), zbqc, ztm_.ZcW().Zlh(), ztm_.ZcW()::Zly);
      if (arrayOfZbqc == null)
        break; 
    } 
    addComponentListener(new Zk0(this, paramList));
    pack();
    Zq(SwingUtilities.getWindowAncestor(paramComponent));
    Zo(new Zmta(this, paramList));
  }
  
  public void ZM(int paramInt) {
    Zo(((Ztm_)this.ZQ.get(paramInt)).Zcp().ZZ());
  }
  
  public void ZM(Zspz paramZspz) {
    this.ZQ.stream().filter(paramZspz::lambda$selectFilterPanel$0).map(Zr7o::lambda$selectFilterPanel$1).findFirst().ifPresent(this::Zo);
  }
  
  public void Zgx() {
    this.ZQ.forEach(Zr7o::lambda$updateUI$2);
  }
  
  public void Zgr() {
    this.ZQ.forEach(Zr7o::lambda$configChanged$3);
  }
  
  public void Zm(Zx0b paramZx0b, Runnable paramRunnable) {
    ZM(paramZx0b.Zw());
    Ztm_ ztm_ = this.ZQ.get(paramZx0b.Zw());
    paramZx0b.Ze(ztm_.ZcW());
    ZW(paramRunnable);
  }
  
  public void ZW(Runnable paramRunnable) {
    ZG(paramRunnable);
    Zq(SwingUtilities.getWindowAncestor(this.ZV));
    setMinimumSize(new Dimension(320, 240));
    setVisible(true);
  }
  
  public void Zgf() {
    setVisible(false);
  }
  
  public void ZgU() {
    Zk(Z_8());
  }
  
  protected boolean Z_8() {
    return Z_G().ZcW().Zly();
  }
  
  public Component Zgn() {
    return this;
  }
  
  protected void ZgN() {
    Z_9();
    super.ZgN();
  }
  
  protected void Z_9() {
    Z_G().ZcW().Zlm();
  }
  
  protected void Zgp() {
    if (Z_O())
      super.Zgp(); 
  }
  
  protected void ZgH() {
    if (Z_O())
      super.ZgH(); 
  }
  
  protected boolean Z_O() {
    return Z_G().ZcW().ZlN();
  }
  
  private Ztm_ Z_G() {
    return this.ZQ.stream().filter(this::lambda$getSelectedPanelMetadata$4).findFirst().orElseThrow();
  }
  
  private boolean lambda$getSelectedPanelMetadata$4(Ztm_ paramZtm_) {
    return paramZtm_.Zcp().ZZ().equals(Zgd());
  }
  
  private static void lambda$configChanged$3(Ztm_ paramZtm_) {
    paramZtm_.ZcW().Zt2();
  }
  
  private static void lambda$updateUI$2(Ztm_ paramZtm_) {
    paramZtm_.ZcW().Zlj().updateUI();
  }
  
  private static String lambda$selectFilterPanel$1(Ztm_ paramZtm_) {
    return paramZtm_.Zcp().ZZ();
  }
  
  private static boolean lambda$selectFilterPanel$0(Zspz paramZspz, Ztm_ paramZtm_) {
    return paramZtm_.ZcW().equals(paramZspz);
  }
  
  public static void ZH(Zbqc[] paramArrayOfZbqc) {
    Zi = paramArrayOfZbqc;
  }
  
  public static Zbqc[] Z_z() {
    return Zi;
  }
  
  static {
    // Byte code:
    //   0: iconst_2
    //   1: anewarray java/lang/String
    //   4: astore #5
    //   6: iconst_0
    //   7: istore_3
    //   8: iconst_5
    //   9: anewarray burp/Zbqc
    //   12: ldc 'ÃŒ]Â¬Ã•xÂ¹TÂ›Â”Â›,Ã£PÃ•Ã§?\\fhÃÃŠZcÃ”VÃªÃ£)'
    //   14: dup
    //   15: astore_2
    //   16: invokevirtual length : ()I
    //   19: istore #4
    //   21: invokestatic ZH : ([Lburp/Zbqc;)V
    //   24: bipush #18
    //   26: istore_1
    //   27: iconst_m1
    //   28: istore_0
    //   29: bipush #34
    //   31: iinc #0, 1
    //   34: aload_2
    //   35: iload_0
    //   36: dup
    //   37: iload_1
    //   38: iadd
    //   39: invokevirtual substring : (II)Ljava/lang/String;
    //   42: iconst_m1
    //   43: goto -> 89
    //   46: aload #5
    //   48: swap
    //   49: iload_3
    //   50: iinc #3, 1
    //   53: swap
    //   54: aastore
    //   55: iload_0
    //   56: iload_1
    //   57: iadd
    //   58: dup
    //   59: istore_0
    //   60: iload #4
    //   62: if_icmpge -> 74
    //   65: aload_2
    //   66: iload_0
    //   67: invokevirtual charAt : (I)C
    //   70: istore_1
    //   71: goto -> 29
    //   74: aload #5
    //   76: putstatic burp/Zr7o.c : [Ljava/lang/String;
    //   79: iconst_2
    //   80: anewarray java/lang/String
    //   83: putstatic burp/Zr7o.d : [Ljava/lang/String;
    //   86: goto -> 234
    //   89: dup_x2
    //   90: pop
    //   91: invokevirtual toCharArray : ()[C
    //   94: dup_x1
    //   95: arraylength
    //   96: dup_x2
    //   97: pop
    //   98: iconst_0
    //   99: istore #6
    //   101: dup2_x1
    //   102: pop2
    //   103: dup_x2
    //   104: iconst_1
    //   105: if_icmpgt -> 207
    //   108: dup2
    //   109: swap
    //   110: iload #6
    //   112: dup2_x1
    //   113: caload
    //   114: swap
    //   115: iload #6
    //   117: bipush #7
    //   119: irem
    //   120: tableswitch default -> 189, 0 -> 160, 1 -> 164, 2 -> 169, 3 -> 174, 4 -> 179, 5 -> 184
    //   160: iconst_1
    //   161: goto -> 191
    //   164: bipush #17
    //   166: goto -> 191
    //   169: bipush #71
    //   171: goto -> 191
    //   174: bipush #52
    //   176: goto -> 191
    //   179: bipush #93
    //   181: goto -> 191
    //   184: bipush #64
    //   186: goto -> 191
    //   189: bipush #85
    //   191: ixor
    //   192: ixor
    //   193: i2c
    //   194: castore
    //   195: iinc #6, 1
    //   198: dup
    //   199: ifne -> 207
    //   202: dup2
    //   203: dup_x1
    //   204: goto -> 112
    //   207: dup2_x1
    //   208: pop2
    //   209: dup_x2
    //   210: iload #6
    //   212: if_icmpgt -> 108
    //   215: pop
    //   216: new java/lang/String
    //   219: dup_x1
    //   220: swap
    //   221: invokespecial <init> : ([C)V
    //   224: invokevirtual intern : ()Ljava/lang/String;
    //   227: swap
    //   228: pop
    //   229: swap
    //   230: pop
    //   231: goto -> 46
    //   234: return
  }
  
  private static String b(int paramInt1, int paramInt2) {
    int i = (paramInt1 ^ 0x26FA) & 0xFFFF;
    if (d[i] == null) {
      char[] arrayOfChar = c[i].toCharArray();
      switch (arrayOfChar[0] & 0xFF) {
        case 0:
        
        case 1:
        
        case 2:
        
        case 3:
        
        case 4:
        
        case 5:
        
        case 6:
        
        case 7:
        
        case 8:
        
        case 9:
        
        case 10:
        
        case 11:
        
        case 12:
        
        case 13:
        
        case 14:
        
        case 15:
        
        case 16:
        
        case 17:
        
        case 18:
        
        case 19:
        
        case 20:
        
        case 21:
        
        case 22:
        
        case 23:
        
        case 24:
        
        case 25:
        
        case 26:
        
        case 27:
        
        case 28:
        
        case 29:
        
        case 30:
        
        case 31:
        
        case 32:
        
        case 33:
        
        case 34:
        
        case 35:
        
        case 36:
        
        case 37:
        
        case 38:
        
        case 39:
        
        case 40:
        
        case 41:
        
        case 42:
        
        case 43:
        
        case 44:
        
        case 45:
        
        case 46:
        
        case 47:
        
        case 48:
        
        case 49:
        
        case 50:
        
        case 51:
        
        case 52:
        
        case 53:
        
        case 54:
        
        case 55:
        
        case 56:
        
        case 57:
        
        case 58:
        
        case 59:
        
        case 60:
        
        case 61:
        
        case 62:
        
        case 63:
        
        case 64:
        
        case 65:
        
        case 66:
        
        case 67:
        
        case 68:
        
        case 69:
        
        case 70:
        
        case 71:
        
        case 72:
        
        case 73:
        
        case 74:
        
        case 75:
        
        case 76:
        
        case 77:
        
        case 78:
        
        case 79:
        
        case 80:
        
        case 81:
        
        case 82:
        
        case 83:
        
        case 84:
        
        case 85:
        
        case 86:
        
        case 87:
        
        case 88:
        
        case 89:
        
        case 90:
        
        case 91:
        
        case 92:
        
        case 93:
        
        case 94:
        
        case 95:
        
        case 96:
        
        case 97:
        
        case 98:
        
        case 99:
        
        case 100:
        
        case 101:
        
        case 102:
        
        case 103:
        
        case 104:
        
        case 105:
        
        case 106:
        
        case 107:
        
        case 108:
        
        case 109:
        
        case 110:
        
        case 111:
        
        case 112:
        
        case 113:
        
        case 114:
        
        case 115:
        
        case 116:
        
        case 117:
        
        case 118:
        
        case 119:
        
        case 120:
        
        case 121:
        
        case 122:
        
        case 123:
        
        case 124:
        
        case 125:
        
        case 126:
        
        case 127:
        
        case 128:
        
        case 129:
        
        case 130:
        
        case 131:
        
        case 132:
        
        case 133:
        
        case 134:
        
        case 135:
        
        case 136:
        
        case 137:
        
        case 138:
        
        case 139:
        
        case 140:
        
        case 141:
        
        case 142:
        
        case 143:
        
        case 144:
        
        case 145:
        
        case 146:
        
        case 147:
        
        case 148:
        
        case 149:
        
        case 150:
        
        case 151:
        
        case 152:
        
        case 153:
        
        case 154:
        
        case 155:
        
        case 156:
        
        case 157:
        
        case 158:
        
        case 159:
        
        case 160:
        
        case 161:
        
        case 162:
        
        case 163:
        
        case 164:
        
        case 165:
        
        case 166:
        
        case 167:
        
        case 168:
        
        case 169:
        
        case 170:
        
        case 171:
        
        case 172:
        
        case 173:
        
        case 174:
        
        case 175:
        
        case 176:
        
        case 177:
        
        case 178:
        
        case 179:
        
        case 180:
        
        case 181:
        
        case 182:
        
        case 183:
        
        case 184:
        
        case 185:
        
        case 186:
        
        case 187:
        
        case 188:
        
        case 189:
        
        case 190:
        
        case 191:
        
        case 192:
        
        case 193:
        
        case 194:
        
        case 195:
        
        case 196:
        
        case 197:
        
        case 198:
        
        case 199:
        
        case 200:
        
        case 201:
        
        case 202:
        
        case 203:
        
        case 204:
        
        case 205:
        
        case 206:
        
        case 207:
        
        case 208:
        
        case 209:
        
        case 210:
        
        case 211:
        
        case 212:
        
        case 213:
        
        case 214:
        
        case 215:
        
        case 216:
        
        case 217:
        
        case 218:
        
        case 219:
        
        case 220:
        
        case 221:
        
        case 222:
        
        case 223:
        
        case 224:
        
        case 225:
        
        case 226:
        
        case 227:
        
        case 228:
        
        case 229:
        
        case 230:
        
        case 231:
        
        case 232:
        
        case 233:
        
        case 234:
        
        case 235:
        
        case 236:
        
        case 237:
        
        case 238:
        
        case 239:
        
        case 240:
        
        case 241:
        
        case 242:
        
        case 243:
        
        case 244:
        
        case 245:
        
        case 246:
        
        case 247:
        
        case 248:
        
        case 249:
        
        case 250:
        
        case 251:
        
        case 252:
        
        case 253:
        
        case 254:
        
        default:
          break;
      } 
      char c = 'Ã‘';
      int j = (paramInt2 & 0xFF) - c;
      if (j < 0)
        j += 256; 
      int k = ((paramInt2 & 0xFFFF) >>> 8) - c;
      if (k < 0)
        k += 256; 
      for (byte b = 0; b < arrayOfChar.length; b++) {
        int m = b % 2;
        if (m == 0) {
          arrayOfChar[b] = (char)(arrayOfChar[b] ^ j);
          j = ((j >>> 3 | j << 5) ^ arrayOfChar[b]) & 0xFF;
        } else {
          arrayOfChar[b] = (char)(arrayOfChar[b] ^ k);
          k = ((k >>> 3 | k << 5) ^ arrayOfChar[b]) & 0xFF;
        } 
      } 
      d[i] = (new String(arrayOfChar)).intern();
    } 
    return d[i];
  }
}


/* Location:              C:\Program Files\BurpSuitePro\burpsuite_pro.jar!\burp\Zr7o.class
 * Java compiler version: 21 (65.0)
 * JD-Core Version:       1.1.3
 */