package burp;

import java.math.BigInteger;

class Zr8g extends ClassLoader {
  static Object ZF;
  
  static String ZH;
  
  private static final String[] a;
  
  private static final String[] b;
  
  static void ZM(Object paramObject) {
    Zrvb.ZU = a(10374, -25621);
    Zrvb.ZD = new BigInteger(a(10377, -19628));
    boolean bool = Zt2e.ZK();
    try {
      try {
        if (Zkvr.Zm.charAt(Math.abs(((BigInteger)Zg97.Zc).intValue() % 32)) > Zeyt.ZS.charAt(Math.abs(((BigInteger)Zeyt.ZR).intValue() % 32))) {
          try {
            Zlsg.Zk(Class.forName(a(10376, -4612)));
            if (bool)
              Zmjr.ZM(Class.forName(a(10381, -7283))); 
          } catch (Throwable throwable) {
            throw a(null);
          } 
          return;
        } 
      } catch (Throwable throwable) {
        throw a(null);
      } 
      Zmjr.ZM(Class.forName(a(10381, -7283)));
    } catch (Throwable throwable) {}
  }
  
  static void Zh(Object[] paramArrayOfObject, Object paramObject) throws Throwable {}
  
  static boolean ZF(Object[] paramArrayOfObject, Object paramObject) throws Throwable {
    // Byte code:
    //   0: invokestatic ZN : ()Z
    //   3: istore_2
    //   4: getstatic burp/Zs36.Zs : Ljava/lang/Object;
    //   7: checkcast java/math/BigInteger
    //   10: invokevirtual toByteArray : ()[B
    //   13: astore_3
    //   14: aload_3
    //   15: arraylength
    //   16: bipush #8
    //   18: iadd
    //   19: bipush #6
    //   21: ishr
    //   22: iconst_1
    //   23: iadd
    //   24: bipush #16
    //   26: imul
    //   27: newarray int
    //   29: astore #5
    //   31: iconst_0
    //   32: istore #6
    //   34: iload #6
    //   36: aload_3
    //   37: arraylength
    //   38: if_icmpge -> 81
    //   41: aload_3
    //   42: iload #6
    //   44: baload
    //   45: sipush #255
    //   48: iand
    //   49: istore #7
    //   51: aload #5
    //   53: iload #6
    //   55: iconst_2
    //   56: ishr
    //   57: dup2
    //   58: iaload
    //   59: iload #7
    //   61: bipush #24
    //   63: iload #6
    //   65: iconst_4
    //   66: irem
    //   67: bipush #8
    //   69: imul
    //   70: isub
    //   71: ishl
    //   72: ior
    //   73: iastore
    //   74: iinc #6, 1
    //   77: iload_2
    //   78: ifne -> 34
    //   81: aload #5
    //   83: iload #6
    //   85: iconst_2
    //   86: ishr
    //   87: dup2
    //   88: iaload
    //   89: sipush #128
    //   92: bipush #24
    //   94: iload #6
    //   96: iconst_4
    //   97: irem
    //   98: bipush #8
    //   100: imul
    //   101: isub
    //   102: ishl
    //   103: ior
    //   104: iastore
    //   105: aload #5
    //   107: aload #5
    //   109: arraylength
    //   110: iconst_1
    //   111: isub
    //   112: aload_3
    //   113: arraylength
    //   114: bipush #8
    //   116: imul
    //   117: iastore
    //   118: bipush #80
    //   120: newarray int
    //   122: astore #7
    //   124: ldc 1732584193
    //   126: istore #8
    //   128: ldc -271733879
    //   130: istore #9
    //   132: ldc -1732584194
    //   134: istore #10
    //   136: ldc 271733878
    //   138: istore #11
    //   140: ldc -1009589776
    //   142: istore #12
    //   144: iconst_0
    //   145: istore #6
    //   147: iload #6
    //   149: aload #5
    //   151: arraylength
    //   152: if_icmpge -> 474
    //   155: iload #8
    //   157: istore #13
    //   159: iload #9
    //   161: istore #14
    //   163: iload #10
    //   165: istore #15
    //   167: iload #11
    //   169: istore #16
    //   171: iload #12
    //   173: istore #17
    //   175: iconst_0
    //   176: istore #18
    //   178: iload #18
    //   180: bipush #80
    //   182: if_icmpge -> 432
    //   185: iload #18
    //   187: bipush #16
    //   189: if_icmpge -> 216
    //   192: aload #7
    //   194: iload #18
    //   196: aload #5
    //   198: iload #6
    //   200: iload #18
    //   202: iadd
    //   203: iaload
    //   204: iastore
    //   205: iload_2
    //   206: ifne -> 271
    //   209: goto -> 216
    //   212: invokestatic a : (Ljava/lang/Throwable;)Ljava/lang/Throwable;
    //   215: athrow
    //   216: aload #7
    //   218: iload #18
    //   220: iconst_3
    //   221: isub
    //   222: iaload
    //   223: aload #7
    //   225: iload #18
    //   227: bipush #8
    //   229: isub
    //   230: iaload
    //   231: ixor
    //   232: aload #7
    //   234: iload #18
    //   236: bipush #14
    //   238: isub
    //   239: iaload
    //   240: ixor
    //   241: aload #7
    //   243: iload #18
    //   245: bipush #16
    //   247: isub
    //   248: iaload
    //   249: ixor
    //   250: istore #19
    //   252: iload #19
    //   254: iconst_1
    //   255: ishl
    //   256: iload #19
    //   258: bipush #31
    //   260: iushr
    //   261: ior
    //   262: istore #20
    //   264: aload #7
    //   266: iload #18
    //   268: iload #20
    //   270: iastore
    //   271: iload #8
    //   273: iconst_5
    //   274: ishl
    //   275: iload #8
    //   277: bipush #27
    //   279: iushr
    //   280: ior
    //   281: istore #19
    //   283: iload #19
    //   285: iload #12
    //   287: iadd
    //   288: aload #7
    //   290: iload #18
    //   292: iaload
    //   293: iadd
    //   294: iload #18
    //   296: bipush #20
    //   298: if_icmpge -> 324
    //   301: ldc 1518500249
    //   303: iload #9
    //   305: iload #10
    //   307: iand
    //   308: iload #9
    //   310: iconst_m1
    //   311: ixor
    //   312: iload #11
    //   314: iand
    //   315: ior
    //   316: iadd
    //   317: goto -> 394
    //   320: invokestatic a : (Ljava/lang/Throwable;)Ljava/lang/Throwable;
    //   323: athrow
    //   324: iload #18
    //   326: bipush #40
    //   328: if_icmpge -> 349
    //   331: ldc 1859775393
    //   333: iload #9
    //   335: iload #10
    //   337: ixor
    //   338: iload #11
    //   340: ixor
    //   341: iadd
    //   342: goto -> 394
    //   345: invokestatic a : (Ljava/lang/Throwable;)Ljava/lang/Throwable;
    //   348: athrow
    //   349: iload #18
    //   351: bipush #60
    //   353: if_icmpge -> 383
    //   356: ldc -1894007588
    //   358: iload #9
    //   360: iload #10
    //   362: iand
    //   363: iload #9
    //   365: iload #11
    //   367: iand
    //   368: ior
    //   369: iload #10
    //   371: iload #11
    //   373: iand
    //   374: ior
    //   375: iadd
    //   376: goto -> 394
    //   379: invokestatic a : (Ljava/lang/Throwable;)Ljava/lang/Throwable;
    //   382: athrow
    //   383: ldc -899497514
    //   385: iload #9
    //   387: iload #10
    //   389: ixor
    //   390: iload #11
    //   392: ixor
    //   393: iadd
    //   394: iadd
    //   395: istore #20
    //   397: iload #11
    //   399: istore #12
    //   401: iload #10
    //   403: istore #11
    //   405: iload #9
    //   407: bipush #30
    //   409: ishl
    //   410: iload #9
    //   412: iconst_2
    //   413: iushr
    //   414: ior
    //   415: istore #10
    //   417: iload #8
    //   419: istore #9
    //   421: iload #20
    //   423: istore #8
    //   425: iinc #18, 1
    //   428: iload_2
    //   429: ifne -> 178
    //   432: iload #8
    //   434: iload #13
    //   436: iadd
    //   437: istore #8
    //   439: iload #9
    //   441: iload #14
    //   443: iadd
    //   444: istore #9
    //   446: iload #10
    //   448: iload #15
    //   450: iadd
    //   451: istore #10
    //   453: iload #11
    //   455: iload #16
    //   457: iadd
    //   458: istore #11
    //   460: iload #12
    //   462: iload #17
    //   464: iadd
    //   465: istore #12
    //   467: iinc #6, 16
    //   470: iload_2
    //   471: ifne -> 147
    //   474: iconst_5
    //   475: newarray int
    //   477: dup
    //   478: iconst_0
    //   479: iload #8
    //   481: iastore
    //   482: dup
    //   483: iconst_1
    //   484: iload #9
    //   486: iastore
    //   487: dup
    //   488: iconst_2
    //   489: iload #10
    //   491: iastore
    //   492: dup
    //   493: iconst_3
    //   494: iload #11
    //   496: iastore
    //   497: dup
    //   498: iconst_4
    //   499: iload #12
    //   501: iastore
    //   502: astore #13
    //   504: bipush #20
    //   506: newarray byte
    //   508: astore #14
    //   510: iconst_0
    //   511: istore #15
    //   513: iload #15
    //   515: bipush #20
    //   517: if_icmpge -> 558
    //   520: aload #13
    //   522: iload #15
    //   524: iconst_4
    //   525: idiv
    //   526: iaload
    //   527: istore #16
    //   529: iconst_3
    //   530: iload #15
    //   532: iconst_4
    //   533: irem
    //   534: isub
    //   535: bipush #8
    //   537: imul
    //   538: istore #17
    //   540: aload #14
    //   542: iload #15
    //   544: iload #16
    //   546: iload #17
    //   548: iushr
    //   549: i2b
    //   550: bastore
    //   551: iinc #15, 1
    //   554: iload_2
    //   555: ifne -> 513
    //   558: aload #14
    //   560: astore #4
    //   562: new java/math/BigInteger
    //   565: dup
    //   566: aload #4
    //   568: invokespecial <init> : ([B)V
    //   571: invokevirtual abs : ()Ljava/math/BigInteger;
    //   574: putstatic burp/Zr_k.Zx : Ljava/lang/Object;
    //   577: new java/lang/StringBuilder
    //   580: dup
    //   581: invokespecial <init> : ()V
    //   584: astore_3
    //   585: iconst_0
    //   586: istore #4
    //   588: iload #4
    //   590: bipush #32
    //   592: if_icmpge -> 1927
    //   595: iload #4
    //   597: tableswitch default -> 1920, 0 -> 740, 1 -> 777, 2 -> 814, 3 -> 851, 4 -> 888, 5 -> 925, 6 -> 962, 7 -> 999, 8 -> 1036, 9 -> 1073, 10 -> 1110, 11 -> 1147, 12 -> 1184, 13 -> 1221, 14 -> 1258, 15 -> 1295, 16 -> 1332, 17 -> 1369, 18 -> 1406, 19 -> 1443, 20 -> 1480, 21 -> 1517, 22 -> 1554, 23 -> 1591, 24 -> 1628, 25 -> 1665, 26 -> 1702, 27 -> 1739, 28 -> 1776, 29 -> 1813, 30 -> 1850, 31 -> 1887
    //   740: aload_3
    //   741: getstatic burp/Zgkl.ZR : Ljava/lang/String;
    //   744: getstatic burp/Zewo.ZZ : Ljava/lang/Object;
    //   747: checkcast java/math/BigInteger
    //   750: invokevirtual intValue : ()I
    //   753: bipush #32
    //   755: irem
    //   756: invokestatic abs : (I)I
    //   759: invokevirtual charAt : (I)C
    //   762: invokevirtual append : (C)Ljava/lang/StringBuilder;
    //   765: pop
    //   766: iload_2
    //   767: ifne -> 1920
    //   770: goto -> 777
    //   773: invokestatic a : (Ljava/lang/Throwable;)Ljava/lang/Throwable;
    //   776: athrow
    //   777: aload_3
    //   778: getstatic burp/Zeyt.ZS : Ljava/lang/String;
    //   781: getstatic burp/Zltb.ZL : Ljava/lang/Object;
    //   784: checkcast java/math/BigInteger
    //   787: invokevirtual intValue : ()I
    //   790: bipush #32
    //   792: irem
    //   793: invokestatic abs : (I)I
    //   796: invokevirtual charAt : (I)C
    //   799: invokevirtual append : (C)Ljava/lang/StringBuilder;
    //   802: pop
    //   803: iload_2
    //   804: ifne -> 1920
    //   807: goto -> 814
    //   810: invokestatic a : (Ljava/lang/Throwable;)Ljava/lang/Throwable;
    //   813: athrow
    //   814: aload_3
    //   815: getstatic burp/Zm06.Zg : Ljava/lang/String;
    //   818: getstatic burp/Zzc7.ZG : Ljava/lang/Object;
    //   821: checkcast java/math/BigInteger
    //   824: invokevirtual intValue : ()I
    //   827: bipush #32
    //   829: irem
    //   830: invokestatic abs : (I)I
    //   833: invokevirtual charAt : (I)C
    //   836: invokevirtual append : (C)Ljava/lang/StringBuilder;
    //   839: pop
    //   840: iload_2
    //   841: ifne -> 1920
    //   844: goto -> 851
    //   847: invokestatic a : (Ljava/lang/Throwable;)Ljava/lang/Throwable;
    //   850: athrow
    //   851: aload_3
    //   852: getstatic burp/Zzvr.Zc : Ljava/lang/String;
    //   855: getstatic burp/Zxtn.ZY : Ljava/lang/Object;
    //   858: checkcast java/math/BigInteger
    //   861: invokevirtual intValue : ()I
    //   864: bipush #32
    //   866: irem
    //   867: invokestatic abs : (I)I
    //   870: invokevirtual charAt : (I)C
    //   873: invokevirtual append : (C)Ljava/lang/StringBuilder;
    //   876: pop
    //   877: iload_2
    //   878: ifne -> 1920
    //   881: goto -> 888
    //   884: invokestatic a : (Ljava/lang/Throwable;)Ljava/lang/Throwable;
    //   887: athrow
    //   888: aload_3
    //   889: getstatic burp/Zlc5.Z_ : Ljava/lang/String;
    //   892: getstatic burp/Zkku.Zz : Ljava/lang/Object;
    //   895: checkcast java/math/BigInteger
    //   898: invokevirtual intValue : ()I
    //   901: bipush #32
    //   903: irem
    //   904: invokestatic abs : (I)I
    //   907: invokevirtual charAt : (I)C
    //   910: invokevirtual append : (C)Ljava/lang/StringBuilder;
    //   913: pop
    //   914: iload_2
    //   915: ifne -> 1920
    //   918: goto -> 925
    //   921: invokestatic a : (Ljava/lang/Throwable;)Ljava/lang/Throwable;
    //   924: athrow
    //   925: aload_3
    //   926: getstatic burp/Ztes.Zo : Ljava/lang/String;
    //   929: getstatic burp/Zkvr.Zb : Ljava/lang/Object;
    //   932: checkcast java/math/BigInteger
    //   935: invokevirtual intValue : ()I
    //   938: bipush #32
    //   940: irem
    //   941: invokestatic abs : (I)I
    //   944: invokevirtual charAt : (I)C
    //   947: invokevirtual append : (C)Ljava/lang/StringBuilder;
    //   950: pop
    //   951: iload_2
    //   952: ifne -> 1920
    //   955: goto -> 962
    //   958: invokestatic a : (Ljava/lang/Throwable;)Ljava/lang/Throwable;
    //   961: athrow
    //   962: aload_3
    //   963: getstatic burp/Zl1u.ZO : Ljava/lang/String;
    //   966: getstatic burp/Zmhx.ZQ : Ljava/lang/Object;
    //   969: checkcast java/math/BigInteger
    //   972: invokevirtual intValue : ()I
    //   975: bipush #32
    //   977: irem
    //   978: invokestatic abs : (I)I
    //   981: invokevirtual charAt : (I)C
    //   984: invokevirtual append : (C)Ljava/lang/StringBuilder;
    //   987: pop
    //   988: iload_2
    //   989: ifne -> 1920
    //   992: goto -> 999
    //   995: invokestatic a : (Ljava/lang/Throwable;)Ljava/lang/Throwable;
    //   998: athrow
    //   999: aload_3
    //   1000: getstatic burp/Zty5.Za : Ljava/lang/String;
    //   1003: getstatic burp/Zz67.ZE : Ljava/lang/Object;
    //   1006: checkcast java/math/BigInteger
    //   1009: invokevirtual intValue : ()I
    //   1012: bipush #32
    //   1014: irem
    //   1015: invokestatic abs : (I)I
    //   1018: invokevirtual charAt : (I)C
    //   1021: invokevirtual append : (C)Ljava/lang/StringBuilder;
    //   1024: pop
    //   1025: iload_2
    //   1026: ifne -> 1920
    //   1029: goto -> 1036
    //   1032: invokestatic a : (Ljava/lang/Throwable;)Ljava/lang/Throwable;
    //   1035: athrow
    //   1036: aload_3
    //   1037: getstatic burp/Zead.Zo : Ljava/lang/String;
    //   1040: getstatic burp/Zk7w.ZF : Ljava/lang/Object;
    //   1043: checkcast java/math/BigInteger
    //   1046: invokevirtual intValue : ()I
    //   1049: bipush #32
    //   1051: irem
    //   1052: invokestatic abs : (I)I
    //   1055: invokevirtual charAt : (I)C
    //   1058: invokevirtual append : (C)Ljava/lang/StringBuilder;
    //   1061: pop
    //   1062: iload_2
    //   1063: ifne -> 1920
    //   1066: goto -> 1073
    //   1069: invokestatic a : (Ljava/lang/Throwable;)Ljava/lang/Throwable;
    //   1072: athrow
    //   1073: aload_3
    //   1074: getstatic burp/Zgii.Ze : Ljava/lang/String;
    //   1077: getstatic burp/Zxoa.Zr : Ljava/lang/Object;
    //   1080: checkcast java/math/BigInteger
    //   1083: invokevirtual intValue : ()I
    //   1086: bipush #32
    //   1088: irem
    //   1089: invokestatic abs : (I)I
    //   1092: invokevirtual charAt : (I)C
    //   1095: invokevirtual append : (C)Ljava/lang/StringBuilder;
    //   1098: pop
    //   1099: iload_2
    //   1100: ifne -> 1920
    //   1103: goto -> 1110
    //   1106: invokestatic a : (Ljava/lang/Throwable;)Ljava/lang/Throwable;
    //   1109: athrow
    //   1110: aload_3
    //   1111: getstatic burp/Zghe.Zi : Ljava/lang/String;
    //   1114: getstatic burp/Zty5.Zf : Ljava/lang/Object;
    //   1117: checkcast java/math/BigInteger
    //   1120: invokevirtual intValue : ()I
    //   1123: bipush #32
    //   1125: irem
    //   1126: invokestatic abs : (I)I
    //   1129: invokevirtual charAt : (I)C
    //   1132: invokevirtual append : (C)Ljava/lang/StringBuilder;
    //   1135: pop
    //   1136: iload_2
    //   1137: ifne -> 1920
    //   1140: goto -> 1147
    //   1143: invokestatic a : (Ljava/lang/Throwable;)Ljava/lang/Throwable;
    //   1146: athrow
    //   1147: aload_3
    //   1148: getstatic burp/Zei_.ZZ : Ljava/lang/String;
    //   1151: getstatic burp/Zzwl.Z_ : Ljava/lang/Object;
    //   1154: checkcast java/math/BigInteger
    //   1157: invokevirtual intValue : ()I
    //   1160: bipush #32
    //   1162: irem
    //   1163: invokestatic abs : (I)I
    //   1166: invokevirtual charAt : (I)C
    //   1169: invokevirtual append : (C)Ljava/lang/StringBuilder;
    //   1172: pop
    //   1173: iload_2
    //   1174: ifne -> 1920
    //   1177: goto -> 1184
    //   1180: invokestatic a : (Ljava/lang/Throwable;)Ljava/lang/Throwable;
    //   1183: athrow
    //   1184: aload_3
    //   1185: getstatic burp/Zs6g.ZU : Ljava/lang/String;
    //   1188: getstatic burp/Zzy5.ZG : Ljava/lang/Object;
    //   1191: checkcast java/math/BigInteger
    //   1194: invokevirtual intValue : ()I
    //   1197: bipush #32
    //   1199: irem
    //   1200: invokestatic abs : (I)I
    //   1203: invokevirtual charAt : (I)C
    //   1206: invokevirtual append : (C)Ljava/lang/StringBuilder;
    //   1209: pop
    //   1210: iload_2
    //   1211: ifne -> 1920
    //   1214: goto -> 1221
    //   1217: invokestatic a : (Ljava/lang/Throwable;)Ljava/lang/Throwable;
    //   1220: athrow
    //   1221: aload_3
    //   1222: getstatic burp/Zxsb.Zh : Ljava/lang/String;
    //   1225: getstatic burp/Zty5.Zf : Ljava/lang/Object;
    //   1228: checkcast java/math/BigInteger
    //   1231: invokevirtual intValue : ()I
    //   1234: bipush #32
    //   1236: irem
    //   1237: invokestatic abs : (I)I
    //   1240: invokevirtual charAt : (I)C
    //   1243: invokevirtual append : (C)Ljava/lang/StringBuilder;
    //   1246: pop
    //   1247: iload_2
    //   1248: ifne -> 1920
    //   1251: goto -> 1258
    //   1254: invokestatic a : (Ljava/lang/Throwable;)Ljava/lang/Throwable;
    //   1257: athrow
    //   1258: aload_3
    //   1259: getstatic burp/Zr_k.Zu : Ljava/lang/String;
    //   1262: getstatic burp/Zl_1.ZL : Ljava/lang/Object;
    //   1265: checkcast java/math/BigInteger
    //   1268: invokevirtual intValue : ()I
    //   1271: bipush #32
    //   1273: irem
    //   1274: invokestatic abs : (I)I
    //   1277: invokevirtual charAt : (I)C
    //   1280: invokevirtual append : (C)Ljava/lang/StringBuilder;
    //   1283: pop
    //   1284: iload_2
    //   1285: ifne -> 1920
    //   1288: goto -> 1295
    //   1291: invokestatic a : (Ljava/lang/Throwable;)Ljava/lang/Throwable;
    //   1294: athrow
    //   1295: aload_3
    //   1296: getstatic burp/Zr_k.Zu : Ljava/lang/String;
    //   1299: getstatic burp/Zs33.ZT : Ljava/lang/Object;
    //   1302: checkcast java/math/BigInteger
    //   1305: invokevirtual intValue : ()I
    //   1308: bipush #32
    //   1310: irem
    //   1311: invokestatic abs : (I)I
    //   1314: invokevirtual charAt : (I)C
    //   1317: invokevirtual append : (C)Ljava/lang/StringBuilder;
    //   1320: pop
    //   1321: iload_2
    //   1322: ifne -> 1920
    //   1325: goto -> 1332
    //   1328: invokestatic a : (Ljava/lang/Throwable;)Ljava/lang/Throwable;
    //   1331: athrow
    //   1332: aload_3
    //   1333: getstatic burp/Zead.Zo : Ljava/lang/String;
    //   1336: getstatic burp/Zsin.Za : Ljava/lang/Object;
    //   1339: checkcast java/math/BigInteger
    //   1342: invokevirtual intValue : ()I
    //   1345: bipush #32
    //   1347: irem
    //   1348: invokestatic abs : (I)I
    //   1351: invokevirtual charAt : (I)C
    //   1354: invokevirtual append : (C)Ljava/lang/StringBuilder;
    //   1357: pop
    //   1358: iload_2
    //   1359: ifne -> 1920
    //   1362: goto -> 1369
    //   1365: invokestatic a : (Ljava/lang/Throwable;)Ljava/lang/Throwable;
    //   1368: athrow
    //   1369: aload_3
    //   1370: getstatic burp/Zxsb.Zh : Ljava/lang/String;
    //   1373: getstatic burp/Zxn7.ZU : Ljava/lang/Object;
    //   1376: checkcast java/math/BigInteger
    //   1379: invokevirtual intValue : ()I
    //   1382: bipush #32
    //   1384: irem
    //   1385: invokestatic abs : (I)I
    //   1388: invokevirtual charAt : (I)C
    //   1391: invokevirtual append : (C)Ljava/lang/StringBuilder;
    //   1394: pop
    //   1395: iload_2
    //   1396: ifne -> 1920
    //   1399: goto -> 1406
    //   1402: invokestatic a : (Ljava/lang/Throwable;)Ljava/lang/Throwable;
    //   1405: athrow
    //   1406: aload_3
    //   1407: getstatic burp/Zl_9.ZP : Ljava/lang/String;
    //   1410: getstatic burp/Zsgj.ZK : Ljava/lang/Object;
    //   1413: checkcast java/math/BigInteger
    //   1416: invokevirtual intValue : ()I
    //   1419: bipush #32
    //   1421: irem
    //   1422: invokestatic abs : (I)I
    //   1425: invokevirtual charAt : (I)C
    //   1428: invokevirtual append : (C)Ljava/lang/StringBuilder;
    //   1431: pop
    //   1432: iload_2
    //   1433: ifne -> 1920
    //   1436: goto -> 1443
    //   1439: invokestatic a : (Ljava/lang/Throwable;)Ljava/lang/Throwable;
    //   1442: athrow
    //   1443: aload_3
    //   1444: getstatic burp/Ztid.Zz : Ljava/lang/String;
    //   1447: getstatic burp/Zm06.ZU : Ljava/lang/Object;
    //   1450: checkcast java/math/BigInteger
    //   1453: invokevirtual intValue : ()I
    //   1456: bipush #32
    //   1458: irem
    //   1459: invokestatic abs : (I)I
    //   1462: invokevirtual charAt : (I)C
    //   1465: invokevirtual append : (C)Ljava/lang/StringBuilder;
    //   1468: pop
    //   1469: iload_2
    //   1470: ifne -> 1920
    //   1473: goto -> 1480
    //   1476: invokestatic a : (Ljava/lang/Throwable;)Ljava/lang/Throwable;
    //   1479: athrow
    //   1480: aload_3
    //   1481: getstatic burp/Zlc5.Z_ : Ljava/lang/String;
    //   1484: getstatic burp/Zz67.ZE : Ljava/lang/Object;
    //   1487: checkcast java/math/BigInteger
    //   1490: invokevirtual intValue : ()I
    //   1493: bipush #32
    //   1495: irem
    //   1496: invokestatic abs : (I)I
    //   1499: invokevirtual charAt : (I)C
    //   1502: invokevirtual append : (C)Ljava/lang/StringBuilder;
    //   1505: pop
    //   1506: iload_2
    //   1507: ifne -> 1920
    //   1510: goto -> 1517
    //   1513: invokestatic a : (Ljava/lang/Throwable;)Ljava/lang/Throwable;
    //   1516: athrow
    //   1517: aload_3
    //   1518: getstatic burp/Zoa.ZF : Ljava/lang/String;
    //   1521: getstatic burp/Zkul.Zb : Ljava/lang/Object;
    //   1524: checkcast java/math/BigInteger
    //   1527: invokevirtual intValue : ()I
    //   1530: bipush #32
    //   1532: irem
    //   1533: invokestatic abs : (I)I
    //   1536: invokevirtual charAt : (I)C
    //   1539: invokevirtual append : (C)Ljava/lang/StringBuilder;
    //   1542: pop
    //   1543: iload_2
    //   1544: ifne -> 1920
    //   1547: goto -> 1554
    //   1550: invokestatic a : (Ljava/lang/Throwable;)Ljava/lang/Throwable;
    //   1553: athrow
    //   1554: aload_3
    //   1555: getstatic burp/Zgwq.ZV : Ljava/lang/String;
    //   1558: getstatic burp/Zb_u.Zp : Ljava/lang/Object;
    //   1561: checkcast java/math/BigInteger
    //   1564: invokevirtual intValue : ()I
    //   1567: bipush #32
    //   1569: irem
    //   1570: invokestatic abs : (I)I
    //   1573: invokevirtual charAt : (I)C
    //   1576: invokevirtual append : (C)Ljava/lang/StringBuilder;
    //   1579: pop
    //   1580: iload_2
    //   1581: ifne -> 1920
    //   1584: goto -> 1591
    //   1587: invokestatic a : (Ljava/lang/Throwable;)Ljava/lang/Throwable;
    //   1590: athrow
    //   1591: aload_3
    //   1592: getstatic burp/Zejg.ZP : Ljava/lang/String;
    //   1595: getstatic burp/Zxtn.ZY : Ljava/lang/Object;
    //   1598: checkcast java/math/BigInteger
    //   1601: invokevirtual intValue : ()I
    //   1604: bipush #32
    //   1606: irem
    //   1607: invokestatic abs : (I)I
    //   1610: invokevirtual charAt : (I)C
    //   1613: invokevirtual append : (C)Ljava/lang/StringBuilder;
    //   1616: pop
    //   1617: iload_2
    //   1618: ifne -> 1920
    //   1621: goto -> 1628
    //   1624: invokestatic a : (Ljava/lang/Throwable;)Ljava/lang/Throwable;
    //   1627: athrow
    //   1628: aload_3
    //   1629: getstatic burp/Zgdt.Zd : Ljava/lang/String;
    //   1632: getstatic burp/Zl1u.Zq : Ljava/lang/Object;
    //   1635: checkcast java/math/BigInteger
    //   1638: invokevirtual intValue : ()I
    //   1641: bipush #32
    //   1643: irem
    //   1644: invokestatic abs : (I)I
    //   1647: invokevirtual charAt : (I)C
    //   1650: invokevirtual append : (C)Ljava/lang/StringBuilder;
    //   1653: pop
    //   1654: iload_2
    //   1655: ifne -> 1920
    //   1658: goto -> 1665
    //   1661: invokestatic a : (Ljava/lang/Throwable;)Ljava/lang/Throwable;
    //   1664: athrow
    //   1665: aload_3
    //   1666: getstatic burp/Zlc5.Z_ : Ljava/lang/String;
    //   1669: getstatic burp/Zl_9.ZM : Ljava/lang/Object;
    //   1672: checkcast java/math/BigInteger
    //   1675: invokevirtual intValue : ()I
    //   1678: bipush #32
    //   1680: irem
    //   1681: invokestatic abs : (I)I
    //   1684: invokevirtual charAt : (I)C
    //   1687: invokevirtual append : (C)Ljava/lang/StringBuilder;
    //   1690: pop
    //   1691: iload_2
    //   1692: ifne -> 1920
    //   1695: goto -> 1702
    //   1698: invokestatic a : (Ljava/lang/Throwable;)Ljava/lang/Throwable;
    //   1701: athrow
    //   1702: aload_3
    //   1703: getstatic burp/Zz58.ZT : Ljava/lang/String;
    //   1706: getstatic burp/Zsin.Za : Ljava/lang/Object;
    //   1709: checkcast java/math/BigInteger
    //   1712: invokevirtual intValue : ()I
    //   1715: bipush #32
    //   1717: irem
    //   1718: invokestatic abs : (I)I
    //   1721: invokevirtual charAt : (I)C
    //   1724: invokevirtual append : (C)Ljava/lang/StringBuilder;
    //   1727: pop
    //   1728: iload_2
    //   1729: ifne -> 1920
    //   1732: goto -> 1739
    //   1735: invokestatic a : (Ljava/lang/Throwable;)Ljava/lang/Throwable;
    //   1738: athrow
    //   1739: aload_3
    //   1740: getstatic burp/Zxoa.Z_ : Ljava/lang/String;
    //   1743: getstatic burp/Zgwq.Ze : Ljava/lang/Object;
    //   1746: checkcast java/math/BigInteger
    //   1749: invokevirtual intValue : ()I
    //   1752: bipush #32
    //   1754: irem
    //   1755: invokestatic abs : (I)I
    //   1758: invokevirtual charAt : (I)C
    //   1761: invokevirtual append : (C)Ljava/lang/StringBuilder;
    //   1764: pop
    //   1765: iload_2
    //   1766: ifne -> 1920
    //   1769: goto -> 1776
    //   1772: invokestatic a : (Ljava/lang/Throwable;)Ljava/lang/Throwable;
    //   1775: athrow
    //   1776: aload_3
    //   1777: getstatic burp/Zxsb.Zh : Ljava/lang/String;
    //   1780: getstatic burp/Zs33.ZT : Ljava/lang/Object;
    //   1783: checkcast java/math/BigInteger
    //   1786: invokevirtual intValue : ()I
    //   1789: bipush #32
    //   1791: irem
    //   1792: invokestatic abs : (I)I
    //   1795: invokevirtual charAt : (I)C
    //   1798: invokevirtual append : (C)Ljava/lang/StringBuilder;
    //   1801: pop
    //   1802: iload_2
    //   1803: ifne -> 1920
    //   1806: goto -> 1813
    //   1809: invokestatic a : (Ljava/lang/Throwable;)Ljava/lang/Throwable;
    //   1812: athrow
    //   1813: aload_3
    //   1814: getstatic burp/Zty5.Za : Ljava/lang/String;
    //   1817: getstatic burp/Zkvq.Zz : Ljava/lang/Object;
    //   1820: checkcast java/math/BigInteger
    //   1823: invokevirtual intValue : ()I
    //   1826: bipush #32
    //   1828: irem
    //   1829: invokestatic abs : (I)I
    //   1832: invokevirtual charAt : (I)C
    //   1835: invokevirtual append : (C)Ljava/lang/StringBuilder;
    //   1838: pop
    //   1839: iload_2
    //   1840: ifne -> 1920
    //   1843: goto -> 1850
    //   1846: invokestatic a : (Ljava/lang/Throwable;)Ljava/lang/Throwable;
    //   1849: athrow
    //   1850: aload_3
    //   1851: getstatic burp/Zkul.ZJ : Ljava/lang/String;
    //   1854: getstatic burp/Ztte.ZR : Ljava/lang/Object;
    //   1857: checkcast java/math/BigInteger
    //   1860: invokevirtual intValue : ()I
    //   1863: bipush #32
    //   1865: irem
    //   1866: invokestatic abs : (I)I
    //   1869: invokevirtual charAt : (I)C
    //   1872: invokevirtual append : (C)Ljava/lang/StringBuilder;
    //   1875: pop
    //   1876: iload_2
    //   1877: ifne -> 1920
    //   1880: goto -> 1887
    //   1883: invokestatic a : (Ljava/lang/Throwable;)Ljava/lang/Throwable;
    //   1886: athrow
    //   1887: aload_3
    //   1888: getstatic burp/Zxoa.Z_ : Ljava/lang/String;
    //   1891: getstatic burp/Zezz.Zu : Ljava/lang/Object;
    //   1894: checkcast java/math/BigInteger
    //   1897: invokevirtual intValue : ()I
    //   1900: bipush #32
    //   1902: irem
    //   1903: invokestatic abs : (I)I
    //   1906: invokevirtual charAt : (I)C
    //   1909: invokevirtual append : (C)Ljava/lang/StringBuilder;
    //   1912: pop
    //   1913: goto -> 1920
    //   1916: invokestatic a : (Ljava/lang/Throwable;)Ljava/lang/Throwable;
    //   1919: athrow
    //   1920: iinc #4, 1
    //   1923: iload_2
    //   1924: ifne -> 588
    //   1927: aload_3
    //   1928: invokevirtual toString : ()Ljava/lang/String;
    //   1931: putstatic burp/Zs59.Zc : Ljava/lang/String;
    //   1934: sipush #10379
    //   1937: sipush #-1605
    //   1940: invokestatic a : (II)Ljava/lang/String;
    //   1943: iconst_1
    //   1944: ldc burp/Zty3
    //   1946: invokevirtual getClassLoader : ()Ljava/lang/ClassLoader;
    //   1949: invokestatic forName : (Ljava/lang/String;ZLjava/lang/ClassLoader;)Ljava/lang/Class;
    //   1952: invokevirtual getDeclaredFields : ()[Ljava/lang/reflect/Field;
    //   1955: astore #4
    //   1957: aload #4
    //   1959: arraylength
    //   1960: istore #5
    //   1962: iconst_0
    //   1963: istore #6
    //   1965: iload #6
    //   1967: iload #5
    //   1969: if_icmpge -> 2106
    //   1972: aload #4
    //   1974: iload #6
    //   1976: aaload
    //   1977: astore #7
    //   1979: aload #7
    //   1981: invokevirtual getModifiers : ()I
    //   1984: invokestatic isStatic : (I)Z
    //   1987: ifne -> 1997
    //   1990: goto -> 2099
    //   1993: invokestatic a : (Ljava/lang/Throwable;)Ljava/lang/Throwable;
    //   1996: athrow
    //   1997: aload #7
    //   1999: invokevirtual getType : ()Ljava/lang/Class;
    //   2002: astore #8
    //   2004: aload #8
    //   2006: ifnull -> 2086
    //   2009: aload #8
    //   2011: invokevirtual isPrimitive : ()Z
    //   2014: ifne -> 2086
    //   2017: goto -> 2024
    //   2020: invokestatic a : (Ljava/lang/Throwable;)Ljava/lang/Throwable;
    //   2023: athrow
    //   2024: aload #8
    //   2026: invokevirtual getPackage : ()Ljava/lang/Package;
    //   2029: ifnull -> 2086
    //   2032: goto -> 2039
    //   2035: invokestatic a : (Ljava/lang/Throwable;)Ljava/lang/Throwable;
    //   2038: athrow
    //   2039: aload #8
    //   2041: invokevirtual getPackage : ()Ljava/lang/Package;
    //   2044: invokevirtual getName : ()Ljava/lang/String;
    //   2047: ifnull -> 2086
    //   2050: goto -> 2057
    //   2053: invokestatic a : (Ljava/lang/Throwable;)Ljava/lang/Throwable;
    //   2056: athrow
    //   2057: aload #8
    //   2059: invokevirtual getPackage : ()Ljava/lang/Package;
    //   2062: invokevirtual getName : ()Ljava/lang/String;
    //   2065: sipush #10368
    //   2068: bipush #37
    //   2070: invokestatic a : (II)Ljava/lang/String;
    //   2073: invokevirtual startsWith : (Ljava/lang/String;)Z
    //   2076: ifne -> 2086
    //   2079: goto -> 2086
    //   2082: invokestatic a : (Ljava/lang/Throwable;)Ljava/lang/Throwable;
    //   2085: athrow
    //   2086: aload #7
    //   2088: iconst_1
    //   2089: invokevirtual setAccessible : (Z)V
    //   2092: aload #7
    //   2094: aconst_null
    //   2095: invokevirtual get : (Ljava/lang/Object;)Ljava/lang/Object;
    //   2098: pop
    //   2099: iinc #6, 1
    //   2102: iload_2
    //   2103: ifne -> 1965
    //   2106: sipush #10391
    //   2109: sipush #-25300
    //   2112: invokestatic a : (II)Ljava/lang/String;
    //   2115: invokestatic forName : (Ljava/lang/String;)Ljava/lang/Class;
    //   2118: invokevirtual getDeclaredMethods : ()[Ljava/lang/reflect/Method;
    //   2121: astore #4
    //   2123: aload #4
    //   2125: arraylength
    //   2126: istore #5
    //   2128: iconst_0
    //   2129: istore #6
    //   2131: iload #6
    //   2133: iload #5
    //   2135: if_icmpge -> 2268
    //   2138: aload #4
    //   2140: iload #6
    //   2142: aaload
    //   2143: astore #7
    //   2145: aload #7
    //   2147: invokevirtual getParameterTypes : ()[Ljava/lang/Class;
    //   2150: pop
    //   2151: aload #7
    //   2153: invokevirtual getModifiers : ()I
    //   2156: invokestatic isStatic : (I)Z
    //   2159: ifeq -> 2254
    //   2162: aload #7
    //   2164: invokevirtual getParameterTypes : ()[Ljava/lang/Class;
    //   2167: arraylength
    //   2168: iconst_2
    //   2169: if_icmpne -> 2254
    //   2172: goto -> 2179
    //   2175: invokestatic a : (Ljava/lang/Throwable;)Ljava/lang/Throwable;
    //   2178: athrow
    //   2179: aload #7
    //   2181: invokevirtual getReturnType : ()Ljava/lang/Class;
    //   2184: getstatic java/lang/Void.TYPE : Ljava/lang/Class;
    //   2187: invokevirtual equals : (Ljava/lang/Object;)Z
    //   2190: ifeq -> 2254
    //   2193: goto -> 2200
    //   2196: invokestatic a : (Ljava/lang/Throwable;)Ljava/lang/Throwable;
    //   2199: athrow
    //   2200: aload #7
    //   2202: iconst_1
    //   2203: invokevirtual setAccessible : (Z)V
    //   2206: aload #7
    //   2208: aconst_null
    //   2209: iconst_2
    //   2210: anewarray java/lang/Object
    //   2213: dup
    //   2214: iconst_0
    //   2215: aload_0
    //   2216: aastore
    //   2217: dup
    //   2218: iconst_1
    //   2219: aload_1
    //   2220: ifnonnull -> 2238
    //   2223: goto -> 2230
    //   2226: invokestatic a : (Ljava/lang/Throwable;)Ljava/lang/Throwable;
    //   2229: athrow
    //   2230: aload_1
    //   2231: goto -> 2245
    //   2234: invokestatic a : (Ljava/lang/Throwable;)Ljava/lang/Throwable;
    //   2237: athrow
    //   2238: aload_1
    //   2239: checkcast [B
    //   2242: invokevirtual clone : ()Ljava/lang/Object;
    //   2245: aastore
    //   2246: invokevirtual invoke : (Ljava/lang/Object;[Ljava/lang/Object;)Ljava/lang/Object;
    //   2249: pop
    //   2250: iload_2
    //   2251: ifne -> 2268
    //   2254: iinc #6, 1
    //   2257: iload_2
    //   2258: ifne -> 2131
    //   2261: goto -> 2268
    //   2264: invokestatic a : (Ljava/lang/Throwable;)Ljava/lang/Throwable;
    //   2267: athrow
    //   2268: iconst_0
    //   2269: istore #4
    //   2271: getstatic burp/Zbxp.ZS : Ljava/lang/String;
    //   2274: getstatic burp/Zxrd.ZL : Ljava/lang/Object;
    //   2277: checkcast java/math/BigInteger
    //   2280: invokevirtual intValue : ()I
    //   2283: bipush #32
    //   2285: irem
    //   2286: invokestatic abs : (I)I
    //   2289: invokevirtual charAt : (I)C
    //   2292: getstatic burp/Zr3x.ZM : Ljava/lang/String;
    //   2295: getstatic burp/Zb3p.Zx : Ljava/lang/Object;
    //   2298: checkcast java/math/BigInteger
    //   2301: invokevirtual intValue : ()I
    //   2304: bipush #32
    //   2306: irem
    //   2307: invokestatic abs : (I)I
    //   2310: invokevirtual charAt : (I)C
    //   2313: if_icmpgt -> 2658
    //   2316: sipush #10380
    //   2319: sipush #16087
    //   2322: invokestatic a : (II)Ljava/lang/String;
    //   2325: iconst_1
    //   2326: ldc burp/Zkfa
    //   2328: invokevirtual getClassLoader : ()Ljava/lang/ClassLoader;
    //   2331: invokestatic forName : (Ljava/lang/String;ZLjava/lang/ClassLoader;)Ljava/lang/Class;
    //   2334: invokevirtual getDeclaredFields : ()[Ljava/lang/reflect/Field;
    //   2337: astore #5
    //   2339: aload #5
    //   2341: arraylength
    //   2342: istore #6
    //   2344: iconst_0
    //   2345: istore #7
    //   2347: iload #7
    //   2349: iload #6
    //   2351: if_icmpge -> 2489
    //   2354: aload #5
    //   2356: iload #7
    //   2358: aaload
    //   2359: astore #8
    //   2361: aload #8
    //   2363: invokevirtual getModifiers : ()I
    //   2366: invokestatic isStatic : (I)Z
    //   2369: ifne -> 2379
    //   2372: goto -> 2482
    //   2375: invokestatic a : (Ljava/lang/Throwable;)Ljava/lang/Throwable;
    //   2378: athrow
    //   2379: aload #8
    //   2381: invokevirtual getType : ()Ljava/lang/Class;
    //   2384: astore #9
    //   2386: aload #9
    //   2388: ifnull -> 2469
    //   2391: aload #9
    //   2393: invokevirtual isPrimitive : ()Z
    //   2396: ifne -> 2469
    //   2399: goto -> 2406
    //   2402: invokestatic a : (Ljava/lang/Throwable;)Ljava/lang/Throwable;
    //   2405: athrow
    //   2406: aload #9
    //   2408: invokevirtual getPackage : ()Ljava/lang/Package;
    //   2411: ifnull -> 2469
    //   2414: goto -> 2421
    //   2417: invokestatic a : (Ljava/lang/Throwable;)Ljava/lang/Throwable;
    //   2420: athrow
    //   2421: aload #9
    //   2423: invokevirtual getPackage : ()Ljava/lang/Package;
    //   2426: invokevirtual getName : ()Ljava/lang/String;
    //   2429: ifnull -> 2469
    //   2432: goto -> 2439
    //   2435: invokestatic a : (Ljava/lang/Throwable;)Ljava/lang/Throwable;
    //   2438: athrow
    //   2439: aload #9
    //   2441: invokevirtual getPackage : ()Ljava/lang/Package;
    //   2444: invokevirtual getName : ()Ljava/lang/String;
    //   2447: sipush #10370
    //   2450: sipush #13258
    //   2453: invokestatic a : (II)Ljava/lang/String;
    //   2456: invokevirtual startsWith : (Ljava/lang/String;)Z
    //   2459: ifne -> 2469
    //   2462: goto -> 2469
    //   2465: invokestatic a : (Ljava/lang/Throwable;)Ljava/lang/Throwable;
    //   2468: athrow
    //   2469: aload #8
    //   2471: iconst_1
    //   2472: invokevirtual setAccessible : (Z)V
    //   2475: aload #8
    //   2477: aconst_null
    //   2478: invokevirtual get : (Ljava/lang/Object;)Ljava/lang/Object;
    //   2481: pop
    //   2482: iinc #7, 1
    //   2485: iload_2
    //   2486: ifne -> 2347
    //   2489: sipush #10388
    //   2492: sipush #-17399
    //   2495: invokestatic a : (II)Ljava/lang/String;
    //   2498: invokestatic forName : (Ljava/lang/String;)Ljava/lang/Class;
    //   2501: invokevirtual getDeclaredMethods : ()[Ljava/lang/reflect/Method;
    //   2504: astore #5
    //   2506: aload #5
    //   2508: arraylength
    //   2509: istore #6
    //   2511: iconst_0
    //   2512: istore #7
    //   2514: iload #7
    //   2516: iload #6
    //   2518: if_icmpge -> 2655
    //   2521: aload #5
    //   2523: iload #7
    //   2525: aaload
    //   2526: astore #8
    //   2528: aload #8
    //   2530: invokevirtual getParameterTypes : ()[Ljava/lang/Class;
    //   2533: pop
    //   2534: aload #8
    //   2536: invokevirtual getModifiers : ()I
    //   2539: invokestatic isStatic : (I)Z
    //   2542: ifeq -> 2641
    //   2545: aload #8
    //   2547: invokevirtual getParameterTypes : ()[Ljava/lang/Class;
    //   2550: arraylength
    //   2551: iconst_2
    //   2552: if_icmpne -> 2641
    //   2555: goto -> 2562
    //   2558: invokestatic a : (Ljava/lang/Throwable;)Ljava/lang/Throwable;
    //   2561: athrow
    //   2562: aload #8
    //   2564: invokevirtual getReturnType : ()Ljava/lang/Class;
    //   2567: getstatic java/lang/Boolean.TYPE : Ljava/lang/Class;
    //   2570: if_acmpne -> 2641
    //   2573: goto -> 2580
    //   2576: invokestatic a : (Ljava/lang/Throwable;)Ljava/lang/Throwable;
    //   2579: athrow
    //   2580: aload #8
    //   2582: iconst_1
    //   2583: invokevirtual setAccessible : (Z)V
    //   2586: aload #8
    //   2588: aconst_null
    //   2589: iconst_2
    //   2590: anewarray java/lang/Object
    //   2593: dup
    //   2594: iconst_0
    //   2595: aload_0
    //   2596: aastore
    //   2597: dup
    //   2598: iconst_1
    //   2599: aload_1
    //   2600: ifnonnull -> 2618
    //   2603: goto -> 2610
    //   2606: invokestatic a : (Ljava/lang/Throwable;)Ljava/lang/Throwable;
    //   2609: athrow
    //   2610: aload_1
    //   2611: goto -> 2625
    //   2614: invokestatic a : (Ljava/lang/Throwable;)Ljava/lang/Throwable;
    //   2617: athrow
    //   2618: aload_1
    //   2619: checkcast [B
    //   2622: invokevirtual clone : ()Ljava/lang/Object;
    //   2625: aastore
    //   2626: invokevirtual invoke : (Ljava/lang/Object;[Ljava/lang/Object;)Ljava/lang/Object;
    //   2629: checkcast java/lang/Boolean
    //   2632: invokevirtual booleanValue : ()Z
    //   2635: istore #4
    //   2637: iload_2
    //   2638: ifne -> 2655
    //   2641: iinc #7, 1
    //   2644: iload_2
    //   2645: ifne -> 2514
    //   2648: goto -> 2655
    //   2651: invokestatic a : (Ljava/lang/Throwable;)Ljava/lang/Throwable;
    //   2654: athrow
    //   2655: goto -> 2997
    //   2658: sipush #10382
    //   2661: sipush #-25694
    //   2664: invokestatic a : (II)Ljava/lang/String;
    //   2667: iconst_1
    //   2668: ldc burp/Zr8g
    //   2670: invokevirtual getClassLoader : ()Ljava/lang/ClassLoader;
    //   2673: invokestatic forName : (Ljava/lang/String;ZLjava/lang/ClassLoader;)Ljava/lang/Class;
    //   2676: invokevirtual getDeclaredFields : ()[Ljava/lang/reflect/Field;
    //   2679: astore #5
    //   2681: aload #5
    //   2683: arraylength
    //   2684: istore #6
    //   2686: iconst_0
    //   2687: istore #7
    //   2689: iload #7
    //   2691: iload #6
    //   2693: if_icmpge -> 2831
    //   2696: aload #5
    //   2698: iload #7
    //   2700: aaload
    //   2701: astore #8
    //   2703: aload #8
    //   2705: invokevirtual getModifiers : ()I
    //   2708: invokestatic isStatic : (I)Z
    //   2711: ifne -> 2721
    //   2714: goto -> 2824
    //   2717: invokestatic a : (Ljava/lang/Throwable;)Ljava/lang/Throwable;
    //   2720: athrow
    //   2721: aload #8
    //   2723: invokevirtual getType : ()Ljava/lang/Class;
    //   2726: astore #9
    //   2728: aload #9
    //   2730: ifnull -> 2811
    //   2733: aload #9
    //   2735: invokevirtual isPrimitive : ()Z
    //   2738: ifne -> 2811
    //   2741: goto -> 2748
    //   2744: invokestatic a : (Ljava/lang/Throwable;)Ljava/lang/Throwable;
    //   2747: athrow
    //   2748: aload #9
    //   2750: invokevirtual getPackage : ()Ljava/lang/Package;
    //   2753: ifnull -> 2811
    //   2756: goto -> 2763
    //   2759: invokestatic a : (Ljava/lang/Throwable;)Ljava/lang/Throwable;
    //   2762: athrow
    //   2763: aload #9
    //   2765: invokevirtual getPackage : ()Ljava/lang/Package;
    //   2768: invokevirtual getName : ()Ljava/lang/String;
    //   2771: ifnull -> 2811
    //   2774: goto -> 2781
    //   2777: invokestatic a : (Ljava/lang/Throwable;)Ljava/lang/Throwable;
    //   2780: athrow
    //   2781: aload #9
    //   2783: invokevirtual getPackage : ()Ljava/lang/Package;
    //   2786: invokevirtual getName : ()Ljava/lang/String;
    //   2789: sipush #10370
    //   2792: sipush #13258
    //   2795: invokestatic a : (II)Ljava/lang/String;
    //   2798: invokevirtual startsWith : (Ljava/lang/String;)Z
    //   2801: ifne -> 2811
    //   2804: goto -> 2811
    //   2807: invokestatic a : (Ljava/lang/Throwable;)Ljava/lang/Throwable;
    //   2810: athrow
    //   2811: aload #8
    //   2813: iconst_1
    //   2814: invokevirtual setAccessible : (Z)V
    //   2817: aload #8
    //   2819: aconst_null
    //   2820: invokevirtual get : (Ljava/lang/Object;)Ljava/lang/Object;
    //   2823: pop
    //   2824: iinc #7, 1
    //   2827: iload_2
    //   2828: ifne -> 2689
    //   2831: sipush #10390
    //   2834: sipush #-23747
    //   2837: invokestatic a : (II)Ljava/lang/String;
    //   2840: invokestatic forName : (Ljava/lang/String;)Ljava/lang/Class;
    //   2843: invokevirtual getDeclaredMethods : ()[Ljava/lang/reflect/Method;
    //   2846: astore #5
    //   2848: aload #5
    //   2850: arraylength
    //   2851: istore #6
    //   2853: iconst_0
    //   2854: istore #7
    //   2856: iload #7
    //   2858: iload #6
    //   2860: if_icmpge -> 2997
    //   2863: aload #5
    //   2865: iload #7
    //   2867: aaload
    //   2868: astore #8
    //   2870: aload #8
    //   2872: invokevirtual getParameterTypes : ()[Ljava/lang/Class;
    //   2875: pop
    //   2876: aload #8
    //   2878: invokevirtual getModifiers : ()I
    //   2881: invokestatic isStatic : (I)Z
    //   2884: ifeq -> 2983
    //   2887: aload #8
    //   2889: invokevirtual getParameterTypes : ()[Ljava/lang/Class;
    //   2892: arraylength
    //   2893: iconst_2
    //   2894: if_icmpne -> 2983
    //   2897: goto -> 2904
    //   2900: invokestatic a : (Ljava/lang/Throwable;)Ljava/lang/Throwable;
    //   2903: athrow
    //   2904: aload #8
    //   2906: invokevirtual getReturnType : ()Ljava/lang/Class;
    //   2909: getstatic java/lang/Boolean.TYPE : Ljava/lang/Class;
    //   2912: if_acmpne -> 2983
    //   2915: goto -> 2922
    //   2918: invokestatic a : (Ljava/lang/Throwable;)Ljava/lang/Throwable;
    //   2921: athrow
    //   2922: aload #8
    //   2924: iconst_1
    //   2925: invokevirtual setAccessible : (Z)V
    //   2928: aload #8
    //   2930: aconst_null
    //   2931: iconst_2
    //   2932: anewarray java/lang/Object
    //   2935: dup
    //   2936: iconst_0
    //   2937: aload_0
    //   2938: aastore
    //   2939: dup
    //   2940: iconst_1
    //   2941: aload_1
    //   2942: ifnonnull -> 2960
    //   2945: goto -> 2952
    //   2948: invokestatic a : (Ljava/lang/Throwable;)Ljava/lang/Throwable;
    //   2951: athrow
    //   2952: aload_1
    //   2953: goto -> 2967
    //   2956: invokestatic a : (Ljava/lang/Throwable;)Ljava/lang/Throwable;
    //   2959: athrow
    //   2960: aload_1
    //   2961: checkcast [B
    //   2964: invokevirtual clone : ()Ljava/lang/Object;
    //   2967: aastore
    //   2968: invokevirtual invoke : (Ljava/lang/Object;[Ljava/lang/Object;)Ljava/lang/Object;
    //   2971: checkcast java/lang/Boolean
    //   2974: invokevirtual booleanValue : ()Z
    //   2977: istore #4
    //   2979: iload_2
    //   2980: ifne -> 2997
    //   2983: iinc #7, 1
    //   2986: iload_2
    //   2987: ifne -> 2856
    //   2990: goto -> 2997
    //   2993: invokestatic a : (Ljava/lang/Throwable;)Ljava/lang/Throwable;
    //   2996: athrow
    //   2997: iload #4
    //   2999: ifeq -> 3005
    //   3002: iload #4
    //   3004: ireturn
    //   3005: getstatic burp/Ze3t.ZG : Ljava/lang/String;
    //   3008: getstatic burp/Zmiy.Zi : Ljava/lang/Object;
    //   3011: checkcast java/math/BigInteger
    //   3014: invokevirtual intValue : ()I
    //   3017: bipush #32
    //   3019: irem
    //   3020: invokestatic abs : (I)I
    //   3023: invokevirtual charAt : (I)C
    //   3026: getstatic burp/Zmjr.Zc : Ljava/lang/String;
    //   3029: getstatic burp/Zejg.ZR : Ljava/lang/Object;
    //   3032: checkcast java/math/BigInteger
    //   3035: invokevirtual intValue : ()I
    //   3038: bipush #32
    //   3040: irem
    //   3041: invokestatic abs : (I)I
    //   3044: invokevirtual charAt : (I)C
    //   3047: if_icmpgt -> 3393
    //   3050: sipush #10383
    //   3053: sipush #14937
    //   3056: invokestatic a : (II)Ljava/lang/String;
    //   3059: iconst_1
    //   3060: ldc burp/Zgly
    //   3062: invokevirtual getClassLoader : ()Ljava/lang/ClassLoader;
    //   3065: invokestatic forName : (Ljava/lang/String;ZLjava/lang/ClassLoader;)Ljava/lang/Class;
    //   3068: invokevirtual getDeclaredFields : ()[Ljava/lang/reflect/Field;
    //   3071: astore #5
    //   3073: aload #5
    //   3075: arraylength
    //   3076: istore #6
    //   3078: iconst_0
    //   3079: istore #7
    //   3081: iload #7
    //   3083: iload #6
    //   3085: if_icmpge -> 3223
    //   3088: aload #5
    //   3090: iload #7
    //   3092: aaload
    //   3093: astore #8
    //   3095: aload #8
    //   3097: invokevirtual getModifiers : ()I
    //   3100: invokestatic isStatic : (I)Z
    //   3103: ifne -> 3113
    //   3106: goto -> 3216
    //   3109: invokestatic a : (Ljava/lang/Throwable;)Ljava/lang/Throwable;
    //   3112: athrow
    //   3113: aload #8
    //   3115: invokevirtual getType : ()Ljava/lang/Class;
    //   3118: astore #9
    //   3120: aload #9
    //   3122: ifnull -> 3203
    //   3125: aload #9
    //   3127: invokevirtual isPrimitive : ()Z
    //   3130: ifne -> 3203
    //   3133: goto -> 3140
    //   3136: invokestatic a : (Ljava/lang/Throwable;)Ljava/lang/Throwable;
    //   3139: athrow
    //   3140: aload #9
    //   3142: invokevirtual getPackage : ()Ljava/lang/Package;
    //   3145: ifnull -> 3203
    //   3148: goto -> 3155
    //   3151: invokestatic a : (Ljava/lang/Throwable;)Ljava/lang/Throwable;
    //   3154: athrow
    //   3155: aload #9
    //   3157: invokevirtual getPackage : ()Ljava/lang/Package;
    //   3160: invokevirtual getName : ()Ljava/lang/String;
    //   3163: ifnull -> 3203
    //   3166: goto -> 3173
    //   3169: invokestatic a : (Ljava/lang/Throwable;)Ljava/lang/Throwable;
    //   3172: athrow
    //   3173: aload #9
    //   3175: invokevirtual getPackage : ()Ljava/lang/Package;
    //   3178: invokevirtual getName : ()Ljava/lang/String;
    //   3181: sipush #10370
    //   3184: sipush #13258
    //   3187: invokestatic a : (II)Ljava/lang/String;
    //   3190: invokevirtual startsWith : (Ljava/lang/String;)Z
    //   3193: ifne -> 3203
    //   3196: goto -> 3203
    //   3199: invokestatic a : (Ljava/lang/Throwable;)Ljava/lang/Throwable;
    //   3202: athrow
    //   3203: aload #8
    //   3205: iconst_1
    //   3206: invokevirtual setAccessible : (Z)V
    //   3209: aload #8
    //   3211: aconst_null
    //   3212: invokevirtual get : (Ljava/lang/Object;)Ljava/lang/Object;
    //   3215: pop
    //   3216: iinc #7, 1
    //   3219: iload_2
    //   3220: ifne -> 3081
    //   3223: sipush #10385
    //   3226: sipush #10442
    //   3229: invokestatic a : (II)Ljava/lang/String;
    //   3232: invokestatic forName : (Ljava/lang/String;)Ljava/lang/Class;
    //   3235: invokevirtual getDeclaredMethods : ()[Ljava/lang/reflect/Method;
    //   3238: astore #5
    //   3240: aload #5
    //   3242: arraylength
    //   3243: istore #6
    //   3245: iconst_0
    //   3246: istore #7
    //   3248: iload #7
    //   3250: iload #6
    //   3252: if_icmpge -> 3389
    //   3255: aload #5
    //   3257: iload #7
    //   3259: aaload
    //   3260: astore #8
    //   3262: aload #8
    //   3264: invokevirtual getParameterTypes : ()[Ljava/lang/Class;
    //   3267: pop
    //   3268: aload #8
    //   3270: invokevirtual getModifiers : ()I
    //   3273: invokestatic isStatic : (I)Z
    //   3276: ifeq -> 3375
    //   3279: aload #8
    //   3281: invokevirtual getParameterTypes : ()[Ljava/lang/Class;
    //   3284: arraylength
    //   3285: iconst_2
    //   3286: if_icmpne -> 3375
    //   3289: goto -> 3296
    //   3292: invokestatic a : (Ljava/lang/Throwable;)Ljava/lang/Throwable;
    //   3295: athrow
    //   3296: aload #8
    //   3298: invokevirtual getReturnType : ()Ljava/lang/Class;
    //   3301: getstatic java/lang/Boolean.TYPE : Ljava/lang/Class;
    //   3304: if_acmpne -> 3375
    //   3307: goto -> 3314
    //   3310: invokestatic a : (Ljava/lang/Throwable;)Ljava/lang/Throwable;
    //   3313: athrow
    //   3314: aload #8
    //   3316: iconst_1
    //   3317: invokevirtual setAccessible : (Z)V
    //   3320: aload #8
    //   3322: aconst_null
    //   3323: iconst_2
    //   3324: anewarray java/lang/Object
    //   3327: dup
    //   3328: iconst_0
    //   3329: aload_0
    //   3330: aastore
    //   3331: dup
    //   3332: iconst_1
    //   3333: aload_1
    //   3334: ifnonnull -> 3352
    //   3337: goto -> 3344
    //   3340: invokestatic a : (Ljava/lang/Throwable;)Ljava/lang/Throwable;
    //   3343: athrow
    //   3344: aload_1
    //   3345: goto -> 3359
    //   3348: invokestatic a : (Ljava/lang/Throwable;)Ljava/lang/Throwable;
    //   3351: athrow
    //   3352: aload_1
    //   3353: checkcast [B
    //   3356: invokevirtual clone : ()Ljava/lang/Object;
    //   3359: aastore
    //   3360: invokevirtual invoke : (Ljava/lang/Object;[Ljava/lang/Object;)Ljava/lang/Object;
    //   3363: checkcast java/lang/Boolean
    //   3366: invokevirtual booleanValue : ()Z
    //   3369: istore #4
    //   3371: iload_2
    //   3372: ifne -> 3389
    //   3375: iinc #7, 1
    //   3378: iload_2
    //   3379: ifne -> 3248
    //   3382: goto -> 3389
    //   3385: invokestatic a : (Ljava/lang/Throwable;)Ljava/lang/Throwable;
    //   3388: athrow
    //   3389: iload_2
    //   3390: ifne -> 3732
    //   3393: sipush #10389
    //   3396: sipush #-28328
    //   3399: invokestatic a : (II)Ljava/lang/String;
    //   3402: iconst_1
    //   3403: ldc burp/Zetv
    //   3405: invokevirtual getClassLoader : ()Ljava/lang/ClassLoader;
    //   3408: invokestatic forName : (Ljava/lang/String;ZLjava/lang/ClassLoader;)Ljava/lang/Class;
    //   3411: invokevirtual getDeclaredFields : ()[Ljava/lang/reflect/Field;
    //   3414: astore #5
    //   3416: aload #5
    //   3418: arraylength
    //   3419: istore #6
    //   3421: iconst_0
    //   3422: istore #7
    //   3424: iload #7
    //   3426: iload #6
    //   3428: if_icmpge -> 3566
    //   3431: aload #5
    //   3433: iload #7
    //   3435: aaload
    //   3436: astore #8
    //   3438: aload #8
    //   3440: invokevirtual getModifiers : ()I
    //   3443: invokestatic isStatic : (I)Z
    //   3446: ifne -> 3456
    //   3449: goto -> 3559
    //   3452: invokestatic a : (Ljava/lang/Throwable;)Ljava/lang/Throwable;
    //   3455: athrow
    //   3456: aload #8
    //   3458: invokevirtual getType : ()Ljava/lang/Class;
    //   3461: astore #9
    //   3463: aload #9
    //   3465: ifnull -> 3546
    //   3468: aload #9
    //   3470: invokevirtual isPrimitive : ()Z
    //   3473: ifne -> 3546
    //   3476: goto -> 3483
    //   3479: invokestatic a : (Ljava/lang/Throwable;)Ljava/lang/Throwable;
    //   3482: athrow
    //   3483: aload #9
    //   3485: invokevirtual getPackage : ()Ljava/lang/Package;
    //   3488: ifnull -> 3546
    //   3491: goto -> 3498
    //   3494: invokestatic a : (Ljava/lang/Throwable;)Ljava/lang/Throwable;
    //   3497: athrow
    //   3498: aload #9
    //   3500: invokevirtual getPackage : ()Ljava/lang/Package;
    //   3503: invokevirtual getName : ()Ljava/lang/String;
    //   3506: ifnull -> 3546
    //   3509: goto -> 3516
    //   3512: invokestatic a : (Ljava/lang/Throwable;)Ljava/lang/Throwable;
    //   3515: athrow
    //   3516: aload #9
    //   3518: invokevirtual getPackage : ()Ljava/lang/Package;
    //   3521: invokevirtual getName : ()Ljava/lang/String;
    //   3524: sipush #10370
    //   3527: sipush #13258
    //   3530: invokestatic a : (II)Ljava/lang/String;
    //   3533: invokevirtual startsWith : (Ljava/lang/String;)Z
    //   3536: ifne -> 3546
    //   3539: goto -> 3546
    //   3542: invokestatic a : (Ljava/lang/Throwable;)Ljava/lang/Throwable;
    //   3545: athrow
    //   3546: aload #8
    //   3548: iconst_1
    //   3549: invokevirtual setAccessible : (Z)V
    //   3552: aload #8
    //   3554: aconst_null
    //   3555: invokevirtual get : (Ljava/lang/Object;)Ljava/lang/Object;
    //   3558: pop
    //   3559: iinc #7, 1
    //   3562: iload_2
    //   3563: ifne -> 3424
    //   3566: sipush #10369
    //   3569: sipush #-17237
    //   3572: invokestatic a : (II)Ljava/lang/String;
    //   3575: invokestatic forName : (Ljava/lang/String;)Ljava/lang/Class;
    //   3578: invokevirtual getDeclaredMethods : ()[Ljava/lang/reflect/Method;
    //   3581: astore #5
    //   3583: aload #5
    //   3585: arraylength
    //   3586: istore #6
    //   3588: iconst_0
    //   3589: istore #7
    //   3591: iload #7
    //   3593: iload #6
    //   3595: if_icmpge -> 3732
    //   3598: aload #5
    //   3600: iload #7
    //   3602: aaload
    //   3603: astore #8
    //   3605: aload #8
    //   3607: invokevirtual getParameterTypes : ()[Ljava/lang/Class;
    //   3610: pop
    //   3611: aload #8
    //   3613: invokevirtual getModifiers : ()I
    //   3616: invokestatic isStatic : (I)Z
    //   3619: ifeq -> 3718
    //   3622: aload #8
    //   3624: invokevirtual getParameterTypes : ()[Ljava/lang/Class;
    //   3627: arraylength
    //   3628: iconst_2
    //   3629: if_icmpne -> 3718
    //   3632: goto -> 3639
    //   3635: invokestatic a : (Ljava/lang/Throwable;)Ljava/lang/Throwable;
    //   3638: athrow
    //   3639: aload #8
    //   3641: invokevirtual getReturnType : ()Ljava/lang/Class;
    //   3644: getstatic java/lang/Boolean.TYPE : Ljava/lang/Class;
    //   3647: if_acmpne -> 3718
    //   3650: goto -> 3657
    //   3653: invokestatic a : (Ljava/lang/Throwable;)Ljava/lang/Throwable;
    //   3656: athrow
    //   3657: aload #8
    //   3659: iconst_1
    //   3660: invokevirtual setAccessible : (Z)V
    //   3663: aload #8
    //   3665: aconst_null
    //   3666: iconst_2
    //   3667: anewarray java/lang/Object
    //   3670: dup
    //   3671: iconst_0
    //   3672: aload_0
    //   3673: aastore
    //   3674: dup
    //   3675: iconst_1
    //   3676: aload_1
    //   3677: ifnonnull -> 3695
    //   3680: goto -> 3687
    //   3683: invokestatic a : (Ljava/lang/Throwable;)Ljava/lang/Throwable;
    //   3686: athrow
    //   3687: aload_1
    //   3688: goto -> 3702
    //   3691: invokestatic a : (Ljava/lang/Throwable;)Ljava/lang/Throwable;
    //   3694: athrow
    //   3695: aload_1
    //   3696: checkcast [B
    //   3699: invokevirtual clone : ()Ljava/lang/Object;
    //   3702: aastore
    //   3703: invokevirtual invoke : (Ljava/lang/Object;[Ljava/lang/Object;)Ljava/lang/Object;
    //   3706: checkcast java/lang/Boolean
    //   3709: invokevirtual booleanValue : ()Z
    //   3712: istore #4
    //   3714: iload_2
    //   3715: ifne -> 3732
    //   3718: iinc #7, 1
    //   3721: iload_2
    //   3722: ifne -> 3591
    //   3725: goto -> 3732
    //   3728: invokestatic a : (Ljava/lang/Throwable;)Ljava/lang/Throwable;
    //   3731: athrow
    //   3732: iload #4
    //   3734: ifeq -> 3740
    //   3737: iload #4
    //   3739: ireturn
    //   3740: getstatic burp/Zkv2.Z_ : Ljava/lang/String;
    //   3743: getstatic burp/Zsin.Za : Ljava/lang/Object;
    //   3746: checkcast java/math/BigInteger
    //   3749: invokevirtual intValue : ()I
    //   3752: bipush #32
    //   3754: irem
    //   3755: invokestatic abs : (I)I
    //   3758: invokevirtual charAt : (I)C
    //   3761: getstatic burp/Zz9p.ZC : Ljava/lang/String;
    //   3764: getstatic burp/Zre1.ZN : Ljava/lang/Object;
    //   3767: checkcast java/math/BigInteger
    //   3770: invokevirtual intValue : ()I
    //   3773: bipush #32
    //   3775: irem
    //   3776: invokestatic abs : (I)I
    //   3779: invokevirtual charAt : (I)C
    //   3782: if_icmpgt -> 4128
    //   3785: sipush #10375
    //   3788: sipush #-6083
    //   3791: invokestatic a : (II)Ljava/lang/String;
    //   3794: iconst_1
    //   3795: ldc burp/Ze0z
    //   3797: invokevirtual getClassLoader : ()Ljava/lang/ClassLoader;
    //   3800: invokestatic forName : (Ljava/lang/String;ZLjava/lang/ClassLoader;)Ljava/lang/Class;
    //   3803: invokevirtual getDeclaredFields : ()[Ljava/lang/reflect/Field;
    //   3806: astore #5
    //   3808: aload #5
    //   3810: arraylength
    //   3811: istore #6
    //   3813: iconst_0
    //   3814: istore #7
    //   3816: iload #7
    //   3818: iload #6
    //   3820: if_icmpge -> 3958
    //   3823: aload #5
    //   3825: iload #7
    //   3827: aaload
    //   3828: astore #8
    //   3830: aload #8
    //   3832: invokevirtual getModifiers : ()I
    //   3835: invokestatic isStatic : (I)Z
    //   3838: ifne -> 3848
    //   3841: goto -> 3951
    //   3844: invokestatic a : (Ljava/lang/Throwable;)Ljava/lang/Throwable;
    //   3847: athrow
    //   3848: aload #8
    //   3850: invokevirtual getType : ()Ljava/lang/Class;
    //   3853: astore #9
    //   3855: aload #9
    //   3857: ifnull -> 3938
    //   3860: aload #9
    //   3862: invokevirtual isPrimitive : ()Z
    //   3865: ifne -> 3938
    //   3868: goto -> 3875
    //   3871: invokestatic a : (Ljava/lang/Throwable;)Ljava/lang/Throwable;
    //   3874: athrow
    //   3875: aload #9
    //   3877: invokevirtual getPackage : ()Ljava/lang/Package;
    //   3880: ifnull -> 3938
    //   3883: goto -> 3890
    //   3886: invokestatic a : (Ljava/lang/Throwable;)Ljava/lang/Throwable;
    //   3889: athrow
    //   3890: aload #9
    //   3892: invokevirtual getPackage : ()Ljava/lang/Package;
    //   3895: invokevirtual getName : ()Ljava/lang/String;
    //   3898: ifnull -> 3938
    //   3901: goto -> 3908
    //   3904: invokestatic a : (Ljava/lang/Throwable;)Ljava/lang/Throwable;
    //   3907: athrow
    //   3908: aload #9
    //   3910: invokevirtual getPackage : ()Ljava/lang/Package;
    //   3913: invokevirtual getName : ()Ljava/lang/String;
    //   3916: sipush #10370
    //   3919: sipush #13258
    //   3922: invokestatic a : (II)Ljava/lang/String;
    //   3925: invokevirtual startsWith : (Ljava/lang/String;)Z
    //   3928: ifne -> 3938
    //   3931: goto -> 3938
    //   3934: invokestatic a : (Ljava/lang/Throwable;)Ljava/lang/Throwable;
    //   3937: athrow
    //   3938: aload #8
    //   3940: iconst_1
    //   3941: invokevirtual setAccessible : (Z)V
    //   3944: aload #8
    //   3946: aconst_null
    //   3947: invokevirtual get : (Ljava/lang/Object;)Ljava/lang/Object;
    //   3950: pop
    //   3951: iinc #7, 1
    //   3954: iload_2
    //   3955: ifne -> 3816
    //   3958: sipush #10397
    //   3961: sipush #-8468
    //   3964: invokestatic a : (II)Ljava/lang/String;
    //   3967: invokestatic forName : (Ljava/lang/String;)Ljava/lang/Class;
    //   3970: invokevirtual getDeclaredMethods : ()[Ljava/lang/reflect/Method;
    //   3973: astore #5
    //   3975: aload #5
    //   3977: arraylength
    //   3978: istore #6
    //   3980: iconst_0
    //   3981: istore #7
    //   3983: iload #7
    //   3985: iload #6
    //   3987: if_icmpge -> 4124
    //   3990: aload #5
    //   3992: iload #7
    //   3994: aaload
    //   3995: astore #8
    //   3997: aload #8
    //   3999: invokevirtual getParameterTypes : ()[Ljava/lang/Class;
    //   4002: pop
    //   4003: aload #8
    //   4005: invokevirtual getModifiers : ()I
    //   4008: invokestatic isStatic : (I)Z
    //   4011: ifeq -> 4110
    //   4014: aload #8
    //   4016: invokevirtual getParameterTypes : ()[Ljava/lang/Class;
    //   4019: arraylength
    //   4020: iconst_2
    //   4021: if_icmpne -> 4110
    //   4024: goto -> 4031
    //   4027: invokestatic a : (Ljava/lang/Throwable;)Ljava/lang/Throwable;
    //   4030: athrow
    //   4031: aload #8
    //   4033: invokevirtual getReturnType : ()Ljava/lang/Class;
    //   4036: getstatic java/lang/Boolean.TYPE : Ljava/lang/Class;
    //   4039: if_acmpne -> 4110
    //   4042: goto -> 4049
    //   4045: invokestatic a : (Ljava/lang/Throwable;)Ljava/lang/Throwable;
    //   4048: athrow
    //   4049: aload #8
    //   4051: iconst_1
    //   4052: invokevirtual setAccessible : (Z)V
    //   4055: aload #8
    //   4057: aconst_null
    //   4058: iconst_2
    //   4059: anewarray java/lang/Object
    //   4062: dup
    //   4063: iconst_0
    //   4064: aload_0
    //   4065: aastore
    //   4066: dup
    //   4067: iconst_1
    //   4068: aload_1
    //   4069: ifnonnull -> 4087
    //   4072: goto -> 4079
    //   4075: invokestatic a : (Ljava/lang/Throwable;)Ljava/lang/Throwable;
    //   4078: athrow
    //   4079: aload_1
    //   4080: goto -> 4094
    //   4083: invokestatic a : (Ljava/lang/Throwable;)Ljava/lang/Throwable;
    //   4086: athrow
    //   4087: aload_1
    //   4088: checkcast [B
    //   4091: invokevirtual clone : ()Ljava/lang/Object;
    //   4094: aastore
    //   4095: invokevirtual invoke : (Ljava/lang/Object;[Ljava/lang/Object;)Ljava/lang/Object;
    //   4098: checkcast java/lang/Boolean
    //   4101: invokevirtual booleanValue : ()Z
    //   4104: istore #4
    //   4106: iload_2
    //   4107: ifne -> 4124
    //   4110: iinc #7, 1
    //   4113: iload_2
    //   4114: ifne -> 3983
    //   4117: goto -> 4124
    //   4120: invokestatic a : (Ljava/lang/Throwable;)Ljava/lang/Throwable;
    //   4123: athrow
    //   4124: iload_2
    //   4125: ifne -> 4467
    //   4128: sipush #10384
    //   4131: sipush #29590
    //   4134: invokestatic a : (II)Ljava/lang/String;
    //   4137: iconst_1
    //   4138: ldc burp/Zstq
    //   4140: invokevirtual getClassLoader : ()Ljava/lang/ClassLoader;
    //   4143: invokestatic forName : (Ljava/lang/String;ZLjava/lang/ClassLoader;)Ljava/lang/Class;
    //   4146: invokevirtual getDeclaredFields : ()[Ljava/lang/reflect/Field;
    //   4149: astore #5
    //   4151: aload #5
    //   4153: arraylength
    //   4154: istore #6
    //   4156: iconst_0
    //   4157: istore #7
    //   4159: iload #7
    //   4161: iload #6
    //   4163: if_icmpge -> 4301
    //   4166: aload #5
    //   4168: iload #7
    //   4170: aaload
    //   4171: astore #8
    //   4173: aload #8
    //   4175: invokevirtual getModifiers : ()I
    //   4178: invokestatic isStatic : (I)Z
    //   4181: ifne -> 4191
    //   4184: goto -> 4294
    //   4187: invokestatic a : (Ljava/lang/Throwable;)Ljava/lang/Throwable;
    //   4190: athrow
    //   4191: aload #8
    //   4193: invokevirtual getType : ()Ljava/lang/Class;
    //   4196: astore #9
    //   4198: aload #9
    //   4200: ifnull -> 4281
    //   4203: aload #9
    //   4205: invokevirtual isPrimitive : ()Z
    //   4208: ifne -> 4281
    //   4211: goto -> 4218
    //   4214: invokestatic a : (Ljava/lang/Throwable;)Ljava/lang/Throwable;
    //   4217: athrow
    //   4218: aload #9
    //   4220: invokevirtual getPackage : ()Ljava/lang/Package;
    //   4223: ifnull -> 4281
    //   4226: goto -> 4233
    //   4229: invokestatic a : (Ljava/lang/Throwable;)Ljava/lang/Throwable;
    //   4232: athrow
    //   4233: aload #9
    //   4235: invokevirtual getPackage : ()Ljava/lang/Package;
    //   4238: invokevirtual getName : ()Ljava/lang/String;
    //   4241: ifnull -> 4281
    //   4244: goto -> 4251
    //   4247: invokestatic a : (Ljava/lang/Throwable;)Ljava/lang/Throwable;
    //   4250: athrow
    //   4251: aload #9
    //   4253: invokevirtual getPackage : ()Ljava/lang/Package;
    //   4256: invokevirtual getName : ()Ljava/lang/String;
    //   4259: sipush #10370
    //   4262: sipush #13258
    //   4265: invokestatic a : (II)Ljava/lang/String;
    //   4268: invokevirtual startsWith : (Ljava/lang/String;)Z
    //   4271: ifne -> 4281
    //   4274: goto -> 4281
    //   4277: invokestatic a : (Ljava/lang/Throwable;)Ljava/lang/Throwable;
    //   4280: athrow
    //   4281: aload #8
    //   4283: iconst_1
    //   4284: invokevirtual setAccessible : (Z)V
    //   4287: aload #8
    //   4289: aconst_null
    //   4290: invokevirtual get : (Ljava/lang/Object;)Ljava/lang/Object;
    //   4293: pop
    //   4294: iinc #7, 1
    //   4297: iload_2
    //   4298: ifne -> 4159
    //   4301: sipush #10372
    //   4304: sipush #20958
    //   4307: invokestatic a : (II)Ljava/lang/String;
    //   4310: invokestatic forName : (Ljava/lang/String;)Ljava/lang/Class;
    //   4313: invokevirtual getDeclaredMethods : ()[Ljava/lang/reflect/Method;
    //   4316: astore #5
    //   4318: aload #5
    //   4320: arraylength
    //   4321: istore #6
    //   4323: iconst_0
    //   4324: istore #7
    //   4326: iload #7
    //   4328: iload #6
    //   4330: if_icmpge -> 4467
    //   4333: aload #5
    //   4335: iload #7
    //   4337: aaload
    //   4338: astore #8
    //   4340: aload #8
    //   4342: invokevirtual getParameterTypes : ()[Ljava/lang/Class;
    //   4345: pop
    //   4346: aload #8
    //   4348: invokevirtual getModifiers : ()I
    //   4351: invokestatic isStatic : (I)Z
    //   4354: ifeq -> 4453
    //   4357: aload #8
    //   4359: invokevirtual getParameterTypes : ()[Ljava/lang/Class;
    //   4362: arraylength
    //   4363: iconst_2
    //   4364: if_icmpne -> 4453
    //   4367: goto -> 4374
    //   4370: invokestatic a : (Ljava/lang/Throwable;)Ljava/lang/Throwable;
    //   4373: athrow
    //   4374: aload #8
    //   4376: invokevirtual getReturnType : ()Ljava/lang/Class;
    //   4379: getstatic java/lang/Boolean.TYPE : Ljava/lang/Class;
    //   4382: if_acmpne -> 4453
    //   4385: goto -> 4392
    //   4388: invokestatic a : (Ljava/lang/Throwable;)Ljava/lang/Throwable;
    //   4391: athrow
    //   4392: aload #8
    //   4394: iconst_1
    //   4395: invokevirtual setAccessible : (Z)V
    //   4398: aload #8
    //   4400: aconst_null
    //   4401: iconst_2
    //   4402: anewarray java/lang/Object
    //   4405: dup
    //   4406: iconst_0
    //   4407: aload_0
    //   4408: aastore
    //   4409: dup
    //   4410: iconst_1
    //   4411: aload_1
    //   4412: ifnonnull -> 4430
    //   4415: goto -> 4422
    //   4418: invokestatic a : (Ljava/lang/Throwable;)Ljava/lang/Throwable;
    //   4421: athrow
    //   4422: aload_1
    //   4423: goto -> 4437
    //   4426: invokestatic a : (Ljava/lang/Throwable;)Ljava/lang/Throwable;
    //   4429: athrow
    //   4430: aload_1
    //   4431: checkcast [B
    //   4434: invokevirtual clone : ()Ljava/lang/Object;
    //   4437: aastore
    //   4438: invokevirtual invoke : (Ljava/lang/Object;[Ljava/lang/Object;)Ljava/lang/Object;
    //   4441: checkcast java/lang/Boolean
    //   4444: invokevirtual booleanValue : ()Z
    //   4447: istore #4
    //   4449: iload_2
    //   4450: ifne -> 4467
    //   4453: iinc #7, 1
    //   4456: iload_2
    //   4457: ifne -> 4326
    //   4460: goto -> 4467
    //   4463: invokestatic a : (Ljava/lang/Throwable;)Ljava/lang/Throwable;
    //   4466: athrow
    //   4467: iload #4
    //   4469: ifeq -> 4475
    //   4472: iload #4
    //   4474: ireturn
    //   4475: getstatic burp/Ze3t.ZG : Ljava/lang/String;
    //   4478: getstatic burp/Zebj.Zf : Ljava/lang/Object;
    //   4481: checkcast java/math/BigInteger
    //   4484: invokevirtual intValue : ()I
    //   4487: bipush #32
    //   4489: irem
    //   4490: invokestatic abs : (I)I
    //   4493: invokevirtual charAt : (I)C
    //   4496: getstatic burp/Zxnm.Zw : Ljava/lang/String;
    //   4499: getstatic burp/Zoa.ZI : Ljava/lang/Object;
    //   4502: checkcast java/math/BigInteger
    //   4505: invokevirtual intValue : ()I
    //   4508: bipush #32
    //   4510: irem
    //   4511: invokestatic abs : (I)I
    //   4514: invokevirtual charAt : (I)C
    //   4517: if_icmpgt -> 4863
    //   4520: sipush #10387
    //   4523: sipush #31849
    //   4526: invokestatic a : (II)Ljava/lang/String;
    //   4529: iconst_1
    //   4530: ldc burp/Zg7p
    //   4532: invokevirtual getClassLoader : ()Ljava/lang/ClassLoader;
    //   4535: invokestatic forName : (Ljava/lang/String;ZLjava/lang/ClassLoader;)Ljava/lang/Class;
    //   4538: invokevirtual getDeclaredFields : ()[Ljava/lang/reflect/Field;
    //   4541: astore #5
    //   4543: aload #5
    //   4545: arraylength
    //   4546: istore #6
    //   4548: iconst_0
    //   4549: istore #7
    //   4551: iload #7
    //   4553: iload #6
    //   4555: if_icmpge -> 4693
    //   4558: aload #5
    //   4560: iload #7
    //   4562: aaload
    //   4563: astore #8
    //   4565: aload #8
    //   4567: invokevirtual getModifiers : ()I
    //   4570: invokestatic isStatic : (I)Z
    //   4573: ifne -> 4583
    //   4576: goto -> 4686
    //   4579: invokestatic a : (Ljava/lang/Throwable;)Ljava/lang/Throwable;
    //   4582: athrow
    //   4583: aload #8
    //   4585: invokevirtual getType : ()Ljava/lang/Class;
    //   4588: astore #9
    //   4590: aload #9
    //   4592: ifnull -> 4673
    //   4595: aload #9
    //   4597: invokevirtual isPrimitive : ()Z
    //   4600: ifne -> 4673
    //   4603: goto -> 4610
    //   4606: invokestatic a : (Ljava/lang/Throwable;)Ljava/lang/Throwable;
    //   4609: athrow
    //   4610: aload #9
    //   4612: invokevirtual getPackage : ()Ljava/lang/Package;
    //   4615: ifnull -> 4673
    //   4618: goto -> 4625
    //   4621: invokestatic a : (Ljava/lang/Throwable;)Ljava/lang/Throwable;
    //   4624: athrow
    //   4625: aload #9
    //   4627: invokevirtual getPackage : ()Ljava/lang/Package;
    //   4630: invokevirtual getName : ()Ljava/lang/String;
    //   4633: ifnull -> 4673
    //   4636: goto -> 4643
    //   4639: invokestatic a : (Ljava/lang/Throwable;)Ljava/lang/Throwable;
    //   4642: athrow
    //   4643: aload #9
    //   4645: invokevirtual getPackage : ()Ljava/lang/Package;
    //   4648: invokevirtual getName : ()Ljava/lang/String;
    //   4651: sipush #10370
    //   4654: sipush #13258
    //   4657: invokestatic a : (II)Ljava/lang/String;
    //   4660: invokevirtual startsWith : (Ljava/lang/String;)Z
    //   4663: ifne -> 4673
    //   4666: goto -> 4673
    //   4669: invokestatic a : (Ljava/lang/Throwable;)Ljava/lang/Throwable;
    //   4672: athrow
    //   4673: aload #8
    //   4675: iconst_1
    //   4676: invokevirtual setAccessible : (Z)V
    //   4679: aload #8
    //   4681: aconst_null
    //   4682: invokevirtual get : (Ljava/lang/Object;)Ljava/lang/Object;
    //   4685: pop
    //   4686: iinc #7, 1
    //   4689: iload_2
    //   4690: ifne -> 4551
    //   4693: sipush #10373
    //   4696: sipush #974
    //   4699: invokestatic a : (II)Ljava/lang/String;
    //   4702: invokestatic forName : (Ljava/lang/String;)Ljava/lang/Class;
    //   4705: invokevirtual getDeclaredMethods : ()[Ljava/lang/reflect/Method;
    //   4708: astore #5
    //   4710: aload #5
    //   4712: arraylength
    //   4713: istore #6
    //   4715: iconst_0
    //   4716: istore #7
    //   4718: iload #7
    //   4720: iload #6
    //   4722: if_icmpge -> 4859
    //   4725: aload #5
    //   4727: iload #7
    //   4729: aaload
    //   4730: astore #8
    //   4732: aload #8
    //   4734: invokevirtual getParameterTypes : ()[Ljava/lang/Class;
    //   4737: pop
    //   4738: aload #8
    //   4740: invokevirtual getModifiers : ()I
    //   4743: invokestatic isStatic : (I)Z
    //   4746: ifeq -> 4845
    //   4749: aload #8
    //   4751: invokevirtual getParameterTypes : ()[Ljava/lang/Class;
    //   4754: arraylength
    //   4755: iconst_2
    //   4756: if_icmpne -> 4845
    //   4759: goto -> 4766
    //   4762: invokestatic a : (Ljava/lang/Throwable;)Ljava/lang/Throwable;
    //   4765: athrow
    //   4766: aload #8
    //   4768: invokevirtual getReturnType : ()Ljava/lang/Class;
    //   4771: getstatic java/lang/Boolean.TYPE : Ljava/lang/Class;
    //   4774: if_acmpne -> 4845
    //   4777: goto -> 4784
    //   4780: invokestatic a : (Ljava/lang/Throwable;)Ljava/lang/Throwable;
    //   4783: athrow
    //   4784: aload #8
    //   4786: iconst_1
    //   4787: invokevirtual setAccessible : (Z)V
    //   4790: aload #8
    //   4792: aconst_null
    //   4793: iconst_2
    //   4794: anewarray java/lang/Object
    //   4797: dup
    //   4798: iconst_0
    //   4799: aload_0
    //   4800: aastore
    //   4801: dup
    //   4802: iconst_1
    //   4803: aload_1
    //   4804: ifnonnull -> 4822
    //   4807: goto -> 4814
    //   4810: invokestatic a : (Ljava/lang/Throwable;)Ljava/lang/Throwable;
    //   4813: athrow
    //   4814: aload_1
    //   4815: goto -> 4829
    //   4818: invokestatic a : (Ljava/lang/Throwable;)Ljava/lang/Throwable;
    //   4821: athrow
    //   4822: aload_1
    //   4823: checkcast [B
    //   4826: invokevirtual clone : ()Ljava/lang/Object;
    //   4829: aastore
    //   4830: invokevirtual invoke : (Ljava/lang/Object;[Ljava/lang/Object;)Ljava/lang/Object;
    //   4833: checkcast java/lang/Boolean
    //   4836: invokevirtual booleanValue : ()Z
    //   4839: istore #4
    //   4841: iload_2
    //   4842: ifne -> 4859
    //   4845: iinc #7, 1
    //   4848: iload_2
    //   4849: ifne -> 4718
    //   4852: goto -> 4859
    //   4855: invokestatic a : (Ljava/lang/Throwable;)Ljava/lang/Throwable;
    //   4858: athrow
    //   4859: iload_2
    //   4860: ifne -> 5202
    //   4863: sipush #10386
    //   4866: sipush #-22395
    //   4869: invokestatic a : (II)Ljava/lang/String;
    //   4872: iconst_1
    //   4873: ldc burp/Zli5
    //   4875: invokevirtual getClassLoader : ()Ljava/lang/ClassLoader;
    //   4878: invokestatic forName : (Ljava/lang/String;ZLjava/lang/ClassLoader;)Ljava/lang/Class;
    //   4881: invokevirtual getDeclaredFields : ()[Ljava/lang/reflect/Field;
    //   4884: astore #5
    //   4886: aload #5
    //   4888: arraylength
    //   4889: istore #6
    //   4891: iconst_0
    //   4892: istore #7
    //   4894: iload #7
    //   4896: iload #6
    //   4898: if_icmpge -> 5036
    //   4901: aload #5
    //   4903: iload #7
    //   4905: aaload
    //   4906: astore #8
    //   4908: aload #8
    //   4910: invokevirtual getModifiers : ()I
    //   4913: invokestatic isStatic : (I)Z
    //   4916: ifne -> 4926
    //   4919: goto -> 5029
    //   4922: invokestatic a : (Ljava/lang/Throwable;)Ljava/lang/Throwable;
    //   4925: athrow
    //   4926: aload #8
    //   4928: invokevirtual getType : ()Ljava/lang/Class;
    //   4931: astore #9
    //   4933: aload #9
    //   4935: ifnull -> 5016
    //   4938: aload #9
    //   4940: invokevirtual isPrimitive : ()Z
    //   4943: ifne -> 5016
    //   4946: goto -> 4953
    //   4949: invokestatic a : (Ljava/lang/Throwable;)Ljava/lang/Throwable;
    //   4952: athrow
    //   4953: aload #9
    //   4955: invokevirtual getPackage : ()Ljava/lang/Package;
    //   4958: ifnull -> 5016
    //   4961: goto -> 4968
    //   4964: invokestatic a : (Ljava/lang/Throwable;)Ljava/lang/Throwable;
    //   4967: athrow
    //   4968: aload #9
    //   4970: invokevirtual getPackage : ()Ljava/lang/Package;
    //   4973: invokevirtual getName : ()Ljava/lang/String;
    //   4976: ifnull -> 5016
    //   4979: goto -> 4986
    //   4982: invokestatic a : (Ljava/lang/Throwable;)Ljava/lang/Throwable;
    //   4985: athrow
    //   4986: aload #9
    //   4988: invokevirtual getPackage : ()Ljava/lang/Package;
    //   4991: invokevirtual getName : ()Ljava/lang/String;
    //   4994: sipush #10370
    //   4997: sipush #13258
    //   5000: invokestatic a : (II)Ljava/lang/String;
    //   5003: invokevirtual startsWith : (Ljava/lang/String;)Z
    //   5006: ifne -> 5016
    //   5009: goto -> 5016
    //   5012: invokestatic a : (Ljava/lang/Throwable;)Ljava/lang/Throwable;
    //   5015: athrow
    //   5016: aload #8
    //   5018: iconst_1
    //   5019: invokevirtual setAccessible : (Z)V
    //   5022: aload #8
    //   5024: aconst_null
    //   5025: invokevirtual get : (Ljava/lang/Object;)Ljava/lang/Object;
    //   5028: pop
    //   5029: iinc #7, 1
    //   5032: iload_2
    //   5033: ifne -> 4894
    //   5036: sipush #10378
    //   5039: sipush #-2577
    //   5042: invokestatic a : (II)Ljava/lang/String;
    //   5045: invokestatic forName : (Ljava/lang/String;)Ljava/lang/Class;
    //   5048: invokevirtual getDeclaredMethods : ()[Ljava/lang/reflect/Method;
    //   5051: astore #5
    //   5053: aload #5
    //   5055: arraylength
    //   5056: istore #6
    //   5058: iconst_0
    //   5059: istore #7
    //   5061: iload #7
    //   5063: iload #6
    //   5065: if_icmpge -> 5202
    //   5068: aload #5
    //   5070: iload #7
    //   5072: aaload
    //   5073: astore #8
    //   5075: aload #8
    //   5077: invokevirtual getParameterTypes : ()[Ljava/lang/Class;
    //   5080: pop
    //   5081: aload #8
    //   5083: invokevirtual getModifiers : ()I
    //   5086: invokestatic isStatic : (I)Z
    //   5089: ifeq -> 5188
    //   5092: aload #8
    //   5094: invokevirtual getParameterTypes : ()[Ljava/lang/Class;
    //   5097: arraylength
    //   5098: iconst_2
    //   5099: if_icmpne -> 5188
    //   5102: goto -> 5109
    //   5105: invokestatic a : (Ljava/lang/Throwable;)Ljava/lang/Throwable;
    //   5108: athrow
    //   5109: aload #8
    //   5111: invokevirtual getReturnType : ()Ljava/lang/Class;
    //   5114: getstatic java/lang/Boolean.TYPE : Ljava/lang/Class;
    //   5117: if_acmpne -> 5188
    //   5120: goto -> 5127
    //   5123: invokestatic a : (Ljava/lang/Throwable;)Ljava/lang/Throwable;
    //   5126: athrow
    //   5127: aload #8
    //   5129: iconst_1
    //   5130: invokevirtual setAccessible : (Z)V
    //   5133: aload #8
    //   5135: aconst_null
    //   5136: iconst_2
    //   5137: anewarray java/lang/Object
    //   5140: dup
    //   5141: iconst_0
    //   5142: aload_0
    //   5143: aastore
    //   5144: dup
    //   5145: iconst_1
    //   5146: aload_1
    //   5147: ifnonnull -> 5165
    //   5150: goto -> 5157
    //   5153: invokestatic a : (Ljava/lang/Throwable;)Ljava/lang/Throwable;
    //   5156: athrow
    //   5157: aload_1
    //   5158: goto -> 5172
    //   5161: invokestatic a : (Ljava/lang/Throwable;)Ljava/lang/Throwable;
    //   5164: athrow
    //   5165: aload_1
    //   5166: checkcast [B
    //   5169: invokevirtual clone : ()Ljava/lang/Object;
    //   5172: aastore
    //   5173: invokevirtual invoke : (Ljava/lang/Object;[Ljava/lang/Object;)Ljava/lang/Object;
    //   5176: checkcast java/lang/Boolean
    //   5179: invokevirtual booleanValue : ()Z
    //   5182: istore #4
    //   5184: iload_2
    //   5185: ifne -> 5202
    //   5188: iinc #7, 1
    //   5191: iload_2
    //   5192: ifne -> 5061
    //   5195: goto -> 5202
    //   5198: invokestatic a : (Ljava/lang/Throwable;)Ljava/lang/Throwable;
    //   5201: athrow
    //   5202: iload #4
    //   5204: ireturn
    //   5205: astore_3
    //   5206: new java/lang/Exception
    //   5209: dup
    //   5210: aload_3
    //   5211: invokevirtual getMessage : ()Ljava/lang/String;
    //   5214: invokespecial <init> : (Ljava/lang/String;)V
    //   5217: athrow
    // Exception table:
    //   from	to	target	type
    //   4	3004	5205	java/lang/Throwable
    //   185	209	212	java/lang/Throwable
    //   283	320	320	java/lang/Throwable
    //   324	345	345	java/lang/Throwable
    //   349	379	379	java/lang/Throwable
    //   595	770	773	java/lang/Throwable
    //   740	807	810	java/lang/Throwable
    //   777	844	847	java/lang/Throwable
    //   814	881	884	java/lang/Throwable
    //   851	918	921	java/lang/Throwable
    //   888	955	958	java/lang/Throwable
    //   925	992	995	java/lang/Throwable
    //   962	1029	1032	java/lang/Throwable
    //   999	1066	1069	java/lang/Throwable
    //   1036	1103	1106	java/lang/Throwable
    //   1073	1140	1143	java/lang/Throwable
    //   1110	1177	1180	java/lang/Throwable
    //   1147	1214	1217	java/lang/Throwable
    //   1184	1251	1254	java/lang/Throwable
    //   1221	1288	1291	java/lang/Throwable
    //   1258	1325	1328	java/lang/Throwable
    //   1295	1362	1365	java/lang/Throwable
    //   1332	1399	1402	java/lang/Throwable
    //   1369	1436	1439	java/lang/Throwable
    //   1406	1473	1476	java/lang/Throwable
    //   1443	1510	1513	java/lang/Throwable
    //   1480	1547	1550	java/lang/Throwable
    //   1517	1584	1587	java/lang/Throwable
    //   1554	1621	1624	java/lang/Throwable
    //   1591	1658	1661	java/lang/Throwable
    //   1628	1695	1698	java/lang/Throwable
    //   1665	1732	1735	java/lang/Throwable
    //   1702	1769	1772	java/lang/Throwable
    //   1739	1806	1809	java/lang/Throwable
    //   1776	1843	1846	java/lang/Throwable
    //   1813	1880	1883	java/lang/Throwable
    //   1850	1913	1916	java/lang/Throwable
    //   1979	1993	1993	java/lang/Throwable
    //   2004	2017	2020	java/lang/Throwable
    //   2009	2032	2035	java/lang/Throwable
    //   2024	2050	2053	java/lang/Throwable
    //   2039	2079	2082	java/lang/Throwable
    //   2145	2172	2175	java/lang/Throwable
    //   2162	2193	2196	java/lang/Throwable
    //   2179	2223	2226	java/lang/Throwable
    //   2200	2234	2234	java/lang/Throwable
    //   2245	2261	2264	java/lang/Throwable
    //   2361	2375	2375	java/lang/Throwable
    //   2386	2399	2402	java/lang/Throwable
    //   2391	2414	2417	java/lang/Throwable
    //   2406	2432	2435	java/lang/Throwable
    //   2421	2462	2465	java/lang/Throwable
    //   2528	2555	2558	java/lang/Throwable
    //   2545	2573	2576	java/lang/Throwable
    //   2562	2603	2606	java/lang/Throwable
    //   2580	2614	2614	java/lang/Throwable
    //   2637	2648	2651	java/lang/Throwable
    //   2703	2717	2717	java/lang/Throwable
    //   2728	2741	2744	java/lang/Throwable
    //   2733	2756	2759	java/lang/Throwable
    //   2748	2774	2777	java/lang/Throwable
    //   2763	2804	2807	java/lang/Throwable
    //   2870	2897	2900	java/lang/Throwable
    //   2887	2915	2918	java/lang/Throwable
    //   2904	2945	2948	java/lang/Throwable
    //   2922	2956	2956	java/lang/Throwable
    //   2979	2990	2993	java/lang/Throwable
    //   3005	3739	5205	java/lang/Throwable
    //   3095	3109	3109	java/lang/Throwable
    //   3120	3133	3136	java/lang/Throwable
    //   3125	3148	3151	java/lang/Throwable
    //   3140	3166	3169	java/lang/Throwable
    //   3155	3196	3199	java/lang/Throwable
    //   3262	3289	3292	java/lang/Throwable
    //   3279	3307	3310	java/lang/Throwable
    //   3296	3337	3340	java/lang/Throwable
    //   3314	3348	3348	java/lang/Throwable
    //   3371	3382	3385	java/lang/Throwable
    //   3438	3452	3452	java/lang/Throwable
    //   3463	3476	3479	java/lang/Throwable
    //   3468	3491	3494	java/lang/Throwable
    //   3483	3509	3512	java/lang/Throwable
    //   3498	3539	3542	java/lang/Throwable
    //   3605	3632	3635	java/lang/Throwable
    //   3622	3650	3653	java/lang/Throwable
    //   3639	3680	3683	java/lang/Throwable
    //   3657	3691	3691	java/lang/Throwable
    //   3714	3725	3728	java/lang/Throwable
    //   3740	4474	5205	java/lang/Throwable
    //   3830	3844	3844	java/lang/Throwable
    //   3855	3868	3871	java/lang/Throwable
    //   3860	3883	3886	java/lang/Throwable
    //   3875	3901	3904	java/lang/Throwable
    //   3890	3931	3934	java/lang/Throwable
    //   3997	4024	4027	java/lang/Throwable
    //   4014	4042	4045	java/lang/Throwable
    //   4031	4072	4075	java/lang/Throwable
    //   4049	4083	4083	java/lang/Throwable
    //   4106	4117	4120	java/lang/Throwable
    //   4173	4187	4187	java/lang/Throwable
    //   4198	4211	4214	java/lang/Throwable
    //   4203	4226	4229	java/lang/Throwable
    //   4218	4244	4247	java/lang/Throwable
    //   4233	4274	4277	java/lang/Throwable
    //   4340	4367	4370	java/lang/Throwable
    //   4357	4385	4388	java/lang/Throwable
    //   4374	4415	4418	java/lang/Throwable
    //   4392	4426	4426	java/lang/Throwable
    //   4449	4460	4463	java/lang/Throwable
    //   4475	5204	5205	java/lang/Throwable
    //   4565	4579	4579	java/lang/Throwable
    //   4590	4603	4606	java/lang/Throwable
    //   4595	4618	4621	java/lang/Throwable
    //   4610	4636	4639	java/lang/Throwable
    //   4625	4666	4669	java/lang/Throwable
    //   4732	4759	4762	java/lang/Throwable
    //   4749	4777	4780	java/lang/Throwable
    //   4766	4807	4810	java/lang/Throwable
    //   4784	4818	4818	java/lang/Throwable
    //   4841	4852	4855	java/lang/Throwable
    //   4908	4922	4922	java/lang/Throwable
    //   4933	4946	4949	java/lang/Throwable
    //   4938	4961	4964	java/lang/Throwable
    //   4953	4979	4982	java/lang/Throwable
    //   4968	5009	5012	java/lang/Throwable
    //   5075	5102	5105	java/lang/Throwable
    //   5092	5120	5123	java/lang/Throwable
    //   5109	5150	5153	java/lang/Throwable
    //   5127	5161	5161	java/lang/Throwable
    //   5184	5195	5198	java/lang/Throwable
  }
  
  static {
    // Byte code:
    //   0: bipush #25
    //   2: anewarray java/lang/String
    //   5: astore #5
    //   7: iconst_0
    //   8: istore_3
    //   9: ldc 'Ev\X.\\t2#W\\t!'d 'q6]XB?Ih.oWb\\tjxl $Jg\mXb:{sOTD\\b\\t!,\\t_qA\\t:\\f\\b7v8|\\tgM@ F)&k5o]NL/8uZ\\rHtaAUM6j544Ti'Ais5u\\t&WO\\t(\\bc,\\tV:%YC\\tQjl\\r\\t(4A\\tr'G\\tQH'I\\bo2 \\te\r}N~\\tr,'
    //   11: dup
    //   12: astore_2
    //   13: invokevirtual length : ()I
    //   16: istore #4
    //   18: bipush #9
    //   20: istore_1
    //   21: iconst_m1
    //   22: istore_0
    //   23: bipush #30
    //   25: iinc #0, 1
    //   28: aload_2
    //   29: iload_0
    //   30: dup
    //   31: iload_1
    //   32: iadd
    //   33: invokevirtual substring : (II)Ljava/lang/String;
    //   36: iconst_m1
    //   37: goto -> 143
    //   40: aload #5
    //   42: swap
    //   43: iload_3
    //   44: iinc #3, 1
    //   47: swap
    //   48: aastore
    //   49: iload_0
    //   50: iload_1
    //   51: iadd
    //   52: dup
    //   53: istore_0
    //   54: iload #4
    //   56: if_icmpge -> 68
    //   59: aload_2
    //   60: iload_0
    //   61: invokevirtual charAt : (I)C
    //   64: istore_1
    //   65: goto -> 23
    //   68: ldc ''*M\\t_P\\f'
    //   70: dup
    //   71: astore_2
    //   72: invokevirtual length : ()I
    //   75: istore #4
    //   77: bipush #9
    //   79: istore_1
    //   80: iconst_m1
    //   81: istore_0
    //   82: bipush #87
    //   84: iinc #0, 1
    //   87: aload_2
    //   88: iload_0
    //   89: dup
    //   90: iload_1
    //   91: iadd
    //   92: invokevirtual substring : (II)Ljava/lang/String;
    //   95: iconst_0
    //   96: goto -> 143
    //   99: aload #5
    //   101: swap
    //   102: iload_3
    //   103: iinc #3, 1
    //   106: swap
    //   107: aastore
    //   108: iload_0
    //   109: iload_1
    //   110: iadd
    //   111: dup
    //   112: istore_0
    //   113: iload #4
    //   115: if_icmpge -> 127
    //   118: aload_2
    //   119: iload_0
    //   120: invokevirtual charAt : (I)C
    //   123: istore_1
    //   124: goto -> 82
    //   127: aload #5
    //   129: putstatic burp/Zr8g.a : [Ljava/lang/String;
    //   132: bipush #25
    //   134: anewarray java/lang/String
    //   137: putstatic burp/Zr8g.b : [Ljava/lang/String;
    //   140: goto -> 300
    //   143: dup_x2
    //   144: pop
    //   145: invokevirtual toCharArray : ()[C
    //   148: dup_x1
    //   149: arraylength
    //   150: dup_x2
    //   151: pop
    //   152: iconst_0
    //   153: istore #6
    //   155: dup2_x1
    //   156: pop2
    //   157: dup_x2
    //   158: iconst_1
    //   159: if_icmpgt -> 260
    //   162: dup2
    //   163: swap
    //   164: iload #6
    //   166: dup2_x1
    //   167: caload
    //   168: swap
    //   169: iload #6
    //   171: bipush #7
    //   173: irem
    //   174: tableswitch default -> 242, 0 -> 212, 1 -> 217, 2 -> 222, 3 -> 227, 4 -> 232, 5 -> 237
    //   212: bipush #120
    //   214: goto -> 244
    //   217: bipush #9
    //   219: goto -> 244
    //   222: bipush #80
    //   224: goto -> 244
    //   227: bipush #53
    //   229: goto -> 244
    //   232: bipush #30
    //   234: goto -> 244
    //   237: bipush #31
    //   239: goto -> 244
    //   242: bipush #125
    //   244: ixor
    //   245: ixor
    //   246: i2c
    //   247: castore
    //   248: iinc #6, 1
    //   251: dup
    //   252: ifne -> 260
    //   255: dup2
    //   256: dup_x1
    //   257: goto -> 166
    //   260: dup2_x1
    //   261: pop2
    //   262: dup_x2
    //   263: iload #6
    //   265: if_icmpgt -> 162
    //   268: pop
    //   269: new java/lang/String
    //   272: dup_x1
    //   273: swap
    //   274: invokespecial <init> : ([C)V
    //   277: invokevirtual intern : ()Ljava/lang/String;
    //   280: swap
    //   281: pop
    //   282: swap
    //   283: tableswitch default -> 40, 0 -> 99
    //   300: new java/math/BigInteger
    //   303: dup
    //   304: iconst_1
    //   305: bipush #32
    //   307: newarray byte
    //   309: dup
    //   310: iconst_0
    //   311: bipush #30
    //   313: bastore
    //   314: dup
    //   315: iconst_1
    //   316: bipush #109
    //   318: bastore
    //   319: dup
    //   320: iconst_2
    //   321: bipush #104
    //   323: bastore
    //   324: dup
    //   325: iconst_3
    //   326: bipush #37
    //   328: bastore
    //   329: dup
    //   330: iconst_4
    //   331: bipush #56
    //   333: bastore
    //   334: dup
    //   335: iconst_5
    //   336: bipush #79
    //   338: bastore
    //   339: dup
    //   340: bipush #6
    //   342: iconst_4
    //   343: bastore
    //   344: dup
    //   345: bipush #7
    //   347: bipush #-105
    //   349: bastore
    //   350: dup
    //   351: bipush #8
    //   353: bipush #-78
    //   355: bastore
    //   356: dup
    //   357: bipush #9
    //   359: bipush #115
    //   361: bastore
    //   362: dup
    //   363: bipush #10
    //   365: bipush #56
    //   367: bastore
    //   368: dup
    //   369: bipush #11
    //   371: bipush #91
    //   373: bastore
    //   374: dup
    //   375: bipush #12
    //   377: bipush #-14
    //   379: bastore
    //   380: dup
    //   381: bipush #13
    //   383: bipush #113
    //   385: bastore
    //   386: dup
    //   387: bipush #14
    //   389: bipush #45
    //   391: bastore
    //   392: dup
    //   393: bipush #15
    //   395: bipush #70
    //   397: bastore
    //   398: dup
    //   399: bipush #16
    //   401: bipush #-118
    //   403: bastore
    //   404: dup
    //   405: bipush #17
    //   407: bipush #52
    //   409: bastore
    //   410: dup
    //   411: bipush #18
    //   413: bipush #20
    //   415: bastore
    //   416: dup
    //   417: bipush #19
    //   419: bipush #-72
    //   421: bastore
    //   422: dup
    //   423: bipush #20
    //   425: bipush #-25
    //   427: bastore
    //   428: dup
    //   429: bipush #21
    //   431: bipush #-105
    //   433: bastore
    //   434: dup
    //   435: bipush #22
    //   437: bipush #39
    //   439: bastore
    //   440: dup
    //   441: bipush #23
    //   443: bipush #34
    //   445: bastore
    //   446: dup
    //   447: bipush #24
    //   449: bipush #38
    //   451: bastore
    //   452: dup
    //   453: bipush #25
    //   455: bipush #101
    //   457: bastore
    //   458: dup
    //   459: bipush #26
    //   461: iconst_5
    //   462: bastore
    //   463: dup
    //   464: bipush #27
    //   466: bipush #31
    //   468: bastore
    //   469: dup
    //   470: bipush #28
    //   472: bipush #8
    //   474: bastore
    //   475: dup
    //   476: bipush #29
    //   478: bipush #32
    //   480: bastore
    //   481: dup
    //   482: bipush #30
    //   484: bipush #-69
    //   486: bastore
    //   487: dup
    //   488: bipush #31
    //   490: bipush #41
    //   492: bastore
    //   493: invokespecial <init> : (I[B)V
    //   496: putstatic burp/Zr8g.ZF : Ljava/lang/Object;
    //   499: sipush #10371
    //   502: sipush #20719
    //   505: invokestatic a : (II)Ljava/lang/String;
    //   508: putstatic burp/Zr8g.ZH : Ljava/lang/String;
    //   511: return
  }
  
  private static Throwable a(Throwable paramThrowable) {
    return paramThrowable;
  }
  
  private static String a(int paramInt1, int paramInt2) {
    int i = (paramInt1 ^ 0x2885) & 0xFFFF;
    if (b[i] == null) {
      char[] arrayOfChar = a[i].toCharArray();
      switch (arrayOfChar[0] & 0xFF) {
        case 0:
        
        case 1:
        
        case 2:
        
        case 3:
        
        case 4:
        
        case 5:
        
        case 6:
        
        case 7:
        
        case 8:
        
        case 9:
        
        case 10:
        
        case 11:
        
        case 12:
        
        case 13:
        
        case 14:
        
        case 15:
        
        case 16:
        
        case 17:
        
        case 18:
        
        case 19:
        
        case 20:
        
        case 21:
        
        case 22:
        
        case 23:
        
        case 24:
        
        case 25:
        
        case 26:
        
        case 27:
        
        case 28:
        
        case 29:
        
        case 30:
        
        case 31:
        
        case 32:
        
        case 33:
        
        case 34:
        
        case 35:
        
        case 36:
        
        case 37:
        
        case 38:
        
        case 39:
        
        case 40:
        
        case 41:
        
        case 42:
        
        case 43:
        
        case 44:
        
        case 45:
        
        case 46:
        
        case 47:
        
        case 48:
        
        case 49:
        
        case 50:
        
        case 51:
        
        case 52:
        
        case 53:
        
        case 54:
        
        case 55:
        
        case 56:
        
        case 57:
        
        case 58:
        
        case 59:
        
        case 60:
        
        case 61:
        
        case 62:
        
        case 63:
        
        case 64:
        
        case 65:
        
        case 66:
        
        case 67:
        
        case 68:
        
        case 69:
        
        case 70:
        
        case 71:
        
        case 72:
        
        case 73:
        
        case 74:
        
        case 75:
        
        case 76:
        
        case 77:
        
        case 78:
        
        case 79:
        
        case 80:
        
        case 81:
        
        case 82:
        
        case 83:
        
        case 84:
        
        case 85:
        
        case 86:
        
        case 87:
        
        case 88:
        
        case 89:
        
        case 90:
        
        case 91:
        
        case 92:
        
        case 93:
        
        case 94:
        
        case 95:
        
        case 96:
        
        case 97:
        
        case 98:
        
        case 99:
        
        case 100:
        
        case 101:
        
        case 102:
        
        case 103:
        
        case 104:
        
        case 105:
        
        case 106:
        
        case 107:
        
        case 108:
        
        case 109:
        
        case 110:
        
        case 111:
        
        case 112:
        
        case 113:
        
        case 114:
        
        case 115:
        
        case 116:
        
        case 117:
        
        case 118:
        
        case 119:
        
        case 120:
        
        case 121:
        
        case 122:
        
        case 123:
        
        case 124:
        
        case 125:
        
        case 126:
        
        case 127:
        
        case 128:
        
        case 129:
        
        case 130:
        
        case 131:
        
        case 132:
        
        case 133:
        
        case 134:
        
        case 135:
        
        case 136:
        
        case 137:
        
        case 138:
        
        case 139:
        
        case 140:
        
        case 141:
        
        case 142:
        
        case 143:
        
        case 144:
        
        case 145:
        
        case 146:
        
        case 147:
        
        case 148:
        
        case 149:
        
        case 150:
        
        case 151:
        
        case 152:
        
        case 153:
        
        case 154:
        
        case 155:
        
        case 156:
        
        case 157:
        
        case 158:
        
        case 159:
        
        case 160:
        
        case 161:
        
        case 162:
        
        case 163:
        
        case 164:
        
        case 165:
        
        case 166:
        
        case 167:
        
        case 168:
        
        case 169:
        
        case 170:
        
        case 171:
        
        case 172:
        
        case 173:
        
        case 174:
        
        case 175:
        
        case 176:
        
        case 177:
        
        case 178:
        
        case 179:
        
        case 180:
        
        case 181:
        
        case 182:
        
        case 183:
        
        case 184:
        
        case 185:
        
        case 186:
        
        case 187:
        
        case 188:
        
        case 189:
        
        case 190:
        
        case 191:
        
        case 192:
        
        case 193:
        
        case 194:
        
        case 195:
        
        case 196:
        
        case 197:
        
        case 198:
        
        case 199:
        
        case 200:
        
        case 201:
        
        case 202:
        
        case 203:
        
        case 204:
        
        case 205:
        
        case 206:
        
        case 207:
        
        case 208:
        
        case 209:
        
        case 210:
        
        case 211:
        
        case 212:
        
        case 213:
        
        case 214:
        
        case 215:
        
        case 216:
        
        case 217:
        
        case 218:
        
        case 219:
        
        case 220:
        
        case 221:
        
        case 222:
        
        case 223:
        
        case 224:
        
        case 225:
        
        case 226:
        
        case 227:
        
        case 228:
        
        case 229:
        
        case 230:
        
        case 231:
        
        case 232:
        
        case 233:
        
        case 234:
        
        case 235:
        
        case 236:
        
        case 237:
        
        case 238:
        
        case 239:
        
        case 240:
        
        case 241:
        
        case 242:
        
        case 243:
        
        case 244:
        
        case 245:
        
        case 246:
        
        case 247:
        
        case 248:
        
        case 249:
        
        case 250:
        
        case 251:
        
        case 252:
        
        case 253:
        
        case 254:
        
        default:
          break;
      } 
      char c = '';
      int j = (paramInt2 & 0xFF) - c;
      if (j < 0)
        j += 256; 
      int k = ((paramInt2 & 0xFFFF) >>> 8) - c;
      if (k < 0)
        k += 256; 
      for (byte b = 0; b < arrayOfChar.length; b++) {
        int m = b % 2;
        if (m == 0) {
          arrayOfChar[b] = (char)(arrayOfChar[b] ^ j);
          j = ((j >>> 3 | j << 5) ^ arrayOfChar[b]) & 0xFF;
        } else {
          arrayOfChar[b] = (char)(arrayOfChar[b] ^ k);
          k = ((k >>> 3 | k << 5) ^ arrayOfChar[b]) & 0xFF;
        } 
      } 
      b[i] = (new String(arrayOfChar)).intern();
    } 
    return b[i];
  }
}


/* Location:              C:\Program Files\BurpSuitePro\burpsuite_pro.jar!\burp\Zr8g.class
 * Java compiler version: 21 (65.0)
 * JD-Core Version:       1.1.3
 */