package burp;

import java.awt.event.MouseAdapter;
import java.awt.event.MouseEvent;

class Zr8x extends MouseAdapter {
  final Zbde Zr;
  
  Zr8x(Zbde paramZbde) {}
  
  public void mouseEntered(MouseEvent paramMouseEvent) {
    this.Zr.ZX.Zx();
    this.Zr.ZT.Zx();
    this.Zr.ZQ.repaint();
  }
  
  public void mouseExited(MouseEvent paramMouseEvent) {
    this.Zr.ZX.Zm();
    this.Zr.ZT.Zm();
    this.Zr.ZQ.repaint();
  }
  
  public void mousePressed(MouseEvent paramMouseEvent) {
    this.Zr.ZX.Zj();
    this.Zr.ZT.Zj();
    this.Zr.ZQ.repaint();
  }
  
  public void mouseReleased(MouseEvent paramMouseEvent) {
    // Byte code:
    //   0: invokestatic Zy : ()Ljava/lang/String;
    //   3: astore_2
    //   4: aload_0
    //   5: getfield Zr : Lburp/Zbde;
    //   8: getfield ZA : Z
    //   11: ifeq -> 25
    //   14: aload_0
    //   15: getfield Zr : Lburp/Zbde;
    //   18: invokevirtual ZS : ()V
    //   21: aload_2
    //   22: ifnull -> 32
    //   25: aload_0
    //   26: getfield Zr : Lburp/Zbde;
    //   29: invokevirtual Zr : ()V
    //   32: aload_0
    //   33: getfield Zr : Lburp/Zbde;
    //   36: getfield ZQ : Lburp/Zm9t;
    //   39: invokevirtual repaint : ()V
    //   42: return
  }
}


/* Location:              C:\Program Files\BurpSuitePro\burpsuite_pro.jar!\burp\Zr8x.class
 * Java compiler version: 21 (65.0)
 * JD-Core Version:       1.1.3
 */