package burp;

import java.math.BigInteger;

class Zr_y extends ClassLoader {
  static Object ZI;
  
  static String Zb;
  
  private static final String[] a;
  
  private static final String[] b;
  
  static void ZY(Object paramObject) {
    Zxdh.Zj = a(-15912, -24607);
    Zxdh.ZD = new BigInteger(a(-15905, -10625));
    boolean bool = Zt2e.ZN();
    try {
      try {
        if (Zlp7.ZO.charAt(Math.abs(((BigInteger)Zs9k.ZX).intValue() % 32)) > Zrj3.ZT.charAt(Math.abs(((BigInteger)Zrj3.ZA).intValue() % 32))) {
          try {
            Ztdt.Zo(Class.forName(a(-15911, 13992)));
            if (!bool)
              Zs34.ZT(Class.forName(a(-15916, -31592))); 
          } catch (Throwable throwable) {
            throw a(null);
          } 
          return;
        } 
      } catch (Throwable throwable) {
        throw a(null);
      } 
      Zs34.ZT(Class.forName(a(-15916, -31592)));
    } catch (Throwable throwable) {}
  }
  
  static boolean ZI(Object[] paramArrayOfObject, Object paramObject) throws Throwable {
    // Byte code:
    //   0: invokestatic ZK : ()Z
    //   3: istore_2
    //   4: new java/io/ByteArrayOutputStream
    //   7: dup
    //   8: invokespecial <init> : ()V
    //   11: astore_3
    //   12: getstatic burp/Zth7.Zf : Ljava/lang/String;
    //   15: astore #4
    //   17: iconst_0
    //   18: istore #5
    //   20: iload #5
    //   22: aload #4
    //   24: invokevirtual length : ()I
    //   27: if_icmpge -> 57
    //   30: aload_3
    //   31: aload #4
    //   33: iload #5
    //   35: iload #5
    //   37: iconst_2
    //   38: iadd
    //   39: invokevirtual substring : (II)Ljava/lang/String;
    //   42: bipush #16
    //   44: invokestatic parseInt : (Ljava/lang/String;I)I
    //   47: invokevirtual write : (I)V
    //   50: iinc #5, 2
    //   53: iload_2
    //   54: ifeq -> 20
    //   57: aload_3
    //   58: invokevirtual toByteArray : ()[B
    //   61: astore #5
    //   63: getstatic burp/Zr0.ZX : Ljava/lang/Object;
    //   66: checkcast java/math/BigInteger
    //   69: invokevirtual toByteArray : ()[B
    //   72: astore #6
    //   74: sipush #256
    //   77: newarray byte
    //   79: astore #8
    //   81: sipush #256
    //   84: newarray int
    //   86: astore #9
    //   88: sipush #256
    //   91: newarray int
    //   93: astore #10
    //   95: sipush #256
    //   98: newarray int
    //   100: astore #11
    //   102: sipush #256
    //   105: newarray int
    //   107: astore #12
    //   109: bipush #10
    //   111: newarray int
    //   113: astore #13
    //   115: sipush #283
    //   118: istore #14
    //   120: iconst_0
    //   121: istore #16
    //   123: iload #16
    //   125: sipush #256
    //   128: if_icmpge -> 362
    //   131: sipush #-15914
    //   134: sipush #-9081
    //   137: invokestatic a : (II)Ljava/lang/String;
    //   140: iload #16
    //   142: iconst_1
    //   143: iushr
    //   144: invokevirtual charAt : (I)C
    //   147: istore #25
    //   149: iload #16
    //   151: iconst_1
    //   152: iand
    //   153: ifne -> 168
    //   156: iload #25
    //   158: bipush #8
    //   160: iushr
    //   161: goto -> 170
    //   164: invokestatic a : (Ljava/lang/Throwable;)Ljava/lang/Throwable;
    //   167: athrow
    //   168: iload #25
    //   170: i2b
    //   171: sipush #255
    //   174: iand
    //   175: istore #15
    //   177: iload #16
    //   179: iconst_1
    //   180: ishl
    //   181: istore #17
    //   183: iload #17
    //   185: sipush #256
    //   188: if_icmplt -> 198
    //   191: iload #17
    //   193: iload #14
    //   195: ixor
    //   196: istore #17
    //   198: iload #17
    //   200: iconst_1
    //   201: ishl
    //   202: istore #18
    //   204: iload #18
    //   206: sipush #256
    //   209: if_icmplt -> 219
    //   212: iload #18
    //   214: iload #14
    //   216: ixor
    //   217: istore #18
    //   219: iload #18
    //   221: iconst_1
    //   222: ishl
    //   223: istore #19
    //   225: iload #19
    //   227: sipush #256
    //   230: if_icmplt -> 240
    //   233: iload #19
    //   235: iload #14
    //   237: ixor
    //   238: istore #19
    //   240: iload #19
    //   242: iload #16
    //   244: ixor
    //   245: istore #20
    //   247: iload #20
    //   249: iload #17
    //   251: ixor
    //   252: istore #21
    //   254: iload #20
    //   256: iload #18
    //   258: ixor
    //   259: istore #22
    //   261: iload #19
    //   263: iload #18
    //   265: ixor
    //   266: iload #17
    //   268: ixor
    //   269: istore #23
    //   271: aload #8
    //   273: iload #16
    //   275: iload #15
    //   277: i2b
    //   278: bastore
    //   279: aload #9
    //   281: iload #15
    //   283: iload #23
    //   285: bipush #24
    //   287: ishl
    //   288: iload #20
    //   290: bipush #16
    //   292: ishl
    //   293: ior
    //   294: iload #22
    //   296: bipush #8
    //   298: ishl
    //   299: ior
    //   300: iload #21
    //   302: ior
    //   303: dup
    //   304: istore #24
    //   306: iastore
    //   307: aload #10
    //   309: iload #15
    //   311: iload #24
    //   313: bipush #8
    //   315: iushr
    //   316: iload #24
    //   318: bipush #24
    //   320: ishl
    //   321: ior
    //   322: iastore
    //   323: aload #11
    //   325: iload #15
    //   327: iload #24
    //   329: bipush #16
    //   331: iushr
    //   332: iload #24
    //   334: bipush #16
    //   336: ishl
    //   337: ior
    //   338: iastore
    //   339: aload #12
    //   341: iload #15
    //   343: iload #24
    //   345: bipush #24
    //   347: iushr
    //   348: iload #24
    //   350: bipush #8
    //   352: ishl
    //   353: ior
    //   354: iastore
    //   355: iinc #16, 1
    //   358: iload_2
    //   359: ifeq -> 123
    //   362: iconst_1
    //   363: istore #25
    //   365: aload #13
    //   367: iconst_0
    //   368: iload #25
    //   370: bipush #24
    //   372: ishl
    //   373: iastore
    //   374: iconst_1
    //   375: istore #26
    //   377: iload #26
    //   379: bipush #10
    //   381: if_icmpge -> 422
    //   384: iload #25
    //   386: iconst_1
    //   387: ishl
    //   388: istore #25
    //   390: iload #25
    //   392: sipush #256
    //   395: if_icmplt -> 405
    //   398: iload #25
    //   400: iload #14
    //   402: ixor
    //   403: istore #25
    //   405: aload #13
    //   407: iload #26
    //   409: iload #25
    //   411: bipush #24
    //   413: ishl
    //   414: iastore
    //   415: iinc #26, 1
    //   418: iload_2
    //   419: ifeq -> 377
    //   422: iconst_4
    //   423: istore #26
    //   425: iload #26
    //   427: bipush #6
    //   429: iadd
    //   430: istore #27
    //   432: iconst_4
    //   433: iload #27
    //   435: iconst_1
    //   436: iadd
    //   437: imul
    //   438: istore #28
    //   440: iload #28
    //   442: newarray int
    //   444: astore #29
    //   446: iload #28
    //   448: newarray int
    //   450: astore #30
    //   452: iconst_0
    //   453: istore #25
    //   455: iconst_0
    //   456: istore #32
    //   458: iconst_0
    //   459: istore #33
    //   461: iload #32
    //   463: iload #26
    //   465: if_icmpge -> 533
    //   468: aload #29
    //   470: iload #32
    //   472: aload #5
    //   474: iload #33
    //   476: baload
    //   477: bipush #24
    //   479: ishl
    //   480: aload #5
    //   482: iload #33
    //   484: iconst_1
    //   485: iadd
    //   486: baload
    //   487: sipush #255
    //   490: iand
    //   491: bipush #16
    //   493: ishl
    //   494: ior
    //   495: aload #5
    //   497: iload #33
    //   499: iconst_2
    //   500: iadd
    //   501: baload
    //   502: sipush #255
    //   505: iand
    //   506: bipush #8
    //   508: ishl
    //   509: ior
    //   510: aload #5
    //   512: iload #33
    //   514: iconst_3
    //   515: iadd
    //   516: baload
    //   517: sipush #255
    //   520: iand
    //   521: ior
    //   522: iastore
    //   523: iinc #32, 1
    //   526: iinc #33, 4
    //   529: iload_2
    //   530: ifeq -> 461
    //   533: iload #26
    //   535: istore #32
    //   537: iconst_0
    //   538: istore #33
    //   540: iload #32
    //   542: iload #28
    //   544: if_icmpge -> 671
    //   547: aload #29
    //   549: iload #32
    //   551: iconst_1
    //   552: isub
    //   553: iaload
    //   554: istore #31
    //   556: iload #33
    //   558: ifne -> 645
    //   561: iload #26
    //   563: istore #33
    //   565: aload #8
    //   567: iload #31
    //   569: bipush #16
    //   571: iushr
    //   572: sipush #255
    //   575: iand
    //   576: baload
    //   577: bipush #24
    //   579: ishl
    //   580: aload #8
    //   582: iload #31
    //   584: bipush #8
    //   586: iushr
    //   587: sipush #255
    //   590: iand
    //   591: baload
    //   592: sipush #255
    //   595: iand
    //   596: bipush #16
    //   598: ishl
    //   599: ior
    //   600: aload #8
    //   602: iload #31
    //   604: sipush #255
    //   607: iand
    //   608: baload
    //   609: sipush #255
    //   612: iand
    //   613: bipush #8
    //   615: ishl
    //   616: ior
    //   617: aload #8
    //   619: iload #31
    //   621: bipush #24
    //   623: iushr
    //   624: baload
    //   625: sipush #255
    //   628: iand
    //   629: ior
    //   630: istore #31
    //   632: iload #31
    //   634: aload #13
    //   636: iload #25
    //   638: iinc #25, 1
    //   641: iaload
    //   642: ixor
    //   643: istore #31
    //   645: aload #29
    //   647: iload #32
    //   649: aload #29
    //   651: iload #32
    //   653: iload #26
    //   655: isub
    //   656: iaload
    //   657: iload #31
    //   659: ixor
    //   660: iastore
    //   661: iinc #32, 1
    //   664: iinc #33, -1
    //   667: iload_2
    //   668: ifeq -> 540
    //   671: iconst_0
    //   672: istore #32
    //   674: iconst_4
    //   675: iload #27
    //   677: imul
    //   678: istore #33
    //   680: aload #30
    //   682: iload #32
    //   684: aload #29
    //   686: iload #33
    //   688: iaload
    //   689: iastore
    //   690: aload #30
    //   692: iload #32
    //   694: iconst_1
    //   695: iadd
    //   696: aload #29
    //   698: iload #33
    //   700: iconst_1
    //   701: iadd
    //   702: iaload
    //   703: iastore
    //   704: aload #30
    //   706: iload #32
    //   708: iconst_2
    //   709: iadd
    //   710: aload #29
    //   712: iload #33
    //   714: iconst_2
    //   715: iadd
    //   716: iaload
    //   717: iastore
    //   718: aload #30
    //   720: iload #32
    //   722: iconst_3
    //   723: iadd
    //   724: aload #29
    //   726: iload #33
    //   728: iconst_3
    //   729: iadd
    //   730: iaload
    //   731: iastore
    //   732: iinc #32, 4
    //   735: iinc #33, -4
    //   738: iconst_1
    //   739: istore #35
    //   741: iload #35
    //   743: iload #27
    //   745: if_icmpge -> 1109
    //   748: aload #29
    //   750: iload #33
    //   752: iaload
    //   753: istore #34
    //   755: aload #30
    //   757: iload #32
    //   759: aload #9
    //   761: aload #8
    //   763: iload #34
    //   765: bipush #24
    //   767: iushr
    //   768: baload
    //   769: sipush #255
    //   772: iand
    //   773: iaload
    //   774: aload #10
    //   776: aload #8
    //   778: iload #34
    //   780: bipush #16
    //   782: iushr
    //   783: sipush #255
    //   786: iand
    //   787: baload
    //   788: sipush #255
    //   791: iand
    //   792: iaload
    //   793: ixor
    //   794: aload #11
    //   796: aload #8
    //   798: iload #34
    //   800: bipush #8
    //   802: iushr
    //   803: sipush #255
    //   806: iand
    //   807: baload
    //   808: sipush #255
    //   811: iand
    //   812: iaload
    //   813: ixor
    //   814: aload #12
    //   816: aload #8
    //   818: iload #34
    //   820: sipush #255
    //   823: iand
    //   824: baload
    //   825: sipush #255
    //   828: iand
    //   829: iaload
    //   830: ixor
    //   831: iastore
    //   832: aload #29
    //   834: iload #33
    //   836: iconst_1
    //   837: iadd
    //   838: iaload
    //   839: istore #34
    //   841: aload #30
    //   843: iload #32
    //   845: iconst_1
    //   846: iadd
    //   847: aload #9
    //   849: aload #8
    //   851: iload #34
    //   853: bipush #24
    //   855: iushr
    //   856: baload
    //   857: sipush #255
    //   860: iand
    //   861: iaload
    //   862: aload #10
    //   864: aload #8
    //   866: iload #34
    //   868: bipush #16
    //   870: iushr
    //   871: sipush #255
    //   874: iand
    //   875: baload
    //   876: sipush #255
    //   879: iand
    //   880: iaload
    //   881: ixor
    //   882: aload #11
    //   884: aload #8
    //   886: iload #34
    //   888: bipush #8
    //   890: iushr
    //   891: sipush #255
    //   894: iand
    //   895: baload
    //   896: sipush #255
    //   899: iand
    //   900: iaload
    //   901: ixor
    //   902: aload #12
    //   904: aload #8
    //   906: iload #34
    //   908: sipush #255
    //   911: iand
    //   912: baload
    //   913: sipush #255
    //   916: iand
    //   917: iaload
    //   918: ixor
    //   919: iastore
    //   920: aload #29
    //   922: iload #33
    //   924: iconst_2
    //   925: iadd
    //   926: iaload
    //   927: istore #34
    //   929: aload #30
    //   931: iload #32
    //   933: iconst_2
    //   934: iadd
    //   935: aload #9
    //   937: aload #8
    //   939: iload #34
    //   941: bipush #24
    //   943: iushr
    //   944: baload
    //   945: sipush #255
    //   948: iand
    //   949: iaload
    //   950: aload #10
    //   952: aload #8
    //   954: iload #34
    //   956: bipush #16
    //   958: iushr
    //   959: sipush #255
    //   962: iand
    //   963: baload
    //   964: sipush #255
    //   967: iand
    //   968: iaload
    //   969: ixor
    //   970: aload #11
    //   972: aload #8
    //   974: iload #34
    //   976: bipush #8
    //   978: iushr
    //   979: sipush #255
    //   982: iand
    //   983: baload
    //   984: sipush #255
    //   987: iand
    //   988: iaload
    //   989: ixor
    //   990: aload #12
    //   992: aload #8
    //   994: iload #34
    //   996: sipush #255
    //   999: iand
    //   1000: baload
    //   1001: sipush #255
    //   1004: iand
    //   1005: iaload
    //   1006: ixor
    //   1007: iastore
    //   1008: aload #29
    //   1010: iload #33
    //   1012: iconst_3
    //   1013: iadd
    //   1014: iaload
    //   1015: istore #34
    //   1017: aload #30
    //   1019: iload #32
    //   1021: iconst_3
    //   1022: iadd
    //   1023: aload #9
    //   1025: aload #8
    //   1027: iload #34
    //   1029: bipush #24
    //   1031: iushr
    //   1032: baload
    //   1033: sipush #255
    //   1036: iand
    //   1037: iaload
    //   1038: aload #10
    //   1040: aload #8
    //   1042: iload #34
    //   1044: bipush #16
    //   1046: iushr
    //   1047: sipush #255
    //   1050: iand
    //   1051: baload
    //   1052: sipush #255
    //   1055: iand
    //   1056: iaload
    //   1057: ixor
    //   1058: aload #11
    //   1060: aload #8
    //   1062: iload #34
    //   1064: bipush #8
    //   1066: iushr
    //   1067: sipush #255
    //   1070: iand
    //   1071: baload
    //   1072: sipush #255
    //   1075: iand
    //   1076: iaload
    //   1077: ixor
    //   1078: aload #12
    //   1080: aload #8
    //   1082: iload #34
    //   1084: sipush #255
    //   1087: iand
    //   1088: baload
    //   1089: sipush #255
    //   1092: iand
    //   1093: iaload
    //   1094: ixor
    //   1095: iastore
    //   1096: iinc #32, 4
    //   1099: iinc #33, -4
    //   1102: iinc #35, 1
    //   1105: iload_2
    //   1106: ifeq -> 741
    //   1109: aload #30
    //   1111: iload #32
    //   1113: aload #29
    //   1115: iload #33
    //   1117: iaload
    //   1118: iastore
    //   1119: aload #30
    //   1121: iload #32
    //   1123: iconst_1
    //   1124: iadd
    //   1125: aload #29
    //   1127: iload #33
    //   1129: iconst_1
    //   1130: iadd
    //   1131: iaload
    //   1132: iastore
    //   1133: aload #30
    //   1135: iload #32
    //   1137: iconst_2
    //   1138: iadd
    //   1139: aload #29
    //   1141: iload #33
    //   1143: iconst_2
    //   1144: iadd
    //   1145: iaload
    //   1146: iastore
    //   1147: aload #30
    //   1149: iload #32
    //   1151: iconst_3
    //   1152: iadd
    //   1153: aload #29
    //   1155: iload #33
    //   1157: iconst_3
    //   1158: iadd
    //   1159: iaload
    //   1160: iastore
    //   1161: iconst_0
    //   1162: newarray byte
    //   1164: astore #35
    //   1166: aload #6
    //   1168: arraylength
    //   1169: bipush #16
    //   1171: irem
    //   1172: ifeq -> 1196
    //   1175: new java/lang/Exception
    //   1178: dup
    //   1179: sipush #-15908
    //   1182: sipush #18168
    //   1185: invokestatic a : (II)Ljava/lang/String;
    //   1188: invokespecial <init> : (Ljava/lang/String;)V
    //   1191: athrow
    //   1192: invokestatic a : (Ljava/lang/Throwable;)Ljava/lang/Throwable;
    //   1195: athrow
    //   1196: bipush #10
    //   1198: istore #36
    //   1200: sipush #-15907
    //   1203: sipush #256
    //   1206: newarray byte
    //   1208: astore #37
    //   1210: sipush #-21098
    //   1213: sipush #256
    //   1216: newarray int
    //   1218: astore #38
    //   1220: sipush #256
    //   1223: newarray int
    //   1225: astore #39
    //   1227: sipush #256
    //   1230: newarray int
    //   1232: astore #40
    //   1234: sipush #256
    //   1237: newarray int
    //   1239: astore #41
    //   1241: sipush #283
    //   1244: istore #14
    //   1246: invokestatic a : (II)Ljava/lang/String;
    //   1249: astore #42
    //   1251: iconst_0
    //   1252: istore #16
    //   1254: iload #16
    //   1256: sipush #256
    //   1259: if_icmpge -> 1486
    //   1262: aload #42
    //   1264: iload #16
    //   1266: iconst_1
    //   1267: iushr
    //   1268: invokevirtual charAt : (I)C
    //   1271: istore #43
    //   1273: iload #16
    //   1275: iconst_1
    //   1276: iand
    //   1277: ifne -> 1292
    //   1280: iload #43
    //   1282: bipush #8
    //   1284: iushr
    //   1285: goto -> 1294
    //   1288: invokestatic a : (Ljava/lang/Throwable;)Ljava/lang/Throwable;
    //   1291: athrow
    //   1292: iload #43
    //   1294: i2b
    //   1295: sipush #255
    //   1298: iand
    //   1299: istore #15
    //   1301: iload #16
    //   1303: iconst_1
    //   1304: ishl
    //   1305: istore #17
    //   1307: iload #17
    //   1309: sipush #256
    //   1312: if_icmplt -> 1322
    //   1315: iload #17
    //   1317: iload #14
    //   1319: ixor
    //   1320: istore #17
    //   1322: iload #17
    //   1324: iconst_1
    //   1325: ishl
    //   1326: istore #18
    //   1328: iload #18
    //   1330: sipush #256
    //   1333: if_icmplt -> 1343
    //   1336: iload #18
    //   1338: iload #14
    //   1340: ixor
    //   1341: istore #18
    //   1343: iload #18
    //   1345: iconst_1
    //   1346: ishl
    //   1347: istore #19
    //   1349: iload #19
    //   1351: sipush #256
    //   1354: if_icmplt -> 1364
    //   1357: iload #19
    //   1359: iload #14
    //   1361: ixor
    //   1362: istore #19
    //   1364: iload #19
    //   1366: iload #16
    //   1368: ixor
    //   1369: istore #20
    //   1371: iload #20
    //   1373: iload #17
    //   1375: ixor
    //   1376: istore #21
    //   1378: iload #20
    //   1380: iload #18
    //   1382: ixor
    //   1383: istore #22
    //   1385: iload #19
    //   1387: iload #18
    //   1389: ixor
    //   1390: iload #17
    //   1392: ixor
    //   1393: istore #23
    //   1395: aload #37
    //   1397: iload #15
    //   1399: iload #16
    //   1401: i2b
    //   1402: bastore
    //   1403: aload #38
    //   1405: iload #15
    //   1407: iload #23
    //   1409: bipush #24
    //   1411: ishl
    //   1412: iload #20
    //   1414: bipush #16
    //   1416: ishl
    //   1417: ior
    //   1418: iload #22
    //   1420: bipush #8
    //   1422: ishl
    //   1423: ior
    //   1424: iload #21
    //   1426: ior
    //   1427: dup
    //   1428: istore #24
    //   1430: iastore
    //   1431: aload #39
    //   1433: iload #15
    //   1435: iload #24
    //   1437: bipush #8
    //   1439: iushr
    //   1440: iload #24
    //   1442: bipush #24
    //   1444: ishl
    //   1445: ior
    //   1446: iastore
    //   1447: aload #40
    //   1449: iload #15
    //   1451: iload #24
    //   1453: bipush #16
    //   1455: iushr
    //   1456: iload #24
    //   1458: bipush #16
    //   1460: ishl
    //   1461: ior
    //   1462: iastore
    //   1463: aload #41
    //   1465: iload #15
    //   1467: iload #24
    //   1469: bipush #24
    //   1471: iushr
    //   1472: iload #24
    //   1474: bipush #8
    //   1476: ishl
    //   1477: ior
    //   1478: iastore
    //   1479: iinc #16, 1
    //   1482: iload_2
    //   1483: ifeq -> 1254
    //   1486: aload #6
    //   1488: arraylength
    //   1489: newarray byte
    //   1491: astore #43
    //   1493: iconst_0
    //   1494: istore #44
    //   1496: iload #44
    //   1498: aload #6
    //   1500: arraylength
    //   1501: bipush #16
    //   1503: idiv
    //   1504: if_icmpge -> 2418
    //   1507: bipush #16
    //   1509: newarray byte
    //   1511: astore #45
    //   1513: bipush #16
    //   1515: newarray byte
    //   1517: astore #46
    //   1519: iconst_0
    //   1520: istore #47
    //   1522: iload #47
    //   1524: bipush #16
    //   1526: if_icmpge -> 1552
    //   1529: aload #45
    //   1531: iload #47
    //   1533: aload #6
    //   1535: iload #47
    //   1537: iload #44
    //   1539: bipush #16
    //   1541: imul
    //   1542: iadd
    //   1543: baload
    //   1544: bastore
    //   1545: iinc #47, 1
    //   1548: iload_2
    //   1549: ifeq -> 1522
    //   1552: iconst_0
    //   1553: istore #47
    //   1555: aload #45
    //   1557: iconst_0
    //   1558: baload
    //   1559: bipush #24
    //   1561: ishl
    //   1562: aload #45
    //   1564: iconst_1
    //   1565: baload
    //   1566: sipush #255
    //   1569: iand
    //   1570: bipush #16
    //   1572: ishl
    //   1573: ior
    //   1574: aload #45
    //   1576: iconst_2
    //   1577: baload
    //   1578: sipush #255
    //   1581: iand
    //   1582: bipush #8
    //   1584: ishl
    //   1585: ior
    //   1586: aload #45
    //   1588: iconst_3
    //   1589: baload
    //   1590: sipush #255
    //   1593: iand
    //   1594: ior
    //   1595: aload #30
    //   1597: iconst_0
    //   1598: iaload
    //   1599: ixor
    //   1600: istore #49
    //   1602: aload #45
    //   1604: iconst_4
    //   1605: baload
    //   1606: bipush #24
    //   1608: ishl
    //   1609: aload #45
    //   1611: iconst_5
    //   1612: baload
    //   1613: sipush #255
    //   1616: iand
    //   1617: bipush #16
    //   1619: ishl
    //   1620: ior
    //   1621: aload #45
    //   1623: bipush #6
    //   1625: baload
    //   1626: sipush #255
    //   1629: iand
    //   1630: bipush #8
    //   1632: ishl
    //   1633: ior
    //   1634: aload #45
    //   1636: bipush #7
    //   1638: baload
    //   1639: sipush #255
    //   1642: iand
    //   1643: ior
    //   1644: aload #30
    //   1646: iconst_1
    //   1647: iaload
    //   1648: ixor
    //   1649: istore #50
    //   1651: aload #45
    //   1653: bipush #8
    //   1655: baload
    //   1656: bipush #24
    //   1658: ishl
    //   1659: aload #45
    //   1661: bipush #9
    //   1663: baload
    //   1664: sipush #255
    //   1667: iand
    //   1668: bipush #16
    //   1670: ishl
    //   1671: ior
    //   1672: aload #45
    //   1674: bipush #10
    //   1676: baload
    //   1677: sipush #255
    //   1680: iand
    //   1681: bipush #8
    //   1683: ishl
    //   1684: ior
    //   1685: aload #45
    //   1687: bipush #11
    //   1689: baload
    //   1690: sipush #255
    //   1693: iand
    //   1694: ior
    //   1695: aload #30
    //   1697: iconst_2
    //   1698: iaload
    //   1699: ixor
    //   1700: istore #51
    //   1702: aload #45
    //   1704: bipush #12
    //   1706: baload
    //   1707: bipush #24
    //   1709: ishl
    //   1710: aload #45
    //   1712: bipush #13
    //   1714: baload
    //   1715: sipush #255
    //   1718: iand
    //   1719: bipush #16
    //   1721: ishl
    //   1722: ior
    //   1723: aload #45
    //   1725: bipush #14
    //   1727: baload
    //   1728: sipush #255
    //   1731: iand
    //   1732: bipush #8
    //   1734: ishl
    //   1735: ior
    //   1736: aload #45
    //   1738: bipush #15
    //   1740: baload
    //   1741: sipush #255
    //   1744: iand
    //   1745: ior
    //   1746: aload #30
    //   1748: iconst_3
    //   1749: iaload
    //   1750: ixor
    //   1751: istore #52
    //   1753: iconst_1
    //   1754: istore #53
    //   1756: iload #53
    //   1758: iload #36
    //   1760: if_icmpge -> 2003
    //   1763: iinc #47, 4
    //   1766: aload #38
    //   1768: iload #49
    //   1770: bipush #24
    //   1772: iushr
    //   1773: iaload
    //   1774: aload #39
    //   1776: iload #52
    //   1778: bipush #16
    //   1780: iushr
    //   1781: sipush #255
    //   1784: iand
    //   1785: iaload
    //   1786: ixor
    //   1787: aload #40
    //   1789: iload #51
    //   1791: bipush #8
    //   1793: iushr
    //   1794: sipush #255
    //   1797: iand
    //   1798: iaload
    //   1799: ixor
    //   1800: aload #41
    //   1802: iload #50
    //   1804: sipush #255
    //   1807: iand
    //   1808: iaload
    //   1809: ixor
    //   1810: aload #30
    //   1812: iload #47
    //   1814: iaload
    //   1815: ixor
    //   1816: istore #54
    //   1818: aload #38
    //   1820: iload #50
    //   1822: bipush #24
    //   1824: iushr
    //   1825: iaload
    //   1826: aload #39
    //   1828: iload #49
    //   1830: bipush #16
    //   1832: iushr
    //   1833: sipush #255
    //   1836: iand
    //   1837: iaload
    //   1838: ixor
    //   1839: aload #40
    //   1841: iload #52
    //   1843: bipush #8
    //   1845: iushr
    //   1846: sipush #255
    //   1849: iand
    //   1850: iaload
    //   1851: ixor
    //   1852: aload #41
    //   1854: iload #51
    //   1856: sipush #255
    //   1859: iand
    //   1860: iaload
    //   1861: ixor
    //   1862: aload #30
    //   1864: iload #47
    //   1866: iconst_1
    //   1867: iadd
    //   1868: iaload
    //   1869: ixor
    //   1870: istore #55
    //   1872: aload #38
    //   1874: iload #51
    //   1876: bipush #24
    //   1878: iushr
    //   1879: iaload
    //   1880: aload #39
    //   1882: iload #50
    //   1884: bipush #16
    //   1886: iushr
    //   1887: sipush #255
    //   1890: iand
    //   1891: iaload
    //   1892: ixor
    //   1893: aload #40
    //   1895: iload #49
    //   1897: bipush #8
    //   1899: iushr
    //   1900: sipush #255
    //   1903: iand
    //   1904: iaload
    //   1905: ixor
    //   1906: aload #41
    //   1908: iload #52
    //   1910: sipush #255
    //   1913: iand
    //   1914: iaload
    //   1915: ixor
    //   1916: aload #30
    //   1918: iload #47
    //   1920: iconst_2
    //   1921: iadd
    //   1922: iaload
    //   1923: ixor
    //   1924: istore #56
    //   1926: aload #38
    //   1928: iload #52
    //   1930: bipush #24
    //   1932: iushr
    //   1933: iaload
    //   1934: aload #39
    //   1936: iload #51
    //   1938: bipush #16
    //   1940: iushr
    //   1941: sipush #255
    //   1944: iand
    //   1945: iaload
    //   1946: ixor
    //   1947: aload #40
    //   1949: iload #50
    //   1951: bipush #8
    //   1953: iushr
    //   1954: sipush #255
    //   1957: iand
    //   1958: iaload
    //   1959: ixor
    //   1960: aload #41
    //   1962: iload #49
    //   1964: sipush #255
    //   1967: iand
    //   1968: iaload
    //   1969: ixor
    //   1970: aload #30
    //   1972: iload #47
    //   1974: iconst_3
    //   1975: iadd
    //   1976: iaload
    //   1977: ixor
    //   1978: istore #57
    //   1980: iload #54
    //   1982: istore #49
    //   1984: iload #55
    //   1986: istore #50
    //   1988: iload #56
    //   1990: istore #51
    //   1992: iload #57
    //   1994: istore #52
    //   1996: iinc #53, 1
    //   1999: iload_2
    //   2000: ifeq -> 1756
    //   2003: iinc #47, 4
    //   2006: aload #30
    //   2008: iload #47
    //   2010: iaload
    //   2011: istore #48
    //   2013: aload #46
    //   2015: iconst_0
    //   2016: aload #37
    //   2018: iload #49
    //   2020: bipush #24
    //   2022: iushr
    //   2023: baload
    //   2024: iload #48
    //   2026: bipush #24
    //   2028: iushr
    //   2029: ixor
    //   2030: i2b
    //   2031: bastore
    //   2032: aload #46
    //   2034: iconst_1
    //   2035: aload #37
    //   2037: iload #52
    //   2039: bipush #16
    //   2041: iushr
    //   2042: sipush #255
    //   2045: iand
    //   2046: baload
    //   2047: iload #48
    //   2049: bipush #16
    //   2051: iushr
    //   2052: ixor
    //   2053: i2b
    //   2054: bastore
    //   2055: aload #46
    //   2057: iconst_2
    //   2058: aload #37
    //   2060: iload #51
    //   2062: bipush #8
    //   2064: iushr
    //   2065: sipush #255
    //   2068: iand
    //   2069: baload
    //   2070: iload #48
    //   2072: bipush #8
    //   2074: iushr
    //   2075: ixor
    //   2076: i2b
    //   2077: bastore
    //   2078: aload #46
    //   2080: iconst_3
    //   2081: aload #37
    //   2083: iload #50
    //   2085: sipush #255
    //   2088: iand
    //   2089: baload
    //   2090: iload #48
    //   2092: ixor
    //   2093: i2b
    //   2094: bastore
    //   2095: aload #30
    //   2097: iload #47
    //   2099: iconst_1
    //   2100: iadd
    //   2101: iaload
    //   2102: istore #48
    //   2104: aload #46
    //   2106: iconst_4
    //   2107: aload #37
    //   2109: iload #50
    //   2111: bipush #24
    //   2113: iushr
    //   2114: baload
    //   2115: iload #48
    //   2117: bipush #24
    //   2119: iushr
    //   2120: ixor
    //   2121: i2b
    //   2122: bastore
    //   2123: aload #46
    //   2125: iconst_5
    //   2126: aload #37
    //   2128: iload #49
    //   2130: bipush #16
    //   2132: iushr
    //   2133: sipush #255
    //   2136: iand
    //   2137: baload
    //   2138: iload #48
    //   2140: bipush #16
    //   2142: iushr
    //   2143: ixor
    //   2144: i2b
    //   2145: bastore
    //   2146: aload #46
    //   2148: bipush #6
    //   2150: aload #37
    //   2152: iload #52
    //   2154: bipush #8
    //   2156: iushr
    //   2157: sipush #255
    //   2160: iand
    //   2161: baload
    //   2162: iload #48
    //   2164: bipush #8
    //   2166: iushr
    //   2167: ixor
    //   2168: i2b
    //   2169: bastore
    //   2170: aload #46
    //   2172: bipush #7
    //   2174: aload #37
    //   2176: iload #51
    //   2178: sipush #255
    //   2181: iand
    //   2182: baload
    //   2183: iload #48
    //   2185: ixor
    //   2186: i2b
    //   2187: bastore
    //   2188: aload #30
    //   2190: iload #47
    //   2192: iconst_2
    //   2193: iadd
    //   2194: iaload
    //   2195: istore #48
    //   2197: aload #46
    //   2199: bipush #8
    //   2201: aload #37
    //   2203: iload #51
    //   2205: bipush #24
    //   2207: iushr
    //   2208: baload
    //   2209: iload #48
    //   2211: bipush #24
    //   2213: iushr
    //   2214: ixor
    //   2215: i2b
    //   2216: bastore
    //   2217: aload #46
    //   2219: bipush #9
    //   2221: aload #37
    //   2223: iload #50
    //   2225: bipush #16
    //   2227: iushr
    //   2228: sipush #255
    //   2231: iand
    //   2232: baload
    //   2233: iload #48
    //   2235: bipush #16
    //   2237: iushr
    //   2238: ixor
    //   2239: i2b
    //   2240: bastore
    //   2241: aload #46
    //   2243: bipush #10
    //   2245: aload #37
    //   2247: iload #49
    //   2249: bipush #8
    //   2251: iushr
    //   2252: sipush #255
    //   2255: iand
    //   2256: baload
    //   2257: iload #48
    //   2259: bipush #8
    //   2261: iushr
    //   2262: ixor
    //   2263: i2b
    //   2264: bastore
    //   2265: aload #46
    //   2267: bipush #11
    //   2269: aload #37
    //   2271: iload #52
    //   2273: sipush #255
    //   2276: iand
    //   2277: baload
    //   2278: iload #48
    //   2280: ixor
    //   2281: i2b
    //   2282: bastore
    //   2283: aload #30
    //   2285: iload #47
    //   2287: iconst_3
    //   2288: iadd
    //   2289: iaload
    //   2290: istore #48
    //   2292: aload #46
    //   2294: bipush #12
    //   2296: aload #37
    //   2298: iload #52
    //   2300: bipush #24
    //   2302: iushr
    //   2303: baload
    //   2304: iload #48
    //   2306: bipush #24
    //   2308: iushr
    //   2309: ixor
    //   2310: i2b
    //   2311: bastore
    //   2312: aload #46
    //   2314: bipush #13
    //   2316: aload #37
    //   2318: iload #51
    //   2320: bipush #16
    //   2322: iushr
    //   2323: sipush #255
    //   2326: iand
    //   2327: baload
    //   2328: iload #48
    //   2330: bipush #16
    //   2332: iushr
    //   2333: ixor
    //   2334: i2b
    //   2335: bastore
    //   2336: aload #46
    //   2338: bipush #14
    //   2340: aload #37
    //   2342: iload #50
    //   2344: bipush #8
    //   2346: iushr
    //   2347: sipush #255
    //   2350: iand
    //   2351: baload
    //   2352: iload #48
    //   2354: bipush #8
    //   2356: iushr
    //   2357: ixor
    //   2358: i2b
    //   2359: bastore
    //   2360: aload #46
    //   2362: bipush #15
    //   2364: aload #37
    //   2366: iload #49
    //   2368: sipush #255
    //   2371: iand
    //   2372: baload
    //   2373: iload #48
    //   2375: ixor
    //   2376: i2b
    //   2377: bastore
    //   2378: iconst_0
    //   2379: istore #53
    //   2381: iload #53
    //   2383: bipush #16
    //   2385: if_icmpge -> 2411
    //   2388: aload #43
    //   2390: iload #53
    //   2392: iload #44
    //   2394: bipush #16
    //   2396: imul
    //   2397: iadd
    //   2398: aload #46
    //   2400: iload #53
    //   2402: baload
    //   2403: bastore
    //   2404: iinc #53, 1
    //   2407: iload_2
    //   2408: ifeq -> 2381
    //   2411: iinc #44, 1
    //   2414: iload_2
    //   2415: ifeq -> 1496
    //   2418: aload #43
    //   2420: arraylength
    //   2421: ifle -> 2502
    //   2424: aload #43
    //   2426: aload #43
    //   2428: arraylength
    //   2429: iconst_1
    //   2430: isub
    //   2431: baload
    //   2432: istore #44
    //   2434: iload #44
    //   2436: bipush #16
    //   2438: if_icmple -> 2449
    //   2441: aload #43
    //   2443: astore #35
    //   2445: iload_2
    //   2446: ifeq -> 2502
    //   2449: aload #43
    //   2451: arraylength
    //   2452: iload #44
    //   2454: isub
    //   2455: newarray byte
    //   2457: astore #35
    //   2459: iconst_0
    //   2460: istore #45
    //   2462: iload #45
    //   2464: aload #35
    //   2466: arraylength
    //   2467: if_icmpge -> 2502
    //   2470: iload #45
    //   2472: aload #43
    //   2474: arraylength
    //   2475: if_icmpge -> 2502
    //   2478: aload #35
    //   2480: iload #45
    //   2482: aload #43
    //   2484: iload #45
    //   2486: baload
    //   2487: bastore
    //   2488: iinc #45, 1
    //   2491: iload_2
    //   2492: ifeq -> 2462
    //   2495: goto -> 2502
    //   2498: invokestatic a : (Ljava/lang/Throwable;)Ljava/lang/Throwable;
    //   2501: athrow
    //   2502: aload #35
    //   2504: astore #7
    //   2506: new java/math/BigInteger
    //   2509: dup
    //   2510: aload #7
    //   2512: invokespecial <init> : ([B)V
    //   2515: invokevirtual abs : ()Ljava/math/BigInteger;
    //   2518: putstatic burp/Zgkp.Zp : Ljava/lang/Object;
    //   2521: new java/lang/StringBuilder
    //   2524: dup
    //   2525: invokespecial <init> : ()V
    //   2528: astore_3
    //   2529: iconst_0
    //   2530: istore #4
    //   2532: iload #4
    //   2534: bipush #32
    //   2536: if_icmpge -> 3871
    //   2539: iload #4
    //   2541: tableswitch default -> 3864, 0 -> 2684, 1 -> 2721, 2 -> 2758, 3 -> 2795, 4 -> 2832, 5 -> 2869, 6 -> 2906, 7 -> 2943, 8 -> 2980, 9 -> 3017, 10 -> 3054, 11 -> 3091, 12 -> 3128, 13 -> 3165, 14 -> 3202, 15 -> 3239, 16 -> 3276, 17 -> 3313, 18 -> 3350, 19 -> 3387, 20 -> 3424, 21 -> 3461, 22 -> 3498, 23 -> 3535, 24 -> 3572, 25 -> 3609, 26 -> 3646, 27 -> 3683, 28 -> 3720, 29 -> 3757, 30 -> 3794, 31 -> 3831
    //   2684: aload_3
    //   2685: getstatic burp/Zzr.Zp : Ljava/lang/String;
    //   2688: getstatic burp/Zl22.ZJ : Ljava/lang/Object;
    //   2691: checkcast java/math/BigInteger
    //   2694: invokevirtual intValue : ()I
    //   2697: bipush #32
    //   2699: irem
    //   2700: invokestatic abs : (I)I
    //   2703: invokevirtual charAt : (I)C
    //   2706: invokevirtual append : (C)Ljava/lang/StringBuilder;
    //   2709: pop
    //   2710: iload_2
    //   2711: ifeq -> 3864
    //   2714: goto -> 2721
    //   2717: invokestatic a : (Ljava/lang/Throwable;)Ljava/lang/Throwable;
    //   2720: athrow
    //   2721: aload_3
    //   2722: getstatic burp/Zr8s.ZA : Ljava/lang/String;
    //   2725: getstatic burp/Zgwh.Zl : Ljava/lang/Object;
    //   2728: checkcast java/math/BigInteger
    //   2731: invokevirtual intValue : ()I
    //   2734: bipush #32
    //   2736: irem
    //   2737: invokestatic abs : (I)I
    //   2740: invokevirtual charAt : (I)C
    //   2743: invokevirtual append : (C)Ljava/lang/StringBuilder;
    //   2746: pop
    //   2747: iload_2
    //   2748: ifeq -> 3864
    //   2751: goto -> 2758
    //   2754: invokestatic a : (Ljava/lang/Throwable;)Ljava/lang/Throwable;
    //   2757: athrow
    //   2758: aload_3
    //   2759: getstatic burp/Zepm.Zl : Ljava/lang/String;
    //   2762: getstatic burp/Zgj5.ZO : Ljava/lang/Object;
    //   2765: checkcast java/math/BigInteger
    //   2768: invokevirtual intValue : ()I
    //   2771: bipush #32
    //   2773: irem
    //   2774: invokestatic abs : (I)I
    //   2777: invokevirtual charAt : (I)C
    //   2780: invokevirtual append : (C)Ljava/lang/StringBuilder;
    //   2783: pop
    //   2784: iload_2
    //   2785: ifeq -> 3864
    //   2788: goto -> 2795
    //   2791: invokestatic a : (Ljava/lang/Throwable;)Ljava/lang/Throwable;
    //   2794: athrow
    //   2795: aload_3
    //   2796: getstatic burp/Zmnb.ZD : Ljava/lang/String;
    //   2799: getstatic burp/Zgvl.ZK : Ljava/lang/Object;
    //   2802: checkcast java/math/BigInteger
    //   2805: invokevirtual intValue : ()I
    //   2808: bipush #32
    //   2810: irem
    //   2811: invokestatic abs : (I)I
    //   2814: invokevirtual charAt : (I)C
    //   2817: invokevirtual append : (C)Ljava/lang/StringBuilder;
    //   2820: pop
    //   2821: iload_2
    //   2822: ifeq -> 3864
    //   2825: goto -> 2832
    //   2828: invokestatic a : (Ljava/lang/Throwable;)Ljava/lang/Throwable;
    //   2831: athrow
    //   2832: aload_3
    //   2833: getstatic burp/Zlzo.Zs : Ljava/lang/String;
    //   2836: getstatic burp/Zete.Zm : Ljava/lang/Object;
    //   2839: checkcast java/math/BigInteger
    //   2842: invokevirtual intValue : ()I
    //   2845: bipush #32
    //   2847: irem
    //   2848: invokestatic abs : (I)I
    //   2851: invokevirtual charAt : (I)C
    //   2854: invokevirtual append : (C)Ljava/lang/StringBuilder;
    //   2857: pop
    //   2858: iload_2
    //   2859: ifeq -> 3864
    //   2862: goto -> 2869
    //   2865: invokestatic a : (Ljava/lang/Throwable;)Ljava/lang/Throwable;
    //   2868: athrow
    //   2869: aload_3
    //   2870: getstatic burp/Ztev.Zp : Ljava/lang/String;
    //   2873: getstatic burp/Zezn.Zh : Ljava/lang/Object;
    //   2876: checkcast java/math/BigInteger
    //   2879: invokevirtual intValue : ()I
    //   2882: bipush #32
    //   2884: irem
    //   2885: invokestatic abs : (I)I
    //   2888: invokevirtual charAt : (I)C
    //   2891: invokevirtual append : (C)Ljava/lang/StringBuilder;
    //   2894: pop
    //   2895: iload_2
    //   2896: ifeq -> 3864
    //   2899: goto -> 2906
    //   2902: invokestatic a : (Ljava/lang/Throwable;)Ljava/lang/Throwable;
    //   2905: athrow
    //   2906: aload_3
    //   2907: getstatic burp/Zeu2.ZK : Ljava/lang/String;
    //   2910: getstatic burp/Zeu2.ZW : Ljava/lang/Object;
    //   2913: checkcast java/math/BigInteger
    //   2916: invokevirtual intValue : ()I
    //   2919: bipush #32
    //   2921: irem
    //   2922: invokestatic abs : (I)I
    //   2925: invokevirtual charAt : (I)C
    //   2928: invokevirtual append : (C)Ljava/lang/StringBuilder;
    //   2931: pop
    //   2932: iload_2
    //   2933: ifeq -> 3864
    //   2936: goto -> 2943
    //   2939: invokestatic a : (Ljava/lang/Throwable;)Ljava/lang/Throwable;
    //   2942: athrow
    //   2943: aload_3
    //   2944: getstatic burp/Zr4k.Zy : Ljava/lang/String;
    //   2947: getstatic burp/Zry7.ZZ : Ljava/lang/Object;
    //   2950: checkcast java/math/BigInteger
    //   2953: invokevirtual intValue : ()I
    //   2956: bipush #32
    //   2958: irem
    //   2959: invokestatic abs : (I)I
    //   2962: invokevirtual charAt : (I)C
    //   2965: invokevirtual append : (C)Ljava/lang/StringBuilder;
    //   2968: pop
    //   2969: iload_2
    //   2970: ifeq -> 3864
    //   2973: goto -> 2980
    //   2976: invokestatic a : (Ljava/lang/Throwable;)Ljava/lang/Throwable;
    //   2979: athrow
    //   2980: aload_3
    //   2981: getstatic burp/Zlzo.Zs : Ljava/lang/String;
    //   2984: getstatic burp/Zb_c.ZN : Ljava/lang/Object;
    //   2987: checkcast java/math/BigInteger
    //   2990: invokevirtual intValue : ()I
    //   2993: bipush #32
    //   2995: irem
    //   2996: invokestatic abs : (I)I
    //   2999: invokevirtual charAt : (I)C
    //   3002: invokevirtual append : (C)Ljava/lang/StringBuilder;
    //   3005: pop
    //   3006: iload_2
    //   3007: ifeq -> 3864
    //   3010: goto -> 3017
    //   3013: invokestatic a : (Ljava/lang/Throwable;)Ljava/lang/Throwable;
    //   3016: athrow
    //   3017: aload_3
    //   3018: getstatic burp/Zb29.Zf : Ljava/lang/String;
    //   3021: getstatic burp/Zldx.ZM : Ljava/lang/Object;
    //   3024: checkcast java/math/BigInteger
    //   3027: invokevirtual intValue : ()I
    //   3030: bipush #32
    //   3032: irem
    //   3033: invokestatic abs : (I)I
    //   3036: invokevirtual charAt : (I)C
    //   3039: invokevirtual append : (C)Ljava/lang/StringBuilder;
    //   3042: pop
    //   3043: iload_2
    //   3044: ifeq -> 3864
    //   3047: goto -> 3054
    //   3050: invokestatic a : (Ljava/lang/Throwable;)Ljava/lang/Throwable;
    //   3053: athrow
    //   3054: aload_3
    //   3055: getstatic burp/Zl3l.Z_ : Ljava/lang/String;
    //   3058: getstatic burp/Zx4k.ZE : Ljava/lang/Object;
    //   3061: checkcast java/math/BigInteger
    //   3064: invokevirtual intValue : ()I
    //   3067: bipush #32
    //   3069: irem
    //   3070: invokestatic abs : (I)I
    //   3073: invokevirtual charAt : (I)C
    //   3076: invokevirtual append : (C)Ljava/lang/StringBuilder;
    //   3079: pop
    //   3080: iload_2
    //   3081: ifeq -> 3864
    //   3084: goto -> 3091
    //   3087: invokestatic a : (Ljava/lang/Throwable;)Ljava/lang/Throwable;
    //   3090: athrow
    //   3091: aload_3
    //   3092: getstatic burp/Zrpx.ZM : Ljava/lang/String;
    //   3095: getstatic burp/Zrm4.ZB : Ljava/lang/Object;
    //   3098: checkcast java/math/BigInteger
    //   3101: invokevirtual intValue : ()I
    //   3104: bipush #32
    //   3106: irem
    //   3107: invokestatic abs : (I)I
    //   3110: invokevirtual charAt : (I)C
    //   3113: invokevirtual append : (C)Ljava/lang/StringBuilder;
    //   3116: pop
    //   3117: iload_2
    //   3118: ifeq -> 3864
    //   3121: goto -> 3128
    //   3124: invokestatic a : (Ljava/lang/Throwable;)Ljava/lang/Throwable;
    //   3127: athrow
    //   3128: aload_3
    //   3129: getstatic burp/Zrxm.Zp : Ljava/lang/String;
    //   3132: getstatic burp/Zrpx.Zi : Ljava/lang/Object;
    //   3135: checkcast java/math/BigInteger
    //   3138: invokevirtual intValue : ()I
    //   3141: bipush #32
    //   3143: irem
    //   3144: invokestatic abs : (I)I
    //   3147: invokevirtual charAt : (I)C
    //   3150: invokevirtual append : (C)Ljava/lang/StringBuilder;
    //   3153: pop
    //   3154: iload_2
    //   3155: ifeq -> 3864
    //   3158: goto -> 3165
    //   3161: invokestatic a : (Ljava/lang/Throwable;)Ljava/lang/Throwable;
    //   3164: athrow
    //   3165: aload_3
    //   3166: getstatic burp/Zb6b.Zn : Ljava/lang/String;
    //   3169: getstatic burp/Zzky.Zo : Ljava/lang/Object;
    //   3172: checkcast java/math/BigInteger
    //   3175: invokevirtual intValue : ()I
    //   3178: bipush #32
    //   3180: irem
    //   3181: invokestatic abs : (I)I
    //   3184: invokevirtual charAt : (I)C
    //   3187: invokevirtual append : (C)Ljava/lang/StringBuilder;
    //   3190: pop
    //   3191: iload_2
    //   3192: ifeq -> 3864
    //   3195: goto -> 3202
    //   3198: invokestatic a : (Ljava/lang/Throwable;)Ljava/lang/Throwable;
    //   3201: athrow
    //   3202: aload_3
    //   3203: getstatic burp/Zmh5.Zh : Ljava/lang/String;
    //   3206: getstatic burp/Zkaw.ZB : Ljava/lang/Object;
    //   3209: checkcast java/math/BigInteger
    //   3212: invokevirtual intValue : ()I
    //   3215: bipush #32
    //   3217: irem
    //   3218: invokestatic abs : (I)I
    //   3221: invokevirtual charAt : (I)C
    //   3224: invokevirtual append : (C)Ljava/lang/StringBuilder;
    //   3227: pop
    //   3228: iload_2
    //   3229: ifeq -> 3864
    //   3232: goto -> 3239
    //   3235: invokestatic a : (Ljava/lang/Throwable;)Ljava/lang/Throwable;
    //   3238: athrow
    //   3239: aload_3
    //   3240: getstatic burp/Zb29.Zf : Ljava/lang/String;
    //   3243: getstatic burp/Zkcd.ZE : Ljava/lang/Object;
    //   3246: checkcast java/math/BigInteger
    //   3249: invokevirtual intValue : ()I
    //   3252: bipush #32
    //   3254: irem
    //   3255: invokestatic abs : (I)I
    //   3258: invokevirtual charAt : (I)C
    //   3261: invokevirtual append : (C)Ljava/lang/StringBuilder;
    //   3264: pop
    //   3265: iload_2
    //   3266: ifeq -> 3864
    //   3269: goto -> 3276
    //   3272: invokestatic a : (Ljava/lang/Throwable;)Ljava/lang/Throwable;
    //   3275: athrow
    //   3276: aload_3
    //   3277: getstatic burp/Zeno.ZL : Ljava/lang/String;
    //   3280: getstatic burp/Zgwh.Zl : Ljava/lang/Object;
    //   3283: checkcast java/math/BigInteger
    //   3286: invokevirtual intValue : ()I
    //   3289: bipush #32
    //   3291: irem
    //   3292: invokestatic abs : (I)I
    //   3295: invokevirtual charAt : (I)C
    //   3298: invokevirtual append : (C)Ljava/lang/StringBuilder;
    //   3301: pop
    //   3302: iload_2
    //   3303: ifeq -> 3864
    //   3306: goto -> 3313
    //   3309: invokestatic a : (Ljava/lang/Throwable;)Ljava/lang/Throwable;
    //   3312: athrow
    //   3313: aload_3
    //   3314: getstatic burp/Zmh5.Zh : Ljava/lang/String;
    //   3317: getstatic burp/Zr0.ZX : Ljava/lang/Object;
    //   3320: checkcast java/math/BigInteger
    //   3323: invokevirtual intValue : ()I
    //   3326: bipush #32
    //   3328: irem
    //   3329: invokestatic abs : (I)I
    //   3332: invokevirtual charAt : (I)C
    //   3335: invokevirtual append : (C)Ljava/lang/StringBuilder;
    //   3338: pop
    //   3339: iload_2
    //   3340: ifeq -> 3864
    //   3343: goto -> 3350
    //   3346: invokestatic a : (Ljava/lang/Throwable;)Ljava/lang/Throwable;
    //   3349: athrow
    //   3350: aload_3
    //   3351: getstatic burp/Zezn.Ze : Ljava/lang/String;
    //   3354: getstatic burp/Zdm.ZA : Ljava/lang/Object;
    //   3357: checkcast java/math/BigInteger
    //   3360: invokevirtual intValue : ()I
    //   3363: bipush #32
    //   3365: irem
    //   3366: invokestatic abs : (I)I
    //   3369: invokevirtual charAt : (I)C
    //   3372: invokevirtual append : (C)Ljava/lang/StringBuilder;
    //   3375: pop
    //   3376: iload_2
    //   3377: ifeq -> 3864
    //   3380: goto -> 3387
    //   3383: invokestatic a : (Ljava/lang/Throwable;)Ljava/lang/Throwable;
    //   3386: athrow
    //   3387: aload_3
    //   3388: getstatic burp/Zzky.Zj : Ljava/lang/String;
    //   3391: getstatic burp/Zkcd.ZE : Ljava/lang/Object;
    //   3394: checkcast java/math/BigInteger
    //   3397: invokevirtual intValue : ()I
    //   3400: bipush #32
    //   3402: irem
    //   3403: invokestatic abs : (I)I
    //   3406: invokevirtual charAt : (I)C
    //   3409: invokevirtual append : (C)Ljava/lang/StringBuilder;
    //   3412: pop
    //   3413: iload_2
    //   3414: ifeq -> 3864
    //   3417: goto -> 3424
    //   3420: invokestatic a : (Ljava/lang/Throwable;)Ljava/lang/Throwable;
    //   3423: athrow
    //   3424: aload_3
    //   3425: getstatic burp/Zsq5.ZA : Ljava/lang/String;
    //   3428: getstatic burp/Zete.Zm : Ljava/lang/Object;
    //   3431: checkcast java/math/BigInteger
    //   3434: invokevirtual intValue : ()I
    //   3437: bipush #32
    //   3439: irem
    //   3440: invokestatic abs : (I)I
    //   3443: invokevirtual charAt : (I)C
    //   3446: invokevirtual append : (C)Ljava/lang/StringBuilder;
    //   3449: pop
    //   3450: iload_2
    //   3451: ifeq -> 3864
    //   3454: goto -> 3461
    //   3457: invokestatic a : (Ljava/lang/Throwable;)Ljava/lang/Throwable;
    //   3460: athrow
    //   3461: aload_3
    //   3462: getstatic burp/Zm84.Zd : Ljava/lang/String;
    //   3465: getstatic burp/Zsun.ZP : Ljava/lang/Object;
    //   3468: checkcast java/math/BigInteger
    //   3471: invokevirtual intValue : ()I
    //   3474: bipush #32
    //   3476: irem
    //   3477: invokestatic abs : (I)I
    //   3480: invokevirtual charAt : (I)C
    //   3483: invokevirtual append : (C)Ljava/lang/StringBuilder;
    //   3486: pop
    //   3487: iload_2
    //   3488: ifeq -> 3864
    //   3491: goto -> 3498
    //   3494: invokestatic a : (Ljava/lang/Throwable;)Ljava/lang/Throwable;
    //   3497: athrow
    //   3498: aload_3
    //   3499: getstatic burp/Zgvf.ZM : Ljava/lang/String;
    //   3502: getstatic burp/Zb6b.ZU : Ljava/lang/Object;
    //   3505: checkcast java/math/BigInteger
    //   3508: invokevirtual intValue : ()I
    //   3511: bipush #32
    //   3513: irem
    //   3514: invokestatic abs : (I)I
    //   3517: invokevirtual charAt : (I)C
    //   3520: invokevirtual append : (C)Ljava/lang/StringBuilder;
    //   3523: pop
    //   3524: iload_2
    //   3525: ifeq -> 3864
    //   3528: goto -> 3535
    //   3531: invokestatic a : (Ljava/lang/Throwable;)Ljava/lang/Throwable;
    //   3534: athrow
    //   3535: aload_3
    //   3536: getstatic burp/Zz9v.Zv : Ljava/lang/String;
    //   3539: getstatic burp/Zb_c.ZN : Ljava/lang/Object;
    //   3542: checkcast java/math/BigInteger
    //   3545: invokevirtual intValue : ()I
    //   3548: bipush #32
    //   3550: irem
    //   3551: invokestatic abs : (I)I
    //   3554: invokevirtual charAt : (I)C
    //   3557: invokevirtual append : (C)Ljava/lang/StringBuilder;
    //   3560: pop
    //   3561: iload_2
    //   3562: ifeq -> 3864
    //   3565: goto -> 3572
    //   3568: invokestatic a : (Ljava/lang/Throwable;)Ljava/lang/Throwable;
    //   3571: athrow
    //   3572: aload_3
    //   3573: getstatic burp/Zero.ZL : Ljava/lang/String;
    //   3576: getstatic burp/Zth7.ZT : Ljava/lang/Object;
    //   3579: checkcast java/math/BigInteger
    //   3582: invokevirtual intValue : ()I
    //   3585: bipush #32
    //   3587: irem
    //   3588: invokestatic abs : (I)I
    //   3591: invokevirtual charAt : (I)C
    //   3594: invokevirtual append : (C)Ljava/lang/StringBuilder;
    //   3597: pop
    //   3598: iload_2
    //   3599: ifeq -> 3864
    //   3602: goto -> 3609
    //   3605: invokestatic a : (Ljava/lang/Throwable;)Ljava/lang/Throwable;
    //   3608: athrow
    //   3609: aload_3
    //   3610: getstatic burp/Zz5d.Zb : Ljava/lang/String;
    //   3613: getstatic burp/Zrkc.ZI : Ljava/lang/Object;
    //   3616: checkcast java/math/BigInteger
    //   3619: invokevirtual intValue : ()I
    //   3622: bipush #32
    //   3624: irem
    //   3625: invokestatic abs : (I)I
    //   3628: invokevirtual charAt : (I)C
    //   3631: invokevirtual append : (C)Ljava/lang/StringBuilder;
    //   3634: pop
    //   3635: iload_2
    //   3636: ifeq -> 3864
    //   3639: goto -> 3646
    //   3642: invokestatic a : (Ljava/lang/Throwable;)Ljava/lang/Throwable;
    //   3645: athrow
    //   3646: aload_3
    //   3647: getstatic burp/Zxdh.Zj : Ljava/lang/String;
    //   3650: getstatic burp/Zs9k.ZX : Ljava/lang/Object;
    //   3653: checkcast java/math/BigInteger
    //   3656: invokevirtual intValue : ()I
    //   3659: bipush #32
    //   3661: irem
    //   3662: invokestatic abs : (I)I
    //   3665: invokevirtual charAt : (I)C
    //   3668: invokevirtual append : (C)Ljava/lang/StringBuilder;
    //   3671: pop
    //   3672: iload_2
    //   3673: ifeq -> 3864
    //   3676: goto -> 3683
    //   3679: invokestatic a : (Ljava/lang/Throwable;)Ljava/lang/Throwable;
    //   3682: athrow
    //   3683: aload_3
    //   3684: getstatic burp/Zetv.ZE : Ljava/lang/String;
    //   3687: getstatic burp/Zexu.ZI : Ljava/lang/Object;
    //   3690: checkcast java/math/BigInteger
    //   3693: invokevirtual intValue : ()I
    //   3696: bipush #32
    //   3698: irem
    //   3699: invokestatic abs : (I)I
    //   3702: invokevirtual charAt : (I)C
    //   3705: invokevirtual append : (C)Ljava/lang/StringBuilder;
    //   3708: pop
    //   3709: iload_2
    //   3710: ifeq -> 3864
    //   3713: goto -> 3720
    //   3716: invokestatic a : (Ljava/lang/Throwable;)Ljava/lang/Throwable;
    //   3719: athrow
    //   3720: aload_3
    //   3721: getstatic burp/Zlxm.Zv : Ljava/lang/String;
    //   3724: getstatic burp/Zdm.ZA : Ljava/lang/Object;
    //   3727: checkcast java/math/BigInteger
    //   3730: invokevirtual intValue : ()I
    //   3733: bipush #32
    //   3735: irem
    //   3736: invokestatic abs : (I)I
    //   3739: invokevirtual charAt : (I)C
    //   3742: invokevirtual append : (C)Ljava/lang/StringBuilder;
    //   3745: pop
    //   3746: iload_2
    //   3747: ifeq -> 3864
    //   3750: goto -> 3757
    //   3753: invokestatic a : (Ljava/lang/Throwable;)Ljava/lang/Throwable;
    //   3756: athrow
    //   3757: aload_3
    //   3758: getstatic burp/Zlzo.Zs : Ljava/lang/String;
    //   3761: getstatic burp/Ztap.ZK : Ljava/lang/Object;
    //   3764: checkcast java/math/BigInteger
    //   3767: invokevirtual intValue : ()I
    //   3770: bipush #32
    //   3772: irem
    //   3773: invokestatic abs : (I)I
    //   3776: invokevirtual charAt : (I)C
    //   3779: invokevirtual append : (C)Ljava/lang/StringBuilder;
    //   3782: pop
    //   3783: iload_2
    //   3784: ifeq -> 3864
    //   3787: goto -> 3794
    //   3790: invokestatic a : (Ljava/lang/Throwable;)Ljava/lang/Throwable;
    //   3793: athrow
    //   3794: aload_3
    //   3795: getstatic burp/Zb_c.ZS : Ljava/lang/String;
    //   3798: getstatic burp/Zkhy.Zc : Ljava/lang/Object;
    //   3801: checkcast java/math/BigInteger
    //   3804: invokevirtual intValue : ()I
    //   3807: bipush #32
    //   3809: irem
    //   3810: invokestatic abs : (I)I
    //   3813: invokevirtual charAt : (I)C
    //   3816: invokevirtual append : (C)Ljava/lang/StringBuilder;
    //   3819: pop
    //   3820: iload_2
    //   3821: ifeq -> 3864
    //   3824: goto -> 3831
    //   3827: invokestatic a : (Ljava/lang/Throwable;)Ljava/lang/Throwable;
    //   3830: athrow
    //   3831: aload_3
    //   3832: getstatic burp/Zgj5.ZH : Ljava/lang/String;
    //   3835: getstatic burp/Zkaw.ZB : Ljava/lang/Object;
    //   3838: checkcast java/math/BigInteger
    //   3841: invokevirtual intValue : ()I
    //   3844: bipush #32
    //   3846: irem
    //   3847: invokestatic abs : (I)I
    //   3850: invokevirtual charAt : (I)C
    //   3853: invokevirtual append : (C)Ljava/lang/StringBuilder;
    //   3856: pop
    //   3857: goto -> 3864
    //   3860: invokestatic a : (Ljava/lang/Throwable;)Ljava/lang/Throwable;
    //   3863: athrow
    //   3864: iinc #4, 1
    //   3867: iload_2
    //   3868: ifeq -> 2532
    //   3871: aload_3
    //   3872: invokevirtual toString : ()Ljava/lang/String;
    //   3875: putstatic burp/Zkk6.ZP : Ljava/lang/String;
    //   3878: new java/lang/StringBuilder
    //   3881: dup
    //   3882: invokespecial <init> : ()V
    //   3885: astore #4
    //   3887: iconst_0
    //   3888: istore #5
    //   3890: iload #5
    //   3892: bipush #32
    //   3894: if_icmpge -> 5259
    //   3897: iload #5
    //   3899: tableswitch default -> 5252, 0 -> 4040, 1 -> 4078, 2 -> 4116, 3 -> 4154, 4 -> 4192, 5 -> 4230, 6 -> 4268, 7 -> 4306, 8 -> 4344, 9 -> 4382, 10 -> 4420, 11 -> 4458, 12 -> 4496, 13 -> 4534, 14 -> 4572, 15 -> 4610, 16 -> 4648, 17 -> 4686, 18 -> 4724, 19 -> 4762, 20 -> 4800, 21 -> 4838, 22 -> 4876, 23 -> 4914, 24 -> 4952, 25 -> 4990, 26 -> 5028, 27 -> 5066, 28 -> 5104, 29 -> 5142, 30 -> 5180, 31 -> 5218
    //   4040: aload #4
    //   4042: getstatic burp/Zlxm.Zv : Ljava/lang/String;
    //   4045: getstatic burp/Zz5s.Zg : Ljava/lang/Object;
    //   4048: checkcast java/math/BigInteger
    //   4051: invokevirtual intValue : ()I
    //   4054: bipush #32
    //   4056: irem
    //   4057: invokestatic abs : (I)I
    //   4060: invokevirtual charAt : (I)C
    //   4063: invokevirtual append : (C)Ljava/lang/StringBuilder;
    //   4066: pop
    //   4067: iload_2
    //   4068: ifeq -> 5252
    //   4071: goto -> 4078
    //   4074: invokestatic a : (Ljava/lang/Throwable;)Ljava/lang/Throwable;
    //   4077: athrow
    //   4078: aload #4
    //   4080: getstatic burp/Zrkc.ZE : Ljava/lang/String;
    //   4083: getstatic burp/Zgwh.Zl : Ljava/lang/Object;
    //   4086: checkcast java/math/BigInteger
    //   4089: invokevirtual intValue : ()I
    //   4092: bipush #32
    //   4094: irem
    //   4095: invokestatic abs : (I)I
    //   4098: invokevirtual charAt : (I)C
    //   4101: invokevirtual append : (C)Ljava/lang/StringBuilder;
    //   4104: pop
    //   4105: iload_2
    //   4106: ifeq -> 5252
    //   4109: goto -> 4116
    //   4112: invokestatic a : (Ljava/lang/Throwable;)Ljava/lang/Throwable;
    //   4115: athrow
    //   4116: aload #4
    //   4118: getstatic burp/Zkdc.Zc : Ljava/lang/String;
    //   4121: getstatic burp/Zexu.ZI : Ljava/lang/Object;
    //   4124: checkcast java/math/BigInteger
    //   4127: invokevirtual intValue : ()I
    //   4130: bipush #32
    //   4132: irem
    //   4133: invokestatic abs : (I)I
    //   4136: invokevirtual charAt : (I)C
    //   4139: invokevirtual append : (C)Ljava/lang/StringBuilder;
    //   4142: pop
    //   4143: iload_2
    //   4144: ifeq -> 5252
    //   4147: goto -> 4154
    //   4150: invokestatic a : (Ljava/lang/Throwable;)Ljava/lang/Throwable;
    //   4153: athrow
    //   4154: aload #4
    //   4156: getstatic burp/Zek5.ZE : Ljava/lang/String;
    //   4159: getstatic burp/Ztmy.ZH : Ljava/lang/Object;
    //   4162: checkcast java/math/BigInteger
    //   4165: invokevirtual intValue : ()I
    //   4168: bipush #32
    //   4170: irem
    //   4171: invokestatic abs : (I)I
    //   4174: invokevirtual charAt : (I)C
    //   4177: invokevirtual append : (C)Ljava/lang/StringBuilder;
    //   4180: pop
    //   4181: iload_2
    //   4182: ifeq -> 5252
    //   4185: goto -> 4192
    //   4188: invokestatic a : (Ljava/lang/Throwable;)Ljava/lang/Throwable;
    //   4191: athrow
    //   4192: aload #4
    //   4194: getstatic burp/Zrpx.ZM : Ljava/lang/String;
    //   4197: getstatic burp/Zgw7.Zi : Ljava/lang/Object;
    //   4200: checkcast java/math/BigInteger
    //   4203: invokevirtual intValue : ()I
    //   4206: bipush #32
    //   4208: irem
    //   4209: invokestatic abs : (I)I
    //   4212: invokevirtual charAt : (I)C
    //   4215: invokevirtual append : (C)Ljava/lang/StringBuilder;
    //   4218: pop
    //   4219: iload_2
    //   4220: ifeq -> 5252
    //   4223: goto -> 4230
    //   4226: invokestatic a : (Ljava/lang/Throwable;)Ljava/lang/Throwable;
    //   4229: athrow
    //   4230: aload #4
    //   4232: getstatic burp/Zeud.Za : Ljava/lang/String;
    //   4235: getstatic burp/Zek5.ZP : Ljava/lang/Object;
    //   4238: checkcast java/math/BigInteger
    //   4241: invokevirtual intValue : ()I
    //   4244: bipush #32
    //   4246: irem
    //   4247: invokestatic abs : (I)I
    //   4250: invokevirtual charAt : (I)C
    //   4253: invokevirtual append : (C)Ljava/lang/StringBuilder;
    //   4256: pop
    //   4257: iload_2
    //   4258: ifeq -> 5252
    //   4261: goto -> 4268
    //   4264: invokestatic a : (Ljava/lang/Throwable;)Ljava/lang/Throwable;
    //   4267: athrow
    //   4268: aload #4
    //   4270: getstatic burp/Zete.ZH : Ljava/lang/String;
    //   4273: getstatic burp/Zryq.ZR : Ljava/lang/Object;
    //   4276: checkcast java/math/BigInteger
    //   4279: invokevirtual intValue : ()I
    //   4282: bipush #32
    //   4284: irem
    //   4285: invokestatic abs : (I)I
    //   4288: invokevirtual charAt : (I)C
    //   4291: invokevirtual append : (C)Ljava/lang/StringBuilder;
    //   4294: pop
    //   4295: iload_2
    //   4296: ifeq -> 5252
    //   4299: goto -> 4306
    //   4302: invokestatic a : (Ljava/lang/Throwable;)Ljava/lang/Throwable;
    //   4305: athrow
    //   4306: aload #4
    //   4308: getstatic burp/Zx4k.ZC : Ljava/lang/String;
    //   4311: getstatic burp/Zzr.ZZ : Ljava/lang/Object;
    //   4314: checkcast java/math/BigInteger
    //   4317: invokevirtual intValue : ()I
    //   4320: bipush #32
    //   4322: irem
    //   4323: invokestatic abs : (I)I
    //   4326: invokevirtual charAt : (I)C
    //   4329: invokevirtual append : (C)Ljava/lang/StringBuilder;
    //   4332: pop
    //   4333: iload_2
    //   4334: ifeq -> 5252
    //   4337: goto -> 4344
    //   4340: invokestatic a : (Ljava/lang/Throwable;)Ljava/lang/Throwable;
    //   4343: athrow
    //   4344: aload #4
    //   4346: getstatic burp/Zexu.Zp : Ljava/lang/String;
    //   4349: getstatic burp/Zb6b.ZU : Ljava/lang/Object;
    //   4352: checkcast java/math/BigInteger
    //   4355: invokevirtual intValue : ()I
    //   4358: bipush #32
    //   4360: irem
    //   4361: invokestatic abs : (I)I
    //   4364: invokevirtual charAt : (I)C
    //   4367: invokevirtual append : (C)Ljava/lang/StringBuilder;
    //   4370: pop
    //   4371: iload_2
    //   4372: ifeq -> 5252
    //   4375: goto -> 4382
    //   4378: invokestatic a : (Ljava/lang/Throwable;)Ljava/lang/Throwable;
    //   4381: athrow
    //   4382: aload #4
    //   4384: getstatic burp/Zl5b.Zi : Ljava/lang/String;
    //   4387: getstatic burp/Zttq.Zh : Ljava/lang/Object;
    //   4390: checkcast java/math/BigInteger
    //   4393: invokevirtual intValue : ()I
    //   4396: bipush #32
    //   4398: irem
    //   4399: invokestatic abs : (I)I
    //   4402: invokevirtual charAt : (I)C
    //   4405: invokevirtual append : (C)Ljava/lang/StringBuilder;
    //   4408: pop
    //   4409: iload_2
    //   4410: ifeq -> 5252
    //   4413: goto -> 4420
    //   4416: invokestatic a : (Ljava/lang/Throwable;)Ljava/lang/Throwable;
    //   4419: athrow
    //   4420: aload #4
    //   4422: getstatic burp/Zxjw.Zv : Ljava/lang/String;
    //   4425: getstatic burp/Zzlg.Z_ : Ljava/lang/Object;
    //   4428: checkcast java/math/BigInteger
    //   4431: invokevirtual intValue : ()I
    //   4434: bipush #32
    //   4436: irem
    //   4437: invokestatic abs : (I)I
    //   4440: invokevirtual charAt : (I)C
    //   4443: invokevirtual append : (C)Ljava/lang/StringBuilder;
    //   4446: pop
    //   4447: iload_2
    //   4448: ifeq -> 5252
    //   4451: goto -> 4458
    //   4454: invokestatic a : (Ljava/lang/Throwable;)Ljava/lang/Throwable;
    //   4457: athrow
    //   4458: aload #4
    //   4460: getstatic burp/Zbnb.Zd : Ljava/lang/String;
    //   4463: getstatic burp/Zeu2.ZW : Ljava/lang/Object;
    //   4466: checkcast java/math/BigInteger
    //   4469: invokevirtual intValue : ()I
    //   4472: bipush #32
    //   4474: irem
    //   4475: invokestatic abs : (I)I
    //   4478: invokevirtual charAt : (I)C
    //   4481: invokevirtual append : (C)Ljava/lang/StringBuilder;
    //   4484: pop
    //   4485: iload_2
    //   4486: ifeq -> 5252
    //   4489: goto -> 4496
    //   4492: invokestatic a : (Ljava/lang/Throwable;)Ljava/lang/Throwable;
    //   4495: athrow
    //   4496: aload #4
    //   4498: getstatic burp/Zb_c.ZS : Ljava/lang/String;
    //   4501: getstatic burp/Zry7.ZZ : Ljava/lang/Object;
    //   4504: checkcast java/math/BigInteger
    //   4507: invokevirtual intValue : ()I
    //   4510: bipush #32
    //   4512: irem
    //   4513: invokestatic abs : (I)I
    //   4516: invokevirtual charAt : (I)C
    //   4519: invokevirtual append : (C)Ljava/lang/StringBuilder;
    //   4522: pop
    //   4523: iload_2
    //   4524: ifeq -> 5252
    //   4527: goto -> 4534
    //   4530: invokestatic a : (Ljava/lang/Throwable;)Ljava/lang/Throwable;
    //   4533: athrow
    //   4534: aload #4
    //   4536: getstatic burp/Zezq.Zp : Ljava/lang/String;
    //   4539: getstatic burp/Zxdh.ZD : Ljava/lang/Object;
    //   4542: checkcast java/math/BigInteger
    //   4545: invokevirtual intValue : ()I
    //   4548: bipush #32
    //   4550: irem
    //   4551: invokestatic abs : (I)I
    //   4554: invokevirtual charAt : (I)C
    //   4557: invokevirtual append : (C)Ljava/lang/StringBuilder;
    //   4560: pop
    //   4561: iload_2
    //   4562: ifeq -> 5252
    //   4565: goto -> 4572
    //   4568: invokestatic a : (Ljava/lang/Throwable;)Ljava/lang/Throwable;
    //   4571: athrow
    //   4572: aload #4
    //   4574: getstatic burp/Ze_b.ZX : Ljava/lang/String;
    //   4577: getstatic burp/Zct.ZW : Ljava/lang/Object;
    //   4580: checkcast java/math/BigInteger
    //   4583: invokevirtual intValue : ()I
    //   4586: bipush #32
    //   4588: irem
    //   4589: invokestatic abs : (I)I
    //   4592: invokevirtual charAt : (I)C
    //   4595: invokevirtual append : (C)Ljava/lang/StringBuilder;
    //   4598: pop
    //   4599: iload_2
    //   4600: ifeq -> 5252
    //   4603: goto -> 4610
    //   4606: invokestatic a : (Ljava/lang/Throwable;)Ljava/lang/Throwable;
    //   4609: athrow
    //   4610: aload #4
    //   4612: getstatic burp/Zzlg.Zw : Ljava/lang/String;
    //   4615: getstatic burp/Zek5.ZP : Ljava/lang/Object;
    //   4618: checkcast java/math/BigInteger
    //   4621: invokevirtual intValue : ()I
    //   4624: bipush #32
    //   4626: irem
    //   4627: invokestatic abs : (I)I
    //   4630: invokevirtual charAt : (I)C
    //   4633: invokevirtual append : (C)Ljava/lang/StringBuilder;
    //   4636: pop
    //   4637: iload_2
    //   4638: ifeq -> 5252
    //   4641: goto -> 4648
    //   4644: invokestatic a : (Ljava/lang/Throwable;)Ljava/lang/Throwable;
    //   4647: athrow
    //   4648: aload #4
    //   4650: getstatic burp/Zkhy.Zu : Ljava/lang/String;
    //   4653: getstatic burp/Ze_b.Zp : Ljava/lang/Object;
    //   4656: checkcast java/math/BigInteger
    //   4659: invokevirtual intValue : ()I
    //   4662: bipush #32
    //   4664: irem
    //   4665: invokestatic abs : (I)I
    //   4668: invokevirtual charAt : (I)C
    //   4671: invokevirtual append : (C)Ljava/lang/StringBuilder;
    //   4674: pop
    //   4675: iload_2
    //   4676: ifeq -> 5252
    //   4679: goto -> 4686
    //   4682: invokestatic a : (Ljava/lang/Throwable;)Ljava/lang/Throwable;
    //   4685: athrow
    //   4686: aload #4
    //   4688: getstatic burp/Zkaw.ZI : Ljava/lang/String;
    //   4691: getstatic burp/Zzlg.Z_ : Ljava/lang/Object;
    //   4694: checkcast java/math/BigInteger
    //   4697: invokevirtual intValue : ()I
    //   4700: bipush #32
    //   4702: irem
    //   4703: invokestatic abs : (I)I
    //   4706: invokevirtual charAt : (I)C
    //   4709: invokevirtual append : (C)Ljava/lang/StringBuilder;
    //   4712: pop
    //   4713: iload_2
    //   4714: ifeq -> 5252
    //   4717: goto -> 4724
    //   4720: invokestatic a : (Ljava/lang/Throwable;)Ljava/lang/Throwable;
    //   4723: athrow
    //   4724: aload #4
    //   4726: getstatic burp/Zzky.Zj : Ljava/lang/String;
    //   4729: getstatic burp/Zgwh.Zl : Ljava/lang/Object;
    //   4732: checkcast java/math/BigInteger
    //   4735: invokevirtual intValue : ()I
    //   4738: bipush #32
    //   4740: irem
    //   4741: invokestatic abs : (I)I
    //   4744: invokevirtual charAt : (I)C
    //   4747: invokevirtual append : (C)Ljava/lang/StringBuilder;
    //   4750: pop
    //   4751: iload_2
    //   4752: ifeq -> 5252
    //   4755: goto -> 4762
    //   4758: invokestatic a : (Ljava/lang/Throwable;)Ljava/lang/Throwable;
    //   4761: athrow
    //   4762: aload #4
    //   4764: getstatic burp/Zry7.Z_ : Ljava/lang/String;
    //   4767: getstatic burp/Zb_c.ZN : Ljava/lang/Object;
    //   4770: checkcast java/math/BigInteger
    //   4773: invokevirtual intValue : ()I
    //   4776: bipush #32
    //   4778: irem
    //   4779: invokestatic abs : (I)I
    //   4782: invokevirtual charAt : (I)C
    //   4785: invokevirtual append : (C)Ljava/lang/StringBuilder;
    //   4788: pop
    //   4789: iload_2
    //   4790: ifeq -> 5252
    //   4793: goto -> 4800
    //   4796: invokestatic a : (Ljava/lang/Throwable;)Ljava/lang/Throwable;
    //   4799: athrow
    //   4800: aload #4
    //   4802: getstatic burp/Ztod.Zj : Ljava/lang/String;
    //   4805: getstatic burp/Zblj.Zl : Ljava/lang/Object;
    //   4808: checkcast java/math/BigInteger
    //   4811: invokevirtual intValue : ()I
    //   4814: bipush #32
    //   4816: irem
    //   4817: invokestatic abs : (I)I
    //   4820: invokevirtual charAt : (I)C
    //   4823: invokevirtual append : (C)Ljava/lang/StringBuilder;
    //   4826: pop
    //   4827: iload_2
    //   4828: ifeq -> 5252
    //   4831: goto -> 4838
    //   4834: invokestatic a : (Ljava/lang/Throwable;)Ljava/lang/Throwable;
    //   4837: athrow
    //   4838: aload #4
    //   4840: getstatic burp/Zsq5.ZA : Ljava/lang/String;
    //   4843: getstatic burp/Zete.Zm : Ljava/lang/Object;
    //   4846: checkcast java/math/BigInteger
    //   4849: invokevirtual intValue : ()I
    //   4852: bipush #32
    //   4854: irem
    //   4855: invokestatic abs : (I)I
    //   4858: invokevirtual charAt : (I)C
    //   4861: invokevirtual append : (C)Ljava/lang/StringBuilder;
    //   4864: pop
    //   4865: iload_2
    //   4866: ifeq -> 5252
    //   4869: goto -> 4876
    //   4872: invokestatic a : (Ljava/lang/Throwable;)Ljava/lang/Throwable;
    //   4875: athrow
    //   4876: aload #4
    //   4878: getstatic burp/Zzr.Zp : Ljava/lang/String;
    //   4881: getstatic burp/Zl5b.ZI : Ljava/lang/Object;
    //   4884: checkcast java/math/BigInteger
    //   4887: invokevirtual intValue : ()I
    //   4890: bipush #32
    //   4892: irem
    //   4893: invokestatic abs : (I)I
    //   4896: invokevirtual charAt : (I)C
    //   4899: invokevirtual append : (C)Ljava/lang/StringBuilder;
    //   4902: pop
    //   4903: iload_2
    //   4904: ifeq -> 5252
    //   4907: goto -> 4914
    //   4910: invokestatic a : (Ljava/lang/Throwable;)Ljava/lang/Throwable;
    //   4913: athrow
    //   4914: aload #4
    //   4916: getstatic burp/Ztap.Zk : Ljava/lang/String;
    //   4919: getstatic burp/Zle4.Zh : Ljava/lang/Object;
    //   4922: checkcast java/math/BigInteger
    //   4925: invokevirtual intValue : ()I
    //   4928: bipush #32
    //   4930: irem
    //   4931: invokestatic abs : (I)I
    //   4934: invokevirtual charAt : (I)C
    //   4937: invokevirtual append : (C)Ljava/lang/StringBuilder;
    //   4940: pop
    //   4941: iload_2
    //   4942: ifeq -> 5252
    //   4945: goto -> 4952
    //   4948: invokestatic a : (Ljava/lang/Throwable;)Ljava/lang/Throwable;
    //   4951: athrow
    //   4952: aload #4
    //   4954: getstatic burp/Zsun.Zu : Ljava/lang/String;
    //   4957: getstatic burp/Zb_c.ZN : Ljava/lang/Object;
    //   4960: checkcast java/math/BigInteger
    //   4963: invokevirtual intValue : ()I
    //   4966: bipush #32
    //   4968: irem
    //   4969: invokestatic abs : (I)I
    //   4972: invokevirtual charAt : (I)C
    //   4975: invokevirtual append : (C)Ljava/lang/StringBuilder;
    //   4978: pop
    //   4979: iload_2
    //   4980: ifeq -> 5252
    //   4983: goto -> 4990
    //   4986: invokestatic a : (Ljava/lang/Throwable;)Ljava/lang/Throwable;
    //   4989: athrow
    //   4990: aload #4
    //   4992: getstatic burp/Zlxm.Zv : Ljava/lang/String;
    //   4995: getstatic burp/Zr4k.Zf : Ljava/lang/Object;
    //   4998: checkcast java/math/BigInteger
    //   5001: invokevirtual intValue : ()I
    //   5004: bipush #32
    //   5006: irem
    //   5007: invokestatic abs : (I)I
    //   5010: invokevirtual charAt : (I)C
    //   5013: invokevirtual append : (C)Ljava/lang/StringBuilder;
    //   5016: pop
    //   5017: iload_2
    //   5018: ifeq -> 5252
    //   5021: goto -> 5028
    //   5024: invokestatic a : (Ljava/lang/Throwable;)Ljava/lang/Throwable;
    //   5027: athrow
    //   5028: aload #4
    //   5030: getstatic burp/Zlhz.Zo : Ljava/lang/String;
    //   5033: getstatic burp/Zz9v.Zl : Ljava/lang/Object;
    //   5036: checkcast java/math/BigInteger
    //   5039: invokevirtual intValue : ()I
    //   5042: bipush #32
    //   5044: irem
    //   5045: invokestatic abs : (I)I
    //   5048: invokevirtual charAt : (I)C
    //   5051: invokevirtual append : (C)Ljava/lang/StringBuilder;
    //   5054: pop
    //   5055: iload_2
    //   5056: ifeq -> 5252
    //   5059: goto -> 5066
    //   5062: invokestatic a : (Ljava/lang/Throwable;)Ljava/lang/Throwable;
    //   5065: athrow
    //   5066: aload #4
    //   5068: getstatic burp/Zgyk.ZB : Ljava/lang/String;
    //   5071: getstatic burp/Zlpl.Ze : Ljava/lang/Object;
    //   5074: checkcast java/math/BigInteger
    //   5077: invokevirtual intValue : ()I
    //   5080: bipush #32
    //   5082: irem
    //   5083: invokestatic abs : (I)I
    //   5086: invokevirtual charAt : (I)C
    //   5089: invokevirtual append : (C)Ljava/lang/StringBuilder;
    //   5092: pop
    //   5093: iload_2
    //   5094: ifeq -> 5252
    //   5097: goto -> 5104
    //   5100: invokestatic a : (Ljava/lang/Throwable;)Ljava/lang/Throwable;
    //   5103: athrow
    //   5104: aload #4
    //   5106: getstatic burp/Zrkc.ZE : Ljava/lang/String;
    //   5109: getstatic burp/Zz3k.Zz : Ljava/lang/Object;
    //   5112: checkcast java/math/BigInteger
    //   5115: invokevirtual intValue : ()I
    //   5118: bipush #32
    //   5120: irem
    //   5121: invokestatic abs : (I)I
    //   5124: invokevirtual charAt : (I)C
    //   5127: invokevirtual append : (C)Ljava/lang/StringBuilder;
    //   5130: pop
    //   5131: iload_2
    //   5132: ifeq -> 5252
    //   5135: goto -> 5142
    //   5138: invokestatic a : (Ljava/lang/Throwable;)Ljava/lang/Throwable;
    //   5141: athrow
    //   5142: aload #4
    //   5144: getstatic burp/Zlzo.Zs : Ljava/lang/String;
    //   5147: getstatic burp/Zz5d.Zk : Ljava/lang/Object;
    //   5150: checkcast java/math/BigInteger
    //   5153: invokevirtual intValue : ()I
    //   5156: bipush #32
    //   5158: irem
    //   5159: invokestatic abs : (I)I
    //   5162: invokevirtual charAt : (I)C
    //   5165: invokevirtual append : (C)Ljava/lang/StringBuilder;
    //   5168: pop
    //   5169: iload_2
    //   5170: ifeq -> 5252
    //   5173: goto -> 5180
    //   5176: invokestatic a : (Ljava/lang/Throwable;)Ljava/lang/Throwable;
    //   5179: athrow
    //   5180: aload #4
    //   5182: getstatic burp/Zlxm.Zv : Ljava/lang/String;
    //   5185: getstatic burp/Zr8s.Zt : Ljava/lang/Object;
    //   5188: checkcast java/math/BigInteger
    //   5191: invokevirtual intValue : ()I
    //   5194: bipush #32
    //   5196: irem
    //   5197: invokestatic abs : (I)I
    //   5200: invokevirtual charAt : (I)C
    //   5203: invokevirtual append : (C)Ljava/lang/StringBuilder;
    //   5206: pop
    //   5207: iload_2
    //   5208: ifeq -> 5252
    //   5211: goto -> 5218
    //   5214: invokestatic a : (Ljava/lang/Throwable;)Ljava/lang/Throwable;
    //   5217: athrow
    //   5218: aload #4
    //   5220: getstatic burp/Zl5b.Zi : Ljava/lang/String;
    //   5223: getstatic burp/Zlg1.ZH : Ljava/lang/Object;
    //   5226: checkcast java/math/BigInteger
    //   5229: invokevirtual intValue : ()I
    //   5232: bipush #32
    //   5234: irem
    //   5235: invokestatic abs : (I)I
    //   5238: invokevirtual charAt : (I)C
    //   5241: invokevirtual append : (C)Ljava/lang/StringBuilder;
    //   5244: pop
    //   5245: goto -> 5252
    //   5248: invokestatic a : (Ljava/lang/Throwable;)Ljava/lang/Throwable;
    //   5251: athrow
    //   5252: iinc #5, 1
    //   5255: iload_2
    //   5256: ifeq -> 3890
    //   5259: aload #4
    //   5261: invokevirtual toString : ()Ljava/lang/String;
    //   5264: putstatic burp/Zttq.ZO : Ljava/lang/String;
    //   5267: sipush #-15906
    //   5270: sipush #-1856
    //   5273: invokestatic a : (II)Ljava/lang/String;
    //   5276: iconst_1
    //   5277: ldc burp/Ztex
    //   5279: invokevirtual getClassLoader : ()Ljava/lang/ClassLoader;
    //   5282: invokestatic forName : (Ljava/lang/String;ZLjava/lang/ClassLoader;)Ljava/lang/Class;
    //   5285: invokevirtual getDeclaredFields : ()[Ljava/lang/reflect/Field;
    //   5288: astore #5
    //   5290: aload #5
    //   5292: arraylength
    //   5293: istore #6
    //   5295: iconst_0
    //   5296: istore #7
    //   5298: iload #7
    //   5300: iload #6
    //   5302: if_icmpge -> 5440
    //   5305: aload #5
    //   5307: iload #7
    //   5309: aaload
    //   5310: astore #8
    //   5312: aload #8
    //   5314: invokevirtual getModifiers : ()I
    //   5317: invokestatic isStatic : (I)Z
    //   5320: ifne -> 5330
    //   5323: goto -> 5433
    //   5326: invokestatic a : (Ljava/lang/Throwable;)Ljava/lang/Throwable;
    //   5329: athrow
    //   5330: aload #8
    //   5332: invokevirtual getType : ()Ljava/lang/Class;
    //   5335: astore #9
    //   5337: aload #9
    //   5339: ifnull -> 5420
    //   5342: aload #9
    //   5344: invokevirtual isPrimitive : ()Z
    //   5347: ifne -> 5420
    //   5350: goto -> 5357
    //   5353: invokestatic a : (Ljava/lang/Throwable;)Ljava/lang/Throwable;
    //   5356: athrow
    //   5357: aload #9
    //   5359: invokevirtual getPackage : ()Ljava/lang/Package;
    //   5362: ifnull -> 5420
    //   5365: goto -> 5372
    //   5368: invokestatic a : (Ljava/lang/Throwable;)Ljava/lang/Throwable;
    //   5371: athrow
    //   5372: aload #9
    //   5374: invokevirtual getPackage : ()Ljava/lang/Package;
    //   5377: invokevirtual getName : ()Ljava/lang/String;
    //   5380: ifnull -> 5420
    //   5383: goto -> 5390
    //   5386: invokestatic a : (Ljava/lang/Throwable;)Ljava/lang/Throwable;
    //   5389: athrow
    //   5390: aload #9
    //   5392: invokevirtual getPackage : ()Ljava/lang/Package;
    //   5395: invokevirtual getName : ()Ljava/lang/String;
    //   5398: sipush #-15915
    //   5401: sipush #15957
    //   5404: invokestatic a : (II)Ljava/lang/String;
    //   5407: invokevirtual startsWith : (Ljava/lang/String;)Z
    //   5410: ifne -> 5420
    //   5413: goto -> 5420
    //   5416: invokestatic a : (Ljava/lang/Throwable;)Ljava/lang/Throwable;
    //   5419: athrow
    //   5420: aload #8
    //   5422: iconst_1
    //   5423: invokevirtual setAccessible : (Z)V
    //   5426: aload #8
    //   5428: aconst_null
    //   5429: invokevirtual get : (Ljava/lang/Object;)Ljava/lang/Object;
    //   5432: pop
    //   5433: iinc #7, 1
    //   5436: iload_2
    //   5437: ifeq -> 5298
    //   5440: sipush #-15913
    //   5443: sipush #-25674
    //   5446: invokestatic a : (II)Ljava/lang/String;
    //   5449: invokestatic forName : (Ljava/lang/String;)Ljava/lang/Class;
    //   5452: invokevirtual getDeclaredMethods : ()[Ljava/lang/reflect/Method;
    //   5455: astore #5
    //   5457: aload #5
    //   5459: arraylength
    //   5460: istore #6
    //   5462: iconst_0
    //   5463: istore #7
    //   5465: iload #7
    //   5467: iload #6
    //   5469: if_icmpge -> 5602
    //   5472: aload #5
    //   5474: iload #7
    //   5476: aaload
    //   5477: astore #8
    //   5479: aload #8
    //   5481: invokevirtual getParameterTypes : ()[Ljava/lang/Class;
    //   5484: pop
    //   5485: aload #8
    //   5487: invokevirtual getModifiers : ()I
    //   5490: invokestatic isStatic : (I)Z
    //   5493: ifeq -> 5588
    //   5496: aload #8
    //   5498: invokevirtual getParameterTypes : ()[Ljava/lang/Class;
    //   5501: arraylength
    //   5502: iconst_2
    //   5503: if_icmpne -> 5588
    //   5506: goto -> 5513
    //   5509: invokestatic a : (Ljava/lang/Throwable;)Ljava/lang/Throwable;
    //   5512: athrow
    //   5513: aload #8
    //   5515: invokevirtual getReturnType : ()Ljava/lang/Class;
    //   5518: getstatic java/lang/Void.TYPE : Ljava/lang/Class;
    //   5521: invokevirtual equals : (Ljava/lang/Object;)Z
    //   5524: ifeq -> 5588
    //   5527: goto -> 5534
    //   5530: invokestatic a : (Ljava/lang/Throwable;)Ljava/lang/Throwable;
    //   5533: athrow
    //   5534: aload #8
    //   5536: iconst_1
    //   5537: invokevirtual setAccessible : (Z)V
    //   5540: aload #8
    //   5542: aconst_null
    //   5543: iconst_2
    //   5544: anewarray java/lang/Object
    //   5547: dup
    //   5548: iconst_0
    //   5549: aload_0
    //   5550: aastore
    //   5551: dup
    //   5552: iconst_1
    //   5553: aload_1
    //   5554: ifnonnull -> 5572
    //   5557: goto -> 5564
    //   5560: invokestatic a : (Ljava/lang/Throwable;)Ljava/lang/Throwable;
    //   5563: athrow
    //   5564: aload_1
    //   5565: goto -> 5579
    //   5568: invokestatic a : (Ljava/lang/Throwable;)Ljava/lang/Throwable;
    //   5571: athrow
    //   5572: aload_1
    //   5573: checkcast [B
    //   5576: invokevirtual clone : ()Ljava/lang/Object;
    //   5579: aastore
    //   5580: invokevirtual invoke : (Ljava/lang/Object;[Ljava/lang/Object;)Ljava/lang/Object;
    //   5583: pop
    //   5584: iload_2
    //   5585: ifeq -> 5602
    //   5588: iinc #7, 1
    //   5591: iload_2
    //   5592: ifeq -> 5465
    //   5595: goto -> 5602
    //   5598: invokestatic a : (Ljava/lang/Throwable;)Ljava/lang/Throwable;
    //   5601: athrow
    //   5602: getstatic burp/Zek5.ZP : Ljava/lang/Object;
    //   5605: checkcast java/math/BigInteger
    //   5608: invokevirtual toByteArray : ()[B
    //   5611: astore #5
    //   5613: aload #5
    //   5615: arraylength
    //   5616: iconst_2
    //   5617: iadd
    //   5618: newarray byte
    //   5620: astore #7
    //   5622: iconst_0
    //   5623: istore #8
    //   5625: iload #8
    //   5627: aload #5
    //   5629: arraylength
    //   5630: if_icmpge -> 5650
    //   5633: aload #7
    //   5635: iload #8
    //   5637: aload #5
    //   5639: iload #8
    //   5641: baload
    //   5642: bastore
    //   5643: iinc #8, 1
    //   5646: iload_2
    //   5647: ifeq -> 5625
    //   5650: aload #7
    //   5652: arraylength
    //   5653: iconst_3
    //   5654: idiv
    //   5655: iconst_4
    //   5656: imul
    //   5657: newarray byte
    //   5659: astore #6
    //   5661: iconst_0
    //   5662: istore #8
    //   5664: iconst_0
    //   5665: istore #9
    //   5667: iload #8
    //   5669: aload #5
    //   5671: arraylength
    //   5672: if_icmpge -> 5783
    //   5675: aload #6
    //   5677: iload #9
    //   5679: aload #7
    //   5681: iload #8
    //   5683: baload
    //   5684: iconst_2
    //   5685: iushr
    //   5686: bipush #63
    //   5688: iand
    //   5689: i2b
    //   5690: bastore
    //   5691: aload #6
    //   5693: iload #9
    //   5695: iconst_1
    //   5696: iadd
    //   5697: aload #7
    //   5699: iload #8
    //   5701: iconst_1
    //   5702: iadd
    //   5703: baload
    //   5704: iconst_4
    //   5705: iushr
    //   5706: bipush #15
    //   5708: iand
    //   5709: aload #7
    //   5711: iload #8
    //   5713: baload
    //   5714: iconst_4
    //   5715: ishl
    //   5716: bipush #63
    //   5718: iand
    //   5719: ior
    //   5720: i2b
    //   5721: bastore
    //   5722: aload #6
    //   5724: iload #9
    //   5726: iconst_2
    //   5727: iadd
    //   5728: aload #7
    //   5730: iload #8
    //   5732: iconst_2
    //   5733: iadd
    //   5734: baload
    //   5735: bipush #6
    //   5737: iushr
    //   5738: iconst_3
    //   5739: iand
    //   5740: aload #7
    //   5742: iload #8
    //   5744: iconst_1
    //   5745: iadd
    //   5746: baload
    //   5747: iconst_2
    //   5748: ishl
    //   5749: bipush #63
    //   5751: iand
    //   5752: ior
    //   5753: i2b
    //   5754: bastore
    //   5755: aload #6
    //   5757: iload #9
    //   5759: iconst_3
    //   5760: iadd
    //   5761: aload #7
    //   5763: iload #8
    //   5765: iconst_2
    //   5766: iadd
    //   5767: baload
    //   5768: bipush #63
    //   5770: iand
    //   5771: i2b
    //   5772: bastore
    //   5773: iinc #8, 3
    //   5776: iinc #9, 4
    //   5779: iload_2
    //   5780: ifeq -> 5667
    //   5783: iconst_0
    //   5784: istore #8
    //   5786: iload #8
    //   5788: aload #6
    //   5790: arraylength
    //   5791: if_icmpge -> 5975
    //   5794: aload #6
    //   5796: iload #8
    //   5798: baload
    //   5799: bipush #26
    //   5801: if_icmpge -> 5829
    //   5804: aload #6
    //   5806: iload #8
    //   5808: aload #6
    //   5810: iload #8
    //   5812: baload
    //   5813: bipush #65
    //   5815: iadd
    //   5816: i2b
    //   5817: bastore
    //   5818: iload_2
    //   5819: ifeq -> 5968
    //   5822: goto -> 5829
    //   5825: invokestatic a : (Ljava/lang/Throwable;)Ljava/lang/Throwable;
    //   5828: athrow
    //   5829: aload #6
    //   5831: iload #8
    //   5833: baload
    //   5834: bipush #52
    //   5836: if_icmpge -> 5874
    //   5839: goto -> 5846
    //   5842: invokestatic a : (Ljava/lang/Throwable;)Ljava/lang/Throwable;
    //   5845: athrow
    //   5846: aload #6
    //   5848: iload #8
    //   5850: aload #6
    //   5852: iload #8
    //   5854: baload
    //   5855: bipush #97
    //   5857: iadd
    //   5858: bipush #26
    //   5860: isub
    //   5861: i2b
    //   5862: bastore
    //   5863: iload_2
    //   5864: ifeq -> 5968
    //   5867: goto -> 5874
    //   5870: invokestatic a : (Ljava/lang/Throwable;)Ljava/lang/Throwable;
    //   5873: athrow
    //   5874: aload #6
    //   5876: iload #8
    //   5878: baload
    //   5879: bipush #62
    //   5881: if_icmpge -> 5919
    //   5884: goto -> 5891
    //   5887: invokestatic a : (Ljava/lang/Throwable;)Ljava/lang/Throwable;
    //   5890: athrow
    //   5891: aload #6
    //   5893: iload #8
    //   5895: aload #6
    //   5897: iload #8
    //   5899: baload
    //   5900: bipush #48
    //   5902: iadd
    //   5903: bipush #52
    //   5905: isub
    //   5906: i2b
    //   5907: bastore
    //   5908: iload_2
    //   5909: ifeq -> 5968
    //   5912: goto -> 5919
    //   5915: invokestatic a : (Ljava/lang/Throwable;)Ljava/lang/Throwable;
    //   5918: athrow
    //   5919: aload #6
    //   5921: iload #8
    //   5923: baload
    //   5924: bipush #63
    //   5926: if_icmpge -> 5954
    //   5929: goto -> 5936
    //   5932: invokestatic a : (Ljava/lang/Throwable;)Ljava/lang/Throwable;
    //   5935: athrow
    //   5936: aload #6
    //   5938: iload #8
    //   5940: bipush #43
    //   5942: bastore
    //   5943: iload_2
    //   5944: ifeq -> 5968
    //   5947: goto -> 5954
    //   5950: invokestatic a : (Ljava/lang/Throwable;)Ljava/lang/Throwable;
    //   5953: athrow
    //   5954: aload #6
    //   5956: iload #8
    //   5958: bipush #47
    //   5960: bastore
    //   5961: goto -> 5968
    //   5964: invokestatic a : (Ljava/lang/Throwable;)Ljava/lang/Throwable;
    //   5967: athrow
    //   5968: iinc #8, 1
    //   5971: iload_2
    //   5972: ifeq -> 5786
    //   5975: aload #6
    //   5977: arraylength
    //   5978: iconst_1
    //   5979: isub
    //   5980: istore #8
    //   5982: iload #8
    //   5984: aload #5
    //   5986: arraylength
    //   5987: iconst_4
    //   5988: imul
    //   5989: iconst_3
    //   5990: idiv
    //   5991: if_icmple -> 6008
    //   5994: aload #6
    //   5996: iload #8
    //   5998: bipush #61
    //   6000: bastore
    //   6001: iinc #8, -1
    //   6004: iload_2
    //   6005: ifeq -> 5982
    //   6008: getstatic burp/Zsq5.ZA : Ljava/lang/String;
    //   6011: getstatic burp/Zxjw.ZU : Ljava/lang/Object;
    //   6014: checkcast java/math/BigInteger
    //   6017: invokevirtual intValue : ()I
    //   6020: bipush #32
    //   6022: irem
    //   6023: invokestatic abs : (I)I
    //   6026: invokevirtual charAt : (I)C
    //   6029: getstatic burp/Zz5s.ZL : Ljava/lang/String;
    //   6032: getstatic burp/Ztt0.ZF : Ljava/lang/Object;
    //   6035: checkcast java/math/BigInteger
    //   6038: invokevirtual intValue : ()I
    //   6041: bipush #32
    //   6043: irem
    //   6044: invokestatic abs : (I)I
    //   6047: invokevirtual charAt : (I)C
    //   6050: if_icmpgt -> 6157
    //   6053: getstatic burp/Zgyk.ZB : Ljava/lang/String;
    //   6056: getstatic burp/Ztod.ZP : Ljava/lang/Object;
    //   6059: checkcast java/math/BigInteger
    //   6062: invokevirtual intValue : ()I
    //   6065: bipush #32
    //   6067: irem
    //   6068: invokestatic abs : (I)I
    //   6071: invokevirtual charAt : (I)C
    //   6074: getstatic burp/Ztod.Zj : Ljava/lang/String;
    //   6077: getstatic burp/Zeno.Zo : Ljava/lang/Object;
    //   6080: checkcast java/math/BigInteger
    //   6083: invokevirtual intValue : ()I
    //   6086: bipush #32
    //   6088: irem
    //   6089: invokestatic abs : (I)I
    //   6092: invokevirtual charAt : (I)C
    //   6095: if_icmple -> 6157
    //   6098: goto -> 6105
    //   6101: invokestatic a : (Ljava/lang/Throwable;)Ljava/lang/Throwable;
    //   6104: athrow
    //   6105: getstatic burp/Zmcq.ZY : Ljava/lang/String;
    //   6108: getstatic burp/Zkhy.Zc : Ljava/lang/Object;
    //   6111: checkcast java/math/BigInteger
    //   6114: invokevirtual intValue : ()I
    //   6117: bipush #32
    //   6119: irem
    //   6120: invokestatic abs : (I)I
    //   6123: invokevirtual charAt : (I)C
    //   6126: getstatic burp/Zrd0.Zk : Ljava/lang/String;
    //   6129: getstatic burp/Zr8s.Zt : Ljava/lang/Object;
    //   6132: checkcast java/math/BigInteger
    //   6135: invokevirtual intValue : ()I
    //   6138: bipush #32
    //   6140: irem
    //   6141: invokestatic abs : (I)I
    //   6144: invokevirtual charAt : (I)C
    //   6147: if_icmple -> 6165
    //   6150: goto -> 6157
    //   6153: invokestatic a : (Ljava/lang/Throwable;)Ljava/lang/Throwable;
    //   6156: athrow
    //   6157: iconst_1
    //   6158: goto -> 6166
    //   6161: invokestatic a : (Ljava/lang/Throwable;)Ljava/lang/Throwable;
    //   6164: athrow
    //   6165: iconst_0
    //   6166: ireturn
    //   6167: astore_3
    //   6168: new java/lang/Exception
    //   6171: dup
    //   6172: aload_3
    //   6173: invokevirtual getMessage : ()Ljava/lang/String;
    //   6176: invokespecial <init> : (Ljava/lang/String;)V
    //   6179: athrow
    // Exception table:
    //   from	to	target	type
    //   4	6166	6167	java/lang/Throwable
    //   149	164	164	java/lang/Throwable
    //   1166	1192	1192	java/lang/Throwable
    //   1273	1288	1288	java/lang/Throwable
    //   2470	2495	2498	java/lang/Throwable
    //   2539	2714	2717	java/lang/Throwable
    //   2684	2751	2754	java/lang/Throwable
    //   2721	2788	2791	java/lang/Throwable
    //   2758	2825	2828	java/lang/Throwable
    //   2795	2862	2865	java/lang/Throwable
    //   2832	2899	2902	java/lang/Throwable
    //   2869	2936	2939	java/lang/Throwable
    //   2906	2973	2976	java/lang/Throwable
    //   2943	3010	3013	java/lang/Throwable
    //   2980	3047	3050	java/lang/Throwable
    //   3017	3084	3087	java/lang/Throwable
    //   3054	3121	3124	java/lang/Throwable
    //   3091	3158	3161	java/lang/Throwable
    //   3128	3195	3198	java/lang/Throwable
    //   3165	3232	3235	java/lang/Throwable
    //   3202	3269	3272	java/lang/Throwable
    //   3239	3306	3309	java/lang/Throwable
    //   3276	3343	3346	java/lang/Throwable
    //   3313	3380	3383	java/lang/Throwable
    //   3350	3417	3420	java/lang/Throwable
    //   3387	3454	3457	java/lang/Throwable
    //   3424	3491	3494	java/lang/Throwable
    //   3461	3528	3531	java/lang/Throwable
    //   3498	3565	3568	java/lang/Throwable
    //   3535	3602	3605	java/lang/Throwable
    //   3572	3639	3642	java/lang/Throwable
    //   3609	3676	3679	java/lang/Throwable
    //   3646	3713	3716	java/lang/Throwable
    //   3683	3750	3753	java/lang/Throwable
    //   3720	3787	3790	java/lang/Throwable
    //   3757	3824	3827	java/lang/Throwable
    //   3794	3857	3860	java/lang/Throwable
    //   3897	4071	4074	java/lang/Throwable
    //   4040	4109	4112	java/lang/Throwable
    //   4078	4147	4150	java/lang/Throwable
    //   4116	4185	4188	java/lang/Throwable
    //   4154	4223	4226	java/lang/Throwable
    //   4192	4261	4264	java/lang/Throwable
    //   4230	4299	4302	java/lang/Throwable
    //   4268	4337	4340	java/lang/Throwable
    //   4306	4375	4378	java/lang/Throwable
    //   4344	4413	4416	java/lang/Throwable
    //   4382	4451	4454	java/lang/Throwable
    //   4420	4489	4492	java/lang/Throwable
    //   4458	4527	4530	java/lang/Throwable
    //   4496	4565	4568	java/lang/Throwable
    //   4534	4603	4606	java/lang/Throwable
    //   4572	4641	4644	java/lang/Throwable
    //   4610	4679	4682	java/lang/Throwable
    //   4648	4717	4720	java/lang/Throwable
    //   4686	4755	4758	java/lang/Throwable
    //   4724	4793	4796	java/lang/Throwable
    //   4762	4831	4834	java/lang/Throwable
    //   4800	4869	4872	java/lang/Throwable
    //   4838	4907	4910	java/lang/Throwable
    //   4876	4945	4948	java/lang/Throwable
    //   4914	4983	4986	java/lang/Throwable
    //   4952	5021	5024	java/lang/Throwable
    //   4990	5059	5062	java/lang/Throwable
    //   5028	5097	5100	java/lang/Throwable
    //   5066	5135	5138	java/lang/Throwable
    //   5104	5173	5176	java/lang/Throwable
    //   5142	5211	5214	java/lang/Throwable
    //   5180	5245	5248	java/lang/Throwable
    //   5312	5326	5326	java/lang/Throwable
    //   5337	5350	5353	java/lang/Throwable
    //   5342	5365	5368	java/lang/Throwable
    //   5357	5383	5386	java/lang/Throwable
    //   5372	5413	5416	java/lang/Throwable
    //   5479	5506	5509	java/lang/Throwable
    //   5496	5527	5530	java/lang/Throwable
    //   5513	5557	5560	java/lang/Throwable
    //   5534	5568	5568	java/lang/Throwable
    //   5579	5595	5598	java/lang/Throwable
    //   5794	5822	5825	java/lang/Throwable
    //   5804	5839	5842	java/lang/Throwable
    //   5829	5867	5870	java/lang/Throwable
    //   5846	5884	5887	java/lang/Throwable
    //   5874	5912	5915	java/lang/Throwable
    //   5891	5929	5932	java/lang/Throwable
    //   5919	5947	5950	java/lang/Throwable
    //   5936	5961	5964	java/lang/Throwable
    //   6008	6098	6101	java/lang/Throwable
    //   6053	6150	6153	java/lang/Throwable
    //   6105	6161	6161	java/lang/Throwable
  }
  
  static void Zt(Object[] paramArrayOfObject, Object paramObject) throws Throwable {}
  
  static {
    // Byte code:
    //   0: bipush #12
    //   2: anewarray java/lang/String
    //   5: astore #5
    //   7: iconst_0
    //   8: istore_3
    //   9: ldc 'LZJn`cHP)c'}??\\t.!CM/V:0V<}o#qo5Z7f~W@]k8x:\\fU64UrbA\\tC) 1o 8\6DH5#\\tc,ilM0tq"\\brE@)Vi>inJ&mv`Z]g-x\\rvC'-wX m8j-b@@\\r\\rzb5\\t}z7p'
    //   11: dup
    //   12: astore_2
    //   13: invokevirtual length : ()I
    //   16: istore #4
    //   18: bipush #19
    //   20: istore_1
    //   21: iconst_m1
    //   22: istore_0
    //   23: bipush #56
    //   25: iinc #0, 1
    //   28: aload_2
    //   29: iload_0
    //   30: dup
    //   31: iload_1
    //   32: iadd
    //   33: invokevirtual substring : (II)Ljava/lang/String;
    //   36: iconst_m1
    //   37: goto -> 144
    //   40: aload #5
    //   42: swap
    //   43: iload_3
    //   44: iinc #3, 1
    //   47: swap
    //   48: aastore
    //   49: iload_0
    //   50: iload_1
    //   51: iadd
    //   52: dup
    //   53: istore_0
    //   54: iload #4
    //   56: if_icmpge -> 68
    //   59: aload_2
    //   60: iload_0
    //   61: invokevirtual charAt : (I)C
    //   64: istore_1
    //   65: goto -> 23
    //   68: ldc 'u??\\tJt\\r'
    //   70: dup
    //   71: astore_2
    //   72: invokevirtual length : ()I
    //   75: istore #4
    //   77: sipush #128
    //   80: istore_1
    //   81: iconst_m1
    //   82: istore_0
    //   83: bipush #38
    //   85: iinc #0, 1
    //   88: aload_2
    //   89: iload_0
    //   90: dup
    //   91: iload_1
    //   92: iadd
    //   93: invokevirtual substring : (II)Ljava/lang/String;
    //   96: iconst_0
    //   97: goto -> 144
    //   100: aload #5
    //   102: swap
    //   103: iload_3
    //   104: iinc #3, 1
    //   107: swap
    //   108: aastore
    //   109: iload_0
    //   110: iload_1
    //   111: iadd
    //   112: dup
    //   113: istore_0
    //   114: iload #4
    //   116: if_icmpge -> 128
    //   119: aload_2
    //   120: iload_0
    //   121: invokevirtual charAt : (I)C
    //   124: istore_1
    //   125: goto -> 83
    //   128: aload #5
    //   130: putstatic burp/Zr_y.a : [Ljava/lang/String;
    //   133: bipush #12
    //   135: anewarray java/lang/String
    //   138: putstatic burp/Zr_y.b : [Ljava/lang/String;
    //   141: goto -> 300
    //   144: dup_x2
    //   145: pop
    //   146: invokevirtual toCharArray : ()[C
    //   149: dup_x1
    //   150: arraylength
    //   151: dup_x2
    //   152: pop
    //   153: iconst_0
    //   154: istore #6
    //   156: dup2_x1
    //   157: pop2
    //   158: dup_x2
    //   159: iconst_1
    //   160: if_icmpgt -> 260
    //   163: dup2
    //   164: swap
    //   165: iload #6
    //   167: dup2_x1
    //   168: caload
    //   169: swap
    //   170: iload #6
    //   172: bipush #7
    //   174: irem
    //   175: tableswitch default -> 242, 0 -> 212, 1 -> 217, 2 -> 222, 3 -> 227, 4 -> 232, 5 -> 237
    //   212: bipush #107
    //   214: goto -> 244
    //   217: bipush #15
    //   219: goto -> 244
    //   222: bipush #100
    //   224: goto -> 244
    //   227: bipush #13
    //   229: goto -> 244
    //   232: bipush #8
    //   234: goto -> 244
    //   237: bipush #44
    //   239: goto -> 244
    //   242: bipush #51
    //   244: ixor
    //   245: ixor
    //   246: i2c
    //   247: castore
    //   248: iinc #6, 1
    //   251: dup
    //   252: ifne -> 260
    //   255: dup2
    //   256: dup_x1
    //   257: goto -> 167
    //   260: dup2_x1
    //   261: pop2
    //   262: dup_x2
    //   263: iload #6
    //   265: if_icmpgt -> 163
    //   268: pop
    //   269: new java/lang/String
    //   272: dup_x1
    //   273: swap
    //   274: invokespecial <init> : ([C)V
    //   277: invokevirtual intern : ()Ljava/lang/String;
    //   280: swap
    //   281: pop
    //   282: swap
    //   283: tableswitch default -> 40, 0 -> 100
    //   300: new java/math/BigInteger
    //   303: dup
    //   304: sipush #-15910
    //   307: sipush #19398
    //   310: invokestatic a : (II)Ljava/lang/String;
    //   313: invokespecial <init> : (Ljava/lang/String;)V
    //   316: putstatic burp/Zr_y.ZI : Ljava/lang/Object;
    //   319: sipush #-15909
    //   322: sipush #2811
    //   325: invokestatic a : (II)Ljava/lang/String;
    //   328: putstatic burp/Zr_y.Zb : Ljava/lang/String;
    //   331: return
  }
  
  private static Throwable a(Throwable paramThrowable) {
    return paramThrowable;
  }
  
  private static String a(int paramInt1, int paramInt2) {
    int i = (paramInt1 ^ 0xFFFFC1DC) & 0xFFFF;
    if (b[i] == null) {
      char[] arrayOfChar = a[i].toCharArray();
      switch (arrayOfChar[0] & 0xFF) {
        case 0:
        
        case 1:
        
        case 2:
        
        case 3:
        
        case 4:
        
        case 5:
        
        case 6:
        
        case 7:
        
        case 8:
        
        case 9:
        
        case 10:
        
        case 11:
        
        case 12:
        
        case 13:
        
        case 14:
        
        case 15:
        
        case 16:
        
        case 17:
        
        case 18:
        
        case 19:
        
        case 20:
        
        case 21:
        
        case 22:
        
        case 23:
        
        case 24:
        
        case 25:
        
        case 26:
        
        case 27:
        
        case 28:
        
        case 29:
        
        case 30:
        
        case 31:
        
        case 32:
        
        case 33:
        
        case 34:
        
        case 35:
        
        case 36:
        
        case 37:
        
        case 38:
        
        case 39:
        
        case 40:
        
        case 41:
        
        case 42:
        
        case 43:
        
        case 44:
        
        case 45:
        
        case 46:
        
        case 47:
        
        case 48:
        
        case 49:
        
        case 50:
        
        case 51:
        
        case 52:
        
        case 53:
        
        case 54:
        
        case 55:
        
        case 56:
        
        case 57:
        
        case 58:
        
        case 59:
        
        case 60:
        
        case 61:
        
        case 62:
        
        case 63:
        
        case 64:
        
        case 65:
        
        case 66:
        
        case 67:
        
        case 68:
        
        case 69:
        
        case 70:
        
        case 71:
        
        case 72:
        
        case 73:
        
        case 74:
        
        case 75:
        
        case 76:
        
        case 77:
        
        case 78:
        
        case 79:
        
        case 80:
        
        case 81:
        
        case 82:
        
        case 83:
        
        case 84:
        
        case 85:
        
        case 86:
        
        case 87:
        
        case 88:
        
        case 89:
        
        case 90:
        
        case 91:
        
        case 92:
        
        case 93:
        
        case 94:
        
        case 95:
        
        case 96:
        
        case 97:
        
        case 98:
        
        case 99:
        
        case 100:
        
        case 101:
        
        case 102:
        
        case 103:
        
        case 104:
        
        case 105:
        
        case 106:
        
        case 107:
        
        case 108:
        
        case 109:
        
        case 110:
        
        case 111:
        
        case 112:
        
        case 113:
        
        case 114:
        
        case 115:
        
        case 116:
        
        case 117:
        
        case 118:
        
        case 119:
        
        case 120:
        
        case 121:
        
        case 122:
        
        case 123:
        
        case 124:
        
        case 125:
        
        case 126:
        
        case 127:
        
        case 128:
        
        case 129:
        
        case 130:
        
        case 131:
        
        case 132:
        
        case 133:
        
        case 134:
        
        case 135:
        
        case 136:
        
        case 137:
        
        case 138:
        
        case 139:
        
        case 140:
        
        case 141:
        
        case 142:
        
        case 143:
        
        case 144:
        
        case 145:
        
        case 146:
        
        case 147:
        
        case 148:
        
        case 149:
        
        case 150:
        
        case 151:
        
        case 152:
        
        case 153:
        
        case 154:
        
        case 155:
        
        case 156:
        
        case 157:
        
        case 158:
        
        case 159:
        
        case 160:
        
        case 161:
        
        case 162:
        
        case 163:
        
        case 164:
        
        case 165:
        
        case 166:
        
        case 167:
        
        case 168:
        
        case 169:
        
        case 170:
        
        case 171:
        
        case 172:
        
        case 173:
        
        case 174:
        
        case 175:
        
        case 176:
        
        case 177:
        
        case 178:
        
        case 179:
        
        case 180:
        
        case 181:
        
        case 182:
        
        case 183:
        
        case 184:
        
        case 185:
        
        case 186:
        
        case 187:
        
        case 188:
        
        case 189:
        
        case 190:
        
        case 191:
        
        case 192:
        
        case 193:
        
        case 194:
        
        case 195:
        
        case 196:
        
        case 197:
        
        case 198:
        
        case 199:
        
        case 200:
        
        case 201:
        
        case 202:
        
        case 203:
        
        case 204:
        
        case 205:
        
        case 206:
        
        case 207:
        
        case 208:
        
        case 209:
        
        case 210:
        
        case 211:
        
        case 212:
        
        case 213:
        
        case 214:
        
        case 215:
        
        case 216:
        
        case 217:
        
        case 218:
        
        case 219:
        
        case 220:
        
        case 221:
        
        case 222:
        
        case 223:
        
        case 224:
        
        case 225:
        
        case 226:
        
        case 227:
        
        case 228:
        
        case 229:
        
        case 230:
        
        case 231:
        
        case 232:
        
        case 233:
        
        case 234:
        
        case 235:
        
        case 236:
        
        case 237:
        
        case 238:
        
        case 239:
        
        case 240:
        
        case 241:
        
        case 242:
        
        case 243:
        
        case 244:
        
        case 245:
        
        case 246:
        
        case 247:
        
        case 248:
        
        case 249:
        
        case 250:
        
        case 251:
        
        case 252:
        
        case 253:
        
        case 254:
        
        default:
          break;
      } 
      byte b1 = 63;
      int j = (paramInt2 & 0xFF) - b1;
      if (j < 0)
        j += 256; 
      int k = ((paramInt2 & 0xFFFF) >>> 8) - b1;
      if (k < 0)
        k += 256; 
      for (byte b2 = 0; b2 < arrayOfChar.length; b2++) {
        int m = b2 % 2;
        if (m == 0) {
          arrayOfChar[b2] = (char)(arrayOfChar[b2] ^ j);
          j = ((j >>> 3 | j << 5) ^ arrayOfChar[b2]) & 0xFF;
        } else {
          arrayOfChar[b2] = (char)(arrayOfChar[b2] ^ k);
          k = ((k >>> 3 | k << 5) ^ arrayOfChar[b2]) & 0xFF;
        } 
      } 
      b[i] = (new String(arrayOfChar)).intern();
    } 
    return b[i];
  }
}


/* Location:              C:\Program Files\BurpSuitePro\burpsuite_pro.jar!\burp\Zr_y.class
 * Java compiler version: 21 (65.0)
 * JD-Core Version:       1.1.3
 */