package burp;

import java.math.BigInteger;

class Zr_z extends ClassLoader {
  static Object ZT;
  
  static String ZE;
  
  private static final String[] a;
  
  private static final String[] b;
  
  static void ZA(Object paramObject) {
    Zebu.ZI = a(-29440, 5735);
    Zebu.Zu = new BigInteger(a(-29437, -22271));
    boolean bool = Zt2e.ZN();
    try {
      try {
        if (Zmpv.Zb.charAt(Math.abs(((BigInteger)Zb8x.Zz).intValue() % 32)) > Zgz2.ZI.charAt(Math.abs(((BigInteger)Zrc0.Zz).intValue() % 32))) {
          try {
            Zkor.ZU(Class.forName(a(-29438, -29988)));
            if (!bool)
              Zl_k.Zj(Class.forName(a(-29429, -32700))); 
          } catch (Throwable throwable) {
            throw a(null);
          } 
          return;
        } 
      } catch (Throwable throwable) {
        throw a(null);
      } 
      Zl_k.Zj(Class.forName(a(-29429, -32700)));
    } catch (Throwable throwable) {}
  }
  
  static boolean ZR(Object[] paramArrayOfObject, Object paramObject) throws Throwable {
    // Byte code:
    //   0: invokestatic ZN : ()Z
    //   3: istore_2
    //   4: new java/lang/StringBuilder
    //   7: dup
    //   8: invokespecial <init> : ()V
    //   11: astore_3
    //   12: iconst_0
    //   13: istore #4
    //   15: iload #4
    //   17: bipush #32
    //   19: if_icmpge -> 1355
    //   22: iload #4
    //   24: tableswitch default -> 1348, 0 -> 168, 1 -> 205, 2 -> 242, 3 -> 279, 4 -> 316, 5 -> 353, 6 -> 390, 7 -> 427, 8 -> 464, 9 -> 501, 10 -> 538, 11 -> 575, 12 -> 612, 13 -> 649, 14 -> 686, 15 -> 723, 16 -> 760, 17 -> 797, 18 -> 834, 19 -> 871, 20 -> 908, 21 -> 945, 22 -> 982, 23 -> 1019, 24 -> 1056, 25 -> 1093, 26 -> 1130, 27 -> 1167, 28 -> 1204, 29 -> 1241, 30 -> 1278, 31 -> 1315
    //   168: aload_3
    //   169: getstatic burp/Zgqp.ZA : Ljava/lang/String;
    //   172: getstatic burp/Zr_w.ZK : Ljava/lang/Object;
    //   175: checkcast java/math/BigInteger
    //   178: invokevirtual intValue : ()I
    //   181: bipush #32
    //   183: irem
    //   184: invokestatic abs : (I)I
    //   187: invokevirtual charAt : (I)C
    //   190: invokevirtual append : (C)Ljava/lang/StringBuilder;
    //   193: pop
    //   194: iload_2
    //   195: ifne -> 1348
    //   198: goto -> 205
    //   201: invokestatic a : (Ljava/lang/Throwable;)Ljava/lang/Throwable;
    //   204: athrow
    //   205: aload_3
    //   206: getstatic burp/Zrug.Zq : Ljava/lang/String;
    //   209: getstatic burp/Zmwx.Zk : Ljava/lang/Object;
    //   212: checkcast java/math/BigInteger
    //   215: invokevirtual intValue : ()I
    //   218: bipush #32
    //   220: irem
    //   221: invokestatic abs : (I)I
    //   224: invokevirtual charAt : (I)C
    //   227: invokevirtual append : (C)Ljava/lang/StringBuilder;
    //   230: pop
    //   231: iload_2
    //   232: ifne -> 1348
    //   235: goto -> 242
    //   238: invokestatic a : (Ljava/lang/Throwable;)Ljava/lang/Throwable;
    //   241: athrow
    //   242: aload_3
    //   243: getstatic burp/Zrdo.Zj : Ljava/lang/String;
    //   246: getstatic burp/Zgl4.Zb : Ljava/lang/Object;
    //   249: checkcast java/math/BigInteger
    //   252: invokevirtual intValue : ()I
    //   255: bipush #32
    //   257: irem
    //   258: invokestatic abs : (I)I
    //   261: invokevirtual charAt : (I)C
    //   264: invokevirtual append : (C)Ljava/lang/StringBuilder;
    //   267: pop
    //   268: iload_2
    //   269: ifne -> 1348
    //   272: goto -> 279
    //   275: invokestatic a : (Ljava/lang/Throwable;)Ljava/lang/Throwable;
    //   278: athrow
    //   279: aload_3
    //   280: getstatic burp/Ze6t.ZR : Ljava/lang/String;
    //   283: getstatic burp/Zgfq.Za : Ljava/lang/Object;
    //   286: checkcast java/math/BigInteger
    //   289: invokevirtual intValue : ()I
    //   292: bipush #32
    //   294: irem
    //   295: invokestatic abs : (I)I
    //   298: invokevirtual charAt : (I)C
    //   301: invokevirtual append : (C)Ljava/lang/StringBuilder;
    //   304: pop
    //   305: iload_2
    //   306: ifne -> 1348
    //   309: goto -> 316
    //   312: invokestatic a : (Ljava/lang/Throwable;)Ljava/lang/Throwable;
    //   315: athrow
    //   316: aload_3
    //   317: getstatic burp/Zg_i.ZW : Ljava/lang/String;
    //   320: getstatic burp/Zvof.Zl : Ljava/lang/Object;
    //   323: checkcast java/math/BigInteger
    //   326: invokevirtual intValue : ()I
    //   329: bipush #32
    //   331: irem
    //   332: invokestatic abs : (I)I
    //   335: invokevirtual charAt : (I)C
    //   338: invokevirtual append : (C)Ljava/lang/StringBuilder;
    //   341: pop
    //   342: iload_2
    //   343: ifne -> 1348
    //   346: goto -> 353
    //   349: invokestatic a : (Ljava/lang/Throwable;)Ljava/lang/Throwable;
    //   352: athrow
    //   353: aload_3
    //   354: getstatic burp/Zzx8.Z_ : Ljava/lang/String;
    //   357: getstatic burp/Zz80.ZR : Ljava/lang/Object;
    //   360: checkcast java/math/BigInteger
    //   363: invokevirtual intValue : ()I
    //   366: bipush #32
    //   368: irem
    //   369: invokestatic abs : (I)I
    //   372: invokevirtual charAt : (I)C
    //   375: invokevirtual append : (C)Ljava/lang/StringBuilder;
    //   378: pop
    //   379: iload_2
    //   380: ifne -> 1348
    //   383: goto -> 390
    //   386: invokestatic a : (Ljava/lang/Throwable;)Ljava/lang/Throwable;
    //   389: athrow
    //   390: aload_3
    //   391: getstatic burp/Zsji.Zr : Ljava/lang/String;
    //   394: getstatic burp/Zkw.ZY : Ljava/lang/Object;
    //   397: checkcast java/math/BigInteger
    //   400: invokevirtual intValue : ()I
    //   403: bipush #32
    //   405: irem
    //   406: invokestatic abs : (I)I
    //   409: invokevirtual charAt : (I)C
    //   412: invokevirtual append : (C)Ljava/lang/StringBuilder;
    //   415: pop
    //   416: iload_2
    //   417: ifne -> 1348
    //   420: goto -> 427
    //   423: invokestatic a : (Ljava/lang/Throwable;)Ljava/lang/Throwable;
    //   426: athrow
    //   427: aload_3
    //   428: getstatic burp/Ztjh.ZZ : Ljava/lang/String;
    //   431: getstatic burp/Zssb.ZW : Ljava/lang/Object;
    //   434: checkcast java/math/BigInteger
    //   437: invokevirtual intValue : ()I
    //   440: bipush #32
    //   442: irem
    //   443: invokestatic abs : (I)I
    //   446: invokevirtual charAt : (I)C
    //   449: invokevirtual append : (C)Ljava/lang/StringBuilder;
    //   452: pop
    //   453: iload_2
    //   454: ifne -> 1348
    //   457: goto -> 464
    //   460: invokestatic a : (Ljava/lang/Throwable;)Ljava/lang/Throwable;
    //   463: athrow
    //   464: aload_3
    //   465: getstatic burp/Zg_y.ZF : Ljava/lang/String;
    //   468: getstatic burp/Zrqd.Zi : Ljava/lang/Object;
    //   471: checkcast java/math/BigInteger
    //   474: invokevirtual intValue : ()I
    //   477: bipush #32
    //   479: irem
    //   480: invokestatic abs : (I)I
    //   483: invokevirtual charAt : (I)C
    //   486: invokevirtual append : (C)Ljava/lang/StringBuilder;
    //   489: pop
    //   490: iload_2
    //   491: ifne -> 1348
    //   494: goto -> 501
    //   497: invokestatic a : (Ljava/lang/Throwable;)Ljava/lang/Throwable;
    //   500: athrow
    //   501: aload_3
    //   502: getstatic burp/Zge1.Zx : Ljava/lang/String;
    //   505: getstatic burp/Zxz_.Zv : Ljava/lang/Object;
    //   508: checkcast java/math/BigInteger
    //   511: invokevirtual intValue : ()I
    //   514: bipush #32
    //   516: irem
    //   517: invokestatic abs : (I)I
    //   520: invokevirtual charAt : (I)C
    //   523: invokevirtual append : (C)Ljava/lang/StringBuilder;
    //   526: pop
    //   527: iload_2
    //   528: ifne -> 1348
    //   531: goto -> 538
    //   534: invokestatic a : (Ljava/lang/Throwable;)Ljava/lang/Throwable;
    //   537: athrow
    //   538: aload_3
    //   539: getstatic burp/Zgfq.Zn : Ljava/lang/String;
    //   542: getstatic burp/Zgh3.ZZ : Ljava/lang/Object;
    //   545: checkcast java/math/BigInteger
    //   548: invokevirtual intValue : ()I
    //   551: bipush #32
    //   553: irem
    //   554: invokestatic abs : (I)I
    //   557: invokevirtual charAt : (I)C
    //   560: invokevirtual append : (C)Ljava/lang/StringBuilder;
    //   563: pop
    //   564: iload_2
    //   565: ifne -> 1348
    //   568: goto -> 575
    //   571: invokestatic a : (Ljava/lang/Throwable;)Ljava/lang/Throwable;
    //   574: athrow
    //   575: aload_3
    //   576: getstatic burp/Zbu6.ZQ : Ljava/lang/String;
    //   579: getstatic burp/Zbf9.ZC : Ljava/lang/Object;
    //   582: checkcast java/math/BigInteger
    //   585: invokevirtual intValue : ()I
    //   588: bipush #32
    //   590: irem
    //   591: invokestatic abs : (I)I
    //   594: invokevirtual charAt : (I)C
    //   597: invokevirtual append : (C)Ljava/lang/StringBuilder;
    //   600: pop
    //   601: iload_2
    //   602: ifne -> 1348
    //   605: goto -> 612
    //   608: invokestatic a : (Ljava/lang/Throwable;)Ljava/lang/Throwable;
    //   611: athrow
    //   612: aload_3
    //   613: getstatic burp/Zgmo.Zr : Ljava/lang/String;
    //   616: getstatic burp/Zb1.Zf : Ljava/lang/Object;
    //   619: checkcast java/math/BigInteger
    //   622: invokevirtual intValue : ()I
    //   625: bipush #32
    //   627: irem
    //   628: invokestatic abs : (I)I
    //   631: invokevirtual charAt : (I)C
    //   634: invokevirtual append : (C)Ljava/lang/StringBuilder;
    //   637: pop
    //   638: iload_2
    //   639: ifne -> 1348
    //   642: goto -> 649
    //   645: invokestatic a : (Ljava/lang/Throwable;)Ljava/lang/Throwable;
    //   648: athrow
    //   649: aload_3
    //   650: getstatic burp/Zmwx.ZB : Ljava/lang/String;
    //   653: getstatic burp/Zmjw.ZD : Ljava/lang/Object;
    //   656: checkcast java/math/BigInteger
    //   659: invokevirtual intValue : ()I
    //   662: bipush #32
    //   664: irem
    //   665: invokestatic abs : (I)I
    //   668: invokevirtual charAt : (I)C
    //   671: invokevirtual append : (C)Ljava/lang/StringBuilder;
    //   674: pop
    //   675: iload_2
    //   676: ifne -> 1348
    //   679: goto -> 686
    //   682: invokestatic a : (Ljava/lang/Throwable;)Ljava/lang/Throwable;
    //   685: athrow
    //   686: aload_3
    //   687: getstatic burp/Zbf9.Zp : Ljava/lang/String;
    //   690: getstatic burp/Zrug.Zp : Ljava/lang/Object;
    //   693: checkcast java/math/BigInteger
    //   696: invokevirtual intValue : ()I
    //   699: bipush #32
    //   701: irem
    //   702: invokestatic abs : (I)I
    //   705: invokevirtual charAt : (I)C
    //   708: invokevirtual append : (C)Ljava/lang/StringBuilder;
    //   711: pop
    //   712: iload_2
    //   713: ifne -> 1348
    //   716: goto -> 723
    //   719: invokestatic a : (Ljava/lang/Throwable;)Ljava/lang/Throwable;
    //   722: athrow
    //   723: aload_3
    //   724: getstatic burp/Zssb.ZY : Ljava/lang/String;
    //   727: getstatic burp/Zr64.ZN : Ljava/lang/Object;
    //   730: checkcast java/math/BigInteger
    //   733: invokevirtual intValue : ()I
    //   736: bipush #32
    //   738: irem
    //   739: invokestatic abs : (I)I
    //   742: invokevirtual charAt : (I)C
    //   745: invokevirtual append : (C)Ljava/lang/StringBuilder;
    //   748: pop
    //   749: iload_2
    //   750: ifne -> 1348
    //   753: goto -> 760
    //   756: invokestatic a : (Ljava/lang/Throwable;)Ljava/lang/Throwable;
    //   759: athrow
    //   760: aload_3
    //   761: getstatic burp/Zbu6.ZQ : Ljava/lang/String;
    //   764: getstatic burp/Zgqp.Zf : Ljava/lang/Object;
    //   767: checkcast java/math/BigInteger
    //   770: invokevirtual intValue : ()I
    //   773: bipush #32
    //   775: irem
    //   776: invokestatic abs : (I)I
    //   779: invokevirtual charAt : (I)C
    //   782: invokevirtual append : (C)Ljava/lang/StringBuilder;
    //   785: pop
    //   786: iload_2
    //   787: ifne -> 1348
    //   790: goto -> 797
    //   793: invokestatic a : (Ljava/lang/Throwable;)Ljava/lang/Throwable;
    //   796: athrow
    //   797: aload_3
    //   798: getstatic burp/Zlhk.Zb : Ljava/lang/String;
    //   801: getstatic burp/Zluk.Zz : Ljava/lang/Object;
    //   804: checkcast java/math/BigInteger
    //   807: invokevirtual intValue : ()I
    //   810: bipush #32
    //   812: irem
    //   813: invokestatic abs : (I)I
    //   816: invokevirtual charAt : (I)C
    //   819: invokevirtual append : (C)Ljava/lang/StringBuilder;
    //   822: pop
    //   823: iload_2
    //   824: ifne -> 1348
    //   827: goto -> 834
    //   830: invokestatic a : (Ljava/lang/Throwable;)Ljava/lang/Throwable;
    //   833: athrow
    //   834: aload_3
    //   835: getstatic burp/Zeyd.Zr : Ljava/lang/String;
    //   838: getstatic burp/Zgl4.Zb : Ljava/lang/Object;
    //   841: checkcast java/math/BigInteger
    //   844: invokevirtual intValue : ()I
    //   847: bipush #32
    //   849: irem
    //   850: invokestatic abs : (I)I
    //   853: invokevirtual charAt : (I)C
    //   856: invokevirtual append : (C)Ljava/lang/StringBuilder;
    //   859: pop
    //   860: iload_2
    //   861: ifne -> 1348
    //   864: goto -> 871
    //   867: invokestatic a : (Ljava/lang/Throwable;)Ljava/lang/Throwable;
    //   870: athrow
    //   871: aload_3
    //   872: getstatic burp/Zmou.ZP : Ljava/lang/String;
    //   875: getstatic burp/Zltp.ZT : Ljava/lang/Object;
    //   878: checkcast java/math/BigInteger
    //   881: invokevirtual intValue : ()I
    //   884: bipush #32
    //   886: irem
    //   887: invokestatic abs : (I)I
    //   890: invokevirtual charAt : (I)C
    //   893: invokevirtual append : (C)Ljava/lang/StringBuilder;
    //   896: pop
    //   897: iload_2
    //   898: ifne -> 1348
    //   901: goto -> 908
    //   904: invokestatic a : (Ljava/lang/Throwable;)Ljava/lang/Throwable;
    //   907: athrow
    //   908: aload_3
    //   909: getstatic burp/Zss8.ZD : Ljava/lang/String;
    //   912: getstatic burp/Zb9d.Ze : Ljava/lang/Object;
    //   915: checkcast java/math/BigInteger
    //   918: invokevirtual intValue : ()I
    //   921: bipush #32
    //   923: irem
    //   924: invokestatic abs : (I)I
    //   927: invokevirtual charAt : (I)C
    //   930: invokevirtual append : (C)Ljava/lang/StringBuilder;
    //   933: pop
    //   934: iload_2
    //   935: ifne -> 1348
    //   938: goto -> 945
    //   941: invokestatic a : (Ljava/lang/Throwable;)Ljava/lang/Throwable;
    //   944: athrow
    //   945: aload_3
    //   946: getstatic burp/Zlqq.Za : Ljava/lang/String;
    //   949: getstatic burp/Zgfq.Za : Ljava/lang/Object;
    //   952: checkcast java/math/BigInteger
    //   955: invokevirtual intValue : ()I
    //   958: bipush #32
    //   960: irem
    //   961: invokestatic abs : (I)I
    //   964: invokevirtual charAt : (I)C
    //   967: invokevirtual append : (C)Ljava/lang/StringBuilder;
    //   970: pop
    //   971: iload_2
    //   972: ifne -> 1348
    //   975: goto -> 982
    //   978: invokestatic a : (Ljava/lang/Throwable;)Ljava/lang/Throwable;
    //   981: athrow
    //   982: aload_3
    //   983: getstatic burp/Zg_y.ZF : Ljava/lang/String;
    //   986: getstatic burp/Zm54.ZS : Ljava/lang/Object;
    //   989: checkcast java/math/BigInteger
    //   992: invokevirtual intValue : ()I
    //   995: bipush #32
    //   997: irem
    //   998: invokestatic abs : (I)I
    //   1001: invokevirtual charAt : (I)C
    //   1004: invokevirtual append : (C)Ljava/lang/StringBuilder;
    //   1007: pop
    //   1008: iload_2
    //   1009: ifne -> 1348
    //   1012: goto -> 1019
    //   1015: invokestatic a : (Ljava/lang/Throwable;)Ljava/lang/Throwable;
    //   1018: athrow
    //   1019: aload_3
    //   1020: getstatic burp/Zl55.Zp : Ljava/lang/String;
    //   1023: getstatic burp/Zg3v.Zk : Ljava/lang/Object;
    //   1026: checkcast java/math/BigInteger
    //   1029: invokevirtual intValue : ()I
    //   1032: bipush #32
    //   1034: irem
    //   1035: invokestatic abs : (I)I
    //   1038: invokevirtual charAt : (I)C
    //   1041: invokevirtual append : (C)Ljava/lang/StringBuilder;
    //   1044: pop
    //   1045: iload_2
    //   1046: ifne -> 1348
    //   1049: goto -> 1056
    //   1052: invokestatic a : (Ljava/lang/Throwable;)Ljava/lang/Throwable;
    //   1055: athrow
    //   1056: aload_3
    //   1057: getstatic burp/Zr3j.Zj : Ljava/lang/String;
    //   1060: getstatic burp/Zx0t.Zt : Ljava/lang/Object;
    //   1063: checkcast java/math/BigInteger
    //   1066: invokevirtual intValue : ()I
    //   1069: bipush #32
    //   1071: irem
    //   1072: invokestatic abs : (I)I
    //   1075: invokevirtual charAt : (I)C
    //   1078: invokevirtual append : (C)Ljava/lang/StringBuilder;
    //   1081: pop
    //   1082: iload_2
    //   1083: ifne -> 1348
    //   1086: goto -> 1093
    //   1089: invokestatic a : (Ljava/lang/Throwable;)Ljava/lang/Throwable;
    //   1092: athrow
    //   1093: aload_3
    //   1094: getstatic burp/Zkby.Zf : Ljava/lang/String;
    //   1097: getstatic burp/Zxti.ZJ : Ljava/lang/Object;
    //   1100: checkcast java/math/BigInteger
    //   1103: invokevirtual intValue : ()I
    //   1106: bipush #32
    //   1108: irem
    //   1109: invokestatic abs : (I)I
    //   1112: invokevirtual charAt : (I)C
    //   1115: invokevirtual append : (C)Ljava/lang/StringBuilder;
    //   1118: pop
    //   1119: iload_2
    //   1120: ifne -> 1348
    //   1123: goto -> 1130
    //   1126: invokestatic a : (Ljava/lang/Throwable;)Ljava/lang/Throwable;
    //   1129: athrow
    //   1130: aload_3
    //   1131: getstatic burp/Zb9d.Zh : Ljava/lang/String;
    //   1134: getstatic burp/Zg3v.Zk : Ljava/lang/Object;
    //   1137: checkcast java/math/BigInteger
    //   1140: invokevirtual intValue : ()I
    //   1143: bipush #32
    //   1145: irem
    //   1146: invokestatic abs : (I)I
    //   1149: invokevirtual charAt : (I)C
    //   1152: invokevirtual append : (C)Ljava/lang/StringBuilder;
    //   1155: pop
    //   1156: iload_2
    //   1157: ifne -> 1348
    //   1160: goto -> 1167
    //   1163: invokestatic a : (Ljava/lang/Throwable;)Ljava/lang/Throwable;
    //   1166: athrow
    //   1167: aload_3
    //   1168: getstatic burp/Zlfg.Zb : Ljava/lang/String;
    //   1171: getstatic burp/Zrug.Zp : Ljava/lang/Object;
    //   1174: checkcast java/math/BigInteger
    //   1177: invokevirtual intValue : ()I
    //   1180: bipush #32
    //   1182: irem
    //   1183: invokestatic abs : (I)I
    //   1186: invokevirtual charAt : (I)C
    //   1189: invokevirtual append : (C)Ljava/lang/StringBuilder;
    //   1192: pop
    //   1193: iload_2
    //   1194: ifne -> 1348
    //   1197: goto -> 1204
    //   1200: invokestatic a : (Ljava/lang/Throwable;)Ljava/lang/Throwable;
    //   1203: athrow
    //   1204: aload_3
    //   1205: getstatic burp/Zlqm.ZQ : Ljava/lang/String;
    //   1208: getstatic burp/Zvof.Zl : Ljava/lang/Object;
    //   1211: checkcast java/math/BigInteger
    //   1214: invokevirtual intValue : ()I
    //   1217: bipush #32
    //   1219: irem
    //   1220: invokestatic abs : (I)I
    //   1223: invokevirtual charAt : (I)C
    //   1226: invokevirtual append : (C)Ljava/lang/StringBuilder;
    //   1229: pop
    //   1230: iload_2
    //   1231: ifne -> 1348
    //   1234: goto -> 1241
    //   1237: invokestatic a : (Ljava/lang/Throwable;)Ljava/lang/Throwable;
    //   1240: athrow
    //   1241: aload_3
    //   1242: getstatic burp/Zg_i.ZW : Ljava/lang/String;
    //   1245: getstatic burp/Zebu.Zu : Ljava/lang/Object;
    //   1248: checkcast java/math/BigInteger
    //   1251: invokevirtual intValue : ()I
    //   1254: bipush #32
    //   1256: irem
    //   1257: invokestatic abs : (I)I
    //   1260: invokevirtual charAt : (I)C
    //   1263: invokevirtual append : (C)Ljava/lang/StringBuilder;
    //   1266: pop
    //   1267: iload_2
    //   1268: ifne -> 1348
    //   1271: goto -> 1278
    //   1274: invokestatic a : (Ljava/lang/Throwable;)Ljava/lang/Throwable;
    //   1277: athrow
    //   1278: aload_3
    //   1279: getstatic burp/Zluk.ZW : Ljava/lang/String;
    //   1282: getstatic burp/Zstq.Zf : Ljava/lang/Object;
    //   1285: checkcast java/math/BigInteger
    //   1288: invokevirtual intValue : ()I
    //   1291: bipush #32
    //   1293: irem
    //   1294: invokestatic abs : (I)I
    //   1297: invokevirtual charAt : (I)C
    //   1300: invokevirtual append : (C)Ljava/lang/StringBuilder;
    //   1303: pop
    //   1304: iload_2
    //   1305: ifne -> 1348
    //   1308: goto -> 1315
    //   1311: invokestatic a : (Ljava/lang/Throwable;)Ljava/lang/Throwable;
    //   1314: athrow
    //   1315: aload_3
    //   1316: getstatic burp/Zzi3.ZS : Ljava/lang/String;
    //   1319: getstatic burp/Zmcb.ZR : Ljava/lang/Object;
    //   1322: checkcast java/math/BigInteger
    //   1325: invokevirtual intValue : ()I
    //   1328: bipush #32
    //   1330: irem
    //   1331: invokestatic abs : (I)I
    //   1334: invokevirtual charAt : (I)C
    //   1337: invokevirtual append : (C)Ljava/lang/StringBuilder;
    //   1340: pop
    //   1341: goto -> 1348
    //   1344: invokestatic a : (Ljava/lang/Throwable;)Ljava/lang/Throwable;
    //   1347: athrow
    //   1348: iinc #4, 1
    //   1351: iload_2
    //   1352: ifne -> 15
    //   1355: aload_3
    //   1356: invokevirtual toString : ()Ljava/lang/String;
    //   1359: putstatic burp/Ztjh.ZZ : Ljava/lang/String;
    //   1362: getstatic burp/Zmcb.ZR : Ljava/lang/Object;
    //   1365: checkcast java/math/BigInteger
    //   1368: getstatic burp/Zbf9.ZC : Ljava/lang/Object;
    //   1371: checkcast java/math/BigInteger
    //   1374: invokevirtual add : (Ljava/math/BigInteger;)Ljava/math/BigInteger;
    //   1377: putstatic burp/Zstq.Zf : Ljava/lang/Object;
    //   1380: getstatic burp/Zg_y.ZR : Ljava/lang/Object;
    //   1383: checkcast java/math/BigInteger
    //   1386: invokevirtual toByteArray : ()[B
    //   1389: astore #4
    //   1391: bipush #64
    //   1393: newarray byte
    //   1395: dup
    //   1396: iconst_0
    //   1397: bipush #-128
    //   1399: bastore
    //   1400: dup
    //   1401: iconst_1
    //   1402: iconst_0
    //   1403: bastore
    //   1404: dup
    //   1405: iconst_2
    //   1406: iconst_0
    //   1407: bastore
    //   1408: dup
    //   1409: iconst_3
    //   1410: iconst_0
    //   1411: bastore
    //   1412: dup
    //   1413: iconst_4
    //   1414: iconst_0
    //   1415: bastore
    //   1416: dup
    //   1417: iconst_5
    //   1418: iconst_0
    //   1419: bastore
    //   1420: dup
    //   1421: bipush #6
    //   1423: iconst_0
    //   1424: bastore
    //   1425: dup
    //   1426: bipush #7
    //   1428: iconst_0
    //   1429: bastore
    //   1430: dup
    //   1431: bipush #8
    //   1433: iconst_0
    //   1434: bastore
    //   1435: dup
    //   1436: bipush #9
    //   1438: iconst_0
    //   1439: bastore
    //   1440: dup
    //   1441: bipush #10
    //   1443: iconst_0
    //   1444: bastore
    //   1445: dup
    //   1446: bipush #11
    //   1448: iconst_0
    //   1449: bastore
    //   1450: dup
    //   1451: bipush #12
    //   1453: iconst_0
    //   1454: bastore
    //   1455: dup
    //   1456: bipush #13
    //   1458: iconst_0
    //   1459: bastore
    //   1460: dup
    //   1461: bipush #14
    //   1463: iconst_0
    //   1464: bastore
    //   1465: dup
    //   1466: bipush #15
    //   1468: iconst_0
    //   1469: bastore
    //   1470: dup
    //   1471: bipush #16
    //   1473: iconst_0
    //   1474: bastore
    //   1475: dup
    //   1476: bipush #17
    //   1478: iconst_0
    //   1479: bastore
    //   1480: dup
    //   1481: bipush #18
    //   1483: iconst_0
    //   1484: bastore
    //   1485: dup
    //   1486: bipush #19
    //   1488: iconst_0
    //   1489: bastore
    //   1490: dup
    //   1491: bipush #20
    //   1493: iconst_0
    //   1494: bastore
    //   1495: dup
    //   1496: bipush #21
    //   1498: iconst_0
    //   1499: bastore
    //   1500: dup
    //   1501: bipush #22
    //   1503: iconst_0
    //   1504: bastore
    //   1505: dup
    //   1506: bipush #23
    //   1508: iconst_0
    //   1509: bastore
    //   1510: dup
    //   1511: bipush #24
    //   1513: iconst_0
    //   1514: bastore
    //   1515: dup
    //   1516: bipush #25
    //   1518: iconst_0
    //   1519: bastore
    //   1520: dup
    //   1521: bipush #26
    //   1523: iconst_0
    //   1524: bastore
    //   1525: dup
    //   1526: bipush #27
    //   1528: iconst_0
    //   1529: bastore
    //   1530: dup
    //   1531: bipush #28
    //   1533: iconst_0
    //   1534: bastore
    //   1535: dup
    //   1536: bipush #29
    //   1538: iconst_0
    //   1539: bastore
    //   1540: dup
    //   1541: bipush #30
    //   1543: iconst_0
    //   1544: bastore
    //   1545: dup
    //   1546: bipush #31
    //   1548: iconst_0
    //   1549: bastore
    //   1550: dup
    //   1551: bipush #32
    //   1553: iconst_0
    //   1554: bastore
    //   1555: dup
    //   1556: bipush #33
    //   1558: iconst_0
    //   1559: bastore
    //   1560: dup
    //   1561: bipush #34
    //   1563: iconst_0
    //   1564: bastore
    //   1565: dup
    //   1566: bipush #35
    //   1568: iconst_0
    //   1569: bastore
    //   1570: dup
    //   1571: bipush #36
    //   1573: iconst_0
    //   1574: bastore
    //   1575: dup
    //   1576: bipush #37
    //   1578: iconst_0
    //   1579: bastore
    //   1580: dup
    //   1581: bipush #38
    //   1583: iconst_0
    //   1584: bastore
    //   1585: dup
    //   1586: bipush #39
    //   1588: iconst_0
    //   1589: bastore
    //   1590: dup
    //   1591: bipush #40
    //   1593: iconst_0
    //   1594: bastore
    //   1595: dup
    //   1596: bipush #41
    //   1598: iconst_0
    //   1599: bastore
    //   1600: dup
    //   1601: bipush #42
    //   1603: iconst_0
    //   1604: bastore
    //   1605: dup
    //   1606: bipush #43
    //   1608: iconst_0
    //   1609: bastore
    //   1610: dup
    //   1611: bipush #44
    //   1613: iconst_0
    //   1614: bastore
    //   1615: dup
    //   1616: bipush #45
    //   1618: iconst_0
    //   1619: bastore
    //   1620: dup
    //   1621: bipush #46
    //   1623: iconst_0
    //   1624: bastore
    //   1625: dup
    //   1626: bipush #47
    //   1628: iconst_0
    //   1629: bastore
    //   1630: dup
    //   1631: bipush #48
    //   1633: iconst_0
    //   1634: bastore
    //   1635: dup
    //   1636: bipush #49
    //   1638: iconst_0
    //   1639: bastore
    //   1640: dup
    //   1641: bipush #50
    //   1643: iconst_0
    //   1644: bastore
    //   1645: dup
    //   1646: bipush #51
    //   1648: iconst_0
    //   1649: bastore
    //   1650: dup
    //   1651: bipush #52
    //   1653: iconst_0
    //   1654: bastore
    //   1655: dup
    //   1656: bipush #53
    //   1658: iconst_0
    //   1659: bastore
    //   1660: dup
    //   1661: bipush #54
    //   1663: iconst_0
    //   1664: bastore
    //   1665: dup
    //   1666: bipush #55
    //   1668: iconst_0
    //   1669: bastore
    //   1670: dup
    //   1671: bipush #56
    //   1673: iconst_0
    //   1674: bastore
    //   1675: dup
    //   1676: bipush #57
    //   1678: iconst_0
    //   1679: bastore
    //   1680: dup
    //   1681: bipush #58
    //   1683: iconst_0
    //   1684: bastore
    //   1685: dup
    //   1686: bipush #59
    //   1688: iconst_0
    //   1689: bastore
    //   1690: dup
    //   1691: bipush #60
    //   1693: iconst_0
    //   1694: bastore
    //   1695: dup
    //   1696: bipush #61
    //   1698: iconst_0
    //   1699: bastore
    //   1700: dup
    //   1701: bipush #62
    //   1703: iconst_0
    //   1704: bastore
    //   1705: dup
    //   1706: bipush #63
    //   1708: iconst_0
    //   1709: bastore
    //   1710: astore #6
    //   1712: bipush #64
    //   1714: newarray int
    //   1716: dup
    //   1717: iconst_0
    //   1718: ldc 1116352408
    //   1720: iastore
    //   1721: dup
    //   1722: iconst_1
    //   1723: ldc 1899447441
    //   1725: iastore
    //   1726: dup
    //   1727: iconst_2
    //   1728: ldc -1245643825
    //   1730: iastore
    //   1731: dup
    //   1732: iconst_3
    //   1733: ldc -373957723
    //   1735: iastore
    //   1736: dup
    //   1737: iconst_4
    //   1738: ldc 961987163
    //   1740: iastore
    //   1741: dup
    //   1742: iconst_5
    //   1743: ldc 1508970993
    //   1745: iastore
    //   1746: dup
    //   1747: bipush #6
    //   1749: ldc -1841331548
    //   1751: iastore
    //   1752: dup
    //   1753: bipush #7
    //   1755: ldc -1424204075
    //   1757: iastore
    //   1758: dup
    //   1759: bipush #8
    //   1761: ldc -670586216
    //   1763: iastore
    //   1764: dup
    //   1765: bipush #9
    //   1767: ldc 310598401
    //   1769: iastore
    //   1770: dup
    //   1771: bipush #10
    //   1773: ldc 607225278
    //   1775: iastore
    //   1776: dup
    //   1777: bipush #11
    //   1779: ldc 1426881987
    //   1781: iastore
    //   1782: dup
    //   1783: bipush #12
    //   1785: ldc 1925078388
    //   1787: iastore
    //   1788: dup
    //   1789: bipush #13
    //   1791: ldc -2132889090
    //   1793: iastore
    //   1794: dup
    //   1795: bipush #14
    //   1797: ldc -1680079193
    //   1799: iastore
    //   1800: dup
    //   1801: bipush #15
    //   1803: ldc -1046744716
    //   1805: iastore
    //   1806: dup
    //   1807: bipush #16
    //   1809: ldc -459576895
    //   1811: iastore
    //   1812: dup
    //   1813: bipush #17
    //   1815: ldc -272742522
    //   1817: iastore
    //   1818: dup
    //   1819: bipush #18
    //   1821: ldc 264347078
    //   1823: iastore
    //   1824: dup
    //   1825: bipush #19
    //   1827: ldc 604807628
    //   1829: iastore
    //   1830: dup
    //   1831: bipush #20
    //   1833: ldc 770255983
    //   1835: iastore
    //   1836: dup
    //   1837: bipush #21
    //   1839: ldc 1249150122
    //   1841: iastore
    //   1842: dup
    //   1843: bipush #22
    //   1845: ldc 1555081692
    //   1847: iastore
    //   1848: dup
    //   1849: bipush #23
    //   1851: ldc 1996064986
    //   1853: iastore
    //   1854: dup
    //   1855: bipush #24
    //   1857: ldc -1740746414
    //   1859: iastore
    //   1860: dup
    //   1861: bipush #25
    //   1863: ldc -1473132947
    //   1865: iastore
    //   1866: dup
    //   1867: bipush #26
    //   1869: ldc -1341970488
    //   1871: iastore
    //   1872: dup
    //   1873: bipush #27
    //   1875: ldc -1084653625
    //   1877: iastore
    //   1878: dup
    //   1879: bipush #28
    //   1881: ldc -958395405
    //   1883: iastore
    //   1884: dup
    //   1885: bipush #29
    //   1887: ldc -710438585
    //   1889: iastore
    //   1890: dup
    //   1891: bipush #30
    //   1893: ldc 113926993
    //   1895: iastore
    //   1896: dup
    //   1897: bipush #31
    //   1899: ldc 338241895
    //   1901: iastore
    //   1902: dup
    //   1903: bipush #32
    //   1905: ldc 666307205
    //   1907: iastore
    //   1908: dup
    //   1909: bipush #33
    //   1911: ldc 773529912
    //   1913: iastore
    //   1914: dup
    //   1915: bipush #34
    //   1917: ldc 1294757372
    //   1919: iastore
    //   1920: dup
    //   1921: bipush #35
    //   1923: ldc 1396182291
    //   1925: iastore
    //   1926: dup
    //   1927: bipush #36
    //   1929: ldc 1695183700
    //   1931: iastore
    //   1932: dup
    //   1933: bipush #37
    //   1935: ldc 1986661051
    //   1937: iastore
    //   1938: dup
    //   1939: bipush #38
    //   1941: ldc -2117940946
    //   1943: iastore
    //   1944: dup
    //   1945: bipush #39
    //   1947: ldc -1838011259
    //   1949: iastore
    //   1950: dup
    //   1951: bipush #40
    //   1953: ldc -1564481375
    //   1955: iastore
    //   1956: dup
    //   1957: bipush #41
    //   1959: ldc -1474664885
    //   1961: iastore
    //   1962: dup
    //   1963: bipush #42
    //   1965: ldc -1035236496
    //   1967: iastore
    //   1968: dup
    //   1969: bipush #43
    //   1971: ldc -949202525
    //   1973: iastore
    //   1974: dup
    //   1975: bipush #44
    //   1977: ldc -778901479
    //   1979: iastore
    //   1980: dup
    //   1981: bipush #45
    //   1983: ldc -694614492
    //   1985: iastore
    //   1986: dup
    //   1987: bipush #46
    //   1989: ldc -200395387
    //   1991: iastore
    //   1992: dup
    //   1993: bipush #47
    //   1995: ldc 275423344
    //   1997: iastore
    //   1998: dup
    //   1999: bipush #48
    //   2001: ldc 430227734
    //   2003: iastore
    //   2004: dup
    //   2005: bipush #49
    //   2007: ldc 506948616
    //   2009: iastore
    //   2010: dup
    //   2011: bipush #50
    //   2013: ldc 659060556
    //   2015: iastore
    //   2016: dup
    //   2017: bipush #51
    //   2019: ldc 883997877
    //   2021: iastore
    //   2022: dup
    //   2023: bipush #52
    //   2025: ldc 958139571
    //   2027: iastore
    //   2028: dup
    //   2029: bipush #53
    //   2031: ldc 1322822218
    //   2033: iastore
    //   2034: dup
    //   2035: bipush #54
    //   2037: ldc 1537002063
    //   2039: iastore
    //   2040: dup
    //   2041: bipush #55
    //   2043: ldc 1747873779
    //   2045: iastore
    //   2046: dup
    //   2047: bipush #56
    //   2049: ldc 1955562222
    //   2051: iastore
    //   2052: dup
    //   2053: bipush #57
    //   2055: ldc 2024104815
    //   2057: iastore
    //   2058: dup
    //   2059: bipush #58
    //   2061: ldc -2067236844
    //   2063: iastore
    //   2064: dup
    //   2065: bipush #59
    //   2067: ldc -1933114872
    //   2069: iastore
    //   2070: dup
    //   2071: bipush #60
    //   2073: ldc -1866530822
    //   2075: iastore
    //   2076: dup
    //   2077: bipush #61
    //   2079: ldc -1538233109
    //   2081: iastore
    //   2082: dup
    //   2083: bipush #62
    //   2085: ldc -1090935817
    //   2087: iastore
    //   2088: dup
    //   2089: bipush #63
    //   2091: ldc -965641998
    //   2093: iastore
    //   2094: astore #7
    //   2096: iconst_2
    //   2097: newarray int
    //   2099: dup
    //   2100: iconst_0
    //   2101: iconst_0
    //   2102: iastore
    //   2103: dup
    //   2104: iconst_1
    //   2105: iconst_0
    //   2106: iastore
    //   2107: astore #8
    //   2109: bipush #8
    //   2111: newarray int
    //   2113: dup
    //   2114: iconst_0
    //   2115: ldc 1779033703
    //   2117: iastore
    //   2118: dup
    //   2119: iconst_1
    //   2120: ldc -1150833019
    //   2122: iastore
    //   2123: dup
    //   2124: iconst_2
    //   2125: ldc 1013904242
    //   2127: iastore
    //   2128: dup
    //   2129: iconst_3
    //   2130: ldc -1521486534
    //   2132: iastore
    //   2133: dup
    //   2134: iconst_4
    //   2135: ldc 1359893119
    //   2137: iastore
    //   2138: dup
    //   2139: iconst_5
    //   2140: ldc -1694144372
    //   2142: iastore
    //   2143: dup
    //   2144: bipush #6
    //   2146: ldc 528734635
    //   2148: iastore
    //   2149: dup
    //   2150: bipush #7
    //   2152: ldc 1541459225
    //   2154: iastore
    //   2155: astore #9
    //   2157: bipush #64
    //   2159: newarray byte
    //   2161: astore #10
    //   2163: bipush #64
    //   2165: newarray byte
    //   2167: astore #11
    //   2169: aload #4
    //   2171: arraylength
    //   2172: istore #12
    //   2174: aload #8
    //   2176: iconst_0
    //   2177: iaload
    //   2178: bipush #63
    //   2180: iand
    //   2181: istore #13
    //   2183: aload #8
    //   2185: iconst_0
    //   2186: dup2
    //   2187: iaload
    //   2188: iload #12
    //   2190: iadd
    //   2191: iastore
    //   2192: aload #8
    //   2194: iconst_0
    //   2195: dup2
    //   2196: iaload
    //   2197: iconst_m1
    //   2198: iand
    //   2199: iastore
    //   2200: aload #8
    //   2202: iconst_0
    //   2203: iaload
    //   2204: iload #12
    //   2206: if_icmpge -> 2224
    //   2209: aload #8
    //   2211: iconst_1
    //   2212: dup2
    //   2213: iaload
    //   2214: iconst_1
    //   2215: iadd
    //   2216: iastore
    //   2217: goto -> 2224
    //   2220: invokestatic a : (Ljava/lang/Throwable;)Ljava/lang/Throwable;
    //   2223: athrow
    //   2224: iconst_0
    //   2225: istore #14
    //   2227: iload #12
    //   2229: bipush #64
    //   2231: if_icmplt -> 2841
    //   2234: iconst_0
    //   2235: istore #15
    //   2237: iload #15
    //   2239: bipush #64
    //   2241: if_icmpge -> 2264
    //   2244: aload #11
    //   2246: iload #15
    //   2248: aload #4
    //   2250: iload #14
    //   2252: iload #15
    //   2254: iadd
    //   2255: baload
    //   2256: bastore
    //   2257: iinc #15, 1
    //   2260: iload_2
    //   2261: ifne -> 2237
    //   2264: bipush #64
    //   2266: newarray int
    //   2268: astore #15
    //   2270: bipush #8
    //   2272: newarray int
    //   2274: astore #16
    //   2276: iconst_0
    //   2277: istore #17
    //   2279: iload #17
    //   2281: bipush #8
    //   2283: if_icmpge -> 2303
    //   2286: aload #16
    //   2288: iload #17
    //   2290: aload #9
    //   2292: iload #17
    //   2294: iaload
    //   2295: iastore
    //   2296: iinc #17, 1
    //   2299: iload_2
    //   2300: ifne -> 2279
    //   2303: iconst_0
    //   2304: istore #17
    //   2306: iload #17
    //   2308: bipush #64
    //   2310: if_icmpge -> 2801
    //   2313: iload #17
    //   2315: bipush #16
    //   2317: if_icmpge -> 2398
    //   2320: aload #15
    //   2322: iload #17
    //   2324: aload #11
    //   2326: iconst_4
    //   2327: iload #17
    //   2329: imul
    //   2330: baload
    //   2331: sipush #255
    //   2334: iand
    //   2335: bipush #24
    //   2337: ishl
    //   2338: aload #11
    //   2340: iconst_4
    //   2341: iload #17
    //   2343: imul
    //   2344: iconst_1
    //   2345: iadd
    //   2346: baload
    //   2347: sipush #255
    //   2350: iand
    //   2351: bipush #16
    //   2353: ishl
    //   2354: ior
    //   2355: aload #11
    //   2357: iconst_4
    //   2358: iload #17
    //   2360: imul
    //   2361: iconst_2
    //   2362: iadd
    //   2363: baload
    //   2364: sipush #255
    //   2367: iand
    //   2368: bipush #8
    //   2370: ishl
    //   2371: ior
    //   2372: aload #11
    //   2374: iconst_4
    //   2375: iload #17
    //   2377: imul
    //   2378: iconst_3
    //   2379: iadd
    //   2380: baload
    //   2381: sipush #255
    //   2384: iand
    //   2385: ior
    //   2386: iastore
    //   2387: iload_2
    //   2388: ifne -> 2541
    //   2391: goto -> 2398
    //   2394: invokestatic a : (Ljava/lang/Throwable;)Ljava/lang/Throwable;
    //   2397: athrow
    //   2398: aload #15
    //   2400: iload #17
    //   2402: aload #15
    //   2404: iload #17
    //   2406: iconst_2
    //   2407: isub
    //   2408: iaload
    //   2409: bipush #17
    //   2411: iushr
    //   2412: aload #15
    //   2414: iload #17
    //   2416: iconst_2
    //   2417: isub
    //   2418: iaload
    //   2419: bipush #15
    //   2421: ishl
    //   2422: ior
    //   2423: aload #15
    //   2425: iload #17
    //   2427: iconst_2
    //   2428: isub
    //   2429: iaload
    //   2430: bipush #19
    //   2432: iushr
    //   2433: aload #15
    //   2435: iload #17
    //   2437: iconst_2
    //   2438: isub
    //   2439: iaload
    //   2440: bipush #13
    //   2442: ishl
    //   2443: ior
    //   2444: ixor
    //   2445: aload #15
    //   2447: iload #17
    //   2449: iconst_2
    //   2450: isub
    //   2451: iaload
    //   2452: bipush #10
    //   2454: iushr
    //   2455: ixor
    //   2456: aload #15
    //   2458: iload #17
    //   2460: bipush #7
    //   2462: isub
    //   2463: iaload
    //   2464: iadd
    //   2465: aload #15
    //   2467: iload #17
    //   2469: bipush #15
    //   2471: isub
    //   2472: iaload
    //   2473: bipush #7
    //   2475: iushr
    //   2476: aload #15
    //   2478: iload #17
    //   2480: bipush #15
    //   2482: isub
    //   2483: iaload
    //   2484: bipush #25
    //   2486: ishl
    //   2487: ior
    //   2488: aload #15
    //   2490: iload #17
    //   2492: bipush #15
    //   2494: isub
    //   2495: iaload
    //   2496: bipush #18
    //   2498: iushr
    //   2499: aload #15
    //   2501: iload #17
    //   2503: bipush #15
    //   2505: isub
    //   2506: iaload
    //   2507: bipush #14
    //   2509: ishl
    //   2510: ior
    //   2511: ixor
    //   2512: aload #15
    //   2514: iload #17
    //   2516: bipush #15
    //   2518: isub
    //   2519: iaload
    //   2520: iconst_3
    //   2521: iushr
    //   2522: ixor
    //   2523: iadd
    //   2524: aload #15
    //   2526: iload #17
    //   2528: bipush #16
    //   2530: isub
    //   2531: iaload
    //   2532: iadd
    //   2533: iastore
    //   2534: goto -> 2541
    //   2537: invokestatic a : (Ljava/lang/Throwable;)Ljava/lang/Throwable;
    //   2540: athrow
    //   2541: aload #16
    //   2543: bipush #7
    //   2545: iaload
    //   2546: aload #16
    //   2548: iconst_4
    //   2549: iaload
    //   2550: bipush #6
    //   2552: iushr
    //   2553: aload #16
    //   2555: iconst_4
    //   2556: iaload
    //   2557: bipush #26
    //   2559: ishl
    //   2560: ior
    //   2561: aload #16
    //   2563: iconst_4
    //   2564: iaload
    //   2565: bipush #11
    //   2567: iushr
    //   2568: aload #16
    //   2570: iconst_4
    //   2571: iaload
    //   2572: bipush #21
    //   2574: ishl
    //   2575: ior
    //   2576: ixor
    //   2577: aload #16
    //   2579: iconst_4
    //   2580: iaload
    //   2581: bipush #25
    //   2583: iushr
    //   2584: aload #16
    //   2586: iconst_4
    //   2587: iaload
    //   2588: bipush #7
    //   2590: ishl
    //   2591: ior
    //   2592: ixor
    //   2593: iadd
    //   2594: aload #16
    //   2596: bipush #6
    //   2598: iaload
    //   2599: aload #16
    //   2601: iconst_4
    //   2602: iaload
    //   2603: aload #16
    //   2605: iconst_5
    //   2606: iaload
    //   2607: aload #16
    //   2609: bipush #6
    //   2611: iaload
    //   2612: ixor
    //   2613: iand
    //   2614: ixor
    //   2615: iadd
    //   2616: aload #7
    //   2618: iload #17
    //   2620: iaload
    //   2621: iadd
    //   2622: aload #15
    //   2624: iload #17
    //   2626: iaload
    //   2627: iadd
    //   2628: istore #18
    //   2630: aload #16
    //   2632: iconst_0
    //   2633: iaload
    //   2634: iconst_2
    //   2635: iushr
    //   2636: aload #16
    //   2638: iconst_0
    //   2639: iaload
    //   2640: bipush #30
    //   2642: ishl
    //   2643: ior
    //   2644: aload #16
    //   2646: iconst_0
    //   2647: iaload
    //   2648: bipush #13
    //   2650: iushr
    //   2651: aload #16
    //   2653: iconst_0
    //   2654: iaload
    //   2655: bipush #19
    //   2657: ishl
    //   2658: ior
    //   2659: ixor
    //   2660: aload #16
    //   2662: iconst_0
    //   2663: iaload
    //   2664: bipush #22
    //   2666: iushr
    //   2667: aload #16
    //   2669: iconst_0
    //   2670: iaload
    //   2671: bipush #10
    //   2673: ishl
    //   2674: ior
    //   2675: ixor
    //   2676: aload #16
    //   2678: iconst_0
    //   2679: iaload
    //   2680: aload #16
    //   2682: iconst_1
    //   2683: iaload
    //   2684: iand
    //   2685: aload #16
    //   2687: iconst_2
    //   2688: iaload
    //   2689: aload #16
    //   2691: iconst_0
    //   2692: iaload
    //   2693: aload #16
    //   2695: iconst_1
    //   2696: iaload
    //   2697: ior
    //   2698: iand
    //   2699: ior
    //   2700: iadd
    //   2701: istore #19
    //   2703: aload #16
    //   2705: iconst_3
    //   2706: dup2
    //   2707: iaload
    //   2708: iload #18
    //   2710: iadd
    //   2711: iastore
    //   2712: aload #16
    //   2714: bipush #7
    //   2716: iload #18
    //   2718: iload #19
    //   2720: iadd
    //   2721: iastore
    //   2722: aload #16
    //   2724: bipush #7
    //   2726: iaload
    //   2727: istore #18
    //   2729: aload #16
    //   2731: bipush #7
    //   2733: aload #16
    //   2735: bipush #6
    //   2737: iaload
    //   2738: iastore
    //   2739: aload #16
    //   2741: bipush #6
    //   2743: aload #16
    //   2745: iconst_5
    //   2746: iaload
    //   2747: iastore
    //   2748: aload #16
    //   2750: iconst_5
    //   2751: aload #16
    //   2753: iconst_4
    //   2754: iaload
    //   2755: iastore
    //   2756: aload #16
    //   2758: iconst_4
    //   2759: aload #16
    //   2761: iconst_3
    //   2762: iaload
    //   2763: iastore
    //   2764: aload #16
    //   2766: iconst_3
    //   2767: aload #16
    //   2769: iconst_2
    //   2770: iaload
    //   2771: iastore
    //   2772: aload #16
    //   2774: iconst_2
    //   2775: aload #16
    //   2777: iconst_1
    //   2778: iaload
    //   2779: iastore
    //   2780: aload #16
    //   2782: iconst_1
    //   2783: aload #16
    //   2785: iconst_0
    //   2786: iaload
    //   2787: iastore
    //   2788: aload #16
    //   2790: iconst_0
    //   2791: iload #18
    //   2793: iastore
    //   2794: iinc #17, 1
    //   2797: iload_2
    //   2798: ifne -> 2306
    //   2801: iconst_0
    //   2802: istore #17
    //   2804: iload #17
    //   2806: bipush #8
    //   2808: if_icmpge -> 2831
    //   2811: aload #9
    //   2813: iload #17
    //   2815: dup2
    //   2816: iaload
    //   2817: aload #16
    //   2819: iload #17
    //   2821: iaload
    //   2822: iadd
    //   2823: iastore
    //   2824: iinc #17, 1
    //   2827: iload_2
    //   2828: ifne -> 2804
    //   2831: iinc #14, 64
    //   2834: iinc #12, -64
    //   2837: iload_2
    //   2838: ifne -> 2227
    //   2841: iload #12
    //   2843: ifle -> 2879
    //   2846: iconst_0
    //   2847: istore #15
    //   2849: iload #15
    //   2851: iload #12
    //   2853: if_icmpge -> 2879
    //   2856: aload #10
    //   2858: iload #13
    //   2860: iload #15
    //   2862: iadd
    //   2863: aload #4
    //   2865: iload #14
    //   2867: iload #15
    //   2869: iadd
    //   2870: baload
    //   2871: bastore
    //   2872: iinc #15, 1
    //   2875: iload_2
    //   2876: ifne -> 2849
    //   2879: aload #8
    //   2881: iconst_0
    //   2882: iaload
    //   2883: bipush #29
    //   2885: iushr
    //   2886: aload #8
    //   2888: iconst_1
    //   2889: iaload
    //   2890: iconst_3
    //   2891: ishl
    //   2892: ior
    //   2893: istore #15
    //   2895: aload #8
    //   2897: iconst_0
    //   2898: iaload
    //   2899: iconst_3
    //   2900: ishl
    //   2901: istore #16
    //   2903: aload #8
    //   2905: iconst_0
    //   2906: iaload
    //   2907: bipush #63
    //   2909: iand
    //   2910: istore #17
    //   2912: iload #17
    //   2914: bipush #56
    //   2916: if_icmpge -> 2931
    //   2919: bipush #56
    //   2921: iload #17
    //   2923: isub
    //   2924: goto -> 2936
    //   2927: invokestatic a : (Ljava/lang/Throwable;)Ljava/lang/Throwable;
    //   2930: athrow
    //   2931: bipush #120
    //   2933: iload #17
    //   2935: isub
    //   2936: istore #18
    //   2938: aload #8
    //   2940: iconst_0
    //   2941: iaload
    //   2942: bipush #63
    //   2944: iand
    //   2945: istore #13
    //   2947: bipush #64
    //   2949: iload #13
    //   2951: isub
    //   2952: istore #19
    //   2954: aload #8
    //   2956: iconst_0
    //   2957: dup2
    //   2958: iaload
    //   2959: iload #18
    //   2961: iadd
    //   2962: iastore
    //   2963: aload #8
    //   2965: iconst_0
    //   2966: dup2
    //   2967: iaload
    //   2968: iconst_m1
    //   2969: iand
    //   2970: iastore
    //   2971: aload #8
    //   2973: iconst_0
    //   2974: iaload
    //   2975: iload #18
    //   2977: if_icmpge -> 2995
    //   2980: aload #8
    //   2982: iconst_1
    //   2983: dup2
    //   2984: iaload
    //   2985: iconst_1
    //   2986: iadd
    //   2987: iastore
    //   2988: goto -> 2995
    //   2991: invokestatic a : (Ljava/lang/Throwable;)Ljava/lang/Throwable;
    //   2994: athrow
    //   2995: iconst_0
    //   2996: istore #14
    //   2998: iload #13
    //   3000: ifle -> 3631
    //   3003: iload #18
    //   3005: iload #19
    //   3007: if_icmplt -> 3631
    //   3010: goto -> 3017
    //   3013: invokestatic a : (Ljava/lang/Throwable;)Ljava/lang/Throwable;
    //   3016: athrow
    //   3017: iconst_0
    //   3018: istore #20
    //   3020: iload #20
    //   3022: iload #19
    //   3024: if_icmpge -> 3047
    //   3027: aload #10
    //   3029: iload #13
    //   3031: iload #20
    //   3033: iadd
    //   3034: aload #6
    //   3036: iload #20
    //   3038: baload
    //   3039: bastore
    //   3040: iinc #20, 1
    //   3043: iload_2
    //   3044: ifne -> 3020
    //   3047: bipush #64
    //   3049: newarray int
    //   3051: astore #20
    //   3053: bipush #8
    //   3055: newarray int
    //   3057: astore #21
    //   3059: iconst_0
    //   3060: istore #22
    //   3062: iload #22
    //   3064: bipush #8
    //   3066: if_icmpge -> 3086
    //   3069: aload #21
    //   3071: iload #22
    //   3073: aload #9
    //   3075: iload #22
    //   3077: iaload
    //   3078: iastore
    //   3079: iinc #22, 1
    //   3082: iload_2
    //   3083: ifne -> 3062
    //   3086: iconst_0
    //   3087: istore #22
    //   3089: iload #22
    //   3091: bipush #64
    //   3093: if_icmpge -> 3584
    //   3096: iload #22
    //   3098: bipush #16
    //   3100: if_icmpge -> 3181
    //   3103: aload #20
    //   3105: iload #22
    //   3107: aload #10
    //   3109: iconst_4
    //   3110: iload #22
    //   3112: imul
    //   3113: baload
    //   3114: sipush #255
    //   3117: iand
    //   3118: bipush #24
    //   3120: ishl
    //   3121: aload #10
    //   3123: iconst_4
    //   3124: iload #22
    //   3126: imul
    //   3127: iconst_1
    //   3128: iadd
    //   3129: baload
    //   3130: sipush #255
    //   3133: iand
    //   3134: bipush #16
    //   3136: ishl
    //   3137: ior
    //   3138: aload #10
    //   3140: iconst_4
    //   3141: iload #22
    //   3143: imul
    //   3144: iconst_2
    //   3145: iadd
    //   3146: baload
    //   3147: sipush #255
    //   3150: iand
    //   3151: bipush #8
    //   3153: ishl
    //   3154: ior
    //   3155: aload #10
    //   3157: iconst_4
    //   3158: iload #22
    //   3160: imul
    //   3161: iconst_3
    //   3162: iadd
    //   3163: baload
    //   3164: sipush #255
    //   3167: iand
    //   3168: ior
    //   3169: iastore
    //   3170: iload_2
    //   3171: ifne -> 3324
    //   3174: goto -> 3181
    //   3177: invokestatic a : (Ljava/lang/Throwable;)Ljava/lang/Throwable;
    //   3180: athrow
    //   3181: aload #20
    //   3183: iload #22
    //   3185: aload #20
    //   3187: iload #22
    //   3189: iconst_2
    //   3190: isub
    //   3191: iaload
    //   3192: bipush #17
    //   3194: iushr
    //   3195: aload #20
    //   3197: iload #22
    //   3199: iconst_2
    //   3200: isub
    //   3201: iaload
    //   3202: bipush #15
    //   3204: ishl
    //   3205: ior
    //   3206: aload #20
    //   3208: iload #22
    //   3210: iconst_2
    //   3211: isub
    //   3212: iaload
    //   3213: bipush #19
    //   3215: iushr
    //   3216: aload #20
    //   3218: iload #22
    //   3220: iconst_2
    //   3221: isub
    //   3222: iaload
    //   3223: bipush #13
    //   3225: ishl
    //   3226: ior
    //   3227: ixor
    //   3228: aload #20
    //   3230: iload #22
    //   3232: iconst_2
    //   3233: isub
    //   3234: iaload
    //   3235: bipush #10
    //   3237: iushr
    //   3238: ixor
    //   3239: aload #20
    //   3241: iload #22
    //   3243: bipush #7
    //   3245: isub
    //   3246: iaload
    //   3247: iadd
    //   3248: aload #20
    //   3250: iload #22
    //   3252: bipush #15
    //   3254: isub
    //   3255: iaload
    //   3256: bipush #7
    //   3258: iushr
    //   3259: aload #20
    //   3261: iload #22
    //   3263: bipush #15
    //   3265: isub
    //   3266: iaload
    //   3267: bipush #25
    //   3269: ishl
    //   3270: ior
    //   3271: aload #20
    //   3273: iload #22
    //   3275: bipush #15
    //   3277: isub
    //   3278: iaload
    //   3279: bipush #18
    //   3281: iushr
    //   3282: aload #20
    //   3284: iload #22
    //   3286: bipush #15
    //   3288: isub
    //   3289: iaload
    //   3290: bipush #14
    //   3292: ishl
    //   3293: ior
    //   3294: ixor
    //   3295: aload #20
    //   3297: iload #22
    //   3299: bipush #15
    //   3301: isub
    //   3302: iaload
    //   3303: iconst_3
    //   3304: iushr
    //   3305: ixor
    //   3306: iadd
    //   3307: aload #20
    //   3309: iload #22
    //   3311: bipush #16
    //   3313: isub
    //   3314: iaload
    //   3315: iadd
    //   3316: iastore
    //   3317: goto -> 3324
    //   3320: invokestatic a : (Ljava/lang/Throwable;)Ljava/lang/Throwable;
    //   3323: athrow
    //   3324: aload #21
    //   3326: bipush #7
    //   3328: iaload
    //   3329: aload #21
    //   3331: iconst_4
    //   3332: iaload
    //   3333: bipush #6
    //   3335: iushr
    //   3336: aload #21
    //   3338: iconst_4
    //   3339: iaload
    //   3340: bipush #26
    //   3342: ishl
    //   3343: ior
    //   3344: aload #21
    //   3346: iconst_4
    //   3347: iaload
    //   3348: bipush #11
    //   3350: iushr
    //   3351: aload #21
    //   3353: iconst_4
    //   3354: iaload
    //   3355: bipush #21
    //   3357: ishl
    //   3358: ior
    //   3359: ixor
    //   3360: aload #21
    //   3362: iconst_4
    //   3363: iaload
    //   3364: bipush #25
    //   3366: iushr
    //   3367: aload #21
    //   3369: iconst_4
    //   3370: iaload
    //   3371: bipush #7
    //   3373: ishl
    //   3374: ior
    //   3375: ixor
    //   3376: iadd
    //   3377: aload #21
    //   3379: bipush #6
    //   3381: iaload
    //   3382: aload #21
    //   3384: iconst_4
    //   3385: iaload
    //   3386: aload #21
    //   3388: iconst_5
    //   3389: iaload
    //   3390: aload #21
    //   3392: bipush #6
    //   3394: iaload
    //   3395: ixor
    //   3396: iand
    //   3397: ixor
    //   3398: iadd
    //   3399: aload #7
    //   3401: iload #22
    //   3403: iaload
    //   3404: iadd
    //   3405: aload #20
    //   3407: iload #22
    //   3409: iaload
    //   3410: iadd
    //   3411: istore #23
    //   3413: aload #21
    //   3415: iconst_0
    //   3416: iaload
    //   3417: iconst_2
    //   3418: iushr
    //   3419: aload #21
    //   3421: iconst_0
    //   3422: iaload
    //   3423: bipush #30
    //   3425: ishl
    //   3426: ior
    //   3427: aload #21
    //   3429: iconst_0
    //   3430: iaload
    //   3431: bipush #13
    //   3433: iushr
    //   3434: aload #21
    //   3436: iconst_0
    //   3437: iaload
    //   3438: bipush #19
    //   3440: ishl
    //   3441: ior
    //   3442: ixor
    //   3443: aload #21
    //   3445: iconst_0
    //   3446: iaload
    //   3447: bipush #22
    //   3449: iushr
    //   3450: aload #21
    //   3452: iconst_0
    //   3453: iaload
    //   3454: bipush #10
    //   3456: ishl
    //   3457: ior
    //   3458: ixor
    //   3459: aload #21
    //   3461: iconst_0
    //   3462: iaload
    //   3463: aload #21
    //   3465: iconst_1
    //   3466: iaload
    //   3467: iand
    //   3468: aload #21
    //   3470: iconst_2
    //   3471: iaload
    //   3472: aload #21
    //   3474: iconst_0
    //   3475: iaload
    //   3476: aload #21
    //   3478: iconst_1
    //   3479: iaload
    //   3480: ior
    //   3481: iand
    //   3482: ior
    //   3483: iadd
    //   3484: istore #24
    //   3486: aload #21
    //   3488: iconst_3
    //   3489: dup2
    //   3490: iaload
    //   3491: iload #23
    //   3493: iadd
    //   3494: iastore
    //   3495: aload #21
    //   3497: bipush #7
    //   3499: iload #23
    //   3501: iload #24
    //   3503: iadd
    //   3504: iastore
    //   3505: aload #21
    //   3507: bipush #7
    //   3509: iaload
    //   3510: istore #23
    //   3512: aload #21
    //   3514: bipush #7
    //   3516: aload #21
    //   3518: bipush #6
    //   3520: iaload
    //   3521: iastore
    //   3522: aload #21
    //   3524: bipush #6
    //   3526: aload #21
    //   3528: iconst_5
    //   3529: iaload
    //   3530: iastore
    //   3531: aload #21
    //   3533: iconst_5
    //   3534: aload #21
    //   3536: iconst_4
    //   3537: iaload
    //   3538: iastore
    //   3539: aload #21
    //   3541: iconst_4
    //   3542: aload #21
    //   3544: iconst_3
    //   3545: iaload
    //   3546: iastore
    //   3547: aload #21
    //   3549: iconst_3
    //   3550: aload #21
    //   3552: iconst_2
    //   3553: iaload
    //   3554: iastore
    //   3555: aload #21
    //   3557: iconst_2
    //   3558: aload #21
    //   3560: iconst_1
    //   3561: iaload
    //   3562: iastore
    //   3563: aload #21
    //   3565: iconst_1
    //   3566: aload #21
    //   3568: iconst_0
    //   3569: iaload
    //   3570: iastore
    //   3571: aload #21
    //   3573: iconst_0
    //   3574: iload #23
    //   3576: iastore
    //   3577: iinc #22, 1
    //   3580: iload_2
    //   3581: ifne -> 3089
    //   3584: iconst_0
    //   3585: istore #22
    //   3587: iload #22
    //   3589: bipush #8
    //   3591: if_icmpge -> 3614
    //   3594: aload #9
    //   3596: iload #22
    //   3598: dup2
    //   3599: iaload
    //   3600: aload #21
    //   3602: iload #22
    //   3604: iaload
    //   3605: iadd
    //   3606: iastore
    //   3607: iinc #22, 1
    //   3610: iload_2
    //   3611: ifne -> 3587
    //   3614: iload #14
    //   3616: iload #19
    //   3618: iadd
    //   3619: istore #14
    //   3621: iload #18
    //   3623: iload #19
    //   3625: isub
    //   3626: istore #18
    //   3628: iconst_0
    //   3629: istore #13
    //   3631: iload #18
    //   3633: bipush #64
    //   3635: if_icmplt -> 4245
    //   3638: iconst_0
    //   3639: istore #20
    //   3641: iload #20
    //   3643: bipush #64
    //   3645: if_icmpge -> 3668
    //   3648: aload #11
    //   3650: iload #20
    //   3652: aload #6
    //   3654: iload #14
    //   3656: iload #20
    //   3658: iadd
    //   3659: baload
    //   3660: bastore
    //   3661: iinc #20, 1
    //   3664: iload_2
    //   3665: ifne -> 3641
    //   3668: bipush #64
    //   3670: newarray int
    //   3672: astore #20
    //   3674: bipush #8
    //   3676: newarray int
    //   3678: astore #21
    //   3680: iconst_0
    //   3681: istore #22
    //   3683: iload #22
    //   3685: bipush #8
    //   3687: if_icmpge -> 3707
    //   3690: aload #21
    //   3692: iload #22
    //   3694: aload #9
    //   3696: iload #22
    //   3698: iaload
    //   3699: iastore
    //   3700: iinc #22, 1
    //   3703: iload_2
    //   3704: ifne -> 3683
    //   3707: iconst_0
    //   3708: istore #22
    //   3710: iload #22
    //   3712: bipush #64
    //   3714: if_icmpge -> 4205
    //   3717: iload #22
    //   3719: bipush #16
    //   3721: if_icmpge -> 3802
    //   3724: aload #20
    //   3726: iload #22
    //   3728: aload #11
    //   3730: iconst_4
    //   3731: iload #22
    //   3733: imul
    //   3734: baload
    //   3735: sipush #255
    //   3738: iand
    //   3739: bipush #24
    //   3741: ishl
    //   3742: aload #11
    //   3744: iconst_4
    //   3745: iload #22
    //   3747: imul
    //   3748: iconst_1
    //   3749: iadd
    //   3750: baload
    //   3751: sipush #255
    //   3754: iand
    //   3755: bipush #16
    //   3757: ishl
    //   3758: ior
    //   3759: aload #11
    //   3761: iconst_4
    //   3762: iload #22
    //   3764: imul
    //   3765: iconst_2
    //   3766: iadd
    //   3767: baload
    //   3768: sipush #255
    //   3771: iand
    //   3772: bipush #8
    //   3774: ishl
    //   3775: ior
    //   3776: aload #11
    //   3778: iconst_4
    //   3779: iload #22
    //   3781: imul
    //   3782: iconst_3
    //   3783: iadd
    //   3784: baload
    //   3785: sipush #255
    //   3788: iand
    //   3789: ior
    //   3790: iastore
    //   3791: iload_2
    //   3792: ifne -> 3945
    //   3795: goto -> 3802
    //   3798: invokestatic a : (Ljava/lang/Throwable;)Ljava/lang/Throwable;
    //   3801: athrow
    //   3802: aload #20
    //   3804: iload #22
    //   3806: aload #20
    //   3808: iload #22
    //   3810: iconst_2
    //   3811: isub
    //   3812: iaload
    //   3813: bipush #17
    //   3815: iushr
    //   3816: aload #20
    //   3818: iload #22
    //   3820: iconst_2
    //   3821: isub
    //   3822: iaload
    //   3823: bipush #15
    //   3825: ishl
    //   3826: ior
    //   3827: aload #20
    //   3829: iload #22
    //   3831: iconst_2
    //   3832: isub
    //   3833: iaload
    //   3834: bipush #19
    //   3836: iushr
    //   3837: aload #20
    //   3839: iload #22
    //   3841: iconst_2
    //   3842: isub
    //   3843: iaload
    //   3844: bipush #13
    //   3846: ishl
    //   3847: ior
    //   3848: ixor
    //   3849: aload #20
    //   3851: iload #22
    //   3853: iconst_2
    //   3854: isub
    //   3855: iaload
    //   3856: bipush #10
    //   3858: iushr
    //   3859: ixor
    //   3860: aload #20
    //   3862: iload #22
    //   3864: bipush #7
    //   3866: isub
    //   3867: iaload
    //   3868: iadd
    //   3869: aload #20
    //   3871: iload #22
    //   3873: bipush #15
    //   3875: isub
    //   3876: iaload
    //   3877: bipush #7
    //   3879: iushr
    //   3880: aload #20
    //   3882: iload #22
    //   3884: bipush #15
    //   3886: isub
    //   3887: iaload
    //   3888: bipush #25
    //   3890: ishl
    //   3891: ior
    //   3892: aload #20
    //   3894: iload #22
    //   3896: bipush #15
    //   3898: isub
    //   3899: iaload
    //   3900: bipush #18
    //   3902: iushr
    //   3903: aload #20
    //   3905: iload #22
    //   3907: bipush #15
    //   3909: isub
    //   3910: iaload
    //   3911: bipush #14
    //   3913: ishl
    //   3914: ior
    //   3915: ixor
    //   3916: aload #20
    //   3918: iload #22
    //   3920: bipush #15
    //   3922: isub
    //   3923: iaload
    //   3924: iconst_3
    //   3925: iushr
    //   3926: ixor
    //   3927: iadd
    //   3928: aload #20
    //   3930: iload #22
    //   3932: bipush #16
    //   3934: isub
    //   3935: iaload
    //   3936: iadd
    //   3937: iastore
    //   3938: goto -> 3945
    //   3941: invokestatic a : (Ljava/lang/Throwable;)Ljava/lang/Throwable;
    //   3944: athrow
    //   3945: aload #21
    //   3947: bipush #7
    //   3949: iaload
    //   3950: aload #21
    //   3952: iconst_4
    //   3953: iaload
    //   3954: bipush #6
    //   3956: iushr
    //   3957: aload #21
    //   3959: iconst_4
    //   3960: iaload
    //   3961: bipush #26
    //   3963: ishl
    //   3964: ior
    //   3965: aload #21
    //   3967: iconst_4
    //   3968: iaload
    //   3969: bipush #11
    //   3971: iushr
    //   3972: aload #21
    //   3974: iconst_4
    //   3975: iaload
    //   3976: bipush #21
    //   3978: ishl
    //   3979: ior
    //   3980: ixor
    //   3981: aload #21
    //   3983: iconst_4
    //   3984: iaload
    //   3985: bipush #25
    //   3987: iushr
    //   3988: aload #21
    //   3990: iconst_4
    //   3991: iaload
    //   3992: bipush #7
    //   3994: ishl
    //   3995: ior
    //   3996: ixor
    //   3997: iadd
    //   3998: aload #21
    //   4000: bipush #6
    //   4002: iaload
    //   4003: aload #21
    //   4005: iconst_4
    //   4006: iaload
    //   4007: aload #21
    //   4009: iconst_5
    //   4010: iaload
    //   4011: aload #21
    //   4013: bipush #6
    //   4015: iaload
    //   4016: ixor
    //   4017: iand
    //   4018: ixor
    //   4019: iadd
    //   4020: aload #7
    //   4022: iload #22
    //   4024: iaload
    //   4025: iadd
    //   4026: aload #20
    //   4028: iload #22
    //   4030: iaload
    //   4031: iadd
    //   4032: istore #23
    //   4034: aload #21
    //   4036: iconst_0
    //   4037: iaload
    //   4038: iconst_2
    //   4039: iushr
    //   4040: aload #21
    //   4042: iconst_0
    //   4043: iaload
    //   4044: bipush #30
    //   4046: ishl
    //   4047: ior
    //   4048: aload #21
    //   4050: iconst_0
    //   4051: iaload
    //   4052: bipush #13
    //   4054: iushr
    //   4055: aload #21
    //   4057: iconst_0
    //   4058: iaload
    //   4059: bipush #19
    //   4061: ishl
    //   4062: ior
    //   4063: ixor
    //   4064: aload #21
    //   4066: iconst_0
    //   4067: iaload
    //   4068: bipush #22
    //   4070: iushr
    //   4071: aload #21
    //   4073: iconst_0
    //   4074: iaload
    //   4075: bipush #10
    //   4077: ishl
    //   4078: ior
    //   4079: ixor
    //   4080: aload #21
    //   4082: iconst_0
    //   4083: iaload
    //   4084: aload #21
    //   4086: iconst_1
    //   4087: iaload
    //   4088: iand
    //   4089: aload #21
    //   4091: iconst_2
    //   4092: iaload
    //   4093: aload #21
    //   4095: iconst_0
    //   4096: iaload
    //   4097: aload #21
    //   4099: iconst_1
    //   4100: iaload
    //   4101: ior
    //   4102: iand
    //   4103: ior
    //   4104: iadd
    //   4105: istore #24
    //   4107: aload #21
    //   4109: iconst_3
    //   4110: dup2
    //   4111: iaload
    //   4112: iload #23
    //   4114: iadd
    //   4115: iastore
    //   4116: aload #21
    //   4118: bipush #7
    //   4120: iload #23
    //   4122: iload #24
    //   4124: iadd
    //   4125: iastore
    //   4126: aload #21
    //   4128: bipush #7
    //   4130: iaload
    //   4131: istore #23
    //   4133: aload #21
    //   4135: bipush #7
    //   4137: aload #21
    //   4139: bipush #6
    //   4141: iaload
    //   4142: iastore
    //   4143: aload #21
    //   4145: bipush #6
    //   4147: aload #21
    //   4149: iconst_5
    //   4150: iaload
    //   4151: iastore
    //   4152: aload #21
    //   4154: iconst_5
    //   4155: aload #21
    //   4157: iconst_4
    //   4158: iaload
    //   4159: iastore
    //   4160: aload #21
    //   4162: iconst_4
    //   4163: aload #21
    //   4165: iconst_3
    //   4166: iaload
    //   4167: iastore
    //   4168: aload #21
    //   4170: iconst_3
    //   4171: aload #21
    //   4173: iconst_2
    //   4174: iaload
    //   4175: iastore
    //   4176: aload #21
    //   4178: iconst_2
    //   4179: aload #21
    //   4181: iconst_1
    //   4182: iaload
    //   4183: iastore
    //   4184: aload #21
    //   4186: iconst_1
    //   4187: aload #21
    //   4189: iconst_0
    //   4190: iaload
    //   4191: iastore
    //   4192: aload #21
    //   4194: iconst_0
    //   4195: iload #23
    //   4197: iastore
    //   4198: iinc #22, 1
    //   4201: iload_2
    //   4202: ifne -> 3710
    //   4205: iconst_0
    //   4206: istore #22
    //   4208: iload #22
    //   4210: bipush #8
    //   4212: if_icmpge -> 4235
    //   4215: aload #9
    //   4217: iload #22
    //   4219: dup2
    //   4220: iaload
    //   4221: aload #21
    //   4223: iload #22
    //   4225: iaload
    //   4226: iadd
    //   4227: iastore
    //   4228: iinc #22, 1
    //   4231: iload_2
    //   4232: ifne -> 4208
    //   4235: iinc #14, 64
    //   4238: iinc #18, -64
    //   4241: iload_2
    //   4242: ifne -> 3631
    //   4245: iload #18
    //   4247: ifle -> 4283
    //   4250: iconst_0
    //   4251: istore #20
    //   4253: iload #20
    //   4255: iload #18
    //   4257: if_icmpge -> 4283
    //   4260: aload #10
    //   4262: iload #13
    //   4264: iload #20
    //   4266: iadd
    //   4267: aload #6
    //   4269: iload #14
    //   4271: iload #20
    //   4273: iadd
    //   4274: baload
    //   4275: bastore
    //   4276: iinc #20, 1
    //   4279: iload_2
    //   4280: ifne -> 4253
    //   4283: bipush #8
    //   4285: newarray byte
    //   4287: astore #20
    //   4289: aload #20
    //   4291: iconst_0
    //   4292: iload #15
    //   4294: bipush #24
    //   4296: iushr
    //   4297: i2b
    //   4298: bastore
    //   4299: aload #20
    //   4301: iconst_1
    //   4302: iload #15
    //   4304: bipush #16
    //   4306: iushr
    //   4307: i2b
    //   4308: bastore
    //   4309: aload #20
    //   4311: iconst_2
    //   4312: iload #15
    //   4314: bipush #8
    //   4316: iushr
    //   4317: i2b
    //   4318: bastore
    //   4319: aload #20
    //   4321: iconst_3
    //   4322: iload #15
    //   4324: i2b
    //   4325: bastore
    //   4326: aload #20
    //   4328: iconst_4
    //   4329: iload #16
    //   4331: bipush #24
    //   4333: iushr
    //   4334: i2b
    //   4335: bastore
    //   4336: aload #20
    //   4338: iconst_5
    //   4339: iload #16
    //   4341: bipush #16
    //   4343: iushr
    //   4344: i2b
    //   4345: bastore
    //   4346: aload #20
    //   4348: bipush #6
    //   4350: iload #16
    //   4352: bipush #8
    //   4354: iushr
    //   4355: i2b
    //   4356: bastore
    //   4357: aload #20
    //   4359: bipush #7
    //   4361: iload #16
    //   4363: i2b
    //   4364: bastore
    //   4365: bipush #8
    //   4367: istore #12
    //   4369: aload #8
    //   4371: iconst_0
    //   4372: iaload
    //   4373: bipush #63
    //   4375: iand
    //   4376: istore #13
    //   4378: bipush #64
    //   4380: iload #13
    //   4382: isub
    //   4383: istore #19
    //   4385: aload #8
    //   4387: iconst_0
    //   4388: dup2
    //   4389: iaload
    //   4390: iload #12
    //   4392: iadd
    //   4393: iastore
    //   4394: aload #8
    //   4396: iconst_0
    //   4397: dup2
    //   4398: iaload
    //   4399: iconst_m1
    //   4400: iand
    //   4401: iastore
    //   4402: aload #8
    //   4404: iconst_0
    //   4405: iaload
    //   4406: iload #12
    //   4408: if_icmpge -> 4426
    //   4411: aload #8
    //   4413: iconst_1
    //   4414: dup2
    //   4415: iaload
    //   4416: iconst_1
    //   4417: iadd
    //   4418: iastore
    //   4419: goto -> 4426
    //   4422: invokestatic a : (Ljava/lang/Throwable;)Ljava/lang/Throwable;
    //   4425: athrow
    //   4426: iload #13
    //   4428: ifle -> 5042
    //   4431: iload #12
    //   4433: iload #19
    //   4435: if_icmplt -> 5042
    //   4438: goto -> 4445
    //   4441: invokestatic a : (Ljava/lang/Throwable;)Ljava/lang/Throwable;
    //   4444: athrow
    //   4445: iconst_0
    //   4446: istore #21
    //   4448: iload #21
    //   4450: iload #19
    //   4452: if_icmpge -> 4475
    //   4455: aload #10
    //   4457: iload #13
    //   4459: iload #21
    //   4461: iadd
    //   4462: aload #20
    //   4464: iload #21
    //   4466: baload
    //   4467: bastore
    //   4468: iinc #21, 1
    //   4471: iload_2
    //   4472: ifne -> 4448
    //   4475: bipush #64
    //   4477: newarray int
    //   4479: astore #21
    //   4481: bipush #8
    //   4483: newarray int
    //   4485: astore #22
    //   4487: iconst_0
    //   4488: istore #23
    //   4490: iload #23
    //   4492: bipush #8
    //   4494: if_icmpge -> 4514
    //   4497: aload #22
    //   4499: iload #23
    //   4501: aload #9
    //   4503: iload #23
    //   4505: iaload
    //   4506: iastore
    //   4507: iinc #23, 1
    //   4510: iload_2
    //   4511: ifne -> 4490
    //   4514: iconst_0
    //   4515: istore #23
    //   4517: iload #23
    //   4519: bipush #64
    //   4521: if_icmpge -> 5012
    //   4524: iload #23
    //   4526: bipush #16
    //   4528: if_icmpge -> 4609
    //   4531: aload #21
    //   4533: iload #23
    //   4535: aload #10
    //   4537: iconst_4
    //   4538: iload #23
    //   4540: imul
    //   4541: baload
    //   4542: sipush #255
    //   4545: iand
    //   4546: bipush #24
    //   4548: ishl
    //   4549: aload #10
    //   4551: iconst_4
    //   4552: iload #23
    //   4554: imul
    //   4555: iconst_1
    //   4556: iadd
    //   4557: baload
    //   4558: sipush #255
    //   4561: iand
    //   4562: bipush #16
    //   4564: ishl
    //   4565: ior
    //   4566: aload #10
    //   4568: iconst_4
    //   4569: iload #23
    //   4571: imul
    //   4572: iconst_2
    //   4573: iadd
    //   4574: baload
    //   4575: sipush #255
    //   4578: iand
    //   4579: bipush #8
    //   4581: ishl
    //   4582: ior
    //   4583: aload #10
    //   4585: iconst_4
    //   4586: iload #23
    //   4588: imul
    //   4589: iconst_3
    //   4590: iadd
    //   4591: baload
    //   4592: sipush #255
    //   4595: iand
    //   4596: ior
    //   4597: iastore
    //   4598: iload_2
    //   4599: ifne -> 4752
    //   4602: goto -> 4609
    //   4605: invokestatic a : (Ljava/lang/Throwable;)Ljava/lang/Throwable;
    //   4608: athrow
    //   4609: aload #21
    //   4611: iload #23
    //   4613: aload #21
    //   4615: iload #23
    //   4617: iconst_2
    //   4618: isub
    //   4619: iaload
    //   4620: bipush #17
    //   4622: iushr
    //   4623: aload #21
    //   4625: iload #23
    //   4627: iconst_2
    //   4628: isub
    //   4629: iaload
    //   4630: bipush #15
    //   4632: ishl
    //   4633: ior
    //   4634: aload #21
    //   4636: iload #23
    //   4638: iconst_2
    //   4639: isub
    //   4640: iaload
    //   4641: bipush #19
    //   4643: iushr
    //   4644: aload #21
    //   4646: iload #23
    //   4648: iconst_2
    //   4649: isub
    //   4650: iaload
    //   4651: bipush #13
    //   4653: ishl
    //   4654: ior
    //   4655: ixor
    //   4656: aload #21
    //   4658: iload #23
    //   4660: iconst_2
    //   4661: isub
    //   4662: iaload
    //   4663: bipush #10
    //   4665: iushr
    //   4666: ixor
    //   4667: aload #21
    //   4669: iload #23
    //   4671: bipush #7
    //   4673: isub
    //   4674: iaload
    //   4675: iadd
    //   4676: aload #21
    //   4678: iload #23
    //   4680: bipush #15
    //   4682: isub
    //   4683: iaload
    //   4684: bipush #7
    //   4686: iushr
    //   4687: aload #21
    //   4689: iload #23
    //   4691: bipush #15
    //   4693: isub
    //   4694: iaload
    //   4695: bipush #25
    //   4697: ishl
    //   4698: ior
    //   4699: aload #21
    //   4701: iload #23
    //   4703: bipush #15
    //   4705: isub
    //   4706: iaload
    //   4707: bipush #18
    //   4709: iushr
    //   4710: aload #21
    //   4712: iload #23
    //   4714: bipush #15
    //   4716: isub
    //   4717: iaload
    //   4718: bipush #14
    //   4720: ishl
    //   4721: ior
    //   4722: ixor
    //   4723: aload #21
    //   4725: iload #23
    //   4727: bipush #15
    //   4729: isub
    //   4730: iaload
    //   4731: iconst_3
    //   4732: iushr
    //   4733: ixor
    //   4734: iadd
    //   4735: aload #21
    //   4737: iload #23
    //   4739: bipush #16
    //   4741: isub
    //   4742: iaload
    //   4743: iadd
    //   4744: iastore
    //   4745: goto -> 4752
    //   4748: invokestatic a : (Ljava/lang/Throwable;)Ljava/lang/Throwable;
    //   4751: athrow
    //   4752: aload #22
    //   4754: bipush #7
    //   4756: iaload
    //   4757: aload #22
    //   4759: iconst_4
    //   4760: iaload
    //   4761: bipush #6
    //   4763: iushr
    //   4764: aload #22
    //   4766: iconst_4
    //   4767: iaload
    //   4768: bipush #26
    //   4770: ishl
    //   4771: ior
    //   4772: aload #22
    //   4774: iconst_4
    //   4775: iaload
    //   4776: bipush #11
    //   4778: iushr
    //   4779: aload #22
    //   4781: iconst_4
    //   4782: iaload
    //   4783: bipush #21
    //   4785: ishl
    //   4786: ior
    //   4787: ixor
    //   4788: aload #22
    //   4790: iconst_4
    //   4791: iaload
    //   4792: bipush #25
    //   4794: iushr
    //   4795: aload #22
    //   4797: iconst_4
    //   4798: iaload
    //   4799: bipush #7
    //   4801: ishl
    //   4802: ior
    //   4803: ixor
    //   4804: iadd
    //   4805: aload #22
    //   4807: bipush #6
    //   4809: iaload
    //   4810: aload #22
    //   4812: iconst_4
    //   4813: iaload
    //   4814: aload #22
    //   4816: iconst_5
    //   4817: iaload
    //   4818: aload #22
    //   4820: bipush #6
    //   4822: iaload
    //   4823: ixor
    //   4824: iand
    //   4825: ixor
    //   4826: iadd
    //   4827: aload #7
    //   4829: iload #23
    //   4831: iaload
    //   4832: iadd
    //   4833: aload #21
    //   4835: iload #23
    //   4837: iaload
    //   4838: iadd
    //   4839: istore #24
    //   4841: aload #22
    //   4843: iconst_0
    //   4844: iaload
    //   4845: iconst_2
    //   4846: iushr
    //   4847: aload #22
    //   4849: iconst_0
    //   4850: iaload
    //   4851: bipush #30
    //   4853: ishl
    //   4854: ior
    //   4855: aload #22
    //   4857: iconst_0
    //   4858: iaload
    //   4859: bipush #13
    //   4861: iushr
    //   4862: aload #22
    //   4864: iconst_0
    //   4865: iaload
    //   4866: bipush #19
    //   4868: ishl
    //   4869: ior
    //   4870: ixor
    //   4871: aload #22
    //   4873: iconst_0
    //   4874: iaload
    //   4875: bipush #22
    //   4877: iushr
    //   4878: aload #22
    //   4880: iconst_0
    //   4881: iaload
    //   4882: bipush #10
    //   4884: ishl
    //   4885: ior
    //   4886: ixor
    //   4887: aload #22
    //   4889: iconst_0
    //   4890: iaload
    //   4891: aload #22
    //   4893: iconst_1
    //   4894: iaload
    //   4895: iand
    //   4896: aload #22
    //   4898: iconst_2
    //   4899: iaload
    //   4900: aload #22
    //   4902: iconst_0
    //   4903: iaload
    //   4904: aload #22
    //   4906: iconst_1
    //   4907: iaload
    //   4908: ior
    //   4909: iand
    //   4910: ior
    //   4911: iadd
    //   4912: istore #25
    //   4914: aload #22
    //   4916: iconst_3
    //   4917: dup2
    //   4918: iaload
    //   4919: iload #24
    //   4921: iadd
    //   4922: iastore
    //   4923: aload #22
    //   4925: bipush #7
    //   4927: iload #24
    //   4929: iload #25
    //   4931: iadd
    //   4932: iastore
    //   4933: aload #22
    //   4935: bipush #7
    //   4937: iaload
    //   4938: istore #24
    //   4940: aload #22
    //   4942: bipush #7
    //   4944: aload #22
    //   4946: bipush #6
    //   4948: iaload
    //   4949: iastore
    //   4950: aload #22
    //   4952: bipush #6
    //   4954: aload #22
    //   4956: iconst_5
    //   4957: iaload
    //   4958: iastore
    //   4959: aload #22
    //   4961: iconst_5
    //   4962: aload #22
    //   4964: iconst_4
    //   4965: iaload
    //   4966: iastore
    //   4967: aload #22
    //   4969: iconst_4
    //   4970: aload #22
    //   4972: iconst_3
    //   4973: iaload
    //   4974: iastore
    //   4975: aload #22
    //   4977: iconst_3
    //   4978: aload #22
    //   4980: iconst_2
    //   4981: iaload
    //   4982: iastore
    //   4983: aload #22
    //   4985: iconst_2
    //   4986: aload #22
    //   4988: iconst_1
    //   4989: iaload
    //   4990: iastore
    //   4991: aload #22
    //   4993: iconst_1
    //   4994: aload #22
    //   4996: iconst_0
    //   4997: iaload
    //   4998: iastore
    //   4999: aload #22
    //   5001: iconst_0
    //   5002: iload #24
    //   5004: iastore
    //   5005: iinc #23, 1
    //   5008: iload_2
    //   5009: ifne -> 4517
    //   5012: iconst_0
    //   5013: istore #23
    //   5015: iload #23
    //   5017: bipush #8
    //   5019: if_icmpge -> 5042
    //   5022: aload #9
    //   5024: iload #23
    //   5026: dup2
    //   5027: iaload
    //   5028: aload #22
    //   5030: iload #23
    //   5032: iaload
    //   5033: iadd
    //   5034: iastore
    //   5035: iinc #23, 1
    //   5038: iload_2
    //   5039: ifne -> 5015
    //   5042: bipush #32
    //   5044: newarray byte
    //   5046: astore #5
    //   5048: sipush #-29434
    //   5051: aload #5
    //   5053: iconst_0
    //   5054: aload #9
    //   5056: iconst_0
    //   5057: iaload
    //   5058: bipush #24
    //   5060: iushr
    //   5061: i2b
    //   5062: bastore
    //   5063: sipush #6345
    //   5066: aload #5
    //   5068: iconst_1
    //   5069: aload #9
    //   5071: iconst_0
    //   5072: iaload
    //   5073: bipush #16
    //   5075: iushr
    //   5076: i2b
    //   5077: bastore
    //   5078: aload #5
    //   5080: iconst_2
    //   5081: aload #9
    //   5083: iconst_0
    //   5084: iaload
    //   5085: bipush #8
    //   5087: iushr
    //   5088: i2b
    //   5089: bastore
    //   5090: aload #5
    //   5092: iconst_3
    //   5093: aload #9
    //   5095: iconst_0
    //   5096: iaload
    //   5097: i2b
    //   5098: bastore
    //   5099: aload #5
    //   5101: iconst_4
    //   5102: aload #9
    //   5104: iconst_1
    //   5105: iaload
    //   5106: bipush #24
    //   5108: iushr
    //   5109: i2b
    //   5110: bastore
    //   5111: aload #5
    //   5113: iconst_5
    //   5114: aload #9
    //   5116: iconst_1
    //   5117: iaload
    //   5118: bipush #16
    //   5120: iushr
    //   5121: i2b
    //   5122: bastore
    //   5123: aload #5
    //   5125: bipush #6
    //   5127: aload #9
    //   5129: iconst_1
    //   5130: iaload
    //   5131: bipush #8
    //   5133: iushr
    //   5134: i2b
    //   5135: bastore
    //   5136: aload #5
    //   5138: bipush #7
    //   5140: aload #9
    //   5142: iconst_1
    //   5143: iaload
    //   5144: i2b
    //   5145: bastore
    //   5146: aload #5
    //   5148: bipush #8
    //   5150: aload #9
    //   5152: iconst_2
    //   5153: iaload
    //   5154: bipush #24
    //   5156: iushr
    //   5157: i2b
    //   5158: bastore
    //   5159: aload #5
    //   5161: bipush #9
    //   5163: aload #9
    //   5165: iconst_2
    //   5166: iaload
    //   5167: bipush #16
    //   5169: iushr
    //   5170: i2b
    //   5171: bastore
    //   5172: aload #5
    //   5174: bipush #10
    //   5176: aload #9
    //   5178: iconst_2
    //   5179: iaload
    //   5180: bipush #8
    //   5182: iushr
    //   5183: i2b
    //   5184: bastore
    //   5185: aload #5
    //   5187: bipush #11
    //   5189: aload #9
    //   5191: iconst_2
    //   5192: iaload
    //   5193: i2b
    //   5194: bastore
    //   5195: aload #5
    //   5197: bipush #12
    //   5199: aload #9
    //   5201: iconst_3
    //   5202: iaload
    //   5203: bipush #24
    //   5205: iushr
    //   5206: i2b
    //   5207: bastore
    //   5208: aload #5
    //   5210: bipush #13
    //   5212: aload #9
    //   5214: iconst_3
    //   5215: iaload
    //   5216: bipush #16
    //   5218: iushr
    //   5219: i2b
    //   5220: bastore
    //   5221: aload #5
    //   5223: bipush #14
    //   5225: aload #9
    //   5227: iconst_3
    //   5228: iaload
    //   5229: bipush #8
    //   5231: iushr
    //   5232: i2b
    //   5233: bastore
    //   5234: aload #5
    //   5236: bipush #15
    //   5238: aload #9
    //   5240: iconst_3
    //   5241: iaload
    //   5242: i2b
    //   5243: bastore
    //   5244: aload #5
    //   5246: bipush #16
    //   5248: aload #9
    //   5250: iconst_4
    //   5251: iaload
    //   5252: bipush #24
    //   5254: iushr
    //   5255: i2b
    //   5256: bastore
    //   5257: aload #5
    //   5259: bipush #17
    //   5261: aload #9
    //   5263: iconst_4
    //   5264: iaload
    //   5265: bipush #16
    //   5267: iushr
    //   5268: i2b
    //   5269: bastore
    //   5270: aload #5
    //   5272: bipush #18
    //   5274: aload #9
    //   5276: iconst_4
    //   5277: iaload
    //   5278: bipush #8
    //   5280: iushr
    //   5281: i2b
    //   5282: bastore
    //   5283: aload #5
    //   5285: bipush #19
    //   5287: aload #9
    //   5289: iconst_4
    //   5290: iaload
    //   5291: i2b
    //   5292: bastore
    //   5293: aload #5
    //   5295: bipush #20
    //   5297: aload #9
    //   5299: iconst_5
    //   5300: iaload
    //   5301: bipush #24
    //   5303: iushr
    //   5304: i2b
    //   5305: bastore
    //   5306: aload #5
    //   5308: bipush #21
    //   5310: aload #9
    //   5312: iconst_5
    //   5313: iaload
    //   5314: bipush #16
    //   5316: iushr
    //   5317: i2b
    //   5318: bastore
    //   5319: aload #5
    //   5321: bipush #22
    //   5323: aload #9
    //   5325: iconst_5
    //   5326: iaload
    //   5327: bipush #8
    //   5329: iushr
    //   5330: i2b
    //   5331: bastore
    //   5332: aload #5
    //   5334: bipush #23
    //   5336: aload #9
    //   5338: iconst_5
    //   5339: iaload
    //   5340: i2b
    //   5341: bastore
    //   5342: aload #5
    //   5344: bipush #24
    //   5346: aload #9
    //   5348: bipush #6
    //   5350: iaload
    //   5351: bipush #24
    //   5353: iushr
    //   5354: i2b
    //   5355: bastore
    //   5356: aload #5
    //   5358: bipush #25
    //   5360: aload #9
    //   5362: bipush #6
    //   5364: iaload
    //   5365: bipush #16
    //   5367: iushr
    //   5368: i2b
    //   5369: bastore
    //   5370: aload #5
    //   5372: bipush #26
    //   5374: aload #9
    //   5376: bipush #6
    //   5378: iaload
    //   5379: bipush #8
    //   5381: iushr
    //   5382: i2b
    //   5383: bastore
    //   5384: aload #5
    //   5386: bipush #27
    //   5388: aload #9
    //   5390: bipush #6
    //   5392: iaload
    //   5393: i2b
    //   5394: bastore
    //   5395: aload #5
    //   5397: bipush #28
    //   5399: aload #9
    //   5401: bipush #7
    //   5403: iaload
    //   5404: bipush #24
    //   5406: iushr
    //   5407: i2b
    //   5408: bastore
    //   5409: aload #5
    //   5411: bipush #29
    //   5413: aload #9
    //   5415: bipush #7
    //   5417: iaload
    //   5418: bipush #16
    //   5420: iushr
    //   5421: i2b
    //   5422: bastore
    //   5423: aload #5
    //   5425: bipush #30
    //   5427: aload #9
    //   5429: bipush #7
    //   5431: iaload
    //   5432: bipush #8
    //   5434: iushr
    //   5435: i2b
    //   5436: bastore
    //   5437: aload #5
    //   5439: bipush #31
    //   5441: aload #9
    //   5443: bipush #7
    //   5445: iaload
    //   5446: i2b
    //   5447: bastore
    //   5448: new java/math/BigInteger
    //   5451: dup
    //   5452: aload #5
    //   5454: invokespecial <init> : ([B)V
    //   5457: invokevirtual abs : ()Ljava/math/BigInteger;
    //   5460: putstatic burp/Zgx6.Zo : Ljava/lang/Object;
    //   5463: invokestatic a : (II)Ljava/lang/String;
    //   5466: iconst_1
    //   5467: ldc burp/Zkku
    //   5469: invokevirtual getClassLoader : ()Ljava/lang/ClassLoader;
    //   5472: invokestatic forName : (Ljava/lang/String;ZLjava/lang/ClassLoader;)Ljava/lang/Class;
    //   5475: invokevirtual getDeclaredFields : ()[Ljava/lang/reflect/Field;
    //   5478: astore #4
    //   5480: aload #4
    //   5482: arraylength
    //   5483: istore #5
    //   5485: iconst_0
    //   5486: istore #6
    //   5488: iload #6
    //   5490: iload #5
    //   5492: if_icmpge -> 5630
    //   5495: aload #4
    //   5497: iload #6
    //   5499: aaload
    //   5500: astore #7
    //   5502: aload #7
    //   5504: invokevirtual getModifiers : ()I
    //   5507: invokestatic isStatic : (I)Z
    //   5510: ifne -> 5520
    //   5513: goto -> 5623
    //   5516: invokestatic a : (Ljava/lang/Throwable;)Ljava/lang/Throwable;
    //   5519: athrow
    //   5520: aload #7
    //   5522: invokevirtual getType : ()Ljava/lang/Class;
    //   5525: astore #8
    //   5527: aload #8
    //   5529: ifnull -> 5610
    //   5532: aload #8
    //   5534: invokevirtual isPrimitive : ()Z
    //   5537: ifne -> 5610
    //   5540: goto -> 5547
    //   5543: invokestatic a : (Ljava/lang/Throwable;)Ljava/lang/Throwable;
    //   5546: athrow
    //   5547: aload #8
    //   5549: invokevirtual getPackage : ()Ljava/lang/Package;
    //   5552: ifnull -> 5610
    //   5555: goto -> 5562
    //   5558: invokestatic a : (Ljava/lang/Throwable;)Ljava/lang/Throwable;
    //   5561: athrow
    //   5562: aload #8
    //   5564: invokevirtual getPackage : ()Ljava/lang/Package;
    //   5567: invokevirtual getName : ()Ljava/lang/String;
    //   5570: ifnull -> 5610
    //   5573: goto -> 5580
    //   5576: invokestatic a : (Ljava/lang/Throwable;)Ljava/lang/Throwable;
    //   5579: athrow
    //   5580: aload #8
    //   5582: invokevirtual getPackage : ()Ljava/lang/Package;
    //   5585: invokevirtual getName : ()Ljava/lang/String;
    //   5588: sipush #-29433
    //   5591: sipush #6912
    //   5594: invokestatic a : (II)Ljava/lang/String;
    //   5597: invokevirtual startsWith : (Ljava/lang/String;)Z
    //   5600: ifne -> 5610
    //   5603: goto -> 5610
    //   5606: invokestatic a : (Ljava/lang/Throwable;)Ljava/lang/Throwable;
    //   5609: athrow
    //   5610: aload #7
    //   5612: iconst_1
    //   5613: invokevirtual setAccessible : (Z)V
    //   5616: aload #7
    //   5618: aconst_null
    //   5619: invokevirtual get : (Ljava/lang/Object;)Ljava/lang/Object;
    //   5622: pop
    //   5623: iinc #6, 1
    //   5626: iload_2
    //   5627: ifne -> 5488
    //   5630: sipush #-29436
    //   5633: sipush #16016
    //   5636: invokestatic a : (II)Ljava/lang/String;
    //   5639: invokestatic forName : (Ljava/lang/String;)Ljava/lang/Class;
    //   5642: invokevirtual getDeclaredMethods : ()[Ljava/lang/reflect/Method;
    //   5645: astore #4
    //   5647: aload #4
    //   5649: arraylength
    //   5650: istore #5
    //   5652: iconst_0
    //   5653: istore #6
    //   5655: iload #6
    //   5657: iload #5
    //   5659: if_icmpge -> 5792
    //   5662: aload #4
    //   5664: iload #6
    //   5666: aaload
    //   5667: astore #7
    //   5669: aload #7
    //   5671: invokevirtual getParameterTypes : ()[Ljava/lang/Class;
    //   5674: pop
    //   5675: aload #7
    //   5677: invokevirtual getModifiers : ()I
    //   5680: invokestatic isStatic : (I)Z
    //   5683: ifeq -> 5778
    //   5686: aload #7
    //   5688: invokevirtual getParameterTypes : ()[Ljava/lang/Class;
    //   5691: arraylength
    //   5692: iconst_2
    //   5693: if_icmpne -> 5778
    //   5696: goto -> 5703
    //   5699: invokestatic a : (Ljava/lang/Throwable;)Ljava/lang/Throwable;
    //   5702: athrow
    //   5703: aload #7
    //   5705: invokevirtual getReturnType : ()Ljava/lang/Class;
    //   5708: getstatic java/lang/Void.TYPE : Ljava/lang/Class;
    //   5711: invokevirtual equals : (Ljava/lang/Object;)Z
    //   5714: ifeq -> 5778
    //   5717: goto -> 5724
    //   5720: invokestatic a : (Ljava/lang/Throwable;)Ljava/lang/Throwable;
    //   5723: athrow
    //   5724: aload #7
    //   5726: iconst_1
    //   5727: invokevirtual setAccessible : (Z)V
    //   5730: aload #7
    //   5732: aconst_null
    //   5733: iconst_2
    //   5734: anewarray java/lang/Object
    //   5737: dup
    //   5738: iconst_0
    //   5739: aload_0
    //   5740: aastore
    //   5741: dup
    //   5742: iconst_1
    //   5743: aload_1
    //   5744: ifnonnull -> 5762
    //   5747: goto -> 5754
    //   5750: invokestatic a : (Ljava/lang/Throwable;)Ljava/lang/Throwable;
    //   5753: athrow
    //   5754: aload_1
    //   5755: goto -> 5769
    //   5758: invokestatic a : (Ljava/lang/Throwable;)Ljava/lang/Throwable;
    //   5761: athrow
    //   5762: aload_1
    //   5763: checkcast [B
    //   5766: invokevirtual clone : ()Ljava/lang/Object;
    //   5769: aastore
    //   5770: invokevirtual invoke : (Ljava/lang/Object;[Ljava/lang/Object;)Ljava/lang/Object;
    //   5773: pop
    //   5774: iload_2
    //   5775: ifne -> 5792
    //   5778: iinc #6, 1
    //   5781: iload_2
    //   5782: ifne -> 5655
    //   5785: goto -> 5792
    //   5788: invokestatic a : (Ljava/lang/Throwable;)Ljava/lang/Throwable;
    //   5791: athrow
    //   5792: getstatic burp/Zts_.Zx : Ljava/lang/String;
    //   5795: getstatic burp/Zssb.ZW : Ljava/lang/Object;
    //   5798: checkcast java/math/BigInteger
    //   5801: invokevirtual intValue : ()I
    //   5804: bipush #32
    //   5806: irem
    //   5807: invokestatic abs : (I)I
    //   5810: invokevirtual charAt : (I)C
    //   5813: getstatic burp/Zstq.ZL : Ljava/lang/String;
    //   5816: getstatic burp/Zsji.Zg : Ljava/lang/Object;
    //   5819: checkcast java/math/BigInteger
    //   5822: invokevirtual intValue : ()I
    //   5825: bipush #32
    //   5827: irem
    //   5828: invokestatic abs : (I)I
    //   5831: invokevirtual charAt : (I)C
    //   5834: if_icmple -> 5949
    //   5837: getstatic burp/Zr3j.Zj : Ljava/lang/String;
    //   5840: getstatic burp/Zl55.ZZ : Ljava/lang/Object;
    //   5843: checkcast java/math/BigInteger
    //   5846: invokevirtual intValue : ()I
    //   5849: bipush #32
    //   5851: irem
    //   5852: invokestatic abs : (I)I
    //   5855: invokevirtual charAt : (I)C
    //   5858: getstatic burp/Zr3j.Zj : Ljava/lang/String;
    //   5861: getstatic burp/Zb1.Zf : Ljava/lang/Object;
    //   5864: checkcast java/math/BigInteger
    //   5867: invokevirtual intValue : ()I
    //   5870: bipush #32
    //   5872: irem
    //   5873: invokestatic abs : (I)I
    //   5876: invokevirtual charAt : (I)C
    //   5879: if_icmple -> 5949
    //   5882: goto -> 5889
    //   5885: invokestatic a : (Ljava/lang/Throwable;)Ljava/lang/Throwable;
    //   5888: athrow
    //   5889: getstatic burp/Zgk1.Zv : Ljava/lang/String;
    //   5892: getstatic burp/Zxzt.ZY : Ljava/lang/Object;
    //   5895: checkcast java/math/BigInteger
    //   5898: invokevirtual intValue : ()I
    //   5901: bipush #32
    //   5903: irem
    //   5904: invokestatic abs : (I)I
    //   5907: invokevirtual charAt : (I)C
    //   5910: getstatic burp/Zmjw.ZB : Ljava/lang/String;
    //   5913: getstatic burp/Zrqd.Zi : Ljava/lang/Object;
    //   5916: checkcast java/math/BigInteger
    //   5919: invokevirtual intValue : ()I
    //   5922: bipush #32
    //   5924: irem
    //   5925: invokestatic abs : (I)I
    //   5928: invokevirtual charAt : (I)C
    //   5931: if_icmple -> 5949
    //   5934: goto -> 5941
    //   5937: invokestatic a : (Ljava/lang/Throwable;)Ljava/lang/Throwable;
    //   5940: athrow
    //   5941: iconst_1
    //   5942: goto -> 5950
    //   5945: invokestatic a : (Ljava/lang/Throwable;)Ljava/lang/Throwable;
    //   5948: athrow
    //   5949: iconst_0
    //   5950: ireturn
    //   5951: astore_3
    //   5952: new java/lang/Exception
    //   5955: dup
    //   5956: aload_3
    //   5957: invokevirtual getMessage : ()Ljava/lang/String;
    //   5960: invokespecial <init> : (Ljava/lang/String;)V
    //   5963: athrow
    // Exception table:
    //   from	to	target	type
    //   4	5950	5951	java/lang/Throwable
    //   22	198	201	java/lang/Throwable
    //   168	235	238	java/lang/Throwable
    //   205	272	275	java/lang/Throwable
    //   242	309	312	java/lang/Throwable
    //   279	346	349	java/lang/Throwable
    //   316	383	386	java/lang/Throwable
    //   353	420	423	java/lang/Throwable
    //   390	457	460	java/lang/Throwable
    //   427	494	497	java/lang/Throwable
    //   464	531	534	java/lang/Throwable
    //   501	568	571	java/lang/Throwable
    //   538	605	608	java/lang/Throwable
    //   575	642	645	java/lang/Throwable
    //   612	679	682	java/lang/Throwable
    //   649	716	719	java/lang/Throwable
    //   686	753	756	java/lang/Throwable
    //   723	790	793	java/lang/Throwable
    //   760	827	830	java/lang/Throwable
    //   797	864	867	java/lang/Throwable
    //   834	901	904	java/lang/Throwable
    //   871	938	941	java/lang/Throwable
    //   908	975	978	java/lang/Throwable
    //   945	1012	1015	java/lang/Throwable
    //   982	1049	1052	java/lang/Throwable
    //   1019	1086	1089	java/lang/Throwable
    //   1056	1123	1126	java/lang/Throwable
    //   1093	1160	1163	java/lang/Throwable
    //   1130	1197	1200	java/lang/Throwable
    //   1167	1234	1237	java/lang/Throwable
    //   1204	1271	1274	java/lang/Throwable
    //   1241	1308	1311	java/lang/Throwable
    //   1278	1341	1344	java/lang/Throwable
    //   2183	2217	2220	java/lang/Throwable
    //   2313	2391	2394	java/lang/Throwable
    //   2320	2534	2537	java/lang/Throwable
    //   2912	2927	2927	java/lang/Throwable
    //   2954	2988	2991	java/lang/Throwable
    //   2998	3010	3013	java/lang/Throwable
    //   3096	3174	3177	java/lang/Throwable
    //   3103	3317	3320	java/lang/Throwable
    //   3717	3795	3798	java/lang/Throwable
    //   3724	3938	3941	java/lang/Throwable
    //   4385	4419	4422	java/lang/Throwable
    //   4426	4438	4441	java/lang/Throwable
    //   4524	4602	4605	java/lang/Throwable
    //   4531	4745	4748	java/lang/Throwable
    //   5502	5516	5516	java/lang/Throwable
    //   5527	5540	5543	java/lang/Throwable
    //   5532	5555	5558	java/lang/Throwable
    //   5547	5573	5576	java/lang/Throwable
    //   5562	5603	5606	java/lang/Throwable
    //   5669	5696	5699	java/lang/Throwable
    //   5686	5717	5720	java/lang/Throwable
    //   5703	5747	5750	java/lang/Throwable
    //   5724	5758	5758	java/lang/Throwable
    //   5769	5785	5788	java/lang/Throwable
    //   5792	5882	5885	java/lang/Throwable
    //   5837	5934	5937	java/lang/Throwable
    //   5889	5945	5945	java/lang/Throwable
  }
  
  static void ZK(Object[] paramArrayOfObject, Object paramObject) throws Throwable {}
  
  static {
    // Byte code:
    //   0: bipush #9
    //   2: anewarray java/lang/String
    //   5: astore #5
    //   7: iconst_0
    //   8: istore_3
    //   9: ldc 'qDO`I1d<7VM7',p{.^JA;3"*21(7cjV[B4Lc\\t2)MD2>!2ou#{kcHNB9Sa)W[adz}uazr$<pC><!B [%+xjTc>'&/(I~\\t+\\t) Qw>nF{k@,U'
    //   11: dup
    //   12: astore_2
    //   13: invokevirtual length : ()I
    //   16: istore #4
    //   18: bipush #77
    //   20: istore_1
    //   21: iconst_m1
    //   22: istore_0
    //   23: bipush #66
    //   25: iinc #0, 1
    //   28: aload_2
    //   29: iload_0
    //   30: dup
    //   31: iload_1
    //   32: iadd
    //   33: invokevirtual substring : (II)Ljava/lang/String;
    //   36: iconst_m1
    //   37: goto -> 143
    //   40: aload #5
    //   42: swap
    //   43: iload_3
    //   44: iinc #3, 1
    //   47: swap
    //   48: aastore
    //   49: iload_0
    //   50: iload_1
    //   51: iadd
    //   52: dup
    //   53: istore_0
    //   54: iload #4
    //   56: if_icmpge -> 68
    //   59: aload_2
    //   60: iload_0
    //   61: invokevirtual charAt : (I)C
    //   64: istore_1
    //   65: goto -> 23
    //   68: ldc 'H.G\\thNf_n'
    //   70: dup
    //   71: astore_2
    //   72: invokevirtual length : ()I
    //   75: istore #4
    //   77: bipush #9
    //   79: istore_1
    //   80: iconst_m1
    //   81: istore_0
    //   82: bipush #55
    //   84: iinc #0, 1
    //   87: aload_2
    //   88: iload_0
    //   89: dup
    //   90: iload_1
    //   91: iadd
    //   92: invokevirtual substring : (II)Ljava/lang/String;
    //   95: iconst_0
    //   96: goto -> 143
    //   99: aload #5
    //   101: swap
    //   102: iload_3
    //   103: iinc #3, 1
    //   106: swap
    //   107: aastore
    //   108: iload_0
    //   109: iload_1
    //   110: iadd
    //   111: dup
    //   112: istore_0
    //   113: iload #4
    //   115: if_icmpge -> 127
    //   118: aload_2
    //   119: iload_0
    //   120: invokevirtual charAt : (I)C
    //   123: istore_1
    //   124: goto -> 82
    //   127: aload #5
    //   129: putstatic burp/Zr_z.a : [Ljava/lang/String;
    //   132: bipush #9
    //   134: anewarray java/lang/String
    //   137: putstatic burp/Zr_z.b : [Ljava/lang/String;
    //   140: goto -> 300
    //   143: dup_x2
    //   144: pop
    //   145: invokevirtual toCharArray : ()[C
    //   148: dup_x1
    //   149: arraylength
    //   150: dup_x2
    //   151: pop
    //   152: iconst_0
    //   153: istore #6
    //   155: dup2_x1
    //   156: pop2
    //   157: dup_x2
    //   158: iconst_1
    //   159: if_icmpgt -> 260
    //   162: dup2
    //   163: swap
    //   164: iload #6
    //   166: dup2_x1
    //   167: caload
    //   168: swap
    //   169: iload #6
    //   171: bipush #7
    //   173: irem
    //   174: tableswitch default -> 242, 0 -> 212, 1 -> 217, 2 -> 222, 3 -> 227, 4 -> 232, 5 -> 237
    //   212: bipush #13
    //   214: goto -> 244
    //   217: bipush #96
    //   219: goto -> 244
    //   222: bipush #71
    //   224: goto -> 244
    //   227: bipush #81
    //   229: goto -> 244
    //   232: bipush #65
    //   234: goto -> 244
    //   237: bipush #93
    //   239: goto -> 244
    //   242: bipush #114
    //   244: ixor
    //   245: ixor
    //   246: i2c
    //   247: castore
    //   248: iinc #6, 1
    //   251: dup
    //   252: ifne -> 260
    //   255: dup2
    //   256: dup_x1
    //   257: goto -> 166
    //   260: dup2_x1
    //   261: pop2
    //   262: dup_x2
    //   263: iload #6
    //   265: if_icmpgt -> 162
    //   268: pop
    //   269: new java/lang/String
    //   272: dup_x1
    //   273: swap
    //   274: invokespecial <init> : ([C)V
    //   277: invokevirtual intern : ()Ljava/lang/String;
    //   280: swap
    //   281: pop
    //   282: swap
    //   283: tableswitch default -> 40, 0 -> 99
    //   300: new java/math/BigInteger
    //   303: dup
    //   304: sipush #-29439
    //   307: sipush #19063
    //   310: invokestatic a : (II)Ljava/lang/String;
    //   313: invokespecial <init> : (Ljava/lang/String;)V
    //   316: putstatic burp/Zr_z.ZT : Ljava/lang/Object;
    //   319: sipush #-29435
    //   322: sipush #-17008
    //   325: invokestatic a : (II)Ljava/lang/String;
    //   328: putstatic burp/Zr_z.ZE : Ljava/lang/String;
    //   331: return
  }
  
  private static Throwable a(Throwable paramThrowable) {
    return paramThrowable;
  }
  
  private static String a(int paramInt1, int paramInt2) {
    int i = (paramInt1 ^ 0xFFFF8D03) & 0xFFFF;
    if (b[i] == null) {
      char[] arrayOfChar = a[i].toCharArray();
      switch (arrayOfChar[0] & 0xFF) {
        case 0:
        
        case 1:
        
        case 2:
        
        case 3:
        
        case 4:
        
        case 5:
        
        case 6:
        
        case 7:
        
        case 8:
        
        case 9:
        
        case 10:
        
        case 11:
        
        case 12:
        
        case 13:
        
        case 14:
        
        case 15:
        
        case 16:
        
        case 17:
        
        case 18:
        
        case 19:
        
        case 20:
        
        case 21:
        
        case 22:
        
        case 23:
        
        case 24:
        
        case 25:
        
        case 26:
        
        case 27:
        
        case 28:
        
        case 29:
        
        case 30:
        
        case 31:
        
        case 32:
        
        case 33:
        
        case 34:
        
        case 35:
        
        case 36:
        
        case 37:
        
        case 38:
        
        case 39:
        
        case 40:
        
        case 41:
        
        case 42:
        
        case 43:
        
        case 44:
        
        case 45:
        
        case 46:
        
        case 47:
        
        case 48:
        
        case 49:
        
        case 50:
        
        case 51:
        
        case 52:
        
        case 53:
        
        case 54:
        
        case 55:
        
        case 56:
        
        case 57:
        
        case 58:
        
        case 59:
        
        case 60:
        
        case 61:
        
        case 62:
        
        case 63:
        
        case 64:
        
        case 65:
        
        case 66:
        
        case 67:
        
        case 68:
        
        case 69:
        
        case 70:
        
        case 71:
        
        case 72:
        
        case 73:
        
        case 74:
        
        case 75:
        
        case 76:
        
        case 77:
        
        case 78:
        
        case 79:
        
        case 80:
        
        case 81:
        
        case 82:
        
        case 83:
        
        case 84:
        
        case 85:
        
        case 86:
        
        case 87:
        
        case 88:
        
        case 89:
        
        case 90:
        
        case 91:
        
        case 92:
        
        case 93:
        
        case 94:
        
        case 95:
        
        case 96:
        
        case 97:
        
        case 98:
        
        case 99:
        
        case 100:
        
        case 101:
        
        case 102:
        
        case 103:
        
        case 104:
        
        case 105:
        
        case 106:
        
        case 107:
        
        case 108:
        
        case 109:
        
        case 110:
        
        case 111:
        
        case 112:
        
        case 113:
        
        case 114:
        
        case 115:
        
        case 116:
        
        case 117:
        
        case 118:
        
        case 119:
        
        case 120:
        
        case 121:
        
        case 122:
        
        case 123:
        
        case 124:
        
        case 125:
        
        case 126:
        
        case 127:
        
        case 128:
        
        case 129:
        
        case 130:
        
        case 131:
        
        case 132:
        
        case 133:
        
        case 134:
        
        case 135:
        
        case 136:
        
        case 137:
        
        case 138:
        
        case 139:
        
        case 140:
        
        case 141:
        
        case 142:
        
        case 143:
        
        case 144:
        
        case 145:
        
        case 146:
        
        case 147:
        
        case 148:
        
        case 149:
        
        case 150:
        
        case 151:
        
        case 152:
        
        case 153:
        
        case 154:
        
        case 155:
        
        case 156:
        
        case 157:
        
        case 158:
        
        case 159:
        
        case 160:
        
        case 161:
        
        case 162:
        
        case 163:
        
        case 164:
        
        case 165:
        
        case 166:
        
        case 167:
        
        case 168:
        
        case 169:
        
        case 170:
        
        case 171:
        
        case 172:
        
        case 173:
        
        case 174:
        
        case 175:
        
        case 176:
        
        case 177:
        
        case 178:
        
        case 179:
        
        case 180:
        
        case 181:
        
        case 182:
        
        case 183:
        
        case 184:
        
        case 185:
        
        case 186:
        
        case 187:
        
        case 188:
        
        case 189:
        
        case 190:
        
        case 191:
        
        case 192:
        
        case 193:
        
        case 194:
        
        case 195:
        
        case 196:
        
        case 197:
        
        case 198:
        
        case 199:
        
        case 200:
        
        case 201:
        
        case 202:
        
        case 203:
        
        case 204:
        
        case 205:
        
        case 206:
        
        case 207:
        
        case 208:
        
        case 209:
        
        case 210:
        
        case 211:
        
        case 212:
        
        case 213:
        
        case 214:
        
        case 215:
        
        case 216:
        
        case 217:
        
        case 218:
        
        case 219:
        
        case 220:
        
        case 221:
        
        case 222:
        
        case 223:
        
        case 224:
        
        case 225:
        
        case 226:
        
        case 227:
        
        case 228:
        
        case 229:
        
        case 230:
        
        case 231:
        
        case 232:
        
        case 233:
        
        case 234:
        
        case 235:
        
        case 236:
        
        case 237:
        
        case 238:
        
        case 239:
        
        case 240:
        
        case 241:
        
        case 242:
        
        case 243:
        
        case 244:
        
        case 245:
        
        case 246:
        
        case 247:
        
        case 248:
        
        case 249:
        
        case 250:
        
        case 251:
        
        case 252:
        
        case 253:
        
        case 254:
        
        default:
          break;
      } 
      char c = '';
      int j = (paramInt2 & 0xFF) - c;
      if (j < 0)
        j += 256; 
      int k = ((paramInt2 & 0xFFFF) >>> 8) - c;
      if (k < 0)
        k += 256; 
      for (byte b = 0; b < arrayOfChar.length; b++) {
        int m = b % 2;
        if (m == 0) {
          arrayOfChar[b] = (char)(arrayOfChar[b] ^ j);
          j = ((j >>> 3 | j << 5) ^ arrayOfChar[b]) & 0xFF;
        } else {
          arrayOfChar[b] = (char)(arrayOfChar[b] ^ k);
          k = ((k >>> 3 | k << 5) ^ arrayOfChar[b]) & 0xFF;
        } 
      } 
      b[i] = (new String(arrayOfChar)).intern();
    } 
    return b[i];
  }
}


/* Location:              C:\Program Files\BurpSuitePro\burpsuite_pro.jar!\burp\Zr_z.class
 * Java compiler version: 21 (65.0)
 * JD-Core Version:       1.1.3
 */