package burp;

import java.math.BigInteger;

class Zram extends ClassLoader {
  static String Ze;
  
  static Object ZF;
  
  private static final String[] a;
  
  private static final String[] b;
  
  static void ZI(Object[] paramArrayOfObject, Object paramObject) throws Throwable {}
  
  static boolean ZF(Object[] paramArrayOfObject, Object paramObject) throws Throwable {
    // Byte code:
    //   0: invokestatic ZK : ()Z
    //   3: istore_2
    //   4: getstatic burp/Zs2n.ZK : Ljava/lang/Object;
    //   7: checkcast java/math/BigInteger
    //   10: invokevirtual toByteArray : ()[B
    //   13: astore_3
    //   14: bipush #32
    //   16: newarray int
    //   18: dup
    //   19: iconst_0
    //   20: ldc 943331329
    //   22: iastore
    //   23: dup
    //   24: iconst_1
    //   25: ldc 170788368
    //   27: iastore
    //   28: dup
    //   29: iconst_2
    //   30: ldc 1008414755
    //   32: iastore
    //   33: dup
    //   34: iconst_3
    //   35: ldc 187049985
    //   37: iastore
    //   38: dup
    //   39: iconst_4
    //   40: ldc 1010368540
    //   42: iastore
    //   43: dup
    //   44: iconst_5
    //   45: ldc 220604441
    //   47: iastore
    //   48: dup
    //   49: bipush #6
    //   51: ldc 940377620
    //   53: iastore
    //   54: dup
    //   55: bipush #7
    //   57: ldc 255209728
    //   59: iastore
    //   60: dup
    //   61: bipush #8
    //   63: ldc 689771012
    //   65: iastore
    //   66: dup
    //   67: bipush #9
    //   69: ldc 221709344
    //   71: iastore
    //   72: dup
    //   73: bipush #10
    //   75: ldc 957157408
    //   77: iastore
    //   78: dup
    //   79: bipush #11
    //   81: ldc 892536332
    //   83: iastore
    //   84: dup
    //   85: bipush #12
    //   87: ldc 722417666
    //   89: iastore
    //   90: dup
    //   91: bipush #13
    //   93: ldc 1026621720
    //   95: iastore
    //   96: dup
    //   97: bipush #14
    //   99: ldc 655302664
    //   101: iastore
    //   102: dup
    //   103: bipush #15
    //   105: ldc 890966315
    //   107: iastore
    //   108: dup
    //   109: bipush #16
    //   111: ldc 187632156
    //   113: iastore
    //   114: dup
    //   115: bipush #17
    //   117: ldc 874189824
    //   119: iastore
    //   120: dup
    //   121: bipush #18
    //   123: ldc 254150144
    //   125: iastore
    //   126: dup
    //   127: bipush #19
    //   129: ldc 924386310
    //   131: iastore
    //   132: dup
    //   133: bipush #20
    //   135: ldc 121057538
    //   137: iastore
    //   138: dup
    //   139: bipush #21
    //   141: ldc 840500228
    //   143: iastore
    //   144: dup
    //   145: bipush #22
    //   147: ldc 389160971
    //   149: iastore
    //   150: dup
    //   151: bipush #23
    //   153: ldc 907870729
    //   155: iastore
    //   156: dup
    //   157: bipush #24
    //   159: ldc 389426184
    //   161: iastore
    //   162: dup
    //   163: bipush #25
    //   165: ldc 973875457
    //   167: iastore
    //   168: dup
    //   169: bipush #26
    //   171: ldc 372376604
    //   173: iastore
    //   174: dup
    //   175: bipush #27
    //   177: ldc 707731490
    //   179: iastore
    //   180: dup
    //   181: bipush #28
    //   183: ldc 1043334948
    //   185: iastore
    //   186: dup
    //   187: bipush #29
    //   189: ldc 439222784
    //   191: iastore
    //   192: dup
    //   193: bipush #30
    //   195: ldc 876216579
    //   197: iastore
    //   198: dup
    //   199: bipush #31
    //   201: ldc 455999525
    //   203: iastore
    //   204: astore #5
    //   206: bipush #8
    //   208: aload_3
    //   209: arraylength
    //   210: bipush #8
    //   212: irem
    //   213: isub
    //   214: istore #6
    //   216: aload_3
    //   217: arraylength
    //   218: iload #6
    //   220: iadd
    //   221: newarray byte
    //   223: astore #7
    //   225: iconst_0
    //   226: istore #8
    //   228: iload #8
    //   230: aload_3
    //   231: arraylength
    //   232: if_icmpge -> 251
    //   235: aload #7
    //   237: iload #8
    //   239: aload_3
    //   240: iload #8
    //   242: baload
    //   243: bastore
    //   244: iinc #8, 1
    //   247: iload_2
    //   248: ifeq -> 228
    //   251: aload_3
    //   252: arraylength
    //   253: istore #8
    //   255: iload #8
    //   257: aload #7
    //   259: arraylength
    //   260: if_icmpge -> 278
    //   263: aload #7
    //   265: iload #8
    //   267: iload #6
    //   269: i2b
    //   270: bastore
    //   271: iinc #8, 1
    //   274: iload_2
    //   275: ifeq -> 255
    //   278: aload #7
    //   280: astore_3
    //   281: bipush #64
    //   283: newarray int
    //   285: dup
    //   286: iconst_0
    //   287: ldc 16843776
    //   289: iastore
    //   290: dup
    //   291: iconst_1
    //   292: iconst_0
    //   293: iastore
    //   294: dup
    //   295: iconst_2
    //   296: ldc 65536
    //   298: iastore
    //   299: dup
    //   300: iconst_3
    //   301: ldc 16843780
    //   303: iastore
    //   304: dup
    //   305: iconst_4
    //   306: ldc 16842756
    //   308: iastore
    //   309: dup
    //   310: iconst_5
    //   311: ldc 66564
    //   313: iastore
    //   314: dup
    //   315: bipush #6
    //   317: iconst_4
    //   318: iastore
    //   319: dup
    //   320: bipush #7
    //   322: ldc 65536
    //   324: iastore
    //   325: dup
    //   326: bipush #8
    //   328: sipush #1024
    //   331: iastore
    //   332: dup
    //   333: bipush #9
    //   335: ldc 16843776
    //   337: iastore
    //   338: dup
    //   339: bipush #10
    //   341: ldc 16843780
    //   343: iastore
    //   344: dup
    //   345: bipush #11
    //   347: sipush #1024
    //   350: iastore
    //   351: dup
    //   352: bipush #12
    //   354: ldc 16778244
    //   356: iastore
    //   357: dup
    //   358: bipush #13
    //   360: ldc 16842756
    //   362: iastore
    //   363: dup
    //   364: bipush #14
    //   366: ldc 16777216
    //   368: iastore
    //   369: dup
    //   370: bipush #15
    //   372: iconst_4
    //   373: iastore
    //   374: dup
    //   375: bipush #16
    //   377: sipush #1028
    //   380: iastore
    //   381: dup
    //   382: bipush #17
    //   384: ldc 16778240
    //   386: iastore
    //   387: dup
    //   388: bipush #18
    //   390: ldc 16778240
    //   392: iastore
    //   393: dup
    //   394: bipush #19
    //   396: ldc 66560
    //   398: iastore
    //   399: dup
    //   400: bipush #20
    //   402: ldc 66560
    //   404: iastore
    //   405: dup
    //   406: bipush #21
    //   408: ldc 16842752
    //   410: iastore
    //   411: dup
    //   412: bipush #22
    //   414: ldc 16842752
    //   416: iastore
    //   417: dup
    //   418: bipush #23
    //   420: ldc 16778244
    //   422: iastore
    //   423: dup
    //   424: bipush #24
    //   426: ldc 65540
    //   428: iastore
    //   429: dup
    //   430: bipush #25
    //   432: ldc 16777220
    //   434: iastore
    //   435: dup
    //   436: bipush #26
    //   438: ldc 16777220
    //   440: iastore
    //   441: dup
    //   442: bipush #27
    //   444: ldc 65540
    //   446: iastore
    //   447: dup
    //   448: bipush #28
    //   450: iconst_0
    //   451: iastore
    //   452: dup
    //   453: bipush #29
    //   455: sipush #1028
    //   458: iastore
    //   459: dup
    //   460: bipush #30
    //   462: ldc 66564
    //   464: iastore
    //   465: dup
    //   466: bipush #31
    //   468: ldc 16777216
    //   470: iastore
    //   471: dup
    //   472: bipush #32
    //   474: ldc 65536
    //   476: iastore
    //   477: dup
    //   478: bipush #33
    //   480: ldc 16843780
    //   482: iastore
    //   483: dup
    //   484: bipush #34
    //   486: iconst_4
    //   487: iastore
    //   488: dup
    //   489: bipush #35
    //   491: ldc 16842752
    //   493: iastore
    //   494: dup
    //   495: bipush #36
    //   497: ldc 16843776
    //   499: iastore
    //   500: dup
    //   501: bipush #37
    //   503: ldc 16777216
    //   505: iastore
    //   506: dup
    //   507: bipush #38
    //   509: ldc 16777216
    //   511: iastore
    //   512: dup
    //   513: bipush #39
    //   515: sipush #1024
    //   518: iastore
    //   519: dup
    //   520: bipush #40
    //   522: ldc 16842756
    //   524: iastore
    //   525: dup
    //   526: bipush #41
    //   528: ldc 65536
    //   530: iastore
    //   531: dup
    //   532: bipush #42
    //   534: ldc 66560
    //   536: iastore
    //   537: dup
    //   538: bipush #43
    //   540: ldc 16777220
    //   542: iastore
    //   543: dup
    //   544: bipush #44
    //   546: sipush #1024
    //   549: iastore
    //   550: dup
    //   551: bipush #45
    //   553: iconst_4
    //   554: iastore
    //   555: dup
    //   556: bipush #46
    //   558: ldc 16778244
    //   560: iastore
    //   561: dup
    //   562: bipush #47
    //   564: ldc 66564
    //   566: iastore
    //   567: dup
    //   568: bipush #48
    //   570: ldc 16843780
    //   572: iastore
    //   573: dup
    //   574: bipush #49
    //   576: ldc 65540
    //   578: iastore
    //   579: dup
    //   580: bipush #50
    //   582: ldc 16842752
    //   584: iastore
    //   585: dup
    //   586: bipush #51
    //   588: ldc 16778244
    //   590: iastore
    //   591: dup
    //   592: bipush #52
    //   594: ldc 16777220
    //   596: iastore
    //   597: dup
    //   598: bipush #53
    //   600: sipush #1028
    //   603: iastore
    //   604: dup
    //   605: bipush #54
    //   607: ldc 66564
    //   609: iastore
    //   610: dup
    //   611: bipush #55
    //   613: ldc 16843776
    //   615: iastore
    //   616: dup
    //   617: bipush #56
    //   619: sipush #1028
    //   622: iastore
    //   623: dup
    //   624: bipush #57
    //   626: ldc 16778240
    //   628: iastore
    //   629: dup
    //   630: bipush #58
    //   632: ldc 16778240
    //   634: iastore
    //   635: dup
    //   636: bipush #59
    //   638: iconst_0
    //   639: iastore
    //   640: dup
    //   641: bipush #60
    //   643: ldc 65540
    //   645: iastore
    //   646: dup
    //   647: bipush #61
    //   649: ldc 66560
    //   651: iastore
    //   652: dup
    //   653: bipush #62
    //   655: iconst_0
    //   656: iastore
    //   657: dup
    //   658: bipush #63
    //   660: ldc 16842756
    //   662: iastore
    //   663: astore #8
    //   665: bipush #64
    //   667: newarray int
    //   669: dup
    //   670: iconst_0
    //   671: ldc -2146402272
    //   673: iastore
    //   674: dup
    //   675: iconst_1
    //   676: ldc -2147450880
    //   678: iastore
    //   679: dup
    //   680: iconst_2
    //   681: ldc 32768
    //   683: iastore
    //   684: dup
    //   685: iconst_3
    //   686: ldc 1081376
    //   688: iastore
    //   689: dup
    //   690: iconst_4
    //   691: ldc 1048576
    //   693: iastore
    //   694: dup
    //   695: iconst_5
    //   696: bipush #32
    //   698: iastore
    //   699: dup
    //   700: bipush #6
    //   702: ldc -2146435040
    //   704: iastore
    //   705: dup
    //   706: bipush #7
    //   708: ldc -2147450848
    //   710: iastore
    //   711: dup
    //   712: bipush #8
    //   714: ldc -2147483616
    //   716: iastore
    //   717: dup
    //   718: bipush #9
    //   720: ldc -2146402272
    //   722: iastore
    //   723: dup
    //   724: bipush #10
    //   726: ldc -2146402304
    //   728: iastore
    //   729: dup
    //   730: bipush #11
    //   732: ldc -2147483648
    //   734: iastore
    //   735: dup
    //   736: bipush #12
    //   738: ldc -2147450880
    //   740: iastore
    //   741: dup
    //   742: bipush #13
    //   744: ldc 1048576
    //   746: iastore
    //   747: dup
    //   748: bipush #14
    //   750: bipush #32
    //   752: iastore
    //   753: dup
    //   754: bipush #15
    //   756: ldc -2146435040
    //   758: iastore
    //   759: dup
    //   760: bipush #16
    //   762: ldc 1081344
    //   764: iastore
    //   765: dup
    //   766: bipush #17
    //   768: ldc 1048608
    //   770: iastore
    //   771: dup
    //   772: bipush #18
    //   774: ldc -2147450848
    //   776: iastore
    //   777: dup
    //   778: bipush #19
    //   780: iconst_0
    //   781: iastore
    //   782: dup
    //   783: bipush #20
    //   785: ldc -2147483648
    //   787: iastore
    //   788: dup
    //   789: bipush #21
    //   791: ldc 32768
    //   793: iastore
    //   794: dup
    //   795: bipush #22
    //   797: ldc 1081376
    //   799: iastore
    //   800: dup
    //   801: bipush #23
    //   803: ldc -2146435072
    //   805: iastore
    //   806: dup
    //   807: bipush #24
    //   809: ldc 1048608
    //   811: iastore
    //   812: dup
    //   813: bipush #25
    //   815: ldc -2147483616
    //   817: iastore
    //   818: dup
    //   819: bipush #26
    //   821: iconst_0
    //   822: iastore
    //   823: dup
    //   824: bipush #27
    //   826: ldc 1081344
    //   828: iastore
    //   829: dup
    //   830: bipush #28
    //   832: ldc 32800
    //   834: iastore
    //   835: dup
    //   836: bipush #29
    //   838: ldc -2146402304
    //   840: iastore
    //   841: dup
    //   842: bipush #30
    //   844: ldc -2146435072
    //   846: iastore
    //   847: dup
    //   848: bipush #31
    //   850: ldc 32800
    //   852: iastore
    //   853: dup
    //   854: bipush #32
    //   856: iconst_0
    //   857: iastore
    //   858: dup
    //   859: bipush #33
    //   861: ldc 1081376
    //   863: iastore
    //   864: dup
    //   865: bipush #34
    //   867: ldc -2146435040
    //   869: iastore
    //   870: dup
    //   871: bipush #35
    //   873: ldc 1048576
    //   875: iastore
    //   876: dup
    //   877: bipush #36
    //   879: ldc -2147450848
    //   881: iastore
    //   882: dup
    //   883: bipush #37
    //   885: ldc -2146435072
    //   887: iastore
    //   888: dup
    //   889: bipush #38
    //   891: ldc -2146402304
    //   893: iastore
    //   894: dup
    //   895: bipush #39
    //   897: ldc 32768
    //   899: iastore
    //   900: dup
    //   901: bipush #40
    //   903: ldc -2146435072
    //   905: iastore
    //   906: dup
    //   907: bipush #41
    //   909: ldc -2147450880
    //   911: iastore
    //   912: dup
    //   913: bipush #42
    //   915: bipush #32
    //   917: iastore
    //   918: dup
    //   919: bipush #43
    //   921: ldc -2146402272
    //   923: iastore
    //   924: dup
    //   925: bipush #44
    //   927: ldc 1081376
    //   929: iastore
    //   930: dup
    //   931: bipush #45
    //   933: bipush #32
    //   935: iastore
    //   936: dup
    //   937: bipush #46
    //   939: ldc 32768
    //   941: iastore
    //   942: dup
    //   943: bipush #47
    //   945: ldc -2147483648
    //   947: iastore
    //   948: dup
    //   949: bipush #48
    //   951: ldc 32800
    //   953: iastore
    //   954: dup
    //   955: bipush #49
    //   957: ldc -2146402304
    //   959: iastore
    //   960: dup
    //   961: bipush #50
    //   963: ldc 1048576
    //   965: iastore
    //   966: dup
    //   967: bipush #51
    //   969: ldc -2147483616
    //   971: iastore
    //   972: dup
    //   973: bipush #52
    //   975: ldc 1048608
    //   977: iastore
    //   978: dup
    //   979: bipush #53
    //   981: ldc -2147450848
    //   983: iastore
    //   984: dup
    //   985: bipush #54
    //   987: ldc -2147483616
    //   989: iastore
    //   990: dup
    //   991: bipush #55
    //   993: ldc 1048608
    //   995: iastore
    //   996: dup
    //   997: bipush #56
    //   999: ldc 1081344
    //   1001: iastore
    //   1002: dup
    //   1003: bipush #57
    //   1005: iconst_0
    //   1006: iastore
    //   1007: dup
    //   1008: bipush #58
    //   1010: ldc -2147450880
    //   1012: iastore
    //   1013: dup
    //   1014: bipush #59
    //   1016: ldc 32800
    //   1018: iastore
    //   1019: dup
    //   1020: bipush #60
    //   1022: ldc -2147483648
    //   1024: iastore
    //   1025: dup
    //   1026: bipush #61
    //   1028: ldc -2146435040
    //   1030: iastore
    //   1031: dup
    //   1032: bipush #62
    //   1034: ldc -2146402272
    //   1036: iastore
    //   1037: dup
    //   1038: bipush #63
    //   1040: ldc 1081344
    //   1042: iastore
    //   1043: astore #9
    //   1045: bipush #64
    //   1047: newarray int
    //   1049: dup
    //   1050: iconst_0
    //   1051: sipush #520
    //   1054: iastore
    //   1055: dup
    //   1056: iconst_1
    //   1057: ldc 134349312
    //   1059: iastore
    //   1060: dup
    //   1061: iconst_2
    //   1062: iconst_0
    //   1063: iastore
    //   1064: dup
    //   1065: iconst_3
    //   1066: ldc 134348808
    //   1068: iastore
    //   1069: dup
    //   1070: iconst_4
    //   1071: ldc 134218240
    //   1073: iastore
    //   1074: dup
    //   1075: iconst_5
    //   1076: iconst_0
    //   1077: iastore
    //   1078: dup
    //   1079: bipush #6
    //   1081: ldc 131592
    //   1083: iastore
    //   1084: dup
    //   1085: bipush #7
    //   1087: ldc 134218240
    //   1089: iastore
    //   1090: dup
    //   1091: bipush #8
    //   1093: ldc 131080
    //   1095: iastore
    //   1096: dup
    //   1097: bipush #9
    //   1099: ldc 134217736
    //   1101: iastore
    //   1102: dup
    //   1103: bipush #10
    //   1105: ldc 134217736
    //   1107: iastore
    //   1108: dup
    //   1109: bipush #11
    //   1111: ldc 131072
    //   1113: iastore
    //   1114: dup
    //   1115: bipush #12
    //   1117: ldc 134349320
    //   1119: iastore
    //   1120: dup
    //   1121: bipush #13
    //   1123: ldc 131080
    //   1125: iastore
    //   1126: dup
    //   1127: bipush #14
    //   1129: ldc 134348800
    //   1131: iastore
    //   1132: dup
    //   1133: bipush #15
    //   1135: sipush #520
    //   1138: iastore
    //   1139: dup
    //   1140: bipush #16
    //   1142: ldc 134217728
    //   1144: iastore
    //   1145: dup
    //   1146: bipush #17
    //   1148: bipush #8
    //   1150: iastore
    //   1151: dup
    //   1152: bipush #18
    //   1154: ldc 134349312
    //   1156: iastore
    //   1157: dup
    //   1158: bipush #19
    //   1160: sipush #512
    //   1163: iastore
    //   1164: dup
    //   1165: bipush #20
    //   1167: ldc 131584
    //   1169: iastore
    //   1170: dup
    //   1171: bipush #21
    //   1173: ldc 134348800
    //   1175: iastore
    //   1176: dup
    //   1177: bipush #22
    //   1179: ldc 134348808
    //   1181: iastore
    //   1182: dup
    //   1183: bipush #23
    //   1185: ldc 131592
    //   1187: iastore
    //   1188: dup
    //   1189: bipush #24
    //   1191: ldc 134218248
    //   1193: iastore
    //   1194: dup
    //   1195: bipush #25
    //   1197: ldc 131584
    //   1199: iastore
    //   1200: dup
    //   1201: bipush #26
    //   1203: ldc 131072
    //   1205: iastore
    //   1206: dup
    //   1207: bipush #27
    //   1209: ldc 134218248
    //   1211: iastore
    //   1212: dup
    //   1213: bipush #28
    //   1215: bipush #8
    //   1217: iastore
    //   1218: dup
    //   1219: bipush #29
    //   1221: ldc 134349320
    //   1223: iastore
    //   1224: dup
    //   1225: bipush #30
    //   1227: sipush #512
    //   1230: iastore
    //   1231: dup
    //   1232: bipush #31
    //   1234: ldc 134217728
    //   1236: iastore
    //   1237: dup
    //   1238: bipush #32
    //   1240: ldc 134349312
    //   1242: iastore
    //   1243: dup
    //   1244: bipush #33
    //   1246: ldc 134217728
    //   1248: iastore
    //   1249: dup
    //   1250: bipush #34
    //   1252: ldc 131080
    //   1254: iastore
    //   1255: dup
    //   1256: bipush #35
    //   1258: sipush #520
    //   1261: iastore
    //   1262: dup
    //   1263: bipush #36
    //   1265: ldc 131072
    //   1267: iastore
    //   1268: dup
    //   1269: bipush #37
    //   1271: ldc 134349312
    //   1273: iastore
    //   1274: dup
    //   1275: bipush #38
    //   1277: ldc 134218240
    //   1279: iastore
    //   1280: dup
    //   1281: bipush #39
    //   1283: iconst_0
    //   1284: iastore
    //   1285: dup
    //   1286: bipush #40
    //   1288: sipush #512
    //   1291: iastore
    //   1292: dup
    //   1293: bipush #41
    //   1295: ldc 131080
    //   1297: iastore
    //   1298: dup
    //   1299: bipush #42
    //   1301: ldc 134349320
    //   1303: iastore
    //   1304: dup
    //   1305: bipush #43
    //   1307: ldc 134218240
    //   1309: iastore
    //   1310: dup
    //   1311: bipush #44
    //   1313: ldc 134217736
    //   1315: iastore
    //   1316: dup
    //   1317: bipush #45
    //   1319: sipush #512
    //   1322: iastore
    //   1323: dup
    //   1324: bipush #46
    //   1326: iconst_0
    //   1327: iastore
    //   1328: dup
    //   1329: bipush #47
    //   1331: ldc 134348808
    //   1333: iastore
    //   1334: dup
    //   1335: bipush #48
    //   1337: ldc 134218248
    //   1339: iastore
    //   1340: dup
    //   1341: bipush #49
    //   1343: ldc 131072
    //   1345: iastore
    //   1346: dup
    //   1347: bipush #50
    //   1349: ldc 134217728
    //   1351: iastore
    //   1352: dup
    //   1353: bipush #51
    //   1355: ldc 134349320
    //   1357: iastore
    //   1358: dup
    //   1359: bipush #52
    //   1361: bipush #8
    //   1363: iastore
    //   1364: dup
    //   1365: bipush #53
    //   1367: ldc 131592
    //   1369: iastore
    //   1370: dup
    //   1371: bipush #54
    //   1373: ldc 131584
    //   1375: iastore
    //   1376: dup
    //   1377: bipush #55
    //   1379: ldc 134217736
    //   1381: iastore
    //   1382: dup
    //   1383: bipush #56
    //   1385: ldc 134348800
    //   1387: iastore
    //   1388: dup
    //   1389: bipush #57
    //   1391: ldc 134218248
    //   1393: iastore
    //   1394: dup
    //   1395: bipush #58
    //   1397: sipush #520
    //   1400: iastore
    //   1401: dup
    //   1402: bipush #59
    //   1404: ldc 134348800
    //   1406: iastore
    //   1407: dup
    //   1408: bipush #60
    //   1410: ldc 131592
    //   1412: iastore
    //   1413: dup
    //   1414: bipush #61
    //   1416: bipush #8
    //   1418: iastore
    //   1419: dup
    //   1420: bipush #62
    //   1422: ldc 134348808
    //   1424: iastore
    //   1425: dup
    //   1426: bipush #63
    //   1428: ldc 131584
    //   1430: iastore
    //   1431: astore #10
    //   1433: bipush #64
    //   1435: newarray int
    //   1437: dup
    //   1438: iconst_0
    //   1439: ldc 8396801
    //   1441: iastore
    //   1442: dup
    //   1443: iconst_1
    //   1444: sipush #8321
    //   1447: iastore
    //   1448: dup
    //   1449: iconst_2
    //   1450: sipush #8321
    //   1453: iastore
    //   1454: dup
    //   1455: iconst_3
    //   1456: sipush #128
    //   1459: iastore
    //   1460: dup
    //   1461: iconst_4
    //   1462: ldc 8396928
    //   1464: iastore
    //   1465: dup
    //   1466: iconst_5
    //   1467: ldc 8388737
    //   1469: iastore
    //   1470: dup
    //   1471: bipush #6
    //   1473: ldc 8388609
    //   1475: iastore
    //   1476: dup
    //   1477: bipush #7
    //   1479: sipush #8193
    //   1482: iastore
    //   1483: dup
    //   1484: bipush #8
    //   1486: iconst_0
    //   1487: iastore
    //   1488: dup
    //   1489: bipush #9
    //   1491: ldc 8396800
    //   1493: iastore
    //   1494: dup
    //   1495: bipush #10
    //   1497: ldc 8396800
    //   1499: iastore
    //   1500: dup
    //   1501: bipush #11
    //   1503: ldc 8396929
    //   1505: iastore
    //   1506: dup
    //   1507: bipush #12
    //   1509: sipush #129
    //   1512: iastore
    //   1513: dup
    //   1514: bipush #13
    //   1516: iconst_0
    //   1517: iastore
    //   1518: dup
    //   1519: bipush #14
    //   1521: ldc 8388736
    //   1523: iastore
    //   1524: dup
    //   1525: bipush #15
    //   1527: ldc 8388609
    //   1529: iastore
    //   1530: dup
    //   1531: bipush #16
    //   1533: iconst_1
    //   1534: iastore
    //   1535: dup
    //   1536: bipush #17
    //   1538: sipush #8192
    //   1541: iastore
    //   1542: dup
    //   1543: bipush #18
    //   1545: ldc 8388608
    //   1547: iastore
    //   1548: dup
    //   1549: bipush #19
    //   1551: ldc 8396801
    //   1553: iastore
    //   1554: dup
    //   1555: bipush #20
    //   1557: sipush #128
    //   1560: iastore
    //   1561: dup
    //   1562: bipush #21
    //   1564: ldc 8388608
    //   1566: iastore
    //   1567: dup
    //   1568: bipush #22
    //   1570: sipush #8193
    //   1573: iastore
    //   1574: dup
    //   1575: bipush #23
    //   1577: sipush #8320
    //   1580: iastore
    //   1581: dup
    //   1582: bipush #24
    //   1584: ldc 8388737
    //   1586: iastore
    //   1587: dup
    //   1588: bipush #25
    //   1590: iconst_1
    //   1591: iastore
    //   1592: dup
    //   1593: bipush #26
    //   1595: sipush #8320
    //   1598: iastore
    //   1599: dup
    //   1600: bipush #27
    //   1602: ldc 8388736
    //   1604: iastore
    //   1605: dup
    //   1606: bipush #28
    //   1608: sipush #8192
    //   1611: iastore
    //   1612: dup
    //   1613: bipush #29
    //   1615: ldc 8396928
    //   1617: iastore
    //   1618: dup
    //   1619: bipush #30
    //   1621: ldc 8396929
    //   1623: iastore
    //   1624: dup
    //   1625: bipush #31
    //   1627: sipush #129
    //   1630: iastore
    //   1631: dup
    //   1632: bipush #32
    //   1634: ldc 8388736
    //   1636: iastore
    //   1637: dup
    //   1638: bipush #33
    //   1640: ldc 8388609
    //   1642: iastore
    //   1643: dup
    //   1644: bipush #34
    //   1646: ldc 8396800
    //   1648: iastore
    //   1649: dup
    //   1650: bipush #35
    //   1652: ldc 8396929
    //   1654: iastore
    //   1655: dup
    //   1656: bipush #36
    //   1658: sipush #129
    //   1661: iastore
    //   1662: dup
    //   1663: bipush #37
    //   1665: iconst_0
    //   1666: iastore
    //   1667: dup
    //   1668: bipush #38
    //   1670: iconst_0
    //   1671: iastore
    //   1672: dup
    //   1673: bipush #39
    //   1675: ldc 8396800
    //   1677: iastore
    //   1678: dup
    //   1679: bipush #40
    //   1681: sipush #8320
    //   1684: iastore
    //   1685: dup
    //   1686: bipush #41
    //   1688: ldc 8388736
    //   1690: iastore
    //   1691: dup
    //   1692: bipush #42
    //   1694: ldc 8388737
    //   1696: iastore
    //   1697: dup
    //   1698: bipush #43
    //   1700: iconst_1
    //   1701: iastore
    //   1702: dup
    //   1703: bipush #44
    //   1705: ldc 8396801
    //   1707: iastore
    //   1708: dup
    //   1709: bipush #45
    //   1711: sipush #8321
    //   1714: iastore
    //   1715: dup
    //   1716: bipush #46
    //   1718: sipush #8321
    //   1721: iastore
    //   1722: dup
    //   1723: bipush #47
    //   1725: sipush #128
    //   1728: iastore
    //   1729: dup
    //   1730: bipush #48
    //   1732: ldc 8396929
    //   1734: iastore
    //   1735: dup
    //   1736: bipush #49
    //   1738: sipush #129
    //   1741: iastore
    //   1742: dup
    //   1743: bipush #50
    //   1745: iconst_1
    //   1746: iastore
    //   1747: dup
    //   1748: bipush #51
    //   1750: sipush #8192
    //   1753: iastore
    //   1754: dup
    //   1755: bipush #52
    //   1757: ldc 8388609
    //   1759: iastore
    //   1760: dup
    //   1761: bipush #53
    //   1763: sipush #8193
    //   1766: iastore
    //   1767: dup
    //   1768: bipush #54
    //   1770: ldc 8396928
    //   1772: iastore
    //   1773: dup
    //   1774: bipush #55
    //   1776: ldc 8388737
    //   1778: iastore
    //   1779: dup
    //   1780: bipush #56
    //   1782: sipush #8193
    //   1785: iastore
    //   1786: dup
    //   1787: bipush #57
    //   1789: sipush #8320
    //   1792: iastore
    //   1793: dup
    //   1794: bipush #58
    //   1796: ldc 8388608
    //   1798: iastore
    //   1799: dup
    //   1800: bipush #59
    //   1802: ldc 8396801
    //   1804: iastore
    //   1805: dup
    //   1806: bipush #60
    //   1808: sipush #128
    //   1811: iastore
    //   1812: dup
    //   1813: bipush #61
    //   1815: ldc 8388608
    //   1817: iastore
    //   1818: dup
    //   1819: bipush #62
    //   1821: sipush #8192
    //   1824: iastore
    //   1825: dup
    //   1826: bipush #63
    //   1828: ldc 8396928
    //   1830: iastore
    //   1831: astore #11
    //   1833: bipush #64
    //   1835: newarray int
    //   1837: dup
    //   1838: iconst_0
    //   1839: sipush #256
    //   1842: iastore
    //   1843: dup
    //   1844: iconst_1
    //   1845: ldc 34078976
    //   1847: iastore
    //   1848: dup
    //   1849: iconst_2
    //   1850: ldc 34078720
    //   1852: iastore
    //   1853: dup
    //   1854: iconst_3
    //   1855: ldc 1107296512
    //   1857: iastore
    //   1858: dup
    //   1859: iconst_4
    //   1860: ldc 524288
    //   1862: iastore
    //   1863: dup
    //   1864: iconst_5
    //   1865: sipush #256
    //   1868: iastore
    //   1869: dup
    //   1870: bipush #6
    //   1872: ldc 1073741824
    //   1874: iastore
    //   1875: dup
    //   1876: bipush #7
    //   1878: ldc 34078720
    //   1880: iastore
    //   1881: dup
    //   1882: bipush #8
    //   1884: ldc 1074266368
    //   1886: iastore
    //   1887: dup
    //   1888: bipush #9
    //   1890: ldc 524288
    //   1892: iastore
    //   1893: dup
    //   1894: bipush #10
    //   1896: ldc 33554688
    //   1898: iastore
    //   1899: dup
    //   1900: bipush #11
    //   1902: ldc 1074266368
    //   1904: iastore
    //   1905: dup
    //   1906: bipush #12
    //   1908: ldc 1107296512
    //   1910: iastore
    //   1911: dup
    //   1912: bipush #13
    //   1914: ldc 1107820544
    //   1916: iastore
    //   1917: dup
    //   1918: bipush #14
    //   1920: ldc 524544
    //   1922: iastore
    //   1923: dup
    //   1924: bipush #15
    //   1926: ldc 1073741824
    //   1928: iastore
    //   1929: dup
    //   1930: bipush #16
    //   1932: ldc 33554432
    //   1934: iastore
    //   1935: dup
    //   1936: bipush #17
    //   1938: ldc 1074266112
    //   1940: iastore
    //   1941: dup
    //   1942: bipush #18
    //   1944: ldc 1074266112
    //   1946: iastore
    //   1947: dup
    //   1948: bipush #19
    //   1950: iconst_0
    //   1951: iastore
    //   1952: dup
    //   1953: bipush #20
    //   1955: ldc 1073742080
    //   1957: iastore
    //   1958: dup
    //   1959: bipush #21
    //   1961: ldc 1107820800
    //   1963: iastore
    //   1964: dup
    //   1965: bipush #22
    //   1967: ldc 1107820800
    //   1969: iastore
    //   1970: dup
    //   1971: bipush #23
    //   1973: ldc 33554688
    //   1975: iastore
    //   1976: dup
    //   1977: bipush #24
    //   1979: ldc 1107820544
    //   1981: iastore
    //   1982: dup
    //   1983: bipush #25
    //   1985: ldc 1073742080
    //   1987: iastore
    //   1988: dup
    //   1989: bipush #26
    //   1991: iconst_0
    //   1992: iastore
    //   1993: dup
    //   1994: bipush #27
    //   1996: ldc 1107296256
    //   1998: iastore
    //   1999: dup
    //   2000: bipush #28
    //   2002: ldc 34078976
    //   2004: iastore
    //   2005: dup
    //   2006: bipush #29
    //   2008: ldc 33554432
    //   2010: iastore
    //   2011: dup
    //   2012: bipush #30
    //   2014: ldc 1107296256
    //   2016: iastore
    //   2017: dup
    //   2018: bipush #31
    //   2020: ldc 524544
    //   2022: iastore
    //   2023: dup
    //   2024: bipush #32
    //   2026: ldc 524288
    //   2028: iastore
    //   2029: dup
    //   2030: bipush #33
    //   2032: ldc 1107296512
    //   2034: iastore
    //   2035: dup
    //   2036: bipush #34
    //   2038: sipush #256
    //   2041: iastore
    //   2042: dup
    //   2043: bipush #35
    //   2045: ldc 33554432
    //   2047: iastore
    //   2048: dup
    //   2049: bipush #36
    //   2051: ldc 1073741824
    //   2053: iastore
    //   2054: dup
    //   2055: bipush #37
    //   2057: ldc 34078720
    //   2059: iastore
    //   2060: dup
    //   2061: bipush #38
    //   2063: ldc 1107296512
    //   2065: iastore
    //   2066: dup
    //   2067: bipush #39
    //   2069: ldc 1074266368
    //   2071: iastore
    //   2072: dup
    //   2073: bipush #40
    //   2075: ldc 33554688
    //   2077: iastore
    //   2078: dup
    //   2079: bipush #41
    //   2081: ldc 1073741824
    //   2083: iastore
    //   2084: dup
    //   2085: bipush #42
    //   2087: ldc 1107820544
    //   2089: iastore
    //   2090: dup
    //   2091: bipush #43
    //   2093: ldc 34078976
    //   2095: iastore
    //   2096: dup
    //   2097: bipush #44
    //   2099: ldc 1074266368
    //   2101: iastore
    //   2102: dup
    //   2103: bipush #45
    //   2105: sipush #256
    //   2108: iastore
    //   2109: dup
    //   2110: bipush #46
    //   2112: ldc 33554432
    //   2114: iastore
    //   2115: dup
    //   2116: bipush #47
    //   2118: ldc 1107820544
    //   2120: iastore
    //   2121: dup
    //   2122: bipush #48
    //   2124: ldc 1107820800
    //   2126: iastore
    //   2127: dup
    //   2128: bipush #49
    //   2130: ldc 524544
    //   2132: iastore
    //   2133: dup
    //   2134: bipush #50
    //   2136: ldc 1107296256
    //   2138: iastore
    //   2139: dup
    //   2140: bipush #51
    //   2142: ldc 1107820800
    //   2144: iastore
    //   2145: dup
    //   2146: bipush #52
    //   2148: ldc 34078720
    //   2150: iastore
    //   2151: dup
    //   2152: bipush #53
    //   2154: iconst_0
    //   2155: iastore
    //   2156: dup
    //   2157: bipush #54
    //   2159: ldc 1074266112
    //   2161: iastore
    //   2162: dup
    //   2163: bipush #55
    //   2165: ldc 1107296256
    //   2167: iastore
    //   2168: dup
    //   2169: bipush #56
    //   2171: ldc 524544
    //   2173: iastore
    //   2174: dup
    //   2175: bipush #57
    //   2177: ldc 33554688
    //   2179: iastore
    //   2180: dup
    //   2181: bipush #58
    //   2183: ldc 1073742080
    //   2185: iastore
    //   2186: dup
    //   2187: bipush #59
    //   2189: ldc 524288
    //   2191: iastore
    //   2192: dup
    //   2193: bipush #60
    //   2195: iconst_0
    //   2196: iastore
    //   2197: dup
    //   2198: bipush #61
    //   2200: ldc 1074266112
    //   2202: iastore
    //   2203: dup
    //   2204: bipush #62
    //   2206: ldc 34078976
    //   2208: iastore
    //   2209: dup
    //   2210: bipush #63
    //   2212: ldc 1073742080
    //   2214: iastore
    //   2215: astore #12
    //   2217: bipush #64
    //   2219: newarray int
    //   2221: dup
    //   2222: iconst_0
    //   2223: ldc 536870928
    //   2225: iastore
    //   2226: dup
    //   2227: iconst_1
    //   2228: ldc 541065216
    //   2230: iastore
    //   2231: dup
    //   2232: iconst_2
    //   2233: sipush #16384
    //   2236: iastore
    //   2237: dup
    //   2238: iconst_3
    //   2239: ldc 541081616
    //   2241: iastore
    //   2242: dup
    //   2243: iconst_4
    //   2244: ldc 541065216
    //   2246: iastore
    //   2247: dup
    //   2248: iconst_5
    //   2249: bipush #16
    //   2251: iastore
    //   2252: dup
    //   2253: bipush #6
    //   2255: ldc 541081616
    //   2257: iastore
    //   2258: dup
    //   2259: bipush #7
    //   2261: ldc 4194304
    //   2263: iastore
    //   2264: dup
    //   2265: bipush #8
    //   2267: ldc 536887296
    //   2269: iastore
    //   2270: dup
    //   2271: bipush #9
    //   2273: ldc 4210704
    //   2275: iastore
    //   2276: dup
    //   2277: bipush #10
    //   2279: ldc 4194304
    //   2281: iastore
    //   2282: dup
    //   2283: bipush #11
    //   2285: ldc 536870928
    //   2287: iastore
    //   2288: dup
    //   2289: bipush #12
    //   2291: ldc 4194320
    //   2293: iastore
    //   2294: dup
    //   2295: bipush #13
    //   2297: ldc 536887296
    //   2299: iastore
    //   2300: dup
    //   2301: bipush #14
    //   2303: ldc 536870912
    //   2305: iastore
    //   2306: dup
    //   2307: bipush #15
    //   2309: sipush #16400
    //   2312: iastore
    //   2313: dup
    //   2314: bipush #16
    //   2316: iconst_0
    //   2317: iastore
    //   2318: dup
    //   2319: bipush #17
    //   2321: ldc 4194320
    //   2323: iastore
    //   2324: dup
    //   2325: bipush #18
    //   2327: ldc 536887312
    //   2329: iastore
    //   2330: dup
    //   2331: bipush #19
    //   2333: sipush #16384
    //   2336: iastore
    //   2337: dup
    //   2338: bipush #20
    //   2340: ldc 4210688
    //   2342: iastore
    //   2343: dup
    //   2344: bipush #21
    //   2346: ldc 536887312
    //   2348: iastore
    //   2349: dup
    //   2350: bipush #22
    //   2352: bipush #16
    //   2354: iastore
    //   2355: dup
    //   2356: bipush #23
    //   2358: ldc 541065232
    //   2360: iastore
    //   2361: dup
    //   2362: bipush #24
    //   2364: ldc 541065232
    //   2366: iastore
    //   2367: dup
    //   2368: bipush #25
    //   2370: iconst_0
    //   2371: iastore
    //   2372: dup
    //   2373: bipush #26
    //   2375: ldc 4210704
    //   2377: iastore
    //   2378: dup
    //   2379: bipush #27
    //   2381: ldc 541081600
    //   2383: iastore
    //   2384: dup
    //   2385: bipush #28
    //   2387: sipush #16400
    //   2390: iastore
    //   2391: dup
    //   2392: bipush #29
    //   2394: ldc 4210688
    //   2396: iastore
    //   2397: dup
    //   2398: bipush #30
    //   2400: ldc 541081600
    //   2402: iastore
    //   2403: dup
    //   2404: bipush #31
    //   2406: ldc 536870912
    //   2408: iastore
    //   2409: dup
    //   2410: bipush #32
    //   2412: ldc 536887296
    //   2414: iastore
    //   2415: dup
    //   2416: bipush #33
    //   2418: bipush #16
    //   2420: iastore
    //   2421: dup
    //   2422: bipush #34
    //   2424: ldc 541065232
    //   2426: iastore
    //   2427: dup
    //   2428: bipush #35
    //   2430: ldc 4210688
    //   2432: iastore
    //   2433: dup
    //   2434: bipush #36
    //   2436: ldc 541081616
    //   2438: iastore
    //   2439: dup
    //   2440: bipush #37
    //   2442: ldc 4194304
    //   2444: iastore
    //   2445: dup
    //   2446: bipush #38
    //   2448: sipush #16400
    //   2451: iastore
    //   2452: dup
    //   2453: bipush #39
    //   2455: ldc 536870928
    //   2457: iastore
    //   2458: dup
    //   2459: bipush #40
    //   2461: ldc 4194304
    //   2463: iastore
    //   2464: dup
    //   2465: bipush #41
    //   2467: ldc 536887296
    //   2469: iastore
    //   2470: dup
    //   2471: bipush #42
    //   2473: ldc 536870912
    //   2475: iastore
    //   2476: dup
    //   2477: bipush #43
    //   2479: sipush #16400
    //   2482: iastore
    //   2483: dup
    //   2484: bipush #44
    //   2486: ldc 536870928
    //   2488: iastore
    //   2489: dup
    //   2490: bipush #45
    //   2492: ldc 541081616
    //   2494: iastore
    //   2495: dup
    //   2496: bipush #46
    //   2498: ldc 4210688
    //   2500: iastore
    //   2501: dup
    //   2502: bipush #47
    //   2504: ldc 541065216
    //   2506: iastore
    //   2507: dup
    //   2508: bipush #48
    //   2510: ldc 4210704
    //   2512: iastore
    //   2513: dup
    //   2514: bipush #49
    //   2516: ldc 541081600
    //   2518: iastore
    //   2519: dup
    //   2520: bipush #50
    //   2522: iconst_0
    //   2523: iastore
    //   2524: dup
    //   2525: bipush #51
    //   2527: ldc 541065232
    //   2529: iastore
    //   2530: dup
    //   2531: bipush #52
    //   2533: bipush #16
    //   2535: iastore
    //   2536: dup
    //   2537: bipush #53
    //   2539: sipush #16384
    //   2542: iastore
    //   2543: dup
    //   2544: bipush #54
    //   2546: ldc 541065216
    //   2548: iastore
    //   2549: dup
    //   2550: bipush #55
    //   2552: ldc 4210704
    //   2554: iastore
    //   2555: dup
    //   2556: bipush #56
    //   2558: sipush #16384
    //   2561: iastore
    //   2562: dup
    //   2563: bipush #57
    //   2565: ldc 4194320
    //   2567: iastore
    //   2568: dup
    //   2569: bipush #58
    //   2571: ldc 536887312
    //   2573: iastore
    //   2574: dup
    //   2575: bipush #59
    //   2577: iconst_0
    //   2578: iastore
    //   2579: dup
    //   2580: bipush #60
    //   2582: ldc 541081600
    //   2584: iastore
    //   2585: dup
    //   2586: bipush #61
    //   2588: ldc 536870912
    //   2590: iastore
    //   2591: dup
    //   2592: bipush #62
    //   2594: ldc 4194320
    //   2596: iastore
    //   2597: dup
    //   2598: bipush #63
    //   2600: ldc 536887312
    //   2602: iastore
    //   2603: astore #13
    //   2605: bipush #64
    //   2607: newarray int
    //   2609: dup
    //   2610: iconst_0
    //   2611: ldc 2097152
    //   2613: iastore
    //   2614: dup
    //   2615: iconst_1
    //   2616: ldc 69206018
    //   2618: iastore
    //   2619: dup
    //   2620: iconst_2
    //   2621: ldc 67110914
    //   2623: iastore
    //   2624: dup
    //   2625: iconst_3
    //   2626: iconst_0
    //   2627: iastore
    //   2628: dup
    //   2629: iconst_4
    //   2630: sipush #2048
    //   2633: iastore
    //   2634: dup
    //   2635: iconst_5
    //   2636: ldc 67110914
    //   2638: iastore
    //   2639: dup
    //   2640: bipush #6
    //   2642: ldc 2099202
    //   2644: iastore
    //   2645: dup
    //   2646: bipush #7
    //   2648: ldc 69208064
    //   2650: iastore
    //   2651: dup
    //   2652: bipush #8
    //   2654: ldc 69208066
    //   2656: iastore
    //   2657: dup
    //   2658: bipush #9
    //   2660: ldc 2097152
    //   2662: iastore
    //   2663: dup
    //   2664: bipush #10
    //   2666: iconst_0
    //   2667: iastore
    //   2668: dup
    //   2669: bipush #11
    //   2671: ldc 67108866
    //   2673: iastore
    //   2674: dup
    //   2675: bipush #12
    //   2677: iconst_2
    //   2678: iastore
    //   2679: dup
    //   2680: bipush #13
    //   2682: ldc 67108864
    //   2684: iastore
    //   2685: dup
    //   2686: bipush #14
    //   2688: ldc 69206018
    //   2690: iastore
    //   2691: dup
    //   2692: bipush #15
    //   2694: sipush #2050
    //   2697: iastore
    //   2698: dup
    //   2699: bipush #16
    //   2701: ldc 67110912
    //   2703: iastore
    //   2704: dup
    //   2705: bipush #17
    //   2707: ldc 2099202
    //   2709: iastore
    //   2710: dup
    //   2711: bipush #18
    //   2713: ldc 2097154
    //   2715: iastore
    //   2716: dup
    //   2717: bipush #19
    //   2719: ldc 67110912
    //   2721: iastore
    //   2722: dup
    //   2723: bipush #20
    //   2725: ldc 67108866
    //   2727: iastore
    //   2728: dup
    //   2729: bipush #21
    //   2731: ldc 69206016
    //   2733: iastore
    //   2734: dup
    //   2735: bipush #22
    //   2737: ldc 69208064
    //   2739: iastore
    //   2740: dup
    //   2741: bipush #23
    //   2743: ldc 2097154
    //   2745: iastore
    //   2746: dup
    //   2747: bipush #24
    //   2749: ldc 69206016
    //   2751: iastore
    //   2752: dup
    //   2753: bipush #25
    //   2755: sipush #2048
    //   2758: iastore
    //   2759: dup
    //   2760: bipush #26
    //   2762: sipush #2050
    //   2765: iastore
    //   2766: dup
    //   2767: bipush #27
    //   2769: ldc 69208066
    //   2771: iastore
    //   2772: dup
    //   2773: bipush #28
    //   2775: ldc 2099200
    //   2777: iastore
    //   2778: dup
    //   2779: bipush #29
    //   2781: iconst_2
    //   2782: iastore
    //   2783: dup
    //   2784: bipush #30
    //   2786: ldc 67108864
    //   2788: iastore
    //   2789: dup
    //   2790: bipush #31
    //   2792: ldc 2099200
    //   2794: iastore
    //   2795: dup
    //   2796: bipush #32
    //   2798: ldc 67108864
    //   2800: iastore
    //   2801: dup
    //   2802: bipush #33
    //   2804: ldc 2099200
    //   2806: iastore
    //   2807: dup
    //   2808: bipush #34
    //   2810: ldc 2097152
    //   2812: iastore
    //   2813: dup
    //   2814: bipush #35
    //   2816: ldc 67110914
    //   2818: iastore
    //   2819: dup
    //   2820: bipush #36
    //   2822: ldc 67110914
    //   2824: iastore
    //   2825: dup
    //   2826: bipush #37
    //   2828: ldc 69206018
    //   2830: iastore
    //   2831: dup
    //   2832: bipush #38
    //   2834: ldc 69206018
    //   2836: iastore
    //   2837: dup
    //   2838: bipush #39
    //   2840: iconst_2
    //   2841: iastore
    //   2842: dup
    //   2843: bipush #40
    //   2845: ldc 2097154
    //   2847: iastore
    //   2848: dup
    //   2849: bipush #41
    //   2851: ldc 67108864
    //   2853: iastore
    //   2854: dup
    //   2855: bipush #42
    //   2857: ldc 67110912
    //   2859: iastore
    //   2860: dup
    //   2861: bipush #43
    //   2863: ldc 2097152
    //   2865: iastore
    //   2866: dup
    //   2867: bipush #44
    //   2869: ldc 69208064
    //   2871: iastore
    //   2872: dup
    //   2873: bipush #45
    //   2875: sipush #2050
    //   2878: iastore
    //   2879: dup
    //   2880: bipush #46
    //   2882: ldc 2099202
    //   2884: iastore
    //   2885: dup
    //   2886: bipush #47
    //   2888: ldc 69208064
    //   2890: iastore
    //   2891: dup
    //   2892: bipush #48
    //   2894: sipush #2050
    //   2897: iastore
    //   2898: dup
    //   2899: bipush #49
    //   2901: ldc 67108866
    //   2903: iastore
    //   2904: dup
    //   2905: bipush #50
    //   2907: ldc 69208066
    //   2909: iastore
    //   2910: dup
    //   2911: bipush #51
    //   2913: ldc 69206016
    //   2915: iastore
    //   2916: dup
    //   2917: bipush #52
    //   2919: ldc 2099200
    //   2921: iastore
    //   2922: dup
    //   2923: bipush #53
    //   2925: iconst_0
    //   2926: iastore
    //   2927: dup
    //   2928: bipush #54
    //   2930: iconst_2
    //   2931: iastore
    //   2932: dup
    //   2933: bipush #55
    //   2935: ldc 69208066
    //   2937: iastore
    //   2938: dup
    //   2939: bipush #56
    //   2941: iconst_0
    //   2942: iastore
    //   2943: dup
    //   2944: bipush #57
    //   2946: ldc 2099202
    //   2948: iastore
    //   2949: dup
    //   2950: bipush #58
    //   2952: ldc 69206016
    //   2954: iastore
    //   2955: dup
    //   2956: bipush #59
    //   2958: sipush #2048
    //   2961: iastore
    //   2962: dup
    //   2963: bipush #60
    //   2965: ldc 67108866
    //   2967: iastore
    //   2968: dup
    //   2969: bipush #61
    //   2971: ldc 67110912
    //   2973: iastore
    //   2974: dup
    //   2975: bipush #62
    //   2977: sipush #2048
    //   2980: iastore
    //   2981: dup
    //   2982: bipush #63
    //   2984: ldc 2097154
    //   2986: iastore
    //   2987: astore #14
    //   2989: bipush #64
    //   2991: newarray int
    //   2993: dup
    //   2994: iconst_0
    //   2995: ldc 268439616
    //   2997: iastore
    //   2998: dup
    //   2999: iconst_1
    //   3000: sipush #4096
    //   3003: iastore
    //   3004: dup
    //   3005: iconst_2
    //   3006: ldc 262144
    //   3008: iastore
    //   3009: dup
    //   3010: iconst_3
    //   3011: ldc 268701760
    //   3013: iastore
    //   3014: dup
    //   3015: iconst_4
    //   3016: ldc 268435456
    //   3018: iastore
    //   3019: dup
    //   3020: iconst_5
    //   3021: ldc 268439616
    //   3023: iastore
    //   3024: dup
    //   3025: bipush #6
    //   3027: bipush #64
    //   3029: iastore
    //   3030: dup
    //   3031: bipush #7
    //   3033: ldc 268435456
    //   3035: iastore
    //   3036: dup
    //   3037: bipush #8
    //   3039: ldc 262208
    //   3041: iastore
    //   3042: dup
    //   3043: bipush #9
    //   3045: ldc 268697600
    //   3047: iastore
    //   3048: dup
    //   3049: bipush #10
    //   3051: ldc 268701760
    //   3053: iastore
    //   3054: dup
    //   3055: bipush #11
    //   3057: ldc 266240
    //   3059: iastore
    //   3060: dup
    //   3061: bipush #12
    //   3063: ldc 268701696
    //   3065: iastore
    //   3066: dup
    //   3067: bipush #13
    //   3069: ldc 266304
    //   3071: iastore
    //   3072: dup
    //   3073: bipush #14
    //   3075: sipush #4096
    //   3078: iastore
    //   3079: dup
    //   3080: bipush #15
    //   3082: bipush #64
    //   3084: iastore
    //   3085: dup
    //   3086: bipush #16
    //   3088: ldc 268697600
    //   3090: iastore
    //   3091: dup
    //   3092: bipush #17
    //   3094: ldc 268435520
    //   3096: iastore
    //   3097: dup
    //   3098: bipush #18
    //   3100: ldc 268439552
    //   3102: iastore
    //   3103: dup
    //   3104: bipush #19
    //   3106: sipush #4160
    //   3109: iastore
    //   3110: dup
    //   3111: bipush #20
    //   3113: ldc 266240
    //   3115: iastore
    //   3116: dup
    //   3117: bipush #21
    //   3119: ldc 262208
    //   3121: iastore
    //   3122: dup
    //   3123: bipush #22
    //   3125: ldc 268697664
    //   3127: iastore
    //   3128: dup
    //   3129: bipush #23
    //   3131: ldc 268701696
    //   3133: iastore
    //   3134: dup
    //   3135: bipush #24
    //   3137: sipush #4160
    //   3140: iastore
    //   3141: dup
    //   3142: bipush #25
    //   3144: iconst_0
    //   3145: iastore
    //   3146: dup
    //   3147: bipush #26
    //   3149: iconst_0
    //   3150: iastore
    //   3151: dup
    //   3152: bipush #27
    //   3154: ldc 268697664
    //   3156: iastore
    //   3157: dup
    //   3158: bipush #28
    //   3160: ldc 268435520
    //   3162: iastore
    //   3163: dup
    //   3164: bipush #29
    //   3166: ldc 268439552
    //   3168: iastore
    //   3169: dup
    //   3170: bipush #30
    //   3172: ldc 266304
    //   3174: iastore
    //   3175: dup
    //   3176: bipush #31
    //   3178: ldc 262144
    //   3180: iastore
    //   3181: dup
    //   3182: bipush #32
    //   3184: ldc 266304
    //   3186: iastore
    //   3187: dup
    //   3188: bipush #33
    //   3190: ldc 262144
    //   3192: iastore
    //   3193: dup
    //   3194: bipush #34
    //   3196: ldc 268701696
    //   3198: iastore
    //   3199: dup
    //   3200: bipush #35
    //   3202: sipush #4096
    //   3205: iastore
    //   3206: dup
    //   3207: bipush #36
    //   3209: bipush #64
    //   3211: iastore
    //   3212: dup
    //   3213: bipush #37
    //   3215: ldc 268697664
    //   3217: iastore
    //   3218: dup
    //   3219: bipush #38
    //   3221: sipush #4096
    //   3224: iastore
    //   3225: dup
    //   3226: bipush #39
    //   3228: ldc 266304
    //   3230: iastore
    //   3231: dup
    //   3232: bipush #40
    //   3234: ldc 268439552
    //   3236: iastore
    //   3237: dup
    //   3238: bipush #41
    //   3240: bipush #64
    //   3242: iastore
    //   3243: dup
    //   3244: bipush #42
    //   3246: ldc 268435520
    //   3248: iastore
    //   3249: dup
    //   3250: bipush #43
    //   3252: ldc 268697600
    //   3254: iastore
    //   3255: dup
    //   3256: bipush #44
    //   3258: ldc 268697664
    //   3260: iastore
    //   3261: dup
    //   3262: bipush #45
    //   3264: ldc 268435456
    //   3266: iastore
    //   3267: dup
    //   3268: bipush #46
    //   3270: ldc 262144
    //   3272: iastore
    //   3273: dup
    //   3274: bipush #47
    //   3276: ldc 268439616
    //   3278: iastore
    //   3279: dup
    //   3280: bipush #48
    //   3282: iconst_0
    //   3283: iastore
    //   3284: dup
    //   3285: bipush #49
    //   3287: ldc 268701760
    //   3289: iastore
    //   3290: dup
    //   3291: bipush #50
    //   3293: ldc 262208
    //   3295: iastore
    //   3296: dup
    //   3297: bipush #51
    //   3299: ldc 268435520
    //   3301: iastore
    //   3302: dup
    //   3303: bipush #52
    //   3305: ldc 268697600
    //   3307: iastore
    //   3308: dup
    //   3309: bipush #53
    //   3311: ldc 268439552
    //   3313: iastore
    //   3314: dup
    //   3315: bipush #54
    //   3317: ldc 268439616
    //   3319: iastore
    //   3320: dup
    //   3321: bipush #55
    //   3323: iconst_0
    //   3324: iastore
    //   3325: dup
    //   3326: bipush #56
    //   3328: ldc 268701760
    //   3330: iastore
    //   3331: dup
    //   3332: bipush #57
    //   3334: ldc 266240
    //   3336: iastore
    //   3337: dup
    //   3338: bipush #58
    //   3340: ldc 266240
    //   3342: iastore
    //   3343: dup
    //   3344: bipush #59
    //   3346: sipush #4160
    //   3349: iastore
    //   3350: dup
    //   3351: bipush #60
    //   3353: sipush #4160
    //   3356: iastore
    //   3357: dup
    //   3358: bipush #61
    //   3360: ldc 262208
    //   3362: iastore
    //   3363: dup
    //   3364: bipush #62
    //   3366: ldc 268435456
    //   3368: iastore
    //   3369: dup
    //   3370: bipush #63
    //   3372: ldc 268701696
    //   3374: iastore
    //   3375: astore #15
    //   3377: aload_3
    //   3378: arraylength
    //   3379: istore #16
    //   3381: iconst_2
    //   3382: newarray int
    //   3384: astore #17
    //   3386: iload #16
    //   3388: newarray byte
    //   3390: astore #4
    //   3392: iload #16
    //   3394: bipush #8
    //   3396: idiv
    //   3397: istore #18
    //   3399: iconst_0
    //   3400: istore #19
    //   3402: iload #19
    //   3404: iload #18
    //   3406: if_icmpge -> 4320
    //   3409: iload #19
    //   3411: bipush #8
    //   3413: imul
    //   3414: istore #20
    //   3416: iconst_0
    //   3417: istore #21
    //   3419: iload #21
    //   3421: iconst_2
    //   3422: if_icmpge -> 3507
    //   3425: aload #17
    //   3427: iload #21
    //   3429: aload_3
    //   3430: iload #20
    //   3432: iload #21
    //   3434: iconst_4
    //   3435: imul
    //   3436: iadd
    //   3437: baload
    //   3438: sipush #255
    //   3441: iand
    //   3442: bipush #24
    //   3444: ishl
    //   3445: aload_3
    //   3446: iload #20
    //   3448: iload #21
    //   3450: iconst_4
    //   3451: imul
    //   3452: iadd
    //   3453: iconst_1
    //   3454: iadd
    //   3455: baload
    //   3456: sipush #255
    //   3459: iand
    //   3460: bipush #16
    //   3462: ishl
    //   3463: ior
    //   3464: aload_3
    //   3465: iload #20
    //   3467: iload #21
    //   3469: iconst_4
    //   3470: imul
    //   3471: iadd
    //   3472: iconst_2
    //   3473: iadd
    //   3474: baload
    //   3475: sipush #255
    //   3478: iand
    //   3479: bipush #8
    //   3481: ishl
    //   3482: ior
    //   3483: aload_3
    //   3484: iload #20
    //   3486: iload #21
    //   3488: iconst_4
    //   3489: imul
    //   3490: iadd
    //   3491: iconst_3
    //   3492: iadd
    //   3493: baload
    //   3494: sipush #255
    //   3497: iand
    //   3498: ior
    //   3499: iastore
    //   3500: iinc #21, 1
    //   3503: iload_2
    //   3504: ifeq -> 3419
    //   3507: iconst_0
    //   3508: istore #26
    //   3510: aload #17
    //   3512: iconst_0
    //   3513: iaload
    //   3514: istore #24
    //   3516: aload #17
    //   3518: iconst_1
    //   3519: iaload
    //   3520: istore #23
    //   3522: iload #24
    //   3524: iconst_4
    //   3525: iushr
    //   3526: iload #23
    //   3528: ixor
    //   3529: ldc 252645135
    //   3531: iand
    //   3532: istore #22
    //   3534: iload #23
    //   3536: iload #22
    //   3538: ixor
    //   3539: istore #23
    //   3541: iload #24
    //   3543: iload #22
    //   3545: iconst_4
    //   3546: ishl
    //   3547: ixor
    //   3548: istore #24
    //   3550: iload #24
    //   3552: bipush #16
    //   3554: iushr
    //   3555: iload #23
    //   3557: ixor
    //   3558: ldc 65535
    //   3560: iand
    //   3561: istore #22
    //   3563: iload #23
    //   3565: iload #22
    //   3567: ixor
    //   3568: istore #23
    //   3570: iload #24
    //   3572: iload #22
    //   3574: bipush #16
    //   3576: ishl
    //   3577: ixor
    //   3578: istore #24
    //   3580: iload #23
    //   3582: iconst_2
    //   3583: iushr
    //   3584: iload #24
    //   3586: ixor
    //   3587: ldc 858993459
    //   3589: iand
    //   3590: istore #22
    //   3592: iload #24
    //   3594: iload #22
    //   3596: ixor
    //   3597: istore #24
    //   3599: iload #23
    //   3601: iload #22
    //   3603: iconst_2
    //   3604: ishl
    //   3605: ixor
    //   3606: istore #23
    //   3608: iload #23
    //   3610: bipush #8
    //   3612: iushr
    //   3613: iload #24
    //   3615: ixor
    //   3616: ldc 16711935
    //   3618: iand
    //   3619: istore #22
    //   3621: iload #24
    //   3623: iload #22
    //   3625: ixor
    //   3626: istore #24
    //   3628: iload #23
    //   3630: iload #22
    //   3632: bipush #8
    //   3634: ishl
    //   3635: ixor
    //   3636: istore #23
    //   3638: iload #23
    //   3640: iconst_1
    //   3641: ishl
    //   3642: iload #23
    //   3644: bipush #31
    //   3646: iushr
    //   3647: iconst_1
    //   3648: iand
    //   3649: ior
    //   3650: istore #23
    //   3652: iload #24
    //   3654: iload #23
    //   3656: ixor
    //   3657: ldc -1431655766
    //   3659: iand
    //   3660: istore #22
    //   3662: iload #24
    //   3664: iload #22
    //   3666: ixor
    //   3667: istore #24
    //   3669: iload #23
    //   3671: iload #22
    //   3673: ixor
    //   3674: istore #23
    //   3676: iload #24
    //   3678: iconst_1
    //   3679: ishl
    //   3680: iload #24
    //   3682: bipush #31
    //   3684: iushr
    //   3685: iconst_1
    //   3686: iand
    //   3687: ior
    //   3688: istore #24
    //   3690: iconst_0
    //   3691: istore #25
    //   3693: iload #25
    //   3695: bipush #8
    //   3697: if_icmpge -> 4035
    //   3700: iload #23
    //   3702: bipush #28
    //   3704: ishl
    //   3705: iload #23
    //   3707: iconst_4
    //   3708: iushr
    //   3709: ior
    //   3710: istore #22
    //   3712: iload #22
    //   3714: aload #5
    //   3716: iload #26
    //   3718: iinc #26, 1
    //   3721: iaload
    //   3722: ixor
    //   3723: istore #22
    //   3725: aload #14
    //   3727: iload #22
    //   3729: bipush #63
    //   3731: iand
    //   3732: iaload
    //   3733: istore #21
    //   3735: iload #21
    //   3737: aload #12
    //   3739: iload #22
    //   3741: bipush #8
    //   3743: iushr
    //   3744: bipush #63
    //   3746: iand
    //   3747: iaload
    //   3748: ior
    //   3749: istore #21
    //   3751: iload #21
    //   3753: aload #10
    //   3755: iload #22
    //   3757: bipush #16
    //   3759: iushr
    //   3760: bipush #63
    //   3762: iand
    //   3763: iaload
    //   3764: ior
    //   3765: istore #21
    //   3767: iload #21
    //   3769: aload #8
    //   3771: iload #22
    //   3773: bipush #24
    //   3775: iushr
    //   3776: bipush #63
    //   3778: iand
    //   3779: iaload
    //   3780: ior
    //   3781: istore #21
    //   3783: iload #23
    //   3785: aload #5
    //   3787: iload #26
    //   3789: iinc #26, 1
    //   3792: iaload
    //   3793: ixor
    //   3794: istore #22
    //   3796: iload #21
    //   3798: aload #15
    //   3800: iload #22
    //   3802: bipush #63
    //   3804: iand
    //   3805: iaload
    //   3806: ior
    //   3807: istore #21
    //   3809: iload #21
    //   3811: aload #13
    //   3813: iload #22
    //   3815: bipush #8
    //   3817: iushr
    //   3818: bipush #63
    //   3820: iand
    //   3821: iaload
    //   3822: ior
    //   3823: istore #21
    //   3825: iload #21
    //   3827: aload #11
    //   3829: iload #22
    //   3831: bipush #16
    //   3833: iushr
    //   3834: bipush #63
    //   3836: iand
    //   3837: iaload
    //   3838: ior
    //   3839: istore #21
    //   3841: iload #21
    //   3843: aload #9
    //   3845: iload #22
    //   3847: bipush #24
    //   3849: iushr
    //   3850: bipush #63
    //   3852: iand
    //   3853: iaload
    //   3854: ior
    //   3855: istore #21
    //   3857: iload #24
    //   3859: iload #21
    //   3861: ixor
    //   3862: istore #24
    //   3864: iload #24
    //   3866: bipush #28
    //   3868: ishl
    //   3869: iload #24
    //   3871: iconst_4
    //   3872: iushr
    //   3873: ior
    //   3874: istore #22
    //   3876: iload #22
    //   3878: aload #5
    //   3880: iload #26
    //   3882: iinc #26, 1
    //   3885: iaload
    //   3886: ixor
    //   3887: istore #22
    //   3889: aload #14
    //   3891: iload #22
    //   3893: bipush #63
    //   3895: iand
    //   3896: iaload
    //   3897: istore #21
    //   3899: iload #21
    //   3901: aload #12
    //   3903: iload #22
    //   3905: bipush #8
    //   3907: iushr
    //   3908: bipush #63
    //   3910: iand
    //   3911: iaload
    //   3912: ior
    //   3913: istore #21
    //   3915: iload #21
    //   3917: aload #10
    //   3919: iload #22
    //   3921: bipush #16
    //   3923: iushr
    //   3924: bipush #63
    //   3926: iand
    //   3927: iaload
    //   3928: ior
    //   3929: istore #21
    //   3931: iload #21
    //   3933: aload #8
    //   3935: iload #22
    //   3937: bipush #24
    //   3939: iushr
    //   3940: bipush #63
    //   3942: iand
    //   3943: iaload
    //   3944: ior
    //   3945: istore #21
    //   3947: iload #24
    //   3949: aload #5
    //   3951: iload #26
    //   3953: iinc #26, 1
    //   3956: iaload
    //   3957: ixor
    //   3958: istore #22
    //   3960: iload #21
    //   3962: aload #15
    //   3964: iload #22
    //   3966: bipush #63
    //   3968: iand
    //   3969: iaload
    //   3970: ior
    //   3971: istore #21
    //   3973: iload #21
    //   3975: aload #13
    //   3977: iload #22
    //   3979: bipush #8
    //   3981: iushr
    //   3982: bipush #63
    //   3984: iand
    //   3985: iaload
    //   3986: ior
    //   3987: istore #21
    //   3989: iload #21
    //   3991: aload #11
    //   3993: iload #22
    //   3995: bipush #16
    //   3997: iushr
    //   3998: bipush #63
    //   4000: iand
    //   4001: iaload
    //   4002: ior
    //   4003: istore #21
    //   4005: iload #21
    //   4007: aload #9
    //   4009: iload #22
    //   4011: bipush #24
    //   4013: iushr
    //   4014: bipush #63
    //   4016: iand
    //   4017: iaload
    //   4018: ior
    //   4019: istore #21
    //   4021: iload #23
    //   4023: iload #21
    //   4025: ixor
    //   4026: istore #23
    //   4028: iinc #25, 1
    //   4031: iload_2
    //   4032: ifeq -> 3693
    //   4035: iload #23
    //   4037: bipush #31
    //   4039: ishl
    //   4040: iload #23
    //   4042: iconst_1
    //   4043: iushr
    //   4044: ior
    //   4045: istore #23
    //   4047: iload #24
    //   4049: iload #23
    //   4051: ixor
    //   4052: ldc -1431655766
    //   4054: iand
    //   4055: istore #22
    //   4057: iload #24
    //   4059: iload #22
    //   4061: ixor
    //   4062: istore #24
    //   4064: iload #23
    //   4066: iload #22
    //   4068: ixor
    //   4069: istore #23
    //   4071: iload #24
    //   4073: bipush #31
    //   4075: ishl
    //   4076: iload #24
    //   4078: iconst_1
    //   4079: iushr
    //   4080: ior
    //   4081: istore #24
    //   4083: iload #24
    //   4085: bipush #8
    //   4087: iushr
    //   4088: iload #23
    //   4090: ixor
    //   4091: ldc 16711935
    //   4093: iand
    //   4094: istore #22
    //   4096: iload #23
    //   4098: iload #22
    //   4100: ixor
    //   4101: istore #23
    //   4103: iload #24
    //   4105: iload #22
    //   4107: bipush #8
    //   4109: ishl
    //   4110: ixor
    //   4111: istore #24
    //   4113: iload #24
    //   4115: iconst_2
    //   4116: iushr
    //   4117: iload #23
    //   4119: ixor
    //   4120: ldc 858993459
    //   4122: iand
    //   4123: istore #22
    //   4125: iload #23
    //   4127: iload #22
    //   4129: ixor
    //   4130: istore #23
    //   4132: iload #24
    //   4134: iload #22
    //   4136: iconst_2
    //   4137: ishl
    //   4138: ixor
    //   4139: istore #24
    //   4141: iload #23
    //   4143: bipush #16
    //   4145: iushr
    //   4146: iload #24
    //   4148: ixor
    //   4149: ldc 65535
    //   4151: iand
    //   4152: istore #22
    //   4154: iload #24
    //   4156: iload #22
    //   4158: ixor
    //   4159: istore #24
    //   4161: iload #23
    //   4163: iload #22
    //   4165: bipush #16
    //   4167: ishl
    //   4168: ixor
    //   4169: istore #23
    //   4171: iload #23
    //   4173: iconst_4
    //   4174: iushr
    //   4175: iload #24
    //   4177: ixor
    //   4178: ldc 252645135
    //   4180: iand
    //   4181: istore #22
    //   4183: iload #24
    //   4185: iload #22
    //   4187: ixor
    //   4188: istore #24
    //   4190: iload #23
    //   4192: iload #22
    //   4194: iconst_4
    //   4195: ishl
    //   4196: ixor
    //   4197: istore #23
    //   4199: aload #17
    //   4201: iconst_0
    //   4202: iload #23
    //   4204: iastore
    //   4205: aload #17
    //   4207: iconst_1
    //   4208: iload #24
    //   4210: iastore
    //   4211: iload #19
    //   4213: bipush #8
    //   4215: imul
    //   4216: istore #27
    //   4218: iconst_0
    //   4219: istore #28
    //   4221: iload #28
    //   4223: iconst_2
    //   4224: if_icmpge -> 4313
    //   4227: aload #4
    //   4229: iload #27
    //   4231: iload #28
    //   4233: iconst_4
    //   4234: imul
    //   4235: iadd
    //   4236: aload #17
    //   4238: iload #28
    //   4240: iaload
    //   4241: bipush #24
    //   4243: iushr
    //   4244: i2b
    //   4245: bastore
    //   4246: aload #4
    //   4248: iload #27
    //   4250: iload #28
    //   4252: iconst_4
    //   4253: imul
    //   4254: iadd
    //   4255: iconst_1
    //   4256: iadd
    //   4257: aload #17
    //   4259: iload #28
    //   4261: iaload
    //   4262: bipush #16
    //   4264: iushr
    //   4265: i2b
    //   4266: bastore
    //   4267: aload #4
    //   4269: iload #27
    //   4271: iload #28
    //   4273: iconst_4
    //   4274: imul
    //   4275: iadd
    //   4276: iconst_2
    //   4277: iadd
    //   4278: aload #17
    //   4280: iload #28
    //   4282: iaload
    //   4283: bipush #8
    //   4285: iushr
    //   4286: i2b
    //   4287: bastore
    //   4288: aload #4
    //   4290: iload #27
    //   4292: iload #28
    //   4294: iconst_4
    //   4295: imul
    //   4296: iadd
    //   4297: iconst_3
    //   4298: iadd
    //   4299: aload #17
    //   4301: iload #28
    //   4303: iaload
    //   4304: i2b
    //   4305: bastore
    //   4306: iinc #28, 1
    //   4309: iload_2
    //   4310: ifeq -> 4221
    //   4313: iinc #19, 1
    //   4316: iload_2
    //   4317: ifeq -> 3402
    //   4320: new java/math/BigInteger
    //   4323: dup
    //   4324: aload #4
    //   4326: invokespecial <init> : ([B)V
    //   4329: invokevirtual abs : ()Ljava/math/BigInteger;
    //   4332: putstatic burp/Zmj8.Zz : Ljava/lang/Object;
    //   4335: sipush #-7396
    //   4338: sipush #-27085
    //   4341: invokestatic a : (II)Ljava/lang/String;
    //   4344: iconst_1
    //   4345: ldc burp/Zsgj
    //   4347: invokevirtual getClassLoader : ()Ljava/lang/ClassLoader;
    //   4350: invokestatic forName : (Ljava/lang/String;ZLjava/lang/ClassLoader;)Ljava/lang/Class;
    //   4353: invokevirtual getDeclaredFields : ()[Ljava/lang/reflect/Field;
    //   4356: astore_3
    //   4357: aload_3
    //   4358: arraylength
    //   4359: istore #4
    //   4361: iconst_0
    //   4362: istore #5
    //   4364: iload #5
    //   4366: iload #4
    //   4368: if_icmpge -> 4505
    //   4371: aload_3
    //   4372: iload #5
    //   4374: aaload
    //   4375: astore #6
    //   4377: aload #6
    //   4379: invokevirtual getModifiers : ()I
    //   4382: invokestatic isStatic : (I)Z
    //   4385: ifne -> 4395
    //   4388: goto -> 4498
    //   4391: invokestatic a : (Ljava/lang/Throwable;)Ljava/lang/Throwable;
    //   4394: athrow
    //   4395: aload #6
    //   4397: invokevirtual getType : ()Ljava/lang/Class;
    //   4400: astore #7
    //   4402: aload #7
    //   4404: ifnull -> 4485
    //   4407: aload #7
    //   4409: invokevirtual isPrimitive : ()Z
    //   4412: ifne -> 4485
    //   4415: goto -> 4422
    //   4418: invokestatic a : (Ljava/lang/Throwable;)Ljava/lang/Throwable;
    //   4421: athrow
    //   4422: aload #7
    //   4424: invokevirtual getPackage : ()Ljava/lang/Package;
    //   4427: ifnull -> 4485
    //   4430: goto -> 4437
    //   4433: invokestatic a : (Ljava/lang/Throwable;)Ljava/lang/Throwable;
    //   4436: athrow
    //   4437: aload #7
    //   4439: invokevirtual getPackage : ()Ljava/lang/Package;
    //   4442: invokevirtual getName : ()Ljava/lang/String;
    //   4445: ifnull -> 4485
    //   4448: goto -> 4455
    //   4451: invokestatic a : (Ljava/lang/Throwable;)Ljava/lang/Throwable;
    //   4454: athrow
    //   4455: aload #7
    //   4457: invokevirtual getPackage : ()Ljava/lang/Package;
    //   4460: invokevirtual getName : ()Ljava/lang/String;
    //   4463: sipush #-7371
    //   4466: sipush #-13211
    //   4469: invokestatic a : (II)Ljava/lang/String;
    //   4472: invokevirtual startsWith : (Ljava/lang/String;)Z
    //   4475: ifne -> 4485
    //   4478: goto -> 4485
    //   4481: invokestatic a : (Ljava/lang/Throwable;)Ljava/lang/Throwable;
    //   4484: athrow
    //   4485: aload #6
    //   4487: iconst_1
    //   4488: invokevirtual setAccessible : (Z)V
    //   4491: aload #6
    //   4493: aconst_null
    //   4494: invokevirtual get : (Ljava/lang/Object;)Ljava/lang/Object;
    //   4497: pop
    //   4498: iinc #5, 1
    //   4501: iload_2
    //   4502: ifeq -> 4364
    //   4505: sipush #-7395
    //   4508: sipush #-29740
    //   4511: invokestatic a : (II)Ljava/lang/String;
    //   4514: invokestatic forName : (Ljava/lang/String;)Ljava/lang/Class;
    //   4517: invokevirtual getDeclaredMethods : ()[Ljava/lang/reflect/Method;
    //   4520: astore_3
    //   4521: aload_3
    //   4522: arraylength
    //   4523: istore #4
    //   4525: iconst_0
    //   4526: istore #5
    //   4528: iload #5
    //   4530: iload #4
    //   4532: if_icmpge -> 4664
    //   4535: aload_3
    //   4536: iload #5
    //   4538: aaload
    //   4539: astore #6
    //   4541: aload #6
    //   4543: invokevirtual getParameterTypes : ()[Ljava/lang/Class;
    //   4546: pop
    //   4547: aload #6
    //   4549: invokevirtual getModifiers : ()I
    //   4552: invokestatic isStatic : (I)Z
    //   4555: ifeq -> 4650
    //   4558: aload #6
    //   4560: invokevirtual getParameterTypes : ()[Ljava/lang/Class;
    //   4563: arraylength
    //   4564: iconst_2
    //   4565: if_icmpne -> 4650
    //   4568: goto -> 4575
    //   4571: invokestatic a : (Ljava/lang/Throwable;)Ljava/lang/Throwable;
    //   4574: athrow
    //   4575: aload #6
    //   4577: invokevirtual getReturnType : ()Ljava/lang/Class;
    //   4580: getstatic java/lang/Void.TYPE : Ljava/lang/Class;
    //   4583: invokevirtual equals : (Ljava/lang/Object;)Z
    //   4586: ifeq -> 4650
    //   4589: goto -> 4596
    //   4592: invokestatic a : (Ljava/lang/Throwable;)Ljava/lang/Throwable;
    //   4595: athrow
    //   4596: aload #6
    //   4598: iconst_1
    //   4599: invokevirtual setAccessible : (Z)V
    //   4602: aload #6
    //   4604: aconst_null
    //   4605: iconst_2
    //   4606: anewarray java/lang/Object
    //   4609: dup
    //   4610: iconst_0
    //   4611: aload_0
    //   4612: aastore
    //   4613: dup
    //   4614: iconst_1
    //   4615: aload_1
    //   4616: ifnonnull -> 4634
    //   4619: goto -> 4626
    //   4622: invokestatic a : (Ljava/lang/Throwable;)Ljava/lang/Throwable;
    //   4625: athrow
    //   4626: aload_1
    //   4627: goto -> 4641
    //   4630: invokestatic a : (Ljava/lang/Throwable;)Ljava/lang/Throwable;
    //   4633: athrow
    //   4634: aload_1
    //   4635: checkcast [B
    //   4638: invokevirtual clone : ()Ljava/lang/Object;
    //   4641: aastore
    //   4642: invokevirtual invoke : (Ljava/lang/Object;[Ljava/lang/Object;)Ljava/lang/Object;
    //   4645: pop
    //   4646: iload_2
    //   4647: ifeq -> 4664
    //   4650: iinc #5, 1
    //   4653: iload_2
    //   4654: ifeq -> 4528
    //   4657: goto -> 4664
    //   4660: invokestatic a : (Ljava/lang/Throwable;)Ljava/lang/Throwable;
    //   4663: athrow
    //   4664: getstatic burp/Zqp.ZA : Ljava/lang/Object;
    //   4667: checkcast java/math/BigInteger
    //   4670: invokevirtual toByteArray : ()[B
    //   4673: astore_3
    //   4674: new java/lang/StringBuilder
    //   4677: dup
    //   4678: invokespecial <init> : ()V
    //   4681: astore #5
    //   4683: aload #5
    //   4685: sipush #-7406
    //   4688: sipush #-20624
    //   4691: invokestatic a : (II)Ljava/lang/String;
    //   4694: invokevirtual append : (Ljava/lang/String;)Ljava/lang/StringBuilder;
    //   4697: pop
    //   4698: aload_3
    //   4699: astore #6
    //   4701: aload #6
    //   4703: arraylength
    //   4704: istore #7
    //   4706: iconst_0
    //   4707: istore #8
    //   4709: iload #8
    //   4711: iload #7
    //   4713: if_icmpge -> 4739
    //   4716: aload #6
    //   4718: iload #8
    //   4720: baload
    //   4721: istore #9
    //   4723: aload #5
    //   4725: iload #9
    //   4727: i2c
    //   4728: invokevirtual append : (C)Ljava/lang/StringBuilder;
    //   4731: pop
    //   4732: iinc #8, 1
    //   4735: iload_2
    //   4736: ifeq -> 4709
    //   4739: aload #5
    //   4741: sipush #-7405
    //   4744: sipush #29537
    //   4747: invokestatic a : (II)Ljava/lang/String;
    //   4750: ldc ''
    //   4752: invokestatic getProperty : (Ljava/lang/String;Ljava/lang/String;)Ljava/lang/String;
    //   4755: invokevirtual toLowerCase : ()Ljava/lang/String;
    //   4758: invokevirtual append : (Ljava/lang/String;)Ljava/lang/StringBuilder;
    //   4761: pop
    //   4762: aload #5
    //   4764: sipush #-7409
    //   4767: sipush #6233
    //   4770: invokestatic a : (II)Ljava/lang/String;
    //   4773: ldc ''
    //   4775: invokestatic getProperty : (Ljava/lang/String;Ljava/lang/String;)Ljava/lang/String;
    //   4778: invokevirtual toLowerCase : ()Ljava/lang/String;
    //   4781: invokevirtual append : (Ljava/lang/String;)Ljava/lang/StringBuilder;
    //   4784: pop
    //   4785: aload #5
    //   4787: invokevirtual toString : ()Ljava/lang/String;
    //   4790: invokevirtual getBytes : ()[B
    //   4793: astore #4
    //   4795: aload #4
    //   4797: astore_3
    //   4798: aload_3
    //   4799: arraylength
    //   4800: bipush #8
    //   4802: iadd
    //   4803: bipush #6
    //   4805: ishr
    //   4806: iconst_1
    //   4807: iadd
    //   4808: bipush #16
    //   4810: imul
    //   4811: newarray int
    //   4813: astore #5
    //   4815: iconst_0
    //   4816: istore #6
    //   4818: iload #6
    //   4820: aload_3
    //   4821: arraylength
    //   4822: if_icmpge -> 4865
    //   4825: aload_3
    //   4826: iload #6
    //   4828: baload
    //   4829: sipush #255
    //   4832: iand
    //   4833: istore #7
    //   4835: aload #5
    //   4837: iload #6
    //   4839: iconst_2
    //   4840: ishr
    //   4841: dup2
    //   4842: iaload
    //   4843: iload #7
    //   4845: bipush #24
    //   4847: iload #6
    //   4849: iconst_4
    //   4850: irem
    //   4851: bipush #8
    //   4853: imul
    //   4854: isub
    //   4855: ishl
    //   4856: ior
    //   4857: iastore
    //   4858: iinc #6, 1
    //   4861: iload_2
    //   4862: ifeq -> 4818
    //   4865: aload #5
    //   4867: iload #6
    //   4869: iconst_2
    //   4870: ishr
    //   4871: dup2
    //   4872: iaload
    //   4873: sipush #128
    //   4876: bipush #24
    //   4878: iload #6
    //   4880: iconst_4
    //   4881: irem
    //   4882: bipush #8
    //   4884: imul
    //   4885: isub
    //   4886: ishl
    //   4887: ior
    //   4888: iastore
    //   4889: aload #5
    //   4891: aload #5
    //   4893: arraylength
    //   4894: iconst_1
    //   4895: isub
    //   4896: aload_3
    //   4897: arraylength
    //   4898: bipush #8
    //   4900: imul
    //   4901: iastore
    //   4902: bipush #80
    //   4904: newarray int
    //   4906: astore #7
    //   4908: ldc 1732584193
    //   4910: istore #8
    //   4912: ldc -271733879
    //   4914: istore #9
    //   4916: ldc -1732584194
    //   4918: istore #10
    //   4920: ldc 271733878
    //   4922: istore #11
    //   4924: ldc -1009589776
    //   4926: istore #12
    //   4928: iconst_0
    //   4929: istore #6
    //   4931: iload #6
    //   4933: aload #5
    //   4935: arraylength
    //   4936: if_icmpge -> 5258
    //   4939: iload #8
    //   4941: istore #13
    //   4943: iload #9
    //   4945: istore #14
    //   4947: iload #10
    //   4949: istore #15
    //   4951: iload #11
    //   4953: istore #16
    //   4955: iload #12
    //   4957: istore #17
    //   4959: iconst_0
    //   4960: istore #18
    //   4962: iload #18
    //   4964: bipush #80
    //   4966: if_icmpge -> 5216
    //   4969: iload #18
    //   4971: bipush #16
    //   4973: if_icmpge -> 5000
    //   4976: aload #7
    //   4978: iload #18
    //   4980: aload #5
    //   4982: iload #6
    //   4984: iload #18
    //   4986: iadd
    //   4987: iaload
    //   4988: iastore
    //   4989: iload_2
    //   4990: ifeq -> 5055
    //   4993: goto -> 5000
    //   4996: invokestatic a : (Ljava/lang/Throwable;)Ljava/lang/Throwable;
    //   4999: athrow
    //   5000: aload #7
    //   5002: iload #18
    //   5004: iconst_3
    //   5005: isub
    //   5006: iaload
    //   5007: aload #7
    //   5009: iload #18
    //   5011: bipush #8
    //   5013: isub
    //   5014: iaload
    //   5015: ixor
    //   5016: aload #7
    //   5018: iload #18
    //   5020: bipush #14
    //   5022: isub
    //   5023: iaload
    //   5024: ixor
    //   5025: aload #7
    //   5027: iload #18
    //   5029: bipush #16
    //   5031: isub
    //   5032: iaload
    //   5033: ixor
    //   5034: istore #19
    //   5036: iload #19
    //   5038: iconst_1
    //   5039: ishl
    //   5040: iload #19
    //   5042: bipush #31
    //   5044: iushr
    //   5045: ior
    //   5046: istore #20
    //   5048: aload #7
    //   5050: iload #18
    //   5052: iload #20
    //   5054: iastore
    //   5055: iload #8
    //   5057: iconst_5
    //   5058: ishl
    //   5059: iload #8
    //   5061: bipush #27
    //   5063: iushr
    //   5064: ior
    //   5065: istore #19
    //   5067: iload #19
    //   5069: iload #12
    //   5071: iadd
    //   5072: aload #7
    //   5074: iload #18
    //   5076: iaload
    //   5077: iadd
    //   5078: iload #18
    //   5080: bipush #20
    //   5082: if_icmpge -> 5108
    //   5085: ldc 1518500249
    //   5087: iload #9
    //   5089: iload #10
    //   5091: iand
    //   5092: iload #9
    //   5094: iconst_m1
    //   5095: ixor
    //   5096: iload #11
    //   5098: iand
    //   5099: ior
    //   5100: iadd
    //   5101: goto -> 5178
    //   5104: invokestatic a : (Ljava/lang/Throwable;)Ljava/lang/Throwable;
    //   5107: athrow
    //   5108: iload #18
    //   5110: bipush #40
    //   5112: if_icmpge -> 5133
    //   5115: ldc 1859775393
    //   5117: iload #9
    //   5119: iload #10
    //   5121: ixor
    //   5122: iload #11
    //   5124: ixor
    //   5125: iadd
    //   5126: goto -> 5178
    //   5129: invokestatic a : (Ljava/lang/Throwable;)Ljava/lang/Throwable;
    //   5132: athrow
    //   5133: iload #18
    //   5135: bipush #60
    //   5137: if_icmpge -> 5167
    //   5140: ldc -1894007588
    //   5142: iload #9
    //   5144: iload #10
    //   5146: iand
    //   5147: iload #9
    //   5149: iload #11
    //   5151: iand
    //   5152: ior
    //   5153: iload #10
    //   5155: iload #11
    //   5157: iand
    //   5158: ior
    //   5159: iadd
    //   5160: goto -> 5178
    //   5163: invokestatic a : (Ljava/lang/Throwable;)Ljava/lang/Throwable;
    //   5166: athrow
    //   5167: ldc -899497514
    //   5169: iload #9
    //   5171: iload #10
    //   5173: ixor
    //   5174: iload #11
    //   5176: ixor
    //   5177: iadd
    //   5178: iadd
    //   5179: istore #20
    //   5181: iload #11
    //   5183: istore #12
    //   5185: iload #10
    //   5187: istore #11
    //   5189: iload #9
    //   5191: bipush #30
    //   5193: ishl
    //   5194: iload #9
    //   5196: iconst_2
    //   5197: iushr
    //   5198: ior
    //   5199: istore #10
    //   5201: iload #8
    //   5203: istore #9
    //   5205: iload #20
    //   5207: istore #8
    //   5209: iinc #18, 1
    //   5212: iload_2
    //   5213: ifeq -> 4962
    //   5216: iload #8
    //   5218: iload #13
    //   5220: iadd
    //   5221: istore #8
    //   5223: iload #9
    //   5225: iload #14
    //   5227: iadd
    //   5228: istore #9
    //   5230: iload #10
    //   5232: iload #15
    //   5234: iadd
    //   5235: istore #10
    //   5237: iload #11
    //   5239: iload #16
    //   5241: iadd
    //   5242: istore #11
    //   5244: iload #12
    //   5246: iload #17
    //   5248: iadd
    //   5249: istore #12
    //   5251: iinc #6, 16
    //   5254: iload_2
    //   5255: ifeq -> 4931
    //   5258: iconst_5
    //   5259: newarray int
    //   5261: dup
    //   5262: iconst_0
    //   5263: iload #8
    //   5265: iastore
    //   5266: dup
    //   5267: iconst_1
    //   5268: iload #9
    //   5270: iastore
    //   5271: dup
    //   5272: iconst_2
    //   5273: iload #10
    //   5275: iastore
    //   5276: dup
    //   5277: iconst_3
    //   5278: iload #11
    //   5280: iastore
    //   5281: dup
    //   5282: iconst_4
    //   5283: iload #12
    //   5285: iastore
    //   5286: astore #13
    //   5288: bipush #20
    //   5290: newarray byte
    //   5292: astore #14
    //   5294: iconst_0
    //   5295: istore #15
    //   5297: iload #15
    //   5299: bipush #20
    //   5301: if_icmpge -> 5342
    //   5304: aload #13
    //   5306: iload #15
    //   5308: iconst_4
    //   5309: idiv
    //   5310: iaload
    //   5311: istore #16
    //   5313: iconst_3
    //   5314: iload #15
    //   5316: iconst_4
    //   5317: irem
    //   5318: isub
    //   5319: bipush #8
    //   5321: imul
    //   5322: istore #17
    //   5324: aload #14
    //   5326: iload #15
    //   5328: iload #16
    //   5330: iload #17
    //   5332: iushr
    //   5333: i2b
    //   5334: bastore
    //   5335: iinc #15, 1
    //   5338: iload_2
    //   5339: ifeq -> 5297
    //   5342: aload #14
    //   5344: astore #4
    //   5346: new java/io/ByteArrayOutputStream
    //   5349: dup
    //   5350: invokespecial <init> : ()V
    //   5353: astore_3
    //   5354: sipush #-7414
    //   5357: aload_3
    //   5358: sipush #202
    //   5361: invokevirtual write : (I)V
    //   5364: sipush #-21403
    //   5367: aload_3
    //   5368: sipush #254
    //   5371: invokevirtual write : (I)V
    //   5374: aload_3
    //   5375: sipush #186
    //   5378: invokevirtual write : (I)V
    //   5381: aload_3
    //   5382: sipush #190
    //   5385: invokevirtual write : (I)V
    //   5388: aload_3
    //   5389: iconst_0
    //   5390: invokevirtual write : (I)V
    //   5393: aload_3
    //   5394: iconst_1
    //   5395: invokevirtual write : (I)V
    //   5398: aload_3
    //   5399: iconst_0
    //   5400: invokevirtual write : (I)V
    //   5403: aload_3
    //   5404: bipush #50
    //   5406: invokevirtual write : (I)V
    //   5409: aload_3
    //   5410: getstatic burp/Zg7z.ZV : Ljava/lang/Object;
    //   5413: checkcast java/math/BigInteger
    //   5416: invokevirtual toByteArray : ()[B
    //   5419: invokevirtual write : ([B)V
    //   5422: aload_3
    //   5423: getstatic burp/Zlxs.ZK : Ljava/lang/Object;
    //   5426: checkcast java/math/BigInteger
    //   5429: invokevirtual toByteArray : ()[B
    //   5432: invokevirtual write : ([B)V
    //   5435: aload_3
    //   5436: getstatic burp/Zxdh.ZD : Ljava/lang/Object;
    //   5439: checkcast java/math/BigInteger
    //   5442: invokevirtual toByteArray : ()[B
    //   5445: invokevirtual write : ([B)V
    //   5448: aload_3
    //   5449: invokevirtual toByteArray : ()[B
    //   5452: astore #4
    //   5454: aconst_null
    //   5455: astore #5
    //   5457: invokestatic a : (II)Ljava/lang/String;
    //   5460: invokestatic forName : (Ljava/lang/String;)Ljava/lang/Class;
    //   5463: invokevirtual getDeclaredMethods : ()[Ljava/lang/reflect/Method;
    //   5466: astore #6
    //   5468: aload #6
    //   5470: arraylength
    //   5471: istore #7
    //   5473: iconst_0
    //   5474: istore #8
    //   5476: iload #8
    //   5478: iload #7
    //   5480: if_icmpge -> 5608
    //   5483: aload #6
    //   5485: iload #8
    //   5487: aaload
    //   5488: astore #9
    //   5490: aload #9
    //   5492: invokevirtual getName : ()Ljava/lang/String;
    //   5495: sipush #-7397
    //   5498: sipush #-20909
    //   5501: invokestatic a : (II)Ljava/lang/String;
    //   5504: invokevirtual equals : (Ljava/lang/Object;)Z
    //   5507: ifeq -> 5601
    //   5510: aload #9
    //   5512: invokevirtual getParameterTypes : ()[Ljava/lang/Class;
    //   5515: astore #10
    //   5517: aload #10
    //   5519: arraylength
    //   5520: iconst_4
    //   5521: if_icmpeq -> 5531
    //   5524: goto -> 5601
    //   5527: invokestatic a : (Ljava/lang/Throwable;)Ljava/lang/Throwable;
    //   5530: athrow
    //   5531: aload #10
    //   5533: iconst_0
    //   5534: aaload
    //   5535: ldc java/lang/String
    //   5537: if_acmpeq -> 5547
    //   5540: goto -> 5601
    //   5543: invokestatic a : (Ljava/lang/Throwable;)Ljava/lang/Throwable;
    //   5546: athrow
    //   5547: aload #10
    //   5549: iconst_1
    //   5550: aaload
    //   5551: ldc [B
    //   5553: if_acmpeq -> 5563
    //   5556: goto -> 5601
    //   5559: invokestatic a : (Ljava/lang/Throwable;)Ljava/lang/Throwable;
    //   5562: athrow
    //   5563: aload #10
    //   5565: iconst_2
    //   5566: aaload
    //   5567: getstatic java/lang/Integer.TYPE : Ljava/lang/Class;
    //   5570: if_acmpeq -> 5580
    //   5573: goto -> 5601
    //   5576: invokestatic a : (Ljava/lang/Throwable;)Ljava/lang/Throwable;
    //   5579: athrow
    //   5580: aload #10
    //   5582: iconst_3
    //   5583: aaload
    //   5584: getstatic java/lang/Integer.TYPE : Ljava/lang/Class;
    //   5587: if_acmpeq -> 5597
    //   5590: goto -> 5601
    //   5593: invokestatic a : (Ljava/lang/Throwable;)Ljava/lang/Throwable;
    //   5596: athrow
    //   5597: aload #9
    //   5599: astore #5
    //   5601: iinc #8, 1
    //   5604: iload_2
    //   5605: ifeq -> 5476
    //   5608: aload #5
    //   5610: iconst_1
    //   5611: invokevirtual setAccessible : (Z)V
    //   5614: ldc burp/Zlhu
    //   5616: iconst_0
    //   5617: anewarray java/lang/Class
    //   5620: invokevirtual getDeclaredConstructor : ([Ljava/lang/Class;)Ljava/lang/reflect/Constructor;
    //   5623: astore #6
    //   5625: aload #6
    //   5627: iconst_1
    //   5628: invokevirtual setAccessible : (Z)V
    //   5631: aload #5
    //   5633: aload #6
    //   5635: iconst_0
    //   5636: anewarray java/lang/Object
    //   5639: invokevirtual newInstance : ([Ljava/lang/Object;)Ljava/lang/Object;
    //   5642: iconst_4
    //   5643: anewarray java/lang/Object
    //   5646: dup
    //   5647: iconst_0
    //   5648: sipush #-7398
    //   5651: sipush #-2211
    //   5654: invokestatic a : (II)Ljava/lang/String;
    //   5657: aastore
    //   5658: dup
    //   5659: iconst_1
    //   5660: aload #4
    //   5662: aastore
    //   5663: dup
    //   5664: iconst_2
    //   5665: iconst_0
    //   5666: invokestatic valueOf : (I)Ljava/lang/Integer;
    //   5669: aastore
    //   5670: dup
    //   5671: iconst_3
    //   5672: aload #4
    //   5674: arraylength
    //   5675: invokestatic valueOf : (I)Ljava/lang/Integer;
    //   5678: aastore
    //   5679: invokevirtual invoke : (Ljava/lang/Object;[Ljava/lang/Object;)Ljava/lang/Object;
    //   5682: pop
    //   5683: goto -> 5687
    //   5686: astore_3
    //   5687: iconst_0
    //   5688: istore_3
    //   5689: getstatic burp/Zk12.Zu : Ljava/lang/String;
    //   5692: getstatic burp/Zg_5.ZA : Ljava/lang/Object;
    //   5695: checkcast java/math/BigInteger
    //   5698: invokevirtual intValue : ()I
    //   5701: bipush #32
    //   5703: irem
    //   5704: invokestatic abs : (I)I
    //   5707: invokevirtual charAt : (I)C
    //   5710: getstatic burp/Zzmw.Zd : Ljava/lang/String;
    //   5713: getstatic burp/Zt5j.Zn : Ljava/lang/Object;
    //   5716: checkcast java/math/BigInteger
    //   5719: invokevirtual intValue : ()I
    //   5722: bipush #32
    //   5724: irem
    //   5725: invokestatic abs : (I)I
    //   5728: invokevirtual charAt : (I)C
    //   5731: if_icmpgt -> 6075
    //   5734: sipush #-7402
    //   5737: sipush #26754
    //   5740: invokestatic a : (II)Ljava/lang/String;
    //   5743: iconst_1
    //   5744: ldc burp/Zb3z
    //   5746: invokevirtual getClassLoader : ()Ljava/lang/ClassLoader;
    //   5749: invokestatic forName : (Ljava/lang/String;ZLjava/lang/ClassLoader;)Ljava/lang/Class;
    //   5752: invokevirtual getDeclaredFields : ()[Ljava/lang/reflect/Field;
    //   5755: astore #4
    //   5757: aload #4
    //   5759: arraylength
    //   5760: istore #5
    //   5762: iconst_0
    //   5763: istore #6
    //   5765: iload #6
    //   5767: iload #5
    //   5769: if_icmpge -> 5907
    //   5772: aload #4
    //   5774: iload #6
    //   5776: aaload
    //   5777: astore #7
    //   5779: aload #7
    //   5781: invokevirtual getModifiers : ()I
    //   5784: invokestatic isStatic : (I)Z
    //   5787: ifne -> 5797
    //   5790: goto -> 5900
    //   5793: invokestatic a : (Ljava/lang/Throwable;)Ljava/lang/Throwable;
    //   5796: athrow
    //   5797: aload #7
    //   5799: invokevirtual getType : ()Ljava/lang/Class;
    //   5802: astore #8
    //   5804: aload #8
    //   5806: ifnull -> 5887
    //   5809: aload #8
    //   5811: invokevirtual isPrimitive : ()Z
    //   5814: ifne -> 5887
    //   5817: goto -> 5824
    //   5820: invokestatic a : (Ljava/lang/Throwable;)Ljava/lang/Throwable;
    //   5823: athrow
    //   5824: aload #8
    //   5826: invokevirtual getPackage : ()Ljava/lang/Package;
    //   5829: ifnull -> 5887
    //   5832: goto -> 5839
    //   5835: invokestatic a : (Ljava/lang/Throwable;)Ljava/lang/Throwable;
    //   5838: athrow
    //   5839: aload #8
    //   5841: invokevirtual getPackage : ()Ljava/lang/Package;
    //   5844: invokevirtual getName : ()Ljava/lang/String;
    //   5847: ifnull -> 5887
    //   5850: goto -> 5857
    //   5853: invokestatic a : (Ljava/lang/Throwable;)Ljava/lang/Throwable;
    //   5856: athrow
    //   5857: aload #8
    //   5859: invokevirtual getPackage : ()Ljava/lang/Package;
    //   5862: invokevirtual getName : ()Ljava/lang/String;
    //   5865: sipush #-7410
    //   5868: sipush #-3236
    //   5871: invokestatic a : (II)Ljava/lang/String;
    //   5874: invokevirtual startsWith : (Ljava/lang/String;)Z
    //   5877: ifne -> 5887
    //   5880: goto -> 5887
    //   5883: invokestatic a : (Ljava/lang/Throwable;)Ljava/lang/Throwable;
    //   5886: athrow
    //   5887: aload #7
    //   5889: iconst_1
    //   5890: invokevirtual setAccessible : (Z)V
    //   5893: aload #7
    //   5895: aconst_null
    //   5896: invokevirtual get : (Ljava/lang/Object;)Ljava/lang/Object;
    //   5899: pop
    //   5900: iinc #6, 1
    //   5903: iload_2
    //   5904: ifeq -> 5765
    //   5907: sipush #-7411
    //   5910: sipush #-5628
    //   5913: invokestatic a : (II)Ljava/lang/String;
    //   5916: invokestatic forName : (Ljava/lang/String;)Ljava/lang/Class;
    //   5919: invokevirtual getDeclaredMethods : ()[Ljava/lang/reflect/Method;
    //   5922: astore #4
    //   5924: aload #4
    //   5926: arraylength
    //   5927: istore #5
    //   5929: iconst_0
    //   5930: istore #6
    //   5932: iload #6
    //   5934: iload #5
    //   5936: if_icmpge -> 6072
    //   5939: aload #4
    //   5941: iload #6
    //   5943: aaload
    //   5944: astore #7
    //   5946: aload #7
    //   5948: invokevirtual getParameterTypes : ()[Ljava/lang/Class;
    //   5951: pop
    //   5952: aload #7
    //   5954: invokevirtual getModifiers : ()I
    //   5957: invokestatic isStatic : (I)Z
    //   5960: ifeq -> 6058
    //   5963: aload #7
    //   5965: invokevirtual getParameterTypes : ()[Ljava/lang/Class;
    //   5968: arraylength
    //   5969: iconst_2
    //   5970: if_icmpne -> 6058
    //   5973: goto -> 5980
    //   5976: invokestatic a : (Ljava/lang/Throwable;)Ljava/lang/Throwable;
    //   5979: athrow
    //   5980: aload #7
    //   5982: invokevirtual getReturnType : ()Ljava/lang/Class;
    //   5985: getstatic java/lang/Boolean.TYPE : Ljava/lang/Class;
    //   5988: if_acmpne -> 6058
    //   5991: goto -> 5998
    //   5994: invokestatic a : (Ljava/lang/Throwable;)Ljava/lang/Throwable;
    //   5997: athrow
    //   5998: aload #7
    //   6000: iconst_1
    //   6001: invokevirtual setAccessible : (Z)V
    //   6004: aload #7
    //   6006: aconst_null
    //   6007: iconst_2
    //   6008: anewarray java/lang/Object
    //   6011: dup
    //   6012: iconst_0
    //   6013: aload_0
    //   6014: aastore
    //   6015: dup
    //   6016: iconst_1
    //   6017: aload_1
    //   6018: ifnonnull -> 6036
    //   6021: goto -> 6028
    //   6024: invokestatic a : (Ljava/lang/Throwable;)Ljava/lang/Throwable;
    //   6027: athrow
    //   6028: aload_1
    //   6029: goto -> 6043
    //   6032: invokestatic a : (Ljava/lang/Throwable;)Ljava/lang/Throwable;
    //   6035: athrow
    //   6036: aload_1
    //   6037: checkcast [B
    //   6040: invokevirtual clone : ()Ljava/lang/Object;
    //   6043: aastore
    //   6044: invokevirtual invoke : (Ljava/lang/Object;[Ljava/lang/Object;)Ljava/lang/Object;
    //   6047: checkcast java/lang/Boolean
    //   6050: invokevirtual booleanValue : ()Z
    //   6053: istore_3
    //   6054: iload_2
    //   6055: ifeq -> 6072
    //   6058: iinc #6, 1
    //   6061: iload_2
    //   6062: ifeq -> 5932
    //   6065: goto -> 6072
    //   6068: invokestatic a : (Ljava/lang/Throwable;)Ljava/lang/Throwable;
    //   6071: athrow
    //   6072: goto -> 6413
    //   6075: sipush #-7407
    //   6078: sipush #10214
    //   6081: invokestatic a : (II)Ljava/lang/String;
    //   6084: iconst_1
    //   6085: ldc burp/Zbp_
    //   6087: invokevirtual getClassLoader : ()Ljava/lang/ClassLoader;
    //   6090: invokestatic forName : (Ljava/lang/String;ZLjava/lang/ClassLoader;)Ljava/lang/Class;
    //   6093: invokevirtual getDeclaredFields : ()[Ljava/lang/reflect/Field;
    //   6096: astore #4
    //   6098: aload #4
    //   6100: arraylength
    //   6101: istore #5
    //   6103: iconst_0
    //   6104: istore #6
    //   6106: iload #6
    //   6108: iload #5
    //   6110: if_icmpge -> 6248
    //   6113: aload #4
    //   6115: iload #6
    //   6117: aaload
    //   6118: astore #7
    //   6120: aload #7
    //   6122: invokevirtual getModifiers : ()I
    //   6125: invokestatic isStatic : (I)Z
    //   6128: ifne -> 6138
    //   6131: goto -> 6241
    //   6134: invokestatic a : (Ljava/lang/Throwable;)Ljava/lang/Throwable;
    //   6137: athrow
    //   6138: aload #7
    //   6140: invokevirtual getType : ()Ljava/lang/Class;
    //   6143: astore #8
    //   6145: aload #8
    //   6147: ifnull -> 6228
    //   6150: aload #8
    //   6152: invokevirtual isPrimitive : ()Z
    //   6155: ifne -> 6228
    //   6158: goto -> 6165
    //   6161: invokestatic a : (Ljava/lang/Throwable;)Ljava/lang/Throwable;
    //   6164: athrow
    //   6165: aload #8
    //   6167: invokevirtual getPackage : ()Ljava/lang/Package;
    //   6170: ifnull -> 6228
    //   6173: goto -> 6180
    //   6176: invokestatic a : (Ljava/lang/Throwable;)Ljava/lang/Throwable;
    //   6179: athrow
    //   6180: aload #8
    //   6182: invokevirtual getPackage : ()Ljava/lang/Package;
    //   6185: invokevirtual getName : ()Ljava/lang/String;
    //   6188: ifnull -> 6228
    //   6191: goto -> 6198
    //   6194: invokestatic a : (Ljava/lang/Throwable;)Ljava/lang/Throwable;
    //   6197: athrow
    //   6198: aload #8
    //   6200: invokevirtual getPackage : ()Ljava/lang/Package;
    //   6203: invokevirtual getName : ()Ljava/lang/String;
    //   6206: sipush #-7410
    //   6209: sipush #-3236
    //   6212: invokestatic a : (II)Ljava/lang/String;
    //   6215: invokevirtual startsWith : (Ljava/lang/String;)Z
    //   6218: ifne -> 6228
    //   6221: goto -> 6228
    //   6224: invokestatic a : (Ljava/lang/Throwable;)Ljava/lang/Throwable;
    //   6227: athrow
    //   6228: aload #7
    //   6230: iconst_1
    //   6231: invokevirtual setAccessible : (Z)V
    //   6234: aload #7
    //   6236: aconst_null
    //   6237: invokevirtual get : (Ljava/lang/Object;)Ljava/lang/Object;
    //   6240: pop
    //   6241: iinc #6, 1
    //   6244: iload_2
    //   6245: ifeq -> 6106
    //   6248: sipush #-7369
    //   6251: sipush #-19308
    //   6254: invokestatic a : (II)Ljava/lang/String;
    //   6257: invokestatic forName : (Ljava/lang/String;)Ljava/lang/Class;
    //   6260: invokevirtual getDeclaredMethods : ()[Ljava/lang/reflect/Method;
    //   6263: astore #4
    //   6265: aload #4
    //   6267: arraylength
    //   6268: istore #5
    //   6270: iconst_0
    //   6271: istore #6
    //   6273: iload #6
    //   6275: iload #5
    //   6277: if_icmpge -> 6413
    //   6280: aload #4
    //   6282: iload #6
    //   6284: aaload
    //   6285: astore #7
    //   6287: aload #7
    //   6289: invokevirtual getParameterTypes : ()[Ljava/lang/Class;
    //   6292: pop
    //   6293: aload #7
    //   6295: invokevirtual getModifiers : ()I
    //   6298: invokestatic isStatic : (I)Z
    //   6301: ifeq -> 6399
    //   6304: aload #7
    //   6306: invokevirtual getParameterTypes : ()[Ljava/lang/Class;
    //   6309: arraylength
    //   6310: iconst_2
    //   6311: if_icmpne -> 6399
    //   6314: goto -> 6321
    //   6317: invokestatic a : (Ljava/lang/Throwable;)Ljava/lang/Throwable;
    //   6320: athrow
    //   6321: aload #7
    //   6323: invokevirtual getReturnType : ()Ljava/lang/Class;
    //   6326: getstatic java/lang/Boolean.TYPE : Ljava/lang/Class;
    //   6329: if_acmpne -> 6399
    //   6332: goto -> 6339
    //   6335: invokestatic a : (Ljava/lang/Throwable;)Ljava/lang/Throwable;
    //   6338: athrow
    //   6339: aload #7
    //   6341: iconst_1
    //   6342: invokevirtual setAccessible : (Z)V
    //   6345: aload #7
    //   6347: aconst_null
    //   6348: iconst_2
    //   6349: anewarray java/lang/Object
    //   6352: dup
    //   6353: iconst_0
    //   6354: aload_0
    //   6355: aastore
    //   6356: dup
    //   6357: iconst_1
    //   6358: aload_1
    //   6359: ifnonnull -> 6377
    //   6362: goto -> 6369
    //   6365: invokestatic a : (Ljava/lang/Throwable;)Ljava/lang/Throwable;
    //   6368: athrow
    //   6369: aload_1
    //   6370: goto -> 6384
    //   6373: invokestatic a : (Ljava/lang/Throwable;)Ljava/lang/Throwable;
    //   6376: athrow
    //   6377: aload_1
    //   6378: checkcast [B
    //   6381: invokevirtual clone : ()Ljava/lang/Object;
    //   6384: aastore
    //   6385: invokevirtual invoke : (Ljava/lang/Object;[Ljava/lang/Object;)Ljava/lang/Object;
    //   6388: checkcast java/lang/Boolean
    //   6391: invokevirtual booleanValue : ()Z
    //   6394: istore_3
    //   6395: iload_2
    //   6396: ifeq -> 6413
    //   6399: iinc #6, 1
    //   6402: iload_2
    //   6403: ifeq -> 6273
    //   6406: goto -> 6413
    //   6409: invokestatic a : (Ljava/lang/Throwable;)Ljava/lang/Throwable;
    //   6412: athrow
    //   6413: iload_3
    //   6414: ifeq -> 6419
    //   6417: iload_3
    //   6418: ireturn
    //   6419: getstatic burp/Zlnm.ZL : Ljava/lang/String;
    //   6422: getstatic burp/Zef0.ZX : Ljava/lang/Object;
    //   6425: checkcast java/math/BigInteger
    //   6428: invokevirtual intValue : ()I
    //   6431: bipush #32
    //   6433: irem
    //   6434: invokestatic abs : (I)I
    //   6437: invokevirtual charAt : (I)C
    //   6440: getstatic burp/Zza8.Zm : Ljava/lang/String;
    //   6443: getstatic burp/Zxjv.ZY : Ljava/lang/Object;
    //   6446: checkcast java/math/BigInteger
    //   6449: invokevirtual intValue : ()I
    //   6452: bipush #32
    //   6454: irem
    //   6455: invokestatic abs : (I)I
    //   6458: invokevirtual charAt : (I)C
    //   6461: if_icmpgt -> 6806
    //   6464: sipush #-7370
    //   6467: sipush #10229
    //   6470: invokestatic a : (II)Ljava/lang/String;
    //   6473: iconst_1
    //   6474: ldc burp/Zemp
    //   6476: invokevirtual getClassLoader : ()Ljava/lang/ClassLoader;
    //   6479: invokestatic forName : (Ljava/lang/String;ZLjava/lang/ClassLoader;)Ljava/lang/Class;
    //   6482: invokevirtual getDeclaredFields : ()[Ljava/lang/reflect/Field;
    //   6485: astore #4
    //   6487: aload #4
    //   6489: arraylength
    //   6490: istore #5
    //   6492: iconst_0
    //   6493: istore #6
    //   6495: iload #6
    //   6497: iload #5
    //   6499: if_icmpge -> 6637
    //   6502: aload #4
    //   6504: iload #6
    //   6506: aaload
    //   6507: astore #7
    //   6509: aload #7
    //   6511: invokevirtual getModifiers : ()I
    //   6514: invokestatic isStatic : (I)Z
    //   6517: ifne -> 6527
    //   6520: goto -> 6630
    //   6523: invokestatic a : (Ljava/lang/Throwable;)Ljava/lang/Throwable;
    //   6526: athrow
    //   6527: aload #7
    //   6529: invokevirtual getType : ()Ljava/lang/Class;
    //   6532: astore #8
    //   6534: aload #8
    //   6536: ifnull -> 6617
    //   6539: aload #8
    //   6541: invokevirtual isPrimitive : ()Z
    //   6544: ifne -> 6617
    //   6547: goto -> 6554
    //   6550: invokestatic a : (Ljava/lang/Throwable;)Ljava/lang/Throwable;
    //   6553: athrow
    //   6554: aload #8
    //   6556: invokevirtual getPackage : ()Ljava/lang/Package;
    //   6559: ifnull -> 6617
    //   6562: goto -> 6569
    //   6565: invokestatic a : (Ljava/lang/Throwable;)Ljava/lang/Throwable;
    //   6568: athrow
    //   6569: aload #8
    //   6571: invokevirtual getPackage : ()Ljava/lang/Package;
    //   6574: invokevirtual getName : ()Ljava/lang/String;
    //   6577: ifnull -> 6617
    //   6580: goto -> 6587
    //   6583: invokestatic a : (Ljava/lang/Throwable;)Ljava/lang/Throwable;
    //   6586: athrow
    //   6587: aload #8
    //   6589: invokevirtual getPackage : ()Ljava/lang/Package;
    //   6592: invokevirtual getName : ()Ljava/lang/String;
    //   6595: sipush #-7410
    //   6598: sipush #-3236
    //   6601: invokestatic a : (II)Ljava/lang/String;
    //   6604: invokevirtual startsWith : (Ljava/lang/String;)Z
    //   6607: ifne -> 6617
    //   6610: goto -> 6617
    //   6613: invokestatic a : (Ljava/lang/Throwable;)Ljava/lang/Throwable;
    //   6616: athrow
    //   6617: aload #7
    //   6619: iconst_1
    //   6620: invokevirtual setAccessible : (Z)V
    //   6623: aload #7
    //   6625: aconst_null
    //   6626: invokevirtual get : (Ljava/lang/Object;)Ljava/lang/Object;
    //   6629: pop
    //   6630: iinc #6, 1
    //   6633: iload_2
    //   6634: ifeq -> 6495
    //   6637: sipush #-7400
    //   6640: sipush #12566
    //   6643: invokestatic a : (II)Ljava/lang/String;
    //   6646: invokestatic forName : (Ljava/lang/String;)Ljava/lang/Class;
    //   6649: invokevirtual getDeclaredMethods : ()[Ljava/lang/reflect/Method;
    //   6652: astore #4
    //   6654: aload #4
    //   6656: arraylength
    //   6657: istore #5
    //   6659: iconst_0
    //   6660: istore #6
    //   6662: iload #6
    //   6664: iload #5
    //   6666: if_icmpge -> 6802
    //   6669: aload #4
    //   6671: iload #6
    //   6673: aaload
    //   6674: astore #7
    //   6676: aload #7
    //   6678: invokevirtual getParameterTypes : ()[Ljava/lang/Class;
    //   6681: pop
    //   6682: aload #7
    //   6684: invokevirtual getModifiers : ()I
    //   6687: invokestatic isStatic : (I)Z
    //   6690: ifeq -> 6788
    //   6693: aload #7
    //   6695: invokevirtual getParameterTypes : ()[Ljava/lang/Class;
    //   6698: arraylength
    //   6699: iconst_2
    //   6700: if_icmpne -> 6788
    //   6703: goto -> 6710
    //   6706: invokestatic a : (Ljava/lang/Throwable;)Ljava/lang/Throwable;
    //   6709: athrow
    //   6710: aload #7
    //   6712: invokevirtual getReturnType : ()Ljava/lang/Class;
    //   6715: getstatic java/lang/Boolean.TYPE : Ljava/lang/Class;
    //   6718: if_acmpne -> 6788
    //   6721: goto -> 6728
    //   6724: invokestatic a : (Ljava/lang/Throwable;)Ljava/lang/Throwable;
    //   6727: athrow
    //   6728: aload #7
    //   6730: iconst_1
    //   6731: invokevirtual setAccessible : (Z)V
    //   6734: aload #7
    //   6736: aconst_null
    //   6737: iconst_2
    //   6738: anewarray java/lang/Object
    //   6741: dup
    //   6742: iconst_0
    //   6743: aload_0
    //   6744: aastore
    //   6745: dup
    //   6746: iconst_1
    //   6747: aload_1
    //   6748: ifnonnull -> 6766
    //   6751: goto -> 6758
    //   6754: invokestatic a : (Ljava/lang/Throwable;)Ljava/lang/Throwable;
    //   6757: athrow
    //   6758: aload_1
    //   6759: goto -> 6773
    //   6762: invokestatic a : (Ljava/lang/Throwable;)Ljava/lang/Throwable;
    //   6765: athrow
    //   6766: aload_1
    //   6767: checkcast [B
    //   6770: invokevirtual clone : ()Ljava/lang/Object;
    //   6773: aastore
    //   6774: invokevirtual invoke : (Ljava/lang/Object;[Ljava/lang/Object;)Ljava/lang/Object;
    //   6777: checkcast java/lang/Boolean
    //   6780: invokevirtual booleanValue : ()Z
    //   6783: istore_3
    //   6784: iload_2
    //   6785: ifeq -> 6802
    //   6788: iinc #6, 1
    //   6791: iload_2
    //   6792: ifeq -> 6662
    //   6795: goto -> 6802
    //   6798: invokestatic a : (Ljava/lang/Throwable;)Ljava/lang/Throwable;
    //   6801: athrow
    //   6802: iload_2
    //   6803: ifeq -> 7144
    //   6806: sipush #-7416
    //   6809: sipush #21388
    //   6812: invokestatic a : (II)Ljava/lang/String;
    //   6815: iconst_1
    //   6816: ldc burp/Zs00
    //   6818: invokevirtual getClassLoader : ()Ljava/lang/ClassLoader;
    //   6821: invokestatic forName : (Ljava/lang/String;ZLjava/lang/ClassLoader;)Ljava/lang/Class;
    //   6824: invokevirtual getDeclaredFields : ()[Ljava/lang/reflect/Field;
    //   6827: astore #4
    //   6829: aload #4
    //   6831: arraylength
    //   6832: istore #5
    //   6834: iconst_0
    //   6835: istore #6
    //   6837: iload #6
    //   6839: iload #5
    //   6841: if_icmpge -> 6979
    //   6844: aload #4
    //   6846: iload #6
    //   6848: aaload
    //   6849: astore #7
    //   6851: aload #7
    //   6853: invokevirtual getModifiers : ()I
    //   6856: invokestatic isStatic : (I)Z
    //   6859: ifne -> 6869
    //   6862: goto -> 6972
    //   6865: invokestatic a : (Ljava/lang/Throwable;)Ljava/lang/Throwable;
    //   6868: athrow
    //   6869: aload #7
    //   6871: invokevirtual getType : ()Ljava/lang/Class;
    //   6874: astore #8
    //   6876: aload #8
    //   6878: ifnull -> 6959
    //   6881: aload #8
    //   6883: invokevirtual isPrimitive : ()Z
    //   6886: ifne -> 6959
    //   6889: goto -> 6896
    //   6892: invokestatic a : (Ljava/lang/Throwable;)Ljava/lang/Throwable;
    //   6895: athrow
    //   6896: aload #8
    //   6898: invokevirtual getPackage : ()Ljava/lang/Package;
    //   6901: ifnull -> 6959
    //   6904: goto -> 6911
    //   6907: invokestatic a : (Ljava/lang/Throwable;)Ljava/lang/Throwable;
    //   6910: athrow
    //   6911: aload #8
    //   6913: invokevirtual getPackage : ()Ljava/lang/Package;
    //   6916: invokevirtual getName : ()Ljava/lang/String;
    //   6919: ifnull -> 6959
    //   6922: goto -> 6929
    //   6925: invokestatic a : (Ljava/lang/Throwable;)Ljava/lang/Throwable;
    //   6928: athrow
    //   6929: aload #8
    //   6931: invokevirtual getPackage : ()Ljava/lang/Package;
    //   6934: invokevirtual getName : ()Ljava/lang/String;
    //   6937: sipush #-7410
    //   6940: sipush #-3236
    //   6943: invokestatic a : (II)Ljava/lang/String;
    //   6946: invokevirtual startsWith : (Ljava/lang/String;)Z
    //   6949: ifne -> 6959
    //   6952: goto -> 6959
    //   6955: invokestatic a : (Ljava/lang/Throwable;)Ljava/lang/Throwable;
    //   6958: athrow
    //   6959: aload #7
    //   6961: iconst_1
    //   6962: invokevirtual setAccessible : (Z)V
    //   6965: aload #7
    //   6967: aconst_null
    //   6968: invokevirtual get : (Ljava/lang/Object;)Ljava/lang/Object;
    //   6971: pop
    //   6972: iinc #6, 1
    //   6975: iload_2
    //   6976: ifeq -> 6837
    //   6979: sipush #-7412
    //   6982: sipush #-20849
    //   6985: invokestatic a : (II)Ljava/lang/String;
    //   6988: invokestatic forName : (Ljava/lang/String;)Ljava/lang/Class;
    //   6991: invokevirtual getDeclaredMethods : ()[Ljava/lang/reflect/Method;
    //   6994: astore #4
    //   6996: aload #4
    //   6998: arraylength
    //   6999: istore #5
    //   7001: iconst_0
    //   7002: istore #6
    //   7004: iload #6
    //   7006: iload #5
    //   7008: if_icmpge -> 7144
    //   7011: aload #4
    //   7013: iload #6
    //   7015: aaload
    //   7016: astore #7
    //   7018: aload #7
    //   7020: invokevirtual getParameterTypes : ()[Ljava/lang/Class;
    //   7023: pop
    //   7024: aload #7
    //   7026: invokevirtual getModifiers : ()I
    //   7029: invokestatic isStatic : (I)Z
    //   7032: ifeq -> 7130
    //   7035: aload #7
    //   7037: invokevirtual getParameterTypes : ()[Ljava/lang/Class;
    //   7040: arraylength
    //   7041: iconst_2
    //   7042: if_icmpne -> 7130
    //   7045: goto -> 7052
    //   7048: invokestatic a : (Ljava/lang/Throwable;)Ljava/lang/Throwable;
    //   7051: athrow
    //   7052: aload #7
    //   7054: invokevirtual getReturnType : ()Ljava/lang/Class;
    //   7057: getstatic java/lang/Boolean.TYPE : Ljava/lang/Class;
    //   7060: if_acmpne -> 7130
    //   7063: goto -> 7070
    //   7066: invokestatic a : (Ljava/lang/Throwable;)Ljava/lang/Throwable;
    //   7069: athrow
    //   7070: aload #7
    //   7072: iconst_1
    //   7073: invokevirtual setAccessible : (Z)V
    //   7076: aload #7
    //   7078: aconst_null
    //   7079: iconst_2
    //   7080: anewarray java/lang/Object
    //   7083: dup
    //   7084: iconst_0
    //   7085: aload_0
    //   7086: aastore
    //   7087: dup
    //   7088: iconst_1
    //   7089: aload_1
    //   7090: ifnonnull -> 7108
    //   7093: goto -> 7100
    //   7096: invokestatic a : (Ljava/lang/Throwable;)Ljava/lang/Throwable;
    //   7099: athrow
    //   7100: aload_1
    //   7101: goto -> 7115
    //   7104: invokestatic a : (Ljava/lang/Throwable;)Ljava/lang/Throwable;
    //   7107: athrow
    //   7108: aload_1
    //   7109: checkcast [B
    //   7112: invokevirtual clone : ()Ljava/lang/Object;
    //   7115: aastore
    //   7116: invokevirtual invoke : (Ljava/lang/Object;[Ljava/lang/Object;)Ljava/lang/Object;
    //   7119: checkcast java/lang/Boolean
    //   7122: invokevirtual booleanValue : ()Z
    //   7125: istore_3
    //   7126: iload_2
    //   7127: ifeq -> 7144
    //   7130: iinc #6, 1
    //   7133: iload_2
    //   7134: ifeq -> 7004
    //   7137: goto -> 7144
    //   7140: invokestatic a : (Ljava/lang/Throwable;)Ljava/lang/Throwable;
    //   7143: athrow
    //   7144: iload_3
    //   7145: ifeq -> 7150
    //   7148: iload_3
    //   7149: ireturn
    //   7150: getstatic burp/Zzgh.Zn : Ljava/lang/String;
    //   7153: getstatic burp/Zstb.ZC : Ljava/lang/Object;
    //   7156: checkcast java/math/BigInteger
    //   7159: invokevirtual intValue : ()I
    //   7162: bipush #32
    //   7164: irem
    //   7165: invokestatic abs : (I)I
    //   7168: invokevirtual charAt : (I)C
    //   7171: getstatic burp/Zm6h.Za : Ljava/lang/String;
    //   7174: getstatic burp/Zgnp.Zm : Ljava/lang/Object;
    //   7177: checkcast java/math/BigInteger
    //   7180: invokevirtual intValue : ()I
    //   7183: bipush #32
    //   7185: irem
    //   7186: invokestatic abs : (I)I
    //   7189: invokevirtual charAt : (I)C
    //   7192: if_icmpgt -> 7537
    //   7195: sipush #-7417
    //   7198: sipush #8049
    //   7201: invokestatic a : (II)Ljava/lang/String;
    //   7204: iconst_1
    //   7205: ldc burp/Zztz
    //   7207: invokevirtual getClassLoader : ()Ljava/lang/ClassLoader;
    //   7210: invokestatic forName : (Ljava/lang/String;ZLjava/lang/ClassLoader;)Ljava/lang/Class;
    //   7213: invokevirtual getDeclaredFields : ()[Ljava/lang/reflect/Field;
    //   7216: astore #4
    //   7218: aload #4
    //   7220: arraylength
    //   7221: istore #5
    //   7223: iconst_0
    //   7224: istore #6
    //   7226: iload #6
    //   7228: iload #5
    //   7230: if_icmpge -> 7368
    //   7233: aload #4
    //   7235: iload #6
    //   7237: aaload
    //   7238: astore #7
    //   7240: aload #7
    //   7242: invokevirtual getModifiers : ()I
    //   7245: invokestatic isStatic : (I)Z
    //   7248: ifne -> 7258
    //   7251: goto -> 7361
    //   7254: invokestatic a : (Ljava/lang/Throwable;)Ljava/lang/Throwable;
    //   7257: athrow
    //   7258: aload #7
    //   7260: invokevirtual getType : ()Ljava/lang/Class;
    //   7263: astore #8
    //   7265: aload #8
    //   7267: ifnull -> 7348
    //   7270: aload #8
    //   7272: invokevirtual isPrimitive : ()Z
    //   7275: ifne -> 7348
    //   7278: goto -> 7285
    //   7281: invokestatic a : (Ljava/lang/Throwable;)Ljava/lang/Throwable;
    //   7284: athrow
    //   7285: aload #8
    //   7287: invokevirtual getPackage : ()Ljava/lang/Package;
    //   7290: ifnull -> 7348
    //   7293: goto -> 7300
    //   7296: invokestatic a : (Ljava/lang/Throwable;)Ljava/lang/Throwable;
    //   7299: athrow
    //   7300: aload #8
    //   7302: invokevirtual getPackage : ()Ljava/lang/Package;
    //   7305: invokevirtual getName : ()Ljava/lang/String;
    //   7308: ifnull -> 7348
    //   7311: goto -> 7318
    //   7314: invokestatic a : (Ljava/lang/Throwable;)Ljava/lang/Throwable;
    //   7317: athrow
    //   7318: aload #8
    //   7320: invokevirtual getPackage : ()Ljava/lang/Package;
    //   7323: invokevirtual getName : ()Ljava/lang/String;
    //   7326: sipush #-7410
    //   7329: sipush #-3236
    //   7332: invokestatic a : (II)Ljava/lang/String;
    //   7335: invokevirtual startsWith : (Ljava/lang/String;)Z
    //   7338: ifne -> 7348
    //   7341: goto -> 7348
    //   7344: invokestatic a : (Ljava/lang/Throwable;)Ljava/lang/Throwable;
    //   7347: athrow
    //   7348: aload #7
    //   7350: iconst_1
    //   7351: invokevirtual setAccessible : (Z)V
    //   7354: aload #7
    //   7356: aconst_null
    //   7357: invokevirtual get : (Ljava/lang/Object;)Ljava/lang/Object;
    //   7360: pop
    //   7361: iinc #6, 1
    //   7364: iload_2
    //   7365: ifeq -> 7226
    //   7368: sipush #-7408
    //   7371: sipush #3341
    //   7374: invokestatic a : (II)Ljava/lang/String;
    //   7377: invokestatic forName : (Ljava/lang/String;)Ljava/lang/Class;
    //   7380: invokevirtual getDeclaredMethods : ()[Ljava/lang/reflect/Method;
    //   7383: astore #4
    //   7385: aload #4
    //   7387: arraylength
    //   7388: istore #5
    //   7390: iconst_0
    //   7391: istore #6
    //   7393: iload #6
    //   7395: iload #5
    //   7397: if_icmpge -> 7533
    //   7400: aload #4
    //   7402: iload #6
    //   7404: aaload
    //   7405: astore #7
    //   7407: aload #7
    //   7409: invokevirtual getParameterTypes : ()[Ljava/lang/Class;
    //   7412: pop
    //   7413: aload #7
    //   7415: invokevirtual getModifiers : ()I
    //   7418: invokestatic isStatic : (I)Z
    //   7421: ifeq -> 7519
    //   7424: aload #7
    //   7426: invokevirtual getParameterTypes : ()[Ljava/lang/Class;
    //   7429: arraylength
    //   7430: iconst_2
    //   7431: if_icmpne -> 7519
    //   7434: goto -> 7441
    //   7437: invokestatic a : (Ljava/lang/Throwable;)Ljava/lang/Throwable;
    //   7440: athrow
    //   7441: aload #7
    //   7443: invokevirtual getReturnType : ()Ljava/lang/Class;
    //   7446: getstatic java/lang/Boolean.TYPE : Ljava/lang/Class;
    //   7449: if_acmpne -> 7519
    //   7452: goto -> 7459
    //   7455: invokestatic a : (Ljava/lang/Throwable;)Ljava/lang/Throwable;
    //   7458: athrow
    //   7459: aload #7
    //   7461: iconst_1
    //   7462: invokevirtual setAccessible : (Z)V
    //   7465: aload #7
    //   7467: aconst_null
    //   7468: iconst_2
    //   7469: anewarray java/lang/Object
    //   7472: dup
    //   7473: iconst_0
    //   7474: aload_0
    //   7475: aastore
    //   7476: dup
    //   7477: iconst_1
    //   7478: aload_1
    //   7479: ifnonnull -> 7497
    //   7482: goto -> 7489
    //   7485: invokestatic a : (Ljava/lang/Throwable;)Ljava/lang/Throwable;
    //   7488: athrow
    //   7489: aload_1
    //   7490: goto -> 7504
    //   7493: invokestatic a : (Ljava/lang/Throwable;)Ljava/lang/Throwable;
    //   7496: athrow
    //   7497: aload_1
    //   7498: checkcast [B
    //   7501: invokevirtual clone : ()Ljava/lang/Object;
    //   7504: aastore
    //   7505: invokevirtual invoke : (Ljava/lang/Object;[Ljava/lang/Object;)Ljava/lang/Object;
    //   7508: checkcast java/lang/Boolean
    //   7511: invokevirtual booleanValue : ()Z
    //   7514: istore_3
    //   7515: iload_2
    //   7516: ifeq -> 7533
    //   7519: iinc #6, 1
    //   7522: iload_2
    //   7523: ifeq -> 7393
    //   7526: goto -> 7533
    //   7529: invokestatic a : (Ljava/lang/Throwable;)Ljava/lang/Throwable;
    //   7532: athrow
    //   7533: iload_2
    //   7534: ifeq -> 7875
    //   7537: sipush #-7401
    //   7540: sipush #-28385
    //   7543: invokestatic a : (II)Ljava/lang/String;
    //   7546: iconst_1
    //   7547: ldc burp/Zrs0
    //   7549: invokevirtual getClassLoader : ()Ljava/lang/ClassLoader;
    //   7552: invokestatic forName : (Ljava/lang/String;ZLjava/lang/ClassLoader;)Ljava/lang/Class;
    //   7555: invokevirtual getDeclaredFields : ()[Ljava/lang/reflect/Field;
    //   7558: astore #4
    //   7560: aload #4
    //   7562: arraylength
    //   7563: istore #5
    //   7565: iconst_0
    //   7566: istore #6
    //   7568: iload #6
    //   7570: iload #5
    //   7572: if_icmpge -> 7710
    //   7575: aload #4
    //   7577: iload #6
    //   7579: aaload
    //   7580: astore #7
    //   7582: aload #7
    //   7584: invokevirtual getModifiers : ()I
    //   7587: invokestatic isStatic : (I)Z
    //   7590: ifne -> 7600
    //   7593: goto -> 7703
    //   7596: invokestatic a : (Ljava/lang/Throwable;)Ljava/lang/Throwable;
    //   7599: athrow
    //   7600: aload #7
    //   7602: invokevirtual getType : ()Ljava/lang/Class;
    //   7605: astore #8
    //   7607: aload #8
    //   7609: ifnull -> 7690
    //   7612: aload #8
    //   7614: invokevirtual isPrimitive : ()Z
    //   7617: ifne -> 7690
    //   7620: goto -> 7627
    //   7623: invokestatic a : (Ljava/lang/Throwable;)Ljava/lang/Throwable;
    //   7626: athrow
    //   7627: aload #8
    //   7629: invokevirtual getPackage : ()Ljava/lang/Package;
    //   7632: ifnull -> 7690
    //   7635: goto -> 7642
    //   7638: invokestatic a : (Ljava/lang/Throwable;)Ljava/lang/Throwable;
    //   7641: athrow
    //   7642: aload #8
    //   7644: invokevirtual getPackage : ()Ljava/lang/Package;
    //   7647: invokevirtual getName : ()Ljava/lang/String;
    //   7650: ifnull -> 7690
    //   7653: goto -> 7660
    //   7656: invokestatic a : (Ljava/lang/Throwable;)Ljava/lang/Throwable;
    //   7659: athrow
    //   7660: aload #8
    //   7662: invokevirtual getPackage : ()Ljava/lang/Package;
    //   7665: invokevirtual getName : ()Ljava/lang/String;
    //   7668: sipush #-7410
    //   7671: sipush #-3236
    //   7674: invokestatic a : (II)Ljava/lang/String;
    //   7677: invokevirtual startsWith : (Ljava/lang/String;)Z
    //   7680: ifne -> 7690
    //   7683: goto -> 7690
    //   7686: invokestatic a : (Ljava/lang/Throwable;)Ljava/lang/Throwable;
    //   7689: athrow
    //   7690: aload #7
    //   7692: iconst_1
    //   7693: invokevirtual setAccessible : (Z)V
    //   7696: aload #7
    //   7698: aconst_null
    //   7699: invokevirtual get : (Ljava/lang/Object;)Ljava/lang/Object;
    //   7702: pop
    //   7703: iinc #6, 1
    //   7706: iload_2
    //   7707: ifeq -> 7568
    //   7710: sipush #-7418
    //   7713: sipush #-12471
    //   7716: invokestatic a : (II)Ljava/lang/String;
    //   7719: invokestatic forName : (Ljava/lang/String;)Ljava/lang/Class;
    //   7722: invokevirtual getDeclaredMethods : ()[Ljava/lang/reflect/Method;
    //   7725: astore #4
    //   7727: aload #4
    //   7729: arraylength
    //   7730: istore #5
    //   7732: iconst_0
    //   7733: istore #6
    //   7735: iload #6
    //   7737: iload #5
    //   7739: if_icmpge -> 7875
    //   7742: aload #4
    //   7744: iload #6
    //   7746: aaload
    //   7747: astore #7
    //   7749: aload #7
    //   7751: invokevirtual getParameterTypes : ()[Ljava/lang/Class;
    //   7754: pop
    //   7755: aload #7
    //   7757: invokevirtual getModifiers : ()I
    //   7760: invokestatic isStatic : (I)Z
    //   7763: ifeq -> 7861
    //   7766: aload #7
    //   7768: invokevirtual getParameterTypes : ()[Ljava/lang/Class;
    //   7771: arraylength
    //   7772: iconst_2
    //   7773: if_icmpne -> 7861
    //   7776: goto -> 7783
    //   7779: invokestatic a : (Ljava/lang/Throwable;)Ljava/lang/Throwable;
    //   7782: athrow
    //   7783: aload #7
    //   7785: invokevirtual getReturnType : ()Ljava/lang/Class;
    //   7788: getstatic java/lang/Boolean.TYPE : Ljava/lang/Class;
    //   7791: if_acmpne -> 7861
    //   7794: goto -> 7801
    //   7797: invokestatic a : (Ljava/lang/Throwable;)Ljava/lang/Throwable;
    //   7800: athrow
    //   7801: aload #7
    //   7803: iconst_1
    //   7804: invokevirtual setAccessible : (Z)V
    //   7807: aload #7
    //   7809: aconst_null
    //   7810: iconst_2
    //   7811: anewarray java/lang/Object
    //   7814: dup
    //   7815: iconst_0
    //   7816: aload_0
    //   7817: aastore
    //   7818: dup
    //   7819: iconst_1
    //   7820: aload_1
    //   7821: ifnonnull -> 7839
    //   7824: goto -> 7831
    //   7827: invokestatic a : (Ljava/lang/Throwable;)Ljava/lang/Throwable;
    //   7830: athrow
    //   7831: aload_1
    //   7832: goto -> 7846
    //   7835: invokestatic a : (Ljava/lang/Throwable;)Ljava/lang/Throwable;
    //   7838: athrow
    //   7839: aload_1
    //   7840: checkcast [B
    //   7843: invokevirtual clone : ()Ljava/lang/Object;
    //   7846: aastore
    //   7847: invokevirtual invoke : (Ljava/lang/Object;[Ljava/lang/Object;)Ljava/lang/Object;
    //   7850: checkcast java/lang/Boolean
    //   7853: invokevirtual booleanValue : ()Z
    //   7856: istore_3
    //   7857: iload_2
    //   7858: ifeq -> 7875
    //   7861: iinc #6, 1
    //   7864: iload_2
    //   7865: ifeq -> 7735
    //   7868: goto -> 7875
    //   7871: invokestatic a : (Ljava/lang/Throwable;)Ljava/lang/Throwable;
    //   7874: athrow
    //   7875: iload_3
    //   7876: ifeq -> 7881
    //   7879: iload_3
    //   7880: ireturn
    //   7881: getstatic burp/Zlr.ZO : Ljava/lang/String;
    //   7884: getstatic burp/Zxjv.ZY : Ljava/lang/Object;
    //   7887: checkcast java/math/BigInteger
    //   7890: invokevirtual intValue : ()I
    //   7893: bipush #32
    //   7895: irem
    //   7896: invokestatic abs : (I)I
    //   7899: invokevirtual charAt : (I)C
    //   7902: getstatic burp/Ztcv.Zl : Ljava/lang/String;
    //   7905: getstatic burp/Ze_t.Za : Ljava/lang/Object;
    //   7908: checkcast java/math/BigInteger
    //   7911: invokevirtual intValue : ()I
    //   7914: bipush #32
    //   7916: irem
    //   7917: invokestatic abs : (I)I
    //   7920: invokevirtual charAt : (I)C
    //   7923: if_icmpgt -> 8268
    //   7926: sipush #-7420
    //   7929: sipush #-3452
    //   7932: invokestatic a : (II)Ljava/lang/String;
    //   7935: iconst_1
    //   7936: ldc burp/Zmy4
    //   7938: invokevirtual getClassLoader : ()Ljava/lang/ClassLoader;
    //   7941: invokestatic forName : (Ljava/lang/String;ZLjava/lang/ClassLoader;)Ljava/lang/Class;
    //   7944: invokevirtual getDeclaredFields : ()[Ljava/lang/reflect/Field;
    //   7947: astore #4
    //   7949: aload #4
    //   7951: arraylength
    //   7952: istore #5
    //   7954: iconst_0
    //   7955: istore #6
    //   7957: iload #6
    //   7959: iload #5
    //   7961: if_icmpge -> 8099
    //   7964: aload #4
    //   7966: iload #6
    //   7968: aaload
    //   7969: astore #7
    //   7971: aload #7
    //   7973: invokevirtual getModifiers : ()I
    //   7976: invokestatic isStatic : (I)Z
    //   7979: ifne -> 7989
    //   7982: goto -> 8092
    //   7985: invokestatic a : (Ljava/lang/Throwable;)Ljava/lang/Throwable;
    //   7988: athrow
    //   7989: aload #7
    //   7991: invokevirtual getType : ()Ljava/lang/Class;
    //   7994: astore #8
    //   7996: aload #8
    //   7998: ifnull -> 8079
    //   8001: aload #8
    //   8003: invokevirtual isPrimitive : ()Z
    //   8006: ifne -> 8079
    //   8009: goto -> 8016
    //   8012: invokestatic a : (Ljava/lang/Throwable;)Ljava/lang/Throwable;
    //   8015: athrow
    //   8016: aload #8
    //   8018: invokevirtual getPackage : ()Ljava/lang/Package;
    //   8021: ifnull -> 8079
    //   8024: goto -> 8031
    //   8027: invokestatic a : (Ljava/lang/Throwable;)Ljava/lang/Throwable;
    //   8030: athrow
    //   8031: aload #8
    //   8033: invokevirtual getPackage : ()Ljava/lang/Package;
    //   8036: invokevirtual getName : ()Ljava/lang/String;
    //   8039: ifnull -> 8079
    //   8042: goto -> 8049
    //   8045: invokestatic a : (Ljava/lang/Throwable;)Ljava/lang/Throwable;
    //   8048: athrow
    //   8049: aload #8
    //   8051: invokevirtual getPackage : ()Ljava/lang/Package;
    //   8054: invokevirtual getName : ()Ljava/lang/String;
    //   8057: sipush #-7410
    //   8060: sipush #-3236
    //   8063: invokestatic a : (II)Ljava/lang/String;
    //   8066: invokevirtual startsWith : (Ljava/lang/String;)Z
    //   8069: ifne -> 8079
    //   8072: goto -> 8079
    //   8075: invokestatic a : (Ljava/lang/Throwable;)Ljava/lang/Throwable;
    //   8078: athrow
    //   8079: aload #7
    //   8081: iconst_1
    //   8082: invokevirtual setAccessible : (Z)V
    //   8085: aload #7
    //   8087: aconst_null
    //   8088: invokevirtual get : (Ljava/lang/Object;)Ljava/lang/Object;
    //   8091: pop
    //   8092: iinc #6, 1
    //   8095: iload_2
    //   8096: ifeq -> 7957
    //   8099: sipush #-7413
    //   8102: sipush #-17022
    //   8105: invokestatic a : (II)Ljava/lang/String;
    //   8108: invokestatic forName : (Ljava/lang/String;)Ljava/lang/Class;
    //   8111: invokevirtual getDeclaredMethods : ()[Ljava/lang/reflect/Method;
    //   8114: astore #4
    //   8116: aload #4
    //   8118: arraylength
    //   8119: istore #5
    //   8121: iconst_0
    //   8122: istore #6
    //   8124: iload #6
    //   8126: iload #5
    //   8128: if_icmpge -> 8264
    //   8131: aload #4
    //   8133: iload #6
    //   8135: aaload
    //   8136: astore #7
    //   8138: aload #7
    //   8140: invokevirtual getParameterTypes : ()[Ljava/lang/Class;
    //   8143: pop
    //   8144: aload #7
    //   8146: invokevirtual getModifiers : ()I
    //   8149: invokestatic isStatic : (I)Z
    //   8152: ifeq -> 8250
    //   8155: aload #7
    //   8157: invokevirtual getParameterTypes : ()[Ljava/lang/Class;
    //   8160: arraylength
    //   8161: iconst_2
    //   8162: if_icmpne -> 8250
    //   8165: goto -> 8172
    //   8168: invokestatic a : (Ljava/lang/Throwable;)Ljava/lang/Throwable;
    //   8171: athrow
    //   8172: aload #7
    //   8174: invokevirtual getReturnType : ()Ljava/lang/Class;
    //   8177: getstatic java/lang/Boolean.TYPE : Ljava/lang/Class;
    //   8180: if_acmpne -> 8250
    //   8183: goto -> 8190
    //   8186: invokestatic a : (Ljava/lang/Throwable;)Ljava/lang/Throwable;
    //   8189: athrow
    //   8190: aload #7
    //   8192: iconst_1
    //   8193: invokevirtual setAccessible : (Z)V
    //   8196: aload #7
    //   8198: aconst_null
    //   8199: iconst_2
    //   8200: anewarray java/lang/Object
    //   8203: dup
    //   8204: iconst_0
    //   8205: aload_0
    //   8206: aastore
    //   8207: dup
    //   8208: iconst_1
    //   8209: aload_1
    //   8210: ifnonnull -> 8228
    //   8213: goto -> 8220
    //   8216: invokestatic a : (Ljava/lang/Throwable;)Ljava/lang/Throwable;
    //   8219: athrow
    //   8220: aload_1
    //   8221: goto -> 8235
    //   8224: invokestatic a : (Ljava/lang/Throwable;)Ljava/lang/Throwable;
    //   8227: athrow
    //   8228: aload_1
    //   8229: checkcast [B
    //   8232: invokevirtual clone : ()Ljava/lang/Object;
    //   8235: aastore
    //   8236: invokevirtual invoke : (Ljava/lang/Object;[Ljava/lang/Object;)Ljava/lang/Object;
    //   8239: checkcast java/lang/Boolean
    //   8242: invokevirtual booleanValue : ()Z
    //   8245: istore_3
    //   8246: iload_2
    //   8247: ifeq -> 8264
    //   8250: iinc #6, 1
    //   8253: iload_2
    //   8254: ifeq -> 8124
    //   8257: goto -> 8264
    //   8260: invokestatic a : (Ljava/lang/Throwable;)Ljava/lang/Throwable;
    //   8263: athrow
    //   8264: iload_2
    //   8265: ifeq -> 8606
    //   8268: sipush #-7393
    //   8271: sipush #23976
    //   8274: invokestatic a : (II)Ljava/lang/String;
    //   8277: iconst_1
    //   8278: ldc burp/Zlpu
    //   8280: invokevirtual getClassLoader : ()Ljava/lang/ClassLoader;
    //   8283: invokestatic forName : (Ljava/lang/String;ZLjava/lang/ClassLoader;)Ljava/lang/Class;
    //   8286: invokevirtual getDeclaredFields : ()[Ljava/lang/reflect/Field;
    //   8289: astore #4
    //   8291: aload #4
    //   8293: arraylength
    //   8294: istore #5
    //   8296: iconst_0
    //   8297: istore #6
    //   8299: iload #6
    //   8301: iload #5
    //   8303: if_icmpge -> 8441
    //   8306: aload #4
    //   8308: iload #6
    //   8310: aaload
    //   8311: astore #7
    //   8313: aload #7
    //   8315: invokevirtual getModifiers : ()I
    //   8318: invokestatic isStatic : (I)Z
    //   8321: ifne -> 8331
    //   8324: goto -> 8434
    //   8327: invokestatic a : (Ljava/lang/Throwable;)Ljava/lang/Throwable;
    //   8330: athrow
    //   8331: aload #7
    //   8333: invokevirtual getType : ()Ljava/lang/Class;
    //   8336: astore #8
    //   8338: aload #8
    //   8340: ifnull -> 8421
    //   8343: aload #8
    //   8345: invokevirtual isPrimitive : ()Z
    //   8348: ifne -> 8421
    //   8351: goto -> 8358
    //   8354: invokestatic a : (Ljava/lang/Throwable;)Ljava/lang/Throwable;
    //   8357: athrow
    //   8358: aload #8
    //   8360: invokevirtual getPackage : ()Ljava/lang/Package;
    //   8363: ifnull -> 8421
    //   8366: goto -> 8373
    //   8369: invokestatic a : (Ljava/lang/Throwable;)Ljava/lang/Throwable;
    //   8372: athrow
    //   8373: aload #8
    //   8375: invokevirtual getPackage : ()Ljava/lang/Package;
    //   8378: invokevirtual getName : ()Ljava/lang/String;
    //   8381: ifnull -> 8421
    //   8384: goto -> 8391
    //   8387: invokestatic a : (Ljava/lang/Throwable;)Ljava/lang/Throwable;
    //   8390: athrow
    //   8391: aload #8
    //   8393: invokevirtual getPackage : ()Ljava/lang/Package;
    //   8396: invokevirtual getName : ()Ljava/lang/String;
    //   8399: sipush #-7410
    //   8402: sipush #-3236
    //   8405: invokestatic a : (II)Ljava/lang/String;
    //   8408: invokevirtual startsWith : (Ljava/lang/String;)Z
    //   8411: ifne -> 8421
    //   8414: goto -> 8421
    //   8417: invokestatic a : (Ljava/lang/Throwable;)Ljava/lang/Throwable;
    //   8420: athrow
    //   8421: aload #7
    //   8423: iconst_1
    //   8424: invokevirtual setAccessible : (Z)V
    //   8427: aload #7
    //   8429: aconst_null
    //   8430: invokevirtual get : (Ljava/lang/Object;)Ljava/lang/Object;
    //   8433: pop
    //   8434: iinc #6, 1
    //   8437: iload_2
    //   8438: ifeq -> 8299
    //   8441: sipush #-7423
    //   8444: sipush #-1530
    //   8447: invokestatic a : (II)Ljava/lang/String;
    //   8450: invokestatic forName : (Ljava/lang/String;)Ljava/lang/Class;
    //   8453: invokevirtual getDeclaredMethods : ()[Ljava/lang/reflect/Method;
    //   8456: astore #4
    //   8458: aload #4
    //   8460: arraylength
    //   8461: istore #5
    //   8463: iconst_0
    //   8464: istore #6
    //   8466: iload #6
    //   8468: iload #5
    //   8470: if_icmpge -> 8606
    //   8473: aload #4
    //   8475: iload #6
    //   8477: aaload
    //   8478: astore #7
    //   8480: aload #7
    //   8482: invokevirtual getParameterTypes : ()[Ljava/lang/Class;
    //   8485: pop
    //   8486: aload #7
    //   8488: invokevirtual getModifiers : ()I
    //   8491: invokestatic isStatic : (I)Z
    //   8494: ifeq -> 8592
    //   8497: aload #7
    //   8499: invokevirtual getParameterTypes : ()[Ljava/lang/Class;
    //   8502: arraylength
    //   8503: iconst_2
    //   8504: if_icmpne -> 8592
    //   8507: goto -> 8514
    //   8510: invokestatic a : (Ljava/lang/Throwable;)Ljava/lang/Throwable;
    //   8513: athrow
    //   8514: aload #7
    //   8516: invokevirtual getReturnType : ()Ljava/lang/Class;
    //   8519: getstatic java/lang/Boolean.TYPE : Ljava/lang/Class;
    //   8522: if_acmpne -> 8592
    //   8525: goto -> 8532
    //   8528: invokestatic a : (Ljava/lang/Throwable;)Ljava/lang/Throwable;
    //   8531: athrow
    //   8532: aload #7
    //   8534: iconst_1
    //   8535: invokevirtual setAccessible : (Z)V
    //   8538: aload #7
    //   8540: aconst_null
    //   8541: iconst_2
    //   8542: anewarray java/lang/Object
    //   8545: dup
    //   8546: iconst_0
    //   8547: aload_0
    //   8548: aastore
    //   8549: dup
    //   8550: iconst_1
    //   8551: aload_1
    //   8552: ifnonnull -> 8570
    //   8555: goto -> 8562
    //   8558: invokestatic a : (Ljava/lang/Throwable;)Ljava/lang/Throwable;
    //   8561: athrow
    //   8562: aload_1
    //   8563: goto -> 8577
    //   8566: invokestatic a : (Ljava/lang/Throwable;)Ljava/lang/Throwable;
    //   8569: athrow
    //   8570: aload_1
    //   8571: checkcast [B
    //   8574: invokevirtual clone : ()Ljava/lang/Object;
    //   8577: aastore
    //   8578: invokevirtual invoke : (Ljava/lang/Object;[Ljava/lang/Object;)Ljava/lang/Object;
    //   8581: checkcast java/lang/Boolean
    //   8584: invokevirtual booleanValue : ()Z
    //   8587: istore_3
    //   8588: iload_2
    //   8589: ifeq -> 8606
    //   8592: iinc #6, 1
    //   8595: iload_2
    //   8596: ifeq -> 8466
    //   8599: goto -> 8606
    //   8602: invokestatic a : (Ljava/lang/Throwable;)Ljava/lang/Throwable;
    //   8605: athrow
    //   8606: iload_3
    //   8607: ifeq -> 8612
    //   8610: iload_3
    //   8611: ireturn
    //   8612: getstatic burp/Ze_t.ZZ : Ljava/lang/String;
    //   8615: getstatic burp/Zv8c.Zx : Ljava/lang/Object;
    //   8618: checkcast java/math/BigInteger
    //   8621: invokevirtual intValue : ()I
    //   8624: bipush #32
    //   8626: irem
    //   8627: invokestatic abs : (I)I
    //   8630: invokevirtual charAt : (I)C
    //   8633: getstatic burp/Zmyg.ZE : Ljava/lang/String;
    //   8636: getstatic burp/Zix.ZO : Ljava/lang/Object;
    //   8639: checkcast java/math/BigInteger
    //   8642: invokevirtual intValue : ()I
    //   8645: bipush #32
    //   8647: irem
    //   8648: invokestatic abs : (I)I
    //   8651: invokevirtual charAt : (I)C
    //   8654: if_icmpgt -> 8999
    //   8657: sipush #-7421
    //   8660: sipush #8984
    //   8663: invokestatic a : (II)Ljava/lang/String;
    //   8666: iconst_1
    //   8667: ldc burp/Zry9
    //   8669: invokevirtual getClassLoader : ()Ljava/lang/ClassLoader;
    //   8672: invokestatic forName : (Ljava/lang/String;ZLjava/lang/ClassLoader;)Ljava/lang/Class;
    //   8675: invokevirtual getDeclaredFields : ()[Ljava/lang/reflect/Field;
    //   8678: astore #4
    //   8680: aload #4
    //   8682: arraylength
    //   8683: istore #5
    //   8685: iconst_0
    //   8686: istore #6
    //   8688: iload #6
    //   8690: iload #5
    //   8692: if_icmpge -> 8830
    //   8695: aload #4
    //   8697: iload #6
    //   8699: aaload
    //   8700: astore #7
    //   8702: aload #7
    //   8704: invokevirtual getModifiers : ()I
    //   8707: invokestatic isStatic : (I)Z
    //   8710: ifne -> 8720
    //   8713: goto -> 8823
    //   8716: invokestatic a : (Ljava/lang/Throwable;)Ljava/lang/Throwable;
    //   8719: athrow
    //   8720: aload #7
    //   8722: invokevirtual getType : ()Ljava/lang/Class;
    //   8725: astore #8
    //   8727: aload #8
    //   8729: ifnull -> 8810
    //   8732: aload #8
    //   8734: invokevirtual isPrimitive : ()Z
    //   8737: ifne -> 8810
    //   8740: goto -> 8747
    //   8743: invokestatic a : (Ljava/lang/Throwable;)Ljava/lang/Throwable;
    //   8746: athrow
    //   8747: aload #8
    //   8749: invokevirtual getPackage : ()Ljava/lang/Package;
    //   8752: ifnull -> 8810
    //   8755: goto -> 8762
    //   8758: invokestatic a : (Ljava/lang/Throwable;)Ljava/lang/Throwable;
    //   8761: athrow
    //   8762: aload #8
    //   8764: invokevirtual getPackage : ()Ljava/lang/Package;
    //   8767: invokevirtual getName : ()Ljava/lang/String;
    //   8770: ifnull -> 8810
    //   8773: goto -> 8780
    //   8776: invokestatic a : (Ljava/lang/Throwable;)Ljava/lang/Throwable;
    //   8779: athrow
    //   8780: aload #8
    //   8782: invokevirtual getPackage : ()Ljava/lang/Package;
    //   8785: invokevirtual getName : ()Ljava/lang/String;
    //   8788: sipush #-7410
    //   8791: sipush #-3236
    //   8794: invokestatic a : (II)Ljava/lang/String;
    //   8797: invokevirtual startsWith : (Ljava/lang/String;)Z
    //   8800: ifne -> 8810
    //   8803: goto -> 8810
    //   8806: invokestatic a : (Ljava/lang/Throwable;)Ljava/lang/Throwable;
    //   8809: athrow
    //   8810: aload #7
    //   8812: iconst_1
    //   8813: invokevirtual setAccessible : (Z)V
    //   8816: aload #7
    //   8818: aconst_null
    //   8819: invokevirtual get : (Ljava/lang/Object;)Ljava/lang/Object;
    //   8822: pop
    //   8823: iinc #6, 1
    //   8826: iload_2
    //   8827: ifeq -> 8688
    //   8830: sipush #-7419
    //   8833: sipush #-21646
    //   8836: invokestatic a : (II)Ljava/lang/String;
    //   8839: invokestatic forName : (Ljava/lang/String;)Ljava/lang/Class;
    //   8842: invokevirtual getDeclaredMethods : ()[Ljava/lang/reflect/Method;
    //   8845: astore #4
    //   8847: aload #4
    //   8849: arraylength
    //   8850: istore #5
    //   8852: iconst_0
    //   8853: istore #6
    //   8855: iload #6
    //   8857: iload #5
    //   8859: if_icmpge -> 8995
    //   8862: aload #4
    //   8864: iload #6
    //   8866: aaload
    //   8867: astore #7
    //   8869: aload #7
    //   8871: invokevirtual getParameterTypes : ()[Ljava/lang/Class;
    //   8874: pop
    //   8875: aload #7
    //   8877: invokevirtual getModifiers : ()I
    //   8880: invokestatic isStatic : (I)Z
    //   8883: ifeq -> 8981
    //   8886: aload #7
    //   8888: invokevirtual getParameterTypes : ()[Ljava/lang/Class;
    //   8891: arraylength
    //   8892: iconst_2
    //   8893: if_icmpne -> 8981
    //   8896: goto -> 8903
    //   8899: invokestatic a : (Ljava/lang/Throwable;)Ljava/lang/Throwable;
    //   8902: athrow
    //   8903: aload #7
    //   8905: invokevirtual getReturnType : ()Ljava/lang/Class;
    //   8908: getstatic java/lang/Boolean.TYPE : Ljava/lang/Class;
    //   8911: if_acmpne -> 8981
    //   8914: goto -> 8921
    //   8917: invokestatic a : (Ljava/lang/Throwable;)Ljava/lang/Throwable;
    //   8920: athrow
    //   8921: aload #7
    //   8923: iconst_1
    //   8924: invokevirtual setAccessible : (Z)V
    //   8927: aload #7
    //   8929: aconst_null
    //   8930: iconst_2
    //   8931: anewarray java/lang/Object
    //   8934: dup
    //   8935: iconst_0
    //   8936: aload_0
    //   8937: aastore
    //   8938: dup
    //   8939: iconst_1
    //   8940: aload_1
    //   8941: ifnonnull -> 8959
    //   8944: goto -> 8951
    //   8947: invokestatic a : (Ljava/lang/Throwable;)Ljava/lang/Throwable;
    //   8950: athrow
    //   8951: aload_1
    //   8952: goto -> 8966
    //   8955: invokestatic a : (Ljava/lang/Throwable;)Ljava/lang/Throwable;
    //   8958: athrow
    //   8959: aload_1
    //   8960: checkcast [B
    //   8963: invokevirtual clone : ()Ljava/lang/Object;
    //   8966: aastore
    //   8967: invokevirtual invoke : (Ljava/lang/Object;[Ljava/lang/Object;)Ljava/lang/Object;
    //   8970: checkcast java/lang/Boolean
    //   8973: invokevirtual booleanValue : ()Z
    //   8976: istore_3
    //   8977: iload_2
    //   8978: ifeq -> 8995
    //   8981: iinc #6, 1
    //   8984: iload_2
    //   8985: ifeq -> 8855
    //   8988: goto -> 8995
    //   8991: invokestatic a : (Ljava/lang/Throwable;)Ljava/lang/Throwable;
    //   8994: athrow
    //   8995: iload_2
    //   8996: ifeq -> 9337
    //   8999: sipush #-7403
    //   9002: sipush #15815
    //   9005: invokestatic a : (II)Ljava/lang/String;
    //   9008: iconst_1
    //   9009: ldc burp/Ze54
    //   9011: invokevirtual getClassLoader : ()Ljava/lang/ClassLoader;
    //   9014: invokestatic forName : (Ljava/lang/String;ZLjava/lang/ClassLoader;)Ljava/lang/Class;
    //   9017: invokevirtual getDeclaredFields : ()[Ljava/lang/reflect/Field;
    //   9020: astore #4
    //   9022: aload #4
    //   9024: arraylength
    //   9025: istore #5
    //   9027: iconst_0
    //   9028: istore #6
    //   9030: iload #6
    //   9032: iload #5
    //   9034: if_icmpge -> 9172
    //   9037: aload #4
    //   9039: iload #6
    //   9041: aaload
    //   9042: astore #7
    //   9044: aload #7
    //   9046: invokevirtual getModifiers : ()I
    //   9049: invokestatic isStatic : (I)Z
    //   9052: ifne -> 9062
    //   9055: goto -> 9165
    //   9058: invokestatic a : (Ljava/lang/Throwable;)Ljava/lang/Throwable;
    //   9061: athrow
    //   9062: aload #7
    //   9064: invokevirtual getType : ()Ljava/lang/Class;
    //   9067: astore #8
    //   9069: aload #8
    //   9071: ifnull -> 9152
    //   9074: aload #8
    //   9076: invokevirtual isPrimitive : ()Z
    //   9079: ifne -> 9152
    //   9082: goto -> 9089
    //   9085: invokestatic a : (Ljava/lang/Throwable;)Ljava/lang/Throwable;
    //   9088: athrow
    //   9089: aload #8
    //   9091: invokevirtual getPackage : ()Ljava/lang/Package;
    //   9094: ifnull -> 9152
    //   9097: goto -> 9104
    //   9100: invokestatic a : (Ljava/lang/Throwable;)Ljava/lang/Throwable;
    //   9103: athrow
    //   9104: aload #8
    //   9106: invokevirtual getPackage : ()Ljava/lang/Package;
    //   9109: invokevirtual getName : ()Ljava/lang/String;
    //   9112: ifnull -> 9152
    //   9115: goto -> 9122
    //   9118: invokestatic a : (Ljava/lang/Throwable;)Ljava/lang/Throwable;
    //   9121: athrow
    //   9122: aload #8
    //   9124: invokevirtual getPackage : ()Ljava/lang/Package;
    //   9127: invokevirtual getName : ()Ljava/lang/String;
    //   9130: sipush #-7410
    //   9133: sipush #-3236
    //   9136: invokestatic a : (II)Ljava/lang/String;
    //   9139: invokevirtual startsWith : (Ljava/lang/String;)Z
    //   9142: ifne -> 9152
    //   9145: goto -> 9152
    //   9148: invokestatic a : (Ljava/lang/Throwable;)Ljava/lang/Throwable;
    //   9151: athrow
    //   9152: aload #7
    //   9154: iconst_1
    //   9155: invokevirtual setAccessible : (Z)V
    //   9158: aload #7
    //   9160: aconst_null
    //   9161: invokevirtual get : (Ljava/lang/Object;)Ljava/lang/Object;
    //   9164: pop
    //   9165: iinc #6, 1
    //   9168: iload_2
    //   9169: ifeq -> 9030
    //   9172: sipush #-7424
    //   9175: sipush #7251
    //   9178: invokestatic a : (II)Ljava/lang/String;
    //   9181: invokestatic forName : (Ljava/lang/String;)Ljava/lang/Class;
    //   9184: invokevirtual getDeclaredMethods : ()[Ljava/lang/reflect/Method;
    //   9187: astore #4
    //   9189: aload #4
    //   9191: arraylength
    //   9192: istore #5
    //   9194: iconst_0
    //   9195: istore #6
    //   9197: iload #6
    //   9199: iload #5
    //   9201: if_icmpge -> 9337
    //   9204: aload #4
    //   9206: iload #6
    //   9208: aaload
    //   9209: astore #7
    //   9211: aload #7
    //   9213: invokevirtual getParameterTypes : ()[Ljava/lang/Class;
    //   9216: pop
    //   9217: aload #7
    //   9219: invokevirtual getModifiers : ()I
    //   9222: invokestatic isStatic : (I)Z
    //   9225: ifeq -> 9323
    //   9228: aload #7
    //   9230: invokevirtual getParameterTypes : ()[Ljava/lang/Class;
    //   9233: arraylength
    //   9234: iconst_2
    //   9235: if_icmpne -> 9323
    //   9238: goto -> 9245
    //   9241: invokestatic a : (Ljava/lang/Throwable;)Ljava/lang/Throwable;
    //   9244: athrow
    //   9245: aload #7
    //   9247: invokevirtual getReturnType : ()Ljava/lang/Class;
    //   9250: getstatic java/lang/Boolean.TYPE : Ljava/lang/Class;
    //   9253: if_acmpne -> 9323
    //   9256: goto -> 9263
    //   9259: invokestatic a : (Ljava/lang/Throwable;)Ljava/lang/Throwable;
    //   9262: athrow
    //   9263: aload #7
    //   9265: iconst_1
    //   9266: invokevirtual setAccessible : (Z)V
    //   9269: aload #7
    //   9271: aconst_null
    //   9272: iconst_2
    //   9273: anewarray java/lang/Object
    //   9276: dup
    //   9277: iconst_0
    //   9278: aload_0
    //   9279: aastore
    //   9280: dup
    //   9281: iconst_1
    //   9282: aload_1
    //   9283: ifnonnull -> 9301
    //   9286: goto -> 9293
    //   9289: invokestatic a : (Ljava/lang/Throwable;)Ljava/lang/Throwable;
    //   9292: athrow
    //   9293: aload_1
    //   9294: goto -> 9308
    //   9297: invokestatic a : (Ljava/lang/Throwable;)Ljava/lang/Throwable;
    //   9300: athrow
    //   9301: aload_1
    //   9302: checkcast [B
    //   9305: invokevirtual clone : ()Ljava/lang/Object;
    //   9308: aastore
    //   9309: invokevirtual invoke : (Ljava/lang/Object;[Ljava/lang/Object;)Ljava/lang/Object;
    //   9312: checkcast java/lang/Boolean
    //   9315: invokevirtual booleanValue : ()Z
    //   9318: istore_3
    //   9319: iload_2
    //   9320: ifeq -> 9337
    //   9323: iinc #6, 1
    //   9326: iload_2
    //   9327: ifeq -> 9197
    //   9330: goto -> 9337
    //   9333: invokestatic a : (Ljava/lang/Throwable;)Ljava/lang/Throwable;
    //   9336: athrow
    //   9337: iload_3
    //   9338: ireturn
    //   9339: astore_3
    //   9340: new java/lang/Exception
    //   9343: dup
    //   9344: aload_3
    //   9345: invokevirtual getMessage : ()Ljava/lang/String;
    //   9348: invokespecial <init> : (Ljava/lang/String;)V
    //   9351: athrow
    // Exception table:
    //   from	to	target	type
    //   4	6418	9339	java/lang/Throwable
    //   4377	4391	4391	java/lang/Throwable
    //   4402	4415	4418	java/lang/Throwable
    //   4407	4430	4433	java/lang/Throwable
    //   4422	4448	4451	java/lang/Throwable
    //   4437	4478	4481	java/lang/Throwable
    //   4541	4568	4571	java/lang/Throwable
    //   4558	4589	4592	java/lang/Throwable
    //   4575	4619	4622	java/lang/Throwable
    //   4596	4630	4630	java/lang/Throwable
    //   4641	4657	4660	java/lang/Throwable
    //   4969	4993	4996	java/lang/Throwable
    //   5067	5104	5104	java/lang/Throwable
    //   5108	5129	5129	java/lang/Throwable
    //   5133	5163	5163	java/lang/Throwable
    //   5346	5683	5686	java/lang/Throwable
    //   5517	5527	5527	java/lang/Throwable
    //   5531	5543	5543	java/lang/Throwable
    //   5547	5559	5559	java/lang/Throwable
    //   5563	5576	5576	java/lang/Throwable
    //   5580	5593	5593	java/lang/Throwable
    //   5779	5793	5793	java/lang/Throwable
    //   5804	5817	5820	java/lang/Throwable
    //   5809	5832	5835	java/lang/Throwable
    //   5824	5850	5853	java/lang/Throwable
    //   5839	5880	5883	java/lang/Throwable
    //   5946	5973	5976	java/lang/Throwable
    //   5963	5991	5994	java/lang/Throwable
    //   5980	6021	6024	java/lang/Throwable
    //   5998	6032	6032	java/lang/Throwable
    //   6054	6065	6068	java/lang/Throwable
    //   6120	6134	6134	java/lang/Throwable
    //   6145	6158	6161	java/lang/Throwable
    //   6150	6173	6176	java/lang/Throwable
    //   6165	6191	6194	java/lang/Throwable
    //   6180	6221	6224	java/lang/Throwable
    //   6287	6314	6317	java/lang/Throwable
    //   6304	6332	6335	java/lang/Throwable
    //   6321	6362	6365	java/lang/Throwable
    //   6339	6373	6373	java/lang/Throwable
    //   6395	6406	6409	java/lang/Throwable
    //   6419	7149	9339	java/lang/Throwable
    //   6509	6523	6523	java/lang/Throwable
    //   6534	6547	6550	java/lang/Throwable
    //   6539	6562	6565	java/lang/Throwable
    //   6554	6580	6583	java/lang/Throwable
    //   6569	6610	6613	java/lang/Throwable
    //   6676	6703	6706	java/lang/Throwable
    //   6693	6721	6724	java/lang/Throwable
    //   6710	6751	6754	java/lang/Throwable
    //   6728	6762	6762	java/lang/Throwable
    //   6784	6795	6798	java/lang/Throwable
    //   6851	6865	6865	java/lang/Throwable
    //   6876	6889	6892	java/lang/Throwable
    //   6881	6904	6907	java/lang/Throwable
    //   6896	6922	6925	java/lang/Throwable
    //   6911	6952	6955	java/lang/Throwable
    //   7018	7045	7048	java/lang/Throwable
    //   7035	7063	7066	java/lang/Throwable
    //   7052	7093	7096	java/lang/Throwable
    //   7070	7104	7104	java/lang/Throwable
    //   7126	7137	7140	java/lang/Throwable
    //   7150	7880	9339	java/lang/Throwable
    //   7240	7254	7254	java/lang/Throwable
    //   7265	7278	7281	java/lang/Throwable
    //   7270	7293	7296	java/lang/Throwable
    //   7285	7311	7314	java/lang/Throwable
    //   7300	7341	7344	java/lang/Throwable
    //   7407	7434	7437	java/lang/Throwable
    //   7424	7452	7455	java/lang/Throwable
    //   7441	7482	7485	java/lang/Throwable
    //   7459	7493	7493	java/lang/Throwable
    //   7515	7526	7529	java/lang/Throwable
    //   7582	7596	7596	java/lang/Throwable
    //   7607	7620	7623	java/lang/Throwable
    //   7612	7635	7638	java/lang/Throwable
    //   7627	7653	7656	java/lang/Throwable
    //   7642	7683	7686	java/lang/Throwable
    //   7749	7776	7779	java/lang/Throwable
    //   7766	7794	7797	java/lang/Throwable
    //   7783	7824	7827	java/lang/Throwable
    //   7801	7835	7835	java/lang/Throwable
    //   7857	7868	7871	java/lang/Throwable
    //   7881	8611	9339	java/lang/Throwable
    //   7971	7985	7985	java/lang/Throwable
    //   7996	8009	8012	java/lang/Throwable
    //   8001	8024	8027	java/lang/Throwable
    //   8016	8042	8045	java/lang/Throwable
    //   8031	8072	8075	java/lang/Throwable
    //   8138	8165	8168	java/lang/Throwable
    //   8155	8183	8186	java/lang/Throwable
    //   8172	8213	8216	java/lang/Throwable
    //   8190	8224	8224	java/lang/Throwable
    //   8246	8257	8260	java/lang/Throwable
    //   8313	8327	8327	java/lang/Throwable
    //   8338	8351	8354	java/lang/Throwable
    //   8343	8366	8369	java/lang/Throwable
    //   8358	8384	8387	java/lang/Throwable
    //   8373	8414	8417	java/lang/Throwable
    //   8480	8507	8510	java/lang/Throwable
    //   8497	8525	8528	java/lang/Throwable
    //   8514	8555	8558	java/lang/Throwable
    //   8532	8566	8566	java/lang/Throwable
    //   8588	8599	8602	java/lang/Throwable
    //   8612	9338	9339	java/lang/Throwable
    //   8702	8716	8716	java/lang/Throwable
    //   8727	8740	8743	java/lang/Throwable
    //   8732	8755	8758	java/lang/Throwable
    //   8747	8773	8776	java/lang/Throwable
    //   8762	8803	8806	java/lang/Throwable
    //   8869	8896	8899	java/lang/Throwable
    //   8886	8914	8917	java/lang/Throwable
    //   8903	8944	8947	java/lang/Throwable
    //   8921	8955	8955	java/lang/Throwable
    //   8977	8988	8991	java/lang/Throwable
    //   9044	9058	9058	java/lang/Throwable
    //   9069	9082	9085	java/lang/Throwable
    //   9074	9097	9100	java/lang/Throwable
    //   9089	9115	9118	java/lang/Throwable
    //   9104	9145	9148	java/lang/Throwable
    //   9211	9238	9241	java/lang/Throwable
    //   9228	9256	9259	java/lang/Throwable
    //   9245	9286	9289	java/lang/Throwable
    //   9263	9297	9297	java/lang/Throwable
    //   9319	9330	9333	java/lang/Throwable
  }
  
  static void Zv(Object paramObject) {
    Zz0w.ZO = a(-7415, 32716);
    Zz0w.ZF = new BigInteger(a(-7399, 5481));
    boolean bool = Zt2e.ZK();
    try {
      try {
        if (Zk7e.ZP.charAt(Math.abs(((BigInteger)Zeoy.Zt).intValue() % 32)) > Zkm0.ZL.charAt(Math.abs(((BigInteger)Zg4k.ZE).intValue() % 32))) {
          try {
            Ze64.ZL(Class.forName(a(-7394, -21723)));
            if (bool)
              Zxo7.ZY(Class.forName(a(-7422, -6976))); 
          } catch (Throwable throwable) {
            throw a(null);
          } 
          return;
        } 
      } catch (Throwable throwable) {
        throw a(null);
      } 
      Zxo7.ZY(Class.forName(a(-7422, -6976)));
    } catch (Throwable throwable) {}
  }
  
  static {
    // Byte code:
    //   0: bipush #35
    //   2: anewarray java/lang/String
    //   5: astore #5
    //   7: iconst_0
    //   8: istore_3
    //   9: ldc 'yw\\t"Pk\\t$7#TLC ([=4g3x}z! Et-yuoW:[^| `>dkg'\\tu]1J\\tL).t,a\\tfkFjr{\\t\\nO\\t\\tQpLZ!\\tqHR1"r$?\\b\\nMhlA i5z\\t$-FTGf\\t S5pudz@\\fs\]?a\\b \\t@\\r\\tvAiyKe.e\\t;b\\tCXe\\tv%Q\\t<d bW\\tD[\\r\\t_.L0\\tCo5)5\\tDs*E][U\\ths?3Ek/\\tn*j+ f\\t{j`c:zG&qWAx \\f")J/}us\\b;!\\t|`(]c\\to\\t2wZUP0t'
    //   11: dup
    //   12: astore_2
    //   13: invokevirtual length : ()I
    //   16: istore #4
    //   18: bipush #9
    //   20: istore_1
    //   21: iconst_m1
    //   22: istore_0
    //   23: bipush #91
    //   25: iinc #0, 1
    //   28: aload_2
    //   29: iload_0
    //   30: dup
    //   31: iload_1
    //   32: iadd
    //   33: invokevirtual substring : (II)Ljava/lang/String;
    //   36: iconst_m1
    //   37: goto -> 143
    //   40: aload #5
    //   42: swap
    //   43: iload_3
    //   44: iinc #3, 1
    //   47: swap
    //   48: aastore
    //   49: iload_0
    //   50: iload_1
    //   51: iadd
    //   52: dup
    //   53: istore_0
    //   54: iload #4
    //   56: if_icmpge -> 68
    //   59: aload_2
    //   60: iload_0
    //   61: invokevirtual charAt : (I)C
    //   64: istore_1
    //   65: goto -> 23
    //   68: ldc '\\bbu'
    //   70: dup
    //   71: astore_2
    //   72: invokevirtual length : ()I
    //   75: istore #4
    //   77: bipush #9
    //   79: istore_1
    //   80: iconst_m1
    //   81: istore_0
    //   82: bipush #10
    //   84: iinc #0, 1
    //   87: aload_2
    //   88: iload_0
    //   89: dup
    //   90: iload_1
    //   91: iadd
    //   92: invokevirtual substring : (II)Ljava/lang/String;
    //   95: iconst_0
    //   96: goto -> 143
    //   99: aload #5
    //   101: swap
    //   102: iload_3
    //   103: iinc #3, 1
    //   106: swap
    //   107: aastore
    //   108: iload_0
    //   109: iload_1
    //   110: iadd
    //   111: dup
    //   112: istore_0
    //   113: iload #4
    //   115: if_icmpge -> 127
    //   118: aload_2
    //   119: iload_0
    //   120: invokevirtual charAt : (I)C
    //   123: istore_1
    //   124: goto -> 82
    //   127: aload #5
    //   129: putstatic burp/Zram.a : [Ljava/lang/String;
    //   132: bipush #35
    //   134: anewarray java/lang/String
    //   137: putstatic burp/Zram.b : [Ljava/lang/String;
    //   140: goto -> 300
    //   143: dup_x2
    //   144: pop
    //   145: invokevirtual toCharArray : ()[C
    //   148: dup_x1
    //   149: arraylength
    //   150: dup_x2
    //   151: pop
    //   152: iconst_0
    //   153: istore #6
    //   155: dup2_x1
    //   156: pop2
    //   157: dup_x2
    //   158: iconst_1
    //   159: if_icmpgt -> 260
    //   162: dup2
    //   163: swap
    //   164: iload #6
    //   166: dup2_x1
    //   167: caload
    //   168: swap
    //   169: iload #6
    //   171: bipush #7
    //   173: irem
    //   174: tableswitch default -> 242, 0 -> 212, 1 -> 217, 2 -> 222, 3 -> 227, 4 -> 232, 5 -> 237
    //   212: bipush #28
    //   214: goto -> 244
    //   217: bipush #110
    //   219: goto -> 244
    //   222: bipush #72
    //   224: goto -> 244
    //   227: bipush #7
    //   229: goto -> 244
    //   232: bipush #77
    //   234: goto -> 244
    //   237: bipush #86
    //   239: goto -> 244
    //   242: bipush #19
    //   244: ixor
    //   245: ixor
    //   246: i2c
    //   247: castore
    //   248: iinc #6, 1
    //   251: dup
    //   252: ifne -> 260
    //   255: dup2
    //   256: dup_x1
    //   257: goto -> 166
    //   260: dup2_x1
    //   261: pop2
    //   262: dup_x2
    //   263: iload #6
    //   265: if_icmpgt -> 162
    //   268: pop
    //   269: new java/lang/String
    //   272: dup_x1
    //   273: swap
    //   274: invokespecial <init> : ([C)V
    //   277: invokevirtual intern : ()Ljava/lang/String;
    //   280: swap
    //   281: pop
    //   282: swap
    //   283: tableswitch default -> 40, 0 -> 99
    //   300: sipush #-7404
    //   303: sipush #-11115
    //   306: invokestatic a : (II)Ljava/lang/String;
    //   309: putstatic burp/Zram.Ze : Ljava/lang/String;
    //   312: new java/math/BigInteger
    //   315: dup
    //   316: bipush #32
    //   318: newarray byte
    //   320: dup
    //   321: iconst_0
    //   322: bipush #93
    //   324: bastore
    //   325: dup
    //   326: iconst_1
    //   327: bipush #101
    //   329: bastore
    //   330: dup
    //   331: iconst_2
    //   332: bipush #-58
    //   334: bastore
    //   335: dup
    //   336: iconst_3
    //   337: bipush #12
    //   339: bastore
    //   340: dup
    //   341: iconst_4
    //   342: bipush #-72
    //   344: bastore
    //   345: dup
    //   346: iconst_5
    //   347: bipush #-77
    //   349: bastore
    //   350: dup
    //   351: bipush #6
    //   353: bipush #117
    //   355: bastore
    //   356: dup
    //   357: bipush #7
    //   359: bipush #-122
    //   361: bastore
    //   362: dup
    //   363: bipush #8
    //   365: bipush #-73
    //   367: bastore
    //   368: dup
    //   369: bipush #9
    //   371: bipush #106
    //   373: bastore
    //   374: dup
    //   375: bipush #10
    //   377: bipush #-25
    //   379: bastore
    //   380: dup
    //   381: bipush #11
    //   383: bipush #86
    //   385: bastore
    //   386: dup
    //   387: bipush #12
    //   389: bipush #35
    //   391: bastore
    //   392: dup
    //   393: bipush #13
    //   395: bipush #-104
    //   397: bastore
    //   398: dup
    //   399: bipush #14
    //   401: bipush #-22
    //   403: bastore
    //   404: dup
    //   405: bipush #15
    //   407: bipush #-127
    //   409: bastore
    //   410: dup
    //   411: bipush #16
    //   413: bipush #-25
    //   415: bastore
    //   416: dup
    //   417: bipush #17
    //   419: bipush #117
    //   421: bastore
    //   422: dup
    //   423: bipush #18
    //   425: bipush #-35
    //   427: bastore
    //   428: dup
    //   429: bipush #19
    //   431: bipush #-107
    //   433: bastore
    //   434: dup
    //   435: bipush #20
    //   437: bipush #22
    //   439: bastore
    //   440: dup
    //   441: bipush #21
    //   443: bipush #-128
    //   445: bastore
    //   446: dup
    //   447: bipush #22
    //   449: bipush #124
    //   451: bastore
    //   452: dup
    //   453: bipush #23
    //   455: iconst_2
    //   456: bastore
    //   457: dup
    //   458: bipush #24
    //   460: bipush #119
    //   462: bastore
    //   463: dup
    //   464: bipush #25
    //   466: bipush #-88
    //   468: bastore
    //   469: dup
    //   470: bipush #26
    //   472: bipush #-72
    //   474: bastore
    //   475: dup
    //   476: bipush #27
    //   478: bipush #72
    //   480: bastore
    //   481: dup
    //   482: bipush #28
    //   484: bipush #-46
    //   486: bastore
    //   487: dup
    //   488: bipush #29
    //   490: bipush #-12
    //   492: bastore
    //   493: dup
    //   494: bipush #30
    //   496: bipush #-96
    //   498: bastore
    //   499: dup
    //   500: bipush #31
    //   502: bipush #-71
    //   504: bastore
    //   505: invokespecial <init> : ([B)V
    //   508: putstatic burp/Zram.ZF : Ljava/lang/Object;
    //   511: return
  }
  
  private static Throwable a(Throwable paramThrowable) {
    return paramThrowable;
  }
  
  private static String a(int paramInt1, int paramInt2) {
    int i = (paramInt1 ^ 0xFFFFE317) & 0xFFFF;
    if (b[i] == null) {
      char[] arrayOfChar = a[i].toCharArray();
      switch (arrayOfChar[0] & 0xFF) {
        case 0:
        
        case 1:
        
        case 2:
        
        case 3:
        
        case 4:
        
        case 5:
        
        case 6:
        
        case 7:
        
        case 8:
        
        case 9:
        
        case 10:
        
        case 11:
        
        case 12:
        
        case 13:
        
        case 14:
        
        case 15:
        
        case 16:
        
        case 17:
        
        case 18:
        
        case 19:
        
        case 20:
        
        case 21:
        
        case 22:
        
        case 23:
        
        case 24:
        
        case 25:
        
        case 26:
        
        case 27:
        
        case 28:
        
        case 29:
        
        case 30:
        
        case 31:
        
        case 32:
        
        case 33:
        
        case 34:
        
        case 35:
        
        case 36:
        
        case 37:
        
        case 38:
        
        case 39:
        
        case 40:
        
        case 41:
        
        case 42:
        
        case 43:
        
        case 44:
        
        case 45:
        
        case 46:
        
        case 47:
        
        case 48:
        
        case 49:
        
        case 50:
        
        case 51:
        
        case 52:
        
        case 53:
        
        case 54:
        
        case 55:
        
        case 56:
        
        case 57:
        
        case 58:
        
        case 59:
        
        case 60:
        
        case 61:
        
        case 62:
        
        case 63:
        
        case 64:
        
        case 65:
        
        case 66:
        
        case 67:
        
        case 68:
        
        case 69:
        
        case 70:
        
        case 71:
        
        case 72:
        
        case 73:
        
        case 74:
        
        case 75:
        
        case 76:
        
        case 77:
        
        case 78:
        
        case 79:
        
        case 80:
        
        case 81:
        
        case 82:
        
        case 83:
        
        case 84:
        
        case 85:
        
        case 86:
        
        case 87:
        
        case 88:
        
        case 89:
        
        case 90:
        
        case 91:
        
        case 92:
        
        case 93:
        
        case 94:
        
        case 95:
        
        case 96:
        
        case 97:
        
        case 98:
        
        case 99:
        
        case 100:
        
        case 101:
        
        case 102:
        
        case 103:
        
        case 104:
        
        case 105:
        
        case 106:
        
        case 107:
        
        case 108:
        
        case 109:
        
        case 110:
        
        case 111:
        
        case 112:
        
        case 113:
        
        case 114:
        
        case 115:
        
        case 116:
        
        case 117:
        
        case 118:
        
        case 119:
        
        case 120:
        
        case 121:
        
        case 122:
        
        case 123:
        
        case 124:
        
        case 125:
        
        case 126:
        
        case 127:
        
        case 128:
        
        case 129:
        
        case 130:
        
        case 131:
        
        case 132:
        
        case 133:
        
        case 134:
        
        case 135:
        
        case 136:
        
        case 137:
        
        case 138:
        
        case 139:
        
        case 140:
        
        case 141:
        
        case 142:
        
        case 143:
        
        case 144:
        
        case 145:
        
        case 146:
        
        case 147:
        
        case 148:
        
        case 149:
        
        case 150:
        
        case 151:
        
        case 152:
        
        case 153:
        
        case 154:
        
        case 155:
        
        case 156:
        
        case 157:
        
        case 158:
        
        case 159:
        
        case 160:
        
        case 161:
        
        case 162:
        
        case 163:
        
        case 164:
        
        case 165:
        
        case 166:
        
        case 167:
        
        case 168:
        
        case 169:
        
        case 170:
        
        case 171:
        
        case 172:
        
        case 173:
        
        case 174:
        
        case 175:
        
        case 176:
        
        case 177:
        
        case 178:
        
        case 179:
        
        case 180:
        
        case 181:
        
        case 182:
        
        case 183:
        
        case 184:
        
        case 185:
        
        case 186:
        
        case 187:
        
        case 188:
        
        case 189:
        
        case 190:
        
        case 191:
        
        case 192:
        
        case 193:
        
        case 194:
        
        case 195:
        
        case 196:
        
        case 197:
        
        case 198:
        
        case 199:
        
        case 200:
        
        case 201:
        
        case 202:
        
        case 203:
        
        case 204:
        
        case 205:
        
        case 206:
        
        case 207:
        
        case 208:
        
        case 209:
        
        case 210:
        
        case 211:
        
        case 212:
        
        case 213:
        
        case 214:
        
        case 215:
        
        case 216:
        
        case 217:
        
        case 218:
        
        case 219:
        
        case 220:
        
        case 221:
        
        case 222:
        
        case 223:
        
        case 224:
        
        case 225:
        
        case 226:
        
        case 227:
        
        case 228:
        
        case 229:
        
        case 230:
        
        case 231:
        
        case 232:
        
        case 233:
        
        case 234:
        
        case 235:
        
        case 236:
        
        case 237:
        
        case 238:
        
        case 239:
        
        case 240:
        
        case 241:
        
        case 242:
        
        case 243:
        
        case 244:
        
        case 245:
        
        case 246:
        
        case 247:
        
        case 248:
        
        case 249:
        
        case 250:
        
        case 251:
        
        case 252:
        
        case 253:
        
        case 254:
        
        default:
          break;
      } 
      byte b1 = 92;
      int j = (paramInt2 & 0xFF) - b1;
      if (j < 0)
        j += 256; 
      int k = ((paramInt2 & 0xFFFF) >>> 8) - b1;
      if (k < 0)
        k += 256; 
      for (byte b2 = 0; b2 < arrayOfChar.length; b2++) {
        int m = b2 % 2;
        if (m == 0) {
          arrayOfChar[b2] = (char)(arrayOfChar[b2] ^ j);
          j = ((j >>> 3 | j << 5) ^ arrayOfChar[b2]) & 0xFF;
        } else {
          arrayOfChar[b2] = (char)(arrayOfChar[b2] ^ k);
          k = ((k >>> 3 | k << 5) ^ arrayOfChar[b2]) & 0xFF;
        } 
      } 
      b[i] = (new String(arrayOfChar)).intern();
    } 
    return b[i];
  }
}


/* Location:              C:\Program Files\BurpSuitePro\burpsuite_pro.jar!\burp\Zram.class
 * Java compiler version: 21 (65.0)
 * JD-Core Version:       1.1.3
 */