package burp;

import java.math.BigInteger;

class Zrbp extends ClassLoader {
  static String Ze;
  
  static Object Z_;
  
  private static final String[] a;
  
  private static final String[] b;
  
  static boolean Z_(Object[] paramArrayOfObject, Object paramObject) throws Throwable {
    // Byte code:
    //   0: invokestatic ZN : ()Z
    //   3: istore_2
    //   4: getstatic burp/Zkfz.Zr : Ljava/lang/Object;
    //   7: checkcast java/math/BigInteger
    //   10: invokevirtual toByteArray : ()[B
    //   13: astore_3
    //   14: aload_3
    //   15: arraylength
    //   16: iconst_2
    //   17: iadd
    //   18: newarray byte
    //   20: astore #5
    //   22: iconst_0
    //   23: istore #6
    //   25: iload #6
    //   27: aload_3
    //   28: arraylength
    //   29: if_icmpge -> 48
    //   32: aload #5
    //   34: iload #6
    //   36: aload_3
    //   37: iload #6
    //   39: baload
    //   40: bastore
    //   41: iinc #6, 1
    //   44: iload_2
    //   45: ifne -> 25
    //   48: aload #5
    //   50: arraylength
    //   51: iconst_3
    //   52: idiv
    //   53: iconst_4
    //   54: imul
    //   55: newarray byte
    //   57: astore #4
    //   59: iconst_0
    //   60: istore #6
    //   62: iconst_0
    //   63: istore #7
    //   65: iload #6
    //   67: aload_3
    //   68: arraylength
    //   69: if_icmpge -> 180
    //   72: aload #4
    //   74: iload #7
    //   76: aload #5
    //   78: iload #6
    //   80: baload
    //   81: iconst_2
    //   82: iushr
    //   83: bipush #63
    //   85: iand
    //   86: i2b
    //   87: bastore
    //   88: aload #4
    //   90: iload #7
    //   92: iconst_1
    //   93: iadd
    //   94: aload #5
    //   96: iload #6
    //   98: iconst_1
    //   99: iadd
    //   100: baload
    //   101: iconst_4
    //   102: iushr
    //   103: bipush #15
    //   105: iand
    //   106: aload #5
    //   108: iload #6
    //   110: baload
    //   111: iconst_4
    //   112: ishl
    //   113: bipush #63
    //   115: iand
    //   116: ior
    //   117: i2b
    //   118: bastore
    //   119: aload #4
    //   121: iload #7
    //   123: iconst_2
    //   124: iadd
    //   125: aload #5
    //   127: iload #6
    //   129: iconst_2
    //   130: iadd
    //   131: baload
    //   132: bipush #6
    //   134: iushr
    //   135: iconst_3
    //   136: iand
    //   137: aload #5
    //   139: iload #6
    //   141: iconst_1
    //   142: iadd
    //   143: baload
    //   144: iconst_2
    //   145: ishl
    //   146: bipush #63
    //   148: iand
    //   149: ior
    //   150: i2b
    //   151: bastore
    //   152: aload #4
    //   154: iload #7
    //   156: iconst_3
    //   157: iadd
    //   158: aload #5
    //   160: iload #6
    //   162: iconst_2
    //   163: iadd
    //   164: baload
    //   165: bipush #63
    //   167: iand
    //   168: i2b
    //   169: bastore
    //   170: iinc #6, 3
    //   173: iinc #7, 4
    //   176: iload_2
    //   177: ifne -> 65
    //   180: iconst_0
    //   181: istore #6
    //   183: iload #6
    //   185: aload #4
    //   187: arraylength
    //   188: if_icmpge -> 372
    //   191: aload #4
    //   193: iload #6
    //   195: baload
    //   196: bipush #26
    //   198: if_icmpge -> 226
    //   201: aload #4
    //   203: iload #6
    //   205: aload #4
    //   207: iload #6
    //   209: baload
    //   210: bipush #65
    //   212: iadd
    //   213: i2b
    //   214: bastore
    //   215: iload_2
    //   216: ifne -> 365
    //   219: goto -> 226
    //   222: invokestatic a : (Ljava/lang/Throwable;)Ljava/lang/Throwable;
    //   225: athrow
    //   226: aload #4
    //   228: iload #6
    //   230: baload
    //   231: bipush #52
    //   233: if_icmpge -> 271
    //   236: goto -> 243
    //   239: invokestatic a : (Ljava/lang/Throwable;)Ljava/lang/Throwable;
    //   242: athrow
    //   243: aload #4
    //   245: iload #6
    //   247: aload #4
    //   249: iload #6
    //   251: baload
    //   252: bipush #97
    //   254: iadd
    //   255: bipush #26
    //   257: isub
    //   258: i2b
    //   259: bastore
    //   260: iload_2
    //   261: ifne -> 365
    //   264: goto -> 271
    //   267: invokestatic a : (Ljava/lang/Throwable;)Ljava/lang/Throwable;
    //   270: athrow
    //   271: aload #4
    //   273: iload #6
    //   275: baload
    //   276: bipush #62
    //   278: if_icmpge -> 316
    //   281: goto -> 288
    //   284: invokestatic a : (Ljava/lang/Throwable;)Ljava/lang/Throwable;
    //   287: athrow
    //   288: aload #4
    //   290: iload #6
    //   292: aload #4
    //   294: iload #6
    //   296: baload
    //   297: bipush #48
    //   299: iadd
    //   300: bipush #52
    //   302: isub
    //   303: i2b
    //   304: bastore
    //   305: iload_2
    //   306: ifne -> 365
    //   309: goto -> 316
    //   312: invokestatic a : (Ljava/lang/Throwable;)Ljava/lang/Throwable;
    //   315: athrow
    //   316: aload #4
    //   318: iload #6
    //   320: baload
    //   321: bipush #63
    //   323: if_icmpge -> 351
    //   326: goto -> 333
    //   329: invokestatic a : (Ljava/lang/Throwable;)Ljava/lang/Throwable;
    //   332: athrow
    //   333: aload #4
    //   335: iload #6
    //   337: bipush #43
    //   339: bastore
    //   340: iload_2
    //   341: ifne -> 365
    //   344: goto -> 351
    //   347: invokestatic a : (Ljava/lang/Throwable;)Ljava/lang/Throwable;
    //   350: athrow
    //   351: aload #4
    //   353: iload #6
    //   355: bipush #47
    //   357: bastore
    //   358: goto -> 365
    //   361: invokestatic a : (Ljava/lang/Throwable;)Ljava/lang/Throwable;
    //   364: athrow
    //   365: iinc #6, 1
    //   368: iload_2
    //   369: ifne -> 183
    //   372: aload #4
    //   374: arraylength
    //   375: iconst_1
    //   376: isub
    //   377: istore #6
    //   379: iload #6
    //   381: aload_3
    //   382: arraylength
    //   383: iconst_4
    //   384: imul
    //   385: iconst_3
    //   386: idiv
    //   387: if_icmple -> 404
    //   390: aload #4
    //   392: iload #6
    //   394: bipush #61
    //   396: bastore
    //   397: iinc #6, -1
    //   400: iload_2
    //   401: ifne -> 379
    //   404: new java/math/BigInteger
    //   407: dup
    //   408: aload #4
    //   410: invokespecial <init> : ([B)V
    //   413: invokevirtual abs : ()Ljava/math/BigInteger;
    //   416: putstatic burp/Zsde.Zx : Ljava/lang/Object;
    //   419: getstatic burp/Zr0u.ZB : Ljava/lang/Object;
    //   422: checkcast java/math/BigInteger
    //   425: invokevirtual toByteArray : ()[B
    //   428: astore_3
    //   429: bipush #32
    //   431: newarray int
    //   433: dup
    //   434: iconst_0
    //   435: ldc 876216579
    //   437: iastore
    //   438: dup
    //   439: iconst_1
    //   440: ldc 455999525
    //   442: iastore
    //   443: dup
    //   444: iconst_2
    //   445: ldc 1043334948
    //   447: iastore
    //   448: dup
    //   449: iconst_3
    //   450: ldc 439222784
    //   452: iastore
    //   453: dup
    //   454: iconst_4
    //   455: ldc 372376604
    //   457: iastore
    //   458: dup
    //   459: iconst_5
    //   460: ldc 707731490
    //   462: iastore
    //   463: dup
    //   464: bipush #6
    //   466: ldc 389426184
    //   468: iastore
    //   469: dup
    //   470: bipush #7
    //   472: ldc 973875457
    //   474: iastore
    //   475: dup
    //   476: bipush #8
    //   478: ldc 389160971
    //   480: iastore
    //   481: dup
    //   482: bipush #9
    //   484: ldc 907870729
    //   486: iastore
    //   487: dup
    //   488: bipush #10
    //   490: ldc 121057538
    //   492: iastore
    //   493: dup
    //   494: bipush #11
    //   496: ldc 840500228
    //   498: iastore
    //   499: dup
    //   500: bipush #12
    //   502: ldc 254150144
    //   504: iastore
    //   505: dup
    //   506: bipush #13
    //   508: ldc 924386310
    //   510: iastore
    //   511: dup
    //   512: bipush #14
    //   514: ldc 187632156
    //   516: iastore
    //   517: dup
    //   518: bipush #15
    //   520: ldc 874189824
    //   522: iastore
    //   523: dup
    //   524: bipush #16
    //   526: ldc 655302664
    //   528: iastore
    //   529: dup
    //   530: bipush #17
    //   532: ldc 890966315
    //   534: iastore
    //   535: dup
    //   536: bipush #18
    //   538: ldc 722417666
    //   540: iastore
    //   541: dup
    //   542: bipush #19
    //   544: ldc 1026621720
    //   546: iastore
    //   547: dup
    //   548: bipush #20
    //   550: ldc 957157408
    //   552: iastore
    //   553: dup
    //   554: bipush #21
    //   556: ldc 892536332
    //   558: iastore
    //   559: dup
    //   560: bipush #22
    //   562: ldc 689771012
    //   564: iastore
    //   565: dup
    //   566: bipush #23
    //   568: ldc 221709344
    //   570: iastore
    //   571: dup
    //   572: bipush #24
    //   574: ldc 940377620
    //   576: iastore
    //   577: dup
    //   578: bipush #25
    //   580: ldc 255209728
    //   582: iastore
    //   583: dup
    //   584: bipush #26
    //   586: ldc 1010368540
    //   588: iastore
    //   589: dup
    //   590: bipush #27
    //   592: ldc 220604441
    //   594: iastore
    //   595: dup
    //   596: bipush #28
    //   598: ldc 1008414755
    //   600: iastore
    //   601: dup
    //   602: bipush #29
    //   604: ldc 187049985
    //   606: iastore
    //   607: dup
    //   608: bipush #30
    //   610: ldc 943331329
    //   612: iastore
    //   613: dup
    //   614: bipush #31
    //   616: ldc 170788368
    //   618: iastore
    //   619: astore #5
    //   621: bipush #64
    //   623: newarray int
    //   625: dup
    //   626: iconst_0
    //   627: ldc 16843776
    //   629: iastore
    //   630: dup
    //   631: iconst_1
    //   632: iconst_0
    //   633: iastore
    //   634: dup
    //   635: iconst_2
    //   636: ldc 65536
    //   638: iastore
    //   639: dup
    //   640: iconst_3
    //   641: ldc 16843780
    //   643: iastore
    //   644: dup
    //   645: iconst_4
    //   646: ldc 16842756
    //   648: iastore
    //   649: dup
    //   650: iconst_5
    //   651: ldc 66564
    //   653: iastore
    //   654: dup
    //   655: bipush #6
    //   657: iconst_4
    //   658: iastore
    //   659: dup
    //   660: bipush #7
    //   662: ldc 65536
    //   664: iastore
    //   665: dup
    //   666: bipush #8
    //   668: sipush #1024
    //   671: iastore
    //   672: dup
    //   673: bipush #9
    //   675: ldc 16843776
    //   677: iastore
    //   678: dup
    //   679: bipush #10
    //   681: ldc 16843780
    //   683: iastore
    //   684: dup
    //   685: bipush #11
    //   687: sipush #1024
    //   690: iastore
    //   691: dup
    //   692: bipush #12
    //   694: ldc 16778244
    //   696: iastore
    //   697: dup
    //   698: bipush #13
    //   700: ldc 16842756
    //   702: iastore
    //   703: dup
    //   704: bipush #14
    //   706: ldc 16777216
    //   708: iastore
    //   709: dup
    //   710: bipush #15
    //   712: iconst_4
    //   713: iastore
    //   714: dup
    //   715: bipush #16
    //   717: sipush #1028
    //   720: iastore
    //   721: dup
    //   722: bipush #17
    //   724: ldc 16778240
    //   726: iastore
    //   727: dup
    //   728: bipush #18
    //   730: ldc 16778240
    //   732: iastore
    //   733: dup
    //   734: bipush #19
    //   736: ldc 66560
    //   738: iastore
    //   739: dup
    //   740: bipush #20
    //   742: ldc 66560
    //   744: iastore
    //   745: dup
    //   746: bipush #21
    //   748: ldc 16842752
    //   750: iastore
    //   751: dup
    //   752: bipush #22
    //   754: ldc 16842752
    //   756: iastore
    //   757: dup
    //   758: bipush #23
    //   760: ldc 16778244
    //   762: iastore
    //   763: dup
    //   764: bipush #24
    //   766: ldc 65540
    //   768: iastore
    //   769: dup
    //   770: bipush #25
    //   772: ldc 16777220
    //   774: iastore
    //   775: dup
    //   776: bipush #26
    //   778: ldc 16777220
    //   780: iastore
    //   781: dup
    //   782: bipush #27
    //   784: ldc 65540
    //   786: iastore
    //   787: dup
    //   788: bipush #28
    //   790: iconst_0
    //   791: iastore
    //   792: dup
    //   793: bipush #29
    //   795: sipush #1028
    //   798: iastore
    //   799: dup
    //   800: bipush #30
    //   802: ldc 66564
    //   804: iastore
    //   805: dup
    //   806: bipush #31
    //   808: ldc 16777216
    //   810: iastore
    //   811: dup
    //   812: bipush #32
    //   814: ldc 65536
    //   816: iastore
    //   817: dup
    //   818: bipush #33
    //   820: ldc 16843780
    //   822: iastore
    //   823: dup
    //   824: bipush #34
    //   826: iconst_4
    //   827: iastore
    //   828: dup
    //   829: bipush #35
    //   831: ldc 16842752
    //   833: iastore
    //   834: dup
    //   835: bipush #36
    //   837: ldc 16843776
    //   839: iastore
    //   840: dup
    //   841: bipush #37
    //   843: ldc 16777216
    //   845: iastore
    //   846: dup
    //   847: bipush #38
    //   849: ldc 16777216
    //   851: iastore
    //   852: dup
    //   853: bipush #39
    //   855: sipush #1024
    //   858: iastore
    //   859: dup
    //   860: bipush #40
    //   862: ldc 16842756
    //   864: iastore
    //   865: dup
    //   866: bipush #41
    //   868: ldc 65536
    //   870: iastore
    //   871: dup
    //   872: bipush #42
    //   874: ldc 66560
    //   876: iastore
    //   877: dup
    //   878: bipush #43
    //   880: ldc 16777220
    //   882: iastore
    //   883: dup
    //   884: bipush #44
    //   886: sipush #1024
    //   889: iastore
    //   890: dup
    //   891: bipush #45
    //   893: iconst_4
    //   894: iastore
    //   895: dup
    //   896: bipush #46
    //   898: ldc 16778244
    //   900: iastore
    //   901: dup
    //   902: bipush #47
    //   904: ldc 66564
    //   906: iastore
    //   907: dup
    //   908: bipush #48
    //   910: ldc 16843780
    //   912: iastore
    //   913: dup
    //   914: bipush #49
    //   916: ldc 65540
    //   918: iastore
    //   919: dup
    //   920: bipush #50
    //   922: ldc 16842752
    //   924: iastore
    //   925: dup
    //   926: bipush #51
    //   928: ldc 16778244
    //   930: iastore
    //   931: dup
    //   932: bipush #52
    //   934: ldc 16777220
    //   936: iastore
    //   937: dup
    //   938: bipush #53
    //   940: sipush #1028
    //   943: iastore
    //   944: dup
    //   945: bipush #54
    //   947: ldc 66564
    //   949: iastore
    //   950: dup
    //   951: bipush #55
    //   953: ldc 16843776
    //   955: iastore
    //   956: dup
    //   957: bipush #56
    //   959: sipush #1028
    //   962: iastore
    //   963: dup
    //   964: bipush #57
    //   966: ldc 16778240
    //   968: iastore
    //   969: dup
    //   970: bipush #58
    //   972: ldc 16778240
    //   974: iastore
    //   975: dup
    //   976: bipush #59
    //   978: iconst_0
    //   979: iastore
    //   980: dup
    //   981: bipush #60
    //   983: ldc 65540
    //   985: iastore
    //   986: dup
    //   987: bipush #61
    //   989: ldc 66560
    //   991: iastore
    //   992: dup
    //   993: bipush #62
    //   995: iconst_0
    //   996: iastore
    //   997: dup
    //   998: bipush #63
    //   1000: ldc 16842756
    //   1002: iastore
    //   1003: astore #6
    //   1005: bipush #64
    //   1007: newarray int
    //   1009: dup
    //   1010: iconst_0
    //   1011: ldc -2146402272
    //   1013: iastore
    //   1014: dup
    //   1015: iconst_1
    //   1016: ldc -2147450880
    //   1018: iastore
    //   1019: dup
    //   1020: iconst_2
    //   1021: ldc 32768
    //   1023: iastore
    //   1024: dup
    //   1025: iconst_3
    //   1026: ldc 1081376
    //   1028: iastore
    //   1029: dup
    //   1030: iconst_4
    //   1031: ldc 1048576
    //   1033: iastore
    //   1034: dup
    //   1035: iconst_5
    //   1036: bipush #32
    //   1038: iastore
    //   1039: dup
    //   1040: bipush #6
    //   1042: ldc -2146435040
    //   1044: iastore
    //   1045: dup
    //   1046: bipush #7
    //   1048: ldc -2147450848
    //   1050: iastore
    //   1051: dup
    //   1052: bipush #8
    //   1054: ldc -2147483616
    //   1056: iastore
    //   1057: dup
    //   1058: bipush #9
    //   1060: ldc -2146402272
    //   1062: iastore
    //   1063: dup
    //   1064: bipush #10
    //   1066: ldc -2146402304
    //   1068: iastore
    //   1069: dup
    //   1070: bipush #11
    //   1072: ldc -2147483648
    //   1074: iastore
    //   1075: dup
    //   1076: bipush #12
    //   1078: ldc -2147450880
    //   1080: iastore
    //   1081: dup
    //   1082: bipush #13
    //   1084: ldc 1048576
    //   1086: iastore
    //   1087: dup
    //   1088: bipush #14
    //   1090: bipush #32
    //   1092: iastore
    //   1093: dup
    //   1094: bipush #15
    //   1096: ldc -2146435040
    //   1098: iastore
    //   1099: dup
    //   1100: bipush #16
    //   1102: ldc 1081344
    //   1104: iastore
    //   1105: dup
    //   1106: bipush #17
    //   1108: ldc 1048608
    //   1110: iastore
    //   1111: dup
    //   1112: bipush #18
    //   1114: ldc -2147450848
    //   1116: iastore
    //   1117: dup
    //   1118: bipush #19
    //   1120: iconst_0
    //   1121: iastore
    //   1122: dup
    //   1123: bipush #20
    //   1125: ldc -2147483648
    //   1127: iastore
    //   1128: dup
    //   1129: bipush #21
    //   1131: ldc 32768
    //   1133: iastore
    //   1134: dup
    //   1135: bipush #22
    //   1137: ldc 1081376
    //   1139: iastore
    //   1140: dup
    //   1141: bipush #23
    //   1143: ldc -2146435072
    //   1145: iastore
    //   1146: dup
    //   1147: bipush #24
    //   1149: ldc 1048608
    //   1151: iastore
    //   1152: dup
    //   1153: bipush #25
    //   1155: ldc -2147483616
    //   1157: iastore
    //   1158: dup
    //   1159: bipush #26
    //   1161: iconst_0
    //   1162: iastore
    //   1163: dup
    //   1164: bipush #27
    //   1166: ldc 1081344
    //   1168: iastore
    //   1169: dup
    //   1170: bipush #28
    //   1172: ldc 32800
    //   1174: iastore
    //   1175: dup
    //   1176: bipush #29
    //   1178: ldc -2146402304
    //   1180: iastore
    //   1181: dup
    //   1182: bipush #30
    //   1184: ldc -2146435072
    //   1186: iastore
    //   1187: dup
    //   1188: bipush #31
    //   1190: ldc 32800
    //   1192: iastore
    //   1193: dup
    //   1194: bipush #32
    //   1196: iconst_0
    //   1197: iastore
    //   1198: dup
    //   1199: bipush #33
    //   1201: ldc 1081376
    //   1203: iastore
    //   1204: dup
    //   1205: bipush #34
    //   1207: ldc -2146435040
    //   1209: iastore
    //   1210: dup
    //   1211: bipush #35
    //   1213: ldc 1048576
    //   1215: iastore
    //   1216: dup
    //   1217: bipush #36
    //   1219: ldc -2147450848
    //   1221: iastore
    //   1222: dup
    //   1223: bipush #37
    //   1225: ldc -2146435072
    //   1227: iastore
    //   1228: dup
    //   1229: bipush #38
    //   1231: ldc -2146402304
    //   1233: iastore
    //   1234: dup
    //   1235: bipush #39
    //   1237: ldc 32768
    //   1239: iastore
    //   1240: dup
    //   1241: bipush #40
    //   1243: ldc -2146435072
    //   1245: iastore
    //   1246: dup
    //   1247: bipush #41
    //   1249: ldc -2147450880
    //   1251: iastore
    //   1252: dup
    //   1253: bipush #42
    //   1255: bipush #32
    //   1257: iastore
    //   1258: dup
    //   1259: bipush #43
    //   1261: ldc -2146402272
    //   1263: iastore
    //   1264: dup
    //   1265: bipush #44
    //   1267: ldc 1081376
    //   1269: iastore
    //   1270: dup
    //   1271: bipush #45
    //   1273: bipush #32
    //   1275: iastore
    //   1276: dup
    //   1277: bipush #46
    //   1279: ldc 32768
    //   1281: iastore
    //   1282: dup
    //   1283: bipush #47
    //   1285: ldc -2147483648
    //   1287: iastore
    //   1288: dup
    //   1289: bipush #48
    //   1291: ldc 32800
    //   1293: iastore
    //   1294: dup
    //   1295: bipush #49
    //   1297: ldc -2146402304
    //   1299: iastore
    //   1300: dup
    //   1301: bipush #50
    //   1303: ldc 1048576
    //   1305: iastore
    //   1306: dup
    //   1307: bipush #51
    //   1309: ldc -2147483616
    //   1311: iastore
    //   1312: dup
    //   1313: bipush #52
    //   1315: ldc 1048608
    //   1317: iastore
    //   1318: dup
    //   1319: bipush #53
    //   1321: ldc -2147450848
    //   1323: iastore
    //   1324: dup
    //   1325: bipush #54
    //   1327: ldc -2147483616
    //   1329: iastore
    //   1330: dup
    //   1331: bipush #55
    //   1333: ldc 1048608
    //   1335: iastore
    //   1336: dup
    //   1337: bipush #56
    //   1339: ldc 1081344
    //   1341: iastore
    //   1342: dup
    //   1343: bipush #57
    //   1345: iconst_0
    //   1346: iastore
    //   1347: dup
    //   1348: bipush #58
    //   1350: ldc -2147450880
    //   1352: iastore
    //   1353: dup
    //   1354: bipush #59
    //   1356: ldc 32800
    //   1358: iastore
    //   1359: dup
    //   1360: bipush #60
    //   1362: ldc -2147483648
    //   1364: iastore
    //   1365: dup
    //   1366: bipush #61
    //   1368: ldc -2146435040
    //   1370: iastore
    //   1371: dup
    //   1372: bipush #62
    //   1374: ldc -2146402272
    //   1376: iastore
    //   1377: dup
    //   1378: bipush #63
    //   1380: ldc 1081344
    //   1382: iastore
    //   1383: astore #7
    //   1385: bipush #64
    //   1387: newarray int
    //   1389: dup
    //   1390: iconst_0
    //   1391: sipush #520
    //   1394: iastore
    //   1395: dup
    //   1396: iconst_1
    //   1397: ldc 134349312
    //   1399: iastore
    //   1400: dup
    //   1401: iconst_2
    //   1402: iconst_0
    //   1403: iastore
    //   1404: dup
    //   1405: iconst_3
    //   1406: ldc 134348808
    //   1408: iastore
    //   1409: dup
    //   1410: iconst_4
    //   1411: ldc 134218240
    //   1413: iastore
    //   1414: dup
    //   1415: iconst_5
    //   1416: iconst_0
    //   1417: iastore
    //   1418: dup
    //   1419: bipush #6
    //   1421: ldc 131592
    //   1423: iastore
    //   1424: dup
    //   1425: bipush #7
    //   1427: ldc 134218240
    //   1429: iastore
    //   1430: dup
    //   1431: bipush #8
    //   1433: ldc 131080
    //   1435: iastore
    //   1436: dup
    //   1437: bipush #9
    //   1439: ldc 134217736
    //   1441: iastore
    //   1442: dup
    //   1443: bipush #10
    //   1445: ldc 134217736
    //   1447: iastore
    //   1448: dup
    //   1449: bipush #11
    //   1451: ldc 131072
    //   1453: iastore
    //   1454: dup
    //   1455: bipush #12
    //   1457: ldc 134349320
    //   1459: iastore
    //   1460: dup
    //   1461: bipush #13
    //   1463: ldc 131080
    //   1465: iastore
    //   1466: dup
    //   1467: bipush #14
    //   1469: ldc 134348800
    //   1471: iastore
    //   1472: dup
    //   1473: bipush #15
    //   1475: sipush #520
    //   1478: iastore
    //   1479: dup
    //   1480: bipush #16
    //   1482: ldc 134217728
    //   1484: iastore
    //   1485: dup
    //   1486: bipush #17
    //   1488: bipush #8
    //   1490: iastore
    //   1491: dup
    //   1492: bipush #18
    //   1494: ldc 134349312
    //   1496: iastore
    //   1497: dup
    //   1498: bipush #19
    //   1500: sipush #512
    //   1503: iastore
    //   1504: dup
    //   1505: bipush #20
    //   1507: ldc 131584
    //   1509: iastore
    //   1510: dup
    //   1511: bipush #21
    //   1513: ldc 134348800
    //   1515: iastore
    //   1516: dup
    //   1517: bipush #22
    //   1519: ldc 134348808
    //   1521: iastore
    //   1522: dup
    //   1523: bipush #23
    //   1525: ldc 131592
    //   1527: iastore
    //   1528: dup
    //   1529: bipush #24
    //   1531: ldc 134218248
    //   1533: iastore
    //   1534: dup
    //   1535: bipush #25
    //   1537: ldc 131584
    //   1539: iastore
    //   1540: dup
    //   1541: bipush #26
    //   1543: ldc 131072
    //   1545: iastore
    //   1546: dup
    //   1547: bipush #27
    //   1549: ldc 134218248
    //   1551: iastore
    //   1552: dup
    //   1553: bipush #28
    //   1555: bipush #8
    //   1557: iastore
    //   1558: dup
    //   1559: bipush #29
    //   1561: ldc 134349320
    //   1563: iastore
    //   1564: dup
    //   1565: bipush #30
    //   1567: sipush #512
    //   1570: iastore
    //   1571: dup
    //   1572: bipush #31
    //   1574: ldc 134217728
    //   1576: iastore
    //   1577: dup
    //   1578: bipush #32
    //   1580: ldc 134349312
    //   1582: iastore
    //   1583: dup
    //   1584: bipush #33
    //   1586: ldc 134217728
    //   1588: iastore
    //   1589: dup
    //   1590: bipush #34
    //   1592: ldc 131080
    //   1594: iastore
    //   1595: dup
    //   1596: bipush #35
    //   1598: sipush #520
    //   1601: iastore
    //   1602: dup
    //   1603: bipush #36
    //   1605: ldc 131072
    //   1607: iastore
    //   1608: dup
    //   1609: bipush #37
    //   1611: ldc 134349312
    //   1613: iastore
    //   1614: dup
    //   1615: bipush #38
    //   1617: ldc 134218240
    //   1619: iastore
    //   1620: dup
    //   1621: bipush #39
    //   1623: iconst_0
    //   1624: iastore
    //   1625: dup
    //   1626: bipush #40
    //   1628: sipush #512
    //   1631: iastore
    //   1632: dup
    //   1633: bipush #41
    //   1635: ldc 131080
    //   1637: iastore
    //   1638: dup
    //   1639: bipush #42
    //   1641: ldc 134349320
    //   1643: iastore
    //   1644: dup
    //   1645: bipush #43
    //   1647: ldc 134218240
    //   1649: iastore
    //   1650: dup
    //   1651: bipush #44
    //   1653: ldc 134217736
    //   1655: iastore
    //   1656: dup
    //   1657: bipush #45
    //   1659: sipush #512
    //   1662: iastore
    //   1663: dup
    //   1664: bipush #46
    //   1666: iconst_0
    //   1667: iastore
    //   1668: dup
    //   1669: bipush #47
    //   1671: ldc 134348808
    //   1673: iastore
    //   1674: dup
    //   1675: bipush #48
    //   1677: ldc 134218248
    //   1679: iastore
    //   1680: dup
    //   1681: bipush #49
    //   1683: ldc 131072
    //   1685: iastore
    //   1686: dup
    //   1687: bipush #50
    //   1689: ldc 134217728
    //   1691: iastore
    //   1692: dup
    //   1693: bipush #51
    //   1695: ldc 134349320
    //   1697: iastore
    //   1698: dup
    //   1699: bipush #52
    //   1701: bipush #8
    //   1703: iastore
    //   1704: dup
    //   1705: bipush #53
    //   1707: ldc 131592
    //   1709: iastore
    //   1710: dup
    //   1711: bipush #54
    //   1713: ldc 131584
    //   1715: iastore
    //   1716: dup
    //   1717: bipush #55
    //   1719: ldc 134217736
    //   1721: iastore
    //   1722: dup
    //   1723: bipush #56
    //   1725: ldc 134348800
    //   1727: iastore
    //   1728: dup
    //   1729: bipush #57
    //   1731: ldc 134218248
    //   1733: iastore
    //   1734: dup
    //   1735: bipush #58
    //   1737: sipush #520
    //   1740: iastore
    //   1741: dup
    //   1742: bipush #59
    //   1744: ldc 134348800
    //   1746: iastore
    //   1747: dup
    //   1748: bipush #60
    //   1750: ldc 131592
    //   1752: iastore
    //   1753: dup
    //   1754: bipush #61
    //   1756: bipush #8
    //   1758: iastore
    //   1759: dup
    //   1760: bipush #62
    //   1762: ldc 134348808
    //   1764: iastore
    //   1765: dup
    //   1766: bipush #63
    //   1768: ldc 131584
    //   1770: iastore
    //   1771: astore #8
    //   1773: bipush #64
    //   1775: newarray int
    //   1777: dup
    //   1778: iconst_0
    //   1779: ldc 8396801
    //   1781: iastore
    //   1782: dup
    //   1783: iconst_1
    //   1784: sipush #8321
    //   1787: iastore
    //   1788: dup
    //   1789: iconst_2
    //   1790: sipush #8321
    //   1793: iastore
    //   1794: dup
    //   1795: iconst_3
    //   1796: sipush #128
    //   1799: iastore
    //   1800: dup
    //   1801: iconst_4
    //   1802: ldc 8396928
    //   1804: iastore
    //   1805: dup
    //   1806: iconst_5
    //   1807: ldc 8388737
    //   1809: iastore
    //   1810: dup
    //   1811: bipush #6
    //   1813: ldc 8388609
    //   1815: iastore
    //   1816: dup
    //   1817: bipush #7
    //   1819: sipush #8193
    //   1822: iastore
    //   1823: dup
    //   1824: bipush #8
    //   1826: iconst_0
    //   1827: iastore
    //   1828: dup
    //   1829: bipush #9
    //   1831: ldc 8396800
    //   1833: iastore
    //   1834: dup
    //   1835: bipush #10
    //   1837: ldc 8396800
    //   1839: iastore
    //   1840: dup
    //   1841: bipush #11
    //   1843: ldc 8396929
    //   1845: iastore
    //   1846: dup
    //   1847: bipush #12
    //   1849: sipush #129
    //   1852: iastore
    //   1853: dup
    //   1854: bipush #13
    //   1856: iconst_0
    //   1857: iastore
    //   1858: dup
    //   1859: bipush #14
    //   1861: ldc 8388736
    //   1863: iastore
    //   1864: dup
    //   1865: bipush #15
    //   1867: ldc 8388609
    //   1869: iastore
    //   1870: dup
    //   1871: bipush #16
    //   1873: iconst_1
    //   1874: iastore
    //   1875: dup
    //   1876: bipush #17
    //   1878: sipush #8192
    //   1881: iastore
    //   1882: dup
    //   1883: bipush #18
    //   1885: ldc 8388608
    //   1887: iastore
    //   1888: dup
    //   1889: bipush #19
    //   1891: ldc 8396801
    //   1893: iastore
    //   1894: dup
    //   1895: bipush #20
    //   1897: sipush #128
    //   1900: iastore
    //   1901: dup
    //   1902: bipush #21
    //   1904: ldc 8388608
    //   1906: iastore
    //   1907: dup
    //   1908: bipush #22
    //   1910: sipush #8193
    //   1913: iastore
    //   1914: dup
    //   1915: bipush #23
    //   1917: sipush #8320
    //   1920: iastore
    //   1921: dup
    //   1922: bipush #24
    //   1924: ldc 8388737
    //   1926: iastore
    //   1927: dup
    //   1928: bipush #25
    //   1930: iconst_1
    //   1931: iastore
    //   1932: dup
    //   1933: bipush #26
    //   1935: sipush #8320
    //   1938: iastore
    //   1939: dup
    //   1940: bipush #27
    //   1942: ldc 8388736
    //   1944: iastore
    //   1945: dup
    //   1946: bipush #28
    //   1948: sipush #8192
    //   1951: iastore
    //   1952: dup
    //   1953: bipush #29
    //   1955: ldc 8396928
    //   1957: iastore
    //   1958: dup
    //   1959: bipush #30
    //   1961: ldc 8396929
    //   1963: iastore
    //   1964: dup
    //   1965: bipush #31
    //   1967: sipush #129
    //   1970: iastore
    //   1971: dup
    //   1972: bipush #32
    //   1974: ldc 8388736
    //   1976: iastore
    //   1977: dup
    //   1978: bipush #33
    //   1980: ldc 8388609
    //   1982: iastore
    //   1983: dup
    //   1984: bipush #34
    //   1986: ldc 8396800
    //   1988: iastore
    //   1989: dup
    //   1990: bipush #35
    //   1992: ldc 8396929
    //   1994: iastore
    //   1995: dup
    //   1996: bipush #36
    //   1998: sipush #129
    //   2001: iastore
    //   2002: dup
    //   2003: bipush #37
    //   2005: iconst_0
    //   2006: iastore
    //   2007: dup
    //   2008: bipush #38
    //   2010: iconst_0
    //   2011: iastore
    //   2012: dup
    //   2013: bipush #39
    //   2015: ldc 8396800
    //   2017: iastore
    //   2018: dup
    //   2019: bipush #40
    //   2021: sipush #8320
    //   2024: iastore
    //   2025: dup
    //   2026: bipush #41
    //   2028: ldc 8388736
    //   2030: iastore
    //   2031: dup
    //   2032: bipush #42
    //   2034: ldc 8388737
    //   2036: iastore
    //   2037: dup
    //   2038: bipush #43
    //   2040: iconst_1
    //   2041: iastore
    //   2042: dup
    //   2043: bipush #44
    //   2045: ldc 8396801
    //   2047: iastore
    //   2048: dup
    //   2049: bipush #45
    //   2051: sipush #8321
    //   2054: iastore
    //   2055: dup
    //   2056: bipush #46
    //   2058: sipush #8321
    //   2061: iastore
    //   2062: dup
    //   2063: bipush #47
    //   2065: sipush #128
    //   2068: iastore
    //   2069: dup
    //   2070: bipush #48
    //   2072: ldc 8396929
    //   2074: iastore
    //   2075: dup
    //   2076: bipush #49
    //   2078: sipush #129
    //   2081: iastore
    //   2082: dup
    //   2083: bipush #50
    //   2085: iconst_1
    //   2086: iastore
    //   2087: dup
    //   2088: bipush #51
    //   2090: sipush #8192
    //   2093: iastore
    //   2094: dup
    //   2095: bipush #52
    //   2097: ldc 8388609
    //   2099: iastore
    //   2100: dup
    //   2101: bipush #53
    //   2103: sipush #8193
    //   2106: iastore
    //   2107: dup
    //   2108: bipush #54
    //   2110: ldc 8396928
    //   2112: iastore
    //   2113: dup
    //   2114: bipush #55
    //   2116: ldc 8388737
    //   2118: iastore
    //   2119: dup
    //   2120: bipush #56
    //   2122: sipush #8193
    //   2125: iastore
    //   2126: dup
    //   2127: bipush #57
    //   2129: sipush #8320
    //   2132: iastore
    //   2133: dup
    //   2134: bipush #58
    //   2136: ldc 8388608
    //   2138: iastore
    //   2139: dup
    //   2140: bipush #59
    //   2142: ldc 8396801
    //   2144: iastore
    //   2145: dup
    //   2146: bipush #60
    //   2148: sipush #128
    //   2151: iastore
    //   2152: dup
    //   2153: bipush #61
    //   2155: ldc 8388608
    //   2157: iastore
    //   2158: dup
    //   2159: bipush #62
    //   2161: sipush #8192
    //   2164: iastore
    //   2165: dup
    //   2166: bipush #63
    //   2168: ldc 8396928
    //   2170: iastore
    //   2171: astore #9
    //   2173: bipush #64
    //   2175: newarray int
    //   2177: dup
    //   2178: iconst_0
    //   2179: sipush #256
    //   2182: iastore
    //   2183: dup
    //   2184: iconst_1
    //   2185: ldc 34078976
    //   2187: iastore
    //   2188: dup
    //   2189: iconst_2
    //   2190: ldc 34078720
    //   2192: iastore
    //   2193: dup
    //   2194: iconst_3
    //   2195: ldc 1107296512
    //   2197: iastore
    //   2198: dup
    //   2199: iconst_4
    //   2200: ldc 524288
    //   2202: iastore
    //   2203: dup
    //   2204: iconst_5
    //   2205: sipush #256
    //   2208: iastore
    //   2209: dup
    //   2210: bipush #6
    //   2212: ldc 1073741824
    //   2214: iastore
    //   2215: dup
    //   2216: bipush #7
    //   2218: ldc 34078720
    //   2220: iastore
    //   2221: dup
    //   2222: bipush #8
    //   2224: ldc 1074266368
    //   2226: iastore
    //   2227: dup
    //   2228: bipush #9
    //   2230: ldc 524288
    //   2232: iastore
    //   2233: dup
    //   2234: bipush #10
    //   2236: ldc 33554688
    //   2238: iastore
    //   2239: dup
    //   2240: bipush #11
    //   2242: ldc 1074266368
    //   2244: iastore
    //   2245: dup
    //   2246: bipush #12
    //   2248: ldc 1107296512
    //   2250: iastore
    //   2251: dup
    //   2252: bipush #13
    //   2254: ldc 1107820544
    //   2256: iastore
    //   2257: dup
    //   2258: bipush #14
    //   2260: ldc 524544
    //   2262: iastore
    //   2263: dup
    //   2264: bipush #15
    //   2266: ldc 1073741824
    //   2268: iastore
    //   2269: dup
    //   2270: bipush #16
    //   2272: ldc 33554432
    //   2274: iastore
    //   2275: dup
    //   2276: bipush #17
    //   2278: ldc 1074266112
    //   2280: iastore
    //   2281: dup
    //   2282: bipush #18
    //   2284: ldc 1074266112
    //   2286: iastore
    //   2287: dup
    //   2288: bipush #19
    //   2290: iconst_0
    //   2291: iastore
    //   2292: dup
    //   2293: bipush #20
    //   2295: ldc 1073742080
    //   2297: iastore
    //   2298: dup
    //   2299: bipush #21
    //   2301: ldc 1107820800
    //   2303: iastore
    //   2304: dup
    //   2305: bipush #22
    //   2307: ldc 1107820800
    //   2309: iastore
    //   2310: dup
    //   2311: bipush #23
    //   2313: ldc 33554688
    //   2315: iastore
    //   2316: dup
    //   2317: bipush #24
    //   2319: ldc 1107820544
    //   2321: iastore
    //   2322: dup
    //   2323: bipush #25
    //   2325: ldc 1073742080
    //   2327: iastore
    //   2328: dup
    //   2329: bipush #26
    //   2331: iconst_0
    //   2332: iastore
    //   2333: dup
    //   2334: bipush #27
    //   2336: ldc 1107296256
    //   2338: iastore
    //   2339: dup
    //   2340: bipush #28
    //   2342: ldc 34078976
    //   2344: iastore
    //   2345: dup
    //   2346: bipush #29
    //   2348: ldc 33554432
    //   2350: iastore
    //   2351: dup
    //   2352: bipush #30
    //   2354: ldc 1107296256
    //   2356: iastore
    //   2357: dup
    //   2358: bipush #31
    //   2360: ldc 524544
    //   2362: iastore
    //   2363: dup
    //   2364: bipush #32
    //   2366: ldc 524288
    //   2368: iastore
    //   2369: dup
    //   2370: bipush #33
    //   2372: ldc 1107296512
    //   2374: iastore
    //   2375: dup
    //   2376: bipush #34
    //   2378: sipush #256
    //   2381: iastore
    //   2382: dup
    //   2383: bipush #35
    //   2385: ldc 33554432
    //   2387: iastore
    //   2388: dup
    //   2389: bipush #36
    //   2391: ldc 1073741824
    //   2393: iastore
    //   2394: dup
    //   2395: bipush #37
    //   2397: ldc 34078720
    //   2399: iastore
    //   2400: dup
    //   2401: bipush #38
    //   2403: ldc 1107296512
    //   2405: iastore
    //   2406: dup
    //   2407: bipush #39
    //   2409: ldc 1074266368
    //   2411: iastore
    //   2412: dup
    //   2413: bipush #40
    //   2415: ldc 33554688
    //   2417: iastore
    //   2418: dup
    //   2419: bipush #41
    //   2421: ldc 1073741824
    //   2423: iastore
    //   2424: dup
    //   2425: bipush #42
    //   2427: ldc 1107820544
    //   2429: iastore
    //   2430: dup
    //   2431: bipush #43
    //   2433: ldc 34078976
    //   2435: iastore
    //   2436: dup
    //   2437: bipush #44
    //   2439: ldc 1074266368
    //   2441: iastore
    //   2442: dup
    //   2443: bipush #45
    //   2445: sipush #256
    //   2448: iastore
    //   2449: dup
    //   2450: bipush #46
    //   2452: ldc 33554432
    //   2454: iastore
    //   2455: dup
    //   2456: bipush #47
    //   2458: ldc 1107820544
    //   2460: iastore
    //   2461: dup
    //   2462: bipush #48
    //   2464: ldc 1107820800
    //   2466: iastore
    //   2467: dup
    //   2468: bipush #49
    //   2470: ldc 524544
    //   2472: iastore
    //   2473: dup
    //   2474: bipush #50
    //   2476: ldc 1107296256
    //   2478: iastore
    //   2479: dup
    //   2480: bipush #51
    //   2482: ldc 1107820800
    //   2484: iastore
    //   2485: dup
    //   2486: bipush #52
    //   2488: ldc 34078720
    //   2490: iastore
    //   2491: dup
    //   2492: bipush #53
    //   2494: iconst_0
    //   2495: iastore
    //   2496: dup
    //   2497: bipush #54
    //   2499: ldc 1074266112
    //   2501: iastore
    //   2502: dup
    //   2503: bipush #55
    //   2505: ldc 1107296256
    //   2507: iastore
    //   2508: dup
    //   2509: bipush #56
    //   2511: ldc 524544
    //   2513: iastore
    //   2514: dup
    //   2515: bipush #57
    //   2517: ldc 33554688
    //   2519: iastore
    //   2520: dup
    //   2521: bipush #58
    //   2523: ldc 1073742080
    //   2525: iastore
    //   2526: dup
    //   2527: bipush #59
    //   2529: ldc 524288
    //   2531: iastore
    //   2532: dup
    //   2533: bipush #60
    //   2535: iconst_0
    //   2536: iastore
    //   2537: dup
    //   2538: bipush #61
    //   2540: ldc 1074266112
    //   2542: iastore
    //   2543: dup
    //   2544: bipush #62
    //   2546: ldc 34078976
    //   2548: iastore
    //   2549: dup
    //   2550: bipush #63
    //   2552: ldc 1073742080
    //   2554: iastore
    //   2555: astore #10
    //   2557: bipush #64
    //   2559: newarray int
    //   2561: dup
    //   2562: iconst_0
    //   2563: ldc 536870928
    //   2565: iastore
    //   2566: dup
    //   2567: iconst_1
    //   2568: ldc 541065216
    //   2570: iastore
    //   2571: dup
    //   2572: iconst_2
    //   2573: sipush #16384
    //   2576: iastore
    //   2577: dup
    //   2578: iconst_3
    //   2579: ldc 541081616
    //   2581: iastore
    //   2582: dup
    //   2583: iconst_4
    //   2584: ldc 541065216
    //   2586: iastore
    //   2587: dup
    //   2588: iconst_5
    //   2589: bipush #16
    //   2591: iastore
    //   2592: dup
    //   2593: bipush #6
    //   2595: ldc 541081616
    //   2597: iastore
    //   2598: dup
    //   2599: bipush #7
    //   2601: ldc 4194304
    //   2603: iastore
    //   2604: dup
    //   2605: bipush #8
    //   2607: ldc 536887296
    //   2609: iastore
    //   2610: dup
    //   2611: bipush #9
    //   2613: ldc 4210704
    //   2615: iastore
    //   2616: dup
    //   2617: bipush #10
    //   2619: ldc 4194304
    //   2621: iastore
    //   2622: dup
    //   2623: bipush #11
    //   2625: ldc 536870928
    //   2627: iastore
    //   2628: dup
    //   2629: bipush #12
    //   2631: ldc 4194320
    //   2633: iastore
    //   2634: dup
    //   2635: bipush #13
    //   2637: ldc 536887296
    //   2639: iastore
    //   2640: dup
    //   2641: bipush #14
    //   2643: ldc 536870912
    //   2645: iastore
    //   2646: dup
    //   2647: bipush #15
    //   2649: sipush #16400
    //   2652: iastore
    //   2653: dup
    //   2654: bipush #16
    //   2656: iconst_0
    //   2657: iastore
    //   2658: dup
    //   2659: bipush #17
    //   2661: ldc 4194320
    //   2663: iastore
    //   2664: dup
    //   2665: bipush #18
    //   2667: ldc 536887312
    //   2669: iastore
    //   2670: dup
    //   2671: bipush #19
    //   2673: sipush #16384
    //   2676: iastore
    //   2677: dup
    //   2678: bipush #20
    //   2680: ldc 4210688
    //   2682: iastore
    //   2683: dup
    //   2684: bipush #21
    //   2686: ldc 536887312
    //   2688: iastore
    //   2689: dup
    //   2690: bipush #22
    //   2692: bipush #16
    //   2694: iastore
    //   2695: dup
    //   2696: bipush #23
    //   2698: ldc 541065232
    //   2700: iastore
    //   2701: dup
    //   2702: bipush #24
    //   2704: ldc 541065232
    //   2706: iastore
    //   2707: dup
    //   2708: bipush #25
    //   2710: iconst_0
    //   2711: iastore
    //   2712: dup
    //   2713: bipush #26
    //   2715: ldc 4210704
    //   2717: iastore
    //   2718: dup
    //   2719: bipush #27
    //   2721: ldc 541081600
    //   2723: iastore
    //   2724: dup
    //   2725: bipush #28
    //   2727: sipush #16400
    //   2730: iastore
    //   2731: dup
    //   2732: bipush #29
    //   2734: ldc 4210688
    //   2736: iastore
    //   2737: dup
    //   2738: bipush #30
    //   2740: ldc 541081600
    //   2742: iastore
    //   2743: dup
    //   2744: bipush #31
    //   2746: ldc 536870912
    //   2748: iastore
    //   2749: dup
    //   2750: bipush #32
    //   2752: ldc 536887296
    //   2754: iastore
    //   2755: dup
    //   2756: bipush #33
    //   2758: bipush #16
    //   2760: iastore
    //   2761: dup
    //   2762: bipush #34
    //   2764: ldc 541065232
    //   2766: iastore
    //   2767: dup
    //   2768: bipush #35
    //   2770: ldc 4210688
    //   2772: iastore
    //   2773: dup
    //   2774: bipush #36
    //   2776: ldc 541081616
    //   2778: iastore
    //   2779: dup
    //   2780: bipush #37
    //   2782: ldc 4194304
    //   2784: iastore
    //   2785: dup
    //   2786: bipush #38
    //   2788: sipush #16400
    //   2791: iastore
    //   2792: dup
    //   2793: bipush #39
    //   2795: ldc 536870928
    //   2797: iastore
    //   2798: dup
    //   2799: bipush #40
    //   2801: ldc 4194304
    //   2803: iastore
    //   2804: dup
    //   2805: bipush #41
    //   2807: ldc 536887296
    //   2809: iastore
    //   2810: dup
    //   2811: bipush #42
    //   2813: ldc 536870912
    //   2815: iastore
    //   2816: dup
    //   2817: bipush #43
    //   2819: sipush #16400
    //   2822: iastore
    //   2823: dup
    //   2824: bipush #44
    //   2826: ldc 536870928
    //   2828: iastore
    //   2829: dup
    //   2830: bipush #45
    //   2832: ldc 541081616
    //   2834: iastore
    //   2835: dup
    //   2836: bipush #46
    //   2838: ldc 4210688
    //   2840: iastore
    //   2841: dup
    //   2842: bipush #47
    //   2844: ldc 541065216
    //   2846: iastore
    //   2847: dup
    //   2848: bipush #48
    //   2850: ldc 4210704
    //   2852: iastore
    //   2853: dup
    //   2854: bipush #49
    //   2856: ldc 541081600
    //   2858: iastore
    //   2859: dup
    //   2860: bipush #50
    //   2862: iconst_0
    //   2863: iastore
    //   2864: dup
    //   2865: bipush #51
    //   2867: ldc 541065232
    //   2869: iastore
    //   2870: dup
    //   2871: bipush #52
    //   2873: bipush #16
    //   2875: iastore
    //   2876: dup
    //   2877: bipush #53
    //   2879: sipush #16384
    //   2882: iastore
    //   2883: dup
    //   2884: bipush #54
    //   2886: ldc 541065216
    //   2888: iastore
    //   2889: dup
    //   2890: bipush #55
    //   2892: ldc 4210704
    //   2894: iastore
    //   2895: dup
    //   2896: bipush #56
    //   2898: sipush #16384
    //   2901: iastore
    //   2902: dup
    //   2903: bipush #57
    //   2905: ldc 4194320
    //   2907: iastore
    //   2908: dup
    //   2909: bipush #58
    //   2911: ldc 536887312
    //   2913: iastore
    //   2914: dup
    //   2915: bipush #59
    //   2917: iconst_0
    //   2918: iastore
    //   2919: dup
    //   2920: bipush #60
    //   2922: ldc 541081600
    //   2924: iastore
    //   2925: dup
    //   2926: bipush #61
    //   2928: ldc 536870912
    //   2930: iastore
    //   2931: dup
    //   2932: bipush #62
    //   2934: ldc 4194320
    //   2936: iastore
    //   2937: dup
    //   2938: bipush #63
    //   2940: ldc 536887312
    //   2942: iastore
    //   2943: astore #11
    //   2945: bipush #64
    //   2947: newarray int
    //   2949: dup
    //   2950: iconst_0
    //   2951: ldc 2097152
    //   2953: iastore
    //   2954: dup
    //   2955: iconst_1
    //   2956: ldc 69206018
    //   2958: iastore
    //   2959: dup
    //   2960: iconst_2
    //   2961: ldc 67110914
    //   2963: iastore
    //   2964: dup
    //   2965: iconst_3
    //   2966: iconst_0
    //   2967: iastore
    //   2968: dup
    //   2969: iconst_4
    //   2970: sipush #2048
    //   2973: iastore
    //   2974: dup
    //   2975: iconst_5
    //   2976: ldc 67110914
    //   2978: iastore
    //   2979: dup
    //   2980: bipush #6
    //   2982: ldc 2099202
    //   2984: iastore
    //   2985: dup
    //   2986: bipush #7
    //   2988: ldc 69208064
    //   2990: iastore
    //   2991: dup
    //   2992: bipush #8
    //   2994: ldc 69208066
    //   2996: iastore
    //   2997: dup
    //   2998: bipush #9
    //   3000: ldc 2097152
    //   3002: iastore
    //   3003: dup
    //   3004: bipush #10
    //   3006: iconst_0
    //   3007: iastore
    //   3008: dup
    //   3009: bipush #11
    //   3011: ldc 67108866
    //   3013: iastore
    //   3014: dup
    //   3015: bipush #12
    //   3017: iconst_2
    //   3018: iastore
    //   3019: dup
    //   3020: bipush #13
    //   3022: ldc 67108864
    //   3024: iastore
    //   3025: dup
    //   3026: bipush #14
    //   3028: ldc 69206018
    //   3030: iastore
    //   3031: dup
    //   3032: bipush #15
    //   3034: sipush #2050
    //   3037: iastore
    //   3038: dup
    //   3039: bipush #16
    //   3041: ldc 67110912
    //   3043: iastore
    //   3044: dup
    //   3045: bipush #17
    //   3047: ldc 2099202
    //   3049: iastore
    //   3050: dup
    //   3051: bipush #18
    //   3053: ldc 2097154
    //   3055: iastore
    //   3056: dup
    //   3057: bipush #19
    //   3059: ldc 67110912
    //   3061: iastore
    //   3062: dup
    //   3063: bipush #20
    //   3065: ldc 67108866
    //   3067: iastore
    //   3068: dup
    //   3069: bipush #21
    //   3071: ldc 69206016
    //   3073: iastore
    //   3074: dup
    //   3075: bipush #22
    //   3077: ldc 69208064
    //   3079: iastore
    //   3080: dup
    //   3081: bipush #23
    //   3083: ldc 2097154
    //   3085: iastore
    //   3086: dup
    //   3087: bipush #24
    //   3089: ldc 69206016
    //   3091: iastore
    //   3092: dup
    //   3093: bipush #25
    //   3095: sipush #2048
    //   3098: iastore
    //   3099: dup
    //   3100: bipush #26
    //   3102: sipush #2050
    //   3105: iastore
    //   3106: dup
    //   3107: bipush #27
    //   3109: ldc 69208066
    //   3111: iastore
    //   3112: dup
    //   3113: bipush #28
    //   3115: ldc 2099200
    //   3117: iastore
    //   3118: dup
    //   3119: bipush #29
    //   3121: iconst_2
    //   3122: iastore
    //   3123: dup
    //   3124: bipush #30
    //   3126: ldc 67108864
    //   3128: iastore
    //   3129: dup
    //   3130: bipush #31
    //   3132: ldc 2099200
    //   3134: iastore
    //   3135: dup
    //   3136: bipush #32
    //   3138: ldc 67108864
    //   3140: iastore
    //   3141: dup
    //   3142: bipush #33
    //   3144: ldc 2099200
    //   3146: iastore
    //   3147: dup
    //   3148: bipush #34
    //   3150: ldc 2097152
    //   3152: iastore
    //   3153: dup
    //   3154: bipush #35
    //   3156: ldc 67110914
    //   3158: iastore
    //   3159: dup
    //   3160: bipush #36
    //   3162: ldc 67110914
    //   3164: iastore
    //   3165: dup
    //   3166: bipush #37
    //   3168: ldc 69206018
    //   3170: iastore
    //   3171: dup
    //   3172: bipush #38
    //   3174: ldc 69206018
    //   3176: iastore
    //   3177: dup
    //   3178: bipush #39
    //   3180: iconst_2
    //   3181: iastore
    //   3182: dup
    //   3183: bipush #40
    //   3185: ldc 2097154
    //   3187: iastore
    //   3188: dup
    //   3189: bipush #41
    //   3191: ldc 67108864
    //   3193: iastore
    //   3194: dup
    //   3195: bipush #42
    //   3197: ldc 67110912
    //   3199: iastore
    //   3200: dup
    //   3201: bipush #43
    //   3203: ldc 2097152
    //   3205: iastore
    //   3206: dup
    //   3207: bipush #44
    //   3209: ldc 69208064
    //   3211: iastore
    //   3212: dup
    //   3213: bipush #45
    //   3215: sipush #2050
    //   3218: iastore
    //   3219: dup
    //   3220: bipush #46
    //   3222: ldc 2099202
    //   3224: iastore
    //   3225: dup
    //   3226: bipush #47
    //   3228: ldc 69208064
    //   3230: iastore
    //   3231: dup
    //   3232: bipush #48
    //   3234: sipush #2050
    //   3237: iastore
    //   3238: dup
    //   3239: bipush #49
    //   3241: ldc 67108866
    //   3243: iastore
    //   3244: dup
    //   3245: bipush #50
    //   3247: ldc 69208066
    //   3249: iastore
    //   3250: dup
    //   3251: bipush #51
    //   3253: ldc 69206016
    //   3255: iastore
    //   3256: dup
    //   3257: bipush #52
    //   3259: ldc 2099200
    //   3261: iastore
    //   3262: dup
    //   3263: bipush #53
    //   3265: iconst_0
    //   3266: iastore
    //   3267: dup
    //   3268: bipush #54
    //   3270: iconst_2
    //   3271: iastore
    //   3272: dup
    //   3273: bipush #55
    //   3275: ldc 69208066
    //   3277: iastore
    //   3278: dup
    //   3279: bipush #56
    //   3281: iconst_0
    //   3282: iastore
    //   3283: dup
    //   3284: bipush #57
    //   3286: ldc 2099202
    //   3288: iastore
    //   3289: dup
    //   3290: bipush #58
    //   3292: ldc 69206016
    //   3294: iastore
    //   3295: dup
    //   3296: bipush #59
    //   3298: sipush #2048
    //   3301: iastore
    //   3302: dup
    //   3303: bipush #60
    //   3305: ldc 67108866
    //   3307: iastore
    //   3308: dup
    //   3309: bipush #61
    //   3311: ldc 67110912
    //   3313: iastore
    //   3314: dup
    //   3315: bipush #62
    //   3317: sipush #2048
    //   3320: iastore
    //   3321: dup
    //   3322: bipush #63
    //   3324: ldc 2097154
    //   3326: iastore
    //   3327: astore #12
    //   3329: bipush #64
    //   3331: newarray int
    //   3333: dup
    //   3334: iconst_0
    //   3335: ldc 268439616
    //   3337: iastore
    //   3338: dup
    //   3339: iconst_1
    //   3340: sipush #4096
    //   3343: iastore
    //   3344: dup
    //   3345: iconst_2
    //   3346: ldc 262144
    //   3348: iastore
    //   3349: dup
    //   3350: iconst_3
    //   3351: ldc 268701760
    //   3353: iastore
    //   3354: dup
    //   3355: iconst_4
    //   3356: ldc 268435456
    //   3358: iastore
    //   3359: dup
    //   3360: iconst_5
    //   3361: ldc 268439616
    //   3363: iastore
    //   3364: dup
    //   3365: bipush #6
    //   3367: bipush #64
    //   3369: iastore
    //   3370: dup
    //   3371: bipush #7
    //   3373: ldc 268435456
    //   3375: iastore
    //   3376: dup
    //   3377: bipush #8
    //   3379: ldc 262208
    //   3381: iastore
    //   3382: dup
    //   3383: bipush #9
    //   3385: ldc 268697600
    //   3387: iastore
    //   3388: dup
    //   3389: bipush #10
    //   3391: ldc 268701760
    //   3393: iastore
    //   3394: dup
    //   3395: bipush #11
    //   3397: ldc 266240
    //   3399: iastore
    //   3400: dup
    //   3401: bipush #12
    //   3403: ldc 268701696
    //   3405: iastore
    //   3406: dup
    //   3407: bipush #13
    //   3409: ldc 266304
    //   3411: iastore
    //   3412: dup
    //   3413: bipush #14
    //   3415: sipush #4096
    //   3418: iastore
    //   3419: dup
    //   3420: bipush #15
    //   3422: bipush #64
    //   3424: iastore
    //   3425: dup
    //   3426: bipush #16
    //   3428: ldc 268697600
    //   3430: iastore
    //   3431: dup
    //   3432: bipush #17
    //   3434: ldc 268435520
    //   3436: iastore
    //   3437: dup
    //   3438: bipush #18
    //   3440: ldc 268439552
    //   3442: iastore
    //   3443: dup
    //   3444: bipush #19
    //   3446: sipush #4160
    //   3449: iastore
    //   3450: dup
    //   3451: bipush #20
    //   3453: ldc 266240
    //   3455: iastore
    //   3456: dup
    //   3457: bipush #21
    //   3459: ldc 262208
    //   3461: iastore
    //   3462: dup
    //   3463: bipush #22
    //   3465: ldc 268697664
    //   3467: iastore
    //   3468: dup
    //   3469: bipush #23
    //   3471: ldc 268701696
    //   3473: iastore
    //   3474: dup
    //   3475: bipush #24
    //   3477: sipush #4160
    //   3480: iastore
    //   3481: dup
    //   3482: bipush #25
    //   3484: iconst_0
    //   3485: iastore
    //   3486: dup
    //   3487: bipush #26
    //   3489: iconst_0
    //   3490: iastore
    //   3491: dup
    //   3492: bipush #27
    //   3494: ldc 268697664
    //   3496: iastore
    //   3497: dup
    //   3498: bipush #28
    //   3500: ldc 268435520
    //   3502: iastore
    //   3503: dup
    //   3504: bipush #29
    //   3506: ldc 268439552
    //   3508: iastore
    //   3509: dup
    //   3510: bipush #30
    //   3512: ldc 266304
    //   3514: iastore
    //   3515: dup
    //   3516: bipush #31
    //   3518: ldc 262144
    //   3520: iastore
    //   3521: dup
    //   3522: bipush #32
    //   3524: ldc 266304
    //   3526: iastore
    //   3527: dup
    //   3528: bipush #33
    //   3530: ldc 262144
    //   3532: iastore
    //   3533: dup
    //   3534: bipush #34
    //   3536: ldc 268701696
    //   3538: iastore
    //   3539: dup
    //   3540: bipush #35
    //   3542: sipush #4096
    //   3545: iastore
    //   3546: dup
    //   3547: bipush #36
    //   3549: bipush #64
    //   3551: iastore
    //   3552: dup
    //   3553: bipush #37
    //   3555: ldc 268697664
    //   3557: iastore
    //   3558: dup
    //   3559: bipush #38
    //   3561: sipush #4096
    //   3564: iastore
    //   3565: dup
    //   3566: bipush #39
    //   3568: ldc 266304
    //   3570: iastore
    //   3571: dup
    //   3572: bipush #40
    //   3574: ldc 268439552
    //   3576: iastore
    //   3577: dup
    //   3578: bipush #41
    //   3580: bipush #64
    //   3582: iastore
    //   3583: dup
    //   3584: bipush #42
    //   3586: ldc 268435520
    //   3588: iastore
    //   3589: dup
    //   3590: bipush #43
    //   3592: ldc 268697600
    //   3594: iastore
    //   3595: dup
    //   3596: bipush #44
    //   3598: ldc 268697664
    //   3600: iastore
    //   3601: dup
    //   3602: bipush #45
    //   3604: ldc 268435456
    //   3606: iastore
    //   3607: dup
    //   3608: bipush #46
    //   3610: ldc 262144
    //   3612: iastore
    //   3613: dup
    //   3614: bipush #47
    //   3616: ldc 268439616
    //   3618: iastore
    //   3619: dup
    //   3620: bipush #48
    //   3622: iconst_0
    //   3623: iastore
    //   3624: dup
    //   3625: bipush #49
    //   3627: ldc 268701760
    //   3629: iastore
    //   3630: dup
    //   3631: bipush #50
    //   3633: ldc 262208
    //   3635: iastore
    //   3636: dup
    //   3637: bipush #51
    //   3639: ldc 268435520
    //   3641: iastore
    //   3642: dup
    //   3643: bipush #52
    //   3645: ldc 268697600
    //   3647: iastore
    //   3648: dup
    //   3649: bipush #53
    //   3651: ldc 268439552
    //   3653: iastore
    //   3654: dup
    //   3655: bipush #54
    //   3657: ldc 268439616
    //   3659: iastore
    //   3660: dup
    //   3661: bipush #55
    //   3663: iconst_0
    //   3664: iastore
    //   3665: dup
    //   3666: bipush #56
    //   3668: ldc 268701760
    //   3670: iastore
    //   3671: dup
    //   3672: bipush #57
    //   3674: ldc 266240
    //   3676: iastore
    //   3677: dup
    //   3678: bipush #58
    //   3680: ldc 266240
    //   3682: iastore
    //   3683: dup
    //   3684: bipush #59
    //   3686: sipush #4160
    //   3689: iastore
    //   3690: dup
    //   3691: bipush #60
    //   3693: sipush #4160
    //   3696: iastore
    //   3697: dup
    //   3698: bipush #61
    //   3700: ldc 262208
    //   3702: iastore
    //   3703: dup
    //   3704: bipush #62
    //   3706: ldc 268435456
    //   3708: iastore
    //   3709: dup
    //   3710: bipush #63
    //   3712: ldc 268701696
    //   3714: iastore
    //   3715: astore #13
    //   3717: aload_3
    //   3718: arraylength
    //   3719: istore #14
    //   3721: iload #14
    //   3723: bipush #8
    //   3725: irem
    //   3726: ifeq -> 3750
    //   3729: new java/lang/Exception
    //   3732: dup
    //   3733: sipush #30130
    //   3736: sipush #-4189
    //   3739: invokestatic a : (II)Ljava/lang/String;
    //   3742: invokespecial <init> : (Ljava/lang/String;)V
    //   3745: athrow
    //   3746: invokestatic a : (Ljava/lang/Throwable;)Ljava/lang/Throwable;
    //   3749: athrow
    //   3750: iconst_2
    //   3751: newarray int
    //   3753: astore #15
    //   3755: iload #14
    //   3757: newarray byte
    //   3759: astore #16
    //   3761: iload #14
    //   3763: bipush #8
    //   3765: idiv
    //   3766: istore #17
    //   3768: iconst_0
    //   3769: istore #18
    //   3771: iload #18
    //   3773: iload #17
    //   3775: if_icmpge -> 4689
    //   3778: iload #18
    //   3780: bipush #8
    //   3782: imul
    //   3783: istore #19
    //   3785: iconst_0
    //   3786: istore #20
    //   3788: iload #20
    //   3790: iconst_2
    //   3791: if_icmpge -> 3876
    //   3794: aload #15
    //   3796: iload #20
    //   3798: aload_3
    //   3799: iload #19
    //   3801: iload #20
    //   3803: iconst_4
    //   3804: imul
    //   3805: iadd
    //   3806: baload
    //   3807: sipush #255
    //   3810: iand
    //   3811: bipush #24
    //   3813: ishl
    //   3814: aload_3
    //   3815: iload #19
    //   3817: iload #20
    //   3819: iconst_4
    //   3820: imul
    //   3821: iadd
    //   3822: iconst_1
    //   3823: iadd
    //   3824: baload
    //   3825: sipush #255
    //   3828: iand
    //   3829: bipush #16
    //   3831: ishl
    //   3832: ior
    //   3833: aload_3
    //   3834: iload #19
    //   3836: iload #20
    //   3838: iconst_4
    //   3839: imul
    //   3840: iadd
    //   3841: iconst_2
    //   3842: iadd
    //   3843: baload
    //   3844: sipush #255
    //   3847: iand
    //   3848: bipush #8
    //   3850: ishl
    //   3851: ior
    //   3852: aload_3
    //   3853: iload #19
    //   3855: iload #20
    //   3857: iconst_4
    //   3858: imul
    //   3859: iadd
    //   3860: iconst_3
    //   3861: iadd
    //   3862: baload
    //   3863: sipush #255
    //   3866: iand
    //   3867: ior
    //   3868: iastore
    //   3869: iinc #20, 1
    //   3872: iload_2
    //   3873: ifne -> 3788
    //   3876: iconst_0
    //   3877: istore #25
    //   3879: aload #15
    //   3881: iconst_0
    //   3882: iaload
    //   3883: istore #23
    //   3885: aload #15
    //   3887: iconst_1
    //   3888: iaload
    //   3889: istore #22
    //   3891: iload #23
    //   3893: iconst_4
    //   3894: iushr
    //   3895: iload #22
    //   3897: ixor
    //   3898: ldc 252645135
    //   3900: iand
    //   3901: istore #21
    //   3903: iload #22
    //   3905: iload #21
    //   3907: ixor
    //   3908: istore #22
    //   3910: iload #23
    //   3912: iload #21
    //   3914: iconst_4
    //   3915: ishl
    //   3916: ixor
    //   3917: istore #23
    //   3919: iload #23
    //   3921: bipush #16
    //   3923: iushr
    //   3924: iload #22
    //   3926: ixor
    //   3927: ldc 65535
    //   3929: iand
    //   3930: istore #21
    //   3932: iload #22
    //   3934: iload #21
    //   3936: ixor
    //   3937: istore #22
    //   3939: iload #23
    //   3941: iload #21
    //   3943: bipush #16
    //   3945: ishl
    //   3946: ixor
    //   3947: istore #23
    //   3949: iload #22
    //   3951: iconst_2
    //   3952: iushr
    //   3953: iload #23
    //   3955: ixor
    //   3956: ldc 858993459
    //   3958: iand
    //   3959: istore #21
    //   3961: iload #23
    //   3963: iload #21
    //   3965: ixor
    //   3966: istore #23
    //   3968: iload #22
    //   3970: iload #21
    //   3972: iconst_2
    //   3973: ishl
    //   3974: ixor
    //   3975: istore #22
    //   3977: iload #22
    //   3979: bipush #8
    //   3981: iushr
    //   3982: iload #23
    //   3984: ixor
    //   3985: ldc 16711935
    //   3987: iand
    //   3988: istore #21
    //   3990: iload #23
    //   3992: iload #21
    //   3994: ixor
    //   3995: istore #23
    //   3997: iload #22
    //   3999: iload #21
    //   4001: bipush #8
    //   4003: ishl
    //   4004: ixor
    //   4005: istore #22
    //   4007: iload #22
    //   4009: iconst_1
    //   4010: ishl
    //   4011: iload #22
    //   4013: bipush #31
    //   4015: iushr
    //   4016: iconst_1
    //   4017: iand
    //   4018: ior
    //   4019: istore #22
    //   4021: iload #23
    //   4023: iload #22
    //   4025: ixor
    //   4026: ldc -1431655766
    //   4028: iand
    //   4029: istore #21
    //   4031: iload #23
    //   4033: iload #21
    //   4035: ixor
    //   4036: istore #23
    //   4038: iload #22
    //   4040: iload #21
    //   4042: ixor
    //   4043: istore #22
    //   4045: iload #23
    //   4047: iconst_1
    //   4048: ishl
    //   4049: iload #23
    //   4051: bipush #31
    //   4053: iushr
    //   4054: iconst_1
    //   4055: iand
    //   4056: ior
    //   4057: istore #23
    //   4059: iconst_0
    //   4060: istore #24
    //   4062: iload #24
    //   4064: bipush #8
    //   4066: if_icmpge -> 4404
    //   4069: iload #22
    //   4071: bipush #28
    //   4073: ishl
    //   4074: iload #22
    //   4076: iconst_4
    //   4077: iushr
    //   4078: ior
    //   4079: istore #21
    //   4081: iload #21
    //   4083: aload #5
    //   4085: iload #25
    //   4087: iinc #25, 1
    //   4090: iaload
    //   4091: ixor
    //   4092: istore #21
    //   4094: aload #12
    //   4096: iload #21
    //   4098: bipush #63
    //   4100: iand
    //   4101: iaload
    //   4102: istore #20
    //   4104: iload #20
    //   4106: aload #10
    //   4108: iload #21
    //   4110: bipush #8
    //   4112: iushr
    //   4113: bipush #63
    //   4115: iand
    //   4116: iaload
    //   4117: ior
    //   4118: istore #20
    //   4120: iload #20
    //   4122: aload #8
    //   4124: iload #21
    //   4126: bipush #16
    //   4128: iushr
    //   4129: bipush #63
    //   4131: iand
    //   4132: iaload
    //   4133: ior
    //   4134: istore #20
    //   4136: iload #20
    //   4138: aload #6
    //   4140: iload #21
    //   4142: bipush #24
    //   4144: iushr
    //   4145: bipush #63
    //   4147: iand
    //   4148: iaload
    //   4149: ior
    //   4150: istore #20
    //   4152: iload #22
    //   4154: aload #5
    //   4156: iload #25
    //   4158: iinc #25, 1
    //   4161: iaload
    //   4162: ixor
    //   4163: istore #21
    //   4165: iload #20
    //   4167: aload #13
    //   4169: iload #21
    //   4171: bipush #63
    //   4173: iand
    //   4174: iaload
    //   4175: ior
    //   4176: istore #20
    //   4178: iload #20
    //   4180: aload #11
    //   4182: iload #21
    //   4184: bipush #8
    //   4186: iushr
    //   4187: bipush #63
    //   4189: iand
    //   4190: iaload
    //   4191: ior
    //   4192: istore #20
    //   4194: iload #20
    //   4196: aload #9
    //   4198: iload #21
    //   4200: bipush #16
    //   4202: iushr
    //   4203: bipush #63
    //   4205: iand
    //   4206: iaload
    //   4207: ior
    //   4208: istore #20
    //   4210: iload #20
    //   4212: aload #7
    //   4214: iload #21
    //   4216: bipush #24
    //   4218: iushr
    //   4219: bipush #63
    //   4221: iand
    //   4222: iaload
    //   4223: ior
    //   4224: istore #20
    //   4226: iload #23
    //   4228: iload #20
    //   4230: ixor
    //   4231: istore #23
    //   4233: iload #23
    //   4235: bipush #28
    //   4237: ishl
    //   4238: iload #23
    //   4240: iconst_4
    //   4241: iushr
    //   4242: ior
    //   4243: istore #21
    //   4245: iload #21
    //   4247: aload #5
    //   4249: iload #25
    //   4251: iinc #25, 1
    //   4254: iaload
    //   4255: ixor
    //   4256: istore #21
    //   4258: aload #12
    //   4260: iload #21
    //   4262: bipush #63
    //   4264: iand
    //   4265: iaload
    //   4266: istore #20
    //   4268: iload #20
    //   4270: aload #10
    //   4272: iload #21
    //   4274: bipush #8
    //   4276: iushr
    //   4277: bipush #63
    //   4279: iand
    //   4280: iaload
    //   4281: ior
    //   4282: istore #20
    //   4284: iload #20
    //   4286: aload #8
    //   4288: iload #21
    //   4290: bipush #16
    //   4292: iushr
    //   4293: bipush #63
    //   4295: iand
    //   4296: iaload
    //   4297: ior
    //   4298: istore #20
    //   4300: iload #20
    //   4302: aload #6
    //   4304: iload #21
    //   4306: bipush #24
    //   4308: iushr
    //   4309: bipush #63
    //   4311: iand
    //   4312: iaload
    //   4313: ior
    //   4314: istore #20
    //   4316: iload #23
    //   4318: aload #5
    //   4320: iload #25
    //   4322: iinc #25, 1
    //   4325: iaload
    //   4326: ixor
    //   4327: istore #21
    //   4329: iload #20
    //   4331: aload #13
    //   4333: iload #21
    //   4335: bipush #63
    //   4337: iand
    //   4338: iaload
    //   4339: ior
    //   4340: istore #20
    //   4342: iload #20
    //   4344: aload #11
    //   4346: iload #21
    //   4348: bipush #8
    //   4350: iushr
    //   4351: bipush #63
    //   4353: iand
    //   4354: iaload
    //   4355: ior
    //   4356: istore #20
    //   4358: iload #20
    //   4360: aload #9
    //   4362: iload #21
    //   4364: bipush #16
    //   4366: iushr
    //   4367: bipush #63
    //   4369: iand
    //   4370: iaload
    //   4371: ior
    //   4372: istore #20
    //   4374: iload #20
    //   4376: aload #7
    //   4378: iload #21
    //   4380: bipush #24
    //   4382: iushr
    //   4383: bipush #63
    //   4385: iand
    //   4386: iaload
    //   4387: ior
    //   4388: istore #20
    //   4390: iload #22
    //   4392: iload #20
    //   4394: ixor
    //   4395: istore #22
    //   4397: iinc #24, 1
    //   4400: iload_2
    //   4401: ifne -> 4062
    //   4404: iload #22
    //   4406: bipush #31
    //   4408: ishl
    //   4409: iload #22
    //   4411: iconst_1
    //   4412: iushr
    //   4413: ior
    //   4414: istore #22
    //   4416: iload #23
    //   4418: iload #22
    //   4420: ixor
    //   4421: ldc -1431655766
    //   4423: iand
    //   4424: istore #21
    //   4426: iload #23
    //   4428: iload #21
    //   4430: ixor
    //   4431: istore #23
    //   4433: iload #22
    //   4435: iload #21
    //   4437: ixor
    //   4438: istore #22
    //   4440: iload #23
    //   4442: bipush #31
    //   4444: ishl
    //   4445: iload #23
    //   4447: iconst_1
    //   4448: iushr
    //   4449: ior
    //   4450: istore #23
    //   4452: iload #23
    //   4454: bipush #8
    //   4456: iushr
    //   4457: iload #22
    //   4459: ixor
    //   4460: ldc 16711935
    //   4462: iand
    //   4463: istore #21
    //   4465: iload #22
    //   4467: iload #21
    //   4469: ixor
    //   4470: istore #22
    //   4472: iload #23
    //   4474: iload #21
    //   4476: bipush #8
    //   4478: ishl
    //   4479: ixor
    //   4480: istore #23
    //   4482: iload #23
    //   4484: iconst_2
    //   4485: iushr
    //   4486: iload #22
    //   4488: ixor
    //   4489: ldc 858993459
    //   4491: iand
    //   4492: istore #21
    //   4494: iload #22
    //   4496: iload #21
    //   4498: ixor
    //   4499: istore #22
    //   4501: iload #23
    //   4503: iload #21
    //   4505: iconst_2
    //   4506: ishl
    //   4507: ixor
    //   4508: istore #23
    //   4510: iload #22
    //   4512: bipush #16
    //   4514: iushr
    //   4515: iload #23
    //   4517: ixor
    //   4518: ldc 65535
    //   4520: iand
    //   4521: istore #21
    //   4523: iload #23
    //   4525: iload #21
    //   4527: ixor
    //   4528: istore #23
    //   4530: iload #22
    //   4532: iload #21
    //   4534: bipush #16
    //   4536: ishl
    //   4537: ixor
    //   4538: istore #22
    //   4540: iload #22
    //   4542: iconst_4
    //   4543: iushr
    //   4544: iload #23
    //   4546: ixor
    //   4547: ldc 252645135
    //   4549: iand
    //   4550: istore #21
    //   4552: iload #23
    //   4554: iload #21
    //   4556: ixor
    //   4557: istore #23
    //   4559: iload #22
    //   4561: iload #21
    //   4563: iconst_4
    //   4564: ishl
    //   4565: ixor
    //   4566: istore #22
    //   4568: aload #15
    //   4570: iconst_0
    //   4571: iload #22
    //   4573: iastore
    //   4574: aload #15
    //   4576: iconst_1
    //   4577: iload #23
    //   4579: iastore
    //   4580: iload #18
    //   4582: bipush #8
    //   4584: imul
    //   4585: istore #26
    //   4587: iconst_0
    //   4588: istore #27
    //   4590: iload #27
    //   4592: iconst_2
    //   4593: if_icmpge -> 4682
    //   4596: aload #16
    //   4598: iload #26
    //   4600: iload #27
    //   4602: iconst_4
    //   4603: imul
    //   4604: iadd
    //   4605: aload #15
    //   4607: iload #27
    //   4609: iaload
    //   4610: bipush #24
    //   4612: iushr
    //   4613: i2b
    //   4614: bastore
    //   4615: aload #16
    //   4617: iload #26
    //   4619: iload #27
    //   4621: iconst_4
    //   4622: imul
    //   4623: iadd
    //   4624: iconst_1
    //   4625: iadd
    //   4626: aload #15
    //   4628: iload #27
    //   4630: iaload
    //   4631: bipush #16
    //   4633: iushr
    //   4634: i2b
    //   4635: bastore
    //   4636: aload #16
    //   4638: iload #26
    //   4640: iload #27
    //   4642: iconst_4
    //   4643: imul
    //   4644: iadd
    //   4645: iconst_2
    //   4646: iadd
    //   4647: aload #15
    //   4649: iload #27
    //   4651: iaload
    //   4652: bipush #8
    //   4654: iushr
    //   4655: i2b
    //   4656: bastore
    //   4657: aload #16
    //   4659: iload #26
    //   4661: iload #27
    //   4663: iconst_4
    //   4664: imul
    //   4665: iadd
    //   4666: iconst_3
    //   4667: iadd
    //   4668: aload #15
    //   4670: iload #27
    //   4672: iaload
    //   4673: i2b
    //   4674: bastore
    //   4675: iinc #27, 1
    //   4678: iload_2
    //   4679: ifne -> 4590
    //   4682: iinc #18, 1
    //   4685: iload_2
    //   4686: ifne -> 3771
    //   4689: aload #16
    //   4691: aload #16
    //   4693: arraylength
    //   4694: iconst_1
    //   4695: isub
    //   4696: baload
    //   4697: istore #18
    //   4699: aload #16
    //   4701: arraylength
    //   4702: iload #18
    //   4704: isub
    //   4705: newarray byte
    //   4707: astore #4
    //   4709: aload #16
    //   4711: arraylength
    //   4712: aload #4
    //   4714: arraylength
    //   4715: if_icmpge -> 4739
    //   4718: new java/lang/Exception
    //   4721: dup
    //   4722: sipush #30133
    //   4725: sipush #1109
    //   4728: invokestatic a : (II)Ljava/lang/String;
    //   4731: invokespecial <init> : (Ljava/lang/String;)V
    //   4734: athrow
    //   4735: invokestatic a : (Ljava/lang/Throwable;)Ljava/lang/Throwable;
    //   4738: athrow
    //   4739: iconst_0
    //   4740: istore #19
    //   4742: iload #19
    //   4744: aload #4
    //   4746: arraylength
    //   4747: if_icmpge -> 4767
    //   4750: aload #4
    //   4752: iload #19
    //   4754: aload #16
    //   4756: iload #19
    //   4758: baload
    //   4759: bastore
    //   4760: iinc #19, 1
    //   4763: iload_2
    //   4764: ifne -> 4742
    //   4767: new java/math/BigInteger
    //   4770: dup
    //   4771: aload #4
    //   4773: invokespecial <init> : ([B)V
    //   4776: invokevirtual abs : ()Ljava/math/BigInteger;
    //   4779: putstatic burp/Zr8h.ZH : Ljava/lang/Object;
    //   4782: getstatic burp/Zzai.Z_ : Ljava/lang/Object;
    //   4785: checkcast java/math/BigInteger
    //   4788: invokevirtual toByteArray : ()[B
    //   4791: astore_3
    //   4792: bipush #64
    //   4794: newarray byte
    //   4796: dup
    //   4797: iconst_0
    //   4798: bipush #-128
    //   4800: bastore
    //   4801: dup
    //   4802: iconst_1
    //   4803: iconst_0
    //   4804: bastore
    //   4805: dup
    //   4806: iconst_2
    //   4807: iconst_0
    //   4808: bastore
    //   4809: dup
    //   4810: iconst_3
    //   4811: iconst_0
    //   4812: bastore
    //   4813: dup
    //   4814: iconst_4
    //   4815: iconst_0
    //   4816: bastore
    //   4817: dup
    //   4818: iconst_5
    //   4819: iconst_0
    //   4820: bastore
    //   4821: dup
    //   4822: bipush #6
    //   4824: iconst_0
    //   4825: bastore
    //   4826: dup
    //   4827: bipush #7
    //   4829: iconst_0
    //   4830: bastore
    //   4831: dup
    //   4832: bipush #8
    //   4834: iconst_0
    //   4835: bastore
    //   4836: dup
    //   4837: bipush #9
    //   4839: iconst_0
    //   4840: bastore
    //   4841: dup
    //   4842: bipush #10
    //   4844: iconst_0
    //   4845: bastore
    //   4846: dup
    //   4847: bipush #11
    //   4849: iconst_0
    //   4850: bastore
    //   4851: dup
    //   4852: bipush #12
    //   4854: iconst_0
    //   4855: bastore
    //   4856: dup
    //   4857: bipush #13
    //   4859: iconst_0
    //   4860: bastore
    //   4861: dup
    //   4862: bipush #14
    //   4864: iconst_0
    //   4865: bastore
    //   4866: dup
    //   4867: bipush #15
    //   4869: iconst_0
    //   4870: bastore
    //   4871: dup
    //   4872: bipush #16
    //   4874: iconst_0
    //   4875: bastore
    //   4876: dup
    //   4877: bipush #17
    //   4879: iconst_0
    //   4880: bastore
    //   4881: dup
    //   4882: bipush #18
    //   4884: iconst_0
    //   4885: bastore
    //   4886: dup
    //   4887: bipush #19
    //   4889: iconst_0
    //   4890: bastore
    //   4891: dup
    //   4892: bipush #20
    //   4894: iconst_0
    //   4895: bastore
    //   4896: dup
    //   4897: bipush #21
    //   4899: iconst_0
    //   4900: bastore
    //   4901: dup
    //   4902: bipush #22
    //   4904: iconst_0
    //   4905: bastore
    //   4906: dup
    //   4907: bipush #23
    //   4909: iconst_0
    //   4910: bastore
    //   4911: dup
    //   4912: bipush #24
    //   4914: iconst_0
    //   4915: bastore
    //   4916: dup
    //   4917: bipush #25
    //   4919: iconst_0
    //   4920: bastore
    //   4921: dup
    //   4922: bipush #26
    //   4924: iconst_0
    //   4925: bastore
    //   4926: dup
    //   4927: bipush #27
    //   4929: iconst_0
    //   4930: bastore
    //   4931: dup
    //   4932: bipush #28
    //   4934: iconst_0
    //   4935: bastore
    //   4936: dup
    //   4937: bipush #29
    //   4939: iconst_0
    //   4940: bastore
    //   4941: dup
    //   4942: bipush #30
    //   4944: iconst_0
    //   4945: bastore
    //   4946: dup
    //   4947: bipush #31
    //   4949: iconst_0
    //   4950: bastore
    //   4951: dup
    //   4952: bipush #32
    //   4954: iconst_0
    //   4955: bastore
    //   4956: dup
    //   4957: bipush #33
    //   4959: iconst_0
    //   4960: bastore
    //   4961: dup
    //   4962: bipush #34
    //   4964: iconst_0
    //   4965: bastore
    //   4966: dup
    //   4967: bipush #35
    //   4969: iconst_0
    //   4970: bastore
    //   4971: dup
    //   4972: bipush #36
    //   4974: iconst_0
    //   4975: bastore
    //   4976: dup
    //   4977: bipush #37
    //   4979: iconst_0
    //   4980: bastore
    //   4981: dup
    //   4982: bipush #38
    //   4984: iconst_0
    //   4985: bastore
    //   4986: dup
    //   4987: bipush #39
    //   4989: iconst_0
    //   4990: bastore
    //   4991: dup
    //   4992: bipush #40
    //   4994: iconst_0
    //   4995: bastore
    //   4996: dup
    //   4997: bipush #41
    //   4999: iconst_0
    //   5000: bastore
    //   5001: dup
    //   5002: bipush #42
    //   5004: iconst_0
    //   5005: bastore
    //   5006: dup
    //   5007: bipush #43
    //   5009: iconst_0
    //   5010: bastore
    //   5011: dup
    //   5012: bipush #44
    //   5014: iconst_0
    //   5015: bastore
    //   5016: dup
    //   5017: bipush #45
    //   5019: iconst_0
    //   5020: bastore
    //   5021: dup
    //   5022: bipush #46
    //   5024: iconst_0
    //   5025: bastore
    //   5026: dup
    //   5027: bipush #47
    //   5029: iconst_0
    //   5030: bastore
    //   5031: dup
    //   5032: bipush #48
    //   5034: iconst_0
    //   5035: bastore
    //   5036: dup
    //   5037: bipush #49
    //   5039: iconst_0
    //   5040: bastore
    //   5041: dup
    //   5042: bipush #50
    //   5044: iconst_0
    //   5045: bastore
    //   5046: dup
    //   5047: bipush #51
    //   5049: iconst_0
    //   5050: bastore
    //   5051: dup
    //   5052: bipush #52
    //   5054: iconst_0
    //   5055: bastore
    //   5056: dup
    //   5057: bipush #53
    //   5059: iconst_0
    //   5060: bastore
    //   5061: dup
    //   5062: bipush #54
    //   5064: iconst_0
    //   5065: bastore
    //   5066: dup
    //   5067: bipush #55
    //   5069: iconst_0
    //   5070: bastore
    //   5071: dup
    //   5072: bipush #56
    //   5074: iconst_0
    //   5075: bastore
    //   5076: dup
    //   5077: bipush #57
    //   5079: iconst_0
    //   5080: bastore
    //   5081: dup
    //   5082: bipush #58
    //   5084: iconst_0
    //   5085: bastore
    //   5086: dup
    //   5087: bipush #59
    //   5089: iconst_0
    //   5090: bastore
    //   5091: dup
    //   5092: bipush #60
    //   5094: iconst_0
    //   5095: bastore
    //   5096: dup
    //   5097: bipush #61
    //   5099: iconst_0
    //   5100: bastore
    //   5101: dup
    //   5102: bipush #62
    //   5104: iconst_0
    //   5105: bastore
    //   5106: dup
    //   5107: bipush #63
    //   5109: iconst_0
    //   5110: bastore
    //   5111: astore #5
    //   5113: bipush #64
    //   5115: newarray int
    //   5117: dup
    //   5118: iconst_0
    //   5119: ldc 1116352408
    //   5121: iastore
    //   5122: dup
    //   5123: iconst_1
    //   5124: ldc 1899447441
    //   5126: iastore
    //   5127: dup
    //   5128: iconst_2
    //   5129: ldc -1245643825
    //   5131: iastore
    //   5132: dup
    //   5133: iconst_3
    //   5134: ldc -373957723
    //   5136: iastore
    //   5137: dup
    //   5138: iconst_4
    //   5139: ldc 961987163
    //   5141: iastore
    //   5142: dup
    //   5143: iconst_5
    //   5144: ldc 1508970993
    //   5146: iastore
    //   5147: dup
    //   5148: bipush #6
    //   5150: ldc -1841331548
    //   5152: iastore
    //   5153: dup
    //   5154: bipush #7
    //   5156: ldc -1424204075
    //   5158: iastore
    //   5159: dup
    //   5160: bipush #8
    //   5162: ldc -670586216
    //   5164: iastore
    //   5165: dup
    //   5166: bipush #9
    //   5168: ldc 310598401
    //   5170: iastore
    //   5171: dup
    //   5172: bipush #10
    //   5174: ldc 607225278
    //   5176: iastore
    //   5177: dup
    //   5178: bipush #11
    //   5180: ldc 1426881987
    //   5182: iastore
    //   5183: dup
    //   5184: bipush #12
    //   5186: ldc 1925078388
    //   5188: iastore
    //   5189: dup
    //   5190: bipush #13
    //   5192: ldc -2132889090
    //   5194: iastore
    //   5195: dup
    //   5196: bipush #14
    //   5198: ldc -1680079193
    //   5200: iastore
    //   5201: dup
    //   5202: bipush #15
    //   5204: ldc -1046744716
    //   5206: iastore
    //   5207: dup
    //   5208: bipush #16
    //   5210: ldc -459576895
    //   5212: iastore
    //   5213: dup
    //   5214: bipush #17
    //   5216: ldc -272742522
    //   5218: iastore
    //   5219: dup
    //   5220: bipush #18
    //   5222: ldc 264347078
    //   5224: iastore
    //   5225: dup
    //   5226: bipush #19
    //   5228: ldc 604807628
    //   5230: iastore
    //   5231: dup
    //   5232: bipush #20
    //   5234: ldc 770255983
    //   5236: iastore
    //   5237: dup
    //   5238: bipush #21
    //   5240: ldc 1249150122
    //   5242: iastore
    //   5243: dup
    //   5244: bipush #22
    //   5246: ldc 1555081692
    //   5248: iastore
    //   5249: dup
    //   5250: bipush #23
    //   5252: ldc 1996064986
    //   5254: iastore
    //   5255: dup
    //   5256: bipush #24
    //   5258: ldc -1740746414
    //   5260: iastore
    //   5261: dup
    //   5262: bipush #25
    //   5264: ldc -1473132947
    //   5266: iastore
    //   5267: dup
    //   5268: bipush #26
    //   5270: ldc -1341970488
    //   5272: iastore
    //   5273: dup
    //   5274: bipush #27
    //   5276: ldc -1084653625
    //   5278: iastore
    //   5279: dup
    //   5280: bipush #28
    //   5282: ldc -958395405
    //   5284: iastore
    //   5285: dup
    //   5286: bipush #29
    //   5288: ldc -710438585
    //   5290: iastore
    //   5291: dup
    //   5292: bipush #30
    //   5294: ldc 113926993
    //   5296: iastore
    //   5297: dup
    //   5298: bipush #31
    //   5300: ldc 338241895
    //   5302: iastore
    //   5303: dup
    //   5304: bipush #32
    //   5306: ldc 666307205
    //   5308: iastore
    //   5309: dup
    //   5310: bipush #33
    //   5312: ldc 773529912
    //   5314: iastore
    //   5315: dup
    //   5316: bipush #34
    //   5318: ldc 1294757372
    //   5320: iastore
    //   5321: dup
    //   5322: bipush #35
    //   5324: ldc 1396182291
    //   5326: iastore
    //   5327: dup
    //   5328: bipush #36
    //   5330: ldc 1695183700
    //   5332: iastore
    //   5333: dup
    //   5334: bipush #37
    //   5336: ldc 1986661051
    //   5338: iastore
    //   5339: dup
    //   5340: bipush #38
    //   5342: ldc -2117940946
    //   5344: iastore
    //   5345: dup
    //   5346: bipush #39
    //   5348: ldc -1838011259
    //   5350: iastore
    //   5351: dup
    //   5352: bipush #40
    //   5354: ldc -1564481375
    //   5356: iastore
    //   5357: dup
    //   5358: bipush #41
    //   5360: ldc -1474664885
    //   5362: iastore
    //   5363: dup
    //   5364: bipush #42
    //   5366: ldc -1035236496
    //   5368: iastore
    //   5369: dup
    //   5370: bipush #43
    //   5372: ldc -949202525
    //   5374: iastore
    //   5375: dup
    //   5376: bipush #44
    //   5378: ldc -778901479
    //   5380: iastore
    //   5381: dup
    //   5382: bipush #45
    //   5384: ldc -694614492
    //   5386: iastore
    //   5387: dup
    //   5388: bipush #46
    //   5390: ldc -200395387
    //   5392: iastore
    //   5393: dup
    //   5394: bipush #47
    //   5396: ldc 275423344
    //   5398: iastore
    //   5399: dup
    //   5400: bipush #48
    //   5402: ldc 430227734
    //   5404: iastore
    //   5405: dup
    //   5406: bipush #49
    //   5408: ldc 506948616
    //   5410: iastore
    //   5411: dup
    //   5412: bipush #50
    //   5414: ldc 659060556
    //   5416: iastore
    //   5417: dup
    //   5418: bipush #51
    //   5420: ldc 883997877
    //   5422: iastore
    //   5423: dup
    //   5424: bipush #52
    //   5426: ldc 958139571
    //   5428: iastore
    //   5429: dup
    //   5430: bipush #53
    //   5432: ldc 1322822218
    //   5434: iastore
    //   5435: dup
    //   5436: bipush #54
    //   5438: ldc 1537002063
    //   5440: iastore
    //   5441: dup
    //   5442: bipush #55
    //   5444: ldc 1747873779
    //   5446: iastore
    //   5447: dup
    //   5448: bipush #56
    //   5450: ldc 1955562222
    //   5452: iastore
    //   5453: dup
    //   5454: bipush #57
    //   5456: ldc 2024104815
    //   5458: iastore
    //   5459: dup
    //   5460: bipush #58
    //   5462: ldc -2067236844
    //   5464: iastore
    //   5465: dup
    //   5466: bipush #59
    //   5468: ldc -1933114872
    //   5470: iastore
    //   5471: dup
    //   5472: bipush #60
    //   5474: ldc -1866530822
    //   5476: iastore
    //   5477: dup
    //   5478: bipush #61
    //   5480: ldc -1538233109
    //   5482: iastore
    //   5483: dup
    //   5484: bipush #62
    //   5486: ldc -1090935817
    //   5488: iastore
    //   5489: dup
    //   5490: bipush #63
    //   5492: ldc -965641998
    //   5494: iastore
    //   5495: astore #6
    //   5497: iconst_2
    //   5498: newarray int
    //   5500: dup
    //   5501: iconst_0
    //   5502: iconst_0
    //   5503: iastore
    //   5504: dup
    //   5505: iconst_1
    //   5506: iconst_0
    //   5507: iastore
    //   5508: astore #7
    //   5510: bipush #8
    //   5512: newarray int
    //   5514: dup
    //   5515: iconst_0
    //   5516: ldc 1779033703
    //   5518: iastore
    //   5519: dup
    //   5520: iconst_1
    //   5521: ldc -1150833019
    //   5523: iastore
    //   5524: dup
    //   5525: iconst_2
    //   5526: ldc 1013904242
    //   5528: iastore
    //   5529: dup
    //   5530: iconst_3
    //   5531: ldc -1521486534
    //   5533: iastore
    //   5534: dup
    //   5535: iconst_4
    //   5536: ldc 1359893119
    //   5538: iastore
    //   5539: dup
    //   5540: iconst_5
    //   5541: ldc -1694144372
    //   5543: iastore
    //   5544: dup
    //   5545: bipush #6
    //   5547: ldc 528734635
    //   5549: iastore
    //   5550: dup
    //   5551: bipush #7
    //   5553: ldc 1541459225
    //   5555: iastore
    //   5556: astore #8
    //   5558: bipush #64
    //   5560: newarray byte
    //   5562: astore #9
    //   5564: bipush #64
    //   5566: newarray byte
    //   5568: astore #10
    //   5570: aload_3
    //   5571: arraylength
    //   5572: istore #11
    //   5574: aload #7
    //   5576: iconst_0
    //   5577: iaload
    //   5578: bipush #63
    //   5580: iand
    //   5581: istore #12
    //   5583: aload #7
    //   5585: iconst_0
    //   5586: dup2
    //   5587: iaload
    //   5588: iload #11
    //   5590: iadd
    //   5591: iastore
    //   5592: aload #7
    //   5594: iconst_0
    //   5595: dup2
    //   5596: iaload
    //   5597: iconst_m1
    //   5598: iand
    //   5599: iastore
    //   5600: aload #7
    //   5602: iconst_0
    //   5603: iaload
    //   5604: iload #11
    //   5606: if_icmpge -> 5624
    //   5609: aload #7
    //   5611: iconst_1
    //   5612: dup2
    //   5613: iaload
    //   5614: iconst_1
    //   5615: iadd
    //   5616: iastore
    //   5617: goto -> 5624
    //   5620: invokestatic a : (Ljava/lang/Throwable;)Ljava/lang/Throwable;
    //   5623: athrow
    //   5624: iconst_0
    //   5625: istore #13
    //   5627: iload #11
    //   5629: bipush #64
    //   5631: if_icmplt -> 6240
    //   5634: iconst_0
    //   5635: istore #14
    //   5637: iload #14
    //   5639: bipush #64
    //   5641: if_icmpge -> 5663
    //   5644: aload #10
    //   5646: iload #14
    //   5648: aload_3
    //   5649: iload #13
    //   5651: iload #14
    //   5653: iadd
    //   5654: baload
    //   5655: bastore
    //   5656: iinc #14, 1
    //   5659: iload_2
    //   5660: ifne -> 5637
    //   5663: bipush #64
    //   5665: newarray int
    //   5667: astore #14
    //   5669: bipush #8
    //   5671: newarray int
    //   5673: astore #15
    //   5675: iconst_0
    //   5676: istore #16
    //   5678: iload #16
    //   5680: bipush #8
    //   5682: if_icmpge -> 5702
    //   5685: aload #15
    //   5687: iload #16
    //   5689: aload #8
    //   5691: iload #16
    //   5693: iaload
    //   5694: iastore
    //   5695: iinc #16, 1
    //   5698: iload_2
    //   5699: ifne -> 5678
    //   5702: iconst_0
    //   5703: istore #16
    //   5705: iload #16
    //   5707: bipush #64
    //   5709: if_icmpge -> 6200
    //   5712: iload #16
    //   5714: bipush #16
    //   5716: if_icmpge -> 5797
    //   5719: aload #14
    //   5721: iload #16
    //   5723: aload #10
    //   5725: iconst_4
    //   5726: iload #16
    //   5728: imul
    //   5729: baload
    //   5730: sipush #255
    //   5733: iand
    //   5734: bipush #24
    //   5736: ishl
    //   5737: aload #10
    //   5739: iconst_4
    //   5740: iload #16
    //   5742: imul
    //   5743: iconst_1
    //   5744: iadd
    //   5745: baload
    //   5746: sipush #255
    //   5749: iand
    //   5750: bipush #16
    //   5752: ishl
    //   5753: ior
    //   5754: aload #10
    //   5756: iconst_4
    //   5757: iload #16
    //   5759: imul
    //   5760: iconst_2
    //   5761: iadd
    //   5762: baload
    //   5763: sipush #255
    //   5766: iand
    //   5767: bipush #8
    //   5769: ishl
    //   5770: ior
    //   5771: aload #10
    //   5773: iconst_4
    //   5774: iload #16
    //   5776: imul
    //   5777: iconst_3
    //   5778: iadd
    //   5779: baload
    //   5780: sipush #255
    //   5783: iand
    //   5784: ior
    //   5785: iastore
    //   5786: iload_2
    //   5787: ifne -> 5940
    //   5790: goto -> 5797
    //   5793: invokestatic a : (Ljava/lang/Throwable;)Ljava/lang/Throwable;
    //   5796: athrow
    //   5797: aload #14
    //   5799: iload #16
    //   5801: aload #14
    //   5803: iload #16
    //   5805: iconst_2
    //   5806: isub
    //   5807: iaload
    //   5808: bipush #17
    //   5810: iushr
    //   5811: aload #14
    //   5813: iload #16
    //   5815: iconst_2
    //   5816: isub
    //   5817: iaload
    //   5818: bipush #15
    //   5820: ishl
    //   5821: ior
    //   5822: aload #14
    //   5824: iload #16
    //   5826: iconst_2
    //   5827: isub
    //   5828: iaload
    //   5829: bipush #19
    //   5831: iushr
    //   5832: aload #14
    //   5834: iload #16
    //   5836: iconst_2
    //   5837: isub
    //   5838: iaload
    //   5839: bipush #13
    //   5841: ishl
    //   5842: ior
    //   5843: ixor
    //   5844: aload #14
    //   5846: iload #16
    //   5848: iconst_2
    //   5849: isub
    //   5850: iaload
    //   5851: bipush #10
    //   5853: iushr
    //   5854: ixor
    //   5855: aload #14
    //   5857: iload #16
    //   5859: bipush #7
    //   5861: isub
    //   5862: iaload
    //   5863: iadd
    //   5864: aload #14
    //   5866: iload #16
    //   5868: bipush #15
    //   5870: isub
    //   5871: iaload
    //   5872: bipush #7
    //   5874: iushr
    //   5875: aload #14
    //   5877: iload #16
    //   5879: bipush #15
    //   5881: isub
    //   5882: iaload
    //   5883: bipush #25
    //   5885: ishl
    //   5886: ior
    //   5887: aload #14
    //   5889: iload #16
    //   5891: bipush #15
    //   5893: isub
    //   5894: iaload
    //   5895: bipush #18
    //   5897: iushr
    //   5898: aload #14
    //   5900: iload #16
    //   5902: bipush #15
    //   5904: isub
    //   5905: iaload
    //   5906: bipush #14
    //   5908: ishl
    //   5909: ior
    //   5910: ixor
    //   5911: aload #14
    //   5913: iload #16
    //   5915: bipush #15
    //   5917: isub
    //   5918: iaload
    //   5919: iconst_3
    //   5920: iushr
    //   5921: ixor
    //   5922: iadd
    //   5923: aload #14
    //   5925: iload #16
    //   5927: bipush #16
    //   5929: isub
    //   5930: iaload
    //   5931: iadd
    //   5932: iastore
    //   5933: goto -> 5940
    //   5936: invokestatic a : (Ljava/lang/Throwable;)Ljava/lang/Throwable;
    //   5939: athrow
    //   5940: aload #15
    //   5942: bipush #7
    //   5944: iaload
    //   5945: aload #15
    //   5947: iconst_4
    //   5948: iaload
    //   5949: bipush #6
    //   5951: iushr
    //   5952: aload #15
    //   5954: iconst_4
    //   5955: iaload
    //   5956: bipush #26
    //   5958: ishl
    //   5959: ior
    //   5960: aload #15
    //   5962: iconst_4
    //   5963: iaload
    //   5964: bipush #11
    //   5966: iushr
    //   5967: aload #15
    //   5969: iconst_4
    //   5970: iaload
    //   5971: bipush #21
    //   5973: ishl
    //   5974: ior
    //   5975: ixor
    //   5976: aload #15
    //   5978: iconst_4
    //   5979: iaload
    //   5980: bipush #25
    //   5982: iushr
    //   5983: aload #15
    //   5985: iconst_4
    //   5986: iaload
    //   5987: bipush #7
    //   5989: ishl
    //   5990: ior
    //   5991: ixor
    //   5992: iadd
    //   5993: aload #15
    //   5995: bipush #6
    //   5997: iaload
    //   5998: aload #15
    //   6000: iconst_4
    //   6001: iaload
    //   6002: aload #15
    //   6004: iconst_5
    //   6005: iaload
    //   6006: aload #15
    //   6008: bipush #6
    //   6010: iaload
    //   6011: ixor
    //   6012: iand
    //   6013: ixor
    //   6014: iadd
    //   6015: aload #6
    //   6017: iload #16
    //   6019: iaload
    //   6020: iadd
    //   6021: aload #14
    //   6023: iload #16
    //   6025: iaload
    //   6026: iadd
    //   6027: istore #17
    //   6029: aload #15
    //   6031: iconst_0
    //   6032: iaload
    //   6033: iconst_2
    //   6034: iushr
    //   6035: aload #15
    //   6037: iconst_0
    //   6038: iaload
    //   6039: bipush #30
    //   6041: ishl
    //   6042: ior
    //   6043: aload #15
    //   6045: iconst_0
    //   6046: iaload
    //   6047: bipush #13
    //   6049: iushr
    //   6050: aload #15
    //   6052: iconst_0
    //   6053: iaload
    //   6054: bipush #19
    //   6056: ishl
    //   6057: ior
    //   6058: ixor
    //   6059: aload #15
    //   6061: iconst_0
    //   6062: iaload
    //   6063: bipush #22
    //   6065: iushr
    //   6066: aload #15
    //   6068: iconst_0
    //   6069: iaload
    //   6070: bipush #10
    //   6072: ishl
    //   6073: ior
    //   6074: ixor
    //   6075: aload #15
    //   6077: iconst_0
    //   6078: iaload
    //   6079: aload #15
    //   6081: iconst_1
    //   6082: iaload
    //   6083: iand
    //   6084: aload #15
    //   6086: iconst_2
    //   6087: iaload
    //   6088: aload #15
    //   6090: iconst_0
    //   6091: iaload
    //   6092: aload #15
    //   6094: iconst_1
    //   6095: iaload
    //   6096: ior
    //   6097: iand
    //   6098: ior
    //   6099: iadd
    //   6100: istore #18
    //   6102: aload #15
    //   6104: iconst_3
    //   6105: dup2
    //   6106: iaload
    //   6107: iload #17
    //   6109: iadd
    //   6110: iastore
    //   6111: aload #15
    //   6113: bipush #7
    //   6115: iload #17
    //   6117: iload #18
    //   6119: iadd
    //   6120: iastore
    //   6121: aload #15
    //   6123: bipush #7
    //   6125: iaload
    //   6126: istore #17
    //   6128: aload #15
    //   6130: bipush #7
    //   6132: aload #15
    //   6134: bipush #6
    //   6136: iaload
    //   6137: iastore
    //   6138: aload #15
    //   6140: bipush #6
    //   6142: aload #15
    //   6144: iconst_5
    //   6145: iaload
    //   6146: iastore
    //   6147: aload #15
    //   6149: iconst_5
    //   6150: aload #15
    //   6152: iconst_4
    //   6153: iaload
    //   6154: iastore
    //   6155: aload #15
    //   6157: iconst_4
    //   6158: aload #15
    //   6160: iconst_3
    //   6161: iaload
    //   6162: iastore
    //   6163: aload #15
    //   6165: iconst_3
    //   6166: aload #15
    //   6168: iconst_2
    //   6169: iaload
    //   6170: iastore
    //   6171: aload #15
    //   6173: iconst_2
    //   6174: aload #15
    //   6176: iconst_1
    //   6177: iaload
    //   6178: iastore
    //   6179: aload #15
    //   6181: iconst_1
    //   6182: aload #15
    //   6184: iconst_0
    //   6185: iaload
    //   6186: iastore
    //   6187: aload #15
    //   6189: iconst_0
    //   6190: iload #17
    //   6192: iastore
    //   6193: iinc #16, 1
    //   6196: iload_2
    //   6197: ifne -> 5705
    //   6200: iconst_0
    //   6201: istore #16
    //   6203: iload #16
    //   6205: bipush #8
    //   6207: if_icmpge -> 6230
    //   6210: aload #8
    //   6212: iload #16
    //   6214: dup2
    //   6215: iaload
    //   6216: aload #15
    //   6218: iload #16
    //   6220: iaload
    //   6221: iadd
    //   6222: iastore
    //   6223: iinc #16, 1
    //   6226: iload_2
    //   6227: ifne -> 6203
    //   6230: iinc #13, 64
    //   6233: iinc #11, -64
    //   6236: iload_2
    //   6237: ifne -> 5627
    //   6240: iload #11
    //   6242: ifle -> 6277
    //   6245: iconst_0
    //   6246: istore #14
    //   6248: iload #14
    //   6250: iload #11
    //   6252: if_icmpge -> 6277
    //   6255: aload #9
    //   6257: iload #12
    //   6259: iload #14
    //   6261: iadd
    //   6262: aload_3
    //   6263: iload #13
    //   6265: iload #14
    //   6267: iadd
    //   6268: baload
    //   6269: bastore
    //   6270: iinc #14, 1
    //   6273: iload_2
    //   6274: ifne -> 6248
    //   6277: aload #7
    //   6279: iconst_0
    //   6280: iaload
    //   6281: bipush #29
    //   6283: iushr
    //   6284: aload #7
    //   6286: iconst_1
    //   6287: iaload
    //   6288: iconst_3
    //   6289: ishl
    //   6290: ior
    //   6291: istore #14
    //   6293: aload #7
    //   6295: iconst_0
    //   6296: iaload
    //   6297: iconst_3
    //   6298: ishl
    //   6299: istore #15
    //   6301: aload #7
    //   6303: iconst_0
    //   6304: iaload
    //   6305: bipush #63
    //   6307: iand
    //   6308: istore #16
    //   6310: iload #16
    //   6312: bipush #56
    //   6314: if_icmpge -> 6329
    //   6317: bipush #56
    //   6319: iload #16
    //   6321: isub
    //   6322: goto -> 6334
    //   6325: invokestatic a : (Ljava/lang/Throwable;)Ljava/lang/Throwable;
    //   6328: athrow
    //   6329: bipush #120
    //   6331: iload #16
    //   6333: isub
    //   6334: istore #17
    //   6336: aload #7
    //   6338: iconst_0
    //   6339: iaload
    //   6340: bipush #63
    //   6342: iand
    //   6343: istore #12
    //   6345: bipush #64
    //   6347: iload #12
    //   6349: isub
    //   6350: istore #18
    //   6352: aload #7
    //   6354: iconst_0
    //   6355: dup2
    //   6356: iaload
    //   6357: iload #17
    //   6359: iadd
    //   6360: iastore
    //   6361: aload #7
    //   6363: iconst_0
    //   6364: dup2
    //   6365: iaload
    //   6366: iconst_m1
    //   6367: iand
    //   6368: iastore
    //   6369: aload #7
    //   6371: iconst_0
    //   6372: iaload
    //   6373: iload #17
    //   6375: if_icmpge -> 6393
    //   6378: aload #7
    //   6380: iconst_1
    //   6381: dup2
    //   6382: iaload
    //   6383: iconst_1
    //   6384: iadd
    //   6385: iastore
    //   6386: goto -> 6393
    //   6389: invokestatic a : (Ljava/lang/Throwable;)Ljava/lang/Throwable;
    //   6392: athrow
    //   6393: iconst_0
    //   6394: istore #13
    //   6396: iload #12
    //   6398: ifle -> 7029
    //   6401: iload #17
    //   6403: iload #18
    //   6405: if_icmplt -> 7029
    //   6408: goto -> 6415
    //   6411: invokestatic a : (Ljava/lang/Throwable;)Ljava/lang/Throwable;
    //   6414: athrow
    //   6415: iconst_0
    //   6416: istore #19
    //   6418: iload #19
    //   6420: iload #18
    //   6422: if_icmpge -> 6445
    //   6425: aload #9
    //   6427: iload #12
    //   6429: iload #19
    //   6431: iadd
    //   6432: aload #5
    //   6434: iload #19
    //   6436: baload
    //   6437: bastore
    //   6438: iinc #19, 1
    //   6441: iload_2
    //   6442: ifne -> 6418
    //   6445: bipush #64
    //   6447: newarray int
    //   6449: astore #19
    //   6451: bipush #8
    //   6453: newarray int
    //   6455: astore #20
    //   6457: iconst_0
    //   6458: istore #21
    //   6460: iload #21
    //   6462: bipush #8
    //   6464: if_icmpge -> 6484
    //   6467: aload #20
    //   6469: iload #21
    //   6471: aload #8
    //   6473: iload #21
    //   6475: iaload
    //   6476: iastore
    //   6477: iinc #21, 1
    //   6480: iload_2
    //   6481: ifne -> 6460
    //   6484: iconst_0
    //   6485: istore #21
    //   6487: iload #21
    //   6489: bipush #64
    //   6491: if_icmpge -> 6982
    //   6494: iload #21
    //   6496: bipush #16
    //   6498: if_icmpge -> 6579
    //   6501: aload #19
    //   6503: iload #21
    //   6505: aload #9
    //   6507: iconst_4
    //   6508: iload #21
    //   6510: imul
    //   6511: baload
    //   6512: sipush #255
    //   6515: iand
    //   6516: bipush #24
    //   6518: ishl
    //   6519: aload #9
    //   6521: iconst_4
    //   6522: iload #21
    //   6524: imul
    //   6525: iconst_1
    //   6526: iadd
    //   6527: baload
    //   6528: sipush #255
    //   6531: iand
    //   6532: bipush #16
    //   6534: ishl
    //   6535: ior
    //   6536: aload #9
    //   6538: iconst_4
    //   6539: iload #21
    //   6541: imul
    //   6542: iconst_2
    //   6543: iadd
    //   6544: baload
    //   6545: sipush #255
    //   6548: iand
    //   6549: bipush #8
    //   6551: ishl
    //   6552: ior
    //   6553: aload #9
    //   6555: iconst_4
    //   6556: iload #21
    //   6558: imul
    //   6559: iconst_3
    //   6560: iadd
    //   6561: baload
    //   6562: sipush #255
    //   6565: iand
    //   6566: ior
    //   6567: iastore
    //   6568: iload_2
    //   6569: ifne -> 6722
    //   6572: goto -> 6579
    //   6575: invokestatic a : (Ljava/lang/Throwable;)Ljava/lang/Throwable;
    //   6578: athrow
    //   6579: aload #19
    //   6581: iload #21
    //   6583: aload #19
    //   6585: iload #21
    //   6587: iconst_2
    //   6588: isub
    //   6589: iaload
    //   6590: bipush #17
    //   6592: iushr
    //   6593: aload #19
    //   6595: iload #21
    //   6597: iconst_2
    //   6598: isub
    //   6599: iaload
    //   6600: bipush #15
    //   6602: ishl
    //   6603: ior
    //   6604: aload #19
    //   6606: iload #21
    //   6608: iconst_2
    //   6609: isub
    //   6610: iaload
    //   6611: bipush #19
    //   6613: iushr
    //   6614: aload #19
    //   6616: iload #21
    //   6618: iconst_2
    //   6619: isub
    //   6620: iaload
    //   6621: bipush #13
    //   6623: ishl
    //   6624: ior
    //   6625: ixor
    //   6626: aload #19
    //   6628: iload #21
    //   6630: iconst_2
    //   6631: isub
    //   6632: iaload
    //   6633: bipush #10
    //   6635: iushr
    //   6636: ixor
    //   6637: aload #19
    //   6639: iload #21
    //   6641: bipush #7
    //   6643: isub
    //   6644: iaload
    //   6645: iadd
    //   6646: aload #19
    //   6648: iload #21
    //   6650: bipush #15
    //   6652: isub
    //   6653: iaload
    //   6654: bipush #7
    //   6656: iushr
    //   6657: aload #19
    //   6659: iload #21
    //   6661: bipush #15
    //   6663: isub
    //   6664: iaload
    //   6665: bipush #25
    //   6667: ishl
    //   6668: ior
    //   6669: aload #19
    //   6671: iload #21
    //   6673: bipush #15
    //   6675: isub
    //   6676: iaload
    //   6677: bipush #18
    //   6679: iushr
    //   6680: aload #19
    //   6682: iload #21
    //   6684: bipush #15
    //   6686: isub
    //   6687: iaload
    //   6688: bipush #14
    //   6690: ishl
    //   6691: ior
    //   6692: ixor
    //   6693: aload #19
    //   6695: iload #21
    //   6697: bipush #15
    //   6699: isub
    //   6700: iaload
    //   6701: iconst_3
    //   6702: iushr
    //   6703: ixor
    //   6704: iadd
    //   6705: aload #19
    //   6707: iload #21
    //   6709: bipush #16
    //   6711: isub
    //   6712: iaload
    //   6713: iadd
    //   6714: iastore
    //   6715: goto -> 6722
    //   6718: invokestatic a : (Ljava/lang/Throwable;)Ljava/lang/Throwable;
    //   6721: athrow
    //   6722: aload #20
    //   6724: bipush #7
    //   6726: iaload
    //   6727: aload #20
    //   6729: iconst_4
    //   6730: iaload
    //   6731: bipush #6
    //   6733: iushr
    //   6734: aload #20
    //   6736: iconst_4
    //   6737: iaload
    //   6738: bipush #26
    //   6740: ishl
    //   6741: ior
    //   6742: aload #20
    //   6744: iconst_4
    //   6745: iaload
    //   6746: bipush #11
    //   6748: iushr
    //   6749: aload #20
    //   6751: iconst_4
    //   6752: iaload
    //   6753: bipush #21
    //   6755: ishl
    //   6756: ior
    //   6757: ixor
    //   6758: aload #20
    //   6760: iconst_4
    //   6761: iaload
    //   6762: bipush #25
    //   6764: iushr
    //   6765: aload #20
    //   6767: iconst_4
    //   6768: iaload
    //   6769: bipush #7
    //   6771: ishl
    //   6772: ior
    //   6773: ixor
    //   6774: iadd
    //   6775: aload #20
    //   6777: bipush #6
    //   6779: iaload
    //   6780: aload #20
    //   6782: iconst_4
    //   6783: iaload
    //   6784: aload #20
    //   6786: iconst_5
    //   6787: iaload
    //   6788: aload #20
    //   6790: bipush #6
    //   6792: iaload
    //   6793: ixor
    //   6794: iand
    //   6795: ixor
    //   6796: iadd
    //   6797: aload #6
    //   6799: iload #21
    //   6801: iaload
    //   6802: iadd
    //   6803: aload #19
    //   6805: iload #21
    //   6807: iaload
    //   6808: iadd
    //   6809: istore #22
    //   6811: aload #20
    //   6813: iconst_0
    //   6814: iaload
    //   6815: iconst_2
    //   6816: iushr
    //   6817: aload #20
    //   6819: iconst_0
    //   6820: iaload
    //   6821: bipush #30
    //   6823: ishl
    //   6824: ior
    //   6825: aload #20
    //   6827: iconst_0
    //   6828: iaload
    //   6829: bipush #13
    //   6831: iushr
    //   6832: aload #20
    //   6834: iconst_0
    //   6835: iaload
    //   6836: bipush #19
    //   6838: ishl
    //   6839: ior
    //   6840: ixor
    //   6841: aload #20
    //   6843: iconst_0
    //   6844: iaload
    //   6845: bipush #22
    //   6847: iushr
    //   6848: aload #20
    //   6850: iconst_0
    //   6851: iaload
    //   6852: bipush #10
    //   6854: ishl
    //   6855: ior
    //   6856: ixor
    //   6857: aload #20
    //   6859: iconst_0
    //   6860: iaload
    //   6861: aload #20
    //   6863: iconst_1
    //   6864: iaload
    //   6865: iand
    //   6866: aload #20
    //   6868: iconst_2
    //   6869: iaload
    //   6870: aload #20
    //   6872: iconst_0
    //   6873: iaload
    //   6874: aload #20
    //   6876: iconst_1
    //   6877: iaload
    //   6878: ior
    //   6879: iand
    //   6880: ior
    //   6881: iadd
    //   6882: istore #23
    //   6884: aload #20
    //   6886: iconst_3
    //   6887: dup2
    //   6888: iaload
    //   6889: iload #22
    //   6891: iadd
    //   6892: iastore
    //   6893: aload #20
    //   6895: bipush #7
    //   6897: iload #22
    //   6899: iload #23
    //   6901: iadd
    //   6902: iastore
    //   6903: aload #20
    //   6905: bipush #7
    //   6907: iaload
    //   6908: istore #22
    //   6910: aload #20
    //   6912: bipush #7
    //   6914: aload #20
    //   6916: bipush #6
    //   6918: iaload
    //   6919: iastore
    //   6920: aload #20
    //   6922: bipush #6
    //   6924: aload #20
    //   6926: iconst_5
    //   6927: iaload
    //   6928: iastore
    //   6929: aload #20
    //   6931: iconst_5
    //   6932: aload #20
    //   6934: iconst_4
    //   6935: iaload
    //   6936: iastore
    //   6937: aload #20
    //   6939: iconst_4
    //   6940: aload #20
    //   6942: iconst_3
    //   6943: iaload
    //   6944: iastore
    //   6945: aload #20
    //   6947: iconst_3
    //   6948: aload #20
    //   6950: iconst_2
    //   6951: iaload
    //   6952: iastore
    //   6953: aload #20
    //   6955: iconst_2
    //   6956: aload #20
    //   6958: iconst_1
    //   6959: iaload
    //   6960: iastore
    //   6961: aload #20
    //   6963: iconst_1
    //   6964: aload #20
    //   6966: iconst_0
    //   6967: iaload
    //   6968: iastore
    //   6969: aload #20
    //   6971: iconst_0
    //   6972: iload #22
    //   6974: iastore
    //   6975: iinc #21, 1
    //   6978: iload_2
    //   6979: ifne -> 6487
    //   6982: iconst_0
    //   6983: istore #21
    //   6985: iload #21
    //   6987: bipush #8
    //   6989: if_icmpge -> 7012
    //   6992: aload #8
    //   6994: iload #21
    //   6996: dup2
    //   6997: iaload
    //   6998: aload #20
    //   7000: iload #21
    //   7002: iaload
    //   7003: iadd
    //   7004: iastore
    //   7005: iinc #21, 1
    //   7008: iload_2
    //   7009: ifne -> 6985
    //   7012: iload #13
    //   7014: iload #18
    //   7016: iadd
    //   7017: istore #13
    //   7019: iload #17
    //   7021: iload #18
    //   7023: isub
    //   7024: istore #17
    //   7026: iconst_0
    //   7027: istore #12
    //   7029: iload #17
    //   7031: bipush #64
    //   7033: if_icmplt -> 7643
    //   7036: iconst_0
    //   7037: istore #19
    //   7039: iload #19
    //   7041: bipush #64
    //   7043: if_icmpge -> 7066
    //   7046: aload #10
    //   7048: iload #19
    //   7050: aload #5
    //   7052: iload #13
    //   7054: iload #19
    //   7056: iadd
    //   7057: baload
    //   7058: bastore
    //   7059: iinc #19, 1
    //   7062: iload_2
    //   7063: ifne -> 7039
    //   7066: bipush #64
    //   7068: newarray int
    //   7070: astore #19
    //   7072: bipush #8
    //   7074: newarray int
    //   7076: astore #20
    //   7078: iconst_0
    //   7079: istore #21
    //   7081: iload #21
    //   7083: bipush #8
    //   7085: if_icmpge -> 7105
    //   7088: aload #20
    //   7090: iload #21
    //   7092: aload #8
    //   7094: iload #21
    //   7096: iaload
    //   7097: iastore
    //   7098: iinc #21, 1
    //   7101: iload_2
    //   7102: ifne -> 7081
    //   7105: iconst_0
    //   7106: istore #21
    //   7108: iload #21
    //   7110: bipush #64
    //   7112: if_icmpge -> 7603
    //   7115: iload #21
    //   7117: bipush #16
    //   7119: if_icmpge -> 7200
    //   7122: aload #19
    //   7124: iload #21
    //   7126: aload #10
    //   7128: iconst_4
    //   7129: iload #21
    //   7131: imul
    //   7132: baload
    //   7133: sipush #255
    //   7136: iand
    //   7137: bipush #24
    //   7139: ishl
    //   7140: aload #10
    //   7142: iconst_4
    //   7143: iload #21
    //   7145: imul
    //   7146: iconst_1
    //   7147: iadd
    //   7148: baload
    //   7149: sipush #255
    //   7152: iand
    //   7153: bipush #16
    //   7155: ishl
    //   7156: ior
    //   7157: aload #10
    //   7159: iconst_4
    //   7160: iload #21
    //   7162: imul
    //   7163: iconst_2
    //   7164: iadd
    //   7165: baload
    //   7166: sipush #255
    //   7169: iand
    //   7170: bipush #8
    //   7172: ishl
    //   7173: ior
    //   7174: aload #10
    //   7176: iconst_4
    //   7177: iload #21
    //   7179: imul
    //   7180: iconst_3
    //   7181: iadd
    //   7182: baload
    //   7183: sipush #255
    //   7186: iand
    //   7187: ior
    //   7188: iastore
    //   7189: iload_2
    //   7190: ifne -> 7343
    //   7193: goto -> 7200
    //   7196: invokestatic a : (Ljava/lang/Throwable;)Ljava/lang/Throwable;
    //   7199: athrow
    //   7200: aload #19
    //   7202: iload #21
    //   7204: aload #19
    //   7206: iload #21
    //   7208: iconst_2
    //   7209: isub
    //   7210: iaload
    //   7211: bipush #17
    //   7213: iushr
    //   7214: aload #19
    //   7216: iload #21
    //   7218: iconst_2
    //   7219: isub
    //   7220: iaload
    //   7221: bipush #15
    //   7223: ishl
    //   7224: ior
    //   7225: aload #19
    //   7227: iload #21
    //   7229: iconst_2
    //   7230: isub
    //   7231: iaload
    //   7232: bipush #19
    //   7234: iushr
    //   7235: aload #19
    //   7237: iload #21
    //   7239: iconst_2
    //   7240: isub
    //   7241: iaload
    //   7242: bipush #13
    //   7244: ishl
    //   7245: ior
    //   7246: ixor
    //   7247: aload #19
    //   7249: iload #21
    //   7251: iconst_2
    //   7252: isub
    //   7253: iaload
    //   7254: bipush #10
    //   7256: iushr
    //   7257: ixor
    //   7258: aload #19
    //   7260: iload #21
    //   7262: bipush #7
    //   7264: isub
    //   7265: iaload
    //   7266: iadd
    //   7267: aload #19
    //   7269: iload #21
    //   7271: bipush #15
    //   7273: isub
    //   7274: iaload
    //   7275: bipush #7
    //   7277: iushr
    //   7278: aload #19
    //   7280: iload #21
    //   7282: bipush #15
    //   7284: isub
    //   7285: iaload
    //   7286: bipush #25
    //   7288: ishl
    //   7289: ior
    //   7290: aload #19
    //   7292: iload #21
    //   7294: bipush #15
    //   7296: isub
    //   7297: iaload
    //   7298: bipush #18
    //   7300: iushr
    //   7301: aload #19
    //   7303: iload #21
    //   7305: bipush #15
    //   7307: isub
    //   7308: iaload
    //   7309: bipush #14
    //   7311: ishl
    //   7312: ior
    //   7313: ixor
    //   7314: aload #19
    //   7316: iload #21
    //   7318: bipush #15
    //   7320: isub
    //   7321: iaload
    //   7322: iconst_3
    //   7323: iushr
    //   7324: ixor
    //   7325: iadd
    //   7326: aload #19
    //   7328: iload #21
    //   7330: bipush #16
    //   7332: isub
    //   7333: iaload
    //   7334: iadd
    //   7335: iastore
    //   7336: goto -> 7343
    //   7339: invokestatic a : (Ljava/lang/Throwable;)Ljava/lang/Throwable;
    //   7342: athrow
    //   7343: aload #20
    //   7345: bipush #7
    //   7347: iaload
    //   7348: aload #20
    //   7350: iconst_4
    //   7351: iaload
    //   7352: bipush #6
    //   7354: iushr
    //   7355: aload #20
    //   7357: iconst_4
    //   7358: iaload
    //   7359: bipush #26
    //   7361: ishl
    //   7362: ior
    //   7363: aload #20
    //   7365: iconst_4
    //   7366: iaload
    //   7367: bipush #11
    //   7369: iushr
    //   7370: aload #20
    //   7372: iconst_4
    //   7373: iaload
    //   7374: bipush #21
    //   7376: ishl
    //   7377: ior
    //   7378: ixor
    //   7379: aload #20
    //   7381: iconst_4
    //   7382: iaload
    //   7383: bipush #25
    //   7385: iushr
    //   7386: aload #20
    //   7388: iconst_4
    //   7389: iaload
    //   7390: bipush #7
    //   7392: ishl
    //   7393: ior
    //   7394: ixor
    //   7395: iadd
    //   7396: aload #20
    //   7398: bipush #6
    //   7400: iaload
    //   7401: aload #20
    //   7403: iconst_4
    //   7404: iaload
    //   7405: aload #20
    //   7407: iconst_5
    //   7408: iaload
    //   7409: aload #20
    //   7411: bipush #6
    //   7413: iaload
    //   7414: ixor
    //   7415: iand
    //   7416: ixor
    //   7417: iadd
    //   7418: aload #6
    //   7420: iload #21
    //   7422: iaload
    //   7423: iadd
    //   7424: aload #19
    //   7426: iload #21
    //   7428: iaload
    //   7429: iadd
    //   7430: istore #22
    //   7432: aload #20
    //   7434: iconst_0
    //   7435: iaload
    //   7436: iconst_2
    //   7437: iushr
    //   7438: aload #20
    //   7440: iconst_0
    //   7441: iaload
    //   7442: bipush #30
    //   7444: ishl
    //   7445: ior
    //   7446: aload #20
    //   7448: iconst_0
    //   7449: iaload
    //   7450: bipush #13
    //   7452: iushr
    //   7453: aload #20
    //   7455: iconst_0
    //   7456: iaload
    //   7457: bipush #19
    //   7459: ishl
    //   7460: ior
    //   7461: ixor
    //   7462: aload #20
    //   7464: iconst_0
    //   7465: iaload
    //   7466: bipush #22
    //   7468: iushr
    //   7469: aload #20
    //   7471: iconst_0
    //   7472: iaload
    //   7473: bipush #10
    //   7475: ishl
    //   7476: ior
    //   7477: ixor
    //   7478: aload #20
    //   7480: iconst_0
    //   7481: iaload
    //   7482: aload #20
    //   7484: iconst_1
    //   7485: iaload
    //   7486: iand
    //   7487: aload #20
    //   7489: iconst_2
    //   7490: iaload
    //   7491: aload #20
    //   7493: iconst_0
    //   7494: iaload
    //   7495: aload #20
    //   7497: iconst_1
    //   7498: iaload
    //   7499: ior
    //   7500: iand
    //   7501: ior
    //   7502: iadd
    //   7503: istore #23
    //   7505: aload #20
    //   7507: iconst_3
    //   7508: dup2
    //   7509: iaload
    //   7510: iload #22
    //   7512: iadd
    //   7513: iastore
    //   7514: aload #20
    //   7516: bipush #7
    //   7518: iload #22
    //   7520: iload #23
    //   7522: iadd
    //   7523: iastore
    //   7524: aload #20
    //   7526: bipush #7
    //   7528: iaload
    //   7529: istore #22
    //   7531: aload #20
    //   7533: bipush #7
    //   7535: aload #20
    //   7537: bipush #6
    //   7539: iaload
    //   7540: iastore
    //   7541: aload #20
    //   7543: bipush #6
    //   7545: aload #20
    //   7547: iconst_5
    //   7548: iaload
    //   7549: iastore
    //   7550: aload #20
    //   7552: iconst_5
    //   7553: aload #20
    //   7555: iconst_4
    //   7556: iaload
    //   7557: iastore
    //   7558: aload #20
    //   7560: iconst_4
    //   7561: aload #20
    //   7563: iconst_3
    //   7564: iaload
    //   7565: iastore
    //   7566: aload #20
    //   7568: iconst_3
    //   7569: aload #20
    //   7571: iconst_2
    //   7572: iaload
    //   7573: iastore
    //   7574: aload #20
    //   7576: iconst_2
    //   7577: aload #20
    //   7579: iconst_1
    //   7580: iaload
    //   7581: iastore
    //   7582: aload #20
    //   7584: iconst_1
    //   7585: aload #20
    //   7587: iconst_0
    //   7588: iaload
    //   7589: iastore
    //   7590: aload #20
    //   7592: iconst_0
    //   7593: iload #22
    //   7595: iastore
    //   7596: iinc #21, 1
    //   7599: iload_2
    //   7600: ifne -> 7108
    //   7603: iconst_0
    //   7604: istore #21
    //   7606: iload #21
    //   7608: bipush #8
    //   7610: if_icmpge -> 7633
    //   7613: aload #8
    //   7615: iload #21
    //   7617: dup2
    //   7618: iaload
    //   7619: aload #20
    //   7621: iload #21
    //   7623: iaload
    //   7624: iadd
    //   7625: iastore
    //   7626: iinc #21, 1
    //   7629: iload_2
    //   7630: ifne -> 7606
    //   7633: iinc #13, 64
    //   7636: iinc #17, -64
    //   7639: iload_2
    //   7640: ifne -> 7029
    //   7643: iload #17
    //   7645: ifle -> 7681
    //   7648: iconst_0
    //   7649: istore #19
    //   7651: iload #19
    //   7653: iload #17
    //   7655: if_icmpge -> 7681
    //   7658: aload #9
    //   7660: iload #12
    //   7662: iload #19
    //   7664: iadd
    //   7665: aload #5
    //   7667: iload #13
    //   7669: iload #19
    //   7671: iadd
    //   7672: baload
    //   7673: bastore
    //   7674: iinc #19, 1
    //   7677: iload_2
    //   7678: ifne -> 7651
    //   7681: bipush #8
    //   7683: newarray byte
    //   7685: astore #19
    //   7687: aload #19
    //   7689: iconst_0
    //   7690: iload #14
    //   7692: bipush #24
    //   7694: iushr
    //   7695: i2b
    //   7696: bastore
    //   7697: aload #19
    //   7699: iconst_1
    //   7700: iload #14
    //   7702: bipush #16
    //   7704: iushr
    //   7705: i2b
    //   7706: bastore
    //   7707: aload #19
    //   7709: iconst_2
    //   7710: iload #14
    //   7712: bipush #8
    //   7714: iushr
    //   7715: i2b
    //   7716: bastore
    //   7717: aload #19
    //   7719: iconst_3
    //   7720: iload #14
    //   7722: i2b
    //   7723: bastore
    //   7724: aload #19
    //   7726: iconst_4
    //   7727: iload #15
    //   7729: bipush #24
    //   7731: iushr
    //   7732: i2b
    //   7733: bastore
    //   7734: aload #19
    //   7736: iconst_5
    //   7737: iload #15
    //   7739: bipush #16
    //   7741: iushr
    //   7742: i2b
    //   7743: bastore
    //   7744: aload #19
    //   7746: bipush #6
    //   7748: iload #15
    //   7750: bipush #8
    //   7752: iushr
    //   7753: i2b
    //   7754: bastore
    //   7755: aload #19
    //   7757: bipush #7
    //   7759: iload #15
    //   7761: i2b
    //   7762: bastore
    //   7763: bipush #8
    //   7765: istore #11
    //   7767: aload #7
    //   7769: iconst_0
    //   7770: iaload
    //   7771: bipush #63
    //   7773: iand
    //   7774: istore #12
    //   7776: bipush #64
    //   7778: iload #12
    //   7780: isub
    //   7781: istore #18
    //   7783: aload #7
    //   7785: iconst_0
    //   7786: dup2
    //   7787: iaload
    //   7788: iload #11
    //   7790: iadd
    //   7791: iastore
    //   7792: aload #7
    //   7794: iconst_0
    //   7795: dup2
    //   7796: iaload
    //   7797: iconst_m1
    //   7798: iand
    //   7799: iastore
    //   7800: aload #7
    //   7802: iconst_0
    //   7803: iaload
    //   7804: iload #11
    //   7806: if_icmpge -> 7824
    //   7809: aload #7
    //   7811: iconst_1
    //   7812: dup2
    //   7813: iaload
    //   7814: iconst_1
    //   7815: iadd
    //   7816: iastore
    //   7817: goto -> 7824
    //   7820: invokestatic a : (Ljava/lang/Throwable;)Ljava/lang/Throwable;
    //   7823: athrow
    //   7824: iload #12
    //   7826: ifle -> 8440
    //   7829: iload #11
    //   7831: iload #18
    //   7833: if_icmplt -> 8440
    //   7836: goto -> 7843
    //   7839: invokestatic a : (Ljava/lang/Throwable;)Ljava/lang/Throwable;
    //   7842: athrow
    //   7843: iconst_0
    //   7844: istore #20
    //   7846: iload #20
    //   7848: iload #18
    //   7850: if_icmpge -> 7873
    //   7853: aload #9
    //   7855: iload #12
    //   7857: iload #20
    //   7859: iadd
    //   7860: aload #19
    //   7862: iload #20
    //   7864: baload
    //   7865: bastore
    //   7866: iinc #20, 1
    //   7869: iload_2
    //   7870: ifne -> 7846
    //   7873: bipush #64
    //   7875: newarray int
    //   7877: astore #20
    //   7879: bipush #8
    //   7881: newarray int
    //   7883: astore #21
    //   7885: iconst_0
    //   7886: istore #22
    //   7888: iload #22
    //   7890: bipush #8
    //   7892: if_icmpge -> 7912
    //   7895: aload #21
    //   7897: iload #22
    //   7899: aload #8
    //   7901: iload #22
    //   7903: iaload
    //   7904: iastore
    //   7905: iinc #22, 1
    //   7908: iload_2
    //   7909: ifne -> 7888
    //   7912: iconst_0
    //   7913: istore #22
    //   7915: iload #22
    //   7917: bipush #64
    //   7919: if_icmpge -> 8410
    //   7922: iload #22
    //   7924: bipush #16
    //   7926: if_icmpge -> 8007
    //   7929: aload #20
    //   7931: iload #22
    //   7933: aload #9
    //   7935: iconst_4
    //   7936: iload #22
    //   7938: imul
    //   7939: baload
    //   7940: sipush #255
    //   7943: iand
    //   7944: bipush #24
    //   7946: ishl
    //   7947: aload #9
    //   7949: iconst_4
    //   7950: iload #22
    //   7952: imul
    //   7953: iconst_1
    //   7954: iadd
    //   7955: baload
    //   7956: sipush #255
    //   7959: iand
    //   7960: bipush #16
    //   7962: ishl
    //   7963: ior
    //   7964: aload #9
    //   7966: iconst_4
    //   7967: iload #22
    //   7969: imul
    //   7970: iconst_2
    //   7971: iadd
    //   7972: baload
    //   7973: sipush #255
    //   7976: iand
    //   7977: bipush #8
    //   7979: ishl
    //   7980: ior
    //   7981: aload #9
    //   7983: iconst_4
    //   7984: iload #22
    //   7986: imul
    //   7987: iconst_3
    //   7988: iadd
    //   7989: baload
    //   7990: sipush #255
    //   7993: iand
    //   7994: ior
    //   7995: iastore
    //   7996: iload_2
    //   7997: ifne -> 8150
    //   8000: goto -> 8007
    //   8003: invokestatic a : (Ljava/lang/Throwable;)Ljava/lang/Throwable;
    //   8006: athrow
    //   8007: aload #20
    //   8009: iload #22
    //   8011: aload #20
    //   8013: iload #22
    //   8015: iconst_2
    //   8016: isub
    //   8017: iaload
    //   8018: bipush #17
    //   8020: iushr
    //   8021: aload #20
    //   8023: iload #22
    //   8025: iconst_2
    //   8026: isub
    //   8027: iaload
    //   8028: bipush #15
    //   8030: ishl
    //   8031: ior
    //   8032: aload #20
    //   8034: iload #22
    //   8036: iconst_2
    //   8037: isub
    //   8038: iaload
    //   8039: bipush #19
    //   8041: iushr
    //   8042: aload #20
    //   8044: iload #22
    //   8046: iconst_2
    //   8047: isub
    //   8048: iaload
    //   8049: bipush #13
    //   8051: ishl
    //   8052: ior
    //   8053: ixor
    //   8054: aload #20
    //   8056: iload #22
    //   8058: iconst_2
    //   8059: isub
    //   8060: iaload
    //   8061: bipush #10
    //   8063: iushr
    //   8064: ixor
    //   8065: aload #20
    //   8067: iload #22
    //   8069: bipush #7
    //   8071: isub
    //   8072: iaload
    //   8073: iadd
    //   8074: aload #20
    //   8076: iload #22
    //   8078: bipush #15
    //   8080: isub
    //   8081: iaload
    //   8082: bipush #7
    //   8084: iushr
    //   8085: aload #20
    //   8087: iload #22
    //   8089: bipush #15
    //   8091: isub
    //   8092: iaload
    //   8093: bipush #25
    //   8095: ishl
    //   8096: ior
    //   8097: aload #20
    //   8099: iload #22
    //   8101: bipush #15
    //   8103: isub
    //   8104: iaload
    //   8105: bipush #18
    //   8107: iushr
    //   8108: aload #20
    //   8110: iload #22
    //   8112: bipush #15
    //   8114: isub
    //   8115: iaload
    //   8116: bipush #14
    //   8118: ishl
    //   8119: ior
    //   8120: ixor
    //   8121: aload #20
    //   8123: iload #22
    //   8125: bipush #15
    //   8127: isub
    //   8128: iaload
    //   8129: iconst_3
    //   8130: iushr
    //   8131: ixor
    //   8132: iadd
    //   8133: aload #20
    //   8135: iload #22
    //   8137: bipush #16
    //   8139: isub
    //   8140: iaload
    //   8141: iadd
    //   8142: iastore
    //   8143: goto -> 8150
    //   8146: invokestatic a : (Ljava/lang/Throwable;)Ljava/lang/Throwable;
    //   8149: athrow
    //   8150: aload #21
    //   8152: bipush #7
    //   8154: iaload
    //   8155: aload #21
    //   8157: iconst_4
    //   8158: iaload
    //   8159: bipush #6
    //   8161: iushr
    //   8162: aload #21
    //   8164: iconst_4
    //   8165: iaload
    //   8166: bipush #26
    //   8168: ishl
    //   8169: ior
    //   8170: aload #21
    //   8172: iconst_4
    //   8173: iaload
    //   8174: bipush #11
    //   8176: iushr
    //   8177: aload #21
    //   8179: iconst_4
    //   8180: iaload
    //   8181: bipush #21
    //   8183: ishl
    //   8184: ior
    //   8185: ixor
    //   8186: aload #21
    //   8188: iconst_4
    //   8189: iaload
    //   8190: bipush #25
    //   8192: iushr
    //   8193: aload #21
    //   8195: iconst_4
    //   8196: iaload
    //   8197: bipush #7
    //   8199: ishl
    //   8200: ior
    //   8201: ixor
    //   8202: iadd
    //   8203: aload #21
    //   8205: bipush #6
    //   8207: iaload
    //   8208: aload #21
    //   8210: iconst_4
    //   8211: iaload
    //   8212: aload #21
    //   8214: iconst_5
    //   8215: iaload
    //   8216: aload #21
    //   8218: bipush #6
    //   8220: iaload
    //   8221: ixor
    //   8222: iand
    //   8223: ixor
    //   8224: iadd
    //   8225: aload #6
    //   8227: iload #22
    //   8229: iaload
    //   8230: iadd
    //   8231: aload #20
    //   8233: iload #22
    //   8235: iaload
    //   8236: iadd
    //   8237: istore #23
    //   8239: aload #21
    //   8241: iconst_0
    //   8242: iaload
    //   8243: iconst_2
    //   8244: iushr
    //   8245: aload #21
    //   8247: iconst_0
    //   8248: iaload
    //   8249: bipush #30
    //   8251: ishl
    //   8252: ior
    //   8253: aload #21
    //   8255: iconst_0
    //   8256: iaload
    //   8257: bipush #13
    //   8259: iushr
    //   8260: aload #21
    //   8262: iconst_0
    //   8263: iaload
    //   8264: bipush #19
    //   8266: ishl
    //   8267: ior
    //   8268: ixor
    //   8269: aload #21
    //   8271: iconst_0
    //   8272: iaload
    //   8273: bipush #22
    //   8275: iushr
    //   8276: aload #21
    //   8278: iconst_0
    //   8279: iaload
    //   8280: bipush #10
    //   8282: ishl
    //   8283: ior
    //   8284: ixor
    //   8285: aload #21
    //   8287: iconst_0
    //   8288: iaload
    //   8289: aload #21
    //   8291: iconst_1
    //   8292: iaload
    //   8293: iand
    //   8294: aload #21
    //   8296: iconst_2
    //   8297: iaload
    //   8298: aload #21
    //   8300: iconst_0
    //   8301: iaload
    //   8302: aload #21
    //   8304: iconst_1
    //   8305: iaload
    //   8306: ior
    //   8307: iand
    //   8308: ior
    //   8309: iadd
    //   8310: istore #24
    //   8312: aload #21
    //   8314: iconst_3
    //   8315: dup2
    //   8316: iaload
    //   8317: iload #23
    //   8319: iadd
    //   8320: iastore
    //   8321: aload #21
    //   8323: bipush #7
    //   8325: iload #23
    //   8327: iload #24
    //   8329: iadd
    //   8330: iastore
    //   8331: aload #21
    //   8333: bipush #7
    //   8335: iaload
    //   8336: istore #23
    //   8338: aload #21
    //   8340: bipush #7
    //   8342: aload #21
    //   8344: bipush #6
    //   8346: iaload
    //   8347: iastore
    //   8348: aload #21
    //   8350: bipush #6
    //   8352: aload #21
    //   8354: iconst_5
    //   8355: iaload
    //   8356: iastore
    //   8357: aload #21
    //   8359: iconst_5
    //   8360: aload #21
    //   8362: iconst_4
    //   8363: iaload
    //   8364: iastore
    //   8365: aload #21
    //   8367: iconst_4
    //   8368: aload #21
    //   8370: iconst_3
    //   8371: iaload
    //   8372: iastore
    //   8373: aload #21
    //   8375: iconst_3
    //   8376: aload #21
    //   8378: iconst_2
    //   8379: iaload
    //   8380: iastore
    //   8381: aload #21
    //   8383: iconst_2
    //   8384: aload #21
    //   8386: iconst_1
    //   8387: iaload
    //   8388: iastore
    //   8389: aload #21
    //   8391: iconst_1
    //   8392: aload #21
    //   8394: iconst_0
    //   8395: iaload
    //   8396: iastore
    //   8397: aload #21
    //   8399: iconst_0
    //   8400: iload #23
    //   8402: iastore
    //   8403: iinc #22, 1
    //   8406: iload_2
    //   8407: ifne -> 7915
    //   8410: iconst_0
    //   8411: istore #22
    //   8413: iload #22
    //   8415: bipush #8
    //   8417: if_icmpge -> 8440
    //   8420: aload #8
    //   8422: iload #22
    //   8424: dup2
    //   8425: iaload
    //   8426: aload #21
    //   8428: iload #22
    //   8430: iaload
    //   8431: iadd
    //   8432: iastore
    //   8433: iinc #22, 1
    //   8436: iload_2
    //   8437: ifne -> 8413
    //   8440: bipush #32
    //   8442: newarray byte
    //   8444: astore #4
    //   8446: sipush #30129
    //   8449: aload #4
    //   8451: iconst_0
    //   8452: aload #8
    //   8454: iconst_0
    //   8455: iaload
    //   8456: bipush #24
    //   8458: iushr
    //   8459: i2b
    //   8460: bastore
    //   8461: sipush #314
    //   8464: aload #4
    //   8466: iconst_1
    //   8467: aload #8
    //   8469: iconst_0
    //   8470: iaload
    //   8471: bipush #16
    //   8473: iushr
    //   8474: i2b
    //   8475: bastore
    //   8476: aload #4
    //   8478: iconst_2
    //   8479: aload #8
    //   8481: iconst_0
    //   8482: iaload
    //   8483: bipush #8
    //   8485: iushr
    //   8486: i2b
    //   8487: bastore
    //   8488: aload #4
    //   8490: iconst_3
    //   8491: aload #8
    //   8493: iconst_0
    //   8494: iaload
    //   8495: i2b
    //   8496: bastore
    //   8497: aload #4
    //   8499: iconst_4
    //   8500: aload #8
    //   8502: iconst_1
    //   8503: iaload
    //   8504: bipush #24
    //   8506: iushr
    //   8507: i2b
    //   8508: bastore
    //   8509: aload #4
    //   8511: iconst_5
    //   8512: aload #8
    //   8514: iconst_1
    //   8515: iaload
    //   8516: bipush #16
    //   8518: iushr
    //   8519: i2b
    //   8520: bastore
    //   8521: aload #4
    //   8523: bipush #6
    //   8525: aload #8
    //   8527: iconst_1
    //   8528: iaload
    //   8529: bipush #8
    //   8531: iushr
    //   8532: i2b
    //   8533: bastore
    //   8534: aload #4
    //   8536: bipush #7
    //   8538: aload #8
    //   8540: iconst_1
    //   8541: iaload
    //   8542: i2b
    //   8543: bastore
    //   8544: aload #4
    //   8546: bipush #8
    //   8548: aload #8
    //   8550: iconst_2
    //   8551: iaload
    //   8552: bipush #24
    //   8554: iushr
    //   8555: i2b
    //   8556: bastore
    //   8557: aload #4
    //   8559: bipush #9
    //   8561: aload #8
    //   8563: iconst_2
    //   8564: iaload
    //   8565: bipush #16
    //   8567: iushr
    //   8568: i2b
    //   8569: bastore
    //   8570: aload #4
    //   8572: bipush #10
    //   8574: aload #8
    //   8576: iconst_2
    //   8577: iaload
    //   8578: bipush #8
    //   8580: iushr
    //   8581: i2b
    //   8582: bastore
    //   8583: aload #4
    //   8585: bipush #11
    //   8587: aload #8
    //   8589: iconst_2
    //   8590: iaload
    //   8591: i2b
    //   8592: bastore
    //   8593: aload #4
    //   8595: bipush #12
    //   8597: aload #8
    //   8599: iconst_3
    //   8600: iaload
    //   8601: bipush #24
    //   8603: iushr
    //   8604: i2b
    //   8605: bastore
    //   8606: aload #4
    //   8608: bipush #13
    //   8610: aload #8
    //   8612: iconst_3
    //   8613: iaload
    //   8614: bipush #16
    //   8616: iushr
    //   8617: i2b
    //   8618: bastore
    //   8619: aload #4
    //   8621: bipush #14
    //   8623: aload #8
    //   8625: iconst_3
    //   8626: iaload
    //   8627: bipush #8
    //   8629: iushr
    //   8630: i2b
    //   8631: bastore
    //   8632: aload #4
    //   8634: bipush #15
    //   8636: aload #8
    //   8638: iconst_3
    //   8639: iaload
    //   8640: i2b
    //   8641: bastore
    //   8642: aload #4
    //   8644: bipush #16
    //   8646: aload #8
    //   8648: iconst_4
    //   8649: iaload
    //   8650: bipush #24
    //   8652: iushr
    //   8653: i2b
    //   8654: bastore
    //   8655: aload #4
    //   8657: bipush #17
    //   8659: aload #8
    //   8661: iconst_4
    //   8662: iaload
    //   8663: bipush #16
    //   8665: iushr
    //   8666: i2b
    //   8667: bastore
    //   8668: aload #4
    //   8670: bipush #18
    //   8672: aload #8
    //   8674: iconst_4
    //   8675: iaload
    //   8676: bipush #8
    //   8678: iushr
    //   8679: i2b
    //   8680: bastore
    //   8681: aload #4
    //   8683: bipush #19
    //   8685: aload #8
    //   8687: iconst_4
    //   8688: iaload
    //   8689: i2b
    //   8690: bastore
    //   8691: aload #4
    //   8693: bipush #20
    //   8695: aload #8
    //   8697: iconst_5
    //   8698: iaload
    //   8699: bipush #24
    //   8701: iushr
    //   8702: i2b
    //   8703: bastore
    //   8704: aload #4
    //   8706: bipush #21
    //   8708: aload #8
    //   8710: iconst_5
    //   8711: iaload
    //   8712: bipush #16
    //   8714: iushr
    //   8715: i2b
    //   8716: bastore
    //   8717: aload #4
    //   8719: bipush #22
    //   8721: aload #8
    //   8723: iconst_5
    //   8724: iaload
    //   8725: bipush #8
    //   8727: iushr
    //   8728: i2b
    //   8729: bastore
    //   8730: aload #4
    //   8732: bipush #23
    //   8734: aload #8
    //   8736: iconst_5
    //   8737: iaload
    //   8738: i2b
    //   8739: bastore
    //   8740: aload #4
    //   8742: bipush #24
    //   8744: aload #8
    //   8746: bipush #6
    //   8748: iaload
    //   8749: bipush #24
    //   8751: iushr
    //   8752: i2b
    //   8753: bastore
    //   8754: aload #4
    //   8756: bipush #25
    //   8758: aload #8
    //   8760: bipush #6
    //   8762: iaload
    //   8763: bipush #16
    //   8765: iushr
    //   8766: i2b
    //   8767: bastore
    //   8768: aload #4
    //   8770: bipush #26
    //   8772: aload #8
    //   8774: bipush #6
    //   8776: iaload
    //   8777: bipush #8
    //   8779: iushr
    //   8780: i2b
    //   8781: bastore
    //   8782: aload #4
    //   8784: bipush #27
    //   8786: aload #8
    //   8788: bipush #6
    //   8790: iaload
    //   8791: i2b
    //   8792: bastore
    //   8793: aload #4
    //   8795: bipush #28
    //   8797: aload #8
    //   8799: bipush #7
    //   8801: iaload
    //   8802: bipush #24
    //   8804: iushr
    //   8805: i2b
    //   8806: bastore
    //   8807: aload #4
    //   8809: bipush #29
    //   8811: aload #8
    //   8813: bipush #7
    //   8815: iaload
    //   8816: bipush #16
    //   8818: iushr
    //   8819: i2b
    //   8820: bastore
    //   8821: aload #4
    //   8823: bipush #30
    //   8825: aload #8
    //   8827: bipush #7
    //   8829: iaload
    //   8830: bipush #8
    //   8832: iushr
    //   8833: i2b
    //   8834: bastore
    //   8835: aload #4
    //   8837: bipush #31
    //   8839: aload #8
    //   8841: bipush #7
    //   8843: iaload
    //   8844: i2b
    //   8845: bastore
    //   8846: new java/math/BigInteger
    //   8849: dup
    //   8850: aload #4
    //   8852: invokespecial <init> : ([B)V
    //   8855: invokevirtual abs : ()Ljava/math/BigInteger;
    //   8858: putstatic burp/Zshq.ZK : Ljava/lang/Object;
    //   8861: invokestatic a : (II)Ljava/lang/String;
    //   8864: iconst_1
    //   8865: ldc burp/Ztdd
    //   8867: invokevirtual getClassLoader : ()Ljava/lang/ClassLoader;
    //   8870: invokestatic forName : (Ljava/lang/String;ZLjava/lang/ClassLoader;)Ljava/lang/Class;
    //   8873: invokevirtual getDeclaredFields : ()[Ljava/lang/reflect/Field;
    //   8876: astore_3
    //   8877: aload_3
    //   8878: arraylength
    //   8879: istore #4
    //   8881: iconst_0
    //   8882: istore #5
    //   8884: iload #5
    //   8886: iload #4
    //   8888: if_icmpge -> 9025
    //   8891: aload_3
    //   8892: iload #5
    //   8894: aaload
    //   8895: astore #6
    //   8897: aload #6
    //   8899: invokevirtual getModifiers : ()I
    //   8902: invokestatic isStatic : (I)Z
    //   8905: ifne -> 8915
    //   8908: goto -> 9018
    //   8911: invokestatic a : (Ljava/lang/Throwable;)Ljava/lang/Throwable;
    //   8914: athrow
    //   8915: aload #6
    //   8917: invokevirtual getType : ()Ljava/lang/Class;
    //   8920: astore #7
    //   8922: aload #7
    //   8924: ifnull -> 9005
    //   8927: aload #7
    //   8929: invokevirtual isPrimitive : ()Z
    //   8932: ifne -> 9005
    //   8935: goto -> 8942
    //   8938: invokestatic a : (Ljava/lang/Throwable;)Ljava/lang/Throwable;
    //   8941: athrow
    //   8942: aload #7
    //   8944: invokevirtual getPackage : ()Ljava/lang/Package;
    //   8947: ifnull -> 9005
    //   8950: goto -> 8957
    //   8953: invokestatic a : (Ljava/lang/Throwable;)Ljava/lang/Throwable;
    //   8956: athrow
    //   8957: aload #7
    //   8959: invokevirtual getPackage : ()Ljava/lang/Package;
    //   8962: invokevirtual getName : ()Ljava/lang/String;
    //   8965: ifnull -> 9005
    //   8968: goto -> 8975
    //   8971: invokestatic a : (Ljava/lang/Throwable;)Ljava/lang/Throwable;
    //   8974: athrow
    //   8975: aload #7
    //   8977: invokevirtual getPackage : ()Ljava/lang/Package;
    //   8980: invokevirtual getName : ()Ljava/lang/String;
    //   8983: sipush #30140
    //   8986: sipush #8903
    //   8989: invokestatic a : (II)Ljava/lang/String;
    //   8992: invokevirtual startsWith : (Ljava/lang/String;)Z
    //   8995: ifne -> 9005
    //   8998: goto -> 9005
    //   9001: invokestatic a : (Ljava/lang/Throwable;)Ljava/lang/Throwable;
    //   9004: athrow
    //   9005: aload #6
    //   9007: iconst_1
    //   9008: invokevirtual setAccessible : (Z)V
    //   9011: aload #6
    //   9013: aconst_null
    //   9014: invokevirtual get : (Ljava/lang/Object;)Ljava/lang/Object;
    //   9017: pop
    //   9018: iinc #5, 1
    //   9021: iload_2
    //   9022: ifne -> 8884
    //   9025: sipush #30137
    //   9028: sipush #1960
    //   9031: invokestatic a : (II)Ljava/lang/String;
    //   9034: invokestatic forName : (Ljava/lang/String;)Ljava/lang/Class;
    //   9037: invokevirtual getDeclaredMethods : ()[Ljava/lang/reflect/Method;
    //   9040: astore_3
    //   9041: aload_3
    //   9042: arraylength
    //   9043: istore #4
    //   9045: iconst_0
    //   9046: istore #5
    //   9048: iload #5
    //   9050: iload #4
    //   9052: if_icmpge -> 9184
    //   9055: aload_3
    //   9056: iload #5
    //   9058: aaload
    //   9059: astore #6
    //   9061: aload #6
    //   9063: invokevirtual getParameterTypes : ()[Ljava/lang/Class;
    //   9066: pop
    //   9067: aload #6
    //   9069: invokevirtual getModifiers : ()I
    //   9072: invokestatic isStatic : (I)Z
    //   9075: ifeq -> 9170
    //   9078: aload #6
    //   9080: invokevirtual getParameterTypes : ()[Ljava/lang/Class;
    //   9083: arraylength
    //   9084: iconst_2
    //   9085: if_icmpne -> 9170
    //   9088: goto -> 9095
    //   9091: invokestatic a : (Ljava/lang/Throwable;)Ljava/lang/Throwable;
    //   9094: athrow
    //   9095: aload #6
    //   9097: invokevirtual getReturnType : ()Ljava/lang/Class;
    //   9100: getstatic java/lang/Void.TYPE : Ljava/lang/Class;
    //   9103: invokevirtual equals : (Ljava/lang/Object;)Z
    //   9106: ifeq -> 9170
    //   9109: goto -> 9116
    //   9112: invokestatic a : (Ljava/lang/Throwable;)Ljava/lang/Throwable;
    //   9115: athrow
    //   9116: aload #6
    //   9118: iconst_1
    //   9119: invokevirtual setAccessible : (Z)V
    //   9122: aload #6
    //   9124: aconst_null
    //   9125: iconst_2
    //   9126: anewarray java/lang/Object
    //   9129: dup
    //   9130: iconst_0
    //   9131: aload_0
    //   9132: aastore
    //   9133: dup
    //   9134: iconst_1
    //   9135: aload_1
    //   9136: ifnonnull -> 9154
    //   9139: goto -> 9146
    //   9142: invokestatic a : (Ljava/lang/Throwable;)Ljava/lang/Throwable;
    //   9145: athrow
    //   9146: aload_1
    //   9147: goto -> 9161
    //   9150: invokestatic a : (Ljava/lang/Throwable;)Ljava/lang/Throwable;
    //   9153: athrow
    //   9154: aload_1
    //   9155: checkcast [B
    //   9158: invokevirtual clone : ()Ljava/lang/Object;
    //   9161: aastore
    //   9162: invokevirtual invoke : (Ljava/lang/Object;[Ljava/lang/Object;)Ljava/lang/Object;
    //   9165: pop
    //   9166: iload_2
    //   9167: ifne -> 9184
    //   9170: iinc #5, 1
    //   9173: iload_2
    //   9174: ifne -> 9048
    //   9177: goto -> 9184
    //   9180: invokestatic a : (Ljava/lang/Throwable;)Ljava/lang/Throwable;
    //   9183: athrow
    //   9184: getstatic burp/Zter.Zc : Ljava/lang/Object;
    //   9187: checkcast java/math/BigInteger
    //   9190: invokevirtual toByteArray : ()[B
    //   9193: astore_3
    //   9194: new java/lang/StringBuilder
    //   9197: dup
    //   9198: invokespecial <init> : ()V
    //   9201: astore #5
    //   9203: aload #5
    //   9205: sipush #30141
    //   9208: sipush #-3854
    //   9211: invokestatic a : (II)Ljava/lang/String;
    //   9214: invokevirtual append : (Ljava/lang/String;)Ljava/lang/StringBuilder;
    //   9217: pop
    //   9218: aload_3
    //   9219: astore #6
    //   9221: aload #6
    //   9223: arraylength
    //   9224: istore #7
    //   9226: iconst_0
    //   9227: istore #8
    //   9229: iload #8
    //   9231: iload #7
    //   9233: if_icmpge -> 9259
    //   9236: aload #6
    //   9238: iload #8
    //   9240: baload
    //   9241: istore #9
    //   9243: aload #5
    //   9245: iload #9
    //   9247: i2c
    //   9248: invokevirtual append : (C)Ljava/lang/StringBuilder;
    //   9251: pop
    //   9252: iinc #8, 1
    //   9255: iload_2
    //   9256: ifne -> 9229
    //   9259: aload #5
    //   9261: sipush #30143
    //   9264: sipush #-640
    //   9267: invokestatic a : (II)Ljava/lang/String;
    //   9270: ldc ''
    //   9272: invokestatic getProperty : (Ljava/lang/String;Ljava/lang/String;)Ljava/lang/String;
    //   9275: invokevirtual toLowerCase : ()Ljava/lang/String;
    //   9278: invokevirtual append : (Ljava/lang/String;)Ljava/lang/StringBuilder;
    //   9281: pop
    //   9282: aload #5
    //   9284: sipush #30136
    //   9287: sipush #17081
    //   9290: invokestatic a : (II)Ljava/lang/String;
    //   9293: ldc ''
    //   9295: invokestatic getProperty : (Ljava/lang/String;Ljava/lang/String;)Ljava/lang/String;
    //   9298: invokevirtual toLowerCase : ()Ljava/lang/String;
    //   9301: invokevirtual append : (Ljava/lang/String;)Ljava/lang/StringBuilder;
    //   9304: pop
    //   9305: aload #5
    //   9307: invokevirtual toString : ()Ljava/lang/String;
    //   9310: invokevirtual getBytes : ()[B
    //   9313: astore #4
    //   9315: aload #4
    //   9317: astore_3
    //   9318: aload_3
    //   9319: arraylength
    //   9320: bipush #8
    //   9322: iadd
    //   9323: bipush #6
    //   9325: ishr
    //   9326: iconst_1
    //   9327: iadd
    //   9328: bipush #16
    //   9330: imul
    //   9331: newarray int
    //   9333: astore #5
    //   9335: iconst_0
    //   9336: istore #6
    //   9338: iload #6
    //   9340: aload_3
    //   9341: arraylength
    //   9342: if_icmpge -> 9385
    //   9345: aload_3
    //   9346: iload #6
    //   9348: baload
    //   9349: sipush #255
    //   9352: iand
    //   9353: istore #7
    //   9355: aload #5
    //   9357: iload #6
    //   9359: iconst_2
    //   9360: ishr
    //   9361: dup2
    //   9362: iaload
    //   9363: iload #7
    //   9365: bipush #24
    //   9367: iload #6
    //   9369: iconst_4
    //   9370: irem
    //   9371: bipush #8
    //   9373: imul
    //   9374: isub
    //   9375: ishl
    //   9376: ior
    //   9377: iastore
    //   9378: iinc #6, 1
    //   9381: iload_2
    //   9382: ifne -> 9338
    //   9385: aload #5
    //   9387: iload #6
    //   9389: iconst_2
    //   9390: ishr
    //   9391: dup2
    //   9392: iaload
    //   9393: sipush #128
    //   9396: bipush #24
    //   9398: iload #6
    //   9400: iconst_4
    //   9401: irem
    //   9402: bipush #8
    //   9404: imul
    //   9405: isub
    //   9406: ishl
    //   9407: ior
    //   9408: iastore
    //   9409: aload #5
    //   9411: aload #5
    //   9413: arraylength
    //   9414: iconst_1
    //   9415: isub
    //   9416: aload_3
    //   9417: arraylength
    //   9418: bipush #8
    //   9420: imul
    //   9421: iastore
    //   9422: bipush #80
    //   9424: newarray int
    //   9426: astore #7
    //   9428: ldc 1732584193
    //   9430: istore #8
    //   9432: ldc -271733879
    //   9434: istore #9
    //   9436: ldc -1732584194
    //   9438: istore #10
    //   9440: ldc 271733878
    //   9442: istore #11
    //   9444: ldc -1009589776
    //   9446: istore #12
    //   9448: iconst_0
    //   9449: istore #6
    //   9451: iload #6
    //   9453: aload #5
    //   9455: arraylength
    //   9456: if_icmpge -> 9778
    //   9459: iload #8
    //   9461: istore #13
    //   9463: iload #9
    //   9465: istore #14
    //   9467: iload #10
    //   9469: istore #15
    //   9471: iload #11
    //   9473: istore #16
    //   9475: iload #12
    //   9477: istore #17
    //   9479: iconst_0
    //   9480: istore #18
    //   9482: iload #18
    //   9484: bipush #80
    //   9486: if_icmpge -> 9736
    //   9489: iload #18
    //   9491: bipush #16
    //   9493: if_icmpge -> 9520
    //   9496: aload #7
    //   9498: iload #18
    //   9500: aload #5
    //   9502: iload #6
    //   9504: iload #18
    //   9506: iadd
    //   9507: iaload
    //   9508: iastore
    //   9509: iload_2
    //   9510: ifne -> 9575
    //   9513: goto -> 9520
    //   9516: invokestatic a : (Ljava/lang/Throwable;)Ljava/lang/Throwable;
    //   9519: athrow
    //   9520: aload #7
    //   9522: iload #18
    //   9524: iconst_3
    //   9525: isub
    //   9526: iaload
    //   9527: aload #7
    //   9529: iload #18
    //   9531: bipush #8
    //   9533: isub
    //   9534: iaload
    //   9535: ixor
    //   9536: aload #7
    //   9538: iload #18
    //   9540: bipush #14
    //   9542: isub
    //   9543: iaload
    //   9544: ixor
    //   9545: aload #7
    //   9547: iload #18
    //   9549: bipush #16
    //   9551: isub
    //   9552: iaload
    //   9553: ixor
    //   9554: istore #19
    //   9556: iload #19
    //   9558: iconst_1
    //   9559: ishl
    //   9560: iload #19
    //   9562: bipush #31
    //   9564: iushr
    //   9565: ior
    //   9566: istore #20
    //   9568: aload #7
    //   9570: iload #18
    //   9572: iload #20
    //   9574: iastore
    //   9575: iload #8
    //   9577: iconst_5
    //   9578: ishl
    //   9579: iload #8
    //   9581: bipush #27
    //   9583: iushr
    //   9584: ior
    //   9585: istore #19
    //   9587: iload #19
    //   9589: iload #12
    //   9591: iadd
    //   9592: aload #7
    //   9594: iload #18
    //   9596: iaload
    //   9597: iadd
    //   9598: iload #18
    //   9600: bipush #20
    //   9602: if_icmpge -> 9628
    //   9605: ldc 1518500249
    //   9607: iload #9
    //   9609: iload #10
    //   9611: iand
    //   9612: iload #9
    //   9614: iconst_m1
    //   9615: ixor
    //   9616: iload #11
    //   9618: iand
    //   9619: ior
    //   9620: iadd
    //   9621: goto -> 9698
    //   9624: invokestatic a : (Ljava/lang/Throwable;)Ljava/lang/Throwable;
    //   9627: athrow
    //   9628: iload #18
    //   9630: bipush #40
    //   9632: if_icmpge -> 9653
    //   9635: ldc 1859775393
    //   9637: iload #9
    //   9639: iload #10
    //   9641: ixor
    //   9642: iload #11
    //   9644: ixor
    //   9645: iadd
    //   9646: goto -> 9698
    //   9649: invokestatic a : (Ljava/lang/Throwable;)Ljava/lang/Throwable;
    //   9652: athrow
    //   9653: iload #18
    //   9655: bipush #60
    //   9657: if_icmpge -> 9687
    //   9660: ldc -1894007588
    //   9662: iload #9
    //   9664: iload #10
    //   9666: iand
    //   9667: iload #9
    //   9669: iload #11
    //   9671: iand
    //   9672: ior
    //   9673: iload #10
    //   9675: iload #11
    //   9677: iand
    //   9678: ior
    //   9679: iadd
    //   9680: goto -> 9698
    //   9683: invokestatic a : (Ljava/lang/Throwable;)Ljava/lang/Throwable;
    //   9686: athrow
    //   9687: ldc -899497514
    //   9689: iload #9
    //   9691: iload #10
    //   9693: ixor
    //   9694: iload #11
    //   9696: ixor
    //   9697: iadd
    //   9698: iadd
    //   9699: istore #20
    //   9701: iload #11
    //   9703: istore #12
    //   9705: iload #10
    //   9707: istore #11
    //   9709: iload #9
    //   9711: bipush #30
    //   9713: ishl
    //   9714: iload #9
    //   9716: iconst_2
    //   9717: iushr
    //   9718: ior
    //   9719: istore #10
    //   9721: iload #8
    //   9723: istore #9
    //   9725: iload #20
    //   9727: istore #8
    //   9729: iinc #18, 1
    //   9732: iload_2
    //   9733: ifne -> 9482
    //   9736: iload #8
    //   9738: iload #13
    //   9740: iadd
    //   9741: istore #8
    //   9743: iload #9
    //   9745: iload #14
    //   9747: iadd
    //   9748: istore #9
    //   9750: iload #10
    //   9752: iload #15
    //   9754: iadd
    //   9755: istore #10
    //   9757: iload #11
    //   9759: iload #16
    //   9761: iadd
    //   9762: istore #11
    //   9764: iload #12
    //   9766: iload #17
    //   9768: iadd
    //   9769: istore #12
    //   9771: iinc #6, 16
    //   9774: iload_2
    //   9775: ifne -> 9451
    //   9778: iconst_5
    //   9779: newarray int
    //   9781: dup
    //   9782: iconst_0
    //   9783: iload #8
    //   9785: iastore
    //   9786: dup
    //   9787: iconst_1
    //   9788: iload #9
    //   9790: iastore
    //   9791: dup
    //   9792: iconst_2
    //   9793: iload #10
    //   9795: iastore
    //   9796: dup
    //   9797: iconst_3
    //   9798: iload #11
    //   9800: iastore
    //   9801: dup
    //   9802: iconst_4
    //   9803: iload #12
    //   9805: iastore
    //   9806: astore #13
    //   9808: bipush #20
    //   9810: newarray byte
    //   9812: astore #14
    //   9814: iconst_0
    //   9815: istore #15
    //   9817: iload #15
    //   9819: bipush #20
    //   9821: if_icmpge -> 9862
    //   9824: aload #13
    //   9826: iload #15
    //   9828: iconst_4
    //   9829: idiv
    //   9830: iaload
    //   9831: istore #16
    //   9833: iconst_3
    //   9834: iload #15
    //   9836: iconst_4
    //   9837: irem
    //   9838: isub
    //   9839: bipush #8
    //   9841: imul
    //   9842: istore #17
    //   9844: aload #14
    //   9846: iload #15
    //   9848: iload #16
    //   9850: iload #17
    //   9852: iushr
    //   9853: i2b
    //   9854: bastore
    //   9855: iinc #15, 1
    //   9858: iload_2
    //   9859: ifne -> 9817
    //   9862: aload #14
    //   9864: astore #4
    //   9866: getstatic burp/Zg_p.ZO : Ljava/lang/String;
    //   9869: getstatic burp/Ze7q.Zk : Ljava/lang/Object;
    //   9872: checkcast java/math/BigInteger
    //   9875: invokevirtual intValue : ()I
    //   9878: bipush #32
    //   9880: irem
    //   9881: invokestatic abs : (I)I
    //   9884: invokevirtual charAt : (I)C
    //   9887: getstatic burp/Zxk9.Zx : Ljava/lang/String;
    //   9890: getstatic burp/Ztbf.Zv : Ljava/lang/Object;
    //   9893: checkcast java/math/BigInteger
    //   9896: invokevirtual intValue : ()I
    //   9899: bipush #32
    //   9901: irem
    //   9902: invokestatic abs : (I)I
    //   9905: invokevirtual charAt : (I)C
    //   9908: if_icmpgt -> 10015
    //   9911: getstatic burp/Zl2q.ZI : Ljava/lang/String;
    //   9914: getstatic burp/Zbo7.Zl : Ljava/lang/Object;
    //   9917: checkcast java/math/BigInteger
    //   9920: invokevirtual intValue : ()I
    //   9923: bipush #32
    //   9925: irem
    //   9926: invokestatic abs : (I)I
    //   9929: invokevirtual charAt : (I)C
    //   9932: getstatic burp/Ze13.Zg : Ljava/lang/String;
    //   9935: getstatic burp/Zxzj.ZO : Ljava/lang/Object;
    //   9938: checkcast java/math/BigInteger
    //   9941: invokevirtual intValue : ()I
    //   9944: bipush #32
    //   9946: irem
    //   9947: invokestatic abs : (I)I
    //   9950: invokevirtual charAt : (I)C
    //   9953: if_icmpgt -> 10015
    //   9956: goto -> 9963
    //   9959: invokestatic a : (Ljava/lang/Throwable;)Ljava/lang/Throwable;
    //   9962: athrow
    //   9963: getstatic burp/Zxyp.Z_ : Ljava/lang/String;
    //   9966: getstatic burp/Zzai.Z_ : Ljava/lang/Object;
    //   9969: checkcast java/math/BigInteger
    //   9972: invokevirtual intValue : ()I
    //   9975: bipush #32
    //   9977: irem
    //   9978: invokestatic abs : (I)I
    //   9981: invokevirtual charAt : (I)C
    //   9984: getstatic burp/Zkyc.ZK : Ljava/lang/String;
    //   9987: getstatic burp/Zxwl.Ze : Ljava/lang/Object;
    //   9990: checkcast java/math/BigInteger
    //   9993: invokevirtual intValue : ()I
    //   9996: bipush #32
    //   9998: irem
    //   9999: invokestatic abs : (I)I
    //   10002: invokevirtual charAt : (I)C
    //   10005: if_icmple -> 10023
    //   10008: goto -> 10015
    //   10011: invokestatic a : (Ljava/lang/Throwable;)Ljava/lang/Throwable;
    //   10014: athrow
    //   10015: iconst_1
    //   10016: goto -> 10024
    //   10019: invokestatic a : (Ljava/lang/Throwable;)Ljava/lang/Throwable;
    //   10022: athrow
    //   10023: iconst_0
    //   10024: ireturn
    //   10025: astore_3
    //   10026: new java/lang/Exception
    //   10029: dup
    //   10030: aload_3
    //   10031: invokevirtual getMessage : ()Ljava/lang/String;
    //   10034: invokespecial <init> : (Ljava/lang/String;)V
    //   10037: athrow
    // Exception table:
    //   from	to	target	type
    //   4	10024	10025	java/lang/Throwable
    //   191	219	222	java/lang/Throwable
    //   201	236	239	java/lang/Throwable
    //   226	264	267	java/lang/Throwable
    //   243	281	284	java/lang/Throwable
    //   271	309	312	java/lang/Throwable
    //   288	326	329	java/lang/Throwable
    //   316	344	347	java/lang/Throwable
    //   333	358	361	java/lang/Throwable
    //   3721	3746	3746	java/lang/Throwable
    //   4709	4735	4735	java/lang/Throwable
    //   5583	5617	5620	java/lang/Throwable
    //   5712	5790	5793	java/lang/Throwable
    //   5719	5933	5936	java/lang/Throwable
    //   6310	6325	6325	java/lang/Throwable
    //   6352	6386	6389	java/lang/Throwable
    //   6396	6408	6411	java/lang/Throwable
    //   6494	6572	6575	java/lang/Throwable
    //   6501	6715	6718	java/lang/Throwable
    //   7115	7193	7196	java/lang/Throwable
    //   7122	7336	7339	java/lang/Throwable
    //   7783	7817	7820	java/lang/Throwable
    //   7824	7836	7839	java/lang/Throwable
    //   7922	8000	8003	java/lang/Throwable
    //   7929	8143	8146	java/lang/Throwable
    //   8897	8911	8911	java/lang/Throwable
    //   8922	8935	8938	java/lang/Throwable
    //   8927	8950	8953	java/lang/Throwable
    //   8942	8968	8971	java/lang/Throwable
    //   8957	8998	9001	java/lang/Throwable
    //   9061	9088	9091	java/lang/Throwable
    //   9078	9109	9112	java/lang/Throwable
    //   9095	9139	9142	java/lang/Throwable
    //   9116	9150	9150	java/lang/Throwable
    //   9161	9177	9180	java/lang/Throwable
    //   9489	9513	9516	java/lang/Throwable
    //   9587	9624	9624	java/lang/Throwable
    //   9628	9649	9649	java/lang/Throwable
    //   9653	9683	9683	java/lang/Throwable
    //   9866	9956	9959	java/lang/Throwable
    //   9911	10008	10011	java/lang/Throwable
    //   9963	10019	10019	java/lang/Throwable
  }
  
  static void Zu(Object paramObject) {
    Zllw.Zg = a(30138, -32686);
    Zllw.ZW = new BigInteger(a(30142, -25678));
    boolean bool = Zt2e.ZK();
    try {
      try {
        if (Zxzd.ZM.charAt(Math.abs(((BigInteger)Zd1.ZV).intValue() % 32)) > Zllw.Zg.charAt(Math.abs(((BigInteger)Zlv6.ZN).intValue() % 32))) {
          try {
            Zxl5.Zq(Class.forName(a(30128, 25829)));
            if (bool)
              Zzmo.ZU(Class.forName(a(30139, 31787))); 
          } catch (Throwable throwable) {
            throw a(null);
          } 
          return;
        } 
      } catch (Throwable throwable) {
        throw a(null);
      } 
      Zzmo.ZU(Class.forName(a(30139, 31787)));
    } catch (Throwable throwable) {}
  }
  
  static void ZZ(Object[] paramArrayOfObject, Object paramObject) throws Throwable {}
  
  static {
    // Byte code:
    //   0: bipush #13
    //   2: anewarray java/lang/String
    //   5: astore #5
    //   7: iconst_0
    //   8: istore_3
    //   9: ldc '&\"4<\\tqh\\tGsb/ r<=d`\\rgVS\\rmJZ WgwMgV}x\\fa@$fdA:#(BGMARfl \\bf4lid(=o,{nf,Ol!ofJc5L\\b\\b =n+\\tL bbe\\nc$PuC[w+FG8'
    //   11: dup
    //   12: astore_2
    //   13: invokevirtual length : ()I
    //   16: istore #4
    //   18: bipush #8
    //   20: istore_1
    //   21: iconst_m1
    //   22: istore_0
    //   23: bipush #53
    //   25: iinc #0, 1
    //   28: aload_2
    //   29: iload_0
    //   30: dup
    //   31: iload_1
    //   32: iadd
    //   33: invokevirtual substring : (II)Ljava/lang/String;
    //   36: iconst_m1
    //   37: goto -> 143
    //   40: aload #5
    //   42: swap
    //   43: iload_3
    //   44: iinc #3, 1
    //   47: swap
    //   48: aastore
    //   49: iload_0
    //   50: iload_1
    //   51: iadd
    //   52: dup
    //   53: istore_0
    //   54: iload #4
    //   56: if_icmpge -> 68
    //   59: aload_2
    //   60: iload_0
    //   61: invokevirtual charAt : (I)C
    //   64: istore_1
    //   65: goto -> 23
    //   68: ldc 's0,2}qeWsPAt'
    //   70: dup
    //   71: astore_2
    //   72: invokevirtual length : ()I
    //   75: istore #4
    //   77: bipush #19
    //   79: istore_1
    //   80: iconst_m1
    //   81: istore_0
    //   82: bipush #65
    //   84: iinc #0, 1
    //   87: aload_2
    //   88: iload_0
    //   89: dup
    //   90: iload_1
    //   91: iadd
    //   92: invokevirtual substring : (II)Ljava/lang/String;
    //   95: iconst_0
    //   96: goto -> 143
    //   99: aload #5
    //   101: swap
    //   102: iload_3
    //   103: iinc #3, 1
    //   106: swap
    //   107: aastore
    //   108: iload_0
    //   109: iload_1
    //   110: iadd
    //   111: dup
    //   112: istore_0
    //   113: iload #4
    //   115: if_icmpge -> 127
    //   118: aload_2
    //   119: iload_0
    //   120: invokevirtual charAt : (I)C
    //   123: istore_1
    //   124: goto -> 82
    //   127: aload #5
    //   129: putstatic burp/Zrbp.a : [Ljava/lang/String;
    //   132: bipush #13
    //   134: anewarray java/lang/String
    //   137: putstatic burp/Zrbp.b : [Ljava/lang/String;
    //   140: goto -> 300
    //   143: dup_x2
    //   144: pop
    //   145: invokevirtual toCharArray : ()[C
    //   148: dup_x1
    //   149: arraylength
    //   150: dup_x2
    //   151: pop
    //   152: iconst_0
    //   153: istore #6
    //   155: dup2_x1
    //   156: pop2
    //   157: dup_x2
    //   158: iconst_1
    //   159: if_icmpgt -> 260
    //   162: dup2
    //   163: swap
    //   164: iload #6
    //   166: dup2_x1
    //   167: caload
    //   168: swap
    //   169: iload #6
    //   171: bipush #7
    //   173: irem
    //   174: tableswitch default -> 242, 0 -> 212, 1 -> 217, 2 -> 222, 3 -> 227, 4 -> 232, 5 -> 237
    //   212: bipush #116
    //   214: goto -> 244
    //   217: bipush #120
    //   219: goto -> 244
    //   222: bipush #96
    //   224: goto -> 244
    //   227: bipush #83
    //   229: goto -> 244
    //   232: bipush #19
    //   234: goto -> 244
    //   237: bipush #20
    //   239: goto -> 244
    //   242: bipush #13
    //   244: ixor
    //   245: ixor
    //   246: i2c
    //   247: castore
    //   248: iinc #6, 1
    //   251: dup
    //   252: ifne -> 260
    //   255: dup2
    //   256: dup_x1
    //   257: goto -> 166
    //   260: dup2_x1
    //   261: pop2
    //   262: dup_x2
    //   263: iload #6
    //   265: if_icmpgt -> 162
    //   268: pop
    //   269: new java/lang/String
    //   272: dup_x1
    //   273: swap
    //   274: invokespecial <init> : ([C)V
    //   277: invokevirtual intern : ()Ljava/lang/String;
    //   280: swap
    //   281: pop
    //   282: swap
    //   283: tableswitch default -> 40, 0 -> 99
    //   300: sipush #30131
    //   303: sipush #-23506
    //   306: invokestatic a : (II)Ljava/lang/String;
    //   309: putstatic burp/Zrbp.Ze : Ljava/lang/String;
    //   312: new java/math/BigInteger
    //   315: dup
    //   316: bipush #32
    //   318: newarray byte
    //   320: dup
    //   321: iconst_0
    //   322: iconst_2
    //   323: bastore
    //   324: dup
    //   325: iconst_1
    //   326: bipush #-94
    //   328: bastore
    //   329: dup
    //   330: iconst_2
    //   331: bipush #-20
    //   333: bastore
    //   334: dup
    //   335: iconst_3
    //   336: bipush #-43
    //   338: bastore
    //   339: dup
    //   340: iconst_4
    //   341: bipush #62
    //   343: bastore
    //   344: dup
    //   345: iconst_5
    //   346: bipush #-37
    //   348: bastore
    //   349: dup
    //   350: bipush #6
    //   352: bipush #-103
    //   354: bastore
    //   355: dup
    //   356: bipush #7
    //   358: bipush #104
    //   360: bastore
    //   361: dup
    //   362: bipush #8
    //   364: bipush #-55
    //   366: bastore
    //   367: dup
    //   368: bipush #9
    //   370: bipush #70
    //   372: bastore
    //   373: dup
    //   374: bipush #10
    //   376: bipush #44
    //   378: bastore
    //   379: dup
    //   380: bipush #11
    //   382: bipush #64
    //   384: bastore
    //   385: dup
    //   386: bipush #12
    //   388: bipush #-94
    //   390: bastore
    //   391: dup
    //   392: bipush #13
    //   394: bipush #66
    //   396: bastore
    //   397: dup
    //   398: bipush #14
    //   400: bipush #110
    //   402: bastore
    //   403: dup
    //   404: bipush #15
    //   406: bipush #100
    //   408: bastore
    //   409: dup
    //   410: bipush #16
    //   412: bipush #87
    //   414: bastore
    //   415: dup
    //   416: bipush #17
    //   418: bipush #30
    //   420: bastore
    //   421: dup
    //   422: bipush #18
    //   424: bipush #-120
    //   426: bastore
    //   427: dup
    //   428: bipush #19
    //   430: bipush #-67
    //   432: bastore
    //   433: dup
    //   434: bipush #20
    //   436: bipush #-28
    //   438: bastore
    //   439: dup
    //   440: bipush #21
    //   442: bipush #-124
    //   444: bastore
    //   445: dup
    //   446: bipush #22
    //   448: bipush #56
    //   450: bastore
    //   451: dup
    //   452: bipush #23
    //   454: bipush #-84
    //   456: bastore
    //   457: dup
    //   458: bipush #24
    //   460: bipush #-72
    //   462: bastore
    //   463: dup
    //   464: bipush #25
    //   466: bipush #-73
    //   468: bastore
    //   469: dup
    //   470: bipush #26
    //   472: bipush #116
    //   474: bastore
    //   475: dup
    //   476: bipush #27
    //   478: bipush #41
    //   480: bastore
    //   481: dup
    //   482: bipush #28
    //   484: bipush #42
    //   486: bastore
    //   487: dup
    //   488: bipush #29
    //   490: bipush #-58
    //   492: bastore
    //   493: dup
    //   494: bipush #30
    //   496: bipush #-91
    //   498: bastore
    //   499: dup
    //   500: bipush #31
    //   502: bipush #70
    //   504: bastore
    //   505: invokespecial <init> : ([B)V
    //   508: putstatic burp/Zrbp.Z_ : Ljava/lang/Object;
    //   511: return
  }
  
  private static Throwable a(Throwable paramThrowable) {
    return paramThrowable;
  }
  
  private static String a(int paramInt1, int paramInt2) {
    int i = (paramInt1 ^ 0x75B9) & 0xFFFF;
    if (b[i] == null) {
      char[] arrayOfChar = a[i].toCharArray();
      switch (arrayOfChar[0] & 0xFF) {
        case 0:
        
        case 1:
        
        case 2:
        
        case 3:
        
        case 4:
        
        case 5:
        
        case 6:
        
        case 7:
        
        case 8:
        
        case 9:
        
        case 10:
        
        case 11:
        
        case 12:
        
        case 13:
        
        case 14:
        
        case 15:
        
        case 16:
        
        case 17:
        
        case 18:
        
        case 19:
        
        case 20:
        
        case 21:
        
        case 22:
        
        case 23:
        
        case 24:
        
        case 25:
        
        case 26:
        
        case 27:
        
        case 28:
        
        case 29:
        
        case 30:
        
        case 31:
        
        case 32:
        
        case 33:
        
        case 34:
        
        case 35:
        
        case 36:
        
        case 37:
        
        case 38:
        
        case 39:
        
        case 40:
        
        case 41:
        
        case 42:
        
        case 43:
        
        case 44:
        
        case 45:
        
        case 46:
        
        case 47:
        
        case 48:
        
        case 49:
        
        case 50:
        
        case 51:
        
        case 52:
        
        case 53:
        
        case 54:
        
        case 55:
        
        case 56:
        
        case 57:
        
        case 58:
        
        case 59:
        
        case 60:
        
        case 61:
        
        case 62:
        
        case 63:
        
        case 64:
        
        case 65:
        
        case 66:
        
        case 67:
        
        case 68:
        
        case 69:
        
        case 70:
        
        case 71:
        
        case 72:
        
        case 73:
        
        case 74:
        
        case 75:
        
        case 76:
        
        case 77:
        
        case 78:
        
        case 79:
        
        case 80:
        
        case 81:
        
        case 82:
        
        case 83:
        
        case 84:
        
        case 85:
        
        case 86:
        
        case 87:
        
        case 88:
        
        case 89:
        
        case 90:
        
        case 91:
        
        case 92:
        
        case 93:
        
        case 94:
        
        case 95:
        
        case 96:
        
        case 97:
        
        case 98:
        
        case 99:
        
        case 100:
        
        case 101:
        
        case 102:
        
        case 103:
        
        case 104:
        
        case 105:
        
        case 106:
        
        case 107:
        
        case 108:
        
        case 109:
        
        case 110:
        
        case 111:
        
        case 112:
        
        case 113:
        
        case 114:
        
        case 115:
        
        case 116:
        
        case 117:
        
        case 118:
        
        case 119:
        
        case 120:
        
        case 121:
        
        case 122:
        
        case 123:
        
        case 124:
        
        case 125:
        
        case 126:
        
        case 127:
        
        case 128:
        
        case 129:
        
        case 130:
        
        case 131:
        
        case 132:
        
        case 133:
        
        case 134:
        
        case 135:
        
        case 136:
        
        case 137:
        
        case 138:
        
        case 139:
        
        case 140:
        
        case 141:
        
        case 142:
        
        case 143:
        
        case 144:
        
        case 145:
        
        case 146:
        
        case 147:
        
        case 148:
        
        case 149:
        
        case 150:
        
        case 151:
        
        case 152:
        
        case 153:
        
        case 154:
        
        case 155:
        
        case 156:
        
        case 157:
        
        case 158:
        
        case 159:
        
        case 160:
        
        case 161:
        
        case 162:
        
        case 163:
        
        case 164:
        
        case 165:
        
        case 166:
        
        case 167:
        
        case 168:
        
        case 169:
        
        case 170:
        
        case 171:
        
        case 172:
        
        case 173:
        
        case 174:
        
        case 175:
        
        case 176:
        
        case 177:
        
        case 178:
        
        case 179:
        
        case 180:
        
        case 181:
        
        case 182:
        
        case 183:
        
        case 184:
        
        case 185:
        
        case 186:
        
        case 187:
        
        case 188:
        
        case 189:
        
        case 190:
        
        case 191:
        
        case 192:
        
        case 193:
        
        case 194:
        
        case 195:
        
        case 196:
        
        case 197:
        
        case 198:
        
        case 199:
        
        case 200:
        
        case 201:
        
        case 202:
        
        case 203:
        
        case 204:
        
        case 205:
        
        case 206:
        
        case 207:
        
        case 208:
        
        case 209:
        
        case 210:
        
        case 211:
        
        case 212:
        
        case 213:
        
        case 214:
        
        case 215:
        
        case 216:
        
        case 217:
        
        case 218:
        
        case 219:
        
        case 220:
        
        case 221:
        
        case 222:
        
        case 223:
        
        case 224:
        
        case 225:
        
        case 226:
        
        case 227:
        
        case 228:
        
        case 229:
        
        case 230:
        
        case 231:
        
        case 232:
        
        case 233:
        
        case 234:
        
        case 235:
        
        case 236:
        
        case 237:
        
        case 238:
        
        case 239:
        
        case 240:
        
        case 241:
        
        case 242:
        
        case 243:
        
        case 244:
        
        case 245:
        
        case 246:
        
        case 247:
        
        case 248:
        
        case 249:
        
        case 250:
        
        case 251:
        
        case 252:
        
        case 253:
        
        case 254:
        
        default:
          break;
      } 
      char c = '';
      int j = (paramInt2 & 0xFF) - c;
      if (j < 0)
        j += 256; 
      int k = ((paramInt2 & 0xFFFF) >>> 8) - c;
      if (k < 0)
        k += 256; 
      for (byte b = 0; b < arrayOfChar.length; b++) {
        int m = b % 2;
        if (m == 0) {
          arrayOfChar[b] = (char)(arrayOfChar[b] ^ j);
          j = ((j >>> 3 | j << 5) ^ arrayOfChar[b]) & 0xFF;
        } else {
          arrayOfChar[b] = (char)(arrayOfChar[b] ^ k);
          k = ((k >>> 3 | k << 5) ^ arrayOfChar[b]) & 0xFF;
        } 
      } 
      b[i] = (new String(arrayOfChar)).intern();
    } 
    return b[i];
  }
}


/* Location:              C:\Program Files\BurpSuitePro\burpsuite_pro.jar!\burp\Zrbp.class
 * Java compiler version: 21 (65.0)
 * JD-Core Version:       1.1.3
 */