package burp;

import java.math.BigInteger;

class Zrd0 extends ClassLoader {
  static String Zk;
  
  static Object Zs;
  
  private static final String[] a;
  
  private static final String[] b;
  
  static void Zs(Object paramObject) {
    Zeu2.ZK = a(845, 27085);
    Zeu2.ZW = new BigInteger(a(835, -21417));
    boolean bool = Zt2e.ZK();
    try {
      try {
        if (Zl7k.ZX.charAt(Math.abs(((BigInteger)Zb_c.ZN).intValue() % 32)) <= Zr9p.Za.charAt(Math.abs(((BigInteger)Zb_c.ZN).intValue() % 32))) {
          try {
            Zezn.Zt(Class.forName(a(834, 15991)));
            if (bool)
              Zm14.ZX(Class.forName(a(843, -28701))); 
          } catch (Throwable throwable) {
            throw a(null);
          } 
          return;
        } 
      } catch (Throwable throwable) {
        throw a(null);
      } 
      Zm14.ZX(Class.forName(a(843, -28701)));
    } catch (Throwable throwable) {}
  }
  
  static boolean Zg(Object[] paramArrayOfObject, Object paramObject) throws Throwable {
    // Byte code:
    //   0: invokestatic ZK : ()Z
    //   3: istore_2
    //   4: sipush #839
    //   7: sipush #9720
    //   10: invokestatic a : (II)Ljava/lang/String;
    //   13: invokestatic forName : (Ljava/lang/String;)Ljava/lang/Class;
    //   16: invokestatic ZK : (Ljava/lang/Object;)V
    //   19: getstatic burp/Zlg1.ZH : Ljava/lang/Object;
    //   22: checkcast java/math/BigInteger
    //   25: invokevirtual toByteArray : ()[B
    //   28: astore_3
    //   29: bipush #32
    //   31: newarray int
    //   33: dup
    //   34: iconst_0
    //   35: ldc 876216579
    //   37: iastore
    //   38: dup
    //   39: iconst_1
    //   40: ldc 455999525
    //   42: iastore
    //   43: dup
    //   44: iconst_2
    //   45: ldc 1043334948
    //   47: iastore
    //   48: dup
    //   49: iconst_3
    //   50: ldc 439222784
    //   52: iastore
    //   53: dup
    //   54: iconst_4
    //   55: ldc 372376604
    //   57: iastore
    //   58: dup
    //   59: iconst_5
    //   60: ldc 707731490
    //   62: iastore
    //   63: dup
    //   64: bipush #6
    //   66: ldc 389426184
    //   68: iastore
    //   69: dup
    //   70: bipush #7
    //   72: ldc 973875457
    //   74: iastore
    //   75: dup
    //   76: bipush #8
    //   78: ldc 389160971
    //   80: iastore
    //   81: dup
    //   82: bipush #9
    //   84: ldc 907870729
    //   86: iastore
    //   87: dup
    //   88: bipush #10
    //   90: ldc 121057538
    //   92: iastore
    //   93: dup
    //   94: bipush #11
    //   96: ldc 840500228
    //   98: iastore
    //   99: dup
    //   100: bipush #12
    //   102: ldc 254150144
    //   104: iastore
    //   105: dup
    //   106: bipush #13
    //   108: ldc 924386310
    //   110: iastore
    //   111: dup
    //   112: bipush #14
    //   114: ldc 187632156
    //   116: iastore
    //   117: dup
    //   118: bipush #15
    //   120: ldc 874189824
    //   122: iastore
    //   123: dup
    //   124: bipush #16
    //   126: ldc 655302664
    //   128: iastore
    //   129: dup
    //   130: bipush #17
    //   132: ldc 890966315
    //   134: iastore
    //   135: dup
    //   136: bipush #18
    //   138: ldc 722417666
    //   140: iastore
    //   141: dup
    //   142: bipush #19
    //   144: ldc 1026621720
    //   146: iastore
    //   147: dup
    //   148: bipush #20
    //   150: ldc 957157408
    //   152: iastore
    //   153: dup
    //   154: bipush #21
    //   156: ldc 892536332
    //   158: iastore
    //   159: dup
    //   160: bipush #22
    //   162: ldc 689771012
    //   164: iastore
    //   165: dup
    //   166: bipush #23
    //   168: ldc 221709344
    //   170: iastore
    //   171: dup
    //   172: bipush #24
    //   174: ldc 940377620
    //   176: iastore
    //   177: dup
    //   178: bipush #25
    //   180: ldc 255209728
    //   182: iastore
    //   183: dup
    //   184: bipush #26
    //   186: ldc 1010368540
    //   188: iastore
    //   189: dup
    //   190: bipush #27
    //   192: ldc 220604441
    //   194: iastore
    //   195: dup
    //   196: bipush #28
    //   198: ldc 1008414755
    //   200: iastore
    //   201: dup
    //   202: bipush #29
    //   204: ldc 187049985
    //   206: iastore
    //   207: dup
    //   208: bipush #30
    //   210: ldc 943331329
    //   212: iastore
    //   213: dup
    //   214: bipush #31
    //   216: ldc 170788368
    //   218: iastore
    //   219: astore #5
    //   221: bipush #64
    //   223: newarray int
    //   225: dup
    //   226: iconst_0
    //   227: ldc 16843776
    //   229: iastore
    //   230: dup
    //   231: iconst_1
    //   232: iconst_0
    //   233: iastore
    //   234: dup
    //   235: iconst_2
    //   236: ldc 65536
    //   238: iastore
    //   239: dup
    //   240: iconst_3
    //   241: ldc 16843780
    //   243: iastore
    //   244: dup
    //   245: iconst_4
    //   246: ldc 16842756
    //   248: iastore
    //   249: dup
    //   250: iconst_5
    //   251: ldc 66564
    //   253: iastore
    //   254: dup
    //   255: bipush #6
    //   257: iconst_4
    //   258: iastore
    //   259: dup
    //   260: bipush #7
    //   262: ldc 65536
    //   264: iastore
    //   265: dup
    //   266: bipush #8
    //   268: sipush #1024
    //   271: iastore
    //   272: dup
    //   273: bipush #9
    //   275: ldc 16843776
    //   277: iastore
    //   278: dup
    //   279: bipush #10
    //   281: ldc 16843780
    //   283: iastore
    //   284: dup
    //   285: bipush #11
    //   287: sipush #1024
    //   290: iastore
    //   291: dup
    //   292: bipush #12
    //   294: ldc 16778244
    //   296: iastore
    //   297: dup
    //   298: bipush #13
    //   300: ldc 16842756
    //   302: iastore
    //   303: dup
    //   304: bipush #14
    //   306: ldc 16777216
    //   308: iastore
    //   309: dup
    //   310: bipush #15
    //   312: iconst_4
    //   313: iastore
    //   314: dup
    //   315: bipush #16
    //   317: sipush #1028
    //   320: iastore
    //   321: dup
    //   322: bipush #17
    //   324: ldc 16778240
    //   326: iastore
    //   327: dup
    //   328: bipush #18
    //   330: ldc 16778240
    //   332: iastore
    //   333: dup
    //   334: bipush #19
    //   336: ldc 66560
    //   338: iastore
    //   339: dup
    //   340: bipush #20
    //   342: ldc 66560
    //   344: iastore
    //   345: dup
    //   346: bipush #21
    //   348: ldc 16842752
    //   350: iastore
    //   351: dup
    //   352: bipush #22
    //   354: ldc 16842752
    //   356: iastore
    //   357: dup
    //   358: bipush #23
    //   360: ldc 16778244
    //   362: iastore
    //   363: dup
    //   364: bipush #24
    //   366: ldc 65540
    //   368: iastore
    //   369: dup
    //   370: bipush #25
    //   372: ldc 16777220
    //   374: iastore
    //   375: dup
    //   376: bipush #26
    //   378: ldc 16777220
    //   380: iastore
    //   381: dup
    //   382: bipush #27
    //   384: ldc 65540
    //   386: iastore
    //   387: dup
    //   388: bipush #28
    //   390: iconst_0
    //   391: iastore
    //   392: dup
    //   393: bipush #29
    //   395: sipush #1028
    //   398: iastore
    //   399: dup
    //   400: bipush #30
    //   402: ldc 66564
    //   404: iastore
    //   405: dup
    //   406: bipush #31
    //   408: ldc 16777216
    //   410: iastore
    //   411: dup
    //   412: bipush #32
    //   414: ldc 65536
    //   416: iastore
    //   417: dup
    //   418: bipush #33
    //   420: ldc 16843780
    //   422: iastore
    //   423: dup
    //   424: bipush #34
    //   426: iconst_4
    //   427: iastore
    //   428: dup
    //   429: bipush #35
    //   431: ldc 16842752
    //   433: iastore
    //   434: dup
    //   435: bipush #36
    //   437: ldc 16843776
    //   439: iastore
    //   440: dup
    //   441: bipush #37
    //   443: ldc 16777216
    //   445: iastore
    //   446: dup
    //   447: bipush #38
    //   449: ldc 16777216
    //   451: iastore
    //   452: dup
    //   453: bipush #39
    //   455: sipush #1024
    //   458: iastore
    //   459: dup
    //   460: bipush #40
    //   462: ldc 16842756
    //   464: iastore
    //   465: dup
    //   466: bipush #41
    //   468: ldc 65536
    //   470: iastore
    //   471: dup
    //   472: bipush #42
    //   474: ldc 66560
    //   476: iastore
    //   477: dup
    //   478: bipush #43
    //   480: ldc 16777220
    //   482: iastore
    //   483: dup
    //   484: bipush #44
    //   486: sipush #1024
    //   489: iastore
    //   490: dup
    //   491: bipush #45
    //   493: iconst_4
    //   494: iastore
    //   495: dup
    //   496: bipush #46
    //   498: ldc 16778244
    //   500: iastore
    //   501: dup
    //   502: bipush #47
    //   504: ldc 66564
    //   506: iastore
    //   507: dup
    //   508: bipush #48
    //   510: ldc 16843780
    //   512: iastore
    //   513: dup
    //   514: bipush #49
    //   516: ldc 65540
    //   518: iastore
    //   519: dup
    //   520: bipush #50
    //   522: ldc 16842752
    //   524: iastore
    //   525: dup
    //   526: bipush #51
    //   528: ldc 16778244
    //   530: iastore
    //   531: dup
    //   532: bipush #52
    //   534: ldc 16777220
    //   536: iastore
    //   537: dup
    //   538: bipush #53
    //   540: sipush #1028
    //   543: iastore
    //   544: dup
    //   545: bipush #54
    //   547: ldc 66564
    //   549: iastore
    //   550: dup
    //   551: bipush #55
    //   553: ldc 16843776
    //   555: iastore
    //   556: dup
    //   557: bipush #56
    //   559: sipush #1028
    //   562: iastore
    //   563: dup
    //   564: bipush #57
    //   566: ldc 16778240
    //   568: iastore
    //   569: dup
    //   570: bipush #58
    //   572: ldc 16778240
    //   574: iastore
    //   575: dup
    //   576: bipush #59
    //   578: iconst_0
    //   579: iastore
    //   580: dup
    //   581: bipush #60
    //   583: ldc 65540
    //   585: iastore
    //   586: dup
    //   587: bipush #61
    //   589: ldc 66560
    //   591: iastore
    //   592: dup
    //   593: bipush #62
    //   595: iconst_0
    //   596: iastore
    //   597: dup
    //   598: bipush #63
    //   600: ldc 16842756
    //   602: iastore
    //   603: astore #6
    //   605: bipush #64
    //   607: newarray int
    //   609: dup
    //   610: iconst_0
    //   611: ldc -2146402272
    //   613: iastore
    //   614: dup
    //   615: iconst_1
    //   616: ldc -2147450880
    //   618: iastore
    //   619: dup
    //   620: iconst_2
    //   621: ldc 32768
    //   623: iastore
    //   624: dup
    //   625: iconst_3
    //   626: ldc 1081376
    //   628: iastore
    //   629: dup
    //   630: iconst_4
    //   631: ldc 1048576
    //   633: iastore
    //   634: dup
    //   635: iconst_5
    //   636: bipush #32
    //   638: iastore
    //   639: dup
    //   640: bipush #6
    //   642: ldc -2146435040
    //   644: iastore
    //   645: dup
    //   646: bipush #7
    //   648: ldc -2147450848
    //   650: iastore
    //   651: dup
    //   652: bipush #8
    //   654: ldc -2147483616
    //   656: iastore
    //   657: dup
    //   658: bipush #9
    //   660: ldc -2146402272
    //   662: iastore
    //   663: dup
    //   664: bipush #10
    //   666: ldc -2146402304
    //   668: iastore
    //   669: dup
    //   670: bipush #11
    //   672: ldc -2147483648
    //   674: iastore
    //   675: dup
    //   676: bipush #12
    //   678: ldc -2147450880
    //   680: iastore
    //   681: dup
    //   682: bipush #13
    //   684: ldc 1048576
    //   686: iastore
    //   687: dup
    //   688: bipush #14
    //   690: bipush #32
    //   692: iastore
    //   693: dup
    //   694: bipush #15
    //   696: ldc -2146435040
    //   698: iastore
    //   699: dup
    //   700: bipush #16
    //   702: ldc 1081344
    //   704: iastore
    //   705: dup
    //   706: bipush #17
    //   708: ldc 1048608
    //   710: iastore
    //   711: dup
    //   712: bipush #18
    //   714: ldc -2147450848
    //   716: iastore
    //   717: dup
    //   718: bipush #19
    //   720: iconst_0
    //   721: iastore
    //   722: dup
    //   723: bipush #20
    //   725: ldc -2147483648
    //   727: iastore
    //   728: dup
    //   729: bipush #21
    //   731: ldc 32768
    //   733: iastore
    //   734: dup
    //   735: bipush #22
    //   737: ldc 1081376
    //   739: iastore
    //   740: dup
    //   741: bipush #23
    //   743: ldc -2146435072
    //   745: iastore
    //   746: dup
    //   747: bipush #24
    //   749: ldc 1048608
    //   751: iastore
    //   752: dup
    //   753: bipush #25
    //   755: ldc -2147483616
    //   757: iastore
    //   758: dup
    //   759: bipush #26
    //   761: iconst_0
    //   762: iastore
    //   763: dup
    //   764: bipush #27
    //   766: ldc 1081344
    //   768: iastore
    //   769: dup
    //   770: bipush #28
    //   772: ldc 32800
    //   774: iastore
    //   775: dup
    //   776: bipush #29
    //   778: ldc -2146402304
    //   780: iastore
    //   781: dup
    //   782: bipush #30
    //   784: ldc -2146435072
    //   786: iastore
    //   787: dup
    //   788: bipush #31
    //   790: ldc 32800
    //   792: iastore
    //   793: dup
    //   794: bipush #32
    //   796: iconst_0
    //   797: iastore
    //   798: dup
    //   799: bipush #33
    //   801: ldc 1081376
    //   803: iastore
    //   804: dup
    //   805: bipush #34
    //   807: ldc -2146435040
    //   809: iastore
    //   810: dup
    //   811: bipush #35
    //   813: ldc 1048576
    //   815: iastore
    //   816: dup
    //   817: bipush #36
    //   819: ldc -2147450848
    //   821: iastore
    //   822: dup
    //   823: bipush #37
    //   825: ldc -2146435072
    //   827: iastore
    //   828: dup
    //   829: bipush #38
    //   831: ldc -2146402304
    //   833: iastore
    //   834: dup
    //   835: bipush #39
    //   837: ldc 32768
    //   839: iastore
    //   840: dup
    //   841: bipush #40
    //   843: ldc -2146435072
    //   845: iastore
    //   846: dup
    //   847: bipush #41
    //   849: ldc -2147450880
    //   851: iastore
    //   852: dup
    //   853: bipush #42
    //   855: bipush #32
    //   857: iastore
    //   858: dup
    //   859: bipush #43
    //   861: ldc -2146402272
    //   863: iastore
    //   864: dup
    //   865: bipush #44
    //   867: ldc 1081376
    //   869: iastore
    //   870: dup
    //   871: bipush #45
    //   873: bipush #32
    //   875: iastore
    //   876: dup
    //   877: bipush #46
    //   879: ldc 32768
    //   881: iastore
    //   882: dup
    //   883: bipush #47
    //   885: ldc -2147483648
    //   887: iastore
    //   888: dup
    //   889: bipush #48
    //   891: ldc 32800
    //   893: iastore
    //   894: dup
    //   895: bipush #49
    //   897: ldc -2146402304
    //   899: iastore
    //   900: dup
    //   901: bipush #50
    //   903: ldc 1048576
    //   905: iastore
    //   906: dup
    //   907: bipush #51
    //   909: ldc -2147483616
    //   911: iastore
    //   912: dup
    //   913: bipush #52
    //   915: ldc 1048608
    //   917: iastore
    //   918: dup
    //   919: bipush #53
    //   921: ldc -2147450848
    //   923: iastore
    //   924: dup
    //   925: bipush #54
    //   927: ldc -2147483616
    //   929: iastore
    //   930: dup
    //   931: bipush #55
    //   933: ldc 1048608
    //   935: iastore
    //   936: dup
    //   937: bipush #56
    //   939: ldc 1081344
    //   941: iastore
    //   942: dup
    //   943: bipush #57
    //   945: iconst_0
    //   946: iastore
    //   947: dup
    //   948: bipush #58
    //   950: ldc -2147450880
    //   952: iastore
    //   953: dup
    //   954: bipush #59
    //   956: ldc 32800
    //   958: iastore
    //   959: dup
    //   960: bipush #60
    //   962: ldc -2147483648
    //   964: iastore
    //   965: dup
    //   966: bipush #61
    //   968: ldc -2146435040
    //   970: iastore
    //   971: dup
    //   972: bipush #62
    //   974: ldc -2146402272
    //   976: iastore
    //   977: dup
    //   978: bipush #63
    //   980: ldc 1081344
    //   982: iastore
    //   983: astore #7
    //   985: bipush #64
    //   987: newarray int
    //   989: dup
    //   990: iconst_0
    //   991: sipush #520
    //   994: iastore
    //   995: dup
    //   996: iconst_1
    //   997: ldc 134349312
    //   999: iastore
    //   1000: dup
    //   1001: iconst_2
    //   1002: iconst_0
    //   1003: iastore
    //   1004: dup
    //   1005: iconst_3
    //   1006: ldc 134348808
    //   1008: iastore
    //   1009: dup
    //   1010: iconst_4
    //   1011: ldc 134218240
    //   1013: iastore
    //   1014: dup
    //   1015: iconst_5
    //   1016: iconst_0
    //   1017: iastore
    //   1018: dup
    //   1019: bipush #6
    //   1021: ldc 131592
    //   1023: iastore
    //   1024: dup
    //   1025: bipush #7
    //   1027: ldc 134218240
    //   1029: iastore
    //   1030: dup
    //   1031: bipush #8
    //   1033: ldc 131080
    //   1035: iastore
    //   1036: dup
    //   1037: bipush #9
    //   1039: ldc 134217736
    //   1041: iastore
    //   1042: dup
    //   1043: bipush #10
    //   1045: ldc 134217736
    //   1047: iastore
    //   1048: dup
    //   1049: bipush #11
    //   1051: ldc 131072
    //   1053: iastore
    //   1054: dup
    //   1055: bipush #12
    //   1057: ldc 134349320
    //   1059: iastore
    //   1060: dup
    //   1061: bipush #13
    //   1063: ldc 131080
    //   1065: iastore
    //   1066: dup
    //   1067: bipush #14
    //   1069: ldc 134348800
    //   1071: iastore
    //   1072: dup
    //   1073: bipush #15
    //   1075: sipush #520
    //   1078: iastore
    //   1079: dup
    //   1080: bipush #16
    //   1082: ldc 134217728
    //   1084: iastore
    //   1085: dup
    //   1086: bipush #17
    //   1088: bipush #8
    //   1090: iastore
    //   1091: dup
    //   1092: bipush #18
    //   1094: ldc 134349312
    //   1096: iastore
    //   1097: dup
    //   1098: bipush #19
    //   1100: sipush #512
    //   1103: iastore
    //   1104: dup
    //   1105: bipush #20
    //   1107: ldc 131584
    //   1109: iastore
    //   1110: dup
    //   1111: bipush #21
    //   1113: ldc 134348800
    //   1115: iastore
    //   1116: dup
    //   1117: bipush #22
    //   1119: ldc 134348808
    //   1121: iastore
    //   1122: dup
    //   1123: bipush #23
    //   1125: ldc 131592
    //   1127: iastore
    //   1128: dup
    //   1129: bipush #24
    //   1131: ldc 134218248
    //   1133: iastore
    //   1134: dup
    //   1135: bipush #25
    //   1137: ldc 131584
    //   1139: iastore
    //   1140: dup
    //   1141: bipush #26
    //   1143: ldc 131072
    //   1145: iastore
    //   1146: dup
    //   1147: bipush #27
    //   1149: ldc 134218248
    //   1151: iastore
    //   1152: dup
    //   1153: bipush #28
    //   1155: bipush #8
    //   1157: iastore
    //   1158: dup
    //   1159: bipush #29
    //   1161: ldc 134349320
    //   1163: iastore
    //   1164: dup
    //   1165: bipush #30
    //   1167: sipush #512
    //   1170: iastore
    //   1171: dup
    //   1172: bipush #31
    //   1174: ldc 134217728
    //   1176: iastore
    //   1177: dup
    //   1178: bipush #32
    //   1180: ldc 134349312
    //   1182: iastore
    //   1183: dup
    //   1184: bipush #33
    //   1186: ldc 134217728
    //   1188: iastore
    //   1189: dup
    //   1190: bipush #34
    //   1192: ldc 131080
    //   1194: iastore
    //   1195: dup
    //   1196: bipush #35
    //   1198: sipush #520
    //   1201: iastore
    //   1202: dup
    //   1203: bipush #36
    //   1205: ldc 131072
    //   1207: iastore
    //   1208: dup
    //   1209: bipush #37
    //   1211: ldc 134349312
    //   1213: iastore
    //   1214: dup
    //   1215: bipush #38
    //   1217: ldc 134218240
    //   1219: iastore
    //   1220: dup
    //   1221: bipush #39
    //   1223: iconst_0
    //   1224: iastore
    //   1225: dup
    //   1226: bipush #40
    //   1228: sipush #512
    //   1231: iastore
    //   1232: dup
    //   1233: bipush #41
    //   1235: ldc 131080
    //   1237: iastore
    //   1238: dup
    //   1239: bipush #42
    //   1241: ldc 134349320
    //   1243: iastore
    //   1244: dup
    //   1245: bipush #43
    //   1247: ldc 134218240
    //   1249: iastore
    //   1250: dup
    //   1251: bipush #44
    //   1253: ldc 134217736
    //   1255: iastore
    //   1256: dup
    //   1257: bipush #45
    //   1259: sipush #512
    //   1262: iastore
    //   1263: dup
    //   1264: bipush #46
    //   1266: iconst_0
    //   1267: iastore
    //   1268: dup
    //   1269: bipush #47
    //   1271: ldc 134348808
    //   1273: iastore
    //   1274: dup
    //   1275: bipush #48
    //   1277: ldc 134218248
    //   1279: iastore
    //   1280: dup
    //   1281: bipush #49
    //   1283: ldc 131072
    //   1285: iastore
    //   1286: dup
    //   1287: bipush #50
    //   1289: ldc 134217728
    //   1291: iastore
    //   1292: dup
    //   1293: bipush #51
    //   1295: ldc 134349320
    //   1297: iastore
    //   1298: dup
    //   1299: bipush #52
    //   1301: bipush #8
    //   1303: iastore
    //   1304: dup
    //   1305: bipush #53
    //   1307: ldc 131592
    //   1309: iastore
    //   1310: dup
    //   1311: bipush #54
    //   1313: ldc 131584
    //   1315: iastore
    //   1316: dup
    //   1317: bipush #55
    //   1319: ldc 134217736
    //   1321: iastore
    //   1322: dup
    //   1323: bipush #56
    //   1325: ldc 134348800
    //   1327: iastore
    //   1328: dup
    //   1329: bipush #57
    //   1331: ldc 134218248
    //   1333: iastore
    //   1334: dup
    //   1335: bipush #58
    //   1337: sipush #520
    //   1340: iastore
    //   1341: dup
    //   1342: bipush #59
    //   1344: ldc 134348800
    //   1346: iastore
    //   1347: dup
    //   1348: bipush #60
    //   1350: ldc 131592
    //   1352: iastore
    //   1353: dup
    //   1354: bipush #61
    //   1356: bipush #8
    //   1358: iastore
    //   1359: dup
    //   1360: bipush #62
    //   1362: ldc 134348808
    //   1364: iastore
    //   1365: dup
    //   1366: bipush #63
    //   1368: ldc 131584
    //   1370: iastore
    //   1371: astore #8
    //   1373: bipush #64
    //   1375: newarray int
    //   1377: dup
    //   1378: iconst_0
    //   1379: ldc 8396801
    //   1381: iastore
    //   1382: dup
    //   1383: iconst_1
    //   1384: sipush #8321
    //   1387: iastore
    //   1388: dup
    //   1389: iconst_2
    //   1390: sipush #8321
    //   1393: iastore
    //   1394: dup
    //   1395: iconst_3
    //   1396: sipush #128
    //   1399: iastore
    //   1400: dup
    //   1401: iconst_4
    //   1402: ldc 8396928
    //   1404: iastore
    //   1405: dup
    //   1406: iconst_5
    //   1407: ldc 8388737
    //   1409: iastore
    //   1410: dup
    //   1411: bipush #6
    //   1413: ldc 8388609
    //   1415: iastore
    //   1416: dup
    //   1417: bipush #7
    //   1419: sipush #8193
    //   1422: iastore
    //   1423: dup
    //   1424: bipush #8
    //   1426: iconst_0
    //   1427: iastore
    //   1428: dup
    //   1429: bipush #9
    //   1431: ldc 8396800
    //   1433: iastore
    //   1434: dup
    //   1435: bipush #10
    //   1437: ldc 8396800
    //   1439: iastore
    //   1440: dup
    //   1441: bipush #11
    //   1443: ldc 8396929
    //   1445: iastore
    //   1446: dup
    //   1447: bipush #12
    //   1449: sipush #129
    //   1452: iastore
    //   1453: dup
    //   1454: bipush #13
    //   1456: iconst_0
    //   1457: iastore
    //   1458: dup
    //   1459: bipush #14
    //   1461: ldc 8388736
    //   1463: iastore
    //   1464: dup
    //   1465: bipush #15
    //   1467: ldc 8388609
    //   1469: iastore
    //   1470: dup
    //   1471: bipush #16
    //   1473: iconst_1
    //   1474: iastore
    //   1475: dup
    //   1476: bipush #17
    //   1478: sipush #8192
    //   1481: iastore
    //   1482: dup
    //   1483: bipush #18
    //   1485: ldc 8388608
    //   1487: iastore
    //   1488: dup
    //   1489: bipush #19
    //   1491: ldc 8396801
    //   1493: iastore
    //   1494: dup
    //   1495: bipush #20
    //   1497: sipush #128
    //   1500: iastore
    //   1501: dup
    //   1502: bipush #21
    //   1504: ldc 8388608
    //   1506: iastore
    //   1507: dup
    //   1508: bipush #22
    //   1510: sipush #8193
    //   1513: iastore
    //   1514: dup
    //   1515: bipush #23
    //   1517: sipush #8320
    //   1520: iastore
    //   1521: dup
    //   1522: bipush #24
    //   1524: ldc 8388737
    //   1526: iastore
    //   1527: dup
    //   1528: bipush #25
    //   1530: iconst_1
    //   1531: iastore
    //   1532: dup
    //   1533: bipush #26
    //   1535: sipush #8320
    //   1538: iastore
    //   1539: dup
    //   1540: bipush #27
    //   1542: ldc 8388736
    //   1544: iastore
    //   1545: dup
    //   1546: bipush #28
    //   1548: sipush #8192
    //   1551: iastore
    //   1552: dup
    //   1553: bipush #29
    //   1555: ldc 8396928
    //   1557: iastore
    //   1558: dup
    //   1559: bipush #30
    //   1561: ldc 8396929
    //   1563: iastore
    //   1564: dup
    //   1565: bipush #31
    //   1567: sipush #129
    //   1570: iastore
    //   1571: dup
    //   1572: bipush #32
    //   1574: ldc 8388736
    //   1576: iastore
    //   1577: dup
    //   1578: bipush #33
    //   1580: ldc 8388609
    //   1582: iastore
    //   1583: dup
    //   1584: bipush #34
    //   1586: ldc 8396800
    //   1588: iastore
    //   1589: dup
    //   1590: bipush #35
    //   1592: ldc 8396929
    //   1594: iastore
    //   1595: dup
    //   1596: bipush #36
    //   1598: sipush #129
    //   1601: iastore
    //   1602: dup
    //   1603: bipush #37
    //   1605: iconst_0
    //   1606: iastore
    //   1607: dup
    //   1608: bipush #38
    //   1610: iconst_0
    //   1611: iastore
    //   1612: dup
    //   1613: bipush #39
    //   1615: ldc 8396800
    //   1617: iastore
    //   1618: dup
    //   1619: bipush #40
    //   1621: sipush #8320
    //   1624: iastore
    //   1625: dup
    //   1626: bipush #41
    //   1628: ldc 8388736
    //   1630: iastore
    //   1631: dup
    //   1632: bipush #42
    //   1634: ldc 8388737
    //   1636: iastore
    //   1637: dup
    //   1638: bipush #43
    //   1640: iconst_1
    //   1641: iastore
    //   1642: dup
    //   1643: bipush #44
    //   1645: ldc 8396801
    //   1647: iastore
    //   1648: dup
    //   1649: bipush #45
    //   1651: sipush #8321
    //   1654: iastore
    //   1655: dup
    //   1656: bipush #46
    //   1658: sipush #8321
    //   1661: iastore
    //   1662: dup
    //   1663: bipush #47
    //   1665: sipush #128
    //   1668: iastore
    //   1669: dup
    //   1670: bipush #48
    //   1672: ldc 8396929
    //   1674: iastore
    //   1675: dup
    //   1676: bipush #49
    //   1678: sipush #129
    //   1681: iastore
    //   1682: dup
    //   1683: bipush #50
    //   1685: iconst_1
    //   1686: iastore
    //   1687: dup
    //   1688: bipush #51
    //   1690: sipush #8192
    //   1693: iastore
    //   1694: dup
    //   1695: bipush #52
    //   1697: ldc 8388609
    //   1699: iastore
    //   1700: dup
    //   1701: bipush #53
    //   1703: sipush #8193
    //   1706: iastore
    //   1707: dup
    //   1708: bipush #54
    //   1710: ldc 8396928
    //   1712: iastore
    //   1713: dup
    //   1714: bipush #55
    //   1716: ldc 8388737
    //   1718: iastore
    //   1719: dup
    //   1720: bipush #56
    //   1722: sipush #8193
    //   1725: iastore
    //   1726: dup
    //   1727: bipush #57
    //   1729: sipush #8320
    //   1732: iastore
    //   1733: dup
    //   1734: bipush #58
    //   1736: ldc 8388608
    //   1738: iastore
    //   1739: dup
    //   1740: bipush #59
    //   1742: ldc 8396801
    //   1744: iastore
    //   1745: dup
    //   1746: bipush #60
    //   1748: sipush #128
    //   1751: iastore
    //   1752: dup
    //   1753: bipush #61
    //   1755: ldc 8388608
    //   1757: iastore
    //   1758: dup
    //   1759: bipush #62
    //   1761: sipush #8192
    //   1764: iastore
    //   1765: dup
    //   1766: bipush #63
    //   1768: ldc 8396928
    //   1770: iastore
    //   1771: astore #9
    //   1773: bipush #64
    //   1775: newarray int
    //   1777: dup
    //   1778: iconst_0
    //   1779: sipush #256
    //   1782: iastore
    //   1783: dup
    //   1784: iconst_1
    //   1785: ldc 34078976
    //   1787: iastore
    //   1788: dup
    //   1789: iconst_2
    //   1790: ldc 34078720
    //   1792: iastore
    //   1793: dup
    //   1794: iconst_3
    //   1795: ldc 1107296512
    //   1797: iastore
    //   1798: dup
    //   1799: iconst_4
    //   1800: ldc 524288
    //   1802: iastore
    //   1803: dup
    //   1804: iconst_5
    //   1805: sipush #256
    //   1808: iastore
    //   1809: dup
    //   1810: bipush #6
    //   1812: ldc 1073741824
    //   1814: iastore
    //   1815: dup
    //   1816: bipush #7
    //   1818: ldc 34078720
    //   1820: iastore
    //   1821: dup
    //   1822: bipush #8
    //   1824: ldc 1074266368
    //   1826: iastore
    //   1827: dup
    //   1828: bipush #9
    //   1830: ldc 524288
    //   1832: iastore
    //   1833: dup
    //   1834: bipush #10
    //   1836: ldc 33554688
    //   1838: iastore
    //   1839: dup
    //   1840: bipush #11
    //   1842: ldc 1074266368
    //   1844: iastore
    //   1845: dup
    //   1846: bipush #12
    //   1848: ldc 1107296512
    //   1850: iastore
    //   1851: dup
    //   1852: bipush #13
    //   1854: ldc 1107820544
    //   1856: iastore
    //   1857: dup
    //   1858: bipush #14
    //   1860: ldc 524544
    //   1862: iastore
    //   1863: dup
    //   1864: bipush #15
    //   1866: ldc 1073741824
    //   1868: iastore
    //   1869: dup
    //   1870: bipush #16
    //   1872: ldc 33554432
    //   1874: iastore
    //   1875: dup
    //   1876: bipush #17
    //   1878: ldc 1074266112
    //   1880: iastore
    //   1881: dup
    //   1882: bipush #18
    //   1884: ldc 1074266112
    //   1886: iastore
    //   1887: dup
    //   1888: bipush #19
    //   1890: iconst_0
    //   1891: iastore
    //   1892: dup
    //   1893: bipush #20
    //   1895: ldc 1073742080
    //   1897: iastore
    //   1898: dup
    //   1899: bipush #21
    //   1901: ldc 1107820800
    //   1903: iastore
    //   1904: dup
    //   1905: bipush #22
    //   1907: ldc 1107820800
    //   1909: iastore
    //   1910: dup
    //   1911: bipush #23
    //   1913: ldc 33554688
    //   1915: iastore
    //   1916: dup
    //   1917: bipush #24
    //   1919: ldc 1107820544
    //   1921: iastore
    //   1922: dup
    //   1923: bipush #25
    //   1925: ldc 1073742080
    //   1927: iastore
    //   1928: dup
    //   1929: bipush #26
    //   1931: iconst_0
    //   1932: iastore
    //   1933: dup
    //   1934: bipush #27
    //   1936: ldc 1107296256
    //   1938: iastore
    //   1939: dup
    //   1940: bipush #28
    //   1942: ldc 34078976
    //   1944: iastore
    //   1945: dup
    //   1946: bipush #29
    //   1948: ldc 33554432
    //   1950: iastore
    //   1951: dup
    //   1952: bipush #30
    //   1954: ldc 1107296256
    //   1956: iastore
    //   1957: dup
    //   1958: bipush #31
    //   1960: ldc 524544
    //   1962: iastore
    //   1963: dup
    //   1964: bipush #32
    //   1966: ldc 524288
    //   1968: iastore
    //   1969: dup
    //   1970: bipush #33
    //   1972: ldc 1107296512
    //   1974: iastore
    //   1975: dup
    //   1976: bipush #34
    //   1978: sipush #256
    //   1981: iastore
    //   1982: dup
    //   1983: bipush #35
    //   1985: ldc 33554432
    //   1987: iastore
    //   1988: dup
    //   1989: bipush #36
    //   1991: ldc 1073741824
    //   1993: iastore
    //   1994: dup
    //   1995: bipush #37
    //   1997: ldc 34078720
    //   1999: iastore
    //   2000: dup
    //   2001: bipush #38
    //   2003: ldc 1107296512
    //   2005: iastore
    //   2006: dup
    //   2007: bipush #39
    //   2009: ldc 1074266368
    //   2011: iastore
    //   2012: dup
    //   2013: bipush #40
    //   2015: ldc 33554688
    //   2017: iastore
    //   2018: dup
    //   2019: bipush #41
    //   2021: ldc 1073741824
    //   2023: iastore
    //   2024: dup
    //   2025: bipush #42
    //   2027: ldc 1107820544
    //   2029: iastore
    //   2030: dup
    //   2031: bipush #43
    //   2033: ldc 34078976
    //   2035: iastore
    //   2036: dup
    //   2037: bipush #44
    //   2039: ldc 1074266368
    //   2041: iastore
    //   2042: dup
    //   2043: bipush #45
    //   2045: sipush #256
    //   2048: iastore
    //   2049: dup
    //   2050: bipush #46
    //   2052: ldc 33554432
    //   2054: iastore
    //   2055: dup
    //   2056: bipush #47
    //   2058: ldc 1107820544
    //   2060: iastore
    //   2061: dup
    //   2062: bipush #48
    //   2064: ldc 1107820800
    //   2066: iastore
    //   2067: dup
    //   2068: bipush #49
    //   2070: ldc 524544
    //   2072: iastore
    //   2073: dup
    //   2074: bipush #50
    //   2076: ldc 1107296256
    //   2078: iastore
    //   2079: dup
    //   2080: bipush #51
    //   2082: ldc 1107820800
    //   2084: iastore
    //   2085: dup
    //   2086: bipush #52
    //   2088: ldc 34078720
    //   2090: iastore
    //   2091: dup
    //   2092: bipush #53
    //   2094: iconst_0
    //   2095: iastore
    //   2096: dup
    //   2097: bipush #54
    //   2099: ldc 1074266112
    //   2101: iastore
    //   2102: dup
    //   2103: bipush #55
    //   2105: ldc 1107296256
    //   2107: iastore
    //   2108: dup
    //   2109: bipush #56
    //   2111: ldc 524544
    //   2113: iastore
    //   2114: dup
    //   2115: bipush #57
    //   2117: ldc 33554688
    //   2119: iastore
    //   2120: dup
    //   2121: bipush #58
    //   2123: ldc 1073742080
    //   2125: iastore
    //   2126: dup
    //   2127: bipush #59
    //   2129: ldc 524288
    //   2131: iastore
    //   2132: dup
    //   2133: bipush #60
    //   2135: iconst_0
    //   2136: iastore
    //   2137: dup
    //   2138: bipush #61
    //   2140: ldc 1074266112
    //   2142: iastore
    //   2143: dup
    //   2144: bipush #62
    //   2146: ldc 34078976
    //   2148: iastore
    //   2149: dup
    //   2150: bipush #63
    //   2152: ldc 1073742080
    //   2154: iastore
    //   2155: astore #10
    //   2157: bipush #64
    //   2159: newarray int
    //   2161: dup
    //   2162: iconst_0
    //   2163: ldc 536870928
    //   2165: iastore
    //   2166: dup
    //   2167: iconst_1
    //   2168: ldc 541065216
    //   2170: iastore
    //   2171: dup
    //   2172: iconst_2
    //   2173: sipush #16384
    //   2176: iastore
    //   2177: dup
    //   2178: iconst_3
    //   2179: ldc 541081616
    //   2181: iastore
    //   2182: dup
    //   2183: iconst_4
    //   2184: ldc 541065216
    //   2186: iastore
    //   2187: dup
    //   2188: iconst_5
    //   2189: bipush #16
    //   2191: iastore
    //   2192: dup
    //   2193: bipush #6
    //   2195: ldc 541081616
    //   2197: iastore
    //   2198: dup
    //   2199: bipush #7
    //   2201: ldc 4194304
    //   2203: iastore
    //   2204: dup
    //   2205: bipush #8
    //   2207: ldc 536887296
    //   2209: iastore
    //   2210: dup
    //   2211: bipush #9
    //   2213: ldc 4210704
    //   2215: iastore
    //   2216: dup
    //   2217: bipush #10
    //   2219: ldc 4194304
    //   2221: iastore
    //   2222: dup
    //   2223: bipush #11
    //   2225: ldc 536870928
    //   2227: iastore
    //   2228: dup
    //   2229: bipush #12
    //   2231: ldc 4194320
    //   2233: iastore
    //   2234: dup
    //   2235: bipush #13
    //   2237: ldc 536887296
    //   2239: iastore
    //   2240: dup
    //   2241: bipush #14
    //   2243: ldc 536870912
    //   2245: iastore
    //   2246: dup
    //   2247: bipush #15
    //   2249: sipush #16400
    //   2252: iastore
    //   2253: dup
    //   2254: bipush #16
    //   2256: iconst_0
    //   2257: iastore
    //   2258: dup
    //   2259: bipush #17
    //   2261: ldc 4194320
    //   2263: iastore
    //   2264: dup
    //   2265: bipush #18
    //   2267: ldc 536887312
    //   2269: iastore
    //   2270: dup
    //   2271: bipush #19
    //   2273: sipush #16384
    //   2276: iastore
    //   2277: dup
    //   2278: bipush #20
    //   2280: ldc 4210688
    //   2282: iastore
    //   2283: dup
    //   2284: bipush #21
    //   2286: ldc 536887312
    //   2288: iastore
    //   2289: dup
    //   2290: bipush #22
    //   2292: bipush #16
    //   2294: iastore
    //   2295: dup
    //   2296: bipush #23
    //   2298: ldc 541065232
    //   2300: iastore
    //   2301: dup
    //   2302: bipush #24
    //   2304: ldc 541065232
    //   2306: iastore
    //   2307: dup
    //   2308: bipush #25
    //   2310: iconst_0
    //   2311: iastore
    //   2312: dup
    //   2313: bipush #26
    //   2315: ldc 4210704
    //   2317: iastore
    //   2318: dup
    //   2319: bipush #27
    //   2321: ldc 541081600
    //   2323: iastore
    //   2324: dup
    //   2325: bipush #28
    //   2327: sipush #16400
    //   2330: iastore
    //   2331: dup
    //   2332: bipush #29
    //   2334: ldc 4210688
    //   2336: iastore
    //   2337: dup
    //   2338: bipush #30
    //   2340: ldc 541081600
    //   2342: iastore
    //   2343: dup
    //   2344: bipush #31
    //   2346: ldc 536870912
    //   2348: iastore
    //   2349: dup
    //   2350: bipush #32
    //   2352: ldc 536887296
    //   2354: iastore
    //   2355: dup
    //   2356: bipush #33
    //   2358: bipush #16
    //   2360: iastore
    //   2361: dup
    //   2362: bipush #34
    //   2364: ldc 541065232
    //   2366: iastore
    //   2367: dup
    //   2368: bipush #35
    //   2370: ldc 4210688
    //   2372: iastore
    //   2373: dup
    //   2374: bipush #36
    //   2376: ldc 541081616
    //   2378: iastore
    //   2379: dup
    //   2380: bipush #37
    //   2382: ldc 4194304
    //   2384: iastore
    //   2385: dup
    //   2386: bipush #38
    //   2388: sipush #16400
    //   2391: iastore
    //   2392: dup
    //   2393: bipush #39
    //   2395: ldc 536870928
    //   2397: iastore
    //   2398: dup
    //   2399: bipush #40
    //   2401: ldc 4194304
    //   2403: iastore
    //   2404: dup
    //   2405: bipush #41
    //   2407: ldc 536887296
    //   2409: iastore
    //   2410: dup
    //   2411: bipush #42
    //   2413: ldc 536870912
    //   2415: iastore
    //   2416: dup
    //   2417: bipush #43
    //   2419: sipush #16400
    //   2422: iastore
    //   2423: dup
    //   2424: bipush #44
    //   2426: ldc 536870928
    //   2428: iastore
    //   2429: dup
    //   2430: bipush #45
    //   2432: ldc 541081616
    //   2434: iastore
    //   2435: dup
    //   2436: bipush #46
    //   2438: ldc 4210688
    //   2440: iastore
    //   2441: dup
    //   2442: bipush #47
    //   2444: ldc 541065216
    //   2446: iastore
    //   2447: dup
    //   2448: bipush #48
    //   2450: ldc 4210704
    //   2452: iastore
    //   2453: dup
    //   2454: bipush #49
    //   2456: ldc 541081600
    //   2458: iastore
    //   2459: dup
    //   2460: bipush #50
    //   2462: iconst_0
    //   2463: iastore
    //   2464: dup
    //   2465: bipush #51
    //   2467: ldc 541065232
    //   2469: iastore
    //   2470: dup
    //   2471: bipush #52
    //   2473: bipush #16
    //   2475: iastore
    //   2476: dup
    //   2477: bipush #53
    //   2479: sipush #16384
    //   2482: iastore
    //   2483: dup
    //   2484: bipush #54
    //   2486: ldc 541065216
    //   2488: iastore
    //   2489: dup
    //   2490: bipush #55
    //   2492: ldc 4210704
    //   2494: iastore
    //   2495: dup
    //   2496: bipush #56
    //   2498: sipush #16384
    //   2501: iastore
    //   2502: dup
    //   2503: bipush #57
    //   2505: ldc 4194320
    //   2507: iastore
    //   2508: dup
    //   2509: bipush #58
    //   2511: ldc 536887312
    //   2513: iastore
    //   2514: dup
    //   2515: bipush #59
    //   2517: iconst_0
    //   2518: iastore
    //   2519: dup
    //   2520: bipush #60
    //   2522: ldc 541081600
    //   2524: iastore
    //   2525: dup
    //   2526: bipush #61
    //   2528: ldc 536870912
    //   2530: iastore
    //   2531: dup
    //   2532: bipush #62
    //   2534: ldc 4194320
    //   2536: iastore
    //   2537: dup
    //   2538: bipush #63
    //   2540: ldc 536887312
    //   2542: iastore
    //   2543: astore #11
    //   2545: bipush #64
    //   2547: newarray int
    //   2549: dup
    //   2550: iconst_0
    //   2551: ldc 2097152
    //   2553: iastore
    //   2554: dup
    //   2555: iconst_1
    //   2556: ldc 69206018
    //   2558: iastore
    //   2559: dup
    //   2560: iconst_2
    //   2561: ldc 67110914
    //   2563: iastore
    //   2564: dup
    //   2565: iconst_3
    //   2566: iconst_0
    //   2567: iastore
    //   2568: dup
    //   2569: iconst_4
    //   2570: sipush #2048
    //   2573: iastore
    //   2574: dup
    //   2575: iconst_5
    //   2576: ldc 67110914
    //   2578: iastore
    //   2579: dup
    //   2580: bipush #6
    //   2582: ldc 2099202
    //   2584: iastore
    //   2585: dup
    //   2586: bipush #7
    //   2588: ldc 69208064
    //   2590: iastore
    //   2591: dup
    //   2592: bipush #8
    //   2594: ldc 69208066
    //   2596: iastore
    //   2597: dup
    //   2598: bipush #9
    //   2600: ldc 2097152
    //   2602: iastore
    //   2603: dup
    //   2604: bipush #10
    //   2606: iconst_0
    //   2607: iastore
    //   2608: dup
    //   2609: bipush #11
    //   2611: ldc 67108866
    //   2613: iastore
    //   2614: dup
    //   2615: bipush #12
    //   2617: iconst_2
    //   2618: iastore
    //   2619: dup
    //   2620: bipush #13
    //   2622: ldc 67108864
    //   2624: iastore
    //   2625: dup
    //   2626: bipush #14
    //   2628: ldc 69206018
    //   2630: iastore
    //   2631: dup
    //   2632: bipush #15
    //   2634: sipush #2050
    //   2637: iastore
    //   2638: dup
    //   2639: bipush #16
    //   2641: ldc 67110912
    //   2643: iastore
    //   2644: dup
    //   2645: bipush #17
    //   2647: ldc 2099202
    //   2649: iastore
    //   2650: dup
    //   2651: bipush #18
    //   2653: ldc 2097154
    //   2655: iastore
    //   2656: dup
    //   2657: bipush #19
    //   2659: ldc 67110912
    //   2661: iastore
    //   2662: dup
    //   2663: bipush #20
    //   2665: ldc 67108866
    //   2667: iastore
    //   2668: dup
    //   2669: bipush #21
    //   2671: ldc 69206016
    //   2673: iastore
    //   2674: dup
    //   2675: bipush #22
    //   2677: ldc 69208064
    //   2679: iastore
    //   2680: dup
    //   2681: bipush #23
    //   2683: ldc 2097154
    //   2685: iastore
    //   2686: dup
    //   2687: bipush #24
    //   2689: ldc 69206016
    //   2691: iastore
    //   2692: dup
    //   2693: bipush #25
    //   2695: sipush #2048
    //   2698: iastore
    //   2699: dup
    //   2700: bipush #26
    //   2702: sipush #2050
    //   2705: iastore
    //   2706: dup
    //   2707: bipush #27
    //   2709: ldc 69208066
    //   2711: iastore
    //   2712: dup
    //   2713: bipush #28
    //   2715: ldc 2099200
    //   2717: iastore
    //   2718: dup
    //   2719: bipush #29
    //   2721: iconst_2
    //   2722: iastore
    //   2723: dup
    //   2724: bipush #30
    //   2726: ldc 67108864
    //   2728: iastore
    //   2729: dup
    //   2730: bipush #31
    //   2732: ldc 2099200
    //   2734: iastore
    //   2735: dup
    //   2736: bipush #32
    //   2738: ldc 67108864
    //   2740: iastore
    //   2741: dup
    //   2742: bipush #33
    //   2744: ldc 2099200
    //   2746: iastore
    //   2747: dup
    //   2748: bipush #34
    //   2750: ldc 2097152
    //   2752: iastore
    //   2753: dup
    //   2754: bipush #35
    //   2756: ldc 67110914
    //   2758: iastore
    //   2759: dup
    //   2760: bipush #36
    //   2762: ldc 67110914
    //   2764: iastore
    //   2765: dup
    //   2766: bipush #37
    //   2768: ldc 69206018
    //   2770: iastore
    //   2771: dup
    //   2772: bipush #38
    //   2774: ldc 69206018
    //   2776: iastore
    //   2777: dup
    //   2778: bipush #39
    //   2780: iconst_2
    //   2781: iastore
    //   2782: dup
    //   2783: bipush #40
    //   2785: ldc 2097154
    //   2787: iastore
    //   2788: dup
    //   2789: bipush #41
    //   2791: ldc 67108864
    //   2793: iastore
    //   2794: dup
    //   2795: bipush #42
    //   2797: ldc 67110912
    //   2799: iastore
    //   2800: dup
    //   2801: bipush #43
    //   2803: ldc 2097152
    //   2805: iastore
    //   2806: dup
    //   2807: bipush #44
    //   2809: ldc 69208064
    //   2811: iastore
    //   2812: dup
    //   2813: bipush #45
    //   2815: sipush #2050
    //   2818: iastore
    //   2819: dup
    //   2820: bipush #46
    //   2822: ldc 2099202
    //   2824: iastore
    //   2825: dup
    //   2826: bipush #47
    //   2828: ldc 69208064
    //   2830: iastore
    //   2831: dup
    //   2832: bipush #48
    //   2834: sipush #2050
    //   2837: iastore
    //   2838: dup
    //   2839: bipush #49
    //   2841: ldc 67108866
    //   2843: iastore
    //   2844: dup
    //   2845: bipush #50
    //   2847: ldc 69208066
    //   2849: iastore
    //   2850: dup
    //   2851: bipush #51
    //   2853: ldc 69206016
    //   2855: iastore
    //   2856: dup
    //   2857: bipush #52
    //   2859: ldc 2099200
    //   2861: iastore
    //   2862: dup
    //   2863: bipush #53
    //   2865: iconst_0
    //   2866: iastore
    //   2867: dup
    //   2868: bipush #54
    //   2870: iconst_2
    //   2871: iastore
    //   2872: dup
    //   2873: bipush #55
    //   2875: ldc 69208066
    //   2877: iastore
    //   2878: dup
    //   2879: bipush #56
    //   2881: iconst_0
    //   2882: iastore
    //   2883: dup
    //   2884: bipush #57
    //   2886: ldc 2099202
    //   2888: iastore
    //   2889: dup
    //   2890: bipush #58
    //   2892: ldc 69206016
    //   2894: iastore
    //   2895: dup
    //   2896: bipush #59
    //   2898: sipush #2048
    //   2901: iastore
    //   2902: dup
    //   2903: bipush #60
    //   2905: ldc 67108866
    //   2907: iastore
    //   2908: dup
    //   2909: bipush #61
    //   2911: ldc 67110912
    //   2913: iastore
    //   2914: dup
    //   2915: bipush #62
    //   2917: sipush #2048
    //   2920: iastore
    //   2921: dup
    //   2922: bipush #63
    //   2924: ldc 2097154
    //   2926: iastore
    //   2927: astore #12
    //   2929: bipush #64
    //   2931: newarray int
    //   2933: dup
    //   2934: iconst_0
    //   2935: ldc 268439616
    //   2937: iastore
    //   2938: dup
    //   2939: iconst_1
    //   2940: sipush #4096
    //   2943: iastore
    //   2944: dup
    //   2945: iconst_2
    //   2946: ldc 262144
    //   2948: iastore
    //   2949: dup
    //   2950: iconst_3
    //   2951: ldc 268701760
    //   2953: iastore
    //   2954: dup
    //   2955: iconst_4
    //   2956: ldc 268435456
    //   2958: iastore
    //   2959: dup
    //   2960: iconst_5
    //   2961: ldc 268439616
    //   2963: iastore
    //   2964: dup
    //   2965: bipush #6
    //   2967: bipush #64
    //   2969: iastore
    //   2970: dup
    //   2971: bipush #7
    //   2973: ldc 268435456
    //   2975: iastore
    //   2976: dup
    //   2977: bipush #8
    //   2979: ldc 262208
    //   2981: iastore
    //   2982: dup
    //   2983: bipush #9
    //   2985: ldc 268697600
    //   2987: iastore
    //   2988: dup
    //   2989: bipush #10
    //   2991: ldc 268701760
    //   2993: iastore
    //   2994: dup
    //   2995: bipush #11
    //   2997: ldc 266240
    //   2999: iastore
    //   3000: dup
    //   3001: bipush #12
    //   3003: ldc 268701696
    //   3005: iastore
    //   3006: dup
    //   3007: bipush #13
    //   3009: ldc 266304
    //   3011: iastore
    //   3012: dup
    //   3013: bipush #14
    //   3015: sipush #4096
    //   3018: iastore
    //   3019: dup
    //   3020: bipush #15
    //   3022: bipush #64
    //   3024: iastore
    //   3025: dup
    //   3026: bipush #16
    //   3028: ldc 268697600
    //   3030: iastore
    //   3031: dup
    //   3032: bipush #17
    //   3034: ldc 268435520
    //   3036: iastore
    //   3037: dup
    //   3038: bipush #18
    //   3040: ldc 268439552
    //   3042: iastore
    //   3043: dup
    //   3044: bipush #19
    //   3046: sipush #4160
    //   3049: iastore
    //   3050: dup
    //   3051: bipush #20
    //   3053: ldc 266240
    //   3055: iastore
    //   3056: dup
    //   3057: bipush #21
    //   3059: ldc 262208
    //   3061: iastore
    //   3062: dup
    //   3063: bipush #22
    //   3065: ldc 268697664
    //   3067: iastore
    //   3068: dup
    //   3069: bipush #23
    //   3071: ldc 268701696
    //   3073: iastore
    //   3074: dup
    //   3075: bipush #24
    //   3077: sipush #4160
    //   3080: iastore
    //   3081: dup
    //   3082: bipush #25
    //   3084: iconst_0
    //   3085: iastore
    //   3086: dup
    //   3087: bipush #26
    //   3089: iconst_0
    //   3090: iastore
    //   3091: dup
    //   3092: bipush #27
    //   3094: ldc 268697664
    //   3096: iastore
    //   3097: dup
    //   3098: bipush #28
    //   3100: ldc 268435520
    //   3102: iastore
    //   3103: dup
    //   3104: bipush #29
    //   3106: ldc 268439552
    //   3108: iastore
    //   3109: dup
    //   3110: bipush #30
    //   3112: ldc 266304
    //   3114: iastore
    //   3115: dup
    //   3116: bipush #31
    //   3118: ldc 262144
    //   3120: iastore
    //   3121: dup
    //   3122: bipush #32
    //   3124: ldc 266304
    //   3126: iastore
    //   3127: dup
    //   3128: bipush #33
    //   3130: ldc 262144
    //   3132: iastore
    //   3133: dup
    //   3134: bipush #34
    //   3136: ldc 268701696
    //   3138: iastore
    //   3139: dup
    //   3140: bipush #35
    //   3142: sipush #4096
    //   3145: iastore
    //   3146: dup
    //   3147: bipush #36
    //   3149: bipush #64
    //   3151: iastore
    //   3152: dup
    //   3153: bipush #37
    //   3155: ldc 268697664
    //   3157: iastore
    //   3158: dup
    //   3159: bipush #38
    //   3161: sipush #4096
    //   3164: iastore
    //   3165: dup
    //   3166: bipush #39
    //   3168: ldc 266304
    //   3170: iastore
    //   3171: dup
    //   3172: bipush #40
    //   3174: ldc 268439552
    //   3176: iastore
    //   3177: dup
    //   3178: bipush #41
    //   3180: bipush #64
    //   3182: iastore
    //   3183: dup
    //   3184: bipush #42
    //   3186: ldc 268435520
    //   3188: iastore
    //   3189: dup
    //   3190: bipush #43
    //   3192: ldc 268697600
    //   3194: iastore
    //   3195: dup
    //   3196: bipush #44
    //   3198: ldc 268697664
    //   3200: iastore
    //   3201: dup
    //   3202: bipush #45
    //   3204: ldc 268435456
    //   3206: iastore
    //   3207: dup
    //   3208: bipush #46
    //   3210: ldc 262144
    //   3212: iastore
    //   3213: dup
    //   3214: bipush #47
    //   3216: ldc 268439616
    //   3218: iastore
    //   3219: dup
    //   3220: bipush #48
    //   3222: iconst_0
    //   3223: iastore
    //   3224: dup
    //   3225: bipush #49
    //   3227: ldc 268701760
    //   3229: iastore
    //   3230: dup
    //   3231: bipush #50
    //   3233: ldc 262208
    //   3235: iastore
    //   3236: dup
    //   3237: bipush #51
    //   3239: ldc 268435520
    //   3241: iastore
    //   3242: dup
    //   3243: bipush #52
    //   3245: ldc 268697600
    //   3247: iastore
    //   3248: dup
    //   3249: bipush #53
    //   3251: ldc 268439552
    //   3253: iastore
    //   3254: dup
    //   3255: bipush #54
    //   3257: ldc 268439616
    //   3259: iastore
    //   3260: dup
    //   3261: bipush #55
    //   3263: iconst_0
    //   3264: iastore
    //   3265: dup
    //   3266: bipush #56
    //   3268: ldc 268701760
    //   3270: iastore
    //   3271: dup
    //   3272: bipush #57
    //   3274: ldc 266240
    //   3276: iastore
    //   3277: dup
    //   3278: bipush #58
    //   3280: ldc 266240
    //   3282: iastore
    //   3283: dup
    //   3284: bipush #59
    //   3286: sipush #4160
    //   3289: iastore
    //   3290: dup
    //   3291: bipush #60
    //   3293: sipush #4160
    //   3296: iastore
    //   3297: dup
    //   3298: bipush #61
    //   3300: ldc 262208
    //   3302: iastore
    //   3303: dup
    //   3304: bipush #62
    //   3306: ldc 268435456
    //   3308: iastore
    //   3309: dup
    //   3310: bipush #63
    //   3312: ldc 268701696
    //   3314: iastore
    //   3315: astore #13
    //   3317: aload_3
    //   3318: arraylength
    //   3319: istore #14
    //   3321: iload #14
    //   3323: bipush #8
    //   3325: irem
    //   3326: ifeq -> 3350
    //   3329: new java/lang/Exception
    //   3332: dup
    //   3333: sipush #844
    //   3336: sipush #-2377
    //   3339: invokestatic a : (II)Ljava/lang/String;
    //   3342: invokespecial <init> : (Ljava/lang/String;)V
    //   3345: athrow
    //   3346: invokestatic a : (Ljava/lang/Throwable;)Ljava/lang/Throwable;
    //   3349: athrow
    //   3350: iconst_2
    //   3351: newarray int
    //   3353: astore #15
    //   3355: iload #14
    //   3357: newarray byte
    //   3359: astore #16
    //   3361: iload #14
    //   3363: bipush #8
    //   3365: idiv
    //   3366: istore #17
    //   3368: iconst_0
    //   3369: istore #18
    //   3371: iload #18
    //   3373: iload #17
    //   3375: if_icmpge -> 4289
    //   3378: iload #18
    //   3380: bipush #8
    //   3382: imul
    //   3383: istore #19
    //   3385: iconst_0
    //   3386: istore #20
    //   3388: iload #20
    //   3390: iconst_2
    //   3391: if_icmpge -> 3476
    //   3394: aload #15
    //   3396: iload #20
    //   3398: aload_3
    //   3399: iload #19
    //   3401: iload #20
    //   3403: iconst_4
    //   3404: imul
    //   3405: iadd
    //   3406: baload
    //   3407: sipush #255
    //   3410: iand
    //   3411: bipush #24
    //   3413: ishl
    //   3414: aload_3
    //   3415: iload #19
    //   3417: iload #20
    //   3419: iconst_4
    //   3420: imul
    //   3421: iadd
    //   3422: iconst_1
    //   3423: iadd
    //   3424: baload
    //   3425: sipush #255
    //   3428: iand
    //   3429: bipush #16
    //   3431: ishl
    //   3432: ior
    //   3433: aload_3
    //   3434: iload #19
    //   3436: iload #20
    //   3438: iconst_4
    //   3439: imul
    //   3440: iadd
    //   3441: iconst_2
    //   3442: iadd
    //   3443: baload
    //   3444: sipush #255
    //   3447: iand
    //   3448: bipush #8
    //   3450: ishl
    //   3451: ior
    //   3452: aload_3
    //   3453: iload #19
    //   3455: iload #20
    //   3457: iconst_4
    //   3458: imul
    //   3459: iadd
    //   3460: iconst_3
    //   3461: iadd
    //   3462: baload
    //   3463: sipush #255
    //   3466: iand
    //   3467: ior
    //   3468: iastore
    //   3469: iinc #20, 1
    //   3472: iload_2
    //   3473: ifeq -> 3388
    //   3476: iconst_0
    //   3477: istore #25
    //   3479: aload #15
    //   3481: iconst_0
    //   3482: iaload
    //   3483: istore #23
    //   3485: aload #15
    //   3487: iconst_1
    //   3488: iaload
    //   3489: istore #22
    //   3491: iload #23
    //   3493: iconst_4
    //   3494: iushr
    //   3495: iload #22
    //   3497: ixor
    //   3498: ldc 252645135
    //   3500: iand
    //   3501: istore #21
    //   3503: iload #22
    //   3505: iload #21
    //   3507: ixor
    //   3508: istore #22
    //   3510: iload #23
    //   3512: iload #21
    //   3514: iconst_4
    //   3515: ishl
    //   3516: ixor
    //   3517: istore #23
    //   3519: iload #23
    //   3521: bipush #16
    //   3523: iushr
    //   3524: iload #22
    //   3526: ixor
    //   3527: ldc 65535
    //   3529: iand
    //   3530: istore #21
    //   3532: iload #22
    //   3534: iload #21
    //   3536: ixor
    //   3537: istore #22
    //   3539: iload #23
    //   3541: iload #21
    //   3543: bipush #16
    //   3545: ishl
    //   3546: ixor
    //   3547: istore #23
    //   3549: iload #22
    //   3551: iconst_2
    //   3552: iushr
    //   3553: iload #23
    //   3555: ixor
    //   3556: ldc 858993459
    //   3558: iand
    //   3559: istore #21
    //   3561: iload #23
    //   3563: iload #21
    //   3565: ixor
    //   3566: istore #23
    //   3568: iload #22
    //   3570: iload #21
    //   3572: iconst_2
    //   3573: ishl
    //   3574: ixor
    //   3575: istore #22
    //   3577: iload #22
    //   3579: bipush #8
    //   3581: iushr
    //   3582: iload #23
    //   3584: ixor
    //   3585: ldc 16711935
    //   3587: iand
    //   3588: istore #21
    //   3590: iload #23
    //   3592: iload #21
    //   3594: ixor
    //   3595: istore #23
    //   3597: iload #22
    //   3599: iload #21
    //   3601: bipush #8
    //   3603: ishl
    //   3604: ixor
    //   3605: istore #22
    //   3607: iload #22
    //   3609: iconst_1
    //   3610: ishl
    //   3611: iload #22
    //   3613: bipush #31
    //   3615: iushr
    //   3616: iconst_1
    //   3617: iand
    //   3618: ior
    //   3619: istore #22
    //   3621: iload #23
    //   3623: iload #22
    //   3625: ixor
    //   3626: ldc -1431655766
    //   3628: iand
    //   3629: istore #21
    //   3631: iload #23
    //   3633: iload #21
    //   3635: ixor
    //   3636: istore #23
    //   3638: iload #22
    //   3640: iload #21
    //   3642: ixor
    //   3643: istore #22
    //   3645: iload #23
    //   3647: iconst_1
    //   3648: ishl
    //   3649: iload #23
    //   3651: bipush #31
    //   3653: iushr
    //   3654: iconst_1
    //   3655: iand
    //   3656: ior
    //   3657: istore #23
    //   3659: iconst_0
    //   3660: istore #24
    //   3662: iload #24
    //   3664: bipush #8
    //   3666: if_icmpge -> 4004
    //   3669: iload #22
    //   3671: bipush #28
    //   3673: ishl
    //   3674: iload #22
    //   3676: iconst_4
    //   3677: iushr
    //   3678: ior
    //   3679: istore #21
    //   3681: iload #21
    //   3683: aload #5
    //   3685: iload #25
    //   3687: iinc #25, 1
    //   3690: iaload
    //   3691: ixor
    //   3692: istore #21
    //   3694: aload #12
    //   3696: iload #21
    //   3698: bipush #63
    //   3700: iand
    //   3701: iaload
    //   3702: istore #20
    //   3704: iload #20
    //   3706: aload #10
    //   3708: iload #21
    //   3710: bipush #8
    //   3712: iushr
    //   3713: bipush #63
    //   3715: iand
    //   3716: iaload
    //   3717: ior
    //   3718: istore #20
    //   3720: iload #20
    //   3722: aload #8
    //   3724: iload #21
    //   3726: bipush #16
    //   3728: iushr
    //   3729: bipush #63
    //   3731: iand
    //   3732: iaload
    //   3733: ior
    //   3734: istore #20
    //   3736: iload #20
    //   3738: aload #6
    //   3740: iload #21
    //   3742: bipush #24
    //   3744: iushr
    //   3745: bipush #63
    //   3747: iand
    //   3748: iaload
    //   3749: ior
    //   3750: istore #20
    //   3752: iload #22
    //   3754: aload #5
    //   3756: iload #25
    //   3758: iinc #25, 1
    //   3761: iaload
    //   3762: ixor
    //   3763: istore #21
    //   3765: iload #20
    //   3767: aload #13
    //   3769: iload #21
    //   3771: bipush #63
    //   3773: iand
    //   3774: iaload
    //   3775: ior
    //   3776: istore #20
    //   3778: iload #20
    //   3780: aload #11
    //   3782: iload #21
    //   3784: bipush #8
    //   3786: iushr
    //   3787: bipush #63
    //   3789: iand
    //   3790: iaload
    //   3791: ior
    //   3792: istore #20
    //   3794: iload #20
    //   3796: aload #9
    //   3798: iload #21
    //   3800: bipush #16
    //   3802: iushr
    //   3803: bipush #63
    //   3805: iand
    //   3806: iaload
    //   3807: ior
    //   3808: istore #20
    //   3810: iload #20
    //   3812: aload #7
    //   3814: iload #21
    //   3816: bipush #24
    //   3818: iushr
    //   3819: bipush #63
    //   3821: iand
    //   3822: iaload
    //   3823: ior
    //   3824: istore #20
    //   3826: iload #23
    //   3828: iload #20
    //   3830: ixor
    //   3831: istore #23
    //   3833: iload #23
    //   3835: bipush #28
    //   3837: ishl
    //   3838: iload #23
    //   3840: iconst_4
    //   3841: iushr
    //   3842: ior
    //   3843: istore #21
    //   3845: iload #21
    //   3847: aload #5
    //   3849: iload #25
    //   3851: iinc #25, 1
    //   3854: iaload
    //   3855: ixor
    //   3856: istore #21
    //   3858: aload #12
    //   3860: iload #21
    //   3862: bipush #63
    //   3864: iand
    //   3865: iaload
    //   3866: istore #20
    //   3868: iload #20
    //   3870: aload #10
    //   3872: iload #21
    //   3874: bipush #8
    //   3876: iushr
    //   3877: bipush #63
    //   3879: iand
    //   3880: iaload
    //   3881: ior
    //   3882: istore #20
    //   3884: iload #20
    //   3886: aload #8
    //   3888: iload #21
    //   3890: bipush #16
    //   3892: iushr
    //   3893: bipush #63
    //   3895: iand
    //   3896: iaload
    //   3897: ior
    //   3898: istore #20
    //   3900: iload #20
    //   3902: aload #6
    //   3904: iload #21
    //   3906: bipush #24
    //   3908: iushr
    //   3909: bipush #63
    //   3911: iand
    //   3912: iaload
    //   3913: ior
    //   3914: istore #20
    //   3916: iload #23
    //   3918: aload #5
    //   3920: iload #25
    //   3922: iinc #25, 1
    //   3925: iaload
    //   3926: ixor
    //   3927: istore #21
    //   3929: iload #20
    //   3931: aload #13
    //   3933: iload #21
    //   3935: bipush #63
    //   3937: iand
    //   3938: iaload
    //   3939: ior
    //   3940: istore #20
    //   3942: iload #20
    //   3944: aload #11
    //   3946: iload #21
    //   3948: bipush #8
    //   3950: iushr
    //   3951: bipush #63
    //   3953: iand
    //   3954: iaload
    //   3955: ior
    //   3956: istore #20
    //   3958: iload #20
    //   3960: aload #9
    //   3962: iload #21
    //   3964: bipush #16
    //   3966: iushr
    //   3967: bipush #63
    //   3969: iand
    //   3970: iaload
    //   3971: ior
    //   3972: istore #20
    //   3974: iload #20
    //   3976: aload #7
    //   3978: iload #21
    //   3980: bipush #24
    //   3982: iushr
    //   3983: bipush #63
    //   3985: iand
    //   3986: iaload
    //   3987: ior
    //   3988: istore #20
    //   3990: iload #22
    //   3992: iload #20
    //   3994: ixor
    //   3995: istore #22
    //   3997: iinc #24, 1
    //   4000: iload_2
    //   4001: ifeq -> 3662
    //   4004: iload #22
    //   4006: bipush #31
    //   4008: ishl
    //   4009: iload #22
    //   4011: iconst_1
    //   4012: iushr
    //   4013: ior
    //   4014: istore #22
    //   4016: iload #23
    //   4018: iload #22
    //   4020: ixor
    //   4021: ldc -1431655766
    //   4023: iand
    //   4024: istore #21
    //   4026: iload #23
    //   4028: iload #21
    //   4030: ixor
    //   4031: istore #23
    //   4033: iload #22
    //   4035: iload #21
    //   4037: ixor
    //   4038: istore #22
    //   4040: iload #23
    //   4042: bipush #31
    //   4044: ishl
    //   4045: iload #23
    //   4047: iconst_1
    //   4048: iushr
    //   4049: ior
    //   4050: istore #23
    //   4052: iload #23
    //   4054: bipush #8
    //   4056: iushr
    //   4057: iload #22
    //   4059: ixor
    //   4060: ldc 16711935
    //   4062: iand
    //   4063: istore #21
    //   4065: iload #22
    //   4067: iload #21
    //   4069: ixor
    //   4070: istore #22
    //   4072: iload #23
    //   4074: iload #21
    //   4076: bipush #8
    //   4078: ishl
    //   4079: ixor
    //   4080: istore #23
    //   4082: iload #23
    //   4084: iconst_2
    //   4085: iushr
    //   4086: iload #22
    //   4088: ixor
    //   4089: ldc 858993459
    //   4091: iand
    //   4092: istore #21
    //   4094: iload #22
    //   4096: iload #21
    //   4098: ixor
    //   4099: istore #22
    //   4101: iload #23
    //   4103: iload #21
    //   4105: iconst_2
    //   4106: ishl
    //   4107: ixor
    //   4108: istore #23
    //   4110: iload #22
    //   4112: bipush #16
    //   4114: iushr
    //   4115: iload #23
    //   4117: ixor
    //   4118: ldc 65535
    //   4120: iand
    //   4121: istore #21
    //   4123: iload #23
    //   4125: iload #21
    //   4127: ixor
    //   4128: istore #23
    //   4130: iload #22
    //   4132: iload #21
    //   4134: bipush #16
    //   4136: ishl
    //   4137: ixor
    //   4138: istore #22
    //   4140: iload #22
    //   4142: iconst_4
    //   4143: iushr
    //   4144: iload #23
    //   4146: ixor
    //   4147: ldc 252645135
    //   4149: iand
    //   4150: istore #21
    //   4152: iload #23
    //   4154: iload #21
    //   4156: ixor
    //   4157: istore #23
    //   4159: iload #22
    //   4161: iload #21
    //   4163: iconst_4
    //   4164: ishl
    //   4165: ixor
    //   4166: istore #22
    //   4168: aload #15
    //   4170: iconst_0
    //   4171: iload #22
    //   4173: iastore
    //   4174: aload #15
    //   4176: iconst_1
    //   4177: iload #23
    //   4179: iastore
    //   4180: iload #18
    //   4182: bipush #8
    //   4184: imul
    //   4185: istore #26
    //   4187: iconst_0
    //   4188: istore #27
    //   4190: iload #27
    //   4192: iconst_2
    //   4193: if_icmpge -> 4282
    //   4196: aload #16
    //   4198: iload #26
    //   4200: iload #27
    //   4202: iconst_4
    //   4203: imul
    //   4204: iadd
    //   4205: aload #15
    //   4207: iload #27
    //   4209: iaload
    //   4210: bipush #24
    //   4212: iushr
    //   4213: i2b
    //   4214: bastore
    //   4215: aload #16
    //   4217: iload #26
    //   4219: iload #27
    //   4221: iconst_4
    //   4222: imul
    //   4223: iadd
    //   4224: iconst_1
    //   4225: iadd
    //   4226: aload #15
    //   4228: iload #27
    //   4230: iaload
    //   4231: bipush #16
    //   4233: iushr
    //   4234: i2b
    //   4235: bastore
    //   4236: aload #16
    //   4238: iload #26
    //   4240: iload #27
    //   4242: iconst_4
    //   4243: imul
    //   4244: iadd
    //   4245: iconst_2
    //   4246: iadd
    //   4247: aload #15
    //   4249: iload #27
    //   4251: iaload
    //   4252: bipush #8
    //   4254: iushr
    //   4255: i2b
    //   4256: bastore
    //   4257: aload #16
    //   4259: iload #26
    //   4261: iload #27
    //   4263: iconst_4
    //   4264: imul
    //   4265: iadd
    //   4266: iconst_3
    //   4267: iadd
    //   4268: aload #15
    //   4270: iload #27
    //   4272: iaload
    //   4273: i2b
    //   4274: bastore
    //   4275: iinc #27, 1
    //   4278: iload_2
    //   4279: ifeq -> 4190
    //   4282: iinc #18, 1
    //   4285: iload_2
    //   4286: ifeq -> 3371
    //   4289: aload #16
    //   4291: aload #16
    //   4293: arraylength
    //   4294: iconst_1
    //   4295: isub
    //   4296: baload
    //   4297: istore #18
    //   4299: aload #16
    //   4301: arraylength
    //   4302: iload #18
    //   4304: isub
    //   4305: newarray byte
    //   4307: astore #4
    //   4309: aload #16
    //   4311: arraylength
    //   4312: aload #4
    //   4314: arraylength
    //   4315: if_icmpge -> 4339
    //   4318: new java/lang/Exception
    //   4321: dup
    //   4322: sipush #846
    //   4325: sipush #26894
    //   4328: invokestatic a : (II)Ljava/lang/String;
    //   4331: invokespecial <init> : (Ljava/lang/String;)V
    //   4334: athrow
    //   4335: invokestatic a : (Ljava/lang/Throwable;)Ljava/lang/Throwable;
    //   4338: athrow
    //   4339: iconst_0
    //   4340: istore #19
    //   4342: iload #19
    //   4344: aload #4
    //   4346: arraylength
    //   4347: if_icmpge -> 4367
    //   4350: aload #4
    //   4352: iload #19
    //   4354: aload #16
    //   4356: iload #19
    //   4358: baload
    //   4359: bastore
    //   4360: iinc #19, 1
    //   4363: iload_2
    //   4364: ifeq -> 4342
    //   4367: new java/math/BigInteger
    //   4370: dup
    //   4371: aload #4
    //   4373: invokespecial <init> : ([B)V
    //   4376: invokevirtual abs : ()Ljava/math/BigInteger;
    //   4379: putstatic burp/Zlg1.ZH : Ljava/lang/Object;
    //   4382: sipush #833
    //   4385: sipush #-24843
    //   4388: invokestatic a : (II)Ljava/lang/String;
    //   4391: iconst_1
    //   4392: ldc burp/Zxtc
    //   4394: invokevirtual getClassLoader : ()Ljava/lang/ClassLoader;
    //   4397: invokestatic forName : (Ljava/lang/String;ZLjava/lang/ClassLoader;)Ljava/lang/Class;
    //   4400: invokevirtual getDeclaredFields : ()[Ljava/lang/reflect/Field;
    //   4403: astore_3
    //   4404: aload_3
    //   4405: arraylength
    //   4406: istore #4
    //   4408: iconst_0
    //   4409: istore #5
    //   4411: iload #5
    //   4413: iload #4
    //   4415: if_icmpge -> 4552
    //   4418: aload_3
    //   4419: iload #5
    //   4421: aaload
    //   4422: astore #6
    //   4424: aload #6
    //   4426: invokevirtual getModifiers : ()I
    //   4429: invokestatic isStatic : (I)Z
    //   4432: ifne -> 4442
    //   4435: goto -> 4545
    //   4438: invokestatic a : (Ljava/lang/Throwable;)Ljava/lang/Throwable;
    //   4441: athrow
    //   4442: aload #6
    //   4444: invokevirtual getType : ()Ljava/lang/Class;
    //   4447: astore #7
    //   4449: aload #7
    //   4451: ifnull -> 4532
    //   4454: aload #7
    //   4456: invokevirtual isPrimitive : ()Z
    //   4459: ifne -> 4532
    //   4462: goto -> 4469
    //   4465: invokestatic a : (Ljava/lang/Throwable;)Ljava/lang/Throwable;
    //   4468: athrow
    //   4469: aload #7
    //   4471: invokevirtual getPackage : ()Ljava/lang/Package;
    //   4474: ifnull -> 4532
    //   4477: goto -> 4484
    //   4480: invokestatic a : (Ljava/lang/Throwable;)Ljava/lang/Throwable;
    //   4483: athrow
    //   4484: aload #7
    //   4486: invokevirtual getPackage : ()Ljava/lang/Package;
    //   4489: invokevirtual getName : ()Ljava/lang/String;
    //   4492: ifnull -> 4532
    //   4495: goto -> 4502
    //   4498: invokestatic a : (Ljava/lang/Throwable;)Ljava/lang/Throwable;
    //   4501: athrow
    //   4502: aload #7
    //   4504: invokevirtual getPackage : ()Ljava/lang/Package;
    //   4507: invokevirtual getName : ()Ljava/lang/String;
    //   4510: sipush #847
    //   4513: sipush #-25075
    //   4516: invokestatic a : (II)Ljava/lang/String;
    //   4519: invokevirtual startsWith : (Ljava/lang/String;)Z
    //   4522: ifne -> 4532
    //   4525: goto -> 4532
    //   4528: invokestatic a : (Ljava/lang/Throwable;)Ljava/lang/Throwable;
    //   4531: athrow
    //   4532: aload #6
    //   4534: iconst_1
    //   4535: invokevirtual setAccessible : (Z)V
    //   4538: aload #6
    //   4540: aconst_null
    //   4541: invokevirtual get : (Ljava/lang/Object;)Ljava/lang/Object;
    //   4544: pop
    //   4545: iinc #5, 1
    //   4548: iload_2
    //   4549: ifeq -> 4411
    //   4552: sipush #842
    //   4555: sipush #15233
    //   4558: invokestatic a : (II)Ljava/lang/String;
    //   4561: invokestatic forName : (Ljava/lang/String;)Ljava/lang/Class;
    //   4564: invokevirtual getDeclaredMethods : ()[Ljava/lang/reflect/Method;
    //   4567: astore_3
    //   4568: aload_3
    //   4569: arraylength
    //   4570: istore #4
    //   4572: iconst_0
    //   4573: istore #5
    //   4575: iload #5
    //   4577: iload #4
    //   4579: if_icmpge -> 4708
    //   4582: aload_3
    //   4583: iload #5
    //   4585: aaload
    //   4586: astore #6
    //   4588: aload #6
    //   4590: invokevirtual getParameterTypes : ()[Ljava/lang/Class;
    //   4593: pop
    //   4594: aload #6
    //   4596: invokevirtual getModifiers : ()I
    //   4599: invokestatic isStatic : (I)Z
    //   4602: ifeq -> 4694
    //   4605: aload #6
    //   4607: invokevirtual getParameterTypes : ()[Ljava/lang/Class;
    //   4610: arraylength
    //   4611: iconst_2
    //   4612: if_icmpne -> 4694
    //   4615: goto -> 4622
    //   4618: invokestatic a : (Ljava/lang/Throwable;)Ljava/lang/Throwable;
    //   4621: athrow
    //   4622: aload #6
    //   4624: invokevirtual getReturnType : ()Ljava/lang/Class;
    //   4627: getstatic java/lang/Boolean.TYPE : Ljava/lang/Class;
    //   4630: if_acmpne -> 4694
    //   4633: goto -> 4640
    //   4636: invokestatic a : (Ljava/lang/Throwable;)Ljava/lang/Throwable;
    //   4639: athrow
    //   4640: aload #6
    //   4642: iconst_1
    //   4643: invokevirtual setAccessible : (Z)V
    //   4646: aload #6
    //   4648: aconst_null
    //   4649: iconst_2
    //   4650: anewarray java/lang/Object
    //   4653: dup
    //   4654: iconst_0
    //   4655: aload_0
    //   4656: aastore
    //   4657: dup
    //   4658: iconst_1
    //   4659: aload_1
    //   4660: ifnonnull -> 4678
    //   4663: goto -> 4670
    //   4666: invokestatic a : (Ljava/lang/Throwable;)Ljava/lang/Throwable;
    //   4669: athrow
    //   4670: aload_1
    //   4671: goto -> 4685
    //   4674: invokestatic a : (Ljava/lang/Throwable;)Ljava/lang/Throwable;
    //   4677: athrow
    //   4678: aload_1
    //   4679: checkcast [B
    //   4682: invokevirtual clone : ()Ljava/lang/Object;
    //   4685: aastore
    //   4686: invokevirtual invoke : (Ljava/lang/Object;[Ljava/lang/Object;)Ljava/lang/Object;
    //   4689: pop
    //   4690: iload_2
    //   4691: ifeq -> 4708
    //   4694: iinc #5, 1
    //   4697: iload_2
    //   4698: ifeq -> 4575
    //   4701: goto -> 4708
    //   4704: invokestatic a : (Ljava/lang/Throwable;)Ljava/lang/Throwable;
    //   4707: athrow
    //   4708: sipush #838
    //   4711: sipush #-31318
    //   4714: invokestatic a : (II)Ljava/lang/String;
    //   4717: iconst_1
    //   4718: ldc burp/Zb_c
    //   4720: invokevirtual getClassLoader : ()Ljava/lang/ClassLoader;
    //   4723: invokestatic forName : (Ljava/lang/String;ZLjava/lang/ClassLoader;)Ljava/lang/Class;
    //   4726: invokevirtual getDeclaredFields : ()[Ljava/lang/reflect/Field;
    //   4729: astore_3
    //   4730: aload_3
    //   4731: arraylength
    //   4732: istore #4
    //   4734: iconst_0
    //   4735: istore #5
    //   4737: iload #5
    //   4739: iload #4
    //   4741: if_icmpge -> 4878
    //   4744: aload_3
    //   4745: iload #5
    //   4747: aaload
    //   4748: astore #6
    //   4750: aload #6
    //   4752: invokevirtual getModifiers : ()I
    //   4755: invokestatic isStatic : (I)Z
    //   4758: ifne -> 4768
    //   4761: goto -> 4871
    //   4764: invokestatic a : (Ljava/lang/Throwable;)Ljava/lang/Throwable;
    //   4767: athrow
    //   4768: aload #6
    //   4770: invokevirtual getType : ()Ljava/lang/Class;
    //   4773: astore #7
    //   4775: aload #7
    //   4777: ifnull -> 4858
    //   4780: aload #7
    //   4782: invokevirtual isPrimitive : ()Z
    //   4785: ifne -> 4858
    //   4788: goto -> 4795
    //   4791: invokestatic a : (Ljava/lang/Throwable;)Ljava/lang/Throwable;
    //   4794: athrow
    //   4795: aload #7
    //   4797: invokevirtual getPackage : ()Ljava/lang/Package;
    //   4800: ifnull -> 4858
    //   4803: goto -> 4810
    //   4806: invokestatic a : (Ljava/lang/Throwable;)Ljava/lang/Throwable;
    //   4809: athrow
    //   4810: aload #7
    //   4812: invokevirtual getPackage : ()Ljava/lang/Package;
    //   4815: invokevirtual getName : ()Ljava/lang/String;
    //   4818: ifnull -> 4858
    //   4821: goto -> 4828
    //   4824: invokestatic a : (Ljava/lang/Throwable;)Ljava/lang/Throwable;
    //   4827: athrow
    //   4828: aload #7
    //   4830: invokevirtual getPackage : ()Ljava/lang/Package;
    //   4833: invokevirtual getName : ()Ljava/lang/String;
    //   4836: sipush #837
    //   4839: sipush #-21761
    //   4842: invokestatic a : (II)Ljava/lang/String;
    //   4845: invokevirtual startsWith : (Ljava/lang/String;)Z
    //   4848: ifne -> 4858
    //   4851: goto -> 4858
    //   4854: invokestatic a : (Ljava/lang/Throwable;)Ljava/lang/Throwable;
    //   4857: athrow
    //   4858: aload #6
    //   4860: iconst_1
    //   4861: invokevirtual setAccessible : (Z)V
    //   4864: aload #6
    //   4866: aconst_null
    //   4867: invokevirtual get : (Ljava/lang/Object;)Ljava/lang/Object;
    //   4870: pop
    //   4871: iinc #5, 1
    //   4874: iload_2
    //   4875: ifeq -> 4737
    //   4878: sipush #832
    //   4881: sipush #21713
    //   4884: invokestatic a : (II)Ljava/lang/String;
    //   4887: invokestatic forName : (Ljava/lang/String;)Ljava/lang/Class;
    //   4890: invokevirtual getDeclaredMethods : ()[Ljava/lang/reflect/Method;
    //   4893: astore_3
    //   4894: aload_3
    //   4895: arraylength
    //   4896: istore #4
    //   4898: iconst_0
    //   4899: istore #5
    //   4901: iload #5
    //   4903: iload #4
    //   4905: if_icmpge -> 5037
    //   4908: aload_3
    //   4909: iload #5
    //   4911: aaload
    //   4912: astore #6
    //   4914: aload #6
    //   4916: invokevirtual getParameterTypes : ()[Ljava/lang/Class;
    //   4919: pop
    //   4920: aload #6
    //   4922: invokevirtual getModifiers : ()I
    //   4925: invokestatic isStatic : (I)Z
    //   4928: ifeq -> 5023
    //   4931: aload #6
    //   4933: invokevirtual getParameterTypes : ()[Ljava/lang/Class;
    //   4936: arraylength
    //   4937: iconst_2
    //   4938: if_icmpne -> 5023
    //   4941: goto -> 4948
    //   4944: invokestatic a : (Ljava/lang/Throwable;)Ljava/lang/Throwable;
    //   4947: athrow
    //   4948: aload #6
    //   4950: invokevirtual getReturnType : ()Ljava/lang/Class;
    //   4953: getstatic java/lang/Void.TYPE : Ljava/lang/Class;
    //   4956: invokevirtual equals : (Ljava/lang/Object;)Z
    //   4959: ifeq -> 5023
    //   4962: goto -> 4969
    //   4965: invokestatic a : (Ljava/lang/Throwable;)Ljava/lang/Throwable;
    //   4968: athrow
    //   4969: aload #6
    //   4971: iconst_1
    //   4972: invokevirtual setAccessible : (Z)V
    //   4975: aload #6
    //   4977: aconst_null
    //   4978: iconst_2
    //   4979: anewarray java/lang/Object
    //   4982: dup
    //   4983: iconst_0
    //   4984: aload_0
    //   4985: aastore
    //   4986: dup
    //   4987: iconst_1
    //   4988: aload_1
    //   4989: ifnonnull -> 5007
    //   4992: goto -> 4999
    //   4995: invokestatic a : (Ljava/lang/Throwable;)Ljava/lang/Throwable;
    //   4998: athrow
    //   4999: aload_1
    //   5000: goto -> 5014
    //   5003: invokestatic a : (Ljava/lang/Throwable;)Ljava/lang/Throwable;
    //   5006: athrow
    //   5007: aload_1
    //   5008: checkcast [B
    //   5011: invokevirtual clone : ()Ljava/lang/Object;
    //   5014: aastore
    //   5015: invokevirtual invoke : (Ljava/lang/Object;[Ljava/lang/Object;)Ljava/lang/Object;
    //   5018: pop
    //   5019: iload_2
    //   5020: ifeq -> 5037
    //   5023: iinc #5, 1
    //   5026: iload_2
    //   5027: ifeq -> 4901
    //   5030: goto -> 5037
    //   5033: invokestatic a : (Ljava/lang/Throwable;)Ljava/lang/Throwable;
    //   5036: athrow
    //   5037: getstatic burp/Zkgp.ZM : Ljava/lang/String;
    //   5040: getstatic burp/Zkf9.ZX : Ljava/lang/Object;
    //   5043: checkcast java/math/BigInteger
    //   5046: invokevirtual intValue : ()I
    //   5049: bipush #32
    //   5051: irem
    //   5052: invokestatic abs : (I)I
    //   5055: invokevirtual charAt : (I)C
    //   5058: getstatic burp/Zb9k.Za : Ljava/lang/String;
    //   5061: getstatic burp/Zb_u.Zp : Ljava/lang/Object;
    //   5064: checkcast java/math/BigInteger
    //   5067: invokevirtual intValue : ()I
    //   5070: bipush #32
    //   5072: irem
    //   5073: invokestatic abs : (I)I
    //   5076: invokevirtual charAt : (I)C
    //   5079: if_icmple -> 5186
    //   5082: getstatic burp/Zz6t.Zx : Ljava/lang/String;
    //   5085: getstatic burp/Ze3t.Zp : Ljava/lang/Object;
    //   5088: checkcast java/math/BigInteger
    //   5091: invokevirtual intValue : ()I
    //   5094: bipush #32
    //   5096: irem
    //   5097: invokestatic abs : (I)I
    //   5100: invokevirtual charAt : (I)C
    //   5103: getstatic burp/Zrnu.ZO : Ljava/lang/String;
    //   5106: getstatic burp/Zrm4.ZB : Ljava/lang/Object;
    //   5109: checkcast java/math/BigInteger
    //   5112: invokevirtual intValue : ()I
    //   5115: bipush #32
    //   5117: irem
    //   5118: invokestatic abs : (I)I
    //   5121: invokevirtual charAt : (I)C
    //   5124: if_icmple -> 5186
    //   5127: goto -> 5134
    //   5130: invokestatic a : (Ljava/lang/Throwable;)Ljava/lang/Throwable;
    //   5133: athrow
    //   5134: getstatic burp/Zxso.ZH : Ljava/lang/String;
    //   5137: getstatic burp/Zlh2.Zc : Ljava/lang/Object;
    //   5140: checkcast java/math/BigInteger
    //   5143: invokevirtual intValue : ()I
    //   5146: bipush #32
    //   5148: irem
    //   5149: invokestatic abs : (I)I
    //   5152: invokevirtual charAt : (I)C
    //   5155: getstatic burp/Zs8y.Zr : Ljava/lang/String;
    //   5158: getstatic burp/Zea9.Zt : Ljava/lang/Object;
    //   5161: checkcast java/math/BigInteger
    //   5164: invokevirtual intValue : ()I
    //   5167: bipush #32
    //   5169: irem
    //   5170: invokestatic abs : (I)I
    //   5173: invokevirtual charAt : (I)C
    //   5176: if_icmple -> 5194
    //   5179: goto -> 5186
    //   5182: invokestatic a : (Ljava/lang/Throwable;)Ljava/lang/Throwable;
    //   5185: athrow
    //   5186: iconst_1
    //   5187: goto -> 5195
    //   5190: invokestatic a : (Ljava/lang/Throwable;)Ljava/lang/Throwable;
    //   5193: athrow
    //   5194: iconst_0
    //   5195: ireturn
    //   5196: astore_3
    //   5197: new java/lang/Exception
    //   5200: dup
    //   5201: aload_3
    //   5202: invokevirtual getMessage : ()Ljava/lang/String;
    //   5205: invokespecial <init> : (Ljava/lang/String;)V
    //   5208: athrow
    // Exception table:
    //   from	to	target	type
    //   4	5195	5196	java/lang/Throwable
    //   3321	3346	3346	java/lang/Throwable
    //   4309	4335	4335	java/lang/Throwable
    //   4424	4438	4438	java/lang/Throwable
    //   4449	4462	4465	java/lang/Throwable
    //   4454	4477	4480	java/lang/Throwable
    //   4469	4495	4498	java/lang/Throwable
    //   4484	4525	4528	java/lang/Throwable
    //   4588	4615	4618	java/lang/Throwable
    //   4605	4633	4636	java/lang/Throwable
    //   4622	4663	4666	java/lang/Throwable
    //   4640	4674	4674	java/lang/Throwable
    //   4685	4701	4704	java/lang/Throwable
    //   4750	4764	4764	java/lang/Throwable
    //   4775	4788	4791	java/lang/Throwable
    //   4780	4803	4806	java/lang/Throwable
    //   4795	4821	4824	java/lang/Throwable
    //   4810	4851	4854	java/lang/Throwable
    //   4914	4941	4944	java/lang/Throwable
    //   4931	4962	4965	java/lang/Throwable
    //   4948	4992	4995	java/lang/Throwable
    //   4969	5003	5003	java/lang/Throwable
    //   5014	5030	5033	java/lang/Throwable
    //   5037	5127	5130	java/lang/Throwable
    //   5082	5179	5182	java/lang/Throwable
    //   5134	5190	5190	java/lang/Throwable
  }
  
  static void ZC(Object[] paramArrayOfObject, Object paramObject) throws Throwable {}
  
  static {
    // Byte code:
    //   0: bipush #14
    //   2: anewarray java/lang/String
    //   5: astore #5
    //   7: iconst_0
    //   8: istore_3
    //   9: ldc ')SK\\t.h]1^ i0,\\rI%'BV=\\tD.!H\\t'rI8ywM?#'O(Z2DY4BR)|2)W, \\bXGJiG)\\nF5@{Q^\\t+G\\t\\t1Mu1AhF;/\\f?Jd~ `fG?~ ?To"f{`Eo\\bb>'
    //   11: dup
    //   12: astore_2
    //   13: invokevirtual length : ()I
    //   16: istore #4
    //   18: bipush #9
    //   20: istore_1
    //   21: iconst_m1
    //   22: istore_0
    //   23: bipush #100
    //   25: iinc #0, 1
    //   28: aload_2
    //   29: iload_0
    //   30: dup
    //   31: iload_1
    //   32: iadd
    //   33: invokevirtual substring : (II)Ljava/lang/String;
    //   36: iconst_m1
    //   37: goto -> 143
    //   40: aload #5
    //   42: swap
    //   43: iload_3
    //   44: iinc #3, 1
    //   47: swap
    //   48: aastore
    //   49: iload_0
    //   50: iload_1
    //   51: iadd
    //   52: dup
    //   53: istore_0
    //   54: iload #4
    //   56: if_icmpge -> 68
    //   59: aload_2
    //   60: iload_0
    //   61: invokevirtual charAt : (I)C
    //   64: istore_1
    //   65: goto -> 23
    //   68: ldc '+\\bv8\\b\ R@'
    //   70: dup
    //   71: astore_2
    //   72: invokevirtual length : ()I
    //   75: istore #4
    //   77: bipush #9
    //   79: istore_1
    //   80: iconst_m1
    //   81: istore_0
    //   82: bipush #15
    //   84: iinc #0, 1
    //   87: aload_2
    //   88: iload_0
    //   89: dup
    //   90: iload_1
    //   91: iadd
    //   92: invokevirtual substring : (II)Ljava/lang/String;
    //   95: iconst_0
    //   96: goto -> 143
    //   99: aload #5
    //   101: swap
    //   102: iload_3
    //   103: iinc #3, 1
    //   106: swap
    //   107: aastore
    //   108: iload_0
    //   109: iload_1
    //   110: iadd
    //   111: dup
    //   112: istore_0
    //   113: iload #4
    //   115: if_icmpge -> 127
    //   118: aload_2
    //   119: iload_0
    //   120: invokevirtual charAt : (I)C
    //   123: istore_1
    //   124: goto -> 82
    //   127: aload #5
    //   129: putstatic burp/Zrd0.a : [Ljava/lang/String;
    //   132: bipush #14
    //   134: anewarray java/lang/String
    //   137: putstatic burp/Zrd0.b : [Ljava/lang/String;
    //   140: goto -> 300
    //   143: dup_x2
    //   144: pop
    //   145: invokevirtual toCharArray : ()[C
    //   148: dup_x1
    //   149: arraylength
    //   150: dup_x2
    //   151: pop
    //   152: iconst_0
    //   153: istore #6
    //   155: dup2_x1
    //   156: pop2
    //   157: dup_x2
    //   158: iconst_1
    //   159: if_icmpgt -> 259
    //   162: dup2
    //   163: swap
    //   164: iload #6
    //   166: dup2_x1
    //   167: caload
    //   168: swap
    //   169: iload #6
    //   171: bipush #7
    //   173: irem
    //   174: tableswitch default -> 241, 0 -> 212, 1 -> 217, 2 -> 222, 3 -> 227, 4 -> 232, 5 -> 236
    //   212: bipush #99
    //   214: goto -> 243
    //   217: bipush #106
    //   219: goto -> 243
    //   222: bipush #117
    //   224: goto -> 243
    //   227: bipush #120
    //   229: goto -> 243
    //   232: iconst_4
    //   233: goto -> 243
    //   236: bipush #48
    //   238: goto -> 243
    //   241: bipush #17
    //   243: ixor
    //   244: ixor
    //   245: i2c
    //   246: castore
    //   247: iinc #6, 1
    //   250: dup
    //   251: ifne -> 259
    //   254: dup2
    //   255: dup_x1
    //   256: goto -> 166
    //   259: dup2_x1
    //   260: pop2
    //   261: dup_x2
    //   262: iload #6
    //   264: if_icmpgt -> 162
    //   267: pop
    //   268: new java/lang/String
    //   271: dup_x1
    //   272: swap
    //   273: invokespecial <init> : ([C)V
    //   276: invokevirtual intern : ()Ljava/lang/String;
    //   279: swap
    //   280: pop
    //   281: swap
    //   282: tableswitch default -> 40, 0 -> 99
    //   300: sipush #836
    //   303: sipush #-14555
    //   306: invokestatic a : (II)Ljava/lang/String;
    //   309: putstatic burp/Zrd0.Zk : Ljava/lang/String;
    //   312: new java/math/BigInteger
    //   315: dup
    //   316: iconst_1
    //   317: bipush #32
    //   319: newarray byte
    //   321: dup
    //   322: iconst_0
    //   323: bipush #115
    //   325: bastore
    //   326: dup
    //   327: iconst_1
    //   328: bipush #-4
    //   330: bastore
    //   331: dup
    //   332: iconst_2
    //   333: bipush #109
    //   335: bastore
    //   336: dup
    //   337: iconst_3
    //   338: bipush #92
    //   340: bastore
    //   341: dup
    //   342: iconst_4
    //   343: bipush #13
    //   345: bastore
    //   346: dup
    //   347: iconst_5
    //   348: bipush #114
    //   350: bastore
    //   351: dup
    //   352: bipush #6
    //   354: bipush #41
    //   356: bastore
    //   357: dup
    //   358: bipush #7
    //   360: bipush #-30
    //   362: bastore
    //   363: dup
    //   364: bipush #8
    //   366: bipush #23
    //   368: bastore
    //   369: dup
    //   370: bipush #9
    //   372: bipush #-40
    //   374: bastore
    //   375: dup
    //   376: bipush #10
    //   378: bipush #120
    //   380: bastore
    //   381: dup
    //   382: bipush #11
    //   384: bipush #51
    //   386: bastore
    //   387: dup
    //   388: bipush #12
    //   390: bipush #-107
    //   392: bastore
    //   393: dup
    //   394: bipush #13
    //   396: bipush #-96
    //   398: bastore
    //   399: dup
    //   400: bipush #14
    //   402: bipush #-27
    //   404: bastore
    //   405: dup
    //   406: bipush #15
    //   408: bipush #27
    //   410: bastore
    //   411: dup
    //   412: bipush #16
    //   414: bipush #101
    //   416: bastore
    //   417: dup
    //   418: bipush #17
    //   420: bipush #-121
    //   422: bastore
    //   423: dup
    //   424: bipush #18
    //   426: bipush #114
    //   428: bastore
    //   429: dup
    //   430: bipush #19
    //   432: bipush #-68
    //   434: bastore
    //   435: dup
    //   436: bipush #20
    //   438: bipush #117
    //   440: bastore
    //   441: dup
    //   442: bipush #21
    //   444: bipush #-28
    //   446: bastore
    //   447: dup
    //   448: bipush #22
    //   450: bipush #-66
    //   452: bastore
    //   453: dup
    //   454: bipush #23
    //   456: iconst_3
    //   457: bastore
    //   458: dup
    //   459: bipush #24
    //   461: bipush #-128
    //   463: bastore
    //   464: dup
    //   465: bipush #25
    //   467: bipush #-68
    //   469: bastore
    //   470: dup
    //   471: bipush #26
    //   473: bipush #53
    //   475: bastore
    //   476: dup
    //   477: bipush #27
    //   479: bipush #-33
    //   481: bastore
    //   482: dup
    //   483: bipush #28
    //   485: bipush #125
    //   487: bastore
    //   488: dup
    //   489: bipush #29
    //   491: bipush #-24
    //   493: bastore
    //   494: dup
    //   495: bipush #30
    //   497: bipush #-60
    //   499: bastore
    //   500: dup
    //   501: bipush #31
    //   503: bipush #-7
    //   505: bastore
    //   506: invokespecial <init> : (I[B)V
    //   509: putstatic burp/Zrd0.Zs : Ljava/lang/Object;
    //   512: return
  }
  
  private static Throwable a(Throwable paramThrowable) {
    return paramThrowable;
  }
  
  private static String a(int paramInt1, int paramInt2) {
    int i = (paramInt1 ^ 0x346) & 0xFFFF;
    if (b[i] == null) {
      char[] arrayOfChar = a[i].toCharArray();
      switch (arrayOfChar[0] & 0xFF) {
        case 0:
        
        case 1:
        
        case 2:
        
        case 3:
        
        case 4:
        
        case 5:
        
        case 6:
        
        case 7:
        
        case 8:
        
        case 9:
        
        case 10:
        
        case 11:
        
        case 12:
        
        case 13:
        
        case 14:
        
        case 15:
        
        case 16:
        
        case 17:
        
        case 18:
        
        case 19:
        
        case 20:
        
        case 21:
        
        case 22:
        
        case 23:
        
        case 24:
        
        case 25:
        
        case 26:
        
        case 27:
        
        case 28:
        
        case 29:
        
        case 30:
        
        case 31:
        
        case 32:
        
        case 33:
        
        case 34:
        
        case 35:
        
        case 36:
        
        case 37:
        
        case 38:
        
        case 39:
        
        case 40:
        
        case 41:
        
        case 42:
        
        case 43:
        
        case 44:
        
        case 45:
        
        case 46:
        
        case 47:
        
        case 48:
        
        case 49:
        
        case 50:
        
        case 51:
        
        case 52:
        
        case 53:
        
        case 54:
        
        case 55:
        
        case 56:
        
        case 57:
        
        case 58:
        
        case 59:
        
        case 60:
        
        case 61:
        
        case 62:
        
        case 63:
        
        case 64:
        
        case 65:
        
        case 66:
        
        case 67:
        
        case 68:
        
        case 69:
        
        case 70:
        
        case 71:
        
        case 72:
        
        case 73:
        
        case 74:
        
        case 75:
        
        case 76:
        
        case 77:
        
        case 78:
        
        case 79:
        
        case 80:
        
        case 81:
        
        case 82:
        
        case 83:
        
        case 84:
        
        case 85:
        
        case 86:
        
        case 87:
        
        case 88:
        
        case 89:
        
        case 90:
        
        case 91:
        
        case 92:
        
        case 93:
        
        case 94:
        
        case 95:
        
        case 96:
        
        case 97:
        
        case 98:
        
        case 99:
        
        case 100:
        
        case 101:
        
        case 102:
        
        case 103:
        
        case 104:
        
        case 105:
        
        case 106:
        
        case 107:
        
        case 108:
        
        case 109:
        
        case 110:
        
        case 111:
        
        case 112:
        
        case 113:
        
        case 114:
        
        case 115:
        
        case 116:
        
        case 117:
        
        case 118:
        
        case 119:
        
        case 120:
        
        case 121:
        
        case 122:
        
        case 123:
        
        case 124:
        
        case 125:
        
        case 126:
        
        case 127:
        
        case 128:
        
        case 129:
        
        case 130:
        
        case 131:
        
        case 132:
        
        case 133:
        
        case 134:
        
        case 135:
        
        case 136:
        
        case 137:
        
        case 138:
        
        case 139:
        
        case 140:
        
        case 141:
        
        case 142:
        
        case 143:
        
        case 144:
        
        case 145:
        
        case 146:
        
        case 147:
        
        case 148:
        
        case 149:
        
        case 150:
        
        case 151:
        
        case 152:
        
        case 153:
        
        case 154:
        
        case 155:
        
        case 156:
        
        case 157:
        
        case 158:
        
        case 159:
        
        case 160:
        
        case 161:
        
        case 162:
        
        case 163:
        
        case 164:
        
        case 165:
        
        case 166:
        
        case 167:
        
        case 168:
        
        case 169:
        
        case 170:
        
        case 171:
        
        case 172:
        
        case 173:
        
        case 174:
        
        case 175:
        
        case 176:
        
        case 177:
        
        case 178:
        
        case 179:
        
        case 180:
        
        case 181:
        
        case 182:
        
        case 183:
        
        case 184:
        
        case 185:
        
        case 186:
        
        case 187:
        
        case 188:
        
        case 189:
        
        case 190:
        
        case 191:
        
        case 192:
        
        case 193:
        
        case 194:
        
        case 195:
        
        case 196:
        
        case 197:
        
        case 198:
        
        case 199:
        
        case 200:
        
        case 201:
        
        case 202:
        
        case 203:
        
        case 204:
        
        case 205:
        
        case 206:
        
        case 207:
        
        case 208:
        
        case 209:
        
        case 210:
        
        case 211:
        
        case 212:
        
        case 213:
        
        case 214:
        
        case 215:
        
        case 216:
        
        case 217:
        
        case 218:
        
        case 219:
        
        case 220:
        
        case 221:
        
        case 222:
        
        case 223:
        
        case 224:
        
        case 225:
        
        case 226:
        
        case 227:
        
        case 228:
        
        case 229:
        
        case 230:
        
        case 231:
        
        case 232:
        
        case 233:
        
        case 234:
        
        case 235:
        
        case 236:
        
        case 237:
        
        case 238:
        
        case 239:
        
        case 240:
        
        case 241:
        
        case 242:
        
        case 243:
        
        case 244:
        
        case 245:
        
        case 246:
        
        case 247:
        
        case 248:
        
        case 249:
        
        case 250:
        
        case 251:
        
        case 252:
        
        case 253:
        
        case 254:
        
        default:
          break;
      } 
      byte b1 = 117;
      int j = (paramInt2 & 0xFF) - b1;
      if (j < 0)
        j += 256; 
      int k = ((paramInt2 & 0xFFFF) >>> 8) - b1;
      if (k < 0)
        k += 256; 
      for (byte b2 = 0; b2 < arrayOfChar.length; b2++) {
        int m = b2 % 2;
        if (m == 0) {
          arrayOfChar[b2] = (char)(arrayOfChar[b2] ^ j);
          j = ((j >>> 3 | j << 5) ^ arrayOfChar[b2]) & 0xFF;
        } else {
          arrayOfChar[b2] = (char)(arrayOfChar[b2] ^ k);
          k = ((k >>> 3 | k << 5) ^ arrayOfChar[b2]) & 0xFF;
        } 
      } 
      b[i] = (new String(arrayOfChar)).intern();
    } 
    return b[i];
  }
}


/* Location:              C:\Program Files\BurpSuitePro\burpsuite_pro.jar!\burp\Zrd0.class
 * Java compiler version: 21 (65.0)
 * JD-Core Version:       1.1.3
 */