package burp;

import java.math.BigInteger;

class Zrfh extends ClassLoader {
  static String ZH;
  
  static Object ZJ;
  
  private static final String[] a;
  
  private static final String[] b;
  
  static void ZP(Object paramObject) {
    Zl6z.ZL = a(-8090, -9534);
    Zl6z.Zt = new BigInteger(a(-8078, 7109));
    boolean bool = Zt2e.ZK();
    try {
      try {
        if (Zlwi.ZN.charAt(Math.abs(((BigInteger)Ztc2.ZM).intValue() % 32)) > Ztc2.Zr.charAt(Math.abs(((BigInteger)Zenq.Zd).intValue() % 32))) {
          try {
            Zm14.ZX(Class.forName(a(-8065, 16016)));
            if (bool)
              Zz5l.Zy(Class.forName(a(-8083, 24283))); 
          } catch (Throwable throwable) {
            throw a(null);
          } 
          return;
        } 
      } catch (Throwable throwable) {
        throw a(null);
      } 
      Zz5l.Zy(Class.forName(a(-8083, 24283)));
    } catch (Throwable throwable) {}
  }
  
  static boolean Zd(Object[] paramArrayOfObject, Object paramObject) throws Throwable {
    // Byte code:
    //   0: invokestatic ZN : ()Z
    //   3: istore_2
    //   4: new java/lang/StringBuilder
    //   7: dup
    //   8: invokespecial <init> : ()V
    //   11: astore_3
    //   12: iconst_0
    //   13: istore #4
    //   15: iload #4
    //   17: bipush #32
    //   19: if_icmpge -> 1355
    //   22: iload #4
    //   24: tableswitch default -> 1348, 0 -> 168, 1 -> 205, 2 -> 242, 3 -> 279, 4 -> 316, 5 -> 353, 6 -> 390, 7 -> 427, 8 -> 464, 9 -> 501, 10 -> 538, 11 -> 575, 12 -> 612, 13 -> 649, 14 -> 686, 15 -> 723, 16 -> 760, 17 -> 797, 18 -> 834, 19 -> 871, 20 -> 908, 21 -> 945, 22 -> 982, 23 -> 1019, 24 -> 1056, 25 -> 1093, 26 -> 1130, 27 -> 1167, 28 -> 1204, 29 -> 1241, 30 -> 1278, 31 -> 1315
    //   168: aload_3
    //   169: getstatic burp/Zzb2.ZJ : Ljava/lang/String;
    //   172: getstatic burp/Zlwi.Zw : Ljava/lang/Object;
    //   175: checkcast java/math/BigInteger
    //   178: invokevirtual intValue : ()I
    //   181: bipush #32
    //   183: irem
    //   184: invokestatic abs : (I)I
    //   187: invokevirtual charAt : (I)C
    //   190: invokevirtual append : (C)Ljava/lang/StringBuilder;
    //   193: pop
    //   194: iload_2
    //   195: ifne -> 1348
    //   198: goto -> 205
    //   201: invokestatic a : (Ljava/lang/Throwable;)Ljava/lang/Throwable;
    //   204: athrow
    //   205: aload_3
    //   206: getstatic burp/Zecm.Zv : Ljava/lang/String;
    //   209: getstatic burp/Zbsc.ZA : Ljava/lang/Object;
    //   212: checkcast java/math/BigInteger
    //   215: invokevirtual intValue : ()I
    //   218: bipush #32
    //   220: irem
    //   221: invokestatic abs : (I)I
    //   224: invokevirtual charAt : (I)C
    //   227: invokevirtual append : (C)Ljava/lang/StringBuilder;
    //   230: pop
    //   231: iload_2
    //   232: ifne -> 1348
    //   235: goto -> 242
    //   238: invokestatic a : (Ljava/lang/Throwable;)Ljava/lang/Throwable;
    //   241: athrow
    //   242: aload_3
    //   243: getstatic burp/Zbzj.Zw : Ljava/lang/String;
    //   246: getstatic burp/Zenq.Zd : Ljava/lang/Object;
    //   249: checkcast java/math/BigInteger
    //   252: invokevirtual intValue : ()I
    //   255: bipush #32
    //   257: irem
    //   258: invokestatic abs : (I)I
    //   261: invokevirtual charAt : (I)C
    //   264: invokevirtual append : (C)Ljava/lang/StringBuilder;
    //   267: pop
    //   268: iload_2
    //   269: ifne -> 1348
    //   272: goto -> 279
    //   275: invokestatic a : (Ljava/lang/Throwable;)Ljava/lang/Throwable;
    //   278: athrow
    //   279: aload_3
    //   280: getstatic burp/Zrfh.ZH : Ljava/lang/String;
    //   283: getstatic burp/Zlzs.ZL : Ljava/lang/Object;
    //   286: checkcast java/math/BigInteger
    //   289: invokevirtual intValue : ()I
    //   292: bipush #32
    //   294: irem
    //   295: invokestatic abs : (I)I
    //   298: invokevirtual charAt : (I)C
    //   301: invokevirtual append : (C)Ljava/lang/StringBuilder;
    //   304: pop
    //   305: iload_2
    //   306: ifne -> 1348
    //   309: goto -> 316
    //   312: invokestatic a : (Ljava/lang/Throwable;)Ljava/lang/Throwable;
    //   315: athrow
    //   316: aload_3
    //   317: getstatic burp/Zro_.Zz : Ljava/lang/String;
    //   320: getstatic burp/Zlvx.ZM : Ljava/lang/Object;
    //   323: checkcast java/math/BigInteger
    //   326: invokevirtual intValue : ()I
    //   329: bipush #32
    //   331: irem
    //   332: invokestatic abs : (I)I
    //   335: invokevirtual charAt : (I)C
    //   338: invokevirtual append : (C)Ljava/lang/StringBuilder;
    //   341: pop
    //   342: iload_2
    //   343: ifne -> 1348
    //   346: goto -> 353
    //   349: invokestatic a : (Ljava/lang/Throwable;)Ljava/lang/Throwable;
    //   352: athrow
    //   353: aload_3
    //   354: getstatic burp/Ze9.Zh : Ljava/lang/String;
    //   357: getstatic burp/Zg5.Zs : Ljava/lang/Object;
    //   360: checkcast java/math/BigInteger
    //   363: invokevirtual intValue : ()I
    //   366: bipush #32
    //   368: irem
    //   369: invokestatic abs : (I)I
    //   372: invokevirtual charAt : (I)C
    //   375: invokevirtual append : (C)Ljava/lang/StringBuilder;
    //   378: pop
    //   379: iload_2
    //   380: ifne -> 1348
    //   383: goto -> 390
    //   386: invokestatic a : (Ljava/lang/Throwable;)Ljava/lang/Throwable;
    //   389: athrow
    //   390: aload_3
    //   391: getstatic burp/Zeai.ZA : Ljava/lang/String;
    //   394: getstatic burp/Zbzj.Zz : Ljava/lang/Object;
    //   397: checkcast java/math/BigInteger
    //   400: invokevirtual intValue : ()I
    //   403: bipush #32
    //   405: irem
    //   406: invokestatic abs : (I)I
    //   409: invokevirtual charAt : (I)C
    //   412: invokevirtual append : (C)Ljava/lang/StringBuilder;
    //   415: pop
    //   416: iload_2
    //   417: ifne -> 1348
    //   420: goto -> 427
    //   423: invokestatic a : (Ljava/lang/Throwable;)Ljava/lang/Throwable;
    //   426: athrow
    //   427: aload_3
    //   428: getstatic burp/Zgl2.Zw : Ljava/lang/String;
    //   431: getstatic burp/Zg5.Zs : Ljava/lang/Object;
    //   434: checkcast java/math/BigInteger
    //   437: invokevirtual intValue : ()I
    //   440: bipush #32
    //   442: irem
    //   443: invokestatic abs : (I)I
    //   446: invokevirtual charAt : (I)C
    //   449: invokevirtual append : (C)Ljava/lang/StringBuilder;
    //   452: pop
    //   453: iload_2
    //   454: ifne -> 1348
    //   457: goto -> 464
    //   460: invokestatic a : (Ljava/lang/Throwable;)Ljava/lang/Throwable;
    //   463: athrow
    //   464: aload_3
    //   465: getstatic burp/Ztpg.Zr : Ljava/lang/String;
    //   468: getstatic burp/Zsot.ZJ : Ljava/lang/Object;
    //   471: checkcast java/math/BigInteger
    //   474: invokevirtual intValue : ()I
    //   477: bipush #32
    //   479: irem
    //   480: invokestatic abs : (I)I
    //   483: invokevirtual charAt : (I)C
    //   486: invokevirtual append : (C)Ljava/lang/StringBuilder;
    //   489: pop
    //   490: iload_2
    //   491: ifne -> 1348
    //   494: goto -> 501
    //   497: invokestatic a : (Ljava/lang/Throwable;)Ljava/lang/Throwable;
    //   500: athrow
    //   501: aload_3
    //   502: getstatic burp/Zzpj.ZR : Ljava/lang/String;
    //   505: getstatic burp/Zecm.ZJ : Ljava/lang/Object;
    //   508: checkcast java/math/BigInteger
    //   511: invokevirtual intValue : ()I
    //   514: bipush #32
    //   516: irem
    //   517: invokestatic abs : (I)I
    //   520: invokevirtual charAt : (I)C
    //   523: invokevirtual append : (C)Ljava/lang/StringBuilder;
    //   526: pop
    //   527: iload_2
    //   528: ifne -> 1348
    //   531: goto -> 538
    //   534: invokestatic a : (Ljava/lang/Throwable;)Ljava/lang/Throwable;
    //   537: athrow
    //   538: aload_3
    //   539: getstatic burp/Zsot.Zb : Ljava/lang/String;
    //   542: getstatic burp/Zro_.ZP : Ljava/lang/Object;
    //   545: checkcast java/math/BigInteger
    //   548: invokevirtual intValue : ()I
    //   551: bipush #32
    //   553: irem
    //   554: invokestatic abs : (I)I
    //   557: invokevirtual charAt : (I)C
    //   560: invokevirtual append : (C)Ljava/lang/StringBuilder;
    //   563: pop
    //   564: iload_2
    //   565: ifne -> 1348
    //   568: goto -> 575
    //   571: invokestatic a : (Ljava/lang/Throwable;)Ljava/lang/Throwable;
    //   574: athrow
    //   575: aload_3
    //   576: getstatic burp/Zl6z.ZL : Ljava/lang/String;
    //   579: getstatic burp/Zrfh.ZJ : Ljava/lang/Object;
    //   582: checkcast java/math/BigInteger
    //   585: invokevirtual intValue : ()I
    //   588: bipush #32
    //   590: irem
    //   591: invokestatic abs : (I)I
    //   594: invokevirtual charAt : (I)C
    //   597: invokevirtual append : (C)Ljava/lang/StringBuilder;
    //   600: pop
    //   601: iload_2
    //   602: ifne -> 1348
    //   605: goto -> 612
    //   608: invokestatic a : (Ljava/lang/Throwable;)Ljava/lang/Throwable;
    //   611: athrow
    //   612: aload_3
    //   613: getstatic burp/Zlzs.Zp : Ljava/lang/String;
    //   616: getstatic burp/Zlhu.ZJ : Ljava/lang/Object;
    //   619: checkcast java/math/BigInteger
    //   622: invokevirtual intValue : ()I
    //   625: bipush #32
    //   627: irem
    //   628: invokestatic abs : (I)I
    //   631: invokevirtual charAt : (I)C
    //   634: invokevirtual append : (C)Ljava/lang/StringBuilder;
    //   637: pop
    //   638: iload_2
    //   639: ifne -> 1348
    //   642: goto -> 649
    //   645: invokestatic a : (Ljava/lang/Throwable;)Ljava/lang/Throwable;
    //   648: athrow
    //   649: aload_3
    //   650: getstatic burp/Zza3.ZU : Ljava/lang/String;
    //   653: getstatic burp/Zre4.Zx : Ljava/lang/Object;
    //   656: checkcast java/math/BigInteger
    //   659: invokevirtual intValue : ()I
    //   662: bipush #32
    //   664: irem
    //   665: invokestatic abs : (I)I
    //   668: invokevirtual charAt : (I)C
    //   671: invokevirtual append : (C)Ljava/lang/StringBuilder;
    //   674: pop
    //   675: iload_2
    //   676: ifne -> 1348
    //   679: goto -> 686
    //   682: invokestatic a : (Ljava/lang/Throwable;)Ljava/lang/Throwable;
    //   685: athrow
    //   686: aload_3
    //   687: getstatic burp/Zzhu.ZT : Ljava/lang/String;
    //   690: getstatic burp/Zl6z.Zt : Ljava/lang/Object;
    //   693: checkcast java/math/BigInteger
    //   696: invokevirtual intValue : ()I
    //   699: bipush #32
    //   701: irem
    //   702: invokestatic abs : (I)I
    //   705: invokevirtual charAt : (I)C
    //   708: invokevirtual append : (C)Ljava/lang/StringBuilder;
    //   711: pop
    //   712: iload_2
    //   713: ifne -> 1348
    //   716: goto -> 723
    //   719: invokestatic a : (Ljava/lang/Throwable;)Ljava/lang/Throwable;
    //   722: athrow
    //   723: aload_3
    //   724: getstatic burp/Zzxa.Zl : Ljava/lang/String;
    //   727: getstatic burp/Zgr1.Zf : Ljava/lang/Object;
    //   730: checkcast java/math/BigInteger
    //   733: invokevirtual intValue : ()I
    //   736: bipush #32
    //   738: irem
    //   739: invokestatic abs : (I)I
    //   742: invokevirtual charAt : (I)C
    //   745: invokevirtual append : (C)Ljava/lang/StringBuilder;
    //   748: pop
    //   749: iload_2
    //   750: ifne -> 1348
    //   753: goto -> 760
    //   756: invokestatic a : (Ljava/lang/Throwable;)Ljava/lang/Throwable;
    //   759: athrow
    //   760: aload_3
    //   761: getstatic burp/Zrh1.Zg : Ljava/lang/String;
    //   764: getstatic burp/Zs56.ZC : Ljava/lang/Object;
    //   767: checkcast java/math/BigInteger
    //   770: invokevirtual intValue : ()I
    //   773: bipush #32
    //   775: irem
    //   776: invokestatic abs : (I)I
    //   779: invokevirtual charAt : (I)C
    //   782: invokevirtual append : (C)Ljava/lang/StringBuilder;
    //   785: pop
    //   786: iload_2
    //   787: ifne -> 1348
    //   790: goto -> 797
    //   793: invokestatic a : (Ljava/lang/Throwable;)Ljava/lang/Throwable;
    //   796: athrow
    //   797: aload_3
    //   798: getstatic burp/Zl15.ZI : Ljava/lang/String;
    //   801: getstatic burp/Zmly.ZT : Ljava/lang/Object;
    //   804: checkcast java/math/BigInteger
    //   807: invokevirtual intValue : ()I
    //   810: bipush #32
    //   812: irem
    //   813: invokestatic abs : (I)I
    //   816: invokevirtual charAt : (I)C
    //   819: invokevirtual append : (C)Ljava/lang/StringBuilder;
    //   822: pop
    //   823: iload_2
    //   824: ifne -> 1348
    //   827: goto -> 834
    //   830: invokestatic a : (Ljava/lang/Throwable;)Ljava/lang/Throwable;
    //   833: athrow
    //   834: aload_3
    //   835: getstatic burp/Zl1z.Zh : Ljava/lang/String;
    //   838: getstatic burp/Zr4z.ZH : Ljava/lang/Object;
    //   841: checkcast java/math/BigInteger
    //   844: invokevirtual intValue : ()I
    //   847: bipush #32
    //   849: irem
    //   850: invokestatic abs : (I)I
    //   853: invokevirtual charAt : (I)C
    //   856: invokevirtual append : (C)Ljava/lang/StringBuilder;
    //   859: pop
    //   860: iload_2
    //   861: ifne -> 1348
    //   864: goto -> 871
    //   867: invokestatic a : (Ljava/lang/Throwable;)Ljava/lang/Throwable;
    //   870: athrow
    //   871: aload_3
    //   872: getstatic burp/Ze9.Zh : Ljava/lang/String;
    //   875: getstatic burp/Ztsc.Zr : Ljava/lang/Object;
    //   878: checkcast java/math/BigInteger
    //   881: invokevirtual intValue : ()I
    //   884: bipush #32
    //   886: irem
    //   887: invokestatic abs : (I)I
    //   890: invokevirtual charAt : (I)C
    //   893: invokevirtual append : (C)Ljava/lang/StringBuilder;
    //   896: pop
    //   897: iload_2
    //   898: ifne -> 1348
    //   901: goto -> 908
    //   904: invokestatic a : (Ljava/lang/Throwable;)Ljava/lang/Throwable;
    //   907: athrow
    //   908: aload_3
    //   909: getstatic burp/Zzh9.ZF : Ljava/lang/String;
    //   912: getstatic burp/Zrx5.ZE : Ljava/lang/Object;
    //   915: checkcast java/math/BigInteger
    //   918: invokevirtual intValue : ()I
    //   921: bipush #32
    //   923: irem
    //   924: invokestatic abs : (I)I
    //   927: invokevirtual charAt : (I)C
    //   930: invokevirtual append : (C)Ljava/lang/StringBuilder;
    //   933: pop
    //   934: iload_2
    //   935: ifne -> 1348
    //   938: goto -> 945
    //   941: invokestatic a : (Ljava/lang/Throwable;)Ljava/lang/Throwable;
    //   944: athrow
    //   945: aload_3
    //   946: getstatic burp/Zrh1.Zg : Ljava/lang/String;
    //   949: getstatic burp/Zmly.ZT : Ljava/lang/Object;
    //   952: checkcast java/math/BigInteger
    //   955: invokevirtual intValue : ()I
    //   958: bipush #32
    //   960: irem
    //   961: invokestatic abs : (I)I
    //   964: invokevirtual charAt : (I)C
    //   967: invokevirtual append : (C)Ljava/lang/StringBuilder;
    //   970: pop
    //   971: iload_2
    //   972: ifne -> 1348
    //   975: goto -> 982
    //   978: invokestatic a : (Ljava/lang/Throwable;)Ljava/lang/Throwable;
    //   981: athrow
    //   982: aload_3
    //   983: getstatic burp/Zlvx.Zr : Ljava/lang/String;
    //   986: getstatic burp/Zbxa.ZS : Ljava/lang/Object;
    //   989: checkcast java/math/BigInteger
    //   992: invokevirtual intValue : ()I
    //   995: bipush #32
    //   997: irem
    //   998: invokestatic abs : (I)I
    //   1001: invokevirtual charAt : (I)C
    //   1004: invokevirtual append : (C)Ljava/lang/StringBuilder;
    //   1007: pop
    //   1008: iload_2
    //   1009: ifne -> 1348
    //   1012: goto -> 1019
    //   1015: invokestatic a : (Ljava/lang/Throwable;)Ljava/lang/Throwable;
    //   1018: athrow
    //   1019: aload_3
    //   1020: getstatic burp/Zecm.Zv : Ljava/lang/String;
    //   1023: getstatic burp/Zktq.Zn : Ljava/lang/Object;
    //   1026: checkcast java/math/BigInteger
    //   1029: invokevirtual intValue : ()I
    //   1032: bipush #32
    //   1034: irem
    //   1035: invokestatic abs : (I)I
    //   1038: invokevirtual charAt : (I)C
    //   1041: invokevirtual append : (C)Ljava/lang/StringBuilder;
    //   1044: pop
    //   1045: iload_2
    //   1046: ifne -> 1348
    //   1049: goto -> 1056
    //   1052: invokestatic a : (Ljava/lang/Throwable;)Ljava/lang/Throwable;
    //   1055: athrow
    //   1056: aload_3
    //   1057: getstatic burp/Zszm.Zf : Ljava/lang/String;
    //   1060: getstatic burp/Zefn.ZJ : Ljava/lang/Object;
    //   1063: checkcast java/math/BigInteger
    //   1066: invokevirtual intValue : ()I
    //   1069: bipush #32
    //   1071: irem
    //   1072: invokestatic abs : (I)I
    //   1075: invokevirtual charAt : (I)C
    //   1078: invokevirtual append : (C)Ljava/lang/StringBuilder;
    //   1081: pop
    //   1082: iload_2
    //   1083: ifne -> 1348
    //   1086: goto -> 1093
    //   1089: invokestatic a : (Ljava/lang/Throwable;)Ljava/lang/Throwable;
    //   1092: athrow
    //   1093: aload_3
    //   1094: getstatic burp/Zb8_.ZP : Ljava/lang/String;
    //   1097: getstatic burp/Zspk.ZF : Ljava/lang/Object;
    //   1100: checkcast java/math/BigInteger
    //   1103: invokevirtual intValue : ()I
    //   1106: bipush #32
    //   1108: irem
    //   1109: invokestatic abs : (I)I
    //   1112: invokevirtual charAt : (I)C
    //   1115: invokevirtual append : (C)Ljava/lang/StringBuilder;
    //   1118: pop
    //   1119: iload_2
    //   1120: ifne -> 1348
    //   1123: goto -> 1130
    //   1126: invokestatic a : (Ljava/lang/Throwable;)Ljava/lang/Throwable;
    //   1129: athrow
    //   1130: aload_3
    //   1131: getstatic burp/Zenq.ZG : Ljava/lang/String;
    //   1134: getstatic burp/Zzhu.ZW : Ljava/lang/Object;
    //   1137: checkcast java/math/BigInteger
    //   1140: invokevirtual intValue : ()I
    //   1143: bipush #32
    //   1145: irem
    //   1146: invokestatic abs : (I)I
    //   1149: invokevirtual charAt : (I)C
    //   1152: invokevirtual append : (C)Ljava/lang/StringBuilder;
    //   1155: pop
    //   1156: iload_2
    //   1157: ifne -> 1348
    //   1160: goto -> 1167
    //   1163: invokestatic a : (Ljava/lang/Throwable;)Ljava/lang/Throwable;
    //   1166: athrow
    //   1167: aload_3
    //   1168: getstatic burp/Zl15.ZI : Ljava/lang/String;
    //   1171: getstatic burp/Zt5a.Zs : Ljava/lang/Object;
    //   1174: checkcast java/math/BigInteger
    //   1177: invokevirtual intValue : ()I
    //   1180: bipush #32
    //   1182: irem
    //   1183: invokestatic abs : (I)I
    //   1186: invokevirtual charAt : (I)C
    //   1189: invokevirtual append : (C)Ljava/lang/StringBuilder;
    //   1192: pop
    //   1193: iload_2
    //   1194: ifne -> 1348
    //   1197: goto -> 1204
    //   1200: invokestatic a : (Ljava/lang/Throwable;)Ljava/lang/Throwable;
    //   1203: athrow
    //   1204: aload_3
    //   1205: getstatic burp/Zefn.Ze : Ljava/lang/String;
    //   1208: getstatic burp/Zz5l.Zb : Ljava/lang/Object;
    //   1211: checkcast java/math/BigInteger
    //   1214: invokevirtual intValue : ()I
    //   1217: bipush #32
    //   1219: irem
    //   1220: invokestatic abs : (I)I
    //   1223: invokevirtual charAt : (I)C
    //   1226: invokevirtual append : (C)Ljava/lang/StringBuilder;
    //   1229: pop
    //   1230: iload_2
    //   1231: ifne -> 1348
    //   1234: goto -> 1241
    //   1237: invokestatic a : (Ljava/lang/Throwable;)Ljava/lang/Throwable;
    //   1240: athrow
    //   1241: aload_3
    //   1242: getstatic burp/Zszm.Zf : Ljava/lang/String;
    //   1245: getstatic burp/Zbxa.ZS : Ljava/lang/Object;
    //   1248: checkcast java/math/BigInteger
    //   1251: invokevirtual intValue : ()I
    //   1254: bipush #32
    //   1256: irem
    //   1257: invokestatic abs : (I)I
    //   1260: invokevirtual charAt : (I)C
    //   1263: invokevirtual append : (C)Ljava/lang/StringBuilder;
    //   1266: pop
    //   1267: iload_2
    //   1268: ifne -> 1348
    //   1271: goto -> 1278
    //   1274: invokestatic a : (Ljava/lang/Throwable;)Ljava/lang/Throwable;
    //   1277: athrow
    //   1278: aload_3
    //   1279: getstatic burp/Zeju.ZR : Ljava/lang/String;
    //   1282: getstatic burp/Zzpj.ZI : Ljava/lang/Object;
    //   1285: checkcast java/math/BigInteger
    //   1288: invokevirtual intValue : ()I
    //   1291: bipush #32
    //   1293: irem
    //   1294: invokestatic abs : (I)I
    //   1297: invokevirtual charAt : (I)C
    //   1300: invokevirtual append : (C)Ljava/lang/StringBuilder;
    //   1303: pop
    //   1304: iload_2
    //   1305: ifne -> 1348
    //   1308: goto -> 1315
    //   1311: invokestatic a : (Ljava/lang/Throwable;)Ljava/lang/Throwable;
    //   1314: athrow
    //   1315: aload_3
    //   1316: getstatic burp/Zecm.Zv : Ljava/lang/String;
    //   1319: getstatic burp/Zmec.ZY : Ljava/lang/Object;
    //   1322: checkcast java/math/BigInteger
    //   1325: invokevirtual intValue : ()I
    //   1328: bipush #32
    //   1330: irem
    //   1331: invokestatic abs : (I)I
    //   1334: invokevirtual charAt : (I)C
    //   1337: invokevirtual append : (C)Ljava/lang/StringBuilder;
    //   1340: pop
    //   1341: goto -> 1348
    //   1344: invokestatic a : (Ljava/lang/Throwable;)Ljava/lang/Throwable;
    //   1347: athrow
    //   1348: iinc #4, 1
    //   1351: iload_2
    //   1352: ifne -> 15
    //   1355: aload_3
    //   1356: invokevirtual toString : ()Ljava/lang/String;
    //   1359: putstatic burp/Zr9j.Zc : Ljava/lang/String;
    //   1362: sipush #-8093
    //   1365: sipush #-10201
    //   1368: invokestatic a : (II)Ljava/lang/String;
    //   1371: iconst_1
    //   1372: ldc burp/Zrcx
    //   1374: invokevirtual getClassLoader : ()Ljava/lang/ClassLoader;
    //   1377: invokestatic forName : (Ljava/lang/String;ZLjava/lang/ClassLoader;)Ljava/lang/Class;
    //   1380: invokevirtual getDeclaredFields : ()[Ljava/lang/reflect/Field;
    //   1383: astore #4
    //   1385: aload #4
    //   1387: arraylength
    //   1388: istore #5
    //   1390: iconst_0
    //   1391: istore #6
    //   1393: iload #6
    //   1395: iload #5
    //   1397: if_icmpge -> 1535
    //   1400: aload #4
    //   1402: iload #6
    //   1404: aaload
    //   1405: astore #7
    //   1407: aload #7
    //   1409: invokevirtual getModifiers : ()I
    //   1412: invokestatic isStatic : (I)Z
    //   1415: ifne -> 1425
    //   1418: goto -> 1528
    //   1421: invokestatic a : (Ljava/lang/Throwable;)Ljava/lang/Throwable;
    //   1424: athrow
    //   1425: aload #7
    //   1427: invokevirtual getType : ()Ljava/lang/Class;
    //   1430: astore #8
    //   1432: aload #8
    //   1434: ifnull -> 1515
    //   1437: aload #8
    //   1439: invokevirtual isPrimitive : ()Z
    //   1442: ifne -> 1515
    //   1445: goto -> 1452
    //   1448: invokestatic a : (Ljava/lang/Throwable;)Ljava/lang/Throwable;
    //   1451: athrow
    //   1452: aload #8
    //   1454: invokevirtual getPackage : ()Ljava/lang/Package;
    //   1457: ifnull -> 1515
    //   1460: goto -> 1467
    //   1463: invokestatic a : (Ljava/lang/Throwable;)Ljava/lang/Throwable;
    //   1466: athrow
    //   1467: aload #8
    //   1469: invokevirtual getPackage : ()Ljava/lang/Package;
    //   1472: invokevirtual getName : ()Ljava/lang/String;
    //   1475: ifnull -> 1515
    //   1478: goto -> 1485
    //   1481: invokestatic a : (Ljava/lang/Throwable;)Ljava/lang/Throwable;
    //   1484: athrow
    //   1485: aload #8
    //   1487: invokevirtual getPackage : ()Ljava/lang/Package;
    //   1490: invokevirtual getName : ()Ljava/lang/String;
    //   1493: sipush #-8079
    //   1496: sipush #5463
    //   1499: invokestatic a : (II)Ljava/lang/String;
    //   1502: invokevirtual startsWith : (Ljava/lang/String;)Z
    //   1505: ifne -> 1515
    //   1508: goto -> 1515
    //   1511: invokestatic a : (Ljava/lang/Throwable;)Ljava/lang/Throwable;
    //   1514: athrow
    //   1515: aload #7
    //   1517: iconst_1
    //   1518: invokevirtual setAccessible : (Z)V
    //   1521: aload #7
    //   1523: aconst_null
    //   1524: invokevirtual get : (Ljava/lang/Object;)Ljava/lang/Object;
    //   1527: pop
    //   1528: iinc #6, 1
    //   1531: iload_2
    //   1532: ifne -> 1393
    //   1535: sipush #-8071
    //   1538: sipush #4544
    //   1541: invokestatic a : (II)Ljava/lang/String;
    //   1544: invokestatic forName : (Ljava/lang/String;)Ljava/lang/Class;
    //   1547: invokevirtual getDeclaredMethods : ()[Ljava/lang/reflect/Method;
    //   1550: astore #4
    //   1552: aload #4
    //   1554: arraylength
    //   1555: istore #5
    //   1557: iconst_0
    //   1558: istore #6
    //   1560: iload #6
    //   1562: iload #5
    //   1564: if_icmpge -> 1697
    //   1567: aload #4
    //   1569: iload #6
    //   1571: aaload
    //   1572: astore #7
    //   1574: aload #7
    //   1576: invokevirtual getParameterTypes : ()[Ljava/lang/Class;
    //   1579: pop
    //   1580: aload #7
    //   1582: invokevirtual getModifiers : ()I
    //   1585: invokestatic isStatic : (I)Z
    //   1588: ifeq -> 1683
    //   1591: aload #7
    //   1593: invokevirtual getParameterTypes : ()[Ljava/lang/Class;
    //   1596: arraylength
    //   1597: iconst_2
    //   1598: if_icmpne -> 1683
    //   1601: goto -> 1608
    //   1604: invokestatic a : (Ljava/lang/Throwable;)Ljava/lang/Throwable;
    //   1607: athrow
    //   1608: aload #7
    //   1610: invokevirtual getReturnType : ()Ljava/lang/Class;
    //   1613: getstatic java/lang/Void.TYPE : Ljava/lang/Class;
    //   1616: invokevirtual equals : (Ljava/lang/Object;)Z
    //   1619: ifeq -> 1683
    //   1622: goto -> 1629
    //   1625: invokestatic a : (Ljava/lang/Throwable;)Ljava/lang/Throwable;
    //   1628: athrow
    //   1629: aload #7
    //   1631: iconst_1
    //   1632: invokevirtual setAccessible : (Z)V
    //   1635: aload #7
    //   1637: aconst_null
    //   1638: iconst_2
    //   1639: anewarray java/lang/Object
    //   1642: dup
    //   1643: iconst_0
    //   1644: aload_0
    //   1645: aastore
    //   1646: dup
    //   1647: iconst_1
    //   1648: aload_1
    //   1649: ifnonnull -> 1667
    //   1652: goto -> 1659
    //   1655: invokestatic a : (Ljava/lang/Throwable;)Ljava/lang/Throwable;
    //   1658: athrow
    //   1659: aload_1
    //   1660: goto -> 1674
    //   1663: invokestatic a : (Ljava/lang/Throwable;)Ljava/lang/Throwable;
    //   1666: athrow
    //   1667: aload_1
    //   1668: checkcast [B
    //   1671: invokevirtual clone : ()Ljava/lang/Object;
    //   1674: aastore
    //   1675: invokevirtual invoke : (Ljava/lang/Object;[Ljava/lang/Object;)Ljava/lang/Object;
    //   1678: pop
    //   1679: iload_2
    //   1680: ifne -> 1697
    //   1683: iinc #6, 1
    //   1686: iload_2
    //   1687: ifne -> 1560
    //   1690: goto -> 1697
    //   1693: invokestatic a : (Ljava/lang/Throwable;)Ljava/lang/Throwable;
    //   1696: athrow
    //   1697: new java/io/ByteArrayOutputStream
    //   1700: dup
    //   1701: invokespecial <init> : ()V
    //   1704: astore #4
    //   1706: sipush #-8066
    //   1709: aload #4
    //   1711: sipush #202
    //   1714: invokevirtual write : (I)V
    //   1717: sipush #-21309
    //   1720: aload #4
    //   1722: sipush #254
    //   1725: invokevirtual write : (I)V
    //   1728: aload #4
    //   1730: sipush #186
    //   1733: invokevirtual write : (I)V
    //   1736: aload #4
    //   1738: sipush #190
    //   1741: invokevirtual write : (I)V
    //   1744: aload #4
    //   1746: iconst_0
    //   1747: invokevirtual write : (I)V
    //   1750: aload #4
    //   1752: iconst_1
    //   1753: invokevirtual write : (I)V
    //   1756: aload #4
    //   1758: iconst_0
    //   1759: invokevirtual write : (I)V
    //   1762: aload #4
    //   1764: bipush #50
    //   1766: invokevirtual write : (I)V
    //   1769: aload #4
    //   1771: getstatic burp/Zezn.Zh : Ljava/lang/Object;
    //   1774: checkcast java/math/BigInteger
    //   1777: invokevirtual toByteArray : ()[B
    //   1780: invokevirtual write : ([B)V
    //   1783: aload #4
    //   1785: getstatic burp/Zsqi.Zf : Ljava/lang/Object;
    //   1788: checkcast java/math/BigInteger
    //   1791: invokevirtual toByteArray : ()[B
    //   1794: invokevirtual write : ([B)V
    //   1797: aload #4
    //   1799: getstatic burp/Zeqr.ZM : Ljava/lang/Object;
    //   1802: checkcast java/math/BigInteger
    //   1805: invokevirtual toByteArray : ()[B
    //   1808: invokevirtual write : ([B)V
    //   1811: aload #4
    //   1813: invokevirtual toByteArray : ()[B
    //   1816: astore #5
    //   1818: aconst_null
    //   1819: astore #6
    //   1821: invokestatic a : (II)Ljava/lang/String;
    //   1824: invokestatic forName : (Ljava/lang/String;)Ljava/lang/Class;
    //   1827: invokevirtual getDeclaredMethods : ()[Ljava/lang/reflect/Method;
    //   1830: astore #7
    //   1832: aload #7
    //   1834: arraylength
    //   1835: istore #8
    //   1837: iconst_0
    //   1838: istore #9
    //   1840: iload #9
    //   1842: iload #8
    //   1844: if_icmpge -> 1972
    //   1847: aload #7
    //   1849: iload #9
    //   1851: aaload
    //   1852: astore #10
    //   1854: aload #10
    //   1856: invokevirtual getName : ()Ljava/lang/String;
    //   1859: sipush #-8082
    //   1862: sipush #-19645
    //   1865: invokestatic a : (II)Ljava/lang/String;
    //   1868: invokevirtual equals : (Ljava/lang/Object;)Z
    //   1871: ifeq -> 1965
    //   1874: aload #10
    //   1876: invokevirtual getParameterTypes : ()[Ljava/lang/Class;
    //   1879: astore #11
    //   1881: aload #11
    //   1883: arraylength
    //   1884: iconst_4
    //   1885: if_icmpeq -> 1895
    //   1888: goto -> 1965
    //   1891: invokestatic a : (Ljava/lang/Throwable;)Ljava/lang/Throwable;
    //   1894: athrow
    //   1895: aload #11
    //   1897: iconst_0
    //   1898: aaload
    //   1899: ldc java/lang/String
    //   1901: if_acmpeq -> 1911
    //   1904: goto -> 1965
    //   1907: invokestatic a : (Ljava/lang/Throwable;)Ljava/lang/Throwable;
    //   1910: athrow
    //   1911: aload #11
    //   1913: iconst_1
    //   1914: aaload
    //   1915: ldc [B
    //   1917: if_acmpeq -> 1927
    //   1920: goto -> 1965
    //   1923: invokestatic a : (Ljava/lang/Throwable;)Ljava/lang/Throwable;
    //   1926: athrow
    //   1927: aload #11
    //   1929: iconst_2
    //   1930: aaload
    //   1931: getstatic java/lang/Integer.TYPE : Ljava/lang/Class;
    //   1934: if_acmpeq -> 1944
    //   1937: goto -> 1965
    //   1940: invokestatic a : (Ljava/lang/Throwable;)Ljava/lang/Throwable;
    //   1943: athrow
    //   1944: aload #11
    //   1946: iconst_3
    //   1947: aaload
    //   1948: getstatic java/lang/Integer.TYPE : Ljava/lang/Class;
    //   1951: if_acmpeq -> 1961
    //   1954: goto -> 1965
    //   1957: invokestatic a : (Ljava/lang/Throwable;)Ljava/lang/Throwable;
    //   1960: athrow
    //   1961: aload #10
    //   1963: astore #6
    //   1965: iinc #9, 1
    //   1968: iload_2
    //   1969: ifne -> 1840
    //   1972: aload #6
    //   1974: iconst_1
    //   1975: invokevirtual setAccessible : (Z)V
    //   1978: ldc burp/Zb0z
    //   1980: iconst_0
    //   1981: anewarray java/lang/Class
    //   1984: invokevirtual getDeclaredConstructor : ([Ljava/lang/Class;)Ljava/lang/reflect/Constructor;
    //   1987: astore #7
    //   1989: aload #7
    //   1991: iconst_1
    //   1992: invokevirtual setAccessible : (Z)V
    //   1995: aload #6
    //   1997: aload #7
    //   1999: iconst_0
    //   2000: anewarray java/lang/Object
    //   2003: invokevirtual newInstance : ([Ljava/lang/Object;)Ljava/lang/Object;
    //   2006: iconst_4
    //   2007: anewarray java/lang/Object
    //   2010: dup
    //   2011: iconst_0
    //   2012: sipush #-8084
    //   2015: sipush #8582
    //   2018: invokestatic a : (II)Ljava/lang/String;
    //   2021: aastore
    //   2022: dup
    //   2023: iconst_1
    //   2024: aload #5
    //   2026: aastore
    //   2027: dup
    //   2028: iconst_2
    //   2029: iconst_0
    //   2030: invokestatic valueOf : (I)Ljava/lang/Integer;
    //   2033: aastore
    //   2034: dup
    //   2035: iconst_3
    //   2036: aload #5
    //   2038: arraylength
    //   2039: invokestatic valueOf : (I)Ljava/lang/Integer;
    //   2042: aastore
    //   2043: invokevirtual invoke : (Ljava/lang/Object;[Ljava/lang/Object;)Ljava/lang/Object;
    //   2046: pop
    //   2047: goto -> 2052
    //   2050: astore #4
    //   2052: iconst_0
    //   2053: istore #4
    //   2055: getstatic burp/Zso7.Zr : Ljava/lang/String;
    //   2058: getstatic burp/Zmh0.Zt : Ljava/lang/Object;
    //   2061: checkcast java/math/BigInteger
    //   2064: invokevirtual intValue : ()I
    //   2067: bipush #32
    //   2069: irem
    //   2070: invokestatic abs : (I)I
    //   2073: invokevirtual charAt : (I)C
    //   2076: getstatic burp/Zth8.ZN : Ljava/lang/String;
    //   2079: getstatic burp/Zej5.ZB : Ljava/lang/Object;
    //   2082: checkcast java/math/BigInteger
    //   2085: invokevirtual intValue : ()I
    //   2088: bipush #32
    //   2090: irem
    //   2091: invokestatic abs : (I)I
    //   2094: invokevirtual charAt : (I)C
    //   2097: if_icmple -> 2443
    //   2100: sipush #-8092
    //   2103: sipush #438
    //   2106: invokestatic a : (II)Ljava/lang/String;
    //   2109: iconst_1
    //   2110: ldc burp/Zx4k
    //   2112: invokevirtual getClassLoader : ()Ljava/lang/ClassLoader;
    //   2115: invokestatic forName : (Ljava/lang/String;ZLjava/lang/ClassLoader;)Ljava/lang/Class;
    //   2118: invokevirtual getDeclaredFields : ()[Ljava/lang/reflect/Field;
    //   2121: astore #5
    //   2123: aload #5
    //   2125: arraylength
    //   2126: istore #6
    //   2128: iconst_0
    //   2129: istore #7
    //   2131: iload #7
    //   2133: iload #6
    //   2135: if_icmpge -> 2273
    //   2138: aload #5
    //   2140: iload #7
    //   2142: aaload
    //   2143: astore #8
    //   2145: aload #8
    //   2147: invokevirtual getModifiers : ()I
    //   2150: invokestatic isStatic : (I)Z
    //   2153: ifne -> 2163
    //   2156: goto -> 2266
    //   2159: invokestatic a : (Ljava/lang/Throwable;)Ljava/lang/Throwable;
    //   2162: athrow
    //   2163: aload #8
    //   2165: invokevirtual getType : ()Ljava/lang/Class;
    //   2168: astore #9
    //   2170: aload #9
    //   2172: ifnull -> 2253
    //   2175: aload #9
    //   2177: invokevirtual isPrimitive : ()Z
    //   2180: ifne -> 2253
    //   2183: goto -> 2190
    //   2186: invokestatic a : (Ljava/lang/Throwable;)Ljava/lang/Throwable;
    //   2189: athrow
    //   2190: aload #9
    //   2192: invokevirtual getPackage : ()Ljava/lang/Package;
    //   2195: ifnull -> 2253
    //   2198: goto -> 2205
    //   2201: invokestatic a : (Ljava/lang/Throwable;)Ljava/lang/Throwable;
    //   2204: athrow
    //   2205: aload #9
    //   2207: invokevirtual getPackage : ()Ljava/lang/Package;
    //   2210: invokevirtual getName : ()Ljava/lang/String;
    //   2213: ifnull -> 2253
    //   2216: goto -> 2223
    //   2219: invokestatic a : (Ljava/lang/Throwable;)Ljava/lang/Throwable;
    //   2222: athrow
    //   2223: aload #9
    //   2225: invokevirtual getPackage : ()Ljava/lang/Package;
    //   2228: invokevirtual getName : ()Ljava/lang/String;
    //   2231: sipush #-8089
    //   2234: sipush #4027
    //   2237: invokestatic a : (II)Ljava/lang/String;
    //   2240: invokevirtual startsWith : (Ljava/lang/String;)Z
    //   2243: ifne -> 2253
    //   2246: goto -> 2253
    //   2249: invokestatic a : (Ljava/lang/Throwable;)Ljava/lang/Throwable;
    //   2252: athrow
    //   2253: aload #8
    //   2255: iconst_1
    //   2256: invokevirtual setAccessible : (Z)V
    //   2259: aload #8
    //   2261: aconst_null
    //   2262: invokevirtual get : (Ljava/lang/Object;)Ljava/lang/Object;
    //   2265: pop
    //   2266: iinc #7, 1
    //   2269: iload_2
    //   2270: ifne -> 2131
    //   2273: sipush #-8087
    //   2276: sipush #26071
    //   2279: invokestatic a : (II)Ljava/lang/String;
    //   2282: invokestatic forName : (Ljava/lang/String;)Ljava/lang/Class;
    //   2285: invokevirtual getDeclaredMethods : ()[Ljava/lang/reflect/Method;
    //   2288: astore #5
    //   2290: aload #5
    //   2292: arraylength
    //   2293: istore #6
    //   2295: iconst_0
    //   2296: istore #7
    //   2298: iload #7
    //   2300: iload #6
    //   2302: if_icmpge -> 2439
    //   2305: aload #5
    //   2307: iload #7
    //   2309: aaload
    //   2310: astore #8
    //   2312: aload #8
    //   2314: invokevirtual getParameterTypes : ()[Ljava/lang/Class;
    //   2317: pop
    //   2318: aload #8
    //   2320: invokevirtual getModifiers : ()I
    //   2323: invokestatic isStatic : (I)Z
    //   2326: ifeq -> 2425
    //   2329: aload #8
    //   2331: invokevirtual getParameterTypes : ()[Ljava/lang/Class;
    //   2334: arraylength
    //   2335: iconst_2
    //   2336: if_icmpne -> 2425
    //   2339: goto -> 2346
    //   2342: invokestatic a : (Ljava/lang/Throwable;)Ljava/lang/Throwable;
    //   2345: athrow
    //   2346: aload #8
    //   2348: invokevirtual getReturnType : ()Ljava/lang/Class;
    //   2351: getstatic java/lang/Boolean.TYPE : Ljava/lang/Class;
    //   2354: if_acmpne -> 2425
    //   2357: goto -> 2364
    //   2360: invokestatic a : (Ljava/lang/Throwable;)Ljava/lang/Throwable;
    //   2363: athrow
    //   2364: aload #8
    //   2366: iconst_1
    //   2367: invokevirtual setAccessible : (Z)V
    //   2370: aload #8
    //   2372: aconst_null
    //   2373: iconst_2
    //   2374: anewarray java/lang/Object
    //   2377: dup
    //   2378: iconst_0
    //   2379: aload_0
    //   2380: aastore
    //   2381: dup
    //   2382: iconst_1
    //   2383: aload_1
    //   2384: ifnonnull -> 2402
    //   2387: goto -> 2394
    //   2390: invokestatic a : (Ljava/lang/Throwable;)Ljava/lang/Throwable;
    //   2393: athrow
    //   2394: aload_1
    //   2395: goto -> 2409
    //   2398: invokestatic a : (Ljava/lang/Throwable;)Ljava/lang/Throwable;
    //   2401: athrow
    //   2402: aload_1
    //   2403: checkcast [B
    //   2406: invokevirtual clone : ()Ljava/lang/Object;
    //   2409: aastore
    //   2410: invokevirtual invoke : (Ljava/lang/Object;[Ljava/lang/Object;)Ljava/lang/Object;
    //   2413: checkcast java/lang/Boolean
    //   2416: invokevirtual booleanValue : ()Z
    //   2419: istore #4
    //   2421: iload_2
    //   2422: ifne -> 2439
    //   2425: iinc #7, 1
    //   2428: iload_2
    //   2429: ifne -> 2298
    //   2432: goto -> 2439
    //   2435: invokestatic a : (Ljava/lang/Throwable;)Ljava/lang/Throwable;
    //   2438: athrow
    //   2439: iload_2
    //   2440: ifne -> 2782
    //   2443: sipush #-8067
    //   2446: sipush #-29773
    //   2449: invokestatic a : (II)Ljava/lang/String;
    //   2452: iconst_1
    //   2453: ldc burp/Zkdc
    //   2455: invokevirtual getClassLoader : ()Ljava/lang/ClassLoader;
    //   2458: invokestatic forName : (Ljava/lang/String;ZLjava/lang/ClassLoader;)Ljava/lang/Class;
    //   2461: invokevirtual getDeclaredFields : ()[Ljava/lang/reflect/Field;
    //   2464: astore #5
    //   2466: aload #5
    //   2468: arraylength
    //   2469: istore #6
    //   2471: iconst_0
    //   2472: istore #7
    //   2474: iload #7
    //   2476: iload #6
    //   2478: if_icmpge -> 2616
    //   2481: aload #5
    //   2483: iload #7
    //   2485: aaload
    //   2486: astore #8
    //   2488: aload #8
    //   2490: invokevirtual getModifiers : ()I
    //   2493: invokestatic isStatic : (I)Z
    //   2496: ifne -> 2506
    //   2499: goto -> 2609
    //   2502: invokestatic a : (Ljava/lang/Throwable;)Ljava/lang/Throwable;
    //   2505: athrow
    //   2506: aload #8
    //   2508: invokevirtual getType : ()Ljava/lang/Class;
    //   2511: astore #9
    //   2513: aload #9
    //   2515: ifnull -> 2596
    //   2518: aload #9
    //   2520: invokevirtual isPrimitive : ()Z
    //   2523: ifne -> 2596
    //   2526: goto -> 2533
    //   2529: invokestatic a : (Ljava/lang/Throwable;)Ljava/lang/Throwable;
    //   2532: athrow
    //   2533: aload #9
    //   2535: invokevirtual getPackage : ()Ljava/lang/Package;
    //   2538: ifnull -> 2596
    //   2541: goto -> 2548
    //   2544: invokestatic a : (Ljava/lang/Throwable;)Ljava/lang/Throwable;
    //   2547: athrow
    //   2548: aload #9
    //   2550: invokevirtual getPackage : ()Ljava/lang/Package;
    //   2553: invokevirtual getName : ()Ljava/lang/String;
    //   2556: ifnull -> 2596
    //   2559: goto -> 2566
    //   2562: invokestatic a : (Ljava/lang/Throwable;)Ljava/lang/Throwable;
    //   2565: athrow
    //   2566: aload #9
    //   2568: invokevirtual getPackage : ()Ljava/lang/Package;
    //   2571: invokevirtual getName : ()Ljava/lang/String;
    //   2574: sipush #-8089
    //   2577: sipush #4027
    //   2580: invokestatic a : (II)Ljava/lang/String;
    //   2583: invokevirtual startsWith : (Ljava/lang/String;)Z
    //   2586: ifne -> 2596
    //   2589: goto -> 2596
    //   2592: invokestatic a : (Ljava/lang/Throwable;)Ljava/lang/Throwable;
    //   2595: athrow
    //   2596: aload #8
    //   2598: iconst_1
    //   2599: invokevirtual setAccessible : (Z)V
    //   2602: aload #8
    //   2604: aconst_null
    //   2605: invokevirtual get : (Ljava/lang/Object;)Ljava/lang/Object;
    //   2608: pop
    //   2609: iinc #7, 1
    //   2612: iload_2
    //   2613: ifne -> 2474
    //   2616: sipush #-8072
    //   2619: sipush #-13959
    //   2622: invokestatic a : (II)Ljava/lang/String;
    //   2625: invokestatic forName : (Ljava/lang/String;)Ljava/lang/Class;
    //   2628: invokevirtual getDeclaredMethods : ()[Ljava/lang/reflect/Method;
    //   2631: astore #5
    //   2633: aload #5
    //   2635: arraylength
    //   2636: istore #6
    //   2638: iconst_0
    //   2639: istore #7
    //   2641: iload #7
    //   2643: iload #6
    //   2645: if_icmpge -> 2782
    //   2648: aload #5
    //   2650: iload #7
    //   2652: aaload
    //   2653: astore #8
    //   2655: aload #8
    //   2657: invokevirtual getParameterTypes : ()[Ljava/lang/Class;
    //   2660: pop
    //   2661: aload #8
    //   2663: invokevirtual getModifiers : ()I
    //   2666: invokestatic isStatic : (I)Z
    //   2669: ifeq -> 2768
    //   2672: aload #8
    //   2674: invokevirtual getParameterTypes : ()[Ljava/lang/Class;
    //   2677: arraylength
    //   2678: iconst_2
    //   2679: if_icmpne -> 2768
    //   2682: goto -> 2689
    //   2685: invokestatic a : (Ljava/lang/Throwable;)Ljava/lang/Throwable;
    //   2688: athrow
    //   2689: aload #8
    //   2691: invokevirtual getReturnType : ()Ljava/lang/Class;
    //   2694: getstatic java/lang/Boolean.TYPE : Ljava/lang/Class;
    //   2697: if_acmpne -> 2768
    //   2700: goto -> 2707
    //   2703: invokestatic a : (Ljava/lang/Throwable;)Ljava/lang/Throwable;
    //   2706: athrow
    //   2707: aload #8
    //   2709: iconst_1
    //   2710: invokevirtual setAccessible : (Z)V
    //   2713: aload #8
    //   2715: aconst_null
    //   2716: iconst_2
    //   2717: anewarray java/lang/Object
    //   2720: dup
    //   2721: iconst_0
    //   2722: aload_0
    //   2723: aastore
    //   2724: dup
    //   2725: iconst_1
    //   2726: aload_1
    //   2727: ifnonnull -> 2745
    //   2730: goto -> 2737
    //   2733: invokestatic a : (Ljava/lang/Throwable;)Ljava/lang/Throwable;
    //   2736: athrow
    //   2737: aload_1
    //   2738: goto -> 2752
    //   2741: invokestatic a : (Ljava/lang/Throwable;)Ljava/lang/Throwable;
    //   2744: athrow
    //   2745: aload_1
    //   2746: checkcast [B
    //   2749: invokevirtual clone : ()Ljava/lang/Object;
    //   2752: aastore
    //   2753: invokevirtual invoke : (Ljava/lang/Object;[Ljava/lang/Object;)Ljava/lang/Object;
    //   2756: checkcast java/lang/Boolean
    //   2759: invokevirtual booleanValue : ()Z
    //   2762: istore #4
    //   2764: iload_2
    //   2765: ifne -> 2782
    //   2768: iinc #7, 1
    //   2771: iload_2
    //   2772: ifne -> 2641
    //   2775: goto -> 2782
    //   2778: invokestatic a : (Ljava/lang/Throwable;)Ljava/lang/Throwable;
    //   2781: athrow
    //   2782: iload #4
    //   2784: ifeq -> 2790
    //   2787: iload #4
    //   2789: ireturn
    //   2790: getstatic burp/Zre4.Zh : Ljava/lang/String;
    //   2793: getstatic burp/Zzpj.ZI : Ljava/lang/Object;
    //   2796: checkcast java/math/BigInteger
    //   2799: invokevirtual intValue : ()I
    //   2802: bipush #32
    //   2804: irem
    //   2805: invokestatic abs : (I)I
    //   2808: invokevirtual charAt : (I)C
    //   2811: getstatic burp/Zs5i.ZJ : Ljava/lang/String;
    //   2814: getstatic burp/Ze_e.Za : Ljava/lang/Object;
    //   2817: checkcast java/math/BigInteger
    //   2820: invokevirtual intValue : ()I
    //   2823: bipush #32
    //   2825: irem
    //   2826: invokestatic abs : (I)I
    //   2829: invokevirtual charAt : (I)C
    //   2832: if_icmple -> 3178
    //   2835: sipush #-8088
    //   2838: sipush #4278
    //   2841: invokestatic a : (II)Ljava/lang/String;
    //   2844: iconst_1
    //   2845: ldc burp/Zs59
    //   2847: invokevirtual getClassLoader : ()Ljava/lang/ClassLoader;
    //   2850: invokestatic forName : (Ljava/lang/String;ZLjava/lang/ClassLoader;)Ljava/lang/Class;
    //   2853: invokevirtual getDeclaredFields : ()[Ljava/lang/reflect/Field;
    //   2856: astore #5
    //   2858: aload #5
    //   2860: arraylength
    //   2861: istore #6
    //   2863: iconst_0
    //   2864: istore #7
    //   2866: iload #7
    //   2868: iload #6
    //   2870: if_icmpge -> 3008
    //   2873: aload #5
    //   2875: iload #7
    //   2877: aaload
    //   2878: astore #8
    //   2880: aload #8
    //   2882: invokevirtual getModifiers : ()I
    //   2885: invokestatic isStatic : (I)Z
    //   2888: ifne -> 2898
    //   2891: goto -> 3001
    //   2894: invokestatic a : (Ljava/lang/Throwable;)Ljava/lang/Throwable;
    //   2897: athrow
    //   2898: aload #8
    //   2900: invokevirtual getType : ()Ljava/lang/Class;
    //   2903: astore #9
    //   2905: aload #9
    //   2907: ifnull -> 2988
    //   2910: aload #9
    //   2912: invokevirtual isPrimitive : ()Z
    //   2915: ifne -> 2988
    //   2918: goto -> 2925
    //   2921: invokestatic a : (Ljava/lang/Throwable;)Ljava/lang/Throwable;
    //   2924: athrow
    //   2925: aload #9
    //   2927: invokevirtual getPackage : ()Ljava/lang/Package;
    //   2930: ifnull -> 2988
    //   2933: goto -> 2940
    //   2936: invokestatic a : (Ljava/lang/Throwable;)Ljava/lang/Throwable;
    //   2939: athrow
    //   2940: aload #9
    //   2942: invokevirtual getPackage : ()Ljava/lang/Package;
    //   2945: invokevirtual getName : ()Ljava/lang/String;
    //   2948: ifnull -> 2988
    //   2951: goto -> 2958
    //   2954: invokestatic a : (Ljava/lang/Throwable;)Ljava/lang/Throwable;
    //   2957: athrow
    //   2958: aload #9
    //   2960: invokevirtual getPackage : ()Ljava/lang/Package;
    //   2963: invokevirtual getName : ()Ljava/lang/String;
    //   2966: sipush #-8089
    //   2969: sipush #4027
    //   2972: invokestatic a : (II)Ljava/lang/String;
    //   2975: invokevirtual startsWith : (Ljava/lang/String;)Z
    //   2978: ifne -> 2988
    //   2981: goto -> 2988
    //   2984: invokestatic a : (Ljava/lang/Throwable;)Ljava/lang/Throwable;
    //   2987: athrow
    //   2988: aload #8
    //   2990: iconst_1
    //   2991: invokevirtual setAccessible : (Z)V
    //   2994: aload #8
    //   2996: aconst_null
    //   2997: invokevirtual get : (Ljava/lang/Object;)Ljava/lang/Object;
    //   3000: pop
    //   3001: iinc #7, 1
    //   3004: iload_2
    //   3005: ifne -> 2866
    //   3008: sipush #-8077
    //   3011: sipush #27406
    //   3014: invokestatic a : (II)Ljava/lang/String;
    //   3017: invokestatic forName : (Ljava/lang/String;)Ljava/lang/Class;
    //   3020: invokevirtual getDeclaredMethods : ()[Ljava/lang/reflect/Method;
    //   3023: astore #5
    //   3025: aload #5
    //   3027: arraylength
    //   3028: istore #6
    //   3030: iconst_0
    //   3031: istore #7
    //   3033: iload #7
    //   3035: iload #6
    //   3037: if_icmpge -> 3174
    //   3040: aload #5
    //   3042: iload #7
    //   3044: aaload
    //   3045: astore #8
    //   3047: aload #8
    //   3049: invokevirtual getParameterTypes : ()[Ljava/lang/Class;
    //   3052: pop
    //   3053: aload #8
    //   3055: invokevirtual getModifiers : ()I
    //   3058: invokestatic isStatic : (I)Z
    //   3061: ifeq -> 3160
    //   3064: aload #8
    //   3066: invokevirtual getParameterTypes : ()[Ljava/lang/Class;
    //   3069: arraylength
    //   3070: iconst_2
    //   3071: if_icmpne -> 3160
    //   3074: goto -> 3081
    //   3077: invokestatic a : (Ljava/lang/Throwable;)Ljava/lang/Throwable;
    //   3080: athrow
    //   3081: aload #8
    //   3083: invokevirtual getReturnType : ()Ljava/lang/Class;
    //   3086: getstatic java/lang/Boolean.TYPE : Ljava/lang/Class;
    //   3089: if_acmpne -> 3160
    //   3092: goto -> 3099
    //   3095: invokestatic a : (Ljava/lang/Throwable;)Ljava/lang/Throwable;
    //   3098: athrow
    //   3099: aload #8
    //   3101: iconst_1
    //   3102: invokevirtual setAccessible : (Z)V
    //   3105: aload #8
    //   3107: aconst_null
    //   3108: iconst_2
    //   3109: anewarray java/lang/Object
    //   3112: dup
    //   3113: iconst_0
    //   3114: aload_0
    //   3115: aastore
    //   3116: dup
    //   3117: iconst_1
    //   3118: aload_1
    //   3119: ifnonnull -> 3137
    //   3122: goto -> 3129
    //   3125: invokestatic a : (Ljava/lang/Throwable;)Ljava/lang/Throwable;
    //   3128: athrow
    //   3129: aload_1
    //   3130: goto -> 3144
    //   3133: invokestatic a : (Ljava/lang/Throwable;)Ljava/lang/Throwable;
    //   3136: athrow
    //   3137: aload_1
    //   3138: checkcast [B
    //   3141: invokevirtual clone : ()Ljava/lang/Object;
    //   3144: aastore
    //   3145: invokevirtual invoke : (Ljava/lang/Object;[Ljava/lang/Object;)Ljava/lang/Object;
    //   3148: checkcast java/lang/Boolean
    //   3151: invokevirtual booleanValue : ()Z
    //   3154: istore #4
    //   3156: iload_2
    //   3157: ifne -> 3174
    //   3160: iinc #7, 1
    //   3163: iload_2
    //   3164: ifne -> 3033
    //   3167: goto -> 3174
    //   3170: invokestatic a : (Ljava/lang/Throwable;)Ljava/lang/Throwable;
    //   3173: athrow
    //   3174: iload_2
    //   3175: ifne -> 3517
    //   3178: sipush #-8095
    //   3181: sipush #31135
    //   3184: invokestatic a : (II)Ljava/lang/String;
    //   3187: iconst_1
    //   3188: ldc burp/Zldt
    //   3190: invokevirtual getClassLoader : ()Ljava/lang/ClassLoader;
    //   3193: invokestatic forName : (Ljava/lang/String;ZLjava/lang/ClassLoader;)Ljava/lang/Class;
    //   3196: invokevirtual getDeclaredFields : ()[Ljava/lang/reflect/Field;
    //   3199: astore #5
    //   3201: aload #5
    //   3203: arraylength
    //   3204: istore #6
    //   3206: iconst_0
    //   3207: istore #7
    //   3209: iload #7
    //   3211: iload #6
    //   3213: if_icmpge -> 3351
    //   3216: aload #5
    //   3218: iload #7
    //   3220: aaload
    //   3221: astore #8
    //   3223: aload #8
    //   3225: invokevirtual getModifiers : ()I
    //   3228: invokestatic isStatic : (I)Z
    //   3231: ifne -> 3241
    //   3234: goto -> 3344
    //   3237: invokestatic a : (Ljava/lang/Throwable;)Ljava/lang/Throwable;
    //   3240: athrow
    //   3241: aload #8
    //   3243: invokevirtual getType : ()Ljava/lang/Class;
    //   3246: astore #9
    //   3248: aload #9
    //   3250: ifnull -> 3331
    //   3253: aload #9
    //   3255: invokevirtual isPrimitive : ()Z
    //   3258: ifne -> 3331
    //   3261: goto -> 3268
    //   3264: invokestatic a : (Ljava/lang/Throwable;)Ljava/lang/Throwable;
    //   3267: athrow
    //   3268: aload #9
    //   3270: invokevirtual getPackage : ()Ljava/lang/Package;
    //   3273: ifnull -> 3331
    //   3276: goto -> 3283
    //   3279: invokestatic a : (Ljava/lang/Throwable;)Ljava/lang/Throwable;
    //   3282: athrow
    //   3283: aload #9
    //   3285: invokevirtual getPackage : ()Ljava/lang/Package;
    //   3288: invokevirtual getName : ()Ljava/lang/String;
    //   3291: ifnull -> 3331
    //   3294: goto -> 3301
    //   3297: invokestatic a : (Ljava/lang/Throwable;)Ljava/lang/Throwable;
    //   3300: athrow
    //   3301: aload #9
    //   3303: invokevirtual getPackage : ()Ljava/lang/Package;
    //   3306: invokevirtual getName : ()Ljava/lang/String;
    //   3309: sipush #-8089
    //   3312: sipush #4027
    //   3315: invokestatic a : (II)Ljava/lang/String;
    //   3318: invokevirtual startsWith : (Ljava/lang/String;)Z
    //   3321: ifne -> 3331
    //   3324: goto -> 3331
    //   3327: invokestatic a : (Ljava/lang/Throwable;)Ljava/lang/Throwable;
    //   3330: athrow
    //   3331: aload #8
    //   3333: iconst_1
    //   3334: invokevirtual setAccessible : (Z)V
    //   3337: aload #8
    //   3339: aconst_null
    //   3340: invokevirtual get : (Ljava/lang/Object;)Ljava/lang/Object;
    //   3343: pop
    //   3344: iinc #7, 1
    //   3347: iload_2
    //   3348: ifne -> 3209
    //   3351: sipush #-8081
    //   3354: sipush #8548
    //   3357: invokestatic a : (II)Ljava/lang/String;
    //   3360: invokestatic forName : (Ljava/lang/String;)Ljava/lang/Class;
    //   3363: invokevirtual getDeclaredMethods : ()[Ljava/lang/reflect/Method;
    //   3366: astore #5
    //   3368: aload #5
    //   3370: arraylength
    //   3371: istore #6
    //   3373: iconst_0
    //   3374: istore #7
    //   3376: iload #7
    //   3378: iload #6
    //   3380: if_icmpge -> 3517
    //   3383: aload #5
    //   3385: iload #7
    //   3387: aaload
    //   3388: astore #8
    //   3390: aload #8
    //   3392: invokevirtual getParameterTypes : ()[Ljava/lang/Class;
    //   3395: pop
    //   3396: aload #8
    //   3398: invokevirtual getModifiers : ()I
    //   3401: invokestatic isStatic : (I)Z
    //   3404: ifeq -> 3503
    //   3407: aload #8
    //   3409: invokevirtual getParameterTypes : ()[Ljava/lang/Class;
    //   3412: arraylength
    //   3413: iconst_2
    //   3414: if_icmpne -> 3503
    //   3417: goto -> 3424
    //   3420: invokestatic a : (Ljava/lang/Throwable;)Ljava/lang/Throwable;
    //   3423: athrow
    //   3424: aload #8
    //   3426: invokevirtual getReturnType : ()Ljava/lang/Class;
    //   3429: getstatic java/lang/Boolean.TYPE : Ljava/lang/Class;
    //   3432: if_acmpne -> 3503
    //   3435: goto -> 3442
    //   3438: invokestatic a : (Ljava/lang/Throwable;)Ljava/lang/Throwable;
    //   3441: athrow
    //   3442: aload #8
    //   3444: iconst_1
    //   3445: invokevirtual setAccessible : (Z)V
    //   3448: aload #8
    //   3450: aconst_null
    //   3451: iconst_2
    //   3452: anewarray java/lang/Object
    //   3455: dup
    //   3456: iconst_0
    //   3457: aload_0
    //   3458: aastore
    //   3459: dup
    //   3460: iconst_1
    //   3461: aload_1
    //   3462: ifnonnull -> 3480
    //   3465: goto -> 3472
    //   3468: invokestatic a : (Ljava/lang/Throwable;)Ljava/lang/Throwable;
    //   3471: athrow
    //   3472: aload_1
    //   3473: goto -> 3487
    //   3476: invokestatic a : (Ljava/lang/Throwable;)Ljava/lang/Throwable;
    //   3479: athrow
    //   3480: aload_1
    //   3481: checkcast [B
    //   3484: invokevirtual clone : ()Ljava/lang/Object;
    //   3487: aastore
    //   3488: invokevirtual invoke : (Ljava/lang/Object;[Ljava/lang/Object;)Ljava/lang/Object;
    //   3491: checkcast java/lang/Boolean
    //   3494: invokevirtual booleanValue : ()Z
    //   3497: istore #4
    //   3499: iload_2
    //   3500: ifne -> 3517
    //   3503: iinc #7, 1
    //   3506: iload_2
    //   3507: ifne -> 3376
    //   3510: goto -> 3517
    //   3513: invokestatic a : (Ljava/lang/Throwable;)Ljava/lang/Throwable;
    //   3516: athrow
    //   3517: iload #4
    //   3519: ifeq -> 3525
    //   3522: iload #4
    //   3524: ireturn
    //   3525: getstatic burp/Zeqw.Zw : Ljava/lang/String;
    //   3528: getstatic burp/Zrp3.Zd : Ljava/lang/Object;
    //   3531: checkcast java/math/BigInteger
    //   3534: invokevirtual intValue : ()I
    //   3537: bipush #32
    //   3539: irem
    //   3540: invokestatic abs : (I)I
    //   3543: invokevirtual charAt : (I)C
    //   3546: getstatic burp/Zr4z.Zw : Ljava/lang/String;
    //   3549: getstatic burp/Zl15.Zn : Ljava/lang/Object;
    //   3552: checkcast java/math/BigInteger
    //   3555: invokevirtual intValue : ()I
    //   3558: bipush #32
    //   3560: irem
    //   3561: invokestatic abs : (I)I
    //   3564: invokevirtual charAt : (I)C
    //   3567: if_icmpgt -> 3913
    //   3570: sipush #-8085
    //   3573: sipush #-11286
    //   3576: invokestatic a : (II)Ljava/lang/String;
    //   3579: iconst_1
    //   3580: ldc burp/Zsvh
    //   3582: invokevirtual getClassLoader : ()Ljava/lang/ClassLoader;
    //   3585: invokestatic forName : (Ljava/lang/String;ZLjava/lang/ClassLoader;)Ljava/lang/Class;
    //   3588: invokevirtual getDeclaredFields : ()[Ljava/lang/reflect/Field;
    //   3591: astore #5
    //   3593: aload #5
    //   3595: arraylength
    //   3596: istore #6
    //   3598: iconst_0
    //   3599: istore #7
    //   3601: iload #7
    //   3603: iload #6
    //   3605: if_icmpge -> 3743
    //   3608: aload #5
    //   3610: iload #7
    //   3612: aaload
    //   3613: astore #8
    //   3615: aload #8
    //   3617: invokevirtual getModifiers : ()I
    //   3620: invokestatic isStatic : (I)Z
    //   3623: ifne -> 3633
    //   3626: goto -> 3736
    //   3629: invokestatic a : (Ljava/lang/Throwable;)Ljava/lang/Throwable;
    //   3632: athrow
    //   3633: aload #8
    //   3635: invokevirtual getType : ()Ljava/lang/Class;
    //   3638: astore #9
    //   3640: aload #9
    //   3642: ifnull -> 3723
    //   3645: aload #9
    //   3647: invokevirtual isPrimitive : ()Z
    //   3650: ifne -> 3723
    //   3653: goto -> 3660
    //   3656: invokestatic a : (Ljava/lang/Throwable;)Ljava/lang/Throwable;
    //   3659: athrow
    //   3660: aload #9
    //   3662: invokevirtual getPackage : ()Ljava/lang/Package;
    //   3665: ifnull -> 3723
    //   3668: goto -> 3675
    //   3671: invokestatic a : (Ljava/lang/Throwable;)Ljava/lang/Throwable;
    //   3674: athrow
    //   3675: aload #9
    //   3677: invokevirtual getPackage : ()Ljava/lang/Package;
    //   3680: invokevirtual getName : ()Ljava/lang/String;
    //   3683: ifnull -> 3723
    //   3686: goto -> 3693
    //   3689: invokestatic a : (Ljava/lang/Throwable;)Ljava/lang/Throwable;
    //   3692: athrow
    //   3693: aload #9
    //   3695: invokevirtual getPackage : ()Ljava/lang/Package;
    //   3698: invokevirtual getName : ()Ljava/lang/String;
    //   3701: sipush #-8089
    //   3704: sipush #4027
    //   3707: invokestatic a : (II)Ljava/lang/String;
    //   3710: invokevirtual startsWith : (Ljava/lang/String;)Z
    //   3713: ifne -> 3723
    //   3716: goto -> 3723
    //   3719: invokestatic a : (Ljava/lang/Throwable;)Ljava/lang/Throwable;
    //   3722: athrow
    //   3723: aload #8
    //   3725: iconst_1
    //   3726: invokevirtual setAccessible : (Z)V
    //   3729: aload #8
    //   3731: aconst_null
    //   3732: invokevirtual get : (Ljava/lang/Object;)Ljava/lang/Object;
    //   3735: pop
    //   3736: iinc #7, 1
    //   3739: iload_2
    //   3740: ifne -> 3601
    //   3743: sipush #-8091
    //   3746: sipush #4501
    //   3749: invokestatic a : (II)Ljava/lang/String;
    //   3752: invokestatic forName : (Ljava/lang/String;)Ljava/lang/Class;
    //   3755: invokevirtual getDeclaredMethods : ()[Ljava/lang/reflect/Method;
    //   3758: astore #5
    //   3760: aload #5
    //   3762: arraylength
    //   3763: istore #6
    //   3765: iconst_0
    //   3766: istore #7
    //   3768: iload #7
    //   3770: iload #6
    //   3772: if_icmpge -> 3909
    //   3775: aload #5
    //   3777: iload #7
    //   3779: aaload
    //   3780: astore #8
    //   3782: aload #8
    //   3784: invokevirtual getParameterTypes : ()[Ljava/lang/Class;
    //   3787: pop
    //   3788: aload #8
    //   3790: invokevirtual getModifiers : ()I
    //   3793: invokestatic isStatic : (I)Z
    //   3796: ifeq -> 3895
    //   3799: aload #8
    //   3801: invokevirtual getParameterTypes : ()[Ljava/lang/Class;
    //   3804: arraylength
    //   3805: iconst_2
    //   3806: if_icmpne -> 3895
    //   3809: goto -> 3816
    //   3812: invokestatic a : (Ljava/lang/Throwable;)Ljava/lang/Throwable;
    //   3815: athrow
    //   3816: aload #8
    //   3818: invokevirtual getReturnType : ()Ljava/lang/Class;
    //   3821: getstatic java/lang/Boolean.TYPE : Ljava/lang/Class;
    //   3824: if_acmpne -> 3895
    //   3827: goto -> 3834
    //   3830: invokestatic a : (Ljava/lang/Throwable;)Ljava/lang/Throwable;
    //   3833: athrow
    //   3834: aload #8
    //   3836: iconst_1
    //   3837: invokevirtual setAccessible : (Z)V
    //   3840: aload #8
    //   3842: aconst_null
    //   3843: iconst_2
    //   3844: anewarray java/lang/Object
    //   3847: dup
    //   3848: iconst_0
    //   3849: aload_0
    //   3850: aastore
    //   3851: dup
    //   3852: iconst_1
    //   3853: aload_1
    //   3854: ifnonnull -> 3872
    //   3857: goto -> 3864
    //   3860: invokestatic a : (Ljava/lang/Throwable;)Ljava/lang/Throwable;
    //   3863: athrow
    //   3864: aload_1
    //   3865: goto -> 3879
    //   3868: invokestatic a : (Ljava/lang/Throwable;)Ljava/lang/Throwable;
    //   3871: athrow
    //   3872: aload_1
    //   3873: checkcast [B
    //   3876: invokevirtual clone : ()Ljava/lang/Object;
    //   3879: aastore
    //   3880: invokevirtual invoke : (Ljava/lang/Object;[Ljava/lang/Object;)Ljava/lang/Object;
    //   3883: checkcast java/lang/Boolean
    //   3886: invokevirtual booleanValue : ()Z
    //   3889: istore #4
    //   3891: iload_2
    //   3892: ifne -> 3909
    //   3895: iinc #7, 1
    //   3898: iload_2
    //   3899: ifne -> 3768
    //   3902: goto -> 3909
    //   3905: invokestatic a : (Ljava/lang/Throwable;)Ljava/lang/Throwable;
    //   3908: athrow
    //   3909: iload_2
    //   3910: ifne -> 4252
    //   3913: sipush #-8080
    //   3916: sipush #13244
    //   3919: invokestatic a : (II)Ljava/lang/String;
    //   3922: iconst_1
    //   3923: ldc burp/Zl_u
    //   3925: invokevirtual getClassLoader : ()Ljava/lang/ClassLoader;
    //   3928: invokestatic forName : (Ljava/lang/String;ZLjava/lang/ClassLoader;)Ljava/lang/Class;
    //   3931: invokevirtual getDeclaredFields : ()[Ljava/lang/reflect/Field;
    //   3934: astore #5
    //   3936: aload #5
    //   3938: arraylength
    //   3939: istore #6
    //   3941: iconst_0
    //   3942: istore #7
    //   3944: iload #7
    //   3946: iload #6
    //   3948: if_icmpge -> 4086
    //   3951: aload #5
    //   3953: iload #7
    //   3955: aaload
    //   3956: astore #8
    //   3958: aload #8
    //   3960: invokevirtual getModifiers : ()I
    //   3963: invokestatic isStatic : (I)Z
    //   3966: ifne -> 3976
    //   3969: goto -> 4079
    //   3972: invokestatic a : (Ljava/lang/Throwable;)Ljava/lang/Throwable;
    //   3975: athrow
    //   3976: aload #8
    //   3978: invokevirtual getType : ()Ljava/lang/Class;
    //   3981: astore #9
    //   3983: aload #9
    //   3985: ifnull -> 4066
    //   3988: aload #9
    //   3990: invokevirtual isPrimitive : ()Z
    //   3993: ifne -> 4066
    //   3996: goto -> 4003
    //   3999: invokestatic a : (Ljava/lang/Throwable;)Ljava/lang/Throwable;
    //   4002: athrow
    //   4003: aload #9
    //   4005: invokevirtual getPackage : ()Ljava/lang/Package;
    //   4008: ifnull -> 4066
    //   4011: goto -> 4018
    //   4014: invokestatic a : (Ljava/lang/Throwable;)Ljava/lang/Throwable;
    //   4017: athrow
    //   4018: aload #9
    //   4020: invokevirtual getPackage : ()Ljava/lang/Package;
    //   4023: invokevirtual getName : ()Ljava/lang/String;
    //   4026: ifnull -> 4066
    //   4029: goto -> 4036
    //   4032: invokestatic a : (Ljava/lang/Throwable;)Ljava/lang/Throwable;
    //   4035: athrow
    //   4036: aload #9
    //   4038: invokevirtual getPackage : ()Ljava/lang/Package;
    //   4041: invokevirtual getName : ()Ljava/lang/String;
    //   4044: sipush #-8089
    //   4047: sipush #4027
    //   4050: invokestatic a : (II)Ljava/lang/String;
    //   4053: invokevirtual startsWith : (Ljava/lang/String;)Z
    //   4056: ifne -> 4066
    //   4059: goto -> 4066
    //   4062: invokestatic a : (Ljava/lang/Throwable;)Ljava/lang/Throwable;
    //   4065: athrow
    //   4066: aload #8
    //   4068: iconst_1
    //   4069: invokevirtual setAccessible : (Z)V
    //   4072: aload #8
    //   4074: aconst_null
    //   4075: invokevirtual get : (Ljava/lang/Object;)Ljava/lang/Object;
    //   4078: pop
    //   4079: iinc #7, 1
    //   4082: iload_2
    //   4083: ifne -> 3944
    //   4086: sipush #-8068
    //   4089: sipush #24816
    //   4092: invokestatic a : (II)Ljava/lang/String;
    //   4095: invokestatic forName : (Ljava/lang/String;)Ljava/lang/Class;
    //   4098: invokevirtual getDeclaredMethods : ()[Ljava/lang/reflect/Method;
    //   4101: astore #5
    //   4103: aload #5
    //   4105: arraylength
    //   4106: istore #6
    //   4108: iconst_0
    //   4109: istore #7
    //   4111: iload #7
    //   4113: iload #6
    //   4115: if_icmpge -> 4252
    //   4118: aload #5
    //   4120: iload #7
    //   4122: aaload
    //   4123: astore #8
    //   4125: aload #8
    //   4127: invokevirtual getParameterTypes : ()[Ljava/lang/Class;
    //   4130: pop
    //   4131: aload #8
    //   4133: invokevirtual getModifiers : ()I
    //   4136: invokestatic isStatic : (I)Z
    //   4139: ifeq -> 4238
    //   4142: aload #8
    //   4144: invokevirtual getParameterTypes : ()[Ljava/lang/Class;
    //   4147: arraylength
    //   4148: iconst_2
    //   4149: if_icmpne -> 4238
    //   4152: goto -> 4159
    //   4155: invokestatic a : (Ljava/lang/Throwable;)Ljava/lang/Throwable;
    //   4158: athrow
    //   4159: aload #8
    //   4161: invokevirtual getReturnType : ()Ljava/lang/Class;
    //   4164: getstatic java/lang/Boolean.TYPE : Ljava/lang/Class;
    //   4167: if_acmpne -> 4238
    //   4170: goto -> 4177
    //   4173: invokestatic a : (Ljava/lang/Throwable;)Ljava/lang/Throwable;
    //   4176: athrow
    //   4177: aload #8
    //   4179: iconst_1
    //   4180: invokevirtual setAccessible : (Z)V
    //   4183: aload #8
    //   4185: aconst_null
    //   4186: iconst_2
    //   4187: anewarray java/lang/Object
    //   4190: dup
    //   4191: iconst_0
    //   4192: aload_0
    //   4193: aastore
    //   4194: dup
    //   4195: iconst_1
    //   4196: aload_1
    //   4197: ifnonnull -> 4215
    //   4200: goto -> 4207
    //   4203: invokestatic a : (Ljava/lang/Throwable;)Ljava/lang/Throwable;
    //   4206: athrow
    //   4207: aload_1
    //   4208: goto -> 4222
    //   4211: invokestatic a : (Ljava/lang/Throwable;)Ljava/lang/Throwable;
    //   4214: athrow
    //   4215: aload_1
    //   4216: checkcast [B
    //   4219: invokevirtual clone : ()Ljava/lang/Object;
    //   4222: aastore
    //   4223: invokevirtual invoke : (Ljava/lang/Object;[Ljava/lang/Object;)Ljava/lang/Object;
    //   4226: checkcast java/lang/Boolean
    //   4229: invokevirtual booleanValue : ()Z
    //   4232: istore #4
    //   4234: iload_2
    //   4235: ifne -> 4252
    //   4238: iinc #7, 1
    //   4241: iload_2
    //   4242: ifne -> 4111
    //   4245: goto -> 4252
    //   4248: invokestatic a : (Ljava/lang/Throwable;)Ljava/lang/Throwable;
    //   4251: athrow
    //   4252: iload #4
    //   4254: ifeq -> 4260
    //   4257: iload #4
    //   4259: ireturn
    //   4260: getstatic burp/Zrp3.Zf : Ljava/lang/String;
    //   4263: getstatic burp/Zg5.Zs : Ljava/lang/Object;
    //   4266: checkcast java/math/BigInteger
    //   4269: invokevirtual intValue : ()I
    //   4272: bipush #32
    //   4274: irem
    //   4275: invokestatic abs : (I)I
    //   4278: invokevirtual charAt : (I)C
    //   4281: getstatic burp/Zmvk.Z_ : Ljava/lang/String;
    //   4284: getstatic burp/Zrx5.ZE : Ljava/lang/Object;
    //   4287: checkcast java/math/BigInteger
    //   4290: invokevirtual intValue : ()I
    //   4293: bipush #32
    //   4295: irem
    //   4296: invokestatic abs : (I)I
    //   4299: invokevirtual charAt : (I)C
    //   4302: if_icmple -> 4648
    //   4305: sipush #-8094
    //   4308: sipush #-13974
    //   4311: invokestatic a : (II)Ljava/lang/String;
    //   4314: iconst_1
    //   4315: ldc burp/Zr4k
    //   4317: invokevirtual getClassLoader : ()Ljava/lang/ClassLoader;
    //   4320: invokestatic forName : (Ljava/lang/String;ZLjava/lang/ClassLoader;)Ljava/lang/Class;
    //   4323: invokevirtual getDeclaredFields : ()[Ljava/lang/reflect/Field;
    //   4326: astore #5
    //   4328: aload #5
    //   4330: arraylength
    //   4331: istore #6
    //   4333: iconst_0
    //   4334: istore #7
    //   4336: iload #7
    //   4338: iload #6
    //   4340: if_icmpge -> 4478
    //   4343: aload #5
    //   4345: iload #7
    //   4347: aaload
    //   4348: astore #8
    //   4350: aload #8
    //   4352: invokevirtual getModifiers : ()I
    //   4355: invokestatic isStatic : (I)Z
    //   4358: ifne -> 4368
    //   4361: goto -> 4471
    //   4364: invokestatic a : (Ljava/lang/Throwable;)Ljava/lang/Throwable;
    //   4367: athrow
    //   4368: aload #8
    //   4370: invokevirtual getType : ()Ljava/lang/Class;
    //   4373: astore #9
    //   4375: aload #9
    //   4377: ifnull -> 4458
    //   4380: aload #9
    //   4382: invokevirtual isPrimitive : ()Z
    //   4385: ifne -> 4458
    //   4388: goto -> 4395
    //   4391: invokestatic a : (Ljava/lang/Throwable;)Ljava/lang/Throwable;
    //   4394: athrow
    //   4395: aload #9
    //   4397: invokevirtual getPackage : ()Ljava/lang/Package;
    //   4400: ifnull -> 4458
    //   4403: goto -> 4410
    //   4406: invokestatic a : (Ljava/lang/Throwable;)Ljava/lang/Throwable;
    //   4409: athrow
    //   4410: aload #9
    //   4412: invokevirtual getPackage : ()Ljava/lang/Package;
    //   4415: invokevirtual getName : ()Ljava/lang/String;
    //   4418: ifnull -> 4458
    //   4421: goto -> 4428
    //   4424: invokestatic a : (Ljava/lang/Throwable;)Ljava/lang/Throwable;
    //   4427: athrow
    //   4428: aload #9
    //   4430: invokevirtual getPackage : ()Ljava/lang/Package;
    //   4433: invokevirtual getName : ()Ljava/lang/String;
    //   4436: sipush #-8089
    //   4439: sipush #4027
    //   4442: invokestatic a : (II)Ljava/lang/String;
    //   4445: invokevirtual startsWith : (Ljava/lang/String;)Z
    //   4448: ifne -> 4458
    //   4451: goto -> 4458
    //   4454: invokestatic a : (Ljava/lang/Throwable;)Ljava/lang/Throwable;
    //   4457: athrow
    //   4458: aload #8
    //   4460: iconst_1
    //   4461: invokevirtual setAccessible : (Z)V
    //   4464: aload #8
    //   4466: aconst_null
    //   4467: invokevirtual get : (Ljava/lang/Object;)Ljava/lang/Object;
    //   4470: pop
    //   4471: iinc #7, 1
    //   4474: iload_2
    //   4475: ifne -> 4336
    //   4478: sipush #-8086
    //   4481: sipush #-8845
    //   4484: invokestatic a : (II)Ljava/lang/String;
    //   4487: invokestatic forName : (Ljava/lang/String;)Ljava/lang/Class;
    //   4490: invokevirtual getDeclaredMethods : ()[Ljava/lang/reflect/Method;
    //   4493: astore #5
    //   4495: aload #5
    //   4497: arraylength
    //   4498: istore #6
    //   4500: iconst_0
    //   4501: istore #7
    //   4503: iload #7
    //   4505: iload #6
    //   4507: if_icmpge -> 4644
    //   4510: aload #5
    //   4512: iload #7
    //   4514: aaload
    //   4515: astore #8
    //   4517: aload #8
    //   4519: invokevirtual getParameterTypes : ()[Ljava/lang/Class;
    //   4522: pop
    //   4523: aload #8
    //   4525: invokevirtual getModifiers : ()I
    //   4528: invokestatic isStatic : (I)Z
    //   4531: ifeq -> 4630
    //   4534: aload #8
    //   4536: invokevirtual getParameterTypes : ()[Ljava/lang/Class;
    //   4539: arraylength
    //   4540: iconst_2
    //   4541: if_icmpne -> 4630
    //   4544: goto -> 4551
    //   4547: invokestatic a : (Ljava/lang/Throwable;)Ljava/lang/Throwable;
    //   4550: athrow
    //   4551: aload #8
    //   4553: invokevirtual getReturnType : ()Ljava/lang/Class;
    //   4556: getstatic java/lang/Boolean.TYPE : Ljava/lang/Class;
    //   4559: if_acmpne -> 4630
    //   4562: goto -> 4569
    //   4565: invokestatic a : (Ljava/lang/Throwable;)Ljava/lang/Throwable;
    //   4568: athrow
    //   4569: aload #8
    //   4571: iconst_1
    //   4572: invokevirtual setAccessible : (Z)V
    //   4575: aload #8
    //   4577: aconst_null
    //   4578: iconst_2
    //   4579: anewarray java/lang/Object
    //   4582: dup
    //   4583: iconst_0
    //   4584: aload_0
    //   4585: aastore
    //   4586: dup
    //   4587: iconst_1
    //   4588: aload_1
    //   4589: ifnonnull -> 4607
    //   4592: goto -> 4599
    //   4595: invokestatic a : (Ljava/lang/Throwable;)Ljava/lang/Throwable;
    //   4598: athrow
    //   4599: aload_1
    //   4600: goto -> 4614
    //   4603: invokestatic a : (Ljava/lang/Throwable;)Ljava/lang/Throwable;
    //   4606: athrow
    //   4607: aload_1
    //   4608: checkcast [B
    //   4611: invokevirtual clone : ()Ljava/lang/Object;
    //   4614: aastore
    //   4615: invokevirtual invoke : (Ljava/lang/Object;[Ljava/lang/Object;)Ljava/lang/Object;
    //   4618: checkcast java/lang/Boolean
    //   4621: invokevirtual booleanValue : ()Z
    //   4624: istore #4
    //   4626: iload_2
    //   4627: ifne -> 4644
    //   4630: iinc #7, 1
    //   4633: iload_2
    //   4634: ifne -> 4503
    //   4637: goto -> 4644
    //   4640: invokestatic a : (Ljava/lang/Throwable;)Ljava/lang/Throwable;
    //   4643: athrow
    //   4644: iload_2
    //   4645: ifne -> 4987
    //   4648: sipush #-8069
    //   4651: sipush #17412
    //   4654: invokestatic a : (II)Ljava/lang/String;
    //   4657: iconst_1
    //   4658: ldc burp/Zkc8
    //   4660: invokevirtual getClassLoader : ()Ljava/lang/ClassLoader;
    //   4663: invokestatic forName : (Ljava/lang/String;ZLjava/lang/ClassLoader;)Ljava/lang/Class;
    //   4666: invokevirtual getDeclaredFields : ()[Ljava/lang/reflect/Field;
    //   4669: astore #5
    //   4671: aload #5
    //   4673: arraylength
    //   4674: istore #6
    //   4676: iconst_0
    //   4677: istore #7
    //   4679: iload #7
    //   4681: iload #6
    //   4683: if_icmpge -> 4821
    //   4686: aload #5
    //   4688: iload #7
    //   4690: aaload
    //   4691: astore #8
    //   4693: aload #8
    //   4695: invokevirtual getModifiers : ()I
    //   4698: invokestatic isStatic : (I)Z
    //   4701: ifne -> 4711
    //   4704: goto -> 4814
    //   4707: invokestatic a : (Ljava/lang/Throwable;)Ljava/lang/Throwable;
    //   4710: athrow
    //   4711: aload #8
    //   4713: invokevirtual getType : ()Ljava/lang/Class;
    //   4716: astore #9
    //   4718: aload #9
    //   4720: ifnull -> 4801
    //   4723: aload #9
    //   4725: invokevirtual isPrimitive : ()Z
    //   4728: ifne -> 4801
    //   4731: goto -> 4738
    //   4734: invokestatic a : (Ljava/lang/Throwable;)Ljava/lang/Throwable;
    //   4737: athrow
    //   4738: aload #9
    //   4740: invokevirtual getPackage : ()Ljava/lang/Package;
    //   4743: ifnull -> 4801
    //   4746: goto -> 4753
    //   4749: invokestatic a : (Ljava/lang/Throwable;)Ljava/lang/Throwable;
    //   4752: athrow
    //   4753: aload #9
    //   4755: invokevirtual getPackage : ()Ljava/lang/Package;
    //   4758: invokevirtual getName : ()Ljava/lang/String;
    //   4761: ifnull -> 4801
    //   4764: goto -> 4771
    //   4767: invokestatic a : (Ljava/lang/Throwable;)Ljava/lang/Throwable;
    //   4770: athrow
    //   4771: aload #9
    //   4773: invokevirtual getPackage : ()Ljava/lang/Package;
    //   4776: invokevirtual getName : ()Ljava/lang/String;
    //   4779: sipush #-8089
    //   4782: sipush #4027
    //   4785: invokestatic a : (II)Ljava/lang/String;
    //   4788: invokevirtual startsWith : (Ljava/lang/String;)Z
    //   4791: ifne -> 4801
    //   4794: goto -> 4801
    //   4797: invokestatic a : (Ljava/lang/Throwable;)Ljava/lang/Throwable;
    //   4800: athrow
    //   4801: aload #8
    //   4803: iconst_1
    //   4804: invokevirtual setAccessible : (Z)V
    //   4807: aload #8
    //   4809: aconst_null
    //   4810: invokevirtual get : (Ljava/lang/Object;)Ljava/lang/Object;
    //   4813: pop
    //   4814: iinc #7, 1
    //   4817: iload_2
    //   4818: ifne -> 4679
    //   4821: sipush #-8070
    //   4824: sipush #-13447
    //   4827: invokestatic a : (II)Ljava/lang/String;
    //   4830: invokestatic forName : (Ljava/lang/String;)Ljava/lang/Class;
    //   4833: invokevirtual getDeclaredMethods : ()[Ljava/lang/reflect/Method;
    //   4836: astore #5
    //   4838: aload #5
    //   4840: arraylength
    //   4841: istore #6
    //   4843: iconst_0
    //   4844: istore #7
    //   4846: iload #7
    //   4848: iload #6
    //   4850: if_icmpge -> 4987
    //   4853: aload #5
    //   4855: iload #7
    //   4857: aaload
    //   4858: astore #8
    //   4860: aload #8
    //   4862: invokevirtual getParameterTypes : ()[Ljava/lang/Class;
    //   4865: pop
    //   4866: aload #8
    //   4868: invokevirtual getModifiers : ()I
    //   4871: invokestatic isStatic : (I)Z
    //   4874: ifeq -> 4973
    //   4877: aload #8
    //   4879: invokevirtual getParameterTypes : ()[Ljava/lang/Class;
    //   4882: arraylength
    //   4883: iconst_2
    //   4884: if_icmpne -> 4973
    //   4887: goto -> 4894
    //   4890: invokestatic a : (Ljava/lang/Throwable;)Ljava/lang/Throwable;
    //   4893: athrow
    //   4894: aload #8
    //   4896: invokevirtual getReturnType : ()Ljava/lang/Class;
    //   4899: getstatic java/lang/Boolean.TYPE : Ljava/lang/Class;
    //   4902: if_acmpne -> 4973
    //   4905: goto -> 4912
    //   4908: invokestatic a : (Ljava/lang/Throwable;)Ljava/lang/Throwable;
    //   4911: athrow
    //   4912: aload #8
    //   4914: iconst_1
    //   4915: invokevirtual setAccessible : (Z)V
    //   4918: aload #8
    //   4920: aconst_null
    //   4921: iconst_2
    //   4922: anewarray java/lang/Object
    //   4925: dup
    //   4926: iconst_0
    //   4927: aload_0
    //   4928: aastore
    //   4929: dup
    //   4930: iconst_1
    //   4931: aload_1
    //   4932: ifnonnull -> 4950
    //   4935: goto -> 4942
    //   4938: invokestatic a : (Ljava/lang/Throwable;)Ljava/lang/Throwable;
    //   4941: athrow
    //   4942: aload_1
    //   4943: goto -> 4957
    //   4946: invokestatic a : (Ljava/lang/Throwable;)Ljava/lang/Throwable;
    //   4949: athrow
    //   4950: aload_1
    //   4951: checkcast [B
    //   4954: invokevirtual clone : ()Ljava/lang/Object;
    //   4957: aastore
    //   4958: invokevirtual invoke : (Ljava/lang/Object;[Ljava/lang/Object;)Ljava/lang/Object;
    //   4961: checkcast java/lang/Boolean
    //   4964: invokevirtual booleanValue : ()Z
    //   4967: istore #4
    //   4969: iload_2
    //   4970: ifne -> 4987
    //   4973: iinc #7, 1
    //   4976: iload_2
    //   4977: ifne -> 4846
    //   4980: goto -> 4987
    //   4983: invokestatic a : (Ljava/lang/Throwable;)Ljava/lang/Throwable;
    //   4986: athrow
    //   4987: iload #4
    //   4989: ireturn
    //   4990: astore_3
    //   4991: new java/lang/Exception
    //   4994: dup
    //   4995: aload_3
    //   4996: invokevirtual getMessage : ()Ljava/lang/String;
    //   4999: invokespecial <init> : (Ljava/lang/String;)V
    //   5002: athrow
    // Exception table:
    //   from	to	target	type
    //   4	2789	4990	java/lang/Throwable
    //   22	198	201	java/lang/Throwable
    //   168	235	238	java/lang/Throwable
    //   205	272	275	java/lang/Throwable
    //   242	309	312	java/lang/Throwable
    //   279	346	349	java/lang/Throwable
    //   316	383	386	java/lang/Throwable
    //   353	420	423	java/lang/Throwable
    //   390	457	460	java/lang/Throwable
    //   427	494	497	java/lang/Throwable
    //   464	531	534	java/lang/Throwable
    //   501	568	571	java/lang/Throwable
    //   538	605	608	java/lang/Throwable
    //   575	642	645	java/lang/Throwable
    //   612	679	682	java/lang/Throwable
    //   649	716	719	java/lang/Throwable
    //   686	753	756	java/lang/Throwable
    //   723	790	793	java/lang/Throwable
    //   760	827	830	java/lang/Throwable
    //   797	864	867	java/lang/Throwable
    //   834	901	904	java/lang/Throwable
    //   871	938	941	java/lang/Throwable
    //   908	975	978	java/lang/Throwable
    //   945	1012	1015	java/lang/Throwable
    //   982	1049	1052	java/lang/Throwable
    //   1019	1086	1089	java/lang/Throwable
    //   1056	1123	1126	java/lang/Throwable
    //   1093	1160	1163	java/lang/Throwable
    //   1130	1197	1200	java/lang/Throwable
    //   1167	1234	1237	java/lang/Throwable
    //   1204	1271	1274	java/lang/Throwable
    //   1241	1308	1311	java/lang/Throwable
    //   1278	1341	1344	java/lang/Throwable
    //   1407	1421	1421	java/lang/Throwable
    //   1432	1445	1448	java/lang/Throwable
    //   1437	1460	1463	java/lang/Throwable
    //   1452	1478	1481	java/lang/Throwable
    //   1467	1508	1511	java/lang/Throwable
    //   1574	1601	1604	java/lang/Throwable
    //   1591	1622	1625	java/lang/Throwable
    //   1608	1652	1655	java/lang/Throwable
    //   1629	1663	1663	java/lang/Throwable
    //   1674	1690	1693	java/lang/Throwable
    //   1697	2047	2050	java/lang/Throwable
    //   1881	1891	1891	java/lang/Throwable
    //   1895	1907	1907	java/lang/Throwable
    //   1911	1923	1923	java/lang/Throwable
    //   1927	1940	1940	java/lang/Throwable
    //   1944	1957	1957	java/lang/Throwable
    //   2145	2159	2159	java/lang/Throwable
    //   2170	2183	2186	java/lang/Throwable
    //   2175	2198	2201	java/lang/Throwable
    //   2190	2216	2219	java/lang/Throwable
    //   2205	2246	2249	java/lang/Throwable
    //   2312	2339	2342	java/lang/Throwable
    //   2329	2357	2360	java/lang/Throwable
    //   2346	2387	2390	java/lang/Throwable
    //   2364	2398	2398	java/lang/Throwable
    //   2421	2432	2435	java/lang/Throwable
    //   2488	2502	2502	java/lang/Throwable
    //   2513	2526	2529	java/lang/Throwable
    //   2518	2541	2544	java/lang/Throwable
    //   2533	2559	2562	java/lang/Throwable
    //   2548	2589	2592	java/lang/Throwable
    //   2655	2682	2685	java/lang/Throwable
    //   2672	2700	2703	java/lang/Throwable
    //   2689	2730	2733	java/lang/Throwable
    //   2707	2741	2741	java/lang/Throwable
    //   2764	2775	2778	java/lang/Throwable
    //   2790	3524	4990	java/lang/Throwable
    //   2880	2894	2894	java/lang/Throwable
    //   2905	2918	2921	java/lang/Throwable
    //   2910	2933	2936	java/lang/Throwable
    //   2925	2951	2954	java/lang/Throwable
    //   2940	2981	2984	java/lang/Throwable
    //   3047	3074	3077	java/lang/Throwable
    //   3064	3092	3095	java/lang/Throwable
    //   3081	3122	3125	java/lang/Throwable
    //   3099	3133	3133	java/lang/Throwable
    //   3156	3167	3170	java/lang/Throwable
    //   3223	3237	3237	java/lang/Throwable
    //   3248	3261	3264	java/lang/Throwable
    //   3253	3276	3279	java/lang/Throwable
    //   3268	3294	3297	java/lang/Throwable
    //   3283	3324	3327	java/lang/Throwable
    //   3390	3417	3420	java/lang/Throwable
    //   3407	3435	3438	java/lang/Throwable
    //   3424	3465	3468	java/lang/Throwable
    //   3442	3476	3476	java/lang/Throwable
    //   3499	3510	3513	java/lang/Throwable
    //   3525	4259	4990	java/lang/Throwable
    //   3615	3629	3629	java/lang/Throwable
    //   3640	3653	3656	java/lang/Throwable
    //   3645	3668	3671	java/lang/Throwable
    //   3660	3686	3689	java/lang/Throwable
    //   3675	3716	3719	java/lang/Throwable
    //   3782	3809	3812	java/lang/Throwable
    //   3799	3827	3830	java/lang/Throwable
    //   3816	3857	3860	java/lang/Throwable
    //   3834	3868	3868	java/lang/Throwable
    //   3891	3902	3905	java/lang/Throwable
    //   3958	3972	3972	java/lang/Throwable
    //   3983	3996	3999	java/lang/Throwable
    //   3988	4011	4014	java/lang/Throwable
    //   4003	4029	4032	java/lang/Throwable
    //   4018	4059	4062	java/lang/Throwable
    //   4125	4152	4155	java/lang/Throwable
    //   4142	4170	4173	java/lang/Throwable
    //   4159	4200	4203	java/lang/Throwable
    //   4177	4211	4211	java/lang/Throwable
    //   4234	4245	4248	java/lang/Throwable
    //   4260	4989	4990	java/lang/Throwable
    //   4350	4364	4364	java/lang/Throwable
    //   4375	4388	4391	java/lang/Throwable
    //   4380	4403	4406	java/lang/Throwable
    //   4395	4421	4424	java/lang/Throwable
    //   4410	4451	4454	java/lang/Throwable
    //   4517	4544	4547	java/lang/Throwable
    //   4534	4562	4565	java/lang/Throwable
    //   4551	4592	4595	java/lang/Throwable
    //   4569	4603	4603	java/lang/Throwable
    //   4626	4637	4640	java/lang/Throwable
    //   4693	4707	4707	java/lang/Throwable
    //   4718	4731	4734	java/lang/Throwable
    //   4723	4746	4749	java/lang/Throwable
    //   4738	4764	4767	java/lang/Throwable
    //   4753	4794	4797	java/lang/Throwable
    //   4860	4887	4890	java/lang/Throwable
    //   4877	4905	4908	java/lang/Throwable
    //   4894	4935	4938	java/lang/Throwable
    //   4912	4946	4946	java/lang/Throwable
    //   4969	4980	4983	java/lang/Throwable
  }
  
  static void ZT(Object[] paramArrayOfObject, Object paramObject) throws Throwable {}
  
  static {
    // Byte code:
    //   0: bipush #28
    //   2: anewarray java/lang/String
    //   5: astore #5
    //   7: iconst_0
    //   8: istore_3
    //   9: ldc '<"vP/\\tkXoT4\\tPe\\tlA(*\\bjuz\\tZpPvO7` 3*\\t\\b\\r@ X7'>pJ$r'8]%zN\\t5t\\\t-S\\t`Xc\\t<"K\\t|A* /NJXk?P0GMZR+\\rq\\t[Gi\\tV0`\\r\\tGq\\tPA\\tSf&i'w\\tTD\\t %!mH\fS\\t<r\\tVe}zM3'
    //   11: dup
    //   12: astore_2
    //   13: invokevirtual length : ()I
    //   16: istore #4
    //   18: bipush #9
    //   20: istore_1
    //   21: iconst_m1
    //   22: istore_0
    //   23: bipush #72
    //   25: iinc #0, 1
    //   28: aload_2
    //   29: iload_0
    //   30: dup
    //   31: iload_1
    //   32: iadd
    //   33: invokevirtual substring : (II)Ljava/lang/String;
    //   36: iconst_m1
    //   37: goto -> 143
    //   40: aload #5
    //   42: swap
    //   43: iload_3
    //   44: iinc #3, 1
    //   47: swap
    //   48: aastore
    //   49: iload_0
    //   50: iload_1
    //   51: iadd
    //   52: dup
    //   53: istore_0
    //   54: iload #4
    //   56: if_icmpge -> 68
    //   59: aload_2
    //   60: iload_0
    //   61: invokevirtual charAt : (I)C
    //   64: istore_1
    //   65: goto -> 23
    //   68: ldc '1h!Pkkk~ \\tgK\\rq9e0im[g\\r/D@hDv8{C*)C\\tuO?n'
    //   70: dup
    //   71: astore_2
    //   72: invokevirtual length : ()I
    //   75: istore #4
    //   77: bipush #77
    //   79: istore_1
    //   80: iconst_m1
    //   81: istore_0
    //   82: bipush #125
    //   84: iinc #0, 1
    //   87: aload_2
    //   88: iload_0
    //   89: dup
    //   90: iload_1
    //   91: iadd
    //   92: invokevirtual substring : (II)Ljava/lang/String;
    //   95: iconst_0
    //   96: goto -> 143
    //   99: aload #5
    //   101: swap
    //   102: iload_3
    //   103: iinc #3, 1
    //   106: swap
    //   107: aastore
    //   108: iload_0
    //   109: iload_1
    //   110: iadd
    //   111: dup
    //   112: istore_0
    //   113: iload #4
    //   115: if_icmpge -> 127
    //   118: aload_2
    //   119: iload_0
    //   120: invokevirtual charAt : (I)C
    //   123: istore_1
    //   124: goto -> 82
    //   127: aload #5
    //   129: putstatic burp/Zrfh.a : [Ljava/lang/String;
    //   132: bipush #28
    //   134: anewarray java/lang/String
    //   137: putstatic burp/Zrfh.b : [Ljava/lang/String;
    //   140: goto -> 300
    //   143: dup_x2
    //   144: pop
    //   145: invokevirtual toCharArray : ()[C
    //   148: dup_x1
    //   149: arraylength
    //   150: dup_x2
    //   151: pop
    //   152: iconst_0
    //   153: istore #6
    //   155: dup2_x1
    //   156: pop2
    //   157: dup_x2
    //   158: iconst_1
    //   159: if_icmpgt -> 260
    //   162: dup2
    //   163: swap
    //   164: iload #6
    //   166: dup2_x1
    //   167: caload
    //   168: swap
    //   169: iload #6
    //   171: bipush #7
    //   173: irem
    //   174: tableswitch default -> 242, 0 -> 212, 1 -> 217, 2 -> 222, 3 -> 227, 4 -> 232, 5 -> 237
    //   212: bipush #32
    //   214: goto -> 244
    //   217: bipush #11
    //   219: goto -> 244
    //   222: bipush #21
    //   224: goto -> 244
    //   227: bipush #82
    //   229: goto -> 244
    //   232: bipush #84
    //   234: goto -> 244
    //   237: bipush #45
    //   239: goto -> 244
    //   242: bipush #89
    //   244: ixor
    //   245: ixor
    //   246: i2c
    //   247: castore
    //   248: iinc #6, 1
    //   251: dup
    //   252: ifne -> 260
    //   255: dup2
    //   256: dup_x1
    //   257: goto -> 166
    //   260: dup2_x1
    //   261: pop2
    //   262: dup_x2
    //   263: iload #6
    //   265: if_icmpgt -> 162
    //   268: pop
    //   269: new java/lang/String
    //   272: dup_x1
    //   273: swap
    //   274: invokespecial <init> : ([C)V
    //   277: invokevirtual intern : ()Ljava/lang/String;
    //   280: swap
    //   281: pop
    //   282: swap
    //   283: tableswitch default -> 40, 0 -> 99
    //   300: sipush #-8096
    //   303: sipush #-31595
    //   306: invokestatic a : (II)Ljava/lang/String;
    //   309: putstatic burp/Zrfh.ZH : Ljava/lang/String;
    //   312: new java/math/BigInteger
    //   315: dup
    //   316: bipush #32
    //   318: newarray byte
    //   320: dup
    //   321: iconst_0
    //   322: bipush #84
    //   324: bastore
    //   325: dup
    //   326: iconst_1
    //   327: bipush #127
    //   329: bastore
    //   330: dup
    //   331: iconst_2
    //   332: bipush #34
    //   334: bastore
    //   335: dup
    //   336: iconst_3
    //   337: bipush #-84
    //   339: bastore
    //   340: dup
    //   341: iconst_4
    //   342: bipush #-55
    //   344: bastore
    //   345: dup
    //   346: iconst_5
    //   347: bipush #43
    //   349: bastore
    //   350: dup
    //   351: bipush #6
    //   353: bipush #-38
    //   355: bastore
    //   356: dup
    //   357: bipush #7
    //   359: bipush #-28
    //   361: bastore
    //   362: dup
    //   363: bipush #8
    //   365: bipush #65
    //   367: bastore
    //   368: dup
    //   369: bipush #9
    //   371: bipush #-51
    //   373: bastore
    //   374: dup
    //   375: bipush #10
    //   377: bipush #-35
    //   379: bastore
    //   380: dup
    //   381: bipush #11
    //   383: bipush #79
    //   385: bastore
    //   386: dup
    //   387: bipush #12
    //   389: bipush #127
    //   391: bastore
    //   392: dup
    //   393: bipush #13
    //   395: bipush #125
    //   397: bastore
    //   398: dup
    //   399: bipush #14
    //   401: bipush #-72
    //   403: bastore
    //   404: dup
    //   405: bipush #15
    //   407: bipush #-26
    //   409: bastore
    //   410: dup
    //   411: bipush #16
    //   413: bipush #24
    //   415: bastore
    //   416: dup
    //   417: bipush #17
    //   419: bipush #-23
    //   421: bastore
    //   422: dup
    //   423: bipush #18
    //   425: bipush #30
    //   427: bastore
    //   428: dup
    //   429: bipush #19
    //   431: bipush #-122
    //   433: bastore
    //   434: dup
    //   435: bipush #20
    //   437: bipush #-60
    //   439: bastore
    //   440: dup
    //   441: bipush #21
    //   443: bipush #79
    //   445: bastore
    //   446: dup
    //   447: bipush #22
    //   449: bipush #-107
    //   451: bastore
    //   452: dup
    //   453: bipush #23
    //   455: bipush #77
    //   457: bastore
    //   458: dup
    //   459: bipush #24
    //   461: bipush #13
    //   463: bastore
    //   464: dup
    //   465: bipush #25
    //   467: bipush #-120
    //   469: bastore
    //   470: dup
    //   471: bipush #26
    //   473: bipush #55
    //   475: bastore
    //   476: dup
    //   477: bipush #27
    //   479: bipush #-118
    //   481: bastore
    //   482: dup
    //   483: bipush #28
    //   485: bipush #-71
    //   487: bastore
    //   488: dup
    //   489: bipush #29
    //   491: bipush #-64
    //   493: bastore
    //   494: dup
    //   495: bipush #30
    //   497: bipush #107
    //   499: bastore
    //   500: dup
    //   501: bipush #31
    //   503: bipush #67
    //   505: bastore
    //   506: invokespecial <init> : ([B)V
    //   509: putstatic burp/Zrfh.ZJ : Ljava/lang/Object;
    //   512: return
  }
  
  private static Throwable a(Throwable paramThrowable) {
    return paramThrowable;
  }
  
  private static String a(int paramInt1, int paramInt2) {
    int i = (paramInt1 ^ 0xFFFFE068) & 0xFFFF;
    if (b[i] == null) {
      char[] arrayOfChar = a[i].toCharArray();
      switch (arrayOfChar[0] & 0xFF) {
        case 0:
        
        case 1:
        
        case 2:
        
        case 3:
        
        case 4:
        
        case 5:
        
        case 6:
        
        case 7:
        
        case 8:
        
        case 9:
        
        case 10:
        
        case 11:
        
        case 12:
        
        case 13:
        
        case 14:
        
        case 15:
        
        case 16:
        
        case 17:
        
        case 18:
        
        case 19:
        
        case 20:
        
        case 21:
        
        case 22:
        
        case 23:
        
        case 24:
        
        case 25:
        
        case 26:
        
        case 27:
        
        case 28:
        
        case 29:
        
        case 30:
        
        case 31:
        
        case 32:
        
        case 33:
        
        case 34:
        
        case 35:
        
        case 36:
        
        case 37:
        
        case 38:
        
        case 39:
        
        case 40:
        
        case 41:
        
        case 42:
        
        case 43:
        
        case 44:
        
        case 45:
        
        case 46:
        
        case 47:
        
        case 48:
        
        case 49:
        
        case 50:
        
        case 51:
        
        case 52:
        
        case 53:
        
        case 54:
        
        case 55:
        
        case 56:
        
        case 57:
        
        case 58:
        
        case 59:
        
        case 60:
        
        case 61:
        
        case 62:
        
        case 63:
        
        case 64:
        
        case 65:
        
        case 66:
        
        case 67:
        
        case 68:
        
        case 69:
        
        case 70:
        
        case 71:
        
        case 72:
        
        case 73:
        
        case 74:
        
        case 75:
        
        case 76:
        
        case 77:
        
        case 78:
        
        case 79:
        
        case 80:
        
        case 81:
        
        case 82:
        
        case 83:
        
        case 84:
        
        case 85:
        
        case 86:
        
        case 87:
        
        case 88:
        
        case 89:
        
        case 90:
        
        case 91:
        
        case 92:
        
        case 93:
        
        case 94:
        
        case 95:
        
        case 96:
        
        case 97:
        
        case 98:
        
        case 99:
        
        case 100:
        
        case 101:
        
        case 102:
        
        case 103:
        
        case 104:
        
        case 105:
        
        case 106:
        
        case 107:
        
        case 108:
        
        case 109:
        
        case 110:
        
        case 111:
        
        case 112:
        
        case 113:
        
        case 114:
        
        case 115:
        
        case 116:
        
        case 117:
        
        case 118:
        
        case 119:
        
        case 120:
        
        case 121:
        
        case 122:
        
        case 123:
        
        case 124:
        
        case 125:
        
        case 126:
        
        case 127:
        
        case 128:
        
        case 129:
        
        case 130:
        
        case 131:
        
        case 132:
        
        case 133:
        
        case 134:
        
        case 135:
        
        case 136:
        
        case 137:
        
        case 138:
        
        case 139:
        
        case 140:
        
        case 141:
        
        case 142:
        
        case 143:
        
        case 144:
        
        case 145:
        
        case 146:
        
        case 147:
        
        case 148:
        
        case 149:
        
        case 150:
        
        case 151:
        
        case 152:
        
        case 153:
        
        case 154:
        
        case 155:
        
        case 156:
        
        case 157:
        
        case 158:
        
        case 159:
        
        case 160:
        
        case 161:
        
        case 162:
        
        case 163:
        
        case 164:
        
        case 165:
        
        case 166:
        
        case 167:
        
        case 168:
        
        case 169:
        
        case 170:
        
        case 171:
        
        case 172:
        
        case 173:
        
        case 174:
        
        case 175:
        
        case 176:
        
        case 177:
        
        case 178:
        
        case 179:
        
        case 180:
        
        case 181:
        
        case 182:
        
        case 183:
        
        case 184:
        
        case 185:
        
        case 186:
        
        case 187:
        
        case 188:
        
        case 189:
        
        case 190:
        
        case 191:
        
        case 192:
        
        case 193:
        
        case 194:
        
        case 195:
        
        case 196:
        
        case 197:
        
        case 198:
        
        case 199:
        
        case 200:
        
        case 201:
        
        case 202:
        
        case 203:
        
        case 204:
        
        case 205:
        
        case 206:
        
        case 207:
        
        case 208:
        
        case 209:
        
        case 210:
        
        case 211:
        
        case 212:
        
        case 213:
        
        case 214:
        
        case 215:
        
        case 216:
        
        case 217:
        
        case 218:
        
        case 219:
        
        case 220:
        
        case 221:
        
        case 222:
        
        case 223:
        
        case 224:
        
        case 225:
        
        case 226:
        
        case 227:
        
        case 228:
        
        case 229:
        
        case 230:
        
        case 231:
        
        case 232:
        
        case 233:
        
        case 234:
        
        case 235:
        
        case 236:
        
        case 237:
        
        case 238:
        
        case 239:
        
        case 240:
        
        case 241:
        
        case 242:
        
        case 243:
        
        case 244:
        
        case 245:
        
        case 246:
        
        case 247:
        
        case 248:
        
        case 249:
        
        case 250:
        
        case 251:
        
        case 252:
        
        case 253:
        
        case 254:
        
        default:
          break;
      } 
      byte b1 = 113;
      int j = (paramInt2 & 0xFF) - b1;
      if (j < 0)
        j += 256; 
      int k = ((paramInt2 & 0xFFFF) >>> 8) - b1;
      if (k < 0)
        k += 256; 
      for (byte b2 = 0; b2 < arrayOfChar.length; b2++) {
        int m = b2 % 2;
        if (m == 0) {
          arrayOfChar[b2] = (char)(arrayOfChar[b2] ^ j);
          j = ((j >>> 3 | j << 5) ^ arrayOfChar[b2]) & 0xFF;
        } else {
          arrayOfChar[b2] = (char)(arrayOfChar[b2] ^ k);
          k = ((k >>> 3 | k << 5) ^ arrayOfChar[b2]) & 0xFF;
        } 
      } 
      b[i] = (new String(arrayOfChar)).intern();
    } 
    return b[i];
  }
}


/* Location:              C:\Program Files\BurpSuitePro\burpsuite_pro.jar!\burp\Zrfh.class
 * Java compiler version: 21 (65.0)
 * JD-Core Version:       1.1.3
 */