package burp;

import java.math.BigInteger;

class Zrhu extends ClassLoader {
  static Object Zs;
  
  static String ZJ;
  
  private static final String[] a;
  
  private static final String[] b;
  
  static boolean Zi(Object[] paramArrayOfObject, Object paramObject) throws Throwable {
    // Byte code:
    //   0: invokestatic ZN : ()Z
    //   3: istore_2
    //   4: new java/lang/StringBuilder
    //   7: dup
    //   8: invokespecial <init> : ()V
    //   11: astore_3
    //   12: iconst_0
    //   13: istore #4
    //   15: iload #4
    //   17: bipush #32
    //   19: if_icmpge -> 1355
    //   22: iload #4
    //   24: tableswitch default -> 1348, 0 -> 168, 1 -> 205, 2 -> 242, 3 -> 279, 4 -> 316, 5 -> 353, 6 -> 390, 7 -> 427, 8 -> 464, 9 -> 501, 10 -> 538, 11 -> 575, 12 -> 612, 13 -> 649, 14 -> 686, 15 -> 723, 16 -> 760, 17 -> 797, 18 -> 834, 19 -> 871, 20 -> 908, 21 -> 945, 22 -> 982, 23 -> 1019, 24 -> 1056, 25 -> 1093, 26 -> 1130, 27 -> 1167, 28 -> 1204, 29 -> 1241, 30 -> 1278, 31 -> 1315
    //   168: aload_3
    //   169: getstatic burp/Zge1.Zx : Ljava/lang/String;
    //   172: getstatic burp/Zefn.ZJ : Ljava/lang/Object;
    //   175: checkcast java/math/BigInteger
    //   178: invokevirtual intValue : ()I
    //   181: bipush #32
    //   183: irem
    //   184: invokestatic abs : (I)I
    //   187: invokevirtual charAt : (I)C
    //   190: invokevirtual append : (C)Ljava/lang/StringBuilder;
    //   193: pop
    //   194: iload_2
    //   195: ifne -> 1348
    //   198: goto -> 205
    //   201: invokestatic a : (Ljava/lang/Throwable;)Ljava/lang/Throwable;
    //   204: athrow
    //   205: aload_3
    //   206: getstatic burp/Zl88.Zd : Ljava/lang/String;
    //   209: getstatic burp/Zzpu.ZS : Ljava/lang/Object;
    //   212: checkcast java/math/BigInteger
    //   215: invokevirtual intValue : ()I
    //   218: bipush #32
    //   220: irem
    //   221: invokestatic abs : (I)I
    //   224: invokevirtual charAt : (I)C
    //   227: invokevirtual append : (C)Ljava/lang/StringBuilder;
    //   230: pop
    //   231: iload_2
    //   232: ifne -> 1348
    //   235: goto -> 242
    //   238: invokestatic a : (Ljava/lang/Throwable;)Ljava/lang/Throwable;
    //   241: athrow
    //   242: aload_3
    //   243: getstatic burp/Zs15.Zs : Ljava/lang/String;
    //   246: getstatic burp/Zrom.ZF : Ljava/lang/Object;
    //   249: checkcast java/math/BigInteger
    //   252: invokevirtual intValue : ()I
    //   255: bipush #32
    //   257: irem
    //   258: invokestatic abs : (I)I
    //   261: invokevirtual charAt : (I)C
    //   264: invokevirtual append : (C)Ljava/lang/StringBuilder;
    //   267: pop
    //   268: iload_2
    //   269: ifne -> 1348
    //   272: goto -> 279
    //   275: invokestatic a : (Ljava/lang/Throwable;)Ljava/lang/Throwable;
    //   278: athrow
    //   279: aload_3
    //   280: getstatic burp/Zm54.Zg : Ljava/lang/String;
    //   283: getstatic burp/Zrva.ZE : Ljava/lang/Object;
    //   286: checkcast java/math/BigInteger
    //   289: invokevirtual intValue : ()I
    //   292: bipush #32
    //   294: irem
    //   295: invokestatic abs : (I)I
    //   298: invokevirtual charAt : (I)C
    //   301: invokevirtual append : (C)Ljava/lang/StringBuilder;
    //   304: pop
    //   305: iload_2
    //   306: ifne -> 1348
    //   309: goto -> 316
    //   312: invokestatic a : (Ljava/lang/Throwable;)Ljava/lang/Throwable;
    //   315: athrow
    //   316: aload_3
    //   317: getstatic burp/Zljx.ZD : Ljava/lang/String;
    //   320: getstatic burp/Zec0.Zg : Ljava/lang/Object;
    //   323: checkcast java/math/BigInteger
    //   326: invokevirtual intValue : ()I
    //   329: bipush #32
    //   331: irem
    //   332: invokestatic abs : (I)I
    //   335: invokevirtual charAt : (I)C
    //   338: invokevirtual append : (C)Ljava/lang/StringBuilder;
    //   341: pop
    //   342: iload_2
    //   343: ifne -> 1348
    //   346: goto -> 353
    //   349: invokestatic a : (Ljava/lang/Throwable;)Ljava/lang/Throwable;
    //   352: athrow
    //   353: aload_3
    //   354: getstatic burp/Zzi_.ZG : Ljava/lang/String;
    //   357: getstatic burp/Zsn4.ZQ : Ljava/lang/Object;
    //   360: checkcast java/math/BigInteger
    //   363: invokevirtual intValue : ()I
    //   366: bipush #32
    //   368: irem
    //   369: invokestatic abs : (I)I
    //   372: invokevirtual charAt : (I)C
    //   375: invokevirtual append : (C)Ljava/lang/StringBuilder;
    //   378: pop
    //   379: iload_2
    //   380: ifne -> 1348
    //   383: goto -> 390
    //   386: invokestatic a : (Ljava/lang/Throwable;)Ljava/lang/Throwable;
    //   389: athrow
    //   390: aload_3
    //   391: getstatic burp/Zmd.Zf : Ljava/lang/String;
    //   394: getstatic burp/Zl7k.ZS : Ljava/lang/Object;
    //   397: checkcast java/math/BigInteger
    //   400: invokevirtual intValue : ()I
    //   403: bipush #32
    //   405: irem
    //   406: invokestatic abs : (I)I
    //   409: invokevirtual charAt : (I)C
    //   412: invokevirtual append : (C)Ljava/lang/StringBuilder;
    //   415: pop
    //   416: iload_2
    //   417: ifne -> 1348
    //   420: goto -> 427
    //   423: invokestatic a : (Ljava/lang/Throwable;)Ljava/lang/Throwable;
    //   426: athrow
    //   427: aload_3
    //   428: getstatic burp/Zevf.ZL : Ljava/lang/String;
    //   431: getstatic burp/Zzox.Zq : Ljava/lang/Object;
    //   434: checkcast java/math/BigInteger
    //   437: invokevirtual intValue : ()I
    //   440: bipush #32
    //   442: irem
    //   443: invokestatic abs : (I)I
    //   446: invokevirtual charAt : (I)C
    //   449: invokevirtual append : (C)Ljava/lang/StringBuilder;
    //   452: pop
    //   453: iload_2
    //   454: ifne -> 1348
    //   457: goto -> 464
    //   460: invokestatic a : (Ljava/lang/Throwable;)Ljava/lang/Throwable;
    //   463: athrow
    //   464: aload_3
    //   465: getstatic burp/Zxxd.Za : Ljava/lang/String;
    //   468: getstatic burp/Zzok.ZY : Ljava/lang/Object;
    //   471: checkcast java/math/BigInteger
    //   474: invokevirtual intValue : ()I
    //   477: bipush #32
    //   479: irem
    //   480: invokestatic abs : (I)I
    //   483: invokevirtual charAt : (I)C
    //   486: invokevirtual append : (C)Ljava/lang/StringBuilder;
    //   489: pop
    //   490: iload_2
    //   491: ifne -> 1348
    //   494: goto -> 501
    //   497: invokestatic a : (Ljava/lang/Throwable;)Ljava/lang/Throwable;
    //   500: athrow
    //   501: aload_3
    //   502: getstatic burp/Zr04.ZA : Ljava/lang/String;
    //   505: getstatic burp/Zzok.ZY : Ljava/lang/Object;
    //   508: checkcast java/math/BigInteger
    //   511: invokevirtual intValue : ()I
    //   514: bipush #32
    //   516: irem
    //   517: invokestatic abs : (I)I
    //   520: invokevirtual charAt : (I)C
    //   523: invokevirtual append : (C)Ljava/lang/StringBuilder;
    //   526: pop
    //   527: iload_2
    //   528: ifne -> 1348
    //   531: goto -> 538
    //   534: invokestatic a : (Ljava/lang/Throwable;)Ljava/lang/Throwable;
    //   537: athrow
    //   538: aload_3
    //   539: getstatic burp/Zgd7.Zs : Ljava/lang/String;
    //   542: getstatic burp/Zbxp.ZW : Ljava/lang/Object;
    //   545: checkcast java/math/BigInteger
    //   548: invokevirtual intValue : ()I
    //   551: bipush #32
    //   553: irem
    //   554: invokestatic abs : (I)I
    //   557: invokevirtual charAt : (I)C
    //   560: invokevirtual append : (C)Ljava/lang/StringBuilder;
    //   563: pop
    //   564: iload_2
    //   565: ifne -> 1348
    //   568: goto -> 575
    //   571: invokestatic a : (Ljava/lang/Throwable;)Ljava/lang/Throwable;
    //   574: athrow
    //   575: aload_3
    //   576: getstatic burp/Zgp_.Zn : Ljava/lang/String;
    //   579: getstatic burp/Zl8i.ZY : Ljava/lang/Object;
    //   582: checkcast java/math/BigInteger
    //   585: invokevirtual intValue : ()I
    //   588: bipush #32
    //   590: irem
    //   591: invokestatic abs : (I)I
    //   594: invokevirtual charAt : (I)C
    //   597: invokevirtual append : (C)Ljava/lang/StringBuilder;
    //   600: pop
    //   601: iload_2
    //   602: ifne -> 1348
    //   605: goto -> 612
    //   608: invokestatic a : (Ljava/lang/Throwable;)Ljava/lang/Throwable;
    //   611: athrow
    //   612: aload_3
    //   613: getstatic burp/Zg3m.Za : Ljava/lang/String;
    //   616: getstatic burp/Zzef.Zw : Ljava/lang/Object;
    //   619: checkcast java/math/BigInteger
    //   622: invokevirtual intValue : ()I
    //   625: bipush #32
    //   627: irem
    //   628: invokestatic abs : (I)I
    //   631: invokevirtual charAt : (I)C
    //   634: invokevirtual append : (C)Ljava/lang/StringBuilder;
    //   637: pop
    //   638: iload_2
    //   639: ifne -> 1348
    //   642: goto -> 649
    //   645: invokestatic a : (Ljava/lang/Throwable;)Ljava/lang/Throwable;
    //   648: athrow
    //   649: aload_3
    //   650: getstatic burp/Zest.Zd : Ljava/lang/String;
    //   653: getstatic burp/Zkde.Zk : Ljava/lang/Object;
    //   656: checkcast java/math/BigInteger
    //   659: invokevirtual intValue : ()I
    //   662: bipush #32
    //   664: irem
    //   665: invokestatic abs : (I)I
    //   668: invokevirtual charAt : (I)C
    //   671: invokevirtual append : (C)Ljava/lang/StringBuilder;
    //   674: pop
    //   675: iload_2
    //   676: ifne -> 1348
    //   679: goto -> 686
    //   682: invokestatic a : (Ljava/lang/Throwable;)Ljava/lang/Throwable;
    //   685: athrow
    //   686: aload_3
    //   687: getstatic burp/Zec_.Zv : Ljava/lang/String;
    //   690: getstatic burp/Zsxo.Za : Ljava/lang/Object;
    //   693: checkcast java/math/BigInteger
    //   696: invokevirtual intValue : ()I
    //   699: bipush #32
    //   701: irem
    //   702: invokestatic abs : (I)I
    //   705: invokevirtual charAt : (I)C
    //   708: invokevirtual append : (C)Ljava/lang/StringBuilder;
    //   711: pop
    //   712: iload_2
    //   713: ifne -> 1348
    //   716: goto -> 723
    //   719: invokestatic a : (Ljava/lang/Throwable;)Ljava/lang/Throwable;
    //   722: athrow
    //   723: aload_3
    //   724: getstatic burp/Zt7k.ZH : Ljava/lang/String;
    //   727: getstatic burp/Zssb.ZW : Ljava/lang/Object;
    //   730: checkcast java/math/BigInteger
    //   733: invokevirtual intValue : ()I
    //   736: bipush #32
    //   738: irem
    //   739: invokestatic abs : (I)I
    //   742: invokevirtual charAt : (I)C
    //   745: invokevirtual append : (C)Ljava/lang/StringBuilder;
    //   748: pop
    //   749: iload_2
    //   750: ifne -> 1348
    //   753: goto -> 760
    //   756: invokestatic a : (Ljava/lang/Throwable;)Ljava/lang/Throwable;
    //   759: athrow
    //   760: aload_3
    //   761: getstatic burp/Zx4k.ZC : Ljava/lang/String;
    //   764: getstatic burp/Zrly.ZB : Ljava/lang/Object;
    //   767: checkcast java/math/BigInteger
    //   770: invokevirtual intValue : ()I
    //   773: bipush #32
    //   775: irem
    //   776: invokestatic abs : (I)I
    //   779: invokevirtual charAt : (I)C
    //   782: invokevirtual append : (C)Ljava/lang/StringBuilder;
    //   785: pop
    //   786: iload_2
    //   787: ifne -> 1348
    //   790: goto -> 797
    //   793: invokestatic a : (Ljava/lang/Throwable;)Ljava/lang/Throwable;
    //   796: athrow
    //   797: aload_3
    //   798: getstatic burp/Zr9b.ZC : Ljava/lang/String;
    //   801: getstatic burp/Zgqi.Zp : Ljava/lang/Object;
    //   804: checkcast java/math/BigInteger
    //   807: invokevirtual intValue : ()I
    //   810: bipush #32
    //   812: irem
    //   813: invokestatic abs : (I)I
    //   816: invokevirtual charAt : (I)C
    //   819: invokevirtual append : (C)Ljava/lang/StringBuilder;
    //   822: pop
    //   823: iload_2
    //   824: ifne -> 1348
    //   827: goto -> 834
    //   830: invokestatic a : (Ljava/lang/Throwable;)Ljava/lang/Throwable;
    //   833: athrow
    //   834: aload_3
    //   835: getstatic burp/Zsdn.Zf : Ljava/lang/String;
    //   838: getstatic burp/Zrh1.ZF : Ljava/lang/Object;
    //   841: checkcast java/math/BigInteger
    //   844: invokevirtual intValue : ()I
    //   847: bipush #32
    //   849: irem
    //   850: invokestatic abs : (I)I
    //   853: invokevirtual charAt : (I)C
    //   856: invokevirtual append : (C)Ljava/lang/StringBuilder;
    //   859: pop
    //   860: iload_2
    //   861: ifne -> 1348
    //   864: goto -> 871
    //   867: invokestatic a : (Ljava/lang/Throwable;)Ljava/lang/Throwable;
    //   870: athrow
    //   871: aload_3
    //   872: getstatic burp/Zmrc.Zx : Ljava/lang/String;
    //   875: getstatic burp/Zl5.ZY : Ljava/lang/Object;
    //   878: checkcast java/math/BigInteger
    //   881: invokevirtual intValue : ()I
    //   884: bipush #32
    //   886: irem
    //   887: invokestatic abs : (I)I
    //   890: invokevirtual charAt : (I)C
    //   893: invokevirtual append : (C)Ljava/lang/StringBuilder;
    //   896: pop
    //   897: iload_2
    //   898: ifne -> 1348
    //   901: goto -> 908
    //   904: invokestatic a : (Ljava/lang/Throwable;)Ljava/lang/Throwable;
    //   907: athrow
    //   908: aload_3
    //   909: getstatic burp/Zbzk.ZS : Ljava/lang/String;
    //   912: getstatic burp/Ztzw.Zk : Ljava/lang/Object;
    //   915: checkcast java/math/BigInteger
    //   918: invokevirtual intValue : ()I
    //   921: bipush #32
    //   923: irem
    //   924: invokestatic abs : (I)I
    //   927: invokevirtual charAt : (I)C
    //   930: invokevirtual append : (C)Ljava/lang/StringBuilder;
    //   933: pop
    //   934: iload_2
    //   935: ifne -> 1348
    //   938: goto -> 945
    //   941: invokestatic a : (Ljava/lang/Throwable;)Ljava/lang/Throwable;
    //   944: athrow
    //   945: aload_3
    //   946: getstatic burp/Zm3x.Zu : Ljava/lang/String;
    //   949: getstatic burp/Zex0.Ze : Ljava/lang/Object;
    //   952: checkcast java/math/BigInteger
    //   955: invokevirtual intValue : ()I
    //   958: bipush #32
    //   960: irem
    //   961: invokestatic abs : (I)I
    //   964: invokevirtual charAt : (I)C
    //   967: invokevirtual append : (C)Ljava/lang/StringBuilder;
    //   970: pop
    //   971: iload_2
    //   972: ifne -> 1348
    //   975: goto -> 982
    //   978: invokestatic a : (Ljava/lang/Throwable;)Ljava/lang/Throwable;
    //   981: athrow
    //   982: aload_3
    //   983: getstatic burp/Zz5d.Zb : Ljava/lang/String;
    //   986: getstatic burp/Zeai.ZI : Ljava/lang/Object;
    //   989: checkcast java/math/BigInteger
    //   992: invokevirtual intValue : ()I
    //   995: bipush #32
    //   997: irem
    //   998: invokestatic abs : (I)I
    //   1001: invokevirtual charAt : (I)C
    //   1004: invokevirtual append : (C)Ljava/lang/StringBuilder;
    //   1007: pop
    //   1008: iload_2
    //   1009: ifne -> 1348
    //   1012: goto -> 1019
    //   1015: invokestatic a : (Ljava/lang/Throwable;)Ljava/lang/Throwable;
    //   1018: athrow
    //   1019: aload_3
    //   1020: getstatic burp/Zl4v.ZD : Ljava/lang/String;
    //   1023: getstatic burp/Zezn.Zh : Ljava/lang/Object;
    //   1026: checkcast java/math/BigInteger
    //   1029: invokevirtual intValue : ()I
    //   1032: bipush #32
    //   1034: irem
    //   1035: invokestatic abs : (I)I
    //   1038: invokevirtual charAt : (I)C
    //   1041: invokevirtual append : (C)Ljava/lang/StringBuilder;
    //   1044: pop
    //   1045: iload_2
    //   1046: ifne -> 1348
    //   1049: goto -> 1056
    //   1052: invokestatic a : (Ljava/lang/Throwable;)Ljava/lang/Throwable;
    //   1055: athrow
    //   1056: aload_3
    //   1057: getstatic burp/Zlfi.Zg : Ljava/lang/String;
    //   1060: getstatic burp/Zkgp.Zw : Ljava/lang/Object;
    //   1063: checkcast java/math/BigInteger
    //   1066: invokevirtual intValue : ()I
    //   1069: bipush #32
    //   1071: irem
    //   1072: invokestatic abs : (I)I
    //   1075: invokevirtual charAt : (I)C
    //   1078: invokevirtual append : (C)Ljava/lang/StringBuilder;
    //   1081: pop
    //   1082: iload_2
    //   1083: ifne -> 1348
    //   1086: goto -> 1093
    //   1089: invokestatic a : (Ljava/lang/Throwable;)Ljava/lang/Throwable;
    //   1092: athrow
    //   1093: aload_3
    //   1094: getstatic burp/Ze64.ZM : Ljava/lang/String;
    //   1097: getstatic burp/Ze4x.Zp : Ljava/lang/Object;
    //   1100: checkcast java/math/BigInteger
    //   1103: invokevirtual intValue : ()I
    //   1106: bipush #32
    //   1108: irem
    //   1109: invokestatic abs : (I)I
    //   1112: invokevirtual charAt : (I)C
    //   1115: invokevirtual append : (C)Ljava/lang/StringBuilder;
    //   1118: pop
    //   1119: iload_2
    //   1120: ifne -> 1348
    //   1123: goto -> 1130
    //   1126: invokestatic a : (Ljava/lang/Throwable;)Ljava/lang/Throwable;
    //   1129: athrow
    //   1130: aload_3
    //   1131: getstatic burp/Zsn4.ZZ : Ljava/lang/String;
    //   1134: getstatic burp/Zeb3.Zb : Ljava/lang/Object;
    //   1137: checkcast java/math/BigInteger
    //   1140: invokevirtual intValue : ()I
    //   1143: bipush #32
    //   1145: irem
    //   1146: invokestatic abs : (I)I
    //   1149: invokevirtual charAt : (I)C
    //   1152: invokevirtual append : (C)Ljava/lang/StringBuilder;
    //   1155: pop
    //   1156: iload_2
    //   1157: ifne -> 1348
    //   1160: goto -> 1167
    //   1163: invokestatic a : (Ljava/lang/Throwable;)Ljava/lang/Throwable;
    //   1166: athrow
    //   1167: aload_3
    //   1168: getstatic burp/Zel.Zi : Ljava/lang/String;
    //   1171: getstatic burp/Zrx5.ZE : Ljava/lang/Object;
    //   1174: checkcast java/math/BigInteger
    //   1177: invokevirtual intValue : ()I
    //   1180: bipush #32
    //   1182: irem
    //   1183: invokestatic abs : (I)I
    //   1186: invokevirtual charAt : (I)C
    //   1189: invokevirtual append : (C)Ljava/lang/StringBuilder;
    //   1192: pop
    //   1193: iload_2
    //   1194: ifne -> 1348
    //   1197: goto -> 1204
    //   1200: invokestatic a : (Ljava/lang/Throwable;)Ljava/lang/Throwable;
    //   1203: athrow
    //   1204: aload_3
    //   1205: getstatic burp/Zss6.ZN : Ljava/lang/String;
    //   1208: getstatic burp/Ze_e.Za : Ljava/lang/Object;
    //   1211: checkcast java/math/BigInteger
    //   1214: invokevirtual intValue : ()I
    //   1217: bipush #32
    //   1219: irem
    //   1220: invokestatic abs : (I)I
    //   1223: invokevirtual charAt : (I)C
    //   1226: invokevirtual append : (C)Ljava/lang/StringBuilder;
    //   1229: pop
    //   1230: iload_2
    //   1231: ifne -> 1348
    //   1234: goto -> 1241
    //   1237: invokestatic a : (Ljava/lang/Throwable;)Ljava/lang/Throwable;
    //   1240: athrow
    //   1241: aload_3
    //   1242: getstatic burp/Zeqw.Zw : Ljava/lang/String;
    //   1245: getstatic burp/Zg1l.Zg : Ljava/lang/Object;
    //   1248: checkcast java/math/BigInteger
    //   1251: invokevirtual intValue : ()I
    //   1254: bipush #32
    //   1256: irem
    //   1257: invokestatic abs : (I)I
    //   1260: invokevirtual charAt : (I)C
    //   1263: invokevirtual append : (C)Ljava/lang/StringBuilder;
    //   1266: pop
    //   1267: iload_2
    //   1268: ifne -> 1348
    //   1271: goto -> 1278
    //   1274: invokestatic a : (Ljava/lang/Throwable;)Ljava/lang/Throwable;
    //   1277: athrow
    //   1278: aload_3
    //   1279: getstatic burp/Zzk9.Zb : Ljava/lang/String;
    //   1282: getstatic burp/Zz16.ZK : Ljava/lang/Object;
    //   1285: checkcast java/math/BigInteger
    //   1288: invokevirtual intValue : ()I
    //   1291: bipush #32
    //   1293: irem
    //   1294: invokestatic abs : (I)I
    //   1297: invokevirtual charAt : (I)C
    //   1300: invokevirtual append : (C)Ljava/lang/StringBuilder;
    //   1303: pop
    //   1304: iload_2
    //   1305: ifne -> 1348
    //   1308: goto -> 1315
    //   1311: invokestatic a : (Ljava/lang/Throwable;)Ljava/lang/Throwable;
    //   1314: athrow
    //   1315: aload_3
    //   1316: getstatic burp/Zl15.ZI : Ljava/lang/String;
    //   1319: getstatic burp/Zs8y.ZG : Ljava/lang/Object;
    //   1322: checkcast java/math/BigInteger
    //   1325: invokevirtual intValue : ()I
    //   1328: bipush #32
    //   1330: irem
    //   1331: invokestatic abs : (I)I
    //   1334: invokevirtual charAt : (I)C
    //   1337: invokevirtual append : (C)Ljava/lang/StringBuilder;
    //   1340: pop
    //   1341: goto -> 1348
    //   1344: invokestatic a : (Ljava/lang/Throwable;)Ljava/lang/Throwable;
    //   1347: athrow
    //   1348: iinc #4, 1
    //   1351: iload_2
    //   1352: ifne -> 15
    //   1355: aload_3
    //   1356: invokevirtual toString : ()Ljava/lang/String;
    //   1359: putstatic burp/Zsin.ZC : Ljava/lang/String;
    //   1362: sipush #-11111
    //   1365: getstatic burp/Zs56.ZC : Ljava/lang/Object;
    //   1368: checkcast java/math/BigInteger
    //   1371: getstatic burp/Zr8s.Zt : Ljava/lang/Object;
    //   1374: checkcast java/math/BigInteger
    //   1377: invokevirtual subtract : (Ljava/math/BigInteger;)Ljava/math/BigInteger;
    //   1380: putstatic burp/Zs9k.ZX : Ljava/lang/Object;
    //   1383: sipush #-1724
    //   1386: getstatic burp/Zt7k.Zc : Ljava/lang/Object;
    //   1389: checkcast java/math/BigInteger
    //   1392: getstatic burp/Zx8t.ZA : Ljava/lang/Object;
    //   1395: checkcast java/math/BigInteger
    //   1398: invokevirtual add : (Ljava/math/BigInteger;)Ljava/math/BigInteger;
    //   1401: putstatic burp/Zlgh.Zd : Ljava/lang/Object;
    //   1404: invokestatic a : (II)Ljava/lang/String;
    //   1407: iconst_1
    //   1408: ldc burp/Znp
    //   1410: invokevirtual getClassLoader : ()Ljava/lang/ClassLoader;
    //   1413: invokestatic forName : (Ljava/lang/String;ZLjava/lang/ClassLoader;)Ljava/lang/Class;
    //   1416: invokevirtual getDeclaredFields : ()[Ljava/lang/reflect/Field;
    //   1419: astore #4
    //   1421: aload #4
    //   1423: arraylength
    //   1424: istore #5
    //   1426: iconst_0
    //   1427: istore #6
    //   1429: iload #6
    //   1431: iload #5
    //   1433: if_icmpge -> 1571
    //   1436: aload #4
    //   1438: iload #6
    //   1440: aaload
    //   1441: astore #7
    //   1443: aload #7
    //   1445: invokevirtual getModifiers : ()I
    //   1448: invokestatic isStatic : (I)Z
    //   1451: ifne -> 1461
    //   1454: goto -> 1564
    //   1457: invokestatic a : (Ljava/lang/Throwable;)Ljava/lang/Throwable;
    //   1460: athrow
    //   1461: aload #7
    //   1463: invokevirtual getType : ()Ljava/lang/Class;
    //   1466: astore #8
    //   1468: aload #8
    //   1470: ifnull -> 1551
    //   1473: aload #8
    //   1475: invokevirtual isPrimitive : ()Z
    //   1478: ifne -> 1551
    //   1481: goto -> 1488
    //   1484: invokestatic a : (Ljava/lang/Throwable;)Ljava/lang/Throwable;
    //   1487: athrow
    //   1488: aload #8
    //   1490: invokevirtual getPackage : ()Ljava/lang/Package;
    //   1493: ifnull -> 1551
    //   1496: goto -> 1503
    //   1499: invokestatic a : (Ljava/lang/Throwable;)Ljava/lang/Throwable;
    //   1502: athrow
    //   1503: aload #8
    //   1505: invokevirtual getPackage : ()Ljava/lang/Package;
    //   1508: invokevirtual getName : ()Ljava/lang/String;
    //   1511: ifnull -> 1551
    //   1514: goto -> 1521
    //   1517: invokestatic a : (Ljava/lang/Throwable;)Ljava/lang/Throwable;
    //   1520: athrow
    //   1521: aload #8
    //   1523: invokevirtual getPackage : ()Ljava/lang/Package;
    //   1526: invokevirtual getName : ()Ljava/lang/String;
    //   1529: sipush #-11105
    //   1532: sipush #31303
    //   1535: invokestatic a : (II)Ljava/lang/String;
    //   1538: invokevirtual startsWith : (Ljava/lang/String;)Z
    //   1541: ifne -> 1551
    //   1544: goto -> 1551
    //   1547: invokestatic a : (Ljava/lang/Throwable;)Ljava/lang/Throwable;
    //   1550: athrow
    //   1551: aload #7
    //   1553: iconst_1
    //   1554: invokevirtual setAccessible : (Z)V
    //   1557: aload #7
    //   1559: aconst_null
    //   1560: invokevirtual get : (Ljava/lang/Object;)Ljava/lang/Object;
    //   1563: pop
    //   1564: iinc #6, 1
    //   1567: iload_2
    //   1568: ifne -> 1429
    //   1571: sipush #-11118
    //   1574: sipush #150
    //   1577: invokestatic a : (II)Ljava/lang/String;
    //   1580: invokestatic forName : (Ljava/lang/String;)Ljava/lang/Class;
    //   1583: invokevirtual getDeclaredMethods : ()[Ljava/lang/reflect/Method;
    //   1586: astore #4
    //   1588: aload #4
    //   1590: arraylength
    //   1591: istore #5
    //   1593: iconst_0
    //   1594: istore #6
    //   1596: iload #6
    //   1598: iload #5
    //   1600: if_icmpge -> 1712
    //   1603: aload #4
    //   1605: iload #6
    //   1607: aaload
    //   1608: astore #7
    //   1610: aload #7
    //   1612: invokevirtual getParameterTypes : ()[Ljava/lang/Class;
    //   1615: pop
    //   1616: aload #7
    //   1618: invokevirtual getModifiers : ()I
    //   1621: invokestatic isStatic : (I)Z
    //   1624: ifeq -> 1698
    //   1627: aload #7
    //   1629: invokevirtual getParameterTypes : ()[Ljava/lang/Class;
    //   1632: arraylength
    //   1633: iconst_2
    //   1634: if_icmpne -> 1698
    //   1637: goto -> 1644
    //   1640: invokestatic a : (Ljava/lang/Throwable;)Ljava/lang/Throwable;
    //   1643: athrow
    //   1644: aload #7
    //   1646: invokevirtual getReturnType : ()Ljava/lang/Class;
    //   1649: getstatic java/lang/Boolean.TYPE : Ljava/lang/Class;
    //   1652: if_acmpne -> 1698
    //   1655: goto -> 1662
    //   1658: invokestatic a : (Ljava/lang/Throwable;)Ljava/lang/Throwable;
    //   1661: athrow
    //   1662: aload #7
    //   1664: iconst_1
    //   1665: invokevirtual setAccessible : (Z)V
    //   1668: aload #7
    //   1670: aconst_null
    //   1671: iconst_2
    //   1672: anewarray java/lang/Object
    //   1675: dup
    //   1676: iconst_0
    //   1677: aload_0
    //   1678: aastore
    //   1679: dup
    //   1680: iconst_1
    //   1681: aload_1
    //   1682: aastore
    //   1683: invokevirtual invoke : (Ljava/lang/Object;[Ljava/lang/Object;)Ljava/lang/Object;
    //   1686: pop
    //   1687: iload_2
    //   1688: ifne -> 1712
    //   1691: goto -> 1698
    //   1694: invokestatic a : (Ljava/lang/Throwable;)Ljava/lang/Throwable;
    //   1697: athrow
    //   1698: iinc #6, 1
    //   1701: iload_2
    //   1702: ifne -> 1596
    //   1705: goto -> 1712
    //   1708: invokestatic a : (Ljava/lang/Throwable;)Ljava/lang/Throwable;
    //   1711: athrow
    //   1712: sipush #-11112
    //   1715: sipush #17247
    //   1718: invokestatic a : (II)Ljava/lang/String;
    //   1721: iconst_1
    //   1722: ldc burp/Zmtr
    //   1724: invokevirtual getClassLoader : ()Ljava/lang/ClassLoader;
    //   1727: invokestatic forName : (Ljava/lang/String;ZLjava/lang/ClassLoader;)Ljava/lang/Class;
    //   1730: invokevirtual getDeclaredFields : ()[Ljava/lang/reflect/Field;
    //   1733: astore #4
    //   1735: aload #4
    //   1737: arraylength
    //   1738: istore #5
    //   1740: iconst_0
    //   1741: istore #6
    //   1743: iload #6
    //   1745: iload #5
    //   1747: if_icmpge -> 1885
    //   1750: aload #4
    //   1752: iload #6
    //   1754: aaload
    //   1755: astore #7
    //   1757: aload #7
    //   1759: invokevirtual getModifiers : ()I
    //   1762: invokestatic isStatic : (I)Z
    //   1765: ifne -> 1775
    //   1768: goto -> 1878
    //   1771: invokestatic a : (Ljava/lang/Throwable;)Ljava/lang/Throwable;
    //   1774: athrow
    //   1775: aload #7
    //   1777: invokevirtual getType : ()Ljava/lang/Class;
    //   1780: astore #8
    //   1782: aload #8
    //   1784: ifnull -> 1865
    //   1787: aload #8
    //   1789: invokevirtual isPrimitive : ()Z
    //   1792: ifne -> 1865
    //   1795: goto -> 1802
    //   1798: invokestatic a : (Ljava/lang/Throwable;)Ljava/lang/Throwable;
    //   1801: athrow
    //   1802: aload #8
    //   1804: invokevirtual getPackage : ()Ljava/lang/Package;
    //   1807: ifnull -> 1865
    //   1810: goto -> 1817
    //   1813: invokestatic a : (Ljava/lang/Throwable;)Ljava/lang/Throwable;
    //   1816: athrow
    //   1817: aload #8
    //   1819: invokevirtual getPackage : ()Ljava/lang/Package;
    //   1822: invokevirtual getName : ()Ljava/lang/String;
    //   1825: ifnull -> 1865
    //   1828: goto -> 1835
    //   1831: invokestatic a : (Ljava/lang/Throwable;)Ljava/lang/Throwable;
    //   1834: athrow
    //   1835: aload #8
    //   1837: invokevirtual getPackage : ()Ljava/lang/Package;
    //   1840: invokevirtual getName : ()Ljava/lang/String;
    //   1843: sipush #-11108
    //   1846: sipush #-9952
    //   1849: invokestatic a : (II)Ljava/lang/String;
    //   1852: invokevirtual startsWith : (Ljava/lang/String;)Z
    //   1855: ifne -> 1865
    //   1858: goto -> 1865
    //   1861: invokestatic a : (Ljava/lang/Throwable;)Ljava/lang/Throwable;
    //   1864: athrow
    //   1865: aload #7
    //   1867: iconst_1
    //   1868: invokevirtual setAccessible : (Z)V
    //   1871: aload #7
    //   1873: aconst_null
    //   1874: invokevirtual get : (Ljava/lang/Object;)Ljava/lang/Object;
    //   1877: pop
    //   1878: iinc #6, 1
    //   1881: iload_2
    //   1882: ifne -> 1743
    //   1885: sipush #-11120
    //   1888: sipush #-18924
    //   1891: invokestatic a : (II)Ljava/lang/String;
    //   1894: invokestatic forName : (Ljava/lang/String;)Ljava/lang/Class;
    //   1897: invokevirtual getDeclaredMethods : ()[Ljava/lang/reflect/Method;
    //   1900: astore #4
    //   1902: aload #4
    //   1904: arraylength
    //   1905: istore #5
    //   1907: iconst_0
    //   1908: istore #6
    //   1910: iload #6
    //   1912: iload #5
    //   1914: if_icmpge -> 2047
    //   1917: aload #4
    //   1919: iload #6
    //   1921: aaload
    //   1922: astore #7
    //   1924: aload #7
    //   1926: invokevirtual getParameterTypes : ()[Ljava/lang/Class;
    //   1929: pop
    //   1930: aload #7
    //   1932: invokevirtual getModifiers : ()I
    //   1935: invokestatic isStatic : (I)Z
    //   1938: ifeq -> 2033
    //   1941: aload #7
    //   1943: invokevirtual getParameterTypes : ()[Ljava/lang/Class;
    //   1946: arraylength
    //   1947: iconst_2
    //   1948: if_icmpne -> 2033
    //   1951: goto -> 1958
    //   1954: invokestatic a : (Ljava/lang/Throwable;)Ljava/lang/Throwable;
    //   1957: athrow
    //   1958: aload #7
    //   1960: invokevirtual getReturnType : ()Ljava/lang/Class;
    //   1963: getstatic java/lang/Void.TYPE : Ljava/lang/Class;
    //   1966: invokevirtual equals : (Ljava/lang/Object;)Z
    //   1969: ifeq -> 2033
    //   1972: goto -> 1979
    //   1975: invokestatic a : (Ljava/lang/Throwable;)Ljava/lang/Throwable;
    //   1978: athrow
    //   1979: aload #7
    //   1981: iconst_1
    //   1982: invokevirtual setAccessible : (Z)V
    //   1985: aload #7
    //   1987: aconst_null
    //   1988: iconst_2
    //   1989: anewarray java/lang/Object
    //   1992: dup
    //   1993: iconst_0
    //   1994: aload_0
    //   1995: aastore
    //   1996: dup
    //   1997: iconst_1
    //   1998: aload_1
    //   1999: ifnonnull -> 2017
    //   2002: goto -> 2009
    //   2005: invokestatic a : (Ljava/lang/Throwable;)Ljava/lang/Throwable;
    //   2008: athrow
    //   2009: aload_1
    //   2010: goto -> 2024
    //   2013: invokestatic a : (Ljava/lang/Throwable;)Ljava/lang/Throwable;
    //   2016: athrow
    //   2017: aload_1
    //   2018: checkcast [B
    //   2021: invokevirtual clone : ()Ljava/lang/Object;
    //   2024: aastore
    //   2025: invokevirtual invoke : (Ljava/lang/Object;[Ljava/lang/Object;)Ljava/lang/Object;
    //   2028: pop
    //   2029: iload_2
    //   2030: ifne -> 2047
    //   2033: iinc #6, 1
    //   2036: iload_2
    //   2037: ifne -> 1910
    //   2040: goto -> 2047
    //   2043: invokestatic a : (Ljava/lang/Throwable;)Ljava/lang/Throwable;
    //   2046: athrow
    //   2047: iconst_0
    //   2048: istore #4
    //   2050: sipush #-11117
    //   2053: sipush #2442
    //   2056: invokestatic a : (II)Ljava/lang/String;
    //   2059: iconst_1
    //   2060: ldc burp/Zs8s
    //   2062: invokevirtual getClassLoader : ()Ljava/lang/ClassLoader;
    //   2065: invokestatic forName : (Ljava/lang/String;ZLjava/lang/ClassLoader;)Ljava/lang/Class;
    //   2068: invokevirtual getDeclaredFields : ()[Ljava/lang/reflect/Field;
    //   2071: astore #5
    //   2073: aload #5
    //   2075: arraylength
    //   2076: istore #6
    //   2078: iconst_0
    //   2079: istore #7
    //   2081: iload #7
    //   2083: iload #6
    //   2085: if_icmpge -> 2223
    //   2088: aload #5
    //   2090: iload #7
    //   2092: aaload
    //   2093: astore #8
    //   2095: aload #8
    //   2097: invokevirtual getModifiers : ()I
    //   2100: invokestatic isStatic : (I)Z
    //   2103: ifne -> 2113
    //   2106: goto -> 2216
    //   2109: invokestatic a : (Ljava/lang/Throwable;)Ljava/lang/Throwable;
    //   2112: athrow
    //   2113: aload #8
    //   2115: invokevirtual getType : ()Ljava/lang/Class;
    //   2118: astore #9
    //   2120: aload #9
    //   2122: ifnull -> 2203
    //   2125: aload #9
    //   2127: invokevirtual isPrimitive : ()Z
    //   2130: ifne -> 2203
    //   2133: goto -> 2140
    //   2136: invokestatic a : (Ljava/lang/Throwable;)Ljava/lang/Throwable;
    //   2139: athrow
    //   2140: aload #9
    //   2142: invokevirtual getPackage : ()Ljava/lang/Package;
    //   2145: ifnull -> 2203
    //   2148: goto -> 2155
    //   2151: invokestatic a : (Ljava/lang/Throwable;)Ljava/lang/Throwable;
    //   2154: athrow
    //   2155: aload #9
    //   2157: invokevirtual getPackage : ()Ljava/lang/Package;
    //   2160: invokevirtual getName : ()Ljava/lang/String;
    //   2163: ifnull -> 2203
    //   2166: goto -> 2173
    //   2169: invokestatic a : (Ljava/lang/Throwable;)Ljava/lang/Throwable;
    //   2172: athrow
    //   2173: aload #9
    //   2175: invokevirtual getPackage : ()Ljava/lang/Package;
    //   2178: invokevirtual getName : ()Ljava/lang/String;
    //   2181: sipush #-11108
    //   2184: sipush #-9952
    //   2187: invokestatic a : (II)Ljava/lang/String;
    //   2190: invokevirtual startsWith : (Ljava/lang/String;)Z
    //   2193: ifne -> 2203
    //   2196: goto -> 2203
    //   2199: invokestatic a : (Ljava/lang/Throwable;)Ljava/lang/Throwable;
    //   2202: athrow
    //   2203: aload #8
    //   2205: iconst_1
    //   2206: invokevirtual setAccessible : (Z)V
    //   2209: aload #8
    //   2211: aconst_null
    //   2212: invokevirtual get : (Ljava/lang/Object;)Ljava/lang/Object;
    //   2215: pop
    //   2216: iinc #7, 1
    //   2219: iload_2
    //   2220: ifne -> 2081
    //   2223: sipush #-11113
    //   2226: sipush #-26914
    //   2229: invokestatic a : (II)Ljava/lang/String;
    //   2232: invokestatic forName : (Ljava/lang/String;)Ljava/lang/Class;
    //   2235: invokevirtual getDeclaredMethods : ()[Ljava/lang/reflect/Method;
    //   2238: astore #5
    //   2240: aload #5
    //   2242: arraylength
    //   2243: istore #6
    //   2245: iconst_0
    //   2246: istore #7
    //   2248: iload #7
    //   2250: iload #6
    //   2252: if_icmpge -> 2389
    //   2255: aload #5
    //   2257: iload #7
    //   2259: aaload
    //   2260: astore #8
    //   2262: aload #8
    //   2264: invokevirtual getParameterTypes : ()[Ljava/lang/Class;
    //   2267: pop
    //   2268: aload #8
    //   2270: invokevirtual getModifiers : ()I
    //   2273: invokestatic isStatic : (I)Z
    //   2276: ifeq -> 2375
    //   2279: aload #8
    //   2281: invokevirtual getParameterTypes : ()[Ljava/lang/Class;
    //   2284: arraylength
    //   2285: iconst_2
    //   2286: if_icmpne -> 2375
    //   2289: goto -> 2296
    //   2292: invokestatic a : (Ljava/lang/Throwable;)Ljava/lang/Throwable;
    //   2295: athrow
    //   2296: aload #8
    //   2298: invokevirtual getReturnType : ()Ljava/lang/Class;
    //   2301: getstatic java/lang/Boolean.TYPE : Ljava/lang/Class;
    //   2304: if_acmpne -> 2375
    //   2307: goto -> 2314
    //   2310: invokestatic a : (Ljava/lang/Throwable;)Ljava/lang/Throwable;
    //   2313: athrow
    //   2314: aload #8
    //   2316: iconst_1
    //   2317: invokevirtual setAccessible : (Z)V
    //   2320: aload #8
    //   2322: aconst_null
    //   2323: iconst_2
    //   2324: anewarray java/lang/Object
    //   2327: dup
    //   2328: iconst_0
    //   2329: aload_0
    //   2330: aastore
    //   2331: dup
    //   2332: iconst_1
    //   2333: aload_1
    //   2334: ifnonnull -> 2352
    //   2337: goto -> 2344
    //   2340: invokestatic a : (Ljava/lang/Throwable;)Ljava/lang/Throwable;
    //   2343: athrow
    //   2344: aload_1
    //   2345: goto -> 2359
    //   2348: invokestatic a : (Ljava/lang/Throwable;)Ljava/lang/Throwable;
    //   2351: athrow
    //   2352: aload_1
    //   2353: checkcast [B
    //   2356: invokevirtual clone : ()Ljava/lang/Object;
    //   2359: aastore
    //   2360: invokevirtual invoke : (Ljava/lang/Object;[Ljava/lang/Object;)Ljava/lang/Object;
    //   2363: checkcast java/lang/Boolean
    //   2366: invokevirtual booleanValue : ()Z
    //   2369: istore #4
    //   2371: iload_2
    //   2372: ifne -> 2389
    //   2375: iinc #7, 1
    //   2378: iload_2
    //   2379: ifne -> 2248
    //   2382: goto -> 2389
    //   2385: invokestatic a : (Ljava/lang/Throwable;)Ljava/lang/Throwable;
    //   2388: athrow
    //   2389: iload #4
    //   2391: ireturn
    //   2392: astore_3
    //   2393: new java/lang/Exception
    //   2396: dup
    //   2397: aload_3
    //   2398: invokevirtual getMessage : ()Ljava/lang/String;
    //   2401: invokespecial <init> : (Ljava/lang/String;)V
    //   2404: athrow
    // Exception table:
    //   from	to	target	type
    //   4	2391	2392	java/lang/Throwable
    //   22	198	201	java/lang/Throwable
    //   168	235	238	java/lang/Throwable
    //   205	272	275	java/lang/Throwable
    //   242	309	312	java/lang/Throwable
    //   279	346	349	java/lang/Throwable
    //   316	383	386	java/lang/Throwable
    //   353	420	423	java/lang/Throwable
    //   390	457	460	java/lang/Throwable
    //   427	494	497	java/lang/Throwable
    //   464	531	534	java/lang/Throwable
    //   501	568	571	java/lang/Throwable
    //   538	605	608	java/lang/Throwable
    //   575	642	645	java/lang/Throwable
    //   612	679	682	java/lang/Throwable
    //   649	716	719	java/lang/Throwable
    //   686	753	756	java/lang/Throwable
    //   723	790	793	java/lang/Throwable
    //   760	827	830	java/lang/Throwable
    //   797	864	867	java/lang/Throwable
    //   834	901	904	java/lang/Throwable
    //   871	938	941	java/lang/Throwable
    //   908	975	978	java/lang/Throwable
    //   945	1012	1015	java/lang/Throwable
    //   982	1049	1052	java/lang/Throwable
    //   1019	1086	1089	java/lang/Throwable
    //   1056	1123	1126	java/lang/Throwable
    //   1093	1160	1163	java/lang/Throwable
    //   1130	1197	1200	java/lang/Throwable
    //   1167	1234	1237	java/lang/Throwable
    //   1204	1271	1274	java/lang/Throwable
    //   1241	1308	1311	java/lang/Throwable
    //   1278	1341	1344	java/lang/Throwable
    //   1443	1457	1457	java/lang/Throwable
    //   1468	1481	1484	java/lang/Throwable
    //   1473	1496	1499	java/lang/Throwable
    //   1488	1514	1517	java/lang/Throwable
    //   1503	1544	1547	java/lang/Throwable
    //   1610	1637	1640	java/lang/Throwable
    //   1627	1655	1658	java/lang/Throwable
    //   1644	1691	1694	java/lang/Throwable
    //   1662	1705	1708	java/lang/Throwable
    //   1757	1771	1771	java/lang/Throwable
    //   1782	1795	1798	java/lang/Throwable
    //   1787	1810	1813	java/lang/Throwable
    //   1802	1828	1831	java/lang/Throwable
    //   1817	1858	1861	java/lang/Throwable
    //   1924	1951	1954	java/lang/Throwable
    //   1941	1972	1975	java/lang/Throwable
    //   1958	2002	2005	java/lang/Throwable
    //   1979	2013	2013	java/lang/Throwable
    //   2024	2040	2043	java/lang/Throwable
    //   2095	2109	2109	java/lang/Throwable
    //   2120	2133	2136	java/lang/Throwable
    //   2125	2148	2151	java/lang/Throwable
    //   2140	2166	2169	java/lang/Throwable
    //   2155	2196	2199	java/lang/Throwable
    //   2262	2289	2292	java/lang/Throwable
    //   2279	2307	2310	java/lang/Throwable
    //   2296	2337	2340	java/lang/Throwable
    //   2314	2348	2348	java/lang/Throwable
    //   2371	2382	2385	java/lang/Throwable
  }
  
  static void Zz(Object paramObject) {
    Zl8y.ZY = a(-11119, 20442);
    Zl8y.ZD = new BigInteger(a(-11110, 17755));
    boolean bool = Zt2e.ZN();
    try {
      try {
        if (Zrod.ZQ.charAt(Math.abs(((BigInteger)Zrod.ZX).intValue() % 32)) <= Zg2.ZN.charAt(Math.abs(((BigInteger)Zkf9.ZX).intValue() % 32))) {
          try {
            Zkde.ZC(Class.forName(a(-11109, 20129)));
            if (!bool)
              Zeb3.Za(Class.forName(a(-11106, -23844))); 
          } catch (Throwable throwable) {
            throw a(null);
          } 
          return;
        } 
      } catch (Throwable throwable) {
        throw a(null);
      } 
      Zeb3.Za(Class.forName(a(-11106, -23844)));
    } catch (Throwable throwable) {}
  }
  
  static void Zl(Object[] paramArrayOfObject, Object paramObject) throws Throwable {}
  
  static {
    // Byte code:
    //   0: bipush #13
    //   2: anewarray java/lang/String
    //   5: astore #5
    //   7: iconst_0
    //   8: istore_3
    //   9: ldc '\\fÂ°)ÂœiÃ’Â¨"ÂµMr'Â™ÃÃ§:Ã°Ã½Ã¯cDHMÃ±oaMyÂ Â¬cÃ›pVvÃƒÃŒPÃ°mEÂÃŽÃ‰Ã›Ã©Âž<ÃÃ–^/Ã‰_Ã™MÂƒjaOÃ´ÂÃ¦Ã¥?Ã‚ÃÂ¿ÂˆVÃ„Ã©ÃžÃŒWm9l&\\t-Â›\\rÃ¹Ã­~6ÃµÂª\\t1|ÂŽÂÃ¡'\\n HkÂƒ\\t~Eg"Â ÂˆÃŸÂŽ Ã¤I Ã…Â¯MÂ£U7iv.AÃ¾Â¡("Ã¾/ÂšÃ‘`Ã«Ã¢e-Ã…ÃÂ€8Â¸Â\\t\\tÃ©Â‰Â·}Â·-ÃÂµ\\tÂ›ÂŒÃ›7"m~Ã K?ÂˆÃ²uÂªBÂœÂ‚Ã·}Â»'Ã€ÃÂ±uÃÃˆdÂ¬Ã–XÂ†"NÃ:Â·'
    //   11: dup
    //   12: astore_2
    //   13: invokevirtual length : ()I
    //   16: istore #4
    //   18: bipush #9
    //   20: istore_1
    //   21: iconst_m1
    //   22: istore_0
    //   23: bipush #44
    //   25: iinc #0, 1
    //   28: aload_2
    //   29: iload_0
    //   30: dup
    //   31: iload_1
    //   32: iadd
    //   33: invokevirtual substring : (II)Ljava/lang/String;
    //   36: iconst_m1
    //   37: goto -> 143
    //   40: aload #5
    //   42: swap
    //   43: iload_3
    //   44: iinc #3, 1
    //   47: swap
    //   48: aastore
    //   49: iload_0
    //   50: iload_1
    //   51: iadd
    //   52: dup
    //   53: istore_0
    //   54: iload #4
    //   56: if_icmpge -> 68
    //   59: aload_2
    //   60: iload_0
    //   61: invokevirtual charAt : (I)C
    //   64: istore_1
    //   65: goto -> 23
    //   68: ldc 'ÃÃ€rL!X\\tÃœÃµcdpÂÃ—ÂšÃ'
    //   70: dup
    //   71: astore_2
    //   72: invokevirtual length : ()I
    //   75: istore #4
    //   77: bipush #9
    //   79: istore_1
    //   80: iconst_m1
    //   81: istore_0
    //   82: bipush #62
    //   84: iinc #0, 1
    //   87: aload_2
    //   88: iload_0
    //   89: dup
    //   90: iload_1
    //   91: iadd
    //   92: invokevirtual substring : (II)Ljava/lang/String;
    //   95: iconst_0
    //   96: goto -> 143
    //   99: aload #5
    //   101: swap
    //   102: iload_3
    //   103: iinc #3, 1
    //   106: swap
    //   107: aastore
    //   108: iload_0
    //   109: iload_1
    //   110: iadd
    //   111: dup
    //   112: istore_0
    //   113: iload #4
    //   115: if_icmpge -> 127
    //   118: aload_2
    //   119: iload_0
    //   120: invokevirtual charAt : (I)C
    //   123: istore_1
    //   124: goto -> 82
    //   127: aload #5
    //   129: putstatic burp/Zrhu.a : [Ljava/lang/String;
    //   132: bipush #13
    //   134: anewarray java/lang/String
    //   137: putstatic burp/Zrhu.b : [Ljava/lang/String;
    //   140: goto -> 300
    //   143: dup_x2
    //   144: pop
    //   145: invokevirtual toCharArray : ()[C
    //   148: dup_x1
    //   149: arraylength
    //   150: dup_x2
    //   151: pop
    //   152: iconst_0
    //   153: istore #6
    //   155: dup2_x1
    //   156: pop2
    //   157: dup_x2
    //   158: iconst_1
    //   159: if_icmpgt -> 260
    //   162: dup2
    //   163: swap
    //   164: iload #6
    //   166: dup2_x1
    //   167: caload
    //   168: swap
    //   169: iload #6
    //   171: bipush #7
    //   173: irem
    //   174: tableswitch default -> 242, 0 -> 212, 1 -> 217, 2 -> 222, 3 -> 227, 4 -> 232, 5 -> 237
    //   212: bipush #90
    //   214: goto -> 244
    //   217: bipush #44
    //   219: goto -> 244
    //   222: bipush #22
    //   224: goto -> 244
    //   227: bipush #13
    //   229: goto -> 244
    //   232: bipush #53
    //   234: goto -> 244
    //   237: bipush #109
    //   239: goto -> 244
    //   242: bipush #10
    //   244: ixor
    //   245: ixor
    //   246: i2c
    //   247: castore
    //   248: iinc #6, 1
    //   251: dup
    //   252: ifne -> 260
    //   255: dup2
    //   256: dup_x1
    //   257: goto -> 166
    //   260: dup2_x1
    //   261: pop2
    //   262: dup_x2
    //   263: iload #6
    //   265: if_icmpgt -> 162
    //   268: pop
    //   269: new java/lang/String
    //   272: dup_x1
    //   273: swap
    //   274: invokespecial <init> : ([C)V
    //   277: invokevirtual intern : ()Ljava/lang/String;
    //   280: swap
    //   281: pop
    //   282: swap
    //   283: tableswitch default -> 40, 0 -> 99
    //   300: new java/math/BigInteger
    //   303: dup
    //   304: iconst_1
    //   305: bipush #32
    //   307: newarray byte
    //   309: dup
    //   310: iconst_0
    //   311: bipush #80
    //   313: bastore
    //   314: dup
    //   315: iconst_1
    //   316: bipush #106
    //   318: bastore
    //   319: dup
    //   320: iconst_2
    //   321: bipush #-103
    //   323: bastore
    //   324: dup
    //   325: iconst_3
    //   326: bipush #-120
    //   328: bastore
    //   329: dup
    //   330: iconst_4
    //   331: bipush #75
    //   333: bastore
    //   334: dup
    //   335: iconst_5
    //   336: bipush #30
    //   338: bastore
    //   339: dup
    //   340: bipush #6
    //   342: bipush #33
    //   344: bastore
    //   345: dup
    //   346: bipush #7
    //   348: bipush #-33
    //   350: bastore
    //   351: dup
    //   352: bipush #8
    //   354: bipush #-66
    //   356: bastore
    //   357: dup
    //   358: bipush #9
    //   360: bipush #-111
    //   362: bastore
    //   363: dup
    //   364: bipush #10
    //   366: bipush #108
    //   368: bastore
    //   369: dup
    //   370: bipush #11
    //   372: bipush #-3
    //   374: bastore
    //   375: dup
    //   376: bipush #12
    //   378: bipush #-75
    //   380: bastore
    //   381: dup
    //   382: bipush #13
    //   384: bipush #-100
    //   386: bastore
    //   387: dup
    //   388: bipush #14
    //   390: bipush #15
    //   392: bastore
    //   393: dup
    //   394: bipush #15
    //   396: bipush #-19
    //   398: bastore
    //   399: dup
    //   400: bipush #16
    //   402: bipush #94
    //   404: bastore
    //   405: dup
    //   406: bipush #17
    //   408: bipush #11
    //   410: bastore
    //   411: dup
    //   412: bipush #18
    //   414: bipush #32
    //   416: bastore
    //   417: dup
    //   418: bipush #19
    //   420: bipush #-111
    //   422: bastore
    //   423: dup
    //   424: bipush #20
    //   426: bipush #33
    //   428: bastore
    //   429: dup
    //   430: bipush #21
    //   432: bipush #29
    //   434: bastore
    //   435: dup
    //   436: bipush #22
    //   438: bipush #39
    //   440: bastore
    //   441: dup
    //   442: bipush #23
    //   444: bipush #-9
    //   446: bastore
    //   447: dup
    //   448: bipush #24
    //   450: bipush #69
    //   452: bastore
    //   453: dup
    //   454: bipush #25
    //   456: bipush #-5
    //   458: bastore
    //   459: dup
    //   460: bipush #26
    //   462: bipush #-22
    //   464: bastore
    //   465: dup
    //   466: bipush #27
    //   468: bipush #-117
    //   470: bastore
    //   471: dup
    //   472: bipush #28
    //   474: bipush #-12
    //   476: bastore
    //   477: dup
    //   478: bipush #29
    //   480: bipush #50
    //   482: bastore
    //   483: dup
    //   484: bipush #30
    //   486: bipush #63
    //   488: bastore
    //   489: dup
    //   490: bipush #31
    //   492: bipush #126
    //   494: bastore
    //   495: invokespecial <init> : (I[B)V
    //   498: putstatic burp/Zrhu.Zs : Ljava/lang/Object;
    //   501: sipush #-11107
    //   504: sipush #21193
    //   507: invokestatic a : (II)Ljava/lang/String;
    //   510: putstatic burp/Zrhu.ZJ : Ljava/lang/String;
    //   513: return
  }
  
  private static Throwable a(Throwable paramThrowable) {
    return paramThrowable;
  }
  
  private static String a(int paramInt1, int paramInt2) {
    int i = (paramInt1 ^ 0xFFFFD49B) & 0xFFFF;
    if (b[i] == null) {
      char[] arrayOfChar = a[i].toCharArray();
      switch (arrayOfChar[0] & 0xFF) {
        case 0:
        
        case 1:
        
        case 2:
        
        case 3:
        
        case 4:
        
        case 5:
        
        case 6:
        
        case 7:
        
        case 8:
        
        case 9:
        
        case 10:
        
        case 11:
        
        case 12:
        
        case 13:
        
        case 14:
        
        case 15:
        
        case 16:
        
        case 17:
        
        case 18:
        
        case 19:
        
        case 20:
        
        case 21:
        
        case 22:
        
        case 23:
        
        case 24:
        
        case 25:
        
        case 26:
        
        case 27:
        
        case 28:
        
        case 29:
        
        case 30:
        
        case 31:
        
        case 32:
        
        case 33:
        
        case 34:
        
        case 35:
        
        case 36:
        
        case 37:
        
        case 38:
        
        case 39:
        
        case 40:
        
        case 41:
        
        case 42:
        
        case 43:
        
        case 44:
        
        case 45:
        
        case 46:
        
        case 47:
        
        case 48:
        
        case 49:
        
        case 50:
        
        case 51:
        
        case 52:
        
        case 53:
        
        case 54:
        
        case 55:
        
        case 56:
        
        case 57:
        
        case 58:
        
        case 59:
        
        case 60:
        
        case 61:
        
        case 62:
        
        case 63:
        
        case 64:
        
        case 65:
        
        case 66:
        
        case 67:
        
        case 68:
        
        case 69:
        
        case 70:
        
        case 71:
        
        case 72:
        
        case 73:
        
        case 74:
        
        case 75:
        
        case 76:
        
        case 77:
        
        case 78:
        
        case 79:
        
        case 80:
        
        case 81:
        
        case 82:
        
        case 83:
        
        case 84:
        
        case 85:
        
        case 86:
        
        case 87:
        
        case 88:
        
        case 89:
        
        case 90:
        
        case 91:
        
        case 92:
        
        case 93:
        
        case 94:
        
        case 95:
        
        case 96:
        
        case 97:
        
        case 98:
        
        case 99:
        
        case 100:
        
        case 101:
        
        case 102:
        
        case 103:
        
        case 104:
        
        case 105:
        
        case 106:
        
        case 107:
        
        case 108:
        
        case 109:
        
        case 110:
        
        case 111:
        
        case 112:
        
        case 113:
        
        case 114:
        
        case 115:
        
        case 116:
        
        case 117:
        
        case 118:
        
        case 119:
        
        case 120:
        
        case 121:
        
        case 122:
        
        case 123:
        
        case 124:
        
        case 125:
        
        case 126:
        
        case 127:
        
        case 128:
        
        case 129:
        
        case 130:
        
        case 131:
        
        case 132:
        
        case 133:
        
        case 134:
        
        case 135:
        
        case 136:
        
        case 137:
        
        case 138:
        
        case 139:
        
        case 140:
        
        case 141:
        
        case 142:
        
        case 143:
        
        case 144:
        
        case 145:
        
        case 146:
        
        case 147:
        
        case 148:
        
        case 149:
        
        case 150:
        
        case 151:
        
        case 152:
        
        case 153:
        
        case 154:
        
        case 155:
        
        case 156:
        
        case 157:
        
        case 158:
        
        case 159:
        
        case 160:
        
        case 161:
        
        case 162:
        
        case 163:
        
        case 164:
        
        case 165:
        
        case 166:
        
        case 167:
        
        case 168:
        
        case 169:
        
        case 170:
        
        case 171:
        
        case 172:
        
        case 173:
        
        case 174:
        
        case 175:
        
        case 176:
        
        case 177:
        
        case 178:
        
        case 179:
        
        case 180:
        
        case 181:
        
        case 182:
        
        case 183:
        
        case 184:
        
        case 185:
        
        case 186:
        
        case 187:
        
        case 188:
        
        case 189:
        
        case 190:
        
        case 191:
        
        case 192:
        
        case 193:
        
        case 194:
        
        case 195:
        
        case 196:
        
        case 197:
        
        case 198:
        
        case 199:
        
        case 200:
        
        case 201:
        
        case 202:
        
        case 203:
        
        case 204:
        
        case 205:
        
        case 206:
        
        case 207:
        
        case 208:
        
        case 209:
        
        case 210:
        
        case 211:
        
        case 212:
        
        case 213:
        
        case 214:
        
        case 215:
        
        case 216:
        
        case 217:
        
        case 218:
        
        case 219:
        
        case 220:
        
        case 221:
        
        case 222:
        
        case 223:
        
        case 224:
        
        case 225:
        
        case 226:
        
        case 227:
        
        case 228:
        
        case 229:
        
        case 230:
        
        case 231:
        
        case 232:
        
        case 233:
        
        case 234:
        
        case 235:
        
        case 236:
        
        case 237:
        
        case 238:
        
        case 239:
        
        case 240:
        
        case 241:
        
        case 242:
        
        case 243:
        
        case 244:
        
        case 245:
        
        case 246:
        
        case 247:
        
        case 248:
        
        case 249:
        
        case 250:
        
        case 251:
        
        case 252:
        
        case 253:
        
        case 254:
        
        default:
          break;
      } 
      char c = 'Ã€';
      int j = (paramInt2 & 0xFF) - c;
      if (j < 0)
        j += 256; 
      int k = ((paramInt2 & 0xFFFF) >>> 8) - c;
      if (k < 0)
        k += 256; 
      for (byte b = 0; b < arrayOfChar.length; b++) {
        int m = b % 2;
        if (m == 0) {
          arrayOfChar[b] = (char)(arrayOfChar[b] ^ j);
          j = ((j >>> 3 | j << 5) ^ arrayOfChar[b]) & 0xFF;
        } else {
          arrayOfChar[b] = (char)(arrayOfChar[b] ^ k);
          k = ((k >>> 3 | k << 5) ^ arrayOfChar[b]) & 0xFF;
        } 
      } 
      b[i] = (new String(arrayOfChar)).intern();
    } 
    return b[i];
  }
}


/* Location:              C:\Program Files\BurpSuitePro\burpsuite_pro.jar!\burp\Zrhu.class
 * Java compiler version: 21 (65.0)
 * JD-Core Version:       1.1.3
 */