package burp;

import java.math.BigInteger;

class Zrkv extends ClassLoader {
  static Object ZQ;
  
  static String ZZ;
  
  private static final String[] a;
  
  private static final String[] b;
  
  static void Zo(Object[] paramArrayOfObject, Object paramObject) throws Throwable {}
  
  static boolean ZV(Object[] paramArrayOfObject, Object paramObject) throws Throwable {
    // Byte code:
    //   0: invokestatic ZK : ()Z
    //   3: istore_2
    //   4: new java/lang/StringBuilder
    //   7: dup
    //   8: invokespecial <init> : ()V
    //   11: astore_3
    //   12: iconst_0
    //   13: istore #4
    //   15: iload #4
    //   17: bipush #32
    //   19: if_icmpge -> 1355
    //   22: iload #4
    //   24: tableswitch default -> 1348, 0 -> 168, 1 -> 205, 2 -> 242, 3 -> 279, 4 -> 316, 5 -> 353, 6 -> 390, 7 -> 427, 8 -> 464, 9 -> 501, 10 -> 538, 11 -> 575, 12 -> 612, 13 -> 649, 14 -> 686, 15 -> 723, 16 -> 760, 17 -> 797, 18 -> 834, 19 -> 871, 20 -> 908, 21 -> 945, 22 -> 982, 23 -> 1019, 24 -> 1056, 25 -> 1093, 26 -> 1130, 27 -> 1167, 28 -> 1204, 29 -> 1241, 30 -> 1278, 31 -> 1315
    //   168: aload_3
    //   169: getstatic burp/Zbp_.ZQ : Ljava/lang/String;
    //   172: getstatic burp/Zlr2.Zq : Ljava/lang/Object;
    //   175: checkcast java/math/BigInteger
    //   178: invokevirtual intValue : ()I
    //   181: bipush #32
    //   183: irem
    //   184: invokestatic abs : (I)I
    //   187: invokevirtual charAt : (I)C
    //   190: invokevirtual append : (C)Ljava/lang/StringBuilder;
    //   193: pop
    //   194: iload_2
    //   195: ifeq -> 1348
    //   198: goto -> 205
    //   201: invokestatic a : (Ljava/lang/Throwable;)Ljava/lang/Throwable;
    //   204: athrow
    //   205: aload_3
    //   206: getstatic burp/Zmzh.Zm : Ljava/lang/String;
    //   209: getstatic burp/Zlsw.ZJ : Ljava/lang/Object;
    //   212: checkcast java/math/BigInteger
    //   215: invokevirtual intValue : ()I
    //   218: bipush #32
    //   220: irem
    //   221: invokestatic abs : (I)I
    //   224: invokevirtual charAt : (I)C
    //   227: invokevirtual append : (C)Ljava/lang/StringBuilder;
    //   230: pop
    //   231: iload_2
    //   232: ifeq -> 1348
    //   235: goto -> 242
    //   238: invokestatic a : (Ljava/lang/Throwable;)Ljava/lang/Throwable;
    //   241: athrow
    //   242: aload_3
    //   243: getstatic burp/Zeb3.ZG : Ljava/lang/String;
    //   246: getstatic burp/Zb0z.ZQ : Ljava/lang/Object;
    //   249: checkcast java/math/BigInteger
    //   252: invokevirtual intValue : ()I
    //   255: bipush #32
    //   257: irem
    //   258: invokestatic abs : (I)I
    //   261: invokevirtual charAt : (I)C
    //   264: invokevirtual append : (C)Ljava/lang/StringBuilder;
    //   267: pop
    //   268: iload_2
    //   269: ifeq -> 1348
    //   272: goto -> 279
    //   275: invokestatic a : (Ljava/lang/Throwable;)Ljava/lang/Throwable;
    //   278: athrow
    //   279: aload_3
    //   280: getstatic burp/Zgt6.Zu : Ljava/lang/String;
    //   283: getstatic burp/Zrs0.Zz : Ljava/lang/Object;
    //   286: checkcast java/math/BigInteger
    //   289: invokevirtual intValue : ()I
    //   292: bipush #32
    //   294: irem
    //   295: invokestatic abs : (I)I
    //   298: invokevirtual charAt : (I)C
    //   301: invokevirtual append : (C)Ljava/lang/StringBuilder;
    //   304: pop
    //   305: iload_2
    //   306: ifeq -> 1348
    //   309: goto -> 316
    //   312: invokestatic a : (Ljava/lang/Throwable;)Ljava/lang/Throwable;
    //   315: athrow
    //   316: aload_3
    //   317: getstatic burp/Zlpn.ZF : Ljava/lang/String;
    //   320: getstatic burp/Ztkc.ZV : Ljava/lang/Object;
    //   323: checkcast java/math/BigInteger
    //   326: invokevirtual intValue : ()I
    //   329: bipush #32
    //   331: irem
    //   332: invokestatic abs : (I)I
    //   335: invokevirtual charAt : (I)C
    //   338: invokevirtual append : (C)Ljava/lang/StringBuilder;
    //   341: pop
    //   342: iload_2
    //   343: ifeq -> 1348
    //   346: goto -> 353
    //   349: invokestatic a : (Ljava/lang/Throwable;)Ljava/lang/Throwable;
    //   352: athrow
    //   353: aload_3
    //   354: getstatic burp/Ztd3.ZC : Ljava/lang/String;
    //   357: getstatic burp/Zsf3.ZH : Ljava/lang/Object;
    //   360: checkcast java/math/BigInteger
    //   363: invokevirtual intValue : ()I
    //   366: bipush #32
    //   368: irem
    //   369: invokestatic abs : (I)I
    //   372: invokevirtual charAt : (I)C
    //   375: invokevirtual append : (C)Ljava/lang/StringBuilder;
    //   378: pop
    //   379: iload_2
    //   380: ifeq -> 1348
    //   383: goto -> 390
    //   386: invokestatic a : (Ljava/lang/Throwable;)Ljava/lang/Throwable;
    //   389: athrow
    //   390: aload_3
    //   391: getstatic burp/Zkfa.Zy : Ljava/lang/String;
    //   394: getstatic burp/Zkfa.Zw : Ljava/lang/Object;
    //   397: checkcast java/math/BigInteger
    //   400: invokevirtual intValue : ()I
    //   403: bipush #32
    //   405: irem
    //   406: invokestatic abs : (I)I
    //   409: invokevirtual charAt : (I)C
    //   412: invokevirtual append : (C)Ljava/lang/StringBuilder;
    //   415: pop
    //   416: iload_2
    //   417: ifeq -> 1348
    //   420: goto -> 427
    //   423: invokestatic a : (Ljava/lang/Throwable;)Ljava/lang/Throwable;
    //   426: athrow
    //   427: aload_3
    //   428: getstatic burp/Ztys.Zn : Ljava/lang/String;
    //   431: getstatic burp/Zxpb.Zo : Ljava/lang/Object;
    //   434: checkcast java/math/BigInteger
    //   437: invokevirtual intValue : ()I
    //   440: bipush #32
    //   442: irem
    //   443: invokestatic abs : (I)I
    //   446: invokevirtual charAt : (I)C
    //   449: invokevirtual append : (C)Ljava/lang/StringBuilder;
    //   452: pop
    //   453: iload_2
    //   454: ifeq -> 1348
    //   457: goto -> 464
    //   460: invokestatic a : (Ljava/lang/Throwable;)Ljava/lang/Throwable;
    //   463: athrow
    //   464: aload_3
    //   465: getstatic burp/Ztdx.Zl : Ljava/lang/String;
    //   468: getstatic burp/Zeb3.Zb : Ljava/lang/Object;
    //   471: checkcast java/math/BigInteger
    //   474: invokevirtual intValue : ()I
    //   477: bipush #32
    //   479: irem
    //   480: invokestatic abs : (I)I
    //   483: invokevirtual charAt : (I)C
    //   486: invokevirtual append : (C)Ljava/lang/StringBuilder;
    //   489: pop
    //   490: iload_2
    //   491: ifeq -> 1348
    //   494: goto -> 501
    //   497: invokestatic a : (Ljava/lang/Throwable;)Ljava/lang/Throwable;
    //   500: athrow
    //   501: aload_3
    //   502: getstatic burp/Zkfa.Zy : Ljava/lang/String;
    //   505: getstatic burp/Zzou.Zz : Ljava/lang/Object;
    //   508: checkcast java/math/BigInteger
    //   511: invokevirtual intValue : ()I
    //   514: bipush #32
    //   516: irem
    //   517: invokestatic abs : (I)I
    //   520: invokevirtual charAt : (I)C
    //   523: invokevirtual append : (C)Ljava/lang/StringBuilder;
    //   526: pop
    //   527: iload_2
    //   528: ifeq -> 1348
    //   531: goto -> 538
    //   534: invokestatic a : (Ljava/lang/Throwable;)Ljava/lang/Throwable;
    //   537: athrow
    //   538: aload_3
    //   539: getstatic burp/Zelc.ZI : Ljava/lang/String;
    //   542: getstatic burp/Zlb6.Zz : Ljava/lang/Object;
    //   545: checkcast java/math/BigInteger
    //   548: invokevirtual intValue : ()I
    //   551: bipush #32
    //   553: irem
    //   554: invokestatic abs : (I)I
    //   557: invokevirtual charAt : (I)C
    //   560: invokevirtual append : (C)Ljava/lang/StringBuilder;
    //   563: pop
    //   564: iload_2
    //   565: ifeq -> 1348
    //   568: goto -> 575
    //   571: invokestatic a : (Ljava/lang/Throwable;)Ljava/lang/Throwable;
    //   574: athrow
    //   575: aload_3
    //   576: getstatic burp/Zrhu.ZJ : Ljava/lang/String;
    //   579: getstatic burp/Zx_s.ZX : Ljava/lang/Object;
    //   582: checkcast java/math/BigInteger
    //   585: invokevirtual intValue : ()I
    //   588: bipush #32
    //   590: irem
    //   591: invokestatic abs : (I)I
    //   594: invokevirtual charAt : (I)C
    //   597: invokevirtual append : (C)Ljava/lang/StringBuilder;
    //   600: pop
    //   601: iload_2
    //   602: ifeq -> 1348
    //   605: goto -> 612
    //   608: invokestatic a : (Ljava/lang/Throwable;)Ljava/lang/Throwable;
    //   611: athrow
    //   612: aload_3
    //   613: getstatic burp/Zzbr.Zp : Ljava/lang/String;
    //   616: getstatic burp/Zro5.ZT : Ljava/lang/Object;
    //   619: checkcast java/math/BigInteger
    //   622: invokevirtual intValue : ()I
    //   625: bipush #32
    //   627: irem
    //   628: invokestatic abs : (I)I
    //   631: invokevirtual charAt : (I)C
    //   634: invokevirtual append : (C)Ljava/lang/StringBuilder;
    //   637: pop
    //   638: iload_2
    //   639: ifeq -> 1348
    //   642: goto -> 649
    //   645: invokestatic a : (Ljava/lang/Throwable;)Ljava/lang/Throwable;
    //   648: athrow
    //   649: aload_3
    //   650: getstatic burp/Zelc.ZI : Ljava/lang/String;
    //   653: getstatic burp/Ztd3.ZX : Ljava/lang/Object;
    //   656: checkcast java/math/BigInteger
    //   659: invokevirtual intValue : ()I
    //   662: bipush #32
    //   664: irem
    //   665: invokestatic abs : (I)I
    //   668: invokevirtual charAt : (I)C
    //   671: invokevirtual append : (C)Ljava/lang/StringBuilder;
    //   674: pop
    //   675: iload_2
    //   676: ifeq -> 1348
    //   679: goto -> 686
    //   682: invokestatic a : (Ljava/lang/Throwable;)Ljava/lang/Throwable;
    //   685: athrow
    //   686: aload_3
    //   687: getstatic burp/Zlpn.ZF : Ljava/lang/String;
    //   690: getstatic burp/Zlo2.ZM : Ljava/lang/Object;
    //   693: checkcast java/math/BigInteger
    //   696: invokevirtual intValue : ()I
    //   699: bipush #32
    //   701: irem
    //   702: invokestatic abs : (I)I
    //   705: invokevirtual charAt : (I)C
    //   708: invokevirtual append : (C)Ljava/lang/StringBuilder;
    //   711: pop
    //   712: iload_2
    //   713: ifeq -> 1348
    //   716: goto -> 723
    //   719: invokestatic a : (Ljava/lang/Throwable;)Ljava/lang/Throwable;
    //   722: athrow
    //   723: aload_3
    //   724: getstatic burp/Zmji.Zs : Ljava/lang/String;
    //   727: getstatic burp/Zzxs.Zg : Ljava/lang/Object;
    //   730: checkcast java/math/BigInteger
    //   733: invokevirtual intValue : ()I
    //   736: bipush #32
    //   738: irem
    //   739: invokestatic abs : (I)I
    //   742: invokevirtual charAt : (I)C
    //   745: invokevirtual append : (C)Ljava/lang/StringBuilder;
    //   748: pop
    //   749: iload_2
    //   750: ifeq -> 1348
    //   753: goto -> 760
    //   756: invokestatic a : (Ljava/lang/Throwable;)Ljava/lang/Throwable;
    //   759: athrow
    //   760: aload_3
    //   761: getstatic burp/Zx_x.Zv : Ljava/lang/String;
    //   764: getstatic burp/Zsf3.ZH : Ljava/lang/Object;
    //   767: checkcast java/math/BigInteger
    //   770: invokevirtual intValue : ()I
    //   773: bipush #32
    //   775: irem
    //   776: invokestatic abs : (I)I
    //   779: invokevirtual charAt : (I)C
    //   782: invokevirtual append : (C)Ljava/lang/StringBuilder;
    //   785: pop
    //   786: iload_2
    //   787: ifeq -> 1348
    //   790: goto -> 797
    //   793: invokestatic a : (Ljava/lang/Throwable;)Ljava/lang/Throwable;
    //   796: athrow
    //   797: aload_3
    //   798: getstatic burp/Zzbr.Zp : Ljava/lang/String;
    //   801: getstatic burp/Zb9h.Zm : Ljava/lang/Object;
    //   804: checkcast java/math/BigInteger
    //   807: invokevirtual intValue : ()I
    //   810: bipush #32
    //   812: irem
    //   813: invokestatic abs : (I)I
    //   816: invokevirtual charAt : (I)C
    //   819: invokevirtual append : (C)Ljava/lang/StringBuilder;
    //   822: pop
    //   823: iload_2
    //   824: ifeq -> 1348
    //   827: goto -> 834
    //   830: invokestatic a : (Ljava/lang/Throwable;)Ljava/lang/Throwable;
    //   833: athrow
    //   834: aload_3
    //   835: getstatic burp/Zscs.Zw : Ljava/lang/String;
    //   838: getstatic burp/Zzxs.Zg : Ljava/lang/Object;
    //   841: checkcast java/math/BigInteger
    //   844: invokevirtual intValue : ()I
    //   847: bipush #32
    //   849: irem
    //   850: invokestatic abs : (I)I
    //   853: invokevirtual charAt : (I)C
    //   856: invokevirtual append : (C)Ljava/lang/StringBuilder;
    //   859: pop
    //   860: iload_2
    //   861: ifeq -> 1348
    //   864: goto -> 871
    //   867: invokestatic a : (Ljava/lang/Throwable;)Ljava/lang/Throwable;
    //   870: athrow
    //   871: aload_3
    //   872: getstatic burp/Zx_x.Zv : Ljava/lang/String;
    //   875: getstatic burp/Zrf9.Zu : Ljava/lang/Object;
    //   878: checkcast java/math/BigInteger
    //   881: invokevirtual intValue : ()I
    //   884: bipush #32
    //   886: irem
    //   887: invokestatic abs : (I)I
    //   890: invokevirtual charAt : (I)C
    //   893: invokevirtual append : (C)Ljava/lang/StringBuilder;
    //   896: pop
    //   897: iload_2
    //   898: ifeq -> 1348
    //   901: goto -> 908
    //   904: invokestatic a : (Ljava/lang/Throwable;)Ljava/lang/Throwable;
    //   907: athrow
    //   908: aload_3
    //   909: getstatic burp/Zlav.ZW : Ljava/lang/String;
    //   912: getstatic burp/Ztys.Zs : Ljava/lang/Object;
    //   915: checkcast java/math/BigInteger
    //   918: invokevirtual intValue : ()I
    //   921: bipush #32
    //   923: irem
    //   924: invokestatic abs : (I)I
    //   927: invokevirtual charAt : (I)C
    //   930: invokevirtual append : (C)Ljava/lang/StringBuilder;
    //   933: pop
    //   934: iload_2
    //   935: ifeq -> 1348
    //   938: goto -> 945
    //   941: invokestatic a : (Ljava/lang/Throwable;)Ljava/lang/Throwable;
    //   944: athrow
    //   945: aload_3
    //   946: getstatic burp/Zg2.ZN : Ljava/lang/String;
    //   949: getstatic burp/Zb0z.ZQ : Ljava/lang/Object;
    //   952: checkcast java/math/BigInteger
    //   955: invokevirtual intValue : ()I
    //   958: bipush #32
    //   960: irem
    //   961: invokestatic abs : (I)I
    //   964: invokevirtual charAt : (I)C
    //   967: invokevirtual append : (C)Ljava/lang/StringBuilder;
    //   970: pop
    //   971: iload_2
    //   972: ifeq -> 1348
    //   975: goto -> 982
    //   978: invokestatic a : (Ljava/lang/Throwable;)Ljava/lang/Throwable;
    //   981: athrow
    //   982: aload_3
    //   983: getstatic burp/Zlna.Zo : Ljava/lang/String;
    //   986: getstatic burp/Zx_s.ZX : Ljava/lang/Object;
    //   989: checkcast java/math/BigInteger
    //   992: invokevirtual intValue : ()I
    //   995: bipush #32
    //   997: irem
    //   998: invokestatic abs : (I)I
    //   1001: invokevirtual charAt : (I)C
    //   1004: invokevirtual append : (C)Ljava/lang/StringBuilder;
    //   1007: pop
    //   1008: iload_2
    //   1009: ifeq -> 1348
    //   1012: goto -> 1019
    //   1015: invokestatic a : (Ljava/lang/Throwable;)Ljava/lang/Throwable;
    //   1018: athrow
    //   1019: aload_3
    //   1020: getstatic burp/Zmt7.Zl : Ljava/lang/String;
    //   1023: getstatic burp/Zr5k.Zj : Ljava/lang/Object;
    //   1026: checkcast java/math/BigInteger
    //   1029: invokevirtual intValue : ()I
    //   1032: bipush #32
    //   1034: irem
    //   1035: invokestatic abs : (I)I
    //   1038: invokevirtual charAt : (I)C
    //   1041: invokevirtual append : (C)Ljava/lang/StringBuilder;
    //   1044: pop
    //   1045: iload_2
    //   1046: ifeq -> 1348
    //   1049: goto -> 1056
    //   1052: invokestatic a : (Ljava/lang/Throwable;)Ljava/lang/Throwable;
    //   1055: athrow
    //   1056: aload_3
    //   1057: getstatic burp/Zx_s.Za : Ljava/lang/String;
    //   1060: getstatic burp/Zx_x.Zi : Ljava/lang/Object;
    //   1063: checkcast java/math/BigInteger
    //   1066: invokevirtual intValue : ()I
    //   1069: bipush #32
    //   1071: irem
    //   1072: invokestatic abs : (I)I
    //   1075: invokevirtual charAt : (I)C
    //   1078: invokevirtual append : (C)Ljava/lang/StringBuilder;
    //   1081: pop
    //   1082: iload_2
    //   1083: ifeq -> 1348
    //   1086: goto -> 1093
    //   1089: invokestatic a : (Ljava/lang/Throwable;)Ljava/lang/Throwable;
    //   1092: athrow
    //   1093: aload_3
    //   1094: getstatic burp/Zrs0.Zt : Ljava/lang/String;
    //   1097: getstatic burp/Zz35.ZB : Ljava/lang/Object;
    //   1100: checkcast java/math/BigInteger
    //   1103: invokevirtual intValue : ()I
    //   1106: bipush #32
    //   1108: irem
    //   1109: invokestatic abs : (I)I
    //   1112: invokevirtual charAt : (I)C
    //   1115: invokevirtual append : (C)Ljava/lang/StringBuilder;
    //   1118: pop
    //   1119: iload_2
    //   1120: ifeq -> 1348
    //   1123: goto -> 1130
    //   1126: invokestatic a : (Ljava/lang/Throwable;)Ljava/lang/Throwable;
    //   1129: athrow
    //   1130: aload_3
    //   1131: getstatic burp/Zgkn.ZV : Ljava/lang/String;
    //   1134: getstatic burp/Zb20.Zq : Ljava/lang/Object;
    //   1137: checkcast java/math/BigInteger
    //   1140: invokevirtual intValue : ()I
    //   1143: bipush #32
    //   1145: irem
    //   1146: invokestatic abs : (I)I
    //   1149: invokevirtual charAt : (I)C
    //   1152: invokevirtual append : (C)Ljava/lang/StringBuilder;
    //   1155: pop
    //   1156: iload_2
    //   1157: ifeq -> 1348
    //   1160: goto -> 1167
    //   1163: invokestatic a : (Ljava/lang/Throwable;)Ljava/lang/Throwable;
    //   1166: athrow
    //   1167: aload_3
    //   1168: getstatic burp/Zzh0.ZK : Ljava/lang/String;
    //   1171: getstatic burp/Zlb6.Zz : Ljava/lang/Object;
    //   1174: checkcast java/math/BigInteger
    //   1177: invokevirtual intValue : ()I
    //   1180: bipush #32
    //   1182: irem
    //   1183: invokestatic abs : (I)I
    //   1186: invokevirtual charAt : (I)C
    //   1189: invokevirtual append : (C)Ljava/lang/StringBuilder;
    //   1192: pop
    //   1193: iload_2
    //   1194: ifeq -> 1348
    //   1197: goto -> 1204
    //   1200: invokestatic a : (Ljava/lang/Throwable;)Ljava/lang/Throwable;
    //   1203: athrow
    //   1204: aload_3
    //   1205: getstatic burp/Zzou.ZN : Ljava/lang/String;
    //   1208: getstatic burp/Zb2k.ZZ : Ljava/lang/Object;
    //   1211: checkcast java/math/BigInteger
    //   1214: invokevirtual intValue : ()I
    //   1217: bipush #32
    //   1219: irem
    //   1220: invokestatic abs : (I)I
    //   1223: invokevirtual charAt : (I)C
    //   1226: invokevirtual append : (C)Ljava/lang/StringBuilder;
    //   1229: pop
    //   1230: iload_2
    //   1231: ifeq -> 1348
    //   1234: goto -> 1241
    //   1237: invokestatic a : (Ljava/lang/Throwable;)Ljava/lang/Throwable;
    //   1240: athrow
    //   1241: aload_3
    //   1242: getstatic burp/Zx8t.Zi : Ljava/lang/String;
    //   1245: getstatic burp/Zry0.Zr : Ljava/lang/Object;
    //   1248: checkcast java/math/BigInteger
    //   1251: invokevirtual intValue : ()I
    //   1254: bipush #32
    //   1256: irem
    //   1257: invokestatic abs : (I)I
    //   1260: invokevirtual charAt : (I)C
    //   1263: invokevirtual append : (C)Ljava/lang/StringBuilder;
    //   1266: pop
    //   1267: iload_2
    //   1268: ifeq -> 1348
    //   1271: goto -> 1278
    //   1274: invokestatic a : (Ljava/lang/Throwable;)Ljava/lang/Throwable;
    //   1277: athrow
    //   1278: aload_3
    //   1279: getstatic burp/Zgkn.ZV : Ljava/lang/String;
    //   1282: getstatic burp/Zztz.Zq : Ljava/lang/Object;
    //   1285: checkcast java/math/BigInteger
    //   1288: invokevirtual intValue : ()I
    //   1291: bipush #32
    //   1293: irem
    //   1294: invokestatic abs : (I)I
    //   1297: invokevirtual charAt : (I)C
    //   1300: invokevirtual append : (C)Ljava/lang/StringBuilder;
    //   1303: pop
    //   1304: iload_2
    //   1305: ifeq -> 1348
    //   1308: goto -> 1315
    //   1311: invokestatic a : (Ljava/lang/Throwable;)Ljava/lang/Throwable;
    //   1314: athrow
    //   1315: aload_3
    //   1316: getstatic burp/Zeqo.Zw : Ljava/lang/String;
    //   1319: getstatic burp/Zz3w.ZX : Ljava/lang/Object;
    //   1322: checkcast java/math/BigInteger
    //   1325: invokevirtual intValue : ()I
    //   1328: bipush #32
    //   1330: irem
    //   1331: invokestatic abs : (I)I
    //   1334: invokevirtual charAt : (I)C
    //   1337: invokevirtual append : (C)Ljava/lang/StringBuilder;
    //   1340: pop
    //   1341: goto -> 1348
    //   1344: invokestatic a : (Ljava/lang/Throwable;)Ljava/lang/Throwable;
    //   1347: athrow
    //   1348: iinc #4, 1
    //   1351: iload_2
    //   1352: ifeq -> 15
    //   1355: sipush #21618
    //   1358: sipush #-30672
    //   1361: invokestatic a : (II)Ljava/lang/String;
    //   1364: invokestatic forName : (Ljava/lang/String;)Ljava/lang/Class;
    //   1367: invokevirtual getDeclaredFields : ()[Ljava/lang/reflect/Field;
    //   1370: astore #4
    //   1372: aload #4
    //   1374: arraylength
    //   1375: istore #5
    //   1377: iconst_0
    //   1378: istore #6
    //   1380: iload #6
    //   1382: iload #5
    //   1384: if_icmpge -> 1515
    //   1387: aload #4
    //   1389: iload #6
    //   1391: aaload
    //   1392: astore #7
    //   1394: aload #7
    //   1396: invokevirtual getType : ()Ljava/lang/Class;
    //   1399: ldc java/lang/Object
    //   1401: invokevirtual equals : (Ljava/lang/Object;)Z
    //   1404: ifeq -> 1508
    //   1407: aload #7
    //   1409: iconst_1
    //   1410: invokevirtual setAccessible : (Z)V
    //   1413: sipush #21622
    //   1416: sipush #-3522
    //   1419: invokestatic a : (II)Ljava/lang/String;
    //   1422: invokestatic forName : (Ljava/lang/String;)Ljava/lang/Class;
    //   1425: invokevirtual getDeclaredFields : ()[Ljava/lang/reflect/Field;
    //   1428: astore #8
    //   1430: aload #8
    //   1432: arraylength
    //   1433: istore #9
    //   1435: iconst_0
    //   1436: istore #10
    //   1438: iload #10
    //   1440: iload #9
    //   1442: if_icmpge -> 1508
    //   1445: aload #8
    //   1447: iload #10
    //   1449: aaload
    //   1450: astore #11
    //   1452: aload #11
    //   1454: invokevirtual getType : ()Ljava/lang/Class;
    //   1457: ldc java/lang/Object
    //   1459: invokevirtual equals : (Ljava/lang/Object;)Z
    //   1462: ifeq -> 1494
    //   1465: aload #11
    //   1467: iconst_1
    //   1468: invokevirtual setAccessible : (Z)V
    //   1471: aload #7
    //   1473: aconst_null
    //   1474: aload #11
    //   1476: aconst_null
    //   1477: invokevirtual get : (Ljava/lang/Object;)Ljava/lang/Object;
    //   1480: invokevirtual set : (Ljava/lang/Object;Ljava/lang/Object;)V
    //   1483: iload_2
    //   1484: ifeq -> 1515
    //   1487: goto -> 1494
    //   1490: invokestatic a : (Ljava/lang/Throwable;)Ljava/lang/Throwable;
    //   1493: athrow
    //   1494: iinc #10, 1
    //   1497: iload_2
    //   1498: ifeq -> 1438
    //   1501: goto -> 1508
    //   1504: invokestatic a : (Ljava/lang/Throwable;)Ljava/lang/Throwable;
    //   1507: athrow
    //   1508: iinc #6, 1
    //   1511: iload_2
    //   1512: ifeq -> 1380
    //   1515: sipush #21619
    //   1518: sipush #3842
    //   1521: invokestatic a : (II)Ljava/lang/String;
    //   1524: iconst_1
    //   1525: ldc burp/Zghe
    //   1527: invokevirtual getClassLoader : ()Ljava/lang/ClassLoader;
    //   1530: invokestatic forName : (Ljava/lang/String;ZLjava/lang/ClassLoader;)Ljava/lang/Class;
    //   1533: invokevirtual getDeclaredFields : ()[Ljava/lang/reflect/Field;
    //   1536: astore #4
    //   1538: aload #4
    //   1540: arraylength
    //   1541: istore #5
    //   1543: iconst_0
    //   1544: istore #6
    //   1546: iload #6
    //   1548: iload #5
    //   1550: if_icmpge -> 1688
    //   1553: aload #4
    //   1555: iload #6
    //   1557: aaload
    //   1558: astore #7
    //   1560: aload #7
    //   1562: invokevirtual getModifiers : ()I
    //   1565: invokestatic isStatic : (I)Z
    //   1568: ifne -> 1578
    //   1571: goto -> 1681
    //   1574: invokestatic a : (Ljava/lang/Throwable;)Ljava/lang/Throwable;
    //   1577: athrow
    //   1578: aload #7
    //   1580: invokevirtual getType : ()Ljava/lang/Class;
    //   1583: astore #8
    //   1585: aload #8
    //   1587: ifnull -> 1668
    //   1590: aload #8
    //   1592: invokevirtual isPrimitive : ()Z
    //   1595: ifne -> 1668
    //   1598: goto -> 1605
    //   1601: invokestatic a : (Ljava/lang/Throwable;)Ljava/lang/Throwable;
    //   1604: athrow
    //   1605: aload #8
    //   1607: invokevirtual getPackage : ()Ljava/lang/Package;
    //   1610: ifnull -> 1668
    //   1613: goto -> 1620
    //   1616: invokestatic a : (Ljava/lang/Throwable;)Ljava/lang/Throwable;
    //   1619: athrow
    //   1620: aload #8
    //   1622: invokevirtual getPackage : ()Ljava/lang/Package;
    //   1625: invokevirtual getName : ()Ljava/lang/String;
    //   1628: ifnull -> 1668
    //   1631: goto -> 1638
    //   1634: invokestatic a : (Ljava/lang/Throwable;)Ljava/lang/Throwable;
    //   1637: athrow
    //   1638: aload #8
    //   1640: invokevirtual getPackage : ()Ljava/lang/Package;
    //   1643: invokevirtual getName : ()Ljava/lang/String;
    //   1646: sipush #21617
    //   1649: sipush #23833
    //   1652: invokestatic a : (II)Ljava/lang/String;
    //   1655: invokevirtual startsWith : (Ljava/lang/String;)Z
    //   1658: ifne -> 1668
    //   1661: goto -> 1668
    //   1664: invokestatic a : (Ljava/lang/Throwable;)Ljava/lang/Throwable;
    //   1667: athrow
    //   1668: aload #7
    //   1670: iconst_1
    //   1671: invokevirtual setAccessible : (Z)V
    //   1674: aload #7
    //   1676: aconst_null
    //   1677: invokevirtual get : (Ljava/lang/Object;)Ljava/lang/Object;
    //   1680: pop
    //   1681: iinc #6, 1
    //   1684: iload_2
    //   1685: ifeq -> 1546
    //   1688: sipush #21616
    //   1691: sipush #2412
    //   1694: invokestatic a : (II)Ljava/lang/String;
    //   1697: invokestatic forName : (Ljava/lang/String;)Ljava/lang/Class;
    //   1700: invokevirtual getDeclaredMethods : ()[Ljava/lang/reflect/Method;
    //   1703: astore #4
    //   1705: aload #4
    //   1707: arraylength
    //   1708: istore #5
    //   1710: iconst_0
    //   1711: istore #6
    //   1713: iload #6
    //   1715: iload #5
    //   1717: if_icmpge -> 1850
    //   1720: aload #4
    //   1722: iload #6
    //   1724: aaload
    //   1725: astore #7
    //   1727: aload #7
    //   1729: invokevirtual getParameterTypes : ()[Ljava/lang/Class;
    //   1732: pop
    //   1733: aload #7
    //   1735: invokevirtual getModifiers : ()I
    //   1738: invokestatic isStatic : (I)Z
    //   1741: ifeq -> 1836
    //   1744: aload #7
    //   1746: invokevirtual getParameterTypes : ()[Ljava/lang/Class;
    //   1749: arraylength
    //   1750: iconst_2
    //   1751: if_icmpne -> 1836
    //   1754: goto -> 1761
    //   1757: invokestatic a : (Ljava/lang/Throwable;)Ljava/lang/Throwable;
    //   1760: athrow
    //   1761: aload #7
    //   1763: invokevirtual getReturnType : ()Ljava/lang/Class;
    //   1766: getstatic java/lang/Void.TYPE : Ljava/lang/Class;
    //   1769: invokevirtual equals : (Ljava/lang/Object;)Z
    //   1772: ifeq -> 1836
    //   1775: goto -> 1782
    //   1778: invokestatic a : (Ljava/lang/Throwable;)Ljava/lang/Throwable;
    //   1781: athrow
    //   1782: aload #7
    //   1784: iconst_1
    //   1785: invokevirtual setAccessible : (Z)V
    //   1788: aload #7
    //   1790: aconst_null
    //   1791: iconst_2
    //   1792: anewarray java/lang/Object
    //   1795: dup
    //   1796: iconst_0
    //   1797: aload_0
    //   1798: aastore
    //   1799: dup
    //   1800: iconst_1
    //   1801: aload_1
    //   1802: ifnonnull -> 1820
    //   1805: goto -> 1812
    //   1808: invokestatic a : (Ljava/lang/Throwable;)Ljava/lang/Throwable;
    //   1811: athrow
    //   1812: aload_1
    //   1813: goto -> 1827
    //   1816: invokestatic a : (Ljava/lang/Throwable;)Ljava/lang/Throwable;
    //   1819: athrow
    //   1820: aload_1
    //   1821: checkcast [B
    //   1824: invokevirtual clone : ()Ljava/lang/Object;
    //   1827: aastore
    //   1828: invokevirtual invoke : (Ljava/lang/Object;[Ljava/lang/Object;)Ljava/lang/Object;
    //   1831: pop
    //   1832: iload_2
    //   1833: ifeq -> 1850
    //   1836: iinc #6, 1
    //   1839: iload_2
    //   1840: ifeq -> 1713
    //   1843: goto -> 1850
    //   1846: invokestatic a : (Ljava/lang/Throwable;)Ljava/lang/Throwable;
    //   1849: athrow
    //   1850: getstatic burp/Zgt6.Zu : Ljava/lang/String;
    //   1853: getstatic burp/Zsf3.ZH : Ljava/lang/Object;
    //   1856: checkcast java/math/BigInteger
    //   1859: invokevirtual intValue : ()I
    //   1862: bipush #32
    //   1864: irem
    //   1865: invokestatic abs : (I)I
    //   1868: invokevirtual charAt : (I)C
    //   1871: getstatic burp/Zgta.ZL : Ljava/lang/String;
    //   1874: getstatic burp/Zx4y.Zc : Ljava/lang/Object;
    //   1877: checkcast java/math/BigInteger
    //   1880: invokevirtual intValue : ()I
    //   1883: bipush #32
    //   1885: irem
    //   1886: invokestatic abs : (I)I
    //   1889: invokevirtual charAt : (I)C
    //   1892: if_icmpgt -> 1999
    //   1895: getstatic burp/Zb9h.Zf : Ljava/lang/String;
    //   1898: getstatic burp/Zrpy.ZG : Ljava/lang/Object;
    //   1901: checkcast java/math/BigInteger
    //   1904: invokevirtual intValue : ()I
    //   1907: bipush #32
    //   1909: irem
    //   1910: invokestatic abs : (I)I
    //   1913: invokevirtual charAt : (I)C
    //   1916: getstatic burp/Zx_s.Za : Ljava/lang/String;
    //   1919: getstatic burp/Zrs0.Zz : Ljava/lang/Object;
    //   1922: checkcast java/math/BigInteger
    //   1925: invokevirtual intValue : ()I
    //   1928: bipush #32
    //   1930: irem
    //   1931: invokestatic abs : (I)I
    //   1934: invokevirtual charAt : (I)C
    //   1937: if_icmpgt -> 1999
    //   1940: goto -> 1947
    //   1943: invokestatic a : (Ljava/lang/Throwable;)Ljava/lang/Throwable;
    //   1946: athrow
    //   1947: getstatic burp/Zeor.Zj : Ljava/lang/String;
    //   1950: getstatic burp/Zgkn.Zm : Ljava/lang/Object;
    //   1953: checkcast java/math/BigInteger
    //   1956: invokevirtual intValue : ()I
    //   1959: bipush #32
    //   1961: irem
    //   1962: invokestatic abs : (I)I
    //   1965: invokevirtual charAt : (I)C
    //   1968: getstatic burp/Zzok.ZC : Ljava/lang/String;
    //   1971: getstatic burp/Ztkc.ZV : Ljava/lang/Object;
    //   1974: checkcast java/math/BigInteger
    //   1977: invokevirtual intValue : ()I
    //   1980: bipush #32
    //   1982: irem
    //   1983: invokestatic abs : (I)I
    //   1986: invokevirtual charAt : (I)C
    //   1989: if_icmple -> 2007
    //   1992: goto -> 1999
    //   1995: invokestatic a : (Ljava/lang/Throwable;)Ljava/lang/Throwable;
    //   1998: athrow
    //   1999: iconst_1
    //   2000: goto -> 2008
    //   2003: invokestatic a : (Ljava/lang/Throwable;)Ljava/lang/Throwable;
    //   2006: athrow
    //   2007: iconst_0
    //   2008: ireturn
    //   2009: astore_3
    //   2010: new java/lang/Exception
    //   2013: dup
    //   2014: aload_3
    //   2015: invokevirtual getMessage : ()Ljava/lang/String;
    //   2018: invokespecial <init> : (Ljava/lang/String;)V
    //   2021: athrow
    // Exception table:
    //   from	to	target	type
    //   4	2008	2009	java/lang/Throwable
    //   22	198	201	java/lang/Throwable
    //   168	235	238	java/lang/Throwable
    //   205	272	275	java/lang/Throwable
    //   242	309	312	java/lang/Throwable
    //   279	346	349	java/lang/Throwable
    //   316	383	386	java/lang/Throwable
    //   353	420	423	java/lang/Throwable
    //   390	457	460	java/lang/Throwable
    //   427	494	497	java/lang/Throwable
    //   464	531	534	java/lang/Throwable
    //   501	568	571	java/lang/Throwable
    //   538	605	608	java/lang/Throwable
    //   575	642	645	java/lang/Throwable
    //   612	679	682	java/lang/Throwable
    //   649	716	719	java/lang/Throwable
    //   686	753	756	java/lang/Throwable
    //   723	790	793	java/lang/Throwable
    //   760	827	830	java/lang/Throwable
    //   797	864	867	java/lang/Throwable
    //   834	901	904	java/lang/Throwable
    //   871	938	941	java/lang/Throwable
    //   908	975	978	java/lang/Throwable
    //   945	1012	1015	java/lang/Throwable
    //   982	1049	1052	java/lang/Throwable
    //   1019	1086	1089	java/lang/Throwable
    //   1056	1123	1126	java/lang/Throwable
    //   1093	1160	1163	java/lang/Throwable
    //   1130	1197	1200	java/lang/Throwable
    //   1167	1234	1237	java/lang/Throwable
    //   1204	1271	1274	java/lang/Throwable
    //   1241	1308	1311	java/lang/Throwable
    //   1278	1341	1344	java/lang/Throwable
    //   1452	1487	1490	java/lang/Throwable
    //   1465	1501	1504	java/lang/Throwable
    //   1560	1574	1574	java/lang/Throwable
    //   1585	1598	1601	java/lang/Throwable
    //   1590	1613	1616	java/lang/Throwable
    //   1605	1631	1634	java/lang/Throwable
    //   1620	1661	1664	java/lang/Throwable
    //   1727	1754	1757	java/lang/Throwable
    //   1744	1775	1778	java/lang/Throwable
    //   1761	1805	1808	java/lang/Throwable
    //   1782	1816	1816	java/lang/Throwable
    //   1827	1843	1846	java/lang/Throwable
    //   1850	1940	1943	java/lang/Throwable
    //   1895	1992	1995	java/lang/Throwable
    //   1947	2003	2003	java/lang/Throwable
  }
  
  static void ZE(Object paramObject) {
    Zbzc.ZL = a(21620, 3892);
    Zbzc.Zp = new BigInteger(a(21621, -23863));
    boolean bool = Zt2e.ZN();
    try {
      try {
        if (Zzpj.ZR.charAt(Math.abs(((BigInteger)Zb8_.ZT).intValue() % 32)) > Ztev.Zp.charAt(Math.abs(((BigInteger)Zsuw.ZB).intValue() % 32))) {
          try {
            Zead.ZW(Class.forName(a(21628, 5852)));
            if (!bool)
              Zs26.Zj(Class.forName(a(21629, -22571))); 
          } catch (Throwable throwable) {
            throw a(null);
          } 
          return;
        } 
      } catch (Throwable throwable) {
        throw a(null);
      } 
      Zs26.Zj(Class.forName(a(21629, -22571)));
    } catch (Throwable throwable) {}
  }
  
  static {
    // Byte code:
    //   0: bipush #10
    //   2: anewarray java/lang/String
    //   5: astore #5
    //   7: iconst_0
    //   8: istore_3
    //   9: ldc 'gJÂ€ Â“Ã˜Ã½qÃ¤Â§$4Ã–*<\\bD6Â¼Ã³Â‡ÂŸÃ¾Â•Ã·EoÃ†Â±ÂªMÂ‚Â³\\tÃ†0Â’CÃ£Ã…iÂœ"Âœ?7?HÂ“ Â¦Ã•ÃŽÂ·ÃµÃ¡s$ÃŸÃ¾ÂÂ‘Â¥Ã˜iUÃ Ã¯ÃŠQÂ¬ÃšÂ­\Ã’Ã’Â“Ã£BÂƒÂ‡a\\nuqÂ³Ã¢Â¿Â¯wÂ‰Â»Â¤RÃ‘XÂšÂ½'Â£Ã‹Â²\\tÂ¼1Â˜*Â·Ã Ã—T,_mÃ³Â®SPDRÂ½Ã—ÂžÂ¹H"ÂºÂ´dÃ´Ã©LÃ¸ÂºÂº8\\tÃ?Â¼?Â›Ã«Â[Ã„p&Â¨\\tÃŒ~?Ã«Ã®ÂˆÃ´\\t\\tiPÂ‹Ã’}VLÃ¬_'
    //   11: dup
    //   12: astore_2
    //   13: invokevirtual length : ()I
    //   16: istore #4
    //   18: bipush #32
    //   20: istore_1
    //   21: iconst_m1
    //   22: istore_0
    //   23: bipush #68
    //   25: iinc #0, 1
    //   28: aload_2
    //   29: iload_0
    //   30: dup
    //   31: iload_1
    //   32: iadd
    //   33: invokevirtual substring : (II)Ljava/lang/String;
    //   36: iconst_m1
    //   37: goto -> 143
    //   40: aload #5
    //   42: swap
    //   43: iload_3
    //   44: iinc #3, 1
    //   47: swap
    //   48: aastore
    //   49: iload_0
    //   50: iload_1
    //   51: iadd
    //   52: dup
    //   53: istore_0
    //   54: iload #4
    //   56: if_icmpge -> 68
    //   59: aload_2
    //   60: iload_0
    //   61: invokevirtual charAt : (I)C
    //   64: istore_1
    //   65: goto -> 23
    //   68: ldc 'FÃ½Â‹ Ã®cdÃ\\tÃÃŒÂ©ÂªÂ¡Ã¤C'
    //   70: dup
    //   71: astore_2
    //   72: invokevirtual length : ()I
    //   75: istore #4
    //   77: bipush #9
    //   79: istore_1
    //   80: iconst_m1
    //   81: istore_0
    //   82: bipush #113
    //   84: iinc #0, 1
    //   87: aload_2
    //   88: iload_0
    //   89: dup
    //   90: iload_1
    //   91: iadd
    //   92: invokevirtual substring : (II)Ljava/lang/String;
    //   95: iconst_0
    //   96: goto -> 143
    //   99: aload #5
    //   101: swap
    //   102: iload_3
    //   103: iinc #3, 1
    //   106: swap
    //   107: aastore
    //   108: iload_0
    //   109: iload_1
    //   110: iadd
    //   111: dup
    //   112: istore_0
    //   113: iload #4
    //   115: if_icmpge -> 127
    //   118: aload_2
    //   119: iload_0
    //   120: invokevirtual charAt : (I)C
    //   123: istore_1
    //   124: goto -> 82
    //   127: aload #5
    //   129: putstatic burp/Zrkv.a : [Ljava/lang/String;
    //   132: bipush #10
    //   134: anewarray java/lang/String
    //   137: putstatic burp/Zrkv.b : [Ljava/lang/String;
    //   140: goto -> 300
    //   143: dup_x2
    //   144: pop
    //   145: invokevirtual toCharArray : ()[C
    //   148: dup_x1
    //   149: arraylength
    //   150: dup_x2
    //   151: pop
    //   152: iconst_0
    //   153: istore #6
    //   155: dup2_x1
    //   156: pop2
    //   157: dup_x2
    //   158: iconst_1
    //   159: if_icmpgt -> 260
    //   162: dup2
    //   163: swap
    //   164: iload #6
    //   166: dup2_x1
    //   167: caload
    //   168: swap
    //   169: iload #6
    //   171: bipush #7
    //   173: irem
    //   174: tableswitch default -> 242, 0 -> 212, 1 -> 217, 2 -> 222, 3 -> 227, 4 -> 232, 5 -> 237
    //   212: bipush #88
    //   214: goto -> 244
    //   217: bipush #69
    //   219: goto -> 244
    //   222: bipush #61
    //   224: goto -> 244
    //   227: bipush #23
    //   229: goto -> 244
    //   232: bipush #117
    //   234: goto -> 244
    //   237: bipush #6
    //   239: goto -> 244
    //   242: bipush #15
    //   244: ixor
    //   245: ixor
    //   246: i2c
    //   247: castore
    //   248: iinc #6, 1
    //   251: dup
    //   252: ifne -> 260
    //   255: dup2
    //   256: dup_x1
    //   257: goto -> 166
    //   260: dup2_x1
    //   261: pop2
    //   262: dup_x2
    //   263: iload #6
    //   265: if_icmpgt -> 162
    //   268: pop
    //   269: new java/lang/String
    //   272: dup_x1
    //   273: swap
    //   274: invokespecial <init> : ([C)V
    //   277: invokevirtual intern : ()Ljava/lang/String;
    //   280: swap
    //   281: pop
    //   282: swap
    //   283: tableswitch default -> 40, 0 -> 99
    //   300: new java/math/BigInteger
    //   303: dup
    //   304: bipush #32
    //   306: newarray byte
    //   308: dup
    //   309: iconst_0
    //   310: bipush #37
    //   312: bastore
    //   313: dup
    //   314: iconst_1
    //   315: bipush #-29
    //   317: bastore
    //   318: dup
    //   319: iconst_2
    //   320: bipush #-74
    //   322: bastore
    //   323: dup
    //   324: iconst_3
    //   325: bipush #-16
    //   327: bastore
    //   328: dup
    //   329: iconst_4
    //   330: bipush #25
    //   332: bastore
    //   333: dup
    //   334: iconst_5
    //   335: bipush #37
    //   337: bastore
    //   338: dup
    //   339: bipush #6
    //   341: bipush #-90
    //   343: bastore
    //   344: dup
    //   345: bipush #7
    //   347: bipush #96
    //   349: bastore
    //   350: dup
    //   351: bipush #8
    //   353: bipush #111
    //   355: bastore
    //   356: dup
    //   357: bipush #9
    //   359: bipush #-83
    //   361: bastore
    //   362: dup
    //   363: bipush #10
    //   365: iconst_1
    //   366: bastore
    //   367: dup
    //   368: bipush #11
    //   370: bipush #-69
    //   372: bastore
    //   373: dup
    //   374: bipush #12
    //   376: bipush #-111
    //   378: bastore
    //   379: dup
    //   380: bipush #13
    //   382: bipush #-104
    //   384: bastore
    //   385: dup
    //   386: bipush #14
    //   388: bipush #-12
    //   390: bastore
    //   391: dup
    //   392: bipush #15
    //   394: bipush #60
    //   396: bastore
    //   397: dup
    //   398: bipush #16
    //   400: bipush #-122
    //   402: bastore
    //   403: dup
    //   404: bipush #17
    //   406: bipush #-92
    //   408: bastore
    //   409: dup
    //   410: bipush #18
    //   412: bipush #41
    //   414: bastore
    //   415: dup
    //   416: bipush #19
    //   418: bipush #12
    //   420: bastore
    //   421: dup
    //   422: bipush #20
    //   424: bipush #-94
    //   426: bastore
    //   427: dup
    //   428: bipush #21
    //   430: bipush #-81
    //   432: bastore
    //   433: dup
    //   434: bipush #22
    //   436: bipush #71
    //   438: bastore
    //   439: dup
    //   440: bipush #23
    //   442: bipush #-19
    //   444: bastore
    //   445: dup
    //   446: bipush #24
    //   448: bipush #88
    //   450: bastore
    //   451: dup
    //   452: bipush #25
    //   454: bipush #-98
    //   456: bastore
    //   457: dup
    //   458: bipush #26
    //   460: bipush #127
    //   462: bastore
    //   463: dup
    //   464: bipush #27
    //   466: bipush #94
    //   468: bastore
    //   469: dup
    //   470: bipush #28
    //   472: bipush #-103
    //   474: bastore
    //   475: dup
    //   476: bipush #29
    //   478: bipush #-122
    //   480: bastore
    //   481: dup
    //   482: bipush #30
    //   484: bipush #-113
    //   486: bastore
    //   487: dup
    //   488: bipush #31
    //   490: bipush #-109
    //   492: bastore
    //   493: invokespecial <init> : ([B)V
    //   496: putstatic burp/Zrkv.ZQ : Ljava/lang/Object;
    //   499: sipush #21623
    //   502: sipush #-2934
    //   505: invokestatic a : (II)Ljava/lang/String;
    //   508: putstatic burp/Zrkv.ZZ : Ljava/lang/String;
    //   511: return
  }
  
  private static Throwable a(Throwable paramThrowable) {
    return paramThrowable;
  }
  
  private static String a(int paramInt1, int paramInt2) {
    int i = (paramInt1 ^ 0x5474) & 0xFFFF;
    if (b[i] == null) {
      char[] arrayOfChar = a[i].toCharArray();
      switch (arrayOfChar[0] & 0xFF) {
        case 0:
        
        case 1:
        
        case 2:
        
        case 3:
        
        case 4:
        
        case 5:
        
        case 6:
        
        case 7:
        
        case 8:
        
        case 9:
        
        case 10:
        
        case 11:
        
        case 12:
        
        case 13:
        
        case 14:
        
        case 15:
        
        case 16:
        
        case 17:
        
        case 18:
        
        case 19:
        
        case 20:
        
        case 21:
        
        case 22:
        
        case 23:
        
        case 24:
        
        case 25:
        
        case 26:
        
        case 27:
        
        case 28:
        
        case 29:
        
        case 30:
        
        case 31:
        
        case 32:
        
        case 33:
        
        case 34:
        
        case 35:
        
        case 36:
        
        case 37:
        
        case 38:
        
        case 39:
        
        case 40:
        
        case 41:
        
        case 42:
        
        case 43:
        
        case 44:
        
        case 45:
        
        case 46:
        
        case 47:
        
        case 48:
        
        case 49:
        
        case 50:
        
        case 51:
        
        case 52:
        
        case 53:
        
        case 54:
        
        case 55:
        
        case 56:
        
        case 57:
        
        case 58:
        
        case 59:
        
        case 60:
        
        case 61:
        
        case 62:
        
        case 63:
        
        case 64:
        
        case 65:
        
        case 66:
        
        case 67:
        
        case 68:
        
        case 69:
        
        case 70:
        
        case 71:
        
        case 72:
        
        case 73:
        
        case 74:
        
        case 75:
        
        case 76:
        
        case 77:
        
        case 78:
        
        case 79:
        
        case 80:
        
        case 81:
        
        case 82:
        
        case 83:
        
        case 84:
        
        case 85:
        
        case 86:
        
        case 87:
        
        case 88:
        
        case 89:
        
        case 90:
        
        case 91:
        
        case 92:
        
        case 93:
        
        case 94:
        
        case 95:
        
        case 96:
        
        case 97:
        
        case 98:
        
        case 99:
        
        case 100:
        
        case 101:
        
        case 102:
        
        case 103:
        
        case 104:
        
        case 105:
        
        case 106:
        
        case 107:
        
        case 108:
        
        case 109:
        
        case 110:
        
        case 111:
        
        case 112:
        
        case 113:
        
        case 114:
        
        case 115:
        
        case 116:
        
        case 117:
        
        case 118:
        
        case 119:
        
        case 120:
        
        case 121:
        
        case 122:
        
        case 123:
        
        case 124:
        
        case 125:
        
        case 126:
        
        case 127:
        
        case 128:
        
        case 129:
        
        case 130:
        
        case 131:
        
        case 132:
        
        case 133:
        
        case 134:
        
        case 135:
        
        case 136:
        
        case 137:
        
        case 138:
        
        case 139:
        
        case 140:
        
        case 141:
        
        case 142:
        
        case 143:
        
        case 144:
        
        case 145:
        
        case 146:
        
        case 147:
        
        case 148:
        
        case 149:
        
        case 150:
        
        case 151:
        
        case 152:
        
        case 153:
        
        case 154:
        
        case 155:
        
        case 156:
        
        case 157:
        
        case 158:
        
        case 159:
        
        case 160:
        
        case 161:
        
        case 162:
        
        case 163:
        
        case 164:
        
        case 165:
        
        case 166:
        
        case 167:
        
        case 168:
        
        case 169:
        
        case 170:
        
        case 171:
        
        case 172:
        
        case 173:
        
        case 174:
        
        case 175:
        
        case 176:
        
        case 177:
        
        case 178:
        
        case 179:
        
        case 180:
        
        case 181:
        
        case 182:
        
        case 183:
        
        case 184:
        
        case 185:
        
        case 186:
        
        case 187:
        
        case 188:
        
        case 189:
        
        case 190:
        
        case 191:
        
        case 192:
        
        case 193:
        
        case 194:
        
        case 195:
        
        case 196:
        
        case 197:
        
        case 198:
        
        case 199:
        
        case 200:
        
        case 201:
        
        case 202:
        
        case 203:
        
        case 204:
        
        case 205:
        
        case 206:
        
        case 207:
        
        case 208:
        
        case 209:
        
        case 210:
        
        case 211:
        
        case 212:
        
        case 213:
        
        case 214:
        
        case 215:
        
        case 216:
        
        case 217:
        
        case 218:
        
        case 219:
        
        case 220:
        
        case 221:
        
        case 222:
        
        case 223:
        
        case 224:
        
        case 225:
        
        case 226:
        
        case 227:
        
        case 228:
        
        case 229:
        
        case 230:
        
        case 231:
        
        case 232:
        
        case 233:
        
        case 234:
        
        case 235:
        
        case 236:
        
        case 237:
        
        case 238:
        
        case 239:
        
        case 240:
        
        case 241:
        
        case 242:
        
        case 243:
        
        case 244:
        
        case 245:
        
        case 246:
        
        case 247:
        
        case 248:
        
        case 249:
        
        case 250:
        
        case 251:
        
        case 252:
        
        case 253:
        
        case 254:
        
        default:
          break;
      } 
      char c = 'Âƒ';
      int j = (paramInt2 & 0xFF) - c;
      if (j < 0)
        j += 256; 
      int k = ((paramInt2 & 0xFFFF) >>> 8) - c;
      if (k < 0)
        k += 256; 
      for (byte b = 0; b < arrayOfChar.length; b++) {
        int m = b % 2;
        if (m == 0) {
          arrayOfChar[b] = (char)(arrayOfChar[b] ^ j);
          j = ((j >>> 3 | j << 5) ^ arrayOfChar[b]) & 0xFF;
        } else {
          arrayOfChar[b] = (char)(arrayOfChar[b] ^ k);
          k = ((k >>> 3 | k << 5) ^ arrayOfChar[b]) & 0xFF;
        } 
      } 
      b[i] = (new String(arrayOfChar)).intern();
    } 
    return b[i];
  }
}


/* Location:              C:\Program Files\BurpSuitePro\burpsuite_pro.jar!\burp\Zrkv.class
 * Java compiler version: 21 (65.0)
 * JD-Core Version:       1.1.3
 */