package burp;

import java.math.BigInteger;

class Zrkw extends ClassLoader {
  static String ZU;
  
  static Object ZV;
  
  private static final String[] a;
  
  private static final String[] b;
  
  static void Zy(Object[] paramArrayOfObject, Object paramObject) throws Throwable {}
  
  static void ZE(Object paramObject) {
    Zg61.ZX = a(-11046, -13865);
    Zg61.Zp = new BigInteger(a(-11044, 18935));
    boolean bool = Zt2e.ZN();
    try {
      try {
        if (Zmhq.Zy.charAt(Math.abs(((BigInteger)Zrex.Zr).intValue() % 32)) <= Zer1.ZV.charAt(Math.abs(((BigInteger)Zegj.ZT).intValue() % 32))) {
          try {
            Zk7f.Zu(Class.forName(a(-11041, -17455)));
            if (!bool)
              Zrw0.Zo(Class.forName(a(-11053, -14275))); 
          } catch (Throwable throwable) {
            throw a(null);
          } 
          return;
        } 
      } catch (Throwable throwable) {
        throw a(null);
      } 
      Zrw0.Zo(Class.forName(a(-11053, -14275)));
    } catch (Throwable throwable) {}
  }
  
  static boolean Zl(Object[] paramArrayOfObject, Object paramObject) throws Throwable {
    // Byte code:
    //   0: invokestatic ZK : ()Z
    //   3: istore_2
    //   4: getstatic burp/Zelt.ZC : Ljava/lang/Object;
    //   7: checkcast java/math/BigInteger
    //   10: invokevirtual toByteArray : ()[B
    //   13: astore_3
    //   14: bipush #64
    //   16: newarray byte
    //   18: dup
    //   19: iconst_0
    //   20: bipush #-128
    //   22: bastore
    //   23: dup
    //   24: iconst_1
    //   25: iconst_0
    //   26: bastore
    //   27: dup
    //   28: iconst_2
    //   29: iconst_0
    //   30: bastore
    //   31: dup
    //   32: iconst_3
    //   33: iconst_0
    //   34: bastore
    //   35: dup
    //   36: iconst_4
    //   37: iconst_0
    //   38: bastore
    //   39: dup
    //   40: iconst_5
    //   41: iconst_0
    //   42: bastore
    //   43: dup
    //   44: bipush #6
    //   46: iconst_0
    //   47: bastore
    //   48: dup
    //   49: bipush #7
    //   51: iconst_0
    //   52: bastore
    //   53: dup
    //   54: bipush #8
    //   56: iconst_0
    //   57: bastore
    //   58: dup
    //   59: bipush #9
    //   61: iconst_0
    //   62: bastore
    //   63: dup
    //   64: bipush #10
    //   66: iconst_0
    //   67: bastore
    //   68: dup
    //   69: bipush #11
    //   71: iconst_0
    //   72: bastore
    //   73: dup
    //   74: bipush #12
    //   76: iconst_0
    //   77: bastore
    //   78: dup
    //   79: bipush #13
    //   81: iconst_0
    //   82: bastore
    //   83: dup
    //   84: bipush #14
    //   86: iconst_0
    //   87: bastore
    //   88: dup
    //   89: bipush #15
    //   91: iconst_0
    //   92: bastore
    //   93: dup
    //   94: bipush #16
    //   96: iconst_0
    //   97: bastore
    //   98: dup
    //   99: bipush #17
    //   101: iconst_0
    //   102: bastore
    //   103: dup
    //   104: bipush #18
    //   106: iconst_0
    //   107: bastore
    //   108: dup
    //   109: bipush #19
    //   111: iconst_0
    //   112: bastore
    //   113: dup
    //   114: bipush #20
    //   116: iconst_0
    //   117: bastore
    //   118: dup
    //   119: bipush #21
    //   121: iconst_0
    //   122: bastore
    //   123: dup
    //   124: bipush #22
    //   126: iconst_0
    //   127: bastore
    //   128: dup
    //   129: bipush #23
    //   131: iconst_0
    //   132: bastore
    //   133: dup
    //   134: bipush #24
    //   136: iconst_0
    //   137: bastore
    //   138: dup
    //   139: bipush #25
    //   141: iconst_0
    //   142: bastore
    //   143: dup
    //   144: bipush #26
    //   146: iconst_0
    //   147: bastore
    //   148: dup
    //   149: bipush #27
    //   151: iconst_0
    //   152: bastore
    //   153: dup
    //   154: bipush #28
    //   156: iconst_0
    //   157: bastore
    //   158: dup
    //   159: bipush #29
    //   161: iconst_0
    //   162: bastore
    //   163: dup
    //   164: bipush #30
    //   166: iconst_0
    //   167: bastore
    //   168: dup
    //   169: bipush #31
    //   171: iconst_0
    //   172: bastore
    //   173: dup
    //   174: bipush #32
    //   176: iconst_0
    //   177: bastore
    //   178: dup
    //   179: bipush #33
    //   181: iconst_0
    //   182: bastore
    //   183: dup
    //   184: bipush #34
    //   186: iconst_0
    //   187: bastore
    //   188: dup
    //   189: bipush #35
    //   191: iconst_0
    //   192: bastore
    //   193: dup
    //   194: bipush #36
    //   196: iconst_0
    //   197: bastore
    //   198: dup
    //   199: bipush #37
    //   201: iconst_0
    //   202: bastore
    //   203: dup
    //   204: bipush #38
    //   206: iconst_0
    //   207: bastore
    //   208: dup
    //   209: bipush #39
    //   211: iconst_0
    //   212: bastore
    //   213: dup
    //   214: bipush #40
    //   216: iconst_0
    //   217: bastore
    //   218: dup
    //   219: bipush #41
    //   221: iconst_0
    //   222: bastore
    //   223: dup
    //   224: bipush #42
    //   226: iconst_0
    //   227: bastore
    //   228: dup
    //   229: bipush #43
    //   231: iconst_0
    //   232: bastore
    //   233: dup
    //   234: bipush #44
    //   236: iconst_0
    //   237: bastore
    //   238: dup
    //   239: bipush #45
    //   241: iconst_0
    //   242: bastore
    //   243: dup
    //   244: bipush #46
    //   246: iconst_0
    //   247: bastore
    //   248: dup
    //   249: bipush #47
    //   251: iconst_0
    //   252: bastore
    //   253: dup
    //   254: bipush #48
    //   256: iconst_0
    //   257: bastore
    //   258: dup
    //   259: bipush #49
    //   261: iconst_0
    //   262: bastore
    //   263: dup
    //   264: bipush #50
    //   266: iconst_0
    //   267: bastore
    //   268: dup
    //   269: bipush #51
    //   271: iconst_0
    //   272: bastore
    //   273: dup
    //   274: bipush #52
    //   276: iconst_0
    //   277: bastore
    //   278: dup
    //   279: bipush #53
    //   281: iconst_0
    //   282: bastore
    //   283: dup
    //   284: bipush #54
    //   286: iconst_0
    //   287: bastore
    //   288: dup
    //   289: bipush #55
    //   291: iconst_0
    //   292: bastore
    //   293: dup
    //   294: bipush #56
    //   296: iconst_0
    //   297: bastore
    //   298: dup
    //   299: bipush #57
    //   301: iconst_0
    //   302: bastore
    //   303: dup
    //   304: bipush #58
    //   306: iconst_0
    //   307: bastore
    //   308: dup
    //   309: bipush #59
    //   311: iconst_0
    //   312: bastore
    //   313: dup
    //   314: bipush #60
    //   316: iconst_0
    //   317: bastore
    //   318: dup
    //   319: bipush #61
    //   321: iconst_0
    //   322: bastore
    //   323: dup
    //   324: bipush #62
    //   326: iconst_0
    //   327: bastore
    //   328: dup
    //   329: bipush #63
    //   331: iconst_0
    //   332: bastore
    //   333: astore #5
    //   335: bipush #64
    //   337: newarray int
    //   339: dup
    //   340: iconst_0
    //   341: ldc 1116352408
    //   343: iastore
    //   344: dup
    //   345: iconst_1
    //   346: ldc 1899447441
    //   348: iastore
    //   349: dup
    //   350: iconst_2
    //   351: ldc -1245643825
    //   353: iastore
    //   354: dup
    //   355: iconst_3
    //   356: ldc -373957723
    //   358: iastore
    //   359: dup
    //   360: iconst_4
    //   361: ldc 961987163
    //   363: iastore
    //   364: dup
    //   365: iconst_5
    //   366: ldc 1508970993
    //   368: iastore
    //   369: dup
    //   370: bipush #6
    //   372: ldc -1841331548
    //   374: iastore
    //   375: dup
    //   376: bipush #7
    //   378: ldc -1424204075
    //   380: iastore
    //   381: dup
    //   382: bipush #8
    //   384: ldc -670586216
    //   386: iastore
    //   387: dup
    //   388: bipush #9
    //   390: ldc 310598401
    //   392: iastore
    //   393: dup
    //   394: bipush #10
    //   396: ldc 607225278
    //   398: iastore
    //   399: dup
    //   400: bipush #11
    //   402: ldc 1426881987
    //   404: iastore
    //   405: dup
    //   406: bipush #12
    //   408: ldc 1925078388
    //   410: iastore
    //   411: dup
    //   412: bipush #13
    //   414: ldc -2132889090
    //   416: iastore
    //   417: dup
    //   418: bipush #14
    //   420: ldc -1680079193
    //   422: iastore
    //   423: dup
    //   424: bipush #15
    //   426: ldc -1046744716
    //   428: iastore
    //   429: dup
    //   430: bipush #16
    //   432: ldc -459576895
    //   434: iastore
    //   435: dup
    //   436: bipush #17
    //   438: ldc -272742522
    //   440: iastore
    //   441: dup
    //   442: bipush #18
    //   444: ldc 264347078
    //   446: iastore
    //   447: dup
    //   448: bipush #19
    //   450: ldc 604807628
    //   452: iastore
    //   453: dup
    //   454: bipush #20
    //   456: ldc 770255983
    //   458: iastore
    //   459: dup
    //   460: bipush #21
    //   462: ldc 1249150122
    //   464: iastore
    //   465: dup
    //   466: bipush #22
    //   468: ldc 1555081692
    //   470: iastore
    //   471: dup
    //   472: bipush #23
    //   474: ldc 1996064986
    //   476: iastore
    //   477: dup
    //   478: bipush #24
    //   480: ldc -1740746414
    //   482: iastore
    //   483: dup
    //   484: bipush #25
    //   486: ldc -1473132947
    //   488: iastore
    //   489: dup
    //   490: bipush #26
    //   492: ldc -1341970488
    //   494: iastore
    //   495: dup
    //   496: bipush #27
    //   498: ldc -1084653625
    //   500: iastore
    //   501: dup
    //   502: bipush #28
    //   504: ldc -958395405
    //   506: iastore
    //   507: dup
    //   508: bipush #29
    //   510: ldc -710438585
    //   512: iastore
    //   513: dup
    //   514: bipush #30
    //   516: ldc 113926993
    //   518: iastore
    //   519: dup
    //   520: bipush #31
    //   522: ldc 338241895
    //   524: iastore
    //   525: dup
    //   526: bipush #32
    //   528: ldc 666307205
    //   530: iastore
    //   531: dup
    //   532: bipush #33
    //   534: ldc 773529912
    //   536: iastore
    //   537: dup
    //   538: bipush #34
    //   540: ldc 1294757372
    //   542: iastore
    //   543: dup
    //   544: bipush #35
    //   546: ldc 1396182291
    //   548: iastore
    //   549: dup
    //   550: bipush #36
    //   552: ldc 1695183700
    //   554: iastore
    //   555: dup
    //   556: bipush #37
    //   558: ldc 1986661051
    //   560: iastore
    //   561: dup
    //   562: bipush #38
    //   564: ldc -2117940946
    //   566: iastore
    //   567: dup
    //   568: bipush #39
    //   570: ldc -1838011259
    //   572: iastore
    //   573: dup
    //   574: bipush #40
    //   576: ldc -1564481375
    //   578: iastore
    //   579: dup
    //   580: bipush #41
    //   582: ldc -1474664885
    //   584: iastore
    //   585: dup
    //   586: bipush #42
    //   588: ldc -1035236496
    //   590: iastore
    //   591: dup
    //   592: bipush #43
    //   594: ldc -949202525
    //   596: iastore
    //   597: dup
    //   598: bipush #44
    //   600: ldc -778901479
    //   602: iastore
    //   603: dup
    //   604: bipush #45
    //   606: ldc -694614492
    //   608: iastore
    //   609: dup
    //   610: bipush #46
    //   612: ldc -200395387
    //   614: iastore
    //   615: dup
    //   616: bipush #47
    //   618: ldc 275423344
    //   620: iastore
    //   621: dup
    //   622: bipush #48
    //   624: ldc 430227734
    //   626: iastore
    //   627: dup
    //   628: bipush #49
    //   630: ldc 506948616
    //   632: iastore
    //   633: dup
    //   634: bipush #50
    //   636: ldc 659060556
    //   638: iastore
    //   639: dup
    //   640: bipush #51
    //   642: ldc 883997877
    //   644: iastore
    //   645: dup
    //   646: bipush #52
    //   648: ldc 958139571
    //   650: iastore
    //   651: dup
    //   652: bipush #53
    //   654: ldc 1322822218
    //   656: iastore
    //   657: dup
    //   658: bipush #54
    //   660: ldc 1537002063
    //   662: iastore
    //   663: dup
    //   664: bipush #55
    //   666: ldc 1747873779
    //   668: iastore
    //   669: dup
    //   670: bipush #56
    //   672: ldc 1955562222
    //   674: iastore
    //   675: dup
    //   676: bipush #57
    //   678: ldc 2024104815
    //   680: iastore
    //   681: dup
    //   682: bipush #58
    //   684: ldc -2067236844
    //   686: iastore
    //   687: dup
    //   688: bipush #59
    //   690: ldc -1933114872
    //   692: iastore
    //   693: dup
    //   694: bipush #60
    //   696: ldc -1866530822
    //   698: iastore
    //   699: dup
    //   700: bipush #61
    //   702: ldc -1538233109
    //   704: iastore
    //   705: dup
    //   706: bipush #62
    //   708: ldc -1090935817
    //   710: iastore
    //   711: dup
    //   712: bipush #63
    //   714: ldc -965641998
    //   716: iastore
    //   717: astore #6
    //   719: iconst_2
    //   720: newarray int
    //   722: dup
    //   723: iconst_0
    //   724: iconst_0
    //   725: iastore
    //   726: dup
    //   727: iconst_1
    //   728: iconst_0
    //   729: iastore
    //   730: astore #7
    //   732: bipush #8
    //   734: newarray int
    //   736: dup
    //   737: iconst_0
    //   738: ldc 1779033703
    //   740: iastore
    //   741: dup
    //   742: iconst_1
    //   743: ldc -1150833019
    //   745: iastore
    //   746: dup
    //   747: iconst_2
    //   748: ldc 1013904242
    //   750: iastore
    //   751: dup
    //   752: iconst_3
    //   753: ldc -1521486534
    //   755: iastore
    //   756: dup
    //   757: iconst_4
    //   758: ldc 1359893119
    //   760: iastore
    //   761: dup
    //   762: iconst_5
    //   763: ldc -1694144372
    //   765: iastore
    //   766: dup
    //   767: bipush #6
    //   769: ldc 528734635
    //   771: iastore
    //   772: dup
    //   773: bipush #7
    //   775: ldc 1541459225
    //   777: iastore
    //   778: astore #8
    //   780: bipush #64
    //   782: newarray byte
    //   784: astore #9
    //   786: bipush #64
    //   788: newarray byte
    //   790: astore #10
    //   792: aload_3
    //   793: arraylength
    //   794: istore #11
    //   796: aload #7
    //   798: iconst_0
    //   799: iaload
    //   800: bipush #63
    //   802: iand
    //   803: istore #12
    //   805: aload #7
    //   807: iconst_0
    //   808: dup2
    //   809: iaload
    //   810: iload #11
    //   812: iadd
    //   813: iastore
    //   814: aload #7
    //   816: iconst_0
    //   817: dup2
    //   818: iaload
    //   819: iconst_m1
    //   820: iand
    //   821: iastore
    //   822: aload #7
    //   824: iconst_0
    //   825: iaload
    //   826: iload #11
    //   828: if_icmpge -> 846
    //   831: aload #7
    //   833: iconst_1
    //   834: dup2
    //   835: iaload
    //   836: iconst_1
    //   837: iadd
    //   838: iastore
    //   839: goto -> 846
    //   842: invokestatic a : (Ljava/lang/Throwable;)Ljava/lang/Throwable;
    //   845: athrow
    //   846: iconst_0
    //   847: istore #13
    //   849: iload #11
    //   851: bipush #64
    //   853: if_icmplt -> 1462
    //   856: iconst_0
    //   857: istore #14
    //   859: iload #14
    //   861: bipush #64
    //   863: if_icmpge -> 885
    //   866: aload #10
    //   868: iload #14
    //   870: aload_3
    //   871: iload #13
    //   873: iload #14
    //   875: iadd
    //   876: baload
    //   877: bastore
    //   878: iinc #14, 1
    //   881: iload_2
    //   882: ifeq -> 859
    //   885: bipush #64
    //   887: newarray int
    //   889: astore #14
    //   891: bipush #8
    //   893: newarray int
    //   895: astore #15
    //   897: iconst_0
    //   898: istore #16
    //   900: iload #16
    //   902: bipush #8
    //   904: if_icmpge -> 924
    //   907: aload #15
    //   909: iload #16
    //   911: aload #8
    //   913: iload #16
    //   915: iaload
    //   916: iastore
    //   917: iinc #16, 1
    //   920: iload_2
    //   921: ifeq -> 900
    //   924: iconst_0
    //   925: istore #16
    //   927: iload #16
    //   929: bipush #64
    //   931: if_icmpge -> 1422
    //   934: iload #16
    //   936: bipush #16
    //   938: if_icmpge -> 1019
    //   941: aload #14
    //   943: iload #16
    //   945: aload #10
    //   947: iconst_4
    //   948: iload #16
    //   950: imul
    //   951: baload
    //   952: sipush #255
    //   955: iand
    //   956: bipush #24
    //   958: ishl
    //   959: aload #10
    //   961: iconst_4
    //   962: iload #16
    //   964: imul
    //   965: iconst_1
    //   966: iadd
    //   967: baload
    //   968: sipush #255
    //   971: iand
    //   972: bipush #16
    //   974: ishl
    //   975: ior
    //   976: aload #10
    //   978: iconst_4
    //   979: iload #16
    //   981: imul
    //   982: iconst_2
    //   983: iadd
    //   984: baload
    //   985: sipush #255
    //   988: iand
    //   989: bipush #8
    //   991: ishl
    //   992: ior
    //   993: aload #10
    //   995: iconst_4
    //   996: iload #16
    //   998: imul
    //   999: iconst_3
    //   1000: iadd
    //   1001: baload
    //   1002: sipush #255
    //   1005: iand
    //   1006: ior
    //   1007: iastore
    //   1008: iload_2
    //   1009: ifeq -> 1162
    //   1012: goto -> 1019
    //   1015: invokestatic a : (Ljava/lang/Throwable;)Ljava/lang/Throwable;
    //   1018: athrow
    //   1019: aload #14
    //   1021: iload #16
    //   1023: aload #14
    //   1025: iload #16
    //   1027: iconst_2
    //   1028: isub
    //   1029: iaload
    //   1030: bipush #17
    //   1032: iushr
    //   1033: aload #14
    //   1035: iload #16
    //   1037: iconst_2
    //   1038: isub
    //   1039: iaload
    //   1040: bipush #15
    //   1042: ishl
    //   1043: ior
    //   1044: aload #14
    //   1046: iload #16
    //   1048: iconst_2
    //   1049: isub
    //   1050: iaload
    //   1051: bipush #19
    //   1053: iushr
    //   1054: aload #14
    //   1056: iload #16
    //   1058: iconst_2
    //   1059: isub
    //   1060: iaload
    //   1061: bipush #13
    //   1063: ishl
    //   1064: ior
    //   1065: ixor
    //   1066: aload #14
    //   1068: iload #16
    //   1070: iconst_2
    //   1071: isub
    //   1072: iaload
    //   1073: bipush #10
    //   1075: iushr
    //   1076: ixor
    //   1077: aload #14
    //   1079: iload #16
    //   1081: bipush #7
    //   1083: isub
    //   1084: iaload
    //   1085: iadd
    //   1086: aload #14
    //   1088: iload #16
    //   1090: bipush #15
    //   1092: isub
    //   1093: iaload
    //   1094: bipush #7
    //   1096: iushr
    //   1097: aload #14
    //   1099: iload #16
    //   1101: bipush #15
    //   1103: isub
    //   1104: iaload
    //   1105: bipush #25
    //   1107: ishl
    //   1108: ior
    //   1109: aload #14
    //   1111: iload #16
    //   1113: bipush #15
    //   1115: isub
    //   1116: iaload
    //   1117: bipush #18
    //   1119: iushr
    //   1120: aload #14
    //   1122: iload #16
    //   1124: bipush #15
    //   1126: isub
    //   1127: iaload
    //   1128: bipush #14
    //   1130: ishl
    //   1131: ior
    //   1132: ixor
    //   1133: aload #14
    //   1135: iload #16
    //   1137: bipush #15
    //   1139: isub
    //   1140: iaload
    //   1141: iconst_3
    //   1142: iushr
    //   1143: ixor
    //   1144: iadd
    //   1145: aload #14
    //   1147: iload #16
    //   1149: bipush #16
    //   1151: isub
    //   1152: iaload
    //   1153: iadd
    //   1154: iastore
    //   1155: goto -> 1162
    //   1158: invokestatic a : (Ljava/lang/Throwable;)Ljava/lang/Throwable;
    //   1161: athrow
    //   1162: aload #15
    //   1164: bipush #7
    //   1166: iaload
    //   1167: aload #15
    //   1169: iconst_4
    //   1170: iaload
    //   1171: bipush #6
    //   1173: iushr
    //   1174: aload #15
    //   1176: iconst_4
    //   1177: iaload
    //   1178: bipush #26
    //   1180: ishl
    //   1181: ior
    //   1182: aload #15
    //   1184: iconst_4
    //   1185: iaload
    //   1186: bipush #11
    //   1188: iushr
    //   1189: aload #15
    //   1191: iconst_4
    //   1192: iaload
    //   1193: bipush #21
    //   1195: ishl
    //   1196: ior
    //   1197: ixor
    //   1198: aload #15
    //   1200: iconst_4
    //   1201: iaload
    //   1202: bipush #25
    //   1204: iushr
    //   1205: aload #15
    //   1207: iconst_4
    //   1208: iaload
    //   1209: bipush #7
    //   1211: ishl
    //   1212: ior
    //   1213: ixor
    //   1214: iadd
    //   1215: aload #15
    //   1217: bipush #6
    //   1219: iaload
    //   1220: aload #15
    //   1222: iconst_4
    //   1223: iaload
    //   1224: aload #15
    //   1226: iconst_5
    //   1227: iaload
    //   1228: aload #15
    //   1230: bipush #6
    //   1232: iaload
    //   1233: ixor
    //   1234: iand
    //   1235: ixor
    //   1236: iadd
    //   1237: aload #6
    //   1239: iload #16
    //   1241: iaload
    //   1242: iadd
    //   1243: aload #14
    //   1245: iload #16
    //   1247: iaload
    //   1248: iadd
    //   1249: istore #17
    //   1251: aload #15
    //   1253: iconst_0
    //   1254: iaload
    //   1255: iconst_2
    //   1256: iushr
    //   1257: aload #15
    //   1259: iconst_0
    //   1260: iaload
    //   1261: bipush #30
    //   1263: ishl
    //   1264: ior
    //   1265: aload #15
    //   1267: iconst_0
    //   1268: iaload
    //   1269: bipush #13
    //   1271: iushr
    //   1272: aload #15
    //   1274: iconst_0
    //   1275: iaload
    //   1276: bipush #19
    //   1278: ishl
    //   1279: ior
    //   1280: ixor
    //   1281: aload #15
    //   1283: iconst_0
    //   1284: iaload
    //   1285: bipush #22
    //   1287: iushr
    //   1288: aload #15
    //   1290: iconst_0
    //   1291: iaload
    //   1292: bipush #10
    //   1294: ishl
    //   1295: ior
    //   1296: ixor
    //   1297: aload #15
    //   1299: iconst_0
    //   1300: iaload
    //   1301: aload #15
    //   1303: iconst_1
    //   1304: iaload
    //   1305: iand
    //   1306: aload #15
    //   1308: iconst_2
    //   1309: iaload
    //   1310: aload #15
    //   1312: iconst_0
    //   1313: iaload
    //   1314: aload #15
    //   1316: iconst_1
    //   1317: iaload
    //   1318: ior
    //   1319: iand
    //   1320: ior
    //   1321: iadd
    //   1322: istore #18
    //   1324: aload #15
    //   1326: iconst_3
    //   1327: dup2
    //   1328: iaload
    //   1329: iload #17
    //   1331: iadd
    //   1332: iastore
    //   1333: aload #15
    //   1335: bipush #7
    //   1337: iload #17
    //   1339: iload #18
    //   1341: iadd
    //   1342: iastore
    //   1343: aload #15
    //   1345: bipush #7
    //   1347: iaload
    //   1348: istore #17
    //   1350: aload #15
    //   1352: bipush #7
    //   1354: aload #15
    //   1356: bipush #6
    //   1358: iaload
    //   1359: iastore
    //   1360: aload #15
    //   1362: bipush #6
    //   1364: aload #15
    //   1366: iconst_5
    //   1367: iaload
    //   1368: iastore
    //   1369: aload #15
    //   1371: iconst_5
    //   1372: aload #15
    //   1374: iconst_4
    //   1375: iaload
    //   1376: iastore
    //   1377: aload #15
    //   1379: iconst_4
    //   1380: aload #15
    //   1382: iconst_3
    //   1383: iaload
    //   1384: iastore
    //   1385: aload #15
    //   1387: iconst_3
    //   1388: aload #15
    //   1390: iconst_2
    //   1391: iaload
    //   1392: iastore
    //   1393: aload #15
    //   1395: iconst_2
    //   1396: aload #15
    //   1398: iconst_1
    //   1399: iaload
    //   1400: iastore
    //   1401: aload #15
    //   1403: iconst_1
    //   1404: aload #15
    //   1406: iconst_0
    //   1407: iaload
    //   1408: iastore
    //   1409: aload #15
    //   1411: iconst_0
    //   1412: iload #17
    //   1414: iastore
    //   1415: iinc #16, 1
    //   1418: iload_2
    //   1419: ifeq -> 927
    //   1422: iconst_0
    //   1423: istore #16
    //   1425: iload #16
    //   1427: bipush #8
    //   1429: if_icmpge -> 1452
    //   1432: aload #8
    //   1434: iload #16
    //   1436: dup2
    //   1437: iaload
    //   1438: aload #15
    //   1440: iload #16
    //   1442: iaload
    //   1443: iadd
    //   1444: iastore
    //   1445: iinc #16, 1
    //   1448: iload_2
    //   1449: ifeq -> 1425
    //   1452: iinc #13, 64
    //   1455: iinc #11, -64
    //   1458: iload_2
    //   1459: ifeq -> 849
    //   1462: iload #11
    //   1464: ifle -> 1499
    //   1467: iconst_0
    //   1468: istore #14
    //   1470: iload #14
    //   1472: iload #11
    //   1474: if_icmpge -> 1499
    //   1477: aload #9
    //   1479: iload #12
    //   1481: iload #14
    //   1483: iadd
    //   1484: aload_3
    //   1485: iload #13
    //   1487: iload #14
    //   1489: iadd
    //   1490: baload
    //   1491: bastore
    //   1492: iinc #14, 1
    //   1495: iload_2
    //   1496: ifeq -> 1470
    //   1499: aload #7
    //   1501: iconst_0
    //   1502: iaload
    //   1503: bipush #29
    //   1505: iushr
    //   1506: aload #7
    //   1508: iconst_1
    //   1509: iaload
    //   1510: iconst_3
    //   1511: ishl
    //   1512: ior
    //   1513: istore #14
    //   1515: aload #7
    //   1517: iconst_0
    //   1518: iaload
    //   1519: iconst_3
    //   1520: ishl
    //   1521: istore #15
    //   1523: aload #7
    //   1525: iconst_0
    //   1526: iaload
    //   1527: bipush #63
    //   1529: iand
    //   1530: istore #16
    //   1532: iload #16
    //   1534: bipush #56
    //   1536: if_icmpge -> 1551
    //   1539: bipush #56
    //   1541: iload #16
    //   1543: isub
    //   1544: goto -> 1556
    //   1547: invokestatic a : (Ljava/lang/Throwable;)Ljava/lang/Throwable;
    //   1550: athrow
    //   1551: bipush #120
    //   1553: iload #16
    //   1555: isub
    //   1556: istore #17
    //   1558: aload #7
    //   1560: iconst_0
    //   1561: iaload
    //   1562: bipush #63
    //   1564: iand
    //   1565: istore #12
    //   1567: bipush #64
    //   1569: iload #12
    //   1571: isub
    //   1572: istore #18
    //   1574: aload #7
    //   1576: iconst_0
    //   1577: dup2
    //   1578: iaload
    //   1579: iload #17
    //   1581: iadd
    //   1582: iastore
    //   1583: aload #7
    //   1585: iconst_0
    //   1586: dup2
    //   1587: iaload
    //   1588: iconst_m1
    //   1589: iand
    //   1590: iastore
    //   1591: aload #7
    //   1593: iconst_0
    //   1594: iaload
    //   1595: iload #17
    //   1597: if_icmpge -> 1615
    //   1600: aload #7
    //   1602: iconst_1
    //   1603: dup2
    //   1604: iaload
    //   1605: iconst_1
    //   1606: iadd
    //   1607: iastore
    //   1608: goto -> 1615
    //   1611: invokestatic a : (Ljava/lang/Throwable;)Ljava/lang/Throwable;
    //   1614: athrow
    //   1615: iconst_0
    //   1616: istore #13
    //   1618: iload #12
    //   1620: ifle -> 2251
    //   1623: iload #17
    //   1625: iload #18
    //   1627: if_icmplt -> 2251
    //   1630: goto -> 1637
    //   1633: invokestatic a : (Ljava/lang/Throwable;)Ljava/lang/Throwable;
    //   1636: athrow
    //   1637: iconst_0
    //   1638: istore #19
    //   1640: iload #19
    //   1642: iload #18
    //   1644: if_icmpge -> 1667
    //   1647: aload #9
    //   1649: iload #12
    //   1651: iload #19
    //   1653: iadd
    //   1654: aload #5
    //   1656: iload #19
    //   1658: baload
    //   1659: bastore
    //   1660: iinc #19, 1
    //   1663: iload_2
    //   1664: ifeq -> 1640
    //   1667: bipush #64
    //   1669: newarray int
    //   1671: astore #19
    //   1673: bipush #8
    //   1675: newarray int
    //   1677: astore #20
    //   1679: iconst_0
    //   1680: istore #21
    //   1682: iload #21
    //   1684: bipush #8
    //   1686: if_icmpge -> 1706
    //   1689: aload #20
    //   1691: iload #21
    //   1693: aload #8
    //   1695: iload #21
    //   1697: iaload
    //   1698: iastore
    //   1699: iinc #21, 1
    //   1702: iload_2
    //   1703: ifeq -> 1682
    //   1706: iconst_0
    //   1707: istore #21
    //   1709: iload #21
    //   1711: bipush #64
    //   1713: if_icmpge -> 2204
    //   1716: iload #21
    //   1718: bipush #16
    //   1720: if_icmpge -> 1801
    //   1723: aload #19
    //   1725: iload #21
    //   1727: aload #9
    //   1729: iconst_4
    //   1730: iload #21
    //   1732: imul
    //   1733: baload
    //   1734: sipush #255
    //   1737: iand
    //   1738: bipush #24
    //   1740: ishl
    //   1741: aload #9
    //   1743: iconst_4
    //   1744: iload #21
    //   1746: imul
    //   1747: iconst_1
    //   1748: iadd
    //   1749: baload
    //   1750: sipush #255
    //   1753: iand
    //   1754: bipush #16
    //   1756: ishl
    //   1757: ior
    //   1758: aload #9
    //   1760: iconst_4
    //   1761: iload #21
    //   1763: imul
    //   1764: iconst_2
    //   1765: iadd
    //   1766: baload
    //   1767: sipush #255
    //   1770: iand
    //   1771: bipush #8
    //   1773: ishl
    //   1774: ior
    //   1775: aload #9
    //   1777: iconst_4
    //   1778: iload #21
    //   1780: imul
    //   1781: iconst_3
    //   1782: iadd
    //   1783: baload
    //   1784: sipush #255
    //   1787: iand
    //   1788: ior
    //   1789: iastore
    //   1790: iload_2
    //   1791: ifeq -> 1944
    //   1794: goto -> 1801
    //   1797: invokestatic a : (Ljava/lang/Throwable;)Ljava/lang/Throwable;
    //   1800: athrow
    //   1801: aload #19
    //   1803: iload #21
    //   1805: aload #19
    //   1807: iload #21
    //   1809: iconst_2
    //   1810: isub
    //   1811: iaload
    //   1812: bipush #17
    //   1814: iushr
    //   1815: aload #19
    //   1817: iload #21
    //   1819: iconst_2
    //   1820: isub
    //   1821: iaload
    //   1822: bipush #15
    //   1824: ishl
    //   1825: ior
    //   1826: aload #19
    //   1828: iload #21
    //   1830: iconst_2
    //   1831: isub
    //   1832: iaload
    //   1833: bipush #19
    //   1835: iushr
    //   1836: aload #19
    //   1838: iload #21
    //   1840: iconst_2
    //   1841: isub
    //   1842: iaload
    //   1843: bipush #13
    //   1845: ishl
    //   1846: ior
    //   1847: ixor
    //   1848: aload #19
    //   1850: iload #21
    //   1852: iconst_2
    //   1853: isub
    //   1854: iaload
    //   1855: bipush #10
    //   1857: iushr
    //   1858: ixor
    //   1859: aload #19
    //   1861: iload #21
    //   1863: bipush #7
    //   1865: isub
    //   1866: iaload
    //   1867: iadd
    //   1868: aload #19
    //   1870: iload #21
    //   1872: bipush #15
    //   1874: isub
    //   1875: iaload
    //   1876: bipush #7
    //   1878: iushr
    //   1879: aload #19
    //   1881: iload #21
    //   1883: bipush #15
    //   1885: isub
    //   1886: iaload
    //   1887: bipush #25
    //   1889: ishl
    //   1890: ior
    //   1891: aload #19
    //   1893: iload #21
    //   1895: bipush #15
    //   1897: isub
    //   1898: iaload
    //   1899: bipush #18
    //   1901: iushr
    //   1902: aload #19
    //   1904: iload #21
    //   1906: bipush #15
    //   1908: isub
    //   1909: iaload
    //   1910: bipush #14
    //   1912: ishl
    //   1913: ior
    //   1914: ixor
    //   1915: aload #19
    //   1917: iload #21
    //   1919: bipush #15
    //   1921: isub
    //   1922: iaload
    //   1923: iconst_3
    //   1924: iushr
    //   1925: ixor
    //   1926: iadd
    //   1927: aload #19
    //   1929: iload #21
    //   1931: bipush #16
    //   1933: isub
    //   1934: iaload
    //   1935: iadd
    //   1936: iastore
    //   1937: goto -> 1944
    //   1940: invokestatic a : (Ljava/lang/Throwable;)Ljava/lang/Throwable;
    //   1943: athrow
    //   1944: aload #20
    //   1946: bipush #7
    //   1948: iaload
    //   1949: aload #20
    //   1951: iconst_4
    //   1952: iaload
    //   1953: bipush #6
    //   1955: iushr
    //   1956: aload #20
    //   1958: iconst_4
    //   1959: iaload
    //   1960: bipush #26
    //   1962: ishl
    //   1963: ior
    //   1964: aload #20
    //   1966: iconst_4
    //   1967: iaload
    //   1968: bipush #11
    //   1970: iushr
    //   1971: aload #20
    //   1973: iconst_4
    //   1974: iaload
    //   1975: bipush #21
    //   1977: ishl
    //   1978: ior
    //   1979: ixor
    //   1980: aload #20
    //   1982: iconst_4
    //   1983: iaload
    //   1984: bipush #25
    //   1986: iushr
    //   1987: aload #20
    //   1989: iconst_4
    //   1990: iaload
    //   1991: bipush #7
    //   1993: ishl
    //   1994: ior
    //   1995: ixor
    //   1996: iadd
    //   1997: aload #20
    //   1999: bipush #6
    //   2001: iaload
    //   2002: aload #20
    //   2004: iconst_4
    //   2005: iaload
    //   2006: aload #20
    //   2008: iconst_5
    //   2009: iaload
    //   2010: aload #20
    //   2012: bipush #6
    //   2014: iaload
    //   2015: ixor
    //   2016: iand
    //   2017: ixor
    //   2018: iadd
    //   2019: aload #6
    //   2021: iload #21
    //   2023: iaload
    //   2024: iadd
    //   2025: aload #19
    //   2027: iload #21
    //   2029: iaload
    //   2030: iadd
    //   2031: istore #22
    //   2033: aload #20
    //   2035: iconst_0
    //   2036: iaload
    //   2037: iconst_2
    //   2038: iushr
    //   2039: aload #20
    //   2041: iconst_0
    //   2042: iaload
    //   2043: bipush #30
    //   2045: ishl
    //   2046: ior
    //   2047: aload #20
    //   2049: iconst_0
    //   2050: iaload
    //   2051: bipush #13
    //   2053: iushr
    //   2054: aload #20
    //   2056: iconst_0
    //   2057: iaload
    //   2058: bipush #19
    //   2060: ishl
    //   2061: ior
    //   2062: ixor
    //   2063: aload #20
    //   2065: iconst_0
    //   2066: iaload
    //   2067: bipush #22
    //   2069: iushr
    //   2070: aload #20
    //   2072: iconst_0
    //   2073: iaload
    //   2074: bipush #10
    //   2076: ishl
    //   2077: ior
    //   2078: ixor
    //   2079: aload #20
    //   2081: iconst_0
    //   2082: iaload
    //   2083: aload #20
    //   2085: iconst_1
    //   2086: iaload
    //   2087: iand
    //   2088: aload #20
    //   2090: iconst_2
    //   2091: iaload
    //   2092: aload #20
    //   2094: iconst_0
    //   2095: iaload
    //   2096: aload #20
    //   2098: iconst_1
    //   2099: iaload
    //   2100: ior
    //   2101: iand
    //   2102: ior
    //   2103: iadd
    //   2104: istore #23
    //   2106: aload #20
    //   2108: iconst_3
    //   2109: dup2
    //   2110: iaload
    //   2111: iload #22
    //   2113: iadd
    //   2114: iastore
    //   2115: aload #20
    //   2117: bipush #7
    //   2119: iload #22
    //   2121: iload #23
    //   2123: iadd
    //   2124: iastore
    //   2125: aload #20
    //   2127: bipush #7
    //   2129: iaload
    //   2130: istore #22
    //   2132: aload #20
    //   2134: bipush #7
    //   2136: aload #20
    //   2138: bipush #6
    //   2140: iaload
    //   2141: iastore
    //   2142: aload #20
    //   2144: bipush #6
    //   2146: aload #20
    //   2148: iconst_5
    //   2149: iaload
    //   2150: iastore
    //   2151: aload #20
    //   2153: iconst_5
    //   2154: aload #20
    //   2156: iconst_4
    //   2157: iaload
    //   2158: iastore
    //   2159: aload #20
    //   2161: iconst_4
    //   2162: aload #20
    //   2164: iconst_3
    //   2165: iaload
    //   2166: iastore
    //   2167: aload #20
    //   2169: iconst_3
    //   2170: aload #20
    //   2172: iconst_2
    //   2173: iaload
    //   2174: iastore
    //   2175: aload #20
    //   2177: iconst_2
    //   2178: aload #20
    //   2180: iconst_1
    //   2181: iaload
    //   2182: iastore
    //   2183: aload #20
    //   2185: iconst_1
    //   2186: aload #20
    //   2188: iconst_0
    //   2189: iaload
    //   2190: iastore
    //   2191: aload #20
    //   2193: iconst_0
    //   2194: iload #22
    //   2196: iastore
    //   2197: iinc #21, 1
    //   2200: iload_2
    //   2201: ifeq -> 1709
    //   2204: iconst_0
    //   2205: istore #21
    //   2207: iload #21
    //   2209: bipush #8
    //   2211: if_icmpge -> 2234
    //   2214: aload #8
    //   2216: iload #21
    //   2218: dup2
    //   2219: iaload
    //   2220: aload #20
    //   2222: iload #21
    //   2224: iaload
    //   2225: iadd
    //   2226: iastore
    //   2227: iinc #21, 1
    //   2230: iload_2
    //   2231: ifeq -> 2207
    //   2234: iload #13
    //   2236: iload #18
    //   2238: iadd
    //   2239: istore #13
    //   2241: iload #17
    //   2243: iload #18
    //   2245: isub
    //   2246: istore #17
    //   2248: iconst_0
    //   2249: istore #12
    //   2251: iload #17
    //   2253: bipush #64
    //   2255: if_icmplt -> 2865
    //   2258: iconst_0
    //   2259: istore #19
    //   2261: iload #19
    //   2263: bipush #64
    //   2265: if_icmpge -> 2288
    //   2268: aload #10
    //   2270: iload #19
    //   2272: aload #5
    //   2274: iload #13
    //   2276: iload #19
    //   2278: iadd
    //   2279: baload
    //   2280: bastore
    //   2281: iinc #19, 1
    //   2284: iload_2
    //   2285: ifeq -> 2261
    //   2288: bipush #64
    //   2290: newarray int
    //   2292: astore #19
    //   2294: bipush #8
    //   2296: newarray int
    //   2298: astore #20
    //   2300: iconst_0
    //   2301: istore #21
    //   2303: iload #21
    //   2305: bipush #8
    //   2307: if_icmpge -> 2327
    //   2310: aload #20
    //   2312: iload #21
    //   2314: aload #8
    //   2316: iload #21
    //   2318: iaload
    //   2319: iastore
    //   2320: iinc #21, 1
    //   2323: iload_2
    //   2324: ifeq -> 2303
    //   2327: iconst_0
    //   2328: istore #21
    //   2330: iload #21
    //   2332: bipush #64
    //   2334: if_icmpge -> 2825
    //   2337: iload #21
    //   2339: bipush #16
    //   2341: if_icmpge -> 2422
    //   2344: aload #19
    //   2346: iload #21
    //   2348: aload #10
    //   2350: iconst_4
    //   2351: iload #21
    //   2353: imul
    //   2354: baload
    //   2355: sipush #255
    //   2358: iand
    //   2359: bipush #24
    //   2361: ishl
    //   2362: aload #10
    //   2364: iconst_4
    //   2365: iload #21
    //   2367: imul
    //   2368: iconst_1
    //   2369: iadd
    //   2370: baload
    //   2371: sipush #255
    //   2374: iand
    //   2375: bipush #16
    //   2377: ishl
    //   2378: ior
    //   2379: aload #10
    //   2381: iconst_4
    //   2382: iload #21
    //   2384: imul
    //   2385: iconst_2
    //   2386: iadd
    //   2387: baload
    //   2388: sipush #255
    //   2391: iand
    //   2392: bipush #8
    //   2394: ishl
    //   2395: ior
    //   2396: aload #10
    //   2398: iconst_4
    //   2399: iload #21
    //   2401: imul
    //   2402: iconst_3
    //   2403: iadd
    //   2404: baload
    //   2405: sipush #255
    //   2408: iand
    //   2409: ior
    //   2410: iastore
    //   2411: iload_2
    //   2412: ifeq -> 2565
    //   2415: goto -> 2422
    //   2418: invokestatic a : (Ljava/lang/Throwable;)Ljava/lang/Throwable;
    //   2421: athrow
    //   2422: aload #19
    //   2424: iload #21
    //   2426: aload #19
    //   2428: iload #21
    //   2430: iconst_2
    //   2431: isub
    //   2432: iaload
    //   2433: bipush #17
    //   2435: iushr
    //   2436: aload #19
    //   2438: iload #21
    //   2440: iconst_2
    //   2441: isub
    //   2442: iaload
    //   2443: bipush #15
    //   2445: ishl
    //   2446: ior
    //   2447: aload #19
    //   2449: iload #21
    //   2451: iconst_2
    //   2452: isub
    //   2453: iaload
    //   2454: bipush #19
    //   2456: iushr
    //   2457: aload #19
    //   2459: iload #21
    //   2461: iconst_2
    //   2462: isub
    //   2463: iaload
    //   2464: bipush #13
    //   2466: ishl
    //   2467: ior
    //   2468: ixor
    //   2469: aload #19
    //   2471: iload #21
    //   2473: iconst_2
    //   2474: isub
    //   2475: iaload
    //   2476: bipush #10
    //   2478: iushr
    //   2479: ixor
    //   2480: aload #19
    //   2482: iload #21
    //   2484: bipush #7
    //   2486: isub
    //   2487: iaload
    //   2488: iadd
    //   2489: aload #19
    //   2491: iload #21
    //   2493: bipush #15
    //   2495: isub
    //   2496: iaload
    //   2497: bipush #7
    //   2499: iushr
    //   2500: aload #19
    //   2502: iload #21
    //   2504: bipush #15
    //   2506: isub
    //   2507: iaload
    //   2508: bipush #25
    //   2510: ishl
    //   2511: ior
    //   2512: aload #19
    //   2514: iload #21
    //   2516: bipush #15
    //   2518: isub
    //   2519: iaload
    //   2520: bipush #18
    //   2522: iushr
    //   2523: aload #19
    //   2525: iload #21
    //   2527: bipush #15
    //   2529: isub
    //   2530: iaload
    //   2531: bipush #14
    //   2533: ishl
    //   2534: ior
    //   2535: ixor
    //   2536: aload #19
    //   2538: iload #21
    //   2540: bipush #15
    //   2542: isub
    //   2543: iaload
    //   2544: iconst_3
    //   2545: iushr
    //   2546: ixor
    //   2547: iadd
    //   2548: aload #19
    //   2550: iload #21
    //   2552: bipush #16
    //   2554: isub
    //   2555: iaload
    //   2556: iadd
    //   2557: iastore
    //   2558: goto -> 2565
    //   2561: invokestatic a : (Ljava/lang/Throwable;)Ljava/lang/Throwable;
    //   2564: athrow
    //   2565: aload #20
    //   2567: bipush #7
    //   2569: iaload
    //   2570: aload #20
    //   2572: iconst_4
    //   2573: iaload
    //   2574: bipush #6
    //   2576: iushr
    //   2577: aload #20
    //   2579: iconst_4
    //   2580: iaload
    //   2581: bipush #26
    //   2583: ishl
    //   2584: ior
    //   2585: aload #20
    //   2587: iconst_4
    //   2588: iaload
    //   2589: bipush #11
    //   2591: iushr
    //   2592: aload #20
    //   2594: iconst_4
    //   2595: iaload
    //   2596: bipush #21
    //   2598: ishl
    //   2599: ior
    //   2600: ixor
    //   2601: aload #20
    //   2603: iconst_4
    //   2604: iaload
    //   2605: bipush #25
    //   2607: iushr
    //   2608: aload #20
    //   2610: iconst_4
    //   2611: iaload
    //   2612: bipush #7
    //   2614: ishl
    //   2615: ior
    //   2616: ixor
    //   2617: iadd
    //   2618: aload #20
    //   2620: bipush #6
    //   2622: iaload
    //   2623: aload #20
    //   2625: iconst_4
    //   2626: iaload
    //   2627: aload #20
    //   2629: iconst_5
    //   2630: iaload
    //   2631: aload #20
    //   2633: bipush #6
    //   2635: iaload
    //   2636: ixor
    //   2637: iand
    //   2638: ixor
    //   2639: iadd
    //   2640: aload #6
    //   2642: iload #21
    //   2644: iaload
    //   2645: iadd
    //   2646: aload #19
    //   2648: iload #21
    //   2650: iaload
    //   2651: iadd
    //   2652: istore #22
    //   2654: aload #20
    //   2656: iconst_0
    //   2657: iaload
    //   2658: iconst_2
    //   2659: iushr
    //   2660: aload #20
    //   2662: iconst_0
    //   2663: iaload
    //   2664: bipush #30
    //   2666: ishl
    //   2667: ior
    //   2668: aload #20
    //   2670: iconst_0
    //   2671: iaload
    //   2672: bipush #13
    //   2674: iushr
    //   2675: aload #20
    //   2677: iconst_0
    //   2678: iaload
    //   2679: bipush #19
    //   2681: ishl
    //   2682: ior
    //   2683: ixor
    //   2684: aload #20
    //   2686: iconst_0
    //   2687: iaload
    //   2688: bipush #22
    //   2690: iushr
    //   2691: aload #20
    //   2693: iconst_0
    //   2694: iaload
    //   2695: bipush #10
    //   2697: ishl
    //   2698: ior
    //   2699: ixor
    //   2700: aload #20
    //   2702: iconst_0
    //   2703: iaload
    //   2704: aload #20
    //   2706: iconst_1
    //   2707: iaload
    //   2708: iand
    //   2709: aload #20
    //   2711: iconst_2
    //   2712: iaload
    //   2713: aload #20
    //   2715: iconst_0
    //   2716: iaload
    //   2717: aload #20
    //   2719: iconst_1
    //   2720: iaload
    //   2721: ior
    //   2722: iand
    //   2723: ior
    //   2724: iadd
    //   2725: istore #23
    //   2727: aload #20
    //   2729: iconst_3
    //   2730: dup2
    //   2731: iaload
    //   2732: iload #22
    //   2734: iadd
    //   2735: iastore
    //   2736: aload #20
    //   2738: bipush #7
    //   2740: iload #22
    //   2742: iload #23
    //   2744: iadd
    //   2745: iastore
    //   2746: aload #20
    //   2748: bipush #7
    //   2750: iaload
    //   2751: istore #22
    //   2753: aload #20
    //   2755: bipush #7
    //   2757: aload #20
    //   2759: bipush #6
    //   2761: iaload
    //   2762: iastore
    //   2763: aload #20
    //   2765: bipush #6
    //   2767: aload #20
    //   2769: iconst_5
    //   2770: iaload
    //   2771: iastore
    //   2772: aload #20
    //   2774: iconst_5
    //   2775: aload #20
    //   2777: iconst_4
    //   2778: iaload
    //   2779: iastore
    //   2780: aload #20
    //   2782: iconst_4
    //   2783: aload #20
    //   2785: iconst_3
    //   2786: iaload
    //   2787: iastore
    //   2788: aload #20
    //   2790: iconst_3
    //   2791: aload #20
    //   2793: iconst_2
    //   2794: iaload
    //   2795: iastore
    //   2796: aload #20
    //   2798: iconst_2
    //   2799: aload #20
    //   2801: iconst_1
    //   2802: iaload
    //   2803: iastore
    //   2804: aload #20
    //   2806: iconst_1
    //   2807: aload #20
    //   2809: iconst_0
    //   2810: iaload
    //   2811: iastore
    //   2812: aload #20
    //   2814: iconst_0
    //   2815: iload #22
    //   2817: iastore
    //   2818: iinc #21, 1
    //   2821: iload_2
    //   2822: ifeq -> 2330
    //   2825: iconst_0
    //   2826: istore #21
    //   2828: iload #21
    //   2830: bipush #8
    //   2832: if_icmpge -> 2855
    //   2835: aload #8
    //   2837: iload #21
    //   2839: dup2
    //   2840: iaload
    //   2841: aload #20
    //   2843: iload #21
    //   2845: iaload
    //   2846: iadd
    //   2847: iastore
    //   2848: iinc #21, 1
    //   2851: iload_2
    //   2852: ifeq -> 2828
    //   2855: iinc #13, 64
    //   2858: iinc #17, -64
    //   2861: iload_2
    //   2862: ifeq -> 2251
    //   2865: iload #17
    //   2867: ifle -> 2903
    //   2870: iconst_0
    //   2871: istore #19
    //   2873: iload #19
    //   2875: iload #17
    //   2877: if_icmpge -> 2903
    //   2880: aload #9
    //   2882: iload #12
    //   2884: iload #19
    //   2886: iadd
    //   2887: aload #5
    //   2889: iload #13
    //   2891: iload #19
    //   2893: iadd
    //   2894: baload
    //   2895: bastore
    //   2896: iinc #19, 1
    //   2899: iload_2
    //   2900: ifeq -> 2873
    //   2903: bipush #8
    //   2905: newarray byte
    //   2907: astore #19
    //   2909: aload #19
    //   2911: iconst_0
    //   2912: iload #14
    //   2914: bipush #24
    //   2916: iushr
    //   2917: i2b
    //   2918: bastore
    //   2919: aload #19
    //   2921: iconst_1
    //   2922: iload #14
    //   2924: bipush #16
    //   2926: iushr
    //   2927: i2b
    //   2928: bastore
    //   2929: aload #19
    //   2931: iconst_2
    //   2932: iload #14
    //   2934: bipush #8
    //   2936: iushr
    //   2937: i2b
    //   2938: bastore
    //   2939: aload #19
    //   2941: iconst_3
    //   2942: iload #14
    //   2944: i2b
    //   2945: bastore
    //   2946: aload #19
    //   2948: iconst_4
    //   2949: iload #15
    //   2951: bipush #24
    //   2953: iushr
    //   2954: i2b
    //   2955: bastore
    //   2956: aload #19
    //   2958: iconst_5
    //   2959: iload #15
    //   2961: bipush #16
    //   2963: iushr
    //   2964: i2b
    //   2965: bastore
    //   2966: aload #19
    //   2968: bipush #6
    //   2970: iload #15
    //   2972: bipush #8
    //   2974: iushr
    //   2975: i2b
    //   2976: bastore
    //   2977: aload #19
    //   2979: bipush #7
    //   2981: iload #15
    //   2983: i2b
    //   2984: bastore
    //   2985: bipush #8
    //   2987: istore #11
    //   2989: aload #7
    //   2991: iconst_0
    //   2992: iaload
    //   2993: bipush #63
    //   2995: iand
    //   2996: istore #12
    //   2998: bipush #64
    //   3000: iload #12
    //   3002: isub
    //   3003: istore #18
    //   3005: aload #7
    //   3007: iconst_0
    //   3008: dup2
    //   3009: iaload
    //   3010: iload #11
    //   3012: iadd
    //   3013: iastore
    //   3014: aload #7
    //   3016: iconst_0
    //   3017: dup2
    //   3018: iaload
    //   3019: iconst_m1
    //   3020: iand
    //   3021: iastore
    //   3022: aload #7
    //   3024: iconst_0
    //   3025: iaload
    //   3026: iload #11
    //   3028: if_icmpge -> 3046
    //   3031: aload #7
    //   3033: iconst_1
    //   3034: dup2
    //   3035: iaload
    //   3036: iconst_1
    //   3037: iadd
    //   3038: iastore
    //   3039: goto -> 3046
    //   3042: invokestatic a : (Ljava/lang/Throwable;)Ljava/lang/Throwable;
    //   3045: athrow
    //   3046: iload #12
    //   3048: ifle -> 3662
    //   3051: iload #11
    //   3053: iload #18
    //   3055: if_icmplt -> 3662
    //   3058: goto -> 3065
    //   3061: invokestatic a : (Ljava/lang/Throwable;)Ljava/lang/Throwable;
    //   3064: athrow
    //   3065: iconst_0
    //   3066: istore #20
    //   3068: iload #20
    //   3070: iload #18
    //   3072: if_icmpge -> 3095
    //   3075: aload #9
    //   3077: iload #12
    //   3079: iload #20
    //   3081: iadd
    //   3082: aload #19
    //   3084: iload #20
    //   3086: baload
    //   3087: bastore
    //   3088: iinc #20, 1
    //   3091: iload_2
    //   3092: ifeq -> 3068
    //   3095: bipush #64
    //   3097: newarray int
    //   3099: astore #20
    //   3101: bipush #8
    //   3103: newarray int
    //   3105: astore #21
    //   3107: iconst_0
    //   3108: istore #22
    //   3110: iload #22
    //   3112: bipush #8
    //   3114: if_icmpge -> 3134
    //   3117: aload #21
    //   3119: iload #22
    //   3121: aload #8
    //   3123: iload #22
    //   3125: iaload
    //   3126: iastore
    //   3127: iinc #22, 1
    //   3130: iload_2
    //   3131: ifeq -> 3110
    //   3134: iconst_0
    //   3135: istore #22
    //   3137: iload #22
    //   3139: bipush #64
    //   3141: if_icmpge -> 3632
    //   3144: iload #22
    //   3146: bipush #16
    //   3148: if_icmpge -> 3229
    //   3151: aload #20
    //   3153: iload #22
    //   3155: aload #9
    //   3157: iconst_4
    //   3158: iload #22
    //   3160: imul
    //   3161: baload
    //   3162: sipush #255
    //   3165: iand
    //   3166: bipush #24
    //   3168: ishl
    //   3169: aload #9
    //   3171: iconst_4
    //   3172: iload #22
    //   3174: imul
    //   3175: iconst_1
    //   3176: iadd
    //   3177: baload
    //   3178: sipush #255
    //   3181: iand
    //   3182: bipush #16
    //   3184: ishl
    //   3185: ior
    //   3186: aload #9
    //   3188: iconst_4
    //   3189: iload #22
    //   3191: imul
    //   3192: iconst_2
    //   3193: iadd
    //   3194: baload
    //   3195: sipush #255
    //   3198: iand
    //   3199: bipush #8
    //   3201: ishl
    //   3202: ior
    //   3203: aload #9
    //   3205: iconst_4
    //   3206: iload #22
    //   3208: imul
    //   3209: iconst_3
    //   3210: iadd
    //   3211: baload
    //   3212: sipush #255
    //   3215: iand
    //   3216: ior
    //   3217: iastore
    //   3218: iload_2
    //   3219: ifeq -> 3372
    //   3222: goto -> 3229
    //   3225: invokestatic a : (Ljava/lang/Throwable;)Ljava/lang/Throwable;
    //   3228: athrow
    //   3229: aload #20
    //   3231: iload #22
    //   3233: aload #20
    //   3235: iload #22
    //   3237: iconst_2
    //   3238: isub
    //   3239: iaload
    //   3240: bipush #17
    //   3242: iushr
    //   3243: aload #20
    //   3245: iload #22
    //   3247: iconst_2
    //   3248: isub
    //   3249: iaload
    //   3250: bipush #15
    //   3252: ishl
    //   3253: ior
    //   3254: aload #20
    //   3256: iload #22
    //   3258: iconst_2
    //   3259: isub
    //   3260: iaload
    //   3261: bipush #19
    //   3263: iushr
    //   3264: aload #20
    //   3266: iload #22
    //   3268: iconst_2
    //   3269: isub
    //   3270: iaload
    //   3271: bipush #13
    //   3273: ishl
    //   3274: ior
    //   3275: ixor
    //   3276: aload #20
    //   3278: iload #22
    //   3280: iconst_2
    //   3281: isub
    //   3282: iaload
    //   3283: bipush #10
    //   3285: iushr
    //   3286: ixor
    //   3287: aload #20
    //   3289: iload #22
    //   3291: bipush #7
    //   3293: isub
    //   3294: iaload
    //   3295: iadd
    //   3296: aload #20
    //   3298: iload #22
    //   3300: bipush #15
    //   3302: isub
    //   3303: iaload
    //   3304: bipush #7
    //   3306: iushr
    //   3307: aload #20
    //   3309: iload #22
    //   3311: bipush #15
    //   3313: isub
    //   3314: iaload
    //   3315: bipush #25
    //   3317: ishl
    //   3318: ior
    //   3319: aload #20
    //   3321: iload #22
    //   3323: bipush #15
    //   3325: isub
    //   3326: iaload
    //   3327: bipush #18
    //   3329: iushr
    //   3330: aload #20
    //   3332: iload #22
    //   3334: bipush #15
    //   3336: isub
    //   3337: iaload
    //   3338: bipush #14
    //   3340: ishl
    //   3341: ior
    //   3342: ixor
    //   3343: aload #20
    //   3345: iload #22
    //   3347: bipush #15
    //   3349: isub
    //   3350: iaload
    //   3351: iconst_3
    //   3352: iushr
    //   3353: ixor
    //   3354: iadd
    //   3355: aload #20
    //   3357: iload #22
    //   3359: bipush #16
    //   3361: isub
    //   3362: iaload
    //   3363: iadd
    //   3364: iastore
    //   3365: goto -> 3372
    //   3368: invokestatic a : (Ljava/lang/Throwable;)Ljava/lang/Throwable;
    //   3371: athrow
    //   3372: aload #21
    //   3374: bipush #7
    //   3376: iaload
    //   3377: aload #21
    //   3379: iconst_4
    //   3380: iaload
    //   3381: bipush #6
    //   3383: iushr
    //   3384: aload #21
    //   3386: iconst_4
    //   3387: iaload
    //   3388: bipush #26
    //   3390: ishl
    //   3391: ior
    //   3392: aload #21
    //   3394: iconst_4
    //   3395: iaload
    //   3396: bipush #11
    //   3398: iushr
    //   3399: aload #21
    //   3401: iconst_4
    //   3402: iaload
    //   3403: bipush #21
    //   3405: ishl
    //   3406: ior
    //   3407: ixor
    //   3408: aload #21
    //   3410: iconst_4
    //   3411: iaload
    //   3412: bipush #25
    //   3414: iushr
    //   3415: aload #21
    //   3417: iconst_4
    //   3418: iaload
    //   3419: bipush #7
    //   3421: ishl
    //   3422: ior
    //   3423: ixor
    //   3424: iadd
    //   3425: aload #21
    //   3427: bipush #6
    //   3429: iaload
    //   3430: aload #21
    //   3432: iconst_4
    //   3433: iaload
    //   3434: aload #21
    //   3436: iconst_5
    //   3437: iaload
    //   3438: aload #21
    //   3440: bipush #6
    //   3442: iaload
    //   3443: ixor
    //   3444: iand
    //   3445: ixor
    //   3446: iadd
    //   3447: aload #6
    //   3449: iload #22
    //   3451: iaload
    //   3452: iadd
    //   3453: aload #20
    //   3455: iload #22
    //   3457: iaload
    //   3458: iadd
    //   3459: istore #23
    //   3461: aload #21
    //   3463: iconst_0
    //   3464: iaload
    //   3465: iconst_2
    //   3466: iushr
    //   3467: aload #21
    //   3469: iconst_0
    //   3470: iaload
    //   3471: bipush #30
    //   3473: ishl
    //   3474: ior
    //   3475: aload #21
    //   3477: iconst_0
    //   3478: iaload
    //   3479: bipush #13
    //   3481: iushr
    //   3482: aload #21
    //   3484: iconst_0
    //   3485: iaload
    //   3486: bipush #19
    //   3488: ishl
    //   3489: ior
    //   3490: ixor
    //   3491: aload #21
    //   3493: iconst_0
    //   3494: iaload
    //   3495: bipush #22
    //   3497: iushr
    //   3498: aload #21
    //   3500: iconst_0
    //   3501: iaload
    //   3502: bipush #10
    //   3504: ishl
    //   3505: ior
    //   3506: ixor
    //   3507: aload #21
    //   3509: iconst_0
    //   3510: iaload
    //   3511: aload #21
    //   3513: iconst_1
    //   3514: iaload
    //   3515: iand
    //   3516: aload #21
    //   3518: iconst_2
    //   3519: iaload
    //   3520: aload #21
    //   3522: iconst_0
    //   3523: iaload
    //   3524: aload #21
    //   3526: iconst_1
    //   3527: iaload
    //   3528: ior
    //   3529: iand
    //   3530: ior
    //   3531: iadd
    //   3532: istore #24
    //   3534: aload #21
    //   3536: iconst_3
    //   3537: dup2
    //   3538: iaload
    //   3539: iload #23
    //   3541: iadd
    //   3542: iastore
    //   3543: aload #21
    //   3545: bipush #7
    //   3547: iload #23
    //   3549: iload #24
    //   3551: iadd
    //   3552: iastore
    //   3553: aload #21
    //   3555: bipush #7
    //   3557: iaload
    //   3558: istore #23
    //   3560: aload #21
    //   3562: bipush #7
    //   3564: aload #21
    //   3566: bipush #6
    //   3568: iaload
    //   3569: iastore
    //   3570: aload #21
    //   3572: bipush #6
    //   3574: aload #21
    //   3576: iconst_5
    //   3577: iaload
    //   3578: iastore
    //   3579: aload #21
    //   3581: iconst_5
    //   3582: aload #21
    //   3584: iconst_4
    //   3585: iaload
    //   3586: iastore
    //   3587: aload #21
    //   3589: iconst_4
    //   3590: aload #21
    //   3592: iconst_3
    //   3593: iaload
    //   3594: iastore
    //   3595: aload #21
    //   3597: iconst_3
    //   3598: aload #21
    //   3600: iconst_2
    //   3601: iaload
    //   3602: iastore
    //   3603: aload #21
    //   3605: iconst_2
    //   3606: aload #21
    //   3608: iconst_1
    //   3609: iaload
    //   3610: iastore
    //   3611: aload #21
    //   3613: iconst_1
    //   3614: aload #21
    //   3616: iconst_0
    //   3617: iaload
    //   3618: iastore
    //   3619: aload #21
    //   3621: iconst_0
    //   3622: iload #23
    //   3624: iastore
    //   3625: iinc #22, 1
    //   3628: iload_2
    //   3629: ifeq -> 3137
    //   3632: iconst_0
    //   3633: istore #22
    //   3635: iload #22
    //   3637: bipush #8
    //   3639: if_icmpge -> 3662
    //   3642: aload #8
    //   3644: iload #22
    //   3646: dup2
    //   3647: iaload
    //   3648: aload #21
    //   3650: iload #22
    //   3652: iaload
    //   3653: iadd
    //   3654: iastore
    //   3655: iinc #22, 1
    //   3658: iload_2
    //   3659: ifeq -> 3635
    //   3662: bipush #32
    //   3664: newarray byte
    //   3666: astore #4
    //   3668: sipush #-11054
    //   3671: aload #4
    //   3673: iconst_0
    //   3674: aload #8
    //   3676: iconst_0
    //   3677: iaload
    //   3678: bipush #24
    //   3680: iushr
    //   3681: i2b
    //   3682: bastore
    //   3683: sipush #899
    //   3686: aload #4
    //   3688: iconst_1
    //   3689: aload #8
    //   3691: iconst_0
    //   3692: iaload
    //   3693: bipush #16
    //   3695: iushr
    //   3696: i2b
    //   3697: bastore
    //   3698: aload #4
    //   3700: iconst_2
    //   3701: aload #8
    //   3703: iconst_0
    //   3704: iaload
    //   3705: bipush #8
    //   3707: iushr
    //   3708: i2b
    //   3709: bastore
    //   3710: aload #4
    //   3712: iconst_3
    //   3713: aload #8
    //   3715: iconst_0
    //   3716: iaload
    //   3717: i2b
    //   3718: bastore
    //   3719: aload #4
    //   3721: iconst_4
    //   3722: aload #8
    //   3724: iconst_1
    //   3725: iaload
    //   3726: bipush #24
    //   3728: iushr
    //   3729: i2b
    //   3730: bastore
    //   3731: aload #4
    //   3733: iconst_5
    //   3734: aload #8
    //   3736: iconst_1
    //   3737: iaload
    //   3738: bipush #16
    //   3740: iushr
    //   3741: i2b
    //   3742: bastore
    //   3743: aload #4
    //   3745: bipush #6
    //   3747: aload #8
    //   3749: iconst_1
    //   3750: iaload
    //   3751: bipush #8
    //   3753: iushr
    //   3754: i2b
    //   3755: bastore
    //   3756: aload #4
    //   3758: bipush #7
    //   3760: aload #8
    //   3762: iconst_1
    //   3763: iaload
    //   3764: i2b
    //   3765: bastore
    //   3766: aload #4
    //   3768: bipush #8
    //   3770: aload #8
    //   3772: iconst_2
    //   3773: iaload
    //   3774: bipush #24
    //   3776: iushr
    //   3777: i2b
    //   3778: bastore
    //   3779: aload #4
    //   3781: bipush #9
    //   3783: aload #8
    //   3785: iconst_2
    //   3786: iaload
    //   3787: bipush #16
    //   3789: iushr
    //   3790: i2b
    //   3791: bastore
    //   3792: aload #4
    //   3794: bipush #10
    //   3796: aload #8
    //   3798: iconst_2
    //   3799: iaload
    //   3800: bipush #8
    //   3802: iushr
    //   3803: i2b
    //   3804: bastore
    //   3805: aload #4
    //   3807: bipush #11
    //   3809: aload #8
    //   3811: iconst_2
    //   3812: iaload
    //   3813: i2b
    //   3814: bastore
    //   3815: aload #4
    //   3817: bipush #12
    //   3819: aload #8
    //   3821: iconst_3
    //   3822: iaload
    //   3823: bipush #24
    //   3825: iushr
    //   3826: i2b
    //   3827: bastore
    //   3828: aload #4
    //   3830: bipush #13
    //   3832: aload #8
    //   3834: iconst_3
    //   3835: iaload
    //   3836: bipush #16
    //   3838: iushr
    //   3839: i2b
    //   3840: bastore
    //   3841: aload #4
    //   3843: bipush #14
    //   3845: aload #8
    //   3847: iconst_3
    //   3848: iaload
    //   3849: bipush #8
    //   3851: iushr
    //   3852: i2b
    //   3853: bastore
    //   3854: aload #4
    //   3856: bipush #15
    //   3858: aload #8
    //   3860: iconst_3
    //   3861: iaload
    //   3862: i2b
    //   3863: bastore
    //   3864: aload #4
    //   3866: bipush #16
    //   3868: aload #8
    //   3870: iconst_4
    //   3871: iaload
    //   3872: bipush #24
    //   3874: iushr
    //   3875: i2b
    //   3876: bastore
    //   3877: aload #4
    //   3879: bipush #17
    //   3881: aload #8
    //   3883: iconst_4
    //   3884: iaload
    //   3885: bipush #16
    //   3887: iushr
    //   3888: i2b
    //   3889: bastore
    //   3890: aload #4
    //   3892: bipush #18
    //   3894: aload #8
    //   3896: iconst_4
    //   3897: iaload
    //   3898: bipush #8
    //   3900: iushr
    //   3901: i2b
    //   3902: bastore
    //   3903: aload #4
    //   3905: bipush #19
    //   3907: aload #8
    //   3909: iconst_4
    //   3910: iaload
    //   3911: i2b
    //   3912: bastore
    //   3913: aload #4
    //   3915: bipush #20
    //   3917: aload #8
    //   3919: iconst_5
    //   3920: iaload
    //   3921: bipush #24
    //   3923: iushr
    //   3924: i2b
    //   3925: bastore
    //   3926: aload #4
    //   3928: bipush #21
    //   3930: aload #8
    //   3932: iconst_5
    //   3933: iaload
    //   3934: bipush #16
    //   3936: iushr
    //   3937: i2b
    //   3938: bastore
    //   3939: aload #4
    //   3941: bipush #22
    //   3943: aload #8
    //   3945: iconst_5
    //   3946: iaload
    //   3947: bipush #8
    //   3949: iushr
    //   3950: i2b
    //   3951: bastore
    //   3952: aload #4
    //   3954: bipush #23
    //   3956: aload #8
    //   3958: iconst_5
    //   3959: iaload
    //   3960: i2b
    //   3961: bastore
    //   3962: aload #4
    //   3964: bipush #24
    //   3966: aload #8
    //   3968: bipush #6
    //   3970: iaload
    //   3971: bipush #24
    //   3973: iushr
    //   3974: i2b
    //   3975: bastore
    //   3976: aload #4
    //   3978: bipush #25
    //   3980: aload #8
    //   3982: bipush #6
    //   3984: iaload
    //   3985: bipush #16
    //   3987: iushr
    //   3988: i2b
    //   3989: bastore
    //   3990: aload #4
    //   3992: bipush #26
    //   3994: aload #8
    //   3996: bipush #6
    //   3998: iaload
    //   3999: bipush #8
    //   4001: iushr
    //   4002: i2b
    //   4003: bastore
    //   4004: aload #4
    //   4006: bipush #27
    //   4008: aload #8
    //   4010: bipush #6
    //   4012: iaload
    //   4013: i2b
    //   4014: bastore
    //   4015: aload #4
    //   4017: bipush #28
    //   4019: aload #8
    //   4021: bipush #7
    //   4023: iaload
    //   4024: bipush #24
    //   4026: iushr
    //   4027: i2b
    //   4028: bastore
    //   4029: aload #4
    //   4031: bipush #29
    //   4033: aload #8
    //   4035: bipush #7
    //   4037: iaload
    //   4038: bipush #16
    //   4040: iushr
    //   4041: i2b
    //   4042: bastore
    //   4043: aload #4
    //   4045: bipush #30
    //   4047: aload #8
    //   4049: bipush #7
    //   4051: iaload
    //   4052: bipush #8
    //   4054: iushr
    //   4055: i2b
    //   4056: bastore
    //   4057: aload #4
    //   4059: bipush #31
    //   4061: aload #8
    //   4063: bipush #7
    //   4065: iaload
    //   4066: i2b
    //   4067: bastore
    //   4068: new java/math/BigInteger
    //   4071: dup
    //   4072: aload #4
    //   4074: invokespecial <init> : ([B)V
    //   4077: invokevirtual abs : ()Ljava/math/BigInteger;
    //   4080: putstatic burp/Zeqz.ZG : Ljava/lang/Object;
    //   4083: invokestatic a : (II)Ljava/lang/String;
    //   4086: iconst_1
    //   4087: ldc burp/Zgpx
    //   4089: invokevirtual getClassLoader : ()Ljava/lang/ClassLoader;
    //   4092: invokestatic forName : (Ljava/lang/String;ZLjava/lang/ClassLoader;)Ljava/lang/Class;
    //   4095: invokevirtual getDeclaredFields : ()[Ljava/lang/reflect/Field;
    //   4098: astore_3
    //   4099: aload_3
    //   4100: arraylength
    //   4101: istore #4
    //   4103: iconst_0
    //   4104: istore #5
    //   4106: iload #5
    //   4108: iload #4
    //   4110: if_icmpge -> 4247
    //   4113: aload_3
    //   4114: iload #5
    //   4116: aaload
    //   4117: astore #6
    //   4119: aload #6
    //   4121: invokevirtual getModifiers : ()I
    //   4124: invokestatic isStatic : (I)Z
    //   4127: ifne -> 4137
    //   4130: goto -> 4240
    //   4133: invokestatic a : (Ljava/lang/Throwable;)Ljava/lang/Throwable;
    //   4136: athrow
    //   4137: aload #6
    //   4139: invokevirtual getType : ()Ljava/lang/Class;
    //   4142: astore #7
    //   4144: aload #7
    //   4146: ifnull -> 4227
    //   4149: aload #7
    //   4151: invokevirtual isPrimitive : ()Z
    //   4154: ifne -> 4227
    //   4157: goto -> 4164
    //   4160: invokestatic a : (Ljava/lang/Throwable;)Ljava/lang/Throwable;
    //   4163: athrow
    //   4164: aload #7
    //   4166: invokevirtual getPackage : ()Ljava/lang/Package;
    //   4169: ifnull -> 4227
    //   4172: goto -> 4179
    //   4175: invokestatic a : (Ljava/lang/Throwable;)Ljava/lang/Throwable;
    //   4178: athrow
    //   4179: aload #7
    //   4181: invokevirtual getPackage : ()Ljava/lang/Package;
    //   4184: invokevirtual getName : ()Ljava/lang/String;
    //   4187: ifnull -> 4227
    //   4190: goto -> 4197
    //   4193: invokestatic a : (Ljava/lang/Throwable;)Ljava/lang/Throwable;
    //   4196: athrow
    //   4197: aload #7
    //   4199: invokevirtual getPackage : ()Ljava/lang/Package;
    //   4202: invokevirtual getName : ()Ljava/lang/String;
    //   4205: sipush #-11043
    //   4208: sipush #13465
    //   4211: invokestatic a : (II)Ljava/lang/String;
    //   4214: invokevirtual startsWith : (Ljava/lang/String;)Z
    //   4217: ifne -> 4227
    //   4220: goto -> 4227
    //   4223: invokestatic a : (Ljava/lang/Throwable;)Ljava/lang/Throwable;
    //   4226: athrow
    //   4227: aload #6
    //   4229: iconst_1
    //   4230: invokevirtual setAccessible : (Z)V
    //   4233: aload #6
    //   4235: aconst_null
    //   4236: invokevirtual get : (Ljava/lang/Object;)Ljava/lang/Object;
    //   4239: pop
    //   4240: iinc #5, 1
    //   4243: iload_2
    //   4244: ifeq -> 4106
    //   4247: sipush #-11045
    //   4250: sipush #-17960
    //   4253: invokestatic a : (II)Ljava/lang/String;
    //   4256: invokestatic forName : (Ljava/lang/String;)Ljava/lang/Class;
    //   4259: invokevirtual getDeclaredMethods : ()[Ljava/lang/reflect/Method;
    //   4262: astore_3
    //   4263: aload_3
    //   4264: arraylength
    //   4265: istore #4
    //   4267: iconst_0
    //   4268: istore #5
    //   4270: iload #5
    //   4272: iload #4
    //   4274: if_icmpge -> 4406
    //   4277: aload_3
    //   4278: iload #5
    //   4280: aaload
    //   4281: astore #6
    //   4283: aload #6
    //   4285: invokevirtual getParameterTypes : ()[Ljava/lang/Class;
    //   4288: pop
    //   4289: aload #6
    //   4291: invokevirtual getModifiers : ()I
    //   4294: invokestatic isStatic : (I)Z
    //   4297: ifeq -> 4392
    //   4300: aload #6
    //   4302: invokevirtual getParameterTypes : ()[Ljava/lang/Class;
    //   4305: arraylength
    //   4306: iconst_2
    //   4307: if_icmpne -> 4392
    //   4310: goto -> 4317
    //   4313: invokestatic a : (Ljava/lang/Throwable;)Ljava/lang/Throwable;
    //   4316: athrow
    //   4317: aload #6
    //   4319: invokevirtual getReturnType : ()Ljava/lang/Class;
    //   4322: getstatic java/lang/Void.TYPE : Ljava/lang/Class;
    //   4325: invokevirtual equals : (Ljava/lang/Object;)Z
    //   4328: ifeq -> 4392
    //   4331: goto -> 4338
    //   4334: invokestatic a : (Ljava/lang/Throwable;)Ljava/lang/Throwable;
    //   4337: athrow
    //   4338: aload #6
    //   4340: iconst_1
    //   4341: invokevirtual setAccessible : (Z)V
    //   4344: aload #6
    //   4346: aconst_null
    //   4347: iconst_2
    //   4348: anewarray java/lang/Object
    //   4351: dup
    //   4352: iconst_0
    //   4353: aload_0
    //   4354: aastore
    //   4355: dup
    //   4356: iconst_1
    //   4357: aload_1
    //   4358: ifnonnull -> 4376
    //   4361: goto -> 4368
    //   4364: invokestatic a : (Ljava/lang/Throwable;)Ljava/lang/Throwable;
    //   4367: athrow
    //   4368: aload_1
    //   4369: goto -> 4383
    //   4372: invokestatic a : (Ljava/lang/Throwable;)Ljava/lang/Throwable;
    //   4375: athrow
    //   4376: aload_1
    //   4377: checkcast [B
    //   4380: invokevirtual clone : ()Ljava/lang/Object;
    //   4383: aastore
    //   4384: invokevirtual invoke : (Ljava/lang/Object;[Ljava/lang/Object;)Ljava/lang/Object;
    //   4387: pop
    //   4388: iload_2
    //   4389: ifeq -> 4406
    //   4392: iinc #5, 1
    //   4395: iload_2
    //   4396: ifeq -> 4270
    //   4399: goto -> 4406
    //   4402: invokestatic a : (Ljava/lang/Throwable;)Ljava/lang/Throwable;
    //   4405: athrow
    //   4406: getstatic burp/Zlg2.ZO : Ljava/lang/Object;
    //   4409: checkcast java/math/BigInteger
    //   4412: invokevirtual toByteArray : ()[B
    //   4415: astore_3
    //   4416: bipush #32
    //   4418: newarray int
    //   4420: dup
    //   4421: iconst_0
    //   4422: ldc 876216579
    //   4424: iastore
    //   4425: dup
    //   4426: iconst_1
    //   4427: ldc 455999525
    //   4429: iastore
    //   4430: dup
    //   4431: iconst_2
    //   4432: ldc 1043334948
    //   4434: iastore
    //   4435: dup
    //   4436: iconst_3
    //   4437: ldc 439222784
    //   4439: iastore
    //   4440: dup
    //   4441: iconst_4
    //   4442: ldc 372376604
    //   4444: iastore
    //   4445: dup
    //   4446: iconst_5
    //   4447: ldc 707731490
    //   4449: iastore
    //   4450: dup
    //   4451: bipush #6
    //   4453: ldc 389426184
    //   4455: iastore
    //   4456: dup
    //   4457: bipush #7
    //   4459: ldc 973875457
    //   4461: iastore
    //   4462: dup
    //   4463: bipush #8
    //   4465: ldc 389160971
    //   4467: iastore
    //   4468: dup
    //   4469: bipush #9
    //   4471: ldc 907870729
    //   4473: iastore
    //   4474: dup
    //   4475: bipush #10
    //   4477: ldc 121057538
    //   4479: iastore
    //   4480: dup
    //   4481: bipush #11
    //   4483: ldc 840500228
    //   4485: iastore
    //   4486: dup
    //   4487: bipush #12
    //   4489: ldc 254150144
    //   4491: iastore
    //   4492: dup
    //   4493: bipush #13
    //   4495: ldc 924386310
    //   4497: iastore
    //   4498: dup
    //   4499: bipush #14
    //   4501: ldc 187632156
    //   4503: iastore
    //   4504: dup
    //   4505: bipush #15
    //   4507: ldc 874189824
    //   4509: iastore
    //   4510: dup
    //   4511: bipush #16
    //   4513: ldc 655302664
    //   4515: iastore
    //   4516: dup
    //   4517: bipush #17
    //   4519: ldc 890966315
    //   4521: iastore
    //   4522: dup
    //   4523: bipush #18
    //   4525: ldc 722417666
    //   4527: iastore
    //   4528: dup
    //   4529: bipush #19
    //   4531: ldc 1026621720
    //   4533: iastore
    //   4534: dup
    //   4535: bipush #20
    //   4537: ldc 957157408
    //   4539: iastore
    //   4540: dup
    //   4541: bipush #21
    //   4543: ldc 892536332
    //   4545: iastore
    //   4546: dup
    //   4547: bipush #22
    //   4549: ldc 689771012
    //   4551: iastore
    //   4552: dup
    //   4553: bipush #23
    //   4555: ldc 221709344
    //   4557: iastore
    //   4558: dup
    //   4559: bipush #24
    //   4561: ldc 940377620
    //   4563: iastore
    //   4564: dup
    //   4565: bipush #25
    //   4567: ldc 255209728
    //   4569: iastore
    //   4570: dup
    //   4571: bipush #26
    //   4573: ldc 1010368540
    //   4575: iastore
    //   4576: dup
    //   4577: bipush #27
    //   4579: ldc 220604441
    //   4581: iastore
    //   4582: dup
    //   4583: bipush #28
    //   4585: ldc 1008414755
    //   4587: iastore
    //   4588: dup
    //   4589: bipush #29
    //   4591: ldc 187049985
    //   4593: iastore
    //   4594: dup
    //   4595: bipush #30
    //   4597: ldc 943331329
    //   4599: iastore
    //   4600: dup
    //   4601: bipush #31
    //   4603: ldc 170788368
    //   4605: iastore
    //   4606: astore #5
    //   4608: bipush #64
    //   4610: newarray int
    //   4612: dup
    //   4613: iconst_0
    //   4614: ldc 16843776
    //   4616: iastore
    //   4617: dup
    //   4618: iconst_1
    //   4619: iconst_0
    //   4620: iastore
    //   4621: dup
    //   4622: iconst_2
    //   4623: ldc 65536
    //   4625: iastore
    //   4626: dup
    //   4627: iconst_3
    //   4628: ldc 16843780
    //   4630: iastore
    //   4631: dup
    //   4632: iconst_4
    //   4633: ldc 16842756
    //   4635: iastore
    //   4636: dup
    //   4637: iconst_5
    //   4638: ldc 66564
    //   4640: iastore
    //   4641: dup
    //   4642: bipush #6
    //   4644: iconst_4
    //   4645: iastore
    //   4646: dup
    //   4647: bipush #7
    //   4649: ldc 65536
    //   4651: iastore
    //   4652: dup
    //   4653: bipush #8
    //   4655: sipush #1024
    //   4658: iastore
    //   4659: dup
    //   4660: bipush #9
    //   4662: ldc 16843776
    //   4664: iastore
    //   4665: dup
    //   4666: bipush #10
    //   4668: ldc 16843780
    //   4670: iastore
    //   4671: dup
    //   4672: bipush #11
    //   4674: sipush #1024
    //   4677: iastore
    //   4678: dup
    //   4679: bipush #12
    //   4681: ldc 16778244
    //   4683: iastore
    //   4684: dup
    //   4685: bipush #13
    //   4687: ldc 16842756
    //   4689: iastore
    //   4690: dup
    //   4691: bipush #14
    //   4693: ldc 16777216
    //   4695: iastore
    //   4696: dup
    //   4697: bipush #15
    //   4699: iconst_4
    //   4700: iastore
    //   4701: dup
    //   4702: bipush #16
    //   4704: sipush #1028
    //   4707: iastore
    //   4708: dup
    //   4709: bipush #17
    //   4711: ldc 16778240
    //   4713: iastore
    //   4714: dup
    //   4715: bipush #18
    //   4717: ldc 16778240
    //   4719: iastore
    //   4720: dup
    //   4721: bipush #19
    //   4723: ldc 66560
    //   4725: iastore
    //   4726: dup
    //   4727: bipush #20
    //   4729: ldc 66560
    //   4731: iastore
    //   4732: dup
    //   4733: bipush #21
    //   4735: ldc 16842752
    //   4737: iastore
    //   4738: dup
    //   4739: bipush #22
    //   4741: ldc 16842752
    //   4743: iastore
    //   4744: dup
    //   4745: bipush #23
    //   4747: ldc 16778244
    //   4749: iastore
    //   4750: dup
    //   4751: bipush #24
    //   4753: ldc 65540
    //   4755: iastore
    //   4756: dup
    //   4757: bipush #25
    //   4759: ldc 16777220
    //   4761: iastore
    //   4762: dup
    //   4763: bipush #26
    //   4765: ldc 16777220
    //   4767: iastore
    //   4768: dup
    //   4769: bipush #27
    //   4771: ldc 65540
    //   4773: iastore
    //   4774: dup
    //   4775: bipush #28
    //   4777: iconst_0
    //   4778: iastore
    //   4779: dup
    //   4780: bipush #29
    //   4782: sipush #1028
    //   4785: iastore
    //   4786: dup
    //   4787: bipush #30
    //   4789: ldc 66564
    //   4791: iastore
    //   4792: dup
    //   4793: bipush #31
    //   4795: ldc 16777216
    //   4797: iastore
    //   4798: dup
    //   4799: bipush #32
    //   4801: ldc 65536
    //   4803: iastore
    //   4804: dup
    //   4805: bipush #33
    //   4807: ldc 16843780
    //   4809: iastore
    //   4810: dup
    //   4811: bipush #34
    //   4813: iconst_4
    //   4814: iastore
    //   4815: dup
    //   4816: bipush #35
    //   4818: ldc 16842752
    //   4820: iastore
    //   4821: dup
    //   4822: bipush #36
    //   4824: ldc 16843776
    //   4826: iastore
    //   4827: dup
    //   4828: bipush #37
    //   4830: ldc 16777216
    //   4832: iastore
    //   4833: dup
    //   4834: bipush #38
    //   4836: ldc 16777216
    //   4838: iastore
    //   4839: dup
    //   4840: bipush #39
    //   4842: sipush #1024
    //   4845: iastore
    //   4846: dup
    //   4847: bipush #40
    //   4849: ldc 16842756
    //   4851: iastore
    //   4852: dup
    //   4853: bipush #41
    //   4855: ldc 65536
    //   4857: iastore
    //   4858: dup
    //   4859: bipush #42
    //   4861: ldc 66560
    //   4863: iastore
    //   4864: dup
    //   4865: bipush #43
    //   4867: ldc 16777220
    //   4869: iastore
    //   4870: dup
    //   4871: bipush #44
    //   4873: sipush #1024
    //   4876: iastore
    //   4877: dup
    //   4878: bipush #45
    //   4880: iconst_4
    //   4881: iastore
    //   4882: dup
    //   4883: bipush #46
    //   4885: ldc 16778244
    //   4887: iastore
    //   4888: dup
    //   4889: bipush #47
    //   4891: ldc 66564
    //   4893: iastore
    //   4894: dup
    //   4895: bipush #48
    //   4897: ldc 16843780
    //   4899: iastore
    //   4900: dup
    //   4901: bipush #49
    //   4903: ldc 65540
    //   4905: iastore
    //   4906: dup
    //   4907: bipush #50
    //   4909: ldc 16842752
    //   4911: iastore
    //   4912: dup
    //   4913: bipush #51
    //   4915: ldc 16778244
    //   4917: iastore
    //   4918: dup
    //   4919: bipush #52
    //   4921: ldc 16777220
    //   4923: iastore
    //   4924: dup
    //   4925: bipush #53
    //   4927: sipush #1028
    //   4930: iastore
    //   4931: dup
    //   4932: bipush #54
    //   4934: ldc 66564
    //   4936: iastore
    //   4937: dup
    //   4938: bipush #55
    //   4940: ldc 16843776
    //   4942: iastore
    //   4943: dup
    //   4944: bipush #56
    //   4946: sipush #1028
    //   4949: iastore
    //   4950: dup
    //   4951: bipush #57
    //   4953: ldc 16778240
    //   4955: iastore
    //   4956: dup
    //   4957: bipush #58
    //   4959: ldc 16778240
    //   4961: iastore
    //   4962: dup
    //   4963: bipush #59
    //   4965: iconst_0
    //   4966: iastore
    //   4967: dup
    //   4968: bipush #60
    //   4970: ldc 65540
    //   4972: iastore
    //   4973: dup
    //   4974: bipush #61
    //   4976: ldc 66560
    //   4978: iastore
    //   4979: dup
    //   4980: bipush #62
    //   4982: iconst_0
    //   4983: iastore
    //   4984: dup
    //   4985: bipush #63
    //   4987: ldc 16842756
    //   4989: iastore
    //   4990: astore #6
    //   4992: bipush #64
    //   4994: newarray int
    //   4996: dup
    //   4997: iconst_0
    //   4998: ldc -2146402272
    //   5000: iastore
    //   5001: dup
    //   5002: iconst_1
    //   5003: ldc -2147450880
    //   5005: iastore
    //   5006: dup
    //   5007: iconst_2
    //   5008: ldc 32768
    //   5010: iastore
    //   5011: dup
    //   5012: iconst_3
    //   5013: ldc 1081376
    //   5015: iastore
    //   5016: dup
    //   5017: iconst_4
    //   5018: ldc 1048576
    //   5020: iastore
    //   5021: dup
    //   5022: iconst_5
    //   5023: bipush #32
    //   5025: iastore
    //   5026: dup
    //   5027: bipush #6
    //   5029: ldc -2146435040
    //   5031: iastore
    //   5032: dup
    //   5033: bipush #7
    //   5035: ldc -2147450848
    //   5037: iastore
    //   5038: dup
    //   5039: bipush #8
    //   5041: ldc -2147483616
    //   5043: iastore
    //   5044: dup
    //   5045: bipush #9
    //   5047: ldc -2146402272
    //   5049: iastore
    //   5050: dup
    //   5051: bipush #10
    //   5053: ldc -2146402304
    //   5055: iastore
    //   5056: dup
    //   5057: bipush #11
    //   5059: ldc -2147483648
    //   5061: iastore
    //   5062: dup
    //   5063: bipush #12
    //   5065: ldc -2147450880
    //   5067: iastore
    //   5068: dup
    //   5069: bipush #13
    //   5071: ldc 1048576
    //   5073: iastore
    //   5074: dup
    //   5075: bipush #14
    //   5077: bipush #32
    //   5079: iastore
    //   5080: dup
    //   5081: bipush #15
    //   5083: ldc -2146435040
    //   5085: iastore
    //   5086: dup
    //   5087: bipush #16
    //   5089: ldc 1081344
    //   5091: iastore
    //   5092: dup
    //   5093: bipush #17
    //   5095: ldc 1048608
    //   5097: iastore
    //   5098: dup
    //   5099: bipush #18
    //   5101: ldc -2147450848
    //   5103: iastore
    //   5104: dup
    //   5105: bipush #19
    //   5107: iconst_0
    //   5108: iastore
    //   5109: dup
    //   5110: bipush #20
    //   5112: ldc -2147483648
    //   5114: iastore
    //   5115: dup
    //   5116: bipush #21
    //   5118: ldc 32768
    //   5120: iastore
    //   5121: dup
    //   5122: bipush #22
    //   5124: ldc 1081376
    //   5126: iastore
    //   5127: dup
    //   5128: bipush #23
    //   5130: ldc -2146435072
    //   5132: iastore
    //   5133: dup
    //   5134: bipush #24
    //   5136: ldc 1048608
    //   5138: iastore
    //   5139: dup
    //   5140: bipush #25
    //   5142: ldc -2147483616
    //   5144: iastore
    //   5145: dup
    //   5146: bipush #26
    //   5148: iconst_0
    //   5149: iastore
    //   5150: dup
    //   5151: bipush #27
    //   5153: ldc 1081344
    //   5155: iastore
    //   5156: dup
    //   5157: bipush #28
    //   5159: ldc 32800
    //   5161: iastore
    //   5162: dup
    //   5163: bipush #29
    //   5165: ldc -2146402304
    //   5167: iastore
    //   5168: dup
    //   5169: bipush #30
    //   5171: ldc -2146435072
    //   5173: iastore
    //   5174: dup
    //   5175: bipush #31
    //   5177: ldc 32800
    //   5179: iastore
    //   5180: dup
    //   5181: bipush #32
    //   5183: iconst_0
    //   5184: iastore
    //   5185: dup
    //   5186: bipush #33
    //   5188: ldc 1081376
    //   5190: iastore
    //   5191: dup
    //   5192: bipush #34
    //   5194: ldc -2146435040
    //   5196: iastore
    //   5197: dup
    //   5198: bipush #35
    //   5200: ldc 1048576
    //   5202: iastore
    //   5203: dup
    //   5204: bipush #36
    //   5206: ldc -2147450848
    //   5208: iastore
    //   5209: dup
    //   5210: bipush #37
    //   5212: ldc -2146435072
    //   5214: iastore
    //   5215: dup
    //   5216: bipush #38
    //   5218: ldc -2146402304
    //   5220: iastore
    //   5221: dup
    //   5222: bipush #39
    //   5224: ldc 32768
    //   5226: iastore
    //   5227: dup
    //   5228: bipush #40
    //   5230: ldc -2146435072
    //   5232: iastore
    //   5233: dup
    //   5234: bipush #41
    //   5236: ldc -2147450880
    //   5238: iastore
    //   5239: dup
    //   5240: bipush #42
    //   5242: bipush #32
    //   5244: iastore
    //   5245: dup
    //   5246: bipush #43
    //   5248: ldc -2146402272
    //   5250: iastore
    //   5251: dup
    //   5252: bipush #44
    //   5254: ldc 1081376
    //   5256: iastore
    //   5257: dup
    //   5258: bipush #45
    //   5260: bipush #32
    //   5262: iastore
    //   5263: dup
    //   5264: bipush #46
    //   5266: ldc 32768
    //   5268: iastore
    //   5269: dup
    //   5270: bipush #47
    //   5272: ldc -2147483648
    //   5274: iastore
    //   5275: dup
    //   5276: bipush #48
    //   5278: ldc 32800
    //   5280: iastore
    //   5281: dup
    //   5282: bipush #49
    //   5284: ldc -2146402304
    //   5286: iastore
    //   5287: dup
    //   5288: bipush #50
    //   5290: ldc 1048576
    //   5292: iastore
    //   5293: dup
    //   5294: bipush #51
    //   5296: ldc -2147483616
    //   5298: iastore
    //   5299: dup
    //   5300: bipush #52
    //   5302: ldc 1048608
    //   5304: iastore
    //   5305: dup
    //   5306: bipush #53
    //   5308: ldc -2147450848
    //   5310: iastore
    //   5311: dup
    //   5312: bipush #54
    //   5314: ldc -2147483616
    //   5316: iastore
    //   5317: dup
    //   5318: bipush #55
    //   5320: ldc 1048608
    //   5322: iastore
    //   5323: dup
    //   5324: bipush #56
    //   5326: ldc 1081344
    //   5328: iastore
    //   5329: dup
    //   5330: bipush #57
    //   5332: iconst_0
    //   5333: iastore
    //   5334: dup
    //   5335: bipush #58
    //   5337: ldc -2147450880
    //   5339: iastore
    //   5340: dup
    //   5341: bipush #59
    //   5343: ldc 32800
    //   5345: iastore
    //   5346: dup
    //   5347: bipush #60
    //   5349: ldc -2147483648
    //   5351: iastore
    //   5352: dup
    //   5353: bipush #61
    //   5355: ldc -2146435040
    //   5357: iastore
    //   5358: dup
    //   5359: bipush #62
    //   5361: ldc -2146402272
    //   5363: iastore
    //   5364: dup
    //   5365: bipush #63
    //   5367: ldc 1081344
    //   5369: iastore
    //   5370: astore #7
    //   5372: bipush #64
    //   5374: newarray int
    //   5376: dup
    //   5377: iconst_0
    //   5378: sipush #520
    //   5381: iastore
    //   5382: dup
    //   5383: iconst_1
    //   5384: ldc 134349312
    //   5386: iastore
    //   5387: dup
    //   5388: iconst_2
    //   5389: iconst_0
    //   5390: iastore
    //   5391: dup
    //   5392: iconst_3
    //   5393: ldc 134348808
    //   5395: iastore
    //   5396: dup
    //   5397: iconst_4
    //   5398: ldc 134218240
    //   5400: iastore
    //   5401: dup
    //   5402: iconst_5
    //   5403: iconst_0
    //   5404: iastore
    //   5405: dup
    //   5406: bipush #6
    //   5408: ldc 131592
    //   5410: iastore
    //   5411: dup
    //   5412: bipush #7
    //   5414: ldc 134218240
    //   5416: iastore
    //   5417: dup
    //   5418: bipush #8
    //   5420: ldc 131080
    //   5422: iastore
    //   5423: dup
    //   5424: bipush #9
    //   5426: ldc 134217736
    //   5428: iastore
    //   5429: dup
    //   5430: bipush #10
    //   5432: ldc 134217736
    //   5434: iastore
    //   5435: dup
    //   5436: bipush #11
    //   5438: ldc 131072
    //   5440: iastore
    //   5441: dup
    //   5442: bipush #12
    //   5444: ldc 134349320
    //   5446: iastore
    //   5447: dup
    //   5448: bipush #13
    //   5450: ldc 131080
    //   5452: iastore
    //   5453: dup
    //   5454: bipush #14
    //   5456: ldc 134348800
    //   5458: iastore
    //   5459: dup
    //   5460: bipush #15
    //   5462: sipush #520
    //   5465: iastore
    //   5466: dup
    //   5467: bipush #16
    //   5469: ldc 134217728
    //   5471: iastore
    //   5472: dup
    //   5473: bipush #17
    //   5475: bipush #8
    //   5477: iastore
    //   5478: dup
    //   5479: bipush #18
    //   5481: ldc 134349312
    //   5483: iastore
    //   5484: dup
    //   5485: bipush #19
    //   5487: sipush #512
    //   5490: iastore
    //   5491: dup
    //   5492: bipush #20
    //   5494: ldc 131584
    //   5496: iastore
    //   5497: dup
    //   5498: bipush #21
    //   5500: ldc 134348800
    //   5502: iastore
    //   5503: dup
    //   5504: bipush #22
    //   5506: ldc 134348808
    //   5508: iastore
    //   5509: dup
    //   5510: bipush #23
    //   5512: ldc 131592
    //   5514: iastore
    //   5515: dup
    //   5516: bipush #24
    //   5518: ldc 134218248
    //   5520: iastore
    //   5521: dup
    //   5522: bipush #25
    //   5524: ldc 131584
    //   5526: iastore
    //   5527: dup
    //   5528: bipush #26
    //   5530: ldc 131072
    //   5532: iastore
    //   5533: dup
    //   5534: bipush #27
    //   5536: ldc 134218248
    //   5538: iastore
    //   5539: dup
    //   5540: bipush #28
    //   5542: bipush #8
    //   5544: iastore
    //   5545: dup
    //   5546: bipush #29
    //   5548: ldc 134349320
    //   5550: iastore
    //   5551: dup
    //   5552: bipush #30
    //   5554: sipush #512
    //   5557: iastore
    //   5558: dup
    //   5559: bipush #31
    //   5561: ldc 134217728
    //   5563: iastore
    //   5564: dup
    //   5565: bipush #32
    //   5567: ldc 134349312
    //   5569: iastore
    //   5570: dup
    //   5571: bipush #33
    //   5573: ldc 134217728
    //   5575: iastore
    //   5576: dup
    //   5577: bipush #34
    //   5579: ldc 131080
    //   5581: iastore
    //   5582: dup
    //   5583: bipush #35
    //   5585: sipush #520
    //   5588: iastore
    //   5589: dup
    //   5590: bipush #36
    //   5592: ldc 131072
    //   5594: iastore
    //   5595: dup
    //   5596: bipush #37
    //   5598: ldc 134349312
    //   5600: iastore
    //   5601: dup
    //   5602: bipush #38
    //   5604: ldc 134218240
    //   5606: iastore
    //   5607: dup
    //   5608: bipush #39
    //   5610: iconst_0
    //   5611: iastore
    //   5612: dup
    //   5613: bipush #40
    //   5615: sipush #512
    //   5618: iastore
    //   5619: dup
    //   5620: bipush #41
    //   5622: ldc 131080
    //   5624: iastore
    //   5625: dup
    //   5626: bipush #42
    //   5628: ldc 134349320
    //   5630: iastore
    //   5631: dup
    //   5632: bipush #43
    //   5634: ldc 134218240
    //   5636: iastore
    //   5637: dup
    //   5638: bipush #44
    //   5640: ldc 134217736
    //   5642: iastore
    //   5643: dup
    //   5644: bipush #45
    //   5646: sipush #512
    //   5649: iastore
    //   5650: dup
    //   5651: bipush #46
    //   5653: iconst_0
    //   5654: iastore
    //   5655: dup
    //   5656: bipush #47
    //   5658: ldc 134348808
    //   5660: iastore
    //   5661: dup
    //   5662: bipush #48
    //   5664: ldc 134218248
    //   5666: iastore
    //   5667: dup
    //   5668: bipush #49
    //   5670: ldc 131072
    //   5672: iastore
    //   5673: dup
    //   5674: bipush #50
    //   5676: ldc 134217728
    //   5678: iastore
    //   5679: dup
    //   5680: bipush #51
    //   5682: ldc 134349320
    //   5684: iastore
    //   5685: dup
    //   5686: bipush #52
    //   5688: bipush #8
    //   5690: iastore
    //   5691: dup
    //   5692: bipush #53
    //   5694: ldc 131592
    //   5696: iastore
    //   5697: dup
    //   5698: bipush #54
    //   5700: ldc 131584
    //   5702: iastore
    //   5703: dup
    //   5704: bipush #55
    //   5706: ldc 134217736
    //   5708: iastore
    //   5709: dup
    //   5710: bipush #56
    //   5712: ldc 134348800
    //   5714: iastore
    //   5715: dup
    //   5716: bipush #57
    //   5718: ldc 134218248
    //   5720: iastore
    //   5721: dup
    //   5722: bipush #58
    //   5724: sipush #520
    //   5727: iastore
    //   5728: dup
    //   5729: bipush #59
    //   5731: ldc 134348800
    //   5733: iastore
    //   5734: dup
    //   5735: bipush #60
    //   5737: ldc 131592
    //   5739: iastore
    //   5740: dup
    //   5741: bipush #61
    //   5743: bipush #8
    //   5745: iastore
    //   5746: dup
    //   5747: bipush #62
    //   5749: ldc 134348808
    //   5751: iastore
    //   5752: dup
    //   5753: bipush #63
    //   5755: ldc 131584
    //   5757: iastore
    //   5758: astore #8
    //   5760: bipush #64
    //   5762: newarray int
    //   5764: dup
    //   5765: iconst_0
    //   5766: ldc 8396801
    //   5768: iastore
    //   5769: dup
    //   5770: iconst_1
    //   5771: sipush #8321
    //   5774: iastore
    //   5775: dup
    //   5776: iconst_2
    //   5777: sipush #8321
    //   5780: iastore
    //   5781: dup
    //   5782: iconst_3
    //   5783: sipush #128
    //   5786: iastore
    //   5787: dup
    //   5788: iconst_4
    //   5789: ldc 8396928
    //   5791: iastore
    //   5792: dup
    //   5793: iconst_5
    //   5794: ldc 8388737
    //   5796: iastore
    //   5797: dup
    //   5798: bipush #6
    //   5800: ldc 8388609
    //   5802: iastore
    //   5803: dup
    //   5804: bipush #7
    //   5806: sipush #8193
    //   5809: iastore
    //   5810: dup
    //   5811: bipush #8
    //   5813: iconst_0
    //   5814: iastore
    //   5815: dup
    //   5816: bipush #9
    //   5818: ldc 8396800
    //   5820: iastore
    //   5821: dup
    //   5822: bipush #10
    //   5824: ldc 8396800
    //   5826: iastore
    //   5827: dup
    //   5828: bipush #11
    //   5830: ldc 8396929
    //   5832: iastore
    //   5833: dup
    //   5834: bipush #12
    //   5836: sipush #129
    //   5839: iastore
    //   5840: dup
    //   5841: bipush #13
    //   5843: iconst_0
    //   5844: iastore
    //   5845: dup
    //   5846: bipush #14
    //   5848: ldc 8388736
    //   5850: iastore
    //   5851: dup
    //   5852: bipush #15
    //   5854: ldc 8388609
    //   5856: iastore
    //   5857: dup
    //   5858: bipush #16
    //   5860: iconst_1
    //   5861: iastore
    //   5862: dup
    //   5863: bipush #17
    //   5865: sipush #8192
    //   5868: iastore
    //   5869: dup
    //   5870: bipush #18
    //   5872: ldc 8388608
    //   5874: iastore
    //   5875: dup
    //   5876: bipush #19
    //   5878: ldc 8396801
    //   5880: iastore
    //   5881: dup
    //   5882: bipush #20
    //   5884: sipush #128
    //   5887: iastore
    //   5888: dup
    //   5889: bipush #21
    //   5891: ldc 8388608
    //   5893: iastore
    //   5894: dup
    //   5895: bipush #22
    //   5897: sipush #8193
    //   5900: iastore
    //   5901: dup
    //   5902: bipush #23
    //   5904: sipush #8320
    //   5907: iastore
    //   5908: dup
    //   5909: bipush #24
    //   5911: ldc 8388737
    //   5913: iastore
    //   5914: dup
    //   5915: bipush #25
    //   5917: iconst_1
    //   5918: iastore
    //   5919: dup
    //   5920: bipush #26
    //   5922: sipush #8320
    //   5925: iastore
    //   5926: dup
    //   5927: bipush #27
    //   5929: ldc 8388736
    //   5931: iastore
    //   5932: dup
    //   5933: bipush #28
    //   5935: sipush #8192
    //   5938: iastore
    //   5939: dup
    //   5940: bipush #29
    //   5942: ldc 8396928
    //   5944: iastore
    //   5945: dup
    //   5946: bipush #30
    //   5948: ldc 8396929
    //   5950: iastore
    //   5951: dup
    //   5952: bipush #31
    //   5954: sipush #129
    //   5957: iastore
    //   5958: dup
    //   5959: bipush #32
    //   5961: ldc 8388736
    //   5963: iastore
    //   5964: dup
    //   5965: bipush #33
    //   5967: ldc 8388609
    //   5969: iastore
    //   5970: dup
    //   5971: bipush #34
    //   5973: ldc 8396800
    //   5975: iastore
    //   5976: dup
    //   5977: bipush #35
    //   5979: ldc 8396929
    //   5981: iastore
    //   5982: dup
    //   5983: bipush #36
    //   5985: sipush #129
    //   5988: iastore
    //   5989: dup
    //   5990: bipush #37
    //   5992: iconst_0
    //   5993: iastore
    //   5994: dup
    //   5995: bipush #38
    //   5997: iconst_0
    //   5998: iastore
    //   5999: dup
    //   6000: bipush #39
    //   6002: ldc 8396800
    //   6004: iastore
    //   6005: dup
    //   6006: bipush #40
    //   6008: sipush #8320
    //   6011: iastore
    //   6012: dup
    //   6013: bipush #41
    //   6015: ldc 8388736
    //   6017: iastore
    //   6018: dup
    //   6019: bipush #42
    //   6021: ldc 8388737
    //   6023: iastore
    //   6024: dup
    //   6025: bipush #43
    //   6027: iconst_1
    //   6028: iastore
    //   6029: dup
    //   6030: bipush #44
    //   6032: ldc 8396801
    //   6034: iastore
    //   6035: dup
    //   6036: bipush #45
    //   6038: sipush #8321
    //   6041: iastore
    //   6042: dup
    //   6043: bipush #46
    //   6045: sipush #8321
    //   6048: iastore
    //   6049: dup
    //   6050: bipush #47
    //   6052: sipush #128
    //   6055: iastore
    //   6056: dup
    //   6057: bipush #48
    //   6059: ldc 8396929
    //   6061: iastore
    //   6062: dup
    //   6063: bipush #49
    //   6065: sipush #129
    //   6068: iastore
    //   6069: dup
    //   6070: bipush #50
    //   6072: iconst_1
    //   6073: iastore
    //   6074: dup
    //   6075: bipush #51
    //   6077: sipush #8192
    //   6080: iastore
    //   6081: dup
    //   6082: bipush #52
    //   6084: ldc 8388609
    //   6086: iastore
    //   6087: dup
    //   6088: bipush #53
    //   6090: sipush #8193
    //   6093: iastore
    //   6094: dup
    //   6095: bipush #54
    //   6097: ldc 8396928
    //   6099: iastore
    //   6100: dup
    //   6101: bipush #55
    //   6103: ldc 8388737
    //   6105: iastore
    //   6106: dup
    //   6107: bipush #56
    //   6109: sipush #8193
    //   6112: iastore
    //   6113: dup
    //   6114: bipush #57
    //   6116: sipush #8320
    //   6119: iastore
    //   6120: dup
    //   6121: bipush #58
    //   6123: ldc 8388608
    //   6125: iastore
    //   6126: dup
    //   6127: bipush #59
    //   6129: ldc 8396801
    //   6131: iastore
    //   6132: dup
    //   6133: bipush #60
    //   6135: sipush #128
    //   6138: iastore
    //   6139: dup
    //   6140: bipush #61
    //   6142: ldc 8388608
    //   6144: iastore
    //   6145: dup
    //   6146: bipush #62
    //   6148: sipush #8192
    //   6151: iastore
    //   6152: dup
    //   6153: bipush #63
    //   6155: ldc 8396928
    //   6157: iastore
    //   6158: astore #9
    //   6160: bipush #64
    //   6162: newarray int
    //   6164: dup
    //   6165: iconst_0
    //   6166: sipush #256
    //   6169: iastore
    //   6170: dup
    //   6171: iconst_1
    //   6172: ldc 34078976
    //   6174: iastore
    //   6175: dup
    //   6176: iconst_2
    //   6177: ldc 34078720
    //   6179: iastore
    //   6180: dup
    //   6181: iconst_3
    //   6182: ldc 1107296512
    //   6184: iastore
    //   6185: dup
    //   6186: iconst_4
    //   6187: ldc 524288
    //   6189: iastore
    //   6190: dup
    //   6191: iconst_5
    //   6192: sipush #256
    //   6195: iastore
    //   6196: dup
    //   6197: bipush #6
    //   6199: ldc 1073741824
    //   6201: iastore
    //   6202: dup
    //   6203: bipush #7
    //   6205: ldc 34078720
    //   6207: iastore
    //   6208: dup
    //   6209: bipush #8
    //   6211: ldc 1074266368
    //   6213: iastore
    //   6214: dup
    //   6215: bipush #9
    //   6217: ldc 524288
    //   6219: iastore
    //   6220: dup
    //   6221: bipush #10
    //   6223: ldc 33554688
    //   6225: iastore
    //   6226: dup
    //   6227: bipush #11
    //   6229: ldc 1074266368
    //   6231: iastore
    //   6232: dup
    //   6233: bipush #12
    //   6235: ldc 1107296512
    //   6237: iastore
    //   6238: dup
    //   6239: bipush #13
    //   6241: ldc 1107820544
    //   6243: iastore
    //   6244: dup
    //   6245: bipush #14
    //   6247: ldc 524544
    //   6249: iastore
    //   6250: dup
    //   6251: bipush #15
    //   6253: ldc 1073741824
    //   6255: iastore
    //   6256: dup
    //   6257: bipush #16
    //   6259: ldc 33554432
    //   6261: iastore
    //   6262: dup
    //   6263: bipush #17
    //   6265: ldc 1074266112
    //   6267: iastore
    //   6268: dup
    //   6269: bipush #18
    //   6271: ldc 1074266112
    //   6273: iastore
    //   6274: dup
    //   6275: bipush #19
    //   6277: iconst_0
    //   6278: iastore
    //   6279: dup
    //   6280: bipush #20
    //   6282: ldc 1073742080
    //   6284: iastore
    //   6285: dup
    //   6286: bipush #21
    //   6288: ldc 1107820800
    //   6290: iastore
    //   6291: dup
    //   6292: bipush #22
    //   6294: ldc 1107820800
    //   6296: iastore
    //   6297: dup
    //   6298: bipush #23
    //   6300: ldc 33554688
    //   6302: iastore
    //   6303: dup
    //   6304: bipush #24
    //   6306: ldc 1107820544
    //   6308: iastore
    //   6309: dup
    //   6310: bipush #25
    //   6312: ldc 1073742080
    //   6314: iastore
    //   6315: dup
    //   6316: bipush #26
    //   6318: iconst_0
    //   6319: iastore
    //   6320: dup
    //   6321: bipush #27
    //   6323: ldc 1107296256
    //   6325: iastore
    //   6326: dup
    //   6327: bipush #28
    //   6329: ldc 34078976
    //   6331: iastore
    //   6332: dup
    //   6333: bipush #29
    //   6335: ldc 33554432
    //   6337: iastore
    //   6338: dup
    //   6339: bipush #30
    //   6341: ldc 1107296256
    //   6343: iastore
    //   6344: dup
    //   6345: bipush #31
    //   6347: ldc 524544
    //   6349: iastore
    //   6350: dup
    //   6351: bipush #32
    //   6353: ldc 524288
    //   6355: iastore
    //   6356: dup
    //   6357: bipush #33
    //   6359: ldc 1107296512
    //   6361: iastore
    //   6362: dup
    //   6363: bipush #34
    //   6365: sipush #256
    //   6368: iastore
    //   6369: dup
    //   6370: bipush #35
    //   6372: ldc 33554432
    //   6374: iastore
    //   6375: dup
    //   6376: bipush #36
    //   6378: ldc 1073741824
    //   6380: iastore
    //   6381: dup
    //   6382: bipush #37
    //   6384: ldc 34078720
    //   6386: iastore
    //   6387: dup
    //   6388: bipush #38
    //   6390: ldc 1107296512
    //   6392: iastore
    //   6393: dup
    //   6394: bipush #39
    //   6396: ldc 1074266368
    //   6398: iastore
    //   6399: dup
    //   6400: bipush #40
    //   6402: ldc 33554688
    //   6404: iastore
    //   6405: dup
    //   6406: bipush #41
    //   6408: ldc 1073741824
    //   6410: iastore
    //   6411: dup
    //   6412: bipush #42
    //   6414: ldc 1107820544
    //   6416: iastore
    //   6417: dup
    //   6418: bipush #43
    //   6420: ldc 34078976
    //   6422: iastore
    //   6423: dup
    //   6424: bipush #44
    //   6426: ldc 1074266368
    //   6428: iastore
    //   6429: dup
    //   6430: bipush #45
    //   6432: sipush #256
    //   6435: iastore
    //   6436: dup
    //   6437: bipush #46
    //   6439: ldc 33554432
    //   6441: iastore
    //   6442: dup
    //   6443: bipush #47
    //   6445: ldc 1107820544
    //   6447: iastore
    //   6448: dup
    //   6449: bipush #48
    //   6451: ldc 1107820800
    //   6453: iastore
    //   6454: dup
    //   6455: bipush #49
    //   6457: ldc 524544
    //   6459: iastore
    //   6460: dup
    //   6461: bipush #50
    //   6463: ldc 1107296256
    //   6465: iastore
    //   6466: dup
    //   6467: bipush #51
    //   6469: ldc 1107820800
    //   6471: iastore
    //   6472: dup
    //   6473: bipush #52
    //   6475: ldc 34078720
    //   6477: iastore
    //   6478: dup
    //   6479: bipush #53
    //   6481: iconst_0
    //   6482: iastore
    //   6483: dup
    //   6484: bipush #54
    //   6486: ldc 1074266112
    //   6488: iastore
    //   6489: dup
    //   6490: bipush #55
    //   6492: ldc 1107296256
    //   6494: iastore
    //   6495: dup
    //   6496: bipush #56
    //   6498: ldc 524544
    //   6500: iastore
    //   6501: dup
    //   6502: bipush #57
    //   6504: ldc 33554688
    //   6506: iastore
    //   6507: dup
    //   6508: bipush #58
    //   6510: ldc 1073742080
    //   6512: iastore
    //   6513: dup
    //   6514: bipush #59
    //   6516: ldc 524288
    //   6518: iastore
    //   6519: dup
    //   6520: bipush #60
    //   6522: iconst_0
    //   6523: iastore
    //   6524: dup
    //   6525: bipush #61
    //   6527: ldc 1074266112
    //   6529: iastore
    //   6530: dup
    //   6531: bipush #62
    //   6533: ldc 34078976
    //   6535: iastore
    //   6536: dup
    //   6537: bipush #63
    //   6539: ldc 1073742080
    //   6541: iastore
    //   6542: astore #10
    //   6544: bipush #64
    //   6546: newarray int
    //   6548: dup
    //   6549: iconst_0
    //   6550: ldc 536870928
    //   6552: iastore
    //   6553: dup
    //   6554: iconst_1
    //   6555: ldc 541065216
    //   6557: iastore
    //   6558: dup
    //   6559: iconst_2
    //   6560: sipush #16384
    //   6563: iastore
    //   6564: dup
    //   6565: iconst_3
    //   6566: ldc 541081616
    //   6568: iastore
    //   6569: dup
    //   6570: iconst_4
    //   6571: ldc 541065216
    //   6573: iastore
    //   6574: dup
    //   6575: iconst_5
    //   6576: bipush #16
    //   6578: iastore
    //   6579: dup
    //   6580: bipush #6
    //   6582: ldc 541081616
    //   6584: iastore
    //   6585: dup
    //   6586: bipush #7
    //   6588: ldc 4194304
    //   6590: iastore
    //   6591: dup
    //   6592: bipush #8
    //   6594: ldc 536887296
    //   6596: iastore
    //   6597: dup
    //   6598: bipush #9
    //   6600: ldc 4210704
    //   6602: iastore
    //   6603: dup
    //   6604: bipush #10
    //   6606: ldc 4194304
    //   6608: iastore
    //   6609: dup
    //   6610: bipush #11
    //   6612: ldc 536870928
    //   6614: iastore
    //   6615: dup
    //   6616: bipush #12
    //   6618: ldc 4194320
    //   6620: iastore
    //   6621: dup
    //   6622: bipush #13
    //   6624: ldc 536887296
    //   6626: iastore
    //   6627: dup
    //   6628: bipush #14
    //   6630: ldc 536870912
    //   6632: iastore
    //   6633: dup
    //   6634: bipush #15
    //   6636: sipush #16400
    //   6639: iastore
    //   6640: dup
    //   6641: bipush #16
    //   6643: iconst_0
    //   6644: iastore
    //   6645: dup
    //   6646: bipush #17
    //   6648: ldc 4194320
    //   6650: iastore
    //   6651: dup
    //   6652: bipush #18
    //   6654: ldc 536887312
    //   6656: iastore
    //   6657: dup
    //   6658: bipush #19
    //   6660: sipush #16384
    //   6663: iastore
    //   6664: dup
    //   6665: bipush #20
    //   6667: ldc 4210688
    //   6669: iastore
    //   6670: dup
    //   6671: bipush #21
    //   6673: ldc 536887312
    //   6675: iastore
    //   6676: dup
    //   6677: bipush #22
    //   6679: bipush #16
    //   6681: iastore
    //   6682: dup
    //   6683: bipush #23
    //   6685: ldc 541065232
    //   6687: iastore
    //   6688: dup
    //   6689: bipush #24
    //   6691: ldc 541065232
    //   6693: iastore
    //   6694: dup
    //   6695: bipush #25
    //   6697: iconst_0
    //   6698: iastore
    //   6699: dup
    //   6700: bipush #26
    //   6702: ldc 4210704
    //   6704: iastore
    //   6705: dup
    //   6706: bipush #27
    //   6708: ldc 541081600
    //   6710: iastore
    //   6711: dup
    //   6712: bipush #28
    //   6714: sipush #16400
    //   6717: iastore
    //   6718: dup
    //   6719: bipush #29
    //   6721: ldc 4210688
    //   6723: iastore
    //   6724: dup
    //   6725: bipush #30
    //   6727: ldc 541081600
    //   6729: iastore
    //   6730: dup
    //   6731: bipush #31
    //   6733: ldc 536870912
    //   6735: iastore
    //   6736: dup
    //   6737: bipush #32
    //   6739: ldc 536887296
    //   6741: iastore
    //   6742: dup
    //   6743: bipush #33
    //   6745: bipush #16
    //   6747: iastore
    //   6748: dup
    //   6749: bipush #34
    //   6751: ldc 541065232
    //   6753: iastore
    //   6754: dup
    //   6755: bipush #35
    //   6757: ldc 4210688
    //   6759: iastore
    //   6760: dup
    //   6761: bipush #36
    //   6763: ldc 541081616
    //   6765: iastore
    //   6766: dup
    //   6767: bipush #37
    //   6769: ldc 4194304
    //   6771: iastore
    //   6772: dup
    //   6773: bipush #38
    //   6775: sipush #16400
    //   6778: iastore
    //   6779: dup
    //   6780: bipush #39
    //   6782: ldc 536870928
    //   6784: iastore
    //   6785: dup
    //   6786: bipush #40
    //   6788: ldc 4194304
    //   6790: iastore
    //   6791: dup
    //   6792: bipush #41
    //   6794: ldc 536887296
    //   6796: iastore
    //   6797: dup
    //   6798: bipush #42
    //   6800: ldc 536870912
    //   6802: iastore
    //   6803: dup
    //   6804: bipush #43
    //   6806: sipush #16400
    //   6809: iastore
    //   6810: dup
    //   6811: bipush #44
    //   6813: ldc 536870928
    //   6815: iastore
    //   6816: dup
    //   6817: bipush #45
    //   6819: ldc 541081616
    //   6821: iastore
    //   6822: dup
    //   6823: bipush #46
    //   6825: ldc 4210688
    //   6827: iastore
    //   6828: dup
    //   6829: bipush #47
    //   6831: ldc 541065216
    //   6833: iastore
    //   6834: dup
    //   6835: bipush #48
    //   6837: ldc 4210704
    //   6839: iastore
    //   6840: dup
    //   6841: bipush #49
    //   6843: ldc 541081600
    //   6845: iastore
    //   6846: dup
    //   6847: bipush #50
    //   6849: iconst_0
    //   6850: iastore
    //   6851: dup
    //   6852: bipush #51
    //   6854: ldc 541065232
    //   6856: iastore
    //   6857: dup
    //   6858: bipush #52
    //   6860: bipush #16
    //   6862: iastore
    //   6863: dup
    //   6864: bipush #53
    //   6866: sipush #16384
    //   6869: iastore
    //   6870: dup
    //   6871: bipush #54
    //   6873: ldc 541065216
    //   6875: iastore
    //   6876: dup
    //   6877: bipush #55
    //   6879: ldc 4210704
    //   6881: iastore
    //   6882: dup
    //   6883: bipush #56
    //   6885: sipush #16384
    //   6888: iastore
    //   6889: dup
    //   6890: bipush #57
    //   6892: ldc 4194320
    //   6894: iastore
    //   6895: dup
    //   6896: bipush #58
    //   6898: ldc 536887312
    //   6900: iastore
    //   6901: dup
    //   6902: bipush #59
    //   6904: iconst_0
    //   6905: iastore
    //   6906: dup
    //   6907: bipush #60
    //   6909: ldc 541081600
    //   6911: iastore
    //   6912: dup
    //   6913: bipush #61
    //   6915: ldc 536870912
    //   6917: iastore
    //   6918: dup
    //   6919: bipush #62
    //   6921: ldc 4194320
    //   6923: iastore
    //   6924: dup
    //   6925: bipush #63
    //   6927: ldc 536887312
    //   6929: iastore
    //   6930: astore #11
    //   6932: bipush #64
    //   6934: newarray int
    //   6936: dup
    //   6937: iconst_0
    //   6938: ldc 2097152
    //   6940: iastore
    //   6941: dup
    //   6942: iconst_1
    //   6943: ldc 69206018
    //   6945: iastore
    //   6946: dup
    //   6947: iconst_2
    //   6948: ldc 67110914
    //   6950: iastore
    //   6951: dup
    //   6952: iconst_3
    //   6953: iconst_0
    //   6954: iastore
    //   6955: dup
    //   6956: iconst_4
    //   6957: sipush #2048
    //   6960: iastore
    //   6961: dup
    //   6962: iconst_5
    //   6963: ldc 67110914
    //   6965: iastore
    //   6966: dup
    //   6967: bipush #6
    //   6969: ldc 2099202
    //   6971: iastore
    //   6972: dup
    //   6973: bipush #7
    //   6975: ldc 69208064
    //   6977: iastore
    //   6978: dup
    //   6979: bipush #8
    //   6981: ldc 69208066
    //   6983: iastore
    //   6984: dup
    //   6985: bipush #9
    //   6987: ldc 2097152
    //   6989: iastore
    //   6990: dup
    //   6991: bipush #10
    //   6993: iconst_0
    //   6994: iastore
    //   6995: dup
    //   6996: bipush #11
    //   6998: ldc 67108866
    //   7000: iastore
    //   7001: dup
    //   7002: bipush #12
    //   7004: iconst_2
    //   7005: iastore
    //   7006: dup
    //   7007: bipush #13
    //   7009: ldc 67108864
    //   7011: iastore
    //   7012: dup
    //   7013: bipush #14
    //   7015: ldc 69206018
    //   7017: iastore
    //   7018: dup
    //   7019: bipush #15
    //   7021: sipush #2050
    //   7024: iastore
    //   7025: dup
    //   7026: bipush #16
    //   7028: ldc 67110912
    //   7030: iastore
    //   7031: dup
    //   7032: bipush #17
    //   7034: ldc 2099202
    //   7036: iastore
    //   7037: dup
    //   7038: bipush #18
    //   7040: ldc 2097154
    //   7042: iastore
    //   7043: dup
    //   7044: bipush #19
    //   7046: ldc 67110912
    //   7048: iastore
    //   7049: dup
    //   7050: bipush #20
    //   7052: ldc 67108866
    //   7054: iastore
    //   7055: dup
    //   7056: bipush #21
    //   7058: ldc 69206016
    //   7060: iastore
    //   7061: dup
    //   7062: bipush #22
    //   7064: ldc 69208064
    //   7066: iastore
    //   7067: dup
    //   7068: bipush #23
    //   7070: ldc 2097154
    //   7072: iastore
    //   7073: dup
    //   7074: bipush #24
    //   7076: ldc 69206016
    //   7078: iastore
    //   7079: dup
    //   7080: bipush #25
    //   7082: sipush #2048
    //   7085: iastore
    //   7086: dup
    //   7087: bipush #26
    //   7089: sipush #2050
    //   7092: iastore
    //   7093: dup
    //   7094: bipush #27
    //   7096: ldc 69208066
    //   7098: iastore
    //   7099: dup
    //   7100: bipush #28
    //   7102: ldc 2099200
    //   7104: iastore
    //   7105: dup
    //   7106: bipush #29
    //   7108: iconst_2
    //   7109: iastore
    //   7110: dup
    //   7111: bipush #30
    //   7113: ldc 67108864
    //   7115: iastore
    //   7116: dup
    //   7117: bipush #31
    //   7119: ldc 2099200
    //   7121: iastore
    //   7122: dup
    //   7123: bipush #32
    //   7125: ldc 67108864
    //   7127: iastore
    //   7128: dup
    //   7129: bipush #33
    //   7131: ldc 2099200
    //   7133: iastore
    //   7134: dup
    //   7135: bipush #34
    //   7137: ldc 2097152
    //   7139: iastore
    //   7140: dup
    //   7141: bipush #35
    //   7143: ldc 67110914
    //   7145: iastore
    //   7146: dup
    //   7147: bipush #36
    //   7149: ldc 67110914
    //   7151: iastore
    //   7152: dup
    //   7153: bipush #37
    //   7155: ldc 69206018
    //   7157: iastore
    //   7158: dup
    //   7159: bipush #38
    //   7161: ldc 69206018
    //   7163: iastore
    //   7164: dup
    //   7165: bipush #39
    //   7167: iconst_2
    //   7168: iastore
    //   7169: dup
    //   7170: bipush #40
    //   7172: ldc 2097154
    //   7174: iastore
    //   7175: dup
    //   7176: bipush #41
    //   7178: ldc 67108864
    //   7180: iastore
    //   7181: dup
    //   7182: bipush #42
    //   7184: ldc 67110912
    //   7186: iastore
    //   7187: dup
    //   7188: bipush #43
    //   7190: ldc 2097152
    //   7192: iastore
    //   7193: dup
    //   7194: bipush #44
    //   7196: ldc 69208064
    //   7198: iastore
    //   7199: dup
    //   7200: bipush #45
    //   7202: sipush #2050
    //   7205: iastore
    //   7206: dup
    //   7207: bipush #46
    //   7209: ldc 2099202
    //   7211: iastore
    //   7212: dup
    //   7213: bipush #47
    //   7215: ldc 69208064
    //   7217: iastore
    //   7218: dup
    //   7219: bipush #48
    //   7221: sipush #2050
    //   7224: iastore
    //   7225: dup
    //   7226: bipush #49
    //   7228: ldc 67108866
    //   7230: iastore
    //   7231: dup
    //   7232: bipush #50
    //   7234: ldc 69208066
    //   7236: iastore
    //   7237: dup
    //   7238: bipush #51
    //   7240: ldc 69206016
    //   7242: iastore
    //   7243: dup
    //   7244: bipush #52
    //   7246: ldc 2099200
    //   7248: iastore
    //   7249: dup
    //   7250: bipush #53
    //   7252: iconst_0
    //   7253: iastore
    //   7254: dup
    //   7255: bipush #54
    //   7257: iconst_2
    //   7258: iastore
    //   7259: dup
    //   7260: bipush #55
    //   7262: ldc 69208066
    //   7264: iastore
    //   7265: dup
    //   7266: bipush #56
    //   7268: iconst_0
    //   7269: iastore
    //   7270: dup
    //   7271: bipush #57
    //   7273: ldc 2099202
    //   7275: iastore
    //   7276: dup
    //   7277: bipush #58
    //   7279: ldc 69206016
    //   7281: iastore
    //   7282: dup
    //   7283: bipush #59
    //   7285: sipush #2048
    //   7288: iastore
    //   7289: dup
    //   7290: bipush #60
    //   7292: ldc 67108866
    //   7294: iastore
    //   7295: dup
    //   7296: bipush #61
    //   7298: ldc 67110912
    //   7300: iastore
    //   7301: dup
    //   7302: bipush #62
    //   7304: sipush #2048
    //   7307: iastore
    //   7308: dup
    //   7309: bipush #63
    //   7311: ldc 2097154
    //   7313: iastore
    //   7314: astore #12
    //   7316: bipush #64
    //   7318: newarray int
    //   7320: dup
    //   7321: iconst_0
    //   7322: ldc 268439616
    //   7324: iastore
    //   7325: dup
    //   7326: iconst_1
    //   7327: sipush #4096
    //   7330: iastore
    //   7331: dup
    //   7332: iconst_2
    //   7333: ldc 262144
    //   7335: iastore
    //   7336: dup
    //   7337: iconst_3
    //   7338: ldc 268701760
    //   7340: iastore
    //   7341: dup
    //   7342: iconst_4
    //   7343: ldc 268435456
    //   7345: iastore
    //   7346: dup
    //   7347: iconst_5
    //   7348: ldc 268439616
    //   7350: iastore
    //   7351: dup
    //   7352: bipush #6
    //   7354: bipush #64
    //   7356: iastore
    //   7357: dup
    //   7358: bipush #7
    //   7360: ldc 268435456
    //   7362: iastore
    //   7363: dup
    //   7364: bipush #8
    //   7366: ldc 262208
    //   7368: iastore
    //   7369: dup
    //   7370: bipush #9
    //   7372: ldc 268697600
    //   7374: iastore
    //   7375: dup
    //   7376: bipush #10
    //   7378: ldc 268701760
    //   7380: iastore
    //   7381: dup
    //   7382: bipush #11
    //   7384: ldc 266240
    //   7386: iastore
    //   7387: dup
    //   7388: bipush #12
    //   7390: ldc 268701696
    //   7392: iastore
    //   7393: dup
    //   7394: bipush #13
    //   7396: ldc 266304
    //   7398: iastore
    //   7399: dup
    //   7400: bipush #14
    //   7402: sipush #4096
    //   7405: iastore
    //   7406: dup
    //   7407: bipush #15
    //   7409: bipush #64
    //   7411: iastore
    //   7412: dup
    //   7413: bipush #16
    //   7415: ldc 268697600
    //   7417: iastore
    //   7418: dup
    //   7419: bipush #17
    //   7421: ldc 268435520
    //   7423: iastore
    //   7424: dup
    //   7425: bipush #18
    //   7427: ldc 268439552
    //   7429: iastore
    //   7430: dup
    //   7431: bipush #19
    //   7433: sipush #4160
    //   7436: iastore
    //   7437: dup
    //   7438: bipush #20
    //   7440: ldc 266240
    //   7442: iastore
    //   7443: dup
    //   7444: bipush #21
    //   7446: ldc 262208
    //   7448: iastore
    //   7449: dup
    //   7450: bipush #22
    //   7452: ldc 268697664
    //   7454: iastore
    //   7455: dup
    //   7456: bipush #23
    //   7458: ldc 268701696
    //   7460: iastore
    //   7461: dup
    //   7462: bipush #24
    //   7464: sipush #4160
    //   7467: iastore
    //   7468: dup
    //   7469: bipush #25
    //   7471: iconst_0
    //   7472: iastore
    //   7473: dup
    //   7474: bipush #26
    //   7476: iconst_0
    //   7477: iastore
    //   7478: dup
    //   7479: bipush #27
    //   7481: ldc 268697664
    //   7483: iastore
    //   7484: dup
    //   7485: bipush #28
    //   7487: ldc 268435520
    //   7489: iastore
    //   7490: dup
    //   7491: bipush #29
    //   7493: ldc 268439552
    //   7495: iastore
    //   7496: dup
    //   7497: bipush #30
    //   7499: ldc 266304
    //   7501: iastore
    //   7502: dup
    //   7503: bipush #31
    //   7505: ldc 262144
    //   7507: iastore
    //   7508: dup
    //   7509: bipush #32
    //   7511: ldc 266304
    //   7513: iastore
    //   7514: dup
    //   7515: bipush #33
    //   7517: ldc 262144
    //   7519: iastore
    //   7520: dup
    //   7521: bipush #34
    //   7523: ldc 268701696
    //   7525: iastore
    //   7526: dup
    //   7527: bipush #35
    //   7529: sipush #4096
    //   7532: iastore
    //   7533: dup
    //   7534: bipush #36
    //   7536: bipush #64
    //   7538: iastore
    //   7539: dup
    //   7540: bipush #37
    //   7542: ldc 268697664
    //   7544: iastore
    //   7545: dup
    //   7546: bipush #38
    //   7548: sipush #4096
    //   7551: iastore
    //   7552: dup
    //   7553: bipush #39
    //   7555: ldc 266304
    //   7557: iastore
    //   7558: dup
    //   7559: bipush #40
    //   7561: ldc 268439552
    //   7563: iastore
    //   7564: dup
    //   7565: bipush #41
    //   7567: bipush #64
    //   7569: iastore
    //   7570: dup
    //   7571: bipush #42
    //   7573: ldc 268435520
    //   7575: iastore
    //   7576: dup
    //   7577: bipush #43
    //   7579: ldc 268697600
    //   7581: iastore
    //   7582: dup
    //   7583: bipush #44
    //   7585: ldc 268697664
    //   7587: iastore
    //   7588: dup
    //   7589: bipush #45
    //   7591: ldc 268435456
    //   7593: iastore
    //   7594: dup
    //   7595: bipush #46
    //   7597: ldc 262144
    //   7599: iastore
    //   7600: dup
    //   7601: bipush #47
    //   7603: ldc 268439616
    //   7605: iastore
    //   7606: dup
    //   7607: bipush #48
    //   7609: iconst_0
    //   7610: iastore
    //   7611: dup
    //   7612: bipush #49
    //   7614: ldc 268701760
    //   7616: iastore
    //   7617: dup
    //   7618: bipush #50
    //   7620: ldc 262208
    //   7622: iastore
    //   7623: dup
    //   7624: bipush #51
    //   7626: ldc 268435520
    //   7628: iastore
    //   7629: dup
    //   7630: bipush #52
    //   7632: ldc 268697600
    //   7634: iastore
    //   7635: dup
    //   7636: bipush #53
    //   7638: ldc 268439552
    //   7640: iastore
    //   7641: dup
    //   7642: bipush #54
    //   7644: ldc 268439616
    //   7646: iastore
    //   7647: dup
    //   7648: bipush #55
    //   7650: iconst_0
    //   7651: iastore
    //   7652: dup
    //   7653: bipush #56
    //   7655: ldc 268701760
    //   7657: iastore
    //   7658: dup
    //   7659: bipush #57
    //   7661: ldc 266240
    //   7663: iastore
    //   7664: dup
    //   7665: bipush #58
    //   7667: ldc 266240
    //   7669: iastore
    //   7670: dup
    //   7671: bipush #59
    //   7673: sipush #4160
    //   7676: iastore
    //   7677: dup
    //   7678: bipush #60
    //   7680: sipush #4160
    //   7683: iastore
    //   7684: dup
    //   7685: bipush #61
    //   7687: ldc 262208
    //   7689: iastore
    //   7690: dup
    //   7691: bipush #62
    //   7693: ldc 268435456
    //   7695: iastore
    //   7696: dup
    //   7697: bipush #63
    //   7699: ldc 268701696
    //   7701: iastore
    //   7702: astore #13
    //   7704: aload_3
    //   7705: arraylength
    //   7706: istore #14
    //   7708: iload #14
    //   7710: bipush #8
    //   7712: irem
    //   7713: ifeq -> 7737
    //   7716: new java/lang/Exception
    //   7719: dup
    //   7720: sipush #-11047
    //   7723: sipush #7918
    //   7726: invokestatic a : (II)Ljava/lang/String;
    //   7729: invokespecial <init> : (Ljava/lang/String;)V
    //   7732: athrow
    //   7733: invokestatic a : (Ljava/lang/Throwable;)Ljava/lang/Throwable;
    //   7736: athrow
    //   7737: iconst_2
    //   7738: newarray int
    //   7740: astore #15
    //   7742: iload #14
    //   7744: newarray byte
    //   7746: astore #16
    //   7748: iload #14
    //   7750: bipush #8
    //   7752: idiv
    //   7753: istore #17
    //   7755: iconst_0
    //   7756: istore #18
    //   7758: iload #18
    //   7760: iload #17
    //   7762: if_icmpge -> 8676
    //   7765: iload #18
    //   7767: bipush #8
    //   7769: imul
    //   7770: istore #19
    //   7772: iconst_0
    //   7773: istore #20
    //   7775: iload #20
    //   7777: iconst_2
    //   7778: if_icmpge -> 7863
    //   7781: aload #15
    //   7783: iload #20
    //   7785: aload_3
    //   7786: iload #19
    //   7788: iload #20
    //   7790: iconst_4
    //   7791: imul
    //   7792: iadd
    //   7793: baload
    //   7794: sipush #255
    //   7797: iand
    //   7798: bipush #24
    //   7800: ishl
    //   7801: aload_3
    //   7802: iload #19
    //   7804: iload #20
    //   7806: iconst_4
    //   7807: imul
    //   7808: iadd
    //   7809: iconst_1
    //   7810: iadd
    //   7811: baload
    //   7812: sipush #255
    //   7815: iand
    //   7816: bipush #16
    //   7818: ishl
    //   7819: ior
    //   7820: aload_3
    //   7821: iload #19
    //   7823: iload #20
    //   7825: iconst_4
    //   7826: imul
    //   7827: iadd
    //   7828: iconst_2
    //   7829: iadd
    //   7830: baload
    //   7831: sipush #255
    //   7834: iand
    //   7835: bipush #8
    //   7837: ishl
    //   7838: ior
    //   7839: aload_3
    //   7840: iload #19
    //   7842: iload #20
    //   7844: iconst_4
    //   7845: imul
    //   7846: iadd
    //   7847: iconst_3
    //   7848: iadd
    //   7849: baload
    //   7850: sipush #255
    //   7853: iand
    //   7854: ior
    //   7855: iastore
    //   7856: iinc #20, 1
    //   7859: iload_2
    //   7860: ifeq -> 7775
    //   7863: iconst_0
    //   7864: istore #25
    //   7866: aload #15
    //   7868: iconst_0
    //   7869: iaload
    //   7870: istore #23
    //   7872: aload #15
    //   7874: iconst_1
    //   7875: iaload
    //   7876: istore #22
    //   7878: iload #23
    //   7880: iconst_4
    //   7881: iushr
    //   7882: iload #22
    //   7884: ixor
    //   7885: ldc 252645135
    //   7887: iand
    //   7888: istore #21
    //   7890: iload #22
    //   7892: iload #21
    //   7894: ixor
    //   7895: istore #22
    //   7897: iload #23
    //   7899: iload #21
    //   7901: iconst_4
    //   7902: ishl
    //   7903: ixor
    //   7904: istore #23
    //   7906: iload #23
    //   7908: bipush #16
    //   7910: iushr
    //   7911: iload #22
    //   7913: ixor
    //   7914: ldc 65535
    //   7916: iand
    //   7917: istore #21
    //   7919: iload #22
    //   7921: iload #21
    //   7923: ixor
    //   7924: istore #22
    //   7926: iload #23
    //   7928: iload #21
    //   7930: bipush #16
    //   7932: ishl
    //   7933: ixor
    //   7934: istore #23
    //   7936: iload #22
    //   7938: iconst_2
    //   7939: iushr
    //   7940: iload #23
    //   7942: ixor
    //   7943: ldc 858993459
    //   7945: iand
    //   7946: istore #21
    //   7948: iload #23
    //   7950: iload #21
    //   7952: ixor
    //   7953: istore #23
    //   7955: iload #22
    //   7957: iload #21
    //   7959: iconst_2
    //   7960: ishl
    //   7961: ixor
    //   7962: istore #22
    //   7964: iload #22
    //   7966: bipush #8
    //   7968: iushr
    //   7969: iload #23
    //   7971: ixor
    //   7972: ldc 16711935
    //   7974: iand
    //   7975: istore #21
    //   7977: iload #23
    //   7979: iload #21
    //   7981: ixor
    //   7982: istore #23
    //   7984: iload #22
    //   7986: iload #21
    //   7988: bipush #8
    //   7990: ishl
    //   7991: ixor
    //   7992: istore #22
    //   7994: iload #22
    //   7996: iconst_1
    //   7997: ishl
    //   7998: iload #22
    //   8000: bipush #31
    //   8002: iushr
    //   8003: iconst_1
    //   8004: iand
    //   8005: ior
    //   8006: istore #22
    //   8008: iload #23
    //   8010: iload #22
    //   8012: ixor
    //   8013: ldc -1431655766
    //   8015: iand
    //   8016: istore #21
    //   8018: iload #23
    //   8020: iload #21
    //   8022: ixor
    //   8023: istore #23
    //   8025: iload #22
    //   8027: iload #21
    //   8029: ixor
    //   8030: istore #22
    //   8032: iload #23
    //   8034: iconst_1
    //   8035: ishl
    //   8036: iload #23
    //   8038: bipush #31
    //   8040: iushr
    //   8041: iconst_1
    //   8042: iand
    //   8043: ior
    //   8044: istore #23
    //   8046: iconst_0
    //   8047: istore #24
    //   8049: iload #24
    //   8051: bipush #8
    //   8053: if_icmpge -> 8391
    //   8056: iload #22
    //   8058: bipush #28
    //   8060: ishl
    //   8061: iload #22
    //   8063: iconst_4
    //   8064: iushr
    //   8065: ior
    //   8066: istore #21
    //   8068: iload #21
    //   8070: aload #5
    //   8072: iload #25
    //   8074: iinc #25, 1
    //   8077: iaload
    //   8078: ixor
    //   8079: istore #21
    //   8081: aload #12
    //   8083: iload #21
    //   8085: bipush #63
    //   8087: iand
    //   8088: iaload
    //   8089: istore #20
    //   8091: iload #20
    //   8093: aload #10
    //   8095: iload #21
    //   8097: bipush #8
    //   8099: iushr
    //   8100: bipush #63
    //   8102: iand
    //   8103: iaload
    //   8104: ior
    //   8105: istore #20
    //   8107: iload #20
    //   8109: aload #8
    //   8111: iload #21
    //   8113: bipush #16
    //   8115: iushr
    //   8116: bipush #63
    //   8118: iand
    //   8119: iaload
    //   8120: ior
    //   8121: istore #20
    //   8123: iload #20
    //   8125: aload #6
    //   8127: iload #21
    //   8129: bipush #24
    //   8131: iushr
    //   8132: bipush #63
    //   8134: iand
    //   8135: iaload
    //   8136: ior
    //   8137: istore #20
    //   8139: iload #22
    //   8141: aload #5
    //   8143: iload #25
    //   8145: iinc #25, 1
    //   8148: iaload
    //   8149: ixor
    //   8150: istore #21
    //   8152: iload #20
    //   8154: aload #13
    //   8156: iload #21
    //   8158: bipush #63
    //   8160: iand
    //   8161: iaload
    //   8162: ior
    //   8163: istore #20
    //   8165: iload #20
    //   8167: aload #11
    //   8169: iload #21
    //   8171: bipush #8
    //   8173: iushr
    //   8174: bipush #63
    //   8176: iand
    //   8177: iaload
    //   8178: ior
    //   8179: istore #20
    //   8181: iload #20
    //   8183: aload #9
    //   8185: iload #21
    //   8187: bipush #16
    //   8189: iushr
    //   8190: bipush #63
    //   8192: iand
    //   8193: iaload
    //   8194: ior
    //   8195: istore #20
    //   8197: iload #20
    //   8199: aload #7
    //   8201: iload #21
    //   8203: bipush #24
    //   8205: iushr
    //   8206: bipush #63
    //   8208: iand
    //   8209: iaload
    //   8210: ior
    //   8211: istore #20
    //   8213: iload #23
    //   8215: iload #20
    //   8217: ixor
    //   8218: istore #23
    //   8220: iload #23
    //   8222: bipush #28
    //   8224: ishl
    //   8225: iload #23
    //   8227: iconst_4
    //   8228: iushr
    //   8229: ior
    //   8230: istore #21
    //   8232: iload #21
    //   8234: aload #5
    //   8236: iload #25
    //   8238: iinc #25, 1
    //   8241: iaload
    //   8242: ixor
    //   8243: istore #21
    //   8245: aload #12
    //   8247: iload #21
    //   8249: bipush #63
    //   8251: iand
    //   8252: iaload
    //   8253: istore #20
    //   8255: iload #20
    //   8257: aload #10
    //   8259: iload #21
    //   8261: bipush #8
    //   8263: iushr
    //   8264: bipush #63
    //   8266: iand
    //   8267: iaload
    //   8268: ior
    //   8269: istore #20
    //   8271: iload #20
    //   8273: aload #8
    //   8275: iload #21
    //   8277: bipush #16
    //   8279: iushr
    //   8280: bipush #63
    //   8282: iand
    //   8283: iaload
    //   8284: ior
    //   8285: istore #20
    //   8287: iload #20
    //   8289: aload #6
    //   8291: iload #21
    //   8293: bipush #24
    //   8295: iushr
    //   8296: bipush #63
    //   8298: iand
    //   8299: iaload
    //   8300: ior
    //   8301: istore #20
    //   8303: iload #23
    //   8305: aload #5
    //   8307: iload #25
    //   8309: iinc #25, 1
    //   8312: iaload
    //   8313: ixor
    //   8314: istore #21
    //   8316: iload #20
    //   8318: aload #13
    //   8320: iload #21
    //   8322: bipush #63
    //   8324: iand
    //   8325: iaload
    //   8326: ior
    //   8327: istore #20
    //   8329: iload #20
    //   8331: aload #11
    //   8333: iload #21
    //   8335: bipush #8
    //   8337: iushr
    //   8338: bipush #63
    //   8340: iand
    //   8341: iaload
    //   8342: ior
    //   8343: istore #20
    //   8345: iload #20
    //   8347: aload #9
    //   8349: iload #21
    //   8351: bipush #16
    //   8353: iushr
    //   8354: bipush #63
    //   8356: iand
    //   8357: iaload
    //   8358: ior
    //   8359: istore #20
    //   8361: iload #20
    //   8363: aload #7
    //   8365: iload #21
    //   8367: bipush #24
    //   8369: iushr
    //   8370: bipush #63
    //   8372: iand
    //   8373: iaload
    //   8374: ior
    //   8375: istore #20
    //   8377: iload #22
    //   8379: iload #20
    //   8381: ixor
    //   8382: istore #22
    //   8384: iinc #24, 1
    //   8387: iload_2
    //   8388: ifeq -> 8049
    //   8391: iload #22
    //   8393: bipush #31
    //   8395: ishl
    //   8396: iload #22
    //   8398: iconst_1
    //   8399: iushr
    //   8400: ior
    //   8401: istore #22
    //   8403: iload #23
    //   8405: iload #22
    //   8407: ixor
    //   8408: ldc -1431655766
    //   8410: iand
    //   8411: istore #21
    //   8413: iload #23
    //   8415: iload #21
    //   8417: ixor
    //   8418: istore #23
    //   8420: iload #22
    //   8422: iload #21
    //   8424: ixor
    //   8425: istore #22
    //   8427: iload #23
    //   8429: bipush #31
    //   8431: ishl
    //   8432: iload #23
    //   8434: iconst_1
    //   8435: iushr
    //   8436: ior
    //   8437: istore #23
    //   8439: iload #23
    //   8441: bipush #8
    //   8443: iushr
    //   8444: iload #22
    //   8446: ixor
    //   8447: ldc 16711935
    //   8449: iand
    //   8450: istore #21
    //   8452: iload #22
    //   8454: iload #21
    //   8456: ixor
    //   8457: istore #22
    //   8459: iload #23
    //   8461: iload #21
    //   8463: bipush #8
    //   8465: ishl
    //   8466: ixor
    //   8467: istore #23
    //   8469: iload #23
    //   8471: iconst_2
    //   8472: iushr
    //   8473: iload #22
    //   8475: ixor
    //   8476: ldc 858993459
    //   8478: iand
    //   8479: istore #21
    //   8481: iload #22
    //   8483: iload #21
    //   8485: ixor
    //   8486: istore #22
    //   8488: iload #23
    //   8490: iload #21
    //   8492: iconst_2
    //   8493: ishl
    //   8494: ixor
    //   8495: istore #23
    //   8497: iload #22
    //   8499: bipush #16
    //   8501: iushr
    //   8502: iload #23
    //   8504: ixor
    //   8505: ldc 65535
    //   8507: iand
    //   8508: istore #21
    //   8510: iload #23
    //   8512: iload #21
    //   8514: ixor
    //   8515: istore #23
    //   8517: iload #22
    //   8519: iload #21
    //   8521: bipush #16
    //   8523: ishl
    //   8524: ixor
    //   8525: istore #22
    //   8527: iload #22
    //   8529: iconst_4
    //   8530: iushr
    //   8531: iload #23
    //   8533: ixor
    //   8534: ldc 252645135
    //   8536: iand
    //   8537: istore #21
    //   8539: iload #23
    //   8541: iload #21
    //   8543: ixor
    //   8544: istore #23
    //   8546: iload #22
    //   8548: iload #21
    //   8550: iconst_4
    //   8551: ishl
    //   8552: ixor
    //   8553: istore #22
    //   8555: aload #15
    //   8557: iconst_0
    //   8558: iload #22
    //   8560: iastore
    //   8561: aload #15
    //   8563: iconst_1
    //   8564: iload #23
    //   8566: iastore
    //   8567: iload #18
    //   8569: bipush #8
    //   8571: imul
    //   8572: istore #26
    //   8574: iconst_0
    //   8575: istore #27
    //   8577: iload #27
    //   8579: iconst_2
    //   8580: if_icmpge -> 8669
    //   8583: aload #16
    //   8585: iload #26
    //   8587: iload #27
    //   8589: iconst_4
    //   8590: imul
    //   8591: iadd
    //   8592: aload #15
    //   8594: iload #27
    //   8596: iaload
    //   8597: bipush #24
    //   8599: iushr
    //   8600: i2b
    //   8601: bastore
    //   8602: aload #16
    //   8604: iload #26
    //   8606: iload #27
    //   8608: iconst_4
    //   8609: imul
    //   8610: iadd
    //   8611: iconst_1
    //   8612: iadd
    //   8613: aload #15
    //   8615: iload #27
    //   8617: iaload
    //   8618: bipush #16
    //   8620: iushr
    //   8621: i2b
    //   8622: bastore
    //   8623: aload #16
    //   8625: iload #26
    //   8627: iload #27
    //   8629: iconst_4
    //   8630: imul
    //   8631: iadd
    //   8632: iconst_2
    //   8633: iadd
    //   8634: aload #15
    //   8636: iload #27
    //   8638: iaload
    //   8639: bipush #8
    //   8641: iushr
    //   8642: i2b
    //   8643: bastore
    //   8644: aload #16
    //   8646: iload #26
    //   8648: iload #27
    //   8650: iconst_4
    //   8651: imul
    //   8652: iadd
    //   8653: iconst_3
    //   8654: iadd
    //   8655: aload #15
    //   8657: iload #27
    //   8659: iaload
    //   8660: i2b
    //   8661: bastore
    //   8662: iinc #27, 1
    //   8665: iload_2
    //   8666: ifeq -> 8577
    //   8669: iinc #18, 1
    //   8672: iload_2
    //   8673: ifeq -> 7758
    //   8676: aload #16
    //   8678: aload #16
    //   8680: arraylength
    //   8681: iconst_1
    //   8682: isub
    //   8683: baload
    //   8684: istore #18
    //   8686: aload #16
    //   8688: arraylength
    //   8689: iload #18
    //   8691: isub
    //   8692: newarray byte
    //   8694: astore #4
    //   8696: aload #16
    //   8698: arraylength
    //   8699: aload #4
    //   8701: arraylength
    //   8702: if_icmpge -> 8726
    //   8705: new java/lang/Exception
    //   8708: dup
    //   8709: sipush #-11042
    //   8712: sipush #-27390
    //   8715: invokestatic a : (II)Ljava/lang/String;
    //   8718: invokespecial <init> : (Ljava/lang/String;)V
    //   8721: athrow
    //   8722: invokestatic a : (Ljava/lang/Throwable;)Ljava/lang/Throwable;
    //   8725: athrow
    //   8726: iconst_0
    //   8727: istore #19
    //   8729: iload #19
    //   8731: aload #4
    //   8733: arraylength
    //   8734: if_icmpge -> 8754
    //   8737: aload #4
    //   8739: iload #19
    //   8741: aload #16
    //   8743: iload #19
    //   8745: baload
    //   8746: bastore
    //   8747: iinc #19, 1
    //   8750: iload_2
    //   8751: ifeq -> 8729
    //   8754: getstatic burp/Zly9.ZS : Ljava/lang/String;
    //   8757: getstatic burp/Zkhf.ZU : Ljava/lang/Object;
    //   8760: checkcast java/math/BigInteger
    //   8763: invokevirtual intValue : ()I
    //   8766: bipush #32
    //   8768: irem
    //   8769: invokestatic abs : (I)I
    //   8772: invokevirtual charAt : (I)C
    //   8775: getstatic burp/Zkkl.Zh : Ljava/lang/String;
    //   8778: getstatic burp/Zbnz.Zb : Ljava/lang/Object;
    //   8781: checkcast java/math/BigInteger
    //   8784: invokevirtual intValue : ()I
    //   8787: bipush #32
    //   8789: irem
    //   8790: invokestatic abs : (I)I
    //   8793: invokevirtual charAt : (I)C
    //   8796: if_icmpgt -> 8903
    //   8799: getstatic burp/Zrye.Za : Ljava/lang/String;
    //   8802: getstatic burp/Zxju.ZN : Ljava/lang/Object;
    //   8805: checkcast java/math/BigInteger
    //   8808: invokevirtual intValue : ()I
    //   8811: bipush #32
    //   8813: irem
    //   8814: invokestatic abs : (I)I
    //   8817: invokevirtual charAt : (I)C
    //   8820: getstatic burp/Zxan.ZJ : Ljava/lang/String;
    //   8823: getstatic burp/Zxn4.Zx : Ljava/lang/Object;
    //   8826: checkcast java/math/BigInteger
    //   8829: invokevirtual intValue : ()I
    //   8832: bipush #32
    //   8834: irem
    //   8835: invokestatic abs : (I)I
    //   8838: invokevirtual charAt : (I)C
    //   8841: if_icmple -> 8903
    //   8844: goto -> 8851
    //   8847: invokestatic a : (Ljava/lang/Throwable;)Ljava/lang/Throwable;
    //   8850: athrow
    //   8851: getstatic burp/Zbx4.ZS : Ljava/lang/String;
    //   8854: getstatic burp/Zxy6.Zd : Ljava/lang/Object;
    //   8857: checkcast java/math/BigInteger
    //   8860: invokevirtual intValue : ()I
    //   8863: bipush #32
    //   8865: irem
    //   8866: invokestatic abs : (I)I
    //   8869: invokevirtual charAt : (I)C
    //   8872: getstatic burp/Zl7b.Zv : Ljava/lang/String;
    //   8875: getstatic burp/Zscf.ZG : Ljava/lang/Object;
    //   8878: checkcast java/math/BigInteger
    //   8881: invokevirtual intValue : ()I
    //   8884: bipush #32
    //   8886: irem
    //   8887: invokestatic abs : (I)I
    //   8890: invokevirtual charAt : (I)C
    //   8893: if_icmpgt -> 8911
    //   8896: goto -> 8903
    //   8899: invokestatic a : (Ljava/lang/Throwable;)Ljava/lang/Throwable;
    //   8902: athrow
    //   8903: iconst_1
    //   8904: goto -> 8912
    //   8907: invokestatic a : (Ljava/lang/Throwable;)Ljava/lang/Throwable;
    //   8910: athrow
    //   8911: iconst_0
    //   8912: ireturn
    //   8913: astore_3
    //   8914: new java/lang/Exception
    //   8917: dup
    //   8918: aload_3
    //   8919: invokevirtual getMessage : ()Ljava/lang/String;
    //   8922: invokespecial <init> : (Ljava/lang/String;)V
    //   8925: athrow
    // Exception table:
    //   from	to	target	type
    //   4	8912	8913	java/lang/Throwable
    //   805	839	842	java/lang/Throwable
    //   934	1012	1015	java/lang/Throwable
    //   941	1155	1158	java/lang/Throwable
    //   1532	1547	1547	java/lang/Throwable
    //   1574	1608	1611	java/lang/Throwable
    //   1618	1630	1633	java/lang/Throwable
    //   1716	1794	1797	java/lang/Throwable
    //   1723	1937	1940	java/lang/Throwable
    //   2337	2415	2418	java/lang/Throwable
    //   2344	2558	2561	java/lang/Throwable
    //   3005	3039	3042	java/lang/Throwable
    //   3046	3058	3061	java/lang/Throwable
    //   3144	3222	3225	java/lang/Throwable
    //   3151	3365	3368	java/lang/Throwable
    //   4119	4133	4133	java/lang/Throwable
    //   4144	4157	4160	java/lang/Throwable
    //   4149	4172	4175	java/lang/Throwable
    //   4164	4190	4193	java/lang/Throwable
    //   4179	4220	4223	java/lang/Throwable
    //   4283	4310	4313	java/lang/Throwable
    //   4300	4331	4334	java/lang/Throwable
    //   4317	4361	4364	java/lang/Throwable
    //   4338	4372	4372	java/lang/Throwable
    //   4383	4399	4402	java/lang/Throwable
    //   7708	7733	7733	java/lang/Throwable
    //   8696	8722	8722	java/lang/Throwable
    //   8754	8844	8847	java/lang/Throwable
    //   8799	8896	8899	java/lang/Throwable
    //   8851	8907	8907	java/lang/Throwable
  }
  
  static {
    // Byte code:
    //   0: bipush #10
    //   2: anewarray java/lang/String
    //   5: astore #5
    //   7: iconst_0
    //   8: istore_3
    //   9: ldc '^&xK b_6!;9\\tmQ`q/\\n ri,,G?r!{K-&3Jq\\t/v?=LKc\\tpuR\G4L}\\rD0#7\\bpg[:\\fq\\n-VSgzk'wj#d'A'
    //   11: dup
    //   12: astore_2
    //   13: invokevirtual length : ()I
    //   16: istore #4
    //   18: bipush #32
    //   20: istore_1
    //   21: iconst_m1
    //   22: istore_0
    //   23: bipush #30
    //   25: iinc #0, 1
    //   28: aload_2
    //   29: iload_0
    //   30: dup
    //   31: iload_1
    //   32: iadd
    //   33: invokevirtual substring : (II)Ljava/lang/String;
    //   36: iconst_m1
    //   37: goto -> 143
    //   40: aload #5
    //   42: swap
    //   43: iload_3
    //   44: iinc #3, 1
    //   47: swap
    //   48: aastore
    //   49: iload_0
    //   50: iload_1
    //   51: iadd
    //   52: dup
    //   53: istore_0
    //   54: iload #4
    //   56: if_icmpge -> 68
    //   59: aload_2
    //   60: iload_0
    //   61: invokevirtual charAt : (I)C
    //   64: istore_1
    //   65: goto -> 23
    //   68: ldc 'X\\tZ\\tk!"'
    //   70: dup
    //   71: astore_2
    //   72: invokevirtual length : ()I
    //   75: istore #4
    //   77: bipush #9
    //   79: istore_1
    //   80: iconst_m1
    //   81: istore_0
    //   82: bipush #47
    //   84: iinc #0, 1
    //   87: aload_2
    //   88: iload_0
    //   89: dup
    //   90: iload_1
    //   91: iadd
    //   92: invokevirtual substring : (II)Ljava/lang/String;
    //   95: iconst_0
    //   96: goto -> 143
    //   99: aload #5
    //   101: swap
    //   102: iload_3
    //   103: iinc #3, 1
    //   106: swap
    //   107: aastore
    //   108: iload_0
    //   109: iload_1
    //   110: iadd
    //   111: dup
    //   112: istore_0
    //   113: iload #4
    //   115: if_icmpge -> 127
    //   118: aload_2
    //   119: iload_0
    //   120: invokevirtual charAt : (I)C
    //   123: istore_1
    //   124: goto -> 82
    //   127: aload #5
    //   129: putstatic burp/Zrkw.a : [Ljava/lang/String;
    //   132: bipush #10
    //   134: anewarray java/lang/String
    //   137: putstatic burp/Zrkw.b : [Ljava/lang/String;
    //   140: goto -> 300
    //   143: dup_x2
    //   144: pop
    //   145: invokevirtual toCharArray : ()[C
    //   148: dup_x1
    //   149: arraylength
    //   150: dup_x2
    //   151: pop
    //   152: iconst_0
    //   153: istore #6
    //   155: dup2_x1
    //   156: pop2
    //   157: dup_x2
    //   158: iconst_1
    //   159: if_icmpgt -> 260
    //   162: dup2
    //   163: swap
    //   164: iload #6
    //   166: dup2_x1
    //   167: caload
    //   168: swap
    //   169: iload #6
    //   171: bipush #7
    //   173: irem
    //   174: tableswitch default -> 242, 0 -> 212, 1 -> 217, 2 -> 222, 3 -> 227, 4 -> 232, 5 -> 237
    //   212: bipush #67
    //   214: goto -> 244
    //   217: bipush #39
    //   219: goto -> 244
    //   222: bipush #7
    //   224: goto -> 244
    //   227: bipush #110
    //   229: goto -> 244
    //   232: bipush #111
    //   234: goto -> 244
    //   237: bipush #111
    //   239: goto -> 244
    //   242: bipush #101
    //   244: ixor
    //   245: ixor
    //   246: i2c
    //   247: castore
    //   248: iinc #6, 1
    //   251: dup
    //   252: ifne -> 260
    //   255: dup2
    //   256: dup_x1
    //   257: goto -> 166
    //   260: dup2_x1
    //   261: pop2
    //   262: dup_x2
    //   263: iload #6
    //   265: if_icmpgt -> 162
    //   268: pop
    //   269: new java/lang/String
    //   272: dup_x1
    //   273: swap
    //   274: invokespecial <init> : ([C)V
    //   277: invokevirtual intern : ()Ljava/lang/String;
    //   280: swap
    //   281: pop
    //   282: swap
    //   283: tableswitch default -> 40, 0 -> 99
    //   300: sipush #-11048
    //   303: sipush #-10850
    //   306: invokestatic a : (II)Ljava/lang/String;
    //   309: putstatic burp/Zrkw.ZU : Ljava/lang/String;
    //   312: new java/math/BigInteger
    //   315: dup
    //   316: bipush #32
    //   318: newarray byte
    //   320: dup
    //   321: iconst_0
    //   322: bipush #101
    //   324: bastore
    //   325: dup
    //   326: iconst_1
    //   327: bipush #-103
    //   329: bastore
    //   330: dup
    //   331: iconst_2
    //   332: bipush #57
    //   334: bastore
    //   335: dup
    //   336: iconst_3
    //   337: bipush #58
    //   339: bastore
    //   340: dup
    //   341: iconst_4
    //   342: iconst_4
    //   343: bastore
    //   344: dup
    //   345: iconst_5
    //   346: bipush #-62
    //   348: bastore
    //   349: dup
    //   350: bipush #6
    //   352: bipush #47
    //   354: bastore
    //   355: dup
    //   356: bipush #7
    //   358: bipush #-110
    //   360: bastore
    //   361: dup
    //   362: bipush #8
    //   364: bipush #14
    //   366: bastore
    //   367: dup
    //   368: bipush #9
    //   370: bipush #21
    //   372: bastore
    //   373: dup
    //   374: bipush #10
    //   376: bipush #-40
    //   378: bastore
    //   379: dup
    //   380: bipush #11
    //   382: bipush #121
    //   384: bastore
    //   385: dup
    //   386: bipush #12
    //   388: bipush #-119
    //   390: bastore
    //   391: dup
    //   392: bipush #13
    //   394: bipush #-57
    //   396: bastore
    //   397: dup
    //   398: bipush #14
    //   400: bipush #96
    //   402: bastore
    //   403: dup
    //   404: bipush #15
    //   406: bipush #-115
    //   408: bastore
    //   409: dup
    //   410: bipush #16
    //   412: bipush #-118
    //   414: bastore
    //   415: dup
    //   416: bipush #17
    //   418: bipush #-123
    //   420: bastore
    //   421: dup
    //   422: bipush #18
    //   424: bipush #-93
    //   426: bastore
    //   427: dup
    //   428: bipush #19
    //   430: bipush #71
    //   432: bastore
    //   433: dup
    //   434: bipush #20
    //   436: bipush #36
    //   438: bastore
    //   439: dup
    //   440: bipush #21
    //   442: bipush #112
    //   444: bastore
    //   445: dup
    //   446: bipush #22
    //   448: bipush #78
    //   450: bastore
    //   451: dup
    //   452: bipush #23
    //   454: bipush #61
    //   456: bastore
    //   457: dup
    //   458: bipush #24
    //   460: bipush #-72
    //   462: bastore
    //   463: dup
    //   464: bipush #25
    //   466: bipush #-16
    //   468: bastore
    //   469: dup
    //   470: bipush #26
    //   472: bipush #94
    //   474: bastore
    //   475: dup
    //   476: bipush #27
    //   478: bipush #8
    //   480: bastore
    //   481: dup
    //   482: bipush #28
    //   484: bipush #-27
    //   486: bastore
    //   487: dup
    //   488: bipush #29
    //   490: bipush #-112
    //   492: bastore
    //   493: dup
    //   494: bipush #30
    //   496: bipush #-13
    //   498: bastore
    //   499: dup
    //   500: bipush #31
    //   502: bipush #55
    //   504: bastore
    //   505: invokespecial <init> : ([B)V
    //   508: putstatic burp/Zrkw.ZV : Ljava/lang/Object;
    //   511: return
  }
  
  private static Throwable a(Throwable paramThrowable) {
    return paramThrowable;
  }
  
  private static String a(int paramInt1, int paramInt2) {
    int i = (paramInt1 ^ 0xFFFFD4DA) & 0xFFFF;
    if (b[i] == null) {
      char[] arrayOfChar = a[i].toCharArray();
      switch (arrayOfChar[0] & 0xFF) {
        case 0:
        
        case 1:
        
        case 2:
        
        case 3:
        
        case 4:
        
        case 5:
        
        case 6:
        
        case 7:
        
        case 8:
        
        case 9:
        
        case 10:
        
        case 11:
        
        case 12:
        
        case 13:
        
        case 14:
        
        case 15:
        
        case 16:
        
        case 17:
        
        case 18:
        
        case 19:
        
        case 20:
        
        case 21:
        
        case 22:
        
        case 23:
        
        case 24:
        
        case 25:
        
        case 26:
        
        case 27:
        
        case 28:
        
        case 29:
        
        case 30:
        
        case 31:
        
        case 32:
        
        case 33:
        
        case 34:
        
        case 35:
        
        case 36:
        
        case 37:
        
        case 38:
        
        case 39:
        
        case 40:
        
        case 41:
        
        case 42:
        
        case 43:
        
        case 44:
        
        case 45:
        
        case 46:
        
        case 47:
        
        case 48:
        
        case 49:
        
        case 50:
        
        case 51:
        
        case 52:
        
        case 53:
        
        case 54:
        
        case 55:
        
        case 56:
        
        case 57:
        
        case 58:
        
        case 59:
        
        case 60:
        
        case 61:
        
        case 62:
        
        case 63:
        
        case 64:
        
        case 65:
        
        case 66:
        
        case 67:
        
        case 68:
        
        case 69:
        
        case 70:
        
        case 71:
        
        case 72:
        
        case 73:
        
        case 74:
        
        case 75:
        
        case 76:
        
        case 77:
        
        case 78:
        
        case 79:
        
        case 80:
        
        case 81:
        
        case 82:
        
        case 83:
        
        case 84:
        
        case 85:
        
        case 86:
        
        case 87:
        
        case 88:
        
        case 89:
        
        case 90:
        
        case 91:
        
        case 92:
        
        case 93:
        
        case 94:
        
        case 95:
        
        case 96:
        
        case 97:
        
        case 98:
        
        case 99:
        
        case 100:
        
        case 101:
        
        case 102:
        
        case 103:
        
        case 104:
        
        case 105:
        
        case 106:
        
        case 107:
        
        case 108:
        
        case 109:
        
        case 110:
        
        case 111:
        
        case 112:
        
        case 113:
        
        case 114:
        
        case 115:
        
        case 116:
        
        case 117:
        
        case 118:
        
        case 119:
        
        case 120:
        
        case 121:
        
        case 122:
        
        case 123:
        
        case 124:
        
        case 125:
        
        case 126:
        
        case 127:
        
        case 128:
        
        case 129:
        
        case 130:
        
        case 131:
        
        case 132:
        
        case 133:
        
        case 134:
        
        case 135:
        
        case 136:
        
        case 137:
        
        case 138:
        
        case 139:
        
        case 140:
        
        case 141:
        
        case 142:
        
        case 143:
        
        case 144:
        
        case 145:
        
        case 146:
        
        case 147:
        
        case 148:
        
        case 149:
        
        case 150:
        
        case 151:
        
        case 152:
        
        case 153:
        
        case 154:
        
        case 155:
        
        case 156:
        
        case 157:
        
        case 158:
        
        case 159:
        
        case 160:
        
        case 161:
        
        case 162:
        
        case 163:
        
        case 164:
        
        case 165:
        
        case 166:
        
        case 167:
        
        case 168:
        
        case 169:
        
        case 170:
        
        case 171:
        
        case 172:
        
        case 173:
        
        case 174:
        
        case 175:
        
        case 176:
        
        case 177:
        
        case 178:
        
        case 179:
        
        case 180:
        
        case 181:
        
        case 182:
        
        case 183:
        
        case 184:
        
        case 185:
        
        case 186:
        
        case 187:
        
        case 188:
        
        case 189:
        
        case 190:
        
        case 191:
        
        case 192:
        
        case 193:
        
        case 194:
        
        case 195:
        
        case 196:
        
        case 197:
        
        case 198:
        
        case 199:
        
        case 200:
        
        case 201:
        
        case 202:
        
        case 203:
        
        case 204:
        
        case 205:
        
        case 206:
        
        case 207:
        
        case 208:
        
        case 209:
        
        case 210:
        
        case 211:
        
        case 212:
        
        case 213:
        
        case 214:
        
        case 215:
        
        case 216:
        
        case 217:
        
        case 218:
        
        case 219:
        
        case 220:
        
        case 221:
        
        case 222:
        
        case 223:
        
        case 224:
        
        case 225:
        
        case 226:
        
        case 227:
        
        case 228:
        
        case 229:
        
        case 230:
        
        case 231:
        
        case 232:
        
        case 233:
        
        case 234:
        
        case 235:
        
        case 236:
        
        case 237:
        
        case 238:
        
        case 239:
        
        case 240:
        
        case 241:
        
        case 242:
        
        case 243:
        
        case 244:
        
        case 245:
        
        case 246:
        
        case 247:
        
        case 248:
        
        case 249:
        
        case 250:
        
        case 251:
        
        case 252:
        
        case 253:
        
        case 254:
        
        default:
          break;
      } 
      char c = '';
      int j = (paramInt2 & 0xFF) - c;
      if (j < 0)
        j += 256; 
      int k = ((paramInt2 & 0xFFFF) >>> 8) - c;
      if (k < 0)
        k += 256; 
      for (byte b = 0; b < arrayOfChar.length; b++) {
        int m = b % 2;
        if (m == 0) {
          arrayOfChar[b] = (char)(arrayOfChar[b] ^ j);
          j = ((j >>> 3 | j << 5) ^ arrayOfChar[b]) & 0xFF;
        } else {
          arrayOfChar[b] = (char)(arrayOfChar[b] ^ k);
          k = ((k >>> 3 | k << 5) ^ arrayOfChar[b]) & 0xFF;
        } 
      } 
      b[i] = (new String(arrayOfChar)).intern();
    } 
    return b[i];
  }
}


/* Location:              C:\Program Files\BurpSuitePro\burpsuite_pro.jar!\burp\Zrkw.class
 * Java compiler version: 21 (65.0)
 * JD-Core Version:       1.1.3
 */