package burp;

import java.time.Duration;
import java.util.Locale;

public interface Zrmh extends Zgpi<Zrmh>, Zxft, Zm3g {
  public static final Zkla Zc;
  
  public static final String[] a;
  
  public static final String[] b;
  
  void ZM(boolean paramBoolean);
  
  void ZU(boolean paramBoolean);
  
  void ZB(boolean paramBoolean);
  
  void ZR(int paramInt);
  
  void Zz(Zbq0 paramZbq0);
  
  void Z_(boolean paramBoolean);
  
  void Zr(int paramInt);
  
  void ZH(int paramInt);
  
  void ZT(int paramInt);
  
  void Zx(int paramInt);
  
  void Zu(int paramInt);
  
  void ZE(int paramInt);
  
  void ZD(int paramInt);
  
  void Zi(int paramInt);
  
  void Zq(int paramInt);
  
  void ZI(int paramInt);
  
  void Ze(int paramInt);
  
  void Zg(Duration paramDuration);
  
  void Zv(Duration paramDuration);
  
  void ZA(Duration paramDuration);
  
  void ZC(int paramInt);
  
  void Zv(int paramInt);
  
  void ZO(int paramInt);
  
  void Zg(boolean paramBoolean);
  
  void ZO(boolean paramBoolean);
  
  void Z_(String paramString);
  
  void ZV(boolean paramBoolean);
  
  void Zx(boolean paramBoolean);
  
  default void Zd(Zmf_ paramZmf_) {
    // Byte code:
    //   0: aload_0
    //   1: aload_1
    //   2: sipush #-14784
    //   5: sipush #7021
    //   8: invokestatic a : (II)Ljava/lang/String;
    //   11: aload_0
    //   12: invokeinterface Zz7 : ()I
    //   17: invokeinterface ZA : (Ljava/lang/String;I)I
    //   22: invokeinterface ZR : (I)V
    //   27: invokestatic ZN : ()Ljava/lang/String;
    //   30: aload_0
    //   31: aload_1
    //   32: sipush #-14743
    //   35: sipush #-19921
    //   38: invokestatic a : (II)Ljava/lang/String;
    //   41: aload_0
    //   42: invokeinterface Zzf : ()Z
    //   47: invokeinterface ZC : (Ljava/lang/String;Z)Z
    //   52: invokeinterface ZM : (Z)V
    //   57: astore_2
    //   58: aload_1
    //   59: sipush #-14759
    //   62: sipush #-29731
    //   65: invokestatic a : (II)Ljava/lang/String;
    //   68: aload_0
    //   69: invokeinterface Zzz : ()Lburp/Zbq0;
    //   74: ifnonnull -> 82
    //   77: ldc ''
    //   79: goto -> 91
    //   82: aload_0
    //   83: invokeinterface Zzz : ()Lburp/Zbq0;
    //   88: getfield name : Ljava/lang/String;
    //   91: invokeinterface Zm : (Ljava/lang/String;Ljava/lang/String;)Ljava/lang/String;
    //   96: astore_3
    //   97: aload_3
    //   98: invokestatic Zd : (Ljava/lang/String;)Lburp/Zbq0;
    //   101: astore #4
    //   103: aload_0
    //   104: aload_1
    //   105: sipush #-14760
    //   108: sipush #-4749
    //   111: invokestatic a : (II)Ljava/lang/String;
    //   114: aload_0
    //   115: invokeinterface ZzA : ()Z
    //   120: invokeinterface ZC : (Ljava/lang/String;Z)Z
    //   125: invokeinterface Z_ : (Z)V
    //   130: aload_0
    //   131: aload #4
    //   133: ifnonnull -> 145
    //   136: aload_0
    //   137: invokeinterface Zzz : ()Lburp/Zbq0;
    //   142: goto -> 147
    //   145: aload #4
    //   147: invokeinterface Zz : (Lburp/Zbq0;)V
    //   152: aload_0
    //   153: aload_1
    //   154: sipush #-14771
    //   157: sipush #-12716
    //   160: invokestatic a : (II)Ljava/lang/String;
    //   163: aload_0
    //   164: invokeinterface Zzv : ()Z
    //   169: invokeinterface ZC : (Ljava/lang/String;Z)Z
    //   174: invokeinterface ZU : (Z)V
    //   179: aload_0
    //   180: aload_1
    //   181: sipush #-14774
    //   184: sipush #32027
    //   187: invokestatic a : (II)Ljava/lang/String;
    //   190: aload_0
    //   191: invokeinterface Zzd : ()Z
    //   196: invokeinterface ZC : (Ljava/lang/String;Z)Z
    //   201: invokeinterface ZB : (Z)V
    //   206: aload_0
    //   207: aload_1
    //   208: getstatic burp/Zk74.CRAWLER__CRAWL_OPTIMIZATION__LINK_FINGERPRINT_TRIGGER : Lburp/Zk74;
    //   211: invokevirtual ZE : ()Ljava/lang/String;
    //   214: aload_0
    //   215: invokeinterface ZzR : ()I
    //   220: invokeinterface ZA : (Ljava/lang/String;I)I
    //   225: invokeinterface Zr : (I)V
    //   230: aload_0
    //   231: aload_1
    //   232: sipush #-14783
    //   235: sipush #21518
    //   238: invokestatic a : (II)Ljava/lang/String;
    //   241: aload_0
    //   242: invokeinterface ZzR : ()I
    //   247: invokeinterface ZA : (Ljava/lang/String;I)I
    //   252: invokeinterface Zr : (I)V
    //   257: aload_0
    //   258: aload_1
    //   259: sipush #-14732
    //   262: sipush #29050
    //   265: invokestatic a : (II)Ljava/lang/String;
    //   268: aload_0
    //   269: invokeinterface Zz2 : ()I
    //   274: invokeinterface ZA : (Ljava/lang/String;I)I
    //   279: invokeinterface ZH : (I)V
    //   284: aload_0
    //   285: aload_1
    //   286: sipush #-14773
    //   289: sipush #-24108
    //   292: invokestatic a : (II)Ljava/lang/String;
    //   295: aload_0
    //   296: invokeinterface ZzU : ()I
    //   301: invokeinterface ZA : (Ljava/lang/String;I)I
    //   306: invokeinterface ZT : (I)V
    //   311: aload_0
    //   312: aload_1
    //   313: getstatic burp/Zk74.CRAWLER__CRAWL_OPTIMIZATION__MAX_SUBMISSIONS_PER_FORM : Lburp/Zk74;
    //   316: invokevirtual ZE : ()Ljava/lang/String;
    //   319: aload_0
    //   320: invokeinterface ZzG : ()I
    //   325: invokeinterface ZA : (Ljava/lang/String;I)I
    //   330: invokeinterface Zx : (I)V
    //   335: aload_0
    //   336: aload_1
    //   337: sipush #-14753
    //   340: sipush #2065
    //   343: invokestatic a : (II)Ljava/lang/String;
    //   346: aload_0
    //   347: invokeinterface ZzG : ()I
    //   352: invokeinterface ZA : (Ljava/lang/String;I)I
    //   357: invokeinterface Zx : (I)V
    //   362: aload_0
    //   363: aload_1
    //   364: getstatic burp/Zk74.CRAWLER__CRAWL_OPTIMIZATION__MAX_UNMATCHED_LINK_TOLERANCE : Lburp/Zk74;
    //   367: invokevirtual ZE : ()Ljava/lang/String;
    //   370: aload_0
    //   371: invokeinterface Zz_ : ()I
    //   376: invokeinterface ZA : (Ljava/lang/String;I)I
    //   381: invokeinterface Zu : (I)V
    //   386: aload_0
    //   387: aload_1
    //   388: sipush #-14740
    //   391: sipush #3563
    //   394: invokestatic a : (II)Ljava/lang/String;
    //   397: aload_0
    //   398: invokeinterface Zz_ : ()I
    //   403: invokeinterface ZA : (Ljava/lang/String;I)I
    //   408: invokeinterface Zu : (I)V
    //   413: aload_0
    //   414: aload_1
    //   415: sipush #-14741
    //   418: sipush #23143
    //   421: invokestatic a : (II)Ljava/lang/String;
    //   424: aload_0
    //   425: invokeinterface Zzn : ()I
    //   430: invokeinterface ZA : (Ljava/lang/String;I)I
    //   435: invokeinterface ZE : (I)V
    //   440: aload_0
    //   441: aload_1
    //   442: sipush #-14727
    //   445: sipush #13327
    //   448: invokestatic a : (II)Ljava/lang/String;
    //   451: aload_0
    //   452: invokeinterface ZzZ : ()I
    //   457: invokeinterface ZA : (Ljava/lang/String;I)I
    //   462: invokeinterface ZD : (I)V
    //   467: aload_0
    //   468: aload_1
    //   469: sipush #-14742
    //   472: sipush #-6826
    //   475: invokestatic a : (II)Ljava/lang/String;
    //   478: aload_0
    //   479: invokeinterface Zz1 : ()I
    //   484: invokeinterface ZA : (Ljava/lang/String;I)I
    //   489: invokeinterface Zi : (I)V
    //   494: aload_0
    //   495: aload_1
    //   496: sipush #-14764
    //   499: sipush #13660
    //   502: invokestatic a : (II)Ljava/lang/String;
    //   505: aload_0
    //   506: invokeinterface Zzx : ()I
    //   511: invokeinterface ZA : (Ljava/lang/String;I)I
    //   516: invokeinterface Zq : (I)V
    //   521: aload_0
    //   522: aload_1
    //   523: sipush #-14749
    //   526: sipush #7717
    //   529: invokestatic a : (II)Ljava/lang/String;
    //   532: aload_0
    //   533: invokeinterface Zzi : ()I
    //   538: invokeinterface ZA : (Ljava/lang/String;I)I
    //   543: invokeinterface ZI : (I)V
    //   548: aload_0
    //   549: aload_1
    //   550: sipush #-14768
    //   553: sipush #-15146
    //   556: invokestatic a : (II)Ljava/lang/String;
    //   559: aload_0
    //   560: invokeinterface Zzy : ()I
    //   565: invokeinterface ZA : (Ljava/lang/String;I)I
    //   570: invokeinterface Ze : (I)V
    //   575: aload_1
    //   576: sipush #-14734
    //   579: sipush #28242
    //   582: invokestatic a : (II)Ljava/lang/String;
    //   585: invokeinterface Zh : (Ljava/lang/String;)Z
    //   590: ifeq -> 667
    //   593: aload_0
    //   594: aload_1
    //   595: sipush #-14777
    //   598: sipush #-17930
    //   601: invokestatic a : (II)Ljava/lang/String;
    //   604: aload_0
    //   605: invokeinterface Zz8 : ()Ljava/time/Duration;
    //   610: invokevirtual toMillis : ()J
    //   613: l2i
    //   614: invokeinterface ZA : (Ljava/lang/String;I)I
    //   619: i2l
    //   620: invokestatic ofMillis : (J)Ljava/time/Duration;
    //   623: invokeinterface Zg : (Ljava/time/Duration;)V
    //   628: aload_0
    //   629: aload_1
    //   630: sipush #-14777
    //   633: sipush #-17930
    //   636: invokestatic a : (II)Ljava/lang/String;
    //   639: aload_0
    //   640: invokeinterface Zzq : ()Ljava/time/Duration;
    //   645: invokevirtual toMillis : ()J
    //   648: l2i
    //   649: invokeinterface ZA : (Ljava/lang/String;I)I
    //   654: i2l
    //   655: invokestatic ofMillis : (J)Ljava/time/Duration;
    //   658: invokeinterface Zv : (Ljava/time/Duration;)V
    //   663: aload_2
    //   664: ifnonnull -> 737
    //   667: aload_0
    //   668: aload_1
    //   669: sipush #-14776
    //   672: sipush #18544
    //   675: invokestatic a : (II)Ljava/lang/String;
    //   678: aload_0
    //   679: invokeinterface Zz8 : ()Ljava/time/Duration;
    //   684: invokevirtual toMillis : ()J
    //   687: l2i
    //   688: invokeinterface ZA : (Ljava/lang/String;I)I
    //   693: i2l
    //   694: invokestatic ofMillis : (J)Ljava/time/Duration;
    //   697: invokeinterface Zg : (Ljava/time/Duration;)V
    //   702: aload_0
    //   703: aload_1
    //   704: sipush #-14762
    //   707: sipush #-5238
    //   710: invokestatic a : (II)Ljava/lang/String;
    //   713: aload_0
    //   714: invokeinterface Zzq : ()Ljava/time/Duration;
    //   719: invokevirtual toMillis : ()J
    //   722: l2i
    //   723: invokeinterface ZA : (Ljava/lang/String;I)I
    //   728: i2l
    //   729: invokestatic ofMillis : (J)Ljava/time/Duration;
    //   732: invokeinterface Zv : (Ljava/time/Duration;)V
    //   737: aload_0
    //   738: aload_1
    //   739: sipush #-14778
    //   742: sipush #8606
    //   745: invokestatic a : (II)Ljava/lang/String;
    //   748: aload_0
    //   749: invokeinterface ZzL : ()Ljava/time/Duration;
    //   754: invokevirtual toMillis : ()J
    //   757: l2i
    //   758: invokeinterface ZA : (Ljava/lang/String;I)I
    //   763: i2l
    //   764: invokestatic ofMillis : (J)Ljava/time/Duration;
    //   767: invokeinterface ZA : (Ljava/time/Duration;)V
    //   772: aload_0
    //   773: aload_1
    //   774: sipush #-14736
    //   777: sipush #10106
    //   780: invokestatic a : (II)Ljava/lang/String;
    //   783: aload_0
    //   784: invokeinterface ZzO : ()I
    //   789: invokeinterface ZA : (Ljava/lang/String;I)I
    //   794: invokeinterface ZC : (I)V
    //   799: aload_0
    //   800: aload_1
    //   801: sipush #-14767
    //   804: sipush #-18603
    //   807: invokestatic a : (II)Ljava/lang/String;
    //   810: aload_0
    //   811: invokeinterface ZzE : ()I
    //   816: invokeinterface ZA : (Ljava/lang/String;I)I
    //   821: invokeinterface Zv : (I)V
    //   826: aload_0
    //   827: aload_1
    //   828: sipush #-14739
    //   831: sipush #-7149
    //   834: invokestatic a : (II)Ljava/lang/String;
    //   837: aload_0
    //   838: invokeinterface ZzC : ()I
    //   843: invokeinterface ZA : (Ljava/lang/String;I)I
    //   848: invokeinterface ZO : (I)V
    //   853: aload_0
    //   854: aload_1
    //   855: sipush #-14728
    //   858: sipush #-13323
    //   861: invokestatic a : (II)Ljava/lang/String;
    //   864: aload_0
    //   865: invokeinterface Zzl : ()Z
    //   870: invokeinterface ZC : (Ljava/lang/String;Z)Z
    //   875: invokeinterface Zg : (Z)V
    //   880: aload_0
    //   881: aload_1
    //   882: sipush #-14735
    //   885: sipush #23350
    //   888: invokestatic a : (II)Ljava/lang/String;
    //   891: aload_0
    //   892: invokeinterface Zzu : ()Z
    //   897: invokeinterface ZC : (Ljava/lang/String;Z)Z
    //   902: invokeinterface ZO : (Z)V
    //   907: aload_0
    //   908: aload_1
    //   909: sipush #-14761
    //   912: sipush #21799
    //   915: invokestatic a : (II)Ljava/lang/String;
    //   918: aload_0
    //   919: invokeinterface ZzF : ()Ljava/lang/String;
    //   924: invokeinterface Zm : (Ljava/lang/String;Ljava/lang/String;)Ljava/lang/String;
    //   929: invokeinterface Z_ : (Ljava/lang/String;)V
    //   934: aload_0
    //   935: aload_1
    //   936: sipush #-14750
    //   939: sipush #-13778
    //   942: invokestatic a : (II)Ljava/lang/String;
    //   945: aload_0
    //   946: invokeinterface ZzS : ()Z
    //   951: invokeinterface ZC : (Ljava/lang/String;Z)Z
    //   956: invokeinterface ZV : (Z)V
    //   961: aload_0
    //   962: aload_1
    //   963: sipush #-14722
    //   966: sipush #-14401
    //   969: invokestatic a : (II)Ljava/lang/String;
    //   972: aload_0
    //   973: invokeinterface Zzo : ()Z
    //   978: invokeinterface ZC : (Ljava/lang/String;Z)Z
    //   983: invokeinterface Zx : (Z)V
    //   988: return
  }
  
  default void Zl(Zg4j paramZg4j) {
    paramZg4j.ZD(a(-14769, -7468), Zz7());
    paramZg4j.Zh(a(-14744, 4196), Zzf());
    paramZg4j.Za(a(-14782, -5923), (Zzz() == null) ? "" : (Zzz()).name.toLowerCase(Locale.ENGLISH));
    paramZg4j.Zh(a(-14772, 16523), ZzA());
    paramZg4j.Zh(a(-14721, 13400), Zzv());
    paramZg4j.Zh(a(-14730, -10440), Zzd());
    paramZg4j.ZD(a(-14763, 32048), ZzR());
    paramZg4j.ZD(a(-14781, -1827), Zz2());
    paramZg4j.ZD(a(-14729, 18042), ZzG());
    paramZg4j.ZD(a(-14737, -10896), Zz_());
    paramZg4j.Zh(a(-14731, 8174), Zzu());
    paramZg4j.Za(a(-14779, 11721), ZzF());
    paramZg4j.ZD(a(-14758, 10362), Zzn());
    paramZg4j.ZD(a(-14775, -12363), ZzZ());
    paramZg4j.ZD(a(-14733, 21534), Zz1());
    paramZg4j.ZD(a(-14725, -27300), Zzx());
    paramZg4j.ZD(a(-14754, -634), Zzi());
    paramZg4j.ZD(a(-14766, 12561), Zzy());
    paramZg4j.ZD(a(-14723, -32329), (int)Zz8().toMillis());
    paramZg4j.ZD(a(-14757, 24151), (int)Zzq().toMillis());
    paramZg4j.ZD(a(-14724, 7050), (int)ZzL().toMillis());
    paramZg4j.ZD(a(-14770, -32064), ZzU());
    paramZg4j.ZD(a(-14755, -16676), ZzO());
    paramZg4j.ZD(a(-14765, 21056), ZzE());
    paramZg4j.ZD(a(-14756, -18313), ZzC());
    paramZg4j.Zh(a(-14726, -18052), Zzl());
    paramZg4j.Zh(a(-14780, 31439), ZzS());
    paramZg4j.Zh(a(-14738, 9250), Zzo());
  }
  
  default void Za(Zbq0 paramZbq0) {
    if (paramZbq0 != null && !ZzA()) {
      ZU(paramZbq0.incyWincy);
      ZB(paramZbq0.useAccessibleTextForVisibleText);
      Zr(paramZbq0.incomingNavigableSignpostFingerprintingThreshold);
      ZH(paramZbq0.incomingClickableSignpostFingerprintingThreshold);
      ZT(paramZbq0.loopbackSignpostFingerprintingThreshold);
      Zx(paramZbq0.minimumKeyRingSizeBeforeDiscontinuationStrategyApplied);
      Zu(paramZbq0.totalUnmatchedSignpostTolerance);
      ZE(paramZbq0.unmatchedAnchorTolerance);
      ZD(paramZbq0.unmatchedIFrameTolerance);
      Zi(paramZbq0.unmatchedFrameTolerance);
      Zq(paramZbq0.unmatchedFormTolerance);
      ZI(paramZbq0.unmatchedRedirectTolerance);
      Ze(paramZbq0.unmatchedImageAreaMapTolerance);
      Zg(paramZbq0.networkIdleThreshold);
      Zv(paramZbq0.domIdleThreshold);
      ZA(paramZbq0.awaitNavigationTimeout);
      ZC(paramZbq0.maximumNumberOfKeysGeneratedPerSignpost);
      Zv(paramZbq0.roomDiscoveryKeyRingDiscontinuationThreshold);
      ZO(paramZbq0.maximumNumberOfKeysGeneratedPerNavigationalControl);
      Zg(paramZbq0.alwaysSubmitGuessKeys);
      Zx(true);
    } 
  }
  
  default void ZC(Ze72 paramZe72) {
    Zbq0 zbq0 = (Zzz() == null) ? Zbq0.NORMAL : Zzz();
    paramZe72.Zx(zbq0, ZzA());
    paramZe72.ZK(this::lambda$configureCrawlerTuning$0);
    paramZe72.ZP(Zzf());
    paramZe72.Zp(Zzv());
    paramZe72.Ze(Zzd());
    paramZe72.ZY(ZzR());
    paramZe72.Ze(Zz2());
    paramZe72.ZC(ZzU());
    paramZe72.Zb(ZzG());
    paramZe72.Ze((new Zlne()).Zs(Zz_()).ZB(Zzn()).ZP(ZzZ()).ZQ(Zzx()).Zc(Zzi()).Zo(Zz1()).ZT(Zzy()).ZO());
    paramZe72.Zz(Zz8());
    paramZe72.ZT(Zzq());
    paramZe72.Zj(ZzL());
    paramZe72.Zm(ZzO());
    paramZe72.Zu(ZzE());
    paramZe72.ZH(ZzC());
    paramZe72.Za(Zzl());
    paramZe72.Zx(ZzS());
    paramZe72.ZR(Zzo());
  }
  
  private Integer lambda$configureCrawlerTuning$0() {
    return Integer.valueOf(Zz7() + 1);
  }
  
  static {
    // Byte code:
    //   0: bipush #58
    //   2: anewarray java/lang/String
    //   5: astore #5
    //   7: iconst_0
    //   8: istore_3
    //   9: ldc 'iÂ½ÃœÂšÂ¬oSÂºÂ¢ÂƒÂšÃ¼Â­8ÂœÃ¥Â†Â¸Â™bjÃ¤%9)Â«6Â©%;WÃªÃ˜QÂŸ$Â Â…Â£=ÂŸÂ½ÃŒFÂ´Ã¿Âª9Ã¯Â”Âºx>Â Â³ÃŒÃ­Â¨Ã«\\\bÂ¤'Ã³Â…Ã• ÃÂ Ã„rÂ³ÃšÂ¤Â¼Ã¬/xÃ˜DOq?Ã‹Âƒ8oÂ‹Â¦Â¾Âœe3Â¯Ã²?)[Ã±TÃÂ§ÃÃˆN+"I-Â†iwÂ€uÃ¶Â»Ãš>.Ã¨Ã£zÃ·Ã¤V:Â¥\\t'8vÂ–Âµ4Ã§Ã©ÃƒÃŒUÂ®Â–Â…Âªdf+cÂ©Ã‹Â˜Ã¢ÃµIÂº`"#b#Ã˜Ã›Ãª"2\\nÃ•X(Âš~(Ã›ÃŒVÂŒÂ´ÃÃ’"sDAp1R}]iÃ¼Ã¥KÃ»ÂƒÃŸ\lkiÂ«XZ-,Ã )ÂºÃ¼Ã¨Â•Ã%Ã¶FSÂ°Ã“Â“Â†Â¶EÂšÂ³Ã´zÂ³_Ã¨rÃ¼<iSÃ´ÃÃpf&"?nÂ“Ã²ÂƒsGR.\\rwÃ¦Âµ/zBÃ¢Ã“ÂºoSÂ¤Â»Ã…Ã™Â©Â‹@Ã‘5\Âc8g:Â§N3Ã©Â»Â®xn&ÃƒÃƒ$=Ã°Ã±Ã€,F`Â¡4wÂœÂ¾Ã”Ã«\*CÂ‘/Ã˜ÂŒÂ´]1Â½&Â¢Ã€mÂŒÂ‹Ã¶uÂ²Ã›Ã¶FÂ¸Ã£ÂÂ¯Â›Â oÃ½Ã€ lÂ¶Ãˆ]Â­Â‰:.Â™ÃºÃ‚ror+Â­Ã·Ã²7-*Ã¨Ã›Ã»n{Â„Â¿eÂÃÂ¹\\tBÂuVÂ…Mc 9kJÂ§Ãƒ\\b|Â•Â•7clÃ¢bfG5BÂ”Â­2Â˜q/Ã¨Â²Ã•Â‚Ã½ÂºÃ–Ã¸Â¸oÂŒÂ„eÃ™Ã™Ã¥Ã‰Ã©ÂÃ¤Â†WLÂ–LMRFpÃƒÃ›Ã¥F|Ã°ÂƒÂ¬nÂ¨Â“ÂÂÃ\Â‹Â‡ÃµÃ¾Ã­Ã\\nAp$1uÂ™]ÃµÃ¼vKÂ‰ÂƒXÃŸÃ‡\ULÂÂ«Ã„ZÂ¾,Â¶.fÂ°l+Ã«NÃ©ÃšÃ£Â†AÂ›!Â´C\\r`Â¨ÃÃ¬fÂ¹ZSÂ­*Â€Â¸Ã™BÂ·!Ã‰Ã•ÂÂ¾wÂ€&Ã„ÂƒrÃ¡Ã¯Â›PÃ¨Ã¬\\bÂ™HF&Ã®Â£Â·Ã‘&Â„8Â¹3Â«Â°ÃœÃtÂƒÂ…Â¥-ÃŠ_Â…Ã“Â¼ÃˆÃ£Ã¢TÂ¼>ÃµO:Ã§Ã½5AÂ›Ã±LÃÂ¤ÃÂ¨B+Âœ"y-Â€iÂ·Â€mÃ¶Â¸Ãš^.Ã¤Ã£Ã»Ã”Ã¯Ã‚Ã€>3SÂ´ÂÃ®\\t8LÂŠNjÂ£Â‹}Â­VÃ‰Ã®Â¯Ã¤Ã­OzÂ´ÃÃµÃ§Â±2,AGÃÃ…DÃ¯@)OÃÂ€VÃœm66 Ã“ 3uIÂˆNqlÂ 9LÃaÂŠÃ¢Â„Â—Â¡Ã»KÂŒ-Ã‰Ã¼ÃˆÂ².jÂ¨Â—R#Â¬Â¨2Â¸ÃÃ±Â®:Âœ2Â¼`Ã°dÂ»Ã»3Â£Â…V/hÃ?.Â´Ã„!8Â]Ã¬ZÂ°|*IÃ¡Â–{8Â¨\\fÂ²,ÃcÂ¬hÃœxÂ´)Ã±EÂ/ÃÂ£Ã•bÃ‘NÃ´aÂno0Ã¼Ã„ZÂ»+Âˆ{\\nÂƒk;ÂŠÃ•nKÃ ^ \\rSiÂ¾j=$\\bHÂ¦Â¤OrÃ¼JÃ–<ÃµÂ¡Ã™UÂgÃ£Ã‘Ã—Ã°f)^nÃ‚\\nlÂ–ÂÂ’Â‘Ã®Â¸Ã±Ã¼fÂ˜Â¿5`AÃ©@Ã¹m\\bÂ‘Ã‡e0xAÃ¥AÃ¤Ã…1#Ã€qgÃ¶ÃƒÃ¸Fikw~hF|Âª`C;Â§Â›8{Ã•[Â•1Ã“VÃ¢"Âš5ÂŠÃ©ÂŸ?Â¬&Âª5xÂ‘3Ã´1VÃ²ÂÂ´Ã˜9Ã—Â€WÂ‹\\fdÂ…Ã…Ã…Â—ÂÂ•ÂªÃ£rnÂ•(wX\.NÃ¡I-Âµ|eÂˆÂˆFe1y=H`Ã¯ÃœÃ´Ã˜qÃ³ÃŠl=Â¸Ã¢(Â­(Â‚9Â–pÃšÂ±Ã©Â™Ã±Â”Â“\\tÂ”4Â–ÃÂ§Ã–Ã’Â½;Ã—Ã¶ZÃ£-W18ÃÂ€\\n-\\nÂ¬Â†Â®(Â¥uÂ”`Â•Ã›Ã¯3OÃ†ÃªLÂ—1W^Ã¦TÃ LKAÂ½o]Â„\'&"Ãº@}Ã­Â‰ÃšSÃ´ÂµqÂ™Ã‰ÃµlfÃ´Ã»,\\tÃ¶ÂˆÃ–ÃÂŸÃºÂº-WUÃ•[Â—\ÃMÂakJÃ¦L{$Ã´bÂ‹H8|(Â©bTÃ§:Â‰Ã§\\fÂšÂªÃÂ€Â…PtÂš;AjÃœrjczPÂ‰]Ã¹xf FÂ­SSnÂ¦Â¸Ã»1FÂ¦NwÂ“Ã½Ã´6Ã¯Â¤qÂ¡\\rnÂœÃ¡\Ã‰Ã¹Ã˜\\tA@XÂÃ£AÂ¢Ã¼Â%Ã²ÃÂƒÃ±Â%Â¾@Ã¨Ã¹0\\b:Ã‡0Ã–A0AÂ©Ã¤Â’1Ã‰Ã€,ÃŒÃ¶Â¶Ã¸Â±zÂ’`Ã™Ã¦ÃŠÂš_Â4ÃdÂ„}Â½Â˜Â‹Ã•&r\\tÃ¨HÂ²Ã…Ã±Â¥DÂ¡ÂŒ}Ã¤Â€Âºw8VaÃÂ·ÃÂ¯uÂ»=n5\ÃÃ°Â¯Ã—Ã˜Ã¯eÂ¡Ã¨Â¯4Ãµ=XA4Ã™Â«\\fIG~ CÂ‰ÂÃ¬t0Ã Â·Â¿vÃ˜Ã¨|r) Ã¶Â‘Â¼ÂÃ™Â•Ã…Ã•pRgÂ’]MÃ·;Â›Ã’XÃ·N.ÂŠj?Ã¤Ã„/r)ÃºÂ³`Â‡!Ã‡>T^Â¦!Â½Â‹{Ã–Ã‚AÂ¾=Ã“Ã®Ã²Ã‡9Â—ÂŸÂ”Ã©\\tÃ·xÂ‘AÂ¡1Â¦Â·Â¯8Â»\\tHÃ$-Â¸c@Â¤ÃœÃ“qÂÂ®Â—xiÃ©89NRÃ¦lÂ»Ã­Ã”:Ã¤Ã°6uÃ„`0D=uÂ¶lÂ’Â¶!,Ã±Â@A-Ã­+Â‚Â”}Â¥Â“r%Â†pÂ—Ã¤Â›3Â¿ÃZÂ£Â­aÂ±eCÂƒNÂ¨IÂ¥\Â¶Ã¤Ã½jÃ¼Ã˜oÂ²Â“Ã¯Ã‡Âº2Ã¯XÃ‚ÃºuhÂ’Ã‹Â±tqdG#$Ãƒ)Ã£Ãƒi|dÃºÂ£yJÃŒiE)3fÃ´2Ã¿Â’Ã©Â¬Ã)P"|Ã_3Ã°!Ã‘\\t\\rgÃ´$JÃƒÂ£Ã›Ã®Ãœp Ã¨Ã«VRÃ¬-Ã°:Â¢Ã„CÃ‡\\fnRÂ¥xÂ¿Ãšq<ÂµmÂ¶0(,Â‘A\\rÃ™ÂŒ\\fÂ­GÃ¢ ÂˆCÃ»ÃÃ¬Â½0,Ã Â[vDÃ¨Ã¯}X!Â¿|gÂ"Ã‡ÂcÂ¢Â›ÃªÂ€,(Ã¡:ÃjÂqy*Ã»Â•)Ã©ÂÃ´vÂšÂ‡&ÃŸÃ¢Âœ%*VS Ã Ã¤ÃŒhÂ§!Â§:7CÂ„;Ã«Ã–B+eRÂÂŒEY|leÃ¤PÃ‡Â§cyFfÂ½Ã£Â‘SÃˆÃšlÃ»Â°=Â·uÃ–Âš?nÂ¬Ã„RÂ¬ÂÂ†Ã³Â’Ã‚Ã˜tÃ°Ã–Â©Â¢7a(Ã´OÂ©Ã•Ã³Ã­Â¶iÂ‘Ã‡[WÂ§MY2ÃSÂ½#Ã‚K~Â¥~z)mÂ—UÂ‘2!\\r+\\teÃ˜aÃŠ`qSÂ¢Â·Â±|Tl=}TÂ{?XÃ›Ã,qQiÃ€DÂ·DQ%Â±B#L-Ã¼ÂŠÂ¹6VmzÃ˜Ã¯&Â›Ã¯Ã§/ÂÃ›VFÂÃÃ· Â`Ãƒ,Â¶Â‚\\rhÂ­a!Ã¦7ÂµÂ»Â‰Â†Ã§Â¿:Â ÂÃ€Â¶Ã²Â¿Ã±;Â™ÃŠÂ¨Â¿ Ã³IGÂ§Â‚KÂÂÃ±CÃ†@rHgÃ¢D\qFÃ¿Â„Ã—Ãv$+"d%Ã²zaÂ¾Ã ÃšÃ”Â“N5#ÃÃ‹5Ã@Â‡Ã´ÃªÃ«r[)ÂÃ®Â»7ZÃ°Â°/Â©Ã…\\nIlÂ±ahÃ¸JÃµ ÃˆÂ…Â´+pp\\nG4Ã‡Â ÂŸ|K tgÂÃ·'R&Â¦PÂ¹Ã¨Âª/Â¬Ã¢Ã·1828Â·*ÃyÃ¾xÃ›Â¥Â‘ÃÂwCÂ6Ã•ÂÃÃÃŸÂ¼Â™8Ã¬Ã¨Â²ÃºtÂ“Ã€ÂªabÂ:Â Ã®ÃƒÂ˜Ã‘Â‰3Ã¼Ã’Â²mjkÂ¥Â—Ã³Â¬.2hÃÃ«Â®yÂœZÂ¼mÃ°Ã€Â£<Ã•Â­ÃŸÃÃ•o%KÃ¹bÃªÃŠ:Ã‚Â­X(Ãµ<GMÃ—XÃ—<Ã†AÂÃ %[NfÂŒk<Ã¶aÃ‹(0p)(BdÃ£<\\t'Â‚Â¨Ã„Ã‡Â€WÃµÃ—ÃµÃ³yJÃ¥IB ÃŸÃ¨ÂšÂ‡ÃŒfÃƒÂ³2Â¹Ã¡\\bÃ,ÂÂ¹`*Ã˜Ã±)Â‘Ã©Â•Â)Ã´0ÂšO&Ã†Ã¢Â¿9YÃ·Ã¤OÂŠÃ‘QÂ­Ã”Ã”NÂŒ7qZÃ…ÂÂ±Â—Ã¦*BQwÃ›ÃƒLDOÃŸ!/cNln VÃ¢ÃŸXÂ²~yÃ©H]Â¬%!Ã¼ÃwÃª!ÂÃÂŠÂ–Ã‘Ã¸4Ã0Ã¶1Ã¢Ã Ã”ÂµÃ\Ã’$Â–#Ã¿\\tÃª%Ã‘Â­Ã’Ã¢Ã±Ã¬K=TÃÂ¡Â¿Ã§~Â©Â NjÃ¤Ã¡Â„2&OÃ”Ã‹:AoÃÃ’\\bw6Ã’ \\rÃˆu^DÂ¢'Â˜CÂ¾Ã³1k"$1Â« jÃ§ÂBjÃ·G.ÂŠ\\rÃœÃ™"Â¾Â¸Â‚.KÂ™Ã«Â¨PÂ”9sUÂ˜~ÃŠuÃ„ÂÂ°=?Ã¹. 4-Â±Â™Ã°dÃ–XÂÃ¡ÃšÂ“Â—Ã•_!\\r1Â¥oÃÃ‚?Âº^Ã¡Ã˜.Ã€ ÃY\\tÃ¤Ã¥Â­l0ÂŠ"09Ã“<@EÃ˜Â¡XÃ›\\fÂ¦ÃˆÃ†*\\rÂˆÂÃ Ã¾+Ã£Â£+Â¼Â±ÃÃœs4Â¢!Ã¹Â¿Ã™Ã¢?Â’ÂtÃ–Ã®S[2Â‚Â®Â²Âº-z%e=tÃÃ¶Ã˜Ã¢ÃsÂµ)\L$E#Ã¿FÃªÃŒÃ¬Â­Â»Ã’Ã¼mL8Ã«Â¨Ã³Ãˆ~Ãª'4<7Â˜KMÂ’ÃŒÃ§Â²QÃº!Ã°JÂ·jEÂ§=\%Â´UÂ»ÂKu>fÂ‹ÂˆÂ¾ÃpTÂ•lÂ§Â‰Â½DÂ˜Â®tÂ´%&Ã‘dÃªÃ‹Ã‰Â«Ã\\rcDQÃƒ#Â¿W!@Â Â˜Ã„_ÃYÂº(ÃƒÃ<bÂ‡sCT$ÃLoÃÂ°OÃšNÃ¶R8_Â¢{Â„\\bÃ±ÂªÂ q9H\\fÂST2Â§{Â¿f0Ã¸ÃŒgÃª{Â±Â¬Ã­Â©4oÃ¹Â‘;Ã¶Ã¡5`Â”Ã„FÃŸ"Â’Ã«ÂÃš~Ã€)\\r!Ã¨Q2\\f!Ã®ÂœÂ»Â‰Ã¬Ã»Ã‚Ã‹Â™uÂ–Â£lnnVMÂ—Â‚\\bÃÂ»Â„LÂ§Tlj;~ÃÃ°*3rZÂˆÃ™W| Ã¦Â¯RÂ¯Ã‘/fÂ¬Â¹Âº0MÂ¾ÃÃbsÃ±Â»L1~+qÃL"\\t\\nÃ™ÃÂÂ¦Ã£Â¼Â‡q{<UÂŒÂ•`ÂŸ;ÃÂ¡Â®Ã¼Ã˜ÃŠrÃ¶Â‚yÃ½Â´YÂƒ/9Â\\b4fÃ¾iYÂŸÃ­Â¿Ãˆ`Ã“Ã©Ã®Â£|Ãš8ÃÂ‡ÃŠAÂªÃŠÂŠÂµ0,*Â¹ÃŒmÃ¦Ã‘/ÃƒÂµGGÃ…ÃŸÂ„=Ã‡o,Âªo<BKÃ¯Ã„f~Ã™Ã‹r\\faÂ§KÂœÃ‘'Ã¤Ã·Â‡j\Âg(hÃ¯~Ã6Ã¾Â¤:ÃŒÂ—Â¦Ã¹W,7M2Ã®Â¬Â´:ZÃ Ã¦Â‡:Ã¥CÃµÂ‘Â…UÃ‘ÂŠUÃ±Â—XÃ™ÂŒÃ¨HldÃ¿bÃŸÂ°Ã¿Â‚Ã¥Ã³9?Ã‚Ã§ÃšaiÃ•<ÂÂ Â7Ã¯ ÂªÃŒÂÃÃšÂ²Ã´Âš9Ã¾Â¼9Â‚#\\fÃ¦Ã¸yÂ™ÂÂ­Â¼Ã€ Ã’Ã¥Ã"xÃªÂ¸Ã›Â—\\nCÂ²OÃ‰Â‚Ã•1 \\n8Ãˆ]fÃ—'
    //   11: dup
    //   12: astore_2
    //   13: invokevirtual length : ()I
    //   16: istore #4
    //   18: bipush #45
    //   20: istore_1
    //   21: iconst_m1
    //   22: istore_0
    //   23: bipush #103
    //   25: iinc #0, 1
    //   28: aload_2
    //   29: iload_0
    //   30: dup
    //   31: iload_1
    //   32: iadd
    //   33: invokevirtual substring : (II)Ljava/lang/String;
    //   36: iconst_m1
    //   37: goto -> 143
    //   40: aload #5
    //   42: swap
    //   43: iload_3
    //   44: iinc #3, 1
    //   47: swap
    //   48: aastore
    //   49: iload_0
    //   50: iload_1
    //   51: iadd
    //   52: dup
    //   53: istore_0
    //   54: iload #4
    //   56: if_icmpge -> 68
    //   59: aload_2
    //   60: iload_0
    //   61: invokevirtual charAt : (I)C
    //   64: istore_1
    //   65: goto -> 23
    //   68: ldc 'Â‰Ã¢4Â—Â‘Ã¿4Ã«Â’Â“/Â¢Â¶Ã Â¥Â“Â®ÂÃ«Ã‚2MZÃ´ÂˆÂ®Â‹Ã’-KÂÂ¼rÂ‘Â¥CÂ‡Â•ÃªUÃ´ÂŸÃ Ã—!Âœ[ÃÃ¦n$Ã¥Ã cO,Ã‹C|Â£Â˜yÃ“ÃÂˆl2ÃÃ“-Ã§2]ÂšÂ„mÃ£Ã¢i@pKÂÃ¥Â˜Â—Ã£BÂ¢Â¢ÂšPEcÂŒÂ•Â¯Ãª'
    //   70: dup
    //   71: astore_2
    //   72: invokevirtual length : ()I
    //   75: istore #4
    //   77: bipush #63
    //   79: istore_1
    //   80: iconst_m1
    //   81: istore_0
    //   82: bipush #126
    //   84: iinc #0, 1
    //   87: aload_2
    //   88: iload_0
    //   89: dup
    //   90: iload_1
    //   91: iadd
    //   92: invokevirtual substring : (II)Ljava/lang/String;
    //   95: iconst_0
    //   96: goto -> 143
    //   99: aload #5
    //   101: swap
    //   102: iload_3
    //   103: iinc #3, 1
    //   106: swap
    //   107: aastore
    //   108: iload_0
    //   109: iload_1
    //   110: iadd
    //   111: dup
    //   112: istore_0
    //   113: iload #4
    //   115: if_icmpge -> 127
    //   118: aload_2
    //   119: iload_0
    //   120: invokevirtual charAt : (I)C
    //   123: istore_1
    //   124: goto -> 82
    //   127: aload #5
    //   129: putstatic burp/Zrmh.a : [Ljava/lang/String;
    //   132: bipush #58
    //   134: anewarray java/lang/String
    //   137: putstatic burp/Zrmh.b : [Ljava/lang/String;
    //   140: goto -> 300
    //   143: dup_x2
    //   144: pop
    //   145: invokevirtual toCharArray : ()[C
    //   148: dup_x1
    //   149: arraylength
    //   150: dup_x2
    //   151: pop
    //   152: iconst_0
    //   153: istore #6
    //   155: dup2_x1
    //   156: pop2
    //   157: dup_x2
    //   158: iconst_1
    //   159: if_icmpgt -> 259
    //   162: dup2
    //   163: swap
    //   164: iload #6
    //   166: dup2_x1
    //   167: caload
    //   168: swap
    //   169: iload #6
    //   171: bipush #7
    //   173: irem
    //   174: tableswitch default -> 241, 0 -> 212, 1 -> 217, 2 -> 221, 3 -> 226, 4 -> 231, 5 -> 236
    //   212: bipush #103
    //   214: goto -> 243
    //   217: iconst_2
    //   218: goto -> 243
    //   221: bipush #54
    //   223: goto -> 243
    //   226: bipush #113
    //   228: goto -> 243
    //   231: bipush #65
    //   233: goto -> 243
    //   236: bipush #110
    //   238: goto -> 243
    //   241: bipush #12
    //   243: ixor
    //   244: ixor
    //   245: i2c
    //   246: castore
    //   247: iinc #6, 1
    //   250: dup
    //   251: ifne -> 259
    //   254: dup2
    //   255: dup_x1
    //   256: goto -> 166
    //   259: dup2_x1
    //   260: pop2
    //   261: dup_x2
    //   262: iload #6
    //   264: if_icmpgt -> 162
    //   267: pop
    //   268: new java/lang/String
    //   271: dup_x1
    //   272: swap
    //   273: invokespecial <init> : ([C)V
    //   276: invokevirtual intern : ()Ljava/lang/String;
    //   279: swap
    //   280: pop
    //   281: swap
    //   282: tableswitch default -> 40, 0 -> 99
    //   300: new burp/Zkla
    //   303: dup
    //   304: invokespecial <init> : ()V
    //   307: putstatic burp/Zrmh.Zc : Lburp/Zkla;
    //   310: return
  }
  
  private static String a(int paramInt1, int paramInt2) {
    int i = (paramInt1 ^ 0xFFFFC65B) & 0xFFFF;
    if (b[i] == null) {
      char[] arrayOfChar = a[i].toCharArray();
      switch (arrayOfChar[0] & 0xFF) {
        case 0:
        
        case 1:
        
        case 2:
        
        case 3:
        
        case 4:
        
        case 5:
        
        case 6:
        
        case 7:
        
        case 8:
        
        case 9:
        
        case 10:
        
        case 11:
        
        case 12:
        
        case 13:
        
        case 14:
        
        case 15:
        
        case 16:
        
        case 17:
        
        case 18:
        
        case 19:
        
        case 20:
        
        case 21:
        
        case 22:
        
        case 23:
        
        case 24:
        
        case 25:
        
        case 26:
        
        case 27:
        
        case 28:
        
        case 29:
        
        case 30:
        
        case 31:
        
        case 32:
        
        case 33:
        
        case 34:
        
        case 35:
        
        case 36:
        
        case 37:
        
        case 38:
        
        case 39:
        
        case 40:
        
        case 41:
        
        case 42:
        
        case 43:
        
        case 44:
        
        case 45:
        
        case 46:
        
        case 47:
        
        case 48:
        
        case 49:
        
        case 50:
        
        case 51:
        
        case 52:
        
        case 53:
        
        case 54:
        
        case 55:
        
        case 56:
        
        case 57:
        
        case 58:
        
        case 59:
        
        case 60:
        
        case 61:
        
        case 62:
        
        case 63:
        
        case 64:
        
        case 65:
        
        case 66:
        
        case 67:
        
        case 68:
        
        case 69:
        
        case 70:
        
        case 71:
        
        case 72:
        
        case 73:
        
        case 74:
        
        case 75:
        
        case 76:
        
        case 77:
        
        case 78:
        
        case 79:
        
        case 80:
        
        case 81:
        
        case 82:
        
        case 83:
        
        case 84:
        
        case 85:
        
        case 86:
        
        case 87:
        
        case 88:
        
        case 89:
        
        case 90:
        
        case 91:
        
        case 92:
        
        case 93:
        
        case 94:
        
        case 95:
        
        case 96:
        
        case 97:
        
        case 98:
        
        case 99:
        
        case 100:
        
        case 101:
        
        case 102:
        
        case 103:
        
        case 104:
        
        case 105:
        
        case 106:
        
        case 107:
        
        case 108:
        
        case 109:
        
        case 110:
        
        case 111:
        
        case 112:
        
        case 113:
        
        case 114:
        
        case 115:
        
        case 116:
        
        case 117:
        
        case 118:
        
        case 119:
        
        case 120:
        
        case 121:
        
        case 122:
        
        case 123:
        
        case 124:
        
        case 125:
        
        case 126:
        
        case 127:
        
        case 128:
        
        case 129:
        
        case 130:
        
        case 131:
        
        case 132:
        
        case 133:
        
        case 134:
        
        case 135:
        
        case 136:
        
        case 137:
        
        case 138:
        
        case 139:
        
        case 140:
        
        case 141:
        
        case 142:
        
        case 143:
        
        case 144:
        
        case 145:
        
        case 146:
        
        case 147:
        
        case 148:
        
        case 149:
        
        case 150:
        
        case 151:
        
        case 152:
        
        case 153:
        
        case 154:
        
        case 155:
        
        case 156:
        
        case 157:
        
        case 158:
        
        case 159:
        
        case 160:
        
        case 161:
        
        case 162:
        
        case 163:
        
        case 164:
        
        case 165:
        
        case 166:
        
        case 167:
        
        case 168:
        
        case 169:
        
        case 170:
        
        case 171:
        
        case 172:
        
        case 173:
        
        case 174:
        
        case 175:
        
        case 176:
        
        case 177:
        
        case 178:
        
        case 179:
        
        case 180:
        
        case 181:
        
        case 182:
        
        case 183:
        
        case 184:
        
        case 185:
        
        case 186:
        
        case 187:
        
        case 188:
        
        case 189:
        
        case 190:
        
        case 191:
        
        case 192:
        
        case 193:
        
        case 194:
        
        case 195:
        
        case 196:
        
        case 197:
        
        case 198:
        
        case 199:
        
        case 200:
        
        case 201:
        
        case 202:
        
        case 203:
        
        case 204:
        
        case 205:
        
        case 206:
        
        case 207:
        
        case 208:
        
        case 209:
        
        case 210:
        
        case 211:
        
        case 212:
        
        case 213:
        
        case 214:
        
        case 215:
        
        case 216:
        
        case 217:
        
        case 218:
        
        case 219:
        
        case 220:
        
        case 221:
        
        case 222:
        
        case 223:
        
        case 224:
        
        case 225:
        
        case 226:
        
        case 227:
        
        case 228:
        
        case 229:
        
        case 230:
        
        case 231:
        
        case 232:
        
        case 233:
        
        case 234:
        
        case 235:
        
        case 236:
        
        case 237:
        
        case 238:
        
        case 239:
        
        case 240:
        
        case 241:
        
        case 242:
        
        case 243:
        
        case 244:
        
        case 245:
        
        case 246:
        
        case 247:
        
        case 248:
        
        case 249:
        
        case 250:
        
        case 251:
        
        case 252:
        
        case 253:
        
        case 254:
        
        default:
          break;
      } 
      char c = 'Ã«';
      int j = (paramInt2 & 0xFF) - c;
      if (j < 0)
        j += 256; 
      int k = ((paramInt2 & 0xFFFF) >>> 8) - c;
      if (k < 0)
        k += 256; 
      for (byte b = 0; b < arrayOfChar.length; b++) {
        int m = b % 2;
        if (m == 0) {
          arrayOfChar[b] = (char)(arrayOfChar[b] ^ j);
          j = ((j >>> 3 | j << 5) ^ arrayOfChar[b]) & 0xFF;
        } else {
          arrayOfChar[b] = (char)(arrayOfChar[b] ^ k);
          k = ((k >>> 3 | k << 5) ^ arrayOfChar[b]) & 0xFF;
        } 
      } 
      b[i] = (new String(arrayOfChar)).intern();
    } 
    return b[i];
  }
}


/* Location:              C:\Program Files\BurpSuitePro\burpsuite_pro.jar!\burp\Zrmh.class
 * Java compiler version: 21 (65.0)
 * JD-Core Version:       1.1.3
 */