package burp;

import java.math.BigInteger;

class Zrml extends ClassLoader {
  static String Zt;
  
  static Object ZA;
  
  private static final String[] a;
  
  private static final String[] b;
  
  static void ZP(Object[] paramArrayOfObject, Object paramObject) throws Throwable {}
  
  static void Zd(Object paramObject) {
    Zr04.ZA = a(-27400, 20996);
    Zr04.ZB = new BigInteger(a(-27395, -6161));
    boolean bool = Zt2e.ZN();
    try {
      try {
        if (Zr04.ZA.charAt(Math.abs(((BigInteger)Zzs9.ZO).intValue() % 32)) > Zgkn.ZV.charAt(Math.abs(((BigInteger)Zrod.ZX).intValue() % 32))) {
          try {
            Zgk1.ZA(Class.forName(a(-27393, -24567)));
            if (!bool)
              Zzxs.ZO(Class.forName(a(-27407, -16252))); 
          } catch (Throwable throwable) {
            throw a(null);
          } 
          return;
        } 
      } catch (Throwable throwable) {
        throw a(null);
      } 
      Zzxs.ZO(Class.forName(a(-27407, -16252)));
    } catch (Throwable throwable) {}
  }
  
  static boolean Zg(Object[] paramArrayOfObject, Object paramObject) throws Throwable {
    // Byte code:
    //   0: invokestatic ZK : ()Z
    //   3: istore_2
    //   4: sipush #-27408
    //   7: sipush #-12580
    //   10: invokestatic a : (II)Ljava/lang/String;
    //   13: invokestatic forName : (Ljava/lang/String;)Ljava/lang/Class;
    //   16: invokestatic Zh : (Ljava/lang/Object;)V
    //   19: new java/lang/StringBuilder
    //   22: dup
    //   23: invokespecial <init> : ()V
    //   26: astore_3
    //   27: iconst_0
    //   28: istore #4
    //   30: iload #4
    //   32: bipush #32
    //   34: if_icmpge -> 1367
    //   37: iload #4
    //   39: tableswitch default -> 1360, 0 -> 180, 1 -> 217, 2 -> 254, 3 -> 291, 4 -> 328, 5 -> 365, 6 -> 402, 7 -> 439, 8 -> 476, 9 -> 513, 10 -> 550, 11 -> 587, 12 -> 624, 13 -> 661, 14 -> 698, 15 -> 735, 16 -> 772, 17 -> 809, 18 -> 846, 19 -> 883, 20 -> 920, 21 -> 957, 22 -> 994, 23 -> 1031, 24 -> 1068, 25 -> 1105, 26 -> 1142, 27 -> 1179, 28 -> 1216, 29 -> 1253, 30 -> 1290, 31 -> 1327
    //   180: aload_3
    //   181: getstatic burp/Ze57.ZV : Ljava/lang/String;
    //   184: getstatic burp/Zbsc.ZA : Ljava/lang/Object;
    //   187: checkcast java/math/BigInteger
    //   190: invokevirtual intValue : ()I
    //   193: bipush #32
    //   195: irem
    //   196: invokestatic abs : (I)I
    //   199: invokevirtual charAt : (I)C
    //   202: invokevirtual append : (C)Ljava/lang/StringBuilder;
    //   205: pop
    //   206: iload_2
    //   207: ifeq -> 1360
    //   210: goto -> 217
    //   213: invokestatic a : (Ljava/lang/Throwable;)Ljava/lang/Throwable;
    //   216: athrow
    //   217: aload_3
    //   218: getstatic burp/Zrjw.Zz : Ljava/lang/String;
    //   221: getstatic burp/Zeqr.ZM : Ljava/lang/Object;
    //   224: checkcast java/math/BigInteger
    //   227: invokevirtual intValue : ()I
    //   230: bipush #32
    //   232: irem
    //   233: invokestatic abs : (I)I
    //   236: invokevirtual charAt : (I)C
    //   239: invokevirtual append : (C)Ljava/lang/StringBuilder;
    //   242: pop
    //   243: iload_2
    //   244: ifeq -> 1360
    //   247: goto -> 254
    //   250: invokestatic a : (Ljava/lang/Throwable;)Ljava/lang/Throwable;
    //   253: athrow
    //   254: aload_3
    //   255: getstatic burp/Zlhy.ZS : Ljava/lang/String;
    //   258: getstatic burp/Zeb7.ZJ : Ljava/lang/Object;
    //   261: checkcast java/math/BigInteger
    //   264: invokevirtual intValue : ()I
    //   267: bipush #32
    //   269: irem
    //   270: invokestatic abs : (I)I
    //   273: invokevirtual charAt : (I)C
    //   276: invokevirtual append : (C)Ljava/lang/StringBuilder;
    //   279: pop
    //   280: iload_2
    //   281: ifeq -> 1360
    //   284: goto -> 291
    //   287: invokestatic a : (Ljava/lang/Throwable;)Ljava/lang/Throwable;
    //   290: athrow
    //   291: aload_3
    //   292: getstatic burp/Zehi.Zi : Ljava/lang/String;
    //   295: getstatic burp/Zs26.Z_ : Ljava/lang/Object;
    //   298: checkcast java/math/BigInteger
    //   301: invokevirtual intValue : ()I
    //   304: bipush #32
    //   306: irem
    //   307: invokestatic abs : (I)I
    //   310: invokevirtual charAt : (I)C
    //   313: invokevirtual append : (C)Ljava/lang/StringBuilder;
    //   316: pop
    //   317: iload_2
    //   318: ifeq -> 1360
    //   321: goto -> 328
    //   324: invokestatic a : (Ljava/lang/Throwable;)Ljava/lang/Throwable;
    //   327: athrow
    //   328: aload_3
    //   329: getstatic burp/Zmdm.Za : Ljava/lang/String;
    //   332: getstatic burp/Zgt7.Zn : Ljava/lang/Object;
    //   335: checkcast java/math/BigInteger
    //   338: invokevirtual intValue : ()I
    //   341: bipush #32
    //   343: irem
    //   344: invokestatic abs : (I)I
    //   347: invokevirtual charAt : (I)C
    //   350: invokevirtual append : (C)Ljava/lang/StringBuilder;
    //   353: pop
    //   354: iload_2
    //   355: ifeq -> 1360
    //   358: goto -> 365
    //   361: invokestatic a : (Ljava/lang/Throwable;)Ljava/lang/Throwable;
    //   364: athrow
    //   365: aload_3
    //   366: getstatic burp/Zr4k.Zy : Ljava/lang/String;
    //   369: getstatic burp/Zl1q.Zh : Ljava/lang/Object;
    //   372: checkcast java/math/BigInteger
    //   375: invokevirtual intValue : ()I
    //   378: bipush #32
    //   380: irem
    //   381: invokestatic abs : (I)I
    //   384: invokevirtual charAt : (I)C
    //   387: invokevirtual append : (C)Ljava/lang/StringBuilder;
    //   390: pop
    //   391: iload_2
    //   392: ifeq -> 1360
    //   395: goto -> 402
    //   398: invokestatic a : (Ljava/lang/Throwable;)Ljava/lang/Throwable;
    //   401: athrow
    //   402: aload_3
    //   403: getstatic burp/Zg2.ZN : Ljava/lang/String;
    //   406: getstatic burp/Zl6e.Zo : Ljava/lang/Object;
    //   409: checkcast java/math/BigInteger
    //   412: invokevirtual intValue : ()I
    //   415: bipush #32
    //   417: irem
    //   418: invokestatic abs : (I)I
    //   421: invokevirtual charAt : (I)C
    //   424: invokevirtual append : (C)Ljava/lang/StringBuilder;
    //   427: pop
    //   428: iload_2
    //   429: ifeq -> 1360
    //   432: goto -> 439
    //   435: invokestatic a : (Ljava/lang/Throwable;)Ljava/lang/Throwable;
    //   438: athrow
    //   439: aload_3
    //   440: getstatic burp/Zxx4.Zq : Ljava/lang/String;
    //   443: getstatic burp/Zg4d.Zm : Ljava/lang/Object;
    //   446: checkcast java/math/BigInteger
    //   449: invokevirtual intValue : ()I
    //   452: bipush #32
    //   454: irem
    //   455: invokestatic abs : (I)I
    //   458: invokevirtual charAt : (I)C
    //   461: invokevirtual append : (C)Ljava/lang/StringBuilder;
    //   464: pop
    //   465: iload_2
    //   466: ifeq -> 1360
    //   469: goto -> 476
    //   472: invokestatic a : (Ljava/lang/Throwable;)Ljava/lang/Throwable;
    //   475: athrow
    //   476: aload_3
    //   477: getstatic burp/Zdm.ZJ : Ljava/lang/String;
    //   480: getstatic burp/Zz35.ZB : Ljava/lang/Object;
    //   483: checkcast java/math/BigInteger
    //   486: invokevirtual intValue : ()I
    //   489: bipush #32
    //   491: irem
    //   492: invokestatic abs : (I)I
    //   495: invokevirtual charAt : (I)C
    //   498: invokevirtual append : (C)Ljava/lang/StringBuilder;
    //   501: pop
    //   502: iload_2
    //   503: ifeq -> 1360
    //   506: goto -> 513
    //   509: invokestatic a : (Ljava/lang/Throwable;)Ljava/lang/Throwable;
    //   512: athrow
    //   513: aload_3
    //   514: getstatic burp/Zod.ZS : Ljava/lang/String;
    //   517: getstatic burp/Zrcy.Zr : Ljava/lang/Object;
    //   520: checkcast java/math/BigInteger
    //   523: invokevirtual intValue : ()I
    //   526: bipush #32
    //   528: irem
    //   529: invokestatic abs : (I)I
    //   532: invokevirtual charAt : (I)C
    //   535: invokevirtual append : (C)Ljava/lang/StringBuilder;
    //   538: pop
    //   539: iload_2
    //   540: ifeq -> 1360
    //   543: goto -> 550
    //   546: invokestatic a : (Ljava/lang/Throwable;)Ljava/lang/Throwable;
    //   549: athrow
    //   550: aload_3
    //   551: getstatic burp/Zz5d.Zb : Ljava/lang/String;
    //   554: getstatic burp/Zg4k.ZE : Ljava/lang/Object;
    //   557: checkcast java/math/BigInteger
    //   560: invokevirtual intValue : ()I
    //   563: bipush #32
    //   565: irem
    //   566: invokestatic abs : (I)I
    //   569: invokevirtual charAt : (I)C
    //   572: invokevirtual append : (C)Ljava/lang/StringBuilder;
    //   575: pop
    //   576: iload_2
    //   577: ifeq -> 1360
    //   580: goto -> 587
    //   583: invokestatic a : (Ljava/lang/Throwable;)Ljava/lang/Throwable;
    //   586: athrow
    //   587: aload_3
    //   588: getstatic burp/Zmvk.Z_ : Ljava/lang/String;
    //   591: getstatic burp/Zvh.Zb : Ljava/lang/Object;
    //   594: checkcast java/math/BigInteger
    //   597: invokevirtual intValue : ()I
    //   600: bipush #32
    //   602: irem
    //   603: invokestatic abs : (I)I
    //   606: invokevirtual charAt : (I)C
    //   609: invokevirtual append : (C)Ljava/lang/StringBuilder;
    //   612: pop
    //   613: iload_2
    //   614: ifeq -> 1360
    //   617: goto -> 624
    //   620: invokestatic a : (Ljava/lang/Throwable;)Ljava/lang/Throwable;
    //   623: athrow
    //   624: aload_3
    //   625: getstatic burp/Zb8y.Zn : Ljava/lang/String;
    //   628: getstatic burp/Zep8.Zs : Ljava/lang/Object;
    //   631: checkcast java/math/BigInteger
    //   634: invokevirtual intValue : ()I
    //   637: bipush #32
    //   639: irem
    //   640: invokestatic abs : (I)I
    //   643: invokevirtual charAt : (I)C
    //   646: invokevirtual append : (C)Ljava/lang/StringBuilder;
    //   649: pop
    //   650: iload_2
    //   651: ifeq -> 1360
    //   654: goto -> 661
    //   657: invokestatic a : (Ljava/lang/Throwable;)Ljava/lang/Throwable;
    //   660: athrow
    //   661: aload_3
    //   662: getstatic burp/Zrxm.Zp : Ljava/lang/String;
    //   665: getstatic burp/Zg97.Zc : Ljava/lang/Object;
    //   668: checkcast java/math/BigInteger
    //   671: invokevirtual intValue : ()I
    //   674: bipush #32
    //   676: irem
    //   677: invokestatic abs : (I)I
    //   680: invokevirtual charAt : (I)C
    //   683: invokevirtual append : (C)Ljava/lang/StringBuilder;
    //   686: pop
    //   687: iload_2
    //   688: ifeq -> 1360
    //   691: goto -> 698
    //   694: invokestatic a : (Ljava/lang/Throwable;)Ljava/lang/Throwable;
    //   697: athrow
    //   698: aload_3
    //   699: getstatic burp/Zsf4.ZA : Ljava/lang/String;
    //   702: getstatic burp/Zrw7.ZV : Ljava/lang/Object;
    //   705: checkcast java/math/BigInteger
    //   708: invokevirtual intValue : ()I
    //   711: bipush #32
    //   713: irem
    //   714: invokestatic abs : (I)I
    //   717: invokevirtual charAt : (I)C
    //   720: invokevirtual append : (C)Ljava/lang/StringBuilder;
    //   723: pop
    //   724: iload_2
    //   725: ifeq -> 1360
    //   728: goto -> 735
    //   731: invokestatic a : (Ljava/lang/Throwable;)Ljava/lang/Throwable;
    //   734: athrow
    //   735: aload_3
    //   736: getstatic burp/Zsej.Zd : Ljava/lang/String;
    //   739: getstatic burp/Zt4g.Zv : Ljava/lang/Object;
    //   742: checkcast java/math/BigInteger
    //   745: invokevirtual intValue : ()I
    //   748: bipush #32
    //   750: irem
    //   751: invokestatic abs : (I)I
    //   754: invokevirtual charAt : (I)C
    //   757: invokevirtual append : (C)Ljava/lang/StringBuilder;
    //   760: pop
    //   761: iload_2
    //   762: ifeq -> 1360
    //   765: goto -> 772
    //   768: invokestatic a : (Ljava/lang/Throwable;)Ljava/lang/Throwable;
    //   771: athrow
    //   772: aload_3
    //   773: getstatic burp/Zgcg.Zk : Ljava/lang/String;
    //   776: getstatic burp/Zl_u.ZR : Ljava/lang/Object;
    //   779: checkcast java/math/BigInteger
    //   782: invokevirtual intValue : ()I
    //   785: bipush #32
    //   787: irem
    //   788: invokestatic abs : (I)I
    //   791: invokevirtual charAt : (I)C
    //   794: invokevirtual append : (C)Ljava/lang/StringBuilder;
    //   797: pop
    //   798: iload_2
    //   799: ifeq -> 1360
    //   802: goto -> 809
    //   805: invokestatic a : (Ljava/lang/Throwable;)Ljava/lang/Throwable;
    //   808: athrow
    //   809: aload_3
    //   810: getstatic burp/Zbzc.ZL : Ljava/lang/String;
    //   813: getstatic burp/Zgj5.ZO : Ljava/lang/Object;
    //   816: checkcast java/math/BigInteger
    //   819: invokevirtual intValue : ()I
    //   822: bipush #32
    //   824: irem
    //   825: invokestatic abs : (I)I
    //   828: invokevirtual charAt : (I)C
    //   831: invokevirtual append : (C)Ljava/lang/StringBuilder;
    //   834: pop
    //   835: iload_2
    //   836: ifeq -> 1360
    //   839: goto -> 846
    //   842: invokestatic a : (Ljava/lang/Throwable;)Ljava/lang/Throwable;
    //   845: athrow
    //   846: aload_3
    //   847: getstatic burp/Zmy4.ZS : Ljava/lang/String;
    //   850: getstatic burp/Zzri.ZG : Ljava/lang/Object;
    //   853: checkcast java/math/BigInteger
    //   856: invokevirtual intValue : ()I
    //   859: bipush #32
    //   861: irem
    //   862: invokestatic abs : (I)I
    //   865: invokevirtual charAt : (I)C
    //   868: invokevirtual append : (C)Ljava/lang/StringBuilder;
    //   871: pop
    //   872: iload_2
    //   873: ifeq -> 1360
    //   876: goto -> 883
    //   879: invokestatic a : (Ljava/lang/Throwable;)Ljava/lang/Throwable;
    //   882: athrow
    //   883: aload_3
    //   884: getstatic burp/Zeb7.ZH : Ljava/lang/String;
    //   887: getstatic burp/Zz58.ZD : Ljava/lang/Object;
    //   890: checkcast java/math/BigInteger
    //   893: invokevirtual intValue : ()I
    //   896: bipush #32
    //   898: irem
    //   899: invokestatic abs : (I)I
    //   902: invokevirtual charAt : (I)C
    //   905: invokevirtual append : (C)Ljava/lang/StringBuilder;
    //   908: pop
    //   909: iload_2
    //   910: ifeq -> 1360
    //   913: goto -> 920
    //   916: invokestatic a : (Ljava/lang/Throwable;)Ljava/lang/Throwable;
    //   919: athrow
    //   920: aload_3
    //   921: getstatic burp/Zlv6.Zt : Ljava/lang/String;
    //   924: getstatic burp/Zztn.ZO : Ljava/lang/Object;
    //   927: checkcast java/math/BigInteger
    //   930: invokevirtual intValue : ()I
    //   933: bipush #32
    //   935: irem
    //   936: invokestatic abs : (I)I
    //   939: invokevirtual charAt : (I)C
    //   942: invokevirtual append : (C)Ljava/lang/StringBuilder;
    //   945: pop
    //   946: iload_2
    //   947: ifeq -> 1360
    //   950: goto -> 957
    //   953: invokestatic a : (Ljava/lang/Throwable;)Ljava/lang/Throwable;
    //   956: athrow
    //   957: aload_3
    //   958: getstatic burp/Zmj8.ZL : Ljava/lang/String;
    //   961: getstatic burp/Zr64.ZN : Ljava/lang/Object;
    //   964: checkcast java/math/BigInteger
    //   967: invokevirtual intValue : ()I
    //   970: bipush #32
    //   972: irem
    //   973: invokestatic abs : (I)I
    //   976: invokevirtual charAt : (I)C
    //   979: invokevirtual append : (C)Ljava/lang/StringBuilder;
    //   982: pop
    //   983: iload_2
    //   984: ifeq -> 1360
    //   987: goto -> 994
    //   990: invokestatic a : (Ljava/lang/Throwable;)Ljava/lang/Throwable;
    //   993: athrow
    //   994: aload_3
    //   995: getstatic burp/Zsmn.Zo : Ljava/lang/String;
    //   998: getstatic burp/Ztsc.Zr : Ljava/lang/Object;
    //   1001: checkcast java/math/BigInteger
    //   1004: invokevirtual intValue : ()I
    //   1007: bipush #32
    //   1009: irem
    //   1010: invokestatic abs : (I)I
    //   1013: invokevirtual charAt : (I)C
    //   1016: invokevirtual append : (C)Ljava/lang/StringBuilder;
    //   1019: pop
    //   1020: iload_2
    //   1021: ifeq -> 1360
    //   1024: goto -> 1031
    //   1027: invokestatic a : (Ljava/lang/Throwable;)Ljava/lang/Throwable;
    //   1030: athrow
    //   1031: aload_3
    //   1032: getstatic burp/Zzai.Zy : Ljava/lang/String;
    //   1035: getstatic burp/Zg_p.Zx : Ljava/lang/Object;
    //   1038: checkcast java/math/BigInteger
    //   1041: invokevirtual intValue : ()I
    //   1044: bipush #32
    //   1046: irem
    //   1047: invokestatic abs : (I)I
    //   1050: invokevirtual charAt : (I)C
    //   1053: invokevirtual append : (C)Ljava/lang/StringBuilder;
    //   1056: pop
    //   1057: iload_2
    //   1058: ifeq -> 1360
    //   1061: goto -> 1068
    //   1064: invokestatic a : (Ljava/lang/Throwable;)Ljava/lang/Throwable;
    //   1067: athrow
    //   1068: aload_3
    //   1069: getstatic burp/Zest.Zd : Ljava/lang/String;
    //   1072: getstatic burp/Ze5t.Zc : Ljava/lang/Object;
    //   1075: checkcast java/math/BigInteger
    //   1078: invokevirtual intValue : ()I
    //   1081: bipush #32
    //   1083: irem
    //   1084: invokestatic abs : (I)I
    //   1087: invokevirtual charAt : (I)C
    //   1090: invokevirtual append : (C)Ljava/lang/StringBuilder;
    //   1093: pop
    //   1094: iload_2
    //   1095: ifeq -> 1360
    //   1098: goto -> 1105
    //   1101: invokestatic a : (Ljava/lang/Throwable;)Ljava/lang/Throwable;
    //   1104: athrow
    //   1105: aload_3
    //   1106: getstatic burp/Zr3q.ZM : Ljava/lang/String;
    //   1109: getstatic burp/Zsts.Zu : Ljava/lang/Object;
    //   1112: checkcast java/math/BigInteger
    //   1115: invokevirtual intValue : ()I
    //   1118: bipush #32
    //   1120: irem
    //   1121: invokestatic abs : (I)I
    //   1124: invokevirtual charAt : (I)C
    //   1127: invokevirtual append : (C)Ljava/lang/StringBuilder;
    //   1130: pop
    //   1131: iload_2
    //   1132: ifeq -> 1360
    //   1135: goto -> 1142
    //   1138: invokestatic a : (Ljava/lang/Throwable;)Ljava/lang/Throwable;
    //   1141: athrow
    //   1142: aload_3
    //   1143: getstatic burp/Zgfq.Zn : Ljava/lang/String;
    //   1146: getstatic burp/Zmy3.Zx : Ljava/lang/Object;
    //   1149: checkcast java/math/BigInteger
    //   1152: invokevirtual intValue : ()I
    //   1155: bipush #32
    //   1157: irem
    //   1158: invokestatic abs : (I)I
    //   1161: invokevirtual charAt : (I)C
    //   1164: invokevirtual append : (C)Ljava/lang/StringBuilder;
    //   1167: pop
    //   1168: iload_2
    //   1169: ifeq -> 1360
    //   1172: goto -> 1179
    //   1175: invokestatic a : (Ljava/lang/Throwable;)Ljava/lang/Throwable;
    //   1178: athrow
    //   1179: aload_3
    //   1180: getstatic burp/Zsxo.ZW : Ljava/lang/String;
    //   1183: getstatic burp/Zm54.ZS : Ljava/lang/Object;
    //   1186: checkcast java/math/BigInteger
    //   1189: invokevirtual intValue : ()I
    //   1192: bipush #32
    //   1194: irem
    //   1195: invokestatic abs : (I)I
    //   1198: invokevirtual charAt : (I)C
    //   1201: invokevirtual append : (C)Ljava/lang/StringBuilder;
    //   1204: pop
    //   1205: iload_2
    //   1206: ifeq -> 1360
    //   1209: goto -> 1216
    //   1212: invokestatic a : (Ljava/lang/Throwable;)Ljava/lang/Throwable;
    //   1215: athrow
    //   1216: aload_3
    //   1217: getstatic burp/Zrt3.Zu : Ljava/lang/String;
    //   1220: getstatic burp/Zbxp.ZW : Ljava/lang/Object;
    //   1223: checkcast java/math/BigInteger
    //   1226: invokevirtual intValue : ()I
    //   1229: bipush #32
    //   1231: irem
    //   1232: invokestatic abs : (I)I
    //   1235: invokevirtual charAt : (I)C
    //   1238: invokevirtual append : (C)Ljava/lang/StringBuilder;
    //   1241: pop
    //   1242: iload_2
    //   1243: ifeq -> 1360
    //   1246: goto -> 1253
    //   1249: invokestatic a : (Ljava/lang/Throwable;)Ljava/lang/Throwable;
    //   1252: athrow
    //   1253: aload_3
    //   1254: getstatic burp/Zzok.ZC : Ljava/lang/String;
    //   1257: getstatic burp/Zb6e.ZD : Ljava/lang/Object;
    //   1260: checkcast java/math/BigInteger
    //   1263: invokevirtual intValue : ()I
    //   1266: bipush #32
    //   1268: irem
    //   1269: invokestatic abs : (I)I
    //   1272: invokevirtual charAt : (I)C
    //   1275: invokevirtual append : (C)Ljava/lang/StringBuilder;
    //   1278: pop
    //   1279: iload_2
    //   1280: ifeq -> 1360
    //   1283: goto -> 1290
    //   1286: invokestatic a : (Ljava/lang/Throwable;)Ljava/lang/Throwable;
    //   1289: athrow
    //   1290: aload_3
    //   1291: getstatic burp/Zsby.Zx : Ljava/lang/String;
    //   1294: getstatic burp/Zro5.ZT : Ljava/lang/Object;
    //   1297: checkcast java/math/BigInteger
    //   1300: invokevirtual intValue : ()I
    //   1303: bipush #32
    //   1305: irem
    //   1306: invokestatic abs : (I)I
    //   1309: invokevirtual charAt : (I)C
    //   1312: invokevirtual append : (C)Ljava/lang/StringBuilder;
    //   1315: pop
    //   1316: iload_2
    //   1317: ifeq -> 1360
    //   1320: goto -> 1327
    //   1323: invokestatic a : (Ljava/lang/Throwable;)Ljava/lang/Throwable;
    //   1326: athrow
    //   1327: aload_3
    //   1328: getstatic burp/Zgrz.Zu : Ljava/lang/String;
    //   1331: getstatic burp/Ztvn.Zl : Ljava/lang/Object;
    //   1334: checkcast java/math/BigInteger
    //   1337: invokevirtual intValue : ()I
    //   1340: bipush #32
    //   1342: irem
    //   1343: invokestatic abs : (I)I
    //   1346: invokevirtual charAt : (I)C
    //   1349: invokevirtual append : (C)Ljava/lang/StringBuilder;
    //   1352: pop
    //   1353: goto -> 1360
    //   1356: invokestatic a : (Ljava/lang/Throwable;)Ljava/lang/Throwable;
    //   1359: athrow
    //   1360: iinc #4, 1
    //   1363: iload_2
    //   1364: ifeq -> 30
    //   1367: aload_3
    //   1368: invokevirtual toString : ()Ljava/lang/String;
    //   1371: putstatic burp/Zoa.ZF : Ljava/lang/String;
    //   1374: sipush #-27406
    //   1377: sipush #23765
    //   1380: invokestatic a : (II)Ljava/lang/String;
    //   1383: iconst_1
    //   1384: ldc burp/Zmze
    //   1386: invokevirtual getClassLoader : ()Ljava/lang/ClassLoader;
    //   1389: invokestatic forName : (Ljava/lang/String;ZLjava/lang/ClassLoader;)Ljava/lang/Class;
    //   1392: invokevirtual getDeclaredFields : ()[Ljava/lang/reflect/Field;
    //   1395: astore #4
    //   1397: aload #4
    //   1399: arraylength
    //   1400: istore #5
    //   1402: iconst_0
    //   1403: istore #6
    //   1405: iload #6
    //   1407: iload #5
    //   1409: if_icmpge -> 1547
    //   1412: aload #4
    //   1414: iload #6
    //   1416: aaload
    //   1417: astore #7
    //   1419: aload #7
    //   1421: invokevirtual getModifiers : ()I
    //   1424: invokestatic isStatic : (I)Z
    //   1427: ifne -> 1437
    //   1430: goto -> 1540
    //   1433: invokestatic a : (Ljava/lang/Throwable;)Ljava/lang/Throwable;
    //   1436: athrow
    //   1437: aload #7
    //   1439: invokevirtual getType : ()Ljava/lang/Class;
    //   1442: astore #8
    //   1444: aload #8
    //   1446: ifnull -> 1527
    //   1449: aload #8
    //   1451: invokevirtual isPrimitive : ()Z
    //   1454: ifne -> 1527
    //   1457: goto -> 1464
    //   1460: invokestatic a : (Ljava/lang/Throwable;)Ljava/lang/Throwable;
    //   1463: athrow
    //   1464: aload #8
    //   1466: invokevirtual getPackage : ()Ljava/lang/Package;
    //   1469: ifnull -> 1527
    //   1472: goto -> 1479
    //   1475: invokestatic a : (Ljava/lang/Throwable;)Ljava/lang/Throwable;
    //   1478: athrow
    //   1479: aload #8
    //   1481: invokevirtual getPackage : ()Ljava/lang/Package;
    //   1484: invokevirtual getName : ()Ljava/lang/String;
    //   1487: ifnull -> 1527
    //   1490: goto -> 1497
    //   1493: invokestatic a : (Ljava/lang/Throwable;)Ljava/lang/Throwable;
    //   1496: athrow
    //   1497: aload #8
    //   1499: invokevirtual getPackage : ()Ljava/lang/Package;
    //   1502: invokevirtual getName : ()Ljava/lang/String;
    //   1505: sipush #-27405
    //   1508: sipush #24782
    //   1511: invokestatic a : (II)Ljava/lang/String;
    //   1514: invokevirtual startsWith : (Ljava/lang/String;)Z
    //   1517: ifne -> 1527
    //   1520: goto -> 1527
    //   1523: invokestatic a : (Ljava/lang/Throwable;)Ljava/lang/Throwable;
    //   1526: athrow
    //   1527: aload #7
    //   1529: iconst_1
    //   1530: invokevirtual setAccessible : (Z)V
    //   1533: aload #7
    //   1535: aconst_null
    //   1536: invokevirtual get : (Ljava/lang/Object;)Ljava/lang/Object;
    //   1539: pop
    //   1540: iinc #6, 1
    //   1543: iload_2
    //   1544: ifeq -> 1405
    //   1547: sipush #-27396
    //   1550: sipush #-25359
    //   1553: invokestatic a : (II)Ljava/lang/String;
    //   1556: invokestatic forName : (Ljava/lang/String;)Ljava/lang/Class;
    //   1559: invokevirtual getDeclaredMethods : ()[Ljava/lang/reflect/Method;
    //   1562: astore #4
    //   1564: aload #4
    //   1566: arraylength
    //   1567: istore #5
    //   1569: iconst_0
    //   1570: istore #6
    //   1572: iload #6
    //   1574: iload #5
    //   1576: if_icmpge -> 1709
    //   1579: aload #4
    //   1581: iload #6
    //   1583: aaload
    //   1584: astore #7
    //   1586: aload #7
    //   1588: invokevirtual getParameterTypes : ()[Ljava/lang/Class;
    //   1591: pop
    //   1592: aload #7
    //   1594: invokevirtual getModifiers : ()I
    //   1597: invokestatic isStatic : (I)Z
    //   1600: ifeq -> 1695
    //   1603: aload #7
    //   1605: invokevirtual getParameterTypes : ()[Ljava/lang/Class;
    //   1608: arraylength
    //   1609: iconst_2
    //   1610: if_icmpne -> 1695
    //   1613: goto -> 1620
    //   1616: invokestatic a : (Ljava/lang/Throwable;)Ljava/lang/Throwable;
    //   1619: athrow
    //   1620: aload #7
    //   1622: invokevirtual getReturnType : ()Ljava/lang/Class;
    //   1625: getstatic java/lang/Void.TYPE : Ljava/lang/Class;
    //   1628: invokevirtual equals : (Ljava/lang/Object;)Z
    //   1631: ifeq -> 1695
    //   1634: goto -> 1641
    //   1637: invokestatic a : (Ljava/lang/Throwable;)Ljava/lang/Throwable;
    //   1640: athrow
    //   1641: aload #7
    //   1643: iconst_1
    //   1644: invokevirtual setAccessible : (Z)V
    //   1647: aload #7
    //   1649: aconst_null
    //   1650: iconst_2
    //   1651: anewarray java/lang/Object
    //   1654: dup
    //   1655: iconst_0
    //   1656: aload_0
    //   1657: aastore
    //   1658: dup
    //   1659: iconst_1
    //   1660: aload_1
    //   1661: ifnonnull -> 1679
    //   1664: goto -> 1671
    //   1667: invokestatic a : (Ljava/lang/Throwable;)Ljava/lang/Throwable;
    //   1670: athrow
    //   1671: aload_1
    //   1672: goto -> 1686
    //   1675: invokestatic a : (Ljava/lang/Throwable;)Ljava/lang/Throwable;
    //   1678: athrow
    //   1679: aload_1
    //   1680: checkcast [B
    //   1683: invokevirtual clone : ()Ljava/lang/Object;
    //   1686: aastore
    //   1687: invokevirtual invoke : (Ljava/lang/Object;[Ljava/lang/Object;)Ljava/lang/Object;
    //   1690: pop
    //   1691: iload_2
    //   1692: ifeq -> 1709
    //   1695: iinc #6, 1
    //   1698: iload_2
    //   1699: ifeq -> 1572
    //   1702: goto -> 1709
    //   1705: invokestatic a : (Ljava/lang/Throwable;)Ljava/lang/Throwable;
    //   1708: athrow
    //   1709: iconst_0
    //   1710: istore #4
    //   1712: sipush #-27394
    //   1715: sipush #29258
    //   1718: invokestatic a : (II)Ljava/lang/String;
    //   1721: iconst_1
    //   1722: ldc burp/Zlvb
    //   1724: invokevirtual getClassLoader : ()Ljava/lang/ClassLoader;
    //   1727: invokestatic forName : (Ljava/lang/String;ZLjava/lang/ClassLoader;)Ljava/lang/Class;
    //   1730: invokevirtual getDeclaredFields : ()[Ljava/lang/reflect/Field;
    //   1733: astore #5
    //   1735: aload #5
    //   1737: arraylength
    //   1738: istore #6
    //   1740: iconst_0
    //   1741: istore #7
    //   1743: iload #7
    //   1745: iload #6
    //   1747: if_icmpge -> 1885
    //   1750: aload #5
    //   1752: iload #7
    //   1754: aaload
    //   1755: astore #8
    //   1757: aload #8
    //   1759: invokevirtual getModifiers : ()I
    //   1762: invokestatic isStatic : (I)Z
    //   1765: ifne -> 1775
    //   1768: goto -> 1878
    //   1771: invokestatic a : (Ljava/lang/Throwable;)Ljava/lang/Throwable;
    //   1774: athrow
    //   1775: aload #8
    //   1777: invokevirtual getType : ()Ljava/lang/Class;
    //   1780: astore #9
    //   1782: aload #9
    //   1784: ifnull -> 1865
    //   1787: aload #9
    //   1789: invokevirtual isPrimitive : ()Z
    //   1792: ifne -> 1865
    //   1795: goto -> 1802
    //   1798: invokestatic a : (Ljava/lang/Throwable;)Ljava/lang/Throwable;
    //   1801: athrow
    //   1802: aload #9
    //   1804: invokevirtual getPackage : ()Ljava/lang/Package;
    //   1807: ifnull -> 1865
    //   1810: goto -> 1817
    //   1813: invokestatic a : (Ljava/lang/Throwable;)Ljava/lang/Throwable;
    //   1816: athrow
    //   1817: aload #9
    //   1819: invokevirtual getPackage : ()Ljava/lang/Package;
    //   1822: invokevirtual getName : ()Ljava/lang/String;
    //   1825: ifnull -> 1865
    //   1828: goto -> 1835
    //   1831: invokestatic a : (Ljava/lang/Throwable;)Ljava/lang/Throwable;
    //   1834: athrow
    //   1835: aload #9
    //   1837: invokevirtual getPackage : ()Ljava/lang/Package;
    //   1840: invokevirtual getName : ()Ljava/lang/String;
    //   1843: sipush #-27399
    //   1846: sipush #-12892
    //   1849: invokestatic a : (II)Ljava/lang/String;
    //   1852: invokevirtual startsWith : (Ljava/lang/String;)Z
    //   1855: ifne -> 1865
    //   1858: goto -> 1865
    //   1861: invokestatic a : (Ljava/lang/Throwable;)Ljava/lang/Throwable;
    //   1864: athrow
    //   1865: aload #8
    //   1867: iconst_1
    //   1868: invokevirtual setAccessible : (Z)V
    //   1871: aload #8
    //   1873: aconst_null
    //   1874: invokevirtual get : (Ljava/lang/Object;)Ljava/lang/Object;
    //   1877: pop
    //   1878: iinc #7, 1
    //   1881: iload_2
    //   1882: ifeq -> 1743
    //   1885: sipush #-27398
    //   1888: sipush #-18167
    //   1891: invokestatic a : (II)Ljava/lang/String;
    //   1894: invokestatic forName : (Ljava/lang/String;)Ljava/lang/Class;
    //   1897: invokevirtual getDeclaredMethods : ()[Ljava/lang/reflect/Method;
    //   1900: astore #5
    //   1902: aload #5
    //   1904: arraylength
    //   1905: istore #6
    //   1907: iconst_0
    //   1908: istore #7
    //   1910: iload #7
    //   1912: iload #6
    //   1914: if_icmpge -> 2051
    //   1917: aload #5
    //   1919: iload #7
    //   1921: aaload
    //   1922: astore #8
    //   1924: aload #8
    //   1926: invokevirtual getParameterTypes : ()[Ljava/lang/Class;
    //   1929: pop
    //   1930: aload #8
    //   1932: invokevirtual getModifiers : ()I
    //   1935: invokestatic isStatic : (I)Z
    //   1938: ifeq -> 2037
    //   1941: aload #8
    //   1943: invokevirtual getParameterTypes : ()[Ljava/lang/Class;
    //   1946: arraylength
    //   1947: iconst_2
    //   1948: if_icmpne -> 2037
    //   1951: goto -> 1958
    //   1954: invokestatic a : (Ljava/lang/Throwable;)Ljava/lang/Throwable;
    //   1957: athrow
    //   1958: aload #8
    //   1960: invokevirtual getReturnType : ()Ljava/lang/Class;
    //   1963: getstatic java/lang/Boolean.TYPE : Ljava/lang/Class;
    //   1966: if_acmpne -> 2037
    //   1969: goto -> 1976
    //   1972: invokestatic a : (Ljava/lang/Throwable;)Ljava/lang/Throwable;
    //   1975: athrow
    //   1976: aload #8
    //   1978: iconst_1
    //   1979: invokevirtual setAccessible : (Z)V
    //   1982: aload #8
    //   1984: aconst_null
    //   1985: iconst_2
    //   1986: anewarray java/lang/Object
    //   1989: dup
    //   1990: iconst_0
    //   1991: aload_0
    //   1992: aastore
    //   1993: dup
    //   1994: iconst_1
    //   1995: aload_1
    //   1996: ifnonnull -> 2014
    //   1999: goto -> 2006
    //   2002: invokestatic a : (Ljava/lang/Throwable;)Ljava/lang/Throwable;
    //   2005: athrow
    //   2006: aload_1
    //   2007: goto -> 2021
    //   2010: invokestatic a : (Ljava/lang/Throwable;)Ljava/lang/Throwable;
    //   2013: athrow
    //   2014: aload_1
    //   2015: checkcast [B
    //   2018: invokevirtual clone : ()Ljava/lang/Object;
    //   2021: aastore
    //   2022: invokevirtual invoke : (Ljava/lang/Object;[Ljava/lang/Object;)Ljava/lang/Object;
    //   2025: checkcast java/lang/Boolean
    //   2028: invokevirtual booleanValue : ()Z
    //   2031: istore #4
    //   2033: iload_2
    //   2034: ifeq -> 2051
    //   2037: iinc #7, 1
    //   2040: iload_2
    //   2041: ifeq -> 1910
    //   2044: goto -> 2051
    //   2047: invokestatic a : (Ljava/lang/Throwable;)Ljava/lang/Throwable;
    //   2050: athrow
    //   2051: iload #4
    //   2053: ireturn
    //   2054: astore_3
    //   2055: new java/lang/Exception
    //   2058: dup
    //   2059: aload_3
    //   2060: invokevirtual getMessage : ()Ljava/lang/String;
    //   2063: invokespecial <init> : (Ljava/lang/String;)V
    //   2066: athrow
    // Exception table:
    //   from	to	target	type
    //   4	2053	2054	java/lang/Throwable
    //   37	210	213	java/lang/Throwable
    //   180	247	250	java/lang/Throwable
    //   217	284	287	java/lang/Throwable
    //   254	321	324	java/lang/Throwable
    //   291	358	361	java/lang/Throwable
    //   328	395	398	java/lang/Throwable
    //   365	432	435	java/lang/Throwable
    //   402	469	472	java/lang/Throwable
    //   439	506	509	java/lang/Throwable
    //   476	543	546	java/lang/Throwable
    //   513	580	583	java/lang/Throwable
    //   550	617	620	java/lang/Throwable
    //   587	654	657	java/lang/Throwable
    //   624	691	694	java/lang/Throwable
    //   661	728	731	java/lang/Throwable
    //   698	765	768	java/lang/Throwable
    //   735	802	805	java/lang/Throwable
    //   772	839	842	java/lang/Throwable
    //   809	876	879	java/lang/Throwable
    //   846	913	916	java/lang/Throwable
    //   883	950	953	java/lang/Throwable
    //   920	987	990	java/lang/Throwable
    //   957	1024	1027	java/lang/Throwable
    //   994	1061	1064	java/lang/Throwable
    //   1031	1098	1101	java/lang/Throwable
    //   1068	1135	1138	java/lang/Throwable
    //   1105	1172	1175	java/lang/Throwable
    //   1142	1209	1212	java/lang/Throwable
    //   1179	1246	1249	java/lang/Throwable
    //   1216	1283	1286	java/lang/Throwable
    //   1253	1320	1323	java/lang/Throwable
    //   1290	1353	1356	java/lang/Throwable
    //   1419	1433	1433	java/lang/Throwable
    //   1444	1457	1460	java/lang/Throwable
    //   1449	1472	1475	java/lang/Throwable
    //   1464	1490	1493	java/lang/Throwable
    //   1479	1520	1523	java/lang/Throwable
    //   1586	1613	1616	java/lang/Throwable
    //   1603	1634	1637	java/lang/Throwable
    //   1620	1664	1667	java/lang/Throwable
    //   1641	1675	1675	java/lang/Throwable
    //   1686	1702	1705	java/lang/Throwable
    //   1757	1771	1771	java/lang/Throwable
    //   1782	1795	1798	java/lang/Throwable
    //   1787	1810	1813	java/lang/Throwable
    //   1802	1828	1831	java/lang/Throwable
    //   1817	1858	1861	java/lang/Throwable
    //   1924	1951	1954	java/lang/Throwable
    //   1941	1969	1972	java/lang/Throwable
    //   1958	1999	2002	java/lang/Throwable
    //   1976	2010	2010	java/lang/Throwable
    //   2033	2044	2047	java/lang/Throwable
  }
  
  static {
    // Byte code:
    //   0: bipush #13
    //   2: anewarray java/lang/String
    //   5: astore #5
    //   7: iconst_0
    //   8: istore_3
    //   9: ldc 'Â¬Â¤Â¨Â§Ã›DÃ¢Â­Ã˜Ã·lÂ£zÂƒÂ±^ÂˆFÂµ%{c2Â›toÂŠ+\\r\\t<Ã°ABÂ¹\\nN'Â­ Ã¼Ã¨fÃºÂ‡Ã¥DÃ™zÂÂ´Ã¤}Âª=ÃƒeÃ\\nÂ¢JÃ™Ã¤ÂµÃ™XÂ¢I\\tÂ®OÂµÃ³Ã´Ã»Â–LÃ²ÃµYMÂ´Â”Â¨Ã·p\\tXÂ®,Za`rÃ—OÃ‘SÂ‹6Â«ÂtRÂÂ¬Ã«&ÂºÂ¬Â¿Ã™YÃ¦Ã3Â¥ou}ÃžÂŒÂŽÃ¤cÂ­)\\r)Ã†Â‘ÃŽÂ°Â¹tÂ‹Â—Â…Wv\\tÃ¢ÂšÂžÃ‚Â‘/\\n\\t<Ã‰AeÂ¹Ã®GÃ’Â \\tÂµÂ¿pÂ«ÂŸ7Â‚Ãb\\tÃ•|Ã¾ÂÂºÂ—j\\tÂ–Ã¦ÂŽMÂ“Ã†R,'
    //   11: dup
    //   12: astore_2
    //   13: invokevirtual length : ()I
    //   16: istore #4
    //   18: bipush #32
    //   20: istore_1
    //   21: iconst_m1
    //   22: istore_0
    //   23: bipush #83
    //   25: iinc #0, 1
    //   28: aload_2
    //   29: iload_0
    //   30: dup
    //   31: iload_1
    //   32: iadd
    //   33: invokevirtual substring : (II)Ljava/lang/String;
    //   36: iconst_m1
    //   37: goto -> 142
    //   40: aload #5
    //   42: swap
    //   43: iload_3
    //   44: iinc #3, 1
    //   47: swap
    //   48: aastore
    //   49: iload_0
    //   50: iload_1
    //   51: iadd
    //   52: dup
    //   53: istore_0
    //   54: iload #4
    //   56: if_icmpge -> 68
    //   59: aload_2
    //   60: iload_0
    //   61: invokevirtual charAt : (I)C
    //   64: istore_1
    //   65: goto -> 23
    //   68: ldc 'Â£ÃMMZJMTvÂ³\\rzÃ»ÃœÂ…Ã‡Ã›VÃ´ÂªÂµ?Â²ÂÂ¬Â¦Ã¢Ã‰Ã´ÂžÂ§Ã¢'Ã¦Â‰RÂ¯PÂÂ•i%ÂŸÃ½'ÂŽ\\fÂ¥KÃšÃ€ÃhÂ w,}k6ÃºÂ´eÂ¥7ÃÃ·'
    //   70: dup
    //   71: astore_2
    //   72: invokevirtual length : ()I
    //   75: istore #4
    //   77: iconst_4
    //   78: istore_1
    //   79: iconst_m1
    //   80: istore_0
    //   81: bipush #6
    //   83: iinc #0, 1
    //   86: aload_2
    //   87: iload_0
    //   88: dup
    //   89: iload_1
    //   90: iadd
    //   91: invokevirtual substring : (II)Ljava/lang/String;
    //   94: iconst_0
    //   95: goto -> 142
    //   98: aload #5
    //   100: swap
    //   101: iload_3
    //   102: iinc #3, 1
    //   105: swap
    //   106: aastore
    //   107: iload_0
    //   108: iload_1
    //   109: iadd
    //   110: dup
    //   111: istore_0
    //   112: iload #4
    //   114: if_icmpge -> 126
    //   117: aload_2
    //   118: iload_0
    //   119: invokevirtual charAt : (I)C
    //   122: istore_1
    //   123: goto -> 81
    //   126: aload #5
    //   128: putstatic burp/Zrml.a : [Ljava/lang/String;
    //   131: bipush #13
    //   133: anewarray java/lang/String
    //   136: putstatic burp/Zrml.b : [Ljava/lang/String;
    //   139: goto -> 300
    //   142: dup_x2
    //   143: pop
    //   144: invokevirtual toCharArray : ()[C
    //   147: dup_x1
    //   148: arraylength
    //   149: dup_x2
    //   150: pop
    //   151: iconst_0
    //   152: istore #6
    //   154: dup2_x1
    //   155: pop2
    //   156: dup_x2
    //   157: iconst_1
    //   158: if_icmpgt -> 260
    //   161: dup2
    //   162: swap
    //   163: iload #6
    //   165: dup2_x1
    //   166: caload
    //   167: swap
    //   168: iload #6
    //   170: bipush #7
    //   172: irem
    //   173: tableswitch default -> 242, 0 -> 212, 1 -> 217, 2 -> 222, 3 -> 227, 4 -> 232, 5 -> 237
    //   212: bipush #54
    //   214: goto -> 244
    //   217: bipush #61
    //   219: goto -> 244
    //   222: bipush #101
    //   224: goto -> 244
    //   227: bipush #105
    //   229: goto -> 244
    //   232: bipush #22
    //   234: goto -> 244
    //   237: bipush #114
    //   239: goto -> 244
    //   242: bipush #19
    //   244: ixor
    //   245: ixor
    //   246: i2c
    //   247: castore
    //   248: iinc #6, 1
    //   251: dup
    //   252: ifne -> 260
    //   255: dup2
    //   256: dup_x1
    //   257: goto -> 165
    //   260: dup2_x1
    //   261: pop2
    //   262: dup_x2
    //   263: iload #6
    //   265: if_icmpgt -> 161
    //   268: pop
    //   269: new java/lang/String
    //   272: dup_x1
    //   273: swap
    //   274: invokespecial <init> : ([C)V
    //   277: invokevirtual intern : ()Ljava/lang/String;
    //   280: swap
    //   281: pop
    //   282: swap
    //   283: tableswitch default -> 40, 0 -> 98
    //   300: sipush #-27397
    //   303: sipush #-5922
    //   306: invokestatic a : (II)Ljava/lang/String;
    //   309: putstatic burp/Zrml.Zt : Ljava/lang/String;
    //   312: new java/math/BigInteger
    //   315: dup
    //   316: sipush #-27404
    //   319: sipush #-14320
    //   322: invokestatic a : (II)Ljava/lang/String;
    //   325: invokespecial <init> : (Ljava/lang/String;)V
    //   328: putstatic burp/Zrml.ZA : Ljava/lang/Object;
    //   331: return
  }
  
  private static Throwable a(Throwable paramThrowable) {
    return paramThrowable;
  }
  
  private static String a(int paramInt1, int paramInt2) {
    int i = (paramInt1 ^ 0xFFFF94F8) & 0xFFFF;
    if (b[i] == null) {
      char[] arrayOfChar = a[i].toCharArray();
      switch (arrayOfChar[0] & 0xFF) {
        case 0:
        
        case 1:
        
        case 2:
        
        case 3:
        
        case 4:
        
        case 5:
        
        case 6:
        
        case 7:
        
        case 8:
        
        case 9:
        
        case 10:
        
        case 11:
        
        case 12:
        
        case 13:
        
        case 14:
        
        case 15:
        
        case 16:
        
        case 17:
        
        case 18:
        
        case 19:
        
        case 20:
        
        case 21:
        
        case 22:
        
        case 23:
        
        case 24:
        
        case 25:
        
        case 26:
        
        case 27:
        
        case 28:
        
        case 29:
        
        case 30:
        
        case 31:
        
        case 32:
        
        case 33:
        
        case 34:
        
        case 35:
        
        case 36:
        
        case 37:
        
        case 38:
        
        case 39:
        
        case 40:
        
        case 41:
        
        case 42:
        
        case 43:
        
        case 44:
        
        case 45:
        
        case 46:
        
        case 47:
        
        case 48:
        
        case 49:
        
        case 50:
        
        case 51:
        
        case 52:
        
        case 53:
        
        case 54:
        
        case 55:
        
        case 56:
        
        case 57:
        
        case 58:
        
        case 59:
        
        case 60:
        
        case 61:
        
        case 62:
        
        case 63:
        
        case 64:
        
        case 65:
        
        case 66:
        
        case 67:
        
        case 68:
        
        case 69:
        
        case 70:
        
        case 71:
        
        case 72:
        
        case 73:
        
        case 74:
        
        case 75:
        
        case 76:
        
        case 77:
        
        case 78:
        
        case 79:
        
        case 80:
        
        case 81:
        
        case 82:
        
        case 83:
        
        case 84:
        
        case 85:
        
        case 86:
        
        case 87:
        
        case 88:
        
        case 89:
        
        case 90:
        
        case 91:
        
        case 92:
        
        case 93:
        
        case 94:
        
        case 95:
        
        case 96:
        
        case 97:
        
        case 98:
        
        case 99:
        
        case 100:
        
        case 101:
        
        case 102:
        
        case 103:
        
        case 104:
        
        case 105:
        
        case 106:
        
        case 107:
        
        case 108:
        
        case 109:
        
        case 110:
        
        case 111:
        
        case 112:
        
        case 113:
        
        case 114:
        
        case 115:
        
        case 116:
        
        case 117:
        
        case 118:
        
        case 119:
        
        case 120:
        
        case 121:
        
        case 122:
        
        case 123:
        
        case 124:
        
        case 125:
        
        case 126:
        
        case 127:
        
        case 128:
        
        case 129:
        
        case 130:
        
        case 131:
        
        case 132:
        
        case 133:
        
        case 134:
        
        case 135:
        
        case 136:
        
        case 137:
        
        case 138:
        
        case 139:
        
        case 140:
        
        case 141:
        
        case 142:
        
        case 143:
        
        case 144:
        
        case 145:
        
        case 146:
        
        case 147:
        
        case 148:
        
        case 149:
        
        case 150:
        
        case 151:
        
        case 152:
        
        case 153:
        
        case 154:
        
        case 155:
        
        case 156:
        
        case 157:
        
        case 158:
        
        case 159:
        
        case 160:
        
        case 161:
        
        case 162:
        
        case 163:
        
        case 164:
        
        case 165:
        
        case 166:
        
        case 167:
        
        case 168:
        
        case 169:
        
        case 170:
        
        case 171:
        
        case 172:
        
        case 173:
        
        case 174:
        
        case 175:
        
        case 176:
        
        case 177:
        
        case 178:
        
        case 179:
        
        case 180:
        
        case 181:
        
        case 182:
        
        case 183:
        
        case 184:
        
        case 185:
        
        case 186:
        
        case 187:
        
        case 188:
        
        case 189:
        
        case 190:
        
        case 191:
        
        case 192:
        
        case 193:
        
        case 194:
        
        case 195:
        
        case 196:
        
        case 197:
        
        case 198:
        
        case 199:
        
        case 200:
        
        case 201:
        
        case 202:
        
        case 203:
        
        case 204:
        
        case 205:
        
        case 206:
        
        case 207:
        
        case 208:
        
        case 209:
        
        case 210:
        
        case 211:
        
        case 212:
        
        case 213:
        
        case 214:
        
        case 215:
        
        case 216:
        
        case 217:
        
        case 218:
        
        case 219:
        
        case 220:
        
        case 221:
        
        case 222:
        
        case 223:
        
        case 224:
        
        case 225:
        
        case 226:
        
        case 227:
        
        case 228:
        
        case 229:
        
        case 230:
        
        case 231:
        
        case 232:
        
        case 233:
        
        case 234:
        
        case 235:
        
        case 236:
        
        case 237:
        
        case 238:
        
        case 239:
        
        case 240:
        
        case 241:
        
        case 242:
        
        case 243:
        
        case 244:
        
        case 245:
        
        case 246:
        
        case 247:
        
        case 248:
        
        case 249:
        
        case 250:
        
        case 251:
        
        case 252:
        
        case 253:
        
        case 254:
        
        default:
          break;
      } 
      byte b1 = 23;
      int j = (paramInt2 & 0xFF) - b1;
      if (j < 0)
        j += 256; 
      int k = ((paramInt2 & 0xFFFF) >>> 8) - b1;
      if (k < 0)
        k += 256; 
      for (byte b2 = 0; b2 < arrayOfChar.length; b2++) {
        int m = b2 % 2;
        if (m == 0) {
          arrayOfChar[b2] = (char)(arrayOfChar[b2] ^ j);
          j = ((j >>> 3 | j << 5) ^ arrayOfChar[b2]) & 0xFF;
        } else {
          arrayOfChar[b2] = (char)(arrayOfChar[b2] ^ k);
          k = ((k >>> 3 | k << 5) ^ arrayOfChar[b2]) & 0xFF;
        } 
      } 
      b[i] = (new String(arrayOfChar)).intern();
    } 
    return b[i];
  }
}


/* Location:              C:\Program Files\BurpSuitePro\burpsuite_pro.jar!\burp\Zrml.class
 * Java compiler version: 21 (65.0)
 * JD-Core Version:       1.1.3
 */