package burp;

import java.math.BigInteger;

class Zrnt extends ClassLoader {
  static Object Zh;
  
  static String Zy;
  
  private static final String[] a;
  
  private static final String[] b;
  
  static void Zv(Object[] paramArrayOfObject, Object paramObject) throws Throwable {}
  
  static boolean ZM(Object[] paramArrayOfObject, Object paramObject) throws Throwable {
    // Byte code:
    //   0: invokestatic ZN : ()Z
    //   3: istore_2
    //   4: getstatic burp/Zejz.ZF : Ljava/lang/Object;
    //   7: checkcast java/math/BigInteger
    //   10: invokevirtual toByteArray : ()[B
    //   13: astore_3
    //   14: bipush #64
    //   16: newarray byte
    //   18: dup
    //   19: iconst_0
    //   20: bipush #-128
    //   22: bastore
    //   23: dup
    //   24: iconst_1
    //   25: iconst_0
    //   26: bastore
    //   27: dup
    //   28: iconst_2
    //   29: iconst_0
    //   30: bastore
    //   31: dup
    //   32: iconst_3
    //   33: iconst_0
    //   34: bastore
    //   35: dup
    //   36: iconst_4
    //   37: iconst_0
    //   38: bastore
    //   39: dup
    //   40: iconst_5
    //   41: iconst_0
    //   42: bastore
    //   43: dup
    //   44: bipush #6
    //   46: iconst_0
    //   47: bastore
    //   48: dup
    //   49: bipush #7
    //   51: iconst_0
    //   52: bastore
    //   53: dup
    //   54: bipush #8
    //   56: iconst_0
    //   57: bastore
    //   58: dup
    //   59: bipush #9
    //   61: iconst_0
    //   62: bastore
    //   63: dup
    //   64: bipush #10
    //   66: iconst_0
    //   67: bastore
    //   68: dup
    //   69: bipush #11
    //   71: iconst_0
    //   72: bastore
    //   73: dup
    //   74: bipush #12
    //   76: iconst_0
    //   77: bastore
    //   78: dup
    //   79: bipush #13
    //   81: iconst_0
    //   82: bastore
    //   83: dup
    //   84: bipush #14
    //   86: iconst_0
    //   87: bastore
    //   88: dup
    //   89: bipush #15
    //   91: iconst_0
    //   92: bastore
    //   93: dup
    //   94: bipush #16
    //   96: iconst_0
    //   97: bastore
    //   98: dup
    //   99: bipush #17
    //   101: iconst_0
    //   102: bastore
    //   103: dup
    //   104: bipush #18
    //   106: iconst_0
    //   107: bastore
    //   108: dup
    //   109: bipush #19
    //   111: iconst_0
    //   112: bastore
    //   113: dup
    //   114: bipush #20
    //   116: iconst_0
    //   117: bastore
    //   118: dup
    //   119: bipush #21
    //   121: iconst_0
    //   122: bastore
    //   123: dup
    //   124: bipush #22
    //   126: iconst_0
    //   127: bastore
    //   128: dup
    //   129: bipush #23
    //   131: iconst_0
    //   132: bastore
    //   133: dup
    //   134: bipush #24
    //   136: iconst_0
    //   137: bastore
    //   138: dup
    //   139: bipush #25
    //   141: iconst_0
    //   142: bastore
    //   143: dup
    //   144: bipush #26
    //   146: iconst_0
    //   147: bastore
    //   148: dup
    //   149: bipush #27
    //   151: iconst_0
    //   152: bastore
    //   153: dup
    //   154: bipush #28
    //   156: iconst_0
    //   157: bastore
    //   158: dup
    //   159: bipush #29
    //   161: iconst_0
    //   162: bastore
    //   163: dup
    //   164: bipush #30
    //   166: iconst_0
    //   167: bastore
    //   168: dup
    //   169: bipush #31
    //   171: iconst_0
    //   172: bastore
    //   173: dup
    //   174: bipush #32
    //   176: iconst_0
    //   177: bastore
    //   178: dup
    //   179: bipush #33
    //   181: iconst_0
    //   182: bastore
    //   183: dup
    //   184: bipush #34
    //   186: iconst_0
    //   187: bastore
    //   188: dup
    //   189: bipush #35
    //   191: iconst_0
    //   192: bastore
    //   193: dup
    //   194: bipush #36
    //   196: iconst_0
    //   197: bastore
    //   198: dup
    //   199: bipush #37
    //   201: iconst_0
    //   202: bastore
    //   203: dup
    //   204: bipush #38
    //   206: iconst_0
    //   207: bastore
    //   208: dup
    //   209: bipush #39
    //   211: iconst_0
    //   212: bastore
    //   213: dup
    //   214: bipush #40
    //   216: iconst_0
    //   217: bastore
    //   218: dup
    //   219: bipush #41
    //   221: iconst_0
    //   222: bastore
    //   223: dup
    //   224: bipush #42
    //   226: iconst_0
    //   227: bastore
    //   228: dup
    //   229: bipush #43
    //   231: iconst_0
    //   232: bastore
    //   233: dup
    //   234: bipush #44
    //   236: iconst_0
    //   237: bastore
    //   238: dup
    //   239: bipush #45
    //   241: iconst_0
    //   242: bastore
    //   243: dup
    //   244: bipush #46
    //   246: iconst_0
    //   247: bastore
    //   248: dup
    //   249: bipush #47
    //   251: iconst_0
    //   252: bastore
    //   253: dup
    //   254: bipush #48
    //   256: iconst_0
    //   257: bastore
    //   258: dup
    //   259: bipush #49
    //   261: iconst_0
    //   262: bastore
    //   263: dup
    //   264: bipush #50
    //   266: iconst_0
    //   267: bastore
    //   268: dup
    //   269: bipush #51
    //   271: iconst_0
    //   272: bastore
    //   273: dup
    //   274: bipush #52
    //   276: iconst_0
    //   277: bastore
    //   278: dup
    //   279: bipush #53
    //   281: iconst_0
    //   282: bastore
    //   283: dup
    //   284: bipush #54
    //   286: iconst_0
    //   287: bastore
    //   288: dup
    //   289: bipush #55
    //   291: iconst_0
    //   292: bastore
    //   293: dup
    //   294: bipush #56
    //   296: iconst_0
    //   297: bastore
    //   298: dup
    //   299: bipush #57
    //   301: iconst_0
    //   302: bastore
    //   303: dup
    //   304: bipush #58
    //   306: iconst_0
    //   307: bastore
    //   308: dup
    //   309: bipush #59
    //   311: iconst_0
    //   312: bastore
    //   313: dup
    //   314: bipush #60
    //   316: iconst_0
    //   317: bastore
    //   318: dup
    //   319: bipush #61
    //   321: iconst_0
    //   322: bastore
    //   323: dup
    //   324: bipush #62
    //   326: iconst_0
    //   327: bastore
    //   328: dup
    //   329: bipush #63
    //   331: iconst_0
    //   332: bastore
    //   333: astore #5
    //   335: bipush #64
    //   337: newarray int
    //   339: dup
    //   340: iconst_0
    //   341: ldc 1116352408
    //   343: iastore
    //   344: dup
    //   345: iconst_1
    //   346: ldc 1899447441
    //   348: iastore
    //   349: dup
    //   350: iconst_2
    //   351: ldc -1245643825
    //   353: iastore
    //   354: dup
    //   355: iconst_3
    //   356: ldc -373957723
    //   358: iastore
    //   359: dup
    //   360: iconst_4
    //   361: ldc 961987163
    //   363: iastore
    //   364: dup
    //   365: iconst_5
    //   366: ldc 1508970993
    //   368: iastore
    //   369: dup
    //   370: bipush #6
    //   372: ldc -1841331548
    //   374: iastore
    //   375: dup
    //   376: bipush #7
    //   378: ldc -1424204075
    //   380: iastore
    //   381: dup
    //   382: bipush #8
    //   384: ldc -670586216
    //   386: iastore
    //   387: dup
    //   388: bipush #9
    //   390: ldc 310598401
    //   392: iastore
    //   393: dup
    //   394: bipush #10
    //   396: ldc 607225278
    //   398: iastore
    //   399: dup
    //   400: bipush #11
    //   402: ldc 1426881987
    //   404: iastore
    //   405: dup
    //   406: bipush #12
    //   408: ldc 1925078388
    //   410: iastore
    //   411: dup
    //   412: bipush #13
    //   414: ldc -2132889090
    //   416: iastore
    //   417: dup
    //   418: bipush #14
    //   420: ldc -1680079193
    //   422: iastore
    //   423: dup
    //   424: bipush #15
    //   426: ldc -1046744716
    //   428: iastore
    //   429: dup
    //   430: bipush #16
    //   432: ldc -459576895
    //   434: iastore
    //   435: dup
    //   436: bipush #17
    //   438: ldc -272742522
    //   440: iastore
    //   441: dup
    //   442: bipush #18
    //   444: ldc 264347078
    //   446: iastore
    //   447: dup
    //   448: bipush #19
    //   450: ldc 604807628
    //   452: iastore
    //   453: dup
    //   454: bipush #20
    //   456: ldc 770255983
    //   458: iastore
    //   459: dup
    //   460: bipush #21
    //   462: ldc 1249150122
    //   464: iastore
    //   465: dup
    //   466: bipush #22
    //   468: ldc 1555081692
    //   470: iastore
    //   471: dup
    //   472: bipush #23
    //   474: ldc 1996064986
    //   476: iastore
    //   477: dup
    //   478: bipush #24
    //   480: ldc -1740746414
    //   482: iastore
    //   483: dup
    //   484: bipush #25
    //   486: ldc -1473132947
    //   488: iastore
    //   489: dup
    //   490: bipush #26
    //   492: ldc -1341970488
    //   494: iastore
    //   495: dup
    //   496: bipush #27
    //   498: ldc -1084653625
    //   500: iastore
    //   501: dup
    //   502: bipush #28
    //   504: ldc -958395405
    //   506: iastore
    //   507: dup
    //   508: bipush #29
    //   510: ldc -710438585
    //   512: iastore
    //   513: dup
    //   514: bipush #30
    //   516: ldc 113926993
    //   518: iastore
    //   519: dup
    //   520: bipush #31
    //   522: ldc 338241895
    //   524: iastore
    //   525: dup
    //   526: bipush #32
    //   528: ldc 666307205
    //   530: iastore
    //   531: dup
    //   532: bipush #33
    //   534: ldc 773529912
    //   536: iastore
    //   537: dup
    //   538: bipush #34
    //   540: ldc 1294757372
    //   542: iastore
    //   543: dup
    //   544: bipush #35
    //   546: ldc 1396182291
    //   548: iastore
    //   549: dup
    //   550: bipush #36
    //   552: ldc 1695183700
    //   554: iastore
    //   555: dup
    //   556: bipush #37
    //   558: ldc 1986661051
    //   560: iastore
    //   561: dup
    //   562: bipush #38
    //   564: ldc -2117940946
    //   566: iastore
    //   567: dup
    //   568: bipush #39
    //   570: ldc -1838011259
    //   572: iastore
    //   573: dup
    //   574: bipush #40
    //   576: ldc -1564481375
    //   578: iastore
    //   579: dup
    //   580: bipush #41
    //   582: ldc -1474664885
    //   584: iastore
    //   585: dup
    //   586: bipush #42
    //   588: ldc -1035236496
    //   590: iastore
    //   591: dup
    //   592: bipush #43
    //   594: ldc -949202525
    //   596: iastore
    //   597: dup
    //   598: bipush #44
    //   600: ldc -778901479
    //   602: iastore
    //   603: dup
    //   604: bipush #45
    //   606: ldc -694614492
    //   608: iastore
    //   609: dup
    //   610: bipush #46
    //   612: ldc -200395387
    //   614: iastore
    //   615: dup
    //   616: bipush #47
    //   618: ldc 275423344
    //   620: iastore
    //   621: dup
    //   622: bipush #48
    //   624: ldc 430227734
    //   626: iastore
    //   627: dup
    //   628: bipush #49
    //   630: ldc 506948616
    //   632: iastore
    //   633: dup
    //   634: bipush #50
    //   636: ldc 659060556
    //   638: iastore
    //   639: dup
    //   640: bipush #51
    //   642: ldc 883997877
    //   644: iastore
    //   645: dup
    //   646: bipush #52
    //   648: ldc 958139571
    //   650: iastore
    //   651: dup
    //   652: bipush #53
    //   654: ldc 1322822218
    //   656: iastore
    //   657: dup
    //   658: bipush #54
    //   660: ldc 1537002063
    //   662: iastore
    //   663: dup
    //   664: bipush #55
    //   666: ldc 1747873779
    //   668: iastore
    //   669: dup
    //   670: bipush #56
    //   672: ldc 1955562222
    //   674: iastore
    //   675: dup
    //   676: bipush #57
    //   678: ldc 2024104815
    //   680: iastore
    //   681: dup
    //   682: bipush #58
    //   684: ldc -2067236844
    //   686: iastore
    //   687: dup
    //   688: bipush #59
    //   690: ldc -1933114872
    //   692: iastore
    //   693: dup
    //   694: bipush #60
    //   696: ldc -1866530822
    //   698: iastore
    //   699: dup
    //   700: bipush #61
    //   702: ldc -1538233109
    //   704: iastore
    //   705: dup
    //   706: bipush #62
    //   708: ldc -1090935817
    //   710: iastore
    //   711: dup
    //   712: bipush #63
    //   714: ldc -965641998
    //   716: iastore
    //   717: astore #6
    //   719: iconst_2
    //   720: newarray int
    //   722: dup
    //   723: iconst_0
    //   724: iconst_0
    //   725: iastore
    //   726: dup
    //   727: iconst_1
    //   728: iconst_0
    //   729: iastore
    //   730: astore #7
    //   732: bipush #8
    //   734: newarray int
    //   736: dup
    //   737: iconst_0
    //   738: ldc 1779033703
    //   740: iastore
    //   741: dup
    //   742: iconst_1
    //   743: ldc -1150833019
    //   745: iastore
    //   746: dup
    //   747: iconst_2
    //   748: ldc 1013904242
    //   750: iastore
    //   751: dup
    //   752: iconst_3
    //   753: ldc -1521486534
    //   755: iastore
    //   756: dup
    //   757: iconst_4
    //   758: ldc 1359893119
    //   760: iastore
    //   761: dup
    //   762: iconst_5
    //   763: ldc -1694144372
    //   765: iastore
    //   766: dup
    //   767: bipush #6
    //   769: ldc 528734635
    //   771: iastore
    //   772: dup
    //   773: bipush #7
    //   775: ldc 1541459225
    //   777: iastore
    //   778: astore #8
    //   780: bipush #64
    //   782: newarray byte
    //   784: astore #9
    //   786: bipush #64
    //   788: newarray byte
    //   790: astore #10
    //   792: aload_3
    //   793: arraylength
    //   794: istore #11
    //   796: aload #7
    //   798: iconst_0
    //   799: iaload
    //   800: bipush #63
    //   802: iand
    //   803: istore #12
    //   805: aload #7
    //   807: iconst_0
    //   808: dup2
    //   809: iaload
    //   810: iload #11
    //   812: iadd
    //   813: iastore
    //   814: aload #7
    //   816: iconst_0
    //   817: dup2
    //   818: iaload
    //   819: iconst_m1
    //   820: iand
    //   821: iastore
    //   822: aload #7
    //   824: iconst_0
    //   825: iaload
    //   826: iload #11
    //   828: if_icmpge -> 846
    //   831: aload #7
    //   833: iconst_1
    //   834: dup2
    //   835: iaload
    //   836: iconst_1
    //   837: iadd
    //   838: iastore
    //   839: goto -> 846
    //   842: invokestatic a : (Ljava/lang/Throwable;)Ljava/lang/Throwable;
    //   845: athrow
    //   846: iconst_0
    //   847: istore #13
    //   849: iload #11
    //   851: bipush #64
    //   853: if_icmplt -> 1462
    //   856: iconst_0
    //   857: istore #14
    //   859: iload #14
    //   861: bipush #64
    //   863: if_icmpge -> 885
    //   866: aload #10
    //   868: iload #14
    //   870: aload_3
    //   871: iload #13
    //   873: iload #14
    //   875: iadd
    //   876: baload
    //   877: bastore
    //   878: iinc #14, 1
    //   881: iload_2
    //   882: ifne -> 859
    //   885: bipush #64
    //   887: newarray int
    //   889: astore #14
    //   891: bipush #8
    //   893: newarray int
    //   895: astore #15
    //   897: iconst_0
    //   898: istore #16
    //   900: iload #16
    //   902: bipush #8
    //   904: if_icmpge -> 924
    //   907: aload #15
    //   909: iload #16
    //   911: aload #8
    //   913: iload #16
    //   915: iaload
    //   916: iastore
    //   917: iinc #16, 1
    //   920: iload_2
    //   921: ifne -> 900
    //   924: iconst_0
    //   925: istore #16
    //   927: iload #16
    //   929: bipush #64
    //   931: if_icmpge -> 1422
    //   934: iload #16
    //   936: bipush #16
    //   938: if_icmpge -> 1019
    //   941: aload #14
    //   943: iload #16
    //   945: aload #10
    //   947: iconst_4
    //   948: iload #16
    //   950: imul
    //   951: baload
    //   952: sipush #255
    //   955: iand
    //   956: bipush #24
    //   958: ishl
    //   959: aload #10
    //   961: iconst_4
    //   962: iload #16
    //   964: imul
    //   965: iconst_1
    //   966: iadd
    //   967: baload
    //   968: sipush #255
    //   971: iand
    //   972: bipush #16
    //   974: ishl
    //   975: ior
    //   976: aload #10
    //   978: iconst_4
    //   979: iload #16
    //   981: imul
    //   982: iconst_2
    //   983: iadd
    //   984: baload
    //   985: sipush #255
    //   988: iand
    //   989: bipush #8
    //   991: ishl
    //   992: ior
    //   993: aload #10
    //   995: iconst_4
    //   996: iload #16
    //   998: imul
    //   999: iconst_3
    //   1000: iadd
    //   1001: baload
    //   1002: sipush #255
    //   1005: iand
    //   1006: ior
    //   1007: iastore
    //   1008: iload_2
    //   1009: ifne -> 1162
    //   1012: goto -> 1019
    //   1015: invokestatic a : (Ljava/lang/Throwable;)Ljava/lang/Throwable;
    //   1018: athrow
    //   1019: aload #14
    //   1021: iload #16
    //   1023: aload #14
    //   1025: iload #16
    //   1027: iconst_2
    //   1028: isub
    //   1029: iaload
    //   1030: bipush #17
    //   1032: iushr
    //   1033: aload #14
    //   1035: iload #16
    //   1037: iconst_2
    //   1038: isub
    //   1039: iaload
    //   1040: bipush #15
    //   1042: ishl
    //   1043: ior
    //   1044: aload #14
    //   1046: iload #16
    //   1048: iconst_2
    //   1049: isub
    //   1050: iaload
    //   1051: bipush #19
    //   1053: iushr
    //   1054: aload #14
    //   1056: iload #16
    //   1058: iconst_2
    //   1059: isub
    //   1060: iaload
    //   1061: bipush #13
    //   1063: ishl
    //   1064: ior
    //   1065: ixor
    //   1066: aload #14
    //   1068: iload #16
    //   1070: iconst_2
    //   1071: isub
    //   1072: iaload
    //   1073: bipush #10
    //   1075: iushr
    //   1076: ixor
    //   1077: aload #14
    //   1079: iload #16
    //   1081: bipush #7
    //   1083: isub
    //   1084: iaload
    //   1085: iadd
    //   1086: aload #14
    //   1088: iload #16
    //   1090: bipush #15
    //   1092: isub
    //   1093: iaload
    //   1094: bipush #7
    //   1096: iushr
    //   1097: aload #14
    //   1099: iload #16
    //   1101: bipush #15
    //   1103: isub
    //   1104: iaload
    //   1105: bipush #25
    //   1107: ishl
    //   1108: ior
    //   1109: aload #14
    //   1111: iload #16
    //   1113: bipush #15
    //   1115: isub
    //   1116: iaload
    //   1117: bipush #18
    //   1119: iushr
    //   1120: aload #14
    //   1122: iload #16
    //   1124: bipush #15
    //   1126: isub
    //   1127: iaload
    //   1128: bipush #14
    //   1130: ishl
    //   1131: ior
    //   1132: ixor
    //   1133: aload #14
    //   1135: iload #16
    //   1137: bipush #15
    //   1139: isub
    //   1140: iaload
    //   1141: iconst_3
    //   1142: iushr
    //   1143: ixor
    //   1144: iadd
    //   1145: aload #14
    //   1147: iload #16
    //   1149: bipush #16
    //   1151: isub
    //   1152: iaload
    //   1153: iadd
    //   1154: iastore
    //   1155: goto -> 1162
    //   1158: invokestatic a : (Ljava/lang/Throwable;)Ljava/lang/Throwable;
    //   1161: athrow
    //   1162: aload #15
    //   1164: bipush #7
    //   1166: iaload
    //   1167: aload #15
    //   1169: iconst_4
    //   1170: iaload
    //   1171: bipush #6
    //   1173: iushr
    //   1174: aload #15
    //   1176: iconst_4
    //   1177: iaload
    //   1178: bipush #26
    //   1180: ishl
    //   1181: ior
    //   1182: aload #15
    //   1184: iconst_4
    //   1185: iaload
    //   1186: bipush #11
    //   1188: iushr
    //   1189: aload #15
    //   1191: iconst_4
    //   1192: iaload
    //   1193: bipush #21
    //   1195: ishl
    //   1196: ior
    //   1197: ixor
    //   1198: aload #15
    //   1200: iconst_4
    //   1201: iaload
    //   1202: bipush #25
    //   1204: iushr
    //   1205: aload #15
    //   1207: iconst_4
    //   1208: iaload
    //   1209: bipush #7
    //   1211: ishl
    //   1212: ior
    //   1213: ixor
    //   1214: iadd
    //   1215: aload #15
    //   1217: bipush #6
    //   1219: iaload
    //   1220: aload #15
    //   1222: iconst_4
    //   1223: iaload
    //   1224: aload #15
    //   1226: iconst_5
    //   1227: iaload
    //   1228: aload #15
    //   1230: bipush #6
    //   1232: iaload
    //   1233: ixor
    //   1234: iand
    //   1235: ixor
    //   1236: iadd
    //   1237: aload #6
    //   1239: iload #16
    //   1241: iaload
    //   1242: iadd
    //   1243: aload #14
    //   1245: iload #16
    //   1247: iaload
    //   1248: iadd
    //   1249: istore #17
    //   1251: aload #15
    //   1253: iconst_0
    //   1254: iaload
    //   1255: iconst_2
    //   1256: iushr
    //   1257: aload #15
    //   1259: iconst_0
    //   1260: iaload
    //   1261: bipush #30
    //   1263: ishl
    //   1264: ior
    //   1265: aload #15
    //   1267: iconst_0
    //   1268: iaload
    //   1269: bipush #13
    //   1271: iushr
    //   1272: aload #15
    //   1274: iconst_0
    //   1275: iaload
    //   1276: bipush #19
    //   1278: ishl
    //   1279: ior
    //   1280: ixor
    //   1281: aload #15
    //   1283: iconst_0
    //   1284: iaload
    //   1285: bipush #22
    //   1287: iushr
    //   1288: aload #15
    //   1290: iconst_0
    //   1291: iaload
    //   1292: bipush #10
    //   1294: ishl
    //   1295: ior
    //   1296: ixor
    //   1297: aload #15
    //   1299: iconst_0
    //   1300: iaload
    //   1301: aload #15
    //   1303: iconst_1
    //   1304: iaload
    //   1305: iand
    //   1306: aload #15
    //   1308: iconst_2
    //   1309: iaload
    //   1310: aload #15
    //   1312: iconst_0
    //   1313: iaload
    //   1314: aload #15
    //   1316: iconst_1
    //   1317: iaload
    //   1318: ior
    //   1319: iand
    //   1320: ior
    //   1321: iadd
    //   1322: istore #18
    //   1324: aload #15
    //   1326: iconst_3
    //   1327: dup2
    //   1328: iaload
    //   1329: iload #17
    //   1331: iadd
    //   1332: iastore
    //   1333: aload #15
    //   1335: bipush #7
    //   1337: iload #17
    //   1339: iload #18
    //   1341: iadd
    //   1342: iastore
    //   1343: aload #15
    //   1345: bipush #7
    //   1347: iaload
    //   1348: istore #17
    //   1350: aload #15
    //   1352: bipush #7
    //   1354: aload #15
    //   1356: bipush #6
    //   1358: iaload
    //   1359: iastore
    //   1360: aload #15
    //   1362: bipush #6
    //   1364: aload #15
    //   1366: iconst_5
    //   1367: iaload
    //   1368: iastore
    //   1369: aload #15
    //   1371: iconst_5
    //   1372: aload #15
    //   1374: iconst_4
    //   1375: iaload
    //   1376: iastore
    //   1377: aload #15
    //   1379: iconst_4
    //   1380: aload #15
    //   1382: iconst_3
    //   1383: iaload
    //   1384: iastore
    //   1385: aload #15
    //   1387: iconst_3
    //   1388: aload #15
    //   1390: iconst_2
    //   1391: iaload
    //   1392: iastore
    //   1393: aload #15
    //   1395: iconst_2
    //   1396: aload #15
    //   1398: iconst_1
    //   1399: iaload
    //   1400: iastore
    //   1401: aload #15
    //   1403: iconst_1
    //   1404: aload #15
    //   1406: iconst_0
    //   1407: iaload
    //   1408: iastore
    //   1409: aload #15
    //   1411: iconst_0
    //   1412: iload #17
    //   1414: iastore
    //   1415: iinc #16, 1
    //   1418: iload_2
    //   1419: ifne -> 927
    //   1422: iconst_0
    //   1423: istore #16
    //   1425: iload #16
    //   1427: bipush #8
    //   1429: if_icmpge -> 1452
    //   1432: aload #8
    //   1434: iload #16
    //   1436: dup2
    //   1437: iaload
    //   1438: aload #15
    //   1440: iload #16
    //   1442: iaload
    //   1443: iadd
    //   1444: iastore
    //   1445: iinc #16, 1
    //   1448: iload_2
    //   1449: ifne -> 1425
    //   1452: iinc #13, 64
    //   1455: iinc #11, -64
    //   1458: iload_2
    //   1459: ifne -> 849
    //   1462: iload #11
    //   1464: ifle -> 1499
    //   1467: iconst_0
    //   1468: istore #14
    //   1470: iload #14
    //   1472: iload #11
    //   1474: if_icmpge -> 1499
    //   1477: aload #9
    //   1479: iload #12
    //   1481: iload #14
    //   1483: iadd
    //   1484: aload_3
    //   1485: iload #13
    //   1487: iload #14
    //   1489: iadd
    //   1490: baload
    //   1491: bastore
    //   1492: iinc #14, 1
    //   1495: iload_2
    //   1496: ifne -> 1470
    //   1499: aload #7
    //   1501: iconst_0
    //   1502: iaload
    //   1503: bipush #29
    //   1505: iushr
    //   1506: aload #7
    //   1508: iconst_1
    //   1509: iaload
    //   1510: iconst_3
    //   1511: ishl
    //   1512: ior
    //   1513: istore #14
    //   1515: aload #7
    //   1517: iconst_0
    //   1518: iaload
    //   1519: iconst_3
    //   1520: ishl
    //   1521: istore #15
    //   1523: aload #7
    //   1525: iconst_0
    //   1526: iaload
    //   1527: bipush #63
    //   1529: iand
    //   1530: istore #16
    //   1532: iload #16
    //   1534: bipush #56
    //   1536: if_icmpge -> 1551
    //   1539: bipush #56
    //   1541: iload #16
    //   1543: isub
    //   1544: goto -> 1556
    //   1547: invokestatic a : (Ljava/lang/Throwable;)Ljava/lang/Throwable;
    //   1550: athrow
    //   1551: bipush #120
    //   1553: iload #16
    //   1555: isub
    //   1556: istore #17
    //   1558: aload #7
    //   1560: iconst_0
    //   1561: iaload
    //   1562: bipush #63
    //   1564: iand
    //   1565: istore #12
    //   1567: bipush #64
    //   1569: iload #12
    //   1571: isub
    //   1572: istore #18
    //   1574: aload #7
    //   1576: iconst_0
    //   1577: dup2
    //   1578: iaload
    //   1579: iload #17
    //   1581: iadd
    //   1582: iastore
    //   1583: aload #7
    //   1585: iconst_0
    //   1586: dup2
    //   1587: iaload
    //   1588: iconst_m1
    //   1589: iand
    //   1590: iastore
    //   1591: aload #7
    //   1593: iconst_0
    //   1594: iaload
    //   1595: iload #17
    //   1597: if_icmpge -> 1615
    //   1600: aload #7
    //   1602: iconst_1
    //   1603: dup2
    //   1604: iaload
    //   1605: iconst_1
    //   1606: iadd
    //   1607: iastore
    //   1608: goto -> 1615
    //   1611: invokestatic a : (Ljava/lang/Throwable;)Ljava/lang/Throwable;
    //   1614: athrow
    //   1615: iconst_0
    //   1616: istore #13
    //   1618: iload #12
    //   1620: ifle -> 2251
    //   1623: iload #17
    //   1625: iload #18
    //   1627: if_icmplt -> 2251
    //   1630: goto -> 1637
    //   1633: invokestatic a : (Ljava/lang/Throwable;)Ljava/lang/Throwable;
    //   1636: athrow
    //   1637: iconst_0
    //   1638: istore #19
    //   1640: iload #19
    //   1642: iload #18
    //   1644: if_icmpge -> 1667
    //   1647: aload #9
    //   1649: iload #12
    //   1651: iload #19
    //   1653: iadd
    //   1654: aload #5
    //   1656: iload #19
    //   1658: baload
    //   1659: bastore
    //   1660: iinc #19, 1
    //   1663: iload_2
    //   1664: ifne -> 1640
    //   1667: bipush #64
    //   1669: newarray int
    //   1671: astore #19
    //   1673: bipush #8
    //   1675: newarray int
    //   1677: astore #20
    //   1679: iconst_0
    //   1680: istore #21
    //   1682: iload #21
    //   1684: bipush #8
    //   1686: if_icmpge -> 1706
    //   1689: aload #20
    //   1691: iload #21
    //   1693: aload #8
    //   1695: iload #21
    //   1697: iaload
    //   1698: iastore
    //   1699: iinc #21, 1
    //   1702: iload_2
    //   1703: ifne -> 1682
    //   1706: iconst_0
    //   1707: istore #21
    //   1709: iload #21
    //   1711: bipush #64
    //   1713: if_icmpge -> 2204
    //   1716: iload #21
    //   1718: bipush #16
    //   1720: if_icmpge -> 1801
    //   1723: aload #19
    //   1725: iload #21
    //   1727: aload #9
    //   1729: iconst_4
    //   1730: iload #21
    //   1732: imul
    //   1733: baload
    //   1734: sipush #255
    //   1737: iand
    //   1738: bipush #24
    //   1740: ishl
    //   1741: aload #9
    //   1743: iconst_4
    //   1744: iload #21
    //   1746: imul
    //   1747: iconst_1
    //   1748: iadd
    //   1749: baload
    //   1750: sipush #255
    //   1753: iand
    //   1754: bipush #16
    //   1756: ishl
    //   1757: ior
    //   1758: aload #9
    //   1760: iconst_4
    //   1761: iload #21
    //   1763: imul
    //   1764: iconst_2
    //   1765: iadd
    //   1766: baload
    //   1767: sipush #255
    //   1770: iand
    //   1771: bipush #8
    //   1773: ishl
    //   1774: ior
    //   1775: aload #9
    //   1777: iconst_4
    //   1778: iload #21
    //   1780: imul
    //   1781: iconst_3
    //   1782: iadd
    //   1783: baload
    //   1784: sipush #255
    //   1787: iand
    //   1788: ior
    //   1789: iastore
    //   1790: iload_2
    //   1791: ifne -> 1944
    //   1794: goto -> 1801
    //   1797: invokestatic a : (Ljava/lang/Throwable;)Ljava/lang/Throwable;
    //   1800: athrow
    //   1801: aload #19
    //   1803: iload #21
    //   1805: aload #19
    //   1807: iload #21
    //   1809: iconst_2
    //   1810: isub
    //   1811: iaload
    //   1812: bipush #17
    //   1814: iushr
    //   1815: aload #19
    //   1817: iload #21
    //   1819: iconst_2
    //   1820: isub
    //   1821: iaload
    //   1822: bipush #15
    //   1824: ishl
    //   1825: ior
    //   1826: aload #19
    //   1828: iload #21
    //   1830: iconst_2
    //   1831: isub
    //   1832: iaload
    //   1833: bipush #19
    //   1835: iushr
    //   1836: aload #19
    //   1838: iload #21
    //   1840: iconst_2
    //   1841: isub
    //   1842: iaload
    //   1843: bipush #13
    //   1845: ishl
    //   1846: ior
    //   1847: ixor
    //   1848: aload #19
    //   1850: iload #21
    //   1852: iconst_2
    //   1853: isub
    //   1854: iaload
    //   1855: bipush #10
    //   1857: iushr
    //   1858: ixor
    //   1859: aload #19
    //   1861: iload #21
    //   1863: bipush #7
    //   1865: isub
    //   1866: iaload
    //   1867: iadd
    //   1868: aload #19
    //   1870: iload #21
    //   1872: bipush #15
    //   1874: isub
    //   1875: iaload
    //   1876: bipush #7
    //   1878: iushr
    //   1879: aload #19
    //   1881: iload #21
    //   1883: bipush #15
    //   1885: isub
    //   1886: iaload
    //   1887: bipush #25
    //   1889: ishl
    //   1890: ior
    //   1891: aload #19
    //   1893: iload #21
    //   1895: bipush #15
    //   1897: isub
    //   1898: iaload
    //   1899: bipush #18
    //   1901: iushr
    //   1902: aload #19
    //   1904: iload #21
    //   1906: bipush #15
    //   1908: isub
    //   1909: iaload
    //   1910: bipush #14
    //   1912: ishl
    //   1913: ior
    //   1914: ixor
    //   1915: aload #19
    //   1917: iload #21
    //   1919: bipush #15
    //   1921: isub
    //   1922: iaload
    //   1923: iconst_3
    //   1924: iushr
    //   1925: ixor
    //   1926: iadd
    //   1927: aload #19
    //   1929: iload #21
    //   1931: bipush #16
    //   1933: isub
    //   1934: iaload
    //   1935: iadd
    //   1936: iastore
    //   1937: goto -> 1944
    //   1940: invokestatic a : (Ljava/lang/Throwable;)Ljava/lang/Throwable;
    //   1943: athrow
    //   1944: aload #20
    //   1946: bipush #7
    //   1948: iaload
    //   1949: aload #20
    //   1951: iconst_4
    //   1952: iaload
    //   1953: bipush #6
    //   1955: iushr
    //   1956: aload #20
    //   1958: iconst_4
    //   1959: iaload
    //   1960: bipush #26
    //   1962: ishl
    //   1963: ior
    //   1964: aload #20
    //   1966: iconst_4
    //   1967: iaload
    //   1968: bipush #11
    //   1970: iushr
    //   1971: aload #20
    //   1973: iconst_4
    //   1974: iaload
    //   1975: bipush #21
    //   1977: ishl
    //   1978: ior
    //   1979: ixor
    //   1980: aload #20
    //   1982: iconst_4
    //   1983: iaload
    //   1984: bipush #25
    //   1986: iushr
    //   1987: aload #20
    //   1989: iconst_4
    //   1990: iaload
    //   1991: bipush #7
    //   1993: ishl
    //   1994: ior
    //   1995: ixor
    //   1996: iadd
    //   1997: aload #20
    //   1999: bipush #6
    //   2001: iaload
    //   2002: aload #20
    //   2004: iconst_4
    //   2005: iaload
    //   2006: aload #20
    //   2008: iconst_5
    //   2009: iaload
    //   2010: aload #20
    //   2012: bipush #6
    //   2014: iaload
    //   2015: ixor
    //   2016: iand
    //   2017: ixor
    //   2018: iadd
    //   2019: aload #6
    //   2021: iload #21
    //   2023: iaload
    //   2024: iadd
    //   2025: aload #19
    //   2027: iload #21
    //   2029: iaload
    //   2030: iadd
    //   2031: istore #22
    //   2033: aload #20
    //   2035: iconst_0
    //   2036: iaload
    //   2037: iconst_2
    //   2038: iushr
    //   2039: aload #20
    //   2041: iconst_0
    //   2042: iaload
    //   2043: bipush #30
    //   2045: ishl
    //   2046: ior
    //   2047: aload #20
    //   2049: iconst_0
    //   2050: iaload
    //   2051: bipush #13
    //   2053: iushr
    //   2054: aload #20
    //   2056: iconst_0
    //   2057: iaload
    //   2058: bipush #19
    //   2060: ishl
    //   2061: ior
    //   2062: ixor
    //   2063: aload #20
    //   2065: iconst_0
    //   2066: iaload
    //   2067: bipush #22
    //   2069: iushr
    //   2070: aload #20
    //   2072: iconst_0
    //   2073: iaload
    //   2074: bipush #10
    //   2076: ishl
    //   2077: ior
    //   2078: ixor
    //   2079: aload #20
    //   2081: iconst_0
    //   2082: iaload
    //   2083: aload #20
    //   2085: iconst_1
    //   2086: iaload
    //   2087: iand
    //   2088: aload #20
    //   2090: iconst_2
    //   2091: iaload
    //   2092: aload #20
    //   2094: iconst_0
    //   2095: iaload
    //   2096: aload #20
    //   2098: iconst_1
    //   2099: iaload
    //   2100: ior
    //   2101: iand
    //   2102: ior
    //   2103: iadd
    //   2104: istore #23
    //   2106: aload #20
    //   2108: iconst_3
    //   2109: dup2
    //   2110: iaload
    //   2111: iload #22
    //   2113: iadd
    //   2114: iastore
    //   2115: aload #20
    //   2117: bipush #7
    //   2119: iload #22
    //   2121: iload #23
    //   2123: iadd
    //   2124: iastore
    //   2125: aload #20
    //   2127: bipush #7
    //   2129: iaload
    //   2130: istore #22
    //   2132: aload #20
    //   2134: bipush #7
    //   2136: aload #20
    //   2138: bipush #6
    //   2140: iaload
    //   2141: iastore
    //   2142: aload #20
    //   2144: bipush #6
    //   2146: aload #20
    //   2148: iconst_5
    //   2149: iaload
    //   2150: iastore
    //   2151: aload #20
    //   2153: iconst_5
    //   2154: aload #20
    //   2156: iconst_4
    //   2157: iaload
    //   2158: iastore
    //   2159: aload #20
    //   2161: iconst_4
    //   2162: aload #20
    //   2164: iconst_3
    //   2165: iaload
    //   2166: iastore
    //   2167: aload #20
    //   2169: iconst_3
    //   2170: aload #20
    //   2172: iconst_2
    //   2173: iaload
    //   2174: iastore
    //   2175: aload #20
    //   2177: iconst_2
    //   2178: aload #20
    //   2180: iconst_1
    //   2181: iaload
    //   2182: iastore
    //   2183: aload #20
    //   2185: iconst_1
    //   2186: aload #20
    //   2188: iconst_0
    //   2189: iaload
    //   2190: iastore
    //   2191: aload #20
    //   2193: iconst_0
    //   2194: iload #22
    //   2196: iastore
    //   2197: iinc #21, 1
    //   2200: iload_2
    //   2201: ifne -> 1709
    //   2204: iconst_0
    //   2205: istore #21
    //   2207: iload #21
    //   2209: bipush #8
    //   2211: if_icmpge -> 2234
    //   2214: aload #8
    //   2216: iload #21
    //   2218: dup2
    //   2219: iaload
    //   2220: aload #20
    //   2222: iload #21
    //   2224: iaload
    //   2225: iadd
    //   2226: iastore
    //   2227: iinc #21, 1
    //   2230: iload_2
    //   2231: ifne -> 2207
    //   2234: iload #13
    //   2236: iload #18
    //   2238: iadd
    //   2239: istore #13
    //   2241: iload #17
    //   2243: iload #18
    //   2245: isub
    //   2246: istore #17
    //   2248: iconst_0
    //   2249: istore #12
    //   2251: iload #17
    //   2253: bipush #64
    //   2255: if_icmplt -> 2865
    //   2258: iconst_0
    //   2259: istore #19
    //   2261: iload #19
    //   2263: bipush #64
    //   2265: if_icmpge -> 2288
    //   2268: aload #10
    //   2270: iload #19
    //   2272: aload #5
    //   2274: iload #13
    //   2276: iload #19
    //   2278: iadd
    //   2279: baload
    //   2280: bastore
    //   2281: iinc #19, 1
    //   2284: iload_2
    //   2285: ifne -> 2261
    //   2288: bipush #64
    //   2290: newarray int
    //   2292: astore #19
    //   2294: bipush #8
    //   2296: newarray int
    //   2298: astore #20
    //   2300: iconst_0
    //   2301: istore #21
    //   2303: iload #21
    //   2305: bipush #8
    //   2307: if_icmpge -> 2327
    //   2310: aload #20
    //   2312: iload #21
    //   2314: aload #8
    //   2316: iload #21
    //   2318: iaload
    //   2319: iastore
    //   2320: iinc #21, 1
    //   2323: iload_2
    //   2324: ifne -> 2303
    //   2327: iconst_0
    //   2328: istore #21
    //   2330: iload #21
    //   2332: bipush #64
    //   2334: if_icmpge -> 2825
    //   2337: iload #21
    //   2339: bipush #16
    //   2341: if_icmpge -> 2422
    //   2344: aload #19
    //   2346: iload #21
    //   2348: aload #10
    //   2350: iconst_4
    //   2351: iload #21
    //   2353: imul
    //   2354: baload
    //   2355: sipush #255
    //   2358: iand
    //   2359: bipush #24
    //   2361: ishl
    //   2362: aload #10
    //   2364: iconst_4
    //   2365: iload #21
    //   2367: imul
    //   2368: iconst_1
    //   2369: iadd
    //   2370: baload
    //   2371: sipush #255
    //   2374: iand
    //   2375: bipush #16
    //   2377: ishl
    //   2378: ior
    //   2379: aload #10
    //   2381: iconst_4
    //   2382: iload #21
    //   2384: imul
    //   2385: iconst_2
    //   2386: iadd
    //   2387: baload
    //   2388: sipush #255
    //   2391: iand
    //   2392: bipush #8
    //   2394: ishl
    //   2395: ior
    //   2396: aload #10
    //   2398: iconst_4
    //   2399: iload #21
    //   2401: imul
    //   2402: iconst_3
    //   2403: iadd
    //   2404: baload
    //   2405: sipush #255
    //   2408: iand
    //   2409: ior
    //   2410: iastore
    //   2411: iload_2
    //   2412: ifne -> 2565
    //   2415: goto -> 2422
    //   2418: invokestatic a : (Ljava/lang/Throwable;)Ljava/lang/Throwable;
    //   2421: athrow
    //   2422: aload #19
    //   2424: iload #21
    //   2426: aload #19
    //   2428: iload #21
    //   2430: iconst_2
    //   2431: isub
    //   2432: iaload
    //   2433: bipush #17
    //   2435: iushr
    //   2436: aload #19
    //   2438: iload #21
    //   2440: iconst_2
    //   2441: isub
    //   2442: iaload
    //   2443: bipush #15
    //   2445: ishl
    //   2446: ior
    //   2447: aload #19
    //   2449: iload #21
    //   2451: iconst_2
    //   2452: isub
    //   2453: iaload
    //   2454: bipush #19
    //   2456: iushr
    //   2457: aload #19
    //   2459: iload #21
    //   2461: iconst_2
    //   2462: isub
    //   2463: iaload
    //   2464: bipush #13
    //   2466: ishl
    //   2467: ior
    //   2468: ixor
    //   2469: aload #19
    //   2471: iload #21
    //   2473: iconst_2
    //   2474: isub
    //   2475: iaload
    //   2476: bipush #10
    //   2478: iushr
    //   2479: ixor
    //   2480: aload #19
    //   2482: iload #21
    //   2484: bipush #7
    //   2486: isub
    //   2487: iaload
    //   2488: iadd
    //   2489: aload #19
    //   2491: iload #21
    //   2493: bipush #15
    //   2495: isub
    //   2496: iaload
    //   2497: bipush #7
    //   2499: iushr
    //   2500: aload #19
    //   2502: iload #21
    //   2504: bipush #15
    //   2506: isub
    //   2507: iaload
    //   2508: bipush #25
    //   2510: ishl
    //   2511: ior
    //   2512: aload #19
    //   2514: iload #21
    //   2516: bipush #15
    //   2518: isub
    //   2519: iaload
    //   2520: bipush #18
    //   2522: iushr
    //   2523: aload #19
    //   2525: iload #21
    //   2527: bipush #15
    //   2529: isub
    //   2530: iaload
    //   2531: bipush #14
    //   2533: ishl
    //   2534: ior
    //   2535: ixor
    //   2536: aload #19
    //   2538: iload #21
    //   2540: bipush #15
    //   2542: isub
    //   2543: iaload
    //   2544: iconst_3
    //   2545: iushr
    //   2546: ixor
    //   2547: iadd
    //   2548: aload #19
    //   2550: iload #21
    //   2552: bipush #16
    //   2554: isub
    //   2555: iaload
    //   2556: iadd
    //   2557: iastore
    //   2558: goto -> 2565
    //   2561: invokestatic a : (Ljava/lang/Throwable;)Ljava/lang/Throwable;
    //   2564: athrow
    //   2565: aload #20
    //   2567: bipush #7
    //   2569: iaload
    //   2570: aload #20
    //   2572: iconst_4
    //   2573: iaload
    //   2574: bipush #6
    //   2576: iushr
    //   2577: aload #20
    //   2579: iconst_4
    //   2580: iaload
    //   2581: bipush #26
    //   2583: ishl
    //   2584: ior
    //   2585: aload #20
    //   2587: iconst_4
    //   2588: iaload
    //   2589: bipush #11
    //   2591: iushr
    //   2592: aload #20
    //   2594: iconst_4
    //   2595: iaload
    //   2596: bipush #21
    //   2598: ishl
    //   2599: ior
    //   2600: ixor
    //   2601: aload #20
    //   2603: iconst_4
    //   2604: iaload
    //   2605: bipush #25
    //   2607: iushr
    //   2608: aload #20
    //   2610: iconst_4
    //   2611: iaload
    //   2612: bipush #7
    //   2614: ishl
    //   2615: ior
    //   2616: ixor
    //   2617: iadd
    //   2618: aload #20
    //   2620: bipush #6
    //   2622: iaload
    //   2623: aload #20
    //   2625: iconst_4
    //   2626: iaload
    //   2627: aload #20
    //   2629: iconst_5
    //   2630: iaload
    //   2631: aload #20
    //   2633: bipush #6
    //   2635: iaload
    //   2636: ixor
    //   2637: iand
    //   2638: ixor
    //   2639: iadd
    //   2640: aload #6
    //   2642: iload #21
    //   2644: iaload
    //   2645: iadd
    //   2646: aload #19
    //   2648: iload #21
    //   2650: iaload
    //   2651: iadd
    //   2652: istore #22
    //   2654: aload #20
    //   2656: iconst_0
    //   2657: iaload
    //   2658: iconst_2
    //   2659: iushr
    //   2660: aload #20
    //   2662: iconst_0
    //   2663: iaload
    //   2664: bipush #30
    //   2666: ishl
    //   2667: ior
    //   2668: aload #20
    //   2670: iconst_0
    //   2671: iaload
    //   2672: bipush #13
    //   2674: iushr
    //   2675: aload #20
    //   2677: iconst_0
    //   2678: iaload
    //   2679: bipush #19
    //   2681: ishl
    //   2682: ior
    //   2683: ixor
    //   2684: aload #20
    //   2686: iconst_0
    //   2687: iaload
    //   2688: bipush #22
    //   2690: iushr
    //   2691: aload #20
    //   2693: iconst_0
    //   2694: iaload
    //   2695: bipush #10
    //   2697: ishl
    //   2698: ior
    //   2699: ixor
    //   2700: aload #20
    //   2702: iconst_0
    //   2703: iaload
    //   2704: aload #20
    //   2706: iconst_1
    //   2707: iaload
    //   2708: iand
    //   2709: aload #20
    //   2711: iconst_2
    //   2712: iaload
    //   2713: aload #20
    //   2715: iconst_0
    //   2716: iaload
    //   2717: aload #20
    //   2719: iconst_1
    //   2720: iaload
    //   2721: ior
    //   2722: iand
    //   2723: ior
    //   2724: iadd
    //   2725: istore #23
    //   2727: aload #20
    //   2729: iconst_3
    //   2730: dup2
    //   2731: iaload
    //   2732: iload #22
    //   2734: iadd
    //   2735: iastore
    //   2736: aload #20
    //   2738: bipush #7
    //   2740: iload #22
    //   2742: iload #23
    //   2744: iadd
    //   2745: iastore
    //   2746: aload #20
    //   2748: bipush #7
    //   2750: iaload
    //   2751: istore #22
    //   2753: aload #20
    //   2755: bipush #7
    //   2757: aload #20
    //   2759: bipush #6
    //   2761: iaload
    //   2762: iastore
    //   2763: aload #20
    //   2765: bipush #6
    //   2767: aload #20
    //   2769: iconst_5
    //   2770: iaload
    //   2771: iastore
    //   2772: aload #20
    //   2774: iconst_5
    //   2775: aload #20
    //   2777: iconst_4
    //   2778: iaload
    //   2779: iastore
    //   2780: aload #20
    //   2782: iconst_4
    //   2783: aload #20
    //   2785: iconst_3
    //   2786: iaload
    //   2787: iastore
    //   2788: aload #20
    //   2790: iconst_3
    //   2791: aload #20
    //   2793: iconst_2
    //   2794: iaload
    //   2795: iastore
    //   2796: aload #20
    //   2798: iconst_2
    //   2799: aload #20
    //   2801: iconst_1
    //   2802: iaload
    //   2803: iastore
    //   2804: aload #20
    //   2806: iconst_1
    //   2807: aload #20
    //   2809: iconst_0
    //   2810: iaload
    //   2811: iastore
    //   2812: aload #20
    //   2814: iconst_0
    //   2815: iload #22
    //   2817: iastore
    //   2818: iinc #21, 1
    //   2821: iload_2
    //   2822: ifne -> 2330
    //   2825: iconst_0
    //   2826: istore #21
    //   2828: iload #21
    //   2830: bipush #8
    //   2832: if_icmpge -> 2855
    //   2835: aload #8
    //   2837: iload #21
    //   2839: dup2
    //   2840: iaload
    //   2841: aload #20
    //   2843: iload #21
    //   2845: iaload
    //   2846: iadd
    //   2847: iastore
    //   2848: iinc #21, 1
    //   2851: iload_2
    //   2852: ifne -> 2828
    //   2855: iinc #13, 64
    //   2858: iinc #17, -64
    //   2861: iload_2
    //   2862: ifne -> 2251
    //   2865: iload #17
    //   2867: ifle -> 2903
    //   2870: iconst_0
    //   2871: istore #19
    //   2873: iload #19
    //   2875: iload #17
    //   2877: if_icmpge -> 2903
    //   2880: aload #9
    //   2882: iload #12
    //   2884: iload #19
    //   2886: iadd
    //   2887: aload #5
    //   2889: iload #13
    //   2891: iload #19
    //   2893: iadd
    //   2894: baload
    //   2895: bastore
    //   2896: iinc #19, 1
    //   2899: iload_2
    //   2900: ifne -> 2873
    //   2903: bipush #8
    //   2905: newarray byte
    //   2907: astore #19
    //   2909: aload #19
    //   2911: iconst_0
    //   2912: iload #14
    //   2914: bipush #24
    //   2916: iushr
    //   2917: i2b
    //   2918: bastore
    //   2919: aload #19
    //   2921: iconst_1
    //   2922: iload #14
    //   2924: bipush #16
    //   2926: iushr
    //   2927: i2b
    //   2928: bastore
    //   2929: aload #19
    //   2931: iconst_2
    //   2932: iload #14
    //   2934: bipush #8
    //   2936: iushr
    //   2937: i2b
    //   2938: bastore
    //   2939: aload #19
    //   2941: iconst_3
    //   2942: iload #14
    //   2944: i2b
    //   2945: bastore
    //   2946: aload #19
    //   2948: iconst_4
    //   2949: iload #15
    //   2951: bipush #24
    //   2953: iushr
    //   2954: i2b
    //   2955: bastore
    //   2956: aload #19
    //   2958: iconst_5
    //   2959: iload #15
    //   2961: bipush #16
    //   2963: iushr
    //   2964: i2b
    //   2965: bastore
    //   2966: aload #19
    //   2968: bipush #6
    //   2970: iload #15
    //   2972: bipush #8
    //   2974: iushr
    //   2975: i2b
    //   2976: bastore
    //   2977: aload #19
    //   2979: bipush #7
    //   2981: iload #15
    //   2983: i2b
    //   2984: bastore
    //   2985: bipush #8
    //   2987: istore #11
    //   2989: aload #7
    //   2991: iconst_0
    //   2992: iaload
    //   2993: bipush #63
    //   2995: iand
    //   2996: istore #12
    //   2998: bipush #64
    //   3000: iload #12
    //   3002: isub
    //   3003: istore #18
    //   3005: aload #7
    //   3007: iconst_0
    //   3008: dup2
    //   3009: iaload
    //   3010: iload #11
    //   3012: iadd
    //   3013: iastore
    //   3014: aload #7
    //   3016: iconst_0
    //   3017: dup2
    //   3018: iaload
    //   3019: iconst_m1
    //   3020: iand
    //   3021: iastore
    //   3022: aload #7
    //   3024: iconst_0
    //   3025: iaload
    //   3026: iload #11
    //   3028: if_icmpge -> 3046
    //   3031: aload #7
    //   3033: iconst_1
    //   3034: dup2
    //   3035: iaload
    //   3036: iconst_1
    //   3037: iadd
    //   3038: iastore
    //   3039: goto -> 3046
    //   3042: invokestatic a : (Ljava/lang/Throwable;)Ljava/lang/Throwable;
    //   3045: athrow
    //   3046: iload #12
    //   3048: ifle -> 3662
    //   3051: iload #11
    //   3053: iload #18
    //   3055: if_icmplt -> 3662
    //   3058: goto -> 3065
    //   3061: invokestatic a : (Ljava/lang/Throwable;)Ljava/lang/Throwable;
    //   3064: athrow
    //   3065: iconst_0
    //   3066: istore #20
    //   3068: iload #20
    //   3070: iload #18
    //   3072: if_icmpge -> 3095
    //   3075: aload #9
    //   3077: iload #12
    //   3079: iload #20
    //   3081: iadd
    //   3082: aload #19
    //   3084: iload #20
    //   3086: baload
    //   3087: bastore
    //   3088: iinc #20, 1
    //   3091: iload_2
    //   3092: ifne -> 3068
    //   3095: bipush #64
    //   3097: newarray int
    //   3099: astore #20
    //   3101: bipush #8
    //   3103: newarray int
    //   3105: astore #21
    //   3107: iconst_0
    //   3108: istore #22
    //   3110: iload #22
    //   3112: bipush #8
    //   3114: if_icmpge -> 3134
    //   3117: aload #21
    //   3119: iload #22
    //   3121: aload #8
    //   3123: iload #22
    //   3125: iaload
    //   3126: iastore
    //   3127: iinc #22, 1
    //   3130: iload_2
    //   3131: ifne -> 3110
    //   3134: iconst_0
    //   3135: istore #22
    //   3137: iload #22
    //   3139: bipush #64
    //   3141: if_icmpge -> 3632
    //   3144: iload #22
    //   3146: bipush #16
    //   3148: if_icmpge -> 3229
    //   3151: aload #20
    //   3153: iload #22
    //   3155: aload #9
    //   3157: iconst_4
    //   3158: iload #22
    //   3160: imul
    //   3161: baload
    //   3162: sipush #255
    //   3165: iand
    //   3166: bipush #24
    //   3168: ishl
    //   3169: aload #9
    //   3171: iconst_4
    //   3172: iload #22
    //   3174: imul
    //   3175: iconst_1
    //   3176: iadd
    //   3177: baload
    //   3178: sipush #255
    //   3181: iand
    //   3182: bipush #16
    //   3184: ishl
    //   3185: ior
    //   3186: aload #9
    //   3188: iconst_4
    //   3189: iload #22
    //   3191: imul
    //   3192: iconst_2
    //   3193: iadd
    //   3194: baload
    //   3195: sipush #255
    //   3198: iand
    //   3199: bipush #8
    //   3201: ishl
    //   3202: ior
    //   3203: aload #9
    //   3205: iconst_4
    //   3206: iload #22
    //   3208: imul
    //   3209: iconst_3
    //   3210: iadd
    //   3211: baload
    //   3212: sipush #255
    //   3215: iand
    //   3216: ior
    //   3217: iastore
    //   3218: iload_2
    //   3219: ifne -> 3372
    //   3222: goto -> 3229
    //   3225: invokestatic a : (Ljava/lang/Throwable;)Ljava/lang/Throwable;
    //   3228: athrow
    //   3229: aload #20
    //   3231: iload #22
    //   3233: aload #20
    //   3235: iload #22
    //   3237: iconst_2
    //   3238: isub
    //   3239: iaload
    //   3240: bipush #17
    //   3242: iushr
    //   3243: aload #20
    //   3245: iload #22
    //   3247: iconst_2
    //   3248: isub
    //   3249: iaload
    //   3250: bipush #15
    //   3252: ishl
    //   3253: ior
    //   3254: aload #20
    //   3256: iload #22
    //   3258: iconst_2
    //   3259: isub
    //   3260: iaload
    //   3261: bipush #19
    //   3263: iushr
    //   3264: aload #20
    //   3266: iload #22
    //   3268: iconst_2
    //   3269: isub
    //   3270: iaload
    //   3271: bipush #13
    //   3273: ishl
    //   3274: ior
    //   3275: ixor
    //   3276: aload #20
    //   3278: iload #22
    //   3280: iconst_2
    //   3281: isub
    //   3282: iaload
    //   3283: bipush #10
    //   3285: iushr
    //   3286: ixor
    //   3287: aload #20
    //   3289: iload #22
    //   3291: bipush #7
    //   3293: isub
    //   3294: iaload
    //   3295: iadd
    //   3296: aload #20
    //   3298: iload #22
    //   3300: bipush #15
    //   3302: isub
    //   3303: iaload
    //   3304: bipush #7
    //   3306: iushr
    //   3307: aload #20
    //   3309: iload #22
    //   3311: bipush #15
    //   3313: isub
    //   3314: iaload
    //   3315: bipush #25
    //   3317: ishl
    //   3318: ior
    //   3319: aload #20
    //   3321: iload #22
    //   3323: bipush #15
    //   3325: isub
    //   3326: iaload
    //   3327: bipush #18
    //   3329: iushr
    //   3330: aload #20
    //   3332: iload #22
    //   3334: bipush #15
    //   3336: isub
    //   3337: iaload
    //   3338: bipush #14
    //   3340: ishl
    //   3341: ior
    //   3342: ixor
    //   3343: aload #20
    //   3345: iload #22
    //   3347: bipush #15
    //   3349: isub
    //   3350: iaload
    //   3351: iconst_3
    //   3352: iushr
    //   3353: ixor
    //   3354: iadd
    //   3355: aload #20
    //   3357: iload #22
    //   3359: bipush #16
    //   3361: isub
    //   3362: iaload
    //   3363: iadd
    //   3364: iastore
    //   3365: goto -> 3372
    //   3368: invokestatic a : (Ljava/lang/Throwable;)Ljava/lang/Throwable;
    //   3371: athrow
    //   3372: aload #21
    //   3374: bipush #7
    //   3376: iaload
    //   3377: aload #21
    //   3379: iconst_4
    //   3380: iaload
    //   3381: bipush #6
    //   3383: iushr
    //   3384: aload #21
    //   3386: iconst_4
    //   3387: iaload
    //   3388: bipush #26
    //   3390: ishl
    //   3391: ior
    //   3392: aload #21
    //   3394: iconst_4
    //   3395: iaload
    //   3396: bipush #11
    //   3398: iushr
    //   3399: aload #21
    //   3401: iconst_4
    //   3402: iaload
    //   3403: bipush #21
    //   3405: ishl
    //   3406: ior
    //   3407: ixor
    //   3408: aload #21
    //   3410: iconst_4
    //   3411: iaload
    //   3412: bipush #25
    //   3414: iushr
    //   3415: aload #21
    //   3417: iconst_4
    //   3418: iaload
    //   3419: bipush #7
    //   3421: ishl
    //   3422: ior
    //   3423: ixor
    //   3424: iadd
    //   3425: aload #21
    //   3427: bipush #6
    //   3429: iaload
    //   3430: aload #21
    //   3432: iconst_4
    //   3433: iaload
    //   3434: aload #21
    //   3436: iconst_5
    //   3437: iaload
    //   3438: aload #21
    //   3440: bipush #6
    //   3442: iaload
    //   3443: ixor
    //   3444: iand
    //   3445: ixor
    //   3446: iadd
    //   3447: aload #6
    //   3449: iload #22
    //   3451: iaload
    //   3452: iadd
    //   3453: aload #20
    //   3455: iload #22
    //   3457: iaload
    //   3458: iadd
    //   3459: istore #23
    //   3461: aload #21
    //   3463: iconst_0
    //   3464: iaload
    //   3465: iconst_2
    //   3466: iushr
    //   3467: aload #21
    //   3469: iconst_0
    //   3470: iaload
    //   3471: bipush #30
    //   3473: ishl
    //   3474: ior
    //   3475: aload #21
    //   3477: iconst_0
    //   3478: iaload
    //   3479: bipush #13
    //   3481: iushr
    //   3482: aload #21
    //   3484: iconst_0
    //   3485: iaload
    //   3486: bipush #19
    //   3488: ishl
    //   3489: ior
    //   3490: ixor
    //   3491: aload #21
    //   3493: iconst_0
    //   3494: iaload
    //   3495: bipush #22
    //   3497: iushr
    //   3498: aload #21
    //   3500: iconst_0
    //   3501: iaload
    //   3502: bipush #10
    //   3504: ishl
    //   3505: ior
    //   3506: ixor
    //   3507: aload #21
    //   3509: iconst_0
    //   3510: iaload
    //   3511: aload #21
    //   3513: iconst_1
    //   3514: iaload
    //   3515: iand
    //   3516: aload #21
    //   3518: iconst_2
    //   3519: iaload
    //   3520: aload #21
    //   3522: iconst_0
    //   3523: iaload
    //   3524: aload #21
    //   3526: iconst_1
    //   3527: iaload
    //   3528: ior
    //   3529: iand
    //   3530: ior
    //   3531: iadd
    //   3532: istore #24
    //   3534: aload #21
    //   3536: iconst_3
    //   3537: dup2
    //   3538: iaload
    //   3539: iload #23
    //   3541: iadd
    //   3542: iastore
    //   3543: aload #21
    //   3545: bipush #7
    //   3547: iload #23
    //   3549: iload #24
    //   3551: iadd
    //   3552: iastore
    //   3553: aload #21
    //   3555: bipush #7
    //   3557: iaload
    //   3558: istore #23
    //   3560: aload #21
    //   3562: bipush #7
    //   3564: aload #21
    //   3566: bipush #6
    //   3568: iaload
    //   3569: iastore
    //   3570: aload #21
    //   3572: bipush #6
    //   3574: aload #21
    //   3576: iconst_5
    //   3577: iaload
    //   3578: iastore
    //   3579: aload #21
    //   3581: iconst_5
    //   3582: aload #21
    //   3584: iconst_4
    //   3585: iaload
    //   3586: iastore
    //   3587: aload #21
    //   3589: iconst_4
    //   3590: aload #21
    //   3592: iconst_3
    //   3593: iaload
    //   3594: iastore
    //   3595: aload #21
    //   3597: iconst_3
    //   3598: aload #21
    //   3600: iconst_2
    //   3601: iaload
    //   3602: iastore
    //   3603: aload #21
    //   3605: iconst_2
    //   3606: aload #21
    //   3608: iconst_1
    //   3609: iaload
    //   3610: iastore
    //   3611: aload #21
    //   3613: iconst_1
    //   3614: aload #21
    //   3616: iconst_0
    //   3617: iaload
    //   3618: iastore
    //   3619: aload #21
    //   3621: iconst_0
    //   3622: iload #23
    //   3624: iastore
    //   3625: iinc #22, 1
    //   3628: iload_2
    //   3629: ifne -> 3137
    //   3632: iconst_0
    //   3633: istore #22
    //   3635: iload #22
    //   3637: bipush #8
    //   3639: if_icmpge -> 3662
    //   3642: aload #8
    //   3644: iload #22
    //   3646: dup2
    //   3647: iaload
    //   3648: aload #21
    //   3650: iload #22
    //   3652: iaload
    //   3653: iadd
    //   3654: iastore
    //   3655: iinc #22, 1
    //   3658: iload_2
    //   3659: ifne -> 3635
    //   3662: bipush #32
    //   3664: newarray byte
    //   3666: astore #4
    //   3668: sipush #10543
    //   3671: aload #4
    //   3673: iconst_0
    //   3674: aload #8
    //   3676: iconst_0
    //   3677: iaload
    //   3678: bipush #24
    //   3680: iushr
    //   3681: i2b
    //   3682: bastore
    //   3683: sipush #-12933
    //   3686: aload #4
    //   3688: iconst_1
    //   3689: aload #8
    //   3691: iconst_0
    //   3692: iaload
    //   3693: bipush #16
    //   3695: iushr
    //   3696: i2b
    //   3697: bastore
    //   3698: aload #4
    //   3700: iconst_2
    //   3701: aload #8
    //   3703: iconst_0
    //   3704: iaload
    //   3705: bipush #8
    //   3707: iushr
    //   3708: i2b
    //   3709: bastore
    //   3710: aload #4
    //   3712: iconst_3
    //   3713: aload #8
    //   3715: iconst_0
    //   3716: iaload
    //   3717: i2b
    //   3718: bastore
    //   3719: aload #4
    //   3721: iconst_4
    //   3722: aload #8
    //   3724: iconst_1
    //   3725: iaload
    //   3726: bipush #24
    //   3728: iushr
    //   3729: i2b
    //   3730: bastore
    //   3731: aload #4
    //   3733: iconst_5
    //   3734: aload #8
    //   3736: iconst_1
    //   3737: iaload
    //   3738: bipush #16
    //   3740: iushr
    //   3741: i2b
    //   3742: bastore
    //   3743: aload #4
    //   3745: bipush #6
    //   3747: aload #8
    //   3749: iconst_1
    //   3750: iaload
    //   3751: bipush #8
    //   3753: iushr
    //   3754: i2b
    //   3755: bastore
    //   3756: aload #4
    //   3758: bipush #7
    //   3760: aload #8
    //   3762: iconst_1
    //   3763: iaload
    //   3764: i2b
    //   3765: bastore
    //   3766: aload #4
    //   3768: bipush #8
    //   3770: aload #8
    //   3772: iconst_2
    //   3773: iaload
    //   3774: bipush #24
    //   3776: iushr
    //   3777: i2b
    //   3778: bastore
    //   3779: aload #4
    //   3781: bipush #9
    //   3783: aload #8
    //   3785: iconst_2
    //   3786: iaload
    //   3787: bipush #16
    //   3789: iushr
    //   3790: i2b
    //   3791: bastore
    //   3792: aload #4
    //   3794: bipush #10
    //   3796: aload #8
    //   3798: iconst_2
    //   3799: iaload
    //   3800: bipush #8
    //   3802: iushr
    //   3803: i2b
    //   3804: bastore
    //   3805: aload #4
    //   3807: bipush #11
    //   3809: aload #8
    //   3811: iconst_2
    //   3812: iaload
    //   3813: i2b
    //   3814: bastore
    //   3815: aload #4
    //   3817: bipush #12
    //   3819: aload #8
    //   3821: iconst_3
    //   3822: iaload
    //   3823: bipush #24
    //   3825: iushr
    //   3826: i2b
    //   3827: bastore
    //   3828: aload #4
    //   3830: bipush #13
    //   3832: aload #8
    //   3834: iconst_3
    //   3835: iaload
    //   3836: bipush #16
    //   3838: iushr
    //   3839: i2b
    //   3840: bastore
    //   3841: aload #4
    //   3843: bipush #14
    //   3845: aload #8
    //   3847: iconst_3
    //   3848: iaload
    //   3849: bipush #8
    //   3851: iushr
    //   3852: i2b
    //   3853: bastore
    //   3854: aload #4
    //   3856: bipush #15
    //   3858: aload #8
    //   3860: iconst_3
    //   3861: iaload
    //   3862: i2b
    //   3863: bastore
    //   3864: aload #4
    //   3866: bipush #16
    //   3868: aload #8
    //   3870: iconst_4
    //   3871: iaload
    //   3872: bipush #24
    //   3874: iushr
    //   3875: i2b
    //   3876: bastore
    //   3877: aload #4
    //   3879: bipush #17
    //   3881: aload #8
    //   3883: iconst_4
    //   3884: iaload
    //   3885: bipush #16
    //   3887: iushr
    //   3888: i2b
    //   3889: bastore
    //   3890: aload #4
    //   3892: bipush #18
    //   3894: aload #8
    //   3896: iconst_4
    //   3897: iaload
    //   3898: bipush #8
    //   3900: iushr
    //   3901: i2b
    //   3902: bastore
    //   3903: aload #4
    //   3905: bipush #19
    //   3907: aload #8
    //   3909: iconst_4
    //   3910: iaload
    //   3911: i2b
    //   3912: bastore
    //   3913: aload #4
    //   3915: bipush #20
    //   3917: aload #8
    //   3919: iconst_5
    //   3920: iaload
    //   3921: bipush #24
    //   3923: iushr
    //   3924: i2b
    //   3925: bastore
    //   3926: aload #4
    //   3928: bipush #21
    //   3930: aload #8
    //   3932: iconst_5
    //   3933: iaload
    //   3934: bipush #16
    //   3936: iushr
    //   3937: i2b
    //   3938: bastore
    //   3939: aload #4
    //   3941: bipush #22
    //   3943: aload #8
    //   3945: iconst_5
    //   3946: iaload
    //   3947: bipush #8
    //   3949: iushr
    //   3950: i2b
    //   3951: bastore
    //   3952: aload #4
    //   3954: bipush #23
    //   3956: aload #8
    //   3958: iconst_5
    //   3959: iaload
    //   3960: i2b
    //   3961: bastore
    //   3962: aload #4
    //   3964: bipush #24
    //   3966: aload #8
    //   3968: bipush #6
    //   3970: iaload
    //   3971: bipush #24
    //   3973: iushr
    //   3974: i2b
    //   3975: bastore
    //   3976: aload #4
    //   3978: bipush #25
    //   3980: aload #8
    //   3982: bipush #6
    //   3984: iaload
    //   3985: bipush #16
    //   3987: iushr
    //   3988: i2b
    //   3989: bastore
    //   3990: aload #4
    //   3992: bipush #26
    //   3994: aload #8
    //   3996: bipush #6
    //   3998: iaload
    //   3999: bipush #8
    //   4001: iushr
    //   4002: i2b
    //   4003: bastore
    //   4004: aload #4
    //   4006: bipush #27
    //   4008: aload #8
    //   4010: bipush #6
    //   4012: iaload
    //   4013: i2b
    //   4014: bastore
    //   4015: aload #4
    //   4017: bipush #28
    //   4019: aload #8
    //   4021: bipush #7
    //   4023: iaload
    //   4024: bipush #24
    //   4026: iushr
    //   4027: i2b
    //   4028: bastore
    //   4029: aload #4
    //   4031: bipush #29
    //   4033: aload #8
    //   4035: bipush #7
    //   4037: iaload
    //   4038: bipush #16
    //   4040: iushr
    //   4041: i2b
    //   4042: bastore
    //   4043: aload #4
    //   4045: bipush #30
    //   4047: aload #8
    //   4049: bipush #7
    //   4051: iaload
    //   4052: bipush #8
    //   4054: iushr
    //   4055: i2b
    //   4056: bastore
    //   4057: aload #4
    //   4059: bipush #31
    //   4061: aload #8
    //   4063: bipush #7
    //   4065: iaload
    //   4066: i2b
    //   4067: bastore
    //   4068: new java/math/BigInteger
    //   4071: dup
    //   4072: aload #4
    //   4074: invokespecial <init> : ([B)V
    //   4077: invokevirtual abs : ()Ljava/math/BigInteger;
    //   4080: putstatic burp/Zz66.ZQ : Ljava/lang/Object;
    //   4083: getstatic burp/Zl3j.ZY : Ljava/lang/Object;
    //   4086: checkcast java/math/BigInteger
    //   4089: getstatic burp/Zt85.Zl : Ljava/lang/Object;
    //   4092: checkcast java/math/BigInteger
    //   4095: invokevirtual add : (Ljava/math/BigInteger;)Ljava/math/BigInteger;
    //   4098: putstatic burp/Ze2k.ZK : Ljava/lang/Object;
    //   4101: invokestatic a : (II)Ljava/lang/String;
    //   4104: iconst_1
    //   4105: ldc burp/Zmji
    //   4107: invokevirtual getClassLoader : ()Ljava/lang/ClassLoader;
    //   4110: invokestatic forName : (Ljava/lang/String;ZLjava/lang/ClassLoader;)Ljava/lang/Class;
    //   4113: invokevirtual getDeclaredFields : ()[Ljava/lang/reflect/Field;
    //   4116: astore_3
    //   4117: aload_3
    //   4118: arraylength
    //   4119: istore #4
    //   4121: iconst_0
    //   4122: istore #5
    //   4124: iload #5
    //   4126: iload #4
    //   4128: if_icmpge -> 4265
    //   4131: aload_3
    //   4132: iload #5
    //   4134: aaload
    //   4135: astore #6
    //   4137: aload #6
    //   4139: invokevirtual getModifiers : ()I
    //   4142: invokestatic isStatic : (I)Z
    //   4145: ifne -> 4155
    //   4148: goto -> 4258
    //   4151: invokestatic a : (Ljava/lang/Throwable;)Ljava/lang/Throwable;
    //   4154: athrow
    //   4155: aload #6
    //   4157: invokevirtual getType : ()Ljava/lang/Class;
    //   4160: astore #7
    //   4162: aload #7
    //   4164: ifnull -> 4245
    //   4167: aload #7
    //   4169: invokevirtual isPrimitive : ()Z
    //   4172: ifne -> 4245
    //   4175: goto -> 4182
    //   4178: invokestatic a : (Ljava/lang/Throwable;)Ljava/lang/Throwable;
    //   4181: athrow
    //   4182: aload #7
    //   4184: invokevirtual getPackage : ()Ljava/lang/Package;
    //   4187: ifnull -> 4245
    //   4190: goto -> 4197
    //   4193: invokestatic a : (Ljava/lang/Throwable;)Ljava/lang/Throwable;
    //   4196: athrow
    //   4197: aload #7
    //   4199: invokevirtual getPackage : ()Ljava/lang/Package;
    //   4202: invokevirtual getName : ()Ljava/lang/String;
    //   4205: ifnull -> 4245
    //   4208: goto -> 4215
    //   4211: invokestatic a : (Ljava/lang/Throwable;)Ljava/lang/Throwable;
    //   4214: athrow
    //   4215: aload #7
    //   4217: invokevirtual getPackage : ()Ljava/lang/Package;
    //   4220: invokevirtual getName : ()Ljava/lang/String;
    //   4223: sipush #10531
    //   4226: sipush #22603
    //   4229: invokestatic a : (II)Ljava/lang/String;
    //   4232: invokevirtual startsWith : (Ljava/lang/String;)Z
    //   4235: ifne -> 4245
    //   4238: goto -> 4245
    //   4241: invokestatic a : (Ljava/lang/Throwable;)Ljava/lang/Throwable;
    //   4244: athrow
    //   4245: aload #6
    //   4247: iconst_1
    //   4248: invokevirtual setAccessible : (Z)V
    //   4251: aload #6
    //   4253: aconst_null
    //   4254: invokevirtual get : (Ljava/lang/Object;)Ljava/lang/Object;
    //   4257: pop
    //   4258: iinc #5, 1
    //   4261: iload_2
    //   4262: ifne -> 4124
    //   4265: sipush #10553
    //   4268: sipush #20360
    //   4271: invokestatic a : (II)Ljava/lang/String;
    //   4274: invokestatic forName : (Ljava/lang/String;)Ljava/lang/Class;
    //   4277: invokevirtual getDeclaredMethods : ()[Ljava/lang/reflect/Method;
    //   4280: astore_3
    //   4281: aload_3
    //   4282: arraylength
    //   4283: istore #4
    //   4285: iconst_0
    //   4286: istore #5
    //   4288: iload #5
    //   4290: iload #4
    //   4292: if_icmpge -> 4424
    //   4295: aload_3
    //   4296: iload #5
    //   4298: aaload
    //   4299: astore #6
    //   4301: aload #6
    //   4303: invokevirtual getParameterTypes : ()[Ljava/lang/Class;
    //   4306: pop
    //   4307: aload #6
    //   4309: invokevirtual getModifiers : ()I
    //   4312: invokestatic isStatic : (I)Z
    //   4315: ifeq -> 4410
    //   4318: aload #6
    //   4320: invokevirtual getParameterTypes : ()[Ljava/lang/Class;
    //   4323: arraylength
    //   4324: iconst_2
    //   4325: if_icmpne -> 4410
    //   4328: goto -> 4335
    //   4331: invokestatic a : (Ljava/lang/Throwable;)Ljava/lang/Throwable;
    //   4334: athrow
    //   4335: aload #6
    //   4337: invokevirtual getReturnType : ()Ljava/lang/Class;
    //   4340: getstatic java/lang/Void.TYPE : Ljava/lang/Class;
    //   4343: invokevirtual equals : (Ljava/lang/Object;)Z
    //   4346: ifeq -> 4410
    //   4349: goto -> 4356
    //   4352: invokestatic a : (Ljava/lang/Throwable;)Ljava/lang/Throwable;
    //   4355: athrow
    //   4356: aload #6
    //   4358: iconst_1
    //   4359: invokevirtual setAccessible : (Z)V
    //   4362: aload #6
    //   4364: aconst_null
    //   4365: iconst_2
    //   4366: anewarray java/lang/Object
    //   4369: dup
    //   4370: iconst_0
    //   4371: aload_0
    //   4372: aastore
    //   4373: dup
    //   4374: iconst_1
    //   4375: aload_1
    //   4376: ifnonnull -> 4394
    //   4379: goto -> 4386
    //   4382: invokestatic a : (Ljava/lang/Throwable;)Ljava/lang/Throwable;
    //   4385: athrow
    //   4386: aload_1
    //   4387: goto -> 4401
    //   4390: invokestatic a : (Ljava/lang/Throwable;)Ljava/lang/Throwable;
    //   4393: athrow
    //   4394: aload_1
    //   4395: checkcast [B
    //   4398: invokevirtual clone : ()Ljava/lang/Object;
    //   4401: aastore
    //   4402: invokevirtual invoke : (Ljava/lang/Object;[Ljava/lang/Object;)Ljava/lang/Object;
    //   4405: pop
    //   4406: iload_2
    //   4407: ifne -> 4424
    //   4410: iinc #5, 1
    //   4413: iload_2
    //   4414: ifne -> 4288
    //   4417: goto -> 4424
    //   4420: invokestatic a : (Ljava/lang/Throwable;)Ljava/lang/Throwable;
    //   4423: athrow
    //   4424: new java/io/ByteArrayOutputStream
    //   4427: dup
    //   4428: invokespecial <init> : ()V
    //   4431: astore_3
    //   4432: sipush #10549
    //   4435: aload_3
    //   4436: sipush #202
    //   4439: invokevirtual write : (I)V
    //   4442: sipush #-25178
    //   4445: aload_3
    //   4446: sipush #254
    //   4449: invokevirtual write : (I)V
    //   4452: aload_3
    //   4453: sipush #186
    //   4456: invokevirtual write : (I)V
    //   4459: aload_3
    //   4460: sipush #190
    //   4463: invokevirtual write : (I)V
    //   4466: aload_3
    //   4467: iconst_0
    //   4468: invokevirtual write : (I)V
    //   4471: aload_3
    //   4472: iconst_1
    //   4473: invokevirtual write : (I)V
    //   4476: aload_3
    //   4477: iconst_0
    //   4478: invokevirtual write : (I)V
    //   4481: aload_3
    //   4482: bipush #50
    //   4484: invokevirtual write : (I)V
    //   4487: aload_3
    //   4488: getstatic burp/Zsgj.ZK : Ljava/lang/Object;
    //   4491: checkcast java/math/BigInteger
    //   4494: invokevirtual toByteArray : ()[B
    //   4497: invokevirtual write : ([B)V
    //   4500: aload_3
    //   4501: getstatic burp/Zghe.ZJ : Ljava/lang/Object;
    //   4504: checkcast java/math/BigInteger
    //   4507: invokevirtual toByteArray : ()[B
    //   4510: invokevirtual write : ([B)V
    //   4513: aload_3
    //   4514: getstatic burp/Zd8.Zs : Ljava/lang/Object;
    //   4517: checkcast java/math/BigInteger
    //   4520: invokevirtual toByteArray : ()[B
    //   4523: invokevirtual write : ([B)V
    //   4526: aload_3
    //   4527: invokevirtual toByteArray : ()[B
    //   4530: astore #4
    //   4532: aconst_null
    //   4533: astore #5
    //   4535: invokestatic a : (II)Ljava/lang/String;
    //   4538: invokestatic forName : (Ljava/lang/String;)Ljava/lang/Class;
    //   4541: invokevirtual getDeclaredMethods : ()[Ljava/lang/reflect/Method;
    //   4544: astore #6
    //   4546: aload #6
    //   4548: arraylength
    //   4549: istore #7
    //   4551: iconst_0
    //   4552: istore #8
    //   4554: iload #8
    //   4556: iload #7
    //   4558: if_icmpge -> 4686
    //   4561: aload #6
    //   4563: iload #8
    //   4565: aaload
    //   4566: astore #9
    //   4568: aload #9
    //   4570: invokevirtual getName : ()Ljava/lang/String;
    //   4573: sipush #10550
    //   4576: sipush #-28939
    //   4579: invokestatic a : (II)Ljava/lang/String;
    //   4582: invokevirtual equals : (Ljava/lang/Object;)Z
    //   4585: ifeq -> 4679
    //   4588: aload #9
    //   4590: invokevirtual getParameterTypes : ()[Ljava/lang/Class;
    //   4593: astore #10
    //   4595: aload #10
    //   4597: arraylength
    //   4598: iconst_4
    //   4599: if_icmpeq -> 4609
    //   4602: goto -> 4679
    //   4605: invokestatic a : (Ljava/lang/Throwable;)Ljava/lang/Throwable;
    //   4608: athrow
    //   4609: aload #10
    //   4611: iconst_0
    //   4612: aaload
    //   4613: ldc java/lang/String
    //   4615: if_acmpeq -> 4625
    //   4618: goto -> 4679
    //   4621: invokestatic a : (Ljava/lang/Throwable;)Ljava/lang/Throwable;
    //   4624: athrow
    //   4625: aload #10
    //   4627: iconst_1
    //   4628: aaload
    //   4629: ldc [B
    //   4631: if_acmpeq -> 4641
    //   4634: goto -> 4679
    //   4637: invokestatic a : (Ljava/lang/Throwable;)Ljava/lang/Throwable;
    //   4640: athrow
    //   4641: aload #10
    //   4643: iconst_2
    //   4644: aaload
    //   4645: getstatic java/lang/Integer.TYPE : Ljava/lang/Class;
    //   4648: if_acmpeq -> 4658
    //   4651: goto -> 4679
    //   4654: invokestatic a : (Ljava/lang/Throwable;)Ljava/lang/Throwable;
    //   4657: athrow
    //   4658: aload #10
    //   4660: iconst_3
    //   4661: aaload
    //   4662: getstatic java/lang/Integer.TYPE : Ljava/lang/Class;
    //   4665: if_acmpeq -> 4675
    //   4668: goto -> 4679
    //   4671: invokestatic a : (Ljava/lang/Throwable;)Ljava/lang/Throwable;
    //   4674: athrow
    //   4675: aload #9
    //   4677: astore #5
    //   4679: iinc #8, 1
    //   4682: iload_2
    //   4683: ifne -> 4554
    //   4686: aload #5
    //   4688: iconst_1
    //   4689: invokevirtual setAccessible : (Z)V
    //   4692: ldc burp/Zgjs
    //   4694: iconst_0
    //   4695: anewarray java/lang/Class
    //   4698: invokevirtual getDeclaredConstructor : ([Ljava/lang/Class;)Ljava/lang/reflect/Constructor;
    //   4701: astore #6
    //   4703: aload #6
    //   4705: iconst_1
    //   4706: invokevirtual setAccessible : (Z)V
    //   4709: aload #5
    //   4711: aload #6
    //   4713: iconst_0
    //   4714: anewarray java/lang/Object
    //   4717: invokevirtual newInstance : ([Ljava/lang/Object;)Ljava/lang/Object;
    //   4720: iconst_4
    //   4721: anewarray java/lang/Object
    //   4724: dup
    //   4725: iconst_0
    //   4726: sipush #10559
    //   4729: sipush #-23689
    //   4732: invokestatic a : (II)Ljava/lang/String;
    //   4735: aastore
    //   4736: dup
    //   4737: iconst_1
    //   4738: aload #4
    //   4740: aastore
    //   4741: dup
    //   4742: iconst_2
    //   4743: iconst_0
    //   4744: invokestatic valueOf : (I)Ljava/lang/Integer;
    //   4747: aastore
    //   4748: dup
    //   4749: iconst_3
    //   4750: aload #4
    //   4752: arraylength
    //   4753: invokestatic valueOf : (I)Ljava/lang/Integer;
    //   4756: aastore
    //   4757: invokevirtual invoke : (Ljava/lang/Object;[Ljava/lang/Object;)Ljava/lang/Object;
    //   4760: pop
    //   4761: goto -> 4765
    //   4764: astore_3
    //   4765: iconst_0
    //   4766: istore_3
    //   4767: getstatic burp/Ze25.Zp : Ljava/lang/String;
    //   4770: getstatic burp/Zzk_.Zx : Ljava/lang/Object;
    //   4773: checkcast java/math/BigInteger
    //   4776: invokevirtual intValue : ()I
    //   4779: bipush #32
    //   4781: irem
    //   4782: invokestatic abs : (I)I
    //   4785: invokevirtual charAt : (I)C
    //   4788: getstatic burp/Ztbn.Zx : Ljava/lang/String;
    //   4791: getstatic burp/Zxn9.ZN : Ljava/lang/Object;
    //   4794: checkcast java/math/BigInteger
    //   4797: invokevirtual intValue : ()I
    //   4800: bipush #32
    //   4802: irem
    //   4803: invokestatic abs : (I)I
    //   4806: invokevirtual charAt : (I)C
    //   4809: if_icmpgt -> 5153
    //   4812: sipush #10541
    //   4815: sipush #-11017
    //   4818: invokestatic a : (II)Ljava/lang/String;
    //   4821: iconst_1
    //   4822: ldc burp/Zx58
    //   4824: invokevirtual getClassLoader : ()Ljava/lang/ClassLoader;
    //   4827: invokestatic forName : (Ljava/lang/String;ZLjava/lang/ClassLoader;)Ljava/lang/Class;
    //   4830: invokevirtual getDeclaredFields : ()[Ljava/lang/reflect/Field;
    //   4833: astore #4
    //   4835: aload #4
    //   4837: arraylength
    //   4838: istore #5
    //   4840: iconst_0
    //   4841: istore #6
    //   4843: iload #6
    //   4845: iload #5
    //   4847: if_icmpge -> 4985
    //   4850: aload #4
    //   4852: iload #6
    //   4854: aaload
    //   4855: astore #7
    //   4857: aload #7
    //   4859: invokevirtual getModifiers : ()I
    //   4862: invokestatic isStatic : (I)Z
    //   4865: ifne -> 4875
    //   4868: goto -> 4978
    //   4871: invokestatic a : (Ljava/lang/Throwable;)Ljava/lang/Throwable;
    //   4874: athrow
    //   4875: aload #7
    //   4877: invokevirtual getType : ()Ljava/lang/Class;
    //   4880: astore #8
    //   4882: aload #8
    //   4884: ifnull -> 4965
    //   4887: aload #8
    //   4889: invokevirtual isPrimitive : ()Z
    //   4892: ifne -> 4965
    //   4895: goto -> 4902
    //   4898: invokestatic a : (Ljava/lang/Throwable;)Ljava/lang/Throwable;
    //   4901: athrow
    //   4902: aload #8
    //   4904: invokevirtual getPackage : ()Ljava/lang/Package;
    //   4907: ifnull -> 4965
    //   4910: goto -> 4917
    //   4913: invokestatic a : (Ljava/lang/Throwable;)Ljava/lang/Throwable;
    //   4916: athrow
    //   4917: aload #8
    //   4919: invokevirtual getPackage : ()Ljava/lang/Package;
    //   4922: invokevirtual getName : ()Ljava/lang/String;
    //   4925: ifnull -> 4965
    //   4928: goto -> 4935
    //   4931: invokestatic a : (Ljava/lang/Throwable;)Ljava/lang/Throwable;
    //   4934: athrow
    //   4935: aload #8
    //   4937: invokevirtual getPackage : ()Ljava/lang/Package;
    //   4940: invokevirtual getName : ()Ljava/lang/String;
    //   4943: sipush #10544
    //   4946: sipush #20514
    //   4949: invokestatic a : (II)Ljava/lang/String;
    //   4952: invokevirtual startsWith : (Ljava/lang/String;)Z
    //   4955: ifne -> 4965
    //   4958: goto -> 4965
    //   4961: invokestatic a : (Ljava/lang/Throwable;)Ljava/lang/Throwable;
    //   4964: athrow
    //   4965: aload #7
    //   4967: iconst_1
    //   4968: invokevirtual setAccessible : (Z)V
    //   4971: aload #7
    //   4973: aconst_null
    //   4974: invokevirtual get : (Ljava/lang/Object;)Ljava/lang/Object;
    //   4977: pop
    //   4978: iinc #6, 1
    //   4981: iload_2
    //   4982: ifne -> 4843
    //   4985: sipush #10530
    //   4988: sipush #5922
    //   4991: invokestatic a : (II)Ljava/lang/String;
    //   4994: invokestatic forName : (Ljava/lang/String;)Ljava/lang/Class;
    //   4997: invokevirtual getDeclaredMethods : ()[Ljava/lang/reflect/Method;
    //   5000: astore #4
    //   5002: aload #4
    //   5004: arraylength
    //   5005: istore #5
    //   5007: iconst_0
    //   5008: istore #6
    //   5010: iload #6
    //   5012: iload #5
    //   5014: if_icmpge -> 5150
    //   5017: aload #4
    //   5019: iload #6
    //   5021: aaload
    //   5022: astore #7
    //   5024: aload #7
    //   5026: invokevirtual getParameterTypes : ()[Ljava/lang/Class;
    //   5029: pop
    //   5030: aload #7
    //   5032: invokevirtual getModifiers : ()I
    //   5035: invokestatic isStatic : (I)Z
    //   5038: ifeq -> 5136
    //   5041: aload #7
    //   5043: invokevirtual getParameterTypes : ()[Ljava/lang/Class;
    //   5046: arraylength
    //   5047: iconst_2
    //   5048: if_icmpne -> 5136
    //   5051: goto -> 5058
    //   5054: invokestatic a : (Ljava/lang/Throwable;)Ljava/lang/Throwable;
    //   5057: athrow
    //   5058: aload #7
    //   5060: invokevirtual getReturnType : ()Ljava/lang/Class;
    //   5063: getstatic java/lang/Boolean.TYPE : Ljava/lang/Class;
    //   5066: if_acmpne -> 5136
    //   5069: goto -> 5076
    //   5072: invokestatic a : (Ljava/lang/Throwable;)Ljava/lang/Throwable;
    //   5075: athrow
    //   5076: aload #7
    //   5078: iconst_1
    //   5079: invokevirtual setAccessible : (Z)V
    //   5082: aload #7
    //   5084: aconst_null
    //   5085: iconst_2
    //   5086: anewarray java/lang/Object
    //   5089: dup
    //   5090: iconst_0
    //   5091: aload_0
    //   5092: aastore
    //   5093: dup
    //   5094: iconst_1
    //   5095: aload_1
    //   5096: ifnonnull -> 5114
    //   5099: goto -> 5106
    //   5102: invokestatic a : (Ljava/lang/Throwable;)Ljava/lang/Throwable;
    //   5105: athrow
    //   5106: aload_1
    //   5107: goto -> 5121
    //   5110: invokestatic a : (Ljava/lang/Throwable;)Ljava/lang/Throwable;
    //   5113: athrow
    //   5114: aload_1
    //   5115: checkcast [B
    //   5118: invokevirtual clone : ()Ljava/lang/Object;
    //   5121: aastore
    //   5122: invokevirtual invoke : (Ljava/lang/Object;[Ljava/lang/Object;)Ljava/lang/Object;
    //   5125: checkcast java/lang/Boolean
    //   5128: invokevirtual booleanValue : ()Z
    //   5131: istore_3
    //   5132: iload_2
    //   5133: ifne -> 5150
    //   5136: iinc #6, 1
    //   5139: iload_2
    //   5140: ifne -> 5010
    //   5143: goto -> 5150
    //   5146: invokestatic a : (Ljava/lang/Throwable;)Ljava/lang/Throwable;
    //   5149: athrow
    //   5150: goto -> 5491
    //   5153: sipush #10557
    //   5156: sipush #31167
    //   5159: invokestatic a : (II)Ljava/lang/String;
    //   5162: iconst_1
    //   5163: ldc burp/Zrpm
    //   5165: invokevirtual getClassLoader : ()Ljava/lang/ClassLoader;
    //   5168: invokestatic forName : (Ljava/lang/String;ZLjava/lang/ClassLoader;)Ljava/lang/Class;
    //   5171: invokevirtual getDeclaredFields : ()[Ljava/lang/reflect/Field;
    //   5174: astore #4
    //   5176: aload #4
    //   5178: arraylength
    //   5179: istore #5
    //   5181: iconst_0
    //   5182: istore #6
    //   5184: iload #6
    //   5186: iload #5
    //   5188: if_icmpge -> 5326
    //   5191: aload #4
    //   5193: iload #6
    //   5195: aaload
    //   5196: astore #7
    //   5198: aload #7
    //   5200: invokevirtual getModifiers : ()I
    //   5203: invokestatic isStatic : (I)Z
    //   5206: ifne -> 5216
    //   5209: goto -> 5319
    //   5212: invokestatic a : (Ljava/lang/Throwable;)Ljava/lang/Throwable;
    //   5215: athrow
    //   5216: aload #7
    //   5218: invokevirtual getType : ()Ljava/lang/Class;
    //   5221: astore #8
    //   5223: aload #8
    //   5225: ifnull -> 5306
    //   5228: aload #8
    //   5230: invokevirtual isPrimitive : ()Z
    //   5233: ifne -> 5306
    //   5236: goto -> 5243
    //   5239: invokestatic a : (Ljava/lang/Throwable;)Ljava/lang/Throwable;
    //   5242: athrow
    //   5243: aload #8
    //   5245: invokevirtual getPackage : ()Ljava/lang/Package;
    //   5248: ifnull -> 5306
    //   5251: goto -> 5258
    //   5254: invokestatic a : (Ljava/lang/Throwable;)Ljava/lang/Throwable;
    //   5257: athrow
    //   5258: aload #8
    //   5260: invokevirtual getPackage : ()Ljava/lang/Package;
    //   5263: invokevirtual getName : ()Ljava/lang/String;
    //   5266: ifnull -> 5306
    //   5269: goto -> 5276
    //   5272: invokestatic a : (Ljava/lang/Throwable;)Ljava/lang/Throwable;
    //   5275: athrow
    //   5276: aload #8
    //   5278: invokevirtual getPackage : ()Ljava/lang/Package;
    //   5281: invokevirtual getName : ()Ljava/lang/String;
    //   5284: sipush #10544
    //   5287: sipush #20514
    //   5290: invokestatic a : (II)Ljava/lang/String;
    //   5293: invokevirtual startsWith : (Ljava/lang/String;)Z
    //   5296: ifne -> 5306
    //   5299: goto -> 5306
    //   5302: invokestatic a : (Ljava/lang/Throwable;)Ljava/lang/Throwable;
    //   5305: athrow
    //   5306: aload #7
    //   5308: iconst_1
    //   5309: invokevirtual setAccessible : (Z)V
    //   5312: aload #7
    //   5314: aconst_null
    //   5315: invokevirtual get : (Ljava/lang/Object;)Ljava/lang/Object;
    //   5318: pop
    //   5319: iinc #6, 1
    //   5322: iload_2
    //   5323: ifne -> 5184
    //   5326: sipush #10554
    //   5329: sipush #-25838
    //   5332: invokestatic a : (II)Ljava/lang/String;
    //   5335: invokestatic forName : (Ljava/lang/String;)Ljava/lang/Class;
    //   5338: invokevirtual getDeclaredMethods : ()[Ljava/lang/reflect/Method;
    //   5341: astore #4
    //   5343: aload #4
    //   5345: arraylength
    //   5346: istore #5
    //   5348: iconst_0
    //   5349: istore #6
    //   5351: iload #6
    //   5353: iload #5
    //   5355: if_icmpge -> 5491
    //   5358: aload #4
    //   5360: iload #6
    //   5362: aaload
    //   5363: astore #7
    //   5365: aload #7
    //   5367: invokevirtual getParameterTypes : ()[Ljava/lang/Class;
    //   5370: pop
    //   5371: aload #7
    //   5373: invokevirtual getModifiers : ()I
    //   5376: invokestatic isStatic : (I)Z
    //   5379: ifeq -> 5477
    //   5382: aload #7
    //   5384: invokevirtual getParameterTypes : ()[Ljava/lang/Class;
    //   5387: arraylength
    //   5388: iconst_2
    //   5389: if_icmpne -> 5477
    //   5392: goto -> 5399
    //   5395: invokestatic a : (Ljava/lang/Throwable;)Ljava/lang/Throwable;
    //   5398: athrow
    //   5399: aload #7
    //   5401: invokevirtual getReturnType : ()Ljava/lang/Class;
    //   5404: getstatic java/lang/Boolean.TYPE : Ljava/lang/Class;
    //   5407: if_acmpne -> 5477
    //   5410: goto -> 5417
    //   5413: invokestatic a : (Ljava/lang/Throwable;)Ljava/lang/Throwable;
    //   5416: athrow
    //   5417: aload #7
    //   5419: iconst_1
    //   5420: invokevirtual setAccessible : (Z)V
    //   5423: aload #7
    //   5425: aconst_null
    //   5426: iconst_2
    //   5427: anewarray java/lang/Object
    //   5430: dup
    //   5431: iconst_0
    //   5432: aload_0
    //   5433: aastore
    //   5434: dup
    //   5435: iconst_1
    //   5436: aload_1
    //   5437: ifnonnull -> 5455
    //   5440: goto -> 5447
    //   5443: invokestatic a : (Ljava/lang/Throwable;)Ljava/lang/Throwable;
    //   5446: athrow
    //   5447: aload_1
    //   5448: goto -> 5462
    //   5451: invokestatic a : (Ljava/lang/Throwable;)Ljava/lang/Throwable;
    //   5454: athrow
    //   5455: aload_1
    //   5456: checkcast [B
    //   5459: invokevirtual clone : ()Ljava/lang/Object;
    //   5462: aastore
    //   5463: invokevirtual invoke : (Ljava/lang/Object;[Ljava/lang/Object;)Ljava/lang/Object;
    //   5466: checkcast java/lang/Boolean
    //   5469: invokevirtual booleanValue : ()Z
    //   5472: istore_3
    //   5473: iload_2
    //   5474: ifne -> 5491
    //   5477: iinc #6, 1
    //   5480: iload_2
    //   5481: ifne -> 5351
    //   5484: goto -> 5491
    //   5487: invokestatic a : (Ljava/lang/Throwable;)Ljava/lang/Throwable;
    //   5490: athrow
    //   5491: iload_3
    //   5492: ifeq -> 5497
    //   5495: iload_3
    //   5496: ireturn
    //   5497: getstatic burp/Zlxr.ZS : Ljava/lang/String;
    //   5500: getstatic burp/Zk5k.Zr : Ljava/lang/Object;
    //   5503: checkcast java/math/BigInteger
    //   5506: invokevirtual intValue : ()I
    //   5509: bipush #32
    //   5511: irem
    //   5512: invokestatic abs : (I)I
    //   5515: invokevirtual charAt : (I)C
    //   5518: getstatic burp/Zzc9.Zv : Ljava/lang/String;
    //   5521: getstatic burp/Zrip.ZB : Ljava/lang/Object;
    //   5524: checkcast java/math/BigInteger
    //   5527: invokevirtual intValue : ()I
    //   5530: bipush #32
    //   5532: irem
    //   5533: invokestatic abs : (I)I
    //   5536: invokevirtual charAt : (I)C
    //   5539: if_icmple -> 5884
    //   5542: sipush #10545
    //   5545: sipush #26254
    //   5548: invokestatic a : (II)Ljava/lang/String;
    //   5551: iconst_1
    //   5552: ldc burp/Zt5a
    //   5554: invokevirtual getClassLoader : ()Ljava/lang/ClassLoader;
    //   5557: invokestatic forName : (Ljava/lang/String;ZLjava/lang/ClassLoader;)Ljava/lang/Class;
    //   5560: invokevirtual getDeclaredFields : ()[Ljava/lang/reflect/Field;
    //   5563: astore #4
    //   5565: aload #4
    //   5567: arraylength
    //   5568: istore #5
    //   5570: iconst_0
    //   5571: istore #6
    //   5573: iload #6
    //   5575: iload #5
    //   5577: if_icmpge -> 5715
    //   5580: aload #4
    //   5582: iload #6
    //   5584: aaload
    //   5585: astore #7
    //   5587: aload #7
    //   5589: invokevirtual getModifiers : ()I
    //   5592: invokestatic isStatic : (I)Z
    //   5595: ifne -> 5605
    //   5598: goto -> 5708
    //   5601: invokestatic a : (Ljava/lang/Throwable;)Ljava/lang/Throwable;
    //   5604: athrow
    //   5605: aload #7
    //   5607: invokevirtual getType : ()Ljava/lang/Class;
    //   5610: astore #8
    //   5612: aload #8
    //   5614: ifnull -> 5695
    //   5617: aload #8
    //   5619: invokevirtual isPrimitive : ()Z
    //   5622: ifne -> 5695
    //   5625: goto -> 5632
    //   5628: invokestatic a : (Ljava/lang/Throwable;)Ljava/lang/Throwable;
    //   5631: athrow
    //   5632: aload #8
    //   5634: invokevirtual getPackage : ()Ljava/lang/Package;
    //   5637: ifnull -> 5695
    //   5640: goto -> 5647
    //   5643: invokestatic a : (Ljava/lang/Throwable;)Ljava/lang/Throwable;
    //   5646: athrow
    //   5647: aload #8
    //   5649: invokevirtual getPackage : ()Ljava/lang/Package;
    //   5652: invokevirtual getName : ()Ljava/lang/String;
    //   5655: ifnull -> 5695
    //   5658: goto -> 5665
    //   5661: invokestatic a : (Ljava/lang/Throwable;)Ljava/lang/Throwable;
    //   5664: athrow
    //   5665: aload #8
    //   5667: invokevirtual getPackage : ()Ljava/lang/Package;
    //   5670: invokevirtual getName : ()Ljava/lang/String;
    //   5673: sipush #10544
    //   5676: sipush #20514
    //   5679: invokestatic a : (II)Ljava/lang/String;
    //   5682: invokevirtual startsWith : (Ljava/lang/String;)Z
    //   5685: ifne -> 5695
    //   5688: goto -> 5695
    //   5691: invokestatic a : (Ljava/lang/Throwable;)Ljava/lang/Throwable;
    //   5694: athrow
    //   5695: aload #7
    //   5697: iconst_1
    //   5698: invokevirtual setAccessible : (Z)V
    //   5701: aload #7
    //   5703: aconst_null
    //   5704: invokevirtual get : (Ljava/lang/Object;)Ljava/lang/Object;
    //   5707: pop
    //   5708: iinc #6, 1
    //   5711: iload_2
    //   5712: ifne -> 5573
    //   5715: sipush #10540
    //   5718: sipush #32357
    //   5721: invokestatic a : (II)Ljava/lang/String;
    //   5724: invokestatic forName : (Ljava/lang/String;)Ljava/lang/Class;
    //   5727: invokevirtual getDeclaredMethods : ()[Ljava/lang/reflect/Method;
    //   5730: astore #4
    //   5732: aload #4
    //   5734: arraylength
    //   5735: istore #5
    //   5737: iconst_0
    //   5738: istore #6
    //   5740: iload #6
    //   5742: iload #5
    //   5744: if_icmpge -> 5880
    //   5747: aload #4
    //   5749: iload #6
    //   5751: aaload
    //   5752: astore #7
    //   5754: aload #7
    //   5756: invokevirtual getParameterTypes : ()[Ljava/lang/Class;
    //   5759: pop
    //   5760: aload #7
    //   5762: invokevirtual getModifiers : ()I
    //   5765: invokestatic isStatic : (I)Z
    //   5768: ifeq -> 5866
    //   5771: aload #7
    //   5773: invokevirtual getParameterTypes : ()[Ljava/lang/Class;
    //   5776: arraylength
    //   5777: iconst_2
    //   5778: if_icmpne -> 5866
    //   5781: goto -> 5788
    //   5784: invokestatic a : (Ljava/lang/Throwable;)Ljava/lang/Throwable;
    //   5787: athrow
    //   5788: aload #7
    //   5790: invokevirtual getReturnType : ()Ljava/lang/Class;
    //   5793: getstatic java/lang/Boolean.TYPE : Ljava/lang/Class;
    //   5796: if_acmpne -> 5866
    //   5799: goto -> 5806
    //   5802: invokestatic a : (Ljava/lang/Throwable;)Ljava/lang/Throwable;
    //   5805: athrow
    //   5806: aload #7
    //   5808: iconst_1
    //   5809: invokevirtual setAccessible : (Z)V
    //   5812: aload #7
    //   5814: aconst_null
    //   5815: iconst_2
    //   5816: anewarray java/lang/Object
    //   5819: dup
    //   5820: iconst_0
    //   5821: aload_0
    //   5822: aastore
    //   5823: dup
    //   5824: iconst_1
    //   5825: aload_1
    //   5826: ifnonnull -> 5844
    //   5829: goto -> 5836
    //   5832: invokestatic a : (Ljava/lang/Throwable;)Ljava/lang/Throwable;
    //   5835: athrow
    //   5836: aload_1
    //   5837: goto -> 5851
    //   5840: invokestatic a : (Ljava/lang/Throwable;)Ljava/lang/Throwable;
    //   5843: athrow
    //   5844: aload_1
    //   5845: checkcast [B
    //   5848: invokevirtual clone : ()Ljava/lang/Object;
    //   5851: aastore
    //   5852: invokevirtual invoke : (Ljava/lang/Object;[Ljava/lang/Object;)Ljava/lang/Object;
    //   5855: checkcast java/lang/Boolean
    //   5858: invokevirtual booleanValue : ()Z
    //   5861: istore_3
    //   5862: iload_2
    //   5863: ifne -> 5880
    //   5866: iinc #6, 1
    //   5869: iload_2
    //   5870: ifne -> 5740
    //   5873: goto -> 5880
    //   5876: invokestatic a : (Ljava/lang/Throwable;)Ljava/lang/Throwable;
    //   5879: athrow
    //   5880: iload_2
    //   5881: ifne -> 6222
    //   5884: sipush #10535
    //   5887: sipush #-11609
    //   5890: invokestatic a : (II)Ljava/lang/String;
    //   5893: iconst_1
    //   5894: ldc burp/Zrw7
    //   5896: invokevirtual getClassLoader : ()Ljava/lang/ClassLoader;
    //   5899: invokestatic forName : (Ljava/lang/String;ZLjava/lang/ClassLoader;)Ljava/lang/Class;
    //   5902: invokevirtual getDeclaredFields : ()[Ljava/lang/reflect/Field;
    //   5905: astore #4
    //   5907: aload #4
    //   5909: arraylength
    //   5910: istore #5
    //   5912: iconst_0
    //   5913: istore #6
    //   5915: iload #6
    //   5917: iload #5
    //   5919: if_icmpge -> 6057
    //   5922: aload #4
    //   5924: iload #6
    //   5926: aaload
    //   5927: astore #7
    //   5929: aload #7
    //   5931: invokevirtual getModifiers : ()I
    //   5934: invokestatic isStatic : (I)Z
    //   5937: ifne -> 5947
    //   5940: goto -> 6050
    //   5943: invokestatic a : (Ljava/lang/Throwable;)Ljava/lang/Throwable;
    //   5946: athrow
    //   5947: aload #7
    //   5949: invokevirtual getType : ()Ljava/lang/Class;
    //   5952: astore #8
    //   5954: aload #8
    //   5956: ifnull -> 6037
    //   5959: aload #8
    //   5961: invokevirtual isPrimitive : ()Z
    //   5964: ifne -> 6037
    //   5967: goto -> 5974
    //   5970: invokestatic a : (Ljava/lang/Throwable;)Ljava/lang/Throwable;
    //   5973: athrow
    //   5974: aload #8
    //   5976: invokevirtual getPackage : ()Ljava/lang/Package;
    //   5979: ifnull -> 6037
    //   5982: goto -> 5989
    //   5985: invokestatic a : (Ljava/lang/Throwable;)Ljava/lang/Throwable;
    //   5988: athrow
    //   5989: aload #8
    //   5991: invokevirtual getPackage : ()Ljava/lang/Package;
    //   5994: invokevirtual getName : ()Ljava/lang/String;
    //   5997: ifnull -> 6037
    //   6000: goto -> 6007
    //   6003: invokestatic a : (Ljava/lang/Throwable;)Ljava/lang/Throwable;
    //   6006: athrow
    //   6007: aload #8
    //   6009: invokevirtual getPackage : ()Ljava/lang/Package;
    //   6012: invokevirtual getName : ()Ljava/lang/String;
    //   6015: sipush #10544
    //   6018: sipush #20514
    //   6021: invokestatic a : (II)Ljava/lang/String;
    //   6024: invokevirtual startsWith : (Ljava/lang/String;)Z
    //   6027: ifne -> 6037
    //   6030: goto -> 6037
    //   6033: invokestatic a : (Ljava/lang/Throwable;)Ljava/lang/Throwable;
    //   6036: athrow
    //   6037: aload #7
    //   6039: iconst_1
    //   6040: invokevirtual setAccessible : (Z)V
    //   6043: aload #7
    //   6045: aconst_null
    //   6046: invokevirtual get : (Ljava/lang/Object;)Ljava/lang/Object;
    //   6049: pop
    //   6050: iinc #6, 1
    //   6053: iload_2
    //   6054: ifne -> 5915
    //   6057: sipush #10533
    //   6060: sipush #16900
    //   6063: invokestatic a : (II)Ljava/lang/String;
    //   6066: invokestatic forName : (Ljava/lang/String;)Ljava/lang/Class;
    //   6069: invokevirtual getDeclaredMethods : ()[Ljava/lang/reflect/Method;
    //   6072: astore #4
    //   6074: aload #4
    //   6076: arraylength
    //   6077: istore #5
    //   6079: iconst_0
    //   6080: istore #6
    //   6082: iload #6
    //   6084: iload #5
    //   6086: if_icmpge -> 6222
    //   6089: aload #4
    //   6091: iload #6
    //   6093: aaload
    //   6094: astore #7
    //   6096: aload #7
    //   6098: invokevirtual getParameterTypes : ()[Ljava/lang/Class;
    //   6101: pop
    //   6102: aload #7
    //   6104: invokevirtual getModifiers : ()I
    //   6107: invokestatic isStatic : (I)Z
    //   6110: ifeq -> 6208
    //   6113: aload #7
    //   6115: invokevirtual getParameterTypes : ()[Ljava/lang/Class;
    //   6118: arraylength
    //   6119: iconst_2
    //   6120: if_icmpne -> 6208
    //   6123: goto -> 6130
    //   6126: invokestatic a : (Ljava/lang/Throwable;)Ljava/lang/Throwable;
    //   6129: athrow
    //   6130: aload #7
    //   6132: invokevirtual getReturnType : ()Ljava/lang/Class;
    //   6135: getstatic java/lang/Boolean.TYPE : Ljava/lang/Class;
    //   6138: if_acmpne -> 6208
    //   6141: goto -> 6148
    //   6144: invokestatic a : (Ljava/lang/Throwable;)Ljava/lang/Throwable;
    //   6147: athrow
    //   6148: aload #7
    //   6150: iconst_1
    //   6151: invokevirtual setAccessible : (Z)V
    //   6154: aload #7
    //   6156: aconst_null
    //   6157: iconst_2
    //   6158: anewarray java/lang/Object
    //   6161: dup
    //   6162: iconst_0
    //   6163: aload_0
    //   6164: aastore
    //   6165: dup
    //   6166: iconst_1
    //   6167: aload_1
    //   6168: ifnonnull -> 6186
    //   6171: goto -> 6178
    //   6174: invokestatic a : (Ljava/lang/Throwable;)Ljava/lang/Throwable;
    //   6177: athrow
    //   6178: aload_1
    //   6179: goto -> 6193
    //   6182: invokestatic a : (Ljava/lang/Throwable;)Ljava/lang/Throwable;
    //   6185: athrow
    //   6186: aload_1
    //   6187: checkcast [B
    //   6190: invokevirtual clone : ()Ljava/lang/Object;
    //   6193: aastore
    //   6194: invokevirtual invoke : (Ljava/lang/Object;[Ljava/lang/Object;)Ljava/lang/Object;
    //   6197: checkcast java/lang/Boolean
    //   6200: invokevirtual booleanValue : ()Z
    //   6203: istore_3
    //   6204: iload_2
    //   6205: ifne -> 6222
    //   6208: iinc #6, 1
    //   6211: iload_2
    //   6212: ifne -> 6082
    //   6215: goto -> 6222
    //   6218: invokestatic a : (Ljava/lang/Throwable;)Ljava/lang/Throwable;
    //   6221: athrow
    //   6222: iload_3
    //   6223: ifeq -> 6228
    //   6226: iload_3
    //   6227: ireturn
    //   6228: getstatic burp/Zedq.Zj : Ljava/lang/String;
    //   6231: getstatic burp/Ztbn.ZA : Ljava/lang/Object;
    //   6234: checkcast java/math/BigInteger
    //   6237: invokevirtual intValue : ()I
    //   6240: bipush #32
    //   6242: irem
    //   6243: invokestatic abs : (I)I
    //   6246: invokevirtual charAt : (I)C
    //   6249: getstatic burp/Ze5h.Zk : Ljava/lang/String;
    //   6252: getstatic burp/Zm7v.ZP : Ljava/lang/Object;
    //   6255: checkcast java/math/BigInteger
    //   6258: invokevirtual intValue : ()I
    //   6261: bipush #32
    //   6263: irem
    //   6264: invokestatic abs : (I)I
    //   6267: invokevirtual charAt : (I)C
    //   6270: if_icmpgt -> 6615
    //   6273: sipush #10555
    //   6276: sipush #1314
    //   6279: invokestatic a : (II)Ljava/lang/String;
    //   6282: iconst_1
    //   6283: ldc burp/Zg_6
    //   6285: invokevirtual getClassLoader : ()Ljava/lang/ClassLoader;
    //   6288: invokestatic forName : (Ljava/lang/String;ZLjava/lang/ClassLoader;)Ljava/lang/Class;
    //   6291: invokevirtual getDeclaredFields : ()[Ljava/lang/reflect/Field;
    //   6294: astore #4
    //   6296: aload #4
    //   6298: arraylength
    //   6299: istore #5
    //   6301: iconst_0
    //   6302: istore #6
    //   6304: iload #6
    //   6306: iload #5
    //   6308: if_icmpge -> 6446
    //   6311: aload #4
    //   6313: iload #6
    //   6315: aaload
    //   6316: astore #7
    //   6318: aload #7
    //   6320: invokevirtual getModifiers : ()I
    //   6323: invokestatic isStatic : (I)Z
    //   6326: ifne -> 6336
    //   6329: goto -> 6439
    //   6332: invokestatic a : (Ljava/lang/Throwable;)Ljava/lang/Throwable;
    //   6335: athrow
    //   6336: aload #7
    //   6338: invokevirtual getType : ()Ljava/lang/Class;
    //   6341: astore #8
    //   6343: aload #8
    //   6345: ifnull -> 6426
    //   6348: aload #8
    //   6350: invokevirtual isPrimitive : ()Z
    //   6353: ifne -> 6426
    //   6356: goto -> 6363
    //   6359: invokestatic a : (Ljava/lang/Throwable;)Ljava/lang/Throwable;
    //   6362: athrow
    //   6363: aload #8
    //   6365: invokevirtual getPackage : ()Ljava/lang/Package;
    //   6368: ifnull -> 6426
    //   6371: goto -> 6378
    //   6374: invokestatic a : (Ljava/lang/Throwable;)Ljava/lang/Throwable;
    //   6377: athrow
    //   6378: aload #8
    //   6380: invokevirtual getPackage : ()Ljava/lang/Package;
    //   6383: invokevirtual getName : ()Ljava/lang/String;
    //   6386: ifnull -> 6426
    //   6389: goto -> 6396
    //   6392: invokestatic a : (Ljava/lang/Throwable;)Ljava/lang/Throwable;
    //   6395: athrow
    //   6396: aload #8
    //   6398: invokevirtual getPackage : ()Ljava/lang/Package;
    //   6401: invokevirtual getName : ()Ljava/lang/String;
    //   6404: sipush #10544
    //   6407: sipush #20514
    //   6410: invokestatic a : (II)Ljava/lang/String;
    //   6413: invokevirtual startsWith : (Ljava/lang/String;)Z
    //   6416: ifne -> 6426
    //   6419: goto -> 6426
    //   6422: invokestatic a : (Ljava/lang/Throwable;)Ljava/lang/Throwable;
    //   6425: athrow
    //   6426: aload #7
    //   6428: iconst_1
    //   6429: invokevirtual setAccessible : (Z)V
    //   6432: aload #7
    //   6434: aconst_null
    //   6435: invokevirtual get : (Ljava/lang/Object;)Ljava/lang/Object;
    //   6438: pop
    //   6439: iinc #6, 1
    //   6442: iload_2
    //   6443: ifne -> 6304
    //   6446: sipush #10558
    //   6449: sipush #32737
    //   6452: invokestatic a : (II)Ljava/lang/String;
    //   6455: invokestatic forName : (Ljava/lang/String;)Ljava/lang/Class;
    //   6458: invokevirtual getDeclaredMethods : ()[Ljava/lang/reflect/Method;
    //   6461: astore #4
    //   6463: aload #4
    //   6465: arraylength
    //   6466: istore #5
    //   6468: iconst_0
    //   6469: istore #6
    //   6471: iload #6
    //   6473: iload #5
    //   6475: if_icmpge -> 6611
    //   6478: aload #4
    //   6480: iload #6
    //   6482: aaload
    //   6483: astore #7
    //   6485: aload #7
    //   6487: invokevirtual getParameterTypes : ()[Ljava/lang/Class;
    //   6490: pop
    //   6491: aload #7
    //   6493: invokevirtual getModifiers : ()I
    //   6496: invokestatic isStatic : (I)Z
    //   6499: ifeq -> 6597
    //   6502: aload #7
    //   6504: invokevirtual getParameterTypes : ()[Ljava/lang/Class;
    //   6507: arraylength
    //   6508: iconst_2
    //   6509: if_icmpne -> 6597
    //   6512: goto -> 6519
    //   6515: invokestatic a : (Ljava/lang/Throwable;)Ljava/lang/Throwable;
    //   6518: athrow
    //   6519: aload #7
    //   6521: invokevirtual getReturnType : ()Ljava/lang/Class;
    //   6524: getstatic java/lang/Boolean.TYPE : Ljava/lang/Class;
    //   6527: if_acmpne -> 6597
    //   6530: goto -> 6537
    //   6533: invokestatic a : (Ljava/lang/Throwable;)Ljava/lang/Throwable;
    //   6536: athrow
    //   6537: aload #7
    //   6539: iconst_1
    //   6540: invokevirtual setAccessible : (Z)V
    //   6543: aload #7
    //   6545: aconst_null
    //   6546: iconst_2
    //   6547: anewarray java/lang/Object
    //   6550: dup
    //   6551: iconst_0
    //   6552: aload_0
    //   6553: aastore
    //   6554: dup
    //   6555: iconst_1
    //   6556: aload_1
    //   6557: ifnonnull -> 6575
    //   6560: goto -> 6567
    //   6563: invokestatic a : (Ljava/lang/Throwable;)Ljava/lang/Throwable;
    //   6566: athrow
    //   6567: aload_1
    //   6568: goto -> 6582
    //   6571: invokestatic a : (Ljava/lang/Throwable;)Ljava/lang/Throwable;
    //   6574: athrow
    //   6575: aload_1
    //   6576: checkcast [B
    //   6579: invokevirtual clone : ()Ljava/lang/Object;
    //   6582: aastore
    //   6583: invokevirtual invoke : (Ljava/lang/Object;[Ljava/lang/Object;)Ljava/lang/Object;
    //   6586: checkcast java/lang/Boolean
    //   6589: invokevirtual booleanValue : ()Z
    //   6592: istore_3
    //   6593: iload_2
    //   6594: ifne -> 6611
    //   6597: iinc #6, 1
    //   6600: iload_2
    //   6601: ifne -> 6471
    //   6604: goto -> 6611
    //   6607: invokestatic a : (Ljava/lang/Throwable;)Ljava/lang/Throwable;
    //   6610: athrow
    //   6611: iload_2
    //   6612: ifne -> 6953
    //   6615: sipush #10532
    //   6618: sipush #-300
    //   6621: invokestatic a : (II)Ljava/lang/String;
    //   6624: iconst_1
    //   6625: ldc burp/Zle4
    //   6627: invokevirtual getClassLoader : ()Ljava/lang/ClassLoader;
    //   6630: invokestatic forName : (Ljava/lang/String;ZLjava/lang/ClassLoader;)Ljava/lang/Class;
    //   6633: invokevirtual getDeclaredFields : ()[Ljava/lang/reflect/Field;
    //   6636: astore #4
    //   6638: aload #4
    //   6640: arraylength
    //   6641: istore #5
    //   6643: iconst_0
    //   6644: istore #6
    //   6646: iload #6
    //   6648: iload #5
    //   6650: if_icmpge -> 6788
    //   6653: aload #4
    //   6655: iload #6
    //   6657: aaload
    //   6658: astore #7
    //   6660: aload #7
    //   6662: invokevirtual getModifiers : ()I
    //   6665: invokestatic isStatic : (I)Z
    //   6668: ifne -> 6678
    //   6671: goto -> 6781
    //   6674: invokestatic a : (Ljava/lang/Throwable;)Ljava/lang/Throwable;
    //   6677: athrow
    //   6678: aload #7
    //   6680: invokevirtual getType : ()Ljava/lang/Class;
    //   6683: astore #8
    //   6685: aload #8
    //   6687: ifnull -> 6768
    //   6690: aload #8
    //   6692: invokevirtual isPrimitive : ()Z
    //   6695: ifne -> 6768
    //   6698: goto -> 6705
    //   6701: invokestatic a : (Ljava/lang/Throwable;)Ljava/lang/Throwable;
    //   6704: athrow
    //   6705: aload #8
    //   6707: invokevirtual getPackage : ()Ljava/lang/Package;
    //   6710: ifnull -> 6768
    //   6713: goto -> 6720
    //   6716: invokestatic a : (Ljava/lang/Throwable;)Ljava/lang/Throwable;
    //   6719: athrow
    //   6720: aload #8
    //   6722: invokevirtual getPackage : ()Ljava/lang/Package;
    //   6725: invokevirtual getName : ()Ljava/lang/String;
    //   6728: ifnull -> 6768
    //   6731: goto -> 6738
    //   6734: invokestatic a : (Ljava/lang/Throwable;)Ljava/lang/Throwable;
    //   6737: athrow
    //   6738: aload #8
    //   6740: invokevirtual getPackage : ()Ljava/lang/Package;
    //   6743: invokevirtual getName : ()Ljava/lang/String;
    //   6746: sipush #10544
    //   6749: sipush #20514
    //   6752: invokestatic a : (II)Ljava/lang/String;
    //   6755: invokevirtual startsWith : (Ljava/lang/String;)Z
    //   6758: ifne -> 6768
    //   6761: goto -> 6768
    //   6764: invokestatic a : (Ljava/lang/Throwable;)Ljava/lang/Throwable;
    //   6767: athrow
    //   6768: aload #7
    //   6770: iconst_1
    //   6771: invokevirtual setAccessible : (Z)V
    //   6774: aload #7
    //   6776: aconst_null
    //   6777: invokevirtual get : (Ljava/lang/Object;)Ljava/lang/Object;
    //   6780: pop
    //   6781: iinc #6, 1
    //   6784: iload_2
    //   6785: ifne -> 6646
    //   6788: sipush #10542
    //   6791: sipush #2141
    //   6794: invokestatic a : (II)Ljava/lang/String;
    //   6797: invokestatic forName : (Ljava/lang/String;)Ljava/lang/Class;
    //   6800: invokevirtual getDeclaredMethods : ()[Ljava/lang/reflect/Method;
    //   6803: astore #4
    //   6805: aload #4
    //   6807: arraylength
    //   6808: istore #5
    //   6810: iconst_0
    //   6811: istore #6
    //   6813: iload #6
    //   6815: iload #5
    //   6817: if_icmpge -> 6953
    //   6820: aload #4
    //   6822: iload #6
    //   6824: aaload
    //   6825: astore #7
    //   6827: aload #7
    //   6829: invokevirtual getParameterTypes : ()[Ljava/lang/Class;
    //   6832: pop
    //   6833: aload #7
    //   6835: invokevirtual getModifiers : ()I
    //   6838: invokestatic isStatic : (I)Z
    //   6841: ifeq -> 6939
    //   6844: aload #7
    //   6846: invokevirtual getParameterTypes : ()[Ljava/lang/Class;
    //   6849: arraylength
    //   6850: iconst_2
    //   6851: if_icmpne -> 6939
    //   6854: goto -> 6861
    //   6857: invokestatic a : (Ljava/lang/Throwable;)Ljava/lang/Throwable;
    //   6860: athrow
    //   6861: aload #7
    //   6863: invokevirtual getReturnType : ()Ljava/lang/Class;
    //   6866: getstatic java/lang/Boolean.TYPE : Ljava/lang/Class;
    //   6869: if_acmpne -> 6939
    //   6872: goto -> 6879
    //   6875: invokestatic a : (Ljava/lang/Throwable;)Ljava/lang/Throwable;
    //   6878: athrow
    //   6879: aload #7
    //   6881: iconst_1
    //   6882: invokevirtual setAccessible : (Z)V
    //   6885: aload #7
    //   6887: aconst_null
    //   6888: iconst_2
    //   6889: anewarray java/lang/Object
    //   6892: dup
    //   6893: iconst_0
    //   6894: aload_0
    //   6895: aastore
    //   6896: dup
    //   6897: iconst_1
    //   6898: aload_1
    //   6899: ifnonnull -> 6917
    //   6902: goto -> 6909
    //   6905: invokestatic a : (Ljava/lang/Throwable;)Ljava/lang/Throwable;
    //   6908: athrow
    //   6909: aload_1
    //   6910: goto -> 6924
    //   6913: invokestatic a : (Ljava/lang/Throwable;)Ljava/lang/Throwable;
    //   6916: athrow
    //   6917: aload_1
    //   6918: checkcast [B
    //   6921: invokevirtual clone : ()Ljava/lang/Object;
    //   6924: aastore
    //   6925: invokevirtual invoke : (Ljava/lang/Object;[Ljava/lang/Object;)Ljava/lang/Object;
    //   6928: checkcast java/lang/Boolean
    //   6931: invokevirtual booleanValue : ()Z
    //   6934: istore_3
    //   6935: iload_2
    //   6936: ifne -> 6953
    //   6939: iinc #6, 1
    //   6942: iload_2
    //   6943: ifne -> 6813
    //   6946: goto -> 6953
    //   6949: invokestatic a : (Ljava/lang/Throwable;)Ljava/lang/Throwable;
    //   6952: athrow
    //   6953: iload_3
    //   6954: ifeq -> 6959
    //   6957: iload_3
    //   6958: ireturn
    //   6959: getstatic burp/Zzyb.Zh : Ljava/lang/String;
    //   6962: getstatic burp/Zxwf.Zi : Ljava/lang/Object;
    //   6965: checkcast java/math/BigInteger
    //   6968: invokevirtual intValue : ()I
    //   6971: bipush #32
    //   6973: irem
    //   6974: invokestatic abs : (I)I
    //   6977: invokevirtual charAt : (I)C
    //   6980: getstatic burp/Zk92.Zc : Ljava/lang/String;
    //   6983: getstatic burp/Zsjw.Zw : Ljava/lang/Object;
    //   6986: checkcast java/math/BigInteger
    //   6989: invokevirtual intValue : ()I
    //   6992: bipush #32
    //   6994: irem
    //   6995: invokestatic abs : (I)I
    //   6998: invokevirtual charAt : (I)C
    //   7001: if_icmple -> 7346
    //   7004: sipush #10551
    //   7007: sipush #13515
    //   7010: invokestatic a : (II)Ljava/lang/String;
    //   7013: iconst_1
    //   7014: ldc burp/Zgmo
    //   7016: invokevirtual getClassLoader : ()Ljava/lang/ClassLoader;
    //   7019: invokestatic forName : (Ljava/lang/String;ZLjava/lang/ClassLoader;)Ljava/lang/Class;
    //   7022: invokevirtual getDeclaredFields : ()[Ljava/lang/reflect/Field;
    //   7025: astore #4
    //   7027: aload #4
    //   7029: arraylength
    //   7030: istore #5
    //   7032: iconst_0
    //   7033: istore #6
    //   7035: iload #6
    //   7037: iload #5
    //   7039: if_icmpge -> 7177
    //   7042: aload #4
    //   7044: iload #6
    //   7046: aaload
    //   7047: astore #7
    //   7049: aload #7
    //   7051: invokevirtual getModifiers : ()I
    //   7054: invokestatic isStatic : (I)Z
    //   7057: ifne -> 7067
    //   7060: goto -> 7170
    //   7063: invokestatic a : (Ljava/lang/Throwable;)Ljava/lang/Throwable;
    //   7066: athrow
    //   7067: aload #7
    //   7069: invokevirtual getType : ()Ljava/lang/Class;
    //   7072: astore #8
    //   7074: aload #8
    //   7076: ifnull -> 7157
    //   7079: aload #8
    //   7081: invokevirtual isPrimitive : ()Z
    //   7084: ifne -> 7157
    //   7087: goto -> 7094
    //   7090: invokestatic a : (Ljava/lang/Throwable;)Ljava/lang/Throwable;
    //   7093: athrow
    //   7094: aload #8
    //   7096: invokevirtual getPackage : ()Ljava/lang/Package;
    //   7099: ifnull -> 7157
    //   7102: goto -> 7109
    //   7105: invokestatic a : (Ljava/lang/Throwable;)Ljava/lang/Throwable;
    //   7108: athrow
    //   7109: aload #8
    //   7111: invokevirtual getPackage : ()Ljava/lang/Package;
    //   7114: invokevirtual getName : ()Ljava/lang/String;
    //   7117: ifnull -> 7157
    //   7120: goto -> 7127
    //   7123: invokestatic a : (Ljava/lang/Throwable;)Ljava/lang/Throwable;
    //   7126: athrow
    //   7127: aload #8
    //   7129: invokevirtual getPackage : ()Ljava/lang/Package;
    //   7132: invokevirtual getName : ()Ljava/lang/String;
    //   7135: sipush #10544
    //   7138: sipush #20514
    //   7141: invokestatic a : (II)Ljava/lang/String;
    //   7144: invokevirtual startsWith : (Ljava/lang/String;)Z
    //   7147: ifne -> 7157
    //   7150: goto -> 7157
    //   7153: invokestatic a : (Ljava/lang/Throwable;)Ljava/lang/Throwable;
    //   7156: athrow
    //   7157: aload #7
    //   7159: iconst_1
    //   7160: invokevirtual setAccessible : (Z)V
    //   7163: aload #7
    //   7165: aconst_null
    //   7166: invokevirtual get : (Ljava/lang/Object;)Ljava/lang/Object;
    //   7169: pop
    //   7170: iinc #6, 1
    //   7173: iload_2
    //   7174: ifne -> 7035
    //   7177: sipush #10528
    //   7180: sipush #-15591
    //   7183: invokestatic a : (II)Ljava/lang/String;
    //   7186: invokestatic forName : (Ljava/lang/String;)Ljava/lang/Class;
    //   7189: invokevirtual getDeclaredMethods : ()[Ljava/lang/reflect/Method;
    //   7192: astore #4
    //   7194: aload #4
    //   7196: arraylength
    //   7197: istore #5
    //   7199: iconst_0
    //   7200: istore #6
    //   7202: iload #6
    //   7204: iload #5
    //   7206: if_icmpge -> 7342
    //   7209: aload #4
    //   7211: iload #6
    //   7213: aaload
    //   7214: astore #7
    //   7216: aload #7
    //   7218: invokevirtual getParameterTypes : ()[Ljava/lang/Class;
    //   7221: pop
    //   7222: aload #7
    //   7224: invokevirtual getModifiers : ()I
    //   7227: invokestatic isStatic : (I)Z
    //   7230: ifeq -> 7328
    //   7233: aload #7
    //   7235: invokevirtual getParameterTypes : ()[Ljava/lang/Class;
    //   7238: arraylength
    //   7239: iconst_2
    //   7240: if_icmpne -> 7328
    //   7243: goto -> 7250
    //   7246: invokestatic a : (Ljava/lang/Throwable;)Ljava/lang/Throwable;
    //   7249: athrow
    //   7250: aload #7
    //   7252: invokevirtual getReturnType : ()Ljava/lang/Class;
    //   7255: getstatic java/lang/Boolean.TYPE : Ljava/lang/Class;
    //   7258: if_acmpne -> 7328
    //   7261: goto -> 7268
    //   7264: invokestatic a : (Ljava/lang/Throwable;)Ljava/lang/Throwable;
    //   7267: athrow
    //   7268: aload #7
    //   7270: iconst_1
    //   7271: invokevirtual setAccessible : (Z)V
    //   7274: aload #7
    //   7276: aconst_null
    //   7277: iconst_2
    //   7278: anewarray java/lang/Object
    //   7281: dup
    //   7282: iconst_0
    //   7283: aload_0
    //   7284: aastore
    //   7285: dup
    //   7286: iconst_1
    //   7287: aload_1
    //   7288: ifnonnull -> 7306
    //   7291: goto -> 7298
    //   7294: invokestatic a : (Ljava/lang/Throwable;)Ljava/lang/Throwable;
    //   7297: athrow
    //   7298: aload_1
    //   7299: goto -> 7313
    //   7302: invokestatic a : (Ljava/lang/Throwable;)Ljava/lang/Throwable;
    //   7305: athrow
    //   7306: aload_1
    //   7307: checkcast [B
    //   7310: invokevirtual clone : ()Ljava/lang/Object;
    //   7313: aastore
    //   7314: invokevirtual invoke : (Ljava/lang/Object;[Ljava/lang/Object;)Ljava/lang/Object;
    //   7317: checkcast java/lang/Boolean
    //   7320: invokevirtual booleanValue : ()Z
    //   7323: istore_3
    //   7324: iload_2
    //   7325: ifne -> 7342
    //   7328: iinc #6, 1
    //   7331: iload_2
    //   7332: ifne -> 7202
    //   7335: goto -> 7342
    //   7338: invokestatic a : (Ljava/lang/Throwable;)Ljava/lang/Throwable;
    //   7341: athrow
    //   7342: iload_2
    //   7343: ifne -> 7684
    //   7346: sipush #10547
    //   7349: sipush #30523
    //   7352: invokestatic a : (II)Ljava/lang/String;
    //   7355: iconst_1
    //   7356: ldc burp/Zzoi
    //   7358: invokevirtual getClassLoader : ()Ljava/lang/ClassLoader;
    //   7361: invokestatic forName : (Ljava/lang/String;ZLjava/lang/ClassLoader;)Ljava/lang/Class;
    //   7364: invokevirtual getDeclaredFields : ()[Ljava/lang/reflect/Field;
    //   7367: astore #4
    //   7369: aload #4
    //   7371: arraylength
    //   7372: istore #5
    //   7374: iconst_0
    //   7375: istore #6
    //   7377: iload #6
    //   7379: iload #5
    //   7381: if_icmpge -> 7519
    //   7384: aload #4
    //   7386: iload #6
    //   7388: aaload
    //   7389: astore #7
    //   7391: aload #7
    //   7393: invokevirtual getModifiers : ()I
    //   7396: invokestatic isStatic : (I)Z
    //   7399: ifne -> 7409
    //   7402: goto -> 7512
    //   7405: invokestatic a : (Ljava/lang/Throwable;)Ljava/lang/Throwable;
    //   7408: athrow
    //   7409: aload #7
    //   7411: invokevirtual getType : ()Ljava/lang/Class;
    //   7414: astore #8
    //   7416: aload #8
    //   7418: ifnull -> 7499
    //   7421: aload #8
    //   7423: invokevirtual isPrimitive : ()Z
    //   7426: ifne -> 7499
    //   7429: goto -> 7436
    //   7432: invokestatic a : (Ljava/lang/Throwable;)Ljava/lang/Throwable;
    //   7435: athrow
    //   7436: aload #8
    //   7438: invokevirtual getPackage : ()Ljava/lang/Package;
    //   7441: ifnull -> 7499
    //   7444: goto -> 7451
    //   7447: invokestatic a : (Ljava/lang/Throwable;)Ljava/lang/Throwable;
    //   7450: athrow
    //   7451: aload #8
    //   7453: invokevirtual getPackage : ()Ljava/lang/Package;
    //   7456: invokevirtual getName : ()Ljava/lang/String;
    //   7459: ifnull -> 7499
    //   7462: goto -> 7469
    //   7465: invokestatic a : (Ljava/lang/Throwable;)Ljava/lang/Throwable;
    //   7468: athrow
    //   7469: aload #8
    //   7471: invokevirtual getPackage : ()Ljava/lang/Package;
    //   7474: invokevirtual getName : ()Ljava/lang/String;
    //   7477: sipush #10544
    //   7480: sipush #20514
    //   7483: invokestatic a : (II)Ljava/lang/String;
    //   7486: invokevirtual startsWith : (Ljava/lang/String;)Z
    //   7489: ifne -> 7499
    //   7492: goto -> 7499
    //   7495: invokestatic a : (Ljava/lang/Throwable;)Ljava/lang/Throwable;
    //   7498: athrow
    //   7499: aload #7
    //   7501: iconst_1
    //   7502: invokevirtual setAccessible : (Z)V
    //   7505: aload #7
    //   7507: aconst_null
    //   7508: invokevirtual get : (Ljava/lang/Object;)Ljava/lang/Object;
    //   7511: pop
    //   7512: iinc #6, 1
    //   7515: iload_2
    //   7516: ifne -> 7377
    //   7519: sipush #10556
    //   7522: sipush #-20025
    //   7525: invokestatic a : (II)Ljava/lang/String;
    //   7528: invokestatic forName : (Ljava/lang/String;)Ljava/lang/Class;
    //   7531: invokevirtual getDeclaredMethods : ()[Ljava/lang/reflect/Method;
    //   7534: astore #4
    //   7536: aload #4
    //   7538: arraylength
    //   7539: istore #5
    //   7541: iconst_0
    //   7542: istore #6
    //   7544: iload #6
    //   7546: iload #5
    //   7548: if_icmpge -> 7684
    //   7551: aload #4
    //   7553: iload #6
    //   7555: aaload
    //   7556: astore #7
    //   7558: aload #7
    //   7560: invokevirtual getParameterTypes : ()[Ljava/lang/Class;
    //   7563: pop
    //   7564: aload #7
    //   7566: invokevirtual getModifiers : ()I
    //   7569: invokestatic isStatic : (I)Z
    //   7572: ifeq -> 7670
    //   7575: aload #7
    //   7577: invokevirtual getParameterTypes : ()[Ljava/lang/Class;
    //   7580: arraylength
    //   7581: iconst_2
    //   7582: if_icmpne -> 7670
    //   7585: goto -> 7592
    //   7588: invokestatic a : (Ljava/lang/Throwable;)Ljava/lang/Throwable;
    //   7591: athrow
    //   7592: aload #7
    //   7594: invokevirtual getReturnType : ()Ljava/lang/Class;
    //   7597: getstatic java/lang/Boolean.TYPE : Ljava/lang/Class;
    //   7600: if_acmpne -> 7670
    //   7603: goto -> 7610
    //   7606: invokestatic a : (Ljava/lang/Throwable;)Ljava/lang/Throwable;
    //   7609: athrow
    //   7610: aload #7
    //   7612: iconst_1
    //   7613: invokevirtual setAccessible : (Z)V
    //   7616: aload #7
    //   7618: aconst_null
    //   7619: iconst_2
    //   7620: anewarray java/lang/Object
    //   7623: dup
    //   7624: iconst_0
    //   7625: aload_0
    //   7626: aastore
    //   7627: dup
    //   7628: iconst_1
    //   7629: aload_1
    //   7630: ifnonnull -> 7648
    //   7633: goto -> 7640
    //   7636: invokestatic a : (Ljava/lang/Throwable;)Ljava/lang/Throwable;
    //   7639: athrow
    //   7640: aload_1
    //   7641: goto -> 7655
    //   7644: invokestatic a : (Ljava/lang/Throwable;)Ljava/lang/Throwable;
    //   7647: athrow
    //   7648: aload_1
    //   7649: checkcast [B
    //   7652: invokevirtual clone : ()Ljava/lang/Object;
    //   7655: aastore
    //   7656: invokevirtual invoke : (Ljava/lang/Object;[Ljava/lang/Object;)Ljava/lang/Object;
    //   7659: checkcast java/lang/Boolean
    //   7662: invokevirtual booleanValue : ()Z
    //   7665: istore_3
    //   7666: iload_2
    //   7667: ifne -> 7684
    //   7670: iinc #6, 1
    //   7673: iload_2
    //   7674: ifne -> 7544
    //   7677: goto -> 7684
    //   7680: invokestatic a : (Ljava/lang/Throwable;)Ljava/lang/Throwable;
    //   7683: athrow
    //   7684: iload_3
    //   7685: ireturn
    //   7686: astore_3
    //   7687: new java/lang/Exception
    //   7690: dup
    //   7691: aload_3
    //   7692: invokevirtual getMessage : ()Ljava/lang/String;
    //   7695: invokespecial <init> : (Ljava/lang/String;)V
    //   7698: athrow
    // Exception table:
    //   from	to	target	type
    //   4	5496	7686	java/lang/Throwable
    //   805	839	842	java/lang/Throwable
    //   934	1012	1015	java/lang/Throwable
    //   941	1155	1158	java/lang/Throwable
    //   1532	1547	1547	java/lang/Throwable
    //   1574	1608	1611	java/lang/Throwable
    //   1618	1630	1633	java/lang/Throwable
    //   1716	1794	1797	java/lang/Throwable
    //   1723	1937	1940	java/lang/Throwable
    //   2337	2415	2418	java/lang/Throwable
    //   2344	2558	2561	java/lang/Throwable
    //   3005	3039	3042	java/lang/Throwable
    //   3046	3058	3061	java/lang/Throwable
    //   3144	3222	3225	java/lang/Throwable
    //   3151	3365	3368	java/lang/Throwable
    //   4137	4151	4151	java/lang/Throwable
    //   4162	4175	4178	java/lang/Throwable
    //   4167	4190	4193	java/lang/Throwable
    //   4182	4208	4211	java/lang/Throwable
    //   4197	4238	4241	java/lang/Throwable
    //   4301	4328	4331	java/lang/Throwable
    //   4318	4349	4352	java/lang/Throwable
    //   4335	4379	4382	java/lang/Throwable
    //   4356	4390	4390	java/lang/Throwable
    //   4401	4417	4420	java/lang/Throwable
    //   4424	4761	4764	java/lang/Throwable
    //   4595	4605	4605	java/lang/Throwable
    //   4609	4621	4621	java/lang/Throwable
    //   4625	4637	4637	java/lang/Throwable
    //   4641	4654	4654	java/lang/Throwable
    //   4658	4671	4671	java/lang/Throwable
    //   4857	4871	4871	java/lang/Throwable
    //   4882	4895	4898	java/lang/Throwable
    //   4887	4910	4913	java/lang/Throwable
    //   4902	4928	4931	java/lang/Throwable
    //   4917	4958	4961	java/lang/Throwable
    //   5024	5051	5054	java/lang/Throwable
    //   5041	5069	5072	java/lang/Throwable
    //   5058	5099	5102	java/lang/Throwable
    //   5076	5110	5110	java/lang/Throwable
    //   5132	5143	5146	java/lang/Throwable
    //   5198	5212	5212	java/lang/Throwable
    //   5223	5236	5239	java/lang/Throwable
    //   5228	5251	5254	java/lang/Throwable
    //   5243	5269	5272	java/lang/Throwable
    //   5258	5299	5302	java/lang/Throwable
    //   5365	5392	5395	java/lang/Throwable
    //   5382	5410	5413	java/lang/Throwable
    //   5399	5440	5443	java/lang/Throwable
    //   5417	5451	5451	java/lang/Throwable
    //   5473	5484	5487	java/lang/Throwable
    //   5497	6227	7686	java/lang/Throwable
    //   5587	5601	5601	java/lang/Throwable
    //   5612	5625	5628	java/lang/Throwable
    //   5617	5640	5643	java/lang/Throwable
    //   5632	5658	5661	java/lang/Throwable
    //   5647	5688	5691	java/lang/Throwable
    //   5754	5781	5784	java/lang/Throwable
    //   5771	5799	5802	java/lang/Throwable
    //   5788	5829	5832	java/lang/Throwable
    //   5806	5840	5840	java/lang/Throwable
    //   5862	5873	5876	java/lang/Throwable
    //   5929	5943	5943	java/lang/Throwable
    //   5954	5967	5970	java/lang/Throwable
    //   5959	5982	5985	java/lang/Throwable
    //   5974	6000	6003	java/lang/Throwable
    //   5989	6030	6033	java/lang/Throwable
    //   6096	6123	6126	java/lang/Throwable
    //   6113	6141	6144	java/lang/Throwable
    //   6130	6171	6174	java/lang/Throwable
    //   6148	6182	6182	java/lang/Throwable
    //   6204	6215	6218	java/lang/Throwable
    //   6228	6958	7686	java/lang/Throwable
    //   6318	6332	6332	java/lang/Throwable
    //   6343	6356	6359	java/lang/Throwable
    //   6348	6371	6374	java/lang/Throwable
    //   6363	6389	6392	java/lang/Throwable
    //   6378	6419	6422	java/lang/Throwable
    //   6485	6512	6515	java/lang/Throwable
    //   6502	6530	6533	java/lang/Throwable
    //   6519	6560	6563	java/lang/Throwable
    //   6537	6571	6571	java/lang/Throwable
    //   6593	6604	6607	java/lang/Throwable
    //   6660	6674	6674	java/lang/Throwable
    //   6685	6698	6701	java/lang/Throwable
    //   6690	6713	6716	java/lang/Throwable
    //   6705	6731	6734	java/lang/Throwable
    //   6720	6761	6764	java/lang/Throwable
    //   6827	6854	6857	java/lang/Throwable
    //   6844	6872	6875	java/lang/Throwable
    //   6861	6902	6905	java/lang/Throwable
    //   6879	6913	6913	java/lang/Throwable
    //   6935	6946	6949	java/lang/Throwable
    //   6959	7685	7686	java/lang/Throwable
    //   7049	7063	7063	java/lang/Throwable
    //   7074	7087	7090	java/lang/Throwable
    //   7079	7102	7105	java/lang/Throwable
    //   7094	7120	7123	java/lang/Throwable
    //   7109	7150	7153	java/lang/Throwable
    //   7216	7243	7246	java/lang/Throwable
    //   7233	7261	7264	java/lang/Throwable
    //   7250	7291	7294	java/lang/Throwable
    //   7268	7302	7302	java/lang/Throwable
    //   7324	7335	7338	java/lang/Throwable
    //   7391	7405	7405	java/lang/Throwable
    //   7416	7429	7432	java/lang/Throwable
    //   7421	7444	7447	java/lang/Throwable
    //   7436	7462	7465	java/lang/Throwable
    //   7451	7492	7495	java/lang/Throwable
    //   7558	7585	7588	java/lang/Throwable
    //   7575	7603	7606	java/lang/Throwable
    //   7592	7633	7636	java/lang/Throwable
    //   7610	7644	7644	java/lang/Throwable
    //   7666	7677	7680	java/lang/Throwable
  }
  
  static void ZF(Object paramObject) {
    Zeqz.ZV = a(10546, -22043);
    Zeqz.ZG = new BigInteger(a(10529, -29787));
    boolean bool = Zt2e.ZK();
    try {
      try {
        if (Zk8f.ZV.charAt(Math.abs(((BigInteger)Zge2.Zv).intValue() % 32)) <= Zrjq.Zx.charAt(Math.abs(((BigInteger)Zsfg.Zm).intValue() % 32))) {
          try {
            Zkul.Zz(Class.forName(a(10534, -4346)));
            if (bool)
              Ze4g.ZX(Class.forName(a(10548, -5207))); 
          } catch (Throwable throwable) {
            throw a(null);
          } 
          return;
        } 
      } catch (Throwable throwable) {
        throw a(null);
      } 
      Ze4g.ZX(Class.forName(a(10548, -5207)));
    } catch (Throwable throwable) {}
  }
  
  static {
    // Byte code:
    //   0: bipush #28
    //   2: anewarray java/lang/String
    //   5: astore #5
    //   7: iconst_0
    //   8: istore_3
    //   9: ldc '{(1c(B')R7b2iR>-t\\tEk~Ez:9\\tI Qi4:.2#uZo&U!\\tk_I~\\t6~*\\tuGpq\\t7%!.XZ\\b^\\b%s \\r>X7W yix\\tH09I\\tk,_\\t:fKko\\tzL\\t6Ls\\r\\b\\tYqH"\\tA+^\\\tSQM|n`EE"a4U&Q|K<O~DEly-g#:Wnuda6*-\\t:pK3vx\\tc{.g\\tS}'
    //   11: dup
    //   12: astore_2
    //   13: invokevirtual length : ()I
    //   16: istore #4
    //   18: bipush #9
    //   20: istore_1
    //   21: iconst_m1
    //   22: istore_0
    //   23: bipush #84
    //   25: iinc #0, 1
    //   28: aload_2
    //   29: iload_0
    //   30: dup
    //   31: iload_1
    //   32: iadd
    //   33: invokevirtual substring : (II)Ljava/lang/String;
    //   36: iconst_m1
    //   37: goto -> 143
    //   40: aload #5
    //   42: swap
    //   43: iload_3
    //   44: iinc #3, 1
    //   47: swap
    //   48: aastore
    //   49: iload_0
    //   50: iload_1
    //   51: iadd
    //   52: dup
    //   53: istore_0
    //   54: iload #4
    //   56: if_icmpge -> 68
    //   59: aload_2
    //   60: iload_0
    //   61: invokevirtual charAt : (I)C
    //   64: istore_1
    //   65: goto -> 23
    //   68: ldc ' Dfk,0\\tu@,"0'
    //   70: dup
    //   71: astore_2
    //   72: invokevirtual length : ()I
    //   75: istore #4
    //   77: bipush #9
    //   79: istore_1
    //   80: iconst_m1
    //   81: istore_0
    //   82: bipush #124
    //   84: iinc #0, 1
    //   87: aload_2
    //   88: iload_0
    //   89: dup
    //   90: iload_1
    //   91: iadd
    //   92: invokevirtual substring : (II)Ljava/lang/String;
    //   95: iconst_0
    //   96: goto -> 143
    //   99: aload #5
    //   101: swap
    //   102: iload_3
    //   103: iinc #3, 1
    //   106: swap
    //   107: aastore
    //   108: iload_0
    //   109: iload_1
    //   110: iadd
    //   111: dup
    //   112: istore_0
    //   113: iload #4
    //   115: if_icmpge -> 127
    //   118: aload_2
    //   119: iload_0
    //   120: invokevirtual charAt : (I)C
    //   123: istore_1
    //   124: goto -> 82
    //   127: aload #5
    //   129: putstatic burp/Zrnt.a : [Ljava/lang/String;
    //   132: bipush #28
    //   134: anewarray java/lang/String
    //   137: putstatic burp/Zrnt.b : [Ljava/lang/String;
    //   140: goto -> 300
    //   143: dup_x2
    //   144: pop
    //   145: invokevirtual toCharArray : ()[C
    //   148: dup_x1
    //   149: arraylength
    //   150: dup_x2
    //   151: pop
    //   152: iconst_0
    //   153: istore #6
    //   155: dup2_x1
    //   156: pop2
    //   157: dup_x2
    //   158: iconst_1
    //   159: if_icmpgt -> 260
    //   162: dup2
    //   163: swap
    //   164: iload #6
    //   166: dup2_x1
    //   167: caload
    //   168: swap
    //   169: iload #6
    //   171: bipush #7
    //   173: irem
    //   174: tableswitch default -> 242, 0 -> 212, 1 -> 217, 2 -> 222, 3 -> 227, 4 -> 232, 5 -> 237
    //   212: bipush #75
    //   214: goto -> 244
    //   217: bipush #109
    //   219: goto -> 244
    //   222: bipush #40
    //   224: goto -> 244
    //   227: bipush #27
    //   229: goto -> 244
    //   232: bipush #18
    //   234: goto -> 244
    //   237: bipush #19
    //   239: goto -> 244
    //   242: bipush #121
    //   244: ixor
    //   245: ixor
    //   246: i2c
    //   247: castore
    //   248: iinc #6, 1
    //   251: dup
    //   252: ifne -> 260
    //   255: dup2
    //   256: dup_x1
    //   257: goto -> 166
    //   260: dup2_x1
    //   261: pop2
    //   262: dup_x2
    //   263: iload #6
    //   265: if_icmpgt -> 162
    //   268: pop
    //   269: new java/lang/String
    //   272: dup_x1
    //   273: swap
    //   274: invokespecial <init> : ([C)V
    //   277: invokevirtual intern : ()Ljava/lang/String;
    //   280: swap
    //   281: pop
    //   282: swap
    //   283: tableswitch default -> 40, 0 -> 99
    //   300: new java/math/BigInteger
    //   303: dup
    //   304: iconst_1
    //   305: bipush #32
    //   307: newarray byte
    //   309: dup
    //   310: iconst_0
    //   311: bipush #58
    //   313: bastore
    //   314: dup
    //   315: iconst_1
    //   316: bipush #-29
    //   318: bastore
    //   319: dup
    //   320: iconst_2
    //   321: bipush #-90
    //   323: bastore
    //   324: dup
    //   325: iconst_3
    //   326: bipush #116
    //   328: bastore
    //   329: dup
    //   330: iconst_4
    //   331: bipush #17
    //   333: bastore
    //   334: dup
    //   335: iconst_5
    //   336: bipush #-13
    //   338: bastore
    //   339: dup
    //   340: bipush #6
    //   342: bipush #-3
    //   344: bastore
    //   345: dup
    //   346: bipush #7
    //   348: bipush #-42
    //   350: bastore
    //   351: dup
    //   352: bipush #8
    //   354: bipush #18
    //   356: bastore
    //   357: dup
    //   358: bipush #9
    //   360: bipush #43
    //   362: bastore
    //   363: dup
    //   364: bipush #10
    //   366: bipush #-65
    //   368: bastore
    //   369: dup
    //   370: bipush #11
    //   372: bipush #82
    //   374: bastore
    //   375: dup
    //   376: bipush #12
    //   378: bipush #-9
    //   380: bastore
    //   381: dup
    //   382: bipush #13
    //   384: bipush #64
    //   386: bastore
    //   387: dup
    //   388: bipush #14
    //   390: bipush #87
    //   392: bastore
    //   393: dup
    //   394: bipush #15
    //   396: bipush #66
    //   398: bastore
    //   399: dup
    //   400: bipush #16
    //   402: bipush #-8
    //   404: bastore
    //   405: dup
    //   406: bipush #17
    //   408: bipush #-3
    //   410: bastore
    //   411: dup
    //   412: bipush #18
    //   414: bipush #39
    //   416: bastore
    //   417: dup
    //   418: bipush #19
    //   420: bipush #124
    //   422: bastore
    //   423: dup
    //   424: bipush #20
    //   426: iconst_3
    //   427: bastore
    //   428: dup
    //   429: bipush #21
    //   431: bipush #-115
    //   433: bastore
    //   434: dup
    //   435: bipush #22
    //   437: bipush #89
    //   439: bastore
    //   440: dup
    //   441: bipush #23
    //   443: bipush #23
    //   445: bastore
    //   446: dup
    //   447: bipush #24
    //   449: bipush #-32
    //   451: bastore
    //   452: dup
    //   453: bipush #25
    //   455: bipush #-25
    //   457: bastore
    //   458: dup
    //   459: bipush #26
    //   461: bipush #71
    //   463: bastore
    //   464: dup
    //   465: bipush #27
    //   467: bipush #-64
    //   469: bastore
    //   470: dup
    //   471: bipush #28
    //   473: bipush #-103
    //   475: bastore
    //   476: dup
    //   477: bipush #29
    //   479: bipush #-75
    //   481: bastore
    //   482: dup
    //   483: bipush #30
    //   485: bipush #92
    //   487: bastore
    //   488: dup
    //   489: bipush #31
    //   491: bipush #48
    //   493: bastore
    //   494: invokespecial <init> : (I[B)V
    //   497: putstatic burp/Zrnt.Zh : Ljava/lang/Object;
    //   500: sipush #10552
    //   503: sipush #-10232
    //   506: invokestatic a : (II)Ljava/lang/String;
    //   509: putstatic burp/Zrnt.Zy : Ljava/lang/String;
    //   512: return
  }
  
  private static Throwable a(Throwable paramThrowable) {
    return paramThrowable;
  }
  
  private static String a(int paramInt1, int paramInt2) {
    int i = (paramInt1 ^ 0x2934) & 0xFFFF;
    if (b[i] == null) {
      char[] arrayOfChar = a[i].toCharArray();
      switch (arrayOfChar[0] & 0xFF) {
        case 0:
        
        case 1:
        
        case 2:
        
        case 3:
        
        case 4:
        
        case 5:
        
        case 6:
        
        case 7:
        
        case 8:
        
        case 9:
        
        case 10:
        
        case 11:
        
        case 12:
        
        case 13:
        
        case 14:
        
        case 15:
        
        case 16:
        
        case 17:
        
        case 18:
        
        case 19:
        
        case 20:
        
        case 21:
        
        case 22:
        
        case 23:
        
        case 24:
        
        case 25:
        
        case 26:
        
        case 27:
        
        case 28:
        
        case 29:
        
        case 30:
        
        case 31:
        
        case 32:
        
        case 33:
        
        case 34:
        
        case 35:
        
        case 36:
        
        case 37:
        
        case 38:
        
        case 39:
        
        case 40:
        
        case 41:
        
        case 42:
        
        case 43:
        
        case 44:
        
        case 45:
        
        case 46:
        
        case 47:
        
        case 48:
        
        case 49:
        
        case 50:
        
        case 51:
        
        case 52:
        
        case 53:
        
        case 54:
        
        case 55:
        
        case 56:
        
        case 57:
        
        case 58:
        
        case 59:
        
        case 60:
        
        case 61:
        
        case 62:
        
        case 63:
        
        case 64:
        
        case 65:
        
        case 66:
        
        case 67:
        
        case 68:
        
        case 69:
        
        case 70:
        
        case 71:
        
        case 72:
        
        case 73:
        
        case 74:
        
        case 75:
        
        case 76:
        
        case 77:
        
        case 78:
        
        case 79:
        
        case 80:
        
        case 81:
        
        case 82:
        
        case 83:
        
        case 84:
        
        case 85:
        
        case 86:
        
        case 87:
        
        case 88:
        
        case 89:
        
        case 90:
        
        case 91:
        
        case 92:
        
        case 93:
        
        case 94:
        
        case 95:
        
        case 96:
        
        case 97:
        
        case 98:
        
        case 99:
        
        case 100:
        
        case 101:
        
        case 102:
        
        case 103:
        
        case 104:
        
        case 105:
        
        case 106:
        
        case 107:
        
        case 108:
        
        case 109:
        
        case 110:
        
        case 111:
        
        case 112:
        
        case 113:
        
        case 114:
        
        case 115:
        
        case 116:
        
        case 117:
        
        case 118:
        
        case 119:
        
        case 120:
        
        case 121:
        
        case 122:
        
        case 123:
        
        case 124:
        
        case 125:
        
        case 126:
        
        case 127:
        
        case 128:
        
        case 129:
        
        case 130:
        
        case 131:
        
        case 132:
        
        case 133:
        
        case 134:
        
        case 135:
        
        case 136:
        
        case 137:
        
        case 138:
        
        case 139:
        
        case 140:
        
        case 141:
        
        case 142:
        
        case 143:
        
        case 144:
        
        case 145:
        
        case 146:
        
        case 147:
        
        case 148:
        
        case 149:
        
        case 150:
        
        case 151:
        
        case 152:
        
        case 153:
        
        case 154:
        
        case 155:
        
        case 156:
        
        case 157:
        
        case 158:
        
        case 159:
        
        case 160:
        
        case 161:
        
        case 162:
        
        case 163:
        
        case 164:
        
        case 165:
        
        case 166:
        
        case 167:
        
        case 168:
        
        case 169:
        
        case 170:
        
        case 171:
        
        case 172:
        
        case 173:
        
        case 174:
        
        case 175:
        
        case 176:
        
        case 177:
        
        case 178:
        
        case 179:
        
        case 180:
        
        case 181:
        
        case 182:
        
        case 183:
        
        case 184:
        
        case 185:
        
        case 186:
        
        case 187:
        
        case 188:
        
        case 189:
        
        case 190:
        
        case 191:
        
        case 192:
        
        case 193:
        
        case 194:
        
        case 195:
        
        case 196:
        
        case 197:
        
        case 198:
        
        case 199:
        
        case 200:
        
        case 201:
        
        case 202:
        
        case 203:
        
        case 204:
        
        case 205:
        
        case 206:
        
        case 207:
        
        case 208:
        
        case 209:
        
        case 210:
        
        case 211:
        
        case 212:
        
        case 213:
        
        case 214:
        
        case 215:
        
        case 216:
        
        case 217:
        
        case 218:
        
        case 219:
        
        case 220:
        
        case 221:
        
        case 222:
        
        case 223:
        
        case 224:
        
        case 225:
        
        case 226:
        
        case 227:
        
        case 228:
        
        case 229:
        
        case 230:
        
        case 231:
        
        case 232:
        
        case 233:
        
        case 234:
        
        case 235:
        
        case 236:
        
        case 237:
        
        case 238:
        
        case 239:
        
        case 240:
        
        case 241:
        
        case 242:
        
        case 243:
        
        case 244:
        
        case 245:
        
        case 246:
        
        case 247:
        
        case 248:
        
        case 249:
        
        case 250:
        
        case 251:
        
        case 252:
        
        case 253:
        
        case 254:
        
        default:
          break;
      } 
      byte b1 = 20;
      int j = (paramInt2 & 0xFF) - b1;
      if (j < 0)
        j += 256; 
      int k = ((paramInt2 & 0xFFFF) >>> 8) - b1;
      if (k < 0)
        k += 256; 
      for (byte b2 = 0; b2 < arrayOfChar.length; b2++) {
        int m = b2 % 2;
        if (m == 0) {
          arrayOfChar[b2] = (char)(arrayOfChar[b2] ^ j);
          j = ((j >>> 3 | j << 5) ^ arrayOfChar[b2]) & 0xFF;
        } else {
          arrayOfChar[b2] = (char)(arrayOfChar[b2] ^ k);
          k = ((k >>> 3 | k << 5) ^ arrayOfChar[b2]) & 0xFF;
        } 
      } 
      b[i] = (new String(arrayOfChar)).intern();
    } 
    return b[i];
  }
}


/* Location:              C:\Program Files\BurpSuitePro\burpsuite_pro.jar!\burp\Zrnt.class
 * Java compiler version: 21 (65.0)
 * JD-Core Version:       1.1.3
 */