package burp;

import java.math.BigInteger;

class Zro2 extends ClassLoader {
  static Object Zu;
  
  static String ZF;
  
  private static final String[] a;
  
  private static final String[] b;
  
  static boolean ZY(Object[] paramArrayOfObject, Object paramObject) throws Throwable {
    // Byte code:
    //   0: invokestatic ZN : ()Z
    //   3: istore_2
    //   4: getstatic burp/Zxc.ZR : Ljava/lang/Object;
    //   7: checkcast java/math/BigInteger
    //   10: invokevirtual toByteArray : ()[B
    //   13: astore_3
    //   14: new java/lang/StringBuilder
    //   17: dup
    //   18: invokespecial <init> : ()V
    //   21: astore #5
    //   23: aload #5
    //   25: sipush #-7015
    //   28: sipush #-30622
    //   31: invokestatic a : (II)Ljava/lang/String;
    //   34: invokevirtual append : (Ljava/lang/String;)Ljava/lang/StringBuilder;
    //   37: pop
    //   38: aload_3
    //   39: astore #6
    //   41: aload #6
    //   43: arraylength
    //   44: istore #7
    //   46: iconst_0
    //   47: istore #8
    //   49: iload #8
    //   51: iload #7
    //   53: if_icmpge -> 79
    //   56: aload #6
    //   58: iload #8
    //   60: baload
    //   61: istore #9
    //   63: aload #5
    //   65: iload #9
    //   67: i2c
    //   68: invokevirtual append : (C)Ljava/lang/StringBuilder;
    //   71: pop
    //   72: iinc #8, 1
    //   75: iload_2
    //   76: ifne -> 49
    //   79: aload #5
    //   81: sipush #-7024
    //   84: sipush #-29667
    //   87: invokestatic a : (II)Ljava/lang/String;
    //   90: ldc ''
    //   92: invokestatic getProperty : (Ljava/lang/String;Ljava/lang/String;)Ljava/lang/String;
    //   95: invokevirtual toLowerCase : ()Ljava/lang/String;
    //   98: invokevirtual append : (Ljava/lang/String;)Ljava/lang/StringBuilder;
    //   101: pop
    //   102: aload #5
    //   104: sipush #-7020
    //   107: sipush #10072
    //   110: invokestatic a : (II)Ljava/lang/String;
    //   113: ldc ''
    //   115: invokestatic getProperty : (Ljava/lang/String;Ljava/lang/String;)Ljava/lang/String;
    //   118: invokevirtual toLowerCase : ()Ljava/lang/String;
    //   121: invokevirtual append : (Ljava/lang/String;)Ljava/lang/StringBuilder;
    //   124: pop
    //   125: aload #5
    //   127: invokevirtual toString : ()Ljava/lang/String;
    //   130: invokevirtual getBytes : ()[B
    //   133: astore #4
    //   135: aload #4
    //   137: astore_3
    //   138: aload_3
    //   139: arraylength
    //   140: bipush #8
    //   142: iadd
    //   143: bipush #6
    //   145: ishr
    //   146: iconst_1
    //   147: iadd
    //   148: bipush #16
    //   150: imul
    //   151: newarray int
    //   153: astore #5
    //   155: iconst_0
    //   156: istore #6
    //   158: iload #6
    //   160: aload_3
    //   161: arraylength
    //   162: if_icmpge -> 205
    //   165: aload_3
    //   166: iload #6
    //   168: baload
    //   169: sipush #255
    //   172: iand
    //   173: istore #7
    //   175: aload #5
    //   177: iload #6
    //   179: iconst_2
    //   180: ishr
    //   181: dup2
    //   182: iaload
    //   183: iload #7
    //   185: bipush #24
    //   187: iload #6
    //   189: iconst_4
    //   190: irem
    //   191: bipush #8
    //   193: imul
    //   194: isub
    //   195: ishl
    //   196: ior
    //   197: iastore
    //   198: iinc #6, 1
    //   201: iload_2
    //   202: ifne -> 158
    //   205: aload #5
    //   207: iload #6
    //   209: iconst_2
    //   210: ishr
    //   211: dup2
    //   212: iaload
    //   213: sipush #128
    //   216: bipush #24
    //   218: iload #6
    //   220: iconst_4
    //   221: irem
    //   222: bipush #8
    //   224: imul
    //   225: isub
    //   226: ishl
    //   227: ior
    //   228: iastore
    //   229: aload #5
    //   231: aload #5
    //   233: arraylength
    //   234: iconst_1
    //   235: isub
    //   236: aload_3
    //   237: arraylength
    //   238: bipush #8
    //   240: imul
    //   241: iastore
    //   242: bipush #80
    //   244: newarray int
    //   246: astore #7
    //   248: ldc 1732584193
    //   250: istore #8
    //   252: ldc -271733879
    //   254: istore #9
    //   256: ldc -1732584194
    //   258: istore #10
    //   260: ldc 271733878
    //   262: istore #11
    //   264: ldc -1009589776
    //   266: istore #12
    //   268: iconst_0
    //   269: istore #6
    //   271: iload #6
    //   273: aload #5
    //   275: arraylength
    //   276: if_icmpge -> 598
    //   279: iload #8
    //   281: istore #13
    //   283: iload #9
    //   285: istore #14
    //   287: iload #10
    //   289: istore #15
    //   291: iload #11
    //   293: istore #16
    //   295: iload #12
    //   297: istore #17
    //   299: iconst_0
    //   300: istore #18
    //   302: iload #18
    //   304: bipush #80
    //   306: if_icmpge -> 556
    //   309: iload #18
    //   311: bipush #16
    //   313: if_icmpge -> 340
    //   316: aload #7
    //   318: iload #18
    //   320: aload #5
    //   322: iload #6
    //   324: iload #18
    //   326: iadd
    //   327: iaload
    //   328: iastore
    //   329: iload_2
    //   330: ifne -> 395
    //   333: goto -> 340
    //   336: invokestatic a : (Ljava/lang/Throwable;)Ljava/lang/Throwable;
    //   339: athrow
    //   340: aload #7
    //   342: iload #18
    //   344: iconst_3
    //   345: isub
    //   346: iaload
    //   347: aload #7
    //   349: iload #18
    //   351: bipush #8
    //   353: isub
    //   354: iaload
    //   355: ixor
    //   356: aload #7
    //   358: iload #18
    //   360: bipush #14
    //   362: isub
    //   363: iaload
    //   364: ixor
    //   365: aload #7
    //   367: iload #18
    //   369: bipush #16
    //   371: isub
    //   372: iaload
    //   373: ixor
    //   374: istore #19
    //   376: iload #19
    //   378: iconst_1
    //   379: ishl
    //   380: iload #19
    //   382: bipush #31
    //   384: iushr
    //   385: ior
    //   386: istore #20
    //   388: aload #7
    //   390: iload #18
    //   392: iload #20
    //   394: iastore
    //   395: iload #8
    //   397: iconst_5
    //   398: ishl
    //   399: iload #8
    //   401: bipush #27
    //   403: iushr
    //   404: ior
    //   405: istore #19
    //   407: iload #19
    //   409: iload #12
    //   411: iadd
    //   412: aload #7
    //   414: iload #18
    //   416: iaload
    //   417: iadd
    //   418: iload #18
    //   420: bipush #20
    //   422: if_icmpge -> 448
    //   425: ldc 1518500249
    //   427: iload #9
    //   429: iload #10
    //   431: iand
    //   432: iload #9
    //   434: iconst_m1
    //   435: ixor
    //   436: iload #11
    //   438: iand
    //   439: ior
    //   440: iadd
    //   441: goto -> 518
    //   444: invokestatic a : (Ljava/lang/Throwable;)Ljava/lang/Throwable;
    //   447: athrow
    //   448: iload #18
    //   450: bipush #40
    //   452: if_icmpge -> 473
    //   455: ldc 1859775393
    //   457: iload #9
    //   459: iload #10
    //   461: ixor
    //   462: iload #11
    //   464: ixor
    //   465: iadd
    //   466: goto -> 518
    //   469: invokestatic a : (Ljava/lang/Throwable;)Ljava/lang/Throwable;
    //   472: athrow
    //   473: iload #18
    //   475: bipush #60
    //   477: if_icmpge -> 507
    //   480: ldc -1894007588
    //   482: iload #9
    //   484: iload #10
    //   486: iand
    //   487: iload #9
    //   489: iload #11
    //   491: iand
    //   492: ior
    //   493: iload #10
    //   495: iload #11
    //   497: iand
    //   498: ior
    //   499: iadd
    //   500: goto -> 518
    //   503: invokestatic a : (Ljava/lang/Throwable;)Ljava/lang/Throwable;
    //   506: athrow
    //   507: ldc -899497514
    //   509: iload #9
    //   511: iload #10
    //   513: ixor
    //   514: iload #11
    //   516: ixor
    //   517: iadd
    //   518: iadd
    //   519: istore #20
    //   521: iload #11
    //   523: istore #12
    //   525: iload #10
    //   527: istore #11
    //   529: iload #9
    //   531: bipush #30
    //   533: ishl
    //   534: iload #9
    //   536: iconst_2
    //   537: iushr
    //   538: ior
    //   539: istore #10
    //   541: iload #8
    //   543: istore #9
    //   545: iload #20
    //   547: istore #8
    //   549: iinc #18, 1
    //   552: iload_2
    //   553: ifne -> 302
    //   556: iload #8
    //   558: iload #13
    //   560: iadd
    //   561: istore #8
    //   563: iload #9
    //   565: iload #14
    //   567: iadd
    //   568: istore #9
    //   570: iload #10
    //   572: iload #15
    //   574: iadd
    //   575: istore #10
    //   577: iload #11
    //   579: iload #16
    //   581: iadd
    //   582: istore #11
    //   584: iload #12
    //   586: iload #17
    //   588: iadd
    //   589: istore #12
    //   591: iinc #6, 16
    //   594: iload_2
    //   595: ifne -> 271
    //   598: iconst_5
    //   599: newarray int
    //   601: dup
    //   602: iconst_0
    //   603: iload #8
    //   605: iastore
    //   606: dup
    //   607: iconst_1
    //   608: iload #9
    //   610: iastore
    //   611: dup
    //   612: iconst_2
    //   613: iload #10
    //   615: iastore
    //   616: dup
    //   617: iconst_3
    //   618: iload #11
    //   620: iastore
    //   621: dup
    //   622: iconst_4
    //   623: iload #12
    //   625: iastore
    //   626: astore #13
    //   628: bipush #20
    //   630: newarray byte
    //   632: astore #14
    //   634: iconst_0
    //   635: istore #15
    //   637: iload #15
    //   639: bipush #20
    //   641: if_icmpge -> 682
    //   644: aload #13
    //   646: iload #15
    //   648: iconst_4
    //   649: idiv
    //   650: iaload
    //   651: istore #16
    //   653: iconst_3
    //   654: iload #15
    //   656: iconst_4
    //   657: irem
    //   658: isub
    //   659: bipush #8
    //   661: imul
    //   662: istore #17
    //   664: aload #14
    //   666: iload #15
    //   668: iload #16
    //   670: iload #17
    //   672: iushr
    //   673: i2b
    //   674: bastore
    //   675: iinc #15, 1
    //   678: iload_2
    //   679: ifne -> 637
    //   682: aload #14
    //   684: astore #4
    //   686: ldc2_w 8682522807148012
    //   689: invokestatic currentTimeMillis : ()J
    //   692: lxor
    //   693: lstore #4
    //   695: lload #4
    //   697: ldc2_w 25214903917
    //   700: lmul
    //   701: ldc2_w 11
    //   704: ladd
    //   705: ldc2_w 281474976710655
    //   708: land
    //   709: lstore #4
    //   711: lload #4
    //   713: bipush #32
    //   715: lshl
    //   716: lstore #6
    //   718: lload #4
    //   720: ldc2_w 25214903917
    //   723: lmul
    //   724: ldc2_w 11
    //   727: ladd
    //   728: ldc2_w 281474976710655
    //   731: land
    //   732: lstore #4
    //   734: lload #6
    //   736: lload #4
    //   738: ladd
    //   739: lstore #6
    //   741: bipush #16
    //   743: newarray byte
    //   745: dup
    //   746: iconst_0
    //   747: bipush #48
    //   749: bastore
    //   750: dup
    //   751: iconst_1
    //   752: bipush #49
    //   754: bastore
    //   755: dup
    //   756: iconst_2
    //   757: bipush #50
    //   759: bastore
    //   760: dup
    //   761: iconst_3
    //   762: bipush #51
    //   764: bastore
    //   765: dup
    //   766: iconst_4
    //   767: bipush #52
    //   769: bastore
    //   770: dup
    //   771: iconst_5
    //   772: bipush #53
    //   774: bastore
    //   775: dup
    //   776: bipush #6
    //   778: bipush #54
    //   780: bastore
    //   781: dup
    //   782: bipush #7
    //   784: bipush #55
    //   786: bastore
    //   787: dup
    //   788: bipush #8
    //   790: bipush #56
    //   792: bastore
    //   793: dup
    //   794: bipush #9
    //   796: bipush #57
    //   798: bastore
    //   799: dup
    //   800: bipush #10
    //   802: bipush #97
    //   804: bastore
    //   805: dup
    //   806: bipush #11
    //   808: bipush #98
    //   810: bastore
    //   811: dup
    //   812: bipush #12
    //   814: bipush #99
    //   816: bastore
    //   817: dup
    //   818: bipush #13
    //   820: bipush #100
    //   822: bastore
    //   823: dup
    //   824: bipush #14
    //   826: bipush #101
    //   828: bastore
    //   829: dup
    //   830: bipush #15
    //   832: bipush #102
    //   834: bastore
    //   835: astore #8
    //   837: bipush #64
    //   839: newarray byte
    //   841: astore #9
    //   843: bipush #64
    //   845: istore #10
    //   847: bipush #16
    //   849: istore #11
    //   851: iload #11
    //   853: iconst_1
    //   854: isub
    //   855: i2l
    //   856: lstore #12
    //   858: aload #9
    //   860: iinc #10, -1
    //   863: iload #10
    //   865: aload #8
    //   867: lload #6
    //   869: lload #12
    //   871: land
    //   872: l2i
    //   873: baload
    //   874: bastore
    //   875: lload #6
    //   877: iconst_4
    //   878: lushr
    //   879: lstore #6
    //   881: lload #6
    //   883: lconst_0
    //   884: lcmp
    //   885: ifne -> 858
    //   888: bipush #64
    //   890: iload #10
    //   892: isub
    //   893: newarray byte
    //   895: astore_3
    //   896: iconst_0
    //   897: istore #14
    //   899: iload #14
    //   901: aload_3
    //   902: arraylength
    //   903: if_icmpge -> 925
    //   906: aload_3
    //   907: iload #14
    //   909: aload #9
    //   911: iload #10
    //   913: iload #14
    //   915: iadd
    //   916: baload
    //   917: bastore
    //   918: iinc #14, 1
    //   921: iload_2
    //   922: ifne -> 899
    //   925: aload_3
    //   926: arraylength
    //   927: bipush #10
    //   929: if_icmplt -> 695
    //   932: new java/lang/StringBuilder
    //   935: dup
    //   936: invokespecial <init> : ()V
    //   939: astore_3
    //   940: iconst_0
    //   941: istore #4
    //   943: iload #4
    //   945: bipush #32
    //   947: if_icmpge -> 2283
    //   950: iload #4
    //   952: tableswitch default -> 2276, 0 -> 1096, 1 -> 1133, 2 -> 1170, 3 -> 1207, 4 -> 1244, 5 -> 1281, 6 -> 1318, 7 -> 1355, 8 -> 1392, 9 -> 1429, 10 -> 1466, 11 -> 1503, 12 -> 1540, 13 -> 1577, 14 -> 1614, 15 -> 1651, 16 -> 1688, 17 -> 1725, 18 -> 1762, 19 -> 1799, 20 -> 1836, 21 -> 1873, 22 -> 1910, 23 -> 1947, 24 -> 1984, 25 -> 2021, 26 -> 2058, 27 -> 2095, 28 -> 2132, 29 -> 2169, 30 -> 2206, 31 -> 2243
    //   1096: aload_3
    //   1097: getstatic burp/Zb0s.Zi : Ljava/lang/String;
    //   1100: getstatic burp/Zlp8.Zu : Ljava/lang/Object;
    //   1103: checkcast java/math/BigInteger
    //   1106: invokevirtual intValue : ()I
    //   1109: bipush #32
    //   1111: irem
    //   1112: invokestatic abs : (I)I
    //   1115: invokevirtual charAt : (I)C
    //   1118: invokevirtual append : (C)Ljava/lang/StringBuilder;
    //   1121: pop
    //   1122: iload_2
    //   1123: ifne -> 2276
    //   1126: goto -> 1133
    //   1129: invokestatic a : (Ljava/lang/Throwable;)Ljava/lang/Throwable;
    //   1132: athrow
    //   1133: aload_3
    //   1134: getstatic burp/Zgp_.Zn : Ljava/lang/String;
    //   1137: getstatic burp/Zs26.Z_ : Ljava/lang/Object;
    //   1140: checkcast java/math/BigInteger
    //   1143: invokevirtual intValue : ()I
    //   1146: bipush #32
    //   1148: irem
    //   1149: invokestatic abs : (I)I
    //   1152: invokevirtual charAt : (I)C
    //   1155: invokevirtual append : (C)Ljava/lang/StringBuilder;
    //   1158: pop
    //   1159: iload_2
    //   1160: ifne -> 2276
    //   1163: goto -> 1170
    //   1166: invokestatic a : (Ljava/lang/Throwable;)Ljava/lang/Throwable;
    //   1169: athrow
    //   1170: aload_3
    //   1171: getstatic burp/Zzco.Zu : Ljava/lang/String;
    //   1174: getstatic burp/Zb38.ZC : Ljava/lang/Object;
    //   1177: checkcast java/math/BigInteger
    //   1180: invokevirtual intValue : ()I
    //   1183: bipush #32
    //   1185: irem
    //   1186: invokestatic abs : (I)I
    //   1189: invokevirtual charAt : (I)C
    //   1192: invokevirtual append : (C)Ljava/lang/StringBuilder;
    //   1195: pop
    //   1196: iload_2
    //   1197: ifne -> 2276
    //   1200: goto -> 1207
    //   1203: invokestatic a : (Ljava/lang/Throwable;)Ljava/lang/Throwable;
    //   1206: athrow
    //   1207: aload_3
    //   1208: getstatic burp/Zle6.Zh : Ljava/lang/String;
    //   1211: getstatic burp/Zlkm.ZQ : Ljava/lang/Object;
    //   1214: checkcast java/math/BigInteger
    //   1217: invokevirtual intValue : ()I
    //   1220: bipush #32
    //   1222: irem
    //   1223: invokestatic abs : (I)I
    //   1226: invokevirtual charAt : (I)C
    //   1229: invokevirtual append : (C)Ljava/lang/StringBuilder;
    //   1232: pop
    //   1233: iload_2
    //   1234: ifne -> 2276
    //   1237: goto -> 1244
    //   1240: invokestatic a : (Ljava/lang/Throwable;)Ljava/lang/Throwable;
    //   1243: athrow
    //   1244: aload_3
    //   1245: getstatic burp/Zkht.Zd : Ljava/lang/String;
    //   1248: getstatic burp/Zlp8.Zu : Ljava/lang/Object;
    //   1251: checkcast java/math/BigInteger
    //   1254: invokevirtual intValue : ()I
    //   1257: bipush #32
    //   1259: irem
    //   1260: invokestatic abs : (I)I
    //   1263: invokevirtual charAt : (I)C
    //   1266: invokevirtual append : (C)Ljava/lang/StringBuilder;
    //   1269: pop
    //   1270: iload_2
    //   1271: ifne -> 2276
    //   1274: goto -> 1281
    //   1277: invokestatic a : (Ljava/lang/Throwable;)Ljava/lang/Throwable;
    //   1280: athrow
    //   1281: aload_3
    //   1282: getstatic burp/Zlo4.Zn : Ljava/lang/String;
    //   1285: getstatic burp/Zlot.ZJ : Ljava/lang/Object;
    //   1288: checkcast java/math/BigInteger
    //   1291: invokevirtual intValue : ()I
    //   1294: bipush #32
    //   1296: irem
    //   1297: invokestatic abs : (I)I
    //   1300: invokevirtual charAt : (I)C
    //   1303: invokevirtual append : (C)Ljava/lang/StringBuilder;
    //   1306: pop
    //   1307: iload_2
    //   1308: ifne -> 2276
    //   1311: goto -> 1318
    //   1314: invokestatic a : (Ljava/lang/Throwable;)Ljava/lang/Throwable;
    //   1317: athrow
    //   1318: aload_3
    //   1319: getstatic burp/Zsow.Zh : Ljava/lang/String;
    //   1322: getstatic burp/Zgrf.ZN : Ljava/lang/Object;
    //   1325: checkcast java/math/BigInteger
    //   1328: invokevirtual intValue : ()I
    //   1331: bipush #32
    //   1333: irem
    //   1334: invokestatic abs : (I)I
    //   1337: invokevirtual charAt : (I)C
    //   1340: invokevirtual append : (C)Ljava/lang/StringBuilder;
    //   1343: pop
    //   1344: iload_2
    //   1345: ifne -> 2276
    //   1348: goto -> 1355
    //   1351: invokestatic a : (Ljava/lang/Throwable;)Ljava/lang/Throwable;
    //   1354: athrow
    //   1355: aload_3
    //   1356: getstatic burp/Zez0.Zp : Ljava/lang/String;
    //   1359: getstatic burp/Zkk2.Zq : Ljava/lang/Object;
    //   1362: checkcast java/math/BigInteger
    //   1365: invokevirtual intValue : ()I
    //   1368: bipush #32
    //   1370: irem
    //   1371: invokestatic abs : (I)I
    //   1374: invokevirtual charAt : (I)C
    //   1377: invokevirtual append : (C)Ljava/lang/StringBuilder;
    //   1380: pop
    //   1381: iload_2
    //   1382: ifne -> 2276
    //   1385: goto -> 1392
    //   1388: invokestatic a : (Ljava/lang/Throwable;)Ljava/lang/Throwable;
    //   1391: athrow
    //   1392: aload_3
    //   1393: getstatic burp/Zls0.ZI : Ljava/lang/String;
    //   1396: getstatic burp/Zb0s.Zv : Ljava/lang/Object;
    //   1399: checkcast java/math/BigInteger
    //   1402: invokevirtual intValue : ()I
    //   1405: bipush #32
    //   1407: irem
    //   1408: invokestatic abs : (I)I
    //   1411: invokevirtual charAt : (I)C
    //   1414: invokevirtual append : (C)Ljava/lang/StringBuilder;
    //   1417: pop
    //   1418: iload_2
    //   1419: ifne -> 2276
    //   1422: goto -> 1429
    //   1425: invokestatic a : (Ljava/lang/Throwable;)Ljava/lang/Throwable;
    //   1428: athrow
    //   1429: aload_3
    //   1430: getstatic burp/Zbz_.ZW : Ljava/lang/String;
    //   1433: getstatic burp/Zlp8.Zu : Ljava/lang/Object;
    //   1436: checkcast java/math/BigInteger
    //   1439: invokevirtual intValue : ()I
    //   1442: bipush #32
    //   1444: irem
    //   1445: invokestatic abs : (I)I
    //   1448: invokevirtual charAt : (I)C
    //   1451: invokevirtual append : (C)Ljava/lang/StringBuilder;
    //   1454: pop
    //   1455: iload_2
    //   1456: ifne -> 2276
    //   1459: goto -> 1466
    //   1462: invokestatic a : (Ljava/lang/Throwable;)Ljava/lang/Throwable;
    //   1465: athrow
    //   1466: aload_3
    //   1467: getstatic burp/Ztp.ZG : Ljava/lang/String;
    //   1470: getstatic burp/Ze57.ZR : Ljava/lang/Object;
    //   1473: checkcast java/math/BigInteger
    //   1476: invokevirtual intValue : ()I
    //   1479: bipush #32
    //   1481: irem
    //   1482: invokestatic abs : (I)I
    //   1485: invokevirtual charAt : (I)C
    //   1488: invokevirtual append : (C)Ljava/lang/StringBuilder;
    //   1491: pop
    //   1492: iload_2
    //   1493: ifne -> 2276
    //   1496: goto -> 1503
    //   1499: invokestatic a : (Ljava/lang/Throwable;)Ljava/lang/Throwable;
    //   1502: athrow
    //   1503: aload_3
    //   1504: getstatic burp/Zvos.Zk : Ljava/lang/String;
    //   1507: getstatic burp/Zzco.ZC : Ljava/lang/Object;
    //   1510: checkcast java/math/BigInteger
    //   1513: invokevirtual intValue : ()I
    //   1516: bipush #32
    //   1518: irem
    //   1519: invokestatic abs : (I)I
    //   1522: invokevirtual charAt : (I)C
    //   1525: invokevirtual append : (C)Ljava/lang/StringBuilder;
    //   1528: pop
    //   1529: iload_2
    //   1530: ifne -> 2276
    //   1533: goto -> 1540
    //   1536: invokestatic a : (Ljava/lang/Throwable;)Ljava/lang/Throwable;
    //   1539: athrow
    //   1540: aload_3
    //   1541: getstatic burp/Ze57.ZV : Ljava/lang/String;
    //   1544: getstatic burp/Zgjs.Za : Ljava/lang/Object;
    //   1547: checkcast java/math/BigInteger
    //   1550: invokevirtual intValue : ()I
    //   1553: bipush #32
    //   1555: irem
    //   1556: invokestatic abs : (I)I
    //   1559: invokevirtual charAt : (I)C
    //   1562: invokevirtual append : (C)Ljava/lang/StringBuilder;
    //   1565: pop
    //   1566: iload_2
    //   1567: ifne -> 2276
    //   1570: goto -> 1577
    //   1573: invokestatic a : (Ljava/lang/Throwable;)Ljava/lang/Throwable;
    //   1576: athrow
    //   1577: aload_3
    //   1578: getstatic burp/Zzco.Zu : Ljava/lang/String;
    //   1581: getstatic burp/Zgia.Zx : Ljava/lang/Object;
    //   1584: checkcast java/math/BigInteger
    //   1587: invokevirtual intValue : ()I
    //   1590: bipush #32
    //   1592: irem
    //   1593: invokestatic abs : (I)I
    //   1596: invokevirtual charAt : (I)C
    //   1599: invokevirtual append : (C)Ljava/lang/StringBuilder;
    //   1602: pop
    //   1603: iload_2
    //   1604: ifne -> 2276
    //   1607: goto -> 1614
    //   1610: invokestatic a : (Ljava/lang/Throwable;)Ljava/lang/Throwable;
    //   1613: athrow
    //   1614: aload_3
    //   1615: getstatic burp/Zxt5.ZM : Ljava/lang/String;
    //   1618: getstatic burp/Zb4m.Zp : Ljava/lang/Object;
    //   1621: checkcast java/math/BigInteger
    //   1624: invokevirtual intValue : ()I
    //   1627: bipush #32
    //   1629: irem
    //   1630: invokestatic abs : (I)I
    //   1633: invokevirtual charAt : (I)C
    //   1636: invokevirtual append : (C)Ljava/lang/StringBuilder;
    //   1639: pop
    //   1640: iload_2
    //   1641: ifne -> 2276
    //   1644: goto -> 1651
    //   1647: invokestatic a : (Ljava/lang/Throwable;)Ljava/lang/Throwable;
    //   1650: athrow
    //   1651: aload_3
    //   1652: getstatic burp/Zlot.ZD : Ljava/lang/String;
    //   1655: getstatic burp/Zgja.ZD : Ljava/lang/Object;
    //   1658: checkcast java/math/BigInteger
    //   1661: invokevirtual intValue : ()I
    //   1664: bipush #32
    //   1666: irem
    //   1667: invokestatic abs : (I)I
    //   1670: invokevirtual charAt : (I)C
    //   1673: invokevirtual append : (C)Ljava/lang/StringBuilder;
    //   1676: pop
    //   1677: iload_2
    //   1678: ifne -> 2276
    //   1681: goto -> 1688
    //   1684: invokestatic a : (Ljava/lang/Throwable;)Ljava/lang/Throwable;
    //   1687: athrow
    //   1688: aload_3
    //   1689: getstatic burp/Zs26.ZV : Ljava/lang/String;
    //   1692: getstatic burp/Zgjs.Za : Ljava/lang/Object;
    //   1695: checkcast java/math/BigInteger
    //   1698: invokevirtual intValue : ()I
    //   1701: bipush #32
    //   1703: irem
    //   1704: invokestatic abs : (I)I
    //   1707: invokevirtual charAt : (I)C
    //   1710: invokevirtual append : (C)Ljava/lang/StringBuilder;
    //   1713: pop
    //   1714: iload_2
    //   1715: ifne -> 2276
    //   1718: goto -> 1725
    //   1721: invokestatic a : (Ljava/lang/Throwable;)Ljava/lang/Throwable;
    //   1724: athrow
    //   1725: aload_3
    //   1726: getstatic burp/Zs26.ZV : Ljava/lang/String;
    //   1729: getstatic burp/Zgyc.ZT : Ljava/lang/Object;
    //   1732: checkcast java/math/BigInteger
    //   1735: invokevirtual intValue : ()I
    //   1738: bipush #32
    //   1740: irem
    //   1741: invokestatic abs : (I)I
    //   1744: invokevirtual charAt : (I)C
    //   1747: invokevirtual append : (C)Ljava/lang/StringBuilder;
    //   1750: pop
    //   1751: iload_2
    //   1752: ifne -> 2276
    //   1755: goto -> 1762
    //   1758: invokestatic a : (Ljava/lang/Throwable;)Ljava/lang/Throwable;
    //   1761: athrow
    //   1762: aload_3
    //   1763: getstatic burp/Zb0s.Zi : Ljava/lang/String;
    //   1766: getstatic burp/Zgly.ZN : Ljava/lang/Object;
    //   1769: checkcast java/math/BigInteger
    //   1772: invokevirtual intValue : ()I
    //   1775: bipush #32
    //   1777: irem
    //   1778: invokestatic abs : (I)I
    //   1781: invokevirtual charAt : (I)C
    //   1784: invokevirtual append : (C)Ljava/lang/StringBuilder;
    //   1787: pop
    //   1788: iload_2
    //   1789: ifne -> 2276
    //   1792: goto -> 1799
    //   1795: invokestatic a : (Ljava/lang/Throwable;)Ljava/lang/Throwable;
    //   1798: athrow
    //   1799: aload_3
    //   1800: getstatic burp/Ztzh.ZE : Ljava/lang/String;
    //   1803: getstatic burp/Zml.ZR : Ljava/lang/Object;
    //   1806: checkcast java/math/BigInteger
    //   1809: invokevirtual intValue : ()I
    //   1812: bipush #32
    //   1814: irem
    //   1815: invokestatic abs : (I)I
    //   1818: invokevirtual charAt : (I)C
    //   1821: invokevirtual append : (C)Ljava/lang/StringBuilder;
    //   1824: pop
    //   1825: iload_2
    //   1826: ifne -> 2276
    //   1829: goto -> 1836
    //   1832: invokestatic a : (Ljava/lang/Throwable;)Ljava/lang/Throwable;
    //   1835: athrow
    //   1836: aload_3
    //   1837: getstatic burp/Zzh1.Zn : Ljava/lang/String;
    //   1840: getstatic burp/Zsjo.ZB : Ljava/lang/Object;
    //   1843: checkcast java/math/BigInteger
    //   1846: invokevirtual intValue : ()I
    //   1849: bipush #32
    //   1851: irem
    //   1852: invokestatic abs : (I)I
    //   1855: invokevirtual charAt : (I)C
    //   1858: invokevirtual append : (C)Ljava/lang/StringBuilder;
    //   1861: pop
    //   1862: iload_2
    //   1863: ifne -> 2276
    //   1866: goto -> 1873
    //   1869: invokestatic a : (Ljava/lang/Throwable;)Ljava/lang/Throwable;
    //   1872: athrow
    //   1873: aload_3
    //   1874: getstatic burp/Zlbt.ZE : Ljava/lang/String;
    //   1877: getstatic burp/Zsow.ZV : Ljava/lang/Object;
    //   1880: checkcast java/math/BigInteger
    //   1883: invokevirtual intValue : ()I
    //   1886: bipush #32
    //   1888: irem
    //   1889: invokestatic abs : (I)I
    //   1892: invokevirtual charAt : (I)C
    //   1895: invokevirtual append : (C)Ljava/lang/StringBuilder;
    //   1898: pop
    //   1899: iload_2
    //   1900: ifne -> 2276
    //   1903: goto -> 1910
    //   1906: invokestatic a : (Ljava/lang/Throwable;)Ljava/lang/Throwable;
    //   1909: athrow
    //   1910: aload_3
    //   1911: getstatic burp/Zgja.Zb : Ljava/lang/String;
    //   1914: getstatic burp/Zl8i.ZY : Ljava/lang/Object;
    //   1917: checkcast java/math/BigInteger
    //   1920: invokevirtual intValue : ()I
    //   1923: bipush #32
    //   1925: irem
    //   1926: invokestatic abs : (I)I
    //   1929: invokevirtual charAt : (I)C
    //   1932: invokevirtual append : (C)Ljava/lang/StringBuilder;
    //   1935: pop
    //   1936: iload_2
    //   1937: ifne -> 2276
    //   1940: goto -> 1947
    //   1943: invokestatic a : (Ljava/lang/Throwable;)Ljava/lang/Throwable;
    //   1946: athrow
    //   1947: aload_3
    //   1948: getstatic burp/Zxf8.Zq : Ljava/lang/String;
    //   1951: getstatic burp/Ztv8.ZS : Ljava/lang/Object;
    //   1954: checkcast java/math/BigInteger
    //   1957: invokevirtual intValue : ()I
    //   1960: bipush #32
    //   1962: irem
    //   1963: invokestatic abs : (I)I
    //   1966: invokevirtual charAt : (I)C
    //   1969: invokevirtual append : (C)Ljava/lang/StringBuilder;
    //   1972: pop
    //   1973: iload_2
    //   1974: ifne -> 2276
    //   1977: goto -> 1984
    //   1980: invokestatic a : (Ljava/lang/Throwable;)Ljava/lang/Throwable;
    //   1983: athrow
    //   1984: aload_3
    //   1985: getstatic burp/Zbqk.ZZ : Ljava/lang/String;
    //   1988: getstatic burp/Ze4x.Zp : Ljava/lang/Object;
    //   1991: checkcast java/math/BigInteger
    //   1994: invokevirtual intValue : ()I
    //   1997: bipush #32
    //   1999: irem
    //   2000: invokestatic abs : (I)I
    //   2003: invokevirtual charAt : (I)C
    //   2006: invokevirtual append : (C)Ljava/lang/StringBuilder;
    //   2009: pop
    //   2010: iload_2
    //   2011: ifne -> 2276
    //   2014: goto -> 2021
    //   2017: invokestatic a : (Ljava/lang/Throwable;)Ljava/lang/Throwable;
    //   2020: athrow
    //   2021: aload_3
    //   2022: getstatic burp/Ze_0.Zi : Ljava/lang/String;
    //   2025: getstatic burp/Ztgj.ZY : Ljava/lang/Object;
    //   2028: checkcast java/math/BigInteger
    //   2031: invokevirtual intValue : ()I
    //   2034: bipush #32
    //   2036: irem
    //   2037: invokestatic abs : (I)I
    //   2040: invokevirtual charAt : (I)C
    //   2043: invokevirtual append : (C)Ljava/lang/StringBuilder;
    //   2046: pop
    //   2047: iload_2
    //   2048: ifne -> 2276
    //   2051: goto -> 2058
    //   2054: invokestatic a : (Ljava/lang/Throwable;)Ljava/lang/Throwable;
    //   2057: athrow
    //   2058: aload_3
    //   2059: getstatic burp/Zzmo.Zx : Ljava/lang/String;
    //   2062: getstatic burp/Zxc.ZR : Ljava/lang/Object;
    //   2065: checkcast java/math/BigInteger
    //   2068: invokevirtual intValue : ()I
    //   2071: bipush #32
    //   2073: irem
    //   2074: invokestatic abs : (I)I
    //   2077: invokevirtual charAt : (I)C
    //   2080: invokevirtual append : (C)Ljava/lang/StringBuilder;
    //   2083: pop
    //   2084: iload_2
    //   2085: ifne -> 2276
    //   2088: goto -> 2095
    //   2091: invokestatic a : (Ljava/lang/Throwable;)Ljava/lang/Throwable;
    //   2094: athrow
    //   2095: aload_3
    //   2096: getstatic burp/Zg8v.Zd : Ljava/lang/String;
    //   2099: getstatic burp/Zmze.Zo : Ljava/lang/Object;
    //   2102: checkcast java/math/BigInteger
    //   2105: invokevirtual intValue : ()I
    //   2108: bipush #32
    //   2110: irem
    //   2111: invokestatic abs : (I)I
    //   2114: invokevirtual charAt : (I)C
    //   2117: invokevirtual append : (C)Ljava/lang/StringBuilder;
    //   2120: pop
    //   2121: iload_2
    //   2122: ifne -> 2276
    //   2125: goto -> 2132
    //   2128: invokestatic a : (Ljava/lang/Throwable;)Ljava/lang/Throwable;
    //   2131: athrow
    //   2132: aload_3
    //   2133: getstatic burp/Zexn.ZE : Ljava/lang/String;
    //   2136: getstatic burp/Zxx4.Zo : Ljava/lang/Object;
    //   2139: checkcast java/math/BigInteger
    //   2142: invokevirtual intValue : ()I
    //   2145: bipush #32
    //   2147: irem
    //   2148: invokestatic abs : (I)I
    //   2151: invokevirtual charAt : (I)C
    //   2154: invokevirtual append : (C)Ljava/lang/StringBuilder;
    //   2157: pop
    //   2158: iload_2
    //   2159: ifne -> 2276
    //   2162: goto -> 2169
    //   2165: invokestatic a : (Ljava/lang/Throwable;)Ljava/lang/Throwable;
    //   2168: athrow
    //   2169: aload_3
    //   2170: getstatic burp/Zxo4.ZW : Ljava/lang/String;
    //   2173: getstatic burp/Ze_0.ZY : Ljava/lang/Object;
    //   2176: checkcast java/math/BigInteger
    //   2179: invokevirtual intValue : ()I
    //   2182: bipush #32
    //   2184: irem
    //   2185: invokestatic abs : (I)I
    //   2188: invokevirtual charAt : (I)C
    //   2191: invokevirtual append : (C)Ljava/lang/StringBuilder;
    //   2194: pop
    //   2195: iload_2
    //   2196: ifne -> 2276
    //   2199: goto -> 2206
    //   2202: invokestatic a : (Ljava/lang/Throwable;)Ljava/lang/Throwable;
    //   2205: athrow
    //   2206: aload_3
    //   2207: getstatic burp/Zlxs.ZM : Ljava/lang/String;
    //   2210: getstatic burp/Zt5b.Zc : Ljava/lang/Object;
    //   2213: checkcast java/math/BigInteger
    //   2216: invokevirtual intValue : ()I
    //   2219: bipush #32
    //   2221: irem
    //   2222: invokestatic abs : (I)I
    //   2225: invokevirtual charAt : (I)C
    //   2228: invokevirtual append : (C)Ljava/lang/StringBuilder;
    //   2231: pop
    //   2232: iload_2
    //   2233: ifne -> 2276
    //   2236: goto -> 2243
    //   2239: invokestatic a : (Ljava/lang/Throwable;)Ljava/lang/Throwable;
    //   2242: athrow
    //   2243: aload_3
    //   2244: getstatic burp/Zlot.ZD : Ljava/lang/String;
    //   2247: getstatic burp/Zzmo.ZI : Ljava/lang/Object;
    //   2250: checkcast java/math/BigInteger
    //   2253: invokevirtual intValue : ()I
    //   2256: bipush #32
    //   2258: irem
    //   2259: invokestatic abs : (I)I
    //   2262: invokevirtual charAt : (I)C
    //   2265: invokevirtual append : (C)Ljava/lang/StringBuilder;
    //   2268: pop
    //   2269: goto -> 2276
    //   2272: invokestatic a : (Ljava/lang/Throwable;)Ljava/lang/Throwable;
    //   2275: athrow
    //   2276: iinc #4, 1
    //   2279: iload_2
    //   2280: ifne -> 943
    //   2283: aload_3
    //   2284: invokevirtual toString : ()Ljava/lang/String;
    //   2287: putstatic burp/Zgp_.Zn : Ljava/lang/String;
    //   2290: sipush #-7018
    //   2293: sipush #28600
    //   2296: invokestatic a : (II)Ljava/lang/String;
    //   2299: iconst_1
    //   2300: ldc burp/Zsji
    //   2302: invokevirtual getClassLoader : ()Ljava/lang/ClassLoader;
    //   2305: invokestatic forName : (Ljava/lang/String;ZLjava/lang/ClassLoader;)Ljava/lang/Class;
    //   2308: invokevirtual getDeclaredFields : ()[Ljava/lang/reflect/Field;
    //   2311: astore #4
    //   2313: aload #4
    //   2315: arraylength
    //   2316: istore #5
    //   2318: iconst_0
    //   2319: istore #6
    //   2321: iload #6
    //   2323: iload #5
    //   2325: if_icmpge -> 2463
    //   2328: aload #4
    //   2330: iload #6
    //   2332: aaload
    //   2333: astore #7
    //   2335: aload #7
    //   2337: invokevirtual getModifiers : ()I
    //   2340: invokestatic isStatic : (I)Z
    //   2343: ifne -> 2353
    //   2346: goto -> 2456
    //   2349: invokestatic a : (Ljava/lang/Throwable;)Ljava/lang/Throwable;
    //   2352: athrow
    //   2353: aload #7
    //   2355: invokevirtual getType : ()Ljava/lang/Class;
    //   2358: astore #8
    //   2360: aload #8
    //   2362: ifnull -> 2443
    //   2365: aload #8
    //   2367: invokevirtual isPrimitive : ()Z
    //   2370: ifne -> 2443
    //   2373: goto -> 2380
    //   2376: invokestatic a : (Ljava/lang/Throwable;)Ljava/lang/Throwable;
    //   2379: athrow
    //   2380: aload #8
    //   2382: invokevirtual getPackage : ()Ljava/lang/Package;
    //   2385: ifnull -> 2443
    //   2388: goto -> 2395
    //   2391: invokestatic a : (Ljava/lang/Throwable;)Ljava/lang/Throwable;
    //   2394: athrow
    //   2395: aload #8
    //   2397: invokevirtual getPackage : ()Ljava/lang/Package;
    //   2400: invokevirtual getName : ()Ljava/lang/String;
    //   2403: ifnull -> 2443
    //   2406: goto -> 2413
    //   2409: invokestatic a : (Ljava/lang/Throwable;)Ljava/lang/Throwable;
    //   2412: athrow
    //   2413: aload #8
    //   2415: invokevirtual getPackage : ()Ljava/lang/Package;
    //   2418: invokevirtual getName : ()Ljava/lang/String;
    //   2421: sipush #-7040
    //   2424: sipush #20801
    //   2427: invokestatic a : (II)Ljava/lang/String;
    //   2430: invokevirtual startsWith : (Ljava/lang/String;)Z
    //   2433: ifne -> 2443
    //   2436: goto -> 2443
    //   2439: invokestatic a : (Ljava/lang/Throwable;)Ljava/lang/Throwable;
    //   2442: athrow
    //   2443: aload #7
    //   2445: iconst_1
    //   2446: invokevirtual setAccessible : (Z)V
    //   2449: aload #7
    //   2451: aconst_null
    //   2452: invokevirtual get : (Ljava/lang/Object;)Ljava/lang/Object;
    //   2455: pop
    //   2456: iinc #6, 1
    //   2459: iload_2
    //   2460: ifne -> 2321
    //   2463: sipush #-7009
    //   2466: sipush #-1415
    //   2469: invokestatic a : (II)Ljava/lang/String;
    //   2472: invokestatic forName : (Ljava/lang/String;)Ljava/lang/Class;
    //   2475: invokevirtual getDeclaredMethods : ()[Ljava/lang/reflect/Method;
    //   2478: astore #4
    //   2480: aload #4
    //   2482: arraylength
    //   2483: istore #5
    //   2485: iconst_0
    //   2486: istore #6
    //   2488: iload #6
    //   2490: iload #5
    //   2492: if_icmpge -> 2625
    //   2495: aload #4
    //   2497: iload #6
    //   2499: aaload
    //   2500: astore #7
    //   2502: aload #7
    //   2504: invokevirtual getParameterTypes : ()[Ljava/lang/Class;
    //   2507: pop
    //   2508: aload #7
    //   2510: invokevirtual getModifiers : ()I
    //   2513: invokestatic isStatic : (I)Z
    //   2516: ifeq -> 2611
    //   2519: aload #7
    //   2521: invokevirtual getParameterTypes : ()[Ljava/lang/Class;
    //   2524: arraylength
    //   2525: iconst_2
    //   2526: if_icmpne -> 2611
    //   2529: goto -> 2536
    //   2532: invokestatic a : (Ljava/lang/Throwable;)Ljava/lang/Throwable;
    //   2535: athrow
    //   2536: aload #7
    //   2538: invokevirtual getReturnType : ()Ljava/lang/Class;
    //   2541: getstatic java/lang/Void.TYPE : Ljava/lang/Class;
    //   2544: invokevirtual equals : (Ljava/lang/Object;)Z
    //   2547: ifeq -> 2611
    //   2550: goto -> 2557
    //   2553: invokestatic a : (Ljava/lang/Throwable;)Ljava/lang/Throwable;
    //   2556: athrow
    //   2557: aload #7
    //   2559: iconst_1
    //   2560: invokevirtual setAccessible : (Z)V
    //   2563: aload #7
    //   2565: aconst_null
    //   2566: iconst_2
    //   2567: anewarray java/lang/Object
    //   2570: dup
    //   2571: iconst_0
    //   2572: aload_0
    //   2573: aastore
    //   2574: dup
    //   2575: iconst_1
    //   2576: aload_1
    //   2577: ifnonnull -> 2595
    //   2580: goto -> 2587
    //   2583: invokestatic a : (Ljava/lang/Throwable;)Ljava/lang/Throwable;
    //   2586: athrow
    //   2587: aload_1
    //   2588: goto -> 2602
    //   2591: invokestatic a : (Ljava/lang/Throwable;)Ljava/lang/Throwable;
    //   2594: athrow
    //   2595: aload_1
    //   2596: checkcast [B
    //   2599: invokevirtual clone : ()Ljava/lang/Object;
    //   2602: aastore
    //   2603: invokevirtual invoke : (Ljava/lang/Object;[Ljava/lang/Object;)Ljava/lang/Object;
    //   2606: pop
    //   2607: iload_2
    //   2608: ifne -> 2625
    //   2611: iinc #6, 1
    //   2614: iload_2
    //   2615: ifne -> 2488
    //   2618: goto -> 2625
    //   2621: invokestatic a : (Ljava/lang/Throwable;)Ljava/lang/Throwable;
    //   2624: athrow
    //   2625: iconst_0
    //   2626: istore #4
    //   2628: getstatic burp/Zxzp.ZH : Ljava/lang/String;
    //   2631: getstatic burp/Zb6a.Zz : Ljava/lang/Object;
    //   2634: checkcast java/math/BigInteger
    //   2637: invokevirtual intValue : ()I
    //   2640: bipush #32
    //   2642: irem
    //   2643: invokestatic abs : (I)I
    //   2646: invokevirtual charAt : (I)C
    //   2649: getstatic burp/Zkq9.ZO : Ljava/lang/String;
    //   2652: getstatic burp/Zva.Zu : Ljava/lang/Object;
    //   2655: checkcast java/math/BigInteger
    //   2658: invokevirtual intValue : ()I
    //   2661: bipush #32
    //   2663: irem
    //   2664: invokestatic abs : (I)I
    //   2667: invokevirtual charAt : (I)C
    //   2670: if_icmpgt -> 3015
    //   2673: sipush #-7027
    //   2676: sipush #23717
    //   2679: invokestatic a : (II)Ljava/lang/String;
    //   2682: iconst_1
    //   2683: ldc burp/Zrpm
    //   2685: invokevirtual getClassLoader : ()Ljava/lang/ClassLoader;
    //   2688: invokestatic forName : (Ljava/lang/String;ZLjava/lang/ClassLoader;)Ljava/lang/Class;
    //   2691: invokevirtual getDeclaredFields : ()[Ljava/lang/reflect/Field;
    //   2694: astore #5
    //   2696: aload #5
    //   2698: arraylength
    //   2699: istore #6
    //   2701: iconst_0
    //   2702: istore #7
    //   2704: iload #7
    //   2706: iload #6
    //   2708: if_icmpge -> 2846
    //   2711: aload #5
    //   2713: iload #7
    //   2715: aaload
    //   2716: astore #8
    //   2718: aload #8
    //   2720: invokevirtual getModifiers : ()I
    //   2723: invokestatic isStatic : (I)Z
    //   2726: ifne -> 2736
    //   2729: goto -> 2839
    //   2732: invokestatic a : (Ljava/lang/Throwable;)Ljava/lang/Throwable;
    //   2735: athrow
    //   2736: aload #8
    //   2738: invokevirtual getType : ()Ljava/lang/Class;
    //   2741: astore #9
    //   2743: aload #9
    //   2745: ifnull -> 2826
    //   2748: aload #9
    //   2750: invokevirtual isPrimitive : ()Z
    //   2753: ifne -> 2826
    //   2756: goto -> 2763
    //   2759: invokestatic a : (Ljava/lang/Throwable;)Ljava/lang/Throwable;
    //   2762: athrow
    //   2763: aload #9
    //   2765: invokevirtual getPackage : ()Ljava/lang/Package;
    //   2768: ifnull -> 2826
    //   2771: goto -> 2778
    //   2774: invokestatic a : (Ljava/lang/Throwable;)Ljava/lang/Throwable;
    //   2777: athrow
    //   2778: aload #9
    //   2780: invokevirtual getPackage : ()Ljava/lang/Package;
    //   2783: invokevirtual getName : ()Ljava/lang/String;
    //   2786: ifnull -> 2826
    //   2789: goto -> 2796
    //   2792: invokestatic a : (Ljava/lang/Throwable;)Ljava/lang/Throwable;
    //   2795: athrow
    //   2796: aload #9
    //   2798: invokevirtual getPackage : ()Ljava/lang/Package;
    //   2801: invokevirtual getName : ()Ljava/lang/String;
    //   2804: sipush #-7025
    //   2807: sipush #2271
    //   2810: invokestatic a : (II)Ljava/lang/String;
    //   2813: invokevirtual startsWith : (Ljava/lang/String;)Z
    //   2816: ifne -> 2826
    //   2819: goto -> 2826
    //   2822: invokestatic a : (Ljava/lang/Throwable;)Ljava/lang/Throwable;
    //   2825: athrow
    //   2826: aload #8
    //   2828: iconst_1
    //   2829: invokevirtual setAccessible : (Z)V
    //   2832: aload #8
    //   2834: aconst_null
    //   2835: invokevirtual get : (Ljava/lang/Object;)Ljava/lang/Object;
    //   2838: pop
    //   2839: iinc #7, 1
    //   2842: iload_2
    //   2843: ifne -> 2704
    //   2846: sipush #-7028
    //   2849: sipush #-4676
    //   2852: invokestatic a : (II)Ljava/lang/String;
    //   2855: invokestatic forName : (Ljava/lang/String;)Ljava/lang/Class;
    //   2858: invokevirtual getDeclaredMethods : ()[Ljava/lang/reflect/Method;
    //   2861: astore #5
    //   2863: aload #5
    //   2865: arraylength
    //   2866: istore #6
    //   2868: iconst_0
    //   2869: istore #7
    //   2871: iload #7
    //   2873: iload #6
    //   2875: if_icmpge -> 3012
    //   2878: aload #5
    //   2880: iload #7
    //   2882: aaload
    //   2883: astore #8
    //   2885: aload #8
    //   2887: invokevirtual getParameterTypes : ()[Ljava/lang/Class;
    //   2890: pop
    //   2891: aload #8
    //   2893: invokevirtual getModifiers : ()I
    //   2896: invokestatic isStatic : (I)Z
    //   2899: ifeq -> 2998
    //   2902: aload #8
    //   2904: invokevirtual getParameterTypes : ()[Ljava/lang/Class;
    //   2907: arraylength
    //   2908: iconst_2
    //   2909: if_icmpne -> 2998
    //   2912: goto -> 2919
    //   2915: invokestatic a : (Ljava/lang/Throwable;)Ljava/lang/Throwable;
    //   2918: athrow
    //   2919: aload #8
    //   2921: invokevirtual getReturnType : ()Ljava/lang/Class;
    //   2924: getstatic java/lang/Boolean.TYPE : Ljava/lang/Class;
    //   2927: if_acmpne -> 2998
    //   2930: goto -> 2937
    //   2933: invokestatic a : (Ljava/lang/Throwable;)Ljava/lang/Throwable;
    //   2936: athrow
    //   2937: aload #8
    //   2939: iconst_1
    //   2940: invokevirtual setAccessible : (Z)V
    //   2943: aload #8
    //   2945: aconst_null
    //   2946: iconst_2
    //   2947: anewarray java/lang/Object
    //   2950: dup
    //   2951: iconst_0
    //   2952: aload_0
    //   2953: aastore
    //   2954: dup
    //   2955: iconst_1
    //   2956: aload_1
    //   2957: ifnonnull -> 2975
    //   2960: goto -> 2967
    //   2963: invokestatic a : (Ljava/lang/Throwable;)Ljava/lang/Throwable;
    //   2966: athrow
    //   2967: aload_1
    //   2968: goto -> 2982
    //   2971: invokestatic a : (Ljava/lang/Throwable;)Ljava/lang/Throwable;
    //   2974: athrow
    //   2975: aload_1
    //   2976: checkcast [B
    //   2979: invokevirtual clone : ()Ljava/lang/Object;
    //   2982: aastore
    //   2983: invokevirtual invoke : (Ljava/lang/Object;[Ljava/lang/Object;)Ljava/lang/Object;
    //   2986: checkcast java/lang/Boolean
    //   2989: invokevirtual booleanValue : ()Z
    //   2992: istore #4
    //   2994: iload_2
    //   2995: ifne -> 3012
    //   2998: iinc #7, 1
    //   3001: iload_2
    //   3002: ifne -> 2871
    //   3005: goto -> 3012
    //   3008: invokestatic a : (Ljava/lang/Throwable;)Ljava/lang/Throwable;
    //   3011: athrow
    //   3012: goto -> 3354
    //   3015: sipush #-7038
    //   3018: sipush #21261
    //   3021: invokestatic a : (II)Ljava/lang/String;
    //   3024: iconst_1
    //   3025: ldc burp/Zgjj
    //   3027: invokevirtual getClassLoader : ()Ljava/lang/ClassLoader;
    //   3030: invokestatic forName : (Ljava/lang/String;ZLjava/lang/ClassLoader;)Ljava/lang/Class;
    //   3033: invokevirtual getDeclaredFields : ()[Ljava/lang/reflect/Field;
    //   3036: astore #5
    //   3038: aload #5
    //   3040: arraylength
    //   3041: istore #6
    //   3043: iconst_0
    //   3044: istore #7
    //   3046: iload #7
    //   3048: iload #6
    //   3050: if_icmpge -> 3188
    //   3053: aload #5
    //   3055: iload #7
    //   3057: aaload
    //   3058: astore #8
    //   3060: aload #8
    //   3062: invokevirtual getModifiers : ()I
    //   3065: invokestatic isStatic : (I)Z
    //   3068: ifne -> 3078
    //   3071: goto -> 3181
    //   3074: invokestatic a : (Ljava/lang/Throwable;)Ljava/lang/Throwable;
    //   3077: athrow
    //   3078: aload #8
    //   3080: invokevirtual getType : ()Ljava/lang/Class;
    //   3083: astore #9
    //   3085: aload #9
    //   3087: ifnull -> 3168
    //   3090: aload #9
    //   3092: invokevirtual isPrimitive : ()Z
    //   3095: ifne -> 3168
    //   3098: goto -> 3105
    //   3101: invokestatic a : (Ljava/lang/Throwable;)Ljava/lang/Throwable;
    //   3104: athrow
    //   3105: aload #9
    //   3107: invokevirtual getPackage : ()Ljava/lang/Package;
    //   3110: ifnull -> 3168
    //   3113: goto -> 3120
    //   3116: invokestatic a : (Ljava/lang/Throwable;)Ljava/lang/Throwable;
    //   3119: athrow
    //   3120: aload #9
    //   3122: invokevirtual getPackage : ()Ljava/lang/Package;
    //   3125: invokevirtual getName : ()Ljava/lang/String;
    //   3128: ifnull -> 3168
    //   3131: goto -> 3138
    //   3134: invokestatic a : (Ljava/lang/Throwable;)Ljava/lang/Throwable;
    //   3137: athrow
    //   3138: aload #9
    //   3140: invokevirtual getPackage : ()Ljava/lang/Package;
    //   3143: invokevirtual getName : ()Ljava/lang/String;
    //   3146: sipush #-7025
    //   3149: sipush #2271
    //   3152: invokestatic a : (II)Ljava/lang/String;
    //   3155: invokevirtual startsWith : (Ljava/lang/String;)Z
    //   3158: ifne -> 3168
    //   3161: goto -> 3168
    //   3164: invokestatic a : (Ljava/lang/Throwable;)Ljava/lang/Throwable;
    //   3167: athrow
    //   3168: aload #8
    //   3170: iconst_1
    //   3171: invokevirtual setAccessible : (Z)V
    //   3174: aload #8
    //   3176: aconst_null
    //   3177: invokevirtual get : (Ljava/lang/Object;)Ljava/lang/Object;
    //   3180: pop
    //   3181: iinc #7, 1
    //   3184: iload_2
    //   3185: ifne -> 3046
    //   3188: sipush #-7036
    //   3191: sipush #-28104
    //   3194: invokestatic a : (II)Ljava/lang/String;
    //   3197: invokestatic forName : (Ljava/lang/String;)Ljava/lang/Class;
    //   3200: invokevirtual getDeclaredMethods : ()[Ljava/lang/reflect/Method;
    //   3203: astore #5
    //   3205: aload #5
    //   3207: arraylength
    //   3208: istore #6
    //   3210: iconst_0
    //   3211: istore #7
    //   3213: iload #7
    //   3215: iload #6
    //   3217: if_icmpge -> 3354
    //   3220: aload #5
    //   3222: iload #7
    //   3224: aaload
    //   3225: astore #8
    //   3227: aload #8
    //   3229: invokevirtual getParameterTypes : ()[Ljava/lang/Class;
    //   3232: pop
    //   3233: aload #8
    //   3235: invokevirtual getModifiers : ()I
    //   3238: invokestatic isStatic : (I)Z
    //   3241: ifeq -> 3340
    //   3244: aload #8
    //   3246: invokevirtual getParameterTypes : ()[Ljava/lang/Class;
    //   3249: arraylength
    //   3250: iconst_2
    //   3251: if_icmpne -> 3340
    //   3254: goto -> 3261
    //   3257: invokestatic a : (Ljava/lang/Throwable;)Ljava/lang/Throwable;
    //   3260: athrow
    //   3261: aload #8
    //   3263: invokevirtual getReturnType : ()Ljava/lang/Class;
    //   3266: getstatic java/lang/Boolean.TYPE : Ljava/lang/Class;
    //   3269: if_acmpne -> 3340
    //   3272: goto -> 3279
    //   3275: invokestatic a : (Ljava/lang/Throwable;)Ljava/lang/Throwable;
    //   3278: athrow
    //   3279: aload #8
    //   3281: iconst_1
    //   3282: invokevirtual setAccessible : (Z)V
    //   3285: aload #8
    //   3287: aconst_null
    //   3288: iconst_2
    //   3289: anewarray java/lang/Object
    //   3292: dup
    //   3293: iconst_0
    //   3294: aload_0
    //   3295: aastore
    //   3296: dup
    //   3297: iconst_1
    //   3298: aload_1
    //   3299: ifnonnull -> 3317
    //   3302: goto -> 3309
    //   3305: invokestatic a : (Ljava/lang/Throwable;)Ljava/lang/Throwable;
    //   3308: athrow
    //   3309: aload_1
    //   3310: goto -> 3324
    //   3313: invokestatic a : (Ljava/lang/Throwable;)Ljava/lang/Throwable;
    //   3316: athrow
    //   3317: aload_1
    //   3318: checkcast [B
    //   3321: invokevirtual clone : ()Ljava/lang/Object;
    //   3324: aastore
    //   3325: invokevirtual invoke : (Ljava/lang/Object;[Ljava/lang/Object;)Ljava/lang/Object;
    //   3328: checkcast java/lang/Boolean
    //   3331: invokevirtual booleanValue : ()Z
    //   3334: istore #4
    //   3336: iload_2
    //   3337: ifne -> 3354
    //   3340: iinc #7, 1
    //   3343: iload_2
    //   3344: ifne -> 3213
    //   3347: goto -> 3354
    //   3350: invokestatic a : (Ljava/lang/Throwable;)Ljava/lang/Throwable;
    //   3353: athrow
    //   3354: iload #4
    //   3356: ifeq -> 3362
    //   3359: iload #4
    //   3361: ireturn
    //   3362: getstatic burp/Zkk2.ZI : Ljava/lang/String;
    //   3365: getstatic burp/Zb2p.ZQ : Ljava/lang/Object;
    //   3368: checkcast java/math/BigInteger
    //   3371: invokevirtual intValue : ()I
    //   3374: bipush #32
    //   3376: irem
    //   3377: invokestatic abs : (I)I
    //   3380: invokevirtual charAt : (I)C
    //   3383: getstatic burp/Zro2.ZF : Ljava/lang/String;
    //   3386: getstatic burp/Zxo4.ZV : Ljava/lang/Object;
    //   3389: checkcast java/math/BigInteger
    //   3392: invokevirtual intValue : ()I
    //   3395: bipush #32
    //   3397: irem
    //   3398: invokestatic abs : (I)I
    //   3401: invokevirtual charAt : (I)C
    //   3404: if_icmple -> 3749
    //   3407: sipush #-7021
    //   3410: sipush #1369
    //   3413: invokestatic a : (II)Ljava/lang/String;
    //   3416: iconst_1
    //   3417: ldc burp/Zxf8
    //   3419: invokevirtual getClassLoader : ()Ljava/lang/ClassLoader;
    //   3422: invokestatic forName : (Ljava/lang/String;ZLjava/lang/ClassLoader;)Ljava/lang/Class;
    //   3425: invokevirtual getDeclaredFields : ()[Ljava/lang/reflect/Field;
    //   3428: astore #5
    //   3430: aload #5
    //   3432: arraylength
    //   3433: istore #6
    //   3435: iconst_0
    //   3436: istore #7
    //   3438: iload #7
    //   3440: iload #6
    //   3442: if_icmpge -> 3580
    //   3445: aload #5
    //   3447: iload #7
    //   3449: aaload
    //   3450: astore #8
    //   3452: aload #8
    //   3454: invokevirtual getModifiers : ()I
    //   3457: invokestatic isStatic : (I)Z
    //   3460: ifne -> 3470
    //   3463: goto -> 3573
    //   3466: invokestatic a : (Ljava/lang/Throwable;)Ljava/lang/Throwable;
    //   3469: athrow
    //   3470: aload #8
    //   3472: invokevirtual getType : ()Ljava/lang/Class;
    //   3475: astore #9
    //   3477: aload #9
    //   3479: ifnull -> 3560
    //   3482: aload #9
    //   3484: invokevirtual isPrimitive : ()Z
    //   3487: ifne -> 3560
    //   3490: goto -> 3497
    //   3493: invokestatic a : (Ljava/lang/Throwable;)Ljava/lang/Throwable;
    //   3496: athrow
    //   3497: aload #9
    //   3499: invokevirtual getPackage : ()Ljava/lang/Package;
    //   3502: ifnull -> 3560
    //   3505: goto -> 3512
    //   3508: invokestatic a : (Ljava/lang/Throwable;)Ljava/lang/Throwable;
    //   3511: athrow
    //   3512: aload #9
    //   3514: invokevirtual getPackage : ()Ljava/lang/Package;
    //   3517: invokevirtual getName : ()Ljava/lang/String;
    //   3520: ifnull -> 3560
    //   3523: goto -> 3530
    //   3526: invokestatic a : (Ljava/lang/Throwable;)Ljava/lang/Throwable;
    //   3529: athrow
    //   3530: aload #9
    //   3532: invokevirtual getPackage : ()Ljava/lang/Package;
    //   3535: invokevirtual getName : ()Ljava/lang/String;
    //   3538: sipush #-7025
    //   3541: sipush #2271
    //   3544: invokestatic a : (II)Ljava/lang/String;
    //   3547: invokevirtual startsWith : (Ljava/lang/String;)Z
    //   3550: ifne -> 3560
    //   3553: goto -> 3560
    //   3556: invokestatic a : (Ljava/lang/Throwable;)Ljava/lang/Throwable;
    //   3559: athrow
    //   3560: aload #8
    //   3562: iconst_1
    //   3563: invokevirtual setAccessible : (Z)V
    //   3566: aload #8
    //   3568: aconst_null
    //   3569: invokevirtual get : (Ljava/lang/Object;)Ljava/lang/Object;
    //   3572: pop
    //   3573: iinc #7, 1
    //   3576: iload_2
    //   3577: ifne -> 3438
    //   3580: sipush #-7013
    //   3583: bipush #109
    //   3585: invokestatic a : (II)Ljava/lang/String;
    //   3588: invokestatic forName : (Ljava/lang/String;)Ljava/lang/Class;
    //   3591: invokevirtual getDeclaredMethods : ()[Ljava/lang/reflect/Method;
    //   3594: astore #5
    //   3596: aload #5
    //   3598: arraylength
    //   3599: istore #6
    //   3601: iconst_0
    //   3602: istore #7
    //   3604: iload #7
    //   3606: iload #6
    //   3608: if_icmpge -> 3745
    //   3611: aload #5
    //   3613: iload #7
    //   3615: aaload
    //   3616: astore #8
    //   3618: aload #8
    //   3620: invokevirtual getParameterTypes : ()[Ljava/lang/Class;
    //   3623: pop
    //   3624: aload #8
    //   3626: invokevirtual getModifiers : ()I
    //   3629: invokestatic isStatic : (I)Z
    //   3632: ifeq -> 3731
    //   3635: aload #8
    //   3637: invokevirtual getParameterTypes : ()[Ljava/lang/Class;
    //   3640: arraylength
    //   3641: iconst_2
    //   3642: if_icmpne -> 3731
    //   3645: goto -> 3652
    //   3648: invokestatic a : (Ljava/lang/Throwable;)Ljava/lang/Throwable;
    //   3651: athrow
    //   3652: aload #8
    //   3654: invokevirtual getReturnType : ()Ljava/lang/Class;
    //   3657: getstatic java/lang/Boolean.TYPE : Ljava/lang/Class;
    //   3660: if_acmpne -> 3731
    //   3663: goto -> 3670
    //   3666: invokestatic a : (Ljava/lang/Throwable;)Ljava/lang/Throwable;
    //   3669: athrow
    //   3670: aload #8
    //   3672: iconst_1
    //   3673: invokevirtual setAccessible : (Z)V
    //   3676: aload #8
    //   3678: aconst_null
    //   3679: iconst_2
    //   3680: anewarray java/lang/Object
    //   3683: dup
    //   3684: iconst_0
    //   3685: aload_0
    //   3686: aastore
    //   3687: dup
    //   3688: iconst_1
    //   3689: aload_1
    //   3690: ifnonnull -> 3708
    //   3693: goto -> 3700
    //   3696: invokestatic a : (Ljava/lang/Throwable;)Ljava/lang/Throwable;
    //   3699: athrow
    //   3700: aload_1
    //   3701: goto -> 3715
    //   3704: invokestatic a : (Ljava/lang/Throwable;)Ljava/lang/Throwable;
    //   3707: athrow
    //   3708: aload_1
    //   3709: checkcast [B
    //   3712: invokevirtual clone : ()Ljava/lang/Object;
    //   3715: aastore
    //   3716: invokevirtual invoke : (Ljava/lang/Object;[Ljava/lang/Object;)Ljava/lang/Object;
    //   3719: checkcast java/lang/Boolean
    //   3722: invokevirtual booleanValue : ()Z
    //   3725: istore #4
    //   3727: iload_2
    //   3728: ifne -> 3745
    //   3731: iinc #7, 1
    //   3734: iload_2
    //   3735: ifne -> 3604
    //   3738: goto -> 3745
    //   3741: invokestatic a : (Ljava/lang/Throwable;)Ljava/lang/Throwable;
    //   3744: athrow
    //   3745: iload_2
    //   3746: ifne -> 4088
    //   3749: sipush #-7016
    //   3752: sipush #19085
    //   3755: invokestatic a : (II)Ljava/lang/String;
    //   3758: iconst_1
    //   3759: ldc burp/Zeh9
    //   3761: invokevirtual getClassLoader : ()Ljava/lang/ClassLoader;
    //   3764: invokestatic forName : (Ljava/lang/String;ZLjava/lang/ClassLoader;)Ljava/lang/Class;
    //   3767: invokevirtual getDeclaredFields : ()[Ljava/lang/reflect/Field;
    //   3770: astore #5
    //   3772: aload #5
    //   3774: arraylength
    //   3775: istore #6
    //   3777: iconst_0
    //   3778: istore #7
    //   3780: iload #7
    //   3782: iload #6
    //   3784: if_icmpge -> 3922
    //   3787: aload #5
    //   3789: iload #7
    //   3791: aaload
    //   3792: astore #8
    //   3794: aload #8
    //   3796: invokevirtual getModifiers : ()I
    //   3799: invokestatic isStatic : (I)Z
    //   3802: ifne -> 3812
    //   3805: goto -> 3915
    //   3808: invokestatic a : (Ljava/lang/Throwable;)Ljava/lang/Throwable;
    //   3811: athrow
    //   3812: aload #8
    //   3814: invokevirtual getType : ()Ljava/lang/Class;
    //   3817: astore #9
    //   3819: aload #9
    //   3821: ifnull -> 3902
    //   3824: aload #9
    //   3826: invokevirtual isPrimitive : ()Z
    //   3829: ifne -> 3902
    //   3832: goto -> 3839
    //   3835: invokestatic a : (Ljava/lang/Throwable;)Ljava/lang/Throwable;
    //   3838: athrow
    //   3839: aload #9
    //   3841: invokevirtual getPackage : ()Ljava/lang/Package;
    //   3844: ifnull -> 3902
    //   3847: goto -> 3854
    //   3850: invokestatic a : (Ljava/lang/Throwable;)Ljava/lang/Throwable;
    //   3853: athrow
    //   3854: aload #9
    //   3856: invokevirtual getPackage : ()Ljava/lang/Package;
    //   3859: invokevirtual getName : ()Ljava/lang/String;
    //   3862: ifnull -> 3902
    //   3865: goto -> 3872
    //   3868: invokestatic a : (Ljava/lang/Throwable;)Ljava/lang/Throwable;
    //   3871: athrow
    //   3872: aload #9
    //   3874: invokevirtual getPackage : ()Ljava/lang/Package;
    //   3877: invokevirtual getName : ()Ljava/lang/String;
    //   3880: sipush #-7025
    //   3883: sipush #2271
    //   3886: invokestatic a : (II)Ljava/lang/String;
    //   3889: invokevirtual startsWith : (Ljava/lang/String;)Z
    //   3892: ifne -> 3902
    //   3895: goto -> 3902
    //   3898: invokestatic a : (Ljava/lang/Throwable;)Ljava/lang/Throwable;
    //   3901: athrow
    //   3902: aload #8
    //   3904: iconst_1
    //   3905: invokevirtual setAccessible : (Z)V
    //   3908: aload #8
    //   3910: aconst_null
    //   3911: invokevirtual get : (Ljava/lang/Object;)Ljava/lang/Object;
    //   3914: pop
    //   3915: iinc #7, 1
    //   3918: iload_2
    //   3919: ifne -> 3780
    //   3922: sipush #-7029
    //   3925: sipush #-24521
    //   3928: invokestatic a : (II)Ljava/lang/String;
    //   3931: invokestatic forName : (Ljava/lang/String;)Ljava/lang/Class;
    //   3934: invokevirtual getDeclaredMethods : ()[Ljava/lang/reflect/Method;
    //   3937: astore #5
    //   3939: aload #5
    //   3941: arraylength
    //   3942: istore #6
    //   3944: iconst_0
    //   3945: istore #7
    //   3947: iload #7
    //   3949: iload #6
    //   3951: if_icmpge -> 4088
    //   3954: aload #5
    //   3956: iload #7
    //   3958: aaload
    //   3959: astore #8
    //   3961: aload #8
    //   3963: invokevirtual getParameterTypes : ()[Ljava/lang/Class;
    //   3966: pop
    //   3967: aload #8
    //   3969: invokevirtual getModifiers : ()I
    //   3972: invokestatic isStatic : (I)Z
    //   3975: ifeq -> 4074
    //   3978: aload #8
    //   3980: invokevirtual getParameterTypes : ()[Ljava/lang/Class;
    //   3983: arraylength
    //   3984: iconst_2
    //   3985: if_icmpne -> 4074
    //   3988: goto -> 3995
    //   3991: invokestatic a : (Ljava/lang/Throwable;)Ljava/lang/Throwable;
    //   3994: athrow
    //   3995: aload #8
    //   3997: invokevirtual getReturnType : ()Ljava/lang/Class;
    //   4000: getstatic java/lang/Boolean.TYPE : Ljava/lang/Class;
    //   4003: if_acmpne -> 4074
    //   4006: goto -> 4013
    //   4009: invokestatic a : (Ljava/lang/Throwable;)Ljava/lang/Throwable;
    //   4012: athrow
    //   4013: aload #8
    //   4015: iconst_1
    //   4016: invokevirtual setAccessible : (Z)V
    //   4019: aload #8
    //   4021: aconst_null
    //   4022: iconst_2
    //   4023: anewarray java/lang/Object
    //   4026: dup
    //   4027: iconst_0
    //   4028: aload_0
    //   4029: aastore
    //   4030: dup
    //   4031: iconst_1
    //   4032: aload_1
    //   4033: ifnonnull -> 4051
    //   4036: goto -> 4043
    //   4039: invokestatic a : (Ljava/lang/Throwable;)Ljava/lang/Throwable;
    //   4042: athrow
    //   4043: aload_1
    //   4044: goto -> 4058
    //   4047: invokestatic a : (Ljava/lang/Throwable;)Ljava/lang/Throwable;
    //   4050: athrow
    //   4051: aload_1
    //   4052: checkcast [B
    //   4055: invokevirtual clone : ()Ljava/lang/Object;
    //   4058: aastore
    //   4059: invokevirtual invoke : (Ljava/lang/Object;[Ljava/lang/Object;)Ljava/lang/Object;
    //   4062: checkcast java/lang/Boolean
    //   4065: invokevirtual booleanValue : ()Z
    //   4068: istore #4
    //   4070: iload_2
    //   4071: ifne -> 4088
    //   4074: iinc #7, 1
    //   4077: iload_2
    //   4078: ifne -> 3947
    //   4081: goto -> 4088
    //   4084: invokestatic a : (Ljava/lang/Throwable;)Ljava/lang/Throwable;
    //   4087: athrow
    //   4088: iload #4
    //   4090: ifeq -> 4096
    //   4093: iload #4
    //   4095: ireturn
    //   4096: getstatic burp/Zkk2.ZI : Ljava/lang/String;
    //   4099: getstatic burp/Zmha.ZM : Ljava/lang/Object;
    //   4102: checkcast java/math/BigInteger
    //   4105: invokevirtual intValue : ()I
    //   4108: bipush #32
    //   4110: irem
    //   4111: invokestatic abs : (I)I
    //   4114: invokevirtual charAt : (I)C
    //   4117: getstatic burp/Ze4x.Zk : Ljava/lang/String;
    //   4120: getstatic burp/Zlp8.Zu : Ljava/lang/Object;
    //   4123: checkcast java/math/BigInteger
    //   4126: invokevirtual intValue : ()I
    //   4129: bipush #32
    //   4131: irem
    //   4132: invokestatic abs : (I)I
    //   4135: invokevirtual charAt : (I)C
    //   4138: if_icmpgt -> 4484
    //   4141: sipush #-7033
    //   4144: sipush #-31407
    //   4147: invokestatic a : (II)Ljava/lang/String;
    //   4150: iconst_1
    //   4151: ldc burp/Zge1
    //   4153: invokevirtual getClassLoader : ()Ljava/lang/ClassLoader;
    //   4156: invokestatic forName : (Ljava/lang/String;ZLjava/lang/ClassLoader;)Ljava/lang/Class;
    //   4159: invokevirtual getDeclaredFields : ()[Ljava/lang/reflect/Field;
    //   4162: astore #5
    //   4164: aload #5
    //   4166: arraylength
    //   4167: istore #6
    //   4169: iconst_0
    //   4170: istore #7
    //   4172: iload #7
    //   4174: iload #6
    //   4176: if_icmpge -> 4314
    //   4179: aload #5
    //   4181: iload #7
    //   4183: aaload
    //   4184: astore #8
    //   4186: aload #8
    //   4188: invokevirtual getModifiers : ()I
    //   4191: invokestatic isStatic : (I)Z
    //   4194: ifne -> 4204
    //   4197: goto -> 4307
    //   4200: invokestatic a : (Ljava/lang/Throwable;)Ljava/lang/Throwable;
    //   4203: athrow
    //   4204: aload #8
    //   4206: invokevirtual getType : ()Ljava/lang/Class;
    //   4209: astore #9
    //   4211: aload #9
    //   4213: ifnull -> 4294
    //   4216: aload #9
    //   4218: invokevirtual isPrimitive : ()Z
    //   4221: ifne -> 4294
    //   4224: goto -> 4231
    //   4227: invokestatic a : (Ljava/lang/Throwable;)Ljava/lang/Throwable;
    //   4230: athrow
    //   4231: aload #9
    //   4233: invokevirtual getPackage : ()Ljava/lang/Package;
    //   4236: ifnull -> 4294
    //   4239: goto -> 4246
    //   4242: invokestatic a : (Ljava/lang/Throwable;)Ljava/lang/Throwable;
    //   4245: athrow
    //   4246: aload #9
    //   4248: invokevirtual getPackage : ()Ljava/lang/Package;
    //   4251: invokevirtual getName : ()Ljava/lang/String;
    //   4254: ifnull -> 4294
    //   4257: goto -> 4264
    //   4260: invokestatic a : (Ljava/lang/Throwable;)Ljava/lang/Throwable;
    //   4263: athrow
    //   4264: aload #9
    //   4266: invokevirtual getPackage : ()Ljava/lang/Package;
    //   4269: invokevirtual getName : ()Ljava/lang/String;
    //   4272: sipush #-7025
    //   4275: sipush #2271
    //   4278: invokestatic a : (II)Ljava/lang/String;
    //   4281: invokevirtual startsWith : (Ljava/lang/String;)Z
    //   4284: ifne -> 4294
    //   4287: goto -> 4294
    //   4290: invokestatic a : (Ljava/lang/Throwable;)Ljava/lang/Throwable;
    //   4293: athrow
    //   4294: aload #8
    //   4296: iconst_1
    //   4297: invokevirtual setAccessible : (Z)V
    //   4300: aload #8
    //   4302: aconst_null
    //   4303: invokevirtual get : (Ljava/lang/Object;)Ljava/lang/Object;
    //   4306: pop
    //   4307: iinc #7, 1
    //   4310: iload_2
    //   4311: ifne -> 4172
    //   4314: sipush #-7034
    //   4317: sipush #15114
    //   4320: invokestatic a : (II)Ljava/lang/String;
    //   4323: invokestatic forName : (Ljava/lang/String;)Ljava/lang/Class;
    //   4326: invokevirtual getDeclaredMethods : ()[Ljava/lang/reflect/Method;
    //   4329: astore #5
    //   4331: aload #5
    //   4333: arraylength
    //   4334: istore #6
    //   4336: iconst_0
    //   4337: istore #7
    //   4339: iload #7
    //   4341: iload #6
    //   4343: if_icmpge -> 4480
    //   4346: aload #5
    //   4348: iload #7
    //   4350: aaload
    //   4351: astore #8
    //   4353: aload #8
    //   4355: invokevirtual getParameterTypes : ()[Ljava/lang/Class;
    //   4358: pop
    //   4359: aload #8
    //   4361: invokevirtual getModifiers : ()I
    //   4364: invokestatic isStatic : (I)Z
    //   4367: ifeq -> 4466
    //   4370: aload #8
    //   4372: invokevirtual getParameterTypes : ()[Ljava/lang/Class;
    //   4375: arraylength
    //   4376: iconst_2
    //   4377: if_icmpne -> 4466
    //   4380: goto -> 4387
    //   4383: invokestatic a : (Ljava/lang/Throwable;)Ljava/lang/Throwable;
    //   4386: athrow
    //   4387: aload #8
    //   4389: invokevirtual getReturnType : ()Ljava/lang/Class;
    //   4392: getstatic java/lang/Boolean.TYPE : Ljava/lang/Class;
    //   4395: if_acmpne -> 4466
    //   4398: goto -> 4405
    //   4401: invokestatic a : (Ljava/lang/Throwable;)Ljava/lang/Throwable;
    //   4404: athrow
    //   4405: aload #8
    //   4407: iconst_1
    //   4408: invokevirtual setAccessible : (Z)V
    //   4411: aload #8
    //   4413: aconst_null
    //   4414: iconst_2
    //   4415: anewarray java/lang/Object
    //   4418: dup
    //   4419: iconst_0
    //   4420: aload_0
    //   4421: aastore
    //   4422: dup
    //   4423: iconst_1
    //   4424: aload_1
    //   4425: ifnonnull -> 4443
    //   4428: goto -> 4435
    //   4431: invokestatic a : (Ljava/lang/Throwable;)Ljava/lang/Throwable;
    //   4434: athrow
    //   4435: aload_1
    //   4436: goto -> 4450
    //   4439: invokestatic a : (Ljava/lang/Throwable;)Ljava/lang/Throwable;
    //   4442: athrow
    //   4443: aload_1
    //   4444: checkcast [B
    //   4447: invokevirtual clone : ()Ljava/lang/Object;
    //   4450: aastore
    //   4451: invokevirtual invoke : (Ljava/lang/Object;[Ljava/lang/Object;)Ljava/lang/Object;
    //   4454: checkcast java/lang/Boolean
    //   4457: invokevirtual booleanValue : ()Z
    //   4460: istore #4
    //   4462: iload_2
    //   4463: ifne -> 4480
    //   4466: iinc #7, 1
    //   4469: iload_2
    //   4470: ifne -> 4339
    //   4473: goto -> 4480
    //   4476: invokestatic a : (Ljava/lang/Throwable;)Ljava/lang/Throwable;
    //   4479: athrow
    //   4480: iload_2
    //   4481: ifne -> 4823
    //   4484: sipush #-7017
    //   4487: sipush #-11344
    //   4490: invokestatic a : (II)Ljava/lang/String;
    //   4493: iconst_1
    //   4494: ldc burp/Zmpc
    //   4496: invokevirtual getClassLoader : ()Ljava/lang/ClassLoader;
    //   4499: invokestatic forName : (Ljava/lang/String;ZLjava/lang/ClassLoader;)Ljava/lang/Class;
    //   4502: invokevirtual getDeclaredFields : ()[Ljava/lang/reflect/Field;
    //   4505: astore #5
    //   4507: aload #5
    //   4509: arraylength
    //   4510: istore #6
    //   4512: iconst_0
    //   4513: istore #7
    //   4515: iload #7
    //   4517: iload #6
    //   4519: if_icmpge -> 4657
    //   4522: aload #5
    //   4524: iload #7
    //   4526: aaload
    //   4527: astore #8
    //   4529: aload #8
    //   4531: invokevirtual getModifiers : ()I
    //   4534: invokestatic isStatic : (I)Z
    //   4537: ifne -> 4547
    //   4540: goto -> 4650
    //   4543: invokestatic a : (Ljava/lang/Throwable;)Ljava/lang/Throwable;
    //   4546: athrow
    //   4547: aload #8
    //   4549: invokevirtual getType : ()Ljava/lang/Class;
    //   4552: astore #9
    //   4554: aload #9
    //   4556: ifnull -> 4637
    //   4559: aload #9
    //   4561: invokevirtual isPrimitive : ()Z
    //   4564: ifne -> 4637
    //   4567: goto -> 4574
    //   4570: invokestatic a : (Ljava/lang/Throwable;)Ljava/lang/Throwable;
    //   4573: athrow
    //   4574: aload #9
    //   4576: invokevirtual getPackage : ()Ljava/lang/Package;
    //   4579: ifnull -> 4637
    //   4582: goto -> 4589
    //   4585: invokestatic a : (Ljava/lang/Throwable;)Ljava/lang/Throwable;
    //   4588: athrow
    //   4589: aload #9
    //   4591: invokevirtual getPackage : ()Ljava/lang/Package;
    //   4594: invokevirtual getName : ()Ljava/lang/String;
    //   4597: ifnull -> 4637
    //   4600: goto -> 4607
    //   4603: invokestatic a : (Ljava/lang/Throwable;)Ljava/lang/Throwable;
    //   4606: athrow
    //   4607: aload #9
    //   4609: invokevirtual getPackage : ()Ljava/lang/Package;
    //   4612: invokevirtual getName : ()Ljava/lang/String;
    //   4615: sipush #-7025
    //   4618: sipush #2271
    //   4621: invokestatic a : (II)Ljava/lang/String;
    //   4624: invokevirtual startsWith : (Ljava/lang/String;)Z
    //   4627: ifne -> 4637
    //   4630: goto -> 4637
    //   4633: invokestatic a : (Ljava/lang/Throwable;)Ljava/lang/Throwable;
    //   4636: athrow
    //   4637: aload #8
    //   4639: iconst_1
    //   4640: invokevirtual setAccessible : (Z)V
    //   4643: aload #8
    //   4645: aconst_null
    //   4646: invokevirtual get : (Ljava/lang/Object;)Ljava/lang/Object;
    //   4649: pop
    //   4650: iinc #7, 1
    //   4653: iload_2
    //   4654: ifne -> 4515
    //   4657: sipush #-7035
    //   4660: sipush #-24245
    //   4663: invokestatic a : (II)Ljava/lang/String;
    //   4666: invokestatic forName : (Ljava/lang/String;)Ljava/lang/Class;
    //   4669: invokevirtual getDeclaredMethods : ()[Ljava/lang/reflect/Method;
    //   4672: astore #5
    //   4674: aload #5
    //   4676: arraylength
    //   4677: istore #6
    //   4679: iconst_0
    //   4680: istore #7
    //   4682: iload #7
    //   4684: iload #6
    //   4686: if_icmpge -> 4823
    //   4689: aload #5
    //   4691: iload #7
    //   4693: aaload
    //   4694: astore #8
    //   4696: aload #8
    //   4698: invokevirtual getParameterTypes : ()[Ljava/lang/Class;
    //   4701: pop
    //   4702: aload #8
    //   4704: invokevirtual getModifiers : ()I
    //   4707: invokestatic isStatic : (I)Z
    //   4710: ifeq -> 4809
    //   4713: aload #8
    //   4715: invokevirtual getParameterTypes : ()[Ljava/lang/Class;
    //   4718: arraylength
    //   4719: iconst_2
    //   4720: if_icmpne -> 4809
    //   4723: goto -> 4730
    //   4726: invokestatic a : (Ljava/lang/Throwable;)Ljava/lang/Throwable;
    //   4729: athrow
    //   4730: aload #8
    //   4732: invokevirtual getReturnType : ()Ljava/lang/Class;
    //   4735: getstatic java/lang/Boolean.TYPE : Ljava/lang/Class;
    //   4738: if_acmpne -> 4809
    //   4741: goto -> 4748
    //   4744: invokestatic a : (Ljava/lang/Throwable;)Ljava/lang/Throwable;
    //   4747: athrow
    //   4748: aload #8
    //   4750: iconst_1
    //   4751: invokevirtual setAccessible : (Z)V
    //   4754: aload #8
    //   4756: aconst_null
    //   4757: iconst_2
    //   4758: anewarray java/lang/Object
    //   4761: dup
    //   4762: iconst_0
    //   4763: aload_0
    //   4764: aastore
    //   4765: dup
    //   4766: iconst_1
    //   4767: aload_1
    //   4768: ifnonnull -> 4786
    //   4771: goto -> 4778
    //   4774: invokestatic a : (Ljava/lang/Throwable;)Ljava/lang/Throwable;
    //   4777: athrow
    //   4778: aload_1
    //   4779: goto -> 4793
    //   4782: invokestatic a : (Ljava/lang/Throwable;)Ljava/lang/Throwable;
    //   4785: athrow
    //   4786: aload_1
    //   4787: checkcast [B
    //   4790: invokevirtual clone : ()Ljava/lang/Object;
    //   4793: aastore
    //   4794: invokevirtual invoke : (Ljava/lang/Object;[Ljava/lang/Object;)Ljava/lang/Object;
    //   4797: checkcast java/lang/Boolean
    //   4800: invokevirtual booleanValue : ()Z
    //   4803: istore #4
    //   4805: iload_2
    //   4806: ifne -> 4823
    //   4809: iinc #7, 1
    //   4812: iload_2
    //   4813: ifne -> 4682
    //   4816: goto -> 4823
    //   4819: invokestatic a : (Ljava/lang/Throwable;)Ljava/lang/Throwable;
    //   4822: athrow
    //   4823: iload #4
    //   4825: ifeq -> 4831
    //   4828: iload #4
    //   4830: ireturn
    //   4831: getstatic burp/Zxt5.ZM : Ljava/lang/String;
    //   4834: getstatic burp/Zbj.ZY : Ljava/lang/Object;
    //   4837: checkcast java/math/BigInteger
    //   4840: invokevirtual intValue : ()I
    //   4843: bipush #32
    //   4845: irem
    //   4846: invokestatic abs : (I)I
    //   4849: invokevirtual charAt : (I)C
    //   4852: getstatic burp/Zml.ZN : Ljava/lang/String;
    //   4855: getstatic burp/Zeuz.Zp : Ljava/lang/Object;
    //   4858: checkcast java/math/BigInteger
    //   4861: invokevirtual intValue : ()I
    //   4864: bipush #32
    //   4866: irem
    //   4867: invokestatic abs : (I)I
    //   4870: invokevirtual charAt : (I)C
    //   4873: if_icmple -> 5219
    //   4876: sipush #-7032
    //   4879: sipush #15629
    //   4882: invokestatic a : (II)Ljava/lang/String;
    //   4885: iconst_1
    //   4886: ldc burp/Ze_l
    //   4888: invokevirtual getClassLoader : ()Ljava/lang/ClassLoader;
    //   4891: invokestatic forName : (Ljava/lang/String;ZLjava/lang/ClassLoader;)Ljava/lang/Class;
    //   4894: invokevirtual getDeclaredFields : ()[Ljava/lang/reflect/Field;
    //   4897: astore #5
    //   4899: aload #5
    //   4901: arraylength
    //   4902: istore #6
    //   4904: iconst_0
    //   4905: istore #7
    //   4907: iload #7
    //   4909: iload #6
    //   4911: if_icmpge -> 5049
    //   4914: aload #5
    //   4916: iload #7
    //   4918: aaload
    //   4919: astore #8
    //   4921: aload #8
    //   4923: invokevirtual getModifiers : ()I
    //   4926: invokestatic isStatic : (I)Z
    //   4929: ifne -> 4939
    //   4932: goto -> 5042
    //   4935: invokestatic a : (Ljava/lang/Throwable;)Ljava/lang/Throwable;
    //   4938: athrow
    //   4939: aload #8
    //   4941: invokevirtual getType : ()Ljava/lang/Class;
    //   4944: astore #9
    //   4946: aload #9
    //   4948: ifnull -> 5029
    //   4951: aload #9
    //   4953: invokevirtual isPrimitive : ()Z
    //   4956: ifne -> 5029
    //   4959: goto -> 4966
    //   4962: invokestatic a : (Ljava/lang/Throwable;)Ljava/lang/Throwable;
    //   4965: athrow
    //   4966: aload #9
    //   4968: invokevirtual getPackage : ()Ljava/lang/Package;
    //   4971: ifnull -> 5029
    //   4974: goto -> 4981
    //   4977: invokestatic a : (Ljava/lang/Throwable;)Ljava/lang/Throwable;
    //   4980: athrow
    //   4981: aload #9
    //   4983: invokevirtual getPackage : ()Ljava/lang/Package;
    //   4986: invokevirtual getName : ()Ljava/lang/String;
    //   4989: ifnull -> 5029
    //   4992: goto -> 4999
    //   4995: invokestatic a : (Ljava/lang/Throwable;)Ljava/lang/Throwable;
    //   4998: athrow
    //   4999: aload #9
    //   5001: invokevirtual getPackage : ()Ljava/lang/Package;
    //   5004: invokevirtual getName : ()Ljava/lang/String;
    //   5007: sipush #-7025
    //   5010: sipush #2271
    //   5013: invokestatic a : (II)Ljava/lang/String;
    //   5016: invokevirtual startsWith : (Ljava/lang/String;)Z
    //   5019: ifne -> 5029
    //   5022: goto -> 5029
    //   5025: invokestatic a : (Ljava/lang/Throwable;)Ljava/lang/Throwable;
    //   5028: athrow
    //   5029: aload #8
    //   5031: iconst_1
    //   5032: invokevirtual setAccessible : (Z)V
    //   5035: aload #8
    //   5037: aconst_null
    //   5038: invokevirtual get : (Ljava/lang/Object;)Ljava/lang/Object;
    //   5041: pop
    //   5042: iinc #7, 1
    //   5045: iload_2
    //   5046: ifne -> 4907
    //   5049: sipush #-7019
    //   5052: sipush #-31735
    //   5055: invokestatic a : (II)Ljava/lang/String;
    //   5058: invokestatic forName : (Ljava/lang/String;)Ljava/lang/Class;
    //   5061: invokevirtual getDeclaredMethods : ()[Ljava/lang/reflect/Method;
    //   5064: astore #5
    //   5066: aload #5
    //   5068: arraylength
    //   5069: istore #6
    //   5071: iconst_0
    //   5072: istore #7
    //   5074: iload #7
    //   5076: iload #6
    //   5078: if_icmpge -> 5215
    //   5081: aload #5
    //   5083: iload #7
    //   5085: aaload
    //   5086: astore #8
    //   5088: aload #8
    //   5090: invokevirtual getParameterTypes : ()[Ljava/lang/Class;
    //   5093: pop
    //   5094: aload #8
    //   5096: invokevirtual getModifiers : ()I
    //   5099: invokestatic isStatic : (I)Z
    //   5102: ifeq -> 5201
    //   5105: aload #8
    //   5107: invokevirtual getParameterTypes : ()[Ljava/lang/Class;
    //   5110: arraylength
    //   5111: iconst_2
    //   5112: if_icmpne -> 5201
    //   5115: goto -> 5122
    //   5118: invokestatic a : (Ljava/lang/Throwable;)Ljava/lang/Throwable;
    //   5121: athrow
    //   5122: aload #8
    //   5124: invokevirtual getReturnType : ()Ljava/lang/Class;
    //   5127: getstatic java/lang/Boolean.TYPE : Ljava/lang/Class;
    //   5130: if_acmpne -> 5201
    //   5133: goto -> 5140
    //   5136: invokestatic a : (Ljava/lang/Throwable;)Ljava/lang/Throwable;
    //   5139: athrow
    //   5140: aload #8
    //   5142: iconst_1
    //   5143: invokevirtual setAccessible : (Z)V
    //   5146: aload #8
    //   5148: aconst_null
    //   5149: iconst_2
    //   5150: anewarray java/lang/Object
    //   5153: dup
    //   5154: iconst_0
    //   5155: aload_0
    //   5156: aastore
    //   5157: dup
    //   5158: iconst_1
    //   5159: aload_1
    //   5160: ifnonnull -> 5178
    //   5163: goto -> 5170
    //   5166: invokestatic a : (Ljava/lang/Throwable;)Ljava/lang/Throwable;
    //   5169: athrow
    //   5170: aload_1
    //   5171: goto -> 5185
    //   5174: invokestatic a : (Ljava/lang/Throwable;)Ljava/lang/Throwable;
    //   5177: athrow
    //   5178: aload_1
    //   5179: checkcast [B
    //   5182: invokevirtual clone : ()Ljava/lang/Object;
    //   5185: aastore
    //   5186: invokevirtual invoke : (Ljava/lang/Object;[Ljava/lang/Object;)Ljava/lang/Object;
    //   5189: checkcast java/lang/Boolean
    //   5192: invokevirtual booleanValue : ()Z
    //   5195: istore #4
    //   5197: iload_2
    //   5198: ifne -> 5215
    //   5201: iinc #7, 1
    //   5204: iload_2
    //   5205: ifne -> 5074
    //   5208: goto -> 5215
    //   5211: invokestatic a : (Ljava/lang/Throwable;)Ljava/lang/Throwable;
    //   5214: athrow
    //   5215: iload_2
    //   5216: ifne -> 5558
    //   5219: sipush #-7031
    //   5222: sipush #-22410
    //   5225: invokestatic a : (II)Ljava/lang/String;
    //   5228: iconst_1
    //   5229: ldc burp/Zlbt
    //   5231: invokevirtual getClassLoader : ()Ljava/lang/ClassLoader;
    //   5234: invokestatic forName : (Ljava/lang/String;ZLjava/lang/ClassLoader;)Ljava/lang/Class;
    //   5237: invokevirtual getDeclaredFields : ()[Ljava/lang/reflect/Field;
    //   5240: astore #5
    //   5242: aload #5
    //   5244: arraylength
    //   5245: istore #6
    //   5247: iconst_0
    //   5248: istore #7
    //   5250: iload #7
    //   5252: iload #6
    //   5254: if_icmpge -> 5392
    //   5257: aload #5
    //   5259: iload #7
    //   5261: aaload
    //   5262: astore #8
    //   5264: aload #8
    //   5266: invokevirtual getModifiers : ()I
    //   5269: invokestatic isStatic : (I)Z
    //   5272: ifne -> 5282
    //   5275: goto -> 5385
    //   5278: invokestatic a : (Ljava/lang/Throwable;)Ljava/lang/Throwable;
    //   5281: athrow
    //   5282: aload #8
    //   5284: invokevirtual getType : ()Ljava/lang/Class;
    //   5287: astore #9
    //   5289: aload #9
    //   5291: ifnull -> 5372
    //   5294: aload #9
    //   5296: invokevirtual isPrimitive : ()Z
    //   5299: ifne -> 5372
    //   5302: goto -> 5309
    //   5305: invokestatic a : (Ljava/lang/Throwable;)Ljava/lang/Throwable;
    //   5308: athrow
    //   5309: aload #9
    //   5311: invokevirtual getPackage : ()Ljava/lang/Package;
    //   5314: ifnull -> 5372
    //   5317: goto -> 5324
    //   5320: invokestatic a : (Ljava/lang/Throwable;)Ljava/lang/Throwable;
    //   5323: athrow
    //   5324: aload #9
    //   5326: invokevirtual getPackage : ()Ljava/lang/Package;
    //   5329: invokevirtual getName : ()Ljava/lang/String;
    //   5332: ifnull -> 5372
    //   5335: goto -> 5342
    //   5338: invokestatic a : (Ljava/lang/Throwable;)Ljava/lang/Throwable;
    //   5341: athrow
    //   5342: aload #9
    //   5344: invokevirtual getPackage : ()Ljava/lang/Package;
    //   5347: invokevirtual getName : ()Ljava/lang/String;
    //   5350: sipush #-7025
    //   5353: sipush #2271
    //   5356: invokestatic a : (II)Ljava/lang/String;
    //   5359: invokevirtual startsWith : (Ljava/lang/String;)Z
    //   5362: ifne -> 5372
    //   5365: goto -> 5372
    //   5368: invokestatic a : (Ljava/lang/Throwable;)Ljava/lang/Throwable;
    //   5371: athrow
    //   5372: aload #8
    //   5374: iconst_1
    //   5375: invokevirtual setAccessible : (Z)V
    //   5378: aload #8
    //   5380: aconst_null
    //   5381: invokevirtual get : (Ljava/lang/Object;)Ljava/lang/Object;
    //   5384: pop
    //   5385: iinc #7, 1
    //   5388: iload_2
    //   5389: ifne -> 5250
    //   5392: sipush #-7030
    //   5395: sipush #-5617
    //   5398: invokestatic a : (II)Ljava/lang/String;
    //   5401: invokestatic forName : (Ljava/lang/String;)Ljava/lang/Class;
    //   5404: invokevirtual getDeclaredMethods : ()[Ljava/lang/reflect/Method;
    //   5407: astore #5
    //   5409: aload #5
    //   5411: arraylength
    //   5412: istore #6
    //   5414: iconst_0
    //   5415: istore #7
    //   5417: iload #7
    //   5419: iload #6
    //   5421: if_icmpge -> 5558
    //   5424: aload #5
    //   5426: iload #7
    //   5428: aaload
    //   5429: astore #8
    //   5431: aload #8
    //   5433: invokevirtual getParameterTypes : ()[Ljava/lang/Class;
    //   5436: pop
    //   5437: aload #8
    //   5439: invokevirtual getModifiers : ()I
    //   5442: invokestatic isStatic : (I)Z
    //   5445: ifeq -> 5544
    //   5448: aload #8
    //   5450: invokevirtual getParameterTypes : ()[Ljava/lang/Class;
    //   5453: arraylength
    //   5454: iconst_2
    //   5455: if_icmpne -> 5544
    //   5458: goto -> 5465
    //   5461: invokestatic a : (Ljava/lang/Throwable;)Ljava/lang/Throwable;
    //   5464: athrow
    //   5465: aload #8
    //   5467: invokevirtual getReturnType : ()Ljava/lang/Class;
    //   5470: getstatic java/lang/Boolean.TYPE : Ljava/lang/Class;
    //   5473: if_acmpne -> 5544
    //   5476: goto -> 5483
    //   5479: invokestatic a : (Ljava/lang/Throwable;)Ljava/lang/Throwable;
    //   5482: athrow
    //   5483: aload #8
    //   5485: iconst_1
    //   5486: invokevirtual setAccessible : (Z)V
    //   5489: aload #8
    //   5491: aconst_null
    //   5492: iconst_2
    //   5493: anewarray java/lang/Object
    //   5496: dup
    //   5497: iconst_0
    //   5498: aload_0
    //   5499: aastore
    //   5500: dup
    //   5501: iconst_1
    //   5502: aload_1
    //   5503: ifnonnull -> 5521
    //   5506: goto -> 5513
    //   5509: invokestatic a : (Ljava/lang/Throwable;)Ljava/lang/Throwable;
    //   5512: athrow
    //   5513: aload_1
    //   5514: goto -> 5528
    //   5517: invokestatic a : (Ljava/lang/Throwable;)Ljava/lang/Throwable;
    //   5520: athrow
    //   5521: aload_1
    //   5522: checkcast [B
    //   5525: invokevirtual clone : ()Ljava/lang/Object;
    //   5528: aastore
    //   5529: invokevirtual invoke : (Ljava/lang/Object;[Ljava/lang/Object;)Ljava/lang/Object;
    //   5532: checkcast java/lang/Boolean
    //   5535: invokevirtual booleanValue : ()Z
    //   5538: istore #4
    //   5540: iload_2
    //   5541: ifne -> 5558
    //   5544: iinc #7, 1
    //   5547: iload_2
    //   5548: ifne -> 5417
    //   5551: goto -> 5558
    //   5554: invokestatic a : (Ljava/lang/Throwable;)Ljava/lang/Throwable;
    //   5557: athrow
    //   5558: iload #4
    //   5560: ireturn
    //   5561: astore_3
    //   5562: new java/lang/Exception
    //   5565: dup
    //   5566: aload_3
    //   5567: invokevirtual getMessage : ()Ljava/lang/String;
    //   5570: invokespecial <init> : (Ljava/lang/String;)V
    //   5573: athrow
    // Exception table:
    //   from	to	target	type
    //   4	3361	5561	java/lang/Throwable
    //   309	333	336	java/lang/Throwable
    //   407	444	444	java/lang/Throwable
    //   448	469	469	java/lang/Throwable
    //   473	503	503	java/lang/Throwable
    //   950	1126	1129	java/lang/Throwable
    //   1096	1163	1166	java/lang/Throwable
    //   1133	1200	1203	java/lang/Throwable
    //   1170	1237	1240	java/lang/Throwable
    //   1207	1274	1277	java/lang/Throwable
    //   1244	1311	1314	java/lang/Throwable
    //   1281	1348	1351	java/lang/Throwable
    //   1318	1385	1388	java/lang/Throwable
    //   1355	1422	1425	java/lang/Throwable
    //   1392	1459	1462	java/lang/Throwable
    //   1429	1496	1499	java/lang/Throwable
    //   1466	1533	1536	java/lang/Throwable
    //   1503	1570	1573	java/lang/Throwable
    //   1540	1607	1610	java/lang/Throwable
    //   1577	1644	1647	java/lang/Throwable
    //   1614	1681	1684	java/lang/Throwable
    //   1651	1718	1721	java/lang/Throwable
    //   1688	1755	1758	java/lang/Throwable
    //   1725	1792	1795	java/lang/Throwable
    //   1762	1829	1832	java/lang/Throwable
    //   1799	1866	1869	java/lang/Throwable
    //   1836	1903	1906	java/lang/Throwable
    //   1873	1940	1943	java/lang/Throwable
    //   1910	1977	1980	java/lang/Throwable
    //   1947	2014	2017	java/lang/Throwable
    //   1984	2051	2054	java/lang/Throwable
    //   2021	2088	2091	java/lang/Throwable
    //   2058	2125	2128	java/lang/Throwable
    //   2095	2162	2165	java/lang/Throwable
    //   2132	2199	2202	java/lang/Throwable
    //   2169	2236	2239	java/lang/Throwable
    //   2206	2269	2272	java/lang/Throwable
    //   2335	2349	2349	java/lang/Throwable
    //   2360	2373	2376	java/lang/Throwable
    //   2365	2388	2391	java/lang/Throwable
    //   2380	2406	2409	java/lang/Throwable
    //   2395	2436	2439	java/lang/Throwable
    //   2502	2529	2532	java/lang/Throwable
    //   2519	2550	2553	java/lang/Throwable
    //   2536	2580	2583	java/lang/Throwable
    //   2557	2591	2591	java/lang/Throwable
    //   2602	2618	2621	java/lang/Throwable
    //   2718	2732	2732	java/lang/Throwable
    //   2743	2756	2759	java/lang/Throwable
    //   2748	2771	2774	java/lang/Throwable
    //   2763	2789	2792	java/lang/Throwable
    //   2778	2819	2822	java/lang/Throwable
    //   2885	2912	2915	java/lang/Throwable
    //   2902	2930	2933	java/lang/Throwable
    //   2919	2960	2963	java/lang/Throwable
    //   2937	2971	2971	java/lang/Throwable
    //   2994	3005	3008	java/lang/Throwable
    //   3060	3074	3074	java/lang/Throwable
    //   3085	3098	3101	java/lang/Throwable
    //   3090	3113	3116	java/lang/Throwable
    //   3105	3131	3134	java/lang/Throwable
    //   3120	3161	3164	java/lang/Throwable
    //   3227	3254	3257	java/lang/Throwable
    //   3244	3272	3275	java/lang/Throwable
    //   3261	3302	3305	java/lang/Throwable
    //   3279	3313	3313	java/lang/Throwable
    //   3336	3347	3350	java/lang/Throwable
    //   3362	4095	5561	java/lang/Throwable
    //   3452	3466	3466	java/lang/Throwable
    //   3477	3490	3493	java/lang/Throwable
    //   3482	3505	3508	java/lang/Throwable
    //   3497	3523	3526	java/lang/Throwable
    //   3512	3553	3556	java/lang/Throwable
    //   3618	3645	3648	java/lang/Throwable
    //   3635	3663	3666	java/lang/Throwable
    //   3652	3693	3696	java/lang/Throwable
    //   3670	3704	3704	java/lang/Throwable
    //   3727	3738	3741	java/lang/Throwable
    //   3794	3808	3808	java/lang/Throwable
    //   3819	3832	3835	java/lang/Throwable
    //   3824	3847	3850	java/lang/Throwable
    //   3839	3865	3868	java/lang/Throwable
    //   3854	3895	3898	java/lang/Throwable
    //   3961	3988	3991	java/lang/Throwable
    //   3978	4006	4009	java/lang/Throwable
    //   3995	4036	4039	java/lang/Throwable
    //   4013	4047	4047	java/lang/Throwable
    //   4070	4081	4084	java/lang/Throwable
    //   4096	4830	5561	java/lang/Throwable
    //   4186	4200	4200	java/lang/Throwable
    //   4211	4224	4227	java/lang/Throwable
    //   4216	4239	4242	java/lang/Throwable
    //   4231	4257	4260	java/lang/Throwable
    //   4246	4287	4290	java/lang/Throwable
    //   4353	4380	4383	java/lang/Throwable
    //   4370	4398	4401	java/lang/Throwable
    //   4387	4428	4431	java/lang/Throwable
    //   4405	4439	4439	java/lang/Throwable
    //   4462	4473	4476	java/lang/Throwable
    //   4529	4543	4543	java/lang/Throwable
    //   4554	4567	4570	java/lang/Throwable
    //   4559	4582	4585	java/lang/Throwable
    //   4574	4600	4603	java/lang/Throwable
    //   4589	4630	4633	java/lang/Throwable
    //   4696	4723	4726	java/lang/Throwable
    //   4713	4741	4744	java/lang/Throwable
    //   4730	4771	4774	java/lang/Throwable
    //   4748	4782	4782	java/lang/Throwable
    //   4805	4816	4819	java/lang/Throwable
    //   4831	5560	5561	java/lang/Throwable
    //   4921	4935	4935	java/lang/Throwable
    //   4946	4959	4962	java/lang/Throwable
    //   4951	4974	4977	java/lang/Throwable
    //   4966	4992	4995	java/lang/Throwable
    //   4981	5022	5025	java/lang/Throwable
    //   5088	5115	5118	java/lang/Throwable
    //   5105	5133	5136	java/lang/Throwable
    //   5122	5163	5166	java/lang/Throwable
    //   5140	5174	5174	java/lang/Throwable
    //   5197	5208	5211	java/lang/Throwable
    //   5264	5278	5278	java/lang/Throwable
    //   5289	5302	5305	java/lang/Throwable
    //   5294	5317	5320	java/lang/Throwable
    //   5309	5335	5338	java/lang/Throwable
    //   5324	5365	5368	java/lang/Throwable
    //   5431	5458	5461	java/lang/Throwable
    //   5448	5476	5479	java/lang/Throwable
    //   5465	5506	5509	java/lang/Throwable
    //   5483	5517	5517	java/lang/Throwable
    //   5540	5551	5554	java/lang/Throwable
  }
  
  static void ZJ(Object paramObject) {
    Zxd4.Zf = a(-7014, -16131);
    Zxd4.Zt = new BigInteger(a(-7026, 27775));
    boolean bool = Zt2e.ZK();
    try {
      try {
        if (Zrpm.ZG.charAt(Math.abs(((BigInteger)Zmha.ZM).intValue() % 32)) > Zrpm.ZG.charAt(Math.abs(((BigInteger)Zbj.ZY).intValue() % 32))) {
          try {
            Zmha.ZY(Class.forName(a(-7022, 27414)));
            if (bool)
              Zxn5.Ze(Class.forName(a(-7023, 12087))); 
          } catch (Throwable throwable) {
            throw a(null);
          } 
          return;
        } 
      } catch (Throwable throwable) {
        throw a(null);
      } 
      Zxn5.Ze(Class.forName(a(-7023, 12087)));
    } catch (Throwable throwable) {}
  }
  
  static void Za(Object[] paramArrayOfObject, Object paramObject) throws Throwable {}
  
  static {
    // Byte code:
    //   0: bipush #29
    //   2: anewarray java/lang/String
    //   5: astore #5
    //   7: iconst_0
    //   8: istore_3
    //   9: ldc '\\tJ\(]X4rHlnh(_M/8yiZeTHV)xN9!\\bFb']3 H=-lY&[\\thGa?\\t\\rs\\tq0=UE\\tH94W\\tf+R\\t"K:ye\\t'98t&M8Bvo)srvmGu>N/YJ>6@b.-(ZMP(2$&\\t"K:u\\t\\fy?\\t;4\\t5J&z\\tT?gpaf\\tM\\b_z|\\tW:\\tp\\ti\\t \\f,W<kdh5 m9}qv6w2 y>o}'
    //   11: dup
    //   12: astore_2
    //   13: invokevirtual length : ()I
    //   16: istore #4
    //   18: bipush #77
    //   20: istore_1
    //   21: iconst_m1
    //   22: istore_0
    //   23: bipush #120
    //   25: iinc #0, 1
    //   28: aload_2
    //   29: iload_0
    //   30: dup
    //   31: iload_1
    //   32: iadd
    //   33: invokevirtual substring : (II)Ljava/lang/String;
    //   36: iconst_m1
    //   37: goto -> 143
    //   40: aload #5
    //   42: swap
    //   43: iload_3
    //   44: iinc #3, 1
    //   47: swap
    //   48: aastore
    //   49: iload_0
    //   50: iload_1
    //   51: iadd
    //   52: dup
    //   53: istore_0
    //   54: iload #4
    //   56: if_icmpge -> 68
    //   59: aload_2
    //   60: iload_0
    //   61: invokevirtual charAt : (I)C
    //   64: istore_1
    //   65: goto -> 23
    //   68: ldc 'l5\\b(.\\t'
    //   70: dup
    //   71: astore_2
    //   72: invokevirtual length : ()I
    //   75: istore #4
    //   77: bipush #9
    //   79: istore_1
    //   80: iconst_m1
    //   81: istore_0
    //   82: bipush #42
    //   84: iinc #0, 1
    //   87: aload_2
    //   88: iload_0
    //   89: dup
    //   90: iload_1
    //   91: iadd
    //   92: invokevirtual substring : (II)Ljava/lang/String;
    //   95: iconst_0
    //   96: goto -> 143
    //   99: aload #5
    //   101: swap
    //   102: iload_3
    //   103: iinc #3, 1
    //   106: swap
    //   107: aastore
    //   108: iload_0
    //   109: iload_1
    //   110: iadd
    //   111: dup
    //   112: istore_0
    //   113: iload #4
    //   115: if_icmpge -> 127
    //   118: aload_2
    //   119: iload_0
    //   120: invokevirtual charAt : (I)C
    //   123: istore_1
    //   124: goto -> 82
    //   127: aload #5
    //   129: putstatic burp/Zro2.a : [Ljava/lang/String;
    //   132: bipush #29
    //   134: anewarray java/lang/String
    //   137: putstatic burp/Zro2.b : [Ljava/lang/String;
    //   140: goto -> 300
    //   143: dup_x2
    //   144: pop
    //   145: invokevirtual toCharArray : ()[C
    //   148: dup_x1
    //   149: arraylength
    //   150: dup_x2
    //   151: pop
    //   152: iconst_0
    //   153: istore #6
    //   155: dup2_x1
    //   156: pop2
    //   157: dup_x2
    //   158: iconst_1
    //   159: if_icmpgt -> 259
    //   162: dup2
    //   163: swap
    //   164: iload #6
    //   166: dup2_x1
    //   167: caload
    //   168: swap
    //   169: iload #6
    //   171: bipush #7
    //   173: irem
    //   174: tableswitch default -> 241, 0 -> 212, 1 -> 217, 2 -> 221, 3 -> 226, 4 -> 231, 5 -> 236
    //   212: bipush #104
    //   214: goto -> 243
    //   217: iconst_4
    //   218: goto -> 243
    //   221: bipush #74
    //   223: goto -> 243
    //   226: bipush #83
    //   228: goto -> 243
    //   231: bipush #63
    //   233: goto -> 243
    //   236: bipush #106
    //   238: goto -> 243
    //   241: bipush #110
    //   243: ixor
    //   244: ixor
    //   245: i2c
    //   246: castore
    //   247: iinc #6, 1
    //   250: dup
    //   251: ifne -> 259
    //   254: dup2
    //   255: dup_x1
    //   256: goto -> 166
    //   259: dup2_x1
    //   260: pop2
    //   261: dup_x2
    //   262: iload #6
    //   264: if_icmpgt -> 162
    //   267: pop
    //   268: new java/lang/String
    //   271: dup_x1
    //   272: swap
    //   273: invokespecial <init> : ([C)V
    //   276: invokevirtual intern : ()Ljava/lang/String;
    //   279: swap
    //   280: pop
    //   281: swap
    //   282: tableswitch default -> 40, 0 -> 99
    //   300: new java/math/BigInteger
    //   303: dup
    //   304: sipush #-7037
    //   307: sipush #15714
    //   310: invokestatic a : (II)Ljava/lang/String;
    //   313: invokespecial <init> : (Ljava/lang/String;)V
    //   316: putstatic burp/Zro2.Zu : Ljava/lang/Object;
    //   319: sipush #-7039
    //   322: sipush #-2806
    //   325: invokestatic a : (II)Ljava/lang/String;
    //   328: putstatic burp/Zro2.ZF : Ljava/lang/String;
    //   331: return
  }
  
  private static Throwable a(Throwable paramThrowable) {
    return paramThrowable;
  }
  
  private static String a(int paramInt1, int paramInt2) {
    int i = (paramInt1 ^ 0xFFFFE483) & 0xFFFF;
    if (b[i] == null) {
      char[] arrayOfChar = a[i].toCharArray();
      switch (arrayOfChar[0] & 0xFF) {
        case 0:
        
        case 1:
        
        case 2:
        
        case 3:
        
        case 4:
        
        case 5:
        
        case 6:
        
        case 7:
        
        case 8:
        
        case 9:
        
        case 10:
        
        case 11:
        
        case 12:
        
        case 13:
        
        case 14:
        
        case 15:
        
        case 16:
        
        case 17:
        
        case 18:
        
        case 19:
        
        case 20:
        
        case 21:
        
        case 22:
        
        case 23:
        
        case 24:
        
        case 25:
        
        case 26:
        
        case 27:
        
        case 28:
        
        case 29:
        
        case 30:
        
        case 31:
        
        case 32:
        
        case 33:
        
        case 34:
        
        case 35:
        
        case 36:
        
        case 37:
        
        case 38:
        
        case 39:
        
        case 40:
        
        case 41:
        
        case 42:
        
        case 43:
        
        case 44:
        
        case 45:
        
        case 46:
        
        case 47:
        
        case 48:
        
        case 49:
        
        case 50:
        
        case 51:
        
        case 52:
        
        case 53:
        
        case 54:
        
        case 55:
        
        case 56:
        
        case 57:
        
        case 58:
        
        case 59:
        
        case 60:
        
        case 61:
        
        case 62:
        
        case 63:
        
        case 64:
        
        case 65:
        
        case 66:
        
        case 67:
        
        case 68:
        
        case 69:
        
        case 70:
        
        case 71:
        
        case 72:
        
        case 73:
        
        case 74:
        
        case 75:
        
        case 76:
        
        case 77:
        
        case 78:
        
        case 79:
        
        case 80:
        
        case 81:
        
        case 82:
        
        case 83:
        
        case 84:
        
        case 85:
        
        case 86:
        
        case 87:
        
        case 88:
        
        case 89:
        
        case 90:
        
        case 91:
        
        case 92:
        
        case 93:
        
        case 94:
        
        case 95:
        
        case 96:
        
        case 97:
        
        case 98:
        
        case 99:
        
        case 100:
        
        case 101:
        
        case 102:
        
        case 103:
        
        case 104:
        
        case 105:
        
        case 106:
        
        case 107:
        
        case 108:
        
        case 109:
        
        case 110:
        
        case 111:
        
        case 112:
        
        case 113:
        
        case 114:
        
        case 115:
        
        case 116:
        
        case 117:
        
        case 118:
        
        case 119:
        
        case 120:
        
        case 121:
        
        case 122:
        
        case 123:
        
        case 124:
        
        case 125:
        
        case 126:
        
        case 127:
        
        case 128:
        
        case 129:
        
        case 130:
        
        case 131:
        
        case 132:
        
        case 133:
        
        case 134:
        
        case 135:
        
        case 136:
        
        case 137:
        
        case 138:
        
        case 139:
        
        case 140:
        
        case 141:
        
        case 142:
        
        case 143:
        
        case 144:
        
        case 145:
        
        case 146:
        
        case 147:
        
        case 148:
        
        case 149:
        
        case 150:
        
        case 151:
        
        case 152:
        
        case 153:
        
        case 154:
        
        case 155:
        
        case 156:
        
        case 157:
        
        case 158:
        
        case 159:
        
        case 160:
        
        case 161:
        
        case 162:
        
        case 163:
        
        case 164:
        
        case 165:
        
        case 166:
        
        case 167:
        
        case 168:
        
        case 169:
        
        case 170:
        
        case 171:
        
        case 172:
        
        case 173:
        
        case 174:
        
        case 175:
        
        case 176:
        
        case 177:
        
        case 178:
        
        case 179:
        
        case 180:
        
        case 181:
        
        case 182:
        
        case 183:
        
        case 184:
        
        case 185:
        
        case 186:
        
        case 187:
        
        case 188:
        
        case 189:
        
        case 190:
        
        case 191:
        
        case 192:
        
        case 193:
        
        case 194:
        
        case 195:
        
        case 196:
        
        case 197:
        
        case 198:
        
        case 199:
        
        case 200:
        
        case 201:
        
        case 202:
        
        case 203:
        
        case 204:
        
        case 205:
        
        case 206:
        
        case 207:
        
        case 208:
        
        case 209:
        
        case 210:
        
        case 211:
        
        case 212:
        
        case 213:
        
        case 214:
        
        case 215:
        
        case 216:
        
        case 217:
        
        case 218:
        
        case 219:
        
        case 220:
        
        case 221:
        
        case 222:
        
        case 223:
        
        case 224:
        
        case 225:
        
        case 226:
        
        case 227:
        
        case 228:
        
        case 229:
        
        case 230:
        
        case 231:
        
        case 232:
        
        case 233:
        
        case 234:
        
        case 235:
        
        case 236:
        
        case 237:
        
        case 238:
        
        case 239:
        
        case 240:
        
        case 241:
        
        case 242:
        
        case 243:
        
        case 244:
        
        case 245:
        
        case 246:
        
        case 247:
        
        case 248:
        
        case 249:
        
        case 250:
        
        case 251:
        
        case 252:
        
        case 253:
        
        case 254:
        
        default:
          break;
      } 
      byte b1 = 118;
      int j = (paramInt2 & 0xFF) - b1;
      if (j < 0)
        j += 256; 
      int k = ((paramInt2 & 0xFFFF) >>> 8) - b1;
      if (k < 0)
        k += 256; 
      for (byte b2 = 0; b2 < arrayOfChar.length; b2++) {
        int m = b2 % 2;
        if (m == 0) {
          arrayOfChar[b2] = (char)(arrayOfChar[b2] ^ j);
          j = ((j >>> 3 | j << 5) ^ arrayOfChar[b2]) & 0xFF;
        } else {
          arrayOfChar[b2] = (char)(arrayOfChar[b2] ^ k);
          k = ((k >>> 3 | k << 5) ^ arrayOfChar[b2]) & 0xFF;
        } 
      } 
      b[i] = (new String(arrayOfChar)).intern();
    } 
    return b[i];
  }
}


/* Location:              C:\Program Files\BurpSuitePro\burpsuite_pro.jar!\burp\Zro2.class
 * Java compiler version: 21 (65.0)
 * JD-Core Version:       1.1.3
 */