package burp;

import java.math.BigInteger;

class Zrof extends ClassLoader {
  static String ZE;
  
  static Object ZB;
  
  private static final String[] a;
  
  private static final String[] b;
  
  static boolean Zo(Object[] paramArrayOfObject, Object paramObject) throws Throwable {
    // Byte code:
    //   0: invokestatic ZN : ()Z
    //   3: istore_2
    //   4: ldc2_w 8682522807148012
    //   7: invokestatic currentTimeMillis : ()J
    //   10: lxor
    //   11: lstore #4
    //   13: lload #4
    //   15: ldc2_w 25214903917
    //   18: lmul
    //   19: ldc2_w 11
    //   22: ladd
    //   23: ldc2_w 281474976710655
    //   26: land
    //   27: lstore #4
    //   29: lload #4
    //   31: bipush #32
    //   33: lshl
    //   34: lstore #6
    //   36: lload #4
    //   38: ldc2_w 25214903917
    //   41: lmul
    //   42: ldc2_w 11
    //   45: ladd
    //   46: ldc2_w 281474976710655
    //   49: land
    //   50: lstore #4
    //   52: lload #6
    //   54: lload #4
    //   56: ladd
    //   57: lstore #6
    //   59: bipush #16
    //   61: newarray byte
    //   63: dup
    //   64: iconst_0
    //   65: bipush #48
    //   67: bastore
    //   68: dup
    //   69: iconst_1
    //   70: bipush #49
    //   72: bastore
    //   73: dup
    //   74: iconst_2
    //   75: bipush #50
    //   77: bastore
    //   78: dup
    //   79: iconst_3
    //   80: bipush #51
    //   82: bastore
    //   83: dup
    //   84: iconst_4
    //   85: bipush #52
    //   87: bastore
    //   88: dup
    //   89: iconst_5
    //   90: bipush #53
    //   92: bastore
    //   93: dup
    //   94: bipush #6
    //   96: bipush #54
    //   98: bastore
    //   99: dup
    //   100: bipush #7
    //   102: bipush #55
    //   104: bastore
    //   105: dup
    //   106: bipush #8
    //   108: bipush #56
    //   110: bastore
    //   111: dup
    //   112: bipush #9
    //   114: bipush #57
    //   116: bastore
    //   117: dup
    //   118: bipush #10
    //   120: bipush #97
    //   122: bastore
    //   123: dup
    //   124: bipush #11
    //   126: bipush #98
    //   128: bastore
    //   129: dup
    //   130: bipush #12
    //   132: bipush #99
    //   134: bastore
    //   135: dup
    //   136: bipush #13
    //   138: bipush #100
    //   140: bastore
    //   141: dup
    //   142: bipush #14
    //   144: bipush #101
    //   146: bastore
    //   147: dup
    //   148: bipush #15
    //   150: bipush #102
    //   152: bastore
    //   153: astore #8
    //   155: bipush #64
    //   157: newarray byte
    //   159: astore #9
    //   161: bipush #64
    //   163: istore #10
    //   165: bipush #16
    //   167: istore #11
    //   169: iload #11
    //   171: iconst_1
    //   172: isub
    //   173: i2l
    //   174: lstore #12
    //   176: aload #9
    //   178: iinc #10, -1
    //   181: iload #10
    //   183: aload #8
    //   185: lload #6
    //   187: lload #12
    //   189: land
    //   190: l2i
    //   191: baload
    //   192: bastore
    //   193: lload #6
    //   195: iconst_4
    //   196: lushr
    //   197: lstore #6
    //   199: lload #6
    //   201: lconst_0
    //   202: lcmp
    //   203: ifne -> 176
    //   206: bipush #64
    //   208: iload #10
    //   210: isub
    //   211: newarray byte
    //   213: astore_3
    //   214: iconst_0
    //   215: istore #14
    //   217: iload #14
    //   219: aload_3
    //   220: arraylength
    //   221: if_icmpge -> 243
    //   224: aload_3
    //   225: iload #14
    //   227: aload #9
    //   229: iload #10
    //   231: iload #14
    //   233: iadd
    //   234: baload
    //   235: bastore
    //   236: iinc #14, 1
    //   239: iload_2
    //   240: ifne -> 217
    //   243: aload_3
    //   244: arraylength
    //   245: bipush #10
    //   247: if_icmplt -> 13
    //   250: new java/lang/StringBuilder
    //   253: dup
    //   254: invokespecial <init> : ()V
    //   257: astore_3
    //   258: iconst_0
    //   259: istore #4
    //   261: iload #4
    //   263: bipush #32
    //   265: if_icmpge -> 1599
    //   268: iload #4
    //   270: tableswitch default -> 1592, 0 -> 412, 1 -> 449, 2 -> 486, 3 -> 523, 4 -> 560, 5 -> 597, 6 -> 634, 7 -> 671, 8 -> 708, 9 -> 745, 10 -> 782, 11 -> 819, 12 -> 856, 13 -> 893, 14 -> 930, 15 -> 967, 16 -> 1004, 17 -> 1041, 18 -> 1078, 19 -> 1115, 20 -> 1152, 21 -> 1189, 22 -> 1226, 23 -> 1263, 24 -> 1300, 25 -> 1337, 26 -> 1374, 27 -> 1411, 28 -> 1448, 29 -> 1485, 30 -> 1522, 31 -> 1559
    //   412: aload_3
    //   413: getstatic burp/Zex.Zn : Ljava/lang/String;
    //   416: getstatic burp/Zs83.ZT : Ljava/lang/Object;
    //   419: checkcast java/math/BigInteger
    //   422: invokevirtual intValue : ()I
    //   425: bipush #32
    //   427: irem
    //   428: invokestatic abs : (I)I
    //   431: invokevirtual charAt : (I)C
    //   434: invokevirtual append : (C)Ljava/lang/StringBuilder;
    //   437: pop
    //   438: iload_2
    //   439: ifne -> 1592
    //   442: goto -> 449
    //   445: invokestatic a : (Ljava/lang/Throwable;)Ljava/lang/Throwable;
    //   448: athrow
    //   449: aload_3
    //   450: getstatic burp/Zkt7.ZM : Ljava/lang/String;
    //   453: getstatic burp/Zzym.ZK : Ljava/lang/Object;
    //   456: checkcast java/math/BigInteger
    //   459: invokevirtual intValue : ()I
    //   462: bipush #32
    //   464: irem
    //   465: invokestatic abs : (I)I
    //   468: invokevirtual charAt : (I)C
    //   471: invokevirtual append : (C)Ljava/lang/StringBuilder;
    //   474: pop
    //   475: iload_2
    //   476: ifne -> 1592
    //   479: goto -> 486
    //   482: invokestatic a : (Ljava/lang/Throwable;)Ljava/lang/Throwable;
    //   485: athrow
    //   486: aload_3
    //   487: getstatic burp/Zs_v.Zn : Ljava/lang/String;
    //   490: getstatic burp/Zz0w.ZF : Ljava/lang/Object;
    //   493: checkcast java/math/BigInteger
    //   496: invokevirtual intValue : ()I
    //   499: bipush #32
    //   501: irem
    //   502: invokestatic abs : (I)I
    //   505: invokevirtual charAt : (I)C
    //   508: invokevirtual append : (C)Ljava/lang/StringBuilder;
    //   511: pop
    //   512: iload_2
    //   513: ifne -> 1592
    //   516: goto -> 523
    //   519: invokestatic a : (Ljava/lang/Throwable;)Ljava/lang/Throwable;
    //   522: athrow
    //   523: aload_3
    //   524: getstatic burp/Zg6f.Zf : Ljava/lang/String;
    //   527: getstatic burp/Zt98.Zz : Ljava/lang/Object;
    //   530: checkcast java/math/BigInteger
    //   533: invokevirtual intValue : ()I
    //   536: bipush #32
    //   538: irem
    //   539: invokestatic abs : (I)I
    //   542: invokevirtual charAt : (I)C
    //   545: invokevirtual append : (C)Ljava/lang/StringBuilder;
    //   548: pop
    //   549: iload_2
    //   550: ifne -> 1592
    //   553: goto -> 560
    //   556: invokestatic a : (Ljava/lang/Throwable;)Ljava/lang/Throwable;
    //   559: athrow
    //   560: aload_3
    //   561: getstatic burp/Zevr.Zk : Ljava/lang/String;
    //   564: getstatic burp/Zxn5.Zd : Ljava/lang/Object;
    //   567: checkcast java/math/BigInteger
    //   570: invokevirtual intValue : ()I
    //   573: bipush #32
    //   575: irem
    //   576: invokestatic abs : (I)I
    //   579: invokevirtual charAt : (I)C
    //   582: invokevirtual append : (C)Ljava/lang/StringBuilder;
    //   585: pop
    //   586: iload_2
    //   587: ifne -> 1592
    //   590: goto -> 597
    //   593: invokestatic a : (Ljava/lang/Throwable;)Ljava/lang/Throwable;
    //   596: athrow
    //   597: aload_3
    //   598: getstatic burp/Zkc8.Za : Ljava/lang/String;
    //   601: getstatic burp/Zlck.Zr : Ljava/lang/Object;
    //   604: checkcast java/math/BigInteger
    //   607: invokevirtual intValue : ()I
    //   610: bipush #32
    //   612: irem
    //   613: invokestatic abs : (I)I
    //   616: invokevirtual charAt : (I)C
    //   619: invokevirtual append : (C)Ljava/lang/StringBuilder;
    //   622: pop
    //   623: iload_2
    //   624: ifne -> 1592
    //   627: goto -> 634
    //   630: invokestatic a : (Ljava/lang/Throwable;)Ljava/lang/Throwable;
    //   633: athrow
    //   634: aload_3
    //   635: getstatic burp/Zm52.Ze : Ljava/lang/String;
    //   638: getstatic burp/Zbzk.ZI : Ljava/lang/Object;
    //   641: checkcast java/math/BigInteger
    //   644: invokevirtual intValue : ()I
    //   647: bipush #32
    //   649: irem
    //   650: invokestatic abs : (I)I
    //   653: invokevirtual charAt : (I)C
    //   656: invokevirtual append : (C)Ljava/lang/StringBuilder;
    //   659: pop
    //   660: iload_2
    //   661: ifne -> 1592
    //   664: goto -> 671
    //   667: invokestatic a : (Ljava/lang/Throwable;)Ljava/lang/Throwable;
    //   670: athrow
    //   671: aload_3
    //   672: getstatic burp/Ze5t.ZX : Ljava/lang/String;
    //   675: getstatic burp/Ze54.Zx : Ljava/lang/Object;
    //   678: checkcast java/math/BigInteger
    //   681: invokevirtual intValue : ()I
    //   684: bipush #32
    //   686: irem
    //   687: invokestatic abs : (I)I
    //   690: invokevirtual charAt : (I)C
    //   693: invokevirtual append : (C)Ljava/lang/StringBuilder;
    //   696: pop
    //   697: iload_2
    //   698: ifne -> 1592
    //   701: goto -> 708
    //   704: invokestatic a : (Ljava/lang/Throwable;)Ljava/lang/Throwable;
    //   707: athrow
    //   708: aload_3
    //   709: getstatic burp/Zm3p.ZE : Ljava/lang/String;
    //   712: getstatic burp/Ztlz.ZW : Ljava/lang/Object;
    //   715: checkcast java/math/BigInteger
    //   718: invokevirtual intValue : ()I
    //   721: bipush #32
    //   723: irem
    //   724: invokestatic abs : (I)I
    //   727: invokevirtual charAt : (I)C
    //   730: invokevirtual append : (C)Ljava/lang/StringBuilder;
    //   733: pop
    //   734: iload_2
    //   735: ifne -> 1592
    //   738: goto -> 745
    //   741: invokestatic a : (Ljava/lang/Throwable;)Ljava/lang/Throwable;
    //   744: athrow
    //   745: aload_3
    //   746: getstatic burp/Zre5.ZR : Ljava/lang/String;
    //   749: getstatic burp/Zlx5.Zp : Ljava/lang/Object;
    //   752: checkcast java/math/BigInteger
    //   755: invokevirtual intValue : ()I
    //   758: bipush #32
    //   760: irem
    //   761: invokestatic abs : (I)I
    //   764: invokevirtual charAt : (I)C
    //   767: invokevirtual append : (C)Ljava/lang/StringBuilder;
    //   770: pop
    //   771: iload_2
    //   772: ifne -> 1592
    //   775: goto -> 782
    //   778: invokestatic a : (Ljava/lang/Throwable;)Ljava/lang/Throwable;
    //   781: athrow
    //   782: aload_3
    //   783: getstatic burp/Ztsu.ZE : Ljava/lang/String;
    //   786: getstatic burp/Zxjv.ZY : Ljava/lang/Object;
    //   789: checkcast java/math/BigInteger
    //   792: invokevirtual intValue : ()I
    //   795: bipush #32
    //   797: irem
    //   798: invokestatic abs : (I)I
    //   801: invokevirtual charAt : (I)C
    //   804: invokevirtual append : (C)Ljava/lang/StringBuilder;
    //   807: pop
    //   808: iload_2
    //   809: ifne -> 1592
    //   812: goto -> 819
    //   815: invokestatic a : (Ljava/lang/Throwable;)Ljava/lang/Throwable;
    //   818: athrow
    //   819: aload_3
    //   820: getstatic burp/Zzmu.ZF : Ljava/lang/String;
    //   823: getstatic burp/Zg6f.Zl : Ljava/lang/Object;
    //   826: checkcast java/math/BigInteger
    //   829: invokevirtual intValue : ()I
    //   832: bipush #32
    //   834: irem
    //   835: invokestatic abs : (I)I
    //   838: invokevirtual charAt : (I)C
    //   841: invokevirtual append : (C)Ljava/lang/StringBuilder;
    //   844: pop
    //   845: iload_2
    //   846: ifne -> 1592
    //   849: goto -> 856
    //   852: invokestatic a : (Ljava/lang/Throwable;)Ljava/lang/Throwable;
    //   855: athrow
    //   856: aload_3
    //   857: getstatic burp/Ze82.Zx : Ljava/lang/String;
    //   860: getstatic burp/Zb8y.ZI : Ljava/lang/Object;
    //   863: checkcast java/math/BigInteger
    //   866: invokevirtual intValue : ()I
    //   869: bipush #32
    //   871: irem
    //   872: invokestatic abs : (I)I
    //   875: invokevirtual charAt : (I)C
    //   878: invokevirtual append : (C)Ljava/lang/StringBuilder;
    //   881: pop
    //   882: iload_2
    //   883: ifne -> 1592
    //   886: goto -> 893
    //   889: invokestatic a : (Ljava/lang/Throwable;)Ljava/lang/Throwable;
    //   892: athrow
    //   893: aload_3
    //   894: getstatic burp/Zlr.ZO : Ljava/lang/String;
    //   897: getstatic burp/Zg4k.ZE : Ljava/lang/Object;
    //   900: checkcast java/math/BigInteger
    //   903: invokevirtual intValue : ()I
    //   906: bipush #32
    //   908: irem
    //   909: invokestatic abs : (I)I
    //   912: invokevirtual charAt : (I)C
    //   915: invokevirtual append : (C)Ljava/lang/StringBuilder;
    //   918: pop
    //   919: iload_2
    //   920: ifne -> 1592
    //   923: goto -> 930
    //   926: invokestatic a : (Ljava/lang/Throwable;)Ljava/lang/Throwable;
    //   929: athrow
    //   930: aload_3
    //   931: getstatic burp/Zxo7.Zl : Ljava/lang/String;
    //   934: getstatic burp/Zsj5.Zv : Ljava/lang/Object;
    //   937: checkcast java/math/BigInteger
    //   940: invokevirtual intValue : ()I
    //   943: bipush #32
    //   945: irem
    //   946: invokestatic abs : (I)I
    //   949: invokevirtual charAt : (I)C
    //   952: invokevirtual append : (C)Ljava/lang/StringBuilder;
    //   955: pop
    //   956: iload_2
    //   957: ifne -> 1592
    //   960: goto -> 967
    //   963: invokestatic a : (Ljava/lang/Throwable;)Ljava/lang/Throwable;
    //   966: athrow
    //   967: aload_3
    //   968: getstatic burp/Zkt7.ZM : Ljava/lang/String;
    //   971: getstatic burp/Zkjr.Zw : Ljava/lang/Object;
    //   974: checkcast java/math/BigInteger
    //   977: invokevirtual intValue : ()I
    //   980: bipush #32
    //   982: irem
    //   983: invokestatic abs : (I)I
    //   986: invokevirtual charAt : (I)C
    //   989: invokevirtual append : (C)Ljava/lang/StringBuilder;
    //   992: pop
    //   993: iload_2
    //   994: ifne -> 1592
    //   997: goto -> 1004
    //   1000: invokestatic a : (Ljava/lang/Throwable;)Ljava/lang/Throwable;
    //   1003: athrow
    //   1004: aload_3
    //   1005: getstatic burp/Zeoy.ZS : Ljava/lang/String;
    //   1008: getstatic burp/Zlx5.Zp : Ljava/lang/Object;
    //   1011: checkcast java/math/BigInteger
    //   1014: invokevirtual intValue : ()I
    //   1017: bipush #32
    //   1019: irem
    //   1020: invokestatic abs : (I)I
    //   1023: invokevirtual charAt : (I)C
    //   1026: invokevirtual append : (C)Ljava/lang/StringBuilder;
    //   1029: pop
    //   1030: iload_2
    //   1031: ifne -> 1592
    //   1034: goto -> 1041
    //   1037: invokestatic a : (Ljava/lang/Throwable;)Ljava/lang/Throwable;
    //   1040: athrow
    //   1041: aload_3
    //   1042: getstatic burp/Zlem.Zl : Ljava/lang/String;
    //   1045: getstatic burp/Zlpj.Zc : Ljava/lang/Object;
    //   1048: checkcast java/math/BigInteger
    //   1051: invokevirtual intValue : ()I
    //   1054: bipush #32
    //   1056: irem
    //   1057: invokestatic abs : (I)I
    //   1060: invokevirtual charAt : (I)C
    //   1063: invokevirtual append : (C)Ljava/lang/StringBuilder;
    //   1066: pop
    //   1067: iload_2
    //   1068: ifne -> 1592
    //   1071: goto -> 1078
    //   1074: invokestatic a : (Ljava/lang/Throwable;)Ljava/lang/Throwable;
    //   1077: athrow
    //   1078: aload_3
    //   1079: getstatic burp/Zix.Zp : Ljava/lang/String;
    //   1082: getstatic burp/Zmr7.ZO : Ljava/lang/Object;
    //   1085: checkcast java/math/BigInteger
    //   1088: invokevirtual intValue : ()I
    //   1091: bipush #32
    //   1093: irem
    //   1094: invokestatic abs : (I)I
    //   1097: invokevirtual charAt : (I)C
    //   1100: invokevirtual append : (C)Ljava/lang/StringBuilder;
    //   1103: pop
    //   1104: iload_2
    //   1105: ifne -> 1592
    //   1108: goto -> 1115
    //   1111: invokestatic a : (Ljava/lang/Throwable;)Ljava/lang/Throwable;
    //   1114: athrow
    //   1115: aload_3
    //   1116: getstatic burp/Zlo5.ZJ : Ljava/lang/String;
    //   1119: getstatic burp/Zgzv.Zb : Ljava/lang/Object;
    //   1122: checkcast java/math/BigInteger
    //   1125: invokevirtual intValue : ()I
    //   1128: bipush #32
    //   1130: irem
    //   1131: invokestatic abs : (I)I
    //   1134: invokevirtual charAt : (I)C
    //   1137: invokevirtual append : (C)Ljava/lang/StringBuilder;
    //   1140: pop
    //   1141: iload_2
    //   1142: ifne -> 1592
    //   1145: goto -> 1152
    //   1148: invokestatic a : (Ljava/lang/Throwable;)Ljava/lang/Throwable;
    //   1151: athrow
    //   1152: aload_3
    //   1153: getstatic burp/Zr1z.ZB : Ljava/lang/String;
    //   1156: getstatic burp/Zrtc.Zr : Ljava/lang/Object;
    //   1159: checkcast java/math/BigInteger
    //   1162: invokevirtual intValue : ()I
    //   1165: bipush #32
    //   1167: irem
    //   1168: invokestatic abs : (I)I
    //   1171: invokevirtual charAt : (I)C
    //   1174: invokevirtual append : (C)Ljava/lang/StringBuilder;
    //   1177: pop
    //   1178: iload_2
    //   1179: ifne -> 1592
    //   1182: goto -> 1189
    //   1185: invokestatic a : (Ljava/lang/Throwable;)Ljava/lang/Throwable;
    //   1188: athrow
    //   1189: aload_3
    //   1190: getstatic burp/Zzmw.Zd : Ljava/lang/String;
    //   1193: getstatic burp/Zlck.Zr : Ljava/lang/Object;
    //   1196: checkcast java/math/BigInteger
    //   1199: invokevirtual intValue : ()I
    //   1202: bipush #32
    //   1204: irem
    //   1205: invokestatic abs : (I)I
    //   1208: invokevirtual charAt : (I)C
    //   1211: invokevirtual append : (C)Ljava/lang/StringBuilder;
    //   1214: pop
    //   1215: iload_2
    //   1216: ifne -> 1592
    //   1219: goto -> 1226
    //   1222: invokestatic a : (Ljava/lang/Throwable;)Ljava/lang/Throwable;
    //   1225: athrow
    //   1226: aload_3
    //   1227: getstatic burp/Zs0_.ZH : Ljava/lang/String;
    //   1230: getstatic burp/Zmr7.ZO : Ljava/lang/Object;
    //   1233: checkcast java/math/BigInteger
    //   1236: invokevirtual intValue : ()I
    //   1239: bipush #32
    //   1241: irem
    //   1242: invokestatic abs : (I)I
    //   1245: invokevirtual charAt : (I)C
    //   1248: invokevirtual append : (C)Ljava/lang/StringBuilder;
    //   1251: pop
    //   1252: iload_2
    //   1253: ifne -> 1592
    //   1256: goto -> 1263
    //   1259: invokestatic a : (Ljava/lang/Throwable;)Ljava/lang/Throwable;
    //   1262: athrow
    //   1263: aload_3
    //   1264: getstatic burp/Zl06.ZL : Ljava/lang/String;
    //   1267: getstatic burp/Zix.ZO : Ljava/lang/Object;
    //   1270: checkcast java/math/BigInteger
    //   1273: invokevirtual intValue : ()I
    //   1276: bipush #32
    //   1278: irem
    //   1279: invokestatic abs : (I)I
    //   1282: invokevirtual charAt : (I)C
    //   1285: invokevirtual append : (C)Ljava/lang/StringBuilder;
    //   1288: pop
    //   1289: iload_2
    //   1290: ifne -> 1592
    //   1293: goto -> 1300
    //   1296: invokestatic a : (Ljava/lang/Throwable;)Ljava/lang/Throwable;
    //   1299: athrow
    //   1300: aload_3
    //   1301: getstatic burp/Zt5j.ZR : Ljava/lang/String;
    //   1304: getstatic burp/Ztj5.Zj : Ljava/lang/Object;
    //   1307: checkcast java/math/BigInteger
    //   1310: invokevirtual intValue : ()I
    //   1313: bipush #32
    //   1315: irem
    //   1316: invokestatic abs : (I)I
    //   1319: invokevirtual charAt : (I)C
    //   1322: invokevirtual append : (C)Ljava/lang/StringBuilder;
    //   1325: pop
    //   1326: iload_2
    //   1327: ifne -> 1592
    //   1330: goto -> 1337
    //   1333: invokestatic a : (Ljava/lang/Throwable;)Ljava/lang/Throwable;
    //   1336: athrow
    //   1337: aload_3
    //   1338: getstatic burp/Ztj5.Zt : Ljava/lang/String;
    //   1341: getstatic burp/Zm4i.Zr : Ljava/lang/Object;
    //   1344: checkcast java/math/BigInteger
    //   1347: invokevirtual intValue : ()I
    //   1350: bipush #32
    //   1352: irem
    //   1353: invokestatic abs : (I)I
    //   1356: invokevirtual charAt : (I)C
    //   1359: invokevirtual append : (C)Ljava/lang/StringBuilder;
    //   1362: pop
    //   1363: iload_2
    //   1364: ifne -> 1592
    //   1367: goto -> 1374
    //   1370: invokestatic a : (Ljava/lang/Throwable;)Ljava/lang/Throwable;
    //   1373: athrow
    //   1374: aload_3
    //   1375: getstatic burp/Zess.Zc : Ljava/lang/String;
    //   1378: getstatic burp/Zv8c.Zx : Ljava/lang/Object;
    //   1381: checkcast java/math/BigInteger
    //   1384: invokevirtual intValue : ()I
    //   1387: bipush #32
    //   1389: irem
    //   1390: invokestatic abs : (I)I
    //   1393: invokevirtual charAt : (I)C
    //   1396: invokevirtual append : (C)Ljava/lang/StringBuilder;
    //   1399: pop
    //   1400: iload_2
    //   1401: ifne -> 1592
    //   1404: goto -> 1411
    //   1407: invokestatic a : (Ljava/lang/Throwable;)Ljava/lang/Throwable;
    //   1410: athrow
    //   1411: aload_3
    //   1412: getstatic burp/Ze64.ZM : Ljava/lang/String;
    //   1415: getstatic burp/Zix.ZO : Ljava/lang/Object;
    //   1418: checkcast java/math/BigInteger
    //   1421: invokevirtual intValue : ()I
    //   1424: bipush #32
    //   1426: irem
    //   1427: invokestatic abs : (I)I
    //   1430: invokevirtual charAt : (I)C
    //   1433: invokevirtual append : (C)Ljava/lang/StringBuilder;
    //   1436: pop
    //   1437: iload_2
    //   1438: ifne -> 1592
    //   1441: goto -> 1448
    //   1444: invokestatic a : (Ljava/lang/Throwable;)Ljava/lang/Throwable;
    //   1447: athrow
    //   1448: aload_3
    //   1449: getstatic burp/Zix.Zp : Ljava/lang/String;
    //   1452: getstatic burp/Zlo5.Zf : Ljava/lang/Object;
    //   1455: checkcast java/math/BigInteger
    //   1458: invokevirtual intValue : ()I
    //   1461: bipush #32
    //   1463: irem
    //   1464: invokestatic abs : (I)I
    //   1467: invokevirtual charAt : (I)C
    //   1470: invokevirtual append : (C)Ljava/lang/StringBuilder;
    //   1473: pop
    //   1474: iload_2
    //   1475: ifne -> 1592
    //   1478: goto -> 1485
    //   1481: invokestatic a : (Ljava/lang/Throwable;)Ljava/lang/Throwable;
    //   1484: athrow
    //   1485: aload_3
    //   1486: getstatic burp/Zlh8.ZY : Ljava/lang/String;
    //   1489: getstatic burp/Ze8i.Zq : Ljava/lang/Object;
    //   1492: checkcast java/math/BigInteger
    //   1495: invokevirtual intValue : ()I
    //   1498: bipush #32
    //   1500: irem
    //   1501: invokestatic abs : (I)I
    //   1504: invokevirtual charAt : (I)C
    //   1507: invokevirtual append : (C)Ljava/lang/StringBuilder;
    //   1510: pop
    //   1511: iload_2
    //   1512: ifne -> 1592
    //   1515: goto -> 1522
    //   1518: invokestatic a : (Ljava/lang/Throwable;)Ljava/lang/Throwable;
    //   1521: athrow
    //   1522: aload_3
    //   1523: getstatic burp/Zsqy.Zo : Ljava/lang/String;
    //   1526: getstatic burp/Zx6d.ZU : Ljava/lang/Object;
    //   1529: checkcast java/math/BigInteger
    //   1532: invokevirtual intValue : ()I
    //   1535: bipush #32
    //   1537: irem
    //   1538: invokestatic abs : (I)I
    //   1541: invokevirtual charAt : (I)C
    //   1544: invokevirtual append : (C)Ljava/lang/StringBuilder;
    //   1547: pop
    //   1548: iload_2
    //   1549: ifne -> 1592
    //   1552: goto -> 1559
    //   1555: invokestatic a : (Ljava/lang/Throwable;)Ljava/lang/Throwable;
    //   1558: athrow
    //   1559: aload_3
    //   1560: getstatic burp/Zs0_.ZH : Ljava/lang/String;
    //   1563: getstatic burp/Zstb.ZC : Ljava/lang/Object;
    //   1566: checkcast java/math/BigInteger
    //   1569: invokevirtual intValue : ()I
    //   1572: bipush #32
    //   1574: irem
    //   1575: invokestatic abs : (I)I
    //   1578: invokevirtual charAt : (I)C
    //   1581: invokevirtual append : (C)Ljava/lang/StringBuilder;
    //   1584: pop
    //   1585: goto -> 1592
    //   1588: invokestatic a : (Ljava/lang/Throwable;)Ljava/lang/Throwable;
    //   1591: athrow
    //   1592: iinc #4, 1
    //   1595: iload_2
    //   1596: ifne -> 261
    //   1599: aload_3
    //   1600: invokevirtual toString : ()Ljava/lang/String;
    //   1603: putstatic burp/Zmx6.ZG : Ljava/lang/String;
    //   1606: getstatic burp/Zkb_.ZG : Ljava/lang/Object;
    //   1609: checkcast java/math/BigInteger
    //   1612: invokevirtual toByteArray : ()[B
    //   1615: astore #4
    //   1617: aload #4
    //   1619: arraylength
    //   1620: bipush #8
    //   1622: iadd
    //   1623: bipush #6
    //   1625: ishr
    //   1626: iconst_1
    //   1627: iadd
    //   1628: bipush #16
    //   1630: imul
    //   1631: newarray int
    //   1633: astore #6
    //   1635: iconst_0
    //   1636: istore #7
    //   1638: iload #7
    //   1640: aload #4
    //   1642: arraylength
    //   1643: if_icmpge -> 1687
    //   1646: aload #4
    //   1648: iload #7
    //   1650: baload
    //   1651: sipush #255
    //   1654: iand
    //   1655: istore #8
    //   1657: aload #6
    //   1659: iload #7
    //   1661: iconst_2
    //   1662: ishr
    //   1663: dup2
    //   1664: iaload
    //   1665: iload #8
    //   1667: bipush #24
    //   1669: iload #7
    //   1671: iconst_4
    //   1672: irem
    //   1673: bipush #8
    //   1675: imul
    //   1676: isub
    //   1677: ishl
    //   1678: ior
    //   1679: iastore
    //   1680: iinc #7, 1
    //   1683: iload_2
    //   1684: ifne -> 1638
    //   1687: aload #6
    //   1689: iload #7
    //   1691: iconst_2
    //   1692: ishr
    //   1693: dup2
    //   1694: iaload
    //   1695: sipush #128
    //   1698: bipush #24
    //   1700: iload #7
    //   1702: iconst_4
    //   1703: irem
    //   1704: bipush #8
    //   1706: imul
    //   1707: isub
    //   1708: ishl
    //   1709: ior
    //   1710: iastore
    //   1711: aload #6
    //   1713: aload #6
    //   1715: arraylength
    //   1716: iconst_1
    //   1717: isub
    //   1718: aload #4
    //   1720: arraylength
    //   1721: bipush #8
    //   1723: imul
    //   1724: iastore
    //   1725: bipush #80
    //   1727: newarray int
    //   1729: astore #8
    //   1731: ldc 1732584193
    //   1733: istore #9
    //   1735: ldc -271733879
    //   1737: istore #10
    //   1739: ldc -1732584194
    //   1741: istore #11
    //   1743: ldc 271733878
    //   1745: istore #12
    //   1747: ldc -1009589776
    //   1749: istore #13
    //   1751: iconst_0
    //   1752: istore #7
    //   1754: iload #7
    //   1756: aload #6
    //   1758: arraylength
    //   1759: if_icmpge -> 2081
    //   1762: iload #9
    //   1764: istore #14
    //   1766: iload #10
    //   1768: istore #15
    //   1770: iload #11
    //   1772: istore #16
    //   1774: iload #12
    //   1776: istore #17
    //   1778: iload #13
    //   1780: istore #18
    //   1782: iconst_0
    //   1783: istore #19
    //   1785: iload #19
    //   1787: bipush #80
    //   1789: if_icmpge -> 2039
    //   1792: iload #19
    //   1794: bipush #16
    //   1796: if_icmpge -> 1823
    //   1799: aload #8
    //   1801: iload #19
    //   1803: aload #6
    //   1805: iload #7
    //   1807: iload #19
    //   1809: iadd
    //   1810: iaload
    //   1811: iastore
    //   1812: iload_2
    //   1813: ifne -> 1878
    //   1816: goto -> 1823
    //   1819: invokestatic a : (Ljava/lang/Throwable;)Ljava/lang/Throwable;
    //   1822: athrow
    //   1823: aload #8
    //   1825: iload #19
    //   1827: iconst_3
    //   1828: isub
    //   1829: iaload
    //   1830: aload #8
    //   1832: iload #19
    //   1834: bipush #8
    //   1836: isub
    //   1837: iaload
    //   1838: ixor
    //   1839: aload #8
    //   1841: iload #19
    //   1843: bipush #14
    //   1845: isub
    //   1846: iaload
    //   1847: ixor
    //   1848: aload #8
    //   1850: iload #19
    //   1852: bipush #16
    //   1854: isub
    //   1855: iaload
    //   1856: ixor
    //   1857: istore #20
    //   1859: iload #20
    //   1861: iconst_1
    //   1862: ishl
    //   1863: iload #20
    //   1865: bipush #31
    //   1867: iushr
    //   1868: ior
    //   1869: istore #21
    //   1871: aload #8
    //   1873: iload #19
    //   1875: iload #21
    //   1877: iastore
    //   1878: iload #9
    //   1880: iconst_5
    //   1881: ishl
    //   1882: iload #9
    //   1884: bipush #27
    //   1886: iushr
    //   1887: ior
    //   1888: istore #20
    //   1890: iload #20
    //   1892: iload #13
    //   1894: iadd
    //   1895: aload #8
    //   1897: iload #19
    //   1899: iaload
    //   1900: iadd
    //   1901: iload #19
    //   1903: bipush #20
    //   1905: if_icmpge -> 1931
    //   1908: ldc 1518500249
    //   1910: iload #10
    //   1912: iload #11
    //   1914: iand
    //   1915: iload #10
    //   1917: iconst_m1
    //   1918: ixor
    //   1919: iload #12
    //   1921: iand
    //   1922: ior
    //   1923: iadd
    //   1924: goto -> 2001
    //   1927: invokestatic a : (Ljava/lang/Throwable;)Ljava/lang/Throwable;
    //   1930: athrow
    //   1931: iload #19
    //   1933: bipush #40
    //   1935: if_icmpge -> 1956
    //   1938: ldc 1859775393
    //   1940: iload #10
    //   1942: iload #11
    //   1944: ixor
    //   1945: iload #12
    //   1947: ixor
    //   1948: iadd
    //   1949: goto -> 2001
    //   1952: invokestatic a : (Ljava/lang/Throwable;)Ljava/lang/Throwable;
    //   1955: athrow
    //   1956: iload #19
    //   1958: bipush #60
    //   1960: if_icmpge -> 1990
    //   1963: ldc -1894007588
    //   1965: iload #10
    //   1967: iload #11
    //   1969: iand
    //   1970: iload #10
    //   1972: iload #12
    //   1974: iand
    //   1975: ior
    //   1976: iload #11
    //   1978: iload #12
    //   1980: iand
    //   1981: ior
    //   1982: iadd
    //   1983: goto -> 2001
    //   1986: invokestatic a : (Ljava/lang/Throwable;)Ljava/lang/Throwable;
    //   1989: athrow
    //   1990: ldc -899497514
    //   1992: iload #10
    //   1994: iload #11
    //   1996: ixor
    //   1997: iload #12
    //   1999: ixor
    //   2000: iadd
    //   2001: iadd
    //   2002: istore #21
    //   2004: iload #12
    //   2006: istore #13
    //   2008: iload #11
    //   2010: istore #12
    //   2012: iload #10
    //   2014: bipush #30
    //   2016: ishl
    //   2017: iload #10
    //   2019: iconst_2
    //   2020: iushr
    //   2021: ior
    //   2022: istore #11
    //   2024: iload #9
    //   2026: istore #10
    //   2028: iload #21
    //   2030: istore #9
    //   2032: iinc #19, 1
    //   2035: iload_2
    //   2036: ifne -> 1785
    //   2039: iload #9
    //   2041: iload #14
    //   2043: iadd
    //   2044: istore #9
    //   2046: iload #10
    //   2048: iload #15
    //   2050: iadd
    //   2051: istore #10
    //   2053: iload #11
    //   2055: iload #16
    //   2057: iadd
    //   2058: istore #11
    //   2060: iload #12
    //   2062: iload #17
    //   2064: iadd
    //   2065: istore #12
    //   2067: iload #13
    //   2069: iload #18
    //   2071: iadd
    //   2072: istore #13
    //   2074: iinc #7, 16
    //   2077: iload_2
    //   2078: ifne -> 1754
    //   2081: iconst_5
    //   2082: newarray int
    //   2084: dup
    //   2085: iconst_0
    //   2086: iload #9
    //   2088: iastore
    //   2089: dup
    //   2090: iconst_1
    //   2091: iload #10
    //   2093: iastore
    //   2094: dup
    //   2095: iconst_2
    //   2096: iload #11
    //   2098: iastore
    //   2099: dup
    //   2100: iconst_3
    //   2101: iload #12
    //   2103: iastore
    //   2104: dup
    //   2105: iconst_4
    //   2106: iload #13
    //   2108: iastore
    //   2109: astore #14
    //   2111: bipush #20
    //   2113: newarray byte
    //   2115: astore #15
    //   2117: iconst_0
    //   2118: istore #16
    //   2120: iload #16
    //   2122: bipush #20
    //   2124: if_icmpge -> 2165
    //   2127: aload #14
    //   2129: iload #16
    //   2131: iconst_4
    //   2132: idiv
    //   2133: iaload
    //   2134: istore #17
    //   2136: iconst_3
    //   2137: iload #16
    //   2139: iconst_4
    //   2140: irem
    //   2141: isub
    //   2142: bipush #8
    //   2144: imul
    //   2145: istore #18
    //   2147: aload #15
    //   2149: iload #16
    //   2151: iload #17
    //   2153: iload #18
    //   2155: iushr
    //   2156: i2b
    //   2157: bastore
    //   2158: iinc #16, 1
    //   2161: iload_2
    //   2162: ifne -> 2120
    //   2165: aload #15
    //   2167: astore #5
    //   2169: sipush #6309
    //   2172: new java/math/BigInteger
    //   2175: dup
    //   2176: aload #5
    //   2178: invokespecial <init> : ([B)V
    //   2181: invokevirtual abs : ()Ljava/math/BigInteger;
    //   2184: putstatic burp/Zkb_.ZG : Ljava/lang/Object;
    //   2187: sipush #18683
    //   2190: invokestatic a : (II)Ljava/lang/String;
    //   2193: iconst_1
    //   2194: ldc burp/Zrug
    //   2196: invokevirtual getClassLoader : ()Ljava/lang/ClassLoader;
    //   2199: invokestatic forName : (Ljava/lang/String;ZLjava/lang/ClassLoader;)Ljava/lang/Class;
    //   2202: invokevirtual getDeclaredFields : ()[Ljava/lang/reflect/Field;
    //   2205: astore #4
    //   2207: aload #4
    //   2209: arraylength
    //   2210: istore #5
    //   2212: iconst_0
    //   2213: istore #6
    //   2215: iload #6
    //   2217: iload #5
    //   2219: if_icmpge -> 2357
    //   2222: aload #4
    //   2224: iload #6
    //   2226: aaload
    //   2227: astore #7
    //   2229: aload #7
    //   2231: invokevirtual getModifiers : ()I
    //   2234: invokestatic isStatic : (I)Z
    //   2237: ifne -> 2247
    //   2240: goto -> 2350
    //   2243: invokestatic a : (Ljava/lang/Throwable;)Ljava/lang/Throwable;
    //   2246: athrow
    //   2247: aload #7
    //   2249: invokevirtual getType : ()Ljava/lang/Class;
    //   2252: astore #8
    //   2254: aload #8
    //   2256: ifnull -> 2337
    //   2259: aload #8
    //   2261: invokevirtual isPrimitive : ()Z
    //   2264: ifne -> 2337
    //   2267: goto -> 2274
    //   2270: invokestatic a : (Ljava/lang/Throwable;)Ljava/lang/Throwable;
    //   2273: athrow
    //   2274: aload #8
    //   2276: invokevirtual getPackage : ()Ljava/lang/Package;
    //   2279: ifnull -> 2337
    //   2282: goto -> 2289
    //   2285: invokestatic a : (Ljava/lang/Throwable;)Ljava/lang/Throwable;
    //   2288: athrow
    //   2289: aload #8
    //   2291: invokevirtual getPackage : ()Ljava/lang/Package;
    //   2294: invokevirtual getName : ()Ljava/lang/String;
    //   2297: ifnull -> 2337
    //   2300: goto -> 2307
    //   2303: invokestatic a : (Ljava/lang/Throwable;)Ljava/lang/Throwable;
    //   2306: athrow
    //   2307: aload #8
    //   2309: invokevirtual getPackage : ()Ljava/lang/Package;
    //   2312: invokevirtual getName : ()Ljava/lang/String;
    //   2315: sipush #6317
    //   2318: sipush #12342
    //   2321: invokestatic a : (II)Ljava/lang/String;
    //   2324: invokevirtual startsWith : (Ljava/lang/String;)Z
    //   2327: ifne -> 2337
    //   2330: goto -> 2337
    //   2333: invokestatic a : (Ljava/lang/Throwable;)Ljava/lang/Throwable;
    //   2336: athrow
    //   2337: aload #7
    //   2339: iconst_1
    //   2340: invokevirtual setAccessible : (Z)V
    //   2343: aload #7
    //   2345: aconst_null
    //   2346: invokevirtual get : (Ljava/lang/Object;)Ljava/lang/Object;
    //   2349: pop
    //   2350: iinc #6, 1
    //   2353: iload_2
    //   2354: ifne -> 2215
    //   2357: sipush #6316
    //   2360: sipush #-15919
    //   2363: invokestatic a : (II)Ljava/lang/String;
    //   2366: invokestatic forName : (Ljava/lang/String;)Ljava/lang/Class;
    //   2369: invokevirtual getDeclaredMethods : ()[Ljava/lang/reflect/Method;
    //   2372: astore #4
    //   2374: aload #4
    //   2376: arraylength
    //   2377: istore #5
    //   2379: iconst_0
    //   2380: istore #6
    //   2382: iload #6
    //   2384: iload #5
    //   2386: if_icmpge -> 2519
    //   2389: aload #4
    //   2391: iload #6
    //   2393: aaload
    //   2394: astore #7
    //   2396: aload #7
    //   2398: invokevirtual getParameterTypes : ()[Ljava/lang/Class;
    //   2401: pop
    //   2402: aload #7
    //   2404: invokevirtual getModifiers : ()I
    //   2407: invokestatic isStatic : (I)Z
    //   2410: ifeq -> 2505
    //   2413: aload #7
    //   2415: invokevirtual getParameterTypes : ()[Ljava/lang/Class;
    //   2418: arraylength
    //   2419: iconst_2
    //   2420: if_icmpne -> 2505
    //   2423: goto -> 2430
    //   2426: invokestatic a : (Ljava/lang/Throwable;)Ljava/lang/Throwable;
    //   2429: athrow
    //   2430: aload #7
    //   2432: invokevirtual getReturnType : ()Ljava/lang/Class;
    //   2435: getstatic java/lang/Void.TYPE : Ljava/lang/Class;
    //   2438: invokevirtual equals : (Ljava/lang/Object;)Z
    //   2441: ifeq -> 2505
    //   2444: goto -> 2451
    //   2447: invokestatic a : (Ljava/lang/Throwable;)Ljava/lang/Throwable;
    //   2450: athrow
    //   2451: aload #7
    //   2453: iconst_1
    //   2454: invokevirtual setAccessible : (Z)V
    //   2457: aload #7
    //   2459: aconst_null
    //   2460: iconst_2
    //   2461: anewarray java/lang/Object
    //   2464: dup
    //   2465: iconst_0
    //   2466: aload_0
    //   2467: aastore
    //   2468: dup
    //   2469: iconst_1
    //   2470: aload_1
    //   2471: ifnonnull -> 2489
    //   2474: goto -> 2481
    //   2477: invokestatic a : (Ljava/lang/Throwable;)Ljava/lang/Throwable;
    //   2480: athrow
    //   2481: aload_1
    //   2482: goto -> 2496
    //   2485: invokestatic a : (Ljava/lang/Throwable;)Ljava/lang/Throwable;
    //   2488: athrow
    //   2489: aload_1
    //   2490: checkcast [B
    //   2493: invokevirtual clone : ()Ljava/lang/Object;
    //   2496: aastore
    //   2497: invokevirtual invoke : (Ljava/lang/Object;[Ljava/lang/Object;)Ljava/lang/Object;
    //   2500: pop
    //   2501: iload_2
    //   2502: ifne -> 2519
    //   2505: iinc #6, 1
    //   2508: iload_2
    //   2509: ifne -> 2382
    //   2512: goto -> 2519
    //   2515: invokestatic a : (Ljava/lang/Throwable;)Ljava/lang/Throwable;
    //   2518: athrow
    //   2519: getstatic burp/Ztkh.Zh : Ljava/lang/Object;
    //   2522: checkcast java/math/BigInteger
    //   2525: invokevirtual intValue : ()I
    //   2528: i2l
    //   2529: invokestatic currentTimeMillis : ()J
    //   2532: ladd
    //   2533: getstatic burp/Zsbt.Zl : Ljava/lang/Object;
    //   2536: checkcast java/math/BigInteger
    //   2539: invokevirtual intValue : ()I
    //   2542: i2l
    //   2543: lcmp
    //   2544: ifge -> 2882
    //   2547: sipush #6313
    //   2550: sipush #-17558
    //   2553: invokestatic a : (II)Ljava/lang/String;
    //   2556: iconst_1
    //   2557: ldc burp/Zti7
    //   2559: invokevirtual getClassLoader : ()Ljava/lang/ClassLoader;
    //   2562: invokestatic forName : (Ljava/lang/String;ZLjava/lang/ClassLoader;)Ljava/lang/Class;
    //   2565: invokevirtual getDeclaredFields : ()[Ljava/lang/reflect/Field;
    //   2568: astore #4
    //   2570: aload #4
    //   2572: arraylength
    //   2573: istore #5
    //   2575: iconst_0
    //   2576: istore #6
    //   2578: iload #6
    //   2580: iload #5
    //   2582: if_icmpge -> 2720
    //   2585: aload #4
    //   2587: iload #6
    //   2589: aaload
    //   2590: astore #7
    //   2592: aload #7
    //   2594: invokevirtual getModifiers : ()I
    //   2597: invokestatic isStatic : (I)Z
    //   2600: ifne -> 2610
    //   2603: goto -> 2713
    //   2606: invokestatic a : (Ljava/lang/Throwable;)Ljava/lang/Throwable;
    //   2609: athrow
    //   2610: aload #7
    //   2612: invokevirtual getType : ()Ljava/lang/Class;
    //   2615: astore #8
    //   2617: aload #8
    //   2619: ifnull -> 2700
    //   2622: aload #8
    //   2624: invokevirtual isPrimitive : ()Z
    //   2627: ifne -> 2700
    //   2630: goto -> 2637
    //   2633: invokestatic a : (Ljava/lang/Throwable;)Ljava/lang/Throwable;
    //   2636: athrow
    //   2637: aload #8
    //   2639: invokevirtual getPackage : ()Ljava/lang/Package;
    //   2642: ifnull -> 2700
    //   2645: goto -> 2652
    //   2648: invokestatic a : (Ljava/lang/Throwable;)Ljava/lang/Throwable;
    //   2651: athrow
    //   2652: aload #8
    //   2654: invokevirtual getPackage : ()Ljava/lang/Package;
    //   2657: invokevirtual getName : ()Ljava/lang/String;
    //   2660: ifnull -> 2700
    //   2663: goto -> 2670
    //   2666: invokestatic a : (Ljava/lang/Throwable;)Ljava/lang/Throwable;
    //   2669: athrow
    //   2670: aload #8
    //   2672: invokevirtual getPackage : ()Ljava/lang/Package;
    //   2675: invokevirtual getName : ()Ljava/lang/String;
    //   2678: sipush #6308
    //   2681: sipush #-19862
    //   2684: invokestatic a : (II)Ljava/lang/String;
    //   2687: invokevirtual startsWith : (Ljava/lang/String;)Z
    //   2690: ifne -> 2700
    //   2693: goto -> 2700
    //   2696: invokestatic a : (Ljava/lang/Throwable;)Ljava/lang/Throwable;
    //   2699: athrow
    //   2700: aload #7
    //   2702: iconst_1
    //   2703: invokevirtual setAccessible : (Z)V
    //   2706: aload #7
    //   2708: aconst_null
    //   2709: invokevirtual get : (Ljava/lang/Object;)Ljava/lang/Object;
    //   2712: pop
    //   2713: iinc #6, 1
    //   2716: iload_2
    //   2717: ifne -> 2578
    //   2720: sipush #6314
    //   2723: sipush #219
    //   2726: invokestatic a : (II)Ljava/lang/String;
    //   2729: invokestatic forName : (Ljava/lang/String;)Ljava/lang/Class;
    //   2732: invokevirtual getDeclaredMethods : ()[Ljava/lang/reflect/Method;
    //   2735: astore #4
    //   2737: aload #4
    //   2739: arraylength
    //   2740: istore #5
    //   2742: iconst_0
    //   2743: istore #6
    //   2745: iload #6
    //   2747: iload #5
    //   2749: if_icmpge -> 2882
    //   2752: aload #4
    //   2754: iload #6
    //   2756: aaload
    //   2757: astore #7
    //   2759: aload #7
    //   2761: invokevirtual getParameterTypes : ()[Ljava/lang/Class;
    //   2764: pop
    //   2765: aload #7
    //   2767: invokevirtual getModifiers : ()I
    //   2770: invokestatic isStatic : (I)Z
    //   2773: ifeq -> 2868
    //   2776: aload #7
    //   2778: invokevirtual getParameterTypes : ()[Ljava/lang/Class;
    //   2781: arraylength
    //   2782: iconst_2
    //   2783: if_icmpne -> 2868
    //   2786: goto -> 2793
    //   2789: invokestatic a : (Ljava/lang/Throwable;)Ljava/lang/Throwable;
    //   2792: athrow
    //   2793: aload #7
    //   2795: invokevirtual getReturnType : ()Ljava/lang/Class;
    //   2798: getstatic java/lang/Void.TYPE : Ljava/lang/Class;
    //   2801: invokevirtual equals : (Ljava/lang/Object;)Z
    //   2804: ifeq -> 2868
    //   2807: goto -> 2814
    //   2810: invokestatic a : (Ljava/lang/Throwable;)Ljava/lang/Throwable;
    //   2813: athrow
    //   2814: aload #7
    //   2816: iconst_1
    //   2817: invokevirtual setAccessible : (Z)V
    //   2820: aload #7
    //   2822: aconst_null
    //   2823: iconst_2
    //   2824: anewarray java/lang/Object
    //   2827: dup
    //   2828: iconst_0
    //   2829: aload_0
    //   2830: aastore
    //   2831: dup
    //   2832: iconst_1
    //   2833: aload_1
    //   2834: ifnonnull -> 2852
    //   2837: goto -> 2844
    //   2840: invokestatic a : (Ljava/lang/Throwable;)Ljava/lang/Throwable;
    //   2843: athrow
    //   2844: aload_1
    //   2845: goto -> 2859
    //   2848: invokestatic a : (Ljava/lang/Throwable;)Ljava/lang/Throwable;
    //   2851: athrow
    //   2852: aload_1
    //   2853: checkcast [B
    //   2856: invokevirtual clone : ()Ljava/lang/Object;
    //   2859: aastore
    //   2860: invokevirtual invoke : (Ljava/lang/Object;[Ljava/lang/Object;)Ljava/lang/Object;
    //   2863: pop
    //   2864: iload_2
    //   2865: ifne -> 2882
    //   2868: iinc #6, 1
    //   2871: iload_2
    //   2872: ifne -> 2745
    //   2875: goto -> 2882
    //   2878: invokestatic a : (Ljava/lang/Throwable;)Ljava/lang/Throwable;
    //   2881: athrow
    //   2882: getstatic burp/Zb4a.Zi : Ljava/lang/String;
    //   2885: getstatic burp/Zs8y.ZG : Ljava/lang/Object;
    //   2888: checkcast java/math/BigInteger
    //   2891: invokevirtual intValue : ()I
    //   2894: bipush #32
    //   2896: irem
    //   2897: invokestatic abs : (I)I
    //   2900: invokevirtual charAt : (I)C
    //   2903: getstatic burp/Zkb_.ZR : Ljava/lang/String;
    //   2906: getstatic burp/Ztcv.ZY : Ljava/lang/Object;
    //   2909: checkcast java/math/BigInteger
    //   2912: invokevirtual intValue : ()I
    //   2915: bipush #32
    //   2917: irem
    //   2918: invokestatic abs : (I)I
    //   2921: invokevirtual charAt : (I)C
    //   2924: if_icmpgt -> 3031
    //   2927: getstatic burp/Zb4a.Zi : Ljava/lang/String;
    //   2930: getstatic burp/Ztfh.Zo : Ljava/lang/Object;
    //   2933: checkcast java/math/BigInteger
    //   2936: invokevirtual intValue : ()I
    //   2939: bipush #32
    //   2941: irem
    //   2942: invokestatic abs : (I)I
    //   2945: invokevirtual charAt : (I)C
    //   2948: getstatic burp/Zs2n.ZI : Ljava/lang/String;
    //   2951: getstatic burp/Ztlz.ZW : Ljava/lang/Object;
    //   2954: checkcast java/math/BigInteger
    //   2957: invokevirtual intValue : ()I
    //   2960: bipush #32
    //   2962: irem
    //   2963: invokestatic abs : (I)I
    //   2966: invokevirtual charAt : (I)C
    //   2969: if_icmpgt -> 3031
    //   2972: goto -> 2979
    //   2975: invokestatic a : (Ljava/lang/Throwable;)Ljava/lang/Throwable;
    //   2978: athrow
    //   2979: getstatic burp/Zt9_.Zf : Ljava/lang/String;
    //   2982: getstatic burp/Zzc_.Zi : Ljava/lang/Object;
    //   2985: checkcast java/math/BigInteger
    //   2988: invokevirtual intValue : ()I
    //   2991: bipush #32
    //   2993: irem
    //   2994: invokestatic abs : (I)I
    //   2997: invokevirtual charAt : (I)C
    //   3000: getstatic burp/Zrtv.ZA : Ljava/lang/String;
    //   3003: getstatic burp/Ze54.Zx : Ljava/lang/Object;
    //   3006: checkcast java/math/BigInteger
    //   3009: invokevirtual intValue : ()I
    //   3012: bipush #32
    //   3014: irem
    //   3015: invokestatic abs : (I)I
    //   3018: invokevirtual charAt : (I)C
    //   3021: if_icmpgt -> 3039
    //   3024: goto -> 3031
    //   3027: invokestatic a : (Ljava/lang/Throwable;)Ljava/lang/Throwable;
    //   3030: athrow
    //   3031: iconst_1
    //   3032: goto -> 3040
    //   3035: invokestatic a : (Ljava/lang/Throwable;)Ljava/lang/Throwable;
    //   3038: athrow
    //   3039: iconst_0
    //   3040: ireturn
    //   3041: astore_3
    //   3042: new java/lang/Exception
    //   3045: dup
    //   3046: aload_3
    //   3047: invokevirtual getMessage : ()Ljava/lang/String;
    //   3050: invokespecial <init> : (Ljava/lang/String;)V
    //   3053: athrow
    // Exception table:
    //   from	to	target	type
    //   4	3040	3041	java/lang/Throwable
    //   268	442	445	java/lang/Throwable
    //   412	479	482	java/lang/Throwable
    //   449	516	519	java/lang/Throwable
    //   486	553	556	java/lang/Throwable
    //   523	590	593	java/lang/Throwable
    //   560	627	630	java/lang/Throwable
    //   597	664	667	java/lang/Throwable
    //   634	701	704	java/lang/Throwable
    //   671	738	741	java/lang/Throwable
    //   708	775	778	java/lang/Throwable
    //   745	812	815	java/lang/Throwable
    //   782	849	852	java/lang/Throwable
    //   819	886	889	java/lang/Throwable
    //   856	923	926	java/lang/Throwable
    //   893	960	963	java/lang/Throwable
    //   930	997	1000	java/lang/Throwable
    //   967	1034	1037	java/lang/Throwable
    //   1004	1071	1074	java/lang/Throwable
    //   1041	1108	1111	java/lang/Throwable
    //   1078	1145	1148	java/lang/Throwable
    //   1115	1182	1185	java/lang/Throwable
    //   1152	1219	1222	java/lang/Throwable
    //   1189	1256	1259	java/lang/Throwable
    //   1226	1293	1296	java/lang/Throwable
    //   1263	1330	1333	java/lang/Throwable
    //   1300	1367	1370	java/lang/Throwable
    //   1337	1404	1407	java/lang/Throwable
    //   1374	1441	1444	java/lang/Throwable
    //   1411	1478	1481	java/lang/Throwable
    //   1448	1515	1518	java/lang/Throwable
    //   1485	1552	1555	java/lang/Throwable
    //   1522	1585	1588	java/lang/Throwable
    //   1792	1816	1819	java/lang/Throwable
    //   1890	1927	1927	java/lang/Throwable
    //   1931	1952	1952	java/lang/Throwable
    //   1956	1986	1986	java/lang/Throwable
    //   2229	2243	2243	java/lang/Throwable
    //   2254	2267	2270	java/lang/Throwable
    //   2259	2282	2285	java/lang/Throwable
    //   2274	2300	2303	java/lang/Throwable
    //   2289	2330	2333	java/lang/Throwable
    //   2396	2423	2426	java/lang/Throwable
    //   2413	2444	2447	java/lang/Throwable
    //   2430	2474	2477	java/lang/Throwable
    //   2451	2485	2485	java/lang/Throwable
    //   2496	2512	2515	java/lang/Throwable
    //   2592	2606	2606	java/lang/Throwable
    //   2617	2630	2633	java/lang/Throwable
    //   2622	2645	2648	java/lang/Throwable
    //   2637	2663	2666	java/lang/Throwable
    //   2652	2693	2696	java/lang/Throwable
    //   2759	2786	2789	java/lang/Throwable
    //   2776	2807	2810	java/lang/Throwable
    //   2793	2837	2840	java/lang/Throwable
    //   2814	2848	2848	java/lang/Throwable
    //   2859	2875	2878	java/lang/Throwable
    //   2882	2972	2975	java/lang/Throwable
    //   2927	3024	3027	java/lang/Throwable
    //   2979	3035	3035	java/lang/Throwable
  }
  
  static void Zr(Object[] paramArrayOfObject, Object paramObject) throws Throwable {}
  
  static void ZM(Object paramObject) {
    Zk12.Zu = a(6319, -4939);
    Zk12.Zh = new BigInteger(a(6312, 5575));
    boolean bool = Zt2e.ZK();
    try {
      try {
        if (Zrpu.Zy.charAt(Math.abs(((BigInteger)Zlpj.Zc).intValue() % 32)) <= Zz20.ZX.charAt(Math.abs(((BigInteger)Zeqg.Zm).intValue() % 32))) {
          try {
            Zg7j.Zi(Class.forName(a(6318, 24682)));
            if (bool)
              Zx6d.Zu(Class.forName(a(6315, 14730))); 
          } catch (Throwable throwable) {
            throw a(null);
          } 
          return;
        } 
      } catch (Throwable throwable) {
        throw a(null);
      } 
      Zx6d.Zu(Class.forName(a(6315, 14730)));
    } catch (Throwable throwable) {}
  }
  
  static {
    // Byte code:
    //   0: bipush #11
    //   2: anewarray java/lang/String
    //   5: astore #5
    //   7: iconst_0
    //   8: istore_3
    //   9: ldc '*Kp\\t\\fp y(Bw\\rK\\t5b%\\tV\\t'CwM!\\r_\\f/3n%82qepH(C{4<oA1}\\r%>DY/hdc*oapdX\\tJ \\t\\t\\t w%'
    //   11: dup
    //   12: astore_2
    //   13: invokevirtual length : ()I
    //   16: istore #4
    //   18: iconst_4
    //   19: istore_1
    //   20: iconst_m1
    //   21: istore_0
    //   22: bipush #46
    //   24: iinc #0, 1
    //   27: aload_2
    //   28: iload_0
    //   29: dup
    //   30: iload_1
    //   31: iadd
    //   32: invokevirtual substring : (II)Ljava/lang/String;
    //   35: iconst_m1
    //   36: goto -> 141
    //   39: aload #5
    //   41: swap
    //   42: iload_3
    //   43: iinc #3, 1
    //   46: swap
    //   47: aastore
    //   48: iload_0
    //   49: iload_1
    //   50: iadd
    //   51: dup
    //   52: istore_0
    //   53: iload #4
    //   55: if_icmpge -> 67
    //   58: aload_2
    //   59: iload_0
    //   60: invokevirtual charAt : (I)C
    //   63: istore_1
    //   64: goto -> 22
    //   67: ldc 'ym Ec}bZ@<fzhz7\\fw#f'
    //   69: dup
    //   70: astore_2
    //   71: invokevirtual length : ()I
    //   74: istore #4
    //   76: iconst_4
    //   77: istore_1
    //   78: iconst_m1
    //   79: istore_0
    //   80: bipush #16
    //   82: iinc #0, 1
    //   85: aload_2
    //   86: iload_0
    //   87: dup
    //   88: iload_1
    //   89: iadd
    //   90: invokevirtual substring : (II)Ljava/lang/String;
    //   93: iconst_0
    //   94: goto -> 141
    //   97: aload #5
    //   99: swap
    //   100: iload_3
    //   101: iinc #3, 1
    //   104: swap
    //   105: aastore
    //   106: iload_0
    //   107: iload_1
    //   108: iadd
    //   109: dup
    //   110: istore_0
    //   111: iload #4
    //   113: if_icmpge -> 125
    //   116: aload_2
    //   117: iload_0
    //   118: invokevirtual charAt : (I)C
    //   121: istore_1
    //   122: goto -> 80
    //   125: aload #5
    //   127: putstatic burp/Zrof.a : [Ljava/lang/String;
    //   130: bipush #11
    //   132: anewarray java/lang/String
    //   135: putstatic burp/Zrof.b : [Ljava/lang/String;
    //   138: goto -> 300
    //   141: dup_x2
    //   142: pop
    //   143: invokevirtual toCharArray : ()[C
    //   146: dup_x1
    //   147: arraylength
    //   148: dup_x2
    //   149: pop
    //   150: iconst_0
    //   151: istore #6
    //   153: dup2_x1
    //   154: pop2
    //   155: dup_x2
    //   156: iconst_1
    //   157: if_icmpgt -> 260
    //   160: dup2
    //   161: swap
    //   162: iload #6
    //   164: dup2_x1
    //   165: caload
    //   166: swap
    //   167: iload #6
    //   169: bipush #7
    //   171: irem
    //   172: tableswitch default -> 242, 0 -> 212, 1 -> 217, 2 -> 222, 3 -> 227, 4 -> 232, 5 -> 237
    //   212: bipush #38
    //   214: goto -> 244
    //   217: bipush #125
    //   219: goto -> 244
    //   222: bipush #125
    //   224: goto -> 244
    //   227: bipush #28
    //   229: goto -> 244
    //   232: bipush #72
    //   234: goto -> 244
    //   237: bipush #59
    //   239: goto -> 244
    //   242: bipush #96
    //   244: ixor
    //   245: ixor
    //   246: i2c
    //   247: castore
    //   248: iinc #6, 1
    //   251: dup
    //   252: ifne -> 260
    //   255: dup2
    //   256: dup_x1
    //   257: goto -> 164
    //   260: dup2_x1
    //   261: pop2
    //   262: dup_x2
    //   263: iload #6
    //   265: if_icmpgt -> 160
    //   268: pop
    //   269: new java/lang/String
    //   272: dup_x1
    //   273: swap
    //   274: invokespecial <init> : ([C)V
    //   277: invokevirtual intern : ()Ljava/lang/String;
    //   280: swap
    //   281: pop
    //   282: swap
    //   283: tableswitch default -> 39, 0 -> 97
    //   300: sipush #6311
    //   303: sipush #-6192
    //   306: invokestatic a : (II)Ljava/lang/String;
    //   309: putstatic burp/Zrof.ZE : Ljava/lang/String;
    //   312: new java/math/BigInteger
    //   315: dup
    //   316: iconst_1
    //   317: bipush #32
    //   319: newarray byte
    //   321: dup
    //   322: iconst_0
    //   323: bipush #26
    //   325: bastore
    //   326: dup
    //   327: iconst_1
    //   328: bipush #-36
    //   330: bastore
    //   331: dup
    //   332: iconst_2
    //   333: bipush #-53
    //   335: bastore
    //   336: dup
    //   337: iconst_3
    //   338: bipush #85
    //   340: bastore
    //   341: dup
    //   342: iconst_4
    //   343: bipush #13
    //   345: bastore
    //   346: dup
    //   347: iconst_5
    //   348: bipush #16
    //   350: bastore
    //   351: dup
    //   352: bipush #6
    //   354: bipush #46
    //   356: bastore
    //   357: dup
    //   358: bipush #7
    //   360: bipush #103
    //   362: bastore
    //   363: dup
    //   364: bipush #8
    //   366: bipush #28
    //   368: bastore
    //   369: dup
    //   370: bipush #9
    //   372: bipush #-87
    //   374: bastore
    //   375: dup
    //   376: bipush #10
    //   378: bipush #-27
    //   380: bastore
    //   381: dup
    //   382: bipush #11
    //   384: bipush #87
    //   386: bastore
    //   387: dup
    //   388: bipush #12
    //   390: bipush #85
    //   392: bastore
    //   393: dup
    //   394: bipush #13
    //   396: bipush #13
    //   398: bastore
    //   399: dup
    //   400: bipush #14
    //   402: bipush #126
    //   404: bastore
    //   405: dup
    //   406: bipush #15
    //   408: bipush #109
    //   410: bastore
    //   411: dup
    //   412: bipush #16
    //   414: iconst_0
    //   415: bastore
    //   416: dup
    //   417: bipush #17
    //   419: bipush #33
    //   421: bastore
    //   422: dup
    //   423: bipush #18
    //   425: bipush #-78
    //   427: bastore
    //   428: dup
    //   429: bipush #19
    //   431: bipush #-84
    //   433: bastore
    //   434: dup
    //   435: bipush #20
    //   437: bipush #57
    //   439: bastore
    //   440: dup
    //   441: bipush #21
    //   443: bipush #65
    //   445: bastore
    //   446: dup
    //   447: bipush #22
    //   449: bipush #-56
    //   451: bastore
    //   452: dup
    //   453: bipush #23
    //   455: bipush #99
    //   457: bastore
    //   458: dup
    //   459: bipush #24
    //   461: bipush #-108
    //   463: bastore
    //   464: dup
    //   465: bipush #25
    //   467: bipush #70
    //   469: bastore
    //   470: dup
    //   471: bipush #26
    //   473: bipush #76
    //   475: bastore
    //   476: dup
    //   477: bipush #27
    //   479: bipush #89
    //   481: bastore
    //   482: dup
    //   483: bipush #28
    //   485: bipush #87
    //   487: bastore
    //   488: dup
    //   489: bipush #29
    //   491: bipush #-36
    //   493: bastore
    //   494: dup
    //   495: bipush #30
    //   497: bipush #111
    //   499: bastore
    //   500: dup
    //   501: bipush #31
    //   503: bipush #96
    //   505: bastore
    //   506: invokespecial <init> : (I[B)V
    //   509: putstatic burp/Zrof.ZB : Ljava/lang/Object;
    //   512: return
  }
  
  private static Throwable a(Throwable paramThrowable) {
    return paramThrowable;
  }
  
  private static String a(int paramInt1, int paramInt2) {
    int i = (paramInt1 ^ 0x18AD) & 0xFFFF;
    if (b[i] == null) {
      char[] arrayOfChar = a[i].toCharArray();
      switch (arrayOfChar[0] & 0xFF) {
        case 0:
        
        case 1:
        
        case 2:
        
        case 3:
        
        case 4:
        
        case 5:
        
        case 6:
        
        case 7:
        
        case 8:
        
        case 9:
        
        case 10:
        
        case 11:
        
        case 12:
        
        case 13:
        
        case 14:
        
        case 15:
        
        case 16:
        
        case 17:
        
        case 18:
        
        case 19:
        
        case 20:
        
        case 21:
        
        case 22:
        
        case 23:
        
        case 24:
        
        case 25:
        
        case 26:
        
        case 27:
        
        case 28:
        
        case 29:
        
        case 30:
        
        case 31:
        
        case 32:
        
        case 33:
        
        case 34:
        
        case 35:
        
        case 36:
        
        case 37:
        
        case 38:
        
        case 39:
        
        case 40:
        
        case 41:
        
        case 42:
        
        case 43:
        
        case 44:
        
        case 45:
        
        case 46:
        
        case 47:
        
        case 48:
        
        case 49:
        
        case 50:
        
        case 51:
        
        case 52:
        
        case 53:
        
        case 54:
        
        case 55:
        
        case 56:
        
        case 57:
        
        case 58:
        
        case 59:
        
        case 60:
        
        case 61:
        
        case 62:
        
        case 63:
        
        case 64:
        
        case 65:
        
        case 66:
        
        case 67:
        
        case 68:
        
        case 69:
        
        case 70:
        
        case 71:
        
        case 72:
        
        case 73:
        
        case 74:
        
        case 75:
        
        case 76:
        
        case 77:
        
        case 78:
        
        case 79:
        
        case 80:
        
        case 81:
        
        case 82:
        
        case 83:
        
        case 84:
        
        case 85:
        
        case 86:
        
        case 87:
        
        case 88:
        
        case 89:
        
        case 90:
        
        case 91:
        
        case 92:
        
        case 93:
        
        case 94:
        
        case 95:
        
        case 96:
        
        case 97:
        
        case 98:
        
        case 99:
        
        case 100:
        
        case 101:
        
        case 102:
        
        case 103:
        
        case 104:
        
        case 105:
        
        case 106:
        
        case 107:
        
        case 108:
        
        case 109:
        
        case 110:
        
        case 111:
        
        case 112:
        
        case 113:
        
        case 114:
        
        case 115:
        
        case 116:
        
        case 117:
        
        case 118:
        
        case 119:
        
        case 120:
        
        case 121:
        
        case 122:
        
        case 123:
        
        case 124:
        
        case 125:
        
        case 126:
        
        case 127:
        
        case 128:
        
        case 129:
        
        case 130:
        
        case 131:
        
        case 132:
        
        case 133:
        
        case 134:
        
        case 135:
        
        case 136:
        
        case 137:
        
        case 138:
        
        case 139:
        
        case 140:
        
        case 141:
        
        case 142:
        
        case 143:
        
        case 144:
        
        case 145:
        
        case 146:
        
        case 147:
        
        case 148:
        
        case 149:
        
        case 150:
        
        case 151:
        
        case 152:
        
        case 153:
        
        case 154:
        
        case 155:
        
        case 156:
        
        case 157:
        
        case 158:
        
        case 159:
        
        case 160:
        
        case 161:
        
        case 162:
        
        case 163:
        
        case 164:
        
        case 165:
        
        case 166:
        
        case 167:
        
        case 168:
        
        case 169:
        
        case 170:
        
        case 171:
        
        case 172:
        
        case 173:
        
        case 174:
        
        case 175:
        
        case 176:
        
        case 177:
        
        case 178:
        
        case 179:
        
        case 180:
        
        case 181:
        
        case 182:
        
        case 183:
        
        case 184:
        
        case 185:
        
        case 186:
        
        case 187:
        
        case 188:
        
        case 189:
        
        case 190:
        
        case 191:
        
        case 192:
        
        case 193:
        
        case 194:
        
        case 195:
        
        case 196:
        
        case 197:
        
        case 198:
        
        case 199:
        
        case 200:
        
        case 201:
        
        case 202:
        
        case 203:
        
        case 204:
        
        case 205:
        
        case 206:
        
        case 207:
        
        case 208:
        
        case 209:
        
        case 210:
        
        case 211:
        
        case 212:
        
        case 213:
        
        case 214:
        
        case 215:
        
        case 216:
        
        case 217:
        
        case 218:
        
        case 219:
        
        case 220:
        
        case 221:
        
        case 222:
        
        case 223:
        
        case 224:
        
        case 225:
        
        case 226:
        
        case 227:
        
        case 228:
        
        case 229:
        
        case 230:
        
        case 231:
        
        case 232:
        
        case 233:
        
        case 234:
        
        case 235:
        
        case 236:
        
        case 237:
        
        case 238:
        
        case 239:
        
        case 240:
        
        case 241:
        
        case 242:
        
        case 243:
        
        case 244:
        
        case 245:
        
        case 246:
        
        case 247:
        
        case 248:
        
        case 249:
        
        case 250:
        
        case 251:
        
        case 252:
        
        case 253:
        
        case 254:
        
        default:
          break;
      } 
      byte b1 = 89;
      int j = (paramInt2 & 0xFF) - b1;
      if (j < 0)
        j += 256; 
      int k = ((paramInt2 & 0xFFFF) >>> 8) - b1;
      if (k < 0)
        k += 256; 
      for (byte b2 = 0; b2 < arrayOfChar.length; b2++) {
        int m = b2 % 2;
        if (m == 0) {
          arrayOfChar[b2] = (char)(arrayOfChar[b2] ^ j);
          j = ((j >>> 3 | j << 5) ^ arrayOfChar[b2]) & 0xFF;
        } else {
          arrayOfChar[b2] = (char)(arrayOfChar[b2] ^ k);
          k = ((k >>> 3 | k << 5) ^ arrayOfChar[b2]) & 0xFF;
        } 
      } 
      b[i] = (new String(arrayOfChar)).intern();
    } 
    return b[i];
  }
}


/* Location:              C:\Program Files\BurpSuitePro\burpsuite_pro.jar!\burp\Zrof.class
 * Java compiler version: 21 (65.0)
 * JD-Core Version:       1.1.3
 */