package burp;

import java.math.BigInteger;

class Zrs0 extends ClassLoader {
  static Object Zz;
  
  static String Zt;
  
  private static final String[] a;
  
  private static final String[] b;
  
  static boolean ZS(Object[] paramArrayOfObject, Object paramObject) throws Throwable {
    // Byte code:
    //   0: invokestatic ZN : ()Z
    //   3: istore_2
    //   4: getstatic burp/Zmlu.Zi : Ljava/lang/Object;
    //   7: checkcast java/math/BigInteger
    //   10: invokevirtual toByteArray : ()[B
    //   13: astore_3
    //   14: iconst_0
    //   15: istore #5
    //   17: iconst_0
    //   18: istore #6
    //   20: iload #6
    //   22: aload_3
    //   23: arraylength
    //   24: if_icmpge -> 169
    //   27: aload_3
    //   28: iload #6
    //   30: baload
    //   31: istore #7
    //   33: iload #7
    //   35: bipush #48
    //   37: if_icmplt -> 54
    //   40: iload #7
    //   42: bipush #57
    //   44: if_icmple -> 152
    //   47: goto -> 54
    //   50: invokestatic a : (Ljava/lang/Throwable;)Ljava/lang/Throwable;
    //   53: athrow
    //   54: iload #7
    //   56: bipush #65
    //   58: if_icmplt -> 82
    //   61: goto -> 68
    //   64: invokestatic a : (Ljava/lang/Throwable;)Ljava/lang/Throwable;
    //   67: athrow
    //   68: iload #7
    //   70: bipush #90
    //   72: if_icmple -> 152
    //   75: goto -> 82
    //   78: invokestatic a : (Ljava/lang/Throwable;)Ljava/lang/Throwable;
    //   81: athrow
    //   82: iload #7
    //   84: bipush #97
    //   86: if_icmplt -> 110
    //   89: goto -> 96
    //   92: invokestatic a : (Ljava/lang/Throwable;)Ljava/lang/Throwable;
    //   95: athrow
    //   96: iload #7
    //   98: bipush #122
    //   100: if_icmple -> 152
    //   103: goto -> 110
    //   106: invokestatic a : (Ljava/lang/Throwable;)Ljava/lang/Throwable;
    //   109: athrow
    //   110: iload #7
    //   112: bipush #43
    //   114: if_icmpeq -> 152
    //   117: goto -> 124
    //   120: invokestatic a : (Ljava/lang/Throwable;)Ljava/lang/Throwable;
    //   123: athrow
    //   124: iload #7
    //   126: bipush #47
    //   128: if_icmpeq -> 152
    //   131: goto -> 138
    //   134: invokestatic a : (Ljava/lang/Throwable;)Ljava/lang/Throwable;
    //   137: athrow
    //   138: iload #7
    //   140: bipush #61
    //   142: if_icmpne -> 162
    //   145: goto -> 152
    //   148: invokestatic a : (Ljava/lang/Throwable;)Ljava/lang/Throwable;
    //   151: athrow
    //   152: iinc #5, 1
    //   155: goto -> 162
    //   158: invokestatic a : (Ljava/lang/Throwable;)Ljava/lang/Throwable;
    //   161: athrow
    //   162: iinc #6, 1
    //   165: iload_2
    //   166: ifne -> 20
    //   169: iload #5
    //   171: newarray byte
    //   173: astore #6
    //   175: iconst_0
    //   176: istore #7
    //   178: iconst_0
    //   179: istore #8
    //   181: iload #8
    //   183: aload_3
    //   184: arraylength
    //   185: if_icmpge -> 337
    //   188: aload_3
    //   189: iload #8
    //   191: baload
    //   192: istore #9
    //   194: iload #9
    //   196: bipush #48
    //   198: if_icmplt -> 215
    //   201: iload #9
    //   203: bipush #57
    //   205: if_icmple -> 313
    //   208: goto -> 215
    //   211: invokestatic a : (Ljava/lang/Throwable;)Ljava/lang/Throwable;
    //   214: athrow
    //   215: iload #9
    //   217: bipush #65
    //   219: if_icmplt -> 243
    //   222: goto -> 229
    //   225: invokestatic a : (Ljava/lang/Throwable;)Ljava/lang/Throwable;
    //   228: athrow
    //   229: iload #9
    //   231: bipush #90
    //   233: if_icmple -> 313
    //   236: goto -> 243
    //   239: invokestatic a : (Ljava/lang/Throwable;)Ljava/lang/Throwable;
    //   242: athrow
    //   243: iload #9
    //   245: bipush #97
    //   247: if_icmplt -> 271
    //   250: goto -> 257
    //   253: invokestatic a : (Ljava/lang/Throwable;)Ljava/lang/Throwable;
    //   256: athrow
    //   257: iload #9
    //   259: bipush #122
    //   261: if_icmple -> 313
    //   264: goto -> 271
    //   267: invokestatic a : (Ljava/lang/Throwable;)Ljava/lang/Throwable;
    //   270: athrow
    //   271: iload #9
    //   273: bipush #43
    //   275: if_icmpeq -> 313
    //   278: goto -> 285
    //   281: invokestatic a : (Ljava/lang/Throwable;)Ljava/lang/Throwable;
    //   284: athrow
    //   285: iload #9
    //   287: bipush #47
    //   289: if_icmpeq -> 313
    //   292: goto -> 299
    //   295: invokestatic a : (Ljava/lang/Throwable;)Ljava/lang/Throwable;
    //   298: athrow
    //   299: iload #9
    //   301: bipush #61
    //   303: if_icmpne -> 330
    //   306: goto -> 313
    //   309: invokestatic a : (Ljava/lang/Throwable;)Ljava/lang/Throwable;
    //   312: athrow
    //   313: aload #6
    //   315: iload #7
    //   317: iload #9
    //   319: bastore
    //   320: iinc #7, 1
    //   323: goto -> 330
    //   326: invokestatic a : (Ljava/lang/Throwable;)Ljava/lang/Throwable;
    //   329: athrow
    //   330: iinc #8, 1
    //   333: iload_2
    //   334: ifne -> 181
    //   337: aload #6
    //   339: astore #4
    //   341: aload #4
    //   343: astore_3
    //   344: aload_3
    //   345: arraylength
    //   346: istore #5
    //   348: aload_3
    //   349: iload #5
    //   351: iconst_1
    //   352: isub
    //   353: baload
    //   354: bipush #61
    //   356: if_icmpne -> 366
    //   359: iinc #5, -1
    //   362: iload_2
    //   363: ifne -> 348
    //   366: iload #5
    //   368: aload_3
    //   369: arraylength
    //   370: iconst_4
    //   371: idiv
    //   372: isub
    //   373: newarray byte
    //   375: astore #6
    //   377: iconst_0
    //   378: istore #7
    //   380: iload #7
    //   382: aload_3
    //   383: arraylength
    //   384: if_icmpge -> 646
    //   387: aload_3
    //   388: iload #7
    //   390: baload
    //   391: bipush #61
    //   393: if_icmpne -> 412
    //   396: aload_3
    //   397: iload #7
    //   399: iconst_0
    //   400: bastore
    //   401: iload_2
    //   402: ifne -> 639
    //   405: goto -> 412
    //   408: invokestatic a : (Ljava/lang/Throwable;)Ljava/lang/Throwable;
    //   411: athrow
    //   412: aload_3
    //   413: iload #7
    //   415: baload
    //   416: bipush #47
    //   418: if_icmpne -> 445
    //   421: goto -> 428
    //   424: invokestatic a : (Ljava/lang/Throwable;)Ljava/lang/Throwable;
    //   427: athrow
    //   428: aload_3
    //   429: iload #7
    //   431: bipush #63
    //   433: bastore
    //   434: iload_2
    //   435: ifne -> 639
    //   438: goto -> 445
    //   441: invokestatic a : (Ljava/lang/Throwable;)Ljava/lang/Throwable;
    //   444: athrow
    //   445: aload_3
    //   446: iload #7
    //   448: baload
    //   449: bipush #43
    //   451: if_icmpne -> 478
    //   454: goto -> 461
    //   457: invokestatic a : (Ljava/lang/Throwable;)Ljava/lang/Throwable;
    //   460: athrow
    //   461: aload_3
    //   462: iload #7
    //   464: bipush #62
    //   466: bastore
    //   467: iload_2
    //   468: ifne -> 639
    //   471: goto -> 478
    //   474: invokestatic a : (Ljava/lang/Throwable;)Ljava/lang/Throwable;
    //   477: athrow
    //   478: aload_3
    //   479: iload #7
    //   481: baload
    //   482: bipush #48
    //   484: if_icmplt -> 533
    //   487: goto -> 494
    //   490: invokestatic a : (Ljava/lang/Throwable;)Ljava/lang/Throwable;
    //   493: athrow
    //   494: aload_3
    //   495: iload #7
    //   497: baload
    //   498: bipush #57
    //   500: if_icmpgt -> 533
    //   503: goto -> 510
    //   506: invokestatic a : (Ljava/lang/Throwable;)Ljava/lang/Throwable;
    //   509: athrow
    //   510: aload_3
    //   511: iload #7
    //   513: aload_3
    //   514: iload #7
    //   516: baload
    //   517: bipush #-4
    //   519: isub
    //   520: i2b
    //   521: bastore
    //   522: iload_2
    //   523: ifne -> 639
    //   526: goto -> 533
    //   529: invokestatic a : (Ljava/lang/Throwable;)Ljava/lang/Throwable;
    //   532: athrow
    //   533: aload_3
    //   534: iload #7
    //   536: baload
    //   537: bipush #97
    //   539: if_icmplt -> 588
    //   542: goto -> 549
    //   545: invokestatic a : (Ljava/lang/Throwable;)Ljava/lang/Throwable;
    //   548: athrow
    //   549: aload_3
    //   550: iload #7
    //   552: baload
    //   553: bipush #122
    //   555: if_icmpgt -> 588
    //   558: goto -> 565
    //   561: invokestatic a : (Ljava/lang/Throwable;)Ljava/lang/Throwable;
    //   564: athrow
    //   565: aload_3
    //   566: iload #7
    //   568: aload_3
    //   569: iload #7
    //   571: baload
    //   572: bipush #71
    //   574: isub
    //   575: i2b
    //   576: bastore
    //   577: iload_2
    //   578: ifne -> 639
    //   581: goto -> 588
    //   584: invokestatic a : (Ljava/lang/Throwable;)Ljava/lang/Throwable;
    //   587: athrow
    //   588: aload_3
    //   589: iload #7
    //   591: baload
    //   592: bipush #65
    //   594: if_icmplt -> 639
    //   597: goto -> 604
    //   600: invokestatic a : (Ljava/lang/Throwable;)Ljava/lang/Throwable;
    //   603: athrow
    //   604: aload_3
    //   605: iload #7
    //   607: baload
    //   608: bipush #90
    //   610: if_icmpgt -> 639
    //   613: goto -> 620
    //   616: invokestatic a : (Ljava/lang/Throwable;)Ljava/lang/Throwable;
    //   619: athrow
    //   620: aload_3
    //   621: iload #7
    //   623: aload_3
    //   624: iload #7
    //   626: baload
    //   627: bipush #65
    //   629: isub
    //   630: i2b
    //   631: bastore
    //   632: goto -> 639
    //   635: invokestatic a : (Ljava/lang/Throwable;)Ljava/lang/Throwable;
    //   638: athrow
    //   639: iinc #7, 1
    //   642: iload_2
    //   643: ifne -> 380
    //   646: iconst_0
    //   647: istore #7
    //   649: iconst_0
    //   650: istore #8
    //   652: iload #8
    //   654: aload #6
    //   656: arraylength
    //   657: iconst_2
    //   658: isub
    //   659: if_icmpge -> 762
    //   662: aload #6
    //   664: iload #8
    //   666: aload_3
    //   667: iload #7
    //   669: baload
    //   670: iconst_2
    //   671: ishl
    //   672: sipush #255
    //   675: iand
    //   676: aload_3
    //   677: iload #7
    //   679: iconst_1
    //   680: iadd
    //   681: baload
    //   682: iconst_4
    //   683: iushr
    //   684: iconst_3
    //   685: iand
    //   686: ior
    //   687: i2b
    //   688: bastore
    //   689: aload #6
    //   691: iload #8
    //   693: iconst_1
    //   694: iadd
    //   695: aload_3
    //   696: iload #7
    //   698: iconst_1
    //   699: iadd
    //   700: baload
    //   701: iconst_4
    //   702: ishl
    //   703: sipush #255
    //   706: iand
    //   707: aload_3
    //   708: iload #7
    //   710: iconst_2
    //   711: iadd
    //   712: baload
    //   713: iconst_2
    //   714: iushr
    //   715: bipush #15
    //   717: iand
    //   718: ior
    //   719: i2b
    //   720: bastore
    //   721: aload #6
    //   723: iload #8
    //   725: iconst_2
    //   726: iadd
    //   727: aload_3
    //   728: iload #7
    //   730: iconst_2
    //   731: iadd
    //   732: baload
    //   733: bipush #6
    //   735: ishl
    //   736: sipush #255
    //   739: iand
    //   740: aload_3
    //   741: iload #7
    //   743: iconst_3
    //   744: iadd
    //   745: baload
    //   746: bipush #63
    //   748: iand
    //   749: ior
    //   750: i2b
    //   751: bastore
    //   752: iinc #7, 4
    //   755: iinc #8, 3
    //   758: iload_2
    //   759: ifne -> 652
    //   762: iload #8
    //   764: aload #6
    //   766: arraylength
    //   767: if_icmpge -> 804
    //   770: aload #6
    //   772: iload #8
    //   774: aload_3
    //   775: iload #7
    //   777: baload
    //   778: iconst_2
    //   779: ishl
    //   780: sipush #255
    //   783: iand
    //   784: aload_3
    //   785: iload #7
    //   787: iconst_1
    //   788: iadd
    //   789: baload
    //   790: iconst_4
    //   791: iushr
    //   792: iconst_3
    //   793: iand
    //   794: ior
    //   795: i2b
    //   796: bastore
    //   797: goto -> 804
    //   800: invokestatic a : (Ljava/lang/Throwable;)Ljava/lang/Throwable;
    //   803: athrow
    //   804: iinc #8, 1
    //   807: iload #8
    //   809: aload #6
    //   811: arraylength
    //   812: if_icmpge -> 852
    //   815: aload #6
    //   817: iload #8
    //   819: aload_3
    //   820: iload #7
    //   822: iconst_1
    //   823: iadd
    //   824: baload
    //   825: iconst_4
    //   826: ishl
    //   827: sipush #255
    //   830: iand
    //   831: aload_3
    //   832: iload #7
    //   834: iconst_2
    //   835: iadd
    //   836: baload
    //   837: iconst_2
    //   838: iushr
    //   839: bipush #15
    //   841: iand
    //   842: ior
    //   843: i2b
    //   844: bastore
    //   845: goto -> 852
    //   848: invokestatic a : (Ljava/lang/Throwable;)Ljava/lang/Throwable;
    //   851: athrow
    //   852: aload #6
    //   854: astore #4
    //   856: new java/math/BigInteger
    //   859: dup
    //   860: aload #4
    //   862: invokespecial <init> : ([B)V
    //   865: invokevirtual abs : ()Ljava/math/BigInteger;
    //   868: putstatic burp/Zm5p.Ze : Ljava/lang/Object;
    //   871: getstatic burp/Zg2.ZE : Ljava/lang/Object;
    //   874: checkcast java/math/BigInteger
    //   877: invokevirtual toByteArray : ()[B
    //   880: astore_3
    //   881: bipush #32
    //   883: newarray int
    //   885: dup
    //   886: iconst_0
    //   887: ldc 876216579
    //   889: iastore
    //   890: dup
    //   891: iconst_1
    //   892: ldc 455999525
    //   894: iastore
    //   895: dup
    //   896: iconst_2
    //   897: ldc 1043334948
    //   899: iastore
    //   900: dup
    //   901: iconst_3
    //   902: ldc 439222784
    //   904: iastore
    //   905: dup
    //   906: iconst_4
    //   907: ldc 372376604
    //   909: iastore
    //   910: dup
    //   911: iconst_5
    //   912: ldc 707731490
    //   914: iastore
    //   915: dup
    //   916: bipush #6
    //   918: ldc 389426184
    //   920: iastore
    //   921: dup
    //   922: bipush #7
    //   924: ldc 973875457
    //   926: iastore
    //   927: dup
    //   928: bipush #8
    //   930: ldc 389160971
    //   932: iastore
    //   933: dup
    //   934: bipush #9
    //   936: ldc 907870729
    //   938: iastore
    //   939: dup
    //   940: bipush #10
    //   942: ldc 121057538
    //   944: iastore
    //   945: dup
    //   946: bipush #11
    //   948: ldc 840500228
    //   950: iastore
    //   951: dup
    //   952: bipush #12
    //   954: ldc 254150144
    //   956: iastore
    //   957: dup
    //   958: bipush #13
    //   960: ldc 924386310
    //   962: iastore
    //   963: dup
    //   964: bipush #14
    //   966: ldc 187632156
    //   968: iastore
    //   969: dup
    //   970: bipush #15
    //   972: ldc 874189824
    //   974: iastore
    //   975: dup
    //   976: bipush #16
    //   978: ldc 655302664
    //   980: iastore
    //   981: dup
    //   982: bipush #17
    //   984: ldc 890966315
    //   986: iastore
    //   987: dup
    //   988: bipush #18
    //   990: ldc 722417666
    //   992: iastore
    //   993: dup
    //   994: bipush #19
    //   996: ldc 1026621720
    //   998: iastore
    //   999: dup
    //   1000: bipush #20
    //   1002: ldc 957157408
    //   1004: iastore
    //   1005: dup
    //   1006: bipush #21
    //   1008: ldc 892536332
    //   1010: iastore
    //   1011: dup
    //   1012: bipush #22
    //   1014: ldc 689771012
    //   1016: iastore
    //   1017: dup
    //   1018: bipush #23
    //   1020: ldc 221709344
    //   1022: iastore
    //   1023: dup
    //   1024: bipush #24
    //   1026: ldc 940377620
    //   1028: iastore
    //   1029: dup
    //   1030: bipush #25
    //   1032: ldc 255209728
    //   1034: iastore
    //   1035: dup
    //   1036: bipush #26
    //   1038: ldc 1010368540
    //   1040: iastore
    //   1041: dup
    //   1042: bipush #27
    //   1044: ldc 220604441
    //   1046: iastore
    //   1047: dup
    //   1048: bipush #28
    //   1050: ldc 1008414755
    //   1052: iastore
    //   1053: dup
    //   1054: bipush #29
    //   1056: ldc 187049985
    //   1058: iastore
    //   1059: dup
    //   1060: bipush #30
    //   1062: ldc 943331329
    //   1064: iastore
    //   1065: dup
    //   1066: bipush #31
    //   1068: ldc 170788368
    //   1070: iastore
    //   1071: astore #5
    //   1073: bipush #64
    //   1075: newarray int
    //   1077: dup
    //   1078: iconst_0
    //   1079: ldc 16843776
    //   1081: iastore
    //   1082: dup
    //   1083: iconst_1
    //   1084: iconst_0
    //   1085: iastore
    //   1086: dup
    //   1087: iconst_2
    //   1088: ldc 65536
    //   1090: iastore
    //   1091: dup
    //   1092: iconst_3
    //   1093: ldc 16843780
    //   1095: iastore
    //   1096: dup
    //   1097: iconst_4
    //   1098: ldc 16842756
    //   1100: iastore
    //   1101: dup
    //   1102: iconst_5
    //   1103: ldc 66564
    //   1105: iastore
    //   1106: dup
    //   1107: bipush #6
    //   1109: iconst_4
    //   1110: iastore
    //   1111: dup
    //   1112: bipush #7
    //   1114: ldc 65536
    //   1116: iastore
    //   1117: dup
    //   1118: bipush #8
    //   1120: sipush #1024
    //   1123: iastore
    //   1124: dup
    //   1125: bipush #9
    //   1127: ldc 16843776
    //   1129: iastore
    //   1130: dup
    //   1131: bipush #10
    //   1133: ldc 16843780
    //   1135: iastore
    //   1136: dup
    //   1137: bipush #11
    //   1139: sipush #1024
    //   1142: iastore
    //   1143: dup
    //   1144: bipush #12
    //   1146: ldc 16778244
    //   1148: iastore
    //   1149: dup
    //   1150: bipush #13
    //   1152: ldc 16842756
    //   1154: iastore
    //   1155: dup
    //   1156: bipush #14
    //   1158: ldc 16777216
    //   1160: iastore
    //   1161: dup
    //   1162: bipush #15
    //   1164: iconst_4
    //   1165: iastore
    //   1166: dup
    //   1167: bipush #16
    //   1169: sipush #1028
    //   1172: iastore
    //   1173: dup
    //   1174: bipush #17
    //   1176: ldc 16778240
    //   1178: iastore
    //   1179: dup
    //   1180: bipush #18
    //   1182: ldc 16778240
    //   1184: iastore
    //   1185: dup
    //   1186: bipush #19
    //   1188: ldc 66560
    //   1190: iastore
    //   1191: dup
    //   1192: bipush #20
    //   1194: ldc 66560
    //   1196: iastore
    //   1197: dup
    //   1198: bipush #21
    //   1200: ldc 16842752
    //   1202: iastore
    //   1203: dup
    //   1204: bipush #22
    //   1206: ldc 16842752
    //   1208: iastore
    //   1209: dup
    //   1210: bipush #23
    //   1212: ldc 16778244
    //   1214: iastore
    //   1215: dup
    //   1216: bipush #24
    //   1218: ldc 65540
    //   1220: iastore
    //   1221: dup
    //   1222: bipush #25
    //   1224: ldc 16777220
    //   1226: iastore
    //   1227: dup
    //   1228: bipush #26
    //   1230: ldc 16777220
    //   1232: iastore
    //   1233: dup
    //   1234: bipush #27
    //   1236: ldc 65540
    //   1238: iastore
    //   1239: dup
    //   1240: bipush #28
    //   1242: iconst_0
    //   1243: iastore
    //   1244: dup
    //   1245: bipush #29
    //   1247: sipush #1028
    //   1250: iastore
    //   1251: dup
    //   1252: bipush #30
    //   1254: ldc 66564
    //   1256: iastore
    //   1257: dup
    //   1258: bipush #31
    //   1260: ldc 16777216
    //   1262: iastore
    //   1263: dup
    //   1264: bipush #32
    //   1266: ldc 65536
    //   1268: iastore
    //   1269: dup
    //   1270: bipush #33
    //   1272: ldc 16843780
    //   1274: iastore
    //   1275: dup
    //   1276: bipush #34
    //   1278: iconst_4
    //   1279: iastore
    //   1280: dup
    //   1281: bipush #35
    //   1283: ldc 16842752
    //   1285: iastore
    //   1286: dup
    //   1287: bipush #36
    //   1289: ldc 16843776
    //   1291: iastore
    //   1292: dup
    //   1293: bipush #37
    //   1295: ldc 16777216
    //   1297: iastore
    //   1298: dup
    //   1299: bipush #38
    //   1301: ldc 16777216
    //   1303: iastore
    //   1304: dup
    //   1305: bipush #39
    //   1307: sipush #1024
    //   1310: iastore
    //   1311: dup
    //   1312: bipush #40
    //   1314: ldc 16842756
    //   1316: iastore
    //   1317: dup
    //   1318: bipush #41
    //   1320: ldc 65536
    //   1322: iastore
    //   1323: dup
    //   1324: bipush #42
    //   1326: ldc 66560
    //   1328: iastore
    //   1329: dup
    //   1330: bipush #43
    //   1332: ldc 16777220
    //   1334: iastore
    //   1335: dup
    //   1336: bipush #44
    //   1338: sipush #1024
    //   1341: iastore
    //   1342: dup
    //   1343: bipush #45
    //   1345: iconst_4
    //   1346: iastore
    //   1347: dup
    //   1348: bipush #46
    //   1350: ldc 16778244
    //   1352: iastore
    //   1353: dup
    //   1354: bipush #47
    //   1356: ldc 66564
    //   1358: iastore
    //   1359: dup
    //   1360: bipush #48
    //   1362: ldc 16843780
    //   1364: iastore
    //   1365: dup
    //   1366: bipush #49
    //   1368: ldc 65540
    //   1370: iastore
    //   1371: dup
    //   1372: bipush #50
    //   1374: ldc 16842752
    //   1376: iastore
    //   1377: dup
    //   1378: bipush #51
    //   1380: ldc 16778244
    //   1382: iastore
    //   1383: dup
    //   1384: bipush #52
    //   1386: ldc 16777220
    //   1388: iastore
    //   1389: dup
    //   1390: bipush #53
    //   1392: sipush #1028
    //   1395: iastore
    //   1396: dup
    //   1397: bipush #54
    //   1399: ldc 66564
    //   1401: iastore
    //   1402: dup
    //   1403: bipush #55
    //   1405: ldc 16843776
    //   1407: iastore
    //   1408: dup
    //   1409: bipush #56
    //   1411: sipush #1028
    //   1414: iastore
    //   1415: dup
    //   1416: bipush #57
    //   1418: ldc 16778240
    //   1420: iastore
    //   1421: dup
    //   1422: bipush #58
    //   1424: ldc 16778240
    //   1426: iastore
    //   1427: dup
    //   1428: bipush #59
    //   1430: iconst_0
    //   1431: iastore
    //   1432: dup
    //   1433: bipush #60
    //   1435: ldc 65540
    //   1437: iastore
    //   1438: dup
    //   1439: bipush #61
    //   1441: ldc 66560
    //   1443: iastore
    //   1444: dup
    //   1445: bipush #62
    //   1447: iconst_0
    //   1448: iastore
    //   1449: dup
    //   1450: bipush #63
    //   1452: ldc 16842756
    //   1454: iastore
    //   1455: astore #6
    //   1457: bipush #64
    //   1459: newarray int
    //   1461: dup
    //   1462: iconst_0
    //   1463: ldc -2146402272
    //   1465: iastore
    //   1466: dup
    //   1467: iconst_1
    //   1468: ldc -2147450880
    //   1470: iastore
    //   1471: dup
    //   1472: iconst_2
    //   1473: ldc 32768
    //   1475: iastore
    //   1476: dup
    //   1477: iconst_3
    //   1478: ldc 1081376
    //   1480: iastore
    //   1481: dup
    //   1482: iconst_4
    //   1483: ldc 1048576
    //   1485: iastore
    //   1486: dup
    //   1487: iconst_5
    //   1488: bipush #32
    //   1490: iastore
    //   1491: dup
    //   1492: bipush #6
    //   1494: ldc -2146435040
    //   1496: iastore
    //   1497: dup
    //   1498: bipush #7
    //   1500: ldc -2147450848
    //   1502: iastore
    //   1503: dup
    //   1504: bipush #8
    //   1506: ldc -2147483616
    //   1508: iastore
    //   1509: dup
    //   1510: bipush #9
    //   1512: ldc -2146402272
    //   1514: iastore
    //   1515: dup
    //   1516: bipush #10
    //   1518: ldc -2146402304
    //   1520: iastore
    //   1521: dup
    //   1522: bipush #11
    //   1524: ldc -2147483648
    //   1526: iastore
    //   1527: dup
    //   1528: bipush #12
    //   1530: ldc -2147450880
    //   1532: iastore
    //   1533: dup
    //   1534: bipush #13
    //   1536: ldc 1048576
    //   1538: iastore
    //   1539: dup
    //   1540: bipush #14
    //   1542: bipush #32
    //   1544: iastore
    //   1545: dup
    //   1546: bipush #15
    //   1548: ldc -2146435040
    //   1550: iastore
    //   1551: dup
    //   1552: bipush #16
    //   1554: ldc 1081344
    //   1556: iastore
    //   1557: dup
    //   1558: bipush #17
    //   1560: ldc 1048608
    //   1562: iastore
    //   1563: dup
    //   1564: bipush #18
    //   1566: ldc -2147450848
    //   1568: iastore
    //   1569: dup
    //   1570: bipush #19
    //   1572: iconst_0
    //   1573: iastore
    //   1574: dup
    //   1575: bipush #20
    //   1577: ldc -2147483648
    //   1579: iastore
    //   1580: dup
    //   1581: bipush #21
    //   1583: ldc 32768
    //   1585: iastore
    //   1586: dup
    //   1587: bipush #22
    //   1589: ldc 1081376
    //   1591: iastore
    //   1592: dup
    //   1593: bipush #23
    //   1595: ldc -2146435072
    //   1597: iastore
    //   1598: dup
    //   1599: bipush #24
    //   1601: ldc 1048608
    //   1603: iastore
    //   1604: dup
    //   1605: bipush #25
    //   1607: ldc -2147483616
    //   1609: iastore
    //   1610: dup
    //   1611: bipush #26
    //   1613: iconst_0
    //   1614: iastore
    //   1615: dup
    //   1616: bipush #27
    //   1618: ldc 1081344
    //   1620: iastore
    //   1621: dup
    //   1622: bipush #28
    //   1624: ldc 32800
    //   1626: iastore
    //   1627: dup
    //   1628: bipush #29
    //   1630: ldc -2146402304
    //   1632: iastore
    //   1633: dup
    //   1634: bipush #30
    //   1636: ldc -2146435072
    //   1638: iastore
    //   1639: dup
    //   1640: bipush #31
    //   1642: ldc 32800
    //   1644: iastore
    //   1645: dup
    //   1646: bipush #32
    //   1648: iconst_0
    //   1649: iastore
    //   1650: dup
    //   1651: bipush #33
    //   1653: ldc 1081376
    //   1655: iastore
    //   1656: dup
    //   1657: bipush #34
    //   1659: ldc -2146435040
    //   1661: iastore
    //   1662: dup
    //   1663: bipush #35
    //   1665: ldc 1048576
    //   1667: iastore
    //   1668: dup
    //   1669: bipush #36
    //   1671: ldc -2147450848
    //   1673: iastore
    //   1674: dup
    //   1675: bipush #37
    //   1677: ldc -2146435072
    //   1679: iastore
    //   1680: dup
    //   1681: bipush #38
    //   1683: ldc -2146402304
    //   1685: iastore
    //   1686: dup
    //   1687: bipush #39
    //   1689: ldc 32768
    //   1691: iastore
    //   1692: dup
    //   1693: bipush #40
    //   1695: ldc -2146435072
    //   1697: iastore
    //   1698: dup
    //   1699: bipush #41
    //   1701: ldc -2147450880
    //   1703: iastore
    //   1704: dup
    //   1705: bipush #42
    //   1707: bipush #32
    //   1709: iastore
    //   1710: dup
    //   1711: bipush #43
    //   1713: ldc -2146402272
    //   1715: iastore
    //   1716: dup
    //   1717: bipush #44
    //   1719: ldc 1081376
    //   1721: iastore
    //   1722: dup
    //   1723: bipush #45
    //   1725: bipush #32
    //   1727: iastore
    //   1728: dup
    //   1729: bipush #46
    //   1731: ldc 32768
    //   1733: iastore
    //   1734: dup
    //   1735: bipush #47
    //   1737: ldc -2147483648
    //   1739: iastore
    //   1740: dup
    //   1741: bipush #48
    //   1743: ldc 32800
    //   1745: iastore
    //   1746: dup
    //   1747: bipush #49
    //   1749: ldc -2146402304
    //   1751: iastore
    //   1752: dup
    //   1753: bipush #50
    //   1755: ldc 1048576
    //   1757: iastore
    //   1758: dup
    //   1759: bipush #51
    //   1761: ldc -2147483616
    //   1763: iastore
    //   1764: dup
    //   1765: bipush #52
    //   1767: ldc 1048608
    //   1769: iastore
    //   1770: dup
    //   1771: bipush #53
    //   1773: ldc -2147450848
    //   1775: iastore
    //   1776: dup
    //   1777: bipush #54
    //   1779: ldc -2147483616
    //   1781: iastore
    //   1782: dup
    //   1783: bipush #55
    //   1785: ldc 1048608
    //   1787: iastore
    //   1788: dup
    //   1789: bipush #56
    //   1791: ldc 1081344
    //   1793: iastore
    //   1794: dup
    //   1795: bipush #57
    //   1797: iconst_0
    //   1798: iastore
    //   1799: dup
    //   1800: bipush #58
    //   1802: ldc -2147450880
    //   1804: iastore
    //   1805: dup
    //   1806: bipush #59
    //   1808: ldc 32800
    //   1810: iastore
    //   1811: dup
    //   1812: bipush #60
    //   1814: ldc -2147483648
    //   1816: iastore
    //   1817: dup
    //   1818: bipush #61
    //   1820: ldc -2146435040
    //   1822: iastore
    //   1823: dup
    //   1824: bipush #62
    //   1826: ldc -2146402272
    //   1828: iastore
    //   1829: dup
    //   1830: bipush #63
    //   1832: ldc 1081344
    //   1834: iastore
    //   1835: astore #7
    //   1837: bipush #64
    //   1839: newarray int
    //   1841: dup
    //   1842: iconst_0
    //   1843: sipush #520
    //   1846: iastore
    //   1847: dup
    //   1848: iconst_1
    //   1849: ldc 134349312
    //   1851: iastore
    //   1852: dup
    //   1853: iconst_2
    //   1854: iconst_0
    //   1855: iastore
    //   1856: dup
    //   1857: iconst_3
    //   1858: ldc 134348808
    //   1860: iastore
    //   1861: dup
    //   1862: iconst_4
    //   1863: ldc 134218240
    //   1865: iastore
    //   1866: dup
    //   1867: iconst_5
    //   1868: iconst_0
    //   1869: iastore
    //   1870: dup
    //   1871: bipush #6
    //   1873: ldc 131592
    //   1875: iastore
    //   1876: dup
    //   1877: bipush #7
    //   1879: ldc 134218240
    //   1881: iastore
    //   1882: dup
    //   1883: bipush #8
    //   1885: ldc 131080
    //   1887: iastore
    //   1888: dup
    //   1889: bipush #9
    //   1891: ldc 134217736
    //   1893: iastore
    //   1894: dup
    //   1895: bipush #10
    //   1897: ldc 134217736
    //   1899: iastore
    //   1900: dup
    //   1901: bipush #11
    //   1903: ldc 131072
    //   1905: iastore
    //   1906: dup
    //   1907: bipush #12
    //   1909: ldc 134349320
    //   1911: iastore
    //   1912: dup
    //   1913: bipush #13
    //   1915: ldc 131080
    //   1917: iastore
    //   1918: dup
    //   1919: bipush #14
    //   1921: ldc 134348800
    //   1923: iastore
    //   1924: dup
    //   1925: bipush #15
    //   1927: sipush #520
    //   1930: iastore
    //   1931: dup
    //   1932: bipush #16
    //   1934: ldc 134217728
    //   1936: iastore
    //   1937: dup
    //   1938: bipush #17
    //   1940: bipush #8
    //   1942: iastore
    //   1943: dup
    //   1944: bipush #18
    //   1946: ldc 134349312
    //   1948: iastore
    //   1949: dup
    //   1950: bipush #19
    //   1952: sipush #512
    //   1955: iastore
    //   1956: dup
    //   1957: bipush #20
    //   1959: ldc 131584
    //   1961: iastore
    //   1962: dup
    //   1963: bipush #21
    //   1965: ldc 134348800
    //   1967: iastore
    //   1968: dup
    //   1969: bipush #22
    //   1971: ldc 134348808
    //   1973: iastore
    //   1974: dup
    //   1975: bipush #23
    //   1977: ldc 131592
    //   1979: iastore
    //   1980: dup
    //   1981: bipush #24
    //   1983: ldc 134218248
    //   1985: iastore
    //   1986: dup
    //   1987: bipush #25
    //   1989: ldc 131584
    //   1991: iastore
    //   1992: dup
    //   1993: bipush #26
    //   1995: ldc 131072
    //   1997: iastore
    //   1998: dup
    //   1999: bipush #27
    //   2001: ldc 134218248
    //   2003: iastore
    //   2004: dup
    //   2005: bipush #28
    //   2007: bipush #8
    //   2009: iastore
    //   2010: dup
    //   2011: bipush #29
    //   2013: ldc 134349320
    //   2015: iastore
    //   2016: dup
    //   2017: bipush #30
    //   2019: sipush #512
    //   2022: iastore
    //   2023: dup
    //   2024: bipush #31
    //   2026: ldc 134217728
    //   2028: iastore
    //   2029: dup
    //   2030: bipush #32
    //   2032: ldc 134349312
    //   2034: iastore
    //   2035: dup
    //   2036: bipush #33
    //   2038: ldc 134217728
    //   2040: iastore
    //   2041: dup
    //   2042: bipush #34
    //   2044: ldc 131080
    //   2046: iastore
    //   2047: dup
    //   2048: bipush #35
    //   2050: sipush #520
    //   2053: iastore
    //   2054: dup
    //   2055: bipush #36
    //   2057: ldc 131072
    //   2059: iastore
    //   2060: dup
    //   2061: bipush #37
    //   2063: ldc 134349312
    //   2065: iastore
    //   2066: dup
    //   2067: bipush #38
    //   2069: ldc 134218240
    //   2071: iastore
    //   2072: dup
    //   2073: bipush #39
    //   2075: iconst_0
    //   2076: iastore
    //   2077: dup
    //   2078: bipush #40
    //   2080: sipush #512
    //   2083: iastore
    //   2084: dup
    //   2085: bipush #41
    //   2087: ldc 131080
    //   2089: iastore
    //   2090: dup
    //   2091: bipush #42
    //   2093: ldc 134349320
    //   2095: iastore
    //   2096: dup
    //   2097: bipush #43
    //   2099: ldc 134218240
    //   2101: iastore
    //   2102: dup
    //   2103: bipush #44
    //   2105: ldc 134217736
    //   2107: iastore
    //   2108: dup
    //   2109: bipush #45
    //   2111: sipush #512
    //   2114: iastore
    //   2115: dup
    //   2116: bipush #46
    //   2118: iconst_0
    //   2119: iastore
    //   2120: dup
    //   2121: bipush #47
    //   2123: ldc 134348808
    //   2125: iastore
    //   2126: dup
    //   2127: bipush #48
    //   2129: ldc 134218248
    //   2131: iastore
    //   2132: dup
    //   2133: bipush #49
    //   2135: ldc 131072
    //   2137: iastore
    //   2138: dup
    //   2139: bipush #50
    //   2141: ldc 134217728
    //   2143: iastore
    //   2144: dup
    //   2145: bipush #51
    //   2147: ldc 134349320
    //   2149: iastore
    //   2150: dup
    //   2151: bipush #52
    //   2153: bipush #8
    //   2155: iastore
    //   2156: dup
    //   2157: bipush #53
    //   2159: ldc 131592
    //   2161: iastore
    //   2162: dup
    //   2163: bipush #54
    //   2165: ldc 131584
    //   2167: iastore
    //   2168: dup
    //   2169: bipush #55
    //   2171: ldc 134217736
    //   2173: iastore
    //   2174: dup
    //   2175: bipush #56
    //   2177: ldc 134348800
    //   2179: iastore
    //   2180: dup
    //   2181: bipush #57
    //   2183: ldc 134218248
    //   2185: iastore
    //   2186: dup
    //   2187: bipush #58
    //   2189: sipush #520
    //   2192: iastore
    //   2193: dup
    //   2194: bipush #59
    //   2196: ldc 134348800
    //   2198: iastore
    //   2199: dup
    //   2200: bipush #60
    //   2202: ldc 131592
    //   2204: iastore
    //   2205: dup
    //   2206: bipush #61
    //   2208: bipush #8
    //   2210: iastore
    //   2211: dup
    //   2212: bipush #62
    //   2214: ldc 134348808
    //   2216: iastore
    //   2217: dup
    //   2218: bipush #63
    //   2220: ldc 131584
    //   2222: iastore
    //   2223: astore #8
    //   2225: bipush #64
    //   2227: newarray int
    //   2229: dup
    //   2230: iconst_0
    //   2231: ldc 8396801
    //   2233: iastore
    //   2234: dup
    //   2235: iconst_1
    //   2236: sipush #8321
    //   2239: iastore
    //   2240: dup
    //   2241: iconst_2
    //   2242: sipush #8321
    //   2245: iastore
    //   2246: dup
    //   2247: iconst_3
    //   2248: sipush #128
    //   2251: iastore
    //   2252: dup
    //   2253: iconst_4
    //   2254: ldc 8396928
    //   2256: iastore
    //   2257: dup
    //   2258: iconst_5
    //   2259: ldc 8388737
    //   2261: iastore
    //   2262: dup
    //   2263: bipush #6
    //   2265: ldc 8388609
    //   2267: iastore
    //   2268: dup
    //   2269: bipush #7
    //   2271: sipush #8193
    //   2274: iastore
    //   2275: dup
    //   2276: bipush #8
    //   2278: iconst_0
    //   2279: iastore
    //   2280: dup
    //   2281: bipush #9
    //   2283: ldc 8396800
    //   2285: iastore
    //   2286: dup
    //   2287: bipush #10
    //   2289: ldc 8396800
    //   2291: iastore
    //   2292: dup
    //   2293: bipush #11
    //   2295: ldc 8396929
    //   2297: iastore
    //   2298: dup
    //   2299: bipush #12
    //   2301: sipush #129
    //   2304: iastore
    //   2305: dup
    //   2306: bipush #13
    //   2308: iconst_0
    //   2309: iastore
    //   2310: dup
    //   2311: bipush #14
    //   2313: ldc 8388736
    //   2315: iastore
    //   2316: dup
    //   2317: bipush #15
    //   2319: ldc 8388609
    //   2321: iastore
    //   2322: dup
    //   2323: bipush #16
    //   2325: iconst_1
    //   2326: iastore
    //   2327: dup
    //   2328: bipush #17
    //   2330: sipush #8192
    //   2333: iastore
    //   2334: dup
    //   2335: bipush #18
    //   2337: ldc 8388608
    //   2339: iastore
    //   2340: dup
    //   2341: bipush #19
    //   2343: ldc 8396801
    //   2345: iastore
    //   2346: dup
    //   2347: bipush #20
    //   2349: sipush #128
    //   2352: iastore
    //   2353: dup
    //   2354: bipush #21
    //   2356: ldc 8388608
    //   2358: iastore
    //   2359: dup
    //   2360: bipush #22
    //   2362: sipush #8193
    //   2365: iastore
    //   2366: dup
    //   2367: bipush #23
    //   2369: sipush #8320
    //   2372: iastore
    //   2373: dup
    //   2374: bipush #24
    //   2376: ldc 8388737
    //   2378: iastore
    //   2379: dup
    //   2380: bipush #25
    //   2382: iconst_1
    //   2383: iastore
    //   2384: dup
    //   2385: bipush #26
    //   2387: sipush #8320
    //   2390: iastore
    //   2391: dup
    //   2392: bipush #27
    //   2394: ldc 8388736
    //   2396: iastore
    //   2397: dup
    //   2398: bipush #28
    //   2400: sipush #8192
    //   2403: iastore
    //   2404: dup
    //   2405: bipush #29
    //   2407: ldc 8396928
    //   2409: iastore
    //   2410: dup
    //   2411: bipush #30
    //   2413: ldc 8396929
    //   2415: iastore
    //   2416: dup
    //   2417: bipush #31
    //   2419: sipush #129
    //   2422: iastore
    //   2423: dup
    //   2424: bipush #32
    //   2426: ldc 8388736
    //   2428: iastore
    //   2429: dup
    //   2430: bipush #33
    //   2432: ldc 8388609
    //   2434: iastore
    //   2435: dup
    //   2436: bipush #34
    //   2438: ldc 8396800
    //   2440: iastore
    //   2441: dup
    //   2442: bipush #35
    //   2444: ldc 8396929
    //   2446: iastore
    //   2447: dup
    //   2448: bipush #36
    //   2450: sipush #129
    //   2453: iastore
    //   2454: dup
    //   2455: bipush #37
    //   2457: iconst_0
    //   2458: iastore
    //   2459: dup
    //   2460: bipush #38
    //   2462: iconst_0
    //   2463: iastore
    //   2464: dup
    //   2465: bipush #39
    //   2467: ldc 8396800
    //   2469: iastore
    //   2470: dup
    //   2471: bipush #40
    //   2473: sipush #8320
    //   2476: iastore
    //   2477: dup
    //   2478: bipush #41
    //   2480: ldc 8388736
    //   2482: iastore
    //   2483: dup
    //   2484: bipush #42
    //   2486: ldc 8388737
    //   2488: iastore
    //   2489: dup
    //   2490: bipush #43
    //   2492: iconst_1
    //   2493: iastore
    //   2494: dup
    //   2495: bipush #44
    //   2497: ldc 8396801
    //   2499: iastore
    //   2500: dup
    //   2501: bipush #45
    //   2503: sipush #8321
    //   2506: iastore
    //   2507: dup
    //   2508: bipush #46
    //   2510: sipush #8321
    //   2513: iastore
    //   2514: dup
    //   2515: bipush #47
    //   2517: sipush #128
    //   2520: iastore
    //   2521: dup
    //   2522: bipush #48
    //   2524: ldc 8396929
    //   2526: iastore
    //   2527: dup
    //   2528: bipush #49
    //   2530: sipush #129
    //   2533: iastore
    //   2534: dup
    //   2535: bipush #50
    //   2537: iconst_1
    //   2538: iastore
    //   2539: dup
    //   2540: bipush #51
    //   2542: sipush #8192
    //   2545: iastore
    //   2546: dup
    //   2547: bipush #52
    //   2549: ldc 8388609
    //   2551: iastore
    //   2552: dup
    //   2553: bipush #53
    //   2555: sipush #8193
    //   2558: iastore
    //   2559: dup
    //   2560: bipush #54
    //   2562: ldc 8396928
    //   2564: iastore
    //   2565: dup
    //   2566: bipush #55
    //   2568: ldc 8388737
    //   2570: iastore
    //   2571: dup
    //   2572: bipush #56
    //   2574: sipush #8193
    //   2577: iastore
    //   2578: dup
    //   2579: bipush #57
    //   2581: sipush #8320
    //   2584: iastore
    //   2585: dup
    //   2586: bipush #58
    //   2588: ldc 8388608
    //   2590: iastore
    //   2591: dup
    //   2592: bipush #59
    //   2594: ldc 8396801
    //   2596: iastore
    //   2597: dup
    //   2598: bipush #60
    //   2600: sipush #128
    //   2603: iastore
    //   2604: dup
    //   2605: bipush #61
    //   2607: ldc 8388608
    //   2609: iastore
    //   2610: dup
    //   2611: bipush #62
    //   2613: sipush #8192
    //   2616: iastore
    //   2617: dup
    //   2618: bipush #63
    //   2620: ldc 8396928
    //   2622: iastore
    //   2623: astore #9
    //   2625: bipush #64
    //   2627: newarray int
    //   2629: dup
    //   2630: iconst_0
    //   2631: sipush #256
    //   2634: iastore
    //   2635: dup
    //   2636: iconst_1
    //   2637: ldc 34078976
    //   2639: iastore
    //   2640: dup
    //   2641: iconst_2
    //   2642: ldc 34078720
    //   2644: iastore
    //   2645: dup
    //   2646: iconst_3
    //   2647: ldc 1107296512
    //   2649: iastore
    //   2650: dup
    //   2651: iconst_4
    //   2652: ldc 524288
    //   2654: iastore
    //   2655: dup
    //   2656: iconst_5
    //   2657: sipush #256
    //   2660: iastore
    //   2661: dup
    //   2662: bipush #6
    //   2664: ldc 1073741824
    //   2666: iastore
    //   2667: dup
    //   2668: bipush #7
    //   2670: ldc 34078720
    //   2672: iastore
    //   2673: dup
    //   2674: bipush #8
    //   2676: ldc 1074266368
    //   2678: iastore
    //   2679: dup
    //   2680: bipush #9
    //   2682: ldc 524288
    //   2684: iastore
    //   2685: dup
    //   2686: bipush #10
    //   2688: ldc 33554688
    //   2690: iastore
    //   2691: dup
    //   2692: bipush #11
    //   2694: ldc 1074266368
    //   2696: iastore
    //   2697: dup
    //   2698: bipush #12
    //   2700: ldc 1107296512
    //   2702: iastore
    //   2703: dup
    //   2704: bipush #13
    //   2706: ldc 1107820544
    //   2708: iastore
    //   2709: dup
    //   2710: bipush #14
    //   2712: ldc 524544
    //   2714: iastore
    //   2715: dup
    //   2716: bipush #15
    //   2718: ldc 1073741824
    //   2720: iastore
    //   2721: dup
    //   2722: bipush #16
    //   2724: ldc 33554432
    //   2726: iastore
    //   2727: dup
    //   2728: bipush #17
    //   2730: ldc 1074266112
    //   2732: iastore
    //   2733: dup
    //   2734: bipush #18
    //   2736: ldc 1074266112
    //   2738: iastore
    //   2739: dup
    //   2740: bipush #19
    //   2742: iconst_0
    //   2743: iastore
    //   2744: dup
    //   2745: bipush #20
    //   2747: ldc 1073742080
    //   2749: iastore
    //   2750: dup
    //   2751: bipush #21
    //   2753: ldc 1107820800
    //   2755: iastore
    //   2756: dup
    //   2757: bipush #22
    //   2759: ldc 1107820800
    //   2761: iastore
    //   2762: dup
    //   2763: bipush #23
    //   2765: ldc 33554688
    //   2767: iastore
    //   2768: dup
    //   2769: bipush #24
    //   2771: ldc 1107820544
    //   2773: iastore
    //   2774: dup
    //   2775: bipush #25
    //   2777: ldc 1073742080
    //   2779: iastore
    //   2780: dup
    //   2781: bipush #26
    //   2783: iconst_0
    //   2784: iastore
    //   2785: dup
    //   2786: bipush #27
    //   2788: ldc 1107296256
    //   2790: iastore
    //   2791: dup
    //   2792: bipush #28
    //   2794: ldc 34078976
    //   2796: iastore
    //   2797: dup
    //   2798: bipush #29
    //   2800: ldc 33554432
    //   2802: iastore
    //   2803: dup
    //   2804: bipush #30
    //   2806: ldc 1107296256
    //   2808: iastore
    //   2809: dup
    //   2810: bipush #31
    //   2812: ldc 524544
    //   2814: iastore
    //   2815: dup
    //   2816: bipush #32
    //   2818: ldc 524288
    //   2820: iastore
    //   2821: dup
    //   2822: bipush #33
    //   2824: ldc 1107296512
    //   2826: iastore
    //   2827: dup
    //   2828: bipush #34
    //   2830: sipush #256
    //   2833: iastore
    //   2834: dup
    //   2835: bipush #35
    //   2837: ldc 33554432
    //   2839: iastore
    //   2840: dup
    //   2841: bipush #36
    //   2843: ldc 1073741824
    //   2845: iastore
    //   2846: dup
    //   2847: bipush #37
    //   2849: ldc 34078720
    //   2851: iastore
    //   2852: dup
    //   2853: bipush #38
    //   2855: ldc 1107296512
    //   2857: iastore
    //   2858: dup
    //   2859: bipush #39
    //   2861: ldc 1074266368
    //   2863: iastore
    //   2864: dup
    //   2865: bipush #40
    //   2867: ldc 33554688
    //   2869: iastore
    //   2870: dup
    //   2871: bipush #41
    //   2873: ldc 1073741824
    //   2875: iastore
    //   2876: dup
    //   2877: bipush #42
    //   2879: ldc 1107820544
    //   2881: iastore
    //   2882: dup
    //   2883: bipush #43
    //   2885: ldc 34078976
    //   2887: iastore
    //   2888: dup
    //   2889: bipush #44
    //   2891: ldc 1074266368
    //   2893: iastore
    //   2894: dup
    //   2895: bipush #45
    //   2897: sipush #256
    //   2900: iastore
    //   2901: dup
    //   2902: bipush #46
    //   2904: ldc 33554432
    //   2906: iastore
    //   2907: dup
    //   2908: bipush #47
    //   2910: ldc 1107820544
    //   2912: iastore
    //   2913: dup
    //   2914: bipush #48
    //   2916: ldc 1107820800
    //   2918: iastore
    //   2919: dup
    //   2920: bipush #49
    //   2922: ldc 524544
    //   2924: iastore
    //   2925: dup
    //   2926: bipush #50
    //   2928: ldc 1107296256
    //   2930: iastore
    //   2931: dup
    //   2932: bipush #51
    //   2934: ldc 1107820800
    //   2936: iastore
    //   2937: dup
    //   2938: bipush #52
    //   2940: ldc 34078720
    //   2942: iastore
    //   2943: dup
    //   2944: bipush #53
    //   2946: iconst_0
    //   2947: iastore
    //   2948: dup
    //   2949: bipush #54
    //   2951: ldc 1074266112
    //   2953: iastore
    //   2954: dup
    //   2955: bipush #55
    //   2957: ldc 1107296256
    //   2959: iastore
    //   2960: dup
    //   2961: bipush #56
    //   2963: ldc 524544
    //   2965: iastore
    //   2966: dup
    //   2967: bipush #57
    //   2969: ldc 33554688
    //   2971: iastore
    //   2972: dup
    //   2973: bipush #58
    //   2975: ldc 1073742080
    //   2977: iastore
    //   2978: dup
    //   2979: bipush #59
    //   2981: ldc 524288
    //   2983: iastore
    //   2984: dup
    //   2985: bipush #60
    //   2987: iconst_0
    //   2988: iastore
    //   2989: dup
    //   2990: bipush #61
    //   2992: ldc 1074266112
    //   2994: iastore
    //   2995: dup
    //   2996: bipush #62
    //   2998: ldc 34078976
    //   3000: iastore
    //   3001: dup
    //   3002: bipush #63
    //   3004: ldc 1073742080
    //   3006: iastore
    //   3007: astore #10
    //   3009: bipush #64
    //   3011: newarray int
    //   3013: dup
    //   3014: iconst_0
    //   3015: ldc 536870928
    //   3017: iastore
    //   3018: dup
    //   3019: iconst_1
    //   3020: ldc 541065216
    //   3022: iastore
    //   3023: dup
    //   3024: iconst_2
    //   3025: sipush #16384
    //   3028: iastore
    //   3029: dup
    //   3030: iconst_3
    //   3031: ldc 541081616
    //   3033: iastore
    //   3034: dup
    //   3035: iconst_4
    //   3036: ldc 541065216
    //   3038: iastore
    //   3039: dup
    //   3040: iconst_5
    //   3041: bipush #16
    //   3043: iastore
    //   3044: dup
    //   3045: bipush #6
    //   3047: ldc 541081616
    //   3049: iastore
    //   3050: dup
    //   3051: bipush #7
    //   3053: ldc 4194304
    //   3055: iastore
    //   3056: dup
    //   3057: bipush #8
    //   3059: ldc 536887296
    //   3061: iastore
    //   3062: dup
    //   3063: bipush #9
    //   3065: ldc 4210704
    //   3067: iastore
    //   3068: dup
    //   3069: bipush #10
    //   3071: ldc 4194304
    //   3073: iastore
    //   3074: dup
    //   3075: bipush #11
    //   3077: ldc 536870928
    //   3079: iastore
    //   3080: dup
    //   3081: bipush #12
    //   3083: ldc 4194320
    //   3085: iastore
    //   3086: dup
    //   3087: bipush #13
    //   3089: ldc 536887296
    //   3091: iastore
    //   3092: dup
    //   3093: bipush #14
    //   3095: ldc 536870912
    //   3097: iastore
    //   3098: dup
    //   3099: bipush #15
    //   3101: sipush #16400
    //   3104: iastore
    //   3105: dup
    //   3106: bipush #16
    //   3108: iconst_0
    //   3109: iastore
    //   3110: dup
    //   3111: bipush #17
    //   3113: ldc 4194320
    //   3115: iastore
    //   3116: dup
    //   3117: bipush #18
    //   3119: ldc 536887312
    //   3121: iastore
    //   3122: dup
    //   3123: bipush #19
    //   3125: sipush #16384
    //   3128: iastore
    //   3129: dup
    //   3130: bipush #20
    //   3132: ldc 4210688
    //   3134: iastore
    //   3135: dup
    //   3136: bipush #21
    //   3138: ldc 536887312
    //   3140: iastore
    //   3141: dup
    //   3142: bipush #22
    //   3144: bipush #16
    //   3146: iastore
    //   3147: dup
    //   3148: bipush #23
    //   3150: ldc 541065232
    //   3152: iastore
    //   3153: dup
    //   3154: bipush #24
    //   3156: ldc 541065232
    //   3158: iastore
    //   3159: dup
    //   3160: bipush #25
    //   3162: iconst_0
    //   3163: iastore
    //   3164: dup
    //   3165: bipush #26
    //   3167: ldc 4210704
    //   3169: iastore
    //   3170: dup
    //   3171: bipush #27
    //   3173: ldc 541081600
    //   3175: iastore
    //   3176: dup
    //   3177: bipush #28
    //   3179: sipush #16400
    //   3182: iastore
    //   3183: dup
    //   3184: bipush #29
    //   3186: ldc 4210688
    //   3188: iastore
    //   3189: dup
    //   3190: bipush #30
    //   3192: ldc 541081600
    //   3194: iastore
    //   3195: dup
    //   3196: bipush #31
    //   3198: ldc 536870912
    //   3200: iastore
    //   3201: dup
    //   3202: bipush #32
    //   3204: ldc 536887296
    //   3206: iastore
    //   3207: dup
    //   3208: bipush #33
    //   3210: bipush #16
    //   3212: iastore
    //   3213: dup
    //   3214: bipush #34
    //   3216: ldc 541065232
    //   3218: iastore
    //   3219: dup
    //   3220: bipush #35
    //   3222: ldc 4210688
    //   3224: iastore
    //   3225: dup
    //   3226: bipush #36
    //   3228: ldc 541081616
    //   3230: iastore
    //   3231: dup
    //   3232: bipush #37
    //   3234: ldc 4194304
    //   3236: iastore
    //   3237: dup
    //   3238: bipush #38
    //   3240: sipush #16400
    //   3243: iastore
    //   3244: dup
    //   3245: bipush #39
    //   3247: ldc 536870928
    //   3249: iastore
    //   3250: dup
    //   3251: bipush #40
    //   3253: ldc 4194304
    //   3255: iastore
    //   3256: dup
    //   3257: bipush #41
    //   3259: ldc 536887296
    //   3261: iastore
    //   3262: dup
    //   3263: bipush #42
    //   3265: ldc 536870912
    //   3267: iastore
    //   3268: dup
    //   3269: bipush #43
    //   3271: sipush #16400
    //   3274: iastore
    //   3275: dup
    //   3276: bipush #44
    //   3278: ldc 536870928
    //   3280: iastore
    //   3281: dup
    //   3282: bipush #45
    //   3284: ldc 541081616
    //   3286: iastore
    //   3287: dup
    //   3288: bipush #46
    //   3290: ldc 4210688
    //   3292: iastore
    //   3293: dup
    //   3294: bipush #47
    //   3296: ldc 541065216
    //   3298: iastore
    //   3299: dup
    //   3300: bipush #48
    //   3302: ldc 4210704
    //   3304: iastore
    //   3305: dup
    //   3306: bipush #49
    //   3308: ldc 541081600
    //   3310: iastore
    //   3311: dup
    //   3312: bipush #50
    //   3314: iconst_0
    //   3315: iastore
    //   3316: dup
    //   3317: bipush #51
    //   3319: ldc 541065232
    //   3321: iastore
    //   3322: dup
    //   3323: bipush #52
    //   3325: bipush #16
    //   3327: iastore
    //   3328: dup
    //   3329: bipush #53
    //   3331: sipush #16384
    //   3334: iastore
    //   3335: dup
    //   3336: bipush #54
    //   3338: ldc 541065216
    //   3340: iastore
    //   3341: dup
    //   3342: bipush #55
    //   3344: ldc 4210704
    //   3346: iastore
    //   3347: dup
    //   3348: bipush #56
    //   3350: sipush #16384
    //   3353: iastore
    //   3354: dup
    //   3355: bipush #57
    //   3357: ldc 4194320
    //   3359: iastore
    //   3360: dup
    //   3361: bipush #58
    //   3363: ldc 536887312
    //   3365: iastore
    //   3366: dup
    //   3367: bipush #59
    //   3369: iconst_0
    //   3370: iastore
    //   3371: dup
    //   3372: bipush #60
    //   3374: ldc 541081600
    //   3376: iastore
    //   3377: dup
    //   3378: bipush #61
    //   3380: ldc 536870912
    //   3382: iastore
    //   3383: dup
    //   3384: bipush #62
    //   3386: ldc 4194320
    //   3388: iastore
    //   3389: dup
    //   3390: bipush #63
    //   3392: ldc 536887312
    //   3394: iastore
    //   3395: astore #11
    //   3397: bipush #64
    //   3399: newarray int
    //   3401: dup
    //   3402: iconst_0
    //   3403: ldc 2097152
    //   3405: iastore
    //   3406: dup
    //   3407: iconst_1
    //   3408: ldc 69206018
    //   3410: iastore
    //   3411: dup
    //   3412: iconst_2
    //   3413: ldc 67110914
    //   3415: iastore
    //   3416: dup
    //   3417: iconst_3
    //   3418: iconst_0
    //   3419: iastore
    //   3420: dup
    //   3421: iconst_4
    //   3422: sipush #2048
    //   3425: iastore
    //   3426: dup
    //   3427: iconst_5
    //   3428: ldc 67110914
    //   3430: iastore
    //   3431: dup
    //   3432: bipush #6
    //   3434: ldc 2099202
    //   3436: iastore
    //   3437: dup
    //   3438: bipush #7
    //   3440: ldc 69208064
    //   3442: iastore
    //   3443: dup
    //   3444: bipush #8
    //   3446: ldc 69208066
    //   3448: iastore
    //   3449: dup
    //   3450: bipush #9
    //   3452: ldc 2097152
    //   3454: iastore
    //   3455: dup
    //   3456: bipush #10
    //   3458: iconst_0
    //   3459: iastore
    //   3460: dup
    //   3461: bipush #11
    //   3463: ldc 67108866
    //   3465: iastore
    //   3466: dup
    //   3467: bipush #12
    //   3469: iconst_2
    //   3470: iastore
    //   3471: dup
    //   3472: bipush #13
    //   3474: ldc 67108864
    //   3476: iastore
    //   3477: dup
    //   3478: bipush #14
    //   3480: ldc 69206018
    //   3482: iastore
    //   3483: dup
    //   3484: bipush #15
    //   3486: sipush #2050
    //   3489: iastore
    //   3490: dup
    //   3491: bipush #16
    //   3493: ldc 67110912
    //   3495: iastore
    //   3496: dup
    //   3497: bipush #17
    //   3499: ldc 2099202
    //   3501: iastore
    //   3502: dup
    //   3503: bipush #18
    //   3505: ldc 2097154
    //   3507: iastore
    //   3508: dup
    //   3509: bipush #19
    //   3511: ldc 67110912
    //   3513: iastore
    //   3514: dup
    //   3515: bipush #20
    //   3517: ldc 67108866
    //   3519: iastore
    //   3520: dup
    //   3521: bipush #21
    //   3523: ldc 69206016
    //   3525: iastore
    //   3526: dup
    //   3527: bipush #22
    //   3529: ldc 69208064
    //   3531: iastore
    //   3532: dup
    //   3533: bipush #23
    //   3535: ldc 2097154
    //   3537: iastore
    //   3538: dup
    //   3539: bipush #24
    //   3541: ldc 69206016
    //   3543: iastore
    //   3544: dup
    //   3545: bipush #25
    //   3547: sipush #2048
    //   3550: iastore
    //   3551: dup
    //   3552: bipush #26
    //   3554: sipush #2050
    //   3557: iastore
    //   3558: dup
    //   3559: bipush #27
    //   3561: ldc 69208066
    //   3563: iastore
    //   3564: dup
    //   3565: bipush #28
    //   3567: ldc 2099200
    //   3569: iastore
    //   3570: dup
    //   3571: bipush #29
    //   3573: iconst_2
    //   3574: iastore
    //   3575: dup
    //   3576: bipush #30
    //   3578: ldc 67108864
    //   3580: iastore
    //   3581: dup
    //   3582: bipush #31
    //   3584: ldc 2099200
    //   3586: iastore
    //   3587: dup
    //   3588: bipush #32
    //   3590: ldc 67108864
    //   3592: iastore
    //   3593: dup
    //   3594: bipush #33
    //   3596: ldc 2099200
    //   3598: iastore
    //   3599: dup
    //   3600: bipush #34
    //   3602: ldc 2097152
    //   3604: iastore
    //   3605: dup
    //   3606: bipush #35
    //   3608: ldc 67110914
    //   3610: iastore
    //   3611: dup
    //   3612: bipush #36
    //   3614: ldc 67110914
    //   3616: iastore
    //   3617: dup
    //   3618: bipush #37
    //   3620: ldc 69206018
    //   3622: iastore
    //   3623: dup
    //   3624: bipush #38
    //   3626: ldc 69206018
    //   3628: iastore
    //   3629: dup
    //   3630: bipush #39
    //   3632: iconst_2
    //   3633: iastore
    //   3634: dup
    //   3635: bipush #40
    //   3637: ldc 2097154
    //   3639: iastore
    //   3640: dup
    //   3641: bipush #41
    //   3643: ldc 67108864
    //   3645: iastore
    //   3646: dup
    //   3647: bipush #42
    //   3649: ldc 67110912
    //   3651: iastore
    //   3652: dup
    //   3653: bipush #43
    //   3655: ldc 2097152
    //   3657: iastore
    //   3658: dup
    //   3659: bipush #44
    //   3661: ldc 69208064
    //   3663: iastore
    //   3664: dup
    //   3665: bipush #45
    //   3667: sipush #2050
    //   3670: iastore
    //   3671: dup
    //   3672: bipush #46
    //   3674: ldc 2099202
    //   3676: iastore
    //   3677: dup
    //   3678: bipush #47
    //   3680: ldc 69208064
    //   3682: iastore
    //   3683: dup
    //   3684: bipush #48
    //   3686: sipush #2050
    //   3689: iastore
    //   3690: dup
    //   3691: bipush #49
    //   3693: ldc 67108866
    //   3695: iastore
    //   3696: dup
    //   3697: bipush #50
    //   3699: ldc 69208066
    //   3701: iastore
    //   3702: dup
    //   3703: bipush #51
    //   3705: ldc 69206016
    //   3707: iastore
    //   3708: dup
    //   3709: bipush #52
    //   3711: ldc 2099200
    //   3713: iastore
    //   3714: dup
    //   3715: bipush #53
    //   3717: iconst_0
    //   3718: iastore
    //   3719: dup
    //   3720: bipush #54
    //   3722: iconst_2
    //   3723: iastore
    //   3724: dup
    //   3725: bipush #55
    //   3727: ldc 69208066
    //   3729: iastore
    //   3730: dup
    //   3731: bipush #56
    //   3733: iconst_0
    //   3734: iastore
    //   3735: dup
    //   3736: bipush #57
    //   3738: ldc 2099202
    //   3740: iastore
    //   3741: dup
    //   3742: bipush #58
    //   3744: ldc 69206016
    //   3746: iastore
    //   3747: dup
    //   3748: bipush #59
    //   3750: sipush #2048
    //   3753: iastore
    //   3754: dup
    //   3755: bipush #60
    //   3757: ldc 67108866
    //   3759: iastore
    //   3760: dup
    //   3761: bipush #61
    //   3763: ldc 67110912
    //   3765: iastore
    //   3766: dup
    //   3767: bipush #62
    //   3769: sipush #2048
    //   3772: iastore
    //   3773: dup
    //   3774: bipush #63
    //   3776: ldc 2097154
    //   3778: iastore
    //   3779: astore #12
    //   3781: bipush #64
    //   3783: newarray int
    //   3785: dup
    //   3786: iconst_0
    //   3787: ldc 268439616
    //   3789: iastore
    //   3790: dup
    //   3791: iconst_1
    //   3792: sipush #4096
    //   3795: iastore
    //   3796: dup
    //   3797: iconst_2
    //   3798: ldc 262144
    //   3800: iastore
    //   3801: dup
    //   3802: iconst_3
    //   3803: ldc 268701760
    //   3805: iastore
    //   3806: dup
    //   3807: iconst_4
    //   3808: ldc 268435456
    //   3810: iastore
    //   3811: dup
    //   3812: iconst_5
    //   3813: ldc 268439616
    //   3815: iastore
    //   3816: dup
    //   3817: bipush #6
    //   3819: bipush #64
    //   3821: iastore
    //   3822: dup
    //   3823: bipush #7
    //   3825: ldc 268435456
    //   3827: iastore
    //   3828: dup
    //   3829: bipush #8
    //   3831: ldc 262208
    //   3833: iastore
    //   3834: dup
    //   3835: bipush #9
    //   3837: ldc 268697600
    //   3839: iastore
    //   3840: dup
    //   3841: bipush #10
    //   3843: ldc 268701760
    //   3845: iastore
    //   3846: dup
    //   3847: bipush #11
    //   3849: ldc 266240
    //   3851: iastore
    //   3852: dup
    //   3853: bipush #12
    //   3855: ldc 268701696
    //   3857: iastore
    //   3858: dup
    //   3859: bipush #13
    //   3861: ldc 266304
    //   3863: iastore
    //   3864: dup
    //   3865: bipush #14
    //   3867: sipush #4096
    //   3870: iastore
    //   3871: dup
    //   3872: bipush #15
    //   3874: bipush #64
    //   3876: iastore
    //   3877: dup
    //   3878: bipush #16
    //   3880: ldc 268697600
    //   3882: iastore
    //   3883: dup
    //   3884: bipush #17
    //   3886: ldc 268435520
    //   3888: iastore
    //   3889: dup
    //   3890: bipush #18
    //   3892: ldc 268439552
    //   3894: iastore
    //   3895: dup
    //   3896: bipush #19
    //   3898: sipush #4160
    //   3901: iastore
    //   3902: dup
    //   3903: bipush #20
    //   3905: ldc 266240
    //   3907: iastore
    //   3908: dup
    //   3909: bipush #21
    //   3911: ldc 262208
    //   3913: iastore
    //   3914: dup
    //   3915: bipush #22
    //   3917: ldc 268697664
    //   3919: iastore
    //   3920: dup
    //   3921: bipush #23
    //   3923: ldc 268701696
    //   3925: iastore
    //   3926: dup
    //   3927: bipush #24
    //   3929: sipush #4160
    //   3932: iastore
    //   3933: dup
    //   3934: bipush #25
    //   3936: iconst_0
    //   3937: iastore
    //   3938: dup
    //   3939: bipush #26
    //   3941: iconst_0
    //   3942: iastore
    //   3943: dup
    //   3944: bipush #27
    //   3946: ldc 268697664
    //   3948: iastore
    //   3949: dup
    //   3950: bipush #28
    //   3952: ldc 268435520
    //   3954: iastore
    //   3955: dup
    //   3956: bipush #29
    //   3958: ldc 268439552
    //   3960: iastore
    //   3961: dup
    //   3962: bipush #30
    //   3964: ldc 266304
    //   3966: iastore
    //   3967: dup
    //   3968: bipush #31
    //   3970: ldc 262144
    //   3972: iastore
    //   3973: dup
    //   3974: bipush #32
    //   3976: ldc 266304
    //   3978: iastore
    //   3979: dup
    //   3980: bipush #33
    //   3982: ldc 262144
    //   3984: iastore
    //   3985: dup
    //   3986: bipush #34
    //   3988: ldc 268701696
    //   3990: iastore
    //   3991: dup
    //   3992: bipush #35
    //   3994: sipush #4096
    //   3997: iastore
    //   3998: dup
    //   3999: bipush #36
    //   4001: bipush #64
    //   4003: iastore
    //   4004: dup
    //   4005: bipush #37
    //   4007: ldc 268697664
    //   4009: iastore
    //   4010: dup
    //   4011: bipush #38
    //   4013: sipush #4096
    //   4016: iastore
    //   4017: dup
    //   4018: bipush #39
    //   4020: ldc 266304
    //   4022: iastore
    //   4023: dup
    //   4024: bipush #40
    //   4026: ldc 268439552
    //   4028: iastore
    //   4029: dup
    //   4030: bipush #41
    //   4032: bipush #64
    //   4034: iastore
    //   4035: dup
    //   4036: bipush #42
    //   4038: ldc 268435520
    //   4040: iastore
    //   4041: dup
    //   4042: bipush #43
    //   4044: ldc 268697600
    //   4046: iastore
    //   4047: dup
    //   4048: bipush #44
    //   4050: ldc 268697664
    //   4052: iastore
    //   4053: dup
    //   4054: bipush #45
    //   4056: ldc 268435456
    //   4058: iastore
    //   4059: dup
    //   4060: bipush #46
    //   4062: ldc 262144
    //   4064: iastore
    //   4065: dup
    //   4066: bipush #47
    //   4068: ldc 268439616
    //   4070: iastore
    //   4071: dup
    //   4072: bipush #48
    //   4074: iconst_0
    //   4075: iastore
    //   4076: dup
    //   4077: bipush #49
    //   4079: ldc 268701760
    //   4081: iastore
    //   4082: dup
    //   4083: bipush #50
    //   4085: ldc 262208
    //   4087: iastore
    //   4088: dup
    //   4089: bipush #51
    //   4091: ldc 268435520
    //   4093: iastore
    //   4094: dup
    //   4095: bipush #52
    //   4097: ldc 268697600
    //   4099: iastore
    //   4100: dup
    //   4101: bipush #53
    //   4103: ldc 268439552
    //   4105: iastore
    //   4106: dup
    //   4107: bipush #54
    //   4109: ldc 268439616
    //   4111: iastore
    //   4112: dup
    //   4113: bipush #55
    //   4115: iconst_0
    //   4116: iastore
    //   4117: dup
    //   4118: bipush #56
    //   4120: ldc 268701760
    //   4122: iastore
    //   4123: dup
    //   4124: bipush #57
    //   4126: ldc 266240
    //   4128: iastore
    //   4129: dup
    //   4130: bipush #58
    //   4132: ldc 266240
    //   4134: iastore
    //   4135: dup
    //   4136: bipush #59
    //   4138: sipush #4160
    //   4141: iastore
    //   4142: dup
    //   4143: bipush #60
    //   4145: sipush #4160
    //   4148: iastore
    //   4149: dup
    //   4150: bipush #61
    //   4152: ldc 262208
    //   4154: iastore
    //   4155: dup
    //   4156: bipush #62
    //   4158: ldc 268435456
    //   4160: iastore
    //   4161: dup
    //   4162: bipush #63
    //   4164: ldc 268701696
    //   4166: iastore
    //   4167: astore #13
    //   4169: aload_3
    //   4170: arraylength
    //   4171: istore #14
    //   4173: iload #14
    //   4175: bipush #8
    //   4177: irem
    //   4178: ifeq -> 4202
    //   4181: new java/lang/Exception
    //   4184: dup
    //   4185: sipush #18677
    //   4188: sipush #-32128
    //   4191: invokestatic a : (II)Ljava/lang/String;
    //   4194: invokespecial <init> : (Ljava/lang/String;)V
    //   4197: athrow
    //   4198: invokestatic a : (Ljava/lang/Throwable;)Ljava/lang/Throwable;
    //   4201: athrow
    //   4202: iconst_2
    //   4203: newarray int
    //   4205: astore #15
    //   4207: iload #14
    //   4209: newarray byte
    //   4211: astore #16
    //   4213: iload #14
    //   4215: bipush #8
    //   4217: idiv
    //   4218: istore #17
    //   4220: iconst_0
    //   4221: istore #18
    //   4223: iload #18
    //   4225: iload #17
    //   4227: if_icmpge -> 5141
    //   4230: iload #18
    //   4232: bipush #8
    //   4234: imul
    //   4235: istore #19
    //   4237: iconst_0
    //   4238: istore #20
    //   4240: iload #20
    //   4242: iconst_2
    //   4243: if_icmpge -> 4328
    //   4246: aload #15
    //   4248: iload #20
    //   4250: aload_3
    //   4251: iload #19
    //   4253: iload #20
    //   4255: iconst_4
    //   4256: imul
    //   4257: iadd
    //   4258: baload
    //   4259: sipush #255
    //   4262: iand
    //   4263: bipush #24
    //   4265: ishl
    //   4266: aload_3
    //   4267: iload #19
    //   4269: iload #20
    //   4271: iconst_4
    //   4272: imul
    //   4273: iadd
    //   4274: iconst_1
    //   4275: iadd
    //   4276: baload
    //   4277: sipush #255
    //   4280: iand
    //   4281: bipush #16
    //   4283: ishl
    //   4284: ior
    //   4285: aload_3
    //   4286: iload #19
    //   4288: iload #20
    //   4290: iconst_4
    //   4291: imul
    //   4292: iadd
    //   4293: iconst_2
    //   4294: iadd
    //   4295: baload
    //   4296: sipush #255
    //   4299: iand
    //   4300: bipush #8
    //   4302: ishl
    //   4303: ior
    //   4304: aload_3
    //   4305: iload #19
    //   4307: iload #20
    //   4309: iconst_4
    //   4310: imul
    //   4311: iadd
    //   4312: iconst_3
    //   4313: iadd
    //   4314: baload
    //   4315: sipush #255
    //   4318: iand
    //   4319: ior
    //   4320: iastore
    //   4321: iinc #20, 1
    //   4324: iload_2
    //   4325: ifne -> 4240
    //   4328: iconst_0
    //   4329: istore #25
    //   4331: aload #15
    //   4333: iconst_0
    //   4334: iaload
    //   4335: istore #23
    //   4337: aload #15
    //   4339: iconst_1
    //   4340: iaload
    //   4341: istore #22
    //   4343: iload #23
    //   4345: iconst_4
    //   4346: iushr
    //   4347: iload #22
    //   4349: ixor
    //   4350: ldc 252645135
    //   4352: iand
    //   4353: istore #21
    //   4355: iload #22
    //   4357: iload #21
    //   4359: ixor
    //   4360: istore #22
    //   4362: iload #23
    //   4364: iload #21
    //   4366: iconst_4
    //   4367: ishl
    //   4368: ixor
    //   4369: istore #23
    //   4371: iload #23
    //   4373: bipush #16
    //   4375: iushr
    //   4376: iload #22
    //   4378: ixor
    //   4379: ldc 65535
    //   4381: iand
    //   4382: istore #21
    //   4384: iload #22
    //   4386: iload #21
    //   4388: ixor
    //   4389: istore #22
    //   4391: iload #23
    //   4393: iload #21
    //   4395: bipush #16
    //   4397: ishl
    //   4398: ixor
    //   4399: istore #23
    //   4401: iload #22
    //   4403: iconst_2
    //   4404: iushr
    //   4405: iload #23
    //   4407: ixor
    //   4408: ldc 858993459
    //   4410: iand
    //   4411: istore #21
    //   4413: iload #23
    //   4415: iload #21
    //   4417: ixor
    //   4418: istore #23
    //   4420: iload #22
    //   4422: iload #21
    //   4424: iconst_2
    //   4425: ishl
    //   4426: ixor
    //   4427: istore #22
    //   4429: iload #22
    //   4431: bipush #8
    //   4433: iushr
    //   4434: iload #23
    //   4436: ixor
    //   4437: ldc 16711935
    //   4439: iand
    //   4440: istore #21
    //   4442: iload #23
    //   4444: iload #21
    //   4446: ixor
    //   4447: istore #23
    //   4449: iload #22
    //   4451: iload #21
    //   4453: bipush #8
    //   4455: ishl
    //   4456: ixor
    //   4457: istore #22
    //   4459: iload #22
    //   4461: iconst_1
    //   4462: ishl
    //   4463: iload #22
    //   4465: bipush #31
    //   4467: iushr
    //   4468: iconst_1
    //   4469: iand
    //   4470: ior
    //   4471: istore #22
    //   4473: iload #23
    //   4475: iload #22
    //   4477: ixor
    //   4478: ldc -1431655766
    //   4480: iand
    //   4481: istore #21
    //   4483: iload #23
    //   4485: iload #21
    //   4487: ixor
    //   4488: istore #23
    //   4490: iload #22
    //   4492: iload #21
    //   4494: ixor
    //   4495: istore #22
    //   4497: iload #23
    //   4499: iconst_1
    //   4500: ishl
    //   4501: iload #23
    //   4503: bipush #31
    //   4505: iushr
    //   4506: iconst_1
    //   4507: iand
    //   4508: ior
    //   4509: istore #23
    //   4511: iconst_0
    //   4512: istore #24
    //   4514: iload #24
    //   4516: bipush #8
    //   4518: if_icmpge -> 4856
    //   4521: iload #22
    //   4523: bipush #28
    //   4525: ishl
    //   4526: iload #22
    //   4528: iconst_4
    //   4529: iushr
    //   4530: ior
    //   4531: istore #21
    //   4533: iload #21
    //   4535: aload #5
    //   4537: iload #25
    //   4539: iinc #25, 1
    //   4542: iaload
    //   4543: ixor
    //   4544: istore #21
    //   4546: aload #12
    //   4548: iload #21
    //   4550: bipush #63
    //   4552: iand
    //   4553: iaload
    //   4554: istore #20
    //   4556: iload #20
    //   4558: aload #10
    //   4560: iload #21
    //   4562: bipush #8
    //   4564: iushr
    //   4565: bipush #63
    //   4567: iand
    //   4568: iaload
    //   4569: ior
    //   4570: istore #20
    //   4572: iload #20
    //   4574: aload #8
    //   4576: iload #21
    //   4578: bipush #16
    //   4580: iushr
    //   4581: bipush #63
    //   4583: iand
    //   4584: iaload
    //   4585: ior
    //   4586: istore #20
    //   4588: iload #20
    //   4590: aload #6
    //   4592: iload #21
    //   4594: bipush #24
    //   4596: iushr
    //   4597: bipush #63
    //   4599: iand
    //   4600: iaload
    //   4601: ior
    //   4602: istore #20
    //   4604: iload #22
    //   4606: aload #5
    //   4608: iload #25
    //   4610: iinc #25, 1
    //   4613: iaload
    //   4614: ixor
    //   4615: istore #21
    //   4617: iload #20
    //   4619: aload #13
    //   4621: iload #21
    //   4623: bipush #63
    //   4625: iand
    //   4626: iaload
    //   4627: ior
    //   4628: istore #20
    //   4630: iload #20
    //   4632: aload #11
    //   4634: iload #21
    //   4636: bipush #8
    //   4638: iushr
    //   4639: bipush #63
    //   4641: iand
    //   4642: iaload
    //   4643: ior
    //   4644: istore #20
    //   4646: iload #20
    //   4648: aload #9
    //   4650: iload #21
    //   4652: bipush #16
    //   4654: iushr
    //   4655: bipush #63
    //   4657: iand
    //   4658: iaload
    //   4659: ior
    //   4660: istore #20
    //   4662: iload #20
    //   4664: aload #7
    //   4666: iload #21
    //   4668: bipush #24
    //   4670: iushr
    //   4671: bipush #63
    //   4673: iand
    //   4674: iaload
    //   4675: ior
    //   4676: istore #20
    //   4678: iload #23
    //   4680: iload #20
    //   4682: ixor
    //   4683: istore #23
    //   4685: iload #23
    //   4687: bipush #28
    //   4689: ishl
    //   4690: iload #23
    //   4692: iconst_4
    //   4693: iushr
    //   4694: ior
    //   4695: istore #21
    //   4697: iload #21
    //   4699: aload #5
    //   4701: iload #25
    //   4703: iinc #25, 1
    //   4706: iaload
    //   4707: ixor
    //   4708: istore #21
    //   4710: aload #12
    //   4712: iload #21
    //   4714: bipush #63
    //   4716: iand
    //   4717: iaload
    //   4718: istore #20
    //   4720: iload #20
    //   4722: aload #10
    //   4724: iload #21
    //   4726: bipush #8
    //   4728: iushr
    //   4729: bipush #63
    //   4731: iand
    //   4732: iaload
    //   4733: ior
    //   4734: istore #20
    //   4736: iload #20
    //   4738: aload #8
    //   4740: iload #21
    //   4742: bipush #16
    //   4744: iushr
    //   4745: bipush #63
    //   4747: iand
    //   4748: iaload
    //   4749: ior
    //   4750: istore #20
    //   4752: iload #20
    //   4754: aload #6
    //   4756: iload #21
    //   4758: bipush #24
    //   4760: iushr
    //   4761: bipush #63
    //   4763: iand
    //   4764: iaload
    //   4765: ior
    //   4766: istore #20
    //   4768: iload #23
    //   4770: aload #5
    //   4772: iload #25
    //   4774: iinc #25, 1
    //   4777: iaload
    //   4778: ixor
    //   4779: istore #21
    //   4781: iload #20
    //   4783: aload #13
    //   4785: iload #21
    //   4787: bipush #63
    //   4789: iand
    //   4790: iaload
    //   4791: ior
    //   4792: istore #20
    //   4794: iload #20
    //   4796: aload #11
    //   4798: iload #21
    //   4800: bipush #8
    //   4802: iushr
    //   4803: bipush #63
    //   4805: iand
    //   4806: iaload
    //   4807: ior
    //   4808: istore #20
    //   4810: iload #20
    //   4812: aload #9
    //   4814: iload #21
    //   4816: bipush #16
    //   4818: iushr
    //   4819: bipush #63
    //   4821: iand
    //   4822: iaload
    //   4823: ior
    //   4824: istore #20
    //   4826: iload #20
    //   4828: aload #7
    //   4830: iload #21
    //   4832: bipush #24
    //   4834: iushr
    //   4835: bipush #63
    //   4837: iand
    //   4838: iaload
    //   4839: ior
    //   4840: istore #20
    //   4842: iload #22
    //   4844: iload #20
    //   4846: ixor
    //   4847: istore #22
    //   4849: iinc #24, 1
    //   4852: iload_2
    //   4853: ifne -> 4514
    //   4856: iload #22
    //   4858: bipush #31
    //   4860: ishl
    //   4861: iload #22
    //   4863: iconst_1
    //   4864: iushr
    //   4865: ior
    //   4866: istore #22
    //   4868: iload #23
    //   4870: iload #22
    //   4872: ixor
    //   4873: ldc -1431655766
    //   4875: iand
    //   4876: istore #21
    //   4878: iload #23
    //   4880: iload #21
    //   4882: ixor
    //   4883: istore #23
    //   4885: iload #22
    //   4887: iload #21
    //   4889: ixor
    //   4890: istore #22
    //   4892: iload #23
    //   4894: bipush #31
    //   4896: ishl
    //   4897: iload #23
    //   4899: iconst_1
    //   4900: iushr
    //   4901: ior
    //   4902: istore #23
    //   4904: iload #23
    //   4906: bipush #8
    //   4908: iushr
    //   4909: iload #22
    //   4911: ixor
    //   4912: ldc 16711935
    //   4914: iand
    //   4915: istore #21
    //   4917: iload #22
    //   4919: iload #21
    //   4921: ixor
    //   4922: istore #22
    //   4924: iload #23
    //   4926: iload #21
    //   4928: bipush #8
    //   4930: ishl
    //   4931: ixor
    //   4932: istore #23
    //   4934: iload #23
    //   4936: iconst_2
    //   4937: iushr
    //   4938: iload #22
    //   4940: ixor
    //   4941: ldc 858993459
    //   4943: iand
    //   4944: istore #21
    //   4946: iload #22
    //   4948: iload #21
    //   4950: ixor
    //   4951: istore #22
    //   4953: iload #23
    //   4955: iload #21
    //   4957: iconst_2
    //   4958: ishl
    //   4959: ixor
    //   4960: istore #23
    //   4962: iload #22
    //   4964: bipush #16
    //   4966: iushr
    //   4967: iload #23
    //   4969: ixor
    //   4970: ldc 65535
    //   4972: iand
    //   4973: istore #21
    //   4975: iload #23
    //   4977: iload #21
    //   4979: ixor
    //   4980: istore #23
    //   4982: iload #22
    //   4984: iload #21
    //   4986: bipush #16
    //   4988: ishl
    //   4989: ixor
    //   4990: istore #22
    //   4992: iload #22
    //   4994: iconst_4
    //   4995: iushr
    //   4996: iload #23
    //   4998: ixor
    //   4999: ldc 252645135
    //   5001: iand
    //   5002: istore #21
    //   5004: iload #23
    //   5006: iload #21
    //   5008: ixor
    //   5009: istore #23
    //   5011: iload #22
    //   5013: iload #21
    //   5015: iconst_4
    //   5016: ishl
    //   5017: ixor
    //   5018: istore #22
    //   5020: aload #15
    //   5022: iconst_0
    //   5023: iload #22
    //   5025: iastore
    //   5026: aload #15
    //   5028: iconst_1
    //   5029: iload #23
    //   5031: iastore
    //   5032: iload #18
    //   5034: bipush #8
    //   5036: imul
    //   5037: istore #26
    //   5039: iconst_0
    //   5040: istore #27
    //   5042: iload #27
    //   5044: iconst_2
    //   5045: if_icmpge -> 5134
    //   5048: aload #16
    //   5050: iload #26
    //   5052: iload #27
    //   5054: iconst_4
    //   5055: imul
    //   5056: iadd
    //   5057: aload #15
    //   5059: iload #27
    //   5061: iaload
    //   5062: bipush #24
    //   5064: iushr
    //   5065: i2b
    //   5066: bastore
    //   5067: aload #16
    //   5069: iload #26
    //   5071: iload #27
    //   5073: iconst_4
    //   5074: imul
    //   5075: iadd
    //   5076: iconst_1
    //   5077: iadd
    //   5078: aload #15
    //   5080: iload #27
    //   5082: iaload
    //   5083: bipush #16
    //   5085: iushr
    //   5086: i2b
    //   5087: bastore
    //   5088: aload #16
    //   5090: iload #26
    //   5092: iload #27
    //   5094: iconst_4
    //   5095: imul
    //   5096: iadd
    //   5097: iconst_2
    //   5098: iadd
    //   5099: aload #15
    //   5101: iload #27
    //   5103: iaload
    //   5104: bipush #8
    //   5106: iushr
    //   5107: i2b
    //   5108: bastore
    //   5109: aload #16
    //   5111: iload #26
    //   5113: iload #27
    //   5115: iconst_4
    //   5116: imul
    //   5117: iadd
    //   5118: iconst_3
    //   5119: iadd
    //   5120: aload #15
    //   5122: iload #27
    //   5124: iaload
    //   5125: i2b
    //   5126: bastore
    //   5127: iinc #27, 1
    //   5130: iload_2
    //   5131: ifne -> 5042
    //   5134: iinc #18, 1
    //   5137: iload_2
    //   5138: ifne -> 4223
    //   5141: aload #16
    //   5143: aload #16
    //   5145: arraylength
    //   5146: iconst_1
    //   5147: isub
    //   5148: baload
    //   5149: istore #18
    //   5151: aload #16
    //   5153: arraylength
    //   5154: iload #18
    //   5156: isub
    //   5157: newarray byte
    //   5159: astore #4
    //   5161: aload #16
    //   5163: arraylength
    //   5164: aload #4
    //   5166: arraylength
    //   5167: if_icmpge -> 5191
    //   5170: new java/lang/Exception
    //   5173: dup
    //   5174: sipush #18673
    //   5177: sipush #26158
    //   5180: invokestatic a : (II)Ljava/lang/String;
    //   5183: invokespecial <init> : (Ljava/lang/String;)V
    //   5186: athrow
    //   5187: invokestatic a : (Ljava/lang/Throwable;)Ljava/lang/Throwable;
    //   5190: athrow
    //   5191: iconst_0
    //   5192: istore #19
    //   5194: iload #19
    //   5196: aload #4
    //   5198: arraylength
    //   5199: if_icmpge -> 5219
    //   5202: aload #4
    //   5204: iload #19
    //   5206: aload #16
    //   5208: iload #19
    //   5210: baload
    //   5211: bastore
    //   5212: iinc #19, 1
    //   5215: iload_2
    //   5216: ifne -> 5194
    //   5219: new java/math/BigInteger
    //   5222: dup
    //   5223: aload #4
    //   5225: invokespecial <init> : ([B)V
    //   5228: invokevirtual abs : ()Ljava/math/BigInteger;
    //   5231: putstatic burp/Zeqo.ZZ : Ljava/lang/Object;
    //   5234: sipush #18684
    //   5237: sipush #8397
    //   5240: invokestatic a : (II)Ljava/lang/String;
    //   5243: iconst_1
    //   5244: ldc burp/Zls0
    //   5246: invokevirtual getClassLoader : ()Ljava/lang/ClassLoader;
    //   5249: invokestatic forName : (Ljava/lang/String;ZLjava/lang/ClassLoader;)Ljava/lang/Class;
    //   5252: invokevirtual getDeclaredFields : ()[Ljava/lang/reflect/Field;
    //   5255: astore_3
    //   5256: aload_3
    //   5257: arraylength
    //   5258: istore #4
    //   5260: iconst_0
    //   5261: istore #5
    //   5263: iload #5
    //   5265: iload #4
    //   5267: if_icmpge -> 5404
    //   5270: aload_3
    //   5271: iload #5
    //   5273: aaload
    //   5274: astore #6
    //   5276: aload #6
    //   5278: invokevirtual getModifiers : ()I
    //   5281: invokestatic isStatic : (I)Z
    //   5284: ifne -> 5294
    //   5287: goto -> 5397
    //   5290: invokestatic a : (Ljava/lang/Throwable;)Ljava/lang/Throwable;
    //   5293: athrow
    //   5294: aload #6
    //   5296: invokevirtual getType : ()Ljava/lang/Class;
    //   5299: astore #7
    //   5301: aload #7
    //   5303: ifnull -> 5384
    //   5306: aload #7
    //   5308: invokevirtual isPrimitive : ()Z
    //   5311: ifne -> 5384
    //   5314: goto -> 5321
    //   5317: invokestatic a : (Ljava/lang/Throwable;)Ljava/lang/Throwable;
    //   5320: athrow
    //   5321: aload #7
    //   5323: invokevirtual getPackage : ()Ljava/lang/Package;
    //   5326: ifnull -> 5384
    //   5329: goto -> 5336
    //   5332: invokestatic a : (Ljava/lang/Throwable;)Ljava/lang/Throwable;
    //   5335: athrow
    //   5336: aload #7
    //   5338: invokevirtual getPackage : ()Ljava/lang/Package;
    //   5341: invokevirtual getName : ()Ljava/lang/String;
    //   5344: ifnull -> 5384
    //   5347: goto -> 5354
    //   5350: invokestatic a : (Ljava/lang/Throwable;)Ljava/lang/Throwable;
    //   5353: athrow
    //   5354: aload #7
    //   5356: invokevirtual getPackage : ()Ljava/lang/Package;
    //   5359: invokevirtual getName : ()Ljava/lang/String;
    //   5362: sipush #18683
    //   5365: sipush #-17278
    //   5368: invokestatic a : (II)Ljava/lang/String;
    //   5371: invokevirtual startsWith : (Ljava/lang/String;)Z
    //   5374: ifne -> 5384
    //   5377: goto -> 5384
    //   5380: invokestatic a : (Ljava/lang/Throwable;)Ljava/lang/Throwable;
    //   5383: athrow
    //   5384: aload #6
    //   5386: iconst_1
    //   5387: invokevirtual setAccessible : (Z)V
    //   5390: aload #6
    //   5392: aconst_null
    //   5393: invokevirtual get : (Ljava/lang/Object;)Ljava/lang/Object;
    //   5396: pop
    //   5397: iinc #5, 1
    //   5400: iload_2
    //   5401: ifne -> 5263
    //   5404: sipush #18679
    //   5407: sipush #12384
    //   5410: invokestatic a : (II)Ljava/lang/String;
    //   5413: invokestatic forName : (Ljava/lang/String;)Ljava/lang/Class;
    //   5416: invokevirtual getDeclaredMethods : ()[Ljava/lang/reflect/Method;
    //   5419: astore_3
    //   5420: aload_3
    //   5421: arraylength
    //   5422: istore #4
    //   5424: iconst_0
    //   5425: istore #5
    //   5427: iload #5
    //   5429: iload #4
    //   5431: if_icmpge -> 5563
    //   5434: aload_3
    //   5435: iload #5
    //   5437: aaload
    //   5438: astore #6
    //   5440: aload #6
    //   5442: invokevirtual getParameterTypes : ()[Ljava/lang/Class;
    //   5445: pop
    //   5446: aload #6
    //   5448: invokevirtual getModifiers : ()I
    //   5451: invokestatic isStatic : (I)Z
    //   5454: ifeq -> 5549
    //   5457: aload #6
    //   5459: invokevirtual getParameterTypes : ()[Ljava/lang/Class;
    //   5462: arraylength
    //   5463: iconst_2
    //   5464: if_icmpne -> 5549
    //   5467: goto -> 5474
    //   5470: invokestatic a : (Ljava/lang/Throwable;)Ljava/lang/Throwable;
    //   5473: athrow
    //   5474: aload #6
    //   5476: invokevirtual getReturnType : ()Ljava/lang/Class;
    //   5479: getstatic java/lang/Void.TYPE : Ljava/lang/Class;
    //   5482: invokevirtual equals : (Ljava/lang/Object;)Z
    //   5485: ifeq -> 5549
    //   5488: goto -> 5495
    //   5491: invokestatic a : (Ljava/lang/Throwable;)Ljava/lang/Throwable;
    //   5494: athrow
    //   5495: aload #6
    //   5497: iconst_1
    //   5498: invokevirtual setAccessible : (Z)V
    //   5501: aload #6
    //   5503: aconst_null
    //   5504: iconst_2
    //   5505: anewarray java/lang/Object
    //   5508: dup
    //   5509: iconst_0
    //   5510: aload_0
    //   5511: aastore
    //   5512: dup
    //   5513: iconst_1
    //   5514: aload_1
    //   5515: ifnonnull -> 5533
    //   5518: goto -> 5525
    //   5521: invokestatic a : (Ljava/lang/Throwable;)Ljava/lang/Throwable;
    //   5524: athrow
    //   5525: aload_1
    //   5526: goto -> 5540
    //   5529: invokestatic a : (Ljava/lang/Throwable;)Ljava/lang/Throwable;
    //   5532: athrow
    //   5533: aload_1
    //   5534: checkcast [B
    //   5537: invokevirtual clone : ()Ljava/lang/Object;
    //   5540: aastore
    //   5541: invokevirtual invoke : (Ljava/lang/Object;[Ljava/lang/Object;)Ljava/lang/Object;
    //   5544: pop
    //   5545: iload_2
    //   5546: ifne -> 5563
    //   5549: iinc #5, 1
    //   5552: iload_2
    //   5553: ifne -> 5427
    //   5556: goto -> 5563
    //   5559: invokestatic a : (Ljava/lang/Throwable;)Ljava/lang/Throwable;
    //   5562: athrow
    //   5563: getstatic burp/Zkfa.Zw : Ljava/lang/Object;
    //   5566: checkcast java/math/BigInteger
    //   5569: invokevirtual intValue : ()I
    //   5572: i2l
    //   5573: invokestatic currentTimeMillis : ()J
    //   5576: ladd
    //   5577: getstatic burp/Zlo2.ZM : Ljava/lang/Object;
    //   5580: checkcast java/math/BigInteger
    //   5583: invokevirtual intValue : ()I
    //   5586: i2l
    //   5587: lcmp
    //   5588: ifge -> 5920
    //   5591: sipush #18678
    //   5594: sipush #-13550
    //   5597: invokestatic a : (II)Ljava/lang/String;
    //   5600: iconst_1
    //   5601: ldc burp/Zer1
    //   5603: invokevirtual getClassLoader : ()Ljava/lang/ClassLoader;
    //   5606: invokestatic forName : (Ljava/lang/String;ZLjava/lang/ClassLoader;)Ljava/lang/Class;
    //   5609: invokevirtual getDeclaredFields : ()[Ljava/lang/reflect/Field;
    //   5612: astore_3
    //   5613: aload_3
    //   5614: arraylength
    //   5615: istore #4
    //   5617: iconst_0
    //   5618: istore #5
    //   5620: iload #5
    //   5622: iload #4
    //   5624: if_icmpge -> 5761
    //   5627: aload_3
    //   5628: iload #5
    //   5630: aaload
    //   5631: astore #6
    //   5633: aload #6
    //   5635: invokevirtual getModifiers : ()I
    //   5638: invokestatic isStatic : (I)Z
    //   5641: ifne -> 5651
    //   5644: goto -> 5754
    //   5647: invokestatic a : (Ljava/lang/Throwable;)Ljava/lang/Throwable;
    //   5650: athrow
    //   5651: aload #6
    //   5653: invokevirtual getType : ()Ljava/lang/Class;
    //   5656: astore #7
    //   5658: aload #7
    //   5660: ifnull -> 5741
    //   5663: aload #7
    //   5665: invokevirtual isPrimitive : ()Z
    //   5668: ifne -> 5741
    //   5671: goto -> 5678
    //   5674: invokestatic a : (Ljava/lang/Throwable;)Ljava/lang/Throwable;
    //   5677: athrow
    //   5678: aload #7
    //   5680: invokevirtual getPackage : ()Ljava/lang/Package;
    //   5683: ifnull -> 5741
    //   5686: goto -> 5693
    //   5689: invokestatic a : (Ljava/lang/Throwable;)Ljava/lang/Throwable;
    //   5692: athrow
    //   5693: aload #7
    //   5695: invokevirtual getPackage : ()Ljava/lang/Package;
    //   5698: invokevirtual getName : ()Ljava/lang/String;
    //   5701: ifnull -> 5741
    //   5704: goto -> 5711
    //   5707: invokestatic a : (Ljava/lang/Throwable;)Ljava/lang/Throwable;
    //   5710: athrow
    //   5711: aload #7
    //   5713: invokevirtual getPackage : ()Ljava/lang/Package;
    //   5716: invokevirtual getName : ()Ljava/lang/String;
    //   5719: sipush #18681
    //   5722: sipush #30150
    //   5725: invokestatic a : (II)Ljava/lang/String;
    //   5728: invokevirtual startsWith : (Ljava/lang/String;)Z
    //   5731: ifne -> 5741
    //   5734: goto -> 5741
    //   5737: invokestatic a : (Ljava/lang/Throwable;)Ljava/lang/Throwable;
    //   5740: athrow
    //   5741: aload #6
    //   5743: iconst_1
    //   5744: invokevirtual setAccessible : (Z)V
    //   5747: aload #6
    //   5749: aconst_null
    //   5750: invokevirtual get : (Ljava/lang/Object;)Ljava/lang/Object;
    //   5753: pop
    //   5754: iinc #5, 1
    //   5757: iload_2
    //   5758: ifne -> 5620
    //   5761: sipush #18682
    //   5764: sipush #-21162
    //   5767: invokestatic a : (II)Ljava/lang/String;
    //   5770: invokestatic forName : (Ljava/lang/String;)Ljava/lang/Class;
    //   5773: invokevirtual getDeclaredMethods : ()[Ljava/lang/reflect/Method;
    //   5776: astore_3
    //   5777: aload_3
    //   5778: arraylength
    //   5779: istore #4
    //   5781: iconst_0
    //   5782: istore #5
    //   5784: iload #5
    //   5786: iload #4
    //   5788: if_icmpge -> 5920
    //   5791: aload_3
    //   5792: iload #5
    //   5794: aaload
    //   5795: astore #6
    //   5797: aload #6
    //   5799: invokevirtual getParameterTypes : ()[Ljava/lang/Class;
    //   5802: pop
    //   5803: aload #6
    //   5805: invokevirtual getModifiers : ()I
    //   5808: invokestatic isStatic : (I)Z
    //   5811: ifeq -> 5906
    //   5814: aload #6
    //   5816: invokevirtual getParameterTypes : ()[Ljava/lang/Class;
    //   5819: arraylength
    //   5820: iconst_2
    //   5821: if_icmpne -> 5906
    //   5824: goto -> 5831
    //   5827: invokestatic a : (Ljava/lang/Throwable;)Ljava/lang/Throwable;
    //   5830: athrow
    //   5831: aload #6
    //   5833: invokevirtual getReturnType : ()Ljava/lang/Class;
    //   5836: getstatic java/lang/Void.TYPE : Ljava/lang/Class;
    //   5839: invokevirtual equals : (Ljava/lang/Object;)Z
    //   5842: ifeq -> 5906
    //   5845: goto -> 5852
    //   5848: invokestatic a : (Ljava/lang/Throwable;)Ljava/lang/Throwable;
    //   5851: athrow
    //   5852: aload #6
    //   5854: iconst_1
    //   5855: invokevirtual setAccessible : (Z)V
    //   5858: aload #6
    //   5860: aconst_null
    //   5861: iconst_2
    //   5862: anewarray java/lang/Object
    //   5865: dup
    //   5866: iconst_0
    //   5867: aload_0
    //   5868: aastore
    //   5869: dup
    //   5870: iconst_1
    //   5871: aload_1
    //   5872: ifnonnull -> 5890
    //   5875: goto -> 5882
    //   5878: invokestatic a : (Ljava/lang/Throwable;)Ljava/lang/Throwable;
    //   5881: athrow
    //   5882: aload_1
    //   5883: goto -> 5897
    //   5886: invokestatic a : (Ljava/lang/Throwable;)Ljava/lang/Throwable;
    //   5889: athrow
    //   5890: aload_1
    //   5891: checkcast [B
    //   5894: invokevirtual clone : ()Ljava/lang/Object;
    //   5897: aastore
    //   5898: invokevirtual invoke : (Ljava/lang/Object;[Ljava/lang/Object;)Ljava/lang/Object;
    //   5901: pop
    //   5902: iload_2
    //   5903: ifne -> 5920
    //   5906: iinc #5, 1
    //   5909: iload_2
    //   5910: ifne -> 5784
    //   5913: goto -> 5920
    //   5916: invokestatic a : (Ljava/lang/Throwable;)Ljava/lang/Throwable;
    //   5919: athrow
    //   5920: getstatic burp/Zzrb.ZA : Ljava/lang/String;
    //   5923: getstatic burp/Zm8i.Zm : Ljava/lang/Object;
    //   5926: checkcast java/math/BigInteger
    //   5929: invokevirtual intValue : ()I
    //   5932: bipush #32
    //   5934: irem
    //   5935: invokestatic abs : (I)I
    //   5938: invokevirtual charAt : (I)C
    //   5941: getstatic burp/Zmtf.Zx : Ljava/lang/String;
    //   5944: getstatic burp/Zejj.Zy : Ljava/lang/Object;
    //   5947: checkcast java/math/BigInteger
    //   5950: invokevirtual intValue : ()I
    //   5953: bipush #32
    //   5955: irem
    //   5956: invokestatic abs : (I)I
    //   5959: invokevirtual charAt : (I)C
    //   5962: if_icmpgt -> 6069
    //   5965: getstatic burp/Zeor.Zj : Ljava/lang/String;
    //   5968: getstatic burp/Zg2.ZE : Ljava/lang/Object;
    //   5971: checkcast java/math/BigInteger
    //   5974: invokevirtual intValue : ()I
    //   5977: bipush #32
    //   5979: irem
    //   5980: invokestatic abs : (I)I
    //   5983: invokevirtual charAt : (I)C
    //   5986: getstatic burp/Zm8i.Z_ : Ljava/lang/String;
    //   5989: getstatic burp/Zlpn.ZU : Ljava/lang/Object;
    //   5992: checkcast java/math/BigInteger
    //   5995: invokevirtual intValue : ()I
    //   5998: bipush #32
    //   6000: irem
    //   6001: invokestatic abs : (I)I
    //   6004: invokevirtual charAt : (I)C
    //   6007: if_icmple -> 6069
    //   6010: goto -> 6017
    //   6013: invokestatic a : (Ljava/lang/Throwable;)Ljava/lang/Throwable;
    //   6016: athrow
    //   6017: getstatic burp/Zeb3.ZG : Ljava/lang/String;
    //   6020: getstatic burp/Zzou.Zz : Ljava/lang/Object;
    //   6023: checkcast java/math/BigInteger
    //   6026: invokevirtual intValue : ()I
    //   6029: bipush #32
    //   6031: irem
    //   6032: invokestatic abs : (I)I
    //   6035: invokevirtual charAt : (I)C
    //   6038: getstatic burp/Ztdx.Zl : Ljava/lang/String;
    //   6041: getstatic burp/Zxtc.ZF : Ljava/lang/Object;
    //   6044: checkcast java/math/BigInteger
    //   6047: invokevirtual intValue : ()I
    //   6050: bipush #32
    //   6052: irem
    //   6053: invokestatic abs : (I)I
    //   6056: invokevirtual charAt : (I)C
    //   6059: if_icmple -> 6077
    //   6062: goto -> 6069
    //   6065: invokestatic a : (Ljava/lang/Throwable;)Ljava/lang/Throwable;
    //   6068: athrow
    //   6069: iconst_1
    //   6070: goto -> 6078
    //   6073: invokestatic a : (Ljava/lang/Throwable;)Ljava/lang/Throwable;
    //   6076: athrow
    //   6077: iconst_0
    //   6078: ireturn
    //   6079: astore_3
    //   6080: new java/lang/Exception
    //   6083: dup
    //   6084: aload_3
    //   6085: invokevirtual getMessage : ()Ljava/lang/String;
    //   6088: invokespecial <init> : (Ljava/lang/String;)V
    //   6091: athrow
    // Exception table:
    //   from	to	target	type
    //   4	6078	6079	java/lang/Throwable
    //   33	47	50	java/lang/Throwable
    //   40	61	64	java/lang/Throwable
    //   54	75	78	java/lang/Throwable
    //   68	89	92	java/lang/Throwable
    //   82	103	106	java/lang/Throwable
    //   96	117	120	java/lang/Throwable
    //   110	131	134	java/lang/Throwable
    //   124	145	148	java/lang/Throwable
    //   138	155	158	java/lang/Throwable
    //   194	208	211	java/lang/Throwable
    //   201	222	225	java/lang/Throwable
    //   215	236	239	java/lang/Throwable
    //   229	250	253	java/lang/Throwable
    //   243	264	267	java/lang/Throwable
    //   257	278	281	java/lang/Throwable
    //   271	292	295	java/lang/Throwable
    //   285	306	309	java/lang/Throwable
    //   299	323	326	java/lang/Throwable
    //   387	405	408	java/lang/Throwable
    //   396	421	424	java/lang/Throwable
    //   412	438	441	java/lang/Throwable
    //   428	454	457	java/lang/Throwable
    //   445	471	474	java/lang/Throwable
    //   461	487	490	java/lang/Throwable
    //   478	503	506	java/lang/Throwable
    //   494	526	529	java/lang/Throwable
    //   510	542	545	java/lang/Throwable
    //   533	558	561	java/lang/Throwable
    //   549	581	584	java/lang/Throwable
    //   565	597	600	java/lang/Throwable
    //   588	613	616	java/lang/Throwable
    //   604	632	635	java/lang/Throwable
    //   762	797	800	java/lang/Throwable
    //   804	845	848	java/lang/Throwable
    //   4173	4198	4198	java/lang/Throwable
    //   5161	5187	5187	java/lang/Throwable
    //   5276	5290	5290	java/lang/Throwable
    //   5301	5314	5317	java/lang/Throwable
    //   5306	5329	5332	java/lang/Throwable
    //   5321	5347	5350	java/lang/Throwable
    //   5336	5377	5380	java/lang/Throwable
    //   5440	5467	5470	java/lang/Throwable
    //   5457	5488	5491	java/lang/Throwable
    //   5474	5518	5521	java/lang/Throwable
    //   5495	5529	5529	java/lang/Throwable
    //   5540	5556	5559	java/lang/Throwable
    //   5633	5647	5647	java/lang/Throwable
    //   5658	5671	5674	java/lang/Throwable
    //   5663	5686	5689	java/lang/Throwable
    //   5678	5704	5707	java/lang/Throwable
    //   5693	5734	5737	java/lang/Throwable
    //   5797	5824	5827	java/lang/Throwable
    //   5814	5845	5848	java/lang/Throwable
    //   5831	5875	5878	java/lang/Throwable
    //   5852	5886	5886	java/lang/Throwable
    //   5897	5913	5916	java/lang/Throwable
    //   5920	6010	6013	java/lang/Throwable
    //   5965	6062	6065	java/lang/Throwable
    //   6017	6073	6073	java/lang/Throwable
  }
  
  static void Z_(Object[] paramArrayOfObject, Object paramObject) throws Throwable {}
  
  static void ZS(Object paramObject) {
    Zme.Zp = a(18672, 27851);
    Zme.Zd = new BigInteger(a(18676, 31540));
    boolean bool = Zt2e.ZK();
    try {
      try {
        if (Zgkn.ZV.charAt(Math.abs(((BigInteger)Zldt.ZS).intValue() % 32)) <= Zx4y.Zh.charAt(Math.abs(((BigInteger)Zxpb.Zo).intValue() % 32))) {
          try {
            Zsf7.Zm(Class.forName(a(18687, -5972)));
            if (bool)
              Zejj.Zm(Class.forName(a(18680, 16725))); 
          } catch (Throwable throwable) {
            throw a(null);
          } 
          return;
        } 
      } catch (Throwable throwable) {
        throw a(null);
      } 
      Zejj.Zm(Class.forName(a(18680, 16725)));
    } catch (Throwable throwable) {}
  }
  
  static {
    // Byte code:
    //   0: bipush #14
    //   2: anewarray java/lang/String
    //   5: astore #5
    //   7: iconst_0
    //   8: istore_3
    //   9: ldc '3?)p"6 dfQp6p27"T1Y,qMQYK\\r|\*A\\t2LEiw4$ >p6yv;=(02\\tjo\\r59\\tJ1Z-4\\t9|-Z%MdT=W4yHg?WxXwI,FO_\29of)Q\\n_sHy\\t1!r\\tjg'
    //   11: dup
    //   12: astore_2
    //   13: invokevirtual length : ()I
    //   16: istore #4
    //   18: bipush #9
    //   20: istore_1
    //   21: iconst_m1
    //   22: istore_0
    //   23: bipush #91
    //   25: iinc #0, 1
    //   28: aload_2
    //   29: iload_0
    //   30: dup
    //   31: iload_1
    //   32: iadd
    //   33: invokevirtual substring : (II)Ljava/lang/String;
    //   36: iconst_m1
    //   37: goto -> 143
    //   40: aload #5
    //   42: swap
    //   43: iload_3
    //   44: iinc #3, 1
    //   47: swap
    //   48: aastore
    //   49: iload_0
    //   50: iload_1
    //   51: iadd
    //   52: dup
    //   53: istore_0
    //   54: iload #4
    //   56: if_icmpge -> 68
    //   59: aload_2
    //   60: iload_0
    //   61: invokevirtual charAt : (I)C
    //   64: istore_1
    //   65: goto -> 23
    //   68: ldc 'RO]re\dKcS-A%.X%2c=.\\rxp'uIV\\r'
    //   70: dup
    //   71: astore_2
    //   72: invokevirtual length : ()I
    //   75: istore #4
    //   77: bipush #32
    //   79: istore_1
    //   80: iconst_m1
    //   81: istore_0
    //   82: bipush #76
    //   84: iinc #0, 1
    //   87: aload_2
    //   88: iload_0
    //   89: dup
    //   90: iload_1
    //   91: iadd
    //   92: invokevirtual substring : (II)Ljava/lang/String;
    //   95: iconst_0
    //   96: goto -> 143
    //   99: aload #5
    //   101: swap
    //   102: iload_3
    //   103: iinc #3, 1
    //   106: swap
    //   107: aastore
    //   108: iload_0
    //   109: iload_1
    //   110: iadd
    //   111: dup
    //   112: istore_0
    //   113: iload #4
    //   115: if_icmpge -> 127
    //   118: aload_2
    //   119: iload_0
    //   120: invokevirtual charAt : (I)C
    //   123: istore_1
    //   124: goto -> 82
    //   127: aload #5
    //   129: putstatic burp/Zrs0.a : [Ljava/lang/String;
    //   132: bipush #14
    //   134: anewarray java/lang/String
    //   137: putstatic burp/Zrs0.b : [Ljava/lang/String;
    //   140: goto -> 300
    //   143: dup_x2
    //   144: pop
    //   145: invokevirtual toCharArray : ()[C
    //   148: dup_x1
    //   149: arraylength
    //   150: dup_x2
    //   151: pop
    //   152: iconst_0
    //   153: istore #6
    //   155: dup2_x1
    //   156: pop2
    //   157: dup_x2
    //   158: iconst_1
    //   159: if_icmpgt -> 260
    //   162: dup2
    //   163: swap
    //   164: iload #6
    //   166: dup2_x1
    //   167: caload
    //   168: swap
    //   169: iload #6
    //   171: bipush #7
    //   173: irem
    //   174: tableswitch default -> 242, 0 -> 212, 1 -> 217, 2 -> 222, 3 -> 227, 4 -> 232, 5 -> 237
    //   212: bipush #92
    //   214: goto -> 244
    //   217: bipush #40
    //   219: goto -> 244
    //   222: bipush #118
    //   224: goto -> 244
    //   227: bipush #84
    //   229: goto -> 244
    //   232: bipush #59
    //   234: goto -> 244
    //   237: bipush #9
    //   239: goto -> 244
    //   242: bipush #48
    //   244: ixor
    //   245: ixor
    //   246: i2c
    //   247: castore
    //   248: iinc #6, 1
    //   251: dup
    //   252: ifne -> 260
    //   255: dup2
    //   256: dup_x1
    //   257: goto -> 166
    //   260: dup2_x1
    //   261: pop2
    //   262: dup_x2
    //   263: iload #6
    //   265: if_icmpgt -> 162
    //   268: pop
    //   269: new java/lang/String
    //   272: dup_x1
    //   273: swap
    //   274: invokespecial <init> : ([C)V
    //   277: invokevirtual intern : ()Ljava/lang/String;
    //   280: swap
    //   281: pop
    //   282: swap
    //   283: tableswitch default -> 40, 0 -> 99
    //   300: new java/math/BigInteger
    //   303: dup
    //   304: sipush #18686
    //   307: sipush #18047
    //   310: invokestatic a : (II)Ljava/lang/String;
    //   313: invokespecial <init> : (Ljava/lang/String;)V
    //   316: putstatic burp/Zrs0.Zz : Ljava/lang/Object;
    //   319: sipush #18685
    //   322: sipush #-24307
    //   325: invokestatic a : (II)Ljava/lang/String;
    //   328: putstatic burp/Zrs0.Zt : Ljava/lang/String;
    //   331: return
  }
  
  private static Throwable a(Throwable paramThrowable) {
    return paramThrowable;
  }
  
  private static String a(int paramInt1, int paramInt2) {
    int i = (paramInt1 ^ 0x48FC) & 0xFFFF;
    if (b[i] == null) {
      char[] arrayOfChar = a[i].toCharArray();
      switch (arrayOfChar[0] & 0xFF) {
        case 0:
        
        case 1:
        
        case 2:
        
        case 3:
        
        case 4:
        
        case 5:
        
        case 6:
        
        case 7:
        
        case 8:
        
        case 9:
        
        case 10:
        
        case 11:
        
        case 12:
        
        case 13:
        
        case 14:
        
        case 15:
        
        case 16:
        
        case 17:
        
        case 18:
        
        case 19:
        
        case 20:
        
        case 21:
        
        case 22:
        
        case 23:
        
        case 24:
        
        case 25:
        
        case 26:
        
        case 27:
        
        case 28:
        
        case 29:
        
        case 30:
        
        case 31:
        
        case 32:
        
        case 33:
        
        case 34:
        
        case 35:
        
        case 36:
        
        case 37:
        
        case 38:
        
        case 39:
        
        case 40:
        
        case 41:
        
        case 42:
        
        case 43:
        
        case 44:
        
        case 45:
        
        case 46:
        
        case 47:
        
        case 48:
        
        case 49:
        
        case 50:
        
        case 51:
        
        case 52:
        
        case 53:
        
        case 54:
        
        case 55:
        
        case 56:
        
        case 57:
        
        case 58:
        
        case 59:
        
        case 60:
        
        case 61:
        
        case 62:
        
        case 63:
        
        case 64:
        
        case 65:
        
        case 66:
        
        case 67:
        
        case 68:
        
        case 69:
        
        case 70:
        
        case 71:
        
        case 72:
        
        case 73:
        
        case 74:
        
        case 75:
        
        case 76:
        
        case 77:
        
        case 78:
        
        case 79:
        
        case 80:
        
        case 81:
        
        case 82:
        
        case 83:
        
        case 84:
        
        case 85:
        
        case 86:
        
        case 87:
        
        case 88:
        
        case 89:
        
        case 90:
        
        case 91:
        
        case 92:
        
        case 93:
        
        case 94:
        
        case 95:
        
        case 96:
        
        case 97:
        
        case 98:
        
        case 99:
        
        case 100:
        
        case 101:
        
        case 102:
        
        case 103:
        
        case 104:
        
        case 105:
        
        case 106:
        
        case 107:
        
        case 108:
        
        case 109:
        
        case 110:
        
        case 111:
        
        case 112:
        
        case 113:
        
        case 114:
        
        case 115:
        
        case 116:
        
        case 117:
        
        case 118:
        
        case 119:
        
        case 120:
        
        case 121:
        
        case 122:
        
        case 123:
        
        case 124:
        
        case 125:
        
        case 126:
        
        case 127:
        
        case 128:
        
        case 129:
        
        case 130:
        
        case 131:
        
        case 132:
        
        case 133:
        
        case 134:
        
        case 135:
        
        case 136:
        
        case 137:
        
        case 138:
        
        case 139:
        
        case 140:
        
        case 141:
        
        case 142:
        
        case 143:
        
        case 144:
        
        case 145:
        
        case 146:
        
        case 147:
        
        case 148:
        
        case 149:
        
        case 150:
        
        case 151:
        
        case 152:
        
        case 153:
        
        case 154:
        
        case 155:
        
        case 156:
        
        case 157:
        
        case 158:
        
        case 159:
        
        case 160:
        
        case 161:
        
        case 162:
        
        case 163:
        
        case 164:
        
        case 165:
        
        case 166:
        
        case 167:
        
        case 168:
        
        case 169:
        
        case 170:
        
        case 171:
        
        case 172:
        
        case 173:
        
        case 174:
        
        case 175:
        
        case 176:
        
        case 177:
        
        case 178:
        
        case 179:
        
        case 180:
        
        case 181:
        
        case 182:
        
        case 183:
        
        case 184:
        
        case 185:
        
        case 186:
        
        case 187:
        
        case 188:
        
        case 189:
        
        case 190:
        
        case 191:
        
        case 192:
        
        case 193:
        
        case 194:
        
        case 195:
        
        case 196:
        
        case 197:
        
        case 198:
        
        case 199:
        
        case 200:
        
        case 201:
        
        case 202:
        
        case 203:
        
        case 204:
        
        case 205:
        
        case 206:
        
        case 207:
        
        case 208:
        
        case 209:
        
        case 210:
        
        case 211:
        
        case 212:
        
        case 213:
        
        case 214:
        
        case 215:
        
        case 216:
        
        case 217:
        
        case 218:
        
        case 219:
        
        case 220:
        
        case 221:
        
        case 222:
        
        case 223:
        
        case 224:
        
        case 225:
        
        case 226:
        
        case 227:
        
        case 228:
        
        case 229:
        
        case 230:
        
        case 231:
        
        case 232:
        
        case 233:
        
        case 234:
        
        case 235:
        
        case 236:
        
        case 237:
        
        case 238:
        
        case 239:
        
        case 240:
        
        case 241:
        
        case 242:
        
        case 243:
        
        case 244:
        
        case 245:
        
        case 246:
        
        case 247:
        
        case 248:
        
        case 249:
        
        case 250:
        
        case 251:
        
        case 252:
        
        case 253:
        
        case 254:
        
        default:
          break;
      } 
      byte b1 = 120;
      int j = (paramInt2 & 0xFF) - b1;
      if (j < 0)
        j += 256; 
      int k = ((paramInt2 & 0xFFFF) >>> 8) - b1;
      if (k < 0)
        k += 256; 
      for (byte b2 = 0; b2 < arrayOfChar.length; b2++) {
        int m = b2 % 2;
        if (m == 0) {
          arrayOfChar[b2] = (char)(arrayOfChar[b2] ^ j);
          j = ((j >>> 3 | j << 5) ^ arrayOfChar[b2]) & 0xFF;
        } else {
          arrayOfChar[b2] = (char)(arrayOfChar[b2] ^ k);
          k = ((k >>> 3 | k << 5) ^ arrayOfChar[b2]) & 0xFF;
        } 
      } 
      b[i] = (new String(arrayOfChar)).intern();
    } 
    return b[i];
  }
}


/* Location:              C:\Program Files\BurpSuitePro\burpsuite_pro.jar!\burp\Zrs0.class
 * Java compiler version: 21 (65.0)
 * JD-Core Version:       1.1.3
 */