package burp;

import java.util.Currency;

public class Zrsy {
  static void Zu(Currency paramCurrency, Zxck paramZxck, Zkit paramZkit) {
    // Byte code:
    //   0: invokestatic ZL : ()Ljava/lang/String;
    //   3: astore_3
    //   4: aload_0
    //   5: ifnonnull -> 21
    //   8: aload_2
    //   9: aload_1
    //   10: getstatic burp/Zkn5.ZM : Lburp/Zekc;
    //   13: aconst_null
    //   14: invokevirtual Zi : (Lburp/Zgpi;Lburp/Zekc;Ljava/lang/String;)V
    //   17: aload_3
    //   18: ifnonnull -> 33
    //   21: aload_2
    //   22: aload_1
    //   23: getstatic burp/Zkn5.ZM : Lburp/Zekc;
    //   26: aload_0
    //   27: invokevirtual getCurrencyCode : ()Ljava/lang/String;
    //   30: invokevirtual Zi : (Lburp/Zgpi;Lburp/Zekc;Ljava/lang/String;)V
    //   33: invokestatic Zwu : ()[Lburp/Zbqc;
    //   36: ifnonnull -> 44
    //   39: ldc 'OamC1'
    //   41: invokestatic Ze : (Ljava/lang/String;)V
    //   44: return
  }
}


/* Location:              C:\Program Files\BurpSuitePro\burpsuite_pro.jar!\burp\Zrsy.class
 * Java compiler version: 21 (65.0)
 * JD-Core Version:       1.1.3
 */