package burp;

import java.math.BigInteger;

class Zrtc extends ClassLoader {
  static Object Zr;
  
  static String Zl;
  
  private static final String[] a;
  
  private static final String[] b;
  
  static boolean Zk(Object[] paramArrayOfObject, Object paramObject) throws Throwable {
    // Byte code:
    //   0: invokestatic ZK : ()Z
    //   3: istore_2
    //   4: getstatic burp/Zl50.ZV : Ljava/lang/Object;
    //   7: checkcast java/math/BigInteger
    //   10: invokevirtual toByteArray : ()[B
    //   13: astore_3
    //   14: bipush #32
    //   16: newarray int
    //   18: dup
    //   19: iconst_0
    //   20: ldc 876216579
    //   22: iastore
    //   23: dup
    //   24: iconst_1
    //   25: ldc 455999525
    //   27: iastore
    //   28: dup
    //   29: iconst_2
    //   30: ldc 1043334948
    //   32: iastore
    //   33: dup
    //   34: iconst_3
    //   35: ldc 439222784
    //   37: iastore
    //   38: dup
    //   39: iconst_4
    //   40: ldc 372376604
    //   42: iastore
    //   43: dup
    //   44: iconst_5
    //   45: ldc 707731490
    //   47: iastore
    //   48: dup
    //   49: bipush #6
    //   51: ldc 389426184
    //   53: iastore
    //   54: dup
    //   55: bipush #7
    //   57: ldc 973875457
    //   59: iastore
    //   60: dup
    //   61: bipush #8
    //   63: ldc 389160971
    //   65: iastore
    //   66: dup
    //   67: bipush #9
    //   69: ldc 907870729
    //   71: iastore
    //   72: dup
    //   73: bipush #10
    //   75: ldc 121057538
    //   77: iastore
    //   78: dup
    //   79: bipush #11
    //   81: ldc 840500228
    //   83: iastore
    //   84: dup
    //   85: bipush #12
    //   87: ldc 254150144
    //   89: iastore
    //   90: dup
    //   91: bipush #13
    //   93: ldc 924386310
    //   95: iastore
    //   96: dup
    //   97: bipush #14
    //   99: ldc 187632156
    //   101: iastore
    //   102: dup
    //   103: bipush #15
    //   105: ldc 874189824
    //   107: iastore
    //   108: dup
    //   109: bipush #16
    //   111: ldc 655302664
    //   113: iastore
    //   114: dup
    //   115: bipush #17
    //   117: ldc 890966315
    //   119: iastore
    //   120: dup
    //   121: bipush #18
    //   123: ldc 722417666
    //   125: iastore
    //   126: dup
    //   127: bipush #19
    //   129: ldc 1026621720
    //   131: iastore
    //   132: dup
    //   133: bipush #20
    //   135: ldc 957157408
    //   137: iastore
    //   138: dup
    //   139: bipush #21
    //   141: ldc 892536332
    //   143: iastore
    //   144: dup
    //   145: bipush #22
    //   147: ldc 689771012
    //   149: iastore
    //   150: dup
    //   151: bipush #23
    //   153: ldc 221709344
    //   155: iastore
    //   156: dup
    //   157: bipush #24
    //   159: ldc 940377620
    //   161: iastore
    //   162: dup
    //   163: bipush #25
    //   165: ldc 255209728
    //   167: iastore
    //   168: dup
    //   169: bipush #26
    //   171: ldc 1010368540
    //   173: iastore
    //   174: dup
    //   175: bipush #27
    //   177: ldc 220604441
    //   179: iastore
    //   180: dup
    //   181: bipush #28
    //   183: ldc 1008414755
    //   185: iastore
    //   186: dup
    //   187: bipush #29
    //   189: ldc 187049985
    //   191: iastore
    //   192: dup
    //   193: bipush #30
    //   195: ldc 943331329
    //   197: iastore
    //   198: dup
    //   199: bipush #31
    //   201: ldc 170788368
    //   203: iastore
    //   204: astore #5
    //   206: bipush #64
    //   208: newarray int
    //   210: dup
    //   211: iconst_0
    //   212: ldc 16843776
    //   214: iastore
    //   215: dup
    //   216: iconst_1
    //   217: iconst_0
    //   218: iastore
    //   219: dup
    //   220: iconst_2
    //   221: ldc 65536
    //   223: iastore
    //   224: dup
    //   225: iconst_3
    //   226: ldc 16843780
    //   228: iastore
    //   229: dup
    //   230: iconst_4
    //   231: ldc 16842756
    //   233: iastore
    //   234: dup
    //   235: iconst_5
    //   236: ldc 66564
    //   238: iastore
    //   239: dup
    //   240: bipush #6
    //   242: iconst_4
    //   243: iastore
    //   244: dup
    //   245: bipush #7
    //   247: ldc 65536
    //   249: iastore
    //   250: dup
    //   251: bipush #8
    //   253: sipush #1024
    //   256: iastore
    //   257: dup
    //   258: bipush #9
    //   260: ldc 16843776
    //   262: iastore
    //   263: dup
    //   264: bipush #10
    //   266: ldc 16843780
    //   268: iastore
    //   269: dup
    //   270: bipush #11
    //   272: sipush #1024
    //   275: iastore
    //   276: dup
    //   277: bipush #12
    //   279: ldc 16778244
    //   281: iastore
    //   282: dup
    //   283: bipush #13
    //   285: ldc 16842756
    //   287: iastore
    //   288: dup
    //   289: bipush #14
    //   291: ldc 16777216
    //   293: iastore
    //   294: dup
    //   295: bipush #15
    //   297: iconst_4
    //   298: iastore
    //   299: dup
    //   300: bipush #16
    //   302: sipush #1028
    //   305: iastore
    //   306: dup
    //   307: bipush #17
    //   309: ldc 16778240
    //   311: iastore
    //   312: dup
    //   313: bipush #18
    //   315: ldc 16778240
    //   317: iastore
    //   318: dup
    //   319: bipush #19
    //   321: ldc 66560
    //   323: iastore
    //   324: dup
    //   325: bipush #20
    //   327: ldc 66560
    //   329: iastore
    //   330: dup
    //   331: bipush #21
    //   333: ldc 16842752
    //   335: iastore
    //   336: dup
    //   337: bipush #22
    //   339: ldc 16842752
    //   341: iastore
    //   342: dup
    //   343: bipush #23
    //   345: ldc 16778244
    //   347: iastore
    //   348: dup
    //   349: bipush #24
    //   351: ldc 65540
    //   353: iastore
    //   354: dup
    //   355: bipush #25
    //   357: ldc 16777220
    //   359: iastore
    //   360: dup
    //   361: bipush #26
    //   363: ldc 16777220
    //   365: iastore
    //   366: dup
    //   367: bipush #27
    //   369: ldc 65540
    //   371: iastore
    //   372: dup
    //   373: bipush #28
    //   375: iconst_0
    //   376: iastore
    //   377: dup
    //   378: bipush #29
    //   380: sipush #1028
    //   383: iastore
    //   384: dup
    //   385: bipush #30
    //   387: ldc 66564
    //   389: iastore
    //   390: dup
    //   391: bipush #31
    //   393: ldc 16777216
    //   395: iastore
    //   396: dup
    //   397: bipush #32
    //   399: ldc 65536
    //   401: iastore
    //   402: dup
    //   403: bipush #33
    //   405: ldc 16843780
    //   407: iastore
    //   408: dup
    //   409: bipush #34
    //   411: iconst_4
    //   412: iastore
    //   413: dup
    //   414: bipush #35
    //   416: ldc 16842752
    //   418: iastore
    //   419: dup
    //   420: bipush #36
    //   422: ldc 16843776
    //   424: iastore
    //   425: dup
    //   426: bipush #37
    //   428: ldc 16777216
    //   430: iastore
    //   431: dup
    //   432: bipush #38
    //   434: ldc 16777216
    //   436: iastore
    //   437: dup
    //   438: bipush #39
    //   440: sipush #1024
    //   443: iastore
    //   444: dup
    //   445: bipush #40
    //   447: ldc 16842756
    //   449: iastore
    //   450: dup
    //   451: bipush #41
    //   453: ldc 65536
    //   455: iastore
    //   456: dup
    //   457: bipush #42
    //   459: ldc 66560
    //   461: iastore
    //   462: dup
    //   463: bipush #43
    //   465: ldc 16777220
    //   467: iastore
    //   468: dup
    //   469: bipush #44
    //   471: sipush #1024
    //   474: iastore
    //   475: dup
    //   476: bipush #45
    //   478: iconst_4
    //   479: iastore
    //   480: dup
    //   481: bipush #46
    //   483: ldc 16778244
    //   485: iastore
    //   486: dup
    //   487: bipush #47
    //   489: ldc 66564
    //   491: iastore
    //   492: dup
    //   493: bipush #48
    //   495: ldc 16843780
    //   497: iastore
    //   498: dup
    //   499: bipush #49
    //   501: ldc 65540
    //   503: iastore
    //   504: dup
    //   505: bipush #50
    //   507: ldc 16842752
    //   509: iastore
    //   510: dup
    //   511: bipush #51
    //   513: ldc 16778244
    //   515: iastore
    //   516: dup
    //   517: bipush #52
    //   519: ldc 16777220
    //   521: iastore
    //   522: dup
    //   523: bipush #53
    //   525: sipush #1028
    //   528: iastore
    //   529: dup
    //   530: bipush #54
    //   532: ldc 66564
    //   534: iastore
    //   535: dup
    //   536: bipush #55
    //   538: ldc 16843776
    //   540: iastore
    //   541: dup
    //   542: bipush #56
    //   544: sipush #1028
    //   547: iastore
    //   548: dup
    //   549: bipush #57
    //   551: ldc 16778240
    //   553: iastore
    //   554: dup
    //   555: bipush #58
    //   557: ldc 16778240
    //   559: iastore
    //   560: dup
    //   561: bipush #59
    //   563: iconst_0
    //   564: iastore
    //   565: dup
    //   566: bipush #60
    //   568: ldc 65540
    //   570: iastore
    //   571: dup
    //   572: bipush #61
    //   574: ldc 66560
    //   576: iastore
    //   577: dup
    //   578: bipush #62
    //   580: iconst_0
    //   581: iastore
    //   582: dup
    //   583: bipush #63
    //   585: ldc 16842756
    //   587: iastore
    //   588: astore #6
    //   590: bipush #64
    //   592: newarray int
    //   594: dup
    //   595: iconst_0
    //   596: ldc -2146402272
    //   598: iastore
    //   599: dup
    //   600: iconst_1
    //   601: ldc -2147450880
    //   603: iastore
    //   604: dup
    //   605: iconst_2
    //   606: ldc 32768
    //   608: iastore
    //   609: dup
    //   610: iconst_3
    //   611: ldc 1081376
    //   613: iastore
    //   614: dup
    //   615: iconst_4
    //   616: ldc 1048576
    //   618: iastore
    //   619: dup
    //   620: iconst_5
    //   621: bipush #32
    //   623: iastore
    //   624: dup
    //   625: bipush #6
    //   627: ldc -2146435040
    //   629: iastore
    //   630: dup
    //   631: bipush #7
    //   633: ldc -2147450848
    //   635: iastore
    //   636: dup
    //   637: bipush #8
    //   639: ldc -2147483616
    //   641: iastore
    //   642: dup
    //   643: bipush #9
    //   645: ldc -2146402272
    //   647: iastore
    //   648: dup
    //   649: bipush #10
    //   651: ldc -2146402304
    //   653: iastore
    //   654: dup
    //   655: bipush #11
    //   657: ldc -2147483648
    //   659: iastore
    //   660: dup
    //   661: bipush #12
    //   663: ldc -2147450880
    //   665: iastore
    //   666: dup
    //   667: bipush #13
    //   669: ldc 1048576
    //   671: iastore
    //   672: dup
    //   673: bipush #14
    //   675: bipush #32
    //   677: iastore
    //   678: dup
    //   679: bipush #15
    //   681: ldc -2146435040
    //   683: iastore
    //   684: dup
    //   685: bipush #16
    //   687: ldc 1081344
    //   689: iastore
    //   690: dup
    //   691: bipush #17
    //   693: ldc 1048608
    //   695: iastore
    //   696: dup
    //   697: bipush #18
    //   699: ldc -2147450848
    //   701: iastore
    //   702: dup
    //   703: bipush #19
    //   705: iconst_0
    //   706: iastore
    //   707: dup
    //   708: bipush #20
    //   710: ldc -2147483648
    //   712: iastore
    //   713: dup
    //   714: bipush #21
    //   716: ldc 32768
    //   718: iastore
    //   719: dup
    //   720: bipush #22
    //   722: ldc 1081376
    //   724: iastore
    //   725: dup
    //   726: bipush #23
    //   728: ldc -2146435072
    //   730: iastore
    //   731: dup
    //   732: bipush #24
    //   734: ldc 1048608
    //   736: iastore
    //   737: dup
    //   738: bipush #25
    //   740: ldc -2147483616
    //   742: iastore
    //   743: dup
    //   744: bipush #26
    //   746: iconst_0
    //   747: iastore
    //   748: dup
    //   749: bipush #27
    //   751: ldc 1081344
    //   753: iastore
    //   754: dup
    //   755: bipush #28
    //   757: ldc 32800
    //   759: iastore
    //   760: dup
    //   761: bipush #29
    //   763: ldc -2146402304
    //   765: iastore
    //   766: dup
    //   767: bipush #30
    //   769: ldc -2146435072
    //   771: iastore
    //   772: dup
    //   773: bipush #31
    //   775: ldc 32800
    //   777: iastore
    //   778: dup
    //   779: bipush #32
    //   781: iconst_0
    //   782: iastore
    //   783: dup
    //   784: bipush #33
    //   786: ldc 1081376
    //   788: iastore
    //   789: dup
    //   790: bipush #34
    //   792: ldc -2146435040
    //   794: iastore
    //   795: dup
    //   796: bipush #35
    //   798: ldc 1048576
    //   800: iastore
    //   801: dup
    //   802: bipush #36
    //   804: ldc -2147450848
    //   806: iastore
    //   807: dup
    //   808: bipush #37
    //   810: ldc -2146435072
    //   812: iastore
    //   813: dup
    //   814: bipush #38
    //   816: ldc -2146402304
    //   818: iastore
    //   819: dup
    //   820: bipush #39
    //   822: ldc 32768
    //   824: iastore
    //   825: dup
    //   826: bipush #40
    //   828: ldc -2146435072
    //   830: iastore
    //   831: dup
    //   832: bipush #41
    //   834: ldc -2147450880
    //   836: iastore
    //   837: dup
    //   838: bipush #42
    //   840: bipush #32
    //   842: iastore
    //   843: dup
    //   844: bipush #43
    //   846: ldc -2146402272
    //   848: iastore
    //   849: dup
    //   850: bipush #44
    //   852: ldc 1081376
    //   854: iastore
    //   855: dup
    //   856: bipush #45
    //   858: bipush #32
    //   860: iastore
    //   861: dup
    //   862: bipush #46
    //   864: ldc 32768
    //   866: iastore
    //   867: dup
    //   868: bipush #47
    //   870: ldc -2147483648
    //   872: iastore
    //   873: dup
    //   874: bipush #48
    //   876: ldc 32800
    //   878: iastore
    //   879: dup
    //   880: bipush #49
    //   882: ldc -2146402304
    //   884: iastore
    //   885: dup
    //   886: bipush #50
    //   888: ldc 1048576
    //   890: iastore
    //   891: dup
    //   892: bipush #51
    //   894: ldc -2147483616
    //   896: iastore
    //   897: dup
    //   898: bipush #52
    //   900: ldc 1048608
    //   902: iastore
    //   903: dup
    //   904: bipush #53
    //   906: ldc -2147450848
    //   908: iastore
    //   909: dup
    //   910: bipush #54
    //   912: ldc -2147483616
    //   914: iastore
    //   915: dup
    //   916: bipush #55
    //   918: ldc 1048608
    //   920: iastore
    //   921: dup
    //   922: bipush #56
    //   924: ldc 1081344
    //   926: iastore
    //   927: dup
    //   928: bipush #57
    //   930: iconst_0
    //   931: iastore
    //   932: dup
    //   933: bipush #58
    //   935: ldc -2147450880
    //   937: iastore
    //   938: dup
    //   939: bipush #59
    //   941: ldc 32800
    //   943: iastore
    //   944: dup
    //   945: bipush #60
    //   947: ldc -2147483648
    //   949: iastore
    //   950: dup
    //   951: bipush #61
    //   953: ldc -2146435040
    //   955: iastore
    //   956: dup
    //   957: bipush #62
    //   959: ldc -2146402272
    //   961: iastore
    //   962: dup
    //   963: bipush #63
    //   965: ldc 1081344
    //   967: iastore
    //   968: astore #7
    //   970: bipush #64
    //   972: newarray int
    //   974: dup
    //   975: iconst_0
    //   976: sipush #520
    //   979: iastore
    //   980: dup
    //   981: iconst_1
    //   982: ldc 134349312
    //   984: iastore
    //   985: dup
    //   986: iconst_2
    //   987: iconst_0
    //   988: iastore
    //   989: dup
    //   990: iconst_3
    //   991: ldc 134348808
    //   993: iastore
    //   994: dup
    //   995: iconst_4
    //   996: ldc 134218240
    //   998: iastore
    //   999: dup
    //   1000: iconst_5
    //   1001: iconst_0
    //   1002: iastore
    //   1003: dup
    //   1004: bipush #6
    //   1006: ldc 131592
    //   1008: iastore
    //   1009: dup
    //   1010: bipush #7
    //   1012: ldc 134218240
    //   1014: iastore
    //   1015: dup
    //   1016: bipush #8
    //   1018: ldc 131080
    //   1020: iastore
    //   1021: dup
    //   1022: bipush #9
    //   1024: ldc 134217736
    //   1026: iastore
    //   1027: dup
    //   1028: bipush #10
    //   1030: ldc 134217736
    //   1032: iastore
    //   1033: dup
    //   1034: bipush #11
    //   1036: ldc 131072
    //   1038: iastore
    //   1039: dup
    //   1040: bipush #12
    //   1042: ldc 134349320
    //   1044: iastore
    //   1045: dup
    //   1046: bipush #13
    //   1048: ldc 131080
    //   1050: iastore
    //   1051: dup
    //   1052: bipush #14
    //   1054: ldc 134348800
    //   1056: iastore
    //   1057: dup
    //   1058: bipush #15
    //   1060: sipush #520
    //   1063: iastore
    //   1064: dup
    //   1065: bipush #16
    //   1067: ldc 134217728
    //   1069: iastore
    //   1070: dup
    //   1071: bipush #17
    //   1073: bipush #8
    //   1075: iastore
    //   1076: dup
    //   1077: bipush #18
    //   1079: ldc 134349312
    //   1081: iastore
    //   1082: dup
    //   1083: bipush #19
    //   1085: sipush #512
    //   1088: iastore
    //   1089: dup
    //   1090: bipush #20
    //   1092: ldc 131584
    //   1094: iastore
    //   1095: dup
    //   1096: bipush #21
    //   1098: ldc 134348800
    //   1100: iastore
    //   1101: dup
    //   1102: bipush #22
    //   1104: ldc 134348808
    //   1106: iastore
    //   1107: dup
    //   1108: bipush #23
    //   1110: ldc 131592
    //   1112: iastore
    //   1113: dup
    //   1114: bipush #24
    //   1116: ldc 134218248
    //   1118: iastore
    //   1119: dup
    //   1120: bipush #25
    //   1122: ldc 131584
    //   1124: iastore
    //   1125: dup
    //   1126: bipush #26
    //   1128: ldc 131072
    //   1130: iastore
    //   1131: dup
    //   1132: bipush #27
    //   1134: ldc 134218248
    //   1136: iastore
    //   1137: dup
    //   1138: bipush #28
    //   1140: bipush #8
    //   1142: iastore
    //   1143: dup
    //   1144: bipush #29
    //   1146: ldc 134349320
    //   1148: iastore
    //   1149: dup
    //   1150: bipush #30
    //   1152: sipush #512
    //   1155: iastore
    //   1156: dup
    //   1157: bipush #31
    //   1159: ldc 134217728
    //   1161: iastore
    //   1162: dup
    //   1163: bipush #32
    //   1165: ldc 134349312
    //   1167: iastore
    //   1168: dup
    //   1169: bipush #33
    //   1171: ldc 134217728
    //   1173: iastore
    //   1174: dup
    //   1175: bipush #34
    //   1177: ldc 131080
    //   1179: iastore
    //   1180: dup
    //   1181: bipush #35
    //   1183: sipush #520
    //   1186: iastore
    //   1187: dup
    //   1188: bipush #36
    //   1190: ldc 131072
    //   1192: iastore
    //   1193: dup
    //   1194: bipush #37
    //   1196: ldc 134349312
    //   1198: iastore
    //   1199: dup
    //   1200: bipush #38
    //   1202: ldc 134218240
    //   1204: iastore
    //   1205: dup
    //   1206: bipush #39
    //   1208: iconst_0
    //   1209: iastore
    //   1210: dup
    //   1211: bipush #40
    //   1213: sipush #512
    //   1216: iastore
    //   1217: dup
    //   1218: bipush #41
    //   1220: ldc 131080
    //   1222: iastore
    //   1223: dup
    //   1224: bipush #42
    //   1226: ldc 134349320
    //   1228: iastore
    //   1229: dup
    //   1230: bipush #43
    //   1232: ldc 134218240
    //   1234: iastore
    //   1235: dup
    //   1236: bipush #44
    //   1238: ldc 134217736
    //   1240: iastore
    //   1241: dup
    //   1242: bipush #45
    //   1244: sipush #512
    //   1247: iastore
    //   1248: dup
    //   1249: bipush #46
    //   1251: iconst_0
    //   1252: iastore
    //   1253: dup
    //   1254: bipush #47
    //   1256: ldc 134348808
    //   1258: iastore
    //   1259: dup
    //   1260: bipush #48
    //   1262: ldc 134218248
    //   1264: iastore
    //   1265: dup
    //   1266: bipush #49
    //   1268: ldc 131072
    //   1270: iastore
    //   1271: dup
    //   1272: bipush #50
    //   1274: ldc 134217728
    //   1276: iastore
    //   1277: dup
    //   1278: bipush #51
    //   1280: ldc 134349320
    //   1282: iastore
    //   1283: dup
    //   1284: bipush #52
    //   1286: bipush #8
    //   1288: iastore
    //   1289: dup
    //   1290: bipush #53
    //   1292: ldc 131592
    //   1294: iastore
    //   1295: dup
    //   1296: bipush #54
    //   1298: ldc 131584
    //   1300: iastore
    //   1301: dup
    //   1302: bipush #55
    //   1304: ldc 134217736
    //   1306: iastore
    //   1307: dup
    //   1308: bipush #56
    //   1310: ldc 134348800
    //   1312: iastore
    //   1313: dup
    //   1314: bipush #57
    //   1316: ldc 134218248
    //   1318: iastore
    //   1319: dup
    //   1320: bipush #58
    //   1322: sipush #520
    //   1325: iastore
    //   1326: dup
    //   1327: bipush #59
    //   1329: ldc 134348800
    //   1331: iastore
    //   1332: dup
    //   1333: bipush #60
    //   1335: ldc 131592
    //   1337: iastore
    //   1338: dup
    //   1339: bipush #61
    //   1341: bipush #8
    //   1343: iastore
    //   1344: dup
    //   1345: bipush #62
    //   1347: ldc 134348808
    //   1349: iastore
    //   1350: dup
    //   1351: bipush #63
    //   1353: ldc 131584
    //   1355: iastore
    //   1356: astore #8
    //   1358: bipush #64
    //   1360: newarray int
    //   1362: dup
    //   1363: iconst_0
    //   1364: ldc 8396801
    //   1366: iastore
    //   1367: dup
    //   1368: iconst_1
    //   1369: sipush #8321
    //   1372: iastore
    //   1373: dup
    //   1374: iconst_2
    //   1375: sipush #8321
    //   1378: iastore
    //   1379: dup
    //   1380: iconst_3
    //   1381: sipush #128
    //   1384: iastore
    //   1385: dup
    //   1386: iconst_4
    //   1387: ldc 8396928
    //   1389: iastore
    //   1390: dup
    //   1391: iconst_5
    //   1392: ldc 8388737
    //   1394: iastore
    //   1395: dup
    //   1396: bipush #6
    //   1398: ldc 8388609
    //   1400: iastore
    //   1401: dup
    //   1402: bipush #7
    //   1404: sipush #8193
    //   1407: iastore
    //   1408: dup
    //   1409: bipush #8
    //   1411: iconst_0
    //   1412: iastore
    //   1413: dup
    //   1414: bipush #9
    //   1416: ldc 8396800
    //   1418: iastore
    //   1419: dup
    //   1420: bipush #10
    //   1422: ldc 8396800
    //   1424: iastore
    //   1425: dup
    //   1426: bipush #11
    //   1428: ldc 8396929
    //   1430: iastore
    //   1431: dup
    //   1432: bipush #12
    //   1434: sipush #129
    //   1437: iastore
    //   1438: dup
    //   1439: bipush #13
    //   1441: iconst_0
    //   1442: iastore
    //   1443: dup
    //   1444: bipush #14
    //   1446: ldc 8388736
    //   1448: iastore
    //   1449: dup
    //   1450: bipush #15
    //   1452: ldc 8388609
    //   1454: iastore
    //   1455: dup
    //   1456: bipush #16
    //   1458: iconst_1
    //   1459: iastore
    //   1460: dup
    //   1461: bipush #17
    //   1463: sipush #8192
    //   1466: iastore
    //   1467: dup
    //   1468: bipush #18
    //   1470: ldc 8388608
    //   1472: iastore
    //   1473: dup
    //   1474: bipush #19
    //   1476: ldc 8396801
    //   1478: iastore
    //   1479: dup
    //   1480: bipush #20
    //   1482: sipush #128
    //   1485: iastore
    //   1486: dup
    //   1487: bipush #21
    //   1489: ldc 8388608
    //   1491: iastore
    //   1492: dup
    //   1493: bipush #22
    //   1495: sipush #8193
    //   1498: iastore
    //   1499: dup
    //   1500: bipush #23
    //   1502: sipush #8320
    //   1505: iastore
    //   1506: dup
    //   1507: bipush #24
    //   1509: ldc 8388737
    //   1511: iastore
    //   1512: dup
    //   1513: bipush #25
    //   1515: iconst_1
    //   1516: iastore
    //   1517: dup
    //   1518: bipush #26
    //   1520: sipush #8320
    //   1523: iastore
    //   1524: dup
    //   1525: bipush #27
    //   1527: ldc 8388736
    //   1529: iastore
    //   1530: dup
    //   1531: bipush #28
    //   1533: sipush #8192
    //   1536: iastore
    //   1537: dup
    //   1538: bipush #29
    //   1540: ldc 8396928
    //   1542: iastore
    //   1543: dup
    //   1544: bipush #30
    //   1546: ldc 8396929
    //   1548: iastore
    //   1549: dup
    //   1550: bipush #31
    //   1552: sipush #129
    //   1555: iastore
    //   1556: dup
    //   1557: bipush #32
    //   1559: ldc 8388736
    //   1561: iastore
    //   1562: dup
    //   1563: bipush #33
    //   1565: ldc 8388609
    //   1567: iastore
    //   1568: dup
    //   1569: bipush #34
    //   1571: ldc 8396800
    //   1573: iastore
    //   1574: dup
    //   1575: bipush #35
    //   1577: ldc 8396929
    //   1579: iastore
    //   1580: dup
    //   1581: bipush #36
    //   1583: sipush #129
    //   1586: iastore
    //   1587: dup
    //   1588: bipush #37
    //   1590: iconst_0
    //   1591: iastore
    //   1592: dup
    //   1593: bipush #38
    //   1595: iconst_0
    //   1596: iastore
    //   1597: dup
    //   1598: bipush #39
    //   1600: ldc 8396800
    //   1602: iastore
    //   1603: dup
    //   1604: bipush #40
    //   1606: sipush #8320
    //   1609: iastore
    //   1610: dup
    //   1611: bipush #41
    //   1613: ldc 8388736
    //   1615: iastore
    //   1616: dup
    //   1617: bipush #42
    //   1619: ldc 8388737
    //   1621: iastore
    //   1622: dup
    //   1623: bipush #43
    //   1625: iconst_1
    //   1626: iastore
    //   1627: dup
    //   1628: bipush #44
    //   1630: ldc 8396801
    //   1632: iastore
    //   1633: dup
    //   1634: bipush #45
    //   1636: sipush #8321
    //   1639: iastore
    //   1640: dup
    //   1641: bipush #46
    //   1643: sipush #8321
    //   1646: iastore
    //   1647: dup
    //   1648: bipush #47
    //   1650: sipush #128
    //   1653: iastore
    //   1654: dup
    //   1655: bipush #48
    //   1657: ldc 8396929
    //   1659: iastore
    //   1660: dup
    //   1661: bipush #49
    //   1663: sipush #129
    //   1666: iastore
    //   1667: dup
    //   1668: bipush #50
    //   1670: iconst_1
    //   1671: iastore
    //   1672: dup
    //   1673: bipush #51
    //   1675: sipush #8192
    //   1678: iastore
    //   1679: dup
    //   1680: bipush #52
    //   1682: ldc 8388609
    //   1684: iastore
    //   1685: dup
    //   1686: bipush #53
    //   1688: sipush #8193
    //   1691: iastore
    //   1692: dup
    //   1693: bipush #54
    //   1695: ldc 8396928
    //   1697: iastore
    //   1698: dup
    //   1699: bipush #55
    //   1701: ldc 8388737
    //   1703: iastore
    //   1704: dup
    //   1705: bipush #56
    //   1707: sipush #8193
    //   1710: iastore
    //   1711: dup
    //   1712: bipush #57
    //   1714: sipush #8320
    //   1717: iastore
    //   1718: dup
    //   1719: bipush #58
    //   1721: ldc 8388608
    //   1723: iastore
    //   1724: dup
    //   1725: bipush #59
    //   1727: ldc 8396801
    //   1729: iastore
    //   1730: dup
    //   1731: bipush #60
    //   1733: sipush #128
    //   1736: iastore
    //   1737: dup
    //   1738: bipush #61
    //   1740: ldc 8388608
    //   1742: iastore
    //   1743: dup
    //   1744: bipush #62
    //   1746: sipush #8192
    //   1749: iastore
    //   1750: dup
    //   1751: bipush #63
    //   1753: ldc 8396928
    //   1755: iastore
    //   1756: astore #9
    //   1758: bipush #64
    //   1760: newarray int
    //   1762: dup
    //   1763: iconst_0
    //   1764: sipush #256
    //   1767: iastore
    //   1768: dup
    //   1769: iconst_1
    //   1770: ldc 34078976
    //   1772: iastore
    //   1773: dup
    //   1774: iconst_2
    //   1775: ldc 34078720
    //   1777: iastore
    //   1778: dup
    //   1779: iconst_3
    //   1780: ldc 1107296512
    //   1782: iastore
    //   1783: dup
    //   1784: iconst_4
    //   1785: ldc 524288
    //   1787: iastore
    //   1788: dup
    //   1789: iconst_5
    //   1790: sipush #256
    //   1793: iastore
    //   1794: dup
    //   1795: bipush #6
    //   1797: ldc 1073741824
    //   1799: iastore
    //   1800: dup
    //   1801: bipush #7
    //   1803: ldc 34078720
    //   1805: iastore
    //   1806: dup
    //   1807: bipush #8
    //   1809: ldc 1074266368
    //   1811: iastore
    //   1812: dup
    //   1813: bipush #9
    //   1815: ldc 524288
    //   1817: iastore
    //   1818: dup
    //   1819: bipush #10
    //   1821: ldc 33554688
    //   1823: iastore
    //   1824: dup
    //   1825: bipush #11
    //   1827: ldc 1074266368
    //   1829: iastore
    //   1830: dup
    //   1831: bipush #12
    //   1833: ldc 1107296512
    //   1835: iastore
    //   1836: dup
    //   1837: bipush #13
    //   1839: ldc 1107820544
    //   1841: iastore
    //   1842: dup
    //   1843: bipush #14
    //   1845: ldc 524544
    //   1847: iastore
    //   1848: dup
    //   1849: bipush #15
    //   1851: ldc 1073741824
    //   1853: iastore
    //   1854: dup
    //   1855: bipush #16
    //   1857: ldc 33554432
    //   1859: iastore
    //   1860: dup
    //   1861: bipush #17
    //   1863: ldc 1074266112
    //   1865: iastore
    //   1866: dup
    //   1867: bipush #18
    //   1869: ldc 1074266112
    //   1871: iastore
    //   1872: dup
    //   1873: bipush #19
    //   1875: iconst_0
    //   1876: iastore
    //   1877: dup
    //   1878: bipush #20
    //   1880: ldc 1073742080
    //   1882: iastore
    //   1883: dup
    //   1884: bipush #21
    //   1886: ldc 1107820800
    //   1888: iastore
    //   1889: dup
    //   1890: bipush #22
    //   1892: ldc 1107820800
    //   1894: iastore
    //   1895: dup
    //   1896: bipush #23
    //   1898: ldc 33554688
    //   1900: iastore
    //   1901: dup
    //   1902: bipush #24
    //   1904: ldc 1107820544
    //   1906: iastore
    //   1907: dup
    //   1908: bipush #25
    //   1910: ldc 1073742080
    //   1912: iastore
    //   1913: dup
    //   1914: bipush #26
    //   1916: iconst_0
    //   1917: iastore
    //   1918: dup
    //   1919: bipush #27
    //   1921: ldc 1107296256
    //   1923: iastore
    //   1924: dup
    //   1925: bipush #28
    //   1927: ldc 34078976
    //   1929: iastore
    //   1930: dup
    //   1931: bipush #29
    //   1933: ldc 33554432
    //   1935: iastore
    //   1936: dup
    //   1937: bipush #30
    //   1939: ldc 1107296256
    //   1941: iastore
    //   1942: dup
    //   1943: bipush #31
    //   1945: ldc 524544
    //   1947: iastore
    //   1948: dup
    //   1949: bipush #32
    //   1951: ldc 524288
    //   1953: iastore
    //   1954: dup
    //   1955: bipush #33
    //   1957: ldc 1107296512
    //   1959: iastore
    //   1960: dup
    //   1961: bipush #34
    //   1963: sipush #256
    //   1966: iastore
    //   1967: dup
    //   1968: bipush #35
    //   1970: ldc 33554432
    //   1972: iastore
    //   1973: dup
    //   1974: bipush #36
    //   1976: ldc 1073741824
    //   1978: iastore
    //   1979: dup
    //   1980: bipush #37
    //   1982: ldc 34078720
    //   1984: iastore
    //   1985: dup
    //   1986: bipush #38
    //   1988: ldc 1107296512
    //   1990: iastore
    //   1991: dup
    //   1992: bipush #39
    //   1994: ldc 1074266368
    //   1996: iastore
    //   1997: dup
    //   1998: bipush #40
    //   2000: ldc 33554688
    //   2002: iastore
    //   2003: dup
    //   2004: bipush #41
    //   2006: ldc 1073741824
    //   2008: iastore
    //   2009: dup
    //   2010: bipush #42
    //   2012: ldc 1107820544
    //   2014: iastore
    //   2015: dup
    //   2016: bipush #43
    //   2018: ldc 34078976
    //   2020: iastore
    //   2021: dup
    //   2022: bipush #44
    //   2024: ldc 1074266368
    //   2026: iastore
    //   2027: dup
    //   2028: bipush #45
    //   2030: sipush #256
    //   2033: iastore
    //   2034: dup
    //   2035: bipush #46
    //   2037: ldc 33554432
    //   2039: iastore
    //   2040: dup
    //   2041: bipush #47
    //   2043: ldc 1107820544
    //   2045: iastore
    //   2046: dup
    //   2047: bipush #48
    //   2049: ldc 1107820800
    //   2051: iastore
    //   2052: dup
    //   2053: bipush #49
    //   2055: ldc 524544
    //   2057: iastore
    //   2058: dup
    //   2059: bipush #50
    //   2061: ldc 1107296256
    //   2063: iastore
    //   2064: dup
    //   2065: bipush #51
    //   2067: ldc 1107820800
    //   2069: iastore
    //   2070: dup
    //   2071: bipush #52
    //   2073: ldc 34078720
    //   2075: iastore
    //   2076: dup
    //   2077: bipush #53
    //   2079: iconst_0
    //   2080: iastore
    //   2081: dup
    //   2082: bipush #54
    //   2084: ldc 1074266112
    //   2086: iastore
    //   2087: dup
    //   2088: bipush #55
    //   2090: ldc 1107296256
    //   2092: iastore
    //   2093: dup
    //   2094: bipush #56
    //   2096: ldc 524544
    //   2098: iastore
    //   2099: dup
    //   2100: bipush #57
    //   2102: ldc 33554688
    //   2104: iastore
    //   2105: dup
    //   2106: bipush #58
    //   2108: ldc 1073742080
    //   2110: iastore
    //   2111: dup
    //   2112: bipush #59
    //   2114: ldc 524288
    //   2116: iastore
    //   2117: dup
    //   2118: bipush #60
    //   2120: iconst_0
    //   2121: iastore
    //   2122: dup
    //   2123: bipush #61
    //   2125: ldc 1074266112
    //   2127: iastore
    //   2128: dup
    //   2129: bipush #62
    //   2131: ldc 34078976
    //   2133: iastore
    //   2134: dup
    //   2135: bipush #63
    //   2137: ldc 1073742080
    //   2139: iastore
    //   2140: astore #10
    //   2142: bipush #64
    //   2144: newarray int
    //   2146: dup
    //   2147: iconst_0
    //   2148: ldc 536870928
    //   2150: iastore
    //   2151: dup
    //   2152: iconst_1
    //   2153: ldc 541065216
    //   2155: iastore
    //   2156: dup
    //   2157: iconst_2
    //   2158: sipush #16384
    //   2161: iastore
    //   2162: dup
    //   2163: iconst_3
    //   2164: ldc 541081616
    //   2166: iastore
    //   2167: dup
    //   2168: iconst_4
    //   2169: ldc 541065216
    //   2171: iastore
    //   2172: dup
    //   2173: iconst_5
    //   2174: bipush #16
    //   2176: iastore
    //   2177: dup
    //   2178: bipush #6
    //   2180: ldc 541081616
    //   2182: iastore
    //   2183: dup
    //   2184: bipush #7
    //   2186: ldc 4194304
    //   2188: iastore
    //   2189: dup
    //   2190: bipush #8
    //   2192: ldc 536887296
    //   2194: iastore
    //   2195: dup
    //   2196: bipush #9
    //   2198: ldc 4210704
    //   2200: iastore
    //   2201: dup
    //   2202: bipush #10
    //   2204: ldc 4194304
    //   2206: iastore
    //   2207: dup
    //   2208: bipush #11
    //   2210: ldc 536870928
    //   2212: iastore
    //   2213: dup
    //   2214: bipush #12
    //   2216: ldc 4194320
    //   2218: iastore
    //   2219: dup
    //   2220: bipush #13
    //   2222: ldc 536887296
    //   2224: iastore
    //   2225: dup
    //   2226: bipush #14
    //   2228: ldc 536870912
    //   2230: iastore
    //   2231: dup
    //   2232: bipush #15
    //   2234: sipush #16400
    //   2237: iastore
    //   2238: dup
    //   2239: bipush #16
    //   2241: iconst_0
    //   2242: iastore
    //   2243: dup
    //   2244: bipush #17
    //   2246: ldc 4194320
    //   2248: iastore
    //   2249: dup
    //   2250: bipush #18
    //   2252: ldc 536887312
    //   2254: iastore
    //   2255: dup
    //   2256: bipush #19
    //   2258: sipush #16384
    //   2261: iastore
    //   2262: dup
    //   2263: bipush #20
    //   2265: ldc 4210688
    //   2267: iastore
    //   2268: dup
    //   2269: bipush #21
    //   2271: ldc 536887312
    //   2273: iastore
    //   2274: dup
    //   2275: bipush #22
    //   2277: bipush #16
    //   2279: iastore
    //   2280: dup
    //   2281: bipush #23
    //   2283: ldc 541065232
    //   2285: iastore
    //   2286: dup
    //   2287: bipush #24
    //   2289: ldc 541065232
    //   2291: iastore
    //   2292: dup
    //   2293: bipush #25
    //   2295: iconst_0
    //   2296: iastore
    //   2297: dup
    //   2298: bipush #26
    //   2300: ldc 4210704
    //   2302: iastore
    //   2303: dup
    //   2304: bipush #27
    //   2306: ldc 541081600
    //   2308: iastore
    //   2309: dup
    //   2310: bipush #28
    //   2312: sipush #16400
    //   2315: iastore
    //   2316: dup
    //   2317: bipush #29
    //   2319: ldc 4210688
    //   2321: iastore
    //   2322: dup
    //   2323: bipush #30
    //   2325: ldc 541081600
    //   2327: iastore
    //   2328: dup
    //   2329: bipush #31
    //   2331: ldc 536870912
    //   2333: iastore
    //   2334: dup
    //   2335: bipush #32
    //   2337: ldc 536887296
    //   2339: iastore
    //   2340: dup
    //   2341: bipush #33
    //   2343: bipush #16
    //   2345: iastore
    //   2346: dup
    //   2347: bipush #34
    //   2349: ldc 541065232
    //   2351: iastore
    //   2352: dup
    //   2353: bipush #35
    //   2355: ldc 4210688
    //   2357: iastore
    //   2358: dup
    //   2359: bipush #36
    //   2361: ldc 541081616
    //   2363: iastore
    //   2364: dup
    //   2365: bipush #37
    //   2367: ldc 4194304
    //   2369: iastore
    //   2370: dup
    //   2371: bipush #38
    //   2373: sipush #16400
    //   2376: iastore
    //   2377: dup
    //   2378: bipush #39
    //   2380: ldc 536870928
    //   2382: iastore
    //   2383: dup
    //   2384: bipush #40
    //   2386: ldc 4194304
    //   2388: iastore
    //   2389: dup
    //   2390: bipush #41
    //   2392: ldc 536887296
    //   2394: iastore
    //   2395: dup
    //   2396: bipush #42
    //   2398: ldc 536870912
    //   2400: iastore
    //   2401: dup
    //   2402: bipush #43
    //   2404: sipush #16400
    //   2407: iastore
    //   2408: dup
    //   2409: bipush #44
    //   2411: ldc 536870928
    //   2413: iastore
    //   2414: dup
    //   2415: bipush #45
    //   2417: ldc 541081616
    //   2419: iastore
    //   2420: dup
    //   2421: bipush #46
    //   2423: ldc 4210688
    //   2425: iastore
    //   2426: dup
    //   2427: bipush #47
    //   2429: ldc 541065216
    //   2431: iastore
    //   2432: dup
    //   2433: bipush #48
    //   2435: ldc 4210704
    //   2437: iastore
    //   2438: dup
    //   2439: bipush #49
    //   2441: ldc 541081600
    //   2443: iastore
    //   2444: dup
    //   2445: bipush #50
    //   2447: iconst_0
    //   2448: iastore
    //   2449: dup
    //   2450: bipush #51
    //   2452: ldc 541065232
    //   2454: iastore
    //   2455: dup
    //   2456: bipush #52
    //   2458: bipush #16
    //   2460: iastore
    //   2461: dup
    //   2462: bipush #53
    //   2464: sipush #16384
    //   2467: iastore
    //   2468: dup
    //   2469: bipush #54
    //   2471: ldc 541065216
    //   2473: iastore
    //   2474: dup
    //   2475: bipush #55
    //   2477: ldc 4210704
    //   2479: iastore
    //   2480: dup
    //   2481: bipush #56
    //   2483: sipush #16384
    //   2486: iastore
    //   2487: dup
    //   2488: bipush #57
    //   2490: ldc 4194320
    //   2492: iastore
    //   2493: dup
    //   2494: bipush #58
    //   2496: ldc 536887312
    //   2498: iastore
    //   2499: dup
    //   2500: bipush #59
    //   2502: iconst_0
    //   2503: iastore
    //   2504: dup
    //   2505: bipush #60
    //   2507: ldc 541081600
    //   2509: iastore
    //   2510: dup
    //   2511: bipush #61
    //   2513: ldc 536870912
    //   2515: iastore
    //   2516: dup
    //   2517: bipush #62
    //   2519: ldc 4194320
    //   2521: iastore
    //   2522: dup
    //   2523: bipush #63
    //   2525: ldc 536887312
    //   2527: iastore
    //   2528: astore #11
    //   2530: bipush #64
    //   2532: newarray int
    //   2534: dup
    //   2535: iconst_0
    //   2536: ldc 2097152
    //   2538: iastore
    //   2539: dup
    //   2540: iconst_1
    //   2541: ldc 69206018
    //   2543: iastore
    //   2544: dup
    //   2545: iconst_2
    //   2546: ldc 67110914
    //   2548: iastore
    //   2549: dup
    //   2550: iconst_3
    //   2551: iconst_0
    //   2552: iastore
    //   2553: dup
    //   2554: iconst_4
    //   2555: sipush #2048
    //   2558: iastore
    //   2559: dup
    //   2560: iconst_5
    //   2561: ldc 67110914
    //   2563: iastore
    //   2564: dup
    //   2565: bipush #6
    //   2567: ldc 2099202
    //   2569: iastore
    //   2570: dup
    //   2571: bipush #7
    //   2573: ldc 69208064
    //   2575: iastore
    //   2576: dup
    //   2577: bipush #8
    //   2579: ldc 69208066
    //   2581: iastore
    //   2582: dup
    //   2583: bipush #9
    //   2585: ldc 2097152
    //   2587: iastore
    //   2588: dup
    //   2589: bipush #10
    //   2591: iconst_0
    //   2592: iastore
    //   2593: dup
    //   2594: bipush #11
    //   2596: ldc 67108866
    //   2598: iastore
    //   2599: dup
    //   2600: bipush #12
    //   2602: iconst_2
    //   2603: iastore
    //   2604: dup
    //   2605: bipush #13
    //   2607: ldc 67108864
    //   2609: iastore
    //   2610: dup
    //   2611: bipush #14
    //   2613: ldc 69206018
    //   2615: iastore
    //   2616: dup
    //   2617: bipush #15
    //   2619: sipush #2050
    //   2622: iastore
    //   2623: dup
    //   2624: bipush #16
    //   2626: ldc 67110912
    //   2628: iastore
    //   2629: dup
    //   2630: bipush #17
    //   2632: ldc 2099202
    //   2634: iastore
    //   2635: dup
    //   2636: bipush #18
    //   2638: ldc 2097154
    //   2640: iastore
    //   2641: dup
    //   2642: bipush #19
    //   2644: ldc 67110912
    //   2646: iastore
    //   2647: dup
    //   2648: bipush #20
    //   2650: ldc 67108866
    //   2652: iastore
    //   2653: dup
    //   2654: bipush #21
    //   2656: ldc 69206016
    //   2658: iastore
    //   2659: dup
    //   2660: bipush #22
    //   2662: ldc 69208064
    //   2664: iastore
    //   2665: dup
    //   2666: bipush #23
    //   2668: ldc 2097154
    //   2670: iastore
    //   2671: dup
    //   2672: bipush #24
    //   2674: ldc 69206016
    //   2676: iastore
    //   2677: dup
    //   2678: bipush #25
    //   2680: sipush #2048
    //   2683: iastore
    //   2684: dup
    //   2685: bipush #26
    //   2687: sipush #2050
    //   2690: iastore
    //   2691: dup
    //   2692: bipush #27
    //   2694: ldc 69208066
    //   2696: iastore
    //   2697: dup
    //   2698: bipush #28
    //   2700: ldc 2099200
    //   2702: iastore
    //   2703: dup
    //   2704: bipush #29
    //   2706: iconst_2
    //   2707: iastore
    //   2708: dup
    //   2709: bipush #30
    //   2711: ldc 67108864
    //   2713: iastore
    //   2714: dup
    //   2715: bipush #31
    //   2717: ldc 2099200
    //   2719: iastore
    //   2720: dup
    //   2721: bipush #32
    //   2723: ldc 67108864
    //   2725: iastore
    //   2726: dup
    //   2727: bipush #33
    //   2729: ldc 2099200
    //   2731: iastore
    //   2732: dup
    //   2733: bipush #34
    //   2735: ldc 2097152
    //   2737: iastore
    //   2738: dup
    //   2739: bipush #35
    //   2741: ldc 67110914
    //   2743: iastore
    //   2744: dup
    //   2745: bipush #36
    //   2747: ldc 67110914
    //   2749: iastore
    //   2750: dup
    //   2751: bipush #37
    //   2753: ldc 69206018
    //   2755: iastore
    //   2756: dup
    //   2757: bipush #38
    //   2759: ldc 69206018
    //   2761: iastore
    //   2762: dup
    //   2763: bipush #39
    //   2765: iconst_2
    //   2766: iastore
    //   2767: dup
    //   2768: bipush #40
    //   2770: ldc 2097154
    //   2772: iastore
    //   2773: dup
    //   2774: bipush #41
    //   2776: ldc 67108864
    //   2778: iastore
    //   2779: dup
    //   2780: bipush #42
    //   2782: ldc 67110912
    //   2784: iastore
    //   2785: dup
    //   2786: bipush #43
    //   2788: ldc 2097152
    //   2790: iastore
    //   2791: dup
    //   2792: bipush #44
    //   2794: ldc 69208064
    //   2796: iastore
    //   2797: dup
    //   2798: bipush #45
    //   2800: sipush #2050
    //   2803: iastore
    //   2804: dup
    //   2805: bipush #46
    //   2807: ldc 2099202
    //   2809: iastore
    //   2810: dup
    //   2811: bipush #47
    //   2813: ldc 69208064
    //   2815: iastore
    //   2816: dup
    //   2817: bipush #48
    //   2819: sipush #2050
    //   2822: iastore
    //   2823: dup
    //   2824: bipush #49
    //   2826: ldc 67108866
    //   2828: iastore
    //   2829: dup
    //   2830: bipush #50
    //   2832: ldc 69208066
    //   2834: iastore
    //   2835: dup
    //   2836: bipush #51
    //   2838: ldc 69206016
    //   2840: iastore
    //   2841: dup
    //   2842: bipush #52
    //   2844: ldc 2099200
    //   2846: iastore
    //   2847: dup
    //   2848: bipush #53
    //   2850: iconst_0
    //   2851: iastore
    //   2852: dup
    //   2853: bipush #54
    //   2855: iconst_2
    //   2856: iastore
    //   2857: dup
    //   2858: bipush #55
    //   2860: ldc 69208066
    //   2862: iastore
    //   2863: dup
    //   2864: bipush #56
    //   2866: iconst_0
    //   2867: iastore
    //   2868: dup
    //   2869: bipush #57
    //   2871: ldc 2099202
    //   2873: iastore
    //   2874: dup
    //   2875: bipush #58
    //   2877: ldc 69206016
    //   2879: iastore
    //   2880: dup
    //   2881: bipush #59
    //   2883: sipush #2048
    //   2886: iastore
    //   2887: dup
    //   2888: bipush #60
    //   2890: ldc 67108866
    //   2892: iastore
    //   2893: dup
    //   2894: bipush #61
    //   2896: ldc 67110912
    //   2898: iastore
    //   2899: dup
    //   2900: bipush #62
    //   2902: sipush #2048
    //   2905: iastore
    //   2906: dup
    //   2907: bipush #63
    //   2909: ldc 2097154
    //   2911: iastore
    //   2912: astore #12
    //   2914: bipush #64
    //   2916: newarray int
    //   2918: dup
    //   2919: iconst_0
    //   2920: ldc 268439616
    //   2922: iastore
    //   2923: dup
    //   2924: iconst_1
    //   2925: sipush #4096
    //   2928: iastore
    //   2929: dup
    //   2930: iconst_2
    //   2931: ldc 262144
    //   2933: iastore
    //   2934: dup
    //   2935: iconst_3
    //   2936: ldc 268701760
    //   2938: iastore
    //   2939: dup
    //   2940: iconst_4
    //   2941: ldc 268435456
    //   2943: iastore
    //   2944: dup
    //   2945: iconst_5
    //   2946: ldc 268439616
    //   2948: iastore
    //   2949: dup
    //   2950: bipush #6
    //   2952: bipush #64
    //   2954: iastore
    //   2955: dup
    //   2956: bipush #7
    //   2958: ldc 268435456
    //   2960: iastore
    //   2961: dup
    //   2962: bipush #8
    //   2964: ldc 262208
    //   2966: iastore
    //   2967: dup
    //   2968: bipush #9
    //   2970: ldc 268697600
    //   2972: iastore
    //   2973: dup
    //   2974: bipush #10
    //   2976: ldc 268701760
    //   2978: iastore
    //   2979: dup
    //   2980: bipush #11
    //   2982: ldc 266240
    //   2984: iastore
    //   2985: dup
    //   2986: bipush #12
    //   2988: ldc 268701696
    //   2990: iastore
    //   2991: dup
    //   2992: bipush #13
    //   2994: ldc 266304
    //   2996: iastore
    //   2997: dup
    //   2998: bipush #14
    //   3000: sipush #4096
    //   3003: iastore
    //   3004: dup
    //   3005: bipush #15
    //   3007: bipush #64
    //   3009: iastore
    //   3010: dup
    //   3011: bipush #16
    //   3013: ldc 268697600
    //   3015: iastore
    //   3016: dup
    //   3017: bipush #17
    //   3019: ldc 268435520
    //   3021: iastore
    //   3022: dup
    //   3023: bipush #18
    //   3025: ldc 268439552
    //   3027: iastore
    //   3028: dup
    //   3029: bipush #19
    //   3031: sipush #4160
    //   3034: iastore
    //   3035: dup
    //   3036: bipush #20
    //   3038: ldc 266240
    //   3040: iastore
    //   3041: dup
    //   3042: bipush #21
    //   3044: ldc 262208
    //   3046: iastore
    //   3047: dup
    //   3048: bipush #22
    //   3050: ldc 268697664
    //   3052: iastore
    //   3053: dup
    //   3054: bipush #23
    //   3056: ldc 268701696
    //   3058: iastore
    //   3059: dup
    //   3060: bipush #24
    //   3062: sipush #4160
    //   3065: iastore
    //   3066: dup
    //   3067: bipush #25
    //   3069: iconst_0
    //   3070: iastore
    //   3071: dup
    //   3072: bipush #26
    //   3074: iconst_0
    //   3075: iastore
    //   3076: dup
    //   3077: bipush #27
    //   3079: ldc 268697664
    //   3081: iastore
    //   3082: dup
    //   3083: bipush #28
    //   3085: ldc 268435520
    //   3087: iastore
    //   3088: dup
    //   3089: bipush #29
    //   3091: ldc 268439552
    //   3093: iastore
    //   3094: dup
    //   3095: bipush #30
    //   3097: ldc 266304
    //   3099: iastore
    //   3100: dup
    //   3101: bipush #31
    //   3103: ldc 262144
    //   3105: iastore
    //   3106: dup
    //   3107: bipush #32
    //   3109: ldc 266304
    //   3111: iastore
    //   3112: dup
    //   3113: bipush #33
    //   3115: ldc 262144
    //   3117: iastore
    //   3118: dup
    //   3119: bipush #34
    //   3121: ldc 268701696
    //   3123: iastore
    //   3124: dup
    //   3125: bipush #35
    //   3127: sipush #4096
    //   3130: iastore
    //   3131: dup
    //   3132: bipush #36
    //   3134: bipush #64
    //   3136: iastore
    //   3137: dup
    //   3138: bipush #37
    //   3140: ldc 268697664
    //   3142: iastore
    //   3143: dup
    //   3144: bipush #38
    //   3146: sipush #4096
    //   3149: iastore
    //   3150: dup
    //   3151: bipush #39
    //   3153: ldc 266304
    //   3155: iastore
    //   3156: dup
    //   3157: bipush #40
    //   3159: ldc 268439552
    //   3161: iastore
    //   3162: dup
    //   3163: bipush #41
    //   3165: bipush #64
    //   3167: iastore
    //   3168: dup
    //   3169: bipush #42
    //   3171: ldc 268435520
    //   3173: iastore
    //   3174: dup
    //   3175: bipush #43
    //   3177: ldc 268697600
    //   3179: iastore
    //   3180: dup
    //   3181: bipush #44
    //   3183: ldc 268697664
    //   3185: iastore
    //   3186: dup
    //   3187: bipush #45
    //   3189: ldc 268435456
    //   3191: iastore
    //   3192: dup
    //   3193: bipush #46
    //   3195: ldc 262144
    //   3197: iastore
    //   3198: dup
    //   3199: bipush #47
    //   3201: ldc 268439616
    //   3203: iastore
    //   3204: dup
    //   3205: bipush #48
    //   3207: iconst_0
    //   3208: iastore
    //   3209: dup
    //   3210: bipush #49
    //   3212: ldc 268701760
    //   3214: iastore
    //   3215: dup
    //   3216: bipush #50
    //   3218: ldc 262208
    //   3220: iastore
    //   3221: dup
    //   3222: bipush #51
    //   3224: ldc 268435520
    //   3226: iastore
    //   3227: dup
    //   3228: bipush #52
    //   3230: ldc 268697600
    //   3232: iastore
    //   3233: dup
    //   3234: bipush #53
    //   3236: ldc 268439552
    //   3238: iastore
    //   3239: dup
    //   3240: bipush #54
    //   3242: ldc 268439616
    //   3244: iastore
    //   3245: dup
    //   3246: bipush #55
    //   3248: iconst_0
    //   3249: iastore
    //   3250: dup
    //   3251: bipush #56
    //   3253: ldc 268701760
    //   3255: iastore
    //   3256: dup
    //   3257: bipush #57
    //   3259: ldc 266240
    //   3261: iastore
    //   3262: dup
    //   3263: bipush #58
    //   3265: ldc 266240
    //   3267: iastore
    //   3268: dup
    //   3269: bipush #59
    //   3271: sipush #4160
    //   3274: iastore
    //   3275: dup
    //   3276: bipush #60
    //   3278: sipush #4160
    //   3281: iastore
    //   3282: dup
    //   3283: bipush #61
    //   3285: ldc 262208
    //   3287: iastore
    //   3288: dup
    //   3289: bipush #62
    //   3291: ldc 268435456
    //   3293: iastore
    //   3294: dup
    //   3295: bipush #63
    //   3297: ldc 268701696
    //   3299: iastore
    //   3300: astore #13
    //   3302: aload_3
    //   3303: arraylength
    //   3304: istore #14
    //   3306: iload #14
    //   3308: bipush #8
    //   3310: irem
    //   3311: ifeq -> 3335
    //   3314: new java/lang/Exception
    //   3317: dup
    //   3318: sipush #32244
    //   3321: sipush #7699
    //   3324: invokestatic a : (II)Ljava/lang/String;
    //   3327: invokespecial <init> : (Ljava/lang/String;)V
    //   3330: athrow
    //   3331: invokestatic a : (Ljava/lang/Throwable;)Ljava/lang/Throwable;
    //   3334: athrow
    //   3335: iconst_2
    //   3336: newarray int
    //   3338: astore #15
    //   3340: iload #14
    //   3342: newarray byte
    //   3344: astore #16
    //   3346: iload #14
    //   3348: bipush #8
    //   3350: idiv
    //   3351: istore #17
    //   3353: iconst_0
    //   3354: istore #18
    //   3356: iload #18
    //   3358: iload #17
    //   3360: if_icmpge -> 4274
    //   3363: iload #18
    //   3365: bipush #8
    //   3367: imul
    //   3368: istore #19
    //   3370: iconst_0
    //   3371: istore #20
    //   3373: iload #20
    //   3375: iconst_2
    //   3376: if_icmpge -> 3461
    //   3379: aload #15
    //   3381: iload #20
    //   3383: aload_3
    //   3384: iload #19
    //   3386: iload #20
    //   3388: iconst_4
    //   3389: imul
    //   3390: iadd
    //   3391: baload
    //   3392: sipush #255
    //   3395: iand
    //   3396: bipush #24
    //   3398: ishl
    //   3399: aload_3
    //   3400: iload #19
    //   3402: iload #20
    //   3404: iconst_4
    //   3405: imul
    //   3406: iadd
    //   3407: iconst_1
    //   3408: iadd
    //   3409: baload
    //   3410: sipush #255
    //   3413: iand
    //   3414: bipush #16
    //   3416: ishl
    //   3417: ior
    //   3418: aload_3
    //   3419: iload #19
    //   3421: iload #20
    //   3423: iconst_4
    //   3424: imul
    //   3425: iadd
    //   3426: iconst_2
    //   3427: iadd
    //   3428: baload
    //   3429: sipush #255
    //   3432: iand
    //   3433: bipush #8
    //   3435: ishl
    //   3436: ior
    //   3437: aload_3
    //   3438: iload #19
    //   3440: iload #20
    //   3442: iconst_4
    //   3443: imul
    //   3444: iadd
    //   3445: iconst_3
    //   3446: iadd
    //   3447: baload
    //   3448: sipush #255
    //   3451: iand
    //   3452: ior
    //   3453: iastore
    //   3454: iinc #20, 1
    //   3457: iload_2
    //   3458: ifeq -> 3373
    //   3461: iconst_0
    //   3462: istore #25
    //   3464: aload #15
    //   3466: iconst_0
    //   3467: iaload
    //   3468: istore #23
    //   3470: aload #15
    //   3472: iconst_1
    //   3473: iaload
    //   3474: istore #22
    //   3476: iload #23
    //   3478: iconst_4
    //   3479: iushr
    //   3480: iload #22
    //   3482: ixor
    //   3483: ldc 252645135
    //   3485: iand
    //   3486: istore #21
    //   3488: iload #22
    //   3490: iload #21
    //   3492: ixor
    //   3493: istore #22
    //   3495: iload #23
    //   3497: iload #21
    //   3499: iconst_4
    //   3500: ishl
    //   3501: ixor
    //   3502: istore #23
    //   3504: iload #23
    //   3506: bipush #16
    //   3508: iushr
    //   3509: iload #22
    //   3511: ixor
    //   3512: ldc 65535
    //   3514: iand
    //   3515: istore #21
    //   3517: iload #22
    //   3519: iload #21
    //   3521: ixor
    //   3522: istore #22
    //   3524: iload #23
    //   3526: iload #21
    //   3528: bipush #16
    //   3530: ishl
    //   3531: ixor
    //   3532: istore #23
    //   3534: iload #22
    //   3536: iconst_2
    //   3537: iushr
    //   3538: iload #23
    //   3540: ixor
    //   3541: ldc 858993459
    //   3543: iand
    //   3544: istore #21
    //   3546: iload #23
    //   3548: iload #21
    //   3550: ixor
    //   3551: istore #23
    //   3553: iload #22
    //   3555: iload #21
    //   3557: iconst_2
    //   3558: ishl
    //   3559: ixor
    //   3560: istore #22
    //   3562: iload #22
    //   3564: bipush #8
    //   3566: iushr
    //   3567: iload #23
    //   3569: ixor
    //   3570: ldc 16711935
    //   3572: iand
    //   3573: istore #21
    //   3575: iload #23
    //   3577: iload #21
    //   3579: ixor
    //   3580: istore #23
    //   3582: iload #22
    //   3584: iload #21
    //   3586: bipush #8
    //   3588: ishl
    //   3589: ixor
    //   3590: istore #22
    //   3592: iload #22
    //   3594: iconst_1
    //   3595: ishl
    //   3596: iload #22
    //   3598: bipush #31
    //   3600: iushr
    //   3601: iconst_1
    //   3602: iand
    //   3603: ior
    //   3604: istore #22
    //   3606: iload #23
    //   3608: iload #22
    //   3610: ixor
    //   3611: ldc -1431655766
    //   3613: iand
    //   3614: istore #21
    //   3616: iload #23
    //   3618: iload #21
    //   3620: ixor
    //   3621: istore #23
    //   3623: iload #22
    //   3625: iload #21
    //   3627: ixor
    //   3628: istore #22
    //   3630: iload #23
    //   3632: iconst_1
    //   3633: ishl
    //   3634: iload #23
    //   3636: bipush #31
    //   3638: iushr
    //   3639: iconst_1
    //   3640: iand
    //   3641: ior
    //   3642: istore #23
    //   3644: iconst_0
    //   3645: istore #24
    //   3647: iload #24
    //   3649: bipush #8
    //   3651: if_icmpge -> 3989
    //   3654: iload #22
    //   3656: bipush #28
    //   3658: ishl
    //   3659: iload #22
    //   3661: iconst_4
    //   3662: iushr
    //   3663: ior
    //   3664: istore #21
    //   3666: iload #21
    //   3668: aload #5
    //   3670: iload #25
    //   3672: iinc #25, 1
    //   3675: iaload
    //   3676: ixor
    //   3677: istore #21
    //   3679: aload #12
    //   3681: iload #21
    //   3683: bipush #63
    //   3685: iand
    //   3686: iaload
    //   3687: istore #20
    //   3689: iload #20
    //   3691: aload #10
    //   3693: iload #21
    //   3695: bipush #8
    //   3697: iushr
    //   3698: bipush #63
    //   3700: iand
    //   3701: iaload
    //   3702: ior
    //   3703: istore #20
    //   3705: iload #20
    //   3707: aload #8
    //   3709: iload #21
    //   3711: bipush #16
    //   3713: iushr
    //   3714: bipush #63
    //   3716: iand
    //   3717: iaload
    //   3718: ior
    //   3719: istore #20
    //   3721: iload #20
    //   3723: aload #6
    //   3725: iload #21
    //   3727: bipush #24
    //   3729: iushr
    //   3730: bipush #63
    //   3732: iand
    //   3733: iaload
    //   3734: ior
    //   3735: istore #20
    //   3737: iload #22
    //   3739: aload #5
    //   3741: iload #25
    //   3743: iinc #25, 1
    //   3746: iaload
    //   3747: ixor
    //   3748: istore #21
    //   3750: iload #20
    //   3752: aload #13
    //   3754: iload #21
    //   3756: bipush #63
    //   3758: iand
    //   3759: iaload
    //   3760: ior
    //   3761: istore #20
    //   3763: iload #20
    //   3765: aload #11
    //   3767: iload #21
    //   3769: bipush #8
    //   3771: iushr
    //   3772: bipush #63
    //   3774: iand
    //   3775: iaload
    //   3776: ior
    //   3777: istore #20
    //   3779: iload #20
    //   3781: aload #9
    //   3783: iload #21
    //   3785: bipush #16
    //   3787: iushr
    //   3788: bipush #63
    //   3790: iand
    //   3791: iaload
    //   3792: ior
    //   3793: istore #20
    //   3795: iload #20
    //   3797: aload #7
    //   3799: iload #21
    //   3801: bipush #24
    //   3803: iushr
    //   3804: bipush #63
    //   3806: iand
    //   3807: iaload
    //   3808: ior
    //   3809: istore #20
    //   3811: iload #23
    //   3813: iload #20
    //   3815: ixor
    //   3816: istore #23
    //   3818: iload #23
    //   3820: bipush #28
    //   3822: ishl
    //   3823: iload #23
    //   3825: iconst_4
    //   3826: iushr
    //   3827: ior
    //   3828: istore #21
    //   3830: iload #21
    //   3832: aload #5
    //   3834: iload #25
    //   3836: iinc #25, 1
    //   3839: iaload
    //   3840: ixor
    //   3841: istore #21
    //   3843: aload #12
    //   3845: iload #21
    //   3847: bipush #63
    //   3849: iand
    //   3850: iaload
    //   3851: istore #20
    //   3853: iload #20
    //   3855: aload #10
    //   3857: iload #21
    //   3859: bipush #8
    //   3861: iushr
    //   3862: bipush #63
    //   3864: iand
    //   3865: iaload
    //   3866: ior
    //   3867: istore #20
    //   3869: iload #20
    //   3871: aload #8
    //   3873: iload #21
    //   3875: bipush #16
    //   3877: iushr
    //   3878: bipush #63
    //   3880: iand
    //   3881: iaload
    //   3882: ior
    //   3883: istore #20
    //   3885: iload #20
    //   3887: aload #6
    //   3889: iload #21
    //   3891: bipush #24
    //   3893: iushr
    //   3894: bipush #63
    //   3896: iand
    //   3897: iaload
    //   3898: ior
    //   3899: istore #20
    //   3901: iload #23
    //   3903: aload #5
    //   3905: iload #25
    //   3907: iinc #25, 1
    //   3910: iaload
    //   3911: ixor
    //   3912: istore #21
    //   3914: iload #20
    //   3916: aload #13
    //   3918: iload #21
    //   3920: bipush #63
    //   3922: iand
    //   3923: iaload
    //   3924: ior
    //   3925: istore #20
    //   3927: iload #20
    //   3929: aload #11
    //   3931: iload #21
    //   3933: bipush #8
    //   3935: iushr
    //   3936: bipush #63
    //   3938: iand
    //   3939: iaload
    //   3940: ior
    //   3941: istore #20
    //   3943: iload #20
    //   3945: aload #9
    //   3947: iload #21
    //   3949: bipush #16
    //   3951: iushr
    //   3952: bipush #63
    //   3954: iand
    //   3955: iaload
    //   3956: ior
    //   3957: istore #20
    //   3959: iload #20
    //   3961: aload #7
    //   3963: iload #21
    //   3965: bipush #24
    //   3967: iushr
    //   3968: bipush #63
    //   3970: iand
    //   3971: iaload
    //   3972: ior
    //   3973: istore #20
    //   3975: iload #22
    //   3977: iload #20
    //   3979: ixor
    //   3980: istore #22
    //   3982: iinc #24, 1
    //   3985: iload_2
    //   3986: ifeq -> 3647
    //   3989: iload #22
    //   3991: bipush #31
    //   3993: ishl
    //   3994: iload #22
    //   3996: iconst_1
    //   3997: iushr
    //   3998: ior
    //   3999: istore #22
    //   4001: iload #23
    //   4003: iload #22
    //   4005: ixor
    //   4006: ldc -1431655766
    //   4008: iand
    //   4009: istore #21
    //   4011: iload #23
    //   4013: iload #21
    //   4015: ixor
    //   4016: istore #23
    //   4018: iload #22
    //   4020: iload #21
    //   4022: ixor
    //   4023: istore #22
    //   4025: iload #23
    //   4027: bipush #31
    //   4029: ishl
    //   4030: iload #23
    //   4032: iconst_1
    //   4033: iushr
    //   4034: ior
    //   4035: istore #23
    //   4037: iload #23
    //   4039: bipush #8
    //   4041: iushr
    //   4042: iload #22
    //   4044: ixor
    //   4045: ldc 16711935
    //   4047: iand
    //   4048: istore #21
    //   4050: iload #22
    //   4052: iload #21
    //   4054: ixor
    //   4055: istore #22
    //   4057: iload #23
    //   4059: iload #21
    //   4061: bipush #8
    //   4063: ishl
    //   4064: ixor
    //   4065: istore #23
    //   4067: iload #23
    //   4069: iconst_2
    //   4070: iushr
    //   4071: iload #22
    //   4073: ixor
    //   4074: ldc 858993459
    //   4076: iand
    //   4077: istore #21
    //   4079: iload #22
    //   4081: iload #21
    //   4083: ixor
    //   4084: istore #22
    //   4086: iload #23
    //   4088: iload #21
    //   4090: iconst_2
    //   4091: ishl
    //   4092: ixor
    //   4093: istore #23
    //   4095: iload #22
    //   4097: bipush #16
    //   4099: iushr
    //   4100: iload #23
    //   4102: ixor
    //   4103: ldc 65535
    //   4105: iand
    //   4106: istore #21
    //   4108: iload #23
    //   4110: iload #21
    //   4112: ixor
    //   4113: istore #23
    //   4115: iload #22
    //   4117: iload #21
    //   4119: bipush #16
    //   4121: ishl
    //   4122: ixor
    //   4123: istore #22
    //   4125: iload #22
    //   4127: iconst_4
    //   4128: iushr
    //   4129: iload #23
    //   4131: ixor
    //   4132: ldc 252645135
    //   4134: iand
    //   4135: istore #21
    //   4137: iload #23
    //   4139: iload #21
    //   4141: ixor
    //   4142: istore #23
    //   4144: iload #22
    //   4146: iload #21
    //   4148: iconst_4
    //   4149: ishl
    //   4150: ixor
    //   4151: istore #22
    //   4153: aload #15
    //   4155: iconst_0
    //   4156: iload #22
    //   4158: iastore
    //   4159: aload #15
    //   4161: iconst_1
    //   4162: iload #23
    //   4164: iastore
    //   4165: iload #18
    //   4167: bipush #8
    //   4169: imul
    //   4170: istore #26
    //   4172: iconst_0
    //   4173: istore #27
    //   4175: iload #27
    //   4177: iconst_2
    //   4178: if_icmpge -> 4267
    //   4181: aload #16
    //   4183: iload #26
    //   4185: iload #27
    //   4187: iconst_4
    //   4188: imul
    //   4189: iadd
    //   4190: aload #15
    //   4192: iload #27
    //   4194: iaload
    //   4195: bipush #24
    //   4197: iushr
    //   4198: i2b
    //   4199: bastore
    //   4200: aload #16
    //   4202: iload #26
    //   4204: iload #27
    //   4206: iconst_4
    //   4207: imul
    //   4208: iadd
    //   4209: iconst_1
    //   4210: iadd
    //   4211: aload #15
    //   4213: iload #27
    //   4215: iaload
    //   4216: bipush #16
    //   4218: iushr
    //   4219: i2b
    //   4220: bastore
    //   4221: aload #16
    //   4223: iload #26
    //   4225: iload #27
    //   4227: iconst_4
    //   4228: imul
    //   4229: iadd
    //   4230: iconst_2
    //   4231: iadd
    //   4232: aload #15
    //   4234: iload #27
    //   4236: iaload
    //   4237: bipush #8
    //   4239: iushr
    //   4240: i2b
    //   4241: bastore
    //   4242: aload #16
    //   4244: iload #26
    //   4246: iload #27
    //   4248: iconst_4
    //   4249: imul
    //   4250: iadd
    //   4251: iconst_3
    //   4252: iadd
    //   4253: aload #15
    //   4255: iload #27
    //   4257: iaload
    //   4258: i2b
    //   4259: bastore
    //   4260: iinc #27, 1
    //   4263: iload_2
    //   4264: ifeq -> 4175
    //   4267: iinc #18, 1
    //   4270: iload_2
    //   4271: ifeq -> 3356
    //   4274: aload #16
    //   4276: aload #16
    //   4278: arraylength
    //   4279: iconst_1
    //   4280: isub
    //   4281: baload
    //   4282: istore #18
    //   4284: aload #16
    //   4286: arraylength
    //   4287: iload #18
    //   4289: isub
    //   4290: newarray byte
    //   4292: astore #4
    //   4294: aload #16
    //   4296: arraylength
    //   4297: aload #4
    //   4299: arraylength
    //   4300: if_icmpge -> 4324
    //   4303: new java/lang/Exception
    //   4306: dup
    //   4307: sipush #32254
    //   4310: sipush #25248
    //   4313: invokestatic a : (II)Ljava/lang/String;
    //   4316: invokespecial <init> : (Ljava/lang/String;)V
    //   4319: athrow
    //   4320: invokestatic a : (Ljava/lang/Throwable;)Ljava/lang/Throwable;
    //   4323: athrow
    //   4324: iconst_0
    //   4325: istore #19
    //   4327: iload #19
    //   4329: aload #4
    //   4331: arraylength
    //   4332: if_icmpge -> 4352
    //   4335: aload #4
    //   4337: iload #19
    //   4339: aload #16
    //   4341: iload #19
    //   4343: baload
    //   4344: bastore
    //   4345: iinc #19, 1
    //   4348: iload_2
    //   4349: ifeq -> 4327
    //   4352: new java/math/BigInteger
    //   4355: dup
    //   4356: aload #4
    //   4358: invokespecial <init> : ([B)V
    //   4361: invokevirtual abs : ()Ljava/math/BigInteger;
    //   4364: putstatic burp/Zex.ZO : Ljava/lang/Object;
    //   4367: ldc2_w 8682522807148012
    //   4370: invokestatic currentTimeMillis : ()J
    //   4373: lxor
    //   4374: lstore #4
    //   4376: lload #4
    //   4378: ldc2_w 25214903917
    //   4381: lmul
    //   4382: ldc2_w 11
    //   4385: ladd
    //   4386: ldc2_w 281474976710655
    //   4389: land
    //   4390: lstore #4
    //   4392: lload #4
    //   4394: bipush #32
    //   4396: lshl
    //   4397: lstore #6
    //   4399: lload #4
    //   4401: ldc2_w 25214903917
    //   4404: lmul
    //   4405: ldc2_w 11
    //   4408: ladd
    //   4409: ldc2_w 281474976710655
    //   4412: land
    //   4413: lstore #4
    //   4415: lload #6
    //   4417: lload #4
    //   4419: ladd
    //   4420: lstore #6
    //   4422: bipush #16
    //   4424: newarray byte
    //   4426: dup
    //   4427: iconst_0
    //   4428: bipush #48
    //   4430: bastore
    //   4431: dup
    //   4432: iconst_1
    //   4433: bipush #49
    //   4435: bastore
    //   4436: dup
    //   4437: iconst_2
    //   4438: bipush #50
    //   4440: bastore
    //   4441: dup
    //   4442: iconst_3
    //   4443: bipush #51
    //   4445: bastore
    //   4446: dup
    //   4447: iconst_4
    //   4448: bipush #52
    //   4450: bastore
    //   4451: dup
    //   4452: iconst_5
    //   4453: bipush #53
    //   4455: bastore
    //   4456: dup
    //   4457: bipush #6
    //   4459: bipush #54
    //   4461: bastore
    //   4462: dup
    //   4463: bipush #7
    //   4465: bipush #55
    //   4467: bastore
    //   4468: dup
    //   4469: bipush #8
    //   4471: bipush #56
    //   4473: bastore
    //   4474: dup
    //   4475: bipush #9
    //   4477: bipush #57
    //   4479: bastore
    //   4480: dup
    //   4481: bipush #10
    //   4483: bipush #97
    //   4485: bastore
    //   4486: dup
    //   4487: bipush #11
    //   4489: bipush #98
    //   4491: bastore
    //   4492: dup
    //   4493: bipush #12
    //   4495: bipush #99
    //   4497: bastore
    //   4498: dup
    //   4499: bipush #13
    //   4501: bipush #100
    //   4503: bastore
    //   4504: dup
    //   4505: bipush #14
    //   4507: bipush #101
    //   4509: bastore
    //   4510: dup
    //   4511: bipush #15
    //   4513: bipush #102
    //   4515: bastore
    //   4516: astore #8
    //   4518: bipush #64
    //   4520: newarray byte
    //   4522: astore #9
    //   4524: bipush #64
    //   4526: istore #10
    //   4528: bipush #16
    //   4530: istore #11
    //   4532: iload #11
    //   4534: iconst_1
    //   4535: isub
    //   4536: i2l
    //   4537: lstore #12
    //   4539: aload #9
    //   4541: iinc #10, -1
    //   4544: iload #10
    //   4546: aload #8
    //   4548: lload #6
    //   4550: lload #12
    //   4552: land
    //   4553: l2i
    //   4554: baload
    //   4555: bastore
    //   4556: lload #6
    //   4558: iconst_4
    //   4559: lushr
    //   4560: lstore #6
    //   4562: lload #6
    //   4564: lconst_0
    //   4565: lcmp
    //   4566: ifne -> 4539
    //   4569: bipush #64
    //   4571: iload #10
    //   4573: isub
    //   4574: newarray byte
    //   4576: astore_3
    //   4577: iconst_0
    //   4578: istore #14
    //   4580: iload #14
    //   4582: aload_3
    //   4583: arraylength
    //   4584: if_icmpge -> 4606
    //   4587: aload_3
    //   4588: iload #14
    //   4590: aload #9
    //   4592: iload #10
    //   4594: iload #14
    //   4596: iadd
    //   4597: baload
    //   4598: bastore
    //   4599: iinc #14, 1
    //   4602: iload_2
    //   4603: ifeq -> 4580
    //   4606: aload_3
    //   4607: arraylength
    //   4608: bipush #10
    //   4610: if_icmplt -> 4376
    //   4613: new java/lang/StringBuilder
    //   4616: dup
    //   4617: invokespecial <init> : ()V
    //   4620: astore_3
    //   4621: iconst_0
    //   4622: istore #4
    //   4624: iload #4
    //   4626: bipush #32
    //   4628: if_icmpge -> 5963
    //   4631: iload #4
    //   4633: tableswitch default -> 5956, 0 -> 4776, 1 -> 4813, 2 -> 4850, 3 -> 4887, 4 -> 4924, 5 -> 4961, 6 -> 4998, 7 -> 5035, 8 -> 5072, 9 -> 5109, 10 -> 5146, 11 -> 5183, 12 -> 5220, 13 -> 5257, 14 -> 5294, 15 -> 5331, 16 -> 5368, 17 -> 5405, 18 -> 5442, 19 -> 5479, 20 -> 5516, 21 -> 5553, 22 -> 5590, 23 -> 5627, 24 -> 5664, 25 -> 5701, 26 -> 5738, 27 -> 5775, 28 -> 5812, 29 -> 5849, 30 -> 5886, 31 -> 5923
    //   4776: aload_3
    //   4777: getstatic burp/Zxn5.ZI : Ljava/lang/String;
    //   4780: getstatic burp/Zzc_.Zi : Ljava/lang/Object;
    //   4783: checkcast java/math/BigInteger
    //   4786: invokevirtual intValue : ()I
    //   4789: bipush #32
    //   4791: irem
    //   4792: invokestatic abs : (I)I
    //   4795: invokevirtual charAt : (I)C
    //   4798: invokevirtual append : (C)Ljava/lang/StringBuilder;
    //   4801: pop
    //   4802: iload_2
    //   4803: ifeq -> 5956
    //   4806: goto -> 4813
    //   4809: invokestatic a : (Ljava/lang/Throwable;)Ljava/lang/Throwable;
    //   4812: athrow
    //   4813: aload_3
    //   4814: getstatic burp/Zs8s.Za : Ljava/lang/String;
    //   4817: getstatic burp/Zzym.ZK : Ljava/lang/Object;
    //   4820: checkcast java/math/BigInteger
    //   4823: invokevirtual intValue : ()I
    //   4826: bipush #32
    //   4828: irem
    //   4829: invokestatic abs : (I)I
    //   4832: invokevirtual charAt : (I)C
    //   4835: invokevirtual append : (C)Ljava/lang/StringBuilder;
    //   4838: pop
    //   4839: iload_2
    //   4840: ifeq -> 5956
    //   4843: goto -> 4850
    //   4846: invokestatic a : (Ljava/lang/Throwable;)Ljava/lang/Throwable;
    //   4849: athrow
    //   4850: aload_3
    //   4851: getstatic burp/Ze69.ZA : Ljava/lang/String;
    //   4854: getstatic burp/Zke7.Zj : Ljava/lang/Object;
    //   4857: checkcast java/math/BigInteger
    //   4860: invokevirtual intValue : ()I
    //   4863: bipush #32
    //   4865: irem
    //   4866: invokestatic abs : (I)I
    //   4869: invokevirtual charAt : (I)C
    //   4872: invokevirtual append : (C)Ljava/lang/StringBuilder;
    //   4875: pop
    //   4876: iload_2
    //   4877: ifeq -> 5956
    //   4880: goto -> 4887
    //   4883: invokestatic a : (Ljava/lang/Throwable;)Ljava/lang/Throwable;
    //   4886: athrow
    //   4887: aload_3
    //   4888: getstatic burp/Zs0_.ZH : Ljava/lang/String;
    //   4891: getstatic burp/Zxg7.Zy : Ljava/lang/Object;
    //   4894: checkcast java/math/BigInteger
    //   4897: invokevirtual intValue : ()I
    //   4900: bipush #32
    //   4902: irem
    //   4903: invokestatic abs : (I)I
    //   4906: invokevirtual charAt : (I)C
    //   4909: invokevirtual append : (C)Ljava/lang/StringBuilder;
    //   4912: pop
    //   4913: iload_2
    //   4914: ifeq -> 5956
    //   4917: goto -> 4924
    //   4920: invokestatic a : (Ljava/lang/Throwable;)Ljava/lang/Throwable;
    //   4923: athrow
    //   4924: aload_3
    //   4925: getstatic burp/Zlh8.ZY : Ljava/lang/String;
    //   4928: getstatic burp/Zsxh.Zk : Ljava/lang/Object;
    //   4931: checkcast java/math/BigInteger
    //   4934: invokevirtual intValue : ()I
    //   4937: bipush #32
    //   4939: irem
    //   4940: invokestatic abs : (I)I
    //   4943: invokevirtual charAt : (I)C
    //   4946: invokevirtual append : (C)Ljava/lang/StringBuilder;
    //   4949: pop
    //   4950: iload_2
    //   4951: ifeq -> 5956
    //   4954: goto -> 4961
    //   4957: invokestatic a : (Ljava/lang/Throwable;)Ljava/lang/Throwable;
    //   4960: athrow
    //   4961: aload_3
    //   4962: getstatic burp/Zzmu.ZF : Ljava/lang/String;
    //   4965: getstatic burp/Zix.ZO : Ljava/lang/Object;
    //   4968: checkcast java/math/BigInteger
    //   4971: invokevirtual intValue : ()I
    //   4974: bipush #32
    //   4976: irem
    //   4977: invokestatic abs : (I)I
    //   4980: invokevirtual charAt : (I)C
    //   4983: invokevirtual append : (C)Ljava/lang/StringBuilder;
    //   4986: pop
    //   4987: iload_2
    //   4988: ifeq -> 5956
    //   4991: goto -> 4998
    //   4994: invokestatic a : (Ljava/lang/Throwable;)Ljava/lang/Throwable;
    //   4997: athrow
    //   4998: aload_3
    //   4999: getstatic burp/Zkt7.ZM : Ljava/lang/String;
    //   5002: getstatic burp/Zm3p.Zz : Ljava/lang/Object;
    //   5005: checkcast java/math/BigInteger
    //   5008: invokevirtual intValue : ()I
    //   5011: bipush #32
    //   5013: irem
    //   5014: invokestatic abs : (I)I
    //   5017: invokevirtual charAt : (I)C
    //   5020: invokevirtual append : (C)Ljava/lang/StringBuilder;
    //   5023: pop
    //   5024: iload_2
    //   5025: ifeq -> 5956
    //   5028: goto -> 5035
    //   5031: invokestatic a : (Ljava/lang/Throwable;)Ljava/lang/Throwable;
    //   5034: athrow
    //   5035: aload_3
    //   5036: getstatic burp/Zltz.Za : Ljava/lang/String;
    //   5039: getstatic burp/Zb8y.ZI : Ljava/lang/Object;
    //   5042: checkcast java/math/BigInteger
    //   5045: invokevirtual intValue : ()I
    //   5048: bipush #32
    //   5050: irem
    //   5051: invokestatic abs : (I)I
    //   5054: invokevirtual charAt : (I)C
    //   5057: invokevirtual append : (C)Ljava/lang/StringBuilder;
    //   5060: pop
    //   5061: iload_2
    //   5062: ifeq -> 5956
    //   5065: goto -> 5072
    //   5068: invokestatic a : (Ljava/lang/Throwable;)Ljava/lang/Throwable;
    //   5071: athrow
    //   5072: aload_3
    //   5073: getstatic burp/Ze8m.Zx : Ljava/lang/String;
    //   5076: getstatic burp/Zm7x.Zv : Ljava/lang/Object;
    //   5079: checkcast java/math/BigInteger
    //   5082: invokevirtual intValue : ()I
    //   5085: bipush #32
    //   5087: irem
    //   5088: invokestatic abs : (I)I
    //   5091: invokevirtual charAt : (I)C
    //   5094: invokevirtual append : (C)Ljava/lang/StringBuilder;
    //   5097: pop
    //   5098: iload_2
    //   5099: ifeq -> 5956
    //   5102: goto -> 5109
    //   5105: invokestatic a : (Ljava/lang/Throwable;)Ljava/lang/Throwable;
    //   5108: athrow
    //   5109: aload_3
    //   5110: getstatic burp/Zess.Zc : Ljava/lang/String;
    //   5113: getstatic burp/Zkb_.ZG : Ljava/lang/Object;
    //   5116: checkcast java/math/BigInteger
    //   5119: invokevirtual intValue : ()I
    //   5122: bipush #32
    //   5124: irem
    //   5125: invokestatic abs : (I)I
    //   5128: invokevirtual charAt : (I)C
    //   5131: invokevirtual append : (C)Ljava/lang/StringBuilder;
    //   5134: pop
    //   5135: iload_2
    //   5136: ifeq -> 5956
    //   5139: goto -> 5146
    //   5142: invokestatic a : (Ljava/lang/Throwable;)Ljava/lang/Throwable;
    //   5145: athrow
    //   5146: aload_3
    //   5147: getstatic burp/Zt98.Zh : Ljava/lang/String;
    //   5150: getstatic burp/Ze_t.Za : Ljava/lang/Object;
    //   5153: checkcast java/math/BigInteger
    //   5156: invokevirtual intValue : ()I
    //   5159: bipush #32
    //   5161: irem
    //   5162: invokestatic abs : (I)I
    //   5165: invokevirtual charAt : (I)C
    //   5168: invokevirtual append : (C)Ljava/lang/StringBuilder;
    //   5171: pop
    //   5172: iload_2
    //   5173: ifeq -> 5956
    //   5176: goto -> 5183
    //   5179: invokestatic a : (Ljava/lang/Throwable;)Ljava/lang/Throwable;
    //   5182: athrow
    //   5183: aload_3
    //   5184: getstatic burp/Zkjr.Zg : Ljava/lang/String;
    //   5187: getstatic burp/Zkt7.ZY : Ljava/lang/Object;
    //   5190: checkcast java/math/BigInteger
    //   5193: invokevirtual intValue : ()I
    //   5196: bipush #32
    //   5198: irem
    //   5199: invokestatic abs : (I)I
    //   5202: invokevirtual charAt : (I)C
    //   5205: invokevirtual append : (C)Ljava/lang/StringBuilder;
    //   5208: pop
    //   5209: iload_2
    //   5210: ifeq -> 5956
    //   5213: goto -> 5220
    //   5216: invokestatic a : (Ljava/lang/Throwable;)Ljava/lang/Throwable;
    //   5219: athrow
    //   5220: aload_3
    //   5221: getstatic burp/Zstb.Zd : Ljava/lang/String;
    //   5224: getstatic burp/Zzyr.Za : Ljava/lang/Object;
    //   5227: checkcast java/math/BigInteger
    //   5230: invokevirtual intValue : ()I
    //   5233: bipush #32
    //   5235: irem
    //   5236: invokestatic abs : (I)I
    //   5239: invokevirtual charAt : (I)C
    //   5242: invokevirtual append : (C)Ljava/lang/StringBuilder;
    //   5245: pop
    //   5246: iload_2
    //   5247: ifeq -> 5956
    //   5250: goto -> 5257
    //   5253: invokestatic a : (Ljava/lang/Throwable;)Ljava/lang/Throwable;
    //   5256: athrow
    //   5257: aload_3
    //   5258: getstatic burp/Zzox.ZB : Ljava/lang/String;
    //   5261: getstatic burp/Zz2e.Zm : Ljava/lang/Object;
    //   5264: checkcast java/math/BigInteger
    //   5267: invokevirtual intValue : ()I
    //   5270: bipush #32
    //   5272: irem
    //   5273: invokestatic abs : (I)I
    //   5276: invokevirtual charAt : (I)C
    //   5279: invokevirtual append : (C)Ljava/lang/StringBuilder;
    //   5282: pop
    //   5283: iload_2
    //   5284: ifeq -> 5956
    //   5287: goto -> 5294
    //   5290: invokestatic a : (Ljava/lang/Throwable;)Ljava/lang/Throwable;
    //   5293: athrow
    //   5294: aload_3
    //   5295: getstatic burp/Zest.Zd : Ljava/lang/String;
    //   5298: getstatic burp/Zkc8.ZW : Ljava/lang/Object;
    //   5301: checkcast java/math/BigInteger
    //   5304: invokevirtual intValue : ()I
    //   5307: bipush #32
    //   5309: irem
    //   5310: invokestatic abs : (I)I
    //   5313: invokevirtual charAt : (I)C
    //   5316: invokevirtual append : (C)Ljava/lang/StringBuilder;
    //   5319: pop
    //   5320: iload_2
    //   5321: ifeq -> 5956
    //   5324: goto -> 5331
    //   5327: invokestatic a : (Ljava/lang/Throwable;)Ljava/lang/Throwable;
    //   5330: athrow
    //   5331: aload_3
    //   5332: getstatic burp/Zxzz.ZT : Ljava/lang/String;
    //   5335: getstatic burp/Zrof.ZB : Ljava/lang/Object;
    //   5338: checkcast java/math/BigInteger
    //   5341: invokevirtual intValue : ()I
    //   5344: bipush #32
    //   5346: irem
    //   5347: invokestatic abs : (I)I
    //   5350: invokevirtual charAt : (I)C
    //   5353: invokevirtual append : (C)Ljava/lang/StringBuilder;
    //   5356: pop
    //   5357: iload_2
    //   5358: ifeq -> 5956
    //   5361: goto -> 5368
    //   5364: invokestatic a : (Ljava/lang/Throwable;)Ljava/lang/Throwable;
    //   5367: athrow
    //   5368: aload_3
    //   5369: getstatic burp/Ztdd.ZA : Ljava/lang/String;
    //   5372: getstatic burp/Zk7f.Za : Ljava/lang/Object;
    //   5375: checkcast java/math/BigInteger
    //   5378: invokevirtual intValue : ()I
    //   5381: bipush #32
    //   5383: irem
    //   5384: invokestatic abs : (I)I
    //   5387: invokevirtual charAt : (I)C
    //   5390: invokevirtual append : (C)Ljava/lang/StringBuilder;
    //   5393: pop
    //   5394: iload_2
    //   5395: ifeq -> 5956
    //   5398: goto -> 5405
    //   5401: invokestatic a : (Ljava/lang/Throwable;)Ljava/lang/Throwable;
    //   5404: athrow
    //   5405: aload_3
    //   5406: getstatic burp/Zram.Ze : Ljava/lang/String;
    //   5409: getstatic burp/Zzox.Zq : Ljava/lang/Object;
    //   5412: checkcast java/math/BigInteger
    //   5415: invokevirtual intValue : ()I
    //   5418: bipush #32
    //   5420: irem
    //   5421: invokestatic abs : (I)I
    //   5424: invokevirtual charAt : (I)C
    //   5427: invokevirtual append : (C)Ljava/lang/StringBuilder;
    //   5430: pop
    //   5431: iload_2
    //   5432: ifeq -> 5956
    //   5435: goto -> 5442
    //   5438: invokestatic a : (Ljava/lang/Throwable;)Ljava/lang/Throwable;
    //   5441: athrow
    //   5442: aload_3
    //   5443: getstatic burp/Ze64.ZM : Ljava/lang/String;
    //   5446: getstatic burp/Zt3p.ZO : Ljava/lang/Object;
    //   5449: checkcast java/math/BigInteger
    //   5452: invokevirtual intValue : ()I
    //   5455: bipush #32
    //   5457: irem
    //   5458: invokestatic abs : (I)I
    //   5461: invokevirtual charAt : (I)C
    //   5464: invokevirtual append : (C)Ljava/lang/StringBuilder;
    //   5467: pop
    //   5468: iload_2
    //   5469: ifeq -> 5956
    //   5472: goto -> 5479
    //   5475: invokestatic a : (Ljava/lang/Throwable;)Ljava/lang/Throwable;
    //   5478: athrow
    //   5479: aload_3
    //   5480: getstatic burp/Zlx5.ZP : Ljava/lang/String;
    //   5483: getstatic burp/Zltz.Zg : Ljava/lang/Object;
    //   5486: checkcast java/math/BigInteger
    //   5489: invokevirtual intValue : ()I
    //   5492: bipush #32
    //   5494: irem
    //   5495: invokestatic abs : (I)I
    //   5498: invokevirtual charAt : (I)C
    //   5501: invokevirtual append : (C)Ljava/lang/StringBuilder;
    //   5504: pop
    //   5505: iload_2
    //   5506: ifeq -> 5956
    //   5509: goto -> 5516
    //   5512: invokestatic a : (Ljava/lang/Throwable;)Ljava/lang/Throwable;
    //   5515: athrow
    //   5516: aload_3
    //   5517: getstatic burp/Zb4a.Zi : Ljava/lang/String;
    //   5520: getstatic burp/Zlo5.Zf : Ljava/lang/Object;
    //   5523: checkcast java/math/BigInteger
    //   5526: invokevirtual intValue : ()I
    //   5529: bipush #32
    //   5531: irem
    //   5532: invokestatic abs : (I)I
    //   5535: invokevirtual charAt : (I)C
    //   5538: invokevirtual append : (C)Ljava/lang/StringBuilder;
    //   5541: pop
    //   5542: iload_2
    //   5543: ifeq -> 5956
    //   5546: goto -> 5553
    //   5549: invokestatic a : (Ljava/lang/Throwable;)Ljava/lang/Throwable;
    //   5552: athrow
    //   5553: aload_3
    //   5554: getstatic burp/Zg4d.ZE : Ljava/lang/String;
    //   5557: getstatic burp/Zxo7.Zi : Ljava/lang/Object;
    //   5560: checkcast java/math/BigInteger
    //   5563: invokevirtual intValue : ()I
    //   5566: bipush #32
    //   5568: irem
    //   5569: invokestatic abs : (I)I
    //   5572: invokevirtual charAt : (I)C
    //   5575: invokevirtual append : (C)Ljava/lang/StringBuilder;
    //   5578: pop
    //   5579: iload_2
    //   5580: ifeq -> 5956
    //   5583: goto -> 5590
    //   5586: invokestatic a : (Ljava/lang/Throwable;)Ljava/lang/Throwable;
    //   5589: athrow
    //   5590: aload_3
    //   5591: getstatic burp/Ze8i.ZM : Ljava/lang/String;
    //   5594: getstatic burp/Zke7.Zj : Ljava/lang/Object;
    //   5597: checkcast java/math/BigInteger
    //   5600: invokevirtual intValue : ()I
    //   5603: bipush #32
    //   5605: irem
    //   5606: invokestatic abs : (I)I
    //   5609: invokevirtual charAt : (I)C
    //   5612: invokevirtual append : (C)Ljava/lang/StringBuilder;
    //   5615: pop
    //   5616: iload_2
    //   5617: ifeq -> 5956
    //   5620: goto -> 5627
    //   5623: invokestatic a : (Ljava/lang/Throwable;)Ljava/lang/Throwable;
    //   5626: athrow
    //   5627: aload_3
    //   5628: getstatic burp/Ze5t.ZX : Ljava/lang/String;
    //   5631: getstatic burp/Zkm0.ZI : Ljava/lang/Object;
    //   5634: checkcast java/math/BigInteger
    //   5637: invokevirtual intValue : ()I
    //   5640: bipush #32
    //   5642: irem
    //   5643: invokestatic abs : (I)I
    //   5646: invokevirtual charAt : (I)C
    //   5649: invokevirtual append : (C)Ljava/lang/StringBuilder;
    //   5652: pop
    //   5653: iload_2
    //   5654: ifeq -> 5956
    //   5657: goto -> 5664
    //   5660: invokestatic a : (Ljava/lang/Throwable;)Ljava/lang/Throwable;
    //   5663: athrow
    //   5664: aload_3
    //   5665: getstatic burp/Zs83.ZG : Ljava/lang/String;
    //   5668: getstatic burp/Zzyr.Za : Ljava/lang/Object;
    //   5671: checkcast java/math/BigInteger
    //   5674: invokevirtual intValue : ()I
    //   5677: bipush #32
    //   5679: irem
    //   5680: invokestatic abs : (I)I
    //   5683: invokevirtual charAt : (I)C
    //   5686: invokevirtual append : (C)Ljava/lang/StringBuilder;
    //   5689: pop
    //   5690: iload_2
    //   5691: ifeq -> 5956
    //   5694: goto -> 5701
    //   5697: invokestatic a : (Ljava/lang/Throwable;)Ljava/lang/Throwable;
    //   5700: athrow
    //   5701: aload_3
    //   5702: getstatic burp/Zb.Zt : Ljava/lang/String;
    //   5705: getstatic burp/Zxjk.Zk : Ljava/lang/Object;
    //   5708: checkcast java/math/BigInteger
    //   5711: invokevirtual intValue : ()I
    //   5714: bipush #32
    //   5716: irem
    //   5717: invokestatic abs : (I)I
    //   5720: invokevirtual charAt : (I)C
    //   5723: invokevirtual append : (C)Ljava/lang/StringBuilder;
    //   5726: pop
    //   5727: iload_2
    //   5728: ifeq -> 5956
    //   5731: goto -> 5738
    //   5734: invokestatic a : (Ljava/lang/Throwable;)Ljava/lang/Throwable;
    //   5737: athrow
    //   5738: aload_3
    //   5739: getstatic burp/Zt3f.ZU : Ljava/lang/String;
    //   5742: getstatic burp/Zrjg.ZG : Ljava/lang/Object;
    //   5745: checkcast java/math/BigInteger
    //   5748: invokevirtual intValue : ()I
    //   5751: bipush #32
    //   5753: irem
    //   5754: invokestatic abs : (I)I
    //   5757: invokevirtual charAt : (I)C
    //   5760: invokevirtual append : (C)Ljava/lang/StringBuilder;
    //   5763: pop
    //   5764: iload_2
    //   5765: ifeq -> 5956
    //   5768: goto -> 5775
    //   5771: invokestatic a : (Ljava/lang/Throwable;)Ljava/lang/Throwable;
    //   5774: athrow
    //   5775: aload_3
    //   5776: getstatic burp/Zm52.Ze : Ljava/lang/String;
    //   5779: getstatic burp/Zb8y.ZI : Ljava/lang/Object;
    //   5782: checkcast java/math/BigInteger
    //   5785: invokevirtual intValue : ()I
    //   5788: bipush #32
    //   5790: irem
    //   5791: invokestatic abs : (I)I
    //   5794: invokevirtual charAt : (I)C
    //   5797: invokevirtual append : (C)Ljava/lang/StringBuilder;
    //   5800: pop
    //   5801: iload_2
    //   5802: ifeq -> 5956
    //   5805: goto -> 5812
    //   5808: invokestatic a : (Ljava/lang/Throwable;)Ljava/lang/Throwable;
    //   5811: athrow
    //   5812: aload_3
    //   5813: getstatic burp/Ze5f.Zt : Ljava/lang/String;
    //   5816: getstatic burp/Zxn5.Zd : Ljava/lang/Object;
    //   5819: checkcast java/math/BigInteger
    //   5822: invokevirtual intValue : ()I
    //   5825: bipush #32
    //   5827: irem
    //   5828: invokestatic abs : (I)I
    //   5831: invokevirtual charAt : (I)C
    //   5834: invokevirtual append : (C)Ljava/lang/StringBuilder;
    //   5837: pop
    //   5838: iload_2
    //   5839: ifeq -> 5956
    //   5842: goto -> 5849
    //   5845: invokestatic a : (Ljava/lang/Throwable;)Ljava/lang/Throwable;
    //   5848: athrow
    //   5849: aload_3
    //   5850: getstatic burp/Ze69.ZA : Ljava/lang/String;
    //   5853: getstatic burp/Ze5f.Zh : Ljava/lang/Object;
    //   5856: checkcast java/math/BigInteger
    //   5859: invokevirtual intValue : ()I
    //   5862: bipush #32
    //   5864: irem
    //   5865: invokestatic abs : (I)I
    //   5868: invokevirtual charAt : (I)C
    //   5871: invokevirtual append : (C)Ljava/lang/StringBuilder;
    //   5874: pop
    //   5875: iload_2
    //   5876: ifeq -> 5956
    //   5879: goto -> 5886
    //   5882: invokestatic a : (Ljava/lang/Throwable;)Ljava/lang/Throwable;
    //   5885: athrow
    //   5886: aload_3
    //   5887: getstatic burp/Ztye.ZR : Ljava/lang/String;
    //   5890: getstatic burp/Zs_3.ZZ : Ljava/lang/Object;
    //   5893: checkcast java/math/BigInteger
    //   5896: invokevirtual intValue : ()I
    //   5899: bipush #32
    //   5901: irem
    //   5902: invokestatic abs : (I)I
    //   5905: invokevirtual charAt : (I)C
    //   5908: invokevirtual append : (C)Ljava/lang/StringBuilder;
    //   5911: pop
    //   5912: iload_2
    //   5913: ifeq -> 5956
    //   5916: goto -> 5923
    //   5919: invokestatic a : (Ljava/lang/Throwable;)Ljava/lang/Throwable;
    //   5922: athrow
    //   5923: aload_3
    //   5924: getstatic burp/Zb4a.Zi : Ljava/lang/String;
    //   5927: getstatic burp/Zxe.Zg : Ljava/lang/Object;
    //   5930: checkcast java/math/BigInteger
    //   5933: invokevirtual intValue : ()I
    //   5936: bipush #32
    //   5938: irem
    //   5939: invokestatic abs : (I)I
    //   5942: invokevirtual charAt : (I)C
    //   5945: invokevirtual append : (C)Ljava/lang/StringBuilder;
    //   5948: pop
    //   5949: goto -> 5956
    //   5952: invokestatic a : (Ljava/lang/Throwable;)Ljava/lang/Throwable;
    //   5955: athrow
    //   5956: iinc #4, 1
    //   5959: iload_2
    //   5960: ifeq -> 4624
    //   5963: aload_3
    //   5964: invokevirtual toString : ()Ljava/lang/String;
    //   5967: putstatic burp/Zkjr.Zg : Ljava/lang/String;
    //   5970: sipush #32247
    //   5973: sipush #30740
    //   5976: invokestatic a : (II)Ljava/lang/String;
    //   5979: iconst_1
    //   5980: ldc burp/Zgcg
    //   5982: invokevirtual getClassLoader : ()Ljava/lang/ClassLoader;
    //   5985: invokestatic forName : (Ljava/lang/String;ZLjava/lang/ClassLoader;)Ljava/lang/Class;
    //   5988: invokevirtual getDeclaredFields : ()[Ljava/lang/reflect/Field;
    //   5991: astore #4
    //   5993: aload #4
    //   5995: arraylength
    //   5996: istore #5
    //   5998: iconst_0
    //   5999: istore #6
    //   6001: iload #6
    //   6003: iload #5
    //   6005: if_icmpge -> 6143
    //   6008: aload #4
    //   6010: iload #6
    //   6012: aaload
    //   6013: astore #7
    //   6015: aload #7
    //   6017: invokevirtual getModifiers : ()I
    //   6020: invokestatic isStatic : (I)Z
    //   6023: ifne -> 6033
    //   6026: goto -> 6136
    //   6029: invokestatic a : (Ljava/lang/Throwable;)Ljava/lang/Throwable;
    //   6032: athrow
    //   6033: aload #7
    //   6035: invokevirtual getType : ()Ljava/lang/Class;
    //   6038: astore #8
    //   6040: aload #8
    //   6042: ifnull -> 6123
    //   6045: aload #8
    //   6047: invokevirtual isPrimitive : ()Z
    //   6050: ifne -> 6123
    //   6053: goto -> 6060
    //   6056: invokestatic a : (Ljava/lang/Throwable;)Ljava/lang/Throwable;
    //   6059: athrow
    //   6060: aload #8
    //   6062: invokevirtual getPackage : ()Ljava/lang/Package;
    //   6065: ifnull -> 6123
    //   6068: goto -> 6075
    //   6071: invokestatic a : (Ljava/lang/Throwable;)Ljava/lang/Throwable;
    //   6074: athrow
    //   6075: aload #8
    //   6077: invokevirtual getPackage : ()Ljava/lang/Package;
    //   6080: invokevirtual getName : ()Ljava/lang/String;
    //   6083: ifnull -> 6123
    //   6086: goto -> 6093
    //   6089: invokestatic a : (Ljava/lang/Throwable;)Ljava/lang/Throwable;
    //   6092: athrow
    //   6093: aload #8
    //   6095: invokevirtual getPackage : ()Ljava/lang/Package;
    //   6098: invokevirtual getName : ()Ljava/lang/String;
    //   6101: sipush #32243
    //   6104: sipush #22439
    //   6107: invokestatic a : (II)Ljava/lang/String;
    //   6110: invokevirtual startsWith : (Ljava/lang/String;)Z
    //   6113: ifne -> 6123
    //   6116: goto -> 6123
    //   6119: invokestatic a : (Ljava/lang/Throwable;)Ljava/lang/Throwable;
    //   6122: athrow
    //   6123: aload #7
    //   6125: iconst_1
    //   6126: invokevirtual setAccessible : (Z)V
    //   6129: aload #7
    //   6131: aconst_null
    //   6132: invokevirtual get : (Ljava/lang/Object;)Ljava/lang/Object;
    //   6135: pop
    //   6136: iinc #6, 1
    //   6139: iload_2
    //   6140: ifeq -> 6001
    //   6143: sipush #32241
    //   6146: sipush #-23720
    //   6149: invokestatic a : (II)Ljava/lang/String;
    //   6152: invokestatic forName : (Ljava/lang/String;)Ljava/lang/Class;
    //   6155: invokevirtual getDeclaredMethods : ()[Ljava/lang/reflect/Method;
    //   6158: astore #4
    //   6160: aload #4
    //   6162: arraylength
    //   6163: istore #5
    //   6165: iconst_0
    //   6166: istore #6
    //   6168: iload #6
    //   6170: iload #5
    //   6172: if_icmpge -> 6305
    //   6175: aload #4
    //   6177: iload #6
    //   6179: aaload
    //   6180: astore #7
    //   6182: aload #7
    //   6184: invokevirtual getParameterTypes : ()[Ljava/lang/Class;
    //   6187: pop
    //   6188: aload #7
    //   6190: invokevirtual getModifiers : ()I
    //   6193: invokestatic isStatic : (I)Z
    //   6196: ifeq -> 6291
    //   6199: aload #7
    //   6201: invokevirtual getParameterTypes : ()[Ljava/lang/Class;
    //   6204: arraylength
    //   6205: iconst_2
    //   6206: if_icmpne -> 6291
    //   6209: goto -> 6216
    //   6212: invokestatic a : (Ljava/lang/Throwable;)Ljava/lang/Throwable;
    //   6215: athrow
    //   6216: aload #7
    //   6218: invokevirtual getReturnType : ()Ljava/lang/Class;
    //   6221: getstatic java/lang/Void.TYPE : Ljava/lang/Class;
    //   6224: invokevirtual equals : (Ljava/lang/Object;)Z
    //   6227: ifeq -> 6291
    //   6230: goto -> 6237
    //   6233: invokestatic a : (Ljava/lang/Throwable;)Ljava/lang/Throwable;
    //   6236: athrow
    //   6237: aload #7
    //   6239: iconst_1
    //   6240: invokevirtual setAccessible : (Z)V
    //   6243: aload #7
    //   6245: aconst_null
    //   6246: iconst_2
    //   6247: anewarray java/lang/Object
    //   6250: dup
    //   6251: iconst_0
    //   6252: aload_0
    //   6253: aastore
    //   6254: dup
    //   6255: iconst_1
    //   6256: aload_1
    //   6257: ifnonnull -> 6275
    //   6260: goto -> 6267
    //   6263: invokestatic a : (Ljava/lang/Throwable;)Ljava/lang/Throwable;
    //   6266: athrow
    //   6267: aload_1
    //   6268: goto -> 6282
    //   6271: invokestatic a : (Ljava/lang/Throwable;)Ljava/lang/Throwable;
    //   6274: athrow
    //   6275: aload_1
    //   6276: checkcast [B
    //   6279: invokevirtual clone : ()Ljava/lang/Object;
    //   6282: aastore
    //   6283: invokevirtual invoke : (Ljava/lang/Object;[Ljava/lang/Object;)Ljava/lang/Object;
    //   6286: pop
    //   6287: iload_2
    //   6288: ifeq -> 6305
    //   6291: iinc #6, 1
    //   6294: iload_2
    //   6295: ifeq -> 6168
    //   6298: goto -> 6305
    //   6301: invokestatic a : (Ljava/lang/Throwable;)Ljava/lang/Throwable;
    //   6304: athrow
    //   6305: getstatic burp/Zt3p.ZD : Ljava/lang/String;
    //   6308: getstatic burp/Zmr7.ZO : Ljava/lang/Object;
    //   6311: checkcast java/math/BigInteger
    //   6314: invokevirtual intValue : ()I
    //   6317: bipush #32
    //   6319: irem
    //   6320: invokestatic abs : (I)I
    //   6323: invokevirtual charAt : (I)C
    //   6326: getstatic burp/Zel.Zi : Ljava/lang/String;
    //   6329: getstatic burp/Ze54.Zx : Ljava/lang/Object;
    //   6332: checkcast java/math/BigInteger
    //   6335: invokevirtual intValue : ()I
    //   6338: bipush #32
    //   6340: irem
    //   6341: invokestatic abs : (I)I
    //   6344: invokevirtual charAt : (I)C
    //   6347: if_icmpgt -> 6454
    //   6350: getstatic burp/Zlpj.Zj : Ljava/lang/String;
    //   6353: getstatic burp/Zzyr.Za : Ljava/lang/Object;
    //   6356: checkcast java/math/BigInteger
    //   6359: invokevirtual intValue : ()I
    //   6362: bipush #32
    //   6364: irem
    //   6365: invokestatic abs : (I)I
    //   6368: invokevirtual charAt : (I)C
    //   6371: getstatic burp/Zz6t.Zx : Ljava/lang/String;
    //   6374: getstatic burp/Zlpj.Zc : Ljava/lang/Object;
    //   6377: checkcast java/math/BigInteger
    //   6380: invokevirtual intValue : ()I
    //   6383: bipush #32
    //   6385: irem
    //   6386: invokestatic abs : (I)I
    //   6389: invokevirtual charAt : (I)C
    //   6392: if_icmpgt -> 6454
    //   6395: goto -> 6402
    //   6398: invokestatic a : (Ljava/lang/Throwable;)Ljava/lang/Throwable;
    //   6401: athrow
    //   6402: getstatic burp/Zlf0.ZS : Ljava/lang/String;
    //   6405: getstatic burp/Zk7e.ZW : Ljava/lang/Object;
    //   6408: checkcast java/math/BigInteger
    //   6411: invokevirtual intValue : ()I
    //   6414: bipush #32
    //   6416: irem
    //   6417: invokestatic abs : (I)I
    //   6420: invokevirtual charAt : (I)C
    //   6423: getstatic burp/Zg4w.ZC : Ljava/lang/String;
    //   6426: getstatic burp/Zqp.ZA : Ljava/lang/Object;
    //   6429: checkcast java/math/BigInteger
    //   6432: invokevirtual intValue : ()I
    //   6435: bipush #32
    //   6437: irem
    //   6438: invokestatic abs : (I)I
    //   6441: invokevirtual charAt : (I)C
    //   6444: if_icmple -> 6462
    //   6447: goto -> 6454
    //   6450: invokestatic a : (Ljava/lang/Throwable;)Ljava/lang/Throwable;
    //   6453: athrow
    //   6454: iconst_1
    //   6455: goto -> 6463
    //   6458: invokestatic a : (Ljava/lang/Throwable;)Ljava/lang/Throwable;
    //   6461: athrow
    //   6462: iconst_0
    //   6463: ireturn
    //   6464: astore_3
    //   6465: new java/lang/Exception
    //   6468: dup
    //   6469: aload_3
    //   6470: invokevirtual getMessage : ()Ljava/lang/String;
    //   6473: invokespecial <init> : (Ljava/lang/String;)V
    //   6476: athrow
    // Exception table:
    //   from	to	target	type
    //   4	6463	6464	java/lang/Throwable
    //   3306	3331	3331	java/lang/Throwable
    //   4294	4320	4320	java/lang/Throwable
    //   4631	4806	4809	java/lang/Throwable
    //   4776	4843	4846	java/lang/Throwable
    //   4813	4880	4883	java/lang/Throwable
    //   4850	4917	4920	java/lang/Throwable
    //   4887	4954	4957	java/lang/Throwable
    //   4924	4991	4994	java/lang/Throwable
    //   4961	5028	5031	java/lang/Throwable
    //   4998	5065	5068	java/lang/Throwable
    //   5035	5102	5105	java/lang/Throwable
    //   5072	5139	5142	java/lang/Throwable
    //   5109	5176	5179	java/lang/Throwable
    //   5146	5213	5216	java/lang/Throwable
    //   5183	5250	5253	java/lang/Throwable
    //   5220	5287	5290	java/lang/Throwable
    //   5257	5324	5327	java/lang/Throwable
    //   5294	5361	5364	java/lang/Throwable
    //   5331	5398	5401	java/lang/Throwable
    //   5368	5435	5438	java/lang/Throwable
    //   5405	5472	5475	java/lang/Throwable
    //   5442	5509	5512	java/lang/Throwable
    //   5479	5546	5549	java/lang/Throwable
    //   5516	5583	5586	java/lang/Throwable
    //   5553	5620	5623	java/lang/Throwable
    //   5590	5657	5660	java/lang/Throwable
    //   5627	5694	5697	java/lang/Throwable
    //   5664	5731	5734	java/lang/Throwable
    //   5701	5768	5771	java/lang/Throwable
    //   5738	5805	5808	java/lang/Throwable
    //   5775	5842	5845	java/lang/Throwable
    //   5812	5879	5882	java/lang/Throwable
    //   5849	5916	5919	java/lang/Throwable
    //   5886	5949	5952	java/lang/Throwable
    //   6015	6029	6029	java/lang/Throwable
    //   6040	6053	6056	java/lang/Throwable
    //   6045	6068	6071	java/lang/Throwable
    //   6060	6086	6089	java/lang/Throwable
    //   6075	6116	6119	java/lang/Throwable
    //   6182	6209	6212	java/lang/Throwable
    //   6199	6230	6233	java/lang/Throwable
    //   6216	6260	6263	java/lang/Throwable
    //   6237	6271	6271	java/lang/Throwable
    //   6282	6298	6301	java/lang/Throwable
    //   6305	6395	6398	java/lang/Throwable
    //   6350	6447	6450	java/lang/Throwable
    //   6402	6458	6458	java/lang/Throwable
  }
  
  static void ZS(Object paramObject) {
    Ze8m.Zx = a(32240, -28733);
    Ze8m.Zm = new BigInteger(a(32255, 7307));
    boolean bool = Zt2e.ZN();
    try {
      try {
        if (Zef0.ZR.charAt(Math.abs(((BigInteger)Zr48.ZZ).intValue() % 32)) > Zs83.ZG.charAt(Math.abs(((BigInteger)Zlpj.Zc).intValue() % 32))) {
          try {
            Ztzj.Zy(Class.forName(a(32252, -1874)));
            if (!bool)
              Zzmw.ZB(Class.forName(a(32245, -13581))); 
          } catch (Throwable throwable) {
            throw a(null);
          } 
          return;
        } 
      } catch (Throwable throwable) {
        throw a(null);
      } 
      Zzmw.ZB(Class.forName(a(32245, -13581)));
    } catch (Throwable throwable) {}
  }
  
  static void Zw(Object[] paramArrayOfObject, Object paramObject) throws Throwable {}
  
  static {
    // Byte code:
    //   0: bipush #11
    //   2: anewarray java/lang/String
    //   5: astore #5
    //   7: iconst_0
    //   8: istore_3
    //   9: ldc '>t] nL,? ;_)\\tvP\\r5\\rH=M"f69\\t\\ru?KQ1QdM.1rR)&a{\\n]Jn_D[qF?.8!$yz2Ei< =CxN@V>N@G %\\tG;vx\\bsJyagD\\fST'
    //   11: dup
    //   12: astore_2
    //   13: invokevirtual length : ()I
    //   16: istore #4
    //   18: bipush #32
    //   20: istore_1
    //   21: iconst_m1
    //   22: istore_0
    //   23: bipush #35
    //   25: iinc #0, 1
    //   28: aload_2
    //   29: iload_0
    //   30: dup
    //   31: iload_1
    //   32: iadd
    //   33: invokevirtual substring : (II)Ljava/lang/String;
    //   36: iconst_m1
    //   37: goto -> 143
    //   40: aload #5
    //   42: swap
    //   43: iload_3
    //   44: iinc #3, 1
    //   47: swap
    //   48: aastore
    //   49: iload_0
    //   50: iload_1
    //   51: iadd
    //   52: dup
    //   53: istore_0
    //   54: iload #4
    //   56: if_icmpge -> 68
    //   59: aload_2
    //   60: iload_0
    //   61: invokevirtual charAt : (I)C
    //   64: istore_1
    //   65: goto -> 23
    //   68: ldc 'v+yk@1r\\r\nv(SW _zSm;0dq.6}Hh$1X);jt\\ttZ6'
    //   70: dup
    //   71: astore_2
    //   72: invokevirtual length : ()I
    //   75: istore #4
    //   77: bipush #75
    //   79: istore_1
    //   80: iconst_m1
    //   81: istore_0
    //   82: bipush #21
    //   84: iinc #0, 1
    //   87: aload_2
    //   88: iload_0
    //   89: dup
    //   90: iload_1
    //   91: iadd
    //   92: invokevirtual substring : (II)Ljava/lang/String;
    //   95: iconst_0
    //   96: goto -> 143
    //   99: aload #5
    //   101: swap
    //   102: iload_3
    //   103: iinc #3, 1
    //   106: swap
    //   107: aastore
    //   108: iload_0
    //   109: iload_1
    //   110: iadd
    //   111: dup
    //   112: istore_0
    //   113: iload #4
    //   115: if_icmpge -> 127
    //   118: aload_2
    //   119: iload_0
    //   120: invokevirtual charAt : (I)C
    //   123: istore_1
    //   124: goto -> 82
    //   127: aload #5
    //   129: putstatic burp/Zrtc.a : [Ljava/lang/String;
    //   132: bipush #11
    //   134: anewarray java/lang/String
    //   137: putstatic burp/Zrtc.b : [Ljava/lang/String;
    //   140: goto -> 300
    //   143: dup_x2
    //   144: pop
    //   145: invokevirtual toCharArray : ()[C
    //   148: dup_x1
    //   149: arraylength
    //   150: dup_x2
    //   151: pop
    //   152: iconst_0
    //   153: istore #6
    //   155: dup2_x1
    //   156: pop2
    //   157: dup_x2
    //   158: iconst_1
    //   159: if_icmpgt -> 260
    //   162: dup2
    //   163: swap
    //   164: iload #6
    //   166: dup2_x1
    //   167: caload
    //   168: swap
    //   169: iload #6
    //   171: bipush #7
    //   173: irem
    //   174: tableswitch default -> 242, 0 -> 212, 1 -> 217, 2 -> 222, 3 -> 227, 4 -> 232, 5 -> 237
    //   212: bipush #31
    //   214: goto -> 244
    //   217: bipush #9
    //   219: goto -> 244
    //   222: bipush #102
    //   224: goto -> 244
    //   227: bipush #40
    //   229: goto -> 244
    //   232: bipush #47
    //   234: goto -> 244
    //   237: bipush #62
    //   239: goto -> 244
    //   242: bipush #65
    //   244: ixor
    //   245: ixor
    //   246: i2c
    //   247: castore
    //   248: iinc #6, 1
    //   251: dup
    //   252: ifne -> 260
    //   255: dup2
    //   256: dup_x1
    //   257: goto -> 166
    //   260: dup2_x1
    //   261: pop2
    //   262: dup_x2
    //   263: iload #6
    //   265: if_icmpgt -> 162
    //   268: pop
    //   269: new java/lang/String
    //   272: dup_x1
    //   273: swap
    //   274: invokespecial <init> : ([C)V
    //   277: invokevirtual intern : ()Ljava/lang/String;
    //   280: swap
    //   281: pop
    //   282: swap
    //   283: tableswitch default -> 40, 0 -> 99
    //   300: new java/math/BigInteger
    //   303: dup
    //   304: sipush #32242
    //   307: sipush #21723
    //   310: invokestatic a : (II)Ljava/lang/String;
    //   313: invokespecial <init> : (Ljava/lang/String;)V
    //   316: putstatic burp/Zrtc.Zr : Ljava/lang/Object;
    //   319: sipush #32246
    //   322: sipush #27871
    //   325: invokestatic a : (II)Ljava/lang/String;
    //   328: putstatic burp/Zrtc.Zl : Ljava/lang/String;
    //   331: return
  }
  
  private static Throwable a(Throwable paramThrowable) {
    return paramThrowable;
  }
  
  private static String a(int paramInt1, int paramInt2) {
    int i = (paramInt1 ^ 0x7DF6) & 0xFFFF;
    if (b[i] == null) {
      char[] arrayOfChar = a[i].toCharArray();
      switch (arrayOfChar[0] & 0xFF) {
        case 0:
        
        case 1:
        
        case 2:
        
        case 3:
        
        case 4:
        
        case 5:
        
        case 6:
        
        case 7:
        
        case 8:
        
        case 9:
        
        case 10:
        
        case 11:
        
        case 12:
        
        case 13:
        
        case 14:
        
        case 15:
        
        case 16:
        
        case 17:
        
        case 18:
        
        case 19:
        
        case 20:
        
        case 21:
        
        case 22:
        
        case 23:
        
        case 24:
        
        case 25:
        
        case 26:
        
        case 27:
        
        case 28:
        
        case 29:
        
        case 30:
        
        case 31:
        
        case 32:
        
        case 33:
        
        case 34:
        
        case 35:
        
        case 36:
        
        case 37:
        
        case 38:
        
        case 39:
        
        case 40:
        
        case 41:
        
        case 42:
        
        case 43:
        
        case 44:
        
        case 45:
        
        case 46:
        
        case 47:
        
        case 48:
        
        case 49:
        
        case 50:
        
        case 51:
        
        case 52:
        
        case 53:
        
        case 54:
        
        case 55:
        
        case 56:
        
        case 57:
        
        case 58:
        
        case 59:
        
        case 60:
        
        case 61:
        
        case 62:
        
        case 63:
        
        case 64:
        
        case 65:
        
        case 66:
        
        case 67:
        
        case 68:
        
        case 69:
        
        case 70:
        
        case 71:
        
        case 72:
        
        case 73:
        
        case 74:
        
        case 75:
        
        case 76:
        
        case 77:
        
        case 78:
        
        case 79:
        
        case 80:
        
        case 81:
        
        case 82:
        
        case 83:
        
        case 84:
        
        case 85:
        
        case 86:
        
        case 87:
        
        case 88:
        
        case 89:
        
        case 90:
        
        case 91:
        
        case 92:
        
        case 93:
        
        case 94:
        
        case 95:
        
        case 96:
        
        case 97:
        
        case 98:
        
        case 99:
        
        case 100:
        
        case 101:
        
        case 102:
        
        case 103:
        
        case 104:
        
        case 105:
        
        case 106:
        
        case 107:
        
        case 108:
        
        case 109:
        
        case 110:
        
        case 111:
        
        case 112:
        
        case 113:
        
        case 114:
        
        case 115:
        
        case 116:
        
        case 117:
        
        case 118:
        
        case 119:
        
        case 120:
        
        case 121:
        
        case 122:
        
        case 123:
        
        case 124:
        
        case 125:
        
        case 126:
        
        case 127:
        
        case 128:
        
        case 129:
        
        case 130:
        
        case 131:
        
        case 132:
        
        case 133:
        
        case 134:
        
        case 135:
        
        case 136:
        
        case 137:
        
        case 138:
        
        case 139:
        
        case 140:
        
        case 141:
        
        case 142:
        
        case 143:
        
        case 144:
        
        case 145:
        
        case 146:
        
        case 147:
        
        case 148:
        
        case 149:
        
        case 150:
        
        case 151:
        
        case 152:
        
        case 153:
        
        case 154:
        
        case 155:
        
        case 156:
        
        case 157:
        
        case 158:
        
        case 159:
        
        case 160:
        
        case 161:
        
        case 162:
        
        case 163:
        
        case 164:
        
        case 165:
        
        case 166:
        
        case 167:
        
        case 168:
        
        case 169:
        
        case 170:
        
        case 171:
        
        case 172:
        
        case 173:
        
        case 174:
        
        case 175:
        
        case 176:
        
        case 177:
        
        case 178:
        
        case 179:
        
        case 180:
        
        case 181:
        
        case 182:
        
        case 183:
        
        case 184:
        
        case 185:
        
        case 186:
        
        case 187:
        
        case 188:
        
        case 189:
        
        case 190:
        
        case 191:
        
        case 192:
        
        case 193:
        
        case 194:
        
        case 195:
        
        case 196:
        
        case 197:
        
        case 198:
        
        case 199:
        
        case 200:
        
        case 201:
        
        case 202:
        
        case 203:
        
        case 204:
        
        case 205:
        
        case 206:
        
        case 207:
        
        case 208:
        
        case 209:
        
        case 210:
        
        case 211:
        
        case 212:
        
        case 213:
        
        case 214:
        
        case 215:
        
        case 216:
        
        case 217:
        
        case 218:
        
        case 219:
        
        case 220:
        
        case 221:
        
        case 222:
        
        case 223:
        
        case 224:
        
        case 225:
        
        case 226:
        
        case 227:
        
        case 228:
        
        case 229:
        
        case 230:
        
        case 231:
        
        case 232:
        
        case 233:
        
        case 234:
        
        case 235:
        
        case 236:
        
        case 237:
        
        case 238:
        
        case 239:
        
        case 240:
        
        case 241:
        
        case 242:
        
        case 243:
        
        case 244:
        
        case 245:
        
        case 246:
        
        case 247:
        
        case 248:
        
        case 249:
        
        case 250:
        
        case 251:
        
        case 252:
        
        case 253:
        
        case 254:
        
        default:
          break;
      } 
      char c = '';
      int j = (paramInt2 & 0xFF) - c;
      if (j < 0)
        j += 256; 
      int k = ((paramInt2 & 0xFFFF) >>> 8) - c;
      if (k < 0)
        k += 256; 
      for (byte b = 0; b < arrayOfChar.length; b++) {
        int m = b % 2;
        if (m == 0) {
          arrayOfChar[b] = (char)(arrayOfChar[b] ^ j);
          j = ((j >>> 3 | j << 5) ^ arrayOfChar[b]) & 0xFF;
        } else {
          arrayOfChar[b] = (char)(arrayOfChar[b] ^ k);
          k = ((k >>> 3 | k << 5) ^ arrayOfChar[b]) & 0xFF;
        } 
      } 
      b[i] = (new String(arrayOfChar)).intern();
    } 
    return b[i];
  }
}


/* Location:              C:\Program Files\BurpSuitePro\burpsuite_pro.jar!\burp\Zrtc.class
 * Java compiler version: 21 (65.0)
 * JD-Core Version:       1.1.3
 */