package burp;

import java.math.BigInteger;

class Zrvb extends ClassLoader {
  static Object ZD;
  
  static String ZU;
  
  private static final String[] a;
  
  private static final String[] b;
  
  static void Zf(Object[] paramArrayOfObject, Object paramObject) throws Throwable {}
  
  static void ZH(Object paramObject) {
    Zzv.Zy = a(-15412, -32197);
    Zzv.Zu = new BigInteger(a(-15393, 18967));
    boolean bool = Zt2e.ZK();
    try {
      try {
        if (Zg97.ZX.charAt(Math.abs(((BigInteger)Zzc7.ZG).intValue() % 32)) <= Zg97.ZX.charAt(Math.abs(((BigInteger)Zxrd.ZL).intValue() % 32))) {
          try {
            Zlno.ZF(Class.forName(a(-15395, -17212)));
            if (bool)
              Zg_i.Zc(Class.forName(a(-15411, 906))); 
          } catch (Throwable throwable) {
            throw a(null);
          } 
          return;
        } 
      } catch (Throwable throwable) {
        throw a(null);
      } 
      Zg_i.Zc(Class.forName(a(-15411, 906)));
    } catch (Throwable throwable) {}
  }
  
  static boolean Zz(Object[] paramArrayOfObject, Object paramObject) throws Throwable {
    // Byte code:
    //   0: invokestatic ZK : ()Z
    //   3: istore_2
    //   4: getstatic burp/Zzxa.ZI : Ljava/lang/Object;
    //   7: checkcast java/math/BigInteger
    //   10: getstatic burp/Zsgl.Zn : Ljava/lang/Object;
    //   13: checkcast java/math/BigInteger
    //   16: invokevirtual subtract : (Ljava/math/BigInteger;)Ljava/math/BigInteger;
    //   19: putstatic burp/Zbli.Zo : Ljava/lang/Object;
    //   22: getstatic burp/Ze3t.Zp : Ljava/lang/Object;
    //   25: checkcast java/math/BigInteger
    //   28: invokevirtual toByteArray : ()[B
    //   31: astore_3
    //   32: bipush #64
    //   34: newarray byte
    //   36: dup
    //   37: iconst_0
    //   38: bipush #-128
    //   40: bastore
    //   41: dup
    //   42: iconst_1
    //   43: iconst_0
    //   44: bastore
    //   45: dup
    //   46: iconst_2
    //   47: iconst_0
    //   48: bastore
    //   49: dup
    //   50: iconst_3
    //   51: iconst_0
    //   52: bastore
    //   53: dup
    //   54: iconst_4
    //   55: iconst_0
    //   56: bastore
    //   57: dup
    //   58: iconst_5
    //   59: iconst_0
    //   60: bastore
    //   61: dup
    //   62: bipush #6
    //   64: iconst_0
    //   65: bastore
    //   66: dup
    //   67: bipush #7
    //   69: iconst_0
    //   70: bastore
    //   71: dup
    //   72: bipush #8
    //   74: iconst_0
    //   75: bastore
    //   76: dup
    //   77: bipush #9
    //   79: iconst_0
    //   80: bastore
    //   81: dup
    //   82: bipush #10
    //   84: iconst_0
    //   85: bastore
    //   86: dup
    //   87: bipush #11
    //   89: iconst_0
    //   90: bastore
    //   91: dup
    //   92: bipush #12
    //   94: iconst_0
    //   95: bastore
    //   96: dup
    //   97: bipush #13
    //   99: iconst_0
    //   100: bastore
    //   101: dup
    //   102: bipush #14
    //   104: iconst_0
    //   105: bastore
    //   106: dup
    //   107: bipush #15
    //   109: iconst_0
    //   110: bastore
    //   111: dup
    //   112: bipush #16
    //   114: iconst_0
    //   115: bastore
    //   116: dup
    //   117: bipush #17
    //   119: iconst_0
    //   120: bastore
    //   121: dup
    //   122: bipush #18
    //   124: iconst_0
    //   125: bastore
    //   126: dup
    //   127: bipush #19
    //   129: iconst_0
    //   130: bastore
    //   131: dup
    //   132: bipush #20
    //   134: iconst_0
    //   135: bastore
    //   136: dup
    //   137: bipush #21
    //   139: iconst_0
    //   140: bastore
    //   141: dup
    //   142: bipush #22
    //   144: iconst_0
    //   145: bastore
    //   146: dup
    //   147: bipush #23
    //   149: iconst_0
    //   150: bastore
    //   151: dup
    //   152: bipush #24
    //   154: iconst_0
    //   155: bastore
    //   156: dup
    //   157: bipush #25
    //   159: iconst_0
    //   160: bastore
    //   161: dup
    //   162: bipush #26
    //   164: iconst_0
    //   165: bastore
    //   166: dup
    //   167: bipush #27
    //   169: iconst_0
    //   170: bastore
    //   171: dup
    //   172: bipush #28
    //   174: iconst_0
    //   175: bastore
    //   176: dup
    //   177: bipush #29
    //   179: iconst_0
    //   180: bastore
    //   181: dup
    //   182: bipush #30
    //   184: iconst_0
    //   185: bastore
    //   186: dup
    //   187: bipush #31
    //   189: iconst_0
    //   190: bastore
    //   191: dup
    //   192: bipush #32
    //   194: iconst_0
    //   195: bastore
    //   196: dup
    //   197: bipush #33
    //   199: iconst_0
    //   200: bastore
    //   201: dup
    //   202: bipush #34
    //   204: iconst_0
    //   205: bastore
    //   206: dup
    //   207: bipush #35
    //   209: iconst_0
    //   210: bastore
    //   211: dup
    //   212: bipush #36
    //   214: iconst_0
    //   215: bastore
    //   216: dup
    //   217: bipush #37
    //   219: iconst_0
    //   220: bastore
    //   221: dup
    //   222: bipush #38
    //   224: iconst_0
    //   225: bastore
    //   226: dup
    //   227: bipush #39
    //   229: iconst_0
    //   230: bastore
    //   231: dup
    //   232: bipush #40
    //   234: iconst_0
    //   235: bastore
    //   236: dup
    //   237: bipush #41
    //   239: iconst_0
    //   240: bastore
    //   241: dup
    //   242: bipush #42
    //   244: iconst_0
    //   245: bastore
    //   246: dup
    //   247: bipush #43
    //   249: iconst_0
    //   250: bastore
    //   251: dup
    //   252: bipush #44
    //   254: iconst_0
    //   255: bastore
    //   256: dup
    //   257: bipush #45
    //   259: iconst_0
    //   260: bastore
    //   261: dup
    //   262: bipush #46
    //   264: iconst_0
    //   265: bastore
    //   266: dup
    //   267: bipush #47
    //   269: iconst_0
    //   270: bastore
    //   271: dup
    //   272: bipush #48
    //   274: iconst_0
    //   275: bastore
    //   276: dup
    //   277: bipush #49
    //   279: iconst_0
    //   280: bastore
    //   281: dup
    //   282: bipush #50
    //   284: iconst_0
    //   285: bastore
    //   286: dup
    //   287: bipush #51
    //   289: iconst_0
    //   290: bastore
    //   291: dup
    //   292: bipush #52
    //   294: iconst_0
    //   295: bastore
    //   296: dup
    //   297: bipush #53
    //   299: iconst_0
    //   300: bastore
    //   301: dup
    //   302: bipush #54
    //   304: iconst_0
    //   305: bastore
    //   306: dup
    //   307: bipush #55
    //   309: iconst_0
    //   310: bastore
    //   311: dup
    //   312: bipush #56
    //   314: iconst_0
    //   315: bastore
    //   316: dup
    //   317: bipush #57
    //   319: iconst_0
    //   320: bastore
    //   321: dup
    //   322: bipush #58
    //   324: iconst_0
    //   325: bastore
    //   326: dup
    //   327: bipush #59
    //   329: iconst_0
    //   330: bastore
    //   331: dup
    //   332: bipush #60
    //   334: iconst_0
    //   335: bastore
    //   336: dup
    //   337: bipush #61
    //   339: iconst_0
    //   340: bastore
    //   341: dup
    //   342: bipush #62
    //   344: iconst_0
    //   345: bastore
    //   346: dup
    //   347: bipush #63
    //   349: iconst_0
    //   350: bastore
    //   351: astore #5
    //   353: bipush #64
    //   355: newarray int
    //   357: dup
    //   358: iconst_0
    //   359: ldc 1116352408
    //   361: iastore
    //   362: dup
    //   363: iconst_1
    //   364: ldc 1899447441
    //   366: iastore
    //   367: dup
    //   368: iconst_2
    //   369: ldc -1245643825
    //   371: iastore
    //   372: dup
    //   373: iconst_3
    //   374: ldc -373957723
    //   376: iastore
    //   377: dup
    //   378: iconst_4
    //   379: ldc 961987163
    //   381: iastore
    //   382: dup
    //   383: iconst_5
    //   384: ldc 1508970993
    //   386: iastore
    //   387: dup
    //   388: bipush #6
    //   390: ldc -1841331548
    //   392: iastore
    //   393: dup
    //   394: bipush #7
    //   396: ldc -1424204075
    //   398: iastore
    //   399: dup
    //   400: bipush #8
    //   402: ldc -670586216
    //   404: iastore
    //   405: dup
    //   406: bipush #9
    //   408: ldc 310598401
    //   410: iastore
    //   411: dup
    //   412: bipush #10
    //   414: ldc 607225278
    //   416: iastore
    //   417: dup
    //   418: bipush #11
    //   420: ldc 1426881987
    //   422: iastore
    //   423: dup
    //   424: bipush #12
    //   426: ldc 1925078388
    //   428: iastore
    //   429: dup
    //   430: bipush #13
    //   432: ldc -2132889090
    //   434: iastore
    //   435: dup
    //   436: bipush #14
    //   438: ldc -1680079193
    //   440: iastore
    //   441: dup
    //   442: bipush #15
    //   444: ldc -1046744716
    //   446: iastore
    //   447: dup
    //   448: bipush #16
    //   450: ldc -459576895
    //   452: iastore
    //   453: dup
    //   454: bipush #17
    //   456: ldc -272742522
    //   458: iastore
    //   459: dup
    //   460: bipush #18
    //   462: ldc 264347078
    //   464: iastore
    //   465: dup
    //   466: bipush #19
    //   468: ldc 604807628
    //   470: iastore
    //   471: dup
    //   472: bipush #20
    //   474: ldc 770255983
    //   476: iastore
    //   477: dup
    //   478: bipush #21
    //   480: ldc 1249150122
    //   482: iastore
    //   483: dup
    //   484: bipush #22
    //   486: ldc 1555081692
    //   488: iastore
    //   489: dup
    //   490: bipush #23
    //   492: ldc 1996064986
    //   494: iastore
    //   495: dup
    //   496: bipush #24
    //   498: ldc -1740746414
    //   500: iastore
    //   501: dup
    //   502: bipush #25
    //   504: ldc -1473132947
    //   506: iastore
    //   507: dup
    //   508: bipush #26
    //   510: ldc -1341970488
    //   512: iastore
    //   513: dup
    //   514: bipush #27
    //   516: ldc -1084653625
    //   518: iastore
    //   519: dup
    //   520: bipush #28
    //   522: ldc -958395405
    //   524: iastore
    //   525: dup
    //   526: bipush #29
    //   528: ldc -710438585
    //   530: iastore
    //   531: dup
    //   532: bipush #30
    //   534: ldc 113926993
    //   536: iastore
    //   537: dup
    //   538: bipush #31
    //   540: ldc 338241895
    //   542: iastore
    //   543: dup
    //   544: bipush #32
    //   546: ldc 666307205
    //   548: iastore
    //   549: dup
    //   550: bipush #33
    //   552: ldc 773529912
    //   554: iastore
    //   555: dup
    //   556: bipush #34
    //   558: ldc 1294757372
    //   560: iastore
    //   561: dup
    //   562: bipush #35
    //   564: ldc 1396182291
    //   566: iastore
    //   567: dup
    //   568: bipush #36
    //   570: ldc 1695183700
    //   572: iastore
    //   573: dup
    //   574: bipush #37
    //   576: ldc 1986661051
    //   578: iastore
    //   579: dup
    //   580: bipush #38
    //   582: ldc -2117940946
    //   584: iastore
    //   585: dup
    //   586: bipush #39
    //   588: ldc -1838011259
    //   590: iastore
    //   591: dup
    //   592: bipush #40
    //   594: ldc -1564481375
    //   596: iastore
    //   597: dup
    //   598: bipush #41
    //   600: ldc -1474664885
    //   602: iastore
    //   603: dup
    //   604: bipush #42
    //   606: ldc -1035236496
    //   608: iastore
    //   609: dup
    //   610: bipush #43
    //   612: ldc -949202525
    //   614: iastore
    //   615: dup
    //   616: bipush #44
    //   618: ldc -778901479
    //   620: iastore
    //   621: dup
    //   622: bipush #45
    //   624: ldc -694614492
    //   626: iastore
    //   627: dup
    //   628: bipush #46
    //   630: ldc -200395387
    //   632: iastore
    //   633: dup
    //   634: bipush #47
    //   636: ldc 275423344
    //   638: iastore
    //   639: dup
    //   640: bipush #48
    //   642: ldc 430227734
    //   644: iastore
    //   645: dup
    //   646: bipush #49
    //   648: ldc 506948616
    //   650: iastore
    //   651: dup
    //   652: bipush #50
    //   654: ldc 659060556
    //   656: iastore
    //   657: dup
    //   658: bipush #51
    //   660: ldc 883997877
    //   662: iastore
    //   663: dup
    //   664: bipush #52
    //   666: ldc 958139571
    //   668: iastore
    //   669: dup
    //   670: bipush #53
    //   672: ldc 1322822218
    //   674: iastore
    //   675: dup
    //   676: bipush #54
    //   678: ldc 1537002063
    //   680: iastore
    //   681: dup
    //   682: bipush #55
    //   684: ldc 1747873779
    //   686: iastore
    //   687: dup
    //   688: bipush #56
    //   690: ldc 1955562222
    //   692: iastore
    //   693: dup
    //   694: bipush #57
    //   696: ldc 2024104815
    //   698: iastore
    //   699: dup
    //   700: bipush #58
    //   702: ldc -2067236844
    //   704: iastore
    //   705: dup
    //   706: bipush #59
    //   708: ldc -1933114872
    //   710: iastore
    //   711: dup
    //   712: bipush #60
    //   714: ldc -1866530822
    //   716: iastore
    //   717: dup
    //   718: bipush #61
    //   720: ldc -1538233109
    //   722: iastore
    //   723: dup
    //   724: bipush #62
    //   726: ldc -1090935817
    //   728: iastore
    //   729: dup
    //   730: bipush #63
    //   732: ldc -965641998
    //   734: iastore
    //   735: astore #6
    //   737: iconst_2
    //   738: newarray int
    //   740: dup
    //   741: iconst_0
    //   742: iconst_0
    //   743: iastore
    //   744: dup
    //   745: iconst_1
    //   746: iconst_0
    //   747: iastore
    //   748: astore #7
    //   750: bipush #8
    //   752: newarray int
    //   754: dup
    //   755: iconst_0
    //   756: ldc 1779033703
    //   758: iastore
    //   759: dup
    //   760: iconst_1
    //   761: ldc -1150833019
    //   763: iastore
    //   764: dup
    //   765: iconst_2
    //   766: ldc 1013904242
    //   768: iastore
    //   769: dup
    //   770: iconst_3
    //   771: ldc -1521486534
    //   773: iastore
    //   774: dup
    //   775: iconst_4
    //   776: ldc 1359893119
    //   778: iastore
    //   779: dup
    //   780: iconst_5
    //   781: ldc -1694144372
    //   783: iastore
    //   784: dup
    //   785: bipush #6
    //   787: ldc 528734635
    //   789: iastore
    //   790: dup
    //   791: bipush #7
    //   793: ldc 1541459225
    //   795: iastore
    //   796: astore #8
    //   798: bipush #64
    //   800: newarray byte
    //   802: astore #9
    //   804: bipush #64
    //   806: newarray byte
    //   808: astore #10
    //   810: aload_3
    //   811: arraylength
    //   812: istore #11
    //   814: aload #7
    //   816: iconst_0
    //   817: iaload
    //   818: bipush #63
    //   820: iand
    //   821: istore #12
    //   823: aload #7
    //   825: iconst_0
    //   826: dup2
    //   827: iaload
    //   828: iload #11
    //   830: iadd
    //   831: iastore
    //   832: aload #7
    //   834: iconst_0
    //   835: dup2
    //   836: iaload
    //   837: iconst_m1
    //   838: iand
    //   839: iastore
    //   840: aload #7
    //   842: iconst_0
    //   843: iaload
    //   844: iload #11
    //   846: if_icmpge -> 864
    //   849: aload #7
    //   851: iconst_1
    //   852: dup2
    //   853: iaload
    //   854: iconst_1
    //   855: iadd
    //   856: iastore
    //   857: goto -> 864
    //   860: invokestatic a : (Ljava/lang/Throwable;)Ljava/lang/Throwable;
    //   863: athrow
    //   864: iconst_0
    //   865: istore #13
    //   867: iload #11
    //   869: bipush #64
    //   871: if_icmplt -> 1480
    //   874: iconst_0
    //   875: istore #14
    //   877: iload #14
    //   879: bipush #64
    //   881: if_icmpge -> 903
    //   884: aload #10
    //   886: iload #14
    //   888: aload_3
    //   889: iload #13
    //   891: iload #14
    //   893: iadd
    //   894: baload
    //   895: bastore
    //   896: iinc #14, 1
    //   899: iload_2
    //   900: ifeq -> 877
    //   903: bipush #64
    //   905: newarray int
    //   907: astore #14
    //   909: bipush #8
    //   911: newarray int
    //   913: astore #15
    //   915: iconst_0
    //   916: istore #16
    //   918: iload #16
    //   920: bipush #8
    //   922: if_icmpge -> 942
    //   925: aload #15
    //   927: iload #16
    //   929: aload #8
    //   931: iload #16
    //   933: iaload
    //   934: iastore
    //   935: iinc #16, 1
    //   938: iload_2
    //   939: ifeq -> 918
    //   942: iconst_0
    //   943: istore #16
    //   945: iload #16
    //   947: bipush #64
    //   949: if_icmpge -> 1440
    //   952: iload #16
    //   954: bipush #16
    //   956: if_icmpge -> 1037
    //   959: aload #14
    //   961: iload #16
    //   963: aload #10
    //   965: iconst_4
    //   966: iload #16
    //   968: imul
    //   969: baload
    //   970: sipush #255
    //   973: iand
    //   974: bipush #24
    //   976: ishl
    //   977: aload #10
    //   979: iconst_4
    //   980: iload #16
    //   982: imul
    //   983: iconst_1
    //   984: iadd
    //   985: baload
    //   986: sipush #255
    //   989: iand
    //   990: bipush #16
    //   992: ishl
    //   993: ior
    //   994: aload #10
    //   996: iconst_4
    //   997: iload #16
    //   999: imul
    //   1000: iconst_2
    //   1001: iadd
    //   1002: baload
    //   1003: sipush #255
    //   1006: iand
    //   1007: bipush #8
    //   1009: ishl
    //   1010: ior
    //   1011: aload #10
    //   1013: iconst_4
    //   1014: iload #16
    //   1016: imul
    //   1017: iconst_3
    //   1018: iadd
    //   1019: baload
    //   1020: sipush #255
    //   1023: iand
    //   1024: ior
    //   1025: iastore
    //   1026: iload_2
    //   1027: ifeq -> 1180
    //   1030: goto -> 1037
    //   1033: invokestatic a : (Ljava/lang/Throwable;)Ljava/lang/Throwable;
    //   1036: athrow
    //   1037: aload #14
    //   1039: iload #16
    //   1041: aload #14
    //   1043: iload #16
    //   1045: iconst_2
    //   1046: isub
    //   1047: iaload
    //   1048: bipush #17
    //   1050: iushr
    //   1051: aload #14
    //   1053: iload #16
    //   1055: iconst_2
    //   1056: isub
    //   1057: iaload
    //   1058: bipush #15
    //   1060: ishl
    //   1061: ior
    //   1062: aload #14
    //   1064: iload #16
    //   1066: iconst_2
    //   1067: isub
    //   1068: iaload
    //   1069: bipush #19
    //   1071: iushr
    //   1072: aload #14
    //   1074: iload #16
    //   1076: iconst_2
    //   1077: isub
    //   1078: iaload
    //   1079: bipush #13
    //   1081: ishl
    //   1082: ior
    //   1083: ixor
    //   1084: aload #14
    //   1086: iload #16
    //   1088: iconst_2
    //   1089: isub
    //   1090: iaload
    //   1091: bipush #10
    //   1093: iushr
    //   1094: ixor
    //   1095: aload #14
    //   1097: iload #16
    //   1099: bipush #7
    //   1101: isub
    //   1102: iaload
    //   1103: iadd
    //   1104: aload #14
    //   1106: iload #16
    //   1108: bipush #15
    //   1110: isub
    //   1111: iaload
    //   1112: bipush #7
    //   1114: iushr
    //   1115: aload #14
    //   1117: iload #16
    //   1119: bipush #15
    //   1121: isub
    //   1122: iaload
    //   1123: bipush #25
    //   1125: ishl
    //   1126: ior
    //   1127: aload #14
    //   1129: iload #16
    //   1131: bipush #15
    //   1133: isub
    //   1134: iaload
    //   1135: bipush #18
    //   1137: iushr
    //   1138: aload #14
    //   1140: iload #16
    //   1142: bipush #15
    //   1144: isub
    //   1145: iaload
    //   1146: bipush #14
    //   1148: ishl
    //   1149: ior
    //   1150: ixor
    //   1151: aload #14
    //   1153: iload #16
    //   1155: bipush #15
    //   1157: isub
    //   1158: iaload
    //   1159: iconst_3
    //   1160: iushr
    //   1161: ixor
    //   1162: iadd
    //   1163: aload #14
    //   1165: iload #16
    //   1167: bipush #16
    //   1169: isub
    //   1170: iaload
    //   1171: iadd
    //   1172: iastore
    //   1173: goto -> 1180
    //   1176: invokestatic a : (Ljava/lang/Throwable;)Ljava/lang/Throwable;
    //   1179: athrow
    //   1180: aload #15
    //   1182: bipush #7
    //   1184: iaload
    //   1185: aload #15
    //   1187: iconst_4
    //   1188: iaload
    //   1189: bipush #6
    //   1191: iushr
    //   1192: aload #15
    //   1194: iconst_4
    //   1195: iaload
    //   1196: bipush #26
    //   1198: ishl
    //   1199: ior
    //   1200: aload #15
    //   1202: iconst_4
    //   1203: iaload
    //   1204: bipush #11
    //   1206: iushr
    //   1207: aload #15
    //   1209: iconst_4
    //   1210: iaload
    //   1211: bipush #21
    //   1213: ishl
    //   1214: ior
    //   1215: ixor
    //   1216: aload #15
    //   1218: iconst_4
    //   1219: iaload
    //   1220: bipush #25
    //   1222: iushr
    //   1223: aload #15
    //   1225: iconst_4
    //   1226: iaload
    //   1227: bipush #7
    //   1229: ishl
    //   1230: ior
    //   1231: ixor
    //   1232: iadd
    //   1233: aload #15
    //   1235: bipush #6
    //   1237: iaload
    //   1238: aload #15
    //   1240: iconst_4
    //   1241: iaload
    //   1242: aload #15
    //   1244: iconst_5
    //   1245: iaload
    //   1246: aload #15
    //   1248: bipush #6
    //   1250: iaload
    //   1251: ixor
    //   1252: iand
    //   1253: ixor
    //   1254: iadd
    //   1255: aload #6
    //   1257: iload #16
    //   1259: iaload
    //   1260: iadd
    //   1261: aload #14
    //   1263: iload #16
    //   1265: iaload
    //   1266: iadd
    //   1267: istore #17
    //   1269: aload #15
    //   1271: iconst_0
    //   1272: iaload
    //   1273: iconst_2
    //   1274: iushr
    //   1275: aload #15
    //   1277: iconst_0
    //   1278: iaload
    //   1279: bipush #30
    //   1281: ishl
    //   1282: ior
    //   1283: aload #15
    //   1285: iconst_0
    //   1286: iaload
    //   1287: bipush #13
    //   1289: iushr
    //   1290: aload #15
    //   1292: iconst_0
    //   1293: iaload
    //   1294: bipush #19
    //   1296: ishl
    //   1297: ior
    //   1298: ixor
    //   1299: aload #15
    //   1301: iconst_0
    //   1302: iaload
    //   1303: bipush #22
    //   1305: iushr
    //   1306: aload #15
    //   1308: iconst_0
    //   1309: iaload
    //   1310: bipush #10
    //   1312: ishl
    //   1313: ior
    //   1314: ixor
    //   1315: aload #15
    //   1317: iconst_0
    //   1318: iaload
    //   1319: aload #15
    //   1321: iconst_1
    //   1322: iaload
    //   1323: iand
    //   1324: aload #15
    //   1326: iconst_2
    //   1327: iaload
    //   1328: aload #15
    //   1330: iconst_0
    //   1331: iaload
    //   1332: aload #15
    //   1334: iconst_1
    //   1335: iaload
    //   1336: ior
    //   1337: iand
    //   1338: ior
    //   1339: iadd
    //   1340: istore #18
    //   1342: aload #15
    //   1344: iconst_3
    //   1345: dup2
    //   1346: iaload
    //   1347: iload #17
    //   1349: iadd
    //   1350: iastore
    //   1351: aload #15
    //   1353: bipush #7
    //   1355: iload #17
    //   1357: iload #18
    //   1359: iadd
    //   1360: iastore
    //   1361: aload #15
    //   1363: bipush #7
    //   1365: iaload
    //   1366: istore #17
    //   1368: aload #15
    //   1370: bipush #7
    //   1372: aload #15
    //   1374: bipush #6
    //   1376: iaload
    //   1377: iastore
    //   1378: aload #15
    //   1380: bipush #6
    //   1382: aload #15
    //   1384: iconst_5
    //   1385: iaload
    //   1386: iastore
    //   1387: aload #15
    //   1389: iconst_5
    //   1390: aload #15
    //   1392: iconst_4
    //   1393: iaload
    //   1394: iastore
    //   1395: aload #15
    //   1397: iconst_4
    //   1398: aload #15
    //   1400: iconst_3
    //   1401: iaload
    //   1402: iastore
    //   1403: aload #15
    //   1405: iconst_3
    //   1406: aload #15
    //   1408: iconst_2
    //   1409: iaload
    //   1410: iastore
    //   1411: aload #15
    //   1413: iconst_2
    //   1414: aload #15
    //   1416: iconst_1
    //   1417: iaload
    //   1418: iastore
    //   1419: aload #15
    //   1421: iconst_1
    //   1422: aload #15
    //   1424: iconst_0
    //   1425: iaload
    //   1426: iastore
    //   1427: aload #15
    //   1429: iconst_0
    //   1430: iload #17
    //   1432: iastore
    //   1433: iinc #16, 1
    //   1436: iload_2
    //   1437: ifeq -> 945
    //   1440: iconst_0
    //   1441: istore #16
    //   1443: iload #16
    //   1445: bipush #8
    //   1447: if_icmpge -> 1470
    //   1450: aload #8
    //   1452: iload #16
    //   1454: dup2
    //   1455: iaload
    //   1456: aload #15
    //   1458: iload #16
    //   1460: iaload
    //   1461: iadd
    //   1462: iastore
    //   1463: iinc #16, 1
    //   1466: iload_2
    //   1467: ifeq -> 1443
    //   1470: iinc #13, 64
    //   1473: iinc #11, -64
    //   1476: iload_2
    //   1477: ifeq -> 867
    //   1480: iload #11
    //   1482: ifle -> 1517
    //   1485: iconst_0
    //   1486: istore #14
    //   1488: iload #14
    //   1490: iload #11
    //   1492: if_icmpge -> 1517
    //   1495: aload #9
    //   1497: iload #12
    //   1499: iload #14
    //   1501: iadd
    //   1502: aload_3
    //   1503: iload #13
    //   1505: iload #14
    //   1507: iadd
    //   1508: baload
    //   1509: bastore
    //   1510: iinc #14, 1
    //   1513: iload_2
    //   1514: ifeq -> 1488
    //   1517: aload #7
    //   1519: iconst_0
    //   1520: iaload
    //   1521: bipush #29
    //   1523: iushr
    //   1524: aload #7
    //   1526: iconst_1
    //   1527: iaload
    //   1528: iconst_3
    //   1529: ishl
    //   1530: ior
    //   1531: istore #14
    //   1533: aload #7
    //   1535: iconst_0
    //   1536: iaload
    //   1537: iconst_3
    //   1538: ishl
    //   1539: istore #15
    //   1541: aload #7
    //   1543: iconst_0
    //   1544: iaload
    //   1545: bipush #63
    //   1547: iand
    //   1548: istore #16
    //   1550: iload #16
    //   1552: bipush #56
    //   1554: if_icmpge -> 1569
    //   1557: bipush #56
    //   1559: iload #16
    //   1561: isub
    //   1562: goto -> 1574
    //   1565: invokestatic a : (Ljava/lang/Throwable;)Ljava/lang/Throwable;
    //   1568: athrow
    //   1569: bipush #120
    //   1571: iload #16
    //   1573: isub
    //   1574: istore #17
    //   1576: aload #7
    //   1578: iconst_0
    //   1579: iaload
    //   1580: bipush #63
    //   1582: iand
    //   1583: istore #12
    //   1585: bipush #64
    //   1587: iload #12
    //   1589: isub
    //   1590: istore #18
    //   1592: aload #7
    //   1594: iconst_0
    //   1595: dup2
    //   1596: iaload
    //   1597: iload #17
    //   1599: iadd
    //   1600: iastore
    //   1601: aload #7
    //   1603: iconst_0
    //   1604: dup2
    //   1605: iaload
    //   1606: iconst_m1
    //   1607: iand
    //   1608: iastore
    //   1609: aload #7
    //   1611: iconst_0
    //   1612: iaload
    //   1613: iload #17
    //   1615: if_icmpge -> 1633
    //   1618: aload #7
    //   1620: iconst_1
    //   1621: dup2
    //   1622: iaload
    //   1623: iconst_1
    //   1624: iadd
    //   1625: iastore
    //   1626: goto -> 1633
    //   1629: invokestatic a : (Ljava/lang/Throwable;)Ljava/lang/Throwable;
    //   1632: athrow
    //   1633: iconst_0
    //   1634: istore #13
    //   1636: iload #12
    //   1638: ifle -> 2269
    //   1641: iload #17
    //   1643: iload #18
    //   1645: if_icmplt -> 2269
    //   1648: goto -> 1655
    //   1651: invokestatic a : (Ljava/lang/Throwable;)Ljava/lang/Throwable;
    //   1654: athrow
    //   1655: iconst_0
    //   1656: istore #19
    //   1658: iload #19
    //   1660: iload #18
    //   1662: if_icmpge -> 1685
    //   1665: aload #9
    //   1667: iload #12
    //   1669: iload #19
    //   1671: iadd
    //   1672: aload #5
    //   1674: iload #19
    //   1676: baload
    //   1677: bastore
    //   1678: iinc #19, 1
    //   1681: iload_2
    //   1682: ifeq -> 1658
    //   1685: bipush #64
    //   1687: newarray int
    //   1689: astore #19
    //   1691: bipush #8
    //   1693: newarray int
    //   1695: astore #20
    //   1697: iconst_0
    //   1698: istore #21
    //   1700: iload #21
    //   1702: bipush #8
    //   1704: if_icmpge -> 1724
    //   1707: aload #20
    //   1709: iload #21
    //   1711: aload #8
    //   1713: iload #21
    //   1715: iaload
    //   1716: iastore
    //   1717: iinc #21, 1
    //   1720: iload_2
    //   1721: ifeq -> 1700
    //   1724: iconst_0
    //   1725: istore #21
    //   1727: iload #21
    //   1729: bipush #64
    //   1731: if_icmpge -> 2222
    //   1734: iload #21
    //   1736: bipush #16
    //   1738: if_icmpge -> 1819
    //   1741: aload #19
    //   1743: iload #21
    //   1745: aload #9
    //   1747: iconst_4
    //   1748: iload #21
    //   1750: imul
    //   1751: baload
    //   1752: sipush #255
    //   1755: iand
    //   1756: bipush #24
    //   1758: ishl
    //   1759: aload #9
    //   1761: iconst_4
    //   1762: iload #21
    //   1764: imul
    //   1765: iconst_1
    //   1766: iadd
    //   1767: baload
    //   1768: sipush #255
    //   1771: iand
    //   1772: bipush #16
    //   1774: ishl
    //   1775: ior
    //   1776: aload #9
    //   1778: iconst_4
    //   1779: iload #21
    //   1781: imul
    //   1782: iconst_2
    //   1783: iadd
    //   1784: baload
    //   1785: sipush #255
    //   1788: iand
    //   1789: bipush #8
    //   1791: ishl
    //   1792: ior
    //   1793: aload #9
    //   1795: iconst_4
    //   1796: iload #21
    //   1798: imul
    //   1799: iconst_3
    //   1800: iadd
    //   1801: baload
    //   1802: sipush #255
    //   1805: iand
    //   1806: ior
    //   1807: iastore
    //   1808: iload_2
    //   1809: ifeq -> 1962
    //   1812: goto -> 1819
    //   1815: invokestatic a : (Ljava/lang/Throwable;)Ljava/lang/Throwable;
    //   1818: athrow
    //   1819: aload #19
    //   1821: iload #21
    //   1823: aload #19
    //   1825: iload #21
    //   1827: iconst_2
    //   1828: isub
    //   1829: iaload
    //   1830: bipush #17
    //   1832: iushr
    //   1833: aload #19
    //   1835: iload #21
    //   1837: iconst_2
    //   1838: isub
    //   1839: iaload
    //   1840: bipush #15
    //   1842: ishl
    //   1843: ior
    //   1844: aload #19
    //   1846: iload #21
    //   1848: iconst_2
    //   1849: isub
    //   1850: iaload
    //   1851: bipush #19
    //   1853: iushr
    //   1854: aload #19
    //   1856: iload #21
    //   1858: iconst_2
    //   1859: isub
    //   1860: iaload
    //   1861: bipush #13
    //   1863: ishl
    //   1864: ior
    //   1865: ixor
    //   1866: aload #19
    //   1868: iload #21
    //   1870: iconst_2
    //   1871: isub
    //   1872: iaload
    //   1873: bipush #10
    //   1875: iushr
    //   1876: ixor
    //   1877: aload #19
    //   1879: iload #21
    //   1881: bipush #7
    //   1883: isub
    //   1884: iaload
    //   1885: iadd
    //   1886: aload #19
    //   1888: iload #21
    //   1890: bipush #15
    //   1892: isub
    //   1893: iaload
    //   1894: bipush #7
    //   1896: iushr
    //   1897: aload #19
    //   1899: iload #21
    //   1901: bipush #15
    //   1903: isub
    //   1904: iaload
    //   1905: bipush #25
    //   1907: ishl
    //   1908: ior
    //   1909: aload #19
    //   1911: iload #21
    //   1913: bipush #15
    //   1915: isub
    //   1916: iaload
    //   1917: bipush #18
    //   1919: iushr
    //   1920: aload #19
    //   1922: iload #21
    //   1924: bipush #15
    //   1926: isub
    //   1927: iaload
    //   1928: bipush #14
    //   1930: ishl
    //   1931: ior
    //   1932: ixor
    //   1933: aload #19
    //   1935: iload #21
    //   1937: bipush #15
    //   1939: isub
    //   1940: iaload
    //   1941: iconst_3
    //   1942: iushr
    //   1943: ixor
    //   1944: iadd
    //   1945: aload #19
    //   1947: iload #21
    //   1949: bipush #16
    //   1951: isub
    //   1952: iaload
    //   1953: iadd
    //   1954: iastore
    //   1955: goto -> 1962
    //   1958: invokestatic a : (Ljava/lang/Throwable;)Ljava/lang/Throwable;
    //   1961: athrow
    //   1962: aload #20
    //   1964: bipush #7
    //   1966: iaload
    //   1967: aload #20
    //   1969: iconst_4
    //   1970: iaload
    //   1971: bipush #6
    //   1973: iushr
    //   1974: aload #20
    //   1976: iconst_4
    //   1977: iaload
    //   1978: bipush #26
    //   1980: ishl
    //   1981: ior
    //   1982: aload #20
    //   1984: iconst_4
    //   1985: iaload
    //   1986: bipush #11
    //   1988: iushr
    //   1989: aload #20
    //   1991: iconst_4
    //   1992: iaload
    //   1993: bipush #21
    //   1995: ishl
    //   1996: ior
    //   1997: ixor
    //   1998: aload #20
    //   2000: iconst_4
    //   2001: iaload
    //   2002: bipush #25
    //   2004: iushr
    //   2005: aload #20
    //   2007: iconst_4
    //   2008: iaload
    //   2009: bipush #7
    //   2011: ishl
    //   2012: ior
    //   2013: ixor
    //   2014: iadd
    //   2015: aload #20
    //   2017: bipush #6
    //   2019: iaload
    //   2020: aload #20
    //   2022: iconst_4
    //   2023: iaload
    //   2024: aload #20
    //   2026: iconst_5
    //   2027: iaload
    //   2028: aload #20
    //   2030: bipush #6
    //   2032: iaload
    //   2033: ixor
    //   2034: iand
    //   2035: ixor
    //   2036: iadd
    //   2037: aload #6
    //   2039: iload #21
    //   2041: iaload
    //   2042: iadd
    //   2043: aload #19
    //   2045: iload #21
    //   2047: iaload
    //   2048: iadd
    //   2049: istore #22
    //   2051: aload #20
    //   2053: iconst_0
    //   2054: iaload
    //   2055: iconst_2
    //   2056: iushr
    //   2057: aload #20
    //   2059: iconst_0
    //   2060: iaload
    //   2061: bipush #30
    //   2063: ishl
    //   2064: ior
    //   2065: aload #20
    //   2067: iconst_0
    //   2068: iaload
    //   2069: bipush #13
    //   2071: iushr
    //   2072: aload #20
    //   2074: iconst_0
    //   2075: iaload
    //   2076: bipush #19
    //   2078: ishl
    //   2079: ior
    //   2080: ixor
    //   2081: aload #20
    //   2083: iconst_0
    //   2084: iaload
    //   2085: bipush #22
    //   2087: iushr
    //   2088: aload #20
    //   2090: iconst_0
    //   2091: iaload
    //   2092: bipush #10
    //   2094: ishl
    //   2095: ior
    //   2096: ixor
    //   2097: aload #20
    //   2099: iconst_0
    //   2100: iaload
    //   2101: aload #20
    //   2103: iconst_1
    //   2104: iaload
    //   2105: iand
    //   2106: aload #20
    //   2108: iconst_2
    //   2109: iaload
    //   2110: aload #20
    //   2112: iconst_0
    //   2113: iaload
    //   2114: aload #20
    //   2116: iconst_1
    //   2117: iaload
    //   2118: ior
    //   2119: iand
    //   2120: ior
    //   2121: iadd
    //   2122: istore #23
    //   2124: aload #20
    //   2126: iconst_3
    //   2127: dup2
    //   2128: iaload
    //   2129: iload #22
    //   2131: iadd
    //   2132: iastore
    //   2133: aload #20
    //   2135: bipush #7
    //   2137: iload #22
    //   2139: iload #23
    //   2141: iadd
    //   2142: iastore
    //   2143: aload #20
    //   2145: bipush #7
    //   2147: iaload
    //   2148: istore #22
    //   2150: aload #20
    //   2152: bipush #7
    //   2154: aload #20
    //   2156: bipush #6
    //   2158: iaload
    //   2159: iastore
    //   2160: aload #20
    //   2162: bipush #6
    //   2164: aload #20
    //   2166: iconst_5
    //   2167: iaload
    //   2168: iastore
    //   2169: aload #20
    //   2171: iconst_5
    //   2172: aload #20
    //   2174: iconst_4
    //   2175: iaload
    //   2176: iastore
    //   2177: aload #20
    //   2179: iconst_4
    //   2180: aload #20
    //   2182: iconst_3
    //   2183: iaload
    //   2184: iastore
    //   2185: aload #20
    //   2187: iconst_3
    //   2188: aload #20
    //   2190: iconst_2
    //   2191: iaload
    //   2192: iastore
    //   2193: aload #20
    //   2195: iconst_2
    //   2196: aload #20
    //   2198: iconst_1
    //   2199: iaload
    //   2200: iastore
    //   2201: aload #20
    //   2203: iconst_1
    //   2204: aload #20
    //   2206: iconst_0
    //   2207: iaload
    //   2208: iastore
    //   2209: aload #20
    //   2211: iconst_0
    //   2212: iload #22
    //   2214: iastore
    //   2215: iinc #21, 1
    //   2218: iload_2
    //   2219: ifeq -> 1727
    //   2222: iconst_0
    //   2223: istore #21
    //   2225: iload #21
    //   2227: bipush #8
    //   2229: if_icmpge -> 2252
    //   2232: aload #8
    //   2234: iload #21
    //   2236: dup2
    //   2237: iaload
    //   2238: aload #20
    //   2240: iload #21
    //   2242: iaload
    //   2243: iadd
    //   2244: iastore
    //   2245: iinc #21, 1
    //   2248: iload_2
    //   2249: ifeq -> 2225
    //   2252: iload #13
    //   2254: iload #18
    //   2256: iadd
    //   2257: istore #13
    //   2259: iload #17
    //   2261: iload #18
    //   2263: isub
    //   2264: istore #17
    //   2266: iconst_0
    //   2267: istore #12
    //   2269: iload #17
    //   2271: bipush #64
    //   2273: if_icmplt -> 2883
    //   2276: iconst_0
    //   2277: istore #19
    //   2279: iload #19
    //   2281: bipush #64
    //   2283: if_icmpge -> 2306
    //   2286: aload #10
    //   2288: iload #19
    //   2290: aload #5
    //   2292: iload #13
    //   2294: iload #19
    //   2296: iadd
    //   2297: baload
    //   2298: bastore
    //   2299: iinc #19, 1
    //   2302: iload_2
    //   2303: ifeq -> 2279
    //   2306: bipush #64
    //   2308: newarray int
    //   2310: astore #19
    //   2312: bipush #8
    //   2314: newarray int
    //   2316: astore #20
    //   2318: iconst_0
    //   2319: istore #21
    //   2321: iload #21
    //   2323: bipush #8
    //   2325: if_icmpge -> 2345
    //   2328: aload #20
    //   2330: iload #21
    //   2332: aload #8
    //   2334: iload #21
    //   2336: iaload
    //   2337: iastore
    //   2338: iinc #21, 1
    //   2341: iload_2
    //   2342: ifeq -> 2321
    //   2345: iconst_0
    //   2346: istore #21
    //   2348: iload #21
    //   2350: bipush #64
    //   2352: if_icmpge -> 2843
    //   2355: iload #21
    //   2357: bipush #16
    //   2359: if_icmpge -> 2440
    //   2362: aload #19
    //   2364: iload #21
    //   2366: aload #10
    //   2368: iconst_4
    //   2369: iload #21
    //   2371: imul
    //   2372: baload
    //   2373: sipush #255
    //   2376: iand
    //   2377: bipush #24
    //   2379: ishl
    //   2380: aload #10
    //   2382: iconst_4
    //   2383: iload #21
    //   2385: imul
    //   2386: iconst_1
    //   2387: iadd
    //   2388: baload
    //   2389: sipush #255
    //   2392: iand
    //   2393: bipush #16
    //   2395: ishl
    //   2396: ior
    //   2397: aload #10
    //   2399: iconst_4
    //   2400: iload #21
    //   2402: imul
    //   2403: iconst_2
    //   2404: iadd
    //   2405: baload
    //   2406: sipush #255
    //   2409: iand
    //   2410: bipush #8
    //   2412: ishl
    //   2413: ior
    //   2414: aload #10
    //   2416: iconst_4
    //   2417: iload #21
    //   2419: imul
    //   2420: iconst_3
    //   2421: iadd
    //   2422: baload
    //   2423: sipush #255
    //   2426: iand
    //   2427: ior
    //   2428: iastore
    //   2429: iload_2
    //   2430: ifeq -> 2583
    //   2433: goto -> 2440
    //   2436: invokestatic a : (Ljava/lang/Throwable;)Ljava/lang/Throwable;
    //   2439: athrow
    //   2440: aload #19
    //   2442: iload #21
    //   2444: aload #19
    //   2446: iload #21
    //   2448: iconst_2
    //   2449: isub
    //   2450: iaload
    //   2451: bipush #17
    //   2453: iushr
    //   2454: aload #19
    //   2456: iload #21
    //   2458: iconst_2
    //   2459: isub
    //   2460: iaload
    //   2461: bipush #15
    //   2463: ishl
    //   2464: ior
    //   2465: aload #19
    //   2467: iload #21
    //   2469: iconst_2
    //   2470: isub
    //   2471: iaload
    //   2472: bipush #19
    //   2474: iushr
    //   2475: aload #19
    //   2477: iload #21
    //   2479: iconst_2
    //   2480: isub
    //   2481: iaload
    //   2482: bipush #13
    //   2484: ishl
    //   2485: ior
    //   2486: ixor
    //   2487: aload #19
    //   2489: iload #21
    //   2491: iconst_2
    //   2492: isub
    //   2493: iaload
    //   2494: bipush #10
    //   2496: iushr
    //   2497: ixor
    //   2498: aload #19
    //   2500: iload #21
    //   2502: bipush #7
    //   2504: isub
    //   2505: iaload
    //   2506: iadd
    //   2507: aload #19
    //   2509: iload #21
    //   2511: bipush #15
    //   2513: isub
    //   2514: iaload
    //   2515: bipush #7
    //   2517: iushr
    //   2518: aload #19
    //   2520: iload #21
    //   2522: bipush #15
    //   2524: isub
    //   2525: iaload
    //   2526: bipush #25
    //   2528: ishl
    //   2529: ior
    //   2530: aload #19
    //   2532: iload #21
    //   2534: bipush #15
    //   2536: isub
    //   2537: iaload
    //   2538: bipush #18
    //   2540: iushr
    //   2541: aload #19
    //   2543: iload #21
    //   2545: bipush #15
    //   2547: isub
    //   2548: iaload
    //   2549: bipush #14
    //   2551: ishl
    //   2552: ior
    //   2553: ixor
    //   2554: aload #19
    //   2556: iload #21
    //   2558: bipush #15
    //   2560: isub
    //   2561: iaload
    //   2562: iconst_3
    //   2563: iushr
    //   2564: ixor
    //   2565: iadd
    //   2566: aload #19
    //   2568: iload #21
    //   2570: bipush #16
    //   2572: isub
    //   2573: iaload
    //   2574: iadd
    //   2575: iastore
    //   2576: goto -> 2583
    //   2579: invokestatic a : (Ljava/lang/Throwable;)Ljava/lang/Throwable;
    //   2582: athrow
    //   2583: aload #20
    //   2585: bipush #7
    //   2587: iaload
    //   2588: aload #20
    //   2590: iconst_4
    //   2591: iaload
    //   2592: bipush #6
    //   2594: iushr
    //   2595: aload #20
    //   2597: iconst_4
    //   2598: iaload
    //   2599: bipush #26
    //   2601: ishl
    //   2602: ior
    //   2603: aload #20
    //   2605: iconst_4
    //   2606: iaload
    //   2607: bipush #11
    //   2609: iushr
    //   2610: aload #20
    //   2612: iconst_4
    //   2613: iaload
    //   2614: bipush #21
    //   2616: ishl
    //   2617: ior
    //   2618: ixor
    //   2619: aload #20
    //   2621: iconst_4
    //   2622: iaload
    //   2623: bipush #25
    //   2625: iushr
    //   2626: aload #20
    //   2628: iconst_4
    //   2629: iaload
    //   2630: bipush #7
    //   2632: ishl
    //   2633: ior
    //   2634: ixor
    //   2635: iadd
    //   2636: aload #20
    //   2638: bipush #6
    //   2640: iaload
    //   2641: aload #20
    //   2643: iconst_4
    //   2644: iaload
    //   2645: aload #20
    //   2647: iconst_5
    //   2648: iaload
    //   2649: aload #20
    //   2651: bipush #6
    //   2653: iaload
    //   2654: ixor
    //   2655: iand
    //   2656: ixor
    //   2657: iadd
    //   2658: aload #6
    //   2660: iload #21
    //   2662: iaload
    //   2663: iadd
    //   2664: aload #19
    //   2666: iload #21
    //   2668: iaload
    //   2669: iadd
    //   2670: istore #22
    //   2672: aload #20
    //   2674: iconst_0
    //   2675: iaload
    //   2676: iconst_2
    //   2677: iushr
    //   2678: aload #20
    //   2680: iconst_0
    //   2681: iaload
    //   2682: bipush #30
    //   2684: ishl
    //   2685: ior
    //   2686: aload #20
    //   2688: iconst_0
    //   2689: iaload
    //   2690: bipush #13
    //   2692: iushr
    //   2693: aload #20
    //   2695: iconst_0
    //   2696: iaload
    //   2697: bipush #19
    //   2699: ishl
    //   2700: ior
    //   2701: ixor
    //   2702: aload #20
    //   2704: iconst_0
    //   2705: iaload
    //   2706: bipush #22
    //   2708: iushr
    //   2709: aload #20
    //   2711: iconst_0
    //   2712: iaload
    //   2713: bipush #10
    //   2715: ishl
    //   2716: ior
    //   2717: ixor
    //   2718: aload #20
    //   2720: iconst_0
    //   2721: iaload
    //   2722: aload #20
    //   2724: iconst_1
    //   2725: iaload
    //   2726: iand
    //   2727: aload #20
    //   2729: iconst_2
    //   2730: iaload
    //   2731: aload #20
    //   2733: iconst_0
    //   2734: iaload
    //   2735: aload #20
    //   2737: iconst_1
    //   2738: iaload
    //   2739: ior
    //   2740: iand
    //   2741: ior
    //   2742: iadd
    //   2743: istore #23
    //   2745: aload #20
    //   2747: iconst_3
    //   2748: dup2
    //   2749: iaload
    //   2750: iload #22
    //   2752: iadd
    //   2753: iastore
    //   2754: aload #20
    //   2756: bipush #7
    //   2758: iload #22
    //   2760: iload #23
    //   2762: iadd
    //   2763: iastore
    //   2764: aload #20
    //   2766: bipush #7
    //   2768: iaload
    //   2769: istore #22
    //   2771: aload #20
    //   2773: bipush #7
    //   2775: aload #20
    //   2777: bipush #6
    //   2779: iaload
    //   2780: iastore
    //   2781: aload #20
    //   2783: bipush #6
    //   2785: aload #20
    //   2787: iconst_5
    //   2788: iaload
    //   2789: iastore
    //   2790: aload #20
    //   2792: iconst_5
    //   2793: aload #20
    //   2795: iconst_4
    //   2796: iaload
    //   2797: iastore
    //   2798: aload #20
    //   2800: iconst_4
    //   2801: aload #20
    //   2803: iconst_3
    //   2804: iaload
    //   2805: iastore
    //   2806: aload #20
    //   2808: iconst_3
    //   2809: aload #20
    //   2811: iconst_2
    //   2812: iaload
    //   2813: iastore
    //   2814: aload #20
    //   2816: iconst_2
    //   2817: aload #20
    //   2819: iconst_1
    //   2820: iaload
    //   2821: iastore
    //   2822: aload #20
    //   2824: iconst_1
    //   2825: aload #20
    //   2827: iconst_0
    //   2828: iaload
    //   2829: iastore
    //   2830: aload #20
    //   2832: iconst_0
    //   2833: iload #22
    //   2835: iastore
    //   2836: iinc #21, 1
    //   2839: iload_2
    //   2840: ifeq -> 2348
    //   2843: iconst_0
    //   2844: istore #21
    //   2846: iload #21
    //   2848: bipush #8
    //   2850: if_icmpge -> 2873
    //   2853: aload #8
    //   2855: iload #21
    //   2857: dup2
    //   2858: iaload
    //   2859: aload #20
    //   2861: iload #21
    //   2863: iaload
    //   2864: iadd
    //   2865: iastore
    //   2866: iinc #21, 1
    //   2869: iload_2
    //   2870: ifeq -> 2846
    //   2873: iinc #13, 64
    //   2876: iinc #17, -64
    //   2879: iload_2
    //   2880: ifeq -> 2269
    //   2883: iload #17
    //   2885: ifle -> 2921
    //   2888: iconst_0
    //   2889: istore #19
    //   2891: iload #19
    //   2893: iload #17
    //   2895: if_icmpge -> 2921
    //   2898: aload #9
    //   2900: iload #12
    //   2902: iload #19
    //   2904: iadd
    //   2905: aload #5
    //   2907: iload #13
    //   2909: iload #19
    //   2911: iadd
    //   2912: baload
    //   2913: bastore
    //   2914: iinc #19, 1
    //   2917: iload_2
    //   2918: ifeq -> 2891
    //   2921: bipush #8
    //   2923: newarray byte
    //   2925: astore #19
    //   2927: aload #19
    //   2929: iconst_0
    //   2930: iload #14
    //   2932: bipush #24
    //   2934: iushr
    //   2935: i2b
    //   2936: bastore
    //   2937: aload #19
    //   2939: iconst_1
    //   2940: iload #14
    //   2942: bipush #16
    //   2944: iushr
    //   2945: i2b
    //   2946: bastore
    //   2947: aload #19
    //   2949: iconst_2
    //   2950: iload #14
    //   2952: bipush #8
    //   2954: iushr
    //   2955: i2b
    //   2956: bastore
    //   2957: aload #19
    //   2959: iconst_3
    //   2960: iload #14
    //   2962: i2b
    //   2963: bastore
    //   2964: aload #19
    //   2966: iconst_4
    //   2967: iload #15
    //   2969: bipush #24
    //   2971: iushr
    //   2972: i2b
    //   2973: bastore
    //   2974: aload #19
    //   2976: iconst_5
    //   2977: iload #15
    //   2979: bipush #16
    //   2981: iushr
    //   2982: i2b
    //   2983: bastore
    //   2984: aload #19
    //   2986: bipush #6
    //   2988: iload #15
    //   2990: bipush #8
    //   2992: iushr
    //   2993: i2b
    //   2994: bastore
    //   2995: aload #19
    //   2997: bipush #7
    //   2999: iload #15
    //   3001: i2b
    //   3002: bastore
    //   3003: bipush #8
    //   3005: istore #11
    //   3007: aload #7
    //   3009: iconst_0
    //   3010: iaload
    //   3011: bipush #63
    //   3013: iand
    //   3014: istore #12
    //   3016: bipush #64
    //   3018: iload #12
    //   3020: isub
    //   3021: istore #18
    //   3023: aload #7
    //   3025: iconst_0
    //   3026: dup2
    //   3027: iaload
    //   3028: iload #11
    //   3030: iadd
    //   3031: iastore
    //   3032: aload #7
    //   3034: iconst_0
    //   3035: dup2
    //   3036: iaload
    //   3037: iconst_m1
    //   3038: iand
    //   3039: iastore
    //   3040: aload #7
    //   3042: iconst_0
    //   3043: iaload
    //   3044: iload #11
    //   3046: if_icmpge -> 3064
    //   3049: aload #7
    //   3051: iconst_1
    //   3052: dup2
    //   3053: iaload
    //   3054: iconst_1
    //   3055: iadd
    //   3056: iastore
    //   3057: goto -> 3064
    //   3060: invokestatic a : (Ljava/lang/Throwable;)Ljava/lang/Throwable;
    //   3063: athrow
    //   3064: iload #12
    //   3066: ifle -> 3680
    //   3069: iload #11
    //   3071: iload #18
    //   3073: if_icmplt -> 3680
    //   3076: goto -> 3083
    //   3079: invokestatic a : (Ljava/lang/Throwable;)Ljava/lang/Throwable;
    //   3082: athrow
    //   3083: iconst_0
    //   3084: istore #20
    //   3086: iload #20
    //   3088: iload #18
    //   3090: if_icmpge -> 3113
    //   3093: aload #9
    //   3095: iload #12
    //   3097: iload #20
    //   3099: iadd
    //   3100: aload #19
    //   3102: iload #20
    //   3104: baload
    //   3105: bastore
    //   3106: iinc #20, 1
    //   3109: iload_2
    //   3110: ifeq -> 3086
    //   3113: bipush #64
    //   3115: newarray int
    //   3117: astore #20
    //   3119: bipush #8
    //   3121: newarray int
    //   3123: astore #21
    //   3125: iconst_0
    //   3126: istore #22
    //   3128: iload #22
    //   3130: bipush #8
    //   3132: if_icmpge -> 3152
    //   3135: aload #21
    //   3137: iload #22
    //   3139: aload #8
    //   3141: iload #22
    //   3143: iaload
    //   3144: iastore
    //   3145: iinc #22, 1
    //   3148: iload_2
    //   3149: ifeq -> 3128
    //   3152: iconst_0
    //   3153: istore #22
    //   3155: iload #22
    //   3157: bipush #64
    //   3159: if_icmpge -> 3650
    //   3162: iload #22
    //   3164: bipush #16
    //   3166: if_icmpge -> 3247
    //   3169: aload #20
    //   3171: iload #22
    //   3173: aload #9
    //   3175: iconst_4
    //   3176: iload #22
    //   3178: imul
    //   3179: baload
    //   3180: sipush #255
    //   3183: iand
    //   3184: bipush #24
    //   3186: ishl
    //   3187: aload #9
    //   3189: iconst_4
    //   3190: iload #22
    //   3192: imul
    //   3193: iconst_1
    //   3194: iadd
    //   3195: baload
    //   3196: sipush #255
    //   3199: iand
    //   3200: bipush #16
    //   3202: ishl
    //   3203: ior
    //   3204: aload #9
    //   3206: iconst_4
    //   3207: iload #22
    //   3209: imul
    //   3210: iconst_2
    //   3211: iadd
    //   3212: baload
    //   3213: sipush #255
    //   3216: iand
    //   3217: bipush #8
    //   3219: ishl
    //   3220: ior
    //   3221: aload #9
    //   3223: iconst_4
    //   3224: iload #22
    //   3226: imul
    //   3227: iconst_3
    //   3228: iadd
    //   3229: baload
    //   3230: sipush #255
    //   3233: iand
    //   3234: ior
    //   3235: iastore
    //   3236: iload_2
    //   3237: ifeq -> 3390
    //   3240: goto -> 3247
    //   3243: invokestatic a : (Ljava/lang/Throwable;)Ljava/lang/Throwable;
    //   3246: athrow
    //   3247: aload #20
    //   3249: iload #22
    //   3251: aload #20
    //   3253: iload #22
    //   3255: iconst_2
    //   3256: isub
    //   3257: iaload
    //   3258: bipush #17
    //   3260: iushr
    //   3261: aload #20
    //   3263: iload #22
    //   3265: iconst_2
    //   3266: isub
    //   3267: iaload
    //   3268: bipush #15
    //   3270: ishl
    //   3271: ior
    //   3272: aload #20
    //   3274: iload #22
    //   3276: iconst_2
    //   3277: isub
    //   3278: iaload
    //   3279: bipush #19
    //   3281: iushr
    //   3282: aload #20
    //   3284: iload #22
    //   3286: iconst_2
    //   3287: isub
    //   3288: iaload
    //   3289: bipush #13
    //   3291: ishl
    //   3292: ior
    //   3293: ixor
    //   3294: aload #20
    //   3296: iload #22
    //   3298: iconst_2
    //   3299: isub
    //   3300: iaload
    //   3301: bipush #10
    //   3303: iushr
    //   3304: ixor
    //   3305: aload #20
    //   3307: iload #22
    //   3309: bipush #7
    //   3311: isub
    //   3312: iaload
    //   3313: iadd
    //   3314: aload #20
    //   3316: iload #22
    //   3318: bipush #15
    //   3320: isub
    //   3321: iaload
    //   3322: bipush #7
    //   3324: iushr
    //   3325: aload #20
    //   3327: iload #22
    //   3329: bipush #15
    //   3331: isub
    //   3332: iaload
    //   3333: bipush #25
    //   3335: ishl
    //   3336: ior
    //   3337: aload #20
    //   3339: iload #22
    //   3341: bipush #15
    //   3343: isub
    //   3344: iaload
    //   3345: bipush #18
    //   3347: iushr
    //   3348: aload #20
    //   3350: iload #22
    //   3352: bipush #15
    //   3354: isub
    //   3355: iaload
    //   3356: bipush #14
    //   3358: ishl
    //   3359: ior
    //   3360: ixor
    //   3361: aload #20
    //   3363: iload #22
    //   3365: bipush #15
    //   3367: isub
    //   3368: iaload
    //   3369: iconst_3
    //   3370: iushr
    //   3371: ixor
    //   3372: iadd
    //   3373: aload #20
    //   3375: iload #22
    //   3377: bipush #16
    //   3379: isub
    //   3380: iaload
    //   3381: iadd
    //   3382: iastore
    //   3383: goto -> 3390
    //   3386: invokestatic a : (Ljava/lang/Throwable;)Ljava/lang/Throwable;
    //   3389: athrow
    //   3390: aload #21
    //   3392: bipush #7
    //   3394: iaload
    //   3395: aload #21
    //   3397: iconst_4
    //   3398: iaload
    //   3399: bipush #6
    //   3401: iushr
    //   3402: aload #21
    //   3404: iconst_4
    //   3405: iaload
    //   3406: bipush #26
    //   3408: ishl
    //   3409: ior
    //   3410: aload #21
    //   3412: iconst_4
    //   3413: iaload
    //   3414: bipush #11
    //   3416: iushr
    //   3417: aload #21
    //   3419: iconst_4
    //   3420: iaload
    //   3421: bipush #21
    //   3423: ishl
    //   3424: ior
    //   3425: ixor
    //   3426: aload #21
    //   3428: iconst_4
    //   3429: iaload
    //   3430: bipush #25
    //   3432: iushr
    //   3433: aload #21
    //   3435: iconst_4
    //   3436: iaload
    //   3437: bipush #7
    //   3439: ishl
    //   3440: ior
    //   3441: ixor
    //   3442: iadd
    //   3443: aload #21
    //   3445: bipush #6
    //   3447: iaload
    //   3448: aload #21
    //   3450: iconst_4
    //   3451: iaload
    //   3452: aload #21
    //   3454: iconst_5
    //   3455: iaload
    //   3456: aload #21
    //   3458: bipush #6
    //   3460: iaload
    //   3461: ixor
    //   3462: iand
    //   3463: ixor
    //   3464: iadd
    //   3465: aload #6
    //   3467: iload #22
    //   3469: iaload
    //   3470: iadd
    //   3471: aload #20
    //   3473: iload #22
    //   3475: iaload
    //   3476: iadd
    //   3477: istore #23
    //   3479: aload #21
    //   3481: iconst_0
    //   3482: iaload
    //   3483: iconst_2
    //   3484: iushr
    //   3485: aload #21
    //   3487: iconst_0
    //   3488: iaload
    //   3489: bipush #30
    //   3491: ishl
    //   3492: ior
    //   3493: aload #21
    //   3495: iconst_0
    //   3496: iaload
    //   3497: bipush #13
    //   3499: iushr
    //   3500: aload #21
    //   3502: iconst_0
    //   3503: iaload
    //   3504: bipush #19
    //   3506: ishl
    //   3507: ior
    //   3508: ixor
    //   3509: aload #21
    //   3511: iconst_0
    //   3512: iaload
    //   3513: bipush #22
    //   3515: iushr
    //   3516: aload #21
    //   3518: iconst_0
    //   3519: iaload
    //   3520: bipush #10
    //   3522: ishl
    //   3523: ior
    //   3524: ixor
    //   3525: aload #21
    //   3527: iconst_0
    //   3528: iaload
    //   3529: aload #21
    //   3531: iconst_1
    //   3532: iaload
    //   3533: iand
    //   3534: aload #21
    //   3536: iconst_2
    //   3537: iaload
    //   3538: aload #21
    //   3540: iconst_0
    //   3541: iaload
    //   3542: aload #21
    //   3544: iconst_1
    //   3545: iaload
    //   3546: ior
    //   3547: iand
    //   3548: ior
    //   3549: iadd
    //   3550: istore #24
    //   3552: aload #21
    //   3554: iconst_3
    //   3555: dup2
    //   3556: iaload
    //   3557: iload #23
    //   3559: iadd
    //   3560: iastore
    //   3561: aload #21
    //   3563: bipush #7
    //   3565: iload #23
    //   3567: iload #24
    //   3569: iadd
    //   3570: iastore
    //   3571: aload #21
    //   3573: bipush #7
    //   3575: iaload
    //   3576: istore #23
    //   3578: aload #21
    //   3580: bipush #7
    //   3582: aload #21
    //   3584: bipush #6
    //   3586: iaload
    //   3587: iastore
    //   3588: aload #21
    //   3590: bipush #6
    //   3592: aload #21
    //   3594: iconst_5
    //   3595: iaload
    //   3596: iastore
    //   3597: aload #21
    //   3599: iconst_5
    //   3600: aload #21
    //   3602: iconst_4
    //   3603: iaload
    //   3604: iastore
    //   3605: aload #21
    //   3607: iconst_4
    //   3608: aload #21
    //   3610: iconst_3
    //   3611: iaload
    //   3612: iastore
    //   3613: aload #21
    //   3615: iconst_3
    //   3616: aload #21
    //   3618: iconst_2
    //   3619: iaload
    //   3620: iastore
    //   3621: aload #21
    //   3623: iconst_2
    //   3624: aload #21
    //   3626: iconst_1
    //   3627: iaload
    //   3628: iastore
    //   3629: aload #21
    //   3631: iconst_1
    //   3632: aload #21
    //   3634: iconst_0
    //   3635: iaload
    //   3636: iastore
    //   3637: aload #21
    //   3639: iconst_0
    //   3640: iload #23
    //   3642: iastore
    //   3643: iinc #22, 1
    //   3646: iload_2
    //   3647: ifeq -> 3155
    //   3650: iconst_0
    //   3651: istore #22
    //   3653: iload #22
    //   3655: bipush #8
    //   3657: if_icmpge -> 3680
    //   3660: aload #8
    //   3662: iload #22
    //   3664: dup2
    //   3665: iaload
    //   3666: aload #21
    //   3668: iload #22
    //   3670: iaload
    //   3671: iadd
    //   3672: iastore
    //   3673: iinc #22, 1
    //   3676: iload_2
    //   3677: ifeq -> 3653
    //   3680: bipush #32
    //   3682: newarray byte
    //   3684: astore #4
    //   3686: sipush #-15409
    //   3689: aload #4
    //   3691: iconst_0
    //   3692: aload #8
    //   3694: iconst_0
    //   3695: iaload
    //   3696: bipush #24
    //   3698: iushr
    //   3699: i2b
    //   3700: bastore
    //   3701: bipush #-54
    //   3703: aload #4
    //   3705: iconst_1
    //   3706: aload #8
    //   3708: iconst_0
    //   3709: iaload
    //   3710: bipush #16
    //   3712: iushr
    //   3713: i2b
    //   3714: bastore
    //   3715: aload #4
    //   3717: iconst_2
    //   3718: aload #8
    //   3720: iconst_0
    //   3721: iaload
    //   3722: bipush #8
    //   3724: iushr
    //   3725: i2b
    //   3726: bastore
    //   3727: aload #4
    //   3729: iconst_3
    //   3730: aload #8
    //   3732: iconst_0
    //   3733: iaload
    //   3734: i2b
    //   3735: bastore
    //   3736: aload #4
    //   3738: iconst_4
    //   3739: aload #8
    //   3741: iconst_1
    //   3742: iaload
    //   3743: bipush #24
    //   3745: iushr
    //   3746: i2b
    //   3747: bastore
    //   3748: aload #4
    //   3750: iconst_5
    //   3751: aload #8
    //   3753: iconst_1
    //   3754: iaload
    //   3755: bipush #16
    //   3757: iushr
    //   3758: i2b
    //   3759: bastore
    //   3760: aload #4
    //   3762: bipush #6
    //   3764: aload #8
    //   3766: iconst_1
    //   3767: iaload
    //   3768: bipush #8
    //   3770: iushr
    //   3771: i2b
    //   3772: bastore
    //   3773: aload #4
    //   3775: bipush #7
    //   3777: aload #8
    //   3779: iconst_1
    //   3780: iaload
    //   3781: i2b
    //   3782: bastore
    //   3783: aload #4
    //   3785: bipush #8
    //   3787: aload #8
    //   3789: iconst_2
    //   3790: iaload
    //   3791: bipush #24
    //   3793: iushr
    //   3794: i2b
    //   3795: bastore
    //   3796: aload #4
    //   3798: bipush #9
    //   3800: aload #8
    //   3802: iconst_2
    //   3803: iaload
    //   3804: bipush #16
    //   3806: iushr
    //   3807: i2b
    //   3808: bastore
    //   3809: aload #4
    //   3811: bipush #10
    //   3813: aload #8
    //   3815: iconst_2
    //   3816: iaload
    //   3817: bipush #8
    //   3819: iushr
    //   3820: i2b
    //   3821: bastore
    //   3822: aload #4
    //   3824: bipush #11
    //   3826: aload #8
    //   3828: iconst_2
    //   3829: iaload
    //   3830: i2b
    //   3831: bastore
    //   3832: aload #4
    //   3834: bipush #12
    //   3836: aload #8
    //   3838: iconst_3
    //   3839: iaload
    //   3840: bipush #24
    //   3842: iushr
    //   3843: i2b
    //   3844: bastore
    //   3845: aload #4
    //   3847: bipush #13
    //   3849: aload #8
    //   3851: iconst_3
    //   3852: iaload
    //   3853: bipush #16
    //   3855: iushr
    //   3856: i2b
    //   3857: bastore
    //   3858: aload #4
    //   3860: bipush #14
    //   3862: aload #8
    //   3864: iconst_3
    //   3865: iaload
    //   3866: bipush #8
    //   3868: iushr
    //   3869: i2b
    //   3870: bastore
    //   3871: aload #4
    //   3873: bipush #15
    //   3875: aload #8
    //   3877: iconst_3
    //   3878: iaload
    //   3879: i2b
    //   3880: bastore
    //   3881: aload #4
    //   3883: bipush #16
    //   3885: aload #8
    //   3887: iconst_4
    //   3888: iaload
    //   3889: bipush #24
    //   3891: iushr
    //   3892: i2b
    //   3893: bastore
    //   3894: aload #4
    //   3896: bipush #17
    //   3898: aload #8
    //   3900: iconst_4
    //   3901: iaload
    //   3902: bipush #16
    //   3904: iushr
    //   3905: i2b
    //   3906: bastore
    //   3907: aload #4
    //   3909: bipush #18
    //   3911: aload #8
    //   3913: iconst_4
    //   3914: iaload
    //   3915: bipush #8
    //   3917: iushr
    //   3918: i2b
    //   3919: bastore
    //   3920: aload #4
    //   3922: bipush #19
    //   3924: aload #8
    //   3926: iconst_4
    //   3927: iaload
    //   3928: i2b
    //   3929: bastore
    //   3930: aload #4
    //   3932: bipush #20
    //   3934: aload #8
    //   3936: iconst_5
    //   3937: iaload
    //   3938: bipush #24
    //   3940: iushr
    //   3941: i2b
    //   3942: bastore
    //   3943: aload #4
    //   3945: bipush #21
    //   3947: aload #8
    //   3949: iconst_5
    //   3950: iaload
    //   3951: bipush #16
    //   3953: iushr
    //   3954: i2b
    //   3955: bastore
    //   3956: aload #4
    //   3958: bipush #22
    //   3960: aload #8
    //   3962: iconst_5
    //   3963: iaload
    //   3964: bipush #8
    //   3966: iushr
    //   3967: i2b
    //   3968: bastore
    //   3969: aload #4
    //   3971: bipush #23
    //   3973: aload #8
    //   3975: iconst_5
    //   3976: iaload
    //   3977: i2b
    //   3978: bastore
    //   3979: aload #4
    //   3981: bipush #24
    //   3983: aload #8
    //   3985: bipush #6
    //   3987: iaload
    //   3988: bipush #24
    //   3990: iushr
    //   3991: i2b
    //   3992: bastore
    //   3993: aload #4
    //   3995: bipush #25
    //   3997: aload #8
    //   3999: bipush #6
    //   4001: iaload
    //   4002: bipush #16
    //   4004: iushr
    //   4005: i2b
    //   4006: bastore
    //   4007: aload #4
    //   4009: bipush #26
    //   4011: aload #8
    //   4013: bipush #6
    //   4015: iaload
    //   4016: bipush #8
    //   4018: iushr
    //   4019: i2b
    //   4020: bastore
    //   4021: aload #4
    //   4023: bipush #27
    //   4025: aload #8
    //   4027: bipush #6
    //   4029: iaload
    //   4030: i2b
    //   4031: bastore
    //   4032: aload #4
    //   4034: bipush #28
    //   4036: aload #8
    //   4038: bipush #7
    //   4040: iaload
    //   4041: bipush #24
    //   4043: iushr
    //   4044: i2b
    //   4045: bastore
    //   4046: aload #4
    //   4048: bipush #29
    //   4050: aload #8
    //   4052: bipush #7
    //   4054: iaload
    //   4055: bipush #16
    //   4057: iushr
    //   4058: i2b
    //   4059: bastore
    //   4060: aload #4
    //   4062: bipush #30
    //   4064: aload #8
    //   4066: bipush #7
    //   4068: iaload
    //   4069: bipush #8
    //   4071: iushr
    //   4072: i2b
    //   4073: bastore
    //   4074: aload #4
    //   4076: bipush #31
    //   4078: aload #8
    //   4080: bipush #7
    //   4082: iaload
    //   4083: i2b
    //   4084: bastore
    //   4085: new java/math/BigInteger
    //   4088: dup
    //   4089: aload #4
    //   4091: invokespecial <init> : ([B)V
    //   4094: invokevirtual abs : ()Ljava/math/BigInteger;
    //   4097: putstatic burp/Zs36.Zs : Ljava/lang/Object;
    //   4100: invokestatic a : (II)Ljava/lang/String;
    //   4103: iconst_1
    //   4104: ldc burp/Zlbr
    //   4106: invokevirtual getClassLoader : ()Ljava/lang/ClassLoader;
    //   4109: invokestatic forName : (Ljava/lang/String;ZLjava/lang/ClassLoader;)Ljava/lang/Class;
    //   4112: invokevirtual getDeclaredFields : ()[Ljava/lang/reflect/Field;
    //   4115: astore_3
    //   4116: aload_3
    //   4117: arraylength
    //   4118: istore #4
    //   4120: iconst_0
    //   4121: istore #5
    //   4123: iload #5
    //   4125: iload #4
    //   4127: if_icmpge -> 4264
    //   4130: aload_3
    //   4131: iload #5
    //   4133: aaload
    //   4134: astore #6
    //   4136: aload #6
    //   4138: invokevirtual getModifiers : ()I
    //   4141: invokestatic isStatic : (I)Z
    //   4144: ifne -> 4154
    //   4147: goto -> 4257
    //   4150: invokestatic a : (Ljava/lang/Throwable;)Ljava/lang/Throwable;
    //   4153: athrow
    //   4154: aload #6
    //   4156: invokevirtual getType : ()Ljava/lang/Class;
    //   4159: astore #7
    //   4161: aload #7
    //   4163: ifnull -> 4244
    //   4166: aload #7
    //   4168: invokevirtual isPrimitive : ()Z
    //   4171: ifne -> 4244
    //   4174: goto -> 4181
    //   4177: invokestatic a : (Ljava/lang/Throwable;)Ljava/lang/Throwable;
    //   4180: athrow
    //   4181: aload #7
    //   4183: invokevirtual getPackage : ()Ljava/lang/Package;
    //   4186: ifnull -> 4244
    //   4189: goto -> 4196
    //   4192: invokestatic a : (Ljava/lang/Throwable;)Ljava/lang/Throwable;
    //   4195: athrow
    //   4196: aload #7
    //   4198: invokevirtual getPackage : ()Ljava/lang/Package;
    //   4201: invokevirtual getName : ()Ljava/lang/String;
    //   4204: ifnull -> 4244
    //   4207: goto -> 4214
    //   4210: invokestatic a : (Ljava/lang/Throwable;)Ljava/lang/Throwable;
    //   4213: athrow
    //   4214: aload #7
    //   4216: invokevirtual getPackage : ()Ljava/lang/Package;
    //   4219: invokevirtual getName : ()Ljava/lang/String;
    //   4222: sipush #-15422
    //   4225: sipush #19309
    //   4228: invokestatic a : (II)Ljava/lang/String;
    //   4231: invokevirtual startsWith : (Ljava/lang/String;)Z
    //   4234: ifne -> 4244
    //   4237: goto -> 4244
    //   4240: invokestatic a : (Ljava/lang/Throwable;)Ljava/lang/Throwable;
    //   4243: athrow
    //   4244: aload #6
    //   4246: iconst_1
    //   4247: invokevirtual setAccessible : (Z)V
    //   4250: aload #6
    //   4252: aconst_null
    //   4253: invokevirtual get : (Ljava/lang/Object;)Ljava/lang/Object;
    //   4256: pop
    //   4257: iinc #5, 1
    //   4260: iload_2
    //   4261: ifeq -> 4123
    //   4264: sipush #-15413
    //   4267: sipush #-8773
    //   4270: invokestatic a : (II)Ljava/lang/String;
    //   4273: invokestatic forName : (Ljava/lang/String;)Ljava/lang/Class;
    //   4276: invokevirtual getDeclaredMethods : ()[Ljava/lang/reflect/Method;
    //   4279: astore_3
    //   4280: aload_3
    //   4281: arraylength
    //   4282: istore #4
    //   4284: iconst_0
    //   4285: istore #5
    //   4287: iload #5
    //   4289: iload #4
    //   4291: if_icmpge -> 4423
    //   4294: aload_3
    //   4295: iload #5
    //   4297: aaload
    //   4298: astore #6
    //   4300: aload #6
    //   4302: invokevirtual getParameterTypes : ()[Ljava/lang/Class;
    //   4305: pop
    //   4306: aload #6
    //   4308: invokevirtual getModifiers : ()I
    //   4311: invokestatic isStatic : (I)Z
    //   4314: ifeq -> 4409
    //   4317: aload #6
    //   4319: invokevirtual getParameterTypes : ()[Ljava/lang/Class;
    //   4322: arraylength
    //   4323: iconst_2
    //   4324: if_icmpne -> 4409
    //   4327: goto -> 4334
    //   4330: invokestatic a : (Ljava/lang/Throwable;)Ljava/lang/Throwable;
    //   4333: athrow
    //   4334: aload #6
    //   4336: invokevirtual getReturnType : ()Ljava/lang/Class;
    //   4339: getstatic java/lang/Void.TYPE : Ljava/lang/Class;
    //   4342: invokevirtual equals : (Ljava/lang/Object;)Z
    //   4345: ifeq -> 4409
    //   4348: goto -> 4355
    //   4351: invokestatic a : (Ljava/lang/Throwable;)Ljava/lang/Throwable;
    //   4354: athrow
    //   4355: aload #6
    //   4357: iconst_1
    //   4358: invokevirtual setAccessible : (Z)V
    //   4361: aload #6
    //   4363: aconst_null
    //   4364: iconst_2
    //   4365: anewarray java/lang/Object
    //   4368: dup
    //   4369: iconst_0
    //   4370: aload_0
    //   4371: aastore
    //   4372: dup
    //   4373: iconst_1
    //   4374: aload_1
    //   4375: ifnonnull -> 4393
    //   4378: goto -> 4385
    //   4381: invokestatic a : (Ljava/lang/Throwable;)Ljava/lang/Throwable;
    //   4384: athrow
    //   4385: aload_1
    //   4386: goto -> 4400
    //   4389: invokestatic a : (Ljava/lang/Throwable;)Ljava/lang/Throwable;
    //   4392: athrow
    //   4393: aload_1
    //   4394: checkcast [B
    //   4397: invokevirtual clone : ()Ljava/lang/Object;
    //   4400: aastore
    //   4401: invokevirtual invoke : (Ljava/lang/Object;[Ljava/lang/Object;)Ljava/lang/Object;
    //   4404: pop
    //   4405: iload_2
    //   4406: ifeq -> 4423
    //   4409: iinc #5, 1
    //   4412: iload_2
    //   4413: ifeq -> 4287
    //   4416: goto -> 4423
    //   4419: invokestatic a : (Ljava/lang/Throwable;)Ljava/lang/Throwable;
    //   4422: athrow
    //   4423: getstatic burp/Zlyf.Zm : Ljava/lang/Object;
    //   4426: checkcast java/math/BigInteger
    //   4429: invokevirtual toByteArray : ()[B
    //   4432: astore_3
    //   4433: new java/lang/StringBuilder
    //   4436: dup
    //   4437: invokespecial <init> : ()V
    //   4440: astore #5
    //   4442: aload #5
    //   4444: sipush #-15408
    //   4447: sipush #-5325
    //   4450: invokestatic a : (II)Ljava/lang/String;
    //   4453: invokevirtual append : (Ljava/lang/String;)Ljava/lang/StringBuilder;
    //   4456: pop
    //   4457: aload_3
    //   4458: astore #6
    //   4460: aload #6
    //   4462: arraylength
    //   4463: istore #7
    //   4465: iconst_0
    //   4466: istore #8
    //   4468: iload #8
    //   4470: iload #7
    //   4472: if_icmpge -> 4498
    //   4475: aload #6
    //   4477: iload #8
    //   4479: baload
    //   4480: istore #9
    //   4482: aload #5
    //   4484: iload #9
    //   4486: i2c
    //   4487: invokevirtual append : (C)Ljava/lang/StringBuilder;
    //   4490: pop
    //   4491: iinc #8, 1
    //   4494: iload_2
    //   4495: ifeq -> 4468
    //   4498: aload #5
    //   4500: sipush #-15416
    //   4503: sipush #1662
    //   4506: invokestatic a : (II)Ljava/lang/String;
    //   4509: ldc ''
    //   4511: invokestatic getProperty : (Ljava/lang/String;Ljava/lang/String;)Ljava/lang/String;
    //   4514: invokevirtual toLowerCase : ()Ljava/lang/String;
    //   4517: invokevirtual append : (Ljava/lang/String;)Ljava/lang/StringBuilder;
    //   4520: pop
    //   4521: aload #5
    //   4523: sipush #-15406
    //   4526: sipush #-30548
    //   4529: invokestatic a : (II)Ljava/lang/String;
    //   4532: ldc ''
    //   4534: invokestatic getProperty : (Ljava/lang/String;Ljava/lang/String;)Ljava/lang/String;
    //   4537: invokevirtual toLowerCase : ()Ljava/lang/String;
    //   4540: invokevirtual append : (Ljava/lang/String;)Ljava/lang/StringBuilder;
    //   4543: pop
    //   4544: aload #5
    //   4546: invokevirtual toString : ()Ljava/lang/String;
    //   4549: invokevirtual getBytes : ()[B
    //   4552: astore #4
    //   4554: aload #4
    //   4556: astore_3
    //   4557: aload_3
    //   4558: arraylength
    //   4559: bipush #8
    //   4561: iadd
    //   4562: bipush #6
    //   4564: ishr
    //   4565: iconst_1
    //   4566: iadd
    //   4567: bipush #16
    //   4569: imul
    //   4570: newarray int
    //   4572: astore #5
    //   4574: iconst_0
    //   4575: istore #6
    //   4577: iload #6
    //   4579: aload_3
    //   4580: arraylength
    //   4581: if_icmpge -> 4624
    //   4584: aload_3
    //   4585: iload #6
    //   4587: baload
    //   4588: sipush #255
    //   4591: iand
    //   4592: istore #7
    //   4594: aload #5
    //   4596: iload #6
    //   4598: iconst_2
    //   4599: ishr
    //   4600: dup2
    //   4601: iaload
    //   4602: iload #7
    //   4604: bipush #24
    //   4606: iload #6
    //   4608: iconst_4
    //   4609: irem
    //   4610: bipush #8
    //   4612: imul
    //   4613: isub
    //   4614: ishl
    //   4615: ior
    //   4616: iastore
    //   4617: iinc #6, 1
    //   4620: iload_2
    //   4621: ifeq -> 4577
    //   4624: aload #5
    //   4626: iload #6
    //   4628: iconst_2
    //   4629: ishr
    //   4630: dup2
    //   4631: iaload
    //   4632: sipush #128
    //   4635: bipush #24
    //   4637: iload #6
    //   4639: iconst_4
    //   4640: irem
    //   4641: bipush #8
    //   4643: imul
    //   4644: isub
    //   4645: ishl
    //   4646: ior
    //   4647: iastore
    //   4648: aload #5
    //   4650: aload #5
    //   4652: arraylength
    //   4653: iconst_1
    //   4654: isub
    //   4655: aload_3
    //   4656: arraylength
    //   4657: bipush #8
    //   4659: imul
    //   4660: iastore
    //   4661: bipush #80
    //   4663: newarray int
    //   4665: astore #7
    //   4667: ldc 1732584193
    //   4669: istore #8
    //   4671: ldc -271733879
    //   4673: istore #9
    //   4675: ldc -1732584194
    //   4677: istore #10
    //   4679: ldc 271733878
    //   4681: istore #11
    //   4683: ldc -1009589776
    //   4685: istore #12
    //   4687: iconst_0
    //   4688: istore #6
    //   4690: iload #6
    //   4692: aload #5
    //   4694: arraylength
    //   4695: if_icmpge -> 5017
    //   4698: iload #8
    //   4700: istore #13
    //   4702: iload #9
    //   4704: istore #14
    //   4706: iload #10
    //   4708: istore #15
    //   4710: iload #11
    //   4712: istore #16
    //   4714: iload #12
    //   4716: istore #17
    //   4718: iconst_0
    //   4719: istore #18
    //   4721: iload #18
    //   4723: bipush #80
    //   4725: if_icmpge -> 4975
    //   4728: iload #18
    //   4730: bipush #16
    //   4732: if_icmpge -> 4759
    //   4735: aload #7
    //   4737: iload #18
    //   4739: aload #5
    //   4741: iload #6
    //   4743: iload #18
    //   4745: iadd
    //   4746: iaload
    //   4747: iastore
    //   4748: iload_2
    //   4749: ifeq -> 4814
    //   4752: goto -> 4759
    //   4755: invokestatic a : (Ljava/lang/Throwable;)Ljava/lang/Throwable;
    //   4758: athrow
    //   4759: aload #7
    //   4761: iload #18
    //   4763: iconst_3
    //   4764: isub
    //   4765: iaload
    //   4766: aload #7
    //   4768: iload #18
    //   4770: bipush #8
    //   4772: isub
    //   4773: iaload
    //   4774: ixor
    //   4775: aload #7
    //   4777: iload #18
    //   4779: bipush #14
    //   4781: isub
    //   4782: iaload
    //   4783: ixor
    //   4784: aload #7
    //   4786: iload #18
    //   4788: bipush #16
    //   4790: isub
    //   4791: iaload
    //   4792: ixor
    //   4793: istore #19
    //   4795: iload #19
    //   4797: iconst_1
    //   4798: ishl
    //   4799: iload #19
    //   4801: bipush #31
    //   4803: iushr
    //   4804: ior
    //   4805: istore #20
    //   4807: aload #7
    //   4809: iload #18
    //   4811: iload #20
    //   4813: iastore
    //   4814: iload #8
    //   4816: iconst_5
    //   4817: ishl
    //   4818: iload #8
    //   4820: bipush #27
    //   4822: iushr
    //   4823: ior
    //   4824: istore #19
    //   4826: iload #19
    //   4828: iload #12
    //   4830: iadd
    //   4831: aload #7
    //   4833: iload #18
    //   4835: iaload
    //   4836: iadd
    //   4837: iload #18
    //   4839: bipush #20
    //   4841: if_icmpge -> 4867
    //   4844: ldc 1518500249
    //   4846: iload #9
    //   4848: iload #10
    //   4850: iand
    //   4851: iload #9
    //   4853: iconst_m1
    //   4854: ixor
    //   4855: iload #11
    //   4857: iand
    //   4858: ior
    //   4859: iadd
    //   4860: goto -> 4937
    //   4863: invokestatic a : (Ljava/lang/Throwable;)Ljava/lang/Throwable;
    //   4866: athrow
    //   4867: iload #18
    //   4869: bipush #40
    //   4871: if_icmpge -> 4892
    //   4874: ldc 1859775393
    //   4876: iload #9
    //   4878: iload #10
    //   4880: ixor
    //   4881: iload #11
    //   4883: ixor
    //   4884: iadd
    //   4885: goto -> 4937
    //   4888: invokestatic a : (Ljava/lang/Throwable;)Ljava/lang/Throwable;
    //   4891: athrow
    //   4892: iload #18
    //   4894: bipush #60
    //   4896: if_icmpge -> 4926
    //   4899: ldc -1894007588
    //   4901: iload #9
    //   4903: iload #10
    //   4905: iand
    //   4906: iload #9
    //   4908: iload #11
    //   4910: iand
    //   4911: ior
    //   4912: iload #10
    //   4914: iload #11
    //   4916: iand
    //   4917: ior
    //   4918: iadd
    //   4919: goto -> 4937
    //   4922: invokestatic a : (Ljava/lang/Throwable;)Ljava/lang/Throwable;
    //   4925: athrow
    //   4926: ldc -899497514
    //   4928: iload #9
    //   4930: iload #10
    //   4932: ixor
    //   4933: iload #11
    //   4935: ixor
    //   4936: iadd
    //   4937: iadd
    //   4938: istore #20
    //   4940: iload #11
    //   4942: istore #12
    //   4944: iload #10
    //   4946: istore #11
    //   4948: iload #9
    //   4950: bipush #30
    //   4952: ishl
    //   4953: iload #9
    //   4955: iconst_2
    //   4956: iushr
    //   4957: ior
    //   4958: istore #10
    //   4960: iload #8
    //   4962: istore #9
    //   4964: iload #20
    //   4966: istore #8
    //   4968: iinc #18, 1
    //   4971: iload_2
    //   4972: ifeq -> 4721
    //   4975: iload #8
    //   4977: iload #13
    //   4979: iadd
    //   4980: istore #8
    //   4982: iload #9
    //   4984: iload #14
    //   4986: iadd
    //   4987: istore #9
    //   4989: iload #10
    //   4991: iload #15
    //   4993: iadd
    //   4994: istore #10
    //   4996: iload #11
    //   4998: iload #16
    //   5000: iadd
    //   5001: istore #11
    //   5003: iload #12
    //   5005: iload #17
    //   5007: iadd
    //   5008: istore #12
    //   5010: iinc #6, 16
    //   5013: iload_2
    //   5014: ifeq -> 4690
    //   5017: iconst_5
    //   5018: newarray int
    //   5020: dup
    //   5021: iconst_0
    //   5022: iload #8
    //   5024: iastore
    //   5025: dup
    //   5026: iconst_1
    //   5027: iload #9
    //   5029: iastore
    //   5030: dup
    //   5031: iconst_2
    //   5032: iload #10
    //   5034: iastore
    //   5035: dup
    //   5036: iconst_3
    //   5037: iload #11
    //   5039: iastore
    //   5040: dup
    //   5041: iconst_4
    //   5042: iload #12
    //   5044: iastore
    //   5045: astore #13
    //   5047: bipush #20
    //   5049: newarray byte
    //   5051: astore #14
    //   5053: iconst_0
    //   5054: istore #15
    //   5056: iload #15
    //   5058: bipush #20
    //   5060: if_icmpge -> 5101
    //   5063: aload #13
    //   5065: iload #15
    //   5067: iconst_4
    //   5068: idiv
    //   5069: iaload
    //   5070: istore #16
    //   5072: iconst_3
    //   5073: iload #15
    //   5075: iconst_4
    //   5076: irem
    //   5077: isub
    //   5078: bipush #8
    //   5080: imul
    //   5081: istore #17
    //   5083: aload #14
    //   5085: iload #15
    //   5087: iload #16
    //   5089: iload #17
    //   5091: iushr
    //   5092: i2b
    //   5093: bastore
    //   5094: iinc #15, 1
    //   5097: iload_2
    //   5098: ifeq -> 5056
    //   5101: aload #14
    //   5103: astore #4
    //   5105: iconst_0
    //   5106: istore_3
    //   5107: getstatic burp/Zz9p.ZC : Ljava/lang/String;
    //   5110: getstatic burp/Ztte.ZR : Ljava/lang/Object;
    //   5113: checkcast java/math/BigInteger
    //   5116: invokevirtual intValue : ()I
    //   5119: bipush #32
    //   5121: irem
    //   5122: invokestatic abs : (I)I
    //   5125: invokevirtual charAt : (I)C
    //   5128: getstatic burp/Zkvr.Zm : Ljava/lang/String;
    //   5131: getstatic burp/Zly0.ZB : Ljava/lang/Object;
    //   5134: checkcast java/math/BigInteger
    //   5137: invokevirtual intValue : ()I
    //   5140: bipush #32
    //   5142: irem
    //   5143: invokestatic abs : (I)I
    //   5146: invokevirtual charAt : (I)C
    //   5149: if_icmple -> 5493
    //   5152: sipush #-15402
    //   5155: sipush #28020
    //   5158: invokestatic a : (II)Ljava/lang/String;
    //   5161: iconst_1
    //   5162: ldc burp/Zec0
    //   5164: invokevirtual getClassLoader : ()Ljava/lang/ClassLoader;
    //   5167: invokestatic forName : (Ljava/lang/String;ZLjava/lang/ClassLoader;)Ljava/lang/Class;
    //   5170: invokevirtual getDeclaredFields : ()[Ljava/lang/reflect/Field;
    //   5173: astore #4
    //   5175: aload #4
    //   5177: arraylength
    //   5178: istore #5
    //   5180: iconst_0
    //   5181: istore #6
    //   5183: iload #6
    //   5185: iload #5
    //   5187: if_icmpge -> 5325
    //   5190: aload #4
    //   5192: iload #6
    //   5194: aaload
    //   5195: astore #7
    //   5197: aload #7
    //   5199: invokevirtual getModifiers : ()I
    //   5202: invokestatic isStatic : (I)Z
    //   5205: ifne -> 5215
    //   5208: goto -> 5318
    //   5211: invokestatic a : (Ljava/lang/Throwable;)Ljava/lang/Throwable;
    //   5214: athrow
    //   5215: aload #7
    //   5217: invokevirtual getType : ()Ljava/lang/Class;
    //   5220: astore #8
    //   5222: aload #8
    //   5224: ifnull -> 5305
    //   5227: aload #8
    //   5229: invokevirtual isPrimitive : ()Z
    //   5232: ifne -> 5305
    //   5235: goto -> 5242
    //   5238: invokestatic a : (Ljava/lang/Throwable;)Ljava/lang/Throwable;
    //   5241: athrow
    //   5242: aload #8
    //   5244: invokevirtual getPackage : ()Ljava/lang/Package;
    //   5247: ifnull -> 5305
    //   5250: goto -> 5257
    //   5253: invokestatic a : (Ljava/lang/Throwable;)Ljava/lang/Throwable;
    //   5256: athrow
    //   5257: aload #8
    //   5259: invokevirtual getPackage : ()Ljava/lang/Package;
    //   5262: invokevirtual getName : ()Ljava/lang/String;
    //   5265: ifnull -> 5305
    //   5268: goto -> 5275
    //   5271: invokestatic a : (Ljava/lang/Throwable;)Ljava/lang/Throwable;
    //   5274: athrow
    //   5275: aload #8
    //   5277: invokevirtual getPackage : ()Ljava/lang/Package;
    //   5280: invokevirtual getName : ()Ljava/lang/String;
    //   5283: sipush #-15407
    //   5286: sipush #-22402
    //   5289: invokestatic a : (II)Ljava/lang/String;
    //   5292: invokevirtual startsWith : (Ljava/lang/String;)Z
    //   5295: ifne -> 5305
    //   5298: goto -> 5305
    //   5301: invokestatic a : (Ljava/lang/Throwable;)Ljava/lang/Throwable;
    //   5304: athrow
    //   5305: aload #7
    //   5307: iconst_1
    //   5308: invokevirtual setAccessible : (Z)V
    //   5311: aload #7
    //   5313: aconst_null
    //   5314: invokevirtual get : (Ljava/lang/Object;)Ljava/lang/Object;
    //   5317: pop
    //   5318: iinc #6, 1
    //   5321: iload_2
    //   5322: ifeq -> 5183
    //   5325: sipush #-15415
    //   5328: sipush #-8845
    //   5331: invokestatic a : (II)Ljava/lang/String;
    //   5334: invokestatic forName : (Ljava/lang/String;)Ljava/lang/Class;
    //   5337: invokevirtual getDeclaredMethods : ()[Ljava/lang/reflect/Method;
    //   5340: astore #4
    //   5342: aload #4
    //   5344: arraylength
    //   5345: istore #5
    //   5347: iconst_0
    //   5348: istore #6
    //   5350: iload #6
    //   5352: iload #5
    //   5354: if_icmpge -> 5490
    //   5357: aload #4
    //   5359: iload #6
    //   5361: aaload
    //   5362: astore #7
    //   5364: aload #7
    //   5366: invokevirtual getParameterTypes : ()[Ljava/lang/Class;
    //   5369: pop
    //   5370: aload #7
    //   5372: invokevirtual getModifiers : ()I
    //   5375: invokestatic isStatic : (I)Z
    //   5378: ifeq -> 5476
    //   5381: aload #7
    //   5383: invokevirtual getParameterTypes : ()[Ljava/lang/Class;
    //   5386: arraylength
    //   5387: iconst_2
    //   5388: if_icmpne -> 5476
    //   5391: goto -> 5398
    //   5394: invokestatic a : (Ljava/lang/Throwable;)Ljava/lang/Throwable;
    //   5397: athrow
    //   5398: aload #7
    //   5400: invokevirtual getReturnType : ()Ljava/lang/Class;
    //   5403: getstatic java/lang/Boolean.TYPE : Ljava/lang/Class;
    //   5406: if_acmpne -> 5476
    //   5409: goto -> 5416
    //   5412: invokestatic a : (Ljava/lang/Throwable;)Ljava/lang/Throwable;
    //   5415: athrow
    //   5416: aload #7
    //   5418: iconst_1
    //   5419: invokevirtual setAccessible : (Z)V
    //   5422: aload #7
    //   5424: aconst_null
    //   5425: iconst_2
    //   5426: anewarray java/lang/Object
    //   5429: dup
    //   5430: iconst_0
    //   5431: aload_0
    //   5432: aastore
    //   5433: dup
    //   5434: iconst_1
    //   5435: aload_1
    //   5436: ifnonnull -> 5454
    //   5439: goto -> 5446
    //   5442: invokestatic a : (Ljava/lang/Throwable;)Ljava/lang/Throwable;
    //   5445: athrow
    //   5446: aload_1
    //   5447: goto -> 5461
    //   5450: invokestatic a : (Ljava/lang/Throwable;)Ljava/lang/Throwable;
    //   5453: athrow
    //   5454: aload_1
    //   5455: checkcast [B
    //   5458: invokevirtual clone : ()Ljava/lang/Object;
    //   5461: aastore
    //   5462: invokevirtual invoke : (Ljava/lang/Object;[Ljava/lang/Object;)Ljava/lang/Object;
    //   5465: checkcast java/lang/Boolean
    //   5468: invokevirtual booleanValue : ()Z
    //   5471: istore_3
    //   5472: iload_2
    //   5473: ifeq -> 5490
    //   5476: iinc #6, 1
    //   5479: iload_2
    //   5480: ifeq -> 5350
    //   5483: goto -> 5490
    //   5486: invokestatic a : (Ljava/lang/Throwable;)Ljava/lang/Throwable;
    //   5489: athrow
    //   5490: goto -> 5831
    //   5493: sipush #-15403
    //   5496: sipush #27363
    //   5499: invokestatic a : (II)Ljava/lang/String;
    //   5502: iconst_1
    //   5503: ldc burp/Zg0j
    //   5505: invokevirtual getClassLoader : ()Ljava/lang/ClassLoader;
    //   5508: invokestatic forName : (Ljava/lang/String;ZLjava/lang/ClassLoader;)Ljava/lang/Class;
    //   5511: invokevirtual getDeclaredFields : ()[Ljava/lang/reflect/Field;
    //   5514: astore #4
    //   5516: aload #4
    //   5518: arraylength
    //   5519: istore #5
    //   5521: iconst_0
    //   5522: istore #6
    //   5524: iload #6
    //   5526: iload #5
    //   5528: if_icmpge -> 5666
    //   5531: aload #4
    //   5533: iload #6
    //   5535: aaload
    //   5536: astore #7
    //   5538: aload #7
    //   5540: invokevirtual getModifiers : ()I
    //   5543: invokestatic isStatic : (I)Z
    //   5546: ifne -> 5556
    //   5549: goto -> 5659
    //   5552: invokestatic a : (Ljava/lang/Throwable;)Ljava/lang/Throwable;
    //   5555: athrow
    //   5556: aload #7
    //   5558: invokevirtual getType : ()Ljava/lang/Class;
    //   5561: astore #8
    //   5563: aload #8
    //   5565: ifnull -> 5646
    //   5568: aload #8
    //   5570: invokevirtual isPrimitive : ()Z
    //   5573: ifne -> 5646
    //   5576: goto -> 5583
    //   5579: invokestatic a : (Ljava/lang/Throwable;)Ljava/lang/Throwable;
    //   5582: athrow
    //   5583: aload #8
    //   5585: invokevirtual getPackage : ()Ljava/lang/Package;
    //   5588: ifnull -> 5646
    //   5591: goto -> 5598
    //   5594: invokestatic a : (Ljava/lang/Throwable;)Ljava/lang/Throwable;
    //   5597: athrow
    //   5598: aload #8
    //   5600: invokevirtual getPackage : ()Ljava/lang/Package;
    //   5603: invokevirtual getName : ()Ljava/lang/String;
    //   5606: ifnull -> 5646
    //   5609: goto -> 5616
    //   5612: invokestatic a : (Ljava/lang/Throwable;)Ljava/lang/Throwable;
    //   5615: athrow
    //   5616: aload #8
    //   5618: invokevirtual getPackage : ()Ljava/lang/Package;
    //   5621: invokevirtual getName : ()Ljava/lang/String;
    //   5624: sipush #-15407
    //   5627: sipush #-22402
    //   5630: invokestatic a : (II)Ljava/lang/String;
    //   5633: invokevirtual startsWith : (Ljava/lang/String;)Z
    //   5636: ifne -> 5646
    //   5639: goto -> 5646
    //   5642: invokestatic a : (Ljava/lang/Throwable;)Ljava/lang/Throwable;
    //   5645: athrow
    //   5646: aload #7
    //   5648: iconst_1
    //   5649: invokevirtual setAccessible : (Z)V
    //   5652: aload #7
    //   5654: aconst_null
    //   5655: invokevirtual get : (Ljava/lang/Object;)Ljava/lang/Object;
    //   5658: pop
    //   5659: iinc #6, 1
    //   5662: iload_2
    //   5663: ifeq -> 5524
    //   5666: sipush #-15419
    //   5669: sipush #-8630
    //   5672: invokestatic a : (II)Ljava/lang/String;
    //   5675: invokestatic forName : (Ljava/lang/String;)Ljava/lang/Class;
    //   5678: invokevirtual getDeclaredMethods : ()[Ljava/lang/reflect/Method;
    //   5681: astore #4
    //   5683: aload #4
    //   5685: arraylength
    //   5686: istore #5
    //   5688: iconst_0
    //   5689: istore #6
    //   5691: iload #6
    //   5693: iload #5
    //   5695: if_icmpge -> 5831
    //   5698: aload #4
    //   5700: iload #6
    //   5702: aaload
    //   5703: astore #7
    //   5705: aload #7
    //   5707: invokevirtual getParameterTypes : ()[Ljava/lang/Class;
    //   5710: pop
    //   5711: aload #7
    //   5713: invokevirtual getModifiers : ()I
    //   5716: invokestatic isStatic : (I)Z
    //   5719: ifeq -> 5817
    //   5722: aload #7
    //   5724: invokevirtual getParameterTypes : ()[Ljava/lang/Class;
    //   5727: arraylength
    //   5728: iconst_2
    //   5729: if_icmpne -> 5817
    //   5732: goto -> 5739
    //   5735: invokestatic a : (Ljava/lang/Throwable;)Ljava/lang/Throwable;
    //   5738: athrow
    //   5739: aload #7
    //   5741: invokevirtual getReturnType : ()Ljava/lang/Class;
    //   5744: getstatic java/lang/Boolean.TYPE : Ljava/lang/Class;
    //   5747: if_acmpne -> 5817
    //   5750: goto -> 5757
    //   5753: invokestatic a : (Ljava/lang/Throwable;)Ljava/lang/Throwable;
    //   5756: athrow
    //   5757: aload #7
    //   5759: iconst_1
    //   5760: invokevirtual setAccessible : (Z)V
    //   5763: aload #7
    //   5765: aconst_null
    //   5766: iconst_2
    //   5767: anewarray java/lang/Object
    //   5770: dup
    //   5771: iconst_0
    //   5772: aload_0
    //   5773: aastore
    //   5774: dup
    //   5775: iconst_1
    //   5776: aload_1
    //   5777: ifnonnull -> 5795
    //   5780: goto -> 5787
    //   5783: invokestatic a : (Ljava/lang/Throwable;)Ljava/lang/Throwable;
    //   5786: athrow
    //   5787: aload_1
    //   5788: goto -> 5802
    //   5791: invokestatic a : (Ljava/lang/Throwable;)Ljava/lang/Throwable;
    //   5794: athrow
    //   5795: aload_1
    //   5796: checkcast [B
    //   5799: invokevirtual clone : ()Ljava/lang/Object;
    //   5802: aastore
    //   5803: invokevirtual invoke : (Ljava/lang/Object;[Ljava/lang/Object;)Ljava/lang/Object;
    //   5806: checkcast java/lang/Boolean
    //   5809: invokevirtual booleanValue : ()Z
    //   5812: istore_3
    //   5813: iload_2
    //   5814: ifeq -> 5831
    //   5817: iinc #6, 1
    //   5820: iload_2
    //   5821: ifeq -> 5691
    //   5824: goto -> 5831
    //   5827: invokestatic a : (Ljava/lang/Throwable;)Ljava/lang/Throwable;
    //   5830: athrow
    //   5831: iload_3
    //   5832: ifeq -> 5837
    //   5835: iload_3
    //   5836: ireturn
    //   5837: getstatic burp/Zmhx.ZD : Ljava/lang/String;
    //   5840: getstatic burp/Zz67.ZE : Ljava/lang/Object;
    //   5843: checkcast java/math/BigInteger
    //   5846: invokevirtual intValue : ()I
    //   5849: bipush #32
    //   5851: irem
    //   5852: invokestatic abs : (I)I
    //   5855: invokevirtual charAt : (I)C
    //   5858: getstatic burp/Zkv2.Z_ : Ljava/lang/String;
    //   5861: getstatic burp/Zl_9.ZM : Ljava/lang/Object;
    //   5864: checkcast java/math/BigInteger
    //   5867: invokevirtual intValue : ()I
    //   5870: bipush #32
    //   5872: irem
    //   5873: invokestatic abs : (I)I
    //   5876: invokevirtual charAt : (I)C
    //   5879: if_icmpgt -> 6224
    //   5882: sipush #-15417
    //   5885: sipush #27715
    //   5888: invokestatic a : (II)Ljava/lang/String;
    //   5891: iconst_1
    //   5892: ldc burp/Zetv
    //   5894: invokevirtual getClassLoader : ()Ljava/lang/ClassLoader;
    //   5897: invokestatic forName : (Ljava/lang/String;ZLjava/lang/ClassLoader;)Ljava/lang/Class;
    //   5900: invokevirtual getDeclaredFields : ()[Ljava/lang/reflect/Field;
    //   5903: astore #4
    //   5905: aload #4
    //   5907: arraylength
    //   5908: istore #5
    //   5910: iconst_0
    //   5911: istore #6
    //   5913: iload #6
    //   5915: iload #5
    //   5917: if_icmpge -> 6055
    //   5920: aload #4
    //   5922: iload #6
    //   5924: aaload
    //   5925: astore #7
    //   5927: aload #7
    //   5929: invokevirtual getModifiers : ()I
    //   5932: invokestatic isStatic : (I)Z
    //   5935: ifne -> 5945
    //   5938: goto -> 6048
    //   5941: invokestatic a : (Ljava/lang/Throwable;)Ljava/lang/Throwable;
    //   5944: athrow
    //   5945: aload #7
    //   5947: invokevirtual getType : ()Ljava/lang/Class;
    //   5950: astore #8
    //   5952: aload #8
    //   5954: ifnull -> 6035
    //   5957: aload #8
    //   5959: invokevirtual isPrimitive : ()Z
    //   5962: ifne -> 6035
    //   5965: goto -> 5972
    //   5968: invokestatic a : (Ljava/lang/Throwable;)Ljava/lang/Throwable;
    //   5971: athrow
    //   5972: aload #8
    //   5974: invokevirtual getPackage : ()Ljava/lang/Package;
    //   5977: ifnull -> 6035
    //   5980: goto -> 5987
    //   5983: invokestatic a : (Ljava/lang/Throwable;)Ljava/lang/Throwable;
    //   5986: athrow
    //   5987: aload #8
    //   5989: invokevirtual getPackage : ()Ljava/lang/Package;
    //   5992: invokevirtual getName : ()Ljava/lang/String;
    //   5995: ifnull -> 6035
    //   5998: goto -> 6005
    //   6001: invokestatic a : (Ljava/lang/Throwable;)Ljava/lang/Throwable;
    //   6004: athrow
    //   6005: aload #8
    //   6007: invokevirtual getPackage : ()Ljava/lang/Package;
    //   6010: invokevirtual getName : ()Ljava/lang/String;
    //   6013: sipush #-15407
    //   6016: sipush #-22402
    //   6019: invokestatic a : (II)Ljava/lang/String;
    //   6022: invokevirtual startsWith : (Ljava/lang/String;)Z
    //   6025: ifne -> 6035
    //   6028: goto -> 6035
    //   6031: invokestatic a : (Ljava/lang/Throwable;)Ljava/lang/Throwable;
    //   6034: athrow
    //   6035: aload #7
    //   6037: iconst_1
    //   6038: invokevirtual setAccessible : (Z)V
    //   6041: aload #7
    //   6043: aconst_null
    //   6044: invokevirtual get : (Ljava/lang/Object;)Ljava/lang/Object;
    //   6047: pop
    //   6048: iinc #6, 1
    //   6051: iload_2
    //   6052: ifeq -> 5913
    //   6055: sipush #-15423
    //   6058: sipush #-9599
    //   6061: invokestatic a : (II)Ljava/lang/String;
    //   6064: invokestatic forName : (Ljava/lang/String;)Ljava/lang/Class;
    //   6067: invokevirtual getDeclaredMethods : ()[Ljava/lang/reflect/Method;
    //   6070: astore #4
    //   6072: aload #4
    //   6074: arraylength
    //   6075: istore #5
    //   6077: iconst_0
    //   6078: istore #6
    //   6080: iload #6
    //   6082: iload #5
    //   6084: if_icmpge -> 6220
    //   6087: aload #4
    //   6089: iload #6
    //   6091: aaload
    //   6092: astore #7
    //   6094: aload #7
    //   6096: invokevirtual getParameterTypes : ()[Ljava/lang/Class;
    //   6099: pop
    //   6100: aload #7
    //   6102: invokevirtual getModifiers : ()I
    //   6105: invokestatic isStatic : (I)Z
    //   6108: ifeq -> 6206
    //   6111: aload #7
    //   6113: invokevirtual getParameterTypes : ()[Ljava/lang/Class;
    //   6116: arraylength
    //   6117: iconst_2
    //   6118: if_icmpne -> 6206
    //   6121: goto -> 6128
    //   6124: invokestatic a : (Ljava/lang/Throwable;)Ljava/lang/Throwable;
    //   6127: athrow
    //   6128: aload #7
    //   6130: invokevirtual getReturnType : ()Ljava/lang/Class;
    //   6133: getstatic java/lang/Boolean.TYPE : Ljava/lang/Class;
    //   6136: if_acmpne -> 6206
    //   6139: goto -> 6146
    //   6142: invokestatic a : (Ljava/lang/Throwable;)Ljava/lang/Throwable;
    //   6145: athrow
    //   6146: aload #7
    //   6148: iconst_1
    //   6149: invokevirtual setAccessible : (Z)V
    //   6152: aload #7
    //   6154: aconst_null
    //   6155: iconst_2
    //   6156: anewarray java/lang/Object
    //   6159: dup
    //   6160: iconst_0
    //   6161: aload_0
    //   6162: aastore
    //   6163: dup
    //   6164: iconst_1
    //   6165: aload_1
    //   6166: ifnonnull -> 6184
    //   6169: goto -> 6176
    //   6172: invokestatic a : (Ljava/lang/Throwable;)Ljava/lang/Throwable;
    //   6175: athrow
    //   6176: aload_1
    //   6177: goto -> 6191
    //   6180: invokestatic a : (Ljava/lang/Throwable;)Ljava/lang/Throwable;
    //   6183: athrow
    //   6184: aload_1
    //   6185: checkcast [B
    //   6188: invokevirtual clone : ()Ljava/lang/Object;
    //   6191: aastore
    //   6192: invokevirtual invoke : (Ljava/lang/Object;[Ljava/lang/Object;)Ljava/lang/Object;
    //   6195: checkcast java/lang/Boolean
    //   6198: invokevirtual booleanValue : ()Z
    //   6201: istore_3
    //   6202: iload_2
    //   6203: ifeq -> 6220
    //   6206: iinc #6, 1
    //   6209: iload_2
    //   6210: ifeq -> 6080
    //   6213: goto -> 6220
    //   6216: invokestatic a : (Ljava/lang/Throwable;)Ljava/lang/Throwable;
    //   6219: athrow
    //   6220: iload_2
    //   6221: ifeq -> 6562
    //   6224: sipush #-15421
    //   6227: sipush #-11085
    //   6230: invokestatic a : (II)Ljava/lang/String;
    //   6233: iconst_1
    //   6234: ldc burp/Zg_y
    //   6236: invokevirtual getClassLoader : ()Ljava/lang/ClassLoader;
    //   6239: invokestatic forName : (Ljava/lang/String;ZLjava/lang/ClassLoader;)Ljava/lang/Class;
    //   6242: invokevirtual getDeclaredFields : ()[Ljava/lang/reflect/Field;
    //   6245: astore #4
    //   6247: aload #4
    //   6249: arraylength
    //   6250: istore #5
    //   6252: iconst_0
    //   6253: istore #6
    //   6255: iload #6
    //   6257: iload #5
    //   6259: if_icmpge -> 6397
    //   6262: aload #4
    //   6264: iload #6
    //   6266: aaload
    //   6267: astore #7
    //   6269: aload #7
    //   6271: invokevirtual getModifiers : ()I
    //   6274: invokestatic isStatic : (I)Z
    //   6277: ifne -> 6287
    //   6280: goto -> 6390
    //   6283: invokestatic a : (Ljava/lang/Throwable;)Ljava/lang/Throwable;
    //   6286: athrow
    //   6287: aload #7
    //   6289: invokevirtual getType : ()Ljava/lang/Class;
    //   6292: astore #8
    //   6294: aload #8
    //   6296: ifnull -> 6377
    //   6299: aload #8
    //   6301: invokevirtual isPrimitive : ()Z
    //   6304: ifne -> 6377
    //   6307: goto -> 6314
    //   6310: invokestatic a : (Ljava/lang/Throwable;)Ljava/lang/Throwable;
    //   6313: athrow
    //   6314: aload #8
    //   6316: invokevirtual getPackage : ()Ljava/lang/Package;
    //   6319: ifnull -> 6377
    //   6322: goto -> 6329
    //   6325: invokestatic a : (Ljava/lang/Throwable;)Ljava/lang/Throwable;
    //   6328: athrow
    //   6329: aload #8
    //   6331: invokevirtual getPackage : ()Ljava/lang/Package;
    //   6334: invokevirtual getName : ()Ljava/lang/String;
    //   6337: ifnull -> 6377
    //   6340: goto -> 6347
    //   6343: invokestatic a : (Ljava/lang/Throwable;)Ljava/lang/Throwable;
    //   6346: athrow
    //   6347: aload #8
    //   6349: invokevirtual getPackage : ()Ljava/lang/Package;
    //   6352: invokevirtual getName : ()Ljava/lang/String;
    //   6355: sipush #-15407
    //   6358: sipush #-22402
    //   6361: invokestatic a : (II)Ljava/lang/String;
    //   6364: invokevirtual startsWith : (Ljava/lang/String;)Z
    //   6367: ifne -> 6377
    //   6370: goto -> 6377
    //   6373: invokestatic a : (Ljava/lang/Throwable;)Ljava/lang/Throwable;
    //   6376: athrow
    //   6377: aload #7
    //   6379: iconst_1
    //   6380: invokevirtual setAccessible : (Z)V
    //   6383: aload #7
    //   6385: aconst_null
    //   6386: invokevirtual get : (Ljava/lang/Object;)Ljava/lang/Object;
    //   6389: pop
    //   6390: iinc #6, 1
    //   6393: iload_2
    //   6394: ifeq -> 6255
    //   6397: sipush #-15396
    //   6400: sipush #-1682
    //   6403: invokestatic a : (II)Ljava/lang/String;
    //   6406: invokestatic forName : (Ljava/lang/String;)Ljava/lang/Class;
    //   6409: invokevirtual getDeclaredMethods : ()[Ljava/lang/reflect/Method;
    //   6412: astore #4
    //   6414: aload #4
    //   6416: arraylength
    //   6417: istore #5
    //   6419: iconst_0
    //   6420: istore #6
    //   6422: iload #6
    //   6424: iload #5
    //   6426: if_icmpge -> 6562
    //   6429: aload #4
    //   6431: iload #6
    //   6433: aaload
    //   6434: astore #7
    //   6436: aload #7
    //   6438: invokevirtual getParameterTypes : ()[Ljava/lang/Class;
    //   6441: pop
    //   6442: aload #7
    //   6444: invokevirtual getModifiers : ()I
    //   6447: invokestatic isStatic : (I)Z
    //   6450: ifeq -> 6548
    //   6453: aload #7
    //   6455: invokevirtual getParameterTypes : ()[Ljava/lang/Class;
    //   6458: arraylength
    //   6459: iconst_2
    //   6460: if_icmpne -> 6548
    //   6463: goto -> 6470
    //   6466: invokestatic a : (Ljava/lang/Throwable;)Ljava/lang/Throwable;
    //   6469: athrow
    //   6470: aload #7
    //   6472: invokevirtual getReturnType : ()Ljava/lang/Class;
    //   6475: getstatic java/lang/Boolean.TYPE : Ljava/lang/Class;
    //   6478: if_acmpne -> 6548
    //   6481: goto -> 6488
    //   6484: invokestatic a : (Ljava/lang/Throwable;)Ljava/lang/Throwable;
    //   6487: athrow
    //   6488: aload #7
    //   6490: iconst_1
    //   6491: invokevirtual setAccessible : (Z)V
    //   6494: aload #7
    //   6496: aconst_null
    //   6497: iconst_2
    //   6498: anewarray java/lang/Object
    //   6501: dup
    //   6502: iconst_0
    //   6503: aload_0
    //   6504: aastore
    //   6505: dup
    //   6506: iconst_1
    //   6507: aload_1
    //   6508: ifnonnull -> 6526
    //   6511: goto -> 6518
    //   6514: invokestatic a : (Ljava/lang/Throwable;)Ljava/lang/Throwable;
    //   6517: athrow
    //   6518: aload_1
    //   6519: goto -> 6533
    //   6522: invokestatic a : (Ljava/lang/Throwable;)Ljava/lang/Throwable;
    //   6525: athrow
    //   6526: aload_1
    //   6527: checkcast [B
    //   6530: invokevirtual clone : ()Ljava/lang/Object;
    //   6533: aastore
    //   6534: invokevirtual invoke : (Ljava/lang/Object;[Ljava/lang/Object;)Ljava/lang/Object;
    //   6537: checkcast java/lang/Boolean
    //   6540: invokevirtual booleanValue : ()Z
    //   6543: istore_3
    //   6544: iload_2
    //   6545: ifeq -> 6562
    //   6548: iinc #6, 1
    //   6551: iload_2
    //   6552: ifeq -> 6422
    //   6555: goto -> 6562
    //   6558: invokestatic a : (Ljava/lang/Throwable;)Ljava/lang/Throwable;
    //   6561: athrow
    //   6562: iload_3
    //   6563: ifeq -> 6568
    //   6566: iload_3
    //   6567: ireturn
    //   6568: getstatic burp/Zebj.ZF : Ljava/lang/String;
    //   6571: getstatic burp/Zzy5.ZG : Ljava/lang/Object;
    //   6574: checkcast java/math/BigInteger
    //   6577: invokevirtual intValue : ()I
    //   6580: bipush #32
    //   6582: irem
    //   6583: invokestatic abs : (I)I
    //   6586: invokevirtual charAt : (I)C
    //   6589: getstatic burp/Zs36.Zr : Ljava/lang/String;
    //   6592: getstatic burp/Zzv.Zu : Ljava/lang/Object;
    //   6595: checkcast java/math/BigInteger
    //   6598: invokevirtual intValue : ()I
    //   6601: bipush #32
    //   6603: irem
    //   6604: invokestatic abs : (I)I
    //   6607: invokevirtual charAt : (I)C
    //   6610: if_icmpgt -> 6955
    //   6613: sipush #-15394
    //   6616: sipush #1798
    //   6619: invokestatic a : (II)Ljava/lang/String;
    //   6622: iconst_1
    //   6623: ldc burp/Zzs9
    //   6625: invokevirtual getClassLoader : ()Ljava/lang/ClassLoader;
    //   6628: invokestatic forName : (Ljava/lang/String;ZLjava/lang/ClassLoader;)Ljava/lang/Class;
    //   6631: invokevirtual getDeclaredFields : ()[Ljava/lang/reflect/Field;
    //   6634: astore #4
    //   6636: aload #4
    //   6638: arraylength
    //   6639: istore #5
    //   6641: iconst_0
    //   6642: istore #6
    //   6644: iload #6
    //   6646: iload #5
    //   6648: if_icmpge -> 6786
    //   6651: aload #4
    //   6653: iload #6
    //   6655: aaload
    //   6656: astore #7
    //   6658: aload #7
    //   6660: invokevirtual getModifiers : ()I
    //   6663: invokestatic isStatic : (I)Z
    //   6666: ifne -> 6676
    //   6669: goto -> 6779
    //   6672: invokestatic a : (Ljava/lang/Throwable;)Ljava/lang/Throwable;
    //   6675: athrow
    //   6676: aload #7
    //   6678: invokevirtual getType : ()Ljava/lang/Class;
    //   6681: astore #8
    //   6683: aload #8
    //   6685: ifnull -> 6766
    //   6688: aload #8
    //   6690: invokevirtual isPrimitive : ()Z
    //   6693: ifne -> 6766
    //   6696: goto -> 6703
    //   6699: invokestatic a : (Ljava/lang/Throwable;)Ljava/lang/Throwable;
    //   6702: athrow
    //   6703: aload #8
    //   6705: invokevirtual getPackage : ()Ljava/lang/Package;
    //   6708: ifnull -> 6766
    //   6711: goto -> 6718
    //   6714: invokestatic a : (Ljava/lang/Throwable;)Ljava/lang/Throwable;
    //   6717: athrow
    //   6718: aload #8
    //   6720: invokevirtual getPackage : ()Ljava/lang/Package;
    //   6723: invokevirtual getName : ()Ljava/lang/String;
    //   6726: ifnull -> 6766
    //   6729: goto -> 6736
    //   6732: invokestatic a : (Ljava/lang/Throwable;)Ljava/lang/Throwable;
    //   6735: athrow
    //   6736: aload #8
    //   6738: invokevirtual getPackage : ()Ljava/lang/Package;
    //   6741: invokevirtual getName : ()Ljava/lang/String;
    //   6744: sipush #-15407
    //   6747: sipush #-22402
    //   6750: invokestatic a : (II)Ljava/lang/String;
    //   6753: invokevirtual startsWith : (Ljava/lang/String;)Z
    //   6756: ifne -> 6766
    //   6759: goto -> 6766
    //   6762: invokestatic a : (Ljava/lang/Throwable;)Ljava/lang/Throwable;
    //   6765: athrow
    //   6766: aload #7
    //   6768: iconst_1
    //   6769: invokevirtual setAccessible : (Z)V
    //   6772: aload #7
    //   6774: aconst_null
    //   6775: invokevirtual get : (Ljava/lang/Object;)Ljava/lang/Object;
    //   6778: pop
    //   6779: iinc #6, 1
    //   6782: iload_2
    //   6783: ifeq -> 6644
    //   6786: sipush #-15398
    //   6789: sipush #-7580
    //   6792: invokestatic a : (II)Ljava/lang/String;
    //   6795: invokestatic forName : (Ljava/lang/String;)Ljava/lang/Class;
    //   6798: invokevirtual getDeclaredMethods : ()[Ljava/lang/reflect/Method;
    //   6801: astore #4
    //   6803: aload #4
    //   6805: arraylength
    //   6806: istore #5
    //   6808: iconst_0
    //   6809: istore #6
    //   6811: iload #6
    //   6813: iload #5
    //   6815: if_icmpge -> 6951
    //   6818: aload #4
    //   6820: iload #6
    //   6822: aaload
    //   6823: astore #7
    //   6825: aload #7
    //   6827: invokevirtual getParameterTypes : ()[Ljava/lang/Class;
    //   6830: pop
    //   6831: aload #7
    //   6833: invokevirtual getModifiers : ()I
    //   6836: invokestatic isStatic : (I)Z
    //   6839: ifeq -> 6937
    //   6842: aload #7
    //   6844: invokevirtual getParameterTypes : ()[Ljava/lang/Class;
    //   6847: arraylength
    //   6848: iconst_2
    //   6849: if_icmpne -> 6937
    //   6852: goto -> 6859
    //   6855: invokestatic a : (Ljava/lang/Throwable;)Ljava/lang/Throwable;
    //   6858: athrow
    //   6859: aload #7
    //   6861: invokevirtual getReturnType : ()Ljava/lang/Class;
    //   6864: getstatic java/lang/Boolean.TYPE : Ljava/lang/Class;
    //   6867: if_acmpne -> 6937
    //   6870: goto -> 6877
    //   6873: invokestatic a : (Ljava/lang/Throwable;)Ljava/lang/Throwable;
    //   6876: athrow
    //   6877: aload #7
    //   6879: iconst_1
    //   6880: invokevirtual setAccessible : (Z)V
    //   6883: aload #7
    //   6885: aconst_null
    //   6886: iconst_2
    //   6887: anewarray java/lang/Object
    //   6890: dup
    //   6891: iconst_0
    //   6892: aload_0
    //   6893: aastore
    //   6894: dup
    //   6895: iconst_1
    //   6896: aload_1
    //   6897: ifnonnull -> 6915
    //   6900: goto -> 6907
    //   6903: invokestatic a : (Ljava/lang/Throwable;)Ljava/lang/Throwable;
    //   6906: athrow
    //   6907: aload_1
    //   6908: goto -> 6922
    //   6911: invokestatic a : (Ljava/lang/Throwable;)Ljava/lang/Throwable;
    //   6914: athrow
    //   6915: aload_1
    //   6916: checkcast [B
    //   6919: invokevirtual clone : ()Ljava/lang/Object;
    //   6922: aastore
    //   6923: invokevirtual invoke : (Ljava/lang/Object;[Ljava/lang/Object;)Ljava/lang/Object;
    //   6926: checkcast java/lang/Boolean
    //   6929: invokevirtual booleanValue : ()Z
    //   6932: istore_3
    //   6933: iload_2
    //   6934: ifeq -> 6951
    //   6937: iinc #6, 1
    //   6940: iload_2
    //   6941: ifeq -> 6811
    //   6944: goto -> 6951
    //   6947: invokestatic a : (Ljava/lang/Throwable;)Ljava/lang/Throwable;
    //   6950: athrow
    //   6951: iload_2
    //   6952: ifeq -> 7293
    //   6955: sipush #-15401
    //   6958: sipush #-20365
    //   6961: invokestatic a : (II)Ljava/lang/String;
    //   6964: iconst_1
    //   6965: ldc burp/Zrvb
    //   6967: invokevirtual getClassLoader : ()Ljava/lang/ClassLoader;
    //   6970: invokestatic forName : (Ljava/lang/String;ZLjava/lang/ClassLoader;)Ljava/lang/Class;
    //   6973: invokevirtual getDeclaredFields : ()[Ljava/lang/reflect/Field;
    //   6976: astore #4
    //   6978: aload #4
    //   6980: arraylength
    //   6981: istore #5
    //   6983: iconst_0
    //   6984: istore #6
    //   6986: iload #6
    //   6988: iload #5
    //   6990: if_icmpge -> 7128
    //   6993: aload #4
    //   6995: iload #6
    //   6997: aaload
    //   6998: astore #7
    //   7000: aload #7
    //   7002: invokevirtual getModifiers : ()I
    //   7005: invokestatic isStatic : (I)Z
    //   7008: ifne -> 7018
    //   7011: goto -> 7121
    //   7014: invokestatic a : (Ljava/lang/Throwable;)Ljava/lang/Throwable;
    //   7017: athrow
    //   7018: aload #7
    //   7020: invokevirtual getType : ()Ljava/lang/Class;
    //   7023: astore #8
    //   7025: aload #8
    //   7027: ifnull -> 7108
    //   7030: aload #8
    //   7032: invokevirtual isPrimitive : ()Z
    //   7035: ifne -> 7108
    //   7038: goto -> 7045
    //   7041: invokestatic a : (Ljava/lang/Throwable;)Ljava/lang/Throwable;
    //   7044: athrow
    //   7045: aload #8
    //   7047: invokevirtual getPackage : ()Ljava/lang/Package;
    //   7050: ifnull -> 7108
    //   7053: goto -> 7060
    //   7056: invokestatic a : (Ljava/lang/Throwable;)Ljava/lang/Throwable;
    //   7059: athrow
    //   7060: aload #8
    //   7062: invokevirtual getPackage : ()Ljava/lang/Package;
    //   7065: invokevirtual getName : ()Ljava/lang/String;
    //   7068: ifnull -> 7108
    //   7071: goto -> 7078
    //   7074: invokestatic a : (Ljava/lang/Throwable;)Ljava/lang/Throwable;
    //   7077: athrow
    //   7078: aload #8
    //   7080: invokevirtual getPackage : ()Ljava/lang/Package;
    //   7083: invokevirtual getName : ()Ljava/lang/String;
    //   7086: sipush #-15407
    //   7089: sipush #-22402
    //   7092: invokestatic a : (II)Ljava/lang/String;
    //   7095: invokevirtual startsWith : (Ljava/lang/String;)Z
    //   7098: ifne -> 7108
    //   7101: goto -> 7108
    //   7104: invokestatic a : (Ljava/lang/Throwable;)Ljava/lang/Throwable;
    //   7107: athrow
    //   7108: aload #7
    //   7110: iconst_1
    //   7111: invokevirtual setAccessible : (Z)V
    //   7114: aload #7
    //   7116: aconst_null
    //   7117: invokevirtual get : (Ljava/lang/Object;)Ljava/lang/Object;
    //   7120: pop
    //   7121: iinc #6, 1
    //   7124: iload_2
    //   7125: ifeq -> 6986
    //   7128: sipush #-15410
    //   7131: sipush #-16963
    //   7134: invokestatic a : (II)Ljava/lang/String;
    //   7137: invokestatic forName : (Ljava/lang/String;)Ljava/lang/Class;
    //   7140: invokevirtual getDeclaredMethods : ()[Ljava/lang/reflect/Method;
    //   7143: astore #4
    //   7145: aload #4
    //   7147: arraylength
    //   7148: istore #5
    //   7150: iconst_0
    //   7151: istore #6
    //   7153: iload #6
    //   7155: iload #5
    //   7157: if_icmpge -> 7293
    //   7160: aload #4
    //   7162: iload #6
    //   7164: aaload
    //   7165: astore #7
    //   7167: aload #7
    //   7169: invokevirtual getParameterTypes : ()[Ljava/lang/Class;
    //   7172: pop
    //   7173: aload #7
    //   7175: invokevirtual getModifiers : ()I
    //   7178: invokestatic isStatic : (I)Z
    //   7181: ifeq -> 7279
    //   7184: aload #7
    //   7186: invokevirtual getParameterTypes : ()[Ljava/lang/Class;
    //   7189: arraylength
    //   7190: iconst_2
    //   7191: if_icmpne -> 7279
    //   7194: goto -> 7201
    //   7197: invokestatic a : (Ljava/lang/Throwable;)Ljava/lang/Throwable;
    //   7200: athrow
    //   7201: aload #7
    //   7203: invokevirtual getReturnType : ()Ljava/lang/Class;
    //   7206: getstatic java/lang/Boolean.TYPE : Ljava/lang/Class;
    //   7209: if_acmpne -> 7279
    //   7212: goto -> 7219
    //   7215: invokestatic a : (Ljava/lang/Throwable;)Ljava/lang/Throwable;
    //   7218: athrow
    //   7219: aload #7
    //   7221: iconst_1
    //   7222: invokevirtual setAccessible : (Z)V
    //   7225: aload #7
    //   7227: aconst_null
    //   7228: iconst_2
    //   7229: anewarray java/lang/Object
    //   7232: dup
    //   7233: iconst_0
    //   7234: aload_0
    //   7235: aastore
    //   7236: dup
    //   7237: iconst_1
    //   7238: aload_1
    //   7239: ifnonnull -> 7257
    //   7242: goto -> 7249
    //   7245: invokestatic a : (Ljava/lang/Throwable;)Ljava/lang/Throwable;
    //   7248: athrow
    //   7249: aload_1
    //   7250: goto -> 7264
    //   7253: invokestatic a : (Ljava/lang/Throwable;)Ljava/lang/Throwable;
    //   7256: athrow
    //   7257: aload_1
    //   7258: checkcast [B
    //   7261: invokevirtual clone : ()Ljava/lang/Object;
    //   7264: aastore
    //   7265: invokevirtual invoke : (Ljava/lang/Object;[Ljava/lang/Object;)Ljava/lang/Object;
    //   7268: checkcast java/lang/Boolean
    //   7271: invokevirtual booleanValue : ()Z
    //   7274: istore_3
    //   7275: iload_2
    //   7276: ifeq -> 7293
    //   7279: iinc #6, 1
    //   7282: iload_2
    //   7283: ifeq -> 7153
    //   7286: goto -> 7293
    //   7289: invokestatic a : (Ljava/lang/Throwable;)Ljava/lang/Throwable;
    //   7292: athrow
    //   7293: iload_3
    //   7294: ifeq -> 7299
    //   7297: iload_3
    //   7298: ireturn
    //   7299: getstatic burp/Zewo.ZM : Ljava/lang/String;
    //   7302: getstatic burp/Zre1.ZN : Ljava/lang/Object;
    //   7305: checkcast java/math/BigInteger
    //   7308: invokevirtual intValue : ()I
    //   7311: bipush #32
    //   7313: irem
    //   7314: invokestatic abs : (I)I
    //   7317: invokevirtual charAt : (I)C
    //   7320: getstatic burp/Zs9u.ZM : Ljava/lang/String;
    //   7323: getstatic burp/Ztes.ZX : Ljava/lang/Object;
    //   7326: checkcast java/math/BigInteger
    //   7329: invokevirtual intValue : ()I
    //   7332: bipush #32
    //   7334: irem
    //   7335: invokestatic abs : (I)I
    //   7338: invokevirtual charAt : (I)C
    //   7341: if_icmpgt -> 7686
    //   7344: sipush #-15414
    //   7347: sipush #27911
    //   7350: invokestatic a : (II)Ljava/lang/String;
    //   7353: iconst_1
    //   7354: ldc burp/Zgdt
    //   7356: invokevirtual getClassLoader : ()Ljava/lang/ClassLoader;
    //   7359: invokestatic forName : (Ljava/lang/String;ZLjava/lang/ClassLoader;)Ljava/lang/Class;
    //   7362: invokevirtual getDeclaredFields : ()[Ljava/lang/reflect/Field;
    //   7365: astore #4
    //   7367: aload #4
    //   7369: arraylength
    //   7370: istore #5
    //   7372: iconst_0
    //   7373: istore #6
    //   7375: iload #6
    //   7377: iload #5
    //   7379: if_icmpge -> 7517
    //   7382: aload #4
    //   7384: iload #6
    //   7386: aaload
    //   7387: astore #7
    //   7389: aload #7
    //   7391: invokevirtual getModifiers : ()I
    //   7394: invokestatic isStatic : (I)Z
    //   7397: ifne -> 7407
    //   7400: goto -> 7510
    //   7403: invokestatic a : (Ljava/lang/Throwable;)Ljava/lang/Throwable;
    //   7406: athrow
    //   7407: aload #7
    //   7409: invokevirtual getType : ()Ljava/lang/Class;
    //   7412: astore #8
    //   7414: aload #8
    //   7416: ifnull -> 7497
    //   7419: aload #8
    //   7421: invokevirtual isPrimitive : ()Z
    //   7424: ifne -> 7497
    //   7427: goto -> 7434
    //   7430: invokestatic a : (Ljava/lang/Throwable;)Ljava/lang/Throwable;
    //   7433: athrow
    //   7434: aload #8
    //   7436: invokevirtual getPackage : ()Ljava/lang/Package;
    //   7439: ifnull -> 7497
    //   7442: goto -> 7449
    //   7445: invokestatic a : (Ljava/lang/Throwable;)Ljava/lang/Throwable;
    //   7448: athrow
    //   7449: aload #8
    //   7451: invokevirtual getPackage : ()Ljava/lang/Package;
    //   7454: invokevirtual getName : ()Ljava/lang/String;
    //   7457: ifnull -> 7497
    //   7460: goto -> 7467
    //   7463: invokestatic a : (Ljava/lang/Throwable;)Ljava/lang/Throwable;
    //   7466: athrow
    //   7467: aload #8
    //   7469: invokevirtual getPackage : ()Ljava/lang/Package;
    //   7472: invokevirtual getName : ()Ljava/lang/String;
    //   7475: sipush #-15407
    //   7478: sipush #-22402
    //   7481: invokestatic a : (II)Ljava/lang/String;
    //   7484: invokevirtual startsWith : (Ljava/lang/String;)Z
    //   7487: ifne -> 7497
    //   7490: goto -> 7497
    //   7493: invokestatic a : (Ljava/lang/Throwable;)Ljava/lang/Throwable;
    //   7496: athrow
    //   7497: aload #7
    //   7499: iconst_1
    //   7500: invokevirtual setAccessible : (Z)V
    //   7503: aload #7
    //   7505: aconst_null
    //   7506: invokevirtual get : (Ljava/lang/Object;)Ljava/lang/Object;
    //   7509: pop
    //   7510: iinc #6, 1
    //   7513: iload_2
    //   7514: ifeq -> 7375
    //   7517: sipush #-15418
    //   7520: sipush #-26981
    //   7523: invokestatic a : (II)Ljava/lang/String;
    //   7526: invokestatic forName : (Ljava/lang/String;)Ljava/lang/Class;
    //   7529: invokevirtual getDeclaredMethods : ()[Ljava/lang/reflect/Method;
    //   7532: astore #4
    //   7534: aload #4
    //   7536: arraylength
    //   7537: istore #5
    //   7539: iconst_0
    //   7540: istore #6
    //   7542: iload #6
    //   7544: iload #5
    //   7546: if_icmpge -> 7682
    //   7549: aload #4
    //   7551: iload #6
    //   7553: aaload
    //   7554: astore #7
    //   7556: aload #7
    //   7558: invokevirtual getParameterTypes : ()[Ljava/lang/Class;
    //   7561: pop
    //   7562: aload #7
    //   7564: invokevirtual getModifiers : ()I
    //   7567: invokestatic isStatic : (I)Z
    //   7570: ifeq -> 7668
    //   7573: aload #7
    //   7575: invokevirtual getParameterTypes : ()[Ljava/lang/Class;
    //   7578: arraylength
    //   7579: iconst_2
    //   7580: if_icmpne -> 7668
    //   7583: goto -> 7590
    //   7586: invokestatic a : (Ljava/lang/Throwable;)Ljava/lang/Throwable;
    //   7589: athrow
    //   7590: aload #7
    //   7592: invokevirtual getReturnType : ()Ljava/lang/Class;
    //   7595: getstatic java/lang/Boolean.TYPE : Ljava/lang/Class;
    //   7598: if_acmpne -> 7668
    //   7601: goto -> 7608
    //   7604: invokestatic a : (Ljava/lang/Throwable;)Ljava/lang/Throwable;
    //   7607: athrow
    //   7608: aload #7
    //   7610: iconst_1
    //   7611: invokevirtual setAccessible : (Z)V
    //   7614: aload #7
    //   7616: aconst_null
    //   7617: iconst_2
    //   7618: anewarray java/lang/Object
    //   7621: dup
    //   7622: iconst_0
    //   7623: aload_0
    //   7624: aastore
    //   7625: dup
    //   7626: iconst_1
    //   7627: aload_1
    //   7628: ifnonnull -> 7646
    //   7631: goto -> 7638
    //   7634: invokestatic a : (Ljava/lang/Throwable;)Ljava/lang/Throwable;
    //   7637: athrow
    //   7638: aload_1
    //   7639: goto -> 7653
    //   7642: invokestatic a : (Ljava/lang/Throwable;)Ljava/lang/Throwable;
    //   7645: athrow
    //   7646: aload_1
    //   7647: checkcast [B
    //   7650: invokevirtual clone : ()Ljava/lang/Object;
    //   7653: aastore
    //   7654: invokevirtual invoke : (Ljava/lang/Object;[Ljava/lang/Object;)Ljava/lang/Object;
    //   7657: checkcast java/lang/Boolean
    //   7660: invokevirtual booleanValue : ()Z
    //   7663: istore_3
    //   7664: iload_2
    //   7665: ifeq -> 7682
    //   7668: iinc #6, 1
    //   7671: iload_2
    //   7672: ifeq -> 7542
    //   7675: goto -> 7682
    //   7678: invokestatic a : (Ljava/lang/Throwable;)Ljava/lang/Throwable;
    //   7681: athrow
    //   7682: iload_2
    //   7683: ifeq -> 8024
    //   7686: sipush #-15404
    //   7689: sipush #-29006
    //   7692: invokestatic a : (II)Ljava/lang/String;
    //   7695: iconst_1
    //   7696: ldc burp/Zstq
    //   7698: invokevirtual getClassLoader : ()Ljava/lang/ClassLoader;
    //   7701: invokestatic forName : (Ljava/lang/String;ZLjava/lang/ClassLoader;)Ljava/lang/Class;
    //   7704: invokevirtual getDeclaredFields : ()[Ljava/lang/reflect/Field;
    //   7707: astore #4
    //   7709: aload #4
    //   7711: arraylength
    //   7712: istore #5
    //   7714: iconst_0
    //   7715: istore #6
    //   7717: iload #6
    //   7719: iload #5
    //   7721: if_icmpge -> 7859
    //   7724: aload #4
    //   7726: iload #6
    //   7728: aaload
    //   7729: astore #7
    //   7731: aload #7
    //   7733: invokevirtual getModifiers : ()I
    //   7736: invokestatic isStatic : (I)Z
    //   7739: ifne -> 7749
    //   7742: goto -> 7852
    //   7745: invokestatic a : (Ljava/lang/Throwable;)Ljava/lang/Throwable;
    //   7748: athrow
    //   7749: aload #7
    //   7751: invokevirtual getType : ()Ljava/lang/Class;
    //   7754: astore #8
    //   7756: aload #8
    //   7758: ifnull -> 7839
    //   7761: aload #8
    //   7763: invokevirtual isPrimitive : ()Z
    //   7766: ifne -> 7839
    //   7769: goto -> 7776
    //   7772: invokestatic a : (Ljava/lang/Throwable;)Ljava/lang/Throwable;
    //   7775: athrow
    //   7776: aload #8
    //   7778: invokevirtual getPackage : ()Ljava/lang/Package;
    //   7781: ifnull -> 7839
    //   7784: goto -> 7791
    //   7787: invokestatic a : (Ljava/lang/Throwable;)Ljava/lang/Throwable;
    //   7790: athrow
    //   7791: aload #8
    //   7793: invokevirtual getPackage : ()Ljava/lang/Package;
    //   7796: invokevirtual getName : ()Ljava/lang/String;
    //   7799: ifnull -> 7839
    //   7802: goto -> 7809
    //   7805: invokestatic a : (Ljava/lang/Throwable;)Ljava/lang/Throwable;
    //   7808: athrow
    //   7809: aload #8
    //   7811: invokevirtual getPackage : ()Ljava/lang/Package;
    //   7814: invokevirtual getName : ()Ljava/lang/String;
    //   7817: sipush #-15407
    //   7820: sipush #-22402
    //   7823: invokestatic a : (II)Ljava/lang/String;
    //   7826: invokevirtual startsWith : (Ljava/lang/String;)Z
    //   7829: ifne -> 7839
    //   7832: goto -> 7839
    //   7835: invokestatic a : (Ljava/lang/Throwable;)Ljava/lang/Throwable;
    //   7838: athrow
    //   7839: aload #7
    //   7841: iconst_1
    //   7842: invokevirtual setAccessible : (Z)V
    //   7845: aload #7
    //   7847: aconst_null
    //   7848: invokevirtual get : (Ljava/lang/Object;)Ljava/lang/Object;
    //   7851: pop
    //   7852: iinc #6, 1
    //   7855: iload_2
    //   7856: ifeq -> 7717
    //   7859: sipush #-15424
    //   7862: sipush #-20131
    //   7865: invokestatic a : (II)Ljava/lang/String;
    //   7868: invokestatic forName : (Ljava/lang/String;)Ljava/lang/Class;
    //   7871: invokevirtual getDeclaredMethods : ()[Ljava/lang/reflect/Method;
    //   7874: astore #4
    //   7876: aload #4
    //   7878: arraylength
    //   7879: istore #5
    //   7881: iconst_0
    //   7882: istore #6
    //   7884: iload #6
    //   7886: iload #5
    //   7888: if_icmpge -> 8024
    //   7891: aload #4
    //   7893: iload #6
    //   7895: aaload
    //   7896: astore #7
    //   7898: aload #7
    //   7900: invokevirtual getParameterTypes : ()[Ljava/lang/Class;
    //   7903: pop
    //   7904: aload #7
    //   7906: invokevirtual getModifiers : ()I
    //   7909: invokestatic isStatic : (I)Z
    //   7912: ifeq -> 8010
    //   7915: aload #7
    //   7917: invokevirtual getParameterTypes : ()[Ljava/lang/Class;
    //   7920: arraylength
    //   7921: iconst_2
    //   7922: if_icmpne -> 8010
    //   7925: goto -> 7932
    //   7928: invokestatic a : (Ljava/lang/Throwable;)Ljava/lang/Throwable;
    //   7931: athrow
    //   7932: aload #7
    //   7934: invokevirtual getReturnType : ()Ljava/lang/Class;
    //   7937: getstatic java/lang/Boolean.TYPE : Ljava/lang/Class;
    //   7940: if_acmpne -> 8010
    //   7943: goto -> 7950
    //   7946: invokestatic a : (Ljava/lang/Throwable;)Ljava/lang/Throwable;
    //   7949: athrow
    //   7950: aload #7
    //   7952: iconst_1
    //   7953: invokevirtual setAccessible : (Z)V
    //   7956: aload #7
    //   7958: aconst_null
    //   7959: iconst_2
    //   7960: anewarray java/lang/Object
    //   7963: dup
    //   7964: iconst_0
    //   7965: aload_0
    //   7966: aastore
    //   7967: dup
    //   7968: iconst_1
    //   7969: aload_1
    //   7970: ifnonnull -> 7988
    //   7973: goto -> 7980
    //   7976: invokestatic a : (Ljava/lang/Throwable;)Ljava/lang/Throwable;
    //   7979: athrow
    //   7980: aload_1
    //   7981: goto -> 7995
    //   7984: invokestatic a : (Ljava/lang/Throwable;)Ljava/lang/Throwable;
    //   7987: athrow
    //   7988: aload_1
    //   7989: checkcast [B
    //   7992: invokevirtual clone : ()Ljava/lang/Object;
    //   7995: aastore
    //   7996: invokevirtual invoke : (Ljava/lang/Object;[Ljava/lang/Object;)Ljava/lang/Object;
    //   7999: checkcast java/lang/Boolean
    //   8002: invokevirtual booleanValue : ()Z
    //   8005: istore_3
    //   8006: iload_2
    //   8007: ifeq -> 8024
    //   8010: iinc #6, 1
    //   8013: iload_2
    //   8014: ifeq -> 7884
    //   8017: goto -> 8024
    //   8020: invokestatic a : (Ljava/lang/Throwable;)Ljava/lang/Throwable;
    //   8023: athrow
    //   8024: iload_3
    //   8025: ireturn
    //   8026: astore_3
    //   8027: new java/lang/Exception
    //   8030: dup
    //   8031: aload_3
    //   8032: invokevirtual getMessage : ()Ljava/lang/String;
    //   8035: invokespecial <init> : (Ljava/lang/String;)V
    //   8038: athrow
    // Exception table:
    //   from	to	target	type
    //   4	5836	8026	java/lang/Throwable
    //   823	857	860	java/lang/Throwable
    //   952	1030	1033	java/lang/Throwable
    //   959	1173	1176	java/lang/Throwable
    //   1550	1565	1565	java/lang/Throwable
    //   1592	1626	1629	java/lang/Throwable
    //   1636	1648	1651	java/lang/Throwable
    //   1734	1812	1815	java/lang/Throwable
    //   1741	1955	1958	java/lang/Throwable
    //   2355	2433	2436	java/lang/Throwable
    //   2362	2576	2579	java/lang/Throwable
    //   3023	3057	3060	java/lang/Throwable
    //   3064	3076	3079	java/lang/Throwable
    //   3162	3240	3243	java/lang/Throwable
    //   3169	3383	3386	java/lang/Throwable
    //   4136	4150	4150	java/lang/Throwable
    //   4161	4174	4177	java/lang/Throwable
    //   4166	4189	4192	java/lang/Throwable
    //   4181	4207	4210	java/lang/Throwable
    //   4196	4237	4240	java/lang/Throwable
    //   4300	4327	4330	java/lang/Throwable
    //   4317	4348	4351	java/lang/Throwable
    //   4334	4378	4381	java/lang/Throwable
    //   4355	4389	4389	java/lang/Throwable
    //   4400	4416	4419	java/lang/Throwable
    //   4728	4752	4755	java/lang/Throwable
    //   4826	4863	4863	java/lang/Throwable
    //   4867	4888	4888	java/lang/Throwable
    //   4892	4922	4922	java/lang/Throwable
    //   5197	5211	5211	java/lang/Throwable
    //   5222	5235	5238	java/lang/Throwable
    //   5227	5250	5253	java/lang/Throwable
    //   5242	5268	5271	java/lang/Throwable
    //   5257	5298	5301	java/lang/Throwable
    //   5364	5391	5394	java/lang/Throwable
    //   5381	5409	5412	java/lang/Throwable
    //   5398	5439	5442	java/lang/Throwable
    //   5416	5450	5450	java/lang/Throwable
    //   5472	5483	5486	java/lang/Throwable
    //   5538	5552	5552	java/lang/Throwable
    //   5563	5576	5579	java/lang/Throwable
    //   5568	5591	5594	java/lang/Throwable
    //   5583	5609	5612	java/lang/Throwable
    //   5598	5639	5642	java/lang/Throwable
    //   5705	5732	5735	java/lang/Throwable
    //   5722	5750	5753	java/lang/Throwable
    //   5739	5780	5783	java/lang/Throwable
    //   5757	5791	5791	java/lang/Throwable
    //   5813	5824	5827	java/lang/Throwable
    //   5837	6567	8026	java/lang/Throwable
    //   5927	5941	5941	java/lang/Throwable
    //   5952	5965	5968	java/lang/Throwable
    //   5957	5980	5983	java/lang/Throwable
    //   5972	5998	6001	java/lang/Throwable
    //   5987	6028	6031	java/lang/Throwable
    //   6094	6121	6124	java/lang/Throwable
    //   6111	6139	6142	java/lang/Throwable
    //   6128	6169	6172	java/lang/Throwable
    //   6146	6180	6180	java/lang/Throwable
    //   6202	6213	6216	java/lang/Throwable
    //   6269	6283	6283	java/lang/Throwable
    //   6294	6307	6310	java/lang/Throwable
    //   6299	6322	6325	java/lang/Throwable
    //   6314	6340	6343	java/lang/Throwable
    //   6329	6370	6373	java/lang/Throwable
    //   6436	6463	6466	java/lang/Throwable
    //   6453	6481	6484	java/lang/Throwable
    //   6470	6511	6514	java/lang/Throwable
    //   6488	6522	6522	java/lang/Throwable
    //   6544	6555	6558	java/lang/Throwable
    //   6568	7298	8026	java/lang/Throwable
    //   6658	6672	6672	java/lang/Throwable
    //   6683	6696	6699	java/lang/Throwable
    //   6688	6711	6714	java/lang/Throwable
    //   6703	6729	6732	java/lang/Throwable
    //   6718	6759	6762	java/lang/Throwable
    //   6825	6852	6855	java/lang/Throwable
    //   6842	6870	6873	java/lang/Throwable
    //   6859	6900	6903	java/lang/Throwable
    //   6877	6911	6911	java/lang/Throwable
    //   6933	6944	6947	java/lang/Throwable
    //   7000	7014	7014	java/lang/Throwable
    //   7025	7038	7041	java/lang/Throwable
    //   7030	7053	7056	java/lang/Throwable
    //   7045	7071	7074	java/lang/Throwable
    //   7060	7101	7104	java/lang/Throwable
    //   7167	7194	7197	java/lang/Throwable
    //   7184	7212	7215	java/lang/Throwable
    //   7201	7242	7245	java/lang/Throwable
    //   7219	7253	7253	java/lang/Throwable
    //   7275	7286	7289	java/lang/Throwable
    //   7299	8025	8026	java/lang/Throwable
    //   7389	7403	7403	java/lang/Throwable
    //   7414	7427	7430	java/lang/Throwable
    //   7419	7442	7445	java/lang/Throwable
    //   7434	7460	7463	java/lang/Throwable
    //   7449	7490	7493	java/lang/Throwable
    //   7556	7583	7586	java/lang/Throwable
    //   7573	7601	7604	java/lang/Throwable
    //   7590	7631	7634	java/lang/Throwable
    //   7608	7642	7642	java/lang/Throwable
    //   7664	7675	7678	java/lang/Throwable
    //   7731	7745	7745	java/lang/Throwable
    //   7756	7769	7772	java/lang/Throwable
    //   7761	7784	7787	java/lang/Throwable
    //   7776	7802	7805	java/lang/Throwable
    //   7791	7832	7835	java/lang/Throwable
    //   7898	7925	7928	java/lang/Throwable
    //   7915	7943	7946	java/lang/Throwable
    //   7932	7973	7976	java/lang/Throwable
    //   7950	7984	7984	java/lang/Throwable
    //   8006	8017	8020	java/lang/Throwable
  }
  
  static {
    // Byte code:
    //   0: bipush #29
    //   2: anewarray java/lang/String
    //   5: astore #5
    //   7: iconst_0
    //   8: istore_3
    //   9: ldc 'W<_\\r\\tZq9M51+;?j]Y[ez42n{G0Z>]!ed \\tl>{Jil&o\\t]us0N(h\\tW*tD=\\t=K.Ps3\\tW'_\\t}yCQT\\t:1i(\\r \\r2r#.dD_paL/>?LV^<\\t=\\tOD\\tNb+?,\\tTrx7u\\t*Da@\\t^P,A\\tP\\tIr\\fg0\\t36 cpa,3n>#UO1IcR BHI;Z\\fq\\t<kJL1^4\\bThy*Bv=RvmB\\fp\B^hUbVAtO0{]\\n\\ty'
    //   11: dup
    //   12: astore_2
    //   13: invokevirtual length : ()I
    //   16: istore #4
    //   18: bipush #8
    //   20: istore_1
    //   21: iconst_m1
    //   22: istore_0
    //   23: bipush #93
    //   25: iinc #0, 1
    //   28: aload_2
    //   29: iload_0
    //   30: dup
    //   31: iload_1
    //   32: iadd
    //   33: invokevirtual substring : (II)Ljava/lang/String;
    //   36: iconst_m1
    //   37: goto -> 143
    //   40: aload #5
    //   42: swap
    //   43: iload_3
    //   44: iinc #3, 1
    //   47: swap
    //   48: aastore
    //   49: iload_0
    //   50: iload_1
    //   51: iadd
    //   52: dup
    //   53: istore_0
    //   54: iload #4
    //   56: if_icmpge -> 68
    //   59: aload_2
    //   60: iload_0
    //   61: invokevirtual charAt : (I)C
    //   64: istore_1
    //   65: goto -> 23
    //   68: ldc '8-z.G\\t7'
    //   70: dup
    //   71: astore_2
    //   72: invokevirtual length : ()I
    //   75: istore #4
    //   77: bipush #8
    //   79: istore_1
    //   80: iconst_m1
    //   81: istore_0
    //   82: bipush #105
    //   84: iinc #0, 1
    //   87: aload_2
    //   88: iload_0
    //   89: dup
    //   90: iload_1
    //   91: iadd
    //   92: invokevirtual substring : (II)Ljava/lang/String;
    //   95: iconst_0
    //   96: goto -> 143
    //   99: aload #5
    //   101: swap
    //   102: iload_3
    //   103: iinc #3, 1
    //   106: swap
    //   107: aastore
    //   108: iload_0
    //   109: iload_1
    //   110: iadd
    //   111: dup
    //   112: istore_0
    //   113: iload #4
    //   115: if_icmpge -> 127
    //   118: aload_2
    //   119: iload_0
    //   120: invokevirtual charAt : (I)C
    //   123: istore_1
    //   124: goto -> 82
    //   127: aload #5
    //   129: putstatic burp/Zrvb.a : [Ljava/lang/String;
    //   132: bipush #29
    //   134: anewarray java/lang/String
    //   137: putstatic burp/Zrvb.b : [Ljava/lang/String;
    //   140: goto -> 300
    //   143: dup_x2
    //   144: pop
    //   145: invokevirtual toCharArray : ()[C
    //   148: dup_x1
    //   149: arraylength
    //   150: dup_x2
    //   151: pop
    //   152: iconst_0
    //   153: istore #6
    //   155: dup2_x1
    //   156: pop2
    //   157: dup_x2
    //   158: iconst_1
    //   159: if_icmpgt -> 259
    //   162: dup2
    //   163: swap
    //   164: iload #6
    //   166: dup2_x1
    //   167: caload
    //   168: swap
    //   169: iload #6
    //   171: bipush #7
    //   173: irem
    //   174: tableswitch default -> 241, 0 -> 212, 1 -> 217, 2 -> 222, 3 -> 226, 4 -> 231, 5 -> 236
    //   212: bipush #52
    //   214: goto -> 243
    //   217: bipush #127
    //   219: goto -> 243
    //   222: iconst_2
    //   223: goto -> 243
    //   226: bipush #19
    //   228: goto -> 243
    //   231: bipush #72
    //   233: goto -> 243
    //   236: bipush #104
    //   238: goto -> 243
    //   241: bipush #64
    //   243: ixor
    //   244: ixor
    //   245: i2c
    //   246: castore
    //   247: iinc #6, 1
    //   250: dup
    //   251: ifne -> 259
    //   254: dup2
    //   255: dup_x1
    //   256: goto -> 166
    //   259: dup2_x1
    //   260: pop2
    //   261: dup_x2
    //   262: iload #6
    //   264: if_icmpgt -> 162
    //   267: pop
    //   268: new java/lang/String
    //   271: dup_x1
    //   272: swap
    //   273: invokespecial <init> : ([C)V
    //   276: invokevirtual intern : ()Ljava/lang/String;
    //   279: swap
    //   280: pop
    //   281: swap
    //   282: tableswitch default -> 40, 0 -> 99
    //   300: new java/math/BigInteger
    //   303: dup
    //   304: sipush #-15420
    //   307: sipush #7136
    //   310: invokestatic a : (II)Ljava/lang/String;
    //   313: invokespecial <init> : (Ljava/lang/String;)V
    //   316: putstatic burp/Zrvb.ZD : Ljava/lang/Object;
    //   319: sipush #-15405
    //   322: sipush #4675
    //   325: invokestatic a : (II)Ljava/lang/String;
    //   328: putstatic burp/Zrvb.ZU : Ljava/lang/String;
    //   331: return
  }
  
  private static Throwable a(Throwable paramThrowable) {
    return paramThrowable;
  }
  
  private static String a(int paramInt1, int paramInt2) {
    int i = (paramInt1 ^ 0xFFFFC3C6) & 0xFFFF;
    if (b[i] == null) {
      char[] arrayOfChar = a[i].toCharArray();
      switch (arrayOfChar[0] & 0xFF) {
        case 0:
        
        case 1:
        
        case 2:
        
        case 3:
        
        case 4:
        
        case 5:
        
        case 6:
        
        case 7:
        
        case 8:
        
        case 9:
        
        case 10:
        
        case 11:
        
        case 12:
        
        case 13:
        
        case 14:
        
        case 15:
        
        case 16:
        
        case 17:
        
        case 18:
        
        case 19:
        
        case 20:
        
        case 21:
        
        case 22:
        
        case 23:
        
        case 24:
        
        case 25:
        
        case 26:
        
        case 27:
        
        case 28:
        
        case 29:
        
        case 30:
        
        case 31:
        
        case 32:
        
        case 33:
        
        case 34:
        
        case 35:
        
        case 36:
        
        case 37:
        
        case 38:
        
        case 39:
        
        case 40:
        
        case 41:
        
        case 42:
        
        case 43:
        
        case 44:
        
        case 45:
        
        case 46:
        
        case 47:
        
        case 48:
        
        case 49:
        
        case 50:
        
        case 51:
        
        case 52:
        
        case 53:
        
        case 54:
        
        case 55:
        
        case 56:
        
        case 57:
        
        case 58:
        
        case 59:
        
        case 60:
        
        case 61:
        
        case 62:
        
        case 63:
        
        case 64:
        
        case 65:
        
        case 66:
        
        case 67:
        
        case 68:
        
        case 69:
        
        case 70:
        
        case 71:
        
        case 72:
        
        case 73:
        
        case 74:
        
        case 75:
        
        case 76:
        
        case 77:
        
        case 78:
        
        case 79:
        
        case 80:
        
        case 81:
        
        case 82:
        
        case 83:
        
        case 84:
        
        case 85:
        
        case 86:
        
        case 87:
        
        case 88:
        
        case 89:
        
        case 90:
        
        case 91:
        
        case 92:
        
        case 93:
        
        case 94:
        
        case 95:
        
        case 96:
        
        case 97:
        
        case 98:
        
        case 99:
        
        case 100:
        
        case 101:
        
        case 102:
        
        case 103:
        
        case 104:
        
        case 105:
        
        case 106:
        
        case 107:
        
        case 108:
        
        case 109:
        
        case 110:
        
        case 111:
        
        case 112:
        
        case 113:
        
        case 114:
        
        case 115:
        
        case 116:
        
        case 117:
        
        case 118:
        
        case 119:
        
        case 120:
        
        case 121:
        
        case 122:
        
        case 123:
        
        case 124:
        
        case 125:
        
        case 126:
        
        case 127:
        
        case 128:
        
        case 129:
        
        case 130:
        
        case 131:
        
        case 132:
        
        case 133:
        
        case 134:
        
        case 135:
        
        case 136:
        
        case 137:
        
        case 138:
        
        case 139:
        
        case 140:
        
        case 141:
        
        case 142:
        
        case 143:
        
        case 144:
        
        case 145:
        
        case 146:
        
        case 147:
        
        case 148:
        
        case 149:
        
        case 150:
        
        case 151:
        
        case 152:
        
        case 153:
        
        case 154:
        
        case 155:
        
        case 156:
        
        case 157:
        
        case 158:
        
        case 159:
        
        case 160:
        
        case 161:
        
        case 162:
        
        case 163:
        
        case 164:
        
        case 165:
        
        case 166:
        
        case 167:
        
        case 168:
        
        case 169:
        
        case 170:
        
        case 171:
        
        case 172:
        
        case 173:
        
        case 174:
        
        case 175:
        
        case 176:
        
        case 177:
        
        case 178:
        
        case 179:
        
        case 180:
        
        case 181:
        
        case 182:
        
        case 183:
        
        case 184:
        
        case 185:
        
        case 186:
        
        case 187:
        
        case 188:
        
        case 189:
        
        case 190:
        
        case 191:
        
        case 192:
        
        case 193:
        
        case 194:
        
        case 195:
        
        case 196:
        
        case 197:
        
        case 198:
        
        case 199:
        
        case 200:
        
        case 201:
        
        case 202:
        
        case 203:
        
        case 204:
        
        case 205:
        
        case 206:
        
        case 207:
        
        case 208:
        
        case 209:
        
        case 210:
        
        case 211:
        
        case 212:
        
        case 213:
        
        case 214:
        
        case 215:
        
        case 216:
        
        case 217:
        
        case 218:
        
        case 219:
        
        case 220:
        
        case 221:
        
        case 222:
        
        case 223:
        
        case 224:
        
        case 225:
        
        case 226:
        
        case 227:
        
        case 228:
        
        case 229:
        
        case 230:
        
        case 231:
        
        case 232:
        
        case 233:
        
        case 234:
        
        case 235:
        
        case 236:
        
        case 237:
        
        case 238:
        
        case 239:
        
        case 240:
        
        case 241:
        
        case 242:
        
        case 243:
        
        case 244:
        
        case 245:
        
        case 246:
        
        case 247:
        
        case 248:
        
        case 249:
        
        case 250:
        
        case 251:
        
        case 252:
        
        case 253:
        
        case 254:
        
        default:
          break;
      } 
      char c = '';
      int j = (paramInt2 & 0xFF) - c;
      if (j < 0)
        j += 256; 
      int k = ((paramInt2 & 0xFFFF) >>> 8) - c;
      if (k < 0)
        k += 256; 
      for (byte b = 0; b < arrayOfChar.length; b++) {
        int m = b % 2;
        if (m == 0) {
          arrayOfChar[b] = (char)(arrayOfChar[b] ^ j);
          j = ((j >>> 3 | j << 5) ^ arrayOfChar[b]) & 0xFF;
        } else {
          arrayOfChar[b] = (char)(arrayOfChar[b] ^ k);
          k = ((k >>> 3 | k << 5) ^ arrayOfChar[b]) & 0xFF;
        } 
      } 
      b[i] = (new String(arrayOfChar)).intern();
    } 
    return b[i];
  }
}


/* Location:              C:\Program Files\BurpSuitePro\burpsuite_pro.jar!\burp\Zrvb.class
 * Java compiler version: 21 (65.0)
 * JD-Core Version:       1.1.3
 */