package burp;

import java.awt.GridBagConstraints;
import java.awt.GridBagLayout;
import java.awt.Insets;
import java.awt.Window;
import java.awt.event.ActionEvent;
import javax.swing.BorderFactory;

public class Zrvh extends Zrh7 {
  private static String Zf;
  
  private Zm99 Zh;
  
  private Zm99 ZJ;
  
  private Zm99 Zm;
  
  private Zm99 Zk;
  
  private Zm99 Zw;
  
  private Zbqc ZR;
  
  private Zzdy ZU;
  
  private Ze01 ZX;
  
  private Zl8w ZK;
  
  private Zm99 ZV;
  
  private Zm99 Zy;
  
  private Zm99 Z_;
  
  private Ztln Zt;
  
  private static final String[] a;
  
  private static final String[] b;
  
  public static String Zm(Window paramWindow, String paramString1, String paramString2, String paramString3) {
    if (Zf != null)
      return Zf; 
    if (paramWindow != null && !paramWindow.isVisible())
      paramWindow = null; 
    Zrvh zrvh = new Zrvh(paramWindow, paramString1, paramString2, paramString3);
    zrvh.setVisible(true);
    String str = zrvh.Zq();
    if (zrvh.ZU.isSelected())
      Zf = str; 
    return str;
  }
  
  private Zrvh(Window paramWindow, String paramString1, String paramString2, String paramString3) {
    super(paramWindow, true, Zzv7.FILE_SPECIFIC_PASSWORD_UI_DIALOG);
    Zy();
    String str = Zbk_.Zb();
    this.Zt.requestFocus();
    setTitle(a(-19976, -16005));
    this.Zy.setText(paramString1);
    this.ZV.setText(paramString2);
    this.Z_.setText(paramString3);
    pack();
    if (paramWindow == null) {
      ZN((Window)null);
      if (str == null) {
        Zq(paramWindow);
        return;
      } 
      return;
    } 
    Zq(paramWindow);
  }
  
  public String Zq() {
    return new String(this.Zt.getPassword());
  }
  
  private void Zy() {
    this.ZR = new Zbqc();
    this.ZK = new Zl8w();
    this.Zh = new Zm99();
    this.ZJ = new Zm99();
    this.Zm = new Zm99();
    this.Zk = new Zm99();
    this.Zy = new Zm99();
    this.ZV = new Zm99();
    this.Z_ = new Zm99();
    this.Zt = new Ztln();
    this.ZU = new Zzdy();
    this.ZX = new Ze01();
    this.Zw = new Zm99();
    setDefaultCloseOperation(2);
    this.ZR.setBorder(BorderFactory.createEmptyBorder(15, 15, 15, 15));
    GridBagLayout gridBagLayout = new GridBagLayout();
    gridBagLayout.columnWidths = new int[] { 0, 5, 0, 5, 0, 5, 0, 5, 0 };
    gridBagLayout.rowHeights = new int[] { 
        0, 5, 0, 5, 0, 5, 0, 5, 0, 5, 
        0, 5, 0 };
    this.ZR.setLayout(gridBagLayout);
    this.ZK.setText(a(-19974, 2988));
    GridBagConstraints gridBagConstraints = new GridBagConstraints();
    gridBagConstraints.gridx = 2;
    gridBagConstraints.gridy = 0;
    gridBagConstraints.gridwidth = 3;
    gridBagConstraints.fill = 2;
    gridBagConstraints.anchor = 1280;
    gridBagConstraints.weightx = 1.0D;
    this.ZR.add(this.ZK, gridBagConstraints);
    this.Zh.setText(a(-19973, -20427));
    gridBagConstraints = new GridBagConstraints();
    gridBagConstraints.gridx = 2;
    gridBagConstraints.gridy = 2;
    gridBagConstraints.anchor = 1280;
    this.ZR.add(this.Zh, gridBagConstraints);
    this.ZJ.setText(a(-19975, 27691));
    gridBagConstraints = new GridBagConstraints();
    gridBagConstraints.gridx = 2;
    gridBagConstraints.gridy = 4;
    gridBagConstraints.anchor = 1280;
    this.ZR.add(this.ZJ, gridBagConstraints);
    this.Zm.setText(a(-19971, 26260));
    gridBagConstraints = new GridBagConstraints();
    gridBagConstraints.gridx = 2;
    gridBagConstraints.gridy = 6;
    gridBagConstraints.anchor = 1280;
    this.ZR.add(this.Zm, gridBagConstraints);
    this.Zk.setText(a(-19969, -11897));
    gridBagConstraints = new GridBagConstraints();
    gridBagConstraints.gridx = 2;
    gridBagConstraints.gridy = 10;
    gridBagConstraints.anchor = 1280;
    gridBagConstraints.insets = new Insets(0, 0, 0, 10);
    this.ZR.add(this.Zk, gridBagConstraints);
    gridBagConstraints = new GridBagConstraints();
    gridBagConstraints.gridx = 4;
    gridBagConstraints.gridy = 2;
    gridBagConstraints.gridwidth = 5;
    gridBagConstraints.anchor = 1280;
    this.ZR.add(this.Zy, gridBagConstraints);
    gridBagConstraints = new GridBagConstraints();
    gridBagConstraints.gridx = 4;
    gridBagConstraints.gridy = 4;
    gridBagConstraints.gridwidth = 5;
    gridBagConstraints.anchor = 1280;
    this.ZR.add(this.ZV, gridBagConstraints);
    gridBagConstraints = new GridBagConstraints();
    gridBagConstraints.gridx = 4;
    gridBagConstraints.gridy = 6;
    gridBagConstraints.gridwidth = 5;
    gridBagConstraints.anchor = 1280;
    this.ZR.add(this.Z_, gridBagConstraints);
    this.Zt.setColumns(20);
    this.Zt.addActionListener(new Zgl8(this));
    gridBagConstraints = new GridBagConstraints();
    gridBagConstraints.gridx = 4;
    gridBagConstraints.gridy = 10;
    gridBagConstraints.gridwidth = 5;
    gridBagConstraints.anchor = 1280;
    this.ZR.add(this.Zt, gridBagConstraints);
    this.ZU.setText(a(-19970, -9697));
    gridBagConstraints = new GridBagConstraints();
    gridBagConstraints.gridx = 2;
    gridBagConstraints.gridy = 12;
    gridBagConstraints.gridwidth = 3;
    gridBagConstraints.anchor = 2048;
    gridBagConstraints.insets = new Insets(20, 0, 0, 20);
    this.ZR.add(this.ZU, gridBagConstraints);
    this.ZX.setText(a(-19972, 3582));
    this.ZX.addActionListener(new Zkr9(this));
    gridBagConstraints = new GridBagConstraints();
    gridBagConstraints.gridx = 8;
    gridBagConstraints.gridy = 12;
    gridBagConstraints.anchor = 2304;
    gridBagConstraints.insets = new Insets(20, 0, 0, 0);
    this.ZR.add(this.ZX, gridBagConstraints);
    this.Zw.setText(" ");
    gridBagConstraints = new GridBagConstraints();
    gridBagConstraints.gridx = 2;
    gridBagConstraints.gridy = 8;
    this.ZR.add(this.Zw, gridBagConstraints);
    getContentPane().add(this.ZR, a(-19980, -24533));
    pack();
  }
  
  private void ZJ(ActionEvent paramActionEvent) {
    setVisible(false);
    dispose();
  }
  
  private void Zi(ActionEvent paramActionEvent) {
    ZJ(paramActionEvent);
  }
  
  static {
    // Byte code:
    //   0: bipush #9
    //   2: anewarray java/lang/String
    //   5: astore #5
    //   7: iconst_0
    //   8: istore_3
    //   9: ldc 'eZ\\tÃ}Ã£Ã’Ã„^Ã‘Â°=!Â°Â›Ã\ÂžwÂ–wÃ¨Â·Ãš\\rÂÂ¢Ã¦ÂŠÃ™Â§=8Â•9\\t#Z;sÂ‰Ã¦ÃŒ\\nÂ²&Â‡ÂªÃ¯Ã­Â±Â‘CÂ–{Â¸Ãvn~Ã™0D~Ã¥}ÃÃ›Ã³\\bÂš9Â‚,Ã¹ÂÃŠÃ­Â¹i,Ã¥4NÃ»^2\Â yCÂ¿\\fÂ¤Ãº\\bÂ’ÂŽÃ§|Ã–+\\nruÃ’yÃ¿Â³ÃšÂ›Ã‘Â¹*!\Ã‘H,Ã¹ÃºG2Z'\\nÃ‘Â»`WÃ•Ã—Ã:Ã•|\\f54Â«/Âœ's WÂžÃ†AÂ†Ã«Ã»Â‹Ãª^Ã«RÃÂ¬Â»Âƒ%zpÂ¾Ã™Ã†ÂƒÃ’Ã‹ÂµkPÃš=Ã—Â„sLÃ¡HÂ‚'
    //   11: dup
    //   12: astore_2
    //   13: invokevirtual length : ()I
    //   16: istore #4
    //   18: iconst_2
    //   19: istore_1
    //   20: iconst_m1
    //   21: istore_0
    //   22: bipush #105
    //   24: iinc #0, 1
    //   27: aload_2
    //   28: iload_0
    //   29: dup
    //   30: iload_1
    //   31: iadd
    //   32: invokevirtual substring : (II)Ljava/lang/String;
    //   35: iconst_m1
    //   36: goto -> 142
    //   39: aload #5
    //   41: swap
    //   42: iload_3
    //   43: iinc #3, 1
    //   46: swap
    //   47: aastore
    //   48: iload_0
    //   49: iload_1
    //   50: iadd
    //   51: dup
    //   52: istore_0
    //   53: iload #4
    //   55: if_icmpge -> 67
    //   58: aload_2
    //   59: iload_0
    //   60: invokevirtual charAt : (I)C
    //   63: istore_1
    //   64: goto -> 22
    //   67: ldc '&ÃŽÂ”YÃ§FÂ¥Â…Ã‰PÂœ`{'
    //   69: dup
    //   70: astore_2
    //   71: invokevirtual length : ()I
    //   74: istore #4
    //   76: bipush #8
    //   78: istore_1
    //   79: iconst_m1
    //   80: istore_0
    //   81: bipush #58
    //   83: iinc #0, 1
    //   86: aload_2
    //   87: iload_0
    //   88: dup
    //   89: iload_1
    //   90: iadd
    //   91: invokevirtual substring : (II)Ljava/lang/String;
    //   94: iconst_0
    //   95: goto -> 142
    //   98: aload #5
    //   100: swap
    //   101: iload_3
    //   102: iinc #3, 1
    //   105: swap
    //   106: aastore
    //   107: iload_0
    //   108: iload_1
    //   109: iadd
    //   110: dup
    //   111: istore_0
    //   112: iload #4
    //   114: if_icmpge -> 126
    //   117: aload_2
    //   118: iload_0
    //   119: invokevirtual charAt : (I)C
    //   122: istore_1
    //   123: goto -> 81
    //   126: aload #5
    //   128: putstatic burp/Zrvh.a : [Ljava/lang/String;
    //   131: bipush #9
    //   133: anewarray java/lang/String
    //   136: putstatic burp/Zrvh.b : [Ljava/lang/String;
    //   139: goto -> 300
    //   142: dup_x2
    //   143: pop
    //   144: invokevirtual toCharArray : ()[C
    //   147: dup_x1
    //   148: arraylength
    //   149: dup_x2
    //   150: pop
    //   151: iconst_0
    //   152: istore #6
    //   154: dup2_x1
    //   155: pop2
    //   156: dup_x2
    //   157: iconst_1
    //   158: if_icmpgt -> 259
    //   161: dup2
    //   162: swap
    //   163: iload #6
    //   165: dup2_x1
    //   166: caload
    //   167: swap
    //   168: iload #6
    //   170: bipush #7
    //   172: irem
    //   173: tableswitch default -> 242, 0 -> 212, 1 -> 217, 2 -> 222, 3 -> 227, 4 -> 232, 5 -> 237
    //   212: bipush #113
    //   214: goto -> 243
    //   217: bipush #57
    //   219: goto -> 243
    //   222: bipush #43
    //   224: goto -> 243
    //   227: bipush #113
    //   229: goto -> 243
    //   232: bipush #62
    //   234: goto -> 243
    //   237: bipush #51
    //   239: goto -> 243
    //   242: iconst_4
    //   243: ixor
    //   244: ixor
    //   245: i2c
    //   246: castore
    //   247: iinc #6, 1
    //   250: dup
    //   251: ifne -> 259
    //   254: dup2
    //   255: dup_x1
    //   256: goto -> 165
    //   259: dup2_x1
    //   260: pop2
    //   261: dup_x2
    //   262: iload #6
    //   264: if_icmpgt -> 161
    //   267: pop
    //   268: new java/lang/String
    //   271: dup_x1
    //   272: swap
    //   273: invokespecial <init> : ([C)V
    //   276: invokevirtual intern : ()Ljava/lang/String;
    //   279: swap
    //   280: pop
    //   281: swap
    //   282: tableswitch default -> 39, 0 -> 98
    //   300: return
  }
  
  private static String a(int paramInt1, int paramInt2) {
    int i = (paramInt1 ^ 0xFFFFB1FC) & 0xFFFF;
    if (b[i] == null) {
      char[] arrayOfChar = a[i].toCharArray();
      switch (arrayOfChar[0] & 0xFF) {
        case 0:
        
        case 1:
        
        case 2:
        
        case 3:
        
        case 4:
        
        case 5:
        
        case 6:
        
        case 7:
        
        case 8:
        
        case 9:
        
        case 10:
        
        case 11:
        
        case 12:
        
        case 13:
        
        case 14:
        
        case 15:
        
        case 16:
        
        case 17:
        
        case 18:
        
        case 19:
        
        case 20:
        
        case 21:
        
        case 22:
        
        case 23:
        
        case 24:
        
        case 25:
        
        case 26:
        
        case 27:
        
        case 28:
        
        case 29:
        
        case 30:
        
        case 31:
        
        case 32:
        
        case 33:
        
        case 34:
        
        case 35:
        
        case 36:
        
        case 37:
        
        case 38:
        
        case 39:
        
        case 40:
        
        case 41:
        
        case 42:
        
        case 43:
        
        case 44:
        
        case 45:
        
        case 46:
        
        case 47:
        
        case 48:
        
        case 49:
        
        case 50:
        
        case 51:
        
        case 52:
        
        case 53:
        
        case 54:
        
        case 55:
        
        case 56:
        
        case 57:
        
        case 58:
        
        case 59:
        
        case 60:
        
        case 61:
        
        case 62:
        
        case 63:
        
        case 64:
        
        case 65:
        
        case 66:
        
        case 67:
        
        case 68:
        
        case 69:
        
        case 70:
        
        case 71:
        
        case 72:
        
        case 73:
        
        case 74:
        
        case 75:
        
        case 76:
        
        case 77:
        
        case 78:
        
        case 79:
        
        case 80:
        
        case 81:
        
        case 82:
        
        case 83:
        
        case 84:
        
        case 85:
        
        case 86:
        
        case 87:
        
        case 88:
        
        case 89:
        
        case 90:
        
        case 91:
        
        case 92:
        
        case 93:
        
        case 94:
        
        case 95:
        
        case 96:
        
        case 97:
        
        case 98:
        
        case 99:
        
        case 100:
        
        case 101:
        
        case 102:
        
        case 103:
        
        case 104:
        
        case 105:
        
        case 106:
        
        case 107:
        
        case 108:
        
        case 109:
        
        case 110:
        
        case 111:
        
        case 112:
        
        case 113:
        
        case 114:
        
        case 115:
        
        case 116:
        
        case 117:
        
        case 118:
        
        case 119:
        
        case 120:
        
        case 121:
        
        case 122:
        
        case 123:
        
        case 124:
        
        case 125:
        
        case 126:
        
        case 127:
        
        case 128:
        
        case 129:
        
        case 130:
        
        case 131:
        
        case 132:
        
        case 133:
        
        case 134:
        
        case 135:
        
        case 136:
        
        case 137:
        
        case 138:
        
        case 139:
        
        case 140:
        
        case 141:
        
        case 142:
        
        case 143:
        
        case 144:
        
        case 145:
        
        case 146:
        
        case 147:
        
        case 148:
        
        case 149:
        
        case 150:
        
        case 151:
        
        case 152:
        
        case 153:
        
        case 154:
        
        case 155:
        
        case 156:
        
        case 157:
        
        case 158:
        
        case 159:
        
        case 160:
        
        case 161:
        
        case 162:
        
        case 163:
        
        case 164:
        
        case 165:
        
        case 166:
        
        case 167:
        
        case 168:
        
        case 169:
        
        case 170:
        
        case 171:
        
        case 172:
        
        case 173:
        
        case 174:
        
        case 175:
        
        case 176:
        
        case 177:
        
        case 178:
        
        case 179:
        
        case 180:
        
        case 181:
        
        case 182:
        
        case 183:
        
        case 184:
        
        case 185:
        
        case 186:
        
        case 187:
        
        case 188:
        
        case 189:
        
        case 190:
        
        case 191:
        
        case 192:
        
        case 193:
        
        case 194:
        
        case 195:
        
        case 196:
        
        case 197:
        
        case 198:
        
        case 199:
        
        case 200:
        
        case 201:
        
        case 202:
        
        case 203:
        
        case 204:
        
        case 205:
        
        case 206:
        
        case 207:
        
        case 208:
        
        case 209:
        
        case 210:
        
        case 211:
        
        case 212:
        
        case 213:
        
        case 214:
        
        case 215:
        
        case 216:
        
        case 217:
        
        case 218:
        
        case 219:
        
        case 220:
        
        case 221:
        
        case 222:
        
        case 223:
        
        case 224:
        
        case 225:
        
        case 226:
        
        case 227:
        
        case 228:
        
        case 229:
        
        case 230:
        
        case 231:
        
        case 232:
        
        case 233:
        
        case 234:
        
        case 235:
        
        case 236:
        
        case 237:
        
        case 238:
        
        case 239:
        
        case 240:
        
        case 241:
        
        case 242:
        
        case 243:
        
        case 244:
        
        case 245:
        
        case 246:
        
        case 247:
        
        case 248:
        
        case 249:
        
        case 250:
        
        case 251:
        
        case 252:
        
        case 253:
        
        case 254:
        
        default:
          break;
      } 
      byte b1 = 24;
      int j = (paramInt2 & 0xFF) - b1;
      if (j < 0)
        j += 256; 
      int k = ((paramInt2 & 0xFFFF) >>> 8) - b1;
      if (k < 0)
        k += 256; 
      for (byte b2 = 0; b2 < arrayOfChar.length; b2++) {
        int m = b2 % 2;
        if (m == 0) {
          arrayOfChar[b2] = (char)(arrayOfChar[b2] ^ j);
          j = ((j >>> 3 | j << 5) ^ arrayOfChar[b2]) & 0xFF;
        } else {
          arrayOfChar[b2] = (char)(arrayOfChar[b2] ^ k);
          k = ((k >>> 3 | k << 5) ^ arrayOfChar[b2]) & 0xFF;
        } 
      } 
      b[i] = (new String(arrayOfChar)).intern();
    } 
    return b[i];
  }
}


/* Location:              C:\Program Files\BurpSuitePro\burpsuite_pro.jar!\burp\Zrvh.class
 * Java compiler version: 21 (65.0)
 * JD-Core Version:       1.1.3
 */