package burp;

import java.math.BigInteger;

class Zrym extends ClassLoader {
  static String ZX;
  
  static Object Zk;
  
  private static final String[] a;
  
  private static final String[] b;
  
  static void ZV(Object[] paramArrayOfObject, Object paramObject) throws Throwable {}
  
  static boolean ZM(Object[] paramArrayOfObject, Object paramObject) throws Throwable {
    // Byte code:
    //   0: invokestatic ZK : ()Z
    //   3: istore_2
    //   4: getstatic burp/Zm69.Zg : Ljava/lang/Object;
    //   7: checkcast java/math/BigInteger
    //   10: invokevirtual toByteArray : ()[B
    //   13: astore_3
    //   14: new java/lang/StringBuilder
    //   17: dup
    //   18: invokespecial <init> : ()V
    //   21: astore #5
    //   23: aload #5
    //   25: sipush #20457
    //   28: sipush #-31433
    //   31: invokestatic a : (II)Ljava/lang/String;
    //   34: invokevirtual append : (Ljava/lang/String;)Ljava/lang/StringBuilder;
    //   37: pop
    //   38: aload_3
    //   39: astore #6
    //   41: aload #6
    //   43: arraylength
    //   44: istore #7
    //   46: iconst_0
    //   47: istore #8
    //   49: iload #8
    //   51: iload #7
    //   53: if_icmpge -> 79
    //   56: aload #6
    //   58: iload #8
    //   60: baload
    //   61: istore #9
    //   63: aload #5
    //   65: iload #9
    //   67: i2c
    //   68: invokevirtual append : (C)Ljava/lang/StringBuilder;
    //   71: pop
    //   72: iinc #8, 1
    //   75: iload_2
    //   76: ifeq -> 49
    //   79: aload #5
    //   81: sipush #20458
    //   84: sipush #-22751
    //   87: invokestatic a : (II)Ljava/lang/String;
    //   90: ldc ''
    //   92: invokestatic getProperty : (Ljava/lang/String;Ljava/lang/String;)Ljava/lang/String;
    //   95: invokevirtual toLowerCase : ()Ljava/lang/String;
    //   98: invokevirtual append : (Ljava/lang/String;)Ljava/lang/StringBuilder;
    //   101: pop
    //   102: aload #5
    //   104: sipush #20460
    //   107: sipush #-24619
    //   110: invokestatic a : (II)Ljava/lang/String;
    //   113: ldc ''
    //   115: invokestatic getProperty : (Ljava/lang/String;Ljava/lang/String;)Ljava/lang/String;
    //   118: invokevirtual toLowerCase : ()Ljava/lang/String;
    //   121: invokevirtual append : (Ljava/lang/String;)Ljava/lang/StringBuilder;
    //   124: pop
    //   125: aload #5
    //   127: invokevirtual toString : ()Ljava/lang/String;
    //   130: invokevirtual getBytes : ()[B
    //   133: astore #4
    //   135: aload #4
    //   137: astore_3
    //   138: aload_3
    //   139: arraylength
    //   140: bipush #8
    //   142: iadd
    //   143: bipush #6
    //   145: ishr
    //   146: iconst_1
    //   147: iadd
    //   148: bipush #16
    //   150: imul
    //   151: newarray int
    //   153: astore #5
    //   155: iconst_0
    //   156: istore #6
    //   158: iload #6
    //   160: aload_3
    //   161: arraylength
    //   162: if_icmpge -> 205
    //   165: aload_3
    //   166: iload #6
    //   168: baload
    //   169: sipush #255
    //   172: iand
    //   173: istore #7
    //   175: aload #5
    //   177: iload #6
    //   179: iconst_2
    //   180: ishr
    //   181: dup2
    //   182: iaload
    //   183: iload #7
    //   185: bipush #24
    //   187: iload #6
    //   189: iconst_4
    //   190: irem
    //   191: bipush #8
    //   193: imul
    //   194: isub
    //   195: ishl
    //   196: ior
    //   197: iastore
    //   198: iinc #6, 1
    //   201: iload_2
    //   202: ifeq -> 158
    //   205: aload #5
    //   207: iload #6
    //   209: iconst_2
    //   210: ishr
    //   211: dup2
    //   212: iaload
    //   213: sipush #128
    //   216: bipush #24
    //   218: iload #6
    //   220: iconst_4
    //   221: irem
    //   222: bipush #8
    //   224: imul
    //   225: isub
    //   226: ishl
    //   227: ior
    //   228: iastore
    //   229: aload #5
    //   231: aload #5
    //   233: arraylength
    //   234: iconst_1
    //   235: isub
    //   236: aload_3
    //   237: arraylength
    //   238: bipush #8
    //   240: imul
    //   241: iastore
    //   242: bipush #80
    //   244: newarray int
    //   246: astore #7
    //   248: ldc 1732584193
    //   250: istore #8
    //   252: ldc -271733879
    //   254: istore #9
    //   256: ldc -1732584194
    //   258: istore #10
    //   260: ldc 271733878
    //   262: istore #11
    //   264: ldc -1009589776
    //   266: istore #12
    //   268: iconst_0
    //   269: istore #6
    //   271: iload #6
    //   273: aload #5
    //   275: arraylength
    //   276: if_icmpge -> 598
    //   279: iload #8
    //   281: istore #13
    //   283: iload #9
    //   285: istore #14
    //   287: iload #10
    //   289: istore #15
    //   291: iload #11
    //   293: istore #16
    //   295: iload #12
    //   297: istore #17
    //   299: iconst_0
    //   300: istore #18
    //   302: iload #18
    //   304: bipush #80
    //   306: if_icmpge -> 556
    //   309: iload #18
    //   311: bipush #16
    //   313: if_icmpge -> 340
    //   316: aload #7
    //   318: iload #18
    //   320: aload #5
    //   322: iload #6
    //   324: iload #18
    //   326: iadd
    //   327: iaload
    //   328: iastore
    //   329: iload_2
    //   330: ifeq -> 395
    //   333: goto -> 340
    //   336: invokestatic a : (Ljava/lang/Throwable;)Ljava/lang/Throwable;
    //   339: athrow
    //   340: aload #7
    //   342: iload #18
    //   344: iconst_3
    //   345: isub
    //   346: iaload
    //   347: aload #7
    //   349: iload #18
    //   351: bipush #8
    //   353: isub
    //   354: iaload
    //   355: ixor
    //   356: aload #7
    //   358: iload #18
    //   360: bipush #14
    //   362: isub
    //   363: iaload
    //   364: ixor
    //   365: aload #7
    //   367: iload #18
    //   369: bipush #16
    //   371: isub
    //   372: iaload
    //   373: ixor
    //   374: istore #19
    //   376: iload #19
    //   378: iconst_1
    //   379: ishl
    //   380: iload #19
    //   382: bipush #31
    //   384: iushr
    //   385: ior
    //   386: istore #20
    //   388: aload #7
    //   390: iload #18
    //   392: iload #20
    //   394: iastore
    //   395: iload #8
    //   397: iconst_5
    //   398: ishl
    //   399: iload #8
    //   401: bipush #27
    //   403: iushr
    //   404: ior
    //   405: istore #19
    //   407: iload #19
    //   409: iload #12
    //   411: iadd
    //   412: aload #7
    //   414: iload #18
    //   416: iaload
    //   417: iadd
    //   418: iload #18
    //   420: bipush #20
    //   422: if_icmpge -> 448
    //   425: ldc 1518500249
    //   427: iload #9
    //   429: iload #10
    //   431: iand
    //   432: iload #9
    //   434: iconst_m1
    //   435: ixor
    //   436: iload #11
    //   438: iand
    //   439: ior
    //   440: iadd
    //   441: goto -> 518
    //   444: invokestatic a : (Ljava/lang/Throwable;)Ljava/lang/Throwable;
    //   447: athrow
    //   448: iload #18
    //   450: bipush #40
    //   452: if_icmpge -> 473
    //   455: ldc 1859775393
    //   457: iload #9
    //   459: iload #10
    //   461: ixor
    //   462: iload #11
    //   464: ixor
    //   465: iadd
    //   466: goto -> 518
    //   469: invokestatic a : (Ljava/lang/Throwable;)Ljava/lang/Throwable;
    //   472: athrow
    //   473: iload #18
    //   475: bipush #60
    //   477: if_icmpge -> 507
    //   480: ldc -1894007588
    //   482: iload #9
    //   484: iload #10
    //   486: iand
    //   487: iload #9
    //   489: iload #11
    //   491: iand
    //   492: ior
    //   493: iload #10
    //   495: iload #11
    //   497: iand
    //   498: ior
    //   499: iadd
    //   500: goto -> 518
    //   503: invokestatic a : (Ljava/lang/Throwable;)Ljava/lang/Throwable;
    //   506: athrow
    //   507: ldc -899497514
    //   509: iload #9
    //   511: iload #10
    //   513: ixor
    //   514: iload #11
    //   516: ixor
    //   517: iadd
    //   518: iadd
    //   519: istore #20
    //   521: iload #11
    //   523: istore #12
    //   525: iload #10
    //   527: istore #11
    //   529: iload #9
    //   531: bipush #30
    //   533: ishl
    //   534: iload #9
    //   536: iconst_2
    //   537: iushr
    //   538: ior
    //   539: istore #10
    //   541: iload #8
    //   543: istore #9
    //   545: iload #20
    //   547: istore #8
    //   549: iinc #18, 1
    //   552: iload_2
    //   553: ifeq -> 302
    //   556: iload #8
    //   558: iload #13
    //   560: iadd
    //   561: istore #8
    //   563: iload #9
    //   565: iload #14
    //   567: iadd
    //   568: istore #9
    //   570: iload #10
    //   572: iload #15
    //   574: iadd
    //   575: istore #10
    //   577: iload #11
    //   579: iload #16
    //   581: iadd
    //   582: istore #11
    //   584: iload #12
    //   586: iload #17
    //   588: iadd
    //   589: istore #12
    //   591: iinc #6, 16
    //   594: iload_2
    //   595: ifeq -> 271
    //   598: iconst_5
    //   599: newarray int
    //   601: dup
    //   602: iconst_0
    //   603: iload #8
    //   605: iastore
    //   606: dup
    //   607: iconst_1
    //   608: iload #9
    //   610: iastore
    //   611: dup
    //   612: iconst_2
    //   613: iload #10
    //   615: iastore
    //   616: dup
    //   617: iconst_3
    //   618: iload #11
    //   620: iastore
    //   621: dup
    //   622: iconst_4
    //   623: iload #12
    //   625: iastore
    //   626: astore #13
    //   628: bipush #20
    //   630: newarray byte
    //   632: astore #14
    //   634: iconst_0
    //   635: istore #15
    //   637: iload #15
    //   639: bipush #20
    //   641: if_icmpge -> 682
    //   644: aload #13
    //   646: iload #15
    //   648: iconst_4
    //   649: idiv
    //   650: iaload
    //   651: istore #16
    //   653: iconst_3
    //   654: iload #15
    //   656: iconst_4
    //   657: irem
    //   658: isub
    //   659: bipush #8
    //   661: imul
    //   662: istore #17
    //   664: aload #14
    //   666: iload #15
    //   668: iload #16
    //   670: iload #17
    //   672: iushr
    //   673: i2b
    //   674: bastore
    //   675: iinc #15, 1
    //   678: iload_2
    //   679: ifeq -> 637
    //   682: aload #14
    //   684: astore #4
    //   686: getstatic burp/Zxxf.ZZ : Ljava/lang/Object;
    //   689: checkcast java/math/BigInteger
    //   692: getstatic burp/Zzyb.ZV : Ljava/lang/Object;
    //   695: checkcast java/math/BigInteger
    //   698: invokevirtual add : (Ljava/math/BigInteger;)Ljava/math/BigInteger;
    //   701: putstatic burp/Zrnk.ZM : Ljava/lang/Object;
    //   704: new java/lang/StringBuilder
    //   707: dup
    //   708: invokespecial <init> : ()V
    //   711: astore_3
    //   712: iconst_0
    //   713: istore #4
    //   715: iload #4
    //   717: bipush #32
    //   719: if_icmpge -> 2055
    //   722: iload #4
    //   724: tableswitch default -> 2048, 0 -> 868, 1 -> 905, 2 -> 942, 3 -> 979, 4 -> 1016, 5 -> 1053, 6 -> 1090, 7 -> 1127, 8 -> 1164, 9 -> 1201, 10 -> 1238, 11 -> 1275, 12 -> 1312, 13 -> 1349, 14 -> 1386, 15 -> 1423, 16 -> 1460, 17 -> 1497, 18 -> 1534, 19 -> 1571, 20 -> 1608, 21 -> 1645, 22 -> 1682, 23 -> 1719, 24 -> 1756, 25 -> 1793, 26 -> 1830, 27 -> 1867, 28 -> 1904, 29 -> 1941, 30 -> 1978, 31 -> 2015
    //   868: aload_3
    //   869: getstatic burp/Zt9f.Zg : Ljava/lang/String;
    //   872: getstatic burp/Zk7o.ZO : Ljava/lang/Object;
    //   875: checkcast java/math/BigInteger
    //   878: invokevirtual intValue : ()I
    //   881: bipush #32
    //   883: irem
    //   884: invokestatic abs : (I)I
    //   887: invokevirtual charAt : (I)C
    //   890: invokevirtual append : (C)Ljava/lang/StringBuilder;
    //   893: pop
    //   894: iload_2
    //   895: ifeq -> 2048
    //   898: goto -> 905
    //   901: invokestatic a : (Ljava/lang/Throwable;)Ljava/lang/Throwable;
    //   904: athrow
    //   905: aload_3
    //   906: getstatic burp/Zvob.Zn : Ljava/lang/String;
    //   909: getstatic burp/Zg4z.ZB : Ljava/lang/Object;
    //   912: checkcast java/math/BigInteger
    //   915: invokevirtual intValue : ()I
    //   918: bipush #32
    //   920: irem
    //   921: invokestatic abs : (I)I
    //   924: invokevirtual charAt : (I)C
    //   927: invokevirtual append : (C)Ljava/lang/StringBuilder;
    //   930: pop
    //   931: iload_2
    //   932: ifeq -> 2048
    //   935: goto -> 942
    //   938: invokestatic a : (Ljava/lang/Throwable;)Ljava/lang/Throwable;
    //   941: athrow
    //   942: aload_3
    //   943: getstatic burp/Zmdi.ZA : Ljava/lang/String;
    //   946: getstatic burp/Zkca.ZQ : Ljava/lang/Object;
    //   949: checkcast java/math/BigInteger
    //   952: invokevirtual intValue : ()I
    //   955: bipush #32
    //   957: irem
    //   958: invokestatic abs : (I)I
    //   961: invokevirtual charAt : (I)C
    //   964: invokevirtual append : (C)Ljava/lang/StringBuilder;
    //   967: pop
    //   968: iload_2
    //   969: ifeq -> 2048
    //   972: goto -> 979
    //   975: invokestatic a : (Ljava/lang/Throwable;)Ljava/lang/Throwable;
    //   978: athrow
    //   979: aload_3
    //   980: getstatic burp/Zenr.Z_ : Ljava/lang/String;
    //   983: getstatic burp/Zlab.ZM : Ljava/lang/Object;
    //   986: checkcast java/math/BigInteger
    //   989: invokevirtual intValue : ()I
    //   992: bipush #32
    //   994: irem
    //   995: invokestatic abs : (I)I
    //   998: invokevirtual charAt : (I)C
    //   1001: invokevirtual append : (C)Ljava/lang/StringBuilder;
    //   1004: pop
    //   1005: iload_2
    //   1006: ifeq -> 2048
    //   1009: goto -> 1016
    //   1012: invokestatic a : (Ljava/lang/Throwable;)Ljava/lang/Throwable;
    //   1015: athrow
    //   1016: aload_3
    //   1017: getstatic burp/Zkkl.Zh : Ljava/lang/String;
    //   1020: getstatic burp/Zea.ZO : Ljava/lang/Object;
    //   1023: checkcast java/math/BigInteger
    //   1026: invokevirtual intValue : ()I
    //   1029: bipush #32
    //   1031: irem
    //   1032: invokestatic abs : (I)I
    //   1035: invokevirtual charAt : (I)C
    //   1038: invokevirtual append : (C)Ljava/lang/StringBuilder;
    //   1041: pop
    //   1042: iload_2
    //   1043: ifeq -> 2048
    //   1046: goto -> 1053
    //   1049: invokestatic a : (Ljava/lang/Throwable;)Ljava/lang/Throwable;
    //   1052: athrow
    //   1053: aload_3
    //   1054: getstatic burp/Zz4a.ZC : Ljava/lang/String;
    //   1057: getstatic burp/Zv8d.ZN : Ljava/lang/Object;
    //   1060: checkcast java/math/BigInteger
    //   1063: invokevirtual intValue : ()I
    //   1066: bipush #32
    //   1068: irem
    //   1069: invokestatic abs : (I)I
    //   1072: invokevirtual charAt : (I)C
    //   1075: invokevirtual append : (C)Ljava/lang/StringBuilder;
    //   1078: pop
    //   1079: iload_2
    //   1080: ifeq -> 2048
    //   1083: goto -> 1090
    //   1086: invokestatic a : (Ljava/lang/Throwable;)Ljava/lang/Throwable;
    //   1089: athrow
    //   1090: aload_3
    //   1091: getstatic burp/Zzi_.ZG : Ljava/lang/String;
    //   1094: getstatic burp/Zrnt.Zh : Ljava/lang/Object;
    //   1097: checkcast java/math/BigInteger
    //   1100: invokevirtual intValue : ()I
    //   1103: bipush #32
    //   1105: irem
    //   1106: invokestatic abs : (I)I
    //   1109: invokevirtual charAt : (I)C
    //   1112: invokevirtual append : (C)Ljava/lang/StringBuilder;
    //   1115: pop
    //   1116: iload_2
    //   1117: ifeq -> 2048
    //   1120: goto -> 1127
    //   1123: invokestatic a : (Ljava/lang/Throwable;)Ljava/lang/Throwable;
    //   1126: athrow
    //   1127: aload_3
    //   1128: getstatic burp/Zeqx.Zu : Ljava/lang/String;
    //   1131: getstatic burp/Zrom.ZF : Ljava/lang/Object;
    //   1134: checkcast java/math/BigInteger
    //   1137: invokevirtual intValue : ()I
    //   1140: bipush #32
    //   1142: irem
    //   1143: invokestatic abs : (I)I
    //   1146: invokevirtual charAt : (I)C
    //   1149: invokevirtual append : (C)Ljava/lang/StringBuilder;
    //   1152: pop
    //   1153: iload_2
    //   1154: ifeq -> 2048
    //   1157: goto -> 1164
    //   1160: invokestatic a : (Ljava/lang/Throwable;)Ljava/lang/Throwable;
    //   1163: athrow
    //   1164: aload_3
    //   1165: getstatic burp/Zbx4.ZS : Ljava/lang/String;
    //   1168: getstatic burp/Zmyk.Za : Ljava/lang/Object;
    //   1171: checkcast java/math/BigInteger
    //   1174: invokevirtual intValue : ()I
    //   1177: bipush #32
    //   1179: irem
    //   1180: invokestatic abs : (I)I
    //   1183: invokevirtual charAt : (I)C
    //   1186: invokevirtual append : (C)Ljava/lang/StringBuilder;
    //   1189: pop
    //   1190: iload_2
    //   1191: ifeq -> 2048
    //   1194: goto -> 1201
    //   1197: invokestatic a : (Ljava/lang/Throwable;)Ljava/lang/Throwable;
    //   1200: athrow
    //   1201: aload_3
    //   1202: getstatic burp/Zzhx.ZV : Ljava/lang/String;
    //   1205: getstatic burp/Zthx.ZH : Ljava/lang/Object;
    //   1208: checkcast java/math/BigInteger
    //   1211: invokevirtual intValue : ()I
    //   1214: bipush #32
    //   1216: irem
    //   1217: invokestatic abs : (I)I
    //   1220: invokevirtual charAt : (I)C
    //   1223: invokevirtual append : (C)Ljava/lang/StringBuilder;
    //   1226: pop
    //   1227: iload_2
    //   1228: ifeq -> 2048
    //   1231: goto -> 1238
    //   1234: invokestatic a : (Ljava/lang/Throwable;)Ljava/lang/Throwable;
    //   1237: athrow
    //   1238: aload_3
    //   1239: getstatic burp/Zxju.Zt : Ljava/lang/String;
    //   1242: getstatic burp/Zzl4.ZX : Ljava/lang/Object;
    //   1245: checkcast java/math/BigInteger
    //   1248: invokevirtual intValue : ()I
    //   1251: bipush #32
    //   1253: irem
    //   1254: invokestatic abs : (I)I
    //   1257: invokevirtual charAt : (I)C
    //   1260: invokevirtual append : (C)Ljava/lang/StringBuilder;
    //   1263: pop
    //   1264: iload_2
    //   1265: ifeq -> 2048
    //   1268: goto -> 1275
    //   1271: invokestatic a : (Ljava/lang/Throwable;)Ljava/lang/Throwable;
    //   1274: athrow
    //   1275: aload_3
    //   1276: getstatic burp/Zrnk.Zb : Ljava/lang/String;
    //   1279: getstatic burp/Zz0b.ZT : Ljava/lang/Object;
    //   1282: checkcast java/math/BigInteger
    //   1285: invokevirtual intValue : ()I
    //   1288: bipush #32
    //   1290: irem
    //   1291: invokestatic abs : (I)I
    //   1294: invokevirtual charAt : (I)C
    //   1297: invokevirtual append : (C)Ljava/lang/StringBuilder;
    //   1300: pop
    //   1301: iload_2
    //   1302: ifeq -> 2048
    //   1305: goto -> 1312
    //   1308: invokestatic a : (Ljava/lang/Throwable;)Ljava/lang/Throwable;
    //   1311: athrow
    //   1312: aload_3
    //   1313: getstatic burp/Ze1k.ZI : Ljava/lang/String;
    //   1316: getstatic burp/Zlt1.ZH : Ljava/lang/Object;
    //   1319: checkcast java/math/BigInteger
    //   1322: invokevirtual intValue : ()I
    //   1325: bipush #32
    //   1327: irem
    //   1328: invokestatic abs : (I)I
    //   1331: invokevirtual charAt : (I)C
    //   1334: invokevirtual append : (C)Ljava/lang/StringBuilder;
    //   1337: pop
    //   1338: iload_2
    //   1339: ifeq -> 2048
    //   1342: goto -> 1349
    //   1345: invokestatic a : (Ljava/lang/Throwable;)Ljava/lang/Throwable;
    //   1348: athrow
    //   1349: aload_3
    //   1350: getstatic burp/Zb2u.ZM : Ljava/lang/String;
    //   1353: getstatic burp/Zbjx.ZT : Ljava/lang/Object;
    //   1356: checkcast java/math/BigInteger
    //   1359: invokevirtual intValue : ()I
    //   1362: bipush #32
    //   1364: irem
    //   1365: invokestatic abs : (I)I
    //   1368: invokevirtual charAt : (I)C
    //   1371: invokevirtual append : (C)Ljava/lang/StringBuilder;
    //   1374: pop
    //   1375: iload_2
    //   1376: ifeq -> 2048
    //   1379: goto -> 1386
    //   1382: invokestatic a : (Ljava/lang/Throwable;)Ljava/lang/Throwable;
    //   1385: athrow
    //   1386: aload_3
    //   1387: getstatic burp/Ze25.Zp : Ljava/lang/String;
    //   1390: getstatic burp/Zld5.ZX : Ljava/lang/Object;
    //   1393: checkcast java/math/BigInteger
    //   1396: invokevirtual intValue : ()I
    //   1399: bipush #32
    //   1401: irem
    //   1402: invokestatic abs : (I)I
    //   1405: invokevirtual charAt : (I)C
    //   1408: invokevirtual append : (C)Ljava/lang/StringBuilder;
    //   1411: pop
    //   1412: iload_2
    //   1413: ifeq -> 2048
    //   1416: goto -> 1423
    //   1419: invokestatic a : (Ljava/lang/Throwable;)Ljava/lang/Throwable;
    //   1422: athrow
    //   1423: aload_3
    //   1424: getstatic burp/Zbze.ZK : Ljava/lang/String;
    //   1427: getstatic burp/Znu.Zf : Ljava/lang/Object;
    //   1430: checkcast java/math/BigInteger
    //   1433: invokevirtual intValue : ()I
    //   1436: bipush #32
    //   1438: irem
    //   1439: invokestatic abs : (I)I
    //   1442: invokevirtual charAt : (I)C
    //   1445: invokevirtual append : (C)Ljava/lang/StringBuilder;
    //   1448: pop
    //   1449: iload_2
    //   1450: ifeq -> 2048
    //   1453: goto -> 1460
    //   1456: invokestatic a : (Ljava/lang/Throwable;)Ljava/lang/Throwable;
    //   1459: athrow
    //   1460: aload_3
    //   1461: getstatic burp/Zrye.Za : Ljava/lang/String;
    //   1464: getstatic burp/Zxn9.ZN : Ljava/lang/Object;
    //   1467: checkcast java/math/BigInteger
    //   1470: invokevirtual intValue : ()I
    //   1473: bipush #32
    //   1475: irem
    //   1476: invokestatic abs : (I)I
    //   1479: invokevirtual charAt : (I)C
    //   1482: invokevirtual append : (C)Ljava/lang/StringBuilder;
    //   1485: pop
    //   1486: iload_2
    //   1487: ifeq -> 2048
    //   1490: goto -> 1497
    //   1493: invokestatic a : (Ljava/lang/Throwable;)Ljava/lang/Throwable;
    //   1496: athrow
    //   1497: aload_3
    //   1498: getstatic burp/Zlgh.Zm : Ljava/lang/String;
    //   1501: getstatic burp/Ztq8.Zm : Ljava/lang/Object;
    //   1504: checkcast java/math/BigInteger
    //   1507: invokevirtual intValue : ()I
    //   1510: bipush #32
    //   1512: irem
    //   1513: invokestatic abs : (I)I
    //   1516: invokevirtual charAt : (I)C
    //   1519: invokevirtual append : (C)Ljava/lang/StringBuilder;
    //   1522: pop
    //   1523: iload_2
    //   1524: ifeq -> 2048
    //   1527: goto -> 1534
    //   1530: invokestatic a : (Ljava/lang/Throwable;)Ljava/lang/Throwable;
    //   1533: athrow
    //   1534: aload_3
    //   1535: getstatic burp/Zkhf.Zb : Ljava/lang/String;
    //   1538: getstatic burp/Ztvy.ZH : Ljava/lang/Object;
    //   1541: checkcast java/math/BigInteger
    //   1544: invokevirtual intValue : ()I
    //   1547: bipush #32
    //   1549: irem
    //   1550: invokestatic abs : (I)I
    //   1553: invokevirtual charAt : (I)C
    //   1556: invokevirtual append : (C)Ljava/lang/StringBuilder;
    //   1559: pop
    //   1560: iload_2
    //   1561: ifeq -> 2048
    //   1564: goto -> 1571
    //   1567: invokestatic a : (Ljava/lang/Throwable;)Ljava/lang/Throwable;
    //   1570: athrow
    //   1571: aload_3
    //   1572: getstatic burp/Zry1.Zk : Ljava/lang/String;
    //   1575: getstatic burp/Zl1e.Zp : Ljava/lang/Object;
    //   1578: checkcast java/math/BigInteger
    //   1581: invokevirtual intValue : ()I
    //   1584: bipush #32
    //   1586: irem
    //   1587: invokestatic abs : (I)I
    //   1590: invokevirtual charAt : (I)C
    //   1593: invokevirtual append : (C)Ljava/lang/StringBuilder;
    //   1596: pop
    //   1597: iload_2
    //   1598: ifeq -> 2048
    //   1601: goto -> 1608
    //   1604: invokestatic a : (Ljava/lang/Throwable;)Ljava/lang/Throwable;
    //   1607: athrow
    //   1608: aload_3
    //   1609: getstatic burp/Zs0h.ZX : Ljava/lang/String;
    //   1612: getstatic burp/Zr6c.ZG : Ljava/lang/Object;
    //   1615: checkcast java/math/BigInteger
    //   1618: invokevirtual intValue : ()I
    //   1621: bipush #32
    //   1623: irem
    //   1624: invokestatic abs : (I)I
    //   1627: invokevirtual charAt : (I)C
    //   1630: invokevirtual append : (C)Ljava/lang/StringBuilder;
    //   1633: pop
    //   1634: iload_2
    //   1635: ifeq -> 2048
    //   1638: goto -> 1645
    //   1641: invokestatic a : (Ljava/lang/Throwable;)Ljava/lang/Throwable;
    //   1644: athrow
    //   1645: aload_3
    //   1646: getstatic burp/Zzyb.Zh : Ljava/lang/String;
    //   1649: getstatic burp/Zegv.ZL : Ljava/lang/Object;
    //   1652: checkcast java/math/BigInteger
    //   1655: invokevirtual intValue : ()I
    //   1658: bipush #32
    //   1660: irem
    //   1661: invokestatic abs : (I)I
    //   1664: invokevirtual charAt : (I)C
    //   1667: invokevirtual append : (C)Ljava/lang/StringBuilder;
    //   1670: pop
    //   1671: iload_2
    //   1672: ifeq -> 2048
    //   1675: goto -> 1682
    //   1678: invokestatic a : (Ljava/lang/Throwable;)Ljava/lang/Throwable;
    //   1681: athrow
    //   1682: aload_3
    //   1683: getstatic burp/Zeqz.ZV : Ljava/lang/String;
    //   1686: getstatic burp/Zrzg.ZA : Ljava/lang/Object;
    //   1689: checkcast java/math/BigInteger
    //   1692: invokevirtual intValue : ()I
    //   1695: bipush #32
    //   1697: irem
    //   1698: invokestatic abs : (I)I
    //   1701: invokevirtual charAt : (I)C
    //   1704: invokevirtual append : (C)Ljava/lang/StringBuilder;
    //   1707: pop
    //   1708: iload_2
    //   1709: ifeq -> 2048
    //   1712: goto -> 1719
    //   1715: invokestatic a : (Ljava/lang/Throwable;)Ljava/lang/Throwable;
    //   1718: athrow
    //   1719: aload_3
    //   1720: getstatic burp/Ztlo.Zs : Ljava/lang/String;
    //   1723: getstatic burp/Zzef.Zw : Ljava/lang/Object;
    //   1726: checkcast java/math/BigInteger
    //   1729: invokevirtual intValue : ()I
    //   1732: bipush #32
    //   1734: irem
    //   1735: invokestatic abs : (I)I
    //   1738: invokevirtual charAt : (I)C
    //   1741: invokevirtual append : (C)Ljava/lang/StringBuilder;
    //   1744: pop
    //   1745: iload_2
    //   1746: ifeq -> 2048
    //   1749: goto -> 1756
    //   1752: invokestatic a : (Ljava/lang/Throwable;)Ljava/lang/Throwable;
    //   1755: athrow
    //   1756: aload_3
    //   1757: getstatic burp/Zg2u.Zy : Ljava/lang/String;
    //   1760: getstatic burp/Zbw5.ZR : Ljava/lang/Object;
    //   1763: checkcast java/math/BigInteger
    //   1766: invokevirtual intValue : ()I
    //   1769: bipush #32
    //   1771: irem
    //   1772: invokestatic abs : (I)I
    //   1775: invokevirtual charAt : (I)C
    //   1778: invokevirtual append : (C)Ljava/lang/StringBuilder;
    //   1781: pop
    //   1782: iload_2
    //   1783: ifeq -> 2048
    //   1786: goto -> 1793
    //   1789: invokestatic a : (Ljava/lang/Throwable;)Ljava/lang/Throwable;
    //   1792: athrow
    //   1793: aload_3
    //   1794: getstatic burp/Ztq2.Zt : Ljava/lang/String;
    //   1797: getstatic burp/Zrnk.ZM : Ljava/lang/Object;
    //   1800: checkcast java/math/BigInteger
    //   1803: invokevirtual intValue : ()I
    //   1806: bipush #32
    //   1808: irem
    //   1809: invokestatic abs : (I)I
    //   1812: invokevirtual charAt : (I)C
    //   1815: invokevirtual append : (C)Ljava/lang/StringBuilder;
    //   1818: pop
    //   1819: iload_2
    //   1820: ifeq -> 2048
    //   1823: goto -> 1830
    //   1826: invokestatic a : (Ljava/lang/Throwable;)Ljava/lang/Throwable;
    //   1829: athrow
    //   1830: aload_3
    //   1831: getstatic burp/Zes.ZW : Ljava/lang/String;
    //   1834: getstatic burp/Zb9q.ZI : Ljava/lang/Object;
    //   1837: checkcast java/math/BigInteger
    //   1840: invokevirtual intValue : ()I
    //   1843: bipush #32
    //   1845: irem
    //   1846: invokestatic abs : (I)I
    //   1849: invokevirtual charAt : (I)C
    //   1852: invokevirtual append : (C)Ljava/lang/StringBuilder;
    //   1855: pop
    //   1856: iload_2
    //   1857: ifeq -> 2048
    //   1860: goto -> 1867
    //   1863: invokestatic a : (Ljava/lang/Throwable;)Ljava/lang/Throwable;
    //   1866: athrow
    //   1867: aload_3
    //   1868: getstatic burp/Zrl5.ZG : Ljava/lang/String;
    //   1871: getstatic burp/Ztq8.Zm : Ljava/lang/Object;
    //   1874: checkcast java/math/BigInteger
    //   1877: invokevirtual intValue : ()I
    //   1880: bipush #32
    //   1882: irem
    //   1883: invokestatic abs : (I)I
    //   1886: invokevirtual charAt : (I)C
    //   1889: invokevirtual append : (C)Ljava/lang/StringBuilder;
    //   1892: pop
    //   1893: iload_2
    //   1894: ifeq -> 2048
    //   1897: goto -> 1904
    //   1900: invokestatic a : (Ljava/lang/Throwable;)Ljava/lang/Throwable;
    //   1903: athrow
    //   1904: aload_3
    //   1905: getstatic burp/Zsvd.ZB : Ljava/lang/String;
    //   1908: getstatic burp/Ztdl.Zw : Ljava/lang/Object;
    //   1911: checkcast java/math/BigInteger
    //   1914: invokevirtual intValue : ()I
    //   1917: bipush #32
    //   1919: irem
    //   1920: invokestatic abs : (I)I
    //   1923: invokevirtual charAt : (I)C
    //   1926: invokevirtual append : (C)Ljava/lang/StringBuilder;
    //   1929: pop
    //   1930: iload_2
    //   1931: ifeq -> 2048
    //   1934: goto -> 1941
    //   1937: invokestatic a : (Ljava/lang/Throwable;)Ljava/lang/Throwable;
    //   1940: athrow
    //   1941: aload_3
    //   1942: getstatic burp/Zz4a.ZC : Ljava/lang/String;
    //   1945: getstatic burp/Zrgo.ZJ : Ljava/lang/Object;
    //   1948: checkcast java/math/BigInteger
    //   1951: invokevirtual intValue : ()I
    //   1954: bipush #32
    //   1956: irem
    //   1957: invokestatic abs : (I)I
    //   1960: invokevirtual charAt : (I)C
    //   1963: invokevirtual append : (C)Ljava/lang/StringBuilder;
    //   1966: pop
    //   1967: iload_2
    //   1968: ifeq -> 2048
    //   1971: goto -> 1978
    //   1974: invokestatic a : (Ljava/lang/Throwable;)Ljava/lang/Throwable;
    //   1977: athrow
    //   1978: aload_3
    //   1979: getstatic burp/Zr6c.Zf : Ljava/lang/String;
    //   1982: getstatic burp/Zm83.Zl : Ljava/lang/Object;
    //   1985: checkcast java/math/BigInteger
    //   1988: invokevirtual intValue : ()I
    //   1991: bipush #32
    //   1993: irem
    //   1994: invokestatic abs : (I)I
    //   1997: invokevirtual charAt : (I)C
    //   2000: invokevirtual append : (C)Ljava/lang/StringBuilder;
    //   2003: pop
    //   2004: iload_2
    //   2005: ifeq -> 2048
    //   2008: goto -> 2015
    //   2011: invokestatic a : (Ljava/lang/Throwable;)Ljava/lang/Throwable;
    //   2014: athrow
    //   2015: aload_3
    //   2016: getstatic burp/Zkf6.ZO : Ljava/lang/String;
    //   2019: getstatic burp/Zmh3.ZF : Ljava/lang/Object;
    //   2022: checkcast java/math/BigInteger
    //   2025: invokevirtual intValue : ()I
    //   2028: bipush #32
    //   2030: irem
    //   2031: invokestatic abs : (I)I
    //   2034: invokevirtual charAt : (I)C
    //   2037: invokevirtual append : (C)Ljava/lang/StringBuilder;
    //   2040: pop
    //   2041: goto -> 2048
    //   2044: invokestatic a : (Ljava/lang/Throwable;)Ljava/lang/Throwable;
    //   2047: athrow
    //   2048: iinc #4, 1
    //   2051: iload_2
    //   2052: ifeq -> 715
    //   2055: aload_3
    //   2056: invokevirtual toString : ()Ljava/lang/String;
    //   2059: putstatic burp/Zzna.Zi : Ljava/lang/String;
    //   2062: getstatic burp/Zse8.Ze : Ljava/lang/String;
    //   2065: getstatic burp/Zt7x.ZE : Ljava/lang/Object;
    //   2068: checkcast java/math/BigInteger
    //   2071: invokevirtual intValue : ()I
    //   2074: bipush #32
    //   2076: irem
    //   2077: invokestatic abs : (I)I
    //   2080: invokevirtual charAt : (I)C
    //   2083: getstatic burp/Zr02.ZG : Ljava/lang/String;
    //   2086: getstatic burp/Zry1.Zf : Ljava/lang/Object;
    //   2089: checkcast java/math/BigInteger
    //   2092: invokevirtual intValue : ()I
    //   2095: bipush #32
    //   2097: irem
    //   2098: invokestatic abs : (I)I
    //   2101: invokevirtual charAt : (I)C
    //   2104: if_icmpgt -> 2211
    //   2107: getstatic burp/Zgtd.Zj : Ljava/lang/String;
    //   2110: getstatic burp/Zb2u.ZY : Ljava/lang/Object;
    //   2113: checkcast java/math/BigInteger
    //   2116: invokevirtual intValue : ()I
    //   2119: bipush #32
    //   2121: irem
    //   2122: invokestatic abs : (I)I
    //   2125: invokevirtual charAt : (I)C
    //   2128: getstatic burp/Zx63.ZT : Ljava/lang/String;
    //   2131: getstatic burp/Zb_1.ZK : Ljava/lang/Object;
    //   2134: checkcast java/math/BigInteger
    //   2137: invokevirtual intValue : ()I
    //   2140: bipush #32
    //   2142: irem
    //   2143: invokestatic abs : (I)I
    //   2146: invokevirtual charAt : (I)C
    //   2149: if_icmpgt -> 2211
    //   2152: goto -> 2159
    //   2155: invokestatic a : (Ljava/lang/Throwable;)Ljava/lang/Throwable;
    //   2158: athrow
    //   2159: getstatic burp/Zs_m.Zt : Ljava/lang/String;
    //   2162: getstatic burp/Zrex.Zr : Ljava/lang/Object;
    //   2165: checkcast java/math/BigInteger
    //   2168: invokevirtual intValue : ()I
    //   2171: bipush #32
    //   2173: irem
    //   2174: invokestatic abs : (I)I
    //   2177: invokevirtual charAt : (I)C
    //   2180: getstatic burp/Zt81.ZL : Ljava/lang/String;
    //   2183: getstatic burp/Zlxr.Zz : Ljava/lang/Object;
    //   2186: checkcast java/math/BigInteger
    //   2189: invokevirtual intValue : ()I
    //   2192: bipush #32
    //   2194: irem
    //   2195: invokestatic abs : (I)I
    //   2198: invokevirtual charAt : (I)C
    //   2201: if_icmpgt -> 2219
    //   2204: goto -> 2211
    //   2207: invokestatic a : (Ljava/lang/Throwable;)Ljava/lang/Throwable;
    //   2210: athrow
    //   2211: iconst_1
    //   2212: goto -> 2220
    //   2215: invokestatic a : (Ljava/lang/Throwable;)Ljava/lang/Throwable;
    //   2218: athrow
    //   2219: iconst_0
    //   2220: ireturn
    //   2221: astore_3
    //   2222: new java/lang/Exception
    //   2225: dup
    //   2226: aload_3
    //   2227: invokevirtual getMessage : ()Ljava/lang/String;
    //   2230: invokespecial <init> : (Ljava/lang/String;)V
    //   2233: athrow
    // Exception table:
    //   from	to	target	type
    //   4	2220	2221	java/lang/Throwable
    //   309	333	336	java/lang/Throwable
    //   407	444	444	java/lang/Throwable
    //   448	469	469	java/lang/Throwable
    //   473	503	503	java/lang/Throwable
    //   722	898	901	java/lang/Throwable
    //   868	935	938	java/lang/Throwable
    //   905	972	975	java/lang/Throwable
    //   942	1009	1012	java/lang/Throwable
    //   979	1046	1049	java/lang/Throwable
    //   1016	1083	1086	java/lang/Throwable
    //   1053	1120	1123	java/lang/Throwable
    //   1090	1157	1160	java/lang/Throwable
    //   1127	1194	1197	java/lang/Throwable
    //   1164	1231	1234	java/lang/Throwable
    //   1201	1268	1271	java/lang/Throwable
    //   1238	1305	1308	java/lang/Throwable
    //   1275	1342	1345	java/lang/Throwable
    //   1312	1379	1382	java/lang/Throwable
    //   1349	1416	1419	java/lang/Throwable
    //   1386	1453	1456	java/lang/Throwable
    //   1423	1490	1493	java/lang/Throwable
    //   1460	1527	1530	java/lang/Throwable
    //   1497	1564	1567	java/lang/Throwable
    //   1534	1601	1604	java/lang/Throwable
    //   1571	1638	1641	java/lang/Throwable
    //   1608	1675	1678	java/lang/Throwable
    //   1645	1712	1715	java/lang/Throwable
    //   1682	1749	1752	java/lang/Throwable
    //   1719	1786	1789	java/lang/Throwable
    //   1756	1823	1826	java/lang/Throwable
    //   1793	1860	1863	java/lang/Throwable
    //   1830	1897	1900	java/lang/Throwable
    //   1867	1934	1937	java/lang/Throwable
    //   1904	1971	1974	java/lang/Throwable
    //   1941	2008	2011	java/lang/Throwable
    //   1978	2041	2044	java/lang/Throwable
    //   2055	2152	2155	java/lang/Throwable
    //   2107	2204	2207	java/lang/Throwable
    //   2159	2215	2215	java/lang/Throwable
  }
  
  static void Zt(Object paramObject) {
    Zmui.ZY = a(20461, 26097);
    Zmui.Zz = new BigInteger(a(20456, -23309));
    boolean bool = Zt2e.ZN();
    try {
      try {
        if (Zos.Za.charAt(Math.abs(((BigInteger)Zlbd.ZU).intValue() % 32)) <= Zrfa.ZT.charAt(Math.abs(((BigInteger)Zreu.Zi).intValue() % 32))) {
          try {
            Zlo0.ZN(Class.forName(a(20463, -25439)));
            if (!bool)
              Zxjw.ZK(Class.forName(a(20462, 30667))); 
          } catch (Throwable throwable) {
            throw a(null);
          } 
          return;
        } 
      } catch (Throwable throwable) {
        throw a(null);
      } 
      Zxjw.ZK(Class.forName(a(20462, 30667)));
    } catch (Throwable throwable) {}
  }
  
  static {
    // Byte code:
    //   0: bipush #8
    //   2: anewarray java/lang/String
    //   5: astore #5
    //   7: iconst_0
    //   8: istore_3
    //   9: ldc 'Ã¹MAÂ´-mj][\\tÂ–Â…Â¬Â­ÂNÃ€pÂ±\\t&Ã±XÃ§Ã»qÂ«2\\t _Ã–Â³\\tÃ¯ÂªkÂž%CÂ¼Ã—Â€Â‚Â¿aÂÂ‰ÂˆÂ«ÂŒÃ¨Ã—ZnÃ†uÃZwÂŽsÃ€ Ã©ÃºÂ½Â…Â„Â«Â½wÂºÂ¥Ã¶Â½OÂ¡Â­\\nÂ”<Â¯Ã‡Ã˜\\nÂ¶ÂœÂ¯Ã¡ÃŒÃ¸'
    //   11: dup
    //   12: astore_2
    //   13: invokevirtual length : ()I
    //   16: istore #4
    //   18: bipush #9
    //   20: istore_1
    //   21: iconst_m1
    //   22: istore_0
    //   23: bipush #28
    //   25: iinc #0, 1
    //   28: aload_2
    //   29: iload_0
    //   30: dup
    //   31: iload_1
    //   32: iadd
    //   33: invokevirtual substring : (II)Ljava/lang/String;
    //   36: iconst_m1
    //   37: goto -> 143
    //   40: aload #5
    //   42: swap
    //   43: iload_3
    //   44: iinc #3, 1
    //   47: swap
    //   48: aastore
    //   49: iload_0
    //   50: iload_1
    //   51: iadd
    //   52: dup
    //   53: istore_0
    //   54: iload #4
    //   56: if_icmpge -> 68
    //   59: aload_2
    //   60: iload_0
    //   61: invokevirtual charAt : (I)C
    //   64: istore_1
    //   65: goto -> 23
    //   68: ldc 'Ã¬.ÃµqÃ‚Ã—gÂ…Â˜Ã¸ÃŠFbxÂ˜Â½Ã¿Ã'EÂ˜Ã°>BX]Â½Â–lÂ3\\bÃ’Ã¡Âž3IÂ•>Ã¨Â¿Â]!SW_rÃŸJÂ“8,ÃŸÂŸÃ²Â©eÃ¤>Ã¨Â¿;Â‹Â¹BÃ®Â™ÂŠÃŠxhS X'Ã¤ÂÂ‰loÂ‡Ã”Ã¨ÃŽÃÂ‚Â½Ã™fÂ5rÂ°m;uÃ¡?ÃºÂŠÃš+Ã¤Z'
    //   70: dup
    //   71: astore_2
    //   72: invokevirtual length : ()I
    //   75: istore #4
    //   77: bipush #77
    //   79: istore_1
    //   80: iconst_m1
    //   81: istore_0
    //   82: bipush #52
    //   84: iinc #0, 1
    //   87: aload_2
    //   88: iload_0
    //   89: dup
    //   90: iload_1
    //   91: iadd
    //   92: invokevirtual substring : (II)Ljava/lang/String;
    //   95: iconst_0
    //   96: goto -> 143
    //   99: aload #5
    //   101: swap
    //   102: iload_3
    //   103: iinc #3, 1
    //   106: swap
    //   107: aastore
    //   108: iload_0
    //   109: iload_1
    //   110: iadd
    //   111: dup
    //   112: istore_0
    //   113: iload #4
    //   115: if_icmpge -> 127
    //   118: aload_2
    //   119: iload_0
    //   120: invokevirtual charAt : (I)C
    //   123: istore_1
    //   124: goto -> 82
    //   127: aload #5
    //   129: putstatic burp/Zrym.a : [Ljava/lang/String;
    //   132: bipush #8
    //   134: anewarray java/lang/String
    //   137: putstatic burp/Zrym.b : [Ljava/lang/String;
    //   140: goto -> 300
    //   143: dup_x2
    //   144: pop
    //   145: invokevirtual toCharArray : ()[C
    //   148: dup_x1
    //   149: arraylength
    //   150: dup_x2
    //   151: pop
    //   152: iconst_0
    //   153: istore #6
    //   155: dup2_x1
    //   156: pop2
    //   157: dup_x2
    //   158: iconst_1
    //   159: if_icmpgt -> 259
    //   162: dup2
    //   163: swap
    //   164: iload #6
    //   166: dup2_x1
    //   167: caload
    //   168: swap
    //   169: iload #6
    //   171: bipush #7
    //   173: irem
    //   174: tableswitch default -> 242, 0 -> 212, 1 -> 217, 2 -> 222, 3 -> 227, 4 -> 232, 5 -> 237
    //   212: bipush #68
    //   214: goto -> 243
    //   217: bipush #75
    //   219: goto -> 243
    //   222: bipush #53
    //   224: goto -> 243
    //   227: bipush #64
    //   229: goto -> 243
    //   232: bipush #46
    //   234: goto -> 243
    //   237: bipush #72
    //   239: goto -> 243
    //   242: iconst_4
    //   243: ixor
    //   244: ixor
    //   245: i2c
    //   246: castore
    //   247: iinc #6, 1
    //   250: dup
    //   251: ifne -> 259
    //   254: dup2
    //   255: dup_x1
    //   256: goto -> 166
    //   259: dup2_x1
    //   260: pop2
    //   261: dup_x2
    //   262: iload #6
    //   264: if_icmpgt -> 162
    //   267: pop
    //   268: new java/lang/String
    //   271: dup_x1
    //   272: swap
    //   273: invokespecial <init> : ([C)V
    //   276: invokevirtual intern : ()Ljava/lang/String;
    //   279: swap
    //   280: pop
    //   281: swap
    //   282: tableswitch default -> 40, 0 -> 99
    //   300: sipush #20459
    //   303: sipush #-25980
    //   306: invokestatic a : (II)Ljava/lang/String;
    //   309: putstatic burp/Zrym.ZX : Ljava/lang/String;
    //   312: new java/math/BigInteger
    //   315: dup
    //   316: bipush #32
    //   318: newarray byte
    //   320: dup
    //   321: iconst_0
    //   322: bipush #6
    //   324: bastore
    //   325: dup
    //   326: iconst_1
    //   327: bipush #-15
    //   329: bastore
    //   330: dup
    //   331: iconst_2
    //   332: bipush #-25
    //   334: bastore
    //   335: dup
    //   336: iconst_3
    //   337: bipush #-41
    //   339: bastore
    //   340: dup
    //   341: iconst_4
    //   342: bipush #-78
    //   344: bastore
    //   345: dup
    //   346: iconst_5
    //   347: bipush #-74
    //   349: bastore
    //   350: dup
    //   351: bipush #6
    //   353: bipush #-61
    //   355: bastore
    //   356: dup
    //   357: bipush #7
    //   359: bipush #-67
    //   361: bastore
    //   362: dup
    //   363: bipush #8
    //   365: bipush #25
    //   367: bastore
    //   368: dup
    //   369: bipush #9
    //   371: bipush #75
    //   373: bastore
    //   374: dup
    //   375: bipush #10
    //   377: bipush #54
    //   379: bastore
    //   380: dup
    //   381: bipush #11
    //   383: bipush #-120
    //   385: bastore
    //   386: dup
    //   387: bipush #12
    //   389: bipush #116
    //   391: bastore
    //   392: dup
    //   393: bipush #13
    //   395: bipush #-23
    //   397: bastore
    //   398: dup
    //   399: bipush #14
    //   401: bipush #66
    //   403: bastore
    //   404: dup
    //   405: bipush #15
    //   407: iconst_2
    //   408: bastore
    //   409: dup
    //   410: bipush #16
    //   412: bipush #-48
    //   414: bastore
    //   415: dup
    //   416: bipush #17
    //   418: bipush #45
    //   420: bastore
    //   421: dup
    //   422: bipush #18
    //   424: bipush #-10
    //   426: bastore
    //   427: dup
    //   428: bipush #19
    //   430: bipush #-2
    //   432: bastore
    //   433: dup
    //   434: bipush #20
    //   436: bipush #-70
    //   438: bastore
    //   439: dup
    //   440: bipush #21
    //   442: bipush #101
    //   444: bastore
    //   445: dup
    //   446: bipush #22
    //   448: bipush #-43
    //   450: bastore
    //   451: dup
    //   452: bipush #23
    //   454: bipush #104
    //   456: bastore
    //   457: dup
    //   458: bipush #24
    //   460: bipush #-89
    //   462: bastore
    //   463: dup
    //   464: bipush #25
    //   466: bipush #-69
    //   468: bastore
    //   469: dup
    //   470: bipush #26
    //   472: iconst_4
    //   473: bastore
    //   474: dup
    //   475: bipush #27
    //   477: bipush #-42
    //   479: bastore
    //   480: dup
    //   481: bipush #28
    //   483: bipush #-120
    //   485: bastore
    //   486: dup
    //   487: bipush #29
    //   489: bipush #-106
    //   491: bastore
    //   492: dup
    //   493: bipush #30
    //   495: bipush #-9
    //   497: bastore
    //   498: dup
    //   499: bipush #31
    //   501: bipush #-37
    //   503: bastore
    //   504: invokespecial <init> : ([B)V
    //   507: putstatic burp/Zrym.Zk : Ljava/lang/Object;
    //   510: return
  }
  
  private static Throwable a(Throwable paramThrowable) {
    return paramThrowable;
  }
  
  private static String a(int paramInt1, int paramInt2) {
    int i = (paramInt1 ^ 0x4FEE) & 0xFFFF;
    if (b[i] == null) {
      char[] arrayOfChar = a[i].toCharArray();
      switch (arrayOfChar[0] & 0xFF) {
        case 0:
        
        case 1:
        
        case 2:
        
        case 3:
        
        case 4:
        
        case 5:
        
        case 6:
        
        case 7:
        
        case 8:
        
        case 9:
        
        case 10:
        
        case 11:
        
        case 12:
        
        case 13:
        
        case 14:
        
        case 15:
        
        case 16:
        
        case 17:
        
        case 18:
        
        case 19:
        
        case 20:
        
        case 21:
        
        case 22:
        
        case 23:
        
        case 24:
        
        case 25:
        
        case 26:
        
        case 27:
        
        case 28:
        
        case 29:
        
        case 30:
        
        case 31:
        
        case 32:
        
        case 33:
        
        case 34:
        
        case 35:
        
        case 36:
        
        case 37:
        
        case 38:
        
        case 39:
        
        case 40:
        
        case 41:
        
        case 42:
        
        case 43:
        
        case 44:
        
        case 45:
        
        case 46:
        
        case 47:
        
        case 48:
        
        case 49:
        
        case 50:
        
        case 51:
        
        case 52:
        
        case 53:
        
        case 54:
        
        case 55:
        
        case 56:
        
        case 57:
        
        case 58:
        
        case 59:
        
        case 60:
        
        case 61:
        
        case 62:
        
        case 63:
        
        case 64:
        
        case 65:
        
        case 66:
        
        case 67:
        
        case 68:
        
        case 69:
        
        case 70:
        
        case 71:
        
        case 72:
        
        case 73:
        
        case 74:
        
        case 75:
        
        case 76:
        
        case 77:
        
        case 78:
        
        case 79:
        
        case 80:
        
        case 81:
        
        case 82:
        
        case 83:
        
        case 84:
        
        case 85:
        
        case 86:
        
        case 87:
        
        case 88:
        
        case 89:
        
        case 90:
        
        case 91:
        
        case 92:
        
        case 93:
        
        case 94:
        
        case 95:
        
        case 96:
        
        case 97:
        
        case 98:
        
        case 99:
        
        case 100:
        
        case 101:
        
        case 102:
        
        case 103:
        
        case 104:
        
        case 105:
        
        case 106:
        
        case 107:
        
        case 108:
        
        case 109:
        
        case 110:
        
        case 111:
        
        case 112:
        
        case 113:
        
        case 114:
        
        case 115:
        
        case 116:
        
        case 117:
        
        case 118:
        
        case 119:
        
        case 120:
        
        case 121:
        
        case 122:
        
        case 123:
        
        case 124:
        
        case 125:
        
        case 126:
        
        case 127:
        
        case 128:
        
        case 129:
        
        case 130:
        
        case 131:
        
        case 132:
        
        case 133:
        
        case 134:
        
        case 135:
        
        case 136:
        
        case 137:
        
        case 138:
        
        case 139:
        
        case 140:
        
        case 141:
        
        case 142:
        
        case 143:
        
        case 144:
        
        case 145:
        
        case 146:
        
        case 147:
        
        case 148:
        
        case 149:
        
        case 150:
        
        case 151:
        
        case 152:
        
        case 153:
        
        case 154:
        
        case 155:
        
        case 156:
        
        case 157:
        
        case 158:
        
        case 159:
        
        case 160:
        
        case 161:
        
        case 162:
        
        case 163:
        
        case 164:
        
        case 165:
        
        case 166:
        
        case 167:
        
        case 168:
        
        case 169:
        
        case 170:
        
        case 171:
        
        case 172:
        
        case 173:
        
        case 174:
        
        case 175:
        
        case 176:
        
        case 177:
        
        case 178:
        
        case 179:
        
        case 180:
        
        case 181:
        
        case 182:
        
        case 183:
        
        case 184:
        
        case 185:
        
        case 186:
        
        case 187:
        
        case 188:
        
        case 189:
        
        case 190:
        
        case 191:
        
        case 192:
        
        case 193:
        
        case 194:
        
        case 195:
        
        case 196:
        
        case 197:
        
        case 198:
        
        case 199:
        
        case 200:
        
        case 201:
        
        case 202:
        
        case 203:
        
        case 204:
        
        case 205:
        
        case 206:
        
        case 207:
        
        case 208:
        
        case 209:
        
        case 210:
        
        case 211:
        
        case 212:
        
        case 213:
        
        case 214:
        
        case 215:
        
        case 216:
        
        case 217:
        
        case 218:
        
        case 219:
        
        case 220:
        
        case 221:
        
        case 222:
        
        case 223:
        
        case 224:
        
        case 225:
        
        case 226:
        
        case 227:
        
        case 228:
        
        case 229:
        
        case 230:
        
        case 231:
        
        case 232:
        
        case 233:
        
        case 234:
        
        case 235:
        
        case 236:
        
        case 237:
        
        case 238:
        
        case 239:
        
        case 240:
        
        case 241:
        
        case 242:
        
        case 243:
        
        case 244:
        
        case 245:
        
        case 246:
        
        case 247:
        
        case 248:
        
        case 249:
        
        case 250:
        
        case 251:
        
        case 252:
        
        case 253:
        
        case 254:
        
        default:
          break;
      } 
      char c = 'Â•';
      int j = (paramInt2 & 0xFF) - c;
      if (j < 0)
        j += 256; 
      int k = ((paramInt2 & 0xFFFF) >>> 8) - c;
      if (k < 0)
        k += 256; 
      for (byte b = 0; b < arrayOfChar.length; b++) {
        int m = b % 2;
        if (m == 0) {
          arrayOfChar[b] = (char)(arrayOfChar[b] ^ j);
          j = ((j >>> 3 | j << 5) ^ arrayOfChar[b]) & 0xFF;
        } else {
          arrayOfChar[b] = (char)(arrayOfChar[b] ^ k);
          k = ((k >>> 3 | k << 5) ^ arrayOfChar[b]) & 0xFF;
        } 
      } 
      b[i] = (new String(arrayOfChar)).intern();
    } 
    return b[i];
  }
}


/* Location:              C:\Program Files\BurpSuitePro\burpsuite_pro.jar!\burp\Zrym.class
 * Java compiler version: 21 (65.0)
 * JD-Core Version:       1.1.3
 */