package burp;

import java.math.BigInteger;

class Zs0h extends ClassLoader {
  static Object ZU;
  
  static String ZX;
  
  private static final String[] a;
  
  private static final String[] b;
  
  static void Zr(Object paramObject) {
    Zrov.ZU = a(19700, 24663);
    Zrov.Zk = new BigInteger(a(19709, -14883));
    boolean bool = Zt2e.ZK();
    try {
      try {
        if (Zsvd.ZB.charAt(Math.abs(((BigInteger)Zrex.Zr).intValue() % 32)) > Ztgv.ZC.charAt(Math.abs(((BigInteger)Zewr.Zw).intValue() % 32))) {
          try {
            Zkjj.Zm(Class.forName(a(19706, -21745)));
            if (bool)
              Zg0j.ZC(Class.forName(a(19701, -23982))); 
          } catch (Throwable throwable) {
            throw a(null);
          } 
          return;
        } 
      } catch (Throwable throwable) {
        throw a(null);
      } 
      Zg0j.ZC(Class.forName(a(19701, -23982)));
    } catch (Throwable throwable) {}
  }
  
  static void ZR(Object[] paramArrayOfObject, Object paramObject) throws Throwable {}
  
  static boolean Zi(Object[] paramArrayOfObject, Object paramObject) throws Throwable {
    // Byte code:
    //   0: invokestatic ZK : ()Z
    //   3: istore_2
    //   4: new java/io/ByteArrayOutputStream
    //   7: dup
    //   8: invokespecial <init> : ()V
    //   11: astore_3
    //   12: getstatic burp/Zsn4.ZZ : Ljava/lang/String;
    //   15: astore #4
    //   17: iconst_0
    //   18: istore #5
    //   20: iload #5
    //   22: aload #4
    //   24: invokevirtual length : ()I
    //   27: if_icmpge -> 57
    //   30: aload_3
    //   31: aload #4
    //   33: iload #5
    //   35: iload #5
    //   37: iconst_2
    //   38: iadd
    //   39: invokevirtual substring : (II)Ljava/lang/String;
    //   42: bipush #16
    //   44: invokestatic parseInt : (Ljava/lang/String;I)I
    //   47: invokevirtual write : (I)V
    //   50: iinc #5, 2
    //   53: iload_2
    //   54: ifeq -> 20
    //   57: aload_3
    //   58: invokevirtual toByteArray : ()[B
    //   61: astore #5
    //   63: getstatic burp/Zrnk.ZM : Ljava/lang/Object;
    //   66: checkcast java/math/BigInteger
    //   69: invokevirtual toByteArray : ()[B
    //   72: astore #6
    //   74: sipush #256
    //   77: newarray byte
    //   79: astore #8
    //   81: sipush #256
    //   84: newarray int
    //   86: astore #9
    //   88: sipush #256
    //   91: newarray int
    //   93: astore #10
    //   95: sipush #256
    //   98: newarray int
    //   100: astore #11
    //   102: sipush #256
    //   105: newarray int
    //   107: astore #12
    //   109: bipush #10
    //   111: newarray int
    //   113: astore #13
    //   115: sipush #283
    //   118: istore #14
    //   120: iconst_0
    //   121: istore #16
    //   123: iload #16
    //   125: sipush #256
    //   128: if_icmpge -> 362
    //   131: sipush #19704
    //   134: sipush #-2086
    //   137: invokestatic a : (II)Ljava/lang/String;
    //   140: iload #16
    //   142: iconst_1
    //   143: iushr
    //   144: invokevirtual charAt : (I)C
    //   147: istore #25
    //   149: iload #16
    //   151: iconst_1
    //   152: iand
    //   153: ifne -> 168
    //   156: iload #25
    //   158: bipush #8
    //   160: iushr
    //   161: goto -> 170
    //   164: invokestatic a : (Ljava/lang/Throwable;)Ljava/lang/Throwable;
    //   167: athrow
    //   168: iload #25
    //   170: i2b
    //   171: sipush #255
    //   174: iand
    //   175: istore #15
    //   177: iload #16
    //   179: iconst_1
    //   180: ishl
    //   181: istore #17
    //   183: iload #17
    //   185: sipush #256
    //   188: if_icmplt -> 198
    //   191: iload #17
    //   193: iload #14
    //   195: ixor
    //   196: istore #17
    //   198: iload #17
    //   200: iconst_1
    //   201: ishl
    //   202: istore #18
    //   204: iload #18
    //   206: sipush #256
    //   209: if_icmplt -> 219
    //   212: iload #18
    //   214: iload #14
    //   216: ixor
    //   217: istore #18
    //   219: iload #18
    //   221: iconst_1
    //   222: ishl
    //   223: istore #19
    //   225: iload #19
    //   227: sipush #256
    //   230: if_icmplt -> 240
    //   233: iload #19
    //   235: iload #14
    //   237: ixor
    //   238: istore #19
    //   240: iload #19
    //   242: iload #16
    //   244: ixor
    //   245: istore #20
    //   247: iload #20
    //   249: iload #17
    //   251: ixor
    //   252: istore #21
    //   254: iload #20
    //   256: iload #18
    //   258: ixor
    //   259: istore #22
    //   261: iload #19
    //   263: iload #18
    //   265: ixor
    //   266: iload #17
    //   268: ixor
    //   269: istore #23
    //   271: aload #8
    //   273: iload #16
    //   275: iload #15
    //   277: i2b
    //   278: bastore
    //   279: aload #9
    //   281: iload #15
    //   283: iload #23
    //   285: bipush #24
    //   287: ishl
    //   288: iload #20
    //   290: bipush #16
    //   292: ishl
    //   293: ior
    //   294: iload #22
    //   296: bipush #8
    //   298: ishl
    //   299: ior
    //   300: iload #21
    //   302: ior
    //   303: dup
    //   304: istore #24
    //   306: iastore
    //   307: aload #10
    //   309: iload #15
    //   311: iload #24
    //   313: bipush #8
    //   315: iushr
    //   316: iload #24
    //   318: bipush #24
    //   320: ishl
    //   321: ior
    //   322: iastore
    //   323: aload #11
    //   325: iload #15
    //   327: iload #24
    //   329: bipush #16
    //   331: iushr
    //   332: iload #24
    //   334: bipush #16
    //   336: ishl
    //   337: ior
    //   338: iastore
    //   339: aload #12
    //   341: iload #15
    //   343: iload #24
    //   345: bipush #24
    //   347: iushr
    //   348: iload #24
    //   350: bipush #8
    //   352: ishl
    //   353: ior
    //   354: iastore
    //   355: iinc #16, 1
    //   358: iload_2
    //   359: ifeq -> 123
    //   362: iconst_1
    //   363: istore #25
    //   365: aload #13
    //   367: iconst_0
    //   368: iload #25
    //   370: bipush #24
    //   372: ishl
    //   373: iastore
    //   374: iconst_1
    //   375: istore #26
    //   377: iload #26
    //   379: bipush #10
    //   381: if_icmpge -> 422
    //   384: iload #25
    //   386: iconst_1
    //   387: ishl
    //   388: istore #25
    //   390: iload #25
    //   392: sipush #256
    //   395: if_icmplt -> 405
    //   398: iload #25
    //   400: iload #14
    //   402: ixor
    //   403: istore #25
    //   405: aload #13
    //   407: iload #26
    //   409: iload #25
    //   411: bipush #24
    //   413: ishl
    //   414: iastore
    //   415: iinc #26, 1
    //   418: iload_2
    //   419: ifeq -> 377
    //   422: iconst_4
    //   423: istore #26
    //   425: iload #26
    //   427: bipush #6
    //   429: iadd
    //   430: istore #27
    //   432: iconst_4
    //   433: iload #27
    //   435: iconst_1
    //   436: iadd
    //   437: imul
    //   438: istore #28
    //   440: iload #28
    //   442: newarray int
    //   444: astore #29
    //   446: iload #28
    //   448: newarray int
    //   450: astore #30
    //   452: iconst_0
    //   453: istore #25
    //   455: iconst_0
    //   456: istore #32
    //   458: iconst_0
    //   459: istore #33
    //   461: iload #32
    //   463: iload #26
    //   465: if_icmpge -> 533
    //   468: aload #29
    //   470: iload #32
    //   472: aload #5
    //   474: iload #33
    //   476: baload
    //   477: bipush #24
    //   479: ishl
    //   480: aload #5
    //   482: iload #33
    //   484: iconst_1
    //   485: iadd
    //   486: baload
    //   487: sipush #255
    //   490: iand
    //   491: bipush #16
    //   493: ishl
    //   494: ior
    //   495: aload #5
    //   497: iload #33
    //   499: iconst_2
    //   500: iadd
    //   501: baload
    //   502: sipush #255
    //   505: iand
    //   506: bipush #8
    //   508: ishl
    //   509: ior
    //   510: aload #5
    //   512: iload #33
    //   514: iconst_3
    //   515: iadd
    //   516: baload
    //   517: sipush #255
    //   520: iand
    //   521: ior
    //   522: iastore
    //   523: iinc #32, 1
    //   526: iinc #33, 4
    //   529: iload_2
    //   530: ifeq -> 461
    //   533: iload #26
    //   535: istore #32
    //   537: iconst_0
    //   538: istore #33
    //   540: iload #32
    //   542: iload #28
    //   544: if_icmpge -> 671
    //   547: aload #29
    //   549: iload #32
    //   551: iconst_1
    //   552: isub
    //   553: iaload
    //   554: istore #31
    //   556: iload #33
    //   558: ifne -> 645
    //   561: iload #26
    //   563: istore #33
    //   565: aload #8
    //   567: iload #31
    //   569: bipush #16
    //   571: iushr
    //   572: sipush #255
    //   575: iand
    //   576: baload
    //   577: bipush #24
    //   579: ishl
    //   580: aload #8
    //   582: iload #31
    //   584: bipush #8
    //   586: iushr
    //   587: sipush #255
    //   590: iand
    //   591: baload
    //   592: sipush #255
    //   595: iand
    //   596: bipush #16
    //   598: ishl
    //   599: ior
    //   600: aload #8
    //   602: iload #31
    //   604: sipush #255
    //   607: iand
    //   608: baload
    //   609: sipush #255
    //   612: iand
    //   613: bipush #8
    //   615: ishl
    //   616: ior
    //   617: aload #8
    //   619: iload #31
    //   621: bipush #24
    //   623: iushr
    //   624: baload
    //   625: sipush #255
    //   628: iand
    //   629: ior
    //   630: istore #31
    //   632: iload #31
    //   634: aload #13
    //   636: iload #25
    //   638: iinc #25, 1
    //   641: iaload
    //   642: ixor
    //   643: istore #31
    //   645: aload #29
    //   647: iload #32
    //   649: aload #29
    //   651: iload #32
    //   653: iload #26
    //   655: isub
    //   656: iaload
    //   657: iload #31
    //   659: ixor
    //   660: iastore
    //   661: iinc #32, 1
    //   664: iinc #33, -1
    //   667: iload_2
    //   668: ifeq -> 540
    //   671: iconst_0
    //   672: istore #32
    //   674: iconst_4
    //   675: iload #27
    //   677: imul
    //   678: istore #33
    //   680: aload #30
    //   682: iload #32
    //   684: aload #29
    //   686: iload #33
    //   688: iaload
    //   689: iastore
    //   690: aload #30
    //   692: iload #32
    //   694: iconst_1
    //   695: iadd
    //   696: aload #29
    //   698: iload #33
    //   700: iconst_1
    //   701: iadd
    //   702: iaload
    //   703: iastore
    //   704: aload #30
    //   706: iload #32
    //   708: iconst_2
    //   709: iadd
    //   710: aload #29
    //   712: iload #33
    //   714: iconst_2
    //   715: iadd
    //   716: iaload
    //   717: iastore
    //   718: aload #30
    //   720: iload #32
    //   722: iconst_3
    //   723: iadd
    //   724: aload #29
    //   726: iload #33
    //   728: iconst_3
    //   729: iadd
    //   730: iaload
    //   731: iastore
    //   732: iinc #32, 4
    //   735: iinc #33, -4
    //   738: iconst_1
    //   739: istore #35
    //   741: iload #35
    //   743: iload #27
    //   745: if_icmpge -> 1109
    //   748: aload #29
    //   750: iload #33
    //   752: iaload
    //   753: istore #34
    //   755: aload #30
    //   757: iload #32
    //   759: aload #9
    //   761: aload #8
    //   763: iload #34
    //   765: bipush #24
    //   767: iushr
    //   768: baload
    //   769: sipush #255
    //   772: iand
    //   773: iaload
    //   774: aload #10
    //   776: aload #8
    //   778: iload #34
    //   780: bipush #16
    //   782: iushr
    //   783: sipush #255
    //   786: iand
    //   787: baload
    //   788: sipush #255
    //   791: iand
    //   792: iaload
    //   793: ixor
    //   794: aload #11
    //   796: aload #8
    //   798: iload #34
    //   800: bipush #8
    //   802: iushr
    //   803: sipush #255
    //   806: iand
    //   807: baload
    //   808: sipush #255
    //   811: iand
    //   812: iaload
    //   813: ixor
    //   814: aload #12
    //   816: aload #8
    //   818: iload #34
    //   820: sipush #255
    //   823: iand
    //   824: baload
    //   825: sipush #255
    //   828: iand
    //   829: iaload
    //   830: ixor
    //   831: iastore
    //   832: aload #29
    //   834: iload #33
    //   836: iconst_1
    //   837: iadd
    //   838: iaload
    //   839: istore #34
    //   841: aload #30
    //   843: iload #32
    //   845: iconst_1
    //   846: iadd
    //   847: aload #9
    //   849: aload #8
    //   851: iload #34
    //   853: bipush #24
    //   855: iushr
    //   856: baload
    //   857: sipush #255
    //   860: iand
    //   861: iaload
    //   862: aload #10
    //   864: aload #8
    //   866: iload #34
    //   868: bipush #16
    //   870: iushr
    //   871: sipush #255
    //   874: iand
    //   875: baload
    //   876: sipush #255
    //   879: iand
    //   880: iaload
    //   881: ixor
    //   882: aload #11
    //   884: aload #8
    //   886: iload #34
    //   888: bipush #8
    //   890: iushr
    //   891: sipush #255
    //   894: iand
    //   895: baload
    //   896: sipush #255
    //   899: iand
    //   900: iaload
    //   901: ixor
    //   902: aload #12
    //   904: aload #8
    //   906: iload #34
    //   908: sipush #255
    //   911: iand
    //   912: baload
    //   913: sipush #255
    //   916: iand
    //   917: iaload
    //   918: ixor
    //   919: iastore
    //   920: aload #29
    //   922: iload #33
    //   924: iconst_2
    //   925: iadd
    //   926: iaload
    //   927: istore #34
    //   929: aload #30
    //   931: iload #32
    //   933: iconst_2
    //   934: iadd
    //   935: aload #9
    //   937: aload #8
    //   939: iload #34
    //   941: bipush #24
    //   943: iushr
    //   944: baload
    //   945: sipush #255
    //   948: iand
    //   949: iaload
    //   950: aload #10
    //   952: aload #8
    //   954: iload #34
    //   956: bipush #16
    //   958: iushr
    //   959: sipush #255
    //   962: iand
    //   963: baload
    //   964: sipush #255
    //   967: iand
    //   968: iaload
    //   969: ixor
    //   970: aload #11
    //   972: aload #8
    //   974: iload #34
    //   976: bipush #8
    //   978: iushr
    //   979: sipush #255
    //   982: iand
    //   983: baload
    //   984: sipush #255
    //   987: iand
    //   988: iaload
    //   989: ixor
    //   990: aload #12
    //   992: aload #8
    //   994: iload #34
    //   996: sipush #255
    //   999: iand
    //   1000: baload
    //   1001: sipush #255
    //   1004: iand
    //   1005: iaload
    //   1006: ixor
    //   1007: iastore
    //   1008: aload #29
    //   1010: iload #33
    //   1012: iconst_3
    //   1013: iadd
    //   1014: iaload
    //   1015: istore #34
    //   1017: aload #30
    //   1019: iload #32
    //   1021: iconst_3
    //   1022: iadd
    //   1023: aload #9
    //   1025: aload #8
    //   1027: iload #34
    //   1029: bipush #24
    //   1031: iushr
    //   1032: baload
    //   1033: sipush #255
    //   1036: iand
    //   1037: iaload
    //   1038: aload #10
    //   1040: aload #8
    //   1042: iload #34
    //   1044: bipush #16
    //   1046: iushr
    //   1047: sipush #255
    //   1050: iand
    //   1051: baload
    //   1052: sipush #255
    //   1055: iand
    //   1056: iaload
    //   1057: ixor
    //   1058: aload #11
    //   1060: aload #8
    //   1062: iload #34
    //   1064: bipush #8
    //   1066: iushr
    //   1067: sipush #255
    //   1070: iand
    //   1071: baload
    //   1072: sipush #255
    //   1075: iand
    //   1076: iaload
    //   1077: ixor
    //   1078: aload #12
    //   1080: aload #8
    //   1082: iload #34
    //   1084: sipush #255
    //   1087: iand
    //   1088: baload
    //   1089: sipush #255
    //   1092: iand
    //   1093: iaload
    //   1094: ixor
    //   1095: iastore
    //   1096: iinc #32, 4
    //   1099: iinc #33, -4
    //   1102: iinc #35, 1
    //   1105: iload_2
    //   1106: ifeq -> 741
    //   1109: aload #30
    //   1111: iload #32
    //   1113: aload #29
    //   1115: iload #33
    //   1117: iaload
    //   1118: iastore
    //   1119: aload #30
    //   1121: iload #32
    //   1123: iconst_1
    //   1124: iadd
    //   1125: aload #29
    //   1127: iload #33
    //   1129: iconst_1
    //   1130: iadd
    //   1131: iaload
    //   1132: iastore
    //   1133: aload #30
    //   1135: iload #32
    //   1137: iconst_2
    //   1138: iadd
    //   1139: aload #29
    //   1141: iload #33
    //   1143: iconst_2
    //   1144: iadd
    //   1145: iaload
    //   1146: iastore
    //   1147: aload #30
    //   1149: iload #32
    //   1151: iconst_3
    //   1152: iadd
    //   1153: aload #29
    //   1155: iload #33
    //   1157: iconst_3
    //   1158: iadd
    //   1159: iaload
    //   1160: iastore
    //   1161: iconst_0
    //   1162: newarray byte
    //   1164: astore #35
    //   1166: aload #6
    //   1168: arraylength
    //   1169: bipush #16
    //   1171: irem
    //   1172: ifeq -> 1196
    //   1175: new java/lang/Exception
    //   1178: dup
    //   1179: sipush #19698
    //   1182: sipush #9321
    //   1185: invokestatic a : (II)Ljava/lang/String;
    //   1188: invokespecial <init> : (Ljava/lang/String;)V
    //   1191: athrow
    //   1192: invokestatic a : (Ljava/lang/Throwable;)Ljava/lang/Throwable;
    //   1195: athrow
    //   1196: bipush #10
    //   1198: istore #36
    //   1200: sipush #19699
    //   1203: sipush #256
    //   1206: newarray byte
    //   1208: astore #37
    //   1210: sipush #-18821
    //   1213: sipush #256
    //   1216: newarray int
    //   1218: astore #38
    //   1220: sipush #256
    //   1223: newarray int
    //   1225: astore #39
    //   1227: sipush #256
    //   1230: newarray int
    //   1232: astore #40
    //   1234: sipush #256
    //   1237: newarray int
    //   1239: astore #41
    //   1241: sipush #283
    //   1244: istore #14
    //   1246: invokestatic a : (II)Ljava/lang/String;
    //   1249: astore #42
    //   1251: iconst_0
    //   1252: istore #16
    //   1254: iload #16
    //   1256: sipush #256
    //   1259: if_icmpge -> 1486
    //   1262: aload #42
    //   1264: iload #16
    //   1266: iconst_1
    //   1267: iushr
    //   1268: invokevirtual charAt : (I)C
    //   1271: istore #43
    //   1273: iload #16
    //   1275: iconst_1
    //   1276: iand
    //   1277: ifne -> 1292
    //   1280: iload #43
    //   1282: bipush #8
    //   1284: iushr
    //   1285: goto -> 1294
    //   1288: invokestatic a : (Ljava/lang/Throwable;)Ljava/lang/Throwable;
    //   1291: athrow
    //   1292: iload #43
    //   1294: i2b
    //   1295: sipush #255
    //   1298: iand
    //   1299: istore #15
    //   1301: iload #16
    //   1303: iconst_1
    //   1304: ishl
    //   1305: istore #17
    //   1307: iload #17
    //   1309: sipush #256
    //   1312: if_icmplt -> 1322
    //   1315: iload #17
    //   1317: iload #14
    //   1319: ixor
    //   1320: istore #17
    //   1322: iload #17
    //   1324: iconst_1
    //   1325: ishl
    //   1326: istore #18
    //   1328: iload #18
    //   1330: sipush #256
    //   1333: if_icmplt -> 1343
    //   1336: iload #18
    //   1338: iload #14
    //   1340: ixor
    //   1341: istore #18
    //   1343: iload #18
    //   1345: iconst_1
    //   1346: ishl
    //   1347: istore #19
    //   1349: iload #19
    //   1351: sipush #256
    //   1354: if_icmplt -> 1364
    //   1357: iload #19
    //   1359: iload #14
    //   1361: ixor
    //   1362: istore #19
    //   1364: iload #19
    //   1366: iload #16
    //   1368: ixor
    //   1369: istore #20
    //   1371: iload #20
    //   1373: iload #17
    //   1375: ixor
    //   1376: istore #21
    //   1378: iload #20
    //   1380: iload #18
    //   1382: ixor
    //   1383: istore #22
    //   1385: iload #19
    //   1387: iload #18
    //   1389: ixor
    //   1390: iload #17
    //   1392: ixor
    //   1393: istore #23
    //   1395: aload #37
    //   1397: iload #15
    //   1399: iload #16
    //   1401: i2b
    //   1402: bastore
    //   1403: aload #38
    //   1405: iload #15
    //   1407: iload #23
    //   1409: bipush #24
    //   1411: ishl
    //   1412: iload #20
    //   1414: bipush #16
    //   1416: ishl
    //   1417: ior
    //   1418: iload #22
    //   1420: bipush #8
    //   1422: ishl
    //   1423: ior
    //   1424: iload #21
    //   1426: ior
    //   1427: dup
    //   1428: istore #24
    //   1430: iastore
    //   1431: aload #39
    //   1433: iload #15
    //   1435: iload #24
    //   1437: bipush #8
    //   1439: iushr
    //   1440: iload #24
    //   1442: bipush #24
    //   1444: ishl
    //   1445: ior
    //   1446: iastore
    //   1447: aload #40
    //   1449: iload #15
    //   1451: iload #24
    //   1453: bipush #16
    //   1455: iushr
    //   1456: iload #24
    //   1458: bipush #16
    //   1460: ishl
    //   1461: ior
    //   1462: iastore
    //   1463: aload #41
    //   1465: iload #15
    //   1467: iload #24
    //   1469: bipush #24
    //   1471: iushr
    //   1472: iload #24
    //   1474: bipush #8
    //   1476: ishl
    //   1477: ior
    //   1478: iastore
    //   1479: iinc #16, 1
    //   1482: iload_2
    //   1483: ifeq -> 1254
    //   1486: aload #6
    //   1488: arraylength
    //   1489: newarray byte
    //   1491: astore #43
    //   1493: iconst_0
    //   1494: istore #44
    //   1496: iload #44
    //   1498: aload #6
    //   1500: arraylength
    //   1501: bipush #16
    //   1503: idiv
    //   1504: if_icmpge -> 2418
    //   1507: bipush #16
    //   1509: newarray byte
    //   1511: astore #45
    //   1513: bipush #16
    //   1515: newarray byte
    //   1517: astore #46
    //   1519: iconst_0
    //   1520: istore #47
    //   1522: iload #47
    //   1524: bipush #16
    //   1526: if_icmpge -> 1552
    //   1529: aload #45
    //   1531: iload #47
    //   1533: aload #6
    //   1535: iload #47
    //   1537: iload #44
    //   1539: bipush #16
    //   1541: imul
    //   1542: iadd
    //   1543: baload
    //   1544: bastore
    //   1545: iinc #47, 1
    //   1548: iload_2
    //   1549: ifeq -> 1522
    //   1552: iconst_0
    //   1553: istore #47
    //   1555: aload #45
    //   1557: iconst_0
    //   1558: baload
    //   1559: bipush #24
    //   1561: ishl
    //   1562: aload #45
    //   1564: iconst_1
    //   1565: baload
    //   1566: sipush #255
    //   1569: iand
    //   1570: bipush #16
    //   1572: ishl
    //   1573: ior
    //   1574: aload #45
    //   1576: iconst_2
    //   1577: baload
    //   1578: sipush #255
    //   1581: iand
    //   1582: bipush #8
    //   1584: ishl
    //   1585: ior
    //   1586: aload #45
    //   1588: iconst_3
    //   1589: baload
    //   1590: sipush #255
    //   1593: iand
    //   1594: ior
    //   1595: aload #30
    //   1597: iconst_0
    //   1598: iaload
    //   1599: ixor
    //   1600: istore #49
    //   1602: aload #45
    //   1604: iconst_4
    //   1605: baload
    //   1606: bipush #24
    //   1608: ishl
    //   1609: aload #45
    //   1611: iconst_5
    //   1612: baload
    //   1613: sipush #255
    //   1616: iand
    //   1617: bipush #16
    //   1619: ishl
    //   1620: ior
    //   1621: aload #45
    //   1623: bipush #6
    //   1625: baload
    //   1626: sipush #255
    //   1629: iand
    //   1630: bipush #8
    //   1632: ishl
    //   1633: ior
    //   1634: aload #45
    //   1636: bipush #7
    //   1638: baload
    //   1639: sipush #255
    //   1642: iand
    //   1643: ior
    //   1644: aload #30
    //   1646: iconst_1
    //   1647: iaload
    //   1648: ixor
    //   1649: istore #50
    //   1651: aload #45
    //   1653: bipush #8
    //   1655: baload
    //   1656: bipush #24
    //   1658: ishl
    //   1659: aload #45
    //   1661: bipush #9
    //   1663: baload
    //   1664: sipush #255
    //   1667: iand
    //   1668: bipush #16
    //   1670: ishl
    //   1671: ior
    //   1672: aload #45
    //   1674: bipush #10
    //   1676: baload
    //   1677: sipush #255
    //   1680: iand
    //   1681: bipush #8
    //   1683: ishl
    //   1684: ior
    //   1685: aload #45
    //   1687: bipush #11
    //   1689: baload
    //   1690: sipush #255
    //   1693: iand
    //   1694: ior
    //   1695: aload #30
    //   1697: iconst_2
    //   1698: iaload
    //   1699: ixor
    //   1700: istore #51
    //   1702: aload #45
    //   1704: bipush #12
    //   1706: baload
    //   1707: bipush #24
    //   1709: ishl
    //   1710: aload #45
    //   1712: bipush #13
    //   1714: baload
    //   1715: sipush #255
    //   1718: iand
    //   1719: bipush #16
    //   1721: ishl
    //   1722: ior
    //   1723: aload #45
    //   1725: bipush #14
    //   1727: baload
    //   1728: sipush #255
    //   1731: iand
    //   1732: bipush #8
    //   1734: ishl
    //   1735: ior
    //   1736: aload #45
    //   1738: bipush #15
    //   1740: baload
    //   1741: sipush #255
    //   1744: iand
    //   1745: ior
    //   1746: aload #30
    //   1748: iconst_3
    //   1749: iaload
    //   1750: ixor
    //   1751: istore #52
    //   1753: iconst_1
    //   1754: istore #53
    //   1756: iload #53
    //   1758: iload #36
    //   1760: if_icmpge -> 2003
    //   1763: iinc #47, 4
    //   1766: aload #38
    //   1768: iload #49
    //   1770: bipush #24
    //   1772: iushr
    //   1773: iaload
    //   1774: aload #39
    //   1776: iload #52
    //   1778: bipush #16
    //   1780: iushr
    //   1781: sipush #255
    //   1784: iand
    //   1785: iaload
    //   1786: ixor
    //   1787: aload #40
    //   1789: iload #51
    //   1791: bipush #8
    //   1793: iushr
    //   1794: sipush #255
    //   1797: iand
    //   1798: iaload
    //   1799: ixor
    //   1800: aload #41
    //   1802: iload #50
    //   1804: sipush #255
    //   1807: iand
    //   1808: iaload
    //   1809: ixor
    //   1810: aload #30
    //   1812: iload #47
    //   1814: iaload
    //   1815: ixor
    //   1816: istore #54
    //   1818: aload #38
    //   1820: iload #50
    //   1822: bipush #24
    //   1824: iushr
    //   1825: iaload
    //   1826: aload #39
    //   1828: iload #49
    //   1830: bipush #16
    //   1832: iushr
    //   1833: sipush #255
    //   1836: iand
    //   1837: iaload
    //   1838: ixor
    //   1839: aload #40
    //   1841: iload #52
    //   1843: bipush #8
    //   1845: iushr
    //   1846: sipush #255
    //   1849: iand
    //   1850: iaload
    //   1851: ixor
    //   1852: aload #41
    //   1854: iload #51
    //   1856: sipush #255
    //   1859: iand
    //   1860: iaload
    //   1861: ixor
    //   1862: aload #30
    //   1864: iload #47
    //   1866: iconst_1
    //   1867: iadd
    //   1868: iaload
    //   1869: ixor
    //   1870: istore #55
    //   1872: aload #38
    //   1874: iload #51
    //   1876: bipush #24
    //   1878: iushr
    //   1879: iaload
    //   1880: aload #39
    //   1882: iload #50
    //   1884: bipush #16
    //   1886: iushr
    //   1887: sipush #255
    //   1890: iand
    //   1891: iaload
    //   1892: ixor
    //   1893: aload #40
    //   1895: iload #49
    //   1897: bipush #8
    //   1899: iushr
    //   1900: sipush #255
    //   1903: iand
    //   1904: iaload
    //   1905: ixor
    //   1906: aload #41
    //   1908: iload #52
    //   1910: sipush #255
    //   1913: iand
    //   1914: iaload
    //   1915: ixor
    //   1916: aload #30
    //   1918: iload #47
    //   1920: iconst_2
    //   1921: iadd
    //   1922: iaload
    //   1923: ixor
    //   1924: istore #56
    //   1926: aload #38
    //   1928: iload #52
    //   1930: bipush #24
    //   1932: iushr
    //   1933: iaload
    //   1934: aload #39
    //   1936: iload #51
    //   1938: bipush #16
    //   1940: iushr
    //   1941: sipush #255
    //   1944: iand
    //   1945: iaload
    //   1946: ixor
    //   1947: aload #40
    //   1949: iload #50
    //   1951: bipush #8
    //   1953: iushr
    //   1954: sipush #255
    //   1957: iand
    //   1958: iaload
    //   1959: ixor
    //   1960: aload #41
    //   1962: iload #49
    //   1964: sipush #255
    //   1967: iand
    //   1968: iaload
    //   1969: ixor
    //   1970: aload #30
    //   1972: iload #47
    //   1974: iconst_3
    //   1975: iadd
    //   1976: iaload
    //   1977: ixor
    //   1978: istore #57
    //   1980: iload #54
    //   1982: istore #49
    //   1984: iload #55
    //   1986: istore #50
    //   1988: iload #56
    //   1990: istore #51
    //   1992: iload #57
    //   1994: istore #52
    //   1996: iinc #53, 1
    //   1999: iload_2
    //   2000: ifeq -> 1756
    //   2003: iinc #47, 4
    //   2006: aload #30
    //   2008: iload #47
    //   2010: iaload
    //   2011: istore #48
    //   2013: aload #46
    //   2015: iconst_0
    //   2016: aload #37
    //   2018: iload #49
    //   2020: bipush #24
    //   2022: iushr
    //   2023: baload
    //   2024: iload #48
    //   2026: bipush #24
    //   2028: iushr
    //   2029: ixor
    //   2030: i2b
    //   2031: bastore
    //   2032: aload #46
    //   2034: iconst_1
    //   2035: aload #37
    //   2037: iload #52
    //   2039: bipush #16
    //   2041: iushr
    //   2042: sipush #255
    //   2045: iand
    //   2046: baload
    //   2047: iload #48
    //   2049: bipush #16
    //   2051: iushr
    //   2052: ixor
    //   2053: i2b
    //   2054: bastore
    //   2055: aload #46
    //   2057: iconst_2
    //   2058: aload #37
    //   2060: iload #51
    //   2062: bipush #8
    //   2064: iushr
    //   2065: sipush #255
    //   2068: iand
    //   2069: baload
    //   2070: iload #48
    //   2072: bipush #8
    //   2074: iushr
    //   2075: ixor
    //   2076: i2b
    //   2077: bastore
    //   2078: aload #46
    //   2080: iconst_3
    //   2081: aload #37
    //   2083: iload #50
    //   2085: sipush #255
    //   2088: iand
    //   2089: baload
    //   2090: iload #48
    //   2092: ixor
    //   2093: i2b
    //   2094: bastore
    //   2095: aload #30
    //   2097: iload #47
    //   2099: iconst_1
    //   2100: iadd
    //   2101: iaload
    //   2102: istore #48
    //   2104: aload #46
    //   2106: iconst_4
    //   2107: aload #37
    //   2109: iload #50
    //   2111: bipush #24
    //   2113: iushr
    //   2114: baload
    //   2115: iload #48
    //   2117: bipush #24
    //   2119: iushr
    //   2120: ixor
    //   2121: i2b
    //   2122: bastore
    //   2123: aload #46
    //   2125: iconst_5
    //   2126: aload #37
    //   2128: iload #49
    //   2130: bipush #16
    //   2132: iushr
    //   2133: sipush #255
    //   2136: iand
    //   2137: baload
    //   2138: iload #48
    //   2140: bipush #16
    //   2142: iushr
    //   2143: ixor
    //   2144: i2b
    //   2145: bastore
    //   2146: aload #46
    //   2148: bipush #6
    //   2150: aload #37
    //   2152: iload #52
    //   2154: bipush #8
    //   2156: iushr
    //   2157: sipush #255
    //   2160: iand
    //   2161: baload
    //   2162: iload #48
    //   2164: bipush #8
    //   2166: iushr
    //   2167: ixor
    //   2168: i2b
    //   2169: bastore
    //   2170: aload #46
    //   2172: bipush #7
    //   2174: aload #37
    //   2176: iload #51
    //   2178: sipush #255
    //   2181: iand
    //   2182: baload
    //   2183: iload #48
    //   2185: ixor
    //   2186: i2b
    //   2187: bastore
    //   2188: aload #30
    //   2190: iload #47
    //   2192: iconst_2
    //   2193: iadd
    //   2194: iaload
    //   2195: istore #48
    //   2197: aload #46
    //   2199: bipush #8
    //   2201: aload #37
    //   2203: iload #51
    //   2205: bipush #24
    //   2207: iushr
    //   2208: baload
    //   2209: iload #48
    //   2211: bipush #24
    //   2213: iushr
    //   2214: ixor
    //   2215: i2b
    //   2216: bastore
    //   2217: aload #46
    //   2219: bipush #9
    //   2221: aload #37
    //   2223: iload #50
    //   2225: bipush #16
    //   2227: iushr
    //   2228: sipush #255
    //   2231: iand
    //   2232: baload
    //   2233: iload #48
    //   2235: bipush #16
    //   2237: iushr
    //   2238: ixor
    //   2239: i2b
    //   2240: bastore
    //   2241: aload #46
    //   2243: bipush #10
    //   2245: aload #37
    //   2247: iload #49
    //   2249: bipush #8
    //   2251: iushr
    //   2252: sipush #255
    //   2255: iand
    //   2256: baload
    //   2257: iload #48
    //   2259: bipush #8
    //   2261: iushr
    //   2262: ixor
    //   2263: i2b
    //   2264: bastore
    //   2265: aload #46
    //   2267: bipush #11
    //   2269: aload #37
    //   2271: iload #52
    //   2273: sipush #255
    //   2276: iand
    //   2277: baload
    //   2278: iload #48
    //   2280: ixor
    //   2281: i2b
    //   2282: bastore
    //   2283: aload #30
    //   2285: iload #47
    //   2287: iconst_3
    //   2288: iadd
    //   2289: iaload
    //   2290: istore #48
    //   2292: aload #46
    //   2294: bipush #12
    //   2296: aload #37
    //   2298: iload #52
    //   2300: bipush #24
    //   2302: iushr
    //   2303: baload
    //   2304: iload #48
    //   2306: bipush #24
    //   2308: iushr
    //   2309: ixor
    //   2310: i2b
    //   2311: bastore
    //   2312: aload #46
    //   2314: bipush #13
    //   2316: aload #37
    //   2318: iload #51
    //   2320: bipush #16
    //   2322: iushr
    //   2323: sipush #255
    //   2326: iand
    //   2327: baload
    //   2328: iload #48
    //   2330: bipush #16
    //   2332: iushr
    //   2333: ixor
    //   2334: i2b
    //   2335: bastore
    //   2336: aload #46
    //   2338: bipush #14
    //   2340: aload #37
    //   2342: iload #50
    //   2344: bipush #8
    //   2346: iushr
    //   2347: sipush #255
    //   2350: iand
    //   2351: baload
    //   2352: iload #48
    //   2354: bipush #8
    //   2356: iushr
    //   2357: ixor
    //   2358: i2b
    //   2359: bastore
    //   2360: aload #46
    //   2362: bipush #15
    //   2364: aload #37
    //   2366: iload #49
    //   2368: sipush #255
    //   2371: iand
    //   2372: baload
    //   2373: iload #48
    //   2375: ixor
    //   2376: i2b
    //   2377: bastore
    //   2378: iconst_0
    //   2379: istore #53
    //   2381: iload #53
    //   2383: bipush #16
    //   2385: if_icmpge -> 2411
    //   2388: aload #43
    //   2390: iload #53
    //   2392: iload #44
    //   2394: bipush #16
    //   2396: imul
    //   2397: iadd
    //   2398: aload #46
    //   2400: iload #53
    //   2402: baload
    //   2403: bastore
    //   2404: iinc #53, 1
    //   2407: iload_2
    //   2408: ifeq -> 2381
    //   2411: iinc #44, 1
    //   2414: iload_2
    //   2415: ifeq -> 1496
    //   2418: aload #43
    //   2420: arraylength
    //   2421: ifle -> 2502
    //   2424: aload #43
    //   2426: aload #43
    //   2428: arraylength
    //   2429: iconst_1
    //   2430: isub
    //   2431: baload
    //   2432: istore #44
    //   2434: iload #44
    //   2436: bipush #16
    //   2438: if_icmple -> 2449
    //   2441: aload #43
    //   2443: astore #35
    //   2445: iload_2
    //   2446: ifeq -> 2502
    //   2449: aload #43
    //   2451: arraylength
    //   2452: iload #44
    //   2454: isub
    //   2455: newarray byte
    //   2457: astore #35
    //   2459: iconst_0
    //   2460: istore #45
    //   2462: iload #45
    //   2464: aload #35
    //   2466: arraylength
    //   2467: if_icmpge -> 2502
    //   2470: iload #45
    //   2472: aload #43
    //   2474: arraylength
    //   2475: if_icmpge -> 2502
    //   2478: aload #35
    //   2480: iload #45
    //   2482: aload #43
    //   2484: iload #45
    //   2486: baload
    //   2487: bastore
    //   2488: iinc #45, 1
    //   2491: iload_2
    //   2492: ifeq -> 2462
    //   2495: goto -> 2502
    //   2498: invokestatic a : (Ljava/lang/Throwable;)Ljava/lang/Throwable;
    //   2501: athrow
    //   2502: aload #35
    //   2504: astore #7
    //   2506: new java/math/BigInteger
    //   2509: dup
    //   2510: aload #7
    //   2512: invokespecial <init> : ([B)V
    //   2515: invokevirtual abs : ()Ljava/math/BigInteger;
    //   2518: putstatic burp/Zg0f.Zm : Ljava/lang/Object;
    //   2521: getstatic burp/Zlid.Zx : Ljava/lang/Object;
    //   2524: checkcast java/math/BigInteger
    //   2527: invokevirtual toByteArray : ()[B
    //   2530: astore_3
    //   2531: bipush #64
    //   2533: newarray byte
    //   2535: dup
    //   2536: iconst_0
    //   2537: bipush #-128
    //   2539: bastore
    //   2540: dup
    //   2541: iconst_1
    //   2542: iconst_0
    //   2543: bastore
    //   2544: dup
    //   2545: iconst_2
    //   2546: iconst_0
    //   2547: bastore
    //   2548: dup
    //   2549: iconst_3
    //   2550: iconst_0
    //   2551: bastore
    //   2552: dup
    //   2553: iconst_4
    //   2554: iconst_0
    //   2555: bastore
    //   2556: dup
    //   2557: iconst_5
    //   2558: iconst_0
    //   2559: bastore
    //   2560: dup
    //   2561: bipush #6
    //   2563: iconst_0
    //   2564: bastore
    //   2565: dup
    //   2566: bipush #7
    //   2568: iconst_0
    //   2569: bastore
    //   2570: dup
    //   2571: bipush #8
    //   2573: iconst_0
    //   2574: bastore
    //   2575: dup
    //   2576: bipush #9
    //   2578: iconst_0
    //   2579: bastore
    //   2580: dup
    //   2581: bipush #10
    //   2583: iconst_0
    //   2584: bastore
    //   2585: dup
    //   2586: bipush #11
    //   2588: iconst_0
    //   2589: bastore
    //   2590: dup
    //   2591: bipush #12
    //   2593: iconst_0
    //   2594: bastore
    //   2595: dup
    //   2596: bipush #13
    //   2598: iconst_0
    //   2599: bastore
    //   2600: dup
    //   2601: bipush #14
    //   2603: iconst_0
    //   2604: bastore
    //   2605: dup
    //   2606: bipush #15
    //   2608: iconst_0
    //   2609: bastore
    //   2610: dup
    //   2611: bipush #16
    //   2613: iconst_0
    //   2614: bastore
    //   2615: dup
    //   2616: bipush #17
    //   2618: iconst_0
    //   2619: bastore
    //   2620: dup
    //   2621: bipush #18
    //   2623: iconst_0
    //   2624: bastore
    //   2625: dup
    //   2626: bipush #19
    //   2628: iconst_0
    //   2629: bastore
    //   2630: dup
    //   2631: bipush #20
    //   2633: iconst_0
    //   2634: bastore
    //   2635: dup
    //   2636: bipush #21
    //   2638: iconst_0
    //   2639: bastore
    //   2640: dup
    //   2641: bipush #22
    //   2643: iconst_0
    //   2644: bastore
    //   2645: dup
    //   2646: bipush #23
    //   2648: iconst_0
    //   2649: bastore
    //   2650: dup
    //   2651: bipush #24
    //   2653: iconst_0
    //   2654: bastore
    //   2655: dup
    //   2656: bipush #25
    //   2658: iconst_0
    //   2659: bastore
    //   2660: dup
    //   2661: bipush #26
    //   2663: iconst_0
    //   2664: bastore
    //   2665: dup
    //   2666: bipush #27
    //   2668: iconst_0
    //   2669: bastore
    //   2670: dup
    //   2671: bipush #28
    //   2673: iconst_0
    //   2674: bastore
    //   2675: dup
    //   2676: bipush #29
    //   2678: iconst_0
    //   2679: bastore
    //   2680: dup
    //   2681: bipush #30
    //   2683: iconst_0
    //   2684: bastore
    //   2685: dup
    //   2686: bipush #31
    //   2688: iconst_0
    //   2689: bastore
    //   2690: dup
    //   2691: bipush #32
    //   2693: iconst_0
    //   2694: bastore
    //   2695: dup
    //   2696: bipush #33
    //   2698: iconst_0
    //   2699: bastore
    //   2700: dup
    //   2701: bipush #34
    //   2703: iconst_0
    //   2704: bastore
    //   2705: dup
    //   2706: bipush #35
    //   2708: iconst_0
    //   2709: bastore
    //   2710: dup
    //   2711: bipush #36
    //   2713: iconst_0
    //   2714: bastore
    //   2715: dup
    //   2716: bipush #37
    //   2718: iconst_0
    //   2719: bastore
    //   2720: dup
    //   2721: bipush #38
    //   2723: iconst_0
    //   2724: bastore
    //   2725: dup
    //   2726: bipush #39
    //   2728: iconst_0
    //   2729: bastore
    //   2730: dup
    //   2731: bipush #40
    //   2733: iconst_0
    //   2734: bastore
    //   2735: dup
    //   2736: bipush #41
    //   2738: iconst_0
    //   2739: bastore
    //   2740: dup
    //   2741: bipush #42
    //   2743: iconst_0
    //   2744: bastore
    //   2745: dup
    //   2746: bipush #43
    //   2748: iconst_0
    //   2749: bastore
    //   2750: dup
    //   2751: bipush #44
    //   2753: iconst_0
    //   2754: bastore
    //   2755: dup
    //   2756: bipush #45
    //   2758: iconst_0
    //   2759: bastore
    //   2760: dup
    //   2761: bipush #46
    //   2763: iconst_0
    //   2764: bastore
    //   2765: dup
    //   2766: bipush #47
    //   2768: iconst_0
    //   2769: bastore
    //   2770: dup
    //   2771: bipush #48
    //   2773: iconst_0
    //   2774: bastore
    //   2775: dup
    //   2776: bipush #49
    //   2778: iconst_0
    //   2779: bastore
    //   2780: dup
    //   2781: bipush #50
    //   2783: iconst_0
    //   2784: bastore
    //   2785: dup
    //   2786: bipush #51
    //   2788: iconst_0
    //   2789: bastore
    //   2790: dup
    //   2791: bipush #52
    //   2793: iconst_0
    //   2794: bastore
    //   2795: dup
    //   2796: bipush #53
    //   2798: iconst_0
    //   2799: bastore
    //   2800: dup
    //   2801: bipush #54
    //   2803: iconst_0
    //   2804: bastore
    //   2805: dup
    //   2806: bipush #55
    //   2808: iconst_0
    //   2809: bastore
    //   2810: dup
    //   2811: bipush #56
    //   2813: iconst_0
    //   2814: bastore
    //   2815: dup
    //   2816: bipush #57
    //   2818: iconst_0
    //   2819: bastore
    //   2820: dup
    //   2821: bipush #58
    //   2823: iconst_0
    //   2824: bastore
    //   2825: dup
    //   2826: bipush #59
    //   2828: iconst_0
    //   2829: bastore
    //   2830: dup
    //   2831: bipush #60
    //   2833: iconst_0
    //   2834: bastore
    //   2835: dup
    //   2836: bipush #61
    //   2838: iconst_0
    //   2839: bastore
    //   2840: dup
    //   2841: bipush #62
    //   2843: iconst_0
    //   2844: bastore
    //   2845: dup
    //   2846: bipush #63
    //   2848: iconst_0
    //   2849: bastore
    //   2850: astore #5
    //   2852: bipush #64
    //   2854: newarray int
    //   2856: dup
    //   2857: iconst_0
    //   2858: ldc 1116352408
    //   2860: iastore
    //   2861: dup
    //   2862: iconst_1
    //   2863: ldc 1899447441
    //   2865: iastore
    //   2866: dup
    //   2867: iconst_2
    //   2868: ldc -1245643825
    //   2870: iastore
    //   2871: dup
    //   2872: iconst_3
    //   2873: ldc -373957723
    //   2875: iastore
    //   2876: dup
    //   2877: iconst_4
    //   2878: ldc 961987163
    //   2880: iastore
    //   2881: dup
    //   2882: iconst_5
    //   2883: ldc 1508970993
    //   2885: iastore
    //   2886: dup
    //   2887: bipush #6
    //   2889: ldc -1841331548
    //   2891: iastore
    //   2892: dup
    //   2893: bipush #7
    //   2895: ldc -1424204075
    //   2897: iastore
    //   2898: dup
    //   2899: bipush #8
    //   2901: ldc -670586216
    //   2903: iastore
    //   2904: dup
    //   2905: bipush #9
    //   2907: ldc 310598401
    //   2909: iastore
    //   2910: dup
    //   2911: bipush #10
    //   2913: ldc 607225278
    //   2915: iastore
    //   2916: dup
    //   2917: bipush #11
    //   2919: ldc 1426881987
    //   2921: iastore
    //   2922: dup
    //   2923: bipush #12
    //   2925: ldc 1925078388
    //   2927: iastore
    //   2928: dup
    //   2929: bipush #13
    //   2931: ldc -2132889090
    //   2933: iastore
    //   2934: dup
    //   2935: bipush #14
    //   2937: ldc -1680079193
    //   2939: iastore
    //   2940: dup
    //   2941: bipush #15
    //   2943: ldc -1046744716
    //   2945: iastore
    //   2946: dup
    //   2947: bipush #16
    //   2949: ldc -459576895
    //   2951: iastore
    //   2952: dup
    //   2953: bipush #17
    //   2955: ldc -272742522
    //   2957: iastore
    //   2958: dup
    //   2959: bipush #18
    //   2961: ldc 264347078
    //   2963: iastore
    //   2964: dup
    //   2965: bipush #19
    //   2967: ldc 604807628
    //   2969: iastore
    //   2970: dup
    //   2971: bipush #20
    //   2973: ldc 770255983
    //   2975: iastore
    //   2976: dup
    //   2977: bipush #21
    //   2979: ldc 1249150122
    //   2981: iastore
    //   2982: dup
    //   2983: bipush #22
    //   2985: ldc 1555081692
    //   2987: iastore
    //   2988: dup
    //   2989: bipush #23
    //   2991: ldc 1996064986
    //   2993: iastore
    //   2994: dup
    //   2995: bipush #24
    //   2997: ldc -1740746414
    //   2999: iastore
    //   3000: dup
    //   3001: bipush #25
    //   3003: ldc -1473132947
    //   3005: iastore
    //   3006: dup
    //   3007: bipush #26
    //   3009: ldc -1341970488
    //   3011: iastore
    //   3012: dup
    //   3013: bipush #27
    //   3015: ldc -1084653625
    //   3017: iastore
    //   3018: dup
    //   3019: bipush #28
    //   3021: ldc -958395405
    //   3023: iastore
    //   3024: dup
    //   3025: bipush #29
    //   3027: ldc -710438585
    //   3029: iastore
    //   3030: dup
    //   3031: bipush #30
    //   3033: ldc 113926993
    //   3035: iastore
    //   3036: dup
    //   3037: bipush #31
    //   3039: ldc 338241895
    //   3041: iastore
    //   3042: dup
    //   3043: bipush #32
    //   3045: ldc 666307205
    //   3047: iastore
    //   3048: dup
    //   3049: bipush #33
    //   3051: ldc 773529912
    //   3053: iastore
    //   3054: dup
    //   3055: bipush #34
    //   3057: ldc 1294757372
    //   3059: iastore
    //   3060: dup
    //   3061: bipush #35
    //   3063: ldc 1396182291
    //   3065: iastore
    //   3066: dup
    //   3067: bipush #36
    //   3069: ldc 1695183700
    //   3071: iastore
    //   3072: dup
    //   3073: bipush #37
    //   3075: ldc 1986661051
    //   3077: iastore
    //   3078: dup
    //   3079: bipush #38
    //   3081: ldc -2117940946
    //   3083: iastore
    //   3084: dup
    //   3085: bipush #39
    //   3087: ldc -1838011259
    //   3089: iastore
    //   3090: dup
    //   3091: bipush #40
    //   3093: ldc -1564481375
    //   3095: iastore
    //   3096: dup
    //   3097: bipush #41
    //   3099: ldc -1474664885
    //   3101: iastore
    //   3102: dup
    //   3103: bipush #42
    //   3105: ldc -1035236496
    //   3107: iastore
    //   3108: dup
    //   3109: bipush #43
    //   3111: ldc -949202525
    //   3113: iastore
    //   3114: dup
    //   3115: bipush #44
    //   3117: ldc -778901479
    //   3119: iastore
    //   3120: dup
    //   3121: bipush #45
    //   3123: ldc -694614492
    //   3125: iastore
    //   3126: dup
    //   3127: bipush #46
    //   3129: ldc -200395387
    //   3131: iastore
    //   3132: dup
    //   3133: bipush #47
    //   3135: ldc 275423344
    //   3137: iastore
    //   3138: dup
    //   3139: bipush #48
    //   3141: ldc 430227734
    //   3143: iastore
    //   3144: dup
    //   3145: bipush #49
    //   3147: ldc 506948616
    //   3149: iastore
    //   3150: dup
    //   3151: bipush #50
    //   3153: ldc 659060556
    //   3155: iastore
    //   3156: dup
    //   3157: bipush #51
    //   3159: ldc 883997877
    //   3161: iastore
    //   3162: dup
    //   3163: bipush #52
    //   3165: ldc 958139571
    //   3167: iastore
    //   3168: dup
    //   3169: bipush #53
    //   3171: ldc 1322822218
    //   3173: iastore
    //   3174: dup
    //   3175: bipush #54
    //   3177: ldc 1537002063
    //   3179: iastore
    //   3180: dup
    //   3181: bipush #55
    //   3183: ldc 1747873779
    //   3185: iastore
    //   3186: dup
    //   3187: bipush #56
    //   3189: ldc 1955562222
    //   3191: iastore
    //   3192: dup
    //   3193: bipush #57
    //   3195: ldc 2024104815
    //   3197: iastore
    //   3198: dup
    //   3199: bipush #58
    //   3201: ldc -2067236844
    //   3203: iastore
    //   3204: dup
    //   3205: bipush #59
    //   3207: ldc -1933114872
    //   3209: iastore
    //   3210: dup
    //   3211: bipush #60
    //   3213: ldc -1866530822
    //   3215: iastore
    //   3216: dup
    //   3217: bipush #61
    //   3219: ldc -1538233109
    //   3221: iastore
    //   3222: dup
    //   3223: bipush #62
    //   3225: ldc -1090935817
    //   3227: iastore
    //   3228: dup
    //   3229: bipush #63
    //   3231: ldc -965641998
    //   3233: iastore
    //   3234: astore #6
    //   3236: iconst_2
    //   3237: newarray int
    //   3239: dup
    //   3240: iconst_0
    //   3241: iconst_0
    //   3242: iastore
    //   3243: dup
    //   3244: iconst_1
    //   3245: iconst_0
    //   3246: iastore
    //   3247: astore #7
    //   3249: bipush #8
    //   3251: newarray int
    //   3253: dup
    //   3254: iconst_0
    //   3255: ldc 1779033703
    //   3257: iastore
    //   3258: dup
    //   3259: iconst_1
    //   3260: ldc -1150833019
    //   3262: iastore
    //   3263: dup
    //   3264: iconst_2
    //   3265: ldc 1013904242
    //   3267: iastore
    //   3268: dup
    //   3269: iconst_3
    //   3270: ldc -1521486534
    //   3272: iastore
    //   3273: dup
    //   3274: iconst_4
    //   3275: ldc 1359893119
    //   3277: iastore
    //   3278: dup
    //   3279: iconst_5
    //   3280: ldc -1694144372
    //   3282: iastore
    //   3283: dup
    //   3284: bipush #6
    //   3286: ldc 528734635
    //   3288: iastore
    //   3289: dup
    //   3290: bipush #7
    //   3292: ldc 1541459225
    //   3294: iastore
    //   3295: astore #8
    //   3297: bipush #64
    //   3299: newarray byte
    //   3301: astore #9
    //   3303: bipush #64
    //   3305: newarray byte
    //   3307: astore #10
    //   3309: aload_3
    //   3310: arraylength
    //   3311: istore #11
    //   3313: aload #7
    //   3315: iconst_0
    //   3316: iaload
    //   3317: bipush #63
    //   3319: iand
    //   3320: istore #12
    //   3322: aload #7
    //   3324: iconst_0
    //   3325: dup2
    //   3326: iaload
    //   3327: iload #11
    //   3329: iadd
    //   3330: iastore
    //   3331: aload #7
    //   3333: iconst_0
    //   3334: dup2
    //   3335: iaload
    //   3336: iconst_m1
    //   3337: iand
    //   3338: iastore
    //   3339: aload #7
    //   3341: iconst_0
    //   3342: iaload
    //   3343: iload #11
    //   3345: if_icmpge -> 3363
    //   3348: aload #7
    //   3350: iconst_1
    //   3351: dup2
    //   3352: iaload
    //   3353: iconst_1
    //   3354: iadd
    //   3355: iastore
    //   3356: goto -> 3363
    //   3359: invokestatic a : (Ljava/lang/Throwable;)Ljava/lang/Throwable;
    //   3362: athrow
    //   3363: iconst_0
    //   3364: istore #13
    //   3366: iload #11
    //   3368: bipush #64
    //   3370: if_icmplt -> 3979
    //   3373: iconst_0
    //   3374: istore #14
    //   3376: iload #14
    //   3378: bipush #64
    //   3380: if_icmpge -> 3402
    //   3383: aload #10
    //   3385: iload #14
    //   3387: aload_3
    //   3388: iload #13
    //   3390: iload #14
    //   3392: iadd
    //   3393: baload
    //   3394: bastore
    //   3395: iinc #14, 1
    //   3398: iload_2
    //   3399: ifeq -> 3376
    //   3402: bipush #64
    //   3404: newarray int
    //   3406: astore #14
    //   3408: bipush #8
    //   3410: newarray int
    //   3412: astore #15
    //   3414: iconst_0
    //   3415: istore #16
    //   3417: iload #16
    //   3419: bipush #8
    //   3421: if_icmpge -> 3441
    //   3424: aload #15
    //   3426: iload #16
    //   3428: aload #8
    //   3430: iload #16
    //   3432: iaload
    //   3433: iastore
    //   3434: iinc #16, 1
    //   3437: iload_2
    //   3438: ifeq -> 3417
    //   3441: iconst_0
    //   3442: istore #16
    //   3444: iload #16
    //   3446: bipush #64
    //   3448: if_icmpge -> 3939
    //   3451: iload #16
    //   3453: bipush #16
    //   3455: if_icmpge -> 3536
    //   3458: aload #14
    //   3460: iload #16
    //   3462: aload #10
    //   3464: iconst_4
    //   3465: iload #16
    //   3467: imul
    //   3468: baload
    //   3469: sipush #255
    //   3472: iand
    //   3473: bipush #24
    //   3475: ishl
    //   3476: aload #10
    //   3478: iconst_4
    //   3479: iload #16
    //   3481: imul
    //   3482: iconst_1
    //   3483: iadd
    //   3484: baload
    //   3485: sipush #255
    //   3488: iand
    //   3489: bipush #16
    //   3491: ishl
    //   3492: ior
    //   3493: aload #10
    //   3495: iconst_4
    //   3496: iload #16
    //   3498: imul
    //   3499: iconst_2
    //   3500: iadd
    //   3501: baload
    //   3502: sipush #255
    //   3505: iand
    //   3506: bipush #8
    //   3508: ishl
    //   3509: ior
    //   3510: aload #10
    //   3512: iconst_4
    //   3513: iload #16
    //   3515: imul
    //   3516: iconst_3
    //   3517: iadd
    //   3518: baload
    //   3519: sipush #255
    //   3522: iand
    //   3523: ior
    //   3524: iastore
    //   3525: iload_2
    //   3526: ifeq -> 3679
    //   3529: goto -> 3536
    //   3532: invokestatic a : (Ljava/lang/Throwable;)Ljava/lang/Throwable;
    //   3535: athrow
    //   3536: aload #14
    //   3538: iload #16
    //   3540: aload #14
    //   3542: iload #16
    //   3544: iconst_2
    //   3545: isub
    //   3546: iaload
    //   3547: bipush #17
    //   3549: iushr
    //   3550: aload #14
    //   3552: iload #16
    //   3554: iconst_2
    //   3555: isub
    //   3556: iaload
    //   3557: bipush #15
    //   3559: ishl
    //   3560: ior
    //   3561: aload #14
    //   3563: iload #16
    //   3565: iconst_2
    //   3566: isub
    //   3567: iaload
    //   3568: bipush #19
    //   3570: iushr
    //   3571: aload #14
    //   3573: iload #16
    //   3575: iconst_2
    //   3576: isub
    //   3577: iaload
    //   3578: bipush #13
    //   3580: ishl
    //   3581: ior
    //   3582: ixor
    //   3583: aload #14
    //   3585: iload #16
    //   3587: iconst_2
    //   3588: isub
    //   3589: iaload
    //   3590: bipush #10
    //   3592: iushr
    //   3593: ixor
    //   3594: aload #14
    //   3596: iload #16
    //   3598: bipush #7
    //   3600: isub
    //   3601: iaload
    //   3602: iadd
    //   3603: aload #14
    //   3605: iload #16
    //   3607: bipush #15
    //   3609: isub
    //   3610: iaload
    //   3611: bipush #7
    //   3613: iushr
    //   3614: aload #14
    //   3616: iload #16
    //   3618: bipush #15
    //   3620: isub
    //   3621: iaload
    //   3622: bipush #25
    //   3624: ishl
    //   3625: ior
    //   3626: aload #14
    //   3628: iload #16
    //   3630: bipush #15
    //   3632: isub
    //   3633: iaload
    //   3634: bipush #18
    //   3636: iushr
    //   3637: aload #14
    //   3639: iload #16
    //   3641: bipush #15
    //   3643: isub
    //   3644: iaload
    //   3645: bipush #14
    //   3647: ishl
    //   3648: ior
    //   3649: ixor
    //   3650: aload #14
    //   3652: iload #16
    //   3654: bipush #15
    //   3656: isub
    //   3657: iaload
    //   3658: iconst_3
    //   3659: iushr
    //   3660: ixor
    //   3661: iadd
    //   3662: aload #14
    //   3664: iload #16
    //   3666: bipush #16
    //   3668: isub
    //   3669: iaload
    //   3670: iadd
    //   3671: iastore
    //   3672: goto -> 3679
    //   3675: invokestatic a : (Ljava/lang/Throwable;)Ljava/lang/Throwable;
    //   3678: athrow
    //   3679: aload #15
    //   3681: bipush #7
    //   3683: iaload
    //   3684: aload #15
    //   3686: iconst_4
    //   3687: iaload
    //   3688: bipush #6
    //   3690: iushr
    //   3691: aload #15
    //   3693: iconst_4
    //   3694: iaload
    //   3695: bipush #26
    //   3697: ishl
    //   3698: ior
    //   3699: aload #15
    //   3701: iconst_4
    //   3702: iaload
    //   3703: bipush #11
    //   3705: iushr
    //   3706: aload #15
    //   3708: iconst_4
    //   3709: iaload
    //   3710: bipush #21
    //   3712: ishl
    //   3713: ior
    //   3714: ixor
    //   3715: aload #15
    //   3717: iconst_4
    //   3718: iaload
    //   3719: bipush #25
    //   3721: iushr
    //   3722: aload #15
    //   3724: iconst_4
    //   3725: iaload
    //   3726: bipush #7
    //   3728: ishl
    //   3729: ior
    //   3730: ixor
    //   3731: iadd
    //   3732: aload #15
    //   3734: bipush #6
    //   3736: iaload
    //   3737: aload #15
    //   3739: iconst_4
    //   3740: iaload
    //   3741: aload #15
    //   3743: iconst_5
    //   3744: iaload
    //   3745: aload #15
    //   3747: bipush #6
    //   3749: iaload
    //   3750: ixor
    //   3751: iand
    //   3752: ixor
    //   3753: iadd
    //   3754: aload #6
    //   3756: iload #16
    //   3758: iaload
    //   3759: iadd
    //   3760: aload #14
    //   3762: iload #16
    //   3764: iaload
    //   3765: iadd
    //   3766: istore #17
    //   3768: aload #15
    //   3770: iconst_0
    //   3771: iaload
    //   3772: iconst_2
    //   3773: iushr
    //   3774: aload #15
    //   3776: iconst_0
    //   3777: iaload
    //   3778: bipush #30
    //   3780: ishl
    //   3781: ior
    //   3782: aload #15
    //   3784: iconst_0
    //   3785: iaload
    //   3786: bipush #13
    //   3788: iushr
    //   3789: aload #15
    //   3791: iconst_0
    //   3792: iaload
    //   3793: bipush #19
    //   3795: ishl
    //   3796: ior
    //   3797: ixor
    //   3798: aload #15
    //   3800: iconst_0
    //   3801: iaload
    //   3802: bipush #22
    //   3804: iushr
    //   3805: aload #15
    //   3807: iconst_0
    //   3808: iaload
    //   3809: bipush #10
    //   3811: ishl
    //   3812: ior
    //   3813: ixor
    //   3814: aload #15
    //   3816: iconst_0
    //   3817: iaload
    //   3818: aload #15
    //   3820: iconst_1
    //   3821: iaload
    //   3822: iand
    //   3823: aload #15
    //   3825: iconst_2
    //   3826: iaload
    //   3827: aload #15
    //   3829: iconst_0
    //   3830: iaload
    //   3831: aload #15
    //   3833: iconst_1
    //   3834: iaload
    //   3835: ior
    //   3836: iand
    //   3837: ior
    //   3838: iadd
    //   3839: istore #18
    //   3841: aload #15
    //   3843: iconst_3
    //   3844: dup2
    //   3845: iaload
    //   3846: iload #17
    //   3848: iadd
    //   3849: iastore
    //   3850: aload #15
    //   3852: bipush #7
    //   3854: iload #17
    //   3856: iload #18
    //   3858: iadd
    //   3859: iastore
    //   3860: aload #15
    //   3862: bipush #7
    //   3864: iaload
    //   3865: istore #17
    //   3867: aload #15
    //   3869: bipush #7
    //   3871: aload #15
    //   3873: bipush #6
    //   3875: iaload
    //   3876: iastore
    //   3877: aload #15
    //   3879: bipush #6
    //   3881: aload #15
    //   3883: iconst_5
    //   3884: iaload
    //   3885: iastore
    //   3886: aload #15
    //   3888: iconst_5
    //   3889: aload #15
    //   3891: iconst_4
    //   3892: iaload
    //   3893: iastore
    //   3894: aload #15
    //   3896: iconst_4
    //   3897: aload #15
    //   3899: iconst_3
    //   3900: iaload
    //   3901: iastore
    //   3902: aload #15
    //   3904: iconst_3
    //   3905: aload #15
    //   3907: iconst_2
    //   3908: iaload
    //   3909: iastore
    //   3910: aload #15
    //   3912: iconst_2
    //   3913: aload #15
    //   3915: iconst_1
    //   3916: iaload
    //   3917: iastore
    //   3918: aload #15
    //   3920: iconst_1
    //   3921: aload #15
    //   3923: iconst_0
    //   3924: iaload
    //   3925: iastore
    //   3926: aload #15
    //   3928: iconst_0
    //   3929: iload #17
    //   3931: iastore
    //   3932: iinc #16, 1
    //   3935: iload_2
    //   3936: ifeq -> 3444
    //   3939: iconst_0
    //   3940: istore #16
    //   3942: iload #16
    //   3944: bipush #8
    //   3946: if_icmpge -> 3969
    //   3949: aload #8
    //   3951: iload #16
    //   3953: dup2
    //   3954: iaload
    //   3955: aload #15
    //   3957: iload #16
    //   3959: iaload
    //   3960: iadd
    //   3961: iastore
    //   3962: iinc #16, 1
    //   3965: iload_2
    //   3966: ifeq -> 3942
    //   3969: iinc #13, 64
    //   3972: iinc #11, -64
    //   3975: iload_2
    //   3976: ifeq -> 3366
    //   3979: iload #11
    //   3981: ifle -> 4016
    //   3984: iconst_0
    //   3985: istore #14
    //   3987: iload #14
    //   3989: iload #11
    //   3991: if_icmpge -> 4016
    //   3994: aload #9
    //   3996: iload #12
    //   3998: iload #14
    //   4000: iadd
    //   4001: aload_3
    //   4002: iload #13
    //   4004: iload #14
    //   4006: iadd
    //   4007: baload
    //   4008: bastore
    //   4009: iinc #14, 1
    //   4012: iload_2
    //   4013: ifeq -> 3987
    //   4016: aload #7
    //   4018: iconst_0
    //   4019: iaload
    //   4020: bipush #29
    //   4022: iushr
    //   4023: aload #7
    //   4025: iconst_1
    //   4026: iaload
    //   4027: iconst_3
    //   4028: ishl
    //   4029: ior
    //   4030: istore #14
    //   4032: aload #7
    //   4034: iconst_0
    //   4035: iaload
    //   4036: iconst_3
    //   4037: ishl
    //   4038: istore #15
    //   4040: aload #7
    //   4042: iconst_0
    //   4043: iaload
    //   4044: bipush #63
    //   4046: iand
    //   4047: istore #16
    //   4049: iload #16
    //   4051: bipush #56
    //   4053: if_icmpge -> 4068
    //   4056: bipush #56
    //   4058: iload #16
    //   4060: isub
    //   4061: goto -> 4073
    //   4064: invokestatic a : (Ljava/lang/Throwable;)Ljava/lang/Throwable;
    //   4067: athrow
    //   4068: bipush #120
    //   4070: iload #16
    //   4072: isub
    //   4073: istore #17
    //   4075: aload #7
    //   4077: iconst_0
    //   4078: iaload
    //   4079: bipush #63
    //   4081: iand
    //   4082: istore #12
    //   4084: bipush #64
    //   4086: iload #12
    //   4088: isub
    //   4089: istore #18
    //   4091: aload #7
    //   4093: iconst_0
    //   4094: dup2
    //   4095: iaload
    //   4096: iload #17
    //   4098: iadd
    //   4099: iastore
    //   4100: aload #7
    //   4102: iconst_0
    //   4103: dup2
    //   4104: iaload
    //   4105: iconst_m1
    //   4106: iand
    //   4107: iastore
    //   4108: aload #7
    //   4110: iconst_0
    //   4111: iaload
    //   4112: iload #17
    //   4114: if_icmpge -> 4132
    //   4117: aload #7
    //   4119: iconst_1
    //   4120: dup2
    //   4121: iaload
    //   4122: iconst_1
    //   4123: iadd
    //   4124: iastore
    //   4125: goto -> 4132
    //   4128: invokestatic a : (Ljava/lang/Throwable;)Ljava/lang/Throwable;
    //   4131: athrow
    //   4132: iconst_0
    //   4133: istore #13
    //   4135: iload #12
    //   4137: ifle -> 4768
    //   4140: iload #17
    //   4142: iload #18
    //   4144: if_icmplt -> 4768
    //   4147: goto -> 4154
    //   4150: invokestatic a : (Ljava/lang/Throwable;)Ljava/lang/Throwable;
    //   4153: athrow
    //   4154: iconst_0
    //   4155: istore #19
    //   4157: iload #19
    //   4159: iload #18
    //   4161: if_icmpge -> 4184
    //   4164: aload #9
    //   4166: iload #12
    //   4168: iload #19
    //   4170: iadd
    //   4171: aload #5
    //   4173: iload #19
    //   4175: baload
    //   4176: bastore
    //   4177: iinc #19, 1
    //   4180: iload_2
    //   4181: ifeq -> 4157
    //   4184: bipush #64
    //   4186: newarray int
    //   4188: astore #19
    //   4190: bipush #8
    //   4192: newarray int
    //   4194: astore #20
    //   4196: iconst_0
    //   4197: istore #21
    //   4199: iload #21
    //   4201: bipush #8
    //   4203: if_icmpge -> 4223
    //   4206: aload #20
    //   4208: iload #21
    //   4210: aload #8
    //   4212: iload #21
    //   4214: iaload
    //   4215: iastore
    //   4216: iinc #21, 1
    //   4219: iload_2
    //   4220: ifeq -> 4199
    //   4223: iconst_0
    //   4224: istore #21
    //   4226: iload #21
    //   4228: bipush #64
    //   4230: if_icmpge -> 4721
    //   4233: iload #21
    //   4235: bipush #16
    //   4237: if_icmpge -> 4318
    //   4240: aload #19
    //   4242: iload #21
    //   4244: aload #9
    //   4246: iconst_4
    //   4247: iload #21
    //   4249: imul
    //   4250: baload
    //   4251: sipush #255
    //   4254: iand
    //   4255: bipush #24
    //   4257: ishl
    //   4258: aload #9
    //   4260: iconst_4
    //   4261: iload #21
    //   4263: imul
    //   4264: iconst_1
    //   4265: iadd
    //   4266: baload
    //   4267: sipush #255
    //   4270: iand
    //   4271: bipush #16
    //   4273: ishl
    //   4274: ior
    //   4275: aload #9
    //   4277: iconst_4
    //   4278: iload #21
    //   4280: imul
    //   4281: iconst_2
    //   4282: iadd
    //   4283: baload
    //   4284: sipush #255
    //   4287: iand
    //   4288: bipush #8
    //   4290: ishl
    //   4291: ior
    //   4292: aload #9
    //   4294: iconst_4
    //   4295: iload #21
    //   4297: imul
    //   4298: iconst_3
    //   4299: iadd
    //   4300: baload
    //   4301: sipush #255
    //   4304: iand
    //   4305: ior
    //   4306: iastore
    //   4307: iload_2
    //   4308: ifeq -> 4461
    //   4311: goto -> 4318
    //   4314: invokestatic a : (Ljava/lang/Throwable;)Ljava/lang/Throwable;
    //   4317: athrow
    //   4318: aload #19
    //   4320: iload #21
    //   4322: aload #19
    //   4324: iload #21
    //   4326: iconst_2
    //   4327: isub
    //   4328: iaload
    //   4329: bipush #17
    //   4331: iushr
    //   4332: aload #19
    //   4334: iload #21
    //   4336: iconst_2
    //   4337: isub
    //   4338: iaload
    //   4339: bipush #15
    //   4341: ishl
    //   4342: ior
    //   4343: aload #19
    //   4345: iload #21
    //   4347: iconst_2
    //   4348: isub
    //   4349: iaload
    //   4350: bipush #19
    //   4352: iushr
    //   4353: aload #19
    //   4355: iload #21
    //   4357: iconst_2
    //   4358: isub
    //   4359: iaload
    //   4360: bipush #13
    //   4362: ishl
    //   4363: ior
    //   4364: ixor
    //   4365: aload #19
    //   4367: iload #21
    //   4369: iconst_2
    //   4370: isub
    //   4371: iaload
    //   4372: bipush #10
    //   4374: iushr
    //   4375: ixor
    //   4376: aload #19
    //   4378: iload #21
    //   4380: bipush #7
    //   4382: isub
    //   4383: iaload
    //   4384: iadd
    //   4385: aload #19
    //   4387: iload #21
    //   4389: bipush #15
    //   4391: isub
    //   4392: iaload
    //   4393: bipush #7
    //   4395: iushr
    //   4396: aload #19
    //   4398: iload #21
    //   4400: bipush #15
    //   4402: isub
    //   4403: iaload
    //   4404: bipush #25
    //   4406: ishl
    //   4407: ior
    //   4408: aload #19
    //   4410: iload #21
    //   4412: bipush #15
    //   4414: isub
    //   4415: iaload
    //   4416: bipush #18
    //   4418: iushr
    //   4419: aload #19
    //   4421: iload #21
    //   4423: bipush #15
    //   4425: isub
    //   4426: iaload
    //   4427: bipush #14
    //   4429: ishl
    //   4430: ior
    //   4431: ixor
    //   4432: aload #19
    //   4434: iload #21
    //   4436: bipush #15
    //   4438: isub
    //   4439: iaload
    //   4440: iconst_3
    //   4441: iushr
    //   4442: ixor
    //   4443: iadd
    //   4444: aload #19
    //   4446: iload #21
    //   4448: bipush #16
    //   4450: isub
    //   4451: iaload
    //   4452: iadd
    //   4453: iastore
    //   4454: goto -> 4461
    //   4457: invokestatic a : (Ljava/lang/Throwable;)Ljava/lang/Throwable;
    //   4460: athrow
    //   4461: aload #20
    //   4463: bipush #7
    //   4465: iaload
    //   4466: aload #20
    //   4468: iconst_4
    //   4469: iaload
    //   4470: bipush #6
    //   4472: iushr
    //   4473: aload #20
    //   4475: iconst_4
    //   4476: iaload
    //   4477: bipush #26
    //   4479: ishl
    //   4480: ior
    //   4481: aload #20
    //   4483: iconst_4
    //   4484: iaload
    //   4485: bipush #11
    //   4487: iushr
    //   4488: aload #20
    //   4490: iconst_4
    //   4491: iaload
    //   4492: bipush #21
    //   4494: ishl
    //   4495: ior
    //   4496: ixor
    //   4497: aload #20
    //   4499: iconst_4
    //   4500: iaload
    //   4501: bipush #25
    //   4503: iushr
    //   4504: aload #20
    //   4506: iconst_4
    //   4507: iaload
    //   4508: bipush #7
    //   4510: ishl
    //   4511: ior
    //   4512: ixor
    //   4513: iadd
    //   4514: aload #20
    //   4516: bipush #6
    //   4518: iaload
    //   4519: aload #20
    //   4521: iconst_4
    //   4522: iaload
    //   4523: aload #20
    //   4525: iconst_5
    //   4526: iaload
    //   4527: aload #20
    //   4529: bipush #6
    //   4531: iaload
    //   4532: ixor
    //   4533: iand
    //   4534: ixor
    //   4535: iadd
    //   4536: aload #6
    //   4538: iload #21
    //   4540: iaload
    //   4541: iadd
    //   4542: aload #19
    //   4544: iload #21
    //   4546: iaload
    //   4547: iadd
    //   4548: istore #22
    //   4550: aload #20
    //   4552: iconst_0
    //   4553: iaload
    //   4554: iconst_2
    //   4555: iushr
    //   4556: aload #20
    //   4558: iconst_0
    //   4559: iaload
    //   4560: bipush #30
    //   4562: ishl
    //   4563: ior
    //   4564: aload #20
    //   4566: iconst_0
    //   4567: iaload
    //   4568: bipush #13
    //   4570: iushr
    //   4571: aload #20
    //   4573: iconst_0
    //   4574: iaload
    //   4575: bipush #19
    //   4577: ishl
    //   4578: ior
    //   4579: ixor
    //   4580: aload #20
    //   4582: iconst_0
    //   4583: iaload
    //   4584: bipush #22
    //   4586: iushr
    //   4587: aload #20
    //   4589: iconst_0
    //   4590: iaload
    //   4591: bipush #10
    //   4593: ishl
    //   4594: ior
    //   4595: ixor
    //   4596: aload #20
    //   4598: iconst_0
    //   4599: iaload
    //   4600: aload #20
    //   4602: iconst_1
    //   4603: iaload
    //   4604: iand
    //   4605: aload #20
    //   4607: iconst_2
    //   4608: iaload
    //   4609: aload #20
    //   4611: iconst_0
    //   4612: iaload
    //   4613: aload #20
    //   4615: iconst_1
    //   4616: iaload
    //   4617: ior
    //   4618: iand
    //   4619: ior
    //   4620: iadd
    //   4621: istore #23
    //   4623: aload #20
    //   4625: iconst_3
    //   4626: dup2
    //   4627: iaload
    //   4628: iload #22
    //   4630: iadd
    //   4631: iastore
    //   4632: aload #20
    //   4634: bipush #7
    //   4636: iload #22
    //   4638: iload #23
    //   4640: iadd
    //   4641: iastore
    //   4642: aload #20
    //   4644: bipush #7
    //   4646: iaload
    //   4647: istore #22
    //   4649: aload #20
    //   4651: bipush #7
    //   4653: aload #20
    //   4655: bipush #6
    //   4657: iaload
    //   4658: iastore
    //   4659: aload #20
    //   4661: bipush #6
    //   4663: aload #20
    //   4665: iconst_5
    //   4666: iaload
    //   4667: iastore
    //   4668: aload #20
    //   4670: iconst_5
    //   4671: aload #20
    //   4673: iconst_4
    //   4674: iaload
    //   4675: iastore
    //   4676: aload #20
    //   4678: iconst_4
    //   4679: aload #20
    //   4681: iconst_3
    //   4682: iaload
    //   4683: iastore
    //   4684: aload #20
    //   4686: iconst_3
    //   4687: aload #20
    //   4689: iconst_2
    //   4690: iaload
    //   4691: iastore
    //   4692: aload #20
    //   4694: iconst_2
    //   4695: aload #20
    //   4697: iconst_1
    //   4698: iaload
    //   4699: iastore
    //   4700: aload #20
    //   4702: iconst_1
    //   4703: aload #20
    //   4705: iconst_0
    //   4706: iaload
    //   4707: iastore
    //   4708: aload #20
    //   4710: iconst_0
    //   4711: iload #22
    //   4713: iastore
    //   4714: iinc #21, 1
    //   4717: iload_2
    //   4718: ifeq -> 4226
    //   4721: iconst_0
    //   4722: istore #21
    //   4724: iload #21
    //   4726: bipush #8
    //   4728: if_icmpge -> 4751
    //   4731: aload #8
    //   4733: iload #21
    //   4735: dup2
    //   4736: iaload
    //   4737: aload #20
    //   4739: iload #21
    //   4741: iaload
    //   4742: iadd
    //   4743: iastore
    //   4744: iinc #21, 1
    //   4747: iload_2
    //   4748: ifeq -> 4724
    //   4751: iload #13
    //   4753: iload #18
    //   4755: iadd
    //   4756: istore #13
    //   4758: iload #17
    //   4760: iload #18
    //   4762: isub
    //   4763: istore #17
    //   4765: iconst_0
    //   4766: istore #12
    //   4768: iload #17
    //   4770: bipush #64
    //   4772: if_icmplt -> 5382
    //   4775: iconst_0
    //   4776: istore #19
    //   4778: iload #19
    //   4780: bipush #64
    //   4782: if_icmpge -> 4805
    //   4785: aload #10
    //   4787: iload #19
    //   4789: aload #5
    //   4791: iload #13
    //   4793: iload #19
    //   4795: iadd
    //   4796: baload
    //   4797: bastore
    //   4798: iinc #19, 1
    //   4801: iload_2
    //   4802: ifeq -> 4778
    //   4805: bipush #64
    //   4807: newarray int
    //   4809: astore #19
    //   4811: bipush #8
    //   4813: newarray int
    //   4815: astore #20
    //   4817: iconst_0
    //   4818: istore #21
    //   4820: iload #21
    //   4822: bipush #8
    //   4824: if_icmpge -> 4844
    //   4827: aload #20
    //   4829: iload #21
    //   4831: aload #8
    //   4833: iload #21
    //   4835: iaload
    //   4836: iastore
    //   4837: iinc #21, 1
    //   4840: iload_2
    //   4841: ifeq -> 4820
    //   4844: iconst_0
    //   4845: istore #21
    //   4847: iload #21
    //   4849: bipush #64
    //   4851: if_icmpge -> 5342
    //   4854: iload #21
    //   4856: bipush #16
    //   4858: if_icmpge -> 4939
    //   4861: aload #19
    //   4863: iload #21
    //   4865: aload #10
    //   4867: iconst_4
    //   4868: iload #21
    //   4870: imul
    //   4871: baload
    //   4872: sipush #255
    //   4875: iand
    //   4876: bipush #24
    //   4878: ishl
    //   4879: aload #10
    //   4881: iconst_4
    //   4882: iload #21
    //   4884: imul
    //   4885: iconst_1
    //   4886: iadd
    //   4887: baload
    //   4888: sipush #255
    //   4891: iand
    //   4892: bipush #16
    //   4894: ishl
    //   4895: ior
    //   4896: aload #10
    //   4898: iconst_4
    //   4899: iload #21
    //   4901: imul
    //   4902: iconst_2
    //   4903: iadd
    //   4904: baload
    //   4905: sipush #255
    //   4908: iand
    //   4909: bipush #8
    //   4911: ishl
    //   4912: ior
    //   4913: aload #10
    //   4915: iconst_4
    //   4916: iload #21
    //   4918: imul
    //   4919: iconst_3
    //   4920: iadd
    //   4921: baload
    //   4922: sipush #255
    //   4925: iand
    //   4926: ior
    //   4927: iastore
    //   4928: iload_2
    //   4929: ifeq -> 5082
    //   4932: goto -> 4939
    //   4935: invokestatic a : (Ljava/lang/Throwable;)Ljava/lang/Throwable;
    //   4938: athrow
    //   4939: aload #19
    //   4941: iload #21
    //   4943: aload #19
    //   4945: iload #21
    //   4947: iconst_2
    //   4948: isub
    //   4949: iaload
    //   4950: bipush #17
    //   4952: iushr
    //   4953: aload #19
    //   4955: iload #21
    //   4957: iconst_2
    //   4958: isub
    //   4959: iaload
    //   4960: bipush #15
    //   4962: ishl
    //   4963: ior
    //   4964: aload #19
    //   4966: iload #21
    //   4968: iconst_2
    //   4969: isub
    //   4970: iaload
    //   4971: bipush #19
    //   4973: iushr
    //   4974: aload #19
    //   4976: iload #21
    //   4978: iconst_2
    //   4979: isub
    //   4980: iaload
    //   4981: bipush #13
    //   4983: ishl
    //   4984: ior
    //   4985: ixor
    //   4986: aload #19
    //   4988: iload #21
    //   4990: iconst_2
    //   4991: isub
    //   4992: iaload
    //   4993: bipush #10
    //   4995: iushr
    //   4996: ixor
    //   4997: aload #19
    //   4999: iload #21
    //   5001: bipush #7
    //   5003: isub
    //   5004: iaload
    //   5005: iadd
    //   5006: aload #19
    //   5008: iload #21
    //   5010: bipush #15
    //   5012: isub
    //   5013: iaload
    //   5014: bipush #7
    //   5016: iushr
    //   5017: aload #19
    //   5019: iload #21
    //   5021: bipush #15
    //   5023: isub
    //   5024: iaload
    //   5025: bipush #25
    //   5027: ishl
    //   5028: ior
    //   5029: aload #19
    //   5031: iload #21
    //   5033: bipush #15
    //   5035: isub
    //   5036: iaload
    //   5037: bipush #18
    //   5039: iushr
    //   5040: aload #19
    //   5042: iload #21
    //   5044: bipush #15
    //   5046: isub
    //   5047: iaload
    //   5048: bipush #14
    //   5050: ishl
    //   5051: ior
    //   5052: ixor
    //   5053: aload #19
    //   5055: iload #21
    //   5057: bipush #15
    //   5059: isub
    //   5060: iaload
    //   5061: iconst_3
    //   5062: iushr
    //   5063: ixor
    //   5064: iadd
    //   5065: aload #19
    //   5067: iload #21
    //   5069: bipush #16
    //   5071: isub
    //   5072: iaload
    //   5073: iadd
    //   5074: iastore
    //   5075: goto -> 5082
    //   5078: invokestatic a : (Ljava/lang/Throwable;)Ljava/lang/Throwable;
    //   5081: athrow
    //   5082: aload #20
    //   5084: bipush #7
    //   5086: iaload
    //   5087: aload #20
    //   5089: iconst_4
    //   5090: iaload
    //   5091: bipush #6
    //   5093: iushr
    //   5094: aload #20
    //   5096: iconst_4
    //   5097: iaload
    //   5098: bipush #26
    //   5100: ishl
    //   5101: ior
    //   5102: aload #20
    //   5104: iconst_4
    //   5105: iaload
    //   5106: bipush #11
    //   5108: iushr
    //   5109: aload #20
    //   5111: iconst_4
    //   5112: iaload
    //   5113: bipush #21
    //   5115: ishl
    //   5116: ior
    //   5117: ixor
    //   5118: aload #20
    //   5120: iconst_4
    //   5121: iaload
    //   5122: bipush #25
    //   5124: iushr
    //   5125: aload #20
    //   5127: iconst_4
    //   5128: iaload
    //   5129: bipush #7
    //   5131: ishl
    //   5132: ior
    //   5133: ixor
    //   5134: iadd
    //   5135: aload #20
    //   5137: bipush #6
    //   5139: iaload
    //   5140: aload #20
    //   5142: iconst_4
    //   5143: iaload
    //   5144: aload #20
    //   5146: iconst_5
    //   5147: iaload
    //   5148: aload #20
    //   5150: bipush #6
    //   5152: iaload
    //   5153: ixor
    //   5154: iand
    //   5155: ixor
    //   5156: iadd
    //   5157: aload #6
    //   5159: iload #21
    //   5161: iaload
    //   5162: iadd
    //   5163: aload #19
    //   5165: iload #21
    //   5167: iaload
    //   5168: iadd
    //   5169: istore #22
    //   5171: aload #20
    //   5173: iconst_0
    //   5174: iaload
    //   5175: iconst_2
    //   5176: iushr
    //   5177: aload #20
    //   5179: iconst_0
    //   5180: iaload
    //   5181: bipush #30
    //   5183: ishl
    //   5184: ior
    //   5185: aload #20
    //   5187: iconst_0
    //   5188: iaload
    //   5189: bipush #13
    //   5191: iushr
    //   5192: aload #20
    //   5194: iconst_0
    //   5195: iaload
    //   5196: bipush #19
    //   5198: ishl
    //   5199: ior
    //   5200: ixor
    //   5201: aload #20
    //   5203: iconst_0
    //   5204: iaload
    //   5205: bipush #22
    //   5207: iushr
    //   5208: aload #20
    //   5210: iconst_0
    //   5211: iaload
    //   5212: bipush #10
    //   5214: ishl
    //   5215: ior
    //   5216: ixor
    //   5217: aload #20
    //   5219: iconst_0
    //   5220: iaload
    //   5221: aload #20
    //   5223: iconst_1
    //   5224: iaload
    //   5225: iand
    //   5226: aload #20
    //   5228: iconst_2
    //   5229: iaload
    //   5230: aload #20
    //   5232: iconst_0
    //   5233: iaload
    //   5234: aload #20
    //   5236: iconst_1
    //   5237: iaload
    //   5238: ior
    //   5239: iand
    //   5240: ior
    //   5241: iadd
    //   5242: istore #23
    //   5244: aload #20
    //   5246: iconst_3
    //   5247: dup2
    //   5248: iaload
    //   5249: iload #22
    //   5251: iadd
    //   5252: iastore
    //   5253: aload #20
    //   5255: bipush #7
    //   5257: iload #22
    //   5259: iload #23
    //   5261: iadd
    //   5262: iastore
    //   5263: aload #20
    //   5265: bipush #7
    //   5267: iaload
    //   5268: istore #22
    //   5270: aload #20
    //   5272: bipush #7
    //   5274: aload #20
    //   5276: bipush #6
    //   5278: iaload
    //   5279: iastore
    //   5280: aload #20
    //   5282: bipush #6
    //   5284: aload #20
    //   5286: iconst_5
    //   5287: iaload
    //   5288: iastore
    //   5289: aload #20
    //   5291: iconst_5
    //   5292: aload #20
    //   5294: iconst_4
    //   5295: iaload
    //   5296: iastore
    //   5297: aload #20
    //   5299: iconst_4
    //   5300: aload #20
    //   5302: iconst_3
    //   5303: iaload
    //   5304: iastore
    //   5305: aload #20
    //   5307: iconst_3
    //   5308: aload #20
    //   5310: iconst_2
    //   5311: iaload
    //   5312: iastore
    //   5313: aload #20
    //   5315: iconst_2
    //   5316: aload #20
    //   5318: iconst_1
    //   5319: iaload
    //   5320: iastore
    //   5321: aload #20
    //   5323: iconst_1
    //   5324: aload #20
    //   5326: iconst_0
    //   5327: iaload
    //   5328: iastore
    //   5329: aload #20
    //   5331: iconst_0
    //   5332: iload #22
    //   5334: iastore
    //   5335: iinc #21, 1
    //   5338: iload_2
    //   5339: ifeq -> 4847
    //   5342: iconst_0
    //   5343: istore #21
    //   5345: iload #21
    //   5347: bipush #8
    //   5349: if_icmpge -> 5372
    //   5352: aload #8
    //   5354: iload #21
    //   5356: dup2
    //   5357: iaload
    //   5358: aload #20
    //   5360: iload #21
    //   5362: iaload
    //   5363: iadd
    //   5364: iastore
    //   5365: iinc #21, 1
    //   5368: iload_2
    //   5369: ifeq -> 5345
    //   5372: iinc #13, 64
    //   5375: iinc #17, -64
    //   5378: iload_2
    //   5379: ifeq -> 4768
    //   5382: iload #17
    //   5384: ifle -> 5420
    //   5387: iconst_0
    //   5388: istore #19
    //   5390: iload #19
    //   5392: iload #17
    //   5394: if_icmpge -> 5420
    //   5397: aload #9
    //   5399: iload #12
    //   5401: iload #19
    //   5403: iadd
    //   5404: aload #5
    //   5406: iload #13
    //   5408: iload #19
    //   5410: iadd
    //   5411: baload
    //   5412: bastore
    //   5413: iinc #19, 1
    //   5416: iload_2
    //   5417: ifeq -> 5390
    //   5420: bipush #8
    //   5422: newarray byte
    //   5424: astore #19
    //   5426: aload #19
    //   5428: iconst_0
    //   5429: iload #14
    //   5431: bipush #24
    //   5433: iushr
    //   5434: i2b
    //   5435: bastore
    //   5436: aload #19
    //   5438: iconst_1
    //   5439: iload #14
    //   5441: bipush #16
    //   5443: iushr
    //   5444: i2b
    //   5445: bastore
    //   5446: aload #19
    //   5448: iconst_2
    //   5449: iload #14
    //   5451: bipush #8
    //   5453: iushr
    //   5454: i2b
    //   5455: bastore
    //   5456: aload #19
    //   5458: iconst_3
    //   5459: iload #14
    //   5461: i2b
    //   5462: bastore
    //   5463: aload #19
    //   5465: iconst_4
    //   5466: iload #15
    //   5468: bipush #24
    //   5470: iushr
    //   5471: i2b
    //   5472: bastore
    //   5473: aload #19
    //   5475: iconst_5
    //   5476: iload #15
    //   5478: bipush #16
    //   5480: iushr
    //   5481: i2b
    //   5482: bastore
    //   5483: aload #19
    //   5485: bipush #6
    //   5487: iload #15
    //   5489: bipush #8
    //   5491: iushr
    //   5492: i2b
    //   5493: bastore
    //   5494: aload #19
    //   5496: bipush #7
    //   5498: iload #15
    //   5500: i2b
    //   5501: bastore
    //   5502: bipush #8
    //   5504: istore #11
    //   5506: aload #7
    //   5508: iconst_0
    //   5509: iaload
    //   5510: bipush #63
    //   5512: iand
    //   5513: istore #12
    //   5515: bipush #64
    //   5517: iload #12
    //   5519: isub
    //   5520: istore #18
    //   5522: aload #7
    //   5524: iconst_0
    //   5525: dup2
    //   5526: iaload
    //   5527: iload #11
    //   5529: iadd
    //   5530: iastore
    //   5531: aload #7
    //   5533: iconst_0
    //   5534: dup2
    //   5535: iaload
    //   5536: iconst_m1
    //   5537: iand
    //   5538: iastore
    //   5539: aload #7
    //   5541: iconst_0
    //   5542: iaload
    //   5543: iload #11
    //   5545: if_icmpge -> 5563
    //   5548: aload #7
    //   5550: iconst_1
    //   5551: dup2
    //   5552: iaload
    //   5553: iconst_1
    //   5554: iadd
    //   5555: iastore
    //   5556: goto -> 5563
    //   5559: invokestatic a : (Ljava/lang/Throwable;)Ljava/lang/Throwable;
    //   5562: athrow
    //   5563: iload #12
    //   5565: ifle -> 6179
    //   5568: iload #11
    //   5570: iload #18
    //   5572: if_icmplt -> 6179
    //   5575: goto -> 5582
    //   5578: invokestatic a : (Ljava/lang/Throwable;)Ljava/lang/Throwable;
    //   5581: athrow
    //   5582: iconst_0
    //   5583: istore #20
    //   5585: iload #20
    //   5587: iload #18
    //   5589: if_icmpge -> 5612
    //   5592: aload #9
    //   5594: iload #12
    //   5596: iload #20
    //   5598: iadd
    //   5599: aload #19
    //   5601: iload #20
    //   5603: baload
    //   5604: bastore
    //   5605: iinc #20, 1
    //   5608: iload_2
    //   5609: ifeq -> 5585
    //   5612: bipush #64
    //   5614: newarray int
    //   5616: astore #20
    //   5618: bipush #8
    //   5620: newarray int
    //   5622: astore #21
    //   5624: iconst_0
    //   5625: istore #22
    //   5627: iload #22
    //   5629: bipush #8
    //   5631: if_icmpge -> 5651
    //   5634: aload #21
    //   5636: iload #22
    //   5638: aload #8
    //   5640: iload #22
    //   5642: iaload
    //   5643: iastore
    //   5644: iinc #22, 1
    //   5647: iload_2
    //   5648: ifeq -> 5627
    //   5651: iconst_0
    //   5652: istore #22
    //   5654: iload #22
    //   5656: bipush #64
    //   5658: if_icmpge -> 6149
    //   5661: iload #22
    //   5663: bipush #16
    //   5665: if_icmpge -> 5746
    //   5668: aload #20
    //   5670: iload #22
    //   5672: aload #9
    //   5674: iconst_4
    //   5675: iload #22
    //   5677: imul
    //   5678: baload
    //   5679: sipush #255
    //   5682: iand
    //   5683: bipush #24
    //   5685: ishl
    //   5686: aload #9
    //   5688: iconst_4
    //   5689: iload #22
    //   5691: imul
    //   5692: iconst_1
    //   5693: iadd
    //   5694: baload
    //   5695: sipush #255
    //   5698: iand
    //   5699: bipush #16
    //   5701: ishl
    //   5702: ior
    //   5703: aload #9
    //   5705: iconst_4
    //   5706: iload #22
    //   5708: imul
    //   5709: iconst_2
    //   5710: iadd
    //   5711: baload
    //   5712: sipush #255
    //   5715: iand
    //   5716: bipush #8
    //   5718: ishl
    //   5719: ior
    //   5720: aload #9
    //   5722: iconst_4
    //   5723: iload #22
    //   5725: imul
    //   5726: iconst_3
    //   5727: iadd
    //   5728: baload
    //   5729: sipush #255
    //   5732: iand
    //   5733: ior
    //   5734: iastore
    //   5735: iload_2
    //   5736: ifeq -> 5889
    //   5739: goto -> 5746
    //   5742: invokestatic a : (Ljava/lang/Throwable;)Ljava/lang/Throwable;
    //   5745: athrow
    //   5746: aload #20
    //   5748: iload #22
    //   5750: aload #20
    //   5752: iload #22
    //   5754: iconst_2
    //   5755: isub
    //   5756: iaload
    //   5757: bipush #17
    //   5759: iushr
    //   5760: aload #20
    //   5762: iload #22
    //   5764: iconst_2
    //   5765: isub
    //   5766: iaload
    //   5767: bipush #15
    //   5769: ishl
    //   5770: ior
    //   5771: aload #20
    //   5773: iload #22
    //   5775: iconst_2
    //   5776: isub
    //   5777: iaload
    //   5778: bipush #19
    //   5780: iushr
    //   5781: aload #20
    //   5783: iload #22
    //   5785: iconst_2
    //   5786: isub
    //   5787: iaload
    //   5788: bipush #13
    //   5790: ishl
    //   5791: ior
    //   5792: ixor
    //   5793: aload #20
    //   5795: iload #22
    //   5797: iconst_2
    //   5798: isub
    //   5799: iaload
    //   5800: bipush #10
    //   5802: iushr
    //   5803: ixor
    //   5804: aload #20
    //   5806: iload #22
    //   5808: bipush #7
    //   5810: isub
    //   5811: iaload
    //   5812: iadd
    //   5813: aload #20
    //   5815: iload #22
    //   5817: bipush #15
    //   5819: isub
    //   5820: iaload
    //   5821: bipush #7
    //   5823: iushr
    //   5824: aload #20
    //   5826: iload #22
    //   5828: bipush #15
    //   5830: isub
    //   5831: iaload
    //   5832: bipush #25
    //   5834: ishl
    //   5835: ior
    //   5836: aload #20
    //   5838: iload #22
    //   5840: bipush #15
    //   5842: isub
    //   5843: iaload
    //   5844: bipush #18
    //   5846: iushr
    //   5847: aload #20
    //   5849: iload #22
    //   5851: bipush #15
    //   5853: isub
    //   5854: iaload
    //   5855: bipush #14
    //   5857: ishl
    //   5858: ior
    //   5859: ixor
    //   5860: aload #20
    //   5862: iload #22
    //   5864: bipush #15
    //   5866: isub
    //   5867: iaload
    //   5868: iconst_3
    //   5869: iushr
    //   5870: ixor
    //   5871: iadd
    //   5872: aload #20
    //   5874: iload #22
    //   5876: bipush #16
    //   5878: isub
    //   5879: iaload
    //   5880: iadd
    //   5881: iastore
    //   5882: goto -> 5889
    //   5885: invokestatic a : (Ljava/lang/Throwable;)Ljava/lang/Throwable;
    //   5888: athrow
    //   5889: aload #21
    //   5891: bipush #7
    //   5893: iaload
    //   5894: aload #21
    //   5896: iconst_4
    //   5897: iaload
    //   5898: bipush #6
    //   5900: iushr
    //   5901: aload #21
    //   5903: iconst_4
    //   5904: iaload
    //   5905: bipush #26
    //   5907: ishl
    //   5908: ior
    //   5909: aload #21
    //   5911: iconst_4
    //   5912: iaload
    //   5913: bipush #11
    //   5915: iushr
    //   5916: aload #21
    //   5918: iconst_4
    //   5919: iaload
    //   5920: bipush #21
    //   5922: ishl
    //   5923: ior
    //   5924: ixor
    //   5925: aload #21
    //   5927: iconst_4
    //   5928: iaload
    //   5929: bipush #25
    //   5931: iushr
    //   5932: aload #21
    //   5934: iconst_4
    //   5935: iaload
    //   5936: bipush #7
    //   5938: ishl
    //   5939: ior
    //   5940: ixor
    //   5941: iadd
    //   5942: aload #21
    //   5944: bipush #6
    //   5946: iaload
    //   5947: aload #21
    //   5949: iconst_4
    //   5950: iaload
    //   5951: aload #21
    //   5953: iconst_5
    //   5954: iaload
    //   5955: aload #21
    //   5957: bipush #6
    //   5959: iaload
    //   5960: ixor
    //   5961: iand
    //   5962: ixor
    //   5963: iadd
    //   5964: aload #6
    //   5966: iload #22
    //   5968: iaload
    //   5969: iadd
    //   5970: aload #20
    //   5972: iload #22
    //   5974: iaload
    //   5975: iadd
    //   5976: istore #23
    //   5978: aload #21
    //   5980: iconst_0
    //   5981: iaload
    //   5982: iconst_2
    //   5983: iushr
    //   5984: aload #21
    //   5986: iconst_0
    //   5987: iaload
    //   5988: bipush #30
    //   5990: ishl
    //   5991: ior
    //   5992: aload #21
    //   5994: iconst_0
    //   5995: iaload
    //   5996: bipush #13
    //   5998: iushr
    //   5999: aload #21
    //   6001: iconst_0
    //   6002: iaload
    //   6003: bipush #19
    //   6005: ishl
    //   6006: ior
    //   6007: ixor
    //   6008: aload #21
    //   6010: iconst_0
    //   6011: iaload
    //   6012: bipush #22
    //   6014: iushr
    //   6015: aload #21
    //   6017: iconst_0
    //   6018: iaload
    //   6019: bipush #10
    //   6021: ishl
    //   6022: ior
    //   6023: ixor
    //   6024: aload #21
    //   6026: iconst_0
    //   6027: iaload
    //   6028: aload #21
    //   6030: iconst_1
    //   6031: iaload
    //   6032: iand
    //   6033: aload #21
    //   6035: iconst_2
    //   6036: iaload
    //   6037: aload #21
    //   6039: iconst_0
    //   6040: iaload
    //   6041: aload #21
    //   6043: iconst_1
    //   6044: iaload
    //   6045: ior
    //   6046: iand
    //   6047: ior
    //   6048: iadd
    //   6049: istore #24
    //   6051: aload #21
    //   6053: iconst_3
    //   6054: dup2
    //   6055: iaload
    //   6056: iload #23
    //   6058: iadd
    //   6059: iastore
    //   6060: aload #21
    //   6062: bipush #7
    //   6064: iload #23
    //   6066: iload #24
    //   6068: iadd
    //   6069: iastore
    //   6070: aload #21
    //   6072: bipush #7
    //   6074: iaload
    //   6075: istore #23
    //   6077: aload #21
    //   6079: bipush #7
    //   6081: aload #21
    //   6083: bipush #6
    //   6085: iaload
    //   6086: iastore
    //   6087: aload #21
    //   6089: bipush #6
    //   6091: aload #21
    //   6093: iconst_5
    //   6094: iaload
    //   6095: iastore
    //   6096: aload #21
    //   6098: iconst_5
    //   6099: aload #21
    //   6101: iconst_4
    //   6102: iaload
    //   6103: iastore
    //   6104: aload #21
    //   6106: iconst_4
    //   6107: aload #21
    //   6109: iconst_3
    //   6110: iaload
    //   6111: iastore
    //   6112: aload #21
    //   6114: iconst_3
    //   6115: aload #21
    //   6117: iconst_2
    //   6118: iaload
    //   6119: iastore
    //   6120: aload #21
    //   6122: iconst_2
    //   6123: aload #21
    //   6125: iconst_1
    //   6126: iaload
    //   6127: iastore
    //   6128: aload #21
    //   6130: iconst_1
    //   6131: aload #21
    //   6133: iconst_0
    //   6134: iaload
    //   6135: iastore
    //   6136: aload #21
    //   6138: iconst_0
    //   6139: iload #23
    //   6141: iastore
    //   6142: iinc #22, 1
    //   6145: iload_2
    //   6146: ifeq -> 5654
    //   6149: iconst_0
    //   6150: istore #22
    //   6152: iload #22
    //   6154: bipush #8
    //   6156: if_icmpge -> 6179
    //   6159: aload #8
    //   6161: iload #22
    //   6163: dup2
    //   6164: iaload
    //   6165: aload #21
    //   6167: iload #22
    //   6169: iaload
    //   6170: iadd
    //   6171: iastore
    //   6172: iinc #22, 1
    //   6175: iload_2
    //   6176: ifeq -> 6152
    //   6179: bipush #32
    //   6181: newarray byte
    //   6183: astore #4
    //   6185: aload #4
    //   6187: iconst_0
    //   6188: aload #8
    //   6190: iconst_0
    //   6191: iaload
    //   6192: bipush #24
    //   6194: iushr
    //   6195: i2b
    //   6196: bastore
    //   6197: aload #4
    //   6199: iconst_1
    //   6200: aload #8
    //   6202: iconst_0
    //   6203: iaload
    //   6204: bipush #16
    //   6206: iushr
    //   6207: i2b
    //   6208: bastore
    //   6209: aload #4
    //   6211: iconst_2
    //   6212: aload #8
    //   6214: iconst_0
    //   6215: iaload
    //   6216: bipush #8
    //   6218: iushr
    //   6219: i2b
    //   6220: bastore
    //   6221: aload #4
    //   6223: iconst_3
    //   6224: aload #8
    //   6226: iconst_0
    //   6227: iaload
    //   6228: i2b
    //   6229: bastore
    //   6230: aload #4
    //   6232: iconst_4
    //   6233: aload #8
    //   6235: iconst_1
    //   6236: iaload
    //   6237: bipush #24
    //   6239: iushr
    //   6240: i2b
    //   6241: bastore
    //   6242: aload #4
    //   6244: iconst_5
    //   6245: aload #8
    //   6247: iconst_1
    //   6248: iaload
    //   6249: bipush #16
    //   6251: iushr
    //   6252: i2b
    //   6253: bastore
    //   6254: aload #4
    //   6256: bipush #6
    //   6258: aload #8
    //   6260: iconst_1
    //   6261: iaload
    //   6262: bipush #8
    //   6264: iushr
    //   6265: i2b
    //   6266: bastore
    //   6267: aload #4
    //   6269: bipush #7
    //   6271: aload #8
    //   6273: iconst_1
    //   6274: iaload
    //   6275: i2b
    //   6276: bastore
    //   6277: aload #4
    //   6279: bipush #8
    //   6281: aload #8
    //   6283: iconst_2
    //   6284: iaload
    //   6285: bipush #24
    //   6287: iushr
    //   6288: i2b
    //   6289: bastore
    //   6290: aload #4
    //   6292: bipush #9
    //   6294: aload #8
    //   6296: iconst_2
    //   6297: iaload
    //   6298: bipush #16
    //   6300: iushr
    //   6301: i2b
    //   6302: bastore
    //   6303: aload #4
    //   6305: bipush #10
    //   6307: aload #8
    //   6309: iconst_2
    //   6310: iaload
    //   6311: bipush #8
    //   6313: iushr
    //   6314: i2b
    //   6315: bastore
    //   6316: aload #4
    //   6318: bipush #11
    //   6320: aload #8
    //   6322: iconst_2
    //   6323: iaload
    //   6324: i2b
    //   6325: bastore
    //   6326: aload #4
    //   6328: bipush #12
    //   6330: aload #8
    //   6332: iconst_3
    //   6333: iaload
    //   6334: bipush #24
    //   6336: iushr
    //   6337: i2b
    //   6338: bastore
    //   6339: aload #4
    //   6341: bipush #13
    //   6343: aload #8
    //   6345: iconst_3
    //   6346: iaload
    //   6347: bipush #16
    //   6349: iushr
    //   6350: i2b
    //   6351: bastore
    //   6352: aload #4
    //   6354: bipush #14
    //   6356: aload #8
    //   6358: iconst_3
    //   6359: iaload
    //   6360: bipush #8
    //   6362: iushr
    //   6363: i2b
    //   6364: bastore
    //   6365: aload #4
    //   6367: bipush #15
    //   6369: aload #8
    //   6371: iconst_3
    //   6372: iaload
    //   6373: i2b
    //   6374: bastore
    //   6375: aload #4
    //   6377: bipush #16
    //   6379: aload #8
    //   6381: iconst_4
    //   6382: iaload
    //   6383: bipush #24
    //   6385: iushr
    //   6386: i2b
    //   6387: bastore
    //   6388: aload #4
    //   6390: bipush #17
    //   6392: aload #8
    //   6394: iconst_4
    //   6395: iaload
    //   6396: bipush #16
    //   6398: iushr
    //   6399: i2b
    //   6400: bastore
    //   6401: aload #4
    //   6403: bipush #18
    //   6405: aload #8
    //   6407: iconst_4
    //   6408: iaload
    //   6409: bipush #8
    //   6411: iushr
    //   6412: i2b
    //   6413: bastore
    //   6414: aload #4
    //   6416: bipush #19
    //   6418: aload #8
    //   6420: iconst_4
    //   6421: iaload
    //   6422: i2b
    //   6423: bastore
    //   6424: aload #4
    //   6426: bipush #20
    //   6428: aload #8
    //   6430: iconst_5
    //   6431: iaload
    //   6432: bipush #24
    //   6434: iushr
    //   6435: i2b
    //   6436: bastore
    //   6437: aload #4
    //   6439: bipush #21
    //   6441: aload #8
    //   6443: iconst_5
    //   6444: iaload
    //   6445: bipush #16
    //   6447: iushr
    //   6448: i2b
    //   6449: bastore
    //   6450: aload #4
    //   6452: bipush #22
    //   6454: aload #8
    //   6456: iconst_5
    //   6457: iaload
    //   6458: bipush #8
    //   6460: iushr
    //   6461: i2b
    //   6462: bastore
    //   6463: aload #4
    //   6465: bipush #23
    //   6467: aload #8
    //   6469: iconst_5
    //   6470: iaload
    //   6471: i2b
    //   6472: bastore
    //   6473: aload #4
    //   6475: bipush #24
    //   6477: aload #8
    //   6479: bipush #6
    //   6481: iaload
    //   6482: bipush #24
    //   6484: iushr
    //   6485: i2b
    //   6486: bastore
    //   6487: aload #4
    //   6489: bipush #25
    //   6491: aload #8
    //   6493: bipush #6
    //   6495: iaload
    //   6496: bipush #16
    //   6498: iushr
    //   6499: i2b
    //   6500: bastore
    //   6501: aload #4
    //   6503: bipush #26
    //   6505: aload #8
    //   6507: bipush #6
    //   6509: iaload
    //   6510: bipush #8
    //   6512: iushr
    //   6513: i2b
    //   6514: bastore
    //   6515: aload #4
    //   6517: bipush #27
    //   6519: aload #8
    //   6521: bipush #6
    //   6523: iaload
    //   6524: i2b
    //   6525: bastore
    //   6526: aload #4
    //   6528: bipush #28
    //   6530: aload #8
    //   6532: bipush #7
    //   6534: iaload
    //   6535: bipush #24
    //   6537: iushr
    //   6538: i2b
    //   6539: bastore
    //   6540: aload #4
    //   6542: bipush #29
    //   6544: aload #8
    //   6546: bipush #7
    //   6548: iaload
    //   6549: bipush #16
    //   6551: iushr
    //   6552: i2b
    //   6553: bastore
    //   6554: aload #4
    //   6556: bipush #30
    //   6558: aload #8
    //   6560: bipush #7
    //   6562: iaload
    //   6563: bipush #8
    //   6565: iushr
    //   6566: i2b
    //   6567: bastore
    //   6568: aload #4
    //   6570: bipush #31
    //   6572: aload #8
    //   6574: bipush #7
    //   6576: iaload
    //   6577: i2b
    //   6578: bastore
    //   6579: new java/math/BigInteger
    //   6582: dup
    //   6583: aload #4
    //   6585: invokespecial <init> : ([B)V
    //   6588: invokevirtual abs : ()Ljava/math/BigInteger;
    //   6591: putstatic burp/Ze25.ZW : Ljava/lang/Object;
    //   6594: new java/lang/StringBuilder
    //   6597: dup
    //   6598: invokespecial <init> : ()V
    //   6601: astore_3
    //   6602: iconst_0
    //   6603: istore #4
    //   6605: iload #4
    //   6607: bipush #32
    //   6609: if_icmpge -> 7943
    //   6612: iload #4
    //   6614: tableswitch default -> 7936, 0 -> 6756, 1 -> 6793, 2 -> 6830, 3 -> 6867, 4 -> 6904, 5 -> 6941, 6 -> 6978, 7 -> 7015, 8 -> 7052, 9 -> 7089, 10 -> 7126, 11 -> 7163, 12 -> 7200, 13 -> 7237, 14 -> 7274, 15 -> 7311, 16 -> 7348, 17 -> 7385, 18 -> 7422, 19 -> 7459, 20 -> 7496, 21 -> 7533, 22 -> 7570, 23 -> 7607, 24 -> 7644, 25 -> 7681, 26 -> 7718, 27 -> 7755, 28 -> 7792, 29 -> 7829, 30 -> 7866, 31 -> 7903
    //   6756: aload_3
    //   6757: getstatic burp/Zegj.ZS : Ljava/lang/String;
    //   6760: getstatic burp/Zt85.Zl : Ljava/lang/Object;
    //   6763: checkcast java/math/BigInteger
    //   6766: invokevirtual intValue : ()I
    //   6769: bipush #32
    //   6771: irem
    //   6772: invokestatic abs : (I)I
    //   6775: invokevirtual charAt : (I)C
    //   6778: invokevirtual append : (C)Ljava/lang/StringBuilder;
    //   6781: pop
    //   6782: iload_2
    //   6783: ifeq -> 7936
    //   6786: goto -> 6793
    //   6789: invokestatic a : (Ljava/lang/Throwable;)Ljava/lang/Throwable;
    //   6792: athrow
    //   6793: aload_3
    //   6794: getstatic burp/Zl7x.Zo : Ljava/lang/String;
    //   6797: getstatic burp/Zrkw.ZV : Ljava/lang/Object;
    //   6800: checkcast java/math/BigInteger
    //   6803: invokevirtual intValue : ()I
    //   6806: bipush #32
    //   6808: irem
    //   6809: invokestatic abs : (I)I
    //   6812: invokevirtual charAt : (I)C
    //   6815: invokevirtual append : (C)Ljava/lang/StringBuilder;
    //   6818: pop
    //   6819: iload_2
    //   6820: ifeq -> 7936
    //   6823: goto -> 6830
    //   6826: invokestatic a : (Ljava/lang/Throwable;)Ljava/lang/Throwable;
    //   6829: athrow
    //   6830: aload_3
    //   6831: getstatic burp/Zeub.ZT : Ljava/lang/String;
    //   6834: getstatic burp/Zes.Zx : Ljava/lang/Object;
    //   6837: checkcast java/math/BigInteger
    //   6840: invokevirtual intValue : ()I
    //   6843: bipush #32
    //   6845: irem
    //   6846: invokestatic abs : (I)I
    //   6849: invokevirtual charAt : (I)C
    //   6852: invokevirtual append : (C)Ljava/lang/StringBuilder;
    //   6855: pop
    //   6856: iload_2
    //   6857: ifeq -> 7936
    //   6860: goto -> 6867
    //   6863: invokestatic a : (Ljava/lang/Throwable;)Ljava/lang/Throwable;
    //   6866: athrow
    //   6867: aload_3
    //   6868: getstatic burp/Zsfj.Zg : Ljava/lang/String;
    //   6871: getstatic burp/Zr6c.ZG : Ljava/lang/Object;
    //   6874: checkcast java/math/BigInteger
    //   6877: invokevirtual intValue : ()I
    //   6880: bipush #32
    //   6882: irem
    //   6883: invokestatic abs : (I)I
    //   6886: invokevirtual charAt : (I)C
    //   6889: invokevirtual append : (C)Ljava/lang/StringBuilder;
    //   6892: pop
    //   6893: iload_2
    //   6894: ifeq -> 7936
    //   6897: goto -> 6904
    //   6900: invokestatic a : (Ljava/lang/Throwable;)Ljava/lang/Throwable;
    //   6903: athrow
    //   6904: aload_3
    //   6905: getstatic burp/Zly9.ZS : Ljava/lang/String;
    //   6908: getstatic burp/Zzmc.Zg : Ljava/lang/Object;
    //   6911: checkcast java/math/BigInteger
    //   6914: invokevirtual intValue : ()I
    //   6917: bipush #32
    //   6919: irem
    //   6920: invokestatic abs : (I)I
    //   6923: invokevirtual charAt : (I)C
    //   6926: invokevirtual append : (C)Ljava/lang/StringBuilder;
    //   6929: pop
    //   6930: iload_2
    //   6931: ifeq -> 7936
    //   6934: goto -> 6941
    //   6937: invokestatic a : (Ljava/lang/Throwable;)Ljava/lang/Throwable;
    //   6940: athrow
    //   6941: aload_3
    //   6942: getstatic burp/Ztq2.Zt : Ljava/lang/String;
    //   6945: getstatic burp/Zeub.ZD : Ljava/lang/Object;
    //   6948: checkcast java/math/BigInteger
    //   6951: invokevirtual intValue : ()I
    //   6954: bipush #32
    //   6956: irem
    //   6957: invokestatic abs : (I)I
    //   6960: invokevirtual charAt : (I)C
    //   6963: invokevirtual append : (C)Ljava/lang/StringBuilder;
    //   6966: pop
    //   6967: iload_2
    //   6968: ifeq -> 7936
    //   6971: goto -> 6978
    //   6974: invokestatic a : (Ljava/lang/Throwable;)Ljava/lang/Throwable;
    //   6977: athrow
    //   6978: aload_3
    //   6979: getstatic burp/Zssc.ZR : Ljava/lang/String;
    //   6982: getstatic burp/Zm83.Zl : Ljava/lang/Object;
    //   6985: checkcast java/math/BigInteger
    //   6988: invokevirtual intValue : ()I
    //   6991: bipush #32
    //   6993: irem
    //   6994: invokestatic abs : (I)I
    //   6997: invokevirtual charAt : (I)C
    //   7000: invokevirtual append : (C)Ljava/lang/StringBuilder;
    //   7003: pop
    //   7004: iload_2
    //   7005: ifeq -> 7936
    //   7008: goto -> 7015
    //   7011: invokestatic a : (Ljava/lang/Throwable;)Ljava/lang/Throwable;
    //   7014: athrow
    //   7015: aload_3
    //   7016: getstatic burp/Zgeq.ZF : Ljava/lang/String;
    //   7019: getstatic burp/Zzts.Zp : Ljava/lang/Object;
    //   7022: checkcast java/math/BigInteger
    //   7025: invokevirtual intValue : ()I
    //   7028: bipush #32
    //   7030: irem
    //   7031: invokestatic abs : (I)I
    //   7034: invokevirtual charAt : (I)C
    //   7037: invokevirtual append : (C)Ljava/lang/StringBuilder;
    //   7040: pop
    //   7041: iload_2
    //   7042: ifeq -> 7936
    //   7045: goto -> 7052
    //   7048: invokestatic a : (Ljava/lang/Throwable;)Ljava/lang/Throwable;
    //   7051: athrow
    //   7052: aload_3
    //   7053: getstatic burp/Zz0f.ZW : Ljava/lang/String;
    //   7056: getstatic burp/Ze6w.Ze : Ljava/lang/Object;
    //   7059: checkcast java/math/BigInteger
    //   7062: invokevirtual intValue : ()I
    //   7065: bipush #32
    //   7067: irem
    //   7068: invokestatic abs : (I)I
    //   7071: invokevirtual charAt : (I)C
    //   7074: invokevirtual append : (C)Ljava/lang/StringBuilder;
    //   7077: pop
    //   7078: iload_2
    //   7079: ifeq -> 7936
    //   7082: goto -> 7089
    //   7085: invokestatic a : (Ljava/lang/Throwable;)Ljava/lang/Throwable;
    //   7088: athrow
    //   7089: aload_3
    //   7090: getstatic burp/Zb2u.ZM : Ljava/lang/String;
    //   7093: getstatic burp/Zrqe.ZX : Ljava/lang/Object;
    //   7096: checkcast java/math/BigInteger
    //   7099: invokevirtual intValue : ()I
    //   7102: bipush #32
    //   7104: irem
    //   7105: invokestatic abs : (I)I
    //   7108: invokevirtual charAt : (I)C
    //   7111: invokevirtual append : (C)Ljava/lang/StringBuilder;
    //   7114: pop
    //   7115: iload_2
    //   7116: ifeq -> 7936
    //   7119: goto -> 7126
    //   7122: invokestatic a : (Ljava/lang/Throwable;)Ljava/lang/Throwable;
    //   7125: athrow
    //   7126: aload_3
    //   7127: getstatic burp/Zrjq.Zx : Ljava/lang/String;
    //   7130: getstatic burp/Zgk9.ZD : Ljava/lang/Object;
    //   7133: checkcast java/math/BigInteger
    //   7136: invokevirtual intValue : ()I
    //   7139: bipush #32
    //   7141: irem
    //   7142: invokestatic abs : (I)I
    //   7145: invokevirtual charAt : (I)C
    //   7148: invokevirtual append : (C)Ljava/lang/StringBuilder;
    //   7151: pop
    //   7152: iload_2
    //   7153: ifeq -> 7936
    //   7156: goto -> 7163
    //   7159: invokestatic a : (Ljava/lang/Throwable;)Ljava/lang/Throwable;
    //   7162: athrow
    //   7163: aload_3
    //   7164: getstatic burp/Zx4u.ZL : Ljava/lang/String;
    //   7167: getstatic burp/Zoe.ZG : Ljava/lang/Object;
    //   7170: checkcast java/math/BigInteger
    //   7173: invokevirtual intValue : ()I
    //   7176: bipush #32
    //   7178: irem
    //   7179: invokestatic abs : (I)I
    //   7182: invokevirtual charAt : (I)C
    //   7185: invokevirtual append : (C)Ljava/lang/StringBuilder;
    //   7188: pop
    //   7189: iload_2
    //   7190: ifeq -> 7936
    //   7193: goto -> 7200
    //   7196: invokestatic a : (Ljava/lang/Throwable;)Ljava/lang/Throwable;
    //   7199: athrow
    //   7200: aload_3
    //   7201: getstatic burp/Zxp1.Zg : Ljava/lang/String;
    //   7204: getstatic burp/Zkeb.ZH : Ljava/lang/Object;
    //   7207: checkcast java/math/BigInteger
    //   7210: invokevirtual intValue : ()I
    //   7213: bipush #32
    //   7215: irem
    //   7216: invokestatic abs : (I)I
    //   7219: invokevirtual charAt : (I)C
    //   7222: invokevirtual append : (C)Ljava/lang/StringBuilder;
    //   7225: pop
    //   7226: iload_2
    //   7227: ifeq -> 7936
    //   7230: goto -> 7237
    //   7233: invokestatic a : (Ljava/lang/Throwable;)Ljava/lang/Throwable;
    //   7236: athrow
    //   7237: aload_3
    //   7238: getstatic burp/Zttd.Ze : Ljava/lang/String;
    //   7241: getstatic burp/Ztwp.Ze : Ljava/lang/Object;
    //   7244: checkcast java/math/BigInteger
    //   7247: invokevirtual intValue : ()I
    //   7250: bipush #32
    //   7252: irem
    //   7253: invokestatic abs : (I)I
    //   7256: invokevirtual charAt : (I)C
    //   7259: invokevirtual append : (C)Ljava/lang/StringBuilder;
    //   7262: pop
    //   7263: iload_2
    //   7264: ifeq -> 7936
    //   7267: goto -> 7274
    //   7270: invokestatic a : (Ljava/lang/Throwable;)Ljava/lang/Throwable;
    //   7273: athrow
    //   7274: aload_3
    //   7275: getstatic burp/Zld5.ZO : Ljava/lang/String;
    //   7278: getstatic burp/Zea9.Zt : Ljava/lang/Object;
    //   7281: checkcast java/math/BigInteger
    //   7284: invokevirtual intValue : ()I
    //   7287: bipush #32
    //   7289: irem
    //   7290: invokestatic abs : (I)I
    //   7293: invokevirtual charAt : (I)C
    //   7296: invokevirtual append : (C)Ljava/lang/StringBuilder;
    //   7299: pop
    //   7300: iload_2
    //   7301: ifeq -> 7936
    //   7304: goto -> 7311
    //   7307: invokestatic a : (Ljava/lang/Throwable;)Ljava/lang/Throwable;
    //   7310: athrow
    //   7311: aload_3
    //   7312: getstatic burp/Zv8l.Zo : Ljava/lang/String;
    //   7315: getstatic burp/Zbss.Zh : Ljava/lang/Object;
    //   7318: checkcast java/math/BigInteger
    //   7321: invokevirtual intValue : ()I
    //   7324: bipush #32
    //   7326: irem
    //   7327: invokestatic abs : (I)I
    //   7330: invokevirtual charAt : (I)C
    //   7333: invokevirtual append : (C)Ljava/lang/StringBuilder;
    //   7336: pop
    //   7337: iload_2
    //   7338: ifeq -> 7936
    //   7341: goto -> 7348
    //   7344: invokestatic a : (Ljava/lang/Throwable;)Ljava/lang/Throwable;
    //   7347: athrow
    //   7348: aload_3
    //   7349: getstatic burp/Zepy.Zg : Ljava/lang/String;
    //   7352: getstatic burp/Zst7.ZI : Ljava/lang/Object;
    //   7355: checkcast java/math/BigInteger
    //   7358: invokevirtual intValue : ()I
    //   7361: bipush #32
    //   7363: irem
    //   7364: invokestatic abs : (I)I
    //   7367: invokevirtual charAt : (I)C
    //   7370: invokevirtual append : (C)Ljava/lang/StringBuilder;
    //   7373: pop
    //   7374: iload_2
    //   7375: ifeq -> 7936
    //   7378: goto -> 7385
    //   7381: invokestatic a : (Ljava/lang/Throwable;)Ljava/lang/Throwable;
    //   7384: athrow
    //   7385: aload_3
    //   7386: getstatic burp/Zej8.ZP : Ljava/lang/String;
    //   7389: getstatic burp/Zg7u.Zh : Ljava/lang/Object;
    //   7392: checkcast java/math/BigInteger
    //   7395: invokevirtual intValue : ()I
    //   7398: bipush #32
    //   7400: irem
    //   7401: invokestatic abs : (I)I
    //   7404: invokevirtual charAt : (I)C
    //   7407: invokevirtual append : (C)Ljava/lang/StringBuilder;
    //   7410: pop
    //   7411: iload_2
    //   7412: ifeq -> 7936
    //   7415: goto -> 7422
    //   7418: invokestatic a : (Ljava/lang/Throwable;)Ljava/lang/Throwable;
    //   7421: athrow
    //   7422: aload_3
    //   7423: getstatic burp/Zrov.ZU : Ljava/lang/String;
    //   7426: getstatic burp/Zxdp.ZW : Ljava/lang/Object;
    //   7429: checkcast java/math/BigInteger
    //   7432: invokevirtual intValue : ()I
    //   7435: bipush #32
    //   7437: irem
    //   7438: invokestatic abs : (I)I
    //   7441: invokevirtual charAt : (I)C
    //   7444: invokevirtual append : (C)Ljava/lang/StringBuilder;
    //   7447: pop
    //   7448: iload_2
    //   7449: ifeq -> 7936
    //   7452: goto -> 7459
    //   7455: invokestatic a : (Ljava/lang/Throwable;)Ljava/lang/Throwable;
    //   7458: athrow
    //   7459: aload_3
    //   7460: getstatic burp/Zl7x.Zo : Ljava/lang/String;
    //   7463: getstatic burp/Zxxo.ZJ : Ljava/lang/Object;
    //   7466: checkcast java/math/BigInteger
    //   7469: invokevirtual intValue : ()I
    //   7472: bipush #32
    //   7474: irem
    //   7475: invokestatic abs : (I)I
    //   7478: invokevirtual charAt : (I)C
    //   7481: invokevirtual append : (C)Ljava/lang/StringBuilder;
    //   7484: pop
    //   7485: iload_2
    //   7486: ifeq -> 7936
    //   7489: goto -> 7496
    //   7492: invokestatic a : (Ljava/lang/Throwable;)Ljava/lang/Throwable;
    //   7495: athrow
    //   7496: aload_3
    //   7497: getstatic burp/Zrye.Za : Ljava/lang/String;
    //   7500: getstatic burp/Zb87.Zb : Ljava/lang/Object;
    //   7503: checkcast java/math/BigInteger
    //   7506: invokevirtual intValue : ()I
    //   7509: bipush #32
    //   7511: irem
    //   7512: invokestatic abs : (I)I
    //   7515: invokevirtual charAt : (I)C
    //   7518: invokevirtual append : (C)Ljava/lang/StringBuilder;
    //   7521: pop
    //   7522: iload_2
    //   7523: ifeq -> 7936
    //   7526: goto -> 7533
    //   7529: invokestatic a : (Ljava/lang/Throwable;)Ljava/lang/Throwable;
    //   7532: athrow
    //   7533: aload_3
    //   7534: getstatic burp/Zeig.Zg : Ljava/lang/String;
    //   7537: getstatic burp/Zscf.ZG : Ljava/lang/Object;
    //   7540: checkcast java/math/BigInteger
    //   7543: invokevirtual intValue : ()I
    //   7546: bipush #32
    //   7548: irem
    //   7549: invokestatic abs : (I)I
    //   7552: invokevirtual charAt : (I)C
    //   7555: invokevirtual append : (C)Ljava/lang/StringBuilder;
    //   7558: pop
    //   7559: iload_2
    //   7560: ifeq -> 7936
    //   7563: goto -> 7570
    //   7566: invokestatic a : (Ljava/lang/Throwable;)Ljava/lang/Throwable;
    //   7569: athrow
    //   7570: aload_3
    //   7571: getstatic burp/Zzgb.ZT : Ljava/lang/String;
    //   7574: getstatic burp/Ztzj.Zv : Ljava/lang/Object;
    //   7577: checkcast java/math/BigInteger
    //   7580: invokevirtual intValue : ()I
    //   7583: bipush #32
    //   7585: irem
    //   7586: invokestatic abs : (I)I
    //   7589: invokevirtual charAt : (I)C
    //   7592: invokevirtual append : (C)Ljava/lang/StringBuilder;
    //   7595: pop
    //   7596: iload_2
    //   7597: ifeq -> 7936
    //   7600: goto -> 7607
    //   7603: invokestatic a : (Ljava/lang/Throwable;)Ljava/lang/Throwable;
    //   7606: athrow
    //   7607: aload_3
    //   7608: getstatic burp/Zmt_.ZH : Ljava/lang/String;
    //   7611: getstatic burp/Zmll.ZU : Ljava/lang/Object;
    //   7614: checkcast java/math/BigInteger
    //   7617: invokevirtual intValue : ()I
    //   7620: bipush #32
    //   7622: irem
    //   7623: invokestatic abs : (I)I
    //   7626: invokevirtual charAt : (I)C
    //   7629: invokevirtual append : (C)Ljava/lang/StringBuilder;
    //   7632: pop
    //   7633: iload_2
    //   7634: ifeq -> 7936
    //   7637: goto -> 7644
    //   7640: invokestatic a : (Ljava/lang/Throwable;)Ljava/lang/Throwable;
    //   7643: athrow
    //   7644: aload_3
    //   7645: getstatic burp/Zrd2.Zj : Ljava/lang/String;
    //   7648: getstatic burp/Zrom.ZF : Ljava/lang/Object;
    //   7651: checkcast java/math/BigInteger
    //   7654: invokevirtual intValue : ()I
    //   7657: bipush #32
    //   7659: irem
    //   7660: invokestatic abs : (I)I
    //   7663: invokevirtual charAt : (I)C
    //   7666: invokevirtual append : (C)Ljava/lang/StringBuilder;
    //   7669: pop
    //   7670: iload_2
    //   7671: ifeq -> 7936
    //   7674: goto -> 7681
    //   7677: invokestatic a : (Ljava/lang/Throwable;)Ljava/lang/Throwable;
    //   7680: athrow
    //   7681: aload_3
    //   7682: getstatic burp/Zkeb.ZW : Ljava/lang/String;
    //   7685: getstatic burp/Zt6z.Zl : Ljava/lang/Object;
    //   7688: checkcast java/math/BigInteger
    //   7691: invokevirtual intValue : ()I
    //   7694: bipush #32
    //   7696: irem
    //   7697: invokestatic abs : (I)I
    //   7700: invokevirtual charAt : (I)C
    //   7703: invokevirtual append : (C)Ljava/lang/StringBuilder;
    //   7706: pop
    //   7707: iload_2
    //   7708: ifeq -> 7936
    //   7711: goto -> 7718
    //   7714: invokestatic a : (Ljava/lang/Throwable;)Ljava/lang/Throwable;
    //   7717: athrow
    //   7718: aload_3
    //   7719: getstatic burp/Zt1h.Zw : Ljava/lang/String;
    //   7722: getstatic burp/Zbw5.ZR : Ljava/lang/Object;
    //   7725: checkcast java/math/BigInteger
    //   7728: invokevirtual intValue : ()I
    //   7731: bipush #32
    //   7733: irem
    //   7734: invokestatic abs : (I)I
    //   7737: invokevirtual charAt : (I)C
    //   7740: invokevirtual append : (C)Ljava/lang/StringBuilder;
    //   7743: pop
    //   7744: iload_2
    //   7745: ifeq -> 7936
    //   7748: goto -> 7755
    //   7751: invokestatic a : (Ljava/lang/Throwable;)Ljava/lang/Throwable;
    //   7754: athrow
    //   7755: aload_3
    //   7756: getstatic burp/Zzk_.ZX : Ljava/lang/String;
    //   7759: getstatic burp/Zkdx.Zn : Ljava/lang/Object;
    //   7762: checkcast java/math/BigInteger
    //   7765: invokevirtual intValue : ()I
    //   7768: bipush #32
    //   7770: irem
    //   7771: invokestatic abs : (I)I
    //   7774: invokevirtual charAt : (I)C
    //   7777: invokevirtual append : (C)Ljava/lang/StringBuilder;
    //   7780: pop
    //   7781: iload_2
    //   7782: ifeq -> 7936
    //   7785: goto -> 7792
    //   7788: invokestatic a : (Ljava/lang/Throwable;)Ljava/lang/Throwable;
    //   7791: athrow
    //   7792: aload_3
    //   7793: getstatic burp/Ze2k.ZY : Ljava/lang/String;
    //   7796: getstatic burp/Zzh5.ZG : Ljava/lang/Object;
    //   7799: checkcast java/math/BigInteger
    //   7802: invokevirtual intValue : ()I
    //   7805: bipush #32
    //   7807: irem
    //   7808: invokestatic abs : (I)I
    //   7811: invokevirtual charAt : (I)C
    //   7814: invokevirtual append : (C)Ljava/lang/StringBuilder;
    //   7817: pop
    //   7818: iload_2
    //   7819: ifeq -> 7936
    //   7822: goto -> 7829
    //   7825: invokestatic a : (Ljava/lang/Throwable;)Ljava/lang/Throwable;
    //   7828: athrow
    //   7829: aload_3
    //   7830: getstatic burp/Zz0y.ZM : Ljava/lang/String;
    //   7833: getstatic burp/Zmhq.ZK : Ljava/lang/Object;
    //   7836: checkcast java/math/BigInteger
    //   7839: invokevirtual intValue : ()I
    //   7842: bipush #32
    //   7844: irem
    //   7845: invokestatic abs : (I)I
    //   7848: invokevirtual charAt : (I)C
    //   7851: invokevirtual append : (C)Ljava/lang/StringBuilder;
    //   7854: pop
    //   7855: iload_2
    //   7856: ifeq -> 7936
    //   7859: goto -> 7866
    //   7862: invokestatic a : (Ljava/lang/Throwable;)Ljava/lang/Throwable;
    //   7865: athrow
    //   7866: aload_3
    //   7867: getstatic burp/Zs3m.Zl : Ljava/lang/String;
    //   7870: getstatic burp/Zgk9.ZD : Ljava/lang/Object;
    //   7873: checkcast java/math/BigInteger
    //   7876: invokevirtual intValue : ()I
    //   7879: bipush #32
    //   7881: irem
    //   7882: invokestatic abs : (I)I
    //   7885: invokevirtual charAt : (I)C
    //   7888: invokevirtual append : (C)Ljava/lang/StringBuilder;
    //   7891: pop
    //   7892: iload_2
    //   7893: ifeq -> 7936
    //   7896: goto -> 7903
    //   7899: invokestatic a : (Ljava/lang/Throwable;)Ljava/lang/Throwable;
    //   7902: athrow
    //   7903: aload_3
    //   7904: getstatic burp/Zmf6.Zn : Ljava/lang/String;
    //   7907: getstatic burp/Zgei.ZN : Ljava/lang/Object;
    //   7910: checkcast java/math/BigInteger
    //   7913: invokevirtual intValue : ()I
    //   7916: bipush #32
    //   7918: irem
    //   7919: invokestatic abs : (I)I
    //   7922: invokevirtual charAt : (I)C
    //   7925: invokevirtual append : (C)Ljava/lang/StringBuilder;
    //   7928: pop
    //   7929: goto -> 7936
    //   7932: invokestatic a : (Ljava/lang/Throwable;)Ljava/lang/Throwable;
    //   7935: athrow
    //   7936: iinc #4, 1
    //   7939: iload_2
    //   7940: ifeq -> 6605
    //   7943: aload_3
    //   7944: invokevirtual toString : ()Ljava/lang/String;
    //   7947: putstatic burp/Zs5y.ZO : Ljava/lang/String;
    //   7950: sipush #19707
    //   7953: sipush #-18396
    //   7956: invokestatic a : (II)Ljava/lang/String;
    //   7959: iconst_1
    //   7960: ldc burp/Zgyk
    //   7962: invokevirtual getClassLoader : ()Ljava/lang/ClassLoader;
    //   7965: invokestatic forName : (Ljava/lang/String;ZLjava/lang/ClassLoader;)Ljava/lang/Class;
    //   7968: invokevirtual getDeclaredFields : ()[Ljava/lang/reflect/Field;
    //   7971: astore #4
    //   7973: aload #4
    //   7975: arraylength
    //   7976: istore #5
    //   7978: iconst_0
    //   7979: istore #6
    //   7981: iload #6
    //   7983: iload #5
    //   7985: if_icmpge -> 8123
    //   7988: aload #4
    //   7990: iload #6
    //   7992: aaload
    //   7993: astore #7
    //   7995: aload #7
    //   7997: invokevirtual getModifiers : ()I
    //   8000: invokestatic isStatic : (I)Z
    //   8003: ifne -> 8013
    //   8006: goto -> 8116
    //   8009: invokestatic a : (Ljava/lang/Throwable;)Ljava/lang/Throwable;
    //   8012: athrow
    //   8013: aload #7
    //   8015: invokevirtual getType : ()Ljava/lang/Class;
    //   8018: astore #8
    //   8020: aload #8
    //   8022: ifnull -> 8103
    //   8025: aload #8
    //   8027: invokevirtual isPrimitive : ()Z
    //   8030: ifne -> 8103
    //   8033: goto -> 8040
    //   8036: invokestatic a : (Ljava/lang/Throwable;)Ljava/lang/Throwable;
    //   8039: athrow
    //   8040: aload #8
    //   8042: invokevirtual getPackage : ()Ljava/lang/Package;
    //   8045: ifnull -> 8103
    //   8048: goto -> 8055
    //   8051: invokestatic a : (Ljava/lang/Throwable;)Ljava/lang/Throwable;
    //   8054: athrow
    //   8055: aload #8
    //   8057: invokevirtual getPackage : ()Ljava/lang/Package;
    //   8060: invokevirtual getName : ()Ljava/lang/String;
    //   8063: ifnull -> 8103
    //   8066: goto -> 8073
    //   8069: invokestatic a : (Ljava/lang/Throwable;)Ljava/lang/Throwable;
    //   8072: athrow
    //   8073: aload #8
    //   8075: invokevirtual getPackage : ()Ljava/lang/Package;
    //   8078: invokevirtual getName : ()Ljava/lang/String;
    //   8081: sipush #19703
    //   8084: sipush #-21237
    //   8087: invokestatic a : (II)Ljava/lang/String;
    //   8090: invokevirtual startsWith : (Ljava/lang/String;)Z
    //   8093: ifne -> 8103
    //   8096: goto -> 8103
    //   8099: invokestatic a : (Ljava/lang/Throwable;)Ljava/lang/Throwable;
    //   8102: athrow
    //   8103: aload #7
    //   8105: iconst_1
    //   8106: invokevirtual setAccessible : (Z)V
    //   8109: aload #7
    //   8111: aconst_null
    //   8112: invokevirtual get : (Ljava/lang/Object;)Ljava/lang/Object;
    //   8115: pop
    //   8116: iinc #6, 1
    //   8119: iload_2
    //   8120: ifeq -> 7981
    //   8123: sipush #19705
    //   8126: sipush #-1791
    //   8129: invokestatic a : (II)Ljava/lang/String;
    //   8132: invokestatic forName : (Ljava/lang/String;)Ljava/lang/Class;
    //   8135: invokevirtual getDeclaredMethods : ()[Ljava/lang/reflect/Method;
    //   8138: astore #4
    //   8140: aload #4
    //   8142: arraylength
    //   8143: istore #5
    //   8145: iconst_0
    //   8146: istore #6
    //   8148: iload #6
    //   8150: iload #5
    //   8152: if_icmpge -> 8285
    //   8155: aload #4
    //   8157: iload #6
    //   8159: aaload
    //   8160: astore #7
    //   8162: aload #7
    //   8164: invokevirtual getParameterTypes : ()[Ljava/lang/Class;
    //   8167: pop
    //   8168: aload #7
    //   8170: invokevirtual getModifiers : ()I
    //   8173: invokestatic isStatic : (I)Z
    //   8176: ifeq -> 8271
    //   8179: aload #7
    //   8181: invokevirtual getParameterTypes : ()[Ljava/lang/Class;
    //   8184: arraylength
    //   8185: iconst_2
    //   8186: if_icmpne -> 8271
    //   8189: goto -> 8196
    //   8192: invokestatic a : (Ljava/lang/Throwable;)Ljava/lang/Throwable;
    //   8195: athrow
    //   8196: aload #7
    //   8198: invokevirtual getReturnType : ()Ljava/lang/Class;
    //   8201: getstatic java/lang/Void.TYPE : Ljava/lang/Class;
    //   8204: invokevirtual equals : (Ljava/lang/Object;)Z
    //   8207: ifeq -> 8271
    //   8210: goto -> 8217
    //   8213: invokestatic a : (Ljava/lang/Throwable;)Ljava/lang/Throwable;
    //   8216: athrow
    //   8217: aload #7
    //   8219: iconst_1
    //   8220: invokevirtual setAccessible : (Z)V
    //   8223: aload #7
    //   8225: aconst_null
    //   8226: iconst_2
    //   8227: anewarray java/lang/Object
    //   8230: dup
    //   8231: iconst_0
    //   8232: aload_0
    //   8233: aastore
    //   8234: dup
    //   8235: iconst_1
    //   8236: aload_1
    //   8237: ifnonnull -> 8255
    //   8240: goto -> 8247
    //   8243: invokestatic a : (Ljava/lang/Throwable;)Ljava/lang/Throwable;
    //   8246: athrow
    //   8247: aload_1
    //   8248: goto -> 8262
    //   8251: invokestatic a : (Ljava/lang/Throwable;)Ljava/lang/Throwable;
    //   8254: athrow
    //   8255: aload_1
    //   8256: checkcast [B
    //   8259: invokevirtual clone : ()Ljava/lang/Object;
    //   8262: aastore
    //   8263: invokevirtual invoke : (Ljava/lang/Object;[Ljava/lang/Object;)Ljava/lang/Object;
    //   8266: pop
    //   8267: iload_2
    //   8268: ifeq -> 8285
    //   8271: iinc #6, 1
    //   8274: iload_2
    //   8275: ifeq -> 8148
    //   8278: goto -> 8285
    //   8281: invokestatic a : (Ljava/lang/Throwable;)Ljava/lang/Throwable;
    //   8284: athrow
    //   8285: new java/io/ByteArrayOutputStream
    //   8288: dup
    //   8289: invokespecial <init> : ()V
    //   8292: astore #4
    //   8294: sipush #19708
    //   8297: aload #4
    //   8299: sipush #202
    //   8302: invokevirtual write : (I)V
    //   8305: sipush #-13856
    //   8308: aload #4
    //   8310: sipush #254
    //   8313: invokevirtual write : (I)V
    //   8316: aload #4
    //   8318: sipush #186
    //   8321: invokevirtual write : (I)V
    //   8324: aload #4
    //   8326: sipush #190
    //   8329: invokevirtual write : (I)V
    //   8332: aload #4
    //   8334: iconst_0
    //   8335: invokevirtual write : (I)V
    //   8338: aload #4
    //   8340: iconst_1
    //   8341: invokevirtual write : (I)V
    //   8344: aload #4
    //   8346: iconst_0
    //   8347: invokevirtual write : (I)V
    //   8350: aload #4
    //   8352: bipush #50
    //   8354: invokevirtual write : (I)V
    //   8357: aload #4
    //   8359: getstatic burp/Zx_s.ZX : Ljava/lang/Object;
    //   8362: checkcast java/math/BigInteger
    //   8365: invokevirtual toByteArray : ()[B
    //   8368: invokevirtual write : ([B)V
    //   8371: aload #4
    //   8373: getstatic burp/Zlwi.Zw : Ljava/lang/Object;
    //   8376: checkcast java/math/BigInteger
    //   8379: invokevirtual toByteArray : ()[B
    //   8382: invokevirtual write : ([B)V
    //   8385: aload #4
    //   8387: getstatic burp/Zkul.Zb : Ljava/lang/Object;
    //   8390: checkcast java/math/BigInteger
    //   8393: invokevirtual toByteArray : ()[B
    //   8396: invokevirtual write : ([B)V
    //   8399: aload #4
    //   8401: invokevirtual toByteArray : ()[B
    //   8404: astore #5
    //   8406: aconst_null
    //   8407: astore #6
    //   8409: invokestatic a : (II)Ljava/lang/String;
    //   8412: invokestatic forName : (Ljava/lang/String;)Ljava/lang/Class;
    //   8415: invokevirtual getDeclaredMethods : ()[Ljava/lang/reflect/Method;
    //   8418: astore #7
    //   8420: aload #7
    //   8422: arraylength
    //   8423: istore #8
    //   8425: iconst_0
    //   8426: istore #9
    //   8428: iload #9
    //   8430: iload #8
    //   8432: if_icmpge -> 8560
    //   8435: aload #7
    //   8437: iload #9
    //   8439: aaload
    //   8440: astore #10
    //   8442: aload #10
    //   8444: invokevirtual getName : ()Ljava/lang/String;
    //   8447: sipush #19711
    //   8450: sipush #-21609
    //   8453: invokestatic a : (II)Ljava/lang/String;
    //   8456: invokevirtual equals : (Ljava/lang/Object;)Z
    //   8459: ifeq -> 8553
    //   8462: aload #10
    //   8464: invokevirtual getParameterTypes : ()[Ljava/lang/Class;
    //   8467: astore #11
    //   8469: aload #11
    //   8471: arraylength
    //   8472: iconst_4
    //   8473: if_icmpeq -> 8483
    //   8476: goto -> 8553
    //   8479: invokestatic a : (Ljava/lang/Throwable;)Ljava/lang/Throwable;
    //   8482: athrow
    //   8483: aload #11
    //   8485: iconst_0
    //   8486: aaload
    //   8487: ldc java/lang/String
    //   8489: if_acmpeq -> 8499
    //   8492: goto -> 8553
    //   8495: invokestatic a : (Ljava/lang/Throwable;)Ljava/lang/Throwable;
    //   8498: athrow
    //   8499: aload #11
    //   8501: iconst_1
    //   8502: aaload
    //   8503: ldc [B
    //   8505: if_acmpeq -> 8515
    //   8508: goto -> 8553
    //   8511: invokestatic a : (Ljava/lang/Throwable;)Ljava/lang/Throwable;
    //   8514: athrow
    //   8515: aload #11
    //   8517: iconst_2
    //   8518: aaload
    //   8519: getstatic java/lang/Integer.TYPE : Ljava/lang/Class;
    //   8522: if_acmpeq -> 8532
    //   8525: goto -> 8553
    //   8528: invokestatic a : (Ljava/lang/Throwable;)Ljava/lang/Throwable;
    //   8531: athrow
    //   8532: aload #11
    //   8534: iconst_3
    //   8535: aaload
    //   8536: getstatic java/lang/Integer.TYPE : Ljava/lang/Class;
    //   8539: if_acmpeq -> 8549
    //   8542: goto -> 8553
    //   8545: invokestatic a : (Ljava/lang/Throwable;)Ljava/lang/Throwable;
    //   8548: athrow
    //   8549: aload #10
    //   8551: astore #6
    //   8553: iinc #9, 1
    //   8556: iload_2
    //   8557: ifeq -> 8428
    //   8560: aload #6
    //   8562: iconst_1
    //   8563: invokevirtual setAccessible : (Z)V
    //   8566: ldc burp/Zx0t
    //   8568: iconst_0
    //   8569: anewarray java/lang/Class
    //   8572: invokevirtual getDeclaredConstructor : ([Ljava/lang/Class;)Ljava/lang/reflect/Constructor;
    //   8575: astore #7
    //   8577: aload #7
    //   8579: iconst_1
    //   8580: invokevirtual setAccessible : (Z)V
    //   8583: aload #6
    //   8585: aload #7
    //   8587: iconst_0
    //   8588: anewarray java/lang/Object
    //   8591: invokevirtual newInstance : ([Ljava/lang/Object;)Ljava/lang/Object;
    //   8594: iconst_4
    //   8595: anewarray java/lang/Object
    //   8598: dup
    //   8599: iconst_0
    //   8600: sipush #19710
    //   8603: sipush #-32607
    //   8606: invokestatic a : (II)Ljava/lang/String;
    //   8609: aastore
    //   8610: dup
    //   8611: iconst_1
    //   8612: aload #5
    //   8614: aastore
    //   8615: dup
    //   8616: iconst_2
    //   8617: iconst_0
    //   8618: invokestatic valueOf : (I)Ljava/lang/Integer;
    //   8621: aastore
    //   8622: dup
    //   8623: iconst_3
    //   8624: aload #5
    //   8626: arraylength
    //   8627: invokestatic valueOf : (I)Ljava/lang/Integer;
    //   8630: aastore
    //   8631: invokevirtual invoke : (Ljava/lang/Object;[Ljava/lang/Object;)Ljava/lang/Object;
    //   8634: pop
    //   8635: goto -> 8640
    //   8638: astore #4
    //   8640: getstatic burp/Zspg.ZG : Ljava/lang/String;
    //   8643: getstatic burp/Ztvy.ZH : Ljava/lang/Object;
    //   8646: checkcast java/math/BigInteger
    //   8649: invokevirtual intValue : ()I
    //   8652: bipush #32
    //   8654: irem
    //   8655: invokestatic abs : (I)I
    //   8658: invokevirtual charAt : (I)C
    //   8661: getstatic burp/Zst7.Zi : Ljava/lang/String;
    //   8664: getstatic burp/Zml9.ZH : Ljava/lang/Object;
    //   8667: checkcast java/math/BigInteger
    //   8670: invokevirtual intValue : ()I
    //   8673: bipush #32
    //   8675: irem
    //   8676: invokestatic abs : (I)I
    //   8679: invokevirtual charAt : (I)C
    //   8682: if_icmpgt -> 8789
    //   8685: getstatic burp/Zxju.Zt : Ljava/lang/String;
    //   8688: getstatic burp/Zxan.ZX : Ljava/lang/Object;
    //   8691: checkcast java/math/BigInteger
    //   8694: invokevirtual intValue : ()I
    //   8697: bipush #32
    //   8699: irem
    //   8700: invokestatic abs : (I)I
    //   8703: invokevirtual charAt : (I)C
    //   8706: getstatic burp/Zma0.ZP : Ljava/lang/String;
    //   8709: getstatic burp/Zmn0.Zo : Ljava/lang/Object;
    //   8712: checkcast java/math/BigInteger
    //   8715: invokevirtual intValue : ()I
    //   8718: bipush #32
    //   8720: irem
    //   8721: invokestatic abs : (I)I
    //   8724: invokevirtual charAt : (I)C
    //   8727: if_icmple -> 8789
    //   8730: goto -> 8737
    //   8733: invokestatic a : (Ljava/lang/Throwable;)Ljava/lang/Throwable;
    //   8736: athrow
    //   8737: getstatic burp/Zz91.Zx : Ljava/lang/String;
    //   8740: getstatic burp/Zmn0.Zo : Ljava/lang/Object;
    //   8743: checkcast java/math/BigInteger
    //   8746: invokevirtual intValue : ()I
    //   8749: bipush #32
    //   8751: irem
    //   8752: invokestatic abs : (I)I
    //   8755: invokevirtual charAt : (I)C
    //   8758: getstatic burp/Zthx.Ze : Ljava/lang/String;
    //   8761: getstatic burp/Ze4g.Zz : Ljava/lang/Object;
    //   8764: checkcast java/math/BigInteger
    //   8767: invokevirtual intValue : ()I
    //   8770: bipush #32
    //   8772: irem
    //   8773: invokestatic abs : (I)I
    //   8776: invokevirtual charAt : (I)C
    //   8779: if_icmple -> 8797
    //   8782: goto -> 8789
    //   8785: invokestatic a : (Ljava/lang/Throwable;)Ljava/lang/Throwable;
    //   8788: athrow
    //   8789: iconst_1
    //   8790: goto -> 8798
    //   8793: invokestatic a : (Ljava/lang/Throwable;)Ljava/lang/Throwable;
    //   8796: athrow
    //   8797: iconst_0
    //   8798: ireturn
    //   8799: astore_3
    //   8800: new java/lang/Exception
    //   8803: dup
    //   8804: aload_3
    //   8805: invokevirtual getMessage : ()Ljava/lang/String;
    //   8808: invokespecial <init> : (Ljava/lang/String;)V
    //   8811: athrow
    // Exception table:
    //   from	to	target	type
    //   4	8798	8799	java/lang/Throwable
    //   149	164	164	java/lang/Throwable
    //   1166	1192	1192	java/lang/Throwable
    //   1273	1288	1288	java/lang/Throwable
    //   2470	2495	2498	java/lang/Throwable
    //   3322	3356	3359	java/lang/Throwable
    //   3451	3529	3532	java/lang/Throwable
    //   3458	3672	3675	java/lang/Throwable
    //   4049	4064	4064	java/lang/Throwable
    //   4091	4125	4128	java/lang/Throwable
    //   4135	4147	4150	java/lang/Throwable
    //   4233	4311	4314	java/lang/Throwable
    //   4240	4454	4457	java/lang/Throwable
    //   4854	4932	4935	java/lang/Throwable
    //   4861	5075	5078	java/lang/Throwable
    //   5522	5556	5559	java/lang/Throwable
    //   5563	5575	5578	java/lang/Throwable
    //   5661	5739	5742	java/lang/Throwable
    //   5668	5882	5885	java/lang/Throwable
    //   6612	6786	6789	java/lang/Throwable
    //   6756	6823	6826	java/lang/Throwable
    //   6793	6860	6863	java/lang/Throwable
    //   6830	6897	6900	java/lang/Throwable
    //   6867	6934	6937	java/lang/Throwable
    //   6904	6971	6974	java/lang/Throwable
    //   6941	7008	7011	java/lang/Throwable
    //   6978	7045	7048	java/lang/Throwable
    //   7015	7082	7085	java/lang/Throwable
    //   7052	7119	7122	java/lang/Throwable
    //   7089	7156	7159	java/lang/Throwable
    //   7126	7193	7196	java/lang/Throwable
    //   7163	7230	7233	java/lang/Throwable
    //   7200	7267	7270	java/lang/Throwable
    //   7237	7304	7307	java/lang/Throwable
    //   7274	7341	7344	java/lang/Throwable
    //   7311	7378	7381	java/lang/Throwable
    //   7348	7415	7418	java/lang/Throwable
    //   7385	7452	7455	java/lang/Throwable
    //   7422	7489	7492	java/lang/Throwable
    //   7459	7526	7529	java/lang/Throwable
    //   7496	7563	7566	java/lang/Throwable
    //   7533	7600	7603	java/lang/Throwable
    //   7570	7637	7640	java/lang/Throwable
    //   7607	7674	7677	java/lang/Throwable
    //   7644	7711	7714	java/lang/Throwable
    //   7681	7748	7751	java/lang/Throwable
    //   7718	7785	7788	java/lang/Throwable
    //   7755	7822	7825	java/lang/Throwable
    //   7792	7859	7862	java/lang/Throwable
    //   7829	7896	7899	java/lang/Throwable
    //   7866	7929	7932	java/lang/Throwable
    //   7995	8009	8009	java/lang/Throwable
    //   8020	8033	8036	java/lang/Throwable
    //   8025	8048	8051	java/lang/Throwable
    //   8040	8066	8069	java/lang/Throwable
    //   8055	8096	8099	java/lang/Throwable
    //   8162	8189	8192	java/lang/Throwable
    //   8179	8210	8213	java/lang/Throwable
    //   8196	8240	8243	java/lang/Throwable
    //   8217	8251	8251	java/lang/Throwable
    //   8262	8278	8281	java/lang/Throwable
    //   8285	8635	8638	java/lang/Throwable
    //   8469	8479	8479	java/lang/Throwable
    //   8483	8495	8495	java/lang/Throwable
    //   8499	8511	8511	java/lang/Throwable
    //   8515	8528	8528	java/lang/Throwable
    //   8532	8545	8545	java/lang/Throwable
    //   8640	8730	8733	java/lang/Throwable
    //   8685	8782	8785	java/lang/Throwable
    //   8737	8793	8793	java/lang/Throwable
  }
  
  static {
    // Byte code:
    //   0: bipush #14
    //   2: anewarray java/lang/String
    //   5: astore #5
    //   7: iconst_0
    //   8: istore_3
    //   9: ldc '}B0o^o!\\b;6ny*4ZtMBz\\nwc8EBg\\tr08[A\AlM`iM#_;#ic]f}\\n\\njw\\t'\\twqv>??\\tv"Qcrg B._!TtgXN.y >*{ 3Wm:W?\\rR5>[6\\\t\\f5'
    //   11: dup
    //   12: astore_2
    //   13: invokevirtual length : ()I
    //   16: istore #4
    //   18: bipush #8
    //   20: istore_1
    //   21: iconst_m1
    //   22: istore_0
    //   23: bipush #116
    //   25: iinc #0, 1
    //   28: aload_2
    //   29: iload_0
    //   30: dup
    //   31: iload_1
    //   32: iadd
    //   33: invokevirtual substring : (II)Ljava/lang/String;
    //   36: iconst_m1
    //   37: goto -> 143
    //   40: aload #5
    //   42: swap
    //   43: iload_3
    //   44: iinc #3, 1
    //   47: swap
    //   48: aastore
    //   49: iload_0
    //   50: iload_1
    //   51: iadd
    //   52: dup
    //   53: istore_0
    //   54: iload #4
    //   56: if_icmpge -> 68
    //   59: aload_2
    //   60: iload_0
    //   61: invokevirtual charAt : (I)C
    //   64: istore_1
    //   65: goto -> 23
    //   68: ldc 'C\\t 11O??'
    //   70: dup
    //   71: astore_2
    //   72: invokevirtual length : ()I
    //   75: istore #4
    //   77: bipush #19
    //   79: istore_1
    //   80: iconst_m1
    //   81: istore_0
    //   82: bipush #91
    //   84: iinc #0, 1
    //   87: aload_2
    //   88: iload_0
    //   89: dup
    //   90: iload_1
    //   91: iadd
    //   92: invokevirtual substring : (II)Ljava/lang/String;
    //   95: iconst_0
    //   96: goto -> 143
    //   99: aload #5
    //   101: swap
    //   102: iload_3
    //   103: iinc #3, 1
    //   106: swap
    //   107: aastore
    //   108: iload_0
    //   109: iload_1
    //   110: iadd
    //   111: dup
    //   112: istore_0
    //   113: iload #4
    //   115: if_icmpge -> 127
    //   118: aload_2
    //   119: iload_0
    //   120: invokevirtual charAt : (I)C
    //   123: istore_1
    //   124: goto -> 82
    //   127: aload #5
    //   129: putstatic burp/Zs0h.a : [Ljava/lang/String;
    //   132: bipush #14
    //   134: anewarray java/lang/String
    //   137: putstatic burp/Zs0h.b : [Ljava/lang/String;
    //   140: goto -> 300
    //   143: dup_x2
    //   144: pop
    //   145: invokevirtual toCharArray : ()[C
    //   148: dup_x1
    //   149: arraylength
    //   150: dup_x2
    //   151: pop
    //   152: iconst_0
    //   153: istore #6
    //   155: dup2_x1
    //   156: pop2
    //   157: dup_x2
    //   158: iconst_1
    //   159: if_icmpgt -> 260
    //   162: dup2
    //   163: swap
    //   164: iload #6
    //   166: dup2_x1
    //   167: caload
    //   168: swap
    //   169: iload #6
    //   171: bipush #7
    //   173: irem
    //   174: tableswitch default -> 242, 0 -> 212, 1 -> 217, 2 -> 222, 3 -> 227, 4 -> 232, 5 -> 237
    //   212: bipush #41
    //   214: goto -> 244
    //   217: bipush #98
    //   219: goto -> 244
    //   222: bipush #28
    //   224: goto -> 244
    //   227: bipush #58
    //   229: goto -> 244
    //   232: bipush #51
    //   234: goto -> 244
    //   237: bipush #32
    //   239: goto -> 244
    //   242: bipush #45
    //   244: ixor
    //   245: ixor
    //   246: i2c
    //   247: castore
    //   248: iinc #6, 1
    //   251: dup
    //   252: ifne -> 260
    //   255: dup2
    //   256: dup_x1
    //   257: goto -> 166
    //   260: dup2_x1
    //   261: pop2
    //   262: dup_x2
    //   263: iload #6
    //   265: if_icmpgt -> 162
    //   268: pop
    //   269: new java/lang/String
    //   272: dup_x1
    //   273: swap
    //   274: invokespecial <init> : ([C)V
    //   277: invokevirtual intern : ()Ljava/lang/String;
    //   280: swap
    //   281: pop
    //   282: swap
    //   283: tableswitch default -> 40, 0 -> 99
    //   300: new java/math/BigInteger
    //   303: dup
    //   304: bipush #32
    //   306: newarray byte
    //   308: dup
    //   309: iconst_0
    //   310: bipush #44
    //   312: bastore
    //   313: dup
    //   314: iconst_1
    //   315: bipush #110
    //   317: bastore
    //   318: dup
    //   319: iconst_2
    //   320: bipush #-22
    //   322: bastore
    //   323: dup
    //   324: iconst_3
    //   325: bipush #-4
    //   327: bastore
    //   328: dup
    //   329: iconst_4
    //   330: bipush #55
    //   332: bastore
    //   333: dup
    //   334: iconst_5
    //   335: bipush #75
    //   337: bastore
    //   338: dup
    //   339: bipush #6
    //   341: bipush #-46
    //   343: bastore
    //   344: dup
    //   345: bipush #7
    //   347: bipush #9
    //   349: bastore
    //   350: dup
    //   351: bipush #8
    //   353: bipush #-87
    //   355: bastore
    //   356: dup
    //   357: bipush #9
    //   359: bipush #-108
    //   361: bastore
    //   362: dup
    //   363: bipush #10
    //   365: bipush #55
    //   367: bastore
    //   368: dup
    //   369: bipush #11
    //   371: bipush #-74
    //   373: bastore
    //   374: dup
    //   375: bipush #12
    //   377: bipush #51
    //   379: bastore
    //   380: dup
    //   381: bipush #13
    //   383: bipush #-88
    //   385: bastore
    //   386: dup
    //   387: bipush #14
    //   389: bipush #-45
    //   391: bastore
    //   392: dup
    //   393: bipush #15
    //   395: bipush #-39
    //   397: bastore
    //   398: dup
    //   399: bipush #16
    //   401: bipush #-69
    //   403: bastore
    //   404: dup
    //   405: bipush #17
    //   407: bipush #-45
    //   409: bastore
    //   410: dup
    //   411: bipush #18
    //   413: bipush #94
    //   415: bastore
    //   416: dup
    //   417: bipush #19
    //   419: bipush #7
    //   421: bastore
    //   422: dup
    //   423: bipush #20
    //   425: bipush #110
    //   427: bastore
    //   428: dup
    //   429: bipush #21
    //   431: bipush #-8
    //   433: bastore
    //   434: dup
    //   435: bipush #22
    //   437: bipush #92
    //   439: bastore
    //   440: dup
    //   441: bipush #23
    //   443: bipush #-22
    //   445: bastore
    //   446: dup
    //   447: bipush #24
    //   449: bipush #10
    //   451: bastore
    //   452: dup
    //   453: bipush #25
    //   455: bipush #91
    //   457: bastore
    //   458: dup
    //   459: bipush #26
    //   461: bipush #-12
    //   463: bastore
    //   464: dup
    //   465: bipush #27
    //   467: bipush #-10
    //   469: bastore
    //   470: dup
    //   471: bipush #28
    //   473: bipush #-48
    //   475: bastore
    //   476: dup
    //   477: bipush #29
    //   479: bipush #-111
    //   481: bastore
    //   482: dup
    //   483: bipush #30
    //   485: bipush #105
    //   487: bastore
    //   488: dup
    //   489: bipush #31
    //   491: bipush #-76
    //   493: bastore
    //   494: invokespecial <init> : ([B)V
    //   497: putstatic burp/Zs0h.ZU : Ljava/lang/Object;
    //   500: sipush #19702
    //   503: sipush #23767
    //   506: invokestatic a : (II)Ljava/lang/String;
    //   509: putstatic burp/Zs0h.ZX : Ljava/lang/String;
    //   512: return
  }
  
  private static Throwable a(Throwable paramThrowable) {
    return paramThrowable;
  }
  
  private static String a(int paramInt1, int paramInt2) {
    int i = (paramInt1 ^ 0x4CFE) & 0xFFFF;
    if (b[i] == null) {
      char[] arrayOfChar = a[i].toCharArray();
      switch (arrayOfChar[0] & 0xFF) {
        case 0:
        
        case 1:
        
        case 2:
        
        case 3:
        
        case 4:
        
        case 5:
        
        case 6:
        
        case 7:
        
        case 8:
        
        case 9:
        
        case 10:
        
        case 11:
        
        case 12:
        
        case 13:
        
        case 14:
        
        case 15:
        
        case 16:
        
        case 17:
        
        case 18:
        
        case 19:
        
        case 20:
        
        case 21:
        
        case 22:
        
        case 23:
        
        case 24:
        
        case 25:
        
        case 26:
        
        case 27:
        
        case 28:
        
        case 29:
        
        case 30:
        
        case 31:
        
        case 32:
        
        case 33:
        
        case 34:
        
        case 35:
        
        case 36:
        
        case 37:
        
        case 38:
        
        case 39:
        
        case 40:
        
        case 41:
        
        case 42:
        
        case 43:
        
        case 44:
        
        case 45:
        
        case 46:
        
        case 47:
        
        case 48:
        
        case 49:
        
        case 50:
        
        case 51:
        
        case 52:
        
        case 53:
        
        case 54:
        
        case 55:
        
        case 56:
        
        case 57:
        
        case 58:
        
        case 59:
        
        case 60:
        
        case 61:
        
        case 62:
        
        case 63:
        
        case 64:
        
        case 65:
        
        case 66:
        
        case 67:
        
        case 68:
        
        case 69:
        
        case 70:
        
        case 71:
        
        case 72:
        
        case 73:
        
        case 74:
        
        case 75:
        
        case 76:
        
        case 77:
        
        case 78:
        
        case 79:
        
        case 80:
        
        case 81:
        
        case 82:
        
        case 83:
        
        case 84:
        
        case 85:
        
        case 86:
        
        case 87:
        
        case 88:
        
        case 89:
        
        case 90:
        
        case 91:
        
        case 92:
        
        case 93:
        
        case 94:
        
        case 95:
        
        case 96:
        
        case 97:
        
        case 98:
        
        case 99:
        
        case 100:
        
        case 101:
        
        case 102:
        
        case 103:
        
        case 104:
        
        case 105:
        
        case 106:
        
        case 107:
        
        case 108:
        
        case 109:
        
        case 110:
        
        case 111:
        
        case 112:
        
        case 113:
        
        case 114:
        
        case 115:
        
        case 116:
        
        case 117:
        
        case 118:
        
        case 119:
        
        case 120:
        
        case 121:
        
        case 122:
        
        case 123:
        
        case 124:
        
        case 125:
        
        case 126:
        
        case 127:
        
        case 128:
        
        case 129:
        
        case 130:
        
        case 131:
        
        case 132:
        
        case 133:
        
        case 134:
        
        case 135:
        
        case 136:
        
        case 137:
        
        case 138:
        
        case 139:
        
        case 140:
        
        case 141:
        
        case 142:
        
        case 143:
        
        case 144:
        
        case 145:
        
        case 146:
        
        case 147:
        
        case 148:
        
        case 149:
        
        case 150:
        
        case 151:
        
        case 152:
        
        case 153:
        
        case 154:
        
        case 155:
        
        case 156:
        
        case 157:
        
        case 158:
        
        case 159:
        
        case 160:
        
        case 161:
        
        case 162:
        
        case 163:
        
        case 164:
        
        case 165:
        
        case 166:
        
        case 167:
        
        case 168:
        
        case 169:
        
        case 170:
        
        case 171:
        
        case 172:
        
        case 173:
        
        case 174:
        
        case 175:
        
        case 176:
        
        case 177:
        
        case 178:
        
        case 179:
        
        case 180:
        
        case 181:
        
        case 182:
        
        case 183:
        
        case 184:
        
        case 185:
        
        case 186:
        
        case 187:
        
        case 188:
        
        case 189:
        
        case 190:
        
        case 191:
        
        case 192:
        
        case 193:
        
        case 194:
        
        case 195:
        
        case 196:
        
        case 197:
        
        case 198:
        
        case 199:
        
        case 200:
        
        case 201:
        
        case 202:
        
        case 203:
        
        case 204:
        
        case 205:
        
        case 206:
        
        case 207:
        
        case 208:
        
        case 209:
        
        case 210:
        
        case 211:
        
        case 212:
        
        case 213:
        
        case 214:
        
        case 215:
        
        case 216:
        
        case 217:
        
        case 218:
        
        case 219:
        
        case 220:
        
        case 221:
        
        case 222:
        
        case 223:
        
        case 224:
        
        case 225:
        
        case 226:
        
        case 227:
        
        case 228:
        
        case 229:
        
        case 230:
        
        case 231:
        
        case 232:
        
        case 233:
        
        case 234:
        
        case 235:
        
        case 236:
        
        case 237:
        
        case 238:
        
        case 239:
        
        case 240:
        
        case 241:
        
        case 242:
        
        case 243:
        
        case 244:
        
        case 245:
        
        case 246:
        
        case 247:
        
        case 248:
        
        case 249:
        
        case 250:
        
        case 251:
        
        case 252:
        
        case 253:
        
        case 254:
        
        default:
          break;
      } 
      char c = '';
      int j = (paramInt2 & 0xFF) - c;
      if (j < 0)
        j += 256; 
      int k = ((paramInt2 & 0xFFFF) >>> 8) - c;
      if (k < 0)
        k += 256; 
      for (byte b = 0; b < arrayOfChar.length; b++) {
        int m = b % 2;
        if (m == 0) {
          arrayOfChar[b] = (char)(arrayOfChar[b] ^ j);
          j = ((j >>> 3 | j << 5) ^ arrayOfChar[b]) & 0xFF;
        } else {
          arrayOfChar[b] = (char)(arrayOfChar[b] ^ k);
          k = ((k >>> 3 | k << 5) ^ arrayOfChar[b]) & 0xFF;
        } 
      } 
      b[i] = (new String(arrayOfChar)).intern();
    } 
    return b[i];
  }
}


/* Location:              C:\Program Files\BurpSuitePro\burpsuite_pro.jar!\burp\Zs0h.class
 * Java compiler version: 21 (65.0)
 * JD-Core Version:       1.1.3
 */