package burp;

import java.math.BigInteger;

class Zs1k extends ClassLoader {
  static Object Ze;
  
  static String Zd;
  
  private static final String[] a;
  
  private static final String[] b;
  
  static void Zw(Object[] paramArrayOfObject, Object paramObject) throws Throwable {}
  
  static void Zr(Object paramObject) {
    Zti4.ZI = a(7315, -16931);
    Zti4.Zi = new BigInteger(a(7326, -18752));
    boolean bool = Zt2e.ZN();
    try {
      try {
        if (Zz4j.ZS.charAt(Math.abs(((BigInteger)Zt1h.Zb).intValue() % 32)) > Zr9u.Zc.charAt(Math.abs(((BigInteger)Zl2t.ZS).intValue() % 32))) {
          try {
            Zr8h.Zh(Class.forName(a(7320, 24705)));
            if (!bool)
              Zeig.ZM(Class.forName(a(7327, -1584))); 
          } catch (Throwable throwable) {
            throw a(null);
          } 
          return;
        } 
      } catch (Throwable throwable) {
        throw a(null);
      } 
      Zeig.ZM(Class.forName(a(7327, -1584)));
    } catch (Throwable throwable) {}
  }
  
  static boolean Zl(Object[] paramArrayOfObject, Object paramObject) throws Throwable {
    // Byte code:
    //   0: invokestatic ZK : ()Z
    //   3: istore_2
    //   4: new java/lang/StringBuilder
    //   7: dup
    //   8: invokespecial <init> : ()V
    //   11: astore_3
    //   12: iconst_0
    //   13: istore #4
    //   15: iload #4
    //   17: bipush #32
    //   19: if_icmpge -> 1355
    //   22: iload #4
    //   24: tableswitch default -> 1348, 0 -> 168, 1 -> 205, 2 -> 242, 3 -> 279, 4 -> 316, 5 -> 353, 6 -> 390, 7 -> 427, 8 -> 464, 9 -> 501, 10 -> 538, 11 -> 575, 12 -> 612, 13 -> 649, 14 -> 686, 15 -> 723, 16 -> 760, 17 -> 797, 18 -> 834, 19 -> 871, 20 -> 908, 21 -> 945, 22 -> 982, 23 -> 1019, 24 -> 1056, 25 -> 1093, 26 -> 1130, 27 -> 1167, 28 -> 1204, 29 -> 1241, 30 -> 1278, 31 -> 1315
    //   168: aload_3
    //   169: getstatic burp/Zk8f.ZV : Ljava/lang/String;
    //   172: getstatic burp/Zeub.ZD : Ljava/lang/Object;
    //   175: checkcast java/math/BigInteger
    //   178: invokevirtual intValue : ()I
    //   181: bipush #32
    //   183: irem
    //   184: invokestatic abs : (I)I
    //   187: invokevirtual charAt : (I)C
    //   190: invokevirtual append : (C)Ljava/lang/StringBuilder;
    //   193: pop
    //   194: iload_2
    //   195: ifeq -> 1348
    //   198: goto -> 205
    //   201: invokestatic a : (Ljava/lang/Throwable;)Ljava/lang/Throwable;
    //   204: athrow
    //   205: aload_3
    //   206: getstatic burp/Zxc0.Zh : Ljava/lang/String;
    //   209: getstatic burp/Zxn9.ZN : Ljava/lang/Object;
    //   212: checkcast java/math/BigInteger
    //   215: invokevirtual intValue : ()I
    //   218: bipush #32
    //   220: irem
    //   221: invokestatic abs : (I)I
    //   224: invokevirtual charAt : (I)C
    //   227: invokevirtual append : (C)Ljava/lang/StringBuilder;
    //   230: pop
    //   231: iload_2
    //   232: ifeq -> 1348
    //   235: goto -> 242
    //   238: invokestatic a : (Ljava/lang/Throwable;)Ljava/lang/Throwable;
    //   241: athrow
    //   242: aload_3
    //   243: getstatic burp/Zmdi.ZA : Ljava/lang/String;
    //   246: getstatic burp/Zeqx.Zh : Ljava/lang/Object;
    //   249: checkcast java/math/BigInteger
    //   252: invokevirtual intValue : ()I
    //   255: bipush #32
    //   257: irem
    //   258: invokestatic abs : (I)I
    //   261: invokevirtual charAt : (I)C
    //   264: invokevirtual append : (C)Ljava/lang/StringBuilder;
    //   267: pop
    //   268: iload_2
    //   269: ifeq -> 1348
    //   272: goto -> 279
    //   275: invokestatic a : (Ljava/lang/Throwable;)Ljava/lang/Throwable;
    //   278: athrow
    //   279: aload_3
    //   280: getstatic burp/Zge2.ZT : Ljava/lang/String;
    //   283: getstatic burp/Zea.ZO : Ljava/lang/Object;
    //   286: checkcast java/math/BigInteger
    //   289: invokevirtual intValue : ()I
    //   292: bipush #32
    //   294: irem
    //   295: invokestatic abs : (I)I
    //   298: invokevirtual charAt : (I)C
    //   301: invokevirtual append : (C)Ljava/lang/StringBuilder;
    //   304: pop
    //   305: iload_2
    //   306: ifeq -> 1348
    //   309: goto -> 316
    //   312: invokestatic a : (Ljava/lang/Throwable;)Ljava/lang/Throwable;
    //   315: athrow
    //   316: aload_3
    //   317: getstatic burp/Zs1k.Zd : Ljava/lang/String;
    //   320: getstatic burp/Zx5w.Zo : Ljava/lang/Object;
    //   323: checkcast java/math/BigInteger
    //   326: invokevirtual intValue : ()I
    //   329: bipush #32
    //   331: irem
    //   332: invokestatic abs : (I)I
    //   335: invokevirtual charAt : (I)C
    //   338: invokevirtual append : (C)Ljava/lang/StringBuilder;
    //   341: pop
    //   342: iload_2
    //   343: ifeq -> 1348
    //   346: goto -> 353
    //   349: invokestatic a : (Ljava/lang/Throwable;)Ljava/lang/Throwable;
    //   352: athrow
    //   353: aload_3
    //   354: getstatic burp/Zzc9.Zv : Ljava/lang/String;
    //   357: getstatic burp/Zm7v.ZP : Ljava/lang/Object;
    //   360: checkcast java/math/BigInteger
    //   363: invokevirtual intValue : ()I
    //   366: bipush #32
    //   368: irem
    //   369: invokestatic abs : (I)I
    //   372: invokevirtual charAt : (I)C
    //   375: invokevirtual append : (C)Ljava/lang/StringBuilder;
    //   378: pop
    //   379: iload_2
    //   380: ifeq -> 1348
    //   383: goto -> 390
    //   386: invokestatic a : (Ljava/lang/Throwable;)Ljava/lang/Throwable;
    //   389: athrow
    //   390: aload_3
    //   391: getstatic burp/Zmtr.Zd : Ljava/lang/String;
    //   394: getstatic burp/Zg0q.Zf : Ljava/lang/Object;
    //   397: checkcast java/math/BigInteger
    //   400: invokevirtual intValue : ()I
    //   403: bipush #32
    //   405: irem
    //   406: invokestatic abs : (I)I
    //   409: invokevirtual charAt : (I)C
    //   412: invokevirtual append : (C)Ljava/lang/StringBuilder;
    //   415: pop
    //   416: iload_2
    //   417: ifeq -> 1348
    //   420: goto -> 427
    //   423: invokestatic a : (Ljava/lang/Throwable;)Ljava/lang/Throwable;
    //   426: athrow
    //   427: aload_3
    //   428: getstatic burp/Zz7m.Zq : Ljava/lang/String;
    //   431: getstatic burp/Zz0y.Zp : Ljava/lang/Object;
    //   434: checkcast java/math/BigInteger
    //   437: invokevirtual intValue : ()I
    //   440: bipush #32
    //   442: irem
    //   443: invokestatic abs : (I)I
    //   446: invokevirtual charAt : (I)C
    //   449: invokevirtual append : (C)Ljava/lang/StringBuilder;
    //   452: pop
    //   453: iload_2
    //   454: ifeq -> 1348
    //   457: goto -> 464
    //   460: invokestatic a : (Ljava/lang/Throwable;)Ljava/lang/Throwable;
    //   463: athrow
    //   464: aload_3
    //   465: getstatic burp/Zeig.Zg : Ljava/lang/String;
    //   468: getstatic burp/Zm1d.ZS : Ljava/lang/Object;
    //   471: checkcast java/math/BigInteger
    //   474: invokevirtual intValue : ()I
    //   477: bipush #32
    //   479: irem
    //   480: invokestatic abs : (I)I
    //   483: invokevirtual charAt : (I)C
    //   486: invokevirtual append : (C)Ljava/lang/StringBuilder;
    //   489: pop
    //   490: iload_2
    //   491: ifeq -> 1348
    //   494: goto -> 501
    //   497: invokestatic a : (Ljava/lang/Throwable;)Ljava/lang/Throwable;
    //   500: athrow
    //   501: aload_3
    //   502: getstatic burp/Zrnk.Zb : Ljava/lang/String;
    //   505: getstatic burp/Zsbo.ZG : Ljava/lang/Object;
    //   508: checkcast java/math/BigInteger
    //   511: invokevirtual intValue : ()I
    //   514: bipush #32
    //   516: irem
    //   517: invokestatic abs : (I)I
    //   520: invokevirtual charAt : (I)C
    //   523: invokevirtual append : (C)Ljava/lang/StringBuilder;
    //   526: pop
    //   527: iload_2
    //   528: ifeq -> 1348
    //   531: goto -> 538
    //   534: invokestatic a : (Ljava/lang/Throwable;)Ljava/lang/Throwable;
    //   537: athrow
    //   538: aload_3
    //   539: getstatic burp/Zz7m.Zq : Ljava/lang/String;
    //   542: getstatic burp/Zrd3.ZI : Ljava/lang/Object;
    //   545: checkcast java/math/BigInteger
    //   548: invokevirtual intValue : ()I
    //   551: bipush #32
    //   553: irem
    //   554: invokestatic abs : (I)I
    //   557: invokevirtual charAt : (I)C
    //   560: invokevirtual append : (C)Ljava/lang/StringBuilder;
    //   563: pop
    //   564: iload_2
    //   565: ifeq -> 1348
    //   568: goto -> 575
    //   571: invokestatic a : (Ljava/lang/Throwable;)Ljava/lang/Throwable;
    //   574: athrow
    //   575: aload_3
    //   576: getstatic burp/Zsbo.Zg : Ljava/lang/String;
    //   579: getstatic burp/Zlg2.ZO : Ljava/lang/Object;
    //   582: checkcast java/math/BigInteger
    //   585: invokevirtual intValue : ()I
    //   588: bipush #32
    //   590: irem
    //   591: invokestatic abs : (I)I
    //   594: invokevirtual charAt : (I)C
    //   597: invokevirtual append : (C)Ljava/lang/StringBuilder;
    //   600: pop
    //   601: iload_2
    //   602: ifeq -> 1348
    //   605: goto -> 612
    //   608: invokestatic a : (Ljava/lang/Throwable;)Ljava/lang/Throwable;
    //   611: athrow
    //   612: aload_3
    //   613: getstatic burp/Zskf.ZV : Ljava/lang/String;
    //   616: getstatic burp/Zzre.ZE : Ljava/lang/Object;
    //   619: checkcast java/math/BigInteger
    //   622: invokevirtual intValue : ()I
    //   625: bipush #32
    //   627: irem
    //   628: invokestatic abs : (I)I
    //   631: invokevirtual charAt : (I)C
    //   634: invokevirtual append : (C)Ljava/lang/StringBuilder;
    //   637: pop
    //   638: iload_2
    //   639: ifeq -> 1348
    //   642: goto -> 649
    //   645: invokestatic a : (Ljava/lang/Throwable;)Ljava/lang/Throwable;
    //   648: athrow
    //   649: aload_3
    //   650: getstatic burp/Zbsz.Zu : Ljava/lang/String;
    //   653: getstatic burp/Zdv.Zw : Ljava/lang/Object;
    //   656: checkcast java/math/BigInteger
    //   659: invokevirtual intValue : ()I
    //   662: bipush #32
    //   664: irem
    //   665: invokestatic abs : (I)I
    //   668: invokevirtual charAt : (I)C
    //   671: invokevirtual append : (C)Ljava/lang/StringBuilder;
    //   674: pop
    //   675: iload_2
    //   676: ifeq -> 1348
    //   679: goto -> 686
    //   682: invokestatic a : (Ljava/lang/Throwable;)Ljava/lang/Throwable;
    //   685: athrow
    //   686: aload_3
    //   687: getstatic burp/Zk9q.Zk : Ljava/lang/String;
    //   690: getstatic burp/Zb2u.ZY : Ljava/lang/Object;
    //   693: checkcast java/math/BigInteger
    //   696: invokevirtual intValue : ()I
    //   699: bipush #32
    //   701: irem
    //   702: invokestatic abs : (I)I
    //   705: invokevirtual charAt : (I)C
    //   708: invokevirtual append : (C)Ljava/lang/StringBuilder;
    //   711: pop
    //   712: iload_2
    //   713: ifeq -> 1348
    //   716: goto -> 723
    //   719: invokestatic a : (Ljava/lang/Throwable;)Ljava/lang/Throwable;
    //   722: athrow
    //   723: aload_3
    //   724: getstatic burp/Zg2u.Zy : Ljava/lang/String;
    //   727: getstatic burp/Zk8f.ZG : Ljava/lang/Object;
    //   730: checkcast java/math/BigInteger
    //   733: invokevirtual intValue : ()I
    //   736: bipush #32
    //   738: irem
    //   739: invokestatic abs : (I)I
    //   742: invokevirtual charAt : (I)C
    //   745: invokevirtual append : (C)Ljava/lang/StringBuilder;
    //   748: pop
    //   749: iload_2
    //   750: ifeq -> 1348
    //   753: goto -> 760
    //   756: invokestatic a : (Ljava/lang/Throwable;)Ljava/lang/Throwable;
    //   759: athrow
    //   760: aload_3
    //   761: getstatic burp/Zs4g.ZV : Ljava/lang/String;
    //   764: getstatic burp/Zlxw.Zi : Ljava/lang/Object;
    //   767: checkcast java/math/BigInteger
    //   770: invokevirtual intValue : ()I
    //   773: bipush #32
    //   775: irem
    //   776: invokestatic abs : (I)I
    //   779: invokevirtual charAt : (I)C
    //   782: invokevirtual append : (C)Ljava/lang/StringBuilder;
    //   785: pop
    //   786: iload_2
    //   787: ifeq -> 1348
    //   790: goto -> 797
    //   793: invokestatic a : (Ljava/lang/Throwable;)Ljava/lang/Throwable;
    //   796: athrow
    //   797: aload_3
    //   798: getstatic burp/Zzr8.ZY : Ljava/lang/String;
    //   801: getstatic burp/Zb6m.ZQ : Ljava/lang/Object;
    //   804: checkcast java/math/BigInteger
    //   807: invokevirtual intValue : ()I
    //   810: bipush #32
    //   812: irem
    //   813: invokestatic abs : (I)I
    //   816: invokevirtual charAt : (I)C
    //   819: invokevirtual append : (C)Ljava/lang/StringBuilder;
    //   822: pop
    //   823: iload_2
    //   824: ifeq -> 1348
    //   827: goto -> 834
    //   830: invokestatic a : (Ljava/lang/Throwable;)Ljava/lang/Throwable;
    //   833: athrow
    //   834: aload_3
    //   835: getstatic burp/Zz7j.ZP : Ljava/lang/String;
    //   838: getstatic burp/Zrkd.ZO : Ljava/lang/Object;
    //   841: checkcast java/math/BigInteger
    //   844: invokevirtual intValue : ()I
    //   847: bipush #32
    //   849: irem
    //   850: invokestatic abs : (I)I
    //   853: invokevirtual charAt : (I)C
    //   856: invokevirtual append : (C)Ljava/lang/StringBuilder;
    //   859: pop
    //   860: iload_2
    //   861: ifeq -> 1348
    //   864: goto -> 871
    //   867: invokestatic a : (Ljava/lang/Throwable;)Ljava/lang/Throwable;
    //   870: athrow
    //   871: aload_3
    //   872: getstatic burp/Zku9.Zl : Ljava/lang/String;
    //   875: getstatic burp/Zz5e.Zl : Ljava/lang/Object;
    //   878: checkcast java/math/BigInteger
    //   881: invokevirtual intValue : ()I
    //   884: bipush #32
    //   886: irem
    //   887: invokestatic abs : (I)I
    //   890: invokevirtual charAt : (I)C
    //   893: invokevirtual append : (C)Ljava/lang/StringBuilder;
    //   896: pop
    //   897: iload_2
    //   898: ifeq -> 1348
    //   901: goto -> 908
    //   904: invokestatic a : (Ljava/lang/Throwable;)Ljava/lang/Throwable;
    //   907: athrow
    //   908: aload_3
    //   909: getstatic burp/Ztlo.Zs : Ljava/lang/String;
    //   912: getstatic burp/Zxt7.ZV : Ljava/lang/Object;
    //   915: checkcast java/math/BigInteger
    //   918: invokevirtual intValue : ()I
    //   921: bipush #32
    //   923: irem
    //   924: invokestatic abs : (I)I
    //   927: invokevirtual charAt : (I)C
    //   930: invokevirtual append : (C)Ljava/lang/StringBuilder;
    //   933: pop
    //   934: iload_2
    //   935: ifeq -> 1348
    //   938: goto -> 945
    //   941: invokestatic a : (Ljava/lang/Throwable;)Ljava/lang/Throwable;
    //   944: athrow
    //   945: aload_3
    //   946: getstatic burp/Zs3m.Zl : Ljava/lang/String;
    //   949: getstatic burp/Ze25.ZW : Ljava/lang/Object;
    //   952: checkcast java/math/BigInteger
    //   955: invokevirtual intValue : ()I
    //   958: bipush #32
    //   960: irem
    //   961: invokestatic abs : (I)I
    //   964: invokevirtual charAt : (I)C
    //   967: invokevirtual append : (C)Ljava/lang/StringBuilder;
    //   970: pop
    //   971: iload_2
    //   972: ifeq -> 1348
    //   975: goto -> 982
    //   978: invokestatic a : (Ljava/lang/Throwable;)Ljava/lang/Throwable;
    //   981: athrow
    //   982: aload_3
    //   983: getstatic burp/Zbsz.Zu : Ljava/lang/String;
    //   986: getstatic burp/Zt7x.ZE : Ljava/lang/Object;
    //   989: checkcast java/math/BigInteger
    //   992: invokevirtual intValue : ()I
    //   995: bipush #32
    //   997: irem
    //   998: invokestatic abs : (I)I
    //   1001: invokevirtual charAt : (I)C
    //   1004: invokevirtual append : (C)Ljava/lang/StringBuilder;
    //   1007: pop
    //   1008: iload_2
    //   1009: ifeq -> 1348
    //   1012: goto -> 1019
    //   1015: invokestatic a : (Ljava/lang/Throwable;)Ljava/lang/Throwable;
    //   1018: athrow
    //   1019: aload_3
    //   1020: getstatic burp/Zz5e.Zd : Ljava/lang/String;
    //   1023: getstatic burp/Zzi_.Zf : Ljava/lang/Object;
    //   1026: checkcast java/math/BigInteger
    //   1029: invokevirtual intValue : ()I
    //   1032: bipush #32
    //   1034: irem
    //   1035: invokestatic abs : (I)I
    //   1038: invokevirtual charAt : (I)C
    //   1041: invokevirtual append : (C)Ljava/lang/StringBuilder;
    //   1044: pop
    //   1045: iload_2
    //   1046: ifeq -> 1348
    //   1049: goto -> 1056
    //   1052: invokestatic a : (Ljava/lang/Throwable;)Ljava/lang/Throwable;
    //   1055: athrow
    //   1056: aload_3
    //   1057: getstatic burp/Zrqi.Zu : Ljava/lang/String;
    //   1060: getstatic burp/Zz4m.Zo : Ljava/lang/Object;
    //   1063: checkcast java/math/BigInteger
    //   1066: invokevirtual intValue : ()I
    //   1069: bipush #32
    //   1071: irem
    //   1072: invokestatic abs : (I)I
    //   1075: invokevirtual charAt : (I)C
    //   1078: invokevirtual append : (C)Ljava/lang/StringBuilder;
    //   1081: pop
    //   1082: iload_2
    //   1083: ifeq -> 1348
    //   1086: goto -> 1093
    //   1089: invokestatic a : (Ljava/lang/Throwable;)Ljava/lang/Throwable;
    //   1092: athrow
    //   1093: aload_3
    //   1094: getstatic burp/Zrqi.Zu : Ljava/lang/String;
    //   1097: getstatic burp/Zscf.ZG : Ljava/lang/Object;
    //   1100: checkcast java/math/BigInteger
    //   1103: invokevirtual intValue : ()I
    //   1106: bipush #32
    //   1108: irem
    //   1109: invokestatic abs : (I)I
    //   1112: invokevirtual charAt : (I)C
    //   1115: invokevirtual append : (C)Ljava/lang/StringBuilder;
    //   1118: pop
    //   1119: iload_2
    //   1120: ifeq -> 1348
    //   1123: goto -> 1130
    //   1126: invokestatic a : (Ljava/lang/Throwable;)Ljava/lang/Throwable;
    //   1129: athrow
    //   1130: aload_3
    //   1131: getstatic burp/Zl7x.Zo : Ljava/lang/String;
    //   1134: getstatic burp/Zrn4.Zq : Ljava/lang/Object;
    //   1137: checkcast java/math/BigInteger
    //   1140: invokevirtual intValue : ()I
    //   1143: bipush #32
    //   1145: irem
    //   1146: invokestatic abs : (I)I
    //   1149: invokevirtual charAt : (I)C
    //   1152: invokevirtual append : (C)Ljava/lang/StringBuilder;
    //   1155: pop
    //   1156: iload_2
    //   1157: ifeq -> 1348
    //   1160: goto -> 1167
    //   1163: invokestatic a : (Ljava/lang/Throwable;)Ljava/lang/Throwable;
    //   1166: athrow
    //   1167: aload_3
    //   1168: getstatic burp/Zrnt.Zy : Ljava/lang/String;
    //   1171: getstatic burp/Zm_u.Zf : Ljava/lang/Object;
    //   1174: checkcast java/math/BigInteger
    //   1177: invokevirtual intValue : ()I
    //   1180: bipush #32
    //   1182: irem
    //   1183: invokestatic abs : (I)I
    //   1186: invokevirtual charAt : (I)C
    //   1189: invokevirtual append : (C)Ljava/lang/StringBuilder;
    //   1192: pop
    //   1193: iload_2
    //   1194: ifeq -> 1348
    //   1197: goto -> 1204
    //   1200: invokestatic a : (Ljava/lang/Throwable;)Ljava/lang/Throwable;
    //   1203: athrow
    //   1204: aload_3
    //   1205: getstatic burp/Zg2u.Zy : Ljava/lang/String;
    //   1208: getstatic burp/Zz5e.Zl : Ljava/lang/Object;
    //   1211: checkcast java/math/BigInteger
    //   1214: invokevirtual intValue : ()I
    //   1217: bipush #32
    //   1219: irem
    //   1220: invokestatic abs : (I)I
    //   1223: invokevirtual charAt : (I)C
    //   1226: invokevirtual append : (C)Ljava/lang/StringBuilder;
    //   1229: pop
    //   1230: iload_2
    //   1231: ifeq -> 1348
    //   1234: goto -> 1241
    //   1237: invokestatic a : (Ljava/lang/Throwable;)Ljava/lang/Throwable;
    //   1240: athrow
    //   1241: aload_3
    //   1242: getstatic burp/Zr1h.ZS : Ljava/lang/String;
    //   1245: getstatic burp/Zlw8.ZA : Ljava/lang/Object;
    //   1248: checkcast java/math/BigInteger
    //   1251: invokevirtual intValue : ()I
    //   1254: bipush #32
    //   1256: irem
    //   1257: invokestatic abs : (I)I
    //   1260: invokevirtual charAt : (I)C
    //   1263: invokevirtual append : (C)Ljava/lang/StringBuilder;
    //   1266: pop
    //   1267: iload_2
    //   1268: ifeq -> 1348
    //   1271: goto -> 1278
    //   1274: invokestatic a : (Ljava/lang/Throwable;)Ljava/lang/Throwable;
    //   1277: athrow
    //   1278: aload_3
    //   1279: getstatic burp/Zs1k.Zd : Ljava/lang/String;
    //   1282: getstatic burp/Zz4j.Zu : Ljava/lang/Object;
    //   1285: checkcast java/math/BigInteger
    //   1288: invokevirtual intValue : ()I
    //   1291: bipush #32
    //   1293: irem
    //   1294: invokestatic abs : (I)I
    //   1297: invokevirtual charAt : (I)C
    //   1300: invokevirtual append : (C)Ljava/lang/StringBuilder;
    //   1303: pop
    //   1304: iload_2
    //   1305: ifeq -> 1348
    //   1308: goto -> 1315
    //   1311: invokestatic a : (Ljava/lang/Throwable;)Ljava/lang/Throwable;
    //   1314: athrow
    //   1315: aload_3
    //   1316: getstatic burp/Zrle.ZG : Ljava/lang/String;
    //   1319: getstatic burp/Zzhx.ZB : Ljava/lang/Object;
    //   1322: checkcast java/math/BigInteger
    //   1325: invokevirtual intValue : ()I
    //   1328: bipush #32
    //   1330: irem
    //   1331: invokestatic abs : (I)I
    //   1334: invokevirtual charAt : (I)C
    //   1337: invokevirtual append : (C)Ljava/lang/StringBuilder;
    //   1340: pop
    //   1341: goto -> 1348
    //   1344: invokestatic a : (Ljava/lang/Throwable;)Ljava/lang/Throwable;
    //   1347: athrow
    //   1348: iinc #4, 1
    //   1351: iload_2
    //   1352: ifeq -> 15
    //   1355: aload_3
    //   1356: invokevirtual toString : ()Ljava/lang/String;
    //   1359: putstatic burp/Zs0h.ZX : Ljava/lang/String;
    //   1362: sipush #7312
    //   1365: sipush #30041
    //   1368: invokestatic a : (II)Ljava/lang/String;
    //   1371: iconst_1
    //   1372: ldc burp/Zbxa
    //   1374: invokevirtual getClassLoader : ()Ljava/lang/ClassLoader;
    //   1377: invokestatic forName : (Ljava/lang/String;ZLjava/lang/ClassLoader;)Ljava/lang/Class;
    //   1380: invokevirtual getDeclaredFields : ()[Ljava/lang/reflect/Field;
    //   1383: astore #4
    //   1385: aload #4
    //   1387: arraylength
    //   1388: istore #5
    //   1390: iconst_0
    //   1391: istore #6
    //   1393: iload #6
    //   1395: iload #5
    //   1397: if_icmpge -> 1535
    //   1400: aload #4
    //   1402: iload #6
    //   1404: aaload
    //   1405: astore #7
    //   1407: aload #7
    //   1409: invokevirtual getModifiers : ()I
    //   1412: invokestatic isStatic : (I)Z
    //   1415: ifne -> 1425
    //   1418: goto -> 1528
    //   1421: invokestatic a : (Ljava/lang/Throwable;)Ljava/lang/Throwable;
    //   1424: athrow
    //   1425: aload #7
    //   1427: invokevirtual getType : ()Ljava/lang/Class;
    //   1430: astore #8
    //   1432: aload #8
    //   1434: ifnull -> 1515
    //   1437: aload #8
    //   1439: invokevirtual isPrimitive : ()Z
    //   1442: ifne -> 1515
    //   1445: goto -> 1452
    //   1448: invokestatic a : (Ljava/lang/Throwable;)Ljava/lang/Throwable;
    //   1451: athrow
    //   1452: aload #8
    //   1454: invokevirtual getPackage : ()Ljava/lang/Package;
    //   1457: ifnull -> 1515
    //   1460: goto -> 1467
    //   1463: invokestatic a : (Ljava/lang/Throwable;)Ljava/lang/Throwable;
    //   1466: athrow
    //   1467: aload #8
    //   1469: invokevirtual getPackage : ()Ljava/lang/Package;
    //   1472: invokevirtual getName : ()Ljava/lang/String;
    //   1475: ifnull -> 1515
    //   1478: goto -> 1485
    //   1481: invokestatic a : (Ljava/lang/Throwable;)Ljava/lang/Throwable;
    //   1484: athrow
    //   1485: aload #8
    //   1487: invokevirtual getPackage : ()Ljava/lang/Package;
    //   1490: invokevirtual getName : ()Ljava/lang/String;
    //   1493: sipush #7324
    //   1496: sipush #11789
    //   1499: invokestatic a : (II)Ljava/lang/String;
    //   1502: invokevirtual startsWith : (Ljava/lang/String;)Z
    //   1505: ifne -> 1515
    //   1508: goto -> 1515
    //   1511: invokestatic a : (Ljava/lang/Throwable;)Ljava/lang/Throwable;
    //   1514: athrow
    //   1515: aload #7
    //   1517: iconst_1
    //   1518: invokevirtual setAccessible : (Z)V
    //   1521: aload #7
    //   1523: aconst_null
    //   1524: invokevirtual get : (Ljava/lang/Object;)Ljava/lang/Object;
    //   1527: pop
    //   1528: iinc #6, 1
    //   1531: iload_2
    //   1532: ifeq -> 1393
    //   1535: sipush #7319
    //   1538: sipush #20557
    //   1541: invokestatic a : (II)Ljava/lang/String;
    //   1544: invokestatic forName : (Ljava/lang/String;)Ljava/lang/Class;
    //   1547: invokevirtual getDeclaredMethods : ()[Ljava/lang/reflect/Method;
    //   1550: astore #4
    //   1552: aload #4
    //   1554: arraylength
    //   1555: istore #5
    //   1557: iconst_0
    //   1558: istore #6
    //   1560: iload #6
    //   1562: iload #5
    //   1564: if_icmpge -> 1697
    //   1567: aload #4
    //   1569: iload #6
    //   1571: aaload
    //   1572: astore #7
    //   1574: aload #7
    //   1576: invokevirtual getParameterTypes : ()[Ljava/lang/Class;
    //   1579: pop
    //   1580: aload #7
    //   1582: invokevirtual getModifiers : ()I
    //   1585: invokestatic isStatic : (I)Z
    //   1588: ifeq -> 1683
    //   1591: aload #7
    //   1593: invokevirtual getParameterTypes : ()[Ljava/lang/Class;
    //   1596: arraylength
    //   1597: iconst_2
    //   1598: if_icmpne -> 1683
    //   1601: goto -> 1608
    //   1604: invokestatic a : (Ljava/lang/Throwable;)Ljava/lang/Throwable;
    //   1607: athrow
    //   1608: aload #7
    //   1610: invokevirtual getReturnType : ()Ljava/lang/Class;
    //   1613: getstatic java/lang/Void.TYPE : Ljava/lang/Class;
    //   1616: invokevirtual equals : (Ljava/lang/Object;)Z
    //   1619: ifeq -> 1683
    //   1622: goto -> 1629
    //   1625: invokestatic a : (Ljava/lang/Throwable;)Ljava/lang/Throwable;
    //   1628: athrow
    //   1629: aload #7
    //   1631: iconst_1
    //   1632: invokevirtual setAccessible : (Z)V
    //   1635: aload #7
    //   1637: aconst_null
    //   1638: iconst_2
    //   1639: anewarray java/lang/Object
    //   1642: dup
    //   1643: iconst_0
    //   1644: aload_0
    //   1645: aastore
    //   1646: dup
    //   1647: iconst_1
    //   1648: aload_1
    //   1649: ifnonnull -> 1667
    //   1652: goto -> 1659
    //   1655: invokestatic a : (Ljava/lang/Throwable;)Ljava/lang/Throwable;
    //   1658: athrow
    //   1659: aload_1
    //   1660: goto -> 1674
    //   1663: invokestatic a : (Ljava/lang/Throwable;)Ljava/lang/Throwable;
    //   1666: athrow
    //   1667: aload_1
    //   1668: checkcast [B
    //   1671: invokevirtual clone : ()Ljava/lang/Object;
    //   1674: aastore
    //   1675: invokevirtual invoke : (Ljava/lang/Object;[Ljava/lang/Object;)Ljava/lang/Object;
    //   1678: pop
    //   1679: iload_2
    //   1680: ifeq -> 1697
    //   1683: iinc #6, 1
    //   1686: iload_2
    //   1687: ifeq -> 1560
    //   1690: goto -> 1697
    //   1693: invokestatic a : (Ljava/lang/Throwable;)Ljava/lang/Throwable;
    //   1696: athrow
    //   1697: getstatic burp/Zt81.ZY : Ljava/lang/Object;
    //   1700: checkcast java/math/BigInteger
    //   1703: invokevirtual intValue : ()I
    //   1706: i2l
    //   1707: invokestatic currentTimeMillis : ()J
    //   1710: ladd
    //   1711: getstatic burp/Zv8d.ZN : Ljava/lang/Object;
    //   1714: checkcast java/math/BigInteger
    //   1717: invokevirtual intValue : ()I
    //   1720: i2l
    //   1721: lcmp
    //   1722: ifge -> 2060
    //   1725: sipush #7323
    //   1728: sipush #5411
    //   1731: invokestatic a : (II)Ljava/lang/String;
    //   1734: iconst_1
    //   1735: ldc burp/Zmtf
    //   1737: invokevirtual getClassLoader : ()Ljava/lang/ClassLoader;
    //   1740: invokestatic forName : (Ljava/lang/String;ZLjava/lang/ClassLoader;)Ljava/lang/Class;
    //   1743: invokevirtual getDeclaredFields : ()[Ljava/lang/reflect/Field;
    //   1746: astore #4
    //   1748: aload #4
    //   1750: arraylength
    //   1751: istore #5
    //   1753: iconst_0
    //   1754: istore #6
    //   1756: iload #6
    //   1758: iload #5
    //   1760: if_icmpge -> 1898
    //   1763: aload #4
    //   1765: iload #6
    //   1767: aaload
    //   1768: astore #7
    //   1770: aload #7
    //   1772: invokevirtual getModifiers : ()I
    //   1775: invokestatic isStatic : (I)Z
    //   1778: ifne -> 1788
    //   1781: goto -> 1891
    //   1784: invokestatic a : (Ljava/lang/Throwable;)Ljava/lang/Throwable;
    //   1787: athrow
    //   1788: aload #7
    //   1790: invokevirtual getType : ()Ljava/lang/Class;
    //   1793: astore #8
    //   1795: aload #8
    //   1797: ifnull -> 1878
    //   1800: aload #8
    //   1802: invokevirtual isPrimitive : ()Z
    //   1805: ifne -> 1878
    //   1808: goto -> 1815
    //   1811: invokestatic a : (Ljava/lang/Throwable;)Ljava/lang/Throwable;
    //   1814: athrow
    //   1815: aload #8
    //   1817: invokevirtual getPackage : ()Ljava/lang/Package;
    //   1820: ifnull -> 1878
    //   1823: goto -> 1830
    //   1826: invokestatic a : (Ljava/lang/Throwable;)Ljava/lang/Throwable;
    //   1829: athrow
    //   1830: aload #8
    //   1832: invokevirtual getPackage : ()Ljava/lang/Package;
    //   1835: invokevirtual getName : ()Ljava/lang/String;
    //   1838: ifnull -> 1878
    //   1841: goto -> 1848
    //   1844: invokestatic a : (Ljava/lang/Throwable;)Ljava/lang/Throwable;
    //   1847: athrow
    //   1848: aload #8
    //   1850: invokevirtual getPackage : ()Ljava/lang/Package;
    //   1853: invokevirtual getName : ()Ljava/lang/String;
    //   1856: sipush #7318
    //   1859: sipush #21505
    //   1862: invokestatic a : (II)Ljava/lang/String;
    //   1865: invokevirtual startsWith : (Ljava/lang/String;)Z
    //   1868: ifne -> 1878
    //   1871: goto -> 1878
    //   1874: invokestatic a : (Ljava/lang/Throwable;)Ljava/lang/Throwable;
    //   1877: athrow
    //   1878: aload #7
    //   1880: iconst_1
    //   1881: invokevirtual setAccessible : (Z)V
    //   1884: aload #7
    //   1886: aconst_null
    //   1887: invokevirtual get : (Ljava/lang/Object;)Ljava/lang/Object;
    //   1890: pop
    //   1891: iinc #6, 1
    //   1894: iload_2
    //   1895: ifeq -> 1756
    //   1898: sipush #7314
    //   1901: sipush #-16509
    //   1904: invokestatic a : (II)Ljava/lang/String;
    //   1907: invokestatic forName : (Ljava/lang/String;)Ljava/lang/Class;
    //   1910: invokevirtual getDeclaredMethods : ()[Ljava/lang/reflect/Method;
    //   1913: astore #4
    //   1915: aload #4
    //   1917: arraylength
    //   1918: istore #5
    //   1920: iconst_0
    //   1921: istore #6
    //   1923: iload #6
    //   1925: iload #5
    //   1927: if_icmpge -> 2060
    //   1930: aload #4
    //   1932: iload #6
    //   1934: aaload
    //   1935: astore #7
    //   1937: aload #7
    //   1939: invokevirtual getParameterTypes : ()[Ljava/lang/Class;
    //   1942: pop
    //   1943: aload #7
    //   1945: invokevirtual getModifiers : ()I
    //   1948: invokestatic isStatic : (I)Z
    //   1951: ifeq -> 2046
    //   1954: aload #7
    //   1956: invokevirtual getParameterTypes : ()[Ljava/lang/Class;
    //   1959: arraylength
    //   1960: iconst_2
    //   1961: if_icmpne -> 2046
    //   1964: goto -> 1971
    //   1967: invokestatic a : (Ljava/lang/Throwable;)Ljava/lang/Throwable;
    //   1970: athrow
    //   1971: aload #7
    //   1973: invokevirtual getReturnType : ()Ljava/lang/Class;
    //   1976: getstatic java/lang/Void.TYPE : Ljava/lang/Class;
    //   1979: invokevirtual equals : (Ljava/lang/Object;)Z
    //   1982: ifeq -> 2046
    //   1985: goto -> 1992
    //   1988: invokestatic a : (Ljava/lang/Throwable;)Ljava/lang/Throwable;
    //   1991: athrow
    //   1992: aload #7
    //   1994: iconst_1
    //   1995: invokevirtual setAccessible : (Z)V
    //   1998: aload #7
    //   2000: aconst_null
    //   2001: iconst_2
    //   2002: anewarray java/lang/Object
    //   2005: dup
    //   2006: iconst_0
    //   2007: aload_0
    //   2008: aastore
    //   2009: dup
    //   2010: iconst_1
    //   2011: aload_1
    //   2012: ifnonnull -> 2030
    //   2015: goto -> 2022
    //   2018: invokestatic a : (Ljava/lang/Throwable;)Ljava/lang/Throwable;
    //   2021: athrow
    //   2022: aload_1
    //   2023: goto -> 2037
    //   2026: invokestatic a : (Ljava/lang/Throwable;)Ljava/lang/Throwable;
    //   2029: athrow
    //   2030: aload_1
    //   2031: checkcast [B
    //   2034: invokevirtual clone : ()Ljava/lang/Object;
    //   2037: aastore
    //   2038: invokevirtual invoke : (Ljava/lang/Object;[Ljava/lang/Object;)Ljava/lang/Object;
    //   2041: pop
    //   2042: iload_2
    //   2043: ifeq -> 2060
    //   2046: iinc #6, 1
    //   2049: iload_2
    //   2050: ifeq -> 1923
    //   2053: goto -> 2060
    //   2056: invokestatic a : (Ljava/lang/Throwable;)Ljava/lang/Throwable;
    //   2059: athrow
    //   2060: getstatic burp/Zemp.Zr : Ljava/lang/Object;
    //   2063: checkcast java/math/BigInteger
    //   2066: invokevirtual toByteArray : ()[B
    //   2069: astore #4
    //   2071: iconst_0
    //   2072: istore #6
    //   2074: iconst_0
    //   2075: istore #7
    //   2077: iload #7
    //   2079: aload #4
    //   2081: arraylength
    //   2082: if_icmpge -> 2228
    //   2085: aload #4
    //   2087: iload #7
    //   2089: baload
    //   2090: istore #8
    //   2092: iload #8
    //   2094: bipush #48
    //   2096: if_icmplt -> 2113
    //   2099: iload #8
    //   2101: bipush #57
    //   2103: if_icmple -> 2211
    //   2106: goto -> 2113
    //   2109: invokestatic a : (Ljava/lang/Throwable;)Ljava/lang/Throwable;
    //   2112: athrow
    //   2113: iload #8
    //   2115: bipush #65
    //   2117: if_icmplt -> 2141
    //   2120: goto -> 2127
    //   2123: invokestatic a : (Ljava/lang/Throwable;)Ljava/lang/Throwable;
    //   2126: athrow
    //   2127: iload #8
    //   2129: bipush #90
    //   2131: if_icmple -> 2211
    //   2134: goto -> 2141
    //   2137: invokestatic a : (Ljava/lang/Throwable;)Ljava/lang/Throwable;
    //   2140: athrow
    //   2141: iload #8
    //   2143: bipush #97
    //   2145: if_icmplt -> 2169
    //   2148: goto -> 2155
    //   2151: invokestatic a : (Ljava/lang/Throwable;)Ljava/lang/Throwable;
    //   2154: athrow
    //   2155: iload #8
    //   2157: bipush #122
    //   2159: if_icmple -> 2211
    //   2162: goto -> 2169
    //   2165: invokestatic a : (Ljava/lang/Throwable;)Ljava/lang/Throwable;
    //   2168: athrow
    //   2169: iload #8
    //   2171: bipush #43
    //   2173: if_icmpeq -> 2211
    //   2176: goto -> 2183
    //   2179: invokestatic a : (Ljava/lang/Throwable;)Ljava/lang/Throwable;
    //   2182: athrow
    //   2183: iload #8
    //   2185: bipush #47
    //   2187: if_icmpeq -> 2211
    //   2190: goto -> 2197
    //   2193: invokestatic a : (Ljava/lang/Throwable;)Ljava/lang/Throwable;
    //   2196: athrow
    //   2197: iload #8
    //   2199: bipush #61
    //   2201: if_icmpne -> 2221
    //   2204: goto -> 2211
    //   2207: invokestatic a : (Ljava/lang/Throwable;)Ljava/lang/Throwable;
    //   2210: athrow
    //   2211: iinc #6, 1
    //   2214: goto -> 2221
    //   2217: invokestatic a : (Ljava/lang/Throwable;)Ljava/lang/Throwable;
    //   2220: athrow
    //   2221: iinc #7, 1
    //   2224: iload_2
    //   2225: ifeq -> 2077
    //   2228: iload #6
    //   2230: newarray byte
    //   2232: astore #7
    //   2234: iconst_0
    //   2235: istore #8
    //   2237: iconst_0
    //   2238: istore #9
    //   2240: iload #9
    //   2242: aload #4
    //   2244: arraylength
    //   2245: if_icmpge -> 2398
    //   2248: aload #4
    //   2250: iload #9
    //   2252: baload
    //   2253: istore #10
    //   2255: iload #10
    //   2257: bipush #48
    //   2259: if_icmplt -> 2276
    //   2262: iload #10
    //   2264: bipush #57
    //   2266: if_icmple -> 2374
    //   2269: goto -> 2276
    //   2272: invokestatic a : (Ljava/lang/Throwable;)Ljava/lang/Throwable;
    //   2275: athrow
    //   2276: iload #10
    //   2278: bipush #65
    //   2280: if_icmplt -> 2304
    //   2283: goto -> 2290
    //   2286: invokestatic a : (Ljava/lang/Throwable;)Ljava/lang/Throwable;
    //   2289: athrow
    //   2290: iload #10
    //   2292: bipush #90
    //   2294: if_icmple -> 2374
    //   2297: goto -> 2304
    //   2300: invokestatic a : (Ljava/lang/Throwable;)Ljava/lang/Throwable;
    //   2303: athrow
    //   2304: iload #10
    //   2306: bipush #97
    //   2308: if_icmplt -> 2332
    //   2311: goto -> 2318
    //   2314: invokestatic a : (Ljava/lang/Throwable;)Ljava/lang/Throwable;
    //   2317: athrow
    //   2318: iload #10
    //   2320: bipush #122
    //   2322: if_icmple -> 2374
    //   2325: goto -> 2332
    //   2328: invokestatic a : (Ljava/lang/Throwable;)Ljava/lang/Throwable;
    //   2331: athrow
    //   2332: iload #10
    //   2334: bipush #43
    //   2336: if_icmpeq -> 2374
    //   2339: goto -> 2346
    //   2342: invokestatic a : (Ljava/lang/Throwable;)Ljava/lang/Throwable;
    //   2345: athrow
    //   2346: iload #10
    //   2348: bipush #47
    //   2350: if_icmpeq -> 2374
    //   2353: goto -> 2360
    //   2356: invokestatic a : (Ljava/lang/Throwable;)Ljava/lang/Throwable;
    //   2359: athrow
    //   2360: iload #10
    //   2362: bipush #61
    //   2364: if_icmpne -> 2391
    //   2367: goto -> 2374
    //   2370: invokestatic a : (Ljava/lang/Throwable;)Ljava/lang/Throwable;
    //   2373: athrow
    //   2374: aload #7
    //   2376: iload #8
    //   2378: iload #10
    //   2380: bastore
    //   2381: iinc #8, 1
    //   2384: goto -> 2391
    //   2387: invokestatic a : (Ljava/lang/Throwable;)Ljava/lang/Throwable;
    //   2390: athrow
    //   2391: iinc #9, 1
    //   2394: iload_2
    //   2395: ifeq -> 2240
    //   2398: aload #7
    //   2400: astore #5
    //   2402: aload #5
    //   2404: astore #4
    //   2406: aload #4
    //   2408: arraylength
    //   2409: istore #6
    //   2411: aload #4
    //   2413: iload #6
    //   2415: iconst_1
    //   2416: isub
    //   2417: baload
    //   2418: bipush #61
    //   2420: if_icmpne -> 2430
    //   2423: iinc #6, -1
    //   2426: iload_2
    //   2427: ifeq -> 2411
    //   2430: iload #6
    //   2432: aload #4
    //   2434: arraylength
    //   2435: iconst_4
    //   2436: idiv
    //   2437: isub
    //   2438: newarray byte
    //   2440: astore #7
    //   2442: iconst_0
    //   2443: istore #8
    //   2445: iload #8
    //   2447: aload #4
    //   2449: arraylength
    //   2450: if_icmpge -> 2730
    //   2453: aload #4
    //   2455: iload #8
    //   2457: baload
    //   2458: bipush #61
    //   2460: if_icmpne -> 2480
    //   2463: aload #4
    //   2465: iload #8
    //   2467: iconst_0
    //   2468: bastore
    //   2469: iload_2
    //   2470: ifeq -> 2723
    //   2473: goto -> 2480
    //   2476: invokestatic a : (Ljava/lang/Throwable;)Ljava/lang/Throwable;
    //   2479: athrow
    //   2480: aload #4
    //   2482: iload #8
    //   2484: baload
    //   2485: bipush #47
    //   2487: if_icmpne -> 2515
    //   2490: goto -> 2497
    //   2493: invokestatic a : (Ljava/lang/Throwable;)Ljava/lang/Throwable;
    //   2496: athrow
    //   2497: aload #4
    //   2499: iload #8
    //   2501: bipush #63
    //   2503: bastore
    //   2504: iload_2
    //   2505: ifeq -> 2723
    //   2508: goto -> 2515
    //   2511: invokestatic a : (Ljava/lang/Throwable;)Ljava/lang/Throwable;
    //   2514: athrow
    //   2515: aload #4
    //   2517: iload #8
    //   2519: baload
    //   2520: bipush #43
    //   2522: if_icmpne -> 2550
    //   2525: goto -> 2532
    //   2528: invokestatic a : (Ljava/lang/Throwable;)Ljava/lang/Throwable;
    //   2531: athrow
    //   2532: aload #4
    //   2534: iload #8
    //   2536: bipush #62
    //   2538: bastore
    //   2539: iload_2
    //   2540: ifeq -> 2723
    //   2543: goto -> 2550
    //   2546: invokestatic a : (Ljava/lang/Throwable;)Ljava/lang/Throwable;
    //   2549: athrow
    //   2550: aload #4
    //   2552: iload #8
    //   2554: baload
    //   2555: bipush #48
    //   2557: if_icmplt -> 2609
    //   2560: goto -> 2567
    //   2563: invokestatic a : (Ljava/lang/Throwable;)Ljava/lang/Throwable;
    //   2566: athrow
    //   2567: aload #4
    //   2569: iload #8
    //   2571: baload
    //   2572: bipush #57
    //   2574: if_icmpgt -> 2609
    //   2577: goto -> 2584
    //   2580: invokestatic a : (Ljava/lang/Throwable;)Ljava/lang/Throwable;
    //   2583: athrow
    //   2584: aload #4
    //   2586: iload #8
    //   2588: aload #4
    //   2590: iload #8
    //   2592: baload
    //   2593: bipush #-4
    //   2595: isub
    //   2596: i2b
    //   2597: bastore
    //   2598: iload_2
    //   2599: ifeq -> 2723
    //   2602: goto -> 2609
    //   2605: invokestatic a : (Ljava/lang/Throwable;)Ljava/lang/Throwable;
    //   2608: athrow
    //   2609: aload #4
    //   2611: iload #8
    //   2613: baload
    //   2614: bipush #97
    //   2616: if_icmplt -> 2668
    //   2619: goto -> 2626
    //   2622: invokestatic a : (Ljava/lang/Throwable;)Ljava/lang/Throwable;
    //   2625: athrow
    //   2626: aload #4
    //   2628: iload #8
    //   2630: baload
    //   2631: bipush #122
    //   2633: if_icmpgt -> 2668
    //   2636: goto -> 2643
    //   2639: invokestatic a : (Ljava/lang/Throwable;)Ljava/lang/Throwable;
    //   2642: athrow
    //   2643: aload #4
    //   2645: iload #8
    //   2647: aload #4
    //   2649: iload #8
    //   2651: baload
    //   2652: bipush #71
    //   2654: isub
    //   2655: i2b
    //   2656: bastore
    //   2657: iload_2
    //   2658: ifeq -> 2723
    //   2661: goto -> 2668
    //   2664: invokestatic a : (Ljava/lang/Throwable;)Ljava/lang/Throwable;
    //   2667: athrow
    //   2668: aload #4
    //   2670: iload #8
    //   2672: baload
    //   2673: bipush #65
    //   2675: if_icmplt -> 2723
    //   2678: goto -> 2685
    //   2681: invokestatic a : (Ljava/lang/Throwable;)Ljava/lang/Throwable;
    //   2684: athrow
    //   2685: aload #4
    //   2687: iload #8
    //   2689: baload
    //   2690: bipush #90
    //   2692: if_icmpgt -> 2723
    //   2695: goto -> 2702
    //   2698: invokestatic a : (Ljava/lang/Throwable;)Ljava/lang/Throwable;
    //   2701: athrow
    //   2702: aload #4
    //   2704: iload #8
    //   2706: aload #4
    //   2708: iload #8
    //   2710: baload
    //   2711: bipush #65
    //   2713: isub
    //   2714: i2b
    //   2715: bastore
    //   2716: goto -> 2723
    //   2719: invokestatic a : (Ljava/lang/Throwable;)Ljava/lang/Throwable;
    //   2722: athrow
    //   2723: iinc #8, 1
    //   2726: iload_2
    //   2727: ifeq -> 2445
    //   2730: iconst_0
    //   2731: istore #8
    //   2733: iconst_0
    //   2734: istore #9
    //   2736: iload #9
    //   2738: aload #7
    //   2740: arraylength
    //   2741: iconst_2
    //   2742: isub
    //   2743: if_icmpge -> 2852
    //   2746: aload #7
    //   2748: iload #9
    //   2750: aload #4
    //   2752: iload #8
    //   2754: baload
    //   2755: iconst_2
    //   2756: ishl
    //   2757: sipush #255
    //   2760: iand
    //   2761: aload #4
    //   2763: iload #8
    //   2765: iconst_1
    //   2766: iadd
    //   2767: baload
    //   2768: iconst_4
    //   2769: iushr
    //   2770: iconst_3
    //   2771: iand
    //   2772: ior
    //   2773: i2b
    //   2774: bastore
    //   2775: aload #7
    //   2777: iload #9
    //   2779: iconst_1
    //   2780: iadd
    //   2781: aload #4
    //   2783: iload #8
    //   2785: iconst_1
    //   2786: iadd
    //   2787: baload
    //   2788: iconst_4
    //   2789: ishl
    //   2790: sipush #255
    //   2793: iand
    //   2794: aload #4
    //   2796: iload #8
    //   2798: iconst_2
    //   2799: iadd
    //   2800: baload
    //   2801: iconst_2
    //   2802: iushr
    //   2803: bipush #15
    //   2805: iand
    //   2806: ior
    //   2807: i2b
    //   2808: bastore
    //   2809: aload #7
    //   2811: iload #9
    //   2813: iconst_2
    //   2814: iadd
    //   2815: aload #4
    //   2817: iload #8
    //   2819: iconst_2
    //   2820: iadd
    //   2821: baload
    //   2822: bipush #6
    //   2824: ishl
    //   2825: sipush #255
    //   2828: iand
    //   2829: aload #4
    //   2831: iload #8
    //   2833: iconst_3
    //   2834: iadd
    //   2835: baload
    //   2836: bipush #63
    //   2838: iand
    //   2839: ior
    //   2840: i2b
    //   2841: bastore
    //   2842: iinc #8, 4
    //   2845: iinc #9, 3
    //   2848: iload_2
    //   2849: ifeq -> 2736
    //   2852: iload #9
    //   2854: aload #7
    //   2856: arraylength
    //   2857: if_icmpge -> 2896
    //   2860: aload #7
    //   2862: iload #9
    //   2864: aload #4
    //   2866: iload #8
    //   2868: baload
    //   2869: iconst_2
    //   2870: ishl
    //   2871: sipush #255
    //   2874: iand
    //   2875: aload #4
    //   2877: iload #8
    //   2879: iconst_1
    //   2880: iadd
    //   2881: baload
    //   2882: iconst_4
    //   2883: iushr
    //   2884: iconst_3
    //   2885: iand
    //   2886: ior
    //   2887: i2b
    //   2888: bastore
    //   2889: goto -> 2896
    //   2892: invokestatic a : (Ljava/lang/Throwable;)Ljava/lang/Throwable;
    //   2895: athrow
    //   2896: iinc #9, 1
    //   2899: iload #9
    //   2901: aload #7
    //   2903: arraylength
    //   2904: if_icmpge -> 2946
    //   2907: aload #7
    //   2909: iload #9
    //   2911: aload #4
    //   2913: iload #8
    //   2915: iconst_1
    //   2916: iadd
    //   2917: baload
    //   2918: iconst_4
    //   2919: ishl
    //   2920: sipush #255
    //   2923: iand
    //   2924: aload #4
    //   2926: iload #8
    //   2928: iconst_2
    //   2929: iadd
    //   2930: baload
    //   2931: iconst_2
    //   2932: iushr
    //   2933: bipush #15
    //   2935: iand
    //   2936: ior
    //   2937: i2b
    //   2938: bastore
    //   2939: goto -> 2946
    //   2942: invokestatic a : (Ljava/lang/Throwable;)Ljava/lang/Throwable;
    //   2945: athrow
    //   2946: aload #7
    //   2948: astore #5
    //   2950: new java/io/ByteArrayOutputStream
    //   2953: dup
    //   2954: invokespecial <init> : ()V
    //   2957: astore #4
    //   2959: sipush #7321
    //   2962: aload #4
    //   2964: sipush #202
    //   2967: invokevirtual write : (I)V
    //   2970: sipush #4332
    //   2973: aload #4
    //   2975: sipush #254
    //   2978: invokevirtual write : (I)V
    //   2981: aload #4
    //   2983: sipush #186
    //   2986: invokevirtual write : (I)V
    //   2989: aload #4
    //   2991: sipush #190
    //   2994: invokevirtual write : (I)V
    //   2997: aload #4
    //   2999: iconst_0
    //   3000: invokevirtual write : (I)V
    //   3003: aload #4
    //   3005: iconst_1
    //   3006: invokevirtual write : (I)V
    //   3009: aload #4
    //   3011: iconst_0
    //   3012: invokevirtual write : (I)V
    //   3015: aload #4
    //   3017: bipush #50
    //   3019: invokevirtual write : (I)V
    //   3022: aload #4
    //   3024: getstatic burp/Zzx8.Zi : Ljava/lang/Object;
    //   3027: checkcast java/math/BigInteger
    //   3030: invokevirtual toByteArray : ()[B
    //   3033: invokevirtual write : ([B)V
    //   3036: aload #4
    //   3038: getstatic burp/Zkw.ZY : Ljava/lang/Object;
    //   3041: checkcast java/math/BigInteger
    //   3044: invokevirtual toByteArray : ()[B
    //   3047: invokevirtual write : ([B)V
    //   3050: aload #4
    //   3052: getstatic burp/Zk5y.ZL : Ljava/lang/Object;
    //   3055: checkcast java/math/BigInteger
    //   3058: invokevirtual toByteArray : ()[B
    //   3061: invokevirtual write : ([B)V
    //   3064: aload #4
    //   3066: invokevirtual toByteArray : ()[B
    //   3069: astore #5
    //   3071: aconst_null
    //   3072: astore #6
    //   3074: invokestatic a : (II)Ljava/lang/String;
    //   3077: invokestatic forName : (Ljava/lang/String;)Ljava/lang/Class;
    //   3080: invokevirtual getDeclaredMethods : ()[Ljava/lang/reflect/Method;
    //   3083: astore #7
    //   3085: aload #7
    //   3087: arraylength
    //   3088: istore #8
    //   3090: iconst_0
    //   3091: istore #9
    //   3093: iload #9
    //   3095: iload #8
    //   3097: if_icmpge -> 3225
    //   3100: aload #7
    //   3102: iload #9
    //   3104: aaload
    //   3105: astore #10
    //   3107: aload #10
    //   3109: invokevirtual getName : ()Ljava/lang/String;
    //   3112: sipush #7313
    //   3115: sipush #15738
    //   3118: invokestatic a : (II)Ljava/lang/String;
    //   3121: invokevirtual equals : (Ljava/lang/Object;)Z
    //   3124: ifeq -> 3218
    //   3127: aload #10
    //   3129: invokevirtual getParameterTypes : ()[Ljava/lang/Class;
    //   3132: astore #11
    //   3134: aload #11
    //   3136: arraylength
    //   3137: iconst_4
    //   3138: if_icmpeq -> 3148
    //   3141: goto -> 3218
    //   3144: invokestatic a : (Ljava/lang/Throwable;)Ljava/lang/Throwable;
    //   3147: athrow
    //   3148: aload #11
    //   3150: iconst_0
    //   3151: aaload
    //   3152: ldc java/lang/String
    //   3154: if_acmpeq -> 3164
    //   3157: goto -> 3218
    //   3160: invokestatic a : (Ljava/lang/Throwable;)Ljava/lang/Throwable;
    //   3163: athrow
    //   3164: aload #11
    //   3166: iconst_1
    //   3167: aaload
    //   3168: ldc [B
    //   3170: if_acmpeq -> 3180
    //   3173: goto -> 3218
    //   3176: invokestatic a : (Ljava/lang/Throwable;)Ljava/lang/Throwable;
    //   3179: athrow
    //   3180: aload #11
    //   3182: iconst_2
    //   3183: aaload
    //   3184: getstatic java/lang/Integer.TYPE : Ljava/lang/Class;
    //   3187: if_acmpeq -> 3197
    //   3190: goto -> 3218
    //   3193: invokestatic a : (Ljava/lang/Throwable;)Ljava/lang/Throwable;
    //   3196: athrow
    //   3197: aload #11
    //   3199: iconst_3
    //   3200: aaload
    //   3201: getstatic java/lang/Integer.TYPE : Ljava/lang/Class;
    //   3204: if_acmpeq -> 3214
    //   3207: goto -> 3218
    //   3210: invokestatic a : (Ljava/lang/Throwable;)Ljava/lang/Throwable;
    //   3213: athrow
    //   3214: aload #10
    //   3216: astore #6
    //   3218: iinc #9, 1
    //   3221: iload_2
    //   3222: ifeq -> 3093
    //   3225: aload #6
    //   3227: iconst_1
    //   3228: invokevirtual setAccessible : (Z)V
    //   3231: ldc burp/Zl8s
    //   3233: iconst_0
    //   3234: anewarray java/lang/Class
    //   3237: invokevirtual getDeclaredConstructor : ([Ljava/lang/Class;)Ljava/lang/reflect/Constructor;
    //   3240: astore #7
    //   3242: aload #7
    //   3244: iconst_1
    //   3245: invokevirtual setAccessible : (Z)V
    //   3248: aload #6
    //   3250: aload #7
    //   3252: iconst_0
    //   3253: anewarray java/lang/Object
    //   3256: invokevirtual newInstance : ([Ljava/lang/Object;)Ljava/lang/Object;
    //   3259: iconst_4
    //   3260: anewarray java/lang/Object
    //   3263: dup
    //   3264: iconst_0
    //   3265: sipush #7322
    //   3268: sipush #7935
    //   3271: invokestatic a : (II)Ljava/lang/String;
    //   3274: aastore
    //   3275: dup
    //   3276: iconst_1
    //   3277: aload #5
    //   3279: aastore
    //   3280: dup
    //   3281: iconst_2
    //   3282: iconst_0
    //   3283: invokestatic valueOf : (I)Ljava/lang/Integer;
    //   3286: aastore
    //   3287: dup
    //   3288: iconst_3
    //   3289: aload #5
    //   3291: arraylength
    //   3292: invokestatic valueOf : (I)Ljava/lang/Integer;
    //   3295: aastore
    //   3296: invokevirtual invoke : (Ljava/lang/Object;[Ljava/lang/Object;)Ljava/lang/Object;
    //   3299: pop
    //   3300: goto -> 3305
    //   3303: astore #4
    //   3305: getstatic burp/Zegj.ZS : Ljava/lang/String;
    //   3308: getstatic burp/Zbnz.Zb : Ljava/lang/Object;
    //   3311: checkcast java/math/BigInteger
    //   3314: invokevirtual intValue : ()I
    //   3317: bipush #32
    //   3319: irem
    //   3320: invokestatic abs : (I)I
    //   3323: invokevirtual charAt : (I)C
    //   3326: getstatic burp/Ze25.Zp : Ljava/lang/String;
    //   3329: getstatic burp/Zos.ZB : Ljava/lang/Object;
    //   3332: checkcast java/math/BigInteger
    //   3335: invokevirtual intValue : ()I
    //   3338: bipush #32
    //   3340: irem
    //   3341: invokestatic abs : (I)I
    //   3344: invokevirtual charAt : (I)C
    //   3347: if_icmpgt -> 3454
    //   3350: getstatic burp/Zrw0.Zj : Ljava/lang/String;
    //   3353: getstatic burp/Zkf6.ZS : Ljava/lang/Object;
    //   3356: checkcast java/math/BigInteger
    //   3359: invokevirtual intValue : ()I
    //   3362: bipush #32
    //   3364: irem
    //   3365: invokestatic abs : (I)I
    //   3368: invokevirtual charAt : (I)C
    //   3371: getstatic burp/Zrl5.ZG : Ljava/lang/String;
    //   3374: getstatic burp/Zrl5.ZI : Ljava/lang/Object;
    //   3377: checkcast java/math/BigInteger
    //   3380: invokevirtual intValue : ()I
    //   3383: bipush #32
    //   3385: irem
    //   3386: invokestatic abs : (I)I
    //   3389: invokevirtual charAt : (I)C
    //   3392: if_icmpgt -> 3454
    //   3395: goto -> 3402
    //   3398: invokestatic a : (Ljava/lang/Throwable;)Ljava/lang/Throwable;
    //   3401: athrow
    //   3402: getstatic burp/Zz4j.ZS : Ljava/lang/String;
    //   3405: getstatic burp/Zl2t.ZS : Ljava/lang/Object;
    //   3408: checkcast java/math/BigInteger
    //   3411: invokevirtual intValue : ()I
    //   3414: bipush #32
    //   3416: irem
    //   3417: invokestatic abs : (I)I
    //   3420: invokevirtual charAt : (I)C
    //   3423: getstatic burp/Zenr.Z_ : Ljava/lang/String;
    //   3426: getstatic burp/Zb_1.ZK : Ljava/lang/Object;
    //   3429: checkcast java/math/BigInteger
    //   3432: invokevirtual intValue : ()I
    //   3435: bipush #32
    //   3437: irem
    //   3438: invokestatic abs : (I)I
    //   3441: invokevirtual charAt : (I)C
    //   3444: if_icmpgt -> 3462
    //   3447: goto -> 3454
    //   3450: invokestatic a : (Ljava/lang/Throwable;)Ljava/lang/Throwable;
    //   3453: athrow
    //   3454: iconst_1
    //   3455: goto -> 3463
    //   3458: invokestatic a : (Ljava/lang/Throwable;)Ljava/lang/Throwable;
    //   3461: athrow
    //   3462: iconst_0
    //   3463: ireturn
    //   3464: astore_3
    //   3465: new java/lang/Exception
    //   3468: dup
    //   3469: aload_3
    //   3470: invokevirtual getMessage : ()Ljava/lang/String;
    //   3473: invokespecial <init> : (Ljava/lang/String;)V
    //   3476: athrow
    // Exception table:
    //   from	to	target	type
    //   4	3463	3464	java/lang/Throwable
    //   22	198	201	java/lang/Throwable
    //   168	235	238	java/lang/Throwable
    //   205	272	275	java/lang/Throwable
    //   242	309	312	java/lang/Throwable
    //   279	346	349	java/lang/Throwable
    //   316	383	386	java/lang/Throwable
    //   353	420	423	java/lang/Throwable
    //   390	457	460	java/lang/Throwable
    //   427	494	497	java/lang/Throwable
    //   464	531	534	java/lang/Throwable
    //   501	568	571	java/lang/Throwable
    //   538	605	608	java/lang/Throwable
    //   575	642	645	java/lang/Throwable
    //   612	679	682	java/lang/Throwable
    //   649	716	719	java/lang/Throwable
    //   686	753	756	java/lang/Throwable
    //   723	790	793	java/lang/Throwable
    //   760	827	830	java/lang/Throwable
    //   797	864	867	java/lang/Throwable
    //   834	901	904	java/lang/Throwable
    //   871	938	941	java/lang/Throwable
    //   908	975	978	java/lang/Throwable
    //   945	1012	1015	java/lang/Throwable
    //   982	1049	1052	java/lang/Throwable
    //   1019	1086	1089	java/lang/Throwable
    //   1056	1123	1126	java/lang/Throwable
    //   1093	1160	1163	java/lang/Throwable
    //   1130	1197	1200	java/lang/Throwable
    //   1167	1234	1237	java/lang/Throwable
    //   1204	1271	1274	java/lang/Throwable
    //   1241	1308	1311	java/lang/Throwable
    //   1278	1341	1344	java/lang/Throwable
    //   1407	1421	1421	java/lang/Throwable
    //   1432	1445	1448	java/lang/Throwable
    //   1437	1460	1463	java/lang/Throwable
    //   1452	1478	1481	java/lang/Throwable
    //   1467	1508	1511	java/lang/Throwable
    //   1574	1601	1604	java/lang/Throwable
    //   1591	1622	1625	java/lang/Throwable
    //   1608	1652	1655	java/lang/Throwable
    //   1629	1663	1663	java/lang/Throwable
    //   1674	1690	1693	java/lang/Throwable
    //   1770	1784	1784	java/lang/Throwable
    //   1795	1808	1811	java/lang/Throwable
    //   1800	1823	1826	java/lang/Throwable
    //   1815	1841	1844	java/lang/Throwable
    //   1830	1871	1874	java/lang/Throwable
    //   1937	1964	1967	java/lang/Throwable
    //   1954	1985	1988	java/lang/Throwable
    //   1971	2015	2018	java/lang/Throwable
    //   1992	2026	2026	java/lang/Throwable
    //   2037	2053	2056	java/lang/Throwable
    //   2092	2106	2109	java/lang/Throwable
    //   2099	2120	2123	java/lang/Throwable
    //   2113	2134	2137	java/lang/Throwable
    //   2127	2148	2151	java/lang/Throwable
    //   2141	2162	2165	java/lang/Throwable
    //   2155	2176	2179	java/lang/Throwable
    //   2169	2190	2193	java/lang/Throwable
    //   2183	2204	2207	java/lang/Throwable
    //   2197	2214	2217	java/lang/Throwable
    //   2255	2269	2272	java/lang/Throwable
    //   2262	2283	2286	java/lang/Throwable
    //   2276	2297	2300	java/lang/Throwable
    //   2290	2311	2314	java/lang/Throwable
    //   2304	2325	2328	java/lang/Throwable
    //   2318	2339	2342	java/lang/Throwable
    //   2332	2353	2356	java/lang/Throwable
    //   2346	2367	2370	java/lang/Throwable
    //   2360	2384	2387	java/lang/Throwable
    //   2453	2473	2476	java/lang/Throwable
    //   2463	2490	2493	java/lang/Throwable
    //   2480	2508	2511	java/lang/Throwable
    //   2497	2525	2528	java/lang/Throwable
    //   2515	2543	2546	java/lang/Throwable
    //   2532	2560	2563	java/lang/Throwable
    //   2550	2577	2580	java/lang/Throwable
    //   2567	2602	2605	java/lang/Throwable
    //   2584	2619	2622	java/lang/Throwable
    //   2609	2636	2639	java/lang/Throwable
    //   2626	2661	2664	java/lang/Throwable
    //   2643	2678	2681	java/lang/Throwable
    //   2668	2695	2698	java/lang/Throwable
    //   2685	2716	2719	java/lang/Throwable
    //   2852	2889	2892	java/lang/Throwable
    //   2896	2939	2942	java/lang/Throwable
    //   2950	3300	3303	java/lang/Throwable
    //   3134	3144	3144	java/lang/Throwable
    //   3148	3160	3160	java/lang/Throwable
    //   3164	3176	3176	java/lang/Throwable
    //   3180	3193	3193	java/lang/Throwable
    //   3197	3210	3210	java/lang/Throwable
    //   3305	3395	3398	java/lang/Throwable
    //   3350	3447	3450	java/lang/Throwable
    //   3402	3458	3458	java/lang/Throwable
  }
  
  static {
    // Byte code:
    //   0: bipush #14
    //   2: anewarray java/lang/String
    //   5: astore #5
    //   7: iconst_0
    //   8: istore_3
    //   9: ldc '\\td\\b+{AUPO7VHEE\\t|5p\\tsa\\tX0M\\n9KI9\\toY\\fb~o^c_\\\flcHCp\\r%3\YKU?k{K.6/4?i y-\\boK!<V@xA- l3CGvwy85\\tr;6}4!3X\\r\\t ?cV'
    //   11: dup
    //   12: astore_2
    //   13: invokevirtual length : ()I
    //   16: istore #4
    //   18: bipush #9
    //   20: istore_1
    //   21: iconst_m1
    //   22: istore_0
    //   23: bipush #80
    //   25: iinc #0, 1
    //   28: aload_2
    //   29: iload_0
    //   30: dup
    //   31: iload_1
    //   32: iadd
    //   33: invokevirtual substring : (II)Ljava/lang/String;
    //   36: iconst_m1
    //   37: goto -> 143
    //   40: aload #5
    //   42: swap
    //   43: iload_3
    //   44: iinc #3, 1
    //   47: swap
    //   48: aastore
    //   49: iload_0
    //   50: iload_1
    //   51: iadd
    //   52: dup
    //   53: istore_0
    //   54: iload #4
    //   56: if_icmpge -> 68
    //   59: aload_2
    //   60: iload_0
    //   61: invokevirtual charAt : (I)C
    //   64: istore_1
    //   65: goto -> 23
    //   68: ldc '+E(b\\t'
    //   70: dup
    //   71: astore_2
    //   72: invokevirtual length : ()I
    //   75: istore #4
    //   77: bipush #9
    //   79: istore_1
    //   80: iconst_m1
    //   81: istore_0
    //   82: bipush #60
    //   84: iinc #0, 1
    //   87: aload_2
    //   88: iload_0
    //   89: dup
    //   90: iload_1
    //   91: iadd
    //   92: invokevirtual substring : (II)Ljava/lang/String;
    //   95: iconst_0
    //   96: goto -> 143
    //   99: aload #5
    //   101: swap
    //   102: iload_3
    //   103: iinc #3, 1
    //   106: swap
    //   107: aastore
    //   108: iload_0
    //   109: iload_1
    //   110: iadd
    //   111: dup
    //   112: istore_0
    //   113: iload #4
    //   115: if_icmpge -> 127
    //   118: aload_2
    //   119: iload_0
    //   120: invokevirtual charAt : (I)C
    //   123: istore_1
    //   124: goto -> 82
    //   127: aload #5
    //   129: putstatic burp/Zs1k.a : [Ljava/lang/String;
    //   132: bipush #14
    //   134: anewarray java/lang/String
    //   137: putstatic burp/Zs1k.b : [Ljava/lang/String;
    //   140: goto -> 300
    //   143: dup_x2
    //   144: pop
    //   145: invokevirtual toCharArray : ()[C
    //   148: dup_x1
    //   149: arraylength
    //   150: dup_x2
    //   151: pop
    //   152: iconst_0
    //   153: istore #6
    //   155: dup2_x1
    //   156: pop2
    //   157: dup_x2
    //   158: iconst_1
    //   159: if_icmpgt -> 260
    //   162: dup2
    //   163: swap
    //   164: iload #6
    //   166: dup2_x1
    //   167: caload
    //   168: swap
    //   169: iload #6
    //   171: bipush #7
    //   173: irem
    //   174: tableswitch default -> 242, 0 -> 212, 1 -> 217, 2 -> 222, 3 -> 227, 4 -> 232, 5 -> 237
    //   212: bipush #49
    //   214: goto -> 244
    //   217: bipush #10
    //   219: goto -> 244
    //   222: bipush #85
    //   224: goto -> 244
    //   227: bipush #19
    //   229: goto -> 244
    //   232: bipush #35
    //   234: goto -> 244
    //   237: bipush #123
    //   239: goto -> 244
    //   242: bipush #82
    //   244: ixor
    //   245: ixor
    //   246: i2c
    //   247: castore
    //   248: iinc #6, 1
    //   251: dup
    //   252: ifne -> 260
    //   255: dup2
    //   256: dup_x1
    //   257: goto -> 166
    //   260: dup2_x1
    //   261: pop2
    //   262: dup_x2
    //   263: iload #6
    //   265: if_icmpgt -> 162
    //   268: pop
    //   269: new java/lang/String
    //   272: dup_x1
    //   273: swap
    //   274: invokespecial <init> : ([C)V
    //   277: invokevirtual intern : ()Ljava/lang/String;
    //   280: swap
    //   281: pop
    //   282: swap
    //   283: tableswitch default -> 40, 0 -> 99
    //   300: new java/math/BigInteger
    //   303: dup
    //   304: bipush #32
    //   306: newarray byte
    //   308: dup
    //   309: iconst_0
    //   310: bipush #25
    //   312: bastore
    //   313: dup
    //   314: iconst_1
    //   315: bipush #14
    //   317: bastore
    //   318: dup
    //   319: iconst_2
    //   320: bipush #-115
    //   322: bastore
    //   323: dup
    //   324: iconst_3
    //   325: bipush #-79
    //   327: bastore
    //   328: dup
    //   329: iconst_4
    //   330: bipush #80
    //   332: bastore
    //   333: dup
    //   334: iconst_5
    //   335: bipush #35
    //   337: bastore
    //   338: dup
    //   339: bipush #6
    //   341: bipush #-6
    //   343: bastore
    //   344: dup
    //   345: bipush #7
    //   347: bipush #91
    //   349: bastore
    //   350: dup
    //   351: bipush #8
    //   353: bipush #-71
    //   355: bastore
    //   356: dup
    //   357: bipush #9
    //   359: bipush #21
    //   361: bastore
    //   362: dup
    //   363: bipush #10
    //   365: bipush #-40
    //   367: bastore
    //   368: dup
    //   369: bipush #11
    //   371: bipush #28
    //   373: bastore
    //   374: dup
    //   375: bipush #12
    //   377: bipush #-68
    //   379: bastore
    //   380: dup
    //   381: bipush #13
    //   383: bipush #126
    //   385: bastore
    //   386: dup
    //   387: bipush #14
    //   389: iconst_2
    //   390: bastore
    //   391: dup
    //   392: bipush #15
    //   394: bipush #122
    //   396: bastore
    //   397: dup
    //   398: bipush #16
    //   400: bipush #-9
    //   402: bastore
    //   403: dup
    //   404: bipush #17
    //   406: bipush #118
    //   408: bastore
    //   409: dup
    //   410: bipush #18
    //   412: bipush #46
    //   414: bastore
    //   415: dup
    //   416: bipush #19
    //   418: bipush #-54
    //   420: bastore
    //   421: dup
    //   422: bipush #20
    //   424: bipush #-75
    //   426: bastore
    //   427: dup
    //   428: bipush #21
    //   430: bipush #63
    //   432: bastore
    //   433: dup
    //   434: bipush #22
    //   436: bipush #-31
    //   438: bastore
    //   439: dup
    //   440: bipush #23
    //   442: bipush #116
    //   444: bastore
    //   445: dup
    //   446: bipush #24
    //   448: bipush #-26
    //   450: bastore
    //   451: dup
    //   452: bipush #25
    //   454: bipush #27
    //   456: bastore
    //   457: dup
    //   458: bipush #26
    //   460: bipush #-47
    //   462: bastore
    //   463: dup
    //   464: bipush #27
    //   466: bipush #114
    //   468: bastore
    //   469: dup
    //   470: bipush #28
    //   472: bipush #-41
    //   474: bastore
    //   475: dup
    //   476: bipush #29
    //   478: bipush #-37
    //   480: bastore
    //   481: dup
    //   482: bipush #30
    //   484: bipush #66
    //   486: bastore
    //   487: dup
    //   488: bipush #31
    //   490: bipush #-12
    //   492: bastore
    //   493: invokespecial <init> : ([B)V
    //   496: putstatic burp/Zs1k.Ze : Ljava/lang/Object;
    //   499: sipush #7325
    //   502: sipush #-17324
    //   505: invokestatic a : (II)Ljava/lang/String;
    //   508: putstatic burp/Zs1k.Zd : Ljava/lang/String;
    //   511: return
  }
  
  private static Throwable a(Throwable paramThrowable) {
    return paramThrowable;
  }
  
  private static String a(int paramInt1, int paramInt2) {
    int i = (paramInt1 ^ 0x1C9B) & 0xFFFF;
    if (b[i] == null) {
      char[] arrayOfChar = a[i].toCharArray();
      switch (arrayOfChar[0] & 0xFF) {
        case 0:
        
        case 1:
        
        case 2:
        
        case 3:
        
        case 4:
        
        case 5:
        
        case 6:
        
        case 7:
        
        case 8:
        
        case 9:
        
        case 10:
        
        case 11:
        
        case 12:
        
        case 13:
        
        case 14:
        
        case 15:
        
        case 16:
        
        case 17:
        
        case 18:
        
        case 19:
        
        case 20:
        
        case 21:
        
        case 22:
        
        case 23:
        
        case 24:
        
        case 25:
        
        case 26:
        
        case 27:
        
        case 28:
        
        case 29:
        
        case 30:
        
        case 31:
        
        case 32:
        
        case 33:
        
        case 34:
        
        case 35:
        
        case 36:
        
        case 37:
        
        case 38:
        
        case 39:
        
        case 40:
        
        case 41:
        
        case 42:
        
        case 43:
        
        case 44:
        
        case 45:
        
        case 46:
        
        case 47:
        
        case 48:
        
        case 49:
        
        case 50:
        
        case 51:
        
        case 52:
        
        case 53:
        
        case 54:
        
        case 55:
        
        case 56:
        
        case 57:
        
        case 58:
        
        case 59:
        
        case 60:
        
        case 61:
        
        case 62:
        
        case 63:
        
        case 64:
        
        case 65:
        
        case 66:
        
        case 67:
        
        case 68:
        
        case 69:
        
        case 70:
        
        case 71:
        
        case 72:
        
        case 73:
        
        case 74:
        
        case 75:
        
        case 76:
        
        case 77:
        
        case 78:
        
        case 79:
        
        case 80:
        
        case 81:
        
        case 82:
        
        case 83:
        
        case 84:
        
        case 85:
        
        case 86:
        
        case 87:
        
        case 88:
        
        case 89:
        
        case 90:
        
        case 91:
        
        case 92:
        
        case 93:
        
        case 94:
        
        case 95:
        
        case 96:
        
        case 97:
        
        case 98:
        
        case 99:
        
        case 100:
        
        case 101:
        
        case 102:
        
        case 103:
        
        case 104:
        
        case 105:
        
        case 106:
        
        case 107:
        
        case 108:
        
        case 109:
        
        case 110:
        
        case 111:
        
        case 112:
        
        case 113:
        
        case 114:
        
        case 115:
        
        case 116:
        
        case 117:
        
        case 118:
        
        case 119:
        
        case 120:
        
        case 121:
        
        case 122:
        
        case 123:
        
        case 124:
        
        case 125:
        
        case 126:
        
        case 127:
        
        case 128:
        
        case 129:
        
        case 130:
        
        case 131:
        
        case 132:
        
        case 133:
        
        case 134:
        
        case 135:
        
        case 136:
        
        case 137:
        
        case 138:
        
        case 139:
        
        case 140:
        
        case 141:
        
        case 142:
        
        case 143:
        
        case 144:
        
        case 145:
        
        case 146:
        
        case 147:
        
        case 148:
        
        case 149:
        
        case 150:
        
        case 151:
        
        case 152:
        
        case 153:
        
        case 154:
        
        case 155:
        
        case 156:
        
        case 157:
        
        case 158:
        
        case 159:
        
        case 160:
        
        case 161:
        
        case 162:
        
        case 163:
        
        case 164:
        
        case 165:
        
        case 166:
        
        case 167:
        
        case 168:
        
        case 169:
        
        case 170:
        
        case 171:
        
        case 172:
        
        case 173:
        
        case 174:
        
        case 175:
        
        case 176:
        
        case 177:
        
        case 178:
        
        case 179:
        
        case 180:
        
        case 181:
        
        case 182:
        
        case 183:
        
        case 184:
        
        case 185:
        
        case 186:
        
        case 187:
        
        case 188:
        
        case 189:
        
        case 190:
        
        case 191:
        
        case 192:
        
        case 193:
        
        case 194:
        
        case 195:
        
        case 196:
        
        case 197:
        
        case 198:
        
        case 199:
        
        case 200:
        
        case 201:
        
        case 202:
        
        case 203:
        
        case 204:
        
        case 205:
        
        case 206:
        
        case 207:
        
        case 208:
        
        case 209:
        
        case 210:
        
        case 211:
        
        case 212:
        
        case 213:
        
        case 214:
        
        case 215:
        
        case 216:
        
        case 217:
        
        case 218:
        
        case 219:
        
        case 220:
        
        case 221:
        
        case 222:
        
        case 223:
        
        case 224:
        
        case 225:
        
        case 226:
        
        case 227:
        
        case 228:
        
        case 229:
        
        case 230:
        
        case 231:
        
        case 232:
        
        case 233:
        
        case 234:
        
        case 235:
        
        case 236:
        
        case 237:
        
        case 238:
        
        case 239:
        
        case 240:
        
        case 241:
        
        case 242:
        
        case 243:
        
        case 244:
        
        case 245:
        
        case 246:
        
        case 247:
        
        case 248:
        
        case 249:
        
        case 250:
        
        case 251:
        
        case 252:
        
        case 253:
        
        case 254:
        
        default:
          break;
      } 
      char c = '';
      int j = (paramInt2 & 0xFF) - c;
      if (j < 0)
        j += 256; 
      int k = ((paramInt2 & 0xFFFF) >>> 8) - c;
      if (k < 0)
        k += 256; 
      for (byte b = 0; b < arrayOfChar.length; b++) {
        int m = b % 2;
        if (m == 0) {
          arrayOfChar[b] = (char)(arrayOfChar[b] ^ j);
          j = ((j >>> 3 | j << 5) ^ arrayOfChar[b]) & 0xFF;
        } else {
          arrayOfChar[b] = (char)(arrayOfChar[b] ^ k);
          k = ((k >>> 3 | k << 5) ^ arrayOfChar[b]) & 0xFF;
        } 
      } 
      b[i] = (new String(arrayOfChar)).intern();
    } 
    return b[i];
  }
}


/* Location:              C:\Program Files\BurpSuitePro\burpsuite_pro.jar!\burp\Zs1k.class
 * Java compiler version: 21 (65.0)
 * JD-Core Version:       1.1.3
 */