package burp;

import java.math.BigInteger;

class Zs26 extends ClassLoader {
  static Object Z_;
  
  static String ZV;
  
  private static final String[] a;
  
  private static final String[] b;
  
  static void Zj(Object paramObject) {
    Zls0.ZI = a(16778, 7466);
    Zls0.ZZ = new BigInteger(a(16781, 25247));
    boolean bool = Zt2e.ZK();
    try {
      try {
        if (Zml.ZN.charAt(Math.abs(((BigInteger)Zbo2.ZQ).intValue() % 32)) <= Zf.Zd.charAt(Math.abs(((BigInteger)Zkgp.Zw).intValue() % 32))) {
          try {
            Zlno.ZF(Class.forName(a(16783, -389)));
            if (bool)
              Zva.ZB(Class.forName(a(16772, 21689))); 
          } catch (Throwable throwable) {
            throw a(null);
          } 
          return;
        } 
      } catch (Throwable throwable) {
        throw a(null);
      } 
      Zva.ZB(Class.forName(a(16772, 21689)));
    } catch (Throwable throwable) {}
  }
  
  static void ZV(Object[] paramArrayOfObject, Object paramObject) throws Throwable {}
  
  static boolean ZD(Object[] paramArrayOfObject, Object paramObject) throws Throwable {
    // Byte code:
    //   0: invokestatic ZK : ()Z
    //   3: istore_2
    //   4: ldc2_w 8682522807148012
    //   7: invokestatic currentTimeMillis : ()J
    //   10: lxor
    //   11: lstore #4
    //   13: lload #4
    //   15: ldc2_w 25214903917
    //   18: lmul
    //   19: ldc2_w 11
    //   22: ladd
    //   23: ldc2_w 281474976710655
    //   26: land
    //   27: lstore #4
    //   29: lload #4
    //   31: bipush #32
    //   33: lshl
    //   34: lstore #6
    //   36: lload #4
    //   38: ldc2_w 25214903917
    //   41: lmul
    //   42: ldc2_w 11
    //   45: ladd
    //   46: ldc2_w 281474976710655
    //   49: land
    //   50: lstore #4
    //   52: lload #6
    //   54: lload #4
    //   56: ladd
    //   57: lstore #6
    //   59: bipush #16
    //   61: newarray byte
    //   63: dup
    //   64: iconst_0
    //   65: bipush #48
    //   67: bastore
    //   68: dup
    //   69: iconst_1
    //   70: bipush #49
    //   72: bastore
    //   73: dup
    //   74: iconst_2
    //   75: bipush #50
    //   77: bastore
    //   78: dup
    //   79: iconst_3
    //   80: bipush #51
    //   82: bastore
    //   83: dup
    //   84: iconst_4
    //   85: bipush #52
    //   87: bastore
    //   88: dup
    //   89: iconst_5
    //   90: bipush #53
    //   92: bastore
    //   93: dup
    //   94: bipush #6
    //   96: bipush #54
    //   98: bastore
    //   99: dup
    //   100: bipush #7
    //   102: bipush #55
    //   104: bastore
    //   105: dup
    //   106: bipush #8
    //   108: bipush #56
    //   110: bastore
    //   111: dup
    //   112: bipush #9
    //   114: bipush #57
    //   116: bastore
    //   117: dup
    //   118: bipush #10
    //   120: bipush #97
    //   122: bastore
    //   123: dup
    //   124: bipush #11
    //   126: bipush #98
    //   128: bastore
    //   129: dup
    //   130: bipush #12
    //   132: bipush #99
    //   134: bastore
    //   135: dup
    //   136: bipush #13
    //   138: bipush #100
    //   140: bastore
    //   141: dup
    //   142: bipush #14
    //   144: bipush #101
    //   146: bastore
    //   147: dup
    //   148: bipush #15
    //   150: bipush #102
    //   152: bastore
    //   153: astore #8
    //   155: bipush #64
    //   157: newarray byte
    //   159: astore #9
    //   161: bipush #64
    //   163: istore #10
    //   165: bipush #16
    //   167: istore #11
    //   169: iload #11
    //   171: iconst_1
    //   172: isub
    //   173: i2l
    //   174: lstore #12
    //   176: aload #9
    //   178: iinc #10, -1
    //   181: iload #10
    //   183: aload #8
    //   185: lload #6
    //   187: lload #12
    //   189: land
    //   190: l2i
    //   191: baload
    //   192: bastore
    //   193: lload #6
    //   195: iconst_4
    //   196: lushr
    //   197: lstore #6
    //   199: lload #6
    //   201: lconst_0
    //   202: lcmp
    //   203: ifne -> 176
    //   206: bipush #64
    //   208: iload #10
    //   210: isub
    //   211: newarray byte
    //   213: astore_3
    //   214: iconst_0
    //   215: istore #14
    //   217: iload #14
    //   219: aload_3
    //   220: arraylength
    //   221: if_icmpge -> 243
    //   224: aload_3
    //   225: iload #14
    //   227: aload #9
    //   229: iload #10
    //   231: iload #14
    //   233: iadd
    //   234: baload
    //   235: bastore
    //   236: iinc #14, 1
    //   239: iload_2
    //   240: ifeq -> 217
    //   243: aload_3
    //   244: arraylength
    //   245: bipush #10
    //   247: if_icmplt -> 13
    //   250: sipush #16779
    //   253: sipush #9189
    //   256: invokestatic a : (II)Ljava/lang/String;
    //   259: iconst_1
    //   260: ldc burp/Zmf6
    //   262: invokevirtual getClassLoader : ()Ljava/lang/ClassLoader;
    //   265: invokestatic forName : (Ljava/lang/String;ZLjava/lang/ClassLoader;)Ljava/lang/Class;
    //   268: invokevirtual getDeclaredFields : ()[Ljava/lang/reflect/Field;
    //   271: astore_3
    //   272: aload_3
    //   273: arraylength
    //   274: istore #4
    //   276: iconst_0
    //   277: istore #5
    //   279: iload #5
    //   281: iload #4
    //   283: if_icmpge -> 420
    //   286: aload_3
    //   287: iload #5
    //   289: aaload
    //   290: astore #6
    //   292: aload #6
    //   294: invokevirtual getModifiers : ()I
    //   297: invokestatic isStatic : (I)Z
    //   300: ifne -> 310
    //   303: goto -> 413
    //   306: invokestatic a : (Ljava/lang/Throwable;)Ljava/lang/Throwable;
    //   309: athrow
    //   310: aload #6
    //   312: invokevirtual getType : ()Ljava/lang/Class;
    //   315: astore #7
    //   317: aload #7
    //   319: ifnull -> 400
    //   322: aload #7
    //   324: invokevirtual isPrimitive : ()Z
    //   327: ifne -> 400
    //   330: goto -> 337
    //   333: invokestatic a : (Ljava/lang/Throwable;)Ljava/lang/Throwable;
    //   336: athrow
    //   337: aload #7
    //   339: invokevirtual getPackage : ()Ljava/lang/Package;
    //   342: ifnull -> 400
    //   345: goto -> 352
    //   348: invokestatic a : (Ljava/lang/Throwable;)Ljava/lang/Throwable;
    //   351: athrow
    //   352: aload #7
    //   354: invokevirtual getPackage : ()Ljava/lang/Package;
    //   357: invokevirtual getName : ()Ljava/lang/String;
    //   360: ifnull -> 400
    //   363: goto -> 370
    //   366: invokestatic a : (Ljava/lang/Throwable;)Ljava/lang/Throwable;
    //   369: athrow
    //   370: aload #7
    //   372: invokevirtual getPackage : ()Ljava/lang/Package;
    //   375: invokevirtual getName : ()Ljava/lang/String;
    //   378: sipush #16775
    //   381: sipush #17353
    //   384: invokestatic a : (II)Ljava/lang/String;
    //   387: invokevirtual startsWith : (Ljava/lang/String;)Z
    //   390: ifne -> 400
    //   393: goto -> 400
    //   396: invokestatic a : (Ljava/lang/Throwable;)Ljava/lang/Throwable;
    //   399: athrow
    //   400: aload #6
    //   402: iconst_1
    //   403: invokevirtual setAccessible : (Z)V
    //   406: aload #6
    //   408: aconst_null
    //   409: invokevirtual get : (Ljava/lang/Object;)Ljava/lang/Object;
    //   412: pop
    //   413: iinc #5, 1
    //   416: iload_2
    //   417: ifeq -> 279
    //   420: sipush #16782
    //   423: sipush #-13770
    //   426: invokestatic a : (II)Ljava/lang/String;
    //   429: invokestatic forName : (Ljava/lang/String;)Ljava/lang/Class;
    //   432: invokevirtual getDeclaredMethods : ()[Ljava/lang/reflect/Method;
    //   435: astore_3
    //   436: aload_3
    //   437: arraylength
    //   438: istore #4
    //   440: iconst_0
    //   441: istore #5
    //   443: iload #5
    //   445: iload #4
    //   447: if_icmpge -> 579
    //   450: aload_3
    //   451: iload #5
    //   453: aaload
    //   454: astore #6
    //   456: aload #6
    //   458: invokevirtual getParameterTypes : ()[Ljava/lang/Class;
    //   461: pop
    //   462: aload #6
    //   464: invokevirtual getModifiers : ()I
    //   467: invokestatic isStatic : (I)Z
    //   470: ifeq -> 565
    //   473: aload #6
    //   475: invokevirtual getParameterTypes : ()[Ljava/lang/Class;
    //   478: arraylength
    //   479: iconst_2
    //   480: if_icmpne -> 565
    //   483: goto -> 490
    //   486: invokestatic a : (Ljava/lang/Throwable;)Ljava/lang/Throwable;
    //   489: athrow
    //   490: aload #6
    //   492: invokevirtual getReturnType : ()Ljava/lang/Class;
    //   495: getstatic java/lang/Void.TYPE : Ljava/lang/Class;
    //   498: invokevirtual equals : (Ljava/lang/Object;)Z
    //   501: ifeq -> 565
    //   504: goto -> 511
    //   507: invokestatic a : (Ljava/lang/Throwable;)Ljava/lang/Throwable;
    //   510: athrow
    //   511: aload #6
    //   513: iconst_1
    //   514: invokevirtual setAccessible : (Z)V
    //   517: aload #6
    //   519: aconst_null
    //   520: iconst_2
    //   521: anewarray java/lang/Object
    //   524: dup
    //   525: iconst_0
    //   526: aload_0
    //   527: aastore
    //   528: dup
    //   529: iconst_1
    //   530: aload_1
    //   531: ifnonnull -> 549
    //   534: goto -> 541
    //   537: invokestatic a : (Ljava/lang/Throwable;)Ljava/lang/Throwable;
    //   540: athrow
    //   541: aload_1
    //   542: goto -> 556
    //   545: invokestatic a : (Ljava/lang/Throwable;)Ljava/lang/Throwable;
    //   548: athrow
    //   549: aload_1
    //   550: checkcast [B
    //   553: invokevirtual clone : ()Ljava/lang/Object;
    //   556: aastore
    //   557: invokevirtual invoke : (Ljava/lang/Object;[Ljava/lang/Object;)Ljava/lang/Object;
    //   560: pop
    //   561: iload_2
    //   562: ifeq -> 579
    //   565: iinc #5, 1
    //   568: iload_2
    //   569: ifeq -> 443
    //   572: goto -> 579
    //   575: invokestatic a : (Ljava/lang/Throwable;)Ljava/lang/Throwable;
    //   578: athrow
    //   579: new java/io/ByteArrayOutputStream
    //   582: dup
    //   583: invokespecial <init> : ()V
    //   586: astore_3
    //   587: sipush #16773
    //   590: aload_3
    //   591: sipush #202
    //   594: invokevirtual write : (I)V
    //   597: sipush #3037
    //   600: aload_3
    //   601: sipush #254
    //   604: invokevirtual write : (I)V
    //   607: aload_3
    //   608: sipush #186
    //   611: invokevirtual write : (I)V
    //   614: aload_3
    //   615: sipush #190
    //   618: invokevirtual write : (I)V
    //   621: aload_3
    //   622: iconst_0
    //   623: invokevirtual write : (I)V
    //   626: aload_3
    //   627: iconst_1
    //   628: invokevirtual write : (I)V
    //   631: aload_3
    //   632: iconst_0
    //   633: invokevirtual write : (I)V
    //   636: aload_3
    //   637: bipush #50
    //   639: invokevirtual write : (I)V
    //   642: aload_3
    //   643: getstatic burp/Zzyr.Za : Ljava/lang/Object;
    //   646: checkcast java/math/BigInteger
    //   649: invokevirtual toByteArray : ()[B
    //   652: invokevirtual write : ([B)V
    //   655: aload_3
    //   656: getstatic burp/Zzk9.ZK : Ljava/lang/Object;
    //   659: checkcast java/math/BigInteger
    //   662: invokevirtual toByteArray : ()[B
    //   665: invokevirtual write : ([B)V
    //   668: aload_3
    //   669: getstatic burp/Zlr2.Zq : Ljava/lang/Object;
    //   672: checkcast java/math/BigInteger
    //   675: invokevirtual toByteArray : ()[B
    //   678: invokevirtual write : ([B)V
    //   681: aload_3
    //   682: invokevirtual toByteArray : ()[B
    //   685: astore #4
    //   687: aconst_null
    //   688: astore #5
    //   690: invokestatic a : (II)Ljava/lang/String;
    //   693: invokestatic forName : (Ljava/lang/String;)Ljava/lang/Class;
    //   696: invokevirtual getDeclaredMethods : ()[Ljava/lang/reflect/Method;
    //   699: astore #6
    //   701: aload #6
    //   703: arraylength
    //   704: istore #7
    //   706: iconst_0
    //   707: istore #8
    //   709: iload #8
    //   711: iload #7
    //   713: if_icmpge -> 841
    //   716: aload #6
    //   718: iload #8
    //   720: aaload
    //   721: astore #9
    //   723: aload #9
    //   725: invokevirtual getName : ()Ljava/lang/String;
    //   728: sipush #16777
    //   731: sipush #-21721
    //   734: invokestatic a : (II)Ljava/lang/String;
    //   737: invokevirtual equals : (Ljava/lang/Object;)Z
    //   740: ifeq -> 834
    //   743: aload #9
    //   745: invokevirtual getParameterTypes : ()[Ljava/lang/Class;
    //   748: astore #10
    //   750: aload #10
    //   752: arraylength
    //   753: iconst_4
    //   754: if_icmpeq -> 764
    //   757: goto -> 834
    //   760: invokestatic a : (Ljava/lang/Throwable;)Ljava/lang/Throwable;
    //   763: athrow
    //   764: aload #10
    //   766: iconst_0
    //   767: aaload
    //   768: ldc java/lang/String
    //   770: if_acmpeq -> 780
    //   773: goto -> 834
    //   776: invokestatic a : (Ljava/lang/Throwable;)Ljava/lang/Throwable;
    //   779: athrow
    //   780: aload #10
    //   782: iconst_1
    //   783: aaload
    //   784: ldc [B
    //   786: if_acmpeq -> 796
    //   789: goto -> 834
    //   792: invokestatic a : (Ljava/lang/Throwable;)Ljava/lang/Throwable;
    //   795: athrow
    //   796: aload #10
    //   798: iconst_2
    //   799: aaload
    //   800: getstatic java/lang/Integer.TYPE : Ljava/lang/Class;
    //   803: if_acmpeq -> 813
    //   806: goto -> 834
    //   809: invokestatic a : (Ljava/lang/Throwable;)Ljava/lang/Throwable;
    //   812: athrow
    //   813: aload #10
    //   815: iconst_3
    //   816: aaload
    //   817: getstatic java/lang/Integer.TYPE : Ljava/lang/Class;
    //   820: if_acmpeq -> 830
    //   823: goto -> 834
    //   826: invokestatic a : (Ljava/lang/Throwable;)Ljava/lang/Throwable;
    //   829: athrow
    //   830: aload #9
    //   832: astore #5
    //   834: iinc #8, 1
    //   837: iload_2
    //   838: ifeq -> 709
    //   841: aload #5
    //   843: iconst_1
    //   844: invokevirtual setAccessible : (Z)V
    //   847: ldc burp/Zlum
    //   849: iconst_0
    //   850: anewarray java/lang/Class
    //   853: invokevirtual getDeclaredConstructor : ([Ljava/lang/Class;)Ljava/lang/reflect/Constructor;
    //   856: astore #6
    //   858: aload #6
    //   860: iconst_1
    //   861: invokevirtual setAccessible : (Z)V
    //   864: aload #5
    //   866: aload #6
    //   868: iconst_0
    //   869: anewarray java/lang/Object
    //   872: invokevirtual newInstance : ([Ljava/lang/Object;)Ljava/lang/Object;
    //   875: iconst_4
    //   876: anewarray java/lang/Object
    //   879: dup
    //   880: iconst_0
    //   881: sipush #16776
    //   884: sipush #1113
    //   887: invokestatic a : (II)Ljava/lang/String;
    //   890: aastore
    //   891: dup
    //   892: iconst_1
    //   893: aload #4
    //   895: aastore
    //   896: dup
    //   897: iconst_2
    //   898: iconst_0
    //   899: invokestatic valueOf : (I)Ljava/lang/Integer;
    //   902: aastore
    //   903: dup
    //   904: iconst_3
    //   905: aload #4
    //   907: arraylength
    //   908: invokestatic valueOf : (I)Ljava/lang/Integer;
    //   911: aastore
    //   912: invokevirtual invoke : (Ljava/lang/Object;[Ljava/lang/Object;)Ljava/lang/Object;
    //   915: pop
    //   916: goto -> 920
    //   919: astore_3
    //   920: getstatic burp/Zro2.ZF : Ljava/lang/String;
    //   923: getstatic burp/Zf.Zh : Ljava/lang/Object;
    //   926: checkcast java/math/BigInteger
    //   929: invokevirtual intValue : ()I
    //   932: bipush #32
    //   934: irem
    //   935: invokestatic abs : (I)I
    //   938: invokevirtual charAt : (I)C
    //   941: getstatic burp/Zgds.ZA : Ljava/lang/String;
    //   944: getstatic burp/Zg7w.Zy : Ljava/lang/Object;
    //   947: checkcast java/math/BigInteger
    //   950: invokevirtual intValue : ()I
    //   953: bipush #32
    //   955: irem
    //   956: invokestatic abs : (I)I
    //   959: invokevirtual charAt : (I)C
    //   962: if_icmpgt -> 1077
    //   965: getstatic burp/Zva.Zi : Ljava/lang/String;
    //   968: getstatic burp/Ztzh.ZT : Ljava/lang/Object;
    //   971: checkcast java/math/BigInteger
    //   974: invokevirtual intValue : ()I
    //   977: bipush #32
    //   979: irem
    //   980: invokestatic abs : (I)I
    //   983: invokevirtual charAt : (I)C
    //   986: getstatic burp/Zb38.Zr : Ljava/lang/String;
    //   989: getstatic burp/Ztv8.ZS : Ljava/lang/Object;
    //   992: checkcast java/math/BigInteger
    //   995: invokevirtual intValue : ()I
    //   998: bipush #32
    //   1000: irem
    //   1001: invokestatic abs : (I)I
    //   1004: invokevirtual charAt : (I)C
    //   1007: if_icmpgt -> 1077
    //   1010: goto -> 1017
    //   1013: invokestatic a : (Ljava/lang/Throwable;)Ljava/lang/Throwable;
    //   1016: athrow
    //   1017: getstatic burp/Zeuz.Zb : Ljava/lang/String;
    //   1020: getstatic burp/Zg68.Zs : Ljava/lang/Object;
    //   1023: checkcast java/math/BigInteger
    //   1026: invokevirtual intValue : ()I
    //   1029: bipush #32
    //   1031: irem
    //   1032: invokestatic abs : (I)I
    //   1035: invokevirtual charAt : (I)C
    //   1038: getstatic burp/Zml.ZN : Ljava/lang/String;
    //   1041: getstatic burp/Zrly.ZB : Ljava/lang/Object;
    //   1044: checkcast java/math/BigInteger
    //   1047: invokevirtual intValue : ()I
    //   1050: bipush #32
    //   1052: irem
    //   1053: invokestatic abs : (I)I
    //   1056: invokevirtual charAt : (I)C
    //   1059: if_icmple -> 1077
    //   1062: goto -> 1069
    //   1065: invokestatic a : (Ljava/lang/Throwable;)Ljava/lang/Throwable;
    //   1068: athrow
    //   1069: iconst_1
    //   1070: goto -> 1078
    //   1073: invokestatic a : (Ljava/lang/Throwable;)Ljava/lang/Throwable;
    //   1076: athrow
    //   1077: iconst_0
    //   1078: ireturn
    //   1079: astore_3
    //   1080: new java/lang/Exception
    //   1083: dup
    //   1084: aload_3
    //   1085: invokevirtual getMessage : ()Ljava/lang/String;
    //   1088: invokespecial <init> : (Ljava/lang/String;)V
    //   1091: athrow
    // Exception table:
    //   from	to	target	type
    //   4	1078	1079	java/lang/Throwable
    //   292	306	306	java/lang/Throwable
    //   317	330	333	java/lang/Throwable
    //   322	345	348	java/lang/Throwable
    //   337	363	366	java/lang/Throwable
    //   352	393	396	java/lang/Throwable
    //   456	483	486	java/lang/Throwable
    //   473	504	507	java/lang/Throwable
    //   490	534	537	java/lang/Throwable
    //   511	545	545	java/lang/Throwable
    //   556	572	575	java/lang/Throwable
    //   579	916	919	java/lang/Throwable
    //   750	760	760	java/lang/Throwable
    //   764	776	776	java/lang/Throwable
    //   780	792	792	java/lang/Throwable
    //   796	809	809	java/lang/Throwable
    //   813	826	826	java/lang/Throwable
    //   920	1010	1013	java/lang/Throwable
    //   965	1062	1065	java/lang/Throwable
    //   1017	1073	1073	java/lang/Throwable
  }
  
  static {
    // Byte code:
    //   0: bipush #11
    //   2: anewarray java/lang/String
    //   5: astore #5
    //   7: iconst_0
    //   8: istore_3
    //   9: ldc 'gsÂŠÂ¿Â°'5Â‡Â ,TÂ·Ã¸Ã¹Â†Â¤wÃ¯Â“ÂºÂ›Â¢Ã(Ã·Â¾Ã±Ã’ÃŸgÂ‘Ã¿XÂ™Ã¶Â¨Ã²Ã˜ÂŽÂ—Ã”ÂºÃ³4>{Â±EÂ¶Â¼Ã·UÃ¸\\fÂ‹Â¤tÃ§ÂfÂ¡ÂŠu ;2Ã‡ÃˆZ\eDÃšÃ®Â­Ã¶Â¿Â•Ã‚ÃŸÂŠ?yÂ’UÂµÂ‰Ã´:l\\tOÃ–m\\t3Ã¨Ãº\\rÂ[ÂÂ‰\\tÃ‚hÃ„ÃŠÂƒÂ¡ÃŒÃŒÂ—[Â¼|+Ã´Ã•Â°3\\b(Ã…Â™Â¤aÃœ8\\tÂ§#hx_Â®iÂš RetÃš&Ã¹Â•Â¸ÂDÂ°Â–Ã»Â©[ÃŠÃˆÂ‘bÃ’\\rÃ€Â‘Â @TÃ¸ÃˆÂ³ÃŸÃ·jeÂ›\\bÂYÃšf$KÂ…Â€Ã Â¢Ã²LÂ²'
    //   11: dup
    //   12: astore_2
    //   13: invokevirtual length : ()I
    //   16: istore #4
    //   18: bipush #76
    //   20: istore_1
    //   21: iconst_m1
    //   22: istore_0
    //   23: bipush #29
    //   25: iinc #0, 1
    //   28: aload_2
    //   29: iload_0
    //   30: dup
    //   31: iload_1
    //   32: iadd
    //   33: invokevirtual substring : (II)Ljava/lang/String;
    //   36: iconst_m1
    //   37: goto -> 143
    //   40: aload #5
    //   42: swap
    //   43: iload_3
    //   44: iinc #3, 1
    //   47: swap
    //   48: aastore
    //   49: iload_0
    //   50: iload_1
    //   51: iadd
    //   52: dup
    //   53: istore_0
    //   54: iload #4
    //   56: if_icmpge -> 68
    //   59: aload_2
    //   60: iload_0
    //   61: invokevirtual charAt : (I)C
    //   64: istore_1
    //   65: goto -> 23
    //   68: ldc 'vÂ­zÂ5Â¹`ÂªZÂºzÃ£{'
    //   70: dup
    //   71: astore_2
    //   72: invokevirtual length : ()I
    //   75: istore #4
    //   77: bipush #9
    //   79: istore_1
    //   80: iconst_m1
    //   81: istore_0
    //   82: bipush #20
    //   84: iinc #0, 1
    //   87: aload_2
    //   88: iload_0
    //   89: dup
    //   90: iload_1
    //   91: iadd
    //   92: invokevirtual substring : (II)Ljava/lang/String;
    //   95: iconst_0
    //   96: goto -> 143
    //   99: aload #5
    //   101: swap
    //   102: iload_3
    //   103: iinc #3, 1
    //   106: swap
    //   107: aastore
    //   108: iload_0
    //   109: iload_1
    //   110: iadd
    //   111: dup
    //   112: istore_0
    //   113: iload #4
    //   115: if_icmpge -> 127
    //   118: aload_2
    //   119: iload_0
    //   120: invokevirtual charAt : (I)C
    //   123: istore_1
    //   124: goto -> 82
    //   127: aload #5
    //   129: putstatic burp/Zs26.a : [Ljava/lang/String;
    //   132: bipush #11
    //   134: anewarray java/lang/String
    //   137: putstatic burp/Zs26.b : [Ljava/lang/String;
    //   140: goto -> 300
    //   143: dup_x2
    //   144: pop
    //   145: invokevirtual toCharArray : ()[C
    //   148: dup_x1
    //   149: arraylength
    //   150: dup_x2
    //   151: pop
    //   152: iconst_0
    //   153: istore #6
    //   155: dup2_x1
    //   156: pop2
    //   157: dup_x2
    //   158: iconst_1
    //   159: if_icmpgt -> 259
    //   162: dup2
    //   163: swap
    //   164: iload #6
    //   166: dup2_x1
    //   167: caload
    //   168: swap
    //   169: iload #6
    //   171: bipush #7
    //   173: irem
    //   174: tableswitch default -> 241, 0 -> 212, 1 -> 216, 2 -> 221, 3 -> 226, 4 -> 231, 5 -> 236
    //   212: iconst_3
    //   213: goto -> 243
    //   216: bipush #82
    //   218: goto -> 243
    //   221: bipush #30
    //   223: goto -> 243
    //   226: bipush #67
    //   228: goto -> 243
    //   231: bipush #61
    //   233: goto -> 243
    //   236: bipush #83
    //   238: goto -> 243
    //   241: bipush #111
    //   243: ixor
    //   244: ixor
    //   245: i2c
    //   246: castore
    //   247: iinc #6, 1
    //   250: dup
    //   251: ifne -> 259
    //   254: dup2
    //   255: dup_x1
    //   256: goto -> 166
    //   259: dup2_x1
    //   260: pop2
    //   261: dup_x2
    //   262: iload #6
    //   264: if_icmpgt -> 162
    //   267: pop
    //   268: new java/lang/String
    //   271: dup_x1
    //   272: swap
    //   273: invokespecial <init> : ([C)V
    //   276: invokevirtual intern : ()Ljava/lang/String;
    //   279: swap
    //   280: pop
    //   281: swap
    //   282: tableswitch default -> 40, 0 -> 99
    //   300: new java/math/BigInteger
    //   303: dup
    //   304: bipush #32
    //   306: newarray byte
    //   308: dup
    //   309: iconst_0
    //   310: bipush #106
    //   312: bastore
    //   313: dup
    //   314: iconst_1
    //   315: bipush #-2
    //   317: bastore
    //   318: dup
    //   319: iconst_2
    //   320: bipush #-23
    //   322: bastore
    //   323: dup
    //   324: iconst_3
    //   325: bipush #65
    //   327: bastore
    //   328: dup
    //   329: iconst_4
    //   330: bipush #-112
    //   332: bastore
    //   333: dup
    //   334: iconst_5
    //   335: bipush #-77
    //   337: bastore
    //   338: dup
    //   339: bipush #6
    //   341: bipush #20
    //   343: bastore
    //   344: dup
    //   345: bipush #7
    //   347: bipush #122
    //   349: bastore
    //   350: dup
    //   351: bipush #8
    //   353: bipush #62
    //   355: bastore
    //   356: dup
    //   357: bipush #9
    //   359: bipush #24
    //   361: bastore
    //   362: dup
    //   363: bipush #10
    //   365: bipush #-111
    //   367: bastore
    //   368: dup
    //   369: bipush #11
    //   371: bipush #-41
    //   373: bastore
    //   374: dup
    //   375: bipush #12
    //   377: bipush #-61
    //   379: bastore
    //   380: dup
    //   381: bipush #13
    //   383: bipush #-50
    //   385: bastore
    //   386: dup
    //   387: bipush #14
    //   389: bipush #-125
    //   391: bastore
    //   392: dup
    //   393: bipush #15
    //   395: bipush #66
    //   397: bastore
    //   398: dup
    //   399: bipush #16
    //   401: bipush #56
    //   403: bastore
    //   404: dup
    //   405: bipush #17
    //   407: bipush #-118
    //   409: bastore
    //   410: dup
    //   411: bipush #18
    //   413: bipush #-105
    //   415: bastore
    //   416: dup
    //   417: bipush #19
    //   419: bipush #27
    //   421: bastore
    //   422: dup
    //   423: bipush #20
    //   425: bipush #-81
    //   427: bastore
    //   428: dup
    //   429: bipush #21
    //   431: bipush #-96
    //   433: bastore
    //   434: dup
    //   435: bipush #22
    //   437: bipush #-59
    //   439: bastore
    //   440: dup
    //   441: bipush #23
    //   443: bipush #96
    //   445: bastore
    //   446: dup
    //   447: bipush #24
    //   449: bipush #-49
    //   451: bastore
    //   452: dup
    //   453: bipush #25
    //   455: bipush #17
    //   457: bastore
    //   458: dup
    //   459: bipush #26
    //   461: bipush #95
    //   463: bastore
    //   464: dup
    //   465: bipush #27
    //   467: bipush #-92
    //   469: bastore
    //   470: dup
    //   471: bipush #28
    //   473: bipush #-123
    //   475: bastore
    //   476: dup
    //   477: bipush #29
    //   479: bipush #58
    //   481: bastore
    //   482: dup
    //   483: bipush #30
    //   485: bipush #-28
    //   487: bastore
    //   488: dup
    //   489: bipush #31
    //   491: bipush #-86
    //   493: bastore
    //   494: invokespecial <init> : ([B)V
    //   497: putstatic burp/Zs26.Z_ : Ljava/lang/Object;
    //   500: sipush #16780
    //   503: sipush #7702
    //   506: invokestatic a : (II)Ljava/lang/String;
    //   509: putstatic burp/Zs26.ZV : Ljava/lang/String;
    //   512: return
  }
  
  private static Throwable a(Throwable paramThrowable) {
    return paramThrowable;
  }
  
  private static String a(int paramInt1, int paramInt2) {
    int i = (paramInt1 ^ 0x418D) & 0xFFFF;
    if (b[i] == null) {
      char[] arrayOfChar = a[i].toCharArray();
      switch (arrayOfChar[0] & 0xFF) {
        case 0:
        
        case 1:
        
        case 2:
        
        case 3:
        
        case 4:
        
        case 5:
        
        case 6:
        
        case 7:
        
        case 8:
        
        case 9:
        
        case 10:
        
        case 11:
        
        case 12:
        
        case 13:
        
        case 14:
        
        case 15:
        
        case 16:
        
        case 17:
        
        case 18:
        
        case 19:
        
        case 20:
        
        case 21:
        
        case 22:
        
        case 23:
        
        case 24:
        
        case 25:
        
        case 26:
        
        case 27:
        
        case 28:
        
        case 29:
        
        case 30:
        
        case 31:
        
        case 32:
        
        case 33:
        
        case 34:
        
        case 35:
        
        case 36:
        
        case 37:
        
        case 38:
        
        case 39:
        
        case 40:
        
        case 41:
        
        case 42:
        
        case 43:
        
        case 44:
        
        case 45:
        
        case 46:
        
        case 47:
        
        case 48:
        
        case 49:
        
        case 50:
        
        case 51:
        
        case 52:
        
        case 53:
        
        case 54:
        
        case 55:
        
        case 56:
        
        case 57:
        
        case 58:
        
        case 59:
        
        case 60:
        
        case 61:
        
        case 62:
        
        case 63:
        
        case 64:
        
        case 65:
        
        case 66:
        
        case 67:
        
        case 68:
        
        case 69:
        
        case 70:
        
        case 71:
        
        case 72:
        
        case 73:
        
        case 74:
        
        case 75:
        
        case 76:
        
        case 77:
        
        case 78:
        
        case 79:
        
        case 80:
        
        case 81:
        
        case 82:
        
        case 83:
        
        case 84:
        
        case 85:
        
        case 86:
        
        case 87:
        
        case 88:
        
        case 89:
        
        case 90:
        
        case 91:
        
        case 92:
        
        case 93:
        
        case 94:
        
        case 95:
        
        case 96:
        
        case 97:
        
        case 98:
        
        case 99:
        
        case 100:
        
        case 101:
        
        case 102:
        
        case 103:
        
        case 104:
        
        case 105:
        
        case 106:
        
        case 107:
        
        case 108:
        
        case 109:
        
        case 110:
        
        case 111:
        
        case 112:
        
        case 113:
        
        case 114:
        
        case 115:
        
        case 116:
        
        case 117:
        
        case 118:
        
        case 119:
        
        case 120:
        
        case 121:
        
        case 122:
        
        case 123:
        
        case 124:
        
        case 125:
        
        case 126:
        
        case 127:
        
        case 128:
        
        case 129:
        
        case 130:
        
        case 131:
        
        case 132:
        
        case 133:
        
        case 134:
        
        case 135:
        
        case 136:
        
        case 137:
        
        case 138:
        
        case 139:
        
        case 140:
        
        case 141:
        
        case 142:
        
        case 143:
        
        case 144:
        
        case 145:
        
        case 146:
        
        case 147:
        
        case 148:
        
        case 149:
        
        case 150:
        
        case 151:
        
        case 152:
        
        case 153:
        
        case 154:
        
        case 155:
        
        case 156:
        
        case 157:
        
        case 158:
        
        case 159:
        
        case 160:
        
        case 161:
        
        case 162:
        
        case 163:
        
        case 164:
        
        case 165:
        
        case 166:
        
        case 167:
        
        case 168:
        
        case 169:
        
        case 170:
        
        case 171:
        
        case 172:
        
        case 173:
        
        case 174:
        
        case 175:
        
        case 176:
        
        case 177:
        
        case 178:
        
        case 179:
        
        case 180:
        
        case 181:
        
        case 182:
        
        case 183:
        
        case 184:
        
        case 185:
        
        case 186:
        
        case 187:
        
        case 188:
        
        case 189:
        
        case 190:
        
        case 191:
        
        case 192:
        
        case 193:
        
        case 194:
        
        case 195:
        
        case 196:
        
        case 197:
        
        case 198:
        
        case 199:
        
        case 200:
        
        case 201:
        
        case 202:
        
        case 203:
        
        case 204:
        
        case 205:
        
        case 206:
        
        case 207:
        
        case 208:
        
        case 209:
        
        case 210:
        
        case 211:
        
        case 212:
        
        case 213:
        
        case 214:
        
        case 215:
        
        case 216:
        
        case 217:
        
        case 218:
        
        case 219:
        
        case 220:
        
        case 221:
        
        case 222:
        
        case 223:
        
        case 224:
        
        case 225:
        
        case 226:
        
        case 227:
        
        case 228:
        
        case 229:
        
        case 230:
        
        case 231:
        
        case 232:
        
        case 233:
        
        case 234:
        
        case 235:
        
        case 236:
        
        case 237:
        
        case 238:
        
        case 239:
        
        case 240:
        
        case 241:
        
        case 242:
        
        case 243:
        
        case 244:
        
        case 245:
        
        case 246:
        
        case 247:
        
        case 248:
        
        case 249:
        
        case 250:
        
        case 251:
        
        case 252:
        
        case 253:
        
        case 254:
        
        default:
          break;
      } 
      byte b1 = 96;
      int j = (paramInt2 & 0xFF) - b1;
      if (j < 0)
        j += 256; 
      int k = ((paramInt2 & 0xFFFF) >>> 8) - b1;
      if (k < 0)
        k += 256; 
      for (byte b2 = 0; b2 < arrayOfChar.length; b2++) {
        int m = b2 % 2;
        if (m == 0) {
          arrayOfChar[b2] = (char)(arrayOfChar[b2] ^ j);
          j = ((j >>> 3 | j << 5) ^ arrayOfChar[b2]) & 0xFF;
        } else {
          arrayOfChar[b2] = (char)(arrayOfChar[b2] ^ k);
          k = ((k >>> 3 | k << 5) ^ arrayOfChar[b2]) & 0xFF;
        } 
      } 
      b[i] = (new String(arrayOfChar)).intern();
    } 
    return b[i];
  }
}


/* Location:              C:\Program Files\BurpSuitePro\burpsuite_pro.jar!\burp\Zs26.class
 * Java compiler version: 21 (65.0)
 * JD-Core Version:       1.1.3
 */